{
  "type": "Feature",
  "properties": {
    "addr:full":"415 Santa Monica Blvd Santa Monica CA 90401",
    "addr:housenumber":"415",
    "addr:postcode":"90401",
    "addr:street":"Santa Monica Blvd",
    "iso:country":"US",
    "sg:address":"415 Santa Monica Blvd",
    "sg:city":"Santa Monica",
    "sg:classifiers":[
        {
            "category":"Shopping",
            "subcategory":"Jewelry",
            "type":"Retail Goods"
        }
    ],
    "sg:phone":"+1 310 394 6585",
    "sg:postcode":"90401",
    "sg:province":"CA",
    "sg:tags":[
        "jeweler"
    ],
    "sg:website":"www.jacksjewelers.com",
    "wof:name":"Jack's Jewelers",
    "wof:placetype":"venue"
},
  "geometry": {"coordinates":[-118.49482500000001,34.016741],"type":"Point"}
}