{
  "type": "Feature",
  "properties": {
    "addr:full":"467 W Channel Islands Blvd Port Hueneme CA 93041",
    "addr:housenumber":"467",
    "addr:postcode":"93041",
    "addr:street":"W Channel Islands Blvd",
    "iso:country":"US",
    "sg:address":"467 W Channel Islands Blvd",
    "sg:city":"Port Hueneme",
    "sg:classifiers":[
        {
            "category":"Restaurant",
            "type":"Food & Drink"
        }
    ],
    "sg:menulink":"http://www.allmenus.com/ca/oxnard/79083-pizza-hut/menu/",
    "sg:phone":"+1 805 984 6500",
    "sg:postcode":"93041",
    "sg:province":"CA",
    "sg:tags":[
        "american",
        "pizza"
    ],
    "wof:name":"Pizza Hut",
    "wof:placetype":"venue"
},
  "geometry": {"coordinates":[-119.210784,34.176013],"type":"Point"}
}