{
  "type": "Feature",
  "properties": {
    "iso:country":"US",
    "sg:address":"PO Box 1501",
    "sg:city":"Culver City",
    "sg:classifiers":[
        {
            "category":"Organizations",
            "subcategory":"Non-profit Organization",
            "type":"Services"
        }
    ],
    "sg:phone":"+1 310 204 2348",
    "sg:postcode":"90232",
    "sg:province":"CA",
    "sg:tags":[
        "service/non-profit",
        "community"
    ],
    "sg:website":"www.wagv.org",
    "wof:name":"Women Against Gun Violence",
    "wof:placetype":"venue"
},
  "geometry": {"coordinates":[-118.393997,34.0191],"type":"Point"}
}