{
  "type": "Feature",
  "properties": {
    "addr:full":"4767 Soquel Dr Soquel CA 95073",
    "addr:housenumber":"4767",
    "addr:postcode":"95073",
    "addr:street":"Soquel Dr",
    "iso:country":"US",
    "sg:address":"4767 Soquel Dr",
    "sg:city":"Soquel",
    "sg:classifiers":[
        {
            "category":"Personal",
            "subcategory":"Barber",
            "type":"Services"
        }
    ],
    "sg:phone":"+1 831 464 9843",
    "sg:postcode":"95073",
    "sg:province":"CA",
    "wof:name":"Ellen Johnson Hair",
    "wof:placetype":"venue"
},
  "geometry": {"coordinates":[-121.956664,36.98843],"type":"Point"}
}