{
  "type": "Feature",
  "properties": {
    "iso:country":"US",
    "sg:address":"140 W Valley Blvd",
    "sg:city":"San Gabriel",
    "sg:classifiers":[
        {
            "category":"Shopping",
            "subcategory":"Jewelry",
            "type":"Retail Goods"
        }
    ],
    "sg:phone":"+1 626 288 7368",
    "sg:postcode":"91776",
    "sg:province":"CA",
    "sg:tags":[
        "jeweler"
    ],
    "wof:name":"King Jewelry Co",
    "wof:placetype":"venue"
},
  "geometry": {"coordinates":[-118.102606,34.079592],"type":"Point"}
}