{
  "type": "Feature",
  "properties": {
    "iso:country":"US",
    "sg:address":"101 Nellen Ave",
    "sg:city":"Corte Madera",
    "sg:classifiers":[
        {
            "category":"Sports & Exercise",
            "subcategory":"Gym",
            "type":"Entertainment"
        }
    ],
    "sg:phone":"+1 415 927 4653",
    "sg:postcode":"94925",
    "sg:province":"CA",
    "sg:tags":[
        "club",
        "health",
        "studio",
        "gymnasium"
    ],
    "wof:name":"Management Offices-Gold's Gym",
    "wof:placetype":"venue"
},
  "geometry": {"coordinates":[-122.516792,37.939358],"type":"Point"}
}