{
  "type": "Feature",
  "properties": {
    "addr:full":"200 E Beverly Blvd Apt 103 Montebello CA 90640",
    "addr:housenumber":"200;103",
    "addr:postcode":"90640",
    "addr:street":"E Beverly Blvd Apt",
    "iso:country":"US",
    "sg:address":"200 E Beverly Blvd Apt 103",
    "sg:city":"Montebello",
    "sg:classifiers":[
        {
            "category":"Health Services",
            "subcategory":"Doctor",
            "type":"Services"
        }
    ],
    "sg:phone":"+1 323 888 1192",
    "sg:postcode":"90640",
    "sg:province":"CA",
    "sg:tags":[
        "surgeon",
        "oral"
    ],
    "wof:name":"Patrick Ohara DDS",
    "wof:placetype":"venue"
},
  "geometry": {"coordinates":[-118.097313,34.015522],"type":"Point"}
}