{
  "type": "Feature",
  "properties": {
    "iso:country":"US",
    "sg:address":"4178 N 1st St",
    "sg:city":"Fresno",
    "sg:classifiers":[
        {
            "category":"Retail",
            "subcategory":"Animal Services",
            "type":"Services"
        }
    ],
    "sg:phone":"+1 559 226 4483",
    "sg:postcode":"93726",
    "sg:province":"CA",
    "wof:name":"Personal Touch Pet Grooming",
    "wof:placetype":"venue"
},
  "geometry": {"coordinates":[-119.77224200000001,36.793114],"type":"Point"}
}