{
  "type": "Feature",
  "properties": {
    "addr:full":"6600 Bruceville Rd Sacramento CA 95823",
    "addr:postcode":"6600;95823",
    "addr:street":"Bruceville Rd",
    "iso:country":"US",
    "sg:address":"6600 Bruceville Rd",
    "sg:city":"Sacramento",
    "sg:classifiers":[
        {
            "category":"Health Services",
            "subcategory":"Doctor",
            "type":"Services"
        }
    ],
    "sg:phone":"+1 916 688 2030",
    "sg:postcode":"95823",
    "sg:province":"CA",
    "sg:tags":[
        "physician",
        "surgeon"
    ],
    "wof:name":"Kaiser Permanente Orthopedic",
    "wof:placetype":"venue"
},
  "geometry": {"coordinates":[-121.424188,38.471466],"type":"Point"}
}