{
  "type": "Feature",
  "properties": {
    "acgov:api":"0.0",
    "acgov:type":"K-12",
    "addr:full":"6363 Tassjara Road Dublin CA",
    "wof:categories":[
        "education_and_religion:education=school"
    ],
    "wof:name":"Quarry Lane School, The",
    "wof:placetype":"venue"
},
  "geometry": {"coordinates":[-121.87121080993765,37.72786546412408],"type":"Point"}
}