{
  "type": "Feature",
  "properties": {
    "iso:country":"US",
    "sg:address":"23 Pasteur",
    "sg:city":"Irvine",
    "sg:classifiers":[
        {
            "category":"Banks & Credit Unions",
            "subcategory":"Bank",
            "type":"Services"
        }
    ],
    "sg:phone":"+1 949 885 9700",
    "sg:postcode":"92618",
    "sg:province":"CA",
    "sg:website":"www.wachoviadealer.com",
    "wof:name":"Wachovia Dealer Services",
    "wof:placetype":"venue"
},
  "geometry": {"coordinates":[-117.767096,33.654323],"type":"Point"}
}