{
  "type": "Feature",
  "properties": {
    "iso:country":"US",
    "sg:address":"1605 Pacific Rim Ct",
    "sg:city":"San Diego",
    "sg:classifiers":[
        {
            "category":"Professional",
            "subcategory":"Computer Services",
            "type":"Services"
        }
    ],
    "sg:phone":"+1 619 661 9466",
    "sg:postcode":"92154",
    "sg:province":"CA",
    "sg:tags":[
        "component",
        "exporting"
    ],
    "wof:name":"Turn Key Services Inc",
    "wof:placetype":"venue"
},
  "geometry": {"coordinates":[-116.992521,32.567001],"type":"Point"}
}