{
  "type": "Feature",
  "properties": {
    "addr:full":"1056 Ski Run Blvd South Lake Tahoe CA 96150",
    "addr:postcode":"1056;96150",
    "addr:street":"Ski Run Blvd",
    "iso:country":"US",
    "sg:address":"1056 Ski Run Blvd",
    "sg:city":"South Lake Tahoe",
    "sg:classifiers":[
        {
            "category":"Shopping",
            "subcategory":"Bicycles & Sporting Goods",
            "type":"Retail Goods"
        }
    ],
    "sg:phone":"+1 530 541 7272",
    "sg:postcode":"96150",
    "sg:province":"CA",
    "sg:tags":[
        "equipment",
        "skiing"
    ],
    "wof:name":"George's Skis & Boards",
    "wof:placetype":"venue"
},
  "geometry": {"coordinates":[-119.956428,38.94678],"type":"Point"}
}