{
  "type": "Feature",
  "properties": {
    "addr:full":"989 E Washington Blvd Pasadena CA 91104",
    "addr:housenumber":"989",
    "addr:postcode":"91104",
    "addr:street":"E Washington Blvd",
    "iso:country":"US",
    "sg:address":"989 E Washington Blvd",
    "sg:city":"Pasadena",
    "sg:classifiers":[
        {
            "category":"Wholesale",
            "subcategory":"Photographic Equipment",
            "type":"Manufacturing & Wholesale Goods"
        }
    ],
    "sg:phone":"+1 626 791 8502",
    "sg:postcode":"91104",
    "sg:province":"CA",
    "sg:tags":[
        "photo"
    ],
    "wof:name":"Composite Components",
    "wof:placetype":"venue"
},
  "geometry": {"coordinates":[-118.130216,34.169072],"type":"Point"}
}