{
  "type": "Feature",
  "properties": {
    "iso:country":"US",
    "sg:address":"26500 Agoura Rd",
    "sg:city":"Calabasas",
    "sg:classifiers":[
        {
            "category":"Manufacturing",
            "subcategory":"Motor Vehicles & Parts",
            "type":"Manufacturing & Wholesale Goods"
        }
    ],
    "sg:phone":"+1 818 597 0030",
    "sg:postcode":"91301",
    "sg:province":"CA",
    "sg:tags":[
        "bicycle",
        "banner",
        "advertising",
        "mfg"
    ],
    "wof:name":"Th Gov Sales",
    "wof:placetype":"venue"
},
  "geometry": {"coordinates":[-118.700486,34.143741],"type":"Point"}
}