{
  "type": "Feature",
  "properties": {
    "iso:country":"US",
    "sg:address":"1126 E Route 66",
    "sg:city":"Glendora",
    "sg:classifiers":[
        {
            "category":"Communications",
            "subcategory":"Film & Video Production",
            "type":"Services"
        }
    ],
    "sg:phone":"+1 626 705 2382",
    "sg:postcode":"91740",
    "sg:province":"CA",
    "sg:tags":[
        "tv",
        "radio",
        "services-commercial",
        "companies-film"
    ],
    "wof:name":"Inside Take",
    "wof:placetype":"venue"
},
  "geometry": {"coordinates":[-117.845619,34.128738],"type":"Point"}
}