{
  "type": "Feature",
  "properties": {
    "addr:full":"1142 Buckingham Dr Costa Mesa CA 92626",
    "addr:housenumber":"1142",
    "addr:postcode":"92626",
    "addr:street":"Buckingham Dr",
    "iso:country":"US",
    "sg:address":"1142 Buckingham Dr",
    "sg:city":"Costa Mesa",
    "sg:classifiers":[
        {
            "category":"Real Estate",
            "subcategory":"Real Estate Operator",
            "type":"Services"
        }
    ],
    "sg:phone":"+1 714 241 0500",
    "sg:postcode":"92626",
    "sg:province":"CA",
    "sg:tags":[
        "apartment"
    ],
    "wof:name":"Wimbledon Glen Apartments",
    "wof:placetype":"venue"
},
  "geometry": {"coordinates":[-117.905998,33.688599],"type":"Point"}
}