{
  "type": "Feature",
  "properties": {
    "addr:full":"246 S Market St Inglewood CA 90301",
    "addr:housenumber":"246",
    "addr:postcode":"90301",
    "addr:street":"S Market St",
    "iso:country":"US",
    "sg:address":"246 S Market St",
    "sg:city":"Inglewood",
    "sg:classifiers":[
        {
            "category":"Shopping",
            "subcategory":"Clothing, Apparel, & Fashions",
            "type":"Retail Goods"
        }
    ],
    "sg:phone":"+1 310 673 4808",
    "sg:postcode":"90301",
    "sg:province":"CA",
    "sg:tags":[
        "accessory"
    ],
    "wof:name":"Sunny Uniforms",
    "wof:placetype":"venue"
},
  "geometry": {"coordinates":[-118.351997,33.960701],"type":"Point"}
}