{
  "type": "Feature",
  "properties": {
    "iso:country":"US",
    "sg:address":"2916 N Rowell Ave",
    "sg:city":"Fresno",
    "sg:classifiers":[
        {
            "category":"Building & Trades",
            "subcategory":"Construction",
            "type":"Services"
        }
    ],
    "sg:phone":"+1 559 322 8325",
    "sg:postcode":"93703",
    "sg:province":"CA",
    "sg:tags":[
        "resurfacing",
        "laying",
        "refinishing",
        "floor"
    ],
    "wof:name":"Central Valley Aggregate",
    "wof:placetype":"venue"
},
  "geometry": {"coordinates":[-119.751581,36.7767],"type":"Point"}
}