{
  "type": "Feature",
  "properties": {
    "addr:full":"1355 Lawndale Rd Kenwood CA 95452",
    "addr:housenumber":"1355",
    "addr:postcode":"95452",
    "addr:street":"Lawndale Rd",
    "iso:country":"US",
    "sg:address":"1355 Lawndale Rd",
    "sg:city":"Kenwood",
    "sg:classifiers":[
        {
            "category":"Real Estate",
            "subcategory":"Real Estate Services",
            "type":"Services"
        },
        {
            "category":"Real Estate",
            "subcategory":"Real Estate Agent",
            "type":"Services"
        }
    ],
    "sg:phone":"+1 707 833 1252",
    "sg:postcode":"95452",
    "sg:province":"CA",
    "sg:tags":[
        "buyer",
        "broker"
    ],
    "sg:website":"http://www.wendygibson.com",
    "wof:name":"Mountain, Wendy Real Estate",
    "wof:placetype":"venue"
},
  "geometry": {"coordinates":[-122.575187,38.413397],"type":"Point"}
}