{
  "type": "Feature",
  "properties": {
    "iso:country":"US",
    "sg:address":"111 Gable St",
    "sg:city":"Folsom",
    "sg:phone":"+1 916 983 5664",
    "sg:postcode":"95630",
    "sg:province":"CA",
    "sg:tags":[
        "equipment",
        "supply"
    ],
    "wof:name":"Brace Supply",
    "wof:placetype":"venue"
},
  "geometry": {"coordinates":[-121.130691,38.681139],"type":"Point"}
}