{
  "type": "Feature",
  "properties": {
    "addr:full":"26920 Cherry Hills Blvd Sun City CA 92586",
    "addr:housenumber":"26920",
    "addr:postcode":"92586",
    "addr:street":"Cherry Hills Blvd",
    "iso:country":"US",
    "sg:address":"26920 Cherry Hills Blvd",
    "sg:city":"Sun City",
    "sg:classifiers":[
        {
            "category":"Restaurant",
            "type":"Food & Drink"
        }
    ],
    "sg:phone":"+1 951 672 1545",
    "sg:postcode":"92586",
    "sg:province":"CA",
    "sg:tags":[
        "pizza"
    ],
    "sg:website":"dominos.com",
    "wof:name":"Dominos Pizza",
    "wof:placetype":"venue"
},
  "geometry": {"coordinates":[-117.190201,33.710793],"type":"Point"}
}