{
  "type": "Feature",
  "properties": {
    "iso:country":"US",
    "sg:address":"663 N Wendy Dr",
    "sg:city":"Newbury Park",
    "sg:classifiers":[
        {
            "category":"Personal",
            "type":"Services"
        }
    ],
    "sg:phone":"+1 805 376 1817",
    "sg:postcode":"91320",
    "sg:province":"CA",
    "sg:tags":[
        "consultant",
        "wedding"
    ],
    "wof:name":"Simply Elegant Wedding Prodtns",
    "wof:placetype":"venue"
},
  "geometry": {"coordinates":[-118.942227,34.18783],"type":"Point"}
}