{
  "type": "Feature",
  "properties": {
    "addr:full":"3440 la Grande Blvd Sacramento CA 95823",
    "addr:housenumber":"3440",
    "addr:postcode":"95823",
    "addr:street":"La Grande Blvd",
    "iso:country":"US",
    "sg:address":"3440 la Grande Blvd",
    "sg:city":"Sacramento",
    "sg:classifiers":[
        {
            "category":"Wholesale",
            "subcategory":"Construction Materials",
            "type":"Manufacturing & Wholesale Goods"
        },
        {
            "category":"Wholesale",
            "subcategory":"Home Furnishings",
            "type":"Manufacturing & Wholesale Goods"
        }
    ],
    "sg:phone":"+1 916 394 2828",
    "sg:postcode":"95823",
    "sg:province":"CA",
    "sg:tags":[
        "supply",
        "mattresses-wholesale",
        "mattress",
        "makers'",
        "manufacturer"
    ],
    "wof:name":"Imperial Mattress Spm",
    "wof:placetype":"venue"
},
  "geometry": {"coordinates":[-121.470039,38.508401],"type":"Point"}
}