{
  "type": "Feature",
  "properties": {
    "iso:country":"US",
    "sg:address":"2950 Grace Ln",
    "sg:city":"Costa Mesa",
    "sg:classifiers":[
        {
            "category":"Building & Trades",
            "subcategory":"Landscaping Services",
            "type":"Services"
        }
    ],
    "sg:phone":"+1 714 432 1562",
    "sg:postcode":"92626",
    "sg:province":"CA",
    "wof:name":"Green Life Environmental",
    "wof:placetype":"venue"
},
  "geometry": {"coordinates":[-117.902495,33.679283],"type":"Point"}
}