{
  "type": "Feature",
  "properties": {
    "iso:country":"US",
    "sg:address":"941 E Chia Rd",
    "sg:city":"Palm Springs",
    "sg:classifiers":[
        {
            "category":"Wholesale",
            "subcategory":"Non-durable Goods",
            "type":"Manufacturing & Wholesale Goods"
        }
    ],
    "sg:phone":"+1 760 322 6442",
    "sg:postcode":"92262",
    "sg:province":"CA",
    "wof:name":"MTC Distributing",
    "wof:placetype":"venue"
},
  "geometry": {"coordinates":[-116.537216,33.841532],"type":"Point"}
}