{
  "type": "Feature",
  "properties": {
    "addr:full":"1207 W Shaw Ave Fresno CA 93711",
    "addr:housenumber":"1207",
    "addr:postcode":"93711",
    "addr:street":"W Shaw Ave",
    "iso:country":"US",
    "sg:address":"1207 W Shaw Ave",
    "sg:city":"Fresno",
    "sg:classifiers":[
        {
            "category":"Health Services",
            "subcategory":"Doctor",
            "type":"Services"
        }
    ],
    "sg:phone":"+1 559 229 3556",
    "sg:postcode":"93711",
    "sg:province":"CA",
    "sg:tags":[
        "dentist"
    ],
    "wof:name":"Theodore S Falk Inc",
    "wof:placetype":"venue"
},
  "geometry": {"coordinates":[-119.814333,36.808264],"type":"Point"}
}