{
  "type": "Feature",
  "properties": {
    "iso:country":"US",
    "sg:address":"22996 el Toro Rd",
    "sg:city":"Lake Forest",
    "sg:classifiers":[
        {
            "category":"Real Estate",
            "subcategory":"Architect",
            "type":"Services"
        }
    ],
    "sg:phone":"+1 949 770 8550",
    "sg:postcode":"92630",
    "sg:province":"CA",
    "wof:name":"Kenneth Brown & Co",
    "wof:placetype":"venue"
},
  "geometry": {"coordinates":[-117.62810899999999,33.669998],"type":"Point"}
}