{
  "type": "Feature",
  "properties": {
    "iso:country":"US",
    "sg:address":"801 Montgomery St",
    "sg:city":"San Francisco",
    "sg:classifiers":[
        {
            "category":"Insurance",
            "subcategory":"Insurance Agent",
            "type":"Services"
        }
    ],
    "sg:phone":"+1 415 391 1399",
    "sg:postcode":"94133",
    "sg:province":"CA",
    "wof:name":"Benefit Point Inc",
    "wof:placetype":"venue"
},
  "geometry": {"coordinates":[-122.403549,37.796671],"type":"Point"}
}