{
  "type": "Feature",
  "properties": {
    "addr:full":"211 Main St San Francisco CA 94105",
    "addr:housenumber":"211",
    "addr:postcode":"94105",
    "addr:street":"Main St",
    "iso:country":"US",
    "sg:address":"211 Main St",
    "sg:city":"San Francisco",
    "sg:classifiers":[
        {
            "category":"Government",
            "subcategory":"Office",
            "type":"Public Place"
        }
    ],
    "sg:phone":"+1 925 866 1034",
    "sg:postcode":"94105",
    "sg:province":"CA",
    "sg:tags":[
        "personnel",
        "agency"
    ],
    "wof:name":"Personnel Management U S Off",
    "wof:placetype":"venue"
},
  "geometry": {"coordinates":[-122.39193,37.789549],"type":"Point"}
}