{
  "type": "Feature",
  "properties": {
    "iso:country":"US",
    "sg:address":"68307 Descanso Cir",
    "sg:city":"Cathedral City",
    "sg:classifiers":[
        {
            "category":"Building & Trades",
            "subcategory":"Landscaping Services",
            "type":"Services"
        }
    ],
    "sg:phone":"+1 760 218 3046",
    "sg:postcode":"92234",
    "sg:province":"CA",
    "sg:tags":[
        "landscape"
    ],
    "wof:name":"Sal Alaniz Ldscpg & Gardening",
    "wof:placetype":"venue"
},
  "geometry": {"coordinates":[-116.47005900000001,33.830514],"type":"Point"}
}