{
  "type": "Feature",
  "properties": {
    "iso:country":"US",
    "sg:address":"1601 Lane St",
    "sg:city":"San Francisco",
    "sg:classifiers":[
        {
            "category":"Sports & Exercise",
            "subcategory":"Playing Field",
            "type":"Entertainment"
        },
        {
            "category":"Organizations",
            "subcategory":"Non-profit Organization",
            "type":"Services"
        }
    ],
    "sg:phone":"+1 415 822 7728",
    "sg:postcode":"94124",
    "sg:province":"CA",
    "sg:tags":[
        "instruction",
        "service/non-profit",
        "community",
        "fitness"
    ],
    "wof:name":"Bayview Hunters Point YMCA",
    "wof:placetype":"venue"
},
  "geometry": {"coordinates":[-122.38958100000001,37.731805],"type":"Point"}
}