{
  "type": "Feature",
  "properties": {
    "iso:country":"US",
    "sg:address":"13381 White Sand Dr",
    "sg:city":"Tustin",
    "sg:classifiers":[
        {
            "category":"Manufacturing",
            "subcategory":"Printing",
            "type":"Manufacturing & Wholesale Goods"
        }
    ],
    "sg:phone":"+1 714 544 0248",
    "sg:postcode":"92780",
    "sg:province":"CA",
    "sg:tags":[
        "consulting",
        "book",
        "business"
    ],
    "wof:name":"Out of Yr Mndand Into V Mrk",
    "wof:placetype":"venue"
},
  "geometry": {"coordinates":[-117.810835,33.740955],"type":"Point"}
}