{
  "type": "Feature",
  "properties": {
    "iso:country":"US",
    "sg:address":"2083 Parnell Way",
    "sg:city":"Altadena",
    "sg:classifiers":[
        {
            "category":"Shopping",
            "subcategory":"Catalog Store",
            "type":"Retail Goods"
        }
    ],
    "sg:phone":"+1 626 794 8443",
    "sg:postcode":"91001",
    "sg:province":"CA",
    "sg:tags":[
        "mail",
        "order"
    ],
    "sg:website":"www.winsomesgiftworld.com",
    "wof:name":"Winsomes Gift World",
    "wof:placetype":"venue"
},
  "geometry": {"coordinates":[-118.162989,34.180824],"type":"Point"}
}