{
  "type": "Feature",
  "properties": {
    "iso:country":"US",
    "sg:address":"156 W Verdugo Ave",
    "sg:city":"Burbank",
    "sg:classifiers":[
        {
            "category":"Restaurant",
            "type":"Food & Drink"
        }
    ],
    "sg:phone":"+1 818 841 5040",
    "sg:postcode":"91502",
    "sg:province":"CA",
    "sg:tags":[
        "house",
        "steak"
    ],
    "wof:name":"Morels French Steakhouse",
    "wof:placetype":"venue"
},
  "geometry": {"coordinates":[-118.310464,34.174188],"type":"Point"}
}