{
  "type": "Feature",
  "properties": {
    "iso:country":"US",
    "sg:address":"21636 Marilla St",
    "sg:city":"Chatsworth",
    "sg:classifiers":[
        {
            "category":"Food & Beverages",
            "subcategory":"Specialty",
            "type":"Retail Goods"
        }
    ],
    "sg:phone":"+1 818 772 8441",
    "sg:postcode":"91311",
    "sg:province":"CA",
    "sg:tags":[
        "vitamin"
    ],
    "sg:website":"www.californianatural.net",
    "wof:name":"Ca Naturals",
    "wof:placetype":"venue"
},
  "geometry": {"coordinates":[-118.600635,34.247527],"type":"Point"}
}