{
  "type": "Feature",
  "properties": {
    "iso:country":"US",
    "sg:address":"260 N 2nd Ave",
    "sg:city":"Upland",
    "sg:classifiers":[
        {
            "category":"Personal",
            "subcategory":"Barber",
            "type":"Services"
        }
    ],
    "sg:phone":"+1 909 981 5501",
    "sg:postcode":"91786",
    "sg:province":"CA",
    "wof:name":"Upland Barber Shop",
    "wof:placetype":"venue"
},
  "geometry": {"coordinates":[-117.648356,34.096577],"type":"Point"}
}