{
  "type": "Feature",
  "properties": {
    "addr:full":"333 S Spring St Los Angeles CA 90013",
    "addr:housenumber":"333",
    "addr:postcode":"90013",
    "addr:street":"S Spring St",
    "iso:country":"US",
    "sg:address":"333 S Spring St",
    "sg:city":"Los Angeles",
    "sg:classifiers":[
        {
            "category":"Building & Trades",
            "subcategory":"Cleaning & Sanitation",
            "type":"Services"
        }
    ],
    "sg:phone":"+1 818 369 1726",
    "sg:postcode":"90013",
    "sg:province":"CA",
    "sg:tags":[
        "carpet"
    ],
    "sg:website":"clean-and-green-team.com",
    "wof:name":"Clean And Green Team Carpet Cleaning",
    "wof:placetype":"venue"
},
  "geometry": {"coordinates":[-118.247681,34.049675],"type":"Point"}
}