{
  "type": "Feature",
  "properties": {
    "addr:full":"240 Polaris Ave Mountain View CA 94043",
    "addr:housenumber":"240",
    "addr:postcode":"94043",
    "addr:street":"Polaris Ave",
    "iso:country":"US",
    "sg:address":"240 Polaris Ave",
    "sg:city":"Mountain View",
    "sg:classifiers":[
        {
            "category":"Building & Trades",
            "subcategory":"Electrical",
            "type":"Services"
        }
    ],
    "sg:phone":"+1 650 428 0710",
    "sg:postcode":"94043",
    "sg:province":"CA",
    "sg:tags":[
        "electrical",
        "contractor"
    ],
    "wof:name":"Marks Electrical Services",
    "wof:placetype":"venue"
},
  "geometry": {"coordinates":[-122.083838,37.398914],"type":"Point"}
}