{
  "type": "Feature",
  "properties": {
    "iso:country":"US",
    "sg:address":"5681 Snell Avenue Suite 1",
    "sg:city":"San Jose",
    "sg:classifiers":[
        {
            "category":"Juice Bar",
            "subcategory":"None",
            "type":"Food & Drink"
        },
        {
            "category":"Coffee & Tea",
            "type":"Food & Drink"
        }
    ],
    "sg:phone":"+1 408 972 2587",
    "sg:postcode":"95123",
    "sg:province":"CA",
    "sg:tags":[
        "smoothy"
    ],
    "sg:website":"www.tapiocaexpress.com",
    "wof:name":"Tapioca Express",
    "wof:placetype":"venue"
},
  "geometry": {"coordinates":[-121.83000199999999,37.248299],"type":"Point"}
}