{
  "type": "Feature",
  "properties": {
    "addr:full":"5521 19th Ave Sacramento CA 95820",
    "addr:housenumber":"5521",
    "addr:postcode":"95820",
    "addr:street":"19Th Ave",
    "iso:country":"US",
    "sg:address":"5521 19th Ave",
    "sg:city":"Sacramento",
    "sg:classifiers":[
        {
            "category":"Real Estate",
            "subcategory":"Real Estate Agent",
            "type":"Services"
        }
    ],
    "sg:phone":"+1 916 452 1576",
    "sg:postcode":"95820",
    "sg:province":"CA",
    "wof:name":"Aztlan",
    "wof:placetype":"venue"
},
  "geometry": {"coordinates":[-121.441704,38.534855],"type":"Point"}
}