{
  "type": "Feature",
  "properties": {
    "addr:full":"2321 Devonshire Dr Oxnard CA 93030",
    "addr:housenumber":"2321",
    "addr:postcode":"93030",
    "addr:street":"Devonshire Dr",
    "iso:country":"US",
    "sg:address":"2321 Devonshire Dr",
    "sg:city":"Oxnard",
    "sg:classifiers":[
        {
            "category":"Professional",
            "subcategory":"Accounting & Tax Preparation",
            "type":"Services"
        },
        {
            "category":"Professional",
            "subcategory":"Management & Consulting",
            "type":"Services"
        },
        {
            "category":"Banks & Credit Unions",
            "subcategory":"Financial Services",
            "type":"Services"
        }
    ],
    "sg:phone":"+1 805 984 0248",
    "sg:postcode":"93030",
    "sg:province":"CA",
    "sg:tags":[
        "financing",
        "return",
        "taxes-consultants",
        "consultant",
        "planning",
        "representative",
        "bookkeeping"
    ],
    "wof:name":"Bakir I L",
    "wof:placetype":"venue"
},
  "geometry": {"coordinates":[-119.202349,34.211665],"type":"Point"}
}