{
  "type": "Feature",
  "properties": {
    "addr:full":"822 Cassia St Redwood City CA 94063",
    "addr:housenumber":"822",
    "addr:postcode":"94063",
    "addr:street":"Cassia St",
    "iso:country":"US",
    "sg:address":"822 Cassia St",
    "sg:city":"Redwood City",
    "sg:classifiers":[
        {
            "category":"Education",
            "subcategory":"Dance Studio",
            "type":"Public Place"
        }
    ],
    "sg:phone":"+1 650 366 0504",
    "sg:postcode":"94063",
    "sg:province":"CA",
    "sg:tags":[
        "instruction",
        "dancing"
    ],
    "sg:website":"www.sfopen.com",
    "wof:name":"Imperial Dance Club Ballroom",
    "wof:placetype":"venue"
},
  "geometry": {"coordinates":[-122.22257399999999,37.486616],"type":"Point"}
}