{
  "type": "Feature",
  "properties": {
    "addr:full":"41746 Enterprise Cir N Temecula CA 92590",
    "addr:housenumber":"41746",
    "addr:postcode":"92590",
    "addr:street":"Enterprise Cir N",
    "iso:country":"US",
    "sg:address":"41746 Enterprise Cir N",
    "sg:city":"Temecula",
    "sg:classifiers":[
        {
            "category":"Manufacturing",
            "subcategory":"Building Materials",
            "type":"Manufacturing & Wholesale Goods"
        }
    ],
    "sg:phone":"+1 951 695 1730",
    "sg:postcode":"92590",
    "sg:province":"CA",
    "sg:tags":[
        "mfg",
        "wood",
        "kitchen",
        "cabinet"
    ],
    "wof:name":"Custom Cabinets of Abilit",
    "wof:placetype":"venue"
},
  "geometry": {"coordinates":[-117.168577,33.520196],"type":"Point"}
}