{
  "type": "Feature",
  "properties": {
    "addr:full":"2104 W Martin Luther King Jr Blvd Los Angeles CA 90008",
    "addr:housenumber":"2104",
    "addr:postcode":"90008",
    "addr:street":"W Martin Luther King Jr Blvd",
    "iso:country":"US",
    "sg:address":"2104 W Martin Luther King Jr Blvd",
    "sg:city":"Los Angeles",
    "sg:classifiers":[
        {
            "category":"Education",
            "subcategory":"School",
            "type":"Public Place"
        }
    ],
    "sg:phone":"+1 323 299 4666",
    "sg:postcode":"90008",
    "sg:province":"CA",
    "sg:tags":[
        "religious"
    ],
    "wof:name":"Berean Bible School & Library",
    "wof:placetype":"venue"
},
  "geometry": {"coordinates":[-118.31820500000001,34.010746],"type":"Point"}
}