{
  "type": "Feature",
  "properties": {
    "iso:country":"US",
    "sg:address":"2325 Riverside Rd",
    "sg:city":"Watsonville",
    "sg:classifiers":[
        {
            "category":"Farming",
            "subcategory":"Livestock Farm",
            "type":"Manufacturing & Wholesale Goods"
        }
    ],
    "sg:phone":"+1 831 726 1687",
    "sg:postcode":"95076",
    "sg:province":"CA",
    "sg:tags":[
        "beef",
        "feedlot",
        "cattle"
    ],
    "wof:name":"John Rocha Jr & Sons",
    "wof:placetype":"venue"
},
  "geometry": {"coordinates":[-121.599383,36.901514],"type":"Point"}
}