{
  "type": "Feature",
  "properties": {
    "addr:full":"6565 Hollywod Blvd. Los Angeles CA 90028",
    "addr:housenumber":"6565",
    "addr:postcode":"90028",
    "addr:street":"Hollywod Blvd.",
    "iso:country":"US",
    "sg:address":"6565 Hollywod Blvd.",
    "sg:city":"Los Angeles",
    "sg:classifiers":[
        {
            "category":"Banks & Credit Unions",
            "subcategory":"Bank",
            "type":"Services"
        }
    ],
    "sg:postcode":"90028",
    "sg:province":"CA",
    "sg:website":"www.westernunion.com",
    "wof:name":"Western Union - Continental Currency",
    "wof:placetype":"venue"
},
  "geometry": {"coordinates":[-118.333151,34.101576],"type":"Point"}
}