{
  "type": "Feature",
  "properties": {
    "iso:country":"US",
    "sg:address":"946 Belmont Pl",
    "sg:city":"Pittsburg",
    "sg:classifiers":[
        {
            "category":"Real Estate",
            "subcategory":"Real Estate Services",
            "type":"Services"
        },
        {
            "category":"Real Estate",
            "subcategory":"Real Estate Agent",
            "type":"Services"
        }
    ],
    "sg:phone":"+1 925 727 1618",
    "sg:postcode":"94565",
    "sg:province":"CA",
    "sg:tags":[
        "management"
    ],
    "wof:name":"Mts Enterprises",
    "wof:placetype":"venue"
},
  "geometry": {"coordinates":[-121.882456,37.999091],"type":"Point"}
}