{
  "type": "Feature",
  "properties": {
    "addr:full":"3804 Ventura Canyon Ave Sherman Oaks CA 91423",
    "addr:housenumber":"3804",
    "addr:postcode":"91423",
    "addr:street":"Ventura Canyon Ave",
    "iso:country":"US",
    "sg:address":"3804 Ventura Canyon Ave",
    "sg:city":"Sherman Oaks",
    "sg:classifiers":[
        {
            "category":"Communications",
            "subcategory":"Film & Video Production",
            "type":"Services"
        }
    ],
    "sg:phone":"+1 818 285 7411",
    "sg:postcode":"91423",
    "sg:province":"CA",
    "sg:tags":[
        "motion",
        "picture",
        "studio",
        "producer"
    ],
    "wof:name":"Beddingfield Co",
    "wof:placetype":"venue"
},
  "geometry": {"coordinates":[-118.42795,34.139925],"type":"Point"}
}