{
  "type": "Feature",
  "properties": {
    "iso:country":"US",
    "sg:address":"163 Academy St",
    "sg:city":"Bishop",
    "sg:classifiers":[
        {
            "category":"Retail",
            "subcategory":"Laundry & Dry Cleaning",
            "type":"Services"
        }
    ],
    "sg:phone":"+1 760 873 8338",
    "sg:postcode":"93514",
    "sg:province":"CA",
    "wof:name":"Sierra Suds",
    "wof:placetype":"venue"
},
  "geometry": {"coordinates":[-118.39576700000001,37.363196],"type":"Point"}
}