{
  "type": "Feature",
  "properties": {
    "iso:country":"US",
    "sg:address":"560 S Los Angeles St",
    "sg:city":"Los Angeles",
    "sg:classifiers":[
        {
            "category":"Shopping",
            "subcategory":"Clothing, Apparel, & Fashions",
            "type":"Retail Goods"
        }
    ],
    "sg:phone":"+1 213 623 9877",
    "sg:postcode":"90013",
    "sg:province":"CA",
    "wof:name":"Multigram Merchandising",
    "wof:placetype":"venue"
},
  "geometry": {"coordinates":[-118.248124,34.04544],"type":"Point"}
}