{
  "type": "Feature",
  "properties": {
    "iso:country":"US",
    "sg:address":"31101 Blue Heron Way",
    "sg:city":"Coarsegold",
    "sg:classifiers":[
        {
            "category":"Professional",
            "subcategory":"Management & Consulting",
            "type":"Services"
        }
    ],
    "sg:phone":"+1 559 658 7421",
    "sg:postcode":"93614",
    "sg:province":"CA",
    "sg:tags":[
        "retail",
        "direct",
        "sales"
    ],
    "wof:name":"Hall Custom Golf",
    "wof:placetype":"venue"
},
  "geometry": {"coordinates":[-119.742739,37.200423],"type":"Point"}
}