{
  "type": "Feature",
  "properties": {
    "iso:country":"US",
    "sg:address":"Pier 39",
    "sg:city":"San Francisco",
    "sg:classifiers":[
        {
            "category":"Recreation",
            "subcategory":"Boat Charter",
            "type":"Entertainment"
        },
        {
            "category":"Landmark",
            "subcategory":"Tourist Information",
            "type":"Public Place"
        }
    ],
    "sg:phone":"+1 415 706 7364",
    "sg:postcode":"94123",
    "sg:province":"CA",
    "sg:tags":[
        "boating",
        "tour"
    ],
    "sg:website":"www.sanfranciscowhaletours.com",
    "wof:name":"San Francisco Whale Tours",
    "wof:placetype":"venue"
},
  "geometry": {"coordinates":[-122.410054,37.808919],"type":"Point"}
}