{
  "type": "Feature",
  "properties": {
    "iso:country":"US",
    "sg:address":"13871 Red Hill Ave",
    "sg:city":"Tustin",
    "sg:classifiers":[
        {
            "category":"Retail",
            "subcategory":"Car Wash",
            "type":"Services"
        }
    ],
    "sg:phone":"+1 714 838 9783",
    "sg:postcode":"92780",
    "sg:province":"CA",
    "wof:name":"Red Hill Car Wash",
    "wof:placetype":"venue"
},
  "geometry": {"coordinates":[-117.814003,33.734901],"type":"Point"}
}