{
  "type": "Feature",
  "properties": {
    "addr:full":"1661 S Garth Ave Los Angeles CA 90035",
    "addr:housenumber":"1661",
    "addr:postcode":"90035",
    "addr:street":"S Garth Ave",
    "iso:country":"US",
    "sg:address":"1661 S Garth Ave",
    "sg:city":"Los Angeles",
    "sg:classifiers":[
        {
            "category":"Professional",
            "type":"Services"
        }
    ],
    "sg:phone":"+1 310 288 1721",
    "sg:postcode":"90035",
    "sg:province":"CA",
    "wof:name":"Billiejaxx LLC",
    "wof:placetype":"venue"
},
  "geometry": {"coordinates":[-118.377307,34.048503],"type":"Point"}
}