{
  "type": "Feature",
  "properties": {
    "addr:full":"1621 Terrace Way Santa Rosa CA 95404",
    "addr:housenumber":"1621",
    "addr:postcode":"95404",
    "addr:street":"Terrace Way",
    "iso:country":"US",
    "sg:address":"1621 Terrace Way",
    "sg:city":"Santa Rosa",
    "sg:classifiers":[
        {
            "category":"Personal",
            "subcategory":"Beauty Salon",
            "type":"Services"
        }
    ],
    "sg:phone":"+1 707 578 5557",
    "sg:postcode":"95404",
    "sg:province":"CA",
    "wof:name":"Splits",
    "wof:placetype":"venue"
},
  "geometry": {"coordinates":[-122.70293700000001,38.456245],"type":"Point"}
}