{
  "type": "Feature",
  "properties": {
    "iso:country":"US",
    "sg:address":"489 Van Buren Dr",
    "sg:city":"Monterey Park",
    "sg:classifiers":[
        {
            "category":"Building & Trades",
            "subcategory":"Electrical",
            "type":"Services"
        }
    ],
    "sg:phone":"+1 626 573 1331",
    "sg:postcode":"91755",
    "sg:province":"CA",
    "sg:tags":[
        "electrical",
        "contractor"
    ],
    "wof:name":"Zavala Electric",
    "wof:placetype":"venue"
},
  "geometry": {"coordinates":[-118.118134,34.045895],"type":"Point"}
}