{
  "type": "Feature",
  "properties": {
    "iso:country":"US",
    "sg:address":"20725 Ave 144",
    "sg:city":"Porterville",
    "sg:classifiers":[
        {
            "category":"Farming",
            "subcategory":"Farm",
            "type":"Manufacturing & Wholesale Goods"
        }
    ],
    "sg:phone":"+1 559 793 0800",
    "sg:postcode":"93257",
    "sg:province":"CA",
    "wof:name":"Golden Valley Farms",
    "wof:placetype":"venue"
},
  "geometry": {"coordinates":[-119.11478700000001,36.051144],"type":"Point"}
}