{
  "type": "Feature",
  "properties": {
    "iso:country":"US",
    "sg:address":"361 Kipling St",
    "sg:city":"Palo Alto",
    "sg:classifiers":[
        {
            "category":"Health Services",
            "subcategory":"Health Practitioner",
            "type":"Services"
        }
    ],
    "sg:phone":"+1 650 327 7446",
    "sg:postcode":"94301",
    "sg:province":"CA",
    "sg:tags":[
        "psychologist"
    ],
    "wof:name":"C Donald Williams",
    "wof:placetype":"venue"
},
  "geometry": {"coordinates":[-122.161655,37.449045],"type":"Point"}
}