{
  "type": "Feature",
  "properties": {
    "iso:country":"US",
    "sg:address":"119 Aberdeen Dr Ste 5",
    "sg:city":"Cardiff by the Sea",
    "sg:classifiers":[
        {
            "category":"Building & Trades",
            "subcategory":"Construction",
            "type":"Services"
        }
    ],
    "sg:phone":"+1 760 436 0187",
    "sg:postcode":"92007",
    "sg:province":"CA",
    "sg:tags":[
        "contractor"
    ],
    "wof:name":"R & R Custom Builders",
    "wof:placetype":"venue"
},
  "geometry": {"coordinates":[-117.28155700000001,33.027679],"type":"Point"}
}