{
  "type": "Feature",
  "properties": {
    "iso:country":"US",
    "sg:address":"2053 Saratoga Pl",
    "sg:city":"Hanford",
    "sg:classifiers":[
        {
            "category":"Manufacturing",
            "subcategory":"Food",
            "type":"Manufacturing & Wholesale Goods"
        }
    ],
    "sg:phone":"+1 559 998 4669",
    "sg:postcode":"93230",
    "sg:province":"CA",
    "sg:tags":[
        "preparation",
        "mfg"
    ],
    "wof:name":"Bryce Melancon",
    "wof:placetype":"venue"
},
  "geometry": {"coordinates":[-119.67999500000001,36.328529],"type":"Point"}
}