{
  "type": "Feature",
  "properties": {
    "addr:full":"560 Canal St King City CA 93930",
    "addr:housenumber":"560",
    "addr:postcode":"93930",
    "addr:street":"Canal St",
    "iso:country":"US",
    "sg:address":"560 Canal St",
    "sg:city":"King City",
    "sg:classifiers":[
        {
            "category":"Restaurant",
            "type":"Food & Drink"
        }
    ],
    "sg:phone":"+1 831 385 2888",
    "sg:postcode":"93930",
    "sg:province":"CA",
    "wof:name":"China One Express",
    "wof:placetype":"venue"
},
  "geometry": {"coordinates":[-121.12975900000001,36.203717],"type":"Point"}
}