{
  "type": "Feature",
  "properties": {
    "iso:country":"US",
    "sg:address":"499 W Shaw Ave",
    "sg:city":"Fresno",
    "sg:classifiers":[
        {
            "category":"Insurance",
            "subcategory":"Insurance Agent",
            "type":"Services"
        }
    ],
    "sg:phone":"+1 559 226 4700",
    "sg:postcode":"93704",
    "sg:province":"CA",
    "wof:name":"Reinhardt Insurance",
    "wof:placetype":"venue"
},
  "geometry": {"coordinates":[-119.801965,36.808348],"type":"Point"}
}