{
  "type": "Feature",
  "properties": {
    "addr:full":"22661 Lambert St., Suite 204 Lake Forest CA 92630",
    "addr:housenumber":"22661",
    "addr:postcode":"92630",
    "addr:street":"Lambert St. Suite 204",
    "iso:country":"US",
    "sg:address":"22661 Lambert St., Suite 204",
    "sg:city":"Lake Forest",
    "sg:classifiers":[
        {
            "category":"Building & Trades",
            "subcategory":"Construction",
            "type":"Services"
        }
    ],
    "sg:phone":"+1 888 253 3628",
    "sg:postcode":"92630",
    "sg:province":"CA",
    "sg:tags":[
        "installation",
        "solar"
    ],
    "sg:website":"www.akeena.com",
    "wof:name":"Akeena Solar",
    "wof:placetype":"venue"
},
  "geometry": {"coordinates":[-117.714083,33.633647],"type":"Point"}
}