{
  "type": "Feature",
  "properties": {
    "addr:full":"100 Old County Rd Brisbane CA 94005",
    "addr:housenumber":"100",
    "addr:postcode":"94005",
    "addr:street":"Old County Rd",
    "iso:country":"US",
    "sg:address":"100 Old County Rd",
    "sg:city":"Brisbane",
    "sg:classifiers":[
        {
            "category":"Travel",
            "subcategory":"Travel Agent",
            "type":"Entertainment"
        }
    ],
    "sg:phone":"+1 415 467 1806",
    "sg:postcode":"94005",
    "sg:province":"CA",
    "sg:tags":[
        "agency"
    ],
    "wof:name":"Cook International Travel",
    "wof:placetype":"venue"
},
  "geometry": {"coordinates":[-122.40149,37.68576],"type":"Point"}
}