{
  "type": "Feature",
  "properties": {
    "iso:country":"US",
    "sg:address":"16053 Via de Las Palmas",
    "sg:city":"Rancho Santa Fe",
    "sg:classifiers":[
        {
            "category":"Real Estate",
            "subcategory":"Real Estate Agent",
            "type":"Services"
        }
    ],
    "sg:phone":"+1 858 756 4411",
    "sg:postcode":"92091",
    "sg:province":"CA",
    "wof:name":"Larry D Russell",
    "wof:placetype":"venue"
},
  "geometry": {"coordinates":[-117.21274,32.990226],"type":"Point"}
}