{
  "type": "Feature",
  "properties": {
    "iso:country":"US",
    "sg:address":"8323 Baldwin St",
    "sg:city":"Oakland",
    "sg:classifiers":[
        {
            "category":"Retail",
            "subcategory":"Animal Services",
            "type":"Services"
        }
    ],
    "sg:phone":"+1 510 569 1606",
    "sg:postcode":"94621",
    "sg:province":"CA",
    "sg:tags":[
        "shelter"
    ],
    "sg:website":"www.ospca.org.com",
    "wof:name":"Oakland SPCA Veterinary",
    "wof:placetype":"venue"
},
  "geometry": {"coordinates":[-122.1945,37.747014],"type":"Point"}
}