{
  "type": "Feature",
  "properties": {
    "iso:country":"US",
    "sg:address":"6466 Livia Ave",
    "sg:city":"Temple City",
    "sg:classifiers":[
        {
            "category":"Manufacturing",
            "subcategory":"Electronics",
            "type":"Manufacturing & Wholesale Goods"
        }
    ],
    "sg:phone":"+1 626 625 2637",
    "sg:postcode":"91780",
    "sg:province":"CA",
    "sg:tags":[
        "electronic",
        "component",
        "mfg"
    ],
    "wof:name":"Optin Global Inc",
    "wof:placetype":"venue"
},
  "geometry": {"coordinates":[-118.071214,34.117053],"type":"Point"}
}