{
  "type": "Feature",
  "properties": {
    "addr:full":"1400 Mountain Ave Duarte CA 91010",
    "addr:housenumber":"1400",
    "addr:postcode":"91010",
    "addr:street":"Mountain Ave",
    "iso:country":"US",
    "sg:address":"1400 Mountain Ave",
    "sg:city":"Duarte",
    "sg:classifiers":[
        {
            "category":"Autos & Motor Vehicles",
            "subcategory":"Auto Supplies",
            "type":"Retail Goods"
        }
    ],
    "sg:phone":"+1 626 358 8472",
    "sg:postcode":"91010",
    "sg:province":"CA",
    "sg:tags":[
        "tire"
    ],
    "wof:name":"Speedwurk & Wheel Repair USA",
    "wof:placetype":"venue"
},
  "geometry": {"coordinates":[-117.986334,34.137395],"type":"Point"}
}