{
  "type": "Feature",
  "properties": {
    "iso:country":"US",
    "sg:address":"3312 Don Pedro Rd",
    "sg:city":"Ceres",
    "sg:classifiers":[
        {
            "category":"Transit Center",
            "subcategory":"Freight",
            "type":"Transportation"
        },
        {
            "category":"Freight",
            "type":"Transportation"
        }
    ],
    "sg:phone":"+1 209 537 8417",
    "sg:postcode":"95307",
    "sg:province":"CA",
    "sg:tags":[
        "local",
        "trucking-motor",
        "trucking"
    ],
    "wof:name":"Raul Reyes",
    "wof:placetype":"venue"
},
  "geometry": {"coordinates":[-120.935017,37.583881],"type":"Point"}
}