{
  "type": "Feature",
  "properties": {
    "addr:full":"745 E 12th St Oakland CA 94620",
    "addr:housenumber":"745",
    "addr:postcode":"94620",
    "addr:street":"E 12Th St",
    "iso:country":"US",
    "sg:address":"745 E 12th St",
    "sg:city":"Oakland",
    "sg:classifiers":[
        {
            "category":"Restaurant",
            "type":"Food & Drink"
        },
        {
            "category":"Food & Beverages",
            "subcategory":"Bakery",
            "type":"Retail Goods"
        }
    ],
    "sg:phone":"+1 510 836 1212",
    "sg:postcode":"94620",
    "sg:province":"CA",
    "sg:tags":[
        "sandwich",
        "vietnamese"
    ],
    "wof:name":"Thanh Thuy Deli",
    "wof:placetype":"venue"
},
  "geometry": {"coordinates":[-122.252809,37.793264],"type":"Point"}
}