{
  "type": "Feature",
  "properties": {
    "addr:full":"1301 W Olive Ave Madera CA 93637",
    "addr:housenumber":"1301",
    "addr:postcode":"93637",
    "addr:street":"W Olive Ave",
    "iso:country":"US",
    "sg:address":"1301 W Olive Ave",
    "sg:city":"Madera",
    "sg:classifiers":[
        {
            "category":"Banks & Credit Unions",
            "subcategory":"Financial Services",
            "type":"Services"
        }
    ],
    "sg:phone":"+1 559 675 3939",
    "sg:postcode":"93637",
    "sg:province":"CA",
    "sg:tags":[
        "cashing",
        "loan",
        "check"
    ],
    "wof:name":"Payday Services Plus",
    "wof:placetype":"venue"
},
  "geometry": {"coordinates":[-120.072365,36.952805],"type":"Point"}
}