{
  "type": "Feature",
  "properties": {
    "iso:country":"US",
    "sg:address":"1111 Ulatis Dr",
    "sg:city":"Vacaville",
    "sg:classifiers":[
        {
            "category":"Social Services",
            "subcategory":"Adult Care",
            "type":"Services"
        }
    ],
    "sg:phone":"+1 707 447 7100",
    "sg:postcode":"95687",
    "sg:province":"CA",
    "sg:tags":[
        "home",
        "residential"
    ],
    "sg:website":"www.summerfieldhousealf.com",
    "wof:name":"Summerfield House Assisted",
    "wof:placetype":"venue"
},
  "geometry": {"coordinates":[-121.963997,38.357184],"type":"Point"}
}