{
  "type": "Feature",
  "properties": {
    "iso:country":"US",
    "sg:address":"10022 S Inglewood Avenue",
    "sg:city":"Inglewood",
    "sg:classifiers":[
        {
            "category":"Restaurant",
            "type":"Food & Drink"
        }
    ],
    "sg:phone":"+1 310 671 6295",
    "sg:postcode":"90304",
    "sg:province":"CA",
    "wof:name":"Restaurant Y Panaderia Ilobasco",
    "wof:placetype":"venue"
},
  "geometry": {"coordinates":[-118.361466,33.945264],"type":"Point"}
}