{
  "type": "Feature",
  "properties": {
    "iso:country":"US",
    "sg:address":"435 Arden Ave",
    "sg:city":"Glendale",
    "sg:classifiers":[
        {
            "category":"Health Services",
            "subcategory":"Podiatrist",
            "type":"Services"
        }
    ],
    "sg:phone":"+1 818 240 5575",
    "sg:postcode":"91203",
    "sg:province":"CA",
    "wof:name":"Glendale Podiatry Group",
    "wof:placetype":"venue"
},
  "geometry": {"coordinates":[-118.263187,34.158526],"type":"Point"}
}