{
  "type": "Feature",
  "properties": {
    "addr:full":"2727 McKee Rd San Jose CA 95127",
    "addr:housenumber":"2727",
    "addr:postcode":"95127",
    "addr:street":"Mckee Rd",
    "iso:country":"US",
    "sg:address":"2727 McKee Rd",
    "sg:city":"San Jose",
    "sg:classifiers":[
        {
            "category":"Health Services",
            "subcategory":"Doctor",
            "type":"Services"
        }
    ],
    "sg:phone":"+1 408 259 5545",
    "sg:postcode":"95127",
    "sg:province":"CA",
    "sg:tags":[
        "dentist"
    ],
    "wof:name":"Capitol Square Dental Care",
    "wof:placetype":"venue"
},
  "geometry": {"coordinates":[-121.84200300000001,37.371201],"type":"Point"}
}