{
  "type": "Feature",
  "properties": {
    "iso:country":"US",
    "sg:address":"3728 W Olympic Blvd",
    "sg:city":"Los Angeles",
    "sg:classifiers":[
        {
            "category":"Restaurant",
            "type":"Food & Drink"
        }
    ],
    "sg:phone":"+1 323 731 5405",
    "sg:postcode":"90019",
    "sg:province":"CA",
    "wof:name":"Olympic Cafe",
    "wof:placetype":"venue"
},
  "geometry": {"coordinates":[-118.319,34.053398],"type":"Point"}
}