{
  "type": "Feature",
  "properties": {
    "iso:country":"US",
    "sg:address":"13732 Clinton St",
    "sg:city":"Garden Grove",
    "sg:classifiers":[
        {
            "category":"Organizations",
            "subcategory":"Religious Organization",
            "type":"Services"
        }
    ],
    "sg:phone":"+1 714 537 8748",
    "sg:postcode":"92843",
    "sg:province":"CA",
    "wof:name":"Southeastern CA Conference SDA",
    "wof:placetype":"venue"
},
  "geometry": {"coordinates":[-117.91149900000001,33.76148],"type":"Point"}
}