{
  "type": "Feature",
  "properties": {
    "iso:country":"US",
    "sg:address":"4045 Bonita Rd Ste 308",
    "sg:city":"Bonita",
    "sg:classifiers":[
        {
            "category":"Restaurant",
            "type":"Food & Drink"
        },
        {
            "category":"Utilities",
            "type":"Services"
        }
    ],
    "sg:phone":"+1 619 470 7316",
    "sg:postcode":"91902",
    "sg:province":"CA",
    "sg:tags":[
        "provider",
        "internet"
    ],
    "wof:name":"Internet Ventures West",
    "wof:placetype":"venue"
},
  "geometry": {"coordinates":[-117.039461,32.658848],"type":"Point"}
}