{
  "type": "Feature",
  "properties": {
    "iso:country":"US",
    "sg:address":"625 River Oaks Pkwy",
    "sg:city":"San Jose",
    "sg:classifiers":[
        {
            "category":"Communications",
            "type":"Services"
        }
    ],
    "sg:phone":"+1 408 324 1791",
    "sg:postcode":"95134",
    "sg:province":"CA",
    "wof:name":"Cellynk Communications",
    "wof:placetype":"venue"
},
  "geometry": {"coordinates":[-121.92205800000001,37.39882],"type":"Point"}
}