{
  "type": "Feature",
  "properties": {
    "addr:full":"44916 10th St W Lancaster CA 93534",
    "addr:housenumber":"44916",
    "addr:postcode":"93534",
    "addr:street":"10Th St W",
    "iso:country":"US",
    "sg:address":"44916 10th St W",
    "sg:city":"Lancaster",
    "sg:classifiers":[
        {
            "category":"Professional",
            "subcategory":"Secretarial Services",
            "type":"Services"
        }
    ],
    "sg:phone":"+1 661 945 5300",
    "sg:postcode":"93534",
    "sg:province":"CA",
    "sg:tags":[
        "reporting",
        "court"
    ],
    "wof:name":"Twill Be Done",
    "wof:placetype":"venue"
},
  "geometry": {"coordinates":[-118.14799499999999,34.700422],"type":"Point"}
}