{
  "type": "Feature",
  "properties": {
    "iso:country":"US",
    "sg:address":"312 8th St",
    "sg:city":"San Francisco",
    "sg:classifiers":[
        {
            "category":"Retail",
            "subcategory":"Auto Rental",
            "type":"Services"
        }
    ],
    "sg:phone":"+1 415 703 9000",
    "sg:postcode":"94103",
    "sg:province":"CA",
    "sg:tags":[
        "renting",
        "car",
        "automobile"
    ],
    "sg:website":"www.enterprise.com",
    "wof:name":"Enterprise Rent-A-Car",
    "wof:placetype":"venue"
},
  "geometry": {"coordinates":[-122.409887,37.774866],"type":"Point"}
}