{
  "type": "Feature",
  "properties": {
    "addr:full":"4675 Union St Eureka CA 95503",
    "addr:housenumber":"4675",
    "addr:postcode":"95503",
    "addr:street":"Union St",
    "iso:country":"US",
    "sg:address":"4675 Union St",
    "sg:city":"Eureka",
    "sg:classifiers":[
        {
            "category":"Organizations",
            "subcategory":"Religious Organization",
            "type":"Services"
        }
    ],
    "sg:phone":"+1 707 443 9490",
    "sg:postcode":"95503",
    "sg:province":"CA",
    "sg:tags":[
        "church"
    ],
    "wof:name":"Pinehill Baptist Church",
    "wof:placetype":"venue"
},
  "geometry": {"coordinates":[-124.175346,40.765443],"type":"Point"}
}