{
  "type": "Feature",
  "properties": {
    "addr:full":"1515 State St Santa Barbara CA 93101",
    "addr:housenumber":"1515",
    "addr:postcode":"93101",
    "addr:street":"State St",
    "iso:country":"US",
    "sg:address":"1515 State St",
    "sg:city":"Santa Barbara",
    "sg:classifiers":[
        {
            "category":"Health Services",
            "subcategory":"Health Practitioner",
            "type":"Services"
        }
    ],
    "sg:phone":"+1 805 963 0549",
    "sg:postcode":"93101",
    "sg:province":"CA",
    "sg:tags":[
        "psychologist"
    ],
    "wof:name":"Michael A Errico PHD",
    "wof:placetype":"venue"
},
  "geometry": {"coordinates":[-119.709464,34.426901],"type":"Point"}
}