{
  "type": "Feature",
  "properties": {
    "addr:full":"1720 E 17th St Santa Ana CA 92705",
    "addr:housenumber":"1720",
    "addr:postcode":"92705",
    "addr:street":"E 17Th St",
    "iso:country":"US",
    "sg:address":"1720 E 17th St",
    "sg:city":"Santa Ana",
    "sg:classifiers":[
        {
            "category":"Communications",
            "type":"Services"
        }
    ],
    "sg:phone":"+1 714 564 9781",
    "sg:postcode":"92705",
    "sg:province":"CA",
    "sg:tags":[
        "communication",
        "merchandise"
    ],
    "wof:name":"Kc Communications",
    "wof:placetype":"venue"
},
  "geometry": {"coordinates":[-117.84201400000001,33.759866],"type":"Point"}
}