{
  "type": "Feature",
  "properties": {
    "addr:full":"195 Glen Cove Marina Rd E Vallejo CA 94591",
    "addr:housenumber":"195",
    "addr:postcode":"94591",
    "addr:street":"Glen Cove Marina Rd E",
    "iso:country":"US",
    "sg:address":"195 Glen Cove Marina Rd E",
    "sg:city":"Vallejo",
    "sg:classifiers":[
        {
            "category":"Wholesale",
            "subcategory":"Chemicals & Plastics",
            "type":"Manufacturing & Wholesale Goods"
        }
    ],
    "sg:phone":"+1 707 645 1131",
    "sg:postcode":"94591",
    "sg:province":"CA",
    "sg:website":"www.nalco.com",
    "wof:name":"Nalco Energy Svc",
    "wof:placetype":"venue"
},
  "geometry": {"coordinates":[-122.21259000000001,38.070902],"type":"Point"}
}