{
  "type": "Feature",
  "properties": {
    "iso:country":"US",
    "sg:address":"24953 Pso de Valencia",
    "sg:city":"Laguna Hills",
    "sg:classifiers":[
        {
            "category":"Health Services",
            "subcategory":"Medical Lab",
            "type":"Services"
        }
    ],
    "sg:phone":"+1 949 770 4137",
    "sg:postcode":"92653",
    "sg:province":"CA",
    "sg:tags":[
        "laboratory"
    ],
    "wof:name":"La Paz Medical Laboratory Inc",
    "wof:placetype":"venue"
},
  "geometry": {"coordinates":[-117.700293,33.593519],"type":"Point"}
}