{
  "type": "Feature",
  "properties": {
    "addr:full":"7092 Betty Dr Huntington Beach CA 92647",
    "addr:housenumber":"7092",
    "addr:postcode":"92647",
    "addr:street":"Betty Dr",
    "iso:country":"US",
    "sg:address":"7092 Betty Dr",
    "sg:city":"Huntington Beach",
    "sg:classifiers":[
        {
            "category":"Manufacturing",
            "subcategory":"Tools & Machinery",
            "type":"Manufacturing & Wholesale Goods"
        }
    ],
    "sg:phone":"+1 714 310 6742",
    "sg:postcode":"92647",
    "sg:province":"CA",
    "sg:tags":[
        "lab",
        "mfg"
    ],
    "wof:name":"Rek Enterprises",
    "wof:placetype":"venue"
},
  "geometry": {"coordinates":[-118.003918,33.711525],"type":"Point"}
}