{
  "type": "Feature",
  "properties": {
    "addr:full":"2427 E Santa Fe Ave Merced CA 95340",
    "addr:housenumber":"2427",
    "addr:postcode":"95340",
    "addr:street":"E Santa Fe Ave",
    "iso:country":"US",
    "sg:address":"2427 E Santa Fe Ave",
    "sg:city":"Merced",
    "sg:classifiers":[
        {
            "category":"Organizations",
            "subcategory":"Religious Organization",
            "type":"Services"
        }
    ],
    "sg:phone":"+1 209 722 6142",
    "sg:postcode":"95340",
    "sg:province":"CA",
    "sg:tags":[
        "church"
    ],
    "wof:name":"Apostolic Assembly Church",
    "wof:placetype":"venue"
},
  "geometry": {"coordinates":[-120.44172,37.29539],"type":"Point"}
}