{
  "type": "Feature",
  "properties": {
    "addr:full":"5927 Atlantic Ave Long Beach CA 90805",
    "addr:housenumber":"5927",
    "addr:postcode":"90805",
    "addr:street":"Atlantic Ave",
    "iso:country":"US",
    "sg:address":"5927 Atlantic Ave",
    "sg:city":"Long Beach",
    "sg:classifiers":[
        {
            "category":"Health Services",
            "subcategory":"Nursing And Care Facility",
            "type":"Services"
        }
    ],
    "sg:phone":"+1 562 422 0201",
    "sg:postcode":"90805",
    "sg:province":"CA",
    "sg:tags":[
        "home",
        "convalescent"
    ],
    "wof:name":"Four Seasons Manor",
    "wof:placetype":"venue"
},
  "geometry": {"coordinates":[-118.18506600000001,33.863211],"type":"Point"}
}