{
  "type": "Feature",
  "properties": {
    "addr:full":"811 S Victory Blvd Burbank CA 91502",
    "addr:housenumber":"811",
    "addr:postcode":"91502",
    "addr:street":"S Victory Blvd",
    "iso:country":"US",
    "sg:address":"811 S Victory Blvd",
    "sg:city":"Burbank",
    "sg:classifiers":[
        {
            "category":"Personal",
            "subcategory":"Beauty Salon",
            "type":"Services"
        }
    ],
    "sg:phone":"+1 818 954 9423",
    "sg:postcode":"91502",
    "sg:province":"CA",
    "wof:name":"Argelio's Beauty Salon",
    "wof:placetype":"venue"
},
  "geometry": {"coordinates":[-118.309533,34.167891],"type":"Point"}
}