{
  "type": "Feature",
  "properties": {
    "iso:country":"US",
    "sg:address":"28 Porteous Ave",
    "sg:city":"Fairfax",
    "sg:classifiers":[
        {
            "category":"Food & Beverages",
            "subcategory":"Specialty",
            "type":"Retail Goods"
        }
    ],
    "sg:phone":"+1 415 453 7970",
    "sg:postcode":"94930",
    "sg:province":"CA",
    "sg:tags":[
        "consulting",
        "management"
    ],
    "wof:name":"Gourmet Helping",
    "wof:placetype":"venue"
},
  "geometry": {"coordinates":[-122.591809,37.979986],"type":"Point"}
}