{
  "type": "Feature",
  "properties": {
    "addr:full":"451 34th St Sacramento CA 95816",
    "addr:housenumber":"451",
    "addr:postcode":"95816",
    "addr:street":"34Th St",
    "iso:country":"US",
    "sg:address":"451 34th St",
    "sg:city":"Sacramento",
    "sg:classifiers":[
        {
            "category":"Professional",
            "type":"Services"
        }
    ],
    "sg:phone":"+1 916 444 5683",
    "sg:postcode":"95816",
    "sg:province":"CA",
    "wof:name":"Queen of Hearts",
    "wof:placetype":"venue"
},
  "geometry": {"coordinates":[-121.457562,38.578638],"type":"Point"}
}