{
  "type": "Feature",
  "properties": {
    "addr:full":"4055 Wilshire Blvd Los Angeles CA 90010",
    "addr:housenumber":"4055",
    "addr:postcode":"90010",
    "addr:street":"Wilshire Blvd",
    "iso:country":"US",
    "sg:address":"4055 Wilshire Blvd",
    "sg:city":"Los Angeles",
    "sg:classifiers":[
        {
            "category":"Personal",
            "type":"Services"
        }
    ],
    "sg:phone":"+1 213 389 3817",
    "sg:postcode":"90010",
    "sg:province":"CA",
    "sg:tags":[
        "electrolysis"
    ],
    "wof:name":"Ambassador Electrolysis Studio",
    "wof:placetype":"venue"
},
  "geometry": {"coordinates":[-118.316136,34.061771],"type":"Point"}
}