{
  "type": "Feature",
  "properties": {
    "iso:country":"US",
    "sg:address":"1855 Industrial St Studio 607",
    "sg:city":"Los Angeles",
    "sg:classifiers":[
        {
            "category":"Professional",
            "subcategory":"Art Services",
            "type":"Services"
        }
    ],
    "sg:phone":"+1 213 415 1838",
    "sg:postcode":"90021",
    "sg:province":"CA",
    "sg:tags":[
        "photographer"
    ],
    "sg:website":"www.kennethdolin.com",
    "wof:name":"Kenneth Dolin Photography",
    "wof:placetype":"venue"
},
  "geometry": {"coordinates":[-118.233054,34.036016],"type":"Point"}
}