{
  "type": "Feature",
  "properties": {
    "addr:full":"6852 Wilbur Ave Reseda CA 91335",
    "addr:housenumber":"6852",
    "addr:postcode":"91335",
    "addr:street":"Wilbur Ave",
    "iso:country":"US",
    "sg:address":"6852 Wilbur Ave",
    "sg:city":"Reseda",
    "sg:classifiers":[
        {
            "category":"Professional",
            "type":"Services"
        }
    ],
    "sg:phone":"+1 818 757 7738",
    "sg:postcode":"91335",
    "sg:province":"CA",
    "sg:tags":[
        "establishment"
    ],
    "wof:name":"LA Mont",
    "wof:placetype":"venue"
},
  "geometry": {"coordinates":[-118.54469400000001,34.195373],"type":"Point"}
}