{
  "type": "Feature",
  "properties": {
    "iso:country":"US",
    "sg:address":"215 N State College Blvd Ste E",
    "sg:city":"Anaheim",
    "sg:classifiers":[
        {
            "category":"Health Services",
            "subcategory":"Doctor",
            "type":"Services"
        }
    ],
    "sg:phone":"+1 714 635 0892",
    "sg:postcode":"92806",
    "sg:province":"CA",
    "sg:tags":[
        "surgeon",
        "oral"
    ],
    "sg:website":"www.anaheimdentalcare.com",
    "wof:name":"Scott Richard B DDS",
    "wof:placetype":"venue"
},
  "geometry": {"coordinates":[-117.889,33.8419],"type":"Point"}
}