{
  "type": "Feature",
  "properties": {
    "addr:full":"912 S Santa Fe Ave Vista CA 92084",
    "addr:housenumber":"912",
    "addr:postcode":"92084",
    "addr:street":"S Santa Fe Ave",
    "iso:country":"US",
    "sg:address":"912 S Santa Fe Ave",
    "sg:city":"Vista",
    "sg:classifiers":[
        {
            "category":"Wholesale",
            "subcategory":"Electrical",
            "type":"Manufacturing & Wholesale Goods"
        }
    ],
    "sg:phone":"+1 760 407 1400",
    "sg:postcode":"92084",
    "sg:province":"CA",
    "sg:tags":[
        "electronic"
    ],
    "wof:name":"Pacific Paging & Wireless No 3",
    "wof:placetype":"venue"
},
  "geometry": {"coordinates":[-117.232764,33.193251],"type":"Point"}
}