{
  "type": "Feature",
  "properties": {
    "addr:full":"5901 Hollywood Blvd Los Angeles CA 90028",
    "addr:housenumber":"5901",
    "addr:postcode":"90028",
    "addr:street":"Hollywood Blvd",
    "iso:country":"US",
    "sg:address":"5901 Hollywood Blvd",
    "sg:city":"Los Angeles",
    "sg:classifiers":[
        {
            "category":"Food & Beverages",
            "subcategory":"Liquor & Beverages",
            "type":"Retail Goods"
        }
    ],
    "sg:phone":"+1 323 462 2891",
    "sg:postcode":"90028",
    "sg:province":"CA",
    "wof:name":"Liquor To Go Go",
    "wof:placetype":"venue"
},
  "geometry": {"coordinates":[-118.320133,34.101664],"type":"Point"}
}