{
  "type": "Feature",
  "properties": {
    "iso:country":"US",
    "sg:address":"2400 Coffee Rd",
    "sg:city":"Modesto",
    "sg:classifiers":[
        {
            "category":"Banks & Credit Unions",
            "subcategory":"Bank",
            "type":"Services"
        }
    ],
    "sg:phone":"+1 209 529 8367",
    "sg:postcode":"95355",
    "sg:province":"CA",
    "sg:tags":[
        "cashing",
        "check"
    ],
    "wof:name":"Advance America",
    "wof:placetype":"venue"
},
  "geometry": {"coordinates":[-120.975725,37.676842],"type":"Point"}
}