{
  "type": "Feature",
  "properties": {
    "addr:full":"3184 22nd St San Francisco CA 94110",
    "addr:housenumber":"3184",
    "addr:postcode":"94110",
    "addr:street":"22Nd St",
    "iso:country":"US",
    "sg:address":"3184 22nd St",
    "sg:city":"San Francisco",
    "sg:classifiers":[
        {
            "category":"Health Services",
            "subcategory":"Dentist",
            "type":"Services"
        }
    ],
    "sg:phone":"+1 415 642 2050",
    "sg:postcode":"94110",
    "sg:province":"CA",
    "wof:name":"Calabio Roberto Z",
    "wof:placetype":"venue"
},
  "geometry": {"coordinates":[-122.418431,37.755594],"type":"Point"}
}