{
  "type": "Feature",
  "properties": {
    "iso:country":"US",
    "sg:address":"3184 22nd St",
    "sg:city":"San Francisco",
    "sg:classifiers":[
        {
            "category":"Health Services",
            "subcategory":"Dentist",
            "type":"Services"
        }
    ],
    "sg:phone":"+1 415 642 2050",
    "sg:postcode":"94110",
    "sg:province":"CA",
    "wof:name":"Calabio Roberto Z",
    "wof:placetype":"venue"
},
  "geometry": {"coordinates":[-122.418431,37.755594],"type":"Point"}
}