{
  "type": "Feature",
  "properties": {
    "addr:full":"20701 Keswick St Canoga Park CA 91306",
    "addr:housenumber":"20701",
    "addr:postcode":"91306",
    "addr:street":"Keswick St",
    "iso:country":"US",
    "sg:address":"20701 Keswick St",
    "sg:city":"Canoga Park",
    "sg:classifiers":[
        {
            "category":"Marine",
            "type":"Transportation"
        }
    ],
    "sg:phone":"+1 818 348 8063",
    "sg:postcode":"91306",
    "sg:province":"CA",
    "sg:tags":[
        "surveyor"
    ],
    "wof:name":"Great Wave Marine",
    "wof:placetype":"venue"
},
  "geometry": {"coordinates":[-118.587388,34.21039],"type":"Point"}
}