{
  "type": "Feature",
  "properties": {
    "addr:full":"11201 Valley Spring Ln North Hollywood CA 91602",
    "addr:housenumber":"11201",
    "addr:postcode":"91602",
    "addr:street":"Valley Spring Ln",
    "iso:country":"US",
    "sg:address":"11201 Valley Spring Ln",
    "sg:city":"North Hollywood",
    "sg:classifiers":[
        {
            "category":"Professional",
            "subcategory":"Art Services",
            "type":"Services"
        }
    ],
    "sg:phone":"+1 818 760 0216",
    "sg:postcode":"91602",
    "sg:province":"CA",
    "sg:tags":[
        "commercial",
        "design"
    ],
    "wof:name":"Spencer Design",
    "wof:placetype":"venue"
},
  "geometry": {"coordinates":[-118.37570599999999,34.147182],"type":"Point"}
}