{
  "type": "Feature",
  "properties": {
    "addr:full":"756 Jasper St San Jose CA 95116",
    "addr:housenumber":"756",
    "addr:postcode":"95116",
    "addr:street":"Jasper St",
    "iso:country":"US",
    "sg:address":"756 Jasper St",
    "sg:city":"San Jose",
    "sg:classifiers":[
        {
            "category":"Building & Trades",
            "subcategory":"Landscaping Services",
            "type":"Services"
        }
    ],
    "sg:phone":"+1 530 795 0236",
    "sg:postcode":"95116",
    "sg:province":"CA",
    "wof:name":"Jose Munoz Garden Service",
    "wof:placetype":"venue"
},
  "geometry": {"coordinates":[-121.857291,37.338888],"type":"Point"}
}