{
  "type": "Feature",
  "properties": {
    "iso:country":"US",
    "sg:address":"1256 Delresto Dr",
    "sg:city":"Beverly Hills",
    "sg:classifiers":[
        {
            "category":"Professional",
            "type":"Services"
        }
    ],
    "sg:phone":"+1 310 271 3862",
    "sg:postcode":"90210",
    "sg:province":"CA",
    "wof:name":"Collators Inc",
    "wof:placetype":"venue"
},
  "geometry": {"coordinates":[-118.42586,34.092321],"type":"Point"}
}