{
  "type": "Feature",
  "properties": {
    "addr:full":"322 Nord Ave Chico CA 95926",
    "addr:housenumber":"322",
    "addr:postcode":"95926",
    "addr:street":"Nord Ave",
    "iso:country":"US",
    "sg:address":"322 Nord Ave",
    "sg:city":"Chico",
    "sg:classifiers":[
        {
            "category":"Shopping",
            "type":"Retail Goods"
        }
    ],
    "sg:phone":"+1 530 895 3410",
    "sg:postcode":"95926",
    "sg:province":"CA",
    "sg:tags":[
        "wedding",
        "supply"
    ],
    "wof:name":"Litho Unlimited",
    "wof:placetype":"venue"
},
  "geometry": {"coordinates":[-121.85122,39.725894],"type":"Point"}
}