{
  "type": "Feature",
  "properties": {
    "iso:country":"US",
    "sg:address":"16701 Central Ave",
    "sg:city":"Carson",
    "sg:classifiers":[
        {
            "category":"Retail",
            "subcategory":"Funeral Services",
            "type":"Services"
        }
    ],
    "sg:phone":"+1 310 635 7441",
    "sg:postcode":"90746",
    "sg:province":"CA",
    "sg:tags":[
        "cemetery"
    ],
    "wof:name":"Lincoln Memorial Park Cemetery",
    "wof:placetype":"venue"
},
  "geometry": {"coordinates":[-118.261002,33.8536],"type":"Point"}
}