{
  "type": "Feature",
  "properties": {
    "addr:full":"145 A St Point Reyes Sta CA 94956",
    "addr:housenumber":"145",
    "addr:postcode":"94956",
    "addr:street":"A St;Reyes Sta",
    "iso:country":"US",
    "sg:address":"145 A St",
    "sg:city":"Point Reyes Sta",
    "sg:classifiers":[
        {
            "category":"Professional",
            "subcategory":"Lawyer & Legal Services",
            "type":"Services"
        }
    ],
    "sg:phone":"+1 415 663 8252",
    "sg:postcode":"94956",
    "sg:province":"CA",
    "sg:tags":[
        "attorney"
    ],
    "wof:name":"Burroughs & Froneberger",
    "wof:placetype":"venue"
},
  "geometry": {"coordinates":[-122.807266,38.069066],"type":"Point"}
}