{
  "type": "Feature",
  "properties": {
    "addr:full":"13375 Broadway Rd Moorpark CA 93021",
    "addr:housenumber":"13375",
    "addr:postcode":"ca 93021",
    "addr:street":"Broadway Rd",
    "iso:country":"US",
    "sg:address":"13375 Broadway Rd",
    "sg:city":"Moorpark",
    "sg:classifiers":[
        {
            "category":"Shopping",
            "subcategory":"Bicycles & Sporting Goods",
            "type":"Retail Goods"
        }
    ],
    "sg:phone":"+1 805 532 0191",
    "sg:postcode":"93021",
    "sg:province":"CA",
    "sg:tags":[
        "horse",
        "furnishing"
    ],
    "wof:name":"HKM USA",
    "wof:placetype":"venue"
},
  "geometry": {"coordinates":[-118.877554,34.315223],"type":"Point"}
}