{
  "type": "Feature",
  "properties": {
    "addr:full":"4185 Adams Ave San Diego CA 92116",
    "addr:housenumber":"4185",
    "addr:postcode":"92116",
    "addr:street":"Adams Ave",
    "iso:country":"US",
    "sg:address":"4185 Adams Ave",
    "sg:city":"San Diego",
    "sg:classifiers":[
        {
            "category":"Manufacturing",
            "subcategory":"Printing",
            "type":"Manufacturing & Wholesale Goods"
        }
    ],
    "sg:phone":"+1 619 281 1520",
    "sg:postcode":"92116",
    "sg:province":"CA",
    "sg:tags":[
        "typesetting"
    ],
    "wof:name":"Kensington Type & Graphics",
    "wof:placetype":"venue"
},
  "geometry": {"coordinates":[-117.10486299999999,32.76315],"type":"Point"}
}