{
  "type": "Feature",
  "properties": {
    "iso:country":"US",
    "sg:address":"105 Bronson St",
    "sg:city":"Santa Cruz",
    "sg:classifiers":[
        {
            "category":"Autos & Motor Vehicles",
            "subcategory":"Boat Sales",
            "type":"Retail Goods"
        }
    ],
    "sg:phone":"+1 831 458 3100",
    "sg:postcode":"95062",
    "sg:province":"CA",
    "sg:tags":[
        "outboard"
    ],
    "wof:name":"Dave's Outboard Motor Repair",
    "wof:placetype":"venue"
},
  "geometry": {"coordinates":[-122.006835,36.968772],"type":"Point"}
}