{
  "type": "Feature",
  "properties": {
    "addr:full":"115 W Linden Ave Burbank CA 91502",
    "addr:housenumber":"115",
    "addr:postcode":"91502",
    "addr:street":"W Linden Ave",
    "iso:country":"US",
    "sg:address":"115 W Linden Ave",
    "sg:city":"Burbank",
    "sg:classifiers":[
        {
            "category":"Shopping",
            "subcategory":"Pets & Pet Supplies",
            "type":"Retail Goods"
        },
        {
            "category":"Retail",
            "subcategory":"Pet Boarding",
            "type":"Services"
        }
    ],
    "sg:phone":"+1 818 567 6487",
    "sg:postcode":"91502",
    "sg:province":"CA",
    "sg:tags":[
        "training",
        "boarding/pet",
        "sitting"
    ],
    "wof:name":"Landmark Kennels",
    "wof:placetype":"venue"
},
  "geometry": {"coordinates":[-118.30100299999999,34.169498],"type":"Point"}
}