{
  "type": "Feature",
  "properties": {
    "iso:country":"US",
    "sg:address":"1910 N West St",
    "sg:city":"Tulare",
    "sg:classifiers":[
        {
            "category":"Building & Trades",
            "subcategory":"Construction",
            "type":"Services"
        }
    ],
    "sg:phone":"+1 559 688 7577",
    "sg:postcode":"93274",
    "sg:province":"CA",
    "sg:tags":[
        "concrete",
        "contractor"
    ],
    "wof:name":"E & P Concrete Construction Co",
    "wof:placetype":"venue"
},
  "geometry": {"coordinates":[-119.36664399999999,36.231392],"type":"Point"}
}