{
  "type": "Feature",
  "properties": {
    "addr:full":"7429 Vantage Ave North Hollywood CA 91605",
    "addr:housenumber":"7429",
    "addr:postcode":"91605",
    "addr:street":"Vantage Ave",
    "iso:country":"US",
    "sg:address":"7429 Vantage Ave",
    "sg:city":"North Hollywood",
    "sg:classifiers":[
        {
            "category":"Professional",
            "type":"Services"
        }
    ],
    "sg:phone":"+1 818 765 2720",
    "sg:postcode":"91605",
    "sg:province":"CA",
    "wof:name":"Visalink",
    "wof:placetype":"venue"
},
  "geometry": {"coordinates":[-118.398048,34.207302],"type":"Point"}
}