{
  "type": "Feature",
  "properties": {
    "iso:country":"US",
    "sg:address":"663 Lighthouse Ave",
    "sg:city":"Pacific Grove",
    "sg:classifiers":[
        {
            "category":"Shopping",
            "subcategory":"Clothing, Apparel, & Fashions",
            "type":"Retail Goods"
        }
    ],
    "sg:phone":"+1 831 646 1297",
    "sg:postcode":"93950",
    "sg:province":"CA",
    "sg:tags":[
        "tailor"
    ],
    "wof:name":"Just For You",
    "wof:placetype":"venue"
},
  "geometry": {"coordinates":[-121.919996,36.622036],"type":"Point"}
}