{
  "type": "Feature",
  "properties": {
    "addr:full":"3105 Patrick Henry Drive Santa Clara CA 95054",
    "addr:housenumber":"3105",
    "addr:postcode":"95054",
    "addr:street":"Patrick Henry Drive",
    "iso:country":"US",
    "sg:address":"3105 Patrick Henry Drive",
    "sg:city":"Santa Clara",
    "sg:classifiers":[
        {
            "category":"Health Services",
            "subcategory":"Doctor",
            "type":"Services"
        }
    ],
    "sg:phone":"+1 408 988 0516",
    "sg:postcode":"95054",
    "sg:province":"CA",
    "wof:name":"Drs Precision Echo",
    "wof:placetype":"venue"
},
  "geometry": {"coordinates":[-121.981483,37.395838],"type":"Point"}
}