{
  "type": "Feature",
  "properties": {
    "addr:full":"2710 University Ave Riverside CA 92507",
    "addr:housenumber":"2710",
    "addr:postcode":"92507",
    "addr:street":"University Ave",
    "iso:country":"US",
    "sg:address":"2710 University Ave",
    "sg:city":"Riverside",
    "sg:classifiers":[
        {
            "category":"Shopping",
            "subcategory":"Jewelry",
            "type":"Retail Goods"
        }
    ],
    "sg:phone":"+1 951 686 1053",
    "sg:postcode":"92507",
    "sg:province":"CA",
    "sg:tags":[
        "jeweler"
    ],
    "wof:name":"Maris Joyeria",
    "wof:placetype":"venue"
},
  "geometry": {"coordinates":[-117.36450499999999,33.977201],"type":"Point"}
}