{
  "type": "Feature",
  "properties": {
    "addr:full":"6066 Cam Real Riverside CA 92509",
    "addr:housenumber":"6066",
    "addr:postcode":"92509",
    "addr:street":"Cam Real",
    "iso:country":"US",
    "sg:address":"6066 Cam Real",
    "sg:city":"Riverside",
    "sg:classifiers":[
        {
            "category":"Banks & Credit Unions",
            "subcategory":"Bank",
            "type":"Services"
        }
    ],
    "sg:phone":"+1 951 360 9333",
    "sg:postcode":"92509",
    "sg:province":"CA",
    "sg:tags":[
        "cashing",
        "check"
    ],
    "wof:name":"California Budget Finance",
    "wof:placetype":"venue"
},
  "geometry": {"coordinates":[-117.451179,33.977794],"type":"Point"}
}