{
  "type": "Feature",
  "properties": {
    "iso:country":"US",
    "sg:address":"1906 Foothill Blvd",
    "sg:city":"Oakland",
    "sg:classifiers":[
        {
            "category":"Food & Beverages",
            "subcategory":"Groceries & Convenience Stores",
            "type":"Retail Goods"
        }
    ],
    "sg:phone":"+1 510 532 6833",
    "sg:postcode":"94606",
    "sg:province":"CA",
    "wof:name":"Foothill Mkt",
    "wof:placetype":"venue"
},
  "geometry": {"coordinates":[-122.238998,37.787899],"type":"Point"}
}