{
  "type": "Feature",
  "properties": {
    "addr:full":"2658 Countryside Dr Placerville CA 95667",
    "addr:housenumber":"2658",
    "addr:postcode":"95667",
    "addr:street":"Countryside Dr",
    "iso:country":"US",
    "sg:address":"2658 Countryside Dr",
    "sg:city":"Placerville",
    "sg:classifiers":[
        {
            "category":"Building & Trades",
            "subcategory":"Construction",
            "type":"Services"
        }
    ],
    "sg:phone":"+1 530 621 1438",
    "sg:postcode":"95667",
    "sg:province":"CA",
    "sg:tags":[
        "contractor"
    ],
    "wof:name":"Automatic Gate Systems",
    "wof:placetype":"venue"
},
  "geometry": {"coordinates":[-120.901068,38.738245],"type":"Point"}
}