{
  "type": "Feature",
  "properties": {
    "iso:country":"US",
    "sg:address":"83 Southwind Cir",
    "sg:city":"Richmond",
    "sg:classifiers":[
        {
            "category":"Real Estate",
            "subcategory":"Real Estate Services",
            "type":"Services"
        },
        {
            "category":"Real Estate",
            "subcategory":"Real Estate Agent",
            "type":"Services"
        }
    ],
    "sg:phone":"+1 510 236 8460",
    "sg:postcode":"94804",
    "sg:province":"CA",
    "sg:tags":[
        "management"
    ],
    "sg:website":"http://www.energyworkspace.com",
    "wof:name":"Energy Works",
    "wof:placetype":"venue"
},
  "geometry": {"coordinates":[-122.342097,37.90838],"type":"Point"}
}