{
  "type": "Feature",
  "properties": {
    "iso:country":"US",
    "sg:address":"2304 Mission St",
    "sg:city":"San Francisco",
    "sg:classifiers":[
        {
            "category":"Retail",
            "subcategory":"Repair Shop",
            "type":"Services"
        }
    ],
    "sg:phone":"+1 415 821 2533",
    "sg:postcode":"94110",
    "sg:province":"CA",
    "sg:tags":[
        "lock",
        "locksmith"
    ],
    "wof:name":"1A1 Emerg A Locks-Locksmith",
    "wof:placetype":"venue"
},
  "geometry": {"coordinates":[-122.419132,37.758692],"type":"Point"}
}