{
  "type": "Feature",
  "properties": {
    "iso:country":"US",
    "sg:address":"6741 N Palm Ave",
    "sg:city":"Fresno",
    "sg:classifiers":[
        {
            "category":"Personal",
            "subcategory":"Beauty Salon",
            "type":"Services"
        }
    ],
    "sg:phone":"+1 559 432 9296",
    "sg:postcode":"93704",
    "sg:province":"CA",
    "wof:name":"Strands",
    "wof:placetype":"venue"
},
  "geometry": {"coordinates":[-119.808403,36.836371],"type":"Point"}
}