{
  "type": "Feature",
  "properties": {
    "iso:country":"US",
    "sg:address":"101 S del Puerto Ave",
    "sg:city":"Patterson",
    "sg:classifiers":[
        {
            "category":"Retail",
            "subcategory":"Laundry & Dry Cleaning",
            "type":"Services"
        }
    ],
    "sg:phone":"+1 209 892 6343",
    "sg:postcode":"95363",
    "sg:province":"CA",
    "sg:tags":[
        "cleaners"
    ],
    "wof:name":"Westside Cleaners & Laundry",
    "wof:placetype":"venue"
},
  "geometry": {"coordinates":[-121.130918,37.468142],"type":"Point"}
}