{
  "type": "Feature",
  "properties": {
    "iso:country":"US",
    "sg:address":"806 E F St",
    "sg:city":"Oakdale",
    "sg:classifiers":[
        {
            "category":"Health Services",
            "subcategory":"Chiropractor",
            "type":"Services"
        }
    ],
    "sg:phone":"+1 209 847 8200",
    "sg:postcode":"95361",
    "sg:province":"CA",
    "wof:name":"Whitemyer Chiropractic Clinic",
    "wof:placetype":"venue"
},
  "geometry": {"coordinates":[-120.841604,37.768718],"type":"Point"}
}