{
  "type": "Feature",
  "properties": {
    "addr:full":"21400 Ellinwood Dr Torrance CA 90503",
    "addr:housenumber":"21400",
    "addr:postcode":"90503",
    "addr:street":"Ellinwood Dr",
    "iso:country":"US",
    "sg:address":"21400 Ellinwood Dr",
    "sg:city":"Torrance",
    "sg:classifiers":[
        {
            "category":"Education",
            "subcategory":"School",
            "type":"Public Place"
        }
    ],
    "sg:phone":"+1 310 533 4559",
    "sg:postcode":"90503",
    "sg:province":"CA",
    "sg:tags":[
        "high",
        "middle",
        "elementary"
    ],
    "wof:name":"Torrance Unified School District",
    "wof:placetype":"venue"
},
  "geometry": {"coordinates":[-118.365594,33.834501],"type":"Point"}
}