{
  "type": "Feature",
  "properties": {
    "iso:country":"US",
    "sg:address":"2865 7th St",
    "sg:city":"Berkeley",
    "sg:classifiers":[
        {
            "category":"Animal Shelter",
            "type":"Public Place"
        }
    ],
    "sg:phone":"+1 510 845 3088",
    "sg:postcode":"94710",
    "sg:province":"CA",
    "wof:name":"Berkeley East Bay Humane Society",
    "wof:placetype":"venue"
},
  "geometry": {"coordinates":[-122.291786,37.853108],"type":"Point"}
}