{
  "type": "Feature",
  "properties": {
    "iso:country":"US",
    "sg:address":"215 San Mateo Rd",
    "sg:city":"Half Moon Bay",
    "sg:classifiers":[
        {
            "category":"Retail",
            "subcategory":"Auto Repair",
            "type":"Services"
        }
    ],
    "sg:phone":"+1 650 726 4027",
    "sg:postcode":"94019",
    "sg:province":"CA",
    "sg:tags":[
        "wrecker"
    ],
    "wof:name":"Curley & Red's Body Shop",
    "wof:placetype":"venue"
},
  "geometry": {"coordinates":[-122.425467,37.469248],"type":"Point"}
}