{
  "type": "Feature",
  "properties": {
    "addr:full":"4880 Sierra St Riverside CA 92504",
    "addr:housenumber":"4880",
    "addr:postcode":"92504",
    "addr:street":"Sierra St",
    "iso:country":"US",
    "sg:address":"4880 Sierra St",
    "sg:city":"Riverside",
    "sg:classifiers":[
        {
            "category":"Health Services",
            "subcategory":"Clinic",
            "type":"Services"
        }
    ],
    "sg:phone":"+1 951 359 4700",
    "sg:postcode":"92504",
    "sg:province":"CA",
    "sg:tags":[
        "home"
    ],
    "wof:name":"Affordable Custom Computers",
    "wof:placetype":"venue"
},
  "geometry": {"coordinates":[-117.410876,33.949703],"type":"Point"}
}