{
  "type": "Feature",
  "properties": {
    "addr:full":"5495 Sunrise Blvd Citrus Heights CA 95610",
    "addr:housenumber":"5495",
    "addr:postcode":"95610",
    "addr:street":"Sunrise Blvd",
    "iso:country":"US",
    "sg:address":"5495 Sunrise Blvd",
    "sg:city":"Citrus Heights",
    "sg:classifiers":[
        {
            "category":"Restaurant",
            "type":"Food & Drink"
        }
    ],
    "sg:menulink":"http://www.allmenus.com/ca/sacramento/92796-fuddruckers/menu/",
    "sg:phone":"+1 916 966 1887",
    "sg:postcode":"95610",
    "sg:province":"CA",
    "sg:tags":[
        "burger",
        "american"
    ],
    "wof:name":"Fuddruckers",
    "wof:placetype":"venue"
},
  "geometry": {"coordinates":[-121.27356399999999,38.666326],"type":"Point"}
}