{
  "type": "Feature",
  "properties": {
    "addr:full":"120 N Indian Hill Blvd Claremont CA 91711",
    "addr:housenumber":"120",
    "addr:postcode":"91711",
    "addr:street":"N Indian Hill Blvd",
    "iso:country":"US",
    "sg:address":"120 N Indian Hill Blvd",
    "sg:city":"Claremont",
    "sg:classifiers":[
        {
            "category":"Health Services",
            "subcategory":"Optometrist",
            "type":"Services"
        }
    ],
    "sg:phone":"+1 909 621 3952",
    "sg:postcode":"91711",
    "sg:province":"CA",
    "wof:name":"Lee Goldstein & Assoc",
    "wof:placetype":"venue"
},
  "geometry": {"coordinates":[-117.71921399999999,34.095445],"type":"Point"}
}