{
  "type": "Feature",
  "properties": {
    "addr:full":"3517 E Shallow Brook Ln Orange CA 92867",
    "addr:housenumber":"3517",
    "addr:postcode":"92867",
    "addr:street":"E Shallow Brook Ln",
    "iso:country":"US",
    "sg:address":"3517 E Shallow Brook Ln",
    "sg:city":"Orange",
    "sg:classifiers":[
        {
            "category":"Wholesale",
            "subcategory":"Non-durable Goods",
            "type":"Manufacturing & Wholesale Goods"
        }
    ],
    "sg:phone":"+1 714 685 8520",
    "sg:postcode":"92867",
    "sg:province":"CA",
    "sg:tags":[
        "imprint",
        "product"
    ],
    "wof:name":"Image Maker Ad Specialties",
    "wof:placetype":"venue"
},
  "geometry": {"coordinates":[-117.81598,33.82986],"type":"Point"}
}