{
  "type": "Feature",
  "properties": {
    "addr:full":"8601 Reseda Blvd Northridge CA 91324",
    "addr:housenumber":"8601",
    "addr:postcode":"91324",
    "addr:street":"Reseda Blvd",
    "iso:country":"US",
    "sg:address":"8601 Reseda Blvd",
    "sg:city":"Northridge",
    "sg:classifiers":[
        {
            "category":"Retail",
            "subcategory":"Auto Repair",
            "type":"Services"
        }
    ],
    "sg:phone":"+1 818 993 5121",
    "sg:postcode":"91324",
    "sg:province":"CA",
    "sg:tags":[
        "automobile",
        "smog"
    ],
    "wof:name":"Twins Auto",
    "wof:placetype":"venue"
},
  "geometry": {"coordinates":[-118.536081,34.227329],"type":"Point"}
}