{
  "type": "Feature",
  "properties": {
    "iso:country":"US",
    "sg:address":"11390 Ventura Blvd",
    "sg:city":"Studio City",
    "sg:classifiers":[
        {
            "category":"Retail",
            "subcategory":"Portrait Studio",
            "type":"Services"
        }
    ],
    "sg:phone":"+1 818 761 9590",
    "sg:postcode":"91604",
    "sg:province":"CA",
    "sg:tags":[
        "photographer"
    ],
    "wof:name":"Life Moment Photo Studio",
    "wof:placetype":"venue"
},
  "geometry": {"coordinates":[-118.377717,34.140085],"type":"Point"}
}