{
  "type": "Feature",
  "properties": {
    "addr:full":"121 Sand Creek Rd Brentwood CA 94513",
    "addr:housenumber":"121",
    "addr:postcode":"ca 94513",
    "addr:street":"Sand Creek Rd",
    "iso:country":"US",
    "sg:address":"121 Sand Creek Rd",
    "sg:city":"Brentwood",
    "sg:classifiers":[
        {
            "category":"Banks & Credit Unions",
            "subcategory":"Bank",
            "type":"Services"
        }
    ],
    "sg:phone":"+1 925 240 2140",
    "sg:postcode":"94513",
    "sg:province":"CA",
    "wof:name":"California Pacific Federal Credit Union",
    "wof:placetype":"venue"
},
  "geometry": {"coordinates":[-121.69699900000001,37.947498],"type":"Point"}
}