{
  "type": "Feature",
  "properties": {
    "iso:country":"US",
    "sg:address":"17326 Edwards Rd",
    "sg:city":"Cerritos",
    "sg:classifiers":[
        {
            "category":"Banks & Credit Unions",
            "subcategory":"Bank",
            "type":"Services"
        }
    ],
    "sg:phone":"+1 562 916 7540",
    "sg:postcode":"90703",
    "sg:province":"CA",
    "sg:tags":[
        "financing"
    ],
    "wof:name":"Funding Source Inc",
    "wof:placetype":"venue"
},
  "geometry": {"coordinates":[-118.034372,33.874532],"type":"Point"}
}