{
  "type": "Feature",
  "properties": {
    "iso:country":"US",
    "sg:address":"7880 Alta Valley Dr",
    "sg:city":"Sacramento",
    "sg:classifiers":[
        {
            "category":"Government",
            "subcategory":"Office",
            "type":"Public Place"
        }
    ],
    "sg:phone":"+1 916 689 5293",
    "sg:postcode":"95823",
    "sg:province":"CA",
    "sg:tags":[
        "security",
        "administration",
        "social"
    ],
    "wof:name":"Social Security Administration",
    "wof:placetype":"venue"
},
  "geometry": {"coordinates":[-121.42560400000001,38.473673],"type":"Point"}
}