{
  "type": "Feature",
  "properties": {
    "addr:full":"1290 Walnut St Oakdale CA 95361",
    "addr:housenumber":"1290",
    "addr:postcode":"95361",
    "addr:street":"Walnut St",
    "iso:country":"US",
    "sg:address":"1290 Walnut St",
    "sg:city":"Oakdale",
    "sg:classifiers":[
        {
            "category":"Organizations",
            "subcategory":"Religious Organization",
            "type":"Services"
        }
    ],
    "sg:phone":"+1 209 847 4200",
    "sg:postcode":"95361",
    "sg:province":"CA",
    "sg:tags":[
        "church"
    ],
    "wof:name":"Seventh-Day Adventist Church",
    "wof:placetype":"venue"
},
  "geometry": {"coordinates":[-120.861751,37.769225],"type":"Point"}
}