{
  "type": "Feature",
  "properties": {
    "iso:country":"US",
    "sg:address":"714 Francisco Blvd W",
    "sg:city":"San Rafael",
    "sg:classifiers":[
        {
            "category":"Manufacturing",
            "subcategory":"Metals",
            "type":"Manufacturing & Wholesale Goods"
        }
    ],
    "sg:phone":"+1 415 259 0160",
    "sg:postcode":"94901",
    "sg:province":"CA",
    "wof:name":"Quality Custom Chrome",
    "wof:placetype":"venue"
},
  "geometry": {"coordinates":[-122.51095100000001,37.962652],"type":"Point"}
}