{
  "type": "Feature",
  "properties": {
    "iso:country":"US",
    "sg:address":"8355 Monterey St",
    "sg:city":"Gilroy",
    "sg:classifiers":[
        {
            "category":"Building & Trades",
            "subcategory":"Construction",
            "type":"Services"
        }
    ],
    "sg:phone":"+1 408 847 1759",
    "sg:postcode":"95020",
    "sg:province":"CA",
    "sg:tags":[
        "painter"
    ],
    "wof:name":"Johnson & Sons Painting Contr",
    "wof:placetype":"venue"
},
  "geometry": {"coordinates":[-121.574175,37.017806],"type":"Point"}
}