{
  "type": "Feature",
  "properties": {
    "addr:full":"38 Depot Rd Goleta CA 93117",
    "addr:housenumber":"38",
    "addr:postcode":"93117",
    "addr:street":"Depot Rd",
    "iso:country":"US",
    "sg:address":"38 Depot Rd",
    "sg:city":"Goleta",
    "sg:classifiers":[
        {
            "category":"Building & Trades",
            "subcategory":"Landscaping Services",
            "type":"Services"
        }
    ],
    "sg:phone":"+1 805 964 4900",
    "sg:postcode":"93117",
    "sg:province":"CA",
    "sg:tags":[
        "landscape",
        "contractor"
    ],
    "sg:website":"www.acornlmc.com",
    "wof:name":"Acorn Landscape Management Co",
    "wof:placetype":"venue"
},
  "geometry": {"coordinates":[-119.821018,34.438943],"type":"Point"}
}