{
  "type": "Feature",
  "properties": {
    "iso:country":"US",
    "sg:address":"13615 Victory Blvd",
    "sg:city":"Van Nuys",
    "sg:classifiers":[
        {
            "category":"Arts & Performance",
            "subcategory":"Art Gallery",
            "type":"Entertainment"
        }
    ],
    "sg:phone":"+1 818 901 9030",
    "sg:postcode":"91401",
    "sg:province":"CA",
    "wof:name":"Sun Black Art",
    "wof:placetype":"venue"
},
  "geometry": {"coordinates":[-118.431,34.178501],"type":"Point"}
}