{
  "type": "Feature",
  "properties": {
    "iso:country":"US",
    "sg:address":"539 Sutter St",
    "sg:city":"San Francisco",
    "sg:classifiers":[
        {
            "category":"Food & Beverages",
            "subcategory":"Groceries & Convenience Stores",
            "type":"Retail Goods"
        }
    ],
    "sg:phone":"+1 415 392 4866",
    "sg:postcode":"94102",
    "sg:province":"CA",
    "sg:tags":[
        "grocer"
    ],
    "wof:name":"Theatre Market",
    "wof:placetype":"venue"
},
  "geometry": {"coordinates":[-122.409725,37.789023],"type":"Point"}
}