{
  "type": "Feature",
  "properties": {
    "iso:country":"US",
    "sg:address":"1372 N 2nd Ave",
    "sg:city":"Upland",
    "sg:classifiers":[
        {
            "category":"Organizations",
            "subcategory":"Non-profit Organization",
            "type":"Services"
        }
    ],
    "sg:phone":"+1 909 946 7242",
    "sg:postcode":"91786",
    "sg:province":"CA",
    "sg:tags":[
        "disability"
    ],
    "wof:name":"Casa R & M Enterprise",
    "wof:placetype":"venue"
},
  "geometry": {"coordinates":[-117.64852399999999,34.111617],"type":"Point"}
}