{
  "type": "Feature",
  "properties": {
    "addr:full":"23 Leon Way Fallbrook CA 92028",
    "addr:housenumber":"23",
    "addr:postcode":"92028",
    "addr:street":"Leon Way",
    "iso:country":"US",
    "sg:address":"23 Leon Way",
    "sg:city":"Fallbrook",
    "sg:classifiers":[
        {
            "category":"Wholesale",
            "subcategory":"Plants",
            "type":"Manufacturing & Wholesale Goods"
        }
    ],
    "sg:phone":"+1 760 451 1542",
    "sg:postcode":"92028",
    "sg:province":"CA",
    "sg:tags":[
        "nursery",
        "tree"
    ],
    "wof:name":"Mc Hutchison Horticultural",
    "wof:placetype":"venue"
},
  "geometry": {"coordinates":[-117.19138599999999,33.390671],"type":"Point"}
}