{
  "type": "Feature",
  "properties": {
    "addr:full":"18125 Bloomfield Ave Cerritos CA 90703",
    "addr:housenumber":"18125",
    "addr:postcode":"ca 90703",
    "addr:street":"Bloomfield Ave",
    "iso:country":"US",
    "sg:address":"18125 Bloomfield Ave",
    "sg:city":"Cerritos",
    "sg:classifiers":[
        {
            "category":"Government",
            "subcategory":"Office",
            "type":"Public Place"
        }
    ],
    "sg:phone":"+1 562 916 1311",
    "sg:postcode":"90703",
    "sg:province":"CA",
    "sg:tags":[
        "village"
    ],
    "sg:website":"www.ci.cerritos.ca.us",
    "wof:name":"Cerritos City Manager's Office",
    "wof:placetype":"venue"
},
  "geometry": {"coordinates":[-118.063818,33.866846],"type":"Point"}
}