{
  "type": "Feature",
  "properties": {
    "iso:country":"US",
    "sg:address":"1927 5th Ave",
    "sg:city":"San Diego",
    "sg:classifiers":[
        {
            "category":"Professional",
            "subcategory":"Lawyer & Legal Services",
            "type":"Services"
        }
    ],
    "sg:phone":"+1 619 238 5734",
    "sg:postcode":"92101",
    "sg:province":"CA",
    "sg:tags":[
        "attorney"
    ],
    "wof:name":"Kevin Burton",
    "wof:placetype":"venue"
},
  "geometry": {"coordinates":[-117.160172,32.72589],"type":"Point"}
}