{
  "type": "Feature",
  "properties": {
    "iso:country":"US",
    "sg:address":"22390 Thunderbird Pl",
    "sg:city":"Hayward",
    "sg:classifiers":[
        {
            "category":"Building & Trades",
            "subcategory":"Construction",
            "type":"Services"
        }
    ],
    "sg:phone":"+1 510 293 6996",
    "sg:postcode":"94545",
    "sg:province":"CA",
    "sg:tags":[
        "roofing",
        "contractor"
    ],
    "wof:name":"Davey Roofing",
    "wof:placetype":"venue"
},
  "geometry": {"coordinates":[-122.12258199999999,37.651897],"type":"Point"}
}