{
  "type": "Feature",
  "properties": {
    "iso:country":"US",
    "sg:address":"281 Kentucky St",
    "sg:city":"San Luis Obispo",
    "sg:classifiers":[
        {
            "category":"Recreation",
            "type":"Entertainment"
        }
    ],
    "sg:phone":"+1 805 545 9429",
    "sg:postcode":"93405",
    "sg:province":"CA",
    "sg:tags":[
        "newspaper"
    ],
    "wof:name":"Gordon Douglas Company",
    "wof:placetype":"venue"
},
  "geometry": {"coordinates":[-120.659271,35.29431],"type":"Point"}
}