{
  "type": "Feature",
  "properties": {
    "addr:full":"3250 Dale Rd Modesto CA 95356",
    "addr:housenumber":"3250",
    "addr:postcode":"ca 95356",
    "addr:street":"Dale Rd",
    "iso:country":"US",
    "sg:address":"3250 Dale Rd",
    "sg:city":"Modesto",
    "sg:classifiers":[
        {
            "category":"Restaurant",
            "type":"Food & Drink"
        }
    ],
    "sg:menulink":"http://www.allmenus.com/ca/modesto/219338-velvet-grill/menu/",
    "sg:phone":"+1 209 527 2662",
    "sg:postcode":"95356",
    "sg:province":"CA",
    "sg:tags":[
        "new",
        "american"
    ],
    "wof:name":"Velvet Grill",
    "wof:placetype":"venue"
},
  "geometry": {"coordinates":[-121.049826,37.686746],"type":"Point"}
}