{
  "type": "Feature",
  "properties": {
    "addr:full":"17905 Sky Park Cir Irvine CA 92614",
    "addr:housenumber":"17905",
    "addr:postcode":"92614",
    "addr:street":"Sky Park Cir",
    "iso:country":"US",
    "sg:address":"17905 Sky Park Cir",
    "sg:city":"Irvine",
    "sg:classifiers":[
        {
            "category":"Manufacturing",
            "subcategory":"Printing",
            "type":"Manufacturing & Wholesale Goods"
        }
    ],
    "sg:phone":"+1 949 752 7916",
    "sg:postcode":"92614",
    "sg:province":"CA",
    "sg:tags":[
        "publisher",
        "software"
    ],
    "wof:name":"Shoptech Industrial Software",
    "wof:placetype":"venue"
},
  "geometry": {"coordinates":[-117.860512,33.691087],"type":"Point"}
}