{
  "type": "Feature",
  "properties": {
    "iso:country":"US",
    "sg:address":"2127 Ashby Avenue",
    "sg:city":"Berkeley",
    "sg:classifiers":[
        {
            "category":"Health Services",
            "subcategory":"Clinic",
            "type":"Services"
        }
    ],
    "sg:phone":"+1 510 549 1660",
    "sg:postcode":"94705",
    "sg:province":"CA",
    "sg:tags":[
        "counseling",
        "mental"
    ],
    "wof:name":"Sarazin Gardenia Mft",
    "wof:placetype":"venue"
},
  "geometry": {"coordinates":[-122.264999,37.8554],"type":"Point"}
}