{
  "type": "Feature",
  "properties": {
    "addr:full":"136 E Haley St Santa Barbara CA 93101",
    "addr:housenumber":"136",
    "addr:postcode":"93101",
    "addr:street":"E Haley St",
    "iso:country":"US",
    "sg:address":"136 E Haley St",
    "sg:city":"Santa Barbara",
    "sg:classifiers":[
        {
            "category":"Autos & Motor Vehicles",
            "subcategory":"Auto Supplies",
            "type":"Retail Goods"
        }
    ],
    "sg:phone":"+1 805 962 4523",
    "sg:postcode":"93101",
    "sg:province":"CA",
    "sg:tags":[
        "tire"
    ],
    "wof:name":"Big O Tires",
    "wof:placetype":"venue"
},
  "geometry": {"coordinates":[-119.69375100000001,34.418258],"type":"Point"}
}