{
  "type": "Feature",
  "properties": {
    "addr:full":"816 Cacique St Santa Barbara CA 93103",
    "addr:housenumber":"816",
    "addr:postcode":"93103",
    "addr:street":"Cacique St",
    "iso:country":"US",
    "sg:address":"816 Cacique St",
    "sg:city":"Santa Barbara",
    "sg:classifiers":[
        {
            "category":"Social Services",
            "type":"Services"
        }
    ],
    "sg:phone":"+1 805 564 0093",
    "sg:postcode":"93103",
    "sg:province":"CA",
    "sg:tags":[
        "organization",
        "welfare"
    ],
    "wof:name":"Community Kitchen",
    "wof:placetype":"venue"
},
  "geometry": {"coordinates":[-119.676421,34.419523],"type":"Point"}
}