{
  "type": "Feature",
  "properties": {
    "addr:full":"931 Kearny Street San Francisco CA 94133",
    "addr:housenumber":"931",
    "addr:postcode":"94133",
    "addr:street":"Kearny Street",
    "iso:country":"US",
    "sg:address":"931 Kearny Street",
    "sg:city":"San Francisco",
    "sg:classifiers":[
        {
            "category":"Personal",
            "subcategory":"Massage",
            "type":"Services"
        }
    ],
    "sg:phone":"+1 415 399 9902",
    "sg:postcode":"94133",
    "sg:province":"CA",
    "wof:name":"Thailand Spa & Massage",
    "wof:placetype":"venue"
},
  "geometry": {"coordinates":[-122.404999,37.796501],"type":"Point"}
}