{
  "type": "Feature",
  "properties": {
    "iso:country":"US",
    "sg:address":"3171 Solano Ave",
    "sg:city":"Napa",
    "sg:classifiers":[
        {
            "category":"Real Estate",
            "subcategory":"Architect",
            "type":"Services"
        }
    ],
    "sg:phone":"+1 707 255 0782",
    "sg:postcode":"94558",
    "sg:province":"CA",
    "wof:name":"Herman J Kozlowski",
    "wof:placetype":"venue"
},
  "geometry": {"coordinates":[-122.30777399999999,38.315893],"type":"Point"}
}