{
  "type": "Feature",
  "properties": {
    "addr:full":"964 Borra Pl Escondido CA 92029",
    "addr:housenumber":"964",
    "addr:postcode":"92029",
    "addr:street":"Borra Pl",
    "iso:country":"US",
    "sg:address":"964 Borra Pl",
    "sg:city":"Escondido",
    "sg:classifiers":[
        {
            "category":"Manufacturing",
            "subcategory":"Printing",
            "type":"Manufacturing & Wholesale Goods"
        }
    ],
    "sg:phone":"+1 760 743 0051",
    "sg:postcode":"92029",
    "sg:province":"CA",
    "sg:tags":[
        "printer"
    ],
    "sg:website":"www.allitho.com",
    "wof:name":"A & L Litho Inc",
    "wof:placetype":"venue"
},
  "geometry": {"coordinates":[-117.11463999999999,33.111367],"type":"Point"}
}