{
  "type": "Feature",
  "properties": {
    "iso:country":"US",
    "sg:address":"1004 E Cypress St",
    "sg:city":"Covina",
    "sg:classifiers":[
        {
            "category":"Building & Trades",
            "subcategory":"Construction",
            "type":"Services"
        }
    ],
    "sg:phone":"+1 626 859 2270",
    "sg:postcode":"91724",
    "sg:province":"CA",
    "sg:tags":[
        "contractor"
    ],
    "wof:name":"American Builders",
    "wof:placetype":"venue"
},
  "geometry": {"coordinates":[-117.870493,34.095753],"type":"Point"}
}