{
  "type": "Feature",
  "properties": {
    "addr:full":"8300 Yuma Pl Los Angeles CA 90046",
    "addr:housenumber":"8300",
    "addr:postcode":"90046",
    "addr:street":"Yuma Pl",
    "iso:country":"US",
    "sg:address":"8300 Yuma Pl",
    "sg:city":"Los Angeles",
    "sg:classifiers":[
        {
            "category":"Arts & Performance",
            "subcategory":"Theater",
            "type":"Entertainment"
        }
    ],
    "sg:phone":"+1 323 856 9030",
    "sg:postcode":"90046",
    "sg:province":"CA",
    "sg:tags":[
        "theatrical",
        "manager",
        "producer"
    ],
    "wof:name":"Jerome Martin Entertainment",
    "wof:placetype":"venue"
},
  "geometry": {"coordinates":[-118.373732,34.10655],"type":"Point"}
}