{
  "type": "Feature",
  "properties": {
    "iso:country":"US",
    "sg:address":"4211 Rosewood Dr",
    "sg:city":"Pleasanton",
    "sg:classifiers":[
        {
            "category":"Personal",
            "type":"Services"
        }
    ],
    "sg:phone":"+1 925 227 1477",
    "sg:postcode":"94588",
    "sg:province":"CA",
    "sg:tags":[
        "therapist",
        "massage"
    ],
    "wof:name":"Fuji Therapy",
    "wof:placetype":"venue"
},
  "geometry": {"coordinates":[-121.87499699999999,37.697271],"type":"Point"}
}