{
  "type": "Feature",
  "properties": {
    "iso:country":"US",
    "sg:address":"25-B Noe St",
    "sg:city":"San Francisco",
    "sg:classifiers":[
        {
            "category":"Sports & Exercise",
            "subcategory":"Gym",
            "type":"Entertainment"
        }
    ],
    "sg:phone":"+1 415 730 2385",
    "sg:postcode":"94114",
    "sg:province":"CA",
    "sg:tags":[
        "pilate"
    ],
    "sg:website":"www.volitionfitness.com",
    "wof:name":"Volition Fitness",
    "wof:placetype":"venue"
},
  "geometry": {"coordinates":[-122.43347300000001,37.768705],"type":"Point"}
}