{
  "type": "Feature",
  "properties": {
    "iso:country":"US",
    "sg:address":"1714 Victory Blvd",
    "sg:city":"Glendale",
    "sg:classifiers":[
        {
            "category":"Restaurant",
            "type":"Food & Drink"
        }
    ],
    "sg:phone":"+1 818 247 1851",
    "sg:postcode":"91201",
    "sg:province":"CA",
    "sg:tags":[
        "thai",
        "eating"
    ],
    "wof:name":"Chinda Barbeque & Restaurant",
    "wof:placetype":"venue"
},
  "geometry": {"coordinates":[-118.30100299999999,34.161598],"type":"Point"}
}