{
  "type": "Feature",
  "properties": {
    "iso:country":"US",
    "sg:address":"1531 Elsdon Cir",
    "sg:city":"Carmichael",
    "sg:classifiers":[
        {
            "category":"Health Services",
            "subcategory":"Doctor",
            "type":"Services"
        }
    ],
    "sg:phone":"+1 916 487 9198",
    "sg:postcode":"95608",
    "sg:province":"CA",
    "sg:tags":[
        "physician",
        "family",
        "practice",
        "surgeons",
        "medicine"
    ],
    "wof:name":"Richard F Zipf Md Medical",
    "wof:placetype":"venue"
},
  "geometry": {"coordinates":[-121.34432200000001,38.593401],"type":"Point"}
}