{
  "type": "Feature",
  "properties": {
    "iso:country":"US",
    "sg:address":"101 W Santa Fe Ave",
    "sg:city":"Placentia",
    "sg:classifiers":[
        {
            "category":"Restaurant",
            "type":"Food & Drink"
        }
    ],
    "sg:phone":"+1 714 528 0110",
    "sg:postcode":"92870",
    "sg:province":"CA",
    "sg:tags":[
        "mexican"
    ],
    "wof:name":"Tlaquepaque Restaurant",
    "wof:placetype":"venue"
},
  "geometry": {"coordinates":[-117.87137800000001,33.868999],"type":"Point"}
}