{
  "type": "Feature",
  "properties": {
    "addr:full":"2481 Piedmont Dr Riverside CA 92506",
    "addr:housenumber":"2481",
    "addr:postcode":"92506",
    "addr:street":"Piedmont Dr",
    "iso:country":"US",
    "sg:address":"2481 Piedmont Dr",
    "sg:city":"Riverside",
    "sg:classifiers":[
        {
            "category":"Manufacturing",
            "subcategory":"Printing",
            "type":"Manufacturing & Wholesale Goods"
        }
    ],
    "sg:phone":"+1 951 686 1534",
    "sg:postcode":"92506",
    "sg:province":"CA",
    "sg:tags":[
        "book"
    ],
    "wof:name":"Cappuccino Productions",
    "wof:placetype":"venue"
},
  "geometry": {"coordinates":[-117.366277,33.941865],"type":"Point"}
}