{
  "type": "Feature",
  "properties": {
    "iso:country":"US",
    "sg:address":"275 Bon Air Ctr",
    "sg:city":"Greenbrae",
    "sg:classifiers":[
        {
            "category":"Personal",
            "subcategory":"Beauty Salon",
            "type":"Services"
        },
        {
            "category":"Personal",
            "subcategory":"Barber",
            "type":"Services"
        }
    ],
    "sg:phone":"+1 415 461 0960",
    "sg:postcode":"94904",
    "sg:province":"CA",
    "sg:tags":[
        "hair",
        "stylist"
    ],
    "sg:website":"http://www.theranchsalons.com",
    "wof:name":"Ranch Of Bon Air",
    "wof:placetype":"venue"
},
  "geometry": {"coordinates":[-122.53707900000001,37.948608],"type":"Point"}
}