{
  "type": "Feature",
  "properties": {
    "addr:full":"13345 Telegraph Rd Ste G Whittier CA 90605",
    "addr:housenumber":"13345",
    "addr:postcode":"90605",
    "addr:street":"Telegraph Rd Ste G",
    "iso:country":"US",
    "sg:address":"13345 Telegraph Rd Ste G",
    "sg:city":"Whittier",
    "sg:classifiers":[
        {
            "category":"Health Services",
            "subcategory":"Doctor",
            "type":"Services"
        }
    ],
    "sg:phone":"+1 562 944 2181",
    "sg:postcode":"90605",
    "sg:province":"CA",
    "sg:website":"www.montesmedical.com",
    "wof:name":"Montes Medical Group Inc",
    "wof:placetype":"venue"
},
  "geometry": {"coordinates":[-118.047016,33.941206],"type":"Point"}
}