{
  "type": "Feature",
  "properties": {
    "addr:full":"135 City Place Dr Santa Ana CA 92705",
    "addr:housenumber":"135",
    "addr:postcode":"92705",
    "addr:street":"City Place Dr",
    "iso:country":"US",
    "sg:address":"135 City Place Dr",
    "sg:city":"Santa Ana",
    "sg:classifiers":[
        {
            "category":"Personal",
            "type":"Services"
        }
    ],
    "sg:phone":"+1 714 547 9330",
    "sg:postcode":"92705",
    "sg:province":"CA",
    "sg:tags":[
        "sewing",
        "alteration"
    ],
    "sg:website":"www.makeitfitinc.com",
    "wof:name":"Original Hems",
    "wof:placetype":"venue"
},
  "geometry": {"coordinates":[-117.865392,33.77435],"type":"Point"}
}