{
  "type": "Feature",
  "properties": {
    "iso:country":"US",
    "sg:address":"1632 6th St",
    "sg:city":"Coachella",
    "sg:classifiers":[
        {
            "category":"Food & Beverages",
            "subcategory":"Meat & Fish",
            "type":"Retail Goods"
        }
    ],
    "sg:phone":"+1 760 398 5313",
    "sg:postcode":"92236",
    "sg:province":"CA",
    "wof:name":"Super Rancho Meat Market",
    "wof:placetype":"venue"
},
  "geometry": {"coordinates":[-116.174548,33.679886],"type":"Point"}
}