{
  "type": "Feature",
  "properties": {
    "addr:full":"2385 Marron Rd Carlsbad CA 92008",
    "addr:housenumber":"2385",
    "addr:postcode":"92008",
    "addr:street":"Marron Rd",
    "iso:country":"US",
    "sg:address":"2385 Marron Rd",
    "sg:city":"Carlsbad",
    "sg:classifiers":[
        {
            "category":"Cinema",
            "subcategory":"Movie Theater",
            "type":"Entertainment"
        }
    ],
    "sg:phone":"+1 760 720 7000",
    "sg:postcode":"92008",
    "sg:province":"CA",
    "wof:name":"Moviemax Theaters",
    "wof:placetype":"venue"
},
  "geometry": {"coordinates":[-117.327322,33.177309],"type":"Point"}
}