{
  "type": "Feature",
  "properties": {
    "iso:country":"US",
    "sg:address":"3446 E Orangethorpe Ave",
    "sg:city":"Anaheim",
    "sg:classifiers":[
        {
            "category":"Banks & Credit Unions",
            "subcategory":"Bank",
            "type":"Services"
        }
    ],
    "sg:phone":"+1 714 524 1131",
    "sg:postcode":"92806",
    "sg:province":"CA",
    "sg:tags":[
        "depository",
        "banking",
        "check",
        "cashing"
    ],
    "wof:name":"Check Cashers Plus",
    "wof:placetype":"venue"
},
  "geometry": {"coordinates":[-117.850533,33.867856],"type":"Point"}
}