{
  "type": "Feature",
  "properties": {
    "iso:country":"US",
    "sg:address":"6120 Reseda Blvd",
    "sg:city":"Tarzana",
    "sg:classifiers":[
        {
            "category":"Restaurant",
            "type":"Food & Drink"
        }
    ],
    "sg:phone":"+1 818 342 3333",
    "sg:postcode":"91335",
    "sg:province":"CA",
    "wof:name":"ABC Chinese Fastfood",
    "wof:placetype":"venue"
},
  "geometry": {"coordinates":[-118.53594,34.181324],"type":"Point"}
}