{
  "type": "Feature",
  "properties": {
    "iso:country":"US",
    "sg:address":"1026 Palm St",
    "sg:city":"San Luis Obispo",
    "sg:classifiers":[
        {
            "category":"Professional",
            "subcategory":"Secretarial Services",
            "type":"Services"
        }
    ],
    "sg:phone":"+1 805 541 4324",
    "sg:postcode":"93401",
    "sg:province":"CA",
    "sg:tags":[
        "convention",
        "reporting",
        "court",
        "reporter"
    ],
    "wof:name":"Frank O Nelson & Associates",
    "wof:placetype":"venue"
},
  "geometry": {"coordinates":[-120.661076,35.283327],"type":"Point"}
}