{
  "type": "Feature",
  "properties": {
    "iso:country":"US",
    "sg:address":"300 S Raymond Ave Ste 5",
    "sg:city":"Pasadena",
    "sg:classifiers":[
        {
            "category":"Travel",
            "subcategory":"Travel Agent",
            "type":"Entertainment"
        }
    ],
    "sg:phone":"+1 626 584 9002",
    "sg:postcode":"91105",
    "sg:province":"CA",
    "sg:website":"www.crowncitytravel.com",
    "wof:name":"Crown City Travel",
    "wof:placetype":"venue"
},
  "geometry": {"coordinates":[-118.148472,34.140161],"type":"Point"}
}