{
  "type": "Feature",
  "properties": {
    "iso:country":"US",
    "sg:address":"1500 Scenic Dr",
    "sg:city":"Modesto",
    "sg:classifiers":[
        {
            "category":"Building & Trades",
            "subcategory":"Construction",
            "type":"Services"
        }
    ],
    "sg:phone":"+1 209 523 4223",
    "sg:postcode":"95355",
    "sg:province":"CA",
    "sg:tags":[
        "home",
        "builder"
    ],
    "wof:name":"Rodney K Lowe Development Inc",
    "wof:placetype":"venue"
},
  "geometry": {"coordinates":[-120.966496,37.651379],"type":"Point"}
}