{
  "type": "Feature",
  "properties": {
    "addr:full":"6005 Arlington Ave Riverside CA 92504",
    "addr:housenumber":"6005",
    "addr:postcode":"92504",
    "addr:street":"Arlington Ave",
    "iso:country":"US",
    "sg:address":"6005 Arlington Ave",
    "sg:city":"Riverside",
    "sg:classifiers":[
        {
            "category":"Health Services",
            "subcategory":"Doctor",
            "type":"Services"
        }
    ],
    "sg:phone":"+1 951 352 8318",
    "sg:postcode":"92504",
    "sg:province":"CA",
    "sg:tags":[
        "dentist"
    ],
    "wof:name":"Central City Dental Group",
    "wof:placetype":"venue"
},
  "geometry": {"coordinates":[-117.432096,33.946034],"type":"Point"}
}