{
  "type": "Feature",
  "properties": {
    "iso:country":"US",
    "sg:address":"6769 Skyway Rd",
    "sg:city":"Paradise",
    "sg:classifiers":[
        {
            "category":"Organizations",
            "subcategory":"Religious Organization",
            "type":"Services"
        }
    ],
    "sg:phone":"+1 530 877 9329",
    "sg:postcode":"95969",
    "sg:province":"CA",
    "sg:tags":[
        "church"
    ],
    "wof:name":"I AM Temple",
    "wof:placetype":"venue"
},
  "geometry": {"coordinates":[-121.620712,39.76348],"type":"Point"}
}