{
  "type": "Feature",
  "properties": {
    "addr:full":"74200 Parosella St Palm Desert CA 92260",
    "addr:postcode":"74200;92260",
    "addr:street":"Parosella St",
    "iso:country":"US",
    "sg:address":"74200 Parosella St",
    "sg:city":"Palm Desert",
    "sg:classifiers":[
        {
            "category":"Building & Trades",
            "subcategory":"Cleaning & Sanitation",
            "type":"Services"
        }
    ],
    "sg:phone":"+1 760 568 2396",
    "sg:postcode":"92260",
    "sg:province":"CA",
    "sg:tags":[
        "window"
    ],
    "wof:name":"Chuck Cornelius",
    "wof:placetype":"venue"
},
  "geometry": {"coordinates":[-116.36646500000001,33.716108],"type":"Point"}
}