{
  "type": "Feature",
  "properties": {
    "iso:country":"US",
    "sg:address":"1175 W Steele Ln",
    "sg:city":"Santa Rosa",
    "sg:classifiers":[
        {
            "category":"Health Services",
            "subcategory":"Chiropractor",
            "type":"Services"
        }
    ],
    "sg:phone":"+1 707 578 4156",
    "sg:postcode":"95403",
    "sg:province":"CA",
    "wof:name":"Judevine Chiropractic",
    "wof:placetype":"venue"
},
  "geometry": {"coordinates":[-122.72954799999999,38.460089],"type":"Point"}
}