{
  "type": "Feature",
  "properties": {
    "iso:country":"US",
    "sg:address":"20700 Ventura Blvd Ste 226",
    "sg:city":"Woodland Hills",
    "sg:classifiers":[
        {
            "category":"Professional",
            "subcategory":"Lawyer & Legal Services",
            "type":"Services"
        }
    ],
    "sg:phone":"+1 818 704 8900",
    "sg:postcode":"91364",
    "sg:province":"CA",
    "wof:name":"Glukhovsky Gregory Law Offices Of",
    "wof:placetype":"venue"
},
  "geometry": {"coordinates":[-118.58349,34.166876],"type":"Point"}
}