{
  "type": "Feature",
  "properties": {
    "addr:full":"4790 Dewey Dr Fair Oaks CA 95628",
    "addr:housenumber":"4790",
    "addr:postcode":"95628",
    "addr:street":"Dewey Dr",
    "iso:country":"US",
    "sg:address":"4790 Dewey Dr",
    "sg:city":"Fair Oaks",
    "sg:classifiers":[
        {
            "category":"Building & Trades",
            "subcategory":"Construction",
            "type":"Services"
        }
    ],
    "sg:phone":"+1 916 921 0684",
    "sg:postcode":"95628",
    "sg:province":"CA",
    "sg:tags":[
        "home",
        "improvement"
    ],
    "wof:name":"Brian Moody Co",
    "wof:placetype":"venue"
},
  "geometry": {"coordinates":[-121.308305,38.651676],"type":"Point"}
}