{
  "type": "Feature",
  "properties": {
    "addr:full":"5120 Goldleaf Cir Los Angeles CA 90056",
    "addr:postcode":"5120;90056",
    "addr:street":"Goldleaf Cir",
    "iso:country":"US",
    "sg:address":"5120 Goldleaf Cir",
    "sg:city":"Los Angeles",
    "sg:classifiers":[
        {
            "category":"Insurance",
            "subcategory":"Insurance Agent",
            "type":"Services"
        }
    ],
    "sg:phone":"+1 323 294 1885",
    "sg:postcode":"90056",
    "sg:province":"CA",
    "sg:tags":[
        "consultant"
    ],
    "sg:website":"www.foresters.biz",
    "wof:name":"IOF Foresters",
    "wof:placetype":"venue"
},
  "geometry": {"coordinates":[-118.36820899999999,33.988349],"type":"Point"}
}