{
  "type": "Feature",
  "properties": {
    "addr:full":"415 Bamboo Ln Los Angeles CA 90012",
    "addr:housenumber":"415",
    "addr:postcode":"90012",
    "addr:street":"Bamboo Ln",
    "iso:country":"US",
    "sg:address":"415 Bamboo Ln",
    "sg:city":"Los Angeles",
    "sg:classifiers":[
        {
            "category":"Organizations",
            "subcategory":"Professional Association",
            "type":"Services"
        }
    ],
    "sg:phone":"+1 213 628 8015",
    "sg:postcode":"90012",
    "sg:province":"CA",
    "wof:name":"Chinese American Citizens",
    "wof:placetype":"venue"
},
  "geometry": {"coordinates":[-118.237273,34.06689],"type":"Point"}
}