{
  "type": "Feature",
  "properties": {
    "addr:full":"1324 Texas St Fairfield CA 94533",
    "addr:housenumber":"1324",
    "addr:postcode":"94533",
    "addr:street":"Texas St",
    "iso:country":"US",
    "sg:address":"1324 Texas St",
    "sg:city":"Fairfield",
    "sg:classifiers":[
        {
            "category":"Professional",
            "subcategory":"Accounting & Tax Preparation",
            "type":"Services"
        }
    ],
    "sg:phone":"+1 707 422 8009",
    "sg:postcode":"94533",
    "sg:province":"CA",
    "sg:tags":[
        "bookkeeping",
        "general"
    ],
    "wof:name":"Nor-Cal Accounting & Tax Svc",
    "wof:placetype":"venue"
},
  "geometry": {"coordinates":[-122.05195999999999,38.249337],"type":"Point"}
}