{
  "type": "Feature",
  "properties": {
    "iso:country":"US",
    "sg:address":"59 Landers St",
    "sg:city":"San Francisco",
    "sg:classifiers":[
        {
            "category":"Wholesale",
            "subcategory":"Hardware",
            "type":"Manufacturing & Wholesale Goods"
        },
        {
            "category":"Building & Trades",
            "subcategory":"Plumbing",
            "type":"Services"
        }
    ],
    "sg:phone":"+1 415 407 9285",
    "sg:postcode":"94114",
    "sg:province":"CA",
    "sg:tags":[
        "furnace",
        "contractor"
    ],
    "sg:website":"kohlerheating@yahoo.com",
    "wof:name":"Kohler Heating",
    "wof:placetype":"venue"
},
  "geometry": {"coordinates":[-122.42746,37.766915],"type":"Point"}
}