{
  "type": "Feature",
  "properties": {
    "addr:full":"2495 Hangtree Trl Arnold CA 95223",
    "addr:housenumber":"2495",
    "addr:postcode":"95223",
    "addr:street":"Hangtree Trl",
    "iso:country":"US",
    "sg:address":"2495 Hangtree Trl",
    "sg:city":"Arnold",
    "sg:classifiers":[
        {
            "category":"Manufacturing",
            "subcategory":"Lumber",
            "type":"Manufacturing & Wholesale Goods"
        }
    ],
    "sg:phone":"+1 209 795 7649",
    "sg:postcode":"95223",
    "sg:province":"CA",
    "sg:tags":[
        "company",
        "logging"
    ],
    "wof:name":"Finn's Tree Svc",
    "wof:placetype":"venue"
},
  "geometry": {"coordinates":[-120.27247,38.287357],"type":"Point"}
}