{
  "type": "Feature",
  "properties": {
    "iso:country":"US",
    "sg:address":"139 S Market St",
    "sg:city":"Inglewood",
    "sg:classifiers":[
        {
            "category":"Shopping",
            "subcategory":"Clothing, Apparel, & Fashions",
            "type":"Retail Goods"
        }
    ],
    "sg:phone":"+1 310 673 1363",
    "sg:postcode":"90301",
    "sg:province":"CA",
    "sg:tags":[
        "gown",
        "cap"
    ],
    "wof:name":"C K Hat",
    "wof:placetype":"venue"
},
  "geometry": {"coordinates":[-118.351952,33.962582],"type":"Point"}
}