{
  "type": "Feature",
  "properties": {
    "addr:full":"3918 W Olive Ave Burbank CA 91505",
    "addr:housenumber":"3918",
    "addr:postcode":"91505",
    "addr:street":"W Olive Ave",
    "iso:country":"US",
    "sg:address":"3918 W Olive Ave",
    "sg:city":"Burbank",
    "sg:classifiers":[
        {
            "category":"Arts & Performance",
            "subcategory":"Art Gallery",
            "type":"Entertainment"
        }
    ],
    "sg:phone":"+1 888 368 5213",
    "sg:postcode":"91505",
    "sg:province":"CA",
    "sg:website":"www.McKenzieArtStudio.com",
    "wof:name":"McKenzie Art Studio",
    "wof:placetype":"venue"
},
  "geometry": {"coordinates":[-118.34104499999999,34.150296],"type":"Point"}
}