{
  "type": "Feature",
  "properties": {
    "addr:full":"4065 W Clinton Ave Fresno CA 93722",
    "addr:housenumber":"4065",
    "addr:postcode":"93722",
    "addr:street":"W Clinton Ave",
    "iso:country":"US",
    "sg:address":"4065 W Clinton Ave",
    "sg:city":"Fresno",
    "sg:classifiers":[
        {
            "category":"Restaurant",
            "type":"Food & Drink"
        }
    ],
    "sg:phone":"+1 559 277 2981",
    "sg:postcode":"93722",
    "sg:province":"CA",
    "wof:name":"Dragon Restaurant Chinese",
    "wof:placetype":"venue"
},
  "geometry": {"coordinates":[-119.864172,36.771773],"type":"Point"}
}