{
  "type": "Feature",
  "properties": {
    "iso:country":"US",
    "sg:address":"6322 East Ave",
    "sg:city":"Etiwanda",
    "sg:classifiers":[
        {
            "category":"Insurance",
            "subcategory":"Hazard Insurance",
            "type":"Services"
        }
    ],
    "sg:phone":"+1 909 803 2999",
    "sg:postcode":"91739",
    "sg:province":"CA",
    "sg:tags":[
        "bond"
    ],
    "wof:name":"Southwest Bail Bonds",
    "wof:placetype":"venue"
},
  "geometry": {"coordinates":[-117.514551,34.138795],"type":"Point"}
}