{
  "type": "Feature",
  "properties": {
    "addr:full":"300 E Green Street Pasadena CA 91101",
    "addr:housenumber":"300",
    "addr:postcode":"91101",
    "addr:street":"E Green Street",
    "iso:country":"US",
    "sg:address":"300 E Green Street",
    "sg:city":"Pasadena",
    "sg:classifiers":[
        {
            "category":"Retail",
            "subcategory":"Event Space",
            "type":"Services"
        }
    ],
    "sg:phone":"+1 626 793 2122",
    "sg:postcode":"91101",
    "sg:province":"CA",
    "sg:tags":[
        "venue"
    ],
    "sg:website":"pasadenacenter.com",
    "wof:name":"Pasadena Convention Center",
    "wof:placetype":"venue"
},
  "geometry": {"coordinates":[-118.144243,34.143383],"type":"Point"}
}