{
  "type": "Feature",
  "properties": {
    "iso:country":"US",
    "sg:address":"45238 17th St W",
    "sg:city":"Lancaster",
    "sg:classifiers":[
        {
            "category":"Personal",
            "subcategory":"Beauty Salon",
            "type":"Services"
        }
    ],
    "sg:phone":"+1 661 726 2880",
    "sg:postcode":"93534",
    "sg:province":"CA",
    "sg:tags":[
        "manicuring"
    ],
    "wof:name":"Purple Nail Crafts",
    "wof:placetype":"venue"
},
  "geometry": {"coordinates":[-118.161423,34.705426],"type":"Point"}
}