{
  "type": "Feature",
  "properties": {
    "iso:country":"US",
    "sg:address":"7917 Fruitridge Rd Ste C",
    "sg:city":"Sacramento",
    "sg:classifiers":[
        {
            "category":"Wholesale",
            "subcategory":"Non-durable Goods",
            "type":"Manufacturing & Wholesale Goods"
        },
        {
            "category":"Shopping",
            "subcategory":"Department Store",
            "type":"Retail Goods"
        },
        {
            "category":"Building & Trades",
            "subcategory":"Cleaning & Sanitation",
            "type":"Services"
        },
        {
            "category":"Home & Garden",
            "subcategory":"Hardware",
            "type":"Retail Goods"
        }
    ],
    "sg:phone":"+1 916 379 0779",
    "sg:postcode":"95820",
    "sg:province":"CA",
    "sg:tags":[
        "cleaner",
        "supply",
        "house",
        "equipment",
        "janitor",
        "janitorial",
        "supplies-wholesale",
        "manufacturer"
    ],
    "wof:name":"Platinum Services",
    "wof:placetype":"venue"
},
  "geometry": {"coordinates":[-121.41156599999999,38.525054],"type":"Point"}
}