{
  "type": "Feature",
  "properties": {
    "iso:country":"US",
    "sg:address":"713 N 6th St",
    "sg:city":"Fowler",
    "sg:classifiers":[
        {
            "category":"Personal",
            "subcategory":"Beauty Salon",
            "type":"Services"
        }
    ],
    "sg:phone":"+1 800 465 4983",
    "sg:postcode":"93625",
    "sg:province":"CA",
    "wof:name":"California Trendz",
    "wof:placetype":"venue"
},
  "geometry": {"coordinates":[-119.683319,36.636345],"type":"Point"}
}