{
  "type": "Feature",
  "properties": {
    "iso:country":"US",
    "sg:address":"17350 17th St Ste E",
    "sg:city":"Tustin",
    "sg:classifiers":[
        {
            "category":"Shopping",
            "subcategory":"Jewelry",
            "type":"Retail Goods"
        },
        {
            "category":"Manufacturing",
            "subcategory":"Jewelry",
            "type":"Manufacturing & Wholesale Goods"
        }
    ],
    "sg:phone":"+1 714 544 6206",
    "sg:postcode":"92780",
    "sg:province":"CA",
    "sg:tags":[
        "designer",
        "jeweler"
    ],
    "wof:name":"Discoveries Art To Wear",
    "wof:placetype":"venue"
},
  "geometry": {"coordinates":[-117.828294,33.759733],"type":"Point"}
}