{
  "type": "Feature",
  "properties": {
    "iso:country":"US",
    "sg:address":"6315 3rd St",
    "sg:city":"San Francisco",
    "sg:classifiers":[
        {
            "category":"Social Services",
            "type":"Services"
        }
    ],
    "sg:phone":"+1 415 656 2020",
    "sg:postcode":"94124",
    "sg:province":"CA",
    "sg:tags":[
        "information",
        "cancer"
    ],
    "wof:name":"Bay Area Cancer Study Group",
    "wof:placetype":"venue"
},
  "geometry": {"coordinates":[-122.396446,37.720287],"type":"Point"}
}