{
  "type": "Feature",
  "properties": {
    "addr:full":"555 12th St Ste 1900 Oakland CA 94607",
    "addr:housenumber":"555",
    "addr:postcode":"94607",
    "addr:street":"12Th St Ste 1900",
    "iso:country":"US",
    "sg:address":"555 12th St Ste 1900",
    "sg:city":"Oakland",
    "sg:classifiers":[
        {
            "category":"Professional",
            "subcategory":"Lawyer & Legal Services",
            "type":"Services"
        }
    ],
    "sg:phone":"+1 510 987 7800",
    "sg:postcode":"94607",
    "sg:province":"CA",
    "sg:tags":[
        "divorce",
        "law",
        "family"
    ],
    "sg:website":"www.bobgoodman.com",
    "wof:name":"Law Offices of Robert A Goodman",
    "wof:placetype":"venue"
},
  "geometry": {"coordinates":[-122.274522,37.803924],"type":"Point"}
}