{
  "type": "Feature",
  "properties": {
    "iso:country":"US",
    "sg:address":"1460 E Holt Ave",
    "sg:city":"Pomona",
    "sg:classifiers":[
        {
            "category":"Health Services",
            "subcategory":"Doctor",
            "type":"Services"
        }
    ],
    "sg:phone":"+1 909 620 5125",
    "sg:postcode":"91767",
    "sg:province":"CA",
    "sg:tags":[
        "physician",
        "surgeon"
    ],
    "wof:name":"Leena Sheth MD",
    "wof:placetype":"venue"
},
  "geometry": {"coordinates":[-117.721386,34.063012],"type":"Point"}
}