{
  "type": "Feature",
  "properties": {
    "addr:full":"4229 Convoy St San Diego CA 92111",
    "addr:housenumber":"4229",
    "addr:postcode":"92111",
    "addr:street":"Convoy St",
    "iso:country":"US",
    "sg:address":"4229 Convoy St",
    "sg:city":"San Diego",
    "sg:classifiers":[
        {
            "category":"Restaurant",
            "type":"Food & Drink"
        }
    ],
    "sg:phone":"+1 858 573 2511",
    "sg:postcode":"92111",
    "sg:province":"CA",
    "sg:tags":[
        "korean"
    ],
    "sg:website":"convoytofuhousemenu.info/",
    "wof:name":"Convoy Tofu House",
    "wof:placetype":"venue"
},
  "geometry": {"coordinates":[-117.154875,32.818974],"type":"Point"}
}