{
  "type": "Feature",
  "properties": {
    "iso:country":"US",
    "sg:address":"7120 Carroll Rd",
    "sg:city":"San Diego",
    "sg:classifiers":[
        {
            "category":"Manufacturing",
            "subcategory":"Metals",
            "type":"Manufacturing & Wholesale Goods"
        }
    ],
    "sg:phone":"+1 858 549 0909",
    "sg:postcode":"92121",
    "sg:province":"CA",
    "sg:tags":[
        "tubing"
    ],
    "wof:name":"Westaflex Inc",
    "wof:placetype":"venue"
},
  "geometry": {"coordinates":[-117.169208,32.885352],"type":"Point"}
}