{
  "type": "Feature",
  "properties": {
    "iso:country":"US",
    "sg:address":"8400 N Magnolia Ave",
    "sg:city":"Santee",
    "sg:classifiers":[
        {
            "category":"Building & Trades",
            "subcategory":"Construction",
            "type":"Services"
        }
    ],
    "sg:phone":"+1 619 449 6998",
    "sg:postcode":"92071",
    "sg:province":"CA",
    "sg:tags":[
        "repairing",
        "remodeling",
        "contractor"
    ],
    "wof:name":"Absolute Construction Inc",
    "wof:placetype":"venue"
},
  "geometry": {"coordinates":[-116.962332,32.829558],"type":"Point"}
}