{
  "type": "Feature",
  "properties": {
    "addr:full":"9404 Genesee Ave Ste 330 La Jolla CA 92037",
    "addr:housenumber":"9404",
    "addr:postcode":"92037",
    "addr:street":"Genesee Ave Ste 330",
    "iso:country":"US",
    "sg:address":"9404 Genesee Ave Ste 330",
    "sg:city":"La Jolla",
    "sg:classifiers":[
        {
            "category":"Professional",
            "subcategory":"Employment Agencies",
            "type":"Services"
        }
    ],
    "sg:phone":"+1 858 587 8100",
    "sg:postcode":"92037",
    "sg:province":"CA",
    "wof:name":"Recruitpro Inc",
    "wof:placetype":"venue"
},
  "geometry": {"coordinates":[-117.21430100000001,32.876092],"type":"Point"}
}