{
  "type": "Feature",
  "properties": {
    "addr:full":"1901 Cottonwood Dr Paso Robles CA 93446",
    "addr:housenumber":"1901",
    "addr:postcode":"93446",
    "addr:street":"Cottonwood Dr",
    "iso:country":"US",
    "sg:address":"1901 Cottonwood Dr",
    "sg:city":"Paso Robles",
    "sg:classifiers":[
        {
            "category":"Wholesale",
            "subcategory":"Vending Machines",
            "type":"Manufacturing & Wholesale Goods"
        }
    ],
    "sg:phone":"+1 805 238 3129",
    "sg:postcode":"93446",
    "sg:province":"CA",
    "sg:tags":[
        "operator"
    ],
    "wof:name":"Johnsons Vending",
    "wof:placetype":"venue"
},
  "geometry": {"coordinates":[-120.653944,35.606739],"type":"Point"}
}