{
  "type": "Feature",
  "properties": {
    "addr:full":"12090 Whittier Blvd Whittier CA 90602",
    "addr:housenumber":"12090",
    "addr:postcode":"90602",
    "addr:street":"Whittier Blvd",
    "iso:country":"US",
    "sg:address":"12090 Whittier Blvd",
    "sg:city":"Whittier",
    "sg:classifiers":[
        {
            "category":"Shopping",
            "subcategory":"Used Merchandise",
            "type":"Retail Goods"
        },
        {
            "category":"Wholesale",
            "subcategory":"Auto Parts",
            "type":"Manufacturing & Wholesale Goods"
        }
    ],
    "sg:phone":"+1 562 945 3511",
    "sg:postcode":"90602",
    "sg:province":"CA",
    "sg:tags":[
        "automobile",
        "wrecking",
        "supply"
    ],
    "wof:name":"A-O K Auto Wrecking",
    "wof:placetype":"venue"
},
  "geometry": {"coordinates":[-118.048221,33.977427],"type":"Point"}
}