{
  "type": "Feature",
  "properties": {
    "iso:country":"US",
    "sg:address":"6092 Bowman Ln",
    "sg:city":"Paradise",
    "sg:classifiers":[
        {
            "category":"Professional",
            "type":"Services"
        }
    ],
    "sg:phone":"+1 530 872 1198",
    "sg:postcode":"95969",
    "sg:province":"CA",
    "wof:name":"Michael K Brown",
    "wof:placetype":"venue"
},
  "geometry": {"coordinates":[-121.608591,39.768107],"type":"Point"}
}