{
  "type": "Feature",
  "properties": {
    "addr:full":"15562 Producer Lane Huntington Beach CA 92649",
    "addr:postcode":"15562;92649",
    "addr:street":"Producer Lane",
    "iso:country":"US",
    "sg:address":"15562 Producer Lane",
    "sg:city":"Huntington Beach",
    "sg:classifiers":[
        {
            "category":"Retail",
            "subcategory":"Auto Repair",
            "type":"Services"
        }
    ],
    "sg:phone":"+1 714 893 5096",
    "sg:postcode":"92649",
    "sg:province":"CA",
    "wof:name":"Ital Meccanica Lexus & Volvo Specialists",
    "wof:placetype":"venue"
},
  "geometry": {"coordinates":[-118.02533200000001,33.735964],"type":"Point"}
}