{
  "type": "Feature",
  "properties": {
    "iso:country":"US",
    "sg:address":"425 Market Street",
    "sg:city":"San Francisco",
    "sg:classifiers":[
        {
            "category":"Professional",
            "subcategory":"Lawyer & Legal Services",
            "type":"Services"
        }
    ],
    "sg:phone":"+1 415 268 6467",
    "sg:postcode":"94105",
    "sg:province":"CA",
    "wof:name":"Kreeger Matherw I",
    "wof:placetype":"venue"
},
  "geometry": {"coordinates":[-122.39857499999999,37.791533],"type":"Point"}
}