{
  "type": "Feature",
  "properties": {
    "iso:country":"US",
    "sg:address":"2701 Eureka Way Ste Ga",
    "sg:city":"Redding",
    "sg:classifiers":[
        {
            "category":"Health Services",
            "subcategory":"Podiatrist",
            "type":"Services"
        }
    ],
    "sg:phone":"+1 530 244 7070",
    "sg:postcode":"96001",
    "sg:province":"CA",
    "sg:tags":[
        "physician",
        "surgeons"
    ],
    "wof:name":"Michael Otoole Dpm",
    "wof:placetype":"venue"
},
  "geometry": {"coordinates":[-122.410595,40.585985],"type":"Point"}
}