{
  "type": "Feature",
  "properties": {
    "iso:country":"US",
    "sg:address":"2201 48th St",
    "sg:city":"Sacramento",
    "sg:classifiers":[
        {
            "category":"Restaurant",
            "type":"Food & Drink"
        },
        {
            "category":"Travel",
            "subcategory":"Hotels & Motels",
            "type":"Entertainment"
        }
    ],
    "sg:phone":"+1 916 736 0116",
    "sg:postcode":"95817",
    "sg:province":"CA",
    "sg:tags":[
        "eating"
    ],
    "wof:name":"Kiwanis Family House Ex Dir",
    "wof:placetype":"venue"
},
  "geometry": {"coordinates":[-121.45007,38.554609],"type":"Point"}
}