{
  "type": "Feature",
  "properties": {
    "iso:country":"US",
    "sg:address":"2602 E Florence Ave",
    "sg:city":"Huntington Park",
    "sg:classifiers":[
        {
            "category":"Banks & Credit Unions",
            "subcategory":"Bank",
            "type":"Services"
        }
    ],
    "sg:phone":"+1 323 582 1777",
    "sg:postcode":"90255",
    "sg:province":"CA",
    "sg:tags":[
        "cashing",
        "check"
    ],
    "wof:name":"Money Express",
    "wof:placetype":"venue"
},
  "geometry": {"coordinates":[-118.224489,33.974056],"type":"Point"}
}