{
  "type": "Feature",
  "properties": {
    "iso:country":"US",
    "sg:address":"1450 N Lake Ave",
    "sg:city":"Pasadena",
    "sg:classifiers":[
        {
            "category":"Health Services",
            "subcategory":"Health Practitioner",
            "type":"Services"
        }
    ],
    "sg:phone":"+1 626 798 7805",
    "sg:postcode":"91104",
    "sg:province":"CA",
    "sg:tags":[
        "acupuncture"
    ],
    "wof:name":"Haber Gina LAc",
    "wof:placetype":"venue"
},
  "geometry": {"coordinates":[-118.131981,34.170965],"type":"Point"}
}