{
  "type": "Feature",
  "properties": {
    "addr:full":"738 Roosevelt Ave Redwood City CA 94061",
    "addr:housenumber":"738",
    "addr:postcode":"94061",
    "addr:street":"Roosevelt Ave",
    "iso:country":"US",
    "sg:address":"738 Roosevelt Ave",
    "sg:city":"Redwood City",
    "sg:classifiers":[
        {
            "category":"Freight",
            "type":"Transportation"
        }
    ],
    "sg:phone":"+1 650 780 0248",
    "sg:postcode":"94061",
    "sg:province":"CA",
    "wof:name":"Normans Transportation",
    "wof:placetype":"venue"
},
  "geometry": {"coordinates":[-122.231274,37.474691],"type":"Point"}
}