{
  "type": "Feature",
  "properties": {
    "iso:country":"US",
    "sg:address":"112 Sunshine Dr",
    "sg:city":"Galt",
    "sg:classifiers":[
        {
            "category":"Manufacturing",
            "subcategory":"Glass & Minerals",
            "type":"Manufacturing & Wholesale Goods"
        }
    ],
    "sg:phone":"+1 209 745 8685",
    "sg:postcode":"95632",
    "sg:province":"CA",
    "sg:tags":[
        "glass-wholesale",
        "shape",
        "circle",
        "special",
        "manufacturer"
    ],
    "wof:name":"Davis Auto Glass",
    "wof:placetype":"venue"
},
  "geometry": {"coordinates":[-121.312123,38.261182],"type":"Point"}
}