{
  "type": "Feature",
  "properties": {
    "iso:country":"US",
    "sg:address":"4826 Whittier Blvd",
    "sg:city":"Los Angeles",
    "sg:classifiers":[
        {
            "category":"Professional",
            "subcategory":"Accounting & Tax Preparation",
            "type":"Services"
        }
    ],
    "sg:phone":"+1 323 267 0312",
    "sg:postcode":"90022",
    "sg:province":"CA",
    "sg:tags":[
        "return",
        "filing"
    ],
    "wof:name":"Arminda's Incometax Svc",
    "wof:placetype":"venue"
},
  "geometry": {"coordinates":[-118.163662,34.021665],"type":"Point"}
}