{
  "type": "Feature",
  "properties": {
    "addr:full":"1826 W Willow St Long Beach CA 90810",
    "addr:housenumber":"1826",
    "addr:postcode":"90810",
    "addr:street":"W Willow St",
    "iso:country":"US",
    "sg:address":"1826 W Willow St",
    "sg:city":"Long Beach",
    "sg:classifiers":[
        {
            "category":"Building & Trades",
            "subcategory":"Construction",
            "type":"Services"
        }
    ],
    "sg:phone":"+1 562 988 8786",
    "sg:postcode":"90810",
    "sg:province":"CA",
    "sg:tags":[
        "contractor"
    ],
    "wof:name":"G H Construction",
    "wof:placetype":"venue"
},
  "geometry": {"coordinates":[-118.217371,33.804301],"type":"Point"}
}