{
  "type": "Feature",
  "properties": {
    "addr:full":"381 Columbia Cir Benicia CA 94510",
    "addr:housenumber":"381",
    "addr:postcode":"94510",
    "addr:street":"Columbia Cir",
    "iso:country":"US",
    "sg:address":"381 Columbia Cir",
    "sg:city":"Benicia",
    "sg:classifiers":[
        {
            "category":"Professional",
            "subcategory":"Advertising",
            "type":"Services"
        }
    ],
    "sg:phone":"+1 707 747 6988",
    "sg:postcode":"94510",
    "sg:province":"CA",
    "sg:tags":[
        "mail"
    ],
    "wof:name":"Schofield Systems",
    "wof:placetype":"venue"
},
  "geometry": {"coordinates":[-122.15209900000001,38.079421],"type":"Point"}
}