{
  "type": "Feature",
  "properties": {
    "iso:country":"US",
    "sg:address":"25411 Hawkwood Trl",
    "sg:city":"Moreno Valley",
    "sg:classifiers":[
        {
            "category":"Real Estate",
            "subcategory":"Real Estate Operator",
            "type":"Services"
        }
    ],
    "sg:phone":"+1 951 242 7435",
    "sg:postcode":"92557",
    "sg:province":"CA",
    "sg:tags":[
        "apartment"
    ],
    "wof:name":"Glory Apartment",
    "wof:placetype":"venue"
},
  "geometry": {"coordinates":[-117.21901,33.946096],"type":"Point"}
}