{
  "type": "Feature",
  "properties": {
    "iso:country":"US",
    "sg:address":"15940 Peach Tree Ln",
    "sg:city":"Fontana",
    "sg:classifiers":[
        {
            "category":"Freight",
            "type":"Transportation"
        }
    ],
    "sg:phone":"+1 909 574 8996",
    "sg:postcode":"92337",
    "sg:province":"CA",
    "sg:tags":[
        "trucking"
    ],
    "wof:name":"Cushing Trucking Co",
    "wof:placetype":"venue"
},
  "geometry": {"coordinates":[-117.456682,34.045664],"type":"Point"}
}