{
  "type": "Feature",
  "properties": {
    "addr:full":"12451 US Hwy 101 Smith River CA 95567",
    "addr:housenumber":"12451",
    "addr:postcode":"95567",
    "addr:street":"Us Hwy 101 Smith",
    "iso:country":"US",
    "sg:address":"12451 US Hwy 101",
    "sg:city":"Smith River",
    "sg:classifiers":[
        {
            "category":"Restaurant",
            "type":"Food & Drink"
        }
    ],
    "sg:phone":"+1 707 487 4504",
    "sg:postcode":"95567",
    "sg:province":"CA",
    "wof:name":"Dj's Restaurant",
    "wof:placetype":"venue"
},
  "geometry": {"coordinates":[-124.194909,41.946535],"type":"Point"}
}