{
  "type": "Feature",
  "properties": {
    "addr:full":"2254 Sunrise Blvd Gold River CA 95670",
    "addr:housenumber":"2254",
    "addr:postcode":"95670",
    "addr:street":"Sunrise Blvd",
    "iso:country":"US",
    "sg:address":"2254 Sunrise Blvd",
    "sg:city":"Gold River",
    "sg:classifiers":[
        {
            "category":"Personal",
            "subcategory":"Beauty Salon",
            "type":"Services"
        }
    ],
    "sg:phone":"+1 916 635 4252",
    "sg:postcode":"95670",
    "sg:province":"CA",
    "wof:name":"Mimi Hair Salon",
    "wof:placetype":"venue"
},
  "geometry": {"coordinates":[-121.268095,38.618903],"type":"Point"}
}