{
  "type": "Feature",
  "properties": {
    "iso:country":"US",
    "sg:address":"7601 Redwood Dr",
    "sg:city":"Cotati",
    "sg:classifiers":[
        {
            "category":"Building & Trades",
            "subcategory":"Plumbing",
            "type":"Services"
        }
    ],
    "sg:phone":"+1 707 795 2236",
    "sg:postcode":"94931",
    "sg:province":"CA",
    "sg:tags":[
        "conditioning",
        "air",
        "system",
        "contractor"
    ],
    "wof:name":"Pacific Heating & Air Cond",
    "wof:placetype":"venue"
},
  "geometry": {"coordinates":[-122.71324,38.337057],"type":"Point"}
}