{
  "type": "Feature",
  "properties": {
    "iso:country":"US",
    "sg:address":"264 Crystal Springs Rd",
    "sg:city":"Saint Helena",
    "sg:classifiers":[
        {
            "category":"Winery",
            "type":"Food & Drink"
        }
    ],
    "sg:phone":"+1 707 963 7760",
    "sg:postcode":"94574",
    "sg:province":"CA",
    "wof:name":"Stoney Springs Winery",
    "wof:placetype":"venue"
},
  "geometry": {"coordinates":[-122.49700199999999,38.554699],"type":"Point"}
}