{
  "type": "Feature",
  "properties": {
    "addr:full":"2011 Westcliff Drive Suite 5 Newport Beach CA 92660",
    "addr:housenumber":"2011",
    "addr:postcode":"92660",
    "addr:street":"Westcliff Drive Suite 5",
    "iso:country":"US",
    "sg:address":"2011 Westcliff Drive Suite 5",
    "sg:city":"Newport Beach",
    "sg:classifiers":[
        {
            "category":"Health Services",
            "subcategory":"Doctor",
            "type":"Services"
        }
    ],
    "sg:phone":"+1 949 645 2520",
    "sg:postcode":"92660",
    "sg:province":"CA",
    "wof:name":"Owsley William J MD",
    "wof:placetype":"venue"
},
  "geometry": {"coordinates":[-117.90743500000001,33.627464],"type":"Point"}
}