{
  "type": "Feature",
  "properties": {
    "addr:full":"2747 Aiello Dr San Jose CA 95111",
    "addr:housenumber":"2747",
    "addr:postcode":"95111",
    "addr:street":"Aiello Dr",
    "iso:country":"US",
    "sg:address":"2747 Aiello Dr",
    "sg:city":"San Jose",
    "sg:classifiers":[
        {
            "category":"Building & Trades",
            "subcategory":"Construction",
            "type":"Services"
        }
    ],
    "sg:phone":"+1 408 274 6131",
    "sg:postcode":"95111",
    "sg:province":"CA",
    "sg:tags":[
        "concrete",
        "contractor"
    ],
    "wof:name":"Sanchez Concrete Construction",
    "wof:placetype":"venue"
},
  "geometry": {"coordinates":[-121.849045,37.295265],"type":"Point"}
}