{
  "type": "Feature",
  "properties": {
    "addr:full":"6780 Miramar Rd San Diego CA 92121",
    "addr:housenumber":"6780",
    "addr:postcode":"92121",
    "addr:street":"Miramar Rd",
    "iso:country":"US",
    "sg:address":"6780 Miramar Rd",
    "sg:city":"San Diego",
    "sg:classifiers":[
        {
            "category":"Wholesale",
            "subcategory":"Computers",
            "type":"Manufacturing & Wholesale Goods"
        }
    ],
    "sg:phone":"+1 619 423 8060",
    "sg:postcode":"92121",
    "sg:province":"CA",
    "sg:tags":[
        "equipment"
    ],
    "wof:name":"Quaser Corporation",
    "wof:placetype":"venue"
},
  "geometry": {"coordinates":[-117.168544,32.878172],"type":"Point"}
}