{
  "type": "Feature",
  "properties": {
    "iso:country":"US",
    "sg:address":"13176 Mapleview St",
    "sg:city":"Lakeside",
    "sg:classifiers":[
        {
            "category":"Organizations",
            "subcategory":"Religious Organization",
            "type":"Services"
        }
    ],
    "sg:phone":"+1 619 443 6467",
    "sg:postcode":"92040",
    "sg:province":"CA",
    "sg:tags":[
        "church"
    ],
    "sg:website":"www.mapleview-church.com",
    "wof:name":"Mapleview Baptist Church",
    "wof:placetype":"venue"
},
  "geometry": {"coordinates":[-116.905725,32.865195],"type":"Point"}
}