{
  "type": "Feature",
  "properties": {
    "iso:country":"US",
    "sg:address":"8165 Melrose Ave",
    "sg:city":"Los Angeles",
    "sg:classifiers":[
        {
            "category":"Autos & Motor Vehicles",
            "subcategory":"Auto Supplies",
            "type":"Retail Goods"
        }
    ],
    "sg:phone":"+1 323 653 7400",
    "sg:postcode":"90046",
    "sg:province":"CA",
    "sg:tags":[
        "tire"
    ],
    "wof:name":"West Hollywood Auto & Tires",
    "wof:placetype":"venue"
},
  "geometry": {"coordinates":[-118.367743,34.083795],"type":"Point"}
}