{
  "type": "Feature",
  "properties": {
    "iso:country":"US",
    "sg:address":"1850 Massachusetts Ave",
    "sg:city":"Riverside",
    "sg:classifiers":[
        {
            "category":"Professional",
            "subcategory":"Business Services",
            "type":"Services"
        }
    ],
    "sg:phone":"+1 951 781 6800",
    "sg:postcode":"92507",
    "sg:province":"CA",
    "sg:tags":[
        "record",
        "document"
    ],
    "wof:name":"T R Storage Inc",
    "wof:placetype":"venue"
},
  "geometry": {"coordinates":[-117.351314,33.986558],"type":"Point"}
}