{
  "type": "Feature",
  "properties": {
    "iso:country":"US",
    "sg:address":"13092 April Dr",
    "sg:city":"Riverside",
    "sg:classifiers":[
        {
            "category":"Freight",
            "type":"Transportation"
        }
    ],
    "sg:phone":"+1 951 830 3789",
    "sg:postcode":"92503",
    "sg:province":"CA",
    "wof:name":"Ngo Transportation",
    "wof:placetype":"venue"
},
  "geometry": {"coordinates":[-117.507945,33.875624],"type":"Point"}
}