{
  "type": "Feature",
  "properties": {
    "iso:country":"US",
    "sg:address":"710 W Napa St",
    "sg:city":"Sonoma",
    "sg:classifiers":[
        {
            "category":"Professional",
            "type":"Services"
        }
    ],
    "sg:phone":"+1 707 933 8352",
    "sg:postcode":"95476",
    "sg:province":"CA",
    "wof:name":"Tim & Lisa Conner",
    "wof:placetype":"venue"
},
  "geometry": {"coordinates":[-122.47200100000001,38.293377],"type":"Point"}
}