{
  "type": "Feature",
  "properties": {
    "iso:country":"US",
    "sg:address":"1641 Firestone Blvd",
    "sg:city":"Los Angeles",
    "sg:classifiers":[
        {
            "category":"Food & Beverages",
            "subcategory":"Groceries & Convenience Stores",
            "type":"Retail Goods"
        }
    ],
    "sg:phone":"+1 323 588 0559",
    "sg:postcode":"90001",
    "sg:province":"CA",
    "sg:tags":[
        "grocer"
    ],
    "sg:website":"www.tuslocutores.com",
    "wof:name":"LA Vaquita Meat Market",
    "wof:placetype":"venue"
},
  "geometry": {"coordinates":[-118.244642,33.960222],"type":"Point"}
}