{
  "type": "Feature",
  "properties": {
    "addr:full":"22217 Old Santa Cruz Hwy Los Gatos CA 95033",
    "addr:housenumber":"22217",
    "addr:postcode":"95033",
    "addr:street":"Old Santa Cruz Hwy",
    "iso:country":"US",
    "sg:address":"22217 Old Santa Cruz Hwy",
    "sg:city":"Los Gatos",
    "sg:classifiers":[
        {
            "category":"Home & Garden",
            "subcategory":"Garden Supply",
            "type":"Retail Goods"
        }
    ],
    "sg:phone":"+1 408 353 1615",
    "sg:postcode":"95033",
    "sg:province":"CA",
    "sg:tags":[
        "tree",
        "christmas"
    ],
    "sg:website":"www.patchencalifornia.com",
    "wof:name":"Patchen Calif",
    "wof:placetype":"venue"
},
  "geometry": {"coordinates":[-121.976872,37.1513],"type":"Point"}
}