{
  "type": "Feature",
  "properties": {
    "iso:country":"US",
    "sg:address":"6678 Ave 304",
    "sg:city":"Visalia",
    "sg:classifiers":[
        {
            "category":"Retail",
            "subcategory":"Repair Shop",
            "type":"Services"
        }
    ],
    "sg:phone":"+1 559 651 1601",
    "sg:postcode":"93291",
    "sg:province":"CA",
    "sg:tags":[
        "equipment",
        "conditioning",
        "air"
    ],
    "wof:name":"Ram Air Conditioning",
    "wof:placetype":"venue"
},
  "geometry": {"coordinates":[-119.426811,36.341757],"type":"Point"}
}