{
  "type": "Feature",
  "properties": {
    "iso:country":"US",
    "sg:address":"1287 Oliver Rd",
    "sg:city":"Fairfield",
    "sg:classifiers":[
        {
            "category":"Health Services",
            "subcategory":"Health Practitioner",
            "type":"Services"
        }
    ],
    "sg:phone":"+1 707 426 4327",
    "sg:postcode":"94534",
    "sg:province":"CA",
    "sg:tags":[
        "audiologists"
    ],
    "wof:name":"Ellen Anderson Hearing Svc",
    "wof:placetype":"venue"
},
  "geometry": {"coordinates":[-122.067524,38.255855],"type":"Point"}
}