{
  "type": "Feature",
  "properties": {
    "iso:country":"US",
    "sg:address":"865 Market St",
    "sg:city":"San Francisco",
    "sg:classifiers":[
        {
            "category":"Shopping",
            "subcategory":"Gifts & Souvenirs",
            "type":"Retail Goods"
        }
    ],
    "sg:phone":"+1 415 546 6667",
    "sg:postcode":"94103",
    "sg:province":"CA",
    "sg:tags":[
        "shop"
    ],
    "wof:name":"Brookstone Inc",
    "wof:placetype":"venue"
},
  "geometry": {"coordinates":[-122.406229,37.785476],"type":"Point"}
}