{
  "type": "Feature",
  "properties": {
    "addr:full":"1409 Sandy Ct Modesto CA 95355",
    "addr:housenumber":"1409",
    "addr:postcode":"ca 95355",
    "addr:street":"Sandy Ct",
    "iso:country":"US",
    "sg:address":"1409 Sandy Ct",
    "sg:city":"Modesto",
    "sg:classifiers":[
        {
            "category":"Professional",
            "subcategory":"Management & Consulting",
            "type":"Services"
        }
    ],
    "sg:phone":"+1 209 571 1175",
    "sg:postcode":"95355",
    "sg:province":"CA",
    "sg:tags":[
        "retail",
        "direct",
        "sales"
    ],
    "wof:name":"Ves Catalina Rau",
    "wof:placetype":"venue"
},
  "geometry": {"coordinates":[-120.922668,37.664345],"type":"Point"}
}