{
  "type": "Feature",
  "properties": {
    "addr:full":"308 Baldwin Ave San Mateo CA 94401",
    "addr:housenumber":"308",
    "addr:postcode":"94401",
    "addr:street":"Baldwin Ave",
    "iso:country":"US",
    "sg:address":"308 Baldwin Ave",
    "sg:city":"San Mateo",
    "sg:classifiers":[
        {
            "category":"Personal",
            "subcategory":"Beauty Salon",
            "type":"Services"
        }
    ],
    "sg:phone":"+1 650 347 1677",
    "sg:postcode":"94401",
    "sg:province":"CA",
    "sg:tags":[
        "care",
        "skin"
    ],
    "wof:name":"Janet Apour Skin Care",
    "wof:placetype":"venue"
},
  "geometry": {"coordinates":[-122.324997,37.567402],"type":"Point"}
}