{
  "type": "Feature",
  "properties": {
    "addr:full":"6565 Edna Rd San Luis Obispo CA 93401",
    "addr:housenumber":"6565",
    "addr:postcode":"93401",
    "addr:street":"Edna Rd",
    "iso:country":"US",
    "sg:address":"6565 Edna Rd",
    "sg:city":"San Luis Obispo",
    "sg:classifiers":[
        {
            "category":"Professional",
            "type":"Services"
        }
    ],
    "sg:phone":"+1 805 543 9860",
    "sg:postcode":"93401",
    "sg:province":"CA",
    "sg:tags":[
        "establishment"
    ],
    "wof:name":"Phss Inc",
    "wof:placetype":"venue"
},
  "geometry": {"coordinates":[-120.610134,35.20119],"type":"Point"}
}