{
  "type": "Feature",
  "properties": {
    "iso:country":"US",
    "sg:address":"3652 Eastham Dr",
    "sg:city":"Culver City",
    "sg:classifiers":[
        {
            "category":"Manufacturing",
            "subcategory":"Printing",
            "type":"Manufacturing & Wholesale Goods"
        }
    ],
    "sg:phone":"+1 310 287 0162",
    "sg:postcode":"90232",
    "sg:province":"CA",
    "sg:tags":[
        "lithographic",
        "commercial"
    ],
    "wof:name":"S & P Printers",
    "wof:placetype":"venue"
},
  "geometry": {"coordinates":[-118.378964,34.02241],"type":"Point"}
}