{
  "type": "Feature",
  "properties": {
    "iso:country":"US",
    "sg:address":"911 Ream Ave",
    "sg:city":"Mt Shasta",
    "sg:classifiers":[
        {
            "category":"Freight",
            "type":"Transportation"
        }
    ],
    "sg:phone":"+1 530 926 3088",
    "sg:postcode":"96067",
    "sg:province":"CA",
    "sg:tags":[
        "warehouse",
        "self",
        "storage"
    ],
    "wof:name":"Ream Ave Mini Storage",
    "wof:placetype":"venue"
},
  "geometry": {"coordinates":[-122.311096,41.305207],"type":"Point"}
}