{
  "type": "Feature",
  "properties": {
    "addr:full":"3700 Thomas Rd Ste 103 Santa Clara CA 95054",
    "addr:housenumber":"3700",
    "addr:postcode":"95054",
    "addr:street":"Thomas Rd Ste 103",
    "iso:country":"US",
    "sg:address":"3700 Thomas Rd Ste 103",
    "sg:city":"Santa Clara",
    "sg:classifiers":[
        {
            "category":"Food & Beverages",
            "subcategory":"Bakery",
            "type":"Retail Goods"
        }
    ],
    "sg:phone":"+1 408 748 0080",
    "sg:postcode":"95054",
    "sg:province":"CA",
    "sg:tags":[
        "sandwich"
    ],
    "sg:website":"www.subway.com",
    "wof:name":"Subway",
    "wof:placetype":"venue"
},
  "geometry": {"coordinates":[-121.960093,37.386012],"type":"Point"}
}