{
  "type": "Feature",
  "properties": {
    "addr:full":"1081 Camino Del Rio S San Diego CA 92108",
    "addr:housenumber":"1081",
    "addr:postcode":"92108",
    "addr:street":"Camino Del Rio S",
    "iso:country":"US",
    "sg:address":"1081 Camino Del Rio S",
    "sg:city":"San Diego",
    "sg:classifiers":[
        {
            "category":"Casinos & Gambling",
            "type":"Entertainment"
        }
    ],
    "sg:phone":"+1 619 764 5322",
    "sg:postcode":"92108",
    "sg:province":"CA",
    "wof:name":"Casino Essentials",
    "wof:placetype":"venue"
},
  "geometry": {"coordinates":[-117.153848,32.764326],"type":"Point"}
}