{
  "type": "Feature",
  "properties": {
    "iso:country":"US",
    "sg:address":"21515 Hawthorne Blvd",
    "sg:city":"Torrance",
    "sg:classifiers":[
        {
            "category":"Education",
            "subcategory":"Special Training",
            "type":"Public Place"
        }
    ],
    "sg:phone":"+1 310 792 7270",
    "sg:postcode":"90503",
    "sg:province":"CA",
    "sg:tags":[
        "school",
        "language"
    ],
    "wof:name":"Geos English Academy",
    "wof:placetype":"venue"
},
  "geometry": {"coordinates":[-118.352579,33.831713],"type":"Point"}
}