{
  "type": "Feature",
  "properties": {
    "iso:country":"US",
    "sg:address":"2231 Fargo St",
    "sg:city":"Los Angeles",
    "sg:classifiers":[
        {
            "category":"Building & Trades",
            "subcategory":"Construction",
            "type":"Services"
        }
    ],
    "sg:phone":"+1 323 644 7642",
    "sg:postcode":"90039",
    "sg:province":"CA",
    "sg:tags":[
        "designer",
        "dealer",
        "pool",
        "swimming"
    ],
    "wof:name":"Total Swimming Pool",
    "wof:placetype":"venue"
},
  "geometry": {"coordinates":[-118.260225,34.092665],"type":"Point"}
}