{
  "type": "Feature",
  "properties": {
    "iso:country":"US",
    "sg:address":"125 Old Grove Rd Ste 9",
    "sg:city":"Oceanside",
    "sg:classifiers":[
        {
            "category":"Building & Trades",
            "subcategory":"Construction",
            "type":"Services"
        }
    ],
    "sg:phone":"+1 760 277 4866",
    "sg:postcode":"92057",
    "sg:province":"CA",
    "sg:tags":[
        "consultant",
        "management"
    ],
    "wof:name":"Tower Development Services",
    "wof:placetype":"venue"
},
  "geometry": {"coordinates":[-117.306586,33.229843],"type":"Point"}
}