{
  "type": "Feature",
  "properties": {
    "addr:full":"2601 Ec Reems Ct Oakland CA 94605",
    "addr:postcode":"2601 ec;94605",
    "addr:street":"Reems Ct",
    "iso:country":"US",
    "sg:address":"2601 Ec Reems Ct",
    "sg:city":"Oakland",
    "sg:classifiers":[
        {
            "category":"Organizations",
            "subcategory":"Religious Organization",
            "type":"Services"
        }
    ],
    "sg:phone":"+1 510 633 5130",
    "sg:postcode":"94605",
    "sg:province":"CA",
    "sg:tags":[
        "church"
    ],
    "wof:name":"Center-Hope Comm Chr",
    "wof:placetype":"venue"
},
  "geometry": {"coordinates":[-122.163363,37.761032],"type":"Point"}
}