{
  "type": "Feature",
  "properties": {
    "addr:full":"813 A St San Rafael CA 94901",
    "addr:housenumber":"813",
    "addr:postcode":"94901",
    "addr:street":"A St",
    "iso:country":"US",
    "sg:address":"813 A St",
    "sg:city":"San Rafael",
    "sg:classifiers":[
        {
            "category":"Wholesale",
            "subcategory":"Non-durable Goods",
            "type":"Manufacturing & Wholesale Goods"
        }
    ],
    "sg:phone":"+1 415 453 3626",
    "sg:postcode":"94901",
    "sg:province":"CA",
    "sg:tags":[
        "rubber",
        "sponge"
    ],
    "wof:name":"Foam Store",
    "wof:placetype":"venue"
},
  "geometry": {"coordinates":[-122.52846700000001,37.972052],"type":"Point"}
}