{
  "type": "Feature",
  "properties": {
    "addr:full":"1589 W Shaw Ave Fresno CA 93711",
    "addr:housenumber":"1589",
    "addr:postcode":"93711",
    "addr:street":"W Shaw Ave",
    "iso:country":"US",
    "sg:address":"1589 W Shaw Ave",
    "sg:city":"Fresno",
    "sg:classifiers":[
        {
            "category":"Shopping",
            "subcategory":"Computers & Home Electronics",
            "type":"Retail Goods"
        }
    ],
    "sg:phone":"+1 559 227 2600",
    "sg:postcode":"93711",
    "sg:province":"CA",
    "sg:tags":[
        "equipment",
        "dealer"
    ],
    "wof:name":"Creative Computers Plus",
    "wof:placetype":"venue"
},
  "geometry": {"coordinates":[-119.820139,36.808242],"type":"Point"}
}