{
  "type": "Feature",
  "properties": {
    "iso:country":"US",
    "sg:address":"6218 E Pacific Coast Hwy",
    "sg:city":"Long Beach",
    "sg:classifiers":[
        {
            "category":"Food & Beverages",
            "subcategory":"Bakery",
            "type":"Retail Goods"
        }
    ],
    "sg:phone":"+1 562 498 3928",
    "sg:postcode":"90803",
    "sg:province":"CA",
    "sg:tags":[
        "baker"
    ],
    "wof:name":"Linden Bakery",
    "wof:placetype":"venue"
},
  "geometry": {"coordinates":[-118.115997,33.764931],"type":"Point"}
}