{
  "type": "Feature",
  "properties": {
    "addr:full":"10113 Riverside Dr Toluca Lake CA 91602",
    "addr:housenumber":"10113",
    "addr:postcode":"91602",
    "addr:street":"Riverside Dr",
    "iso:country":"US",
    "sg:address":"10113 Riverside Dr",
    "sg:city":"Toluca Lake",
    "sg:classifiers":[
        {
            "category":"Shopping",
            "type":"Retail Goods"
        }
    ],
    "sg:phone":"+1 818 761 6397",
    "sg:postcode":"91602",
    "sg:province":"CA",
    "sg:tags":[
        "coin",
        "jewelry",
        "supply"
    ],
    "wof:name":"Gabrelow & Albarian",
    "wof:placetype":"venue"
},
  "geometry": {"coordinates":[-118.350998,34.1521],"type":"Point"}
}