{
  "type": "Feature",
  "properties": {
    "iso:country":"US",
    "sg:address":"821 Oregon St",
    "sg:city":"Bakersfield",
    "sg:classifiers":[
        {
            "category":"Building & Trades",
            "subcategory":"Electrical",
            "type":"Services"
        }
    ],
    "sg:phone":"+1 661 326 1275",
    "sg:postcode":"93305",
    "sg:province":"CA",
    "sg:tags":[
        "electric",
        "contractor"
    ],
    "wof:name":"Nu Electric",
    "wof:placetype":"venue"
},
  "geometry": {"coordinates":[-118.987843,35.382336],"type":"Point"}
}