{
  "type": "Feature",
  "properties": {
    "iso:country":"US",
    "sg:address":"242 Bingham Dr",
    "sg:city":"San Marcos",
    "sg:classifiers":[
        {
            "category":"Wholesale",
            "subcategory":"Groceries",
            "type":"Manufacturing & Wholesale Goods"
        }
    ],
    "sg:phone":"+1 760 744 4495",
    "sg:postcode":"92069",
    "sg:province":"CA",
    "sg:tags":[
        "food"
    ],
    "wof:name":"Great Spice Company The",
    "wof:placetype":"venue"
},
  "geometry": {"coordinates":[-117.184079,33.145097],"type":"Point"}
}