{
  "type": "Feature",
  "properties": {
    "addr:full":"1422 Franklin St Santa Clara CA 95050",
    "addr:housenumber":"1422",
    "addr:postcode":"95050",
    "addr:street":"Franklin St",
    "iso:country":"US",
    "sg:address":"1422 Franklin St",
    "sg:city":"Santa Clara",
    "sg:classifiers":[
        {
            "category":"Personal",
            "subcategory":"Beauty Salon",
            "type":"Services"
        }
    ],
    "sg:phone":"+1 408 984 3303",
    "sg:postcode":"95050",
    "sg:province":"CA",
    "wof:name":"Hair & Nails",
    "wof:placetype":"venue"
},
  "geometry": {"coordinates":[-121.950152,37.347672],"type":"Point"}
}