{
  "type": "Feature",
  "properties": {
    "iso:country":"US",
    "sg:address":"4200 Birch Street",
    "sg:city":"Newport Beach",
    "sg:classifiers":[
        {
            "category":"Retail",
            "subcategory":"Auto Repair",
            "type":"Services"
        }
    ],
    "sg:phone":"+1 949 862 7474",
    "sg:postcode":"92660",
    "sg:province":"CA",
    "sg:tags":[
        "detailing"
    ],
    "sg:website":"www.stevesdetailingoc.com",
    "wof:name":"Steve's Detailing",
    "wof:placetype":"venue"
},
  "geometry": {"coordinates":[-117.86806,33.666341],"type":"Point"}
}