{
  "type": "Feature",
  "properties": {
    "iso:country":"US",
    "sg:address":"1605 S Main St",
    "sg:city":"Lakeport",
    "sg:classifiers":[
        {
            "category":"Personal",
            "subcategory":"Beauty Salon",
            "type":"Services"
        }
    ],
    "sg:phone":"+1 707 262 1332",
    "sg:postcode":"95453",
    "sg:province":"CA",
    "wof:name":"Great Hair Salon",
    "wof:placetype":"venue"
},
  "geometry": {"coordinates":[-122.916031,39.032303],"type":"Point"}
}