{
  "type": "Feature",
  "properties": {
    "addr:full":"5396 Ent Olmos San Jose CA 95123",
    "addr:housenumber":"5396;olmos",
    "addr:postcode":"95123",
    "addr:street":"Ent",
    "iso:country":"US",
    "sg:address":"5396 Ent Olmos",
    "sg:city":"San Jose",
    "sg:classifiers":[
        {
            "category":"Professional",
            "type":"Services"
        },
        {
            "category":"Wholesale",
            "subcategory":"Durable Goods & Equipment",
            "type":"Manufacturing & Wholesale Goods"
        }
    ],
    "sg:phone":"+1 408 365 9693",
    "sg:postcode":"95123",
    "sg:province":"CA",
    "wof:name":"Carlstrom's Service & Supply",
    "wof:placetype":"venue"
},
  "geometry": {"coordinates":[-121.839454,37.255728],"type":"Point"}
}