{
  "type": "Feature",
  "properties": {
    "iso:country":"US",
    "sg:address":"1115 Underhills Rd",
    "sg:city":"Oakland",
    "sg:classifiers":[
        {
            "category":"Professional",
            "type":"Services"
        }
    ],
    "sg:phone":"+1 510 268 4947",
    "sg:postcode":"94610",
    "sg:province":"CA",
    "wof:name":"Colorful Penguin",
    "wof:placetype":"venue"
},
  "geometry": {"coordinates":[-122.22929,37.808087],"type":"Point"}
}