{
  "type": "Feature",
  "properties": {
    "addr:full":"1730 Sepulveda Blvd Ste 4 Torrance CA 90501",
    "addr:housenumber":"1730",
    "addr:postcode":"90501",
    "addr:street":"Sepulveda Blvd Ste 4",
    "iso:country":"US",
    "sg:address":"1730 Sepulveda Blvd Ste 4",
    "sg:city":"Torrance",
    "sg:classifiers":[
        {
            "category":"Shopping",
            "subcategory":"Bridal",
            "type":"Retail Goods"
        }
    ],
    "sg:phone":"+1 310 530 4008",
    "sg:postcode":"90501",
    "sg:province":"CA",
    "wof:name":"House of Brides & Tuxedo",
    "wof:placetype":"venue"
},
  "geometry": {"coordinates":[-118.30953100000001,33.816595],"type":"Point"}
}