{
  "type": "Feature",
  "properties": {
    "iso:country":"US",
    "sg:address":"1658 W 11th St",
    "sg:city":"Upland",
    "sg:classifiers":[
        {
            "category":"Retail",
            "subcategory":"Auto Repair",
            "type":"Services"
        }
    ],
    "sg:phone":"+1 909 981 2637",
    "sg:postcode":"91786",
    "sg:province":"CA",
    "sg:tags":[
        "brake"
    ],
    "wof:name":"Mobile Brake & Clutch Speciali",
    "wof:placetype":"venue"
},
  "geometry": {"coordinates":[-117.682179,34.103262],"type":"Point"}
}