{
  "type": "Feature",
  "properties": {
    "addr:full":"12820 S Pioneer Blvd La Mirada CA 90638",
    "addr:housenumber":"12820",
    "addr:postcode":"90638",
    "addr:street":"S Pioneer Blvd",
    "iso:country":"US",
    "sg:address":"12820 S Pioneer Blvd",
    "sg:city":"La Mirada",
    "sg:classifiers":[
        {
            "category":"Education",
            "subcategory":"School",
            "type":"Public Place"
        }
    ],
    "sg:phone":"+1 562 868 0431",
    "sg:postcode":"90638",
    "sg:province":"CA",
    "sg:tags":[
        "high",
        "middle",
        "elementary"
    ],
    "wof:name":"La Mirada High School",
    "wof:placetype":"venue"
},
  "geometry": {"coordinates":[-118.003998,33.902],"type":"Point"}
}