{
  "type": "Feature",
  "properties": {
    "addr:full":"5605 Woodman Ave Van Nuys CA 91401",
    "addr:housenumber":"5605",
    "addr:postcode":"91401",
    "addr:street":"Woodman Ave",
    "iso:country":"US",
    "sg:address":"5605 Woodman Ave",
    "sg:city":"Van Nuys",
    "sg:classifiers":[
        {
            "category":"Insurance",
            "subcategory":"Insurance Agent",
            "type":"Services"
        }
    ],
    "sg:phone":"+1 818 988 4222",
    "sg:postcode":"91401",
    "sg:province":"CA",
    "wof:name":"HLP Insurance",
    "wof:placetype":"venue"
},
  "geometry": {"coordinates":[-118.43131700000001,34.173865],"type":"Point"}
}