{
  "type": "Feature",
  "properties": {
    "addr:full":"2314 Tripaldi Way Hayward CA 94545",
    "addr:housenumber":"2314",
    "addr:postcode":"94545",
    "addr:street":"Tripaldi Way",
    "iso:country":"US",
    "sg:address":"2314 Tripaldi Way",
    "sg:city":"Hayward",
    "sg:classifiers":[
        {
            "category":"Home & Garden",
            "subcategory":"Carpets & Floor Coverings",
            "type":"Retail Goods"
        }
    ],
    "sg:phone":"+1 415 552 5050",
    "sg:postcode":"94545",
    "sg:province":"CA",
    "sg:tags":[
        "rug",
        "carpeting"
    ],
    "wof:name":"Metropolitan Interiors",
    "wof:placetype":"venue"
},
  "geometry": {"coordinates":[-122.083,37.614601],"type":"Point"}
}