{
  "type": "Feature",
  "properties": {
    "iso:country":"US",
    "sg:address":"21600 Bloomfield Ave",
    "sg:city":"Hawaiian Gardens",
    "sg:classifiers":[
        {
            "category":"Real Estate",
            "subcategory":"Real Estate Operator",
            "type":"Services"
        }
    ],
    "sg:phone":"+1 562 860 9260",
    "sg:postcode":"90716",
    "sg:province":"CA",
    "sg:tags":[
        "apartment"
    ],
    "wof:name":"Cypress Garden Villas",
    "wof:placetype":"venue"
},
  "geometry": {"coordinates":[-118.063004,33.832699],"type":"Point"}
}