{
  "type": "Feature",
  "properties": {
    "addr:full":"1000 Sunrise Ave Roseville CA 95661",
    "addr:housenumber":"1000",
    "addr:postcode":"95661",
    "addr:street":"Sunrise Ave",
    "iso:country":"US",
    "sg:address":"1000 Sunrise Ave",
    "sg:city":"Roseville",
    "sg:classifiers":[
        {
            "category":"Professional",
            "subcategory":"Advertising",
            "type":"Services"
        }
    ],
    "sg:phone":"+1 916 786 5700",
    "sg:postcode":"95661",
    "sg:province":"CA",
    "sg:tags":[
        "mailing",
        "shipping"
    ],
    "wof:name":"It's In The Mail",
    "wof:placetype":"venue"
},
  "geometry": {"coordinates":[-121.272069,38.727157],"type":"Point"}
}