{
  "type": "Feature",
  "properties": {
    "addr:full":"2704 Barcelona Rd Pismo Beach CA 93449",
    "addr:housenumber":"2704",
    "addr:postcode":"93449",
    "addr:street":"Barcelona Rd",
    "iso:country":"US",
    "sg:address":"2704 Barcelona Rd",
    "sg:city":"Pismo Beach",
    "sg:classifiers":[
        {
            "category":"Professional",
            "subcategory":"Computer Services",
            "type":"Services"
        }
    ],
    "sg:phone":"+1 951 343 3438",
    "sg:postcode":"93449",
    "sg:province":"CA",
    "sg:tags":[
        "repair"
    ],
    "wof:name":"Computer Medic",
    "wof:placetype":"venue"
},
  "geometry": {"coordinates":[-120.684679,35.163509],"type":"Point"}
}