{
  "type": "Feature",
  "properties": {
    "addr:full":"416 N Santa Fe St Santa Ana CA 92701",
    "addr:housenumber":"416",
    "addr:postcode":"92701",
    "addr:street":"N Santa Fe St",
    "iso:country":"US",
    "sg:address":"416 N Santa Fe St",
    "sg:city":"Santa Ana",
    "sg:classifiers":[
        {
            "category":"Wholesale",
            "subcategory":"Machinery & Supplies",
            "type":"Manufacturing & Wholesale Goods"
        }
    ],
    "sg:phone":"+1 714 543 0676",
    "sg:postcode":"92701",
    "sg:province":"CA",
    "sg:tags":[
        "equipment",
        "dairy"
    ],
    "wof:name":"Rockview Farms",
    "wof:placetype":"venue"
},
  "geometry": {"coordinates":[-117.85393500000001,33.748478],"type":"Point"}
}