{
  "type": "Feature",
  "properties": {
    "addr:full":"2101 Los Angeles Ave Berkeley CA 94707",
    "addr:housenumber":"2101",
    "addr:postcode":"94707",
    "addr:street":"Los Angeles Ave",
    "iso:country":"US",
    "sg:address":"2101 Los Angeles Ave",
    "sg:city":"Berkeley",
    "sg:classifiers":[
        {
            "category":"Retail",
            "subcategory":"Animal Services",
            "type":"Services"
        }
    ],
    "sg:phone":"+1 510 527 6420",
    "sg:postcode":"94707",
    "sg:province":"CA",
    "sg:tags":[
        "pet",
        "boarding",
        "sitting"
    ],
    "wof:name":"Fetch Pet Care Inc",
    "wof:placetype":"venue"
},
  "geometry": {"coordinates":[-122.26769899999999,37.888729],"type":"Point"}
}