{
  "type": "Feature",
  "properties": {
    "addr:full":"4984 Voltaire St San Diego CA 92107",
    "addr:housenumber":"4984",
    "addr:postcode":"92107",
    "addr:street":"Voltaire St",
    "iso:country":"US",
    "sg:address":"4984 Voltaire St",
    "sg:city":"San Diego",
    "sg:classifiers":[
        {
            "category":"Restaurant",
            "type":"Food & Drink"
        }
    ],
    "sg:menulink":"http://www.allmenus.com/ca/san-diego/59756-subway/menu/",
    "sg:phone":"+1 619 226 8559",
    "sg:postcode":"92107",
    "sg:province":"CA",
    "sg:tags":[
        "american",
        "sandwich"
    ],
    "wof:name":"Subway",
    "wof:placetype":"venue"
},
  "geometry": {"coordinates":[-117.246285,32.751797],"type":"Point"}
}