{
  "type": "Feature",
  "properties": {
    "addr:full":"690 S Almaden Avenue San Jose CA 95110",
    "addr:housenumber":"690",
    "addr:postcode":"95110",
    "addr:street":"S Almaden Avenue",
    "iso:country":"US",
    "sg:address":"690 S Almaden Avenue",
    "sg:city":"San Jose",
    "sg:classifiers":[
        {
            "category":"Food & Beverages",
            "subcategory":"Groceries & Convenience Stores",
            "type":"Retail Goods"
        }
    ],
    "sg:phone":"+1 408 286 0399",
    "sg:postcode":"95110",
    "sg:province":"CA",
    "wof:name":"New Almaden Market",
    "wof:placetype":"venue"
},
  "geometry": {"coordinates":[-121.886077,37.323928],"type":"Point"}
}