{
  "type": "Feature",
  "properties": {
    "iso:country":"US",
    "sg:address":"30 College Rd",
    "sg:city":"Watsonville",
    "sg:classifiers":[
        {
            "category":"Building & Trades",
            "subcategory":"Construction",
            "type":"Services"
        }
    ],
    "sg:phone":"+1 831 359 8175",
    "sg:postcode":"95076",
    "sg:province":"CA",
    "sg:tags":[
        "handyman"
    ],
    "wof:name":"R & M Handiservices",
    "wof:placetype":"venue"
},
  "geometry": {"coordinates":[-121.74126099999999,36.934661],"type":"Point"}
}