{
  "type": "Feature",
  "properties": {
    "addr:full":"5901 Sirl Way Orangevale CA 95662",
    "addr:housenumber":"5901",
    "addr:postcode":"95662",
    "addr:street":"Sirl Way",
    "iso:country":"US",
    "sg:address":"5901 Sirl Way",
    "sg:city":"Orangevale",
    "sg:classifiers":[
        {
            "category":"Building & Trades",
            "subcategory":"Electrical",
            "type":"Services"
        }
    ],
    "sg:phone":"+1 916 990 0536",
    "sg:postcode":"95662",
    "sg:province":"CA",
    "sg:tags":[
        "equipment",
        "electrical",
        "contractor"
    ],
    "wof:name":"Almanor Electric Inc",
    "wof:placetype":"venue"
},
  "geometry": {"coordinates":[-121.207059,38.673989],"type":"Point"}
}