{
  "type": "Feature",
  "properties": {
    "addr:full":"29280 Central Ave Lake Elsinore CA 92532",
    "addr:postcode":"29280;92532",
    "addr:street":"Central Ave",
    "iso:country":"US",
    "sg:address":"29280 Central Ave",
    "sg:city":"Lake Elsinore",
    "sg:classifiers":[
        {
            "category":"Professional",
            "type":"Services"
        }
    ],
    "sg:phone":"+1 951 245 1864",
    "sg:postcode":"92532",
    "sg:province":"CA",
    "sg:tags":[
        "caterer"
    ],
    "wof:name":"Sansui",
    "wof:placetype":"venue"
},
  "geometry": {"coordinates":[-117.33513600000001,33.69399],"type":"Point"}
}