{
  "type": "Feature",
  "properties": {
    "iso:country":"US",
    "sg:address":"402 Canyon Country Rd",
    "sg:city":"Brea",
    "sg:classifiers":[
        {
            "category":"Professional",
            "subcategory":"Detective & Security Services",
            "type":"Services"
        }
    ],
    "sg:phone":"+1 714 257 0007",
    "sg:postcode":"92821",
    "sg:province":"CA",
    "sg:tags":[
        "information",
        "bureau"
    ],
    "wof:name":"Computer Tutor Service",
    "wof:placetype":"venue"
},
  "geometry": {"coordinates":[-117.889488,33.934998],"type":"Point"}
}