{
  "type": "Feature",
  "properties": {
    "iso:country":"US",
    "sg:address":"1011 Folsom Ave",
    "sg:city":"Hayward",
    "sg:classifiers":[
        {
            "category":"Professional",
            "type":"Services"
        }
    ],
    "sg:phone":"+1 510 785 3062",
    "sg:postcode":"94544",
    "sg:province":"CA",
    "wof:name":"Warraich Corp",
    "wof:placetype":"venue"
},
  "geometry": {"coordinates":[-122.069467,37.624919],"type":"Point"}
}