{
  "type": "Feature",
  "properties": {
    "iso:country":"US",
    "sg:address":"24230 Hawthorne Blvd",
    "sg:city":"Torrance",
    "sg:classifiers":[
        {
            "category":"Personal",
            "subcategory":"Beauty Salon",
            "type":"Services"
        }
    ],
    "sg:phone":"+1 310 373 7344",
    "sg:postcode":"90505",
    "sg:province":"CA",
    "wof:name":"Varouj Kioudjian",
    "wof:placetype":"venue"
},
  "geometry": {"coordinates":[-118.35092299999999,33.80375],"type":"Point"}
}