{
  "type": "Feature",
  "properties": {
    "addr:full":"32835 State Hwy 79 S Temecula CA 92592",
    "addr:housenumber":"32835",
    "addr:postcode":"92592",
    "addr:street":"State Hwy 79 S",
    "iso:country":"US",
    "sg:address":"32835 State Hwy 79 S",
    "sg:city":"Temecula",
    "sg:classifiers":[
        {
            "category":"Building & Trades",
            "subcategory":"Construction",
            "type":"Services"
        }
    ],
    "sg:phone":"+1 951 302 2036",
    "sg:postcode":"92592",
    "sg:province":"CA",
    "sg:tags":[
        "general",
        "contractor"
    ],
    "wof:name":"J & P Construction",
    "wof:placetype":"venue"
},
  "geometry": {"coordinates":[-117.079483,33.485842],"type":"Point"}
}