{
  "type": "Feature",
  "properties": {
    "iso:country":"US",
    "sg:address":"260 Topaz St",
    "sg:city":"Redwood City",
    "sg:classifiers":[
        {
            "category":"Building & Trades",
            "subcategory":"Construction",
            "type":"Services"
        }
    ],
    "sg:phone":"+1 650 364 1838",
    "sg:postcode":"94062",
    "sg:province":"CA",
    "sg:tags":[
        "contractor"
    ],
    "wof:name":"K S Construction",
    "wof:placetype":"venue"
},
  "geometry": {"coordinates":[-122.249486,37.473931],"type":"Point"}
}