{
  "type": "Feature",
  "properties": {
    "iso:country":"US",
    "sg:address":"2455 Bennett Valley Rd",
    "sg:city":"Santa Rosa",
    "sg:classifiers":[
        {
            "category":"Real Estate",
            "subcategory":"Real Estate Operator",
            "type":"Services"
        }
    ],
    "sg:phone":"+1 707 576 1200",
    "sg:postcode":"95404",
    "sg:province":"CA",
    "sg:tags":[
        "building",
        "nonresidential"
    ],
    "wof:name":"Waterfall Towers",
    "wof:placetype":"venue"
},
  "geometry": {"coordinates":[-122.687735,38.432791],"type":"Point"}
}