{
  "type": "Feature",
  "properties": {
    "addr:full":"130 Washburn Ave Santa Cruz CA 95060",
    "addr:housenumber":"130",
    "addr:postcode":"95060",
    "addr:street":"Washburn Ave",
    "iso:country":"US",
    "sg:address":"130 Washburn Ave",
    "sg:city":"Santa Cruz",
    "sg:classifiers":[
        {
            "category":"Building & Trades",
            "subcategory":"Construction",
            "type":"Services"
        }
    ],
    "sg:phone":"+1 831 464 1462",
    "sg:postcode":"95060",
    "sg:province":"CA",
    "sg:tags":[
        "general",
        "contractor"
    ],
    "wof:name":"Built To Last Construction",
    "wof:placetype":"venue"
},
  "geometry": {"coordinates":[-122.02131,36.982828],"type":"Point"}
}