{
  "type": "Feature",
  "properties": {
    "addr:full":"3702 Euclid Ave San Diego CA 92105",
    "addr:housenumber":"3702",
    "addr:postcode":"92105",
    "addr:street":"Euclid Ave",
    "iso:country":"US",
    "sg:address":"3702 Euclid Ave",
    "sg:city":"San Diego",
    "sg:classifiers":[
        {
            "category":"Food & Beverages",
            "subcategory":"Groceries & Convenience Stores",
            "type":"Retail Goods"
        }
    ],
    "sg:phone":"+1 619 281 8212",
    "sg:postcode":"92105",
    "sg:province":"CA",
    "sg:tags":[
        "grocer"
    ],
    "wof:name":"Rangelos Market & Produce",
    "wof:placetype":"venue"
},
  "geometry": {"coordinates":[-117.092386,32.746577],"type":"Point"}
}