{
  "type": "Feature",
  "properties": {
    "addr:full":"10706 Weaver Ave South El Monte CA 91733",
    "addr:housenumber":"10706",
    "addr:postcode":"91733",
    "addr:street":"Weaver Ave",
    "iso:country":"US",
    "sg:address":"10706 Weaver Ave",
    "sg:city":"South El Monte",
    "sg:classifiers":[
        {
            "category":"Wholesale",
            "subcategory":"Machinery & Supplies",
            "type":"Manufacturing & Wholesale Goods"
        }
    ],
    "sg:phone":"+1 626 575 6196",
    "sg:postcode":"91733",
    "sg:province":"CA",
    "sg:tags":[
        "equipment",
        "screen",
        "printing"
    ],
    "wof:name":"Majestic Printing",
    "wof:placetype":"venue"
},
  "geometry": {"coordinates":[-118.04079900000001,34.054181],"type":"Point"}
}