{
  "type": "Feature",
  "properties": {
    "addr:full":"800 E Oak Ave Lompoc CA 93436",
    "addr:housenumber":"800",
    "addr:postcode":"93436",
    "addr:street":"E Oak Ave",
    "iso:country":"US",
    "sg:address":"800 E Oak Ave",
    "sg:city":"Lompoc",
    "sg:classifiers":[
        {
            "category":"Real Estate",
            "subcategory":"Real Estate Operator",
            "type":"Services"
        }
    ],
    "sg:phone":"+1 805 736 8342",
    "sg:postcode":"93436",
    "sg:province":"CA",
    "sg:tags":[
        "apartment"
    ],
    "wof:name":"Four Storage",
    "wof:placetype":"venue"
},
  "geometry": {"coordinates":[-120.448868,34.651699],"type":"Point"}
}