{
  "type": "Feature",
  "properties": {
    "iso:country":"US",
    "sg:address":"9010 Reseda Blvd",
    "sg:city":"Northridge",
    "sg:classifiers":[
        {
            "category":"Professional",
            "subcategory":"Research",
            "type":"Services"
        }
    ],
    "sg:phone":"+1 818 993 5500",
    "sg:postcode":"91324",
    "sg:province":"CA",
    "sg:tags":[
        "analysis",
        "market"
    ],
    "wof:name":"LA Research",
    "wof:placetype":"venue"
},
  "geometry": {"coordinates":[-118.536074,34.234501],"type":"Point"}
}