{
  "type": "Feature",
  "properties": {
    "addr:full":"171 S Gulling St Portola CA 96122",
    "addr:housenumber":"171",
    "addr:postcode":"96122",
    "addr:street":"S Gulling St",
    "iso:country":"US",
    "sg:address":"171 S Gulling St",
    "sg:city":"Portola",
    "sg:classifiers":[
        {
            "category":"Organizations",
            "subcategory":"Religious Organization",
            "type":"Services"
        }
    ],
    "sg:phone":"+1 530 832 4334",
    "sg:postcode":"96122",
    "sg:province":"CA",
    "sg:tags":[
        "church"
    ],
    "sg:website":"www.portolastation.com",
    "wof:name":"Portola Station",
    "wof:placetype":"venue"
},
  "geometry": {"coordinates":[-120.466855,39.806736],"type":"Point"}
}