{
  "type": "Feature",
  "properties": {
    "iso:country":"US",
    "sg:address":"4801 Avalon Blvd",
    "sg:city":"Los Angeles",
    "sg:classifiers":[
        {
            "category":"Food & Beverages",
            "subcategory":"Groceries & Convenience Stores",
            "type":"Retail Goods"
        }
    ],
    "sg:phone":"+1 323 234 8966",
    "sg:postcode":"90011",
    "sg:province":"CA",
    "sg:website":"www.leesmarket.com",
    "wof:name":"Lee's Market",
    "wof:placetype":"venue"
},
  "geometry": {"coordinates":[-118.264999,33.999599],"type":"Point"}
}