{
  "type": "Feature",
  "properties": {
    "iso:country":"US",
    "sg:address":"15171 del Amo Ave",
    "sg:city":"Tustin",
    "sg:classifiers":[
        {
            "category":"Freight",
            "type":"Transportation"
        }
    ],
    "sg:phone":"+1 714 247 4940",
    "sg:postcode":"92780",
    "sg:province":"CA",
    "sg:tags":[
        "arrangement"
    ],
    "wof:name":"Casey Transportation Services",
    "wof:placetype":"venue"
},
  "geometry": {"coordinates":[-117.835188,33.721226],"type":"Point"}
}