{
  "type": "Feature",
  "properties": {
    "iso:country":"US",
    "sg:address":"420 E Pico Blvd",
    "sg:city":"Los Angeles",
    "sg:classifiers":[
        {
            "category":"Shopping",
            "subcategory":"Clothing, Apparel, & Fashions",
            "type":"Retail Goods"
        }
    ],
    "sg:phone":"+1 213 746 4989",
    "sg:postcode":"90015",
    "sg:province":"CA",
    "sg:tags":[
        "infant",
        "wear"
    ],
    "wof:name":"It's A Boy",
    "wof:placetype":"venue"
},
  "geometry": {"coordinates":[-118.257029,34.03443],"type":"Point"}
}