{
  "type": "Feature",
  "properties": {
    "iso:country":"US",
    "sg:address":"219 N Central Ave",
    "sg:city":"Glendale",
    "sg:classifiers":[
        {
            "category":"Restaurant",
            "type":"Food & Drink"
        }
    ],
    "sg:phone":"+1 818 242 2722",
    "sg:postcode":"91203",
    "sg:province":"CA",
    "sg:tags":[
        "seafood"
    ],
    "sg:website":"www.clancyscrabbroiler.com/",
    "wof:name":"Clancy's Crab Broiler",
    "wof:placetype":"venue"
},
  "geometry": {"coordinates":[-118.258003,34.148602],"type":"Point"}
}