{
  "type": "Feature",
  "properties": {
    "addr:full":"5586 Mission Rd Bonsall CA 92003",
    "addr:housenumber":"5586",
    "addr:postcode":"92003",
    "addr:street":"Mission Rd",
    "iso:country":"US",
    "sg:address":"5586 Mission Rd",
    "sg:city":"Bonsall",
    "sg:classifiers":[
        {
            "category":"Personal",
            "subcategory":"Tattoo Parlor",
            "type":"Services"
        }
    ],
    "sg:phone":"+1 760 945 0888",
    "sg:postcode":"92003",
    "sg:province":"CA",
    "wof:name":"Body Graphics",
    "wof:placetype":"venue"
},
  "geometry": {"coordinates":[-117.225998,33.289001],"type":"Point"}
}