{
  "type": "Feature",
  "properties": {
    "addr:full":"1375 Blossom Hill Rd San Jose CA 95118",
    "addr:housenumber":"1375",
    "addr:postcode":"95118",
    "addr:street":"Blossom Hill Rd",
    "iso:country":"US",
    "sg:address":"1375 Blossom Hill Rd",
    "sg:city":"San Jose",
    "sg:classifiers":[
        {
            "category":"Health Services",
            "subcategory":"Optometrist",
            "type":"Services"
        }
    ],
    "sg:phone":"+1 408 264 1264",
    "sg:postcode":"95118",
    "sg:province":"CA",
    "wof:name":"Dear Weyland B OD",
    "wof:placetype":"venue"
},
  "geometry": {"coordinates":[-121.889999,37.242802],"type":"Point"}
}