{
  "type": "Feature",
  "properties": {
    "iso:country":"US",
    "sg:address":"15523 E Carrington Dr",
    "sg:city":"La Mirada",
    "sg:classifiers":[
        {
            "category":"Building & Trades",
            "subcategory":"Construction",
            "type":"Services"
        }
    ],
    "sg:phone":"+1 562 696 0339",
    "sg:postcode":"90638",
    "sg:province":"CA",
    "sg:tags":[
        "hanging",
        "contractor"
    ],
    "wof:name":"Color Craft Painting",
    "wof:placetype":"venue"
},
  "geometry": {"coordinates":[-117.999847,33.91113],"type":"Point"}
}