{
  "type": "Feature",
  "properties": {
    "iso:country":"US",
    "sg:address":"1470 N Hundley St",
    "sg:city":"Anaheim",
    "sg:classifiers":[
        {
            "category":"Manufacturing",
            "subcategory":"Printing",
            "type":"Manufacturing & Wholesale Goods"
        }
    ],
    "sg:phone":"+1 714 630 6195",
    "sg:postcode":"92806",
    "sg:province":"CA",
    "sg:tags":[
        "publisher",
        "book",
        "pamphlet"
    ],
    "wof:name":"Findley Reports Inc",
    "wof:placetype":"venue"
},
  "geometry": {"coordinates":[-117.863957,33.861877],"type":"Point"}
}