{
  "type": "Feature",
  "properties": {
    "addr:full":"501 N Gateway Dr Madera CA 93637",
    "addr:housenumber":"501",
    "addr:postcode":"93637",
    "addr:street":"N Gateway Dr",
    "iso:country":"US",
    "sg:address":"501 N Gateway Dr",
    "sg:city":"Madera",
    "sg:classifiers":[
        {
            "category":"Home & Garden",
            "subcategory":"Hardware",
            "type":"Retail Goods"
        }
    ],
    "sg:phone":"+1 559 674 5626",
    "sg:postcode":"93637",
    "sg:province":"CA",
    "sg:website":"www.keithbrown.com",
    "wof:name":"Keith Brown Building Material",
    "wof:placetype":"venue"
},
  "geometry": {"coordinates":[-120.065288,36.965803],"type":"Point"}
}