{
  "type": "Feature",
  "properties": {
    "addr:full":"355 Lakeport Blvd Lakeport CA 95453",
    "addr:housenumber":"355",
    "addr:postcode":"95453",
    "addr:street":"Lakeport Blvd",
    "iso:country":"US",
    "sg:address":"355 Lakeport Blvd",
    "sg:city":"Lakeport",
    "sg:classifiers":[
        {
            "category":"Shopping",
            "subcategory":"Pharmacy",
            "type":"Retail Goods"
        }
    ],
    "sg:phone":"+1 707 263 1328",
    "sg:postcode":"95453",
    "sg:province":"CA",
    "wof:name":"North Lake Medical Pharmacy",
    "wof:placetype":"venue"
},
  "geometry": {"coordinates":[-122.91801700000001,39.034578],"type":"Point"}
}