{
  "type": "Feature",
  "properties": {
    "addr:full":"12570 Lemon Crest Dr Lakeside CA 92040",
    "addr:housenumber":"12570",
    "addr:postcode":"92040",
    "addr:street":"Lemon Crest Dr",
    "iso:country":"US",
    "sg:address":"12570 Lemon Crest Dr",
    "sg:city":"Lakeside",
    "sg:classifiers":[
        {
            "category":"Retail",
            "subcategory":"Repair Shop",
            "type":"Services"
        }
    ],
    "sg:phone":"+1 619 561 6221",
    "sg:postcode":"92040",
    "sg:province":"CA",
    "sg:tags":[
        "leather",
        "good"
    ],
    "wof:name":"Total Leather Care",
    "wof:placetype":"venue"
},
  "geometry": {"coordinates":[-116.921587,32.854747],"type":"Point"}
}