{
  "type": "Feature",
  "properties": {
    "iso:country":"US",
    "sg:address":"2618 Guerneville Rd",
    "sg:city":"Santa Rosa",
    "sg:classifiers":[
        {
            "category":"Personal",
            "type":"Services"
        }
    ],
    "sg:phone":"+1 707 546 6208",
    "sg:postcode":"95401",
    "sg:province":"CA",
    "sg:tags":[
        "electrolysis"
    ],
    "wof:name":"Ageless Skin Care & Electrolgy",
    "wof:placetype":"venue"
},
  "geometry": {"coordinates":[-122.776847,38.452471],"type":"Point"}
}