{
  "type": "Feature",
  "properties": {
    "addr:full":"22 Hetfield Pl Moraga CA 94556",
    "addr:housenumber":"22",
    "addr:postcode":"94556",
    "addr:street":"Hetfield Pl",
    "iso:country":"US",
    "sg:address":"22 Hetfield Pl",
    "sg:city":"Moraga",
    "sg:classifiers":[
        {
            "category":"Professional",
            "subcategory":"Business Services",
            "type":"Services"
        }
    ],
    "sg:phone":"+1 925 376 9768",
    "sg:postcode":"94556",
    "sg:province":"CA",
    "sg:tags":[
        "holding"
    ],
    "wof:name":"1995 Jeffrey E Schwartz Family Lp",
    "wof:placetype":"venue"
},
  "geometry": {"coordinates":[-122.121065,37.830323],"type":"Point"}
}