{
  "type": "Feature",
  "properties": {
    "addr:full":"745 W Foothill Blvd Upland CA 91786",
    "addr:housenumber":"745",
    "addr:postcode":"91786",
    "addr:street":"W Foothill Blvd",
    "iso:country":"US",
    "sg:address":"745 W Foothill Blvd",
    "sg:city":"Upland",
    "sg:classifiers":[
        {
            "category":"Shopping",
            "subcategory":"Clothing, Apparel, & Fashions",
            "type":"Retail Goods"
        }
    ],
    "sg:phone":"+1 909 920 0998",
    "sg:postcode":"91786",
    "sg:province":"CA",
    "sg:tags":[
        "wear"
    ],
    "wof:name":"Picky Kids",
    "wof:placetype":"venue"
},
  "geometry": {"coordinates":[-117.660398,34.107059],"type":"Point"}
}