{
  "type": "Feature",
  "properties": {
    "iso:country":"US",
    "sg:address":"8926 Benson Ave",
    "sg:city":"Montclair",
    "sg:classifiers":[
        {
            "category":"Health Services",
            "subcategory":"Nursing And Care Facility",
            "type":"Services"
        }
    ],
    "sg:phone":"+1 909 373 0101",
    "sg:postcode":"91763",
    "sg:province":"CA",
    "sg:tags":[
        "hospice"
    ],
    "wof:name":"Integrity Hospice",
    "wof:placetype":"venue"
},
  "geometry": {"coordinates":[-117.68098000000001,34.088914],"type":"Point"}
}