{
  "type": "Feature",
  "properties": {
    "addr:full":"103 N Oregon St Yreka CA 96097",
    "addr:housenumber":"103",
    "addr:postcode":"96097",
    "addr:street":"N Oregon St",
    "iso:country":"US",
    "sg:address":"103 N Oregon St",
    "sg:city":"Yreka",
    "sg:classifiers":[
        {
            "category":"Personal",
            "subcategory":"Beauty Salon",
            "type":"Services"
        }
    ],
    "sg:phone":"+1 530 842 7143",
    "sg:postcode":"96097",
    "sg:province":"CA",
    "wof:name":"Total Image",
    "wof:placetype":"venue"
},
  "geometry": {"coordinates":[-122.63805600000001,41.732948],"type":"Point"}
}