{
  "type": "Feature",
  "properties": {
    "addr:full":"41915 3rd St Temecula CA 92590",
    "addr:housenumber":"41915",
    "addr:postcode":"92590",
    "addr:street":"3Rd St",
    "iso:country":"US",
    "sg:address":"41915 3rd St",
    "sg:city":"Temecula",
    "sg:classifiers":[
        {
            "category":"Restaurant",
            "type":"Food & Drink"
        }
    ],
    "sg:phone":"+1 951 693 5909",
    "sg:postcode":"92590",
    "sg:province":"CA",
    "sg:tags":[
        "shop",
        "coffee"
    ],
    "wof:name":"Old Town Coffee House",
    "wof:placetype":"venue"
},
  "geometry": {"coordinates":[-117.14701700000001,33.493549],"type":"Point"}
}