{
  "type": "Feature",
  "properties": {
    "iso:country":"US",
    "sg:address":"4402 N Glenfinnan Ave",
    "sg:city":"Covina",
    "sg:classifiers":[
        {
            "category":"Manufacturing",
            "subcategory":"Printing",
            "type":"Manufacturing & Wholesale Goods"
        }
    ],
    "sg:phone":"+1 626 331 8716",
    "sg:postcode":"91723",
    "sg:province":"CA",
    "sg:tags":[
        "lithographic",
        "commercial"
    ],
    "wof:name":"Johnsons Numbering Service",
    "wof:placetype":"venue"
},
  "geometry": {"coordinates":[-117.89827,34.095695],"type":"Point"}
}