{
  "type": "Feature",
  "properties": {
    "addr:full":"24025 Park Sorrento Calabasas CA 91302",
    "addr:housenumber":"24025",
    "addr:postcode":"91302",
    "addr:street":"Park",
    "iso:country":"US",
    "sg:address":"24025 Park Sorrento",
    "sg:city":"Calabasas",
    "sg:classifiers":[
        {
            "category":"Building & Trades",
            "subcategory":"Construction",
            "type":"Services"
        }
    ],
    "sg:phone":"+1 818 223 7500",
    "sg:postcode":"91302",
    "sg:province":"CA",
    "sg:tags":[
        "contractor"
    ],
    "wof:name":"Ryland Group",
    "wof:placetype":"venue"
},
  "geometry": {"coordinates":[-118.649002,34.152199],"type":"Point"}
}