{
  "type": "Feature",
  "properties": {
    "addr:full":"3965 Buena Vista Dr Paso Robles CA 93446",
    "addr:housenumber":"3965",
    "addr:postcode":"93446",
    "addr:street":"Buena Vista Dr",
    "iso:country":"US",
    "sg:address":"3965 Buena Vista Dr",
    "sg:city":"Paso Robles",
    "sg:classifiers":[
        {
            "category":"Insurance",
            "subcategory":"Insurance Agent",
            "type":"Services"
        }
    ],
    "sg:phone":"+1 805 239 1991",
    "sg:postcode":"93446",
    "sg:province":"CA",
    "wof:name":"Prudential",
    "wof:placetype":"venue"
},
  "geometry": {"coordinates":[-120.672241,35.659375],"type":"Point"}
}