{
  "type": "Feature",
  "properties": {
    "addr:full":"2343 3rd St Ste 299 San Francisco CA 94107",
    "addr:housenumber":"2343",
    "addr:postcode":"94107",
    "addr:street":"3Rd St Ste 299",
    "iso:country":"US",
    "sg:address":"2343 3rd St Ste 299",
    "sg:city":"San Francisco",
    "sg:classifiers":[
        {
            "category":"Professional",
            "type":"Services"
        }
    ],
    "sg:phone":"+1 415 863 8395",
    "sg:postcode":"94107",
    "sg:province":"CA",
    "sg:website":"www.pressarts.com",
    "wof:name":"pressArts",
    "wof:placetype":"venue"
},
  "geometry": {"coordinates":[-122.38833099999999,37.758686],"type":"Point"}
}