{
  "type": "Feature",
  "properties": {
    "addr:full":"9035 Sheep Creek Rd Phelan CA 92371",
    "addr:housenumber":"9035",
    "addr:postcode":"92371",
    "addr:street":"Sheep Creek Rd",
    "iso:country":"US",
    "sg:address":"9035 Sheep Creek Rd",
    "sg:city":"Phelan",
    "sg:classifiers":[
        {
            "category":"Real Estate",
            "subcategory":"Real Estate Agent",
            "type":"Services"
        }
    ],
    "sg:phone":"+1 760 868 5555",
    "sg:postcode":"92371",
    "sg:province":"CA",
    "wof:name":"Marinelli Realty",
    "wof:placetype":"venue"
},
  "geometry": {"coordinates":[-117.572281,34.413208],"type":"Point"}
}