{
  "type": "Feature",
  "properties": {
    "addr:full":"12139 South St Artesia CA 90701",
    "addr:housenumber":"12139",
    "addr:postcode":"90701",
    "addr:street":"South St",
    "iso:country":"US",
    "sg:address":"12139 South St",
    "sg:city":"Artesia",
    "sg:classifiers":[
        {
            "category":"Personal",
            "subcategory":"Beauty Salon",
            "type":"Services"
        }
    ],
    "sg:phone":"+1 562 924 3484",
    "sg:postcode":"90701",
    "sg:province":"CA",
    "wof:name":"Hi Beauty Salon",
    "wof:placetype":"venue"
},
  "geometry": {"coordinates":[-118.07253799999999,33.858597],"type":"Point"}
}