{
  "type": "Feature",
  "properties": {
    "iso:country":"US",
    "sg:address":"1900 Ave of the Stars",
    "sg:city":"Los Angeles",
    "sg:classifiers":[
        {
            "category":"Professional",
            "subcategory":"Lawyer & Legal Services",
            "type":"Services"
        }
    ],
    "sg:phone":"+1 310 552 2500",
    "sg:postcode":"90067",
    "sg:province":"CA",
    "sg:tags":[
        "attorney"
    ],
    "sg:website":"www.arnoldporter.com",
    "wof:name":"Arnold & Porter",
    "wof:placetype":"venue"
},
  "geometry": {"coordinates":[-118.416805,34.05999],"type":"Point"}
}