{
  "type": "Feature",
  "properties": {
    "addr:full":"4618 N Montpelier Rd Denair CA 95316",
    "addr:housenumber":"4618",
    "addr:postcode":"95316",
    "addr:street":"N Montpelier Rd",
    "iso:country":"US",
    "sg:address":"4618 N Montpelier Rd",
    "sg:city":"Denair",
    "sg:classifiers":[
        {
            "category":"Farming",
            "subcategory":"Crops",
            "type":"Manufacturing & Wholesale Goods"
        }
    ],
    "sg:phone":"+1 209 874 1764",
    "sg:postcode":"95316",
    "sg:province":"CA",
    "sg:tags":[
        "grove",
        "nut",
        "tree"
    ],
    "wof:name":"Roy A Johnson Farms Inc",
    "wof:placetype":"venue"
},
  "geometry": {"coordinates":[-120.69256900000001,37.532213],"type":"Point"}
}