{
  "type": "Feature",
  "properties": {
    "addr:full":"1161 E F St Oakdale CA 95361",
    "addr:housenumber":"1161",
    "addr:postcode":"95361",
    "addr:street":"E F St",
    "iso:country":"US",
    "sg:address":"1161 E F St",
    "sg:city":"Oakdale",
    "sg:classifiers":[
        {
            "category":"Restaurant",
            "type":"Food & Drink"
        }
    ],
    "sg:phone":"+1 209 847 2079",
    "sg:postcode":"95361",
    "sg:province":"CA",
    "wof:name":"Ferrarese's Deli Restaurant",
    "wof:placetype":"venue"
},
  "geometry": {"coordinates":[-120.838645,37.769719],"type":"Point"}
}