{
  "type": "Feature",
  "properties": {
    "iso:country":"US",
    "sg:address":"5924 E Los Angeles Ave",
    "sg:city":"Simi Valley",
    "sg:classifiers":[
        {
            "category":"Retail",
            "subcategory":"Animal Services",
            "type":"Services"
        }
    ],
    "sg:phone":"+1 805 520 0321",
    "sg:postcode":"93063",
    "sg:province":"CA",
    "sg:tags":[
        "pet",
        "grooming",
        "washing",
        "merchandise"
    ],
    "wof:name":"Land of Paws",
    "wof:placetype":"venue"
},
  "geometry": {"coordinates":[-118.675009,34.271655],"type":"Point"}
}