{
  "type": "Feature",
  "properties": {
    "addr:full":"849 Ocean Ave Santa Monica CA 90403",
    "addr:housenumber":"849",
    "addr:postcode":"90403",
    "addr:street":"Ocean Ave",
    "iso:country":"US",
    "sg:address":"849 Ocean Ave",
    "sg:city":"Santa Monica",
    "sg:classifiers":[
        {
            "category":"Travel",
            "subcategory":"Hotels & Motels",
            "type":"Entertainment"
        }
    ],
    "sg:phone":"+1 310 393 0486",
    "sg:postcode":"90403",
    "sg:province":"CA",
    "sg:website":"www.hoteloceana.com",
    "wof:name":"Hotel Oceana",
    "wof:placetype":"venue"
},
  "geometry": {"coordinates":[-118.506503,34.021576],"type":"Point"}
}