{
  "type": "Feature",
  "properties": {
    "iso:country":"US",
    "sg:address":"26447 Ynez Rd",
    "sg:city":"Temecula",
    "sg:classifiers":[
        {
            "category":"Home & Garden",
            "subcategory":"Home Furnishings",
            "type":"Retail Goods"
        }
    ],
    "sg:phone":"+1 951 296 0812",
    "sg:postcode":"92591",
    "sg:province":"CA",
    "sg:tags":[
        "linen"
    ],
    "wof:name":"Anna's Linens",
    "wof:placetype":"venue"
},
  "geometry": {"coordinates":[-117.158123,33.52265],"type":"Point"}
}