{
  "type": "Feature",
  "properties": {
    "addr:full":"2179 Summerpark Ct Thousand Oaks CA 91362",
    "addr:housenumber":"2179",
    "addr:postcode":"91362",
    "addr:street":"Summerpark Ct",
    "iso:country":"US",
    "sg:address":"2179 Summerpark Ct",
    "sg:city":"Thousand Oaks",
    "sg:classifiers":[
        {
            "category":"Professional",
            "subcategory":"Management & Consulting",
            "type":"Services"
        }
    ],
    "sg:phone":"+1 805 492 9958",
    "sg:postcode":"91362",
    "sg:province":"CA",
    "sg:tags":[
        "sales"
    ],
    "wof:name":"Rewards and More Inc",
    "wof:placetype":"venue"
},
  "geometry": {"coordinates":[-118.837386,34.210527],"type":"Point"}
}