{
  "type": "Feature",
  "properties": {
    "addr:full":"2555 Morena Blvd San Diego CA 92110",
    "addr:housenumber":"2555",
    "addr:postcode":"92110",
    "addr:street":"Morena Blvd",
    "iso:country":"US",
    "sg:address":"2555 Morena Blvd",
    "sg:city":"San Diego",
    "sg:classifiers":[
        {
            "category":"Insurance",
            "subcategory":"Insurance Agent",
            "type":"Services"
        }
    ],
    "sg:phone":"+1 619 858 7700",
    "sg:postcode":"92110",
    "sg:province":"CA",
    "wof:name":"Kenneth Sawyer Insurance",
    "wof:placetype":"venue"
},
  "geometry": {"coordinates":[-117.20587500000001,32.788926],"type":"Point"}
}