{
  "type": "Feature",
  "properties": {
    "addr:full":"3739 Marysville Boulevard Sacramento CA 95838",
    "addr:housenumber":"3739",
    "addr:postcode":"95838",
    "addr:street":"Marysville Boulevard",
    "iso:country":"US",
    "sg:address":"3739 Marysville Boulevard",
    "sg:city":"Sacramento",
    "sg:classifiers":[
        {
            "category":"Autos & Motor Vehicles",
            "subcategory":"Fuel & Gas Station",
            "type":"Retail Goods"
        }
    ],
    "sg:phone":"+1 916 924 8981",
    "sg:postcode":"95838",
    "sg:province":"CA",
    "wof:name":"Indus Gasoline",
    "wof:placetype":"venue"
},
  "geometry": {"coordinates":[-121.430013,38.636084],"type":"Point"}
}