{
  "type": "Feature",
  "properties": {
    "addr:full":"409 Brannan St San Francisco CA 94107",
    "addr:housenumber":"409",
    "addr:postcode":"94107",
    "addr:street":"Brannan St",
    "iso:country":"US",
    "sg:address":"409 Brannan St",
    "sg:city":"San Francisco",
    "sg:classifiers":[
        {
            "category":"Professional",
            "subcategory":"Management & Consulting",
            "type":"Services"
        }
    ],
    "sg:phone":"+1 415 541 9113",
    "sg:postcode":"94107",
    "sg:province":"CA",
    "sg:tags":[
        "consultant",
        "business"
    ],
    "wof:name":"Dependable Business Svc",
    "wof:placetype":"venue"
},
  "geometry": {"coordinates":[-122.394616,37.779781],"type":"Point"}
}