{
  "type": "Feature",
  "properties": {
    "addr:full":"6200 Washington St Napa CA 94558",
    "addr:housenumber":"6200",
    "addr:postcode":"94558",
    "addr:street":"Washington St",
    "iso:country":"US",
    "sg:address":"6200 Washington St",
    "sg:city":"Napa",
    "sg:classifiers":[
        {
            "category":"Manufacturing",
            "subcategory":"Food",
            "type":"Manufacturing & Wholesale Goods"
        }
    ],
    "sg:phone":"+1 707 944 1673",
    "sg:postcode":"94558",
    "sg:province":"CA",
    "sg:tags":[
        "winery"
    ],
    "sg:website":"www.bellwine.com",
    "wof:name":"Bell Wine Cellars",
    "wof:placetype":"venue"
},
  "geometry": {"coordinates":[-122.34999000000001,38.387329],"type":"Point"}
}