{
  "type": "Feature",
  "properties": {
    "addr:full":"5308 Derry Ave Agoura Hills CA 91301",
    "addr:housenumber":"5308",
    "addr:postcode":"91301",
    "addr:street":"Derry Ave",
    "iso:country":"US",
    "sg:address":"5308 Derry Ave",
    "sg:city":"Agoura Hills",
    "sg:classifiers":[
        {
            "category":"Utilities",
            "subcategory":"Telephone",
            "type":"Services"
        }
    ],
    "sg:phone":"+1 818 597 2338",
    "sg:postcode":"91301",
    "sg:province":"CA",
    "sg:tags":[
        "company"
    ],
    "wof:name":"Pannon Telecom Inc",
    "wof:placetype":"venue"
},
  "geometry": {"coordinates":[-118.7479,34.147566],"type":"Point"}
}