{
  "type": "Feature",
  "properties": {
    "addr:full":"375 N Capitol Ave Ste B San Jose CA 95133",
    "addr:housenumber":"375",
    "addr:postcode":"95133",
    "addr:street":"N Capitol Ave Ste B",
    "iso:country":"US",
    "sg:address":"375 N Capitol Ave Ste B",
    "sg:city":"San Jose",
    "sg:classifiers":[
        {
            "category":"Food & Beverages",
            "subcategory":"Groceries & Convenience Stores",
            "type":"Retail Goods"
        }
    ],
    "sg:phone":"+1 408 258 1194",
    "sg:postcode":"95133",
    "sg:province":"CA",
    "wof:name":"Pak N Save",
    "wof:placetype":"venue"
},
  "geometry": {"coordinates":[-121.845027,37.371758],"type":"Point"}
}