{
  "type": "Feature",
  "properties": {
    "addr:full":"435 Stockton St San Francisco CA 94108",
    "addr:housenumber":"435",
    "addr:postcode":"94108",
    "addr:street":"Stockton St",
    "iso:country":"US",
    "sg:address":"435 Stockton St",
    "sg:city":"San Francisco",
    "sg:classifiers":[
        {
            "category":"Shopping",
            "subcategory":"Florist",
            "type":"Retail Goods"
        }
    ],
    "sg:phone":"+1 415 291 0728",
    "sg:postcode":"94108",
    "sg:province":"CA",
    "wof:name":"Enchanted Garden Florist",
    "wof:placetype":"venue"
},
  "geometry": {"coordinates":[-122.40720899999999,37.79027],"type":"Point"}
}