{
  "type": "Feature",
  "properties": {
    "addr:full":"4803 Everett Ave Los Angeles CA 90058",
    "addr:housenumber":"4803",
    "addr:postcode":"90058",
    "addr:street":"Everett Ave",
    "iso:country":"US",
    "sg:address":"4803 Everett Ave",
    "sg:city":"Los Angeles",
    "sg:classifiers":[
        {
            "category":"Wholesale",
            "subcategory":"Stationery",
            "type":"Manufacturing & Wholesale Goods"
        }
    ],
    "sg:phone":"+1 323 588 8555",
    "sg:postcode":"90058",
    "sg:province":"CA",
    "sg:tags":[
        "product",
        "paper"
    ],
    "wof:name":"TBF Paper Converting",
    "wof:placetype":"venue"
},
  "geometry": {"coordinates":[-118.200614,33.999096],"type":"Point"}
}