{
  "type": "Feature",
  "properties": {
    "addr:full":"1600 Long Beach Blvd Long Beach CA 90813",
    "addr:housenumber":"1600",
    "addr:postcode":"90813",
    "addr:street":"Long Beach Blvd",
    "iso:country":"US",
    "sg:address":"1600 Long Beach Blvd",
    "sg:city":"Long Beach",
    "sg:classifiers":[
        {
            "category":"Retail",
            "subcategory":"Auto Repair",
            "type":"Services"
        }
    ],
    "sg:phone":"+1 562 599 2222",
    "sg:postcode":"90813",
    "sg:province":"CA",
    "wof:name":"J C Smog & Lube",
    "wof:placetype":"venue"
},
  "geometry": {"coordinates":[-118.189003,33.787399],"type":"Point"}
}