{
  "type": "Feature",
  "properties": {
    "addr:full":"13941 Cll Bueno Ganar Jamul CA 91935",
    "addr:housenumber":"13941",
    "addr:postcode":"jamul ca 91935",
    "addr:street":"Cll Bueno Ganar",
    "iso:country":"US",
    "sg:address":"13941 Cll Bueno Ganar",
    "sg:city":"Jamul",
    "sg:classifiers":[
        {
            "category":"Arts & Performance",
            "subcategory":"Theater",
            "type":"Entertainment"
        }
    ],
    "sg:phone":"+1 619 669 9933",
    "sg:postcode":"91935",
    "sg:province":"CA",
    "sg:tags":[
        "bureau"
    ],
    "wof:name":"NRG Music Production",
    "wof:placetype":"venue"
},
  "geometry": {"coordinates":[-116.875935,32.709532],"type":"Point"}
}