{
  "type": "Feature",
  "properties": {
    "addr:full":"2598 Fortune Way Vista CA 92081",
    "addr:housenumber":"2598",
    "addr:postcode":"92081",
    "addr:street":"Fortune Way",
    "iso:country":"US",
    "sg:address":"2598 Fortune Way",
    "sg:city":"Vista",
    "sg:classifiers":[
        {
            "category":"Wholesale",
            "subcategory":"Durable Goods & Equipment",
            "type":"Manufacturing & Wholesale Goods"
        }
    ],
    "sg:phone":"+1 760 734 1685",
    "sg:postcode":"92081",
    "sg:province":"CA",
    "sg:tags":[
        "environmental",
        "product"
    ],
    "wof:name":"Solmar Corp",
    "wof:placetype":"venue"
},
  "geometry": {"coordinates":[-117.223804,33.150906],"type":"Point"}
}