{
  "type": "Feature",
  "properties": {
    "iso:country":"US",
    "sg:address":"2599 8th St Ste 41",
    "sg:city":"Berkeley",
    "sg:classifiers":[
        {
            "category":"Shopping",
            "subcategory":"Clothing, Apparel, & Fashions",
            "type":"Retail Goods"
        },
        {
            "category":"Manufacturing",
            "subcategory":"Apparel",
            "type":"Manufacturing & Wholesale Goods"
        }
    ],
    "sg:phone":"+1 510 704 0203",
    "sg:postcode":"94710",
    "sg:province":"CA",
    "sg:tags":[
        "apparel-wholesale",
        "manufacturer",
        "women's"
    ],
    "wof:name":"Barbini",
    "wof:placetype":"venue"
},
  "geometry": {"coordinates":[-122.292374,37.85865],"type":"Point"}
}