{
  "type": "Feature",
  "properties": {
    "addr:full":"7840 Cll Juela La Jolla CA 92037",
    "addr:postcode":"7840;92037",
    "addr:street":"Cll Juela",
    "iso:country":"US",
    "sg:address":"7840 Cll Juela",
    "sg:city":"La Jolla",
    "sg:classifiers":[
        {
            "category":"Personal",
            "subcategory":"Beauty Salon",
            "type":"Services"
        }
    ],
    "sg:phone":"+1 858 551 8086",
    "sg:postcode":"92037",
    "sg:province":"CA",
    "sg:website":"www.reginaldoflondon.com",
    "wof:name":"Reginald Of London",
    "wof:placetype":"venue"
},
  "geometry": {"coordinates":[-117.25497900000001,32.849685],"type":"Point"}
}