{
  "type": "Feature",
  "properties": {
    "iso:country":"US",
    "sg:address":"20222 3rd Ave",
    "sg:city":"Stevinson",
    "sg:classifiers":[
        {
            "category":"Organizations",
            "subcategory":"Religious Organization",
            "type":"Services"
        }
    ],
    "sg:phone":"+1 209 634 8038",
    "sg:postcode":"95374",
    "sg:province":"CA",
    "sg:tags":[
        "church"
    ],
    "wof:name":"Stevinson Chapel",
    "wof:placetype":"venue"
},
  "geometry": {"coordinates":[-120.85607899999999,37.327715],"type":"Point"}
}