{
  "type": "Feature",
  "properties": {
    "addr:full":"600 16th St Ste 30 Oakland CA 94612",
    "addr:housenumber":"600",
    "addr:postcode":"94612",
    "addr:street":"16Th St Ste 30",
    "iso:country":"US",
    "sg:address":"600 16th St Ste 30",
    "sg:city":"Oakland",
    "sg:classifiers":[
        {
            "category":"Government",
            "subcategory":"Post Office",
            "type":"Public Place"
        }
    ],
    "sg:phone":"+1 510 464 3033",
    "sg:postcode":"94612",
    "sg:province":"CA",
    "sg:tags":[
        "poster"
    ],
    "sg:website":"http://www.simaapublicity.com",
    "wof:name":"Simaa",
    "wof:placetype":"venue"
},
  "geometry": {"coordinates":[-122.273949,37.80706],"type":"Point"}
}