{
  "type": "Feature",
  "properties": {
    "addr:full":"880 Northrdge Shppng Ctr Salinas CA 93906",
    "addr:housenumber":"880",
    "addr:postcode":"93906",
    "addr:street":"Northrdge Shppng Ctr",
    "iso:country":"US",
    "sg:address":"880 Northrdge Shppng Ctr",
    "sg:city":"Salinas",
    "sg:classifiers":[
        {
            "category":"Home & Garden",
            "subcategory":"Garden Supply",
            "type":"Retail Goods"
        },
        {
            "category":"Shopping",
            "subcategory":"Pharmacy",
            "type":"Retail Goods"
        }
    ],
    "sg:phone":"+1 831 449 2481",
    "sg:postcode":"93906",
    "sg:province":"CA",
    "sg:tags":[
        "drugstore",
        "nursery",
        "gardening"
    ],
    "wof:name":"Rite Aid",
    "wof:placetype":"venue"
},
  "geometry": {"coordinates":[-121.656998,36.720699],"type":"Point"}
}