{
  "type": "Feature",
  "properties": {
    "addr:full":"10523 Sandy Way Westwood CA 96145",
    "addr:housenumber":"10523",
    "addr:postcode":"96145",
    "addr:street":"Sandy Way",
    "iso:country":"US",
    "sg:address":"10523 Sandy Way",
    "sg:city":"Westwood",
    "sg:classifiers":[
        {
            "category":"Manufacturing",
            "subcategory":"Printing",
            "type":"Manufacturing & Wholesale Goods"
        }
    ],
    "sg:phone":"+1 310 470 1346",
    "sg:postcode":"96145",
    "sg:province":"CA",
    "sg:tags":[
        "printer"
    ],
    "wof:name":"Printers Gallery-Designer",
    "wof:placetype":"venue"
},
  "geometry": {"coordinates":[-120.23121,39.201457],"type":"Point"}
}