{
  "type": "Feature",
  "properties": {
    "iso:country":"US",
    "sg:address":"1476 Los Cedros Ln",
    "sg:city":"Escondido",
    "sg:classifiers":[
        {
            "category":"Travel",
            "subcategory":"Travel Agent",
            "type":"Entertainment"
        }
    ],
    "sg:phone":"+1 760 489 7795",
    "sg:postcode":"92026",
    "sg:province":"CA",
    "sg:tags":[
        "operator",
        "tour"
    ],
    "wof:name":"Bice Tours",
    "wof:placetype":"venue"
},
  "geometry": {"coordinates":[-117.117124,33.152],"type":"Point"}
}