{
  "type": "Feature",
  "properties": {
    "addr:full":"1040 N Las Palmas Avenue Los Angeles CA 90038",
    "addr:housenumber":"1040",
    "addr:postcode":"90038",
    "addr:street":"N Las Palmas Avenue",
    "iso:country":"US",
    "sg:address":"1040 N Las Palmas Avenue",
    "sg:city":"Los Angeles",
    "sg:classifiers":[
        {
            "category":"Retail",
            "subcategory":"Portrait Studio",
            "type":"Services"
        }
    ],
    "sg:phone":"+1 323 860 3526",
    "sg:postcode":"90038",
    "sg:province":"CA",
    "sg:tags":[
        "photography",
        "store"
    ],
    "wof:name":"Shelter Films",
    "wof:placetype":"venue"
},
  "geometry": {"coordinates":[-118.336152,34.089514],"type":"Point"}
}