{
  "type": "Feature",
  "properties": {
    "addr:full":"13861 Brookhurst St Garden Grove CA 92843",
    "addr:housenumber":"13861",
    "addr:postcode":"92843",
    "addr:street":"Brookhurst St",
    "iso:country":"US",
    "sg:address":"13861 Brookhurst St",
    "sg:city":"Garden Grove",
    "sg:classifiers":[
        {
            "category":"Shopping",
            "subcategory":"Florist",
            "type":"Retail Goods"
        }
    ],
    "sg:phone":"+1 714 467 0622",
    "sg:postcode":"92843",
    "sg:province":"CA",
    "wof:name":"Hosen Flowers",
    "wof:placetype":"venue"
},
  "geometry": {"coordinates":[-117.95519400000001,33.760818],"type":"Point"}
}