{
  "type": "Feature",
  "properties": {
    "addr:full":"701 Lincoln Ave San Jose CA 95126",
    "addr:housenumber":"701",
    "addr:postcode":"95126",
    "addr:street":"Lincoln Ave",
    "iso:country":"US",
    "sg:address":"701 Lincoln Ave",
    "sg:city":"San Jose",
    "sg:classifiers":[
        {
            "category":"Retail",
            "subcategory":"Auto Repair",
            "type":"Services"
        }
    ],
    "sg:phone":"+1 408 279 9301",
    "sg:postcode":"95126",
    "sg:province":"CA",
    "wof:name":"L & T Auto Repair",
    "wof:placetype":"venue"
},
  "geometry": {"coordinates":[-121.90749700000001,37.316839],"type":"Point"}
}