{
  "type": "Feature",
  "properties": {
    "addr:full":"3539 Clover Way Ontario CA 91761",
    "addr:housenumber":"3539",
    "addr:postcode":"91761",
    "addr:street":"Clover Way",
    "iso:country":"US",
    "sg:address":"3539 Clover Way",
    "sg:city":"Ontario",
    "sg:classifiers":[
        {
            "category":"Professional",
            "type":"Services"
        }
    ],
    "sg:phone":"+1 909 930 1959",
    "sg:postcode":"91761",
    "sg:province":"CA",
    "wof:name":"Mobile Signing Svc",
    "wof:placetype":"venue"
},
  "geometry": {"coordinates":[-117.581146,34.009003],"type":"Point"}
}