{
  "type": "Feature",
  "properties": {
    "iso:country":"US",
    "sg:address":"2021 Main St",
    "sg:city":"Ramona",
    "sg:classifiers":[
        {
            "category":"Shopping",
            "type":"Retail Goods"
        }
    ],
    "sg:phone":"+1 760 789 1752",
    "sg:postcode":"92065",
    "sg:province":"CA",
    "sg:tags":[
        "craft",
        "gallery",
        "dealer"
    ],
    "wof:name":"Ramona Country Crafts",
    "wof:placetype":"venue"
},
  "geometry": {"coordinates":[-116.885404,33.031447],"type":"Point"}
}