{
  "type": "Feature",
  "properties": {
    "addr:full":"1838 W 11th St Upland CA 91786",
    "addr:housenumber":"1838",
    "addr:postcode":"91786",
    "addr:street":"W 11Th St",
    "iso:country":"US",
    "sg:address":"1838 W 11th St",
    "sg:city":"Upland",
    "sg:classifiers":[
        {
            "category":"Retail",
            "subcategory":"Auto Repair",
            "type":"Services"
        }
    ],
    "sg:phone":"+1 909 920 3046",
    "sg:postcode":"91786",
    "sg:province":"CA",
    "sg:tags":[
        "body",
        "automobile",
        "painting"
    ],
    "wof:name":"West Works Auto Body",
    "wof:placetype":"venue"
},
  "geometry": {"coordinates":[-117.689021,34.103135],"type":"Point"}
}