{
  "type": "Feature",
  "properties": {
    "iso:country":"US",
    "sg:address":"50 E 20th St",
    "sg:city":"Merced",
    "sg:classifiers":[
        {
            "category":"Education",
            "subcategory":"School",
            "type":"Public Place"
        }
    ],
    "sg:phone":"+1 209 385 6524",
    "sg:postcode":"95340",
    "sg:province":"CA",
    "wof:name":"Merced Adult School",
    "wof:placetype":"venue"
},
  "geometry": {"coordinates":[-120.473471,37.301289],"type":"Point"}
}