{
  "type": "Feature",
  "properties": {
    "iso:country":"US",
    "sg:address":"4938 W State Hwy 140",
    "sg:city":"Merced",
    "sg:classifiers":[
        {
            "category":"Manufacturing",
            "subcategory":"Signs",
            "type":"Manufacturing & Wholesale Goods"
        }
    ],
    "sg:phone":"+1 209 383 2727",
    "sg:postcode":"95340",
    "sg:province":"CA",
    "wof:name":"Sign Works",
    "wof:placetype":"venue"
},
  "geometry": {"coordinates":[-120.57696,37.302344],"type":"Point"}
}