{
  "type": "Feature",
  "properties": {
    "addr:full":"2795 E Via Escuela Palm Springs CA 92262",
    "addr:housenumber":"2795",
    "addr:postcode":"92262",
    "addr:street":"E Via Escuela",
    "iso:country":"US",
    "sg:address":"2795 E Via Escuela",
    "sg:city":"Palm Springs",
    "sg:classifiers":[
        {
            "category":"Retail",
            "subcategory":"Laundry & Dry Cleaning",
            "type":"Services"
        }
    ],
    "sg:phone":"+1 760 327 5600",
    "sg:postcode":"92262",
    "sg:province":"CA",
    "sg:tags":[
        "cleaners",
        "rug",
        "carpet"
    ],
    "wof:name":"Mike Webb's Carpet & Window",
    "wof:placetype":"venue"
},
  "geometry": {"coordinates":[-116.516789,33.848483],"type":"Point"}
}