{
  "type": "Feature",
  "properties": {
    "addr:full":"4276 S Main St Los Angeles CA 90037",
    "addr:housenumber":"4276",
    "addr:postcode":"90037",
    "addr:street":"S Main St",
    "iso:country":"US",
    "sg:address":"4276 S Main St",
    "sg:city":"Los Angeles",
    "sg:classifiers":[
        {
            "category":"Food & Beverages",
            "subcategory":"Groceries & Convenience Stores",
            "type":"Retail Goods"
        }
    ],
    "sg:phone":"+1 323 231 5998",
    "sg:postcode":"90037",
    "sg:province":"CA",
    "sg:tags":[
        "market"
    ],
    "wof:name":"Gusie's Market",
    "wof:placetype":"venue"
},
  "geometry": {"coordinates":[-118.27391,34.006152],"type":"Point"}
}