{
  "type": "Feature",
  "properties": {
    "iso:country":"US",
    "sg:address":"2750 E Main St",
    "sg:city":"Ventura",
    "sg:classifiers":[
        {
            "category":"Wholesale",
            "subcategory":"Groceries",
            "type":"Manufacturing & Wholesale Goods"
        }
    ],
    "sg:phone":"+1 805 643 5556",
    "sg:postcode":"93003",
    "sg:province":"CA",
    "sg:tags":[
        "grocer",
        "store"
    ],
    "sg:website":"http://www.smartandfinal.com",
    "wof:name":"Smart & Final",
    "wof:placetype":"venue"
},
  "geometry": {"coordinates":[-119.259349,34.273315],"type":"Point"}
}