{
  "type": "Feature",
  "properties": {
    "iso:country":"US",
    "sg:address":"6791 Airport Dr",
    "sg:city":"Riverside",
    "sg:classifiers":[
        {
            "category":"Education",
            "subcategory":"Special Training",
            "type":"Public Place"
        }
    ],
    "sg:phone":"+1 951 354 5274",
    "sg:postcode":"92504",
    "sg:province":"CA",
    "sg:tags":[
        "aircraft",
        "school"
    ],
    "sg:website":"www.caaviationservices.com",
    "wof:name":"California Aviation Svc Inc",
    "wof:placetype":"venue"
},
  "geometry": {"coordinates":[-117.44513999999999,33.949474],"type":"Point"}
}