{
  "type": "Feature",
  "properties": {
    "addr:full":"9901 Venice Boulevard Los Angeles CA 90034",
    "addr:housenumber":"9901",
    "addr:postcode":"90034",
    "addr:street":"Venice Boulevard",
    "iso:country":"US",
    "sg:address":"9901 Venice Boulevard",
    "sg:city":"Los Angeles",
    "sg:classifiers":[
        {
            "category":"Shopping",
            "subcategory":"Florist",
            "type":"Retail Goods"
        }
    ],
    "sg:phone":"+1 310 836 0439",
    "sg:postcode":"90034",
    "sg:province":"CA",
    "wof:name":"Mahalo Flowers",
    "wof:placetype":"venue"
},
  "geometry": {"coordinates":[-118.398894,34.023261],"type":"Point"}
}