{
  "type": "Feature",
  "properties": {
    "iso:country":"US",
    "sg:address":"327 Moffett Blvd Ste C",
    "sg:city":"Mountain View",
    "sg:classifiers":[
        {
            "category":"Health Services",
            "subcategory":"Dentist",
            "type":"Services"
        }
    ],
    "sg:postcode":"94043",
    "sg:province":"CA",
    "wof:name":"May Y. Antonio",
    "wof:placetype":"venue"
},
  "geometry": {"coordinates":[-122.075985,37.398052],"type":"Point"}
}