{
  "type": "Feature",
  "properties": {
    "iso:country":"US",
    "sg:address":"31991 Pleasant Glen Rd",
    "sg:city":"Trabuco Canyon",
    "sg:classifiers":[
        {
            "category":"Professional",
            "type":"Services"
        }
    ],
    "sg:phone":"+1 949 858 1083",
    "sg:postcode":"92679",
    "sg:province":"CA",
    "wof:name":"Solo Sports",
    "wof:placetype":"venue"
},
  "geometry": {"coordinates":[-117.574661,33.652452],"type":"Point"}
}