{
  "type": "Feature",
  "properties": {
    "iso:country":"US",
    "sg:address":"345 S Fowler Ave",
    "sg:city":"Fowler",
    "sg:classifiers":[
        {
            "category":"Professional",
            "subcategory":"Lawyer & Legal Services",
            "type":"Services"
        }
    ],
    "sg:phone":"+1 559 834 2561",
    "sg:postcode":"93625",
    "sg:province":"CA",
    "sg:tags":[
        "attorney"
    ],
    "wof:name":"Mikio Uchiyama",
    "wof:placetype":"venue"
},
  "geometry": {"coordinates":[-119.682185,36.620731],"type":"Point"}
}