{
  "type": "Feature",
  "properties": {
    "addr:full":"473 Hudson St Oakland CA 94618",
    "addr:housenumber":"473",
    "addr:postcode":"94618",
    "addr:street":"Hudson St",
    "iso:country":"US",
    "sg:address":"473 Hudson St",
    "sg:city":"Oakland",
    "sg:classifiers":[
        {
            "category":"Arts & Performance",
            "subcategory":"Arts Center",
            "type":"Entertainment"
        },
        {
            "category":"Education",
            "subcategory":"School",
            "type":"Public Place"
        }
    ],
    "sg:phone":"+1 510 420 0920",
    "sg:postcode":"94618",
    "sg:province":"CA",
    "sg:tags":[
        "performing"
    ],
    "sg:website":"www.danspace.com",
    "wof:name":"Danspace",
    "wof:placetype":"venue"
},
  "geometry": {"coordinates":[-122.25599699999999,37.841999],"type":"Point"}
}