{
  "type": "Feature",
  "properties": {
    "addr:full":"1745 S Enterprise St Tulare CA 93274",
    "addr:housenumber":"1745",
    "addr:postcode":"93274",
    "addr:street":"S Enterprise St",
    "iso:country":"US",
    "sg:address":"1745 S Enterprise St",
    "sg:city":"Tulare",
    "sg:classifiers":[
        {
            "category":"Building & Trades",
            "subcategory":"Plumbing",
            "type":"Services"
        }
    ],
    "sg:phone":"+1 559 684 8160",
    "sg:postcode":"93274",
    "sg:province":"CA",
    "sg:tags":[
        "plumber",
        "industrial",
        "contractors-commercial"
    ],
    "wof:name":"L & L Plumbing",
    "wof:placetype":"venue"
},
  "geometry": {"coordinates":[-119.384094,36.185161],"type":"Point"}
}