{
  "type": "Feature",
  "properties": {
    "iso:country":"US",
    "sg:address":"2566 Barrington Ct",
    "sg:city":"Hayward",
    "sg:classifiers":[
        {
            "category":"Building & Trades",
            "subcategory":"Construction",
            "type":"Services"
        }
    ],
    "sg:phone":"+1 510 732 6111",
    "sg:postcode":"94545",
    "sg:province":"CA",
    "sg:tags":[
        "contractor"
    ],
    "sg:website":"www.axisconstruction.com",
    "wof:name":"Axis Construction",
    "wof:placetype":"venue"
},
  "geometry": {"coordinates":[-122.141668,37.655182],"type":"Point"}
}