{
  "type": "Feature",
  "properties": {
    "addr:full":"100 Webster St Tube Oakland CA 94607",
    "addr:housenumber":"100",
    "addr:postcode":"94607",
    "addr:street":"Webster St",
    "iso:country":"US",
    "sg:address":"100 Webster St Tube",
    "sg:city":"Oakland",
    "sg:classifiers":[
        {
            "category":"Building & Trades",
            "subcategory":"Construction",
            "type":"Services"
        }
    ],
    "sg:phone":"+1 510 452 1186",
    "sg:postcode":"94607",
    "sg:province":"CA",
    "sg:tags":[
        "designer",
        "marine",
        "contractor"
    ],
    "sg:website":"www.pma-sf.com",
    "wof:name":"Pacific Marine Assoc",
    "wof:placetype":"venue"
},
  "geometry": {"coordinates":[-122.274117,37.795172],"type":"Point"}
}