{
  "type": "Feature",
  "properties": {
    "addr:full":"1563 Rose Anna Dr San Jose CA 95118",
    "addr:housenumber":"1563",
    "addr:postcode":"95118",
    "addr:street":"Rose Anna Dr",
    "iso:country":"US",
    "sg:address":"1563 Rose Anna Dr",
    "sg:city":"San Jose",
    "sg:classifiers":[
        {
            "category":"Professional",
            "subcategory":"Lawyer & Legal Services",
            "type":"Services"
        }
    ],
    "sg:phone":"+1 408 266 7389",
    "sg:postcode":"95118",
    "sg:province":"CA",
    "sg:tags":[
        "attorney"
    ],
    "wof:name":"Francis Smallwood",
    "wof:placetype":"venue"
},
  "geometry": {"coordinates":[-121.899377,37.245788],"type":"Point"}
}