{
  "type": "Feature",
  "properties": {
    "iso:country":"US",
    "sg:address":"360 Grand Ave # 390",
    "sg:city":"Oakland",
    "sg:classifiers":[
        {
            "category":"Personal",
            "type":"Services"
        }
    ],
    "sg:phone":"+1 510 281 1919",
    "sg:postcode":"94610",
    "sg:province":"CA",
    "sg:tags":[
        "towing"
    ],
    "sg:website":"www.theautotowing.com",
    "wof:name":"Auto Towing Oakland",
    "wof:placetype":"venue"
},
  "geometry": {"coordinates":[-122.255555,37.808918],"type":"Point"}
}