{
  "type": "Feature",
  "properties": {
    "addr:full":"4725 Torrance Blvd Torrance CA 90503",
    "addr:housenumber":"4725",
    "addr:postcode":"90503",
    "addr:street":"Torrance Blvd",
    "iso:country":"US",
    "sg:address":"4725 Torrance Blvd",
    "sg:city":"Torrance",
    "sg:classifiers":[
        {
            "category":"Shopping",
            "subcategory":"Gifts & Souvenirs",
            "type":"Retail Goods"
        }
    ],
    "sg:phone":"+1 310 370 5455",
    "sg:postcode":"90503",
    "sg:province":"CA",
    "wof:name":"Morning Glory",
    "wof:placetype":"venue"
},
  "geometry": {"coordinates":[-118.36499000000001,33.83767],"type":"Point"}
}