{
  "type": "Feature",
  "properties": {
    "iso:country":"US",
    "sg:address":"150 Tejas Pl",
    "sg:city":"Nipomo",
    "sg:classifiers":[
        {
            "category":"Health Services",
            "subcategory":"Clinic",
            "type":"Services"
        },
        {
            "category":"Community Center",
            "type":"Public Place"
        },
        {
            "category":"Health Services",
            "subcategory":"Hospital",
            "type":"Services"
        },
        {
            "category":"Health Services",
            "subcategory":"Dentist",
            "type":"Services"
        },
        {
            "category":"Health Services",
            "subcategory":"Doctor",
            "type":"Services"
        },
        {
            "category":"Health Services",
            "subcategory":"Chiropractor",
            "type":"Services"
        }
    ],
    "sg:phone":"+1 805 929 3211",
    "sg:postcode":"93444",
    "sg:province":"CA",
    "sg:tags":[
        "information",
        "family",
        "chiropractic",
        "medical",
        "welfare",
        "dentists-pediatric",
        "physician",
        "urgent",
        "planning",
        "dentistry",
        "surgeon",
        "care"
    ],
    "sg:website":"http://www.chccc.org/",
    "wof:name":"Community Health Center",
    "wof:placetype":"venue"
},
  "geometry": {"coordinates":[-120.498682,35.02647],"type":"Point"}
}