{
  "type": "Feature",
  "properties": {
    "iso:country":"US",
    "sg:address":"571 E el Paso Ave",
    "sg:city":"Fresno",
    "sg:classifiers":[
        {
            "category":"Health Services",
            "subcategory":"Health Practitioner",
            "type":"Services"
        }
    ],
    "sg:phone":"+1 559 233 3995",
    "sg:postcode":"93720",
    "sg:province":"CA",
    "sg:tags":[
        "therapist",
        "physical"
    ],
    "wof:name":"Premiere Physical Therapy",
    "wof:placetype":"venue"
},
  "geometry": {"coordinates":[-119.77503,36.848237],"type":"Point"}
}