{
  "type": "Feature",
  "properties": {
    "iso:country":"US",
    "sg:address":"16 S Oakland Ave",
    "sg:city":"Pasadena",
    "sg:classifiers":[
        {
            "category":"Social Services",
            "type":"Services"
        }
    ],
    "sg:phone":"+1 626 229 0303",
    "sg:postcode":"91101",
    "sg:province":"CA",
    "sg:tags":[
        "counselor",
        "marriage",
        "family"
    ],
    "wof:name":"Catherine Wulfensmith",
    "wof:placetype":"venue"
},
  "geometry": {"coordinates":[-118.139658,34.145504],"type":"Point"}
}