{
  "type": "Feature",
  "properties": {
    "addr:full":"1500 Davidson Ave San Francisco CA 94124",
    "addr:housenumber":"1500",
    "addr:postcode":"94124",
    "addr:street":"Davidson Ave",
    "iso:country":"US",
    "sg:address":"1500 Davidson Ave",
    "sg:city":"San Francisco",
    "sg:classifiers":[
        {
            "category":"Manufacturing",
            "subcategory":"Signs",
            "type":"Manufacturing & Wholesale Goods"
        }
    ],
    "sg:phone":"+1 415 648 3400",
    "sg:postcode":"94124",
    "sg:province":"CA",
    "wof:name":"Smith Signs",
    "wof:placetype":"venue"
},
  "geometry": {"coordinates":[-122.391617,37.745734],"type":"Point"}
}