{
  "type": "Feature",
  "properties": {
    "iso:country":"US",
    "sg:address":"2250 Taraval Street",
    "sg:city":"San Francisco",
    "sg:classifiers":[
        {
            "category":"Personal",
            "subcategory":"Beauty Salon",
            "type":"Services"
        }
    ],
    "sg:phone":"+1 415 566 8227",
    "sg:postcode":"94116",
    "sg:province":"CA",
    "sg:tags":[
        "hair"
    ],
    "wof:name":"Super Rainbow Beauty Salon",
    "wof:placetype":"venue"
},
  "geometry": {"coordinates":[-122.49099699999999,37.7425],"type":"Point"}
}