{
  "type": "Feature",
  "properties": {
    "addr:full":"330 N Lantana St Camarillo CA 93010",
    "addr:housenumber":"330",
    "addr:postcode":"93010",
    "addr:street":"N Lantana St",
    "iso:country":"US",
    "sg:address":"330 N Lantana St",
    "sg:city":"Camarillo",
    "sg:classifiers":[
        {
            "category":"Retail",
            "subcategory":"Auto Repair",
            "type":"Services"
        }
    ],
    "sg:phone":"+1 805 482 4521",
    "sg:postcode":"93010",
    "sg:province":"CA",
    "sg:tags":[
        "body",
        "automobile",
        "painting",
        "repairing"
    ],
    "wof:name":"Paintin' Place",
    "wof:placetype":"venue"
},
  "geometry": {"coordinates":[-119.054706,34.237479],"type":"Point"}
}