{
  "type": "Feature",
  "properties": {
    "iso:country":"US",
    "sg:address":"55 Prairie Falcon",
    "sg:city":"Aliso Viejo",
    "sg:classifiers":[
        {
            "category":"Professional",
            "subcategory":"Employment Agencies",
            "type":"Services"
        }
    ],
    "sg:phone":"+1 949 707 4585",
    "sg:postcode":"92656",
    "sg:province":"CA",
    "wof:name":"First Priority",
    "wof:placetype":"venue"
},
  "geometry": {"coordinates":[-117.737999,33.604801],"type":"Point"}
}