{
  "type": "Feature",
  "properties": {
    "addr:full":"295 Sun Haven Pl Manteca CA 95337",
    "addr:housenumber":"295",
    "addr:postcode":"95337",
    "addr:street":"Sun Haven Pl",
    "iso:country":"US",
    "sg:address":"295 Sun Haven Pl",
    "sg:city":"Manteca",
    "sg:classifiers":[
        {
            "category":"Real Estate",
            "subcategory":"Real Estate Services",
            "type":"Services"
        }
    ],
    "sg:phone":"+1 209 239 9538",
    "sg:postcode":"95337",
    "sg:province":"CA",
    "sg:tags":[
        "company",
        "title"
    ],
    "wof:name":"Old Republic Title Co",
    "wof:placetype":"venue"
},
  "geometry": {"coordinates":[-121.230188,37.801247],"type":"Point"}
}