{
  "type": "Feature",
  "properties": {
    "addr:full":"320 10th St Ste 234 Oakland CA 94607",
    "addr:housenumber":"320",
    "addr:postcode":"94607",
    "addr:street":"10Th St Ste 234",
    "iso:country":"US",
    "sg:address":"320 10th St Ste 234",
    "sg:city":"Oakland",
    "sg:classifiers":[
        {
            "category":"Health Services",
            "subcategory":"Health Practitioner",
            "type":"Services"
        }
    ],
    "sg:phone":"+1 510 268 9989",
    "sg:postcode":"94607",
    "sg:province":"CA",
    "sg:tags":[
        "acupuncture",
        "traditional",
        "medicine",
        "chinese"
    ],
    "wof:name":"Zheng Li Zhou",
    "wof:placetype":"venue"
},
  "geometry": {"coordinates":[-122.26965,37.800425],"type":"Point"}
}