{
  "type": "Feature",
  "properties": {
    "addr:full":"275 N Valeria St Fresno CA 93701",
    "addr:housenumber":"275",
    "addr:postcode":"93701",
    "addr:street":"N Valeria St",
    "iso:country":"US",
    "sg:address":"275 N Valeria St",
    "sg:city":"Fresno",
    "sg:classifiers":[
        {
            "category":"Taxi",
            "type":"Transportation"
        }
    ],
    "sg:phone":"+1 559 222 1515",
    "sg:postcode":"93701",
    "sg:province":"CA",
    "sg:tags":[
        "taxicab"
    ],
    "wof:name":"Fiesta Cab Co",
    "wof:placetype":"venue"
},
  "geometry": {"coordinates":[-119.784943,36.745488],"type":"Point"}
}