{
  "type": "Feature",
  "properties": {
    "iso:country":"US",
    "sg:address":"325 E Paige Ave",
    "sg:city":"Tulare",
    "sg:classifiers":[
        {
            "category":"Retail",
            "subcategory":"Repair Shop",
            "type":"Services"
        }
    ],
    "sg:phone":"+1 559 688 4997",
    "sg:postcode":"93274",
    "sg:province":"CA",
    "sg:tags":[
        "equipment",
        "dairy",
        "supply"
    ],
    "wof:name":"Rossiter Construction",
    "wof:placetype":"venue"
},
  "geometry": {"coordinates":[-119.340321,36.182082],"type":"Point"}
}