{
  "type": "Feature",
  "properties": {
    "addr:full":"2439 Valine Ln Chico CA 95928",
    "addr:housenumber":"2439",
    "addr:postcode":"95928",
    "addr:street":"Valine Ln",
    "iso:country":"US",
    "sg:address":"2439 Valine Ln",
    "sg:city":"Chico",
    "sg:classifiers":[
        {
            "category":"Food & Beverages",
            "subcategory":"Liquor & Beverages",
            "type":"Retail Goods"
        }
    ],
    "sg:phone":"+1 530 566 9878",
    "sg:postcode":"95928",
    "sg:province":"CA",
    "wof:name":"MGM Packages",
    "wof:placetype":"venue"
},
  "geometry": {"coordinates":[-121.81734299999999,39.713533],"type":"Point"}
}