{
  "type": "Feature",
  "properties": {
    "iso:country":"US",
    "sg:address":"6256 N 1st St",
    "sg:city":"Fresno",
    "sg:classifiers":[
        {
            "category":"Health Services",
            "subcategory":"Doctor",
            "type":"Services"
        }
    ],
    "sg:phone":"+1 559 432 1833",
    "sg:postcode":"93710",
    "sg:province":"CA",
    "sg:tags":[
        "dentist"
    ],
    "wof:name":"Terry C Loeffler DDS",
    "wof:placetype":"venue"
},
  "geometry": {"coordinates":[-119.772178,36.826415],"type":"Point"}
}