{
  "type": "Feature",
  "properties": {
    "addr:full":"1484 Gardenia Ave Camarillo CA 93010",
    "addr:housenumber":"1484",
    "addr:postcode":"93010",
    "addr:street":"Gardenia Ave",
    "iso:country":"US",
    "sg:address":"1484 Gardenia Ave",
    "sg:city":"Camarillo",
    "sg:classifiers":[
        {
            "category":"Professional",
            "subcategory":"Art Services",
            "type":"Services"
        }
    ],
    "sg:phone":"+1 805 389 8902",
    "sg:postcode":"93010",
    "sg:province":"CA",
    "sg:tags":[
        "graphic",
        "designer"
    ],
    "wof:name":"Creative Alliance",
    "wof:placetype":"venue"
},
  "geometry": {"coordinates":[-119.05021000000001,34.240134],"type":"Point"}
}