{
  "type": "Feature",
  "properties": {
    "iso:country":"US",
    "sg:address":"497 Reservation Rd",
    "sg:city":"Marina",
    "sg:classifiers":[
        {
            "category":"Building & Trades",
            "subcategory":"Equipment Rental",
            "type":"Services"
        }
    ],
    "sg:phone":"+1 831 384 4111",
    "sg:postcode":"93933",
    "sg:province":"CA",
    "sg:tags":[
        "yard"
    ],
    "wof:name":"U-Haul Co",
    "wof:placetype":"venue"
},
  "geometry": {"coordinates":[-121.78089,36.678824],"type":"Point"}
}