{
  "type": "Feature",
  "properties": {
    "addr:full":"5000 S Central Avenue Los Angeles CA 90011",
    "addr:housenumber":"5000",
    "addr:postcode":"90011",
    "addr:street":"S Central Avenue",
    "iso:country":"US",
    "sg:address":"5000 S Central Avenue",
    "sg:city":"Los Angeles",
    "sg:classifiers":[
        {
            "category":"Food & Beverages",
            "subcategory":"Liquor & Beverages",
            "type":"Retail Goods"
        }
    ],
    "sg:phone":"+1 323 231 4700",
    "sg:postcode":"90011",
    "sg:province":"CA",
    "sg:tags":[
        "beer",
        "spirit",
        "wine"
    ],
    "wof:name":"Central Liquor Market",
    "wof:placetype":"venue"
},
  "geometry": {"coordinates":[-118.25658799999999,33.997818],"type":"Point"}
}