{
  "type": "Feature",
  "properties": {
    "addr:full":"147 Atlantic Ave Pittsburg CA 94565",
    "addr:housenumber":"147",
    "addr:postcode":"94565",
    "addr:street":"Atlantic Ave",
    "iso:country":"US",
    "sg:address":"147 Atlantic Ave",
    "sg:city":"Pittsburg",
    "sg:classifiers":[
        {
            "category":"Food & Beverages",
            "subcategory":"Liquor & Beverages",
            "type":"Retail Goods"
        }
    ],
    "sg:phone":"+1 925 432 6700",
    "sg:postcode":"94565",
    "sg:province":"CA",
    "wof:name":"Rice Wine & Liquors",
    "wof:placetype":"venue"
},
  "geometry": {"coordinates":[-121.892112,38.008129],"type":"Point"}
}