{
  "type": "Feature",
  "properties": {
    "addr:full":"2020 Alameda Padre Serra Santa Barbara CA 93103",
    "addr:housenumber":"2020",
    "addr:postcode":"93103",
    "addr:street":"Alameda Padre Serra",
    "iso:country":"US",
    "sg:address":"2020 Alameda Padre Serra",
    "sg:city":"Santa Barbara",
    "sg:classifiers":[
        {
            "category":"Real Estate",
            "subcategory":"Architect",
            "type":"Services"
        }
    ],
    "sg:phone":"+1 805 966 1547",
    "sg:postcode":"93103",
    "sg:province":"CA",
    "sg:website":"www.b3architects.com",
    "wof:name":"B 3 Architects",
    "wof:placetype":"venue"
},
  "geometry": {"coordinates":[-119.70797899999999,34.438482],"type":"Point"}
}