{
  "type": "Feature",
  "properties": {
    "addr:full":"929 N Main St Salinas CA 93906",
    "addr:housenumber":"929",
    "addr:postcode":"93906",
    "addr:street":"N Main St",
    "iso:country":"US",
    "sg:address":"929 N Main St",
    "sg:city":"Salinas",
    "sg:classifiers":[
        {
            "category":"Health Services",
            "subcategory":"Doctor",
            "type":"Services"
        }
    ],
    "sg:phone":"+1 831 783 1336",
    "sg:postcode":"93906",
    "sg:province":"CA",
    "sg:tags":[
        "dentist"
    ],
    "wof:name":"Salinas Dental Care",
    "wof:placetype":"venue"
},
  "geometry": {"coordinates":[-121.652243,36.692294],"type":"Point"}
}