{
  "type": "Feature",
  "properties": {
    "iso:country":"US",
    "sg:address":"2525 Williams St",
    "sg:city":"San Leandro",
    "sg:classifiers":[
        {
            "category":"Building & Trades",
            "subcategory":"Electrical",
            "type":"Services"
        }
    ],
    "sg:phone":"+1 510 635 8868",
    "sg:postcode":"94577",
    "sg:province":"CA",
    "sg:tags":[
        "electrical",
        "contractor"
    ],
    "wof:name":"R A N Electric Inc",
    "wof:placetype":"venue"
},
  "geometry": {"coordinates":[-122.189713,37.705014],"type":"Point"}
}