{
  "type": "Feature",
  "properties": {
    "iso:country":"US",
    "sg:address":"11421 Moorpark St",
    "sg:city":"North Hollywood",
    "sg:classifiers":[
        {
            "category":"Personal",
            "subcategory":"Massage",
            "type":"Services"
        }
    ],
    "sg:phone":"+1 818 763 8803",
    "sg:postcode":"91602",
    "sg:province":"CA",
    "wof:name":"Pretty Body Work",
    "wof:placetype":"venue"
},
  "geometry": {"coordinates":[-118.37990499999999,34.150391],"type":"Point"}
}