{
  "type": "Feature",
  "properties": {
    "iso:country":"US",
    "sg:address":"1112 N Main St",
    "sg:city":"Manteca",
    "sg:classifiers":[
        {
            "category":"Utilities",
            "subcategory":"Mobile Phone",
            "type":"Services"
        }
    ],
    "sg:phone":"+1 209 825 2003",
    "sg:postcode":"95336",
    "sg:province":"CA",
    "sg:tags":[
        "communication",
        "radiotelephone"
    ],
    "wof:name":"Pagers Etc",
    "wof:placetype":"venue"
},
  "geometry": {"coordinates":[-121.217023,37.812238],"type":"Point"}
}