{
  "type": "Feature",
  "properties": {
    "iso:country":"US",
    "sg:address":"5363 Balboa Blvd",
    "sg:city":"Encino",
    "sg:classifiers":[
        {
            "category":"Health Services",
            "subcategory":"Doctor",
            "type":"Services"
        }
    ],
    "sg:phone":"+1 818 783 1800",
    "sg:postcode":"91316",
    "sg:province":"CA",
    "sg:tags":[
        "physician",
        "surgeon"
    ],
    "wof:name":"Robert B Shpiner MD",
    "wof:placetype":"venue"
},
  "geometry": {"coordinates":[-118.50116800000001,34.170235],"type":"Point"}
}