{
  "type": "Feature",
  "properties": {
    "iso:country":"US",
    "sg:address":"5075 Shoreham Place # 260",
    "sg:city":"San Diego",
    "sg:classifiers":[
        {
            "category":"Banks & Credit Unions",
            "subcategory":"Financial Services",
            "type":"Services"
        }
    ],
    "sg:phone":"+1 619 806 8646",
    "sg:postcode":"92122",
    "sg:province":"CA",
    "sg:tags":[
        "broker",
        "mortgage"
    ],
    "sg:website":"www.sandiegohomeloans.biz/",
    "wof:name":"Sandy Tremble - Guild Mortgage Company",
    "wof:placetype":"venue"
},
  "geometry": {"coordinates":[-117.18474500000001,32.852684],"type":"Point"}
}