{
  "type": "Feature",
  "properties": {
    "iso:country":"US",
    "sg:address":"43 Cayetano St",
    "sg:city":"Watsonville",
    "sg:classifiers":[
        {
            "category":"Professional",
            "type":"Services"
        }
    ],
    "sg:phone":"+1 831 722 0149",
    "sg:postcode":"95076",
    "sg:province":"CA",
    "wof:name":"Sally Rugerio Placido",
    "wof:placetype":"venue"
},
  "geometry": {"coordinates":[-121.751398,36.901418],"type":"Point"}
}