{
  "type": "Feature",
  "properties": {
    "iso:country":"US",
    "sg:address":"3260 Corporate Vw",
    "sg:city":"Vista",
    "sg:classifiers":[
        {
            "category":"Professional",
            "type":"Services"
        }
    ],
    "sg:phone":"+1 760 734 4500",
    "sg:postcode":"92081",
    "sg:province":"CA",
    "sg:tags":[
        "establishment"
    ],
    "wof:name":"Rene Van Rems Inc",
    "wof:placetype":"venue"
},
  "geometry": {"coordinates":[-117.225994,33.134244],"type":"Point"}
}