{
  "type": "Feature",
  "properties": {
    "iso:country":"US",
    "sg:address":"1409 R St",
    "sg:city":"Sacramento",
    "sg:classifiers":[
        {
            "category":"Shopping",
            "type":"Retail Goods"
        }
    ],
    "sg:phone":"+1 916 443 9080",
    "sg:postcode":"95811",
    "sg:province":"CA",
    "sg:tags":[
        "mural"
    ],
    "wof:name":"Lunia Blue Graphics",
    "wof:placetype":"venue"
},
  "geometry": {"coordinates":[-121.490441,38.569737],"type":"Point"}
}