{
  "type": "Feature",
  "properties": {
    "addr:full":"856 Manhattan Beach Blvd Manhattan Beach CA 90266",
    "addr:housenumber":"856",
    "addr:postcode":"90266",
    "addr:street":"Manhattan Beach Blvd",
    "iso:country":"US",
    "sg:address":"856 Manhattan Beach Blvd",
    "sg:city":"Manhattan Beach",
    "sg:classifiers":[
        {
            "category":"Wholesale",
            "subcategory":"Durable Goods & Equipment",
            "type":"Manufacturing & Wholesale Goods"
        }
    ],
    "sg:phone":"+1 310 546 3303",
    "sg:postcode":"90266",
    "sg:province":"CA",
    "sg:tags":[
        "representative",
        "manufacturer"
    ],
    "wof:name":"Coastline Sales",
    "wof:placetype":"venue"
},
  "geometry": {"coordinates":[-118.400932,33.887303],"type":"Point"}
}