{
  "type": "Feature",
  "properties": {
    "iso:country":"US",
    "sg:address":"2001 Fortune Dr",
    "sg:city":"San Jose",
    "sg:classifiers":[
        {
            "category":"Manufacturing",
            "subcategory":"Tools & Machinery",
            "type":"Manufacturing & Wholesale Goods"
        }
    ],
    "sg:phone":"+1 408 232 6600",
    "sg:postcode":"95131",
    "sg:province":"CA",
    "sg:tags":[
        "equipment",
        "peripheral",
        "computer",
        "storage",
        "mfg"
    ],
    "sg:website":"www.mmctechnology.com",
    "wof:name":"MMC Technology Inc",
    "wof:placetype":"venue"
},
  "geometry": {"coordinates":[-121.89444899999999,37.401068],"type":"Point"}
}