{
  "type": "Feature",
  "properties": {
    "iso:country":"US",
    "sg:address":"4444 S K St",
    "sg:city":"Tulare",
    "sg:classifiers":[
        {
            "category":"Building & Trades",
            "subcategory":"Electrical",
            "type":"Services"
        }
    ],
    "sg:phone":"+1 559 685 2400",
    "sg:postcode":"93274",
    "sg:province":"CA",
    "sg:tags":[
        "electric",
        "contractor"
    ],
    "wof:name":"Ace Electric Inc",
    "wof:placetype":"venue"
},
  "geometry": {"coordinates":[-119.336517,36.16936],"type":"Point"}
}