{
  "type": "Feature",
  "properties": {
    "iso:country":"US",
    "sg:address":"320 10th St",
    "sg:city":"Petaluma",
    "sg:classifiers":[
        {
            "category":"Building & Trades",
            "subcategory":"Construction",
            "type":"Services"
        }
    ],
    "sg:phone":"+1 415 472 3848",
    "sg:postcode":"94952",
    "sg:province":"CA",
    "sg:tags":[
        "painter"
    ],
    "wof:name":"Stroke & KOTE Painting",
    "wof:placetype":"venue"
},
  "geometry": {"coordinates":[-122.639161,38.224996],"type":"Point"}
}