{
  "type": "Feature",
  "properties": {
    "iso:country":"US",
    "sg:address":"7 Petaluma Blvd N",
    "sg:city":"Petaluma",
    "sg:classifiers":[
        {
            "category":"Shopping",
            "type":"Retail Goods"
        }
    ],
    "sg:phone":"+1 707 763 5363",
    "sg:postcode":"94952",
    "sg:province":"CA",
    "sg:tags":[
        "cosmetic",
        "perfume"
    ],
    "wof:name":"Moon Essence",
    "wof:placetype":"venue"
},
  "geometry": {"coordinates":[-122.63928900000001,38.233328],"type":"Point"}
}