{
  "type": "Feature",
  "properties": {
    "addr:full":"4240 El Camino Real Atascadero CA 93422",
    "addr:housenumber":"4240",
    "addr:postcode":"93422",
    "addr:street":"El Camino Real",
    "iso:country":"US",
    "sg:address":"4240 El Camino Real",
    "sg:city":"Atascadero",
    "sg:classifiers":[
        {
            "category":"Restaurant",
            "type":"Food & Drink"
        }
    ],
    "sg:phone":"+1 805 464 2220",
    "sg:postcode":"93422",
    "sg:province":"CA",
    "sg:website":"http://www.dansthegrubshack.com/",
    "wof:name":"Dan's The Grub Shack",
    "wof:placetype":"venue"
},
  "geometry": {"coordinates":[-120.682508,35.498763],"type":"Point"}
}