{
  "type": "Feature",
  "properties": {
    "iso:country":"US",
    "sg:address":"3608 Via Palomino",
    "sg:city":"Palos Verdes Peninsula",
    "sg:classifiers":[
        {
            "category":"Real Estate",
            "subcategory":"Real Estate Agent",
            "type":"Services"
        }
    ],
    "sg:phone":"+1 310 378 3055",
    "sg:postcode":"90274",
    "sg:province":"CA",
    "wof:name":"Betty Biddick Realtor",
    "wof:placetype":"venue"
},
  "geometry": {"coordinates":[-118.367774,33.799321],"type":"Point"}
}