{
  "type": "Feature",
  "properties": {
    "iso:country":"US",
    "sg:address":"3177 Padaro Ln",
    "sg:city":"Carpinteria",
    "sg:classifiers":[
        {
            "category":"Shopping",
            "subcategory":"Pharmacy",
            "type":"Retail Goods"
        }
    ],
    "sg:phone":"+1 805 566 4749",
    "sg:postcode":"93013",
    "sg:province":"CA",
    "sg:tags":[
        "pharmaceutical",
        "consultant"
    ],
    "wof:name":"Amer & Co",
    "wof:placetype":"venue"
},
  "geometry": {"coordinates":[-119.567676,34.41605],"type":"Point"}
}