{
  "type": "Feature",
  "properties": {
    "addr:full":"1015 Hope St # A South Pasadena CA 91030",
    "addr:housenumber":"1015",
    "addr:postcode":"91030",
    "addr:street":"Hope St # A",
    "iso:country":"US",
    "sg:address":"1015 Hope St # A",
    "sg:city":"South Pasadena",
    "sg:classifiers":[
        {
            "category":"Real Estate",
            "subcategory":"Real Estate Agent",
            "type":"Services"
        }
    ],
    "sg:phone":"+1 323 254 2206",
    "sg:postcode":"91030",
    "sg:province":"CA",
    "sg:website":"www.lascasasrealty.com",
    "wof:name":"Las Casas Realty Inc",
    "wof:placetype":"venue"
},
  "geometry": {"coordinates":[-118.156542,34.116507],"type":"Point"}
}