{
  "type": "Feature",
  "properties": {
    "addr:full":"2163 Virginia St Berkeley CA 94709",
    "addr:housenumber":"2163",
    "addr:postcode":"94709",
    "addr:street":"Virginia St",
    "iso:country":"US",
    "sg:address":"2163 Virginia St",
    "sg:city":"Berkeley",
    "sg:classifiers":[
        {
            "category":"Food & Beverages",
            "subcategory":"Liquor & Beverages",
            "type":"Retail Goods"
        },
        {
            "category":"Wholesale",
            "subcategory":"Wine & Distilled Alcoholic Beverages",
            "type":"Manufacturing & Wholesale Goods"
        }
    ],
    "sg:phone":"+1 510 849 9861",
    "sg:postcode":"94709",
    "sg:province":"CA",
    "sg:tags":[
        "broker"
    ],
    "wof:name":"Joli Vin",
    "wof:placetype":"venue"
},
  "geometry": {"coordinates":[-122.267363,37.876789],"type":"Point"}
}