{
  "type": "Feature",
  "properties": {
    "addr:full":"771 E 14th St Los Angeles CA 90021",
    "addr:housenumber":"771",
    "addr:postcode":"90021",
    "addr:street":"E 14Th St",
    "iso:country":"US",
    "sg:address":"771 E 14th St",
    "sg:city":"Los Angeles",
    "sg:classifiers":[
        {
            "category":"Shopping",
            "subcategory":"Clothing, Apparel, & Fashions",
            "type":"Retail Goods"
        }
    ],
    "sg:phone":"+1 213 749 7686",
    "sg:postcode":"90021",
    "sg:province":"CA",
    "wof:name":"California Dream Co Inc",
    "wof:placetype":"venue"
},
  "geometry": {"coordinates":[-118.251994,34.031148],"type":"Point"}
}