{
  "type": "Feature",
  "properties": {
    "iso:country":"US",
    "sg:address":"616 W 3rd Ave",
    "sg:city":"Escondido",
    "sg:classifiers":[
        {
            "category":"Building & Trades",
            "subcategory":"Plumbing",
            "type":"Services"
        }
    ],
    "sg:phone":"+1 760 871 9800",
    "sg:postcode":"92025",
    "sg:province":"CA",
    "sg:tags":[
        "contractor"
    ],
    "wof:name":"Paschall Mechanical",
    "wof:placetype":"venue"
},
  "geometry": {"coordinates":[-117.088121,33.115963],"type":"Point"}
}