{
  "type": "Feature",
  "properties": {
    "iso:country":"US",
    "sg:address":"2175 Ocean Dr",
    "sg:city":"Oxnard",
    "sg:phone":"+1 805 320 7750",
    "sg:postcode":"93035",
    "sg:province":"CA",
    "wof:name":"Jj Properties",
    "wof:placetype":"venue"
},
  "geometry": {"coordinates":[-119.222048,34.156048],"type":"Point"}
}