{
  "type": "Feature",
  "properties": {
    "addr:full":"2175 Ocean Dr Oxnard CA 93035",
    "addr:housenumber":"2175",
    "addr:postcode":"93035",
    "addr:street":"Ocean Dr",
    "iso:country":"US",
    "sg:address":"2175 Ocean Dr",
    "sg:city":"Oxnard",
    "sg:phone":"+1 805 320 7750",
    "sg:postcode":"93035",
    "sg:province":"CA",
    "wof:name":"Jj Properties",
    "wof:placetype":"venue"
},
  "geometry": {"coordinates":[-119.222048,34.156048],"type":"Point"}
}