{
  "type": "Feature",
  "properties": {
    "iso:country":"US",
    "sg:address":"3615 W. 3rd St",
    "sg:city":"Los Angeles",
    "sg:classifiers":[
        {
            "category":"Utilities",
            "subcategory":"Recycling",
            "type":"Services"
        }
    ],
    "sg:phone":"+1 213 393 6893",
    "sg:postcode":"90020",
    "sg:province":"CA",
    "wof:name":"Catalina Bike Shop",
    "wof:placetype":"venue"
},
  "geometry": {"coordinates":[-118.294752,34.069031],"type":"Point"}
}