{
  "type": "Feature",
  "properties": {
    "addr:full":"4301 Hacienda Dr Pleasanton CA 94588",
    "addr:housenumber":"4301",
    "addr:postcode":"94588",
    "addr:street":"Hacienda Dr",
    "iso:country":"US",
    "sg:address":"4301 Hacienda Dr",
    "sg:city":"Pleasanton",
    "sg:phone":"+1 800 221 5626",
    "sg:postcode":"94588",
    "sg:province":"CA",
    "sg:website":"http://www.cherrycreekloans.com",
    "wof:name":"Cherry Creek Mortgage",
    "wof:placetype":"venue"
},
  "geometry": {"coordinates":[-121.89444,37.69454],"type":"Point"}
}