{
  "type": "Feature",
  "properties": {
    "addr:full":"12747 Ave 416 Orosi CA 93647",
    "addr:housenumber":"12747",
    "addr:postcode":"93647",
    "addr:street":"Ave 416",
    "iso:country":"US",
    "sg:address":"12747 Ave 416",
    "sg:city":"Orosi",
    "sg:classifiers":[
        {
            "category":"Restaurant",
            "type":"Food & Drink"
        }
    ],
    "sg:phone":"+1 559 528 4897",
    "sg:postcode":"93647",
    "sg:province":"CA",
    "wof:name":"El Cesar",
    "wof:placetype":"venue"
},
  "geometry": {"coordinates":[-119.287374,36.544733],"type":"Point"}
}