{
  "type": "Feature",
  "properties": {
    "addr:full":"247 E Canal Dr Turlock CA 95380",
    "addr:housenumber":"247",
    "addr:postcode":"95380",
    "addr:street":"E Canal Dr",
    "iso:country":"US",
    "sg:address":"247 E Canal Dr",
    "sg:city":"Turlock",
    "sg:classifiers":[
        {
            "category":"Recreation",
            "type":"Entertainment"
        }
    ],
    "sg:phone":"+1 209 667 9908",
    "sg:postcode":"95380",
    "sg:province":"CA",
    "sg:tags":[
        "hall",
        "auditorium"
    ],
    "wof:name":"War Memorial Auditorium",
    "wof:placetype":"venue"
},
  "geometry": {"coordinates":[-120.84616200000001,37.5006],"type":"Point"}
}