{
  "type": "Feature",
  "properties": {
    "iso:country":"US",
    "sg:address":"1470 Crest Dr",
    "sg:city":"Altadena",
    "sg:classifiers":[
        {
            "category":"Banks & Credit Unions",
            "subcategory":"Investment Brokerage",
            "type":"Services"
        }
    ],
    "sg:phone":"+1 626 794 9099",
    "sg:postcode":"91001",
    "sg:province":"CA",
    "sg:tags":[
        "investing"
    ],
    "wof:name":"Family Trust Services",
    "wof:placetype":"venue"
},
  "geometry": {"coordinates":[-118.119773,34.191807],"type":"Point"}
}