{
  "type": "Feature",
  "properties": {
    "iso:country":"US",
    "sg:address":"1015 Sperry Ave",
    "sg:city":"Patterson",
    "sg:classifiers":[
        {
            "category":"Restaurant",
            "type":"Food & Drink"
        }
    ],
    "sg:menulink":"http://www.allmenus.com/ca/patterson/69279-mountain-mikes-pizza/menu/",
    "sg:phone":"+1 209 892 8400",
    "sg:postcode":"95363",
    "sg:province":"CA",
    "sg:tags":[
        "american",
        "pizza"
    ],
    "wof:name":"Mountain Mike's Pizza",
    "wof:placetype":"venue"
},
  "geometry": {"coordinates":[-121.14137700000001,37.465398],"type":"Point"}
}