{
  "type": "Feature",
  "properties": {
    "addr:full":"6500 Watt Ave North Highlands CA 95660",
    "addr:housenumber":"6500",
    "addr:postcode":"95660",
    "addr:street":"Watt Ave",
    "iso:country":"US",
    "sg:address":"6500 Watt Ave",
    "sg:city":"North Highlands",
    "sg:classifiers":[
        {
            "category":"Cinema",
            "subcategory":"Movie Rental",
            "type":"Entertainment"
        }
    ],
    "sg:phone":"+1 916 344 5500",
    "sg:postcode":"95660",
    "sg:province":"CA",
    "sg:tags":[
        "game",
        "video"
    ],
    "wof:name":"Enterprise Rent-A-Car",
    "wof:placetype":"venue"
},
  "geometry": {"coordinates":[-121.383003,38.685101],"type":"Point"}
}