{
  "type": "Feature",
  "properties": {
    "addr:full":"1012 Pacific St San Luis Obispo CA 93401",
    "addr:housenumber":"1012",
    "addr:postcode":"93401",
    "addr:street":"Pacific St",
    "iso:country":"US",
    "sg:address":"1012 Pacific St",
    "sg:city":"San Luis Obispo",
    "sg:classifiers":[
        {
            "category":"Professional",
            "subcategory":"Secretarial Services",
            "type":"Services"
        }
    ],
    "sg:phone":"+1 805 546 8468",
    "sg:postcode":"93401",
    "sg:province":"CA",
    "sg:tags":[
        "convention",
        "court",
        "reporter"
    ],
    "wof:name":"Mc Daniel Reporting",
    "wof:placetype":"venue"
},
  "geometry": {"coordinates":[-120.658255,35.280412],"type":"Point"}
}