{
  "type": "Feature",
  "properties": {
    "iso:country":"US",
    "sg:address":"8431 Nandina Way",
    "sg:city":"Antelope",
    "sg:classifiers":[
        {
            "category":"Professional",
            "subcategory":"Management & Consulting",
            "type":"Services"
        }
    ],
    "sg:phone":"+1 916 338 1597",
    "sg:postcode":"95843",
    "sg:province":"CA",
    "sg:tags":[
        "marketing",
        "consultant"
    ],
    "wof:name":"Mc Clellan Marketing Group",
    "wof:placetype":"venue"
},
  "geometry": {"coordinates":[-121.393135,38.722866],"type":"Point"}
}