{
  "type": "Feature",
  "properties": {
    "addr:full":"604 Torrance Blvd Redondo Beach CA 90277",
    "addr:housenumber":"604",
    "addr:postcode":"90277",
    "addr:street":"Torrance Blvd",
    "iso:country":"US",
    "sg:address":"604 Torrance Blvd",
    "sg:city":"Redondo Beach",
    "sg:classifiers":[
        {
            "category":"Food & Beverages",
            "subcategory":"Liquor & Beverages",
            "type":"Retail Goods"
        }
    ],
    "sg:phone":"+1 310 316 7644",
    "sg:postcode":"90277",
    "sg:province":"CA",
    "sg:tags":[
        "beer",
        "spirit",
        "wine"
    ],
    "wof:name":"Vip Liquor & Market",
    "wof:placetype":"venue"
},
  "geometry": {"coordinates":[-118.38200399999999,33.837502],"type":"Point"}
}