{
  "type": "Feature",
  "properties": {
    "addr:full":"256 E Java Drive Sunnyvale CA 94089",
    "addr:housenumber":"256",
    "addr:postcode":"94089",
    "addr:street":"E Java Drive",
    "iso:country":"US",
    "sg:address":"256 E Java Drive",
    "sg:city":"Sunnyvale",
    "sg:classifiers":[
        {
            "category":"Retail",
            "subcategory":"Laundry & Dry Cleaning",
            "type":"Services"
        }
    ],
    "sg:phone":"+1 408 745 1868",
    "sg:postcode":"94089",
    "sg:province":"CA",
    "wof:name":"Java Cleaners",
    "wof:placetype":"venue"
},
  "geometry": {"coordinates":[-122.016318,37.411071],"type":"Point"}
}