{
  "type": "Feature",
  "properties": {
    "iso:country":"US",
    "sg:address":"9895 Stephens St",
    "sg:city":"Delhi",
    "sg:classifiers":[
        {
            "category":"Bars & Pubs",
            "type":"Food & Drink"
        }
    ],
    "sg:phone":"+1 209 667 8424",
    "sg:postcode":"95315",
    "sg:province":"CA",
    "sg:tags":[
        "lounge",
        "cocktail"
    ],
    "wof:name":"Bert's Place",
    "wof:placetype":"venue"
},
  "geometry": {"coordinates":[-120.779129,37.432815],"type":"Point"}
}