{
  "type": "Feature",
  "properties": {
    "addr:full":"5500 N Cerritos Ave Azusa CA 91702",
    "addr:housenumber":"5500",
    "addr:postcode":"91702",
    "addr:street":"N Cerritos Ave",
    "iso:country":"US",
    "sg:address":"5500 N Cerritos Ave",
    "sg:city":"Azusa",
    "sg:classifiers":[
        {
            "category":"Education",
            "subcategory":"School",
            "type":"Public Place"
        }
    ],
    "sg:phone":"+1 626 815 5184",
    "sg:postcode":"91702",
    "sg:province":"CA",
    "wof:name":"Center Middle School",
    "wof:placetype":"venue"
},
  "geometry": {"coordinates":[-117.89883,34.113168],"type":"Point"}
}