{
  "type": "Feature",
  "properties": {
    "iso:country":"US",
    "sg:address":"823 S Westvale Dr",
    "sg:city":"Anaheim",
    "sg:classifiers":[
        {
            "category":"Manufacturing",
            "subcategory":"Musical Instruments",
            "type":"Manufacturing & Wholesale Goods"
        }
    ],
    "sg:phone":"+1 714 827 2535",
    "sg:postcode":"92804",
    "sg:province":"CA",
    "sg:tags":[
        "mfg"
    ],
    "wof:name":"Double D Percussions",
    "wof:placetype":"venue"
},
  "geometry": {"coordinates":[-118.00743,33.819791],"type":"Point"}
}