{
  "type": "Feature",
  "properties": {
    "iso:country":"US",
    "sg:address":"611 Veterans Blvd",
    "sg:city":"Redwood City",
    "sg:classifiers":[
        {
            "category":"Insurance",
            "subcategory":"Insurance Agent",
            "type":"Services"
        }
    ],
    "sg:phone":"+1 650 306 4050",
    "sg:postcode":"94063",
    "sg:province":"CA",
    "sg:tags":[
        "agency"
    ],
    "wof:name":"Allstate",
    "wof:placetype":"venue"
},
  "geometry": {"coordinates":[-122.23112500000001,37.49187],"type":"Point"}
}