{
  "type": "Feature",
  "properties": {
    "iso:country":"US",
    "sg:address":"12752 1/2 Oxnard St",
    "sg:city":"North Hollywood",
    "sg:classifiers":[
        {
            "category":"Personal",
            "type":"Services"
        }
    ],
    "sg:phone":"+1 818 980 8281",
    "sg:postcode":"91606",
    "sg:province":"CA",
    "sg:tags":[
        "party",
        "planning",
        "event"
    ],
    "wof:name":"RC Decor",
    "wof:placetype":"venue"
},
  "geometry": {"coordinates":[-118.41057000000001,34.179267],"type":"Point"}
}