{
  "type": "Feature",
  "properties": {
    "addr:full":"65 N Barlow Ln Bishop CA 93514",
    "addr:housenumber":"65",
    "addr:postcode":"93514",
    "addr:street":"N Barlow Ln",
    "iso:country":"US",
    "sg:address":"65 N Barlow Ln",
    "sg:city":"Bishop",
    "sg:classifiers":[
        {
            "category":"Professional",
            "type":"Services"
        }
    ],
    "sg:phone":"+1 760 873 4432",
    "sg:postcode":"93514",
    "sg:province":"CA",
    "sg:tags":[
        "establishment"
    ],
    "wof:name":"Bishop Pauite Tribe Justice",
    "wof:placetype":"venue"
},
  "geometry": {"coordinates":[-118.42298599999999,37.361357],"type":"Point"}
}