{
  "type": "Feature",
  "properties": {
    "addr:full":"426 8th St Petaluma CA 94952",
    "addr:housenumber":"426",
    "addr:postcode":"94952",
    "addr:street":"8Th St",
    "iso:country":"US",
    "sg:address":"426 8th St",
    "sg:city":"Petaluma",
    "sg:classifiers":[
        {
            "category":"Recreation",
            "type":"Entertainment"
        }
    ],
    "sg:phone":"+1 707 778 4519",
    "sg:postcode":"94952",
    "sg:province":"CA",
    "sg:tags":[
        "center"
    ],
    "wof:name":"Cavanagh Recreation Ctr",
    "wof:placetype":"venue"
},
  "geometry": {"coordinates":[-122.63653600000001,38.226072],"type":"Point"}
}