{
  "type": "Feature",
  "properties": {
    "addr:full":"212 S Brand Blvd Glendale CA 91204",
    "addr:housenumber":"212",
    "addr:postcode":"91204",
    "addr:street":"S Brand Blvd",
    "iso:country":"US",
    "sg:address":"212 S Brand Blvd",
    "sg:city":"Glendale",
    "sg:classifiers":[
        {
            "category":"Recreation",
            "subcategory":"Amusement Park",
            "type":"Entertainment"
        },
        {
            "category":"Recreation",
            "subcategory":"Arcade",
            "type":"Entertainment"
        }
    ],
    "sg:phone":"+1 818 502 1731",
    "sg:postcode":"91204",
    "sg:province":"CA",
    "wof:name":"Video West Arcade",
    "wof:placetype":"venue"
},
  "geometry": {"coordinates":[-118.254997,34.144798],"type":"Point"}
}