{
  "type": "Feature",
  "properties": {
    "addr:full":"580 Linne Rd Paso Robles CA 93446",
    "addr:housenumber":"580",
    "addr:postcode":"93446",
    "addr:street":"Linne Rd",
    "iso:country":"US",
    "sg:address":"580 Linne Rd",
    "sg:city":"Paso Robles",
    "sg:classifiers":[
        {
            "category":"Manufacturing",
            "subcategory":"Tools & Machinery",
            "type":"Manufacturing & Wholesale Goods"
        }
    ],
    "sg:phone":"+1 805 226 9546",
    "sg:postcode":"93446",
    "sg:province":"CA",
    "sg:tags":[
        "machine",
        "shop"
    ],
    "wof:name":"L & M Machining Ctr",
    "wof:placetype":"venue"
},
  "geometry": {"coordinates":[-120.642753,35.611988],"type":"Point"}
}