{
  "type": "Feature",
  "properties": {
    "iso:country":"US",
    "sg:address":"21435 Golondrina St",
    "sg:city":"Woodland Hills",
    "sg:classifiers":[
        {
            "category":"Professional",
            "subcategory":"Computer Services",
            "type":"Services"
        }
    ],
    "sg:phone":"+1 818 347 1119",
    "sg:postcode":"91364",
    "sg:province":"CA",
    "sg:tags":[
        "hardware",
        "provider",
        "internet",
        "software"
    ],
    "sg:website":"www.kadegconsulting.com",
    "wof:name":"Kadeg Consulting",
    "wof:placetype":"venue"
},
  "geometry": {"coordinates":[-118.59648300000001,34.147678],"type":"Point"}
}