{
  "type": "Feature",
  "properties": {
    "addr:full":"241 Carl St San Francisco CA 94117",
    "addr:housenumber":"241",
    "addr:postcode":"94117",
    "addr:street":"Carl St",
    "iso:country":"US",
    "sg:address":"241 Carl St",
    "sg:city":"San Francisco",
    "sg:classifiers":[
        {
            "category":"Building & Trades",
            "subcategory":"Landscaping Services",
            "type":"Services"
        }
    ],
    "sg:phone":"+1 415 664 5913",
    "sg:postcode":"94117",
    "sg:province":"CA",
    "sg:tags":[
        "designer",
        "landscape"
    ],
    "wof:name":"Gardenart Group",
    "wof:placetype":"venue"
},
  "geometry": {"coordinates":[-122.453861,37.765244],"type":"Point"}
}