{
  "type": "Feature",
  "properties": {
    "addr:full":"2243 el Sereno Ave Altadena CA 91001",
    "addr:housenumber":"2243",
    "addr:postcode":"91001",
    "addr:street":"El Sereno Ave",
    "iso:country":"US",
    "sg:address":"2243 el Sereno Ave",
    "sg:city":"Altadena",
    "sg:classifiers":[
        {
            "category":"Retail",
            "subcategory":"Car Wash",
            "type":"Services"
        }
    ],
    "sg:phone":"+1 626 797 6970",
    "sg:postcode":"91001",
    "sg:province":"CA",
    "sg:tags":[
        "automobile",
        "detail",
        "clean"
    ],
    "wof:name":"Double D's Auto Care",
    "wof:placetype":"venue"
},
  "geometry": {"coordinates":[-118.15231199999999,34.18454],"type":"Point"}
}