{
  "type": "Feature",
  "properties": {
    "iso:country":"US",
    "sg:address":"700 N Lemoore Ave",
    "sg:city":"Lemoore",
    "sg:classifiers":[
        {
            "category":"Professional",
            "type":"Services"
        }
    ],
    "sg:phone":"+1 559 924 3773",
    "sg:postcode":"93245",
    "sg:province":"CA",
    "sg:tags":[
        "establishment"
    ],
    "wof:name":"Granary",
    "wof:placetype":"venue"
},
  "geometry": {"coordinates":[-119.780798,36.306408],"type":"Point"}
}