{
  "type": "Feature",
  "properties": {
    "iso:country":"US",
    "sg:address":"7243 Engineer Rd",
    "sg:city":"San Diego",
    "sg:classifiers":[
        {
            "category":"Wholesale",
            "subcategory":"Hardware",
            "type":"Manufacturing & Wholesale Goods"
        }
    ],
    "sg:phone":"+1 858 560 0884",
    "sg:postcode":"92111",
    "sg:province":"CA",
    "sg:tags":[
        "refrigeration"
    ],
    "wof:name":"Thermal Products Inc",
    "wof:placetype":"venue"
},
  "geometry": {"coordinates":[-117.160178,32.827083],"type":"Point"}
}