{
  "type": "Feature",
  "properties": {
    "iso:country":"US",
    "sg:address":"27963 Cabot Rd",
    "sg:city":"Laguna Niguel",
    "sg:classifiers":[
        {
            "category":"Manufacturing",
            "subcategory":"Electronics",
            "type":"Manufacturing & Wholesale Goods"
        }
    ],
    "sg:phone":"+1 949 582 3163",
    "sg:postcode":"92677",
    "sg:province":"CA",
    "sg:tags":[
        "equipment",
        "electronic",
        "supply"
    ],
    "sg:website":"www.tsi-ndt.com",
    "wof:name":"Test Systems Intl Inc",
    "wof:placetype":"venue"
},
  "geometry": {"coordinates":[-117.678752,33.559982],"type":"Point"}
}