{
  "type": "Feature",
  "properties": {
    "addr:full":"133 Cascade Falls Dr Folsom CA 95630",
    "addr:housenumber":"133",
    "addr:postcode":"95630",
    "addr:street":"Cascade Falls Dr",
    "iso:country":"US",
    "sg:address":"133 Cascade Falls Dr",
    "sg:city":"Folsom",
    "sg:classifiers":[
        {
            "category":"Personal",
            "subcategory":"Day Spa",
            "type":"Services"
        }
    ],
    "sg:phone":"+1 916 988 5885",
    "sg:postcode":"95630",
    "sg:province":"CA",
    "wof:name":"Khosravifard, Nassrin",
    "wof:placetype":"venue"
},
  "geometry": {"coordinates":[-121.186487,38.701097],"type":"Point"}
}