{
  "type": "Feature",
  "properties": {
    "addr:full":"122 Great Mall Dr Milpitas CA 95035",
    "addr:housenumber":"122",
    "addr:postcode":"95035",
    "addr:street":"Great Mall Dr",
    "iso:country":"US",
    "sg:address":"122 Great Mall Dr",
    "sg:city":"Milpitas",
    "sg:classifiers":[
        {
            "category":"Shopping",
            "subcategory":"Clothing, Apparel, & Fashions",
            "type":"Retail Goods"
        }
    ],
    "sg:phone":"+1 408 956 8744",
    "sg:postcode":"95035",
    "sg:province":"CA",
    "sg:tags":[
        "sportswear"
    ],
    "sg:website":"www.pacsun.com",
    "wof:name":"Pacific Sunwear",
    "wof:placetype":"venue"
},
  "geometry": {"coordinates":[-121.901489,37.419044],"type":"Point"}
}