{
  "type": "Feature",
  "properties": {
    "iso:country":"US",
    "sg:address":"2403 Castillo St",
    "sg:city":"Santa Barbara",
    "sg:classifiers":[
        {
            "category":"Health Services",
            "subcategory":"Doctor",
            "type":"Services"
        }
    ],
    "sg:phone":"+1 805 682 3585",
    "sg:postcode":"93105",
    "sg:province":"CA",
    "sg:tags":[
        "physician",
        "surgeon"
    ],
    "sg:website":"www.santabarbaragi.com",
    "wof:name":"Gastroenterology Consultants",
    "wof:placetype":"venue"
},
  "geometry": {"coordinates":[-119.725485,34.431367],"type":"Point"}
}