{
  "type": "Feature",
  "properties": {
    "iso:country":"US",
    "sg:address":"2263 N Lakewood Blvd",
    "sg:city":"Long Beach",
    "sg:classifiers":[
        {
            "category":"Professional",
            "type":"Services"
        }
    ],
    "sg:phone":"+1 562 961 8877",
    "sg:postcode":"90815",
    "sg:province":"CA",
    "sg:tags":[
        "establishment"
    ],
    "wof:name":"ARC",
    "wof:placetype":"venue"
},
  "geometry": {"coordinates":[-118.14276099999999,33.798188],"type":"Point"}
}