{
  "type": "Feature",
  "properties": {
    "iso:country":"US",
    "sg:address":"9267 Jurupa Rd",
    "sg:city":"Riverside",
    "sg:classifiers":[
        {
            "category":"Autos & Motor Vehicles",
            "subcategory":"Fuel & Gas Station",
            "type":"Retail Goods"
        }
    ],
    "sg:phone":"+1 951 685 0237",
    "sg:postcode":"92509",
    "sg:province":"CA",
    "sg:tags":[
        "oil"
    ],
    "wof:name":"G & M Oil Co",
    "wof:placetype":"venue"
},
  "geometry": {"coordinates":[-117.48607,33.996905],"type":"Point"}
}