{
  "type": "Feature",
  "properties": {
    "iso:country":"US",
    "sg:address":"21777 Ventura Blvd Ste 213",
    "sg:city":"Woodland Hills",
    "sg:classifiers":[
        {
            "category":"Education",
            "subcategory":"Kindergarten",
            "type":"Public Place"
        }
    ],
    "sg:phone":"+1 818 887 9441",
    "sg:postcode":"91364",
    "sg:province":"CA",
    "sg:tags":[
        "school",
        "driving"
    ],
    "wof:name":"Heart To Heart Traffic School",
    "wof:placetype":"venue"
},
  "geometry": {"coordinates":[-118.601997,34.1684],"type":"Point"}
}