{
  "type": "Feature",
  "properties": {
    "iso:country":"US",
    "sg:address":"1247 S San Joaquin St",
    "sg:city":"Stockton",
    "sg:classifiers":[
        {
            "category":"Personal",
            "subcategory":"Beauty Salon",
            "type":"Services"
        }
    ],
    "sg:phone":"+1 209 464 9755",
    "sg:postcode":"95206",
    "sg:province":"CA",
    "wof:name":"Claudia's House Of Beauty",
    "wof:placetype":"venue"
},
  "geometry": {"coordinates":[-121.283858,37.94075],"type":"Point"}
}