{
  "type": "Feature",
  "properties": {
    "addr:full":"1713 Cassidy St Oceanside CA 92054",
    "addr:housenumber":"1713",
    "addr:postcode":"92054",
    "addr:street":"Cassidy St",
    "iso:country":"US",
    "sg:address":"1713 Cassidy St",
    "sg:city":"Oceanside",
    "sg:classifiers":[
        {
            "category":"Travel",
            "subcategory":"Travel Agent",
            "type":"Entertainment"
        }
    ],
    "sg:phone":"+1 760 721 9420",
    "sg:postcode":"92054",
    "sg:province":"CA",
    "sg:tags":[
        "agency"
    ],
    "sg:website":"www.distinctive-cruises.com",
    "wof:name":"Distinctive Cruises",
    "wof:placetype":"venue"
},
  "geometry": {"coordinates":[-117.350998,33.182201],"type":"Point"}
}