{
  "type": "Feature",
  "properties": {
    "addr:full":"16776 Bernardo Center Dr San Diego CA 92128",
    "addr:housenumber":"16776",
    "addr:postcode":"92128",
    "addr:street":"Bernardo Center Dr",
    "iso:country":"US",
    "sg:address":"16776 Bernardo Center Dr",
    "sg:city":"San Diego",
    "sg:classifiers":[
        {
            "category":"Education",
            "subcategory":"School",
            "type":"Public Place"
        }
    ],
    "sg:phone":"+1 858 487 0464",
    "sg:postcode":"92128",
    "sg:province":"CA",
    "wof:name":"Continuing Education Center",
    "wof:placetype":"venue"
},
  "geometry": {"coordinates":[-117.076049,33.017077],"type":"Point"}
}