{
  "type": "Feature",
  "properties": {
    "addr:full":"2018 10th Ave San Francisco CA 94116",
    "addr:housenumber":"2018",
    "addr:postcode":"94116",
    "addr:street":"10Th Ave",
    "iso:country":"US",
    "sg:address":"2018 10th Ave",
    "sg:city":"San Francisco",
    "sg:classifiers":[
        {
            "category":"Professional",
            "type":"Services"
        }
    ],
    "sg:phone":"+1 415 564 9636",
    "sg:postcode":"94116",
    "sg:province":"CA",
    "wof:name":"Andrew Ajschnydrig",
    "wof:placetype":"venue"
},
  "geometry": {"coordinates":[-122.46628,37.749421],"type":"Point"}
}