{
  "type": "Feature",
  "properties": {
    "addr:full":"2118 W Pomona Blvd Pomona CA 91768",
    "addr:housenumber":"2118",
    "addr:postcode":"91768",
    "addr:street":"W Pomona Blvd",
    "iso:country":"US",
    "sg:address":"2118 W Pomona Blvd",
    "sg:city":"Pomona",
    "sg:classifiers":[
        {
            "category":"Shopping",
            "type":"Retail Goods"
        }
    ],
    "sg:phone":"+1 909 397 8880",
    "sg:postcode":"91768",
    "sg:province":"CA",
    "sg:tags":[
        "transportation",
        "merchandise",
        "freight"
    ],
    "wof:name":"Unipack Trading Inc",
    "wof:placetype":"venue"
},
  "geometry": {"coordinates":[-117.78655000000001,34.057866],"type":"Point"}
}