{
  "type": "Feature",
  "properties": {
    "iso:country":"US",
    "sg:address":"1550 el Camino Real",
    "sg:city":"Menlo Park",
    "sg:classifiers":[
        {
            "category":"Banks & Credit Unions",
            "subcategory":"Investment Brokerage",
            "type":"Services"
        }
    ],
    "sg:phone":"+1 650 321 9400",
    "sg:postcode":"94025",
    "sg:province":"CA",
    "sg:tags":[
        "management"
    ],
    "wof:name":"Sequoia Associates",
    "wof:placetype":"venue"
},
  "geometry": {"coordinates":[-122.18865,37.456282],"type":"Point"}
}