{
  "type": "Feature",
  "properties": {
    "addr:full":"2908 Oregon Ct Torrance CA 90503",
    "addr:housenumber":"2908",
    "addr:postcode":"90503",
    "addr:street":"Oregon Ct",
    "iso:country":"US",
    "sg:address":"2908 Oregon Ct",
    "sg:city":"Torrance",
    "sg:classifiers":[
        {
            "category":"Professional",
            "type":"Services"
        },
        {
            "category":"Wholesale",
            "subcategory":"Non-durable Goods",
            "type":"Manufacturing & Wholesale Goods"
        }
    ],
    "sg:phone":"+1 310 618 1231",
    "sg:postcode":"90503",
    "sg:province":"CA",
    "sg:tags":[
        "arts",
        "artist"
    ],
    "sg:website":"www.fortunefa.com",
    "wof:name":"Fortune Fine Art",
    "wof:placetype":"venue"
},
  "geometry": {"coordinates":[-118.338826,33.846341],"type":"Point"}
}