{
  "type": "Feature",
  "properties": {
    "addr:full":"315 E Tulare Ave Visalia CA 93277",
    "addr:housenumber":"315",
    "addr:postcode":"93277",
    "addr:street":"E Tulare Ave",
    "iso:country":"US",
    "sg:address":"315 E Tulare Ave",
    "sg:city":"Visalia",
    "sg:classifiers":[
        {
            "category":"Freight",
            "type":"Transportation"
        }
    ],
    "sg:phone":"+1 559 741 7188",
    "sg:postcode":"93277",
    "sg:province":"CA",
    "sg:tags":[
        "warehouse",
        "self",
        "storage"
    ],
    "wof:name":"Central Ca Warehousing Svc Inc",
    "wof:placetype":"venue"
},
  "geometry": {"coordinates":[-119.288876,36.320058],"type":"Point"}
}