{
  "type": "Feature",
  "properties": {
    "iso:country":"US",
    "sg:address":"1170 3rd St",
    "sg:city":"Atwater",
    "sg:classifiers":[
        {
            "category":"Health Services",
            "subcategory":"Chiropractor",
            "type":"Services"
        }
    ],
    "sg:phone":"+1 209 358 6464",
    "sg:postcode":"95301",
    "sg:province":"CA",
    "wof:name":"Atwater Chiropractic Office",
    "wof:placetype":"venue"
},
  "geometry": {"coordinates":[-120.60862899999999,37.347031],"type":"Point"}
}