{
  "type": "Feature",
  "properties": {
    "addr:full":"2627 Covington Rd San Diego CA 92104",
    "addr:housenumber":"2627",
    "addr:postcode":"92104",
    "addr:street":"Covington Rd",
    "iso:country":"US",
    "sg:address":"2627 Covington Rd",
    "sg:city":"San Diego",
    "sg:classifiers":[
        {
            "category":"Professional",
            "type":"Services"
        }
    ],
    "sg:phone":"+1 619 584 4216",
    "sg:postcode":"92104",
    "sg:province":"CA",
    "wof:name":"Deborah Poole",
    "wof:placetype":"venue"
},
  "geometry": {"coordinates":[-117.118415,32.733113],"type":"Point"}
}