{
  "type": "Feature",
  "properties": {
    "iso:country":"US",
    "sg:address":"46 E Colorado Blvd",
    "sg:city":"Pasadena",
    "sg:classifiers":[
        {
            "category":"Bars & Pubs",
            "type":"Food & Drink"
        },
        {
            "category":"Restaurant",
            "type":"Food & Drink"
        },
        {
            "category":"Bars & Pubs",
            "subcategory":"Wine Bar",
            "type":"Food & Drink"
        }
    ],
    "sg:phone":"+1 626 405 1000",
    "sg:postcode":"91105",
    "sg:province":"CA",
    "sg:tags":[
        "tapa",
        "spanish",
        "basque"
    ],
    "sg:website":"www.barcelonapasadena.com",
    "wof:name":"Bar Celona",
    "wof:placetype":"venue"
},
  "geometry": {"coordinates":[-118.149396,34.14551],"type":"Point"}
}