{
  "type": "Feature",
  "properties": {
    "iso:country":"US",
    "sg:address":"3709 San Gabriel River Pkwy",
    "sg:city":"Pico Rivera",
    "sg:classifiers":[
        {
            "category":"Wholesale",
            "subcategory":"Wine & Distilled Alcoholic Beverages",
            "type":"Manufacturing & Wholesale Goods"
        }
    ],
    "sg:phone":"+1 562 695 6344",
    "sg:postcode":"90660",
    "sg:province":"CA",
    "sg:tags":[
        "broker"
    ],
    "wof:name":"S & H Imports LLC",
    "wof:placetype":"venue"
},
  "geometry": {"coordinates":[-118.06215899999999,34.01349],"type":"Point"}
}