{
  "type": "Feature",
  "properties": {
    "addr:full":"932 E Turmont St Carson CA 90746",
    "addr:housenumber":"932",
    "addr:postcode":"90746",
    "addr:street":"E Turmont St",
    "iso:country":"US",
    "sg:address":"932 E Turmont St",
    "sg:city":"Carson",
    "sg:classifiers":[
        {
            "category":"Professional",
            "subcategory":"Computer Services",
            "type":"Services"
        }
    ],
    "sg:phone":"+1 310 632 6786",
    "sg:postcode":"90746",
    "sg:province":"CA",
    "sg:tags":[
        "consultant",
        "designer"
    ],
    "wof:name":"Systems Operation Solutions",
    "wof:placetype":"venue"
},
  "geometry": {"coordinates":[-118.257295,33.852347],"type":"Point"}
}