{
  "type": "Feature",
  "properties": {
    "iso:country":"US",
    "sg:address":"950 N Diamond Bar Blvd",
    "sg:city":"Diamond Bar",
    "sg:classifiers":[
        {
            "category":"Government",
            "subcategory":"Office",
            "type":"Public Place"
        }
    ],
    "sg:phone":"+1 909 860 7067",
    "sg:postcode":"91765",
    "sg:province":"CA",
    "sg:tags":[
        "state",
        "security"
    ],
    "wof:name":"US Navy Recruiting",
    "wof:placetype":"venue"
},
  "geometry": {"coordinates":[-117.806175,34.035609],"type":"Point"}
}