{
  "type": "Feature",
  "properties": {
    "addr:full":"165 Ely St Oceanside CA 92054",
    "addr:housenumber":"165",
    "addr:postcode":"92054",
    "addr:street":"Ely St",
    "iso:country":"US",
    "sg:address":"165 Ely St",
    "sg:city":"Oceanside",
    "sg:classifiers":[
        {
            "category":"Shopping",
            "subcategory":"Musical Instruments",
            "type":"Retail Goods"
        }
    ],
    "sg:phone":"+1 760 721 3391",
    "sg:postcode":"92054",
    "sg:province":"CA",
    "wof:name":"Mabuhay Videos Plus",
    "wof:placetype":"venue"
},
  "geometry": {"coordinates":[-117.337249,33.213564],"type":"Point"}
}