{
  "type": "Feature",
  "properties": {
    "iso:country":"US",
    "sg:address":"2350 Mission College Blvd",
    "sg:city":"Santa Clara",
    "sg:classifiers":[
        {
            "category":"Communications",
            "type":"Services"
        },
        {
            "category":"Wholesale",
            "subcategory":"Electrical",
            "type":"Manufacturing & Wholesale Goods"
        }
    ],
    "sg:phone":"+1 408 855 8600",
    "sg:postcode":"95054",
    "sg:province":"CA",
    "sg:tags":[
        "communication",
        "radio",
        "system"
    ],
    "wof:name":"A Vision Communications Co",
    "wof:placetype":"venue"
},
  "geometry": {"coordinates":[-121.96659,37.38879],"type":"Point"}
}