{
  "type": "Feature",
  "properties": {
    "addr:full":"3403 Yale Way Fremont CA 94538",
    "addr:housenumber":"3403",
    "addr:postcode":"94538",
    "addr:street":"Yale Way",
    "iso:country":"US",
    "sg:address":"3403 Yale Way",
    "sg:city":"Fremont",
    "sg:classifiers":[
        {
            "category":"Manufacturing",
            "subcategory":"Tools & Machinery",
            "type":"Manufacturing & Wholesale Goods"
        }
    ],
    "sg:phone":"+1 510 656 0387",
    "sg:postcode":"94538",
    "sg:province":"CA",
    "sg:tags":[
        "machine",
        "shop"
    ],
    "sg:website":"www.proswiss.com",
    "wof:name":"Pro-Swiss Machining Mfg",
    "wof:placetype":"venue"
},
  "geometry": {"coordinates":[-121.947588,37.509617],"type":"Point"}
}