{
  "type": "Feature",
  "properties": {
    "iso:country":"US",
    "sg:address":"1203 E Lodi Ave",
    "sg:city":"Lodi",
    "sg:classifiers":[
        {
            "category":"Wholesale",
            "subcategory":"Groceries",
            "type":"Manufacturing & Wholesale Goods"
        }
    ],
    "sg:phone":"+1 209 367 1556",
    "sg:postcode":"95240",
    "sg:province":"CA",
    "wof:name":"Siqueria Wine Company",
    "wof:placetype":"venue"
},
  "geometry": {"coordinates":[-121.287271,38.130056],"type":"Point"}
}