{
  "type": "Feature",
  "properties": {
    "addr:full":"3245 W Imperial Hwy Inglewood CA 90303",
    "addr:housenumber":"3245",
    "addr:postcode":"90303",
    "addr:street":"W Imperial Hwy",
    "iso:country":"US",
    "sg:address":"3245 W Imperial Hwy",
    "sg:city":"Inglewood",
    "sg:classifiers":[
        {
            "category":"Retail",
            "subcategory":"Car Wash",
            "type":"Services"
        }
    ],
    "sg:phone":"+1 310 672 0335",
    "sg:postcode":"90303",
    "sg:province":"CA",
    "wof:name":"Crenshaw Imperial Car Wash Inc",
    "wof:placetype":"venue"
},
  "geometry": {"coordinates":[-118.33000199999999,33.930901],"type":"Point"}
}