{
  "type": "Feature",
  "properties": {
    "iso:country":"US",
    "sg:address":"224 N Indian Hill Blvd",
    "sg:city":"Claremont",
    "sg:classifiers":[
        {
            "category":"Health Services",
            "subcategory":"Health Practitioner",
            "type":"Services"
        }
    ],
    "sg:phone":"+1 909 621 0447",
    "sg:postcode":"91711",
    "sg:province":"CA",
    "sg:tags":[
        "therapist",
        "physical"
    ],
    "wof:name":"Body Studio",
    "wof:placetype":"venue"
},
  "geometry": {"coordinates":[-117.719217,34.096374],"type":"Point"}
}