{
  "type": "Feature",
  "properties": {
    "iso:country":"US",
    "sg:address":"1450 Boughton Dr",
    "sg:city":"Bakersfield",
    "sg:classifiers":[
        {
            "category":"Education",
            "subcategory":"Special Training",
            "type":"Public Place"
        }
    ],
    "sg:phone":"+1 661 391 1100",
    "sg:postcode":"93308",
    "sg:province":"CA",
    "sg:tags":[
        "aircraft",
        "school"
    ],
    "sg:website":"www.ifta.net",
    "wof:name":"International Flight Training",
    "wof:placetype":"venue"
},
  "geometry": {"coordinates":[-119.045394,35.434226],"type":"Point"}
}