{
  "type": "Feature",
  "properties": {
    "addr:full":"4704 Oyster Bay Dr San Jose CA 95136",
    "addr:housenumber":"4704",
    "addr:postcode":"95136",
    "addr:street":"Oyster Bay Dr",
    "iso:country":"US",
    "sg:address":"4704 Oyster Bay Dr",
    "sg:city":"San Jose",
    "sg:classifiers":[
        {
            "category":"Building & Trades",
            "subcategory":"Landscaping Services",
            "type":"Services"
        }
    ],
    "sg:phone":"+1 408 445 9608",
    "sg:postcode":"95136",
    "sg:province":"CA",
    "sg:tags":[
        "landscape"
    ],
    "wof:name":"Prestige Landscaping",
    "wof:placetype":"venue"
},
  "geometry": {"coordinates":[-121.86841200000001,37.262598],"type":"Point"}
}