{
  "type": "Feature",
  "properties": {
    "addr:full":"524 N Garfield St Coalinga CA 93210",
    "addr:housenumber":"524",
    "addr:postcode":"93210",
    "addr:street":"N Garfield St",
    "iso:country":"US",
    "sg:address":"524 N Garfield St",
    "sg:city":"Coalinga",
    "sg:classifiers":[
        {
            "category":"Building & Trades",
            "subcategory":"Construction",
            "type":"Services"
        }
    ],
    "sg:phone":"+1 559 935 3329",
    "sg:postcode":"93210",
    "sg:province":"CA",
    "sg:tags":[
        "water",
        "well",
        "drilling"
    ],
    "wof:name":"Garys Well Service",
    "wof:placetype":"venue"
},
  "geometry": {"coordinates":[-120.34942100000001,36.136965],"type":"Point"}
}