{
  "type": "Feature",
  "properties": {
    "addr:full":"815 S Escondido Blvd Escondido CA 92025",
    "addr:housenumber":"815",
    "addr:postcode":"92025",
    "addr:street":"S Escondido Blvd",
    "iso:country":"US",
    "sg:address":"815 S Escondido Blvd",
    "sg:city":"Escondido",
    "sg:classifiers":[
        {
            "category":"Shopping",
            "subcategory":"Used Merchandise",
            "type":"Retail Goods"
        }
    ],
    "sg:phone":"+1 760 480 1111",
    "sg:postcode":"92025",
    "sg:province":"CA",
    "wof:name":"Aa House of Pawn",
    "wof:placetype":"venue"
},
  "geometry": {"coordinates":[-117.079564,33.113659],"type":"Point"}
}