{
  "type": "Feature",
  "properties": {
    "iso:country":"US",
    "sg:address":"340 Eva Ct",
    "sg:city":"Manteca",
    "sg:classifiers":[
        {
            "category":"Shopping",
            "type":"Retail Goods"
        }
    ],
    "sg:phone":"+1 209 823 9276",
    "sg:postcode":"95336",
    "sg:province":"CA",
    "sg:tags":[
        "ice"
    ],
    "wof:name":"Manteca Dry Ice",
    "wof:placetype":"venue"
},
  "geometry": {"coordinates":[-121.22033399999999,37.813024],"type":"Point"}
}