{
  "type": "Feature",
  "properties": {
    "iso:country":"US",
    "sg:address":"7048 E Main St",
    "sg:city":"Stockton",
    "sg:classifiers":[
        {
            "category":"Freight",
            "type":"Transportation"
        }
    ],
    "sg:phone":"+1 209 469 3999",
    "sg:postcode":"95215",
    "sg:province":"CA",
    "sg:tags":[
        "trucking"
    ],
    "wof:name":"AJL Agricultural Svc Inc",
    "wof:placetype":"venue"
},
  "geometry": {"coordinates":[-121.19147,37.964896],"type":"Point"}
}