{
  "type": "Feature",
  "properties": {
    "addr:full":"3600 Power Inn Rd Ste G Sacramento CA 95826",
    "addr:housenumber":"3600",
    "addr:postcode":"95826",
    "addr:street":"Power Inn Rd Ste G",
    "iso:country":"US",
    "sg:address":"3600 Power Inn Rd Ste G",
    "sg:city":"Sacramento",
    "sg:classifiers":[
        {
            "category":"Banks & Credit Unions",
            "subcategory":"Financial Services",
            "type":"Services"
        }
    ],
    "sg:phone":"+1 916 231 6232",
    "sg:postcode":"95826",
    "sg:province":"CA",
    "sg:tags":[
        "broker",
        "mortgage"
    ],
    "wof:name":"Custom Realty Loans",
    "wof:placetype":"venue"
},
  "geometry": {"coordinates":[-121.409122,38.542144],"type":"Point"}
}