{
  "type": "Feature",
  "properties": {
    "iso:country":"US",
    "sg:address":"741 W Arrow Hwy",
    "sg:city":"San Dimas",
    "sg:classifiers":[
        {
            "category":"Restaurant",
            "type":"Food & Drink"
        }
    ],
    "sg:menulink":"http://www.allmenus.com/ca/east-san-gabriel-valley/216675-mcdonalds/menu/",
    "sg:postcode":"91773",
    "sg:province":"CA",
    "sg:tags":[
        "burger",
        "american"
    ],
    "wof:name":"McDonald's",
    "wof:placetype":"venue"
},
  "geometry": {"coordinates":[-117.820251,34.106532],"type":"Point"}
}