{
  "type": "Feature",
  "properties": {
    "iso:country":"US",
    "sg:address":"6081 Sunrise Blvd",
    "sg:city":"Citrus Heights",
    "sg:classifiers":[
        {
            "category":"Food & Beverages",
            "subcategory":"Bakery",
            "type":"Retail Goods"
        }
    ],
    "sg:phone":"+1 916 721 3177",
    "sg:postcode":"95610",
    "sg:province":"CA",
    "sg:tags":[
        "cookie",
        "cracker"
    ],
    "wof:name":"Mrs Field's Original Cookies",
    "wof:placetype":"venue"
},
  "geometry": {"coordinates":[-121.271579,38.674178],"type":"Point"}
}