{
  "type": "Feature",
  "properties": {
    "addr:full":"669 Palmetto Ave Chico CA 95926",
    "addr:housenumber":"669",
    "addr:postcode":"95926",
    "addr:street":"Palmetto Ave",
    "iso:country":"US",
    "sg:address":"669 Palmetto Ave",
    "sg:city":"Chico",
    "sg:classifiers":[
        {
            "category":"Health Services",
            "subcategory":"Doctor",
            "type":"Services"
        }
    ],
    "sg:phone":"+1 530 891 4811",
    "sg:postcode":"95926",
    "sg:province":"CA",
    "sg:tags":[
        "physician",
        "immunology",
        "pediatrics-allergy",
        "allergy",
        "surgeons",
        "treatment",
        "surgeon"
    ],
    "wof:name":"McCann, Norman MD",
    "wof:placetype":"venue"
},
  "geometry": {"coordinates":[-121.83443699999999,39.738913],"type":"Point"}
}