{
  "type": "Feature",
  "properties": {
    "addr:full":"1693 Commerce St Corona CA 92880",
    "addr:housenumber":"1693",
    "addr:postcode":"92880",
    "addr:street":"Commerce St",
    "iso:country":"US",
    "sg:address":"1693 Commerce St",
    "sg:city":"Corona",
    "sg:classifiers":[
        {
            "category":"Building & Trades",
            "subcategory":"Construction",
            "type":"Services"
        }
    ],
    "sg:phone":"+1 951 520 9992",
    "sg:postcode":"92880",
    "sg:province":"CA",
    "sg:tags":[
        "coating",
        "contractor"
    ],
    "wof:name":"Endless Powder Coating",
    "wof:placetype":"venue"
},
  "geometry": {"coordinates":[-117.593448,33.885308],"type":"Point"}
}