{
  "type": "Feature",
  "properties": {
    "addr:full":"3239 Danville Blvd Alamo CA 94507",
    "addr:housenumber":"3239",
    "addr:postcode":"94507",
    "addr:street":"Danville Blvd",
    "iso:country":"US",
    "sg:address":"3239 Danville Blvd",
    "sg:city":"Alamo",
    "sg:classifiers":[
        {
            "category":"Real Estate",
            "subcategory":"Real Estate Agent",
            "type":"Services"
        }
    ],
    "sg:phone":"+1 925 831 8970",
    "sg:postcode":"94507",
    "sg:province":"CA",
    "sg:tags":[
        "management"
    ],
    "wof:name":"Perchak Properties",
    "wof:placetype":"venue"
},
  "geometry": {"coordinates":[-122.045889,37.871392],"type":"Point"}
}