{
  "type": "Feature",
  "properties": {
    "iso:country":"US",
    "sg:address":"706 Marguerite Ave",
    "sg:city":"Corona Del Mar",
    "sg:classifiers":[
        {
            "category":"Wholesale",
            "subcategory":"Apparel",
            "type":"Manufacturing & Wholesale Goods"
        }
    ],
    "sg:phone":"+1 949 294 9594",
    "sg:postcode":"92625",
    "sg:province":"CA",
    "sg:tags":[
        "design"
    ],
    "wof:name":"Established Clothing Inc",
    "wof:placetype":"venue"
},
  "geometry": {"coordinates":[-117.867436,33.599644],"type":"Point"}
}