{
  "type": "Feature",
  "properties": {
    "addr:full":"1711 Noriega Street San Francisco CA 94122",
    "addr:housenumber":"1711",
    "addr:postcode":"94122",
    "addr:street":"Noriega Street",
    "iso:country":"US",
    "sg:address":"1711 Noriega Street",
    "sg:city":"San Francisco",
    "sg:classifiers":[
        {
            "category":"Retail",
            "subcategory":"Laundry & Dry Cleaning",
            "type":"Services"
        }
    ],
    "sg:phone":"+1 415 661 1320",
    "sg:postcode":"94122",
    "sg:province":"CA",
    "wof:name":"Noriega Street Cleaners",
    "wof:placetype":"venue"
},
  "geometry": {"coordinates":[-122.48200199999999,37.753899],"type":"Point"}
}