{
  "type": "Feature",
  "properties": {
    "addr:full":"1870 Cresta Dr Palm Springs CA 92264",
    "addr:housenumber":"1870",
    "addr:postcode":"92264",
    "addr:street":"Cresta Dr",
    "iso:country":"US",
    "sg:address":"1870 Cresta Dr",
    "sg:city":"Palm Springs",
    "sg:classifiers":[
        {
            "category":"Arts & Performance",
            "subcategory":"Theater",
            "type":"Entertainment"
        }
    ],
    "sg:phone":"+1 760 327 0084",
    "sg:postcode":"92264",
    "sg:province":"CA",
    "sg:tags":[
        "magician"
    ],
    "wof:name":"Interior Magic",
    "wof:placetype":"venue"
},
  "geometry": {"coordinates":[-116.531066,33.799304],"type":"Point"}
}