{
  "type": "Feature",
  "properties": {
    "iso:country":"US",
    "sg:address":"13501 S Main Street",
    "sg:city":"Los Angeles",
    "sg:classifiers":[
        {
            "category":"Autos & Motor Vehicles",
            "subcategory":"Motorcycle Sales",
            "type":"Retail Goods"
        }
    ],
    "sg:phone":"+1 310 327 1674",
    "sg:postcode":"90061",
    "sg:province":"CA",
    "wof:name":"Bartel's Race Shop",
    "wof:placetype":"venue"
},
  "geometry": {"coordinates":[-118.273928,33.909183],"type":"Point"}
}