{
  "type": "Feature",
  "properties": {
    "addr:full":"34324 Yucaipa Blvd Yucaipa CA 92399",
    "addr:postcode":"34324;92399",
    "addr:street":"Yucaipa Blvd",
    "iso:country":"US",
    "sg:address":"34324 Yucaipa Blvd",
    "sg:city":"Yucaipa",
    "sg:classifiers":[
        {
            "category":"Personal",
            "subcategory":"Beauty Salon",
            "type":"Services"
        }
    ],
    "sg:phone":"+1 909 790 2275",
    "sg:postcode":"92399",
    "sg:province":"CA",
    "wof:name":"Clippers Family Cuts",
    "wof:placetype":"venue"
},
  "geometry": {"coordinates":[-117.052312,34.033956],"type":"Point"}
}