{
  "type": "Feature",
  "properties": {
    "addr:full":"1913 E Gage Ave Los Angeles CA 90001",
    "addr:housenumber":"1913",
    "addr:postcode":"90001",
    "addr:street":"E Gage Ave",
    "iso:country":"US",
    "sg:address":"1913 E Gage Ave",
    "sg:city":"Los Angeles",
    "sg:classifiers":[
        {
            "category":"Restaurant",
            "type":"Food & Drink"
        }
    ],
    "sg:phone":"+1 323 585 2270",
    "sg:postcode":"90001",
    "sg:province":"CA",
    "sg:tags":[
        "mexican"
    ],
    "wof:name":"Ranchito Jr 2",
    "wof:placetype":"venue"
},
  "geometry": {"coordinates":[-118.23863299999999,33.982147],"type":"Point"}
}