{
  "type": "Feature",
  "properties": {
    "iso:country":"US",
    "sg:address":"4731 Mendocino Ter",
    "sg:city":"Fremont",
    "sg:classifiers":[
        {
            "category":"Manufacturing",
            "subcategory":"Jewelry",
            "type":"Manufacturing & Wholesale Goods"
        }
    ],
    "sg:phone":"+1 510 791 5956",
    "sg:postcode":"94555",
    "sg:province":"CA",
    "sg:tags":[
        "precious",
        "metal",
        "mfg"
    ],
    "wof:name":"Jeannies Jewels",
    "wof:placetype":"venue"
},
  "geometry": {"coordinates":[-122.04271,37.565917],"type":"Point"}
}