{
  "type": "Feature",
  "properties": {
    "addr:full":"1015 S Orange Grove Ave Los Angeles CA 90019",
    "addr:housenumber":"1015",
    "addr:postcode":"90019",
    "addr:street":"S Orange Grove Ave",
    "iso:country":"US",
    "sg:address":"1015 S Orange Grove Ave",
    "sg:city":"Los Angeles",
    "sg:classifiers":[
        {
            "category":"Professional",
            "type":"Services"
        }
    ],
    "sg:phone":"+1 323 933 8271",
    "sg:postcode":"90019",
    "sg:province":"CA",
    "wof:name":"Gloria P Bagon",
    "wof:placetype":"venue"
},
  "geometry": {"coordinates":[-118.362787,34.057894],"type":"Point"}
}