{
  "type": "Feature",
  "properties": {
    "iso:country":"US",
    "sg:address":"14130 Alondra Blvd Ste H",
    "sg:city":"Santa Fe Springs",
    "sg:classifiers":[
        {
            "category":"Building & Trades",
            "subcategory":"Construction",
            "type":"Services"
        }
    ],
    "sg:phone":"+1 714 632 5600",
    "sg:postcode":"90670",
    "sg:province":"CA",
    "sg:tags":[
        "contractor"
    ],
    "wof:name":"Projective Development Internatl",
    "wof:placetype":"venue"
},
  "geometry": {"coordinates":[-118.030998,33.887901],"type":"Point"}
}