{
  "type": "Feature",
  "properties": {
    "addr:full":"4601 Brooks St Montclair CA 91763",
    "addr:housenumber":"4601",
    "addr:postcode":"91763",
    "addr:street":"Brooks St",
    "iso:country":"US",
    "sg:address":"4601 Brooks St",
    "sg:city":"Montclair",
    "sg:classifiers":[
        {
            "category":"Retail",
            "subcategory":"Auto Repair",
            "type":"Services"
        }
    ],
    "sg:phone":"+1 909 626 0305",
    "sg:postcode":"91763",
    "sg:province":"CA",
    "sg:tags":[
        "automotive",
        "general",
        "carburetor"
    ],
    "wof:name":"Figueroa's Carburetors",
    "wof:placetype":"venue"
},
  "geometry": {"coordinates":[-117.700388,34.06158],"type":"Point"}
}