{
  "type": "Feature",
  "properties": {
    "iso:country":"US",
    "sg:address":"2270 W Lincoln Ave Ste A",
    "sg:city":"Anaheim",
    "sg:classifiers":[
        {
            "category":"Health Services",
            "subcategory":"Dentist",
            "type":"Services"
        }
    ],
    "sg:phone":"+1 714 224 0240",
    "sg:postcode":"92801",
    "sg:province":"CA",
    "sg:website":"www.pacificdentalclinic.com",
    "wof:name":"Pacific Dental Clinic",
    "wof:placetype":"venue"
},
  "geometry": {"coordinates":[-117.96244,33.832262],"type":"Point"}
}