{
  "type": "Feature",
  "properties": {
    "addr:full":"1900 W 135th St Gardena CA 90249",
    "addr:housenumber":"1900",
    "addr:postcode":"90249",
    "addr:street":"W 135Th St",
    "iso:country":"US",
    "sg:address":"1900 W 135th St",
    "sg:city":"Gardena",
    "sg:classifiers":[
        {
            "category":"Wholesale",
            "subcategory":"Durable Goods & Equipment",
            "type":"Manufacturing & Wholesale Goods"
        }
    ],
    "sg:phone":"+1 310 719 1200",
    "sg:postcode":"90249",
    "sg:province":"CA",
    "sg:tags":[
        "importer"
    ],
    "wof:name":"Michaud",
    "wof:placetype":"venue"
},
  "geometry": {"coordinates":[-118.310112,33.909114],"type":"Point"}
}