{
  "type": "Feature",
  "properties": {
    "iso:country":"US",
    "sg:address":"5759 Dunsmuir Ave",
    "sg:city":"Dunsmuir",
    "sg:classifiers":[
        {
            "category":"Restaurant",
            "type":"Food & Drink"
        }
    ],
    "sg:phone":"+1 530 235 4677",
    "sg:postcode":"96025",
    "sg:province":"CA",
    "wof:name":"Cornerstone Bakery & Cafe",
    "wof:placetype":"venue"
},
  "geometry": {"coordinates":[-122.27243900000001,41.210146],"type":"Point"}
}