{
  "type": "Feature",
  "properties": {
    "iso:country":"US",
    "sg:address":"1701 S Grove Ave",
    "sg:city":"Ontario",
    "sg:classifiers":[
        {
            "category":"Utilities",
            "subcategory":"Telephone",
            "type":"Services"
        }
    ],
    "sg:phone":"+1 909 773 1145",
    "sg:postcode":"91761",
    "sg:province":"CA",
    "sg:tags":[
        "telecommunication"
    ],
    "wof:name":"Mastec North America Inc",
    "wof:placetype":"venue"
},
  "geometry": {"coordinates":[-117.62849,34.04476],"type":"Point"}
}