{
  "type": "Feature",
  "properties": {
    "iso:country":"US",
    "sg:address":"4394 University Pkwy",
    "sg:city":"San Bernardino",
    "sg:classifiers":[
        {
            "category":"Restaurant",
            "type":"Food & Drink"
        }
    ],
    "sg:phone":"+1 909 473 7944",
    "sg:postcode":"92407",
    "sg:province":"CA",
    "wof:name":"Wienerschnitzel No 667",
    "wof:placetype":"venue"
},
  "geometry": {"coordinates":[-117.33200100000001,34.167198],"type":"Point"}
}