{
  "type": "Feature",
  "properties": {
    "addr:full":"26549 Carmel Rancho Boulevard Carmel CA 93923",
    "addr:housenumber":"26549",
    "addr:postcode":"93923",
    "addr:street":"Carmel Rancho Boulevard",
    "iso:country":"US",
    "sg:address":"26549 Carmel Rancho Boulevard",
    "sg:city":"Carmel",
    "sg:classifiers":[
        {
            "category":"Shopping",
            "subcategory":"Pets & Pet Supplies",
            "type":"Retail Goods"
        }
    ],
    "sg:phone":"+1 831 626 7555",
    "sg:postcode":"93923",
    "sg:province":"CA",
    "sg:tags":[
        "store"
    ],
    "sg:website":"www.therawconnection.com",
    "wof:name":"The Raw Connection",
    "wof:placetype":"venue"
},
  "geometry": {"coordinates":[-121.904275,36.542553],"type":"Point"}
}