{
  "type": "Feature",
  "properties": {
    "addr:full":"7300 El Camino Real Atascadero CA 93422",
    "addr:housenumber":"7300",
    "addr:postcode":"93422",
    "addr:street":"El Camino Real",
    "iso:country":"US",
    "sg:address":"7300 El Camino Real",
    "sg:city":"Atascadero",
    "sg:classifiers":[
        {
            "category":"Restaurant",
            "type":"Food & Drink"
        }
    ],
    "sg:menulink":"http://www.allmenus.com/ca/atascadero/152816-carrows/menu/",
    "sg:phone":"+1 805 466 3861",
    "sg:postcode":"93422",
    "sg:province":"CA",
    "sg:tags":[
        "sandwich",
        "salad",
        "burger",
        "dog",
        "soup",
        "hot",
        "wrap",
        "american"
    ],
    "wof:name":"Carrows",
    "wof:placetype":"venue"
},
  "geometry": {"coordinates":[-120.662524,35.484386],"type":"Point"}
}