{
  "type": "Feature",
  "properties": {
    "addr:full":"1590 University Ave Riverside CA 92507",
    "addr:housenumber":"1590",
    "addr:postcode":"92507",
    "addr:street":"University Ave",
    "iso:country":"US",
    "sg:address":"1590 University Ave",
    "sg:city":"Riverside",
    "sg:classifiers":[
        {
            "category":"Professional",
            "subcategory":"Advertising",
            "type":"Services"
        }
    ],
    "sg:phone":"+1 951 684 6478",
    "sg:postcode":"92507",
    "sg:province":"CA",
    "sg:tags":[
        "good"
    ],
    "wof:name":"Hospitality Directory",
    "wof:placetype":"venue"
},
  "geometry": {"coordinates":[-117.34672399999999,33.975612],"type":"Point"}
}