{
  "type": "Feature",
  "properties": {
    "addr:full":"1160 Cragmont Ave Berkeley CA 94708",
    "addr:housenumber":"1160",
    "addr:postcode":"94708",
    "addr:street":"Cragmont Ave",
    "iso:country":"US",
    "sg:address":"1160 Cragmont Ave",
    "sg:city":"Berkeley",
    "sg:classifiers":[
        {
            "category":"Professional",
            "subcategory":"Management & Consulting",
            "type":"Services"
        }
    ],
    "sg:phone":"+1 510 883 9630",
    "sg:postcode":"94708",
    "sg:province":"CA",
    "sg:tags":[
        "science",
        "consultant",
        "academic"
    ],
    "wof:name":"Cragmont Environmental",
    "wof:placetype":"venue"
},
  "geometry": {"coordinates":[-122.258814,37.88895],"type":"Point"}
}