{
  "type": "Feature",
  "properties": {
    "addr:full":"3354 Redwood Dr Redway CA 95560",
    "addr:housenumber":"3354",
    "addr:postcode":"95560",
    "addr:street":"Redwood Dr",
    "iso:country":"US",
    "sg:address":"3354 Redwood Dr",
    "sg:city":"Redway",
    "sg:classifiers":[
        {
            "category":"Professional",
            "subcategory":"Lawyer & Legal Services",
            "type":"Services"
        }
    ],
    "sg:phone":"+1 707 923 2509",
    "sg:postcode":"95560",
    "sg:province":"CA",
    "sg:tags":[
        "attorney"
    ],
    "wof:name":"Robert J Burke",
    "wof:placetype":"venue"
},
  "geometry": {"coordinates":[-123.814491,40.115483],"type":"Point"}
}