{
  "type": "Feature",
  "properties": {
    "addr:full":"1611 Garnet Ave San Diego CA 92109",
    "addr:housenumber":"1611",
    "addr:postcode":"92109",
    "addr:street":"Garnet Ave",
    "iso:country":"US",
    "sg:address":"1611 Garnet Ave",
    "sg:city":"San Diego",
    "sg:classifiers":[
        {
            "category":"Retail",
            "subcategory":"Self-service Laundry",
            "type":"Services"
        }
    ],
    "sg:phone":"+1 858 270 7007",
    "sg:postcode":"92109",
    "sg:province":"CA",
    "wof:name":"Clean Jeans",
    "wof:placetype":"venue"
},
  "geometry": {"coordinates":[-117.23913,32.800086],"type":"Point"}
}