{
  "type": "Feature",
  "properties": {
    "addr:full":"409 Summit Ave Mill Valley CA 94941",
    "addr:housenumber":"409",
    "addr:postcode":"94941",
    "addr:street":"Summit Ave",
    "iso:country":"US",
    "sg:address":"409 Summit Ave",
    "sg:city":"Mill Valley",
    "sg:classifiers":[
        {
            "category":"Banks & Credit Unions",
            "subcategory":"Investment Brokerage",
            "type":"Services"
        }
    ],
    "sg:phone":"+1 415 381 4800",
    "sg:postcode":"94941",
    "sg:province":"CA",
    "sg:tags":[
        "management"
    ],
    "wof:name":"Rosewood Stone Group",
    "wof:placetype":"venue"
},
  "geometry": {"coordinates":[-122.557821,37.91342],"type":"Point"}
}