{
  "type": "Feature",
  "properties": {
    "addr:full":"1707 E Capital Expy San Jose CA 95121",
    "addr:housenumber":"1707",
    "addr:postcode":"95121",
    "addr:street":"E Capital Expy",
    "iso:country":"US",
    "sg:address":"1707 E Capital Expy",
    "sg:city":"San Jose",
    "sg:classifiers":[
        {
            "category":"Banks & Credit Unions",
            "subcategory":"Bank",
            "type":"Services"
        }
    ],
    "sg:postcode":"95121",
    "sg:province":"CA",
    "sg:website":"www.bankofamerica.com",
    "wof:name":"Bank of America",
    "wof:placetype":"venue"
},
  "geometry": {"coordinates":[-121.809387,37.309645],"type":"Point"}
}