{
  "type": "Feature",
  "properties": {
    "addr:full":"3752 Monolith Trl Perris CA 92570",
    "addr:housenumber":"3752",
    "addr:postcode":"92570",
    "addr:street":"Monolith Trl",
    "iso:country":"US",
    "sg:address":"3752 Monolith Trl",
    "sg:city":"Perris",
    "sg:classifiers":[
        {
            "category":"Retail",
            "subcategory":"Photofinishing",
            "type":"Services"
        }
    ],
    "sg:phone":"+1 559 577 7648",
    "sg:postcode":"92570",
    "sg:province":"CA",
    "sg:tags":[
        "photo",
        "finishing"
    ],
    "wof:name":"Ash Brothers Films",
    "wof:placetype":"venue"
},
  "geometry": {"coordinates":[-117.240639,33.737389],"type":"Point"}
}