{
  "type": "Feature",
  "properties": {
    "addr:full":"1200 N Coast Hwy Laguna Beach CA 92651",
    "addr:housenumber":"1200",
    "addr:postcode":"92651",
    "addr:street":"N Coast Hwy",
    "iso:country":"US",
    "sg:address":"1200 N Coast Hwy",
    "sg:city":"Laguna Beach",
    "sg:classifiers":[
        {
            "category":"Shopping",
            "subcategory":"Clothing, Apparel, & Fashions",
            "type":"Retail Goods"
        }
    ],
    "sg:phone":"+1 949 500 1857",
    "sg:postcode":"92651",
    "sg:province":"CA",
    "sg:tags":[
        "family"
    ],
    "wof:name":"Meeschka",
    "wof:placetype":"venue"
},
  "geometry": {"coordinates":[-117.800229,33.548411],"type":"Point"}
}