{
  "type": "Feature",
  "properties": {
    "addr:full":"1077 Main St Ramona CA 92065",
    "addr:housenumber":"1077",
    "addr:postcode":"92065",
    "addr:street":"Main St",
    "iso:country":"US",
    "sg:address":"1077 Main St",
    "sg:city":"Ramona",
    "sg:classifiers":[
        {
            "category":"Manufacturing",
            "subcategory":"Tools & Machinery",
            "type":"Manufacturing & Wholesale Goods"
        }
    ],
    "sg:phone":"+1 760 789 2455",
    "sg:postcode":"92065",
    "sg:province":"CA",
    "sg:tags":[
        "industrial",
        "mfg"
    ],
    "wof:name":"Busheys Machine Shop",
    "wof:placetype":"venue"
},
  "geometry": {"coordinates":[-116.86913800000001,33.0419],"type":"Point"}
}