{
  "type": "Feature",
  "properties": {
    "iso:country":"US",
    "sg:address":"1721 Garvey Ave",
    "sg:city":"Alhambra",
    "sg:classifiers":[
        {
            "category":"Arena",
            "subcategory":"Sports Club",
            "type":"Entertainment"
        }
    ],
    "sg:phone":"+1 626 284 3289",
    "sg:postcode":"91803",
    "sg:province":"CA",
    "sg:tags":[
        "martial art"
    ],
    "wof:name":"U S Advisory Group",
    "wof:placetype":"venue"
},
  "geometry": {"coordinates":[-118.146004,34.060299],"type":"Point"}
}