{
  "type": "Feature",
  "properties": {
    "iso:country":"US",
    "sg:address":"8545 Etiwanda Ave",
    "sg:city":"Etiwanda",
    "sg:classifiers":[
        {
            "category":"Retail",
            "subcategory":"Auto Repair",
            "type":"Services"
        }
    ],
    "sg:phone":"+1 909 899 5919",
    "sg:postcode":"91739",
    "sg:province":"CA",
    "sg:tags":[
        "recreational",
        "vehicle"
    ],
    "wof:name":"Inland Valley RV Svc & Supply",
    "wof:placetype":"venue"
},
  "geometry": {"coordinates":[-117.523721,34.095174],"type":"Point"}
}