{
  "type": "Feature",
  "properties": {
    "iso:country":"US",
    "sg:address":"4692 Dana Dr",
    "sg:city":"La Palma",
    "sg:classifiers":[
        {
            "category":"Banks & Credit Unions",
            "subcategory":"Bank",
            "type":"Services"
        }
    ],
    "sg:phone":"+1 562 924 7020",
    "sg:postcode":"90623",
    "sg:province":"CA",
    "sg:tags":[
        "national",
        "commercial"
    ],
    "wof:name":"NA & Co",
    "wof:placetype":"venue"
},
  "geometry": {"coordinates":[-118.05212400000001,33.84863],"type":"Point"}
}