{
  "type": "Feature",
  "properties": {
    "iso:country":"US",
    "sg:address":"2755 Nelson Blvd",
    "sg:city":"Selma",
    "sg:classifiers":[
        {
            "category":"Real Estate",
            "subcategory":"Real Estate Operator",
            "type":"Services"
        }
    ],
    "sg:phone":"+1 559 896 3042",
    "sg:postcode":"93662",
    "sg:province":"CA",
    "sg:tags":[
        "apartment"
    ],
    "wof:name":"Capri Villa Apartments",
    "wof:placetype":"venue"
},
  "geometry": {"coordinates":[-119.620081,36.585324],"type":"Point"}
}