{
  "type": "Feature",
  "properties": {
    "addr:full":"3000 Colby St Ste 301 Berkeley CA 94705",
    "addr:housenumber":"3000",
    "addr:postcode":"94705",
    "addr:street":"Colby St Ste 301",
    "iso:country":"US",
    "sg:address":"3000 Colby St Ste 301",
    "sg:city":"Berkeley",
    "sg:classifiers":[
        {
            "category":"Health Services",
            "subcategory":"Doctor",
            "type":"Services"
        },
        {
            "category":"Health Services",
            "subcategory":"Health Practitioner",
            "type":"Services"
        }
    ],
    "sg:phone":"+1 510 540 6800",
    "sg:postcode":"94705",
    "sg:province":"CA",
    "sg:tags":[
        "orthopedist",
        "therapy",
        "physical"
    ],
    "sg:website":"www.cardon.md",
    "wof:name":"Lamont J Cardon MD",
    "wof:placetype":"venue"
},
  "geometry": {"coordinates":[-122.25779,37.855218],"type":"Point"}
}