{
  "type": "Feature",
  "properties": {
    "addr:full":"21710 Sherman Way Canoga Park CA 91303",
    "addr:housenumber":"21710",
    "addr:postcode":"91303",
    "addr:street":"Sherman Way",
    "iso:country":"US",
    "sg:address":"21710 Sherman Way",
    "sg:city":"Canoga Park",
    "sg:classifiers":[
        {
            "category":"Shopping",
            "subcategory":"Thrift Store",
            "type":"Retail Goods"
        }
    ],
    "sg:phone":"+1 818 999 9746",
    "sg:postcode":"91303",
    "sg:province":"CA",
    "wof:name":"Herb's Thrift City",
    "wof:placetype":"venue"
},
  "geometry": {"coordinates":[-118.602024,34.201023],"type":"Point"}
}