{
  "type": "Feature",
  "properties": {
    "iso:country":"US",
    "sg:address":"11601 Wilshire Blvd",
    "sg:city":"Los Angeles",
    "sg:classifiers":[
        {
            "category":"Sports & Exercise",
            "subcategory":"Gym",
            "type":"Entertainment"
        }
    ],
    "sg:phone":"+1 310 724 3442",
    "sg:postcode":"90025",
    "sg:province":"CA",
    "sg:tags":[
        "personal",
        "trainer"
    ],
    "wof:name":"Janatrains Personal Trainer",
    "wof:placetype":"venue"
},
  "geometry": {"coordinates":[-118.460072,34.050095],"type":"Point"}
}