{
  "type": "Feature",
  "properties": {
    "iso:country":"US",
    "sg:address":"210 W Connecticut Ave",
    "sg:city":"Vista",
    "sg:classifiers":[
        {
            "category":"Building & Trades",
            "subcategory":"Construction",
            "type":"Services"
        }
    ],
    "sg:phone":"+1 760 945 9991",
    "sg:postcode":"92083",
    "sg:province":"CA",
    "sg:tags":[
        "site",
        "clean"
    ],
    "wof:name":"Construction Services",
    "wof:placetype":"venue"
},
  "geometry": {"coordinates":[-117.24685599999999,33.206122],"type":"Point"}
}