{
  "type": "Feature",
  "properties": {
    "addr:full":"1550 Howard St San Francisco CA 94103",
    "addr:housenumber":"1550",
    "addr:postcode":"94103",
    "addr:street":"Howard St",
    "iso:country":"US",
    "sg:address":"1550 Howard St",
    "sg:city":"San Francisco",
    "sg:classifiers":[
        {
            "category":"Restaurant",
            "type":"Food & Drink"
        }
    ],
    "sg:menulink":"http://www.allmenus.com/ca/san-francisco/81850-taqueria-reinas/menu/",
    "sg:phone":"+1 415 431 0160",
    "sg:postcode":"94103",
    "sg:province":"CA",
    "sg:tags":[
        "mexican"
    ],
    "wof:name":"Taqueria Reina's",
    "wof:placetype":"venue"
},
  "geometry": {"coordinates":[-122.41640200000001,37.772418],"type":"Point"}
}