{
  "type": "Feature",
  "properties": {
    "iso:country":"US",
    "sg:address":"11715 State Hwy 99",
    "sg:city":"Red Bluff",
    "sg:classifiers":[
        {
            "category":"Real Estate",
            "subcategory":"Real Estate Agent",
            "type":"Services"
        }
    ],
    "sg:phone":"+1 530 528 8165",
    "sg:postcode":"96080",
    "sg:province":"CA",
    "sg:tags":[
        "inspection"
    ],
    "wof:name":"Hossle Home Inspection's",
    "wof:placetype":"venue"
},
  "geometry": {"coordinates":[-122.12560999999999,40.134277],"type":"Point"}
}