{
  "type": "Feature",
  "properties": {
    "addr:full":"7340 N Laurel Canyon Blvd North Hollywood CA 91605",
    "addr:housenumber":"7340",
    "addr:postcode":"91605",
    "addr:street":"N Laurel Canyon Blvd",
    "iso:country":"US",
    "sg:address":"7340 N Laurel Canyon Blvd",
    "sg:city":"North Hollywood",
    "sg:classifiers":[
        {
            "category":"Manufacturing",
            "subcategory":"Printing",
            "type":"Manufacturing & Wholesale Goods"
        }
    ],
    "sg:phone":"+1 818 767 1422",
    "sg:postcode":"91605",
    "sg:province":"CA",
    "sg:tags":[
        "printer"
    ],
    "wof:name":"Bill Scott & Assoc",
    "wof:placetype":"venue"
},
  "geometry": {"coordinates":[-118.396736,34.202132],"type":"Point"}
}