{
  "type": "Feature",
  "properties": {
    "addr:full":"1303 J St Sacramento CA 95814",
    "addr:housenumber":"1303",
    "addr:postcode":"95814",
    "addr:street":"J St",
    "iso:country":"US",
    "sg:address":"1303 J St",
    "sg:city":"Sacramento",
    "sg:classifiers":[
        {
            "category":"Government",
            "subcategory":"Office",
            "type":"Public Place"
        }
    ],
    "sg:phone":"+1 916 445 3173",
    "sg:postcode":"95814",
    "sg:province":"CA",
    "sg:tags":[
        "state",
        "resource"
    ],
    "sg:website":"www.women.ca.gov",
    "wof:name":"Status Of Women",
    "wof:placetype":"venue"
},
  "geometry": {"coordinates":[-121.48787900000001,38.578902],"type":"Point"}
}