{
  "type": "Feature",
  "properties": {
    "addr:full":"3604 E Madison Ave Fresno CA 93702",
    "addr:housenumber":"3604",
    "addr:postcode":"93702",
    "addr:street":"E Madison Ave",
    "iso:country":"US",
    "sg:address":"3604 E Madison Ave",
    "sg:city":"Fresno",
    "sg:classifiers":[
        {
            "category":"Manufacturing",
            "subcategory":"Petroleum Products",
            "type":"Manufacturing & Wholesale Goods"
        }
    ],
    "sg:phone":"+1 559 485 5327",
    "sg:postcode":"93702",
    "sg:province":"CA",
    "sg:tags":[
        "contract"
    ],
    "wof:name":"Saico Industries",
    "wof:placetype":"venue"
},
  "geometry": {"coordinates":[-119.76427200000001,36.749531],"type":"Point"}
}