{
  "type": "Feature",
  "properties": {
    "addr:full":"1629 Sherman Ave Chico CA 95926",
    "addr:housenumber":"1629",
    "addr:postcode":"95926",
    "addr:street":"Sherman Ave",
    "iso:country":"US",
    "sg:address":"1629 Sherman Ave",
    "sg:city":"Chico",
    "sg:classifiers":[
        {
            "category":"Professional",
            "subcategory":"Accounting & Tax Preparation",
            "type":"Services"
        }
    ],
    "sg:phone":"+1 530 895 0987",
    "sg:postcode":"95926",
    "sg:province":"CA",
    "sg:tags":[
        "bookkeeping",
        "general"
    ],
    "wof:name":"C K Business Svc",
    "wof:placetype":"venue"
},
  "geometry": {"coordinates":[-121.83813600000001,39.747641],"type":"Point"}
}