{
  "type": "Feature",
  "properties": {
    "iso:country":"US",
    "sg:address":"1544 E Ridgewood Ln",
    "sg:city":"Fresno",
    "sg:classifiers":[
        {
            "category":"Communications",
            "type":"Services"
        }
    ],
    "sg:phone":"+1 559 673 2411",
    "sg:postcode":"93730",
    "sg:province":"CA",
    "wof:name":"Media Cube",
    "wof:placetype":"venue"
},
  "geometry": {"coordinates":[-119.75559800000001,36.891601],"type":"Point"}
}