{
  "type": "Feature",
  "properties": {
    "iso:country":"US",
    "sg:address":"1782 D St",
    "sg:city":"Hayward",
    "sg:classifiers":[
        {
            "category":"Retail",
            "subcategory":"Auto Repair",
            "type":"Services"
        }
    ],
    "sg:phone":"+1 510 382 1100",
    "sg:postcode":"94541",
    "sg:province":"CA",
    "sg:tags":[
        "wrecker"
    ],
    "wof:name":"Fast Tow Towing",
    "wof:placetype":"venue"
},
  "geometry": {"coordinates":[-122.06546,37.677921],"type":"Point"}
}