{
  "type": "Feature",
  "properties": {
    "iso:country":"US",
    "sg:address":"725 Merchant Street",
    "sg:city":"Los Angeles",
    "sg:classifiers":[
        {
            "category":"Wholesale",
            "subcategory":"Fruits & Vegetables",
            "type":"Manufacturing & Wholesale Goods"
        }
    ],
    "sg:phone":"+1 213 622 5874",
    "sg:postcode":"90021",
    "sg:province":"CA",
    "sg:tags":[
        "veggie"
    ],
    "wof:name":"Produce Services of Los Angeles",
    "wof:placetype":"venue"
},
  "geometry": {"coordinates":[-118.242412,34.036285],"type":"Point"}
}