{
  "type": "Feature",
  "properties": {
    "iso:country":"US",
    "sg:address":"3538 Manthey Rd",
    "sg:city":"Stockton",
    "sg:classifiers":[
        {
            "category":"Health Services",
            "subcategory":"Doctor",
            "type":"Services"
        }
    ],
    "sg:phone":"+1 209 983 1000",
    "sg:postcode":"95206",
    "sg:province":"CA",
    "sg:tags":[
        "dentist"
    ],
    "wof:name":"Valley View Dental",
    "wof:placetype":"venue"
},
  "geometry": {"coordinates":[-121.293541,37.910907],"type":"Point"}
}