{
  "type": "Feature",
  "properties": {
    "iso:country":"US",
    "sg:address":"54425 N Circle Dr",
    "sg:city":"Idyllwild",
    "sg:classifiers":[
        {
            "category":"Shopping",
            "type":"Retail Goods"
        }
    ],
    "sg:phone":"+1 951 659 2306",
    "sg:postcode":"92549",
    "sg:province":"CA",
    "sg:tags":[
        "art",
        "gallery",
        "dealer"
    ],
    "wof:name":"Whirlwind Studios",
    "wof:placetype":"venue"
},
  "geometry": {"coordinates":[-116.711692,33.746622],"type":"Point"}
}