{
  "type": "Feature",
  "properties": {
    "addr:full":"1595 Mono Dr Modesto CA 95354",
    "addr:housenumber":"1595",
    "addr:postcode":"ca 95354",
    "addr:street":"Mono Dr",
    "iso:country":"US",
    "sg:address":"1595 Mono Dr",
    "sg:city":"Modesto",
    "sg:classifiers":[
        {
            "category":"Manufacturing",
            "subcategory":"Tools & Machinery",
            "type":"Manufacturing & Wholesale Goods"
        }
    ],
    "sg:phone":"+1 209 524 9384",
    "sg:postcode":"95354",
    "sg:province":"CA",
    "sg:tags":[
        "food",
        "product"
    ],
    "wof:name":"T & C Mfg Co",
    "wof:placetype":"venue"
},
  "geometry": {"coordinates":[-120.97108,37.635525],"type":"Point"}
}