{
  "type": "Feature",
  "properties": {
    "addr:full":"517 N Central Ave Glendale CA 91202",
    "addr:housenumber":"517",
    "addr:postcode":"91202",
    "addr:street":"N Central Ave",
    "iso:country":"US",
    "sg:address":"517 N Central Ave",
    "sg:city":"Glendale",
    "sg:classifiers":[
        {
            "category":"Health Services",
            "subcategory":"Doctor",
            "type":"Services"
        }
    ],
    "sg:phone":"+1 818 550 1777",
    "sg:postcode":"91202",
    "sg:province":"CA",
    "sg:tags":[
        "clinic"
    ],
    "wof:name":"Sami Nafoosi",
    "wof:placetype":"venue"
},
  "geometry": {"coordinates":[-118.25792,34.152868],"type":"Point"}
}