{
  "type": "Feature",
  "properties": {
    "addr:full":"715 Falcon Ave Davis CA 95616",
    "addr:housenumber":"715",
    "addr:postcode":"95616",
    "addr:street":"Falcon Ave",
    "iso:country":"US",
    "sg:address":"715 Falcon Ave",
    "sg:city":"Davis",
    "sg:classifiers":[
        {
            "category":"Health Services",
            "subcategory":"Hospital",
            "type":"Services"
        }
    ],
    "sg:phone":"+1 530 668 8988",
    "sg:postcode":"95616",
    "sg:province":"CA",
    "sg:tags":[
        "specialty"
    ],
    "wof:name":"Active Diagnostics Inc",
    "wof:placetype":"venue"
},
  "geometry": {"coordinates":[-121.759488,38.56888],"type":"Point"}
}