{
  "type": "Feature",
  "properties": {
    "addr:full":"8650 Genesee Ave San Diego CA 92122",
    "addr:housenumber":"8650",
    "addr:postcode":"92122",
    "addr:street":"Genesee Ave",
    "iso:country":"US",
    "sg:address":"8650 Genesee Ave",
    "sg:city":"San Diego",
    "sg:classifiers":[
        {
            "category":"Retail",
            "subcategory":"Repair Shop",
            "type":"Services"
        }
    ],
    "sg:phone":"+1 858 625 8411",
    "sg:postcode":"92122",
    "sg:province":"CA",
    "sg:tags":[
        "lock",
        "locksmith"
    ],
    "wof:name":"24 Hour Emergency Locksmith",
    "wof:placetype":"venue"
},
  "geometry": {"coordinates":[-117.214083,32.868301],"type":"Point"}
}