{
  "type": "Feature",
  "properties": {
    "iso:country":"US",
    "sg:address":"1437 N Montebello Blvd",
    "sg:city":"Montebello",
    "sg:classifiers":[
        {
            "category":"Arena",
            "subcategory":"Sports Club",
            "type":"Entertainment"
        }
    ],
    "sg:phone":"+1 323 726 1153",
    "sg:postcode":"90640",
    "sg:province":"CA",
    "sg:tags":[
        "martial art"
    ],
    "sg:website":"www.selvabjj.com",
    "wof:name":"Selva Brazilian Jiu-Jitsu",
    "wof:placetype":"venue"
},
  "geometry": {"coordinates":[-118.096424,34.032251],"type":"Point"}
}