{
  "type": "Feature",
  "properties": {
    "addr:full":"1740 S Palmetto Ave Ontario CA 91762",
    "addr:housenumber":"1740",
    "addr:postcode":"91762",
    "addr:street":"S Palmetto Ave",
    "iso:country":"US",
    "sg:address":"1740 S Palmetto Ave",
    "sg:city":"Ontario",
    "sg:classifiers":[
        {
            "category":"Professional",
            "type":"Services"
        }
    ],
    "sg:phone":"+1 909 395 0943",
    "sg:postcode":"91762",
    "sg:province":"CA",
    "wof:name":"Marina & Maria",
    "wof:placetype":"venue"
},
  "geometry": {"coordinates":[-117.66782000000001,34.043183],"type":"Point"}
}