{
  "type": "Feature",
  "properties": {
    "iso:country":"US",
    "sg:address":"3255 Scott Blvd",
    "sg:city":"Santa Clara",
    "sg:classifiers":[
        {
            "category":"Professional",
            "subcategory":"Computer Services",
            "type":"Services"
        }
    ],
    "sg:phone":"+1 408 562 9400",
    "sg:postcode":"95050",
    "sg:province":"CA",
    "wof:name":"Atrica Inc",
    "wof:placetype":"venue"
},
  "geometry": {"coordinates":[-121.971729,37.379775],"type":"Point"}
}