{
  "type": "Feature",
  "properties": {
    "iso:country":"US",
    "sg:address":"620 W 135th St",
    "sg:city":"Gardena",
    "sg:classifiers":[
        {
            "category":"Home & Garden",
            "subcategory":"Household Appliances",
            "type":"Retail Goods"
        },
        {
            "category":"Retail",
            "subcategory":"Laundry & Dry Cleaning",
            "type":"Services"
        }
    ],
    "sg:phone":"+1 310 527 0770",
    "sg:postcode":"90248",
    "sg:province":"CA",
    "sg:tags":[
        "repair",
        "operated",
        "dryer",
        "laundries-self",
        "washer",
        "coin"
    ],
    "sg:website":"http://www.consolidatedsmart.com",
    "wof:name":"Consolidated Lauco Systems",
    "wof:placetype":"venue"
},
  "geometry": {"coordinates":[-118.285004,33.909302],"type":"Point"}
}