{
  "type": "Feature",
  "properties": {
    "iso:country":"US",
    "sg:address":"8708 S Gate Ave",
    "sg:city":"South Gate",
    "sg:classifiers":[
        {
            "category":"Food & Beverages",
            "subcategory":"Groceries & Convenience Stores",
            "type":"Retail Goods"
        }
    ],
    "sg:phone":"+1 323 566 0722",
    "sg:postcode":"90280",
    "sg:province":"CA",
    "wof:name":"7-Eleven",
    "wof:placetype":"venue"
},
  "geometry": {"coordinates":[-118.214309,33.956177],"type":"Point"}
}