{
  "type": "Feature",
  "properties": {
    "iso:country":"US",
    "sfac:artist":"Berlandina, Jane",
    "sfac:created_at":"01/01/1970 12:32:14 AM +0000",
    "sfac:credit_line":"Commissioned for Coit Tower",
    "sfac:display_dimensions":"9' X 34'",
    "sfac:location_description":"Public Display : District 3 : Coit Tower",
    "sfac:medium":"Egg tempura",
    "sfac:revision":"2-e44fb57214b1fa5a4b5489be285c6f71",
    "sfac:title":"Home Life",
    "wof:name":"Home Life",
    "wof:placetype":"venue"
},
  "geometry": {"coordinates":[-122.4058194,37.8023686],"type":"Point"}
}