{
  "type": "Feature",
  "properties": {
    "iso:country":"US",
    "sg:address":"2998 El Camino Real",
    "sg:city":"Santa Clara",
    "sg:classifiers":[
        {
            "category":"Health Services",
            "subcategory":"Dentist",
            "type":"Services"
        }
    ],
    "sg:phone":"+1 408 241 2397",
    "sg:postcode":"95051",
    "sg:province":"CA",
    "sg:website":"www.drahndentist.com/",
    "wof:name":"Central Dental Group",
    "wof:placetype":"venue"
},
  "geometry": {"coordinates":[-121.980226,37.352022],"type":"Point"}
}