{
  "type": "Feature",
  "properties": {
    "addr:full":"7926 Bear Mountain Blvd Bakersfield CA 93313",
    "addr:housenumber":"7926",
    "addr:postcode":"93313",
    "addr:street":"Bear Mountain Blvd",
    "iso:country":"US",
    "sg:address":"7926 Bear Mountain Blvd",
    "sg:city":"Bakersfield",
    "sg:classifiers":[
        {
            "category":"Freight",
            "type":"Transportation"
        }
    ],
    "sg:phone":"+1 661 831 1662",
    "sg:postcode":"93313",
    "sg:province":"CA",
    "sg:tags":[
        "operator",
        "local",
        "trucking"
    ],
    "wof:name":"West Kern Transfer",
    "wof:placetype":"venue"
},
  "geometry": {"coordinates":[-119.086665,35.208848],"type":"Point"}
}