{
  "type": "Feature",
  "properties": {
    "iso:country":"US",
    "sg:address":"621 W 1st St",
    "sg:city":"Tustin",
    "sg:classifiers":[
        {
            "category":"Health Services",
            "subcategory":"Clinic",
            "type":"Services"
        }
    ],
    "sg:phone":"+1 714 505 6563",
    "sg:postcode":"92780",
    "sg:province":"CA",
    "sg:tags":[
        "specialty",
        "outpatient"
    ],
    "wof:name":"Outpatient Center At Tustin RE",
    "wof:placetype":"venue"
},
  "geometry": {"coordinates":[-117.831208,33.745688],"type":"Point"}
}