{
  "type": "Feature",
  "properties": {
    "iso:country":"US",
    "sg:address":"1042 Palm St",
    "sg:city":"San Luis Obispo",
    "sg:classifiers":[
        {
            "category":"Retail",
            "subcategory":"Veterinary Services",
            "type":"Services"
        }
    ],
    "sg:phone":"+1 805 481 2595",
    "sg:postcode":"93401",
    "sg:province":"CA",
    "sg:tags":[
        "vet",
        "animal"
    ],
    "wof:name":"Grand Ave Veterinary Hospital",
    "wof:placetype":"venue"
},
  "geometry": {"coordinates":[-120.661259,35.283194],"type":"Point"}
}