{
  "type": "Feature",
  "properties": {
    "iso:country":"US",
    "sg:address":"85989 Ave 52",
    "sg:city":"Coachella",
    "sg:classifiers":[
        {
            "category":"Building & Trades",
            "subcategory":"Construction",
            "type":"Services"
        }
    ],
    "sg:phone":"+1 760 347 2291",
    "sg:postcode":"92236",
    "sg:province":"CA",
    "sg:tags":[
        "contractor"
    ],
    "wof:name":"Jones Brothers Construction",
    "wof:placetype":"venue"
},
  "geometry": {"coordinates":[-116.165317,33.671223],"type":"Point"}
}