{
  "type": "Feature",
  "properties": {
    "addr:full":"247 Hearst Ave San Francisco CA 94131",
    "addr:housenumber":"247",
    "addr:postcode":"94131",
    "addr:street":"Hearst Ave",
    "iso:country":"US",
    "sg:address":"247 Hearst Ave",
    "sg:city":"San Francisco",
    "sg:classifiers":[
        {
            "category":"Building & Trades",
            "subcategory":"Construction",
            "type":"Services"
        }
    ],
    "sg:phone":"+1 415 586 3925",
    "sg:postcode":"94131",
    "sg:province":"CA",
    "sg:tags":[
        "home",
        "handyman"
    ],
    "sg:website":"www.daddycanfixit.com",
    "wof:name":"Daddy Can Fix It",
    "wof:placetype":"venue"
},
  "geometry": {"coordinates":[-122.443119,37.730752],"type":"Point"}
}