{
  "type": "Feature",
  "properties": {
    "iso:country":"US",
    "sg:address":"850 Salt Lake Dr",
    "sg:city":"San Jose",
    "sg:classifiers":[
        {
            "category":"Professional",
            "subcategory":"Computer Services",
            "type":"Services"
        }
    ],
    "sg:phone":"+1 408 325 8439",
    "sg:postcode":"95133",
    "sg:province":"CA",
    "sg:tags":[
        "consultant",
        "designer"
    ],
    "wof:name":"Software Solutions",
    "wof:placetype":"venue"
},
  "geometry": {"coordinates":[-121.84714200000001,37.385718],"type":"Point"}
}