{
  "type": "Feature",
  "properties": {
    "iso:country":"US",
    "sg:address":"11374 Tuxford St",
    "sg:city":"Sun Valley",
    "sg:classifiers":[
        {
            "category":"Freight",
            "type":"Transportation"
        }
    ],
    "sg:phone":"+1 818 767 8576",
    "sg:postcode":"91352",
    "sg:province":"CA",
    "sg:tags":[
        "local",
        "storage",
        "trucking"
    ],
    "wof:name":"Amari Inc",
    "wof:placetype":"venue"
},
  "geometry": {"coordinates":[-118.378983,34.229089],"type":"Point"}
}