{
  "type": "Feature",
  "properties": {
    "iso:country":"US",
    "sg:address":"14430 Polk St",
    "sg:city":"Sylmar",
    "sg:classifiers":[
        {
            "category":"Government",
            "subcategory":"Fire Station",
            "type":"Public Place"
        }
    ],
    "sg:phone":"+1 818 756 8691",
    "sg:postcode":"91342",
    "sg:province":"CA",
    "sg:tags":[
        "protection"
    ],
    "wof:name":"Fire Dept-Station 91",
    "wof:placetype":"venue"
},
  "geometry": {"coordinates":[-118.447497,34.309575],"type":"Point"}
}