{
  "type": "Feature",
  "properties": {
    "iso:country":"US",
    "sg:address":"37012 Bernardin Dr",
    "sg:city":"Palmdale",
    "sg:classifiers":[
        {
            "category":"Social Services",
            "subcategory":"Child Care",
            "type":"Services"
        }
    ],
    "sg:phone":"+1 661 860 8659",
    "sg:postcode":"93550",
    "sg:province":"CA",
    "wof:name":"Little Blessings Family Child",
    "wof:placetype":"venue"
},
  "geometry": {"coordinates":[-118.076688,34.553322],"type":"Point"}
}