{
  "type": "Feature",
  "properties": {
    "iso:country":"US",
    "sg:address":"711 N Main St",
    "sg:city":"Fort Bragg",
    "sg:classifiers":[
        {
            "category":"Wholesale",
            "subcategory":"Stationery",
            "type":"Manufacturing & Wholesale Goods"
        }
    ],
    "sg:phone":"+1 707 964 9448",
    "sg:postcode":"95437",
    "sg:province":"CA",
    "sg:tags":[
        "cards",
        "greeting"
    ],
    "wof:name":"Studio Z Mendocino",
    "wof:placetype":"venue"
},
  "geometry": {"coordinates":[-123.806004,39.449411],"type":"Point"}
}