{
  "type": "Feature",
  "properties": {
    "iso:country":"US",
    "sg:address":"40601 de Portola Rd",
    "sg:city":"Temecula",
    "sg:classifiers":[
        {
            "category":"Organizations",
            "subcategory":"Professional Association",
            "type":"Services"
        }
    ],
    "sg:phone":"+1 951 302 9039",
    "sg:postcode":"92592",
    "sg:province":"CA",
    "wof:name":"Glenoak Hills Community",
    "wof:placetype":"venue"
},
  "geometry": {"coordinates":[-116.995965,33.550819],"type":"Point"}
}