{
  "type": "Feature",
  "properties": {
    "addr:full":"1034 Mission St South Pasadena CA 91030",
    "addr:housenumber":"1034",
    "addr:postcode":"91030",
    "addr:street":"Mission St",
    "iso:country":"US",
    "sg:address":"1034 Mission St",
    "sg:city":"South Pasadena",
    "sg:classifiers":[
        {
            "category":"Professional",
            "type":"Services"
        }
    ],
    "sg:phone":"+1 626 799 3011",
    "sg:postcode":"91030",
    "sg:province":"CA",
    "sg:tags":[
        "establishment"
    ],
    "wof:name":"Misha",
    "wof:placetype":"venue"
},
  "geometry": {"coordinates":[-118.15532,34.115827],"type":"Point"}
}