{
  "type": "Feature",
  "properties": {
    "iso:country":"US",
    "sg:address":"2224 Fox Hills Drive",
    "sg:city":"Los Angeles",
    "sg:classifiers":[
        {
            "category":"Building & Trades",
            "subcategory":"Construction",
            "type":"Services"
        }
    ],
    "sg:phone":"+1 310 552 8113",
    "sg:postcode":"90064",
    "sg:province":"CA",
    "sg:tags":[
        "contractor"
    ],
    "wof:name":"The Fox Hills Homeowners Assoc",
    "wof:placetype":"venue"
},
  "geometry": {"coordinates":[-118.415851,34.051779],"type":"Point"}
}