{
  "type": "Feature",
  "properties": {
    "addr:full":"137 Bay Street Suite 3 Santa Monica CA 90405",
    "addr:housenumber":"137",
    "addr:postcode":"90405",
    "addr:street":"Bay Street Suite 3",
    "iso:country":"US",
    "sg:address":"137 Bay Street Suite 3",
    "sg:city":"Santa Monica",
    "sg:classifiers":[
        {
            "category":"Professional",
            "subcategory":"Advertising",
            "type":"Services"
        }
    ],
    "sg:phone":"+1 310 314 5519",
    "sg:postcode":"90405",
    "sg:province":"CA",
    "sg:tags":[
        "user-generated-ads",
        "hollywood",
        "shorts",
        "commercials",
        "crowd-source",
        "crowdsource",
        "instructional-video",
        "music-video",
        "prediction",
        "crowdsourcing"
    ],
    "sg:website":"http://www.tongal.com",
    "wof:name":"Tongal",
    "wof:placetype":"venue"
},
  "geometry": {"coordinates":[-118.488964,34.007203],"type":"Point"}
}