{
  "type": "Feature",
  "properties": {
    "iso:country":"US",
    "sg:address":"34 E Essex St",
    "sg:city":"Stockton",
    "sg:classifiers":[
        {
            "category":"Shopping",
            "subcategory":"Bicycles & Sporting Goods",
            "type":"Retail Goods"
        },
        {
            "category":"Sports & Exercise",
            "subcategory":"Golf",
            "type":"Entertainment"
        }
    ],
    "sg:phone":"+1 209 462 4653",
    "sg:postcode":"95204",
    "sg:province":"CA",
    "sg:tags":[
        "equipment",
        "course",
        "supply"
    ],
    "wof:name":"Caddy Shack Golf",
    "wof:placetype":"venue"
},
  "geometry": {"coordinates":[-121.302905,37.987001],"type":"Point"}
}