{
  "type": "Feature",
  "properties": {
    "addr:full":"459 Duane St Redwood City CA 94062",
    "addr:housenumber":"459",
    "addr:postcode":"94062",
    "addr:street":"Duane St",
    "iso:country":"US",
    "sg:address":"459 Duane St",
    "sg:city":"Redwood City",
    "sg:classifiers":[
        {
            "category":"Professional",
            "type":"Services"
        }
    ],
    "sg:phone":"+1 650 367 6862",
    "sg:postcode":"94062",
    "sg:province":"CA",
    "wof:name":"Felicity House Home & Office",
    "wof:placetype":"venue"
},
  "geometry": {"coordinates":[-122.235158,37.481632],"type":"Point"}
}