{
  "type": "Feature",
  "properties": {
    "addr:full":"177 Jefferson Dr Menlo Park CA 94025",
    "addr:housenumber":"177",
    "addr:postcode":"94025",
    "addr:street":"Jefferson Dr",
    "iso:country":"US",
    "sg:address":"177 Jefferson Dr",
    "sg:city":"Menlo Park",
    "sg:classifiers":[
        {
            "category":"Professional",
            "subcategory":"Computer Services",
            "type":"Services"
        }
    ],
    "sg:phone":"+1 650 566 8800",
    "sg:postcode":"94025",
    "sg:province":"CA",
    "wof:name":"MPA Networks",
    "wof:placetype":"venue"
},
  "geometry": {"coordinates":[-122.17516500000001,37.483077],"type":"Point"}
}