{
  "type": "Feature",
  "properties": {
    "addr:full":"210 S Juniper St Escondido CA 92025",
    "addr:housenumber":"210",
    "addr:postcode":"92025",
    "addr:street":"S Juniper St",
    "iso:country":"US",
    "sg:address":"210 S Juniper St",
    "sg:city":"Escondido",
    "sg:classifiers":[
        {
            "category":"Insurance",
            "subcategory":"Insurance Agent",
            "type":"Services"
        }
    ],
    "sg:phone":"+1 760 746 4777",
    "sg:postcode":"92025",
    "sg:province":"CA",
    "wof:name":"Kevin S Svetich Insurance",
    "wof:placetype":"venue"
},
  "geometry": {"coordinates":[-117.077769,33.121782],"type":"Point"}
}