{
  "type": "Feature",
  "properties": {
    "addr:full":"3759 Ming Ave Bakersfield CA 93309",
    "addr:housenumber":"3759",
    "addr:postcode":"93309",
    "addr:street":"Ming Ave",
    "iso:country":"US",
    "sg:address":"3759 Ming Ave",
    "sg:city":"Bakersfield",
    "sg:classifiers":[
        {
            "category":"Shopping",
            "subcategory":"Department Store",
            "type":"Retail Goods"
        }
    ],
    "sg:phone":"+1 661 835 7523",
    "sg:postcode":"93309",
    "sg:province":"CA",
    "sg:website":"www.rossstores.com",
    "wof:name":"Ross Dress For Less",
    "wof:placetype":"venue"
},
  "geometry": {"coordinates":[-119.045536,35.339448],"type":"Point"}
}