{
  "type": "Feature",
  "properties": {
    "addr:full":"18701 Parthenia St Northridge CA 91324",
    "addr:housenumber":"18701",
    "addr:postcode":"91324",
    "addr:street":"Parthenia St",
    "iso:country":"US",
    "sg:address":"18701 Parthenia St",
    "sg:city":"Northridge",
    "sg:classifiers":[
        {
            "category":"Manufacturing",
            "subcategory":"Tools & Machinery",
            "type":"Manufacturing & Wholesale Goods"
        }
    ],
    "sg:phone":"+1 818 727 0451",
    "sg:postcode":"91324",
    "sg:province":"CA",
    "sg:tags":[
        "machine",
        "shop"
    ],
    "wof:name":"A S Machine Shop",
    "wof:placetype":"venue"
},
  "geometry": {"coordinates":[-118.543778,34.228232],"type":"Point"}
}