{
  "type": "Feature",
  "properties": {
    "iso:country":"US",
    "sg:address":"421 N Glendale Ave",
    "sg:city":"Glendale",
    "sg:classifiers":[
        {
            "category":"Shopping",
            "subcategory":"Musical Instruments",
            "type":"Retail Goods"
        }
    ],
    "sg:phone":"+1 323 245 3096",
    "sg:postcode":"91206",
    "sg:province":"CA",
    "sg:tags":[
        "teacher"
    ],
    "sg:website":"www.charlesmusicstore.com",
    "wof:name":"Charles Music Store & Studios",
    "wof:placetype":"venue"
},
  "geometry": {"coordinates":[-118.24400300000001,34.153198],"type":"Point"}
}