{
  "type": "Feature",
  "properties": {
    "addr:full":"3655 Nobel Drive San Diego CA 92122",
    "addr:housenumber":"3655",
    "addr:postcode":"92122",
    "addr:street":"Nobel Drive",
    "iso:country":"US",
    "sg:address":"3655 Nobel Drive",
    "sg:city":"San Diego",
    "sg:classifiers":[
        {
            "category":"Real Estate",
            "subcategory":"Architect",
            "type":"Services"
        }
    ],
    "sg:phone":"+1 858 458 5944",
    "sg:postcode":"92122",
    "sg:province":"CA",
    "wof:name":"J R Bardin Company",
    "wof:placetype":"venue"
},
  "geometry": {"coordinates":[-117.227332,32.868261],"type":"Point"}
}