{
  "type": "Feature",
  "properties": {
    "addr:full":"5860 Compton Ave Los Angeles CA 90001",
    "addr:housenumber":"5860",
    "addr:postcode":"90001",
    "addr:street":"Compton Ave",
    "iso:country":"US",
    "sg:address":"5860 Compton Ave",
    "sg:city":"Los Angeles",
    "sg:classifiers":[
        {
            "category":"Shopping",
            "subcategory":"Computers & Home Electronics",
            "type":"Retail Goods"
        }
    ],
    "sg:phone":"+1 323 589 1630",
    "sg:postcode":"90001",
    "sg:province":"CA",
    "sg:tags":[
        "television",
        "radio"
    ],
    "wof:name":"Joses' TV VCR Dvd & Stereo Rpr",
    "wof:placetype":"venue"
},
  "geometry": {"coordinates":[-118.24765600000001,33.988311],"type":"Point"}
}