{
  "type": "Feature",
  "properties": {
    "iso:country":"US",
    "sg:address":"26873 Sierra Hwy",
    "sg:city":"Newhall",
    "sg:classifiers":[
        {
            "category":"Professional",
            "subcategory":"Management & Consulting",
            "type":"Services"
        }
    ],
    "sg:phone":"+1 661 424 9342",
    "sg:postcode":"91321",
    "sg:province":"CA",
    "sg:tags":[
        "business"
    ],
    "wof:name":"Md3 Inc",
    "wof:placetype":"venue"
},
  "geometry": {"coordinates":[-118.467028,34.404134],"type":"Point"}
}