{
  "type": "Feature",
  "properties": {
    "iso:country":"US",
    "sg:address":"4715 Muirfield Ct",
    "sg:city":"Santa Rosa",
    "sg:classifiers":[
        {
            "category":"Manufacturing",
            "subcategory":"Tools & Machinery",
            "type":"Manufacturing & Wholesale Goods"
        }
    ],
    "sg:phone":"+1 707 526 5460",
    "sg:postcode":"95405",
    "sg:province":"CA",
    "sg:tags":[
        "industrial",
        "design",
        "mfg"
    ],
    "wof:name":"Concise Design",
    "wof:placetype":"venue"
},
  "geometry": {"coordinates":[-122.652574,38.423238],"type":"Point"}
}