{
  "type": "Feature",
  "properties": {
    "iso:country":"US",
    "sg:address":"581 Picasso Ct",
    "sg:city":"Fairfield",
    "sg:classifiers":[
        {
            "category":"Arts & Performance",
            "subcategory":"Theater",
            "type":"Entertainment"
        }
    ],
    "sg:phone":"+1 707 863 9723",
    "sg:postcode":"94534",
    "sg:province":"CA",
    "sg:tags":[
        "talent",
        "agency",
        "casting"
    ],
    "wof:name":"Ravenrock Productions",
    "wof:placetype":"venue"
},
  "geometry": {"coordinates":[-122.15317,38.217878],"type":"Point"}
}