{
  "type": "Feature",
  "properties": {
    "addr:full":"1775 E Daily Dr Ste I Camarillo CA 93010",
    "addr:housenumber":"1775",
    "addr:postcode":"93010",
    "addr:street":"E Daily Dr Ste I",
    "iso:country":"US",
    "sg:address":"1775 E Daily Dr Ste I",
    "sg:city":"Camarillo",
    "sg:classifiers":[
        {
            "category":"Coffee & Tea",
            "type":"Food & Drink"
        }
    ],
    "sg:phone":"+1 805 383 3775",
    "sg:postcode":"93010",
    "sg:province":"CA",
    "wof:name":"Oak Ranch Coffe Company",
    "wof:placetype":"venue"
},
  "geometry": {"coordinates":[-119.047997,34.217899],"type":"Point"}
}