{
  "type": "Feature",
  "properties": {
    "iso:country":"US",
    "sg:address":"2408 S Hacienda Blvd",
    "sg:city":"Hacienda Heights",
    "sg:classifiers":[
        {
            "category":"Utilities",
            "subcategory":"Telephone",
            "type":"Services"
        }
    ],
    "sg:phone":"+1 626 333 6788",
    "sg:postcode":"91745",
    "sg:province":"CA",
    "sg:tags":[
        "communications"
    ],
    "wof:name":"Dkc Gear",
    "wof:placetype":"venue"
},
  "geometry": {"coordinates":[-117.969123,33.990836],"type":"Point"}
}