{
  "type": "Feature",
  "properties": {
    "addr:full":"20939 Burgess Ct Bakersfield CA 93314",
    "addr:housenumber":"20939",
    "addr:postcode":"93314",
    "addr:street":"Burgess Ct",
    "iso:country":"US",
    "sg:address":"20939 Burgess Ct",
    "sg:city":"Bakersfield",
    "sg:classifiers":[
        {
            "category":"Building & Trades",
            "subcategory":"Construction",
            "type":"Services"
        }
    ],
    "sg:phone":"+1 661 588 4160",
    "sg:postcode":"93314",
    "sg:province":"CA",
    "sg:tags":[
        "pipe",
        "line",
        "contractor"
    ],
    "wof:name":"B & H Maintenance & Constr Inc",
    "wof:placetype":"venue"
},
  "geometry": {"coordinates":[-119.23454099999999,35.417014],"type":"Point"}
}