{
  "type": "Feature",
  "properties": {
    "iso:country":"US",
    "sg:address":"1117 Sunnyglenn Ave",
    "sg:city":"Ojai",
    "sg:classifiers":[
        {
            "category":"Social Services",
            "subcategory":"Adult Care",
            "type":"Services"
        }
    ],
    "sg:phone":"+1 805 646 6180",
    "sg:postcode":"93023",
    "sg:province":"CA",
    "sg:tags":[
        "home",
        "residential"
    ],
    "wof:name":"Villa At Ojai",
    "wof:placetype":"venue"
},
  "geometry": {"coordinates":[-119.232152,34.449981],"type":"Point"}
}