{
  "type": "Feature",
  "properties": {
    "addr:full":"1561 Rosewood Dr Healdsburg CA 95448",
    "addr:housenumber":"1561",
    "addr:postcode":"95448",
    "addr:street":"Rosewood Dr",
    "iso:country":"US",
    "sg:address":"1561 Rosewood Dr",
    "sg:city":"Healdsburg",
    "sg:classifiers":[
        {
            "category":"Government",
            "subcategory":"Office",
            "type":"Public Place"
        }
    ],
    "sg:phone":"+1 707 431 9130",
    "sg:postcode":"95448",
    "sg:province":"CA",
    "sg:tags":[
        "housing",
        "program"
    ],
    "wof:name":"Healdsburg Hope Homes Inc",
    "wof:placetype":"venue"
},
  "geometry": {"coordinates":[-122.870632,38.631761],"type":"Point"}
}