{
  "type": "Feature",
  "properties": {
    "iso:country":"US",
    "sg:address":"121 Gray Ave",
    "sg:city":"Santa Barbara",
    "sg:classifiers":[
        {
            "category":"Shopping",
            "subcategory":"Clothing, Apparel, & Fashions",
            "type":"Retail Goods"
        }
    ],
    "sg:phone":"+1 805 963 8727",
    "sg:postcode":"93101",
    "sg:province":"CA",
    "sg:tags":[
        "mail",
        "sport",
        "order"
    ],
    "wof:name":"BIG DOG SPORTSWEAR",
    "wof:placetype":"venue"
},
  "geometry": {"coordinates":[-119.689787,34.415344],"type":"Point"}
}