{
  "type": "Feature",
  "properties": {
    "iso:country":"US",
    "sg:address":"2230 International Blvd",
    "sg:city":"Oakland",
    "sg:classifiers":[
        {
            "category":"Retail",
            "subcategory":"Auto Repair",
            "type":"Services"
        }
    ],
    "sg:phone":"+1 510 434 1544",
    "sg:postcode":"94606",
    "sg:province":"CA",
    "sg:tags":[
        "wrecker"
    ],
    "wof:name":"Micki's Towing",
    "wof:placetype":"venue"
},
  "geometry": {"coordinates":[-122.237421,37.784459],"type":"Point"}
}