{
  "type": "Feature",
  "properties": {
    "addr:full":"2230 International Blvd Oakland CA 94606",
    "addr:housenumber":"2230",
    "addr:postcode":"94606",
    "addr:street":"International Blvd",
    "iso:country":"US",
    "sg:address":"2230 International Blvd",
    "sg:city":"Oakland",
    "sg:classifiers":[
        {
            "category":"Retail",
            "subcategory":"Auto Repair",
            "type":"Services"
        }
    ],
    "sg:phone":"+1 510 434 1544",
    "sg:postcode":"94606",
    "sg:province":"CA",
    "sg:tags":[
        "wrecker"
    ],
    "wof:name":"Micki's Towing",
    "wof:placetype":"venue"
},
  "geometry": {"coordinates":[-122.237421,37.784459],"type":"Point"}
}