{
  "type": "Feature",
  "properties": {
    "addr:full":"5632 Van Nuys Blvd Van Nuys CA 91401",
    "addr:housenumber":"5632",
    "addr:postcode":"91401",
    "addr:street":"Van Nuys Blvd",
    "iso:country":"US",
    "sg:address":"5632 Van Nuys Blvd",
    "sg:city":"Van Nuys",
    "sg:classifiers":[
        {
            "category":"Arts & Performance",
            "subcategory":"Theater",
            "type":"Entertainment"
        }
    ],
    "sg:phone":"+1 818 905 5180",
    "sg:postcode":"91401",
    "sg:province":"CA",
    "sg:tags":[
        "bureau"
    ],
    "sg:website":"www.worldsfair2004.com",
    "wof:name":"Rare Talent Booking Agency Inc",
    "wof:placetype":"venue"
},
  "geometry": {"coordinates":[-118.448632,34.175158],"type":"Point"}
}