{
  "type": "Feature",
  "properties": {
    "addr:full":"1030 Benicia Rd Vallejo CA 94591",
    "addr:postcode":"1030;94591",
    "addr:street":"Benicia Rd",
    "iso:country":"US",
    "sg:address":"1030 Benicia Rd",
    "sg:city":"Vallejo",
    "sg:classifiers":[
        {
            "category":"Restaurant",
            "type":"Food & Drink"
        }
    ],
    "sg:phone":"+1 707 557 5766",
    "sg:postcode":"94591",
    "sg:province":"CA",
    "wof:name":"Sardine Can Office",
    "wof:placetype":"venue"
},
  "geometry": {"coordinates":[-122.217866,38.092079],"type":"Point"}
}