{
  "type": "Feature",
  "properties": {
    "iso:country":"US",
    "sg:address":"415 Parkway Plz",
    "sg:city":"El Cajon",
    "sg:classifiers":[
        {
            "category":"Shopping",
            "subcategory":"Jewelry",
            "type":"Retail Goods"
        }
    ],
    "sg:phone":"+1 619 401 2295",
    "sg:postcode":"92020",
    "sg:province":"CA",
    "wof:name":"Piercing Pagoda",
    "wof:placetype":"venue"
},
  "geometry": {"coordinates":[-116.96399700000001,32.804798],"type":"Point"}
}