{
  "type": "Feature",
  "properties": {
    "addr:full":"5250 W Century Blvd Ste 105 Los Angeles CA 90045",
    "addr:housenumber":"5250",
    "addr:postcode":"90045",
    "addr:street":"W Century Blvd Ste 105",
    "iso:country":"US",
    "sg:address":"5250 W Century Blvd Ste 105",
    "sg:city":"Los Angeles",
    "sg:classifiers":[
        {
            "category":"Autos & Motor Vehicles",
            "subcategory":"Automobile Sales",
            "type":"Retail Goods"
        }
    ],
    "sg:phone":"+1 310 204 6000",
    "sg:postcode":"90045",
    "sg:province":"CA",
    "sg:tags":[
        "limo"
    ],
    "sg:website":"www.liveryautosales.com",
    "wof:name":"Livery Auto Sales",
    "wof:placetype":"venue"
},
  "geometry": {"coordinates":[-118.371039,33.945312],"type":"Point"}
}