{
  "type": "Feature",
  "properties": {
    "iso:country":"US",
    "sg:address":"2318 W Jefferson Blvd",
    "sg:city":"Los Angeles",
    "sg:classifiers":[
        {
            "category":"Food & Beverages",
            "subcategory":"Bakery",
            "type":"Retail Goods"
        }
    ],
    "sg:phone":"+1 323 766 1727",
    "sg:postcode":"90018",
    "sg:province":"CA",
    "sg:tags":[
        "baker"
    ],
    "wof:name":"2 Stars Bakery",
    "wof:placetype":"venue"
},
  "geometry": {"coordinates":[-118.321067,34.0255],"type":"Point"}
}