{
  "type": "Feature",
  "properties": {
    "addr:full":"14900 Nubia St Baldwin Park CA 91706",
    "addr:housenumber":"14900",
    "addr:postcode":"91706",
    "addr:street":"Nubia St",
    "iso:country":"US",
    "sg:address":"14900 Nubia St",
    "sg:city":"Baldwin Park",
    "sg:classifiers":[
        {
            "category":"Education",
            "subcategory":"School",
            "type":"Public Place"
        }
    ],
    "sg:phone":"+1 626 962 8512",
    "sg:postcode":"91706",
    "sg:province":"CA",
    "wof:name":"Pleasant View Elementary",
    "wof:placetype":"venue"
},
  "geometry": {"coordinates":[-117.95175,34.10328],"type":"Point"}
}