{
  "type": "Feature",
  "properties": {
    "iso:country":"US",
    "sg:address":"224 Jason Ct",
    "sg:city":"Corona",
    "sg:classifiers":[
        {
            "category":"Retail",
            "subcategory":"Auto Repair",
            "type":"Services"
        }
    ],
    "sg:phone":"+1 951 279 6393",
    "sg:postcode":"92879",
    "sg:province":"CA",
    "sg:tags":[
        "transmission",
        "tractor"
    ],
    "sg:website":"www.westernstatestrans.com",
    "wof:name":"Western States Converters",
    "wof:placetype":"venue"
},
  "geometry": {"coordinates":[-117.50518,33.890424],"type":"Point"}
}