{
  "type": "Feature",
  "properties": {
    "addr:full":"205 Washington Ave Santa Monica CA 90403",
    "addr:housenumber":"205",
    "addr:postcode":"90403",
    "addr:street":"Washington Ave",
    "iso:country":"US",
    "sg:address":"205 Washington Ave",
    "sg:city":"Santa Monica",
    "sg:classifiers":[
        {
            "category":"Professional",
            "subcategory":"Management & Consulting",
            "type":"Services"
        }
    ],
    "sg:phone":"+1 310 395 4723",
    "sg:postcode":"90403",
    "sg:province":"CA",
    "sg:tags":[
        "consultant"
    ],
    "wof:name":"Full Service Organizing",
    "wof:placetype":"venue"
},
  "geometry": {"coordinates":[-118.50299,34.020729],"type":"Point"}
}