{
  "type": "Feature",
  "properties": {
    "iso:country":"US",
    "sg:address":"1155 California Dr",
    "sg:city":"Burlingame",
    "sg:classifiers":[
        {
            "category":"Personal",
            "subcategory":"Beauty Salon",
            "type":"Services"
        }
    ],
    "sg:phone":"+1 650 347 8267",
    "sg:postcode":"94010",
    "sg:province":"CA",
    "sg:tags":[
        "care",
        "skin"
    ],
    "wof:name":"Euro Tan Sun Spa",
    "wof:placetype":"venue"
},
  "geometry": {"coordinates":[-122.362999,37.587299],"type":"Point"}
}