{
  "type": "Feature",
  "properties": {
    "addr:full":"8228 W 3rd St Los Angeles CA 90048",
    "addr:housenumber":"8228",
    "addr:postcode":"90048",
    "addr:street":"W 3Rd St",
    "iso:country":"US",
    "sg:address":"8228 W 3rd St",
    "sg:city":"Los Angeles",
    "sg:classifiers":[
        {
            "category":"Banks & Credit Unions",
            "subcategory":"Financial Services",
            "type":"Services"
        }
    ],
    "sg:phone":"+1 323 653 3853",
    "sg:postcode":"90048",
    "sg:province":"CA",
    "sg:tags":[
        "trust"
    ],
    "wof:name":"Gazin Family Trust",
    "wof:placetype":"venue"
},
  "geometry": {"coordinates":[-118.36793299999999,34.072407],"type":"Point"}
}