{
  "type": "Feature",
  "properties": {
    "addr:full":"14145 Red Hill Ave Tustin CA 92780",
    "addr:housenumber":"14145",
    "addr:postcode":"92780",
    "addr:street":"Red Hill Ave",
    "iso:country":"US",
    "sg:address":"14145 Red Hill Ave",
    "sg:city":"Tustin",
    "sg:classifiers":[
        {
            "category":"Education",
            "subcategory":"Dance Studio",
            "type":"Public Place"
        }
    ],
    "sg:phone":"+1 714 731 1357",
    "sg:postcode":"92780",
    "sg:province":"CA",
    "sg:tags":[
        "instruction",
        "dancing"
    ],
    "wof:name":"Korean Dance Studio",
    "wof:placetype":"venue"
},
  "geometry": {"coordinates":[-117.817144,33.731965],"type":"Point"}
}