{
  "type": "Feature",
  "properties": {
    "iso:country":"US",
    "sg:address":"3720 Madison Ave",
    "sg:city":"North Highlands",
    "sg:classifiers":[
        {
            "category":"Professional",
            "type":"Services"
        }
    ],
    "sg:phone":"+1 916 334 6051",
    "sg:postcode":"95660",
    "sg:province":"CA",
    "wof:name":"Ctgy",
    "wof:placetype":"venue"
},
  "geometry": {"coordinates":[-121.376531,38.661143],"type":"Point"}
}