{
  "type": "Feature",
  "properties": {
    "addr:full":"24 Harbor Island Rd Newport Beach CA 92660",
    "addr:housenumber":"24",
    "addr:postcode":"92660",
    "addr:street":"Harbor Island Rd",
    "iso:country":"US",
    "sg:address":"24 Harbor Island Rd",
    "sg:city":"Newport Beach",
    "sg:classifiers":[
        {
            "category":"Professional",
            "subcategory":"Management & Consulting",
            "type":"Services"
        }
    ],
    "sg:phone":"+1 949 833 9444",
    "sg:postcode":"92660",
    "sg:province":"CA",
    "sg:tags":[
        "consultant",
        "educational"
    ],
    "sg:website":"www.childtreatment.com",
    "wof:name":"Academic Guidance Svc",
    "wof:placetype":"venue"
},
  "geometry": {"coordinates":[-117.902432,33.61037],"type":"Point"}
}