{
  "type": "Feature",
  "properties": {
    "addr:full":"39020 Ocean Dr Gualala CA 95445",
    "addr:housenumber":"39020",
    "addr:postcode":"95445",
    "addr:street":"Ocean Dr",
    "iso:country":"US",
    "sg:address":"39020 Ocean Dr",
    "sg:city":"Gualala",
    "sg:classifiers":[
        {
            "category":"Real Estate",
            "subcategory":"Architect",
            "type":"Services"
        }
    ],
    "sg:phone":"+1 707 884 9553",
    "sg:postcode":"95445",
    "sg:province":"CA",
    "wof:name":"Theodore T Boutmy",
    "wof:placetype":"venue"
},
  "geometry": {"coordinates":[-123.53268199999999,38.769468],"type":"Point"}
}