{
  "type": "Feature",
  "properties": {
    "iso:country":"US",
    "sg:address":"3561 Mt Diablo Blvd",
    "sg:city":"Lafayette",
    "sg:phone":"+1 925 283 2855",
    "sg:postcode":"94549",
    "sg:province":"CA",
    "sg:website":"http://www.mskarensplace.com",
    "wof:name":"Ms Karen's Place",
    "wof:placetype":"venue"
},
  "geometry": {"coordinates":[-122.120987,37.891757],"type":"Point"}
}