{
  "type": "Feature",
  "properties": {
    "addr:full":"221 Morrow St Fort Bragg CA 95437",
    "addr:housenumber":"221",
    "addr:postcode":"95437",
    "addr:street":"Morrow St",
    "iso:country":"US",
    "sg:address":"221 Morrow St",
    "sg:city":"Fort Bragg",
    "sg:classifiers":[
        {
            "category":"Professional",
            "subcategory":"Lawyer & Legal Services",
            "type":"Services"
        }
    ],
    "sg:phone":"+1 707 964 5989",
    "sg:postcode":"95437",
    "sg:province":"CA",
    "sg:tags":[
        "attorney"
    ],
    "wof:name":"Meredith J Lintott Attorney",
    "wof:placetype":"venue"
},
  "geometry": {"coordinates":[-123.79665799999999,39.44311],"type":"Point"}
}