{
  "type": "Feature",
  "properties": {
    "iso:country":"US",
    "sg:address":"4100 Chiles Rd",
    "sg:city":"Davis",
    "sg:classifiers":[
        {
            "category":"Autos & Motor Vehicles",
            "subcategory":"Automobile Sales",
            "type":"Retail Goods"
        },
        {
            "category":"Retail",
            "subcategory":"Auto Rental",
            "type":"Services"
        }
    ],
    "sg:phone":"+1 530 747 0274",
    "sg:postcode":"95618",
    "sg:province":"CA",
    "sg:tags":[
        "car",
        "leasing",
        "truck"
    ],
    "sg:website":"http://budget.com/IYP_tl",
    "wof:name":"Budget Rent A Car",
    "wof:placetype":"venue"
},
  "geometry": {"coordinates":[-121.703003,38.550626],"type":"Point"}
}