{
  "type": "Feature",
  "properties": {
    "iso:country":"US",
    "sg:address":"2979 Temescal Ave",
    "sg:city":"Norco",
    "sg:classifiers":[
        {
            "category":"Professional",
            "type":"Services"
        }
    ],
    "sg:phone":"+1 951 273 1696",
    "sg:postcode":"92860",
    "sg:province":"CA",
    "wof:name":"Midway Consulting",
    "wof:placetype":"venue"
},
  "geometry": {"coordinates":[-117.541049,33.925334],"type":"Point"}
}