{
  "type": "Feature",
  "properties": {
    "addr:full":"56816 Aspen Dr Springville CA 93265",
    "addr:housenumber":"56816",
    "addr:postcode":"93265",
    "addr:street":"Aspen Dr",
    "iso:country":"US",
    "sg:address":"56816 Aspen Dr",
    "sg:city":"Springville",
    "sg:classifiers":[
        {
            "category":"Travel",
            "subcategory":"Hotels & Motels",
            "type":"Entertainment"
        }
    ],
    "sg:phone":"+1 559 542 2639",
    "sg:postcode":"93265",
    "sg:province":"CA",
    "sg:tags":[
        "breakfast",
        "accommodation",
        "bed"
    ],
    "wof:name":"Mountain Top Bed & Breakfast",
    "wof:placetype":"venue"
},
  "geometry": {"coordinates":[-118.53075699999999,36.100979],"type":"Point"}
}