{
  "type": "Feature",
  "properties": {
    "iso:country":"US",
    "sg:address":"9604 Las Tunas Dr",
    "sg:city":"Temple City",
    "sg:classifiers":[
        {
            "category":"Professional",
            "type":"Services"
        }
    ],
    "sg:phone":"+1 626 642 8787",
    "sg:postcode":"91780",
    "sg:province":"CA",
    "wof:name":"Jade Escrow",
    "wof:placetype":"venue"
},
  "geometry": {"coordinates":[-118.059562,34.10679],"type":"Point"}
}