{
  "type": "Feature",
  "properties": {
    "iso:country":"US",
    "sg:address":"1497 Solano Ave",
    "sg:city":"Albany",
    "sg:classifiers":[
        {
            "category":"Restaurant",
            "type":"Food & Drink"
        }
    ],
    "sg:phone":"+1 510 527 7222",
    "sg:postcode":"94706",
    "sg:province":"CA",
    "sg:tags":[
        "mexican"
    ],
    "sg:website":"www.hightechburrito.com",
    "wof:name":"High Tech Burrito",
    "wof:placetype":"venue"
},
  "geometry": {"coordinates":[-122.28800200000001,37.890999],"type":"Point"}
}