{
  "type": "Feature",
  "properties": {
    "addr:full":"2023 Beverly Boulevard Los Angeles CA 90057",
    "addr:housenumber":"2023",
    "addr:postcode":"90057",
    "addr:street":"Beverly Boulevard",
    "iso:country":"US",
    "sg:address":"2023 Beverly Boulevard",
    "sg:city":"Los Angeles",
    "sg:classifiers":[
        {
            "category":"Health Services",
            "subcategory":"Dentist",
            "type":"Services"
        }
    ],
    "sg:phone":"+1 213 353 9930",
    "sg:postcode":"90057",
    "sg:province":"CA",
    "wof:name":"Octoman Celia DDS",
    "wof:placetype":"venue"
},
  "geometry": {"coordinates":[-118.269638,34.066247],"type":"Point"}
}