{
  "type": "Feature",
  "properties": {
    "addr:full":"912 High St Delano CA 93215",
    "addr:housenumber":"912",
    "addr:postcode":"93215",
    "addr:street":"High St",
    "iso:country":"US",
    "sg:address":"912 High St",
    "sg:city":"Delano",
    "sg:classifiers":[
        {
            "category":"Professional",
            "subcategory":"Accounting & Tax Preparation",
            "type":"Services"
        }
    ],
    "sg:phone":"+1 661 725 3246",
    "sg:postcode":"93215",
    "sg:province":"CA",
    "sg:tags":[
        "accountant"
    ],
    "wof:name":"Hocking Denton Palmquist",
    "wof:placetype":"venue"
},
  "geometry": {"coordinates":[-119.246855,35.768726],"type":"Point"}
}