{
  "type": "Feature",
  "properties": {
    "addr:full":"3220 Watt Ave Sacramento CA 95821",
    "addr:housenumber":"3220",
    "addr:postcode":"95821",
    "addr:street":"Watt Ave",
    "iso:country":"US",
    "sg:address":"3220 Watt Ave",
    "sg:city":"Sacramento",
    "sg:classifiers":[
        {
            "category":"Local Transit",
            "type":"Transportation"
        }
    ],
    "sg:phone":"+1 916 485 4664",
    "sg:postcode":"95821",
    "sg:province":"CA",
    "sg:tags":[
        "passenger"
    ],
    "wof:name":"At Your Service Limousine",
    "wof:placetype":"venue"
},
  "geometry": {"coordinates":[-121.38288900000001,38.625213],"type":"Point"}
}