{
  "type": "Feature",
  "properties": {
    "addr:full":"450 N Mountain Ave Upland CA 91786",
    "addr:housenumber":"450",
    "addr:postcode":"91786",
    "addr:street":"N Mountain Ave",
    "iso:country":"US",
    "sg:address":"450 N Mountain Ave",
    "sg:city":"Upland",
    "sg:classifiers":[
        {
            "category":"Personal",
            "type":"Services"
        }
    ],
    "sg:phone":"+1 909 985 2733",
    "sg:postcode":"91786",
    "sg:province":"CA",
    "sg:tags":[
        "dating"
    ],
    "wof:name":"Great Expectations",
    "wof:placetype":"venue"
},
  "geometry": {"coordinates":[-117.670091,34.09845],"type":"Point"}
}