{
  "type": "Feature",
  "properties": {
    "addr:full":"425 Bel Marin Keys Blvd Novato CA 94949",
    "addr:housenumber":"425",
    "addr:postcode":"94949",
    "addr:street":"Bel Marin Keys Blvd",
    "iso:country":"US",
    "sg:address":"425 Bel Marin Keys Blvd",
    "sg:city":"Novato",
    "sg:classifiers":[
        {
            "category":"Personal",
            "type":"Services"
        },
        {
            "category":"Retail",
            "subcategory":"Auto Rental",
            "type":"Services"
        },
        {
            "category":"Building & Trades",
            "subcategory":"Equipment Rental",
            "type":"Services"
        },
        {
            "category":"Retail",
            "subcategory":"Storage",
            "type":"Services"
        }
    ],
    "sg:phone":"+1 415 382 1751",
    "sg:postcode":"94949",
    "sg:province":"CA",
    "sg:tags":[
        "renting",
        "moving-self",
        "full",
        "leasing",
        "household",
        "commercial",
        "truck",
        "moving",
        "mover",
        "self",
        "trailer"
    ],
    "sg:website":"http://www.uhaul.com/Locations/Rentals-near-Novato-CA-94949/039534",
    "wof:name":"U-Haul Neighborhood Dealer - Empire Mini Storage Novato",
    "wof:placetype":"venue"
},
  "geometry": {"coordinates":[-122.535365,38.076872],"type":"Point"}
}