{
  "type": "Feature",
  "properties": {
    "iso:country":"US",
    "sg:address":"3720 San Gabriel River Pkwy",
    "sg:city":"Pico Rivera",
    "sg:classifiers":[
        {
            "category":"Manufacturing",
            "subcategory":"Metals",
            "type":"Manufacturing & Wholesale Goods"
        }
    ],
    "sg:phone":"+1 562 692 0466",
    "sg:postcode":"90660",
    "sg:province":"CA",
    "sg:tags":[
        "plating"
    ],
    "wof:name":"W F Scott & Co",
    "wof:placetype":"venue"
},
  "geometry": {"coordinates":[-118.061917,34.013291],"type":"Point"}
}