{
  "type": "Feature",
  "properties": {
    "addr:full":"3939 Snell Ave San Jose CA 95136",
    "addr:housenumber":"3939",
    "addr:postcode":"95136",
    "addr:street":"Snell Ave",
    "iso:country":"US",
    "sg:address":"3939 Snell Ave",
    "sg:city":"San Jose",
    "sg:classifiers":[
        {
            "category":"Autos & Motor Vehicles",
            "subcategory":"Auto Supplies",
            "type":"Retail Goods"
        }
    ],
    "sg:phone":"+1 408 225 2800",
    "sg:postcode":"95136",
    "sg:province":"CA",
    "sg:tags":[
        "tire"
    ],
    "wof:name":"El Ranchero Tires",
    "wof:placetype":"venue"
},
  "geometry": {"coordinates":[-121.842446,37.277238],"type":"Point"}
}