{
  "type": "Feature",
  "properties": {
    "addr:full":"19865 Geyserville Ave Geyserville CA 95441",
    "addr:housenumber":"19865",
    "addr:postcode":"95441",
    "addr:street":"Geyserville Ave",
    "iso:country":"US",
    "sg:address":"19865 Geyserville Ave",
    "sg:city":"Geyserville",
    "sg:classifiers":[
        {
            "category":"Retail",
            "subcategory":"Auto Repair",
            "type":"Services"
        }
    ],
    "sg:phone":"+1 707 857 4500",
    "sg:postcode":"95441",
    "sg:province":"CA",
    "sg:tags":[
        "automobile",
        "top",
        "upholstery"
    ],
    "wof:name":"Mercedes Tops & Upholstery",
    "wof:placetype":"venue"
},
  "geometry": {"coordinates":[-122.886696,38.692132],"type":"Point"}
}