{
  "type": "Feature",
  "properties": {
    "addr:full":"335 N Maple Drive Beverly Hills CA 90210",
    "addr:housenumber":"335",
    "addr:postcode":"90210",
    "addr:street":"N Maple Drive",
    "iso:country":"US",
    "sg:address":"335 N Maple Drive",
    "sg:city":"Beverly Hills",
    "sg:classifiers":[
        {
            "category":"Banks & Credit Unions",
            "subcategory":"Investment Brokerage",
            "type":"Services"
        }
    ],
    "sg:phone":"+1 310 859 7644",
    "sg:postcode":"90210",
    "sg:province":"CA",
    "sg:tags":[
        "investing"
    ],
    "wof:name":"A R Asset Mgmt.",
    "wof:placetype":"venue"
},
  "geometry": {"coordinates":[-118.39353800000001,34.073632],"type":"Point"}
}