{
  "type": "Feature",
  "properties": {
    "iso:country":"US",
    "sg:address":"454 N Wiget Ln",
    "sg:city":"Walnut Creek",
    "sg:classifiers":[
        {
            "category":"Insurance",
            "subcategory":"Insurance Agent",
            "type":"Services"
        }
    ],
    "sg:phone":"+1 925 906 1000",
    "sg:postcode":"94598",
    "sg:province":"CA",
    "sg:website":"www.clmis.com",
    "wof:name":"Cravens Leffler & Mc Cormick",
    "wof:placetype":"venue"
},
  "geometry": {"coordinates":[-122.027221,37.929194],"type":"Point"}
}