{
  "type": "Feature",
  "properties": {
    "iso:country":"US",
    "sg:address":"100 Technology Cir",
    "sg:city":"Scotts Valley",
    "sg:classifiers":[
        {
            "category":"Manufacturing",
            "subcategory":"Tools & Machinery",
            "type":"Manufacturing & Wholesale Goods"
        }
    ],
    "sg:phone":"+1 831 438 0701",
    "sg:postcode":"95066",
    "sg:province":"CA",
    "sg:tags":[
        "disc",
        "industrial",
        "wafer",
        "mfg",
        "cleaners",
        "hard",
        "computer",
        "clea"
    ],
    "sg:website":"www.oliverdesign.net",
    "wof:name":"Oliver Design Inc",
    "wof:placetype":"venue"
},
  "geometry": {"coordinates":[-122.00821,37.059155],"type":"Point"}
}