{
  "type": "Feature",
  "properties": {
    "addr:full":"700 Joliet Way Napa CA 94559",
    "addr:housenumber":"700",
    "addr:postcode":"94559",
    "addr:street":"Joliet Way",
    "iso:country":"US",
    "sg:address":"700 Joliet Way",
    "sg:city":"Napa",
    "sg:classifiers":[
        {
            "category":"Freight",
            "type":"Transportation"
        }
    ],
    "sg:phone":"+1 707 224 7727",
    "sg:postcode":"94559",
    "sg:province":"CA",
    "sg:tags":[
        "general"
    ],
    "wof:name":"River Park Self Storage",
    "wof:placetype":"venue"
},
  "geometry": {"coordinates":[-122.286568,38.28064],"type":"Point"}
}