{
  "type": "Feature",
  "properties": {
    "iso:country":"US",
    "sg:address":"9611 Robin Ave",
    "sg:city":"Westminster",
    "sg:classifiers":[
        {
            "category":"Manufacturing",
            "subcategory":"Tools & Machinery",
            "type":"Manufacturing & Wholesale Goods"
        }
    ],
    "sg:phone":"+1 714 839 0663",
    "sg:postcode":"92683",
    "sg:province":"CA",
    "sg:tags":[
        "measuring",
        "instrument",
        "electrical",
        "mfg"
    ],
    "wof:name":"American Network Technology",
    "wof:placetype":"venue"
},
  "geometry": {"coordinates":[-117.96241499999999,33.738507],"type":"Point"}
}