{
  "type": "Feature",
  "properties": {
    "addr:full":"114 E 20th St Costa Mesa CA 92627",
    "addr:housenumber":"114",
    "addr:postcode":"92627",
    "addr:street":"E 20Th St",
    "iso:country":"US",
    "sg:address":"114 E 20th St",
    "sg:city":"Costa Mesa",
    "sg:classifiers":[
        {
            "category":"Building & Trades",
            "subcategory":"Cleaning & Sanitation",
            "type":"Services"
        }
    ],
    "sg:phone":"+1 949 631 2526",
    "sg:postcode":"92627",
    "sg:province":"CA",
    "sg:tags":[
        "butler",
        "maid"
    ],
    "wof:name":"Euro Maid",
    "wof:placetype":"venue"
},
  "geometry": {"coordinates":[-117.913326,33.645954],"type":"Point"}
}