{
  "type": "Feature",
  "properties": {
    "iso:country":"US",
    "sg:address":"14175 Lodgepole Dr",
    "sg:city":"Penn Valley",
    "sg:classifiers":[
        {
            "category":"Professional",
            "subcategory":"Business Services",
            "type":"Services"
        }
    ],
    "sg:phone":"+1 530 432 1282",
    "sg:postcode":"95946",
    "sg:province":"CA",
    "wof:name":"J & B Telecom",
    "wof:placetype":"venue"
},
  "geometry": {"coordinates":[-121.189181,39.247973],"type":"Point"}
}