{
  "type": "Feature",
  "properties": {
    "addr:full":"2701 Dow Ave Tustin CA 92780",
    "addr:housenumber":"2701",
    "addr:postcode":"92780",
    "addr:street":"Dow Ave",
    "iso:country":"US",
    "sg:address":"2701 Dow Ave",
    "sg:city":"Tustin",
    "sg:classifiers":[
        {
            "category":"Wholesale",
            "subcategory":"Computers",
            "type":"Manufacturing & Wholesale Goods"
        }
    ],
    "sg:phone":"+1 714 573 2721",
    "sg:postcode":"92780",
    "sg:province":"CA",
    "wof:name":"Itochu Technology Inc",
    "wof:placetype":"venue"
},
  "geometry": {"coordinates":[-117.80679600000001,33.711755],"type":"Point"}
}