{
  "type": "Feature",
  "properties": {
    "addr:full":"19327 Ventura Blvd Tarzana CA 91356",
    "addr:housenumber":"19327",
    "addr:postcode":"91356",
    "addr:street":"Ventura Blvd",
    "iso:country":"US",
    "sg:address":"19327 Ventura Blvd",
    "sg:city":"Tarzana",
    "sg:classifiers":[
        {
            "category":"Banks & Credit Unions",
            "subcategory":"Bank",
            "type":"Services"
        }
    ],
    "sg:phone":"+1 818 999 2224",
    "sg:postcode":"91356",
    "sg:province":"CA",
    "sg:tags":[
        "loan",
        "real estate"
    ],
    "wof:name":"RMG Funding",
    "wof:placetype":"venue"
},
  "geometry": {"coordinates":[-118.553905,34.172735],"type":"Point"}
}