{
  "type": "Feature",
  "properties": {
    "addr:full":"1075 S Vail Ave Montebello CA 90640",
    "addr:housenumber":"1075",
    "addr:postcode":"90640",
    "addr:street":"S Vail Ave",
    "iso:country":"US",
    "sg:address":"1075 S Vail Ave",
    "sg:city":"Montebello",
    "sg:classifiers":[
        {
            "category":"Manufacturing",
            "subcategory":"Apparel",
            "type":"Manufacturing & Wholesale Goods"
        }
    ],
    "sg:phone":"+1 323 278 9200",
    "sg:postcode":"90640",
    "sg:province":"CA",
    "sg:tags":[
        "outerwear",
        "mfg"
    ],
    "sg:website":"www.amcruiser.com",
    "wof:name":"American Cruiser Inc",
    "wof:placetype":"venue"
},
  "geometry": {"coordinates":[-118.127472,33.997323],"type":"Point"}
}