{
  "type": "Feature",
  "properties": {
    "addr:full":"153 Kentucky St Petaluma CA 94952",
    "addr:housenumber":"153",
    "addr:postcode":"94952",
    "addr:street":"Kentucky St",
    "iso:country":"US",
    "sg:address":"153 Kentucky St",
    "sg:city":"Petaluma",
    "sg:classifiers":[
        {
            "category":"Shopping",
            "subcategory":"Used Merchandise",
            "type":"Retail Goods"
        }
    ],
    "sg:phone":"+1 707 776 2873",
    "sg:postcode":"94952",
    "sg:province":"CA",
    "wof:name":"Summer Cottage Antiques",
    "wof:placetype":"venue"
},
  "geometry": {"coordinates":[-122.64164,38.234621],"type":"Point"}
}