{
  "type": "Feature",
  "properties": {
    "iso:country":"US",
    "sg:address":"135 C St",
    "sg:city":"Lemoore",
    "sg:classifiers":[
        {
            "category":"Personal",
            "subcategory":"Beauty Salon",
            "type":"Services"
        }
    ],
    "sg:phone":"+1 559 924 3022",
    "sg:postcode":"93245",
    "sg:province":"CA",
    "sg:tags":[
        "shop",
        "equipment",
        "supplies-wholesale",
        "salons-equipment",
        "manufacturer"
    ],
    "wof:name":"Trend Setters",
    "wof:placetype":"venue"
},
  "geometry": {"coordinates":[-119.782132,36.301112],"type":"Point"}
}