{
  "type": "Feature",
  "properties": {
    "addr:full":"2960 Alvarado St San Leandro CA 94577",
    "addr:housenumber":"2960",
    "addr:postcode":"94577",
    "addr:street":"Alvarado St",
    "iso:country":"US",
    "sg:address":"2960 Alvarado St",
    "sg:city":"San Leandro",
    "sg:classifiers":[
        {
            "category":"Freight",
            "type":"Transportation"
        }
    ],
    "sg:phone":"+1 510 346 9901",
    "sg:postcode":"94577",
    "sg:province":"CA",
    "sg:tags":[
        "delivery"
    ],
    "sg:website":"www.movingmaids.com",
    "wof:name":"Hays Home Delivery Svc Inc",
    "wof:placetype":"venue"
},
  "geometry": {"coordinates":[-122.154201,37.708714],"type":"Point"}
}