{
  "type": "Feature",
  "properties": {
    "iso:country":"US",
    "sg:address":"4351 Hillview Dr",
    "sg:city":"Pittsburg",
    "sg:classifiers":[
        {
            "category":"Professional",
            "subcategory":"Detective & Security Services",
            "type":"Services"
        }
    ],
    "sg:phone":"+1 925 439 9504",
    "sg:postcode":"94565",
    "sg:province":"CA",
    "sg:tags":[
        "information",
        "bureau"
    ],
    "wof:name":"Ligaya A Diokno",
    "wof:placetype":"venue"
},
  "geometry": {"coordinates":[-121.89161900000001,37.992661],"type":"Point"}
}