{
  "type": "Feature",
  "properties": {
    "addr:full":"7920 Frost St San Diego CA 92123",
    "addr:housenumber":"7920",
    "addr:postcode":"92123",
    "addr:street":"Frost St",
    "iso:country":"US",
    "sg:address":"7920 Frost St",
    "sg:city":"San Diego",
    "sg:classifiers":[
        {
            "category":"Professional",
            "subcategory":"Management & Consulting",
            "type":"Services"
        }
    ],
    "sg:phone":"+1 858 751 0136",
    "sg:postcode":"92123",
    "sg:province":"CA",
    "sg:tags":[
        "consultant",
        "medical",
        "legal"
    ],
    "wof:name":"Absolute Solutions",
    "wof:placetype":"venue"
},
  "geometry": {"coordinates":[-117.154993,32.800329],"type":"Point"}
}