{
  "type": "Feature",
  "properties": {
    "iso:country":"US",
    "sg:address":"7197 Brockton Ave",
    "sg:city":"Riverside",
    "sg:classifiers":[
        {
            "category":"Real Estate",
            "subcategory":"Real Estate Agent",
            "type":"Services"
        }
    ],
    "sg:phone":"+1 951 682 8184",
    "sg:postcode":"92506",
    "sg:province":"CA",
    "sg:tags":[
        "management"
    ],
    "wof:name":"Lighthouse Property Management",
    "wof:placetype":"venue"
},
  "geometry": {"coordinates":[-117.395389,33.944123],"type":"Point"}
}