{
  "type": "Feature",
  "properties": {
    "addr:full":"6957 Greenback Ln Citrus Heights CA 95621",
    "addr:housenumber":"6957",
    "addr:postcode":"95621",
    "addr:street":"Greenback Ln",
    "iso:country":"US",
    "sg:address":"6957 Greenback Ln",
    "sg:city":"Citrus Heights",
    "sg:classifiers":[
        {
            "category":"Building & Trades",
            "subcategory":"Plumbing",
            "type":"Services"
        }
    ],
    "sg:phone":"+1 916 995 1706",
    "sg:postcode":"95621",
    "sg:province":"CA",
    "sg:tags":[
        "contractor"
    ],
    "wof:name":"Rja Heating & Air Conditioning",
    "wof:placetype":"venue"
},
  "geometry": {"coordinates":[-121.301897,38.678121],"type":"Point"}
}