{
  "type": "Feature",
  "properties": {
    "iso:country":"US",
    "sg:address":"316 W Pacific Coast Hwy",
    "sg:city":"Wilmington",
    "sg:classifiers":[
        {
            "category":"Arena",
            "subcategory":"Sports Club",
            "type":"Entertainment"
        }
    ],
    "sg:phone":"+1 310 835 5917",
    "sg:postcode":"90744",
    "sg:province":"CA",
    "sg:tags":[
        "martial art"
    ],
    "wof:name":"Karate Studio",
    "wof:placetype":"venue"
},
  "geometry": {"coordinates":[-118.265999,33.7911],"type":"Point"}
}