{
  "type": "Feature",
  "properties": {
    "addr:full":"255 E Temple St Los Angeles CA 90012",
    "addr:housenumber":"255",
    "addr:postcode":"90012",
    "addr:street":"E Temple St",
    "iso:country":"US",
    "sg:address":"255 E Temple St",
    "sg:city":"Los Angeles",
    "sg:classifiers":[
        {
            "category":"Education",
            "subcategory":"Preschool",
            "type":"Public Place"
        }
    ],
    "sg:phone":"+1 213 894 1556",
    "sg:postcode":"90012",
    "sg:province":"CA",
    "sg:website":"www.mtwashingtonpreschools.org",
    "wof:name":"Harry Pregerson Child Care Center",
    "wof:placetype":"venue"
},
  "geometry": {"coordinates":[-118.239248,34.052848],"type":"Point"}
}