{
  "type": "Feature",
  "properties": {
    "addr:full":"12502 Riverside Drive Valley Village CA 91607",
    "addr:housenumber":"12502",
    "addr:postcode":"91607",
    "addr:street":"Riverside Drive",
    "iso:country":"US",
    "sg:address":"12502 Riverside Drive",
    "sg:city":"Valley Village",
    "sg:classifiers":[
        {
            "category":"Ice Cream",
            "type":"Food & Drink"
        }
    ],
    "sg:phone":"+1 818 505 8415",
    "sg:postcode":"91607",
    "sg:province":"CA",
    "sg:tags":[
        "frozen",
        "yogurt"
    ],
    "wof:name":"Sweet Fruit Bar Frozen Yogurt",
    "wof:placetype":"venue"
},
  "geometry": {"coordinates":[-118.405736,34.157632],"type":"Point"}
}