{
  "type": "Feature",
  "properties": {
    "addr:full":"601 S Fremont Ave Alhambra CA 91803",
    "addr:housenumber":"601",
    "addr:postcode":"91803",
    "addr:street":"S Fremont Ave",
    "iso:country":"US",
    "sg:address":"601 S Fremont Ave",
    "sg:city":"Alhambra",
    "sg:classifiers":[
        {
            "category":"Food & Beverages",
            "subcategory":"Groceries & Convenience Stores",
            "type":"Retail Goods"
        }
    ],
    "sg:phone":"+1 626 570 1224",
    "sg:postcode":"91803",
    "sg:province":"CA",
    "sg:website":"www.7-eleven.com",
    "wof:name":"7-Eleven",
    "wof:placetype":"venue"
},
  "geometry": {"coordinates":[-118.15201399999999,34.087827],"type":"Point"}
}