{
  "type": "Feature",
  "properties": {
    "iso:country":"US",
    "sg:address":"14871 Stockdale St",
    "sg:city":"Baldwin Park",
    "sg:classifiers":[
        {
            "category":"Manufacturing",
            "subcategory":"Printing",
            "type":"Manufacturing & Wholesale Goods"
        }
    ],
    "sg:phone":"+1 626 824 4507",
    "sg:postcode":"91706",
    "sg:province":"CA",
    "sg:tags":[
        "publishing"
    ],
    "wof:name":"Alatorre Publishing & Prom",
    "wof:placetype":"venue"
},
  "geometry": {"coordinates":[-117.951628,34.077024],"type":"Point"}
}