{
  "type": "Feature",
  "properties": {
    "iso:country":"US",
    "sg:address":"4141 Manzanita Ave",
    "sg:city":"Carmichael",
    "sg:classifiers":[
        {
            "category":"Banks & Credit Unions",
            "subcategory":"Bank",
            "type":"Services"
        }
    ],
    "sg:phone":"+1 916 483 5550",
    "sg:postcode":"95608",
    "sg:province":"CA",
    "sg:tags":[
        "loan",
        "real estate"
    ],
    "wof:name":"Novastar Home Mortgage",
    "wof:placetype":"venue"
},
  "geometry": {"coordinates":[-121.328018,38.639971],"type":"Point"}
}