{
  "type": "Feature",
  "properties": {
    "addr:full":"2739 Allegiance Ln Riverbank CA 95357",
    "addr:housenumber":"2739",
    "addr:postcode":"95357",
    "addr:street":"Allegiance Ln",
    "iso:country":"US",
    "sg:address":"2739 Allegiance Ln",
    "sg:city":"Riverbank",
    "sg:classifiers":[
        {
            "category":"Building & Trades",
            "subcategory":"Electrical",
            "type":"Services"
        }
    ],
    "sg:phone":"+1 209 606 4006",
    "sg:postcode":"95357",
    "sg:province":"CA",
    "sg:tags":[
        "installation"
    ],
    "wof:name":"Security System Solutions",
    "wof:placetype":"venue"
},
  "geometry": {"coordinates":[-120.94631200000001,37.715321],"type":"Point"}
}