{
  "type": "Feature",
  "properties": {
    "iso:country":"US",
    "sg:address":"8786 19th St",
    "sg:city":"Rancho Cucamonga",
    "sg:classifiers":[
        {
            "category":"Ice Cream",
            "type":"Food & Drink"
        }
    ],
    "sg:menulink":"http://www.allmenus.com/ca/ontario/242647-baskin-robbins/menu/",
    "sg:phone":"+1 909 989 8055",
    "sg:postcode":"91701",
    "sg:province":"CA",
    "sg:tags":[
        "american"
    ],
    "wof:name":"Baskin-Robbins",
    "wof:placetype":"venue"
},
  "geometry": {"coordinates":[-117.61418399999999,34.13262],"type":"Point"}
}