{
  "type": "Feature",
  "properties": {
    "iso:country":"US",
    "sg:address":"1801 Morena Blvd",
    "sg:city":"San Diego",
    "sg:classifiers":[
        {
            "category":"Banks & Credit Unions",
            "subcategory":"Investment Brokerage",
            "type":"Services"
        }
    ],
    "sg:phone":"+1 619 275 2538",
    "sg:postcode":"92110",
    "sg:province":"CA",
    "sg:tags":[
        "financial"
    ],
    "wof:name":"American Express",
    "wof:placetype":"venue"
},
  "geometry": {"coordinates":[-117.207402,32.780419],"type":"Point"}
}