{
  "type": "Feature",
  "properties": {
    "iso:country":"US",
    "sg:address":"1013 Ramona Ave",
    "sg:city":"San Jose",
    "sg:classifiers":[
        {
            "category":"Wholesale",
            "subcategory":"Medical Equipment & Supplies",
            "type":"Manufacturing & Wholesale Goods"
        }
    ],
    "sg:phone":"+1 408 294 2002",
    "sg:postcode":"95125",
    "sg:province":"CA",
    "sg:tags":[
        "hospital"
    ],
    "wof:name":"Almar Safety Products",
    "wof:placetype":"venue"
},
  "geometry": {"coordinates":[-121.901659,37.311453],"type":"Point"}
}