{
  "type": "Feature",
  "properties": {
    "addr:full":"1430 Arroyo Way Walnut Creek CA 94596",
    "addr:housenumber":"1430",
    "addr:postcode":"94596",
    "addr:street":"Arroyo Way",
    "iso:country":"US",
    "sg:address":"1430 Arroyo Way",
    "sg:city":"Walnut Creek",
    "sg:classifiers":[
        {
            "category":"Personal",
            "subcategory":"Beauty Salon",
            "type":"Services"
        }
    ],
    "sg:phone":"+1 925 932 8103",
    "sg:postcode":"94596",
    "sg:province":"CA",
    "wof:name":"Manely Hair",
    "wof:placetype":"venue"
},
  "geometry": {"coordinates":[-122.062202,37.905128],"type":"Point"}
}