{
  "type": "Feature",
  "properties": {
    "iso:country":"US",
    "sg:address":"1327 Webster St",
    "sg:city":"Alameda",
    "sg:classifiers":[
        {
            "category":"Shopping",
            "subcategory":"Catalog Store",
            "type":"Retail Goods"
        }
    ],
    "sg:phone":"+1 510 522 0962",
    "sg:postcode":"94501",
    "sg:province":"CA",
    "sg:tags":[
        "mail",
        "house"
    ],
    "wof:name":"St Johns",
    "wof:placetype":"venue"
},
  "geometry": {"coordinates":[-122.276929,37.770983],"type":"Point"}
}