{
  "type": "Feature",
  "properties": {
    "iso:country":"US",
    "sg:address":"515 L Street",
    "sg:city":"Sacramento",
    "sg:classifiers":[
        {
            "category":"Insurance",
            "subcategory":"Health Insurance",
            "type":"Services"
        }
    ],
    "sg:phone":"+1 916 448 3041",
    "sg:postcode":"95814",
    "sg:province":"CA",
    "sg:tags":[
        "market"
    ],
    "wof:name":"General Nutrition Center",
    "wof:placetype":"venue"
},
  "geometry": {"coordinates":[-121.50084,38.579861],"type":"Point"}
}