{
  "type": "Feature",
  "properties": {
    "addr:full":"7522 Belle View Ave Sebastopol CA 95472",
    "addr:housenumber":"7522",
    "addr:postcode":"95472",
    "addr:street":"Belle View Ave",
    "iso:country":"US",
    "sg:address":"7522 Belle View Ave",
    "sg:city":"Sebastopol",
    "sg:classifiers":[
        {
            "category":"Professional",
            "subcategory":"Engineering",
            "type":"Services"
        }
    ],
    "sg:phone":"+1 707 829 7345",
    "sg:postcode":"95472",
    "sg:province":"CA",
    "sg:tags":[
        "engineer"
    ],
    "wof:name":"Organic Waste Management",
    "wof:placetype":"venue"
},
  "geometry": {"coordinates":[-122.825948,38.390038],"type":"Point"}
}