{
  "type": "Feature",
  "properties": {
    "addr:full":"12211 Garvey Ave El Monte CA 91732",
    "addr:housenumber":"12211",
    "addr:postcode":"91732",
    "addr:street":"Garvey Ave",
    "iso:country":"US",
    "sg:address":"12211 Garvey Ave",
    "sg:city":"El Monte",
    "sg:classifiers":[
        {
            "category":"Home & Garden",
            "subcategory":"Building Materials",
            "type":"Retail Goods"
        }
    ],
    "sg:phone":"+1 626 288 3866",
    "sg:postcode":"91732",
    "sg:province":"CA",
    "sg:tags":[
        "windows"
    ],
    "wof:name":"J S Glass Corp",
    "wof:placetype":"venue"
},
  "geometry": {"coordinates":[-118.013723,34.063491],"type":"Point"}
}