{
  "type": "Feature",
  "properties": {
    "addr:full":"2350 Midway Dr Santa Rosa CA 95405",
    "addr:housenumber":"2350",
    "addr:postcode":"95405",
    "addr:street":"Midway Dr",
    "iso:country":"US",
    "sg:address":"2350 Midway Dr",
    "sg:city":"Santa Rosa",
    "sg:classifiers":[
        {
            "category":"Restaurant",
            "type":"Food & Drink"
        }
    ],
    "sg:phone":"+1 707 575 5557",
    "sg:postcode":"95405",
    "sg:province":"CA",
    "wof:name":"Shogun",
    "wof:placetype":"venue"
},
  "geometry": {"coordinates":[-122.69114999999999,38.444883],"type":"Point"}
}