{
  "type": "Feature",
  "properties": {
    "addr:full":"18726 S Western Ave Gardena CA 90248",
    "addr:housenumber":"18726",
    "addr:postcode":"90248",
    "addr:street":"S Western Ave",
    "iso:country":"US",
    "sg:address":"18726 S Western Ave",
    "sg:city":"Gardena",
    "sg:classifiers":[
        {
            "category":"Freight",
            "type":"Transportation"
        }
    ],
    "sg:phone":"+1 310 353 5050",
    "sg:postcode":"90248",
    "sg:province":"CA",
    "wof:name":"Delcon Line USA Inc",
    "wof:placetype":"venue"
},
  "geometry": {"coordinates":[-118.30914799999999,33.860997],"type":"Point"}
}