{
  "type": "Feature",
  "properties": {
    "iso:country":"US",
    "sg:address":"954 86th Ave",
    "sg:city":"Oakland",
    "sg:classifiers":[
        {
            "category":"Building & Trades",
            "subcategory":"Construction",
            "type":"Services"
        }
    ],
    "sg:phone":"+1 510 538 7588",
    "sg:postcode":"94621",
    "sg:province":"CA",
    "sg:tags":[
        "roofing",
        "contractor"
    ],
    "wof:name":"Aloha Roofing Co",
    "wof:placetype":"venue"
},
  "geometry": {"coordinates":[-122.183798,37.74907],"type":"Point"}
}