{
  "type": "Feature",
  "properties": {
    "addr:full":"26841 Aliso Creek Rd Aliso Viejo CA 92656",
    "addr:housenumber":"26841",
    "addr:postcode":"92656",
    "addr:street":"Aliso Creek Rd",
    "iso:country":"US",
    "sg:address":"26841 Aliso Creek Rd",
    "sg:city":"Aliso Viejo",
    "sg:classifiers":[
        {
            "category":"Shopping",
            "subcategory":"Used Merchandise",
            "type":"Retail Goods"
        }
    ],
    "sg:phone":"+1 949 643 7300",
    "sg:postcode":"92656",
    "sg:province":"CA",
    "wof:name":"A Chez Elle Designer",
    "wof:placetype":"venue"
},
  "geometry": {"coordinates":[-117.723522,33.571798],"type":"Point"}
}