{
  "type": "Feature",
  "properties": {
    "addr:full":"2281 Fairmount Ave San Diego CA 92105",
    "addr:housenumber":"2281",
    "addr:postcode":"92105",
    "addr:street":"Fairmount Ave",
    "iso:country":"US",
    "sg:address":"2281 Fairmount Ave",
    "sg:city":"San Diego",
    "sg:classifiers":[
        {
            "category":"Retail",
            "subcategory":"Auto Repair",
            "type":"Services"
        }
    ],
    "sg:phone":"+1 619 262 6045",
    "sg:postcode":"92105",
    "sg:province":"CA",
    "sg:tags":[
        "repairing",
        "automobile"
    ],
    "wof:name":"B & B Auto Repair",
    "wof:placetype":"venue"
},
  "geometry": {"coordinates":[-117.098006,32.726667],"type":"Point"}
}