{
  "type": "Feature",
  "properties": {
    "addr:full":"16899 Cll de Sarah Pacific Palisades CA 90272",
    "addr:housenumber":"16899",
    "addr:postcode":"90272",
    "addr:street":"Cll De Sarah",
    "iso:country":"US",
    "sg:address":"16899 Cll de Sarah",
    "sg:city":"Pacific Palisades",
    "sg:classifiers":[
        {
            "category":"Professional",
            "type":"Services"
        }
    ],
    "sg:phone":"+1 310 454 3675",
    "sg:postcode":"90272",
    "sg:province":"CA",
    "wof:name":"Yummy International LLC",
    "wof:placetype":"venue"
},
  "geometry": {"coordinates":[-118.552184,34.077149],"type":"Point"}
}