{
  "type": "Feature",
  "properties": {
    "addr:full":"2965 Almond St Dos Palos CA 93620",
    "addr:housenumber":"2965",
    "addr:postcode":"93620",
    "addr:street":"Almond St",
    "iso:country":"US",
    "sg:address":"2965 Almond St",
    "sg:city":"Dos Palos",
    "sg:classifiers":[
        {
            "category":"Wholesale",
            "subcategory":"Machinery & Supplies",
            "type":"Manufacturing & Wholesale Goods"
        },
        {
            "category":"Manufacturing",
            "subcategory":"Metals",
            "type":"Manufacturing & Wholesale Goods"
        }
    ],
    "sg:phone":"+1 209 392 8866",
    "sg:postcode":"93620",
    "sg:province":"CA",
    "sg:tags":[
        "barrels",
        "industrial",
        "drum",
        "fiber",
        "mfg"
    ],
    "wof:name":"Michael's Cooperage Co",
    "wof:placetype":"venue"
},
  "geometry": {"coordinates":[-120.643019,36.984781],"type":"Point"}
}