{
  "type": "Feature",
  "properties": {
    "iso:country":"US",
    "sg:address":"3637 Snell Ave # 50",
    "sg:city":"San Jose",
    "sg:classifiers":[
        {
            "category":"Building & Trades",
            "subcategory":"Construction",
            "type":"Services"
        }
    ],
    "sg:phone":"+1 408 602 1278",
    "sg:postcode":"95136",
    "sg:province":"CA",
    "sg:tags":[
        "contractor"
    ],
    "wof:name":"GenCon2",
    "wof:placetype":"venue"
},
  "geometry": {"coordinates":[-121.846377,37.277871],"type":"Point"}
}