{
  "type": "Feature",
  "properties": {
    "addr:full":"5920 Riley St San Diego CA 92110",
    "addr:housenumber":"5920",
    "addr:postcode":"92110",
    "addr:street":"Riley St",
    "iso:country":"US",
    "sg:address":"5920 Riley St",
    "sg:city":"San Diego",
    "sg:classifiers":[
        {
            "category":"Professional",
            "subcategory":"Business Services",
            "type":"Services"
        }
    ],
    "sg:phone":"+1 619 296 7854",
    "sg:postcode":"92110",
    "sg:province":"CA",
    "sg:tags":[
        "transcribing",
        "disc"
    ],
    "wof:name":"A Better Type",
    "wof:placetype":"venue"
},
  "geometry": {"coordinates":[-117.186149,32.768032],"type":"Point"}
}