{
  "type": "Feature",
  "properties": {
    "addr:full":"8484 Wilshire Blvd Beverly Hills CA 90211",
    "addr:housenumber":"8484",
    "addr:postcode":"90211",
    "addr:street":"Wilshire Blvd",
    "iso:country":"US",
    "sg:address":"8484 Wilshire Blvd",
    "sg:city":"Beverly Hills",
    "sg:classifiers":[
        {
            "category":"Professional",
            "type":"Services"
        }
    ],
    "sg:phone":"+1 310 652 6901",
    "sg:postcode":"90211",
    "sg:province":"CA",
    "wof:name":"California Irb Inc",
    "wof:placetype":"venue"
},
  "geometry": {"coordinates":[-118.37554,34.064925],"type":"Point"}
}