{
  "type": "Feature",
  "properties": {
    "addr:full":"9695 Live Oak Ave Ben Lomond CA 95005",
    "addr:housenumber":"9695",
    "addr:postcode":"95005",
    "addr:street":"Live Oak Ave",
    "iso:country":"US",
    "sg:address":"9695 Live Oak Ave",
    "sg:city":"Ben Lomond",
    "sg:classifiers":[
        {
            "category":"Professional",
            "type":"Services"
        }
    ],
    "sg:phone":"+1 831 336 2290",
    "sg:postcode":"95005",
    "sg:province":"CA",
    "sg:tags":[
        "establishment"
    ],
    "wof:name":"Heart N Hand",
    "wof:placetype":"venue"
},
  "geometry": {"coordinates":[-122.08541099999999,37.089619],"type":"Point"}
}