{
  "type": "Feature",
  "properties": {
    "addr:full":"4500 Cabello St Union City CA 94587",
    "addr:postcode":"4500;94587",
    "addr:street":"Cabello St",
    "iso:country":"US",
    "sg:address":"4500 Cabello St",
    "sg:city":"Union City",
    "sg:classifiers":[
        {
            "category":"Education",
            "subcategory":"School",
            "type":"Public Place"
        }
    ],
    "sg:phone":"+1 510 489 4141",
    "sg:postcode":"94587",
    "sg:province":"CA",
    "wof:name":"Cabello Elementary",
    "wof:placetype":"venue"
},
  "geometry": {"coordinates":[-122.07754,37.585125],"type":"Point"}
}