{
  "type": "Feature",
  "properties": {
    "iso:country":"US",
    "sg:address":"5447 Martin Luther King Jr Blvd",
    "sg:city":"Lynwood",
    "sg:classifiers":[
        {
            "category":"Manufacturing",
            "subcategory":"Tools & Machinery",
            "type":"Manufacturing & Wholesale Goods"
        }
    ],
    "sg:phone":"+1 310 635 8867",
    "sg:postcode":"90262",
    "sg:province":"CA",
    "sg:tags":[
        "engine"
    ],
    "wof:name":"Diesel Mobile Svc",
    "wof:placetype":"venue"
},
  "geometry": {"coordinates":[-118.180927,33.919419],"type":"Point"}
}