{
  "type": "Feature",
  "properties": {
    "iso:country":"US",
    "sg:address":"943 S Van Ness Avenue",
    "sg:city":"San Francisco",
    "sg:classifiers":[
        {
            "category":"Travel",
            "subcategory":"Hotels & Motels",
            "type":"Entertainment"
        },
        {
            "category":"Travel",
            "subcategory":"Bed & Breakfast",
            "type":"Entertainment"
        }
    ],
    "sg:phone":"+1 415 641 0188",
    "sg:postcode":"94110",
    "sg:province":"CA",
    "sg:website":"www.InnSF.com",
    "wof:name":"The Inn San Francisco",
    "wof:placetype":"venue"
},
  "geometry": {"coordinates":[-122.417,37.758099],"type":"Point"}
}