{
  "type": "Feature",
  "properties": {
    "addr:full":"1050 Shaw Ave Ste 1050 Clovis CA 93612",
    "addr:housenumber":"1050",
    "addr:postcode":"93612",
    "addr:street":"Shaw Ave Ste 1050",
    "iso:country":"US",
    "sg:address":"1050 Shaw Ave Ste 1050",
    "sg:city":"Clovis",
    "sg:classifiers":[
        {
            "category":"Restaurant",
            "type":"Food & Drink"
        }
    ],
    "sg:phone":"+1 559 323 7211",
    "sg:postcode":"93612",
    "sg:province":"CA",
    "sg:tags":[
        "asian",
        "chinese",
        "pan"
    ],
    "wof:name":"Oriental Express",
    "wof:placetype":"venue"
},
  "geometry": {"coordinates":[-119.695503,36.80846],"type":"Point"}
}