{
  "type": "Feature",
  "properties": {
    "iso:country":"US",
    "sg:address":"18725 Co Rd 95A",
    "sg:city":"Woodland",
    "sg:classifiers":[
        {
            "category":"Building & Trades",
            "subcategory":"Plumbing",
            "type":"Services"
        }
    ],
    "sg:phone":"+1 530 662 5534",
    "sg:postcode":"95695",
    "sg:province":"CA",
    "sg:tags":[
        "tank",
        "septic"
    ],
    "wof:name":"Yolo Pumping Svc",
    "wof:placetype":"venue"
},
  "geometry": {"coordinates":[-121.848858,38.666629],"type":"Point"}
}