{
  "type": "Feature",
  "properties": {
    "addr:full":"2526 S Figueroa St Los Angeles CA 90007",
    "addr:housenumber":"2526",
    "addr:postcode":"90007",
    "addr:street":"S Figueroa St",
    "iso:country":"US",
    "sg:address":"2526 S Figueroa St",
    "sg:city":"Los Angeles",
    "sg:classifiers":[
        {
            "category":"Restaurant",
            "type":"Food & Drink"
        }
    ],
    "sg:phone":"+1 213 747 6903",
    "sg:postcode":"90007",
    "sg:province":"CA",
    "wof:name":"Royal Express",
    "wof:placetype":"venue"
},
  "geometry": {"coordinates":[-118.275379,34.029172],"type":"Point"}
}