{
  "type": "Feature",
  "properties": {
    "iso:country":"US",
    "sg:address":"28901 S Western Ave Ste 221",
    "sg:city":"Rancho Palos Verdes",
    "sg:classifiers":[
        {
            "category":"Insurance",
            "subcategory":"Health Insurance",
            "type":"Services"
        }
    ],
    "sg:phone":"+1 310 547 2337",
    "sg:postcode":"90275",
    "sg:province":"CA",
    "sg:tags":[
        "market"
    ],
    "wof:name":"Gnc",
    "wof:placetype":"venue"
},
  "geometry": {"coordinates":[-118.30999799999999,33.755501],"type":"Point"}
}