{
  "type": "Feature",
  "properties": {
    "addr:full":"10628 S San Pedro St Los Angeles CA 90003",
    "addr:housenumber":"10628",
    "addr:postcode":"90003",
    "addr:street":"S San Pedro St",
    "iso:country":"US",
    "sg:address":"10628 S San Pedro St",
    "sg:city":"Los Angeles",
    "sg:classifiers":[
        {
            "category":"Wholesale",
            "subcategory":"Dairy",
            "type":"Manufacturing & Wholesale Goods"
        }
    ],
    "sg:phone":"+1 323 757 0231",
    "sg:postcode":"90003",
    "sg:province":"CA",
    "sg:tags":[
        "frozen",
        "dessert",
        "ice",
        "cream"
    ],
    "wof:name":"H P Ice Cream",
    "wof:placetype":"venue"
},
  "geometry": {"coordinates":[-118.26943900000001,33.939547],"type":"Point"}
}