{
  "type": "Feature",
  "properties": {
    "iso:country":"US",
    "sg:address":"10628 S San Pedro St",
    "sg:city":"Los Angeles",
    "sg:classifiers":[
        {
            "category":"Wholesale",
            "subcategory":"Dairy",
            "type":"Manufacturing & Wholesale Goods"
        }
    ],
    "sg:phone":"+1 323 757 0231",
    "sg:postcode":"90003",
    "sg:province":"CA",
    "sg:tags":[
        "frozen",
        "dessert",
        "ice",
        "cream"
    ],
    "wof:name":"H P Ice Cream",
    "wof:placetype":"venue"
},
  "geometry": {"coordinates":[-118.269439,33.939547],"type":"Point"}
}