{
  "type": "Feature",
  "properties": {
    "iso:country":"US",
    "sg:address":"654 G St",
    "sg:city":"Davis",
    "sg:classifiers":[
        {
            "category":"Shopping",
            "subcategory":"Used Merchandise",
            "type":"Retail Goods"
        }
    ],
    "sg:phone":"+1 530 750 2665",
    "sg:postcode":"95616",
    "sg:province":"CA",
    "sg:tags":[
        "book",
        "rare",
        "dealer"
    ],
    "wof:name":"Sweet Briar Books",
    "wof:placetype":"venue"
},
  "geometry": {"coordinates":[-121.740487,38.549498],"type":"Point"}
}