{
  "type": "Feature",
  "properties": {
    "iso:country":"US",
    "sg:address":"6913 Ave 408",
    "sg:city":"Dinuba",
    "sg:classifiers":[
        {
            "category":"Farming",
            "subcategory":"Orchard",
            "type":"Manufacturing & Wholesale Goods"
        }
    ],
    "sg:phone":"+1 559 591 2293",
    "sg:postcode":"93618",
    "sg:province":"CA",
    "sg:tags":[
        "fruit",
        "tree"
    ],
    "wof:name":"Frank Buller",
    "wof:placetype":"venue"
},
  "geometry": {"coordinates":[-119.417706,36.531565],"type":"Point"}
}