{
  "type": "Feature",
  "properties": {
    "addr:full":"2314 Stevens Creek Blvd San Jose CA 95128",
    "addr:housenumber":"2314",
    "addr:postcode":"95128",
    "addr:street":"Stevens Creek Blvd",
    "iso:country":"US",
    "sg:address":"2314 Stevens Creek Blvd",
    "sg:city":"San Jose",
    "sg:classifiers":[
        {
            "category":"Shopping",
            "subcategory":"Used Merchandise",
            "type":"Retail Goods"
        }
    ],
    "sg:phone":"+1 408 977 1758",
    "sg:postcode":"95128",
    "sg:province":"CA",
    "sg:tags":[
        "antique"
    ],
    "wof:name":"Antique Memories & Collectables",
    "wof:placetype":"venue"
},
  "geometry": {"coordinates":[-121.933998,37.323399],"type":"Point"}
}