{
  "type": "Feature",
  "properties": {
    "iso:country":"US",
    "sg:address":"1537 White Pine Dr",
    "sg:city":"Morro Bay",
    "sg:classifiers":[
        {
            "category":"Arts & Performance",
            "subcategory":"Theater",
            "type":"Entertainment"
        }
    ],
    "sg:phone":"+1 805 772 9086",
    "sg:postcode":"93442",
    "sg:province":"CA",
    "sg:tags":[
        "musician"
    ],
    "wof:name":"Morro Bay German Band",
    "wof:placetype":"venue"
},
  "geometry": {"coordinates":[-120.821653,35.363423],"type":"Point"}
}