{
  "type": "Feature",
  "properties": {
    "addr:full":"1548 California St San Francisco CA 94109",
    "addr:housenumber":"1548",
    "addr:postcode":"94109",
    "addr:street":"California St",
    "iso:country":"US",
    "sg:address":"1548 California St",
    "sg:city":"San Francisco",
    "sg:classifiers":[
        {
            "category":"Bars & Pubs",
            "type":"Food & Drink"
        }
    ],
    "sg:phone":"+1 415 292 5004",
    "sg:postcode":"94109",
    "sg:province":"CA",
    "sg:tags":[
        "lounge",
        "cocktail"
    ],
    "wof:name":"Hanauma Bay Cocktail Lounge",
    "wof:placetype":"venue"
},
  "geometry": {"coordinates":[-122.42006000000001,37.790755],"type":"Point"}
}