{
  "type": "Feature",
  "properties": {
    "addr:full":"5375 FARWELL PL FREMONT CA 94536",
    "addr:housenumber":"5375",
    "addr:postcode":"94536",
    "addr:street":"Farwell Pl",
    "iso:country":"US",
    "sg:address":"5375 FARWELL PL",
    "sg:city":"FREMONT",
    "sg:phone":"+1 510 794 9693",
    "sg:postcode":"94536",
    "sg:province":"CA",
    "sg:website":"http://redirect.searchignite.com/si/cm/tracking/DGTrackingRedirect.aspx?siclientid=2918&siredirect=http%3A%2F%2Fwww%2Eextendedstaydeluxe%2Ecom%2FSJF&sisearchengine=155&siproduct=ESD+Fremont+%2D+Newark&clearppc=1",
    "wof:name":"Extended Stay Deluxe Fremont - Newark",
    "wof:placetype":"venue"
},
  "geometry": {"coordinates":[-122.002037,37.533314],"type":"Point"}
}