{
  "type": "Feature",
  "properties": {
    "iso:country":"US",
    "sg:address":"1781 Central Ave",
    "sg:city":"Mckinleyville",
    "sg:classifiers":[
        {
            "category":"Personal",
            "subcategory":"Beauty Salon",
            "type":"Services"
        }
    ],
    "sg:phone":"+1 707 839 1103",
    "sg:postcode":"95519",
    "sg:province":"CA",
    "wof:name":"All About Me",
    "wof:placetype":"venue"
},
  "geometry": {"coordinates":[-124.10077699999999,40.938114],"type":"Point"}
}