{
  "type": "Feature",
  "properties": {
    "addr:full":"6850 Canby Ave Reseda CA 91335",
    "addr:housenumber":"6850",
    "addr:postcode":"91335",
    "addr:street":"Canby Ave",
    "iso:country":"US",
    "sg:address":"6850 Canby Ave",
    "sg:city":"Reseda",
    "sg:classifiers":[
        {
            "category":"Professional",
            "subcategory":"Computer Services",
            "type":"Services"
        }
    ],
    "sg:phone":"+1 818 345 6811",
    "sg:postcode":"91335",
    "sg:province":"CA",
    "sg:tags":[
        "graphics"
    ],
    "wof:name":"Enventive",
    "wof:placetype":"venue"
},
  "geometry": {"coordinates":[-118.53467000000001,34.194501],"type":"Point"}
}