{
  "type": "Feature",
  "properties": {
    "addr:full":"847 N Raymond Ave Unit 1 Pasadena CA 91103",
    "addr:housenumber":"847;1",
    "addr:postcode":"91103",
    "addr:street":"N Raymond Ave Unit",
    "iso:country":"US",
    "sg:address":"847 N Raymond Ave Unit 1",
    "sg:city":"Pasadena",
    "sg:classifiers":[
        {
            "category":"Wholesale",
            "subcategory":"Non-durable Goods",
            "type":"Manufacturing & Wholesale Goods"
        }
    ],
    "sg:phone":"+1 626 683 9445",
    "sg:postcode":"91103",
    "sg:province":"CA",
    "sg:tags":[
        "merchandise-wholesale"
    ],
    "wof:name":"Ralo Imports Inc",
    "wof:placetype":"venue"
},
  "geometry": {"coordinates":[-118.149055,34.160471],"type":"Point"}
}