{
  "type": "Feature",
  "properties": {
    "iso:country":"US",
    "sg:address":"3056 Castro Valley Blvd",
    "sg:city":"Castro Valley",
    "sg:classifiers":[
        {
            "category":"Building & Trades",
            "subcategory":"Plumbing",
            "type":"Services"
        }
    ],
    "sg:phone":"+1 510 690 0251",
    "sg:postcode":"94546",
    "sg:province":"CA",
    "sg:tags":[
        "contractor"
    ],
    "wof:name":"Greer Family Plumbing",
    "wof:placetype":"venue"
},
  "geometry": {"coordinates":[-122.081787,37.695616],"type":"Point"}
}