{
  "type": "Feature",
  "properties": {
    "iso:country":"US",
    "sg:address":"1545 Albret St",
    "sg:city":"Lancaster",
    "sg:classifiers":[
        {
            "category":"Wholesale",
            "subcategory":"Groceries",
            "type":"Manufacturing & Wholesale Goods"
        }
    ],
    "sg:phone":"+1 661 948 3485",
    "sg:postcode":"93534",
    "sg:province":"CA",
    "wof:name":"Brew Buddys",
    "wof:placetype":"venue"
},
  "geometry": {"coordinates":[-118.158539,34.697316],"type":"Point"}
}