{
  "type": "Feature",
  "properties": {
    "iso:country":"US",
    "sg:address":"17333 Valley Blvd",
    "sg:city":"Fontana",
    "sg:classifiers":[
        {
            "category":"Building & Trades",
            "subcategory":"Construction",
            "type":"Services"
        }
    ],
    "sg:phone":"+1 909 822 4141",
    "sg:postcode":"92335",
    "sg:province":"CA",
    "sg:tags":[
        "concrete",
        "contractor"
    ],
    "wof:name":"Specialty Concrete Service",
    "wof:placetype":"venue"
},
  "geometry": {"coordinates":[-117.427984,34.070296],"type":"Point"}
}