{
  "type": "Feature",
  "properties": {
    "addr:full":"225 W Santa Clara Ste 1500 San Jose CA 95113",
    "addr:housenumber":"225",
    "addr:postcode":"95113",
    "addr:street":"W Santa;Ste 1500",
    "iso:country":"US",
    "sg:address":"225 W Santa Clara Ste 1500",
    "sg:city":"San Jose",
    "sg:classifiers":[
        {
            "category":"Professional",
            "subcategory":"Lawyer & Legal Services",
            "type":"Services"
        }
    ],
    "sg:phone":"+1 408 286 5100",
    "sg:postcode":"95113",
    "sg:province":"CA",
    "sg:website":"www.pahl-mccay.com",
    "wof:name":"Pahl & McCay",
    "wof:placetype":"venue"
},
  "geometry": {"coordinates":[-121.89454600000001,37.334641],"type":"Point"}
}