{
  "type": "Feature",
  "properties": {
    "iso:country":"US",
    "sg:address":"17441 Jerry Pl",
    "sg:city":"Hayward",
    "sg:classifiers":[
        {
            "category":"Real Estate",
            "subcategory":"Real Estate Agent",
            "type":"Services"
        }
    ],
    "sg:phone":"+1 510 278 9486",
    "sg:postcode":"94541",
    "sg:province":"CA",
    "wof:name":"L & K Investments",
    "wof:placetype":"venue"
},
  "geometry": {"coordinates":[-122.114403,37.683477],"type":"Point"}
}