{
  "type": "Feature",
  "properties": {
    "iso:country":"US",
    "sg:address":"1277 E 7th St",
    "sg:city":"Upland",
    "sg:classifiers":[
        {
            "category":"Professional",
            "subcategory":"Art Services",
            "type":"Services"
        }
    ],
    "sg:phone":"+1 909 982 1928",
    "sg:postcode":"91786",
    "sg:province":"CA",
    "sg:tags":[
        "graphic",
        "designer"
    ],
    "wof:name":"A Plus Shirt Graphics & Design",
    "wof:placetype":"venue"
},
  "geometry": {"coordinates":[-117.629152,34.08897],"type":"Point"}
}