{
  "type": "Feature",
  "properties": {
    "iso:country":"US",
    "sg:address":"121 E Whittier Blvd",
    "sg:city":"Montebello",
    "sg:classifiers":[
        {
            "category":"Autos & Motor Vehicles",
            "subcategory":"Automobile Sales",
            "type":"Retail Goods"
        }
    ],
    "sg:phone":"+1 323 887 7337",
    "sg:postcode":"90640",
    "sg:province":"CA",
    "sg:tags":[
        "car",
        "dealer"
    ],
    "wof:name":"MGS Motors Inc",
    "wof:placetype":"venue"
},
  "geometry": {"coordinates":[-118.100287,34.008307],"type":"Point"}
}