{
  "type": "Feature",
  "properties": {
    "addr:full":"2366 Front St San Diego CA 92101",
    "addr:housenumber":"2366",
    "addr:postcode":"92101",
    "addr:street":"Front St",
    "iso:country":"US",
    "sg:address":"2366 Front St",
    "sg:city":"San Diego",
    "sg:classifiers":[
        {
            "category":"Professional",
            "subcategory":"Lawyer & Legal Services",
            "type":"Services"
        }
    ],
    "sg:phone":"+1 619 696 7330",
    "sg:postcode":"92101",
    "sg:province":"CA",
    "sg:tags":[
        "attorney"
    ],
    "wof:name":"Michael H Crosby",
    "wof:placetype":"venue"
},
  "geometry": {"coordinates":[-117.16490400000001,32.729617],"type":"Point"}
}