{
  "type": "Feature",
  "properties": {
    "addr:full":"1545 Nutmeg Pl Costa Mesa CA 92626",
    "addr:housenumber":"1545",
    "addr:postcode":"92626",
    "addr:street":"Nutmeg Pl",
    "iso:country":"US",
    "sg:address":"1545 Nutmeg Pl",
    "sg:city":"Costa Mesa",
    "sg:classifiers":[
        {
            "category":"Health Services",
            "subcategory":"Optometrist",
            "type":"Services"
        }
    ],
    "sg:phone":"+1 714 435 1150",
    "sg:postcode":"92626",
    "sg:province":"CA",
    "wof:name":"Dr Dawn Vu Od",
    "wof:placetype":"venue"
},
  "geometry": {"coordinates":[-117.92030800000001,33.681815],"type":"Point"}
}