{
  "type": "Feature",
  "properties": {
    "addr:full":"10250 Cmt Cuervo San Diego CA 92108",
    "addr:postcode":"10250;cuervo;92108",
    "iso:country":"US",
    "sg:address":"10250 Cmt Cuervo",
    "sg:city":"San Diego",
    "sg:classifiers":[
        {
            "category":"Wholesale",
            "subcategory":"Durable Goods & Equipment",
            "type":"Manufacturing & Wholesale Goods"
        }
    ],
    "sg:phone":"+1 619 584 1846",
    "sg:postcode":"92108",
    "sg:province":"CA",
    "wof:name":"Gms Publishing",
    "wof:placetype":"venue"
},
  "geometry": {"coordinates":[-117.110603,32.785977],"type":"Point"}
}