{
  "type": "Feature",
  "properties": {
    "addr:full":"14315 Valley Blvd Fontana CA 92335",
    "addr:housenumber":"14315",
    "addr:postcode":"92335",
    "addr:street":"Valley Blvd",
    "iso:country":"US",
    "sg:address":"14315 Valley Blvd",
    "sg:city":"Fontana",
    "sg:classifiers":[
        {
            "category":"Autos & Motor Vehicles",
            "subcategory":"Automobile Sales",
            "type":"Retail Goods"
        }
    ],
    "sg:phone":"+1 909 355 5555",
    "sg:postcode":"92335",
    "sg:province":"CA",
    "sg:tags":[
        "truck"
    ],
    "sg:website":"www.diversifiedtruckcenter.com",
    "wof:name":"Diversified Sales Svc Corp",
    "wof:placetype":"venue"
},
  "geometry": {"coordinates":[-117.489087,34.070115],"type":"Point"}
}