{
  "type": "Feature",
  "properties": {
    "iso:country":"US",
    "sg:address":"2437 Ocean Avenue",
    "sg:city":"San Francisco",
    "sg:classifiers":[
        {
            "category":"Health Services",
            "subcategory":"Health Practitioner",
            "type":"Services"
        }
    ],
    "sg:phone":"+1 415 497 4495",
    "sg:postcode":"94127",
    "sg:province":"CA",
    "sg:tags":[
        "acupuncture"
    ],
    "wof:name":"Jung Sik Kim, L.Ac.",
    "wof:placetype":"venue"
},
  "geometry": {"coordinates":[-122.470901,37.730602],"type":"Point"}
}