{
  "type": "Feature",
  "properties": {
    "iso:country":"US",
    "sg:address":"1613 Escalero Rd",
    "sg:city":"Santa Rosa",
    "sg:classifiers":[
        {
            "category":"Professional",
            "subcategory":"Engineering",
            "type":"Services"
        }
    ],
    "sg:phone":"+1 707 529 7704",
    "sg:postcode":"95409",
    "sg:province":"CA",
    "sg:tags":[
        "lighting",
        "engineer"
    ],
    "wof:name":"Oaktree Real Estate Staging",
    "wof:placetype":"venue"
},
  "geometry": {"coordinates":[-122.642551,38.471967],"type":"Point"}
}