{
  "type": "Feature",
  "properties": {
    "iso:country":"US",
    "sg:address":"2180 Garnet Ave",
    "sg:city":"San Diego",
    "sg:classifiers":[
        {
            "category":"Professional",
            "type":"Services"
        }
    ],
    "sg:phone":"+1 619 682 0042",
    "sg:postcode":"92109",
    "sg:province":"CA",
    "sg:tags":[
        "establishment"
    ],
    "wof:name":"Dottie Post-Cranio Sacral",
    "wof:placetype":"venue"
},
  "geometry": {"coordinates":[-117.231368,32.801954],"type":"Point"}
}