{
  "type": "Feature",
  "properties": {
    "addr:full":"542 Ocean St Exn Santa Cruz CA 95060",
    "addr:housenumber":"542",
    "addr:postcode":"95060",
    "addr:street":"Ocean St Exn",
    "iso:country":"US",
    "sg:address":"542 Ocean St Exn",
    "sg:city":"Santa Cruz",
    "sg:classifiers":[
        {
            "category":"Professional",
            "subcategory":"Business Services",
            "type":"Services"
        }
    ],
    "sg:phone":"+1 831 458 3633",
    "sg:postcode":"95060",
    "sg:province":"CA",
    "wof:name":"Abril Bail Bonds Inc",
    "wof:placetype":"venue"
},
  "geometry": {"coordinates":[-122.04319599999999,37.010089],"type":"Point"}
}