{
  "type": "Feature",
  "properties": {
    "iso:country":"US",
    "sg:address":"244 Millar Ave",
    "sg:city":"El Cajon",
    "sg:classifiers":[
        {
            "category":"Manufacturing",
            "subcategory":"Metals",
            "type":"Manufacturing & Wholesale Goods"
        }
    ],
    "sg:phone":"+1 619 447 5061",
    "sg:postcode":"92020",
    "sg:province":"CA",
    "sg:tags":[
        "closer",
        "door",
        "check"
    ],
    "sg:website":"www.cal-dor.com",
    "wof:name":"Cal Dor Specialties Inc",
    "wof:placetype":"venue"
},
  "geometry": {"coordinates":[-116.974451,32.793079],"type":"Point"}
}