{
  "type": "Feature",
  "properties": {
    "addr:full":"13750 Rosecrans Ave Santa Fe Springs CA 90670",
    "addr:housenumber":"13750",
    "addr:postcode":"90670",
    "addr:street":"Rosecrans Ave",
    "iso:country":"US",
    "sg:address":"13750 Rosecrans Ave",
    "sg:city":"Santa Fe Springs",
    "sg:classifiers":[
        {
            "category":"Manufacturing",
            "subcategory":"Metals",
            "type":"Manufacturing & Wholesale Goods"
        }
    ],
    "sg:phone":"+1 562 483 7378",
    "sg:postcode":"90670",
    "sg:province":"CA",
    "sg:tags":[
        "stamping"
    ],
    "wof:name":"Gordon Industries",
    "wof:placetype":"venue"
},
  "geometry": {"coordinates":[-118.038842,33.902467],"type":"Point"}
}