{
  "type": "Feature",
  "properties": {
    "iso:country":"US",
    "sg:address":"1876 Denkinger Rd",
    "sg:city":"Concord",
    "sg:classifiers":[
        {
            "category":"Real Estate",
            "subcategory":"Developer",
            "type":"Services"
        }
    ],
    "sg:phone":"+1 925 691 7077",
    "sg:postcode":"94521",
    "sg:province":"CA",
    "wof:name":"New Britton Land",
    "wof:placetype":"venue"
},
  "geometry": {"coordinates":[-121.9817,37.976416],"type":"Point"}
}