{
  "type": "Feature",
  "properties": {
    "addr:full":"23000 Avalon Blvd Carson CA 90745",
    "addr:housenumber":"23000",
    "addr:postcode":"90745",
    "addr:street":"Avalon Blvd",
    "iso:country":"US",
    "sg:address":"23000 Avalon Blvd",
    "sg:city":"Carson",
    "sg:classifiers":[
        {
            "category":"Manufacturing",
            "subcategory":"Glass & Minerals",
            "type":"Manufacturing & Wholesale Goods"
        }
    ],
    "sg:phone":"+1 310 549 6000",
    "sg:postcode":"90745",
    "sg:province":"CA",
    "sg:tags":[
        "crystal",
        "glassware",
        "china"
    ],
    "sg:website":"http://www.tabletopsunltd.com",
    "wof:name":"Tabletops Unlimited",
    "wof:placetype":"venue"
},
  "geometry": {"coordinates":[-118.26373100000001,33.816508],"type":"Point"}
}