{
  "type": "Feature",
  "properties": {
    "iso:country":"US",
    "sg:address":"321 N Redondo Ave",
    "sg:city":"Long Beach",
    "sg:classifiers":[
        {
            "category":"Professional",
            "subcategory":"Accounting & Tax Preparation",
            "type":"Services"
        }
    ],
    "sg:phone":"+1 562 434 4199",
    "sg:postcode":"90814",
    "sg:province":"CA",
    "sg:tags":[
        "return",
        "filing"
    ],
    "wof:name":"Lake & Assoc",
    "wof:placetype":"venue"
},
  "geometry": {"coordinates":[-118.152483,33.769134],"type":"Point"}
}