{
  "type": "Feature",
  "properties": {
    "iso:country":"US",
    "sg:address":"1111 W 6th St",
    "sg:city":"Los Angeles",
    "sg:classifiers":[
        {
            "category":"Organizations",
            "subcategory":"Religious Organization",
            "type":"Services"
        }
    ],
    "sg:phone":"+1 213 481 2780",
    "sg:postcode":"90017",
    "sg:province":"CA",
    "sg:tags":[
        "church"
    ],
    "wof:name":"Native American Adventist",
    "wof:placetype":"venue"
},
  "geometry": {"coordinates":[-118.263598,34.054744],"type":"Point"}
}