{
  "type": "Feature",
  "properties": {
    "addr:full":"805 Bay Blvd Chula Vista CA 91911",
    "addr:housenumber":"805",
    "addr:postcode":"91911",
    "addr:street":"Bay Blvd",
    "iso:country":"US",
    "sg:address":"805 Bay Blvd",
    "sg:city":"Chula Vista",
    "sg:classifiers":[
        {
            "category":"Wholesale",
            "subcategory":"Auto Parts",
            "type":"Manufacturing & Wholesale Goods"
        }
    ],
    "sg:phone":"+1 619 661 0055",
    "sg:postcode":"91911",
    "sg:province":"CA",
    "sg:tags":[
        "automobile"
    ],
    "wof:name":"All Toyo Lex Auto Recycling",
    "wof:placetype":"venue"
},
  "geometry": {"coordinates":[-117.091917,32.615124],"type":"Point"}
}