{
  "type": "Feature",
  "properties": {
    "addr:full":"1153 Lincoln Ave San Jose CA 95125",
    "addr:housenumber":"1153",
    "addr:postcode":"95125",
    "addr:street":"Lincoln Ave",
    "iso:country":"US",
    "sg:address":"1153 Lincoln Ave",
    "sg:city":"San Jose",
    "sg:classifiers":[
        {
            "category":"Museum",
            "type":"Entertainment"
        }
    ],
    "sg:phone":"+1 408 283 7000",
    "sg:postcode":"95125",
    "sg:province":"CA",
    "sg:tags":[
        "organization",
        "arts",
        "information"
    ],
    "sg:website":"www.culturalinitiatives.com",
    "wof:name":"Cultural Initiatives Silcn Vly",
    "wof:placetype":"venue"
},
  "geometry": {"coordinates":[-121.900524,37.307635],"type":"Point"}
}