{
  "type": "Feature",
  "properties": {
    "addr:full":"309 S Montgomery St Apt C Ojai CA 93023",
    "addr:housenumber":"309",
    "addr:postcode":"93023",
    "addr:street":"S Montgomery St Apt C",
    "iso:country":"US",
    "sg:address":"309 S Montgomery St Apt C",
    "sg:city":"Ojai",
    "sg:classifiers":[
        {
            "category":"Manufacturing",
            "subcategory":"Food",
            "type":"Manufacturing & Wholesale Goods"
        }
    ],
    "sg:phone":"+1 805 640 9441",
    "sg:postcode":"93023",
    "sg:province":"CA",
    "sg:tags":[
        "product"
    ],
    "wof:name":"Cartgirls",
    "wof:placetype":"venue"
},
  "geometry": {"coordinates":[-119.243481,34.445381],"type":"Point"}
}