{
  "type": "Feature",
  "properties": {
    "addr:full":"4766 Park Granada Calabasas CA 91302",
    "addr:housenumber":"4766",
    "addr:postcode":"91302",
    "addr:street":"Park Granada",
    "iso:country":"US",
    "sg:address":"4766 Park Granada",
    "sg:city":"Calabasas",
    "sg:classifiers":[
        {
            "category":"Professional",
            "subcategory":"Lawyer & Legal Services",
            "type":"Services"
        }
    ],
    "sg:phone":"+1 818 591 1755",
    "sg:postcode":"91302",
    "sg:province":"CA",
    "sg:tags":[
        "attorney"
    ],
    "wof:name":"Kevin C Boyle Law Offices",
    "wof:placetype":"venue"
},
  "geometry": {"coordinates":[-118.642449,34.154695],"type":"Point"}
}