{
  "type": "Feature",
  "properties": {
    "addr:full":"1165 L St San Miguel CA 93451",
    "addr:housenumber":"1165",
    "addr:postcode":"93451",
    "addr:street":"L St",
    "iso:country":"US",
    "sg:address":"1165 L St",
    "sg:city":"San Miguel",
    "sg:classifiers":[
        {
            "category":"Building & Trades",
            "subcategory":"Cleaning & Sanitation",
            "type":"Services"
        }
    ],
    "sg:phone":"+1 805 467 3255",
    "sg:postcode":"93451",
    "sg:province":"CA",
    "sg:tags":[
        "janitor"
    ],
    "wof:name":"Veronica's Cleaning Svc",
    "wof:placetype":"venue"
},
  "geometry": {"coordinates":[-120.698083,35.749485],"type":"Point"}
}