{
  "type": "Feature",
  "properties": {
    "addr:full":"360 N McKinley St Corona CA 92879",
    "addr:housenumber":"360",
    "addr:postcode":"92879",
    "addr:street":"N Mckinley St",
    "iso:country":"US",
    "sg:address":"360 N McKinley St",
    "sg:city":"Corona",
    "sg:classifiers":[
        {
            "category":"Banks & Credit Unions",
            "subcategory":"Bank",
            "type":"Services"
        }
    ],
    "sg:phone":"+1 951 279 2397",
    "sg:postcode":"92879",
    "sg:province":"CA",
    "wof:name":"Washington Mutual",
    "wof:placetype":"venue"
},
  "geometry": {"coordinates":[-117.518592,33.88723],"type":"Point"}
}