{
  "type": "Feature",
  "properties": {
    "iso:country":"US",
    "sg:address":"320 E 2nd Ave",
    "sg:city":"Escondido",
    "sg:classifiers":[
        {
            "category":"Wholesale",
            "subcategory":"Non-durable Goods",
            "type":"Manufacturing & Wholesale Goods"
        }
    ],
    "sg:phone":"+1 760 743 2384",
    "sg:postcode":"92025",
    "sg:province":"CA",
    "wof:name":"Scholastic Sports",
    "wof:placetype":"venue"
},
  "geometry": {"coordinates":[-117.07709199999999,33.122683],"type":"Point"}
}