{
  "type": "Feature",
  "properties": {
    "addr:full":"10769 Woodside Ave Ste 107 Santee CA 92071",
    "addr:housenumber":"10769",
    "addr:postcode":"92071",
    "addr:street":"Woodside Ave Ste 107",
    "iso:country":"US",
    "sg:address":"10769 Woodside Ave Ste 107",
    "sg:city":"Santee",
    "sg:classifiers":[
        {
            "category":"Personal",
            "subcategory":"Day Spa",
            "type":"Services"
        },
        {
            "category":"Personal",
            "subcategory":"Nail Salon",
            "type":"Services"
        }
    ],
    "sg:phone":"+1 619 579 8738",
    "sg:postcode":"92071",
    "sg:province":"CA",
    "wof:name":"Steph's Nails & Spa",
    "wof:placetype":"venue"
},
  "geometry": {"coordinates":[-116.96453700000001,32.839585],"type":"Point"}
}