{
  "type": "Feature",
  "properties": {
    "addr:full":"64 Lyford Dr Belvedere Tibrn CA 94920",
    "addr:housenumber":"64",
    "addr:postcode":"94920",
    "addr:street":"Lyford Dr",
    "iso:country":"US",
    "sg:address":"64 Lyford Dr",
    "sg:city":"Belvedere Tibrn",
    "sg:classifiers":[
        {
            "category":"Real Estate",
            "subcategory":"Real Estate Agent",
            "type":"Services"
        }
    ],
    "sg:phone":"+1 415 435 8596",
    "sg:postcode":"94920",
    "sg:province":"CA",
    "wof:name":"W & R Pratt Properties",
    "wof:placetype":"venue"
},
  "geometry": {"coordinates":[-122.459883,37.881885],"type":"Point"}
}