{
  "type": "Feature",
  "properties": {
    "addr:full":"10106 Cobblestone Ave Bakersfield CA 93311",
    "addr:housenumber":"10106",
    "addr:postcode":"93311",
    "addr:street":"Cobblestone Ave",
    "iso:country":"US",
    "sg:address":"10106 Cobblestone Ave",
    "sg:city":"Bakersfield",
    "sg:classifiers":[
        {
            "category":"Health Services",
            "subcategory":"Nursing And Care Facility",
            "type":"Services"
        },
        {
            "category":"Health Services",
            "subcategory":"Health Practitioner",
            "type":"Services"
        }
    ],
    "sg:phone":"+1 661 858 0862",
    "sg:postcode":"93311",
    "sg:province":"CA",
    "sg:tags":[
        "home",
        "eldercare-home"
    ],
    "wof:name":"Blue Pearl Home Care",
    "wof:placetype":"venue"
},
  "geometry": {"coordinates":[-119.114853,35.30817],"type":"Point"}
}