{
  "type": "Feature",
  "properties": {
    "addr:full":"81 Ardmore Irvine CA 92602",
    "addr:housenumber":"81",
    "addr:postcode":"92602",
    "addr:street":"Ardmore",
    "iso:country":"US",
    "sg:address":"81 Ardmore",
    "sg:city":"Irvine",
    "sg:classifiers":[
        {
            "category":"Professional",
            "type":"Services"
        }
    ],
    "sg:phone":"+1 714 692 7488",
    "sg:postcode":"92602",
    "sg:province":"CA",
    "wof:name":"Emerald Empire",
    "wof:placetype":"venue"
},
  "geometry": {"coordinates":[-117.769181,33.744913],"type":"Point"}
}