{
  "type": "Feature",
  "properties": {
    "addr:full":"8844 Millergrove Dr Santa Fe Springs CA 90670",
    "addr:housenumber":"8844",
    "addr:postcode":"90670",
    "addr:street":"Millergrove Dr",
    "iso:country":"US",
    "sg:address":"8844 Millergrove Dr",
    "sg:city":"Santa Fe Springs",
    "sg:classifiers":[
        {
            "category":"Manufacturing",
            "subcategory":"Paper Products",
            "type":"Manufacturing & Wholesale Goods"
        }
    ],
    "sg:phone":"+1 323 685 8844",
    "sg:postcode":"90670",
    "sg:province":"CA",
    "sg:tags":[
        "corrugated",
        "solid",
        "fiber",
        "box"
    ],
    "wof:name":"Gabriel Container Co",
    "wof:placetype":"venue"
},
  "geometry": {"coordinates":[-118.080601,33.962065],"type":"Point"}
}