{
  "type": "Feature",
  "properties": {
    "iso:country":"US",
    "sg:address":"1591 W Whittier Blvd",
    "sg:city":"La Habra",
    "sg:classifiers":[
        {
            "category":"Personal",
            "subcategory":"Barber",
            "type":"Services"
        }
    ],
    "sg:phone":"+1 562 694 5100",
    "sg:postcode":"90631",
    "sg:province":"CA",
    "wof:name":"La Habra Square Barbers",
    "wof:placetype":"venue"
},
  "geometry": {"coordinates":[-117.962997,33.9394],"type":"Point"}
}