{
  "type": "Feature",
  "properties": {
    "addr:full":"500 Henry St Vallejo CA 94591",
    "addr:housenumber":"500",
    "addr:postcode":"94591",
    "addr:street":"Henry St",
    "iso:country":"US",
    "sg:address":"500 Henry St",
    "sg:city":"Vallejo",
    "sg:classifiers":[
        {
            "category":"Personal",
            "subcategory":"Tattoo Parlor",
            "type":"Services"
        },
        {
            "category":"Personal",
            "subcategory":"Piercing",
            "type":"Services"
        }
    ],
    "sg:phone":"+1 707 552 3869",
    "sg:postcode":"94591",
    "sg:province":"CA",
    "sg:tags":[
        "body"
    ],
    "wof:name":"Henry Tattoo Shop",
    "wof:placetype":"venue"
},
  "geometry": {"coordinates":[-122.224678,38.112251],"type":"Point"}
}