{
  "type": "Feature",
  "properties": {
    "iso:country":"US",
    "sg:address":"5528 Everglades St",
    "sg:city":"Ventura",
    "sg:classifiers":[
        {
            "category":"Building & Trades",
            "subcategory":"Construction",
            "type":"Services"
        }
    ],
    "sg:phone":"+1 805 642 2698",
    "sg:postcode":"93003",
    "sg:province":"CA",
    "sg:tags":[
        "general",
        "contractor"
    ],
    "wof:name":"Cain Construction",
    "wof:placetype":"venue"
},
  "geometry": {"coordinates":[-119.21598,34.258797],"type":"Point"}
}