{
  "type": "Feature",
  "properties": {
    "addr:full":"2447 Lincoln Blvd Venice CA 90291",
    "addr:housenumber":"2447",
    "addr:postcode":"90291",
    "addr:street":"Lincoln Blvd",
    "iso:country":"US",
    "sg:address":"2447 Lincoln Blvd",
    "sg:city":"Venice",
    "sg:classifiers":[
        {
            "category":"Travel",
            "subcategory":"Hotels & Motels",
            "type":"Entertainment"
        }
    ],
    "sg:phone":"+1 310 822 0686",
    "sg:postcode":"90291",
    "sg:province":"CA",
    "wof:name":"Lincoln Inn",
    "wof:placetype":"venue"
},
  "geometry": {"coordinates":[-118.45236800000001,33.993873],"type":"Point"}
}