{
  "type": "Feature",
  "properties": {
    "addr:full":"24004 Via Faricante Ste 222 Mission Viejo CA 92691",
    "addr:housenumber":"24004",
    "addr:postcode":"92691",
    "addr:street":"Via Faricante Ste 222",
    "iso:country":"US",
    "sg:address":"24004 Via Faricante Ste 222",
    "sg:city":"Mission Viejo",
    "sg:classifiers":[
        {
            "category":"Banks & Credit Unions",
            "subcategory":"Financial Services",
            "type":"Services"
        }
    ],
    "sg:phone":"+1 949 600 8188",
    "sg:postcode":"92691",
    "sg:province":"CA",
    "sg:website":"ocaccounting.powersites.net/",
    "wof:name":"OC Accounting & Legal Services",
    "wof:placetype":"venue"
},
  "geometry": {"coordinates":[-117.680592,33.615503],"type":"Point"}
}