{
  "type": "Feature",
  "properties": {
    "addr:full":"730 San Pablo Ave Pinole CA 94564",
    "addr:housenumber":"730",
    "addr:postcode":"94564",
    "addr:street":"San Pablo Ave",
    "iso:country":"US",
    "sg:address":"730 San Pablo Ave",
    "sg:city":"Pinole",
    "sg:classifiers":[
        {
            "category":"Retail",
            "subcategory":"Auto Repair",
            "type":"Services"
        }
    ],
    "sg:phone":"+1 510 741 8891",
    "sg:postcode":"94564",
    "sg:province":"CA",
    "sg:tags":[
        "scooter",
        "motorcycle",
        "motor"
    ],
    "wof:name":"Bayou Custom",
    "wof:placetype":"venue"
},
  "geometry": {"coordinates":[-122.309364,38.005193],"type":"Point"}
}