{
  "type": "Feature",
  "properties": {
    "iso:country":"US",
    "sg:address":"131 N Ave 51",
    "sg:city":"Los Angeles",
    "sg:classifiers":[
        {
            "category":"Personal",
            "subcategory":"Beauty Salon",
            "type":"Services"
        }
    ],
    "sg:phone":"+1 323 258 2812",
    "sg:postcode":"90042",
    "sg:province":"CA",
    "wof:name":"Soki Beauty Salon",
    "wof:placetype":"venue"
},
  "geometry": {"coordinates":[-118.20133,34.106393],"type":"Point"}
}