{
  "type": "Feature",
  "properties": {
    "addr:full":"27995 Greenfield Dr Laguna Niguel CA 92677",
    "addr:housenumber":"27995",
    "addr:postcode":"92677",
    "addr:street":"Greenfield Dr",
    "iso:country":"US",
    "sg:address":"27995 Greenfield Dr",
    "sg:city":"Laguna Niguel",
    "sg:classifiers":[
        {
            "category":"Home & Garden",
            "subcategory":"Furniture",
            "type":"Retail Goods"
        }
    ],
    "sg:phone":"+1 949 448 5770",
    "sg:postcode":"92677",
    "sg:province":"CA",
    "sg:tags":[
        "house",
        "furnishing"
    ],
    "wof:name":"Bassman Blaine Assoc",
    "wof:placetype":"venue"
},
  "geometry": {"coordinates":[-117.685417,33.55822],"type":"Point"}
}