{
  "type": "Feature",
  "properties": {
    "addr:full":"425 E Colorado St Ste 420 Glendale CA 91205",
    "addr:housenumber":"425",
    "addr:postcode":"91205",
    "addr:street":"E Colorado St Ste 420",
    "iso:country":"US",
    "sg:address":"425 E Colorado St Ste 420",
    "sg:city":"Glendale",
    "sg:classifiers":[
        {
            "category":"Professional",
            "subcategory":"Employment Agencies",
            "type":"Services"
        }
    ],
    "sg:phone":"+1 818 638 0902",
    "sg:postcode":"91205",
    "sg:province":"CA",
    "sg:website":"www.aerotek.com",
    "wof:name":"Aerotek",
    "wof:placetype":"venue"
},
  "geometry": {"coordinates":[-118.25099899999999,34.142601],"type":"Point"}
}