{
  "type": "Feature",
  "properties": {
    "iso:country":"US",
    "sg:address":"373 Meridian Ave",
    "sg:city":"San Jose",
    "sg:classifiers":[
        {
            "category":"Health Services",
            "subcategory":"Dentist",
            "type":"Services"
        }
    ],
    "sg:phone":"+1 408 294 4403",
    "sg:postcode":"95126",
    "sg:province":"CA",
    "sg:website":"calvertdds.com",
    "wof:name":"Kevin W Calvert, DDS",
    "wof:placetype":"venue"
},
  "geometry": {"coordinates":[-121.914001,37.322498],"type":"Point"}
}