{
  "type": "Feature",
  "properties": {
    "addr:full":"781 Bay Blvd Chula Vista CA 91911",
    "addr:housenumber":"781",
    "addr:postcode":"91911",
    "addr:street":"Bay Blvd",
    "iso:country":"US",
    "sg:address":"781 Bay Blvd",
    "sg:city":"Chula Vista",
    "sg:classifiers":[
        {
            "category":"Wholesale",
            "subcategory":"Auto Parts",
            "type":"Manufacturing & Wholesale Goods"
        }
    ],
    "sg:phone":"+1 619 482 2124",
    "sg:postcode":"91911",
    "sg:province":"CA",
    "sg:tags":[
        "automobile"
    ],
    "wof:name":"Energy Way Auto Wrecking Inc",
    "wof:placetype":"venue"
},
  "geometry": {"coordinates":[-117.094308,32.621181],"type":"Point"}
}