{
  "type": "Feature",
  "properties": {
    "addr:full":"3811 Dividend Dr Shingle Springs CA 95682",
    "addr:housenumber":"3811",
    "addr:postcode":"95682",
    "addr:street":"Dividend Dr",
    "iso:country":"US",
    "sg:address":"3811 Dividend Dr",
    "sg:city":"Shingle Springs",
    "sg:classifiers":[
        {
            "category":"Wholesale",
            "subcategory":"Electrical",
            "type":"Manufacturing & Wholesale Goods"
        }
    ],
    "sg:phone":"+1 530 672 2318",
    "sg:postcode":"95682",
    "sg:province":"CA",
    "sg:tags":[
        "control"
    ],
    "wof:name":"Performance Controls",
    "wof:placetype":"venue"
},
  "geometry": {"coordinates":[-120.94985699999999,38.650388],"type":"Point"}
}