{
  "type": "Feature",
  "properties": {
    "addr:full":"1136 Clement St San Francisco CA 94118",
    "addr:housenumber":"1136",
    "addr:postcode":"94118",
    "addr:street":"Clement St",
    "iso:country":"US",
    "sg:address":"1136 Clement St",
    "sg:city":"San Francisco",
    "sg:classifiers":[
        {
            "category":"Autos & Motor Vehicles",
            "subcategory":"Motorcycle Sales",
            "type":"Retail Goods"
        }
    ],
    "sg:phone":"+1 415 668 8133",
    "sg:postcode":"94118",
    "sg:province":"CA",
    "wof:name":"West Coast Motorsports",
    "wof:placetype":"venue"
},
  "geometry": {"coordinates":[-122.47124100000001,37.782758],"type":"Point"}
}