{
  "type": "Feature",
  "properties": {
    "addr:full":"1423 21st St Sacramento CA 95814",
    "addr:housenumber":"1423",
    "addr:postcode":"95814",
    "addr:street":"21St St",
    "iso:country":"US",
    "sg:address":"1423 21st St",
    "sg:city":"Sacramento",
    "sg:classifiers":[
        {
            "category":"Personal",
            "subcategory":"Barber",
            "type":"Services"
        }
    ],
    "sg:phone":"+1 916 442 1170",
    "sg:postcode":"95814",
    "sg:province":"CA",
    "wof:name":"Limon's Barber Salon",
    "wof:placetype":"venue"
},
  "geometry": {"coordinates":[-121.481003,38.571201],"type":"Point"}
}