{
  "type": "Feature",
  "properties": {
    "iso:country":"US",
    "sg:address":"26231 Mission Blvd",
    "sg:city":"Hayward",
    "sg:classifiers":[
        {
            "category":"Shopping",
            "subcategory":"Department Store",
            "type":"Retail Goods"
        }
    ],
    "sg:phone":"+1 510 582 3884",
    "sg:postcode":"94544",
    "sg:province":"CA",
    "wof:name":"Kmart Stores",
    "wof:placetype":"venue"
},
  "geometry": {"coordinates":[-122.06500200000001,37.648899],"type":"Point"}
}