{
  "type": "Feature",
  "properties": {
    "iso:country":"US",
    "sg:address":"12175 Arbor Hill St",
    "sg:city":"Moorpark",
    "sg:classifiers":[
        {
            "category":"Professional",
            "type":"Services"
        }
    ],
    "sg:phone":"+1 805 523 0048",
    "sg:postcode":"93021",
    "sg:province":"CA",
    "wof:name":"Lakshmi Educational & Cul",
    "wof:placetype":"venue"
},
  "geometry": {"coordinates":[-118.88975000000001,34.261346],"type":"Point"}
}