{
  "type": "Feature",
  "properties": {
    "addr:full":"616 W Doran St Glendale CA 91203",
    "addr:housenumber":"616",
    "addr:postcode":"91203",
    "addr:street":"W Doran St",
    "iso:country":"US",
    "sg:address":"616 W Doran St",
    "sg:city":"Glendale",
    "sg:classifiers":[
        {
            "category":"Professional",
            "subcategory":"Computer Services",
            "type":"Services"
        }
    ],
    "sg:phone":"+1 818 548 1211",
    "sg:postcode":"91203",
    "sg:province":"CA",
    "sg:tags":[
        "programing",
        "custom"
    ],
    "wof:name":"Halaby & Assoc",
    "wof:placetype":"venue"
},
  "geometry": {"coordinates":[-118.268916,34.153968],"type":"Point"}
}