{
  "type": "Feature",
  "properties": {
    "iso:country":"US",
    "sg:address":"4373 N Harrison Ave",
    "sg:city":"Fresno",
    "sg:classifiers":[
        {
            "category":"Building & Trades",
            "subcategory":"Construction",
            "type":"Services"
        }
    ],
    "sg:phone":"+1 559 228 1098",
    "sg:postcode":"93704",
    "sg:province":"CA",
    "sg:tags":[
        "contractor"
    ],
    "wof:name":"Creative Construction",
    "wof:placetype":"venue"
},
  "geometry": {"coordinates":[-119.810861,36.796717],"type":"Point"}
}