{
  "type": "Feature",
  "properties": {
    "iso:country":"US",
    "sg:address":"2295 Pso de Las Americas",
    "sg:city":"San Diego",
    "sg:classifiers":[
        {
            "category":"Freight",
            "type":"Transportation"
        }
    ],
    "sg:phone":"+1 619 661 8223",
    "sg:postcode":"92154",
    "sg:province":"CA",
    "sg:tags":[
        "arrangement"
    ],
    "wof:name":"Pacific Basin Freight Forward",
    "wof:placetype":"venue"
},
  "geometry": {"coordinates":[-116.93586999999999,32.558492],"type":"Point"}
}