{
  "type": "Feature",
  "properties": {
    "addr:full":"4980 Appian Way El Sobrante CA 94803",
    "addr:housenumber":"4980",
    "addr:postcode":"94803",
    "addr:street":"Appian Way",
    "iso:country":"US",
    "sg:address":"4980 Appian Way",
    "sg:city":"El Sobrante",
    "sg:classifiers":[
        {
            "category":"Shopping",
            "subcategory":"Clothing, Apparel, & Fashions",
            "type":"Retail Goods"
        }
    ],
    "sg:phone":"+1 510 222 7350",
    "sg:postcode":"94803",
    "sg:province":"CA",
    "sg:tags":[
        "uniform"
    ],
    "wof:name":"Game Time Uniforms",
    "wof:placetype":"venue"
},
  "geometry": {"coordinates":[-122.297406,37.976227],"type":"Point"}
}