{
  "type": "Feature",
  "properties": {
    "iso:country":"US",
    "sg:address":"12 Corporate Plaza Dr",
    "sg:city":"Newport Beach",
    "sg:classifiers":[
        {
            "category":"Health Services",
            "subcategory":"Clinic",
            "type":"Services"
        }
    ],
    "sg:phone":"+1 949 717 4811",
    "sg:postcode":"92660",
    "sg:province":"CA",
    "wof:name":"NPM Consulting",
    "wof:placetype":"venue"
},
  "geometry": {"coordinates":[-117.876929,33.608285],"type":"Point"}
}