{
  "type": "Feature",
  "properties": {
    "addr:full":"131 Outlook Cir Pacifica CA 94044",
    "addr:housenumber":"131",
    "addr:postcode":"94044",
    "addr:street":"Outlook Cir",
    "iso:country":"US",
    "sg:address":"131 Outlook Cir",
    "sg:city":"Pacifica",
    "sg:classifiers":[
        {
            "category":"Professional",
            "subcategory":"Management & Consulting",
            "type":"Services"
        }
    ],
    "sg:phone":"+1 650 355 3521",
    "sg:postcode":"94044",
    "sg:province":"CA",
    "sg:tags":[
        "consultant"
    ],
    "wof:name":"Computational Genetics Conslnt",
    "wof:placetype":"venue"
},
  "geometry": {"coordinates":[-122.476123,37.632398],"type":"Point"}
}