{
  "type": "Feature",
  "properties": {
    "addr:full":"893 Arroyo Rd Sonoma CA 95476",
    "addr:housenumber":"893",
    "addr:postcode":"95476",
    "addr:street":"Arroyo Rd",
    "iso:country":"US",
    "sg:address":"893 Arroyo Rd",
    "sg:city":"Sonoma",
    "sg:classifiers":[
        {
            "category":"Retail",
            "subcategory":"Car Wash",
            "type":"Services"
        }
    ],
    "sg:phone":"+1 707 323 0056",
    "sg:postcode":"95476",
    "sg:province":"CA",
    "sg:tags":[
        "automobile",
        "detail",
        "clean"
    ],
    "wof:name":"Professional Auto Detailing",
    "wof:placetype":"venue"
},
  "geometry": {"coordinates":[-122.47756699999999,38.314938],"type":"Point"}
}