{
  "type": "Feature",
  "properties": {
    "addr:full":"14421 Bonelli St City Of Industry CA 91746",
    "addr:housenumber":"14421",
    "addr:postcode":"91746",
    "addr:street":"Bonelli St",
    "iso:country":"US",
    "sg:address":"14421 Bonelli St",
    "sg:city":"City Of Industry",
    "sg:phone":"+1 626 333 0666",
    "sg:postcode":"91746",
    "sg:province":"CA",
    "sg:tags":[
        "rack"
    ],
    "wof:name":"Sammons & Sons",
    "wof:placetype":"venue"
},
  "geometry": {"coordinates":[-117.987347,34.026725],"type":"Point"}
}