{
  "type": "Feature",
  "properties": {
    "iso:country":"US",
    "sg:address":"2900 Main St",
    "sg:city":"Alameda",
    "sg:classifiers":[
        {
            "category":"Freight",
            "type":"Transportation"
        }
    ],
    "sg:phone":"+1 415 546 2600",
    "sg:postcode":"94501",
    "sg:province":"CA",
    "sg:tags":[
        "marine"
    ],
    "wof:name":"Crowley Marine Services Inc",
    "wof:placetype":"venue"
},
  "geometry": {"coordinates":[-122.294231,37.789522],"type":"Point"}
}