{
  "type": "Feature",
  "properties": {
    "iso:country":"US",
    "sg:address":"12534 Valley View St",
    "sg:city":"Garden Grove",
    "sg:classifiers":[
        {
            "category":"Professional",
            "subcategory":"Management & Consulting",
            "type":"Services"
        }
    ],
    "sg:phone":"+1 714 284 9466",
    "sg:postcode":"92845",
    "sg:province":"CA",
    "sg:tags":[
        "consultant",
        "telecommunication"
    ],
    "wof:name":"AJM Communications",
    "wof:placetype":"venue"
},
  "geometry": {"coordinates":[-118.03085799999999,33.780536],"type":"Point"}
}