{
  "type": "Feature",
  "properties": {
    "iso:country":"US",
    "sg:address":"13075 Ave 200",
    "sg:city":"Tulare",
    "sg:classifiers":[
        {
            "category":"Food & Beverages",
            "subcategory":"Dairy",
            "type":"Retail Goods"
        }
    ],
    "sg:phone":"+1 559 686 6929",
    "sg:postcode":"93274",
    "sg:province":"CA",
    "sg:tags":[
        "product"
    ],
    "wof:name":"Triple H Dairy",
    "wof:placetype":"venue"
},
  "geometry": {"coordinates":[-119.28154,36.152706],"type":"Point"}
}