{
  "type": "Feature",
  "properties": {
    "addr:full":"37181 Moraine St Fremont CA 94536",
    "addr:postcode":"37181;94536",
    "addr:street":"Moraine St",
    "iso:country":"US",
    "sg:address":"37181 Moraine St",
    "sg:city":"Fremont",
    "sg:classifiers":[
        {
            "category":"Real Estate",
            "subcategory":"Real Estate Agent",
            "type":"Services"
        }
    ],
    "sg:phone":"+1 510 744 9269",
    "sg:postcode":"94536",
    "sg:province":"CA",
    "wof:name":"Realty World Broker's Network",
    "wof:placetype":"venue"
},
  "geometry": {"coordinates":[-122.00716799999999,37.561583],"type":"Point"}
}