{
  "type": "Feature",
  "properties": {
    "addr:full":"437 Roberts Rd Pacifica CA 94044",
    "addr:housenumber":"437",
    "addr:postcode":"94044",
    "addr:street":"Roberts Rd",
    "iso:country":"US",
    "sg:address":"437 Roberts Rd",
    "sg:city":"Pacifica",
    "sg:classifiers":[
        {
            "category":"Social Services",
            "type":"Services"
        }
    ],
    "sg:phone":"+1 650 359 6580",
    "sg:postcode":"94044",
    "sg:province":"CA",
    "sg:tags":[
        "counselor",
        "marriage",
        "family"
    ],
    "wof:name":"Rosemary A Jalovaara PHD",
    "wof:placetype":"venue"
},
  "geometry": {"coordinates":[-122.496078,37.602132],"type":"Point"}
}