{
  "type": "Feature",
  "properties": {
    "addr:full":"1517 N Cahuenga Boulevard Los Angeles CA 90028",
    "addr:housenumber":"1517",
    "addr:postcode":"90028",
    "addr:street":"N Cahuenga Boulevard",
    "iso:country":"US",
    "sg:address":"1517 N Cahuenga Boulevard",
    "sg:city":"Los Angeles",
    "sg:classifiers":[
        {
            "category":"Building & Trades",
            "subcategory":"Locksmith",
            "type":"Services"
        }
    ],
    "sg:phone":"+1 323 206 4404",
    "sg:postcode":"90028",
    "sg:province":"CA",
    "sg:tags":[
        "key"
    ],
    "wof:name":"All Day 24 7 Locks & Locksmith",
    "wof:placetype":"venue"
},
  "geometry": {"coordinates":[-118.32964,34.098879],"type":"Point"}
}