{
  "type": "Feature",
  "properties": {
    "iso:country":"US",
    "sg:address":"7791 Magnolia Avenue",
    "sg:city":"Fair Oaks",
    "sg:classifiers":[
        {
            "category":"Shopping",
            "subcategory":"Beauty & Cosmetics",
            "type":"Retail Goods"
        }
    ],
    "sg:phone":"+1 916 966 2887",
    "sg:postcode":"95628",
    "sg:province":"CA",
    "sg:tags":[
        "supply"
    ],
    "wof:name":"Butticci's Hair Company",
    "wof:placetype":"venue"
},
  "geometry": {"coordinates":[-121.27871,38.636728],"type":"Point"}
}