{
  "type": "Feature",
  "properties": {
    "addr:full":"1217 Sutter St San Francisco CA 94109",
    "addr:housenumber":"1217",
    "addr:postcode":"94109",
    "addr:street":"Sutter St",
    "iso:country":"US",
    "sg:address":"1217 Sutter St",
    "sg:city":"San Francisco",
    "sg:classifiers":[
        {
            "category":"Restaurant",
            "type":"Food & Drink"
        }
    ],
    "sg:menulink":"http://www.allmenus.com/ca/san-francisco/21974-juni/menu/",
    "sg:phone":"+1 415 292 5864",
    "sg:postcode":"94109",
    "sg:province":"CA",
    "sg:tags":[
        "japanese",
        "asian"
    ],
    "wof:name":"Juni",
    "wof:placetype":"venue"
},
  "geometry": {"coordinates":[-122.420475,37.787756],"type":"Point"}
}