{
  "type": "Feature",
  "properties": {
    "iso:country":"US",
    "sg:address":"4340 La Jolla Village Dr",
    "sg:city":"San Diego",
    "sg:classifiers":[
        {
            "category":"Restaurant",
            "type":"Food & Drink"
        }
    ],
    "sg:menulink":"http://www.allmenus.com/ca/san-diego/266967-donovans-of-la-jolla/menu/",
    "sg:phone":"+1 858 450 6666",
    "sg:postcode":"92122",
    "sg:province":"CA",
    "wof:name":"Donovan's of La Jolla",
    "wof:placetype":"venue"
},
  "geometry": {"coordinates":[-117.212411,32.873507],"type":"Point"}
}