{
  "type": "Feature",
  "properties": {
    "addr:full":"8595 Nevada Ave Canoga Park CA 91304",
    "addr:housenumber":"8595",
    "addr:postcode":"91304",
    "addr:street":"Nevada Ave",
    "iso:country":"US",
    "sg:address":"8595 Nevada Ave",
    "sg:city":"Canoga Park",
    "sg:classifiers":[
        {
            "category":"Real Estate",
            "subcategory":"Real Estate Agent",
            "type":"Services"
        }
    ],
    "sg:phone":"+1 818 992 3307",
    "sg:postcode":"91304",
    "sg:province":"CA",
    "wof:name":"Dean Webb",
    "wof:placetype":"venue"
},
  "geometry": {"coordinates":[-118.60910199999999,34.226158],"type":"Point"}
}