{
  "type": "Feature",
  "properties": {
    "iso:country":"US",
    "sg:address":"8595 Nevada Ave",
    "sg:city":"Canoga Park",
    "sg:classifiers":[
        {
            "category":"Real Estate",
            "subcategory":"Real Estate Agent",
            "type":"Services"
        }
    ],
    "sg:phone":"+1 818 992 3307",
    "sg:postcode":"91304",
    "sg:province":"CA",
    "wof:name":"Dean Webb",
    "wof:placetype":"venue"
},
  "geometry": {"coordinates":[-118.609102,34.226158],"type":"Point"}
}