{
  "type": "Feature",
  "properties": {
    "iso:country":"US",
    "sg:address":"1700 N Broadway",
    "sg:city":"Walnut Creek",
    "sg:classifiers":[
        {
            "category":"Professional",
            "subcategory":"Lawyer & Legal Services",
            "type":"Services"
        }
    ],
    "sg:phone":"+1 925 943 5400",
    "sg:postcode":"94596",
    "sg:province":"CA",
    "sg:tags":[
        "attorney"
    ],
    "wof:name":"Bonnie L Johnson",
    "wof:placetype":"venue"
},
  "geometry": {"coordinates":[-122.061162,37.90406],"type":"Point"}
}