{
  "type": "Feature",
  "properties": {
    "iso:country":"US",
    "sg:address":"1624 W Redondo Beach Boulevard",
    "sg:city":"Gardena",
    "sg:classifiers":[
        {
            "category":"Travel",
            "subcategory":"Hotels & Motels",
            "type":"Entertainment"
        }
    ],
    "sg:phone":"+1 310 532 5200",
    "sg:postcode":"90247",
    "sg:province":"CA",
    "wof:name":"Pico Professional Building",
    "wof:placetype":"venue"
},
  "geometry": {"coordinates":[-118.305108,33.889936],"type":"Point"}
}