{
  "type": "Feature",
  "properties": {
    "addr:full":"1506 A St Antioch CA 94509",
    "addr:housenumber":"1506",
    "addr:postcode":"ca 94509",
    "addr:street":"A St",
    "iso:country":"US",
    "sg:address":"1506 A St",
    "sg:city":"Antioch",
    "sg:classifiers":[
        {
            "category":"Insurance",
            "subcategory":"Insurance Agent",
            "type":"Services"
        }
    ],
    "sg:phone":"+1 925 727 3100",
    "sg:postcode":"94509",
    "sg:province":"CA",
    "wof:name":"Access Avenue Insurance",
    "wof:placetype":"venue"
},
  "geometry": {"coordinates":[-121.8061,38.007233],"type":"Point"}
}