{
  "type": "Feature",
  "properties": {
    "addr:full":"6520 Monitor St Bakersfield CA 93307",
    "addr:housenumber":"6520",
    "addr:postcode":"93307",
    "addr:street":"Monitor St",
    "iso:country":"US",
    "sg:address":"6520 Monitor St",
    "sg:city":"Bakersfield",
    "sg:classifiers":[
        {
            "category":"Retail",
            "subcategory":"Photofinishing",
            "type":"Services"
        },
        {
            "category":"Professional",
            "subcategory":"Printing & Photocopies",
            "type":"Services"
        }
    ],
    "sg:phone":"+1 661 397 3897",
    "sg:postcode":"93307",
    "sg:province":"CA",
    "sg:tags":[
        "laboratory",
        "laboratories-commercial",
        "finishing-custom",
        "photo"
    ],
    "wof:name":"M G M",
    "wof:placetype":"venue"
},
  "geometry": {"coordinates":[-119.011887,35.295617],"type":"Point"}
}