{
  "type": "Feature",
  "properties": {
    "iso:country":"US",
    "sg:address":"17739 Halsted St",
    "sg:city":"Northridge",
    "sg:classifiers":[
        {
            "category":"Organizations",
            "subcategory":"Community Association",
            "type":"Services"
        }
    ],
    "sg:phone":"+1 818 993 9159",
    "sg:postcode":"91325",
    "sg:province":"CA",
    "sg:tags":[
        "sorority",
        "fraternity"
    ],
    "wof:name":"Delta Delta Delta",
    "wof:placetype":"venue"
},
  "geometry": {"coordinates":[-118.522738,34.24502],"type":"Point"}
}