{
  "type": "Feature",
  "properties": {
    "iso:country":"US",
    "sg:address":"14341 San Pablo Ave",
    "sg:city":"San Pablo",
    "sg:classifiers":[
        {
            "category":"Health Services",
            "subcategory":"Chiropractor",
            "type":"Services"
        }
    ],
    "sg:phone":"+1 510 237 2663",
    "sg:postcode":"94806",
    "sg:province":"CA",
    "wof:name":"San Pablo Chiropractic Group",
    "wof:placetype":"venue"
},
  "geometry": {"coordinates":[-122.34492,37.965394],"type":"Point"}
}