{
  "type": "Feature",
  "properties": {
    "addr:full":"605 S Harbor Blvd Santa Ana CA 92704",
    "addr:housenumber":"605",
    "addr:postcode":"92704",
    "addr:street":"S Harbor Blvd",
    "iso:country":"US",
    "sg:address":"605 S Harbor Blvd",
    "sg:city":"Santa Ana",
    "sg:classifiers":[
        {
            "category":"Shopping",
            "subcategory":"Shoes",
            "type":"Retail Goods"
        }
    ],
    "sg:phone":"+1 714 531 3622",
    "sg:postcode":"92704",
    "sg:province":"CA",
    "sg:tags":[
        "store"
    ],
    "sg:website":"www.shoecity.com",
    "wof:name":"Shoe City",
    "wof:placetype":"venue"
},
  "geometry": {"coordinates":[-117.91999800000001,33.7393],"type":"Point"}
}