{
  "type": "Feature",
  "properties": {
    "addr:full":"1431 7th St Santa Monica CA 90401",
    "addr:housenumber":"1431",
    "addr:postcode":"90401",
    "addr:street":"7Th St",
    "iso:country":"US",
    "sg:address":"1431 7th St",
    "sg:city":"Santa Monica",
    "sg:classifiers":[
        {
            "category":"Professional",
            "subcategory":"Detective & Security Services",
            "type":"Services"
        }
    ],
    "sg:phone":"+1 310 393 9673",
    "sg:postcode":"90401",
    "sg:province":"CA",
    "sg:tags":[
        "guard",
        "patrol"
    ],
    "wof:name":"Tandem Security",
    "wof:placetype":"venue"
},
  "geometry": {"coordinates":[-118.491117,34.017838],"type":"Point"}
}