{
  "type": "Feature",
  "properties": {
    "iso:country":"US",
    "sg:address":"1199 Broadway Ave",
    "sg:city":"Atwater",
    "sg:classifiers":[
        {
            "category":"Home & Garden",
            "subcategory":"Building Materials",
            "type":"Retail Goods"
        }
    ],
    "sg:phone":"+1 209 358 3188",
    "sg:postcode":"95301",
    "sg:province":"CA",
    "sg:tags":[
        "glass",
        "leaded"
    ],
    "wof:name":"Resse's Riginal Stained Glass",
    "wof:placetype":"venue"
},
  "geometry": {"coordinates":[-120.60786299999999,37.346463],"type":"Point"}
}