{
  "type": "Feature",
  "properties": {
    "addr:full":"245 N Villa Ave Willows CA 95988",
    "addr:housenumber":"245",
    "addr:postcode":"95988",
    "addr:street":"N Villa Ave",
    "iso:country":"US",
    "sg:address":"245 N Villa Ave",
    "sg:city":"Willows",
    "sg:classifiers":[
        {
            "category":"Health Services",
            "subcategory":"Doctor",
            "type":"Services"
        }
    ],
    "sg:phone":"+1 530 934 4040",
    "sg:postcode":"95988",
    "sg:province":"CA",
    "sg:tags":[
        "physician",
        "surgeon"
    ],
    "wof:name":"Victor Szanto MD",
    "wof:placetype":"venue"
},
  "geometry": {"coordinates":[-122.208866,39.524164],"type":"Point"}
}