{
  "type": "Feature",
  "properties": {
    "iso:country":"US",
    "sg:address":"1666 The Alameda",
    "sg:city":"San Jose",
    "sg:classifiers":[
        {
            "category":"Professional",
            "subcategory":"Lawyer & Legal Services",
            "type":"Services"
        }
    ],
    "sg:phone":"+1 408 286 6314",
    "sg:postcode":"95126",
    "sg:province":"CA",
    "wof:name":"Vanasse Charles F Atty",
    "wof:placetype":"venue"
},
  "geometry": {"coordinates":[-121.91799899999999,37.3367],"type":"Point"}
}