{
  "type": "Feature",
  "properties": {
    "iso:country":"US",
    "sg:address":"3401 Pacific Ave",
    "sg:city":"Marina Del Rey",
    "sg:classifiers":[
        {
            "category":"Professional",
            "subcategory":"Management & Consulting",
            "type":"Services"
        }
    ],
    "sg:phone":"+1 310 827 9927",
    "sg:postcode":"90292",
    "sg:province":"CA",
    "sg:tags":[
        "marketing",
        "program"
    ],
    "wof:name":"Cobalt Marketing",
    "wof:placetype":"venue"
},
  "geometry": {"coordinates":[-118.463975,33.977591],"type":"Point"}
}