{
  "type": "Feature",
  "properties": {
    "addr:full":"2155 Golden Centre Ln Rancho Cordova CA 95670",
    "addr:housenumber":"2155",
    "addr:postcode":"95670",
    "addr:street":"Golden Centre Ln",
    "iso:country":"US",
    "sg:address":"2155 Golden Centre Ln",
    "sg:city":"Rancho Cordova",
    "sg:classifiers":[
        {
            "category":"Banks & Credit Unions",
            "subcategory":"Bank",
            "type":"Services"
        },
        {
            "category":"Banks & Credit Unions",
            "subcategory":"Financial Services",
            "type":"Services"
        }
    ],
    "sg:phone":"+1 916 861 9458",
    "sg:postcode":"95670",
    "sg:province":"CA",
    "sg:tags":[
        "broker",
        "mortgage"
    ],
    "sg:website":"www.bankofamerica.com",
    "wof:name":"Bank of America",
    "wof:placetype":"venue"
},
  "geometry": {"coordinates":[-121.262001,38.6255],"type":"Point"}
}