{
  "type": "Feature",
  "properties": {
    "addr:full":"103 Sunnyhills Dr Watsonville CA 95076",
    "addr:housenumber":"103",
    "addr:postcode":"95076",
    "addr:street":"Sunnyhills Dr",
    "iso:country":"US",
    "sg:address":"103 Sunnyhills Dr",
    "sg:city":"Watsonville",
    "sg:classifiers":[
        {
            "category":"Home & Garden",
            "subcategory":"Carpets & Floor Coverings",
            "type":"Retail Goods"
        }
    ],
    "sg:phone":"+1 831 728 1036",
    "sg:postcode":"95076",
    "sg:province":"CA",
    "sg:tags":[
        "distributor",
        "rug",
        "manufacturer"
    ],
    "wof:name":"Nine One One Productions",
    "wof:placetype":"venue"
},
  "geometry": {"coordinates":[-121.785751,36.930199],"type":"Point"}
}