{
  "type": "Feature",
  "properties": {
    "iso:country":"US",
    "sg:address":"2855 Stevens Creek Blvd",
    "sg:city":"San Jose",
    "sg:classifiers":[
        {
            "category":"Shopping",
            "subcategory":"Gifts & Souvenirs",
            "type":"Retail Goods"
        }
    ],
    "sg:phone":"+1 408 261 9120",
    "sg:postcode":"95014",
    "sg:province":"CA",
    "sg:tags":[
        "collectible"
    ],
    "wof:name":"Sports World Collectables",
    "wof:placetype":"venue"
},
  "geometry": {"coordinates":[-121.945719,37.323439],"type":"Point"}
}