{
  "type": "Feature",
  "properties": {
    "addr:full":"3752 Allen Rd Bakersfield CA 93314",
    "addr:housenumber":"3752",
    "addr:postcode":"93314",
    "addr:street":"Allen Rd",
    "iso:country":"US",
    "sg:address":"3752 Allen Rd",
    "sg:city":"Bakersfield",
    "sg:classifiers":[
        {
            "category":"Professional",
            "subcategory":"Research",
            "type":"Services"
        }
    ],
    "sg:phone":"+1 661 589 5220",
    "sg:postcode":"93314",
    "sg:province":"CA",
    "sg:tags":[
        "environmental",
        "ecological"
    ],
    "wof:name":"KES-KERN Environmental Svc",
    "wof:placetype":"venue"
},
  "geometry": {"coordinates":[-119.145439,35.390121],"type":"Point"}
}