{
  "type": "Feature",
  "properties": {
    "iso:country":"US",
    "sg:address":"16935 W Bernardo Dr",
    "sg:city":"San Diego",
    "sg:classifiers":[
        {
            "category":"Manufacturing",
            "subcategory":"Retail Goods",
            "type":"Manufacturing & Wholesale Goods"
        }
    ],
    "sg:phone":"+1 858 674 8455",
    "sg:postcode":"92127",
    "sg:province":"CA",
    "sg:tags":[
        "manufacturer"
    ],
    "wof:name":"Imagenetix",
    "wof:placetype":"venue"
},
  "geometry": {"coordinates":[-117.089285,33.012866],"type":"Point"}
}