{
  "type": "Feature",
  "properties": {
    "addr:full":"8976 Huntington Dr San Gabriel CA 91775",
    "addr:housenumber":"8976",
    "addr:postcode":"91775",
    "addr:street":"Huntington Dr",
    "iso:country":"US",
    "sg:address":"8976 Huntington Dr",
    "sg:city":"San Gabriel",
    "sg:classifiers":[
        {
            "category":"Restaurant",
            "type":"Food & Drink"
        }
    ],
    "sg:phone":"+1 626 286 1484",
    "sg:postcode":"91775",
    "sg:province":"CA",
    "wof:name":"Clearman's North Woods Inn of San Gabriel",
    "wof:placetype":"venue"
},
  "geometry": {"coordinates":[-118.072998,34.130199],"type":"Point"}
}