{
  "type": "Feature",
  "properties": {
    "addr:full":"2020 Webber Ave Yountville CA 94599",
    "addr:housenumber":"2020",
    "addr:postcode":"ca 94599",
    "addr:street":"Webber Ave",
    "iso:country":"US",
    "sg:address":"2020 Webber Ave",
    "sg:city":"Yountville",
    "sg:classifiers":[
        {
            "category":"Travel",
            "subcategory":"Hotels & Motels",
            "type":"Entertainment"
        }
    ],
    "sg:phone":"+1 707 944 1388",
    "sg:postcode":"94599",
    "sg:province":"CA",
    "sg:tags":[
        "breakfast",
        "accommodation",
        "bed"
    ],
    "wof:name":"Lavender",
    "wof:placetype":"venue"
},
  "geometry": {"coordinates":[-122.363519,38.404169],"type":"Point"}
}