{
  "type": "Feature",
  "properties": {
    "iso:country":"US",
    "sg:address":"2066 Old Middlefield Way",
    "sg:city":"Mountain View",
    "sg:classifiers":[
        {
            "category":"Shopping",
            "subcategory":"Jewelry",
            "type":"Retail Goods"
        }
    ],
    "sg:phone":"+1 650 961 3347",
    "sg:postcode":"94043",
    "sg:province":"CA",
    "wof:name":"Jennifer Jewelers",
    "wof:placetype":"venue"
},
  "geometry": {"coordinates":[-122.09159200000001,37.414573],"type":"Point"}
}