{
  "type": "Feature",
  "properties": {
    "iso:country":"US",
    "sg:address":"826 J Street",
    "sg:city":"Sacramento",
    "sg:classifiers":[
        {
            "category":"Restaurant",
            "type":"Food & Drink"
        },
        {
            "category":"Food & Beverages",
            "subcategory":"Ethnic Foods",
            "type":"Retail Goods"
        }
    ],
    "sg:phone":"+1 916 447 2260",
    "sg:postcode":"95814",
    "sg:province":"CA",
    "sg:tags":[
        "new",
        "american",
        "soul"
    ],
    "wof:name":"Table 260",
    "wof:placetype":"venue"
},
  "geometry": {"coordinates":[-121.49519600000001,38.580759],"type":"Point"}
}