{
  "type": "Feature",
  "properties": {
    "iso:country":"US",
    "sg:address":"1542 E Lincoln Ave",
    "sg:city":"Escondido",
    "sg:classifiers":[
        {
            "category":"Wholesale",
            "subcategory":"Non-durable Goods",
            "type":"Manufacturing & Wholesale Goods"
        }
    ],
    "sg:phone":"+1 760 740 1739",
    "sg:postcode":"92027",
    "sg:province":"CA",
    "sg:tags":[
        "textile",
        "leather",
        "belt"
    ],
    "wof:name":"La Fargo Del Mar Inc",
    "wof:placetype":"venue"
},
  "geometry": {"coordinates":[-117.067277,33.142486],"type":"Point"}
}