{
  "type": "Feature",
  "properties": {
    "addr:full":"450 Ocean Ave Laguna Beach CA 92651",
    "addr:housenumber":"450",
    "addr:postcode":"92651",
    "addr:street":"Ocean Ave",
    "iso:country":"US",
    "sg:address":"450 Ocean Ave",
    "sg:city":"Laguna Beach",
    "sg:classifiers":[
        {
            "category":"Wholesale",
            "subcategory":"Non-durable Goods",
            "type":"Manufacturing & Wholesale Goods"
        }
    ],
    "sg:phone":"+1 949 376 6907",
    "sg:postcode":"92651",
    "sg:province":"CA",
    "wof:name":"Textile Dreams",
    "wof:placetype":"venue"
},
  "geometry": {"coordinates":[-117.782703,33.544479],"type":"Point"}
}