{
  "type": "Feature",
  "properties": {
    "addr:full":"13215 Leadwell St North Hollywood CA 91605",
    "addr:housenumber":"13215",
    "addr:postcode":"91605",
    "addr:street":"Leadwell St",
    "iso:country":"US",
    "sg:address":"13215 Leadwell St",
    "sg:city":"North Hollywood",
    "sg:classifiers":[
        {
            "category":"Autos & Motor Vehicles",
            "subcategory":"Motorcycle Sales",
            "type":"Retail Goods"
        }
    ],
    "sg:phone":"+1 818 765 0895",
    "sg:postcode":"91605",
    "sg:province":"CA",
    "wof:name":"Sources Unlimited",
    "wof:placetype":"venue"
},
  "geometry": {"coordinates":[-118.420998,34.2038],"type":"Point"}
}