{
  "type": "Feature",
  "properties": {
    "addr:full":"530 Moorpark Ave Moorpark CA 93021",
    "addr:housenumber":"530",
    "addr:postcode":"ca 93021",
    "addr:street":"Moorpark Ave",
    "iso:country":"US",
    "sg:address":"530 Moorpark Ave",
    "sg:city":"Moorpark",
    "sg:classifiers":[
        {
            "category":"Professional",
            "subcategory":"Accounting & Tax Preparation",
            "type":"Services"
        }
    ],
    "sg:phone":"+1 805 529 4415",
    "sg:postcode":"93021",
    "sg:province":"CA",
    "sg:tags":[
        "bookkeeping",
        "general"
    ],
    "wof:name":"Ireland Tax & Business Svc",
    "wof:placetype":"venue"
},
  "geometry": {"coordinates":[-118.88202099999999,34.28423],"type":"Point"}
}