{
  "type": "Feature",
  "properties": {
    "addr:full":"14969 Los Gatos Almaden Rd Los Gatos CA 95032",
    "addr:housenumber":"14969",
    "addr:postcode":"95032",
    "addr:street":"Almaden Rd",
    "iso:country":"US",
    "sg:address":"14969 Los Gatos Almaden Rd",
    "sg:city":"Los Gatos",
    "sg:classifiers":[
        {
            "category":"Education",
            "subcategory":"School",
            "type":"Public Place"
        }
    ],
    "sg:phone":"+1 408 371 5620",
    "sg:postcode":"95032",
    "sg:province":"CA",
    "sg:tags":[
        "academic",
        "special"
    ],
    "wof:name":"Beginning Steps-Independence",
    "wof:placetype":"venue"
},
  "geometry": {"coordinates":[-121.930333,37.243501],"type":"Point"}
}