{
  "type": "Feature",
  "properties": {
    "addr:full":"4250 Executive Sq Ste 125 La Jolla CA 92037",
    "addr:housenumber":"4250",
    "addr:postcode":"92037",
    "addr:street":"Executive Sq Ste 125",
    "iso:country":"US",
    "sg:address":"4250 Executive Sq Ste 125",
    "sg:city":"La Jolla",
    "sg:classifiers":[
        {
            "category":"Restaurant",
            "type":"Food & Drink"
        }
    ],
    "sg:phone":"+1 858 452 3939",
    "sg:postcode":"92037",
    "sg:province":"CA",
    "wof:name":"Brothers Restaurant & Deli",
    "wof:placetype":"venue"
},
  "geometry": {"coordinates":[-117.214996,32.874001],"type":"Point"}
}