{
  "type": "Feature",
  "properties": {
    "addr:full":"1153 Catalina Dr Livermore CA 94550",
    "addr:housenumber":"1153",
    "addr:postcode":"94550",
    "addr:street":"Catalina Dr",
    "iso:country":"US",
    "sg:address":"1153 Catalina Dr",
    "sg:city":"Livermore",
    "sg:classifiers":[
        {
            "category":"Food & Beverages",
            "subcategory":"Liquor & Beverages",
            "type":"Retail Goods"
        }
    ],
    "sg:phone":"+1 925 447 4622",
    "sg:postcode":"94550",
    "sg:province":"CA",
    "wof:name":"Ernie's Wine & Liquor",
    "wof:placetype":"venue"
},
  "geometry": {"coordinates":[-121.781175,37.662847],"type":"Point"}
}