{
  "type": "Feature",
  "properties": {
    "addr:full":"7341 Coati Pl Ventura CA 93003",
    "addr:housenumber":"7341",
    "addr:postcode":"93003",
    "addr:street":"Coati Pl",
    "iso:country":"US",
    "sg:address":"7341 Coati Pl",
    "sg:city":"Ventura",
    "sg:classifiers":[
        {
            "category":"Manufacturing",
            "subcategory":"Apparel",
            "type":"Manufacturing & Wholesale Goods"
        }
    ],
    "sg:phone":"+1 805 647 2269",
    "sg:postcode":"93003",
    "sg:province":"CA",
    "sg:tags":[
        "embroidery"
    ],
    "wof:name":"Creative Stitches",
    "wof:placetype":"venue"
},
  "geometry": {"coordinates":[-119.190073,34.256046],"type":"Point"}
}