{
  "type": "Feature",
  "properties": {
    "addr:full":"2656 Eel River Dr Loleta CA 95551",
    "addr:housenumber":"2656",
    "addr:postcode":"95551",
    "addr:street":"Eel River Dr",
    "iso:country":"US",
    "sg:address":"2656 Eel River Dr",
    "sg:city":"Loleta",
    "sg:classifiers":[
        {
            "category":"Utilities",
            "subcategory":"Refuse",
            "type":"Services"
        }
    ],
    "sg:phone":"+1 707 733 5122",
    "sg:postcode":"95551",
    "sg:province":"CA",
    "sg:tags":[
        "sanitation"
    ],
    "wof:name":"Loleta Waste Water Plant",
    "wof:placetype":"venue"
},
  "geometry": {"coordinates":[-124.226286,40.640107],"type":"Point"}
}