{
  "type": "Feature",
  "properties": {
    "iso:country":"US",
    "sg:address":"1175 W 11th St",
    "sg:city":"Tracy",
    "sg:classifiers":[
        {
            "category":"Place Of Worship",
            "subcategory":"Church",
            "type":"Public Place"
        },
        {
            "category":"Place Of Worship",
            "type":"Public Place"
        },
        {
            "category":"Education",
            "subcategory":"School",
            "type":"Public Place"
        }
    ],
    "sg:phone":"+1 209 835 8777",
    "sg:postcode":"95376",
    "sg:province":"CA",
    "sg:tags":[
        "k-",
        "denomination",
        "private",
        "interest",
        "churches-interdenominational",
        "religious",
        "churches-various"
    ],
    "sg:website":"http://www.vcctracy.org",
    "wof:name":"Victory Christian Academy",
    "wof:placetype":"venue"
},
  "geometry": {"coordinates":[-121.43975,37.739705],"type":"Point"}
}