{
  "type": "Feature",
  "properties": {
    "addr:full":"2900 Rheem Ave Richmond CA 94804",
    "addr:housenumber":"2900",
    "addr:postcode":"94804",
    "addr:street":"Rheem Ave",
    "iso:country":"US",
    "sg:address":"2900 Rheem Ave",
    "sg:city":"Richmond",
    "sg:classifiers":[
        {
            "category":"Building & Trades",
            "subcategory":"Plumbing",
            "type":"Services"
        }
    ],
    "sg:phone":"+1 510 236 8564",
    "sg:postcode":"94804",
    "sg:province":"CA",
    "wof:name":"Provider Plumbing",
    "wof:placetype":"venue"
},
  "geometry": {"coordinates":[-122.336725,37.949864],"type":"Point"}
}