{
  "type": "Feature",
  "properties": {
    "iso:country":"US",
    "sg:address":"267 E Campbell Ave",
    "sg:city":"Campbell",
    "sg:classifiers":[
        {
            "category":"Banks & Credit Unions",
            "subcategory":"Bank",
            "type":"Services"
        }
    ],
    "sg:phone":"+1 408 374 7004",
    "sg:postcode":"95008",
    "sg:province":"CA",
    "sg:tags":[
        "loan"
    ],
    "wof:name":"Ameritrust Mortgage Group",
    "wof:placetype":"venue"
},
  "geometry": {"coordinates":[-121.94586200000001,37.287115],"type":"Point"}
}