{
  "type": "Feature",
  "properties": {
    "iso:country":"US",
    "sg:address":"5405 Arrow Hwy",
    "sg:city":"Montclair",
    "sg:classifiers":[
        {
            "category":"Professional",
            "subcategory":"Management & Consulting",
            "type":"Services"
        }
    ],
    "sg:phone":"+1 909 982 9916",
    "sg:postcode":"91763",
    "sg:province":"CA",
    "wof:name":"Primerica",
    "wof:placetype":"venue"
},
  "geometry": {"coordinates":[-117.687201,34.092267],"type":"Point"}
}