{
  "type": "Feature",
  "properties": {
    "addr:full":"1464 S Coast Hwy Laguna Beach CA 92651",
    "addr:housenumber":"1464",
    "addr:postcode":"92651",
    "addr:street":"S Coast Hwy",
    "iso:country":"US",
    "sg:address":"1464 S Coast Hwy",
    "sg:city":"Laguna Beach",
    "sg:classifiers":[
        {
            "category":"Restaurant",
            "type":"Food & Drink"
        }
    ],
    "sg:phone":"+1 949 494 8444",
    "sg:postcode":"92651",
    "sg:province":"CA",
    "wof:name":"French 75",
    "wof:placetype":"venue"
},
  "geometry": {"coordinates":[-117.774468,33.531545],"type":"Point"}
}