{
  "type": "Feature",
  "properties": {
    "iso:country":"US",
    "sg:address":"12708 Norton Ave",
    "sg:city":"Chino",
    "sg:classifiers":[
        {
            "category":"Manufacturing",
            "subcategory":"Food",
            "type":"Manufacturing & Wholesale Goods"
        }
    ],
    "sg:phone":"+1 909 590 3145",
    "sg:postcode":"91710",
    "sg:province":"CA",
    "sg:tags":[
        "ice",
        "mfg"
    ],
    "wof:name":"Redco Metal Services",
    "wof:placetype":"venue"
},
  "geometry": {"coordinates":[-117.711166,34.021979],"type":"Point"}
}