{
  "type": "Feature",
  "properties": {
    "addr:full":"12708 Norton Ave Chino CA 91710",
    "addr:housenumber":"12708",
    "addr:postcode":"91710",
    "addr:street":"Norton Ave",
    "iso:country":"US",
    "sg:address":"12708 Norton Ave",
    "sg:city":"Chino",
    "sg:classifiers":[
        {
            "category":"Manufacturing",
            "subcategory":"Food",
            "type":"Manufacturing & Wholesale Goods"
        }
    ],
    "sg:phone":"+1 909 590 3145",
    "sg:postcode":"91710",
    "sg:province":"CA",
    "sg:tags":[
        "ice",
        "mfg"
    ],
    "wof:name":"Redco Metal Services",
    "wof:placetype":"venue"
},
  "geometry": {"coordinates":[-117.71116600000001,34.021979],"type":"Point"}
}