{
  "type": "Feature",
  "properties": {
    "iso:country":"US",
    "sg:address":"203 Springview",
    "sg:city":"Irvine",
    "sg:classifiers":[
        {
            "category":"Professional",
            "type":"Services"
        }
    ],
    "sg:phone":"+1 714 832 5463",
    "sg:postcode":"92620",
    "sg:province":"CA",
    "sg:tags":[
        "shop",
        "pet",
        "calligrapher",
        "balloon",
        "sitting"
    ],
    "wof:name":"Calligraphy Artisan",
    "wof:placetype":"venue"
},
  "geometry": {"coordinates":[-117.758357,33.713854],"type":"Point"}
}