{
  "type": "Feature",
  "properties": {
    "iso:country":"US",
    "sg:address":"819 E 62nd St",
    "sg:city":"Los Angeles",
    "sg:classifiers":[
        {
            "category":"Wholesale",
            "subcategory":"Furniture",
            "type":"Manufacturing & Wholesale Goods"
        }
    ],
    "sg:phone":"+1 323 234 6745",
    "sg:postcode":"90001",
    "sg:province":"CA",
    "sg:tags":[
        "mattress"
    ],
    "wof:name":"Good Matttress Co",
    "wof:placetype":"venue"
},
  "geometry": {"coordinates":[-118.26204199999999,33.983289],"type":"Point"}
}