{
  "type": "Feature",
  "properties": {
    "addr:full":"3618 Oso St San Mateo CA 94403",
    "addr:housenumber":"3618",
    "addr:postcode":"94403",
    "addr:street":"Oso St",
    "iso:country":"US",
    "sg:address":"3618 Oso St",
    "sg:city":"San Mateo",
    "sg:classifiers":[
        {
            "category":"Arts & Performance",
            "subcategory":"Theater",
            "type":"Entertainment"
        }
    ],
    "sg:phone":"+1 650 572 0690",
    "sg:postcode":"94403",
    "sg:province":"CA",
    "sg:tags":[
        "music"
    ],
    "wof:name":"Entertainment",
    "wof:placetype":"venue"
},
  "geometry": {"coordinates":[-122.292311,37.535578],"type":"Point"}
}