{
  "type": "Feature",
  "properties": {
    "addr:full":"945 Whitley Ave Corcoran CA 93212",
    "addr:housenumber":"945",
    "addr:postcode":"93212",
    "addr:street":"Whitley Ave",
    "iso:country":"US",
    "sg:address":"945 Whitley Ave",
    "sg:city":"Corcoran",
    "sg:classifiers":[
        {
            "category":"Personal",
            "subcategory":"Barber",
            "type":"Services"
        }
    ],
    "sg:phone":"+1 559 992 2793",
    "sg:postcode":"93212",
    "sg:province":"CA",
    "wof:name":"Ernie's Barber Shop",
    "wof:placetype":"venue"
},
  "geometry": {"coordinates":[-119.559224,36.097961],"type":"Point"}
}