{
  "type": "Feature",
  "properties": {
    "addr:full":"26339 Stanwood Ave Hayward CA 94544",
    "addr:postcode":"26339;94544",
    "addr:street":"Stanwood Ave",
    "iso:country":"US",
    "sg:address":"26339 Stanwood Ave",
    "sg:city":"Hayward",
    "sg:classifiers":[
        {
            "category":"Shopping",
            "subcategory":"Crafts & Fabrics",
            "type":"Retail Goods"
        }
    ],
    "sg:phone":"+1 510 887 4280",
    "sg:postcode":"94544",
    "sg:province":"CA",
    "sg:tags":[
        "sewing"
    ],
    "wof:name":"Keep U In Stitches",
    "wof:placetype":"venue"
},
  "geometry": {"coordinates":[-122.085217,37.641533],"type":"Point"}
}