{
  "type": "Feature",
  "properties": {
    "iso:country":"US",
    "sg:address":"1224 Fernot Way",
    "sg:city":"Hanford",
    "sg:classifiers":[
        {
            "category":"Real Estate",
            "subcategory":"Real Estate Operator",
            "type":"Services"
        }
    ],
    "sg:phone":"+1 559 584 4498",
    "sg:postcode":"93230",
    "sg:province":"CA",
    "sg:tags":[
        "apartment"
    ],
    "wof:name":"Kings Garden 236 Apartments",
    "wof:placetype":"venue"
},
  "geometry": {"coordinates":[-119.626501,36.337688],"type":"Point"}
}