{
  "type": "Feature",
  "properties": {
    "addr:full":"6320 Canoga Ave Woodland Hills CA 91367",
    "addr:housenumber":"6320",
    "addr:postcode":"91367",
    "addr:street":"Canoga Ave",
    "iso:country":"US",
    "sg:address":"6320 Canoga Ave",
    "sg:city":"Woodland Hills",
    "sg:classifiers":[
        {
            "category":"Retail",
            "subcategory":"Car Wash",
            "type":"Services"
        },
        {
            "category":"Retail",
            "subcategory":"Auto Repair",
            "type":"Services"
        }
    ],
    "sg:phone":"+1 818 883 8300",
    "sg:postcode":"91367",
    "sg:province":"CA",
    "sg:tags":[
        "detailing"
    ],
    "wof:name":"Aztec Auto Detailing",
    "wof:placetype":"venue"
},
  "geometry": {"coordinates":[-118.597364,34.185596],"type":"Point"}
}