{
  "type": "Feature",
  "properties": {
    "iso:country":"US",
    "sg:address":"1043 Grand Ave",
    "sg:city":"San Marcos",
    "sg:classifiers":[
        {
            "category":"Manufacturing",
            "subcategory":"Metals",
            "type":"Manufacturing & Wholesale Goods"
        }
    ],
    "sg:phone":"+1 760 752 9825",
    "sg:postcode":"92069",
    "sg:province":"CA",
    "sg:tags":[
        "polishing"
    ],
    "wof:name":"San Marcos Polishing",
    "wof:placetype":"venue"
},
  "geometry": {"coordinates":[-117.18738999999999,33.141319],"type":"Point"}
}