{
  "type": "Feature",
  "properties": {
    "addr:full":"3301 E Main St Ste 2212 Ventura CA 93003",
    "addr:housenumber":"3301",
    "addr:postcode":"93003",
    "addr:street":"E Main St Ste 2212",
    "iso:country":"US",
    "sg:address":"3301 E Main St Ste 2212",
    "sg:city":"Ventura",
    "sg:classifiers":[
        {
            "category":"Shopping",
            "subcategory":"Clothing, Apparel, & Fashions",
            "type":"Retail Goods"
        }
    ],
    "sg:phone":"+1 805 650 1510",
    "sg:postcode":"93003",
    "sg:province":"CA",
    "sg:tags":[
        "apparel",
        "racing",
        "sportswear",
        "merchandise"
    ],
    "wof:name":"Athletico",
    "wof:placetype":"venue"
},
  "geometry": {"coordinates":[-119.249903,34.266915],"type":"Point"}
}