{
  "type": "Feature",
  "properties": {
    "addr:full":"211 Owens Peak St Inyokern CA 93527",
    "addr:housenumber":"211",
    "addr:postcode":"93527",
    "addr:street":"Owens Peak St",
    "iso:country":"US",
    "sg:address":"211 Owens Peak St",
    "sg:city":"Inyokern",
    "sg:classifiers":[
        {
            "category":"Shopping",
            "type":"Retail Goods"
        }
    ],
    "sg:phone":"+1 760 377 4922",
    "sg:postcode":"93527",
    "sg:province":"CA",
    "sg:tags":[
        "pet",
        "food",
        "supply"
    ],
    "wof:name":"Grey Feather Ranch",
    "wof:placetype":"venue"
},
  "geometry": {"coordinates":[-117.81212600000001,35.624356],"type":"Point"}
}