{
  "type": "Feature",
  "properties": {
    "iso:country":"US",
    "sg:address":"1401 Airport Dr",
    "sg:city":"Bakersfield",
    "sg:classifiers":[
        {
            "category":"Professional",
            "subcategory":"Computer Services",
            "type":"Services"
        }
    ],
    "sg:phone":"+1 661 391 8126",
    "sg:postcode":"93308",
    "sg:province":"CA",
    "sg:tags":[
        "consultant",
        "designer"
    ],
    "wof:name":"Iknowtechnology Inc",
    "wof:placetype":"venue"
},
  "geometry": {"coordinates":[-119.039061,35.419389],"type":"Point"}
}