{
  "type": "Feature",
  "properties": {
    "addr:full":"19909 Vanowen St Canoga Park CA 91306",
    "addr:housenumber":"19909",
    "addr:postcode":"91306",
    "addr:street":"Vanowen St",
    "iso:country":"US",
    "sg:address":"19909 Vanowen St",
    "sg:city":"Canoga Park",
    "sg:classifiers":[
        {
            "category":"Building & Trades",
            "subcategory":"Construction",
            "type":"Services"
        }
    ],
    "sg:phone":"+1 818 347 0900",
    "sg:postcode":"91306",
    "sg:province":"CA",
    "sg:tags":[
        "concrete",
        "contractor"
    ],
    "wof:name":"Jorge Serrano Custom Concrete",
    "wof:placetype":"venue"
},
  "geometry": {"coordinates":[-118.567452,34.193884],"type":"Point"}
}