{
  "type": "Feature",
  "properties": {
    "addr:full":"18400 Pioneer Blvd Artesia CA 90701",
    "addr:housenumber":"18400",
    "addr:postcode":"90701",
    "addr:street":"Pioneer Blvd",
    "iso:country":"US",
    "sg:address":"18400 Pioneer Blvd",
    "sg:city":"Artesia",
    "sg:classifiers":[
        {
            "category":"Building & Trades",
            "subcategory":"Cleaning & Sanitation",
            "type":"Services"
        }
    ],
    "sg:phone":"+1 562 402 6000",
    "sg:postcode":"90701",
    "sg:province":"CA",
    "sg:tags":[
        "carpet"
    ],
    "sg:website":"www.chemdry.com",
    "wof:name":"Chem-Dry Clean Masters",
    "wof:placetype":"venue"
},
  "geometry": {"coordinates":[-118.202144,33.864632],"type":"Point"}
}