{
  "type": "Feature",
  "properties": {
    "addr:full":"1604 Newton Avenue San Diego CA 92113",
    "addr:housenumber":"1604",
    "addr:postcode":"92113",
    "addr:street":"Newton Avenue",
    "iso:country":"US",
    "sg:address":"1604 Newton Avenue",
    "sg:city":"San Diego",
    "sg:classifiers":[
        {
            "category":"Autos & Motor Vehicles",
            "subcategory":"Automobile Sales",
            "type":"Retail Goods"
        }
    ],
    "sg:phone":"+1 619 239 8080",
    "sg:postcode":"92113",
    "sg:province":"CA",
    "sg:tags":[
        "limo"
    ],
    "wof:name":"Cinderella Carriage Company",
    "wof:placetype":"venue"
},
  "geometry": {"coordinates":[-117.150752,32.703109],"type":"Point"}
}