{
  "type": "Feature",
  "properties": {
    "addr:full":"96 W Foothill Blvd Upland CA 91786",
    "addr:housenumber":"96",
    "addr:postcode":"91786",
    "addr:street":"W Foothill Blvd",
    "iso:country":"US",
    "sg:address":"96 W Foothill Blvd",
    "sg:city":"Upland",
    "sg:classifiers":[
        {
            "category":"Shopping",
            "type":"Retail Goods"
        }
    ],
    "sg:phone":"+1 909 981 5734",
    "sg:postcode":"91786",
    "sg:province":"CA",
    "sg:tags":[
        "cosmetic",
        "perfume"
    ],
    "wof:name":"Beauti Control Cosmetics Inc",
    "wof:placetype":"venue"
},
  "geometry": {"coordinates":[-117.65395700000001,34.106924],"type":"Point"}
}