{
  "type": "Feature",
  "properties": {
    "addr:full":"588 S Brea Blvd Brea CA 92821",
    "addr:housenumber":"588",
    "addr:postcode":"92821",
    "addr:street":"S Brea Blvd",
    "iso:country":"US",
    "sg:address":"588 S Brea Blvd",
    "sg:city":"Brea",
    "sg:classifiers":[
        {
            "category":"Personal",
            "subcategory":"Beauty Salon",
            "type":"Services"
        },
        {
            "category":"Personal",
            "subcategory":"Skin Care",
            "type":"Services"
        }
    ],
    "sg:phone":"+1 714 671 1921",
    "sg:postcode":"92821",
    "sg:province":"CA",
    "wof:name":"Salon Sonal",
    "wof:placetype":"venue"
},
  "geometry": {"coordinates":[-117.903006,33.911614],"type":"Point"}
}