{
  "type": "Feature",
  "properties": {
    "addr:full":"1147 Doon Ct Sunnyvale CA 94087",
    "addr:housenumber":"1147",
    "addr:postcode":"94087",
    "addr:street":"Doon Ct",
    "iso:country":"US",
    "sg:address":"1147 Doon Ct",
    "sg:city":"Sunnyvale",
    "sg:classifiers":[
        {
            "category":"Building & Trades",
            "subcategory":"Construction",
            "type":"Services"
        }
    ],
    "sg:phone":"+1 408 247 8006",
    "sg:postcode":"94087",
    "sg:province":"CA",
    "sg:tags":[
        "system",
        "contractor",
        "air conditioning"
    ],
    "wof:name":"Laura A Rebholtz",
    "wof:placetype":"venue"
},
  "geometry": {"coordinates":[-122.000884,37.346001],"type":"Point"}
}