{
  "type": "Feature",
  "properties": {
    "addr:full":"1735 N 1st St San Jose CA 95112",
    "addr:housenumber":"1735",
    "addr:postcode":"95112",
    "addr:street":"N 1St St",
    "iso:country":"US",
    "sg:address":"1735 N 1st St",
    "sg:city":"San Jose",
    "sg:classifiers":[
        {
            "category":"Manufacturing",
            "subcategory":"Printing",
            "type":"Manufacturing & Wholesale Goods"
        }
    ],
    "sg:phone":"+1 408 387 0083",
    "sg:postcode":"95112",
    "sg:province":"CA",
    "sg:tags":[
        "publisher",
        "software"
    ],
    "wof:name":"Aankhen Inc",
    "wof:placetype":"venue"
},
  "geometry": {"coordinates":[-121.915457,37.369473],"type":"Point"}
}