{
  "type": "Feature",
  "properties": {
    "iso:country":"US",
    "sg:address":"59 Shrine Dr",
    "sg:city":"Sacramento",
    "sg:classifiers":[
        {
            "category":"Shopping",
            "subcategory":"Gifts & Souvenirs",
            "type":"Retail Goods"
        }
    ],
    "sg:phone":"+1 916 369 0697",
    "sg:postcode":"95827",
    "sg:province":"CA",
    "wof:name":"Marks Special Gifts",
    "wof:placetype":"venue"
},
  "geometry": {"coordinates":[-121.31688,38.578612],"type":"Point"}
}