{
  "type": "Feature",
  "properties": {
    "iso:country":"US",
    "sg:address":"1575 el Cerrito Dr",
    "sg:city":"Red Bluff",
    "sg:classifiers":[
        {
            "category":"Social Services",
            "subcategory":"Child Care",
            "type":"Services"
        }
    ],
    "sg:phone":"+1 530 527 1940",
    "sg:postcode":"96080",
    "sg:province":"CA",
    "wof:name":"Rhonda's Lil Rascals",
    "wof:placetype":"venue"
},
  "geometry": {"coordinates":[-122.24915300000001,40.165458],"type":"Point"}
}