{
  "type": "Feature",
  "properties": {
    "addr:full":"1258 E 123rd St Los Angeles CA 90059",
    "addr:housenumber":"1258",
    "addr:postcode":"90059",
    "addr:street":"E 123Rd St",
    "iso:country":"US",
    "sg:address":"1258 E 123rd St",
    "sg:city":"Los Angeles",
    "sg:classifiers":[
        {
            "category":"Manufacturing",
            "subcategory":"Textiles",
            "type":"Manufacturing & Wholesale Goods"
        }
    ],
    "sg:phone":"+1 310 603 1320",
    "sg:postcode":"90059",
    "sg:province":"CA",
    "sg:tags":[
        "towel",
        "mfg"
    ],
    "wof:name":"Soft & Luxurious Inc",
    "wof:placetype":"venue"
},
  "geometry": {"coordinates":[-118.252077,33.920426],"type":"Point"}
}