{
  "type": "Feature",
  "properties": {
    "addr:full":"610 W Market St San Diego CA 92101",
    "addr:housenumber":"610",
    "addr:postcode":"92101",
    "addr:street":"W Market St",
    "iso:country":"US",
    "sg:address":"610 W Market St",
    "sg:city":"San Diego",
    "sg:classifiers":[
        {
            "category":"Professional",
            "type":"Services"
        },
        {
            "category":"Restaurant",
            "type":"Food & Drink"
        }
    ],
    "sg:phone":"+1 619 365 4599",
    "sg:postcode":"92101",
    "sg:province":"CA",
    "sg:tags":[
        "barbeque",
        "caterer"
    ],
    "wof:name":"Kansas City Barbeque",
    "wof:placetype":"venue"
},
  "geometry": {"coordinates":[-117.168233,32.711234],"type":"Point"}
}