{
  "type": "Feature",
  "properties": {
    "addr:full":"939 10th St Modesto CA 95354",
    "addr:housenumber":"939",
    "addr:postcode":"ca 95354",
    "addr:street":"10Th St",
    "iso:country":"US",
    "sg:address":"939 10th St",
    "sg:city":"Modesto",
    "sg:classifiers":[
        {
            "category":"Shopping",
            "type":"Retail Goods"
        }
    ],
    "sg:phone":"+1 209 527 2912",
    "sg:postcode":"95354",
    "sg:province":"CA",
    "sg:tags":[
        "coin",
        "dealer",
        "supply"
    ],
    "wof:name":"Central Stamp & Coin Co",
    "wof:placetype":"venue"
},
  "geometry": {"coordinates":[-120.999387,37.639591],"type":"Point"}
}