{
  "type": "Feature",
  "properties": {
    "iso:country":"US",
    "sg:address":"7026 Sunrise Blvd",
    "sg:city":"Citrus Heights",
    "sg:classifiers":[
        {
            "category":"Shopping",
            "subcategory":"Tobacco",
            "type":"Retail Goods"
        }
    ],
    "sg:phone":"+1 916 729 3046",
    "sg:postcode":"95610",
    "sg:province":"CA",
    "sg:tags":[
        "shop"
    ],
    "wof:name":"Cigarettes and Gifts For Less",
    "wof:placetype":"venue"
},
  "geometry": {"coordinates":[-121.271004,38.6936],"type":"Point"}
}