{
  "type": "Feature",
  "properties": {
    "iso:country":"US",
    "sg:address":"312 Brookside Ave",
    "sg:city":"Redlands",
    "sg:classifiers":[
        {
            "category":"Professional",
            "subcategory":"Accounting & Tax Preparation",
            "type":"Services"
        }
    ],
    "sg:phone":"+1 909 793 8740",
    "sg:postcode":"92373",
    "sg:province":"CA",
    "sg:tags":[
        "bookkeeping",
        "general"
    ],
    "wof:name":"Kramer's Bookkeeping & Income",
    "wof:placetype":"venue"
},
  "geometry": {"coordinates":[-117.18812699999999,34.054112],"type":"Point"}
}