{
  "type": "Feature",
  "properties": {
    "addr:full":"4250 Morena Blvd San Diego CA 92110",
    "addr:housenumber":"4250",
    "addr:postcode":"92110",
    "addr:street":"Morena Blvd",
    "iso:country":"US",
    "sg:address":"4250 Morena Blvd",
    "sg:city":"San Diego",
    "sg:classifiers":[
        {
            "category":"Wholesale",
            "subcategory":"Furniture",
            "type":"Manufacturing & Wholesale Goods"
        }
    ],
    "sg:phone":"+1 858 272 7877",
    "sg:postcode":"92110",
    "sg:province":"CA",
    "wof:name":"Panasonic Chairs",
    "wof:placetype":"venue"
},
  "geometry": {"coordinates":[-117.220902,32.816673],"type":"Point"}
}