{
  "type": "Feature",
  "properties": {
    "addr:full":"400 W Alameda Ave Burbank CA 91506",
    "addr:housenumber":"400",
    "addr:postcode":"91506",
    "addr:street":"W Alameda Ave",
    "iso:country":"US",
    "sg:address":"400 W Alameda Ave",
    "sg:city":"Burbank",
    "sg:classifiers":[
        {
            "category":"Arts & Performance",
            "subcategory":"Theater",
            "type":"Entertainment"
        }
    ],
    "sg:phone":"+1 818 787 3937",
    "sg:postcode":"91506",
    "sg:province":"CA",
    "sg:tags":[
        "including",
        "television",
        "program",
        "commercial",
        "producer"
    ],
    "wof:name":"Producer Dept",
    "wof:placetype":"venue"
},
  "geometry": {"coordinates":[-118.311724,34.163691],"type":"Point"}
}