{
  "type": "Feature",
  "properties": {
    "iso:country":"US",
    "sg:address":"11225 Trade Center Drive",
    "sg:city":"Rancho Cordova",
    "sg:classifiers":[
        {
            "category":"Professional",
            "subcategory":"Printing & Photocopies",
            "type":"Services"
        }
    ],
    "sg:phone":"+1 916 631 7612",
    "sg:postcode":"95742",
    "sg:province":"CA",
    "sg:website":"www.copycentral.com",
    "wof:name":"Copy Central",
    "wof:placetype":"venue"
},
  "geometry": {"coordinates":[-121.26706,38.60434],"type":"Point"}
}