{
  "type": "Feature",
  "properties": {
    "addr:full":"416 Unknown Ave San Diego CA 92101",
    "addr:housenumber":"416",
    "addr:postcode":"92101",
    "addr:street":"Unknown Ave",
    "iso:country":"US",
    "sg:address":"416 Unknown Ave",
    "sg:city":"San Diego",
    "sg:classifiers":[
        {
            "category":"Restaurant",
            "type":"Food & Drink"
        }
    ],
    "sg:menulink":"http://www.allmenus.com/ca/san-diego/43621-candelas-restaurant/menu/",
    "sg:phone":"+1 619 702 4455",
    "sg:postcode":"92101",
    "sg:province":"CA",
    "sg:tags":[
        "mexican"
    ],
    "wof:name":"Candela's Restaurant",
    "wof:placetype":"venue"
},
  "geometry": {"coordinates":[-117.161923,32.709546],"type":"Point"}
}