{
  "type": "Feature",
  "properties": {
    "iso:country":"US",
    "sg:address":"1587 El Camino Real",
    "sg:city":"Millbrae",
    "sg:classifiers":[
        {
            "category":"Retail",
            "subcategory":"Auto Repair",
            "type":"Services"
        }
    ],
    "sg:phone":"+1 650 872 2354",
    "sg:postcode":"94030",
    "sg:province":"CA",
    "sg:tags":[
        "scooters-repairing",
        "motorcycle",
        "motor"
    ],
    "sg:website":"www.norcal-cycles.com",
    "wof:name":"NorCal Cycles",
    "wof:placetype":"venue"
},
  "geometry": {"coordinates":[-122.40341600000001,37.612248],"type":"Point"}
}