{
  "type": "Feature",
  "properties": {
    "iso:country":"US",
    "sg:address":"5385 Camden Ave.",
    "sg:city":"San Jose",
    "sg:classifiers":[
        {
            "category":"Restaurant",
            "type":"Food & Drink"
        }
    ],
    "sg:phone":"+1 408 267 9600",
    "sg:postcode":"95124",
    "sg:province":"CA",
    "sg:website":"www.roundtablepizza.com/",
    "wof:name":"Round Table Pizza",
    "wof:placetype":"venue"
},
  "geometry": {"coordinates":[-121.90458599999999,37.241023],"type":"Point"}
}