{
  "type": "Feature",
  "properties": {
    "iso:country":"US",
    "sg:address":"18906 Roscoe Blvd",
    "sg:city":"Northridge",
    "sg:classifiers":[
        {
            "category":"Personal",
            "subcategory":"Beauty Salon",
            "type":"Services"
        }
    ],
    "sg:phone":"+1 818 718 9220",
    "sg:postcode":"91324",
    "sg:province":"CA",
    "wof:name":"Hair 2000",
    "wof:placetype":"venue"
},
  "geometry": {"coordinates":[-118.545441,34.220586],"type":"Point"}
}