{
  "type": "Feature",
  "properties": {
    "addr:full":"2675 S Willow Ave Bloomington CA 92316",
    "addr:housenumber":"2675",
    "addr:postcode":"92316",
    "addr:street":"S Willow Ave",
    "iso:country":"US",
    "sg:address":"2675 S Willow Ave",
    "sg:city":"Bloomington",
    "sg:classifiers":[
        {
            "category":"Building & Trades",
            "subcategory":"Equipment Rental",
            "type":"Services"
        }
    ],
    "sg:phone":"+1 909 820 9886",
    "sg:postcode":"92316",
    "sg:province":"CA",
    "sg:tags":[
        "cranes-renting",
        "forklift",
        "leasing",
        "trucks-rental",
        "contractors'"
    ],
    "wof:name":"Hill Crane Service Inc",
    "wof:placetype":"venue"
},
  "geometry": {"coordinates":[-117.374579,34.051441],"type":"Point"}
}