{
  "type": "Feature",
  "properties": {
    "addr:full":"53 Trish Dr Novato CA 94947",
    "addr:housenumber":"53",
    "addr:postcode":"94947",
    "addr:street":"Trish Dr",
    "iso:country":"US",
    "sg:address":"53 Trish Dr",
    "sg:city":"Novato",
    "sg:classifiers":[
        {
            "category":"Manufacturing",
            "subcategory":"Buildings",
            "type":"Manufacturing & Wholesale Goods"
        },
        {
            "category":"Building & Trades",
            "subcategory":"Construction",
            "type":"Services"
        }
    ],
    "sg:phone":"+1 415 892 8030",
    "sg:postcode":"94947",
    "sg:province":"CA",
    "sg:tags":[
        "repair",
        "altering",
        "builder",
        "preservation",
        "contractor",
        "restoration",
        "maintenance",
        "home",
        "remodeling"
    ],
    "wof:name":"Scheiner Construction",
    "wof:placetype":"venue"
},
  "geometry": {"coordinates":[-122.616285,38.112576],"type":"Point"}
}