{
  "type": "Feature",
  "properties": {
    "addr:full":"26330 Diamond Pl Ste 110 Santa Clarita CA 91350",
    "addr:housenumber":"26330",
    "addr:postcode":"91350",
    "addr:street":"Diamond Pl Ste 110",
    "iso:country":"US",
    "sg:address":"26330 Diamond Pl Ste 110",
    "sg:city":"Santa Clarita",
    "sg:classifiers":[
        {
            "category":"Sports & Exercise",
            "subcategory":"Gym",
            "type":"Entertainment"
        }
    ],
    "sg:phone":"+1 661 257 9955",
    "sg:postcode":"91350",
    "sg:province":"CA",
    "sg:tags":[
        "trainer",
        "yoga"
    ],
    "sg:website":"hotyogavalencia.com",
    "wof:name":"Hot Yoga Health & Wellness Center",
    "wof:placetype":"venue"
},
  "geometry": {"coordinates":[-118.507503,34.409518],"type":"Point"}
}