{
  "type": "Feature",
  "properties": {
    "addr:full":"1054 W Ave K Lancaster CA 93534",
    "addr:housenumber":"1054",
    "addr:postcode":"93534",
    "addr:street":"W Ave K",
    "iso:country":"US",
    "sg:address":"1054 W Ave K",
    "sg:city":"Lancaster",
    "sg:classifiers":[
        {
            "category":"Wholesale",
            "subcategory":"Machinery & Supplies",
            "type":"Manufacturing & Wholesale Goods"
        }
    ],
    "sg:phone":"+1 661 723 3884",
    "sg:postcode":"93534",
    "sg:province":"CA",
    "sg:tags":[
        "equipment",
        "salon",
        "establishment",
        "beauty"
    ],
    "wof:name":"Hair Country Beauty Supply",
    "wof:placetype":"venue"
},
  "geometry": {"coordinates":[-118.149035,34.674794],"type":"Point"}
}