{
  "type": "Feature",
  "properties": {
    "iso:country":"US",
    "sg:address":"8943 Atlanta Ave",
    "sg:city":"Huntington Beach",
    "sg:classifiers":[
        {
            "category":"Cinema",
            "subcategory":"Movie Rental",
            "type":"Entertainment"
        }
    ],
    "sg:phone":"+1 714 960 2175",
    "sg:postcode":"92646",
    "sg:province":"CA",
    "sg:tags":[
        "game",
        "video"
    ],
    "wof:name":"Gamestop",
    "wof:placetype":"venue"
},
  "geometry": {"coordinates":[-117.97199999999999,33.657799],"type":"Point"}
}