{
  "type": "Feature",
  "properties": {
    "addr:full":"1530 E Shaw Ave Fresno CA 93710",
    "addr:housenumber":"1530",
    "addr:postcode":"93710",
    "addr:street":"E Shaw Ave",
    "iso:country":"US",
    "sg:address":"1530 E Shaw Ave",
    "sg:city":"Fresno",
    "sg:classifiers":[
        {
            "category":"Professional",
            "subcategory":"Lawyer & Legal Services",
            "type":"Services"
        }
    ],
    "sg:phone":"+1 559 227 7200",
    "sg:postcode":"93710",
    "sg:province":"CA",
    "sg:tags":[
        "attorney"
    ],
    "wof:name":"Steven M Mc Clean",
    "wof:placetype":"venue"
},
  "geometry": {"coordinates":[-119.760345,36.808665],"type":"Point"}
}