{
  "type": "Feature",
  "properties": {
    "iso:country":"US",
    "sg:address":"508 Sacramento St",
    "sg:city":"Vallejo",
    "sg:classifiers":[
        {
            "category":"Personal",
            "subcategory":"Beauty Salon",
            "type":"Services"
        }
    ],
    "sg:phone":"+1 707 642 5641",
    "sg:postcode":"94590",
    "sg:province":"CA",
    "wof:name":"Rita Mimick",
    "wof:placetype":"venue"
},
  "geometry": {"coordinates":[-122.25822100000001,38.101558],"type":"Point"}
}