{
  "type": "Feature",
  "properties": {
    "iso:country":"US",
    "sg:address":"272 N el Camino Real",
    "sg:city":"Encinitas",
    "sg:classifiers":[
        {
            "category":"Retail",
            "subcategory":"Photofinishing",
            "type":"Services"
        }
    ],
    "sg:phone":"+1 760 436 7781",
    "sg:postcode":"92024",
    "sg:province":"CA",
    "sg:tags":[
        "photo",
        "finishing"
    ],
    "wof:name":"Pixel Photo",
    "wof:placetype":"venue"
},
  "geometry": {"coordinates":[-117.260076,33.049362],"type":"Point"}
}