{
  "type": "Feature",
  "properties": {
    "iso:country":"US",
    "sg:address":"3801 W Burbank Blvd",
    "sg:city":"Burbank",
    "sg:classifiers":[
        {
            "category":"Building & Trades",
            "subcategory":"Cleaning & Sanitation",
            "type":"Services"
        }
    ],
    "sg:phone":"+1 818 369 1746",
    "sg:postcode":"91505",
    "sg:province":"CA",
    "sg:tags":[
        "carpet"
    ],
    "wof:name":"Laguna Hills Carpet Care",
    "wof:placetype":"venue"
},
  "geometry": {"coordinates":[-118.351561,34.17444],"type":"Point"}
}