{
  "type": "Feature",
  "properties": {
    "iso:country":"US",
    "sg:address":"130 N Brand Blvd Ste 301",
    "sg:city":"Glendale",
    "sg:classifiers":[
        {
            "category":"Banks & Credit Unions",
            "subcategory":"Financial Services",
            "type":"Services"
        }
    ],
    "sg:phone":"+1 818 551 1229",
    "sg:postcode":"91203",
    "sg:province":"CA",
    "sg:tags":[
        "broker",
        "mortgage"
    ],
    "wof:name":"Loan Closer",
    "wof:placetype":"venue"
},
  "geometry": {"coordinates":[-118.254997,34.146801],"type":"Point"}
}