{
  "type": "Feature",
  "properties": {
    "iso:country":"US",
    "sg:address":"1926 S Pacific Coast Hwy",
    "sg:city":"Redondo Beach",
    "sg:classifiers":[
        {
            "category":"Building & Trades",
            "subcategory":"Construction",
            "type":"Services"
        }
    ],
    "sg:phone":"+1 310 376 5809",
    "sg:postcode":"90277",
    "sg:province":"CA",
    "sg:tags":[
        "resurfacing",
        "laying",
        "refinishing",
        "floor"
    ],
    "wof:name":"Assured Quality Woodcraft",
    "wof:placetype":"venue"
},
  "geometry": {"coordinates":[-118.37571,33.815809],"type":"Point"}
}