{
  "type": "Feature",
  "properties": {
    "addr:full":"3220 51st Ave Sacramento CA 95823",
    "addr:housenumber":"3220",
    "addr:postcode":"95823",
    "addr:street":"51St Ave",
    "iso:country":"US",
    "sg:address":"3220 51st Ave",
    "sg:city":"Sacramento",
    "sg:classifiers":[
        {
            "category":"Home & Garden",
            "subcategory":"Building Materials",
            "type":"Retail Goods"
        }
    ],
    "sg:phone":"+1 916 428 8428",
    "sg:postcode":"95823",
    "sg:province":"CA",
    "sg:tags":[
        "door"
    ],
    "wof:name":"General Glass & Door Svc",
    "wof:placetype":"venue"
},
  "geometry": {"coordinates":[-121.473007,38.504726],"type":"Point"}
}