{
  "type": "Feature",
  "properties": {
    "addr:full":"1919 S Burnside Ave Los Angeles CA 90016",
    "addr:housenumber":"1919",
    "addr:postcode":"90016",
    "addr:street":"S Burnside Ave",
    "iso:country":"US",
    "sg:address":"1919 S Burnside Ave",
    "sg:city":"Los Angeles",
    "sg:classifiers":[
        {
            "category":"Home & Garden",
            "subcategory":"Carpets & Floor Coverings",
            "type":"Retail Goods"
        }
    ],
    "sg:phone":"+1 323 931 4400",
    "sg:postcode":"90016",
    "sg:province":"CA",
    "sg:tags":[
        "dealer",
        "rug"
    ],
    "wof:name":"Washington Carpet Warehouse",
    "wof:placetype":"venue"
},
  "geometry": {"coordinates":[-118.35852800000001,34.037882],"type":"Point"}
}