{
  "type": "Feature",
  "properties": {
    "addr:full":"2650 18th St San Francisco CA 94110",
    "addr:housenumber":"2650",
    "addr:postcode":"94110",
    "addr:street":"18Th St",
    "iso:country":"US",
    "sg:address":"2650 18th St",
    "sg:city":"San Francisco",
    "sg:classifiers":[
        {
            "category":"Real Estate",
            "subcategory":"Real Estate Agent",
            "type":"Services"
        }
    ],
    "sg:phone":"+1 415 864 2929",
    "sg:postcode":"94110",
    "sg:province":"CA",
    "sg:tags":[
        "management"
    ],
    "wof:name":"Steve Themis Properties",
    "wof:placetype":"venue"
},
  "geometry": {"coordinates":[-122.408772,37.761922],"type":"Point"}
}