{
  "type": "Feature",
  "properties": {
    "addr:full":"4630 Santa Monica Ave San Diego CA 92107",
    "addr:housenumber":"4630",
    "addr:postcode":"92107",
    "addr:street":"Santa Monica Ave",
    "iso:country":"US",
    "sg:address":"4630 Santa Monica Ave",
    "sg:city":"San Diego",
    "sg:classifiers":[
        {
            "category":"Professional",
            "subcategory":"Computer Services",
            "type":"Services"
        }
    ],
    "sg:phone":"+1 619 696 9429",
    "sg:postcode":"92107",
    "sg:province":"CA",
    "sg:tags":[
        "repair"
    ],
    "wof:name":"Data Decisions Inc",
    "wof:placetype":"venue"
},
  "geometry": {"coordinates":[-117.24459,32.744241],"type":"Point"}
}