{
  "type": "Feature",
  "properties": {
    "addr:full":"6924 Canby Ave Reseda CA 91335",
    "addr:housenumber":"6924",
    "addr:postcode":"91335",
    "addr:street":"Canby Ave",
    "iso:country":"US",
    "sg:address":"6924 Canby Ave",
    "sg:city":"Reseda",
    "sg:classifiers":[
        {
            "category":"Communications",
            "subcategory":"Film & Video Production",
            "type":"Services"
        }
    ],
    "sg:phone":"+1 818 881 8110",
    "sg:postcode":"91335",
    "sg:province":"CA",
    "sg:tags":[
        "motion",
        "picture",
        "studio",
        "producer"
    ],
    "wof:name":"Em Gee Film Library",
    "wof:placetype":"venue"
},
  "geometry": {"coordinates":[-118.53465,34.195993],"type":"Point"}
}