{
  "type": "Feature",
  "properties": {
    "iso:country":"US",
    "sg:address":"1050 E Dominguez St Ste F",
    "sg:city":"Carson",
    "sg:classifiers":[
        {
            "category":"Food & Beverages",
            "subcategory":"Liquor & Beverages",
            "type":"Retail Goods"
        }
    ],
    "sg:phone":"+1 310 669 9589",
    "sg:postcode":"90746",
    "sg:province":"CA",
    "sg:tags":[
        "beer",
        "spirit",
        "wine"
    ],
    "wof:name":"Muhak Co LTD",
    "wof:placetype":"venue"
},
  "geometry": {"coordinates":[-118.256342,33.840309],"type":"Point"}
}