{
  "type": "Feature",
  "properties": {
    "addr:full":"2175 Stone Ave San Jose CA 95125",
    "addr:housenumber":"2175",
    "addr:postcode":"95125",
    "addr:street":"Stone Ave",
    "iso:country":"US",
    "sg:address":"2175 Stone Ave",
    "sg:city":"San Jose",
    "sg:classifiers":[
        {
            "category":"Building & Trades",
            "subcategory":"Construction",
            "type":"Services"
        }
    ],
    "sg:phone":"+1 408 920 0312",
    "sg:postcode":"95125",
    "sg:province":"CA",
    "sg:tags":[
        "painter"
    ],
    "wof:name":"R & R Specialties Co",
    "wof:placetype":"venue"
},
  "geometry": {"coordinates":[-121.87032600000001,37.299593],"type":"Point"}
}