{
  "type": "Feature",
  "properties": {
    "iso:country":"US",
    "sg:address":"6354 Nantucket Ct",
    "sg:city":"Chino",
    "sg:classifiers":[
        {
            "category":"Shopping",
            "subcategory":"Beauty & Cosmetics",
            "type":"Retail Goods"
        }
    ],
    "sg:phone":"+1 909 627 2331",
    "sg:postcode":"91710",
    "sg:province":"CA",
    "sg:tags":[
        "merchandise"
    ],
    "wof:name":"Fine Lines Permanent Cosmetics",
    "wof:placetype":"venue"
},
  "geometry": {"coordinates":[-117.666585,34.027099],"type":"Point"}
}