{
  "type": "Feature",
  "properties": {
    "addr:full":"2285 Newport Blvd Costa Mesa CA 92627",
    "addr:housenumber":"2285",
    "addr:postcode":"92627",
    "addr:street":"Newport Blvd Costa",
    "iso:country":"US",
    "sg:address":"2285 Newport Blvd",
    "sg:city":"Costa Mesa",
    "sg:classifiers":[
        {
            "category":"Retail",
            "subcategory":"Auto Repair",
            "type":"Services"
        }
    ],
    "sg:phone":"+1 949 646 7282",
    "sg:postcode":"92627",
    "sg:province":"CA",
    "sg:tags":[
        "repairing",
        "automobile"
    ],
    "wof:name":"All Car Svc Inc",
    "wof:placetype":"venue"
},
  "geometry": {"coordinates":[-117.906991,33.653392],"type":"Point"}
}