{
  "type": "Feature",
  "properties": {
    "iso:country":"US",
    "sg:address":"14168 Central Ave",
    "sg:city":"Chino",
    "sg:classifiers":[
        {
            "category":"Wholesale",
            "subcategory":"Hardware",
            "type":"Manufacturing & Wholesale Goods"
        }
    ],
    "sg:phone":"+1 909 590 1488",
    "sg:postcode":"91710",
    "sg:province":"CA",
    "sg:tags":[
        "tool"
    ],
    "wof:name":"Infinity Diamond Tools",
    "wof:placetype":"venue"
},
  "geometry": {"coordinates":[-117.689082,33.995835],"type":"Point"}
}