{
  "type": "Feature",
  "properties": {
    "addr:full":"6700 State Hwy 49 Lotus CA 95651",
    "addr:housenumber":"6700",
    "addr:postcode":"95651",
    "addr:street":"State Hwy 49",
    "iso:country":"US",
    "sg:address":"6700 State Hwy 49",
    "sg:city":"Lotus",
    "sg:classifiers":[
        {
            "category":"Ferry",
            "type":"Transportation"
        }
    ],
    "sg:phone":"+1 530 642 8189",
    "sg:postcode":"95651",
    "sg:province":"CA",
    "sg:tags":[
        "river",
        "trip"
    ],
    "wof:name":"Environmental Traveling",
    "wof:placetype":"venue"
},
  "geometry": {"coordinates":[-120.93078,38.819845],"type":"Point"}
}