{
  "type": "Feature",
  "properties": {
    "addr:full":"18831 Von Karman Ave. Suite 200 Irvine CA 92612",
    "addr:housenumber":"18831",
    "addr:postcode":"92612",
    "addr:street":"Von Karman Ave. Suite 200",
    "iso:country":"US",
    "sg:address":"18831 Von Karman Ave. Suite 200",
    "sg:city":"Irvine",
    "sg:classifiers":[
        {
            "category":"Professional",
            "subcategory":"Computer Services",
            "type":"Services"
        }
    ],
    "sg:phone":"+1 949 333 5111",
    "sg:postcode":"92612",
    "sg:province":"CA",
    "sg:website":"http://www.digmap.com/",
    "wof:name":"Digital Map Products",
    "wof:placetype":"venue"
},
  "geometry": {"coordinates":[-117.856568,33.672475],"type":"Point"}
}