{
  "type": "Feature",
  "properties": {
    "addr:full":"2294 Parkview Ln Chino Hills CA 91709",
    "addr:housenumber":"2294",
    "addr:postcode":"91709",
    "addr:street":"Parkview Ln",
    "iso:country":"US",
    "sg:address":"2294 Parkview Ln",
    "sg:city":"Chino Hills",
    "sg:classifiers":[
        {
            "category":"Professional",
            "type":"Services"
        }
    ],
    "sg:phone":"+1 909 517 3750",
    "sg:postcode":"91709",
    "sg:province":"CA",
    "wof:name":"Sunmexx International Inc",
    "wof:placetype":"venue"
},
  "geometry": {"coordinates":[-117.755576,33.994575],"type":"Point"}
}