{
  "type": "Feature",
  "properties": {
    "addr:full":"1005 Gravenstein Highway North Sebastopol CA 95472",
    "addr:housenumber":"1005",
    "addr:postcode":"95472",
    "addr:street":"Gravenstein Highway North",
    "iso:country":"US",
    "sg:address":"1005 Gravenstein Highway North",
    "sg:city":"Sebastopol",
    "sg:classifiers":[
        {
            "category":"Professional",
            "subcategory":"Advertising",
            "type":"Services"
        }
    ],
    "sg:phone":"+1 707 827 7000",
    "sg:postcode":"95472",
    "sg:province":"CA",
    "sg:website":"http://www.oreilly.com",
    "wof:name":"O'Reilly Media",
    "wof:placetype":"venue"
},
  "geometry": {"coordinates":[-122.842401,38.412105],"type":"Point"}
}