{
  "type": "Feature",
  "properties": {
    "addr:full":"346 Williams Ave San Francisco CA 94124",
    "addr:housenumber":"346",
    "addr:postcode":"94124",
    "addr:street":"Williams Ave",
    "iso:country":"US",
    "sg:address":"346 Williams Ave",
    "sg:city":"San Francisco",
    "sg:classifiers":[
        {
            "category":"Building & Trades",
            "subcategory":"Construction",
            "type":"Services"
        }
    ],
    "sg:phone":"+1 415 386 6797",
    "sg:postcode":"94124",
    "sg:province":"CA",
    "sg:tags":[
        "roofing",
        "contractor"
    ],
    "wof:name":"Lam's Roofing Co",
    "wof:placetype":"venue"
},
  "geometry": {"coordinates":[-122.39952,37.730306],"type":"Point"}
}