{
  "type": "Feature",
  "properties": {
    "iso:country":"US",
    "sg:address":"115 Fortune Dr",
    "sg:city":"Irvine",
    "sg:classifiers":[
        {
            "category":"Food & Beverages",
            "subcategory":"Groceries & Convenience Stores",
            "type":"Retail Goods"
        }
    ],
    "sg:phone":"+1 949 885 0114",
    "sg:postcode":"92618",
    "sg:province":"CA",
    "sg:website":"www.target.com",
    "wof:name":"Pizza Hut Express",
    "wof:placetype":"venue"
},
  "geometry": {"coordinates":[-117.744907,33.648883],"type":"Point"}
}