{
  "type": "Feature",
  "properties": {
    "iso:country":"US",
    "sg:address":"1800 W Beverly Blvd",
    "sg:city":"Montebello",
    "sg:classifiers":[
        {
            "category":"Professional",
            "subcategory":"Lawyer & Legal Services",
            "type":"Services"
        }
    ],
    "sg:phone":"+1 323 721 8520",
    "sg:postcode":"90640",
    "sg:province":"CA",
    "sg:tags":[
        "attorney"
    ],
    "wof:name":"Marilu Moreno Schlicht Law Ofc",
    "wof:placetype":"venue"
},
  "geometry": {"coordinates":[-118.11917099999999,34.019914],"type":"Point"}
}