{
  "type": "Feature",
  "properties": {
    "addr:full":"1018 Seascape Cir Rodeo CA 94572",
    "addr:housenumber":"1018",
    "addr:postcode":"94572",
    "addr:street":"Seascape Cir",
    "iso:country":"US",
    "sg:address":"1018 Seascape Cir",
    "sg:city":"Rodeo",
    "sg:classifiers":[
        {
            "category":"Professional",
            "type":"Services"
        },
        {
            "category":"Arts & Performance",
            "subcategory":"Music",
            "type":"Entertainment"
        }
    ],
    "sg:phone":"+1 510 799 3083",
    "sg:postcode":"94572",
    "sg:province":"CA",
    "sg:tags":[
        "record",
        "producer",
        "label"
    ],
    "wof:name":"Khalsa Enterprise",
    "wof:placetype":"venue"
},
  "geometry": {"coordinates":[-122.25671699999999,38.026736],"type":"Point"}
}