{
  "type": "Feature",
  "properties": {
    "addr:full":"1410 el Paseo de Saratoga San Jose CA 95130",
    "addr:housenumber":"1410",
    "addr:postcode":"95130",
    "addr:street":"El Paseo De Saratoga",
    "iso:country":"US",
    "sg:address":"1410 el Paseo de Saratoga",
    "sg:city":"San Jose",
    "sg:classifiers":[
        {
            "category":"Retail",
            "subcategory":"Photofinishing",
            "type":"Services"
        }
    ],
    "sg:phone":"+1 408 871 1944",
    "sg:postcode":"95130",
    "sg:province":"CA",
    "sg:tags":[
        "photo",
        "finishing"
    ],
    "wof:name":"Wolf Camera & Video",
    "wof:placetype":"venue"
},
  "geometry": {"coordinates":[-121.99044499999999,37.289506],"type":"Point"}
}