{
  "type": "Feature",
  "properties": {
    "addr:full":"350 Berry Rd Watsonville CA 95076",
    "addr:housenumber":"350",
    "addr:postcode":"95076",
    "addr:street":"Berry Rd",
    "iso:country":"US",
    "sg:address":"350 Berry Rd",
    "sg:city":"Watsonville",
    "sg:classifiers":[
        {
            "category":"Freight",
            "type":"Transportation"
        }
    ],
    "sg:phone":"+1 831 728 5550",
    "sg:postcode":"95076",
    "sg:province":"CA",
    "sg:tags":[
        "trucking"
    ],
    "wof:name":"E Duenas Trucking",
    "wof:placetype":"venue"
},
  "geometry": {"coordinates":[-121.738771,36.863188],"type":"Point"}
}