{
  "type": "Feature",
  "properties": {
    "iso:country":"US",
    "sg:address":"7 Washington Ave",
    "sg:city":"San Rafael",
    "sg:classifiers":[
        {
            "category":"Health Services",
            "subcategory":"Hospital",
            "type":"Services"
        }
    ],
    "sg:phone":"+1 415 491 4711",
    "sg:postcode":"94903",
    "sg:province":"CA",
    "sg:tags":[
        "mental"
    ],
    "wof:name":"Lakeside House",
    "wof:placetype":"venue"
},
  "geometry": {"coordinates":[-122.526045,37.998776],"type":"Point"}
}