{
  "type": "Feature",
  "properties": {
    "iso:country":"US",
    "sg:address":"121 Torrance Blvd",
    "sg:city":"Redondo Beach",
    "sg:classifiers":[
        {
            "category":"Wholesale",
            "subcategory":"Home Furnishings",
            "type":"Manufacturing & Wholesale Goods"
        }
    ],
    "sg:phone":"+1 310 379 6688",
    "sg:postcode":"90277",
    "sg:province":"CA",
    "sg:tags":[
        "tile"
    ],
    "wof:name":"Materials Marketing",
    "wof:placetype":"venue"
},
  "geometry": {"coordinates":[-118.387595,33.838316],"type":"Point"}
}