{
  "type": "Feature",
  "properties": {
    "addr:full":"2505 E 7th St Long Beach CA 90804",
    "addr:housenumber":"2505",
    "addr:postcode":"90804",
    "addr:street":"E 7Th St",
    "iso:country":"US",
    "sg:address":"2505 E 7th St",
    "sg:city":"Long Beach",
    "sg:classifiers":[
        {
            "category":"Insurance",
            "subcategory":"Insurance Agent",
            "type":"Services"
        }
    ],
    "sg:phone":"+1 562 438 5118",
    "sg:postcode":"90804",
    "sg:province":"CA",
    "wof:name":"Coleman Insurance",
    "wof:placetype":"venue"
},
  "geometry": {"coordinates":[-118.161175,33.775412],"type":"Point"}
}