{
  "type": "Feature",
  "properties": {
    "iso:country":"US",
    "sg:address":"641 E Bonita Ave",
    "sg:city":"San Dimas",
    "sg:classifiers":[
        {
            "category":"Personal",
            "subcategory":"Barber",
            "type":"Services"
        }
    ],
    "sg:phone":"+1 909 599 3424",
    "sg:postcode":"91773",
    "sg:province":"CA",
    "wof:name":"Bonita's Barbers",
    "wof:placetype":"venue"
},
  "geometry": {"coordinates":[-117.794414,34.106586],"type":"Point"}
}