{
  "type": "Feature",
  "properties": {
    "iso:country":"US",
    "sg:address":"1428 Main St",
    "sg:city":"St Helena",
    "sg:classifiers":[
        {
            "category":"Shopping",
            "subcategory":"Clothing, Apparel, & Fashions",
            "type":"Retail Goods"
        }
    ],
    "sg:phone":"+1 707 963 3236",
    "sg:postcode":"94574",
    "sg:province":"CA",
    "wof:name":"Pearl",
    "wof:placetype":"venue"
},
  "geometry": {"coordinates":[-122.471526,38.506016],"type":"Point"}
}