{
  "type": "Feature",
  "properties": {
    "iso:country":"US",
    "sg:address":"3100 Imperial Hwy",
    "sg:city":"Lynwood",
    "sg:classifiers":[
        {
            "category":"Shopping",
            "subcategory":"Clothing, Apparel, & Fashions",
            "type":"Retail Goods"
        }
    ],
    "sg:phone":"+1 310 639 1370",
    "sg:postcode":"90262",
    "sg:province":"CA",
    "sg:tags":[
        "infant",
        "wear"
    ],
    "wof:name":"Son Bo Hyun",
    "wof:placetype":"venue"
},
  "geometry": {"coordinates":[-118.21160399999999,33.930513],"type":"Point"}
}