{
  "type": "Feature",
  "properties": {
    "iso:country":"US",
    "sg:address":"1403 S Coast Hwy",
    "sg:city":"Oceanside",
    "sg:classifiers":[
        {
            "category":"Manufacturing",
            "subcategory":"Apparel",
            "type":"Manufacturing & Wholesale Goods"
        }
    ],
    "sg:phone":"+1 760 450 0341",
    "sg:postcode":"92054",
    "sg:province":"CA",
    "sg:tags":[
        "sewing",
        "contractor"
    ],
    "wof:name":"Eclipse Apparel Manufacturing",
    "wof:placetype":"venue"
},
  "geometry": {"coordinates":[-117.367908,33.181921],"type":"Point"}
}