{
  "type": "Feature",
  "properties": {
    "iso:country":"US",
    "sg:address":"2532 White Rd",
    "sg:city":"Irvine",
    "sg:classifiers":[
        {
            "category":"Shopping",
            "subcategory":"Computers & Home Electronics",
            "type":"Retail Goods"
        }
    ],
    "sg:phone":"+1 949 852 1811",
    "sg:postcode":"92614",
    "sg:province":"CA",
    "sg:tags":[
        "equipment",
        "dealer"
    ],
    "wof:name":"Power Systems",
    "wof:placetype":"venue"
},
  "geometry": {"coordinates":[-117.842951,33.679728],"type":"Point"}
}