{
  "type": "Feature",
  "properties": {
    "addr:full":"8541 Cerritos Ave Stanton CA 90680",
    "addr:housenumber":"8541",
    "addr:postcode":"ca 90680",
    "addr:street":"Cerritos Ave",
    "iso:country":"US",
    "sg:address":"8541 Cerritos Ave",
    "sg:city":"Stanton",
    "sg:classifiers":[
        {
            "category":"Social Services",
            "subcategory":"Adult Care",
            "type":"Services"
        }
    ],
    "sg:phone":"+1 714 821 5780",
    "sg:postcode":"90680",
    "sg:province":"CA",
    "sg:tags":[
        "home",
        "residential"
    ],
    "wof:name":"New Horizon Lodge",
    "wof:placetype":"venue"
},
  "geometry": {"coordinates":[-117.984525,33.810241],"type":"Point"}
}