{
  "type": "Feature",
  "properties": {
    "iso:country":"US",
    "sg:address":"3000 Blackwell Dr",
    "sg:city":"Vista",
    "sg:classifiers":[
        {
            "category":"Farming",
            "subcategory":"Nursery",
            "type":"Manufacturing & Wholesale Goods"
        },
        {
            "category":"Shopping",
            "subcategory":"Crafts & Fabrics",
            "type":"Retail Goods"
        }
    ],
    "sg:phone":"+1 760 724 4535",
    "sg:postcode":"92084",
    "sg:province":"CA",
    "sg:tags":[
        "supply",
        "nursery-wholesale",
        "equipment",
        "grower",
        "florist",
        "growers'"
    ],
    "wof:name":"Vermeyen Nursery",
    "wof:placetype":"venue"
},
  "geometry": {"coordinates":[-117.232663,33.247913],"type":"Point"}
}