{
  "type": "Feature",
  "properties": {
    "addr:full":"1125 Grand Ave Grover Beach CA 93433",
    "addr:housenumber":"1125",
    "addr:postcode":"93433",
    "addr:street":"Grand Ave",
    "iso:country":"US",
    "sg:address":"1125 Grand Ave",
    "sg:city":"Grover Beach",
    "sg:classifiers":[
        {
            "category":"Professional",
            "subcategory":"Accounting & Tax Preparation",
            "type":"Services"
        }
    ],
    "sg:phone":"+1 805 474 8932",
    "sg:postcode":"93433",
    "sg:province":"CA",
    "sg:tags":[
        "bookkeeping",
        "general"
    ],
    "wof:name":"Past Present Future Bkpg",
    "wof:placetype":"venue"
},
  "geometry": {"coordinates":[-120.61752300000001,35.121463],"type":"Point"}
}