{
  "type": "Feature",
  "properties": {
    "addr:full":"1843 Bus Center Dr Duarte CA 91010",
    "addr:housenumber":"1843",
    "addr:postcode":"91010",
    "addr:street":"Bus Center Dr",
    "iso:country":"US",
    "sg:address":"1843 Bus Center Dr",
    "sg:city":"Duarte",
    "sg:classifiers":[
        {
            "category":"Professional",
            "subcategory":"Management & Consulting",
            "type":"Services"
        }
    ],
    "sg:phone":"+1 626 930 1380",
    "sg:postcode":"91010",
    "sg:province":"CA",
    "sg:tags":[
        "consultant",
        "business"
    ],
    "wof:name":"Boss Med-Legal Management Inc",
    "wof:placetype":"venue"
},
  "geometry": {"coordinates":[-117.96528000000001,34.134029],"type":"Point"}
}