{
  "type": "Feature",
  "properties": {
    "iso:country":"US",
    "sg:address":"866 Cll Haya",
    "sg:city":"Thousand Oaks",
    "sg:classifiers":[
        {
            "category":"Home & Garden",
            "subcategory":"Building Materials",
            "type":"Retail Goods"
        },
        {
            "category":"Building & Trades",
            "subcategory":"Construction",
            "type":"Services"
        }
    ],
    "sg:phone":"+1 805 492 5629",
    "sg:postcode":"91360",
    "sg:province":"CA",
    "sg:tags":[
        "personal",
        "re",
        "improvement"
    ],
    "wof:name":"Screens Plus",
    "wof:placetype":"venue"
},
  "geometry": {"coordinates":[-118.863265,34.215272],"type":"Point"}
}