{
  "type": "Feature",
  "properties": {
    "addr:full":"10741 Calston Way San Diego CA 92126",
    "addr:housenumber":"10741",
    "addr:postcode":"92126",
    "addr:street":"Calston Way",
    "iso:country":"US",
    "sg:address":"10741 Calston Way",
    "sg:city":"San Diego",
    "sg:classifiers":[
        {
            "category":"Professional",
            "type":"Services"
        }
    ],
    "sg:phone":"+1 858 271 7499",
    "sg:postcode":"92126",
    "sg:province":"CA",
    "wof:name":"J&P International",
    "wof:placetype":"venue"
},
  "geometry": {"coordinates":[-117.168333,32.912334],"type":"Point"}
}