{
  "type": "Feature",
  "properties": {
    "addr:full":"16051 Brookhurst St Ste A Fountain Valley CA 92708",
    "addr:housenumber":"16051",
    "addr:postcode":"92708",
    "addr:street":"Brookhurst St Ste A",
    "iso:country":"US",
    "sg:address":"16051 Brookhurst St Ste A",
    "sg:city":"Fountain Valley",
    "sg:classifiers":[
        {
            "category":"Coffee & Tea",
            "type":"Food & Drink"
        }
    ],
    "sg:phone":"+1 714 531 1984",
    "sg:postcode":"92708",
    "sg:province":"CA",
    "sg:website":"www.starbucks.com",
    "wof:name":"Starbucks Coffee",
    "wof:placetype":"venue"
},
  "geometry": {"coordinates":[-117.95471999999999,33.729584],"type":"Point"}
}