{
  "type": "Feature",
  "properties": {
    "iso:country":"US",
    "sg:address":"1021 Fresno St",
    "sg:city":"Newman",
    "sg:classifiers":[
        {
            "category":"Manufacturing",
            "subcategory":"Printing",
            "type":"Manufacturing & Wholesale Goods"
        }
    ],
    "sg:phone":"+1 209 862 2222",
    "sg:postcode":"95360",
    "sg:province":"CA",
    "sg:tags":[
        "newspaper"
    ],
    "wof:name":"Mattos Newspapers",
    "wof:placetype":"venue"
},
  "geometry": {"coordinates":[-121.023519,37.314448],"type":"Point"}
}