{
  "type": "Feature",
  "properties": {
    "iso:country":"US",
    "sg:address":"1455 Indian Hill Blvd",
    "sg:city":"Pomona",
    "sg:classifiers":[
        {
            "category":"Building & Trades",
            "subcategory":"Landscaping Services",
            "type":"Services"
        }
    ],
    "sg:phone":"+1 909 482 0104",
    "sg:postcode":"91767",
    "sg:province":"CA",
    "sg:tags":[
        "landscape",
        "maintenance"
    ],
    "wof:name":"Lsc Grounds Care Inc",
    "wof:placetype":"venue"
},
  "geometry": {"coordinates":[-117.719313,34.072733],"type":"Point"}
}