{
  "type": "Feature",
  "properties": {
    "addr:full":"Fashion Island 849 Newport Center Dr Newport Beach CA 92660",
    "addr:housenumber":"849",
    "addr:postcode":"92660",
    "addr:street":"Fashion;Newport Center Dr",
    "iso:country":"US",
    "sg:address":"Fashion Island 849 Newport Center Dr",
    "sg:city":"Newport Beach",
    "sg:classifiers":[
        {
            "category":"Restaurant",
            "type":"Food & Drink"
        }
    ],
    "sg:phone":"+1 949 640 9273",
    "sg:postcode":"92660",
    "sg:province":"CA",
    "sg:website":"www.yardhouse.com",
    "wof:name":"Yard House",
    "wof:placetype":"venue"
},
  "geometry": {"coordinates":[-117.878164,33.617879],"type":"Point"}
}