{
  "type": "Feature",
  "properties": {
    "addr:full":"340 Dardanelli Ln Los Gatos CA 95032",
    "addr:housenumber":"340",
    "addr:postcode":"95032",
    "addr:street":"Dardanelli Ln",
    "iso:country":"US",
    "sg:address":"340 Dardanelli Ln",
    "sg:city":"Los Gatos",
    "sg:classifiers":[
        {
            "category":"Health Services",
            "subcategory":"Doctor",
            "type":"Services"
        }
    ],
    "sg:phone":"+1 408 374 5340",
    "sg:postcode":"95032",
    "sg:province":"CA",
    "sg:tags":[
        "medicine",
        "internal"
    ],
    "wof:name":"Sumit K. Majumder, MD",
    "wof:placetype":"venue"
},
  "geometry": {"coordinates":[-121.96700300000001,37.2621],"type":"Point"}
}