{
  "type": "Feature",
  "properties": {
    "addr:full":"690 Live Oak Ave Galt CA 95632",
    "addr:housenumber":"690",
    "addr:postcode":"95632",
    "addr:street":"Live Oak Ave",
    "iso:country":"US",
    "sg:address":"690 Live Oak Ave",
    "sg:city":"Galt",
    "sg:classifiers":[
        {
            "category":"Manufacturing",
            "subcategory":"Buildings",
            "type":"Manufacturing & Wholesale Goods"
        },
        {
            "category":"Building & Trades",
            "subcategory":"Construction",
            "type":"Services"
        }
    ],
    "sg:phone":"+1 209 744 1001",
    "sg:postcode":"95632",
    "sg:province":"CA",
    "sg:tags":[
        "home",
        "builder",
        "contractor"
    ],
    "wof:name":"RA Nemetz Construction Co. Inc.",
    "wof:placetype":"venue"
},
  "geometry": {"coordinates":[-121.325996,38.272776],"type":"Point"}
}