{
  "type": "Feature",
  "properties": {
    "iso:country":"US",
    "sg:address":"2001 Quail St",
    "sg:city":"Newport Beach",
    "sg:classifiers":[
        {
            "category":"Real Estate",
            "subcategory":"Architect",
            "type":"Services"
        }
    ],
    "sg:phone":"+1 949 222 1200",
    "sg:postcode":"92660",
    "sg:province":"CA",
    "wof:name":"Fish Gillz Sun Glass Co",
    "wof:placetype":"venue"
},
  "geometry": {"coordinates":[-117.871054,33.663427],"type":"Point"}
}