{
  "type": "Feature",
  "properties": {
    "iso:country":"US",
    "sg:address":"1117 Outrigger Ln",
    "sg:city":"Foster City",
    "sg:classifiers":[
        {
            "category":"Building & Trades",
            "subcategory":"Landscaping Services",
            "type":"Services"
        }
    ],
    "sg:phone":"+1 650 572 9971",
    "sg:postcode":"94404",
    "sg:province":"CA",
    "sg:tags":[
        "tree"
    ],
    "wof:name":"Proficient Tree Care",
    "wof:placetype":"venue"
},
  "geometry": {"coordinates":[-122.253342,37.548826],"type":"Point"}
}