{
  "type": "Feature",
  "properties": {
    "iso:country":"US",
    "sg:address":"2401 E el Segundo Blvd",
    "sg:city":"El Segundo",
    "sg:classifiers":[
        {
            "category":"Insurance",
            "subcategory":"Insurance Agent",
            "type":"Services"
        }
    ],
    "sg:phone":"+1 310 297 2050",
    "sg:postcode":"90245",
    "sg:province":"CA",
    "wof:name":"Farmers Insurance",
    "wof:placetype":"venue"
},
  "geometry": {"coordinates":[-118.377378,33.916323],"type":"Point"}
}