{
  "type": "Feature",
  "properties": {
    "iso:country":"US",
    "sg:address":"1769 N Orange Dr",
    "sg:city":"Los Angeles",
    "sg:classifiers":[
        {
            "category":"Professional",
            "subcategory":"Business Services",
            "type":"Services"
        }
    ],
    "sg:phone":"+1 323 876 8156",
    "sg:postcode":"90028",
    "sg:province":"CA",
    "sg:tags":[
        "interior",
        "consultant",
        "design",
        "decorator"
    ],
    "wof:name":"White Dragon Assoc Inc",
    "wof:placetype":"venue"
},
  "geometry": {"coordinates":[-118.341818,34.102329],"type":"Point"}
}