{
  "type": "Feature",
  "properties": {
    "iso:country":"US",
    "sg:address":"1453 14th St",
    "sg:city":"Santa Monica",
    "sg:classifiers":[
        {
            "category":"Manufacturing",
            "subcategory":"Signs",
            "type":"Manufacturing & Wholesale Goods"
        }
    ],
    "sg:phone":"+1 310 458 3809",
    "sg:postcode":"90404",
    "sg:province":"CA",
    "sg:tags":[
        "advertising",
        "specialty"
    ],
    "wof:name":"A Custom Quick Signs",
    "wof:placetype":"venue"
},
  "geometry": {"coordinates":[-118.484846,34.023514],"type":"Point"}
}