{
  "type": "Feature",
  "properties": {
    "addr:full":"5827 San Pablo Ave Oakland CA 94608",
    "addr:housenumber":"5827",
    "addr:postcode":"94608",
    "addr:street":"San Pablo Ave",
    "iso:country":"US",
    "sg:address":"5827 San Pablo Ave",
    "sg:city":"Oakland",
    "sg:classifiers":[
        {
            "category":"Personal",
            "type":"Services"
        }
    ],
    "sg:phone":"+1 510 886 5155",
    "sg:postcode":"94608",
    "sg:province":"CA",
    "sg:tags":[
        "consultant",
        "image"
    ],
    "wof:name":"Sylvia E Montgomery Image",
    "wof:placetype":"venue"
},
  "geometry": {"coordinates":[-122.28349900000001,37.841715],"type":"Point"}
}