{
  "type": "Feature",
  "properties": {
    "addr:full":"300 S Imperial Ave El Centro CA 92243",
    "addr:housenumber":"300",
    "addr:postcode":"92243",
    "addr:street":"S Imperial Ave",
    "iso:country":"US",
    "sg:address":"300 S Imperial Ave",
    "sg:city":"El Centro",
    "sg:classifiers":[
        {
            "category":"Professional",
            "subcategory":"Lawyer & Legal Services",
            "type":"Services"
        }
    ],
    "sg:phone":"+1 760 339 4844",
    "sg:postcode":"92243",
    "sg:province":"CA",
    "sg:tags":[
        "attorney"
    ],
    "wof:name":"Beard Hobbs & Assoc",
    "wof:placetype":"venue"
},
  "geometry": {"coordinates":[-115.569907,32.790703],"type":"Point"}
}