{
  "type": "Feature",
  "properties": {
    "addr:full":"48017 Fremont Blvd Fremont CA 94538",
    "addr:housenumber":"48017",
    "addr:postcode":"94538",
    "addr:street":"Fremont Blvd",
    "iso:country":"US",
    "sg:address":"48017 Fremont Blvd",
    "sg:city":"Fremont",
    "sg:classifiers":[
        {
            "category":"Professional",
            "subcategory":"Advertising",
            "type":"Services"
        }
    ],
    "sg:phone":"+1 510 651 0881",
    "sg:postcode":"94538",
    "sg:province":"CA",
    "sg:tags":[
        "distribution"
    ],
    "wof:name":"Vivitek Corp",
    "wof:placetype":"venue"
},
  "geometry": {"coordinates":[-121.937894,37.470249],"type":"Point"}
}