{
  "type": "Feature",
  "properties": {
    "iso:country":"US",
    "sg:address":"1312 Blinn Ave",
    "sg:city":"Wilmington",
    "sg:classifiers":[
        {
            "category":"Retail",
            "subcategory":"Repair Shop",
            "type":"Services"
        }
    ],
    "sg:phone":"+1 310 518 3100",
    "sg:postcode":"90744",
    "sg:province":"CA",
    "sg:tags":[
        "lock",
        "locksmith"
    ],
    "wof:name":"Roberto's Key Shop",
    "wof:placetype":"venue"
},
  "geometry": {"coordinates":[-118.245338,33.791536],"type":"Point"}
}