{
  "type": "Feature",
  "properties": {
    "addr:full":"1226 Furukawa Way Santa Maria CA 93458",
    "addr:housenumber":"1226",
    "addr:postcode":"93458",
    "addr:street":"Furukawa Way",
    "iso:country":"US",
    "sg:address":"1226 Furukawa Way",
    "sg:city":"Santa Maria",
    "sg:classifiers":[
        {
            "category":"Professional",
            "type":"Services"
        }
    ],
    "sg:phone":"+1 805 928 5055",
    "sg:postcode":"93458",
    "sg:province":"CA",
    "wof:name":"McDonalds",
    "wof:placetype":"venue"
},
  "geometry": {"coordinates":[-120.454161,34.940082],"type":"Point"}
}