{
  "type": "Feature",
  "properties": {
    "iso:country":"US",
    "sg:address":"1040 Filbert St",
    "sg:city":"San Francisco",
    "sg:classifiers":[
        {
            "category":"Education",
            "subcategory":"College",
            "type":"Public Place"
        }
    ],
    "sg:phone":"+1 415 673 4938",
    "sg:postcode":"94133",
    "sg:province":"CA",
    "wof:name":"Thomas Ingmire",
    "wof:placetype":"venue"
},
  "geometry": {"coordinates":[-122.417574,37.800418],"type":"Point"}
}