{
  "type": "Feature",
  "properties": {
    "iso:country":"US",
    "sg:address":"1109 Maple Ave",
    "sg:city":"Vallejo",
    "sg:classifiers":[
        {
            "category":"Restaurant",
            "type":"Food & Drink"
        }
    ],
    "sg:phone":"+1 707 644 0518",
    "sg:postcode":"94591",
    "sg:province":"CA",
    "wof:name":"Andrea Foods",
    "wof:placetype":"venue"
},
  "geometry": {"coordinates":[-122.221131,38.108202],"type":"Point"}
}