{
  "type": "Feature",
  "properties": {
    "addr:full":"10844 W Chandler Blvd North Hollywood CA 91601",
    "addr:housenumber":"10844",
    "addr:postcode":"91601",
    "addr:street":"W Chandler Blvd",
    "iso:country":"US",
    "sg:address":"10844 W Chandler Blvd",
    "sg:city":"North Hollywood",
    "sg:classifiers":[
        {
            "category":"Restaurant",
            "type":"Food & Drink"
        }
    ],
    "sg:phone":"+1 818 655 9700",
    "sg:postcode":"91601",
    "sg:province":"CA",
    "sg:tags":[
        "caterer"
    ],
    "wof:name":"Smokin' Jack's Food Svc Inc",
    "wof:placetype":"venue"
},
  "geometry": {"coordinates":[-118.365635,34.168779],"type":"Point"}
}