{
  "type": "Feature",
  "properties": {
    "addr:full":"1654 E 2nd St Benicia CA 94510",
    "addr:housenumber":"1654",
    "addr:postcode":"94510",
    "addr:street":"E 2Nd St",
    "iso:country":"US",
    "sg:address":"1654 E 2nd St",
    "sg:city":"Benicia",
    "sg:classifiers":[
        {
            "category":"Restaurant",
            "type":"Food & Drink"
        }
    ],
    "sg:phone":"+1 707 745 0314",
    "sg:postcode":"94510",
    "sg:province":"CA",
    "wof:name":"Pappas Restaurant",
    "wof:placetype":"venue"
},
  "geometry": {"coordinates":[-122.150779,38.05662],"type":"Point"}
}