{
  "type": "Feature",
  "properties": {
    "addr:full":"2348 Mar East St Belvedere Tibrn CA 94920",
    "addr:housenumber":"2348",
    "addr:postcode":"94920",
    "addr:street":"Mar East St",
    "iso:country":"US",
    "sg:address":"2348 Mar East St",
    "sg:city":"Belvedere Tibrn",
    "sg:classifiers":[
        {
            "category":"Professional",
            "subcategory":"Management & Consulting",
            "type":"Services"
        }
    ],
    "sg:phone":"+1 415 789 1732",
    "sg:postcode":"94920",
    "sg:province":"CA",
    "sg:tags":[
        "consultant",
        "business"
    ],
    "wof:name":"Indigo Consulting",
    "wof:placetype":"venue"
},
  "geometry": {"coordinates":[-122.445587,37.875625],"type":"Point"}
}