{
  "type": "Feature",
  "properties": {
    "addr:full":"739 1st St Benicia CA 94510",
    "addr:housenumber":"739",
    "addr:postcode":"94510",
    "addr:street":"1St St",
    "iso:country":"US",
    "sg:address":"739 1st St",
    "sg:city":"Benicia",
    "sg:classifiers":[
        {
            "category":"Shopping",
            "type":"Retail Goods"
        }
    ],
    "sg:phone":"+1 707 747 0755",
    "sg:postcode":"94510",
    "sg:province":"CA",
    "sg:tags":[
        "art",
        "gallery",
        "dealer"
    ],
    "wof:name":"Ethnic Notions",
    "wof:placetype":"venue"
},
  "geometry": {"coordinates":[-122.15824000000001,38.050315],"type":"Point"}
}