{
  "type": "Feature",
  "properties": {
    "iso:country":"US",
    "sg:address":"13781 Newhope St",
    "sg:city":"Garden Grove",
    "sg:classifiers":[
        {
            "category":"Building & Trades",
            "subcategory":"Construction",
            "type":"Services"
        }
    ],
    "sg:phone":"+1 714 534 6398",
    "sg:postcode":"92843",
    "sg:province":"CA",
    "sg:tags":[
        "roofing",
        "contractor"
    ],
    "wof:name":"Dale's Roofing",
    "wof:placetype":"venue"
},
  "geometry": {"coordinates":[-117.928982,33.762904],"type":"Point"}
}