{
  "type": "Feature",
  "properties": {
    "iso:country":"US",
    "sg:address":"12885 Petaluma Rd",
    "sg:city":"Victorville",
    "sg:classifiers":[
        {
            "category":"Retail",
            "subcategory":"Animal Services",
            "type":"Services"
        }
    ],
    "sg:phone":"+1 760 963 7602",
    "sg:postcode":"92392",
    "sg:province":"CA",
    "sg:tags":[
        "pet",
        "boarding",
        "sitting"
    ],
    "wof:name":"High Desert Pet Nanny",
    "wof:placetype":"venue"
},
  "geometry": {"coordinates":[-117.351905,34.484825],"type":"Point"}
}