{
  "type": "Feature",
  "properties": {
    "addr:full":"136 E Kearney Blvd Fresno CA 93706",
    "addr:housenumber":"136",
    "addr:postcode":"93706",
    "addr:street":"E Kearney Blvd",
    "iso:country":"US",
    "sg:address":"136 E Kearney Blvd",
    "sg:city":"Fresno",
    "sg:classifiers":[
        {
            "category":"Professional",
            "subcategory":"Business Services",
            "type":"Services"
        }
    ],
    "sg:phone":"+1 559 352 2694",
    "sg:postcode":"93706",
    "sg:province":"CA",
    "sg:tags":[
        "consultant",
        "coach"
    ],
    "wof:name":"Potts Enterprise Inc.",
    "wof:placetype":"venue"
},
  "geometry": {"coordinates":[-119.811072,36.728467],"type":"Point"}
}