{
  "type": "Feature",
  "properties": {
    "iso:country":"US",
    "sg:address":"10970 Ashton Ave",
    "sg:city":"Los Angeles",
    "sg:classifiers":[
        {
            "category":"Building & Trades",
            "subcategory":"Construction",
            "type":"Services"
        }
    ],
    "sg:phone":"+1 310 478 4314",
    "sg:postcode":"90024",
    "sg:province":"CA",
    "sg:tags":[
        "nonresidential"
    ],
    "wof:name":"Howard W Terry Co",
    "wof:placetype":"venue"
},
  "geometry": {"coordinates":[-118.446248,34.056974],"type":"Point"}
}