{
  "type": "Feature",
  "properties": {
    "addr:full":"1545 Sacramento Avenue West Sacramento CA 95605",
    "addr:housenumber":"1545",
    "addr:postcode":"95605",
    "addr:street":"Sacramento Avenue",
    "iso:country":"US",
    "sg:address":"1545 Sacramento Avenue",
    "sg:city":"West Sacramento",
    "sg:classifiers":[
        {
            "category":"Autos & Motor Vehicles",
            "subcategory":"Auto Supplies",
            "type":"Retail Goods"
        }
    ],
    "sg:phone":"+1 916 371 7572",
    "sg:postcode":"95605",
    "sg:province":"CA",
    "sg:tags":[
        "tire"
    ],
    "wof:name":"Chichoche Tire Shop",
    "wof:placetype":"venue"
},
  "geometry": {"coordinates":[-121.53882299999999,38.59084],"type":"Point"}
}