{
  "type": "Feature",
  "properties": {
    "iso:country":"US",
    "sg:address":"4307 S Vermont Ave",
    "sg:city":"Los Angeles",
    "sg:classifiers":[
        {
            "category":"Restaurant",
            "type":"Food & Drink"
        }
    ],
    "sg:phone":"+1 323 234 5024",
    "sg:postcode":"90037",
    "sg:province":"CA",
    "sg:tags":[
        "out"
    ],
    "wof:name":"Yadimar Restaurant",
    "wof:placetype":"venue"
},
  "geometry": {"coordinates":[-118.291616,34.004691],"type":"Point"}
}