{
  "type": "Feature",
  "properties": {
    "iso:country":"US",
    "sg:address":"113 West Las Tunas Suite 202",
    "sg:city":"San Gabriel",
    "sg:classifiers":[
        {
            "category":"Insurance",
            "subcategory":"Hazard Insurance",
            "type":"Services"
        }
    ],
    "sg:phone":"+1 626 285 8969",
    "sg:postcode":"91776",
    "sg:province":"CA",
    "sg:website":"www.premierchoiceins.com",
    "wof:name":"Premier Choice Insurance",
    "wof:placetype":"venue"
},
  "geometry": {"coordinates":[-118.100503,34.103083],"type":"Point"}
}