{
  "type": "Feature",
  "properties": {
    "iso:country":"US",
    "sg:address":"1659 Columbia St",
    "sg:city":"San Diego",
    "sg:classifiers":[
        {
            "category":"Place Of Worship",
            "subcategory":"Church",
            "type":"Public Place"
        }
    ],
    "sg:phone":"+1 619 233 7039",
    "sg:postcode":"92101",
    "sg:province":"CA",
    "wof:name":"Our Lady of the Rosary Catholic Church",
    "wof:placetype":"venue"
},
  "geometry": {"coordinates":[-117.16799899999999,32.722599],"type":"Point"}
}