{
  "type": "Feature",
  "properties": {
    "iso:country":"US",
    "sg:address":"6811 Woodman Ave",
    "sg:city":"Van Nuys",
    "sg:classifiers":[
        {
            "category":"Shopping",
            "subcategory":"Pharmacy",
            "type":"Retail Goods"
        }
    ],
    "sg:phone":"+1 818 994 1045",
    "sg:postcode":"91405",
    "sg:province":"CA",
    "sg:tags":[
        "drugstore"
    ],
    "wof:name":"Green Earth Pharmacy",
    "wof:placetype":"venue"
},
  "geometry": {"coordinates":[-118.431425,34.194281],"type":"Point"}
}