{
  "type": "Feature",
  "properties": {
    "addr:full":"606 Williams St Murphys CA 95247",
    "addr:housenumber":"606",
    "addr:postcode":"95247",
    "addr:street":"Williams St",
    "iso:country":"US",
    "sg:address":"606 Williams St",
    "sg:city":"Murphys",
    "sg:classifiers":[
        {
            "category":"Shopping",
            "subcategory":"Clothing, Apparel, & Fashions",
            "type":"Retail Goods"
        }
    ],
    "sg:phone":"+1 209 728 8268",
    "sg:postcode":"95247",
    "sg:province":"CA",
    "sg:tags":[
        "western"
    ],
    "wof:name":"Lisa C Melone",
    "wof:placetype":"venue"
},
  "geometry": {"coordinates":[-120.45582400000001,38.144881],"type":"Point"}
}