{
  "type": "Feature",
  "properties": {
    "iso:country":"US",
    "sg:address":"20465 Saratoga Los Gatos R",
    "sg:city":"Saratoga",
    "sg:classifiers":[
        {
            "category":"Building & Trades",
            "subcategory":"Construction",
            "type":"Services"
        }
    ],
    "sg:phone":"+1 408 867 3076",
    "sg:postcode":"95070",
    "sg:province":"CA",
    "sg:tags":[
        "interior",
        "design"
    ],
    "wof:name":"D'ercole Barbara Design",
    "wof:placetype":"venue"
},
  "geometry": {"coordinates":[-122.03124099999999,37.258178],"type":"Point"}
}