{
  "type": "Feature",
  "properties": {
    "addr:full":"14042 Garfield Ave Paramount CA 90723",
    "addr:housenumber":"14042",
    "addr:postcode":"90723",
    "addr:street":"Garfield Ave",
    "iso:country":"US",
    "sg:address":"14042 Garfield Ave",
    "sg:city":"Paramount",
    "sg:classifiers":[
        {
            "category":"Wholesale",
            "subcategory":"Toys & Hobbies",
            "type":"Manufacturing & Wholesale Goods"
        }
    ],
    "sg:phone":"+1 562 259 1292",
    "sg:postcode":"90723",
    "sg:province":"CA",
    "sg:tags":[
        "educational"
    ],
    "wof:name":"West Coast Industries",
    "wof:placetype":"venue"
},
  "geometry": {"coordinates":[-118.168781,33.906301],"type":"Point"}
}