{
  "type": "Feature",
  "properties": {
    "addr:full":"1015 Jefferson Boulevard West Sacramento CA 95691",
    "addr:housenumber":"1015",
    "addr:postcode":"95691",
    "addr:street":"Jefferson Boulevard",
    "iso:country":"US",
    "sg:address":"1015 Jefferson Boulevard",
    "sg:city":"West Sacramento",
    "sg:classifiers":[
        {
            "category":"Autos & Motor Vehicles",
            "subcategory":"Fuel & Gas Station",
            "type":"Retail Goods"
        }
    ],
    "sg:phone":"+1 916 371 8129",
    "sg:postcode":"95691",
    "sg:province":"CA",
    "wof:name":"Rick's Chevron",
    "wof:placetype":"venue"
},
  "geometry": {"coordinates":[-121.52441399999999,38.574603],"type":"Point"}
}