{
  "type": "Feature",
  "properties": {
    "addr:full":"131 6th Ave Bassett CA 91746",
    "addr:housenumber":"131",
    "addr:postcode":"91746",
    "addr:street":"6Th Ave",
    "iso:country":"US",
    "sg:address":"131 6th Ave",
    "sg:city":"Bassett",
    "sg:classifiers":[
        {
            "category":"Building & Trades",
            "subcategory":"Construction",
            "type":"Services"
        }
    ],
    "sg:phone":"+1 626 333 0905",
    "sg:postcode":"91746",
    "sg:province":"CA",
    "sg:tags":[
        "paving",
        "contractor"
    ],
    "wof:name":"Valinda Asphalt & Concrete",
    "wof:placetype":"venue"
},
  "geometry": {"coordinates":[-117.978364,34.037306],"type":"Point"}
}