{
  "type": "Feature",
  "properties": {
    "addr:full":"625 Talbert Ave Simi Valley CA 93065",
    "addr:housenumber":"625",
    "addr:postcode":"93065",
    "addr:street":"Talbert Ave",
    "iso:country":"US",
    "sg:address":"625 Talbert Ave",
    "sg:city":"Simi Valley",
    "sg:classifiers":[
        {
            "category":"Professional",
            "subcategory":"Accounting & Tax Preparation",
            "type":"Services"
        }
    ],
    "sg:phone":"+1 805 583 3721",
    "sg:postcode":"93065",
    "sg:province":"CA",
    "sg:tags":[
        "return",
        "filing"
    ],
    "wof:name":"Diane M Hardesty",
    "wof:placetype":"venue"
},
  "geometry": {"coordinates":[-118.738806,34.252003],"type":"Point"}
}