{
  "type": "Feature",
  "properties": {
    "iso:country":"US",
    "sg:address":"1621 S Westgate Ave",
    "sg:city":"Los Angeles",
    "sg:classifiers":[
        {
            "category":"Professional",
            "type":"Services"
        }
    ],
    "sg:phone":"+1 310 979 8302",
    "sg:postcode":"90025",
    "sg:province":"CA",
    "wof:name":"Apple Studio",
    "wof:placetype":"venue"
},
  "geometry": {"coordinates":[-118.457105,34.039894],"type":"Point"}
}