{
  "type": "Feature",
  "properties": {
    "addr:full":"1327 Shell Ln Clayton CA 94517",
    "addr:housenumber":"1327",
    "addr:postcode":"94517",
    "addr:street":"Shell Ln",
    "iso:country":"US",
    "sg:address":"1327 Shell Ln",
    "sg:city":"Clayton",
    "sg:classifiers":[
        {
            "category":"Utilities",
            "subcategory":"Telephone",
            "type":"Services"
        }
    ],
    "sg:phone":"+1 925 672 0819",
    "sg:postcode":"94517",
    "sg:province":"CA",
    "sg:tags":[
        "communications"
    ],
    "wof:name":"Megatomic Internet",
    "wof:placetype":"venue"
},
  "geometry": {"coordinates":[-121.932394,37.944939],"type":"Point"}
}