{
  "type": "Feature",
  "properties": {
    "addr:full":"4500 Ocean Blvd San Diego CA 92109",
    "addr:housenumber":"4500",
    "addr:postcode":"92109",
    "addr:street":"Ocean Blvd",
    "iso:country":"US",
    "sg:address":"4500 Ocean Blvd",
    "sg:city":"San Diego",
    "sg:classifiers":[
        {
            "category":"Home & Garden",
            "subcategory":"Home Furnishings",
            "type":"Retail Goods"
        }
    ],
    "sg:phone":"+1 858 657 9099",
    "sg:postcode":"92109",
    "sg:province":"CA",
    "sg:tags":[
        "decor"
    ],
    "sg:website":"sandiegocandlefactory.com",
    "wof:name":"San Diego Candle Factory",
    "wof:placetype":"venue"
},
  "geometry": {"coordinates":[-117.257023,32.79623],"type":"Point"}
}