{
  "type": "Feature",
  "properties": {
    "addr:full":"1380 Estates Dr Dixon CA 95620",
    "addr:housenumber":"1380",
    "addr:postcode":"95620",
    "addr:street":"Estates Dr",
    "iso:country":"US",
    "sg:address":"1380 Estates Dr",
    "sg:city":"Dixon",
    "sg:phone":"+1 707 678 9768",
    "sg:postcode":"95620",
    "sg:province":"CA",
    "sg:tags":[
        "farm"
    ],
    "wof:name":"Tom Nishimura Farming",
    "wof:placetype":"venue"
},
  "geometry": {"coordinates":[-121.840163,38.445201],"type":"Point"}
}