{
  "type": "Feature",
  "properties": {
    "addr:full":"13 Via Candelaria Trabuco Canyon CA 92679",
    "addr:postcode":"92679",
    "addr:street":"Via Candelaria",
    "iso:country":"US",
    "sg:address":"13 Via Candelaria",
    "sg:city":"Trabuco Canyon",
    "sg:classifiers":[
        {
            "category":"Shopping",
            "subcategory":"Computers & Home Electronics",
            "type":"Retail Goods"
        }
    ],
    "sg:phone":"+1 949 766 4852",
    "sg:postcode":"92679",
    "sg:province":"CA",
    "sg:tags":[
        "store",
        "software"
    ],
    "wof:name":"Pda 360",
    "wof:placetype":"venue"
},
  "geometry": {"coordinates":[-117.588472,33.622869],"type":"Point"}
}