{
  "type": "Feature",
  "properties": {
    "iso:country":"US",
    "sg:address":"1317 H Street",
    "sg:city":"Sacramento",
    "sg:classifiers":[
        {
            "category":"Health Services",
            "subcategory":"Doctor",
            "type":"Services"
        }
    ],
    "sg:phone":"+1 916 446 6640",
    "sg:postcode":"95814",
    "sg:province":"CA",
    "sg:tags":[
        "psychiatrist"
    ],
    "wof:name":"Rounds Barbara MD",
    "wof:placetype":"venue"
},
  "geometry": {"coordinates":[-121.489372,38.58287],"type":"Point"}
}