{
  "type": "Feature",
  "properties": {
    "addr:full":"10135 Three Oaks Way Santee CA 92071",
    "addr:housenumber":"10135",
    "addr:postcode":"92071",
    "addr:street":"Three Oaks Way",
    "iso:country":"US",
    "sg:address":"10135 Three Oaks Way",
    "sg:city":"Santee",
    "sg:classifiers":[
        {
            "category":"Professional",
            "type":"Services"
        }
    ],
    "sg:phone":"+1 619 449 4454",
    "sg:postcode":"92071",
    "sg:province":"CA",
    "wof:name":"Baby Fabulous",
    "wof:placetype":"venue"
},
  "geometry": {"coordinates":[-116.97701000000001,32.863095],"type":"Point"}
}