{
  "type": "Feature",
  "properties": {
    "iso:country":"US",
    "sg:address":"117 W 9th St",
    "sg:city":"Los Angeles",
    "sg:classifiers":[
        {
            "category":"Wholesale",
            "subcategory":"Apparel",
            "type":"Manufacturing & Wholesale Goods"
        },
        {
            "category":"Wholesale",
            "subcategory":"Durable Goods & Equipment",
            "type":"Manufacturing & Wholesale Goods"
        }
    ],
    "sg:phone":"+1 213 622 2245",
    "sg:postcode":"90015",
    "sg:province":"CA",
    "sg:tags":[
        "importer",
        "clothing",
        "junior"
    ],
    "wof:name":"Fabrique Inc",
    "wof:placetype":"venue"
},
  "geometry": {"coordinates":[-118.255214,34.041843],"type":"Point"}
}