{
  "type": "Feature",
  "properties": {
    "iso:country":"US",
    "sg:address":"151 Bernal Rd Ste 2B",
    "sg:city":"San Jose",
    "sg:classifiers":[
        {
            "category":"Banks & Credit Unions",
            "subcategory":"Financial Services",
            "type":"Services"
        }
    ],
    "sg:phone":"+1 408 281 8383",
    "sg:postcode":"95119",
    "sg:province":"CA",
    "sg:tags":[
        "broker",
        "mortgage"
    ],
    "wof:name":"Community West Mortgage",
    "wof:placetype":"venue"
},
  "geometry": {"coordinates":[-121.77552900000001,37.22863],"type":"Point"}
}