{
  "type": "Feature",
  "properties": {
    "iso:country":"US",
    "sg:address":"87 W Sierra Madre Blvd",
    "sg:city":"Sierra Madre",
    "sg:classifiers":[
        {
            "category":"Arts & Performance",
            "subcategory":"Arts Center",
            "type":"Entertainment"
        }
    ],
    "sg:phone":"+1 626 355 4318",
    "sg:postcode":"91024",
    "sg:province":"CA",
    "sg:tags":[
        "performing"
    ],
    "sg:website":"www.sierramadreplayhouse.org",
    "wof:name":"Sierra Madre Playhouse",
    "wof:placetype":"venue"
},
  "geometry": {"coordinates":[-118.055,34.1618],"type":"Point"}
}