{
  "type": "Feature",
  "properties": {
    "addr:full":"2848 Richard Ave Concord CA 94520",
    "addr:housenumber":"2848",
    "addr:postcode":"94520",
    "addr:street":"Richard Ave",
    "iso:country":"US",
    "sg:address":"2848 Richard Ave",
    "sg:city":"Concord",
    "sg:classifiers":[
        {
            "category":"Utilities",
            "subcategory":"Telephone",
            "type":"Services"
        }
    ],
    "sg:phone":"+1 925 363 5356",
    "sg:postcode":"94520",
    "sg:province":"CA",
    "sg:tags":[
        "communications"
    ],
    "wof:name":"Smart Solution",
    "wof:placetype":"venue"
},
  "geometry": {"coordinates":[-122.04755299999999,37.989451],"type":"Point"}
}