{
  "type": "Feature",
  "properties": {
    "iso:country":"US",
    "sg:address":"6315 Pacific Blvd",
    "sg:city":"Huntington Park",
    "sg:classifiers":[
        {
            "category":"Professional",
            "subcategory":"Accounting & Tax Preparation",
            "type":"Services"
        }
    ],
    "sg:phone":"+1 323 587 7959",
    "sg:postcode":"90255",
    "sg:province":"CA",
    "sg:tags":[
        "return",
        "filing"
    ],
    "wof:name":"H & R Block Tax Svc",
    "wof:placetype":"venue"
},
  "geometry": {"coordinates":[-118.22525,33.981908],"type":"Point"}
}