{
  "type": "Feature",
  "properties": {
    "addr:full":"10076 Silver Creek Ln El Cajon CA 92021",
    "addr:housenumber":"10076",
    "addr:postcode":"92021",
    "addr:street":"Silver Creek Ln",
    "iso:country":"US",
    "sg:address":"10076 Silver Creek Ln",
    "sg:city":"El Cajon",
    "sg:classifiers":[
        {
            "category":"Shopping",
            "subcategory":"Clothing, Apparel, & Fashions",
            "type":"Retail Goods"
        }
    ],
    "sg:phone":"+1 619 561 0343",
    "sg:postcode":"92021",
    "sg:province":"CA",
    "sg:tags":[
        "baby",
        "accessory"
    ],
    "wof:name":"ABC Stork & Co",
    "wof:placetype":"venue"
},
  "geometry": {"coordinates":[-116.876322,32.867781],"type":"Point"}
}