{
  "type": "Feature",
  "properties": {
    "iso:country":"US",
    "sg:address":"7060 Rosanna St",
    "sg:city":"Gilroy",
    "sg:classifiers":[
        {
            "category":"Shopping",
            "subcategory":"Gifts & Souvenirs",
            "type":"Retail Goods"
        }
    ],
    "sg:phone":"+1 408 842 0020",
    "sg:postcode":"95020",
    "sg:province":"CA",
    "sg:tags":[
        "party",
        "supply"
    ],
    "wof:name":"Garlic City Jumps",
    "wof:placetype":"venue"
},
  "geometry": {"coordinates":[-121.569607,36.999861],"type":"Point"}
}