{
  "type": "Feature",
  "properties": {
    "iso:country":"US",
    "sg:address":"19619 Temescal Canyon Rd",
    "sg:city":"Corona",
    "sg:classifiers":[
        {
            "category":"Restaurant",
            "type":"Food & Drink"
        }
    ],
    "sg:phone":"+1 951 734 3785",
    "sg:postcode":"92881",
    "sg:province":"CA",
    "sg:tags":[
        "mexican"
    ],
    "wof:name":"Don Pepe's",
    "wof:placetype":"venue"
},
  "geometry": {"coordinates":[-117.520152,33.834051],"type":"Point"}
}