{
  "type": "Feature",
  "properties": {
    "addr:full":"123 Hodencamp Rd Thousand Oaks CA 91360",
    "addr:housenumber":"123",
    "addr:postcode":"91360",
    "addr:street":"Hodencamp Rd",
    "iso:country":"US",
    "sg:address":"123 Hodencamp Rd",
    "sg:city":"Thousand Oaks",
    "sg:classifiers":[
        {
            "category":"Professional",
            "type":"Services"
        }
    ],
    "sg:phone":"+1 805 497 6227",
    "sg:postcode":"91360",
    "sg:province":"CA",
    "wof:name":"Fas Shellee",
    "wof:placetype":"venue"
},
  "geometry": {"coordinates":[-118.868443,34.180235],"type":"Point"}
}