{
  "type": "Feature",
  "properties": {
    "iso:country":"US",
    "sg:address":"11538 Rosecrans Ave",
    "sg:city":"Norwalk",
    "sg:classifiers":[
        {
            "category":"Real Estate",
            "subcategory":"Real Estate Services",
            "type":"Services"
        },
        {
            "category":"Real Estate",
            "subcategory":"Real Estate Agent",
            "type":"Services"
        }
    ],
    "sg:phone":"+1 562 929 4624",
    "sg:postcode":"90650",
    "sg:province":"CA",
    "sg:tags":[
        "buyer",
        "loan",
        "broker"
    ],
    "wof:name":"Key Funding Inc",
    "wof:placetype":"venue"
},
  "geometry": {"coordinates":[-118.087849,33.902114],"type":"Point"}
}