{
  "type": "Feature",
  "properties": {
    "addr:full":"945-A Battery Street San Francisco CA 94111",
    "addr:housenumber":"945-a",
    "addr:postcode":"94111",
    "addr:street":"Battery Street",
    "iso:country":"US",
    "sg:address":"945-A Battery Street",
    "sg:city":"San Francisco",
    "sg:classifiers":[
        {
            "category":"Food & Beverages",
            "subcategory":"Groceries & Convenience Stores",
            "type":"Retail Goods"
        }
    ],
    "sg:postcode":"94111",
    "sg:province":"CA",
    "wof:name":"Pika Mart",
    "wof:placetype":"venue"
},
  "geometry": {"coordinates":[-122.40173799999999,37.800199],"type":"Point"}
}