{
  "type": "Feature",
  "properties": {
    "addr:full":"3838 Oakwood Ave Los Angeles CA 90004",
    "addr:housenumber":"3838",
    "addr:postcode":"90004",
    "addr:street":"Oakwood Ave",
    "iso:country":"US",
    "sg:address":"3838 Oakwood Ave",
    "sg:city":"Los Angeles",
    "sg:classifiers":[
        {
            "category":"Wholesale",
            "subcategory":"Furniture",
            "type":"Manufacturing & Wholesale Goods"
        }
    ],
    "sg:phone":"+1 530 283 4551",
    "sg:postcode":"90004",
    "sg:province":"CA",
    "sg:tags":[
        "bleachers",
        "grandstand"
    ],
    "wof:name":"Rollway Grandstand Corp",
    "wof:placetype":"venue"
},
  "geometry": {"coordinates":[-118.289558,34.077658],"type":"Point"}
}