{
  "type": "Feature",
  "properties": {
    "iso:country":"US",
    "sg:address":"1123 S California Blvd",
    "sg:city":"Walnut Creek",
    "sg:classifiers":[
        {
            "category":"Shopping",
            "subcategory":"Pharmacy",
            "type":"Retail Goods"
        }
    ],
    "sg:phone":"+1 925 933 9474",
    "sg:postcode":"94596",
    "sg:province":"CA",
    "wof:name":"Longs Drug",
    "wof:placetype":"venue"
},
  "geometry": {"coordinates":[-122.063075,37.896241],"type":"Point"}
}