{
  "type": "Feature",
  "properties": {
    "addr:full":"656 Lincoln Ave Pasadena CA 91103",
    "addr:housenumber":"656",
    "addr:postcode":"91103",
    "addr:street":"Lincoln Ave",
    "iso:country":"US",
    "sg:address":"656 Lincoln Ave",
    "sg:city":"Pasadena",
    "sg:classifiers":[
        {
            "category":"Shopping",
            "subcategory":"Tobacco",
            "type":"Retail Goods"
        }
    ],
    "sg:phone":"+1 626 792 9405",
    "sg:postcode":"91103",
    "sg:province":"CA",
    "sg:tags":[
        "shop"
    ],
    "wof:name":"A1 Smoke Shop",
    "wof:placetype":"venue"
},
  "geometry": {"coordinates":[-118.15506600000001,34.156384],"type":"Point"}
}