{
  "type": "Feature",
  "properties": {
    "iso:country":"US",
    "sg:address":"914 Carpinteria St",
    "sg:city":"Santa Barbara",
    "sg:classifiers":[
        {
            "category":"Banks & Credit Unions",
            "subcategory":"Bank",
            "type":"Services"
        }
    ],
    "sg:phone":"+1 805 963 8928",
    "sg:postcode":"93103",
    "sg:province":"CA",
    "sg:website":"www.midstate.com",
    "wof:name":"Mid-State Bank & Trust",
    "wof:placetype":"venue"
},
  "geometry": {"coordinates":[-119.676555,34.421521],"type":"Point"}
}