{
  "type": "Feature",
  "properties": {
    "iso:country":"US",
    "sg:address":"711 Van Ness Avenue",
    "sg:city":"San Francisco",
    "sg:classifiers":[
        {
            "category":"Professional",
            "subcategory":"Lawyer & Legal Services",
            "type":"Services"
        }
    ],
    "sg:phone":"+1 415 771 0100",
    "sg:postcode":"94102",
    "sg:province":"CA",
    "wof:name":"The Sapiro Law Firm",
    "wof:placetype":"venue"
},
  "geometry": {"coordinates":[-122.42062900000001,37.78219],"type":"Point"}
}