{
  "type": "Feature",
  "properties": {
    "addr:full":"11347 Washington Blvd Whittier CA 90606",
    "addr:housenumber":"11347",
    "addr:postcode":"blvd;90606",
    "addr:street":"Washington",
    "iso:country":"US",
    "sg:address":"11347 Washington Blvd",
    "sg:city":"Whittier",
    "sg:classifiers":[
        {
            "category":"Autos & Motor Vehicles",
            "subcategory":"Fuel & Gas Station",
            "type":"Retail Goods"
        }
    ],
    "sg:phone":"+1 562 699 0552",
    "sg:postcode":"90606",
    "sg:province":"CA",
    "sg:tags":[
        "oil"
    ],
    "wof:name":"Black Gold Corp",
    "wof:placetype":"venue"
},
  "geometry": {"coordinates":[-118.06898200000001,33.971482],"type":"Point"}
}