{
  "type": "Feature",
  "properties": {
    "iso:country":"US",
    "sg:address":"42076 Agena St",
    "sg:city":"Temecula",
    "sg:classifiers":[
        {
            "category":"Food & Beverages",
            "subcategory":"Bakery",
            "type":"Retail Goods"
        }
    ],
    "sg:phone":"+1 951 522 7232",
    "sg:postcode":"92592",
    "sg:province":"CA",
    "sg:tags":[
        "cooky",
        "cracker"
    ],
    "wof:name":"Mrs. Fields Original Cookies",
    "wof:placetype":"venue"
},
  "geometry": {"coordinates":[-117.13060299999999,33.504649],"type":"Point"}
}