{
  "type": "Feature",
  "properties": {
    "iso:country":"US",
    "sg:address":"1721 N Jade St",
    "sg:city":"Richmond",
    "sg:classifiers":[
        {
            "category":"Building & Trades",
            "subcategory":"Cleaning & Sanitation",
            "type":"Services"
        }
    ],
    "sg:phone":"+1 510 620 0953",
    "sg:postcode":"94801",
    "sg:province":"CA",
    "sg:tags":[
        "house"
    ],
    "wof:name":"Michael's House Cleaning",
    "wof:placetype":"venue"
},
  "geometry": {"coordinates":[-122.37027500000001,37.958136],"type":"Point"}
}