{
  "type": "Feature",
  "properties": {
    "iso:country":"US",
    "sg:address":"10081 Jennrich Ave",
    "sg:city":"Garden Grove",
    "sg:classifiers":[
        {
            "category":"Professional",
            "subcategory":"Accounting & Tax Preparation",
            "type":"Services"
        }
    ],
    "sg:phone":"+1 714 775 1745",
    "sg:postcode":"92843",
    "sg:province":"CA",
    "sg:tags":[
        "billing"
    ],
    "wof:name":"Awan Medical Billing",
    "wof:placetype":"venue"
},
  "geometry": {"coordinates":[-117.953107,33.755394],"type":"Point"}
}