{
  "type": "Feature",
  "properties": {
    "addr:full":"1000 Walnut Ave Pomona CA 91766",
    "addr:housenumber":"1000",
    "addr:postcode":"91766",
    "addr:street":"Walnut Ave",
    "iso:country":"US",
    "sg:address":"1000 Walnut Ave",
    "sg:city":"Pomona",
    "sg:classifiers":[
        {
            "category":"Freight",
            "type":"Transportation"
        }
    ],
    "sg:phone":"+1 909 628 8993",
    "sg:postcode":"91766",
    "sg:province":"CA",
    "sg:tags":[
        "chemical",
        "ship"
    ],
    "wof:name":"Dupont",
    "wof:placetype":"venue"
},
  "geometry": {"coordinates":[-117.731499,34.023514],"type":"Point"}
}