{
  "type": "Feature",
  "properties": {
    "addr:full":"185 Trofello Ln Aliso Viejo CA 92656",
    "addr:housenumber":"185",
    "addr:postcode":"92656",
    "addr:street":"Trofello Ln",
    "iso:country":"US",
    "sg:address":"185 Trofello Ln",
    "sg:city":"Aliso Viejo",
    "sg:classifiers":[
        {
            "category":"Professional",
            "type":"Services"
        }
    ],
    "sg:phone":"+1 949 448 0046",
    "sg:postcode":"92656",
    "sg:province":"CA",
    "wof:name":"Wgs Designs",
    "wof:placetype":"venue"
},
  "geometry": {"coordinates":[-117.732833,33.561634],"type":"Point"}
}