{
  "type": "Feature",
  "properties": {
    "iso:country":"US",
    "sg:address":"1150 Pier F Ave",
    "sg:city":"Long Beach",
    "sg:classifiers":[
        {
            "category":"Wholesale",
            "subcategory":"Construction Materials",
            "type":"Manufacturing & Wholesale Goods"
        }
    ],
    "sg:phone":"+1 562 495 0600",
    "sg:postcode":"90802",
    "sg:province":"CA",
    "sg:tags":[
        "cement"
    ],
    "wof:name":"Mitsubishi Cement",
    "wof:placetype":"venue"
},
  "geometry": {"coordinates":[-118.212279,33.744301],"type":"Point"}
}