{
  "type": "Feature",
  "properties": {
    "addr:full":"2333 Verna Ct San Leandro CA 94577",
    "addr:housenumber":"2333",
    "addr:postcode":"94577",
    "addr:street":"Verna Ct",
    "iso:country":"US",
    "sg:address":"2333 Verna Ct",
    "sg:city":"San Leandro",
    "sg:classifiers":[
        {
            "category":"Home & Garden",
            "subcategory":"Building Materials",
            "type":"Retail Goods"
        },
        {
            "category":"Building & Trades",
            "subcategory":"Construction",
            "type":"Services"
        }
    ],
    "sg:phone":"+1 510 483 5444",
    "sg:postcode":"94577",
    "sg:province":"CA",
    "sg:tags":[
        "windows",
        "house"
    ],
    "sg:website":"www.viplex.com",
    "wof:name":"Viplex Industries Inc",
    "wof:placetype":"venue"
},
  "geometry": {"coordinates":[-122.17245200000001,37.707034],"type":"Point"}
}