{
  "type": "Feature",
  "properties": {
    "addr:full":"147 E 3rd Ave San Mateo CA 94401",
    "addr:housenumber":"147",
    "addr:postcode":"94401",
    "addr:street":"E 3Rd Ave",
    "iso:country":"US",
    "sg:address":"147 E 3rd Ave",
    "sg:city":"San Mateo",
    "sg:classifiers":[
        {
            "category":"Restaurant",
            "type":"Food & Drink"
        }
    ],
    "sg:phone":"+1 650 685 6151",
    "sg:postcode":"94401",
    "sg:province":"CA",
    "sg:tags":[
        "vietnamese"
    ],
    "wof:name":"Pho Little Saigon 3",
    "wof:placetype":"venue"
},
  "geometry": {"coordinates":[-122.323714,37.564626],"type":"Point"}
}