{
  "type": "Feature",
  "properties": {
    "addr:full":"357 Alcatraz Ave Oakland CA 94618",
    "addr:housenumber":"357",
    "addr:postcode":"94618",
    "addr:street":"Alcatraz Ave",
    "iso:country":"US",
    "sg:address":"357 Alcatraz Ave",
    "sg:city":"Oakland",
    "sg:classifiers":[
        {
            "category":"Building & Trades",
            "subcategory":"Construction",
            "type":"Services"
        }
    ],
    "sg:phone":"+1 510 652 0607",
    "sg:postcode":"94618",
    "sg:province":"CA",
    "sg:tags":[
        "road",
        "contractor"
    ],
    "wof:name":"Hands Of Experience",
    "wof:placetype":"venue"
},
  "geometry": {"coordinates":[-122.254975,37.85094],"type":"Point"}
}