{
  "type": "Feature",
  "properties": {
    "addr:full":"1720 S Grand Ave Santa Ana CA 92705",
    "addr:housenumber":"1720",
    "addr:postcode":"92705",
    "addr:street":"S Grand Ave",
    "iso:country":"US",
    "sg:address":"1720 S Grand Ave",
    "sg:city":"Santa Ana",
    "sg:classifiers":[
        {
            "category":"Restaurant",
            "type":"Food & Drink"
        }
    ],
    "sg:phone":"+1 714 542 8877",
    "sg:postcode":"92705",
    "sg:province":"CA",
    "sg:tags":[
        "breakfast",
        "brunch"
    ],
    "wof:name":"Cowgirls Cafe",
    "wof:placetype":"venue"
},
  "geometry": {"coordinates":[-117.850998,33.7243],"type":"Point"}
}