{
  "type": "Feature",
  "properties": {
    "iso:country":"US",
    "sg:address":"112 Los Cerritos Mall",
    "sg:city":"Cerritos",
    "sg:classifiers":[
        {
            "category":"Shopping",
            "subcategory":"Mobile Phones",
            "type":"Retail Goods"
        }
    ],
    "sg:phone":"+1 562 402 1927",
    "sg:postcode":"90703",
    "sg:province":"CA",
    "sg:website":"www.radioshack.com",
    "wof:name":"Radioshack",
    "wof:placetype":"venue"
},
  "geometry": {"coordinates":[-118.095001,33.865501],"type":"Point"}
}