{
  "type": "Feature",
  "properties": {
    "iso:country":"US",
    "sg:address":"620 Las Juntas St",
    "sg:city":"Martinez",
    "sg:classifiers":[
        {
            "category":"Social Services",
            "type":"Services"
        }
    ],
    "sg:phone":"+1 925 957 0780",
    "sg:postcode":"94553",
    "sg:province":"CA",
    "sg:tags":[
        "human"
    ],
    "wof:name":"R E S",
    "wof:placetype":"venue"
},
  "geometry": {"coordinates":[-122.13533,38.01859],"type":"Point"}
}