{
  "type": "Feature",
  "properties": {
    "iso:country":"US",
    "sg:address":"7007 Alcove Ave",
    "sg:city":"North Hollywood",
    "sg:classifiers":[
        {
            "category":"Building & Trades",
            "subcategory":"Construction",
            "type":"Services"
        }
    ],
    "sg:phone":"+1 818 509 0347",
    "sg:postcode":"91605",
    "sg:province":"CA",
    "sg:tags":[
        "painter"
    ],
    "wof:name":"Neat Painter Co",
    "wof:placetype":"venue"
},
  "geometry": {"coordinates":[-118.412689,34.196087],"type":"Point"}
}