{
  "type": "Feature",
  "properties": {
    "addr:full":"4697 Mission Blvd San Diego CA 92109",
    "addr:housenumber":"4697",
    "addr:postcode":"92109",
    "addr:street":"Mission Blvd",
    "iso:country":"US",
    "sg:address":"4697 Mission Blvd",
    "sg:city":"San Diego",
    "sg:classifiers":[
        {
            "category":"Real Estate",
            "subcategory":"Real Estate Operator",
            "type":"Services"
        }
    ],
    "sg:phone":"+1 858 581 6525",
    "sg:postcode":"92109",
    "sg:province":"CA",
    "sg:tags":[
        "building",
        "apartment"
    ],
    "wof:name":"Blue Diamond Apartments",
    "wof:placetype":"venue"
},
  "geometry": {"coordinates":[-117.256159,32.798957],"type":"Point"}
}