{
  "type": "Feature",
  "properties": {
    "iso:country":"US",
    "sg:address":"4 Highgate Rd",
    "sg:city":"Kensington",
    "sg:classifiers":[
        {
            "category":"Professional",
            "subcategory":"Computer Services",
            "type":"Services"
        }
    ],
    "sg:phone":"+1 510 525 3491",
    "sg:postcode":"94707",
    "sg:province":"CA",
    "sg:tags":[
        "consultant",
        "designer"
    ],
    "sg:website":"www.octet-consulting.com",
    "wof:name":"Octet Consulting",
    "wof:placetype":"venue"
},
  "geometry": {"coordinates":[-122.287677,37.91466],"type":"Point"}
}