{
  "type": "Feature",
  "properties": {
    "addr:full":"225 W Carrillo St Santa Barbara CA 93101",
    "addr:housenumber":"225",
    "addr:postcode":"93101",
    "addr:street":"W Carrillo St",
    "iso:country":"US",
    "sg:address":"225 W Carrillo St",
    "sg:city":"Santa Barbara",
    "sg:classifiers":[
        {
            "category":"Autos & Motor Vehicles",
            "subcategory":"Automobile Sales",
            "type":"Retail Goods"
        }
    ],
    "sg:phone":"+1 805 966 7666",
    "sg:postcode":"93101",
    "sg:province":"CA",
    "sg:tags":[
        "car",
        "dealer"
    ],
    "wof:name":"Fiesta Auto Agency",
    "wof:placetype":"venue"
},
  "geometry": {"coordinates":[-119.70516499999999,34.418287],"type":"Point"}
}