{
  "type": "Feature",
  "properties": {
    "iso:country":"US",
    "sg:address":"2439 Durant Ave",
    "sg:city":"Berkeley",
    "sg:classifiers":[
        {
            "category":"Restaurant",
            "type":"Food & Drink"
        }
    ],
    "sg:phone":"+1 510 848 4340",
    "sg:postcode":"94704",
    "sg:province":"CA",
    "sg:tags":[
        "chinese"
    ],
    "wof:name":"Sun Hong Kong Restaurant",
    "wof:placetype":"venue"
},
  "geometry": {"coordinates":[-122.26039299999999,37.867666],"type":"Point"}
}