{
  "type": "Feature",
  "properties": {
    "addr:full":"570 S 9th St Modesto CA 95351",
    "addr:housenumber":"570",
    "addr:postcode":"ca 95351",
    "addr:street":"S 9Th St",
    "iso:country":"US",
    "sg:address":"570 S 9th St",
    "sg:city":"Modesto",
    "sg:classifiers":[
        {
            "category":"Manufacturing",
            "subcategory":"Metals",
            "type":"Manufacturing & Wholesale Goods"
        }
    ],
    "sg:phone":"+1 209 524 1743",
    "sg:postcode":"95351",
    "sg:province":"CA",
    "sg:tags":[
        "steel"
    ],
    "wof:name":"Doyle's Steel Co",
    "wof:placetype":"venue"
},
  "geometry": {"coordinates":[-120.98581,37.621917],"type":"Point"}
}