{
  "type": "Feature",
  "properties": {
    "addr:full":"420 Walnut St Sonoma CA 95476",
    "addr:housenumber":"420",
    "addr:postcode":"95476",
    "addr:street":"Walnut St",
    "iso:country":"US",
    "sg:address":"420 Walnut St",
    "sg:city":"Sonoma",
    "sg:classifiers":[
        {
            "category":"Wholesale",
            "subcategory":"Durable Goods & Equipment",
            "type":"Manufacturing & Wholesale Goods"
        }
    ],
    "sg:phone":"+1 707 996 0485",
    "sg:postcode":"95476",
    "sg:province":"CA",
    "sg:tags":[
        "representative",
        "manufacturer"
    ],
    "wof:name":"C E Sales",
    "wof:placetype":"venue"
},
  "geometry": {"coordinates":[-122.449984,38.290267],"type":"Point"}
}