{
  "type": "Feature",
  "properties": {
    "addr:full":"3040 Valencia Ave Aptos CA 95003",
    "addr:housenumber":"3040",
    "addr:postcode":"ca 95003",
    "addr:street":"Valencia Ave",
    "iso:country":"US",
    "sg:address":"3040 Valencia Ave",
    "sg:city":"Aptos",
    "sg:classifiers":[
        {
            "category":"Utilities",
            "subcategory":"Telephone",
            "type":"Services"
        },
        {
            "category":"Professional",
            "subcategory":"Computer Services",
            "type":"Services"
        }
    ],
    "sg:phone":"+1 831 685 0771",
    "sg:postcode":"95003",
    "sg:province":"CA",
    "sg:tags":[
        "website",
        "web",
        "posting",
        "facility",
        "design",
        "internet"
    ],
    "sg:website":"www.boardwalk-internet.com",
    "wof:name":"Boardwalk Internet Corporation",
    "wof:placetype":"venue"
},
  "geometry": {"coordinates":[-121.886279,36.976227],"type":"Point"}
}