{
  "type": "Feature",
  "properties": {
    "iso:country":"US",
    "sg:address":"1880 Harbor Island Dr",
    "sg:city":"San Diego",
    "sg:classifiers":[
        {
            "category":"Recreation",
            "type":"Entertainment"
        }
    ],
    "sg:phone":"+1 619 291 7245",
    "sg:postcode":"92101",
    "sg:province":"CA",
    "sg:tags":[
        "charter",
        "boat"
    ],
    "sg:website":"www.harborislandyachtclub.com",
    "wof:name":"Harbor Island Yacht Club",
    "wof:placetype":"venue"
},
  "geometry": {"coordinates":[-117.20131600000001,32.725122],"type":"Point"}
}