{
  "type": "Feature",
  "properties": {
    "iso:country":"US",
    "sg:address":"2023 Stierlin Ct",
    "sg:city":"Mountain View",
    "sg:classifiers":[
        {
            "category":"Manufacturing",
            "subcategory":"Printing",
            "type":"Manufacturing & Wholesale Goods"
        }
    ],
    "sg:phone":"+1 650 938 3663",
    "sg:postcode":"94043",
    "sg:province":"CA",
    "sg:tags":[
        "publisher",
        "software"
    ],
    "wof:name":"Vocent",
    "wof:placetype":"venue"
},
  "geometry": {"coordinates":[-122.073224,37.423335],"type":"Point"}
}