{
  "type": "Feature",
  "properties": {
    "addr:full":"11320 Pierce St Riverside CA 92505",
    "addr:housenumber":"11320",
    "addr:postcode":"92505",
    "addr:street":"Pierce St",
    "iso:country":"US",
    "sg:address":"11320 Pierce St",
    "sg:city":"Riverside",
    "sg:classifiers":[
        {
            "category":"Shopping",
            "subcategory":"Books",
            "type":"Retail Goods"
        }
    ],
    "sg:phone":"+1 951 509 2274",
    "sg:postcode":"92505",
    "sg:province":"CA",
    "sg:tags":[
        "dealer"
    ],
    "wof:name":"Adventist Book Ctr",
    "wof:placetype":"venue"
},
  "geometry": {"coordinates":[-117.49597300000001,33.915676],"type":"Point"}
}