{
  "type": "Feature",
  "properties": {
    "iso:country":"US",
    "sg:address":"11320 Pierce St",
    "sg:city":"Riverside",
    "sg:classifiers":[
        {
            "category":"Shopping",
            "subcategory":"Books",
            "type":"Retail Goods"
        }
    ],
    "sg:phone":"+1 951 509 2274",
    "sg:postcode":"92505",
    "sg:province":"CA",
    "sg:tags":[
        "dealer"
    ],
    "wof:name":"Adventist Book Ctr",
    "wof:placetype":"venue"
},
  "geometry": {"coordinates":[-117.495973,33.915676],"type":"Point"}
}