{
  "type": "Feature",
  "properties": {
    "addr:full":"243 N Maple Ave Manteca CA 95336",
    "addr:housenumber":"243",
    "addr:postcode":"95336",
    "addr:street":"N Maple Ave",
    "iso:country":"US",
    "sg:address":"243 N Maple Ave",
    "sg:city":"Manteca",
    "sg:classifiers":[
        {
            "category":"Professional",
            "subcategory":"Business Services",
            "type":"Services"
        }
    ],
    "sg:phone":"+1 209 239 7377",
    "sg:postcode":"95336",
    "sg:province":"CA",
    "sg:tags":[
        "paralegal"
    ],
    "wof:name":"Hoot Paralegal Svc",
    "wof:placetype":"venue"
},
  "geometry": {"coordinates":[-121.217876,37.800183],"type":"Point"}
}