{
  "type": "Feature",
  "properties": {
    "iso:country":"US",
    "sg:address":"7083 Commerce Cir",
    "sg:city":"Pleasanton",
    "sg:classifiers":[
        {
            "category":"Shopping",
            "subcategory":"Clothing, Apparel, & Fashions",
            "type":"Retail Goods"
        }
    ],
    "sg:phone":"+1 925 730 1901",
    "sg:postcode":"94588",
    "sg:province":"CA",
    "sg:tags":[
        "theatrical",
        "costume"
    ],
    "wof:name":"Clicket",
    "wof:placetype":"venue"
},
  "geometry": {"coordinates":[-121.915725,37.698019],"type":"Point"}
}