{
  "type": "Feature",
  "properties": {
    "addr:full":"1100 Isabel St Burbank CA 91506",
    "addr:housenumber":"1100",
    "addr:postcode":"91506",
    "addr:street":"Isabel St",
    "iso:country":"US",
    "sg:address":"1100 Isabel St",
    "sg:city":"Burbank",
    "sg:classifiers":[
        {
            "category":"Building & Trades",
            "subcategory":"Construction",
            "type":"Services"
        }
    ],
    "sg:phone":"+1 818 973 1775",
    "sg:postcode":"91506",
    "sg:province":"CA",
    "sg:tags":[
        "contractor"
    ],
    "sg:website":"www.thunderstoneinc.com",
    "wof:name":"Thunderstone Granite & Marble",
    "wof:placetype":"venue"
},
  "geometry": {"coordinates":[-118.323393,34.182378],"type":"Point"}
}