{
  "type": "Feature",
  "properties": {
    "addr:full":"5880 W Jefferson Boulevard Los Angeles CA 90016",
    "addr:housenumber":"5880",
    "addr:postcode":"90016",
    "addr:street":"W Jefferson Boulevard",
    "iso:country":"US",
    "sg:address":"5880 W Jefferson Boulevard",
    "sg:city":"Los Angeles",
    "sg:classifiers":[
        {
            "category":"Shopping",
            "subcategory":"Department Store",
            "type":"Retail Goods"
        }
    ],
    "sg:phone":"+1 310 945 1300",
    "sg:postcode":"90016",
    "sg:province":"CA",
    "sg:website":"www.perryellis.com",
    "wof:name":"Perry Ellis",
    "wof:placetype":"venue"
},
  "geometry": {"coordinates":[-118.37705200000001,34.022723],"type":"Point"}
}