{
  "type": "Feature",
  "properties": {
    "iso:country":"US",
    "sg:address":"1155 Coast Blvd",
    "sg:city":"La Jolla",
    "sg:classifiers":[
        {
            "category":"Travel",
            "subcategory":"Hotels & Motels",
            "type":"Entertainment"
        }
    ],
    "sg:phone":"+1 858 459 2621",
    "sg:postcode":"92037",
    "sg:province":"CA",
    "sg:website":"www.lajollacove.com",
    "wof:name":"La Jolla Cove Suites",
    "wof:placetype":"venue"
},
  "geometry": {"coordinates":[-117.273003,32.849701],"type":"Point"}
}