{
  "type": "Feature",
  "properties": {
    "addr:full":"345 Franklin St San Francisco CA 94102",
    "addr:housenumber":"345",
    "addr:postcode":"94102",
    "addr:street":"Franklin St",
    "iso:country":"US",
    "sg:address":"345 Franklin St",
    "sg:city":"San Francisco",
    "sg:classifiers":[
        {
            "category":"Professional",
            "subcategory":"Lawyer & Legal Services",
            "type":"Services"
        }
    ],
    "sg:phone":"+1 415 241 2405",
    "sg:postcode":"94102",
    "sg:province":"CA",
    "sg:tags":[
        "attorney"
    ],
    "wof:name":"Ira A Freydkis",
    "wof:placetype":"venue"
},
  "geometry": {"coordinates":[-122.42143,37.777118],"type":"Point"}
}