{
  "type": "Feature",
  "properties": {
    "addr:full":"710 Escondido Ave Vista CA 92084",
    "addr:housenumber":"710",
    "addr:postcode":"92084",
    "addr:street":"Escondido Ave",
    "iso:country":"US",
    "sg:address":"710 Escondido Ave",
    "sg:city":"Vista",
    "sg:classifiers":[
        {
            "category":"Professional",
            "subcategory":"Business Services",
            "type":"Services"
        }
    ],
    "sg:phone":"+1 760 758 2142",
    "sg:postcode":"92084",
    "sg:province":"CA",
    "sg:tags":[
        "repairing",
        "sign"
    ],
    "wof:name":"Allied Sign & Lighting Co",
    "wof:placetype":"venue"
},
  "geometry": {"coordinates":[-117.23381000000001,33.195973],"type":"Point"}
}