{
  "type": "Feature",
  "properties": {
    "iso:country":"US",
    "sg:address":"2965 Quinto Way",
    "sg:city":"San Jose",
    "sg:classifiers":[
        {
            "category":"Organizations",
            "subcategory":"Religious Organization",
            "type":"Services"
        }
    ],
    "sg:phone":"+1 408 265 3267",
    "sg:postcode":"95124",
    "sg:province":"CA",
    "sg:tags":[
        "church"
    ],
    "wof:name":"Rivers Of Living Water",
    "wof:placetype":"venue"
},
  "geometry": {"coordinates":[-121.915638,37.269888],"type":"Point"}
}