{
  "type": "Feature",
  "properties": {
    "iso:country":"US",
    "sg:address":"2724 N Waterman Ave",
    "sg:city":"San Bernardino",
    "sg:classifiers":[
        {
            "category":"Real Estate",
            "subcategory":"Real Estate Agent",
            "type":"Services"
        }
    ],
    "sg:phone":"+1 909 883 8911",
    "sg:postcode":"92404",
    "sg:province":"CA",
    "wof:name":"Spellacy & Assoc Realtors Inc",
    "wof:placetype":"venue"
},
  "geometry": {"coordinates":[-117.278795,34.141278],"type":"Point"}
}