{
  "type": "Feature",
  "properties": {
    "iso:country":"US",
    "sg:address":"1055 Vista Dr",
    "sg:city":"Eureka",
    "sg:classifiers":[
        {
            "category":"Shopping",
            "subcategory":"Gifts & Souvenirs",
            "type":"Retail Goods"
        }
    ],
    "sg:phone":"+1 707 476 8661",
    "sg:postcode":"95503",
    "sg:province":"CA",
    "wof:name":"All Sports Basket",
    "wof:placetype":"venue"
},
  "geometry": {"coordinates":[-124.153863,40.769416],"type":"Point"}
}