{
  "type": "Feature",
  "properties": {
    "iso:country":"US",
    "sg:address":"6 Gumwood",
    "sg:city":"Irvine",
    "sg:classifiers":[
        {
            "category":"Shopping",
            "type":"Retail Goods"
        }
    ],
    "sg:phone":"+1 949 733 8891",
    "sg:postcode":"92612",
    "sg:province":"CA",
    "sg:tags":[
        "merchandise"
    ],
    "wof:name":"Art Showcase",
    "wof:placetype":"venue"
},
  "geometry": {"coordinates":[-117.800737,33.66078],"type":"Point"}
}