{
  "type": "Feature",
  "properties": {
    "iso:country":"US",
    "sg:address":"124 W Main St",
    "sg:city":"Visalia",
    "sg:classifiers":[
        {
            "category":"Shopping",
            "subcategory":"Clothing, Apparel, & Fashions",
            "type":"Retail Goods"
        }
    ],
    "sg:phone":"+1 559 735 0335",
    "sg:postcode":"93291",
    "sg:province":"CA",
    "sg:tags":[
        "shop",
        "bridal"
    ],
    "wof:name":"Apparel Gallery",
    "wof:placetype":"venue"
},
  "geometry": {"coordinates":[-119.293174,36.330224],"type":"Point"}
}