{
  "type": "Feature",
  "properties": {
    "addr:full":"1416 Solano St Corning CA 96021",
    "addr:housenumber":"1416",
    "addr:postcode":"96021",
    "addr:street":"Solano St",
    "iso:country":"US",
    "sg:address":"1416 Solano St",
    "sg:city":"Corning",
    "sg:classifiers":[
        {
            "category":"Health Services",
            "subcategory":"Hospital",
            "type":"Services"
        },
        {
            "category":"Health Services",
            "subcategory":"Chiropractor",
            "type":"Services"
        }
    ],
    "sg:phone":"+1 530 824 1719",
    "sg:postcode":"96021",
    "sg:province":"CA",
    "sg:tags":[
        "disorders-information",
        "sleep",
        "treatment",
        "chiropractic"
    ],
    "wof:name":"Olive Chiropractic",
    "wof:placetype":"venue"
},
  "geometry": {"coordinates":[-122.183849,39.927897],"type":"Point"}
}