{
  "type": "Feature",
  "properties": {
    "iso:country":"US",
    "sg:address":"693 E Sunny Dunes Rd",
    "sg:city":"Palm Springs",
    "sg:classifiers":[
        {
            "category":"Building & Trades",
            "subcategory":"Construction",
            "type":"Services"
        }
    ],
    "sg:phone":"+1 760 323 0220",
    "sg:postcode":"92264",
    "sg:province":"CA",
    "sg:tags":[
        "personal",
        "house"
    ],
    "wof:name":"CVMD Inc",
    "wof:placetype":"venue"
},
  "geometry": {"coordinates":[-116.539731,33.812178],"type":"Point"}
}