{
  "type": "Feature",
  "properties": {
    "iso:country":"US",
    "sg:address":"1501 el Camino Real",
    "sg:city":"Belmont",
    "sg:classifiers":[
        {
            "category":"Professional",
            "type":"Services"
        },
        {
            "category":"Personal",
            "type":"Services"
        }
    ],
    "sg:phone":"+1 650 654 6789",
    "sg:postcode":"94002",
    "sg:province":"CA",
    "sg:tags":[
        "therapist",
        "massage"
    ],
    "wof:name":"Healing Hands",
    "wof:placetype":"venue"
},
  "geometry": {"coordinates":[-122.271558,37.516916],"type":"Point"}
}