{
  "type": "Feature",
  "properties": {
    "addr:full":"324 Lang Road Burlingame CA 94010",
    "addr:housenumber":"324",
    "addr:postcode":"94010",
    "addr:street":"Lang Road",
    "iso:country":"US",
    "sg:address":"324 Lang Road",
    "sg:city":"Burlingame",
    "sg:classifiers":[
        {
            "category":"Building & Trades",
            "subcategory":"Construction",
            "type":"Services"
        }
    ],
    "sg:phone":"+1 650 558 8314",
    "sg:postcode":"94010",
    "sg:province":"CA",
    "sg:tags":[
        "contractor"
    ],
    "wof:name":"Vanguard Construction",
    "wof:placetype":"venue"
},
  "geometry": {"coordinates":[-122.33601400000001,37.58727],"type":"Point"}
}