{
  "type": "Feature",
  "properties": {
    "addr:full":"8523 Reseda Blvd Northridge CA 91324",
    "addr:housenumber":"8523",
    "addr:postcode":"91324",
    "addr:street":"Reseda Blvd",
    "iso:country":"US",
    "sg:address":"8523 Reseda Blvd",
    "sg:city":"Northridge",
    "sg:classifiers":[
        {
            "category":"Communications",
            "subcategory":"Film & Video Production",
            "type":"Services"
        }
    ],
    "sg:phone":"+1 818 885 6501",
    "sg:postcode":"91324",
    "sg:province":"CA",
    "sg:tags":[
        "taping"
    ],
    "wof:name":"Film & Video Transfers Inc",
    "wof:placetype":"venue"
},
  "geometry": {"coordinates":[-118.53615499999999,34.224747],"type":"Point"}
}