{
  "type": "Feature",
  "properties": {
    "addr:full":"4405 Cushing Pkwy Fremont CA 94538",
    "addr:housenumber":"4405",
    "addr:postcode":"94538",
    "addr:street":"Cushing Pkwy",
    "iso:country":"US",
    "sg:address":"4405 Cushing Pkwy",
    "sg:city":"Fremont",
    "sg:classifiers":[
        {
            "category":"Wholesale",
            "subcategory":"Medical Equipment & Supplies",
            "type":"Manufacturing & Wholesale Goods"
        }
    ],
    "sg:phone":"+1 510 668 5100",
    "sg:postcode":"94538",
    "sg:province":"CA",
    "sg:website":"http://www.delta-corp.com",
    "wof:name":"Delta Products Corp",
    "wof:placetype":"venue"
},
  "geometry": {"coordinates":[-121.952617,37.489878],"type":"Point"}
}