{
  "type": "Feature",
  "properties": {
    "addr:full":"325 E Hillcrest Dr Thousand Oaks CA 91360",
    "addr:housenumber":"325",
    "addr:postcode":"91360",
    "addr:street":"E Hillcrest Dr",
    "iso:country":"US",
    "sg:address":"325 E Hillcrest Dr",
    "sg:city":"Thousand Oaks",
    "sg:classifiers":[
        {
            "category":"Professional",
            "type":"Services"
        }
    ],
    "sg:phone":"+1 805 379 2244",
    "sg:postcode":"91360",
    "sg:province":"CA",
    "wof:name":"Romac International",
    "wof:placetype":"venue"
},
  "geometry": {"coordinates":[-118.871323,34.181324],"type":"Point"}
}