{
  "type": "Feature",
  "properties": {
    "addr:full":"229 G St Davis CA 95616",
    "addr:housenumber":"229",
    "addr:postcode":"95616",
    "addr:street":"G St",
    "iso:country":"US",
    "sg:address":"229 G St",
    "sg:city":"Davis",
    "sg:classifiers":[
        {
            "category":"Restaurant",
            "type":"Food & Drink"
        }
    ],
    "sg:phone":"+1 530 753 5750",
    "sg:postcode":"95616",
    "sg:province":"CA",
    "wof:name":"Sunrise Restaurant",
    "wof:placetype":"venue"
},
  "geometry": {"coordinates":[-121.739243,38.544527],"type":"Point"}
}