{
  "type": "Feature",
  "properties": {
    "iso:country":"US",
    "sg:address":"1639 Ridge Rd",
    "sg:city":"Vista",
    "sg:classifiers":[
        {
            "category":"Organizations",
            "subcategory":"Religious Organization",
            "type":"Services"
        }
    ],
    "sg:phone":"+1 760 945 0107",
    "sg:postcode":"92081",
    "sg:province":"CA",
    "sg:tags":[
        "church"
    ],
    "wof:name":"Apostolic Christian Church",
    "wof:placetype":"venue"
},
  "geometry": {"coordinates":[-117.264843,33.17944],"type":"Point"}
}