{
  "type": "Feature",
  "properties": {
    "addr:full":"745 E. Valley Blvd., #518 San Gabriel CA 91776",
    "addr:housenumber":"745",
    "addr:postcode":"91776",
    "addr:street":"E. Valley Blvd. # 518",
    "iso:country":"US",
    "sg:address":"745 E. Valley Blvd., #518",
    "sg:city":"San Gabriel",
    "sg:classifiers":[
        {
            "category":"Professional",
            "subcategory":"Detective & Security Services",
            "type":"Services"
        }
    ],
    "sg:phone":"+1 626 285 9178",
    "sg:postcode":"91776",
    "sg:province":"CA",
    "sg:tags":[
        "system"
    ],
    "sg:website":"www.earl-security.com",
    "wof:name":"EARL Security, Inc.",
    "wof:placetype":"venue"
},
  "geometry": {"coordinates":[-118.091093,34.080166],"type":"Point"}
}