{
  "type": "Feature",
  "properties": {
    "addr:full":"3030 Oak St Santa Ana CA 92707",
    "addr:housenumber":"3030",
    "addr:postcode":"92707",
    "addr:street":"Oak St",
    "iso:country":"US",
    "sg:address":"3030 Oak St",
    "sg:city":"Santa Ana",
    "sg:classifiers":[
        {
            "category":"Wholesale",
            "subcategory":"Machinery & Supplies",
            "type":"Manufacturing & Wholesale Goods"
        }
    ],
    "sg:phone":"+1 714 754 0551",
    "sg:postcode":"92707",
    "sg:province":"CA",
    "sg:tags":[
        "taps",
        "bit",
        "drill"
    ],
    "wof:name":"Adams Supply",
    "wof:placetype":"venue"
},
  "geometry": {"coordinates":[-117.863204,33.70661],"type":"Point"}
}