{
  "type": "Feature",
  "properties": {
    "iso:country":"US",
    "sg:address":"222 N. Sepulveda Blvd., Suite 2000",
    "sg:city":"El Segundo",
    "sg:classifiers":[
        {
            "category":"Professional",
            "type":"Services"
        }
    ],
    "sg:phone":"+1 310 645 2875",
    "sg:postcode":"90245",
    "sg:province":"CA",
    "sg:website":"www.dependablerights.com",
    "wof:name":"Dependable Solutions, Inc.",
    "wof:placetype":"venue"
},
  "geometry": {"coordinates":[-118.394836,33.918882],"type":"Point"}
}