{
  "type": "Feature",
  "properties": {
    "addr:full":"3418 Long Beach Blvd Long Beach CA 90807",
    "addr:housenumber":"3418",
    "addr:postcode":"90807",
    "addr:street":"Long Beach Blvd",
    "iso:country":"US",
    "sg:address":"3418 Long Beach Blvd",
    "sg:city":"Long Beach",
    "sg:classifiers":[
        {
            "category":"Restaurant",
            "type":"Food & Drink"
        }
    ],
    "sg:phone":"+1 562 426 8200",
    "sg:postcode":"90807",
    "sg:province":"CA",
    "sg:tags":[
        "mexican"
    ],
    "wof:name":"Ernesto's Mexican Grill",
    "wof:placetype":"venue"
},
  "geometry": {"coordinates":[-118.189154,33.819253],"type":"Point"}
}