{
  "type": "Feature",
  "properties": {
    "iso:country":"US",
    "sg:address":"14117 Lambert Rd",
    "sg:city":"Whittier",
    "sg:classifiers":[
        {
            "category":"Professional",
            "subcategory":"Accounting & Tax Preparation",
            "type":"Services"
        }
    ],
    "sg:phone":"+1 562 696 2358",
    "sg:postcode":"90605",
    "sg:province":"CA",
    "sg:tags":[
        "return",
        "filing"
    ],
    "wof:name":"Maria's Income Tax",
    "wof:placetype":"venue"
},
  "geometry": {"coordinates":[-118.026009,33.95005],"type":"Point"}
}