{
  "type": "Feature",
  "properties": {
    "iso:country":"US",
    "sg:address":"2109 W Compton Blvd",
    "sg:city":"Compton",
    "sg:classifiers":[
        {
            "category":"Insurance",
            "subcategory":"Hazard Insurance",
            "type":"Services"
        }
    ],
    "sg:phone":"+1 310 764 2500",
    "sg:postcode":"90220",
    "sg:province":"CA",
    "sg:tags":[
        "bond"
    ],
    "wof:name":"Donald Sullivan Bail Bonds",
    "wof:placetype":"venue"
},
  "geometry": {"coordinates":[-118.254181,33.89584],"type":"Point"}
}