{
  "type": "Feature",
  "properties": {
    "iso:country":"US",
    "sg:address":"7310 Home Leisure Plz",
    "sg:city":"Sacramento",
    "sg:classifiers":[
        {
            "category":"Home & Garden",
            "subcategory":"Building Materials",
            "type":"Retail Goods"
        }
    ],
    "sg:phone":"+1 916 681 2588",
    "sg:postcode":"95823",
    "sg:province":"CA",
    "sg:tags":[
        "paint"
    ],
    "wof:name":"Vista Paint Window & Wlcvrngs",
    "wof:placetype":"venue"
},
  "geometry": {"coordinates":[-121.43999599999999,38.491046],"type":"Point"}
}