{
  "type": "Feature",
  "properties": {
    "addr:full":"19256 Cottonwood Dr Apple Valley CA 92308",
    "addr:housenumber":"19256",
    "addr:postcode":"92308",
    "addr:street":"Cottonwood Dr",
    "iso:country":"US",
    "sg:address":"19256 Cottonwood Dr",
    "sg:city":"Apple Valley",
    "sg:classifiers":[
        {
            "category":"Organizations",
            "subcategory":"Non-profit Organization",
            "type":"Services"
        }
    ],
    "sg:phone":"+1 760 240 4147",
    "sg:postcode":"92308",
    "sg:province":"CA",
    "sg:tags":[
        "social"
    ],
    "wof:name":"National Society of Daugh",
    "wof:placetype":"venue"
},
  "geometry": {"coordinates":[-117.242914,34.464722],"type":"Point"}
}