{
  "type": "Feature",
  "properties": {
    "iso:country":"US",
    "sg:address":"636 E Garvey Ave",
    "sg:city":"Monterey Park",
    "sg:classifiers":[
        {
            "category":"Retail",
            "subcategory":"Laundry & Dry Cleaning",
            "type":"Services"
        }
    ],
    "sg:phone":"+1 626 288 6513",
    "sg:postcode":"91755",
    "sg:province":"CA",
    "wof:name":"Norge Cleaners",
    "wof:placetype":"venue"
},
  "geometry": {"coordinates":[-118.112999,34.062401],"type":"Point"}
}