{
  "type": "Feature",
  "properties": {
    "iso:country":"US",
    "sg:address":"790 E Colorado Blvd",
    "sg:city":"Pasadena",
    "sg:classifiers":[
        {
            "category":"Professional",
            "subcategory":"Lawyer & Legal Services",
            "type":"Services"
        }
    ],
    "sg:phone":"+1 626 397 2745",
    "sg:postcode":"91106",
    "sg:province":"CA",
    "sg:tags":[
        "attorney"
    ],
    "sg:website":"www.risleylaw.com",
    "wof:name":"Robert L Risley Law Offices",
    "wof:placetype":"venue"
},
  "geometry": {"coordinates":[-118.134854,34.145806],"type":"Point"}
}