{
  "type": "Feature",
  "properties": {
    "iso:country":"US",
    "sg:address":"3052 Clairemont Dr",
    "sg:city":"San Diego",
    "sg:classifiers":[
        {
            "category":"Professional",
            "subcategory":"Advertising",
            "type":"Services"
        }
    ],
    "sg:phone":"+1 619 276 2279",
    "sg:postcode":"92117",
    "sg:province":"CA",
    "sg:tags":[
        "mail"
    ],
    "sg:website":"www.autofavor.com",
    "wof:name":"Automotive Advantage",
    "wof:placetype":"venue"
},
  "geometry": {"coordinates":[-117.193994,32.794622],"type":"Point"}
}