{
  "type": "Feature",
  "properties": {
    "iso:country":"US",
    "sg:address":"2580 San Pablo Ave",
    "sg:city":"Oakland",
    "sg:classifiers":[
        {
            "category":"Insurance",
            "subcategory":"Health Insurance",
            "type":"Services"
        }
    ],
    "sg:phone":"+1 510 444 9155",
    "sg:postcode":"94612",
    "sg:province":"CA",
    "sg:tags":[
        "plans-information",
        "referral"
    ],
    "wof:name":"Save A Life Wellness Center",
    "wof:placetype":"venue"
},
  "geometry": {"coordinates":[-122.275204,37.816711],"type":"Point"}
}