{
  "type": "Feature",
  "properties": {
    "iso:country":"US",
    "sg:address":"2078 Sunset Dr",
    "sg:city":"Pacific Grove",
    "sg:classifiers":[
        {
            "category":"Home & Garden",
            "subcategory":"Home Furnishings",
            "type":"Retail Goods"
        }
    ],
    "sg:phone":"+1 831 372 8867",
    "sg:postcode":"93950",
    "sg:province":"CA",
    "sg:tags":[
        "pottery"
    ],
    "sg:website":"www.penpots.com",
    "wof:name":"Peninsula Potters",
    "wof:placetype":"venue"
},
  "geometry": {"coordinates":[-121.933888,36.615757],"type":"Point"}
}