{
  "type": "Feature",
  "properties": {
    "iso:country":"US",
    "sg:address":"18559 Northridge Dr",
    "sg:city":"Salinas",
    "sg:classifiers":[
        {
            "category":"Utilities",
            "subcategory":"Fuel Oil & Lpg",
            "type":"Services"
        }
    ],
    "sg:phone":"+1 831 444 6660",
    "sg:postcode":"93906",
    "sg:province":"CA",
    "sg:tags":[
        "firewood"
    ],
    "wof:name":"Firewood Express",
    "wof:placetype":"venue"
},
  "geometry": {"coordinates":[-121.649225,36.722226],"type":"Point"}
}