{
  "type": "Feature",
  "properties": {
    "iso:country":"US",
    "sg:address":"1541 Skyline Dr",
    "sg:city":"South Lake Tahoe",
    "sg:classifiers":[
        {
            "category":"Real Estate",
            "subcategory":"Architect",
            "type":"Services"
        }
    ],
    "sg:phone":"+1 530 577 2710",
    "sg:postcode":"96150",
    "sg:province":"CA",
    "wof:name":"Mark Allione",
    "wof:placetype":"venue"
},
  "geometry": {"coordinates":[-119.99867399999999,38.868649],"type":"Point"}
}