{
  "type": "Feature",
  "properties": {
    "addr:full":"9460 Brighton Way Beverly Hills CA 90210",
    "addr:housenumber":"9460",
    "addr:postcode":"90210",
    "addr:street":"Brighton Way",
    "iso:country":"US",
    "sg:address":"9460 Brighton Way",
    "sg:city":"Beverly Hills",
    "sg:classifiers":[
        {
            "category":"Shopping",
            "type":"Retail Goods"
        }
    ],
    "sg:phone":"+1 310 288 9700",
    "sg:postcode":"90210",
    "sg:province":"CA",
    "sg:website":"www.paper-source.com",
    "wof:name":"Paper Source",
    "wof:placetype":"venue"
},
  "geometry": {"coordinates":[-118.402,34.069801],"type":"Point"}
}