{
  "type": "Feature",
  "properties": {
    "addr:full":"3919 E Guasti Rd Ontario CA 91761",
    "addr:housenumber":"3919",
    "addr:postcode":"91761",
    "addr:street":"E Guasti Rd",
    "iso:country":"US",
    "sg:address":"3919 E Guasti Rd",
    "sg:city":"Ontario",
    "sg:classifiers":[
        {
            "category":"Wholesale",
            "subcategory":"Furniture",
            "type":"Manufacturing & Wholesale Goods"
        }
    ],
    "sg:phone":"+1 909 605 0511",
    "sg:postcode":"91761",
    "sg:province":"CA",
    "wof:name":"Suhlim Gas Spindle Corp",
    "wof:placetype":"venue"
},
  "geometry": {"coordinates":[-117.561983,34.063953],"type":"Point"}
}