{
  "type": "Feature",
  "properties": {
    "iso:country":"US",
    "sg:address":"9112 W Pico Boulevard",
    "sg:city":"Los Angeles",
    "sg:classifiers":[
        {
            "category":"Shopping",
            "subcategory":"Beauty & Cosmetics",
            "type":"Retail Goods"
        }
    ],
    "sg:phone":"+1 310 246 0918",
    "sg:postcode":"90035",
    "sg:province":"CA",
    "sg:tags":[
        "supply"
    ],
    "wof:name":"Bait Miryam",
    "wof:placetype":"venue"
},
  "geometry": {"coordinates":[-118.390416,34.055379],"type":"Point"}
}