{
  "type": "Feature",
  "properties": {
    "addr:full":"22912 Pacific Park Dr Ste A Aliso Viejo CA 92656",
    "addr:housenumber":"22912",
    "addr:postcode":"92656",
    "addr:street":"Pacific Park Dr Ste A",
    "iso:country":"US",
    "sg:address":"22912 Pacific Park Dr Ste A",
    "sg:city":"Aliso Viejo",
    "sg:classifiers":[
        {
            "category":"Health Services",
            "subcategory":"Dentist",
            "type":"Services"
        }
    ],
    "sg:phone":"+1 949 716 6900",
    "sg:postcode":"92656",
    "sg:province":"CA",
    "sg:website":"www.allsmiledentalgroup.com",
    "wof:name":"AllSmile Dental Group",
    "wof:placetype":"venue"
},
  "geometry": {"coordinates":[-117.730237,33.570516],"type":"Point"}
}