{
  "type": "Feature",
  "properties": {
    "addr:full":"358 Noe St San Francisco CA 94114",
    "addr:housenumber":"358",
    "addr:postcode":"94114",
    "addr:street":"Noe St",
    "iso:country":"US",
    "sg:address":"358 Noe St",
    "sg:city":"San Francisco",
    "sg:classifiers":[
        {
            "category":"Professional",
            "subcategory":"Management & Consulting",
            "type":"Services"
        }
    ],
    "sg:phone":"+1 415 503 1375",
    "sg:postcode":"94114",
    "sg:province":"CA",
    "sg:tags":[
        "counselor",
        "public",
        "relations"
    ],
    "wof:name":"Sullivan Communications Inc",
    "wof:placetype":"venue"
},
  "geometry": {"coordinates":[-122.43309600000001,37.763545],"type":"Point"}
}