{
  "type": "Feature",
  "properties": {
    "iso:country":"US",
    "sg:address":"328 S Atlantic Blvd Ste 201",
    "sg:city":"Monterey Park",
    "sg:classifiers":[
        {
            "category":"Health Services",
            "subcategory":"Dentist",
            "type":"Services"
        }
    ],
    "sg:phone":"+1 626 300 8339",
    "sg:postcode":"91754",
    "sg:province":"CA",
    "wof:name":"Sun Hai DDS Dental Office",
    "wof:placetype":"venue"
},
  "geometry": {"coordinates":[-118.13400300000001,34.059601],"type":"Point"}
}