{
  "type": "Feature",
  "properties": {
    "iso:country":"US",
    "sg:address":"712 S Olive St",
    "sg:city":"Los Angeles",
    "sg:classifiers":[
        {
            "category":"Shopping",
            "subcategory":"Jewelry",
            "type":"Retail Goods"
        }
    ],
    "sg:phone":"+1 213 627 5435",
    "sg:postcode":"90014",
    "sg:province":"CA",
    "sg:tags":[
        "jeweler"
    ],
    "wof:name":"Petrosyan Jewelry",
    "wof:placetype":"venue"
},
  "geometry": {"coordinates":[-118.256669,34.045292],"type":"Point"}
}