{
  "type": "Feature",
  "properties": {
    "addr:full":"8740 S Sepulveda Blvd Los Angeles CA 90045",
    "addr:housenumber":"8740",
    "addr:postcode":"90045",
    "addr:street":"S Sepulveda Blvd",
    "iso:country":"US",
    "sg:address":"8740 S Sepulveda Blvd",
    "sg:city":"Los Angeles",
    "sg:classifiers":[
        {
            "category":"Real Estate",
            "subcategory":"Real Estate Agent",
            "type":"Services"
        }
    ],
    "sg:phone":"+1 310 337 7696",
    "sg:postcode":"90045",
    "sg:province":"CA",
    "wof:name":"Manchester Realty Co",
    "wof:placetype":"venue"
},
  "geometry": {"coordinates":[-118.39605400000001,33.959052],"type":"Point"}
}