{
  "type": "Feature",
  "properties": {
    "addr:full":"28028 Sea Lane Dr Malibu CA 90265",
    "addr:housenumber":"28028",
    "addr:postcode":"90265",
    "addr:street":"Sea Lane Dr",
    "iso:country":"US",
    "sg:address":"28028 Sea Lane Dr",
    "sg:city":"Malibu",
    "sg:classifiers":[
        {
            "category":"Real Estate",
            "subcategory":"Real Estate Operator",
            "type":"Services"
        }
    ],
    "sg:phone":"+1 310 471 7200",
    "sg:postcode":"90265",
    "sg:province":"CA",
    "sg:tags":[
        "owner",
        "commercial"
    ],
    "wof:name":"Nordhoff Associates",
    "wof:placetype":"venue"
},
  "geometry": {"coordinates":[-118.78357099999999,34.024465],"type":"Point"}
}