{
  "type": "Feature",
  "properties": {
    "addr:full":"18003 Sky Park Cir Suite A Irvine CA 92614",
    "addr:housenumber":"18003",
    "addr:postcode":"92614",
    "addr:street":"Sky Park Cir Suite A",
    "iso:country":"US",
    "sg:address":"18003 Sky Park Cir Suite A",
    "sg:city":"Irvine",
    "sg:classifiers":[
        {
            "category":"Professional",
            "type":"Services"
        }
    ],
    "sg:phone":"+1 866 733 5775",
    "sg:postcode":"92614",
    "sg:province":"CA",
    "sg:tags":[
        "caterer"
    ],
    "sg:website":"http://orangecounty.citysearch.com/profile/external/47395707/irvine_ca/labite_com.html?publisher=yellowpages&reference_id=1&placement=ypwebsitemip",
    "wof:name":"LAbite.com",
    "wof:placetype":"venue"
},
  "geometry": {"coordinates":[-117.85852800000001,33.68861],"type":"Point"}
}