{
  "type": "Feature",
  "properties": {
    "iso:country":"US",
    "sg:address":"2550 Barrington Ct",
    "sg:city":"Hayward",
    "sg:classifiers":[
        {
            "category":"Professional",
            "subcategory":"Business Services",
            "type":"Services"
        }
    ],
    "sg:phone":"+1 510 259 0482",
    "sg:postcode":"94545",
    "sg:province":"CA",
    "sg:tags":[
        "organizing",
        "services-household"
    ],
    "wof:name":"Starzz Management Services",
    "wof:placetype":"venue"
},
  "geometry": {"coordinates":[-122.140793,37.655451],"type":"Point"}
}