{
  "type": "Feature",
  "properties": {
    "addr:full":"4915 5th St Fallbrook CA 92028",
    "addr:housenumber":"4915",
    "addr:postcode":"92028",
    "addr:street":"5Th St",
    "iso:country":"US",
    "sg:address":"4915 5th St",
    "sg:city":"Fallbrook",
    "sg:classifiers":[
        {
            "category":"Wholesale",
            "subcategory":"Plants",
            "type":"Manufacturing & Wholesale Goods"
        }
    ],
    "sg:phone":"+1 760 723 2301",
    "sg:postcode":"92028",
    "sg:province":"CA",
    "sg:tags":[
        "nursery",
        "tree"
    ],
    "wof:name":"R Z Nursery",
    "wof:placetype":"venue"
},
  "geometry": {"coordinates":[-117.154206,33.413777],"type":"Point"}
}