{
  "type": "Feature",
  "properties": {
    "iso:country":"US",
    "sg:address":"2095 N Indian Canyon Dr",
    "sg:city":"Palm Springs",
    "sg:classifiers":[
        {
            "category":"Health Services",
            "subcategory":"Doctor",
            "type":"Services"
        },
        {
            "category":"Health Services",
            "subcategory":"Clinic",
            "type":"Services"
        }
    ],
    "sg:phone":"+1 877 345 8494",
    "sg:postcode":"92262",
    "sg:province":"CA",
    "sg:tags":[
        "counseling",
        "mental",
        "psychiatrist"
    ],
    "sg:website":"www.michaelshouse.com/",
    "wof:name":"Michael's House",
    "wof:placetype":"venue"
},
  "geometry": {"coordinates":[-116.54598,33.848198],"type":"Point"}
}