{
  "type": "Feature",
  "properties": {
    "addr:full":"27611 Miami Ave Hayward CA 94545",
    "addr:housenumber":"27611",
    "addr:postcode":"94545",
    "addr:street":"Miami Ave",
    "iso:country":"US",
    "sg:address":"27611 Miami Ave",
    "sg:city":"Hayward",
    "sg:classifiers":[
        {
            "category":"Building & Trades",
            "subcategory":"Cleaning & Sanitation",
            "type":"Services"
        }
    ],
    "sg:phone":"+1 510 784 9996",
    "sg:postcode":"94545",
    "sg:province":"CA",
    "sg:tags":[
        "chemical"
    ],
    "wof:name":"Nalfleet Inc",
    "wof:placetype":"venue"
},
  "geometry": {"coordinates":[-122.08432500000001,37.627357],"type":"Point"}
}