{
  "type": "Feature",
  "properties": {
    "iso:country":"US",
    "sg:address":"7324 Pacific Blvd",
    "sg:city":"Huntington Park",
    "sg:classifiers":[
        {
            "category":"Education",
            "subcategory":"Special Training",
            "type":"Public Place"
        }
    ],
    "sg:phone":"+1 323 589 5089",
    "sg:postcode":"90255",
    "sg:province":"CA",
    "sg:tags":[
        "school",
        "language"
    ],
    "wof:name":"Ingles Conversacional Usa",
    "wof:placetype":"venue"
},
  "geometry": {"coordinates":[-118.225061,33.973146],"type":"Point"}
}