{
  "type": "Feature",
  "properties": {
    "iso:country":"US",
    "sg:address":"409 8th St",
    "sg:city":"Oakland",
    "sg:classifiers":[
        {
            "category":"Personal",
            "subcategory":"Beauty Salon",
            "type":"Services"
        }
    ],
    "sg:phone":"+1 510 835 7730",
    "sg:postcode":"94607",
    "sg:province":"CA",
    "sg:tags":[
        "hair",
        "stylist"
    ],
    "wof:name":"Best Hair Design",
    "wof:placetype":"venue"
},
  "geometry": {"coordinates":[-122.272728,37.799791],"type":"Point"}
}