{
  "type": "Feature",
  "properties": {
    "addr:full":"3650 Clairemont Dr San Diego CA 92117",
    "addr:housenumber":"3650",
    "addr:postcode":"92117",
    "addr:street":"Clairemont Dr",
    "iso:country":"US",
    "sg:address":"3650 Clairemont Dr",
    "sg:city":"San Diego",
    "sg:classifiers":[
        {
            "category":"Real Estate",
            "subcategory":"Real Estate Agent",
            "type":"Services"
        }
    ],
    "sg:phone":"+1 858 581 2588",
    "sg:postcode":"92117",
    "sg:province":"CA",
    "wof:name":"Barry E Fowler",
    "wof:placetype":"venue"
},
  "geometry": {"coordinates":[-117.20099399999999,32.805902],"type":"Point"}
}