{
  "type": "Feature",
  "properties": {
    "addr:full":"303 W Katella Ave Frnt Orange CA 92867",
    "addr:housenumber":"303",
    "addr:postcode":"92867",
    "addr:street":"W Katella Ave",
    "iso:country":"US",
    "sg:address":"303 W Katella Ave Frnt",
    "sg:city":"Orange",
    "sg:classifiers":[
        {
            "category":"Banks & Credit Unions",
            "subcategory":"Bank",
            "type":"Services"
        }
    ],
    "sg:phone":"+1 714 771 2700",
    "sg:postcode":"92867",
    "sg:province":"CA",
    "wof:name":"U S Bank",
    "wof:placetype":"venue"
},
  "geometry": {"coordinates":[-117.855003,33.8092],"type":"Point"}
}