{
  "type": "Feature",
  "properties": {
    "addr:full":"2000 Alameda de Las Pulgas San Mateo CA 94403",
    "addr:housenumber":"2000",
    "addr:postcode":"94403",
    "addr:street":"Alameda De Las Pulgas",
    "iso:country":"US",
    "sg:address":"2000 Alameda de Las Pulgas",
    "sg:city":"San Mateo",
    "sg:classifiers":[
        {
            "category":"Insurance",
            "subcategory":"Insurance Agent",
            "type":"Services"
        }
    ],
    "sg:phone":"+1 650 655 3750",
    "sg:postcode":"94403",
    "sg:province":"CA",
    "sg:website":"www.ta-retirement.com",
    "wof:name":"Transamerica Insurance",
    "wof:placetype":"venue"
},
  "geometry": {"coordinates":[-122.322636,37.54687],"type":"Point"}
}