{
  "type": "Feature",
  "properties": {
    "addr:full":"10440 S De Anza Blvd Ste D4 Cupertino CA 95014",
    "addr:housenumber":"10440",
    "addr:postcode":"95014",
    "addr:street":"S De Anza Blvd Ste D4",
    "iso:country":"US",
    "sg:address":"10440 S De Anza Blvd Ste D4",
    "sg:city":"Cupertino",
    "sg:classifiers":[
        {
            "category":"Health Services",
            "subcategory":"Optometrist",
            "type":"Services"
        }
    ],
    "sg:phone":"+1 408 446 3937",
    "sg:postcode":"95014",
    "sg:province":"CA",
    "wof:name":"Shao Benny OD",
    "wof:placetype":"venue"
},
  "geometry": {"coordinates":[-122.031998,37.317101],"type":"Point"}
}