{
  "type": "Feature",
  "properties": {
    "iso:country":"US",
    "sg:address":"17740 Retrac Way",
    "sg:city":"Grass Valley",
    "sg:classifiers":[
        {
            "category":"Building & Trades",
            "subcategory":"Landscaping Services",
            "type":"Services"
        }
    ],
    "sg:phone":"+1 530 268 2137",
    "sg:postcode":"95949",
    "sg:province":"CA",
    "wof:name":"Green Leaf Tree Care",
    "wof:placetype":"venue"
},
  "geometry": {"coordinates":[-121.091292,39.110692],"type":"Point"}
}