{
  "type": "Feature",
  "properties": {
    "addr:full":"541 Jefferson Ave Redwood City CA 94063",
    "addr:housenumber":"541",
    "addr:postcode":"94063",
    "addr:street":"Jefferson Ave",
    "iso:country":"US",
    "sg:address":"541 Jefferson Ave",
    "sg:city":"Redwood City",
    "sg:classifiers":[
        {
            "category":"Manufacturing",
            "subcategory":"Printing",
            "type":"Manufacturing & Wholesale Goods"
        }
    ],
    "sg:phone":"+1 650 622 3020",
    "sg:postcode":"94063",
    "sg:province":"CA",
    "sg:tags":[
        "publisher",
        "software"
    ],
    "wof:name":"Cotagesoft",
    "wof:placetype":"venue"
},
  "geometry": {"coordinates":[-122.228272,37.4889],"type":"Point"}
}