{
  "type": "Feature",
  "properties": {
    "iso:country":"US",
    "sg:address":"2741 W Lincoln Ave",
    "sg:city":"Anaheim",
    "sg:classifiers":[
        {
            "category":"Restaurant",
            "type":"Food & Drink"
        }
    ],
    "sg:phone":"+1 714 229 9730",
    "sg:postcode":"92801",
    "sg:province":"CA",
    "sg:tags":[
        "indian",
        "halal",
        "chinese"
    ],
    "wof:name":"DJ Indian Chinese Restaurant",
    "wof:placetype":"venue"
},
  "geometry": {"coordinates":[-117.98209799999999,33.832243],"type":"Point"}
}