{
  "type": "Feature",
  "properties": {
    "iso:country":"US",
    "sg:address":"3201 Corte Melpaso",
    "sg:city":"Camarillo",
    "sg:classifiers":[
        {
            "category":"Professional",
            "subcategory":"Art Services",
            "type":"Services"
        }
    ],
    "sg:phone":"+1 805 388 7060",
    "sg:postcode":"93012",
    "sg:province":"CA",
    "sg:tags":[
        "graphic",
        "designer"
    ],
    "wof:name":"MD 2",
    "wof:placetype":"venue"
},
  "geometry": {"coordinates":[-119.026796,34.222184],"type":"Point"}
}