{
  "type": "Feature",
  "properties": {
    "addr:full":"1868 Clayton Way Concord CA 94519",
    "addr:housenumber":"1868",
    "addr:postcode":"94519",
    "addr:street":"Clayton Way",
    "iso:country":"US",
    "sg:address":"1868 Clayton Way",
    "sg:city":"Concord",
    "sg:classifiers":[
        {
            "category":"Professional",
            "subcategory":"Computer Services",
            "type":"Services"
        }
    ],
    "sg:phone":"+1 925 798 8441",
    "sg:postcode":"94519",
    "sg:province":"CA",
    "sg:tags":[
        "website",
        "design"
    ],
    "wof:name":"Hazan Enterprises",
    "wof:placetype":"venue"
},
  "geometry": {"coordinates":[-122.009086,37.983022],"type":"Point"}
}