{
  "type": "Feature",
  "properties": {
    "iso:country":"US",
    "sg:address":"3231 University Ave",
    "sg:city":"San Diego",
    "sg:classifiers":[
        {
            "category":"Retail",
            "subcategory":"Auto Repair",
            "type":"Services"
        }
    ],
    "sg:phone":"+1 619 280 5943",
    "sg:postcode":"92104",
    "sg:province":"CA",
    "sg:tags":[
        "repairing",
        "automobile"
    ],
    "wof:name":"Nutek Auto Repair Shop",
    "wof:placetype":"venue"
},
  "geometry": {"coordinates":[-117.124501,32.748408],"type":"Point"}
}