{
  "type": "Feature",
  "properties": {
    "addr:full":"110 Hillcrest Blvd Millbrae CA 94030",
    "addr:housenumber":"110",
    "addr:postcode":"94030",
    "addr:street":"Hillcrest Blvd",
    "iso:country":"US",
    "sg:address":"110 Hillcrest Blvd",
    "sg:city":"Millbrae",
    "sg:classifiers":[
        {
            "category":"Retail",
            "subcategory":"Laundry & Dry Cleaning",
            "type":"Services"
        }
    ],
    "sg:phone":"+1 650 697 5174",
    "sg:postcode":"94030",
    "sg:province":"CA",
    "sg:tags":[
        "cleaners"
    ],
    "wof:name":"Jiffy Cleaners",
    "wof:placetype":"venue"
},
  "geometry": {"coordinates":[-122.393278,37.601141],"type":"Point"}
}