{
  "type": "Feature",
  "properties": {
    "addr:full":"7901 Freeport Blvd Sacramento CA 95832",
    "addr:housenumber":"7901",
    "addr:postcode":"95832",
    "addr:street":"Freeport Blvd",
    "iso:country":"US",
    "sg:address":"7901 Freeport Blvd",
    "sg:city":"Sacramento",
    "sg:classifiers":[
        {
            "category":"Professional",
            "subcategory":"Computer Services",
            "type":"Services"
        }
    ],
    "sg:phone":"+1 916 665 3200",
    "sg:postcode":"95832",
    "sg:province":"CA",
    "sg:tags":[
        "datum",
        "facility"
    ],
    "wof:name":"Verizon",
    "wof:placetype":"venue"
},
  "geometry": {"coordinates":[-121.502835,38.465554],"type":"Point"}
}