{
  "type": "Feature",
  "properties": {
    "addr:full":"1060 G St Reedley CA 93654",
    "addr:housenumber":"1060",
    "addr:postcode":"93654",
    "addr:street":"G St",
    "iso:country":"US",
    "sg:address":"1060 G St",
    "sg:city":"Reedley",
    "sg:classifiers":[
        {
            "category":"Insurance",
            "subcategory":"Insurance Agent",
            "type":"Services"
        }
    ],
    "sg:phone":"+1 559 638 2226",
    "sg:postcode":"93654",
    "sg:province":"CA",
    "wof:name":"Reedley Insurance",
    "wof:placetype":"venue"
},
  "geometry": {"coordinates":[-119.451363,36.597058],"type":"Point"}
}