{
  "type": "Feature",
  "properties": {
    "addr:full":"820 28th St Emeryville CA 94608",
    "addr:housenumber":"820",
    "addr:postcode":"94608",
    "addr:street":"28Th St",
    "iso:country":"US",
    "sg:address":"820 28th St",
    "sg:city":"Emeryville",
    "sg:classifiers":[
        {
            "category":"Organizations",
            "subcategory":"Religious Organization",
            "type":"Services"
        }
    ],
    "sg:phone":"+1 510 452 1796",
    "sg:postcode":"94608",
    "sg:province":"CA",
    "sg:tags":[
        "church"
    ],
    "wof:name":"Solid Foundation Baptist Chr",
    "wof:placetype":"venue"
},
  "geometry": {"coordinates":[-122.27430200000001,37.818345],"type":"Point"}
}