{
  "type": "Feature",
  "properties": {
    "addr:full":"3425 E Chapman Ave Orange CA 92869",
    "addr:housenumber":"3425",
    "addr:postcode":"92869",
    "addr:street":"E Chapman Ave",
    "iso:country":"US",
    "sg:address":"3425 E Chapman Ave",
    "sg:city":"Orange",
    "sg:classifiers":[
        {
            "category":"Bars & Pubs",
            "subcategory":"Nightclub",
            "type":"Food & Drink"
        }
    ],
    "sg:phone":"+1 714 538 9832",
    "sg:postcode":"92869",
    "sg:province":"CA",
    "sg:tags":[
        "nightlife"
    ],
    "wof:name":"James Murphy",
    "wof:placetype":"venue"
},
  "geometry": {"coordinates":[-117.816688,33.787919],"type":"Point"}
}