{
  "type": "Feature",
  "properties": {
    "iso:country":"US",
    "sg:address":"529 E Manchester Blvd",
    "sg:city":"Inglewood",
    "sg:classifiers":[
        {
            "category":"Professional",
            "type":"Services"
        }
    ],
    "sg:phone":"+1 310 412 1160",
    "sg:postcode":"90301",
    "sg:province":"CA",
    "wof:name":"Davis Alonzo",
    "wof:placetype":"venue"
},
  "geometry": {"coordinates":[-118.3477,33.961202],"type":"Point"}
}