{
  "type": "Feature",
  "properties": {
    "addr:full":"42 Verde Dr San Luis Obispo CA 93405",
    "addr:housenumber":"42",
    "addr:postcode":"93405",
    "addr:street":"Verde Dr",
    "iso:country":"US",
    "sg:address":"42 Verde Dr",
    "sg:city":"San Luis Obispo",
    "sg:classifiers":[
        {
            "category":"Health Services",
            "subcategory":"Clinic",
            "type":"Services"
        }
    ],
    "sg:phone":"+1 805 541 4947",
    "sg:postcode":"93405",
    "sg:province":"CA",
    "sg:tags":[
        "organization",
        "medical",
        "surgical"
    ],
    "wof:name":"Central Coast Verification",
    "wof:placetype":"venue"
},
  "geometry": {"coordinates":[-120.67633499999999,35.29254],"type":"Point"}
}