{
  "type": "Feature",
  "properties": {
    "iso:country":"US",
    "sg:address":"345 S Broadway",
    "sg:city":"Los Angeles",
    "sg:classifiers":[
        {
            "category":"Shopping",
            "subcategory":"Tobacco",
            "type":"Retail Goods"
        }
    ],
    "sg:phone":"+1 213 229 8875",
    "sg:postcode":"90013",
    "sg:province":"CA",
    "sg:tags":[
        "shop"
    ],
    "wof:name":"PI Tobacco",
    "wof:placetype":"venue"
},
  "geometry": {"coordinates":[-118.248696,34.042305],"type":"Point"}
}