{
  "type": "Feature",
  "properties": {
    "addr:full":"1067 Mono Way Sonora CA 95370",
    "addr:housenumber":"1067",
    "addr:postcode":"95370",
    "addr:street":"Mono Way",
    "iso:country":"US",
    "sg:address":"1067 Mono Way",
    "sg:city":"Sonora",
    "sg:classifiers":[
        {
            "category":"Food & Beverages",
            "subcategory":"Specialty",
            "type":"Retail Goods"
        }
    ],
    "sg:phone":"+1 209 588 1406",
    "sg:postcode":"95370",
    "sg:province":"CA",
    "sg:tags":[
        "health",
        "diet"
    ],
    "wof:name":"General Nutrition Ctr",
    "wof:placetype":"venue"
},
  "geometry": {"coordinates":[-120.36657,37.975895],"type":"Point"}
}