{
  "type": "Feature",
  "properties": {
    "addr:full":"317 S Broadway Los Angeles CA 90013",
    "addr:housenumber":"317",
    "addr:postcode":"90013",
    "addr:street":"S Broadway",
    "iso:country":"US",
    "sg:address":"317 S Broadway",
    "sg:city":"Los Angeles",
    "sg:classifiers":[
        {
            "category":"Shopping",
            "subcategory":"Clothing, Apparel, & Fashions",
            "type":"Retail Goods"
        },
        {
            "category":"Restaurant",
            "type":"Food & Drink"
        },
        {
            "category":"Food & Beverages",
            "subcategory":"Groceries & Convenience Stores",
            "type":"Retail Goods"
        }
    ],
    "sg:phone":"+1 213 624 2378",
    "sg:postcode":"90013",
    "sg:province":"CA",
    "sg:website":"www.grandcentralsquare.com",
    "wof:name":"Grand Central Market",
    "wof:placetype":"venue"
},
  "geometry": {"coordinates":[-118.248234,34.050702],"type":"Point"}
}