{
  "type": "Feature",
  "properties": {
    "addr:full":"4370 Worth St Los Angeles CA 90063",
    "addr:housenumber":"4370",
    "addr:postcode":"90063",
    "addr:street":"Worth St",
    "iso:country":"US",
    "sg:address":"4370 Worth St",
    "sg:city":"Los Angeles",
    "sg:classifiers":[
        {
            "category":"Manufacturing",
            "subcategory":"Chemicals & Compounds",
            "type":"Manufacturing & Wholesale Goods"
        }
    ],
    "sg:phone":"+1 323 267 1516",
    "sg:postcode":"90063",
    "sg:province":"CA",
    "sg:tags":[
        "specialty"
    ],
    "wof:name":"A & A Wiping Cloth Inc",
    "wof:placetype":"venue"
},
  "geometry": {"coordinates":[-118.19132500000001,34.062875],"type":"Point"}
}