{
  "type": "Feature",
  "properties": {
    "addr:full":"2027 W 157th St Gardena CA 90249",
    "addr:housenumber":"2027",
    "addr:postcode":"90249",
    "addr:street":"W 157Th St",
    "iso:country":"US",
    "sg:address":"2027 W 157th St",
    "sg:city":"Gardena",
    "sg:classifiers":[
        {
            "category":"Building & Trades",
            "subcategory":"Cleaning & Sanitation",
            "type":"Services"
        }
    ],
    "sg:phone":"+1 310 538 1368",
    "sg:postcode":"90249",
    "sg:province":"CA",
    "sg:tags":[
        "janitor"
    ],
    "wof:name":"Tomo Maintenance Svc",
    "wof:placetype":"venue"
},
  "geometry": {"coordinates":[-118.317342,33.887959],"type":"Point"}
}