{
  "type": "Feature",
  "properties": {
    "addr:full":"20062 SW Birch St Newport Beach CA 92660",
    "addr:housenumber":"20062",
    "addr:postcode":"92660",
    "addr:street":"Sw Birch St",
    "iso:country":"US",
    "sg:address":"20062 SW Birch St",
    "sg:city":"Newport Beach",
    "sg:classifiers":[
        {
            "category":"Professional",
            "subcategory":"Engineering",
            "type":"Services"
        }
    ],
    "sg:phone":"+1 949 250 7277",
    "sg:postcode":"92660",
    "sg:province":"CA",
    "sg:tags":[
        "engineer"
    ],
    "wof:name":"Questar Engineering Inc",
    "wof:placetype":"venue"
},
  "geometry": {"coordinates":[-117.87584099999999,33.658545],"type":"Point"}
}