{
  "type": "Feature",
  "properties": {
    "iso:country":"US",
    "sg:address":"2187 1st St",
    "sg:city":"Livermore",
    "sg:classifiers":[
        {
            "category":"Shopping",
            "type":"Retail Goods"
        }
    ],
    "sg:phone":"+1 925 449 6147",
    "sg:postcode":"94550",
    "sg:province":"CA",
    "sg:tags":[
        "picture",
        "frame"
    ],
    "wof:name":"Art D'Cor",
    "wof:placetype":"venue"
},
  "geometry": {"coordinates":[-121.770014,37.681294],"type":"Point"}
}