{
  "type": "Feature",
  "properties": {
    "iso:country":"US",
    "sg:address":"815 Factory Stores Dr",
    "sg:city":"Napa",
    "sg:classifiers":[
        {
            "category":"Shopping",
            "subcategory":"Shoes",
            "type":"Retail Goods"
        }
    ],
    "sg:phone":"+1 707 253 7795",
    "sg:postcode":"94558",
    "sg:province":"CA",
    "sg:website":"www.famousfootwear.com",
    "wof:name":"Factory Brand Shoes",
    "wof:placetype":"venue"
},
  "geometry": {"coordinates":[-122.303571,38.296147],"type":"Point"}
}