{
  "type": "Feature",
  "properties": {
    "iso:country":"US",
    "sg:address":"21284 Corwin Rd",
    "sg:city":"Apple Valley",
    "sg:classifiers":[
        {
            "category":"Freight",
            "type":"Transportation"
        }
    ],
    "sg:phone":"+1 760 247 4878",
    "sg:postcode":"92307",
    "sg:province":"CA",
    "sg:tags":[
        "storage",
        "mover",
        "moving",
        "local"
    ],
    "wof:name":"Apple Valley Transfer Storage",
    "wof:placetype":"venue"
},
  "geometry": {"coordinates":[-117.198862,34.570005],"type":"Point"}
}