{
  "type": "Feature",
  "properties": {
    "iso:country":"US",
    "sg:address":"4742 63rd St",
    "sg:city":"San Diego",
    "sg:classifiers":[
        {
            "category":"Building & Trades",
            "subcategory":"Cleaning & Sanitation",
            "type":"Services"
        }
    ],
    "sg:phone":"+1 800 619 2335",
    "sg:postcode":"92115",
    "sg:province":"CA",
    "sg:tags":[
        "carpet"
    ],
    "sg:website":"www.samedaycarpetcare.com",
    "wof:name":"Same Day Carpet & Air Duct Cleaning",
    "wof:placetype":"venue"
},
  "geometry": {"coordinates":[-117.063675,32.764649],"type":"Point"}
}