{
  "type": "Feature",
  "properties": {
    "iso:country":"US",
    "sg:address":"3984 N Granada Ave",
    "sg:city":"Spring Valley",
    "sg:classifiers":[
        {
            "category":"Freight",
            "type":"Transportation"
        }
    ],
    "sg:phone":"+1 619 670 5544",
    "sg:postcode":"91977",
    "sg:province":"CA",
    "sg:tags":[
        "operator",
        "local",
        "storage",
        "trucking"
    ],
    "wof:name":"A-1 Moving & Storage",
    "wof:placetype":"venue"
},
  "geometry": {"coordinates":[-116.979018,32.749173],"type":"Point"}
}