{
  "type": "Feature",
  "properties": {
    "addr:full":"372 Crestview Ave San Bernardino CA 92410",
    "addr:housenumber":"372",
    "addr:postcode":"92410",
    "addr:street":"Crestview Ave",
    "iso:country":"US",
    "sg:address":"372 Crestview Ave",
    "sg:city":"San Bernardino",
    "sg:classifiers":[
        {
            "category":"Social Services",
            "subcategory":"Child Care",
            "type":"Services"
        }
    ],
    "sg:phone":"+1 909 884 9766",
    "sg:postcode":"92410",
    "sg:province":"CA",
    "wof:name":"First Steps Child Dev Ctr",
    "wof:placetype":"venue"
},
  "geometry": {"coordinates":[-117.277159,34.118793],"type":"Point"}
}