{
  "type": "Feature",
  "properties": {
    "addr:full":"239 Forrester Rd Los Gatos CA 95032",
    "addr:housenumber":"239",
    "addr:postcode":"95032",
    "addr:street":"Forrester Rd",
    "iso:country":"US",
    "sg:address":"239 Forrester Rd",
    "sg:city":"Los Gatos",
    "sg:classifiers":[
        {
            "category":"Education",
            "subcategory":"School",
            "type":"Public Place"
        }
    ],
    "sg:phone":"+1 408 605 4433",
    "sg:postcode":"95032",
    "sg:province":"CA",
    "wof:name":"Project Funway",
    "wof:placetype":"venue"
},
  "geometry": {"coordinates":[-121.941767,37.219533],"type":"Point"}
}