{
  "type": "Feature",
  "properties": {
    "iso:country":"US",
    "sg:address":"343 Soquel Ave",
    "sg:city":"Santa Cruz",
    "sg:classifiers":[
        {
            "category":"Shopping",
            "subcategory":"Crafts & Fabrics",
            "type":"Retail Goods"
        }
    ],
    "sg:phone":"+1 831 420 0118",
    "sg:postcode":"95062",
    "sg:province":"CA",
    "sg:tags":[
        "hemp",
        "product"
    ],
    "wof:name":"Goodhumans",
    "wof:placetype":"venue"
},
  "geometry": {"coordinates":[-122.01994500000001,36.974312],"type":"Point"}
}