{
  "type": "Feature",
  "properties": {
    "addr:full":"235 Central Ave Oxnard CA 93036",
    "addr:housenumber":"235",
    "addr:postcode":"93036",
    "addr:street":"Central Ave",
    "iso:country":"US",
    "sg:address":"235 Central Ave",
    "sg:city":"Oxnard",
    "sg:classifiers":[
        {
            "category":"Home & Garden",
            "subcategory":"Furniture",
            "type":"Retail Goods"
        }
    ],
    "sg:phone":"+1 805 647 6066",
    "sg:postcode":"93036",
    "sg:province":"CA",
    "sg:tags":[
        "equipment",
        "kitchen",
        "cabinet"
    ],
    "wof:name":"Terry Breese Construction",
    "wof:placetype":"venue"
},
  "geometry": {"coordinates":[-119.15136200000001,34.256879],"type":"Point"}
}