{
  "type": "Feature",
  "properties": {
    "addr:full":"14375 Saratoga Ave Saratoga CA 95070",
    "addr:housenumber":"14375",
    "addr:postcode":"95070",
    "addr:street":"Saratoga Ave",
    "iso:country":"US",
    "sg:address":"14375 Saratoga Ave",
    "sg:city":"Saratoga",
    "sg:classifiers":[
        {
            "category":"Wholesale",
            "subcategory":"Medical Equipment & Supplies",
            "type":"Manufacturing & Wholesale Goods"
        }
    ],
    "sg:phone":"+1 408 872 9393",
    "sg:postcode":"95070",
    "sg:province":"CA",
    "sg:tags":[
        "hospital"
    ],
    "wof:name":"Visioncare Ophthalmic Technolo",
    "wof:placetype":"venue"
},
  "geometry": {"coordinates":[-122.031452,37.259461],"type":"Point"}
}