{
  "type": "Feature",
  "properties": {
    "iso:country":"US",
    "sg:address":"1837 Grand Oaks Ave",
    "sg:city":"Altadena",
    "sg:classifiers":[
        {
            "category":"Building & Trades",
            "subcategory":"Landscaping Services",
            "type":"Services"
        }
    ],
    "sg:phone":"+1 626 797 9100",
    "sg:postcode":"91001",
    "sg:province":"CA",
    "sg:website":"www.youcandigittool.com",
    "wof:name":"Bottoms Up Garden & Maintenance",
    "wof:placetype":"venue"
},
  "geometry": {"coordinates":[-118.103996,34.178001],"type":"Point"}
}