{
  "type": "Feature",
  "properties": {
    "addr:full":"1241 S Petit Ave Ventura CA 93004",
    "addr:housenumber":"1241",
    "addr:postcode":"93004",
    "addr:street":"S Petit Ave",
    "iso:country":"US",
    "sg:address":"1241 S Petit Ave",
    "sg:city":"Ventura",
    "sg:classifiers":[
        {
            "category":"Building & Trades",
            "subcategory":"Landscaping Services",
            "type":"Services"
        }
    ],
    "sg:phone":"+1 805 647 3193",
    "sg:postcode":"93004",
    "sg:province":"CA",
    "sg:tags":[
        "landscape"
    ],
    "wof:name":"Newberrys Gardening & Ldscpg",
    "wof:placetype":"venue"
},
  "geometry": {"coordinates":[-119.170383,34.272114],"type":"Point"}
}