{
  "type": "Feature",
  "properties": {
    "iso:country":"US",
    "sg:address":"9410 Magnolia Ave",
    "sg:city":"Riverside",
    "sg:classifiers":[
        {
            "category":"Travel",
            "subcategory":"Travel Agent",
            "type":"Entertainment"
        },
        {
            "category":"Professional",
            "subcategory":"Accounting & Tax Preparation",
            "type":"Services"
        }
    ],
    "sg:phone":"+1 951 354 0401",
    "sg:postcode":"92503",
    "sg:province":"CA",
    "sg:tags":[
        "bureau",
        "agency",
        "return",
        "insurance"
    ],
    "wof:name":"Z Travel & Insurance Inc",
    "wof:placetype":"venue"
},
  "geometry": {"coordinates":[-117.44487100000001,33.921247],"type":"Point"}
}