{
  "type": "Feature",
  "properties": {
    "iso:country":"US",
    "sg:address":"3566 S Higuera St",
    "sg:city":"San Luis Obispo",
    "sg:classifiers":[
        {
            "category":"Professional",
            "subcategory":"Art Services",
            "type":"Services"
        }
    ],
    "sg:phone":"+1 805 543 8090",
    "sg:postcode":"93401",
    "sg:province":"CA",
    "sg:tags":[
        "graphic",
        "designer"
    ],
    "sg:website":"www.axentgraphics.com",
    "wof:name":"Axent Graphics",
    "wof:placetype":"venue"
},
  "geometry": {"coordinates":[-120.670582,35.251832],"type":"Point"}
}