{
  "type": "Feature",
  "properties": {
    "addr:full":"560 Fremont St Monterey CA 93940",
    "addr:housenumber":"560",
    "addr:postcode":"93940",
    "addr:street":"Fremont St",
    "iso:country":"US",
    "sg:address":"560 Fremont St",
    "sg:city":"Monterey",
    "sg:classifiers":[
        {
            "category":"Shopping",
            "subcategory":"Computers & Home Electronics",
            "type":"Retail Goods"
        }
    ],
    "sg:phone":"+1 831 649 9800",
    "sg:postcode":"93940",
    "sg:province":"CA",
    "sg:tags":[
        "consumer",
        "television",
        "radio",
        "store"
    ],
    "wof:name":"Electronic Home Lifestyles Inc",
    "wof:placetype":"venue"
},
  "geometry": {"coordinates":[-121.889707,36.595145],"type":"Point"}
}