{
  "type": "Feature",
  "properties": {
    "addr:full":"30991 Huntwood Ave Hayward CA 94544",
    "addr:housenumber":"30991",
    "addr:postcode":"94544",
    "addr:street":"Huntwood Ave",
    "iso:country":"US",
    "sg:address":"30991 Huntwood Ave",
    "sg:city":"Hayward",
    "sg:classifiers":[
        {
            "category":"Manufacturing",
            "subcategory":"Tools & Machinery",
            "type":"Manufacturing & Wholesale Goods"
        }
    ],
    "sg:phone":"+1 510 487 8290",
    "sg:postcode":"94544",
    "sg:province":"CA",
    "wof:name":"Danworth Manufacturing",
    "wof:placetype":"venue"
},
  "geometry": {"coordinates":[-122.054922,37.616761],"type":"Point"}
}