{
  "type": "Feature",
  "properties": {
    "iso:country":"US",
    "sg:address":"628 E Arrow Hwy",
    "sg:city":"Pomona",
    "sg:classifiers":[
        {
            "category":"Shopping",
            "subcategory":"Used Merchandise",
            "type":"Retail Goods"
        }
    ],
    "sg:phone":"+1 909 624 4405",
    "sg:postcode":"91767",
    "sg:province":"CA",
    "sg:tags":[
        "shop",
        "thrift"
    ],
    "wof:name":"Uptown Thrift Store",
    "wof:placetype":"venue"
},
  "geometry": {"coordinates":[-117.738294,34.089945],"type":"Point"}
}