{
  "type": "Feature",
  "properties": {
    "addr:full":"2 N Lake Ave Pasadena CA 91101",
    "addr:housenumber":"2",
    "addr:postcode":"91101",
    "addr:street":"N Lake Ave",
    "iso:country":"US",
    "sg:address":"2 N Lake Ave",
    "sg:city":"Pasadena",
    "sg:classifiers":[
        {
            "category":"Professional",
            "subcategory":"Lawyer & Legal Services",
            "type":"Services"
        }
    ],
    "sg:phone":"+1 626 796 9621",
    "sg:postcode":"91101",
    "sg:province":"CA",
    "sg:tags":[
        "divorce",
        "law",
        "family"
    ],
    "sg:website":"www.kearney-law.com",
    "wof:name":"Condon Danl B Atty",
    "wof:placetype":"venue"
},
  "geometry": {"coordinates":[-118.131882,34.14629],"type":"Point"}
}