{
  "type": "Feature",
  "properties": {
    "iso:country":"US",
    "sg:address":"747 52nd St Fl 1",
    "sg:city":"Oakland",
    "sg:classifiers":[
        {
            "category":"Professional",
            "subcategory":"Research",
            "type":"Services"
        },
        {
            "category":"Science Facility",
            "type":"Public Place"
        }
    ],
    "sg:phone":"+1 510 428 3888",
    "sg:postcode":"94609",
    "sg:province":"CA",
    "sg:tags":[
        "development",
        "laboratories-research"
    ],
    "wof:name":"Denise Bales",
    "wof:placetype":"venue"
},
  "geometry": {"coordinates":[-122.26808800000001,37.837276],"type":"Point"}
}