{
  "type": "Feature",
  "properties": {
    "addr:full":"633 Oneill Ave Belmont CA 94002",
    "addr:housenumber":"633",
    "addr:postcode":"94002",
    "addr:street":"Oneill Ave",
    "iso:country":"US",
    "sg:address":"633 Oneill Ave",
    "sg:city":"Belmont",
    "sg:classifiers":[
        {
            "category":"Professional",
            "type":"Services"
        }
    ],
    "sg:phone":"+1 650 631 9735",
    "sg:postcode":"94002",
    "sg:province":"CA",
    "sg:tags":[
        "pet"
    ],
    "wof:name":"Dogland",
    "wof:placetype":"venue"
},
  "geometry": {"coordinates":[-122.272003,37.519798],"type":"Point"}
}