{
  "type": "Feature",
  "properties": {
    "iso:country":"US",
    "sg:address":"223 S Glendora Ave",
    "sg:city":"Glendora",
    "sg:classifiers":[
        {
            "category":"Health Services",
            "subcategory":"Doctor",
            "type":"Services"
        }
    ],
    "sg:phone":"+1 626 857 0551",
    "sg:postcode":"91741",
    "sg:province":"CA",
    "sg:tags":[
        "medical"
    ],
    "wof:name":"San Marino Psychiatric",
    "wof:placetype":"venue"
},
  "geometry": {"coordinates":[-117.865482,34.132396],"type":"Point"}
}