{
  "type": "Feature",
  "properties": {
    "iso:country":"US",
    "sg:address":"41421 Date St",
    "sg:city":"Murrieta",
    "sg:classifiers":[
        {
            "category":"Shopping",
            "type":"Retail Goods"
        }
    ],
    "sg:phone":"+1 951 698 0975",
    "sg:postcode":"92562",
    "sg:province":"CA",
    "sg:tags":[
        "art",
        "gallery",
        "dealer"
    ],
    "wof:name":"Rustic Gallery",
    "wof:placetype":"venue"
},
  "geometry": {"coordinates":[-117.173779,33.530703],"type":"Point"}
}