{
  "type": "Feature",
  "properties": {
    "iso:country":"US",
    "sg:address":"1726 Sacramento St",
    "sg:city":"San Francisco",
    "sg:classifiers":[
        {
            "category":"Personal",
            "subcategory":"Beauty Salon",
            "type":"Services"
        }
    ],
    "sg:phone":"+1 415 441 8857",
    "sg:postcode":"94109",
    "sg:province":"CA",
    "sg:tags":[
        "manicuring"
    ],
    "wof:name":"Lady Gold Finger",
    "wof:placetype":"venue"
},
  "geometry": {"coordinates":[-122.422183,37.791418],"type":"Point"}
}