{
  "type": "Feature",
  "properties": {
    "iso:country":"US",
    "sg:address":"1304 Railroad St",
    "sg:city":"Paso Robles",
    "sg:classifiers":[
        {
            "category":"Restaurant",
            "type":"Food & Drink"
        }
    ],
    "sg:phone":"+1 805 239 2141",
    "sg:postcode":"93446",
    "sg:province":"CA",
    "wof:name":"Chubby Chandler's Pizza",
    "wof:placetype":"venue"
},
  "geometry": {"coordinates":[-120.688267,35.627845],"type":"Point"}
}