{
  "type": "Feature",
  "properties": {
    "addr:full":"5995 Sepulveda Blvd Culver City CA 90230",
    "addr:housenumber":"5995",
    "addr:postcode":"90230",
    "addr:street":"Sepulveda Blvd",
    "iso:country":"US",
    "sg:address":"5995 Sepulveda Blvd",
    "sg:city":"Culver City",
    "sg:classifiers":[
        {
            "category":"Professional",
            "subcategory":"Management & Consulting",
            "type":"Services"
        }
    ],
    "sg:phone":"+1 310 390 9558",
    "sg:postcode":"90230",
    "sg:province":"CA",
    "sg:tags":[
        "construction"
    ],
    "sg:website":"www.cmts.com",
    "wof:name":"CMTS Inc",
    "wof:placetype":"venue"
},
  "geometry": {"coordinates":[-118.395724,33.985582],"type":"Point"}
}