{
  "type": "Feature",
  "properties": {
    "iso:country":"US",
    "sg:address":"1638 Sepulveda Blvd",
    "sg:city":"Harbor City",
    "sg:classifiers":[
        {
            "category":"Home & Garden",
            "subcategory":"Furniture",
            "type":"Retail Goods"
        }
    ],
    "sg:phone":"+1 310 784 0033",
    "sg:postcode":"90710",
    "sg:province":"CA",
    "sg:tags":[
        "store"
    ],
    "sg:website":"www.futoncityca.com",
    "wof:name":"Futon City",
    "wof:placetype":"venue"
},
  "geometry": {"coordinates":[-118.306999,33.816502],"type":"Point"}
}