{
  "type": "Feature",
  "properties": {
    "addr:full":"23632 Calabasas Rd Calabasas CA 91302",
    "addr:housenumber":"23632",
    "addr:postcode":"91302",
    "addr:street":"Calabasas Rd",
    "iso:country":"US",
    "sg:address":"23632 Calabasas Rd",
    "sg:city":"Calabasas",
    "sg:classifiers":[
        {
            "category":"Real Estate",
            "subcategory":"Real Estate Services",
            "type":"Services"
        }
    ],
    "sg:phone":"+1 818 222 4840",
    "sg:postcode":"91302",
    "sg:province":"CA",
    "sg:tags":[
        "management",
        "property"
    ],
    "wof:name":"Cirrus Asset Management Inc",
    "wof:placetype":"venue"
},
  "geometry": {"coordinates":[-118.64184400000001,34.156241],"type":"Point"}
}