{
  "type": "Feature",
  "properties": {
    "iso:country":"US",
    "sg:address":"214 Powell St",
    "sg:city":"San Francisco",
    "sg:classifiers":[
        {
            "category":"Shopping",
            "subcategory":"Jewelry",
            "type":"Retail Goods"
        }
    ],
    "sg:phone":"+1 415 788 5552",
    "sg:postcode":"94102",
    "sg:province":"CA",
    "sg:tags":[
        "jeweler"
    ],
    "wof:name":"Shanghai Jewelry & Gifts",
    "wof:placetype":"venue"
},
  "geometry": {"coordinates":[-122.408131,37.787234],"type":"Point"}
}