{
  "type": "Feature",
  "properties": {
    "iso:country":"US",
    "sg:address":"3026 Colusa Hwy",
    "sg:city":"Yuba City",
    "sg:classifiers":[
        {
            "category":"Shopping",
            "type":"Retail Goods"
        }
    ],
    "sg:phone":"+1 530 673 7525",
    "sg:postcode":"95993",
    "sg:province":"CA",
    "sg:tags":[
        "canvas",
        "product",
        "merchandise"
    ],
    "wof:name":"Live Oak Canvass Shop",
    "wof:placetype":"venue"
},
  "geometry": {"coordinates":[-121.685402,39.141233],"type":"Point"}
}