{
  "type": "Feature",
  "properties": {
    "iso:country":"US",
    "sg:address":"1676 N California Blvd",
    "sg:city":"Walnut Creek",
    "sg:classifiers":[
        {
            "category":"Airline",
            "type":"Transportation"
        }
    ],
    "sg:phone":"+1 925 932 8040",
    "sg:postcode":"94596",
    "sg:province":"CA",
    "sg:tags":[
        "scheduled",
        "air"
    ],
    "wof:name":"United",
    "wof:placetype":"venue"
},
  "geometry": {"coordinates":[-122.064992,37.902862],"type":"Point"}
}