{
  "type": "Feature",
  "properties": {
    "iso:country":"US",
    "sg:address":"28971 Hopkins St",
    "sg:city":"Hayward",
    "sg:classifiers":[
        {
            "category":"Wholesale",
            "subcategory":"Toys & Hobbies",
            "type":"Manufacturing & Wholesale Goods"
        }
    ],
    "sg:phone":"+1 510 887 4773",
    "sg:postcode":"94545",
    "sg:province":"CA",
    "sg:tags":[
        "wholesaler"
    ],
    "wof:name":"New Zealand Lamb Tradition",
    "wof:placetype":"venue"
},
  "geometry": {"coordinates":[-122.077974,37.618228],"type":"Point"}
}