{
  "type": "Feature",
  "properties": {
    "iso:country":"US",
    "sg:address":"601 Van Ness Ave Ste E3806",
    "sg:city":"San Francisco",
    "sg:classifiers":[
        {
            "category":"Autos & Motor Vehicles",
            "subcategory":"Automobile Sales",
            "type":"Retail Goods"
        }
    ],
    "sg:phone":"+1 415 552 5222",
    "sg:postcode":"94102",
    "sg:province":"CA",
    "sg:tags":[
        "limo"
    ],
    "sg:website":"www.mosconelimousine.com",
    "wof:name":"Moscone Limousine Service",
    "wof:placetype":"venue"
},
  "geometry": {"coordinates":[-122.420697,37.781099],"type":"Point"}
}