{
  "type": "Feature",
  "properties": {
    "iso:country":"US",
    "sg:address":"34766 Monaco Cmn",
    "sg:city":"Fremont",
    "sg:classifiers":[
        {
            "category":"Wholesale",
            "subcategory":"Durable Goods & Equipment",
            "type":"Manufacturing & Wholesale Goods"
        }
    ],
    "sg:phone":"+1 510 793 7511",
    "sg:postcode":"94555",
    "sg:province":"CA",
    "sg:tags":[
        "equipment-dealers",
        "stereo",
        "audio",
        "video"
    ],
    "sg:website":"http://www.ardenwoodsnd-dvd.com",
    "wof:name":"Ardenwood Sound & D V D",
    "wof:placetype":"venue"
},
  "geometry": {"coordinates":[-122.043199,37.56406],"type":"Point"}
}