{
  "type": "Feature",
  "properties": {
    "iso:country":"US",
    "sg:address":"191 Military E",
    "sg:city":"Benicia",
    "sg:classifiers":[
        {
            "category":"Insurance",
            "subcategory":"Insurance Agent",
            "type":"Services"
        },
        {
            "category":"Insurance",
            "subcategory":"Hazard Insurance",
            "type":"Services"
        },
        {
            "category":"Insurance",
            "subcategory":"Title Insurance",
            "type":"Services"
        },
        {
            "category":"Insurance",
            "subcategory":"Life Insurance",
            "type":"Services"
        }
    ],
    "sg:phone":"+1 707 748 5815",
    "sg:postcode":"94510",
    "sg:province":"CA",
    "sg:tags":[
        "business",
        "auto",
        "commercial",
        "homeowner",
        "motorcycle",
        "renter"
    ],
    "wof:name":"Allstate Insurance Company - Jose Guillermo",
    "wof:placetype":"venue"
},
  "geometry": {"coordinates":[-122.153255,38.053773],"type":"Point"}
}