{
  "type": "Feature",
  "properties": {
    "addr:full":"20000 S Western Ave Torrance CA 90501",
    "addr:housenumber":"20000",
    "addr:postcode":"90501",
    "addr:street":"S Western Ave",
    "iso:country":"US",
    "sg:address":"20000 S Western Ave",
    "sg:city":"Torrance",
    "sg:classifiers":[
        {
            "category":"Freight",
            "type":"Transportation"
        }
    ],
    "sg:phone":"+1 310 328 2334",
    "sg:postcode":"90501",
    "sg:province":"CA",
    "sg:tags":[
        "operator",
        "local",
        "trucking"
    ],
    "wof:name":"Martinez Trucking",
    "wof:placetype":"venue"
},
  "geometry": {"coordinates":[-118.30937900000001,33.854199],"type":"Point"}
}