{
  "type": "Feature",
  "properties": {
    "iso:country":"US",
    "sg:address":"1535 E 17th St",
    "sg:city":"Santa Ana",
    "sg:classifiers":[
        {
            "category":"Banks & Credit Unions",
            "subcategory":"Investment Brokerage",
            "type":"Services"
        }
    ],
    "sg:phone":"+1 714 285 1446",
    "sg:postcode":"92705",
    "sg:province":"CA",
    "sg:tags":[
        "investing"
    ],
    "wof:name":"Durham Investment Inc",
    "wof:placetype":"venue"
},
  "geometry": {"coordinates":[-117.84699999999999,33.759998],"type":"Point"}
}