{
  "type": "Feature",
  "properties": {
    "addr:full":"2964 Encinal Rd Live Oak CA 95953",
    "addr:housenumber":"2964",
    "addr:postcode":"95953",
    "addr:street":"Encinal Rd",
    "iso:country":"US",
    "sg:address":"2964 Encinal Rd",
    "sg:city":"Live Oak",
    "sg:classifiers":[
        {
            "category":"Farming",
            "subcategory":"Farm & Veterinary Services",
            "type":"Manufacturing & Wholesale Goods"
        }
    ],
    "sg:phone":"+1 530 695 9069",
    "sg:postcode":"95953",
    "sg:province":"CA",
    "sg:tags":[
        "preparation",
        "soil"
    ],
    "wof:name":"Rotary Joint Venture Inc",
    "wof:placetype":"venue"
},
  "geometry": {"coordinates":[-121.66923,39.21818],"type":"Point"}
}