{
  "type": "Feature",
  "properties": {
    "addr:full":"306 Oakbranch Dr Encinitas CA 92024",
    "addr:housenumber":"306",
    "addr:postcode":"92024",
    "addr:street":"Oakbranch Dr",
    "iso:country":"US",
    "sg:address":"306 Oakbranch Dr",
    "sg:city":"Encinitas",
    "sg:classifiers":[
        {
            "category":"Social Services",
            "subcategory":"Child Care",
            "type":"Services"
        },
        {
            "category":"Education",
            "subcategory":"Preschool",
            "type":"Public Place"
        }
    ],
    "sg:phone":"+1 760 525 9356",
    "sg:postcode":"92024",
    "sg:province":"CA",
    "sg:tags":[
        "day"
    ],
    "wof:name":"Daddy Daughter Infant Daycare",
    "wof:placetype":"venue"
},
  "geometry": {"coordinates":[-117.25632299999999,33.041263],"type":"Point"}
}