{
  "type": "Feature",
  "properties": {
    "addr:full":"3861 N Willow Rd Bethel Island CA 94511",
    "addr:housenumber":"3861",
    "addr:postcode":"94511",
    "addr:street":"N Willow Rd",
    "iso:country":"US",
    "sg:address":"3861 N Willow Rd",
    "sg:city":"Bethel Island",
    "sg:classifiers":[
        {
            "category":"Recreation",
            "subcategory":"Marina",
            "type":"Entertainment"
        }
    ],
    "sg:phone":"+1 925 684 2174",
    "sg:postcode":"94511",
    "sg:province":"CA",
    "wof:name":"Beacon Harbor",
    "wof:placetype":"venue"
},
  "geometry": {"coordinates":[-121.62661300000001,38.036723],"type":"Point"}
}