{
  "type": "Feature",
  "properties": {
    "iso:country":"US",
    "sg:address":"1777 N Bellflower Blvd Ste 108",
    "sg:city":"Long Beach",
    "sg:classifiers":[
        {
            "category":"Health Services",
            "subcategory":"Doctor",
            "type":"Services"
        }
    ],
    "sg:phone":"+1 562 597 5700",
    "sg:postcode":"90815",
    "sg:province":"CA",
    "sg:tags":[
        "surgeon",
        "oral"
    ],
    "wof:name":"Kaufman Howard DDS",
    "wof:placetype":"venue"
},
  "geometry": {"coordinates":[-118.12400100000001,33.788101],"type":"Point"}
}