{
  "type": "Feature",
  "properties": {
    "addr:full":"5305 Comercio Ln Woodland Hills CA 91364",
    "addr:postcode":"5305;91364",
    "addr:street":"Comercio Ln",
    "iso:country":"US",
    "sg:address":"5305 Comercio Ln",
    "sg:city":"Woodland Hills",
    "sg:classifiers":[
        {
            "category":"Health Services",
            "subcategory":"Health Practitioner",
            "type":"Services"
        }
    ],
    "sg:phone":"+1 818 347 0191",
    "sg:postcode":"91364",
    "sg:province":"CA",
    "sg:tags":[
        "psychologist"
    ],
    "wof:name":"Ronald M Doctor PHD",
    "wof:placetype":"venue"
},
  "geometry": {"coordinates":[-118.59492400000001,34.166259],"type":"Point"}
}