{
  "type": "Feature",
  "properties": {
    "iso:country":"US",
    "sg:address":"1119 Park Hills Rd",
    "sg:city":"Berkeley",
    "sg:classifiers":[
        {
            "category":"Professional",
            "subcategory":"Engineering",
            "type":"Services"
        },
        {
            "category":"Professional",
            "subcategory":"Computer Services",
            "type":"Services"
        }
    ],
    "sg:phone":"+1 510 649 8401",
    "sg:postcode":"94708",
    "sg:province":"CA",
    "sg:tags":[
        "designer",
        "consultant",
        "integration",
        "system",
        "engineer"
    ],
    "wof:name":"General Nanotechnology",
    "wof:placetype":"venue"
},
  "geometry": {"coordinates":[-122.25238400000001,37.891526],"type":"Point"}
}