{
  "type": "Feature",
  "properties": {
    "addr:full":"14031 Tierra Bonita Rd Poway CA 92064",
    "addr:housenumber":"14031",
    "addr:postcode":"ca 92064",
    "addr:street":"Tierra Bonita Rd",
    "iso:country":"US",
    "sg:address":"14031 Tierra Bonita Rd",
    "sg:city":"Poway",
    "sg:phone":"+1 858 486 6146",
    "sg:postcode":"92064",
    "sg:province":"CA",
    "sg:tags":[
        "farm",
        "soybean"
    ],
    "wof:name":"Bill Bailey",
    "wof:placetype":"venue"
},
  "geometry": {"coordinates":[-117.027362,32.969709],"type":"Point"}
}