{
  "type": "Feature",
  "properties": {
    "addr:full":"1942 E Gladwick St Compton CA 90220",
    "addr:housenumber":"1942",
    "addr:postcode":"90220",
    "addr:street":"E Gladwick St",
    "iso:country":"US",
    "sg:address":"1942 E Gladwick St",
    "sg:city":"Compton",
    "sg:classifiers":[
        {
            "category":"Wholesale",
            "subcategory":"Machinery & Supplies",
            "type":"Manufacturing & Wholesale Goods"
        }
    ],
    "sg:phone":"+1 310 537 2882",
    "sg:postcode":"90220",
    "sg:province":"CA",
    "sg:tags":[
        "equipment",
        "industrial"
    ],
    "wof:name":"Action Process Inc",
    "wof:placetype":"venue"
},
  "geometry": {"coordinates":[-118.232229,33.853264],"type":"Point"}
}