{
  "type": "Feature",
  "properties": {
    "iso:country":"US",
    "sg:address":"16025 S Figueroa St",
    "sg:city":"Gardena",
    "sg:classifiers":[
        {
            "category":"Fast Food",
            "type":"Food & Drink"
        }
    ],
    "sg:phone":"+1 310 324 6483",
    "sg:postcode":"90248",
    "sg:province":"CA",
    "sg:tags":[
        "burger"
    ],
    "wof:name":"Jim's Burgers #9",
    "wof:placetype":"venue"
},
  "geometry": {"coordinates":[-118.283123,33.885799],"type":"Point"}
}