{
  "type": "Feature",
  "properties": {
    "addr:full":"1015 E Katella Ave Anaheim CA 92805",
    "addr:housenumber":"1015",
    "addr:postcode":"92805",
    "addr:street":"E Katella Ave",
    "iso:country":"US",
    "sg:address":"1015 E Katella Ave",
    "sg:city":"Anaheim",
    "sg:classifiers":[
        {
            "category":"Food & Beverages",
            "subcategory":"Specialty",
            "type":"Retail Goods"
        }
    ],
    "sg:phone":"+1 714 535 6086",
    "sg:postcode":"92805",
    "sg:province":"CA",
    "sg:tags":[
        "vitamin"
    ],
    "wof:name":"Ines Aguilar",
    "wof:placetype":"venue"
},
  "geometry": {"coordinates":[-117.89757899999999,33.803415],"type":"Point"}
}