{
  "type": "Feature",
  "properties": {
    "addr:full":"3195 Cll Jazmin San Luis Obispo CA 93401",
    "addr:postcode":"3195;93401",
    "addr:street":"Cll Jazmin",
    "iso:country":"US",
    "sg:address":"3195 Cll Jazmin",
    "sg:city":"San Luis Obispo",
    "sg:classifiers":[
        {
            "category":"Professional",
            "subcategory":"Business Services",
            "type":"Services"
        }
    ],
    "sg:phone":"+1 805 544 3961",
    "sg:postcode":"93401",
    "sg:province":"CA",
    "sg:tags":[
        "information",
        "referral"
    ],
    "wof:name":"Judy Tyner Mgmt Info Conslnt",
    "wof:placetype":"venue"
},
  "geometry": {"coordinates":[-120.661869,35.256195],"type":"Point"}
}