{
  "type": "Feature",
  "properties": {
    "addr:full":"1238 Crows Landing Rd Modesto CA 95351",
    "addr:housenumber":"1238",
    "addr:postcode":"ca 95351",
    "addr:street":"Crows Landing Rd",
    "iso:country":"US",
    "sg:address":"1238 Crows Landing Rd",
    "sg:city":"Modesto",
    "sg:classifiers":[
        {
            "category":"Food & Beverages",
            "subcategory":"Meat & Fish",
            "type":"Retail Goods"
        }
    ],
    "sg:phone":"+1 209 576 2871",
    "sg:postcode":"95351",
    "sg:province":"CA",
    "wof:name":"Carniceria 3 Hermanos",
    "wof:placetype":"venue"
},
  "geometry": {"coordinates":[-120.99356400000001,37.611346],"type":"Point"}
}