{
  "type": "Feature",
  "properties": {
    "addr:full":"14548 Donnington Ln Truckee CA 96161",
    "addr:housenumber":"14548",
    "addr:postcode":"96161",
    "addr:street":"Donnington Ln",
    "iso:country":"US",
    "sg:address":"14548 Donnington Ln",
    "sg:city":"Truckee",
    "sg:classifiers":[
        {
            "category":"Health Services",
            "subcategory":"Clinic",
            "type":"Services"
        }
    ],
    "sg:phone":"+1 530 587 7770",
    "sg:postcode":"96161",
    "sg:province":"CA",
    "wof:name":"Expert Iv Access",
    "wof:placetype":"venue"
},
  "geometry": {"coordinates":[-120.11081299999999,39.350717],"type":"Point"}
}