{
  "type": "Feature",
  "properties": {
    "addr:full":"9039 Bolsa Ave Westminster CA 92683",
    "addr:housenumber":"9039",
    "addr:postcode":"92683",
    "addr:street":"Bolsa Ave",
    "iso:country":"US",
    "sg:address":"9039 Bolsa Ave",
    "sg:city":"Westminster",
    "sg:classifiers":[
        {
            "category":"Professional",
            "subcategory":"Business Services",
            "type":"Services"
        }
    ],
    "sg:phone":"+1 714 903 8182",
    "sg:postcode":"92683",
    "sg:province":"CA",
    "sg:tags":[
        "delivery",
        "courier"
    ],
    "wof:name":"Speedy Overnight Express Service",
    "wof:placetype":"venue"
},
  "geometry": {"coordinates":[-117.971001,33.7449],"type":"Point"}
}