{
  "type": "Feature",
  "properties": {
    "iso:country":"US",
    "sg:address":"1465 Mangrove Ave",
    "sg:city":"Chico",
    "sg:classifiers":[
        {
            "category":"Shopping",
            "type":"Retail Goods"
        }
    ],
    "sg:phone":"+1 530 343 9341",
    "sg:postcode":"95926",
    "sg:province":"CA",
    "sg:tags":[
        "cards",
        "sport",
        "baseball",
        "memorabilia"
    ],
    "wof:name":"J & R Sports Cards",
    "wof:placetype":"venue"
},
  "geometry": {"coordinates":[-121.840547,39.744912],"type":"Point"}
}