{
  "type": "Feature",
  "properties": {
    "addr:full":"5309 E 8th St Oakland CA 94601",
    "addr:housenumber":"5309",
    "addr:postcode":"94601",
    "addr:street":"E 8Th St",
    "iso:country":"US",
    "sg:address":"5309 E 8th St",
    "sg:city":"Oakland",
    "sg:classifiers":[
        {
            "category":"Wholesale",
            "subcategory":"Medical Equipment & Supplies",
            "type":"Manufacturing & Wholesale Goods"
        },
        {
            "category":"Shopping",
            "subcategory":"Pharmacy",
            "type":"Retail Goods"
        }
    ],
    "sg:phone":"+1 510 436 5040",
    "sg:postcode":"94601",
    "sg:province":"CA",
    "sg:tags":[
        "wheelchair",
        "disabled",
        "person",
        "health",
        "home",
        "care"
    ],
    "wof:name":"Wheelcare Express",
    "wof:placetype":"venue"
},
  "geometry": {"coordinates":[-122.210977,37.764133],"type":"Point"}
}