{
  "type": "Feature",
  "properties": {
    "addr:full":"3312 Gaylor Ln San Jose CA 95118",
    "addr:housenumber":"3312",
    "addr:postcode":"95118",
    "addr:street":"Gaylor Ln",
    "iso:country":"US",
    "sg:address":"3312 Gaylor Ln",
    "sg:city":"San Jose",
    "sg:classifiers":[
        {
            "category":"Wholesale",
            "subcategory":"Home Furnishings",
            "type":"Manufacturing & Wholesale Goods"
        }
    ],
    "sg:phone":"+1 408 266 9477",
    "sg:postcode":"95118",
    "sg:province":"CA",
    "sg:tags":[
        "piece"
    ],
    "wof:name":"West-Tex Copywright",
    "wof:placetype":"venue"
},
  "geometry": {"coordinates":[-121.89958300000001,37.267956],"type":"Point"}
}