{
  "type": "Feature",
  "properties": {
    "iso:country":"US",
    "sg:address":"208 Otto Cir Ste 1",
    "sg:city":"Sacramento",
    "sg:classifiers":[
        {
            "category":"Personal",
            "type":"Services"
        }
    ],
    "sg:phone":"+1 800 716 5684",
    "sg:postcode":"95822",
    "sg:province":"CA",
    "sg:tags":[
        "mover"
    ],
    "wof:name":"STARVING STUDENTS MOVERS",
    "wof:placetype":"venue"
},
  "geometry": {"coordinates":[-121.476574,38.509355],"type":"Point"}
}