{
  "type": "Feature",
  "properties": {
    "iso:country":"US",
    "sg:address":"242 Broadway St",
    "sg:city":"Chico",
    "sg:classifiers":[
        {
            "category":"Personal",
            "type":"Services"
        },
        {
            "category":"Restaurant",
            "type":"Food & Drink"
        }
    ],
    "sg:phone":"+1 530 899 8331",
    "sg:postcode":"95928",
    "sg:province":"CA",
    "sg:tags":[
        "banquet",
        "rooms"
    ],
    "wof:name":"Grand Ballroom On Broadway",
    "wof:placetype":"venue"
},
  "geometry": {"coordinates":[-121.840789,39.729277],"type":"Point"}
}