{
  "type": "Feature",
  "properties": {
    "iso:country":"US",
    "sg:address":"808 Alamo Dr",
    "sg:city":"Vacaville",
    "sg:classifiers":[
        {
            "category":"Wholesale",
            "subcategory":"Electrical",
            "type":"Manufacturing & Wholesale Goods"
        }
    ],
    "sg:phone":"+1 707 447 7707",
    "sg:postcode":"95688",
    "sg:province":"CA",
    "sg:tags":[
        "radio"
    ],
    "wof:name":"Pagers Etc",
    "wof:placetype":"venue"
},
  "geometry": {"coordinates":[-121.997769,38.34756],"type":"Point"}
}