{
  "type": "Feature",
  "properties": {
    "addr:full":"2390 Lafayette St Santa Clara CA 95050",
    "addr:housenumber":"2390",
    "addr:postcode":"95050",
    "addr:street":"Lafayette St",
    "iso:country":"US",
    "sg:address":"2390 Lafayette St",
    "sg:city":"Santa Clara",
    "sg:classifiers":[
        {
            "category":"Retail",
            "subcategory":"Auto Rental",
            "type":"Services"
        }
    ],
    "sg:phone":"+1 408 988 4319",
    "sg:postcode":"95050",
    "sg:province":"CA",
    "sg:tags":[
        "renting",
        "truck",
        "leasing"
    ],
    "wof:name":"U-Haul Co",
    "wof:placetype":"venue"
},
  "geometry": {"coordinates":[-121.949888,37.364594],"type":"Point"}
}