{
  "type": "Feature",
  "properties": {
    "addr:full":"28075 N Ave Stanford Valencia CA 91355",
    "addr:housenumber":"28075",
    "addr:postcode":"91355",
    "addr:street":"N Ave",
    "iso:country":"US",
    "sg:address":"28075 N Ave Stanford",
    "sg:city":"Valencia",
    "sg:classifiers":[
        {
            "category":"Professional",
            "subcategory":"Computer Services",
            "type":"Services"
        }
    ],
    "sg:phone":"+1 661 702 9292",
    "sg:postcode":"91355",
    "sg:province":"CA",
    "sg:tags":[
        "consultant",
        "designer"
    ],
    "sg:website":"www.al-ter.com",
    "wof:name":"Al Ter Computers",
    "wof:placetype":"venue"
},
  "geometry": {"coordinates":[-118.598159,34.440178],"type":"Point"}
}