{
  "type": "Feature",
  "properties": {
    "addr:full":"556 Glenwood Rd Glendale CA 91202",
    "addr:housenumber":"556",
    "addr:postcode":"91202",
    "addr:street":"Glenwood Rd",
    "iso:country":"US",
    "sg:address":"556 Glenwood Rd",
    "sg:city":"Glendale",
    "sg:classifiers":[
        {
            "category":"Utilities",
            "subcategory":"Telephone",
            "type":"Services"
        }
    ],
    "sg:phone":"+1 818 242 2452",
    "sg:postcode":"91202",
    "sg:province":"CA",
    "sg:tags":[
        "communications"
    ],
    "wof:name":"Irakli Gagua",
    "wof:placetype":"venue"
},
  "geometry": {"coordinates":[-118.266722,34.164436],"type":"Point"}
}