{
  "type": "Feature",
  "properties": {
    "iso:country":"US",
    "sg:address":"316 L St",
    "sg:city":"Davis",
    "sg:classifiers":[
        {
            "category":"Utilities",
            "subcategory":"Electric",
            "type":"Services"
        },
        {
            "category":"Manufacturing",
            "subcategory":"Electronics",
            "type":"Manufacturing & Wholesale Goods"
        }
    ],
    "sg:phone":"+1 530 757 5803",
    "sg:postcode":"95616",
    "sg:province":"CA",
    "sg:tags":[
        "equipment-testing"
    ],
    "sg:website":"http://www.pge.com",
    "wof:name":"Pg&E",
    "wof:placetype":"venue"
},
  "geometry": {"coordinates":[-121.733802,38.54611],"type":"Point"}
}