{
  "type": "Feature",
  "properties": {
    "iso:country":"US",
    "sg:address":"8009 S Broadway",
    "sg:city":"Los Angeles",
    "sg:classifiers":[
        {
            "category":"Professional",
            "subcategory":"Printing & Photocopies",
            "type":"Services"
        }
    ],
    "sg:phone":"+1 323 971 5300",
    "sg:postcode":"90003",
    "sg:province":"CA",
    "sg:tags":[
        "duplicating",
        "copying"
    ],
    "wof:name":"Moorer's Computerized Office",
    "wof:placetype":"venue"
},
  "geometry": {"coordinates":[-118.278363,33.966036],"type":"Point"}
}