{
  "type": "Feature",
  "properties": {
    "addr:full":"8505 Indiana Ave Riverside CA 92504",
    "addr:housenumber":"8505",
    "addr:postcode":"92504",
    "addr:street":"Indiana Ave",
    "iso:country":"US",
    "sg:address":"8505 Indiana Ave",
    "sg:city":"Riverside",
    "sg:classifiers":[
        {
            "category":"Autos & Motor Vehicles",
            "subcategory":"Automobile Sales",
            "type":"Retail Goods"
        }
    ],
    "sg:phone":"+1 951 509 1025",
    "sg:postcode":"92504",
    "sg:province":"CA",
    "sg:tags":[
        "car",
        "dealer"
    ],
    "wof:name":"Walters Auto Sales",
    "wof:placetype":"venue"
},
  "geometry": {"coordinates":[-117.424604,33.923797],"type":"Point"}
}