{
  "type": "Feature",
  "properties": {
    "iso:country":"US",
    "sg:address":"16654 Soledad Canyon Rd",
    "sg:city":"Canyon Country",
    "sg:classifiers":[
        {
            "category":"Arts & Performance",
            "subcategory":"Theater",
            "type":"Entertainment"
        }
    ],
    "sg:phone":"+1 661 298 1818",
    "sg:postcode":"91387",
    "sg:province":"CA",
    "sg:tags":[
        "manufacture",
        "disc",
        "electronic"
    ],
    "wof:name":"Audiofile Pro",
    "wof:placetype":"venue"
},
  "geometry": {"coordinates":[-118.426199,34.426553],"type":"Point"}
}