{
  "type": "Feature",
  "properties": {
    "addr:full":"479 42nd St Oakland CA 94609",
    "addr:housenumber":"479",
    "addr:postcode":"94609",
    "addr:street":"42Nd St",
    "iso:country":"US",
    "sg:address":"479 42nd St",
    "sg:city":"Oakland",
    "sg:classifiers":[
        {
            "category":"Organizations",
            "subcategory":"Religious Organization",
            "type":"Services"
        }
    ],
    "sg:phone":"+1 510 658 3077",
    "sg:postcode":"94609",
    "sg:province":"CA",
    "sg:tags":[
        "church"
    ],
    "wof:name":"Glorious Kingdom Primitive Chr",
    "wof:placetype":"venue"
},
  "geometry": {"coordinates":[-122.260553,37.830928],"type":"Point"}
}