{
  "type": "Feature",
  "properties": {
    "addr:full":"1515 Palisades Dr Ste I Pacific Palisades CA 90272",
    "addr:housenumber":"1515",
    "addr:postcode":"90272",
    "addr:street":"Palisades Dr Ste I",
    "iso:country":"US",
    "sg:address":"1515 Palisades Dr Ste I",
    "sg:city":"Pacific Palisades",
    "sg:classifiers":[
        {
            "category":"Landmark",
            "subcategory":"Tourist Information",
            "type":"Public Place"
        }
    ],
    "sg:phone":"+1 310 459 4691",
    "sg:postcode":"90272",
    "sg:province":"CA",
    "sg:tags":[
        "tour"
    ],
    "wof:name":"V I P Meetings & Conventions",
    "wof:placetype":"venue"
},
  "geometry": {"coordinates":[-118.565414,34.076063],"type":"Point"}
}