{
  "type": "Feature",
  "properties": {
    "addr:full":"1221 N Peach Ave Fresno CA 93727",
    "addr:housenumber":"1221",
    "addr:postcode":"93727",
    "addr:street":"N Peach Ave",
    "iso:country":"US",
    "sg:address":"1221 N Peach Ave",
    "sg:city":"Fresno",
    "sg:classifiers":[
        {
            "category":"Real Estate",
            "subcategory":"Real Estate Operator",
            "type":"Services"
        }
    ],
    "sg:phone":"+1 559 456 1367",
    "sg:postcode":"93727",
    "sg:province":"CA",
    "sg:tags":[
        "apartment"
    ],
    "wof:name":"Peachwood Homeowners Assoc",
    "wof:placetype":"venue"
},
  "geometry": {"coordinates":[-119.71833599999999,36.759102],"type":"Point"}
}