{
  "type": "Feature",
  "properties": {
    "addr:full":"11210 Lower Azusa Rd El Monte CA 91731",
    "addr:housenumber":"11210",
    "addr:postcode":"91731",
    "addr:street":"Lower Azusa Rd",
    "iso:country":"US",
    "sg:address":"11210 Lower Azusa Rd",
    "sg:city":"El Monte",
    "sg:classifiers":[
        {
            "category":"Health Services",
            "subcategory":"Nursing And Care Facility",
            "type":"Services"
        }
    ],
    "sg:phone":"+1 626 442 6863",
    "sg:postcode":"91731",
    "sg:province":"CA",
    "sg:tags":[
        "home",
        "convalescent"
    ],
    "wof:name":"Mid Wilshire Healthcare Ctr",
    "wof:placetype":"venue"
},
  "geometry": {"coordinates":[-118.022402,34.091653],"type":"Point"}
}