{
  "type": "Feature",
  "properties": {
    "addr:full":"1705 Branham Ln San Jose CA 95124",
    "addr:housenumber":"1705",
    "addr:postcode":"95124",
    "addr:street":"Branham Ln",
    "iso:country":"US",
    "sg:address":"1705 Branham Ln",
    "sg:city":"San Jose",
    "sg:classifiers":[
        {
            "category":"Shopping",
            "subcategory":"Gifts & Souvenirs",
            "type":"Retail Goods"
        }
    ],
    "sg:phone":"+1 408 978 6499",
    "sg:postcode":"95124",
    "sg:province":"CA",
    "sg:tags":[
        "novelty"
    ],
    "wof:name":"Le Giftbox",
    "wof:placetype":"venue"
},
  "geometry": {"coordinates":[-121.91709899999999,37.250947],"type":"Point"}
}