{
  "type": "Feature",
  "properties": {
    "iso:country":"US",
    "sg:address":"2721 Main St",
    "sg:city":"Santa Monica",
    "sg:classifiers":[
        {
            "category":"Shopping",
            "subcategory":"Clothing, Apparel, & Fashions",
            "type":"Retail Goods"
        }
    ],
    "sg:phone":"+1 310 392 3378",
    "sg:postcode":"90405",
    "sg:province":"CA",
    "wof:name":"Gioia",
    "wof:placetype":"venue"
},
  "geometry": {"coordinates":[-118.481154,33.999723],"type":"Point"}
}