{
  "type": "Feature",
  "properties": {
    "addr:full":"9751 Independence Ave Chatsworth CA 91311",
    "addr:housenumber":"9751",
    "addr:postcode":"91311",
    "addr:street":"Independence Ave",
    "iso:country":"US",
    "sg:address":"9751 Independence Ave",
    "sg:city":"Chatsworth",
    "sg:classifiers":[
        {
            "category":"Communications",
            "subcategory":"Film & Video Production",
            "type":"Services"
        }
    ],
    "sg:phone":"+1 818 280 3700",
    "sg:postcode":"91311",
    "sg:province":"CA",
    "sg:tags":[
        "taping"
    ],
    "wof:name":"Juicy Entertainment",
    "wof:placetype":"venue"
},
  "geometry": {"coordinates":[-118.590813,34.249062],"type":"Point"}
}