{
  "type": "Feature",
  "properties": {
    "addr:full":"2805 J Street Suite 300 Sacramento CA 95816",
    "addr:housenumber":"2805",
    "addr:postcode":"95816",
    "addr:street":"J Street Suite 300",
    "iso:country":"US",
    "sg:address":"2805 J Street Suite 300",
    "sg:city":"Sacramento",
    "sg:classifiers":[
        {
            "category":"Health Services",
            "subcategory":"Doctor",
            "type":"Services"
        }
    ],
    "sg:phone":"+1 916 451 5730",
    "sg:postcode":"95816",
    "sg:province":"CA",
    "sg:tags":[
        "medicine",
        "sport"
    ],
    "wof:name":"Tanji Jeffrey L MD Sports Medicine",
    "wof:placetype":"venue"
},
  "geometry": {"coordinates":[-121.46913000000001,38.573839],"type":"Point"}
}