{
  "type": "Feature",
  "properties": {
    "iso:country":"US",
    "sg:address":"1581 15th Ave",
    "sg:city":"San Francisco",
    "sg:classifiers":[
        {
            "category":"Building & Trades",
            "subcategory":"Electrical",
            "type":"Services"
        }
    ],
    "sg:phone":"+1 415 861 5332",
    "sg:postcode":"94122",
    "sg:province":"CA",
    "sg:tags":[
        "electrician"
    ],
    "wof:name":"Yohan Electric",
    "wof:placetype":"venue"
},
  "geometry": {"coordinates":[-122.471918,37.75828],"type":"Point"}
}