{
  "type": "Feature",
  "properties": {
    "iso:country":"US",
    "sg:address":"190 Truman St",
    "sg:city":"Coalinga",
    "sg:classifiers":[
        {
            "category":"Mining & Drilling",
            "type":"Manufacturing & Wholesale Goods"
        }
    ],
    "sg:phone":"+1 559 935 2672",
    "sg:postcode":"93210",
    "sg:province":"CA",
    "sg:tags":[
        "oil",
        "well"
    ],
    "wof:name":"Bud's Equipment Inc",
    "wof:placetype":"venue"
},
  "geometry": {"coordinates":[-120.354492,36.143913],"type":"Point"}
}