{
  "type": "Feature",
  "properties": {
    "iso:country":"US",
    "sg:address":"1085 Fox Chase Dr",
    "sg:city":"San Jose",
    "sg:classifiers":[
        {
            "category":"Shopping",
            "subcategory":"Music",
            "type":"Retail Goods"
        }
    ],
    "sg:phone":"+1 408 267 1407",
    "sg:postcode":"95123",
    "sg:province":"CA",
    "wof:name":"Cub Records",
    "wof:placetype":"venue"
},
  "geometry": {"coordinates":[-121.875041,37.25252],"type":"Point"}
}