{
  "type": "Feature",
  "properties": {
    "addr:full":"415 W Carmel Valley Rd Carmel Valley CA 93924",
    "addr:housenumber":"415",
    "addr:postcode":"93924",
    "addr:street":"W Carmel Valley Rd",
    "iso:country":"US",
    "sg:address":"415 W Carmel Valley Rd",
    "sg:city":"Carmel Valley",
    "sg:classifiers":[
        {
            "category":"Restaurant",
            "type":"Food & Drink"
        }
    ],
    "sg:menulink":"http://www.allmenus.com/ca/carmel-valley/259326-marinus---bernardus-lodge/menu/",
    "sg:phone":"+1 831 658 3400",
    "sg:postcode":"93924",
    "sg:province":"CA",
    "sg:tags":[
        "american",
        "californian"
    ],
    "wof:name":"Marinus - Bernardus Lodge",
    "wof:placetype":"venue"
},
  "geometry": {"coordinates":[-121.753916,36.499351],"type":"Point"}
}