{
  "type": "Feature",
  "properties": {
    "addr:full":"1770 Iowa Ave Riverside CA 92507",
    "addr:housenumber":"1770",
    "addr:postcode":"92507",
    "addr:street":"Iowa Ave",
    "iso:country":"US",
    "sg:address":"1770 Iowa Ave",
    "sg:city":"Riverside",
    "sg:classifiers":[
        {
            "category":"Real Estate",
            "subcategory":"Architect",
            "type":"Services"
        }
    ],
    "sg:phone":"+1 909 944 6343",
    "sg:postcode":"92507",
    "sg:province":"CA",
    "sg:website":"www.fdae.com",
    "wof:name":"Fields Devereaux",
    "wof:placetype":"venue"
},
  "geometry": {"coordinates":[-117.33974000000001,33.995637],"type":"Point"}
}