{
  "type": "Feature",
  "properties": {
    "addr:full":"13100 Melanie Ln Westminster CA 92683",
    "addr:housenumber":"13100",
    "addr:postcode":"92683",
    "addr:street":"Melanie Ln",
    "iso:country":"US",
    "sg:address":"13100 Melanie Ln",
    "sg:city":"Westminster",
    "sg:classifiers":[
        {
            "category":"Real Estate",
            "subcategory":"Real Estate Operator",
            "type":"Services"
        }
    ],
    "sg:phone":"+1 714 893 2293",
    "sg:postcode":"92683",
    "sg:province":"CA",
    "sg:tags":[
        "mobile",
        "home",
        "site"
    ],
    "wof:name":"Losrobles Mobile Home Estates",
    "wof:placetype":"venue"
},
  "geometry": {"coordinates":[-118.026408,33.772026],"type":"Point"}
}