{
  "type": "Feature",
  "properties": {
    "iso:country":"US",
    "sg:address":"2676 Orange Ave",
    "sg:city":"Signal Hill",
    "sg:classifiers":[
        {
            "category":"Mining & Drilling",
            "type":"Manufacturing & Wholesale Goods"
        }
    ],
    "sg:phone":"+1 562 424 2451",
    "sg:postcode":"90755",
    "sg:province":"CA",
    "sg:tags":[
        "oil",
        "gas",
        "producer"
    ],
    "wof:name":"Oil Operators Inc",
    "wof:placetype":"venue"
},
  "geometry": {"coordinates":[-118.17623,33.80541],"type":"Point"}
}