{
  "type": "Feature",
  "properties": {
    "iso:country":"US",
    "sg:address":"10672 Calabash Ave",
    "sg:city":"Fontana",
    "sg:classifiers":[
        {
            "category":"Building & Trades",
            "subcategory":"Construction",
            "type":"Services"
        }
    ],
    "sg:phone":"+1 909 854 9963",
    "sg:postcode":"92337",
    "sg:province":"CA",
    "sg:tags":[
        "shoring"
    ],
    "wof:name":"Trench Plate Rental Co",
    "wof:placetype":"venue"
},
  "geometry": {"coordinates":[-117.501994,34.062186],"type":"Point"}
}