{
  "type": "Feature",
  "properties": {
    "addr:full":"8251 Monroe Ave Ste 4 Stanton CA 90680",
    "addr:housenumber":"8251",
    "addr:postcode":"ca 90680",
    "addr:street":"Monroe Ave Ste 4",
    "iso:country":"US",
    "sg:address":"8251 Monroe Ave Ste 4",
    "sg:city":"Stanton",
    "sg:classifiers":[
        {
            "category":"Autos & Motor Vehicles",
            "subcategory":"Auto Supplies",
            "type":"Retail Goods"
        },
        {
            "category":"Retail",
            "subcategory":"Auto Repair",
            "type":"Services"
        }
    ],
    "sg:phone":"+1 714 826 0073",
    "sg:postcode":"90680",
    "sg:province":"CA",
    "sg:tags":[
        "body",
        "shop",
        "lettering",
        "automobile",
        "truck",
        "painting",
        "repairing"
    ],
    "wof:name":"Bmn Performance",
    "wof:placetype":"venue"
},
  "geometry": {"coordinates":[-117.988998,33.8055],"type":"Point"}
}