{
  "type": "Feature",
  "properties": {
    "iso:country":"US",
    "sg:address":"2230 N Texas St",
    "sg:city":"Fairfield",
    "sg:classifiers":[
        {
            "category":"Home & Garden",
            "subcategory":"Building Materials",
            "type":"Retail Goods"
        }
    ],
    "sg:phone":"+1 707 429 3300",
    "sg:postcode":"94533",
    "sg:province":"CA",
    "sg:tags":[
        "glass",
        "window",
        "plate"
    ],
    "wof:name":"Discovery Tinting",
    "wof:placetype":"venue"
},
  "geometry": {"coordinates":[-122.034077,38.269894],"type":"Point"}
}