{
  "type": "Feature",
  "properties": {
    "iso:country":"US",
    "sg:address":"2932 Joshua Tree Rd",
    "sg:city":"Riverside",
    "sg:classifiers":[
        {
            "category":"Communications",
            "subcategory":"Film & Video Production",
            "type":"Services"
        }
    ],
    "sg:phone":"+1 951 688 6921",
    "sg:postcode":"92503",
    "sg:province":"CA",
    "sg:tags":[
        "taping"
    ],
    "wof:name":"PDR Video Production",
    "wof:placetype":"venue"
},
  "geometry": {"coordinates":[-117.430865,33.912434],"type":"Point"}
}