{
  "type": "Feature",
  "properties": {
    "addr:full":"2225 Via Cerro Riverside CA 92509",
    "addr:housenumber":"2225",
    "addr:postcode":"92509",
    "addr:street":"Via Cerro",
    "iso:country":"US",
    "sg:address":"2225 Via Cerro",
    "sg:city":"Riverside",
    "sg:classifiers":[
        {
            "category":"Wholesale",
            "subcategory":"Auto Parts",
            "type":"Manufacturing & Wholesale Goods"
        }
    ],
    "sg:phone":"+1 951 328 9009",
    "sg:postcode":"92509",
    "sg:province":"CA",
    "sg:tags":[
        "motorcycle"
    ],
    "wof:name":"Platinum One Enterprises Inc",
    "wof:placetype":"venue"
},
  "geometry": {"coordinates":[-117.383065,34.014366],"type":"Point"}
}