{
  "type": "Feature",
  "properties": {
    "iso:country":"US",
    "sg:address":"3118 Vineland Ave",
    "sg:city":"Baldwin Park",
    "sg:classifiers":[
        {
            "category":"Manufacturing",
            "subcategory":"Tools & Machinery",
            "type":"Manufacturing & Wholesale Goods"
        }
    ],
    "sg:phone":"+1 626 374 6925",
    "sg:postcode":"91706",
    "sg:province":"CA",
    "sg:tags":[
        "terminal",
        "computer",
        "mfg"
    ],
    "wof:name":"Ideal Workshop Inc",
    "wof:placetype":"venue"
},
  "geometry": {"coordinates":[-117.969572,34.07092],"type":"Point"}
}