{
  "type": "Feature",
  "properties": {
    "addr:full":"9256 Slauson Ave Pico Rivera CA 90660",
    "addr:housenumber":"9256",
    "addr:postcode":"90660",
    "addr:street":"Slauson Ave",
    "iso:country":"US",
    "sg:address":"9256 Slauson Ave",
    "sg:city":"Pico Rivera",
    "sg:classifiers":[
        {
            "category":"Shopping",
            "subcategory":"Pharmacy",
            "type":"Retail Goods"
        }
    ],
    "sg:phone":"+1 562 949 5424",
    "sg:postcode":"90660",
    "sg:province":"CA",
    "wof:name":"Sav-On Express",
    "wof:placetype":"venue"
},
  "geometry": {"coordinates":[-118.100078,33.969352],"type":"Point"}
}