{
  "type": "Feature",
  "properties": {
    "addr:full":"350 S Milliken Ave Ontario CA 91761",
    "addr:housenumber":"350",
    "addr:postcode":"91761",
    "addr:street":"S Milliken Ave",
    "iso:country":"US",
    "sg:address":"350 S Milliken Ave",
    "sg:city":"Ontario",
    "sg:classifiers":[
        {
            "category":"Building & Trades",
            "subcategory":"Construction",
            "type":"Services"
        }
    ],
    "sg:phone":"+1 909 390 8551",
    "sg:postcode":"91761",
    "sg:province":"CA",
    "sg:tags":[
        "painter"
    ],
    "wof:name":"Giant Painting",
    "wof:placetype":"venue"
},
  "geometry": {"coordinates":[-117.55820900000001,34.06181],"type":"Point"}
}