{
  "type": "Feature",
  "properties": {
    "addr:full":"3336 E Colorado Blvd Pasadena CA 91107",
    "addr:housenumber":"3336",
    "addr:postcode":"91107",
    "addr:street":"E Colorado Blvd",
    "iso:country":"US",
    "sg:address":"3336 E Colorado Blvd",
    "sg:city":"Pasadena",
    "sg:classifiers":[
        {
            "category":"Manufacturing",
            "subcategory":"Printing",
            "type":"Manufacturing & Wholesale Goods"
        }
    ],
    "sg:phone":"+1 626 793 7034",
    "sg:postcode":"91107",
    "sg:province":"CA",
    "sg:tags":[
        "commercial"
    ],
    "sg:website":"www.houseofprintinginc.com",
    "wof:name":"House Of Printing Inc",
    "wof:placetype":"venue"
},
  "geometry": {"coordinates":[-118.08187599999999,34.146159],"type":"Point"}
}