{
  "type": "Feature",
  "properties": {
    "iso:country":"US",
    "sg:address":"17495 Hurley St",
    "sg:city":"City Of Industry",
    "sg:classifiers":[
        {
            "category":"Organizations",
            "subcategory":"Labor Organization",
            "type":"Services"
        }
    ],
    "sg:phone":"+1 626 964 2500",
    "sg:postcode":"91744",
    "sg:province":"CA",
    "wof:name":"Ironworkers Local",
    "wof:placetype":"venue"
},
  "geometry": {"coordinates":[-117.923715,34.011354],"type":"Point"}
}