{
  "type": "Feature",
  "properties": {
    "addr:full":"1833 Springs Rd Vallejo CA 94591",
    "addr:housenumber":"1833",
    "addr:postcode":"94591",
    "addr:street":"Springs Rd",
    "iso:country":"US",
    "sg:address":"1833 Springs Rd",
    "sg:city":"Vallejo",
    "sg:classifiers":[
        {
            "category":"Restaurant",
            "type":"Food & Drink"
        }
    ],
    "sg:menulink":"http://www.allmenus.com/ca/vallejo/74254-dominos-pizza/menu/",
    "sg:phone":"+1 707 553 9860",
    "sg:postcode":"94591",
    "sg:province":"CA",
    "sg:tags":[
        "american",
        "wing",
        "pizza"
    ],
    "wof:name":"Domino's Pizza",
    "wof:placetype":"venue"
},
  "geometry": {"coordinates":[-122.221406,38.105838],"type":"Point"}
}