{
  "type": "Feature",
  "properties": {
    "addr:full":"11 Billou St San Rafael CA 94901",
    "addr:housenumber":"11",
    "addr:postcode":"94901",
    "addr:street":"Billou St",
    "iso:country":"US",
    "sg:address":"11 Billou St",
    "sg:city":"San Rafael",
    "sg:classifiers":[
        {
            "category":"Home & Garden",
            "subcategory":"Home Furnishings",
            "type":"Retail Goods"
        }
    ],
    "sg:phone":"+1 415 453 6808",
    "sg:postcode":"94901",
    "sg:province":"CA",
    "wof:name":"Soldman Laurie Custom Intr Sew",
    "wof:placetype":"venue"
},
  "geometry": {"coordinates":[-122.51972000000001,37.961891],"type":"Point"}
}