{
  "type": "Feature",
  "properties": {
    "addr:full":"5747 Laurel Canyon Blvd Valley Village CA 91607",
    "addr:housenumber":"5747",
    "addr:postcode":"91607",
    "addr:street":"Laurel Canyon Blvd",
    "iso:country":"US",
    "sg:address":"5747 Laurel Canyon Blvd",
    "sg:city":"Valley Village",
    "sg:classifiers":[
        {
            "category":"Wholesale",
            "subcategory":"Computers",
            "type":"Manufacturing & Wholesale Goods"
        }
    ],
    "sg:phone":"+1 818 752 0725",
    "sg:postcode":"91607",
    "sg:province":"CA",
    "sg:tags":[
        "compact",
        "disc"
    ],
    "wof:name":"Schoolhouse Music Shoppe",
    "wof:placetype":"venue"
},
  "geometry": {"coordinates":[-118.39657800000001,34.173868],"type":"Point"}
}