{
  "type": "Feature",
  "properties": {
    "addr:full":"1140 Main St Ramona CA 92065",
    "addr:housenumber":"1140",
    "addr:postcode":"92065",
    "addr:street":"Main St",
    "iso:country":"US",
    "sg:address":"1140 Main St",
    "sg:city":"Ramona",
    "sg:classifiers":[
        {
            "category":"Retail",
            "subcategory":"Laundry & Dry Cleaning",
            "type":"Services"
        }
    ],
    "sg:phone":"+1 760 788 5556",
    "sg:postcode":"92065",
    "sg:province":"CA",
    "sg:tags":[
        "cleaners",
        "rug",
        "carpet"
    ],
    "wof:name":"Big D Carpet Care",
    "wof:placetype":"venue"
},
  "geometry": {"coordinates":[-116.871098,33.040566],"type":"Point"}
}