{
  "type": "Feature",
  "properties": {
    "iso:country":"US",
    "sg:address":"1747 Quail Hollow Rd",
    "sg:city":"Ben Lomond",
    "sg:classifiers":[
        {
            "category":"Real Estate",
            "subcategory":"Real Estate Agent",
            "type":"Services"
        }
    ],
    "sg:phone":"+1 408 248 1874",
    "sg:postcode":"95005",
    "sg:province":"CA",
    "sg:tags":[
        "appraiser"
    ],
    "wof:name":"GWB & Assoc",
    "wof:placetype":"venue"
},
  "geometry": {"coordinates":[-122.07352299999999,37.081485],"type":"Point"}
}