{
  "type": "Feature",
  "properties": {
    "addr:full":"2235 W Lincoln Ave Anaheim CA 92801",
    "addr:housenumber":"2235",
    "addr:postcode":"92801",
    "addr:street":"W Lincoln Ave",
    "iso:country":"US",
    "sg:address":"2235 W Lincoln Ave",
    "sg:city":"Anaheim",
    "sg:classifiers":[
        {
            "category":"Restaurant",
            "type":"Food & Drink"
        }
    ],
    "sg:postcode":"92801",
    "sg:province":"CA",
    "sg:tags":[
        "vietnamese"
    ],
    "wof:name":"Oodles of Noodles",
    "wof:placetype":"venue"
},
  "geometry": {"coordinates":[-117.960842,33.832551],"type":"Point"}
}