{
  "type": "Feature",
  "properties": {
    "iso:country":"US",
    "sg:address":"32252 Cam Capistrano",
    "sg:city":"San Juan Capistrano",
    "sg:classifiers":[
        {
            "category":"Shopping",
            "subcategory":"Used Merchandise",
            "type":"Retail Goods"
        }
    ],
    "sg:phone":"+1 949 496 2056",
    "sg:postcode":"92675",
    "sg:province":"CA",
    "wof:name":"Saint Vincent De Paul Society",
    "wof:placetype":"venue"
},
  "geometry": {"coordinates":[-117.662604,33.493852],"type":"Point"}
}