{
  "type": "Feature",
  "properties": {
    "iso:country":"US",
    "sg:address":"520 Brennan Ave",
    "sg:city":"San Jose",
    "sg:classifiers":[
        {
            "category":"Freight",
            "type":"Transportation"
        }
    ],
    "sg:phone":"+1 408 433 3370",
    "sg:postcode":"95131",
    "sg:province":"CA",
    "sg:tags":[
        "storage",
        "household",
        "moving",
        "local"
    ],
    "wof:name":"Quality Assurance Transport",
    "wof:placetype":"venue"
},
  "geometry": {"coordinates":[-121.913823,37.392271],"type":"Point"}
}