{
  "type": "Feature",
  "properties": {
    "addr:full":"909 E Green St Pasadena CA 91105",
    "addr:housenumber":"909",
    "addr:postcode":"91105",
    "addr:street":"E Green St",
    "iso:country":"US",
    "sg:address":"909 E Green St",
    "sg:city":"Pasadena",
    "sg:classifiers":[
        {
            "category":"Professional",
            "subcategory":"Lawyer & Legal Services",
            "type":"Services"
        }
    ],
    "sg:phone":"+1 626 795 2933",
    "sg:postcode":"91105",
    "sg:province":"CA",
    "sg:tags":[
        "attorney"
    ],
    "sg:website":"www.gjpattorneys.com",
    "wof:name":"Gorton Janosik & Poxon LLP",
    "wof:placetype":"venue"
},
  "geometry": {"coordinates":[-118.131444,34.144632],"type":"Point"}
}