{
  "type": "Feature",
  "properties": {
    "iso:country":"US",
    "sg:address":"10382 Stanford Ave Ste F",
    "sg:city":"Garden Grove",
    "sg:classifiers":[
        {
            "category":"Deli",
            "type":"Food & Drink"
        },
        {
            "category":"Food & Beverages",
            "subcategory":"Meat & Fish",
            "type":"Retail Goods"
        },
        {
            "category":"Food & Beverages",
            "subcategory":"Ethnic Foods",
            "type":"Retail Goods"
        }
    ],
    "sg:phone":"+1 714 539 6334",
    "sg:postcode":"92840",
    "sg:province":"CA",
    "sg:tags":[
        "shop"
    ],
    "sg:website":"intlmeatanddeli.com",
    "wof:name":"International Meat & Deli",
    "wof:placetype":"venue"
},
  "geometry": {"coordinates":[-117.952017,33.77762],"type":"Point"}
}