{
  "type": "Feature",
  "properties": {
    "iso:country":"US",
    "sg:address":"1257 Hassett Ave",
    "sg:city":"Yuba City",
    "sg:classifiers":[
        {
            "category":"Home & Garden",
            "subcategory":"Building Materials",
            "type":"Retail Goods"
        }
    ],
    "sg:phone":"+1 530 671 5061",
    "sg:postcode":"95991",
    "sg:province":"CA",
    "sg:tags":[
        "windows"
    ],
    "wof:name":"Hawkins Exteriors Window",
    "wof:placetype":"venue"
},
  "geometry": {"coordinates":[-121.614013,39.109178],"type":"Point"}
}