{
  "type": "Feature",
  "properties": {
    "iso:country":"US",
    "sg:address":"12 el Portal St",
    "sg:city":"Sausalito",
    "sg:classifiers":[
        {
            "category":"Restaurant",
            "type":"Food & Drink"
        }
    ],
    "sg:phone":"+1 415 332 0211",
    "sg:postcode":"94965",
    "sg:province":"CA",
    "wof:name":"Cafe Tutti",
    "wof:placetype":"venue"
},
  "geometry": {"coordinates":[-122.479441,37.855924],"type":"Point"}
}