{
  "type": "Feature",
  "properties": {
    "iso:country":"US",
    "sg:address":"7240 Hayvenhurst Pl",
    "sg:city":"Van Nuys",
    "sg:classifiers":[
        {
            "category":"Airline",
            "type":"Transportation"
        }
    ],
    "sg:phone":"+1 818 904 6900",
    "sg:postcode":"91406",
    "sg:province":"CA",
    "sg:tags":[
        "nonscheduled",
        "air"
    ],
    "wof:name":"Trans-Exec Air Service",
    "wof:placetype":"venue"
},
  "geometry": {"coordinates":[-118.492418,34.203703],"type":"Point"}
}