{
  "type": "Feature",
  "properties": {
    "iso:country":"US",
    "sg:address":"100 W Foothill Blvd",
    "sg:city":"Pomona",
    "sg:classifiers":[
        {
            "category":"Autos & Motor Vehicles",
            "subcategory":"Fuel & Gas Station",
            "type":"Retail Goods"
        }
    ],
    "sg:phone":"+1 909 593 1502",
    "sg:postcode":"91767",
    "sg:province":"CA",
    "sg:tags":[
        "oil"
    ],
    "wof:name":"Foothill 66",
    "wof:placetype":"venue"
},
  "geometry": {"coordinates":[-117.75081,34.108575],"type":"Point"}
}