{
  "type": "Feature",
  "properties": {
    "addr:full":"9229 Carrari Ct Alta Loma CA 91737",
    "addr:housenumber":"9229",
    "addr:postcode":"91737",
    "addr:street":"Carrari Ct",
    "iso:country":"US",
    "sg:address":"9229 Carrari Ct",
    "sg:city":"Alta Loma",
    "sg:classifiers":[
        {
            "category":"Building & Trades",
            "subcategory":"Landscaping Services",
            "type":"Services"
        }
    ],
    "sg:phone":"+1 909 980 7866",
    "sg:postcode":"91737",
    "sg:province":"CA",
    "sg:tags":[
        "landscape",
        "contractor"
    ],
    "wof:name":"Natural Lawn of America",
    "wof:placetype":"venue"
},
  "geometry": {"coordinates":[-117.605052,34.159202],"type":"Point"}
}