{
  "type": "Feature",
  "properties": {
    "addr:full":"31744 Castaic Rd Ste 201 Castaic CA 91384",
    "addr:housenumber":"31744",
    "addr:postcode":"91384",
    "addr:street":"Castaic Rd Ste 201",
    "iso:country":"US",
    "sg:address":"31744 Castaic Rd Ste 201",
    "sg:city":"Castaic",
    "sg:classifiers":[
        {
            "category":"Professional",
            "subcategory":"Lawyer & Legal Services",
            "type":"Services"
        }
    ],
    "sg:phone":"+1 661 257 7999",
    "sg:postcode":"91384",
    "sg:province":"CA",
    "sg:tags":[
        "notary"
    ],
    "wof:name":"Coldwell Banker Vista Realty",
    "wof:placetype":"venue"
},
  "geometry": {"coordinates":[-118.62200199999999,34.495602],"type":"Point"}
}