{
  "type": "Feature",
  "properties": {
    "addr:full":"720 Bloomington Ave Bloomington CA 92316",
    "addr:housenumber":"720",
    "addr:postcode":"92316",
    "addr:street":"Bloomington Ave",
    "iso:country":"US",
    "sg:address":"720 Bloomington Ave",
    "sg:city":"Bloomington",
    "sg:classifiers":[
        {
            "category":"Insurance",
            "subcategory":"Insurance Agent",
            "type":"Services"
        }
    ],
    "sg:phone":"+1 909 421 1111",
    "sg:postcode":"92316",
    "sg:province":"CA",
    "wof:name":"Bayless & Assoc Inc",
    "wof:placetype":"venue"
},
  "geometry": {"coordinates":[-117.385516,34.079773],"type":"Point"}
}