{
  "type": "Feature",
  "properties": {
    "addr:full":"963 E St Brawley CA 92227",
    "addr:housenumber":"963",
    "addr:postcode":"92227",
    "addr:street":"E St",
    "iso:country":"US",
    "sg:address":"963 E St",
    "sg:city":"Brawley",
    "sg:classifiers":[
        {
            "category":"Professional",
            "subcategory":"Management & Consulting",
            "type":"Services"
        }
    ],
    "sg:phone":"+1 760 344 5071",
    "sg:postcode":"92227",
    "sg:province":"CA",
    "sg:tags":[
        "administrative",
        "program",
        "economic",
        "general"
    ],
    "wof:name":"Campesinos Unidos Inc",
    "wof:placetype":"venue"
},
  "geometry": {"coordinates":[-115.527309,32.979848],"type":"Point"}
}