{
  "type": "Feature",
  "properties": {
    "iso:country":"US",
    "sg:address":"25420 Crenshaw Blvd",
    "sg:city":"Torrance",
    "sg:classifiers":[
        {
            "category":"Restaurant",
            "type":"Food & Drink"
        }
    ],
    "sg:phone":"+1 310 534 3770",
    "sg:postcode":"90505",
    "sg:province":"CA",
    "sg:tags":[
        "tea",
        "coffee"
    ],
    "wof:name":"Lollicup Boba Cafe",
    "wof:placetype":"venue"
},
  "geometry": {"coordinates":[-118.333,33.7924],"type":"Point"}
}