{
  "type": "Feature",
  "properties": {
    "addr:full":"8600 Valley Ford Rd Petaluma CA 94952",
    "addr:housenumber":"8600",
    "addr:postcode":"94952",
    "addr:street":"Valley Ford Rd",
    "iso:country":"US",
    "sg:address":"8600 Valley Ford Rd",
    "sg:city":"Petaluma",
    "sg:classifiers":[
        {
            "category":"Retail",
            "subcategory":"Veterinary Services",
            "type":"Services"
        }
    ],
    "sg:phone":"+1 707 765 8520",
    "sg:postcode":"94952",
    "sg:province":"CA",
    "sg:tags":[
        "veterinarian"
    ],
    "wof:name":"St",
    "wof:placetype":"venue"
},
  "geometry": {"coordinates":[-122.80126,38.287582],"type":"Point"}
}