{
  "type": "Feature",
  "properties": {
    "iso:country":"US",
    "sg:address":"10716 Telechron Ave",
    "sg:city":"Whittier",
    "sg:classifiers":[
        {
            "category":"Home & Garden",
            "subcategory":"Carpets & Floor Coverings",
            "type":"Retail Goods"
        }
    ],
    "sg:phone":"+1 562 777 2351",
    "sg:postcode":"90605",
    "sg:province":"CA",
    "sg:tags":[
        "material"
    ],
    "wof:name":"Albertos Hardwood Floors",
    "wof:placetype":"venue"
},
  "geometry": {"coordinates":[-118.039339,33.934979],"type":"Point"}
}