{
  "type": "Feature",
  "properties": {
    "addr:full":"3521 1/2 Ocean View Blvd Glendale CA 91208",
    "addr:housenumber":"3521 1 / 2",
    "addr:postcode":"91208",
    "addr:street":"Ocean View Blvd",
    "iso:country":"US",
    "sg:address":"3521 1/2 Ocean View Blvd",
    "sg:city":"Glendale",
    "sg:classifiers":[
        {
            "category":"Travel",
            "subcategory":"Travel Agent",
            "type":"Entertainment"
        },
        {
            "category":"Landmark",
            "subcategory":"Tourist Information",
            "type":"Public Place"
        }
    ],
    "sg:phone":"+1 818 240 3313",
    "sg:postcode":"91208",
    "sg:province":"CA",
    "sg:tags":[
        "tour"
    ],
    "sg:website":"www.classictravels.com",
    "wof:name":"Classic Travels",
    "wof:placetype":"venue"
},
  "geometry": {"coordinates":[-118.22829400000001,34.203451],"type":"Point"}
}