{
  "type": "Feature",
  "properties": {
    "iso:country":"US",
    "sg:address":"39210 State St",
    "sg:city":"Fremont",
    "sg:classifiers":[
        {
            "category":"Health Services",
            "subcategory":"Doctor",
            "type":"Services"
        }
    ],
    "sg:phone":"+1 510 797 3636",
    "sg:postcode":"94538",
    "sg:province":"CA",
    "sg:tags":[
        "dentist"
    ],
    "wof:name":"Eun Hahn DDS",
    "wof:placetype":"venue"
},
  "geometry": {"coordinates":[-121.98352300000001,37.549536],"type":"Point"}
}