{
  "type": "Feature",
  "properties": {
    "addr:full":"520 S Mountain Ave Ontario CA 91762",
    "addr:housenumber":"520",
    "addr:postcode":"91762",
    "addr:street":"S Mountain Ave",
    "iso:country":"US",
    "sg:address":"520 S Mountain Ave",
    "sg:city":"Ontario",
    "sg:classifiers":[
        {
            "category":"Shopping",
            "subcategory":"Computers & Home Electronics",
            "type":"Retail Goods"
        }
    ],
    "sg:phone":"+1 909 933 3577",
    "sg:postcode":"91762",
    "sg:province":"CA",
    "sg:tags":[
        "equipment",
        "dealer"
    ],
    "sg:website":"www.computerannexusa.com",
    "wof:name":"Computer Annex Corp",
    "wof:placetype":"venue"
},
  "geometry": {"coordinates":[-117.66986799999999,34.059177],"type":"Point"}
}