{
  "type": "Feature",
  "properties": {
    "iso:country":"US",
    "sg:address":"1415 E Colorado St",
    "sg:city":"Glendale",
    "sg:classifiers":[
        {
            "category":"Restaurant",
            "type":"Food & Drink"
        }
    ],
    "sg:phone":"+1 818 662 8988",
    "sg:postcode":"91205",
    "sg:province":"CA",
    "wof:name":"Chang Woo BBQ",
    "wof:placetype":"venue"
},
  "geometry": {"coordinates":[-118.23329200000001,34.14285],"type":"Point"}
}