{
  "type": "Feature",
  "properties": {
    "addr:full":"2625 Sierra Meadows Dr Rocklin CA 95677",
    "addr:housenumber":"2625",
    "addr:postcode":"95677",
    "addr:street":"Sierra Meadows Dr",
    "iso:country":"US",
    "sg:address":"2625 Sierra Meadows Dr",
    "sg:city":"Rocklin",
    "sg:classifiers":[
        {
            "category":"Restaurant",
            "type":"Food & Drink"
        }
    ],
    "sg:menulink":"http://www.allmenus.com/ca/loomis-basin-folsom-lake/135614-jamba-juice/menu/",
    "sg:phone":"+1 916 625 0478",
    "sg:postcode":"95677",
    "sg:province":"CA",
    "sg:tags":[
        "smoothy",
        "juice",
        "american"
    ],
    "wof:name":"Jamba Juice",
    "wof:placetype":"venue"
},
  "geometry": {"coordinates":[-121.22263100000001,38.793171],"type":"Point"}
}