{
  "type": "Feature",
  "properties": {
    "iso:country":"US",
    "sg:address":"3401 International Blvd",
    "sg:city":"Oakland",
    "sg:classifiers":[
        {
            "category":"Food & Beverages",
            "subcategory":"Meat & Fish",
            "type":"Retail Goods"
        }
    ],
    "sg:phone":"+1 510 533 8569",
    "sg:postcode":"94601",
    "sg:province":"CA",
    "sg:tags":[
        "shop",
        "super",
        "supermarket",
        "store"
    ],
    "wof:name":"Carniceria Mi Barrio",
    "wof:placetype":"venue"
},
  "geometry": {"coordinates":[-122.223703,37.776365],"type":"Point"}
}