{
  "type": "Feature",
  "properties": {
    "iso:country":"US",
    "sg:address":"205 Cam Alto",
    "sg:city":"Mill Valley",
    "sg:classifiers":[
        {
            "category":"Social Services",
            "type":"Services"
        }
    ],
    "sg:phone":"+1 415 383 4524",
    "sg:postcode":"94941",
    "sg:province":"CA",
    "sg:tags":[
        "worker"
    ],
    "wof:name":"Gayle Donsky",
    "wof:placetype":"venue"
},
  "geometry": {"coordinates":[-122.526995,37.903729],"type":"Point"}
}