{
  "type": "Feature",
  "properties": {
    "addr:full":"1250 Laurel St. Menlo Park, Ca 94025",
    "wof:categories":[
        "education_and_religion:education=school"
    ],
    "wof:name":"Nativity Elementary School",
    "wof:placetype":"venue"
},
  "geometry": {"coordinates":[-122.18321536934172,37.45776582734885],"type":"Point"}
}