{
  "type": "Feature",
  "properties": {
    "addr:full":"42430 Winchester Rd Temecula CA 92590",
    "addr:housenumber":"42430",
    "addr:postcode":"92590",
    "addr:street":"Winchester Rd",
    "iso:country":"US",
    "sg:address":"42430 Winchester Rd",
    "sg:city":"Temecula",
    "sg:classifiers":[
        {
            "category":"Banks & Credit Unions",
            "subcategory":"Bank",
            "type":"Services"
        }
    ],
    "sg:phone":"+1 951 699 9716",
    "sg:postcode":"92590",
    "sg:province":"CA",
    "sg:tags":[
        "loan",
        "real estate"
    ],
    "wof:name":"Parker Processing",
    "wof:placetype":"venue"
},
  "geometry": {"coordinates":[-117.17783799999999,33.509322],"type":"Point"}
}