{
  "type": "Feature",
  "properties": {
    "iso:country":"US",
    "sg:address":"2044 E Front St",
    "sg:city":"Selma",
    "sg:classifiers":[
        {
            "category":"Wholesale",
            "subcategory":"Electrical",
            "type":"Manufacturing & Wholesale Goods"
        }
    ],
    "sg:phone":"+1 559 891 0636",
    "sg:postcode":"93662",
    "sg:province":"CA",
    "sg:tags":[
        "electric",
        "motor"
    ],
    "wof:name":"Selma Electric Motor Shop",
    "wof:placetype":"venue"
},
  "geometry": {"coordinates":[-119.613445,36.568764],"type":"Point"}
}