{
  "type": "Feature",
  "properties": {
    "addr:full":"9 Arastradero Rd Portola Valley CA 94028",
    "addr:housenumber":"9",
    "addr:postcode":"94028",
    "addr:street":"Arastradero Rd",
    "iso:country":"US",
    "sg:address":"9 Arastradero Rd",
    "sg:city":"Portola Valley",
    "sg:classifiers":[
        {
            "category":"Wholesale",
            "subcategory":"Machinery & Supplies",
            "type":"Manufacturing & Wholesale Goods"
        }
    ],
    "sg:phone":"+1 650 854 7454",
    "sg:postcode":"94028",
    "sg:province":"CA",
    "sg:tags":[
        "equipment",
        "industrial"
    ],
    "wof:name":"Interport Limited",
    "wof:placetype":"venue"
},
  "geometry": {"coordinates":[-122.19328299999999,37.382702],"type":"Point"}
}