{
  "type": "Feature",
  "properties": {
    "addr:full":"207 N 5th St San Jose CA 95112",
    "addr:housenumber":"207",
    "addr:postcode":"95112",
    "addr:street":"N 5Th St",
    "iso:country":"US",
    "sg:address":"207 N 5th St",
    "sg:city":"San Jose",
    "sg:classifiers":[
        {
            "category":"Insurance",
            "subcategory":"Hazard Insurance",
            "type":"Services"
        }
    ],
    "sg:phone":"+1 408 416 3406",
    "sg:postcode":"95112",
    "sg:province":"CA",
    "sg:website":"www.oakhillinsuranceservices.com",
    "wof:name":"Oak Hill Insurance Services",
    "wof:placetype":"venue"
},
  "geometry": {"coordinates":[-121.889043,37.341324],"type":"Point"}
}