{
  "type": "Feature",
  "properties": {
    "iso:country":"US",
    "sg:address":"1300 W Optical Dr",
    "sg:city":"Azusa",
    "sg:classifiers":[
        {
            "category":"Professional",
            "type":"Services"
        }
    ],
    "sg:phone":"+1 626 815 3015",
    "sg:postcode":"91702",
    "sg:province":"CA",
    "sg:tags":[
        "establishment"
    ],
    "wof:name":"Mentor Corp",
    "wof:placetype":"venue"
},
  "geometry": {"coordinates":[-117.927506,34.128634],"type":"Point"}
}