{
  "type": "Feature",
  "properties": {
    "addr:full":"4143 Via Marina Marina Del Rey CA 90292",
    "addr:housenumber":"4143",
    "addr:postcode":"90292",
    "addr:street":"Via Marina",
    "iso:country":"US",
    "sg:address":"4143 Via Marina",
    "sg:city":"Marina Del Rey",
    "sg:classifiers":[
        {
            "category":"Professional",
            "type":"Services"
        }
    ],
    "sg:phone":"+1 310 822 0671",
    "sg:postcode":"90292",
    "sg:province":"CA",
    "wof:name":"Atlas News Corp",
    "wof:placetype":"venue"
},
  "geometry": {"coordinates":[-118.459873,33.981596],"type":"Point"}
}