{
  "type": "Feature",
  "properties": {
    "iso:country":"US",
    "sg:address":"10807 Sheldon Woods Way",
    "sg:city":"Elk Grove",
    "sg:classifiers":[
        {
            "category":"Farming",
            "subcategory":"Farm & Veterinary Services",
            "type":"Manufacturing & Wholesale Goods"
        }
    ],
    "sg:phone":"+1 916 682 4441",
    "sg:postcode":"95624",
    "sg:province":"CA",
    "sg:tags":[
        "livestock"
    ],
    "wof:name":"Vom Deil Bachtal Dog Kennel",
    "wof:placetype":"venue"
},
  "geometry": {"coordinates":[-121.286045,38.433553],"type":"Point"}
}