{
  "type": "Feature",
  "properties": {
    "addr:full":"14085 Valley Blvd Fontana CA 92335",
    "addr:housenumber":"14085",
    "addr:postcode":"92335",
    "addr:street":"Valley Blvd",
    "iso:country":"US",
    "sg:address":"14085 Valley Blvd",
    "sg:city":"Fontana",
    "sg:classifiers":[
        {
            "category":"Autos & Motor Vehicles",
            "subcategory":"Automobile Sales",
            "type":"Retail Goods"
        }
    ],
    "sg:phone":"+1 909 349 0200",
    "sg:postcode":"92335",
    "sg:province":"CA",
    "sg:tags":[
        "truck"
    ],
    "wof:name":"Mack Trucks Inc",
    "wof:placetype":"venue"
},
  "geometry": {"coordinates":[-117.498009,34.070092],"type":"Point"}
}