{
  "type": "Feature",
  "properties": {
    "addr:full":"3350 College Blvd Oceanside CA 92056",
    "addr:housenumber":"3350",
    "addr:postcode":"92056",
    "addr:street":"College Blvd",
    "iso:country":"US",
    "sg:address":"3350 College Blvd",
    "sg:city":"Oceanside",
    "sg:classifiers":[
        {
            "category":"Food & Beverages",
            "subcategory":"Groceries & Convenience Stores",
            "type":"Retail Goods"
        }
    ],
    "sg:phone":"+1 760 724 9740",
    "sg:postcode":"92056",
    "sg:province":"CA",
    "wof:name":"Circle K Food Stores",
    "wof:placetype":"venue"
},
  "geometry": {"coordinates":[-117.296997,33.1847],"type":"Point"}
}