{
  "type": "Feature",
  "properties": {
    "iso:country":"US",
    "sg:address":"38505 Cherry St",
    "sg:city":"Newark",
    "sg:classifiers":[
        {
            "category":"Manufacturing",
            "subcategory":"Building Materials",
            "type":"Manufacturing & Wholesale Goods"
        }
    ],
    "sg:phone":"+1 510 794 8116",
    "sg:postcode":"94560",
    "sg:province":"CA",
    "wof:name":"Accurate Moulding & Millwork",
    "wof:placetype":"venue"
},
  "geometry": {"coordinates":[-122.017323,37.524293],"type":"Point"}
}