{
  "type": "Feature",
  "properties": {
    "iso:country":"US",
    "sg:address":"912 Postal Way",
    "sg:city":"Vista",
    "sg:classifiers":[
        {
            "category":"Retail",
            "subcategory":"Auto Repair",
            "type":"Services"
        }
    ],
    "sg:phone":"+1 760 630 0420",
    "sg:postcode":"92083",
    "sg:province":"CA",
    "sg:tags":[
        "repairing",
        "automobile"
    ],
    "wof:name":"German Auto Clinic",
    "wof:placetype":"venue"
},
  "geometry": {"coordinates":[-117.234981,33.192618],"type":"Point"}
}