{
  "type": "Feature",
  "properties": {
    "iso:country":"US",
    "sg:address":"507 S Warner St",
    "sg:city":"Ridgecrest",
    "sg:classifiers":[
        {
            "category":"Home & Garden",
            "subcategory":"Carpets & Floor Coverings",
            "type":"Retail Goods"
        }
    ],
    "sg:phone":"+1 760 375 6529",
    "sg:postcode":"93555",
    "sg:province":"CA",
    "sg:tags":[
        "cleaning"
    ],
    "wof:name":"Static Attraction Carpet Care",
    "wof:placetype":"venue"
},
  "geometry": {"coordinates":[-117.674653,35.614068],"type":"Point"}
}