{
  "type": "Feature",
  "properties": {
    "addr:full":"22649 Ventura Blvd Woodland Hills CA 91364",
    "addr:housenumber":"22649",
    "addr:postcode":"91364",
    "addr:street":"Ventura Blvd",
    "iso:country":"US",
    "sg:address":"22649 Ventura Blvd",
    "sg:city":"Woodland Hills",
    "sg:classifiers":[
        {
            "category":"Food & Beverages",
            "subcategory":"Bakery",
            "type":"Retail Goods"
        }
    ],
    "sg:phone":"+1 818 224 2725",
    "sg:postcode":"91364",
    "sg:province":"CA",
    "sg:tags":[
        "sandwich"
    ],
    "wof:name":"Quizno's Subs",
    "wof:placetype":"venue"
},
  "geometry": {"coordinates":[-118.620003,34.166901],"type":"Point"}
}