{
  "type": "Feature",
  "properties": {
    "addr:full":"23342 Lyons Ave Newhall CA 91321",
    "addr:housenumber":"23342",
    "addr:postcode":"91321",
    "addr:street":"Lyons Ave",
    "iso:country":"US",
    "sg:address":"23342 Lyons Ave",
    "sg:city":"Newhall",
    "sg:classifiers":[
        {
            "category":"Donuts",
            "subcategory":"None",
            "type":"Food & Drink"
        }
    ],
    "sg:phone":"+1 661 799 3667",
    "sg:postcode":"91321",
    "sg:province":"CA",
    "sg:tags":[
        "shop"
    ],
    "sg:website":"www.yumyumdonuts.com",
    "wof:name":"Yum Yum Donuts",
    "wof:placetype":"venue"
},
  "geometry": {"coordinates":[-118.54151400000001,34.379693],"type":"Point"}
}