{
  "type": "Feature",
  "properties": {
    "addr:full":"1319 Kowalski Ave Santa Barbara CA 93101",
    "addr:housenumber":"1319",
    "addr:postcode":"93101",
    "addr:street":"Kowalski Ave",
    "iso:country":"US",
    "sg:address":"1319 Kowalski Ave",
    "sg:city":"Santa Barbara",
    "sg:classifiers":[
        {
            "category":"Retail",
            "subcategory":"Repair Shop",
            "type":"Services"
        }
    ],
    "sg:phone":"+1 805 965 5897",
    "sg:postcode":"93101",
    "sg:province":"CA",
    "sg:tags":[
        "caning"
    ],
    "wof:name":"Carla Stellwagen Chair Caning",
    "wof:placetype":"venue"
},
  "geometry": {"coordinates":[-119.717386,34.415122],"type":"Point"}
}