{
  "type": "Feature",
  "properties": {
    "iso:country":"US",
    "sg:address":"5934 W Cutler Ct",
    "sg:city":"Visalia",
    "sg:classifiers":[
        {
            "category":"Professional",
            "type":"Services"
        }
    ],
    "sg:phone":"+1 559 627 2724",
    "sg:postcode":"93277",
    "sg:province":"CA",
    "sg:tags":[
        "establishment"
    ],
    "wof:name":"Daizy & Assoc",
    "wof:placetype":"venue"
},
  "geometry": {"coordinates":[-119.357053,36.310787],"type":"Point"}
}