{
  "type": "Feature",
  "properties": {
    "addr:full":"306 W Compton Blvd Compton CA 90220",
    "addr:housenumber":"306",
    "addr:postcode":"90220",
    "addr:street":"W Compton Blvd",
    "iso:country":"US",
    "sg:address":"306 W Compton Blvd",
    "sg:city":"Compton",
    "sg:classifiers":[
        {
            "category":"Shopping",
            "type":"Retail Goods"
        }
    ],
    "sg:phone":"+1 310 632 8654",
    "sg:postcode":"90220",
    "sg:province":"CA",
    "sg:tags":[
        "cosmetic",
        "perfume"
    ],
    "wof:name":"Avon Products",
    "wof:placetype":"venue"
},
  "geometry": {"coordinates":[-118.228589,33.895871],"type":"Point"}
}