{
  "type": "Feature",
  "properties": {
    "addr:full":"2260 Grass Valley Hwy Auburn CA 95603",
    "addr:housenumber":"2260",
    "addr:postcode":"ca 95603",
    "addr:street":"Grass Valley Hwy",
    "iso:country":"US",
    "sg:address":"2260 Grass Valley Hwy",
    "sg:city":"Auburn",
    "sg:classifiers":[
        {
            "category":"Restaurant",
            "type":"Food & Drink"
        }
    ],
    "sg:menulink":"http://www.allmenus.com/ca/auburn/75040-round-table-pizza/menu/",
    "sg:phone":"+1 530 823 0126",
    "sg:postcode":"95603",
    "sg:province":"CA",
    "sg:tags":[
        "american",
        "pizza"
    ],
    "wof:name":"Round Table Pizza",
    "wof:placetype":"venue"
},
  "geometry": {"coordinates":[-121.092615,38.934447],"type":"Point"}
}