{
  "type": "Feature",
  "properties": {
    "iso:country":"US",
    "sg:address":"1533 W Elgenia Ave",
    "sg:city":"West Covina",
    "sg:classifiers":[
        {
            "category":"Building & Trades",
            "subcategory":"Landscaping Services",
            "type":"Services"
        }
    ],
    "sg:phone":"+1 626 814 8005",
    "sg:postcode":"91790",
    "sg:province":"CA",
    "sg:tags":[
        "designer",
        "landscape"
    ],
    "wof:name":"Kiktavi Landscape Design",
    "wof:placetype":"venue"
},
  "geometry": {"coordinates":[-117.93688400000001,34.086341],"type":"Point"}
}