{
  "type": "Feature",
  "properties": {
    "addr:full":"1053 Di Giulio Ave Santa Clara CA 95050",
    "addr:housenumber":"1053",
    "addr:postcode":"95050",
    "addr:street":"Di Giulio Ave",
    "iso:country":"US",
    "sg:address":"1053 Di Giulio Ave",
    "sg:city":"Santa Clara",
    "sg:classifiers":[
        {
            "category":"Shopping",
            "subcategory":"News",
            "type":"Retail Goods"
        }
    ],
    "sg:phone":"+1 510 427 6433",
    "sg:postcode":"95050",
    "sg:province":"CA",
    "sg:tags":[
        "dealer"
    ],
    "wof:name":"Korean Sunday News",
    "wof:placetype":"venue"
},
  "geometry": {"coordinates":[-121.950846,37.361095],"type":"Point"}
}