{
  "type": "Feature",
  "properties": {
    "addr:full":"226 S School St Lodi CA 95240",
    "addr:housenumber":"226",
    "addr:postcode":"95240",
    "addr:street":"S School St",
    "iso:country":"US",
    "sg:address":"226 S School St",
    "sg:city":"Lodi",
    "sg:classifiers":[
        {
            "category":"Shopping",
            "subcategory":"Shoes",
            "type":"Retail Goods"
        }
    ],
    "sg:phone":"+1 209 334 6822",
    "sg:postcode":"95240",
    "sg:province":"CA",
    "wof:name":"Burton's Shoes",
    "wof:placetype":"venue"
},
  "geometry": {"coordinates":[-121.273838,38.130725],"type":"Point"}
}