{
  "type": "Feature",
  "properties": {
    "iso:country":"US",
    "sg:address":"1230 Martin Luther King Jr Ave",
    "sg:city":"Long Beach",
    "sg:classifiers":[
        {
            "category":"Professional",
            "type":"Services"
        },
        {
            "category":"Shopping",
            "subcategory":"Bicycles & Sporting Goods",
            "type":"Retail Goods"
        }
    ],
    "sg:phone":"+1 562 590 6461",
    "sg:postcode":"90813",
    "sg:province":"CA",
    "sg:tags":[
        "equipment",
        "soccer",
        "supply"
    ],
    "wof:name":"Soccer Guadalajara",
    "wof:placetype":"venue"
},
  "geometry": {"coordinates":[-118.180606,33.782309],"type":"Point"}
}