{
  "type": "Feature",
  "properties": {
    "iso:country":"US",
    "sg:address":"2554 Lincoln Blvd",
    "sg:city":"Venice",
    "sg:classifiers":[
        {
            "category":"Professional",
            "subcategory":"Business Services",
            "type":"Services"
        }
    ],
    "sg:phone":"+1 310 822 9674",
    "sg:postcode":"90291",
    "sg:province":"CA",
    "sg:tags":[
        "process",
        "server"
    ],
    "wof:name":"Western Star Attorney Svc",
    "wof:placetype":"venue"
},
  "geometry": {"coordinates":[-118.448256,33.991129],"type":"Point"}
}