{
  "type": "Feature",
  "properties": {
    "iso:country":"US",
    "sg:address":"9051 G Ave Apt 57",
    "sg:city":"Hesperia",
    "sg:classifiers":[
        {
            "category":"Real Estate",
            "subcategory":"Real Estate Operator",
            "type":"Services"
        }
    ],
    "sg:phone":"+1 760 244 1124",
    "sg:postcode":"92345",
    "sg:province":"CA",
    "sg:tags":[
        "apartment"
    ],
    "wof:name":"Desert Manor Apts",
    "wof:placetype":"venue"
},
  "geometry": {"coordinates":[-117.28959999999999,34.411157],"type":"Point"}
}