{
  "type": "Feature",
  "properties": {
    "addr:full":"3576 Unocal Pl Santa Rosa CA 95403",
    "addr:housenumber":"3576",
    "addr:postcode":"95403",
    "addr:street":"Unocal Pl",
    "iso:country":"US",
    "sg:address":"3576 Unocal Pl",
    "sg:city":"Santa Rosa",
    "sg:classifiers":[
        {
            "category":"Wholesale",
            "subcategory":"Medical Equipment & Supplies",
            "type":"Manufacturing & Wholesale Goods"
        }
    ],
    "sg:phone":"+1 707 525 0111",
    "sg:postcode":"95403",
    "sg:province":"CA",
    "sg:tags":[
        "physician",
        "surgeon"
    ],
    "wof:name":"Medtronic Vascular",
    "wof:placetype":"venue"
},
  "geometry": {"coordinates":[-122.722202,38.479854],"type":"Point"}
}