{
  "type": "Feature",
  "properties": {
    "iso:country":"US",
    "sg:address":"918 18th St",
    "sg:city":"Oakland",
    "sg:classifiers":[
        {
            "category":"Shopping",
            "type":"Retail Goods"
        }
    ],
    "sg:phone":"+1 510 452 2059",
    "sg:postcode":"94607",
    "sg:province":"CA",
    "sg:tags":[
        "picture",
        "frame"
    ],
    "sg:website":"http://www.samuelsgallery.com",
    "wof:name":"Samuels Gallery",
    "wof:placetype":"venue"
},
  "geometry": {"coordinates":[-122.280224,37.811224],"type":"Point"}
}