{
  "type": "Feature",
  "properties": {
    "iso:country":"US",
    "sg:address":"2977 Ygnacio Valley Rd",
    "sg:city":"Walnut Creek",
    "sg:classifiers":[
        {
            "category":"Building & Trades",
            "subcategory":"Construction",
            "type":"Services"
        }
    ],
    "sg:phone":"+1 925 930 6690",
    "sg:postcode":"94598",
    "sg:province":"CA",
    "sg:tags":[
        "fire",
        "restoration",
        "damage"
    ],
    "wof:name":"Servpro",
    "wof:placetype":"venue"
},
  "geometry": {"coordinates":[-122.01794599999999,37.926026],"type":"Point"}
}