{
  "type": "Feature",
  "properties": {
    "addr:full":"13131 Wichita Way Moreno Valley CA 92555",
    "addr:housenumber":"13131",
    "addr:postcode":"92555",
    "addr:street":"Wichita Way",
    "iso:country":"US",
    "sg:address":"13131 Wichita Way",
    "sg:city":"Moreno Valley",
    "sg:classifiers":[
        {
            "category":"Organizations",
            "subcategory":"Religious Organization",
            "type":"Services"
        }
    ],
    "sg:phone":"+1 951 485 4422",
    "sg:postcode":"92555",
    "sg:province":"CA",
    "sg:tags":[
        "church"
    ],
    "sg:website":"www.rcawest.org",
    "wof:name":"Reformed Church In America",
    "wof:placetype":"venue"
},
  "geometry": {"coordinates":[-117.205074,33.930736],"type":"Point"}
}