{
  "type": "Feature",
  "properties": {
    "iso:country":"US",
    "sg:address":"1057 Lighthouse Rd",
    "sg:city":"Carlsbad",
    "sg:classifiers":[
        {
            "category":"Wholesale",
            "subcategory":"Computers",
            "type":"Manufacturing & Wholesale Goods"
        }
    ],
    "sg:phone":"+1 760 930 9600",
    "sg:postcode":"92009",
    "sg:province":"CA",
    "sg:website":"www.smart-technologies.com",
    "wof:name":"Smart Technologies",
    "wof:placetype":"venue"
},
  "geometry": {"coordinates":[-117.306,33.1115],"type":"Point"}
}