{
  "type": "Feature",
  "properties": {
    "addr:full":"720 Colusa Hwy Gridley CA 95948",
    "addr:housenumber":"720",
    "addr:postcode":"95948",
    "addr:street":"Colusa Hwy",
    "iso:country":"US",
    "sg:address":"720 Colusa Hwy",
    "sg:city":"Gridley",
    "sg:classifiers":[
        {
            "category":"Building & Trades",
            "subcategory":"Equipment Rental",
            "type":"Services"
        }
    ],
    "sg:phone":"+1 530 824 3201",
    "sg:postcode":"95948",
    "sg:province":"CA",
    "sg:tags":[
        "toilet"
    ],
    "sg:website":"www.benportashowers.com",
    "wof:name":"Ben Toilets",
    "wof:placetype":"venue"
},
  "geometry": {"coordinates":[-121.72236100000001,39.363064],"type":"Point"}
}