{
  "type": "Feature",
  "properties": {
    "iso:country":"US",
    "sg:address":"3100 Foothill Blvd",
    "sg:city":"La Crescenta",
    "sg:classifiers":[
        {
            "category":"Home & Garden",
            "subcategory":"Hardware",
            "type":"Retail Goods"
        }
    ],
    "sg:phone":"+1 818 541 7075",
    "sg:postcode":"91214",
    "sg:province":"CA",
    "sg:tags":[
        "supply"
    ],
    "wof:name":"Orchard Supply Hardware Corp",
    "wof:placetype":"venue"
},
  "geometry": {"coordinates":[-118.24725100000001,34.228698],"type":"Point"}
}