{
  "type": "Feature",
  "properties": {
    "iso:country":"US",
    "sg:address":"737 Dias St",
    "sg:city":"Sand City",
    "sg:classifiers":[
        {
            "category":"Wholesale",
            "subcategory":"Durable Goods & Equipment",
            "type":"Manufacturing & Wholesale Goods"
        }
    ],
    "sg:phone":"+1 831 372 6760",
    "sg:postcode":"93955",
    "sg:province":"CA",
    "sg:tags":[
        "fire",
        "extinguisher"
    ],
    "wof:name":"Monterey Frie Extinguisher",
    "wof:placetype":"venue"
},
  "geometry": {"coordinates":[-121.847925,36.613362],"type":"Point"}
}