{
  "type": "Feature",
  "properties": {
    "iso:country":"US",
    "sg:address":"7410 Melrose Ave",
    "sg:city":"Los Angeles",
    "sg:classifiers":[
        {
            "category":"Shopping",
            "subcategory":"Clothing, Apparel, & Fashions",
            "type":"Retail Goods"
        }
    ],
    "sg:phone":"+1 323 653 1170",
    "sg:postcode":"90046",
    "sg:province":"CA",
    "sg:tags":[
        "men's",
        "clothing",
        "accessory"
    ],
    "sg:website":"www.shopblackjack.com",
    "wof:name":"BlackJack Clothing",
    "wof:placetype":"venue"
},
  "geometry": {"coordinates":[-118.351997,34.083698],"type":"Point"}
}