{
  "type": "Feature",
  "properties": {
    "iso:country":"US",
    "sg:address":"559 Campbell Technology",
    "sg:city":"Campbell",
    "sg:classifiers":[
        {
            "category":"Home & Garden",
            "subcategory":"Building Materials",
            "type":"Retail Goods"
        }
    ],
    "sg:phone":"+1 408 377 0105",
    "sg:postcode":"95008",
    "sg:province":"CA",
    "sg:tags":[
        "equipment",
        "fixture",
        "lighting"
    ],
    "sg:website":"www.jcbarryskylights.com/",
    "wof:name":"Barry J C Skylights Manufacturer",
    "wof:placetype":"venue"
},
  "geometry": {"coordinates":[-121.94113900000001,37.278234],"type":"Point"}
}