{
  "type": "Feature",
  "properties": {
    "iso:country":"US",
    "sg:address":"10806 Prospect Ave",
    "sg:city":"Santee",
    "sg:phone":"+1 619 440 4774",
    "sg:postcode":"92071",
    "sg:province":"CA",
    "wof:name":"Collision Repair Specialists",
    "wof:placetype":"venue"
},
  "geometry": {"coordinates":[-116.963795,32.831074],"type":"Point"}
}