{
  "type": "Feature",
  "properties": {
    "iso:country":"US",
    "sg:address":"15235 Springdale St",
    "sg:city":"Huntington Beach",
    "sg:classifiers":[
        {
            "category":"Professional",
            "subcategory":"Business Services",
            "type":"Services"
        }
    ],
    "sg:phone":"+1 714 379 7020",
    "sg:postcode":"92683",
    "sg:province":"CA",
    "sg:tags":[
        "paralegal"
    ],
    "wof:name":"A-Plus-One Paralegal",
    "wof:placetype":"venue"
},
  "geometry": {"coordinates":[-118.02460499999999,33.742805],"type":"Point"}
}