{
  "type": "Feature",
  "properties": {
    "addr:full":"7258 Bark Ln San Jose CA 95129",
    "addr:housenumber":"7258",
    "addr:postcode":"95129",
    "addr:street":"Bark Ln",
    "iso:country":"US",
    "sg:address":"7258 Bark Ln",
    "sg:city":"San Jose",
    "sg:classifiers":[
        {
            "category":"Professional",
            "subcategory":"Advertising",
            "type":"Services"
        }
    ],
    "sg:phone":"+1 408 973 1191",
    "sg:postcode":"95129",
    "sg:province":"CA",
    "sg:tags":[
        "agency"
    ],
    "wof:name":"Company Image",
    "wof:placetype":"venue"
},
  "geometry": {"coordinates":[-122.03059,37.302949],"type":"Point"}
}