{
  "type": "Feature",
  "properties": {
    "iso:country":"US",
    "sg:address":"5814 N Sunbury Rd",
    "sg:city":"Stockton",
    "sg:classifiers":[
        {
            "category":"Farming",
            "subcategory":"Crops",
            "type":"Manufacturing & Wholesale Goods"
        }
    ],
    "sg:phone":"+1 209 931 1754",
    "sg:postcode":"95212",
    "sg:province":"CA",
    "sg:tags":[
        "grove",
        "nut",
        "tree"
    ],
    "wof:name":"Pacific Breeze",
    "wof:placetype":"venue"
},
  "geometry": {"coordinates":[-121.23851500000001,38.022089],"type":"Point"}
}