{
  "type": "Feature",
  "properties": {
    "addr:full":"1515 W Front St Selma CA 93662",
    "addr:housenumber":"1515",
    "addr:postcode":"93662",
    "addr:street":"W Front St",
    "iso:country":"US",
    "sg:address":"1515 W Front St",
    "sg:city":"Selma",
    "sg:classifiers":[
        {
            "category":"Home & Garden",
            "subcategory":"Garden Supply",
            "type":"Retail Goods"
        }
    ],
    "sg:phone":"+1 559 896 2237",
    "sg:postcode":"93662",
    "sg:province":"CA",
    "sg:tags":[
        "ornamental",
        "nursery"
    ],
    "wof:name":"Selma Nursery",
    "wof:placetype":"venue"
},
  "geometry": {"coordinates":[-119.61068299999999,36.565126],"type":"Point"}
}