{
  "type": "Feature",
  "properties": {
    "addr:full":"15411 Manzanita St Hesperia CA 92345",
    "addr:housenumber":"15411",
    "addr:postcode":"92345",
    "addr:street":"Manzanita St",
    "iso:country":"US",
    "sg:address":"15411 Manzanita St",
    "sg:city":"Hesperia",
    "sg:classifiers":[
        {
            "category":"Building & Trades",
            "subcategory":"Construction",
            "type":"Services"
        }
    ],
    "sg:phone":"+1 760 244 4919",
    "sg:postcode":"92345",
    "sg:province":"CA",
    "sg:tags":[
        "plastering",
        "contractor"
    ],
    "wof:name":"Captain Artisan Plastering",
    "wof:placetype":"venue"
},
  "geometry": {"coordinates":[-117.325648,34.465175],"type":"Point"}
}