{
  "type": "Feature",
  "properties": {
    "iso:country":"US",
    "sg:address":"911 Academy Ave",
    "sg:city":"Sanger",
    "sg:classifiers":[
        {
            "category":"Home & Garden",
            "subcategory":"Hardware",
            "type":"Retail Goods"
        }
    ],
    "sg:phone":"+1 559 875 7989",
    "sg:postcode":"93657",
    "sg:province":"CA",
    "wof:name":"Ace Hardware",
    "wof:placetype":"venue"
},
  "geometry": {"coordinates":[-119.555253,36.702734],"type":"Point"}
}