{
  "type": "Feature",
  "properties": {
    "addr:full":"10150 Venice Blvd Culver City CA 90232",
    "addr:housenumber":"10150",
    "addr:postcode":"90232",
    "addr:street":"Venice Blvd",
    "iso:country":"US",
    "sg:address":"10150 Venice Blvd",
    "sg:city":"Culver City",
    "sg:classifiers":[
        {
            "category":"Restaurant",
            "type":"Food & Drink"
        }
    ],
    "sg:phone":"+1 310 837 8202",
    "sg:postcode":"90232",
    "sg:province":"CA",
    "sg:tags":[
        "shop",
        "coffee"
    ],
    "wof:name":"Coffee To Go",
    "wof:placetype":"venue"
},
  "geometry": {"coordinates":[-118.40103000000001,34.021882],"type":"Point"}
}