{
  "type": "Feature",
  "properties": {
    "addr:full":"3144 S Canfield Ave Los Angeles CA 90034",
    "addr:housenumber":"3144",
    "addr:postcode":"90034",
    "addr:street":"S Canfield Ave",
    "iso:country":"US",
    "sg:address":"3144 S Canfield Ave",
    "sg:city":"Los Angeles",
    "sg:classifiers":[
        {
            "category":"Education",
            "subcategory":"School",
            "type":"Public Place"
        }
    ],
    "sg:phone":"+1 323 224 1263",
    "sg:postcode":"90034",
    "sg:province":"CA",
    "wof:name":"Amer Academy of Complementary",
    "wof:placetype":"venue"
},
  "geometry": {"coordinates":[-118.39443,34.031699],"type":"Point"}
}