{
  "type": "Feature",
  "properties": {
    "addr:full":"2601 Adeline St Oakland CA 94607",
    "addr:housenumber":"2601",
    "addr:postcode":"94607",
    "addr:street":"Adeline St",
    "iso:country":"US",
    "sg:address":"2601 Adeline St",
    "sg:city":"Oakland",
    "sg:classifiers":[
        {
            "category":"Real Estate",
            "subcategory":"Architect",
            "type":"Services"
        }
    ],
    "sg:phone":"+1 510 763 3501",
    "sg:postcode":"94607",
    "sg:province":"CA",
    "sg:website":"www.swanarch.com",
    "wof:name":"SSA Architecture & Planning",
    "wof:placetype":"venue"
},
  "geometry": {"coordinates":[-122.282353,37.820283],"type":"Point"}
}