{
  "type": "Feature",
  "properties": {
    "addr:full":"1433 N Acacia Ave Reedley CA 93654",
    "addr:housenumber":"1433",
    "addr:postcode":"93654",
    "addr:street":"N Acacia Ave",
    "iso:country":"US",
    "sg:address":"1433 N Acacia Ave",
    "sg:city":"Reedley",
    "sg:classifiers":[
        {
            "category":"Health Services",
            "subcategory":"Health Practitioner",
            "type":"Services"
        }
    ],
    "sg:phone":"+1 559 637 7548",
    "sg:postcode":"93654",
    "sg:province":"CA",
    "sg:tags":[
        "therapist",
        "physical"
    ],
    "wof:name":"Sierra-Kings Physical Therapy",
    "wof:placetype":"venue"
},
  "geometry": {"coordinates":[-119.45102199999999,36.608408],"type":"Point"}
}