{
  "type": "Feature",
  "properties": {
    "iso:country":"US",
    "sg:address":"1376 N Main St",
    "sg:city":"Walnut Creek",
    "sg:classifiers":[
        {
            "category":"Manufacturing",
            "subcategory":"Printing",
            "type":"Manufacturing & Wholesale Goods"
        }
    ],
    "sg:phone":"+1 925 295 0205",
    "sg:postcode":"94596",
    "sg:province":"CA",
    "sg:tags":[
        "commercial"
    ],
    "wof:name":"Schurman Fine Papers",
    "wof:placetype":"venue"
},
  "geometry": {"coordinates":[-122.06047,37.898608],"type":"Point"}
}