{
  "type": "Feature",
  "properties": {
    "addr:full":"1059 Vallecito Rd Carpinteria CA 93013",
    "addr:housenumber":"1059",
    "addr:postcode":"93013",
    "addr:street":"Vallecito Rd",
    "iso:country":"US",
    "sg:address":"1059 Vallecito Rd",
    "sg:city":"Carpinteria",
    "sg:classifiers":[
        {
            "category":"Organizations",
            "subcategory":"Community Association",
            "type":"Services"
        }
    ],
    "sg:phone":"+1 805 566 8953",
    "sg:postcode":"93013",
    "sg:province":"CA",
    "wof:name":"Carpinteria Woman's Club",
    "wof:placetype":"venue"
},
  "geometry": {"coordinates":[-119.51527299999999,34.397621],"type":"Point"}
}