{
  "type": "Feature",
  "properties": {
    "iso:country":"US",
    "sg:address":"29737 Niguel Rd",
    "sg:city":"Laguna Niguel",
    "sg:classifiers":[
        {
            "category":"Health Services",
            "subcategory":"Doctor",
            "type":"Services"
        }
    ],
    "sg:phone":"+1 949 249 3058",
    "sg:postcode":"92677",
    "sg:province":"CA",
    "sg:tags":[
        "physician",
        "surgeon"
    ],
    "wof:name":"Allison Purtell MD",
    "wof:placetype":"venue"
},
  "geometry": {"coordinates":[-117.716017,33.529543],"type":"Point"}
}