{
  "type": "Feature",
  "properties": {
    "addr:full":"60 Western Dr Novato CA 94947",
    "addr:housenumber":"60",
    "addr:postcode":"94947",
    "addr:street":"Western Dr",
    "iso:country":"US",
    "sg:address":"60 Western Dr",
    "sg:city":"Novato",
    "sg:classifiers":[
        {
            "category":"Insurance",
            "subcategory":"Insurance Agent",
            "type":"Services"
        }
    ],
    "sg:phone":"+1 415 209 9470",
    "sg:postcode":"94947",
    "sg:province":"CA",
    "wof:name":"Michael F Bosco Insurance",
    "wof:placetype":"venue"
},
  "geometry": {"coordinates":[-122.59902099999999,38.110597],"type":"Point"}
}