{
  "type": "Feature",
  "properties": {
    "addr:full":"55 Mitchell Blvd San Rafael CA 94903",
    "addr:housenumber":"55",
    "addr:postcode":"94903",
    "addr:street":"Mitchell Blvd",
    "iso:country":"US",
    "sg:address":"55 Mitchell Blvd",
    "sg:city":"San Rafael",
    "sg:classifiers":[
        {
            "category":"Insurance",
            "subcategory":"Insurance Agent",
            "type":"Services"
        }
    ],
    "sg:phone":"+1 415 499 8955",
    "sg:postcode":"94903",
    "sg:province":"CA",
    "sg:website":"www.calhealthinsurance.com",
    "wof:name":"Nick Dollwet & Assoc",
    "wof:placetype":"venue"
},
  "geometry": {"coordinates":[-122.539309,38.017223],"type":"Point"}
}