{
  "type": "Feature",
  "properties": {
    "addr:full":"14281 Jeffrey Rd Irvine CA 92620",
    "addr:housenumber":"14281",
    "addr:postcode":"92620",
    "addr:street":"Jeffrey Rd",
    "iso:country":"US",
    "sg:address":"14281 Jeffrey Rd",
    "sg:city":"Irvine",
    "sg:classifiers":[
        {
            "category":"Personal",
            "subcategory":"Beauty Salon",
            "type":"Services"
        }
    ],
    "sg:phone":"+1 949 681 0366",
    "sg:postcode":"92620",
    "sg:province":"CA",
    "wof:name":"B & F Management",
    "wof:placetype":"venue"
},
  "geometry": {"coordinates":[-117.767582,33.690873],"type":"Point"}
}