{
  "type": "Feature",
  "properties": {
    "addr:full":"840 Washington St San Francisco CA 94108",
    "addr:housenumber":"840",
    "addr:postcode":"94108",
    "addr:street":"Washington St",
    "iso:country":"US",
    "sg:address":"840 Washington St",
    "sg:city":"San Francisco",
    "sg:classifiers":[
        {
            "category":"Organizations",
            "subcategory":"Professional Association",
            "type":"Services"
        }
    ],
    "sg:phone":"+1 415 982 0415",
    "sg:postcode":"94108",
    "sg:province":"CA",
    "wof:name":"Gee How Oak Tin Benevolent",
    "wof:placetype":"venue"
},
  "geometry": {"coordinates":[-122.407133,37.795141],"type":"Point"}
}