{
  "type": "Feature",
  "properties": {
    "iso:country":"US",
    "sg:address":"3817 Palmwood Ct",
    "sg:city":"Concord",
    "sg:classifiers":[
        {
            "category":"Farming",
            "subcategory":"Farm",
            "type":"Manufacturing & Wholesale Goods"
        }
    ],
    "sg:phone":"+1 925 285 7047",
    "sg:postcode":"94521",
    "sg:province":"CA",
    "wof:name":"Waredaca Farm",
    "wof:placetype":"venue"
},
  "geometry": {"coordinates":[-122.007553,37.962623],"type":"Point"}
}