{
  "type": "Feature",
  "properties": {
    "iso:country":"US",
    "sg:address":"6850 Vineland Ave Ste C",
    "sg:city":"North Hollywood",
    "sg:classifiers":[
        {
            "category":"Shopping",
            "subcategory":"Florist",
            "type":"Retail Goods"
        }
    ],
    "sg:phone":"+1 818 980 4371",
    "sg:postcode":"91605",
    "sg:province":"CA",
    "wof:name":"Sandy Rose Custom Floral Design",
    "wof:placetype":"venue"
},
  "geometry": {"coordinates":[-118.370003,34.194901],"type":"Point"}
}