{
  "type": "Feature",
  "properties": {
    "iso:country":"US",
    "sg:address":"721 N Wilson Ave",
    "sg:city":"Pasadena",
    "sg:classifiers":[
        {
            "category":"Communications",
            "type":"Services"
        }
    ],
    "sg:phone":"+1 626 797 5712",
    "sg:postcode":"91104",
    "sg:province":"CA",
    "sg:tags":[
        "web",
        "design"
    ],
    "sg:website":"www.usualmonkeys.com",
    "wof:name":"Usual Monkeys The",
    "wof:placetype":"venue"
},
  "geometry": {"coordinates":[-118.12834700000001,34.158146],"type":"Point"}
}