{
  "type": "Feature",
  "properties": {
    "addr:full":"17474 Foothill Blvd Fontana CA 92335",
    "addr:housenumber":"17474",
    "addr:postcode":"92335",
    "addr:street":"Foothill Blvd",
    "iso:country":"US",
    "sg:address":"17474 Foothill Blvd",
    "sg:city":"Fontana",
    "sg:classifiers":[
        {
            "category":"Retail",
            "subcategory":"Auto Repair",
            "type":"Services"
        }
    ],
    "sg:phone":"+1 909 823 1684",
    "sg:postcode":"92335",
    "sg:province":"CA",
    "sg:tags":[
        "repairing",
        "automobile"
    ],
    "wof:name":"United Motors",
    "wof:placetype":"venue"
},
  "geometry": {"coordinates":[-117.426528,34.106732],"type":"Point"}
}