{
  "type": "Feature",
  "properties": {
    "addr:full":"9909 Carmel Mountain Rd San Diego CA 92129",
    "addr:housenumber":"9909",
    "addr:postcode":"92129",
    "addr:street":"Carmel Mountain Rd",
    "iso:country":"US",
    "sg:address":"9909 Carmel Mountain Rd",
    "sg:city":"San Diego",
    "sg:classifiers":[
        {
            "category":"Food & Beverages",
            "subcategory":"Groceries & Convenience Stores",
            "type":"Retail Goods"
        }
    ],
    "sg:phone":"+1 858 484 1281",
    "sg:postcode":"92129",
    "sg:province":"CA",
    "wof:name":"Stater Bros Markets",
    "wof:placetype":"venue"
},
  "geometry": {"coordinates":[-117.115105,32.959776],"type":"Point"}
}