{
  "type": "Feature",
  "properties": {
    "addr:full":"18012 Cowan Irvine CA 92614",
    "addr:housenumber":"18012",
    "addr:postcode":"92614",
    "addr:street":"Cowan",
    "iso:country":"US",
    "sg:address":"18012 Cowan",
    "sg:city":"Irvine",
    "sg:classifiers":[
        {
            "category":"Professional",
            "subcategory":"Business Services",
            "type":"Services"
        }
    ],
    "sg:phone":"+1 949 794 1138",
    "sg:postcode":"92614",
    "sg:province":"CA",
    "sg:tags":[
        "notary"
    ],
    "wof:name":"Notarypro",
    "wof:placetype":"venue"
},
  "geometry": {"coordinates":[-117.865703,33.690183],"type":"Point"}
}