{
  "type": "Feature",
  "properties": {
    "addr:full":"26882 La Paz Rd Aliso Viejo CA 92656",
    "addr:housenumber":"26882",
    "addr:postcode":"92656",
    "addr:street":"La Paz Rd",
    "iso:country":"US",
    "sg:address":"26882 La Paz Rd",
    "sg:city":"Aliso Viejo",
    "sg:classifiers":[
        {
            "category":"Shopping",
            "subcategory":"Clothing, Apparel, & Fashions",
            "type":"Retail Goods"
        },
        {
            "category":"Shopping",
            "subcategory":"Bridal",
            "type":"Retail Goods"
        }
    ],
    "sg:phone":"+1 949 831 9730",
    "sg:postcode":"92656",
    "sg:province":"CA",
    "sg:tags":[
        "men's",
        "clothing"
    ],
    "wof:name":"MW Tux",
    "wof:placetype":"venue"
},
  "geometry": {"coordinates":[-117.707087,33.572417],"type":"Point"}
}