{
  "type": "Feature",
  "properties": {
    "iso:country":"US",
    "sg:address":"407 W Chevy Chase Dr",
    "sg:city":"Glendale",
    "sg:classifiers":[
        {
            "category":"Professional",
            "subcategory":"Art Services",
            "type":"Services"
        }
    ],
    "sg:phone":"+1 818 546 2121",
    "sg:postcode":"91204",
    "sg:province":"CA",
    "sg:tags":[
        "photographer"
    ],
    "sg:website":"www.sarosstudio.com",
    "wof:name":"Saro's Studio",
    "wof:placetype":"venue"
},
  "geometry": {"coordinates":[-118.26117499999999,34.133811],"type":"Point"}
}