{
  "type": "Feature",
  "properties": {
    "iso:country":"US",
    "sg:address":"49625 US Hwy 86",
    "sg:city":"Coachella",
    "sg:classifiers":[
        {
            "category":"Restaurant",
            "type":"Food & Drink"
        }
    ],
    "sg:phone":"+1 760 398 4244",
    "sg:postcode":"92236",
    "sg:province":"CA",
    "wof:name":"Camaron Pelao",
    "wof:placetype":"venue"
},
  "geometry": {"coordinates":[-116.18171700000001,33.687254],"type":"Point"}
}