{
  "type": "Feature",
  "properties": {
    "addr:full":"41 Sutter St San Francisco CA 94103",
    "addr:housenumber":"41",
    "addr:postcode":"94103",
    "addr:street":"Sutter St",
    "iso:country":"US",
    "sg:address":"41 Sutter St",
    "sg:city":"San Francisco",
    "sg:classifiers":[
        {
            "category":"Health Services",
            "subcategory":"Clinic",
            "type":"Services"
        }
    ],
    "sg:phone":"+1 415 399 8853",
    "sg:postcode":"94103",
    "sg:province":"CA",
    "sg:tags":[
        "medical"
    ],
    "wof:name":"d leland castleberry",
    "wof:placetype":"venue"
},
  "geometry": {"coordinates":[-122.401222,37.790218],"type":"Point"}
}