{
  "type": "Feature",
  "properties": {
    "iso:country":"US",
    "sg:address":"3474 Canyon Ridge Dr",
    "sg:city":"Altadena",
    "sg:classifiers":[
        {
            "category":"Farming",
            "subcategory":"Farm",
            "type":"Manufacturing & Wholesale Goods"
        }
    ],
    "sg:phone":"+1 626 296 2961",
    "sg:postcode":"91001",
    "sg:province":"CA",
    "wof:name":"The Rocking Horse Ranch",
    "wof:placetype":"venue"
},
  "geometry": {"coordinates":[-118.161562,34.203841],"type":"Point"}
}