{
  "type": "Feature",
  "properties": {
    "iso:country":"US",
    "sg:address":"7016 Atlantic Ave",
    "sg:city":"Bell",
    "sg:classifiers":[
        {
            "category":"Restaurant",
            "type":"Food & Drink"
        }
    ],
    "sg:menulink":"http://www.allmenus.com/ca/southeast/197986-kfc---kentucky-fried-chicken/menu/",
    "sg:phone":"+1 323 560 9411",
    "sg:postcode":"90201",
    "sg:province":"CA",
    "sg:tags":[
        "american",
        "chicken"
    ],
    "wof:name":"KFC - Kentucky Fried Chicken",
    "wof:placetype":"venue"
},
  "geometry": {"coordinates":[-118.187912,33.971403],"type":"Point"}
}