{
  "type": "Feature",
  "properties": {
    "addr:full":"1861 Landings Dr Mountain View CA 94043",
    "addr:housenumber":"1861",
    "addr:postcode":"94043",
    "addr:street":"Landings Dr",
    "iso:country":"US",
    "sg:address":"1861 Landings Dr",
    "sg:city":"Mountain View",
    "sg:classifiers":[
        {
            "category":"Wholesale",
            "subcategory":"Durable Goods & Equipment",
            "type":"Manufacturing & Wholesale Goods"
        }
    ],
    "sg:phone":"+1 650 962 5300",
    "sg:postcode":"94043",
    "sg:province":"CA",
    "sg:tags":[
        "representative",
        "manufacturer"
    ],
    "wof:name":"James Heaton Co",
    "wof:placetype":"venue"
},
  "geometry": {"coordinates":[-122.08873699999999,37.421143],"type":"Point"}
}