{
  "type": "Feature",
  "properties": {
    "addr:full":"469 Chelsea Way Fairfield CA 94533",
    "addr:housenumber":"469",
    "addr:postcode":"94533",
    "addr:street":"Chelsea Way",
    "iso:country":"US",
    "sg:address":"469 Chelsea Way",
    "sg:city":"Fairfield",
    "sg:classifiers":[
        {
            "category":"Building & Trades",
            "subcategory":"Construction",
            "type":"Services"
        }
    ],
    "sg:phone":"+1 707 432 1466",
    "sg:postcode":"94533",
    "sg:province":"CA",
    "sg:tags":[
        "fence",
        "contractor"
    ],
    "wof:name":"Lou's Maintenance",
    "wof:placetype":"venue"
},
  "geometry": {"coordinates":[-122.030198,38.278151],"type":"Point"}
}