{
  "type": "Feature",
  "properties": {
    "addr:full":"7049 Mills Ln Vacaville CA 95688",
    "addr:housenumber":"7049",
    "addr:postcode":"95688",
    "addr:street":"Mills Ln",
    "iso:country":"US",
    "sg:address":"7049 Mills Ln",
    "sg:city":"Vacaville",
    "sg:classifiers":[
        {
            "category":"Building & Trades",
            "subcategory":"Cleaning & Sanitation",
            "type":"Services"
        }
    ],
    "sg:phone":"+1 707 455 8996",
    "sg:postcode":"95688",
    "sg:province":"CA",
    "sg:tags":[
        "house"
    ],
    "wof:name":"Mom's Housekeeping",
    "wof:placetype":"venue"
},
  "geometry": {"coordinates":[-121.928016,38.395333],"type":"Point"}
}