{
  "type": "Feature",
  "properties": {
    "iso:country":"US",
    "sg:address":"2110 K St",
    "sg:city":"Sacramento",
    "sg:classifiers":[
        {
            "category":"Personal",
            "subcategory":"Massage",
            "type":"Services"
        }
    ],
    "sg:phone":"+1 916 448 1322",
    "sg:postcode":"95816",
    "sg:province":"CA",
    "wof:name":"Sherburn Adena Cmt",
    "wof:placetype":"venue"
},
  "geometry": {"coordinates":[-121.478897,38.575102],"type":"Point"}
}