{
  "type": "Feature",
  "properties": {
    "addr:full":"203 Main St Los Altos CA 94022",
    "addr:housenumber":"203",
    "addr:postcode":"94022",
    "addr:street":"Main St",
    "iso:country":"US",
    "sg:address":"203 Main St",
    "sg:city":"Los Altos",
    "sg:classifiers":[
        {
            "category":"Shopping",
            "subcategory":"Clothing, Apparel, & Fashions",
            "type":"Retail Goods"
        }
    ],
    "sg:phone":"+1 650 941 1414",
    "sg:postcode":"94022",
    "sg:province":"CA",
    "wof:name":"Oz Boutique",
    "wof:placetype":"venue"
},
  "geometry": {"coordinates":[-122.116615,37.378286],"type":"Point"}
}