{
  "type": "Feature",
  "properties": {
    "addr:full":"24988 Blue Ravine Rd Folsom CA 95630",
    "addr:housenumber":"24988",
    "addr:postcode":"95630",
    "addr:street":"Blue Ravine Rd",
    "iso:country":"US",
    "sg:address":"24988 Blue Ravine Rd",
    "sg:city":"Folsom",
    "sg:classifiers":[
        {
            "category":"Professional",
            "subcategory":"Employment Agencies",
            "type":"Services"
        }
    ],
    "sg:phone":"+1 916 353 1548",
    "sg:postcode":"95630",
    "sg:province":"CA",
    "sg:tags":[
        "opportunity"
    ],
    "sg:website":"www.medrecruitusa.com",
    "wof:name":"Peter C Tumminelli & Assoc",
    "wof:placetype":"venue"
},
  "geometry": {"coordinates":[-121.124087,38.688314],"type":"Point"}
}