{
  "type": "Feature",
  "properties": {
    "addr:full":"3055 Wilshire Blvd Los Angeles CA 90010",
    "addr:housenumber":"3055",
    "addr:postcode":"90010",
    "addr:street":"Wilshire Blvd",
    "iso:country":"US",
    "sg:address":"3055 Wilshire Blvd",
    "sg:city":"Los Angeles",
    "sg:classifiers":[
        {
            "category":"Real Estate",
            "subcategory":"Real Estate Agent",
            "type":"Services"
        }
    ],
    "sg:phone":"+1 213 632 4006",
    "sg:postcode":"90010",
    "sg:province":"CA",
    "wof:name":"Promax Commercial & Property",
    "wof:placetype":"venue"
},
  "geometry": {"coordinates":[-118.28746700000001,34.061892],"type":"Point"}
}