{
  "type": "Feature",
  "properties": {
    "iso:country":"US",
    "sg:address":"13660 Hilleary Pl",
    "sg:city":"Poway",
    "sg:classifiers":[
        {
            "category":"Building & Trades",
            "subcategory":"Landscaping Services",
            "type":"Services"
        }
    ],
    "sg:phone":"+1 858 679 9084",
    "sg:postcode":"92064",
    "sg:province":"CA",
    "wof:name":"David L Cencak Lawn Care",
    "wof:placetype":"venue"
},
  "geometry": {"coordinates":[-117.037632,32.960119],"type":"Point"}
}