{
  "type": "Feature",
  "properties": {
    "iso:country":"US",
    "sg:address":"2850 E 29th St",
    "sg:city":"Long Beach",
    "sg:classifiers":[
        {
            "category":"Wholesale",
            "subcategory":"Machinery & Supplies",
            "type":"Manufacturing & Wholesale Goods"
        }
    ],
    "sg:phone":"+1 562 595 7621",
    "sg:postcode":"90806",
    "sg:province":"CA",
    "sg:tags":[
        "equipment",
        "industrial"
    ],
    "wof:name":"Panavise Prod Inc",
    "wof:placetype":"venue"
},
  "geometry": {"coordinates":[-118.152063,33.806515],"type":"Point"}
}