{
  "type": "Feature",
  "properties": {
    "iso:country":"US",
    "sg:address":"500 North State College Blvd.",
    "sg:city":"Orange",
    "sg:classifiers":[
        {
            "category":"Professional",
            "subcategory":"Lawyer & Legal Services",
            "type":"Services"
        }
    ],
    "sg:phone":"+1 714 919 4388",
    "sg:postcode":"92868",
    "sg:province":"CA",
    "sg:tags":[
        "divorce",
        "law",
        "family"
    ],
    "sg:website":"www.ocdissolution.com",
    "wof:name":"Razai Law Firm",
    "wof:placetype":"venue"
},
  "geometry": {"coordinates":[-117.889833,33.795664],"type":"Point"}
}