{
  "type": "Feature",
  "properties": {
    "iso:country":"US",
    "sg:address":"2998 Deadwood Dr",
    "sg:city":"Corona",
    "sg:classifiers":[
        {
            "category":"Freight",
            "type":"Transportation"
        }
    ],
    "sg:phone":"+1 951 735 5990",
    "sg:postcode":"92882",
    "sg:province":"CA",
    "sg:tags":[
        "operator",
        "local",
        "trucking"
    ],
    "wof:name":"C & Y Trucking Inc",
    "wof:placetype":"venue"
},
  "geometry": {"coordinates":[-117.58317,33.847142],"type":"Point"}
}