{
  "type": "Feature",
  "properties": {
    "addr:full":"30382 Via Con Dios Rancho Santa Margarita CA 92688",
    "addr:housenumber":"30382",
    "addr:postcode":"92688",
    "addr:street":"Via Con Dios",
    "iso:country":"US",
    "sg:address":"30382 Via Con Dios",
    "sg:city":"Rancho Santa Margarita",
    "sg:classifiers":[
        {
            "category":"Education",
            "subcategory":"School",
            "type":"Public Place"
        }
    ],
    "sg:phone":"+1 949 858 5144",
    "sg:postcode":"92688",
    "sg:province":"CA",
    "sg:tags":[
        "episcopal",
        "church"
    ],
    "wof:name":"St Johns Episcpal Church Schl",
    "wof:placetype":"venue"
},
  "geometry": {"coordinates":[-117.600362,33.644819],"type":"Point"}
}