{
  "type": "Feature",
  "properties": {
    "addr:full":"13891 Berrington Ct Santa Ana CA 92705",
    "addr:postcode":"13891;92705",
    "addr:street":"Berrington Ct",
    "iso:country":"US",
    "sg:address":"13891 Berrington Ct",
    "sg:city":"Santa Ana",
    "sg:classifiers":[
        {
            "category":"Manufacturing",
            "subcategory":"Signs",
            "type":"Manufacturing & Wholesale Goods"
        }
    ],
    "sg:phone":"+1 714 832 5511",
    "sg:postcode":"92705",
    "sg:province":"CA",
    "sg:tags":[
        "specialty",
        "mfg"
    ],
    "wof:name":"Rohrbaugh Design",
    "wof:placetype":"venue"
},
  "geometry": {"coordinates":[-117.80445,33.760561],"type":"Point"}
}