{
  "type": "Feature",
  "properties": {
    "addr:full":"441 Espinosa Rd Salinas CA 93907",
    "addr:housenumber":"441",
    "addr:postcode":"93907",
    "addr:street":"Espinosa Rd",
    "iso:country":"US",
    "sg:address":"441 Espinosa Rd",
    "sg:city":"Salinas",
    "sg:classifiers":[
        {
            "category":"Freight",
            "type":"Transportation"
        }
    ],
    "sg:phone":"+1 831 443 1685",
    "sg:postcode":"93907",
    "sg:province":"CA",
    "sg:tags":[
        "warehouse",
        "self",
        "storage"
    ],
    "wof:name":"U-Store Mini-Storage",
    "wof:placetype":"venue"
},
  "geometry": {"coordinates":[-121.665235,36.737179],"type":"Point"}
}