{
  "type": "Feature",
  "properties": {
    "iso:country":"US",
    "sg:address":"2001 Rene Ave",
    "sg:city":"Sacramento",
    "sg:classifiers":[
        {
            "category":"Manufacturing",
            "subcategory":"Metals",
            "type":"Manufacturing & Wholesale Goods"
        }
    ],
    "sg:phone":"+1 916 929 3479",
    "sg:postcode":"95838",
    "sg:province":"CA",
    "sg:tags":[
        "work",
        "iron"
    ],
    "wof:name":"Cal Iron Art",
    "wof:placetype":"venue"
},
  "geometry": {"coordinates":[-121.41989100000001,38.643631],"type":"Point"}
}