{
  "type": "Feature",
  "properties": {
    "addr:full":"1130 Columbia St San Diego CA 92101",
    "addr:housenumber":"1130",
    "addr:postcode":"92101",
    "addr:street":"Columbia St",
    "iso:country":"US",
    "sg:address":"1130 Columbia St",
    "sg:city":"San Diego",
    "sg:classifiers":[
        {
            "category":"Personal",
            "subcategory":"Barber",
            "type":"Services"
        }
    ],
    "sg:phone":"+1 619 807 3518",
    "sg:postcode":"92101",
    "sg:province":"CA",
    "wof:name":"Michaele Taylor Haircuts for Men",
    "wof:placetype":"venue"
},
  "geometry": {"coordinates":[-117.167406,32.717084],"type":"Point"}
}