{
  "type": "Feature",
  "properties": {
    "iso:country":"US",
    "sg:address":"1290 Hollister St",
    "sg:city":"San Diego",
    "sg:classifiers":[
        {
            "category":"Food & Beverages",
            "subcategory":"Fruits & Vegetables",
            "type":"Retail Goods"
        }
    ],
    "sg:phone":"+1 619 575 6945",
    "sg:postcode":"92154",
    "sg:province":"CA",
    "sg:tags":[
        "juice"
    ],
    "wof:name":"Fruit Palace",
    "wof:placetype":"venue"
},
  "geometry": {"coordinates":[-117.084162,32.57414],"type":"Point"}
}