{
  "type": "Feature",
  "properties": {
    "iso:country":"US",
    "sg:address":"4200 Turcon Ave",
    "sg:city":"Bakersfield",
    "sg:classifiers":[
        {
            "category":"Wholesale",
            "subcategory":"Machinery & Supplies",
            "type":"Manufacturing & Wholesale Goods"
        }
    ],
    "sg:phone":"+1 661 322 9906",
    "sg:postcode":"93308",
    "sg:province":"CA",
    "sg:tags":[
        "equipment",
        "oil",
        "well"
    ],
    "wof:name":"Packer Service Inc",
    "wof:placetype":"venue"
},
  "geometry": {"coordinates":[-119.050933,35.391739],"type":"Point"}
}