{
  "type": "Feature",
  "properties": {
    "addr:full":"2815 E Coronado St Anaheim CA 92806",
    "addr:housenumber":"2815",
    "addr:postcode":"92806",
    "addr:street":"E Coronado St",
    "iso:country":"US",
    "sg:address":"2815 E Coronado St",
    "sg:city":"Anaheim",
    "sg:classifiers":[
        {
            "category":"Building & Trades",
            "subcategory":"Construction",
            "type":"Services"
        }
    ],
    "sg:phone":"+1 714 630 7857",
    "sg:postcode":"92806",
    "sg:province":"CA",
    "sg:tags":[
        "contractor"
    ],
    "wof:name":"Honeycutt Tear Off",
    "wof:placetype":"venue"
},
  "geometry": {"coordinates":[-117.86858100000001,33.852113],"type":"Point"}
}