{
  "type": "Feature",
  "properties": {
    "iso:country":"US",
    "sg:address":"220 E Clark Ave Ste A",
    "sg:city":"Santa Maria",
    "sg:classifiers":[
        {
            "category":"Building & Trades",
            "subcategory":"Plumbing",
            "type":"Services"
        }
    ],
    "sg:phone":"+1 805 934 1949",
    "sg:postcode":"93455",
    "sg:province":"CA",
    "wof:name":"Zierman Ray Plumbing Inc",
    "wof:placetype":"venue"
},
  "geometry": {"coordinates":[-120.43499799999999,34.865002],"type":"Point"}
}