{
  "type": "Feature",
  "properties": {
    "iso:country":"US",
    "sg:address":"1501 Coffee Rd",
    "sg:city":"Modesto",
    "sg:classifiers":[
        {
            "category":"Insurance",
            "subcategory":"Title Insurance",
            "type":"Services"
        }
    ],
    "sg:phone":"+1 209 521 1458",
    "sg:postcode":"95355",
    "sg:province":"CA",
    "wof:name":"Old Republic Title Company",
    "wof:placetype":"venue"
},
  "geometry": {"coordinates":[-120.975708,37.66534],"type":"Point"}
}