{
  "type": "Feature",
  "properties": {
    "addr:full":"5470 Lauren Dr San Jose CA 95124",
    "addr:housenumber":"5470",
    "addr:postcode":"95124",
    "addr:street":"Lauren Dr",
    "iso:country":"US",
    "sg:address":"5470 Lauren Dr",
    "sg:city":"San Jose",
    "sg:classifiers":[
        {
            "category":"Professional",
            "subcategory":"Business Services",
            "type":"Services"
        }
    ],
    "sg:phone":"+1 408 264 0188",
    "sg:postcode":"95124",
    "sg:province":"CA",
    "sg:tags":[
        "building",
        "inspection"
    ],
    "sg:website":"www.eagleinspectiongroup.com",
    "wof:name":"Eagle Inspection Group",
    "wof:placetype":"venue"
},
  "geometry": {"coordinates":[-121.90673200000001,37.237831],"type":"Point"}
}