{
  "type": "Feature",
  "properties": {
    "iso:country":"US",
    "sg:address":"548 S. Los Angeles Street",
    "sg:city":"Los Angeles",
    "sg:classifiers":[
        {
            "category":"Shopping",
            "subcategory":"Crafts & Fabrics",
            "type":"Retail Goods"
        }
    ],
    "sg:phone":"+1 213 624 9451",
    "sg:postcode":"90013",
    "sg:province":"CA",
    "sg:tags":[
        "store"
    ],
    "sg:website":"www.bblackandsons.com",
    "wof:name":"B. Black & Sons",
    "wof:placetype":"venue"
},
  "geometry": {"coordinates":[-118.24866,34.044906],"type":"Point"}
}