{
  "type": "Feature",
  "properties": {
    "addr:full":"180 Fair Oaks St San Francisco CA 94110",
    "addr:housenumber":"180",
    "addr:postcode":"94110",
    "addr:street":"Fair Oaks St",
    "iso:country":"US",
    "sg:address":"180 Fair Oaks St",
    "sg:city":"San Francisco",
    "sg:classifiers":[
        {
            "category":"Arts & Performance",
            "subcategory":"Arts Center",
            "type":"Entertainment"
        },
        {
            "category":"Education",
            "subcategory":"School",
            "type":"Public Place"
        }
    ],
    "sg:phone":"+1 415 824 2240",
    "sg:postcode":"94110",
    "sg:province":"CA",
    "sg:tags":[
        "performing"
    ],
    "sg:website":"addaclevenger.org/",
    "wof:name":"Adda Clevenger Junior Preparatory & Theater School for Children",
    "wof:placetype":"venue"
},
  "geometry": {"coordinates":[-122.424161,37.75368],"type":"Point"}
}