{
  "type": "Feature",
  "properties": {
    "iso:country":"US",
    "sg:address":"4764 Carrington Dr",
    "sg:city":"Oakley",
    "sg:classifiers":[
        {
            "category":"Shopping",
            "subcategory":"Gifts & Souvenirs",
            "type":"Retail Goods"
        }
    ],
    "sg:phone":"+1 925 679 9296",
    "sg:postcode":"94561",
    "sg:province":"CA",
    "wof:name":"Jump & Beyond",
    "wof:placetype":"venue"
},
  "geometry": {"coordinates":[-121.73585799999999,37.994689],"type":"Point"}
}