{
  "type": "Feature",
  "properties": {
    "iso:country":"US",
    "sg:address":"8416 Specialty Cir",
    "sg:city":"Sacramento",
    "sg:classifiers":[
        {
            "category":"Building & Trades",
            "subcategory":"Equipment Rental",
            "type":"Services"
        },
        {
            "category":"Wholesale",
            "subcategory":"Construction Materials",
            "type":"Manufacturing & Wholesale Goods"
        },
        {
            "category":"Home & Garden",
            "subcategory":"Building Materials",
            "type":"Retail Goods"
        },
        {
            "category":"Building & Trades",
            "subcategory":"Construction",
            "type":"Services"
        }
    ],
    "sg:phone":"+1 800 736 4255",
    "sg:postcode":"95828",
    "sg:province":"CA",
    "sg:tags":[
        "supply",
        "excavation",
        "breaking",
        "contractor",
        "concrete",
        "cutting",
        "sawing",
        "staining",
        "demolition"
    ],
    "sg:website":"http://penhall.com/",
    "wof:name":"Penhall Company",
    "wof:placetype":"venue"
},
  "geometry": {"coordinates":[-121.394104,38.502625],"type":"Point"}
}