{
  "type": "Feature",
  "properties": {
    "addr:full":"5826 Mission Gorge Rd San Diego CA 92120",
    "addr:housenumber":"5826",
    "addr:postcode":"92120",
    "addr:street":"Mission Gorge Rd",
    "iso:country":"US",
    "sg:address":"5826 Mission Gorge Rd",
    "sg:city":"San Diego",
    "sg:classifiers":[
        {
            "category":"Shopping",
            "subcategory":"Pharmacy",
            "type":"Retail Goods"
        }
    ],
    "sg:phone":"+1 619 584 6211",
    "sg:postcode":"92120",
    "sg:province":"CA",
    "sg:tags":[
        "drugstore"
    ],
    "wof:name":"Sav-On Drugs",
    "wof:placetype":"venue"
},
  "geometry": {"coordinates":[-117.100998,32.7817],"type":"Point"}
}