{
  "type": "Feature",
  "properties": {
    "iso:country":"US",
    "sg:address":"253 3rd Ave",
    "sg:city":"Chula Vista",
    "sg:classifiers":[
        {
            "category":"Home & Garden",
            "subcategory":"Carpets & Floor Coverings",
            "type":"Retail Goods"
        }
    ],
    "sg:phone":"+1 619 420 5399",
    "sg:postcode":"91910",
    "sg:province":"CA",
    "sg:tags":[
        "dealer",
        "rug"
    ],
    "wof:name":"Golden Mart",
    "wof:placetype":"venue"
},
  "geometry": {"coordinates":[-117.079955,32.641596],"type":"Point"}
}