{
  "type": "Feature",
  "properties": {
    "addr:full":"1800 California St Stockton CA 95204",
    "addr:housenumber":"1800",
    "addr:postcode":"95204",
    "addr:street":"California St",
    "iso:country":"US",
    "sg:address":"1800 California St",
    "sg:city":"Stockton",
    "sg:classifiers":[
        {
            "category":"Education",
            "subcategory":"Library",
            "type":"Public Place"
        }
    ],
    "sg:phone":"+1 209 467 6550",
    "sg:postcode":"95204",
    "sg:province":"CA",
    "wof:name":"Cancer Center Library",
    "wof:placetype":"venue"
},
  "geometry": {"coordinates":[-121.289046,37.97003],"type":"Point"}
}