{
  "type": "Feature",
  "properties": {
    "iso:country":"US",
    "sg:address":"1875 Charleston Rd",
    "sg:city":"Mountain View",
    "sg:classifiers":[
        {
            "category":"Shopping",
            "subcategory":"Computers & Home Electronics",
            "type":"Retail Goods"
        }
    ],
    "sg:phone":"+1 650 988 6900",
    "sg:postcode":"94043",
    "sg:province":"CA",
    "sg:tags":[
        "software"
    ],
    "wof:name":"Globetech Solutions",
    "wof:placetype":"venue"
},
  "geometry": {"coordinates":[-122.088169,37.421294],"type":"Point"}
}