{
  "type": "Feature",
  "properties": {
    "iso:country":"US",
    "sg:address":"5440 14th Ave",
    "sg:city":"Sacramento",
    "sg:classifiers":[
        {
            "category":"Utilities",
            "subcategory":"Mobile Phone",
            "type":"Services"
        }
    ],
    "sg:phone":"+1 916 453 0446",
    "sg:postcode":"95820",
    "sg:province":"CA",
    "sg:tags":[
        "telephone",
        "cellular"
    ],
    "wof:name":"O P Wireless",
    "wof:placetype":"venue"
},
  "geometry": {"coordinates":[-121.443311,38.539365],"type":"Point"}
}