{
  "type": "Feature",
  "properties": {
    "addr:full":"5080 Shoreham Pl San Diego CA 92122",
    "addr:housenumber":"5080",
    "addr:postcode":"92122",
    "addr:street":"Shoreham Pl",
    "iso:country":"US",
    "sg:address":"5080 Shoreham Pl",
    "sg:city":"San Diego",
    "sg:classifiers":[
        {
            "category":"Professional",
            "subcategory":"Management & Consulting",
            "type":"Services"
        }
    ],
    "sg:phone":"+1 858 552 1904",
    "sg:postcode":"92122",
    "sg:province":"CA",
    "sg:tags":[
        "fuel"
    ],
    "wof:name":"Pheonix Water Management",
    "wof:placetype":"venue"
},
  "geometry": {"coordinates":[-117.185568,32.853166],"type":"Point"}
}