{
  "type": "Feature",
  "properties": {
    "addr:full":"1226 Hagen Rd Napa CA 94558",
    "addr:housenumber":"1226",
    "addr:postcode":"94558",
    "addr:street":"Hagen Rd",
    "iso:country":"US",
    "sg:address":"1226 Hagen Rd",
    "sg:city":"Napa",
    "sg:classifiers":[
        {
            "category":"Freight",
            "type":"Transportation"
        }
    ],
    "sg:phone":"+1 707 226 2679",
    "sg:postcode":"94558",
    "sg:province":"CA",
    "sg:tags":[
        "intrastate",
        "trucking"
    ],
    "wof:name":"Bellani Trucking Co Inc",
    "wof:placetype":"venue"
},
  "geometry": {"coordinates":[-122.26208,38.323931],"type":"Point"}
}