{
  "type": "Feature",
  "properties": {
    "addr:full":"3788 Martha St San Diego CA 92117",
    "addr:housenumber":"3788",
    "addr:postcode":"92117",
    "addr:street":"Martha St",
    "iso:country":"US",
    "sg:address":"3788 Martha St",
    "sg:city":"San Diego",
    "sg:classifiers":[
        {
            "category":"Professional",
            "type":"Services"
        }
    ],
    "sg:phone":"+1 858 273 1356",
    "sg:postcode":"92117",
    "sg:province":"CA",
    "sg:tags":[
        "establishment"
    ],
    "wof:name":"Rude & Sons",
    "wof:placetype":"venue"
},
  "geometry": {"coordinates":[-117.20721500000001,32.834764],"type":"Point"}
}