{
  "type": "Feature",
  "properties": {
    "iso:country":"US",
    "sg:address":"12937 Jolette Ave",
    "sg:city":"Granada Hills",
    "sg:classifiers":[
        {
            "category":"Professional",
            "type":"Services"
        }
    ],
    "sg:phone":"+1 818 366 0017",
    "sg:postcode":"91344",
    "sg:province":"CA",
    "wof:name":"Yousef Machhour",
    "wof:placetype":"venue"
},
  "geometry": {"coordinates":[-118.515318,34.304311],"type":"Point"}
}