{
  "type": "Feature",
  "properties": {
    "iso:country":"US",
    "sg:address":"9861 W Chapman Ave",
    "sg:city":"Garden Grove",
    "sg:classifiers":[
        {
            "category":"Manufacturing",
            "subcategory":"Apparel",
            "type":"Manufacturing & Wholesale Goods"
        }
    ],
    "sg:phone":"+1 714 537 7898",
    "sg:postcode":"92841",
    "sg:province":"CA",
    "sg:tags":[
        "manufacturer"
    ],
    "wof:name":"Fashion Ave",
    "wof:placetype":"venue"
},
  "geometry": {"coordinates":[-117.962307,33.788634],"type":"Point"}
}