{
  "type": "Feature",
  "properties": {
    "addr:full":"10907 Venice Blvd Los Angeles CA 90034",
    "addr:housenumber":"10907",
    "addr:postcode":"90034",
    "addr:street":"Venice Blvd",
    "iso:country":"US",
    "sg:address":"10907 Venice Blvd",
    "sg:city":"Los Angeles",
    "sg:classifiers":[
        {
            "category":"Building & Trades",
            "subcategory":"Cleaning & Sanitation",
            "type":"Services"
        }
    ],
    "sg:phone":"+1 310 559 8191",
    "sg:postcode":"90034",
    "sg:province":"CA",
    "sg:tags":[
        "carpet"
    ],
    "wof:name":"Alco Carpet Service Inc",
    "wof:placetype":"venue"
},
  "geometry": {"coordinates":[-118.41224,34.016157],"type":"Point"}
}