{
  "type": "Feature",
  "properties": {
    "addr:full":"2513 Bambi Ln San Jose CA 95116",
    "addr:housenumber":"2513",
    "addr:postcode":"95116",
    "addr:street":"Bambi Ln",
    "iso:country":"US",
    "sg:address":"2513 Bambi Ln",
    "sg:city":"San Jose",
    "sg:classifiers":[
        {
            "category":"Retail",
            "subcategory":"Laundry & Dry Cleaning",
            "type":"Services"
        }
    ],
    "sg:phone":"+1 408 729 0177",
    "sg:postcode":"95116",
    "sg:province":"CA",
    "wof:name":"Cleaning General",
    "wof:placetype":"venue"
},
  "geometry": {"coordinates":[-121.83435799999999,37.352291],"type":"Point"}
}