{
  "type": "Feature",
  "properties": {
    "addr:full":"4229 Northgate Blvd Ste 3 Sacramento CA 95834",
    "addr:housenumber":"4229",
    "addr:postcode":"95834",
    "addr:street":"Northgate Blvd Ste 3",
    "iso:country":"US",
    "sg:address":"4229 Northgate Blvd Ste 3",
    "sg:city":"Sacramento",
    "sg:classifiers":[
        {
            "category":"Professional",
            "subcategory":"Computer Services",
            "type":"Services"
        },
        {
            "category":"Wholesale",
            "subcategory":"Computers",
            "type":"Manufacturing & Wholesale Goods"
        }
    ],
    "sg:phone":"+1 916 649 1676",
    "sg:postcode":"95834",
    "sg:province":"CA",
    "sg:tags":[
        "equipment",
        "cd-rom",
        "software"
    ],
    "wof:name":"Amity Software Inc.",
    "wof:placetype":"venue"
},
  "geometry": {"coordinates":[-121.475978,38.644816],"type":"Point"}
}