{
  "type": "Feature",
  "properties": {
    "addr:full":"131 Bridge St Arroyo Grande CA 93420",
    "addr:housenumber":"131",
    "addr:postcode":"93420",
    "addr:street":"Bridge St",
    "iso:country":"US",
    "sg:address":"131 Bridge St",
    "sg:city":"Arroyo Grande",
    "sg:classifiers":[
        {
            "category":"Professional",
            "subcategory":"Accounting & Tax Preparation",
            "type":"Services"
        }
    ],
    "sg:phone":"+1 805 474 7804",
    "sg:postcode":"93420",
    "sg:province":"CA",
    "sg:tags":[
        "payroll"
    ],
    "wof:name":"Automatic Data Processing",
    "wof:placetype":"venue"
},
  "geometry": {"coordinates":[-120.57866,35.122723],"type":"Point"}
}