{
  "type": "Feature",
  "properties": {
    "addr:full":"1070 Lavenida St Mountain View CA 94043",
    "addr:housenumber":"1070",
    "addr:postcode":"94043",
    "addr:street":"Lavenida St",
    "iso:country":"US",
    "sg:address":"1070 Lavenida St",
    "sg:city":"Mountain View",
    "sg:classifiers":[
        {
            "category":"Government",
            "subcategory":"Post Office",
            "type":"Public Place"
        }
    ],
    "sg:phone":"+1 650 000 1111",
    "sg:postcode":"94043",
    "sg:province":"CA",
    "wof:name":"US Post Office",
    "wof:placetype":"venue"
},
  "geometry": {"coordinates":[-122.07235,37.413209],"type":"Point"}
}