{
  "type": "Feature",
  "properties": {
    "addr:full":"644 Emerson Street, Suite 200 Palo Alto CA 94301",
    "addr:housenumber":"644",
    "addr:postcode":"94301",
    "addr:street":"Emerson Street Suite 200",
    "iso:country":"US",
    "sg:address":"644 Emerson Street, Suite 200",
    "sg:city":"Palo Alto",
    "sg:classifiers":[
        {
            "category":"Professional",
            "subcategory":"Computer Services",
            "type":"Services"
        }
    ],
    "sg:phone":"+1 650 596 1800",
    "sg:postcode":"94301",
    "sg:province":"CA",
    "sg:website":"http://www.intalio.com",
    "wof:name":"Intalio",
    "wof:placetype":"venue"
},
  "geometry": {"coordinates":[-122.160843,37.443399],"type":"Point"}
}