{
  "type": "Feature",
  "properties": {
    "addr:full":"1245 Wilshire Blvd Los Angeles CA 90017",
    "addr:housenumber":"1245",
    "addr:postcode":"90017",
    "addr:street":"Wilshire Blvd",
    "iso:country":"US",
    "sg:address":"1245 Wilshire Blvd",
    "sg:city":"Los Angeles",
    "sg:classifiers":[
        {
            "category":"Health Services",
            "subcategory":"Doctor",
            "type":"Services"
        }
    ],
    "sg:phone":"+1 213 977 1257",
    "sg:postcode":"90017",
    "sg:province":"CA",
    "sg:tags":[
        "physician",
        "surgeon"
    ],
    "wof:name":"Jong Huang MD",
    "wof:placetype":"venue"
},
  "geometry": {"coordinates":[-118.265946,34.053506],"type":"Point"}
}