{
  "type": "Feature",
  "properties": {
    "iso:country":"US",
    "sg:address":"507 E 4th St",
    "sg:city":"Alturas",
    "sg:classifiers":[
        {
            "category":"Organizations",
            "subcategory":"Religious Organization",
            "type":"Services"
        }
    ],
    "sg:phone":"+1 530 233 2119",
    "sg:postcode":"96101",
    "sg:province":"CA",
    "sg:tags":[
        "church"
    ],
    "wof:name":"Catholic Church Sacred Heart",
    "wof:placetype":"venue"
},
  "geometry": {"coordinates":[-120.537306,41.487309],"type":"Point"}
}