{
  "type": "Feature",
  "properties": {
    "addr:full":"20106 Jamestown Rd Sonora CA 95370",
    "addr:housenumber":"20106",
    "addr:postcode":"95370",
    "addr:street":"Jamestown Rd",
    "iso:country":"US",
    "sg:address":"20106 Jamestown Rd",
    "sg:city":"Sonora",
    "sg:classifiers":[
        {
            "category":"Real Estate",
            "subcategory":"Real Estate Operator",
            "type":"Services"
        }
    ],
    "sg:phone":"+1 209 533 3166",
    "sg:postcode":"95370",
    "sg:province":"CA",
    "sg:tags":[
        "mobile",
        "home",
        "community"
    ],
    "wof:name":"Star Mobile Estates",
    "wof:placetype":"venue"
},
  "geometry": {"coordinates":[-120.41283799999999,37.988109],"type":"Point"}
}