{
  "type": "Feature",
  "properties": {
    "addr:full":"6842 La Tijera Blvd Los Angeles CA 90045",
    "addr:housenumber":"6842",
    "addr:postcode":"90045",
    "addr:street":"La Tijera Blvd",
    "iso:country":"US",
    "sg:address":"6842 La Tijera Blvd",
    "sg:city":"Los Angeles",
    "sg:classifiers":[
        {
            "category":"Cinema",
            "subcategory":"Movie Rental",
            "type":"Entertainment"
        }
    ],
    "sg:phone":"+1 310 216 9595",
    "sg:postcode":"90045",
    "sg:province":"CA",
    "sg:tags":[
        "game",
        "video"
    ],
    "wof:name":"Jungle Video",
    "wof:placetype":"venue"
},
  "geometry": {"coordinates":[-118.37200199999999,33.976898],"type":"Point"}
}