{
  "type": "Feature",
  "properties": {
    "iso:country":"US",
    "sg:address":"3121 E Coast Hwy",
    "sg:city":"Corona Del Mar",
    "sg:classifiers":[
        {
            "category":"Shopping",
            "subcategory":"Photographic Equipment",
            "type":"Retail Goods"
        }
    ],
    "sg:phone":"+1 949 673 4670",
    "sg:postcode":"92625",
    "sg:province":"CA",
    "sg:tags":[
        "supply"
    ],
    "wof:name":"Cal's Camera",
    "wof:placetype":"venue"
},
  "geometry": {"coordinates":[-117.871763,33.598066],"type":"Point"}
}