{
  "type": "Feature",
  "properties": {
    "addr:full":"582 Market St Ste 306 San Francisco CA 94104",
    "addr:housenumber":"582",
    "addr:postcode":"94104",
    "addr:street":"Market St Ste 306",
    "iso:country":"US",
    "sg:address":"582 Market St Ste 306",
    "sg:city":"San Francisco",
    "sg:classifiers":[
        {
            "category":"Museum",
            "type":"Entertainment"
        }
    ],
    "sg:phone":"+1 415 433 4400",
    "sg:postcode":"94104",
    "sg:province":"CA",
    "wof:name":"Varnish Fine Art",
    "wof:placetype":"venue"
},
  "geometry": {"coordinates":[-122.401273,37.789359],"type":"Point"}
}