{
  "type": "Feature",
  "properties": {
    "iso:country":"US",
    "sg:address":"2712 Tirol Dr",
    "sg:city":"Frazier Park",
    "sg:classifiers":[
        {
            "category":"Autos & Motor Vehicles",
            "subcategory":"Auto Supplies",
            "type":"Retail Goods"
        }
    ],
    "sg:phone":"+1 661 242 3980",
    "sg:postcode":"93225",
    "sg:province":"CA",
    "sg:tags":[
        "automobile",
        "parts"
    ],
    "wof:name":"SSF Imported Auto Parts Inc",
    "wof:placetype":"venue"
},
  "geometry": {"coordinates":[-119.136558,34.852462],"type":"Point"}
}