{
  "type": "Feature",
  "properties": {
    "addr:full":"2938 S Meadows Pl Sacramento CA 95822",
    "addr:housenumber":"2938",
    "addr:postcode":"95822",
    "addr:street":"S Meadows Pl",
    "iso:country":"US",
    "sg:address":"2938 S Meadows Pl",
    "sg:city":"Sacramento",
    "sg:classifiers":[
        {
            "category":"Social Services",
            "subcategory":"Child Care",
            "type":"Services"
        }
    ],
    "sg:phone":"+1 916 394 9641",
    "sg:postcode":"95822",
    "sg:province":"CA",
    "wof:name":"Florin Meadows Headstart",
    "wof:placetype":"venue"
},
  "geometry": {"coordinates":[-121.470358,38.493158],"type":"Point"}
}