{
  "type": "Feature",
  "properties": {
    "iso:country":"US",
    "sg:address":"405 Main Street",
    "sg:city":"El Segundo",
    "sg:classifiers":[
        {
            "category":"Shopping",
            "subcategory":"Clothing, Apparel, & Fashions",
            "type":"Retail Goods"
        }
    ],
    "sg:phone":"+1 310 322 4744",
    "sg:postcode":"90245",
    "sg:province":"CA",
    "sg:tags":[
        "accessory",
        "clothing",
        "women's"
    ],
    "wof:name":"D'arte Connection",
    "wof:placetype":"venue"
},
  "geometry": {"coordinates":[-118.416096,33.921157],"type":"Point"}
}