{
  "type": "Feature",
  "properties": {
    "addr:full":"921 S Baldwin Ave Arcadia CA 91007",
    "addr:housenumber":"921",
    "addr:postcode":"91007",
    "addr:street":"S Baldwin Ave",
    "iso:country":"US",
    "sg:address":"921 S Baldwin Ave",
    "sg:city":"Arcadia",
    "sg:classifiers":[
        {
            "category":"Restaurant",
            "type":"Food & Drink"
        }
    ],
    "sg:phone":"+1 626 446 1430",
    "sg:postcode":"91007",
    "sg:province":"CA",
    "sg:tags":[
        "eating"
    ],
    "wof:name":"English House Fish & Chips",
    "wof:placetype":"venue"
},
  "geometry": {"coordinates":[-118.05468500000001,34.130459],"type":"Point"}
}