{
  "type": "Feature",
  "properties": {
    "iso:country":"US",
    "sg:address":"19698 State Hwy 88",
    "sg:city":"Pine Grove",
    "sg:classifiers":[
        {
            "category":"Shopping",
            "subcategory":"Music",
            "type":"Retail Goods"
        }
    ],
    "sg:phone":"+1 209 296 4200",
    "sg:postcode":"95665",
    "sg:province":"CA",
    "wof:name":"Video Rainbow",
    "wof:placetype":"venue"
},
  "geometry": {"coordinates":[-120.662368,38.413643],"type":"Point"}
}