{
  "type": "Feature",
  "properties": {
    "iso:country":"US",
    "sg:address":"16921 Parthenia St",
    "sg:city":"Northridge",
    "sg:classifiers":[
        {
            "category":"Professional",
            "subcategory":"Lawyer & Legal Services",
            "type":"Services"
        }
    ],
    "sg:phone":"+1 818 893 2746",
    "sg:postcode":"91343",
    "sg:province":"CA",
    "sg:tags":[
        "attorney"
    ],
    "wof:name":"A Verne Tjarks",
    "wof:placetype":"venue"
},
  "geometry": {"coordinates":[-118.50049300000001,34.228561],"type":"Point"}
}