{
  "type": "Feature",
  "properties": {
    "iso:country":"US",
    "sg:address":"3903 W Olympic Blvd",
    "sg:city":"Los Angeles",
    "sg:classifiers":[
        {
            "category":"Insurance",
            "subcategory":"Hazard Insurance",
            "type":"Services"
        }
    ],
    "sg:phone":"+1 323 857 1911",
    "sg:postcode":"90019",
    "sg:province":"CA",
    "sg:tags":[
        "bond"
    ],
    "wof:name":"Number One Bail Bonds",
    "wof:placetype":"venue"
},
  "geometry": {"coordinates":[-118.320654,34.053896],"type":"Point"}
}