{
  "type": "Feature",
  "properties": {
    "addr:full":"2736 Miramonte Pl Ontario CA 91761",
    "addr:housenumber":"2736",
    "addr:postcode":"91761",
    "addr:street":"Miramonte Pl",
    "iso:country":"US",
    "sg:address":"2736 Miramonte Pl",
    "sg:city":"Ontario",
    "sg:classifiers":[
        {
            "category":"Manufacturing",
            "subcategory":"Tools & Machinery",
            "type":"Manufacturing & Wholesale Goods"
        }
    ],
    "sg:phone":"+1 909 986 6557",
    "sg:postcode":"91761",
    "sg:province":"CA",
    "sg:tags":[
        "contractor"
    ],
    "wof:name":"Road & Site Equipment & Supply",
    "wof:placetype":"venue"
},
  "geometry": {"coordinates":[-117.643052,34.02442],"type":"Point"}
}