{
  "type": "Feature",
  "properties": {
    "addr:full":"2691 Tapo Canyon Rd Simi Valley CA 93063",
    "addr:housenumber":"2691",
    "addr:postcode":"93063",
    "addr:street":"Tapo Canyon Rd",
    "iso:country":"US",
    "sg:address":"2691 Tapo Canyon Rd",
    "sg:city":"Simi Valley",
    "sg:classifiers":[
        {
            "category":"Utilities",
            "subcategory":"Mobile Phone",
            "type":"Services"
        }
    ],
    "sg:phone":"+1 805 582 4320",
    "sg:postcode":"93063",
    "sg:province":"CA",
    "sg:tags":[
        "telephone",
        "cellular"
    ],
    "wof:name":"Cingular Wireless",
    "wof:placetype":"venue"
},
  "geometry": {"coordinates":[-118.717826,34.28282],"type":"Point"}
}