{
  "type": "Feature",
  "properties": {
    "iso:country":"US",
    "sg:address":"11139 Morning Creek Dr S",
    "sg:city":"San Diego",
    "sg:classifiers":[
        {
            "category":"Real Estate",
            "subcategory":"Real Estate Agent",
            "type":"Services"
        }
    ],
    "sg:phone":"+1 858 486 2591",
    "sg:postcode":"92128",
    "sg:province":"CA",
    "wof:name":"Jensen Appraisal",
    "wof:placetype":"venue"
},
  "geometry": {"coordinates":[-117.089665,32.956247],"type":"Point"}
}