{
  "type": "Feature",
  "properties": {
    "iso:country":"US",
    "sg:address":"725 E Yanonali St",
    "sg:city":"Santa Barbara",
    "sg:classifiers":[
        {
            "category":"Manufacturing",
            "subcategory":"Retail Goods",
            "type":"Manufacturing & Wholesale Goods"
        }
    ],
    "sg:phone":"+1 805 568 0304",
    "sg:postcode":"93103",
    "sg:province":"CA",
    "sg:tags":[
        "manufacturer"
    ],
    "sg:website":"www.strandproducts.com",
    "wof:name":"Strand Products Inc",
    "wof:placetype":"venue"
},
  "geometry": {"coordinates":[-119.682885,34.422225],"type":"Point"}
}