{
  "type": "Feature",
  "properties": {
    "iso:country":"US",
    "sg:address":"1425 Broadway",
    "sg:city":"Burlingame",
    "sg:classifiers":[
        {
            "category":"Health Services",
            "subcategory":"Health Practitioner",
            "type":"Services"
        }
    ],
    "sg:phone":"+1 650 342 6817",
    "sg:postcode":"94010",
    "sg:province":"CA",
    "sg:tags":[
        "psychotherapist"
    ],
    "wof:name":"Anne Hinckle",
    "wof:placetype":"venue"
},
  "geometry": {"coordinates":[-122.36610899999999,37.584329],"type":"Point"}
}