{
  "type": "Feature",
  "properties": {
    "addr:full":"3415 California St San Francisco CA 94118",
    "addr:housenumber":"3415",
    "addr:postcode":"94118",
    "addr:street":"California St",
    "iso:country":"US",
    "sg:address":"3415 California St",
    "sg:city":"San Francisco",
    "sg:classifiers":[
        {
            "category":"Restaurant",
            "type":"Food & Drink"
        }
    ],
    "sg:phone":"+1 415 751 4242",
    "sg:postcode":"94118",
    "sg:province":"CA",
    "wof:name":"Napa Ranch",
    "wof:placetype":"venue"
},
  "geometry": {"coordinates":[-122.451561,37.786576],"type":"Point"}
}