{
  "type": "Feature",
  "properties": {
    "iso:country":"US",
    "sg:address":"1045 N Genesee Ave Ste 10",
    "sg:city":"West Hollywood",
    "sg:classifiers":[
        {
            "category":"Building & Trades",
            "subcategory":"Plumbing",
            "type":"Services"
        }
    ],
    "sg:phone":"+1 323 654 5454",
    "sg:postcode":"90046",
    "sg:province":"CA",
    "sg:website":"www.royaleplumbing.com",
    "wof:name":"Royale Plumbing",
    "wof:placetype":"venue"
},
  "geometry": {"coordinates":[-118.35876,34.090115],"type":"Point"}
}