{
  "type": "Feature",
  "properties": {
    "addr:full":"603 N Towne Ave Pomona CA 91767",
    "addr:housenumber":"603",
    "addr:postcode":"91767",
    "addr:street":"N Towne Ave",
    "iso:country":"US",
    "sg:address":"603 N Towne Ave",
    "sg:city":"Pomona",
    "sg:classifiers":[
        {
            "category":"Shopping",
            "type":"Retail Goods"
        }
    ],
    "sg:phone":"+1 909 622 0822",
    "sg:postcode":"91767",
    "sg:province":"CA",
    "sg:tags":[
        "religious"
    ],
    "wof:name":"Botanica Luz Maria",
    "wof:placetype":"venue"
},
  "geometry": {"coordinates":[-117.741727,34.065104],"type":"Point"}
}