{
  "type": "Feature",
  "properties": {
    "addr:full":"875 W Cypress Rd Oakley CA 94561",
    "addr:housenumber":"875",
    "addr:postcode":"94561",
    "addr:street":"W Cypress Rd",
    "iso:country":"US",
    "sg:address":"875 W Cypress Rd",
    "sg:city":"Oakley",
    "sg:classifiers":[
        {
            "category":"Social Services",
            "subcategory":"Child Care",
            "type":"Services"
        }
    ],
    "sg:phone":"+1 925 625 5600",
    "sg:postcode":"94561",
    "sg:province":"CA",
    "wof:name":"Sunshine House",
    "wof:placetype":"venue"
},
  "geometry": {"coordinates":[-121.70746,37.990511],"type":"Point"}
}