{
  "type": "Feature",
  "properties": {
    "iso:country":"US",
    "sg:address":"926 N La Cienega Boulevard",
    "sg:city":"Los Angeles",
    "sg:classifiers":[
        {
            "category":"Home & Garden",
            "subcategory":"Home Furnishings",
            "type":"Retail Goods"
        }
    ],
    "sg:phone":"+1 310 659 9290",
    "sg:postcode":"90069",
    "sg:province":"CA",
    "sg:tags":[
        "bath",
        "kitchen"
    ],
    "wof:name":"Hollywood Sierra Kitchens",
    "wof:placetype":"venue"
},
  "geometry": {"coordinates":[-118.376309,34.087716],"type":"Point"}
}