{
  "type": "Feature",
  "properties": {
    "iso:country":"US",
    "sg:address":"23505 Crenshaw Blvd",
    "sg:city":"Torrance",
    "sg:classifiers":[
        {
            "category":"Health Services",
            "subcategory":"Doctor",
            "type":"Services"
        }
    ],
    "sg:phone":"+1 310 539 1462",
    "sg:postcode":"90505",
    "sg:province":"CA",
    "sg:tags":[
        "clinic"
    ],
    "wof:name":"Peak Medical",
    "wof:placetype":"venue"
},
  "geometry": {"coordinates":[-118.328115,33.811333],"type":"Point"}
}