{
  "type": "Feature",
  "properties": {
    "iso:country":"US",
    "sg:address":"2720 W Hemlock Ct",
    "sg:city":"Visalia",
    "sg:classifiers":[
        {
            "category":"Social Services",
            "subcategory":"Adult Care",
            "type":"Services"
        }
    ],
    "sg:phone":"+1 559 592 1917",
    "sg:postcode":"93277",
    "sg:province":"CA",
    "sg:tags":[
        "home",
        "residential"
    ],
    "wof:name":"Crestwood Place",
    "wof:placetype":"venue"
},
  "geometry": {"coordinates":[-119.320645,36.300125],"type":"Point"}
}