{
  "type": "Feature",
  "properties": {
    "addr:full":"55 New Montgomery St Ste 725 San Francisco CA 94105",
    "addr:housenumber":"55",
    "addr:postcode":"94105",
    "addr:street":"New Montgomery St Ste 725",
    "iso:country":"US",
    "sg:address":"55 New Montgomery St Ste 725",
    "sg:city":"San Francisco",
    "sg:classifiers":[
        {
            "category":"Health Services",
            "subcategory":"Doctor",
            "type":"Services"
        }
    ],
    "sg:phone":"+1 415 543 2418",
    "sg:postcode":"94105",
    "sg:province":"CA",
    "sg:tags":[
        "psychiatrist"
    ],
    "sg:website":"www.couplesinconflict.com",
    "wof:name":"Couples Counseling And Therapy Clinic",
    "wof:placetype":"venue"
},
  "geometry": {"coordinates":[-122.40105,37.787886],"type":"Point"}
}