{
  "type": "Feature",
  "properties": {
    "addr:full":"208 Haydon St Healdsburg CA 95448",
    "addr:housenumber":"208",
    "addr:postcode":"95448",
    "addr:street":"Haydon St",
    "iso:country":"US",
    "sg:address":"208 Haydon St",
    "sg:city":"Healdsburg",
    "sg:classifiers":[
        {
            "category":"Manufacturing",
            "subcategory":"Food",
            "type":"Manufacturing & Wholesale Goods"
        }
    ],
    "sg:phone":"+1 707 431 1291",
    "sg:postcode":"95448",
    "sg:province":"CA",
    "sg:tags":[
        "winery"
    ],
    "wof:name":"Staley Vineyards & Winery",
    "wof:placetype":"venue"
},
  "geometry": {"coordinates":[-122.86754500000001,38.608388],"type":"Point"}
}