{
  "type": "Feature",
  "properties": {
    "addr:full":"1688 29th St Arcata CA 95521",
    "addr:housenumber":"1688",
    "addr:postcode":"95521",
    "addr:street":"29Th St",
    "iso:country":"US",
    "sg:address":"1688 29th St",
    "sg:city":"Arcata",
    "sg:classifiers":[
        {
            "category":"Professional",
            "subcategory":"Research",
            "type":"Services"
        }
    ],
    "sg:phone":"+1 707 668 1821",
    "sg:postcode":"95521",
    "sg:province":"CA",
    "sg:tags":[
        "environmental",
        "ecological"
    ],
    "wof:name":"Six Rivers Restoration",
    "wof:placetype":"venue"
},
  "geometry": {"coordinates":[-124.088613,40.888212],"type":"Point"}
}