{
  "type": "Feature",
  "properties": {
    "iso:country":"US",
    "sg:address":"1060 Landavo Dr",
    "sg:city":"Escondido",
    "sg:classifiers":[
        {
            "category":"Professional",
            "subcategory":"Computer Services",
            "type":"Services"
        }
    ],
    "sg:phone":"+1 760 745 5514",
    "sg:postcode":"92027",
    "sg:province":"CA",
    "wof:name":"Mobileman Computer Tech Servic",
    "wof:placetype":"venue"
},
  "geometry": {"coordinates":[-117.053251,33.113779],"type":"Point"}
}