{
  "type": "Feature",
  "properties": {
    "iso:country":"US",
    "sg:address":"451 Lovers Ln",
    "sg:city":"Ukiah",
    "sg:classifiers":[
        {
            "category":"Building & Trades",
            "subcategory":"Construction",
            "type":"Services"
        }
    ],
    "sg:phone":"+1 707 485 9468",
    "sg:postcode":"95482",
    "sg:province":"CA",
    "sg:tags":[
        "contractor"
    ],
    "wof:name":"North Coast Construction Corp",
    "wof:placetype":"venue"
},
  "geometry": {"coordinates":[-123.21972100000001,39.172045],"type":"Point"}
}