{
  "type": "Feature",
  "properties": {
    "addr:full":"23357 Mulholland Dr Woodland Hills CA 91364",
    "addr:housenumber":"23357",
    "addr:postcode":"91364",
    "addr:street":"Mulholland Dr",
    "iso:country":"US",
    "sg:address":"23357 Mulholland Dr",
    "sg:city":"Woodland Hills",
    "sg:classifiers":[
        {
            "category":"Shopping",
            "subcategory":"Pharmacy",
            "type":"Retail Goods"
        }
    ],
    "sg:phone":"+1 818 223 8222",
    "sg:postcode":"91364",
    "sg:province":"CA",
    "sg:tags":[
        "drugstore"
    ],
    "wof:name":"Sav-On Drugs",
    "wof:placetype":"venue"
},
  "geometry": {"coordinates":[-118.636002,34.157799],"type":"Point"}
}