{
  "type": "Feature",
  "properties": {
    "iso:country":"US",
    "sg:address":"8125 I Ave",
    "sg:city":"Hesperia",
    "sg:classifiers":[
        {
            "category":"Personal",
            "subcategory":"Tattoo Parlor",
            "type":"Services"
        }
    ],
    "sg:phone":"+1 760 947 9007",
    "sg:postcode":"92345",
    "sg:province":"CA",
    "sg:tags":[
        "tattooing"
    ],
    "wof:name":"Rod Andrade Voodoo Lounge",
    "wof:placetype":"venue"
},
  "geometry": {"coordinates":[-117.28066099999999,34.399179],"type":"Point"}
}