{
  "type": "Feature",
  "properties": {
    "iso:country":"US",
    "sg:address":"119 N Maple St",
    "sg:city":"Corona",
    "sg:classifiers":[
        {
            "category":"Building & Trades",
            "subcategory":"Construction",
            "type":"Services"
        }
    ],
    "sg:phone":"+1 951 735 2275",
    "sg:postcode":"92880",
    "sg:province":"CA",
    "sg:tags":[
        "painter"
    ],
    "sg:website":"www.actionpainting.com",
    "wof:name":"Action Painting Co",
    "wof:placetype":"venue"
},
  "geometry": {"coordinates":[-117.60291100000001,33.884089],"type":"Point"}
}