{
  "type": "Feature",
  "properties": {
    "iso:country":"US",
    "sg:address":"3250 Victory Dr",
    "sg:city":"Rocklin",
    "sg:classifiers":[
        {
            "category":"Education",
            "subcategory":"School",
            "type":"Public Place"
        }
    ],
    "sg:phone":"+1 916 632 3195",
    "sg:postcode":"95765",
    "sg:province":"CA",
    "sg:tags":[
        "high"
    ],
    "wof:name":"Victory High School",
    "wof:placetype":"venue"
},
  "geometry": {"coordinates":[-121.254835,38.815433],"type":"Point"}
}