{
  "type": "Feature",
  "properties": {
    "iso:country":"US",
    "sg:address":"776 S Orange Grove Blvd",
    "sg:city":"Pasadena",
    "sg:classifiers":[
        {
            "category":"Professional",
            "subcategory":"Art Services",
            "type":"Services"
        }
    ],
    "sg:phone":"+1 626 799 6584",
    "sg:postcode":"91105",
    "sg:province":"CA",
    "sg:tags":[
        "graphic",
        "designer"
    ],
    "wof:name":"Ohkagawa Design",
    "wof:placetype":"venue"
},
  "geometry": {"coordinates":[-118.158597,34.132309],"type":"Point"}
}