{
  "type": "Feature",
  "properties": {
    "addr:full":"341 Del AMO Fashion Ctr Torrance CA 90501",
    "addr:housenumber":"341",
    "addr:postcode":"90501",
    "addr:street":"Del Amo Fashion Ctr",
    "iso:country":"US",
    "sg:address":"341 Del AMO Fashion Ctr",
    "sg:city":"Torrance",
    "sg:classifiers":[
        {
            "category":"Shopping",
            "subcategory":"Clothing, Apparel, & Fashions",
            "type":"Retail Goods"
        }
    ],
    "sg:phone":"+1 310 370 8204",
    "sg:postcode":"90501",
    "sg:province":"CA",
    "sg:tags":[
        "accessory",
        "clothing",
        "women's"
    ],
    "sg:website":"www.nyandcompany.com",
    "wof:name":"New York & Company",
    "wof:placetype":"venue"
},
  "geometry": {"coordinates":[-118.351586,33.828577],"type":"Point"}
}