{
  "type": "Feature",
  "properties": {
    "addr:full":"2380 Rochelle Ave Turlock CA 95382",
    "addr:housenumber":"2380",
    "addr:postcode":"95382",
    "addr:street":"Rochelle Ave",
    "iso:country":"US",
    "sg:address":"2380 Rochelle Ave",
    "sg:city":"Turlock",
    "sg:classifiers":[
        {
            "category":"Farming",
            "subcategory":"Farm & Veterinary Services",
            "type":"Manufacturing & Wholesale Goods"
        }
    ],
    "sg:phone":"+1 209 632 4985",
    "sg:postcode":"95382",
    "sg:province":"CA",
    "sg:tags":[
        "crop",
        "harvesting"
    ],
    "wof:name":"Bankson Hay Harvesting",
    "wof:placetype":"venue"
},
  "geometry": {"coordinates":[-120.85672099999999,37.514486],"type":"Point"}
}