{
  "type": "Feature",
  "properties": {
    "addr:full":"1151 Vasquez Ave Sunnyvale CA 94086",
    "addr:housenumber":"1151",
    "addr:postcode":"94086",
    "addr:street":"Vasquez Ave",
    "iso:country":"US",
    "sg:address":"1151 Vasquez Ave",
    "sg:city":"Sunnyvale",
    "sg:classifiers":[
        {
            "category":"Manufacturing",
            "subcategory":"Toys & Sporting Goods",
            "type":"Manufacturing & Wholesale Goods"
        }
    ],
    "sg:phone":"+1 408 733 9542",
    "sg:postcode":"94086",
    "sg:province":"CA",
    "sg:tags":[
        "house",
        "mfg",
        "mail"
    ],
    "wof:name":"Woodstalk Face Mask",
    "wof:placetype":"venue"
},
  "geometry": {"coordinates":[-122.05423,37.3771],"type":"Point"}
}