{
  "type": "Feature",
  "properties": {
    "addr:full":"81 Percy Ave Yuba City CA 95991",
    "addr:housenumber":"81",
    "addr:postcode":"95991",
    "addr:street":"Percy Ave",
    "iso:country":"US",
    "sg:address":"81 Percy Ave",
    "sg:city":"Yuba City",
    "sg:classifiers":[
        {
            "category":"Retail",
            "subcategory":"Auto Repair",
            "type":"Services"
        }
    ],
    "sg:phone":"+1 530 751 0578",
    "sg:postcode":"95991",
    "sg:province":"CA",
    "sg:tags":[
        "repairing",
        "automobile"
    ],
    "wof:name":"Percy Ave Garage",
    "wof:placetype":"venue"
},
  "geometry": {"coordinates":[-121.613088,39.122648],"type":"Point"}
}