{
  "type": "Feature",
  "properties": {
    "addr:full":"1450 W Mission Rd San Marcos CA 92069",
    "addr:housenumber":"1450",
    "addr:postcode":"92069",
    "addr:street":"W Mission Rd",
    "iso:country":"US",
    "sg:address":"1450 W Mission Rd",
    "sg:city":"San Marcos",
    "sg:classifiers":[
        {
            "category":"Restaurant",
            "type":"Food & Drink"
        }
    ],
    "sg:phone":"+1 760 727 3643",
    "sg:postcode":"92069",
    "sg:province":"CA",
    "wof:name":"Bangkok Garden",
    "wof:placetype":"venue"
},
  "geometry": {"coordinates":[-117.192556,33.150824],"type":"Point"}
}