{
  "type": "Feature",
  "properties": {
    "iso:country":"US",
    "sg:address":"8240 Santa Monica Blvd.",
    "sg:city":"West Hollywood",
    "sg:classifiers":[
        {
            "category":"Health Services",
            "subcategory":"Optometrist",
            "type":"Services"
        }
    ],
    "sg:phone":"+1 323 654 2346",
    "sg:postcode":"90046",
    "sg:province":"CA",
    "sg:website":"www.DrJasonPeters.com",
    "wof:name":"Dr. Jason Peters Optometrist",
    "wof:placetype":"venue"
},
  "geometry": {"coordinates":[-118.36847,34.090715],"type":"Point"}
}