{
  "type": "Feature",
  "properties": {
    "iso:country":"US",
    "sg:address":"7942 Cypress Ave",
    "sg:city":"Huntington Beach",
    "sg:classifiers":[
        {
            "category":"Taxi",
            "type":"Transportation"
        }
    ],
    "sg:phone":"+1 714 847 3700",
    "sg:postcode":"92647",
    "sg:province":"CA",
    "wof:name":"Yellow Cab",
    "wof:placetype":"venue"
},
  "geometry": {"coordinates":[-117.98999000000001,33.713282],"type":"Point"}
}