{
  "type": "Feature",
  "properties": {
    "addr:full":"41 Baroness Ln Laguna Niguel CA 92677",
    "addr:housenumber":"41",
    "addr:postcode":"92677",
    "addr:street":"Baroness Ln",
    "iso:country":"US",
    "sg:address":"41 Baroness Ln",
    "sg:city":"Laguna Niguel",
    "sg:classifiers":[
        {
            "category":"Shopping",
            "subcategory":"Clothing, Apparel, & Fashions",
            "type":"Retail Goods"
        }
    ],
    "sg:phone":"+1 949 637 5452",
    "sg:postcode":"92677",
    "sg:province":"CA",
    "wof:name":"Island Tribe",
    "wof:placetype":"venue"
},
  "geometry": {"coordinates":[-117.683497,33.529761],"type":"Point"}
}