{
  "type": "Feature",
  "properties": {
    "iso:country":"US",
    "sg:address":"1758 Corporate Cir",
    "sg:city":"Petaluma",
    "sg:classifiers":[
        {
            "category":"Professional",
            "subcategory":"Management & Consulting",
            "type":"Services"
        }
    ],
    "sg:phone":"+1 707 776 8200",
    "sg:postcode":"94954",
    "sg:province":"CA",
    "sg:tags":[
        "marketing",
        "program"
    ],
    "wof:name":"Water-Pik Technologies",
    "wof:placetype":"venue"
},
  "geometry": {"coordinates":[-122.598803,38.23011],"type":"Point"}
}