{
  "type": "Feature",
  "properties": {
    "addr:full":"2741 Saturn St Brea CA 92821",
    "addr:housenumber":"2741",
    "addr:postcode":"92821",
    "addr:street":"Saturn St",
    "iso:country":"US",
    "sg:address":"2741 Saturn St",
    "sg:city":"Brea",
    "sg:classifiers":[
        {
            "category":"Shopping",
            "type":"Retail Goods"
        }
    ],
    "sg:phone":"+1 714 993 9189",
    "sg:postcode":"92821",
    "sg:province":"CA",
    "sg:tags":[
        "merchandise"
    ],
    "wof:name":"Harness Shop",
    "wof:placetype":"venue"
},
  "geometry": {"coordinates":[-117.85948,33.908441],"type":"Point"}
}