{
  "type": "Feature",
  "properties": {
    "addr:full":"9320 Wilshire Blvd Beverly Hills CA 90212",
    "addr:housenumber":"9320",
    "addr:postcode":"90212",
    "addr:street":"Wilshire Blvd",
    "iso:country":"US",
    "sg:address":"9320 Wilshire Blvd",
    "sg:city":"Beverly Hills",
    "sg:classifiers":[
        {
            "category":"Professional",
            "type":"Services"
        }
    ],
    "sg:phone":"+1 310 247 0079",
    "sg:postcode":"90212",
    "sg:province":"CA",
    "sg:tags":[
        "establishment"
    ],
    "wof:name":"Korbel Media",
    "wof:placetype":"venue"
},
  "geometry": {"coordinates":[-118.39422,34.066975],"type":"Point"}
}