{
  "type": "Feature",
  "properties": {
    "addr:full":"4345 E 14th St Oakland CA 94601",
    "addr:housenumber":"4345",
    "addr:postcode":"94601",
    "addr:street":"E 14Th St",
    "iso:country":"US",
    "sg:address":"4345 E 14th St",
    "sg:city":"Oakland",
    "sg:classifiers":[
        {
            "category":"Restaurant",
            "type":"Food & Drink"
        }
    ],
    "sg:phone":"+1 510 261 9125",
    "sg:postcode":"94601",
    "sg:province":"CA",
    "wof:name":"Taqueria Zamorano",
    "wof:placetype":"venue"
},
  "geometry": {"coordinates":[-122.214336,37.772096],"type":"Point"}
}