{
  "type": "Feature",
  "properties": {
    "iso:country":"US",
    "sg:address":"9449 Balboa Ave",
    "sg:city":"San Diego",
    "sg:classifiers":[
        {
            "category":"Manufacturing",
            "subcategory":"Electronics",
            "type":"Manufacturing & Wholesale Goods"
        }
    ],
    "sg:phone":"+1 858 292 2390",
    "sg:postcode":"92111",
    "sg:province":"CA",
    "sg:tags":[
        "equipment",
        "electronic",
        "supply"
    ],
    "wof:name":"Panasonic Acom",
    "wof:placetype":"venue"
},
  "geometry": {"coordinates":[-117.126023,32.822251],"type":"Point"}
}