{
  "type": "Feature",
  "properties": {
    "iso:country":"US",
    "sg:address":"3931 Durock Rd",
    "sg:city":"Cameron Park",
    "sg:classifiers":[
        {
            "category":"Real Estate",
            "subcategory":"Real Estate Agent",
            "type":"Services"
        }
    ],
    "sg:phone":"+1 530 677 7917",
    "sg:postcode":"95682",
    "sg:province":"CA",
    "sg:tags":[
        "management"
    ],
    "wof:name":"Home Point Property Management",
    "wof:placetype":"venue"
},
  "geometry": {"coordinates":[-120.945769,38.659303],"type":"Point"}
}