{
  "type": "Feature",
  "properties": {
    "addr:full":"8217 Lankershim Blvd North Hollywood CA 91605",
    "addr:housenumber":"8217",
    "addr:postcode":"91605",
    "addr:street":"Lankershim Blvd",
    "iso:country":"US",
    "sg:address":"8217 Lankershim Blvd",
    "sg:city":"North Hollywood",
    "sg:classifiers":[
        {
            "category":"Home & Garden",
            "subcategory":"Home Furnishings",
            "type":"Retail Goods"
        }
    ],
    "sg:phone":"+1 818 771 9249",
    "sg:postcode":"91605",
    "sg:province":"CA",
    "sg:tags":[
        "upholstery",
        "fabric"
    ],
    "wof:name":"Larios Upholstery",
    "wof:placetype":"venue"
},
  "geometry": {"coordinates":[-118.387854,34.222259],"type":"Point"}
}