{
  "type": "Feature",
  "properties": {
    "addr:full":"1250 Bayhill Dr San Bruno CA 94066",
    "addr:housenumber":"1250",
    "addr:postcode":"94066",
    "addr:street":"Bayhill Dr",
    "iso:country":"US",
    "sg:address":"1250 Bayhill Dr",
    "sg:city":"San Bruno",
    "sg:classifiers":[
        {
            "category":"Utilities",
            "subcategory":"Telephone",
            "type":"Services"
        }
    ],
    "sg:phone":"+1 650 737 6000",
    "sg:postcode":"94066",
    "sg:province":"CA",
    "wof:name":"Automted Systems With Chracter",
    "wof:placetype":"venue"
},
  "geometry": {"coordinates":[-122.42535700000001,37.627601],"type":"Point"}
}