{
  "type": "Feature",
  "properties": {
    "addr:full":"36 S Los Robles Ave Pasadena CA 91101",
    "addr:housenumber":"36",
    "addr:postcode":"91101",
    "addr:street":"S Los Robles Ave",
    "iso:country":"US",
    "sg:address":"36 S Los Robles Ave",
    "sg:city":"Pasadena",
    "sg:classifiers":[
        {
            "category":"Arena",
            "subcategory":"Sports Club",
            "type":"Entertainment"
        }
    ],
    "sg:phone":"+1 626 793 8575",
    "sg:postcode":"91101",
    "sg:province":"CA",
    "sg:tags":[
        "martial art"
    ],
    "wof:name":"Scholar & Warrior Kenpo Karate",
    "wof:placetype":"venue"
},
  "geometry": {"coordinates":[-118.141998,34.145302],"type":"Point"}
}