{
  "type": "Feature",
  "properties": {
    "iso:country":"US",
    "sg:address":"9500 Micron Ave",
    "sg:city":"Sacramento",
    "sg:classifiers":[
        {
            "category":"Shopping",
            "subcategory":"Musical Instruments",
            "type":"Retail Goods"
        }
    ],
    "sg:phone":"+1 916 362 4100",
    "sg:postcode":"95827",
    "sg:province":"CA",
    "sg:tags":[
        "piano"
    ],
    "wof:name":"Larrick Piano & Organ",
    "wof:placetype":"venue"
},
  "geometry": {"coordinates":[-121.346622,38.560759],"type":"Point"}
}