{
  "type": "Feature",
  "properties": {
    "iso:country":"US",
    "sg:address":"3518 Mt Diablo Blvd Ste B",
    "sg:city":"Lafayette",
    "sg:classifiers":[
        {
            "category":"Shopping",
            "subcategory":"Stationery & Office Supplies",
            "type":"Retail Goods"
        },
        {
            "category":"Manufacturing",
            "subcategory":"Paper Products",
            "type":"Manufacturing & Wholesale Goods"
        }
    ],
    "sg:phone":"+1 925 299 1024",
    "sg:postcode":"94549",
    "sg:province":"CA",
    "sg:tags":[
        "envelope",
        "stationery-wholesale",
        "store",
        "manufacturer"
    ],
    "wof:name":"Madison",
    "wof:placetype":"venue"
},
  "geometry": {"coordinates":[-122.11747699999999,37.892172],"type":"Point"}
}