{
  "type": "Feature",
  "properties": {
    "addr:full":"2035 Ralston Ave Belmont CA 94002",
    "addr:housenumber":"2035",
    "addr:postcode":"94002",
    "addr:street":"Ralston Ave",
    "iso:country":"US",
    "sg:address":"2035 Ralston Ave",
    "sg:city":"Belmont",
    "sg:classifiers":[
        {
            "category":"Food & Beverages",
            "subcategory":"Liquor & Beverages",
            "type":"Retail Goods"
        },
        {
            "category":"Shopping Center",
            "type":"Public Place"
        }
    ],
    "sg:phone":"+1 650 592 5259",
    "sg:postcode":"94002",
    "sg:province":"CA",
    "sg:tags":[
        "beer",
        "spirit",
        "wine"
    ],
    "wof:name":"Carlmont Liquors",
    "wof:placetype":"venue"
},
  "geometry": {"coordinates":[-122.293999,37.512199],"type":"Point"}
}