{
  "type": "Feature",
  "properties": {
    "addr:full":"26848 Marina Point Ln Santa Clarita CA 91355",
    "addr:postcode":"26848;91355",
    "addr:street":"Marina Point Ln",
    "iso:country":"US",
    "sg:address":"26848 Marina Point Ln",
    "sg:city":"Santa Clarita",
    "sg:classifiers":[
        {
            "category":"Building & Trades",
            "subcategory":"Plumbing",
            "type":"Services"
        }
    ],
    "sg:phone":"+1 661 513 9114",
    "sg:postcode":"91355",
    "sg:province":"CA",
    "wof:name":"All American Water Heaters & Plumbing Inc",
    "wof:placetype":"venue"
},
  "geometry": {"coordinates":[-118.54541999999999,34.427189],"type":"Point"}
}