{
  "type": "Feature",
  "properties": {
    "iso:country":"US",
    "sg:address":"130 E Grand Ave",
    "sg:city":"Escondido",
    "sg:classifiers":[
        {
            "category":"Professional",
            "subcategory":"Computer Services",
            "type":"Services"
        }
    ],
    "sg:phone":"+1 858 674 2860",
    "sg:postcode":"92025",
    "sg:province":"CA",
    "sg:tags":[
        "consultant",
        "designer",
        "datum",
        "system"
    ],
    "wof:name":"Evit Avonni Inc",
    "wof:placetype":"venue"
},
  "geometry": {"coordinates":[-117.080536,33.122202],"type":"Point"}
}