{
  "type": "Feature",
  "properties": {
    "iso:country":"US",
    "sg:address":"18908 Willard St",
    "sg:city":"Reseda",
    "sg:classifiers":[
        {
            "category":"Professional",
            "type":"Services"
        }
    ],
    "sg:phone":"+1 818 701 7569",
    "sg:postcode":"91335",
    "sg:province":"CA",
    "wof:name":"Adalberto Aguirre Jr",
    "wof:placetype":"venue"
},
  "geometry": {"coordinates":[-118.54545899999999,34.218786],"type":"Point"}
}