{
  "type": "Feature",
  "properties": {
    "iso:country":"US",
    "sg:address":"26352 Carmel Rancho Ln",
    "sg:city":"Carmel",
    "sg:classifiers":[
        {
            "category":"Banks & Credit Unions",
            "subcategory":"Investment Brokerage",
            "type":"Services"
        }
    ],
    "sg:phone":"+1 831 622 0262",
    "sg:postcode":"93923",
    "sg:province":"CA",
    "sg:tags":[
        "advisory",
        "financial"
    ],
    "wof:name":"Steven R Hutt Financial Advsr",
    "wof:placetype":"venue"
},
  "geometry": {"coordinates":[-121.906039,36.540403],"type":"Point"}
}