{
  "type": "Feature",
  "properties": {
    "iso:country":"US",
    "sg:address":"145 Neptune Pl",
    "sg:city":"Escondido",
    "sg:classifiers":[
        {
            "category":"Shopping",
            "subcategory":"Hobbies, Toys, & Games",
            "type":"Retail Goods"
        }
    ],
    "sg:phone":"+1 760 738 6286",
    "sg:postcode":"92026",
    "sg:province":"CA",
    "sg:tags":[
        "supply"
    ],
    "wof:name":"BPG Better Priced Games",
    "wof:placetype":"venue"
},
  "geometry": {"coordinates":[-117.090435,33.149392],"type":"Point"}
}