{
  "type": "Feature",
  "properties": {
    "addr:full":"18750 Deerhorn Valley Rd Jamul CA 91935",
    "addr:housenumber":"18750",
    "addr:postcode":"91935",
    "addr:street":"Deerhorn Valley Rd",
    "iso:country":"US",
    "sg:address":"18750 Deerhorn Valley Rd",
    "sg:city":"Jamul",
    "sg:classifiers":[
        {
            "category":"Farming",
            "subcategory":"Fish & Marine Products",
            "type":"Manufacturing & Wholesale Goods"
        }
    ],
    "sg:phone":"+1 619 468 3044",
    "sg:postcode":"91935",
    "sg:province":"CA",
    "sg:tags":[
        "fishing"
    ],
    "wof:name":"Her Grace Fisheries Inc",
    "wof:placetype":"venue"
},
  "geometry": {"coordinates":[-116.743295,32.676907],"type":"Point"}
}