{
  "type": "Feature",
  "properties": {
    "addr:full":"142 10th St San Francisco CA 94103",
    "addr:housenumber":"142",
    "addr:postcode":"94103",
    "addr:street":"10Th St",
    "iso:country":"US",
    "sg:address":"142 10th St",
    "sg:city":"San Francisco",
    "sg:classifiers":[
        {
            "category":"Professional",
            "subcategory":"Computer Services",
            "type":"Services"
        }
    ],
    "sg:phone":"+1 415 581 0700",
    "sg:postcode":"94103",
    "sg:province":"CA",
    "sg:tags":[
        "internet"
    ],
    "wof:name":"Birthday Alarm",
    "wof:placetype":"venue"
},
  "geometry": {"coordinates":[-122.41574300000001,37.775112],"type":"Point"}
}