{
  "type": "Feature",
  "properties": {
    "addr:full":"16366 Blanco St San Leandro CA 94578",
    "addr:housenumber":"16366",
    "addr:postcode":"94578",
    "addr:street":"Blanco St",
    "iso:country":"US",
    "sg:address":"16366 Blanco St",
    "sg:city":"San Leandro",
    "sg:classifiers":[
        {
            "category":"Organizations",
            "subcategory":"Religious Organization",
            "type":"Services"
        }
    ],
    "sg:phone":"+1 510 481 7852",
    "sg:postcode":"94578",
    "sg:province":"CA",
    "wof:name":"Mc Gee Avenue Baptist Church",
    "wof:placetype":"venue"
},
  "geometry": {"coordinates":[-122.113196,37.696003],"type":"Point"}
}