{
  "type": "Feature",
  "properties": {
    "iso:country":"US",
    "sg:address":"220 N Spring St",
    "sg:city":"Blythe",
    "sg:classifiers":[
        {
            "category":"Government",
            "subcategory":"Office",
            "type":"Public Place"
        }
    ],
    "sg:phone":"+1 760 922 6161",
    "sg:postcode":"92225",
    "sg:province":"CA",
    "sg:tags":[
        "city"
    ],
    "wof:name":"City Clerk",
    "wof:placetype":"venue"
},
  "geometry": {"coordinates":[-114.598203,33.613636],"type":"Point"}
}