{
  "type": "Feature",
  "properties": {
    "addr:full":"2009 Chapala St Santa Barbara CA 93105",
    "addr:housenumber":"2009",
    "addr:postcode":"93105",
    "addr:street":"Chapala St",
    "iso:country":"US",
    "sg:address":"2009 Chapala St",
    "sg:city":"Santa Barbara",
    "sg:classifiers":[
        {
            "category":"Shopping",
            "subcategory":"Clothing, Apparel, & Fashions",
            "type":"Retail Goods"
        }
    ],
    "sg:phone":"+1 805 455 7538",
    "sg:postcode":"93105",
    "sg:province":"CA",
    "sg:tags":[
        "shop",
        "bridal"
    ],
    "wof:name":"Beautiful Boutique",
    "wof:placetype":"venue"
},
  "geometry": {"coordinates":[-119.71709199999999,34.430689],"type":"Point"}
}