{
  "type": "Feature",
  "properties": {
    "addr:full":"209 Sanchez St San Francisco CA 94114",
    "addr:housenumber":"209",
    "addr:postcode":"94114",
    "addr:street":"Sanchez St",
    "iso:country":"US",
    "sg:address":"209 Sanchez St",
    "sg:city":"San Francisco",
    "sg:classifiers":[
        {
            "category":"Retail",
            "subcategory":"Animal Services",
            "type":"Services"
        }
    ],
    "sg:phone":"+1 415 431 0969",
    "sg:postcode":"94114",
    "sg:province":"CA",
    "wof:name":"Barking Lot",
    "wof:placetype":"venue"
},
  "geometry": {"coordinates":[-122.43081599999999,37.764502],"type":"Point"}
}