{
  "type": "Feature",
  "properties": {
    "iso:country":"US",
    "sg:address":"660 Floyd Ave",
    "sg:city":"Chula Vista",
    "sg:classifiers":[
        {
            "category":"Banks & Credit Unions",
            "subcategory":"Financial Services",
            "type":"Services"
        }
    ],
    "sg:phone":"+1 619 421 7877",
    "sg:postcode":"91910",
    "sg:province":"CA",
    "sg:tags":[
        "trust",
        "management"
    ],
    "wof:name":"Foss Family Trust 3 06 23",
    "wof:placetype":"venue"
},
  "geometry": {"coordinates":[-117.04263400000001,32.63559],"type":"Point"}
}