{
  "type": "Feature",
  "properties": {
    "addr:full":"2501 W Redondo Beach Blvd Apt 141 Gardena CA 90249",
    "addr:housenumber":"2501;141",
    "addr:postcode":"90249",
    "addr:street":"W Redondo Beach Blvd Apt",
    "iso:country":"US",
    "sg:address":"2501 W Redondo Beach Blvd Apt 141",
    "sg:city":"Gardena",
    "sg:classifiers":[
        {
            "category":"Landmark",
            "subcategory":"Tourist Information",
            "type":"Public Place"
        }
    ],
    "sg:phone":"+1 310 538 1020",
    "sg:postcode":"90249",
    "sg:province":"CA",
    "sg:tags":[
        "tour"
    ],
    "wof:name":"Good Times Charter Tours",
    "wof:placetype":"venue"
},
  "geometry": {"coordinates":[-118.320562,33.885776],"type":"Point"}
}