{
  "type": "Feature",
  "properties": {
    "iso:country":"US",
    "sg:address":"3219 Middlefield Rd",
    "sg:city":"Menlo Park",
    "sg:classifiers":[
        {
            "category":"Retail",
            "subcategory":"Repair Shop",
            "type":"Services"
        }
    ],
    "sg:phone":"+1 650 368 3384",
    "sg:postcode":"94025",
    "sg:province":"CA",
    "sg:tags":[
        "equipment",
        "video"
    ],
    "wof:name":"West Bay Television",
    "wof:placetype":"venue"
},
  "geometry": {"coordinates":[-122.20394400000001,37.471886],"type":"Point"}
}