{
  "type": "Feature",
  "properties": {
    "iso:country":"US",
    "sg:address":"2915 Chanticleer Ave",
    "sg:city":"Santa Cruz",
    "sg:classifiers":[
        {
            "category":"Health Services",
            "subcategory":"Clinic",
            "type":"Services"
        }
    ],
    "sg:phone":"+1 831 477 2375",
    "sg:postcode":"95065",
    "sg:province":"CA",
    "sg:tags":[
        "medical"
    ],
    "wof:name":"Van Ooy Michelle MD",
    "wof:placetype":"venue"
},
  "geometry": {"coordinates":[-121.978323,36.987928],"type":"Point"}
}