{
  "type": "Feature",
  "properties": {
    "iso:country":"US",
    "sg:address":"15200 W Sunset Blvd",
    "sg:city":"Pacific Plsds",
    "sg:classifiers":[
        {
            "category":"Sports & Exercise",
            "subcategory":"Gym",
            "type":"Entertainment"
        }
    ],
    "sg:phone":"+1 310 459 9845",
    "sg:postcode":"90272",
    "sg:province":"CA",
    "sg:tags":[
        "club",
        "health",
        "studio",
        "gymnasium"
    ],
    "wof:name":"Gym'N'Tonic Pilates Exercise",
    "wof:placetype":"venue"
},
  "geometry": {"coordinates":[-118.52506700000001,34.046766],"type":"Point"}
}