{
  "type": "Feature",
  "properties": {
    "iso:country":"US",
    "sg:address":"815 W 15th St",
    "sg:city":"Newport Beach",
    "sg:classifiers":[
        {
            "category":"Real Estate",
            "subcategory":"Real Estate Agent",
            "type":"Services"
        }
    ],
    "sg:phone":"+1 949 642 3101",
    "sg:postcode":"92663",
    "sg:province":"CA",
    "wof:name":"Cs Dobbie Apppraisal Serv",
    "wof:placetype":"venue"
},
  "geometry": {"coordinates":[-117.932314,33.628779],"type":"Point"}
}