{
  "type": "Feature",
  "properties": {
    "iso:country":"US",
    "sg:address":"3227 Napa Dr",
    "sg:city":"San Jose",
    "sg:classifiers":[
        {
            "category":"Real Estate",
            "subcategory":"Real Estate Agent",
            "type":"Services"
        }
    ],
    "sg:phone":"+1 408 251 4080",
    "sg:postcode":"95148",
    "sg:province":"CA",
    "wof:name":"Adair Realty",
    "wof:placetype":"venue"
},
  "geometry": {"coordinates":[-121.79528500000001,37.334092],"type":"Point"}
}