{
  "type": "Feature",
  "properties": {
    "addr:full":"214 S Euclid Ave Ontario CA 91762",
    "addr:housenumber":"214",
    "addr:postcode":"91762",
    "addr:street":"S Euclid Ave",
    "iso:country":"US",
    "sg:address":"214 S Euclid Ave",
    "sg:city":"Ontario",
    "sg:classifiers":[
        {
            "category":"Wholesale",
            "subcategory":"Medical Equipment & Supplies",
            "type":"Manufacturing & Wholesale Goods"
        }
    ],
    "sg:phone":"+1 909 986 1728",
    "sg:postcode":"91762",
    "sg:province":"CA",
    "sg:tags":[
        "physician",
        "surgeon"
    ],
    "wof:name":"Duemah Medical Distribution",
    "wof:placetype":"venue"
},
  "geometry": {"coordinates":[-117.651061,34.06234],"type":"Point"}
}