{
  "type": "Feature",
  "properties": {
    "addr:full":"1719 E 55th St Vernon CA 90058",
    "addr:housenumber":"1719",
    "addr:postcode":"90058",
    "addr:street":"E 55Th St",
    "iso:country":"US",
    "sg:address":"1719 E 55th St",
    "sg:city":"Vernon",
    "sg:classifiers":[
        {
            "category":"Social Services",
            "subcategory":"Child Care",
            "type":"Services"
        }
    ],
    "sg:phone":"+1 323 586 0970",
    "sg:postcode":"90058",
    "sg:province":"CA",
    "sg:tags":[
        "day"
    ],
    "wof:name":"Nay Nay Day Care",
    "wof:placetype":"venue"
},
  "geometry": {"coordinates":[-118.242214,33.993107],"type":"Point"}
}