{
  "type": "Feature",
  "properties": {
    "addr:full":"250 N Clovis Ave Clovis CA 93612",
    "addr:housenumber":"250",
    "addr:postcode":"93612",
    "addr:street":"N Clovis Ave",
    "iso:country":"US",
    "sg:address":"250 N Clovis Ave",
    "sg:city":"Clovis",
    "sg:classifiers":[
        {
            "category":"Recreation",
            "subcategory":"Marina",
            "type":"Entertainment"
        }
    ],
    "sg:phone":"+1 559 299 6752",
    "sg:postcode":"93612",
    "sg:province":"CA",
    "sg:tags":[
        "operation"
    ],
    "wof:name":"Western Storage",
    "wof:placetype":"venue"
},
  "geometry": {"coordinates":[-119.699979,36.833912],"type":"Point"}
}