{
  "type": "Feature",
  "properties": {
    "addr:full":"512 W California Ave Vista CA 92083",
    "addr:housenumber":"512",
    "addr:postcode":"92083",
    "addr:street":"W California Ave",
    "iso:country":"US",
    "sg:address":"512 W California Ave",
    "sg:city":"Vista",
    "sg:classifiers":[
        {
            "category":"Professional",
            "subcategory":"Business Services",
            "type":"Services"
        }
    ],
    "sg:phone":"+1 858 488 0139",
    "sg:postcode":"92083",
    "sg:province":"CA",
    "sg:tags":[
        "interior",
        "consultant",
        "design",
        "decorator"
    ],
    "wof:name":"A C Interior",
    "wof:placetype":"venue"
},
  "geometry": {"coordinates":[-117.250722,33.208425],"type":"Point"}
}