{
  "type": "Feature",
  "properties": {
    "iso:country":"US",
    "sg:address":"815 W 2nd St",
    "sg:city":"San Bernardino",
    "sg:classifiers":[
        {
            "category":"Professional",
            "subcategory":"Lawyer & Legal Services",
            "type":"Services"
        }
    ],
    "sg:phone":"+1 909 381 3818",
    "sg:postcode":"92410",
    "sg:province":"CA",
    "sg:tags":[
        "naturalization",
        "immigration"
    ],
    "wof:name":"Centro Hispano",
    "wof:placetype":"venue"
},
  "geometry": {"coordinates":[-117.301247,34.102645],"type":"Point"}
}