{
  "type": "Feature",
  "properties": {
    "iso:country":"US",
    "sg:address":"529 W Philadelphia St",
    "sg:city":"Ontario",
    "sg:classifiers":[
        {
            "category":"Building & Trades",
            "subcategory":"Landscaping Services",
            "type":"Services"
        },
        {
            "category":"Farming",
            "subcategory":"Nursery",
            "type":"Manufacturing & Wholesale Goods"
        },
        {
            "category":"Shopping",
            "subcategory":"Crafts & Fabrics",
            "type":"Retail Goods"
        },
        {
            "category":"Manufacturing",
            "subcategory":"Paper Products",
            "type":"Manufacturing & Wholesale Goods"
        }
    ],
    "sg:phone":"+1 909 986 0013",
    "sg:postcode":"91762",
    "sg:province":"CA",
    "sg:tags":[
        "lawn",
        "florists'",
        "supply",
        "equipment",
        "florist",
        "bamboo",
        "supplies-wholesale",
        "growers'",
        "manufacturer"
    ],
    "wof:name":"Staffel's Nursery",
    "wof:placetype":"venue"
},
  "geometry": {"coordinates":[-117.65800400000001,34.033778],"type":"Point"}
}