{
  "type": "Feature",
  "properties": {
    "iso:country":"US",
    "sg:address":"4690 Dapple Ln",
    "sg:city":"Riverside",
    "sg:classifiers":[
        {
            "category":"Building & Trades",
            "subcategory":"Construction",
            "type":"Services"
        }
    ],
    "sg:phone":"+1 951 681 8738",
    "sg:postcode":"92509",
    "sg:province":"CA",
    "sg:tags":[
        "floor",
        "laying",
        "contractor"
    ],
    "wof:name":"Afi Flooring Inc",
    "wof:placetype":"venue"
},
  "geometry": {"coordinates":[-117.476163,34.004483],"type":"Point"}
}