{
  "type": "Feature",
  "properties": {
    "iso:country":"US",
    "sg:address":"754 Wall St",
    "sg:city":"Los Angeles",
    "sg:classifiers":[
        {
            "category":"Wholesale",
            "subcategory":"Plants",
            "type":"Manufacturing & Wholesale Goods"
        }
    ],
    "sg:phone":"+1 213 623 5922",
    "sg:postcode":"90014",
    "sg:province":"CA",
    "sg:tags":[
        "florist",
        "supply"
    ],
    "wof:name":"Kim Bros Flower Wholesale",
    "wof:placetype":"venue"
},
  "geometry": {"coordinates":[-118.25,34.040901],"type":"Point"}
}