{
  "type": "Feature",
  "properties": {
    "addr:full":"2000 Powell Street Suite 1290 Emeryville CA 94608",
    "addr:housenumber":"2000",
    "addr:postcode":"94608",
    "addr:street":"Powell Street Suite 1290",
    "iso:country":"US",
    "sg:address":"2000 Powell Street Suite 1290",
    "sg:city":"Emeryville",
    "sg:classifiers":[
        {
            "category":"Professional",
            "subcategory":"Accounting & Tax Preparation",
            "type":"Services"
        }
    ],
    "sg:phone":"+1 510 652 4900",
    "sg:postcode":"94608",
    "sg:province":"CA",
    "sg:tags":[
        "accountant"
    ],
    "sg:website":"www.RSandCO.com",
    "wof:name":"Malcolm J Roberts, CPA",
    "wof:placetype":"venue"
},
  "geometry": {"coordinates":[-122.300856,37.838132],"type":"Point"}
}