{
  "type": "Feature",
  "properties": {
    "iso:country":"US",
    "sg:address":"823 Grant Ave",
    "sg:city":"Novato",
    "sg:classifiers":[
        {
            "category":"Real Estate",
            "subcategory":"Real Estate Agent",
            "type":"Services"
        }
    ],
    "sg:phone":"+1 415 892 7789",
    "sg:postcode":"94945",
    "sg:province":"CA",
    "sg:tags":[
        "appraiser"
    ],
    "wof:name":"Mark Byers Real Estate Apprsr",
    "wof:placetype":"venue"
},
  "geometry": {"coordinates":[-122.5669,38.106923],"type":"Point"}
}