{
  "type": "Feature",
  "properties": {
    "iso:country":"US",
    "sg:address":"178 Edgewater Dr",
    "sg:city":"Rio Vista",
    "sg:phone":"+1 707 374 2038",
    "sg:postcode":"94571",
    "sg:province":"CA",
    "sg:tags":[
        "farm",
        "wheat"
    ],
    "wof:name":"Esperson Farms",
    "wof:placetype":"venue"
},
  "geometry": {"coordinates":[-121.69158,38.151377],"type":"Point"}
}