{
  "type": "Feature",
  "properties": {
    "iso:country":"US",
    "sg:address":"9801 Blue Lake Dr",
    "sg:city":"Folsom",
    "sg:classifiers":[
        {
            "category":"Manufacturing",
            "subcategory":"Toys & Sporting Goods",
            "type":"Manufacturing & Wholesale Goods"
        }
    ],
    "sg:phone":"+1 916 987 2913",
    "sg:postcode":"95630",
    "sg:province":"CA",
    "sg:tags":[
        "mfg"
    ],
    "wof:name":"Virtual Voyage Inc",
    "wof:placetype":"venue"
},
  "geometry": {"coordinates":[-121.180338,38.697579],"type":"Point"}
}