{
  "type": "Feature",
  "properties": {
    "iso:country":"US",
    "sg:address":"590 Pleasant Ave",
    "sg:city":"Windsor",
    "sg:classifiers":[
        {
            "category":"Farming",
            "subcategory":"Vineyard",
            "type":"Manufacturing & Wholesale Goods"
        }
    ],
    "sg:phone":"+1 707 837 9200",
    "sg:postcode":"95403",
    "sg:province":"CA",
    "wof:name":"Shiloh Vineyard",
    "wof:placetype":"venue"
},
  "geometry": {"coordinates":[-122.77673299999999,38.540226],"type":"Point"}
}