{
  "type": "Feature",
  "properties": {
    "iso:country":"US",
    "sg:address":"2700 American River Dr",
    "sg:city":"Sacramento",
    "sg:classifiers":[
        {
            "category":"Professional",
            "subcategory":"Accounting & Tax Preparation",
            "type":"Services"
        }
    ],
    "sg:phone":"+1 916 484 1001",
    "sg:postcode":"95864",
    "sg:province":"CA",
    "sg:tags":[
        "return",
        "filing"
    ],
    "wof:name":"Ray Jacobson",
    "wof:placetype":"venue"
},
  "geometry": {"coordinates":[-121.399254,38.567518],"type":"Point"}
}