{
  "type": "Feature",
  "properties": {
    "addr:full":"28562 Oso Pkwy Las Flores CA 92688",
    "addr:postcode":"28562;92688",
    "addr:street":"Oso Pkwy",
    "iso:country":"US",
    "sg:address":"28562 Oso Pkwy",
    "sg:city":"Las Flores",
    "sg:classifiers":[
        {
            "category":"Restaurant",
            "type":"Food & Drink"
        }
    ],
    "sg:phone":"+1 949 216 9029",
    "sg:postcode":"92688",
    "sg:province":"CA",
    "sg:tags":[
        "pizza",
        "italian"
    ],
    "sg:website":"www.cosmositaliankitchen.com",
    "wof:name":"Cosmo's Italian Kitchen",
    "wof:placetype":"venue"
},
  "geometry": {"coordinates":[-117.632015,33.583631],"type":"Point"}
}