{
  "type": "Feature",
  "properties": {
    "addr:full":"26690 Madison Ave Murrieta CA 92562",
    "addr:housenumber":"26690",
    "addr:postcode":"92562",
    "addr:street":"Madison Ave",
    "iso:country":"US",
    "sg:address":"26690 Madison Ave",
    "sg:city":"Murrieta",
    "sg:classifiers":[
        {
            "category":"Manufacturing",
            "subcategory":"Printing",
            "type":"Manufacturing & Wholesale Goods"
        }
    ],
    "sg:phone":"+1 951 461 2606",
    "sg:postcode":"92562",
    "sg:province":"CA",
    "sg:tags":[
        "printer"
    ],
    "wof:name":"Commercial Copy",
    "wof:placetype":"venue"
},
  "geometry": {"coordinates":[-117.174223,33.533202],"type":"Point"}
}