{
  "type": "Feature",
  "properties": {
    "iso:country":"US",
    "sg:address":"2815 San Mateo St",
    "sg:city":"Richmond",
    "sg:classifiers":[
        {
            "category":"Retail",
            "subcategory":"Laundry & Dry Cleaning",
            "type":"Services"
        }
    ],
    "sg:phone":"+1 510 593 3983",
    "sg:postcode":"94804",
    "sg:province":"CA",
    "sg:tags":[
        "cleaners",
        "rug",
        "carpet"
    ],
    "wof:name":"Alex's Chemdry",
    "wof:placetype":"venue"
},
  "geometry": {"coordinates":[-122.309791,37.902647],"type":"Point"}
}