{
  "type": "Feature",
  "properties": {
    "iso:country":"US",
    "sg:address":"424 N 7th St",
    "sg:city":"Sacramento",
    "sg:classifiers":[
        {
            "category":"Freight",
            "type":"Transportation"
        }
    ],
    "sg:phone":"+1 916 447 4504",
    "sg:postcode":"95811",
    "sg:province":"CA",
    "sg:tags":[
        "warehouse",
        "storage"
    ],
    "wof:name":"Cs65 Cold Storage",
    "wof:placetype":"venue"
},
  "geometry": {"coordinates":[-121.48957799999999,38.599553],"type":"Point"}
}