{
  "type": "Feature",
  "properties": {
    "iso:country":"US",
    "sg:address":"1421 State St",
    "sg:city":"Santa Barbara",
    "sg:classifiers":[
        {
            "category":"Communications",
            "type":"Services"
        }
    ],
    "sg:phone":"+1 805 882 1268",
    "sg:postcode":"93101",
    "sg:province":"CA",
    "sg:tags":[
        "infrastructure",
        "network"
    ],
    "wof:name":"Global App",
    "wof:placetype":"venue"
},
  "geometry": {"coordinates":[-119.70811999999999,34.425908],"type":"Point"}
}