{
  "type": "Feature",
  "properties": {
    "iso:country":"US",
    "sg:address":"624 Carlson Blvd",
    "sg:city":"Richmond",
    "sg:classifiers":[
        {
            "category":"Bus Station",
            "type":"Transportation"
        }
    ],
    "sg:phone":"+1 510 233 8437",
    "sg:postcode":"94804",
    "sg:province":"CA",
    "sg:tags":[
        "maintenance"
    ],
    "wof:name":"Organizational Maint Shop 39",
    "wof:placetype":"venue"
},
  "geometry": {"coordinates":[-122.33636799999999,37.924287],"type":"Point"}
}