{
  "type": "Feature",
  "properties": {
    "iso:country":"US",
    "sg:address":"926 S Purdue Ave",
    "sg:city":"Fresno",
    "sg:classifiers":[
        {
            "category":"Building & Trades",
            "subcategory":"Construction",
            "type":"Services"
        }
    ],
    "sg:phone":"+1 559 456 1809",
    "sg:postcode":"93727",
    "sg:province":"CA",
    "sg:tags":[
        "wallcoverings-installation",
        "wallpaper",
        "painting",
        "contractor"
    ],
    "wof:name":"Mann Painting George",
    "wof:placetype":"venue"
},
  "geometry": {"coordinates":[-119.687825,36.733908],"type":"Point"}
}