{
  "type": "Feature",
  "properties": {
    "iso:country":"US",
    "sg:address":"233 S School St",
    "sg:city":"Lodi",
    "sg:classifiers":[
        {
            "category":"Restaurant",
            "type":"Food & Drink"
        }
    ],
    "sg:phone":"+1 209 367 1668",
    "sg:postcode":"95240",
    "sg:province":"CA",
    "wof:name":"Scramblz",
    "wof:placetype":"venue"
},
  "geometry": {"coordinates":[-121.273887,38.131289],"type":"Point"}
}