{
  "type": "Feature",
  "properties": {
    "addr:full":"6938 E Clinton Ave Fresno CA 93727",
    "addr:housenumber":"6938",
    "addr:postcode":"93727",
    "addr:street":"E Clinton Ave",
    "iso:country":"US",
    "sg:address":"6938 E Clinton Ave",
    "sg:city":"Fresno",
    "sg:classifiers":[
        {
            "category":"Shopping",
            "subcategory":"Gifts & Souvenirs",
            "type":"Retail Goods"
        }
    ],
    "sg:phone":"+1 559 292 6464",
    "sg:postcode":"93727",
    "sg:province":"CA",
    "wof:name":"Gifts By Smitty",
    "wof:placetype":"venue"
},
  "geometry": {"coordinates":[-119.66653700000001,36.772203],"type":"Point"}
}