{
  "type": "Feature",
  "properties": {
    "iso:country":"US",
    "sg:address":"2707 Palma Dr",
    "sg:city":"Ventura",
    "sg:classifiers":[
        {
            "category":"Manufacturing",
            "subcategory":"Metals",
            "type":"Manufacturing & Wholesale Goods"
        }
    ],
    "sg:phone":"+1 805 642 6262",
    "sg:postcode":"93003",
    "sg:province":"CA",
    "sg:tags":[
        "coating"
    ],
    "sg:website":"www.magnaplateca.com",
    "wof:name":"General Magnaplate Corp",
    "wof:placetype":"venue"
},
  "geometry": {"coordinates":[-119.22696000000001,34.245059],"type":"Point"}
}