{
  "type": "Feature",
  "properties": {
    "addr:full":"303 N Church St Visalia CA 93291",
    "addr:housenumber":"303",
    "addr:postcode":"93291",
    "addr:street":"N Church St",
    "iso:country":"US",
    "sg:address":"303 N Church St",
    "sg:city":"Visalia",
    "sg:classifiers":[
        {
            "category":"Real Estate",
            "subcategory":"Architect",
            "type":"Services"
        }
    ],
    "sg:phone":"+1 559 733 7833",
    "sg:postcode":"93291",
    "sg:province":"CA",
    "wof:name":"David L Smith",
    "wof:placetype":"venue"
},
  "geometry": {"coordinates":[-119.29128,36.332404],"type":"Point"}
}