{
  "type": "Feature",
  "properties": {
    "iso:country":"US",
    "sg:address":"11087 Tuxford St",
    "sg:city":"Sun Valley",
    "sg:classifiers":[
        {
            "category":"Wholesale",
            "subcategory":"Auto Parts",
            "type":"Manufacturing & Wholesale Goods"
        }
    ],
    "sg:phone":"+1 818 767 0300",
    "sg:postcode":"91352",
    "sg:province":"CA",
    "sg:tags":[
        "body",
        "automobile",
        "shop"
    ],
    "wof:name":"Master Auto Parts & Supply",
    "wof:placetype":"venue"
},
  "geometry": {"coordinates":[-118.37189600000001,34.234368],"type":"Point"}
}