{
  "type": "Feature",
  "properties": {
    "iso:country":"US",
    "sg:address":"7035 Laurel Canyon Blvd Ste 16812",
    "sg:city":"North Hollywood",
    "sg:classifiers":[
        {
            "category":"Shopping",
            "subcategory":"Computers & Home Electronics",
            "type":"Retail Goods"
        }
    ],
    "sg:phone":"+1 818 257 3732",
    "sg:postcode":"91615",
    "sg:province":"CA",
    "sg:tags":[
        "installation",
        "theatre"
    ],
    "sg:website":"www.standingovationsurroundsound...",
    "wof:name":"Standing Ovation Surround Sound Services",
    "wof:placetype":"venue"
},
  "geometry": {"coordinates":[-118.39662199999999,34.19914],"type":"Point"}
}