{
  "type": "Feature",
  "properties": {
    "iso:country":"US",
    "sg:address":"5150 Sunrise Blvd",
    "sg:city":"Fair Oaks",
    "sg:classifiers":[
        {
            "category":"Professional",
            "subcategory":"Lawyer & Legal Services",
            "type":"Services"
        }
    ],
    "sg:phone":"+1 916 967 8000",
    "sg:postcode":"95628",
    "sg:province":"CA",
    "sg:tags":[
        "attorney"
    ],
    "wof:name":"P Stassinos Attorneys At Law",
    "wof:placetype":"venue"
},
  "geometry": {"coordinates":[-121.27234799999999,38.657567],"type":"Point"}
}