{
  "type": "Feature",
  "properties": {
    "addr:full":"193 S Main St Orange CA 92868",
    "addr:housenumber":"193",
    "addr:postcode":"92868",
    "addr:street":"S Main St",
    "iso:country":"US",
    "sg:address":"193 S Main St",
    "sg:city":"Orange",
    "sg:classifiers":[
        {
            "category":"Retail",
            "subcategory":"Auto Repair",
            "type":"Services"
        },
        {
            "category":"Government",
            "subcategory":"Office",
            "type":"Public Place"
        }
    ],
    "sg:phone":"+1 714 633 1876",
    "sg:postcode":"92868",
    "sg:province":"CA",
    "sg:tags":[
        "smog",
        "check"
    ],
    "wof:name":"The Tune Up Center",
    "wof:placetype":"venue"
},
  "geometry": {"coordinates":[-117.866997,33.7864],"type":"Point"}
}