{
  "type": "Feature",
  "properties": {
    "iso:country":"US",
    "sg:address":"9386 Cedarview Way",
    "sg:city":"Elk Grove",
    "sg:classifiers":[
        {
            "category":"Health Services",
            "subcategory":"Nursing And Care Facility",
            "type":"Services"
        }
    ],
    "sg:phone":"+1 916 743 9822",
    "sg:postcode":"95758",
    "sg:province":"CA",
    "sg:tags":[
        "home",
        "rest"
    ],
    "wof:name":"Golden Senior Care",
    "wof:placetype":"venue"
},
  "geometry": {"coordinates":[-121.46559499999999,38.41632],"type":"Point"}
}