{
  "type": "Feature",
  "properties": {
    "iso:country":"US",
    "sg:address":"17812 Sierra Hwy Ste A",
    "sg:city":"Canyon Country",
    "sg:classifiers":[
        {
            "category":"Building & Trades",
            "subcategory":"Pest Control",
            "type":"Services"
        }
    ],
    "sg:phone":"+1 818 771 0396",
    "sg:postcode":"91351",
    "sg:province":"CA",
    "wof:name":"All Pro Pest Control Inc",
    "wof:placetype":"venue"
},
  "geometry": {"coordinates":[-118.44708300000001,34.42678],"type":"Point"}
}