{
  "type": "Feature",
  "properties": {
    "addr:full":"6545 Seine Ct Highland CA 92346",
    "addr:housenumber":"6545",
    "addr:postcode":"92346",
    "addr:street":"Seine Ct",
    "iso:country":"US",
    "sg:address":"6545 Seine Ct",
    "sg:city":"Highland",
    "sg:classifiers":[
        {
            "category":"Building & Trades",
            "subcategory":"Cleaning & Sanitation",
            "type":"Services"
        }
    ],
    "sg:phone":"+1 909 425 5285",
    "sg:postcode":"92346",
    "sg:province":"CA",
    "sg:tags":[
        "polishing",
        "waxing",
        "floor"
    ],
    "wof:name":"Squaresone Commercial Cleaning",
    "wof:placetype":"venue"
},
  "geometry": {"coordinates":[-117.198255,34.134868],"type":"Point"}
}