{
  "type": "Feature",
  "properties": {
    "iso:country":"US",
    "sg:address":"8455 Beverly Blvd. Suite 309",
    "sg:city":"West Hollywood",
    "sg:classifiers":[
        {
            "category":"Professional",
            "subcategory":"Advertising",
            "type":"Services"
        }
    ],
    "sg:phone":"+1 323 370 1081",
    "sg:postcode":"90048",
    "sg:province":"CA",
    "sg:tags":[
        "digital",
        "digital-advertising",
        "digital-advertising-agency",
        "web-development",
        "online-strategy",
        "digital-strategy",
        "online-ad-campaigns",
        "banner-ads",
        "digital-marketing",
        "websites",
        "viral",
        "viral-campaign",
        "widget",
        "facebook-applications",
        "facebook-apps",
        "design",
        "develo"
    ],
    "sg:website":"http://www.neoganda.com",
    "wof:name":"Neoganda",
    "wof:placetype":"venue"
},
  "geometry": {"coordinates":[-118.374572,34.076122],"type":"Point"}
}