{
  "type": "Feature",
  "properties": {
    "addr:full":"633 W 5th St Los Angeles CA 90071",
    "addr:housenumber":"633",
    "addr:postcode":"90071",
    "addr:street":"W 5Th St",
    "iso:country":"US",
    "sg:address":"633 W 5th St",
    "sg:city":"Los Angeles",
    "sg:classifiers":[
        {
            "category":"Banks & Credit Unions",
            "subcategory":"Investment Brokerage",
            "type":"Services"
        }
    ],
    "sg:phone":"+1 323 656 3200",
    "sg:postcode":"90071",
    "sg:province":"CA",
    "sg:tags":[
        "management"
    ],
    "wof:name":"USA Asset Management",
    "wof:placetype":"venue"
},
  "geometry": {"coordinates":[-118.25461300000001,34.050669],"type":"Point"}
}