{
  "type": "Feature",
  "properties": {
    "iso:country":"US",
    "sg:address":"3930 Sierra College Blvd",
    "sg:city":"Loomis",
    "sg:classifiers":[
        {
            "category":"Building & Trades",
            "subcategory":"Construction",
            "type":"Services"
        }
    ],
    "sg:phone":"+1 916 660 0240",
    "sg:postcode":"95650",
    "sg:province":"CA",
    "sg:tags":[
        "roofing",
        "contractor"
    ],
    "sg:website":"www.kodiakroofing.com",
    "wof:name":"Kodiak Roofing & Waterproofing",
    "wof:placetype":"venue"
},
  "geometry": {"coordinates":[-121.207358,38.813574],"type":"Point"}
}