{
  "type": "Feature",
  "properties": {
    "addr:full":"958 N Main St Orange CA 92867",
    "addr:housenumber":"958",
    "addr:postcode":"92867",
    "addr:street":"N Main St",
    "iso:country":"US",
    "sg:address":"958 N Main St",
    "sg:city":"Orange",
    "sg:classifiers":[
        {
            "category":"Building & Trades",
            "subcategory":"Construction",
            "type":"Services"
        }
    ],
    "sg:phone":"+1 714 744 6911",
    "sg:postcode":"92867",
    "sg:province":"CA",
    "sg:tags":[
        "contractor"
    ],
    "wof:name":"Jemstar Builders",
    "wof:placetype":"venue"
},
  "geometry": {"coordinates":[-117.86704,33.804988],"type":"Point"}
}