{
  "type": "Feature",
  "properties": {
    "addr:full":"1775 Hancock St San Diego CA 92110",
    "addr:housenumber":"1775",
    "addr:postcode":"92110",
    "addr:street":"Hancock St",
    "iso:country":"US",
    "sg:address":"1775 Hancock St",
    "sg:city":"San Diego",
    "sg:classifiers":[
        {
            "category":"Real Estate",
            "subcategory":"Architect",
            "type":"Services"
        }
    ],
    "sg:phone":"+1 619 542 1188",
    "sg:postcode":"92110",
    "sg:province":"CA",
    "wof:name":"White Frisco Aia",
    "wof:placetype":"venue"
},
  "geometry": {"coordinates":[-117.192001,32.746201],"type":"Point"}
}