{
  "type": "Feature",
  "properties": {
    "addr:full":"403 Commercial St Nevada City CA 95959",
    "addr:housenumber":"403",
    "addr:postcode":"95959",
    "addr:street":"Commercial St",
    "iso:country":"US",
    "sg:address":"403 Commercial St",
    "sg:city":"Nevada City",
    "sg:classifiers":[
        {
            "category":"Health Services",
            "subcategory":"Health Practitioner",
            "type":"Services"
        }
    ],
    "sg:phone":"+1 530 265 4113",
    "sg:postcode":"95959",
    "sg:province":"CA",
    "sg:tags":[
        "psychotherapist"
    ],
    "wof:name":"Turning Points Counseling Ctr",
    "wof:placetype":"venue"
},
  "geometry": {"coordinates":[-121.01939400000001,39.263335],"type":"Point"}
}