{
  "type": "Feature",
  "properties": {
    "iso:country":"US",
    "sg:address":"19337 Ventura Blvd",
    "sg:city":"Tarzana",
    "sg:classifiers":[
        {
            "category":"Restaurant",
            "type":"Food & Drink"
        }
    ],
    "sg:phone":"+1 818 654 9918",
    "sg:postcode":"91356",
    "sg:province":"CA",
    "sg:tags":[
        "style",
        "family"
    ],
    "wof:name":"Darband Restaurant",
    "wof:placetype":"venue"
},
  "geometry": {"coordinates":[-118.55462199999999,34.172692],"type":"Point"}
}