{
  "type": "Feature",
  "properties": {
    "addr:full":"1776 C Ave Kingsburg CA 93631",
    "addr:housenumber":"1776",
    "addr:postcode":"93631",
    "addr:street":"C Ave",
    "iso:country":"US",
    "sg:address":"1776 C Ave",
    "sg:city":"Kingsburg",
    "sg:classifiers":[
        {
            "category":"Retail",
            "subcategory":"Portrait Studio",
            "type":"Services"
        }
    ],
    "sg:phone":"+1 559 897 8582",
    "sg:postcode":"93631",
    "sg:province":"CA",
    "sg:tags":[
        "photographer"
    ],
    "wof:name":"Photography By Stephanie",
    "wof:placetype":"venue"
},
  "geometry": {"coordinates":[-119.57096199999999,36.516687],"type":"Point"}
}