{
  "type": "Feature",
  "properties": {
    "addr:full":"601 W 5th St Los Angeles CA 90071",
    "addr:housenumber":"601",
    "addr:postcode":"90071",
    "addr:street":"W 5Th St",
    "iso:country":"US",
    "sg:address":"601 W 5th St",
    "sg:city":"Los Angeles",
    "sg:classifiers":[
        {
            "category":"Professional",
            "subcategory":"Employment Agencies",
            "type":"Services"
        }
    ],
    "sg:phone":"+1 213 486 0010",
    "sg:postcode":"90071",
    "sg:province":"CA",
    "wof:name":"Legal Source",
    "wof:placetype":"venue"
},
  "geometry": {"coordinates":[-118.25377899999999,34.033481],"type":"Point"}
}