{
  "type": "Feature",
  "properties": {
    "iso:country":"US",
    "sg:address":"14550 Big Basin Way",
    "sg:city":"Saratoga",
    "sg:classifiers":[
        {
            "category":"Food & Beverages",
            "subcategory":"Specialty",
            "type":"Retail Goods"
        },
        {
            "category":"Restaurant",
            "type":"Food & Drink"
        }
    ],
    "sg:phone":"+1 408 867 3332",
    "sg:postcode":"95070",
    "sg:province":"CA",
    "sg:tags":[
        "fondue",
        "french"
    ],
    "sg:website":"www.lafondue.com",
    "wof:name":"La Fondue",
    "wof:placetype":"venue"
},
  "geometry": {"coordinates":[-122.034741,37.256677],"type":"Point"}
}