{
  "type": "Feature",
  "properties": {
    "addr:full":"7179 Westminster Boulevard Westminster CA 92683",
    "addr:housenumber":"7179",
    "addr:postcode":"92683",
    "addr:street":"Westminster Boulevard",
    "iso:country":"US",
    "sg:address":"7179 Westminster Boulevard",
    "sg:city":"Westminster",
    "sg:classifiers":[
        {
            "category":"Government",
            "subcategory":"Office",
            "type":"Public Place"
        }
    ],
    "sg:phone":"+1 714 799 1409",
    "sg:postcode":"92683",
    "sg:province":"CA",
    "sg:tags":[
        "smog",
        "check"
    ],
    "wof:name":"Westminster Only Smog",
    "wof:placetype":"venue"
},
  "geometry": {"coordinates":[-118.003339,33.759246],"type":"Point"}
}