{
  "type": "Feature",
  "properties": {
    "iso:country":"US",
    "sg:address":"6589 N Lake Blvd",
    "sg:city":"Tahoe Vista",
    "sg:classifiers":[
        {
            "category":"Travel",
            "subcategory":"Hotels & Motels",
            "type":"Entertainment"
        }
    ],
    "sg:phone":"+1 530 546 4281",
    "sg:postcode":"96148",
    "sg:province":"CA",
    "sg:website":"www.tahoecedarglen.com/",
    "wof:name":"Cedar Glen Lodge",
    "wof:placetype":"venue"
},
  "geometry": {"coordinates":[-120.057999,39.247101],"type":"Point"}
}