{
  "type": "Feature",
  "properties": {
    "addr:full":"989 Keith Way Roseville CA 95661",
    "addr:housenumber":"989",
    "addr:postcode":"95661",
    "addr:street":"Keith Way",
    "iso:country":"US",
    "sg:address":"989 Keith Way",
    "sg:city":"Roseville",
    "sg:classifiers":[
        {
            "category":"Freight",
            "type":"Transportation"
        }
    ],
    "sg:phone":"+1 916 774 9513",
    "sg:postcode":"95661",
    "sg:province":"CA",
    "wof:name":"Linda Dickinson Consulting",
    "wof:placetype":"venue"
},
  "geometry": {"coordinates":[-121.277558,38.722494],"type":"Point"}
}