{
  "type": "Feature",
  "properties": {
    "iso:country":"US",
    "sg:address":"34911 Yucaipa Blvd",
    "sg:city":"Yucaipa",
    "sg:classifiers":[
        {
            "category":"Autos & Motor Vehicles",
            "subcategory":"Auto Supplies",
            "type":"Retail Goods"
        }
    ],
    "sg:phone":"+1 909 790 8600",
    "sg:postcode":"92399",
    "sg:province":"CA",
    "sg:tags":[
        "automobile",
        "parts"
    ],
    "wof:name":"Nationwide Motorsports",
    "wof:placetype":"venue"
},
  "geometry": {"coordinates":[-117.041171,34.0338],"type":"Point"}
}