{
  "type": "Feature",
  "properties": {
    "addr:full":"4309 Hacienda Dr Pleasanton CA 94588",
    "addr:housenumber":"4309",
    "addr:postcode":"94588",
    "addr:street":"Hacienda Dr",
    "iso:country":"US",
    "sg:address":"4309 Hacienda Dr",
    "sg:city":"Pleasanton",
    "sg:classifiers":[
        {
            "category":"Organizations",
            "subcategory":"Non-profit Organization",
            "type":"Services"
        }
    ],
    "sg:phone":"+1 925 474 1300",
    "sg:postcode":"94588",
    "sg:province":"CA",
    "wof:name":"Associated Builders & Contr",
    "wof:placetype":"venue"
},
  "geometry": {"coordinates":[-121.894183,37.695078],"type":"Point"}
}