{
  "type": "Feature",
  "properties": {
    "iso:country":"US",
    "sg:address":"1960 P St",
    "sg:city":"Merced",
    "sg:classifiers":[
        {
            "category":"Health Services",
            "subcategory":"Doctor",
            "type":"Services"
        }
    ],
    "sg:phone":"+1 209 723 7751",
    "sg:postcode":"95340",
    "sg:province":"CA",
    "sg:tags":[
        "clinic"
    ],
    "wof:name":"Planned Parenthood",
    "wof:placetype":"venue"
},
  "geometry": {"coordinates":[-120.487886,37.305998],"type":"Point"}
}