{
  "type": "Feature",
  "properties": {
    "addr:full":"22 E Market St Stockton CA 95205",
    "addr:housenumber":"22",
    "addr:postcode":"95205",
    "addr:street":"E Market St",
    "iso:country":"US",
    "sg:address":"22 E Market St",
    "sg:city":"Stockton",
    "sg:classifiers":[
        {
            "category":"Government",
            "subcategory":"Police Station",
            "type":"Public Place"
        }
    ],
    "sg:phone":"+1 209 937 8208",
    "sg:postcode":"95205",
    "sg:province":"CA",
    "sg:tags":[
        "department"
    ],
    "wof:name":"Police-Field Service Div",
    "wof:placetype":"venue"
},
  "geometry": {"coordinates":[-121.289716,37.951599],"type":"Point"}
}