{
  "type": "Feature",
  "properties": {
    "iso:country":"US",
    "sg:address":"3598 E Imperial Hwy",
    "sg:city":"Lynwood",
    "sg:classifiers":[
        {
            "category":"Food & Beverages",
            "subcategory":"Groceries & Convenience Stores",
            "type":"Retail Goods"
        }
    ],
    "sg:phone":"+1 310 884 5936",
    "sg:postcode":"90262",
    "sg:province":"CA",
    "wof:name":"Goyo's Market",
    "wof:placetype":"venue"
},
  "geometry": {"coordinates":[-118.197328,33.923948],"type":"Point"}
}