{
  "type": "Feature",
  "properties": {
    "iso:country":"US",
    "sg:address":"3424 I St",
    "sg:city":"North Highlands",
    "sg:classifiers":[
        {
            "category":"Organizations",
            "subcategory":"Religious Organization",
            "type":"Services"
        }
    ],
    "sg:phone":"+1 916 339 9191",
    "sg:postcode":"95660",
    "sg:province":"CA",
    "sg:tags":[
        "church"
    ],
    "wof:name":"Korean Bethel Chr Of The Nazar",
    "wof:placetype":"venue"
},
  "geometry": {"coordinates":[-121.383306,38.682992],"type":"Point"}
}