{
  "type": "Feature",
  "properties": {
    "iso:country":"US",
    "sg:address":"1150 Foothill Blvd",
    "sg:city":"La Canada Fltrdg",
    "sg:classifiers":[
        {
            "category":"Professional",
            "type":"Services"
        }
    ],
    "sg:phone":"+1 818 790 3707",
    "sg:postcode":"91011",
    "sg:province":"CA",
    "sg:tags":[
        "establishment"
    ],
    "wof:name":"Foothill Executive Plaza",
    "wof:placetype":"venue"
},
  "geometry": {"coordinates":[-118.204382,34.206375],"type":"Point"}
}