{
  "type": "Feature",
  "properties": {
    "addr:full":"20725 Sherman Way Winnetka CA 91306",
    "addr:housenumber":"20725",
    "addr:postcode":"91306",
    "addr:street":"Sherman Way",
    "iso:country":"US",
    "sg:address":"20725 Sherman Way",
    "sg:city":"Winnetka",
    "sg:classifiers":[
        {
            "category":"Government",
            "subcategory":"Office",
            "type":"Public Place"
        }
    ],
    "sg:phone":"+1 818 346 4690",
    "sg:postcode":"91306",
    "sg:province":"CA",
    "sg:tags":[
        "general"
    ],
    "wof:name":"Department of Motor Vehicles",
    "wof:placetype":"venue"
},
  "geometry": {"coordinates":[-118.585835,34.201017],"type":"Point"}
}