{
  "type": "Feature",
  "properties": {
    "addr:full":"1130 John St Salinas CA 93905",
    "addr:housenumber":"1130",
    "addr:postcode":"93905",
    "addr:street":"John St",
    "iso:country":"US",
    "sg:address":"1130 John St",
    "sg:city":"Salinas",
    "sg:classifiers":[
        {
            "category":"Education",
            "subcategory":"School",
            "type":"Public Place"
        }
    ],
    "sg:phone":"+1 831 753 5630",
    "sg:postcode":"93905",
    "sg:province":"CA",
    "wof:name":"Los Padres Elementary School",
    "wof:placetype":"venue"
},
  "geometry": {"coordinates":[-121.62282399999999,36.670805],"type":"Point"}
}