{
  "type": "Feature",
  "properties": {
    "addr:full":"1016 Laguna St San Francisco CA 94115",
    "addr:housenumber":"1016",
    "addr:postcode":"94115",
    "addr:street":"Laguna St",
    "iso:country":"US",
    "sg:address":"1016 Laguna St",
    "sg:city":"San Francisco",
    "sg:classifiers":[
        {
            "category":"Recreation",
            "subcategory":"Playground",
            "type":"Entertainment"
        }
    ],
    "sg:postcode":"94115",
    "sg:province":"CA",
    "wof:name":"Hayward Playground",
    "wof:placetype":"venue"
},
  "geometry": {"coordinates":[-122.427072,37.78037],"type":"Point"}
}