{
  "type": "Feature",
  "properties": {
    "iso:country":"US",
    "sg:address":"2229 Hampton Rd",
    "sg:city":"Livermore",
    "sg:classifiers":[
        {
            "category":"Building & Trades",
            "subcategory":"Plumbing",
            "type":"Services"
        }
    ],
    "sg:phone":"+1 925 455 5621",
    "sg:postcode":"94550",
    "sg:province":"CA",
    "sg:tags":[
        "contractor"
    ],
    "wof:name":"Plumbing Works",
    "wof:placetype":"venue"
},
  "geometry": {"coordinates":[-121.780415,37.655824],"type":"Point"}
}