{
  "type": "Feature",
  "properties": {
    "addr:full":"1820 Hunter Way Bishop CA 93514",
    "addr:housenumber":"1820",
    "addr:postcode":"93514",
    "addr:street":"Hunter Way",
    "iso:country":"US",
    "sg:address":"1820 Hunter Way",
    "sg:city":"Bishop",
    "sg:classifiers":[
        {
            "category":"Freight",
            "type":"Transportation"
        }
    ],
    "sg:phone":"+1 760 872 7055",
    "sg:postcode":"93514",
    "sg:province":"CA",
    "sg:tags":[
        "operator",
        "local",
        "trucking"
    ],
    "wof:name":"Bishop Delivery Service",
    "wof:placetype":"venue"
},
  "geometry": {"coordinates":[-118.41965999999999,37.388486],"type":"Point"}
}