{
  "type": "Feature",
  "properties": {
    "iso:country":"US",
    "sg:address":"1707 Little Orchard St",
    "sg:city":"San Jose",
    "sg:classifiers":[
        {
            "category":"Manufacturing",
            "subcategory":"Tools & Machinery",
            "type":"Manufacturing & Wholesale Goods"
        }
    ],
    "sg:phone":"+1 408 995 6445",
    "sg:postcode":"95125",
    "sg:province":"CA",
    "sg:tags":[
        "machine",
        "shop",
        "industrial",
        "mfg"
    ],
    "wof:name":"South Valley Engnring & Mfg Co",
    "wof:placetype":"venue"
},
  "geometry": {"coordinates":[-121.871441,37.304865],"type":"Point"}
}