{
  "type": "Feature",
  "properties": {
    "addr:full":"12980 Paraiso Rd Apple Valley CA 92308",
    "addr:housenumber":"12980",
    "addr:postcode":"92308",
    "addr:street":"Paraiso Rd",
    "iso:country":"US",
    "sg:address":"12980 Paraiso Rd",
    "sg:city":"Apple Valley",
    "sg:classifiers":[
        {
            "category":"Shopping",
            "subcategory":"Clothing, Apparel, & Fashions",
            "type":"Retail Goods"
        }
    ],
    "sg:phone":"+1 760 961 8014",
    "sg:postcode":"92308",
    "sg:province":"CA",
    "wof:name":"Delcine Collections",
    "wof:placetype":"venue"
},
  "geometry": {"coordinates":[-117.23653899999999,34.487858],"type":"Point"}
}