{
  "type": "Feature",
  "properties": {
    "iso:country":"US",
    "sg:address":"5538 Del Amo Blvd",
    "sg:city":"Lakewood",
    "sg:classifiers":[
        {
            "category":"Restaurant",
            "type":"Food & Drink"
        }
    ],
    "sg:phone":"+1 562 804 4637",
    "sg:postcode":"90713",
    "sg:province":"CA",
    "sg:tags":[
        "pizza"
    ],
    "sg:website":"www.dominos.com",
    "wof:name":"Domino's Pizza",
    "wof:placetype":"venue"
},
  "geometry": {"coordinates":[-118.124056,33.847029],"type":"Point"}
}