{
  "type": "Feature",
  "properties": {
    "addr:full":"1920 Lake Ave Ste 102 Altadena CA 91001",
    "addr:housenumber":"1920",
    "addr:postcode":"91001",
    "addr:street":"Lake Ave Ste 102",
    "iso:country":"US",
    "sg:address":"1920 Lake Ave Ste 102",
    "sg:city":"Altadena",
    "sg:classifiers":[
        {
            "category":"Shopping",
            "subcategory":"Florist",
            "type":"Retail Goods"
        }
    ],
    "sg:phone":"+1 626 791 8141",
    "sg:postcode":"91001",
    "sg:province":"CA",
    "wof:name":"Pampered Lady Florist",
    "wof:placetype":"venue"
},
  "geometry": {"coordinates":[-118.13200399999999,34.178799],"type":"Point"}
}