{
  "type": "Feature",
  "properties": {
    "addr:full":"2409 N Sepulveda Blvd Manhattan Beach CA 90266",
    "addr:housenumber":"2409",
    "addr:postcode":"90266",
    "addr:street":"N Sepulveda Blvd",
    "iso:country":"US",
    "sg:address":"2409 N Sepulveda Blvd",
    "sg:city":"Manhattan Beach",
    "sg:classifiers":[
        {
            "category":"Health Services",
            "subcategory":"Health Practitioner",
            "type":"Services"
        }
    ],
    "sg:phone":"+1 310 545 8711",
    "sg:postcode":"90266",
    "sg:province":"CA",
    "sg:tags":[
        "occupational",
        "therapist"
    ],
    "wof:name":"Northstar Therapy Consulting",
    "wof:placetype":"venue"
},
  "geometry": {"coordinates":[-118.396069,33.894561],"type":"Point"}
}