{
  "type": "Feature",
  "properties": {
    "addr:full":"269 Lorraine Blvd Los Angeles CA 90004",
    "addr:housenumber":"269",
    "addr:postcode":"90004",
    "addr:street":"Lorraine Blvd",
    "iso:country":"US",
    "sg:address":"269 Lorraine Blvd",
    "sg:city":"Los Angeles",
    "sg:classifiers":[
        {
            "category":"Professional",
            "type":"Services"
        }
    ],
    "sg:phone":"+1 323 934 0379",
    "sg:postcode":"90004",
    "sg:province":"CA",
    "wof:name":"Epic Advisors Inc",
    "wof:placetype":"venue"
},
  "geometry": {"coordinates":[-118.319605,34.070604],"type":"Point"}
}