{
  "type": "Feature",
  "properties": {
    "addr:full":"471 E Tahquitz Canyon Way Palm Springs CA 92262",
    "addr:housenumber":"471",
    "addr:postcode":"92262",
    "addr:street":"E Tahquitz Canyon Way",
    "iso:country":"US",
    "sg:address":"471 E Tahquitz Canyon Way",
    "sg:city":"Palm Springs",
    "sg:classifiers":[
        {
            "category":"Health Services",
            "subcategory":"Chiropractor",
            "type":"Services"
        }
    ],
    "sg:phone":"+1 760 325 8525",
    "sg:postcode":"92262",
    "sg:province":"CA",
    "wof:name":"Sandra Gune DC",
    "wof:placetype":"venue"
},
  "geometry": {"coordinates":[-116.542455,33.82305],"type":"Point"}
}