{
  "type": "Feature",
  "properties": {
    "addr:full":"3121 Main St Chula Vista CA 91911",
    "addr:housenumber":"3121",
    "addr:postcode":"91911",
    "addr:street":"Main St",
    "iso:country":"US",
    "sg:address":"3121 Main St",
    "sg:city":"Chula Vista",
    "sg:classifiers":[
        {
            "category":"Organizations",
            "subcategory":"Religious Organization",
            "type":"Services"
        }
    ],
    "sg:phone":"+1 619 585 7773",
    "sg:postcode":"91911",
    "sg:province":"CA",
    "wof:name":"SOS For Wounded Sheep Fndtn",
    "wof:placetype":"venue"
},
  "geometry": {"coordinates":[-117.064956,32.594705],"type":"Point"}
}