{
  "type": "Feature",
  "properties": {
    "addr:full":"30151 Tomas Rcho Sta Marg CA 92688",
    "addr:housenumber":"30151",
    "addr:postcode":"92688",
    "addr:street":"Tomas;Sta Marg",
    "iso:country":"US",
    "sg:address":"30151 Tomas",
    "sg:city":"Rcho Sta Marg",
    "sg:classifiers":[
        {
            "category":"Professional",
            "subcategory":"Advertising",
            "type":"Services"
        }
    ],
    "sg:phone":"+1 949 858 1953",
    "sg:postcode":"92688",
    "sg:province":"CA",
    "sg:tags":[
        "counselor"
    ],
    "wof:name":"Dsat Productions",
    "wof:placetype":"venue"
},
  "geometry": {"coordinates":[-117.602726,33.636848],"type":"Point"}
}