{
  "type": "Feature",
  "properties": {
    "addr:full":"505 E San Carlos St San Jose CA 95112",
    "addr:housenumber":"505",
    "addr:postcode":"95112",
    "addr:street":"E San Carlos St",
    "iso:country":"US",
    "sg:address":"505 E San Carlos St",
    "sg:city":"San Jose",
    "sg:classifiers":[
        {
            "category":"Professional",
            "type":"Services"
        },
        {
            "category":"Restaurant",
            "type":"Food & Drink"
        }
    ],
    "sg:phone":"+1 408 286 1100",
    "sg:postcode":"95112",
    "sg:province":"CA",
    "sg:tags":[
        "new",
        "american",
        "caterer"
    ],
    "sg:website":"www.nagleeparkgarage.com",
    "wof:name":"Naglee Park Garage",
    "wof:placetype":"venue"
},
  "geometry": {"coordinates":[-121.876278,37.336793],"type":"Point"}
}