{
  "type": "Feature",
  "properties": {
    "iso:country":"US",
    "sg:address":"2711 W Pico Blvd",
    "sg:city":"Los Angeles",
    "sg:classifiers":[
        {
            "category":"Retail",
            "subcategory":"Repair Shop",
            "type":"Services"
        }
    ],
    "sg:phone":"+1 323 766 2741",
    "sg:postcode":"90006",
    "sg:province":"CA",
    "sg:tags":[
        "jewelry"
    ],
    "wof:name":"Kingsley Jewelry Repair",
    "wof:placetype":"venue"
},
  "geometry": {"coordinates":[-118.297825,34.047311],"type":"Point"}
}