{
  "type": "Feature",
  "properties": {
    "addr:full":"501 S Van Ness Ave San Francisco CA 94110",
    "addr:housenumber":"501",
    "addr:postcode":"94110",
    "addr:street":"S Van Ness Ave",
    "iso:country":"US",
    "sg:address":"501 S Van Ness Ave",
    "sg:city":"San Francisco",
    "sg:classifiers":[
        {
            "category":"Autos & Motor Vehicles",
            "subcategory":"Fuel & Gas Station",
            "type":"Retail Goods"
        }
    ],
    "sg:phone":"+1 650 588 3088",
    "sg:postcode":"94110",
    "sg:province":"CA",
    "wof:name":"76",
    "wof:placetype":"venue"
},
  "geometry": {"coordinates":[-122.416995,37.764814],"type":"Point"}
}