{
  "type": "Feature",
  "properties": {
    "addr:full":"24970 Hesperian Blvd Hayward CA 94545",
    "addr:housenumber":"24970",
    "addr:postcode":"94545",
    "addr:street":"Hesperian Blvd",
    "iso:country":"US",
    "sg:address":"24970 Hesperian Blvd",
    "sg:city":"Hayward",
    "sg:classifiers":[
        {
            "category":"Arena",
            "subcategory":"Sports Club",
            "type":"Entertainment"
        }
    ],
    "sg:phone":"+1 510 259 1033",
    "sg:postcode":"94545",
    "sg:province":"CA",
    "sg:tags":[
        "martial art"
    ],
    "wof:name":"World Tong-II Moo DO Federation",
    "wof:placetype":"venue"
},
  "geometry": {"coordinates":[-122.105003,37.644901],"type":"Point"}
}