{
  "type": "Feature",
  "properties": {
    "addr:full":"1180 Aster Ave Sunnyvale CA 94086",
    "addr:housenumber":"1180",
    "addr:postcode":"94086",
    "addr:street":"Aster Ave",
    "iso:country":"US",
    "sg:address":"1180 Aster Ave",
    "sg:city":"Sunnyvale",
    "sg:classifiers":[
        {
            "category":"Education",
            "subcategory":"Music School",
            "type":"Public Place"
        }
    ],
    "sg:phone":"+1 408 554 9041",
    "sg:postcode":"94086",
    "sg:province":"CA",
    "sg:tags":[
        "instrument",
        "teacher",
        "musical"
    ],
    "wof:name":"Starving Musician",
    "wof:placetype":"venue"
},
  "geometry": {"coordinates":[-121.998001,37.369301],"type":"Point"}
}