{
  "type": "Feature",
  "properties": {
    "iso:country":"US",
    "sg:address":"15750 Flamingo Dr",
    "sg:city":"Fontana",
    "sg:classifiers":[
        {
            "category":"Manufacturing",
            "subcategory":"Buildings",
            "type":"Manufacturing & Wholesale Goods"
        },
        {
            "category":"Home & Garden",
            "subcategory":"Home Furnishings",
            "type":"Retail Goods"
        },
        {
            "category":"Building & Trades",
            "subcategory":"Construction",
            "type":"Services"
        }
    ],
    "sg:phone":"+1 909 829 6991",
    "sg:postcode":"92337",
    "sg:province":"CA",
    "sg:tags":[
        "builder",
        "planning",
        "design",
        "contractor"
    ],
    "sg:website":"http://www.kbhome.com",
    "wof:name":"Kb Home",
    "wof:placetype":"venue"
},
  "geometry": {"coordinates":[-117.461281,34.04285],"type":"Point"}
}