{
  "type": "Feature",
  "properties": {
    "iso:country":"US",
    "sg:address":"3033 Limewood Ln",
    "sg:city":"Lancaster",
    "sg:classifiers":[
        {
            "category":"Building & Trades",
            "subcategory":"Plumbing",
            "type":"Services"
        }
    ],
    "sg:phone":"+1 661 722 2597",
    "sg:postcode":"93536",
    "sg:province":"CA",
    "sg:tags":[
        "plumbing",
        "contractor"
    ],
    "wof:name":"Danny's Plumbing & Drain Svc",
    "wof:placetype":"venue"
},
  "geometry": {"coordinates":[-118.184467,34.667149],"type":"Point"}
}