{
  "type": "Feature",
  "properties": {
    "addr:full":"5905 Sky Ranch Ave Bakersfield CA 93306",
    "addr:housenumber":"5905",
    "addr:postcode":"93306",
    "addr:street":"Sky Ranch Ave",
    "iso:country":"US",
    "sg:address":"5905 Sky Ranch Ave",
    "sg:city":"Bakersfield",
    "sg:classifiers":[
        {
            "category":"Wholesale",
            "subcategory":"Vending Machines",
            "type":"Manufacturing & Wholesale Goods"
        }
    ],
    "sg:phone":"+1 661 872 5461",
    "sg:postcode":"93306",
    "sg:province":"CA",
    "wof:name":"Valley Air Systems",
    "wof:placetype":"venue"
},
  "geometry": {"coordinates":[-118.926357,35.404429],"type":"Point"}
}