{
  "type": "Feature",
  "properties": {
    "iso:country":"US",
    "sg:address":"24779 Fairview Ave",
    "sg:city":"Hayward",
    "sg:classifiers":[
        {
            "category":"Retail",
            "subcategory":"Auto Repair",
            "type":"Services"
        }
    ],
    "sg:phone":"+1 510 538 3100",
    "sg:postcode":"94542",
    "sg:province":"CA",
    "sg:tags":[
        "trailer"
    ],
    "wof:name":"Demello Truck Body & Trailer",
    "wof:placetype":"venue"
},
  "geometry": {"coordinates":[-122.048621,37.676372],"type":"Point"}
}