{
  "type": "Feature",
  "properties": {
    "addr:full":"1301 Mason St San Francisco CA 94133",
    "addr:housenumber":"1301",
    "addr:postcode":"94133",
    "addr:street":"Mason St",
    "iso:country":"US",
    "sg:address":"1301 Mason St",
    "sg:city":"San Francisco",
    "sg:classifiers":[
        {
            "category":"Food & Beverages",
            "subcategory":"Groceries & Convenience Stores",
            "type":"Retail Goods"
        }
    ],
    "sg:phone":"+1 415 441 3919",
    "sg:postcode":"94133",
    "sg:province":"CA",
    "sg:tags":[
        "grocer"
    ],
    "wof:name":"Mason Supermarket",
    "wof:placetype":"venue"
},
  "geometry": {"coordinates":[-122.41163,37.795851],"type":"Point"}
}