{
  "type": "Feature",
  "properties": {
    "iso:country":"US",
    "sg:address":"5797 Foothill Blvd",
    "sg:city":"Oakland",
    "sg:classifiers":[
        {
            "category":"Health Services",
            "subcategory":"Nursing And Care Facility",
            "type":"Services"
        }
    ],
    "sg:phone":"+1 510 798 3810",
    "sg:postcode":"94605",
    "sg:province":"CA",
    "sg:tags":[
        "home",
        "referral"
    ],
    "wof:name":"Friendly Elderly Home Care Services",
    "wof:placetype":"venue"
},
  "geometry": {"coordinates":[-122.191805,37.771817],"type":"Point"}
}