{
  "type": "Feature",
  "properties": {
    "addr:full":"43281 Gallegos Ave Fremont CA 94539",
    "addr:postcode":"43281;94539",
    "addr:street":"Gallegos Ave",
    "iso:country":"US",
    "sg:address":"43281 Gallegos Ave",
    "sg:city":"Fremont",
    "sg:classifiers":[
        {
            "category":"Restaurant",
            "type":"Food & Drink"
        }
    ],
    "sg:phone":"+1 510 656 0825",
    "sg:postcode":"94539",
    "sg:province":"CA",
    "sg:tags":[
        "bakery",
        "retail",
        "eating"
    ],
    "wof:name":"Dotties Cakes/Cater",
    "wof:placetype":"venue"
},
  "geometry": {"coordinates":[-121.929777,37.53134],"type":"Point"}
}