{
  "type": "Feature",
  "properties": {
    "addr:full":"15744 Coutolenc Rd Magalia CA 95954",
    "addr:postcode":"15744;95954",
    "addr:street":"Coutolenc Rd",
    "iso:country":"US",
    "sg:address":"15744 Coutolenc Rd",
    "sg:city":"Magalia",
    "sg:classifiers":[
        {
            "category":"Autos & Motor Vehicles",
            "subcategory":"Motorcycle Sales",
            "type":"Retail Goods"
        }
    ],
    "sg:phone":"+1 530 873 2804",
    "sg:postcode":"95954",
    "sg:province":"CA",
    "sg:tags":[
        "scooter"
    ],
    "wof:name":"Helberg's EZ Rider Scooters",
    "wof:placetype":"venue"
},
  "geometry": {"coordinates":[-121.580834,39.877796],"type":"Point"}
}