{
  "type": "Feature",
  "properties": {
    "iso:country":"US",
    "sg:address":"15300 Ventura Blvd",
    "sg:city":"Sherman Oaks",
    "sg:classifiers":[
        {
            "category":"Professional",
            "type":"Services"
        }
    ],
    "sg:phone":"+1 818 817 8001",
    "sg:postcode":"91403",
    "sg:province":"CA",
    "sg:tags":[
        "establishment"
    ],
    "wof:name":"Goossen Tutor Saliba",
    "wof:placetype":"venue"
},
  "geometry": {"coordinates":[-118.467299,34.153997],"type":"Point"}
}