{
  "type": "Feature",
  "properties": {
    "iso:country":"US",
    "sg:address":"1108 W Glenoaks Blvd",
    "sg:city":"Glendale",
    "sg:classifiers":[
        {
            "category":"Restaurant",
            "type":"Food & Drink"
        }
    ],
    "sg:phone":"+1 818 550 9951",
    "sg:postcode":"91202",
    "sg:province":"CA",
    "sg:tags":[
        "greek",
        "mediterranean"
    ],
    "wof:name":"Caravan Restaurant",
    "wof:placetype":"venue"
},
  "geometry": {"coordinates":[-118.279999,34.1642],"type":"Point"}
}