{
  "type": "Feature",
  "properties": {
    "iso:country":"US",
    "sg:address":"25 Windward Ave",
    "sg:city":"Venice",
    "sg:classifiers":[
        {
            "category":"Travel",
            "subcategory":"Hotels & Motels",
            "type":"Entertainment"
        }
    ],
    "sg:phone":"+1 310 399 7649",
    "sg:postcode":"90291",
    "sg:province":"CA",
    "sg:tags":[
        "lodging"
    ],
    "sg:website":"http://www.venicebeachcotel.com",
    "wof:name":"Venice Beach Hotel",
    "wof:placetype":"venue"
},
  "geometry": {"coordinates":[-118.473209,33.987123],"type":"Point"}
}