{
  "type": "Feature",
  "properties": {
    "addr:full":"7549 Carson Blvd Long Beach CA 90808",
    "addr:housenumber":"7549",
    "addr:postcode":"90808",
    "addr:street":"Carson Blvd",
    "iso:country":"US",
    "sg:address":"7549 Carson Blvd",
    "sg:city":"Long Beach",
    "sg:classifiers":[
        {
            "category":"Restaurant",
            "type":"Food & Drink"
        }
    ],
    "sg:phone":"+1 562 627 9180",
    "sg:postcode":"90808",
    "sg:province":"CA",
    "wof:name":"Panda Express Inc",
    "wof:placetype":"venue"
},
  "geometry": {"coordinates":[-118.085999,33.826],"type":"Point"}
}