{
  "type": "Feature",
  "properties": {
    "iso:country":"US",
    "sg:address":"923 E Plymouth Ct",
    "sg:city":"Glendora",
    "sg:classifiers":[
        {
            "category":"Building & Trades",
            "subcategory":"Construction",
            "type":"Services"
        }
    ],
    "sg:phone":"+1 626 963 1886",
    "sg:postcode":"91740",
    "sg:province":"CA",
    "sg:tags":[
        "contractor"
    ],
    "wof:name":"Ideal Pressure Washing",
    "wof:placetype":"venue"
},
  "geometry": {"coordinates":[-117.845192,34.109081],"type":"Point"}
}