{
  "type": "Feature",
  "properties": {
    "iso:country":"US",
    "sg:address":"359 Foothill Dr",
    "sg:city":"Brentwood",
    "sg:classifiers":[
        {
            "category":"Restaurant",
            "type":"Food & Drink"
        }
    ],
    "sg:phone":"+1 925 465 0434",
    "sg:postcode":"94513",
    "sg:province":"CA",
    "wof:name":"Emporio Roma",
    "wof:placetype":"venue"
},
  "geometry": {"coordinates":[-121.738619,37.917136],"type":"Point"}
}