{
  "type": "Feature",
  "properties": {
    "addr:full":"631 S Main St Santa Ana CA 92701",
    "addr:housenumber":"631",
    "addr:postcode":"92701",
    "addr:street":"S Main St",
    "iso:country":"US",
    "sg:address":"631 S Main St",
    "sg:city":"Santa Ana",
    "sg:classifiers":[
        {
            "category":"Wholesale",
            "subcategory":"Computers",
            "type":"Manufacturing & Wholesale Goods"
        },
        {
            "category":"Professional",
            "subcategory":"Computer Services",
            "type":"Services"
        }
    ],
    "sg:phone":"+1 714 541 5561",
    "sg:postcode":"92701",
    "sg:province":"CA",
    "sg:tags":[
        "repair"
    ],
    "wof:name":"Hugo's Computers",
    "wof:placetype":"venue"
},
  "geometry": {"coordinates":[-117.867508,33.740327],"type":"Point"}
}