{
  "type": "Feature",
  "properties": {
    "addr:full":"7270 Mesa Dr Aptos CA 95003",
    "addr:housenumber":"7270",
    "addr:postcode":"ca 95003",
    "addr:street":"Mesa Dr",
    "iso:country":"US",
    "sg:address":"7270 Mesa Dr",
    "sg:city":"Aptos",
    "sg:classifiers":[
        {
            "category":"Building & Trades",
            "subcategory":"Construction",
            "type":"Services"
        }
    ],
    "sg:phone":"+1 831 724 1923",
    "sg:postcode":"95003",
    "sg:province":"CA",
    "sg:tags":[
        "roofing",
        "contractor"
    ],
    "wof:name":"Pacific Coast Roofing",
    "wof:placetype":"venue"
},
  "geometry": {"coordinates":[-121.912357,36.986087],"type":"Point"}
}