{
  "type": "Feature",
  "properties": {
    "iso:country":"US",
    "sg:address":"613 Quantico Ave",
    "sg:city":"Bakersfield",
    "sg:classifiers":[
        {
            "category":"Retail",
            "subcategory":"Auto Repair",
            "type":"Services"
        }
    ],
    "sg:phone":"+1 661 322 4434",
    "sg:postcode":"93307",
    "sg:province":"CA",
    "sg:tags":[
        "wrecker"
    ],
    "wof:name":"8 Ball Towing",
    "wof:placetype":"venue"
},
  "geometry": {"coordinates":[-118.958562,35.363993],"type":"Point"}
}