{
  "type": "Feature",
  "properties": {
    "iso:country":"US",
    "sg:address":"952 S Broadway",
    "sg:city":"Los Angeles",
    "sg:classifiers":[
        {
            "category":"Fast Food",
            "type":"Food & Drink"
        },
        {
            "category":"Restaurant",
            "type":"Food & Drink"
        }
    ],
    "sg:phone":"+1 213 614 8900",
    "sg:postcode":"90015",
    "sg:province":"CA",
    "sg:tags":[
        "middle",
        "mediterranean",
        "eastern"
    ],
    "sg:website":"www.lulakabob.com",
    "wof:name":"Lula Kabob",
    "wof:placetype":"venue"
},
  "geometry": {"coordinates":[-118.256967,34.040984],"type":"Point"}
}