{
  "type": "Feature",
  "properties": {
    "iso:country":"US",
    "sg:address":"9565 Arborglen Dr",
    "sg:city":"Rancho Cucamonga",
    "sg:classifiers":[
        {
            "category":"Freight",
            "type":"Transportation"
        }
    ],
    "sg:phone":"+1 909 484 4201",
    "sg:postcode":"91730",
    "sg:province":"CA",
    "sg:tags":[
        "operator",
        "local",
        "trucking"
    ],
    "wof:name":"Quick Hauling",
    "wof:placetype":"venue"
},
  "geometry": {"coordinates":[-117.597769,34.079466],"type":"Point"}
}