{
  "type": "Feature",
  "properties": {
    "iso:country":"US",
    "sg:address":"631 N Market Blvd",
    "sg:city":"Sacramento",
    "sg:classifiers":[
        {
            "category":"Shopping",
            "subcategory":"Shoes",
            "type":"Retail Goods"
        }
    ],
    "sg:phone":"+1 916 646 9327",
    "sg:postcode":"95834",
    "sg:province":"CA",
    "wof:name":"Bare Bones Work Wear",
    "wof:placetype":"venue"
},
  "geometry": {"coordinates":[-121.475477,38.647326],"type":"Point"}
}