{
  "type": "Feature",
  "properties": {
    "addr:full":"12779 Amber Creek Cir Victorville CA 92395",
    "addr:housenumber":"12779",
    "addr:postcode":"92395",
    "addr:street":"Amber Creek Cir",
    "iso:country":"US",
    "sg:address":"12779 Amber Creek Cir",
    "sg:city":"Victorville",
    "sg:classifiers":[
        {
            "category":"Real Estate",
            "subcategory":"Real Estate Services",
            "type":"Services"
        },
        {
            "category":"Banks & Credit Unions",
            "subcategory":"Financial Services",
            "type":"Services"
        }
    ],
    "sg:phone":"+1 760 243 2952",
    "sg:postcode":"92395",
    "sg:province":"CA",
    "sg:tags":[
        "loan",
        "processing"
    ],
    "sg:website":"http://www.normandymortgage.com",
    "wof:name":"Normandy Mortgage",
    "wof:placetype":"venue"
},
  "geometry": {"coordinates":[-117.298249,34.482427],"type":"Point"}
}