{
  "type": "Feature",
  "properties": {
    "addr:full":"2090 Market St Concord CA 94520",
    "addr:housenumber":"2090",
    "addr:postcode":"94520",
    "addr:street":"Market St",
    "iso:country":"US",
    "sg:address":"2090 Market St",
    "sg:city":"Concord",
    "sg:classifiers":[
        {
            "category":"Retail",
            "subcategory":"Auto Repair",
            "type":"Services"
        }
    ],
    "sg:phone":"+1 925 676 8376",
    "sg:postcode":"94520",
    "sg:province":"CA",
    "sg:tags":[
        "muffler",
        "exhaust",
        "system"
    ],
    "wof:name":"West Coast Muffler & Tire Inc",
    "wof:placetype":"venue"
},
  "geometry": {"coordinates":[-122.043077,37.976182],"type":"Point"}
}