{
  "type": "Feature",
  "properties": {
    "addr:full":"26299 Sandpiper Way Madera CA 93638",
    "addr:housenumber":"26299",
    "addr:postcode":"93638",
    "addr:street":"Sandpiper Way",
    "iso:country":"US",
    "sg:address":"26299 Sandpiper Way",
    "sg:city":"Madera",
    "sg:classifiers":[
        {
            "category":"Building & Trades",
            "subcategory":"Construction",
            "type":"Services"
        }
    ],
    "sg:phone":"+1 559 232 1916",
    "sg:postcode":"93638",
    "sg:province":"CA",
    "sg:tags":[
        "wallcoverings-installation",
        "wallpaper",
        "painting",
        "contractor"
    ],
    "wof:name":"Matt Dolph Painting",
    "wof:placetype":"venue"
},
  "geometry": {"coordinates":[-120.069641,37.020914],"type":"Point"}
}