{
  "type": "Feature",
  "properties": {
    "addr:full":"12801 Prairie Ave Hawthorne CA 90250",
    "addr:housenumber":"12801",
    "addr:postcode":"90250",
    "addr:street":"Prairie Ave",
    "iso:country":"US",
    "sg:address":"12801 Prairie Ave",
    "sg:city":"Hawthorne",
    "sg:classifiers":[
        {
            "category":"Insurance",
            "subcategory":"Insurance Agent",
            "type":"Services"
        }
    ],
    "sg:phone":"+1 310 978 1441",
    "sg:postcode":"90250",
    "sg:province":"CA",
    "wof:name":"21st Century Insurance Co",
    "wof:placetype":"venue"
},
  "geometry": {"coordinates":[-118.343873,33.915341],"type":"Point"}
}