{
  "type": "Feature",
  "properties": {
    "addr:full":"321 N Milpas St Santa Barbara CA 93103",
    "addr:housenumber":"321",
    "addr:postcode":"93103",
    "addr:street":"N Milpas St",
    "iso:country":"US",
    "sg:address":"321 N Milpas St",
    "sg:city":"Santa Barbara",
    "sg:classifiers":[
        {
            "category":"Building & Trades",
            "subcategory":"Landscaping Services",
            "type":"Services"
        }
    ],
    "sg:phone":"+1 805 899 9202",
    "sg:postcode":"93103",
    "sg:province":"CA",
    "wof:name":"Martin Munoz",
    "wof:placetype":"venue"
},
  "geometry": {"coordinates":[-119.683875,34.425128],"type":"Point"}
}