{
  "type": "Feature",
  "properties": {
    "addr:full":"7011 Warner Ave Ste F Huntington Beach CA 92647",
    "addr:housenumber":"7011",
    "addr:postcode":"92647",
    "addr:street":"Warner Ave Ste F",
    "iso:country":"US",
    "sg:address":"7011 Warner Ave Ste F",
    "sg:city":"Huntington Beach",
    "sg:classifiers":[
        {
            "category":"Retail",
            "subcategory":"Laundry & Dry Cleaning",
            "type":"Services"
        }
    ],
    "sg:phone":"+1 714 847 1222",
    "sg:postcode":"92647",
    "sg:province":"CA",
    "wof:name":"Vip Cleaners",
    "wof:placetype":"venue"
},
  "geometry": {"coordinates":[-118.00599699999999,33.715698],"type":"Point"}
}