{
  "type": "Feature",
  "properties": {
    "addr:full":"623 2nd St Davis CA 95616",
    "addr:housenumber":"623",
    "addr:postcode":"95616",
    "addr:street":"2Nd St",
    "iso:country":"US",
    "sg:address":"623 2nd St",
    "sg:city":"Davis",
    "sg:classifiers":[
        {
            "category":"Shopping",
            "subcategory":"Clothing, Apparel, & Fashions",
            "type":"Retail Goods"
        }
    ],
    "sg:phone":"+1 530 753 9595",
    "sg:postcode":"95616",
    "sg:province":"CA",
    "wof:name":"Samira's",
    "wof:placetype":"venue"
},
  "geometry": {"coordinates":[-121.74025,38.543457],"type":"Point"}
}