{
  "type": "Feature",
  "properties": {
    "addr:full":"16644 Roscoe Blvd Van Nuys CA 91402",
    "addr:housenumber":"16644",
    "addr:postcode":"91402",
    "addr:street":"Roscoe Blvd",
    "iso:country":"US",
    "sg:address":"16644 Roscoe Blvd",
    "sg:city":"Van Nuys",
    "sg:classifiers":[
        {
            "category":"Professional",
            "subcategory":"Art Services",
            "type":"Services"
        },
        {
            "category":"Manufacturing",
            "subcategory":"Tools & Machinery",
            "type":"Manufacturing & Wholesale Goods"
        }
    ],
    "sg:phone":"+1 818 780 2708",
    "sg:postcode":"91402",
    "sg:province":"CA",
    "sg:tags":[
        "photographer",
        "photographic",
        "mfg"
    ],
    "wof:name":"Salamati Productions",
    "wof:placetype":"venue"
},
  "geometry": {"coordinates":[-118.497182,34.220202],"type":"Point"}
}