{
  "type": "Feature",
  "properties": {
    "iso:country":"US",
    "sg:address":"6817 Watcher St",
    "sg:city":"City Of Commerce",
    "sg:classifiers":[
        {
            "category":"Freight",
            "type":"Transportation"
        }
    ],
    "sg:phone":"+1 562 928 3214",
    "sg:postcode":"90040",
    "sg:province":"CA",
    "sg:tags":[
        "trucking"
    ],
    "wof:name":"Ca Inland Empire",
    "wof:placetype":"venue"
},
  "geometry": {"coordinates":[-118.13518999999999,33.975599],"type":"Point"}
}