{
  "type": "Feature",
  "properties": {
    "iso:country":"US",
    "sg:address":"720 24th St",
    "sg:city":"Hermosa Beach",
    "sg:classifiers":[
        {
            "category":"Wholesale",
            "subcategory":"Electrical",
            "type":"Manufacturing & Wholesale Goods"
        }
    ],
    "sg:phone":"+1 310 374 1458",
    "sg:postcode":"90254",
    "sg:province":"CA",
    "sg:tags":[
        "video"
    ],
    "wof:name":"Nl & Co",
    "wof:placetype":"venue"
},
  "geometry": {"coordinates":[-118.396082,33.870844],"type":"Point"}
}