{
  "type": "Feature",
  "properties": {
    "iso:country":"US",
    "sg:address":"460 Nelo St",
    "sg:city":"Santa Clara",
    "sg:classifiers":[
        {
            "category":"Building & Trades",
            "subcategory":"Construction",
            "type":"Services"
        }
    ],
    "sg:phone":"+1 408 987 7777",
    "sg:postcode":"95054",
    "sg:province":"CA",
    "sg:tags":[
        "air",
        "heating",
        "conditioning/hvac"
    ],
    "sg:website":"www.efihvac.com",
    "wof:name":"Environmental Filtration Inc",
    "wof:placetype":"venue"
},
  "geometry": {"coordinates":[-121.941864,37.38769],"type":"Point"}
}