{
  "type": "Feature",
  "properties": {
    "iso:country":"US",
    "sg:address":"2014 9th St",
    "sg:city":"Sacramento",
    "sg:classifiers":[
        {
            "category":"Professional",
            "subcategory":"Art Services",
            "type":"Services"
        }
    ],
    "sg:phone":"+1 916 362 8080",
    "sg:postcode":"95818",
    "sg:province":"CA",
    "sg:tags":[
        "photographer"
    ],
    "wof:name":"Martin Smuts Photography",
    "wof:placetype":"venue"
},
  "geometry": {"coordinates":[-121.49982300000001,38.569281],"type":"Point"}
}