{
  "type": "Feature",
  "properties": {
    "iso:country":"US",
    "sg:address":"660 Riverside Rd",
    "sg:city":"Watsonville",
    "sg:classifiers":[
        {
            "category":"Freight",
            "type":"Transportation"
        }
    ],
    "sg:phone":"+1 831 475 1060",
    "sg:postcode":"95076",
    "sg:province":"CA",
    "sg:tags":[
        "operator",
        "local",
        "trucking"
    ],
    "wof:name":"Roberson Trucking Co",
    "wof:placetype":"venue"
},
  "geometry": {"coordinates":[-121.71137299999999,36.921693],"type":"Point"}
}