{
  "type": "Feature",
  "properties": {
    "sfgov:dept":"7",
    "sfgov:deptname":"SF Unified School District (SFUSD)",
    "sfgov:facility_i":"0000060153",
    "sfgov:school_typ":"Early Education",
    "wof:categories":[
        "education_and_religion:education=school"
    ],
    "wof:name":"Serra, Junipero Early Education School (2)",
    "wof:placetype":"venue"
},
  "geometry": {"coordinates":[-122.42259917013139,37.73845825777568],"type":"Point"}
}