{
  "type": "Feature",
  "properties": {
    "addr:full":"38 Conrad Ct Oakland CA 94611",
    "addr:housenumber":"38",
    "addr:postcode":"94611",
    "addr:street":"Conrad Ct",
    "iso:country":"US",
    "sg:address":"38 Conrad Ct",
    "sg:city":"Oakland",
    "sg:classifiers":[
        {
            "category":"Professional",
            "subcategory":"Printing & Photocopies",
            "type":"Services"
        }
    ],
    "sg:phone":"+1 510 339 1527",
    "sg:postcode":"94611",
    "sg:province":"CA",
    "sg:tags":[
        "photographers-commercial"
    ],
    "wof:name":"Matney & Associates",
    "wof:placetype":"venue"
},
  "geometry": {"coordinates":[-122.203472,37.843423],"type":"Point"}
}