{
  "type": "Feature",
  "properties": {
    "iso:country":"US",
    "sg:address":"4516 Brazil St",
    "sg:city":"Los Angeles",
    "sg:classifiers":[
        {
            "category":"Manufacturing",
            "subcategory":"Metals",
            "type":"Manufacturing & Wholesale Goods"
        }
    ],
    "sg:phone":"+1 818 500 0857",
    "sg:postcode":"90039",
    "sg:province":"CA",
    "sg:tags":[
        "machine",
        "parts",
        "mfg"
    ],
    "wof:name":"ARA Engineering LP",
    "wof:placetype":"venue"
},
  "geometry": {"coordinates":[-118.275312,34.146709],"type":"Point"}
}