{
  "type": "Feature",
  "properties": {
    "iso:country":"US",
    "sg:address":"100 Wilshire Blvd",
    "sg:city":"Santa Monica",
    "sg:classifiers":[
        {
            "category":"Professional",
            "subcategory":"Management & Consulting",
            "type":"Services"
        }
    ],
    "sg:phone":"+1 310 752 1405",
    "sg:postcode":"90401",
    "sg:province":"CA",
    "sg:tags":[
        "fuel"
    ],
    "wof:name":"Francis Capital Management LLC",
    "wof:placetype":"venue"
},
  "geometry": {"coordinates":[-118.500187,34.017575],"type":"Point"}
}