{
  "type": "Feature",
  "properties": {
    "iso:country":"US",
    "sg:address":"21885 8th St E",
    "sg:city":"Sonoma",
    "sg:classifiers":[
        {
            "category":"Manufacturing",
            "subcategory":"Tools & Machinery",
            "type":"Manufacturing & Wholesale Goods"
        }
    ],
    "sg:phone":"+1 707 938 5555",
    "sg:postcode":"95476",
    "sg:province":"CA",
    "sg:tags":[
        "industry",
        "special"
    ],
    "wof:name":"Quantum Mechanics",
    "wof:placetype":"venue"
},
  "geometry": {"coordinates":[-122.44008700000001,38.262754],"type":"Point"}
}