{
  "type": "Feature",
  "properties": {
    "addr:full":"3734 Broadway Pl Los Angeles CA 90007",
    "addr:housenumber":"3734",
    "addr:postcode":"90007",
    "addr:street":"Broadway Pl",
    "iso:country":"US",
    "sg:address":"3734 Broadway Pl",
    "sg:city":"Los Angeles",
    "sg:classifiers":[
        {
            "category":"Food & Beverages",
            "subcategory":"Specialty",
            "type":"Retail Goods"
        }
    ],
    "sg:phone":"+1 323 232 7235",
    "sg:postcode":"90007",
    "sg:province":"CA",
    "sg:tags":[
        "american",
        "latin",
        "mexican",
        "product"
    ],
    "wof:name":"Reynaldo's Mexican Food Co",
    "wof:placetype":"venue"
},
  "geometry": {"coordinates":[-118.274873,34.015088],"type":"Point"}
}