{
  "type": "Feature",
  "properties": {
    "iso:country":"US",
    "sg:address":"600 S Alvarado St",
    "sg:city":"Los Angeles",
    "sg:classifiers":[
        {
            "category":"Professional",
            "subcategory":"Accounting & Tax Preparation",
            "type":"Services"
        }
    ],
    "sg:phone":"+1 213 739 9050",
    "sg:postcode":"90057",
    "sg:province":"CA",
    "sg:tags":[
        "bookkeeping",
        "general"
    ],
    "wof:name":"Cardenas Accounting Svc",
    "wof:placetype":"venue"
},
  "geometry": {"coordinates":[-118.275881,34.057928],"type":"Point"}
}