{
  "type": "Feature",
  "properties": {
    "iso:country":"US",
    "sg:address":"1137 S Cabrillo Ave",
    "sg:city":"San Pedro",
    "sg:classifiers":[
        {
            "category":"Building & Trades",
            "subcategory":"Landscaping Services",
            "type":"Services"
        }
    ],
    "sg:phone":"+1 310 832 4064",
    "sg:postcode":"90731",
    "sg:province":"CA",
    "sg:tags":[
        "landscape"
    ],
    "wof:name":"La Forest Landscaping",
    "wof:placetype":"venue"
},
  "geometry": {"coordinates":[-118.29463,33.733671],"type":"Point"}
}