{
  "type": "Feature",
  "properties": {
    "iso:country":"US",
    "sg:address":"5700 E Airport Dr",
    "sg:city":"Ontario",
    "sg:classifiers":[
        {
            "category":"Home & Garden",
            "subcategory":"Building Materials",
            "type":"Retail Goods"
        }
    ],
    "sg:phone":"+1 909 937 3435",
    "sg:postcode":"91761",
    "sg:province":"CA",
    "wof:name":"Crown Building Materials",
    "wof:placetype":"venue"
},
  "geometry": {"coordinates":[-117.535029,34.062742],"type":"Point"}
}