{
  "type": "Feature",
  "properties": {
    "addr:full":"5700 E Airport Dr Ontario CA 91761",
    "addr:housenumber":"5700",
    "addr:postcode":"91761",
    "addr:street":"E Airport Dr",
    "iso:country":"US",
    "sg:address":"5700 E Airport Dr",
    "sg:city":"Ontario",
    "sg:classifiers":[
        {
            "category":"Home & Garden",
            "subcategory":"Building Materials",
            "type":"Retail Goods"
        }
    ],
    "sg:phone":"+1 909 937 3435",
    "sg:postcode":"91761",
    "sg:province":"CA",
    "wof:name":"Crown Building Materials",
    "wof:placetype":"venue"
},
  "geometry": {"coordinates":[-117.53502899999999,34.062742],"type":"Point"}
}