{
  "type": "Feature",
  "properties": {
    "iso:country":"US",
    "sg:address":"1102 Jefferson Blvd",
    "sg:city":"West Sacramento",
    "sg:classifiers":[
        {
            "category":"Professional",
            "subcategory":"Management & Consulting",
            "type":"Services"
        }
    ],
    "sg:phone":"+1 916 372 7023",
    "sg:postcode":"95691",
    "sg:province":"CA",
    "sg:tags":[
        "consultant",
        "business"
    ],
    "wof:name":"Fernandez Barragan & Assoc",
    "wof:placetype":"venue"
},
  "geometry": {"coordinates":[-121.523713,38.572618],"type":"Point"}
}