{
  "type": "Feature",
  "properties": {
    "addr:full":"6123 Inez St Ventura CA 93003",
    "addr:housenumber":"6123",
    "addr:postcode":"93003",
    "addr:street":"Inez St",
    "iso:country":"US",
    "sg:address":"6123 Inez St",
    "sg:city":"Ventura",
    "sg:classifiers":[
        {
            "category":"Professional",
            "type":"Services"
        }
    ],
    "sg:phone":"+1 805 644 6333",
    "sg:postcode":"93003",
    "sg:province":"CA",
    "sg:tags":[
        "establishment"
    ],
    "wof:name":"Bob Stone Enterprises",
    "wof:placetype":"venue"
},
  "geometry": {"coordinates":[-119.205989,34.250548],"type":"Point"}
}