{
  "type": "Feature",
  "properties": {
    "addr:full":"1733 Cherry Hill Rd Santa Paula CA 93060",
    "addr:housenumber":"1733",
    "addr:postcode":"93060",
    "addr:street":"Cherry Hill Rd",
    "iso:country":"US",
    "sg:address":"1733 Cherry Hill Rd",
    "sg:city":"Santa Paula",
    "sg:classifiers":[
        {
            "category":"Manufacturing",
            "subcategory":"Printing",
            "type":"Manufacturing & Wholesale Goods"
        }
    ],
    "sg:phone":"+1 805 525 3732",
    "sg:postcode":"93060",
    "sg:province":"CA",
    "sg:tags":[
        "screen"
    ],
    "wof:name":"Integrity Screenprinting",
    "wof:placetype":"venue"
},
  "geometry": {"coordinates":[-119.069248,34.380994],"type":"Point"}
}