{
  "type": "Feature",
  "properties": {
    "addr:full":"10101 Firmona Avenue Inglewood CA 90304",
    "addr:housenumber":"10101",
    "addr:postcode":"90304",
    "addr:street":"Firmona Avenue",
    "iso:country":"US",
    "sg:address":"10101 Firmona Avenue",
    "sg:city":"Inglewood",
    "sg:classifiers":[
        {
            "category":"Retail",
            "subcategory":"Storage",
            "type":"Services"
        }
    ],
    "sg:phone":"+1 310 674 6112",
    "sg:postcode":"90304",
    "sg:province":"CA",
    "sg:tags":[
        "self"
    ],
    "sg:website":"www.aamericanselfstorage.com/",
    "wof:name":"A-American Self Storage",
    "wof:placetype":"venue"
},
  "geometry": {"coordinates":[-118.357547,33.944425],"type":"Point"}
}