{
  "type": "Feature",
  "properties": {
    "addr:full":"55 Brennan St Watsonville CA 95076",
    "addr:housenumber":"55",
    "addr:postcode":"95076",
    "addr:street":"Brennan St",
    "iso:country":"US",
    "sg:address":"55 Brennan St",
    "sg:city":"Watsonville",
    "sg:classifiers":[
        {
            "category":"Home & Garden",
            "subcategory":"Household Appliances",
            "type":"Retail Goods"
        },
        {
            "category":"Retail",
            "subcategory":"Repair Shop",
            "type":"Services"
        }
    ],
    "sg:phone":"+1 831 722 1776",
    "sg:postcode":"95076",
    "sg:province":"CA",
    "sg:tags":[
        "small",
        "electrical"
    ],
    "wof:name":"Baker Bros Appliance",
    "wof:placetype":"venue"
},
  "geometry": {"coordinates":[-121.758222,36.914063],"type":"Point"}
}