{
  "type": "Feature",
  "properties": {
    "addr:full":"3819 Sunset Rd Santa Barbara CA 93110",
    "addr:housenumber":"3819",
    "addr:postcode":"93110",
    "addr:street":"Sunset Rd",
    "iso:country":"US",
    "sg:address":"3819 Sunset Rd",
    "sg:city":"Santa Barbara",
    "sg:classifiers":[
        {
            "category":"Utilities",
            "subcategory":"Telephone",
            "type":"Services"
        }
    ],
    "sg:phone":"+1 805 682 0794",
    "sg:postcode":"93110",
    "sg:province":"CA",
    "sg:tags":[
        "communications"
    ],
    "wof:name":"Cables & Currents",
    "wof:placetype":"venue"
},
  "geometry": {"coordinates":[-119.750258,34.445454],"type":"Point"}
}