{
  "type": "Feature",
  "properties": {
    "iso:country":"US",
    "sg:address":"10515 Pioneer Blvd",
    "sg:city":"Santa Fe Springs",
    "sg:classifiers":[
        {
            "category":"Education",
            "subcategory":"School",
            "type":"Public Place"
        }
    ],
    "sg:phone":"+1 562 868 8241",
    "sg:postcode":"90670",
    "sg:province":"CA",
    "sg:tags":[
        "high",
        "middle",
        "elementary"
    ],
    "wof:name":"Little Lake City School District",
    "wof:placetype":"venue"
},
  "geometry": {"coordinates":[-118.08200100000001,33.938702],"type":"Point"}
}