{
  "type": "Feature",
  "properties": {
    "iso:country":"US",
    "sg:address":"15458 Valley Blvd",
    "sg:city":"City Of Industry",
    "sg:classifiers":[
        {
            "category":"Home & Garden",
            "subcategory":"Carpets & Floor Coverings",
            "type":"Retail Goods"
        }
    ],
    "sg:phone":"+1 626 961 4299",
    "sg:postcode":"91746",
    "sg:province":"CA",
    "sg:tags":[
        "dealer",
        "rug"
    ],
    "wof:name":"Valley Carpet Distributors Inc",
    "wof:placetype":"venue"
},
  "geometry": {"coordinates":[-117.963708,34.026812],"type":"Point"}
}