{
  "type": "Feature",
  "properties": {
    "iso:country":"US",
    "sg:address":"13951 Valley View Ave",
    "sg:city":"La Mirada",
    "sg:classifiers":[
        {
            "category":"Utilities",
            "subcategory":"Telephone",
            "type":"Services"
        }
    ],
    "sg:phone":"+1 562 404 8580",
    "sg:postcode":"90638",
    "sg:province":"CA",
    "sg:tags":[
        "telecommunication"
    ],
    "wof:name":"DCJ Telecomm Inc",
    "wof:placetype":"venue"
},
  "geometry": {"coordinates":[-118.029118,33.903564],"type":"Point"}
}