{
  "type": "Feature",
  "properties": {
    "iso:country":"US",
    "sg:address":"620 Kings Ct",
    "sg:city":"Ukiah",
    "sg:classifiers":[
        {
            "category":"Professional",
            "subcategory":"Accounting & Tax Preparation",
            "type":"Services"
        }
    ],
    "sg:phone":"+1 707 463 8600",
    "sg:postcode":"95482",
    "sg:province":"CA",
    "sg:tags":[
        "accountant"
    ],
    "wof:name":"Nicolette Hamilton CPA",
    "wof:placetype":"venue"
},
  "geometry": {"coordinates":[-123.197699,39.148166],"type":"Point"}
}