{
  "type": "Feature",
  "properties": {
    "addr:full":"286 Pingree Way Salinas CA 93906",
    "addr:housenumber":"286",
    "addr:postcode":"93906",
    "addr:street":"Pingree Way",
    "iso:country":"US",
    "sg:address":"286 Pingree Way",
    "sg:city":"Salinas",
    "sg:classifiers":[
        {
            "category":"Building & Trades",
            "subcategory":"Electrical",
            "type":"Services"
        }
    ],
    "sg:phone":"+1 831 443 0200",
    "sg:postcode":"93906",
    "sg:province":"CA",
    "sg:tags":[
        "electrical",
        "contractor"
    ],
    "wof:name":"RNS Electrical Co Inc",
    "wof:placetype":"venue"
},
  "geometry": {"coordinates":[-121.634343,36.729843],"type":"Point"}
}