{
  "type": "Feature",
  "properties": {
    "addr:full":"415 W Foothill Blvd Claremont CA 91711",
    "addr:housenumber":"415",
    "addr:postcode":"91711",
    "addr:street":"W Foothill Blvd",
    "iso:country":"US",
    "sg:address":"415 W Foothill Blvd",
    "sg:city":"Claremont",
    "sg:classifiers":[
        {
            "category":"Professional",
            "subcategory":"Business Services",
            "type":"Services"
        }
    ],
    "sg:phone":"+1 909 621 0092",
    "sg:postcode":"91711",
    "sg:province":"CA",
    "sg:tags":[
        "arbitration"
    ],
    "wof:name":"Claremount Dispute Resolution",
    "wof:placetype":"venue"
},
  "geometry": {"coordinates":[-117.72230399999999,34.107055],"type":"Point"}
}