{
  "type": "Feature",
  "properties": {
    "iso:country":"US",
    "sg:address":"5012 Via Jacinto",
    "sg:city":"Santa Barbara",
    "sg:classifiers":[
        {
            "category":"Building & Trades",
            "subcategory":"Plumbing",
            "type":"Services"
        }
    ],
    "sg:phone":"+1 805 964 4386",
    "sg:postcode":"93111",
    "sg:province":"CA",
    "sg:tags":[
        "plumbing",
        "contractor"
    ],
    "wof:name":"Pete's Plumbing & Heating",
    "wof:placetype":"venue"
},
  "geometry": {"coordinates":[-119.798067,34.43447],"type":"Point"}
}