{
  "type": "Feature",
  "properties": {
    "addr:full":"2790 Foxborough Pl Fullerton CA 92833",
    "addr:housenumber":"2790",
    "addr:postcode":"92833",
    "addr:street":"Foxborough Pl",
    "iso:country":"US",
    "sg:address":"2790 Foxborough Pl",
    "sg:city":"Fullerton",
    "sg:classifiers":[
        {
            "category":"Professional",
            "type":"Services"
        }
    ],
    "sg:phone":"+1 714 525 6804",
    "sg:postcode":"92833",
    "sg:province":"CA",
    "wof:name":"Strong Metal Inc",
    "wof:placetype":"venue"
},
  "geometry": {"coordinates":[-117.97517000000001,33.879194],"type":"Point"}
}