{
  "type": "Feature",
  "properties": {
    "addr:full":"104 N Belmont St Ste 208 Glendale CA 91206",
    "addr:housenumber":"104",
    "addr:postcode":"91206",
    "addr:street":"N Belmont St Ste 208",
    "iso:country":"US",
    "sg:address":"104 N Belmont St Ste 208",
    "sg:city":"Glendale",
    "sg:classifiers":[
        {
            "category":"Education",
            "subcategory":"School",
            "type":"Public Place"
        }
    ],
    "sg:phone":"+1 818 500 0822",
    "sg:postcode":"91206",
    "sg:province":"CA",
    "sg:tags":[
        "high",
        "middle",
        "elementary"
    ],
    "wof:name":"Western Prelacy Board of Regents Armenian Schools",
    "wof:placetype":"venue"
},
  "geometry": {"coordinates":[-118.24299600000001,34.146301],"type":"Point"}
}