{
  "type": "Feature",
  "properties": {
    "addr:full":"809 W 2nd St Antioch CA 94509",
    "addr:housenumber":"809",
    "addr:postcode":"ca 94509",
    "addr:street":"W 2Nd St",
    "iso:country":"US",
    "sg:address":"809 W 2nd St",
    "sg:city":"Antioch",
    "sg:classifiers":[
        {
            "category":"Bars & Pubs",
            "type":"Food & Drink"
        }
    ],
    "sg:phone":"+1 925 754 0263",
    "sg:postcode":"94509",
    "sg:province":"CA",
    "wof:name":"Beer Garden",
    "wof:placetype":"venue"
},
  "geometry": {"coordinates":[-121.817482,38.016821],"type":"Point"}
}