{
  "type": "Feature",
  "properties": {
    "iso:country":"US",
    "sg:address":"820 E Dunne Ave",
    "sg:city":"Morgan Hill",
    "sg:classifiers":[
        {
            "category":"Real Estate",
            "subcategory":"Real Estate Agent",
            "type":"Services"
        }
    ],
    "sg:phone":"+1 408 779 2173",
    "sg:postcode":"95037",
    "sg:province":"CA",
    "wof:name":"Coldwell Banker",
    "wof:placetype":"venue"
},
  "geometry": {"coordinates":[-121.63592,37.130657],"type":"Point"}
}