{
  "type": "Feature",
  "properties": {
    "iso:country":"US",
    "sg:address":"515 S Flower St",
    "sg:city":"Los Angeles",
    "sg:classifiers":[
        {
            "category":"Professional",
            "subcategory":"Lawyer & Legal Services",
            "type":"Services"
        }
    ],
    "sg:phone":"+1 213 680 2800",
    "sg:postcode":"90071",
    "sg:province":"CA",
    "wof:name":"Doty Rod Barger & Wolen Atty",
    "wof:placetype":"venue"
},
  "geometry": {"coordinates":[-118.255997,34.051399],"type":"Point"}
}