{
  "type": "Feature",
  "properties": {
    "addr:full":"2061 Coolngreen Way Encinitas CA 92024",
    "addr:housenumber":"2061",
    "addr:postcode":"92024",
    "addr:street":"Coolngreen Way",
    "iso:country":"US",
    "sg:address":"2061 Coolngreen Way",
    "sg:city":"Encinitas",
    "sg:classifiers":[
        {
            "category":"Professional",
            "subcategory":"Accounting & Tax Preparation",
            "type":"Services"
        }
    ],
    "sg:phone":"+1 760 436 1298",
    "sg:postcode":"92024",
    "sg:province":"CA",
    "sg:tags":[
        "return",
        "filing"
    ],
    "wof:name":"Apara Kohl's Financial Svc",
    "wof:placetype":"venue"
},
  "geometry": {"coordinates":[-117.242543,33.053606],"type":"Point"}
}