{
  "type": "Feature",
  "properties": {
    "addr:full":"72770 Hatch Rd Twentynine Palms CA 92277",
    "addr:postcode":"72770;92277",
    "addr:street":"Hatch Rd",
    "iso:country":"US",
    "sg:address":"72770 Hatch Rd",
    "sg:city":"Twentynine Palms",
    "sg:classifiers":[
        {
            "category":"Education",
            "subcategory":"School",
            "type":"Public Place"
        }
    ],
    "sg:phone":"+1 760 367 7273",
    "sg:postcode":"92277",
    "sg:province":"CA",
    "wof:name":"Monument High School",
    "wof:placetype":"venue"
},
  "geometry": {"coordinates":[-116.07547,34.128782],"type":"Point"}
}