{
  "type": "Feature",
  "properties": {
    "iso:country":"US",
    "sg:address":"7446 Orangewood Ave",
    "sg:city":"Stanton",
    "sg:classifiers":[
        {
            "category":"Building & Trades",
            "subcategory":"Construction",
            "type":"Services"
        }
    ],
    "sg:phone":"+1 714 899 1826",
    "sg:postcode":"92841",
    "sg:province":"CA",
    "sg:tags":[
        "painter",
        "contractor"
    ],
    "wof:name":"Angeles Contractor",
    "wof:placetype":"venue"
},
  "geometry": {"coordinates":[-117.99847200000001,33.795619],"type":"Point"}
}