{
  "type": "Feature",
  "properties": {
    "iso:country":"US",
    "sg:address":"23814 President Ave",
    "sg:city":"Harbor City",
    "sg:classifiers":[
        {
            "category":"Shopping",
            "subcategory":"Stationery & Office Supplies",
            "type":"Retail Goods"
        }
    ],
    "sg:phone":"+1 310 539 1911",
    "sg:postcode":"90710",
    "sg:province":"CA",
    "sg:tags":[
        "equipment"
    ],
    "sg:website":"www.calpartitions.com",
    "wof:name":"Cal Partitions",
    "wof:placetype":"venue"
},
  "geometry": {"coordinates":[-118.30500000000001,33.8106],"type":"Point"}
}