{
  "type": "Feature",
  "properties": {
    "iso:country":"US",
    "sg:address":"3400 W Castor St",
    "sg:city":"Santa Ana",
    "sg:classifiers":[
        {
            "category":"Manufacturing",
            "subcategory":"Metals",
            "type":"Manufacturing & Wholesale Goods"
        }
    ],
    "sg:phone":"+1 714 556 6060",
    "sg:postcode":"92704",
    "sg:province":"CA",
    "sg:tags":[
        "fabricator",
        "sheet"
    ],
    "wof:name":"Alco Metal Fab",
    "wof:placetype":"venue"
},
  "geometry": {"coordinates":[-117.913573,33.721904],"type":"Point"}
}