{
  "type": "Feature",
  "properties": {
    "addr:full":"25040 Hesperian Blvd Hayward CA 94545",
    "addr:housenumber":"25040",
    "addr:postcode":"94545",
    "addr:street":"Hesperian Blvd",
    "iso:country":"US",
    "sg:address":"25040 Hesperian Blvd",
    "sg:city":"Hayward",
    "sg:classifiers":[
        {
            "category":"Restaurant",
            "type":"Food & Drink"
        }
    ],
    "sg:menulink":"http://www.allmenus.com/ca/hayward/150516-subway/menu/",
    "sg:phone":"+1 510 783 7827",
    "sg:postcode":"94545",
    "sg:province":"CA",
    "sg:tags":[
        "american",
        "sandwich"
    ],
    "wof:name":"Subway",
    "wof:placetype":"venue"
},
  "geometry": {"coordinates":[-122.104911,37.644501],"type":"Point"}
}