{
  "type": "Feature",
  "properties": {
    "addr:full":"4509 Tompkins Ave Oakland CA 94619",
    "addr:housenumber":"4509",
    "addr:postcode":"94619",
    "addr:street":"Tompkins Ave",
    "iso:country":"US",
    "sg:address":"4509 Tompkins Ave",
    "sg:city":"Oakland",
    "sg:classifiers":[
        {
            "category":"Education",
            "subcategory":"Preschool",
            "type":"Public Place"
        }
    ],
    "sg:phone":"+1 510 482 9614",
    "sg:postcode":"94619",
    "sg:province":"CA",
    "sg:website":"www.narniaps.com",
    "wof:name":"Narnia Preschool",
    "wof:placetype":"venue"
},
  "geometry": {"coordinates":[-122.186211,37.78936],"type":"Point"}
}