{
  "type": "Feature",
  "properties": {
    "addr:full":"1662 Manor Blvd San Leandro CA 94579",
    "addr:housenumber":"1662",
    "addr:postcode":"94579",
    "addr:street":"Manor Blvd",
    "iso:country":"US",
    "sg:address":"1662 Manor Blvd",
    "sg:city":"San Leandro",
    "sg:classifiers":[
        {
            "category":"Place Of Worship",
            "subcategory":"Church",
            "type":"Public Place"
        }
    ],
    "sg:phone":"+1 510 351 5244",
    "sg:postcode":"94579",
    "sg:province":"CA",
    "wof:name":"St. Felicitas Church",
    "wof:placetype":"venue"
},
  "geometry": {"coordinates":[-122.158997,37.6912],"type":"Point"}
}