{
  "type": "Feature",
  "properties": {
    "iso:country":"US",
    "sg:address":"966 Borden Villa Dr",
    "sg:city":"Santa Rosa",
    "sg:classifiers":[
        {
            "category":"Building & Trades",
            "subcategory":"Cleaning & Sanitation",
            "type":"Services"
        }
    ],
    "sg:phone":"+1 707 542 0899",
    "sg:postcode":"95401",
    "sg:province":"CA",
    "sg:tags":[
        "janitor"
    ],
    "wof:name":"Affordable Building Mntnc",
    "wof:placetype":"venue"
},
  "geometry": {"coordinates":[-122.743928,38.443767],"type":"Point"}
}