{
  "type": "Feature",
  "properties": {
    "iso:country":"US",
    "sg:address":"10770 Donner Pass Rd",
    "sg:city":"Truckee",
    "sg:classifiers":[
        {
            "category":"Personal",
            "subcategory":"Nail Salon",
            "type":"Services"
        }
    ],
    "sg:phone":"+1 530 550 7561",
    "sg:postcode":"96161",
    "sg:province":"CA",
    "wof:name":"T & T Nails",
    "wof:placetype":"venue"
},
  "geometry": {"coordinates":[-120.196709,39.32658],"type":"Point"}
}