{
  "type": "Feature",
  "properties": {
    "iso:country":"US",
    "sg:address":"11516 Wimbley Ct",
    "sg:city":"Cerritos",
    "sg:classifiers":[
        {
            "category":"Insurance",
            "subcategory":"Health Insurance",
            "type":"Services"
        }
    ],
    "sg:phone":"+1 562 860 1477",
    "sg:postcode":"90703",
    "sg:province":"CA",
    "sg:tags":[
        "market"
    ],
    "wof:name":"Herbalife Independent Distributor Diane Diyorio",
    "wof:placetype":"venue"
},
  "geometry": {"coordinates":[-118.087997,33.8792],"type":"Point"}
}