{
  "type": "Feature",
  "properties": {
    "iso:country":"US",
    "sg:address":"8802 Tyler St",
    "sg:city":"Spring Valley",
    "sg:classifiers":[
        {
            "category":"Manufacturing",
            "subcategory":"Metals",
            "type":"Manufacturing & Wholesale Goods"
        }
    ],
    "sg:phone":"+1 619 465 5200",
    "sg:postcode":"91977",
    "sg:province":"CA",
    "wof:name":"Laserworks of Art",
    "wof:placetype":"venue"
},
  "geometry": {"coordinates":[-117.006642,32.73121],"type":"Point"}
}