{
  "type": "Feature",
  "properties": {
    "addr:full":"1131 N Vermont Ave Los Angeles CA 90029",
    "addr:housenumber":"1131",
    "addr:postcode":"90029",
    "addr:street":"N Vermont Ave",
    "iso:country":"US",
    "sg:address":"1131 N Vermont Ave",
    "sg:city":"Los Angeles",
    "sg:classifiers":[
        {
            "category":"Health Services",
            "subcategory":"Medical Lab",
            "type":"Services"
        }
    ],
    "sg:phone":"+1 323 666 2047",
    "sg:postcode":"90029",
    "sg:province":"CA",
    "sg:tags":[
        "laboratory"
    ],
    "wof:name":"Vermont Diagnostic",
    "wof:placetype":"venue"
},
  "geometry": {"coordinates":[-118.291814,34.091884],"type":"Point"}
}