{
  "type": "Feature",
  "properties": {
    "iso:country":"US",
    "sg:address":"199 Cirby Way",
    "sg:city":"Roseville",
    "sg:classifiers":[
        {
            "category":"Wholesale",
            "subcategory":"Machinery & Supplies",
            "type":"Manufacturing & Wholesale Goods"
        }
    ],
    "sg:phone":"+1 916 784 3363",
    "sg:postcode":"95678",
    "sg:province":"CA",
    "sg:tags":[
        "equipment",
        "welding"
    ],
    "wof:name":"Airgas Of California & Nevada",
    "wof:placetype":"venue"
},
  "geometry": {"coordinates":[-121.30282200000001,38.729274],"type":"Point"}
}