{
  "type": "Feature",
  "properties": {
    "addr:full":"520 E Palmdale Blvd Palmdale CA 93550",
    "addr:housenumber":"520",
    "addr:postcode":"ca 93550",
    "addr:street":"E Palmdale Blvd",
    "iso:country":"US",
    "sg:address":"520 E Palmdale Blvd",
    "sg:city":"Palmdale",
    "sg:classifiers":[
        {
            "category":"Real Estate",
            "subcategory":"Real Estate Agent",
            "type":"Services"
        }
    ],
    "sg:phone":"+1 661 273 4374",
    "sg:postcode":"93550",
    "sg:province":"CA",
    "wof:name":"Land Inc AV",
    "wof:placetype":"venue"
},
  "geometry": {"coordinates":[-118.12047699999999,34.579603],"type":"Point"}
}