{
  "type": "Feature",
  "properties": {
    "iso:country":"US",
    "sg:address":"17961 Sky Park Cir",
    "sg:city":"Irvine",
    "sg:classifiers":[
        {
            "category":"Education",
            "subcategory":"Dance Studio",
            "type":"Public Place"
        }
    ],
    "sg:phone":"+1 949 250 3332",
    "sg:postcode":"92614",
    "sg:province":"CA",
    "sg:tags":[
        "instruction",
        "dancing"
    ],
    "wof:name":"Atomic Dance Ctr",
    "wof:placetype":"venue"
},
  "geometry": {"coordinates":[-117.859228,33.689036],"type":"Point"}
}