{
  "type": "Feature",
  "properties": {
    "addr:full":"6433 Moss Ln Paradise CA 95969",
    "addr:postcode":"6433;95969",
    "addr:street":"Moss Ln",
    "iso:country":"US",
    "sg:address":"6433 Moss Ln",
    "sg:city":"Paradise",
    "sg:classifiers":[
        {
            "category":"Building & Trades",
            "subcategory":"Plumbing",
            "type":"Services"
        }
    ],
    "sg:phone":"+1 530 345 5003",
    "sg:postcode":"95969",
    "sg:province":"CA",
    "sg:tags":[
        "heating",
        "contractor"
    ],
    "wof:name":"Goodman Services",
    "wof:placetype":"venue"
},
  "geometry": {"coordinates":[-121.59607800000001,39.778297],"type":"Point"}
}