{
  "type": "Feature",
  "properties": {
    "iso:country":"US",
    "sg:address":"3921 24th St",
    "sg:city":"San Francisco",
    "sg:classifiers":[
        {
            "category":"Building & Trades",
            "subcategory":"Plumbing",
            "type":"Services"
        }
    ],
    "sg:phone":"+1 415 683 7677",
    "sg:postcode":"94114",
    "sg:province":"CA",
    "wof:name":"Plumbing Emergency-Sunset District",
    "wof:placetype":"venue"
},
  "geometry": {"coordinates":[-122.43010700000001,37.751398],"type":"Point"}
}