{
  "type": "Feature",
  "properties": {
    "addr:full":"923 Laguna St Santa Barbara CA 93101",
    "addr:housenumber":"923",
    "addr:postcode":"93101",
    "addr:street":"Laguna St",
    "iso:country":"US",
    "sg:address":"923 Laguna St",
    "sg:city":"Santa Barbara",
    "sg:classifiers":[
        {
            "category":"Professional",
            "type":"Services"
        }
    ],
    "sg:phone":"+1 805 560 8620",
    "sg:postcode":"93101",
    "sg:province":"CA",
    "sg:tags":[
        "establishment"
    ],
    "wof:name":"Cameron Associates",
    "wof:placetype":"venue"
},
  "geometry": {"coordinates":[-119.69715600000001,34.42545],"type":"Point"}
}