{
  "type": "Feature",
  "properties": {
    "iso:country":"US",
    "sg:address":"415 Summerhill Ter",
    "sg:city":"Alpine",
    "sg:classifiers":[
        {
            "category":"Professional",
            "subcategory":"Secretarial Services",
            "type":"Services"
        },
        {
            "category":"Professional",
            "subcategory":"Employment Agencies",
            "type":"Services"
        }
    ],
    "sg:phone":"+1 619 659 0438",
    "sg:postcode":"91901",
    "sg:province":"CA",
    "sg:tags":[
        "typing"
    ],
    "wof:name":"R X Traznscription",
    "wof:placetype":"venue"
},
  "geometry": {"coordinates":[-116.80736,32.839055],"type":"Point"}
}