{
  "type": "Feature",
  "properties": {
    "iso:country":"US",
    "sg:address":"901 Sneath Ln",
    "sg:city":"San Bruno",
    "sg:classifiers":[
        {
            "category":"Education",
            "subcategory":"School",
            "type":"Public Place"
        }
    ],
    "sg:phone":"+1 650 589 3865",
    "sg:postcode":"94066",
    "sg:province":"CA",
    "wof:name":"Pillar Education",
    "wof:placetype":"venue"
},
  "geometry": {"coordinates":[-122.423501,37.635534],"type":"Point"}
}