{
  "type": "Feature",
  "properties": {
    "addr:full":"2777 Alvarado St San Leandro CA 94577",
    "addr:housenumber":"2777",
    "addr:postcode":"94577",
    "addr:street":"Alvarado St",
    "iso:country":"US",
    "sg:address":"2777 Alvarado St",
    "sg:city":"San Leandro",
    "sg:classifiers":[
        {
            "category":"Professional",
            "subcategory":"Lawyer & Legal Services",
            "type":"Services"
        }
    ],
    "sg:phone":"+1 510 351 5345",
    "sg:postcode":"94577",
    "sg:province":"CA",
    "wof:name":"Brillet Vonnah Law Office",
    "wof:placetype":"venue"
},
  "geometry": {"coordinates":[-122.154228,37.708348],"type":"Point"}
}