{
  "type": "Feature",
  "properties": {
    "addr:full":"3901 1/2 W Olympic Blvd Los Angeles CA 90019",
    "addr:housenumber":"3901 1 / 2",
    "addr:postcode":"90019",
    "addr:street":"W Olympic Blvd",
    "iso:country":"US",
    "sg:address":"3901 1/2 W Olympic Blvd",
    "sg:city":"Los Angeles",
    "sg:classifiers":[
        {
            "category":"Restaurant",
            "type":"Food & Drink"
        }
    ],
    "sg:phone":"+1 323 935 3356",
    "sg:postcode":"90019",
    "sg:province":"CA",
    "sg:tags":[
        "korean"
    ],
    "wof:name":"Song Jung",
    "wof:placetype":"venue"
},
  "geometry": {"coordinates":[-118.31961099999999,34.053712],"type":"Point"}
}