{
  "type": "Feature",
  "properties": {
    "iso:country":"US",
    "sg:address":"2508 Ventura St",
    "sg:city":"Fresno",
    "sg:classifiers":[
        {
            "category":"Personal",
            "subcategory":"Beauty Salon",
            "type":"Services"
        }
    ],
    "sg:phone":"+1 559 445 9400",
    "sg:postcode":"93721",
    "sg:province":"CA",
    "wof:name":"Style-A-Date",
    "wof:placetype":"venue"
},
  "geometry": {"coordinates":[-119.78057699999999,36.733599],"type":"Point"}
}