{
  "type": "Feature",
  "properties": {
    "addr:full":"26382 Cll Rolando San Juan Cpstrno CA 92675",
    "addr:postcode":"26382;92675",
    "addr:street":"Cll;Juan Cpstrno",
    "iso:country":"US",
    "sg:address":"26382 Cll Rolando",
    "sg:city":"San Juan Cpstrno",
    "sg:classifiers":[
        {
            "category":"Freight",
            "type":"Transportation"
        }
    ],
    "sg:phone":"+1 949 240 0174",
    "sg:postcode":"92675",
    "sg:province":"CA",
    "sg:tags":[
        "commercial",
        "storage"
    ],
    "wof:name":"Capistrano Properties Slf Stge",
    "wof:placetype":"venue"
},
  "geometry": {"coordinates":[-117.669881,33.491092],"type":"Point"}
}