{
  "type": "Feature",
  "properties": {
    "iso:country":"US",
    "sg:address":"6915 Langdon Ave",
    "sg:city":"Van Nuys",
    "sg:classifiers":[
        {
            "category":"Building & Trades",
            "subcategory":"Plumbing",
            "type":"Services"
        }
    ],
    "sg:phone":"+1 818 786 3787",
    "sg:postcode":"91406",
    "sg:province":"CA",
    "sg:tags":[
        "plumbing",
        "contractor"
    ],
    "wof:name":"T & T Plumbing",
    "wof:placetype":"venue"
},
  "geometry": {"coordinates":[-118.46955,34.196612],"type":"Point"}
}