{
  "type": "Feature",
  "properties": {
    "iso:country":"US",
    "sg:address":"2421 Encinal Ave Ste A",
    "sg:city":"Alameda",
    "sg:classifiers":[
        {
            "category":"Health Services",
            "subcategory":"Doctor",
            "type":"Services"
        }
    ],
    "sg:phone":"+1 510 865 1996",
    "sg:postcode":"94501",
    "sg:province":"CA",
    "sg:tags":[
        "surgeon",
        "oral"
    ],
    "wof:name":"Bui Thuy DDS",
    "wof:placetype":"venue"
},
  "geometry": {"coordinates":[-122.24400300000001,37.762402],"type":"Point"}
}