{
  "type": "Feature",
  "properties": {
    "addr:full":"13408 Burton St Van Nuys CA 91402",
    "addr:housenumber":"13408",
    "addr:postcode":"91402",
    "addr:street":"Burton St",
    "iso:country":"US",
    "sg:address":"13408 Burton St",
    "sg:city":"Van Nuys",
    "sg:classifiers":[
        {
            "category":"Organizations",
            "subcategory":"Non-profit Organization",
            "type":"Services"
        }
    ],
    "sg:phone":"+1 818 997 9481",
    "sg:postcode":"91402",
    "sg:province":"CA",
    "sg:tags":[
        "information",
        "alcoholism",
        "treatment"
    ],
    "wof:name":"Serenity Retreat",
    "wof:placetype":"venue"
},
  "geometry": {"coordinates":[-118.424582,34.220653],"type":"Point"}
}