{
  "type": "Feature",
  "properties": {
    "addr:full":"118 Ross St San Rafael CA 94901",
    "addr:housenumber":"118",
    "addr:postcode":"94901",
    "addr:street":"Ross St",
    "iso:country":"US",
    "sg:address":"118 Ross St",
    "sg:city":"San Rafael",
    "sg:classifiers":[
        {
            "category":"Professional",
            "type":"Services"
        }
    ],
    "sg:phone":"+1 415 259 0844",
    "sg:postcode":"94901",
    "sg:province":"CA",
    "wof:name":"Sacred Grove Healing Arts",
    "wof:placetype":"venue"
},
  "geometry": {"coordinates":[-122.536283,37.969069],"type":"Point"}
}