{
  "type": "Feature",
  "properties": {
    "addr:full":"650 Auburn Folsom Rd Auburn CA 95603",
    "addr:housenumber":"650",
    "addr:postcode":"ca 95603",
    "addr:street":"Auburn Folsom Rd",
    "iso:country":"US",
    "sg:address":"650 Auburn Folsom Rd",
    "sg:city":"Auburn",
    "sg:classifiers":[
        {
            "category":"Health Services",
            "subcategory":"Doctor",
            "type":"Services"
        }
    ],
    "sg:phone":"+1 530 823 5141",
    "sg:postcode":"95603",
    "sg:province":"CA",
    "sg:tags":[
        "dentist"
    ],
    "wof:name":"Maidu Vista Dental Care",
    "wof:placetype":"venue"
},
  "geometry": {"coordinates":[-121.079883,38.879971],"type":"Point"}
}