{
  "type": "Feature",
  "properties": {
    "iso:country":"US",
    "sg:address":"7709 Somerset Blvd",
    "sg:city":"Paramount",
    "sg:classifiers":[
        {
            "category":"Professional",
            "subcategory":"Business Services",
            "type":"Services"
        }
    ],
    "sg:phone":"+1 562 630 2787",
    "sg:postcode":"90723",
    "sg:province":"CA",
    "sg:tags":[
        "import",
        "importer",
        "representative"
    ],
    "wof:name":"Highland Enterprise Inc",
    "wof:placetype":"venue"
},
  "geometry": {"coordinates":[-118.165208,33.896453],"type":"Point"}
}