{
  "type": "Feature",
  "properties": {
    "iso:country":"US",
    "sg:address":"2188 Peralta Blvd Ste A",
    "sg:city":"Fremont",
    "sg:classifiers":[
        {
            "category":"Insurance",
            "subcategory":"Insurance Agent",
            "type":"Services"
        },
        {
            "category":"Insurance",
            "subcategory":"Hazard Insurance",
            "type":"Services"
        },
        {
            "category":"Insurance",
            "subcategory":"Title Insurance",
            "type":"Services"
        },
        {
            "category":"Insurance",
            "subcategory":"Health Insurance",
            "type":"Services"
        },
        {
            "category":"Insurance",
            "subcategory":"Life Insurance",
            "type":"Services"
        }
    ],
    "sg:phone":"+1 510 791 6911",
    "sg:postcode":"94536",
    "sg:province":"CA",
    "sg:tags":[
        "business",
        "auto",
        "commercial",
        "homeowner",
        "benefit",
        "employee"
    ],
    "sg:website":"http://www.farmersagent.com/mbromley",
    "wof:name":"Mark Bromley - Farmers Insurance",
    "wof:placetype":"venue"
},
  "geometry": {"coordinates":[-121.989574,37.562339],"type":"Point"}
}