{
  "type": "Feature",
  "properties": {
    "iso:country":"US",
    "sg:address":"234 E Colorado Blvd",
    "sg:city":"Pasadena",
    "sg:classifiers":[
        {
            "category":"Professional",
            "subcategory":"Business Services",
            "type":"Services"
        }
    ],
    "sg:phone":"+1 626 449 6222",
    "sg:postcode":"91106",
    "sg:province":"CA",
    "sg:tags":[
        "interior",
        "consultant",
        "design",
        "decorator"
    ],
    "sg:website":"www.cityspaces.com",
    "wof:name":"City Spaces Inc",
    "wof:placetype":"venue"
},
  "geometry": {"coordinates":[-118.14450100000001,34.145749],"type":"Point"}
}