{
  "type": "Feature",
  "properties": {
    "addr:full":"4022 Papillon Ter Fremont CA 94538",
    "addr:housenumber":"4022",
    "addr:postcode":"94538",
    "addr:street":"Papillon Ter",
    "iso:country":"US",
    "sg:address":"4022 Papillon Ter",
    "sg:city":"Fremont",
    "sg:classifiers":[
        {
            "category":"Real Estate",
            "subcategory":"Real Estate Operator",
            "type":"Services"
        }
    ],
    "sg:phone":"+1 510 490 7833",
    "sg:postcode":"94538",
    "sg:province":"CA",
    "sg:tags":[
        "apartment"
    ],
    "wof:name":"Villas Papillon",
    "wof:placetype":"venue"
},
  "geometry": {"coordinates":[-121.951993,37.512262],"type":"Point"}
}