{
  "type": "Feature",
  "properties": {
    "iso:country":"US",
    "sg:address":"640 E Redlands Blvd",
    "sg:city":"Redlands",
    "sg:classifiers":[
        {
            "category":"Shopping",
            "subcategory":"Department Store",
            "type":"Retail Goods"
        }
    ],
    "sg:phone":"+1 909 307 8584",
    "sg:postcode":"92373",
    "sg:province":"CA",
    "sg:tags":[
        "shop"
    ],
    "wof:name":"What A Bargain",
    "wof:placetype":"venue"
},
  "geometry": {"coordinates":[-117.175265,34.054849],"type":"Point"}
}