{
  "type": "Feature",
  "properties": {
    "iso:country":"US",
    "sg:address":"325 Fallon St",
    "sg:city":"Oakland",
    "sg:classifiers":[
        {
            "category":"Manufacturing",
            "subcategory":"Food",
            "type":"Manufacturing & Wholesale Goods"
        }
    ],
    "sg:phone":"+1 510 763 1737",
    "sg:postcode":"94607",
    "sg:province":"CA",
    "sg:tags":[
        "noodle"
    ],
    "wof:name":"China Noodle Co",
    "wof:placetype":"venue"
},
  "geometry": {"coordinates":[-122.266042,37.79383],"type":"Point"}
}