{
  "type": "Feature",
  "properties": {
    "iso:country":"US",
    "sg:address":"23772 Lagarto",
    "sg:city":"Mission Viejo",
    "sg:classifiers":[
        {
            "category":"Insurance",
            "subcategory":"Insurance Agent",
            "type":"Services"
        }
    ],
    "sg:phone":"+1 949 581 8921",
    "sg:postcode":"92691",
    "sg:province":"CA",
    "wof:name":"Capital Enterprise",
    "wof:placetype":"venue"
},
  "geometry": {"coordinates":[-117.652857,33.616959],"type":"Point"}
}