{
  "type": "Feature",
  "properties": {
    "addr:full":"1176 Menlo Dr Altadena CA 91001",
    "addr:housenumber":"1176",
    "addr:postcode":"91001",
    "addr:street":"Menlo Dr",
    "iso:country":"US",
    "sg:address":"1176 Menlo Dr",
    "sg:city":"Altadena",
    "sg:classifiers":[
        {
            "category":"Manufacturing",
            "subcategory":"Jewelry",
            "type":"Manufacturing & Wholesale Goods"
        }
    ],
    "sg:phone":"+1 626 797 3992",
    "sg:postcode":"91001",
    "sg:province":"CA",
    "sg:tags":[
        "precious",
        "metal",
        "mfg"
    ],
    "wof:name":"Neck Art By Annette",
    "wof:placetype":"venue"
},
  "geometry": {"coordinates":[-118.126761,34.194843],"type":"Point"}
}