{
  "type": "Feature",
  "properties": {
    "iso:country":"US",
    "sg:address":"3604 Laredo St",
    "sg:city":"Carlsbad",
    "sg:classifiers":[
        {
            "category":"Professional",
            "type":"Services"
        }
    ],
    "sg:phone":"+1 760 729 1955",
    "sg:postcode":"92010",
    "sg:province":"CA",
    "wof:name":"All American Table Co",
    "wof:placetype":"venue"
},
  "geometry": {"coordinates":[-117.308708,33.166002],"type":"Point"}
}