{
  "type": "Feature",
  "properties": {
    "addr:full":"1440 7th St Sanger CA 93657",
    "addr:housenumber":"1440",
    "addr:postcode":"ca 93657",
    "addr:street":"7Th St",
    "iso:country":"US",
    "sg:address":"1440 7th St",
    "sg:city":"Sanger",
    "sg:classifiers":[
        {
            "category":"Professional",
            "subcategory":"Accounting & Tax Preparation",
            "type":"Services"
        }
    ],
    "sg:phone":"+1 559 875 1578",
    "sg:postcode":"93657",
    "sg:province":"CA",
    "sg:tags":[
        "bookkeeping",
        "general"
    ],
    "wof:name":"Josie Isquierdo Bookkeeping",
    "wof:placetype":"venue"
},
  "geometry": {"coordinates":[-119.558171,36.706327],"type":"Point"}
}