{
  "type": "Feature",
  "properties": {
    "iso:country":"US",
    "sg:address":"853 S Glendora Ave",
    "sg:city":"West Covina",
    "sg:classifiers":[
        {
            "category":"Banks & Credit Unions",
            "subcategory":"Bank",
            "type":"Services"
        }
    ],
    "sg:phone":"+1 626 851 3399",
    "sg:postcode":"91790",
    "sg:province":"CA",
    "sg:tags":[
        "loan",
        "real estate"
    ],
    "wof:name":"Metroworld Financial Corp",
    "wof:placetype":"venue"
},
  "geometry": {"coordinates":[-117.933992,34.059556],"type":"Point"}
}