{
  "type": "Feature",
  "properties": {
    "addr:full":"122 E Betteravia Rd Santa Maria CA 93454",
    "addr:housenumber":"122",
    "addr:postcode":"93454",
    "addr:street":"E Betteravia Rd",
    "iso:country":"US",
    "sg:address":"122 E Betteravia Rd",
    "sg:city":"Santa Maria",
    "sg:classifiers":[
        {
            "category":"Banks & Credit Unions",
            "subcategory":"Bank",
            "type":"Services"
        }
    ],
    "sg:phone":"+1 805 928 7520",
    "sg:postcode":"93454",
    "sg:province":"CA",
    "sg:tags":[
        "loan",
        "real estate"
    ],
    "wof:name":"R P Acquisitions & Dev Corp",
    "wof:placetype":"venue"
},
  "geometry": {"coordinates":[-120.43162100000001,34.922126],"type":"Point"}
}