{
  "type": "Feature",
  "properties": {
    "iso:country":"US",
    "sg:address":"18614 Delano St",
    "sg:city":"Reseda",
    "sg:classifiers":[
        {
            "category":"Professional",
            "type":"Services"
        }
    ],
    "sg:phone":"+1 818 776 9803",
    "sg:postcode":"91335",
    "sg:province":"CA",
    "wof:name":"May A&A Inc",
    "wof:placetype":"venue"
},
  "geometry": {"coordinates":[-118.53911600000001,34.182789],"type":"Point"}
}