{
  "type": "Feature",
  "properties": {
    "iso:country":"US",
    "sg:address":"12690 Kennedy Flat Rd",
    "sg:city":"Jackson",
    "sg:classifiers":[
        {
            "category":"Wholesale",
            "subcategory":"Construction Materials",
            "type":"Manufacturing & Wholesale Goods"
        },
        {
            "category":"Wholesale",
            "subcategory":"Machinery & Supplies",
            "type":"Manufacturing & Wholesale Goods"
        },
        {
            "category":"Home & Garden",
            "subcategory":"Building Materials",
            "type":"Retail Goods"
        },
        {
            "category":"Manufacturing",
            "subcategory":"Tools & Machinery",
            "type":"Manufacturing & Wholesale Goods"
        },
        {
            "category":"Wholesale",
            "subcategory":"Home Furnishings",
            "type":"Manufacturing & Wholesale Goods"
        },
        {
            "category":"Professional",
            "subcategory":"Engineering",
            "type":"Services"
        }
    ],
    "sg:phone":"+1 209 223 4545",
    "sg:postcode":"95642",
    "sg:province":"CA",
    "sg:tags":[
        "heater",
        "valve",
        "fixture",
        "system",
        "water",
        "equipment",
        "part",
        "plumbing",
        "fixtures",
        "supplies-wholesale",
        "air conditioning",
        "manufacturer"
    ],
    "sg:website":"http://www-ferguson-com.netsolads.com/index.shtml?_nsag=39482",
    "wof:name":"Ferguson",
    "wof:placetype":"venue"
},
  "geometry": {"coordinates":[-120.790345,38.364943],"type":"Point"}
}