{
  "type": "Feature",
  "properties": {
    "iso:country":"US",
    "sg:address":"12104 Park St",
    "sg:city":"Cerritos",
    "sg:classifiers":[
        {
            "category":"Sports & Exercise",
            "subcategory":"Golf",
            "type":"Entertainment"
        }
    ],
    "sg:phone":"+1 562 407 3344",
    "sg:postcode":"90703",
    "sg:province":"CA",
    "sg:website":"www.evertan.com",
    "wof:name":"Evertan Golf International",
    "wof:placetype":"venue"
},
  "geometry": {"coordinates":[-118.073997,33.878101],"type":"Point"}
}