{
  "type": "Feature",
  "properties": {
    "addr:full":"1400 Radio Rd Redwood City CA 94065",
    "addr:housenumber":"1400",
    "addr:postcode":"94065",
    "addr:street":"Radio Rd",
    "iso:country":"US",
    "sg:address":"1400 Radio Rd",
    "sg:city":"Redwood City",
    "sg:classifiers":[
        {
            "category":"Professional",
            "subcategory":"Engineering",
            "type":"Services"
        }
    ],
    "sg:phone":"+1 650 591 7121",
    "sg:postcode":"94065",
    "sg:province":"CA",
    "sg:tags":[
        "water",
        "treatment",
        "engineer"
    ],
    "wof:name":"South Bayside Systems Auth",
    "wof:placetype":"venue"
},
  "geometry": {"coordinates":[-122.226437,37.545307],"type":"Point"}
}