{
  "type": "Feature",
  "properties": {
    "iso:country":"US",
    "sg:address":"1601 New Stine Rd Ste 280",
    "sg:city":"Bakersfield",
    "sg:classifiers":[
        {
            "category":"Professional",
            "subcategory":"Engineering",
            "type":"Services"
        },
        {
            "category":"Real Estate",
            "subcategory":"Architect",
            "type":"Services"
        }
    ],
    "sg:phone":"+1 661 397 4377",
    "sg:postcode":"93309",
    "sg:province":"CA",
    "sg:tags":[
        "architects'",
        "specification",
        "builders'",
        "construction",
        "architectural",
        "engineer"
    ],
    "sg:website":"http://www.scarchitect.com",
    "wof:name":"Scarchitect, Inc.",
    "wof:placetype":"venue"
},
  "geometry": {"coordinates":[-119.06121899999999,35.339498],"type":"Point"}
}