{
  "type": "Feature",
  "properties": {
    "iso:country":"US",
    "sg:address":"40820 Winchester Rd",
    "sg:city":"Temecula",
    "sg:classifiers":[
        {
            "category":"Shopping",
            "subcategory":"Beauty & Cosmetics",
            "type":"Retail Goods"
        }
    ],
    "sg:phone":"+1 951 296 5090",
    "sg:postcode":"92591",
    "sg:province":"CA",
    "sg:tags":[
        "perfume",
        "salons-equipment",
        "supply"
    ],
    "wof:name":"Smile Rejuvenation Cosmetic Teeth Whiting",
    "wof:placetype":"venue"
},
  "geometry": {"coordinates":[-117.157971,33.52626],"type":"Point"}
}