{
  "type": "Feature",
  "properties": {
    "addr:full":"4809 W Ave L Quartz Hill CA 93536",
    "addr:housenumber":"4809",
    "addr:postcode":"93536",
    "addr:street":"W Ave L Quartz Hill",
    "iso:country":"US",
    "sg:address":"4809 W Ave L",
    "sg:city":"Quartz Hill",
    "sg:classifiers":[
        {
            "category":"Personal",
            "subcategory":"Barber",
            "type":"Services"
        }
    ],
    "sg:phone":"+1 661 942 7848",
    "sg:postcode":"93536",
    "sg:province":"CA",
    "wof:name":"Scuttlemug Hair Salon",
    "wof:placetype":"venue"
},
  "geometry": {"coordinates":[-118.21647,34.66033],"type":"Point"}
}