{
  "type": "Feature",
  "properties": {
    "iso:country":"US",
    "sg:address":"225 Santa Monica Blvd",
    "sg:city":"Santa Monica",
    "sg:classifiers":[
        {
            "category":"Restaurant",
            "type":"Food & Drink"
        }
    ],
    "sg:phone":"+1 310 394 3800",
    "sg:postcode":"90401",
    "sg:province":"CA",
    "wof:name":"California Crisp",
    "wof:placetype":"venue"
},
  "geometry": {"coordinates":[-118.496348,34.015534],"type":"Point"}
}