{
  "type": "Feature",
  "properties": {
    "iso:country":"US",
    "sg:address":"765 C Ave",
    "sg:city":"Coronado",
    "sg:classifiers":[
        {
            "category":"Real Estate",
            "subcategory":"Architect",
            "type":"Services"
        }
    ],
    "sg:phone":"+1 619 435 5005",
    "sg:postcode":"92118",
    "sg:province":"CA",
    "wof:name":"Ackerman Group-Architecture",
    "wof:placetype":"venue"
},
  "geometry": {"coordinates":[-117.176429,32.689151],"type":"Point"}
}