{
  "type": "Feature",
  "properties": {
    "addr:full":"12408 Kentucky Derby Ct Etiwanda CA 91739",
    "addr:housenumber":"12408",
    "addr:postcode":"91739",
    "addr:street":"Kentucky Derby Ct",
    "iso:country":"US",
    "sg:address":"12408 Kentucky Derby Ct",
    "sg:city":"Etiwanda",
    "sg:classifiers":[
        {
            "category":"Professional",
            "type":"Services"
        }
    ],
    "sg:phone":"+1 909 646 9065",
    "sg:postcode":"91739",
    "sg:province":"CA",
    "sg:tags":[
        "establishment"
    ],
    "wof:name":"National Offices Support",
    "wof:placetype":"venue"
},
  "geometry": {"coordinates":[-117.53313799999999,34.14194],"type":"Point"}
}