{
  "type": "Feature",
  "properties": {
    "iso:country":"US",
    "sg:address":"720 S Stimson Ave",
    "sg:city":"City Of Industry",
    "sg:classifiers":[
        {
            "category":"Wholesale",
            "subcategory":"Medical Equipment & Supplies",
            "type":"Manufacturing & Wholesale Goods"
        }
    ],
    "sg:phone":"+1 626 934 9819",
    "sg:postcode":"91745",
    "sg:province":"CA",
    "sg:tags":[
        "sun",
        "goggles",
        "sunglasses"
    ],
    "wof:name":"Fairy World Inc",
    "wof:placetype":"venue"
},
  "geometry": {"coordinates":[-117.953507,34.014011],"type":"Point"}
}