{
  "type": "Feature",
  "properties": {
    "addr:full":"1048 Verdemar Dr Alameda CA 94502",
    "addr:housenumber":"1048",
    "addr:postcode":"94502",
    "addr:street":"Verdemar Dr",
    "iso:country":"US",
    "sg:address":"1048 Verdemar Dr",
    "sg:city":"Alameda",
    "sg:classifiers":[
        {
            "category":"Shopping",
            "subcategory":"Hobbies, Toys, & Games",
            "type":"Retail Goods"
        }
    ],
    "sg:phone":"+1 510 865 7941",
    "sg:postcode":"94502",
    "sg:province":"CA",
    "wof:name":"Jins Associates",
    "wof:placetype":"venue"
},
  "geometry": {"coordinates":[-122.245465,37.735513],"type":"Point"}
}