{
  "type": "Feature",
  "properties": {
    "addr:full":"16255 Ventura Blvd Encino CA 91436",
    "addr:housenumber":"16255",
    "addr:postcode":"91436",
    "addr:street":"Ventura Blvd",
    "iso:country":"US",
    "sg:address":"16255 Ventura Blvd",
    "sg:city":"Encino",
    "sg:classifiers":[
        {
            "category":"Professional",
            "type":"Services"
        },
        {
            "category":"Professional",
            "subcategory":"Lawyer & Legal Services",
            "type":"Services"
        }
    ],
    "sg:phone":"+1 818 995 0405",
    "sg:postcode":"91436",
    "sg:province":"CA",
    "sg:tags":[
        "arbitration",
        "attorney",
        "family",
        "divorce",
        "assistance",
        "mediation",
        "child",
        "law",
        "custody"
    ],
    "sg:website":"http://www.afamilylawpractice.com",
    "wof:name":"Tinero Rauch And Aharonov A Family Law Practice, LLP",
    "wof:placetype":"venue"
},
  "geometry": {"coordinates":[-118.487071,34.156831],"type":"Point"}
}