{
  "type": "Feature",
  "properties": {
    "iso:country":"US",
    "sg:address":"310 N Rexford St",
    "sg:city":"Colton",
    "sg:classifiers":[
        {
            "category":"Manufacturing",
            "subcategory":"Motor Vehicles & Parts",
            "type":"Manufacturing & Wholesale Goods"
        }
    ],
    "sg:phone":"+1 909 390 1208",
    "sg:postcode":"92324",
    "sg:province":"CA",
    "sg:tags":[
        "equipment",
        "truck"
    ],
    "wof:name":"Transport Components",
    "wof:placetype":"venue"
},
  "geometry": {"coordinates":[-117.355546,34.070691],"type":"Point"}
}