{
  "type": "Feature",
  "properties": {
    "iso:country":"US",
    "sg:address":"2525 N Grand Ave Ste H",
    "sg:city":"Santa Ana",
    "sg:classifiers":[
        {
            "category":"Professional",
            "subcategory":"Computer Services",
            "type":"Services"
        }
    ],
    "sg:phone":"+1 714 363 0006",
    "sg:postcode":"92705",
    "sg:province":"CA",
    "sg:tags":[
        "repair"
    ],
    "wof:name":"Azteca Technology",
    "wof:placetype":"venue"
},
  "geometry": {"coordinates":[-117.852115,33.770892],"type":"Point"}
}