{
  "type": "Feature",
  "properties": {
    "iso:country":"US",
    "sg:address":"26525 Road 407",
    "sg:city":"Raymond",
    "sg:classifiers":[
        {
            "category":"Building & Trades",
            "subcategory":"Electrical",
            "type":"Services"
        }
    ],
    "sg:phone":"+1 559 674 6206",
    "sg:postcode":"93653",
    "sg:province":"CA",
    "sg:tags":[
        "industrial",
        "electrician",
        "electric",
        "contractors-commercial"
    ],
    "wof:name":"Wolf's Electric Company",
    "wof:placetype":"venue"
},
  "geometry": {"coordinates":[-119.899733,37.133854],"type":"Point"}
}