{
  "type": "Feature",
  "properties": {
    "addr:full":"2009 Niles St Bakersfield CA 93305",
    "addr:housenumber":"2009",
    "addr:postcode":"93305",
    "addr:street":"Niles St",
    "iso:country":"US",
    "sg:address":"2009 Niles St",
    "sg:city":"Bakersfield",
    "sg:phone":"+1 661 634 9999",
    "sg:postcode":"93305",
    "sg:province":"CA",
    "wof:name":"Kern County Sherriff Department",
    "wof:placetype":"venue"
},
  "geometry": {"coordinates":[-118.97025499999999,35.377042],"type":"Point"}
}