{
  "type": "Feature",
  "properties": {
    "addr:full":"413 E Washington Blvd Los Angeles CA 90015",
    "addr:housenumber":"413",
    "addr:postcode":"90015",
    "addr:street":"E Washington Blvd",
    "iso:country":"US",
    "sg:address":"413 E Washington Blvd",
    "sg:city":"Los Angeles",
    "sg:classifiers":[
        {
            "category":"Shopping",
            "subcategory":"Clothing, Apparel, & Fashions",
            "type":"Retail Goods"
        }
    ],
    "sg:phone":"+1 213 744 1455",
    "sg:postcode":"90015",
    "sg:province":"CA",
    "sg:tags":[
        "accessory",
        "clothing",
        "women's"
    ],
    "wof:name":"Doo Ho Corp.",
    "wof:placetype":"venue"
},
  "geometry": {"coordinates":[-118.26115900000001,34.029631],"type":"Point"}
}