{
  "type": "Feature",
  "properties": {
    "addr:full":"120 Town and Country Dr Danville CA 94526",
    "addr:housenumber":"120",
    "addr:postcode":"94526",
    "addr:street":"Town And Country Dr",
    "iso:country":"US",
    "sg:address":"120 Town and Country Dr",
    "sg:city":"Danville",
    "sg:classifiers":[
        {
            "category":"Shopping",
            "type":"Retail Goods"
        }
    ],
    "sg:phone":"+1 925 831 8900",
    "sg:postcode":"94526",
    "sg:province":"CA",
    "sg:tags":[
        "miscellaneous",
        "store"
    ],
    "wof:name":"Promag Retail Svc",
    "wof:placetype":"venue"
},
  "geometry": {"coordinates":[-121.998814,37.814143],"type":"Point"}
}