{
  "type": "Feature",
  "properties": {
    "addr:full":"3259 S James Rd Tranquillity CA 93668",
    "addr:housenumber":"3259",
    "addr:postcode":"93668",
    "addr:street":"S James Rd",
    "iso:country":"US",
    "sg:address":"3259 S James Rd",
    "sg:city":"Tranquillity",
    "sg:classifiers":[
        {
            "category":"Wholesale",
            "subcategory":"Machinery & Supplies",
            "type":"Manufacturing & Wholesale Goods"
        }
    ],
    "sg:phone":"+1 559 698 7473",
    "sg:postcode":"93668",
    "sg:province":"CA",
    "sg:tags":[
        "farm",
        "equipment"
    ],
    "wof:name":"Terra Linda Farm",
    "wof:placetype":"venue"
},
  "geometry": {"coordinates":[-120.227648,36.683588],"type":"Point"}
}