{
  "type": "Feature",
  "properties": {
    "iso:country":"US",
    "sg:address":"5220 N Ashley Ln",
    "sg:city":"Stockton",
    "sg:classifiers":[
        {
            "category":"Farming",
            "subcategory":"Crops",
            "type":"Manufacturing & Wholesale Goods"
        }
    ],
    "sg:phone":"+1 209 931 6334",
    "sg:postcode":"95215",
    "sg:province":"CA",
    "sg:tags":[
        "grove",
        "nut",
        "tree"
    ],
    "wof:name":"Dave Rajkovich Inc",
    "wof:placetype":"venue"
},
  "geometry": {"coordinates":[-121.217349,38.010699],"type":"Point"}
}