{
  "type": "Feature",
  "properties": {
    "iso:country":"US",
    "sg:address":"14310 Hawthorne Boulevard",
    "sg:city":"Lawndale",
    "sg:classifiers":[
        {
            "category":"Food & Beverages",
            "subcategory":"Groceries & Convenience Stores",
            "type":"Retail Goods"
        }
    ],
    "sg:phone":"+1 310 331 4558",
    "sg:postcode":"90260",
    "sg:province":"CA",
    "wof:name":"Big Saver Foods",
    "wof:placetype":"venue"
},
  "geometry": {"coordinates":[-118.352492,33.901677],"type":"Point"}
}