{
  "type": "Feature",
  "properties": {
    "iso:country":"US",
    "sg:address":"5592 Lincoln Ave.",
    "sg:city":"Cypress",
    "sg:classifiers":[
        {
            "category":"Retail",
            "subcategory":"Auto Repair",
            "type":"Services"
        },
        {
            "category":"Government",
            "subcategory":"Office",
            "type":"Public Place"
        }
    ],
    "sg:phone":"+1 714 761 1272",
    "sg:postcode":"90630",
    "sg:province":"CA",
    "sg:tags":[
        "smog",
        "check"
    ],
    "sg:website":"www.californiaautocarecypress.com",
    "wof:name":"California Auto Care",
    "wof:placetype":"venue"
},
  "geometry": {"coordinates":[-118.035565,33.831454],"type":"Point"}
}