{
  "type": "Feature",
  "properties": {
    "iso:country":"US",
    "sg:address":"732 N Sierra Way",
    "sg:city":"San Bernardino",
    "sg:classifiers":[
        {
            "category":"Organizations",
            "subcategory":"Community Association",
            "type":"Services"
        }
    ],
    "sg:phone":"+1 909 885 4090",
    "sg:postcode":"92410",
    "sg:province":"CA",
    "sg:tags":[
        "military"
    ],
    "wof:name":"American Legion",
    "wof:placetype":"venue"
},
  "geometry": {"coordinates":[-117.285242,34.112396],"type":"Point"}
}