{
  "type": "Feature",
  "properties": {
    "addr:full":"4162 Culver St Oakland CA 94619",
    "addr:housenumber":"4162",
    "addr:postcode":"94619",
    "addr:street":"Culver St",
    "iso:country":"US",
    "sg:address":"4162 Culver St",
    "sg:city":"Oakland",
    "sg:classifiers":[
        {
            "category":"Shopping",
            "subcategory":"Pets & Pet Supplies",
            "type":"Retail Goods"
        }
    ],
    "sg:phone":"+1 510 759 9622",
    "sg:postcode":"94619",
    "sg:province":"CA",
    "sg:tags":[
        "furnishing",
        "dog",
        "store",
        "cat"
    ],
    "wof:name":"Kennel Select Pet Products",
    "wof:placetype":"venue"
},
  "geometry": {"coordinates":[-122.199848,37.785519],"type":"Point"}
}