{
  "type": "Feature",
  "properties": {
    "addr:full":"11029 Alondra Blvd Norwalk CA 90650",
    "addr:housenumber":"11029",
    "addr:postcode":"90650",
    "addr:street":"Alondra Blvd",
    "iso:country":"US",
    "sg:address":"11029 Alondra Blvd",
    "sg:city":"Norwalk",
    "sg:classifiers":[
        {
            "category":"Shopping",
            "subcategory":"Discount & Variety Stores",
            "type":"Retail Goods"
        }
    ],
    "sg:phone":"+1 562 807 2004",
    "sg:postcode":"90650",
    "sg:province":"CA",
    "sg:tags":[
        "grocery",
        "merchandise"
    ],
    "wof:name":"Kensco Discount Store 4",
    "wof:placetype":"venue"
},
  "geometry": {"coordinates":[-118.098,33.887699],"type":"Point"}
}