{
  "type": "Feature",
  "properties": {
    "iso:country":"US",
    "sg:address":"1810 S Carlos Ave",
    "sg:city":"Ontario",
    "sg:classifiers":[
        {
            "category":"Manufacturing",
            "subcategory":"Paper Products",
            "type":"Manufacturing & Wholesale Goods"
        }
    ],
    "sg:phone":"+1 909 930 3844",
    "sg:postcode":"91761",
    "sg:province":"CA",
    "sg:tags":[
        "packaging",
        "distributor"
    ],
    "wof:name":"Superior Packaging Solutions",
    "wof:placetype":"venue"
},
  "geometry": {"coordinates":[-117.606458,34.038193],"type":"Point"}
}