{
  "type": "Feature",
  "properties": {
    "addr:full":"1300 E Washington St # 6 Colton CA 92324",
    "addr:housenumber":"1300",
    "addr:postcode":"92324",
    "addr:street":"E Washington St # 6",
    "iso:country":"US",
    "sg:address":"1300 E Washington St # 6",
    "sg:city":"Colton",
    "sg:classifiers":[
        {
            "category":"Banks & Credit Unions",
            "subcategory":"Financial Services",
            "type":"Services"
        }
    ],
    "sg:phone":"+1 909 824 7269",
    "sg:postcode":"92324",
    "sg:province":"CA",
    "sg:tags":[
        "cashing",
        "loan",
        "payday",
        "check"
    ],
    "sg:website":"http://www.checkintocash.com",
    "wof:name":"Check Into Cash",
    "wof:placetype":"venue"
},
  "geometry": {"coordinates":[-117.30516799999999,34.04792],"type":"Point"}
}