{
  "type": "Feature",
  "properties": {
    "iso:country":"US",
    "sg:address":"8383 E Quiet Canyon Ct",
    "sg:city":"Anaheim",
    "sg:classifiers":[
        {
            "category":"Landmark",
            "subcategory":"Tourist Information",
            "type":"Public Place"
        },
        {
            "category":"Landmark",
            "subcategory":"Tourist Attraction",
            "type":"Public Place"
        }
    ],
    "sg:phone":"+1 714 280 8216",
    "sg:postcode":"92808",
    "sg:province":"CA",
    "sg:tags":[
        "tour",
        "promoter",
        "tours-operators",
        "sightseeing"
    ],
    "wof:name":"Coastal Dream Vacations",
    "wof:placetype":"venue"
},
  "geometry": {"coordinates":[-117.728899,33.855368],"type":"Point"}
}