{
  "type": "Feature",
  "properties": {
    "iso:country":"US",
    "sg:address":"3654 S Willow Ave",
    "sg:city":"Fresno",
    "sg:classifiers":[
        {
            "category":"Wholesale",
            "subcategory":"Farm Supplies",
            "type":"Manufacturing & Wholesale Goods"
        }
    ],
    "sg:phone":"+1 559 499 2100",
    "sg:postcode":"93725",
    "sg:province":"CA",
    "sg:tags":[
        "chemical",
        "agricultural"
    ],
    "sg:website":"www.montereylawngarden.com",
    "wof:name":"Monterey Agresources",
    "wof:placetype":"venue"
},
  "geometry": {"coordinates":[-119.726815,36.684613],"type":"Point"}
}