{
  "type": "Feature",
  "properties": {
    "addr:full":"7720 Paradise Valley Road San Diego CA 92139",
    "addr:housenumber":"7720",
    "addr:postcode":"92139",
    "addr:street":"Paradise Valley Road",
    "iso:country":"US",
    "sg:address":"7720 Paradise Valley Road",
    "sg:city":"San Diego",
    "sg:classifiers":[
        {
            "category":"Banks & Credit Unions",
            "subcategory":"Financial Services",
            "type":"Services"
        }
    ],
    "sg:phone":"+1 619 472 7171",
    "sg:postcode":"92139",
    "sg:province":"CA",
    "sg:tags":[
        "broker",
        "mortgage"
    ],
    "wof:name":"Ad Valorem Realty",
    "wof:placetype":"venue"
},
  "geometry": {"coordinates":[-117.02750399999999,32.694195],"type":"Point"}
}