{
  "type": "Feature",
  "properties": {
    "addr:full":"1936 Linda Dr Pleasant Hill CA 94523",
    "addr:housenumber":"1936",
    "addr:postcode":"94523",
    "addr:street":"Linda Dr",
    "iso:country":"US",
    "sg:address":"1936 Linda Dr",
    "sg:city":"Pleasant Hill",
    "sg:classifiers":[
        {
            "category":"Shopping",
            "subcategory":"Computers & Home Electronics",
            "type":"Retail Goods"
        }
    ],
    "sg:phone":"+1 925 827 1200",
    "sg:postcode":"94523",
    "sg:province":"CA",
    "sg:tags":[
        "equipment",
        "dealer"
    ],
    "sg:website":"www.crsfbay.com",
    "wof:name":"Computer Renaissance",
    "wof:placetype":"venue"
},
  "geometry": {"coordinates":[-122.06075199999999,37.951934],"type":"Point"}
}