{
  "type": "Feature",
  "properties": {
    "iso:country":"US",
    "sg:address":"1020 29th Street Suite 570 A",
    "sg:city":"Sacramento",
    "sg:classifiers":[
        {
            "category":"Health Services",
            "subcategory":"Doctor",
            "type":"Services"
        }
    ],
    "sg:phone":"+1 916 733 3792",
    "sg:postcode":"95816",
    "sg:province":"CA",
    "sg:tags":[
        "dermatologist"
    ],
    "wof:name":"Haas Ann MD",
    "wof:placetype":"venue"
},
  "geometry": {"coordinates":[-121.46848900000001,38.572798],"type":"Point"}
}