{
  "type": "Feature",
  "properties": {
    "iso:country":"US",
    "sg:address":"49 W Colorado Blvd",
    "sg:city":"Pasadena",
    "sg:classifiers":[
        {
            "category":"Food & Beverages",
            "subcategory":"Candy",
            "type":"Retail Goods"
        }
    ],
    "sg:phone":"+1 626 577 7121",
    "sg:postcode":"91105",
    "sg:province":"CA",
    "sg:tags":[
        "shop",
        "confectionery",
        "chocolatiers"
    ],
    "sg:website":"www.leonidaschocolatecafe.com",
    "wof:name":"Leonidas",
    "wof:placetype":"venue"
},
  "geometry": {"coordinates":[-118.151504,34.145763],"type":"Point"}
}