{
  "type": "Feature",
  "properties": {
    "addr:full":"18764 Ventura Blvd Tarzana CA 91356",
    "addr:housenumber":"18764",
    "addr:postcode":"91356",
    "addr:street":"Ventura Blvd",
    "iso:country":"US",
    "sg:address":"18764 Ventura Blvd",
    "sg:city":"Tarzana",
    "sg:classifiers":[
        {
            "category":"Shopping",
            "subcategory":"Gifts & Souvenirs",
            "type":"Retail Goods"
        }
    ],
    "sg:phone":"+1 818 996 4748",
    "sg:postcode":"91356",
    "sg:province":"CA",
    "sg:tags":[
        "balloon",
        "artist"
    ],
    "wof:name":"Flowers Plus",
    "wof:placetype":"venue"
},
  "geometry": {"coordinates":[-118.541706,34.170894],"type":"Point"}
}