{
  "type": "Feature",
  "properties": {
    "addr:full":"111 W California St Ontario CA 91762",
    "addr:housenumber":"111",
    "addr:postcode":"91762",
    "addr:street":"W California St",
    "iso:country":"US",
    "sg:address":"111 W California St",
    "sg:city":"Ontario",
    "sg:classifiers":[
        {
            "category":"Retail",
            "subcategory":"Auto Repair",
            "type":"Services"
        }
    ],
    "sg:phone":"+1 909 391 6811",
    "sg:postcode":"91762",
    "sg:province":"CA",
    "sg:tags":[
        "repairing",
        "automobile"
    ],
    "wof:name":"Ontario Auto Repair",
    "wof:placetype":"venue"
},
  "geometry": {"coordinates":[-117.652259,34.055672],"type":"Point"}
}