{
  "type": "Feature",
  "properties": {
    "iso:country":"US",
    "sg:address":"3813 Vistosa Ct",
    "sg:city":"Davis",
    "sg:classifiers":[
        {
            "category":"Professional",
            "type":"Services"
        }
    ],
    "sg:phone":"+1 530 753 9597",
    "sg:postcode":"95618",
    "sg:province":"CA",
    "sg:tags":[
        "establishment"
    ],
    "wof:name":"John Meyer & Assoc",
    "wof:placetype":"venue"
},
  "geometry": {"coordinates":[-121.704768,38.557463],"type":"Point"}
}