{
  "type": "Feature",
  "properties": {
    "addr:full":"27011 McBean Pkwy Valencia CA 91355",
    "addr:postcode":"27011;91355",
    "addr:street":"Mcbean Pkwy",
    "iso:country":"US",
    "sg:address":"27011 McBean Pkwy",
    "sg:city":"Valencia",
    "sg:classifiers":[
        {
            "category":"Health Services",
            "subcategory":"Optometrist",
            "type":"Services"
        }
    ],
    "sg:phone":"+1 661 253 3888",
    "sg:postcode":"91355",
    "sg:province":"CA",
    "wof:name":"Teagle Robert Optometry",
    "wof:placetype":"venue"
},
  "geometry": {"coordinates":[-118.56300400000001,34.4217],"type":"Point"}
}