{
  "type": "Feature",
  "properties": {
    "iso:country":"US",
    "sg:address":"1184 Maple Ln",
    "sg:city":"Calistoga",
    "sg:classifiers":[
        {
            "category":"Wholesale",
            "subcategory":"Machinery & Supplies",
            "type":"Manufacturing & Wholesale Goods"
        }
    ],
    "sg:phone":"+1 707 942 8330",
    "sg:postcode":"94515",
    "sg:province":"CA",
    "sg:tags":[
        "equipment",
        "industrial",
        "establishment",
        "steam",
        "cleaning"
    ],
    "wof:name":"Pressure Washer Company",
    "wof:placetype":"venue"
},
  "geometry": {"coordinates":[-122.537319,38.562156],"type":"Point"}
}