{
  "type": "Feature",
  "properties": {
    "iso:country":"US",
    "sg:address":"14177 Maverick Ln",
    "sg:city":"Grass Valley",
    "sg:classifiers":[
        {
            "category":"Real Estate",
            "subcategory":"Real Estate Agent",
            "type":"Services"
        }
    ],
    "sg:phone":"+1 530 273 6327",
    "sg:postcode":"95949",
    "sg:province":"CA",
    "wof:name":"Maverick Properties",
    "wof:placetype":"venue"
},
  "geometry": {"coordinates":[-121.045081,39.162276],"type":"Point"}
}