{
  "type": "Feature",
  "properties": {
    "iso:country":"US",
    "sg:address":"5511 N Figueroa St",
    "sg:city":"Highland Park",
    "sg:classifiers":[
        {
            "category":"Restaurant",
            "type":"Food & Drink"
        }
    ],
    "sg:phone":"+1 323 982 9480",
    "sg:postcode":"90042",
    "sg:province":"CA",
    "sg:tags":[
        "vegetarian",
        "vegan"
    ],
    "sg:website":"www.cinnamonvegetarian.com",
    "wof:name":"Cinnamon Vegetarian",
    "wof:placetype":"venue"
},
  "geometry": {"coordinates":[-118.19538,34.10834],"type":"Point"}
}