{
  "type": "Feature",
  "properties": {
    "addr:full":"18832 Brookhurst St Fountain Valley CA 92708",
    "addr:housenumber":"18832",
    "addr:postcode":"92708",
    "addr:street":"Brookhurst St",
    "iso:country":"US",
    "sg:address":"18832 Brookhurst St",
    "sg:city":"Fountain Valley",
    "sg:classifiers":[
        {
            "category":"Health Services",
            "subcategory":"Dentist",
            "type":"Services"
        }
    ],
    "sg:phone":"+1 714 964 0036",
    "sg:postcode":"92708",
    "sg:province":"CA",
    "wof:name":"Heng-Tsang Lee DDS",
    "wof:placetype":"venue"
},
  "geometry": {"coordinates":[-117.954002,33.688999],"type":"Point"}
}