{
  "type": "Feature",
  "properties": {
    "iso:country":"US",
    "sg:address":"2459 Pinehurst Ct",
    "sg:city":"Byron",
    "sg:classifiers":[
        {
            "category":"Professional",
            "type":"Services"
        }
    ],
    "sg:phone":"+1 925 513 3545",
    "sg:postcode":"94505",
    "sg:province":"CA",
    "wof:name":"KG Hopkins Inc",
    "wof:placetype":"venue"
},
  "geometry": {"coordinates":[-118.639145,35.093962],"type":"Point"}
}