{
  "type": "Feature",
  "properties": {
    "iso:country":"US",
    "sg:address":"16223 Arrow Hwy",
    "sg:city":"Baldwin Park",
    "sg:classifiers":[
        {
            "category":"Manufacturing",
            "subcategory":"Wood Products",
            "type":"Manufacturing & Wholesale Goods"
        }
    ],
    "sg:phone":"+1 626 334 3435",
    "sg:postcode":"91706",
    "sg:province":"CA",
    "sg:tags":[
        "mfg"
    ],
    "wof:name":"Arpersal Woodwork",
    "wof:placetype":"venue"
},
  "geometry": {"coordinates":[-117.925619,34.107031],"type":"Point"}
}