{
  "type": "Feature",
  "properties": {
    "iso:country":"US",
    "sg:address":"9850 Golden Dr",
    "sg:city":"Orangevale",
    "sg:classifiers":[
        {
            "category":"Building & Trades",
            "subcategory":"Construction",
            "type":"Services"
        }
    ],
    "sg:phone":"+1 916 989 5104",
    "sg:postcode":"95662",
    "sg:province":"CA",
    "sg:tags":[
        "contractor"
    ],
    "wof:name":"Bighorn Construction",
    "wof:placetype":"venue"
},
  "geometry": {"coordinates":[-121.19914900000001,38.659536],"type":"Point"}
}