{
  "type": "Feature",
  "properties": {
    "addr:full":"16135 Monterey St Morgan Hill CA 95037",
    "addr:housenumber":"16135",
    "addr:postcode":"95037",
    "addr:street":"Monterey St",
    "iso:country":"US",
    "sg:address":"16135 Monterey St",
    "sg:city":"Morgan Hill",
    "sg:classifiers":[
        {
            "category":"Restaurant",
            "type":"Food & Drink"
        }
    ],
    "sg:phone":"+1 408 776 7780",
    "sg:postcode":"95037",
    "sg:province":"CA",
    "wof:name":"Great Wall Imperial",
    "wof:placetype":"venue"
},
  "geometry": {"coordinates":[-121.64386,37.114139],"type":"Point"}
}