{
  "type": "Feature",
  "properties": {
    "iso:country":"US",
    "sg:address":"1930 Hubbard St",
    "sg:city":"Simi Valley",
    "sg:classifiers":[
        {
            "category":"Food & Beverages",
            "subcategory":"Groceries & Convenience Stores",
            "type":"Retail Goods"
        }
    ],
    "sg:phone":"+1 805 527 3150",
    "sg:postcode":"93065",
    "sg:province":"CA",
    "sg:tags":[
        "grocer"
    ],
    "wof:name":"Tammy's General Store",
    "wof:placetype":"venue"
},
  "geometry": {"coordinates":[-118.770031,34.270576],"type":"Point"}
}