{
  "type": "Feature",
  "properties": {
    "addr:full":"9307 Woodward Lake Dr Oakdale CA 95361",
    "addr:housenumber":"9307",
    "addr:postcode":"95361",
    "addr:street":"Woodward Lake Dr",
    "iso:country":"US",
    "sg:address":"9307 Woodward Lake Dr",
    "sg:city":"Oakdale",
    "sg:classifiers":[
        {
            "category":"Wholesale",
            "subcategory":"Groceries",
            "type":"Manufacturing & Wholesale Goods"
        }
    ],
    "sg:phone":"+1 209 847 8133",
    "sg:postcode":"95361",
    "sg:province":"CA",
    "sg:tags":[
        "grocer"
    ],
    "wof:name":"Dumas Ventures",
    "wof:placetype":"venue"
},
  "geometry": {"coordinates":[-120.81917300000001,37.837298],"type":"Point"}
}