{
  "type": "Feature",
  "properties": {
    "iso:country":"US",
    "sg:address":"2718 Huntington Dr",
    "sg:city":"Duarte",
    "sg:classifiers":[
        {
            "category":"Professional",
            "subcategory":"Advertising",
            "type":"Services"
        }
    ],
    "sg:phone":"+1 626 357 3768",
    "sg:postcode":"91010",
    "sg:province":"CA",
    "sg:tags":[
        "promotion",
        "sale"
    ],
    "wof:name":"Capitol Equipment Inc",
    "wof:placetype":"venue"
},
  "geometry": {"coordinates":[-117.946654,34.138869],"type":"Point"}
}