{
  "type": "Feature",
  "properties": {
    "addr:full":"1751 4th Ave Chula Vista CA 91911",
    "addr:housenumber":"1751",
    "addr:postcode":"91911",
    "addr:street":"4Th Ave",
    "iso:country":"US",
    "sg:address":"1751 4th Ave",
    "sg:city":"Chula Vista",
    "sg:classifiers":[
        {
            "category":"Wholesale",
            "subcategory":"Electrical",
            "type":"Manufacturing & Wholesale Goods"
        }
    ],
    "sg:phone":"+1 619 827 0618",
    "sg:postcode":"91911",
    "sg:province":"CA",
    "sg:tags":[
        "equipment",
        "electric",
        "supply"
    ],
    "wof:name":"Progressive Wholesale Electric",
    "wof:placetype":"venue"
},
  "geometry": {"coordinates":[-117.064775,32.593072],"type":"Point"}
}