{
  "type": "Feature",
  "properties": {
    "addr:full":"6098 Ranger Rd Clovis CA 93619",
    "addr:housenumber":"6098",
    "addr:postcode":"93619",
    "addr:street":"Ranger Rd",
    "iso:country":"US",
    "sg:address":"6098 Ranger Rd",
    "sg:city":"Clovis",
    "sg:classifiers":[
        {
            "category":"Farming",
            "subcategory":"Farm & Veterinary Services",
            "type":"Manufacturing & Wholesale Goods"
        }
    ],
    "sg:phone":"+1 559 297 8722",
    "sg:postcode":"93619",
    "sg:province":"CA",
    "sg:tags":[
        "management"
    ],
    "wof:name":"Mike Ubick",
    "wof:placetype":"venue"
},
  "geometry": {"coordinates":[-119.603308,36.826334],"type":"Point"}
}