{
  "type": "Feature",
  "properties": {
    "addr:full":"4301 Grissom St Bakersfield CA 93309",
    "addr:housenumber":"4301",
    "addr:postcode":"93309",
    "addr:street":"Grissom St",
    "iso:country":"US",
    "sg:address":"4301 Grissom St",
    "sg:city":"Bakersfield",
    "sg:classifiers":[
        {
            "category":"Building & Trades",
            "subcategory":"Landscaping Services",
            "type":"Services"
        }
    ],
    "sg:phone":"+1 661 665 1826",
    "sg:postcode":"93309",
    "sg:province":"CA",
    "sg:tags":[
        "landscape",
        "contractor"
    ],
    "wof:name":"Southwest Landscape & Mtnc",
    "wof:placetype":"venue"
},
  "geometry": {"coordinates":[-119.06139899999999,35.31537],"type":"Point"}
}