{
  "type": "Feature",
  "properties": {
    "iso:country":"US",
    "sg:address":"12019 Lakeside Ave",
    "sg:city":"Lakeside",
    "sg:classifiers":[
        {
            "category":"Social Services",
            "type":"Services"
        }
    ],
    "sg:phone":"+1 619 390 4064",
    "sg:postcode":"92040",
    "sg:province":"CA",
    "sg:tags":[
        "organization",
        "welfare"
    ],
    "wof:name":"RTC",
    "wof:placetype":"venue"
},
  "geometry": {"coordinates":[-116.93333699999999,32.866972],"type":"Point"}
}