{
  "type": "Feature",
  "properties": {
    "iso:country":"US",
    "sg:address":"1307 W 6th St",
    "sg:city":"Corona",
    "sg:classifiers":[
        {
            "category":"Building & Trades",
            "subcategory":"Construction",
            "type":"Services"
        }
    ],
    "sg:phone":"+1 951 371 4487",
    "sg:postcode":"92882",
    "sg:province":"CA",
    "sg:tags":[
        "contractor"
    ],
    "wof:name":"S & Q Construction Inc",
    "wof:placetype":"venue"
},
  "geometry": {"coordinates":[-117.594385,33.878409],"type":"Point"}
}