{
  "type": "Feature",
  "properties": {
    "iso:country":"US",
    "sg:address":"87 McLea Ct",
    "sg:city":"San Francisco",
    "sg:classifiers":[
        {
            "category":"Professional",
            "subcategory":"Management & Consulting",
            "type":"Services"
        }
    ],
    "sg:phone":"+1 415 962 8200",
    "sg:postcode":"94103",
    "sg:province":"CA",
    "sg:tags":[
        "counselor",
        "public",
        "relations"
    ],
    "wof:name":"Spark PR",
    "wof:placetype":"venue"
},
  "geometry": {"coordinates":[-122.408496,37.772212],"type":"Point"}
}