{
  "type": "Feature",
  "properties": {
    "addr:full":"615 11th St Arcata CA 95521",
    "addr:housenumber":"615",
    "addr:postcode":"95521",
    "addr:street":"11Th St",
    "iso:country":"US",
    "sg:address":"615 11th St",
    "sg:city":"Arcata",
    "sg:classifiers":[
        {
            "category":"Insurance",
            "subcategory":"Insurance Agent",
            "type":"Services"
        }
    ],
    "sg:phone":"+1 707 822 2421",
    "sg:postcode":"95521",
    "sg:province":"CA",
    "sg:tags":[
        "homeowner"
    ],
    "sg:website":"http://www.farmersagent.com/lsundberg/",
    "wof:name":"Linda Sundberg - Farmers Insurance",
    "wof:placetype":"venue"
},
  "geometry": {"coordinates":[-124.08428000000001,40.87021],"type":"Point"}
}