{
  "type": "Feature",
  "properties": {
    "iso:country":"US",
    "sg:address":"137 Racquet Club Dr",
    "sg:city":"Compton",
    "sg:classifiers":[
        {
            "category":"Freight",
            "type":"Transportation"
        }
    ],
    "sg:phone":"+1 310 631 1617",
    "sg:postcode":"90220",
    "sg:province":"CA",
    "sg:tags":[
        "trucking"
    ],
    "wof:name":"Maselli Trucking Inc",
    "wof:placetype":"venue"
},
  "geometry": {"coordinates":[-118.22234400000001,33.893894],"type":"Point"}
}