{
  "type": "Feature",
  "properties": {
    "addr:full":"1855 Pitcairn Dr Costa Mesa CA 92626",
    "addr:housenumber":"1855",
    "addr:postcode":"92626",
    "addr:street":"Pitcairn Dr",
    "iso:country":"US",
    "sg:address":"1855 Pitcairn Dr",
    "sg:city":"Costa Mesa",
    "sg:classifiers":[
        {
            "category":"Manufacturing",
            "subcategory":"Toys & Sporting Goods",
            "type":"Manufacturing & Wholesale Goods"
        }
    ],
    "sg:phone":"+1 949 887 2302",
    "sg:postcode":"92626",
    "sg:province":"CA",
    "sg:tags":[
        "mfg"
    ],
    "wof:name":"Backyard Golf",
    "wof:placetype":"venue"
},
  "geometry": {"coordinates":[-117.935086,33.673005],"type":"Point"}
}