{
  "type": "Feature",
  "properties": {
    "addr:full":"1001 B Avenue Coronado CA 92118",
    "addr:housenumber":"1001 b",
    "addr:postcode":"92118",
    "addr:street":"Avenue",
    "iso:country":"US",
    "sg:address":"1001 B Avenue",
    "sg:city":"Coronado",
    "sg:classifiers":[
        {
            "category":"Real Estate",
            "subcategory":"Real Estate Services",
            "type":"Services"
        }
    ],
    "sg:phone":"+1 619 435 3334",
    "sg:postcode":"92118",
    "sg:province":"CA",
    "sg:tags":[
        "management",
        "property"
    ],
    "wof:name":"Independent Financial Group",
    "wof:placetype":"venue"
},
  "geometry": {"coordinates":[-117.17754100000001,32.684918],"type":"Point"}
}