{
  "type": "Feature",
  "properties": {
    "iso:country":"US",
    "sg:address":"436 Market St",
    "sg:city":"Colusa",
    "sg:classifiers":[
        {
            "category":"Professional",
            "subcategory":"Accounting & Tax Preparation",
            "type":"Services"
        }
    ],
    "sg:phone":"+1 530 458 2197",
    "sg:postcode":"95932",
    "sg:province":"CA",
    "sg:tags":[
        "return",
        "filing"
    ],
    "wof:name":"Beduhn Business & Tax Svc",
    "wof:placetype":"venue"
},
  "geometry": {"coordinates":[-122.007572,39.214015],"type":"Point"}
}