{
  "type": "Feature",
  "properties": {
    "iso:country":"US",
    "sg:address":"1401 Abalone Ave",
    "sg:city":"Torrance",
    "sg:classifiers":[
        {
            "category":"Manufacturing",
            "subcategory":"Metals",
            "type":"Manufacturing & Wholesale Goods"
        }
    ],
    "sg:phone":"+1 310 381 3060",
    "sg:postcode":"90501",
    "sg:province":"CA",
    "sg:tags":[
        "deposition",
        "coating"
    ],
    "sg:website":"www.zcrcoatings.com",
    "wof:name":"Z C & R Coating For Optics",
    "wof:placetype":"venue"
},
  "geometry": {"coordinates":[-118.311747,33.83437],"type":"Point"}
}