{
  "type": "Feature",
  "properties": {
    "addr:full":"3729 Cadwallader Ave San Jose CA 95121",
    "addr:housenumber":"3729",
    "addr:postcode":"95121",
    "addr:street":"Cadwallader Ave",
    "iso:country":"US",
    "sg:address":"3729 Cadwallader Ave",
    "sg:city":"San Jose",
    "sg:classifiers":[
        {
            "category":"Building & Trades",
            "subcategory":"Landscaping Services",
            "type":"Services"
        }
    ],
    "sg:phone":"+1 408 254 9176",
    "sg:postcode":"95121",
    "sg:province":"CA",
    "sg:tags":[
        "lawn",
        "maintenance",
        "grounds"
    ],
    "wof:name":"Solorio's Gardening",
    "wof:placetype":"venue"
},
  "geometry": {"coordinates":[-121.788141,37.308322],"type":"Point"}
}