{
  "type": "Feature",
  "properties": {
    "addr:full":"1518 Yajome St Napa CA 94559",
    "addr:housenumber":"1518",
    "addr:postcode":"94559",
    "addr:street":"Yajome St",
    "iso:country":"US",
    "sg:address":"1518 Yajome St",
    "sg:city":"Napa",
    "sg:classifiers":[
        {
            "category":"Retail",
            "subcategory":"Repair Shop",
            "type":"Services"
        }
    ],
    "sg:phone":"+1 707 224 1905",
    "sg:postcode":"94559",
    "sg:province":"CA",
    "sg:tags":[
        "upholsterer"
    ],
    "wof:name":"Pollin Interiors & Upholstery",
    "wof:placetype":"venue"
},
  "geometry": {"coordinates":[-122.287131,38.304075],"type":"Point"}
}