{
  "type": "Feature",
  "properties": {
    "iso:country":"US",
    "sg:address":"572 Arastradero Rd",
    "sg:city":"Palo Alto",
    "sg:classifiers":[
        {
            "category":"Retail",
            "subcategory":"Animal Services",
            "type":"Services"
        }
    ],
    "sg:phone":"+1 650 856 4090",
    "sg:postcode":"94306",
    "sg:province":"CA",
    "sg:tags":[
        "merchandise"
    ],
    "wof:name":"Classic Pet Grooming Inc",
    "wof:placetype":"venue"
},
  "geometry": {"coordinates":[-122.12490699999999,37.408307],"type":"Point"}
}