{
  "type": "Feature",
  "properties": {
    "iso:country":"US",
    "sg:address":"9281 Sierra Ave",
    "sg:city":"Fontana",
    "sg:classifiers":[
        {
            "category":"Real Estate",
            "subcategory":"Real Estate Agent",
            "type":"Services"
        }
    ],
    "sg:phone":"+1 909 350 9895",
    "sg:postcode":"92335",
    "sg:province":"CA",
    "sg:tags":[
        "management"
    ],
    "wof:name":"H & C Property",
    "wof:placetype":"venue"
},
  "geometry": {"coordinates":[-117.435646,34.088175],"type":"Point"}
}