{
  "type": "Feature",
  "properties": {
    "addr:full":"2013 San Elijo Encinitas CA 92007",
    "addr:housenumber":"2013",
    "addr:postcode":"92007",
    "addr:street":"San Elijo",
    "iso:country":"US",
    "sg:address":"2013 San Elijo",
    "sg:city":"Encinitas",
    "sg:classifiers":[
        {
            "category":"Shopping",
            "subcategory":"Pets & Pet Supplies",
            "type":"Retail Goods"
        }
    ],
    "sg:phone":"+1 760 230 6354",
    "sg:postcode":"92007",
    "sg:province":"CA",
    "sg:tags":[
        "groomers"
    ],
    "wof:name":"Grooming Tails Pet Salon",
    "wof:placetype":"venue"
},
  "geometry": {"coordinates":[-117.282999,33.021963],"type":"Point"}
}