{
  "type": "Feature",
  "properties": {
    "addr:full":"4009 W Segerstrom Ave Santa Ana CA 92704",
    "addr:housenumber":"4009",
    "addr:postcode":"92704",
    "addr:street":"W Segerstrom Ave",
    "iso:country":"US",
    "sg:address":"4009 W Segerstrom Ave",
    "sg:city":"Santa Ana",
    "sg:classifiers":[
        {
            "category":"Manufacturing",
            "subcategory":"Printing",
            "type":"Manufacturing & Wholesale Goods"
        }
    ],
    "sg:phone":"+1 714 556 1400",
    "sg:postcode":"92704",
    "sg:province":"CA",
    "sg:tags":[
        "screen"
    ],
    "wof:name":"Comstar Industries",
    "wof:placetype":"venue"
},
  "geometry": {"coordinates":[-117.92383700000001,33.708703],"type":"Point"}
}