{
  "type": "Feature",
  "properties": {
    "iso:country":"US",
    "sg:address":"8331 Sierra College Blvd",
    "sg:city":"Roseville",
    "sg:classifiers":[
        {
            "category":"Professional",
            "subcategory":"Engineering",
            "type":"Services"
        }
    ],
    "sg:phone":"+1 916 797 1770",
    "sg:postcode":"95661",
    "sg:province":"CA",
    "sg:tags":[
        "engineer"
    ],
    "wof:name":"Kleinfelder",
    "wof:placetype":"venue"
},
  "geometry": {"coordinates":[-121.226156,38.744215],"type":"Point"}
}