{
  "type": "Feature",
  "properties": {
    "iso:country":"US",
    "sg:address":"63205 Argyle Rd",
    "sg:city":"King City",
    "sg:classifiers":[
        {
            "category":"Farming",
            "subcategory":"Vineyard",
            "type":"Manufacturing & Wholesale Goods"
        }
    ],
    "sg:phone":"+1 831 386 9500",
    "sg:postcode":"93930",
    "sg:province":"CA",
    "sg:tags":[
        "grape"
    ],
    "wof:name":"Jolon Vineyards Inc",
    "wof:placetype":"venue"
},
  "geometry": {"coordinates":[-121.164586,35.991923],"type":"Point"}
}