{
  "type": "Feature",
  "properties": {
    "addr:full":"1407 E 4th St Long Beach CA 90802",
    "addr:housenumber":"1407",
    "addr:postcode":"90802",
    "addr:street":"E 4Th St",
    "iso:country":"US",
    "sg:address":"1407 E 4th St",
    "sg:city":"Long Beach",
    "sg:classifiers":[
        {
            "category":"Organizations",
            "subcategory":"Non-profit Organization",
            "type":"Services"
        }
    ],
    "sg:phone":"+1 562 590 8844",
    "sg:postcode":"90802",
    "sg:province":"CA",
    "sg:tags":[
        "human"
    ],
    "wof:name":"Volunteer Center Long Beach",
    "wof:placetype":"venue"
},
  "geometry": {"coordinates":[-118.174599,33.771783],"type":"Point"}
}