{
  "type": "Feature",
  "properties": {
    "addr:full":"14013 Midland Rd Poway CA 92064",
    "addr:housenumber":"14013",
    "addr:postcode":"ca 92064",
    "addr:street":"Midland Rd",
    "iso:country":"US",
    "sg:address":"14013 Midland Rd",
    "sg:city":"Poway",
    "sg:classifiers":[
        {
            "category":"Health Services",
            "subcategory":"Doctor",
            "type":"Services"
        },
        {
            "category":"Personal",
            "subcategory":"Beauty Salon",
            "type":"Services"
        },
        {
            "category":"Personal",
            "subcategory":"Skin Care",
            "type":"Services"
        }
    ],
    "sg:phone":"+1 858 748 9170",
    "sg:postcode":"92064",
    "sg:province":"CA",
    "sg:tags":[
        "hair",
        "replacement"
    ],
    "wof:name":"Professional Skin Care By Kath",
    "wof:placetype":"venue"
},
  "geometry": {"coordinates":[-117.036118,32.967875],"type":"Point"}
}