{
  "type": "Feature",
  "properties": {
    "iso:country":"US",
    "sg:address":"308 W Raymond St",
    "sg:city":"Lynwood",
    "sg:classifiers":[
        {
            "category":"Arts & Performance",
            "subcategory":"Theater",
            "type":"Entertainment"
        }
    ],
    "sg:phone":"+1 310 635 6995",
    "sg:postcode":"90220",
    "sg:province":"CA",
    "sg:tags":[
        "clown"
    ],
    "wof:name":"Tony Bolony The Birthday Clown",
    "wof:placetype":"venue"
},
  "geometry": {"coordinates":[-118.227994,33.887504],"type":"Point"}
}