{
  "type": "Feature",
  "properties": {
    "iso:country":"US",
    "sg:address":"18056 Wika Rd",
    "sg:city":"Apple Valley",
    "sg:classifiers":[
        {
            "category":"Health Services",
            "subcategory":"Doctor",
            "type":"Services"
        }
    ],
    "sg:phone":"+1 760 242 7744",
    "sg:postcode":"92307",
    "sg:province":"CA",
    "sg:tags":[
        "dentist"
    ],
    "wof:name":"Steven E Kratofil DDS",
    "wof:placetype":"venue"
},
  "geometry": {"coordinates":[-117.269158,34.540804],"type":"Point"}
}