{
  "type": "Feature",
  "properties": {
    "addr:full":"2541 W Alhambra Ave Fresno CA 93728",
    "addr:housenumber":"2541",
    "addr:postcode":"93728",
    "addr:street":"W Alhambra Ave",
    "iso:country":"US",
    "sg:address":"2541 W Alhambra Ave",
    "sg:city":"Fresno",
    "sg:classifiers":[
        {
            "category":"Building & Trades",
            "subcategory":"Landscaping Services",
            "type":"Services"
        }
    ],
    "sg:phone":"+1 559 233 5652",
    "sg:postcode":"93728",
    "sg:province":"CA",
    "sg:tags":[
        "tree"
    ],
    "wof:name":"Halls Tree Service",
    "wof:placetype":"venue"
},
  "geometry": {"coordinates":[-119.8415,36.756468],"type":"Point"}
}