{
  "type": "Feature",
  "properties": {
    "addr:full":"4163 W 3rd St Los Angeles CA 90020",
    "addr:housenumber":"4163",
    "addr:postcode":"90020",
    "addr:street":"W 3Rd St",
    "iso:country":"US",
    "sg:address":"4163 W 3rd St",
    "sg:city":"Los Angeles",
    "sg:classifiers":[
        {
            "category":"Restaurant",
            "type":"Food & Drink"
        }
    ],
    "sg:phone":"+1 213 382 2103",
    "sg:postcode":"90020",
    "sg:province":"CA",
    "sg:tags":[
        "sushi",
        "bar",
        "japanese"
    ],
    "wof:name":"Mijori Japanese Restauraunt",
    "wof:placetype":"venue"
},
  "geometry": {"coordinates":[-118.304453,34.068988],"type":"Point"}
}