{
  "type": "Feature",
  "properties": {
    "iso:country":"US",
    "sg:address":"7036 Westside Rd",
    "sg:city":"Redding",
    "sg:classifiers":[
        {
            "category":"Professional",
            "subcategory":"Accounting & Tax Preparation",
            "type":"Services"
        }
    ],
    "sg:phone":"+1 530 243 3647",
    "sg:postcode":"96001",
    "sg:province":"CA",
    "sg:tags":[
        "religious",
        "return",
        "filing"
    ],
    "wof:name":"Barbara D Christ Ea",
    "wof:placetype":"venue"
},
  "geometry": {"coordinates":[-122.381266,40.513169],"type":"Point"}
}