{
  "type": "Feature",
  "properties": {
    "addr:full":"115 Dearborn Pl Goleta CA 93117",
    "addr:housenumber":"115",
    "addr:postcode":"93117",
    "addr:street":"Dearborn Pl",
    "iso:country":"US",
    "sg:address":"115 Dearborn Pl",
    "sg:city":"Goleta",
    "sg:classifiers":[
        {
            "category":"Health Services",
            "subcategory":"Health Practitioner",
            "type":"Services"
        }
    ],
    "sg:phone":"+1 805 683 5338",
    "sg:postcode":"93117",
    "sg:province":"CA",
    "sg:tags":[
        "psychotherapist"
    ],
    "wof:name":"Joseph D Cardona",
    "wof:placetype":"venue"
},
  "geometry": {"coordinates":[-119.818224,34.436002],"type":"Point"}
}