{
  "type": "Feature",
  "properties": {
    "iso:country":"US",
    "sg:address":"808 J St",
    "sg:city":"Sacramento",
    "sg:classifiers":[
        {
            "category":"Health Services",
            "subcategory":"Optometrist",
            "type":"Services"
        }
    ],
    "sg:phone":"+1 916 447 3000",
    "sg:postcode":"95814",
    "sg:province":"CA",
    "sg:website":"www.eyesonj.com",
    "wof:name":"Eyes On J Optometry",
    "wof:placetype":"venue"
},
  "geometry": {"coordinates":[-121.49566,38.58088],"type":"Point"}
}