{
  "type": "Feature",
  "properties": {
    "addr:full":"9200 Bloomfield Ave Cypress CA 90630",
    "addr:housenumber":"9200",
    "addr:postcode":"90630",
    "addr:street":"Bloomfield Ave",
    "iso:country":"US",
    "sg:address":"9200 Bloomfield Ave",
    "sg:city":"Cypress",
    "sg:classifiers":[
        {
            "category":"Manufacturing",
            "subcategory":"Toys & Sporting Goods",
            "type":"Manufacturing & Wholesale Goods"
        }
    ],
    "sg:phone":"+1 714 826 7655",
    "sg:postcode":"90630",
    "sg:province":"CA",
    "sg:tags":[
        "mfg"
    ],
    "wof:name":"Match Maker Targets",
    "wof:placetype":"venue"
},
  "geometry": {"coordinates":[-118.06314399999999,33.827447],"type":"Point"}
}