{
  "type": "Feature",
  "properties": {
    "iso:country":"US",
    "sg:address":"4547 Whittier Blvd",
    "sg:city":"Los Angeles",
    "sg:classifiers":[
        {
            "category":"Shopping",
            "type":"Retail Goods"
        }
    ],
    "sg:phone":"+1 323 261 5429",
    "sg:postcode":"90022",
    "sg:province":"CA",
    "sg:tags":[
        "outlet",
        "store",
        "factory"
    ],
    "wof:name":"Ace Outlet Clothing Store",
    "wof:placetype":"venue"
},
  "geometry": {"coordinates":[-118.168999,34.023102],"type":"Point"}
}