{
  "type": "Feature",
  "properties": {
    "iso:country":"US",
    "sg:address":"826 W Pacific Coast Hwy",
    "sg:city":"Wilmington",
    "sg:classifiers":[
        {
            "category":"Government",
            "subcategory":"Office",
            "type":"Public Place"
        }
    ],
    "sg:phone":"+1 310 830 4249",
    "sg:postcode":"90744",
    "sg:province":"CA",
    "sg:tags":[
        "smog",
        "check"
    ],
    "wof:name":"PCH Smog Test Only",
    "wof:placetype":"venue"
},
  "geometry": {"coordinates":[-118.272636,33.790522],"type":"Point"}
}