{
  "type": "Feature",
  "properties": {
    "addr:full":"7578 Waterwillow Dr Sacramento CA 95828",
    "addr:housenumber":"7578",
    "addr:postcode":"95828",
    "addr:street":"Waterwillow Dr",
    "iso:country":"US",
    "sg:address":"7578 Waterwillow Dr",
    "sg:city":"Sacramento",
    "sg:classifiers":[
        {
            "category":"Building & Trades",
            "subcategory":"Cleaning & Sanitation",
            "type":"Services"
        }
    ],
    "sg:phone":"+1 916 594 6827",
    "sg:postcode":"95828",
    "sg:province":"CA",
    "sg:tags":[
        "house"
    ],
    "wof:name":"Ramos Housekeeping",
    "wof:placetype":"venue"
},
  "geometry": {"coordinates":[-121.421041,38.482832],"type":"Point"}
}