{
  "type": "Feature",
  "properties": {
    "addr:full":"389 Salinas St Salinas CA 93901",
    "addr:housenumber":"389",
    "addr:postcode":"93901",
    "addr:street":"Salinas St",
    "iso:country":"US",
    "sg:address":"389 Salinas St",
    "sg:city":"Salinas",
    "sg:classifiers":[
        {
            "category":"Personal",
            "subcategory":"Beauty Salon",
            "type":"Services"
        }
    ],
    "sg:phone":"+1 831 758 2949",
    "sg:postcode":"93901",
    "sg:province":"CA",
    "wof:name":"World Nails",
    "wof:placetype":"venue"
},
  "geometry": {"coordinates":[-121.65585799999999,36.673486],"type":"Point"}
}