{
  "type": "Feature",
  "properties": {
    "addr:full":"1800 N Kenneth Rd Burbank CA 91504",
    "addr:housenumber":"1800",
    "addr:postcode":"91504",
    "addr:street":"N Kenneth Rd",
    "iso:country":"US",
    "sg:address":"1800 N Kenneth Rd",
    "sg:city":"Burbank",
    "sg:classifiers":[
        {
            "category":"Transit Center",
            "subcategory":"Freight",
            "type":"Transportation"
        }
    ],
    "sg:phone":"+1 818 566 6553",
    "sg:postcode":"91504",
    "sg:province":"CA",
    "sg:tags":[
        "container",
        "broker"
    ],
    "wof:name":"Express Freight Inc",
    "wof:placetype":"venue"
},
  "geometry": {"coordinates":[-118.317947,34.19989],"type":"Point"}
}