{
  "type": "Feature",
  "properties": {
    "addr:full":"744 W Philips Cir Porterville CA 93257",
    "addr:housenumber":"744",
    "addr:postcode":"93257",
    "addr:street":"W Philips Cir",
    "iso:country":"US",
    "sg:address":"744 W Philips Cir",
    "sg:city":"Porterville",
    "sg:classifiers":[
        {
            "category":"Building & Trades",
            "subcategory":"Construction",
            "type":"Services"
        }
    ],
    "sg:phone":"+1 559 781 1044",
    "sg:postcode":"93257",
    "sg:province":"CA",
    "sg:tags":[
        "contractor"
    ],
    "wof:name":"Central Coast Builders",
    "wof:placetype":"venue"
},
  "geometry": {"coordinates":[-119.034628,36.074249],"type":"Point"}
}