{
  "type": "Feature",
  "properties": {
    "addr:full":"258 Robinson Dr Tustin CA 92782",
    "addr:housenumber":"258",
    "addr:postcode":"92782",
    "addr:street":"Robinson Dr",
    "iso:country":"US",
    "sg:address":"258 Robinson Dr",
    "sg:city":"Tustin",
    "sg:classifiers":[
        {
            "category":"Professional",
            "type":"Services"
        }
    ],
    "sg:phone":"+1 714 505 7946",
    "sg:postcode":"92782",
    "sg:province":"CA",
    "wof:name":"Abacus Secrets Co",
    "wof:placetype":"venue"
},
  "geometry": {"coordinates":[-117.786288,33.735044],"type":"Point"}
}