{
  "type": "Feature",
  "properties": {
    "addr:full":"11624 Chimney Rock Rd Paso Robles CA 93446",
    "addr:housenumber":"11624",
    "addr:postcode":"93446",
    "addr:street":"Chimney Rock Rd",
    "iso:country":"US",
    "sg:address":"11624 Chimney Rock Rd",
    "sg:city":"Paso Robles",
    "sg:classifiers":[
        {
            "category":"Mining & Drilling",
            "type":"Manufacturing & Wholesale Goods"
        }
    ],
    "sg:phone":"+1 805 226 8060",
    "sg:postcode":"93446",
    "sg:province":"CA",
    "sg:tags":[
        "company"
    ],
    "wof:name":"Mud Camp Mining",
    "wof:placetype":"venue"
},
  "geometry": {"coordinates":[-120.92970200000001,35.664765],"type":"Point"}
}