{
  "type": "Feature",
  "properties": {
    "iso:country":"US",
    "sg:address":"1388 Church St",
    "sg:city":"San Francisco",
    "sg:classifiers":[
        {
            "category":"Professional",
            "type":"Services"
        }
    ],
    "sg:phone":"+1 415 282 2216",
    "sg:postcode":"94114",
    "sg:province":"CA",
    "wof:name":"San Francisco Reader",
    "wof:placetype":"venue"
},
  "geometry": {"coordinates":[-122.427246,37.749123],"type":"Point"}
}