{
  "type": "Feature",
  "properties": {
    "iso:country":"US",
    "sg:address":"14114 Hartsook St",
    "sg:city":"Sherman Oaks",
    "sg:classifiers":[
        {
            "category":"Manufacturing",
            "subcategory":"Food",
            "type":"Manufacturing & Wholesale Goods"
        }
    ],
    "sg:phone":"+1 818 783 4114",
    "sg:postcode":"91423",
    "sg:province":"CA",
    "sg:tags":[
        "mfg"
    ],
    "wof:name":"Ashurov Inc German",
    "wof:placetype":"venue"
},
  "geometry": {"coordinates":[-118.44062700000001,34.163384],"type":"Point"}
}