{
  "type": "Feature",
  "properties": {
    "addr:full":"663 W Redlands Blvd Redlands CA 92373",
    "addr:housenumber":"663",
    "addr:postcode":"92373",
    "addr:street":"W Redlands Blvd",
    "iso:country":"US",
    "sg:address":"663 W Redlands Blvd",
    "sg:city":"Redlands",
    "sg:classifiers":[
        {
            "category":"Restaurant",
            "type":"Food & Drink"
        }
    ],
    "sg:menulink":"http://www.allmenus.com/ca/san-bernardino/220385-bakers-drive-thru/menu/",
    "sg:phone":"+1 909 798 4802",
    "sg:postcode":"92373",
    "sg:province":"CA",
    "sg:tags":[
        "american"
    ],
    "wof:name":"Baker's Drive-thru",
    "wof:placetype":"venue"
},
  "geometry": {"coordinates":[-117.19009200000001,34.057494],"type":"Point"}
}