{
  "type": "Feature",
  "properties": {
    "addr:full":"4480 Kester Ave Sherman Oaks CA 91403",
    "addr:postcode":"4480;91403",
    "addr:street":"Kester Ave",
    "iso:country":"US",
    "sg:address":"4480 Kester Ave",
    "sg:city":"Sherman Oaks",
    "sg:classifiers":[
        {
            "category":"Retail",
            "subcategory":"Auto Repair",
            "type":"Services"
        }
    ],
    "sg:phone":"+1 818 785 1669",
    "sg:postcode":"91403",
    "sg:province":"CA",
    "sg:tags":[
        "wrecker"
    ],
    "wof:name":"United Towing & Transport",
    "wof:placetype":"venue"
},
  "geometry": {"coordinates":[-118.456642,34.151476],"type":"Point"}
}