{
  "type": "Feature",
  "properties": {
    "iso:country":"US",
    "sg:address":"100 W Q St",
    "sg:city":"Rio Linda",
    "sg:classifiers":[
        {
            "category":"Real Estate",
            "subcategory":"Real Estate Agent",
            "type":"Services"
        }
    ],
    "sg:phone":"+1 916 991 4113",
    "sg:postcode":"95673",
    "sg:province":"CA",
    "wof:name":"Gentry Realty",
    "wof:placetype":"venue"
},
  "geometry": {"coordinates":[-121.4661,38.698502],"type":"Point"}
}