{
  "type": "Feature",
  "properties": {
    "iso:country":"US",
    "sg:address":"1435 River Park Dr",
    "sg:city":"Sacramento",
    "sg:classifiers":[
        {
            "category":"Real Estate",
            "subcategory":"Developer",
            "type":"Services"
        }
    ],
    "sg:phone":"+1 916 929 3193",
    "sg:postcode":"95815",
    "sg:province":"CA",
    "wof:name":"Regis Sares Group-Northern Ca",
    "wof:placetype":"venue"
},
  "geometry": {"coordinates":[-121.434929,38.599241],"type":"Point"}
}