{
  "type": "Feature",
  "properties": {
    "iso:country":"US",
    "sg:address":"1618 Broadway",
    "sg:city":"Sacramento",
    "sg:classifiers":[
        {
            "category":"Cinema",
            "subcategory":"Movie Rental",
            "type":"Entertainment"
        },
        {
            "category":"Shopping",
            "subcategory":"Music",
            "type":"Retail Goods"
        },
        {
            "category":"Banks & Credit Unions",
            "subcategory":"Investment Brokerage",
            "type":"Services"
        }
    ],
    "sg:phone":"+1 916 446 3973",
    "sg:postcode":"95818",
    "sg:province":"CA",
    "sg:tags":[
        "used",
        "tapes",
        "vintage",
        "sale",
        "dvds-rental",
        "records",
        "game",
        "video",
        "cd's",
        "tape",
        "dvd's",
        "store"
    ],
    "sg:website":"rare-records.net",
    "wof:name":"Records",
    "wof:placetype":"venue"
},
  "geometry": {"coordinates":[-121.492161,38.561501],"type":"Point"}
}