{
  "type": "Feature",
  "properties": {
    "iso:country":"US",
    "sg:address":"200 N Main Ave",
    "sg:city":"Fallbrook",
    "sg:classifiers":[
        {
            "category":"Arts & Performance",
            "subcategory":"Arts Center",
            "type":"Entertainment"
        }
    ],
    "sg:phone":"+1 760 731 2278",
    "sg:postcode":"92028",
    "sg:province":"CA",
    "sg:tags":[
        "performing"
    ],
    "wof:name":"Mission Theatre",
    "wof:placetype":"venue"
},
  "geometry": {"coordinates":[-117.25099899999999,33.382801],"type":"Point"}
}