{
  "type": "Feature",
  "properties": {
    "addr:full":"5301 S Normandie Ave Los Angeles CA 90037",
    "addr:housenumber":"5301",
    "addr:postcode":"90037",
    "addr:street":"S Normandie Ave",
    "iso:country":"US",
    "sg:address":"5301 S Normandie Ave",
    "sg:city":"Los Angeles",
    "sg:classifiers":[
        {
            "category":"Arts & Performance",
            "subcategory":"Music",
            "type":"Entertainment"
        }
    ],
    "sg:phone":"+1 323 758 7528",
    "sg:postcode":"90037",
    "sg:province":"CA",
    "sg:tags":[
        "dj"
    ],
    "wof:name":"Sounds of Success",
    "wof:placetype":"venue"
},
  "geometry": {"coordinates":[-118.300003,33.9939],"type":"Point"}
}