{
  "type": "Feature",
  "properties": {
    "addr:full":"12190 Ventura Blvd Studio City CA 91604",
    "addr:housenumber":"12190",
    "addr:postcode":"91604",
    "addr:street":"Ventura Blvd",
    "iso:country":"US",
    "sg:address":"12190 Ventura Blvd",
    "sg:city":"Studio City",
    "sg:classifiers":[
        {
            "category":"Personal",
            "type":"Services"
        }
    ],
    "sg:phone":"+1 818 509 1739",
    "sg:postcode":"91604",
    "sg:province":"CA",
    "sg:tags":[
        "sewing",
        "alteration"
    ],
    "wof:name":"Art House of Tailoring",
    "wof:placetype":"venue"
},
  "geometry": {"coordinates":[-118.398003,34.143398],"type":"Point"}
}