{
  "type": "Feature",
  "properties": {
    "addr:full":"2301 N San Fernando Blvd Burbank CA 91504",
    "addr:housenumber":"2301",
    "addr:postcode":"91504",
    "addr:street":"N San Fernando Blvd",
    "iso:country":"US",
    "sg:address":"2301 N San Fernando Blvd",
    "sg:city":"Burbank",
    "sg:classifiers":[
        {
            "category":"Professional",
            "type":"Services"
        }
    ],
    "sg:phone":"+1 818 557 7797",
    "sg:postcode":"91504",
    "sg:province":"CA",
    "sg:tags":[
        "establishment"
    ],
    "sg:website":"www.leteron.com",
    "wof:name":"Reynolds Group",
    "wof:placetype":"venue"
},
  "geometry": {"coordinates":[-118.336316,34.196807],"type":"Point"}
}