{
  "type": "Feature",
  "properties": {
    "iso:country":"US",
    "sg:address":"4705 Santa Monica Blvd",
    "sg:city":"Los Angeles",
    "sg:classifiers":[
        {
            "category":"Health Services",
            "subcategory":"Medical Lab",
            "type":"Services"
        }
    ],
    "sg:phone":"+1 323 913 0101",
    "sg:postcode":"90029",
    "sg:province":"CA",
    "sg:tags":[
        "laboratory"
    ],
    "wof:name":"Epress Diagnostics",
    "wof:placetype":"venue"
},
  "geometry": {"coordinates":[-118.292695,34.090942],"type":"Point"}
}