{
  "type": "Feature",
  "properties": {
    "addr:full":"810 Calle Plano Camarillo CA 93012",
    "addr:housenumber":"810",
    "addr:postcode":"93012",
    "addr:street":"Calle Plano",
    "iso:country":"US",
    "sg:address":"810 Calle Plano",
    "sg:city":"Camarillo",
    "sg:classifiers":[
        {
            "category":"Place Of Worship",
            "subcategory":"Church",
            "type":"Public Place"
        },
        {
            "category":"Place Of Worship",
            "type":"Public Place"
        },
        {
            "category":"Organizations",
            "subcategory":"Religious Organization",
            "type":"Services"
        }
    ],
    "sg:phone":"+1 805 482 3445",
    "sg:postcode":"93012",
    "sg:province":"CA",
    "sg:tags":[
        "churches-interdenominational",
        "churches-various",
        "denomination"
    ],
    "wof:name":"Legacy Ministries International",
    "wof:placetype":"venue"
},
  "geometry": {"coordinates":[-119.008284,34.199676],"type":"Point"}
}