{
  "type": "Feature",
  "properties": {
    "addr:full":"23762 Foley St Hayward CA 94545",
    "addr:housenumber":"23762",
    "addr:postcode":"94545",
    "addr:street":"Foley St",
    "iso:country":"US",
    "sg:address":"23762 Foley St",
    "sg:city":"Hayward",
    "sg:classifiers":[
        {
            "category":"Retail",
            "subcategory":"Repair Shop",
            "type":"Services"
        }
    ],
    "sg:phone":"+1 510 940 3330",
    "sg:postcode":"94545",
    "sg:province":"CA",
    "sg:tags":[
        "reupholstery",
        "furniture"
    ],
    "wof:name":"Aable Woods",
    "wof:placetype":"venue"
},
  "geometry": {"coordinates":[-122.13082300000001,37.639877],"type":"Point"}
}