{
  "type": "Feature",
  "properties": {
    "addr:full":"850 18th St Oakland CA 94607",
    "addr:housenumber":"850",
    "addr:postcode":"94607",
    "addr:street":"18Th St",
    "iso:country":"US",
    "sg:address":"850 18th St",
    "sg:city":"Oakland",
    "sg:classifiers":[
        {
            "category":"Real Estate",
            "subcategory":"Real Estate Services",
            "type":"Services"
        }
    ],
    "sg:phone":"+1 510 465 5137",
    "sg:postcode":"94607",
    "sg:province":"CA",
    "sg:tags":[
        "apartment",
        "management",
        "rental",
        "finder"
    ],
    "wof:name":"Oak Center Homes Inc",
    "wof:placetype":"venue"
},
  "geometry": {"coordinates":[-122.27929899999999,37.811009],"type":"Point"}
}