{
  "type": "Feature",
  "properties": {
    "iso:country":"US",
    "sg:address":"5711 Water St",
    "sg:city":"La Mesa",
    "sg:classifiers":[
        {
            "category":"Insurance",
            "subcategory":"Insurance Agent",
            "type":"Services"
        }
    ],
    "sg:phone":"+1 619 697 3828",
    "sg:postcode":"91942",
    "sg:province":"CA",
    "wof:name":"Mirman Financial & Insurance",
    "wof:placetype":"venue"
},
  "geometry": {"coordinates":[-116.992059,32.782374],"type":"Point"}
}