{
  "type": "Feature",
  "properties": {
    "iso:country":"US",
    "sg:address":"35547 Grandview Dr",
    "sg:city":"Yucaipa",
    "sg:classifiers":[
        {
            "category":"Autos & Motor Vehicles",
            "subcategory":"Automobile Sales",
            "type":"Retail Goods"
        }
    ],
    "sg:phone":"+1 909 797 3468",
    "sg:postcode":"92399",
    "sg:province":"CA",
    "sg:tags":[
        "performance",
        "race",
        "dealer"
    ],
    "wof:name":"TNT Enterprise",
    "wof:placetype":"venue"
},
  "geometry": {"coordinates":[-117.026726,34.033369],"type":"Point"}
}