{
  "type": "Feature",
  "properties": {
    "addr:full":"712 D St San Rafael CA 94901",
    "addr:housenumber":"712",
    "addr:postcode":"94901",
    "addr:street":"D St",
    "iso:country":"US",
    "sg:address":"712 D St",
    "sg:city":"San Rafael",
    "sg:classifiers":[
        {
            "category":"Health Services",
            "subcategory":"Doctor",
            "type":"Services"
        }
    ],
    "sg:phone":"+1 415 455 1397",
    "sg:postcode":"94901",
    "sg:province":"CA",
    "sg:tags":[
        "physician",
        "surgeon"
    ],
    "wof:name":"Paul Handleman DO",
    "wof:placetype":"venue"
},
  "geometry": {"coordinates":[-122.532245,37.971416],"type":"Point"}
}