{
  "type": "Feature",
  "properties": {
    "iso:country":"US",
    "sg:address":"2005 9th St",
    "sg:city":"Los Osos",
    "sg:classifiers":[
        {
            "category":"Wholesale",
            "subcategory":"Electrical",
            "type":"Manufacturing & Wholesale Goods"
        }
    ],
    "sg:phone":"+1 805 528 1383",
    "sg:postcode":"93402",
    "sg:province":"CA",
    "sg:tags":[
        "intercommunication"
    ],
    "wof:name":"Vf-Tronix",
    "wof:placetype":"venue"
},
  "geometry": {"coordinates":[-120.83334600000001,35.314949],"type":"Point"}
}