{
  "type": "Feature",
  "properties": {
    "addr:full":"1953 E Chapman Ave Fullerton CA 92831",
    "addr:housenumber":"1953",
    "addr:postcode":"92831",
    "addr:street":"E Chapman Ave",
    "iso:country":"US",
    "sg:address":"1953 E Chapman Ave",
    "sg:city":"Fullerton",
    "sg:classifiers":[
        {
            "category":"Professional",
            "subcategory":"Lawyer & Legal Services",
            "type":"Services"
        }
    ],
    "sg:phone":"+1 714 680 3395",
    "sg:postcode":"92831",
    "sg:province":"CA",
    "wof:name":"Grenda A Tim",
    "wof:placetype":"venue"
},
  "geometry": {"coordinates":[-117.896716,33.874308],"type":"Point"}
}