{
  "type": "Feature",
  "properties": {
    "addr:full":"752 Charcot Ave San Jose CA 95131",
    "addr:housenumber":"752",
    "addr:postcode":"95131",
    "addr:street":"Charcot Ave",
    "iso:country":"US",
    "sg:address":"752 Charcot Ave",
    "sg:city":"San Jose",
    "sg:classifiers":[
        {
            "category":"Professional",
            "subcategory":"Detective & Security Services",
            "type":"Services"
        }
    ],
    "sg:phone":"+1 408 324 0170",
    "sg:postcode":"95131",
    "sg:province":"CA",
    "sg:tags":[
        "guard",
        "patrol"
    ],
    "wof:name":"West Coast Security Inc",
    "wof:placetype":"venue"
},
  "geometry": {"coordinates":[-121.908691,37.385837],"type":"Point"}
}