{
  "type": "Feature",
  "properties": {
    "addr:full":"9288 Olive St Fontana CA 92335",
    "addr:housenumber":"9288",
    "addr:postcode":"92335",
    "addr:street":"Olive St",
    "iso:country":"US",
    "sg:address":"9288 Olive St",
    "sg:city":"Fontana",
    "sg:classifiers":[
        {
            "category":"Professional",
            "type":"Services"
        }
    ],
    "sg:phone":"+1 909 829 6859",
    "sg:postcode":"92335",
    "sg:province":"CA",
    "sg:tags":[
        "establishment"
    ],
    "wof:name":"Forston Supply",
    "wof:placetype":"venue"
},
  "geometry": {"coordinates":[-117.43798099999999,34.088324],"type":"Point"}
}