{
  "type": "Feature",
  "properties": {
    "iso:country":"US",
    "sg:address":"17822 Gillette Ave",
    "sg:city":"Irvine",
    "sg:classifiers":[
        {
            "category":"Manufacturing",
            "subcategory":"Leather Goods",
            "type":"Manufacturing & Wholesale Goods"
        }
    ],
    "sg:phone":"+1 949 794 8850",
    "sg:postcode":"92614",
    "sg:province":"CA",
    "sg:tags":[
        "sandal",
        "mfg"
    ],
    "wof:name":"Sanuk Usa LLC",
    "wof:placetype":"venue"
},
  "geometry": {"coordinates":[-117.853174,33.688133],"type":"Point"}
}