{
  "type": "Feature",
  "properties": {
    "iso:country":"US",
    "sg:address":"7700 Edgewater Dr",
    "sg:city":"Oakland",
    "sg:classifiers":[
        {
            "category":"Education",
            "subcategory":"Vocational School",
            "type":"Public Place"
        }
    ],
    "sg:phone":"+1 510 636 2071",
    "sg:postcode":"94621",
    "sg:province":"CA",
    "sg:website":"www.anthonyschool.com",
    "wof:name":"Kaplan Professional",
    "wof:placetype":"venue"
},
  "geometry": {"coordinates":[-122.203422,37.741927],"type":"Point"}
}