{
  "type": "Feature",
  "properties": {
    "iso:country":"US",
    "sg:address":"233 N Harbor Blvd",
    "sg:city":"San Pedro",
    "sg:classifiers":[
        {
            "category":"Retail",
            "subcategory":"Auto Rental",
            "type":"Services"
        }
    ],
    "sg:phone":"+1 310 548 8060",
    "sg:postcode":"90731",
    "sg:province":"CA",
    "sg:tags":[
        "renting",
        "automobile"
    ],
    "wof:name":"Enterprise Rent-A-Car",
    "wof:placetype":"venue"
},
  "geometry": {"coordinates":[-118.279648,33.745694],"type":"Point"}
}