{
  "type": "Feature",
  "properties": {
    "iso:country":"US",
    "sg:address":"5228 Via Valarta",
    "sg:city":"San Diego",
    "sg:classifiers":[
        {
            "category":"Retail",
            "subcategory":"Auto Repair",
            "type":"Services"
        }
    ],
    "sg:phone":"+1 619 242 2784",
    "sg:postcode":"92124",
    "sg:province":"CA",
    "sg:tags":[
        "wrecker"
    ],
    "wof:name":"NAS Towing",
    "wof:placetype":"venue"
},
  "geometry": {"coordinates":[-117.084898,32.838855],"type":"Point"}
}