{
  "type": "Feature",
  "properties": {
    "addr:full":"106 Dixon Rd Milpitas CA 95035",
    "addr:housenumber":"106",
    "addr:postcode":"95035",
    "addr:street":"Dixon Rd",
    "iso:country":"US",
    "sg:address":"106 Dixon Rd",
    "sg:city":"Milpitas",
    "sg:classifiers":[
        {
            "category":"Retail",
            "subcategory":"Portrait Studio",
            "type":"Services"
        }
    ],
    "sg:phone":"+1 408 945 0768",
    "sg:postcode":"95035",
    "sg:province":"CA",
    "sg:tags":[
        "party",
        "supply",
        "photographer"
    ],
    "wof:name":"Excel Photo",
    "wof:placetype":"venue"
},
  "geometry": {"coordinates":[-121.908997,37.458401],"type":"Point"}
}