{
  "type": "Feature",
  "properties": {
    "iso:country":"US",
    "sg:address":"1930 S Bascom Ave Ste 210",
    "sg:city":"Campbell",
    "sg:classifiers":[
        {
            "category":"Health Services",
            "subcategory":"Optometrist",
            "type":"Services"
        }
    ],
    "sg:phone":"+1 408 371 3623",
    "sg:postcode":"95008",
    "sg:province":"CA",
    "sg:website":"bayvieweyecarecenter.com",
    "wof:name":"Bay View Eye Care Center",
    "wof:placetype":"venue"
},
  "geometry": {"coordinates":[-121.931569,37.288468],"type":"Point"}
}