{
  "type": "Feature",
  "properties": {
    "addr:full":"473 Broadway San Francisco CA 94133",
    "addr:housenumber":"473",
    "addr:postcode":"94133",
    "addr:street":"Broadway",
    "iso:country":"US",
    "sg:address":"473 Broadway",
    "sg:city":"San Francisco",
    "sg:classifiers":[
        {
            "category":"Bars & Pubs",
            "type":"Food & Drink"
        }
    ],
    "sg:phone":"+1 415 834 9383",
    "sg:postcode":"94133",
    "sg:province":"CA",
    "sg:tags":[
        "dance",
        "club",
        "night"
    ],
    "sg:website":"www.dragonbarsf.com",
    "wof:name":"Dragon Bar",
    "wof:placetype":"venue"
},
  "geometry": {"coordinates":[-122.404999,37.798],"type":"Point"}
}