{
  "type": "Feature",
  "properties": {
    "addr:full":"7500 Shafter Rd Bakersfield CA 93313",
    "addr:housenumber":"7500",
    "addr:postcode":"93313",
    "addr:street":"Shafter Rd",
    "iso:country":"US",
    "sg:address":"7500 Shafter Rd",
    "sg:city":"Bakersfield",
    "sg:classifiers":[
        {
            "category":"Building & Trades",
            "subcategory":"Construction",
            "type":"Services"
        }
    ],
    "sg:phone":"+1 661 834 7482",
    "sg:postcode":"93313",
    "sg:province":"CA",
    "sg:tags":[
        "concrete",
        "contractor"
    ],
    "wof:name":"Tri-Starr Gunite Co",
    "wof:placetype":"venue"
},
  "geometry": {"coordinates":[-119.086664,35.223493],"type":"Point"}
}