{
  "type": "Feature",
  "properties": {
    "addr:full":"102 Scott St Ukiah CA 95482",
    "addr:housenumber":"102",
    "addr:postcode":"ca 95482",
    "addr:street":"Scott St",
    "iso:country":"US",
    "sg:address":"102 Scott St",
    "sg:city":"Ukiah",
    "sg:classifiers":[
        {
            "category":"Health Services",
            "subcategory":"Optometrist",
            "type":"Services"
        }
    ],
    "sg:phone":"+1 707 462 7040",
    "sg:postcode":"95482",
    "sg:province":"CA",
    "wof:name":"Gilbreath & Park",
    "wof:placetype":"venue"
},
  "geometry": {"coordinates":[-123.208235,39.153668],"type":"Point"}
}