{
  "type": "Feature",
  "properties": {
    "addr:full":"37580 Enterprise Ct Newark CA 94560",
    "addr:housenumber":"37580",
    "addr:postcode":"94560",
    "addr:street":"Enterprise Ct",
    "iso:country":"US",
    "sg:address":"37580 Enterprise Ct",
    "sg:city":"Newark",
    "sg:classifiers":[
        {
            "category":"Home & Garden",
            "subcategory":"Building Materials",
            "type":"Retail Goods"
        }
    ],
    "sg:phone":"+1 510 794 8027",
    "sg:postcode":"94560",
    "sg:province":"CA",
    "sg:tags":[
        "door"
    ],
    "wof:name":"Automatic Door",
    "wof:placetype":"venue"
},
  "geometry": {"coordinates":[-122.04044,37.522976],"type":"Point"}
}