{
  "type": "Feature",
  "properties": {
    "addr:full":"4764 Woodview Dr Santa Rosa CA 95405",
    "addr:housenumber":"4764",
    "addr:postcode":"95405",
    "addr:street":"Woodview Dr",
    "iso:country":"US",
    "sg:address":"4764 Woodview Dr",
    "sg:city":"Santa Rosa",
    "sg:classifiers":[
        {
            "category":"Professional",
            "subcategory":"Accounting & Tax Preparation",
            "type":"Services"
        }
    ],
    "sg:phone":"+1 707 566 7729",
    "sg:postcode":"95405",
    "sg:province":"CA",
    "sg:tags":[
        "bookkeeping",
        "general"
    ],
    "wof:name":"Lisa W Monts",
    "wof:placetype":"venue"
},
  "geometry": {"coordinates":[-122.649123,38.423123],"type":"Point"}
}