{
  "type": "Feature",
  "properties": {
    "iso:country":"US",
    "sg:address":"2141 Rosecrans Ave",
    "sg:city":"El Segundo",
    "sg:classifiers":[
        {
            "category":"Personal",
            "subcategory":"Beauty Salon",
            "type":"Services"
        }
    ],
    "sg:phone":"+1 310 726 0470",
    "sg:postcode":"90266",
    "sg:province":"CA",
    "wof:name":"Murad Medical Spa",
    "wof:placetype":"venue"
},
  "geometry": {"coordinates":[-118.387623,33.901949],"type":"Point"}
}