{
  "type": "Feature",
  "properties": {
    "addr:full":"25 Central Ave Los Gatos CA 95030",
    "addr:housenumber":"25",
    "addr:postcode":"95030",
    "addr:street":"Central Ave",
    "iso:country":"US",
    "sg:address":"25 Central Ave",
    "sg:city":"Los Gatos",
    "sg:classifiers":[
        {
            "category":"Social Services",
            "type":"Services"
        }
    ],
    "sg:phone":"+1 408 399 4611",
    "sg:postcode":"95030",
    "sg:province":"CA",
    "sg:tags":[
        "agency",
        "adoption"
    ],
    "wof:name":"Stephen Ravel Law Offices",
    "wof:placetype":"venue"
},
  "geometry": {"coordinates":[-121.976299,37.216406],"type":"Point"}
}