{
  "type": "Feature",
  "properties": {
    "iso:country":"US",
    "sg:address":"5993 Florin Rd",
    "sg:city":"Sacramento",
    "sg:classifiers":[
        {
            "category":"Shopping",
            "subcategory":"Bicycles & Sporting Goods",
            "type":"Retail Goods"
        }
    ],
    "sg:phone":"+1 916 428 4767",
    "sg:postcode":"95823",
    "sg:province":"CA",
    "wof:name":"Sports Fever",
    "wof:placetype":"venue"
},
  "geometry": {"coordinates":[-121.435086,38.496154],"type":"Point"}
}