{
  "type": "Feature",
  "properties": {
    "addr:full":"20700 Lassen St Chatsworth CA 91311",
    "addr:housenumber":"20700",
    "addr:postcode":"91311",
    "addr:street":"Lassen St",
    "iso:country":"US",
    "sg:address":"20700 Lassen St",
    "sg:city":"Chatsworth",
    "sg:classifiers":[
        {
            "category":"Manufacturing",
            "subcategory":"Electronics",
            "type":"Manufacturing & Wholesale Goods"
        }
    ],
    "sg:phone":"+1 818 678 0011",
    "sg:postcode":"91311",
    "sg:province":"CA",
    "sg:tags":[
        "equipment",
        "electronic",
        "supply"
    ],
    "wof:name":"Dynatrol National Corp",
    "wof:placetype":"venue"
},
  "geometry": {"coordinates":[-118.58855200000001,34.24998],"type":"Point"}
}