{
  "type": "Feature",
  "properties": {
    "iso:country":"US",
    "sg:address":"3901 Carter Ave",
    "sg:city":"Riverside",
    "sg:classifiers":[
        {
            "category":"Building & Trades",
            "subcategory":"Construction",
            "type":"Services"
        }
    ],
    "sg:phone":"+1 951 787 4844",
    "sg:postcode":"92501",
    "sg:province":"CA",
    "sg:tags":[
        "insulation",
        "heat",
        "contractor"
    ],
    "wof:name":"Empire Insulation",
    "wof:placetype":"venue"
},
  "geometry": {"coordinates":[-117.36521500000001,34.010475],"type":"Point"}
}