{
  "type": "Feature",
  "properties": {
    "addr:full":"14515 Mercado Ave La Mirada CA 90638",
    "addr:housenumber":"14515",
    "addr:postcode":"90638",
    "addr:street":"Mercado Ave",
    "iso:country":"US",
    "sg:address":"14515 Mercado Ave",
    "sg:city":"La Mirada",
    "sg:classifiers":[
        {
            "category":"Building & Trades",
            "subcategory":"Landscaping Services",
            "type":"Services"
        }
    ],
    "sg:phone":"+1 714 523 3131",
    "sg:postcode":"90638",
    "sg:province":"CA",
    "sg:tags":[
        "landscape",
        "contractor"
    ],
    "wof:name":"Rubio's Landscape",
    "wof:placetype":"venue"
},
  "geometry": {"coordinates":[-117.990284,33.899946],"type":"Point"}
}