{
  "type": "Feature",
  "properties": {
    "iso:country":"US",
    "sg:address":"4229 Northgate Blvd",
    "sg:city":"Sacramento",
    "sg:classifiers":[
        {
            "category":"Wholesale",
            "subcategory":"Machinery & Supplies",
            "type":"Manufacturing & Wholesale Goods"
        },
        {
            "category":"Wholesale",
            "subcategory":"Office Equipment",
            "type":"Manufacturing & Wholesale Goods"
        }
    ],
    "sg:phone":"+1 916 422 3131",
    "sg:postcode":"95834",
    "sg:province":"CA",
    "sg:tags":[
        "color",
        "machine",
        "distributes",
        "imaging",
        "labeling"
    ],
    "sg:website":"www.imagesupply.com",
    "wof:name":"Image Supply",
    "wof:placetype":"venue"
},
  "geometry": {"coordinates":[-121.47559699999999,38.645399],"type":"Point"}
}