{
  "type": "Feature",
  "properties": {
    "addr:full":"221 Court St Woodland CA 95695",
    "addr:housenumber":"221",
    "addr:postcode":"95695",
    "addr:street":"Court St",
    "iso:country":"US",
    "sg:address":"221 Court St",
    "sg:city":"Woodland",
    "sg:classifiers":[
        {
            "category":"Arts & Performance",
            "subcategory":"Theater",
            "type":"Entertainment"
        }
    ],
    "sg:phone":"+1 530 662 9333",
    "sg:postcode":"95695",
    "sg:province":"CA",
    "sg:tags":[
        "bureau"
    ],
    "wof:name":"Rocky & The Revelletts",
    "wof:placetype":"venue"
},
  "geometry": {"coordinates":[-121.778426,38.678852],"type":"Point"}
}