{
  "type": "Feature",
  "properties": {
    "iso:country":"US",
    "sg:address":"122 Second Street Suite 212",
    "sg:city":"San Mateo",
    "sg:classifiers":[
        {
            "category":"Health Services",
            "subcategory":"Clinic",
            "type":"Services"
        },
        {
            "category":"Organizations",
            "subcategory":"Religious Organization",
            "type":"Services"
        }
    ],
    "sg:phone":"+1 650 430 4115",
    "sg:postcode":"94010",
    "sg:province":"CA",
    "sg:tags":[
        "counseling",
        "mental"
    ],
    "sg:website":"www.aheartcenteredlife.com",
    "wof:name":"Jenn Tasnim Savage",
    "wof:placetype":"venue"
},
  "geometry": {"coordinates":[-122.325062,37.564918],"type":"Point"}
}