{
  "type": "Feature",
  "properties": {
    "iso:country":"US",
    "sg:address":"3300 Overland Avenue",
    "sg:city":"Los Angeles",
    "sg:classifiers":[
        {
            "category":"Education",
            "subcategory":"School",
            "type":"Public Place"
        }
    ],
    "sg:phone":"+1 310 559 1991",
    "sg:postcode":"90034",
    "sg:province":"CA",
    "sg:website":"www.edboost.org",
    "wof:name":"Edboost Learning Center",
    "wof:placetype":"venue"
},
  "geometry": {"coordinates":[-118.413673,34.027629],"type":"Point"}
}