{
  "type": "Feature",
  "properties": {
    "iso:country":"US",
    "sg:address":"1508 Main St",
    "sg:city":"St Helena",
    "sg:classifiers":[
        {
            "category":"Real Estate",
            "subcategory":"Real Estate Agent",
            "type":"Services"
        }
    ],
    "sg:phone":"+1 707 963 3678",
    "sg:postcode":"94574",
    "sg:province":"CA",
    "sg:tags":[
        "management"
    ],
    "wof:name":"Buller & Co Property Mgmt",
    "wof:placetype":"venue"
},
  "geometry": {"coordinates":[-122.473086,38.507034],"type":"Point"}
}