{
  "type": "Feature",
  "properties": {
    "addr:full":"6060 Sunrise Blvd Citrus Heights CA 95610",
    "addr:housenumber":"6060",
    "addr:postcode":"95610",
    "addr:street":"Sunrise Blvd",
    "iso:country":"US",
    "sg:address":"6060 Sunrise Blvd",
    "sg:city":"Citrus Heights",
    "sg:classifiers":[
        {
            "category":"Social Services",
            "type":"Services"
        }
    ],
    "sg:phone":"+1 916 729 2721",
    "sg:postcode":"95610",
    "sg:province":"CA",
    "sg:tags":[
        "organization",
        "welfare"
    ],
    "wof:name":"Crossroads Treatment Ctr",
    "wof:placetype":"venue"
},
  "geometry": {"coordinates":[-121.271434,38.674479],"type":"Point"}
}