{
  "type": "Feature",
  "properties": {
    "addr:full":"3827 W Sunset Blvd Los Angeles CA 90026",
    "addr:housenumber":"3827",
    "addr:postcode":"90026",
    "addr:street":"W Sunset Blvd",
    "iso:country":"US",
    "sg:address":"3827 W Sunset Blvd",
    "sg:city":"Los Angeles",
    "sg:classifiers":[
        {
            "category":"Home & Garden",
            "subcategory":"Household Appliances",
            "type":"Retail Goods"
        },
        {
            "category":"Retail",
            "subcategory":"Repair Shop",
            "type":"Services"
        }
    ],
    "sg:phone":"+1 323 660 6306",
    "sg:postcode":"90026",
    "sg:province":"CA",
    "sg:tags":[
        "machine",
        "sewing"
    ],
    "wof:name":"Filamco Sewing Center",
    "wof:placetype":"venue"
},
  "geometry": {"coordinates":[-118.279403,34.091507],"type":"Point"}
}