{
  "type": "Feature",
  "properties": {
    "addr:full":"3215 Tragon St Madera CA 93637",
    "addr:housenumber":"3215",
    "addr:postcode":"93637",
    "addr:street":"Tragon St",
    "iso:country":"US",
    "sg:address":"3215 Tragon St",
    "sg:city":"Madera",
    "sg:classifiers":[
        {
            "category":"Professional",
            "subcategory":"Advertising",
            "type":"Services"
        }
    ],
    "sg:phone":"+1 559 661 7500",
    "sg:postcode":"93637",
    "sg:province":"CA",
    "sg:tags":[
        "distribution"
    ],
    "wof:name":"Greg Chambers Distributing",
    "wof:placetype":"venue"
},
  "geometry": {"coordinates":[-120.09864,36.963736],"type":"Point"}
}