{
  "type": "Feature",
  "properties": {
    "addr:full":"692 Barber Ln Milpitas CA 95035",
    "addr:housenumber":"692",
    "addr:postcode":"95035",
    "addr:street":"Barber Ln",
    "iso:country":"US",
    "sg:address":"692 Barber Ln",
    "sg:city":"Milpitas",
    "sg:classifiers":[
        {
            "category":"Shopping",
            "subcategory":"Jewelry",
            "type":"Retail Goods"
        }
    ],
    "sg:phone":"+1 408 383 9668",
    "sg:postcode":"95035",
    "sg:province":"CA",
    "sg:tags":[
        "jeweler"
    ],
    "wof:name":"N W Jewelry",
    "wof:placetype":"venue"
},
  "geometry": {"coordinates":[-121.917075,37.419856],"type":"Point"}
}