{
  "type": "Feature",
  "properties": {
    "iso:country":"US",
    "sg:address":"906 11th Ave",
    "sg:city":"Delano",
    "sg:classifiers":[
        {
            "category":"Restaurant",
            "type":"Food & Drink"
        }
    ],
    "sg:phone":"+1 661 725 7025",
    "sg:postcode":"93215",
    "sg:province":"CA",
    "sg:tags":[
        "shop",
        "coffee"
    ],
    "wof:name":"Cafe Latte",
    "wof:placetype":"venue"
},
  "geometry": {"coordinates":[-119.24467,35.770518],"type":"Point"}
}