{
  "type": "Feature",
  "properties": {
    "iso:country":"US",
    "sg:address":"1830 Soscol Ave",
    "sg:city":"Napa",
    "sg:classifiers":[
        {
            "category":"Personal",
            "subcategory":"Beauty Salon",
            "type":"Services"
        }
    ],
    "sg:phone":"+1 707 258 2217",
    "sg:postcode":"94559",
    "sg:province":"CA",
    "wof:name":"Bella Vita",
    "wof:placetype":"venue"
},
  "geometry": {"coordinates":[-122.28501,38.308042],"type":"Point"}
}