{
  "type": "Feature",
  "properties": {
    "addr:full":"700 National Ct Richmond CA 94804",
    "addr:housenumber":"700",
    "addr:postcode":"94804",
    "addr:street":"National Ct",
    "iso:country":"US",
    "sg:address":"700 National Ct",
    "sg:city":"Richmond",
    "sg:classifiers":[
        {
            "category":"Food & Beverages",
            "subcategory":"Liquor & Beverages",
            "type":"Retail Goods"
        }
    ],
    "sg:phone":"+1 510 729 5000",
    "sg:postcode":"94804",
    "sg:province":"CA",
    "sg:tags":[
        "beer",
        "ale",
        "bottler",
        "beverages-distributors"
    ],
    "sg:website":"http://www.bayareabev.com",
    "wof:name":"Bay Area Beverage",
    "wof:placetype":"venue"
},
  "geometry": {"coordinates":[-122.377634,37.92831],"type":"Point"}
}