{
  "type": "Feature",
  "properties": {
    "iso:country":"US",
    "sg:address":"10595 Lawson River Ave",
    "sg:city":"Fountain Valley",
    "sg:classifiers":[
        {
            "category":"Retail",
            "subcategory":"Auto Repair",
            "type":"Services"
        }
    ],
    "sg:phone":"+1 714 378 3966",
    "sg:postcode":"92708",
    "sg:province":"CA",
    "sg:tags":[
        "detailing"
    ],
    "sg:website":"www.hbspeed.com",
    "wof:name":"HB Speed Inc.",
    "wof:placetype":"venue"
},
  "geometry": {"coordinates":[-117.944036,33.69673],"type":"Point"}
}