{
  "type": "Feature",
  "properties": {
    "iso:country":"US",
    "sg:address":"8533 Production Ave",
    "sg:city":"San Diego",
    "sg:classifiers":[
        {
            "category":"Building & Trades",
            "subcategory":"Construction",
            "type":"Services"
        }
    ],
    "sg:phone":"+1 858 514 8824",
    "sg:postcode":"92121",
    "sg:province":"CA",
    "sg:tags":[
        "tile",
        "dealer"
    ],
    "sg:website":"www.afdon.com",
    "wof:name":"Afdon Contracting Ca Inc",
    "wof:placetype":"venue"
},
  "geometry": {"coordinates":[-117.16494400000001,32.885099],"type":"Point"}
}