{
  "type": "Feature",
  "properties": {
    "iso:country":"US",
    "sg:address":"14521 Dickens St",
    "sg:city":"Sherman Oaks",
    "sg:classifiers":[
        {
            "category":"Professional",
            "subcategory":"Art Services",
            "type":"Services"
        }
    ],
    "sg:phone":"+1 818 907 2787",
    "sg:postcode":"91403",
    "sg:province":"CA",
    "sg:tags":[
        "artist"
    ],
    "wof:name":"Henri & Fildi Artist Mgmt",
    "wof:placetype":"venue"
},
  "geometry": {"coordinates":[-118.45124800000001,34.150417],"type":"Point"}
}