{
  "type": "Feature",
  "properties": {
    "addr:full":"1160 Civic Center Blvd Yuba City CA 95993",
    "addr:housenumber":"1160",
    "addr:postcode":"95993",
    "addr:street":"Civic Center Blvd",
    "iso:country":"US",
    "sg:address":"1160 Civic Center Blvd",
    "sg:city":"Yuba City",
    "sg:classifiers":[
        {
            "category":"Government",
            "subcategory":"Office",
            "type":"Public Place"
        }
    ],
    "sg:phone":"+1 530 822 7450",
    "sg:postcode":"95993",
    "sg:province":"CA",
    "wof:name":"Sutter Cnty Road Commissioner",
    "wof:placetype":"venue"
},
  "geometry": {"coordinates":[-121.63929899999999,39.142999],"type":"Point"}
}