{
  "type": "Feature",
  "properties": {
    "iso:country":"US",
    "sg:address":"9239 Kyle Ct",
    "sg:city":"Windsor",
    "sg:classifiers":[
        {
            "category":"Restaurant",
            "type":"Food & Drink"
        }
    ],
    "sg:phone":"+1 707 869 0481",
    "sg:postcode":"95492",
    "sg:province":"CA",
    "wof:name":"River Inn Restaurant",
    "wof:placetype":"venue"
},
  "geometry": {"coordinates":[-122.81792299999999,38.550738],"type":"Point"}
}