{
  "type": "Feature",
  "properties": {
    "iso:country":"US",
    "sg:address":"1907 Fillmore Street",
    "sg:city":"San Francisco",
    "sg:classifiers":[
        {
            "category":"Health Services",
            "subcategory":"Optometrist",
            "type":"Services"
        },
        {
            "category":"Shopping",
            "subcategory":"Optician",
            "type":"Retail Goods"
        }
    ],
    "sg:phone":"+1 415 563 9003",
    "sg:postcode":"94115",
    "sg:province":"CA",
    "sg:tags":[
        "eyewear"
    ],
    "sg:website":"www.invisionopto.com",
    "wof:name":"Invision Optometry",
    "wof:placetype":"venue"
},
  "geometry": {"coordinates":[-122.433998,37.787201],"type":"Point"}
}