{
  "type": "Feature",
  "properties": {
    "iso:country":"US",
    "sg:address":"2001 Marine World Pkwy",
    "sg:city":"Vallejo",
    "sg:classifiers":[
        {
            "category":"Professional",
            "type":"Services"
        }
    ],
    "sg:phone":"+1 707 648 9547",
    "sg:postcode":"94589",
    "sg:province":"CA",
    "sg:tags":[
        "establishment"
    ],
    "wof:name":"Envisioneering",
    "wof:placetype":"venue"
},
  "geometry": {"coordinates":[-122.24629,38.142036],"type":"Point"}
}