{
  "type": "Feature",
  "properties": {
    "addr:full":"1583 Sloat Boulevard San Francisco CA 94132",
    "addr:housenumber":"1583",
    "addr:postcode":"94132",
    "addr:street":"Sloat Boulevard",
    "iso:country":"US",
    "sg:address":"1583 Sloat Boulevard",
    "sg:city":"San Francisco",
    "sg:classifiers":[
        {
            "category":"Wholesale",
            "subcategory":"Home Furnishings",
            "type":"Manufacturing & Wholesale Goods"
        }
    ],
    "sg:phone":"+1 415 665 3669",
    "sg:postcode":"94132",
    "sg:province":"CA",
    "sg:tags":[
        "blind",
        "shade"
    ],
    "wof:name":"3 Day Blinds",
    "wof:placetype":"venue"
},
  "geometry": {"coordinates":[-122.489998,37.733898],"type":"Point"}
}