{
  "type": "Feature",
  "properties": {
    "iso:country":"US",
    "sg:address":"557 E Bonita Ave",
    "sg:city":"San Dimas",
    "sg:classifiers":[
        {
            "category":"Utilities",
            "subcategory":"Mobile Phone",
            "type":"Services"
        }
    ],
    "sg:phone":"+1 909 599 7697",
    "sg:postcode":"91773",
    "sg:province":"CA",
    "sg:tags":[
        "telephone",
        "cellular"
    ],
    "wof:name":"California Service Network",
    "wof:placetype":"venue"
},
  "geometry": {"coordinates":[-117.796551,34.10673],"type":"Point"}
}