{
  "type": "Feature",
  "properties": {
    "iso:country":"US",
    "sg:address":"1057 N Aviation Blvd",
    "sg:city":"Redondo Beach",
    "sg:classifiers":[
        {
            "category":"Communications",
            "subcategory":"Newspaper",
            "type":"Services"
        },
        {
            "category":"Professional",
            "subcategory":"Art Services",
            "type":"Services"
        }
    ],
    "sg:phone":"+1 310 318 1650",
    "sg:postcode":"90266",
    "sg:province":"CA",
    "sg:tags":[
        "print",
        "medium",
        "graphic",
        "design"
    ],
    "sg:website":"www.pelican-signs.com",
    "wof:name":"Pelican Banners & Signs",
    "wof:placetype":"venue"
},
  "geometry": {"coordinates":[-118.382851,33.896957],"type":"Point"}
}