{
  "type": "Feature",
  "properties": {
    "iso:country":"US",
    "sg:address":"5601 Watt Avenue",
    "sg:city":"North Highlands",
    "sg:classifiers":[
        {
            "category":"Food & Beverages",
            "subcategory":"Groceries & Convenience Stores",
            "type":"Retail Goods"
        }
    ],
    "sg:phone":"+1 916 332 1870",
    "sg:postcode":"95660",
    "sg:province":"CA",
    "wof:name":"Emmanuel Food & Produce",
    "wof:placetype":"venue"
},
  "geometry": {"coordinates":[-121.38311400000001,38.66863],"type":"Point"}
}