{
  "type": "Feature",
  "properties": {
    "iso:country":"US",
    "sg:address":"4060 Morena Blvd",
    "sg:city":"San Diego",
    "sg:classifiers":[
        {
            "category":"Wholesale",
            "subcategory":"Non-durable Goods",
            "type":"Manufacturing & Wholesale Goods"
        }
    ],
    "sg:phone":"+1 858 483 3200",
    "sg:postcode":"92110",
    "sg:province":"CA",
    "sg:tags":[
        "interior"
    ],
    "sg:website":"www.maustinfloors.com",
    "wof:name":"M Austin Designer Floors",
    "wof:placetype":"venue"
},
  "geometry": {"coordinates":[-117.223974,32.819358],"type":"Point"}
}