{
  "type": "Feature",
  "properties": {
    "addr:full":"23300 Cinema Dr Ste 220 Santa Clarita CA 91355",
    "addr:housenumber":"23300",
    "addr:postcode":"91355",
    "addr:street":"Cinema Dr Ste 220",
    "iso:country":"US",
    "sg:address":"23300 Cinema Dr Ste 220",
    "sg:city":"Santa Clarita",
    "sg:classifiers":[
        {
            "category":"Professional",
            "subcategory":"Lawyer & Legal Services",
            "type":"Services"
        }
    ],
    "sg:phone":"+1 661 260 1149",
    "sg:postcode":"91355",
    "sg:province":"CA",
    "wof:name":"Drescher Law Firm",
    "wof:placetype":"venue"
},
  "geometry": {"coordinates":[-118.542034,34.419152],"type":"Point"}
}