{
  "type": "Feature",
  "properties": {
    "iso:country":"US",
    "sg:address":"1530 The Alameda",
    "sg:city":"San Jose",
    "sg:classifiers":[
        {
            "category":"Professional",
            "subcategory":"Computer Services",
            "type":"Services"
        }
    ],
    "sg:phone":"+1 408 278 7650",
    "sg:postcode":"95126",
    "sg:province":"CA",
    "sg:tags":[
        "system",
        "cad"
    ],
    "sg:website":"www.solution-ware.com",
    "wof:name":"Solutionware Corp",
    "wof:placetype":"venue"
},
  "geometry": {"coordinates":[-121.915477,37.334485],"type":"Point"}
}