{
  "type": "Feature",
  "properties": {
    "addr:full":"4040 Sonoma Hwy Santa Rosa CA 95409",
    "addr:housenumber":"4040",
    "addr:postcode":"95409",
    "addr:street":"Sonoma Hwy",
    "iso:country":"US",
    "sg:address":"4040 Sonoma Hwy",
    "sg:city":"Santa Rosa",
    "sg:classifiers":[
        {
            "category":"Shopping",
            "type":"Retail Goods"
        }
    ],
    "sg:phone":"+1 707 539 3777",
    "sg:postcode":"95409",
    "sg:province":"CA",
    "sg:tags":[
        "tropical",
        "fish"
    ],
    "wof:name":"Critters",
    "wof:placetype":"venue"
},
  "geometry": {"coordinates":[-122.678584,38.456204],"type":"Point"}
}