{
  "type": "Feature",
  "properties": {
    "iso:country":"US",
    "sg:address":"12312 Culver Blvd",
    "sg:city":"Los Angeles",
    "sg:classifiers":[
        {
            "category":"Government",
            "subcategory":"City Hall",
            "type":"Public Place"
        }
    ],
    "sg:phone":"+1 310 202 4501",
    "sg:postcode":"90066",
    "sg:province":"CA",
    "sg:website":"www.lapdonline.org/pacific_commu...",
    "wof:name":"Pacific Community Police Station",
    "wof:placetype":"venue"
},
  "geometry": {"coordinates":[-118.42103299999999,33.990817],"type":"Point"}
}