{
  "type": "Feature",
  "properties": {
    "addr:full":"3075 Alvarado St San Leandro CA 94577",
    "addr:housenumber":"3075",
    "addr:postcode":"94577",
    "addr:street":"Alvarado St",
    "iso:country":"US",
    "sg:address":"3075 Alvarado St",
    "sg:city":"San Leandro",
    "sg:classifiers":[
        {
            "category":"Shopping",
            "subcategory":"Discount & Variety Stores",
            "type":"Retail Goods"
        }
    ],
    "sg:phone":"+1 510 352 4800",
    "sg:postcode":"94577",
    "sg:province":"CA",
    "sg:tags":[
        "wholesale"
    ],
    "wof:name":"Union Store Supplies & Fixtures",
    "wof:placetype":"venue"
},
  "geometry": {"coordinates":[-122.15245299999999,37.705953],"type":"Point"}
}