{
  "type": "Feature",
  "properties": {
    "addr:full":"1542 48th Ave San Francisco CA 94122",
    "addr:housenumber":"1542",
    "addr:postcode":"94122",
    "addr:street":"48Th Ave",
    "iso:country":"US",
    "sg:address":"1542 48th Ave",
    "sg:city":"San Francisco",
    "sg:classifiers":[
        {
            "category":"Professional",
            "subcategory":"Computer Services",
            "type":"Services"
        }
    ],
    "sg:phone":"+1 415 254 5725",
    "sg:postcode":"94122",
    "sg:province":"CA",
    "wof:name":"Butter Present's Juvio Tech",
    "wof:placetype":"venue"
},
  "geometry": {"coordinates":[-122.507774,37.757403],"type":"Point"}
}