{
  "type": "Feature",
  "properties": {
    "addr:full":"11761 Ridge Rd Grass Valley CA 95945",
    "addr:housenumber":"11761",
    "addr:postcode":"95945",
    "addr:street":"Ridge Rd",
    "iso:country":"US",
    "sg:address":"11761 Ridge Rd",
    "sg:city":"Grass Valley",
    "sg:classifiers":[
        {
            "category":"Education",
            "subcategory":"School",
            "type":"Public Place"
        }
    ],
    "sg:phone":"+1 530 273 4431",
    "sg:postcode":"95945",
    "sg:province":"CA",
    "sg:website":"www.nuhsd.k12.ca.us",
    "wof:name":"Nevada Union High School",
    "wof:placetype":"venue"
},
  "geometry": {"coordinates":[-121.058549,39.238665],"type":"Point"}
}