{
  "type": "Feature",
  "properties": {
    "addr:full":"6135 Tam O Shanter Dr Stockton CA 95210",
    "addr:housenumber":"6135",
    "addr:postcode":"95210",
    "addr:street":"Tam O Shanter Dr",
    "iso:country":"US",
    "sg:address":"6135 Tam O Shanter Dr",
    "sg:city":"Stockton",
    "sg:classifiers":[
        {
            "category":"Professional",
            "subcategory":"Management & Consulting",
            "type":"Services"
        }
    ],
    "sg:phone":"+1 209 951 4088",
    "sg:postcode":"95210",
    "sg:province":"CA",
    "sg:tags":[
        "consultant",
        "publishing"
    ],
    "wof:name":"Image Connection",
    "wof:placetype":"venue"
},
  "geometry": {"coordinates":[-121.296632,38.010934],"type":"Point"}
}