{
  "type": "Feature",
  "properties": {
    "addr:full":"547 S Riverside Ave Rialto CA 92376",
    "addr:housenumber":"547",
    "addr:postcode":"92376",
    "addr:street":"S Riverside Ave",
    "iso:country":"US",
    "sg:address":"547 S Riverside Ave",
    "sg:city":"Rialto",
    "sg:classifiers":[
        {
            "category":"Personal",
            "subcategory":"Beauty Salon",
            "type":"Services"
        }
    ],
    "sg:phone":"+1 909 421 8033",
    "sg:postcode":"92376",
    "sg:province":"CA",
    "wof:name":"Mystique Beauty Salon & Barber",
    "wof:placetype":"venue"
},
  "geometry": {"coordinates":[-117.370279,34.089962],"type":"Point"}
}