{
  "type": "Feature",
  "properties": {
    "iso:country":"US",
    "sg:address":"625 I St",
    "sg:city":"Modesto",
    "sg:classifiers":[
        {
            "category":"Social Services",
            "type":"Services"
        }
    ],
    "sg:phone":"+1 209 522 3209",
    "sg:postcode":"95354",
    "sg:province":"CA",
    "sg:tags":[
        "organization",
        "welfare"
    ],
    "wof:name":"Salvation Army",
    "wof:placetype":"venue"
},
  "geometry": {"coordinates":[-121.00223699999999,37.637288],"type":"Point"}
}