{
  "type": "Feature",
  "properties": {
    "addr:full":"1234 Valencia Street San Francisco CA 94110",
    "addr:housenumber":"1234",
    "addr:postcode":"94110",
    "addr:street":"Valencia Street",
    "iso:country":"US",
    "sg:address":"1234 Valencia Street",
    "sg:city":"San Francisco",
    "sg:classifiers":[
        {
            "category":"Personal",
            "subcategory":"Massage",
            "type":"Services"
        },
        {
            "category":"Sports & Exercise",
            "subcategory":"Gym",
            "type":"Entertainment"
        }
    ],
    "sg:phone":"+1 415 647 9707",
    "sg:postcode":"94110",
    "sg:province":"CA",
    "sg:tags":[
        "yoga"
    ],
    "sg:website":"yogatreesf.com",
    "wof:name":"Yoga Tree",
    "wof:placetype":"venue"
},
  "geometry": {"coordinates":[-122.420998,37.753101],"type":"Point"}
}