{
  "type": "Feature",
  "properties": {
    "addr:full":"665 Bush St San Francisco CA 94108",
    "addr:housenumber":"665",
    "addr:postcode":"94108",
    "addr:street":"Bush St",
    "iso:country":"US",
    "sg:address":"665 Bush St",
    "sg:city":"San Francisco",
    "sg:classifiers":[
        {
            "category":"Restaurant",
            "type":"Food & Drink"
        }
    ],
    "sg:menulink":"http://www.allmenus.com/ca/san-francisco/267329-daffodil/menu/",
    "sg:phone":"+1 415 343 0130",
    "sg:postcode":"94108",
    "sg:province":"CA",
    "sg:tags":[
        "new",
        "american"
    ],
    "wof:name":"Daffodil",
    "wof:placetype":"venue"
},
  "geometry": {"coordinates":[-122.40844,37.79001],"type":"Point"}
}