{
  "type": "Feature",
  "properties": {
    "iso:country":"US",
    "sg:address":"5982 Via Loma",
    "sg:city":"Riverside",
    "sg:classifiers":[
        {
            "category":"Health Services",
            "subcategory":"Doctor",
            "type":"Services"
        },
        {
            "category":"Professional",
            "subcategory":"Detective & Security Services",
            "type":"Services"
        }
    ],
    "sg:phone":"+1 951 369 0540",
    "sg:postcode":"92506",
    "sg:province":"CA",
    "sg:tags":[
        "medicine",
        "physician",
        "forensic",
        "surgeons",
        "consultant"
    ],
    "sg:website":"http://www.forensiconline.com",
    "wof:name":"Forensic Pathologist",
    "wof:placetype":"venue"
},
  "geometry": {"coordinates":[-117.33627199999999,33.942312],"type":"Point"}
}