{
  "type": "Feature",
  "properties": {
    "addr:full":"9171 de Soto Ave Chatsworth CA 91311",
    "addr:housenumber":"9171",
    "addr:postcode":"91311",
    "addr:street":"De Soto Ave",
    "iso:country":"US",
    "sg:address":"9171 de Soto Ave",
    "sg:city":"Chatsworth",
    "sg:classifiers":[
        {
            "category":"Shopping",
            "subcategory":"Bicycles & Sporting Goods",
            "type":"Retail Goods"
        }
    ],
    "sg:phone":"+1 818 996 2695",
    "sg:postcode":"91311",
    "sg:province":"CA",
    "sg:tags":[
        "apparel",
        "bowling",
        "accessory"
    ],
    "wof:name":"Perfect Game Pro Shop",
    "wof:placetype":"venue"
},
  "geometry": {"coordinates":[-118.588611,34.237942],"type":"Point"}
}