{
  "type": "Feature",
  "properties": {
    "iso:country":"US",
    "sg:address":"1303 I St",
    "sg:city":"Modesto",
    "sg:classifiers":[
        {
            "category":"Professional",
            "subcategory":"Business Services",
            "type":"Services"
        }
    ],
    "sg:phone":"+1 209 577 8677",
    "sg:postcode":"95354",
    "sg:province":"CA",
    "sg:tags":[
        "eviction"
    ],
    "wof:name":"Guarantee Eviction Svc",
    "wof:placetype":"venue"
},
  "geometry": {"coordinates":[-120.995386,37.642446],"type":"Point"}
}