{
  "type": "Feature",
  "properties": {
    "iso:country":"US",
    "sg:address":"558 Sacramento St",
    "sg:city":"San Francisco",
    "sg:classifiers":[
        {
            "category":"Professional",
            "subcategory":"Lawyer & Legal Services",
            "type":"Services"
        }
    ],
    "sg:phone":"+1 415 421 4900",
    "sg:postcode":"94111",
    "sg:province":"CA",
    "sg:tags":[
        "attorney"
    ],
    "wof:name":"Eric L Laurence Law Offices",
    "wof:placetype":"venue"
},
  "geometry": {"coordinates":[-122.40286399999999,37.793871],"type":"Point"}
}