{
  "type": "Feature",
  "properties": {
    "addr:full":"4527 S Broadway Los Angeles CA 90037",
    "addr:housenumber":"4527",
    "addr:postcode":"90037",
    "addr:street":"S Broadway",
    "iso:country":"US",
    "sg:address":"4527 S Broadway",
    "sg:city":"Los Angeles",
    "sg:classifiers":[
        {
            "category":"Food & Beverages",
            "subcategory":"Groceries & Convenience Stores",
            "type":"Retail Goods"
        }
    ],
    "sg:phone":"+1 323 235 6150",
    "sg:postcode":"90037",
    "sg:province":"CA",
    "wof:name":"Mexico Discounts",
    "wof:placetype":"venue"
},
  "geometry": {"coordinates":[-118.27820699999999,34.002332],"type":"Point"}
}