{
  "type": "Feature",
  "properties": {
    "iso:country":"US",
    "sg:address":"1559 Westwood Blvd",
    "sg:city":"Los Angeles",
    "sg:classifiers":[
        {
            "category":"Health Services",
            "subcategory":"Clinic",
            "type":"Services"
        }
    ],
    "sg:phone":"+1 310 479 2223",
    "sg:postcode":"90024",
    "sg:province":"CA",
    "sg:tags":[
        "cannabis"
    ],
    "sg:website":"www.mmorrismd.com",
    "wof:name":"Michael Morris, MD",
    "wof:placetype":"venue"
},
  "geometry": {"coordinates":[-118.439835,34.053076],"type":"Point"}
}