{
  "type": "Feature",
  "properties": {
    "addr:full":"730 Tennessee St Vallejo CA 94590",
    "addr:housenumber":"730",
    "addr:postcode":"94590",
    "addr:street":"Tennessee St",
    "iso:country":"US",
    "sg:address":"730 Tennessee St",
    "sg:city":"Vallejo",
    "sg:classifiers":[
        {
            "category":"Real Estate",
            "subcategory":"Real Estate Services",
            "type":"Services"
        },
        {
            "category":"Real Estate",
            "subcategory":"Real Estate Agent",
            "type":"Services"
        }
    ],
    "sg:phone":"+1 707 552 6661",
    "sg:postcode":"94590",
    "sg:province":"CA",
    "sg:tags":[
        "buyer",
        "consultant",
        "management",
        "broker"
    ],
    "wof:name":"Nesci Laurie",
    "wof:placetype":"venue"
},
  "geometry": {"coordinates":[-122.250389,38.109928],"type":"Point"}
}