{
  "type": "Feature",
  "properties": {
    "addr:full":"5632 Melrose Ave Los Angeles CA 90038",
    "addr:housenumber":"5632",
    "addr:postcode":"90038",
    "addr:street":"Melrose Ave",
    "iso:country":"US",
    "sg:address":"5632 Melrose Ave",
    "sg:city":"Los Angeles",
    "sg:classifiers":[
        {
            "category":"Home & Garden",
            "subcategory":"Carpets & Floor Coverings",
            "type":"Retail Goods"
        }
    ],
    "sg:phone":"+1 323 931 0888",
    "sg:postcode":"90038",
    "sg:province":"CA",
    "sg:tags":[
        "dealer",
        "rug"
    ],
    "wof:name":"Ji Gallery",
    "wof:placetype":"venue"
},
  "geometry": {"coordinates":[-118.323402,34.083422],"type":"Point"}
}