{
  "type": "Feature",
  "properties": {
    "addr:full":"2661 Morley Way Sacramento CA 95864",
    "addr:housenumber":"2661",
    "addr:postcode":"95864",
    "addr:street":"Morley Way",
    "iso:country":"US",
    "sg:address":"2661 Morley Way",
    "sg:city":"Sacramento",
    "sg:classifiers":[
        {
            "category":"Building & Trades",
            "subcategory":"Plumbing",
            "type":"Services"
        }
    ],
    "sg:phone":"+1 916 483 3900",
    "sg:postcode":"95864",
    "sg:province":"CA",
    "sg:tags":[
        "plumber",
        "industrial",
        "contractors-commercial"
    ],
    "wof:name":"Metropolis Plumbing",
    "wof:placetype":"venue"
},
  "geometry": {"coordinates":[-121.40024200000001,38.567142],"type":"Point"}
}