{
  "type": "Feature",
  "properties": {
    "addr:full":"4096 Piedmont Ave 216 Oakland CA 94611",
    "addr:housenumber":"4096;216",
    "addr:postcode":"94611",
    "addr:street":"Piedmont Ave",
    "iso:country":"US",
    "sg:address":"4096 Piedmont Ave 216",
    "sg:city":"Oakland",
    "sg:classifiers":[
        {
            "category":"Professional",
            "type":"Services"
        }
    ],
    "sg:phone":"+1 510 636 4024",
    "sg:postcode":"94611",
    "sg:province":"CA",
    "sg:tags":[
        "processing",
        "data"
    ],
    "sg:website":"http://www.ebt1.com",
    "wof:name":"East Bay Transcription",
    "wof:placetype":"venue"
},
  "geometry": {"coordinates":[-122.252083,37.826669],"type":"Point"}
}