{
  "type": "Feature",
  "properties": {
    "iso:country":"US",
    "sg:address":"300 Diamond Dr",
    "sg:city":"Lake Elsinore",
    "sg:classifiers":[
        {
            "category":"Retail",
            "subcategory":"Auto Repair",
            "type":"Services"
        }
    ],
    "sg:phone":"+1 951 674 0794",
    "sg:postcode":"92530",
    "sg:province":"CA",
    "wof:name":"Express Tire & Automotive Service Center",
    "wof:placetype":"venue"
},
  "geometry": {"coordinates":[-117.300003,33.656601],"type":"Point"}
}