{
  "type": "Feature",
  "properties": {
    "addr:full":"16822 Hawthorne Blvd Lawndale CA 90260",
    "addr:housenumber":"16822",
    "addr:postcode":"ca 90260",
    "addr:street":"Hawthorne Blvd",
    "iso:country":"US",
    "sg:address":"16822 Hawthorne Blvd",
    "sg:city":"Lawndale",
    "sg:classifiers":[
        {
            "category":"Food & Beverages",
            "subcategory":"Groceries & Convenience Stores",
            "type":"Retail Goods"
        }
    ],
    "sg:phone":"+1 310 214 8101",
    "sg:postcode":"90260",
    "sg:province":"CA",
    "sg:tags":[
        "market"
    ],
    "wof:name":"S K Liquor & Market",
    "wof:placetype":"venue"
},
  "geometry": {"coordinates":[-118.351997,33.877701],"type":"Point"}
}