{
  "type": "Feature",
  "properties": {
    "addr:full":"50 Drumm Street San Francisco CA 94111",
    "addr:housenumber":"50",
    "addr:postcode":"94111",
    "addr:street":"Drumm Street",
    "iso:country":"US",
    "sg:address":"50 Drumm Street",
    "sg:city":"San Francisco",
    "sg:classifiers":[
        {
            "category":"Bars & Pubs",
            "subcategory":"Nightclub",
            "type":"Food & Drink"
        }
    ],
    "sg:phone":"+1 415 399 0222",
    "sg:postcode":"94111",
    "sg:province":"CA",
    "sg:tags":[
        "nightlife"
    ],
    "wof:name":"Il Massimo Lounge",
    "wof:placetype":"venue"
},
  "geometry": {"coordinates":[-122.396004,37.793598],"type":"Point"}
}