{
  "type": "Feature",
  "properties": {
    "addr:full":"2500 Hospital Dr Ste 5A Mountain View CA 94040",
    "addr:housenumber":"2500",
    "addr:postcode":"94040",
    "addr:street":"Hospital Dr Ste 5A",
    "iso:country":"US",
    "sg:address":"2500 Hospital Dr Ste 5A",
    "sg:city":"Mountain View",
    "sg:classifiers":[
        {
            "category":"Health Services",
            "subcategory":"Dentist",
            "type":"Services"
        }
    ],
    "sg:phone":"+1 650 961 4211",
    "sg:postcode":"94040",
    "sg:province":"CA",
    "wof:name":"Fisher James W DDS",
    "wof:placetype":"venue"
},
  "geometry": {"coordinates":[-122.082041,37.369048],"type":"Point"}
}