{
  "type": "Feature",
  "properties": {
    "iso:country":"US",
    "sg:address":"72300 Highway 111",
    "sg:city":"Palm Desert",
    "sg:classifiers":[
        {
            "category":"Autos & Motor Vehicles",
            "subcategory":"Fuel & Gas Station",
            "type":"Retail Goods"
        }
    ],
    "sg:phone":"+1 760 346 0350",
    "sg:postcode":"92260",
    "sg:province":"CA",
    "wof:name":"Tesoro West Coast Company",
    "wof:placetype":"venue"
},
  "geometry": {"coordinates":[-116.40260600000001,33.7287],"type":"Point"}
}