{
  "type": "Feature",
  "properties": {
    "addr:full":"6116 Lockhurst Dr Woodland Hills CA 91367",
    "addr:housenumber":"6116",
    "addr:postcode":"91367",
    "addr:street":"Lockhurst Dr",
    "iso:country":"US",
    "sg:address":"6116 Lockhurst Dr",
    "sg:city":"Woodland Hills",
    "sg:classifiers":[
        {
            "category":"Wholesale",
            "subcategory":"Groceries",
            "type":"Manufacturing & Wholesale Goods"
        }
    ],
    "sg:phone":"+1 818 346 0640",
    "sg:postcode":"91367",
    "sg:province":"CA",
    "sg:tags":[
        "general"
    ],
    "wof:name":"Bernie Goldman Food Broker",
    "wof:placetype":"venue"
},
  "geometry": {"coordinates":[-118.649328,34.180201],"type":"Point"}
}