{
  "type": "Feature",
  "properties": {
    "addr:full":"730 29th St Apt 114 Oakland CA 94609",
    "addr:housenumber":"730;114",
    "addr:postcode":"94609",
    "addr:street":"29Th St Apt",
    "iso:country":"US",
    "sg:address":"730 29th St Apt 114",
    "sg:city":"Oakland",
    "sg:classifiers":[
        {
            "category":"Farming",
            "subcategory":"Fish & Marine Products",
            "type":"Manufacturing & Wholesale Goods"
        },
        {
            "category":"Retail",
            "subcategory":"Repair Shop",
            "type":"Services"
        },
        {
            "category":"Professional",
            "subcategory":"Art Services",
            "type":"Services"
        }
    ],
    "sg:phone":"+1 510 893 5141",
    "sg:postcode":"94609",
    "sg:province":"CA",
    "sg:tags":[
        "picture",
        "frame",
        "restoration",
        "framing"
    ],
    "wof:name":"Jw Selsor Fine Art Framing & Services",
    "wof:placetype":"venue"
},
  "geometry": {"coordinates":[-122.27258500000001,37.818952],"type":"Point"}
}