{
  "type": "Feature",
  "properties": {
    "addr:full":"4455 Twain Ave San Diego CA 92120",
    "addr:housenumber":"4455",
    "addr:postcode":"92120",
    "addr:street":"Twain Ave",
    "iso:country":"US",
    "sg:address":"4455 Twain Ave",
    "sg:city":"San Diego",
    "sg:classifiers":[
        {
            "category":"Professional",
            "subcategory":"Detective & Security Services",
            "type":"Services"
        }
    ],
    "sg:phone":"+1 619 283 3168",
    "sg:postcode":"92120",
    "sg:province":"CA",
    "sg:tags":[
        "guard",
        "patrol"
    ],
    "wof:name":"Pacific Eagle Intl Security",
    "wof:placetype":"venue"
},
  "geometry": {"coordinates":[-117.10140800000001,32.784947],"type":"Point"}
}