{
  "type": "Feature",
  "properties": {
    "iso:country":"US",
    "sg:address":"3046 W Bullard Ave",
    "sg:city":"Fresno",
    "sg:classifiers":[
        {
            "category":"Restaurant",
            "type":"Food & Drink"
        }
    ],
    "sg:phone":"+1 559 435 2371",
    "sg:postcode":"93711",
    "sg:province":"CA",
    "wof:name":"El Mariachi Restaurant",
    "wof:placetype":"venue"
},
  "geometry": {"coordinates":[-119.844633,36.822723],"type":"Point"}
}