{
  "type": "Feature",
  "properties": {
    "iso:country":"US",
    "sg:address":"16351 Springdale St",
    "sg:city":"Huntington Beach",
    "sg:classifiers":[
        {
            "category":"Education",
            "subcategory":"Preschool",
            "type":"Public Place"
        },
        {
            "category":"Education",
            "subcategory":"School",
            "type":"Public Place"
        }
    ],
    "sg:phone":"+1 714 840 7117",
    "sg:postcode":"92649",
    "sg:province":"CA",
    "sg:tags":[
        "elementary"
    ],
    "wof:name":"Redeemer Lutheran Preschool & Kindergarten",
    "wof:placetype":"venue"
},
  "geometry": {"coordinates":[-118.024126,33.725102],"type":"Point"}
}