{
  "type": "Feature",
  "properties": {
    "addr:full":"21060 Homestead Road Suite 150 Cupertino CA 95014",
    "addr:housenumber":"21060",
    "addr:postcode":"95014",
    "addr:street":"Homestead Road Suite 150",
    "iso:country":"US",
    "sg:address":"21060 Homestead Road Suite 150",
    "sg:city":"Cupertino",
    "sg:classifiers":[
        {
            "category":"Professional",
            "subcategory":"Computer Services",
            "type":"Services"
        }
    ],
    "sg:phone":"+1 408 373 4027",
    "sg:postcode":"95014",
    "sg:province":"CA",
    "sg:tags":[
        "maps",
        "open-source",
        "bugzilla",
        "cvs",
        "subversion",
        "google-maps",
        "map-images",
        "map-pdf",
        "map-jpeg"
    ],
    "sg:website":"http://www.zeesource.net",
    "wof:name":"Zee Source",
    "wof:placetype":"venue"
},
  "geometry": {"coordinates":[-122.042598,37.337488],"type":"Point"}
}