{
  "type": "Feature",
  "properties": {
    "addr:full":"111 N Atlantic Blvd Monterey Park CA 91754",
    "addr:housenumber":"111",
    "addr:postcode":"91754",
    "addr:street":"N Atlantic Blvd",
    "iso:country":"US",
    "sg:address":"111 N Atlantic Blvd",
    "sg:city":"Monterey Park",
    "sg:classifiers":[
        {
            "category":"Shopping",
            "subcategory":"Adult",
            "type":"Retail Goods"
        }
    ],
    "sg:phone":"+1 626 642 7778",
    "sg:postcode":"91754",
    "sg:province":"CA",
    "sg:tags":[
        "entertainment"
    ],
    "wof:name":"01Club Com",
    "wof:placetype":"venue"
},
  "geometry": {"coordinates":[-118.13400300000001,34.062698],"type":"Point"}
}