{
  "type": "Feature",
  "properties": {
    "addr:full":"2600 14th St Sacramento CA 95818",
    "addr:housenumber":"2600",
    "addr:postcode":"95818",
    "addr:street":"14Th St",
    "iso:country":"US",
    "sg:address":"2600 14th St",
    "sg:city":"Sacramento",
    "sg:classifiers":[
        {
            "category":"Real Estate",
            "subcategory":"Architect",
            "type":"Services"
        }
    ],
    "sg:phone":"+1 916 442 0464",
    "sg:postcode":"95818",
    "sg:province":"CA",
    "sg:tags":[
        "architects'",
        "specification",
        "builders'",
        "construction",
        "architectural"
    ],
    "wof:name":"Axelrod Architecture & Fabric",
    "wof:placetype":"venue"
},
  "geometry": {"coordinates":[-121.495712,38.560749],"type":"Point"}
}