{
  "type": "Feature",
  "properties": {
    "addr:full":"The San Francisco Design Center 2 Henry Adams St Ste M45 San Francisco CA 94103",
    "addr:housenumber":"2",
    "addr:postcode":"94103",
    "addr:street":"Henry Adams St;M45",
    "iso:country":"US",
    "sg:address":"The San Francisco Design Center 2 Henry Adams St Ste M45",
    "sg:city":"San Francisco",
    "sg:classifiers":[
        {
            "category":"Building & Trades",
            "subcategory":"Construction",
            "type":"Services"
        },
        {
            "category":"Wholesale",
            "subcategory":"Home Furnishings",
            "type":"Manufacturing & Wholesale Goods"
        }
    ],
    "sg:phone":"+1 415 621 2777",
    "sg:postcode":"94103",
    "sg:province":"CA",
    "sg:tags":[
        "interior",
        "blind",
        "design",
        "shade"
    ],
    "sg:website":"www.theromanshadecompany.com",
    "wof:name":"The Roman Shade Company",
    "wof:placetype":"venue"
},
  "geometry": {"coordinates":[-122.404218,37.769612],"type":"Point"}
}