{
  "type": "Feature",
  "properties": {
    "iso:country":"US",
    "sg:address":"466 Foothill Blvd",
    "sg:city":"La Canada Fltrdg",
    "sg:classifiers":[
        {
            "category":"Personal",
            "subcategory":"Beauty Salon",
            "type":"Services"
        }
    ],
    "sg:phone":"+1 818 952 0005",
    "sg:postcode":"91011",
    "sg:province":"CA",
    "sg:tags":[
        "manicuring"
    ],
    "wof:name":"Perfect Nail",
    "wof:placetype":"venue"
},
  "geometry": {"coordinates":[-118.189009,34.199171],"type":"Point"}
}