{
  "type": "Feature",
  "properties": {
    "addr:full":"38525 Via de Oro Temecula CA 92592",
    "addr:housenumber":"38525",
    "addr:postcode":"92592",
    "addr:street":"Via De Oro",
    "iso:country":"US",
    "sg:address":"38525 Via de Oro",
    "sg:city":"Temecula",
    "sg:classifiers":[
        {
            "category":"Home & Garden",
            "subcategory":"Home Furnishings",
            "type":"Retail Goods"
        },
        {
            "category":"Home & Garden",
            "subcategory":"Building Materials",
            "type":"Retail Goods"
        },
        {
            "category":"Manufacturing",
            "subcategory":"Building Materials",
            "type":"Manufacturing & Wholesale Goods"
        }
    ],
    "sg:phone":"+1 951 302 5981",
    "sg:postcode":"92592",
    "sg:province":"CA",
    "sg:tags":[
        "draperies",
        "accessory",
        "window",
        "treatment",
        "doors",
        "frames",
        "curtain"
    ],
    "wof:name":"Homan's Custom Draperies",
    "wof:placetype":"venue"
},
  "geometry": {"coordinates":[-116.98972999999999,33.542489],"type":"Point"}
}