{
  "type": "Feature",
  "properties": {
    "iso:country":"US",
    "sg:address":"8615 Florence Ave",
    "sg:city":"Downey",
    "sg:classifiers":[
        {
            "category":"Personal",
            "subcategory":"Beauty Salon",
            "type":"Services"
        }
    ],
    "sg:phone":"+1 562 862 4155",
    "sg:postcode":"90240",
    "sg:province":"CA",
    "wof:name":"Marluz",
    "wof:placetype":"venue"
},
  "geometry": {"coordinates":[-118.11869,33.948381],"type":"Point"}
}