{
  "type": "Feature",
  "properties": {
    "iso:country":"US",
    "sg:address":"6851 Archibald Ave",
    "sg:city":"Corona",
    "sg:classifiers":[
        {
            "category":"Farming",
            "subcategory":"Dairy Farm",
            "type":"Manufacturing & Wholesale Goods"
        }
    ],
    "sg:phone":"+1 951 371 1797",
    "sg:postcode":"92880",
    "sg:province":"CA",
    "wof:name":"Vermeer & Goedhart",
    "wof:placetype":"venue"
},
  "geometry": {"coordinates":[-117.593101,33.965355],"type":"Point"}
}