{
  "type": "Feature",
  "properties": {
    "addr:full":"8400 Mammoth Ave Panorama City CA 91402",
    "addr:housenumber":"8400",
    "addr:postcode":"91402",
    "addr:street":"Mammoth Ave",
    "iso:country":"US",
    "sg:address":"8400 Mammoth Ave",
    "sg:city":"Panorama City",
    "sg:classifiers":[
        {
            "category":"Home & Garden",
            "subcategory":"Furniture",
            "type":"Retail Goods"
        }
    ],
    "sg:phone":"+1 818 893 5100",
    "sg:postcode":"91402",
    "sg:province":"CA",
    "wof:name":"Studio Wood Products",
    "wof:placetype":"venue"
},
  "geometry": {"coordinates":[-118.43424400000001,34.225384],"type":"Point"}
}