{
  "type": "Feature",
  "properties": {
    "addr:full":"4749 Coldwater Canyon Studio City CA 91604",
    "addr:housenumber":"4749",
    "addr:postcode":"91604",
    "addr:street":"Coldwater",
    "iso:country":"US",
    "sg:address":"4749 Coldwater Canyon",
    "sg:city":"Studio City",
    "sg:classifiers":[
        {
            "category":"Restaurant",
            "type":"Food & Drink"
        }
    ],
    "sg:phone":"+1 818 762 7771",
    "sg:postcode":"91604",
    "sg:province":"CA",
    "sg:tags":[
        "mexican"
    ],
    "sg:website":"www.hugostacos.com",
    "wof:name":"Hugo's Tacos",
    "wof:placetype":"venue"
},
  "geometry": {"coordinates":[-118.414001,34.157299],"type":"Point"}
}