{
  "type": "Feature",
  "properties": {
    "iso:country":"US",
    "sg:address":"77 N Cluff Ave",
    "sg:city":"Lodi",
    "sg:classifiers":[
        {
            "category":"Home & Garden",
            "subcategory":"Building Materials",
            "type":"Retail Goods"
        }
    ],
    "sg:phone":"+1 209 339 4307",
    "sg:postcode":"95240",
    "sg:province":"CA",
    "sg:tags":[
        "granite"
    ],
    "wof:name":"Omega Stone Solutions",
    "wof:placetype":"venue"
},
  "geometry": {"coordinates":[-121.252538,38.135613],"type":"Point"}
}