{
  "type": "Feature",
  "properties": {
    "addr:full":"5637 Solari Ranch Rd Stockton CA 95215",
    "addr:postcode":"5637;95215",
    "addr:street":"Solari Ranch Rd",
    "iso:country":"US",
    "sg:address":"5637 Solari Ranch Rd",
    "sg:city":"Stockton",
    "sg:classifiers":[
        {
            "category":"Building & Trades",
            "subcategory":"Construction",
            "type":"Services"
        }
    ],
    "sg:phone":"+1 209 931 1822",
    "sg:postcode":"95215",
    "sg:province":"CA",
    "sg:tags":[
        "contractor"
    ],
    "wof:name":"Silver Fern Constr & Rmdlng",
    "wof:placetype":"venue"
},
  "geometry": {"coordinates":[-121.227101,38.013742],"type":"Point"}
}