{
  "type": "Feature",
  "properties": {
    "addr:full":"1760 E 8th St Davis CA 95616",
    "addr:housenumber":"1760",
    "addr:postcode":"95616",
    "addr:street":"E 8Th St",
    "iso:country":"US",
    "sg:address":"1760 E 8th St",
    "sg:city":"Davis",
    "sg:classifiers":[
        {
            "category":"Food & Beverages",
            "subcategory":"Groceries & Convenience Stores",
            "type":"Retail Goods"
        }
    ],
    "sg:phone":"+1 530 756 4262",
    "sg:postcode":"95616",
    "sg:province":"CA",
    "wof:name":"International Food Market",
    "wof:placetype":"venue"
},
  "geometry": {"coordinates":[-121.727636,38.553301],"type":"Point"}
}