{
  "type": "Feature",
  "properties": {
    "iso:country":"US",
    "sg:address":"4501 Collwood Blvd",
    "sg:city":"San Diego",
    "sg:classifiers":[
        {
            "category":"Real Estate",
            "subcategory":"Real Estate Agent",
            "type":"Services"
        }
    ],
    "sg:phone":"+1 619 275 5757",
    "sg:postcode":"92115",
    "sg:province":"CA",
    "sg:tags":[
        "management"
    ],
    "wof:name":"J Harold Management Co",
    "wof:placetype":"venue"
},
  "geometry": {"coordinates":[-117.081321,32.760438],"type":"Point"}
}