{
  "type": "Feature",
  "properties": {
    "addr:full":"6808 San Fernando Rd Glendale CA 91201",
    "addr:housenumber":"6808",
    "addr:postcode":"91201",
    "addr:street":"San Fernando Rd",
    "iso:country":"US",
    "sg:address":"6808 San Fernando Rd",
    "sg:city":"Glendale",
    "sg:classifiers":[
        {
            "category":"Food & Beverages",
            "subcategory":"Liquor & Beverages",
            "type":"Retail Goods"
        }
    ],
    "sg:phone":"+1 818 842 5237",
    "sg:postcode":"91201",
    "sg:province":"CA",
    "sg:tags":[
        "beer",
        "spirit",
        "wine"
    ],
    "wof:name":"Castle Liquors",
    "wof:placetype":"venue"
},
  "geometry": {"coordinates":[-118.295998,34.1721],"type":"Point"}
}