{
  "type": "Feature",
  "properties": {
    "iso:country":"US",
    "sg:address":"811 E Main St",
    "sg:city":"El Cajon",
    "sg:classifiers":[
        {
            "category":"Restaurant",
            "type":"Food & Drink"
        }
    ],
    "sg:phone":"+1 619 401 1000",
    "sg:postcode":"92020",
    "sg:province":"CA",
    "wof:name":"El Cajon Sheash Kabab",
    "wof:placetype":"venue"
},
  "geometry": {"coordinates":[-116.952003,32.7948],"type":"Point"}
}