{
  "type": "Feature",
  "properties": {
    "iso:country":"US",
    "sg:address":"8408 Lander Ave",
    "sg:city":"Hilmar",
    "sg:classifiers":[
        {
            "category":"Real Estate",
            "subcategory":"Real Estate Agent",
            "type":"Services"
        }
    ],
    "sg:phone":"+1 209 634 8215",
    "sg:postcode":"95324",
    "sg:province":"CA",
    "wof:name":"Ranch Co",
    "wof:placetype":"venue"
},
  "geometry": {"coordinates":[-120.849974,37.409789],"type":"Point"}
}