{
  "type": "Feature",
  "properties": {
    "iso:country":"US",
    "sg:address":"1600 W Slauson Ave",
    "sg:city":"Los Angeles",
    "sg:classifiers":[
        {
            "category":"Wholesale",
            "subcategory":"Machinery & Supplies",
            "type":"Manufacturing & Wholesale Goods"
        }
    ],
    "sg:phone":"+1 323 565 3451",
    "sg:postcode":"90047",
    "sg:province":"CA",
    "sg:tags":[
        "equipment",
        "establishment"
    ],
    "wof:name":"M Three Beauty Supply",
    "wof:placetype":"venue"
},
  "geometry": {"coordinates":[-118.306311,33.989122],"type":"Point"}
}