{
  "type": "Feature",
  "properties": {
    "iso:country":"US",
    "sg:address":"1784 York View Cir",
    "sg:city":"Vista",
    "sg:classifiers":[
        {
            "category":"Professional",
            "subcategory":"Management & Consulting",
            "type":"Services"
        }
    ],
    "sg:phone":"+1 760 717 3268",
    "sg:postcode":"92084",
    "sg:province":"CA",
    "sg:tags":[
        "consultant",
        "business"
    ],
    "wof:name":"Doyle Fant Business Consultant",
    "wof:placetype":"venue"
},
  "geometry": {"coordinates":[-117.210211,33.182622],"type":"Point"}
}