{
  "type": "Feature",
  "properties": {
    "iso:country":"US",
    "sg:address":"15541 Product Ln",
    "sg:city":"Huntington Beach",
    "sg:classifiers":[
        {
            "category":"Manufacturing",
            "subcategory":"Tools & Machinery",
            "type":"Manufacturing & Wholesale Goods"
        }
    ],
    "sg:phone":"+1 714 899 4851",
    "sg:postcode":"92649",
    "sg:province":"CA",
    "sg:tags":[
        "industry",
        "special"
    ],
    "wof:name":"Automation Dynamics Inc",
    "wof:placetype":"venue"
},
  "geometry": {"coordinates":[-118.02768500000001,33.734756],"type":"Point"}
}