{
  "type": "Feature",
  "properties": {
    "addr:full":"386 E Shoreline Dr Long Beach CA 90802",
    "addr:housenumber":"386",
    "addr:postcode":"90802",
    "addr:street":"E Shoreline Dr",
    "iso:country":"US",
    "sg:address":"386 E Shoreline Dr",
    "sg:city":"Long Beach",
    "sg:classifiers":[
        {
            "category":"Organizations",
            "subcategory":"Community Association",
            "type":"Services"
        }
    ],
    "sg:phone":"+1 562 435 4093",
    "sg:postcode":"90802",
    "sg:province":"CA",
    "sg:tags":[
        "club"
    ],
    "wof:name":"Shoreline Yacht Club",
    "wof:placetype":"venue"
},
  "geometry": {"coordinates":[-118.187088,33.762527],"type":"Point"}
}