{
  "type": "Feature",
  "properties": {
    "addr:full":"10315 Washington Blvd Culver City CA 90232",
    "addr:housenumber":"10315",
    "addr:postcode":"90232",
    "addr:street":"Washington Blvd",
    "iso:country":"US",
    "sg:address":"10315 Washington Blvd",
    "sg:city":"Culver City",
    "sg:classifiers":[
        {
            "category":"Shopping",
            "type":"Retail Goods"
        }
    ],
    "sg:phone":"+1 310 204 4724",
    "sg:postcode":"90232",
    "sg:province":"CA",
    "sg:tags":[
        "candle"
    ],
    "wof:name":"Antonino Ajello & Bros House",
    "wof:placetype":"venue"
},
  "geometry": {"coordinates":[-118.401691,34.019257],"type":"Point"}
}