{
  "type": "Feature",
  "properties": {
    "addr:full":"1634 S Glendale Ave Glendale CA 91205",
    "addr:housenumber":"1634",
    "addr:postcode":"91205",
    "addr:street":"S Glendale Ave",
    "iso:country":"US",
    "sg:address":"1634 S Glendale Ave",
    "sg:city":"Glendale",
    "sg:classifiers":[
        {
            "category":"Restaurant",
            "type":"Food & Drink"
        }
    ],
    "sg:phone":"+1 818 240 7633",
    "sg:postcode":"91205",
    "sg:province":"CA",
    "sg:tags":[
        "fast"
    ],
    "wof:name":"McDonalds",
    "wof:placetype":"venue"
},
  "geometry": {"coordinates":[-118.25306500000001,34.125921],"type":"Point"}
}