{
  "type": "Feature",
  "properties": {
    "addr:full":"600 W Broadway Suite 1050 San Diego CA 92101",
    "addr:housenumber":"600",
    "addr:postcode":"92101",
    "addr:street":"W Broadway Suite 1050",
    "iso:country":"US",
    "sg:address":"600 W Broadway Suite 1050",
    "sg:city":"San Diego",
    "sg:classifiers":[
        {
            "category":"Professional",
            "subcategory":"Employment Agencies",
            "type":"Services"
        }
    ],
    "sg:phone":"+1 619 234 3078",
    "sg:postcode":"92101",
    "sg:province":"CA",
    "wof:name":"Officeteam",
    "wof:placetype":"venue"
},
  "geometry": {"coordinates":[-117.168235,32.715893],"type":"Point"}
}