{
  "type": "Feature",
  "properties": {
    "addr:full":"17692 Beach Blvd Ste 303 Huntington Beach CA 92647",
    "addr:housenumber":"17692",
    "addr:postcode":"92647",
    "addr:street":"Beach Blvd Ste 303",
    "iso:country":"US",
    "sg:address":"17692 Beach Blvd Ste 303",
    "sg:city":"Huntington Beach",
    "sg:classifiers":[
        {
            "category":"Health Services",
            "subcategory":"Dentist",
            "type":"Services"
        }
    ],
    "sg:phone":"+1 714 596 8989",
    "sg:postcode":"92647",
    "sg:province":"CA",
    "wof:name":"Chen Suelene Y DDS Inc",
    "wof:placetype":"venue"
},
  "geometry": {"coordinates":[-117.989065,33.705596],"type":"Point"}
}