{
  "type": "Feature",
  "properties": {
    "iso:country":"US",
    "sg:address":"1666 Froude St",
    "sg:city":"San Diego",
    "sg:classifiers":[
        {
            "category":"Manufacturing",
            "subcategory":"Printing",
            "type":"Manufacturing & Wholesale Goods"
        }
    ],
    "sg:phone":"+1 619 226 8840",
    "sg:postcode":"92107",
    "sg:province":"CA",
    "sg:tags":[
        "printer"
    ],
    "wof:name":"Leave It To Lee Publishing",
    "wof:placetype":"venue"
},
  "geometry": {"coordinates":[-117.24775200000001,32.738478],"type":"Point"}
}