{
  "type": "Feature",
  "properties": {
    "addr:full":"2130 W Century Blvd Los Angeles CA 90047",
    "addr:housenumber":"2130",
    "addr:postcode":"90047",
    "addr:street":"W Century Blvd",
    "iso:country":"US",
    "sg:address":"2130 W Century Blvd",
    "sg:city":"Los Angeles",
    "sg:classifiers":[
        {
            "category":"Food & Beverages",
            "subcategory":"Liquor & Beverages",
            "type":"Retail Goods"
        }
    ],
    "sg:phone":"+1 323 754 3544",
    "sg:postcode":"90047",
    "sg:province":"CA",
    "sg:tags":[
        "beer",
        "spirit",
        "wine"
    ],
    "wof:name":"Ralph's Drive-In Liquor",
    "wof:placetype":"venue"
},
  "geometry": {"coordinates":[-118.317001,33.945599],"type":"Point"}
}