{
  "type": "Feature",
  "properties": {
    "addr:full":"2501 Industry Way Lynwood CA 90262",
    "addr:housenumber":"2501",
    "addr:postcode":"90262",
    "addr:street":"Industry Way",
    "iso:country":"US",
    "sg:address":"2501 Industry Way",
    "sg:city":"Lynwood",
    "sg:classifiers":[
        {
            "category":"Food & Beverages",
            "subcategory":"Candy",
            "type":"Retail Goods"
        }
    ],
    "sg:phone":"+1 323 569 0222",
    "sg:postcode":"90262",
    "sg:province":"CA",
    "sg:tags":[
        "store"
    ],
    "wof:name":"American Gumball Machine",
    "wof:placetype":"venue"
},
  "geometry": {"coordinates":[-118.227486,33.925345],"type":"Point"}
}