{
  "type": "Feature",
  "properties": {
    "addr:full":"1878 W El Norte Pkwy Escondido CA 92026",
    "addr:housenumber":"1878",
    "addr:postcode":"92026",
    "addr:street":"W El Norte Pkwy",
    "iso:country":"US",
    "sg:address":"1878 W El Norte Pkwy",
    "sg:city":"Escondido",
    "sg:classifiers":[
        {
            "category":"Health Services",
            "subcategory":"Chiropractor",
            "type":"Services"
        }
    ],
    "sg:phone":"+1 760 741 7110",
    "sg:postcode":"92026",
    "sg:province":"CA",
    "sg:tags":[
        "chiropractic"
    ],
    "wof:name":"Lochridge, Steven Dc",
    "wof:placetype":"venue"
},
  "geometry": {"coordinates":[-117.11152199999999,33.147398],"type":"Point"}
}