{
  "type": "Feature",
  "properties": {
    "addr:full":"1413 E Sonora Ave Tulare CA 93274",
    "addr:housenumber":"1413",
    "addr:postcode":"93274",
    "addr:street":"E Sonora Ave",
    "iso:country":"US",
    "sg:address":"1413 E Sonora Ave",
    "sg:city":"Tulare",
    "sg:classifiers":[
        {
            "category":"Restaurant",
            "type":"Food & Drink"
        }
    ],
    "sg:phone":"+1 559 684 1918",
    "sg:postcode":"93274",
    "sg:province":"CA",
    "sg:tags":[
        "caterer"
    ],
    "wof:name":"Mary's Mexican Food",
    "wof:placetype":"venue"
},
  "geometry": {"coordinates":[-119.322574,36.20326],"type":"Point"}
}