{
  "type": "Feature",
  "properties": {
    "iso:country":"US",
    "sg:address":"3303 E 7th St",
    "sg:city":"Long Beach",
    "sg:classifiers":[
        {
            "category":"Retail",
            "subcategory":"Auto Rental",
            "type":"Services"
        }
    ],
    "sg:phone":"+1 562 439 8873",
    "sg:postcode":"90804",
    "sg:province":"CA",
    "sg:tags":[
        "renting",
        "truck",
        "leasing"
    ],
    "wof:name":"Penske Truck Rental",
    "wof:placetype":"venue"
},
  "geometry": {"coordinates":[-118.15243,33.775406],"type":"Point"}
}