{
  "type": "Feature",
  "properties": {
    "addr:full":"15001 S Broadway St Gardena CA 90248",
    "addr:housenumber":"15001",
    "addr:postcode":"90248",
    "addr:street":"S Broadway St",
    "iso:country":"US",
    "sg:address":"15001 S Broadway St",
    "sg:city":"Gardena",
    "sg:classifiers":[
        {
            "category":"Manufacturing",
            "subcategory":"Tools & Machinery",
            "type":"Manufacturing & Wholesale Goods"
        }
    ],
    "sg:phone":"+1 310 851 6060",
    "sg:postcode":"90248",
    "sg:province":"CA",
    "sg:tags":[
        "equipment",
        "refrigeration",
        "mfg"
    ],
    "wof:name":"Kool Star",
    "wof:placetype":"venue"
},
  "geometry": {"coordinates":[-118.27866400000001,33.896072],"type":"Point"}
}