{
  "type": "Feature",
  "properties": {
    "addr:full":"2948 Leigh Ave San Jose CA 95124",
    "addr:housenumber":"2948",
    "addr:postcode":"95124",
    "addr:street":"Leigh Ave",
    "iso:country":"US",
    "sg:address":"2948 Leigh Ave",
    "sg:city":"San Jose",
    "sg:classifiers":[
        {
            "category":"Wholesale",
            "subcategory":"Machinery & Supplies",
            "type":"Manufacturing & Wholesale Goods"
        }
    ],
    "sg:phone":"+1 408 269 6228",
    "sg:postcode":"95124",
    "sg:province":"CA",
    "sg:tags":[
        "janitor"
    ],
    "wof:name":"Platt Supply Co",
    "wof:placetype":"venue"
},
  "geometry": {"coordinates":[-121.92191800000001,37.267878],"type":"Point"}
}