{
  "type": "Feature",
  "properties": {
    "addr:full":"Park Street and San Leandro Blvd San Leandro CA 94577",
    "addr:postcode":"94577",
    "addr:street":"Park Street And San Leandro Blvd",
    "iso:country":"US",
    "sg:address":"Park Street and San Leandro Blvd",
    "sg:city":"San Leandro",
    "sg:classifiers":[
        {
            "category":"Park",
            "type":"Public Place"
        }
    ],
    "sg:postcode":"94577",
    "sg:province":"CA",
    "wof:name":"Siempre Verde Park",
    "wof:placetype":"venue"
},
  "geometry": {"coordinates":[-122.165054,37.728351],"type":"Point"}
}