{
  "type": "Feature",
  "properties": {
    "addr:full":"1015 S Central Ave Glendale CA 91204",
    "addr:housenumber":"1015",
    "addr:postcode":"91204",
    "addr:street":"S Central Ave",
    "iso:country":"US",
    "sg:address":"1015 S Central Ave",
    "sg:city":"Glendale",
    "sg:classifiers":[
        {
            "category":"Retail",
            "subcategory":"Portrait Studio",
            "type":"Services"
        }
    ],
    "sg:phone":"+1 818 546 2520",
    "sg:postcode":"91204",
    "sg:province":"CA",
    "sg:tags":[
        "photographer"
    ],
    "wof:name":"Photo By Kostas",
    "wof:placetype":"venue"
},
  "geometry": {"coordinates":[-118.257903,34.133594],"type":"Point"}
}