{
  "type": "Feature",
  "properties": {
    "addr:full":"1309 Evergreen Rd Wrightwood CA 92397",
    "addr:housenumber":"1309",
    "addr:postcode":"92397",
    "addr:street":"Evergreen Rd",
    "iso:country":"US",
    "sg:address":"1309 Evergreen Rd",
    "sg:city":"Wrightwood",
    "sg:classifiers":[
        {
            "category":"Shopping",
            "type":"Retail Goods"
        }
    ],
    "sg:phone":"+1 760 249 6490",
    "sg:postcode":"92397",
    "sg:province":"CA",
    "sg:tags":[
        "outdoor",
        "lighting",
        "specialty"
    ],
    "wof:name":"Applewood Court",
    "wof:placetype":"venue"
},
  "geometry": {"coordinates":[-117.63346300000001,34.360041],"type":"Point"}
}