{
  "type": "Feature",
  "properties": {
    "addr:full":"1481 E 28th St Signal Hill CA 90755",
    "addr:housenumber":"1481",
    "addr:postcode":"90755",
    "addr:street":"E 28Th St",
    "iso:country":"US",
    "sg:address":"1481 E 28th St",
    "sg:city":"Signal Hill",
    "sg:classifiers":[
        {
            "category":"Building & Trades",
            "subcategory":"Plumbing",
            "type":"Services"
        }
    ],
    "sg:phone":"+1 562 595 9570",
    "sg:postcode":"90755",
    "sg:province":"CA",
    "sg:tags":[
        "heating",
        "solar",
        "contractor"
    ],
    "wof:name":"Ameco",
    "wof:placetype":"venue"
},
  "geometry": {"coordinates":[-118.173924,33.80811],"type":"Point"}
}