{
  "type": "Feature",
  "properties": {
    "iso:country":"US",
    "sg:address":"3660 Wilshire Boulevard",
    "sg:city":"Los Angeles",
    "sg:classifiers":[
        {
            "category":"Banks & Credit Unions",
            "subcategory":"Financial Services",
            "type":"Services"
        }
    ],
    "sg:phone":"+1 213 365 2768",
    "sg:postcode":"90010",
    "sg:province":"CA",
    "sg:tags":[
        "broker",
        "mortgage"
    ],
    "wof:name":"Peoples' Financial",
    "wof:placetype":"venue"
},
  "geometry": {"coordinates":[-118.306595,34.0617],"type":"Point"}
}