{
  "type": "Feature",
  "properties": {
    "addr:full":"3549 W Florida Ave Hemet CA 92545",
    "addr:housenumber":"3549",
    "addr:postcode":"92545",
    "addr:street":"W Florida Ave",
    "iso:country":"US",
    "sg:address":"3549 W Florida Ave",
    "sg:city":"Hemet",
    "sg:classifiers":[
        {
            "category":"Shopping",
            "subcategory":"Shoes",
            "type":"Retail Goods"
        }
    ],
    "sg:phone":"+1 951 929 5408",
    "sg:postcode":"92545",
    "sg:province":"CA",
    "wof:name":"Payless Shoe Source",
    "wof:placetype":"venue"
},
  "geometry": {"coordinates":[-117.006606,33.747329],"type":"Point"}
}