{
  "type": "Feature",
  "properties": {
    "iso:country":"US",
    "sg:address":"3932 Talmage Ct",
    "sg:city":"Sacramento",
    "sg:classifiers":[
        {
            "category":"Freight",
            "type":"Transportation"
        }
    ],
    "sg:phone":"+1 916 362 1524",
    "sg:postcode":"95827",
    "sg:province":"CA",
    "sg:tags":[
        "operator",
        "local",
        "trucking"
    ],
    "wof:name":"S & S Trucking",
    "wof:placetype":"venue"
},
  "geometry": {"coordinates":[-121.34147,38.548071],"type":"Point"}
}