{
  "type": "Feature",
  "properties": {
    "addr:full":"7000 Convoy Ct San Diego CA 92117",
    "addr:housenumber":"7000",
    "addr:postcode":"92117",
    "addr:street":"Convoy Ct",
    "iso:country":"US",
    "sg:address":"7000 Convoy Ct",
    "sg:city":"San Diego",
    "sg:classifiers":[
        {
            "category":"Building & Trades",
            "subcategory":"Electrical",
            "type":"Services"
        }
    ],
    "sg:phone":"+1 858 268 5005",
    "sg:postcode":"92117",
    "sg:province":"CA",
    "sg:tags":[
        "electric",
        "contractor"
    ],
    "wof:name":"JMJ Electric",
    "wof:placetype":"venue"
},
  "geometry": {"coordinates":[-117.167558,32.834709],"type":"Point"}
}