{
  "type": "Feature",
  "properties": {
    "iso:country":"US",
    "sg:address":"408 Tyler Pl",
    "sg:city":"Salinas",
    "sg:classifiers":[
        {
            "category":"Professional",
            "type":"Services"
        }
    ],
    "sg:phone":"+1 831 443 5506",
    "sg:postcode":"93906",
    "sg:province":"CA",
    "wof:name":"Brett Johnston",
    "wof:placetype":"venue"
},
  "geometry": {"coordinates":[-121.658619,36.69641],"type":"Point"}
}