{
  "type": "Feature",
  "properties": {
    "addr:full":"10948 Weyburn Ave Los Angeles CA 90024",
    "addr:housenumber":"10948",
    "addr:postcode":"90024",
    "addr:street":"Weyburn Ave",
    "iso:country":"US",
    "sg:address":"10948 Weyburn Ave",
    "sg:city":"Los Angeles",
    "sg:classifiers":[
        {
            "category":"Food & Beverages",
            "subcategory":"Meat & Fish",
            "type":"Retail Goods"
        }
    ],
    "sg:phone":"+1 310 443 3647",
    "sg:postcode":"90024",
    "sg:province":"CA",
    "sg:tags":[
        "hot",
        "dog"
    ],
    "wof:name":"Fat Dogs",
    "wof:placetype":"venue"
},
  "geometry": {"coordinates":[-118.44702100000001,34.062507],"type":"Point"}
}