{
  "type": "Feature",
  "properties": {
    "addr:full":"13767 N Bloomfield Rd Nevada City CA 95959",
    "addr:housenumber":"13767",
    "addr:postcode":"95959",
    "addr:street":"N Bloomfield Rd",
    "iso:country":"US",
    "sg:address":"13767 N Bloomfield Rd",
    "sg:city":"Nevada City",
    "sg:classifiers":[
        {
            "category":"Travel",
            "subcategory":"Travel Agent",
            "type":"Entertainment"
        }
    ],
    "sg:phone":"+1 530 265 2380",
    "sg:postcode":"95959",
    "sg:province":"CA",
    "sg:tags":[
        "agency"
    ],
    "wof:name":"Mind Body Travel",
    "wof:placetype":"venue"
},
  "geometry": {"coordinates":[-120.98507499999999,39.297426],"type":"Point"}
}