{
  "type": "Feature",
  "properties": {
    "addr:full":"2533 Ganzan Way Rancho Cordova CA 95670",
    "addr:housenumber":"2533",
    "addr:postcode":"95670",
    "addr:street":"Ganzan Way",
    "iso:country":"US",
    "sg:address":"2533 Ganzan Way",
    "sg:city":"Rancho Cordova",
    "sg:classifiers":[
        {
            "category":"Building & Trades",
            "subcategory":"Construction",
            "type":"Services"
        }
    ],
    "sg:phone":"+1 916 363 5911",
    "sg:postcode":"95670",
    "sg:province":"CA",
    "sg:tags":[
        "maintenance",
        "contractor"
    ],
    "wof:name":"Minerva's Maintenance Svc",
    "wof:placetype":"venue"
},
  "geometry": {"coordinates":[-121.300326,38.595727],"type":"Point"}
}