{
  "type": "Feature",
  "properties": {
    "iso:country":"US",
    "sg:address":"811 N Western Avenue",
    "sg:city":"Los Angeles",
    "sg:classifiers":[
        {
            "category":"Retail",
            "subcategory":"Auto Rental",
            "type":"Services"
        }
    ],
    "sg:phone":"+1 323 468 1860",
    "sg:postcode":"90029",
    "sg:province":"CA",
    "sg:tags":[
        "car"
    ],
    "sg:website":"www.enterprise.com",
    "wof:name":"Enterprise Rent A Car",
    "wof:placetype":"venue"
},
  "geometry": {"coordinates":[-118.309261,34.085069],"type":"Point"}
}