{
  "type": "Feature",
  "properties": {
    "iso:country":"US",
    "sg:address":"324 Horton Plz",
    "sg:city":"San Diego",
    "sg:classifiers":[
        {
            "category":"Personal",
            "subcategory":"Beauty Salon",
            "type":"Services"
        }
    ],
    "sg:postcode":"92101",
    "sg:province":"CA",
    "sg:tags":[
        "spa"
    ],
    "sg:website":"milliondollarsmile.com",
    "wof:name":"Million Dollar Smile",
    "wof:placetype":"venue"
},
  "geometry": {"coordinates":[-117.162423,32.713668],"type":"Point"}
}