{
  "type": "Feature",
  "properties": {
    "addr:full":"16103 Montoya St Irwindale CA 91702",
    "addr:postcode":"16103;91702",
    "addr:street":"Montoya St",
    "iso:country":"US",
    "sg:address":"16103 Montoya St",
    "sg:city":"Irwindale",
    "sg:classifiers":[
        {
            "category":"Professional",
            "subcategory":"Advertising",
            "type":"Services"
        }
    ],
    "sg:phone":"+1 626 633 9099",
    "sg:postcode":"91702",
    "sg:province":"CA",
    "sg:tags":[
        "mail"
    ],
    "wof:name":"Boldt Mailing Svc",
    "wof:placetype":"venue"
},
  "geometry": {"coordinates":[-117.931358,34.128663],"type":"Point"}
}