{
  "type": "Feature",
  "properties": {
    "iso:country":"US",
    "sg:address":"5273 N Commerce Ave",
    "sg:city":"Moorpark",
    "sg:classifiers":[
        {
            "category":"Wholesale",
            "subcategory":"Machinery & Supplies",
            "type":"Manufacturing & Wholesale Goods"
        },
        {
            "category":"Manufacturing",
            "subcategory":"Tools & Machinery",
            "type":"Manufacturing & Wholesale Goods"
        }
    ],
    "sg:phone":"+1 805 523 0809",
    "sg:postcode":"93021",
    "sg:province":"CA",
    "sg:tags":[
        "equipment",
        "welding",
        "accessory"
    ],
    "sg:website":"www.danmig.com",
    "wof:name":"Equipment Plus Inc",
    "wof:placetype":"venue"
},
  "geometry": {"coordinates":[-118.898814,34.280693],"type":"Point"}
}