{
  "type": "Feature",
  "properties": {
    "iso:country":"US",
    "sg:address":"1641 Glendale Blvd",
    "sg:city":"Los Angeles",
    "sg:classifiers":[
        {
            "category":"Wholesale",
            "subcategory":"Auto Parts",
            "type":"Manufacturing & Wholesale Goods"
        }
    ],
    "sg:phone":"+1 213 484 9855",
    "sg:postcode":"90026",
    "sg:province":"CA",
    "wof:name":"J B Enterprice",
    "wof:placetype":"venue"
},
  "geometry": {"coordinates":[-118.260086,34.084879],"type":"Point"}
}