{
  "type": "Feature",
  "properties": {
    "iso:country":"US",
    "sg:address":"3 W Carrillo St",
    "sg:city":"Santa Barbara",
    "sg:classifiers":[
        {
            "category":"Health Services",
            "subcategory":"Clinic",
            "type":"Services"
        }
    ],
    "sg:phone":"+1 805 560 6995",
    "sg:postcode":"93101",
    "sg:province":"CA",
    "sg:tags":[
        "home"
    ],
    "wof:name":"Home Instead Senior Care",
    "wof:placetype":"venue"
},
  "geometry": {"coordinates":[-119.702944,34.420369],"type":"Point"}
}