{
  "type": "Feature",
  "properties": {
    "iso:country":"US",
    "sg:address":"13979 W Oak Glen Rd",
    "sg:city":"Valley Center",
    "sg:classifiers":[
        {
            "category":"Wholesale",
            "subcategory":"Plants",
            "type":"Manufacturing & Wholesale Goods"
        }
    ],
    "sg:phone":"+1 760 749 6535",
    "sg:postcode":"92082",
    "sg:province":"CA",
    "sg:tags":[
        "nursery",
        "tree"
    ],
    "wof:name":"Tropicals 2000 Inc",
    "wof:placetype":"venue"
},
  "geometry": {"coordinates":[-117.030614,33.281877],"type":"Point"}
}