{
  "type": "Feature",
  "properties": {
    "addr:full":"2708 Sunset Ave Bakersfield CA 93304",
    "addr:housenumber":"2708",
    "addr:postcode":"93304",
    "addr:street":"Sunset Ave",
    "iso:country":"US",
    "sg:address":"2708 Sunset Ave",
    "sg:city":"Bakersfield",
    "sg:classifiers":[
        {
            "category":"Real Estate",
            "subcategory":"Real Estate Operator",
            "type":"Services"
        }
    ],
    "sg:phone":"+1 661 633 9793",
    "sg:postcode":"93304",
    "sg:province":"CA",
    "sg:tags":[
        "property",
        "lessor"
    ],
    "wof:name":"Kathe Sickles",
    "wof:placetype":"venue"
},
  "geometry": {"coordinates":[-119.03301999999999,35.366769],"type":"Point"}
}