{
  "type": "Feature",
  "properties": {
    "iso:country":"US",
    "sg:address":"9124 Thilow Dr",
    "sg:city":"Sacramento",
    "sg:classifiers":[
        {
            "category":"Shopping",
            "subcategory":"Computers & Home Electronics",
            "type":"Retail Goods"
        }
    ],
    "sg:phone":"+1 916 670 8001",
    "sg:postcode":"95826",
    "sg:province":"CA",
    "sg:tags":[
        "equipment",
        "audio-visual"
    ],
    "wof:name":"Duvall Audio",
    "wof:placetype":"venue"
},
  "geometry": {"coordinates":[-121.36066099999999,38.555716],"type":"Point"}
}