{
  "type": "Feature",
  "properties": {
    "addr:full":"49 Hangar Way Watsonville CA 95076",
    "addr:housenumber":"49",
    "addr:postcode":"95076",
    "addr:street":"Hangar Way",
    "iso:country":"US",
    "sg:address":"49 Hangar Way",
    "sg:city":"Watsonville",
    "sg:classifiers":[
        {
            "category":"Building & Trades",
            "subcategory":"Cleaning & Sanitation",
            "type":"Services"
        }
    ],
    "sg:phone":"+1 831 761 2762",
    "sg:postcode":"95076",
    "sg:province":"CA",
    "sg:tags":[
        "janitor"
    ],
    "wof:name":"Collins Enterprises",
    "wof:placetype":"venue"
},
  "geometry": {"coordinates":[-121.79073200000001,36.92621],"type":"Point"}
}