{
  "type": "Feature",
  "properties": {
    "addr:full":"805 S Catalina St Los Angeles CA 90005",
    "addr:housenumber":"805",
    "addr:postcode":"90005",
    "addr:street":"S Catalina St",
    "iso:country":"US",
    "sg:address":"805 S Catalina St",
    "sg:city":"Los Angeles",
    "sg:classifiers":[
        {
            "category":"Education",
            "subcategory":"Special Training",
            "type":"Public Place"
        }
    ],
    "sg:phone":"+1 213 380 0479",
    "sg:postcode":"90005",
    "sg:province":"CA",
    "sg:tags":[
        "instruction",
        "music"
    ],
    "wof:name":"AMI",
    "wof:placetype":"venue"
},
  "geometry": {"coordinates":[-118.29546000000001,34.055995],"type":"Point"}
}