{
  "type": "Feature",
  "properties": {
    "iso:country":"US",
    "sg:address":"1403 Camden Ave",
    "sg:city":"Campbell",
    "sg:classifiers":[
        {
            "category":"Personal",
            "subcategory":"Nail Salon",
            "type":"Services"
        }
    ],
    "sg:phone":"+1 408 369 6536",
    "sg:postcode":"95008",
    "sg:province":"CA",
    "wof:name":"KT Nails",
    "wof:placetype":"venue"
},
  "geometry": {"coordinates":[-121.944081,37.268434],"type":"Point"}
}