{
  "type": "Feature",
  "properties": {
    "iso:country":"US",
    "sg:address":"198 Ezra Ave",
    "sg:city":"Santa Rosa",
    "sg:classifiers":[
        {
            "category":"Shopping",
            "subcategory":"Gifts & Souvenirs",
            "type":"Retail Goods"
        }
    ],
    "sg:phone":"+1 707 546 5867",
    "sg:postcode":"95401",
    "sg:province":"CA",
    "sg:tags":[
        "party",
        "supply"
    ],
    "wof:name":"Bump & Jump",
    "wof:placetype":"venue"
},
  "geometry": {"coordinates":[-122.76078,38.431013],"type":"Point"}
}