{
  "type": "Feature",
  "properties": {
    "addr:full":"22 4th Street 6th Floor San Francisco CA 94103",
    "addr:housenumber":"22;6th",
    "addr:postcode":"94103",
    "addr:street":"4Th Street;Floor",
    "iso:country":"US",
    "sg:address":"22 4th Street 6th Floor",
    "sg:city":"San Francisco",
    "sg:classifiers":[
        {
            "category":"Professional",
            "subcategory":"Computer Services",
            "type":"Services"
        }
    ],
    "sg:phone":"+1 866 345 1461",
    "sg:postcode":"94103",
    "sg:province":"CA",
    "sg:tags":[
        "social-commerce",
        "social-media",
        "customer-reviews",
        "community-solutions",
        "social-analytics"
    ],
    "sg:website":"http://www.powerreviews.com/",
    "wof:name":"PowerReviews",
    "wof:placetype":"venue"
},
  "geometry": {"coordinates":[-122.405463,37.785389],"type":"Point"}
}