{
  "type": "Feature",
  "properties": {
    "addr:full":"21090 Ave 245 Lindsay CA 93247",
    "addr:housenumber":"21090;245",
    "addr:postcode":"93247",
    "addr:street":"Ave",
    "iso:country":"US",
    "sg:address":"21090 Ave 245",
    "sg:city":"Lindsay",
    "sg:classifiers":[
        {
            "category":"Professional",
            "type":"Services"
        }
    ],
    "sg:phone":"+1 559 562 6024",
    "sg:postcode":"93247",
    "sg:province":"CA",
    "wof:name":"Kyran Rice",
    "wof:placetype":"venue"
},
  "geometry": {"coordinates":[-119.106364,36.233357],"type":"Point"}
}