{
  "type": "Feature",
  "properties": {
    "addr:full":"7840 Old Redwood Hwy Cotati CA 94931",
    "addr:housenumber":"7840",
    "addr:postcode":"94931",
    "addr:street":"Old Redwood Hwy",
    "iso:country":"US",
    "sg:address":"7840 Old Redwood Hwy",
    "sg:city":"Cotati",
    "sg:classifiers":[
        {
            "category":"Personal",
            "type":"Services"
        }
    ],
    "sg:phone":"+1 707 579 7065",
    "sg:postcode":"94931",
    "sg:province":"CA",
    "sg:tags":[
        "therapist",
        "massage"
    ],
    "wof:name":"Hands Of The Heart",
    "wof:placetype":"venue"
},
  "geometry": {"coordinates":[-122.70816499999999,38.328727],"type":"Point"}
}