{
  "type": "Feature",
  "properties": {
    "iso:country":"US",
    "sg:address":"418 S Broadway",
    "sg:city":"Los Angeles",
    "sg:classifiers":[
        {
            "category":"Shopping",
            "type":"Retail Goods"
        }
    ],
    "sg:phone":"+1 213 689 4008",
    "sg:postcode":"90013",
    "sg:province":"CA",
    "sg:tags":[
        "cosmetic",
        "perfume"
    ],
    "wof:name":"Perfumes A LA Carte",
    "wof:placetype":"venue"
},
  "geometry": {"coordinates":[-118.250437,34.048298],"type":"Point"}
}