{
  "type": "Feature",
  "properties": {
    "addr:full":"72 George St San Jose CA 95110",
    "addr:housenumber":"72",
    "addr:postcode":"95110",
    "addr:street":"George St",
    "iso:country":"US",
    "sg:address":"72 George St",
    "sg:city":"San Jose",
    "sg:classifiers":[
        {
            "category":"Professional",
            "subcategory":"Accounting & Tax Preparation",
            "type":"Services"
        }
    ],
    "sg:phone":"+1 408 292 8982",
    "sg:postcode":"95110",
    "sg:province":"CA",
    "sg:tags":[
        "return",
        "filing"
    ],
    "wof:name":"E & D Bookkeeping & Tax Svc",
    "wof:placetype":"venue"
},
  "geometry": {"coordinates":[-121.899308,37.347752],"type":"Point"}
}