{
  "type": "Feature",
  "properties": {
    "addr:full":"7640 Burnet Ave Van Nuys CA 91405",
    "addr:housenumber":"7640",
    "addr:postcode":"91405",
    "addr:street":"Burnet Ave",
    "iso:country":"US",
    "sg:address":"7640 Burnet Ave",
    "sg:city":"Van Nuys",
    "sg:classifiers":[
        {
            "category":"Wholesale",
            "subcategory":"Scrap",
            "type":"Manufacturing & Wholesale Goods"
        }
    ],
    "sg:phone":"+1 818 994 2846",
    "sg:postcode":"91405",
    "sg:province":"CA",
    "sg:tags":[
        "recycling",
        "center"
    ],
    "sg:website":"www.tentworks.com",
    "wof:name":"Hollywood Tentworks",
    "wof:placetype":"venue"
},
  "geometry": {"coordinates":[-118.46285,34.209522],"type":"Point"}
}