{
  "type": "Feature",
  "properties": {
    "iso:country":"US",
    "sg:address":"8560 Brentwood Blvd",
    "sg:city":"Brentwood",
    "sg:classifiers":[
        {
            "category":"Food & Beverages",
            "subcategory":"Groceries & Convenience Stores",
            "type":"Retail Goods"
        }
    ],
    "sg:phone":"+1 925 516 0230",
    "sg:postcode":"94513",
    "sg:province":"CA",
    "sg:tags":[
        "grocer"
    ],
    "wof:name":"La Charrita Market",
    "wof:placetype":"venue"
},
  "geometry": {"coordinates":[-121.693001,37.928101],"type":"Point"}
}