{
  "type": "Feature",
  "properties": {
    "iso:country":"US",
    "sg:address":"15750 Winchester Blvd",
    "sg:city":"Los Gatos",
    "sg:classifiers":[
        {
            "category":"Wholesale",
            "subcategory":"Electrical",
            "type":"Manufacturing & Wholesale Goods"
        }
    ],
    "sg:phone":"+1 408 395 2929",
    "sg:postcode":"95030",
    "sg:province":"CA",
    "sg:tags":[
        "electronic"
    ],
    "wof:name":"Eltron",
    "wof:placetype":"venue"
},
  "geometry": {"coordinates":[-121.97679,37.239693],"type":"Point"}
}