{
  "type": "Feature",
  "properties": {
    "addr:full":"8680 Miralani Dr San Diego CA 92126",
    "addr:housenumber":"8680",
    "addr:postcode":"92126",
    "addr:street":"Miralani Dr",
    "iso:country":"US",
    "sg:address":"8680 Miralani Dr",
    "sg:city":"San Diego",
    "sg:classifiers":[
        {
            "category":"Shopping",
            "type":"Retail Goods"
        }
    ],
    "sg:phone":"+1 858 566 4482",
    "sg:postcode":"92126",
    "sg:province":"CA",
    "sg:tags":[
        "merchandise"
    ],
    "wof:name":"Specialize Two Way Communicati",
    "wof:placetype":"venue"
},
  "geometry": {"coordinates":[-117.143322,32.895625],"type":"Point"}
}