{
  "type": "Feature",
  "properties": {
    "iso:country":"US",
    "sg:address":"14312 Bethany Cir",
    "sg:city":"Magalia",
    "sg:classifiers":[
        {
            "category":"Professional",
            "subcategory":"Accounting & Tax Preparation",
            "type":"Services"
        }
    ],
    "sg:phone":"+1 530 873 3655",
    "sg:postcode":"95954",
    "sg:province":"CA",
    "wof:name":"Friedmans Microwave Outlets",
    "wof:placetype":"venue"
},
  "geometry": {"coordinates":[-121.602765,39.830546],"type":"Point"}
}