{
  "type": "Feature",
  "properties": {
    "iso:country":"US",
    "sg:address":"626 Broadway St",
    "sg:city":"Fresno",
    "sg:classifiers":[
        {
            "category":"Retail",
            "subcategory":"Auto Repair",
            "type":"Services"
        }
    ],
    "sg:phone":"+1 559 268 5091",
    "sg:postcode":"93721",
    "sg:province":"CA",
    "sg:tags":[
        "exchanging",
        "engine"
    ],
    "wof:name":"Schedler's Engine Rebuilding",
    "wof:placetype":"venue"
},
  "geometry": {"coordinates":[-119.787538,36.729983],"type":"Point"}
}