{
  "type": "Feature",
  "properties": {
    "iso:country":"US",
    "sg:address":"754 N Pastoria Ave",
    "sg:city":"Sunnyvale",
    "sg:classifiers":[
        {
            "category":"Shopping",
            "subcategory":"Computers & Home Electronics",
            "type":"Retail Goods"
        }
    ],
    "sg:phone":"+1 408 736 0052",
    "sg:postcode":"94085",
    "sg:province":"CA",
    "sg:tags":[
        "parts",
        "supply"
    ],
    "wof:name":"Epic Technologies",
    "wof:placetype":"venue"
},
  "geometry": {"coordinates":[-122.033142,37.393859],"type":"Point"}
}