{
  "type": "Feature",
  "properties": {
    "addr:full":"548 N 13th Ave Upland CA 91786",
    "addr:housenumber":"548",
    "addr:postcode":"91786",
    "addr:street":"N 13Th Ave",
    "iso:country":"US",
    "sg:address":"548 N 13th Ave",
    "sg:city":"Upland",
    "sg:classifiers":[
        {
            "category":"Health Services",
            "subcategory":"Doctor",
            "type":"Services"
        }
    ],
    "sg:phone":"+1 909 373 8733",
    "sg:postcode":"91786",
    "sg:province":"CA",
    "sg:tags":[
        "physician",
        "surgeon"
    ],
    "wof:name":"Inland Rheumatology",
    "wof:placetype":"venue"
},
  "geometry": {"coordinates":[-117.633827,34.102048],"type":"Point"}
}