{
  "type": "Feature",
  "properties": {
    "addr:full":"236 W Mountain St Ste 107 Pasadena CA 91103",
    "addr:housenumber":"236",
    "addr:postcode":"91103",
    "addr:street":"W Mountain St Ste 107",
    "iso:country":"US",
    "sg:address":"236 W Mountain St Ste 107",
    "sg:city":"Pasadena",
    "sg:classifiers":[
        {
            "category":"Health Services",
            "subcategory":"Chiropractor",
            "type":"Services"
        }
    ],
    "sg:phone":"+1 626 449 0900",
    "sg:postcode":"91103",
    "sg:province":"CA",
    "sg:website":"focuschiropractic.net",
    "wof:name":"Focus Chiropractic",
    "wof:placetype":"venue"
},
  "geometry": {"coordinates":[-118.157766,34.161552],"type":"Point"}
}