{
  "type": "Feature",
  "properties": {
    "addr:full":"634 W Mission Rd San Marcos CA 92069",
    "addr:housenumber":"634",
    "addr:postcode":"92069",
    "addr:street":"W Mission Rd",
    "iso:country":"US",
    "sg:address":"634 W Mission Rd",
    "sg:city":"San Marcos",
    "sg:classifiers":[
        {
            "category":"Social Services",
            "subcategory":"Child Care",
            "type":"Services"
        }
    ],
    "sg:phone":"+1 760 744 2110",
    "sg:postcode":"92069",
    "sg:province":"CA",
    "sg:tags":[
        "kindergarten",
        "academic",
        "school"
    ],
    "wof:name":"Maac Project Head Start",
    "wof:placetype":"venue"
},
  "geometry": {"coordinates":[-117.17512600000001,33.145727],"type":"Point"}
}