{
  "type": "Feature",
  "properties": {
    "iso:country":"US",
    "sg:address":"1438 E Florence Ave",
    "sg:city":"Los Angeles",
    "sg:classifiers":[
        {
            "category":"Shopping",
            "type":"Retail Goods"
        }
    ],
    "sg:phone":"+1 323 583 7785",
    "sg:postcode":"90001",
    "sg:province":"CA",
    "sg:tags":[
        "cosmetic",
        "perfume"
    ],
    "wof:name":"Gloria Cosmetic",
    "wof:placetype":"venue"
},
  "geometry": {"coordinates":[-118.24819599999999,33.974744],"type":"Point"}
}