{
  "type": "Feature",
  "properties": {
    "iso:country":"US",
    "sg:address":"635 Vallejo St",
    "sg:city":"San Francisco",
    "sg:classifiers":[
        {
            "category":"Travel",
            "subcategory":"Travel Agent",
            "type":"Entertainment"
        }
    ],
    "sg:phone":"+1 415 397 6868",
    "sg:postcode":"94133",
    "sg:province":"CA",
    "wof:name":"Cost Less Travel Bargain Center",
    "wof:placetype":"venue"
},
  "geometry": {"coordinates":[-122.408005,37.798667],"type":"Point"}
}