{
  "type": "Feature",
  "properties": {
    "iso:country":"US",
    "sg:address":"101 Bank St",
    "sg:city":"Grass Valley",
    "sg:classifiers":[
        {
            "category":"Wholesale",
            "subcategory":"Non-durable Goods",
            "type":"Manufacturing & Wholesale Goods"
        }
    ],
    "sg:phone":"+1 530 272 9276",
    "sg:postcode":"95945",
    "sg:province":"CA",
    "wof:name":"Fibers",
    "wof:placetype":"venue"
},
  "geometry": {"coordinates":[-121.061919,39.218059],"type":"Point"}
}