{
  "type": "Feature",
  "properties": {
    "addr:full":"3267 N E St San Bernardino CA 92405",
    "addr:housenumber":"3267",
    "addr:postcode":"92405",
    "addr:street":"N E St",
    "iso:country":"US",
    "sg:address":"3267 N E St",
    "sg:city":"San Bernardino",
    "sg:classifiers":[
        {
            "category":"Personal",
            "subcategory":"Barber",
            "type":"Services"
        }
    ],
    "sg:phone":"+1 909 881 3846",
    "sg:postcode":"92405",
    "sg:province":"CA",
    "wof:name":"Patty's Barber Shop",
    "wof:placetype":"venue"
},
  "geometry": {"coordinates":[-117.294012,34.150102],"type":"Point"}
}