{
  "type": "Feature",
  "properties": {
    "addr:full":"850 Oneill Ave Belmont CA 94002",
    "addr:housenumber":"850",
    "addr:postcode":"94002",
    "addr:street":"Oneill Ave",
    "iso:country":"US",
    "sg:address":"850 Oneill Ave",
    "sg:city":"Belmont",
    "sg:classifiers":[
        {
            "category":"Social Services",
            "subcategory":"Job Training",
            "type":"Services"
        }
    ],
    "sg:phone":"+1 650 593 4696",
    "sg:postcode":"94002",
    "sg:province":"CA",
    "sg:tags":[
        "career",
        "counseling",
        "vocational"
    ],
    "wof:name":"Peter Davie & Assoc",
    "wof:placetype":"venue"
},
  "geometry": {"coordinates":[-122.273877,37.518684],"type":"Point"}
}