{
  "type": "Feature",
  "properties": {
    "addr:full":"1829 Granite Hills Dr El Cajon CA 92019",
    "addr:housenumber":"1829",
    "addr:postcode":"92019",
    "addr:street":"Granite Hills Dr",
    "iso:country":"US",
    "sg:address":"1829 Granite Hills Dr",
    "sg:city":"El Cajon",
    "sg:classifiers":[
        {
            "category":"Building & Trades",
            "subcategory":"Construction",
            "type":"Services"
        }
    ],
    "sg:phone":"+1 619 593 6457",
    "sg:postcode":"92019",
    "sg:province":"CA",
    "sg:tags":[
        "waterproofing",
        "contractor"
    ],
    "wof:name":"C & C Waterproofing Inc",
    "wof:placetype":"venue"
},
  "geometry": {"coordinates":[-116.921407,32.795008],"type":"Point"}
}