{
  "type": "Feature",
  "properties": {
    "iso:country":"US",
    "sg:address":"1236 Broadway",
    "sg:city":"Burlingame",
    "sg:classifiers":[
        {
            "category":"Restaurant",
            "type":"Food & Drink"
        }
    ],
    "sg:postcode":"94010",
    "sg:province":"CA",
    "sg:tags":[
        "mexican"
    ],
    "wof:name":"BBQ Time",
    "wof:placetype":"venue"
},
  "geometry": {"coordinates":[-122.36482599999999,37.585994],"type":"Point"}
}