{
  "type": "Feature",
  "properties": {
    "iso:country":"US",
    "sg:address":"25255 Cabot Rd Ste 103",
    "sg:city":"Laguna Hills",
    "sg:classifiers":[
        {
            "category":"Professional",
            "subcategory":"Lawyer & Legal Services",
            "type":"Services"
        }
    ],
    "sg:phone":"+1 949 297 8444",
    "sg:postcode":"92653",
    "sg:province":"CA",
    "wof:name":"Hall Law Firm",
    "wof:placetype":"venue"
},
  "geometry": {"coordinates":[-117.67557499999999,33.594443],"type":"Point"}
}