{
  "type": "Feature",
  "properties": {
    "addr:full":"135 el Camino Real Millbrae CA 94030",
    "addr:housenumber":"135",
    "addr:postcode":"94030",
    "addr:street":"El Camino Real",
    "iso:country":"US",
    "sg:address":"135 el Camino Real",
    "sg:city":"Millbrae",
    "sg:classifiers":[
        {
            "category":"Restaurant",
            "type":"Food & Drink"
        }
    ],
    "sg:phone":"+1 650 941 4204",
    "sg:postcode":"94030",
    "sg:province":"CA",
    "sg:tags":[
        "family"
    ],
    "wof:name":"Lyons Restaurant 360",
    "wof:placetype":"venue"
},
  "geometry": {"coordinates":[-122.389101,37.60009],"type":"Point"}
}