{
  "type": "Feature",
  "properties": {
    "addr:full":"9022 Balboa Blvd Northridge CA 91325",
    "addr:housenumber":"9022",
    "addr:postcode":"91325",
    "addr:street":"Balboa Blvd",
    "iso:country":"US",
    "sg:address":"9022 Balboa Blvd",
    "sg:city":"Northridge",
    "sg:classifiers":[
        {
            "category":"Food & Beverages",
            "subcategory":"Groceries & Convenience Stores",
            "type":"Retail Goods"
        }
    ],
    "sg:phone":"+1 818 894 6415",
    "sg:postcode":"91325",
    "sg:province":"CA",
    "wof:name":"Albertsons 659",
    "wof:placetype":"venue"
},
  "geometry": {"coordinates":[-118.50248000000001,34.2331],"type":"Point"}
}