{
  "type": "Feature",
  "properties": {
    "iso:country":"US",
    "sg:address":"1785 Alum Rock Ave",
    "sg:city":"San Jose",
    "sg:classifiers":[
        {
            "category":"Shopping",
            "subcategory":"Gifts & Souvenirs",
            "type":"Retail Goods"
        }
    ],
    "sg:phone":"+1 408 251 4401",
    "sg:postcode":"95116",
    "sg:province":"CA",
    "sg:tags":[
        "flower"
    ],
    "wof:name":"K & A Party Jumpers",
    "wof:placetype":"venue"
},
  "geometry": {"coordinates":[-121.854083,37.353642],"type":"Point"}
}