{
  "type": "Feature",
  "properties": {
    "addr:full":"8516 Etiwanda Ave Northridge CA 91325",
    "addr:housenumber":"8516",
    "addr:postcode":"91325",
    "addr:street":"Etiwanda Ave",
    "iso:country":"US",
    "sg:address":"8516 Etiwanda Ave",
    "sg:city":"Northridge",
    "sg:classifiers":[
        {
            "category":"Health Services",
            "subcategory":"Hospital",
            "type":"Services"
        }
    ],
    "sg:phone":"+1 818 992 3402",
    "sg:postcode":"91325",
    "sg:province":"CA",
    "sg:tags":[
        "equipment",
        "supply"
    ],
    "wof:name":"Complete Medical Equipment & Supplies",
    "wof:placetype":"venue"
},
  "geometry": {"coordinates":[-118.531734,34.225024],"type":"Point"}
}