{
  "type": "Feature",
  "properties": {
    "addr:full":"524 W Alondra Blvd Compton CA 90220",
    "addr:housenumber":"524",
    "addr:postcode":"90220",
    "addr:street":"W Alondra Blvd",
    "iso:country":"US",
    "sg:address":"524 W Alondra Blvd",
    "sg:city":"Compton",
    "sg:classifiers":[
        {
            "category":"Food & Beverages",
            "subcategory":"Groceries & Convenience Stores",
            "type":"Retail Goods"
        }
    ],
    "sg:phone":"+1 310 223 1747",
    "sg:postcode":"90220",
    "sg:province":"CA",
    "wof:name":"Riteway Market",
    "wof:placetype":"venue"
},
  "geometry": {"coordinates":[-118.233002,33.888699],"type":"Point"}
}