{
  "type": "Feature",
  "properties": {
    "iso:country":"US",
    "sg:address":"328 E Palmdale Blvd",
    "sg:city":"Palmdale",
    "sg:classifiers":[
        {
            "category":"Wholesale",
            "subcategory":"Machinery & Supplies",
            "type":"Manufacturing & Wholesale Goods"
        }
    ],
    "sg:phone":"+1 661 273 9382",
    "sg:postcode":"93550",
    "sg:province":"CA",
    "sg:tags":[
        "salon",
        "beauty"
    ],
    "wof:name":"Patty Beauty Salon & Barber",
    "wof:placetype":"venue"
},
  "geometry": {"coordinates":[-118.124347,34.579783],"type":"Point"}
}