{
  "type": "Feature",
  "properties": {
    "addr:full":"E Sacramento Nat Sacramento CA 95814",
    "addr:postcode":"95814",
    "addr:street":"E;Nat",
    "iso:country":"US",
    "sg:address":"E Sacramento Nat",
    "sg:city":"Sacramento",
    "sg:classifiers":[
        {
            "category":"Building & Trades",
            "subcategory":"Cleaning & Sanitation",
            "type":"Services"
        }
    ],
    "sg:phone":"+1 916 482 3333",
    "sg:postcode":"95814",
    "sg:province":"CA",
    "sg:tags":[
        "home"
    ],
    "wof:name":"Merry Maids",
    "wof:placetype":"venue"
},
  "geometry": {"coordinates":[-121.492394,38.57756],"type":"Point"}
}