{
  "type": "Feature",
  "properties": {
    "addr:full":"914 S Robertson Blvd Ste 106 Los Angeles CA 90035",
    "addr:housenumber":"914",
    "addr:postcode":"90035",
    "addr:street":"S Robertson Blvd Ste 106",
    "iso:country":"US",
    "sg:address":"914 S Robertson Blvd Ste 106",
    "sg:city":"Los Angeles",
    "sg:classifiers":[
        {
            "category":"Banks & Credit Unions",
            "subcategory":"Financial Services",
            "type":"Services"
        }
    ],
    "sg:phone":"+1 310 659 6577",
    "sg:postcode":"90035",
    "sg:province":"CA",
    "sg:tags":[
        "broker",
        "mortgage"
    ],
    "wof:name":"The Argent Corporation",
    "wof:placetype":"venue"
},
  "geometry": {"coordinates":[-118.383416,34.070596],"type":"Point"}
}