{
  "type": "Feature",
  "properties": {
    "iso:country":"US",
    "sg:address":"13567 Ave 180",
    "sg:city":"Tulare",
    "sg:classifiers":[
        {
            "category":"Farming",
            "subcategory":"Livestock Farm",
            "type":"Manufacturing & Wholesale Goods"
        }
    ],
    "sg:phone":"+1 559 686 7187",
    "sg:postcode":"93274",
    "sg:province":"CA",
    "sg:tags":[
        "equine"
    ],
    "wof:name":"Richard Nagel Ranch",
    "wof:placetype":"venue"
},
  "geometry": {"coordinates":[-119.285242,36.116244],"type":"Point"}
}