{
  "type": "Feature",
  "properties": {
    "addr:full":"2290 N Main St Ste A Salinas CA 93906",
    "addr:housenumber":"2290",
    "addr:postcode":"93906",
    "addr:street":"N Main St Ste A",
    "iso:country":"US",
    "sg:address":"2290 N Main St Ste A",
    "sg:city":"Salinas",
    "sg:classifiers":[
        {
            "category":"Real Estate",
            "subcategory":"Real Estate Operator",
            "type":"Services"
        }
    ],
    "sg:phone":"+1 831 443 1740",
    "sg:postcode":"93906",
    "sg:province":"CA",
    "sg:tags":[
        "apartment"
    ],
    "wof:name":"The Pointe At Harden Ranch",
    "wof:placetype":"venue"
},
  "geometry": {"coordinates":[-121.655998,36.729198],"type":"Point"}
}