{
  "type": "Feature",
  "properties": {
    "addr:full":"1295 Hamner Ave Norco CA 92860",
    "addr:housenumber":"1295",
    "addr:postcode":"92860",
    "addr:street":"Hamner Ave",
    "iso:country":"US",
    "sg:address":"1295 Hamner Ave",
    "sg:city":"Norco",
    "sg:classifiers":[
        {
            "category":"Restaurant",
            "type":"Food & Drink"
        }
    ],
    "sg:menulink":"http://www.allmenus.com/ca/norco/238681-wahoos-fish-taco/menu/",
    "sg:phone":"+1 951 270 0526",
    "sg:postcode":"92860",
    "sg:province":"CA",
    "sg:tags":[
        "seafood",
        "mexican",
        "american"
    ],
    "wof:name":"Wahoo's Fish Taco",
    "wof:placetype":"venue"
},
  "geometry": {"coordinates":[-117.56146,33.900351],"type":"Point"}
}