{
  "type": "Feature",
  "properties": {
    "iso:country":"US",
    "sg:address":"2450 Henderson Rd",
    "sg:city":"Redding",
    "sg:classifiers":[
        {
            "category":"Wholesale",
            "subcategory":"Auto Parts",
            "type":"Manufacturing & Wholesale Goods"
        }
    ],
    "sg:phone":"+1 530 223 4110",
    "sg:postcode":"96002",
    "sg:province":"CA",
    "wof:name":"Trim Line Auto Trim Design",
    "wof:placetype":"venue"
},
  "geometry": {"coordinates":[-122.37228,40.568909],"type":"Point"}
}