{
  "type": "Feature",
  "properties": {
    "addr:full":"2045 Sawtelle Blvd Los Angeles CA 90025",
    "addr:housenumber":"2045",
    "addr:postcode":"90025",
    "addr:street":"Sawtelle Blvd",
    "iso:country":"US",
    "sg:address":"2045 Sawtelle Blvd",
    "sg:city":"Los Angeles",
    "sg:classifiers":[
        {
            "category":"Government",
            "subcategory":"Office",
            "type":"Public Place"
        }
    ],
    "sg:phone":"+1 310 479 6000",
    "sg:postcode":"90025",
    "sg:province":"CA",
    "sg:tags":[
        "consulate"
    ],
    "wof:name":"Saudi Arbia Ryal Consulate Gen",
    "wof:placetype":"venue"
},
  "geometry": {"coordinates":[-118.44296300000001,34.040158],"type":"Point"}
}