{
  "type": "Feature",
  "properties": {
    "iso:country":"US",
    "sg:address":"276 N Allen Ave",
    "sg:city":"Pasadena",
    "sg:classifiers":[
        {
            "category":"Real Estate",
            "subcategory":"Real Estate Agent",
            "type":"Services"
        }
    ],
    "sg:phone":"+1 626 584 9569",
    "sg:postcode":"91106",
    "sg:province":"CA",
    "wof:name":"Masten Realty",
    "wof:placetype":"venue"
},
  "geometry": {"coordinates":[-118.113106,34.151705],"type":"Point"}
}