{
  "type": "Feature",
  "properties": {
    "iso:country":"US",
    "sg:address":"1628 Bush St",
    "sg:city":"San Francisco",
    "sg:classifiers":[
        {
            "category":"Retail",
            "subcategory":"Laundry & Dry Cleaning",
            "type":"Services"
        }
    ],
    "sg:phone":"+1 415 351 2878",
    "sg:postcode":"94109",
    "sg:province":"CA",
    "sg:tags":[
        "cleaner"
    ],
    "wof:name":"Lam's Cleaners",
    "wof:placetype":"venue"
},
  "geometry": {"coordinates":[-122.424133,37.788242],"type":"Point"}
}