{
  "type": "Feature",
  "properties": {
    "iso:country":"US",
    "sg:address":"30242 Crown Valley Pkwy",
    "sg:city":"Laguna Niguel",
    "sg:classifiers":[
        {
            "category":"Coffee & Tea",
            "type":"Food & Drink"
        }
    ],
    "sg:menulink":"http://www.allmenus.com/ca/south-coast/119571-starbucks-coffee/menu/",
    "sg:phone":"+1 949 249 9737",
    "sg:postcode":"92677",
    "sg:province":"CA",
    "sg:tags":[
        "american"
    ],
    "wof:name":"Starbucks Coffee",
    "wof:placetype":"venue"
},
  "geometry": {"coordinates":[-117.71472,33.523654],"type":"Point"}
}