{
  "type": "Feature",
  "properties": {
    "addr:full":"711 Lincoln Ave San Jose CA 95126",
    "addr:housenumber":"711",
    "addr:postcode":"95126",
    "addr:street":"Lincoln Ave",
    "iso:country":"US",
    "sg:address":"711 Lincoln Ave",
    "sg:city":"San Jose",
    "sg:classifiers":[
        {
            "category":"Shopping",
            "subcategory":"Bicycles & Sporting Goods",
            "type":"Retail Goods"
        }
    ],
    "sg:phone":"+1 408 271 8841",
    "sg:postcode":"95126",
    "sg:province":"CA",
    "sg:tags":[
        "equipment",
        "playground"
    ],
    "wof:name":"M F Filice & Son Surfaces",
    "wof:placetype":"venue"
},
  "geometry": {"coordinates":[-121.907037,37.316158],"type":"Point"}
}