{
  "type": "Feature",
  "properties": {
    "iso:country":"US",
    "sg:address":"1498 W Sunset Blvd",
    "sg:city":"Los Angeles",
    "sg:classifiers":[
        {
            "category":"Shopping",
            "subcategory":"Music",
            "type":"Retail Goods"
        }
    ],
    "sg:phone":"+1 213 481 2896",
    "sg:postcode":"90026",
    "sg:province":"CA",
    "sg:tags":[
        "video",
        "disc",
        "tape",
        "cassette"
    ],
    "wof:name":"Asian Star Video",
    "wof:placetype":"venue"
},
  "geometry": {"coordinates":[-118.25573,34.075965],"type":"Point"}
}