{
  "type": "Feature",
  "properties": {
    "iso:country":"US",
    "sg:address":"1264 S Waterman Ave",
    "sg:city":"San Bernardino",
    "sg:classifiers":[
        {
            "category":"Building & Trades",
            "subcategory":"Cleaning & Sanitation",
            "type":"Services"
        }
    ],
    "sg:phone":"+1 909 890 1004",
    "sg:postcode":"92408",
    "sg:province":"CA",
    "sg:tags":[
        "painting",
        "janitorial"
    ],
    "wof:name":"Hoons Maintenance Co",
    "wof:placetype":"venue"
},
  "geometry": {"coordinates":[-117.278803,34.07833],"type":"Point"}
}