{
  "type": "Feature",
  "properties": {
    "iso:country":"US",
    "sg:address":"2705 Aramon Dr",
    "sg:city":"Rancho Cordova",
    "sg:classifiers":[
        {
            "category":"Building & Trades",
            "subcategory":"Construction",
            "type":"Services"
        }
    ],
    "sg:phone":"+1 916 363 6673",
    "sg:postcode":"95670",
    "sg:province":"CA",
    "sg:tags":[
        "contractor"
    ],
    "wof:name":"Franklin Ward Contractor",
    "wof:placetype":"venue"
},
  "geometry": {"coordinates":[-121.29467200000001,38.594154],"type":"Point"}
}