{
  "type": "Feature",
  "properties": {
    "addr:full":"5594 E la Palma Ave Anaheim CA 92807",
    "addr:housenumber":"5594",
    "addr:postcode":"92807",
    "addr:street":"E La Palma Ave",
    "iso:country":"US",
    "sg:address":"5594 E la Palma Ave",
    "sg:city":"Anaheim",
    "sg:classifiers":[
        {
            "category":"Professional",
            "subcategory":"Management & Consulting",
            "type":"Services"
        },
        {
            "category":"Professional",
            "subcategory":"Business Services",
            "type":"Services"
        },
        {
            "category":"Building & Trades",
            "subcategory":"Electrical",
            "type":"Services"
        },
        {
            "category":"Professional",
            "subcategory":"Engineering",
            "type":"Services"
        },
        {
            "category":"Organizations",
            "subcategory":"Membership Organization",
            "type":"Services"
        }
    ],
    "sg:phone":"+1 714 696 7599",
    "sg:postcode":"92807",
    "sg:province":"CA",
    "sg:tags":[
        "control",
        "product",
        "consultant",
        "system",
        "controls",
        "regulator",
        "environmental",
        "ecological",
        "conservation",
        "engineer"
    ],
    "wof:name":"Butler-Justice Inc",
    "wof:placetype":"venue"
},
  "geometry": {"coordinates":[-117.79344,33.859776],"type":"Point"}
}