{
  "type": "Feature",
  "properties": {
    "addr:full":"1109 6th St Ramona CA 92065",
    "addr:housenumber":"1109",
    "addr:postcode":"92065",
    "addr:street":"6Th St",
    "iso:country":"US",
    "sg:address":"1109 6th St",
    "sg:city":"Ramona",
    "sg:classifiers":[
        {
            "category":"Shopping",
            "subcategory":"Crafts & Fabrics",
            "type":"Retail Goods"
        }
    ],
    "sg:phone":"+1 760 789 1412",
    "sg:postcode":"92065",
    "sg:province":"CA",
    "sg:tags":[
        "sewing",
        "commercial",
        "desi"
    ],
    "wof:name":"Lynette Bredow Country De",
    "wof:placetype":"venue"
},
  "geometry": {"coordinates":[-116.85716600000001,33.039097],"type":"Point"}
}