{
  "type": "Feature",
  "properties": {
    "addr:full":"8 Harris Ct Monterey CA 93940",
    "addr:housenumber":"8",
    "addr:postcode":"93940",
    "addr:street":"Harris Ct",
    "iso:country":"US",
    "sg:address":"8 Harris Ct",
    "sg:city":"Monterey",
    "sg:classifiers":[
        {
            "category":"Professional",
            "subcategory":"Accounting & Tax Preparation",
            "type":"Services"
        }
    ],
    "sg:phone":"+1 831 649 9200",
    "sg:postcode":"93940",
    "sg:province":"CA",
    "sg:tags":[
        "billing"
    ],
    "wof:name":"Medical Claims & Billing Spec",
    "wof:placetype":"venue"
},
  "geometry": {"coordinates":[-121.81869399999999,36.580114],"type":"Point"}
}