{
  "type": "Feature",
  "properties": {
    "iso:country":"US",
    "sg:address":"802 N Grand Ave",
    "sg:city":"Covina",
    "sg:classifiers":[
        {
            "category":"Shopping",
            "subcategory":"Baby Store",
            "type":"Retail Goods"
        },
        {
            "category":"Wholesale",
            "subcategory":"Apparel",
            "type":"Manufacturing & Wholesale Goods"
        }
    ],
    "sg:phone":"+1 626 859 7700",
    "sg:postcode":"91724",
    "sg:province":"CA",
    "sg:tags":[
        "wear-wholesale",
        "children's",
        "infant",
        "wear",
        "manufacturer"
    ],
    "sg:website":"http://www.broadwaybabe.com",
    "wof:name":"Broadway Babe",
    "wof:placetype":"venue"
},
  "geometry": {"coordinates":[-117.87247600000001,34.093741],"type":"Point"}
}