{
  "type": "Feature",
  "properties": {
    "iso:country":"US",
    "sg:address":"12475 Lime Pl",
    "sg:city":"Chino",
    "sg:classifiers":[
        {
            "category":"Freight",
            "type":"Transportation"
        }
    ],
    "sg:phone":"+1 909 627 2301",
    "sg:postcode":"91710",
    "sg:province":"CA",
    "sg:tags":[
        "operator",
        "trucking"
    ],
    "wof:name":"Tri-State Trucking",
    "wof:placetype":"venue"
},
  "geometry": {"coordinates":[-117.662293,34.02796],"type":"Point"}
}