{
  "type": "Feature",
  "properties": {
    "addr:full":"1700 Standiford Ave Modesto CA 95350",
    "addr:housenumber":"1700",
    "addr:postcode":"ca 95350",
    "addr:street":"Standiford Ave",
    "iso:country":"US",
    "sg:address":"1700 Standiford Ave",
    "sg:city":"Modesto",
    "sg:classifiers":[
        {
            "category":"Banks & Credit Unions",
            "subcategory":"Bank",
            "type":"Services"
        }
    ],
    "sg:phone":"+1 209 527 1418",
    "sg:postcode":"95350",
    "sg:province":"CA",
    "sg:tags":[
        "loan",
        "real estate"
    ],
    "wof:name":"Wells Fargo Home Mortgage Inc",
    "wof:placetype":"venue"
},
  "geometry": {"coordinates":[-121.025178,37.689477],"type":"Point"}
}