{
  "type": "Feature",
  "properties": {
    "iso:country":"US",
    "sg:address":"192 S G St",
    "sg:city":"Arcata",
    "sg:classifiers":[
        {
            "category":"Wholesale",
            "subcategory":"Scrap",
            "type":"Manufacturing & Wholesale Goods"
        }
    ],
    "sg:phone":"+1 707 822 4881",
    "sg:postcode":"95521",
    "sg:province":"CA",
    "sg:tags":[
        "material",
        "metal",
        "iron"
    ],
    "wof:name":"Arcata Scrap and Salvage",
    "wof:placetype":"venue"
},
  "geometry": {"coordinates":[-124.087742,40.863057],"type":"Point"}
}