{
  "type": "Feature",
  "properties": {
    "addr:full":"5101 Yosemite Blvd Modesto CA 95357",
    "addr:housenumber":"5101",
    "addr:postcode":"ca 95357",
    "addr:street":"Yosemite Blvd",
    "iso:country":"US",
    "sg:address":"5101 Yosemite Blvd",
    "sg:city":"Modesto",
    "sg:classifiers":[
        {
            "category":"Organizations",
            "subcategory":"Religious Organization",
            "type":"Services"
        }
    ],
    "sg:phone":"+1 209 522 4302",
    "sg:postcode":"95357",
    "sg:province":"CA",
    "wof:name":"Empire Church of the Brethren",
    "wof:placetype":"venue"
},
  "geometry": {"coordinates":[-120.90100099999999,37.638199],"type":"Point"}
}