{
  "type": "Feature",
  "properties": {
    "addr:full":"16194 Bryant Ave Dos Palos CA 93620",
    "addr:housenumber":"16194",
    "addr:postcode":"93620",
    "addr:street":"Bryant Ave",
    "iso:country":"US",
    "sg:address":"16194 Bryant Ave",
    "sg:city":"Dos Palos",
    "sg:classifiers":[
        {
            "category":"Shopping",
            "subcategory":"Florist",
            "type":"Retail Goods"
        }
    ],
    "sg:phone":"+1 209 392 3530",
    "sg:postcode":"93620",
    "sg:province":"CA",
    "wof:name":"Cactus Flat Nursery",
    "wof:placetype":"venue"
},
  "geometry": {"coordinates":[-120.608486,36.971122],"type":"Point"}
}