{
  "type": "Feature",
  "properties": {
    "iso:country":"US",
    "sg:address":"233 James Rd",
    "sg:city":"American Canyon",
    "sg:classifiers":[
        {
            "category":"Organizations",
            "subcategory":"Religious Organization",
            "type":"Services"
        }
    ],
    "sg:phone":"+1 707 643 0421",
    "sg:postcode":"94503",
    "sg:province":"CA",
    "sg:tags":[
        "church"
    ],
    "wof:name":"Jesus Risen Lord Alliance",
    "wof:placetype":"venue"
},
  "geometry": {"coordinates":[-122.25660499999999,38.172237],"type":"Point"}
}