{
  "type": "Feature",
  "properties": {
    "iso:country":"US",
    "sg:address":"464 Grenache Ave",
    "sg:city":"Madera",
    "sg:classifiers":[
        {
            "category":"Professional",
            "type":"Services"
        }
    ],
    "sg:phone":"+1 559 673 4041",
    "sg:postcode":"93637",
    "sg:province":"CA",
    "wof:name":"Scott Hefler",
    "wof:placetype":"venue"
},
  "geometry": {"coordinates":[-120.09627500000001,36.94838],"type":"Point"}
}