{
  "type": "Feature",
  "properties": {
    "addr:full":"2850 6th Ave San Diego CA 92103",
    "addr:housenumber":"2850",
    "addr:postcode":"92103",
    "addr:street":"6Th Ave",
    "iso:country":"US",
    "sg:address":"2850 6th Ave",
    "sg:city":"San Diego",
    "sg:classifiers":[
        {
            "category":"Restaurant",
            "type":"Food & Drink"
        }
    ],
    "sg:phone":"+1 619 543 9664",
    "sg:postcode":"92103",
    "sg:province":"CA",
    "sg:tags":[
        "delicatessen"
    ],
    "wof:name":"Casa Blanca Deli",
    "wof:placetype":"venue"
},
  "geometry": {"coordinates":[-117.15948899999999,32.735058],"type":"Point"}
}