{
  "type": "Feature",
  "properties": {
    "iso:country":"US",
    "sg:address":"4713 Half Dome Way",
    "sg:city":"Bakersfield",
    "sg:classifiers":[
        {
            "category":"Professional",
            "type":"Services"
        }
    ],
    "sg:phone":"+1 661 831 5157",
    "sg:postcode":"93304",
    "sg:province":"CA",
    "wof:name":"Apanex",
    "wof:placetype":"venue"
},
  "geometry": {"coordinates":[-119.026618,35.311981],"type":"Point"}
}