{
  "type": "Feature",
  "properties": {
    "iso:country":"US",
    "sg:address":"114 Bates Ct",
    "sg:city":"Orinda",
    "sg:classifiers":[
        {
            "category":"Professional",
            "type":"Services"
        }
    ],
    "sg:phone":"+1 925 258 9992",
    "sg:postcode":"94563",
    "sg:province":"CA",
    "wof:name":"Algae Busters",
    "wof:placetype":"venue"
},
  "geometry": {"coordinates":[-122.16573699999999,37.887088],"type":"Point"}
}