{
  "type": "Feature",
  "properties": {
    "iso:country":"US",
    "sg:address":"21600 Norwalk Blvd",
    "sg:city":"Hawaiian Gardens",
    "sg:classifiers":[
        {
            "category":"Shopping",
            "subcategory":"Pets & Pet Supplies",
            "type":"Retail Goods"
        }
    ],
    "sg:phone":"+1 562 924 7685",
    "sg:postcode":"90716",
    "sg:province":"CA",
    "sg:tags":[
        "store"
    ],
    "wof:name":"Carson Tropical Fish",
    "wof:placetype":"venue"
},
  "geometry": {"coordinates":[-118.07186,33.833188],"type":"Point"}
}