{
  "type": "Feature",
  "properties": {
    "addr:full":"4829 Devereaux Way Salida CA 95368",
    "addr:housenumber":"4829",
    "addr:postcode":"95368",
    "addr:street":"Devereaux Way",
    "iso:country":"US",
    "sg:address":"4829 Devereaux Way",
    "sg:city":"Salida",
    "sg:classifiers":[
        {
            "category":"Freight",
            "type":"Transportation"
        }
    ],
    "sg:phone":"+1 209 543 8697",
    "sg:postcode":"95368",
    "sg:province":"CA",
    "sg:tags":[
        "operator",
        "local",
        "hauling",
        "trucking"
    ],
    "wof:name":"J's Hauling",
    "wof:placetype":"venue"
},
  "geometry": {"coordinates":[-121.08546800000001,37.716053],"type":"Point"}
}