{
  "type": "Feature",
  "properties": {
    "iso:country":"US",
    "sg:address":"1015 1/4 W 190th St",
    "sg:city":"Gardena",
    "sg:classifiers":[
        {
            "category":"Building & Trades",
            "subcategory":"Pest Control",
            "type":"Services"
        }
    ],
    "sg:phone":"+1 310 527 4640",
    "sg:postcode":"90248",
    "sg:province":"CA",
    "sg:website":"www.rhinopestcontrol.com",
    "wof:name":"Rhino Pest Control",
    "wof:placetype":"venue"
},
  "geometry": {"coordinates":[-118.292862,33.858911],"type":"Point"}
}