{
  "type": "Feature",
  "properties": {
    "addr:full":"25361 Alicia Pkwy Ste D Laguna Hills CA 92653",
    "addr:housenumber":"25361",
    "addr:postcode":"92653",
    "addr:street":"Alicia Pkwy Ste D",
    "iso:country":"US",
    "sg:address":"25361 Alicia Pkwy Ste D",
    "sg:city":"Laguna Hills",
    "sg:classifiers":[
        {
            "category":"Shopping",
            "subcategory":"Pets & Pet Supplies",
            "type":"Retail Goods"
        },
        {
            "category":"Retail",
            "subcategory":"Veterinary Services",
            "type":"Services"
        },
        {
            "category":"Retail",
            "subcategory":"Pet Boarding",
            "type":"Services"
        }
    ],
    "sg:phone":"+1 949 581 7387",
    "sg:postcode":"92653",
    "sg:province":"CA",
    "sg:tags":[
        "veterinarian",
        "boarding/pet",
        "groomers",
        "sitting"
    ],
    "sg:website":"www.lagunapetcarecenter.com",
    "wof:name":"Laguna Pet Care Center",
    "wof:placetype":"venue"
},
  "geometry": {"coordinates":[-117.697985,33.593576],"type":"Point"}
}