{
  "type": "Feature",
  "properties": {
    "addr:full":"224 Lake Dr Berkeley CA 94708",
    "addr:housenumber":"224",
    "addr:postcode":"94708",
    "addr:street":"Lake Dr",
    "iso:country":"US",
    "sg:address":"224 Lake Dr",
    "sg:city":"Berkeley",
    "sg:classifiers":[
        {
            "category":"Communications",
            "subcategory":"Radio Station",
            "type":"Services"
        }
    ],
    "sg:phone":"+1 510 526 8449",
    "sg:postcode":"94708",
    "sg:province":"CA",
    "sg:tags":[
        "broadcast"
    ],
    "wof:name":"A I C I P P",
    "wof:placetype":"venue"
},
  "geometry": {"coordinates":[-122.272441,37.90962],"type":"Point"}
}