{
  "type": "Feature",
  "properties": {
    "addr:full":"1119 S Los Angeles St Los Angeles CA 90015",
    "addr:housenumber":"1119",
    "addr:postcode":"90015",
    "addr:street":"S;Angeles St",
    "iso:country":"US",
    "sg:address":"1119 S Los Angeles St",
    "sg:city":"Los Angeles",
    "sg:classifiers":[
        {
            "category":"Wholesale",
            "subcategory":"Apparel",
            "type":"Manufacturing & Wholesale Goods"
        }
    ],
    "sg:phone":"+1 213 747 6554",
    "sg:postcode":"90015",
    "sg:province":"CA",
    "sg:tags":[
        "footwear",
        "shoes"
    ],
    "wof:name":"Jenico Shoes",
    "wof:placetype":"venue"
},
  "geometry": {"coordinates":[-118.258206,34.037246],"type":"Point"}
}