{
  "type": "Feature",
  "properties": {
    "addr:full":"1420 S Bascom Ave San Jose CA 95128",
    "addr:housenumber":"1420",
    "addr:postcode":"95128",
    "addr:street":"S Bascom Ave",
    "iso:country":"US",
    "sg:address":"1420 S Bascom Ave",
    "sg:city":"San Jose",
    "sg:classifiers":[
        {
            "category":"Retail",
            "subcategory":"Auto Repair",
            "type":"Services"
        }
    ],
    "sg:phone":"+1 408 288 6141",
    "sg:postcode":"95128",
    "sg:province":"CA",
    "sg:tags":[
        "repairing",
        "automobile",
        "smog",
        "check"
    ],
    "wof:name":"Smog Plus",
    "wof:placetype":"venue"
},
  "geometry": {"coordinates":[-121.931999,37.298199],"type":"Point"}
}