{
  "type": "Feature",
  "properties": {
    "addr:full":"502 S Ross St Santa Ana CA 92701",
    "addr:housenumber":"502",
    "addr:postcode":"92701",
    "addr:street":"S Ross St",
    "iso:country":"US",
    "sg:address":"502 S Ross St",
    "sg:city":"Santa Ana",
    "sg:classifiers":[
        {
            "category":"Social Services",
            "type":"Services"
        }
    ],
    "sg:phone":"+1 714 835 4199",
    "sg:postcode":"92701",
    "sg:province":"CA",
    "sg:tags":[
        "organization",
        "welfare"
    ],
    "sg:website":"www.maof.org",
    "wof:name":"Mexican American Opportunity",
    "wof:placetype":"venue"
},
  "geometry": {"coordinates":[-117.872365,33.739458],"type":"Point"}
}