{
  "type": "Feature",
  "properties": {
    "iso:country":"US",
    "sg:address":"1393 Callens Rd",
    "sg:city":"Ventura",
    "sg:classifiers":[
        {
            "category":"Professional",
            "subcategory":"Business Services",
            "type":"Services"
        }
    ],
    "sg:phone":"+1 805 644 8341",
    "sg:postcode":"93003",
    "sg:province":"CA",
    "sg:tags":[
        "recording",
        "studio"
    ],
    "wof:name":"Goldmine Recording Studio",
    "wof:placetype":"venue"
},
  "geometry": {"coordinates":[-119.241136,34.25942],"type":"Point"}
}