{
  "type": "Feature",
  "properties": {
    "addr:full":"72 Sobrante Aliso Viejo CA 92656",
    "addr:housenumber":"72",
    "addr:postcode":"92656",
    "addr:street":"Sobrante",
    "iso:country":"US",
    "sg:address":"72 Sobrante",
    "sg:city":"Aliso Viejo",
    "sg:classifiers":[
        {
            "category":"Communications",
            "type":"Services"
        }
    ],
    "sg:phone":"+1 949 716 0010",
    "sg:postcode":"92656",
    "sg:province":"CA",
    "sg:tags":[
        "communication"
    ],
    "wof:name":"Webamerica Communications",
    "wof:placetype":"venue"
},
  "geometry": {"coordinates":[-117.735304,33.574832],"type":"Point"}
}