{
  "type": "Feature",
  "properties": {
    "iso:country":"US",
    "sg:address":"317 E Mission Rd",
    "sg:city":"Fallbrook",
    "sg:classifiers":[
        {
            "category":"Personal",
            "subcategory":"Tattoo Parlor",
            "type":"Services"
        }
    ],
    "sg:phone":"+1 760 728 1021",
    "sg:postcode":"92028",
    "sg:province":"CA",
    "wof:name":"Insignia Tattoo",
    "wof:placetype":"venue"
},
  "geometry": {"coordinates":[-117.248803,33.384598],"type":"Point"}
}