{
  "type": "Feature",
  "properties": {
    "iso:country":"US",
    "sg:address":"11300 Sunrise Gold Cir",
    "sg:city":"Rancho Cordova",
    "sg:classifiers":[
        {
            "category":"Building & Trades",
            "subcategory":"Construction",
            "type":"Services"
        }
    ],
    "sg:phone":"+1 916 638 0451",
    "sg:postcode":"95742",
    "sg:province":"CA",
    "sg:tags":[
        "maker",
        "cabinet"
    ],
    "wof:name":"Dave's Quality Custom Cabinets",
    "wof:placetype":"venue"
},
  "geometry": {"coordinates":[-121.263261,38.599778],"type":"Point"}
}