{
  "type": "Feature",
  "properties": {
    "iso:country":"US",
    "sg:address":"16337 Bellflower Blvd",
    "sg:city":"Bellflower",
    "sg:classifiers":[
        {
            "category":"Social Services",
            "subcategory":"Child Care",
            "type":"Services"
        }
    ],
    "sg:phone":"+1 562 925 7070",
    "sg:postcode":"90706",
    "sg:province":"CA",
    "sg:tags":[
        "elementary",
        "kindergarten",
        "school",
        "academic"
    ],
    "sg:website":"www.bethanymanor.org",
    "wof:name":"Bethany Manor",
    "wof:placetype":"venue"
},
  "geometry": {"coordinates":[-118.125,33.886002],"type":"Point"}
}