{
  "type": "Feature",
  "properties": {
    "addr:full":"1040 Grant Rd Mountain View CA 94040",
    "addr:housenumber":"1040",
    "addr:postcode":"94040",
    "addr:street":"Grant Rd",
    "iso:country":"US",
    "sg:address":"1040 Grant Rd",
    "sg:city":"Mountain View",
    "sg:classifiers":[
        {
            "category":"Wholesale",
            "subcategory":"Medical Equipment & Supplies",
            "type":"Manufacturing & Wholesale Goods"
        }
    ],
    "sg:phone":"+1 650 964 2342",
    "sg:postcode":"94040",
    "sg:province":"CA",
    "sg:tags":[
        "physician",
        "surgeon"
    ],
    "wof:name":"Pro-Act Inc",
    "wof:placetype":"venue"
},
  "geometry": {"coordinates":[-122.075135,37.377714],"type":"Point"}
}