{
  "type": "Feature",
  "properties": {
    "iso:country":"US",
    "sg:address":"500 Sansome St",
    "sg:city":"San Francisco",
    "sg:classifiers":[
        {
            "category":"Shopping",
            "subcategory":"Computers & Home Electronics",
            "type":"Retail Goods"
        }
    ],
    "sg:phone":"+1 415 296 1300",
    "sg:postcode":"94111",
    "sg:province":"CA",
    "sg:tags":[
        "software"
    ],
    "sg:website":"www.castsoftware.com",
    "wof:name":"Cast Software Inc",
    "wof:placetype":"venue"
},
  "geometry": {"coordinates":[-122.401581,37.795306],"type":"Point"}
}