{
  "type": "Feature",
  "properties": {
    "iso:country":"US",
    "sg:address":"3434 W 6th St",
    "sg:city":"Los Angeles",
    "sg:classifiers":[
        {
            "category":"Freight",
            "type":"Transportation"
        }
    ],
    "sg:phone":"+1 213 385 0181",
    "sg:postcode":"90020",
    "sg:province":"CA",
    "wof:name":"24 Quick",
    "wof:placetype":"venue"
},
  "geometry": {"coordinates":[-118.29589,34.063518],"type":"Point"}
}