{
  "type": "Feature",
  "properties": {
    "addr:full":"604 W El Camino Ave Sacramento CA 95833",
    "addr:housenumber":"604",
    "addr:postcode":"95833",
    "addr:street":"W El Camino Ave",
    "iso:country":"US",
    "sg:address":"604 W El Camino Ave",
    "sg:city":"Sacramento",
    "sg:classifiers":[
        {
            "category":"Restaurant",
            "type":"Food & Drink"
        }
    ],
    "sg:menulink":"http://www.allmenus.com/ca/sacramento/79034-pizza-hut/menu/",
    "sg:phone":"+1 916 921 1800",
    "sg:postcode":"95833",
    "sg:province":"CA",
    "sg:tags":[
        "american",
        "pizza"
    ],
    "wof:name":"Pizza Hut",
    "wof:placetype":"venue"
},
  "geometry": {"coordinates":[-121.476398,38.610965],"type":"Point"}
}