{
  "type": "Feature",
  "properties": {
    "addr:full":"290 Palm Ave Auburn CA 95603",
    "addr:housenumber":"290",
    "addr:postcode":"ca 95603",
    "addr:street":"Palm Ave",
    "iso:country":"US",
    "sg:address":"290 Palm Ave",
    "sg:city":"Auburn",
    "sg:classifiers":[
        {
            "category":"Home & Garden",
            "subcategory":"Home Furnishings",
            "type":"Retail Goods"
        },
        {
            "category":"Building & Trades",
            "subcategory":"Construction",
            "type":"Services"
        },
        {
            "category":"Home & Garden",
            "subcategory":"Carpets & Floor Coverings",
            "type":"Retail Goods"
        }
    ],
    "sg:phone":"+1 530 888 8889",
    "sg:postcode":"95603",
    "sg:province":"CA",
    "sg:tags":[
        "draperies",
        "flooring",
        "hardwood",
        "rug",
        "contractor",
        "window",
        "treatment",
        "tile-contractors",
        "curtain"
    ],
    "sg:website":"http://www.auburn.abbeycarpet.com",
    "wof:name":"Abbey Carpet Of Auburn",
    "wof:placetype":"venue"
},
  "geometry": {"coordinates":[-121.074528,38.908258],"type":"Point"}
}