{
  "type": "Feature",
  "properties": {
    "iso:country":"US",
    "sg:address":"4657 Dennick Ct",
    "sg:city":"Sacramento",
    "sg:classifiers":[
        {
            "category":"Building & Trades",
            "subcategory":"Electrical",
            "type":"Services"
        }
    ],
    "sg:phone":"+1 916 997 6259",
    "sg:postcode":"95842",
    "sg:province":"CA",
    "sg:tags":[
        "installation"
    ],
    "wof:name":"J D Powell Co",
    "wof:placetype":"venue"
},
  "geometry": {"coordinates":[-121.355588,38.702307],"type":"Point"}
}