{
  "type": "Feature",
  "properties": {
    "addr:full":"39252 Winchester Rd Murrieta CA 92563",
    "addr:housenumber":"39252",
    "addr:postcode":"92563",
    "addr:street":"Winchester Rd",
    "iso:country":"US",
    "sg:address":"39252 Winchester Rd",
    "sg:city":"Murrieta",
    "sg:classifiers":[
        {
            "category":"Restaurant",
            "type":"Food & Drink"
        }
    ],
    "sg:menulink":"http://www.allmenus.com/ca/murrieta/150377-subway/menu/",
    "sg:phone":"+1 951 461 8597",
    "sg:postcode":"92563",
    "sg:province":"CA",
    "sg:tags":[
        "american",
        "sandwich"
    ],
    "wof:name":"Subway",
    "wof:placetype":"venue"
},
  "geometry": {"coordinates":[-117.141544,33.548576],"type":"Point"}
}