{
  "type": "Feature",
  "properties": {
    "iso:country":"US",
    "sg:address":"6032 Clark Rd",
    "sg:city":"Paradise",
    "sg:classifiers":[
        {
            "category":"Home & Garden",
            "subcategory":"Building Materials",
            "type":"Retail Goods"
        }
    ],
    "sg:phone":"+1 530 872 7095",
    "sg:postcode":"95969",
    "sg:province":"CA",
    "sg:tags":[
        "paint"
    ],
    "sg:website":"www.corlinpaint.com",
    "wof:name":"Corlin Paint",
    "wof:placetype":"venue"
},
  "geometry": {"coordinates":[-121.606173,39.760295],"type":"Point"}
}