{
  "type": "Feature",
  "properties": {
    "addr:full":"7036 Santa Teresa Blvd San Jose CA 95139",
    "addr:housenumber":"7036",
    "addr:postcode":"95139",
    "addr:street":"Santa Teresa Blvd",
    "iso:country":"US",
    "sg:address":"7036 Santa Teresa Blvd",
    "sg:city":"San Jose",
    "sg:classifiers":[
        {
            "category":"Personal",
            "subcategory":"Beauty Salon",
            "type":"Services"
        }
    ],
    "sg:phone":"+1 408 224 3775",
    "sg:postcode":"95139",
    "sg:province":"CA",
    "sg:tags":[
        "nail",
        "manicuring"
    ],
    "wof:name":"Expo Nails II",
    "wof:placetype":"venue"
},
  "geometry": {"coordinates":[-121.776044,37.226494],"type":"Point"}
}