{
  "type": "Feature",
  "properties": {
    "addr:full":"2324 Truxtun Ave Bakersfield CA 93301",
    "addr:housenumber":"2324",
    "addr:postcode":"93301",
    "addr:street":"Truxtun Ave",
    "iso:country":"US",
    "sg:address":"2324 Truxtun Ave",
    "sg:city":"Bakersfield",
    "sg:classifiers":[
        {
            "category":"Personal",
            "subcategory":"Beauty Salon",
            "type":"Services"
        }
    ],
    "sg:phone":"+1 661 321 9462",
    "sg:postcode":"93301",
    "sg:province":"CA",
    "wof:name":"Sandee O",
    "wof:placetype":"venue"
},
  "geometry": {"coordinates":[-119.02909099999999,35.37345],"type":"Point"}
}