{
  "type": "Feature",
  "properties": {
    "addr:full":"701 Kings Row Unit B 23 San Jose CA 95112",
    "addr:housenumber":"701;unit b 23",
    "addr:postcode":"95112",
    "addr:street":"Kings;San Jose",
    "iso:country":"US",
    "sg:address":"701 Kings Row Unit B 23",
    "sg:city":"San Jose",
    "sg:classifiers":[
        {
            "category":"Autos & Motor Vehicles",
            "subcategory":"Automobile Sales",
            "type":"Retail Goods"
        }
    ],
    "sg:phone":"+1 408 971 9888",
    "sg:postcode":"95112",
    "sg:province":"CA",
    "sg:tags":[
        "automotive"
    ],
    "sg:website":"www.rshydraulics.com",
    "wof:name":"R&S Hydraulics",
    "wof:placetype":"venue"
},
  "geometry": {"coordinates":[-121.898844,37.373132],"type":"Point"}
}