{
  "type": "Feature",
  "properties": {
    "addr:full":"2211 Corinth Ave Los Angeles CA 90064",
    "addr:housenumber":"2211",
    "addr:postcode":"90064",
    "addr:street":"Corinth Ave",
    "iso:country":"US",
    "sg:address":"2211 Corinth Ave",
    "sg:city":"Los Angeles",
    "sg:classifiers":[
        {
            "category":"Social Services",
            "type":"Services"
        }
    ],
    "sg:phone":"+1 310 444 1951",
    "sg:postcode":"90064",
    "sg:province":"CA",
    "sg:tags":[
        "worker"
    ],
    "wof:name":"Marc Sadoff",
    "wof:placetype":"venue"
},
  "geometry": {"coordinates":[-118.44110000000001,34.036241],"type":"Point"}
}