{
  "type": "Feature",
  "properties": {
    "iso:country":"US",
    "sg:address":"1528 W 22nd St",
    "sg:city":"Merced",
    "sg:classifiers":[
        {
            "category":"Professional",
            "subcategory":"Management & Consulting",
            "type":"Services"
        }
    ],
    "sg:phone":"+1 209 381 0606",
    "sg:postcode":"95340",
    "sg:province":"CA",
    "sg:tags":[
        "consultant",
        "business"
    ],
    "wof:name":"SLM Group Inc",
    "wof:placetype":"venue"
},
  "geometry": {"coordinates":[-120.496601,37.312229],"type":"Point"}
}