{
  "type": "Feature",
  "properties": {
    "iso:country":"US",
    "sg:address":"7901 Stevenson Ave",
    "sg:city":"Sacramento",
    "sg:classifiers":[
        {
            "category":"Place Of Worship",
            "subcategory":"Church",
            "type":"Public Place"
        },
        {
            "category":"Place Of Worship",
            "type":"Public Place"
        }
    ],
    "sg:phone":"+1 916 689 3975",
    "sg:postcode":"95828",
    "sg:province":"CA",
    "sg:tags":[
        "churches-evangelical",
        "churches-baptist-general",
        "covenant",
        "churches-baptist",
        "churches-covenant"
    ],
    "wof:name":"Filipino-American Evang Ch",
    "wof:placetype":"venue"
},
  "geometry": {"coordinates":[-121.413721,38.465256],"type":"Point"}
}