{
  "type": "Feature",
  "properties": {
    "iso:country":"US",
    "sg:address":"3565 Lathrop Ave",
    "sg:city":"Simi Valley",
    "sg:classifiers":[
        {
            "category":"Building & Trades",
            "subcategory":"Plumbing",
            "type":"Services"
        }
    ],
    "sg:phone":"+1 805 526 1765",
    "sg:postcode":"93063",
    "sg:province":"CA",
    "sg:tags":[
        "conditioning",
        "air",
        "system",
        "contractor"
    ],
    "wof:name":"Cuneo Air",
    "wof:placetype":"venue"
},
  "geometry": {"coordinates":[-118.713869,34.297737],"type":"Point"}
}