{
  "type": "Feature",
  "properties": {
    "iso:country":"US",
    "sg:address":"495 S Washington St",
    "sg:city":"Sonora",
    "sg:classifiers":[
        {
            "category":"Retail",
            "subcategory":"Auto Repair",
            "type":"Services"
        }
    ],
    "sg:phone":"+1 209 532 3407",
    "sg:postcode":"95370",
    "sg:province":"CA",
    "sg:tags":[
        "repairing",
        "automobile",
        "radiator"
    ],
    "wof:name":"Radiator Doctor",
    "wof:placetype":"venue"
},
  "geometry": {"coordinates":[-120.380891,37.978739],"type":"Point"}
}