{
  "type": "Feature",
  "properties": {
    "addr:full":"1379 Kintyre Way San Jose CA 95129",
    "addr:housenumber":"1379",
    "addr:postcode":"95129",
    "addr:street":"Kintyre Way",
    "iso:country":"US",
    "sg:address":"1379 Kintyre Way",
    "sg:city":"San Jose",
    "sg:classifiers":[
        {
            "category":"Professional",
            "type":"Services"
        }
    ],
    "sg:phone":"+1 408 865 1940",
    "sg:postcode":"95129",
    "sg:province":"CA",
    "wof:name":"Zohar Golan",
    "wof:placetype":"venue"
},
  "geometry": {"coordinates":[-122.02469600000001,37.298683],"type":"Point"}
}