{
  "type": "Feature",
  "properties": {
    "addr:full":"3498 Green Valley Rd Rescue CA 95672",
    "addr:housenumber":"3498",
    "addr:postcode":"95672",
    "addr:street":"Green Valley Rd",
    "iso:country":"US",
    "sg:address":"3498 Green Valley Rd",
    "sg:city":"Rescue",
    "sg:classifiers":[
        {
            "category":"Social Services",
            "subcategory":"Child Care",
            "type":"Services"
        }
    ],
    "sg:phone":"+1 530 676 4110",
    "sg:postcode":"95672",
    "sg:province":"CA",
    "sg:tags":[
        "kindergarten",
        "academic",
        "school"
    ],
    "wof:name":"Deweese Montessori School",
    "wof:placetype":"venue"
},
  "geometry": {"coordinates":[-120.98051700000001,38.703074],"type":"Point"}
}