{
  "type": "Feature",
  "properties": {
    "addr:full":"303 Main St Rio Vista CA 94571",
    "addr:housenumber":"303",
    "addr:postcode":"94571",
    "addr:street":"Main St",
    "iso:country":"US",
    "sg:address":"303 Main St",
    "sg:city":"Rio Vista",
    "sg:classifiers":[
        {
            "category":"Shopping",
            "type":"Retail Goods"
        }
    ],
    "sg:phone":"+1 707 374 2014",
    "sg:postcode":"94571",
    "sg:province":"CA",
    "sg:tags":[
        "telephone",
        "cellular"
    ],
    "sg:website":"www.completecommunications.com",
    "wof:name":"Complete Communications",
    "wof:placetype":"venue"
},
  "geometry": {"coordinates":[-121.692447,38.157113],"type":"Point"}
}