{
  "type": "Feature",
  "properties": {
    "iso:country":"US",
    "sg:address":"11282 Spruce Ave",
    "sg:city":"Bloomington",
    "sg:classifiers":[
        {
            "category":"Social Services",
            "type":"Services"
        }
    ],
    "sg:phone":"+1 909 877 3330",
    "sg:postcode":"92316",
    "sg:province":"CA",
    "sg:tags":[
        "youth",
        "organization",
        "center"
    ],
    "wof:name":"Diamond L Ranch For Boys",
    "wof:placetype":"venue"
},
  "geometry": {"coordinates":[-117.387681,34.052616],"type":"Point"}
}