{
  "type": "Feature",
  "properties": {
    "addr:full":"80 Mimosa Ln Chico CA 95973",
    "addr:housenumber":"80",
    "addr:postcode":"95973",
    "addr:street":"Mimosa Ln",
    "iso:country":"US",
    "sg:address":"80 Mimosa Ln",
    "sg:city":"Chico",
    "sg:classifiers":[
        {
            "category":"Professional",
            "subcategory":"Management & Consulting",
            "type":"Services"
        }
    ],
    "sg:phone":"+1 530 345 2335",
    "sg:postcode":"95973",
    "sg:province":"CA",
    "sg:tags":[
        "construction"
    ],
    "wof:name":"Construction Solutions",
    "wof:placetype":"venue"
},
  "geometry": {"coordinates":[-121.880818,39.817785],"type":"Point"}
}