{
  "type": "Feature",
  "properties": {
    "iso:country":"US",
    "sg:address":"69410 el Canto Rd",
    "sg:city":"Cathedral City",
    "sg:classifiers":[
        {
            "category":"Communications",
            "subcategory":"Radio Station",
            "type":"Services"
        }
    ],
    "sg:phone":"+1 760 324 0503",
    "sg:postcode":"92234",
    "sg:province":"CA",
    "sg:tags":[
        "broadcast"
    ],
    "wof:name":"M J Rock Climbing",
    "wof:placetype":"venue"
},
  "geometry": {"coordinates":[-116.452455,33.821868],"type":"Point"}
}