{
  "type": "Feature",
  "properties": {
    "addr:full":"8450 Valley Blvd Ste 105 Rosemead CA 91770",
    "addr:housenumber":"8450",
    "addr:postcode":"91770",
    "addr:street":"Valley Blvd Ste 105",
    "iso:country":"US",
    "sg:address":"8450 Valley Blvd Ste 105",
    "sg:city":"Rosemead",
    "sg:classifiers":[
        {
            "category":"Personal",
            "subcategory":"Beauty Salon",
            "type":"Services"
        }
    ],
    "sg:phone":"+1 626 288 9880",
    "sg:postcode":"91770",
    "sg:province":"CA",
    "sg:tags":[
        "hair"
    ],
    "wof:name":"Ann Hair Design",
    "wof:placetype":"venue"
},
  "geometry": {"coordinates":[-118.08482600000001,34.079777],"type":"Point"}
}