{
  "type": "Feature",
  "properties": {
    "iso:country":"US",
    "sg:address":"1175 E Champlain Dr",
    "sg:city":"Fresno",
    "sg:classifiers":[
        {
            "category":"Personal",
            "subcategory":"Beauty Salon",
            "type":"Services"
        }
    ],
    "sg:phone":"+1 559 434 1764",
    "sg:postcode":"93720",
    "sg:province":"CA",
    "sg:tags":[
        "manicuring"
    ],
    "wof:name":"Fashion Nails",
    "wof:placetype":"venue"
},
  "geometry": {"coordinates":[-119.760079,36.869853],"type":"Point"}
}