{
  "type": "Feature",
  "properties": {
    "iso:country":"US",
    "sg:address":"1001 E 3rd St",
    "sg:city":"Hanford",
    "sg:classifiers":[
        {
            "category":"Banks & Credit Unions",
            "subcategory":"Bank",
            "type":"Services"
        }
    ],
    "sg:phone":"+1 559 584 5401",
    "sg:postcode":"93230",
    "sg:province":"CA",
    "sg:tags":[
        "loan"
    ],
    "wof:name":"Federal Land Bank Assn",
    "wof:placetype":"venue"
},
  "geometry": {"coordinates":[-119.625709,36.324191],"type":"Point"}
}