{
  "type": "Feature",
  "properties": {
    "addr:full":"202 C St San Diego CA 92101",
    "addr:housenumber":"202",
    "addr:postcode":"92101",
    "addr:street":"C St",
    "iso:country":"US",
    "sg:address":"202 C St",
    "sg:city":"San Diego",
    "sg:classifiers":[
        {
            "category":"Food & Beverages",
            "subcategory":"Bakery",
            "type":"Retail Goods"
        }
    ],
    "sg:phone":"+1 619 239 0304",
    "sg:postcode":"92101",
    "sg:province":"CA",
    "sg:tags":[
        "sandwich"
    ],
    "wof:name":"City Cafe",
    "wof:placetype":"venue"
},
  "geometry": {"coordinates":[-117.16479,32.716841],"type":"Point"}
}