{
  "type": "Feature",
  "properties": {
    "iso:country":"US",
    "sg:address":"6086 Citracado Cir",
    "sg:city":"Carlsbad",
    "sg:classifiers":[
        {
            "category":"Manufacturing",
            "subcategory":"Toys & Sporting Goods",
            "type":"Manufacturing & Wholesale Goods"
        }
    ],
    "sg:phone":"+1 760 476 0799",
    "sg:postcode":"92009",
    "sg:province":"CA",
    "sg:tags":[
        "mfg"
    ],
    "wof:name":"Ingham Surf Designs",
    "wof:placetype":"venue"
},
  "geometry": {"coordinates":[-117.243798,33.126118],"type":"Point"}
}