{
  "type": "Feature",
  "properties": {
    "addr:full":"9100 E 9th St Rancho Cucamonga CA 91730",
    "addr:housenumber":"9100",
    "addr:postcode":"91730",
    "addr:street":"E 9Th St",
    "iso:country":"US",
    "sg:address":"9100 E 9th St",
    "sg:city":"Rancho Cucamonga",
    "sg:classifiers":[
        {
            "category":"Freight",
            "type":"Transportation"
        }
    ],
    "sg:phone":"+1 951 520 8491",
    "sg:postcode":"91730",
    "sg:province":"CA",
    "sg:tags":[
        "operator",
        "trucking"
    ],
    "wof:name":"Harrow Truck Lines",
    "wof:placetype":"venue"
},
  "geometry": {"coordinates":[-117.60709199999999,34.095771],"type":"Point"}
}