{
  "type": "Feature",
  "properties": {
    "addr:full":"2001 40th Ave Capitola CA 95010",
    "addr:housenumber":"2001",
    "addr:postcode":"95010",
    "addr:street":"40Th Ave",
    "iso:country":"US",
    "sg:address":"2001 40th Ave",
    "sg:city":"Capitola",
    "sg:classifiers":[
        {
            "category":"Professional",
            "subcategory":"Employment Agencies",
            "type":"Services"
        }
    ],
    "sg:phone":"+1 831 476 7700",
    "sg:postcode":"95010",
    "sg:province":"CA",
    "sg:tags":[
        "opportunity"
    ],
    "wof:name":"Manpower Professional",
    "wof:placetype":"venue"
},
  "geometry": {"coordinates":[-121.966003,36.978901],"type":"Point"}
}