{
  "type": "Feature",
  "properties": {
    "iso:country":"US",
    "sg:address":"16633 Ventura Blvd Ste 90",
    "sg:city":"Encino",
    "sg:classifiers":[
        {
            "category":"Real Estate",
            "subcategory":"Real Estate Services",
            "type":"Services"
        },
        {
            "category":"Real Estate",
            "subcategory":"Real Estate Agent",
            "type":"Services"
        }
    ],
    "sg:phone":"+1 818 216 1664",
    "sg:postcode":"91436",
    "sg:province":"CA",
    "sg:tags":[
        "buyer",
        "broker"
    ],
    "wof:name":"Flo-Pallet, Inc.",
    "wof:placetype":"venue"
},
  "geometry": {"coordinates":[-118.495773,34.158035],"type":"Point"}
}