{
  "type": "Feature",
  "properties": {
    "addr:full":"11601 Bryant Rd El Monte CA 91732",
    "addr:housenumber":"11601",
    "addr:postcode":"91732",
    "addr:street":"Bryant Rd",
    "iso:country":"US",
    "sg:address":"11601 Bryant Rd",
    "sg:city":"El Monte",
    "sg:classifiers":[
        {
            "category":"Organizations",
            "subcategory":"Religious Organization",
            "type":"Services"
        }
    ],
    "sg:phone":"+1 626 454 1304",
    "sg:postcode":"91732",
    "sg:province":"CA",
    "sg:tags":[
        "church"
    ],
    "wof:name":"Vietnamese Seventh Day Advntst",
    "wof:placetype":"venue"
},
  "geometry": {"coordinates":[-118.019328,34.078171],"type":"Point"}
}