{
  "type": "Feature",
  "properties": {
    "addr:full":"1663 E del Amo Blvd Carson CA 90746",
    "addr:housenumber":"1663",
    "addr:postcode":"90746",
    "addr:street":"E Del Amo Blvd",
    "iso:country":"US",
    "sg:address":"1663 E del Amo Blvd",
    "sg:city":"Carson",
    "sg:classifiers":[
        {
            "category":"Manufacturing",
            "subcategory":"Printing",
            "type":"Manufacturing & Wholesale Goods"
        }
    ],
    "sg:phone":"+1 323 979 2989",
    "sg:postcode":"90746",
    "sg:province":"CA",
    "sg:tags":[
        "screen"
    ],
    "wof:name":"Sad Sam Screening",
    "wof:placetype":"venue"
},
  "geometry": {"coordinates":[-118.240537,33.846819],"type":"Point"}
}