{
  "type": "Feature",
  "properties": {
    "addr:full":"1122 W Valley Pkwy Escondido CA 92025",
    "addr:housenumber":"1122",
    "addr:postcode":"92025",
    "addr:street":"W Valley Pkwy",
    "iso:country":"US",
    "sg:address":"1122 W Valley Pkwy",
    "sg:city":"Escondido",
    "sg:classifiers":[
        {
            "category":"Retail",
            "subcategory":"Auto Repair",
            "type":"Services"
        }
    ],
    "sg:phone":"+1 760 738 8863",
    "sg:postcode":"92025",
    "sg:province":"CA",
    "sg:tags":[
        "repairing",
        "automobile"
    ],
    "wof:name":"Econo Lube N' Tune",
    "wof:placetype":"venue"
},
  "geometry": {"coordinates":[-117.098922,33.115522],"type":"Point"}
}