{
  "type": "Feature",
  "properties": {
    "iso:country":"US",
    "sg:address":"1437 6th St",
    "sg:city":"Santa Monica",
    "sg:classifiers":[
        {
            "category":"Shopping",
            "subcategory":"Computers & Home Electronics",
            "type":"Retail Goods"
        }
    ],
    "sg:phone":"+1 310 656 6840",
    "sg:postcode":"90401",
    "sg:province":"CA",
    "sg:tags":[
        "software"
    ],
    "wof:name":"Snap System Inc",
    "wof:placetype":"venue"
},
  "geometry": {"coordinates":[-118.492115,34.017154],"type":"Point"}
}