{
  "type": "Feature",
  "properties": {
    "iso:country":"US",
    "sg:address":"2300 Barney Rd",
    "sg:city":"Anderson",
    "sg:classifiers":[
        {
            "category":"Building & Trades",
            "subcategory":"Construction",
            "type":"Services"
        }
    ],
    "sg:phone":"+1 530 365 0108",
    "sg:postcode":"96007",
    "sg:province":"CA",
    "sg:tags":[
        "control",
        "erosion"
    ],
    "wof:name":"California Paving Fabrics Inc",
    "wof:placetype":"venue"
},
  "geometry": {"coordinates":[-122.290701,40.443269],"type":"Point"}
}