{
  "type": "Feature",
  "properties": {
    "iso:country":"US",
    "sg:address":"2669 Mission Village Dr",
    "sg:city":"San Diego",
    "sg:classifiers":[
        {
            "category":"Personal",
            "subcategory":"Adult",
            "type":"Services"
        }
    ],
    "sg:phone":"+1 858 576 7076",
    "sg:postcode":"92123",
    "sg:province":"CA",
    "sg:tags":[
        "escort"
    ],
    "wof:name":"Beautiful Blondes",
    "wof:placetype":"venue"
},
  "geometry": {"coordinates":[-117.124056,32.79456],"type":"Point"}
}