{
  "type": "Feature",
  "properties": {
    "addr:full":"15350 Winchester Blvd Los Gatos CA 95030",
    "addr:housenumber":"15350",
    "addr:postcode":"95030",
    "addr:street":"Winchester Blvd",
    "iso:country":"US",
    "sg:address":"15350 Winchester Blvd",
    "sg:city":"Los Gatos",
    "sg:classifiers":[
        {
            "category":"Travel",
            "subcategory":"Hotels & Motels",
            "type":"Entertainment"
        }
    ],
    "sg:phone":"+1 408 395 6710",
    "sg:postcode":"95030",
    "sg:province":"CA",
    "wof:name":"Lodge At Villa Felice",
    "wof:placetype":"venue"
},
  "geometry": {"coordinates":[-121.974155,37.245352],"type":"Point"}
}