{
  "type": "Feature",
  "properties": {
    "addr:full":"307 N Fries Ave Wilmington CA 90744",
    "addr:housenumber":"307",
    "addr:postcode":"90744",
    "addr:street":"N Fries Ave",
    "iso:country":"US",
    "sg:address":"307 N Fries Ave",
    "sg:city":"Wilmington",
    "sg:classifiers":[
        {
            "category":"Autos & Motor Vehicles",
            "subcategory":"Boat Sales",
            "type":"Retail Goods"
        }
    ],
    "sg:phone":"+1 310 830 2848",
    "sg:postcode":"90744",
    "sg:province":"CA",
    "sg:tags":[
        "equipment",
        "marine",
        "supply"
    ],
    "wof:name":"Seamar Electronics",
    "wof:placetype":"venue"
},
  "geometry": {"coordinates":[-118.26464799999999,33.773938],"type":"Point"}
}