{
  "type": "Feature",
  "properties": {
    "iso:country":"US",
    "sg:address":"924 E Main St",
    "sg:city":"Santa Maria",
    "sg:classifiers":[
        {
            "category":"Recreation",
            "type":"Entertainment"
        }
    ],
    "sg:phone":"+1 805 925 7565",
    "sg:postcode":"93454",
    "sg:province":"CA",
    "sg:tags":[
        "psychic",
        "medium"
    ],
    "wof:name":"Psychic Readings",
    "wof:placetype":"venue"
},
  "geometry": {"coordinates":[-120.420127,34.952992],"type":"Point"}
}