{
  "type": "Feature",
  "properties": {
    "addr:full":"1644 G St Arcata CA 95521",
    "addr:housenumber":"1644",
    "addr:postcode":"95521",
    "addr:street":"G St",
    "iso:country":"US",
    "sg:address":"1644 G St",
    "sg:city":"Arcata",
    "sg:classifiers":[
        {
            "category":"Food & Beverages",
            "subcategory":"Liquor & Beverages",
            "type":"Retail Goods"
        }
    ],
    "sg:phone":"+1 707 822 1965",
    "sg:postcode":"95521",
    "sg:province":"CA",
    "sg:tags":[
        "wine"
    ],
    "wof:name":"Hutchins Grocery",
    "wof:placetype":"venue"
},
  "geometry": {"coordinates":[-124.08343000000001,40.874784],"type":"Point"}
}