{
  "type": "Feature",
  "properties": {
    "iso:country":"US",
    "sg:address":"24363 Southland Dr",
    "sg:city":"Hayward",
    "sg:classifiers":[
        {
            "category":"Utilities",
            "subcategory":"Mobile Phone",
            "type":"Services"
        }
    ],
    "sg:phone":"+1 510 780 0550",
    "sg:postcode":"94545",
    "sg:province":"CA",
    "sg:tags":[
        "communication",
        "electronic",
        "radiotelephone"
    ],
    "wof:name":"Sprint Pcs Personal Comm Svc",
    "wof:placetype":"venue"
},
  "geometry": {"coordinates":[-122.105134,37.654247],"type":"Point"}
}