{
  "type": "Feature",
  "properties": {
    "iso:country":"US",
    "sg:address":"3028 El Camino Real",
    "sg:city":"Santa Clara",
    "sg:classifiers":[
        {
            "category":"Restaurant",
            "type":"Food & Drink"
        }
    ],
    "sg:phone":"+1 408 615 0370",
    "sg:postcode":"95051",
    "sg:province":"CA",
    "sg:tags":[
        "korean"
    ],
    "wof:name":"Seoul Gom Tang",
    "wof:placetype":"venue"
},
  "geometry": {"coordinates":[-121.981003,37.352402],"type":"Point"}
}