{
  "type": "Feature",
  "properties": {
    "addr:full":"14708 Arminta St Panorama City CA 91402",
    "addr:housenumber":"14708",
    "addr:postcode":"91402",
    "addr:street":"Arminta St",
    "iso:country":"US",
    "sg:address":"14708 Arminta St",
    "sg:city":"Panorama City",
    "sg:classifiers":[
        {
            "category":"Manufacturing",
            "subcategory":"Tools & Machinery",
            "type":"Manufacturing & Wholesale Goods"
        }
    ],
    "sg:phone":"+1 818 997 0295",
    "sg:postcode":"91402",
    "sg:province":"CA",
    "sg:tags":[
        "machine",
        "shop"
    ],
    "wof:name":"A S Precision Machining",
    "wof:placetype":"venue"
},
  "geometry": {"coordinates":[-118.451026,34.213329],"type":"Point"}
}