{
  "type": "Feature",
  "properties": {
    "iso:country":"US",
    "sg:address":"1349 Arch St",
    "sg:city":"Berkeley",
    "sg:classifiers":[
        {
            "category":"Professional",
            "subcategory":"Accounting & Tax Preparation",
            "type":"Services"
        }
    ],
    "sg:phone":"+1 510 548 5321",
    "sg:postcode":"94708",
    "sg:province":"CA",
    "sg:tags":[
        "public",
        "accountants-certified"
    ],
    "wof:name":"Amiram Milanov Cpa",
    "wof:placetype":"venue"
},
  "geometry": {"coordinates":[-122.265063,37.882975],"type":"Point"}
}