{
  "type": "Feature",
  "properties": {
    "iso:country":"US",
    "sg:address":"1488 Foxworthy Ave",
    "sg:city":"San Jose",
    "sg:classifiers":[
        {
            "category":"Building & Trades",
            "subcategory":"Pest Control",
            "type":"Services"
        }
    ],
    "sg:phone":"+1 408 267 4709",
    "sg:postcode":"95118",
    "sg:province":"CA",
    "wof:name":"Ma Velle Enterprise",
    "wof:placetype":"venue"
},
  "geometry": {"coordinates":[-121.895957,37.273661],"type":"Point"}
}