{
  "type": "Feature",
  "properties": {
    "iso:country":"US",
    "sg:address":"4598 30th St",
    "sg:city":"San Diego",
    "sg:classifiers":[
        {
            "category":"Personal",
            "subcategory":"Hair Removal",
            "type":"Services"
        }
    ],
    "sg:phone":"+1 619 521 0401",
    "sg:postcode":"92101",
    "sg:province":"CA",
    "wof:name":"Hair & Skin Care",
    "wof:placetype":"venue"
},
  "geometry": {"coordinates":[-117.13038400000001,32.760801],"type":"Point"}
}