{
  "type": "Feature",
  "properties": {
    "iso:country":"US",
    "sg:address":"509 N Norton Ave",
    "sg:city":"Los Angeles",
    "sg:classifiers":[
        {
            "category":"Professional",
            "type":"Services"
        }
    ],
    "sg:phone":"+1 310 385 3879",
    "sg:postcode":"90004",
    "sg:province":"CA",
    "wof:name":"On Line Entertainmnt",
    "wof:placetype":"venue"
},
  "geometry": {"coordinates":[-118.31711799999999,34.079928],"type":"Point"}
}