{
  "type": "Feature",
  "properties": {
    "addr:full":"3130 Castro Valley Blvd Castro Valley CA 94546",
    "addr:housenumber":"3130",
    "addr:postcode":"94546",
    "addr:street":"Castro Valley Blvd",
    "iso:country":"US",
    "sg:address":"3130 Castro Valley Blvd",
    "sg:city":"Castro Valley",
    "sg:classifiers":[
        {
            "category":"Autos & Motor Vehicles",
            "subcategory":"Auto Supplies",
            "type":"Retail Goods"
        }
    ],
    "sg:phone":"+1 510 537 3515",
    "sg:postcode":"94546",
    "sg:province":"CA",
    "sg:tags":[
        "tire"
    ],
    "wof:name":"Brake & Alignment Specialties",
    "wof:placetype":"venue"
},
  "geometry": {"coordinates":[-122.08000199999999,37.695499],"type":"Point"}
}