{
  "type": "Feature",
  "properties": {
    "iso:country":"US",
    "sg:address":"252 S Imperial Ave",
    "sg:city":"El Centro",
    "sg:classifiers":[
        {
            "category":"Banks & Credit Unions",
            "subcategory":"Bank",
            "type":"Services"
        }
    ],
    "sg:phone":"+1 760 353 6130",
    "sg:postcode":"92243",
    "sg:province":"CA",
    "sg:tags":[
        "cashing",
        "check"
    ],
    "wof:name":"Check Cash",
    "wof:placetype":"venue"
},
  "geometry": {"coordinates":[-115.56999500000001,32.791173],"type":"Point"}
}