{
  "type": "Feature",
  "properties": {
    "addr:full":"6833 W 2nd St Rio Linda CA 95673",
    "addr:housenumber":"6833",
    "addr:postcode":"95673",
    "addr:street":"W 2Nd St",
    "iso:country":"US",
    "sg:address":"6833 W 2nd St",
    "sg:city":"Rio Linda",
    "sg:classifiers":[
        {
            "category":"Farming",
            "subcategory":"Nursery",
            "type":"Manufacturing & Wholesale Goods"
        }
    ],
    "sg:phone":"+1 916 991 0314",
    "sg:postcode":"95673",
    "sg:province":"CA",
    "sg:tags":[
        "ornamental"
    ],
    "wof:name":"Gum & Roses",
    "wof:placetype":"venue"
},
  "geometry": {"coordinates":[-121.46617999999999,38.691925],"type":"Point"}
}