{
  "type": "Feature",
  "properties": {
    "iso:country":"US",
    "sg:address":"915 California Ave",
    "sg:city":"Bakersfield",
    "sg:classifiers":[
        {
            "category":"Personal",
            "subcategory":"Beauty Salon",
            "type":"Services"
        }
    ],
    "sg:phone":"+1 661 852 0607",
    "sg:postcode":"93304",
    "sg:province":"CA",
    "wof:name":"Turning Headz Hair & Nails",
    "wof:placetype":"venue"
},
  "geometry": {"coordinates":[-119.012833,35.368389],"type":"Point"}
}