{
  "type": "Feature",
  "properties": {
    "iso:country":"US",
    "sg:address":"25198 Hesperian Blvd",
    "sg:city":"Hayward",
    "sg:classifiers":[
        {
            "category":"Fast Food",
            "type":"Food & Drink"
        }
    ],
    "sg:phone":"+1 510 786 3449",
    "sg:postcode":"94545",
    "sg:province":"CA",
    "sg:tags":[
        "burger"
    ],
    "sg:website":"www.jackinthebox.com",
    "wof:name":"Jack In The Box",
    "wof:placetype":"venue"
},
  "geometry": {"coordinates":[-122.105003,37.643799],"type":"Point"}
}