{
  "type": "Feature",
  "properties": {
    "iso:country":"US",
    "sg:address":"700 S Flower St",
    "sg:city":"Los Angeles",
    "sg:classifiers":[
        {
            "category":"Professional",
            "subcategory":"Employment Agencies",
            "type":"Services"
        }
    ],
    "sg:phone":"+1 213 624 3853",
    "sg:postcode":"90017",
    "sg:province":"CA",
    "sg:tags":[
        "opportunity"
    ],
    "wof:name":"Remedy Intelligent Staffing",
    "wof:placetype":"venue"
},
  "geometry": {"coordinates":[-118.26009999999999,34.047256],"type":"Point"}
}