{
  "type": "Feature",
  "properties": {
    "addr:full":"2447 San Pablo Ave Berkeley CA 94702",
    "addr:housenumber":"2447",
    "addr:postcode":"94702",
    "addr:street":"San Pablo Ave",
    "iso:country":"US",
    "sg:address":"2447 San Pablo Ave",
    "sg:city":"Berkeley",
    "sg:classifiers":[
        {
            "category":"Personal",
            "subcategory":"Beauty Salon",
            "type":"Services"
        }
    ],
    "sg:phone":"+1 510 486 8304",
    "sg:postcode":"94702",
    "sg:province":"CA",
    "wof:name":"Magnificent Hair Stylers",
    "wof:placetype":"venue"
},
  "geometry": {"coordinates":[-122.29004399999999,37.862625],"type":"Point"}
}