{
  "type": "Feature",
  "properties": {
    "iso:country":"US",
    "sg:address":"2829 Bridgeway",
    "sg:city":"Sausalito",
    "sg:classifiers":[
        {
            "category":"Personal",
            "subcategory":"Beauty Salon",
            "type":"Services"
        }
    ],
    "sg:phone":"+1 415 332 2920",
    "sg:postcode":"94965",
    "sg:province":"CA",
    "wof:name":"Jennifer",
    "wof:placetype":"venue"
},
  "geometry": {"coordinates":[-122.503659,37.87027],"type":"Point"}
}