{
  "type": "Feature",
  "properties": {
    "iso:country":"US",
    "sg:address":"2405 Ashby Rd",
    "sg:city":"Merced",
    "sg:classifiers":[
        {
            "category":"Retail",
            "subcategory":"Animal Services",
            "type":"Services"
        }
    ],
    "sg:phone":"+1 209 383 4582",
    "sg:postcode":"95348",
    "sg:province":"CA",
    "sg:tags":[
        "pet",
        "crematory",
        "cemetery"
    ],
    "wof:name":"Franklin Pet Cemetery",
    "wof:placetype":"venue"
},
  "geometry": {"coordinates":[-120.54189100000001,37.322987],"type":"Point"}
}