{
  "type": "Feature",
  "properties": {
    "addr:full":"841 W 14th St Eureka CA 95501",
    "addr:housenumber":"841",
    "addr:postcode":"95501",
    "addr:street":"W 14Th St",
    "iso:country":"US",
    "sg:address":"841 W 14th St",
    "sg:city":"Eureka",
    "sg:classifiers":[
        {
            "category":"Retail",
            "subcategory":"Auto Repair",
            "type":"Services"
        }
    ],
    "sg:phone":"+1 707 443 9872",
    "sg:postcode":"95501",
    "sg:province":"CA",
    "sg:tags":[
        "repairing",
        "automobile"
    ],
    "wof:name":"Master Tech Automotive",
    "wof:placetype":"venue"
},
  "geometry": {"coordinates":[-124.176869,40.794097],"type":"Point"}
}