{
  "type": "Feature",
  "properties": {
    "addr:full":"1011 L Street Sacramento CA 95814",
    "addr:housenumber":"1011",
    "addr:postcode":"95814",
    "addr:street":"L Street",
    "iso:country":"US",
    "sg:address":"1011 L Street",
    "sg:city":"Sacramento",
    "sg:classifiers":[
        {
            "category":"Personal",
            "subcategory":"Barber",
            "type":"Services"
        },
        {
            "category":"Personal",
            "subcategory":"Nail Salon",
            "type":"Services"
        }
    ],
    "sg:phone":"+1 916 446 4111",
    "sg:postcode":"95814",
    "sg:province":"CA",
    "wof:name":"Mr Don's Hair Designing For Men & Women",
    "wof:placetype":"venue"
},
  "geometry": {"coordinates":[-121.493576,38.577991],"type":"Point"}
}