{
  "type": "Feature",
  "properties": {
    "addr:full":"5301 S Main St Los Angeles CA 90037",
    "addr:housenumber":"5301",
    "addr:postcode":"90037",
    "addr:street":"S Main St",
    "iso:country":"US",
    "sg:address":"5301 S Main St",
    "sg:city":"Los Angeles",
    "sg:classifiers":[
        {
            "category":"Shopping",
            "subcategory":"Clothing, Apparel, & Fashions",
            "type":"Retail Goods"
        }
    ],
    "sg:phone":"+1 323 232 8675",
    "sg:postcode":"90037",
    "sg:province":"CA",
    "sg:tags":[
        "children's",
        "clothing"
    ],
    "wof:name":"Vanessa's Clothing Store",
    "wof:placetype":"venue"
},
  "geometry": {"coordinates":[-118.274002,33.994202],"type":"Point"}
}