{
  "type": "Feature",
  "properties": {
    "iso:country":"US",
    "sg:address":"12473 Central Ave",
    "sg:city":"Chino",
    "sg:classifiers":[
        {
            "category":"Retail",
            "subcategory":"Laundry & Dry Cleaning",
            "type":"Services"
        }
    ],
    "sg:phone":"+1 909 364 1100",
    "sg:postcode":"91710",
    "sg:province":"CA",
    "sg:tags":[
        "cleaners"
    ],
    "wof:name":"Dollar Cleaners",
    "wof:placetype":"venue"
},
  "geometry": {"coordinates":[-117.689313,34.027665],"type":"Point"}
}