{
  "type": "Feature",
  "properties": {
    "addr:full":"4425 Jamboree Rd Newport Beach CA 92660",
    "addr:housenumber":"4425",
    "addr:postcode":"92660",
    "addr:street":"Jamboree Rd",
    "iso:country":"US",
    "sg:address":"4425 Jamboree Rd",
    "sg:city":"Newport Beach",
    "sg:classifiers":[
        {
            "category":"Professional",
            "type":"Services"
        },
        {
            "category":"Real Estate",
            "subcategory":"Real Estate Operator",
            "type":"Services"
        }
    ],
    "sg:phone":"+1 949 955 2040",
    "sg:postcode":"92660",
    "sg:province":"CA",
    "sg:tags":[
        "property",
        "establishment",
        "lessor"
    ],
    "wof:name":"Lescot International",
    "wof:placetype":"venue"
},
  "geometry": {"coordinates":[-117.85913600000001,33.661229],"type":"Point"}
}