{
  "type": "Feature",
  "properties": {
    "iso:country":"US",
    "sg:address":"317 Ocean Front Walk",
    "sg:city":"Venice",
    "sg:classifiers":[
        {
            "category":"Professional",
            "subcategory":"Lawyer & Legal Services",
            "type":"Services"
        }
    ],
    "sg:phone":"+1 310 664 0317",
    "sg:postcode":"90291",
    "sg:province":"CA",
    "sg:tags":[
        "attorney"
    ],
    "wof:name":"Voorhies & Kramer Law Offices",
    "wof:placetype":"venue"
},
  "geometry": {"coordinates":[-118.48000999999999,33.994007],"type":"Point"}
}