{
  "type": "Feature",
  "properties": {
    "addr:full":"525 S Broadway Santa Maria CA 93454",
    "addr:housenumber":"525",
    "addr:postcode":"93454",
    "addr:street":"S Broadway",
    "iso:country":"US",
    "sg:address":"525 S Broadway",
    "sg:city":"Santa Maria",
    "sg:classifiers":[
        {
            "category":"Shopping",
            "type":"Retail Goods"
        }
    ],
    "sg:phone":"+1 805 925 6606",
    "sg:postcode":"93454",
    "sg:province":"CA",
    "sg:tags":[
        "pet",
        "food",
        "supply"
    ],
    "wof:name":"Lemos Feed & Pet Supplies",
    "wof:placetype":"venue"
},
  "geometry": {"coordinates":[-120.43607900000001,34.948102],"type":"Point"}
}