{
  "type": "Feature",
  "properties": {
    "addr:full":"2240 5th Ave San Diego CA 92101",
    "addr:housenumber":"2240",
    "addr:postcode":"92101",
    "addr:street":"5Th Ave",
    "iso:country":"US",
    "sg:address":"2240 5th Ave",
    "sg:city":"San Diego",
    "sg:classifiers":[
        {
            "category":"Professional",
            "subcategory":"Lawyer & Legal Services",
            "type":"Services"
        }
    ],
    "sg:phone":"+1 619 232 9571",
    "sg:postcode":"92101",
    "sg:province":"CA",
    "sg:tags":[
        "attorney"
    ],
    "wof:name":"Martha R Logan",
    "wof:placetype":"venue"
},
  "geometry": {"coordinates":[-117.160269,32.729298],"type":"Point"}
}