{
  "type": "Feature",
  "properties": {
    "iso:country":"US",
    "sg:address":"341 W 1st St",
    "sg:city":"Claremont",
    "sg:classifiers":[
        {
            "category":"Banks & Credit Unions",
            "subcategory":"Bank",
            "type":"Services"
        }
    ],
    "sg:phone":"+1 909 621 1114",
    "sg:postcode":"91711",
    "sg:province":"CA",
    "sg:tags":[
        "loan",
        "real estate"
    ],
    "wof:name":"Home Front Mortgage",
    "wof:placetype":"venue"
},
  "geometry": {"coordinates":[-117.718112,34.094772],"type":"Point"}
}