{
  "type": "Feature",
  "properties": {
    "iso:country":"US",
    "sg:address":"242 Dundee Dr",
    "sg:city":"South San Francisco",
    "sg:classifiers":[
        {
            "category":"Shopping",
            "subcategory":"Hobbies, Toys, & Games",
            "type":"Retail Goods"
        }
    ],
    "sg:phone":"+1 650 755 9368",
    "sg:postcode":"94080",
    "sg:province":"CA",
    "wof:name":"Dorothy Jensen",
    "wof:placetype":"venue"
},
  "geometry": {"coordinates":[-122.459112,37.658739],"type":"Point"}
}