{
  "type": "Feature",
  "properties": {
    "addr:full":"10450 Pioneer Blvd Santa Fe Springs CA 90650",
    "addr:housenumber":"10450",
    "addr:postcode":"90650",
    "addr:street":"Pioneer Blvd",
    "iso:country":"US",
    "sg:address":"10450 Pioneer Blvd",
    "sg:city":"Santa Fe Springs",
    "sg:classifiers":[
        {
            "category":"Home & Garden",
            "subcategory":"Home Furnishings",
            "type":"Retail Goods"
        }
    ],
    "sg:phone":"+1 562 906 0554",
    "sg:postcode":"90650",
    "sg:province":"CA",
    "sg:tags":[
        "utensil",
        "cooking"
    ],
    "wof:name":"Happy Cooking Co",
    "wof:placetype":"venue"
},
  "geometry": {"coordinates":[-118.08175900000001,33.938984],"type":"Point"}
}