{
  "type": "Feature",
  "properties": {
    "iso:country":"US",
    "sg:address":"9864 Glenoaks Blvd",
    "sg:city":"Sun Valley",
    "sg:classifiers":[
        {
            "category":"Autos & Motor Vehicles",
            "subcategory":"Auto Supplies",
            "type":"Retail Goods"
        }
    ],
    "sg:phone":"+1 818 768 8736",
    "sg:postcode":"91352",
    "sg:province":"CA",
    "sg:tags":[
        "automobile",
        "parts"
    ],
    "wof:name":"American Racing Equipment",
    "wof:placetype":"venue"
},
  "geometry": {"coordinates":[-118.384514,34.246574],"type":"Point"}
}