{
  "type": "Feature",
  "properties": {
    "addr:full":"10642 Santa Monica Blvd Los Angeles CA 90025",
    "addr:housenumber":"10642",
    "addr:postcode":"90025",
    "addr:street":"Santa Monica Blvd",
    "iso:country":"US",
    "sg:address":"10642 Santa Monica Blvd",
    "sg:city":"Los Angeles",
    "sg:classifiers":[
        {
            "category":"Banks & Credit Unions",
            "subcategory":"Financial Services",
            "type":"Services"
        }
    ],
    "sg:phone":"+1 323 843 4015",
    "sg:postcode":"90025",
    "sg:province":"CA",
    "sg:tags":[
        "broker",
        "mortgage"
    ],
    "sg:website":"www.amerifi-refinance.com",
    "wof:name":"Amerifi Refinance Co",
    "wof:placetype":"venue"
},
  "geometry": {"coordinates":[-118.430459,34.052561],"type":"Point"}
}