{
  "type": "Feature",
  "properties": {
    "addr:full":"3602 Thornton Ave Fremont CA 94536",
    "addr:housenumber":"3602",
    "addr:postcode":"94536",
    "addr:street":"Thornton Ave",
    "iso:country":"US",
    "sg:address":"3602 Thornton Ave",
    "sg:city":"Fremont",
    "sg:classifiers":[
        {
            "category":"Local Transit",
            "type":"Transportation"
        }
    ],
    "sg:phone":"+1 510 790 4703",
    "sg:postcode":"94536",
    "sg:province":"CA",
    "sg:tags":[
        "limousine"
    ],
    "wof:name":"San Francisco Bay Area Limo",
    "wof:placetype":"venue"
},
  "geometry": {"coordinates":[-122.008993,37.562861],"type":"Point"}
}