{
  "type": "Feature",
  "properties": {
    "iso:country":"US",
    "sg:address":"420 Sequoia Dr",
    "sg:city":"Exeter",
    "sg:classifiers":[
        {
            "category":"Social Services",
            "subcategory":"Child Care",
            "type":"Services"
        }
    ],
    "sg:phone":"+1 559 592 1935",
    "sg:postcode":"93221",
    "sg:province":"CA",
    "wof:name":"Little Lambs Preschool",
    "wof:placetype":"venue"
},
  "geometry": {"coordinates":[-119.13836499999999,36.302458],"type":"Point"}
}