{
  "type": "Feature",
  "properties": {
    "addr:full":"17 Monticello Ln Rancho Santa Margarita CA 92688",
    "addr:housenumber":"17",
    "addr:postcode":"92688",
    "addr:street":"Monticello Ln",
    "iso:country":"US",
    "sg:address":"17 Monticello Ln",
    "sg:city":"Rancho Santa Margarita",
    "sg:classifiers":[
        {
            "category":"Shopping",
            "subcategory":"Catalog Store",
            "type":"Retail Goods"
        }
    ],
    "sg:phone":"+1 949 933 3450",
    "sg:postcode":"92688",
    "sg:province":"CA",
    "sg:tags":[
        "mail",
        "house"
    ],
    "wof:name":"Gjc & Associates",
    "wof:placetype":"venue"
},
  "geometry": {"coordinates":[-117.609584,33.621279],"type":"Point"}
}