{
  "type": "Feature",
  "properties": {
    "addr:full":"2695 S Cherry Ave Fresno CA 93706",
    "addr:housenumber":"2695",
    "addr:postcode":"93706",
    "addr:street":"S Cherry Ave",
    "iso:country":"US",
    "sg:address":"2695 S Cherry Ave",
    "sg:city":"Fresno",
    "sg:classifiers":[
        {
            "category":"Autos & Motor Vehicles",
            "subcategory":"Auto Supplies",
            "type":"Retail Goods"
        },
        {
            "category":"Retail",
            "subcategory":"Auto Repair",
            "type":"Services"
        }
    ],
    "sg:phone":"+1 559 485 7555",
    "sg:postcode":"93706",
    "sg:province":"CA",
    "sg:tags":[
        "repairing",
        "automobile",
        "general"
    ],
    "wof:name":"Cap Automotive",
    "wof:placetype":"venue"
},
  "geometry": {"coordinates":[-119.78180399999999,36.703169],"type":"Point"}
}