{
  "type": "Feature",
  "properties": {
    "iso:country":"US",
    "sg:address":"1300 17th St",
    "sg:city":"Bakersfield",
    "sg:classifiers":[
        {
            "category":"Education",
            "subcategory":"Special Training",
            "type":"Public Place"
        }
    ],
    "sg:phone":"+1 661 258 6623",
    "sg:postcode":"93301",
    "sg:province":"CA",
    "sg:tags":[
        "instruction",
        "speaking"
    ],
    "wof:name":"Branch Avenue Special Day Class",
    "wof:placetype":"venue"
},
  "geometry": {"coordinates":[-119.016418,35.374321],"type":"Point"}
}