{
  "type": "Feature",
  "properties": {
    "addr:full":"24040 Postal Ave Moreno Valley CA 92553",
    "addr:postcode":"24040;92553",
    "addr:street":"Postal Ave",
    "iso:country":"US",
    "sg:address":"24040 Postal Ave",
    "sg:city":"Moreno Valley",
    "sg:classifiers":[
        {
            "category":"Government",
            "subcategory":"Post Office",
            "type":"Public Place"
        }
    ],
    "sg:phone":"+1 951 243 9459",
    "sg:postcode":"92553",
    "sg:province":"CA",
    "wof:name":"US Post Office",
    "wof:placetype":"venue"
},
  "geometry": {"coordinates":[-117.240645,33.940451],"type":"Point"}
}