{
  "type": "Feature",
  "properties": {
    "addr:full":"25041 Cll Arenal Lake Forest CA 92630",
    "addr:postcode":"25041;92630",
    "addr:street":"Cll Arenal",
    "iso:country":"US",
    "sg:address":"25041 Cll Arenal",
    "sg:city":"Lake Forest",
    "sg:classifiers":[
        {
            "category":"Professional",
            "type":"Services"
        }
    ],
    "sg:phone":"+1 949 458 9762",
    "sg:postcode":"92630",
    "sg:province":"CA",
    "wof:name":"Sbbec",
    "wof:placetype":"venue"
},
  "geometry": {"coordinates":[-117.693856,33.654864],"type":"Point"}
}