{
  "type": "Feature",
  "properties": {
    "addr:full":"5909 Charles St El Cerrito CA 94530",
    "addr:housenumber":"5909",
    "addr:postcode":"94530",
    "addr:street":"Charles St",
    "iso:country":"US",
    "sg:address":"5909 Charles St",
    "sg:city":"El Cerrito",
    "sg:classifiers":[
        {
            "category":"Wholesale",
            "subcategory":"Groceries",
            "type":"Manufacturing & Wholesale Goods"
        }
    ],
    "sg:phone":"+1 510 237 8168",
    "sg:postcode":"94530",
    "sg:province":"CA",
    "wof:name":"Healthy Doughnut",
    "wof:placetype":"venue"
},
  "geometry": {"coordinates":[-122.314837,37.937715],"type":"Point"}
}