{
  "type": "Feature",
  "properties": {
    "addr:full":"10618 Keswick St Sun Valley CA 91352",
    "addr:housenumber":"10618",
    "addr:postcode":"91352",
    "addr:street":"Keswick St",
    "iso:country":"US",
    "sg:address":"10618 Keswick St",
    "sg:city":"Sun Valley",
    "sg:classifiers":[
        {
            "category":"Manufacturing",
            "subcategory":"Motor Vehicles & Parts",
            "type":"Manufacturing & Wholesale Goods"
        }
    ],
    "sg:phone":"+1 818 768 5880",
    "sg:postcode":"91352",
    "sg:province":"CA",
    "sg:tags":[
        "trailer",
        "hitch"
    ],
    "sg:website":"www.eaz-lift.com",
    "wof:name":"Eaz-Lift Spring Corp",
    "wof:placetype":"venue"
},
  "geometry": {"coordinates":[-118.362246,34.21041],"type":"Point"}
}