{
  "type": "Feature",
  "properties": {
    "addr:full":"1831 Lear Ct Oxnard CA 93030",
    "addr:housenumber":"1831",
    "addr:postcode":"93030",
    "addr:street":"Lear Ct",
    "iso:country":"US",
    "sg:address":"1831 Lear Ct",
    "sg:city":"Oxnard",
    "sg:classifiers":[
        {
            "category":"Building & Trades",
            "subcategory":"Plumbing",
            "type":"Services"
        }
    ],
    "sg:phone":"+1 805 984 2699",
    "sg:postcode":"93030",
    "sg:province":"CA",
    "sg:tags":[
        "conditioning",
        "air",
        "system",
        "contractor"
    ],
    "wof:name":"Commercial Temperature Co",
    "wof:placetype":"venue"
},
  "geometry": {"coordinates":[-119.19767299999999,34.210844],"type":"Point"}
}