{
  "type": "Feature",
  "properties": {
    "iso:country":"US",
    "sg:address":"1161 N Kraemer Blvd",
    "sg:city":"Anaheim",
    "sg:classifiers":[
        {
            "category":"Building & Trades",
            "subcategory":"Electrical",
            "type":"Services"
        }
    ],
    "sg:phone":"+1 714 630 1770",
    "sg:postcode":"92806",
    "sg:province":"CA",
    "sg:tags":[
        "electrician"
    ],
    "wof:name":"Breaker Depot, Inc",
    "wof:placetype":"venue"
},
  "geometry": {"coordinates":[-117.858599,33.853295],"type":"Point"}
}