{
  "type": "Feature",
  "properties": {
    "iso:country":"US",
    "sg:address":"19327 Cam del Aguila",
    "sg:city":"Escondido",
    "sg:classifiers":[
        {
            "category":"Farming",
            "subcategory":"Nursery",
            "type":"Manufacturing & Wholesale Goods"
        }
    ],
    "sg:phone":"+1 760 743 5117",
    "sg:postcode":"92025",
    "sg:province":"CA",
    "sg:tags":[
        "ornamental"
    ],
    "wof:name":"Outback Growers",
    "wof:placetype":"venue"
},
  "geometry": {"coordinates":[-116.996827,33.052104],"type":"Point"}
}