{
  "type": "Feature",
  "properties": {
    "addr:full":"814 Clovis Ave Clovis CA 93612",
    "addr:housenumber":"814",
    "addr:postcode":"93612",
    "addr:street":"Clovis Ave",
    "iso:country":"US",
    "sg:address":"814 Clovis Ave",
    "sg:city":"Clovis",
    "sg:classifiers":[
        {
            "category":"Autos & Motor Vehicles",
            "subcategory":"Fuel & Gas Station",
            "type":"Retail Goods"
        }
    ],
    "sg:phone":"+1 559 299 3218",
    "sg:postcode":"93612",
    "sg:province":"CA",
    "sg:tags":[
        "oil"
    ],
    "wof:name":"Beacon",
    "wof:placetype":"venue"
},
  "geometry": {"coordinates":[-119.70071299999999,36.819621],"type":"Point"}
}