{
  "type": "Feature",
  "properties": {
    "addr:full":"1037 Danielle Dr Roseville CA 95747",
    "addr:housenumber":"1037",
    "addr:postcode":"95747",
    "addr:street":"Danielle Dr",
    "iso:country":"US",
    "sg:address":"1037 Danielle Dr",
    "sg:city":"Roseville",
    "sg:classifiers":[
        {
            "category":"Wholesale",
            "subcategory":"Construction Materials",
            "type":"Manufacturing & Wholesale Goods"
        },
        {
            "category":"Home & Garden",
            "subcategory":"Building Materials",
            "type":"Retail Goods"
        }
    ],
    "sg:phone":"+1 916 704 4518",
    "sg:postcode":"95747",
    "sg:province":"CA",
    "sg:tags":[
        "windows-wholesale",
        "window",
        "manufacturer"
    ],
    "wof:name":"Windows Of Hope",
    "wof:placetype":"venue"
},
  "geometry": {"coordinates":[-121.325715,38.766876],"type":"Point"}
}