{
  "type": "Feature",
  "properties": {
    "addr:full":"1610 San Miguel Dr Newport Beach CA 92660",
    "addr:housenumber":"1610",
    "addr:postcode":"92660",
    "addr:street":"San Miguel Dr",
    "iso:country":"US",
    "sg:address":"1610 San Miguel Dr",
    "sg:city":"Newport Beach",
    "sg:classifiers":[
        {
            "category":"Shopping",
            "subcategory":"Pharmacy",
            "type":"Retail Goods"
        }
    ],
    "sg:phone":"+1 949 999 2980",
    "sg:postcode":"92660",
    "sg:province":"CA",
    "sg:tags":[
        "drugstore"
    ],
    "sg:website":"www.lindorahealthclinic.com",
    "wof:name":"Lindora Health Clinic",
    "wof:placetype":"venue"
},
  "geometry": {"coordinates":[-117.86497,33.611904],"type":"Point"}
}