{
  "type": "Feature",
  "properties": {
    "addr:full":"2183 Lake Ave Altadena CA 91001",
    "addr:housenumber":"2183",
    "addr:postcode":"91001",
    "addr:street":"Lake Ave",
    "iso:country":"US",
    "sg:address":"2183 Lake Ave",
    "sg:city":"Altadena",
    "sg:classifiers":[
        {
            "category":"Organizations",
            "subcategory":"Religious Organization",
            "type":"Services"
        }
    ],
    "sg:phone":"+1 626 398 8392",
    "sg:postcode":"91001",
    "sg:province":"CA",
    "wof:name":"Masjid Al-Taqwa",
    "wof:placetype":"venue"
},
  "geometry": {"coordinates":[-118.13176,34.183479],"type":"Point"}
}