{
  "type": "Feature",
  "properties": {
    "addr:full":"642 Caliente Dr Sunnyvale CA 94085",
    "addr:housenumber":"642",
    "addr:postcode":"94085",
    "addr:street":"Caliente Dr",
    "iso:country":"US",
    "sg:address":"642 Caliente Dr",
    "sg:city":"Sunnyvale",
    "sg:classifiers":[
        {
            "category":"Retail",
            "subcategory":"Auto Repair",
            "type":"Services"
        }
    ],
    "sg:phone":"+1 408 749 0651",
    "sg:postcode":"94085",
    "sg:province":"CA",
    "sg:tags":[
        "automobile",
        "installation",
        "glass"
    ],
    "wof:name":"Nationwide Auto Glass",
    "wof:placetype":"venue"
},
  "geometry": {"coordinates":[-122.01236400000001,37.390815],"type":"Point"}
}