{
  "type": "Feature",
  "properties": {
    "iso:country":"US",
    "sg:address":"1753 Addison Way",
    "sg:city":"Hayward",
    "sg:classifiers":[
        {
            "category":"Shopping",
            "type":"Retail Goods"
        }
    ],
    "sg:phone":"+1 510 732 8710",
    "sg:postcode":"94544",
    "sg:province":"CA",
    "sg:tags":[
        "vault",
        "safe",
        "key",
        "locksmith"
    ],
    "sg:website":"www.securitysafeusa.com",
    "wof:name":"Security Safe",
    "wof:placetype":"venue"
},
  "geometry": {"coordinates":[-122.067001,37.616501],"type":"Point"}
}