{
  "type": "Feature",
  "properties": {
    "addr:full":"2007 Preisker Ln Santa Maria CA 93454",
    "addr:housenumber":"2007",
    "addr:postcode":"93454",
    "addr:street":"Preisker Ln",
    "iso:country":"US",
    "sg:address":"2007 Preisker Ln",
    "sg:city":"Santa Maria",
    "sg:classifiers":[
        {
            "category":"Home & Garden",
            "subcategory":"Carpets & Floor Coverings",
            "type":"Retail Goods"
        }
    ],
    "sg:phone":"+1 805 922 6688",
    "sg:postcode":"93454",
    "sg:province":"CA",
    "wof:name":"Holiday Carpet & Floor Cover",
    "wof:placetype":"venue"
},
  "geometry": {"coordinates":[-120.431618,34.978997],"type":"Point"}
}