{
  "type": "Feature",
  "properties": {
    "iso:country":"US",
    "sg:address":"4545 Feather River Rd",
    "sg:city":"Corona",
    "sg:classifiers":[
        {
            "category":"Building & Trades",
            "subcategory":"Construction",
            "type":"Services"
        }
    ],
    "sg:phone":"+1 951 735 9422",
    "sg:postcode":"92880",
    "sg:province":"CA",
    "sg:tags":[
        "concrete",
        "cutting",
        "breaking",
        "sawing"
    ],
    "wof:name":"All Cities Concrete Sawing",
    "wof:placetype":"venue"
},
  "geometry": {"coordinates":[-117.656595,33.88131],"type":"Point"}
}