{
  "type": "Feature",
  "properties": {
    "addr:full":"153 N Highway 101 Ste 200 Solana Beach CA 92075",
    "addr:housenumber":"153",
    "addr:postcode":"92075",
    "addr:street":"N Highway 101 Ste 200",
    "iso:country":"US",
    "sg:address":"153 N Highway 101 Ste 200",
    "sg:city":"Solana Beach",
    "sg:classifiers":[
        {
            "category":"Building & Trades",
            "subcategory":"Construction",
            "type":"Services"
        }
    ],
    "sg:phone":"+1 858 792 1500",
    "sg:postcode":"92075",
    "sg:province":"CA",
    "sg:tags":[
        "contractor"
    ],
    "sg:website":"www.delmarpacific.com",
    "wof:name":"Del Mar Pacific",
    "wof:placetype":"venue"
},
  "geometry": {"coordinates":[-117.27235,32.993079],"type":"Point"}
}