{
  "type": "Feature",
  "properties": {
    "addr:full":"720 E Colorado Blvd Pasadena CA 91101",
    "addr:housenumber":"720",
    "addr:postcode":"91101",
    "addr:street":"E Colorado Blvd",
    "iso:country":"US",
    "sg:address":"720 E Colorado Blvd",
    "sg:city":"Pasadena",
    "sg:classifiers":[
        {
            "category":"Banks & Credit Unions",
            "subcategory":"Bank",
            "type":"Services"
        }
    ],
    "sg:phone":"+1 626 397 4924",
    "sg:postcode":"91101",
    "sg:province":"CA",
    "wof:name":"U.S. Bank",
    "wof:placetype":"venue"
},
  "geometry": {"coordinates":[-118.135373,34.14575],"type":"Point"}
}