{
  "type": "Feature",
  "properties": {
    "addr:full":"1920 Harbor Blvd Costa Mesa CA 92627",
    "addr:housenumber":"1920",
    "addr:postcode":"92627",
    "addr:street":"Harbor Blvd Costa",
    "iso:country":"US",
    "sg:address":"1920 Harbor Blvd",
    "sg:city":"Costa Mesa",
    "sg:classifiers":[
        {
            "category":"Shopping",
            "subcategory":"Used Merchandise",
            "type":"Retail Goods"
        }
    ],
    "sg:phone":"+1 949 646 8551",
    "sg:postcode":"92627",
    "sg:province":"CA",
    "sg:tags":[
        "record",
        "rare"
    ],
    "wof:name":"Goat Hill Records",
    "wof:placetype":"venue"
},
  "geometry": {"coordinates":[-117.91889500000001,33.643649],"type":"Point"}
}