{
  "type": "Feature",
  "properties": {
    "iso:country":"US",
    "sg:address":"689 N E St",
    "sg:city":"San Bernardino",
    "sg:classifiers":[
        {
            "category":"Recreation",
            "type":"Entertainment"
        }
    ],
    "sg:phone":"+1 909 885 4160",
    "sg:postcode":"92410",
    "sg:province":"CA",
    "sg:tags":[
        "amusement"
    ],
    "wof:name":"Orangeshow Bmx",
    "wof:placetype":"venue"
},
  "geometry": {"coordinates":[-117.29409,34.111322],"type":"Point"}
}