{
  "type": "Feature",
  "properties": {
    "addr:full":"13475 Danielson St Poway CA 92064",
    "addr:housenumber":"13475",
    "addr:postcode":"ca 92064",
    "addr:street":"Danielson St",
    "iso:country":"US",
    "sg:address":"13475 Danielson St",
    "sg:city":"Poway",
    "sg:classifiers":[
        {
            "category":"Banks & Credit Unions",
            "subcategory":"Investment Brokerage",
            "type":"Services"
        }
    ],
    "sg:phone":"+1 858 218 1660",
    "sg:postcode":"92064",
    "sg:province":"CA",
    "sg:tags":[
        "advisory",
        "financial"
    ],
    "wof:name":"Marcap Vendor Finance Corp",
    "wof:placetype":"venue"
},
  "geometry": {"coordinates":[-117.039438,32.939707],"type":"Point"}
}