{
  "type": "Feature",
  "properties": {
    "addr:full":"10542 Walker St Cypress CA 90630",
    "addr:housenumber":"10542",
    "addr:postcode":"90630",
    "addr:street":"Walker St",
    "iso:country":"US",
    "sg:address":"10542 Walker St",
    "sg:city":"Cypress",
    "sg:classifiers":[
        {
            "category":"Retail",
            "subcategory":"Veterinary Services",
            "type":"Services"
        }
    ],
    "sg:phone":"+1 714 952 1134",
    "sg:postcode":"90630",
    "sg:province":"CA",
    "sg:tags":[
        "veterinarian"
    ],
    "wof:name":"Equine Medical Center",
    "wof:placetype":"venue"
},
  "geometry": {"coordinates":[-118.037003,33.809799],"type":"Point"}
}