{
  "type": "Feature",
  "properties": {
    "addr:full":"818 N Avalon Blvd Wilmington CA 90744",
    "addr:housenumber":"818",
    "addr:postcode":"90744",
    "addr:street":"N Avalon Blvd",
    "iso:country":"US",
    "sg:address":"818 N Avalon Blvd",
    "sg:city":"Wilmington",
    "sg:classifiers":[
        {
            "category":"Manufacturing",
            "subcategory":"Printing",
            "type":"Manufacturing & Wholesale Goods"
        }
    ],
    "sg:phone":"+1 310 518 2727",
    "sg:postcode":"90744",
    "sg:province":"CA",
    "sg:tags":[
        "commercial"
    ],
    "wof:name":"Marine Printing Inc",
    "wof:placetype":"venue"
},
  "geometry": {"coordinates":[-118.26243599999999,33.780993],"type":"Point"}
}