{
  "type": "Feature",
  "properties": {
    "iso:country":"US",
    "sg:address":"9048 Garvey Ave",
    "sg:city":"Rosemead",
    "sg:classifiers":[
        {
            "category":"Manufacturing",
            "subcategory":"Metals",
            "type":"Manufacturing & Wholesale Goods"
        }
    ],
    "sg:phone":"+1 626 782 0209",
    "sg:postcode":"91770",
    "sg:province":"CA",
    "sg:tags":[
        "fabricator",
        "sheet"
    ],
    "wof:name":"J P Metal Products",
    "wof:placetype":"venue"
},
  "geometry": {"coordinates":[-118.071558,34.062617],"type":"Point"}
}