{
  "type": "Feature",
  "properties": {
    "iso:country":"US",
    "sg:address":"16086 Darcie Ln",
    "sg:city":"Salinas",
    "sg:classifiers":[
        {
            "category":"Shopping",
            "type":"Retail Goods"
        }
    ],
    "sg:phone":"+1 831 455 0194",
    "sg:postcode":"93908",
    "sg:province":"CA",
    "sg:tags":[
        "cosmetic",
        "perfume"
    ],
    "wof:name":"Mary Kay Cosmetics",
    "wof:placetype":"venue"
},
  "geometry": {"coordinates":[-121.689758,36.614515],"type":"Point"}
}