{
  "type": "Feature",
  "properties": {
    "addr:full":"3209 W Shaw Ave Fresno CA 93711",
    "addr:housenumber":"3209",
    "addr:postcode":"93711",
    "addr:street":"W Shaw Ave",
    "iso:country":"US",
    "sg:address":"3209 W Shaw Ave",
    "sg:city":"Fresno",
    "sg:classifiers":[
        {
            "category":"Restaurant",
            "type":"Food & Drink"
        }
    ],
    "sg:phone":"+1 559 225 1254",
    "sg:postcode":"93711",
    "sg:province":"CA",
    "wof:name":"Tajamal",
    "wof:placetype":"venue"
},
  "geometry": {"coordinates":[-119.849689,36.808203],"type":"Point"}
}