{
  "type": "Feature",
  "properties": {
    "iso:country":"US",
    "sg:address":"10339 Garvey Ave",
    "sg:city":"South El Monte",
    "sg:classifiers":[
        {
            "category":"Travel",
            "subcategory":"Travel Agent",
            "type":"Entertainment"
        }
    ],
    "sg:phone":"+1 626 401 9499",
    "sg:postcode":"91733",
    "sg:province":"CA",
    "sg:tags":[
        "agency"
    ],
    "wof:name":"EZ Travel Inc",
    "wof:placetype":"venue"
},
  "geometry": {"coordinates":[-118.04683,34.062789],"type":"Point"}
}