{
  "type": "Feature",
  "properties": {
    "iso:country":"US",
    "sg:address":"44530 Sierra Hwy",
    "sg:city":"Lancaster",
    "sg:classifiers":[
        {
            "category":"Shopping",
            "subcategory":"Discount & Variety Stores",
            "type":"Retail Goods"
        }
    ],
    "sg:phone":"+1 661 940 3588",
    "sg:postcode":"93534",
    "sg:province":"CA",
    "sg:tags":[
        "car",
        "used",
        "merchandise"
    ],
    "wof:name":"Camacho Auto Sales Inc",
    "wof:placetype":"venue"
},
  "geometry": {"coordinates":[-118.135887,34.691568],"type":"Point"}
}