{
  "type": "Feature",
  "properties": {
    "addr:full":"15091 W Whitesbridge Ave Kerman CA 93630",
    "addr:housenumber":"15091",
    "addr:postcode":"93630",
    "addr:street":"W Whitesbridge Ave",
    "iso:country":"US",
    "sg:address":"15091 W Whitesbridge Ave",
    "sg:city":"Kerman",
    "sg:classifiers":[
        {
            "category":"Food & Beverages",
            "subcategory":"Liquor & Beverages",
            "type":"Retail Goods"
        }
    ],
    "sg:phone":"+1 559 846 9511",
    "sg:postcode":"93630",
    "sg:province":"CA",
    "wof:name":"Kerman-U-Save Liquors",
    "wof:placetype":"venue"
},
  "geometry": {"coordinates":[-120.061206,36.73485],"type":"Point"}
}