{
  "type": "Feature",
  "properties": {
    "addr:full":"3226 Franklin Ave Riverside CA 92507",
    "addr:housenumber":"3226",
    "addr:postcode":"92507",
    "addr:street":"Franklin Ave",
    "iso:country":"US",
    "sg:address":"3226 Franklin Ave",
    "sg:city":"Riverside",
    "sg:classifiers":[
        {
            "category":"Manufacturing",
            "subcategory":"Apparel",
            "type":"Manufacturing & Wholesale Goods"
        }
    ],
    "sg:phone":"+1 951 683 1925",
    "sg:postcode":"92507",
    "sg:province":"CA",
    "sg:tags":[
        "canvas",
        "product",
        "related"
    ],
    "sg:website":"www.riversidetentandawning.com",
    "wof:name":"Riverside Tent & Awning Inc",
    "wof:placetype":"venue"
},
  "geometry": {"coordinates":[-117.357591,33.985612],"type":"Point"}
}