{
  "type": "Feature",
  "properties": {
    "addr:full":"879 Colorado Ave Chula Vista CA 91911",
    "addr:housenumber":"879",
    "addr:postcode":"91911",
    "addr:street":"Colorado Ave",
    "iso:country":"US",
    "sg:address":"879 Colorado Ave",
    "sg:city":"Chula Vista",
    "sg:classifiers":[
        {
            "category":"Real Estate",
            "subcategory":"Real Estate Operator",
            "type":"Services"
        }
    ],
    "sg:phone":"+1 619 422 3788",
    "sg:postcode":"91911",
    "sg:province":"CA",
    "sg:tags":[
        "apartment"
    ],
    "wof:name":"Sierra Park Apartments",
    "wof:placetype":"venue"
},
  "geometry": {"coordinates":[-117.089583,32.616741],"type":"Point"}
}