{
  "type": "Feature",
  "properties": {
    "iso:country":"US",
    "sg:address":"2250 W Whittier Blvd Ste 100",
    "sg:city":"La Habra",
    "sg:classifiers":[
        {
            "category":"Health Services",
            "subcategory":"Doctor",
            "type":"Services"
        }
    ],
    "sg:phone":"+1 562 690 4075",
    "sg:postcode":"90631",
    "sg:province":"CA",
    "wof:name":"Dewan Chanchal MD",
    "wof:placetype":"venue"
},
  "geometry": {"coordinates":[-117.970691,33.939722],"type":"Point"}
}