{
  "type": "Feature",
  "properties": {
    "addr:full":"453 N Canon Dr Beverly Hills CA 90210",
    "addr:housenumber":"453",
    "addr:postcode":"90210",
    "addr:street":"N Canon Dr",
    "iso:country":"US",
    "sg:address":"453 N Canon Dr",
    "sg:city":"Beverly Hills",
    "sg:classifiers":[
        {
            "category":"Restaurant",
            "type":"Food & Drink"
        }
    ],
    "sg:menulink":"http://www.allmenus.com/ca/los-angeles/22607-nics/menu/",
    "sg:phone":"+1 310 550 5707",
    "sg:postcode":"90210",
    "sg:province":"CA",
    "sg:tags":[
        "american"
    ],
    "wof:name":"Nic's",
    "wof:placetype":"venue"
},
  "geometry": {"coordinates":[-118.401858,34.071581],"type":"Point"}
}