{
  "type": "Feature",
  "properties": {
    "addr:full":"8402 N Magnolia Ave Ste H Santee CA 92071",
    "addr:housenumber":"8402",
    "addr:postcode":"92071",
    "addr:street":"N Magnolia Ave Ste H",
    "iso:country":"US",
    "sg:address":"8402 N Magnolia Ave Ste H",
    "sg:city":"Santee",
    "sg:classifiers":[
        {
            "category":"Wholesale",
            "subcategory":"Computers",
            "type":"Manufacturing & Wholesale Goods"
        }
    ],
    "sg:phone":"+1 619 258 7908",
    "sg:postcode":"92071",
    "sg:province":"CA",
    "wof:name":"Access Computer Media",
    "wof:placetype":"venue"
},
  "geometry": {"coordinates":[-116.96199799999999,32.828701],"type":"Point"}
}