{
  "type": "Feature",
  "properties": {
    "iso:country":"US",
    "sg:address":"2500 Noriega St",
    "sg:city":"San Francisco",
    "sg:classifiers":[
        {
            "category":"Restaurant",
            "type":"Food & Drink"
        }
    ],
    "sg:menulink":"http://www.allmenus.com/ca/san-francisco/44563-abc-bakery--restaurant/menu/",
    "sg:phone":"+1 415 681 8800",
    "sg:postcode":"94122",
    "sg:province":"CA",
    "sg:tags":[
        "asian",
        "chinese"
    ],
    "wof:name":"ABC Bakery & Restaurant",
    "wof:placetype":"venue"
},
  "geometry": {"coordinates":[-122.49057500000001,37.753695],"type":"Point"}
}