{
  "type": "Feature",
  "properties": {
    "iso:country":"US",
    "sg:address":"753 Jefferson St",
    "sg:city":"Napa",
    "sg:classifiers":[
        {
            "category":"Freight",
            "type":"Transportation"
        }
    ],
    "sg:phone":"+1 707 265 7702",
    "sg:postcode":"94559",
    "sg:province":"CA",
    "sg:tags":[
        "operator",
        "local",
        "trucking"
    ],
    "wof:name":"Krider Dispatch",
    "wof:placetype":"venue"
},
  "geometry": {"coordinates":[-122.293776,38.295281],"type":"Point"}
}