{
  "type": "Feature",
  "properties": {
    "addr:full":"134 N Cypress St Woodlake CA 93286",
    "addr:housenumber":"134",
    "addr:postcode":"93286",
    "addr:street":"N Cypress St",
    "iso:country":"US",
    "sg:address":"134 N Cypress St",
    "sg:city":"Woodlake",
    "sg:classifiers":[
        {
            "category":"Retail",
            "subcategory":"Funeral Services",
            "type":"Services"
        }
    ],
    "sg:phone":"+1 559 732 8371",
    "sg:postcode":"93286",
    "sg:province":"CA",
    "sg:tags":[
        "director"
    ],
    "wof:name":"Miller Memorial Chapels",
    "wof:placetype":"venue"
},
  "geometry": {"coordinates":[-119.105547,36.414183],"type":"Point"}
}