{
  "type": "Feature",
  "properties": {
    "addr:full":"3880 Broad St San Luis Obispo CA 93401",
    "addr:housenumber":"3880",
    "addr:postcode":"93401",
    "addr:street":"Broad St",
    "iso:country":"US",
    "sg:address":"3880 Broad St",
    "sg:city":"San Luis Obispo",
    "sg:classifiers":[
        {
            "category":"Shopping",
            "subcategory":"Hobbies, Toys, & Games",
            "type":"Retail Goods"
        }
    ],
    "sg:phone":"+1 805 544 0264",
    "sg:postcode":"93401",
    "sg:province":"CA",
    "sg:tags":[
        "craft",
        "supply"
    ],
    "wof:name":"Michaels Arts & Crafts Store",
    "wof:placetype":"venue"
},
  "geometry": {"coordinates":[-120.64402699999999,35.249992],"type":"Point"}
}