{
  "type": "Feature",
  "properties": {
    "addr:full":"5430 Sierra Vista Ave Riverside CA 92505",
    "addr:housenumber":"5430",
    "addr:postcode":"92505",
    "addr:street":"Sierra Vista Ave",
    "iso:country":"US",
    "sg:address":"5430 Sierra Vista Ave",
    "sg:city":"Riverside",
    "sg:classifiers":[
        {
            "category":"Professional",
            "subcategory":"Art Services",
            "type":"Services"
        }
    ],
    "sg:phone":"+1 951 688 1441",
    "sg:postcode":"92505",
    "sg:province":"CA",
    "sg:tags":[
        "commercial",
        "design",
        "merchandise"
    ],
    "wof:name":"Jones Construction & Design",
    "wof:placetype":"venue"
},
  "geometry": {"coordinates":[-117.505539,33.926063],"type":"Point"}
}