{
  "type": "Feature",
  "properties": {
    "iso:country":"US",
    "sg:address":"5750 Grant Avenue",
    "sg:city":"Carmichael",
    "sg:classifiers":[
        {
            "category":"Sports & Exercise",
            "subcategory":"Swimming Pool",
            "type":"Entertainment"
        }
    ],
    "sg:phone":"+1 916 481 6130",
    "sg:postcode":"95608",
    "sg:province":"CA",
    "sg:website":"www.carmichaelpark.com",
    "wof:name":"Carmichael Recreation & Park District",
    "wof:placetype":"venue"
},
  "geometry": {"coordinates":[-121.330911,38.629758],"type":"Point"}
}