{
  "type": "Feature",
  "properties": {
    "addr:full":"2220 Ingalls St San Francisco CA 94124",
    "addr:housenumber":"2220",
    "addr:postcode":"94124",
    "addr:street":"Ingalls St",
    "iso:country":"US",
    "sg:address":"2220 Ingalls St",
    "sg:city":"San Francisco",
    "sg:classifiers":[
        {
            "category":"Building & Trades",
            "subcategory":"Construction",
            "type":"Services"
        }
    ],
    "sg:phone":"+1 415 822 5655",
    "sg:postcode":"94124",
    "sg:province":"CA",
    "sg:tags":[
        "skylight"
    ],
    "sg:website":"www.rollamatic.com",
    "wof:name":"Rollamatic Roofs Inc",
    "wof:placetype":"venue"
},
  "geometry": {"coordinates":[-122.3879,37.7249],"type":"Point"}
}