{
  "type": "Feature",
  "properties": {
    "addr:full":"1129 W Walnut St Stockton CA 95203",
    "addr:housenumber":"1129",
    "addr:postcode":"95203",
    "addr:street":"W Walnut St",
    "iso:country":"US",
    "sg:address":"1129 W Walnut St",
    "sg:city":"Stockton",
    "sg:classifiers":[
        {
            "category":"Shopping",
            "subcategory":"Books",
            "type":"Retail Goods"
        }
    ],
    "sg:phone":"+1 209 466 0194",
    "sg:postcode":"95203",
    "sg:province":"CA",
    "wof:name":"Maxwells Bookmark",
    "wof:placetype":"venue"
},
  "geometry": {"coordinates":[-121.311908,37.965977],"type":"Point"}
}