{
  "type": "Feature",
  "properties": {
    "iso:country":"US",
    "sg:address":"3053 Rancho Vista Blvd",
    "sg:city":"Palmdale",
    "sg:classifiers":[
        {
            "category":"Shopping",
            "subcategory":"Computers & Home Electronics",
            "type":"Retail Goods"
        }
    ],
    "sg:phone":"+1 661 266 3111",
    "sg:postcode":"93551",
    "sg:province":"CA",
    "sg:tags":[
        "equipment",
        "dealer"
    ],
    "wof:name":"PMR",
    "wof:placetype":"venue"
},
  "geometry": {"coordinates":[-118.18925,34.604709],"type":"Point"}
}