{
  "type": "Feature",
  "properties": {
    "iso:country":"US",
    "sg:address":"Buchanan St & Page St",
    "sg:city":"San Francisco",
    "sg:classifiers":[
        {
            "category":"Park",
            "type":"Public Place"
        },
        {
            "category":"Recreation",
            "subcategory":"Playground",
            "type":"Entertainment"
        }
    ],
    "sg:postcode":"94199",
    "sg:province":"CA",
    "wof:name":"Koshland Park",
    "wof:placetype":"venue"
},
  "geometry": {"coordinates":[-122.42739,37.773513],"type":"Point"}
}