{
  "type": "Feature",
  "properties": {
    "addr:full":"6332 Whittier Blvd Los Angeles CA 90022",
    "addr:housenumber":"6332",
    "addr:postcode":"90022",
    "addr:street":"Whittier Blvd",
    "iso:country":"US",
    "sg:address":"6332 Whittier Blvd",
    "sg:city":"Los Angeles",
    "sg:classifiers":[
        {
            "category":"Real Estate",
            "subcategory":"Real Estate Agent",
            "type":"Services"
        }
    ],
    "sg:phone":"+1 323 722 6900",
    "sg:postcode":"90022",
    "sg:province":"CA",
    "wof:name":"Sanchez Realty Invstmnt & Lns",
    "wof:placetype":"venue"
},
  "geometry": {"coordinates":[-118.134792,34.015593],"type":"Point"}
}