{
  "type": "Feature",
  "properties": {
    "iso:country":"US",
    "sg:address":"9691 Bixby Ave",
    "sg:city":"Garden Grove",
    "sg:classifiers":[
        {
            "category":"Education",
            "subcategory":"Preschool",
            "type":"Public Place"
        },
        {
            "category":"Education",
            "subcategory":"School",
            "type":"Public Place"
        }
    ],
    "sg:phone":"+1 714 539 0522",
    "sg:postcode":"92841",
    "sg:province":"CA",
    "sg:tags":[
        "elementary"
    ],
    "wof:name":"Precious Years Christian Acadamy",
    "wof:placetype":"venue"
},
  "geometry": {"coordinates":[-117.964996,33.785],"type":"Point"}
}