{
  "type": "Feature",
  "properties": {
    "addr:full":"7155 Gail Way Fair Oaks CA 95628",
    "addr:housenumber":"7155",
    "addr:postcode":"95628",
    "addr:street":"Gail Way",
    "iso:country":"US",
    "sg:address":"7155 Gail Way",
    "sg:city":"Fair Oaks",
    "sg:classifiers":[
        {
            "category":"Shopping",
            "subcategory":"Clothing, Apparel, & Fashions",
            "type":"Retail Goods"
        }
    ],
    "sg:phone":"+1 916 961 6232",
    "sg:postcode":"95628",
    "sg:province":"CA",
    "sg:tags":[
        "accessory"
    ],
    "wof:name":"Kahlila Accessories",
    "wof:placetype":"venue"
},
  "geometry": {"coordinates":[-121.297912,38.659939],"type":"Point"}
}