{
  "type": "Feature",
  "properties": {
    "iso:country":"US",
    "sg:address":"251 S Lake Ave Ste 520",
    "sg:city":"Pasadena",
    "sg:classifiers":[
        {
            "category":"Professional",
            "subcategory":"Lawyer & Legal Services",
            "type":"Services"
        }
    ],
    "sg:phone":"+1 626 449 2300",
    "sg:postcode":"91101",
    "sg:province":"CA",
    "sg:website":"www.gutierrez-preciado.com",
    "wof:name":"Gutierrez Preciado & House Llp",
    "wof:placetype":"venue"
},
  "geometry": {"coordinates":[-118.13200399999999,34.141399],"type":"Point"}
}