{
  "type": "Feature",
  "properties": {
    "addr:full":"444 High St 4th Floor Palo Alto CA 94301",
    "addr:housenumber":"444;4th",
    "addr:postcode":"94301",
    "addr:street":"High St;Floor",
    "iso:country":"US",
    "sg:address":"444 High St 4th Floor",
    "sg:city":"Palo Alto",
    "sg:classifiers":[
        {
            "category":"Professional",
            "subcategory":"Advertising",
            "type":"Services"
        }
    ],
    "sg:phone":"+1 408 480 0998",
    "sg:postcode":"94301",
    "sg:province":"CA",
    "sg:tags":[
        "pubmatic",
        "advertisement"
    ],
    "sg:website":"http://www.pubmatic.com",
    "wof:name":"PubMatic",
    "wof:placetype":"venue"
},
  "geometry": {"coordinates":[-122.163928,37.444371],"type":"Point"}
}