{
  "type": "Feature",
  "properties": {
    "iso:country":"US",
    "sg:address":"1429 College Ave",
    "sg:city":"Modesto",
    "sg:classifiers":[
        {
            "category":"Professional",
            "subcategory":"Research",
            "type":"Services"
        }
    ],
    "sg:phone":"+1 209 575 9807",
    "sg:postcode":"95350",
    "sg:province":"CA",
    "sg:tags":[
        "laboratory"
    ],
    "wof:name":"Unilab Corp",
    "wof:placetype":"venue"
},
  "geometry": {"coordinates":[-121.007711,37.66523],"type":"Point"}
}