{
  "type": "Feature",
  "properties": {
    "iso:country":"US",
    "sg:address":"3116 Lake Dr",
    "sg:city":"Marina",
    "sg:classifiers":[
        {
            "category":"Real Estate",
            "subcategory":"Real Estate Operator",
            "type":"Services"
        }
    ],
    "sg:phone":"+1 831 883 4242",
    "sg:postcode":"93933",
    "sg:province":"CA",
    "sg:tags":[
        "apartment"
    ],
    "wof:name":"Lake View Terrace Apartments",
    "wof:placetype":"venue"
},
  "geometry": {"coordinates":[-121.803096,36.688751],"type":"Point"}
}