{
  "type": "Feature",
  "properties": {
    "addr:full":"3345 Newport Blvd Newport Beach CA 92663",
    "addr:housenumber":"3345",
    "addr:postcode":"92663",
    "addr:street":"Newport Blvd",
    "iso:country":"US",
    "sg:address":"3345 Newport Blvd",
    "sg:city":"Newport Beach",
    "sg:classifiers":[
        {
            "category":"Professional",
            "subcategory":"Accounting & Tax Preparation",
            "type":"Services"
        }
    ],
    "sg:phone":"+1 949 675 3022",
    "sg:postcode":"92663",
    "sg:province":"CA",
    "sg:tags":[
        "accountant"
    ],
    "wof:name":"Dibella Frank Accountancy Corp",
    "wof:placetype":"venue"
},
  "geometry": {"coordinates":[-117.93000000000001,33.616901],"type":"Point"}
}