{
  "type": "Feature",
  "properties": {
    "addr:full":"24019 Hilderbrand Dr Middletown CA 95461",
    "addr:housenumber":"24019",
    "addr:postcode":"95461",
    "addr:street":"Hilderbrand Dr",
    "iso:country":"US",
    "sg:address":"24019 Hilderbrand Dr",
    "sg:city":"Middletown",
    "sg:classifiers":[
        {
            "category":"Travel",
            "subcategory":"Hotels & Motels",
            "type":"Entertainment"
        }
    ],
    "sg:phone":"+1 707 987 0505",
    "sg:postcode":"95461",
    "sg:province":"CA",
    "sg:tags":[
        "breakfast",
        "accommodation",
        "bed"
    ],
    "sg:website":"www.backyardgardenoasis.com",
    "wof:name":"Backyard Garden Oasis AB & B",
    "wof:placetype":"venue"
},
  "geometry": {"coordinates":[-122.602997,38.705717],"type":"Point"}
}