{
  "type": "Feature",
  "properties": {
    "iso:country":"US",
    "sg:address":"7650 Girard Ave",
    "sg:city":"La Jolla",
    "sg:classifiers":[
        {
            "category":"Shopping",
            "subcategory":"Beauty & Cosmetics",
            "type":"Retail Goods"
        },
        {
            "category":"Shopping",
            "subcategory":"Pharmacy",
            "type":"Retail Goods"
        },
        {
            "category":"Community Center",
            "type":"Public Place"
        }
    ],
    "sg:phone":"+1 858 454 1337",
    "sg:postcode":"92037",
    "sg:province":"CA",
    "sg:tags":[
        "medical",
        "drugstore",
        "supply"
    ],
    "sg:website":"www.pharmaca.com/index.html",
    "wof:name":"Pharmaca Integrative Pharmacy",
    "wof:placetype":"venue"
},
  "geometry": {"coordinates":[-117.273245,32.842834],"type":"Point"}
}