{
  "type": "Feature",
  "properties": {
    "addr:full":"39164 State St Fremont CA 94538",
    "addr:housenumber":"39164",
    "addr:postcode":"94538",
    "addr:street":"State St",
    "iso:country":"US",
    "sg:address":"39164 State St",
    "sg:city":"Fremont",
    "sg:classifiers":[
        {
            "category":"Restaurant",
            "type":"Food & Drink"
        }
    ],
    "sg:menulink":"http://www.allmenus.com/ca/fremont/137797-super-suppers/menu/",
    "sg:phone":"+1 510 745 8270",
    "sg:postcode":"94538",
    "sg:province":"CA",
    "sg:tags":[
        "american"
    ],
    "wof:name":"Super Suppers",
    "wof:placetype":"venue"
},
  "geometry": {"coordinates":[-121.983912,37.549666],"type":"Point"}
}