{
  "type": "Feature",
  "properties": {
    "iso:country":"US",
    "sg:address":"14540 Sontag Rd",
    "sg:city":"Grass Valley",
    "sg:classifiers":[
        {
            "category":"Personal",
            "subcategory":"Beauty Salon",
            "type":"Services"
        }
    ],
    "sg:phone":"+1 530 272 0247",
    "sg:postcode":"95945",
    "sg:province":"CA",
    "wof:name":"Do Or Die Hair Studio",
    "wof:placetype":"venue"
},
  "geometry": {"coordinates":[-120.956538,39.177649],"type":"Point"}
}