{
  "type": "Feature",
  "properties": {
    "addr:full":"7241 Atoll Ave North Hollywood CA 91605",
    "addr:housenumber":"7241",
    "addr:postcode":"91605",
    "addr:street":"Atoll Ave",
    "iso:country":"US",
    "sg:address":"7241 Atoll Ave",
    "sg:city":"North Hollywood",
    "sg:classifiers":[
        {
            "category":"Professional",
            "type":"Services"
        }
    ],
    "sg:phone":"+1 818 784 3790",
    "sg:postcode":"91605",
    "sg:province":"CA",
    "sg:tags":[
        "establishment"
    ],
    "wof:name":"Cn Custom Inc",
    "wof:placetype":"venue"
},
  "geometry": {"coordinates":[-118.42112400000001,34.203137],"type":"Point"}
}