{
  "type": "Feature",
  "properties": {
    "iso:country":"US",
    "sg:address":"3434 W 6th St",
    "sg:city":"Los Angeles",
    "sg:classifiers":[
        {
            "category":"Health Services",
            "subcategory":"Health Practitioner",
            "type":"Services"
        }
    ],
    "sg:phone":"+1 213 381 1010",
    "sg:postcode":"90020",
    "sg:province":"CA",
    "sg:tags":[
        "acupuncture"
    ],
    "wof:name":"Acupuncture Aum's Clinic",
    "wof:placetype":"venue"
},
  "geometry": {"coordinates":[-118.295998,34.063599],"type":"Point"}
}