{
  "type": "Feature",
  "properties": {
    "iso:country":"US",
    "sg:address":"2546 Capitola Rd",
    "sg:city":"Santa Cruz",
    "sg:classifiers":[
        {
            "category":"Real Estate",
            "subcategory":"Real Estate Operator",
            "type":"Services"
        }
    ],
    "sg:phone":"+1 831 475 0559",
    "sg:postcode":"95062",
    "sg:province":"CA",
    "sg:tags":[
        "mobile",
        "home",
        "community"
    ],
    "wof:name":"Pine Knoll Mobile Manor",
    "wof:placetype":"venue"
},
  "geometry": {"coordinates":[-121.975401,36.974552],"type":"Point"}
}