{
  "type": "Feature",
  "properties": {
    "addr:full":"1829 Fir St Corona CA 92882",
    "addr:housenumber":"1829",
    "addr:postcode":"92882",
    "addr:street":"Fir St",
    "iso:country":"US",
    "sg:address":"1829 Fir St",
    "sg:city":"Corona",
    "sg:classifiers":[
        {
            "category":"Building & Trades",
            "subcategory":"Construction",
            "type":"Services"
        }
    ],
    "sg:phone":"+1 951 734 9629",
    "sg:postcode":"92882",
    "sg:province":"CA",
    "sg:tags":[
        "restoration",
        "cleaning",
        "patio",
        "deck"
    ],
    "wof:name":"Pressure Works",
    "wof:placetype":"venue"
},
  "geometry": {"coordinates":[-117.595986,33.863686],"type":"Point"}
}