{
  "type": "Feature",
  "properties": {
    "iso:country":"US",
    "sg:address":"15125 Garfield Ave",
    "sg:city":"Paramount",
    "sg:classifiers":[
        {
            "category":"Professional",
            "type":"Services"
        }
    ],
    "sg:phone":"+1 562 531 4000",
    "sg:postcode":"90723",
    "sg:province":"CA",
    "wof:name":"Fulytor Inc",
    "wof:placetype":"venue"
},
  "geometry": {"coordinates":[-118.168865,33.89505],"type":"Point"}
}