{
  "type": "Feature",
  "properties": {
    "addr:full":"17009 Chatsworth St Granada Hills CA 91344",
    "addr:housenumber":"17009",
    "addr:postcode":"91344",
    "addr:street":"Chatsworth St",
    "iso:country":"US",
    "sg:address":"17009 Chatsworth St",
    "sg:city":"Granada Hills",
    "sg:classifiers":[
        {
            "category":"Shopping",
            "subcategory":"Florist",
            "type":"Retail Goods"
        }
    ],
    "sg:phone":"+1 818 366 6561",
    "sg:postcode":"91344",
    "sg:province":"CA",
    "wof:name":"Flower Lane",
    "wof:placetype":"venue"
},
  "geometry": {"coordinates":[-118.50420200000001,34.26486],"type":"Point"}
}