{
  "type": "Feature",
  "properties": {
    "iso:country":"US",
    "sg:address":"201 Marla Dr",
    "sg:city":"American Canyon",
    "sg:classifiers":[
        {
            "category":"Real Estate",
            "subcategory":"Real Estate Agent",
            "type":"Services"
        }
    ],
    "sg:phone":"+1 707 552 5568",
    "sg:postcode":"94503",
    "sg:province":"CA",
    "sg:tags":[
        "management"
    ],
    "wof:name":"Thomas Antonio",
    "wof:placetype":"venue"
},
  "geometry": {"coordinates":[-122.25788,38.155696],"type":"Point"}
}