{
  "type": "Feature",
  "properties": {
    "iso:country":"US",
    "sg:address":"371 Linfield Dr",
    "sg:city":"Menlo Park",
    "sg:classifiers":[
        {
            "category":"Travel",
            "subcategory":"Travel Agent",
            "type":"Entertainment"
        }
    ],
    "sg:phone":"+1 650 322 2426",
    "sg:postcode":"94025",
    "sg:province":"CA",
    "sg:tags":[
        "agency"
    ],
    "wof:name":"Lilly Calla Productions",
    "wof:placetype":"venue"
},
  "geometry": {"coordinates":[-122.17073600000001,37.452075],"type":"Point"}
}