{
  "type": "Feature",
  "properties": {
    "addr:full":"234 N Main St Bishop CA 93514",
    "addr:housenumber":"234",
    "addr:postcode":"93514",
    "addr:street":"N Main St",
    "iso:country":"US",
    "sg:address":"234 N Main St",
    "sg:city":"Bishop",
    "sg:classifiers":[
        {
            "category":"Personal",
            "subcategory":"Barber",
            "type":"Services"
        }
    ],
    "sg:phone":"+1 760 873 7350",
    "sg:postcode":"93514",
    "sg:province":"CA",
    "wof:name":"Main Barbershop",
    "wof:placetype":"venue"
},
  "geometry": {"coordinates":[-118.395219,37.362593],"type":"Point"}
}