{
  "type": "Feature",
  "properties": {
    "addr:full":"471 Parker Pl Blythe CA 92225",
    "addr:housenumber":"471",
    "addr:postcode":"92225",
    "addr:street":"Parker Pl",
    "iso:country":"US",
    "sg:address":"471 Parker Pl",
    "sg:city":"Blythe",
    "sg:classifiers":[
        {
            "category":"Real Estate",
            "subcategory":"Real Estate Services",
            "type":"Services"
        },
        {
            "category":"Real Estate",
            "subcategory":"Real Estate Agent",
            "type":"Services"
        }
    ],
    "sg:phone":"+1 760 922 5958",
    "sg:postcode":"92225",
    "sg:province":"CA",
    "sg:tags":[
        "management"
    ],
    "wof:name":"Century 21 Osborne Realty",
    "wof:placetype":"venue"
},
  "geometry": {"coordinates":[-114.602255,33.6233],"type":"Point"}
}