{
  "type": "Feature",
  "properties": {
    "iso:country":"US",
    "sg:address":"546 Cleveland Avenue",
    "sg:city":"Richmond",
    "sg:classifiers":[
        {
            "category":"Retail",
            "subcategory":"Auto Repair",
            "type":"Services"
        }
    ],
    "sg:phone":"+1 510 528 3196",
    "sg:postcode":"94710",
    "sg:province":"CA",
    "wof:name":"Auto Europa",
    "wof:placetype":"venue"
},
  "geometry": {"coordinates":[-122.30873099999999,37.895635],"type":"Point"}
}