{
  "type": "Feature",
  "properties": {
    "acgov:api":"0.0",
    "acgov:type":"K-3",
    "addr:full":"4700 Lincoln Avenue Oakland CA",
    "wof:categories":[
        "education_and_religion:education=school"
    ],
    "wof:name":"Growing Light Montessori",
    "wof:placetype":"venue"
},
  "geometry": {"coordinates":[-122.20077413227403,37.8103065275428],"type":"Point"}
}