{
  "type": "Feature",
  "properties": {
    "addr:full":"865 Napoli Dr Pacific Plsds CA 90272",
    "addr:housenumber":"865",
    "addr:postcode":"90272",
    "addr:street":"Napoli Dr",
    "iso:country":"US",
    "sg:address":"865 Napoli Dr",
    "sg:city":"Pacific Plsds",
    "sg:classifiers":[
        {
            "category":"Health Services",
            "subcategory":"Doctor",
            "type":"Services"
        }
    ],
    "sg:phone":"+1 310 454 6226",
    "sg:postcode":"90272",
    "sg:province":"CA",
    "sg:tags":[
        "physician",
        "surgeon"
    ],
    "wof:name":"Portner Medical Corp",
    "wof:placetype":"venue"
},
  "geometry": {"coordinates":[-118.50835600000001,34.043581],"type":"Point"}
}