{
  "type": "Feature",
  "properties": {
    "addr:full":"1030 Colorado Blvd Los Angeles CA 90041",
    "addr:housenumber":"1030",
    "addr:postcode":"90041",
    "addr:street":"Colorado Blvd",
    "iso:country":"US",
    "sg:address":"1030 Colorado Blvd",
    "sg:city":"Los Angeles",
    "sg:classifiers":[
        {
            "category":"Professional",
            "type":"Services"
        }
    ],
    "sg:phone":"+1 310 980 4881",
    "sg:postcode":"90041",
    "sg:province":"CA",
    "wof:name":"Italspain Corporation",
    "wof:placetype":"venue"
},
  "geometry": {"coordinates":[-118.188278,34.137773],"type":"Point"}
}