{
  "type": "Feature",
  "properties": {
    "iso:country":"US",
    "sg:address":"1111 Myrtle Ave Ste 5",
    "sg:city":"Eureka",
    "sg:phone":"+1 707 443 5525",
    "sg:postcode":"95501",
    "sg:province":"CA",
    "sg:website":"http://www.dollartree.com/",
    "wof:name":"Dollar Tree",
    "wof:placetype":"venue"
},
  "geometry": {"coordinates":[-124.147953,40.799418],"type":"Point"}
}