{
  "type": "Feature",
  "properties": {
    "iso:country":"US",
    "sg:address":"1310 N Melrose Dr Ste D",
    "sg:city":"Vista",
    "sg:classifiers":[
        {
            "category":"Government",
            "subcategory":"Office",
            "type":"Public Place"
        }
    ],
    "sg:phone":"+1 760 536 4737",
    "sg:postcode":"92083",
    "sg:province":"CA",
    "sg:tags":[
        "smog",
        "check"
    ],
    "wof:name":"Pacific Coast Smog Check",
    "wof:placetype":"venue"
},
  "geometry": {"coordinates":[-117.24900100000001,33.201801],"type":"Point"}
}