{
  "type": "Feature",
  "properties": {
    "iso:country":"US",
    "sg:address":"2759 Montrose Ave",
    "sg:city":"Montrose",
    "sg:classifiers":[
        {
            "category":"Food & Beverages",
            "subcategory":"Groceries & Convenience Stores",
            "type":"Retail Goods"
        }
    ],
    "sg:phone":"+1 818 249 5016",
    "sg:postcode":"91020",
    "sg:province":"CA",
    "wof:name":"7-Eleven Food Stores",
    "wof:placetype":"venue"
},
  "geometry": {"coordinates":[-118.239998,34.215698],"type":"Point"}
}