{
  "type": "Feature",
  "properties": {
    "iso:country":"US",
    "sg:address":"10656 Cam Ruiz",
    "sg:city":"San Diego",
    "sg:classifiers":[
        {
            "category":"Autos & Motor Vehicles",
            "subcategory":"Auto Supplies",
            "type":"Retail Goods"
        }
    ],
    "sg:phone":"+1 858 695 9605",
    "sg:postcode":"92126",
    "sg:province":"CA",
    "sg:tags":[
        "automobile",
        "parts"
    ],
    "sg:website":"www.kragenauto.com",
    "wof:name":"Kragen Auto Parts",
    "wof:placetype":"venue"
},
  "geometry": {"coordinates":[-117.144036,32.91142],"type":"Point"}
}