{
  "type": "Feature",
  "properties": {
    "addr:full":"1220 S Pacific Ave San Pedro CA 90731",
    "addr:housenumber":"1220",
    "addr:postcode":"90731",
    "addr:street":"S Pacific Ave",
    "iso:country":"US",
    "sg:address":"1220 S Pacific Ave",
    "sg:city":"San Pedro",
    "sg:classifiers":[
        {
            "category":"Arts & Performance",
            "subcategory":"Theater",
            "type":"Entertainment"
        }
    ],
    "sg:phone":"+1 310 832 7520",
    "sg:postcode":"90731",
    "sg:province":"CA",
    "sg:tags":[
        "live",
        "music"
    ],
    "wof:name":"Bj The DJ",
    "wof:placetype":"venue"
},
  "geometry": {"coordinates":[-118.287857,33.732568],"type":"Point"}
}