{
  "type": "Feature",
  "properties": {
    "addr:full":"5610 Kearny Mesa Rd Ste B San Diego CA 92111",
    "addr:housenumber":"5610",
    "addr:postcode":"92111",
    "addr:street":"Kearny Mesa Rd Ste B",
    "iso:country":"US",
    "sg:address":"5610 Kearny Mesa Rd Ste B",
    "sg:city":"San Diego",
    "sg:classifiers":[
        {
            "category":"Retail",
            "subcategory":"Veterinary Services",
            "type":"Services"
        }
    ],
    "sg:phone":"+1 858 560 9393",
    "sg:postcode":"92111",
    "sg:province":"CA",
    "sg:tags":[
        "veterinarian"
    ],
    "wof:name":"James Danielle DVM",
    "wof:placetype":"venue"
},
  "geometry": {"coordinates":[-117.13910300000001,32.835704],"type":"Point"}
}