{
  "type": "Feature",
  "properties": {
    "addr:full":"746 Vertin Ave Salinas CA 93901",
    "addr:housenumber":"746",
    "addr:postcode":"93901",
    "addr:street":"Vertin Ave",
    "iso:country":"US",
    "sg:address":"746 Vertin Ave",
    "sg:city":"Salinas",
    "sg:classifiers":[
        {
            "category":"Wholesale",
            "subcategory":"Machinery & Supplies",
            "type":"Manufacturing & Wholesale Goods"
        }
    ],
    "sg:phone":"+1 831 422 9693",
    "sg:postcode":"93901",
    "sg:province":"CA",
    "sg:tags":[
        "farm",
        "equipment"
    ],
    "sg:website":"www.suttonag.com",
    "wof:name":"Sutton Ag Enterprises",
    "wof:placetype":"venue"
},
  "geometry": {"coordinates":[-121.628304,36.66127],"type":"Point"}
}