{
  "type": "Feature",
  "properties": {
    "addr:full":"8520 Peachtree Ave Newark CA 94560",
    "addr:housenumber":"8520",
    "addr:postcode":"94560",
    "addr:street":"Peachtree Ave",
    "iso:country":"US",
    "sg:address":"8520 Peachtree Ave",
    "sg:city":"Newark",
    "sg:classifiers":[
        {
            "category":"Wholesale",
            "subcategory":"Machinery & Supplies",
            "type":"Manufacturing & Wholesale Goods"
        }
    ],
    "sg:phone":"+1 408 393 9185",
    "sg:postcode":"94560",
    "sg:province":"CA",
    "sg:tags":[
        "equipment",
        "measurement"
    ],
    "wof:name":"Focused Photonics Inc",
    "wof:placetype":"venue"
},
  "geometry": {"coordinates":[-122.054699,37.527042],"type":"Point"}
}