{
  "type": "Feature",
  "properties": {
    "addr:full":"5924 San Fernando Rd Glendale CA 91202",
    "addr:housenumber":"5924",
    "addr:postcode":"91202",
    "addr:street":"San Fernando Rd",
    "iso:country":"US",
    "sg:address":"5924 San Fernando Rd",
    "sg:city":"Glendale",
    "sg:classifiers":[
        {
            "category":"Professional",
            "subcategory":"Engineering",
            "type":"Services"
        }
    ],
    "sg:phone":"+1 818 241 1800",
    "sg:postcode":"91202",
    "sg:province":"CA",
    "sg:tags":[
        "engineer"
    ],
    "sg:website":"www.california-electrical.com",
    "wof:name":"California Electrical Svc",
    "wof:placetype":"venue"
},
  "geometry": {"coordinates":[-118.280247,34.159822],"type":"Point"}
}