{
  "type": "Feature",
  "properties": {
    "addr:full":"610 W 6th St Corona CA 92882",
    "addr:housenumber":"610",
    "addr:postcode":"92882",
    "addr:street":"W 6Th St",
    "iso:country":"US",
    "sg:address":"610 W 6th St",
    "sg:city":"Corona",
    "sg:classifiers":[
        {
            "category":"Shopping",
            "subcategory":"Clothing, Apparel, & Fashions",
            "type":"Retail Goods"
        }
    ],
    "sg:phone":"+1 951 738 8338",
    "sg:postcode":"92882",
    "sg:province":"CA",
    "sg:tags":[
        "shop",
        "bridal"
    ],
    "wof:name":"America's Bridal",
    "wof:placetype":"venue"
},
  "geometry": {"coordinates":[-117.573854,33.87614],"type":"Point"}
}