{
  "type": "Feature",
  "properties": {
    "iso:country":"US",
    "sg:address":"635 Cypress Ave",
    "sg:city":"Hermosa Beach",
    "sg:classifiers":[
        {
            "category":"Manufacturing",
            "subcategory":"Printing",
            "type":"Manufacturing & Wholesale Goods"
        }
    ],
    "sg:phone":"+1 310 406 0610",
    "sg:postcode":"90254",
    "sg:province":"CA",
    "sg:tags":[
        "screen"
    ],
    "wof:name":"Authentic Image Marketing",
    "wof:placetype":"venue"
},
  "geometry": {"coordinates":[-118.395576,33.859176],"type":"Point"}
}