{
  "type": "Feature",
  "properties": {
    "addr:full":"410 Crother Rd Meadow Vista CA 95722",
    "addr:housenumber":"410",
    "addr:postcode":"95722",
    "addr:street":"Crother Rd",
    "iso:country":"US",
    "sg:address":"410 Crother Rd",
    "sg:city":"Meadow Vista",
    "sg:classifiers":[
        {
            "category":"Education",
            "subcategory":"School",
            "type":"Public Place"
        }
    ],
    "sg:phone":"+1 530 878 8720",
    "sg:postcode":"95722",
    "sg:province":"CA",
    "sg:website":"www.liveoakwaldorf.org",
    "wof:name":"Live Oak Waldorf School",
    "wof:placetype":"venue"
},
  "geometry": {"coordinates":[-120.993882,39.01048],"type":"Point"}
}