{
  "type": "Feature",
  "properties": {
    "iso:country":"US",
    "sg:address":"4000 Clayton Rd",
    "sg:city":"Concord",
    "sg:classifiers":[
        {
            "category":"Place Of Worship",
            "subcategory":"Church",
            "type":"Public Place"
        },
        {
            "category":"Place Of Worship",
            "type":"Public Place"
        }
    ],
    "sg:phone":"+1 925 682 8410",
    "sg:postcode":"94521",
    "sg:province":"CA",
    "sg:tags":[
        "lutheran",
        "america",
        "churches-lutheran",
        "churches-lutheran-evangelical"
    ],
    "sg:website":"http://www.gsconcord.com",
    "wof:name":"Good Shepherd Lutheran Church ELCA",
    "wof:placetype":"venue"
},
  "geometry": {"coordinates":[-122.000539,37.967445],"type":"Point"}
}