{
  "type": "Feature",
  "properties": {
    "iso:country":"US",
    "sg:address":"320 W Wilson Ave",
    "sg:city":"Glendale",
    "sg:classifiers":[
        {
            "category":"Arts & Performance",
            "subcategory":"Music",
            "type":"Entertainment"
        }
    ],
    "sg:postcode":"91203",
    "sg:province":"CA",
    "sg:tags":[
        "venue"
    ],
    "sg:website":"www.royaldanceparty.com",
    "wof:name":"Royal Dance Party",
    "wof:placetype":"venue"
},
  "geometry": {"coordinates":[-118.258864,34.148033],"type":"Point"}
}