{
  "type": "Feature",
  "properties": {
    "addr:full":"451 S Coast Hwy Laguna Beach CA 92651",
    "addr:housenumber":"451",
    "addr:postcode":"92651",
    "addr:street":"S Coast Hwy",
    "iso:country":"US",
    "sg:address":"451 S Coast Hwy",
    "sg:city":"Laguna Beach",
    "sg:classifiers":[
        {
            "category":"Shopping",
            "subcategory":"Used Merchandise",
            "type":"Retail Goods"
        }
    ],
    "sg:phone":"+1 949 494 8610",
    "sg:postcode":"92651",
    "sg:province":"CA",
    "sg:tags":[
        "antique"
    ],
    "sg:website":"www.artinlaguna.com",
    "wof:name":"David & Son Fine Arts",
    "wof:placetype":"venue"
},
  "geometry": {"coordinates":[-117.78177599999999,33.54018],"type":"Point"}
}