{
  "type": "Feature",
  "properties": {
    "iso:country":"US",
    "sg:address":"21865 Copley Dr",
    "sg:city":"Diamond Bar",
    "sg:classifiers":[
        {
            "category":"Government",
            "subcategory":"Office",
            "type":"Public Place"
        }
    ],
    "sg:phone":"+1 909 396 2000",
    "sg:postcode":"91765",
    "sg:province":"CA",
    "sg:website":"www.aqmd.gov",
    "wof:name":"South Coast Air Quality Mgmt",
    "wof:placetype":"venue"
},
  "geometry": {"coordinates":[-117.83129700000001,33.999439],"type":"Point"}
}