{
  "type": "Feature",
  "properties": {
    "addr:full":"13614 Dry Creek Rd Victorville CA 92392",
    "addr:housenumber":"13614",
    "addr:postcode":"92392",
    "addr:street":"Dry Creek Rd",
    "iso:country":"US",
    "sg:address":"13614 Dry Creek Rd",
    "sg:city":"Victorville",
    "sg:classifiers":[
        {
            "category":"Professional",
            "subcategory":"Management & Consulting",
            "type":"Services"
        }
    ],
    "sg:phone":"+1 760 241 3400",
    "sg:postcode":"92392",
    "sg:province":"CA",
    "sg:tags":[
        "retail",
        "direct",
        "sales"
    ],
    "wof:name":"Howard Bompass Direct Sales",
    "wof:placetype":"venue"
},
  "geometry": {"coordinates":[-117.366505,34.490093],"type":"Point"}
}