{
  "type": "Feature",
  "properties": {
    "addr:full":"460 Brannan St San Francisco CA 94107",
    "addr:housenumber":"460",
    "addr:postcode":"94107",
    "addr:street":"Brannan St",
    "iso:country":"US",
    "sg:address":"460 Brannan St",
    "sg:city":"San Francisco",
    "sg:classifiers":[
        {
            "category":"Government",
            "subcategory":"Post Office",
            "type":"Public Place"
        }
    ],
    "sg:phone":"+1 415 543 7729",
    "sg:postcode":"94107",
    "sg:province":"CA",
    "wof:name":"Brannan Street Post Office",
    "wof:placetype":"venue"
},
  "geometry": {"coordinates":[-122.396051,37.779173],"type":"Point"}
}