{
  "type": "Feature",
  "properties": {
    "iso:country":"US",
    "sg:address":"831 Casa de Oro Pl",
    "sg:city":"Escondido",
    "sg:classifiers":[
        {
            "category":"Professional",
            "subcategory":"Management & Consulting",
            "type":"Services"
        }
    ],
    "sg:phone":"+1 760 233 8893",
    "sg:postcode":"92025",
    "sg:province":"CA",
    "sg:tags":[
        "personnel",
        "consultant"
    ],
    "wof:name":"Marilyn Temporary Staffing",
    "wof:placetype":"venue"
},
  "geometry": {"coordinates":[-117.081005,33.098748],"type":"Point"}
}