{
  "type": "Feature",
  "properties": {
    "addr:full":"413 Hermosa St Santa Maria CA 93454",
    "addr:housenumber":"413",
    "addr:postcode":"93454",
    "addr:street":"Hermosa St",
    "iso:country":"US",
    "sg:address":"413 Hermosa St",
    "sg:city":"Santa Maria",
    "sg:classifiers":[
        {
            "category":"Social Services",
            "subcategory":"Child Care",
            "type":"Services"
        }
    ],
    "sg:phone":"+1 805 922 4609",
    "sg:postcode":"93454",
    "sg:province":"CA",
    "wof:name":"Groce Family Day Care",
    "wof:placetype":"venue"
},
  "geometry": {"coordinates":[-120.430144,34.959619],"type":"Point"}
}