{
  "type": "Feature",
  "properties": {
    "addr:full":"125 2nd St Oakland CA 94607",
    "addr:housenumber":"125",
    "addr:postcode":"94607",
    "addr:street":"2Nd St",
    "iso:country":"US",
    "sg:address":"125 2nd St",
    "sg:city":"Oakland",
    "sg:classifiers":[
        {
            "category":"Social Services",
            "subcategory":"Child Care",
            "type":"Services"
        }
    ],
    "sg:phone":"+1 877 236 7863",
    "sg:postcode":"94607",
    "sg:province":"CA",
    "sg:tags":[
        "adoption"
    ],
    "wof:name":"Family Outreach Services Team (Fost) Project",
    "wof:placetype":"venue"
},
  "geometry": {"coordinates":[-122.26862300000001,37.793011],"type":"Point"}
}