{
  "type": "Feature",
  "properties": {
    "iso:country":"US",
    "sg:address":"2177 Bancroft Avenue",
    "sg:city":"Berkeley",
    "sg:classifiers":[
        {
            "category":"Retail",
            "subcategory":"Event Space",
            "type":"Services"
        }
    ],
    "sg:phone":"+1 510 528 3203",
    "sg:postcode":"94704",
    "sg:province":"CA",
    "sg:tags":[
        "venue"
    ],
    "sg:website":"www.berkeley.shambhala.org/stree...",
    "wof:name":"Shambhala Streetspace",
    "wof:placetype":"venue"
},
  "geometry": {"coordinates":[-122.266283,37.867803],"type":"Point"}
}