{
  "type": "Feature",
  "properties": {
    "addr:full":"282 Shoreline Dr Pittsburg CA 94565",
    "addr:housenumber":"282",
    "addr:postcode":"94565",
    "addr:street":"Shoreline Dr",
    "iso:country":"US",
    "sg:address":"282 Shoreline Dr",
    "sg:city":"Pittsburg",
    "sg:classifiers":[
        {
            "category":"Shopping",
            "subcategory":"Beauty & Cosmetics",
            "type":"Retail Goods"
        }
    ],
    "sg:phone":"+1 925 439 9095",
    "sg:postcode":"94565",
    "sg:province":"CA",
    "sg:tags":[
        "perfume"
    ],
    "wof:name":"Bubbs Bath & Body",
    "wof:placetype":"venue"
},
  "geometry": {"coordinates":[-121.88094599999999,38.033407],"type":"Point"}
}