{
  "type": "Feature",
  "properties": {
    "addr:full":"224 N 7th Ave Barstow CA 92311",
    "addr:housenumber":"224",
    "addr:postcode":"92311",
    "addr:street":"N 7Th Ave",
    "iso:country":"US",
    "sg:address":"224 N 7th Ave",
    "sg:city":"Barstow",
    "sg:classifiers":[
        {
            "category":"Restaurant",
            "type":"Food & Drink"
        }
    ],
    "sg:phone":"+1 760 256 3168",
    "sg:postcode":"92311",
    "sg:province":"CA",
    "wof:name":"Alvarado Restaurant Mexican Food",
    "wof:placetype":"venue"
},
  "geometry": {"coordinates":[-117.02001,34.8995],"type":"Point"}
}