{
  "type": "Feature",
  "properties": {
    "iso:country":"US",
    "sg:address":"2091 Las Palmas Dr",
    "sg:city":"Carlsbad",
    "sg:classifiers":[
        {
            "category":"Wholesale",
            "subcategory":"Computers",
            "type":"Manufacturing & Wholesale Goods"
        },
        {
            "category":"Professional",
            "subcategory":"Computer Services",
            "type":"Services"
        }
    ],
    "sg:phone":"+1 760 930 0473",
    "sg:postcode":"92011",
    "sg:province":"CA",
    "sg:tags":[
        "repair"
    ],
    "wof:name":"Snyaccess",
    "wof:placetype":"venue"
},
  "geometry": {"coordinates":[-117.275284,33.117093],"type":"Point"}
}