{
  "type": "Feature",
  "properties": {
    "addr:full":"3742 Mission Blvd. San Diego CA 92109",
    "addr:housenumber":"3742",
    "addr:postcode":"92109",
    "addr:street":"Mission Blvd.",
    "iso:country":"US",
    "sg:address":"3742 Mission Blvd.",
    "sg:city":"San Diego",
    "sg:classifiers":[
        {
            "category":"Shopping",
            "subcategory":"Tobacco",
            "type":"Retail Goods"
        }
    ],
    "sg:phone":"+1 858 488 4924",
    "sg:postcode":"92109",
    "sg:province":"CA",
    "sg:tags":[
        "shop"
    ],
    "wof:name":"Freak Factory",
    "wof:placetype":"venue"
},
  "geometry": {"coordinates":[-117.25262499999999,32.783138],"type":"Point"}
}