{
  "type": "Feature",
  "properties": {
    "iso:country":"US",
    "sg:address":"2420 Green Pl",
    "sg:city":"Arroyo Grande",
    "sg:classifiers":[
        {
            "category":"Shopping",
            "subcategory":"Catalog Store",
            "type":"Retail Goods"
        }
    ],
    "sg:phone":"+1 805 481 5344",
    "sg:postcode":"93420",
    "sg:province":"CA",
    "sg:tags":[
        "house",
        "mail",
        "supply"
    ],
    "sg:website":"www.daylilywest.com",
    "wof:name":"Daylily West",
    "wof:placetype":"venue"
},
  "geometry": {"coordinates":[-120.571706,35.081804],"type":"Point"}
}