{
  "type": "Feature",
  "properties": {
    "iso:country":"US",
    "sg:address":"2200 Wood St",
    "sg:city":"Oakland",
    "sg:classifiers":[
        {
            "category":"Professional",
            "subcategory":"Business Services",
            "type":"Services"
        }
    ],
    "sg:phone":"+1 510 986 0722",
    "sg:postcode":"94607",
    "sg:province":"CA",
    "sg:tags":[
        "recording",
        "studio"
    ],
    "wof:name":"Mezcal",
    "wof:placetype":"venue"
},
  "geometry": {"coordinates":[-122.292311,37.820278],"type":"Point"}
}