{
  "type": "Feature",
  "properties": {
    "iso:country":"US",
    "sg:address":"23 Hidden Mine Rd",
    "sg:city":"Oroville",
    "sg:classifiers":[
        {
            "category":"Manufacturing",
            "subcategory":"Metals",
            "type":"Manufacturing & Wholesale Goods"
        }
    ],
    "sg:phone":"+1 530 532 6424",
    "sg:postcode":"95965",
    "sg:province":"CA",
    "sg:tags":[
        "steel",
        "product",
        "mfg"
    ],
    "wof:name":"Yankee Hill Iron Works",
    "wof:placetype":"venue"
},
  "geometry": {"coordinates":[-121.53505699999999,39.682336],"type":"Point"}
}