{
  "type": "Feature",
  "properties": {
    "iso:country":"US",
    "sg:address":"1349 Shadow Ln",
    "sg:city":"Fullerton",
    "sg:classifiers":[
        {
            "category":"Freight",
            "type":"Transportation"
        }
    ],
    "sg:phone":"+1 714 526 5073",
    "sg:postcode":"92831",
    "sg:province":"CA",
    "wof:name":"Ocean Sail Crusing",
    "wof:placetype":"venue"
},
  "geometry": {"coordinates":[-117.919716,33.885268],"type":"Point"}
}