{
  "type": "Feature",
  "properties": {
    "addr:full":"820 Thompson Ave Glendale CA 91201",
    "addr:housenumber":"820",
    "addr:postcode":"91201",
    "addr:street":"Thompson Ave",
    "iso:country":"US",
    "sg:address":"820 Thompson Ave",
    "sg:city":"Glendale",
    "sg:classifiers":[
        {
            "category":"Real Estate",
            "subcategory":"Architect",
            "type":"Services"
        }
    ],
    "sg:phone":"+1 818 545 8156",
    "sg:postcode":"91201",
    "sg:province":"CA",
    "sg:tags":[
        "home",
        "planning",
        "design"
    ],
    "wof:name":"Home Decorating",
    "wof:placetype":"venue"
},
  "geometry": {"coordinates":[-118.296179,34.168004],"type":"Point"}
}