{
  "type": "Feature",
  "properties": {
    "addr:full":"2644 Adams Ave San Diego CA 92116",
    "addr:housenumber":"2644",
    "addr:postcode":"92116",
    "addr:street":"Adams Ave",
    "iso:country":"US",
    "sg:address":"2644 Adams Ave",
    "sg:city":"San Diego",
    "sg:classifiers":[
        {
            "category":"Professional",
            "type":"Services"
        }
    ],
    "sg:phone":"+1 619 295 6232",
    "sg:postcode":"92116",
    "sg:province":"CA",
    "sg:tags":[
        "hair",
        "salon"
    ],
    "wof:name":"Sashay",
    "wof:placetype":"venue"
},
  "geometry": {"coordinates":[-117.136002,32.762798],"type":"Point"}
}