{
  "type": "Feature",
  "properties": {
    "addr:full":"911 Grant Ave San Francisco CA 94108",
    "addr:housenumber":"911",
    "addr:postcode":"94108",
    "addr:street":"Grant Ave",
    "iso:country":"US",
    "sg:address":"911 Grant Ave",
    "sg:city":"San Francisco",
    "sg:classifiers":[
        {
            "category":"Shopping",
            "subcategory":"Jewelry",
            "type":"Retail Goods"
        }
    ],
    "sg:phone":"+1 415 392 3787",
    "sg:postcode":"94108",
    "sg:province":"CA",
    "wof:name":"Wo Yick Co Inc",
    "wof:placetype":"venue"
},
  "geometry": {"coordinates":[-122.406616,37.795431],"type":"Point"}
}