{
  "type": "Feature",
  "properties": {
    "iso:country":"US",
    "sg:address":"3507 Tully Rd Ste F",
    "sg:city":"Modesto",
    "sg:classifiers":[
        {
            "category":"Restaurant",
            "type":"Food & Drink"
        },
        {
            "category":"Bakery",
            "type":"Food & Drink"
        },
        {
            "category":"Donuts",
            "subcategory":"None",
            "type":"Food & Drink"
        }
    ],
    "sg:phone":"+1 209 522 1614",
    "sg:postcode":"95356",
    "sg:province":"CA",
    "sg:tags":[
        "shop"
    ],
    "wof:name":"Mr T's Delicate Donut Shop",
    "wof:placetype":"venue"
},
  "geometry": {"coordinates":[-121.01251499999999,37.689422],"type":"Point"}
}