{
  "type": "Feature",
  "properties": {
    "iso:country":"US",
    "sg:address":"800 Emory St",
    "sg:city":"San Jose",
    "sg:classifiers":[
        {
            "category":"Government",
            "subcategory":"Fire Station",
            "type":"Public Place"
        }
    ],
    "sg:phone":"+1 408 277 4367",
    "sg:postcode":"95126",
    "sg:province":"CA",
    "sg:tags":[
        "department"
    ],
    "wof:name":"San Jose Fire Station 7",
    "wof:placetype":"venue"
},
  "geometry": {"coordinates":[-121.918008,37.340742],"type":"Point"}
}