{
  "type": "Feature",
  "properties": {
    "iso:country":"US",
    "sg:address":"800 Los Lunas Way",
    "sg:city":"Sacramento",
    "sg:classifiers":[
        {
            "category":"Retail",
            "subcategory":"Photofinishing",
            "type":"Services"
        }
    ],
    "sg:phone":"+1 916 971 3456",
    "sg:postcode":"95833",
    "sg:province":"CA",
    "sg:tags":[
        "laboratory",
        "photographic",
        "mfg"
    ],
    "wof:name":"Quicky 1 Hour Photo",
    "wof:placetype":"venue"
},
  "geometry": {"coordinates":[-121.479412,38.618009],"type":"Point"}
}