{
  "type": "Feature",
  "properties": {
    "iso:country":"US",
    "sg:address":"315 E 11th St",
    "sg:city":"Tracy",
    "sg:classifiers":[
        {
            "category":"Education",
            "subcategory":"School",
            "type":"Public Place"
        }
    ],
    "sg:phone":"+1 209 831 5000",
    "sg:postcode":"95376",
    "sg:province":"CA",
    "wof:name":"Tracy Jnt Union High Sch Dist",
    "wof:placetype":"venue"
},
  "geometry": {"coordinates":[-121.419431,37.739812],"type":"Point"}
}