{
  "type": "Feature",
  "properties": {
    "iso:country":"US",
    "sg:address":"328 Ocean St",
    "sg:city":"Santa Cruz",
    "sg:classifiers":[
        {
            "category":"Real Estate",
            "subcategory":"Real Estate Operator",
            "type":"Services"
        }
    ],
    "sg:phone":"+1 831 469 4562",
    "sg:postcode":"95060",
    "sg:province":"CA",
    "sg:tags":[
        "apartment"
    ],
    "wof:name":"Castle Court Apartments",
    "wof:placetype":"venue"
},
  "geometry": {"coordinates":[-122.017912,36.972664],"type":"Point"}
}