{
  "type": "Feature",
  "properties": {
    "addr:full":"1119 W Visalia Rd Exeter CA 93221",
    "addr:housenumber":"1119",
    "addr:postcode":"93221",
    "addr:street":"W Visalia Rd",
    "iso:country":"US",
    "sg:address":"1119 W Visalia Rd",
    "sg:city":"Exeter",
    "sg:classifiers":[
        {
            "category":"Wholesale",
            "subcategory":"Medical Equipment & Supplies",
            "type":"Manufacturing & Wholesale Goods"
        },
        {
            "category":"Shopping",
            "subcategory":"Beauty & Cosmetics",
            "type":"Retail Goods"
        },
        {
            "category":"Food & Beverages",
            "subcategory":"Specialty",
            "type":"Retail Goods"
        },
        {
            "category":"Shopping",
            "subcategory":"Gifts & Souvenirs",
            "type":"Retail Goods"
        },
        {
            "category":"Retail",
            "subcategory":"Photofinishing",
            "type":"Services"
        },
        {
            "category":"Shopping",
            "subcategory":"Pharmacy",
            "type":"Retail Goods"
        }
    ],
    "sg:phone":"+1 559 592 4901",
    "sg:postcode":"93221",
    "sg:province":"CA",
    "sg:tags":[
        "product",
        "photo",
        "vitamin",
        "perfume",
        "supplement",
        "health",
        "wellness",
        "aid",
        "finishing",
        "first",
        "card",
        "greeting"
    ],
    "sg:website":"http://www.riteaid.com",
    "wof:name":"Rite Aid",
    "wof:placetype":"venue"
},
  "geometry": {"coordinates":[-119.15411400000001,36.297329],"type":"Point"}
}