{
  "type": "Feature",
  "properties": {
    "iso:country":"US",
    "sg:address":"11601 Wilshire Blvd",
    "sg:city":"Los Angeles",
    "sg:classifiers":[
        {
            "category":"Real Estate",
            "subcategory":"Real Estate Agent",
            "type":"Services"
        },
        {
            "category":"Professional",
            "subcategory":"Business Services",
            "type":"Services"
        }
    ],
    "sg:phone":"+1 310 201 0962",
    "sg:postcode":"90025",
    "sg:province":"CA",
    "sg:tags":[
        "appraiser"
    ],
    "wof:name":"A Allison Appraisals",
    "wof:placetype":"venue"
},
  "geometry": {"coordinates":[-118.460072,34.050095],"type":"Point"}
}