{
  "type": "Feature",
  "properties": {
    "addr:full":"1660 Alum Rock Ave San Jose CA 95116",
    "addr:housenumber":"1660",
    "addr:postcode":"95116",
    "addr:street":"Alum Rock Ave",
    "iso:country":"US",
    "sg:address":"1660 Alum Rock Ave",
    "sg:city":"San Jose",
    "sg:classifiers":[
        {
            "category":"Manufacturing",
            "subcategory":"Printing",
            "type":"Manufacturing & Wholesale Goods"
        }
    ],
    "sg:phone":"+1 408 923 5800",
    "sg:postcode":"95116",
    "sg:province":"CA",
    "sg:tags":[
        "printer"
    ],
    "wof:name":"Print Sharp-Copy Sharp",
    "wof:placetype":"venue"
},
  "geometry": {"coordinates":[-121.85584900000001,37.352563],"type":"Point"}
}