{
  "type": "Feature",
  "properties": {
    "addr:full":"2731 S Rose Ave Oxnard CA 93033",
    "addr:housenumber":"2731",
    "addr:postcode":"93033",
    "addr:street":"S Rose Ave",
    "iso:country":"US",
    "sg:address":"2731 S Rose Ave",
    "sg:city":"Oxnard",
    "sg:classifiers":[
        {
            "category":"Restaurant",
            "type":"Food & Drink"
        }
    ],
    "sg:menulink":"http://www.allmenus.com/ca/oxnard/147126-charo-chicken/menu/",
    "sg:phone":"+1 805 486 8592",
    "sg:postcode":"93033",
    "sg:province":"CA",
    "sg:tags":[
        "american"
    ],
    "wof:name":"CHARO CHICKEN",
    "wof:placetype":"venue"
},
  "geometry": {"coordinates":[-119.160186,34.173808],"type":"Point"}
}