{
  "type": "Feature",
  "properties": {
    "addr:full":"717 Bridge St Colusa CA 95932",
    "addr:housenumber":"717",
    "addr:postcode":"95932",
    "addr:street":"Bridge St",
    "iso:country":"US",
    "sg:address":"717 Bridge St",
    "sg:city":"Colusa",
    "sg:classifiers":[
        {
            "category":"Health Services",
            "subcategory":"Hospital",
            "type":"Services"
        }
    ],
    "sg:phone":"+1 530 458 5003",
    "sg:postcode":"95932",
    "sg:province":"CA",
    "wof:name":"Colusa Health Clinic",
    "wof:placetype":"venue"
},
  "geometry": {"coordinates":[-122.002906,39.207832],"type":"Point"}
}