{
  "type": "Feature",
  "properties": {
    "addr:full":"5690 Old Redwood Hwy Santa Rosa CA 95403",
    "addr:housenumber":"5690",
    "addr:postcode":"95403",
    "addr:street":"Old Redwood Hwy",
    "iso:country":"US",
    "sg:address":"5690 Old Redwood Hwy",
    "sg:city":"Santa Rosa",
    "sg:classifiers":[
        {
            "category":"Freight",
            "type":"Transportation"
        }
    ],
    "sg:phone":"+1 707 838 7315",
    "sg:postcode":"95403",
    "sg:province":"CA",
    "sg:tags":[
        "recreational",
        "vehicle"
    ],
    "wof:name":"Rv Storage",
    "wof:placetype":"venue"
},
  "geometry": {"coordinates":[-122.77589999999999,38.52201],"type":"Point"}
}