{
  "type": "Feature",
  "properties": {
    "iso:country":"US",
    "sg:address":"30061 Sugarpine St",
    "sg:city":"Lake Elsinore",
    "sg:classifiers":[
        {
            "category":"Professional",
            "type":"Services"
        }
    ],
    "sg:phone":"+1 951 678 6558",
    "sg:postcode":"92530",
    "sg:province":"CA",
    "sg:tags":[
        "establishment"
    ],
    "wof:name":"Adlogic Inc",
    "wof:placetype":"venue"
},
  "geometry": {"coordinates":[-117.391707,33.680201],"type":"Point"}
}