{
  "type": "Feature",
  "properties": {
    "iso:country":"US",
    "sg:address":"10562 Creek Rd",
    "sg:city":"Ojai",
    "sg:classifiers":[
        {
            "category":"Retail",
            "subcategory":"Animal Services",
            "type":"Services"
        }
    ],
    "sg:phone":"+1 805 649 1256",
    "sg:postcode":"93023",
    "sg:province":"CA",
    "wof:name":"Westwinds Ranch",
    "wof:placetype":"venue"
},
  "geometry": {"coordinates":[-119.28322300000001,34.403334],"type":"Point"}
}