{
  "type": "Feature",
  "properties": {
    "addr:full":"2591 Seaboard Ave San Jose CA 95131",
    "addr:housenumber":"2591",
    "addr:postcode":"95131",
    "addr:street":"Seaboard Ave",
    "iso:country":"US",
    "sg:address":"2591 Seaboard Ave",
    "sg:city":"San Jose",
    "sg:classifiers":[
        {
            "category":"Retail",
            "subcategory":"Repair Shop",
            "type":"Services"
        }
    ],
    "sg:phone":"+1 408 434 9500",
    "sg:postcode":"95131",
    "sg:province":"CA",
    "sg:tags":[
        "related"
    ],
    "wof:name":"Dela Cruz Union Auto Repair",
    "wof:placetype":"venue"
},
  "geometry": {"coordinates":[-121.93826199999999,37.376798],"type":"Point"}
}