{
  "type": "Feature",
  "properties": {
    "addr:full":"2487 E Washington Blvd Ste C-D Pasadena CA 91104",
    "addr:housenumber":"2487",
    "addr:postcode":"91104",
    "addr:street":"E Washington Blvd Ste C-D",
    "iso:country":"US",
    "sg:address":"2487 E Washington Blvd Ste C-D",
    "sg:city":"Pasadena",
    "sg:classifiers":[
        {
            "category":"Food & Beverages",
            "subcategory":"Groceries & Convenience Stores",
            "type":"Retail Goods"
        }
    ],
    "sg:phone":"+1 626 345 1802",
    "sg:postcode":"91104",
    "sg:province":"CA",
    "wof:name":"Fresno Produce",
    "wof:placetype":"venue"
},
  "geometry": {"coordinates":[-118.141689,34.172002],"type":"Point"}
}