{
  "type": "Feature",
  "properties": {
    "iso:country":"US",
    "sg:address":"1123 12th St",
    "sg:city":"Sacramento",
    "sg:classifiers":[
        {
            "category":"Shopping",
            "subcategory":"Jewelry",
            "type":"Retail Goods"
        }
    ],
    "sg:phone":"+1 916 443 6031",
    "sg:postcode":"95814",
    "sg:province":"CA",
    "sg:tags":[
        "designer"
    ],
    "wof:name":"Shinjyu Jewelry",
    "wof:placetype":"venue"
},
  "geometry": {"coordinates":[-121.491361,38.578178],"type":"Point"}
}