{
  "type": "Feature",
  "properties": {
    "addr:full":"26548 Moulton Pkwy Laguna Hills CA 92653",
    "addr:postcode":"26548;92653",
    "addr:street":"Moulton Pkwy",
    "iso:country":"US",
    "sg:address":"26548 Moulton Pkwy",
    "sg:city":"Laguna Hills",
    "sg:classifiers":[
        {
            "category":"Restaurant",
            "type":"Food & Drink"
        }
    ],
    "sg:menulink":"http://www.allmenus.com/ca/south-coast/151966-baja-fresh-mexican-grill/menu/",
    "sg:phone":"+1 949 360 4222",
    "sg:postcode":"92653",
    "sg:province":"CA",
    "sg:tags":[
        "mexican"
    ],
    "wof:name":"Baja Fresh Mexican Grill",
    "wof:placetype":"venue"
},
  "geometry": {"coordinates":[-117.70247000000001,33.577475],"type":"Point"}
}