{
  "type": "Feature",
  "properties": {
    "iso:country":"US",
    "sg:address":"19491 Surfset Dr",
    "sg:city":"Huntington Beach",
    "sg:classifiers":[
        {
            "category":"Utilities",
            "subcategory":"Telephone",
            "type":"Services"
        }
    ],
    "sg:phone":"+1 714 536 8982",
    "sg:postcode":"92648",
    "sg:province":"CA",
    "sg:tags":[
        "communications"
    ],
    "wof:name":"Wd6awp Repeater Group",
    "wof:placetype":"venue"
},
  "geometry": {"coordinates":[-118.028806,33.679503],"type":"Point"}
}