{
  "type": "Feature",
  "properties": {
    "iso:country":"US",
    "sg:address":"3801 Watt Ave",
    "sg:city":"Sacramento",
    "sg:classifiers":[
        {
            "category":"Banks & Credit Unions",
            "subcategory":"Bank",
            "type":"Services"
        }
    ],
    "sg:phone":"+1 916 971 1700",
    "sg:postcode":"95821",
    "sg:province":"CA",
    "sg:tags":[
        "loan",
        "real estate"
    ],
    "wof:name":"California Plan Inc",
    "wof:placetype":"venue"
},
  "geometry": {"coordinates":[-121.382931,38.635101],"type":"Point"}
}