{
  "type": "Feature",
  "properties": {
    "iso:country":"US",
    "sg:address":"8788 Ellingham St",
    "sg:city":"San Diego",
    "sg:classifiers":[
        {
            "category":"Manufacturing",
            "subcategory":"Leather Goods",
            "type":"Manufacturing & Wholesale Goods"
        }
    ],
    "sg:phone":"+1 858 213 6643",
    "sg:postcode":"92129",
    "sg:province":"CA",
    "sg:tags":[
        "mfg"
    ],
    "wof:name":"Custom Classic Saddlebags",
    "wof:placetype":"venue"
},
  "geometry": {"coordinates":[-117.140673,32.964735],"type":"Point"}
}