{
  "type": "Feature",
  "properties": {
    "addr:full":"5648 N Pershing Ave Stockton CA 95207",
    "addr:housenumber":"5648",
    "addr:postcode":"95207",
    "addr:street":"N Pershing Ave",
    "iso:country":"US",
    "sg:address":"5648 N Pershing Ave",
    "sg:city":"Stockton",
    "sg:classifiers":[
        {
            "category":"Retail",
            "subcategory":"Laundry & Dry Cleaning",
            "type":"Services"
        }
    ],
    "sg:phone":"+1 209 477 8345",
    "sg:postcode":"95207",
    "sg:province":"CA",
    "sg:tags":[
        "cleaners"
    ],
    "wof:name":"Paul's Cleaners",
    "wof:placetype":"venue"
},
  "geometry": {"coordinates":[-121.32575,37.999087],"type":"Point"}
}