{
  "type": "Feature",
  "properties": {
    "iso:country":"US",
    "sg:address":"7981 State Hwy 99",
    "sg:city":"Los Molinos",
    "sg:classifiers":[
        {
            "category":"Wholesale",
            "subcategory":"Scrap",
            "type":"Manufacturing & Wholesale Goods"
        }
    ],
    "sg:phone":"+1 530 384 2326",
    "sg:postcode":"96055",
    "sg:province":"CA",
    "sg:tags":[
        "recycling",
        "center"
    ],
    "wof:name":"Rob's Recycling",
    "wof:placetype":"venue"
},
  "geometry": {"coordinates":[-122.100027,40.025279],"type":"Point"}
}