{
  "type": "Feature",
  "properties": {
    "addr:full":"320 Pine Ave Ste 400 Long Beach CA 90802",
    "addr:housenumber":"320",
    "addr:postcode":"90802",
    "addr:street":"Pine Ave Ste 400",
    "iso:country":"US",
    "sg:address":"320 Pine Ave Ste 400",
    "sg:city":"Long Beach",
    "sg:classifiers":[
        {
            "category":"Real Estate",
            "subcategory":"Architect",
            "type":"Services"
        }
    ],
    "sg:phone":"+1 562 435 5300",
    "sg:postcode":"90802",
    "sg:province":"CA",
    "sg:website":"www.moenarchitecture.com",
    "wof:name":"Moen Architecture",
    "wof:placetype":"venue"
},
  "geometry": {"coordinates":[-118.192091,33.770951],"type":"Point"}
}