{
  "type": "Feature",
  "properties": {
    "iso:country":"US",
    "sg:address":"9795 Business Park Dr",
    "sg:city":"Sacramento",
    "sg:classifiers":[
        {
            "category":"Professional",
            "subcategory":"Research",
            "type":"Services"
        }
    ],
    "sg:phone":"+1 916 366 1636",
    "sg:postcode":"95827",
    "sg:province":"CA",
    "sg:tags":[
        "development",
        "electronics"
    ],
    "wof:name":"Winchester Electronics",
    "wof:placetype":"venue"
},
  "geometry": {"coordinates":[-121.328996,38.571053],"type":"Point"}
}