{
  "type": "Feature",
  "properties": {
    "iso:country":"US",
    "sg:address":"1001 N Willis St",
    "sg:city":"Visalia",
    "sg:classifiers":[
        {
            "category":"Retail",
            "subcategory":"Animal Services",
            "type":"Services"
        }
    ],
    "sg:phone":"+1 559 636 6373",
    "sg:postcode":"93291",
    "sg:province":"CA",
    "wof:name":"Valeries Pet Salon",
    "wof:placetype":"venue"
},
  "geometry": {"coordinates":[-119.297613,36.339919],"type":"Point"}
}