{
  "type": "Feature",
  "properties": {
    "addr:full":"10239 Old River School Rd Downey CA 90241",
    "addr:housenumber":"10239",
    "addr:postcode":"90241",
    "addr:street":"Old;School Rd",
    "iso:country":"US",
    "sg:address":"10239 Old River School Rd",
    "sg:city":"Downey",
    "sg:classifiers":[
        {
            "category":"Health Services",
            "subcategory":"Clinic",
            "type":"Services"
        },
        {
            "category":"Health Services",
            "subcategory":"Nursing And Care Facility",
            "type":"Services"
        },
        {
            "category":"Health Services",
            "subcategory":"Health Practitioner",
            "type":"Services"
        }
    ],
    "sg:phone":"+1 562 806 8766",
    "sg:postcode":"90241",
    "sg:province":"CA",
    "sg:tags":[
        "home",
        "medical",
        "eldercare-home",
        "welfare"
    ],
    "wof:name":"Extended Health Care Inc Private Duty Nurse",
    "wof:placetype":"venue"
},
  "geometry": {"coordinates":[-118.141079,33.958067],"type":"Point"}
}