{
  "type": "Feature",
  "properties": {
    "iso:country":"US",
    "sg:address":"850 San Jose Ave",
    "sg:city":"Clovis",
    "sg:classifiers":[
        {
            "category":"Retail",
            "subcategory":"Repair Shop",
            "type":"Services"
        }
    ],
    "sg:phone":"+1 559 298 8088",
    "sg:postcode":"93612",
    "sg:province":"CA",
    "sg:tags":[
        "upholsterer"
    ],
    "wof:name":"Renn Upholstery",
    "wof:placetype":"venue"
},
  "geometry": {"coordinates":[-119.696039,36.812065],"type":"Point"}
}