{
  "type": "Feature",
  "properties": {
    "addr:full":"26027 Huntington Ln Valencia CA 91355",
    "addr:housenumber":"26027",
    "addr:postcode":"91355",
    "addr:street":"Huntington Ln",
    "iso:country":"US",
    "sg:address":"26027 Huntington Ln",
    "sg:city":"Valencia",
    "sg:classifiers":[
        {
            "category":"Autos & Motor Vehicles",
            "subcategory":"Auto Supplies",
            "type":"Retail Goods"
        }
    ],
    "sg:phone":"+1 661 257 9993",
    "sg:postcode":"91355",
    "sg:province":"CA",
    "sg:tags":[
        "automobile",
        "stereo",
        "radio"
    ],
    "wof:name":"Sonic Electronix",
    "wof:placetype":"venue"
},
  "geometry": {"coordinates":[-118.59087700000001,34.436929],"type":"Point"}
}