{
  "type": "Feature",
  "properties": {
    "iso:country":"US",
    "sg:address":"3908 E Slauson Ave",
    "sg:city":"Maywood",
    "sg:classifiers":[
        {
            "category":"Manufacturing",
            "subcategory":"Tools & Machinery",
            "type":"Manufacturing & Wholesale Goods"
        }
    ],
    "sg:phone":"+1 323 589 3178",
    "sg:postcode":"90270",
    "sg:province":"CA",
    "sg:tags":[
        "body",
        "automobile",
        "shop",
        "equipment"
    ],
    "wof:name":"Omega Auto Exchange",
    "wof:placetype":"venue"
},
  "geometry": {"coordinates":[-118.19538,33.988098],"type":"Point"}
}