{
  "type": "Feature",
  "properties": {
    "iso:country":"US",
    "sg:address":"4980 Hillsdale Cir",
    "sg:city":"El Dorado Hills",
    "sg:classifiers":[
        {
            "category":"Manufacturing",
            "subcategory":"Electronics",
            "type":"Manufacturing & Wholesale Goods"
        }
    ],
    "sg:phone":"+1 916 933 1033",
    "sg:postcode":"95762",
    "sg:province":"CA",
    "sg:tags":[
        "devices",
        "mfg"
    ],
    "wof:name":"Atmel Corporation",
    "wof:placetype":"venue"
},
  "geometry": {"coordinates":[-121.062068,38.625038],"type":"Point"}
}