{
  "type": "Feature",
  "properties": {
    "iso:country":"US",
    "sg:address":"450 Geary St",
    "sg:city":"San Francisco",
    "sg:classifiers":[
        {
            "category":"Shopping",
            "type":"Retail Goods"
        }
    ],
    "sg:phone":"+1 415 440 1627",
    "sg:postcode":"94102",
    "sg:province":"CA",
    "sg:tags":[
        "picture"
    ],
    "wof:name":"Bella Pictures Inc",
    "wof:placetype":"venue"
},
  "geometry": {"coordinates":[-122.410881,37.787102],"type":"Point"}
}