{
  "type": "Feature",
  "properties": {
    "addr:full":"1100 E Green St Pasadena CA 91105",
    "addr:housenumber":"1100",
    "addr:postcode":"91105",
    "addr:street":"E Green St",
    "iso:country":"US",
    "sg:address":"1100 E Green St",
    "sg:city":"Pasadena",
    "sg:classifiers":[
        {
            "category":"Professional",
            "subcategory":"Lawyer & Legal Services",
            "type":"Services"
        }
    ],
    "sg:phone":"+1 626 793 3949",
    "sg:postcode":"91105",
    "sg:province":"CA",
    "sg:tags":[
        "attorney"
    ],
    "wof:name":"Matthew L Bartholomew Law Ofcs",
    "wof:placetype":"venue"
},
  "geometry": {"coordinates":[-118.126152,34.144522],"type":"Point"}
}