{
  "type": "Feature",
  "properties": {
    "addr:full":"730 Polhemus Rd San Mateo CA 94402",
    "addr:housenumber":"730",
    "addr:postcode":"94402",
    "addr:street":"Polhemus Rd",
    "iso:country":"US",
    "sg:address":"730 Polhemus Rd",
    "sg:city":"San Mateo",
    "sg:classifiers":[
        {
            "category":"Wholesale",
            "subcategory":"Machinery & Supplies",
            "type":"Manufacturing & Wholesale Goods"
        }
    ],
    "sg:phone":"+1 650 572 0106",
    "sg:postcode":"94402",
    "sg:province":"CA",
    "sg:tags":[
        "product",
        "printing",
        "representative"
    ],
    "wof:name":"Impressions",
    "wof:placetype":"venue"
},
  "geometry": {"coordinates":[-122.336477,37.518403],"type":"Point"}
}