{
  "type": "Feature",
  "properties": {
    "addr:full":"9463 N Garden Ave Wshington Rd102 Ste 102 Fresno CA 93720",
    "addr:housenumber":"9463;ste 102",
    "addr:postcode":"rd102;93720",
    "addr:street":"N Garden Ave",
    "iso:country":"US",
    "sg:address":"9463 N Garden Ave Wshington Rd102 Ste 102",
    "sg:city":"Fresno",
    "sg:classifiers":[
        {
            "category":"Shopping",
            "subcategory":"Clothing, Apparel, & Fashions",
            "type":"Retail Goods"
        }
    ],
    "sg:phone":"+1 559 434 4114",
    "sg:postcode":"93720",
    "sg:province":"CA",
    "sg:tags":[
        "apparel",
        "accessory",
        "women's"
    ],
    "wof:name":"She She",
    "wof:placetype":"venue"
},
  "geometry": {"coordinates":[-119.73687200000001,36.872495],"type":"Point"}
}