{
  "type": "Feature",
  "properties": {
    "addr:full":"1450 Ghione Dr Hollister CA 95023",
    "addr:housenumber":"1450",
    "addr:postcode":"hollister ca 95023",
    "addr:street":"Ghione Dr",
    "iso:country":"US",
    "sg:address":"1450 Ghione Dr",
    "sg:city":"Hollister",
    "sg:classifiers":[
        {
            "category":"Building & Trades",
            "subcategory":"Construction",
            "type":"Services"
        }
    ],
    "sg:phone":"+1 831 637 6552",
    "sg:postcode":"95023",
    "sg:province":"CA",
    "wof:name":"Advantage Building Systems",
    "wof:placetype":"venue"
},
  "geometry": {"coordinates":[-121.37655599999999,36.831403],"type":"Point"}
}