{
  "type": "Feature",
  "properties": {
    "addr:full":"328 Virginia Ave San Francisco CA 94110",
    "addr:housenumber":"328",
    "addr:postcode":"94110",
    "addr:street":"Virginia Ave",
    "iso:country":"US",
    "sg:address":"328 Virginia Ave",
    "sg:city":"San Francisco",
    "sg:classifiers":[
        {
            "category":"Professional",
            "subcategory":"Management & Consulting",
            "type":"Services"
        }
    ],
    "sg:phone":"+1 415 824 1650",
    "sg:postcode":"94110",
    "sg:province":"CA",
    "sg:tags":[
        "consultant",
        "business"
    ],
    "wof:name":"Affirmative Human Design",
    "wof:placetype":"venue"
},
  "geometry": {"coordinates":[-122.41882200000001,37.741472],"type":"Point"}
}