{
  "type": "Feature",
  "properties": {
    "addr:full":"43334 Bryant St Fremont CA 94539",
    "addr:housenumber":"43334",
    "addr:postcode":"94539",
    "addr:street":"Bryant St",
    "iso:country":"US",
    "sg:address":"43334 Bryant St",
    "sg:city":"Fremont",
    "sg:classifiers":[
        {
            "category":"Education",
            "subcategory":"Special Training",
            "type":"Public Place"
        }
    ],
    "sg:phone":"+1 510 687 0193",
    "sg:postcode":"94539",
    "sg:province":"CA",
    "sg:tags":[
        "tutoring"
    ],
    "wof:name":"Kumon Learning Ctr",
    "wof:placetype":"venue"
},
  "geometry": {"coordinates":[-121.922428,37.531951],"type":"Point"}
}