{
  "type": "Feature",
  "properties": {
    "addr:full":"2017 Oceanside Blvd Ste A Oceanside CA 92054",
    "addr:housenumber":"2017",
    "addr:postcode":"92054",
    "addr:street":"Oceanside Blvd Ste A",
    "iso:country":"US",
    "sg:address":"2017 Oceanside Blvd Ste A",
    "sg:city":"Oceanside",
    "sg:classifiers":[
        {
            "category":"Government",
            "subcategory":"Office",
            "type":"Public Place"
        }
    ],
    "sg:phone":"+1 888 461 2429",
    "sg:postcode":"92054",
    "sg:province":"CA",
    "sg:tags":[
        "smog",
        "check"
    ],
    "wof:name":"Oceanside Test Only Smog",
    "wof:placetype":"venue"
},
  "geometry": {"coordinates":[-117.35180699999999,33.196031],"type":"Point"}
}