{
  "type": "Feature",
  "properties": {
    "iso:country":"US",
    "sg:address":"2017 N Gateway Blvd",
    "sg:city":"Fresno",
    "sg:classifiers":[
        {
            "category":"Wholesale",
            "subcategory":"Toys & Hobbies",
            "type":"Manufacturing & Wholesale Goods"
        }
    ],
    "sg:phone":"+1 559 256 1560",
    "sg:postcode":"93727",
    "sg:province":"CA",
    "sg:tags":[
        "wholesaler"
    ],
    "wof:name":"International Wholesale Brkrg",
    "wof:placetype":"venue"
},
  "geometry": {"coordinates":[-119.726832,36.767328],"type":"Point"}
}