{
  "type": "Feature",
  "properties": {
    "addr:full":"918 Soule St West Sacramento CA 95691",
    "addr:housenumber":"918",
    "addr:postcode":"95691",
    "addr:street":"Soule St",
    "iso:country":"US",
    "sg:address":"918 Soule St",
    "sg:city":"West Sacramento",
    "sg:classifiers":[
        {
            "category":"Personal",
            "type":"Services"
        }
    ],
    "sg:phone":"+1 530 753 2723",
    "sg:postcode":"95691",
    "sg:province":"CA",
    "sg:tags":[
        "towing"
    ],
    "wof:name":"H & R Towing",
    "wof:placetype":"venue"
},
  "geometry": {"coordinates":[-121.522003,38.575401],"type":"Point"}
}