{
  "type": "Feature",
  "properties": {
    "iso:country":"US",
    "sg:address":"30 Liberty Ship Way",
    "sg:city":"Sausalito",
    "sg:classifiers":[
        {
            "category":"Manufacturing",
            "subcategory":"Wood Products",
            "type":"Manufacturing & Wholesale Goods"
        }
    ],
    "sg:phone":"+1 415 331 2769",
    "sg:postcode":"94965",
    "sg:province":"CA",
    "sg:tags":[
        "manufacturer"
    ],
    "wof:name":"Martinelli Woodworking",
    "wof:placetype":"venue"
},
  "geometry": {"coordinates":[-122.494106,37.862637],"type":"Point"}
}