{
  "type": "Feature",
  "properties": {
    "addr:full":"3061 Lake County Hwy Calistoga CA 94515",
    "addr:housenumber":"3061",
    "addr:postcode":"94515",
    "addr:street":"Lake County Hwy",
    "iso:country":"US",
    "sg:address":"3061 Lake County Hwy",
    "sg:city":"Calistoga",
    "sg:classifiers":[
        {
            "category":"Farming",
            "subcategory":"Vineyard",
            "type":"Manufacturing & Wholesale Goods"
        }
    ],
    "sg:phone":"+1 707 942 4491",
    "sg:postcode":"94515",
    "sg:province":"CA",
    "sg:tags":[
        "grape"
    ],
    "wof:name":"Tolbert Family Vineyards",
    "wof:placetype":"venue"
},
  "geometry": {"coordinates":[-122.588067,38.602969],"type":"Point"}
}