{
  "type": "Feature",
  "properties": {
    "addr:full":"2275 Burning Tree Dr Corona CA 92882",
    "addr:housenumber":"2275",
    "addr:postcode":"92882",
    "addr:street":"Burning Tree Dr",
    "iso:country":"US",
    "sg:address":"2275 Burning Tree Dr",
    "sg:city":"Corona",
    "sg:classifiers":[
        {
            "category":"Wholesale",
            "subcategory":"Sporting Goods",
            "type":"Manufacturing & Wholesale Goods"
        }
    ],
    "sg:phone":"+1 951 273 9706",
    "sg:postcode":"92882",
    "sg:province":"CA",
    "sg:tags":[
        "distributor",
        "boat"
    ],
    "wof:name":"Novurania Of America",
    "wof:placetype":"venue"
},
  "geometry": {"coordinates":[-117.613733,33.873649],"type":"Point"}
}