{
  "type": "Feature",
  "properties": {
    "iso:country":"US",
    "sg:address":"5335 W Rosamond Blvd",
    "sg:city":"Rosamond",
    "sg:classifiers":[
        {
            "category":"Real Estate",
            "subcategory":"Real Estate Operator",
            "type":"Services"
        }
    ],
    "sg:phone":"+1 661 256 2616",
    "sg:postcode":"93560",
    "sg:province":"CA",
    "sg:tags":[
        "mobile",
        "home",
        "site",
        "special"
    ],
    "wof:name":"Shady Grove Mobile Home Park",
    "wof:placetype":"venue"
},
  "geometry": {"coordinates":[-118.226114,34.863901],"type":"Point"}
}