{
  "type": "Feature",
  "properties": {
    "iso:country":"US",
    "sg:address":"4910 Van Nuys Blvd Ste 307",
    "sg:city":"Sherman Oaks",
    "sg:classifiers":[
        {
            "category":"Health Services",
            "subcategory":"Doctor",
            "type":"Services"
        }
    ],
    "sg:phone":"+1 818 906 2354",
    "sg:postcode":"91403",
    "sg:province":"CA",
    "sg:tags":[
        "podiatrist"
    ],
    "wof:name":"Rick Tucker DPM",
    "wof:placetype":"venue"
},
  "geometry": {"coordinates":[-118.44797800000001,34.15959],"type":"Point"}
}