{
  "type": "Feature",
  "properties": {
    "addr:full":"714 N Glendale Ave Glendale CA 91206",
    "addr:housenumber":"714",
    "addr:postcode":"91206",
    "addr:street":"N Glendale Ave",
    "iso:country":"US",
    "sg:address":"714 N Glendale Ave",
    "sg:city":"Glendale",
    "sg:classifiers":[
        {
            "category":"Shopping",
            "subcategory":"Jewelry",
            "type":"Retail Goods"
        }
    ],
    "sg:phone":"+1 818 247 8515",
    "sg:postcode":"91206",
    "sg:province":"CA",
    "wof:name":"Little Switzerland Jeweler the",
    "wof:placetype":"venue"
},
  "geometry": {"coordinates":[-118.241997,34.1562],"type":"Point"}
}