{
  "type": "Feature",
  "properties": {
    "addr:full":"1220 Bennett Way Templeton CA 93465",
    "addr:housenumber":"1220",
    "addr:postcode":"93465",
    "addr:street":"Bennett Way",
    "iso:country":"US",
    "sg:address":"1220 Bennett Way",
    "sg:city":"Templeton",
    "sg:classifiers":[
        {
            "category":"Real Estate",
            "subcategory":"Real Estate Operator",
            "type":"Services"
        }
    ],
    "sg:phone":"+1 805 434 1579",
    "sg:postcode":"93465",
    "sg:province":"CA",
    "sg:tags":[
        "mobile",
        "home",
        "community"
    ],
    "wof:name":"Meadowbrook",
    "wof:placetype":"venue"
},
  "geometry": {"coordinates":[-120.71804400000001,35.540114],"type":"Point"}
}