{
  "type": "Feature",
  "properties": {
    "iso:country":"US",
    "sg:address":"1630 Oakland Rd",
    "sg:city":"San Jose",
    "sg:classifiers":[
        {
            "category":"Autos & Motor Vehicles",
            "subcategory":"Auto Supplies",
            "type":"Retail Goods"
        },
        {
            "category":"Wholesale",
            "subcategory":"Auto Parts",
            "type":"Manufacturing & Wholesale Goods"
        }
    ],
    "sg:phone":"+1 408 441 8562",
    "sg:postcode":"95131",
    "sg:province":"CA",
    "sg:tags":[
        "equipment",
        "automotive",
        "racing",
        "car",
        "automobile"
    ],
    "wof:name":"Geo Enterprises",
    "wof:placetype":"venue"
},
  "geometry": {"coordinates":[-121.895541,37.378775],"type":"Point"}
}