{
  "type": "Feature",
  "properties": {
    "addr:full":"415 Southwind Dr El Centro CA 92243",
    "addr:housenumber":"415",
    "addr:postcode":"92243",
    "addr:street":"Southwind Dr",
    "iso:country":"US",
    "sg:address":"415 Southwind Dr",
    "sg:city":"El Centro",
    "sg:classifiers":[
        {
            "category":"Recreation",
            "type":"Entertainment"
        }
    ],
    "sg:phone":"+1 760 353 0225",
    "sg:postcode":"92243",
    "sg:province":"CA",
    "sg:tags":[
        "martial",
        "arts",
        "instruction"
    ],
    "wof:name":"Southwestern Association",
    "wof:placetype":"venue"
},
  "geometry": {"coordinates":[-115.55419000000001,32.774556],"type":"Point"}
}