{
  "type": "Feature",
  "properties": {
    "addr:full":"657 Saint George Rd Danville CA 94526",
    "addr:housenumber":"657",
    "addr:postcode":"94526",
    "addr:street":"Saint George Rd",
    "iso:country":"US",
    "sg:address":"657 Saint George Rd",
    "sg:city":"Danville",
    "sg:classifiers":[
        {
            "category":"Professional",
            "subcategory":"Engineering",
            "type":"Services"
        }
    ],
    "sg:phone":"+1 925 743 4010",
    "sg:postcode":"94526",
    "sg:province":"CA",
    "sg:tags":[
        "engineer"
    ],
    "wof:name":"John Campbell & Assoc",
    "wof:placetype":"venue"
},
  "geometry": {"coordinates":[-121.96096,37.792351],"type":"Point"}
}