{
  "type": "Feature",
  "properties": {
    "iso:country":"US",
    "sg:address":"2254 S Euclid Ave",
    "sg:city":"Ontario",
    "sg:classifiers":[
        {
            "category":"Restaurant",
            "type":"Food & Drink"
        }
    ],
    "sg:phone":"+1 909 986 3511",
    "sg:postcode":"91762",
    "sg:province":"CA",
    "sg:tags":[
        "pizza"
    ],
    "wof:name":"Giovanni's Pizza",
    "wof:placetype":"venue"
},
  "geometry": {"coordinates":[-117.650925,34.031834],"type":"Point"}
}