{
  "type": "Feature",
  "properties": {
    "iso:country":"US",
    "sg:address":"8288 Santa Monica Blvd",
    "sg:city":"West Hollywood",
    "sg:classifiers":[
        {
            "category":"Arts & Performance",
            "subcategory":"Arts Center",
            "type":"Entertainment"
        }
    ],
    "sg:phone":"+1 323 654 3800",
    "sg:postcode":"90046",
    "sg:province":"CA",
    "sg:tags":[
        "performing"
    ],
    "sg:website":"hamburgermarysweho.com",
    "wof:name":"Follies Burgere @ Hamburger Mary's",
    "wof:placetype":"venue"
},
  "geometry": {"coordinates":[-118.370035,34.090691],"type":"Point"}
}