{
  "type": "Feature",
  "properties": {
    "addr:full":"1200 S Main St Templeton CA 93465",
    "addr:housenumber":"1200",
    "addr:postcode":"93465",
    "addr:street":"S Main St",
    "iso:country":"US",
    "sg:address":"1200 S Main St",
    "sg:city":"Templeton",
    "sg:classifiers":[
        {
            "category":"Education",
            "subcategory":"School",
            "type":"Public Place"
        }
    ],
    "sg:phone":"+1 805 434 5888",
    "sg:postcode":"93465",
    "sg:province":"CA",
    "sg:tags":[
        "high"
    ],
    "sg:website":"http://www.tusdnet.k12.ca.us",
    "wof:name":"Templeton High School",
    "wof:placetype":"venue"
},
  "geometry": {"coordinates":[-120.71072599999999,35.540592],"type":"Point"}
}