{
  "type": "Feature",
  "properties": {
    "iso:country":"US",
    "sg:address":"1269 W Lindmore St",
    "sg:city":"Lindsay",
    "sg:classifiers":[
        {
            "category":"Freight",
            "type":"Transportation"
        }
    ],
    "sg:phone":"+1 559 562 5646",
    "sg:postcode":"93247",
    "sg:province":"CA",
    "sg:tags":[
        "trucking"
    ],
    "wof:name":"Wuacho Trucking",
    "wof:placetype":"venue"
},
  "geometry": {"coordinates":[-119.11101600000001,36.196222],"type":"Point"}
}