{
  "type": "Feature",
  "properties": {
    "iso:country":"US",
    "sg:address":"3461 Castro Valley Blvd",
    "sg:city":"Castro Valley",
    "sg:classifiers":[
        {
            "category":"Building & Trades",
            "subcategory":"Pest Control",
            "type":"Services"
        }
    ],
    "sg:phone":"+1 510 889 9095",
    "sg:postcode":"94546",
    "sg:province":"CA",
    "wof:name":"Liberty Pest Control",
    "wof:placetype":"venue"
},
  "geometry": {"coordinates":[-122.075249,37.695591],"type":"Point"}
}