{
  "type": "Feature",
  "properties": {
    "addr:full":"900 Marina Bay Pkwy Richmond CA 94804",
    "addr:housenumber":"900",
    "addr:postcode":"94804",
    "addr:street":"Marina Bay Pkwy",
    "iso:country":"US",
    "sg:address":"900 Marina Bay Pkwy",
    "sg:city":"Richmond",
    "sg:classifiers":[
        {
            "category":"Wholesale",
            "subcategory":"Seafood",
            "type":"Manufacturing & Wholesale Goods"
        }
    ],
    "sg:phone":"+1 510 233 9970",
    "sg:postcode":"94804",
    "sg:province":"CA",
    "wof:name":"Dreisbach Fish",
    "wof:placetype":"venue"
},
  "geometry": {"coordinates":[-122.344182,37.918661],"type":"Point"}
}