{
  "type": "Feature",
  "properties": {
    "addr:full":"3168 Riverside Boulevard Sacramento CA 95818",
    "addr:housenumber":"3168",
    "addr:postcode":"95818",
    "addr:street":"Riverside Boulevard",
    "iso:country":"US",
    "sg:address":"3168 Riverside Boulevard",
    "sg:city":"Sacramento",
    "sg:classifiers":[
        {
            "category":"Retail",
            "subcategory":"Repair Shop",
            "type":"Services"
        },
        {
            "category":"Home & Garden",
            "subcategory":"Furniture",
            "type":"Retail Goods"
        }
    ],
    "sg:phone":"+1 916 448 2829",
    "sg:postcode":"95818",
    "sg:province":"CA",
    "sg:tags":[
        "reupholstery",
        "store"
    ],
    "wof:name":"Shannon's House",
    "wof:placetype":"venue"
},
  "geometry": {"coordinates":[-121.50577800000001,38.550682],"type":"Point"}
}