{
  "type": "Feature",
  "properties": {
    "addr:full":"29565 Ruus Rd Hayward CA 94544",
    "addr:postcode":"29565;94544",
    "addr:street":"Ruus Rd",
    "iso:country":"US",
    "sg:address":"29565 Ruus Rd",
    "sg:city":"Hayward",
    "sg:classifiers":[
        {
            "category":"Retail",
            "subcategory":"Auto Repair",
            "type":"Services"
        }
    ],
    "sg:phone":"+1 510 783 4765",
    "sg:postcode":"94544",
    "sg:province":"CA",
    "sg:tags":[
        "body",
        "shop",
        "painting",
        "automobile"
    ],
    "sg:website":"www.jandbautobody.com",
    "wof:name":"ASM Auto Body & Repair",
    "wof:placetype":"venue"
},
  "geometry": {"coordinates":[-122.062659,37.618744],"type":"Point"}
}