{
  "type": "Feature",
  "properties": {
    "addr:full":"501 Soquel Avenue Suite A Santa Cruz CA 95062",
    "addr:housenumber":"501",
    "addr:postcode":"95062",
    "addr:street":"Soquel Avenue Suite A",
    "iso:country":"US",
    "sg:address":"501 Soquel Avenue Suite A",
    "sg:city":"Santa Cruz",
    "sg:classifiers":[
        {
            "category":"Retail",
            "subcategory":"Auto Repair",
            "type":"Services"
        }
    ],
    "sg:phone":"+1 831 426 5839",
    "sg:postcode":"95062",
    "sg:province":"CA",
    "wof:name":"Jim Ludy's Automotive Maintenance",
    "wof:placetype":"venue"
},
  "geometry": {"coordinates":[-122.01804799999999,36.975132],"type":"Point"}
}