{
  "type": "Feature",
  "properties": {
    "iso:country":"US",
    "sg:address":"3126 University Ave",
    "sg:city":"San Diego",
    "sg:classifiers":[
        {
            "category":"Shopping",
            "subcategory":"Clothing, Apparel, & Fashions",
            "type":"Retail Goods"
        }
    ],
    "sg:phone":"+1 619 282 8350",
    "sg:postcode":"92104",
    "sg:province":"CA",
    "sg:tags":[
        "sewing",
        "alteration"
    ],
    "wof:name":"Rosas Tailoring Shop",
    "wof:placetype":"venue"
},
  "geometry": {"coordinates":[-117.126999,32.748402],"type":"Point"}
}