{
  "type": "Feature",
  "properties": {
    "iso:country":"US",
    "sg:address":"50 Powell St",
    "sg:city":"San Francisco",
    "sg:classifiers":[
        {
            "category":"Utilities",
            "subcategory":"Mobile Phone",
            "type":"Services"
        }
    ],
    "sg:phone":"+1 415 391 4623",
    "sg:postcode":"94102",
    "sg:province":"CA",
    "sg:tags":[
        "telephone",
        "cellular"
    ],
    "wof:name":"T Mobile Powell & Market",
    "wof:placetype":"venue"
},
  "geometry": {"coordinates":[-122.407718,37.785106],"type":"Point"}
}