{
  "type": "Feature",
  "properties": {
    "iso:country":"US",
    "sg:address":"679 S Santa Fe Ave",
    "sg:city":"Los Angeles",
    "sg:classifiers":[
        {
            "category":"Wholesale",
            "subcategory":"Apparel",
            "type":"Manufacturing & Wholesale Goods"
        },
        {
            "category":"Manufacturing",
            "subcategory":"Textiles",
            "type":"Manufacturing & Wholesale Goods"
        }
    ],
    "sg:phone":"+1 213 627 6116",
    "sg:postcode":"90021",
    "sg:province":"CA",
    "sg:tags":[
        "mill",
        "narrow",
        "dress",
        "fabric",
        "trimmings"
    ],
    "wof:name":"Artisan To Lace N Trim",
    "wof:placetype":"venue"
},
  "geometry": {"coordinates":[-118.23025800000001,34.03561],"type":"Point"}
}