{
  "type": "Feature",
  "properties": {
    "addr:full":"6000 Main St Clayton CA 94517",
    "addr:housenumber":"6000",
    "addr:postcode":"94517",
    "addr:street":"Main St",
    "iso:country":"US",
    "sg:address":"6000 Main St",
    "sg:city":"Clayton",
    "sg:classifiers":[
        {
            "category":"Personal",
            "subcategory":"Beauty Salon",
            "type":"Services"
        },
        {
            "category":"Personal",
            "subcategory":"Barber",
            "type":"Services"
        }
    ],
    "sg:phone":"+1 925 672 0516",
    "sg:postcode":"94517",
    "sg:province":"CA",
    "sg:tags":[
        "hair",
        "stylist"
    ],
    "wof:name":"Hair By David Wall",
    "wof:placetype":"venue"
},
  "geometry": {"coordinates":[-121.93673699999999,37.941231],"type":"Point"}
}