{
  "type": "Feature",
  "properties": {
    "iso:country":"US",
    "sg:address":"2362 Mimosa Ave",
    "sg:city":"Hemet",
    "sg:classifiers":[
        {
            "category":"Building & Trades",
            "subcategory":"Construction",
            "type":"Services"
        }
    ],
    "sg:phone":"+1 951 652 2121",
    "sg:postcode":"92545",
    "sg:province":"CA",
    "sg:tags":[
        "contractor"
    ],
    "wof:name":"Avaco Construction Inc",
    "wof:placetype":"venue"
},
  "geometry": {"coordinates":[-116.994967,33.735446],"type":"Point"}
}