{
  "type": "Feature",
  "properties": {
    "iso:country":"US",
    "sg:address":"2160 Redwood Hwy",
    "sg:city":"Greenbrae",
    "sg:classifiers":[
        {
            "category":"Freight",
            "type":"Transportation"
        }
    ],
    "sg:phone":"+1 415 925 0138",
    "sg:postcode":"94904",
    "sg:province":"CA",
    "sg:tags":[
        "general"
    ],
    "wof:name":"Larkspur Storage",
    "wof:placetype":"venue"
},
  "geometry": {"coordinates":[-122.514363,37.942737],"type":"Point"}
}