{
  "type": "Feature",
  "properties": {
    "iso:country":"US",
    "sg:address":"924 E Central Ave",
    "sg:city":"Redlands",
    "sg:classifiers":[
        {
            "category":"Building & Trades",
            "subcategory":"Construction",
            "type":"Services"
        }
    ],
    "sg:phone":"+1 951 906 4789",
    "sg:postcode":"92374",
    "sg:province":"CA",
    "sg:tags":[
        "carpenter"
    ],
    "wof:name":"K C Co",
    "wof:placetype":"venue"
},
  "geometry": {"coordinates":[-117.172179,34.057278],"type":"Point"}
}