{
  "type": "Feature",
  "properties": {
    "addr:full":"1128 E 4th St Apt 110 Long Beach CA 90802",
    "addr:housenumber":"1128;110",
    "addr:postcode":"90802",
    "addr:street":"E 4Th St Apt",
    "iso:country":"US",
    "sg:address":"1128 E 4th St Apt 110",
    "sg:city":"Long Beach",
    "sg:classifiers":[
        {
            "category":"Real Estate",
            "subcategory":"Real Estate Operator",
            "type":"Services"
        }
    ],
    "sg:phone":"+1 562 435 3498",
    "sg:postcode":"90802",
    "sg:province":"CA",
    "sg:tags":[
        "apartment"
    ],
    "sg:website":"www.magnoliamanor.com",
    "wof:name":"Magnolia Manor",
    "wof:placetype":"venue"
},
  "geometry": {"coordinates":[-118.183998,33.7705],"type":"Point"}
}