{
  "type": "Feature",
  "properties": {
    "addr:full":"1225 E Glenwood Place Santa Ana CA 92707",
    "addr:housenumber":"1225",
    "addr:postcode":"92707",
    "addr:street":"E Glenwood Place",
    "iso:country":"US",
    "sg:address":"1225 E Glenwood Place",
    "sg:city":"Santa Ana",
    "sg:classifiers":[
        {
            "category":"Professional",
            "subcategory":"Art Services",
            "type":"Services"
        }
    ],
    "sg:phone":"+1 213 675 1720",
    "sg:postcode":"92707",
    "sg:province":"CA",
    "sg:tags":[
        "graphic",
        "design"
    ],
    "sg:website":"www.orangecountyscreenprinting.com",
    "wof:name":"Fresh Ink Screenprinting",
    "wof:placetype":"venue"
},
  "geometry": {"coordinates":[-117.855268,33.721875],"type":"Point"}
}