{
  "type": "Feature",
  "properties": {
    "iso:country":"US",
    "sg:address":"1124 Cleghorn Dr",
    "sg:city":"Diamond Bar",
    "sg:classifiers":[
        {
            "category":"Building & Trades",
            "subcategory":"Construction",
            "type":"Services"
        }
    ],
    "sg:phone":"+1 909 861 5440",
    "sg:postcode":"91765",
    "sg:province":"CA",
    "sg:tags":[
        "painter"
    ],
    "wof:name":"Gailon Painting & Wall",
    "wof:placetype":"venue"
},
  "geometry": {"coordinates":[-117.80787599999999,34.001779],"type":"Point"}
}