{
  "type": "Feature",
  "properties": {
    "iso:country":"US",
    "sg:address":"Westfield Promenade At Woodland Hills 6100 Topanga Canyon Blvd",
    "sg:city":"Woodland Hills",
    "sg:classifiers":[
        {
            "category":"Coffee & Tea",
            "type":"Food & Drink"
        }
    ],
    "sg:postcode":"91367",
    "sg:province":"CA",
    "sg:website":"www.coraltreecafe.net/",
    "wof:name":"Coral Tree Express",
    "wof:placetype":"venue"
},
  "geometry": {"coordinates":[-118.60580400000001,34.180599],"type":"Point"}
}