{
  "type": "Feature",
  "properties": {
    "addr:full":"1989 Santa Rita Rd Pleasanton CA 94566",
    "addr:housenumber":"1989",
    "addr:postcode":"94566",
    "addr:street":"Santa Rita Rd",
    "iso:country":"US",
    "sg:address":"1989 Santa Rita Rd",
    "sg:city":"Pleasanton",
    "sg:classifiers":[
        {
            "category":"Personal",
            "type":"Services"
        }
    ],
    "sg:phone":"+1 925 462 3889",
    "sg:postcode":"94566",
    "sg:province":"CA",
    "sg:tags":[
        "therapist",
        "massage"
    ],
    "wof:name":"Lois Perryman",
    "wof:placetype":"venue"
},
  "geometry": {"coordinates":[-121.874786,37.678545],"type":"Point"}
}