{
  "type": "Feature",
  "properties": {
    "iso:country":"US",
    "sg:address":"3637 San Marco Dr",
    "sg:city":"Stockton",
    "sg:classifiers":[
        {
            "category":"Real Estate",
            "subcategory":"Real Estate Agent",
            "type":"Services"
        }
    ],
    "sg:phone":"+1 209 477 1054",
    "sg:postcode":"95212",
    "sg:province":"CA",
    "wof:name":"Matisse At Lawmorada",
    "wof:placetype":"venue"
},
  "geometry": {"coordinates":[-121.265851,38.03828],"type":"Point"}
}