{
  "type": "Feature",
  "properties": {
    "addr:full":"730 Story Rd San Jose CA 95122",
    "addr:housenumber":"730",
    "addr:postcode":"95122",
    "addr:street":"Story Rd",
    "iso:country":"US",
    "sg:address":"730 Story Rd",
    "sg:city":"San Jose",
    "sg:classifiers":[
        {
            "category":"Insurance",
            "subcategory":"Insurance Agent",
            "type":"Services"
        }
    ],
    "sg:phone":"+1 408 925 0210",
    "sg:postcode":"95122",
    "sg:province":"CA",
    "wof:name":"Allstate Insurance",
    "wof:placetype":"venue"
},
  "geometry": {"coordinates":[-121.864655,37.32606],"type":"Point"}
}