{
  "type": "Feature",
  "properties": {
    "iso:country":"US",
    "sg:address":"8630-A Brentwood Blvd",
    "sg:city":"Brentwood",
    "sg:classifiers":[
        {
            "category":"Juice Bar",
            "subcategory":"None",
            "type":"Food & Drink"
        }
    ],
    "sg:phone":"+1 925 240 2999",
    "sg:postcode":"94513",
    "sg:province":"CA",
    "sg:tags":[
        "smoothy"
    ],
    "sg:website":"www.jambajuice.com",
    "wof:name":"Jamba Juice",
    "wof:placetype":"venue"
},
  "geometry": {"coordinates":[-121.691275,37.926332],"type":"Point"}
}