{
  "type": "Feature",
  "properties": {
    "addr:full":"1297 E Calaveras Blvd Milpitas CA 95035",
    "addr:housenumber":"1297",
    "addr:postcode":"95035",
    "addr:street":"E Calaveras Blvd",
    "iso:country":"US",
    "sg:address":"1297 E Calaveras Blvd",
    "sg:city":"Milpitas",
    "sg:classifiers":[
        {
            "category":"Banks & Credit Unions",
            "subcategory":"Bank",
            "type":"Services"
        }
    ],
    "sg:phone":"+1 408 586 6160",
    "sg:postcode":"95035",
    "sg:province":"CA",
    "sg:website":"www.wamu.com",
    "wof:name":"Washington Mutual Bank",
    "wof:placetype":"venue"
},
  "geometry": {"coordinates":[-121.884491,37.435638],"type":"Point"}
}