{
  "type": "Feature",
  "properties": {
    "iso:country":"US",
    "sg:address":"2817 E Barkley Ave",
    "sg:city":"Orange",
    "sg:classifiers":[
        {
            "category":"Professional",
            "subcategory":"Business Services",
            "type":"Services"
        }
    ],
    "sg:phone":"+1 714 639 3131",
    "sg:postcode":"92867",
    "sg:province":"CA",
    "wof:name":"Roys Micro Design",
    "wof:placetype":"venue"
},
  "geometry": {"coordinates":[-117.823778,33.801644],"type":"Point"}
}