{
  "type": "Feature",
  "properties": {
    "addr:full":"27128 Pso Espada San Juan Capistrano CA 92675",
    "addr:postcode":"27128;92675",
    "addr:street":"Espada",
    "iso:country":"US",
    "sg:address":"27128 Pso Espada",
    "sg:city":"San Juan Capistrano",
    "sg:classifiers":[
        {
            "category":"Wholesale",
            "subcategory":"Hardware",
            "type":"Manufacturing & Wholesale Goods"
        }
    ],
    "sg:phone":"+1 949 248 7297",
    "sg:postcode":"92675",
    "sg:province":"CA",
    "sg:tags":[
        "plumbing",
        "computer"
    ],
    "wof:name":"Gonneville Inc",
    "wof:placetype":"venue"
},
  "geometry": {"coordinates":[-117.65467200000001,33.501352],"type":"Point"}
}