{
  "type": "Feature",
  "properties": {
    "addr:full":"310 Evergreen Ln Yreka CA 96097",
    "addr:housenumber":"310",
    "addr:postcode":"96097",
    "addr:street":"Evergreen Ln",
    "iso:country":"US",
    "sg:address":"310 Evergreen Ln",
    "sg:city":"Yreka",
    "sg:classifiers":[
        {
            "category":"Health Services",
            "subcategory":"Doctor",
            "type":"Services"
        }
    ],
    "sg:phone":"+1 530 842 2558",
    "sg:postcode":"96097",
    "sg:province":"CA",
    "sg:tags":[
        "dentist"
    ],
    "wof:name":"Evergreen Family Dentistry",
    "wof:placetype":"venue"
},
  "geometry": {"coordinates":[-122.64091500000001,41.725774],"type":"Point"}
}