{
  "type": "Feature",
  "properties": {
    "iso:country":"US",
    "sg:address":"610 23rd St",
    "sg:city":"Richmond",
    "sg:classifiers":[
        {
            "category":"Banks & Credit Unions",
            "subcategory":"Bank",
            "type":"Services"
        }
    ],
    "sg:phone":"+1 510 232 2300",
    "sg:postcode":"94804",
    "sg:province":"CA",
    "sg:tags":[
        "federal"
    ],
    "wof:name":"United Mtl Emplys Fdrl Crdt Un",
    "wof:placetype":"venue"
},
  "geometry": {"coordinates":[-122.347431,37.940074],"type":"Point"}
}