{
  "type": "Feature",
  "properties": {
    "iso:country":"US",
    "sg:address":"1762 W Hammer Ln",
    "sg:city":"Stockton",
    "sg:classifiers":[
        {
            "category":"Retail",
            "subcategory":"Laundry & Dry Cleaning",
            "type":"Services"
        }
    ],
    "sg:phone":"+1 209 477 4397",
    "sg:postcode":"95209",
    "sg:province":"CA",
    "sg:tags":[
        "cleaners"
    ],
    "wof:name":"Park Woods Cleaners",
    "wof:placetype":"venue"
},
  "geometry": {"coordinates":[-121.335924,38.021112],"type":"Point"}
}