{
  "type": "Feature",
  "properties": {
    "iso:country":"US",
    "sg:address":"9461 Hollister St",
    "sg:city":"Ventura",
    "sg:classifiers":[
        {
            "category":"Building & Trades",
            "subcategory":"Landscaping Services",
            "type":"Services"
        }
    ],
    "sg:phone":"+1 805 659 5742",
    "sg:postcode":"93004",
    "sg:province":"CA",
    "wof:name":"Freds Lawn Care",
    "wof:placetype":"venue"
},
  "geometry": {"coordinates":[-119.17595300000001,34.279007],"type":"Point"}
}