{
  "type": "Feature",
  "properties": {
    "addr:full":"13950 Rosecrans Ave Ste E Santa Fe Springs CA 90670",
    "addr:housenumber":"13950",
    "addr:postcode":"90670",
    "addr:street":"Rosecrans Ave Ste E",
    "iso:country":"US",
    "sg:address":"13950 Rosecrans Ave Ste E",
    "sg:city":"Santa Fe Springs",
    "sg:classifiers":[
        {
            "category":"Personal",
            "type":"Services"
        }
    ],
    "sg:phone":"+1 562 926 4633",
    "sg:postcode":"90670",
    "sg:province":"CA",
    "sg:tags":[
        "mover"
    ],
    "wof:name":"S A M Moving Inc",
    "wof:placetype":"venue"
},
  "geometry": {"coordinates":[-118.03416,33.902352],"type":"Point"}
}