{
  "type": "Feature",
  "properties": {
    "addr:full":"5158 Cochran St Simi Valley CA 93063",
    "addr:housenumber":"5158",
    "addr:postcode":"93063",
    "addr:street":"Cochran St",
    "iso:country":"US",
    "sg:address":"5158 Cochran St",
    "sg:city":"Simi Valley",
    "sg:classifiers":[
        {
            "category":"Building & Trades",
            "subcategory":"Construction",
            "type":"Services"
        }
    ],
    "sg:phone":"+1 805 584 0364",
    "sg:postcode":"93063",
    "sg:province":"CA",
    "sg:tags":[
        "waterproofing",
        "contractor"
    ],
    "wof:name":"K C Industries",
    "wof:placetype":"venue"
},
  "geometry": {"coordinates":[-118.694141,34.278988],"type":"Point"}
}