{
  "type": "Feature",
  "properties": {
    "iso:country":"US",
    "sg:address":"1875 South Grant Street 10th Floor",
    "sg:city":"San Mateo",
    "sg:classifiers":[
        {
            "category":"Professional",
            "subcategory":"Computer Services",
            "type":"Services"
        }
    ],
    "sg:phone":"+1 650 353 4057",
    "sg:postcode":"94402",
    "sg:province":"CA",
    "sg:website":"http://www.lucidimagination.com/",
    "wof:name":"Lucid Imagination",
    "wof:placetype":"venue"
},
  "geometry": {"coordinates":[-122.30556900000001,37.559924],"type":"Point"}
}