{
  "type": "Feature",
  "properties": {
    "iso:country":"US",
    "sg:address":"759 N Mountain Ave",
    "sg:city":"Upland",
    "sg:classifiers":[
        {
            "category":"Insurance",
            "subcategory":"Insurance Agent",
            "type":"Services"
        }
    ],
    "sg:phone":"+1 909 985 8409",
    "sg:postcode":"91786",
    "sg:province":"CA",
    "wof:name":"Insurance Agency Network",
    "wof:placetype":"venue"
},
  "geometry": {"coordinates":[-117.670258,34.102493],"type":"Point"}
}