{
  "type": "Feature",
  "properties": {
    "addr:full":"2391 Arden Way Sacramento CA 95825",
    "addr:housenumber":"2391",
    "addr:postcode":"95825",
    "addr:street":"Arden Way",
    "iso:country":"US",
    "sg:address":"2391 Arden Way",
    "sg:city":"Sacramento",
    "sg:classifiers":[
        {
            "category":"Insurance",
            "subcategory":"Insurance Agent",
            "type":"Services"
        }
    ],
    "sg:phone":"+1 916 489 6507",
    "sg:postcode":"95825",
    "sg:province":"CA",
    "wof:name":"Dennis Von Brauchitsch",
    "wof:placetype":"venue"
},
  "geometry": {"coordinates":[-121.407788,38.596072],"type":"Point"}
}