{
  "type": "Feature",
  "properties": {
    "addr:full":"216 5th St Huntington Beach CA 92648",
    "addr:housenumber":"216",
    "addr:postcode":"92648",
    "addr:street":"5Th St",
    "iso:country":"US",
    "sg:address":"216 5th St",
    "sg:city":"Huntington Beach",
    "sg:classifiers":[
        {
            "category":"Professional",
            "subcategory":"Detective & Security Services",
            "type":"Services"
        },
        {
            "category":"Building & Trades",
            "subcategory":"Construction",
            "type":"Services"
        }
    ],
    "sg:phone":"+1 714 465 5324",
    "sg:postcode":"92648",
    "sg:province":"CA",
    "sg:tags":[
        "system",
        "contractor"
    ],
    "sg:website":"alarm-systems-repair.info",
    "wof:name":"American Alarm Systems",
    "wof:placetype":"venue"
},
  "geometry": {"coordinates":[-118.001385,33.659093],"type":"Point"}
}