{
  "type": "Feature",
  "properties": {
    "addr:full":"6737 Watt Ave North Highlands CA 95660",
    "addr:housenumber":"6737",
    "addr:postcode":"95660",
    "addr:street":"Watt Ave",
    "iso:country":"US",
    "sg:address":"6737 Watt Ave",
    "sg:city":"North Highlands",
    "sg:classifiers":[
        {
            "category":"Shopping",
            "subcategory":"Department Store",
            "type":"Retail Goods"
        }
    ],
    "sg:phone":"+1 916 344 2899",
    "sg:postcode":"95660",
    "sg:province":"CA",
    "sg:website":"www.rossstores.com",
    "wof:name":"Ross Dress for Less",
    "wof:placetype":"venue"
},
  "geometry": {"coordinates":[-121.383115,38.689399],"type":"Point"}
}