{
  "type": "Feature",
  "properties": {
    "iso:country":"US",
    "sg:address":"40441 Gemelos Ct",
    "sg:city":"Palmdale",
    "sg:classifiers":[
        {
            "category":"Building & Trades",
            "subcategory":"Construction",
            "type":"Services"
        }
    ],
    "sg:phone":"+1 661 943 1445",
    "sg:postcode":"93551",
    "sg:province":"CA",
    "sg:tags":[
        "heavy",
        "contractor",
        "grading"
    ],
    "wof:name":"Pepo Weed Abatement Inc",
    "wof:placetype":"venue"
},
  "geometry": {"coordinates":[-118.22159000000001,34.617032],"type":"Point"}
}