{
  "type": "Feature",
  "properties": {
    "addr:full":"2601 Fashion Pl Bakersfield CA 93306",
    "addr:housenumber":"2601",
    "addr:postcode":"93306",
    "addr:street":"Fashion Pl",
    "iso:country":"US",
    "sg:address":"2601 Fashion Pl",
    "sg:city":"Bakersfield",
    "sg:classifiers":[
        {
            "category":"Restaurant",
            "type":"Food & Drink"
        }
    ],
    "sg:menulink":"http://www.allmenus.com/ca/bakersfield/216260-mcdonalds/menu/",
    "sg:postcode":"93306",
    "sg:province":"CA",
    "sg:tags":[
        "burger",
        "american"
    ],
    "wof:name":"McDonald's",
    "wof:placetype":"venue"
},
  "geometry": {"coordinates":[-118.961265,35.391864],"type":"Point"}
}