{
  "type": "Feature",
  "properties": {
    "addr:full":"12505 Oxnard St North Hollywood CA 91606",
    "addr:housenumber":"12505",
    "addr:postcode":"91606",
    "addr:street":"Oxnard St",
    "iso:country":"US",
    "sg:address":"12505 Oxnard St",
    "sg:city":"North Hollywood",
    "sg:classifiers":[
        {
            "category":"Personal",
            "subcategory":"Beauty Salon",
            "type":"Services"
        }
    ],
    "sg:phone":"+1 818 769 0174",
    "sg:postcode":"91606",
    "sg:province":"CA",
    "wof:name":"Mari's Hair Salon",
    "wof:placetype":"venue"
},
  "geometry": {"coordinates":[-118.40705699999999,34.179481],"type":"Point"}
}