{
  "type": "Feature",
  "properties": {
    "addr:full":"1010 S Coast Highway 101 Ste 108 Encinitas CA 92024",
    "addr:housenumber":"1010",
    "addr:postcode":"92024",
    "addr:street":"S Coast Highway 101 Ste 108",
    "iso:country":"US",
    "sg:address":"1010 S Coast Highway 101 Ste 108",
    "sg:city":"Encinitas",
    "sg:classifiers":[
        {
            "category":"Building & Trades",
            "subcategory":"Construction",
            "type":"Services"
        }
    ],
    "sg:phone":"+1 760 436 3333",
    "sg:postcode":"92024",
    "sg:province":"CA",
    "sg:tags":[
        "contractor"
    ],
    "wof:name":"Tekton Master Builders",
    "wof:placetype":"venue"
},
  "geometry": {"coordinates":[-117.29336499999999,33.038956],"type":"Point"}
}