{
  "type": "Feature",
  "properties": {
    "iso:country":"US",
    "sg:address":"3625 del Amo Blvd Ste 210",
    "sg:city":"Torrance",
    "sg:classifiers":[
        {
            "category":"Wholesale",
            "subcategory":"Groceries",
            "type":"Manufacturing & Wholesale Goods"
        }
    ],
    "sg:phone":"+1 310 792 4200",
    "sg:postcode":"90503",
    "sg:province":"CA",
    "sg:tags":[
        "grocers-wholesale"
    ],
    "wof:name":"Foodlink Online",
    "wof:placetype":"venue"
},
  "geometry": {"coordinates":[-118.349693,33.848579],"type":"Point"}
}