{
  "type": "Feature",
  "properties": {
    "addr:full":"205 Maple St Santa Cruz CA 95060",
    "addr:housenumber":"205",
    "addr:postcode":"95060",
    "addr:street":"Maple St",
    "iso:country":"US",
    "sg:address":"205 Maple St",
    "sg:city":"Santa Cruz",
    "sg:classifiers":[
        {
            "category":"Manufacturing",
            "subcategory":"Jewelry",
            "type":"Manufacturing & Wholesale Goods"
        }
    ],
    "sg:phone":"+1 831 423 5780",
    "sg:postcode":"95060",
    "sg:province":"CA",
    "sg:tags":[
        "precious",
        "metal",
        "mfg"
    ],
    "wof:name":"Zoomorphic",
    "wof:placetype":"venue"
},
  "geometry": {"coordinates":[-122.02743599999999,36.969804],"type":"Point"}
}