{
  "type": "Feature",
  "properties": {
    "iso:country":"US",
    "sg:address":"5753 E Pacific Coast Hwy",
    "sg:city":"Long Beach",
    "sg:classifiers":[
        {
            "category":"Food & Beverages",
            "subcategory":"Bakery",
            "type":"Retail Goods"
        }
    ],
    "sg:phone":"+1 562 985 0933",
    "sg:postcode":"90803",
    "sg:province":"CA",
    "sg:tags":[
        "bagel"
    ],
    "wof:name":"East Coast Bagel Co",
    "wof:placetype":"venue"
},
  "geometry": {"coordinates":[-118.120003,33.773899],"type":"Point"}
}