{
  "type": "Feature",
  "properties": {
    "iso:country":"US",
    "sg:address":"1248 Thompson Ave",
    "sg:city":"Santa Cruz",
    "sg:classifiers":[
        {
            "category":"Organizations",
            "subcategory":"Professional Association",
            "type":"Services"
        }
    ],
    "sg:phone":"+1 831 476 3407",
    "sg:postcode":"95062",
    "sg:province":"CA",
    "sg:website":"www.scbuild.com",
    "wof:name":"Santa Cruz Builders Exchange",
    "wof:placetype":"venue"
},
  "geometry": {"coordinates":[-121.970878,36.969247],"type":"Point"}
}