{
  "type": "Feature",
  "properties": {
    "addr:full":"135 Townsend St San Francisco CA 94107",
    "addr:housenumber":"135",
    "addr:postcode":"94107",
    "addr:street":"Townsend St",
    "iso:country":"US",
    "sg:address":"135 Townsend St",
    "sg:city":"San Francisco",
    "sg:classifiers":[
        {
            "category":"Manufacturing",
            "subcategory":"Apparel",
            "type":"Manufacturing & Wholesale Goods"
        }
    ],
    "sg:phone":"+1 415 495 2658",
    "sg:postcode":"94107",
    "sg:province":"CA",
    "sg:tags":[
        "outerwear",
        "mfg"
    ],
    "wof:name":"Izzy Biz",
    "wof:placetype":"venue"
},
  "geometry": {"coordinates":[-122.390631,37.780509],"type":"Point"}
}