{
  "type": "Feature",
  "properties": {
    "iso:country":"US",
    "sg:address":"7120 Miramar Rd",
    "sg:city":"San Diego",
    "sg:classifiers":[
        {
            "category":"Building & Trades",
            "subcategory":"Construction",
            "type":"Services"
        }
    ],
    "sg:phone":"+1 858 271 4320",
    "sg:postcode":"92121",
    "sg:province":"CA",
    "sg:tags":[
        "concrete",
        "contractor"
    ],
    "wof:name":"Concrete Construction",
    "wof:placetype":"venue"
},
  "geometry": {"coordinates":[-117.161146,32.879458],"type":"Point"}
}