{
  "type": "Feature",
  "properties": {
    "addr:full":"699 Lewelling Blvd Ste 300 San Leandro CA 94579",
    "addr:housenumber":"699",
    "addr:postcode":"94579",
    "addr:street":"Lewelling Blvd Ste 300",
    "iso:country":"US",
    "sg:address":"699 Lewelling Blvd Ste 300",
    "sg:city":"San Leandro",
    "sg:classifiers":[
        {
            "category":"Health Services",
            "subcategory":"Dentist",
            "type":"Services"
        }
    ],
    "sg:phone":"+1 510 357 8960",
    "sg:postcode":"94579",
    "sg:province":"CA",
    "wof:name":"Sicam Loreto Jr DMD",
    "wof:placetype":"venue"
},
  "geometry": {"coordinates":[-122.139,37.686699],"type":"Point"}
}