{
  "type": "Feature",
  "properties": {
    "iso:country":"US",
    "sg:address":"9615 Cozycroft Ave",
    "sg:city":"Chatsworth",
    "sg:classifiers":[
        {
            "category":"Home & Garden",
            "subcategory":"Building Materials",
            "type":"Retail Goods"
        }
    ],
    "sg:phone":"+1 818 885 6063",
    "sg:postcode":"91311",
    "sg:province":"CA",
    "sg:tags":[
        "shutter"
    ],
    "wof:name":"Quality Shutters Finish",
    "wof:placetype":"venue"
},
  "geometry": {"coordinates":[-118.582057,34.244266],"type":"Point"}
}