{
  "type": "Feature",
  "properties": {
    "iso:country":"US",
    "sg:address":"1223 3rd Ave",
    "sg:city":"Chula Vista",
    "sg:classifiers":[
        {
            "category":"Restaurant",
            "type":"Food & Drink"
        }
    ],
    "sg:phone":"+1 619 476 0911",
    "sg:postcode":"91911",
    "sg:province":"CA",
    "sg:tags":[
        "mexican"
    ],
    "wof:name":"Maria Bonita",
    "wof:placetype":"venue"
},
  "geometry": {"coordinates":[-117.067452,32.609464],"type":"Point"}
}