{
  "type": "Feature",
  "properties": {
    "iso:country":"US",
    "sg:address":"7255 Worth Way",
    "sg:city":"Camarillo",
    "sg:classifiers":[
        {
            "category":"Food & Beverages",
            "subcategory":"Groceries & Convenience Stores",
            "type":"Retail Goods"
        }
    ],
    "sg:phone":"+1 805 386 5700",
    "sg:postcode":"93012",
    "sg:province":"CA",
    "wof:name":"Buchanan Agricultural Co",
    "wof:placetype":"venue"
},
  "geometry": {"coordinates":[-118.973705,34.251737],"type":"Point"}
}