{
  "type": "Feature",
  "properties": {
    "iso:country":"US",
    "sg:address":"333 Market St",
    "sg:city":"San Francisco",
    "sg:classifiers":[
        {
            "category":"Professional",
            "subcategory":"Business Services",
            "type":"Services"
        }
    ],
    "sg:phone":"+1 408 572 3800",
    "sg:postcode":"94105",
    "sg:province":"CA",
    "sg:tags":[
        "lecture",
        "bureau",
        "seminar"
    ],
    "wof:name":"Lenders Podium",
    "wof:placetype":"venue"
},
  "geometry": {"coordinates":[-122.397932,37.79185],"type":"Point"}
}