{
  "type": "Feature",
  "properties": {
    "iso:country":"US",
    "sg:address":"1024 Mistletoe Ln",
    "sg:city":"Redding",
    "sg:classifiers":[
        {
            "category":"Banks & Credit Unions",
            "subcategory":"Bank",
            "type":"Services"
        }
    ],
    "sg:phone":"+1 530 223 9550",
    "sg:postcode":"96002",
    "sg:province":"CA",
    "wof:name":"Bank Of Commerce Mortgage",
    "wof:placetype":"venue"
},
  "geometry": {"coordinates":[-122.352543,40.578532],"type":"Point"}
}