{
  "type": "Feature",
  "properties": {
    "addr:full":"129 N Broadway Blythe CA 92225",
    "addr:housenumber":"129",
    "addr:postcode":"92225",
    "addr:street":"N Broadway",
    "iso:country":"US",
    "sg:address":"129 N Broadway",
    "sg:city":"Blythe",
    "sg:classifiers":[
        {
            "category":"Real Estate",
            "subcategory":"Real Estate Agent",
            "type":"Services"
        }
    ],
    "sg:phone":"+1 760 922 6619",
    "sg:postcode":"92225",
    "sg:province":"CA",
    "wof:name":"Grubbs-Stake Realty",
    "wof:placetype":"venue"
},
  "geometry": {"coordinates":[-114.59688199999999,33.61075],"type":"Point"}
}