{
  "type": "Feature",
  "properties": {
    "addr:full":"10411 S San Pedro Street Los Angeles CA 90003",
    "addr:housenumber":"10411",
    "addr:postcode":"90003",
    "addr:street":"S San Pedro Street",
    "iso:country":"US",
    "sg:address":"10411 S San Pedro Street",
    "sg:city":"Los Angeles",
    "sg:classifiers":[
        {
            "category":"Home & Garden",
            "subcategory":"Hardware",
            "type":"Retail Goods"
        }
    ],
    "sg:phone":"+1 323 755 6757",
    "sg:postcode":"90003",
    "sg:province":"CA",
    "sg:tags":[
        "store"
    ],
    "sg:website":"www.truevalue.com",
    "wof:name":"Andy's True Value Hardware",
    "wof:placetype":"venue"
},
  "geometry": {"coordinates":[-118.26938699999999,33.941643],"type":"Point"}
}