{
  "type": "Feature",
  "properties": {
    "addr:full":"12211 Washington Blvd Whittier CA 90606",
    "addr:housenumber":"12211",
    "addr:postcode":"90606",
    "addr:street":"Washington Blvd",
    "iso:country":"US",
    "sg:address":"12211 Washington Blvd",
    "sg:city":"Whittier",
    "sg:classifiers":[
        {
            "category":"Recreation",
            "type":"Entertainment"
        }
    ],
    "sg:phone":"+1 310 915 1133",
    "sg:postcode":"90606",
    "sg:province":"CA",
    "sg:tags":[
        "playground"
    ],
    "wof:name":"Under The Sea",
    "wof:placetype":"venue"
},
  "geometry": {"coordinates":[-118.050749,33.967378],"type":"Point"}
}