{
  "type": "Feature",
  "properties": {
    "iso:country":"US",
    "sg:address":"62 Devonshire Ave",
    "sg:city":"Mountain View",
    "sg:classifiers":[
        {
            "category":"Park",
            "type":"Public Place"
        }
    ],
    "sg:phone":"+1 650 903 6326",
    "sg:postcode":"94043",
    "sg:province":"CA",
    "wof:name":"Devonshire Park",
    "wof:placetype":"venue"
},
  "geometry": {"coordinates":[-122.059129,37.403821],"type":"Point"}
}