{
  "type": "Feature",
  "properties": {
    "addr:full":"513 E Broadway Glendale CA 91205",
    "addr:housenumber":"513",
    "addr:postcode":"91205",
    "addr:street":"E Broadway",
    "iso:country":"US",
    "sg:address":"513 E Broadway",
    "sg:city":"Glendale",
    "sg:classifiers":[
        {
            "category":"Personal",
            "subcategory":"Beauty Salon",
            "type":"Services"
        }
    ],
    "sg:phone":"+1 818 240 6340",
    "sg:postcode":"91205",
    "sg:province":"CA",
    "sg:tags":[
        "nail"
    ],
    "sg:website":"www.glendalesalonspa.com",
    "wof:name":"Glendale SalonSpa",
    "wof:placetype":"venue"
},
  "geometry": {"coordinates":[-118.249381,34.146609],"type":"Point"}
}