{
  "type": "Feature",
  "properties": {
    "addr:full":"37165 Lanyard Ter Fremont CA 94536",
    "addr:postcode":"37165;94536",
    "addr:street":"Lanyard Ter",
    "iso:country":"US",
    "sg:address":"37165 Lanyard Ter",
    "sg:city":"Fremont",
    "sg:classifiers":[
        {
            "category":"Manufacturing",
            "subcategory":"Retail Goods",
            "type":"Manufacturing & Wholesale Goods"
        },
        {
            "category":"Professional",
            "subcategory":"Computer Services",
            "type":"Services"
        }
    ],
    "sg:phone":"+1 510 494 9744",
    "sg:postcode":"94536",
    "sg:province":"CA",
    "sg:tags":[
        "product",
        "mfg",
        "internet"
    ],
    "wof:name":"Tao Industries",
    "wof:placetype":"venue"
},
  "geometry": {"coordinates":[-122.005698,37.564021],"type":"Point"}
}