{
  "type": "Feature",
  "properties": {
    "iso:country":"US",
    "sg:address":"20331 Lake Forest Drive",
    "sg:city":"Lake Forest",
    "sg:classifiers":[
        {
            "category":"Building & Trades",
            "subcategory":"Construction",
            "type":"Services"
        }
    ],
    "sg:phone":"+1 949 951 6944",
    "sg:postcode":"92630",
    "sg:province":"CA",
    "sg:tags":[
        "contractor"
    ],
    "wof:name":"Sanders Construction",
    "wof:placetype":"venue"
},
  "geometry": {"coordinates":[-117.68674,33.639248],"type":"Point"}
}