{
  "type": "Feature",
  "properties": {
    "addr:full":"6398 Purple Hills Dr San Jose CA 95119",
    "addr:housenumber":"6398",
    "addr:postcode":"95119",
    "addr:street":"Purple Hills Dr",
    "iso:country":"US",
    "sg:address":"6398 Purple Hills Dr",
    "sg:city":"San Jose",
    "sg:classifiers":[
        {
            "category":"Banks & Credit Unions",
            "subcategory":"Investment Brokerage",
            "type":"Services"
        }
    ],
    "sg:phone":"+1 408 363 1313",
    "sg:postcode":"95119",
    "sg:province":"CA",
    "sg:tags":[
        "advisory",
        "management"
    ],
    "wof:name":"Scion Value Fund LLC",
    "wof:placetype":"venue"
},
  "geometry": {"coordinates":[-121.793449,37.231465],"type":"Point"}
}