{
  "type": "Feature",
  "properties": {
    "iso:country":"US",
    "sg:address":"26039 Charing Cross Rd",
    "sg:city":"Valencia",
    "sg:classifiers":[
        {
            "category":"Insurance",
            "subcategory":"Health Insurance",
            "type":"Services"
        }
    ],
    "sg:phone":"+1 661 259 3229",
    "sg:postcode":"91355",
    "sg:province":"CA",
    "sg:tags":[
        "market"
    ],
    "wof:name":"Nikken Independent Distributor -Jan Lee Bernards",
    "wof:placetype":"venue"
},
  "geometry": {"coordinates":[-118.558412,34.400609],"type":"Point"}
}