{
  "type": "Feature",
  "properties": {
    "addr:full":"1129 Harkins Rd Salinas CA 93901",
    "addr:housenumber":"1129",
    "addr:postcode":"93901",
    "addr:street":"Harkins Rd",
    "iso:country":"US",
    "sg:address":"1129 Harkins Rd",
    "sg:city":"Salinas",
    "sg:classifiers":[
        {
            "category":"Wholesale",
            "subcategory":"Construction Materials",
            "type":"Manufacturing & Wholesale Goods"
        }
    ],
    "sg:phone":"+1 831 759 4835",
    "sg:postcode":"93901",
    "sg:province":"CA",
    "sg:tags":[
        "analytical",
        "mfg"
    ],
    "wof:name":"Trece",
    "wof:placetype":"venue"
},
  "geometry": {"coordinates":[-121.63038,36.650216],"type":"Point"}
}