{
  "type": "Feature",
  "properties": {
    "addr:full":"1557 Imperial Dr Redding CA 96003",
    "addr:housenumber":"1557",
    "addr:postcode":"96003",
    "addr:street":"Imperial Dr",
    "iso:country":"US",
    "sg:address":"1557 Imperial Dr",
    "sg:city":"Redding",
    "sg:classifiers":[
        {
            "category":"Communications",
            "type":"Services"
        }
    ],
    "sg:phone":"+1 530 222 1276",
    "sg:postcode":"96003",
    "sg:province":"CA",
    "sg:tags":[
        "communication"
    ],
    "wof:name":"Welch Communications",
    "wof:placetype":"venue"
},
  "geometry": {"coordinates":[-122.317843,40.584395],"type":"Point"}
}