{
  "type": "Feature",
  "properties": {
    "iso:country":"US",
    "sg:address":"4203 Montair Ave",
    "sg:city":"Long Beach",
    "sg:classifiers":[
        {
            "category":"Shopping",
            "subcategory":"Tobacco",
            "type":"Retail Goods"
        },
        {
            "category":"Wholesale",
            "subcategory":"Stationery",
            "type":"Manufacturing & Wholesale Goods"
        }
    ],
    "sg:phone":"+1 562 429 2700",
    "sg:postcode":"90808",
    "sg:province":"CA",
    "sg:tags":[
        "shop",
        "card"
    ],
    "wof:name":"Humble House",
    "wof:placetype":"venue"
},
  "geometry": {"coordinates":[-118.126792,33.834051],"type":"Point"}
}