{
  "type": "Feature",
  "properties": {
    "addr:full":"1510 Mission Ave Oceanside CA 92054",
    "addr:housenumber":"1510",
    "addr:postcode":"92054",
    "addr:street":"Mission Ave",
    "iso:country":"US",
    "sg:address":"1510 Mission Ave",
    "sg:city":"Oceanside",
    "sg:classifiers":[
        {
            "category":"Home & Garden",
            "subcategory":"Household Appliances",
            "type":"Retail Goods"
        },
        {
            "category":"Home & Garden",
            "subcategory":"Carpets & Floor Coverings",
            "type":"Retail Goods"
        },
        {
            "category":"Home & Garden",
            "subcategory":"Furniture",
            "type":"Retail Goods"
        }
    ],
    "sg:phone":"+1 760 722 7111",
    "sg:postcode":"92054",
    "sg:province":"CA",
    "sg:tags":[
        "repair",
        "store",
        "mattress"
    ],
    "wof:name":"Mission Mattress & Furniture Warehouse",
    "wof:placetype":"venue"
},
  "geometry": {"coordinates":[-117.36900300000001,33.201698],"type":"Point"}
}