{
  "type": "Feature",
  "properties": {
    "addr:full":"499 N Market St Redding CA 96003",
    "addr:housenumber":"499",
    "addr:postcode":"96003",
    "addr:street":"N Market St",
    "iso:country":"US",
    "sg:address":"499 N Market St",
    "sg:city":"Redding",
    "sg:classifiers":[
        {
            "category":"Shopping",
            "subcategory":"Discount & Variety Stores",
            "type":"Retail Goods"
        }
    ],
    "sg:phone":"+1 530 246 7727",
    "sg:postcode":"96003",
    "sg:province":"CA",
    "wof:name":"Miracle Mile Mercantile",
    "wof:placetype":"venue"
},
  "geometry": {"coordinates":[-122.38216799999999,40.60126],"type":"Point"}
}