{
  "type": "Feature",
  "properties": {
    "iso:country":"US",
    "sg:address":"2180 Gratton St",
    "sg:city":"Riverside",
    "sg:classifiers":[
        {
            "category":"Retail",
            "subcategory":"Auto Repair",
            "type":"Services"
        }
    ],
    "sg:phone":"+1 951 738 8669",
    "sg:postcode":"92504",
    "sg:province":"CA",
    "sg:tags":[
        "body",
        "painting",
        "repairing",
        "automobile"
    ],
    "wof:name":"Tony's Auto Restoration Classics & Street Rods",
    "wof:placetype":"venue"
},
  "geometry": {"coordinates":[-117.404842,33.902562],"type":"Point"}
}