{
  "type": "Feature",
  "properties": {
    "iso:country":"US",
    "sg:address":"501 Joan St",
    "sg:city":"La Habra",
    "sg:classifiers":[
        {
            "category":"Building & Trades",
            "subcategory":"Electrical",
            "type":"Services"
        }
    ],
    "sg:phone":"+1 714 990 8877",
    "sg:postcode":"90631",
    "sg:province":"CA",
    "sg:tags":[
        "communications",
        "contractor"
    ],
    "wof:name":"Lighthouse Communications",
    "wof:placetype":"venue"
},
  "geometry": {"coordinates":[-117.927463,33.936564],"type":"Point"}
}