{
  "type": "Feature",
  "properties": {
    "addr:full":"258 E Adams Blvd Los Angeles CA 90011",
    "addr:housenumber":"258",
    "addr:postcode":"90011",
    "addr:street":"E Adams Blvd",
    "iso:country":"US",
    "sg:address":"258 E Adams Blvd",
    "sg:city":"Los Angeles",
    "sg:classifiers":[
        {
            "category":"Personal",
            "subcategory":"Beauty Salon",
            "type":"Services"
        }
    ],
    "sg:phone":"+1 213 746 7107",
    "sg:postcode":"90011",
    "sg:province":"CA",
    "wof:name":"Fantastic Cuts",
    "wof:placetype":"venue"
},
  "geometry": {"coordinates":[-118.266893,34.024107],"type":"Point"}
}