{
  "type": "Feature",
  "properties": {
    "addr:full":"4485 La Jolla Village Dr San Diego CA 92122",
    "addr:housenumber":"4485",
    "addr:postcode":"92122",
    "addr:street":"La Jolla Village Dr",
    "iso:country":"US",
    "sg:address":"4485 La Jolla Village Dr",
    "sg:city":"San Diego",
    "sg:classifiers":[
        {
            "category":"Shopping",
            "subcategory":"Computers & Home Electronics",
            "type":"Retail Goods"
        }
    ],
    "sg:phone":"+1 858 552 1003",
    "sg:postcode":"92122",
    "sg:province":"CA",
    "wof:name":"GameStop",
    "wof:placetype":"venue"
},
  "geometry": {"coordinates":[-117.210002,32.873567],"type":"Point"}
}