{
  "type": "Feature",
  "properties": {
    "addr:full":"801 Mahler Rd Ste C Burlingame CA 94010",
    "addr:housenumber":"801",
    "addr:postcode":"94010",
    "addr:street":"Mahler Rd Ste C",
    "iso:country":"US",
    "sg:address":"801 Mahler Rd Ste C",
    "sg:city":"Burlingame",
    "sg:classifiers":[
        {
            "category":"Restaurant",
            "type":"Food & Drink"
        }
    ],
    "sg:phone":"+1 650 697 8450",
    "sg:postcode":"94010",
    "sg:province":"CA",
    "sg:tags":[
        "sushi",
        "bar"
    ],
    "sg:website":"www.mrteriyaki.webs.com/",
    "wof:name":"Mr Teriyaki",
    "wof:placetype":"venue"
},
  "geometry": {"coordinates":[-122.366336,37.597865],"type":"Point"}
}