{
  "type": "Feature",
  "properties": {
    "addr:full":"26 W Monterey Ave Stockton CA 95204",
    "addr:housenumber":"26",
    "addr:postcode":"95204",
    "addr:street":"W Monterey Ave",
    "iso:country":"US",
    "sg:address":"26 W Monterey Ave",
    "sg:city":"Stockton",
    "sg:classifiers":[
        {
            "category":"Professional",
            "subcategory":"Art Services",
            "type":"Services"
        }
    ],
    "sg:phone":"+1 209 461 0100",
    "sg:postcode":"95204",
    "sg:province":"CA",
    "sg:tags":[
        "interior",
        "designer",
        "decorator"
    ],
    "wof:name":"Janine Lynch Interiors Design",
    "wof:placetype":"venue"
},
  "geometry": {"coordinates":[-121.30036200000001,37.976855],"type":"Point"}
}