{
  "type": "Feature",
  "properties": {
    "addr:full":"5276 Mission St San Francisco CA 94112",
    "addr:housenumber":"5276",
    "addr:postcode":"94112",
    "addr:street":"Mission St",
    "iso:country":"US",
    "sg:address":"5276 Mission St",
    "sg:city":"San Francisco",
    "sg:classifiers":[
        {
            "category":"Retail",
            "subcategory":"Repair Shop",
            "type":"Services"
        }
    ],
    "sg:phone":"+1 415 334 6614",
    "sg:postcode":"94112",
    "sg:province":"CA",
    "sg:tags":[
        "lock",
        "locksmith"
    ],
    "wof:name":"Dads Locksmith",
    "wof:placetype":"venue"
},
  "geometry": {"coordinates":[-122.44228699999999,37.715119],"type":"Point"}
}