{
  "type": "Feature",
  "properties": {
    "iso:country":"US",
    "sg:address":"330 S San Jacinto St",
    "sg:city":"Hemet",
    "sg:classifiers":[
        {
            "category":"Health Services",
            "subcategory":"Nursing And Care Facility",
            "type":"Services"
        }
    ],
    "sg:phone":"+1 951 765 1840",
    "sg:postcode":"92543",
    "sg:province":"CA",
    "sg:tags":[
        "intermediate"
    ],
    "wof:name":"Chateau Battiste",
    "wof:placetype":"venue"
},
  "geometry": {"coordinates":[-116.958532,33.743515],"type":"Point"}
}