{
  "type": "Feature",
  "properties": {
    "iso:country":"US",
    "sg:address":"152 Stanford Ave",
    "sg:city":"Mill Valley",
    "sg:classifiers":[
        {
            "category":"Real Estate",
            "subcategory":"Architect",
            "type":"Services"
        }
    ],
    "sg:phone":"+1 415 383 5105",
    "sg:postcode":"94941",
    "sg:province":"CA",
    "wof:name":"Healthy Home Designs",
    "wof:placetype":"venue"
},
  "geometry": {"coordinates":[-122.530193,37.885676],"type":"Point"}
}