{
  "type": "Feature",
  "properties": {
    "iso:country":"US",
    "sg:address":"4301 Auburn St",
    "sg:city":"Bakersfield",
    "sg:classifiers":[
        {
            "category":"Professional",
            "subcategory":"Accounting & Tax Preparation",
            "type":"Services"
        }
    ],
    "sg:phone":"+1 661 871 2185",
    "sg:postcode":"93306",
    "sg:province":"CA",
    "sg:tags":[
        "bookkeeping",
        "general"
    ],
    "wof:name":"Players Pool League",
    "wof:placetype":"venue"
},
  "geometry": {"coordinates":[-118.94952000000001,35.397661],"type":"Point"}
}