{
  "type": "Feature",
  "properties": {
    "iso:country":"US",
    "sg:address":"4947 Marmol Dr",
    "sg:city":"Woodland Hills",
    "sg:classifiers":[
        {
            "category":"Wholesale",
            "subcategory":"Jewelry",
            "type":"Manufacturing & Wholesale Goods"
        }
    ],
    "sg:phone":"+1 818 999 2361",
    "sg:postcode":"91364",
    "sg:province":"CA",
    "sg:tags":[
        "stone"
    ],
    "wof:name":"Nimica",
    "wof:placetype":"venue"
},
  "geometry": {"coordinates":[-118.589996,34.160301],"type":"Point"}
}