{
  "type": "Feature",
  "properties": {
    "addr:full":"39040 Sky Canyon Dr Murrieta CA 92563",
    "addr:postcode":"39040;92563",
    "addr:street":"Sky Canyon Dr",
    "iso:country":"US",
    "sg:address":"39040 Sky Canyon Dr",
    "sg:city":"Murrieta",
    "sg:classifiers":[
        {
            "category":"Restaurant",
            "type":"Food & Drink"
        }
    ],
    "sg:menulink":"http://www.allmenus.com/ca/murrieta/183025-submarina/menu/",
    "sg:phone":"+1 951 698 5322",
    "sg:postcode":"92563",
    "sg:province":"CA",
    "sg:tags":[
        "wrap",
        "american",
        "sandwich"
    ],
    "wof:name":"Submarina",
    "wof:placetype":"venue"
},
  "geometry": {"coordinates":[-117.137736,33.553072],"type":"Point"}
}