{
  "type": "Feature",
  "properties": {
    "iso:country":"US",
    "sg:address":"236 San Jose St",
    "sg:city":"Salinas",
    "sg:classifiers":[
        {
            "category":"Health Services",
            "subcategory":"Doctor",
            "type":"Services"
        }
    ],
    "sg:phone":"+1 831 424 7389",
    "sg:postcode":"93901",
    "sg:province":"CA",
    "sg:tags":[
        "physician",
        "surgeon"
    ],
    "wof:name":"Lawler Rudo & Smith",
    "wof:placetype":"venue"
},
  "geometry": {"coordinates":[-121.646057,36.658162],"type":"Point"}
}