{
  "type": "Feature",
  "properties": {
    "addr:full":"113 E Main St Ventura CA 93001",
    "addr:housenumber":"113",
    "addr:postcode":"93001",
    "addr:street":"E Main St",
    "iso:country":"US",
    "sg:address":"113 E Main St",
    "sg:city":"Ventura",
    "sg:classifiers":[
        {
            "category":"Government",
            "subcategory":"Office",
            "type":"Public Place"
        }
    ],
    "sg:phone":"+1 805 648 5823",
    "sg:postcode":"93001",
    "sg:province":"CA",
    "sg:tags":[
        "village"
    ],
    "wof:name":"Albinger Archaeological Museum",
    "wof:placetype":"venue"
},
  "geometry": {"coordinates":[-119.29967600000001,34.281004],"type":"Point"}
}