{
  "type": "Feature",
  "properties": {
    "iso:country":"US",
    "sg:address":"3826 Minerva Ave",
    "sg:city":"Los Angeles",
    "sg:classifiers":[
        {
            "category":"Professional",
            "type":"Services"
        }
    ],
    "sg:phone":"+1 310 745 1601",
    "sg:postcode":"90066",
    "sg:province":"CA",
    "wof:name":"Pira Roma",
    "wof:placetype":"venue"
},
  "geometry": {"coordinates":[-118.42116799999999,34.008663],"type":"Point"}
}