{
  "type": "Feature",
  "properties": {
    "iso:country":"US",
    "sg:address":"198 W Scott St",
    "sg:city":"Long Beach",
    "sg:classifiers":[
        {
            "category":"Manufacturing",
            "subcategory":"Printing",
            "type":"Manufacturing & Wholesale Goods"
        }
    ],
    "sg:phone":"+1 310 632 3701",
    "sg:postcode":"90805",
    "sg:province":"CA",
    "sg:tags":[
        "book",
        "co",
        "publishing"
    ],
    "wof:name":"Model T Ford Publishing Co",
    "wof:placetype":"venue"
},
  "geometry": {"coordinates":[-118.201437,33.869189],"type":"Point"}
}