{
  "type": "Feature",
  "properties": {
    "addr:full":"275 Elliott Dr. Menlo Park, Ca 94025",
    "wof:categories":[
        "education_and_religion:education=school"
    ],
    "wof:name":"The German-American International School",
    "wof:placetype":"venue"
},
  "geometry": {"coordinates":[-122.14941540607217,37.45982993273053],"type":"Point"}
}