{
  "type": "Feature",
  "properties": {
    "addr:full":"490 Post St Ste 807 San Francisco CA 94102",
    "addr:housenumber":"490",
    "addr:postcode":"94102",
    "addr:street":"Post St Ste 807",
    "iso:country":"US",
    "sg:address":"490 Post St Ste 807",
    "sg:city":"San Francisco",
    "sg:classifiers":[
        {
            "category":"Health Services",
            "subcategory":"Dentist",
            "type":"Services"
        }
    ],
    "sg:phone":"+1 415 397 4233",
    "sg:postcode":"94102",
    "sg:province":"CA",
    "sg:website":"www.vancampdentistry.com",
    "wof:name":"VanCamp Dentistry",
    "wof:placetype":"venue"
},
  "geometry": {"coordinates":[-122.40989500000001,37.788181],"type":"Point"}
}