{
  "type": "Feature",
  "properties": {
    "addr:full":"929 3rd St Encinitas CA 92024",
    "addr:housenumber":"929",
    "addr:postcode":"92024",
    "addr:street":"3Rd St",
    "iso:country":"US",
    "sg:address":"929 3rd St",
    "sg:city":"Encinitas",
    "sg:classifiers":[
        {
            "category":"Wholesale",
            "subcategory":"Jewelry",
            "type":"Manufacturing & Wholesale Goods"
        }
    ],
    "sg:phone":"+1 760 944 3841",
    "sg:postcode":"92024",
    "sg:province":"CA",
    "sg:tags":[
        "stone"
    ],
    "wof:name":"Omart",
    "wof:placetype":"venue"
},
  "geometry": {"coordinates":[-117.294843,33.039618],"type":"Point"}
}