{
  "type": "Feature",
  "properties": {
    "iso:country":"US",
    "sg:address":"42030 Ave Alvarado",
    "sg:city":"Temecula",
    "sg:classifiers":[
        {
            "category":"Manufacturing",
            "subcategory":"Tools & Machinery",
            "type":"Manufacturing & Wholesale Goods"
        }
    ],
    "sg:phone":"+1 951 719 1290",
    "sg:postcode":"92590",
    "sg:province":"CA",
    "sg:tags":[
        "machine",
        "shop"
    ],
    "wof:name":"Benson Precision Machining",
    "wof:placetype":"venue"
},
  "geometry": {"coordinates":[-117.16789300000001,33.512291],"type":"Point"}
}