{
  "type": "Feature",
  "properties": {
    "iso:country":"US",
    "sg:address":"1720 Huntington Dr",
    "sg:city":"South Pasadena",
    "sg:classifiers":[
        {
            "category":"Real Estate",
            "subcategory":"Real Estate Services",
            "type":"Services"
        }
    ],
    "sg:phone":"+1 626 441 6855",
    "sg:postcode":"91030",
    "sg:province":"CA",
    "sg:tags":[
        "management",
        "property"
    ],
    "wof:name":"Carruth Properties L L C",
    "wof:placetype":"venue"
},
  "geometry": {"coordinates":[-118.14537,34.104367],"type":"Point"}
}