{
  "type": "Feature",
  "properties": {
    "addr:full":"540 N Elm St Escondido CA 92025",
    "addr:housenumber":"540",
    "addr:postcode":"92025",
    "addr:street":"N Elm St",
    "iso:country":"US",
    "sg:address":"540 N Elm St",
    "sg:city":"Escondido",
    "sg:classifiers":[
        {
            "category":"Building & Trades",
            "subcategory":"Construction",
            "type":"Services"
        }
    ],
    "sg:phone":"+1 760 233 5734",
    "sg:postcode":"92025",
    "sg:province":"CA",
    "sg:tags":[
        "concrete",
        "contractor"
    ],
    "wof:name":"Riveras Concrete Construction",
    "wof:placetype":"venue"
},
  "geometry": {"coordinates":[-117.073679,33.129744],"type":"Point"}
}