{
  "type": "Feature",
  "properties": {
    "iso:country":"US",
    "sg:address":"1023 Kansas Ave",
    "sg:city":"Modesto",
    "sg:classifiers":[
        {
            "category":"Autos & Motor Vehicles",
            "subcategory":"Automobile Sales",
            "type":"Retail Goods"
        }
    ],
    "sg:phone":"+1 209 492 9669",
    "sg:postcode":"95351",
    "sg:province":"CA",
    "sg:tags":[
        "car",
        "dealer"
    ],
    "wof:name":"Testosterone Motors",
    "wof:placetype":"venue"
},
  "geometry": {"coordinates":[-121.022393,37.646066],"type":"Point"}
}