{
  "type": "Feature",
  "properties": {
    "addr:full":"1548 Aldrich Way San Jose CA 95121",
    "addr:housenumber":"1548",
    "addr:postcode":"95121",
    "addr:street":"Aldrich Way",
    "iso:country":"US",
    "sg:address":"1548 Aldrich Way",
    "sg:city":"San Jose",
    "sg:classifiers":[
        {
            "category":"Professional",
            "type":"Services"
        }
    ],
    "sg:phone":"+1 408 274 5702",
    "sg:postcode":"95121",
    "sg:province":"CA",
    "wof:name":"Christian R and Chen Frey",
    "wof:placetype":"venue"
},
  "geometry": {"coordinates":[-121.82201499999999,37.312141],"type":"Point"}
}