{
  "type": "Feature",
  "properties": {
    "iso:country":"US",
    "sg:address":"4495 Magnolia Ave",
    "sg:city":"Riverside",
    "sg:classifiers":[
        {
            "category":"Education",
            "subcategory":"School",
            "type":"Public Place"
        }
    ],
    "sg:phone":"+1 951 369 8105",
    "sg:postcode":"92501",
    "sg:province":"CA",
    "sg:tags":[
        "academic",
        "special"
    ],
    "wof:name":"Childrens Center Of Riverside",
    "wof:placetype":"venue"
},
  "geometry": {"coordinates":[-117.381518,33.974754],"type":"Point"}
}