{
  "type": "Feature",
  "properties": {
    "addr:full":"934 Eloise Ave South Lake Tahoe CA 96150",
    "addr:housenumber":"934",
    "addr:postcode":"96150",
    "addr:street":"Eloise Ave",
    "iso:country":"US",
    "sg:address":"934 Eloise Ave",
    "sg:city":"South Lake Tahoe",
    "sg:classifiers":[
        {
            "category":"Retail",
            "subcategory":"Auto Repair",
            "type":"Services"
        }
    ],
    "sg:phone":"+1 530 542 1141",
    "sg:postcode":"96150",
    "sg:province":"CA",
    "sg:tags":[
        "body",
        "automobile",
        "painting"
    ],
    "wof:name":"South Side Auto Body",
    "wof:placetype":"venue"
},
  "geometry": {"coordinates":[-120.005662,38.91661],"type":"Point"}
}