{
  "type": "Feature",
  "properties": {
    "addr:full":"38578 Oak Glen Rd Yucaipa CA 92399",
    "addr:housenumber":"38578",
    "addr:postcode":"92399",
    "addr:street":"Oak Glen Rd",
    "iso:country":"US",
    "sg:address":"38578 Oak Glen Rd",
    "sg:city":"Yucaipa",
    "sg:classifiers":[
        {
            "category":"Bakery",
            "type":"Food & Drink"
        }
    ],
    "sg:phone":"+1 909 797 4422",
    "sg:postcode":"92399",
    "sg:province":"CA",
    "sg:website":"www.appledumplinweddings.com",
    "wof:name":"Apple Dumpling's Restaurant & Bakery",
    "wof:placetype":"venue"
},
  "geometry": {"coordinates":[-116.962997,34.052299],"type":"Point"}
}