{
  "type": "Feature",
  "properties": {
    "iso:country":"US",
    "sg:address":"320 Water View Way",
    "sg:city":"Folsom",
    "sg:classifiers":[
        {
            "category":"Utilities",
            "subcategory":"Electric",
            "type":"Services"
        },
        {
            "category":"Utilities",
            "type":"Services"
        }
    ],
    "sg:phone":"+1 916 802 7509",
    "sg:postcode":"95630",
    "sg:province":"CA",
    "wof:name":"Power System Resources",
    "wof:placetype":"venue"
},
  "geometry": {"coordinates":[-121.18467800000001,38.684177],"type":"Point"}
}