{
  "type": "Feature",
  "properties": {
    "addr:full":"605 Oak St Roseville CA 95678",
    "addr:housenumber":"605",
    "addr:postcode":"95678",
    "addr:street":"Oak St",
    "iso:country":"US",
    "sg:address":"605 Oak St",
    "sg:city":"Roseville",
    "sg:classifiers":[
        {
            "category":"Professional",
            "type":"Services"
        }
    ],
    "sg:phone":"+1 916 789 1515",
    "sg:postcode":"95678",
    "sg:province":"CA",
    "sg:tags":[
        "establishment"
    ],
    "wof:name":"Expense Analysis",
    "wof:placetype":"venue"
},
  "geometry": {"coordinates":[-121.287645,38.744562],"type":"Point"}
}