{
  "type": "Feature",
  "properties": {
    "iso:country":"US",
    "sg:address":"163 Brisas St",
    "sg:city":"Oceanside",
    "sg:classifiers":[
        {
            "category":"Building & Trades",
            "subcategory":"Landscaping Services",
            "type":"Services"
        }
    ],
    "sg:phone":"+1 760 433 5729",
    "sg:postcode":"92058",
    "sg:province":"CA",
    "sg:tags":[
        "landscape"
    ],
    "wof:name":"Dominador Pagala Landscaping",
    "wof:placetype":"venue"
},
  "geometry": {"coordinates":[-117.32858400000001,33.24171],"type":"Point"}
}