{
  "type": "Feature",
  "properties": {
    "iso:country":"US",
    "sg:address":"1200 Santee St",
    "sg:city":"Los Angeles",
    "sg:classifiers":[
        {
            "category":"Professional",
            "type":"Services"
        }
    ],
    "sg:phone":"+1 213 746 4940",
    "sg:postcode":"90015",
    "sg:province":"CA",
    "sg:tags":[
        "establishment"
    ],
    "wof:name":"V & M",
    "wof:placetype":"venue"
},
  "geometry": {"coordinates":[-118.258265,34.03514],"type":"Point"}
}