{
  "type": "Feature",
  "properties": {
    "addr:full":"1778 S Araby Dr Palm Springs CA 92264",
    "addr:housenumber":"1778",
    "addr:postcode":"92264",
    "addr:street":"S Araby Dr",
    "iso:country":"US",
    "sg:address":"1778 S Araby Dr",
    "sg:city":"Palm Springs",
    "sg:classifiers":[
        {
            "category":"Communications",
            "type":"Services"
        }
    ],
    "sg:phone":"+1 760 320 5950",
    "sg:postcode":"92264",
    "sg:province":"CA",
    "sg:tags":[
        "web",
        "design"
    ],
    "sg:website":"www.kinderrelations.com",
    "wof:name":"Kinder Relations Inc.",
    "wof:placetype":"venue"
},
  "geometry": {"coordinates":[-116.514847,33.799361],"type":"Point"}
}