{
  "type": "Feature",
  "properties": {
    "addr:full":"211 Sutter St 8th Floor San Francisco CA 94104",
    "addr:housenumber":"211;8th",
    "addr:postcode":"94104",
    "addr:street":"Sutter St;Floor",
    "iso:country":"US",
    "sg:address":"211 Sutter St 8th Floor",
    "sg:city":"San Francisco",
    "sg:classifiers":[
        {
            "category":"Health Services",
            "subcategory":"Health Practitioner",
            "type":"Services"
        }
    ],
    "sg:phone":"+1 415 713 5620",
    "sg:postcode":"94104",
    "sg:province":"CA",
    "sg:tags":[
        "acupuncture"
    ],
    "sg:website":"www.meganwilldorf.com",
    "wof:name":"Megan Willdorf, MS, L.Ac",
    "wof:placetype":"venue"
},
  "geometry": {"coordinates":[-122.40397,37.789818],"type":"Point"}
}