{
  "type": "Feature",
  "properties": {
    "addr:full":"5770 W Pico Blvd Los Angeles CA 90019",
    "addr:housenumber":"5770",
    "addr:postcode":"90019",
    "addr:street":"W Pico Blvd",
    "iso:country":"US",
    "sg:address":"5770 W Pico Blvd",
    "sg:city":"Los Angeles",
    "sg:classifiers":[
        {
            "category":"Wholesale",
            "subcategory":"Electrical",
            "type":"Manufacturing & Wholesale Goods"
        }
    ],
    "sg:phone":"+1 323 297 0467",
    "sg:postcode":"90019",
    "sg:province":"CA",
    "sg:tags":[
        "equipment",
        "tube",
        "bulb",
        "light"
    ],
    "wof:name":"Sam's Lighting",
    "wof:placetype":"venue"
},
  "geometry": {"coordinates":[-118.36416800000001,34.05093],"type":"Point"}
}