{
  "type": "Feature",
  "properties": {
    "addr:full":"728 N Avalon Blvd Wilmington CA 90744",
    "addr:housenumber":"728",
    "addr:postcode":"90744",
    "addr:street":"N Avalon Blvd",
    "iso:country":"US",
    "sg:address":"728 N Avalon Blvd",
    "sg:city":"Wilmington",
    "sg:classifiers":[
        {
            "category":"Food & Beverages",
            "subcategory":"Groceries & Convenience Stores",
            "type":"Retail Goods"
        }
    ],
    "sg:phone":"+1 310 834 1692",
    "sg:postcode":"90744",
    "sg:province":"CA",
    "sg:tags":[
        "grocer"
    ],
    "wof:name":"Amigos Nutrition Ctr",
    "wof:placetype":"venue"
},
  "geometry": {"coordinates":[-118.262328,33.779564],"type":"Point"}
}