{
  "type": "Feature",
  "properties": {
    "iso:country":"US",
    "sg:address":"101 Pierre Ct",
    "sg:city":"Vallejo",
    "sg:classifiers":[
        {
            "category":"Professional",
            "type":"Services"
        }
    ],
    "sg:phone":"+1 707 642 1352",
    "sg:postcode":"94591",
    "sg:province":"CA",
    "wof:name":"Casey Diggins",
    "wof:placetype":"venue"
},
  "geometry": {"coordinates":[-122.198808,38.112656],"type":"Point"}
}