{
  "type": "Feature",
  "properties": {
    "addr:full":"7858 Convoy Ct San Diego CA 92117",
    "addr:housenumber":"7858",
    "addr:postcode":"92117",
    "addr:street":"Convoy Ct",
    "iso:country":"US",
    "sg:address":"7858 Convoy Ct",
    "sg:city":"San Diego",
    "sg:classifiers":[
        {
            "category":"Building & Trades",
            "subcategory":"Construction",
            "type":"Services"
        }
    ],
    "sg:phone":"+1 858 565 4838",
    "sg:postcode":"92117",
    "sg:province":"CA",
    "sg:tags":[
        "fire",
        "restoration",
        "damage"
    ],
    "wof:name":"Protech Construction",
    "wof:placetype":"venue"
},
  "geometry": {"coordinates":[-117.150879,32.834734],"type":"Point"}
}