{
  "type": "Feature",
  "properties": {
    "iso:country":"US",
    "sg:address":"668 Hofman Dr",
    "sg:city":"Shafter",
    "sg:classifiers":[
        {
            "category":"Real Estate",
            "subcategory":"Real Estate Services",
            "type":"Services"
        }
    ],
    "sg:phone":"+1 661 746 2486",
    "sg:postcode":"93263",
    "sg:province":"CA",
    "sg:tags":[
        "search",
        "oil",
        "title",
        "gas",
        "right",
        "curative",
        "acquisition"
    ],
    "wof:name":"T and T Land Services",
    "wof:placetype":"venue"
},
  "geometry": {"coordinates":[-119.272328,35.509503],"type":"Point"}
}