{
  "type": "Feature",
  "properties": {
    "addr:full":"5137 York Boulevard Los Angeles CA 90042",
    "addr:housenumber":"5137",
    "addr:postcode":"90042",
    "addr:street":"York Boulevard",
    "iso:country":"US",
    "sg:address":"5137 York Boulevard",
    "sg:city":"Los Angeles",
    "sg:classifiers":[
        {
            "category":"Restaurant",
            "type":"Food & Drink"
        }
    ],
    "sg:phone":"+1 323 258 9601",
    "sg:postcode":"90042",
    "sg:province":"CA",
    "wof:name":"El Chubasco DOS Restaurant",
    "wof:placetype":"venue"
},
  "geometry": {"coordinates":[-118.203559,34.120944],"type":"Point"}
}