{
  "type": "Feature",
  "properties": {
    "iso:country":"US",
    "sg:address":"33398 Oak Glen Rd",
    "sg:city":"Yucaipa",
    "sg:classifiers":[
        {
            "category":"Community Center",
            "subcategory":"Senior",
            "type":"Public Place"
        },
        {
            "category":"Health Services",
            "subcategory":"Nursing And Care Facility",
            "type":"Services"
        },
        {
            "category":"Health Services",
            "subcategory":"Health Practitioner",
            "type":"Services"
        },
        {
            "category":"Social Services",
            "subcategory":"Adult Care",
            "type":"Services"
        }
    ],
    "sg:phone":"+1 800 982 9616",
    "sg:postcode":"92399",
    "sg:province":"CA",
    "sg:tags":[
        "living",
        "assisted",
        "elder",
        "citizen",
        "home",
        "eldercare-home"
    ],
    "sg:website":"http://www.rescarehomecare.com",
    "wof:name":"ResCare HomeCare",
    "wof:placetype":"venue"
},
  "geometry": {"coordinates":[-117.076689,34.029503],"type":"Point"}
}