{
  "type": "Feature",
  "properties": {
    "iso:country":"US",
    "sg:address":"22640 Elder Ave",
    "sg:city":"Riverdale",
    "sg:classifiers":[
        {
            "category":"Professional",
            "subcategory":"Detective & Security Services",
            "type":"Services"
        }
    ],
    "sg:phone":"+1 559 867 7100",
    "sg:postcode":"93656",
    "sg:province":"CA",
    "sg:tags":[
        "guard",
        "patrol"
    ],
    "wof:name":"Angel De LA Guarda Security",
    "wof:placetype":"venue"
},
  "geometry": {"coordinates":[-119.862493,36.387549],"type":"Point"}
}