{
  "type": "Feature",
  "properties": {
    "addr:full":"2222 Pier Ave Santa Monica CA 90405",
    "addr:housenumber":"2222",
    "addr:postcode":"90405",
    "addr:street":"Pier Ave",
    "iso:country":"US",
    "sg:address":"2222 Pier Ave",
    "sg:city":"Santa Monica",
    "sg:classifiers":[
        {
            "category":"Professional",
            "type":"Services"
        }
    ],
    "sg:phone":"+1 310 450 7821",
    "sg:postcode":"90405",
    "sg:province":"CA",
    "wof:name":"Frank & Antoinine M Dimod",
    "wof:placetype":"venue"
},
  "geometry": {"coordinates":[-118.460167,34.011349],"type":"Point"}
}