{
  "type": "Feature",
  "properties": {
    "addr:full":"770 Higuera St San Luis Obispo CA 93401",
    "addr:housenumber":"770",
    "addr:postcode":"93401",
    "addr:street":"Higuera St",
    "iso:country":"US",
    "sg:address":"770 Higuera St",
    "sg:city":"San Luis Obispo",
    "sg:classifiers":[
        {
            "category":"Shopping",
            "subcategory":"Clothing, Apparel, & Fashions",
            "type":"Retail Goods"
        }
    ],
    "sg:phone":"+1 805 549 8373",
    "sg:postcode":"93401",
    "sg:province":"CA",
    "wof:name":"Coverings",
    "wof:placetype":"venue"
},
  "geometry": {"coordinates":[-120.663056,35.279822],"type":"Point"}
}