{
  "type": "Feature",
  "properties": {
    "iso:country":"US",
    "sg:address":"7405 Reche Canyon Rd",
    "sg:city":"Colton",
    "sg:classifiers":[
        {
            "category":"Building & Trades",
            "subcategory":"Electrical",
            "type":"Services"
        }
    ],
    "sg:phone":"+1 818 251 6389",
    "sg:postcode":"92324",
    "sg:province":"CA",
    "sg:tags":[
        "electrician"
    ],
    "wof:name":"Perfect Electric",
    "wof:placetype":"venue"
},
  "geometry": {"coordinates":[-117.262179,34.010417],"type":"Point"}
}