{
  "type": "Feature",
  "properties": {
    "iso:country":"US",
    "sg:address":"706 Mission St Fl 6",
    "sg:city":"San Francisco",
    "sg:classifiers":[
        {
            "category":"Social Services",
            "subcategory":"Child Care",
            "type":"Services"
        },
        {
            "category":"Education",
            "subcategory":"Preschool",
            "type":"Public Place"
        },
        {
            "category":"Education",
            "subcategory":"School",
            "type":"Public Place"
        }
    ],
    "sg:phone":"+1 415 677 0100",
    "sg:postcode":"94103",
    "sg:province":"CA",
    "sg:tags":[
        "elementary",
        "day"
    ],
    "sg:website":"www.wuyee.org",
    "wof:name":"Wu Yee Children's Services",
    "wof:placetype":"venue"
},
  "geometry": {"coordinates":[-122.4023,37.786282],"type":"Point"}
}