{
  "type": "Feature",
  "properties": {
    "addr:full":"639 E Blithedale Ave Mill Valley CA 94941",
    "addr:housenumber":"639",
    "addr:postcode":"94941",
    "addr:street":"E Blithedale Ave",
    "iso:country":"US",
    "sg:address":"639 E Blithedale Ave",
    "sg:city":"Mill Valley",
    "sg:classifiers":[
        {
            "category":"Health Services",
            "subcategory":"Health Practitioner",
            "type":"Services"
        }
    ],
    "sg:phone":"+1 415 485 8233",
    "sg:postcode":"94941",
    "sg:province":"CA",
    "sg:tags":[
        "therapist",
        "physical"
    ],
    "wof:name":"Michael K Leary",
    "wof:placetype":"venue"
},
  "geometry": {"coordinates":[-122.527545,37.90044],"type":"Point"}
}