{
  "type": "Feature",
  "properties": {
    "addr:full":"2801 Springfield Dr Rocklin CA 95765",
    "addr:housenumber":"2801",
    "addr:postcode":"95765",
    "addr:street":"Springfield Dr",
    "iso:country":"US",
    "sg:address":"2801 Springfield Dr",
    "sg:city":"Rocklin",
    "sg:classifiers":[
        {
            "category":"Restaurant",
            "type":"Food & Drink"
        }
    ],
    "sg:phone":"+1 916 630 4330",
    "sg:postcode":"95765",
    "sg:province":"CA",
    "sg:tags":[
        "banquet",
        "rooms"
    ],
    "sg:website":"www.pulte.com",
    "wof:name":"Springfield At Whitney Oaks",
    "wof:placetype":"venue"
},
  "geometry": {"coordinates":[-121.241018,38.817253],"type":"Point"}
}