{
  "type": "Feature",
  "properties": {
    "iso:country":"US",
    "sg:address":"306 N Garfield Ave #2",
    "sg:city":"Monterey Park",
    "sg:classifiers":[
        {
            "category":"Restaurant",
            "type":"Food & Drink"
        },
        {
            "category":"Bakery",
            "type":"Food & Drink"
        }
    ],
    "sg:phone":"+1 626 571 0636",
    "sg:postcode":"91754",
    "sg:province":"CA",
    "sg:tags":[
        "chinese"
    ],
    "wof:name":"Dean Sin World",
    "wof:placetype":"venue"
},
  "geometry": {"coordinates":[-118.12227,34.065042],"type":"Point"}
}