{
  "type": "Feature",
  "properties": {
    "addr:full":"13236 Crenshaw Blvd Gardena CA 90249",
    "addr:housenumber":"13236",
    "addr:postcode":"90249",
    "addr:street":"Crenshaw Blvd",
    "iso:country":"US",
    "sg:address":"13236 Crenshaw Blvd",
    "sg:city":"Gardena",
    "sg:classifiers":[
        {
            "category":"Shopping",
            "subcategory":"Jewelry",
            "type":"Retail Goods"
        }
    ],
    "sg:phone":"+1 310 327 2323",
    "sg:postcode":"90249",
    "sg:province":"CA",
    "sg:website":"www.denisbrand.com",
    "wof:name":"Brand Denis",
    "wof:placetype":"venue"
},
  "geometry": {"coordinates":[-118.327003,33.911598],"type":"Point"}
}