{
  "type": "Feature",
  "properties": {
    "addr:full":"4760 Mission Gorge Pl Ste B San Diego CA 92120",
    "addr:housenumber":"4760",
    "addr:postcode":"92120",
    "addr:street":"Mission Gorge Pl Ste B",
    "iso:country":"US",
    "sg:address":"4760 Mission Gorge Pl Ste B",
    "sg:city":"San Diego",
    "sg:classifiers":[
        {
            "category":"Shopping",
            "subcategory":"Bicycles & Sporting Goods",
            "type":"Retail Goods"
        },
        {
            "category":"Shopping",
            "subcategory":"Shoes",
            "type":"Retail Goods"
        }
    ],
    "sg:phone":"+1 619 265 7374",
    "sg:postcode":"92120",
    "sg:province":"CA",
    "sg:tags":[
        "store"
    ],
    "sg:website":"www.sdri.net",
    "wof:name":"San Diego Running Institute",
    "wof:placetype":"venue"
},
  "geometry": {"coordinates":[-117.091004,32.781491],"type":"Point"}
}