{
  "type": "Feature",
  "properties": {
    "iso:country":"US",
    "sg:address":"7059 Owensmouth Ave",
    "sg:city":"Canoga Park",
    "sg:classifiers":[
        {
            "category":"Recreation",
            "type":"Entertainment"
        }
    ],
    "sg:phone":"+1 818 340 9007",
    "sg:postcode":"91303",
    "sg:province":"CA",
    "sg:tags":[
        "astrologer"
    ],
    "wof:name":"California Astrology Assn",
    "wof:placetype":"venue"
},
  "geometry": {"coordinates":[-118.601634,34.198124],"type":"Point"}
}