{
  "type": "Feature",
  "properties": {
    "iso:country":"US",
    "sg:address":"221 Los Gatos -Saratoga Road",
    "sg:city":"Los Gatos",
    "sg:classifiers":[
        {
            "category":"Banks & Credit Unions",
            "subcategory":"Financial Services",
            "type":"Services"
        }
    ],
    "sg:phone":"+1 408 667 2912",
    "sg:postcode":"95030",
    "sg:province":"CA",
    "sg:tags":[
        "broker",
        "mortgage"
    ],
    "sg:website":"loans.princetoncap.com/reneemorg...",
    "wof:name":"Renee Morgan - Princeton Capital",
    "wof:placetype":"venue"
},
  "geometry": {"coordinates":[-121.981703,37.229411],"type":"Point"}
}