{
  "type": "Feature",
  "properties": {
    "iso:country":"US",
    "sg:address":"3700 Mt Diablo Blvd",
    "sg:city":"Lafayette",
    "sg:classifiers":[
        {
            "category":"Professional",
            "subcategory":"Lawyer & Legal Services",
            "type":"Services"
        }
    ],
    "sg:phone":"+1 925 284 7881",
    "sg:postcode":"94549",
    "sg:province":"CA",
    "sg:tags":[
        "attorney"
    ],
    "wof:name":"Magany & Abbass Law Offices",
    "wof:placetype":"venue"
},
  "geometry": {"coordinates":[-122.13171800000001,37.889519],"type":"Point"}
}