{
  "type": "Feature",
  "properties": {
    "addr:full":"2115 San Juan Rd Aromas CA 95004",
    "addr:housenumber":"2115",
    "addr:postcode":"ca 95004",
    "addr:street":"San Juan Rd",
    "iso:country":"US",
    "sg:address":"2115 San Juan Rd",
    "sg:city":"Aromas",
    "sg:classifiers":[
        {
            "category":"Professional",
            "subcategory":"Computer Services",
            "type":"Services"
        }
    ],
    "sg:phone":"+1 831 726 3989",
    "sg:postcode":"95004",
    "sg:province":"CA",
    "sg:tags":[
        "consultant",
        "designer"
    ],
    "wof:name":"Intel Corp",
    "wof:placetype":"venue"
},
  "geometry": {"coordinates":[-121.666898,36.8718],"type":"Point"}
}