{
  "type": "Feature",
  "properties": {
    "addr:full":"360 E 4th St Perris CA 92570",
    "addr:housenumber":"360",
    "addr:postcode":"92570",
    "addr:street":"E 4Th St",
    "iso:country":"US",
    "sg:address":"360 E 4th St",
    "sg:city":"Perris",
    "sg:classifiers":[
        {
            "category":"Wholesale",
            "subcategory":"Non-durable Goods",
            "type":"Manufacturing & Wholesale Goods"
        },
        {
            "category":"Shopping",
            "subcategory":"Gifts & Souvenirs",
            "type":"Retail Goods"
        }
    ],
    "sg:phone":"+1 951 657 9658",
    "sg:postcode":"92570",
    "sg:province":"CA",
    "sg:tags":[
        "party",
        "supply"
    ],
    "wof:name":"Annie's Party Supplies",
    "wof:placetype":"venue"
},
  "geometry": {"coordinates":[-117.220463,33.782464],"type":"Point"}
}