{
  "type": "Feature",
  "properties": {
    "addr:full":"6505 Hollywood Blvd Los Angeles CA 90028",
    "addr:housenumber":"6505",
    "addr:postcode":"90028",
    "addr:street":"Hollywood Blvd",
    "iso:country":"US",
    "sg:address":"6505 Hollywood Blvd",
    "sg:city":"Los Angeles",
    "sg:classifiers":[
        {
            "category":"Shopping",
            "subcategory":"Catalog Store",
            "type":"Retail Goods"
        }
    ],
    "sg:phone":"+1 323 465 3335",
    "sg:postcode":"90028",
    "sg:province":"CA",
    "sg:tags":[
        "mail",
        "order"
    ],
    "wof:name":"Liquid Dreams",
    "wof:placetype":"venue"
},
  "geometry": {"coordinates":[-118.331913,34.101664],"type":"Point"}
}