{
  "type": "Feature",
  "properties": {
    "iso:country":"US",
    "sg:address":"5845 Doverwood Dr",
    "sg:city":"Culver City",
    "sg:classifiers":[
        {
            "category":"Insurance",
            "subcategory":"Hazard Insurance",
            "type":"Services"
        }
    ],
    "sg:phone":"+1 310 670 6407",
    "sg:postcode":"90230",
    "sg:province":"CA",
    "wof:name":"Mc Claire Insurance Agency",
    "wof:placetype":"venue"
},
  "geometry": {"coordinates":[-118.389508,33.982236],"type":"Point"}
}