{
  "type": "Feature",
  "properties": {
    "iso:country":"US",
    "sg:address":"2594 Rio Linda Blvd",
    "sg:city":"Sacramento",
    "sg:classifiers":[
        {
            "category":"Professional",
            "type":"Services"
        }
    ],
    "sg:phone":"+1 916 444 8892",
    "sg:postcode":"95815",
    "sg:province":"CA",
    "sg:tags":[
        "establishment"
    ],
    "wof:name":"Cfma",
    "wof:placetype":"venue"
},
  "geometry": {"coordinates":[-121.447861,38.612963],"type":"Point"}
}