{
  "type": "Feature",
  "properties": {
    "iso:country":"US",
    "sg:address":"2540 Main Street",
    "sg:city":"Irvine",
    "sg:classifiers":[
        {
            "category":"Shopping",
            "subcategory":"Stationery & Office Supplies",
            "type":"Retail Goods"
        }
    ],
    "sg:phone":"+1 949 852 0711",
    "sg:postcode":"92614",
    "sg:province":"CA",
    "sg:tags":[
        "equipment"
    ],
    "wof:name":"Cort Furniture Rental",
    "wof:placetype":"venue"
},
  "geometry": {"coordinates":[-117.84424,33.682713],"type":"Point"}
}