{
  "type": "Feature",
  "properties": {
    "addr:full":"849 W Louise St Colton CA 92324",
    "addr:housenumber":"849",
    "addr:postcode":"92324",
    "addr:street":"W Louise St",
    "iso:country":"US",
    "sg:address":"849 W Louise St",
    "sg:city":"Colton",
    "sg:classifiers":[
        {
            "category":"Restaurant",
            "type":"Food & Drink"
        }
    ],
    "sg:phone":"+1 909 885 0626",
    "sg:postcode":"92324",
    "sg:province":"CA",
    "wof:name":"Manuelita's Mexican Food",
    "wof:placetype":"venue"
},
  "geometry": {"coordinates":[-117.336348,34.090197],"type":"Point"}
}