{
  "type": "Feature",
  "properties": {
    "addr:full":"171 Saxony Rd Encinitas CA 92024",
    "addr:housenumber":"171",
    "addr:postcode":"92024",
    "addr:street":"Saxony Rd",
    "iso:country":"US",
    "sg:address":"171 Saxony Rd",
    "sg:city":"Encinitas",
    "sg:classifiers":[
        {
            "category":"Banks & Credit Unions",
            "subcategory":"Bank",
            "type":"Services"
        }
    ],
    "sg:phone":"+1 760 479 3580",
    "sg:postcode":"92024",
    "sg:province":"CA",
    "sg:tags":[
        "financing"
    ],
    "wof:name":"Dougherty Funding",
    "wof:placetype":"venue"
},
  "geometry": {"coordinates":[-117.28557000000001,33.050369],"type":"Point"}
}