{
  "type": "Feature",
  "properties": {
    "addr:full":"1041 Yorba Linda Blvd Placentia CA 92870",
    "addr:housenumber":"1041",
    "addr:postcode":"ca 92870",
    "addr:street":"Yorba Linda Blvd",
    "iso:country":"US",
    "sg:address":"1041 Yorba Linda Blvd",
    "sg:city":"Placentia",
    "sg:classifiers":[
        {
            "category":"Professional",
            "type":"Services"
        }
    ],
    "sg:phone":"+1 714 524 0055",
    "sg:postcode":"92870",
    "sg:province":"CA",
    "wof:name":"Pommgi",
    "wof:placetype":"venue"
},
  "geometry": {"coordinates":[-117.84624700000001,33.88913],"type":"Point"}
}