{
  "type": "Feature",
  "properties": {
    "iso:country":"US",
    "sg:address":"1041 Yorba Linda Blvd",
    "sg:city":"Placentia",
    "sg:classifiers":[
        {
            "category":"Professional",
            "type":"Services"
        }
    ],
    "sg:phone":"+1 714 524 0055",
    "sg:postcode":"92870",
    "sg:province":"CA",
    "wof:name":"Pommgi",
    "wof:placetype":"venue"
},
  "geometry": {"coordinates":[-117.846247,33.88913],"type":"Point"}
}