{
  "type": "Feature",
  "properties": {
    "addr:full":"1160 Illinois St San Francisco CA 94107",
    "addr:housenumber":"1160",
    "addr:postcode":"94107",
    "addr:street":"Illinois St",
    "iso:country":"US",
    "sg:address":"1160 Illinois St",
    "sg:city":"San Francisco",
    "sg:classifiers":[
        {
            "category":"Real Estate",
            "subcategory":"Real Estate Services",
            "type":"Services"
        }
    ],
    "sg:phone":"+1 415 621 3700",
    "sg:postcode":"94107",
    "sg:province":"CA",
    "sg:website":"www.bellacasasf.com",
    "wof:name":"Bella Casa Home Staging",
    "wof:placetype":"venue"
},
  "geometry": {"coordinates":[-122.38727,37.75725],"type":"Point"}
}