{
  "type": "Feature",
  "properties": {
    "addr:full":"6 Governors Ln Chico CA 95926",
    "addr:housenumber":"6",
    "addr:postcode":"95926",
    "addr:street":"Governors Ln",
    "iso:country":"US",
    "sg:address":"6 Governors Ln",
    "sg:city":"Chico",
    "sg:classifiers":[
        {
            "category":"Professional",
            "type":"Services"
        }
    ],
    "sg:phone":"+1 530 898 0109",
    "sg:postcode":"95926",
    "sg:province":"CA",
    "wof:name":"Steven Hammond Lcsw",
    "wof:placetype":"venue"
},
  "geometry": {"coordinates":[-121.858431,39.755352],"type":"Point"}
}