{
  "type": "Feature",
  "properties": {
    "addr:full":"1055 N Van Ness Ave Fresno CA 93728",
    "addr:housenumber":"1055",
    "addr:postcode":"93728",
    "addr:street":"N Van Ness Ave",
    "iso:country":"US",
    "sg:address":"1055 N Van Ness Ave",
    "sg:city":"Fresno",
    "sg:classifiers":[
        {
            "category":"Home & Garden",
            "subcategory":"Building Materials",
            "type":"Retail Goods"
        }
    ],
    "sg:phone":"+1 559 268 0332",
    "sg:postcode":"93728",
    "sg:province":"CA",
    "sg:tags":[
        "paint"
    ],
    "wof:name":"International Coding & Chem",
    "wof:placetype":"venue"
},
  "geometry": {"coordinates":[-119.79891499999999,36.755939],"type":"Point"}
}