{
  "type": "Feature",
  "properties": {
    "addr:full":"721 Mountain View Ave Petaluma CA 94952",
    "addr:housenumber":"721",
    "addr:postcode":"94952",
    "addr:street":"Mountain View Ave",
    "iso:country":"US",
    "sg:address":"721 Mountain View Ave",
    "sg:city":"Petaluma",
    "sg:classifiers":[
        {
            "category":"Building & Trades",
            "subcategory":"Construction",
            "type":"Services"
        }
    ],
    "sg:phone":"+1 707 769 1002",
    "sg:postcode":"94952",
    "sg:province":"CA",
    "sg:tags":[
        "repair",
        "handyman",
        "maintenance",
        "home"
    ],
    "wof:name":"Gwp Service",
    "wof:placetype":"venue"
},
  "geometry": {"coordinates":[-122.62782300000001,38.224281],"type":"Point"}
}