{
  "type": "Feature",
  "properties": {
    "iso:country":"US",
    "sg:address":"2200 E Anaheim St",
    "sg:city":"Long Beach",
    "sg:classifiers":[
        {
            "category":"Arts & Performance",
            "subcategory":"Theater",
            "type":"Entertainment"
        }
    ],
    "sg:phone":"+1 562 987 4212",
    "sg:postcode":"90804",
    "sg:province":"CA",
    "sg:tags":[
        "karaoke"
    ],
    "wof:name":"Reek Reay Karaoke",
    "wof:placetype":"venue"
},
  "geometry": {"coordinates":[-118.164385,33.782603],"type":"Point"}
}