{
  "type": "Feature",
  "properties": {
    "addr:full":"5425 Broadway St American Canyon CA 94503",
    "addr:housenumber":"5425",
    "addr:postcode":"94503",
    "addr:street":"Broadway St",
    "iso:country":"US",
    "sg:address":"5425 Broadway St",
    "sg:city":"American Canyon",
    "sg:classifiers":[
        {
            "category":"Manufacturing",
            "subcategory":"Metals",
            "type":"Manufacturing & Wholesale Goods"
        }
    ],
    "sg:phone":"+1 707 257 6481",
    "sg:postcode":"94503",
    "sg:province":"CA",
    "sg:tags":[
        "cap",
        "bottle",
        "seal"
    ],
    "sg:website":"www.alcan.com",
    "wof:name":"Pechiney Cork & Seal Of Ca INC",
    "wof:placetype":"venue"
},
  "geometry": {"coordinates":[-122.25623299999999,38.204755],"type":"Point"}
}