{
  "type": "Feature",
  "properties": {
    "addr:full":"10740 Washington Blvd Culver City CA 90232",
    "addr:housenumber":"10740",
    "addr:postcode":"90232",
    "addr:street":"Washington Blvd",
    "iso:country":"US",
    "sg:address":"10740 Washington Blvd",
    "sg:city":"Culver City",
    "sg:classifiers":[
        {
            "category":"Home & Garden",
            "subcategory":"Furniture",
            "type":"Retail Goods"
        }
    ],
    "sg:phone":"+1 310 845 9328",
    "sg:postcode":"90232",
    "sg:province":"CA",
    "sg:tags":[
        "mattress"
    ],
    "wof:name":"Ortho Mattress",
    "wof:placetype":"venue"
},
  "geometry": {"coordinates":[-118.40716,34.015321],"type":"Point"}
}