{
  "type": "Feature",
  "properties": {
    "addr:full":"555 N Mathilda Ave Sunnyvale CA 94085",
    "addr:housenumber":"555",
    "addr:postcode":"94085",
    "addr:street":"N Mathilda Ave",
    "iso:country":"US",
    "sg:address":"555 N Mathilda Ave",
    "sg:city":"Sunnyvale",
    "sg:classifiers":[
        {
            "category":"Banks & Credit Unions",
            "subcategory":"Bank",
            "type":"Services"
        }
    ],
    "sg:phone":"+1 408 733 3880",
    "sg:postcode":"94085",
    "sg:province":"CA",
    "sg:tags":[
        "loan"
    ],
    "wof:name":"Cashflow Connections",
    "wof:placetype":"venue"
},
  "geometry": {"coordinates":[-122.030405,37.390773],"type":"Point"}
}