{
  "type": "Feature",
  "properties": {
    "addr:full":"Altadena Dr & New Yo Pasadena CA 91101",
    "addr:postcode":"91101",
    "addr:street":"Altadena Dr &",
    "iso:country":"US",
    "sg:address":"Altadena Dr & New Yo",
    "sg:city":"Pasadena",
    "sg:classifiers":[
        {
            "category":"Autos & Motor Vehicles",
            "subcategory":"Fuel & Gas Station",
            "type":"Retail Goods"
        },
        {
            "category":"Government",
            "subcategory":"Office",
            "type":"Public Place"
        }
    ],
    "sg:phone":"+1 626 797 0369",
    "sg:postcode":"91101",
    "sg:province":"CA",
    "sg:tags":[
        "smog",
        "check"
    ],
    "wof:name":"Bp-Arco",
    "wof:placetype":"venue"
},
  "geometry": {"coordinates":[-118.13800000000001,34.143002],"type":"Point"}
}