{
  "type": "Feature",
  "properties": {
    "addr:full":"2535 Vista Way Oceanside CA 92054",
    "addr:housenumber":"2535",
    "addr:postcode":"92054",
    "addr:street":"Vista Way",
    "iso:country":"US",
    "sg:address":"2535 Vista Way",
    "sg:city":"Oceanside",
    "sg:classifiers":[
        {
            "category":"Cinema",
            "subcategory":"Movie Rental",
            "type":"Entertainment"
        }
    ],
    "sg:phone":"+1 760 721 8102",
    "sg:postcode":"92054",
    "sg:province":"CA",
    "sg:tags":[
        "game",
        "video"
    ],
    "sg:website":"www.gamestop.com",
    "wof:name":"Gamestop",
    "wof:placetype":"venue"
},
  "geometry": {"coordinates":[-117.333,33.183201],"type":"Point"}
}