{
  "type": "Feature",
  "properties": {
    "addr:full":"9016 Archibald Ave Rancho Cucamonga CA 91730",
    "addr:housenumber":"9016",
    "addr:postcode":"91730",
    "addr:street":"Archibald Ave",
    "iso:country":"US",
    "sg:address":"9016 Archibald Ave",
    "sg:city":"Rancho Cucamonga",
    "sg:classifiers":[
        {
            "category":"Manufacturing",
            "subcategory":"Printing",
            "type":"Manufacturing & Wholesale Goods"
        }
    ],
    "sg:phone":"+1 909 989 8550",
    "sg:postcode":"91730",
    "sg:province":"CA",
    "sg:tags":[
        "printer"
    ],
    "wof:name":"Alpha Graphics",
    "wof:placetype":"venue"
},
  "geometry": {"coordinates":[-117.593546,34.088524],"type":"Point"}
}