{
  "type": "Feature",
  "properties": {
    "addr:full":"121 S School St Lodi CA 95240",
    "addr:housenumber":"121",
    "addr:postcode":"95240",
    "addr:street":"S School St",
    "iso:country":"US",
    "sg:address":"121 S School St",
    "sg:city":"Lodi",
    "sg:classifiers":[
        {
            "category":"Shopping",
            "subcategory":"Used Merchandise",
            "type":"Retail Goods"
        }
    ],
    "sg:phone":"+1 209 339 8454",
    "sg:postcode":"95240",
    "sg:province":"CA",
    "sg:tags":[
        "book"
    ],
    "wof:name":"Old Town Antiques",
    "wof:placetype":"venue"
},
  "geometry": {"coordinates":[-121.273895,38.132035],"type":"Point"}
}