{
  "type": "Feature",
  "properties": {
    "addr:full":"1406 Micheltorena St Los Angeles CA 90026",
    "addr:housenumber":"1406",
    "addr:postcode":"90026",
    "addr:street":"Micheltorena St",
    "iso:country":"US",
    "sg:address":"1406 Micheltorena St",
    "sg:city":"Los Angeles",
    "sg:classifiers":[
        {
            "category":"Shopping",
            "subcategory":"Clothing, Apparel, & Fashions",
            "type":"Retail Goods"
        }
    ],
    "sg:phone":"+1 323 663 1793",
    "sg:postcode":"90026",
    "sg:province":"CA",
    "sg:tags":[
        "item",
        "boutique"
    ],
    "wof:name":"Aorta Los Angeles",
    "wof:placetype":"venue"
},
  "geometry": {"coordinates":[-118.275215,34.088352],"type":"Point"}
}