{
  "type": "Feature",
  "properties": {
    "addr:full":"404 S Figueroa Street Los Angeles CA 90071",
    "addr:housenumber":"404",
    "addr:postcode":"90071",
    "addr:street":"S Figueroa Street",
    "iso:country":"US",
    "sg:address":"404 S Figueroa Street",
    "sg:city":"Los Angeles",
    "sg:classifiers":[
        {
            "category":"Restaurant",
            "type":"Food & Drink"
        }
    ],
    "sg:phone":"+1 213 627 2899",
    "sg:postcode":"90071",
    "sg:province":"CA",
    "sg:tags":[
        "pizza"
    ],
    "wof:name":"The Gourmet Pizzeria",
    "wof:placetype":"venue"
},
  "geometry": {"coordinates":[-118.256503,34.053123],"type":"Point"}
}