{
  "type": "Feature",
  "properties": {
    "addr:full":"3001 High St Ste A Oakland CA 94619",
    "addr:housenumber":"3001",
    "addr:postcode":"94619",
    "addr:street":"High St Ste A",
    "iso:country":"US",
    "sg:address":"3001 High St Ste A",
    "sg:city":"Oakland",
    "sg:classifiers":[
        {
            "category":"Health Services",
            "subcategory":"Dentist",
            "type":"Services"
        }
    ],
    "sg:phone":"+1 510 436 4715",
    "sg:postcode":"94619",
    "sg:province":"CA",
    "wof:name":"John W Gaines, DDS",
    "wof:placetype":"venue"
},
  "geometry": {"coordinates":[-122.200687,37.784603],"type":"Point"}
}