{
  "type": "Feature",
  "properties": {
    "iso:country":"US",
    "sg:address":"8550 Balboa Blvd Ste 250",
    "sg:city":"Northridge",
    "sg:classifiers":[
        {
            "category":"Retail",
            "subcategory":"Repair Shop",
            "type":"Services"
        },
        {
            "category":"Professional",
            "subcategory":"Computer Services",
            "type":"Services"
        }
    ],
    "sg:phone":"+1 818 894 0744",
    "sg:postcode":"91325",
    "sg:province":"CA",
    "sg:tags":[
        "designer",
        "technical",
        "repair-business",
        "assistance",
        "system",
        "equipment-service",
        "support",
        "consultant"
    ],
    "sg:website":"http://www.bgind.com",
    "wof:name":"Saic Inc",
    "wof:placetype":"venue"
},
  "geometry": {"coordinates":[-118.50263200000001,34.224675],"type":"Point"}
}