{
  "type": "Feature",
  "properties": {
    "addr:full":"14380 Euclid Ave Chino CA 91710",
    "addr:housenumber":"14380",
    "addr:postcode":"91710",
    "addr:street":"Euclid Ave",
    "iso:country":"US",
    "sg:address":"14380 Euclid Ave",
    "sg:city":"Chino",
    "sg:classifiers":[
        {
            "category":"Real Estate",
            "subcategory":"Real Estate Agent",
            "type":"Services"
        }
    ],
    "sg:phone":"+1 909 597 7883",
    "sg:postcode":"91710",
    "sg:province":"CA",
    "wof:name":"Vander Dussen & Haringsma",
    "wof:placetype":"venue"
},
  "geometry": {"coordinates":[-117.65075299999999,33.995857],"type":"Point"}
}