{
  "type": "Feature",
  "properties": {
    "iso:country":"US",
    "sg:address":"2842 Gratton St",
    "sg:city":"Riverside",
    "sg:classifiers":[
        {
            "category":"Manufacturing",
            "subcategory":"Signs",
            "type":"Manufacturing & Wholesale Goods"
        }
    ],
    "sg:phone":"+1 951 351 1155",
    "sg:postcode":"92504",
    "sg:province":"CA",
    "wof:name":"Timsigns",
    "wof:placetype":"venue"
},
  "geometry": {"coordinates":[-117.415227,33.915316],"type":"Point"}
}