{
  "type": "Feature",
  "properties": {
    "addr:full":"278 S Madera Ave Kerman CA 93630",
    "addr:housenumber":"278",
    "addr:postcode":"93630",
    "addr:street":"S Madera Ave",
    "iso:country":"US",
    "sg:address":"278 S Madera Ave",
    "sg:city":"Kerman",
    "sg:classifiers":[
        {
            "category":"Personal",
            "subcategory":"Beauty Salon",
            "type":"Services"
        }
    ],
    "sg:phone":"+1 559 846 8199",
    "sg:postcode":"93630",
    "sg:province":"CA",
    "wof:name":"Hair Studio II",
    "wof:placetype":"venue"
},
  "geometry": {"coordinates":[-120.060069,36.731608],"type":"Point"}
}