{
  "type": "Feature",
  "properties": {
    "addr:full":"1445 Oakland Rd San Jose CA 95112",
    "addr:housenumber":"1445",
    "addr:postcode":"95112",
    "addr:street":"Oakland Rd",
    "iso:country":"US",
    "sg:address":"1445 Oakland Rd",
    "sg:city":"San Jose",
    "sg:classifiers":[
        {
            "category":"Organizations",
            "subcategory":"Membership Organization",
            "type":"Services"
        }
    ],
    "sg:phone":"+1 408 971 2789",
    "sg:postcode":"95112",
    "sg:province":"CA",
    "wof:name":"ESO Energy Assistance",
    "wof:placetype":"venue"
},
  "geometry": {"coordinates":[-121.89410599999999,37.372954],"type":"Point"}
}