{
  "type": "Feature",
  "properties": {
    "addr:full":"11418 Missouri Ave Los Angeles CA 90025",
    "addr:housenumber":"11418",
    "addr:postcode":"90025",
    "addr:street":"Missouri Ave",
    "iso:country":"US",
    "sg:address":"11418 Missouri Ave",
    "sg:city":"Los Angeles",
    "sg:classifiers":[
        {
            "category":"Professional",
            "type":"Services"
        }
    ],
    "sg:phone":"+1 310 966 1010",
    "sg:postcode":"90025",
    "sg:province":"CA",
    "wof:name":"Corcoran Gallery",
    "wof:placetype":"venue"
},
  "geometry": {"coordinates":[-118.447188,34.041086],"type":"Point"}
}