{
  "type": "Feature",
  "properties": {
    "iso:country":"US",
    "sg:address":"2555 E. Del Amo Blvd.",
    "sg:city":"Los Angeles",
    "sg:classifiers":[
        {
            "category":"Personal",
            "type":"Services"
        }
    ],
    "sg:phone":"+1 800 709 7007",
    "sg:postcode":"90006",
    "sg:province":"CA",
    "sg:tags":[
        "party",
        "planning",
        "event"
    ],
    "sg:website":"www.designer8furniturerental.com",
    "wof:name":"Designer 8 Event Furniture Rental",
    "wof:placetype":"venue"
},
  "geometry": {"coordinates":[-118.218148,33.846713],"type":"Point"}
}