{
  "type": "Feature",
  "properties": {
    "iso:country":"US",
    "sg:address":"10839 Central Ave",
    "sg:city":"Ontario",
    "sg:classifiers":[
        {
            "category":"Personal",
            "type":"Services"
        }
    ],
    "sg:phone":"+1 909 627 1917",
    "sg:postcode":"91762",
    "sg:province":"CA",
    "sg:tags":[
        "therapist",
        "massage"
    ],
    "wof:name":"Tokyo Health Studio",
    "wof:placetype":"venue"
},
  "geometry": {"coordinates":[-117.689291,34.056126],"type":"Point"}
}