{
  "type": "Feature",
  "properties": {
    "iso:country":"US",
    "sg:address":"3865 24th St",
    "sg:city":"San Francisco",
    "sg:classifiers":[
        {
            "category":"Retail",
            "subcategory":"Car Wash",
            "type":"Services"
        }
    ],
    "sg:phone":"+1 415 593 8100",
    "sg:postcode":"94114",
    "sg:province":"CA",
    "sg:tags":[
        "automobile",
        "detail",
        "clean"
    ],
    "wof:name":"Auto Preparation",
    "wof:placetype":"venue"
},
  "geometry": {"coordinates":[-122.429397,37.751516],"type":"Point"}
}