{
  "type": "Feature",
  "properties": {
    "iso:country":"US",
    "sg:address":"27976 Spring Ln",
    "sg:city":"Keene",
    "sg:classifiers":[
        {
            "category":"Manufacturing",
            "subcategory":"Textiles",
            "type":"Manufacturing & Wholesale Goods"
        }
    ],
    "sg:phone":"+1 661 872 9071",
    "sg:postcode":"93546",
    "sg:province":"CA",
    "sg:tags":[
        "hosiery",
        "mfg"
    ],
    "wof:name":"Fancy Feats",
    "wof:placetype":"venue"
},
  "geometry": {"coordinates":[-118.986373,37.650681],"type":"Point"}
}