{
  "type": "Feature",
  "properties": {
    "addr:full":"139 N Barranca St West Covina CA 91791",
    "addr:housenumber":"139",
    "addr:postcode":"91791",
    "addr:street":"N Barranca St",
    "iso:country":"US",
    "sg:address":"139 N Barranca St",
    "sg:city":"West Covina",
    "sg:classifiers":[
        {
            "category":"Restaurant",
            "type":"Food & Drink"
        }
    ],
    "sg:menulink":"http://www.allmenus.com/ca/east-san-gabriel-valley/8460-islands/menu/",
    "sg:phone":"+1 626 331 6223",
    "sg:postcode":"91791",
    "sg:province":"CA",
    "sg:tags":[
        "burger",
        "american"
    ],
    "wof:name":"Islands Fine Burgers & Drinks",
    "wof:placetype":"venue"
},
  "geometry": {"coordinates":[-117.881351,34.072468],"type":"Point"}
}