{
  "type": "Feature",
  "properties": {
    "addr:full":"1070 Onstott Rd Lompoc CA 93436",
    "addr:housenumber":"1070",
    "addr:postcode":"93436",
    "addr:street":"Onstott Rd",
    "iso:country":"US",
    "sg:address":"1070 Onstott Rd",
    "sg:city":"Lompoc",
    "sg:classifiers":[
        {
            "category":"Health Services",
            "subcategory":"Medical Lab",
            "type":"Services"
        }
    ],
    "sg:phone":"+1 805 733 3922",
    "sg:postcode":"93436",
    "sg:province":"CA",
    "sg:tags":[
        "laboratory",
        "dental"
    ],
    "wof:name":"Razo Dental Laboratory",
    "wof:placetype":"venue"
},
  "geometry": {"coordinates":[-120.44544999999999,34.68317],"type":"Point"}
}