{
  "type": "Feature",
  "properties": {
    "iso:country":"US",
    "sg:address":"6642 Reseda Blvd",
    "sg:city":"Reseda",
    "sg:classifiers":[
        {
            "category":"Organizations",
            "subcategory":"Religious Organization",
            "type":"Services"
        }
    ],
    "sg:phone":"+1 818 776 9696",
    "sg:postcode":"91335",
    "sg:province":"CA",
    "sg:tags":[
        "church"
    ],
    "sg:website":"www.valleyvineyard.org",
    "wof:name":"Valley Vineyard Christian",
    "wof:placetype":"venue"
},
  "geometry": {"coordinates":[-118.53595900000001,34.193373],"type":"Point"}
}