{
  "type": "Feature",
  "properties": {
    "iso:country":"US",
    "sg:address":"5211 Tujunga Blvd",
    "sg:city":"North Hollywood",
    "sg:classifiers":[
        {
            "category":"Sports & Exercise",
            "subcategory":"Playing Field",
            "type":"Entertainment"
        }
    ],
    "sg:postcode":"91601",
    "sg:province":"CA",
    "sg:tags":[
        "instruction",
        "fitness"
    ],
    "sg:website":"www.midnightridazz.com",
    "wof:name":"Midnight Ridazz - North Hollywood",
    "wof:placetype":"venue"
},
  "geometry": {"coordinates":[-118.378963,34.166485],"type":"Point"}
}