{
  "type": "Feature",
  "properties": {
    "iso:country":"US",
    "sg:address":"51420 Cll Jacumba",
    "sg:city":"La Quinta",
    "sg:classifiers":[
        {
            "category":"Retail",
            "subcategory":"Auto Repair",
            "type":"Services"
        }
    ],
    "sg:phone":"+1 760 771 8034",
    "sg:postcode":"92253",
    "sg:province":"CA",
    "sg:tags":[
        "road"
    ],
    "wof:name":"Franco's Road Svc",
    "wof:placetype":"venue"
},
  "geometry": {"coordinates":[-116.296049,33.675884],"type":"Point"}
}