{
  "type": "Feature",
  "properties": {
    "iso:country":"US",
    "sg:address":"897 Broadleaf Lane",
    "sg:city":"San Jose",
    "sg:classifiers":[
        {
            "category":"Education",
            "subcategory":"Preschool",
            "type":"Public Place"
        },
        {
            "category":"Education",
            "subcategory":"School",
            "type":"Public Place"
        }
    ],
    "sg:phone":"+1 408 551 0312",
    "sg:postcode":"95128",
    "sg:province":"CA",
    "sg:tags":[
        "elementary"
    ],
    "wof:name":"Pace Pre-School",
    "wof:placetype":"venue"
},
  "geometry": {"coordinates":[-121.941726,37.331883],"type":"Point"}
}