{
  "type": "Feature",
  "properties": {
    "addr:full":"57 W Portal Ave San Francisco CA 94127",
    "addr:housenumber":"57",
    "addr:postcode":"94127",
    "addr:street":"W Portal Ave",
    "iso:country":"US",
    "sg:address":"57 W Portal Ave",
    "sg:city":"San Francisco",
    "sg:classifiers":[
        {
            "category":"Personal",
            "subcategory":"Beauty Salon",
            "type":"Services"
        }
    ],
    "sg:phone":"+1 415 753 6355",
    "sg:postcode":"94127",
    "sg:province":"CA",
    "sg:tags":[
        "manicuring"
    ],
    "wof:name":"Nails By Tai",
    "wof:placetype":"venue"
},
  "geometry": {"coordinates":[-122.46624300000001,37.740294],"type":"Point"}
}