{
  "type": "Feature",
  "properties": {
    "iso:country":"US",
    "sg:address":"12033 Scripps Summit Dr",
    "sg:city":"San Diego",
    "sg:classifiers":[
        {
            "category":"Autos & Motor Vehicles",
            "subcategory":"Fuel & Gas Station",
            "type":"Retail Goods"
        }
    ],
    "sg:phone":"+1 858 621 6337",
    "sg:postcode":"92131",
    "sg:province":"CA",
    "sg:tags":[
        "oil"
    ],
    "wof:name":"Scripps Arco",
    "wof:placetype":"venue"
},
  "geometry": {"coordinates":[-117.100613,32.937279],"type":"Point"}
}