{
  "type": "Feature",
  "properties": {
    "addr:full":"7879 Armour St San Diego CA 92111",
    "addr:housenumber":"7879",
    "addr:postcode":"92111",
    "addr:street":"Armour St",
    "iso:country":"US",
    "sg:address":"7879 Armour St",
    "sg:city":"San Diego",
    "sg:classifiers":[
        {
            "category":"Shopping",
            "subcategory":"Clothing, Apparel, & Fashions",
            "type":"Retail Goods"
        }
    ],
    "sg:phone":"+1 858 279 9986",
    "sg:postcode":"92111",
    "sg:province":"CA",
    "sg:tags":[
        "t"
    ],
    "wof:name":"Mike's Custom Tees",
    "wof:placetype":"venue"
},
  "geometry": {"coordinates":[-117.15446900000001,32.81988],"type":"Point"}
}