{
  "type": "Feature",
  "properties": {
    "iso:country":"US",
    "sg:address":"5859 Rosebud Ln",
    "sg:city":"Sacramento",
    "sg:classifiers":[
        {
            "category":"Home & Garden",
            "subcategory":"Building Materials",
            "type":"Retail Goods"
        }
    ],
    "sg:phone":"+1 916 334 2326",
    "sg:postcode":"95841",
    "sg:province":"CA",
    "sg:tags":[
        "glass",
        "window",
        "plate"
    ],
    "wof:name":"Neighborhood Glass & Screen",
    "wof:placetype":"venue"
},
  "geometry": {"coordinates":[-121.32949000000001,38.674547],"type":"Point"}
}