{
  "type": "Feature",
  "properties": {
    "iso:country":"US",
    "sg:address":"6436 Bremen Dr",
    "sg:city":"Citrus Heights",
    "sg:classifiers":[
        {
            "category":"Building & Trades",
            "subcategory":"Cleaning & Sanitation",
            "type":"Services"
        }
    ],
    "sg:phone":"+1 916 729 0638",
    "sg:postcode":"95621",
    "sg:province":"CA",
    "sg:tags":[
        "house"
    ],
    "wof:name":"Housecleaning Done Right",
    "wof:placetype":"venue"
},
  "geometry": {"coordinates":[-121.314619,38.679401],"type":"Point"}
}