{
  "type": "Feature",
  "properties": {
    "addr:full":"18173 Pioneer Blvd Artesia CA 90701",
    "addr:housenumber":"18173",
    "addr:postcode":"90701",
    "addr:street":"Pioneer Blvd",
    "iso:country":"US",
    "sg:address":"18173 Pioneer Blvd",
    "sg:city":"Artesia",
    "sg:classifiers":[
        {
            "category":"Banks & Credit Unions",
            "subcategory":"Financial Services",
            "type":"Services"
        }
    ],
    "sg:phone":"+1 562 865 4040",
    "sg:postcode":"90701",
    "sg:province":"CA",
    "sg:tags":[
        "broker",
        "mortgage"
    ],
    "wof:name":"Leader Travel Services",
    "wof:placetype":"venue"
},
  "geometry": {"coordinates":[-118.244831,33.866652],"type":"Point"}
}