{
  "type": "Feature",
  "properties": {
    "iso:country":"US",
    "sg:address":"54 Main St",
    "sg:city":"Sutter Creek",
    "sg:classifiers":[
        {
            "category":"Shopping",
            "subcategory":"Clothing, Apparel, & Fashions",
            "type":"Retail Goods"
        }
    ],
    "sg:phone":"+1 209 267 9090",
    "sg:postcode":"95685",
    "sg:province":"CA",
    "wof:name":"Itemz",
    "wof:placetype":"venue"
},
  "geometry": {"coordinates":[-120.802937,38.393478],"type":"Point"}
}