{
  "type": "Feature",
  "properties": {
    "addr:full":"6634 Winding Creek Dr San Diego CA 92119",
    "addr:housenumber":"6634",
    "addr:postcode":"92119",
    "addr:street":"Winding Creek Dr",
    "iso:country":"US",
    "sg:address":"6634 Winding Creek Dr",
    "sg:city":"San Diego",
    "sg:classifiers":[
        {
            "category":"Professional",
            "subcategory":"Management & Consulting",
            "type":"Services"
        }
    ],
    "sg:phone":"+1 619 286 1132",
    "sg:postcode":"92119",
    "sg:province":"CA",
    "sg:tags":[
        "consultant",
        "training"
    ],
    "wof:name":"Orlando-Ward & Associates",
    "wof:placetype":"venue"
},
  "geometry": {"coordinates":[-117.052808,32.813929],"type":"Point"}
}