{
  "type": "Feature",
  "properties": {
    "addr:full":"4003 Goldfinch St San Diego CA 92103",
    "addr:housenumber":"4003",
    "addr:postcode":"92103",
    "addr:street":"Goldfinch St",
    "iso:country":"US",
    "sg:address":"4003 Goldfinch St",
    "sg:city":"San Diego",
    "sg:classifiers":[
        {
            "category":"Professional",
            "subcategory":"Management & Consulting",
            "type":"Services"
        }
    ],
    "sg:phone":"+1 619 220 0602",
    "sg:postcode":"92103",
    "sg:province":"CA",
    "sg:tags":[
        "consultant",
        "business"
    ],
    "wof:name":"Glaser Consulting",
    "wof:placetype":"venue"
},
  "geometry": {"coordinates":[-117.17131500000001,32.75082],"type":"Point"}
}