{
  "type": "Feature",
  "properties": {
    "addr:full":"5790 Fleet St Carlsbad CA 92008",
    "addr:housenumber":"5790",
    "addr:postcode":"92008",
    "addr:street":"Fleet St",
    "iso:country":"US",
    "sg:address":"5790 Fleet St",
    "sg:city":"Carlsbad",
    "sg:classifiers":[
        {
            "category":"Real Estate",
            "subcategory":"Real Estate Operator",
            "type":"Services"
        }
    ],
    "sg:phone":"+1 760 931 6800",
    "sg:postcode":"92008",
    "sg:province":"CA",
    "sg:tags":[
        "manager",
        "commercial",
        "agent"
    ],
    "wof:name":"Eop La Place Court",
    "wof:placetype":"venue"
},
  "geometry": {"coordinates":[-117.317527,33.130866],"type":"Point"}
}