{
  "type": "Feature",
  "properties": {
    "addr:full":"11600 Venice Blvd Los Angeles CA 90066",
    "addr:housenumber":"11600",
    "addr:postcode":"90066",
    "addr:street":"Venice Blvd",
    "iso:country":"US",
    "sg:address":"11600 Venice Blvd",
    "sg:city":"Los Angeles",
    "sg:classifiers":[
        {
            "category":"Health Services",
            "subcategory":"Hospital",
            "type":"Services"
        },
        {
            "category":"Community Center",
            "type":"Public Place"
        }
    ],
    "sg:phone":"+1 310 390 9551",
    "sg:postcode":"90066",
    "sg:province":"CA",
    "sg:tags":[
        "urgent",
        "medical",
        "care"
    ],
    "sg:website":"www.superiormedclinic.com",
    "wof:name":"Superior Multi-Specialty West LA Urgent Care",
    "wof:placetype":"venue"
},
  "geometry": {"coordinates":[-118.423778,34.008717],"type":"Point"}
}