{
  "type": "Feature",
  "properties": {
    "iso:country":"US",
    "sg:address":"4442 Gomes Rd",
    "sg:city":"Modesto",
    "sg:classifiers":[
        {
            "category":"Building & Trades",
            "subcategory":"Construction",
            "type":"Services"
        }
    ],
    "sg:phone":"+1 209 529 3882",
    "sg:postcode":"95357",
    "sg:province":"CA",
    "sg:tags":[
        "contractor"
    ],
    "wof:name":"Spoon Richard W General Building Contractor Inc",
    "wof:placetype":"venue"
},
  "geometry": {"coordinates":[-120.915001,37.657001],"type":"Point"}
}