{
  "type": "Feature",
  "properties": {
    "iso:country":"US",
    "sg:address":"77700 Enfield Ln",
    "sg:city":"Palm Desert",
    "sg:classifiers":[
        {
            "category":"Manufacturing",
            "subcategory":"Printing",
            "type":"Manufacturing & Wholesale Goods"
        }
    ],
    "sg:phone":"+1 760 345 0731",
    "sg:postcode":"92211",
    "sg:province":"CA",
    "sg:tags":[
        "screen",
        "commercial"
    ],
    "wof:name":"American Screen Printing",
    "wof:placetype":"venue"
},
  "geometry": {"coordinates":[-116.310378,33.760906],"type":"Point"}
}