{
  "type": "Feature",
  "properties": {
    "iso:country":"US",
    "sg:address":"10211 Country Club Dr",
    "sg:city":"Mira Loma",
    "sg:classifiers":[
        {
            "category":"Food & Beverages",
            "subcategory":"Groceries & Convenience Stores",
            "type":"Retail Goods"
        }
    ],
    "sg:phone":"+1 951 685 1429",
    "sg:postcode":"91752",
    "sg:province":"CA",
    "sg:tags":[
        "grocer"
    ],
    "wof:name":"Country Village Market",
    "wof:placetype":"venue"
},
  "geometry": {"coordinates":[-117.50824900000001,34.022863],"type":"Point"}
}