{
  "type": "Feature",
  "properties": {
    "iso:country":"US",
    "sg:address":"13070 Palmdale Rd",
    "sg:city":"Victorville",
    "sg:classifiers":[
        {
            "category":"Bars & Pubs",
            "type":"Food & Drink"
        }
    ],
    "sg:phone":"+1 760 241 7747",
    "sg:postcode":"92392",
    "sg:province":"CA",
    "wof:name":"Emily's Rocket Inn",
    "wof:placetype":"venue"
},
  "geometry": {"coordinates":[-117.37748499999999,34.506803],"type":"Point"}
}