{
  "type": "Feature",
  "properties": {
    "iso:country":"US",
    "sg:address":"10858 Norwalk Blvd",
    "sg:city":"Santa Fe Springs",
    "sg:classifiers":[
        {
            "category":"Wholesale",
            "subcategory":"Machinery & Supplies",
            "type":"Manufacturing & Wholesale Goods"
        }
    ],
    "sg:phone":"+1 562 425 2214",
    "sg:postcode":"90670",
    "sg:province":"CA",
    "sg:tags":[
        "truck"
    ],
    "sg:website":"www.2ndshiftlift.com",
    "wof:name":"2nd Shift Lift",
    "wof:placetype":"venue"
},
  "geometry": {"coordinates":[-118.07261,33.934625],"type":"Point"}
}