{
  "type": "Feature",
  "properties": {
    "iso:country":"US",
    "sg:address":"97 S. 2nd Street,Suite 210",
    "sg:city":"San Jose",
    "sg:classifiers":[
        {
            "category":"Professional",
            "subcategory":"Computer Services",
            "type":"Services"
        }
    ],
    "sg:postcode":"95113",
    "sg:province":"CA",
    "sg:website":"http://www.pinger.com/",
    "wof:name":"Pinger",
    "wof:placetype":"venue"
},
  "geometry": {"coordinates":[-121.88918099999999,37.336146],"type":"Point"}
}