{
  "type": "Feature",
  "properties": {
    "addr:full":"3555 Rosecrans St San Diego CA 92110",
    "addr:housenumber":"3555",
    "addr:postcode":"92110",
    "addr:street":"Rosecrans St",
    "iso:country":"US",
    "sg:address":"3555 Rosecrans St",
    "sg:city":"San Diego",
    "sg:classifiers":[
        {
            "category":"Restaurant",
            "type":"Food & Drink"
        }
    ],
    "sg:phone":"+1 619 223 2631",
    "sg:postcode":"92110",
    "sg:province":"CA",
    "wof:name":"Rubio's Restaurants Inc",
    "wof:placetype":"venue"
},
  "geometry": {"coordinates":[-117.206001,32.749901],"type":"Point"}
}