{
  "type": "Feature",
  "properties": {
    "iso:country":"US",
    "sg:address":"923 W Stockwell St",
    "sg:city":"Compton",
    "sg:classifiers":[
        {
            "category":"Building & Trades",
            "subcategory":"Plumbing",
            "type":"Services"
        }
    ],
    "sg:phone":"+1 310 638 5723",
    "sg:postcode":"90222",
    "sg:province":"CA",
    "sg:tags":[
        "contractor"
    ],
    "wof:name":"Oliver Plumbing",
    "wof:placetype":"venue"
},
  "geometry": {"coordinates":[-118.242921,33.909178],"type":"Point"}
}