{
  "type": "Feature",
  "properties": {
    "iso:country":"US",
    "sg:address":"941 The Alameda",
    "sg:city":"Berkeley",
    "sg:classifiers":[
        {
            "category":"Place Of Worship",
            "subcategory":"Church",
            "type":"Public Place"
        }
    ],
    "sg:phone":"+1 510 526 5553",
    "sg:postcode":"94707",
    "sg:province":"CA",
    "sg:website":"www.northbrae.org/",
    "wof:name":"Northbrae Community Church",
    "wof:placetype":"venue"
},
  "geometry": {"coordinates":[-122.277,37.8904],"type":"Point"}
}