{
  "type": "Feature",
  "properties": {
    "addr:full":"214 E Maple St Compton CA 90220",
    "addr:housenumber":"214",
    "addr:postcode":"90220",
    "addr:street":"E Maple St",
    "iso:country":"US",
    "sg:address":"214 E Maple St",
    "sg:city":"Compton",
    "sg:classifiers":[
        {
            "category":"Building & Trades",
            "subcategory":"Electrical",
            "type":"Services"
        }
    ],
    "sg:phone":"+1 310 632 0741",
    "sg:postcode":"90220",
    "sg:province":"CA",
    "sg:tags":[
        "electric",
        "contractor"
    ],
    "wof:name":"J Hooks Electric",
    "wof:placetype":"venue"
},
  "geometry": {"coordinates":[-118.221729,33.901924],"type":"Point"}
}