{
  "type": "Feature",
  "properties": {
    "iso:country":"US",
    "sg:address":"525 Laurel Street Suite 105",
    "sg:city":"Santa Cruz",
    "sg:classifiers":[
        {
            "category":"Personal",
            "subcategory":"Massage",
            "type":"Services"
        },
        {
            "category":"Health Services",
            "subcategory":"Clinic",
            "type":"Services"
        }
    ],
    "sg:phone":"+1 831 247 0750",
    "sg:postcode":"95060",
    "sg:province":"CA",
    "sg:tags":[
        "medical"
    ],
    "sg:website":"www.janefarrarmassage.com",
    "wof:name":"Jane Farrar Therapeutic Massage",
    "wof:placetype":"venue"
},
  "geometry": {"coordinates":[-122.02882099999999,36.96842],"type":"Point"}
}