{
  "type": "Feature",
  "properties": {
    "iso:country":"US",
    "sg:address":"7539 Reseda Blvd",
    "sg:city":"Reseda",
    "sg:classifiers":[
        {
            "category":"Food & Beverages",
            "subcategory":"Groceries & Convenience Stores",
            "type":"Retail Goods"
        }
    ],
    "sg:phone":"+1 818 996 4984",
    "sg:postcode":"91335",
    "sg:province":"CA",
    "wof:name":"Third Hand Shop",
    "wof:placetype":"venue"
},
  "geometry": {"coordinates":[-118.53613300000001,34.207682],"type":"Point"}
}