{
  "type": "Feature",
  "properties": {
    "iso:country":"US",
    "sg:address":"19245 Saticoy St",
    "sg:city":"Reseda",
    "sg:classifiers":[
        {
            "category":"Food & Beverages",
            "subcategory":"Liquor & Beverages",
            "type":"Retail Goods"
        }
    ],
    "sg:phone":"+1 818 345 4937",
    "sg:postcode":"91335",
    "sg:province":"CA",
    "sg:tags":[
        "store"
    ],
    "wof:name":"Knight Life Liquor Jr Market",
    "wof:placetype":"venue"
},
  "geometry": {"coordinates":[-118.550732,34.208444],"type":"Point"}
}