{
  "type": "Feature",
  "properties": {
    "addr:full":"15256 W Friends St Pacific Palisades CA 90272",
    "addr:housenumber":"15256",
    "addr:postcode":"90272",
    "addr:street":"W Friends St",
    "iso:country":"US",
    "sg:address":"15256 W Friends St",
    "sg:city":"Pacific Palisades",
    "sg:classifiers":[
        {
            "category":"Professional",
            "type":"Services"
        }
    ],
    "sg:phone":"+1 310 573 0404",
    "sg:postcode":"90272",
    "sg:province":"CA",
    "wof:name":"Poetique Inc",
    "wof:placetype":"venue"
},
  "geometry": {"coordinates":[-118.52687299999999,34.034524],"type":"Point"}
}