{
  "type": "Feature",
  "properties": {
    "iso:country":"US",
    "sg:address":"4650 Adam Rd",
    "sg:city":"Simi Valley",
    "sg:classifiers":[
        {
            "category":"Farming",
            "subcategory":"Livestock Farm",
            "type":"Manufacturing & Wholesale Goods"
        }
    ],
    "sg:phone":"+1 805 527 7809",
    "sg:postcode":"93063",
    "sg:province":"CA",
    "sg:tags":[
        "equine"
    ],
    "wof:name":"Regency Morgans",
    "wof:placetype":"venue"
},
  "geometry": {"coordinates":[-118.70335300000001,34.284266],"type":"Point"}
}