{
  "type": "Feature",
  "properties": {
    "iso:country":"US",
    "sg:address":"246 Balclutha Dr",
    "sg:city":"Corte Madera",
    "sg:classifiers":[
        {
            "category":"Building & Trades",
            "subcategory":"Construction",
            "type":"Services"
        }
    ],
    "sg:phone":"+1 415 924 5005",
    "sg:postcode":"94925",
    "sg:province":"CA",
    "sg:tags":[
        "painter"
    ],
    "wof:name":"Marin Wood Restoration & Paint",
    "wof:placetype":"venue"
},
  "geometry": {"coordinates":[-122.49551099999999,37.920134],"type":"Point"}
}