{
  "type": "Feature",
  "properties": {
    "iso:country":"US",
    "sg:address":"1555 Copperhill Pkwy",
    "sg:city":"Santa Rosa",
    "sg:classifiers":[
        {
            "category":"Manufacturing",
            "subcategory":"Glass & Minerals",
            "type":"Manufacturing & Wholesale Goods"
        }
    ],
    "sg:phone":"+1 707 523 2050",
    "sg:postcode":"95403",
    "sg:province":"CA",
    "sg:tags":[
        "fabricator",
        "fiber"
    ],
    "sg:website":"www.westernfg.com",
    "wof:name":"Western Fiberglass",
    "wof:placetype":"venue"
},
  "geometry": {"coordinates":[-122.791691,38.507384],"type":"Point"}
}