{
  "type": "Feature",
  "properties": {
    "iso:country":"US",
    "sg:address":"12424 Wilshire Blvd",
    "sg:city":"Los Angeles",
    "sg:classifiers":[
        {
            "category":"Professional",
            "type":"Services"
        },
        {
            "category":"Insurance",
            "subcategory":"Insurance Agent",
            "type":"Services"
        }
    ],
    "sg:phone":"+1 310 264 7700",
    "sg:postcode":"90025",
    "sg:province":"CA",
    "wof:name":"Premium Financing Specialists",
    "wof:placetype":"venue"
},
  "geometry": {"coordinates":[-118.470691,34.041421],"type":"Point"}
}