{
  "type": "Feature",
  "properties": {
    "iso:country":"US",
    "sg:address":"1717 E Lincoln Ave",
    "sg:city":"Anaheim",
    "sg:classifiers":[
        {
            "category":"Health Services",
            "subcategory":"Doctor",
            "type":"Services"
        }
    ],
    "sg:phone":"+1 714 956 2663",
    "sg:postcode":"92805",
    "sg:province":"CA",
    "sg:tags":[
        "medicine",
        "sport",
        "orthopedist"
    ],
    "wof:name":"HEALTHPOINTE",
    "wof:placetype":"venue"
},
  "geometry": {"coordinates":[-117.893154,33.840322],"type":"Point"}
}