{
  "type": "Feature",
  "properties": {
    "addr:full":"359 W 9th St Santa Rosa CA 95401",
    "addr:housenumber":"359",
    "addr:postcode":"ca 95401",
    "addr:street":"W 9Th St",
    "iso:country":"US",
    "sg:address":"359 W 9th St",
    "sg:city":"Santa Rosa",
    "sg:classifiers":[
        {
            "category":"Retail",
            "subcategory":"Auto Repair",
            "type":"Services"
        }
    ],
    "sg:phone":"+1 707 579 1135",
    "sg:postcode":"95401",
    "sg:province":"CA",
    "sg:tags":[
        "repairing",
        "automobile"
    ],
    "wof:name":"Lopez Auto Svc",
    "wof:placetype":"venue"
},
  "geometry": {"coordinates":[-122.72983499999999,38.441696],"type":"Point"}
}