{
  "type": "Feature",
  "properties": {
    "iso:country":"US",
    "sg:address":"2514 Sepulveda Blvd",
    "sg:city":"Torrance",
    "sg:classifiers":[
        {
            "category":"Autos & Motor Vehicles",
            "subcategory":"Auto Supplies",
            "type":"Retail Goods"
        }
    ],
    "sg:phone":"+1 310 612 8840",
    "sg:postcode":"90505",
    "sg:province":"CA",
    "wof:name":"K Daejong Corp",
    "wof:placetype":"venue"
},
  "geometry": {"coordinates":[-118.329914,33.822142],"type":"Point"}
}