{
  "type": "Feature",
  "properties": {
    "addr:full":"344 Pine St San Francisco CA 94104",
    "addr:housenumber":"344",
    "addr:postcode":"94104",
    "addr:street":"Pine St",
    "iso:country":"US",
    "sg:address":"344 Pine St",
    "sg:city":"San Francisco",
    "sg:classifiers":[
        {
            "category":"Banks & Credit Unions",
            "subcategory":"Bank",
            "type":"Services"
        }
    ],
    "sg:phone":"+1 415 782 8659",
    "sg:postcode":"94104",
    "sg:province":"CA",
    "wof:name":"Wells Fargo & CO",
    "wof:placetype":"venue"
},
  "geometry": {"coordinates":[-122.401624,37.792155],"type":"Point"}
}