{
  "type": "Feature",
  "properties": {
    "iso:country":"US",
    "sg:address":"2455 Bennett Valley Rd",
    "sg:city":"Santa Rosa",
    "sg:classifiers":[
        {
            "category":"Building & Trades",
            "subcategory":"Construction",
            "type":"Services"
        }
    ],
    "sg:phone":"+1 707 544 7900",
    "sg:postcode":"95404",
    "sg:province":"CA",
    "sg:tags":[
        "home",
        "builder"
    ],
    "wof:name":"Evos Homes",
    "wof:placetype":"venue"
},
  "geometry": {"coordinates":[-122.687735,38.432791],"type":"Point"}
}