{
  "type": "Feature",
  "properties": {
    "addr:full":"6127 La Salle Ave Oakland CA 94611",
    "addr:housenumber":"6127",
    "addr:postcode":"94611",
    "addr:street":"La Salle Ave",
    "iso:country":"US",
    "sg:address":"6127 La Salle Ave",
    "sg:city":"Oakland",
    "sg:classifiers":[
        {
            "category":"Shopping",
            "subcategory":"Jewelry",
            "type":"Retail Goods"
        }
    ],
    "sg:phone":"+1 510 339 3440",
    "sg:postcode":"94611",
    "sg:province":"CA",
    "sg:website":"www.lizasonia.com",
    "wof:name":"LIZA SONIA Boutique",
    "wof:placetype":"venue"
},
  "geometry": {"coordinates":[-122.209902,37.826542],"type":"Point"}
}