{
  "type": "Feature",
  "properties": {
    "iso:country":"US",
    "sg:address":"7850 Watt Ave",
    "sg:city":"Antelope",
    "sg:classifiers":[
        {
            "category":"Organizations",
            "subcategory":"Religious Organization",
            "type":"Services"
        }
    ],
    "sg:phone":"+1 916 332 1476",
    "sg:postcode":"95843",
    "sg:province":"CA",
    "sg:tags":[
        "church"
    ],
    "wof:name":"St Andrew's Episcopal Church",
    "wof:placetype":"venue"
},
  "geometry": {"coordinates":[-121.39155700000001,38.712074],"type":"Point"}
}