{
  "type": "Feature",
  "properties": {
    "iso:country":"US",
    "sg:address":"642 N D St",
    "sg:city":"San Bernardino",
    "sg:classifiers":[
        {
            "category":"Restaurant",
            "type":"Food & Drink"
        }
    ],
    "sg:phone":"+1 909 885 4161",
    "sg:postcode":"92401",
    "sg:province":"CA",
    "wof:name":"Nena's Mexican Restaurant",
    "wof:placetype":"venue"
},
  "geometry": {"coordinates":[-117.29199,34.111255],"type":"Point"}
}