{
  "type": "Feature",
  "properties": {
    "iso:country":"US",
    "sg:address":"300 Parker St",
    "sg:city":"Vacaville",
    "sg:classifiers":[
        {
            "category":"Food & Beverages",
            "subcategory":"Liquor & Beverages",
            "type":"Retail Goods"
        }
    ],
    "sg:phone":"+1 707 448 2044",
    "sg:postcode":"95688",
    "sg:province":"CA",
    "wof:name":"Vacaville Food & Liquor",
    "wof:placetype":"venue"
},
  "geometry": {"coordinates":[-121.98993900000001,38.355011],"type":"Point"}
}