{
  "type": "Feature",
  "properties": {
    "addr:full":"706 E Arrow Hwy Covina CA 91722",
    "addr:housenumber":"706",
    "addr:postcode":"91722",
    "addr:street":"E Arrow Hwy",
    "iso:country":"US",
    "sg:address":"706 E Arrow Hwy",
    "sg:city":"Covina",
    "sg:classifiers":[
        {
            "category":"Wholesale",
            "subcategory":"Electrical",
            "type":"Manufacturing & Wholesale Goods"
        },
        {
            "category":"Shopping",
            "subcategory":"Computers & Home Electronics",
            "type":"Retail Goods"
        }
    ],
    "sg:phone":"+1 626 966 2019",
    "sg:postcode":"91722",
    "sg:province":"CA",
    "sg:tags":[
        "wire",
        "assembly",
        "supply",
        "mfg",
        "component",
        "equipment",
        "harness",
        "electronic"
    ],
    "wof:name":"Gourmet Electronics Ltd",
    "wof:placetype":"venue"
},
  "geometry": {"coordinates":[-117.888834,34.10672],"type":"Point"}
}