{
  "type": "Feature",
  "properties": {
    "iso:country":"US",
    "sg:address":"4034 Wabaska Drive",
    "sg:city":"San Diego",
    "sg:classifiers":[
        {
            "category":"Retail",
            "subcategory":"Repair Shop",
            "type":"Services"
        }
    ],
    "sg:phone":"+1 619 222 1345",
    "sg:postcode":"92107",
    "sg:province":"CA",
    "sg:tags":[
        "reupholstery",
        "furniture"
    ],
    "sg:website":"www.alexandersupholstering.com",
    "wof:name":"Alexander's Upholstering",
    "wof:placetype":"venue"
},
  "geometry": {"coordinates":[-117.232809,32.742319],"type":"Point"}
}