{
  "type": "Feature",
  "properties": {
    "iso:country":"US",
    "sg:address":"2931 Niles St",
    "sg:city":"Bakersfield",
    "sg:classifiers":[
        {
            "category":"Restaurant",
            "type":"Food & Drink"
        }
    ],
    "sg:menulink":"http://www.allmenus.com/ca/bakersfield/164256-wienerschnitzel/menu/",
    "sg:phone":"+1 661 323 2502",
    "sg:postcode":"93306",
    "sg:province":"CA",
    "sg:tags":[
        "sandwich",
        "dog",
        "burger",
        "hot",
        "wrap",
        "american"
    ],
    "wof:name":"Wienerschnitzel",
    "wof:placetype":"venue"
},
  "geometry": {"coordinates":[-118.952707,35.375623],"type":"Point"}
}