{
  "type": "Feature",
  "properties": {
    "addr:full":"449 Berthoud St Sacramento CA 95838",
    "addr:housenumber":"449",
    "addr:postcode":"95838",
    "addr:street":"Berthoud St",
    "iso:country":"US",
    "sg:address":"449 Berthoud St",
    "sg:city":"Sacramento",
    "sg:classifiers":[
        {
            "category":"Manufacturing",
            "subcategory":"Electronics",
            "type":"Manufacturing & Wholesale Goods"
        }
    ],
    "sg:phone":"+1 916 922 3683",
    "sg:postcode":"95838",
    "sg:province":"CA",
    "sg:tags":[
        "electronic",
        "component",
        "mfg"
    ],
    "wof:name":"Red Cloud Recordings & Pubg",
    "wof:placetype":"venue"
},
  "geometry": {"coordinates":[-121.454818,38.649199],"type":"Point"}
}