{
  "type": "Feature",
  "properties": {
    "iso:country":"US",
    "sg:address":"18225 Brookhurst St Ste 4",
    "sg:city":"Fountain Valley",
    "sg:classifiers":[
        {
            "category":"Personal",
            "subcategory":"Beauty Salon",
            "type":"Services"
        }
    ],
    "sg:phone":"+1 714 962 8844",
    "sg:postcode":"92708",
    "sg:province":"CA",
    "sg:tags":[
        "hair"
    ],
    "wof:name":"The Beauty Salon",
    "wof:placetype":"venue"
},
  "geometry": {"coordinates":[-117.954393,33.698534],"type":"Point"}
}