{
  "type": "Feature",
  "properties": {
    "iso:country":"US",
    "sg:address":"1160 University Ave",
    "sg:city":"Berkeley",
    "sg:classifiers":[
        {
            "category":"Restaurant",
            "type":"Food & Drink"
        }
    ],
    "sg:phone":"+1 510 549 3781",
    "sg:postcode":"94702",
    "sg:province":"CA",
    "sg:tags":[
        "middle",
        "afghan",
        "eastern"
    ],
    "sg:website":"www.facebook.com/pages/Fremont-C...",
    "wof:name":"De Afghanan Kabob House",
    "wof:placetype":"venue"
},
  "geometry": {"coordinates":[-122.290295,37.869217],"type":"Point"}
}