{
  "type": "Feature",
  "properties": {
    "iso:country":"US",
    "sg:address":"32850 Mill Creek Dr",
    "sg:city":"Fort Bragg",
    "sg:classifiers":[
        {
            "category":"Real Estate",
            "subcategory":"Real Estate Operator",
            "type":"Services"
        }
    ],
    "sg:phone":"+1 707 964 9123",
    "sg:postcode":"95437",
    "sg:province":"CA",
    "sg:tags":[
        "mobile",
        "home",
        "community"
    ],
    "wof:name":"Vagabond Village",
    "wof:placetype":"venue"
},
  "geometry": {"coordinates":[-123.785148,39.489617],"type":"Point"}
}