{
  "type": "Feature",
  "properties": {
    "addr:full":"2499 El Camino Real Santa Clara CA 95051",
    "addr:housenumber":"2499",
    "addr:postcode":"95051",
    "addr:street":"El Camino Real",
    "iso:country":"US",
    "sg:address":"2499 El Camino Real",
    "sg:city":"Santa Clara",
    "sg:classifiers":[
        {
            "category":"Travel",
            "subcategory":"Hotels & Motels",
            "type":"Entertainment"
        }
    ],
    "sg:phone":"+1 408 244 9610",
    "sg:postcode":"95051",
    "sg:province":"CA",
    "sg:website":"www.howardjohnson.com",
    "wof:name":"Howard Johnson Lodge",
    "wof:placetype":"venue"
},
  "geometry": {"coordinates":[-121.97050299999999,37.352355],"type":"Point"}
}