{
  "type": "Feature",
  "properties": {
    "iso:country":"US",
    "sg:address":"1016 Vanston Way",
    "sg:city":"Roseville",
    "sg:classifiers":[
        {
            "category":"Manufacturing",
            "subcategory":"Buildings",
            "type":"Manufacturing & Wholesale Goods"
        },
        {
            "category":"Building & Trades",
            "subcategory":"Construction",
            "type":"Services"
        }
    ],
    "sg:phone":"+1 916 316 1432",
    "sg:postcode":"95747",
    "sg:province":"CA",
    "sg:tags":[
        "home",
        "builder",
        "contractor"
    ],
    "wof:name":"Marshall Construction",
    "wof:placetype":"venue"
},
  "geometry": {"coordinates":[-121.33884399999999,38.75241],"type":"Point"}
}