{
  "type": "Feature",
  "properties": {
    "addr:full":"422 Mchenry Ave Modesto CA 95354",
    "addr:housenumber":"422",
    "addr:postcode":"ca 95354",
    "addr:street":"Mchenry Ave",
    "iso:country":"US",
    "sg:address":"422 Mchenry Ave",
    "sg:city":"Modesto",
    "sg:classifiers":[
        {
            "category":"Social Services",
            "type":"Services"
        },
        {
            "category":"Government",
            "subcategory":"Office",
            "type":"Public Place"
        }
    ],
    "sg:phone":"+1 209 524 1307",
    "sg:postcode":"95354",
    "sg:province":"CA",
    "sg:tags":[
        "parish",
        "government-county"
    ],
    "wof:name":"Volunteer Center",
    "wof:placetype":"venue"
},
  "geometry": {"coordinates":[-120.99376700000001,37.650131],"type":"Point"}
}