{
  "type": "Feature",
  "properties": {
    "addr:full":"219 W Manchester Blvd Ste 4 Inglewood CA 90301",
    "addr:housenumber":"219",
    "addr:postcode":"90301",
    "addr:street":"W Manchester Blvd Ste 4",
    "iso:country":"US",
    "sg:address":"219 W Manchester Blvd Ste 4",
    "sg:city":"Inglewood",
    "sg:classifiers":[
        {
            "category":"Home & Garden",
            "subcategory":"Carpets & Floor Coverings",
            "type":"Retail Goods"
        }
    ],
    "sg:phone":"+1 310 419 6056",
    "sg:postcode":"90301",
    "sg:province":"CA",
    "sg:tags":[
        "carpeting"
    ],
    "wof:name":"Anasa Floors",
    "wof:placetype":"venue"
},
  "geometry": {"coordinates":[-118.358002,33.9618],"type":"Point"}
}