{
  "type": "Feature",
  "properties": {
    "addr:full":"16994 Sorrel Way Morgan Hill CA 95037",
    "addr:housenumber":"16994",
    "addr:postcode":"95037",
    "addr:street":"Sorrel Way",
    "iso:country":"US",
    "sg:address":"16994 Sorrel Way",
    "sg:city":"Morgan Hill",
    "sg:classifiers":[
        {
            "category":"Banks & Credit Unions",
            "subcategory":"Bank",
            "type":"Services"
        }
    ],
    "sg:phone":"+1 408 776 8767",
    "sg:postcode":"95037",
    "sg:province":"CA",
    "sg:tags":[
        "loan",
        "industrial",
        "institution",
        "general"
    ],
    "wof:name":"Quick Draw Atm",
    "wof:placetype":"venue"
},
  "geometry": {"coordinates":[-121.61127999999999,37.14007],"type":"Point"}
}