{
  "type": "Feature",
  "properties": {
    "addr:full":"18344 Oxnard St Tarzana CA 91356",
    "addr:housenumber":"18344",
    "addr:postcode":"91356",
    "addr:street":"Oxnard St",
    "iso:country":"US",
    "sg:address":"18344 Oxnard St",
    "sg:city":"Tarzana",
    "sg:classifiers":[
        {
            "category":"Communications",
            "subcategory":"Film & Video Production",
            "type":"Services"
        }
    ],
    "sg:phone":"+1 818 780 0131",
    "sg:postcode":"91356",
    "sg:province":"CA",
    "sg:tags":[
        "taping"
    ],
    "wof:name":"Standard Digital",
    "wof:placetype":"venue"
},
  "geometry": {"coordinates":[-118.535056,34.179929],"type":"Point"}
}