{
  "type": "Feature",
  "properties": {
    "addr:full":"4193 Concord Ave Santa Rosa CA 95407",
    "addr:housenumber":"4193",
    "addr:postcode":"95407",
    "addr:street":"Concord Ave",
    "iso:country":"US",
    "sg:address":"4193 Concord Ave",
    "sg:city":"Santa Rosa",
    "sg:classifiers":[
        {
            "category":"Communications",
            "subcategory":"Film & Video Production",
            "type":"Services"
        }
    ],
    "sg:phone":"+1 707 591 9999",
    "sg:postcode":"95407",
    "sg:province":"CA",
    "sg:tags":[
        "taping"
    ],
    "wof:name":"Vineyard Video",
    "wof:placetype":"venue"
},
  "geometry": {"coordinates":[-122.769381,38.411093],"type":"Point"}
}