{
  "type": "Feature",
  "properties": {
    "iso:country":"US",
    "sg:address":"569 Main St",
    "sg:city":"Fortuna",
    "sg:classifiers":[
        {
            "category":"Shopping",
            "subcategory":"Used Merchandise",
            "type":"Retail Goods"
        }
    ],
    "sg:phone":"+1 707 725 9175",
    "sg:postcode":"95540",
    "sg:province":"CA",
    "wof:name":"Rundells Antq & Collectibles",
    "wof:placetype":"venue"
},
  "geometry": {"coordinates":[-124.16198199999999,40.598581],"type":"Point"}
}