{
  "type": "Feature",
  "properties": {
    "addr:full":"136 Rochester St Costa Mesa CA 92627",
    "addr:housenumber":"136",
    "addr:postcode":"92627",
    "addr:street":"Rochester St",
    "iso:country":"US",
    "sg:address":"136 Rochester St",
    "sg:city":"Costa Mesa",
    "sg:classifiers":[
        {
            "category":"Building & Trades",
            "subcategory":"Construction",
            "type":"Services"
        }
    ],
    "sg:phone":"+1 949 642 4905",
    "sg:postcode":"92627",
    "sg:province":"CA",
    "sg:tags":[
        "contractor"
    ],
    "wof:name":"Westbay Properties",
    "wof:placetype":"venue"
},
  "geometry": {"coordinates":[-117.917975,33.637981],"type":"Point"}
}