{
  "type": "Feature",
  "properties": {
    "addr:full":"4741 E Palm Canyon Dr Ste B Palm Springs CA 92264",
    "addr:housenumber":"4741",
    "addr:postcode":"92264",
    "addr:street":"E Palm Canyon Dr Ste B",
    "iso:country":"US",
    "sg:address":"4741 E Palm Canyon Dr Ste B",
    "sg:city":"Palm Springs",
    "sg:classifiers":[
        {
            "category":"Home & Garden",
            "subcategory":"Household Appliances",
            "type":"Retail Goods"
        }
    ],
    "sg:phone":"+1 760 202 1199",
    "sg:postcode":"92264",
    "sg:province":"CA",
    "sg:website":"www.desertvacuum.com",
    "wof:name":"DESERT VACUUM & APPLIANCE",
    "wof:placetype":"venue"
},
  "geometry": {"coordinates":[-116.49503900000001,33.793153],"type":"Point"}
}