{
  "type": "Feature",
  "properties": {
    "addr:full":"525 Market St San Francisco CA 94105",
    "addr:housenumber":"525",
    "addr:postcode":"94105",
    "addr:street":"Market St",
    "iso:country":"US",
    "sg:address":"525 Market St",
    "sg:city":"San Francisco",
    "sg:classifiers":[
        {
            "category":"Professional",
            "subcategory":"Computer Services",
            "type":"Services"
        }
    ],
    "sg:phone":"+1 415 267 0300",
    "sg:postcode":"94105",
    "sg:province":"CA",
    "sg:tags":[
        "processing",
        "datum"
    ],
    "wof:name":"Affiliated Computer Services",
    "wof:placetype":"venue"
},
  "geometry": {"coordinates":[-122.39931,37.790827],"type":"Point"}
}