{
  "type": "Feature",
  "properties": {
    "addr:full":"310 15th St Oakland CA 94612",
    "addr:housenumber":"310",
    "addr:postcode":"94612",
    "addr:street":"15Th St",
    "iso:country":"US",
    "sg:address":"310 15th St",
    "sg:city":"Oakland",
    "sg:classifiers":[
        {
            "category":"Professional",
            "subcategory":"Accounting & Tax Preparation",
            "type":"Services"
        }
    ],
    "sg:phone":"+1 510 893 7003",
    "sg:postcode":"94612",
    "sg:province":"CA",
    "sg:tags":[
        "accountant"
    ],
    "wof:name":"Frank Sk Cheung CPA",
    "wof:placetype":"venue"
},
  "geometry": {"coordinates":[-122.26794,37.804319],"type":"Point"}
}