{
  "type": "Feature",
  "properties": {
    "addr:full":"5403 W 8th St Los Angeles CA 90036",
    "addr:housenumber":"5403",
    "addr:postcode":"90036",
    "addr:street":"W 8Th St",
    "iso:country":"US",
    "sg:address":"5403 W 8th St",
    "sg:city":"Los Angeles",
    "sg:classifiers":[
        {
            "category":"Professional",
            "subcategory":"Computer Services",
            "type":"Services"
        }
    ],
    "sg:phone":"+1 323 938 8854",
    "sg:postcode":"90036",
    "sg:province":"CA",
    "sg:tags":[
        "home",
        "consulting",
        "page",
        "dev",
        "internet"
    ],
    "wof:name":"Antol",
    "wof:placetype":"venue"
},
  "geometry": {"coordinates":[-118.347739,34.060658],"type":"Point"}
}