{
  "type": "Feature",
  "properties": {
    "iso:country":"US",
    "sg:address":"128 W Nees Ave",
    "sg:city":"Fresno",
    "sg:classifiers":[
        {
            "category":"Utilities",
            "subcategory":"Mobile Phone",
            "type":"Services"
        },
        {
            "category":"Shopping",
            "subcategory":"Mobile Phones",
            "type":"Retail Goods"
        }
    ],
    "sg:phone":"+1 559 449 9081",
    "sg:postcode":"93711",
    "sg:province":"CA",
    "sg:tags":[
        "supply",
        "communication",
        "telephone",
        "wireless",
        "equipment",
        "cellular"
    ],
    "sg:website":"http://www.sprint.com",
    "wof:name":"Sprint Store",
    "wof:placetype":"venue"
},
  "geometry": {"coordinates":[-119.791696,36.851937],"type":"Point"}
}