{
  "type": "Feature",
  "properties": {
    "iso:country":"US",
    "sg:address":"3336 Cutter Way",
    "sg:city":"Sacramento",
    "sg:classifiers":[
        {
            "category":"Building & Trades",
            "subcategory":"Landscaping Services",
            "type":"Services"
        }
    ],
    "sg:phone":"+1 916 248 2266",
    "sg:postcode":"95818",
    "sg:province":"CA",
    "sg:website":"www.lontranaturescaping.com/",
    "wof:name":"Lontra Naturescaping",
    "wof:placetype":"venue"
},
  "geometry": {"coordinates":[-121.478331,38.544163],"type":"Point"}
}