{
  "type": "Feature",
  "properties": {
    "addr:full":"32444 W Gale Ave Coalinga CA 93210",
    "addr:housenumber":"32444",
    "addr:postcode":"93210",
    "addr:street":"W Gale Ave",
    "iso:country":"US",
    "sg:address":"32444 W Gale Ave",
    "sg:city":"Coalinga",
    "sg:classifiers":[
        {
            "category":"Retail",
            "subcategory":"Repair Shop",
            "type":"Services"
        }
    ],
    "sg:phone":"+1 559 935 1482",
    "sg:postcode":"93210",
    "sg:province":"CA",
    "sg:tags":[
        "welding"
    ],
    "wof:name":"K-Bud's Welding Svc",
    "wof:placetype":"venue"
},
  "geometry": {"coordinates":[-120.380832,36.179967],"type":"Point"}
}