{
  "type": "Feature",
  "properties": {
    "iso:country":"US",
    "sg:address":"PO Box 594",
    "sg:city":"Graton",
    "sg:classifiers":[
        {
            "category":"Home & Garden",
            "subcategory":"Garden Supply",
            "type":"Retail Goods"
        }
    ],
    "sg:phone":"+1 707 823 2605",
    "sg:postcode":"95444",
    "sg:province":"CA",
    "sg:tags":[
        "nursery",
        "gardening"
    ],
    "wof:name":"Shooting Star Propagation Whsle Nrsries",
    "wof:placetype":"venue"
},
  "geometry": {"coordinates":[-122.86799600000001,38.434101],"type":"Point"}
}