{
  "type": "Feature",
  "properties": {
    "addr:full":"679 W Lincoln St Banning CA 92220",
    "addr:housenumber":"679",
    "addr:postcode":"92220",
    "addr:street":"W Lincoln St",
    "iso:country":"US",
    "sg:address":"679 W Lincoln St",
    "sg:city":"Banning",
    "sg:classifiers":[
        {
            "category":"Wholesale",
            "subcategory":"Dairy",
            "type":"Manufacturing & Wholesale Goods"
        }
    ],
    "sg:phone":"+1 951 922 1801",
    "sg:postcode":"92220",
    "sg:province":"CA",
    "sg:tags":[
        "product"
    ],
    "wof:name":"Santee Dairies Inc",
    "wof:placetype":"venue"
},
  "geometry": {"coordinates":[-116.882745,33.921772],"type":"Point"}
}