{
  "type": "Feature",
  "properties": {
    "addr:full":"832 Jury Ct San Jose CA 95112",
    "addr:housenumber":"832",
    "addr:postcode":"95112",
    "addr:street":"Jury Ct",
    "iso:country":"US",
    "sg:address":"832 Jury Ct",
    "sg:city":"San Jose",
    "sg:classifiers":[
        {
            "category":"Manufacturing",
            "subcategory":"Printing",
            "type":"Manufacturing & Wholesale Goods"
        }
    ],
    "sg:phone":"+1 408 295 1969",
    "sg:postcode":"95112",
    "sg:province":"CA",
    "sg:tags":[
        "publisher",
        "software"
    ],
    "sg:website":"www.crypticstudios.com",
    "wof:name":"Cryptic Studios",
    "wof:placetype":"venue"
},
  "geometry": {"coordinates":[-121.89504100000001,37.370927],"type":"Point"}
}