{
  "type": "Feature",
  "properties": {
    "addr:full":"16780 Stagg St Van Nuys CA 91406",
    "addr:housenumber":"16780",
    "addr:postcode":"91406",
    "addr:street":"Stagg St",
    "iso:country":"US",
    "sg:address":"16780 Stagg St",
    "sg:city":"Van Nuys",
    "sg:classifiers":[
        {
            "category":"Home & Garden",
            "subcategory":"Carpets & Floor Coverings",
            "type":"Retail Goods"
        }
    ],
    "sg:phone":"+1 818 780 5255",
    "sg:postcode":"91406",
    "sg:province":"CA",
    "sg:tags":[
        "dealer",
        "rug"
    ],
    "wof:name":"A Warehouse Full Of Rugs",
    "wof:placetype":"venue"
},
  "geometry": {"coordinates":[-118.49722199999999,34.213153],"type":"Point"}
}