{
  "type": "Feature",
  "properties": {
    "iso:country":"US",
    "sg:address":"4254 W 3rd St",
    "sg:city":"Los Angeles",
    "sg:classifiers":[
        {
            "category":"Banks & Credit Unions",
            "subcategory":"Investment Brokerage",
            "type":"Services"
        }
    ],
    "sg:phone":"+1 323 691 0716",
    "sg:postcode":"90020",
    "sg:province":"CA",
    "sg:tags":[
        "advisory",
        "financial"
    ],
    "wof:name":"Eagle Finance Svc",
    "wof:placetype":"venue"
},
  "geometry": {"coordinates":[-118.30781399999999,34.068894],"type":"Point"}
}