{
  "type": "Feature",
  "properties": {
    "addr:full":"632 Sycamore Ave Vista CA 92083",
    "addr:housenumber":"632",
    "addr:postcode":"92083",
    "addr:street":"Sycamore Ave",
    "iso:country":"US",
    "sg:address":"632 Sycamore Ave",
    "sg:city":"Vista",
    "sg:classifiers":[
        {
            "category":"Restaurant",
            "type":"Food & Drink"
        }
    ],
    "sg:menulink":"http://www.allmenus.com/ca/oceanside-escondido/34009-ihop/menu/",
    "sg:phone":"+1 760 727 9642",
    "sg:postcode":"92083",
    "sg:province":"CA",
    "sg:tags":[
        "sandwich",
        "salad",
        "burger",
        "soup",
        "american",
        "steakhouse",
        "wrap"
    ],
    "wof:name":"IHOP",
    "wof:placetype":"venue"
},
  "geometry": {"coordinates":[-117.215576,33.16584],"type":"Point"}
}