{
  "type": "Feature",
  "properties": {
    "addr:full":"30 W 9th St Stockton CA 95206",
    "addr:housenumber":"30",
    "addr:postcode":"95206",
    "addr:street":"W 9Th St",
    "iso:country":"US",
    "sg:address":"30 W 9th St",
    "sg:city":"Stockton",
    "sg:classifiers":[
        {
            "category":"Education",
            "subcategory":"School",
            "type":"Public Place"
        }
    ],
    "sg:phone":"+1 209 933 7245",
    "sg:postcode":"95206",
    "sg:province":"CA",
    "sg:tags":[
        "elementary"
    ],
    "sg:website":"http://www.stockton.k12.ca.us",
    "wof:name":"McKinley Elementary School",
    "wof:placetype":"venue"
},
  "geometry": {"coordinates":[-121.28257499999999,37.926874],"type":"Point"}
}