{
  "type": "Feature",
  "properties": {
    "iso:country":"US",
    "sg:address":"102 S Park Victoria Dr",
    "sg:city":"Milpitas",
    "sg:classifiers":[
        {
            "category":"Restaurant",
            "type":"Food & Drink"
        }
    ],
    "sg:menulink":"http://www.allmenus.com/ca/san-jose/79003-pizza-hut/menu/",
    "sg:phone":"+1 408 946 5000",
    "sg:postcode":"95035",
    "sg:province":"CA",
    "sg:tags":[
        "american",
        "pizza"
    ],
    "wof:name":"Pizza Hut",
    "wof:placetype":"venue"
},
  "geometry": {"coordinates":[-121.883759,37.434054],"type":"Point"}
}