{
  "type": "Feature",
  "properties": {
    "addr:full":"311 1st St Gilroy CA 95020",
    "addr:housenumber":"311",
    "addr:postcode":"95020",
    "addr:street":"1St St",
    "iso:country":"US",
    "sg:address":"311 1st St",
    "sg:city":"Gilroy",
    "sg:classifiers":[
        {
            "category":"Shopping",
            "subcategory":"Bicycles & Sporting Goods",
            "type":"Retail Goods"
        }
    ],
    "sg:phone":"+1 408 842 4889",
    "sg:postcode":"95020",
    "sg:province":"CA",
    "sg:tags":[
        "bicycles-repair"
    ],
    "sg:website":"http://www.sunshinebicycles.com",
    "wof:name":"Sunshine Bicycles",
    "wof:placetype":"venue"
},
  "geometry": {"coordinates":[-121.575968,37.013604],"type":"Point"}
}