{
  "type": "Feature",
  "properties": {
    "addr:full":"4111 San Bernardino Way San Jose CA 95111",
    "addr:housenumber":"4111",
    "addr:postcode":"95111",
    "addr:street":"San Bernardino Way",
    "iso:country":"US",
    "sg:address":"4111 San Bernardino Way",
    "sg:city":"San Jose",
    "sg:classifiers":[
        {
            "category":"Professional",
            "type":"Services"
        },
        {
            "category":"Building & Trades",
            "subcategory":"Construction",
            "type":"Services"
        }
    ],
    "sg:phone":"+1 408 363 9464",
    "sg:postcode":"95111",
    "sg:province":"CA",
    "sg:tags":[
        "mobile",
        "home"
    ],
    "wof:name":"Larry Lang Mobile Home Service",
    "wof:placetype":"venue"
},
  "geometry": {"coordinates":[-121.828012,37.280483],"type":"Point"}
}