{
  "type": "Feature",
  "properties": {
    "addr:full":"1642 Westwood Blvd Los Angeles CA 90024",
    "addr:housenumber":"1642",
    "addr:postcode":"90024",
    "addr:street":"Westwood Blvd",
    "iso:country":"US",
    "sg:address":"1642 Westwood Blvd",
    "sg:city":"Los Angeles",
    "sg:classifiers":[
        {
            "category":"Professional",
            "subcategory":"Lawyer & Legal Services",
            "type":"Services"
        }
    ],
    "sg:phone":"+1 310 473 5550",
    "sg:postcode":"90024",
    "sg:province":"CA",
    "sg:tags":[
        "attorney"
    ],
    "wof:name":"Benjamin Nachimson Law Offices",
    "wof:placetype":"venue"
},
  "geometry": {"coordinates":[-118.439003,34.052334],"type":"Point"}
}