{
  "type": "Feature",
  "properties": {
    "addr:full":"3660 Wilshire Blvd Los Angeles CA 90010",
    "addr:housenumber":"3660",
    "addr:postcode":"90010",
    "addr:street":"Wilshire Blvd",
    "iso:country":"US",
    "sg:address":"3660 Wilshire Blvd",
    "sg:city":"Los Angeles",
    "sg:classifiers":[
        {
            "category":"Banks & Credit Unions",
            "subcategory":"Bank",
            "type":"Services"
        }
    ],
    "sg:phone":"+1 213 384 0123",
    "sg:postcode":"90010",
    "sg:province":"CA",
    "sg:tags":[
        "loan",
        "real estate"
    ],
    "wof:name":"Westland Finance Corp",
    "wof:placetype":"venue"
},
  "geometry": {"coordinates":[-118.30448800000001,34.061645],"type":"Point"}
}