{
  "type": "Feature",
  "properties": {
    "addr:full":"3404 Via Lido Newport Beach CA 92663",
    "addr:housenumber":"3404",
    "addr:postcode":"92663",
    "addr:street":"Via Lido",
    "iso:country":"US",
    "sg:address":"3404 Via Lido",
    "sg:city":"Newport Beach",
    "sg:classifiers":[
        {
            "category":"Health Services",
            "subcategory":"Dentist",
            "type":"Services"
        }
    ],
    "sg:phone":"+1 949 673 9460",
    "sg:postcode":"92663",
    "sg:province":"CA",
    "sg:website":"www.stanarmbrusterdds.com",
    "wof:name":"Armbruster Stanley DDS",
    "wof:placetype":"venue"
},
  "geometry": {"coordinates":[-117.928483,33.618037],"type":"Point"}
}