{
  "type": "Feature",
  "properties": {
    "addr:full":"805 Marina Village Pkwy Alameda CA 94501",
    "addr:housenumber":"805",
    "addr:postcode":"94501",
    "addr:street":"Marina Village Pkwy",
    "iso:country":"US",
    "sg:address":"805 Marina Village Pkwy",
    "sg:city":"Alameda",
    "sg:classifiers":[
        {
            "category":"Shopping",
            "subcategory":"Shoes",
            "type":"Retail Goods"
        }
    ],
    "sg:phone":"+1 510 865 6000",
    "sg:postcode":"94501",
    "sg:province":"CA",
    "wof:name":"Red Wing Shoe Store",
    "wof:placetype":"venue"
},
  "geometry": {"coordinates":[-122.275673,37.783021],"type":"Point"}
}