{
  "type": "Feature",
  "properties": {
    "iso:country":"US",
    "sg:address":"10944 Weyburn Ave",
    "sg:city":"Los Angeles",
    "sg:classifiers":[
        {
            "category":"Personal",
            "subcategory":"Beauty Salon",
            "type":"Services"
        }
    ],
    "sg:phone":"+1 310 208 0081",
    "sg:postcode":"90024",
    "sg:province":"CA",
    "sg:tags":[
        "hair"
    ],
    "wof:name":"La Belle Hair & Skin",
    "wof:placetype":"venue"
},
  "geometry": {"coordinates":[-118.446834,34.062562],"type":"Point"}
}