{
  "type": "Feature",
  "properties": {
    "addr:full":"141 10th St San Francisco CA 94103",
    "addr:housenumber":"141",
    "addr:postcode":"94103",
    "addr:street":"10Th St",
    "iso:country":"US",
    "sg:address":"141 10th St",
    "sg:city":"San Francisco",
    "sg:classifiers":[
        {
            "category":"Manufacturing",
            "subcategory":"Printing",
            "type":"Manufacturing & Wholesale Goods"
        },
        {
            "category":"Professional",
            "subcategory":"Computer Services",
            "type":"Services"
        }
    ],
    "sg:phone":"+1 415 861 7226",
    "sg:postcode":"94103",
    "sg:province":"CA",
    "sg:tags":[
        "scanning",
        "lithographic",
        "commercial",
        "datum"
    ],
    "sg:website":"www.scanatorium.com",
    "wof:name":"Scanatorium",
    "wof:placetype":"venue"
},
  "geometry": {"coordinates":[-122.415583,37.775164],"type":"Point"}
}