{
  "type": "Feature",
  "properties": {
    "addr:full":"4197 17th St San Francisco CA 94114",
    "addr:housenumber":"4197",
    "addr:postcode":"94114",
    "addr:street":"17Th St",
    "iso:country":"US",
    "sg:address":"4197 17th St",
    "sg:city":"San Francisco",
    "sg:classifiers":[
        {
            "category":"Shopping",
            "subcategory":"Pets & Pet Supplies",
            "type":"Retail Goods"
        },
        {
            "category":"Retail",
            "subcategory":"Pet Boarding",
            "type":"Services"
        }
    ],
    "sg:phone":"+1 415 817 1744",
    "sg:postcode":"94114",
    "sg:province":"CA",
    "sg:tags":[
        "walker",
        "dog",
        "boarding/pet",
        "sitting"
    ],
    "sg:website":"www.mrmugglesdogs.com",
    "wof:name":"Mr. Muggles Dog Service",
    "wof:placetype":"venue"
},
  "geometry": {"coordinates":[-122.43931499999999,37.762044],"type":"Point"}
}