{
  "type": "Feature",
  "properties": {
    "iso:country":"US",
    "sg:address":"1018 Main St",
    "sg:city":"Redwood City",
    "sg:classifiers":[
        {
            "category":"Shopping",
            "type":"Retail Goods"
        }
    ],
    "sg:phone":"+1 650 701 1018",
    "sg:postcode":"94063",
    "sg:province":"CA",
    "sg:tags":[
        "merchandise"
    ],
    "wof:name":"Main Gallery",
    "wof:placetype":"venue"
},
  "geometry": {"coordinates":[-122.226136,37.483398],"type":"Point"}
}