{
  "type": "Feature",
  "properties": {
    "addr:full":"249 Griffin St Salinas CA 93901",
    "addr:housenumber":"249",
    "addr:postcode":"93901",
    "addr:street":"Griffin St",
    "iso:country":"US",
    "sg:address":"249 Griffin St",
    "sg:city":"Salinas",
    "sg:classifiers":[
        {
            "category":"Retail",
            "subcategory":"Auto Repair",
            "type":"Services"
        }
    ],
    "sg:phone":"+1 831 422 2932",
    "sg:postcode":"93901",
    "sg:province":"CA",
    "sg:tags":[
        "transmission"
    ],
    "sg:website":"http://www.leemyles.com",
    "wof:name":"Salinas Automatic Transmissions",
    "wof:placetype":"venue"
},
  "geometry": {"coordinates":[-121.64254,36.675909],"type":"Point"}
}