{
  "type": "Feature",
  "properties": {
    "addr:full":"109 Soda Bay Rd Lakeport CA 95453",
    "addr:housenumber":"109",
    "addr:postcode":"95453",
    "addr:street":"Soda Bay Rd",
    "iso:country":"US",
    "sg:address":"109 Soda Bay Rd",
    "sg:city":"Lakeport",
    "sg:classifiers":[
        {
            "category":"Manufacturing",
            "subcategory":"Furniture",
            "type":"Manufacturing & Wholesale Goods"
        }
    ],
    "sg:phone":"+1 707 263 9551",
    "sg:postcode":"95453",
    "sg:province":"CA",
    "wof:name":"Kiddie Komforts",
    "wof:placetype":"venue"
},
  "geometry": {"coordinates":[-122.907527,39.011318],"type":"Point"}
}