{
  "type": "Feature",
  "properties": {
    "iso:country":"US",
    "sg:address":"226 E Canon Perdido St",
    "sg:city":"Santa Barbara",
    "sg:classifiers":[
        {
            "category":"Professional",
            "type":"Services"
        }
    ],
    "sg:phone":"+1 805 568 0424",
    "sg:postcode":"93101",
    "sg:province":"CA",
    "sg:tags":[
        "establishment"
    ],
    "wof:name":"Agility Capital",
    "wof:placetype":"venue"
},
  "geometry": {"coordinates":[-119.697987,34.422795],"type":"Point"}
}