{
  "type": "Feature",
  "properties": {
    "addr:full":"27201 Tourney Rd Valencia CA 91355",
    "addr:housenumber":"27201",
    "addr:postcode":"91355",
    "addr:street":"Tourney Rd",
    "iso:country":"US",
    "sg:address":"27201 Tourney Rd",
    "sg:city":"Valencia",
    "sg:classifiers":[
        {
            "category":"Real Estate",
            "subcategory":"Real Estate Agent",
            "type":"Services"
        }
    ],
    "sg:phone":"+1 661 291 1726",
    "sg:postcode":"91355",
    "sg:province":"CA",
    "wof:name":"Re/Max",
    "wof:placetype":"venue"
},
  "geometry": {"coordinates":[-118.578739,34.418979],"type":"Point"}
}