{
  "type": "Feature",
  "properties": {
    "addr:full":"3671 Mission Ave Oceanside CA 92054",
    "addr:housenumber":"3671",
    "addr:postcode":"92054",
    "addr:street":"Mission Ave",
    "iso:country":"US",
    "sg:address":"3671 Mission Ave",
    "sg:city":"Oceanside",
    "sg:classifiers":[
        {
            "category":"Fast Food",
            "type":"Food & Drink"
        },
        {
            "category":"Restaurant",
            "type":"Food & Drink"
        }
    ],
    "sg:phone":"+1 760 721 0124",
    "sg:postcode":"92054",
    "sg:province":"CA",
    "sg:tags":[
        "burger",
        "breakfast",
        "brunch"
    ],
    "wof:name":"Paul's Place",
    "wof:placetype":"venue"
},
  "geometry": {"coordinates":[-117.333,33.223999],"type":"Point"}
}