{
  "type": "Feature",
  "properties": {
    "addr:full":"1832 Soscol Ave Napa CA 94559",
    "addr:housenumber":"1832",
    "addr:postcode":"94559",
    "addr:street":"Soscol Ave",
    "iso:country":"US",
    "sg:address":"1832 Soscol Ave",
    "sg:city":"Napa",
    "sg:classifiers":[
        {
            "category":"Social Services",
            "type":"Services"
        }
    ],
    "sg:phone":"+1 707 252 7925",
    "sg:postcode":"94559",
    "sg:province":"CA",
    "sg:tags":[
        "counselor",
        "marriage",
        "family"
    ],
    "wof:name":"Colleen Daugherty",
    "wof:placetype":"venue"
},
  "geometry": {"coordinates":[-122.28501,38.308007],"type":"Point"}
}