{
  "type": "Feature",
  "properties": {
    "iso:country":"US",
    "sg:address":"151 Beverlee Way",
    "sg:city":"Westmorland",
    "sg:classifiers":[
        {
            "category":"Manufacturing",
            "subcategory":"Retail Goods",
            "type":"Manufacturing & Wholesale Goods"
        }
    ],
    "sg:phone":"+1 760 344 2217",
    "sg:postcode":"92281",
    "sg:province":"CA",
    "sg:tags":[
        "marking",
        "devices",
        "mfg"
    ],
    "wof:name":"Price Construction Inc",
    "wof:placetype":"venue"
},
  "geometry": {"coordinates":[-115.622474,33.03078],"type":"Point"}
}