{
  "type": "Feature",
  "properties": {
    "iso:country":"US",
    "sg:address":"13589 Mindanao Way",
    "sg:city":"Marina Del Rey",
    "sg:classifiers":[
        {
            "category":"Recreation",
            "subcategory":"Marina",
            "type":"Entertainment"
        }
    ],
    "sg:phone":"+1 310 823 2252",
    "sg:postcode":"90292",
    "sg:province":"CA",
    "sg:tags":[
        "operation"
    ],
    "wof:name":"SMYC Marina",
    "wof:placetype":"venue"
},
  "geometry": {"coordinates":[-118.440111,33.979811],"type":"Point"}
}