{
  "type": "Feature",
  "properties": {
    "addr:full":"6021 Galahad Rd Malibu CA 90265",
    "addr:housenumber":"6021",
    "addr:postcode":"90265",
    "addr:street":"Galahad Rd",
    "iso:country":"US",
    "sg:address":"6021 Galahad Rd",
    "sg:city":"Malibu",
    "sg:classifiers":[
        {
            "category":"Health Services",
            "subcategory":"Doctor",
            "type":"Services"
        },
        {
            "category":"Health Services",
            "subcategory":"Clinic",
            "type":"Services"
        },
        {
            "category":"Health Services",
            "subcategory":"Health Practitioner",
            "type":"Services"
        }
    ],
    "sg:phone":"+1 866 369 1725",
    "sg:postcode":"90265",
    "sg:province":"CA",
    "sg:tags":[
        "physician",
        "information",
        "surgeons",
        "drug",
        "abuse",
        "treatment",
        "medicine",
        "addiction",
        "alcoholism"
    ],
    "sg:website":"http://local.ingenio.com/Listings/Details.aspx?NUM=a%3a10241085%3a13%3a4859924%3a14%3a0%3a7",
    "wof:name":"Recovery Solutions Malibu",
    "wof:placetype":"venue"
},
  "geometry": {"coordinates":[-118.799373,34.027541],"type":"Point"}
}