{
  "type": "Feature",
  "properties": {
    "addr:full":"8630 Pine Tree Pl Los Angeles CA 90069",
    "addr:housenumber":"8630",
    "addr:postcode":"90069",
    "addr:street":"Pine Tree Pl",
    "iso:country":"US",
    "sg:address":"8630 Pine Tree Pl",
    "sg:city":"Los Angeles",
    "sg:classifiers":[
        {
            "category":"Communications",
            "subcategory":"Film & Video Production",
            "type":"Services"
        }
    ],
    "sg:phone":"+1 310 659 7659",
    "sg:postcode":"90069",
    "sg:province":"CA",
    "sg:tags":[
        "motion",
        "picture",
        "studio",
        "producer"
    ],
    "wof:name":"X-Ray Productions",
    "wof:placetype":"venue"
},
  "geometry": {"coordinates":[-118.380927,34.093839],"type":"Point"}
}