{
  "type": "Feature",
  "properties": {
    "iso:country":"US",
    "sg:address":"5600 Casa Grande Ave",
    "sg:city":"Rocklin",
    "sg:classifiers":[
        {
            "category":"Professional",
            "type":"Services"
        }
    ],
    "sg:phone":"+1 916 624 4546",
    "sg:postcode":"95677",
    "sg:province":"CA",
    "wof:name":"Travis Thompson",
    "wof:placetype":"venue"
},
  "geometry": {"coordinates":[-121.26230099999999,38.781974],"type":"Point"}
}