{
  "type": "Feature",
  "properties": {
    "iso:country":"US",
    "sg:address":"4301 Wilson St",
    "sg:city":"Chino",
    "sg:classifiers":[
        {
            "category":"Wholesale",
            "subcategory":"Electrical",
            "type":"Manufacturing & Wholesale Goods"
        }
    ],
    "sg:phone":"+1 909 287 0668",
    "sg:postcode":"91710",
    "sg:province":"CA",
    "sg:tags":[
        "game",
        "video"
    ],
    "wof:name":"LA Modelo Latina",
    "wof:placetype":"venue"
},
  "geometry": {"coordinates":[-117.70769900000001,34.021798],"type":"Point"}
}