{
  "type": "Feature",
  "properties": {
    "iso:country":"US",
    "sg:address":"3250 W Olympic Blvd",
    "sg:city":"Los Angeles",
    "sg:classifiers":[
        {
            "category":"Restaurant",
            "type":"Food & Drink"
        }
    ],
    "sg:phone":"+1 323 735 3254",
    "sg:postcode":"90006",
    "sg:province":"CA",
    "sg:tags":[
        "shop",
        "coffee"
    ],
    "wof:name":"Galleria Coffee Shop",
    "wof:placetype":"venue"
},
  "geometry": {"coordinates":[-118.308683,34.052561],"type":"Point"}
}