{
  "type": "Feature",
  "properties": {
    "iso:country":"US",
    "sg:address":"23 28th Ave",
    "sg:city":"San Mateo",
    "sg:classifiers":[
        {
            "category":"Retail",
            "subcategory":"Auto Rental",
            "type":"Services"
        }
    ],
    "sg:phone":"+1 650 627 9999",
    "sg:postcode":"94403",
    "sg:province":"CA",
    "sg:tags":[
        "renting",
        "automobile"
    ],
    "wof:name":"Stop & Go Car Rental",
    "wof:placetype":"venue"
},
  "geometry": {"coordinates":[-122.30292,37.541541],"type":"Point"}
}