{
  "type": "Feature",
  "properties": {
    "iso:country":"US",
    "sg:address":"295 San Andreas Rd",
    "sg:city":"Watsonville",
    "sg:classifiers":[
        {
            "category":"Organizations",
            "subcategory":"Labor Organization",
            "type":"Services"
        }
    ],
    "sg:phone":"+1 831 728 3567",
    "sg:postcode":"95076",
    "sg:province":"CA",
    "wof:name":"Mid-Peninsula Housing Cltn",
    "wof:placetype":"venue"
},
  "geometry": {"coordinates":[-121.81503499999999,36.895263],"type":"Point"}
}