{
  "type": "Feature",
  "properties": {
    "iso:country":"US",
    "sg:address":"13031 Blodget Ave",
    "sg:city":"Bakersfield",
    "sg:classifiers":[
        {
            "category":"Professional",
            "subcategory":"Advertising",
            "type":"Services"
        }
    ],
    "sg:phone":"+1 661 325 9842",
    "sg:postcode":"93314",
    "sg:province":"CA",
    "wof:name":"Cyrk Inc",
    "wof:placetype":"venue"
},
  "geometry": {"coordinates":[-119.14681299999999,35.393509],"type":"Point"}
}