{
  "type": "Feature",
  "properties": {
    "addr:full":"1527 Locust St Walnut Creek CA 94596",
    "addr:housenumber":"1527",
    "addr:postcode":"94596",
    "addr:street":"Locust St",
    "iso:country":"US",
    "sg:address":"1527 Locust St",
    "sg:city":"Walnut Creek",
    "sg:classifiers":[
        {
            "category":"Restaurant",
            "type":"Food & Drink"
        }
    ],
    "sg:phone":"+1 925 935 7778",
    "sg:postcode":"94596",
    "sg:province":"CA",
    "wof:name":"Mr Lucky's",
    "wof:placetype":"venue"
},
  "geometry": {"coordinates":[-122.06298,37.900993],"type":"Point"}
}