{
  "type": "Feature",
  "properties": {
    "iso:country":"US",
    "sg:address":"1780 Evergreen St",
    "sg:city":"Duarte",
    "sg:classifiers":[
        {
            "category":"Structure",
            "subcategory":"Warehouse",
            "type":"Public Place"
        },
        {
            "category":"Building & Trades",
            "subcategory":"Construction",
            "type":"Services"
        },
        {
            "category":"Retail",
            "subcategory":"Storage",
            "type":"Services"
        }
    ],
    "sg:phone":"+1 626 359 8058",
    "sg:postcode":"91010",
    "sg:province":"CA",
    "sg:tags":[
        "self",
        "industrial",
        "warehouses-public-commercial",
        "contractors-commercial"
    ],
    "wof:name":"Home Pan Development Inc",
    "wof:placetype":"venue"
},
  "geometry": {"coordinates":[-117.967031,34.135059],"type":"Point"}
}