{
  "type": "Feature",
  "properties": {
    "addr:full":"700 E Sycamore St Anaheim CA 92805",
    "addr:housenumber":"700",
    "addr:postcode":"92805",
    "addr:street":"E Sycamore St",
    "iso:country":"US",
    "sg:address":"700 E Sycamore St",
    "sg:city":"Anaheim",
    "sg:classifiers":[
        {
            "category":"Building & Trades",
            "subcategory":"Landscaping Services",
            "type":"Services"
        }
    ],
    "sg:phone":"+1 714 772 9947",
    "sg:postcode":"92805",
    "sg:province":"CA",
    "sg:tags":[
        "which",
        "company",
        "it",
        "through",
        "holding",
        "subsidiary",
        "operate"
    ],
    "wof:name":"Hydro-Dig Inc",
    "wof:placetype":"venue"
},
  "geometry": {"coordinates":[-117.908395,33.841372],"type":"Point"}
}