{
  "type": "Feature",
  "properties": {
    "addr:full":"9680 Old Redwood Hwy Windsor CA 95492",
    "addr:housenumber":"9680",
    "addr:postcode":"95492",
    "addr:street":"Old Redwood Hwy",
    "iso:country":"US",
    "sg:address":"9680 Old Redwood Hwy",
    "sg:city":"Windsor",
    "sg:classifiers":[
        {
            "category":"Building & Trades",
            "subcategory":"Construction",
            "type":"Services"
        }
    ],
    "sg:phone":"+1 707 838 3745",
    "sg:postcode":"95492",
    "sg:province":"CA",
    "sg:tags":[
        "repairing",
        "remodeling",
        "contractor"
    ],
    "wof:name":"CHB General Contractor",
    "wof:placetype":"venue"
},
  "geometry": {"coordinates":[-122.819737,38.556842],"type":"Point"}
}