{
  "type": "Feature",
  "properties": {
    "iso:country":"US",
    "sg:address":"5052 E Montclair Plaza Ln",
    "sg:city":"Montclair",
    "sg:classifiers":[
        {
            "category":"Shopping",
            "subcategory":"Clothing, Apparel, & Fashions",
            "type":"Retail Goods"
        }
    ],
    "sg:phone":"+1 909 398 4698",
    "sg:postcode":"91763",
    "sg:province":"CA",
    "wof:name":"Daisy Shoes",
    "wof:placetype":"venue"
},
  "geometry": {"coordinates":[-117.694625,34.087303],"type":"Point"}
}