{
  "type": "Feature",
  "properties": {
    "iso:country":"US",
    "sg:address":"20 Healdsburg Ave",
    "sg:city":"Healdsburg",
    "sg:classifiers":[
        {
            "category":"Retail",
            "subcategory":"Auto Repair",
            "type":"Services"
        }
    ],
    "sg:phone":"+1 707 431 2993",
    "sg:postcode":"95448",
    "sg:province":"CA",
    "sg:tags":[
        "body",
        "automobile",
        "painting"
    ],
    "wof:name":"Healdsburg Collision Ctr",
    "wof:placetype":"venue"
},
  "geometry": {"coordinates":[-122.862661,38.603983],"type":"Point"}
}