{
  "type": "Feature",
  "properties": {
    "iso:country":"US",
    "sg:address":"1445 Lincoln Way",
    "sg:city":"Auburn",
    "sg:classifiers":[
        {
            "category":"Professional",
            "subcategory":"Lawyer & Legal Services",
            "type":"Services"
        }
    ],
    "sg:phone":"+1 530 823 3501",
    "sg:postcode":"95603",
    "sg:province":"CA",
    "sg:tags":[
        "attorney"
    ],
    "wof:name":"Geri R Bray Law Office",
    "wof:placetype":"venue"
},
  "geometry": {"coordinates":[-121.075894,38.896927],"type":"Point"}
}