{
  "type": "Feature",
  "properties": {
    "iso:country":"US",
    "sg:address":"419 Verbena Dr",
    "sg:city":"Borrego Springs",
    "sg:classifiers":[
        {
            "category":"Real Estate",
            "subcategory":"Architect",
            "type":"Services"
        }
    ],
    "sg:phone":"+1 760 767 5100",
    "sg:postcode":"92004",
    "sg:province":"CA",
    "wof:name":"Desert Architects",
    "wof:placetype":"venue"
},
  "geometry": {"coordinates":[-116.387184,33.259197],"type":"Point"}
}