{
  "type": "Feature",
  "properties": {
    "addr:full":"1511 E Holt Blvd Ontario CA 91761",
    "addr:housenumber":"1511",
    "addr:postcode":"91761",
    "addr:street":"E Holt Blvd",
    "iso:country":"US",
    "sg:address":"1511 E Holt Blvd",
    "sg:city":"Ontario",
    "sg:classifiers":[
        {
            "category":"Government",
            "subcategory":"Jail",
            "type":"Public Place"
        }
    ],
    "sg:phone":"+1 909 983 0692",
    "sg:postcode":"91761",
    "sg:province":"CA",
    "sg:tags":[
        "govt",
        "state",
        "institution"
    ],
    "wof:name":"Corrections Dept",
    "wof:placetype":"venue"
},
  "geometry": {"coordinates":[-117.621235,34.063522],"type":"Point"}
}