{
  "type": "Feature",
  "properties": {
    "addr:full":"909 S Figueroa St Los Angeles CA 90015",
    "addr:housenumber":"909",
    "addr:postcode":"90015",
    "addr:street":"S Figueroa St",
    "iso:country":"US",
    "sg:address":"909 S Figueroa St",
    "sg:city":"Los Angeles",
    "sg:classifiers":[
        {
            "category":"Utilities",
            "subcategory":"Telephone",
            "type":"Services"
        }
    ],
    "sg:phone":"+1 213 488 1007",
    "sg:postcode":"90015",
    "sg:province":"CA",
    "sg:tags":[
        "communications"
    ],
    "wof:name":"Waku Waku Network",
    "wof:placetype":"venue"
},
  "geometry": {"coordinates":[-118.26390499999999,34.045149],"type":"Point"}
}