{
  "type": "Feature",
  "properties": {
    "iso:country":"US",
    "sg:address":"1925 Alum Rock Avenue Suite B",
    "sg:city":"San Jose",
    "sg:classifiers":[
        {
            "category":"Health Services",
            "subcategory":"Chiropractor",
            "type":"Services"
        }
    ],
    "sg:phone":"+1 408 923 0203",
    "sg:postcode":"95116",
    "sg:province":"CA",
    "wof:name":"Rhodes Chiropractic Corporation",
    "wof:placetype":"venue"
},
  "geometry": {"coordinates":[-121.850827,37.355045],"type":"Point"}
}