{
  "type": "Feature",
  "properties": {
    "iso:country":"US",
    "sg:address":"1536 Pacific Ave",
    "sg:city":"San Francisco",
    "sg:classifiers":[
        {
            "category":"Retail",
            "subcategory":"Auto Repair",
            "type":"Services"
        }
    ],
    "sg:phone":"+1 415 885 2433",
    "sg:postcode":"94109",
    "sg:province":"CA",
    "sg:tags":[
        "repairing",
        "automobile"
    ],
    "wof:name":"Jet-Sen Auto Repair",
    "wof:placetype":"venue"
},
  "geometry": {"coordinates":[-122.421117,37.795179],"type":"Point"}
}