{
  "type": "Feature",
  "properties": {
    "iso:country":"US",
    "sg:address":"2629 Hutchison St",
    "sg:city":"Vista",
    "sg:classifiers":[
        {
            "category":"Professional",
            "type":"Services"
        }
    ],
    "sg:phone":"+1 760 945 0248",
    "sg:postcode":"92084",
    "sg:province":"CA",
    "wof:name":"Bc Inc",
    "wof:placetype":"venue"
},
  "geometry": {"coordinates":[-117.242148,33.241977],"type":"Point"}
}