{
  "type": "Feature",
  "properties": {
    "addr:full":"179 S Newmark Ave Sanger CA 93657",
    "addr:housenumber":"179",
    "addr:postcode":"ca 93657",
    "addr:street":"S Newmark Ave",
    "iso:country":"US",
    "sg:address":"179 S Newmark Ave",
    "sg:city":"Sanger",
    "sg:classifiers":[
        {
            "category":"Farming",
            "subcategory":"Crops",
            "type":"Manufacturing & Wholesale Goods"
        }
    ],
    "sg:phone":"+1 559 875 5918",
    "sg:postcode":"93657",
    "sg:province":"CA",
    "sg:tags":[
        "grove",
        "nut",
        "tree"
    ],
    "wof:name":"George L Magnone",
    "wof:placetype":"venue"
},
  "geometry": {"coordinates":[-119.529381,36.730935],"type":"Point"}
}