{
  "type": "Feature",
  "properties": {
    "iso:country":"US",
    "sg:address":"3290 N State St",
    "sg:city":"Ukiah",
    "sg:classifiers":[
        {
            "category":"Government",
            "subcategory":"Office",
            "type":"Public Place"
        }
    ],
    "sg:phone":"+1 707 463 4714",
    "sg:postcode":"95482",
    "sg:province":"CA",
    "sg:tags":[
        "state"
    ],
    "wof:name":"General Services Dept",
    "wof:placetype":"venue"
},
  "geometry": {"coordinates":[-123.206625,39.195117],"type":"Point"}
}