{
  "type": "Feature",
  "properties": {
    "addr:full":"5238 Manzanita Ave Carmichael CA 95608",
    "addr:housenumber":"5238",
    "addr:postcode":"95608",
    "addr:street":"Manzanita Ave",
    "iso:country":"US",
    "sg:address":"5238 Manzanita Ave",
    "sg:city":"Carmichael",
    "sg:classifiers":[
        {
            "category":"Real Estate",
            "subcategory":"Real Estate Agent",
            "type":"Services"
        }
    ],
    "sg:phone":"+1 916 339 3230",
    "sg:postcode":"95608",
    "sg:province":"CA",
    "wof:name":"Kimco Realty Corp",
    "wof:placetype":"venue"
},
  "geometry": {"coordinates":[-121.32731099999999,38.661875],"type":"Point"}
}