{
  "type": "Feature",
  "properties": {
    "iso:country":"US",
    "sg:address":"1250 Aviation Ave",
    "sg:city":"San Jose",
    "sg:classifiers":[
        {
            "category":"Wholesale",
            "subcategory":"Machinery & Supplies",
            "type":"Manufacturing & Wholesale Goods"
        }
    ],
    "sg:phone":"+1 408 920 9620",
    "sg:postcode":"95110",
    "sg:province":"CA",
    "sg:tags":[
        "aircraft",
        "parts"
    ],
    "wof:name":"Hubschrauber Inc",
    "wof:placetype":"venue"
},
  "geometry": {"coordinates":[-121.929999,37.355747],"type":"Point"}
}