{
  "type": "Feature",
  "properties": {
    "addr:full":"6131 Telegraph Rd Los Angeles CA 90040",
    "addr:housenumber":"6131",
    "addr:postcode":"90040",
    "addr:street":"Telegraph Rd",
    "iso:country":"US",
    "sg:address":"6131 Telegraph Rd",
    "sg:city":"Los Angeles",
    "sg:classifiers":[
        {
            "category":"Retail",
            "subcategory":"Laundry & Dry Cleaning",
            "type":"Services"
        }
    ],
    "sg:phone":"+1 323 887 1888",
    "sg:postcode":"90040",
    "sg:province":"CA",
    "wof:name":"Commerce Expert Cleaners Inc",
    "wof:placetype":"venue"
},
  "geometry": {"coordinates":[-118.147003,33.999199],"type":"Point"}
}