{
  "type": "Feature",
  "properties": {
    "iso:country":"US",
    "sg:address":"2279 Ward Ave",
    "sg:city":"Simi Valley",
    "sg:classifiers":[
        {
            "category":"Wholesale",
            "subcategory":"Machinery & Supplies",
            "type":"Manufacturing & Wholesale Goods"
        }
    ],
    "sg:phone":"+1 805 433 0165",
    "sg:postcode":"93065",
    "sg:province":"CA",
    "sg:tags":[
        "glass",
        "tank",
        "plastic"
    ],
    "wof:name":"Flexible Alternative Inc",
    "wof:placetype":"venue"
},
  "geometry": {"coordinates":[-118.785391,34.275527],"type":"Point"}
}