{
  "type": "Feature",
  "properties": {
    "addr:full":"6585 Commerce Blvd Rohnert Park CA 94928",
    "addr:housenumber":"6585",
    "addr:postcode":"94928",
    "addr:street":"Commerce Blvd",
    "iso:country":"US",
    "sg:address":"6585 Commerce Blvd",
    "sg:city":"Rohnert Park",
    "sg:classifiers":[
        {
            "category":"Building & Trades",
            "subcategory":"Construction",
            "type":"Services"
        }
    ],
    "sg:phone":"+1 707 584 8225",
    "sg:postcode":"94928",
    "sg:province":"CA",
    "sg:tags":[
        "contractor"
    ],
    "wof:name":"Excel Roofing",
    "wof:placetype":"venue"
},
  "geometry": {"coordinates":[-122.71005,38.345988],"type":"Point"}
}