{
  "type": "Feature",
  "properties": {
    "addr:full":"9851 Horn Rd Sacramento CA 95827",
    "addr:housenumber":"9851",
    "addr:postcode":"95827",
    "addr:street":"Horn Rd",
    "iso:country":"US",
    "sg:address":"9851 Horn Rd",
    "sg:city":"Sacramento",
    "sg:classifiers":[
        {
            "category":"Manufacturing",
            "subcategory":"Printing",
            "type":"Manufacturing & Wholesale Goods"
        }
    ],
    "sg:phone":"+1 916 363 1913",
    "sg:postcode":"95827",
    "sg:province":"CA",
    "sg:tags":[
        "publisher"
    ],
    "wof:name":"Naylor Publications",
    "wof:placetype":"venue"
},
  "geometry": {"coordinates":[-121.32790199999999,38.574749],"type":"Point"}
}