{
  "type": "Feature",
  "properties": {
    "addr:full":"2500 Michelson Drive Irvine CA 92612",
    "addr:housenumber":"2500",
    "addr:postcode":"92612",
    "addr:street":"Michelson Drive",
    "iso:country":"US",
    "sg:address":"2500 Michelson Drive",
    "sg:city":"Irvine",
    "sg:classifiers":[
        {
            "category":"Real Estate",
            "subcategory":"Architect",
            "type":"Services"
        }
    ],
    "sg:phone":"+1 949 862 7440",
    "sg:postcode":"92612",
    "sg:province":"CA",
    "wof:name":"Sasaki Assocs.",
    "wof:placetype":"venue"
},
  "geometry": {"coordinates":[-117.851354,33.674969],"type":"Point"}
}