{
  "type": "Feature",
  "properties": {
    "iso:country":"US",
    "sg:address":"5897 Oberlin Dr",
    "sg:city":"San Diego",
    "sg:classifiers":[
        {
            "category":"Professional",
            "type":"Services"
        }
    ],
    "sg:phone":"+1 858 373 3300",
    "sg:postcode":"92121",
    "sg:province":"CA",
    "sg:tags":[
        "establishment"
    ],
    "wof:name":"Red I Studios",
    "wof:placetype":"venue"
},
  "geometry": {"coordinates":[-117.195373,32.892286],"type":"Point"}
}