{
  "type": "Feature",
  "properties": {
    "iso:country":"US",
    "sg:address":"10152 Bonser Ave",
    "sg:city":"Garden Grove",
    "sg:classifiers":[
        {
            "category":"Real Estate",
            "subcategory":"Real Estate Agent",
            "type":"Services"
        }
    ],
    "sg:phone":"+1 714 376 1075",
    "sg:postcode":"92840",
    "sg:province":"CA",
    "wof:name":"Team Appraisals",
    "wof:placetype":"venue"
},
  "geometry": {"coordinates":[-117.95634800000001,33.78412],"type":"Point"}
}