{
  "type": "Feature",
  "properties": {
    "iso:country":"US",
    "sg:address":"7803 Telegraph Rd",
    "sg:city":"Montebello",
    "sg:classifiers":[
        {
            "category":"Manufacturing",
            "subcategory":"Metals",
            "type":"Manufacturing & Wholesale Goods"
        }
    ],
    "sg:phone":"+1 323 722 0969",
    "sg:postcode":"90640",
    "sg:province":"CA",
    "sg:tags":[
        "stamping"
    ],
    "wof:name":"Master Washer & Stamping",
    "wof:placetype":"venue"
},
  "geometry": {"coordinates":[-118.1221,33.973868],"type":"Point"}
}