{
  "type": "Feature",
  "properties": {
    "addr:full":"12634 Hortense St Studio City CA 91604",
    "addr:housenumber":"12634",
    "addr:postcode":"91604",
    "addr:street":"Hortense St",
    "iso:country":"US",
    "sg:address":"12634 Hortense St",
    "sg:city":"Studio City",
    "sg:classifiers":[
        {
            "category":"Manufacturing",
            "subcategory":"Printing",
            "type":"Manufacturing & Wholesale Goods"
        }
    ],
    "sg:phone":"+1 818 989 1995",
    "sg:postcode":"91604",
    "sg:province":"CA",
    "sg:tags":[
        "publisher",
        "music"
    ],
    "wof:name":"From Other Worlds",
    "wof:placetype":"venue"
},
  "geometry": {"coordinates":[-118.408638,34.15485],"type":"Point"}
}