{
  "type": "Feature",
  "properties": {
    "addr:full":"14939 Muscatel St Hesperia CA 92345",
    "addr:housenumber":"14939",
    "addr:postcode":"92345",
    "addr:street":"Muscatel St",
    "iso:country":"US",
    "sg:address":"14939 Muscatel St",
    "sg:city":"Hesperia",
    "sg:classifiers":[
        {
            "category":"Building & Trades",
            "subcategory":"Landscaping Services",
            "type":"Services"
        }
    ],
    "sg:phone":"+1 760 244 9013",
    "sg:postcode":"92345",
    "sg:province":"CA",
    "wof:name":"Yard Doctor",
    "wof:placetype":"venue"
},
  "geometry": {"coordinates":[-117.33078,34.412276],"type":"Point"}
}