{
  "type": "Feature",
  "properties": {
    "addr:full":"127 N California Ave City Of Industry CA 91744",
    "addr:housenumber":"127",
    "addr:postcode":"91744",
    "addr:street":"N California Ave",
    "iso:country":"US",
    "sg:address":"127 N California Ave",
    "sg:city":"City Of Industry",
    "sg:classifiers":[
        {
            "category":"Wholesale",
            "subcategory":"Furniture",
            "type":"Manufacturing & Wholesale Goods"
        }
    ],
    "sg:phone":"+1 626 333 6244",
    "sg:postcode":"91744",
    "sg:province":"CA",
    "sg:website":"www.torano.com",
    "wof:name":"John Turano & Sons Inc",
    "wof:placetype":"venue"
},
  "geometry": {"coordinates":[-117.967555,34.033239],"type":"Point"}
}