{
  "type": "Feature",
  "properties": {
    "iso:country":"US",
    "sg:address":"875 National Dr Ste 107",
    "sg:city":"Sacramento",
    "sg:classifiers":[
        {
            "category":"Building & Trades",
            "subcategory":"Plumbing",
            "type":"Services"
        }
    ],
    "sg:phone":"+1 916 928 8926",
    "sg:postcode":"95834",
    "sg:province":"CA",
    "sg:website":"www.bianchiheatingandair.com",
    "wof:name":"Bianchi Heating & Air Plumbing",
    "wof:placetype":"venue"
},
  "geometry": {"coordinates":[-121.48789499999999,38.654901],"type":"Point"}
}