{
  "type": "Feature",
  "properties": {
    "addr:full":"3751 Stockton Blvd Sacramento CA 95820",
    "addr:housenumber":"3751",
    "addr:postcode":"95820",
    "addr:street":"Stockton Blvd",
    "iso:country":"US",
    "sg:address":"3751 Stockton Blvd",
    "sg:city":"Sacramento",
    "sg:classifiers":[
        {
            "category":"Bakery",
            "type":"Food & Drink"
        }
    ],
    "sg:phone":"+1 916 454 1375",
    "sg:postcode":"95820",
    "sg:province":"CA",
    "sg:tags":[
        "cake",
        "pastry",
        "wedding"
    ],
    "wof:name":"Spotlight Cakes",
    "wof:placetype":"venue"
},
  "geometry": {"coordinates":[-121.450169,38.540231],"type":"Point"}
}