{
  "type": "Feature",
  "properties": {
    "addr:full":"1751 Crenshaw Blvd Torrance CA 90501",
    "addr:housenumber":"1751",
    "addr:postcode":"90501",
    "addr:street":"Crenshaw Blvd",
    "iso:country":"US",
    "sg:address":"1751 Crenshaw Blvd",
    "sg:city":"Torrance",
    "sg:classifiers":[
        {
            "category":"Retail",
            "subcategory":"Car Wash",
            "type":"Services"
        }
    ],
    "sg:phone":"+1 310 533 1005",
    "sg:postcode":"90501",
    "sg:province":"CA",
    "wof:name":"Torrance Auto Spa",
    "wof:placetype":"venue"
},
  "geometry": {"coordinates":[-118.328003,33.827599],"type":"Point"}
}