{
  "type": "Feature",
  "properties": {
    "addr:full":"3472 Canoga Pl Camarillo CA 93010",
    "addr:housenumber":"3472",
    "addr:postcode":"93010",
    "addr:street":"Canoga Pl",
    "iso:country":"US",
    "sg:address":"3472 Canoga Pl",
    "sg:city":"Camarillo",
    "sg:classifiers":[
        {
            "category":"Farming",
            "subcategory":"Nursery",
            "type":"Manufacturing & Wholesale Goods"
        }
    ],
    "sg:phone":"+1 805 987 6192",
    "sg:postcode":"93010",
    "sg:province":"CA",
    "sg:tags":[
        "ornamental"
    ],
    "wof:name":"Catanusaka Flower Growers",
    "wof:placetype":"venue"
},
  "geometry": {"coordinates":[-119.02478600000001,34.232883],"type":"Point"}
}