{
  "type": "Feature",
  "properties": {
    "addr:full":"234 S Escondido Blvd Escondido CA 92025",
    "addr:housenumber":"234",
    "addr:postcode":"92025",
    "addr:street":"S Escondido Blvd",
    "iso:country":"US",
    "sg:address":"234 S Escondido Blvd",
    "sg:city":"Escondido",
    "sg:classifiers":[
        {
            "category":"Professional",
            "subcategory":"Lawyer & Legal Services",
            "type":"Services"
        }
    ],
    "sg:phone":"+1 760 735 8030",
    "sg:postcode":"92025",
    "sg:province":"CA",
    "sg:tags":[
        "divorce",
        "assistance"
    ],
    "wof:name":"Calling It Quits",
    "wof:placetype":"venue"
},
  "geometry": {"coordinates":[-117.083376,33.119284],"type":"Point"}
}