{
  "type": "Feature",
  "properties": {
    "addr:full":"382 Pearson Dr Porterville CA 93257",
    "addr:housenumber":"382",
    "addr:postcode":"93257",
    "addr:street":"Pearson Dr",
    "iso:country":"US",
    "sg:address":"382 Pearson Dr",
    "sg:city":"Porterville",
    "sg:classifiers":[
        {
            "category":"Health Services",
            "subcategory":"Doctor",
            "type":"Services"
        }
    ],
    "sg:phone":"+1 559 783 2904",
    "sg:postcode":"93257",
    "sg:province":"CA",
    "sg:tags":[
        "physician",
        "surgeon"
    ],
    "wof:name":"Dunn James S Jr MD Inc.",
    "wof:placetype":"venue"
},
  "geometry": {"coordinates":[-119.027637,36.07122],"type":"Point"}
}