{
  "type": "Feature",
  "properties": {
    "addr:full":"21519 Strathern St Canoga Park CA 91304",
    "addr:postcode":"21519;91304",
    "addr:street":"Strathern St",
    "iso:country":"US",
    "sg:address":"21519 Strathern St",
    "sg:city":"Canoga Park",
    "sg:classifiers":[
        {
            "category":"Retail",
            "subcategory":"Repair Shop",
            "type":"Services"
        }
    ],
    "sg:phone":"+1 818 347 1030",
    "sg:postcode":"91304",
    "sg:province":"CA",
    "sg:tags":[
        "motorcycle"
    ],
    "sg:website":"www.teamimsracing.com",
    "wof:name":"International Motorcycle Svc",
    "wof:placetype":"venue"
},
  "geometry": {"coordinates":[-118.600184,34.21562],"type":"Point"}
}