{
  "type": "Feature",
  "properties": {
    "iso:country":"US",
    "sg:address":"283 W Lewis St",
    "sg:city":"Ventura",
    "sg:classifiers":[
        {
            "category":"Freight",
            "type":"Transportation"
        }
    ],
    "sg:phone":"+1 805 644 1411",
    "sg:postcode":"93001",
    "sg:province":"CA",
    "sg:tags":[
        "vehicle",
        "recreational",
        "general"
    ],
    "wof:name":"Westside Boat & R V Storage",
    "wof:placetype":"venue"
},
  "geometry": {"coordinates":[-119.301138,34.295886],"type":"Point"}
}