{
  "type": "Feature",
  "properties": {
    "iso:country":"US",
    "sg:address":"5327 Jacuzzi #5E",
    "sg:city":"Richmond",
    "sg:classifiers":[
        {
            "category":"Building & Trades",
            "subcategory":"Construction",
            "type":"Services"
        }
    ],
    "sg:phone":"+1 510 559 5530",
    "sg:postcode":"94804",
    "sg:province":"CA",
    "sg:tags":[
        "contractor"
    ],
    "sg:website":"www.ataylormadewindow.com",
    "wof:name":"A-Taylor Made Window",
    "wof:placetype":"venue"
},
  "geometry": {"coordinates":[-122.311753,37.89835],"type":"Point"}
}