{
  "type": "Feature",
  "properties": {
    "addr:full":"1360 Darius Ct City Of Industry CA 91745",
    "addr:housenumber":"1360",
    "addr:postcode":"91745",
    "addr:street":"Darius Ct",
    "iso:country":"US",
    "sg:address":"1360 Darius Ct",
    "sg:city":"City Of Industry",
    "sg:classifiers":[
        {
            "category":"Manufacturing",
            "subcategory":"Tools & Machinery",
            "type":"Manufacturing & Wholesale Goods"
        }
    ],
    "sg:phone":"+1 626 968 0556",
    "sg:postcode":"91745",
    "sg:province":"CA",
    "sg:tags":[
        "equipment",
        "material",
        "handling"
    ],
    "sg:website":"www.crown.com",
    "wof:name":"Crown Lift Trucks",
    "wof:placetype":"venue"
},
  "geometry": {"coordinates":[-117.94695900000001,34.002852],"type":"Point"}
}