{
  "type": "Feature",
  "properties": {
    "addr:full":"2171 Pillsbury Rd Chico CA 95926",
    "addr:housenumber":"2171",
    "addr:postcode":"95926",
    "addr:street":"Pillsbury Rd",
    "iso:country":"US",
    "sg:address":"2171 Pillsbury Rd",
    "sg:city":"Chico",
    "sg:classifiers":[
        {
            "category":"Banks & Credit Unions",
            "subcategory":"Bank",
            "type":"Services"
        }
    ],
    "sg:phone":"+1 530 898 0470",
    "sg:postcode":"95926",
    "sg:province":"CA",
    "wof:name":"Tri Counties Bank",
    "wof:placetype":"venue"
},
  "geometry": {"coordinates":[-121.84446699999999,39.757885],"type":"Point"}
}