{
  "type": "Feature",
  "properties": {
    "iso:country":"US",
    "sg:address":"801 E Walnut St",
    "sg:city":"Pasadena",
    "sg:classifiers":[
        {
            "category":"Real Estate",
            "subcategory":"Real Estate Operator",
            "type":"Services"
        }
    ],
    "sg:phone":"+1 626 564 0006",
    "sg:postcode":"91101",
    "sg:province":"CA",
    "sg:tags":[
        "apartment"
    ],
    "sg:website":"www.liveatalliance.com/cityplace...",
    "wof:name":"City Place",
    "wof:placetype":"venue"
},
  "geometry": {"coordinates":[-118.13419399999999,34.149597],"type":"Point"}
}