{
  "type": "Feature",
  "properties": {
    "iso:country":"US",
    "sg:address":"2801 Townsgate Rd",
    "sg:city":"Westlake Village",
    "sg:classifiers":[
        {
            "category":"Banks & Credit Unions",
            "subcategory":"Bank",
            "type":"Services"
        }
    ],
    "sg:phone":"+1 818 889 3102",
    "sg:postcode":"91361",
    "sg:province":"CA",
    "sg:tags":[
        "escrow"
    ],
    "sg:website":"www.chicagotitle-venturacounty.com",
    "wof:name":"Chicago Title Co",
    "wof:placetype":"venue"
},
  "geometry": {"coordinates":[-118.820781,34.15106],"type":"Point"}
}