{
  "type": "Feature",
  "properties": {
    "iso:country":"US",
    "sg:address":"3330 Main St",
    "sg:city":"Oakley",
    "sg:classifiers":[
        {
            "category":"Shopping",
            "subcategory":"Gifts & Souvenirs",
            "type":"Retail Goods"
        }
    ],
    "sg:phone":"+1 925 625 2879",
    "sg:postcode":"94561",
    "sg:province":"CA",
    "sg:tags":[
        "shop",
        "novelty"
    ],
    "wof:name":"By Yvonne",
    "wof:placetype":"venue"
},
  "geometry": {"coordinates":[-121.71588,37.997878],"type":"Point"}
}