{
  "type": "Feature",
  "properties": {
    "iso:country":"US",
    "sg:address":"109 Stevenson St",
    "sg:city":"San Francisco",
    "sg:classifiers":[
        {
            "category":"Building & Trades",
            "subcategory":"Construction",
            "type":"Services"
        }
    ],
    "sg:phone":"+1 415 882 7422",
    "sg:postcode":"94105",
    "sg:province":"CA",
    "sg:tags":[
        "designer"
    ],
    "wof:name":"HAA Design",
    "wof:placetype":"venue"
},
  "geometry": {"coordinates":[-122.40136099999999,37.788311],"type":"Point"}
}