{
  "type": "Feature",
  "properties": {
    "addr:full":"2839 Old 1st St Livermore CA 94550",
    "addr:housenumber":"2839",
    "addr:postcode":"94550",
    "addr:street":"Old 1St St",
    "iso:country":"US",
    "sg:address":"2839 Old 1st St",
    "sg:city":"Livermore",
    "sg:classifiers":[
        {
            "category":"Home & Garden",
            "subcategory":"Carpets & Floor Coverings",
            "type":"Retail Goods"
        }
    ],
    "sg:phone":"+1 510 714 6739",
    "sg:postcode":"94550",
    "sg:province":"CA",
    "sg:tags":[
        "material"
    ],
    "wof:name":"Bayview Wood Floor Design",
    "wof:placetype":"venue"
},
  "geometry": {"coordinates":[-121.765045,37.684782],"type":"Point"}
}