{
  "type": "Feature",
  "properties": {
    "iso:country":"US",
    "sg:address":"1939 Butte St",
    "sg:city":"Redding",
    "sg:classifiers":[
        {
            "category":"Professional",
            "subcategory":"Lawyer & Legal Services",
            "type":"Services"
        }
    ],
    "sg:phone":"+1 530 246 1578",
    "sg:postcode":"96001",
    "sg:province":"CA",
    "sg:tags":[
        "attorney"
    ],
    "wof:name":"Erin O'Toole-Mc Nally Law Ofc",
    "wof:placetype":"venue"
},
  "geometry": {"coordinates":[-122.397896,40.582771],"type":"Point"}
}