{
  "type": "Feature",
  "properties": {
    "addr:full":"1240 49th Ave Oakland CA 94601",
    "addr:housenumber":"1240",
    "addr:postcode":"94601",
    "addr:street":"49Th Ave",
    "iso:country":"US",
    "sg:address":"1240 49th Ave",
    "sg:city":"Oakland",
    "sg:classifiers":[
        {
            "category":"Manufacturing",
            "subcategory":"Metals",
            "type":"Manufacturing & Wholesale Goods"
        }
    ],
    "sg:phone":"+1 510 536 3334",
    "sg:postcode":"94601",
    "sg:province":"CA",
    "sg:tags":[
        "ornamental",
        "work"
    ],
    "sg:website":"www.cmfmetal.com",
    "wof:name":"CMF Metal",
    "wof:placetype":"venue"
},
  "geometry": {"coordinates":[-122.209678,37.769419],"type":"Point"}
}