{
  "type": "Feature",
  "properties": {
    "iso:country":"US",
    "sg:address":"2627 San Diego Ave",
    "sg:city":"San Diego",
    "sg:classifiers":[
        {
            "category":"Shopping",
            "subcategory":"Books",
            "type":"Retail Goods"
        }
    ],
    "sg:phone":"+1 619 298 3944",
    "sg:postcode":"92110",
    "sg:province":"CA",
    "sg:tags":[
        "dealer"
    ],
    "wof:name":"Captain Fitch's Mercantile",
    "wof:placetype":"venue"
},
  "geometry": {"coordinates":[-117.196697,32.753497],"type":"Point"}
}