{
  "type": "Feature",
  "properties": {
    "iso:country":"US",
    "sg:address":"1044 Broadway",
    "sg:city":"Chula Vista",
    "sg:classifiers":[
        {
            "category":"Manufacturing",
            "subcategory":"Glass & Minerals",
            "type":"Manufacturing & Wholesale Goods"
        }
    ],
    "sg:phone":"+1 619 420 6403",
    "sg:postcode":"91911",
    "sg:province":"CA",
    "sg:tags":[
        "product",
        "mfg"
    ],
    "wof:name":"Elad 6 Laser & Engraving",
    "wof:placetype":"venue"
},
  "geometry": {"coordinates":[-117.08226000000001,32.612396],"type":"Point"}
}