{
  "type": "Feature",
  "properties": {
    "addr:full":"4160 Justin Way Sacramento CA 95826",
    "addr:housenumber":"4160",
    "addr:postcode":"95826",
    "addr:street":"Justin Way",
    "iso:country":"US",
    "sg:address":"4160 Justin Way",
    "sg:city":"Sacramento",
    "sg:classifiers":[
        {
            "category":"Retail",
            "subcategory":"Laundry & Dry Cleaning",
            "type":"Services"
        }
    ],
    "sg:phone":"+1 530 432 2131",
    "sg:postcode":"95826",
    "sg:province":"CA",
    "sg:tags":[
        "cleaner",
        "rug",
        "carpet"
    ],
    "wof:name":"All Clean",
    "wof:placetype":"venue"
},
  "geometry": {"coordinates":[-121.35211200000001,38.542439],"type":"Point"}
}