{
  "type": "Feature",
  "properties": {
    "iso:country":"US",
    "sg:address":"3394 Hamner Ave",
    "sg:city":"Norco",
    "sg:classifiers":[
        {
            "category":"Retail",
            "subcategory":"Auto Repair",
            "type":"Services"
        }
    ],
    "sg:phone":"+1 951 278 3171",
    "sg:postcode":"92860",
    "sg:province":"CA",
    "sg:tags":[
        "repairing",
        "automobile"
    ],
    "wof:name":"Tuneup Masters",
    "wof:placetype":"venue"
},
  "geometry": {"coordinates":[-117.558266,33.928051],"type":"Point"}
}