{
  "type": "Feature",
  "properties": {
    "addr:full":"543 Lindstrom Ct San Jose CA 95111",
    "addr:housenumber":"543",
    "addr:postcode":"95111",
    "addr:street":"Lindstrom Ct",
    "iso:country":"US",
    "sg:address":"543 Lindstrom Ct",
    "sg:city":"San Jose",
    "sg:classifiers":[
        {
            "category":"Building & Trades",
            "subcategory":"Construction",
            "type":"Services"
        }
    ],
    "sg:phone":"+1 408 313 5787",
    "sg:postcode":"95111",
    "sg:province":"CA",
    "sg:tags":[
        "contractor"
    ],
    "wof:name":"Cable Solutions Inc.",
    "wof:placetype":"venue"
},
  "geometry": {"coordinates":[-121.79534200000001,37.262843],"type":"Point"}
}