{
  "type": "Feature",
  "properties": {
    "iso:country":"US",
    "sg:address":"3411 3rd Ave",
    "sg:city":"San Diego",
    "sg:classifiers":[
        {
            "category":"Social Services",
            "type":"Services"
        }
    ],
    "sg:phone":"+1 619 298 5835",
    "sg:postcode":"92103",
    "sg:province":"CA",
    "sg:tags":[
        "counselor",
        "marriage",
        "family"
    ],
    "wof:name":"Eve Boyer",
    "wof:placetype":"venue"
},
  "geometry": {"coordinates":[-117.162114,32.741391],"type":"Point"}
}