{
  "type": "Feature",
  "properties": {
    "addr:full":"7650 Sepulveda Blvd Van Nuys CA 91405",
    "addr:housenumber":"7650",
    "addr:postcode":"91405",
    "addr:street":"Sepulveda Blvd",
    "iso:country":"US",
    "sg:address":"7650 Sepulveda Blvd",
    "sg:city":"Van Nuys",
    "sg:classifiers":[
        {
            "category":"Retail",
            "subcategory":"Auto Repair",
            "type":"Services"
        }
    ],
    "sg:phone":"+1 818 376 1448",
    "sg:postcode":"91405",
    "sg:province":"CA",
    "sg:tags":[
        "repairing",
        "automobile"
    ],
    "wof:name":"Japanese Car Care",
    "wof:placetype":"venue"
},
  "geometry": {"coordinates":[-118.466127,34.211157],"type":"Point"}
}