{
  "type": "Feature",
  "properties": {
    "iso:country":"US",
    "sg:address":"19500 Plummer St",
    "sg:city":"Northridge",
    "sg:classifiers":[
        {
            "category":"Shopping",
            "subcategory":"Shoes",
            "type":"Retail Goods"
        }
    ],
    "sg:phone":"+1 818 727 1470",
    "sg:postcode":"91324",
    "sg:province":"CA",
    "wof:name":"DSW Shoe Warehouse",
    "wof:placetype":"venue"
},
  "geometry": {"coordinates":[-118.56231099999999,34.242736],"type":"Point"}
}