{
  "type": "Feature",
  "properties": {
    "iso:country":"US",
    "sg:address":"4150 Riverside Dr",
    "sg:city":"Burbank",
    "sg:classifiers":[
        {
            "category":"Arts & Performance",
            "subcategory":"Art Gallery",
            "type":"Entertainment"
        },
        {
            "category":"Shopping",
            "subcategory":"Bicycles & Sporting Goods",
            "type":"Retail Goods"
        }
    ],
    "sg:phone":"+1 818 841 8408",
    "sg:postcode":"91505",
    "sg:province":"CA",
    "sg:tags":[
        "bike"
    ],
    "sg:website":"velopasadena.com/",
    "wof:name":"Velo Studio",
    "wof:placetype":"venue"
},
  "geometry": {"coordinates":[-118.344577,34.152034],"type":"Point"}
}