{
  "type": "Feature",
  "properties": {
    "addr:full":"2440 Las Posas Rd Camarillo CA 93010",
    "addr:housenumber":"2440",
    "addr:postcode":"93010",
    "addr:street":"Las Posas Rd",
    "iso:country":"US",
    "sg:address":"2440 Las Posas Rd",
    "sg:city":"Camarillo",
    "sg:classifiers":[
        {
            "category":"Shopping",
            "subcategory":"Gifts & Souvenirs",
            "type":"Retail Goods"
        }
    ],
    "sg:phone":"+1 805 389 4263",
    "sg:postcode":"93010",
    "sg:province":"CA",
    "sg:tags":[
        "shop"
    ],
    "wof:name":"Tuesday Morning Inc",
    "wof:placetype":"venue"
},
  "geometry": {"coordinates":[-119.03798,34.236654],"type":"Point"}
}