{
  "type": "Feature",
  "properties": {
    "iso:country":"US",
    "sg:address":"1743 Colorado Blvd",
    "sg:city":"Los Angeles",
    "sg:classifiers":[
        {
            "category":"Shopping",
            "subcategory":"Tobacco",
            "type":"Retail Goods"
        }
    ],
    "sg:phone":"+1 323 256 0076",
    "sg:postcode":"90041",
    "sg:province":"CA",
    "sg:tags":[
        "shop"
    ],
    "wof:name":"Cig Zone",
    "wof:placetype":"venue"
},
  "geometry": {"coordinates":[-118.206001,34.139301],"type":"Point"}
}