{
  "type": "Feature",
  "properties": {
    "addr:full":"4097 19th Ave San Francisco CA 94132",
    "addr:housenumber":"4097",
    "addr:postcode":"94132",
    "addr:street":"19Th Ave",
    "iso:country":"US",
    "sg:address":"4097 19th Ave",
    "sg:city":"San Francisco",
    "sg:classifiers":[
        {
            "category":"Restaurant",
            "type":"Food & Drink"
        }
    ],
    "sg:menulink":"http://www.allmenus.com/ca/san-francisco/62724-diala-pizza/menu/",
    "sg:phone":"+1 415 566 6455",
    "sg:postcode":"94132",
    "sg:province":"CA",
    "sg:tags":[
        "american",
        "pizza"
    ],
    "wof:name":"Diala Pizza",
    "wof:placetype":"venue"
},
  "geometry": {"coordinates":[-122.470556,37.714998],"type":"Point"}
}