{
  "type": "Feature",
  "properties": {
    "iso:country":"US",
    "sg:address":"715 Plumas St",
    "sg:city":"Yuba City",
    "sg:classifiers":[
        {
            "category":"Shopping",
            "subcategory":"Gifts & Souvenirs",
            "type":"Retail Goods"
        }
    ],
    "sg:phone":"+1 530 674 2790",
    "sg:postcode":"95991",
    "sg:province":"CA",
    "sg:tags":[
        "party",
        "supply"
    ],
    "sg:website":"www.peltonsparty.com",
    "wof:name":"Pelton's Party Rental & Sales",
    "wof:placetype":"venue"
},
  "geometry": {"coordinates":[-121.6164,39.137913],"type":"Point"}
}