{
  "type": "Feature",
  "properties": {
    "addr:full":"2600 Hawthorne St Sacramento CA 95815",
    "addr:housenumber":"2600",
    "addr:postcode":"95815",
    "addr:street":"Hawthorne St",
    "iso:country":"US",
    "sg:address":"2600 Hawthorne St",
    "sg:city":"Sacramento",
    "sg:classifiers":[
        {
            "category":"Professional",
            "subcategory":"Accounting & Tax Preparation",
            "type":"Services"
        }
    ],
    "sg:phone":"+1 916 709 0717",
    "sg:postcode":"95815",
    "sg:province":"CA",
    "sg:tags":[
        "accountant"
    ],
    "wof:name":"Sacramento Accounting Svc",
    "wof:placetype":"venue"
},
  "geometry": {"coordinates":[-121.458128,38.616886],"type":"Point"}
}