{
  "type": "Feature",
  "properties": {
    "iso:country":"US",
    "sg:address":"450 Taraval St",
    "sg:city":"San Francisco",
    "sg:classifiers":[
        {
            "category":"Insurance",
            "subcategory":"Insurance Agent",
            "type":"Services"
        }
    ],
    "sg:phone":"+1 415 337 5052",
    "sg:postcode":"94116",
    "sg:province":"CA",
    "wof:name":"Faulkner Associates",
    "wof:placetype":"venue"
},
  "geometry": {"coordinates":[-122.47090799999999,37.74334],"type":"Point"}
}