{
  "type": "Feature",
  "properties": {
    "addr:full":"323 Nevada St Auburn CA 95603",
    "addr:housenumber":"323",
    "addr:postcode":"ca 95603",
    "addr:street":"Nevada St",
    "iso:country":"US",
    "sg:address":"323 Nevada St",
    "sg:city":"Auburn",
    "sg:classifiers":[
        {
            "category":"Organizations",
            "subcategory":"Professional Association",
            "type":"Services"
        }
    ],
    "sg:phone":"+1 530 889 5689",
    "sg:postcode":"95603",
    "sg:province":"CA",
    "wof:name":"National Association-Dev Edu",
    "wof:placetype":"venue"
},
  "geometry": {"coordinates":[-121.08225299999999,38.909341],"type":"Point"}
}