{
  "type": "Feature",
  "properties": {
    "addr:full":"55 Hawthorne St Ste 440 San Francisco CA 94105",
    "addr:housenumber":"55",
    "addr:postcode":"94105",
    "addr:street":"Hawthorne St Ste 440",
    "iso:country":"US",
    "sg:address":"55 Hawthorne St Ste 440",
    "sg:city":"San Francisco",
    "sg:classifiers":[
        {
            "category":"Professional",
            "subcategory":"Lawyer & Legal Services",
            "type":"Services"
        }
    ],
    "sg:phone":"+1 650 636 2500",
    "sg:postcode":"94105",
    "sg:province":"CA",
    "wof:name":"Silverstein and Pomerantz Llp",
    "wof:placetype":"venue"
},
  "geometry": {"coordinates":[-122.398392,37.785655],"type":"Point"}
}