{
  "type": "Feature",
  "properties": {
    "iso:country":"US",
    "sg:address":"2425 Camino Del Rio S",
    "sg:city":"San Diego",
    "sg:classifiers":[
        {
            "category":"Real Estate",
            "subcategory":"Real Estate Services",
            "type":"Services"
        }
    ],
    "sg:phone":"+1 619 260 1040",
    "sg:postcode":"92108",
    "sg:province":"CA",
    "wof:name":"Finch J Walter Realtor",
    "wof:placetype":"venue"
},
  "geometry": {"coordinates":[-117.139,32.767399],"type":"Point"}
}