{
  "type": "Feature",
  "properties": {
    "addr:full":"43 Beacon Bay Newport Beach CA 92660",
    "addr:housenumber":"43",
    "addr:postcode":"92660",
    "addr:street":"Beacon Bay",
    "iso:country":"US",
    "sg:address":"43 Beacon Bay",
    "sg:city":"Newport Beach",
    "sg:classifiers":[
        {
            "category":"Wholesale",
            "subcategory":"Apparel",
            "type":"Manufacturing & Wholesale Goods"
        }
    ],
    "sg:phone":"+1 949 675 0919",
    "sg:postcode":"92660",
    "sg:province":"CA",
    "sg:tags":[
        "clothing"
    ],
    "wof:name":"Pallies Bags",
    "wof:placetype":"venue"
},
  "geometry": {"coordinates":[-117.900232,33.61054],"type":"Point"}
}