{
  "type": "Feature",
  "properties": {
    "addr:full":"41 Peninsula Ctr Rolling Hills Estates CA 90274",
    "addr:housenumber":"41",
    "addr:postcode":"90274",
    "addr:street":"Peninsula Ctr",
    "iso:country":"US",
    "sg:address":"41 Peninsula Ctr",
    "sg:city":"Rolling Hills Estates",
    "sg:classifiers":[
        {
            "category":"Government",
            "subcategory":"Post Office",
            "type":"Public Place"
        }
    ],
    "sg:phone":"+1 310 377 4527",
    "sg:postcode":"90274",
    "sg:province":"CA",
    "wof:name":"Penunsula Mail & Parcel",
    "wof:placetype":"venue"
},
  "geometry": {"coordinates":[-118.376324,33.775179],"type":"Point"}
}