{
  "type": "Feature",
  "properties": {
    "addr:full":"1125 Terra Nova Blvd Pacifica CA 94044",
    "addr:housenumber":"1125",
    "addr:postcode":"94044",
    "addr:street":"Terra Nova Blvd",
    "iso:country":"US",
    "sg:address":"1125 Terra Nova Blvd",
    "sg:city":"Pacifica",
    "sg:classifiers":[
        {
            "category":"Place Of Worship",
            "subcategory":"Church",
            "type":"Public Place"
        },
        {
            "category":"Place Of Worship",
            "type":"Public Place"
        }
    ],
    "sg:phone":"+1 650 355 6404",
    "sg:postcode":"94044",
    "sg:province":"CA",
    "sg:tags":[
        "churches-baptist"
    ],
    "wof:name":"New Life Christian Fellowship",
    "wof:placetype":"venue"
},
  "geometry": {"coordinates":[-122.47600300000001,37.584944],"type":"Point"}
}