{
  "type": "Feature",
  "properties": {
    "addr:full":"981 Folsom St San Francisco CA 94107",
    "addr:housenumber":"981",
    "addr:postcode":"94107",
    "addr:street":"Folsom St",
    "iso:country":"US",
    "sg:address":"981 Folsom St",
    "sg:city":"San Francisco",
    "sg:classifiers":[
        {
            "category":"Professional",
            "subcategory":"Computer Services",
            "type":"Services"
        }
    ],
    "sg:phone":"+1 415 974 1313",
    "sg:postcode":"94107",
    "sg:province":"CA",
    "sg:tags":[
        "internet"
    ],
    "wof:name":"Monkey Brain",
    "wof:placetype":"venue"
},
  "geometry": {"coordinates":[-122.40495,37.779063],"type":"Point"}
}