{
  "type": "Feature",
  "properties": {
    "iso:country":"US",
    "sg:address":"19980 E Homestead Rd",
    "sg:city":"Cupertino",
    "sg:classifiers":[
        {
            "category":"Restaurant",
            "type":"Food & Drink"
        }
    ],
    "sg:phone":"+1 408 725 0542",
    "sg:postcode":"95014",
    "sg:province":"CA",
    "sg:tags":[
        "japanese"
    ],
    "sg:website":"www.gochifusiontapas.com",
    "wof:name":"Gochi Japanese Fusion Tapas",
    "wof:placetype":"venue"
},
  "geometry": {"coordinates":[-122.02231399999999,37.336965],"type":"Point"}
}