{
  "type": "Feature",
  "properties": {
    "addr:full":"9255 Towne Centre Drive Suite 500 San Diego CA 92121",
    "addr:housenumber":"9255",
    "addr:postcode":"92121",
    "addr:street":"Towne Centre Drive Suite 500",
    "iso:country":"US",
    "sg:address":"9255 Towne Centre Drive Suite 500",
    "sg:city":"San Diego",
    "sg:classifiers":[
        {
            "category":"Social Services",
            "subcategory":"Child Care",
            "type":"Services"
        }
    ],
    "sg:phone":"+1 858 458 0042",
    "sg:postcode":"92121",
    "sg:province":"CA",
    "sg:tags":[
        "day"
    ],
    "sg:website":"www.brighthorizons.com",
    "wof:name":"Bright Horizons Family Solutions",
    "wof:placetype":"venue"
},
  "geometry": {"coordinates":[-117.207475,32.874657],"type":"Point"}
}