{
  "type": "Feature",
  "properties": {
    "addr:full":"1460 Via Monserate Fallbrook CA 92028",
    "addr:housenumber":"1460",
    "addr:postcode":"92028",
    "addr:street":"Via Monserate",
    "iso:country":"US",
    "sg:address":"1460 Via Monserate",
    "sg:city":"Fallbrook",
    "sg:classifiers":[
        {
            "category":"Shopping",
            "type":"Retail Goods"
        }
    ],
    "sg:phone":"+1 760 728 8030",
    "sg:postcode":"92028",
    "sg:province":"CA",
    "sg:tags":[
        "merchandise"
    ],
    "wof:name":"Now Is Thyme",
    "wof:placetype":"venue"
},
  "geometry": {"coordinates":[-117.225143,33.313921],"type":"Point"}
}