{
  "type": "Feature",
  "properties": {
    "addr:full":"2175 Ronald St Santa Clara CA 95050",
    "addr:housenumber":"2175",
    "addr:postcode":"95050",
    "addr:street":"Ronald St",
    "iso:country":"US",
    "sg:address":"2175 Ronald St",
    "sg:city":"Santa Clara",
    "sg:classifiers":[
        {
            "category":"Retail",
            "subcategory":"Auto Repair",
            "type":"Services"
        }
    ],
    "sg:phone":"+1 408 446 9292",
    "sg:postcode":"95050",
    "sg:province":"CA",
    "sg:tags":[
        "wrecker"
    ],
    "sg:website":"www.cupertinotowing.com",
    "wof:name":"Cupertino Towing",
    "wof:placetype":"venue"
},
  "geometry": {"coordinates":[-121.95185600000001,37.361667],"type":"Point"}
}