{
  "type": "Feature",
  "properties": {
    "addr:full":"401 E Taylor St Ste 160 San Jose CA 95112",
    "addr:housenumber":"401",
    "addr:postcode":"95112",
    "addr:street":"E Taylor St Ste 160",
    "iso:country":"US",
    "sg:address":"401 E Taylor St Ste 160",
    "sg:city":"San Jose",
    "sg:classifiers":[
        {
            "category":"Shopping",
            "subcategory":"Clothing, Apparel, & Fashions",
            "type":"Retail Goods"
        }
    ],
    "sg:phone":"+1 408 762 8624",
    "sg:postcode":"95112",
    "sg:province":"CA",
    "sg:tags":[
        "men's",
        "clothing",
        "accessory"
    ],
    "sg:website":"www.cloutonline.com",
    "wof:name":"Clout",
    "wof:placetype":"venue"
},
  "geometry": {"coordinates":[-121.89173599999999,37.353145],"type":"Point"}
}