{
  "type": "Feature",
  "properties": {
    "iso:country":"US",
    "sg:address":"124 S Auburn St",
    "sg:city":"Grass Valley",
    "sg:classifiers":[
        {
            "category":"Shopping",
            "subcategory":"Clothing, Apparel, & Fashions",
            "type":"Retail Goods"
        }
    ],
    "sg:phone":"+1 530 273 5610",
    "sg:postcode":"95945",
    "sg:province":"CA",
    "sg:tags":[
        "baby",
        "accessory"
    ],
    "wof:name":"Baby Bear Boutique",
    "wof:placetype":"venue"
},
  "geometry": {"coordinates":[-121.062043,39.218321],"type":"Point"}
}