{
  "type": "Feature",
  "properties": {
    "iso:country":"US",
    "sg:address":"41811 Albrae St",
    "sg:city":"Fremont",
    "sg:classifiers":[
        {
            "category":"Manufacturing",
            "subcategory":"Printing",
            "type":"Manufacturing & Wholesale Goods"
        }
    ],
    "sg:phone":"+1 510 656 1623",
    "sg:postcode":"94538",
    "sg:province":"CA",
    "sg:tags":[
        "printer"
    ],
    "wof:name":"PDP Copy & Print",
    "wof:placetype":"venue"
},
  "geometry": {"coordinates":[-121.974397,37.512363],"type":"Point"}
}