{
  "type": "Feature",
  "properties": {
    "addr:full":"1524 Toano Ct San Jose CA 95131",
    "addr:housenumber":"1524",
    "addr:postcode":"95131",
    "addr:street":"Toano Ct",
    "iso:country":"US",
    "sg:address":"1524 Toano Ct",
    "sg:city":"San Jose",
    "sg:classifiers":[
        {
            "category":"Manufacturing",
            "subcategory":"Electronics",
            "type":"Manufacturing & Wholesale Goods"
        }
    ],
    "sg:phone":"+1 408 254 3290",
    "sg:postcode":"95131",
    "sg:province":"CA",
    "sg:tags":[
        "equipment",
        "mfg",
        "home"
    ],
    "wof:name":"Quartermile",
    "wof:placetype":"venue"
},
  "geometry": {"coordinates":[-121.875266,37.390309],"type":"Point"}
}