{
  "type": "Feature",
  "properties": {
    "addr:full":"6170 Kinlock Ave Alta Loma CA 91737",
    "addr:postcode":"6170;91737",
    "addr:street":"Kinlock Ave",
    "iso:country":"US",
    "sg:address":"6170 Kinlock Ave",
    "sg:city":"Alta Loma",
    "sg:classifiers":[
        {
            "category":"Professional",
            "subcategory":"Business Services",
            "type":"Services"
        }
    ],
    "sg:phone":"+1 760 241 5339",
    "sg:postcode":"91737",
    "sg:province":"CA",
    "sg:website":"www.cellulargsm.com",
    "wof:name":"Leuven Co",
    "wof:placetype":"venue"
},
  "geometry": {"coordinates":[-117.582267,34.142442],"type":"Point"}
}