{
  "type": "Feature",
  "properties": {
    "addr:full":"329 Stanford Shopping Center Palo Alto CA 94304",
    "addr:housenumber":"329",
    "addr:postcode":"94304",
    "addr:street":"Stanford Shopping Center",
    "iso:country":"US",
    "sg:address":"329 Stanford Shopping Center",
    "sg:city":"Palo Alto",
    "sg:classifiers":[
        {
            "category":"Shopping",
            "subcategory":"Jewelry",
            "type":"Retail Goods"
        }
    ],
    "sg:phone":"+1 650 327 2211",
    "sg:postcode":"94304",
    "sg:province":"CA",
    "sg:tags":[
        "jeweler"
    ],
    "wof:name":"Shreve & Co",
    "wof:placetype":"venue"
},
  "geometry": {"coordinates":[-122.172387,37.444154],"type":"Point"}
}