{
  "type": "Feature",
  "properties": {
    "iso:country":"US",
    "sg:address":"4800 Legray Rd",
    "sg:city":"Arvin",
    "sg:classifiers":[
        {
            "category":"Farming",
            "subcategory":"Orchard",
            "type":"Manufacturing & Wholesale Goods"
        }
    ],
    "sg:phone":"+1 661 858 2868",
    "sg:postcode":"93203",
    "sg:province":"CA",
    "sg:tags":[
        "apple",
        "farm",
        "storage",
        "general",
        "growing",
        "cold"
    ],
    "wof:name":"Key Farm",
    "wof:placetype":"venue"
},
  "geometry": {"coordinates":[-118.914404,35.030996],"type":"Point"}
}