{
  "type": "Feature",
  "properties": {
    "iso:country":"US",
    "sg:address":"11766 Wilshire Blvd",
    "sg:city":"Los Angeles",
    "sg:classifiers":[
        {
            "category":"Manufacturing",
            "subcategory":"Printing",
            "type":"Manufacturing & Wholesale Goods"
        }
    ],
    "sg:phone":"+1 310 479 8003",
    "sg:postcode":"90025",
    "sg:province":"CA",
    "sg:tags":[
        "news",
        "periodical"
    ],
    "wof:name":"Family Money",
    "wof:placetype":"venue"
},
  "geometry": {"coordinates":[-118.462619,34.048033],"type":"Point"}
}