{
  "type": "Feature",
  "properties": {
    "iso:country":"US",
    "sg:address":"8821 Villanova Avenue",
    "sg:city":"Los Angeles",
    "sg:classifiers":[
        {
            "category":"Education",
            "subcategory":"School",
            "type":"Public Place"
        }
    ],
    "sg:phone":"+1 310 670 0480",
    "sg:postcode":"90045",
    "sg:province":"CA",
    "sg:tags":[
        "high",
        "middle",
        "elementary"
    ],
    "wof:name":"Los Angeles Unified School District",
    "wof:placetype":"venue"
},
  "geometry": {"coordinates":[-118.420566,33.958249],"type":"Point"}
}