{
  "type": "Feature",
  "properties": {
    "addr:full":"217 Las Gallinas Ave San Rafael CA 94903",
    "addr:housenumber":"217",
    "addr:postcode":"94903",
    "addr:street":"Las Gallinas Ave",
    "iso:country":"US",
    "sg:address":"217 Las Gallinas Ave",
    "sg:city":"San Rafael",
    "sg:classifiers":[
        {
            "category":"Real Estate",
            "subcategory":"Real Estate Agent",
            "type":"Services"
        }
    ],
    "sg:phone":"+1 415 479 7979",
    "sg:postcode":"94903",
    "sg:province":"CA",
    "wof:name":"West End Prorperties",
    "wof:placetype":"venue"
},
  "geometry": {"coordinates":[-122.538546,37.997591],"type":"Point"}
}