{
  "type": "Feature",
  "properties": {
    "addr:full":"655 Montague St San Leandro CA 94577",
    "addr:housenumber":"655",
    "addr:postcode":"94577",
    "addr:street":"Montague St",
    "iso:country":"US",
    "sg:address":"655 Montague St",
    "sg:city":"San Leandro",
    "sg:classifiers":[
        {
            "category":"Professional",
            "subcategory":"Engineering",
            "type":"Services"
        }
    ],
    "sg:phone":"+1 510 357 4330",
    "sg:postcode":"94577",
    "sg:province":"CA",
    "sg:tags":[
        "engineer"
    ],
    "wof:name":"G T Kuntz & Co Consulting Engn",
    "wof:placetype":"venue"
},
  "geometry": {"coordinates":[-122.154473,37.711793],"type":"Point"}
}