{
  "type": "Feature",
  "properties": {
    "addr:full":"12210 Dorsey St Waterford CA 95386",
    "addr:housenumber":"12210",
    "addr:postcode":"95386",
    "addr:street":"Dorsey St",
    "iso:country":"US",
    "sg:address":"12210 Dorsey St",
    "sg:city":"Waterford",
    "sg:classifiers":[
        {
            "category":"Building & Trades",
            "subcategory":"Plumbing",
            "type":"Services"
        }
    ],
    "sg:phone":"+1 209 874 4773",
    "sg:postcode":"95386",
    "sg:province":"CA",
    "sg:tags":[
        "contractor"
    ],
    "wof:name":"Allstars Heating and Coolg Svc",
    "wof:placetype":"venue"
},
  "geometry": {"coordinates":[-120.76548699999999,37.641388],"type":"Point"}
}