{
  "type": "Feature",
  "properties": {
    "addr:full":"29661 Ave de Las Banderas Rancho Santa Margarita CA 92688",
    "addr:housenumber":"29661",
    "addr:postcode":"92688",
    "addr:street":"Ave De Las Banderas",
    "iso:country":"US",
    "sg:address":"29661 Ave de Las Banderas",
    "sg:city":"Rancho Santa Margarita",
    "sg:classifiers":[
        {
            "category":"Education",
            "subcategory":"School",
            "type":"Public Place"
        }
    ],
    "sg:phone":"+1 949 589 6960",
    "sg:postcode":"92688",
    "sg:province":"CA",
    "wof:name":"Rancho Santa Margarita Arroyo",
    "wof:placetype":"venue"
},
  "geometry": {"coordinates":[-117.61245599999999,33.625315],"type":"Point"}
}