{
  "type": "Feature",
  "properties": {
    "addr:full":"1019 1/2 Alameda de las Pulgas Belmont CA 94002",
    "addr:housenumber":"1019 1 / 2",
    "addr:postcode":"94002",
    "addr:street":"Alameda De Las Pulgas",
    "iso:country":"US",
    "sg:address":"1019 1/2 Alameda de las Pulgas",
    "sg:city":"Belmont",
    "sg:classifiers":[
        {
            "category":"Personal",
            "subcategory":"Beauty Salon",
            "type":"Services"
        },
        {
            "category":"Shopping",
            "subcategory":"Beauty & Cosmetics",
            "type":"Retail Goods"
        }
    ],
    "sg:phone":"+1 650 802 8531",
    "sg:postcode":"94002",
    "sg:province":"CA",
    "sg:tags":[
        "hair",
        "supply"
    ],
    "sg:website":"www.beautiquebeautybar.com",
    "wof:name":"Beautique Beauty Bar",
    "wof:placetype":"venue"
},
  "geometry": {"coordinates":[-122.294212,37.511927],"type":"Point"}
}