{
  "type": "Feature",
  "properties": {
    "iso:country":"US",
    "sg:address":"2995 Van Buren Blvd",
    "sg:city":"Riverside",
    "sg:classifiers":[
        {
            "category":"Shopping",
            "subcategory":"Clothing, Apparel, & Fashions",
            "type":"Retail Goods"
        }
    ],
    "sg:phone":"+1 951 354 6821",
    "sg:postcode":"92503",
    "sg:province":"CA",
    "wof:name":"Cydney Blu & Co",
    "wof:placetype":"venue"
},
  "geometry": {"coordinates":[-117.437127,33.908831],"type":"Point"}
}