{
  "type": "Feature",
  "properties": {
    "addr:full":"3830 Watt Ave Ste 3 Sacramento CA 95821",
    "addr:housenumber":"3830",
    "addr:postcode":"95821",
    "addr:street":"Watt Ave Ste 3",
    "iso:country":"US",
    "sg:address":"3830 Watt Ave Ste 3",
    "sg:city":"Sacramento",
    "sg:classifiers":[
        {
            "category":"Insurance",
            "subcategory":"Insurance Agent",
            "type":"Services"
        },
        {
            "category":"Insurance",
            "subcategory":"Hazard Insurance",
            "type":"Services"
        },
        {
            "category":"Insurance",
            "subcategory":"Title Insurance",
            "type":"Services"
        },
        {
            "category":"Insurance",
            "subcategory":"Health Insurance",
            "type":"Services"
        }
    ],
    "sg:phone":"+1 916 488 4426",
    "sg:postcode":"95821",
    "sg:province":"CA",
    "sg:tags":[
        "business",
        "auto",
        "commercial",
        "homeowner",
        "benefit",
        "employee"
    ],
    "sg:website":"ccisca.com",
    "wof:name":"Cliff Cottam Insurance Services",
    "wof:placetype":"venue"
},
  "geometry": {"coordinates":[-121.38225300000001,38.635326],"type":"Point"}
}