{
  "type": "Feature",
  "properties": {
    "addr:full":"332 del Amo Fashion Sq Torrance CA 90503",
    "addr:housenumber":"332",
    "addr:postcode":"90503",
    "addr:street":"Del Amo Fashion Sq",
    "iso:country":"US",
    "sg:address":"332 del Amo Fashion Sq",
    "sg:city":"Torrance",
    "sg:classifiers":[
        {
            "category":"Utilities",
            "subcategory":"Mobile Phone",
            "type":"Services"
        }
    ],
    "sg:phone":"+1 310 370 0531",
    "sg:postcode":"90503",
    "sg:province":"CA",
    "sg:tags":[
        "telephone",
        "cellular"
    ],
    "wof:name":"Cingular Wireless",
    "wof:placetype":"venue"
},
  "geometry": {"coordinates":[-118.35141299999999,33.82837],"type":"Point"}
}