{
  "type": "Feature",
  "properties": {
    "iso:country":"US",
    "sg:address":"1629 Hopkins Street",
    "sg:city":"Berkeley",
    "sg:classifiers":[
        {
            "category":"Personal",
            "type":"Services"
        }
    ],
    "sg:phone":"+1 510 524 0794",
    "sg:postcode":"94707",
    "sg:province":"CA",
    "sg:tags":[
        "sewing",
        "alteration"
    ],
    "wof:name":"Blue Rose Tailor Shoppe",
    "wof:placetype":"venue"
},
  "geometry": {"coordinates":[-122.280998,37.882198],"type":"Point"}
}