{
  "type": "Feature",
  "properties": {
    "iso:country":"US",
    "sg:address":"100 Civic Plz",
    "sg:city":"Dublin",
    "sg:classifiers":[
        {
            "category":"Government",
            "subcategory":"Office",
            "type":"Public Place"
        }
    ],
    "sg:phone":"+1 925 833 6600",
    "sg:postcode":"94568",
    "sg:province":"CA",
    "sg:tags":[
        "village"
    ],
    "wof:name":"Dublin City General Info",
    "wof:placetype":"venue"
},
  "geometry": {"coordinates":[-121.91718,37.703686],"type":"Point"}
}