{
  "type": "Feature",
  "properties": {
    "addr:full":"7007 Friars Rd Ste 321 San Diego CA 92108",
    "addr:housenumber":"7007",
    "addr:postcode":"92108",
    "addr:street":"Friars Rd Ste 321",
    "iso:country":"US",
    "sg:address":"7007 Friars Rd Ste 321",
    "sg:city":"San Diego",
    "sg:classifiers":[
        {
            "category":"Shopping",
            "subcategory":"Bicycles & Sporting Goods",
            "type":"Retail Goods"
        },
        {
            "category":"Sports & Exercise",
            "subcategory":"Bicycle Rental",
            "type":"Entertainment"
        }
    ],
    "sg:phone":"+1 619 299 3749",
    "sg:postcode":"92108",
    "sg:province":"CA",
    "sg:tags":[
        "outdoor",
        "gear",
        "wear"
    ],
    "wof:name":"The Backshop @ Fashion Valley",
    "wof:placetype":"venue"
},
  "geometry": {"coordinates":[-117.16936,32.769451],"type":"Point"}
}