{
  "type": "Feature",
  "properties": {
    "iso:country":"US",
    "sg:address":"11400 W Olympic Blvd",
    "sg:city":"Los Angeles",
    "sg:classifiers":[
        {
            "category":"Travel",
            "subcategory":"Travel Agent",
            "type":"Entertainment"
        }
    ],
    "sg:phone":"+1 310 954 2500",
    "sg:postcode":"90064",
    "sg:province":"CA",
    "sg:tags":[
        "agency",
        "bureau"
    ],
    "wof:name":"Northstar Travel Media",
    "wof:placetype":"venue"
},
  "geometry": {"coordinates":[-118.444074,34.036502],"type":"Point"}
}