{
  "type": "Feature",
  "properties": {
    "addr:full":"8393 Foothill Blvd Rancho Cucamonga CA 91730",
    "addr:housenumber":"8393",
    "addr:postcode":"91730",
    "addr:street":"Foothill Blvd",
    "iso:country":"US",
    "sg:address":"8393 Foothill Blvd",
    "sg:city":"Rancho Cucamonga",
    "sg:classifiers":[
        {
            "category":"Retail",
            "subcategory":"Auto Repair",
            "type":"Services"
        }
    ],
    "sg:phone":"+1 909 981 4622",
    "sg:postcode":"91730",
    "sg:province":"CA",
    "sg:tags":[
        "repairing",
        "automobile"
    ],
    "wof:name":"Auto Specialists",
    "wof:placetype":"venue"
},
  "geometry": {"coordinates":[-117.62042099999999,34.104753],"type":"Point"}
}