{
  "type": "Feature",
  "properties": {
    "iso:country":"US",
    "sg:address":"3000 Citrus Cir",
    "sg:city":"Walnut Creek",
    "sg:classifiers":[
        {
            "category":"Professional",
            "subcategory":"Accounting & Tax Preparation",
            "type":"Services"
        }
    ],
    "sg:phone":"+1 925 934 6320",
    "sg:postcode":"94598",
    "sg:province":"CA",
    "sg:tags":[
        "accountant"
    ],
    "sg:website":"www.rexcrandell.com",
    "wof:name":"Crandell",
    "wof:placetype":"venue"
},
  "geometry": {"coordinates":[-122.01430999999999,37.930091],"type":"Point"}
}