{
  "type": "Feature",
  "properties": {
    "addr:full":"1551 Colorado Boulevard Los Angeles CA 90041",
    "addr:housenumber":"1551",
    "addr:postcode":"90041",
    "addr:street":"Colorado Boulevard",
    "iso:country":"US",
    "sg:address":"1551 Colorado Boulevard",
    "sg:city":"Los Angeles",
    "sg:classifiers":[
        {
            "category":"Personal",
            "subcategory":"Barber",
            "type":"Services"
        }
    ],
    "sg:phone":"+1 323 255 4781",
    "sg:postcode":"90041",
    "sg:province":"CA",
    "wof:name":"Hair Matters",
    "wof:placetype":"venue"
},
  "geometry": {"coordinates":[-118.199804,34.139561],"type":"Point"}
}