{
  "type": "Feature",
  "properties": {
    "iso:country":"US",
    "sg:address":"2940 N Naomi St",
    "sg:city":"Burbank",
    "sg:classifiers":[
        {
            "category":"Professional",
            "type":"Services"
        }
    ],
    "sg:phone":"+1 818 562 5700",
    "sg:postcode":"91504",
    "sg:province":"CA",
    "sg:tags":[
        "processing",
        "data"
    ],
    "wof:name":"Cyber F/X Inc",
    "wof:placetype":"venue"
},
  "geometry": {"coordinates":[-118.339957,34.205733],"type":"Point"}
}