{
  "type": "Feature",
  "properties": {
    "addr:full":"14455 Ramona Blvd Baldwin Park CA 91706",
    "addr:housenumber":"14455",
    "addr:postcode":"91706",
    "addr:street":"Ramona Blvd",
    "iso:country":"US",
    "sg:address":"14455 Ramona Blvd",
    "sg:city":"Baldwin Park",
    "sg:classifiers":[
        {
            "category":"Restaurant",
            "type":"Food & Drink"
        }
    ],
    "sg:menulink":"http://www.allmenus.com/ca/east-san-gabriel-valley/168916-el-pollo-loco/menu/",
    "sg:phone":"+1 626 960 8861",
    "sg:postcode":"91706",
    "sg:province":"CA",
    "sg:tags":[
        "american",
        "mexican",
        "tex-mex"
    ],
    "wof:name":"El Pollo Loco",
    "wof:placetype":"venue"
},
  "geometry": {"coordinates":[-117.959079,34.087154],"type":"Point"}
}