{
  "type": "Feature",
  "properties": {
    "addr:full":"7715 Santa Fe Ave Huntington Park CA 90255",
    "addr:housenumber":"7715",
    "addr:postcode":"90255",
    "addr:street":"Santa Fe Ave;Park",
    "iso:country":"US",
    "sg:address":"7715 Santa Fe Ave",
    "sg:city":"Huntington Park",
    "sg:classifiers":[
        {
            "category":"Autos & Motor Vehicles",
            "subcategory":"Auto Supplies",
            "type":"Retail Goods"
        }
    ],
    "sg:phone":"+1 323 587 7730",
    "sg:postcode":"90255",
    "sg:province":"CA",
    "sg:tags":[
        "automotive",
        "part",
        "repair"
    ],
    "wof:name":"Pacific Independence",
    "wof:placetype":"venue"
},
  "geometry": {"coordinates":[-118.230203,33.969576],"type":"Point"}
}