{
  "type": "Feature",
  "properties": {
    "addr:full":"10920 Pluma Ct Rancho Cordova CA 95670",
    "addr:housenumber":"10920",
    "addr:postcode":"95670",
    "addr:street":"Pluma Ct",
    "iso:country":"US",
    "sg:address":"10920 Pluma Ct",
    "sg:city":"Rancho Cordova",
    "sg:classifiers":[
        {
            "category":"Building & Trades",
            "subcategory":"Construction",
            "type":"Services"
        }
    ],
    "sg:phone":"+1 916 635 7164",
    "sg:postcode":"95670",
    "sg:province":"CA",
    "sg:tags":[
        "concrete",
        "pumping"
    ],
    "wof:name":"Gray's Concrete Pumping",
    "wof:placetype":"venue"
},
  "geometry": {"coordinates":[-121.280007,38.613491],"type":"Point"}
}