{
  "type": "Feature",
  "properties": {
    "addr:full":"4804 Laurel Canyon Blvd Valley Village CA 91607",
    "addr:housenumber":"4804",
    "addr:postcode":"91607",
    "addr:street":"Laurel Canyon Blvd",
    "iso:country":"US",
    "sg:address":"4804 Laurel Canyon Blvd",
    "sg:city":"Valley Village",
    "sg:classifiers":[
        {
            "category":"Professional",
            "subcategory":"Advertising",
            "type":"Services"
        }
    ],
    "sg:phone":"+1 818 755 5020",
    "sg:postcode":"91607",
    "sg:province":"CA",
    "sg:tags":[
        "counselor"
    ],
    "wof:name":"Mediabuys LLC",
    "wof:placetype":"venue"
},
  "geometry": {"coordinates":[-118.396411,34.158445],"type":"Point"}
}