{
  "type": "Feature",
  "properties": {
    "iso:country":"US",
    "sg:address":"208 Hillard St",
    "sg:city":"Taft",
    "sg:classifiers":[
        {
            "category":"Farming",
            "subcategory":"Farm & Veterinary Services",
            "type":"Manufacturing & Wholesale Goods"
        }
    ],
    "sg:phone":"+1 661 765 2687",
    "sg:postcode":"93268",
    "sg:province":"CA",
    "sg:tags":[
        "protection",
        "aerial",
        "applicator",
        "crop"
    ],
    "wof:name":"Cornerstone AG Aviation",
    "wof:placetype":"venue"
},
  "geometry": {"coordinates":[-119.47402,35.13928],"type":"Point"}
}