{
  "type": "Feature",
  "properties": {
    "iso:country":"US",
    "sg:address":"1820 Industrial St",
    "sg:city":"Los Angeles",
    "sg:postcode":"90021",
    "sg:province":"CA",
    "wof:name":"Daily Dose Cafe",
    "wof:placetype":"venue"
},
  "geometry": {"coordinates":[-118.23398400000001,34.035797],"type":"Point"}
}