{
  "type": "Feature",
  "properties": {
    "addr:full":"1512 Eureka Rd Roseville CA 95661",
    "addr:housenumber":"1512",
    "addr:postcode":"95661",
    "addr:street":"Eureka Rd",
    "iso:country":"US",
    "sg:address":"1512 Eureka Rd",
    "sg:city":"Roseville",
    "sg:classifiers":[
        {
            "category":"Banks & Credit Unions",
            "subcategory":"Bank",
            "type":"Services"
        }
    ],
    "sg:phone":"+1 916 677 2727",
    "sg:postcode":"95661",
    "sg:province":"CA",
    "sg:tags":[
        "loan",
        "real estate"
    ],
    "wof:name":"Paradise Financial",
    "wof:placetype":"venue"
},
  "geometry": {"coordinates":[-121.251571,38.751937],"type":"Point"}
}