{
  "type": "Feature",
  "properties": {
    "iso:country":"US",
    "sg:address":"3200 N Sepulveda Boulevard Ofc",
    "sg:city":"Manhattan Beach",
    "sg:classifiers":[
        {
            "category":"Personal",
            "subcategory":"Nail Salon",
            "type":"Services"
        }
    ],
    "sg:phone":"+1 310 796 8986",
    "sg:postcode":"90266",
    "sg:province":"CA",
    "wof:name":"Nails by Nancy",
    "wof:placetype":"venue"
},
  "geometry": {"coordinates":[-118.395914,33.898434],"type":"Point"}
}