{
  "type": "Feature",
  "properties": {
    "iso:country":"US",
    "sg:address":"3210 Glendale Blvd",
    "sg:city":"Los Angeles",
    "sg:classifiers":[
        {
            "category":"Bars & Pubs",
            "type":"Food & Drink"
        }
    ],
    "sg:phone":"+1 323 669 9631",
    "sg:postcode":"90039",
    "sg:province":"CA",
    "sg:tags":[
        "lounge",
        "diva",
        "cocktail"
    ],
    "wof:name":"Club Tee Gee",
    "wof:placetype":"venue"
},
  "geometry": {"coordinates":[-118.260876,34.117801],"type":"Point"}
}