{
  "type": "Feature",
  "properties": {
    "addr:full":"689 Bauer Pl Vista CA 92081",
    "addr:housenumber":"689",
    "addr:postcode":"92081",
    "addr:street":"Bauer Pl",
    "iso:country":"US",
    "sg:address":"689 Bauer Pl",
    "sg:city":"Vista",
    "sg:classifiers":[
        {
            "category":"Retail",
            "subcategory":"Auto Repair",
            "type":"Services"
        }
    ],
    "sg:phone":"+1 760 945 7173",
    "sg:postcode":"92081",
    "sg:province":"CA",
    "sg:tags":[
        "automobile",
        "top",
        "upholstery"
    ],
    "wof:name":"H & A Svc",
    "wof:placetype":"venue"
},
  "geometry": {"coordinates":[-117.261056,33.187965],"type":"Point"}
}