{
  "type": "Feature",
  "properties": {
    "addr:full":"980 9th St # 16 16th Fl Sacramento CA 95814",
    "addr:housenumber":"980;16",
    "addr:postcode":"95814",
    "addr:street":"9Th St #;16Th Fl",
    "iso:country":"US",
    "sg:address":"980 9th St # 16 16th Fl",
    "sg:city":"Sacramento",
    "sg:classifiers":[
        {
            "category":"Professional",
            "subcategory":"Lawyer & Legal Services",
            "type":"Services"
        }
    ],
    "sg:phone":"+1 916 449 9910",
    "sg:postcode":"95814",
    "sg:province":"CA",
    "sg:tags":[
        "litigation",
        "personal",
        "injury"
    ],
    "sg:website":"www.crowelllawoffices.com",
    "wof:name":"The Choyce Law Firm",
    "wof:placetype":"venue"
},
  "geometry": {"coordinates":[-121.494691,38.580966],"type":"Point"}
}