{
  "type": "Feature",
  "properties": {
    "addr:full":"1945 Front St Oceano CA 93445",
    "addr:housenumber":"1945",
    "addr:postcode":"93445",
    "addr:street":"Front St",
    "iso:country":"US",
    "sg:address":"1945 Front St",
    "sg:city":"Oceano",
    "sg:classifiers":[
        {
            "category":"Recreation",
            "type":"Entertainment"
        }
    ],
    "sg:phone":"+1 805 473 3066",
    "sg:postcode":"93445",
    "sg:province":"CA",
    "sg:tags":[
        "parlor",
        "billiard"
    ],
    "wof:name":"Carambola Amigo",
    "wof:placetype":"venue"
},
  "geometry": {"coordinates":[-120.610113,35.099219],"type":"Point"}
}