{
  "type": "Feature",
  "properties": {
    "iso:country":"US",
    "sg:address":"2065 Martin Ave",
    "sg:city":"Santa Clara",
    "sg:classifiers":[
        {
            "category":"Wholesale",
            "subcategory":"Electrical",
            "type":"Manufacturing & Wholesale Goods"
        }
    ],
    "sg:phone":"+1 408 855 1055",
    "sg:postcode":"95050",
    "sg:province":"CA",
    "sg:tags":[
        "semiconductor"
    ],
    "wof:name":"Suss Microtech",
    "wof:placetype":"venue"
},
  "geometry": {"coordinates":[-121.96110400000001,37.366315],"type":"Point"}
}