{
  "type": "Feature",
  "properties": {
    "iso:country":"US",
    "sg:address":"3801 Pacific Coast Hwy",
    "sg:city":"Torrance",
    "sg:classifiers":[
        {
            "category":"Food & Beverages",
            "subcategory":"Groceries & Convenience Stores",
            "type":"Retail Goods"
        }
    ],
    "sg:phone":"+1 310 375 5597",
    "sg:postcode":"90505",
    "sg:province":"CA",
    "sg:tags":[
        "market"
    ],
    "wof:name":"Super 3",
    "wof:placetype":"venue"
},
  "geometry": {"coordinates":[-118.35386,33.806143],"type":"Point"}
}