{
  "type": "Feature",
  "properties": {
    "iso:country":"US",
    "sg:address":"1281 Westwood Blvd",
    "sg:city":"Los Angeles",
    "sg:classifiers":[
        {
            "category":"Banks & Credit Unions",
            "subcategory":"Bank",
            "type":"Services"
        }
    ],
    "sg:phone":"+1 310 473 4995",
    "sg:postcode":"90024",
    "sg:province":"CA",
    "sg:tags":[
        "loan",
        "real estate"
    ],
    "wof:name":"Phoenix Mortgage Corp",
    "wof:placetype":"venue"
},
  "geometry": {"coordinates":[-118.443072,34.057475],"type":"Point"}
}