{
  "type": "Feature",
  "properties": {
    "iso:country":"US",
    "sg:address":"1309 S Eastern Ave",
    "sg:city":"Los Angeles",
    "sg:classifiers":[
        {
            "category":"Government",
            "subcategory":"Post Office",
            "type":"Public Place"
        }
    ],
    "sg:phone":"+1 323 586 1467",
    "sg:postcode":"90040",
    "sg:province":"CA",
    "sg:tags":[
        "postal",
        "us"
    ],
    "wof:name":"US Post Office",
    "wof:placetype":"venue"
},
  "geometry": {"coordinates":[-118.173993,34.015718],"type":"Point"}
}