{
  "type": "Feature",
  "properties": {
    "iso:country":"US",
    "sg:address":"18189 Valley Blvd",
    "sg:city":"Bloomington",
    "sg:classifiers":[
        {
            "category":"Building & Trades",
            "subcategory":"Construction",
            "type":"Services"
        }
    ],
    "sg:phone":"+1 909 873 0435",
    "sg:postcode":"92316",
    "sg:province":"CA",
    "sg:tags":[
        "floor",
        "laying",
        "contractor"
    ],
    "wof:name":"Flooring 2000",
    "wof:placetype":"venue"
},
  "geometry": {"coordinates":[-117.408652,34.070369],"type":"Point"}
}