{
  "type": "Feature",
  "properties": {
    "addr:full":"414 Brannan St San Francisco CA 94107",
    "addr:housenumber":"414",
    "addr:postcode":"94107",
    "addr:street":"Brannan St",
    "iso:country":"US",
    "sg:address":"414 Brannan St",
    "sg:city":"San Francisco",
    "sg:classifiers":[
        {
            "category":"Building & Trades",
            "subcategory":"Electrical",
            "type":"Services"
        }
    ],
    "sg:phone":"+1 415 597 4700",
    "sg:postcode":"94107",
    "sg:province":"CA",
    "sg:tags":[
        "electric",
        "contractor"
    ],
    "sg:website":"www.dynalectric-sf.com",
    "wof:name":"Dynalectric Co",
    "wof:placetype":"venue"
},
  "geometry": {"coordinates":[-122.394594,37.780015],"type":"Point"}
}