{
  "type": "Feature",
  "properties": {
    "addr:full":"979 Avenida Pico San Clemente CA 92673",
    "addr:housenumber":"979",
    "addr:postcode":"92673",
    "addr:street":"Avenida Pico",
    "iso:country":"US",
    "sg:address":"979 Avenida Pico",
    "sg:city":"San Clemente",
    "sg:classifiers":[
        {
            "category":"Cafe",
            "type":"Food & Drink"
        }
    ],
    "sg:menulink":"http://www.allmenus.com/ca/south-coast/62412-daphnes-greek-cafe/menu/",
    "sg:phone":"+1 949 369 4611",
    "sg:postcode":"92673",
    "sg:province":"CA",
    "sg:tags":[
        "greek"
    ],
    "wof:name":"Daphne's Greek Cafe",
    "wof:placetype":"venue"
},
  "geometry": {"coordinates":[-117.605987,33.453366],"type":"Point"}
}