{
  "type": "Feature",
  "properties": {
    "addr:full":"21551 Brookhurst St Huntington Beach CA 92646",
    "addr:housenumber":"21551",
    "addr:postcode":"92646",
    "addr:street":"Brookhurst St",
    "iso:country":"US",
    "sg:address":"21551 Brookhurst St",
    "sg:city":"Huntington Beach",
    "sg:classifiers":[
        {
            "category":"Wholesale",
            "subcategory":"Groceries",
            "type":"Manufacturing & Wholesale Goods"
        }
    ],
    "sg:phone":"+1 714 642 1749",
    "sg:postcode":"92646",
    "sg:province":"CA",
    "wof:name":"Essence of Espresso",
    "wof:placetype":"venue"
},
  "geometry": {"coordinates":[-117.95357199999999,33.649459],"type":"Point"}
}