{
  "type": "Feature",
  "properties": {
    "addr:full":"1341 Rosecrans St San Diego CA 92106",
    "addr:housenumber":"1341",
    "addr:postcode":"92106",
    "addr:street":"Rosecrans St",
    "iso:country":"US",
    "sg:address":"1341 Rosecrans St",
    "sg:city":"San Diego",
    "sg:classifiers":[
        {
            "category":"Education",
            "subcategory":"College",
            "type":"Public Place"
        }
    ],
    "sg:phone":"+1 619 224 4444",
    "sg:postcode":"92106",
    "sg:province":"CA",
    "sg:tags":[
        "academic",
        "school"
    ],
    "wof:name":"Scandinavian-American Inst",
    "wof:placetype":"venue"
},
  "geometry": {"coordinates":[-117.228883,32.724863],"type":"Point"}
}