{
  "type": "Feature",
  "properties": {
    "iso:country":"US",
    "sg:address":"721 N Crescent Dr",
    "sg:city":"Beverly Hills",
    "sg:classifiers":[
        {
            "category":"Professional",
            "type":"Services"
        }
    ],
    "sg:phone":"+1 310 273 4140",
    "sg:postcode":"90210",
    "sg:province":"CA",
    "wof:name":"Minoco 1980 Iplc Oil and Gas",
    "wof:placetype":"venue"
},
  "geometry": {"coordinates":[-118.408925,34.080432],"type":"Point"}
}