{
  "type": "Feature",
  "properties": {
    "iso:country":"US",
    "sg:address":"118 E F St",
    "sg:city":"Tehachapi",
    "sg:classifiers":[
        {
            "category":"Retail",
            "subcategory":"Laundry & Dry Cleaning",
            "type":"Services"
        }
    ],
    "sg:phone":"+1 661 822 3565",
    "sg:postcode":"93561",
    "sg:province":"CA",
    "sg:tags":[
        "laundries-self",
        "operated",
        "washer",
        "dryer",
        "coin"
    ],
    "wof:name":"The Wash Tub",
    "wof:placetype":"venue"
},
  "geometry": {"coordinates":[-118.44745399999999,35.130972],"type":"Point"}
}