{
  "type": "Feature",
  "properties": {
    "iso:country":"US",
    "sg:address":"3691 Noakes St",
    "sg:city":"Los Angeles",
    "sg:classifiers":[
        {
            "category":"Professional",
            "subcategory":"Advertising",
            "type":"Services"
        }
    ],
    "sg:phone":"+1 323 269 8175",
    "sg:postcode":"90023",
    "sg:province":"CA",
    "sg:tags":[
        "distribution"
    ],
    "wof:name":"ADM Distribution",
    "wof:placetype":"venue"
},
  "geometry": {"coordinates":[-118.19683000000001,34.014279],"type":"Point"}
}