{
  "type": "Feature",
  "properties": {
    "addr:full":"2376 Senter Road San Jose CA 95112",
    "addr:housenumber":"2376",
    "addr:postcode":"95112",
    "addr:street":"Senter Road",
    "iso:country":"US",
    "sg:address":"2376 Senter Road",
    "sg:city":"San Jose",
    "sg:classifiers":[
        {
            "category":"Restaurant",
            "type":"Food & Drink"
        }
    ],
    "sg:phone":"+1 408 293 5857",
    "sg:postcode":"95112",
    "sg:province":"CA",
    "wof:name":"Pho Nui Restaurant",
    "wof:placetype":"venue"
},
  "geometry": {"coordinates":[-121.848178,37.30834],"type":"Point"}
}