{
  "type": "Feature",
  "properties": {
    "addr:full":"11132 Winners Cir Los Alamitos CA 90720",
    "addr:housenumber":"11132",
    "addr:postcode":"90720",
    "addr:street":"Winners Cir",
    "iso:country":"US",
    "sg:address":"11132 Winners Cir",
    "sg:city":"Los Alamitos",
    "sg:classifiers":[
        {
            "category":"Banks & Credit Unions",
            "subcategory":"Financial Services",
            "type":"Services"
        }
    ],
    "sg:phone":"+1 562 799 2000",
    "sg:postcode":"90720",
    "sg:province":"CA",
    "sg:tags":[
        "broker",
        "mortgage"
    ],
    "wof:name":"Countrywide Financial",
    "wof:placetype":"venue"
},
  "geometry": {"coordinates":[-118.041,33.801701],"type":"Point"}
}