{
  "type": "Feature",
  "properties": {
    "addr:full":"2912 Broad St Newport Beach CA 92663",
    "addr:housenumber":"2912",
    "addr:postcode":"92663",
    "addr:street":"Broad St",
    "iso:country":"US",
    "sg:address":"2912 Broad St",
    "sg:city":"Newport Beach",
    "sg:classifiers":[
        {
            "category":"Professional",
            "type":"Services"
        }
    ],
    "sg:phone":"+1 949 548 7193",
    "sg:postcode":"92663",
    "sg:province":"CA",
    "wof:name":"Northdome LLC",
    "wof:placetype":"venue"
},
  "geometry": {"coordinates":[-117.92287399999999,33.62536],"type":"Point"}
}