{
  "type": "Feature",
  "properties": {
    "addr:full":"401 N Beverly Drive Beverly Hills CA 90210",
    "addr:housenumber":"401",
    "addr:postcode":"90210",
    "addr:street":"N Beverly Drive",
    "iso:country":"US",
    "sg:address":"401 N Beverly Drive",
    "sg:city":"Beverly Hills",
    "sg:classifiers":[
        {
            "category":"Shopping",
            "subcategory":"Clothing, Apparel, & Fashions",
            "type":"Retail Goods"
        }
    ],
    "sg:phone":"+1 310 858 0204",
    "sg:postcode":"90210",
    "sg:province":"CA",
    "sg:tags":[
        "accessory",
        "clothing",
        "women's"
    ],
    "wof:name":"Club Monacco International.",
    "wof:placetype":"venue"
},
  "geometry": {"coordinates":[-118.40216599999999,34.070006],"type":"Point"}
}