{
  "type": "Feature",
  "properties": {
    "iso:country":"US",
    "sg:address":"45571 Industrial Pl",
    "sg:city":"Fremont",
    "sg:classifiers":[
        {
            "category":"Wholesale",
            "subcategory":"Machinery & Supplies",
            "type":"Manufacturing & Wholesale Goods"
        }
    ],
    "sg:phone":"+1 510 651 5771",
    "sg:postcode":"94538",
    "sg:province":"CA",
    "sg:tags":[
        "sprinkler"
    ],
    "wof:name":"Driggs & Wood Inc",
    "wof:placetype":"venue"
},
  "geometry": {"coordinates":[-121.950409,37.496715],"type":"Point"}
}