{
  "type": "Feature",
  "properties": {
    "iso:country":"US",
    "sg:address":"3322 W Victory Blvd",
    "sg:city":"Burbank",
    "sg:classifiers":[
        {
            "category":"Professional",
            "subcategory":"Lawyer & Legal Services",
            "type":"Services"
        }
    ],
    "sg:phone":"+1 818 843 1788",
    "sg:postcode":"91505",
    "sg:province":"CA",
    "wof:name":"Wilson Dennis Law Offices of",
    "wof:placetype":"venue"
},
  "geometry": {"coordinates":[-118.347165,34.184577],"type":"Point"}
}