{
  "type": "Feature",
  "properties": {
    "addr:full":"3625 Loma Way San Diego CA 92106",
    "addr:housenumber":"3625",
    "addr:postcode":"92106",
    "addr:street":"Loma Way",
    "iso:country":"US",
    "sg:address":"3625 Loma Way",
    "sg:city":"San Diego",
    "sg:classifiers":[
        {
            "category":"Manufacturing",
            "subcategory":"Printing",
            "type":"Manufacturing & Wholesale Goods"
        }
    ],
    "sg:phone":"+1 619 224 0919",
    "sg:postcode":"92106",
    "sg:province":"CA",
    "sg:tags":[
        "commercial"
    ],
    "wof:name":"Julies Silk Screening",
    "wof:placetype":"venue"
},
  "geometry": {"coordinates":[-117.24378400000001,32.723305],"type":"Point"}
}