{
  "type": "Feature",
  "properties": {
    "iso:country":"US",
    "sg:address":"1115 Fee Dr",
    "sg:city":"Sacramento",
    "sg:classifiers":[
        {
            "category":"Autos & Motor Vehicles",
            "subcategory":"Motorcycle Sales",
            "type":"Retail Goods"
        }
    ],
    "sg:phone":"+1 916 927 2453",
    "sg:postcode":"95815",
    "sg:province":"CA",
    "sg:website":"www.marquiscustomcycles.com",
    "wof:name":"Marquis Custom Cycles",
    "wof:placetype":"venue"
},
  "geometry": {"coordinates":[-121.441255,38.600836],"type":"Point"}
}