{
  "type": "Feature",
  "properties": {
    "iso:country":"US",
    "sg:address":"970 W Foothill Blvd",
    "sg:city":"Azusa",
    "sg:classifiers":[
        {
            "category":"Manufacturing",
            "subcategory":"Building Materials",
            "type":"Manufacturing & Wholesale Goods"
        }
    ],
    "sg:phone":"+1 626 633 0888",
    "sg:postcode":"91702",
    "sg:province":"CA",
    "sg:tags":[
        "door"
    ],
    "sg:website":"www.qsmdoors.com",
    "wof:name":"QSM Enterprise",
    "wof:placetype":"venue"
},
  "geometry": {"coordinates":[-117.92019000000001,34.133693],"type":"Point"}
}