{
  "type": "Feature",
  "properties": {
    "addr:full":"22619 Pacific Coast Hwy Malibu CA 90265",
    "addr:housenumber":"22619",
    "addr:postcode":"90265",
    "addr:street":"Pacific Coast Hwy",
    "iso:country":"US",
    "sg:address":"22619 Pacific Coast Hwy",
    "sg:city":"Malibu",
    "sg:classifiers":[
        {
            "category":"Manufacturing",
            "subcategory":"Toys & Sporting Goods",
            "type":"Manufacturing & Wholesale Goods"
        }
    ],
    "sg:phone":"+1 310 456 7799",
    "sg:postcode":"90265",
    "sg:province":"CA",
    "sg:tags":[
        "mfg"
    ],
    "wof:name":"FLYING COLORS TOYS",
    "wof:placetype":"venue"
},
  "geometry": {"coordinates":[-118.668421,34.039576],"type":"Point"}
}