{
  "type": "Feature",
  "properties": {
    "iso:country":"US",
    "sg:address":"7559 Vineland Ave",
    "sg:city":"Sun Valley",
    "sg:classifiers":[
        {
            "category":"Autos & Motor Vehicles",
            "subcategory":"Automobile Sales",
            "type":"Retail Goods"
        }
    ],
    "sg:phone":"+1 818 255 0905",
    "sg:postcode":"91352",
    "sg:province":"CA",
    "sg:tags":[
        "car",
        "dealer"
    ],
    "wof:name":"Lucky Motors",
    "wof:placetype":"venue"
},
  "geometry": {"coordinates":[-118.370396,34.207365],"type":"Point"}
}