{
  "type": "Feature",
  "properties": {
    "addr:full":"3177 Turner St Placerville CA 95667",
    "addr:housenumber":"3177",
    "addr:postcode":"95667",
    "addr:street":"Turner St",
    "iso:country":"US",
    "sg:address":"3177 Turner St",
    "sg:city":"Placerville",
    "sg:classifiers":[
        {
            "category":"Health Services",
            "subcategory":"Doctor",
            "type":"Services"
        }
    ],
    "sg:phone":"+1 530 622 5054",
    "sg:postcode":"95667",
    "sg:province":"CA",
    "sg:tags":[
        "physician",
        "surgeon"
    ],
    "wof:name":"John A Rulison Inc",
    "wof:placetype":"venue"
},
  "geometry": {"coordinates":[-120.790021,38.726217],"type":"Point"}
}