{
  "type": "Feature",
  "properties": {
    "iso:country":"US",
    "sg:address":"1305 E Saint Gertrude Pl Ste A",
    "sg:city":"Santa Ana",
    "sg:classifiers":[
        {
            "category":"Real Estate",
            "subcategory":"Real Estate Services",
            "type":"Services"
        }
    ],
    "sg:phone":"+1 714 979 7861",
    "sg:postcode":"92705",
    "sg:province":"CA",
    "sg:tags":[
        "management",
        "property"
    ],
    "wof:name":"Vertox Inc",
    "wof:placetype":"venue"
},
  "geometry": {"coordinates":[-117.853996,33.7197],"type":"Point"}
}