{
  "type": "Feature",
  "properties": {
    "addr:full":"South Bay Family Medical Group 855 Manhattan Beach Blvd Manhattan Beach CA 90266",
    "addr:housenumber":"855",
    "addr:postcode":"90266",
    "addr:street":"South;Manhattan Beach Blvd",
    "iso:country":"US",
    "sg:address":"South Bay Family Medical Group 855 Manhattan Beach Blvd",
    "sg:city":"Manhattan Beach",
    "sg:classifiers":[
        {
            "category":"Health Services",
            "subcategory":"Doctor",
            "type":"Services"
        }
    ],
    "sg:phone":"+1 310 939 7858",
    "sg:postcode":"90266",
    "sg:province":"CA",
    "sg:website":"www.sbfmg.com",
    "wof:name":"Lee Kissel,MD",
    "wof:placetype":"venue"
},
  "geometry": {"coordinates":[-118.40163,33.887718],"type":"Point"}
}