{
  "type": "Feature",
  "properties": {
    "addr:full":"22805 Saticoy St Canoga Park CA 91304",
    "addr:housenumber":"22805",
    "addr:postcode":"91304",
    "addr:street":"Saticoy St",
    "iso:country":"US",
    "sg:address":"22805 Saticoy St",
    "sg:city":"Canoga Park",
    "sg:classifiers":[
        {
            "category":"Education",
            "subcategory":"Special Training",
            "type":"Public Place"
        }
    ],
    "sg:phone":"+1 818 999 3771",
    "sg:postcode":"91304",
    "sg:province":"CA",
    "sg:tags":[
        "tutoring"
    ],
    "wof:name":"Learning Castle Educational Materials & Tutoring",
    "wof:placetype":"venue"
},
  "geometry": {"coordinates":[-118.62400100000001,34.208099],"type":"Point"}
}