{
  "type": "Feature",
  "properties": {
    "addr:full":"472 Howe Ave Sacramento CA 95825",
    "addr:housenumber":"472",
    "addr:postcode":"95825",
    "addr:street":"Howe Ave",
    "iso:country":"US",
    "sg:address":"472 Howe Ave",
    "sg:city":"Sacramento",
    "sg:classifiers":[
        {
            "category":"Food & Beverages",
            "subcategory":"Fruits & Vegetables",
            "type":"Retail Goods"
        }
    ],
    "sg:phone":"+1 916 922 9454",
    "sg:postcode":"95825",
    "sg:province":"CA",
    "sg:tags":[
        "juice"
    ],
    "wof:name":"WIKI WIKI Juice Bar",
    "wof:placetype":"venue"
},
  "geometry": {"coordinates":[-121.41503899999999,38.573598],"type":"Point"}
}