{
  "type": "Feature",
  "properties": {
    "addr:full":"660 16th Ave San Francisco CA 94118",
    "addr:housenumber":"660",
    "addr:postcode":"94118",
    "addr:street":"16Th Ave",
    "iso:country":"US",
    "sg:address":"660 16th Ave",
    "sg:city":"San Francisco",
    "sg:classifiers":[
        {
            "category":"Real Estate",
            "subcategory":"Real Estate Agent",
            "type":"Services"
        }
    ],
    "sg:phone":"+1 415 221 9939",
    "sg:postcode":"94118",
    "sg:province":"CA",
    "wof:name":"Coldwell Banker Real Estate",
    "wof:placetype":"venue"
},
  "geometry": {"coordinates":[-122.474675,37.776023],"type":"Point"}
}