{
  "type": "Feature",
  "properties": {
    "addr:full":"11902 Lampson Ave Garden Grove CA 92840",
    "addr:housenumber":"11902",
    "addr:postcode":"92840",
    "addr:street":"Lampson Ave",
    "iso:country":"US",
    "sg:address":"11902 Lampson Ave",
    "sg:city":"Garden Grove",
    "sg:classifiers":[
        {
            "category":"Banks & Credit Unions",
            "subcategory":"Financial Services",
            "type":"Services"
        }
    ],
    "sg:phone":"+1 714 539 6858",
    "sg:postcode":"92840",
    "sg:province":"CA",
    "sg:tags":[
        "investor"
    ],
    "wof:name":"Mr Todd Flewitt",
    "wof:placetype":"venue"
},
  "geometry": {"coordinates":[-117.925579,33.781517],"type":"Point"}
}