{
  "type": "Feature",
  "properties": {
    "iso:country":"US",
    "sg:address":"1626 Wilcox Ave Ste 718",
    "sg:city":"Los Angeles",
    "sg:classifiers":[
        {
            "category":"Building & Trades",
            "subcategory":"Construction",
            "type":"Services"
        }
    ],
    "sg:phone":"+1 818 782 2535",
    "sg:postcode":"90028",
    "sg:province":"CA",
    "sg:tags":[
        "handyman"
    ],
    "wof:name":"Robert Medici",
    "wof:placetype":"venue"
},
  "geometry": {"coordinates":[-118.331009,34.100677],"type":"Point"}
}