{
  "type": "Feature",
  "properties": {
    "addr:full":"231 Oconnor Dr San Jose CA 95128",
    "addr:housenumber":"231",
    "addr:postcode":"95128",
    "addr:street":"Oconnor Dr",
    "iso:country":"US",
    "sg:address":"231 Oconnor Dr",
    "sg:city":"San Jose",
    "sg:classifiers":[
        {
            "category":"Building & Trades",
            "subcategory":"Electrical",
            "type":"Services"
        }
    ],
    "sg:phone":"+1 408 266 9134",
    "sg:postcode":"95128",
    "sg:province":"CA",
    "sg:tags":[
        "electrician"
    ],
    "wof:name":"Christie Electric",
    "wof:placetype":"venue"
},
  "geometry": {"coordinates":[-121.939003,37.323601],"type":"Point"}
}