{
  "type": "Feature",
  "properties": {
    "addr:full":"935 Middlefield Rd Palo Alto CA 94301",
    "addr:housenumber":"935",
    "addr:postcode":"94301",
    "addr:street":"Middlefield Rd",
    "iso:country":"US",
    "sg:address":"935 Middlefield Rd",
    "sg:city":"Palo Alto",
    "sg:classifiers":[
        {
            "category":"Social Services",
            "type":"Services"
        }
    ],
    "sg:phone":"+1 650 323 4533",
    "sg:postcode":"94301",
    "sg:province":"CA",
    "sg:tags":[
        "counselor",
        "marriage",
        "family"
    ],
    "wof:name":"Nancy Trueblood",
    "wof:placetype":"venue"
},
  "geometry": {"coordinates":[-122.150898,37.447116],"type":"Point"}
}