{
  "type": "Feature",
  "properties": {
    "iso:country":"US",
    "sg:address":"2367 W 208th St",
    "sg:city":"Torrance",
    "sg:classifiers":[
        {
            "category":"Wholesale",
            "subcategory":"Durable Goods & Equipment",
            "type":"Manufacturing & Wholesale Goods"
        }
    ],
    "sg:phone":"+1 310 212 1049",
    "sg:postcode":"90501",
    "sg:province":"CA",
    "sg:tags":[
        "exporter"
    ],
    "wof:name":"Pacific Coast Buyers Club",
    "wof:placetype":"venue"
},
  "geometry": {"coordinates":[-118.325677,33.843826],"type":"Point"}
}