{
  "type": "Feature",
  "properties": {
    "addr:full":"3851 Birch St Newport Beach CA 92660",
    "addr:housenumber":"3851",
    "addr:postcode":"92660",
    "addr:street":"Birch St",
    "iso:country":"US",
    "sg:address":"3851 Birch St",
    "sg:city":"Newport Beach",
    "sg:classifiers":[
        {
            "category":"Manufacturing",
            "subcategory":"Printing",
            "type":"Manufacturing & Wholesale Goods"
        }
    ],
    "sg:phone":"+1 949 296 1171",
    "sg:postcode":"92660",
    "sg:province":"CA",
    "sg:tags":[
        "printer"
    ],
    "wof:name":"Jiffy Print",
    "wof:placetype":"venue"
},
  "geometry": {"coordinates":[-117.868523,33.666047],"type":"Point"}
}