{
  "type": "Feature",
  "properties": {
    "iso:country":"US",
    "sg:address":"650 Terrace Dr",
    "sg:city":"San Dimas",
    "sg:classifiers":[
        {
            "category":"Building & Trades",
            "subcategory":"Construction",
            "type":"Services"
        }
    ],
    "sg:phone":"+1 909 599 4079",
    "sg:postcode":"91773",
    "sg:province":"CA",
    "sg:tags":[
        "contractor"
    ],
    "wof:name":"B & D Enterprises",
    "wof:placetype":"venue"
},
  "geometry": {"coordinates":[-117.815022,34.100439],"type":"Point"}
}