{
  "type": "Feature",
  "properties": {
    "addr:full":"7705 Potrero Ave El Cerrito CA 94530",
    "addr:housenumber":"7705",
    "addr:postcode":"94530",
    "addr:street":"Potrero Ave",
    "iso:country":"US",
    "sg:address":"7705 Potrero Ave",
    "sg:city":"El Cerrito",
    "sg:classifiers":[
        {
            "category":"Real Estate",
            "subcategory":"Real Estate Agent",
            "type":"Services"
        }
    ],
    "sg:phone":"+1 510 235 8889",
    "sg:postcode":"94530",
    "sg:province":"CA",
    "wof:name":"Mc Sween Real Estate",
    "wof:placetype":"venue"
},
  "geometry": {"coordinates":[-122.302475,37.927348],"type":"Point"}
}