{
  "type": "Feature",
  "properties": {
    "addr:full":"548 W Acacia Ave Fresno CA 93705",
    "addr:housenumber":"548",
    "addr:postcode":"93705",
    "addr:street":"W Acacia Ave",
    "iso:country":"US",
    "sg:address":"548 W Acacia Ave",
    "sg:city":"Fresno",
    "sg:classifiers":[
        {
            "category":"Real Estate",
            "subcategory":"Real Estate Operator",
            "type":"Services"
        }
    ],
    "sg:phone":"+1 559 229 7797",
    "sg:postcode":"93705",
    "sg:province":"CA",
    "sg:tags":[
        "building",
        "apartment"
    ],
    "wof:name":"Jacqueline M Spence",
    "wof:placetype":"venue"
},
  "geometry": {"coordinates":[-119.81929700000001,36.804253],"type":"Point"}
}