{
  "type": "Feature",
  "properties": {
    "addr:full":"2325 Teasley St La Crescenta CA 91214",
    "addr:housenumber":"2325",
    "addr:postcode":"91214",
    "addr:street":"Teasley St",
    "iso:country":"US",
    "sg:address":"2325 Teasley St",
    "sg:city":"La Crescenta",
    "sg:classifiers":[
        {
            "category":"Education",
            "subcategory":"School",
            "type":"Public Place"
        }
    ],
    "sg:phone":"+1 213 894 0530",
    "sg:postcode":"91214",
    "sg:province":"CA",
    "wof:name":"US Immigration",
    "wof:placetype":"venue"
},
  "geometry": {"coordinates":[-118.230062,34.232671],"type":"Point"}
}