{
  "type": "Feature",
  "properties": {
    "addr:full":"1689 Arden Way Sacramento CA 95815",
    "addr:housenumber":"1689",
    "addr:postcode":"95815",
    "addr:street":"Arden Way",
    "iso:country":"US",
    "sg:address":"1689 Arden Way",
    "sg:city":"Sacramento",
    "sg:classifiers":[
        {
            "category":"Shopping",
            "subcategory":"Shoes",
            "type":"Retail Goods"
        }
    ],
    "sg:phone":"+1 916 923 2377",
    "sg:postcode":"95815",
    "sg:province":"CA",
    "sg:tags":[
        "store"
    ],
    "wof:name":"Van's Tennis Shoes",
    "wof:placetype":"venue"
},
  "geometry": {"coordinates":[-121.42703400000001,38.599719],"type":"Point"}
}