{
  "type": "Feature",
  "properties": {
    "addr:full":"9256 Orangevale Ave Orangevale CA 95662",
    "addr:housenumber":"9256",
    "addr:postcode":"95662",
    "addr:street":"Orangevale Ave",
    "iso:country":"US",
    "sg:address":"9256 Orangevale Ave",
    "sg:city":"Orangevale",
    "sg:classifiers":[
        {
            "category":"Wholesale",
            "subcategory":"Farm Supplies",
            "type":"Manufacturing & Wholesale Goods"
        }
    ],
    "sg:phone":"+1 916 987 6273",
    "sg:postcode":"95662",
    "sg:province":"CA",
    "sg:tags":[
        "agricultural",
        "product"
    ],
    "wof:name":"Multigrain Pulses America LLC",
    "wof:placetype":"venue"
},
  "geometry": {"coordinates":[-121.206936,38.681777],"type":"Point"}
}