{
  "type": "Feature",
  "properties": {
    "addr:full":"5025 E 2nd St Long Beach CA 90803",
    "addr:housenumber":"5025",
    "addr:postcode":"90803",
    "addr:street":"E 2Nd St",
    "iso:country":"US",
    "sg:address":"5025 E 2nd St",
    "sg:city":"Long Beach",
    "sg:classifiers":[
        {
            "category":"Shopping",
            "subcategory":"Clothing, Apparel, & Fashions",
            "type":"Retail Goods"
        }
    ],
    "sg:phone":"+1 562 433 1507",
    "sg:postcode":"90803",
    "sg:province":"CA",
    "sg:website":"www.gap.com",
    "wof:name":"Gap",
    "wof:placetype":"venue"
},
  "geometry": {"coordinates":[-118.136017,33.760855],"type":"Point"}
}