{
  "type": "Feature",
  "properties": {
    "iso:country":"US",
    "sg:address":"7101 Magnolia Ave",
    "sg:city":"Riverside",
    "sg:classifiers":[
        {
            "category":"Travel",
            "subcategory":"Travel Agent",
            "type":"Entertainment"
        }
    ],
    "sg:phone":"+1 951 787 6810",
    "sg:postcode":"92504",
    "sg:province":"CA",
    "sg:tags":[
        "agency",
        "bureau"
    ],
    "sg:website":"www.saver.net",
    "wof:name":"Travel Center",
    "wof:placetype":"venue"
},
  "geometry": {"coordinates":[-117.402011,33.945672],"type":"Point"}
}