{
  "type": "Feature",
  "properties": {
    "iso:country":"US",
    "sg:address":"1350 E Lexington Ave",
    "sg:city":"Pomona",
    "sg:classifiers":[
        {
            "category":"Freight",
            "type":"Transportation"
        }
    ],
    "sg:phone":"+1 909 627 3776",
    "sg:postcode":"91766",
    "sg:province":"CA",
    "sg:tags":[
        "trucking"
    ],
    "wof:name":"Jack Jones Trucking Inc",
    "wof:placetype":"venue"
},
  "geometry": {"coordinates":[-117.72797,34.037391],"type":"Point"}
}