{
  "type": "Feature",
  "properties": {
    "addr:full":"720 Charcot Ave San Jose CA 95131",
    "addr:housenumber":"720",
    "addr:postcode":"95131",
    "addr:street":"Charcot Ave",
    "iso:country":"US",
    "sg:address":"720 Charcot Ave",
    "sg:city":"San Jose",
    "sg:classifiers":[
        {
            "category":"Manufacturing",
            "subcategory":"Rubber & Plastics",
            "type":"Manufacturing & Wholesale Goods"
        }
    ],
    "sg:phone":"+1 408 432 1711",
    "sg:postcode":"95131",
    "sg:province":"CA",
    "sg:tags":[
        "product"
    ],
    "sg:website":"www.mediaproducts.com",
    "wof:name":"Media Products",
    "wof:placetype":"venue"
},
  "geometry": {"coordinates":[-121.90828399999999,37.385959],"type":"Point"}
}