{
  "type": "Feature",
  "properties": {
    "addr:full":"4855 70th St San Diego CA 92115",
    "addr:housenumber":"4855",
    "addr:postcode":"92115",
    "addr:street":"70Th St",
    "iso:country":"US",
    "sg:address":"4855 70th St",
    "sg:city":"San Diego",
    "sg:classifiers":[
        {
            "category":"Building & Trades",
            "subcategory":"Electrical",
            "type":"Services"
        }
    ],
    "sg:phone":"+1 619 225 9733",
    "sg:postcode":"92115",
    "sg:province":"CA",
    "sg:tags":[
        "installation"
    ],
    "wof:name":"Installed",
    "wof:placetype":"venue"
},
  "geometry": {"coordinates":[-117.046753,32.766734],"type":"Point"}
}