{
  "type": "Feature",
  "properties": {
    "iso:country":"US",
    "sg:address":"780 Crocker St",
    "sg:city":"Los Angeles",
    "sg:classifiers":[
        {
            "category":"Shopping",
            "subcategory":"Crafts & Fabrics",
            "type":"Retail Goods"
        }
    ],
    "sg:phone":"+1 213 741 6392",
    "sg:postcode":"90021",
    "sg:province":"CA",
    "sg:tags":[
        "shop"
    ],
    "wof:name":"U S Connection",
    "wof:placetype":"venue"
},
  "geometry": {"coordinates":[-118.247668,34.03846],"type":"Point"}
}