{
  "type": "Feature",
  "properties": {
    "iso:country":"US",
    "sg:address":"1601 Avocado Ave",
    "sg:city":"Newport Beach",
    "sg:classifiers":[
        {
            "category":"Health Services",
            "subcategory":"Medical Lab",
            "type":"Services"
        }
    ],
    "sg:phone":"+1 949 721 1058",
    "sg:postcode":"92660",
    "sg:province":"CA",
    "sg:tags":[
        "laboratory"
    ],
    "wof:name":"Westcliff Medical Labs",
    "wof:placetype":"venue"
},
  "geometry": {"coordinates":[-117.869154,33.613697],"type":"Point"}
}