{
  "type": "Feature",
  "properties": {
    "iso:country":"US",
    "sg:address":"1117 W 190th St",
    "sg:city":"Gardena",
    "sg:classifiers":[
        {
            "category":"Retail",
            "subcategory":"Auto Repair",
            "type":"Services"
        }
    ],
    "sg:phone":"+1 310 618 8606",
    "sg:postcode":"90248",
    "sg:province":"CA",
    "wof:name":"Bm Foreign Cars",
    "wof:placetype":"venue"
},
  "geometry": {"coordinates":[-118.2954,33.858347],"type":"Point"}
}