{
  "type": "Feature",
  "properties": {
    "iso:country":"US",
    "sg:address":"17942 Sky Park Cir Suite C",
    "sg:city":"Irvine",
    "sg:classifiers":[
        {
            "category":"Professional",
            "subcategory":"Employment Agencies",
            "type":"Services"
        }
    ],
    "sg:phone":"+1 949 861 3981",
    "sg:postcode":"92614",
    "sg:province":"CA",
    "wof:name":"Spectrum Management Solutions",
    "wof:placetype":"venue"
},
  "geometry": {"coordinates":[-117.860343,33.68964],"type":"Point"}
}