{
  "type": "Feature",
  "properties": {
    "addr:full":"9833 Independence Ave Chatsworth CA 91311",
    "addr:housenumber":"9833",
    "addr:postcode":"91311",
    "addr:street":"Independence Ave",
    "iso:country":"US",
    "sg:address":"9833 Independence Ave",
    "sg:city":"Chatsworth",
    "sg:classifiers":[
        {
            "category":"Manufacturing",
            "subcategory":"Electronics",
            "type":"Manufacturing & Wholesale Goods"
        }
    ],
    "sg:phone":"+1 818 718 1040",
    "sg:postcode":"91311",
    "sg:province":"CA",
    "sg:tags":[
        "equipment",
        "electronic",
        "supply"
    ],
    "wof:name":"Customs Suppression",
    "wof:placetype":"venue"
},
  "geometry": {"coordinates":[-118.590811,34.247561],"type":"Point"}
}