{
  "type": "Feature",
  "properties": {
    "addr:full":"2125 Centerpointe Pkwy Santa Maria CA 93455",
    "addr:housenumber":"2125",
    "addr:postcode":"93455",
    "addr:street":"Centerpointe Pkwy",
    "iso:country":"US",
    "sg:address":"2125 Centerpointe Pkwy",
    "sg:city":"Santa Maria",
    "sg:classifiers":[
        {
            "category":"Government",
            "subcategory":"Office",
            "type":"Public Place"
        }
    ],
    "sg:phone":"+1 805 346 7129",
    "sg:postcode":"93455",
    "sg:province":"CA",
    "wof:name":"Adoption Agency",
    "wof:placetype":"venue"
},
  "geometry": {"coordinates":[-120.42862700000001,34.922709],"type":"Point"}
}