{
  "type": "Feature",
  "properties": {
    "iso:country":"US",
    "sg:address":"17565 Los Alamos St",
    "sg:city":"Fountain Valley",
    "sg:classifiers":[
        {
            "category":"Social Services",
            "subcategory":"Child Care",
            "type":"Services"
        }
    ],
    "sg:phone":"+1 714 593 6511",
    "sg:postcode":"92708",
    "sg:province":"CA",
    "sg:tags":[
        "elementary",
        "kindergarten",
        "school",
        "academic"
    ],
    "wof:name":"Continuing Development Inc",
    "wof:placetype":"venue"
},
  "geometry": {"coordinates":[-117.949997,33.709],"type":"Point"}
}