{
  "type": "Feature",
  "properties": {
    "iso:country":"US",
    "sg:address":"27225 Calaroga Ave",
    "sg:city":"Hayward",
    "sg:classifiers":[
        {
            "category":"Health Services",
            "subcategory":"Doctor",
            "type":"Services"
        }
    ],
    "sg:phone":"+1 510 293 2039",
    "sg:postcode":"94545",
    "sg:province":"CA",
    "sg:tags":[
        "physician",
        "surgeon"
    ],
    "wof:name":"Calaroga Surgical Ctr",
    "wof:placetype":"venue"
},
  "geometry": {"coordinates":[-122.089966,37.633768],"type":"Point"}
}