{
  "type": "Feature",
  "properties": {
    "iso:country":"US",
    "sg:address":"511 N Bonhill Rd",
    "sg:city":"Los Angeles",
    "sg:classifiers":[
        {
            "category":"Building & Trades",
            "subcategory":"Landscaping Services",
            "type":"Services"
        }
    ],
    "sg:phone":"+1 310 471 4002",
    "sg:postcode":"90049",
    "sg:province":"CA",
    "wof:name":"Normandy Garden Designs",
    "wof:placetype":"venue"
},
  "geometry": {"coordinates":[-118.481216,34.068483],"type":"Point"}
}