{
  "type": "Feature",
  "properties": {
    "addr:full":"1816 Scenic Dr Modesto CA 95355",
    "addr:housenumber":"1816",
    "addr:postcode":"ca 95355",
    "addr:street":"Scenic Dr",
    "iso:country":"US",
    "sg:address":"1816 Scenic Dr",
    "sg:city":"Modesto",
    "sg:classifiers":[
        {
            "category":"Professional",
            "subcategory":"Computer Services",
            "type":"Services"
        }
    ],
    "sg:phone":"+1 209 521 2688",
    "sg:postcode":"95355",
    "sg:province":"CA",
    "wof:name":"Foothill Systems",
    "wof:placetype":"venue"
},
  "geometry": {"coordinates":[-120.96148100000001,37.652406],"type":"Point"}
}