{
  "type": "Feature",
  "properties": {
    "iso:country":"US",
    "sg:address":"Everywhere",
    "sg:city":"Bay Area",
    "sg:classifiers":[
        {
            "category":"Shopping",
            "subcategory":"Florist",
            "type":"Retail Goods"
        }
    ],
    "sg:phone":"+1 800 356 9377",
    "sg:postcode":"95101",
    "sg:province":"CA",
    "sg:website":"ww22.1800flowers.com/?cm_cid=wb0",
    "wof:name":"1 800 Flowers",
    "wof:placetype":"venue"
},
  "geometry": {"coordinates":[-122.300561,37.788219],"type":"Point"}
}