{
  "type": "Feature",
  "properties": {
    "addr:full":"596 Grizzly Peak Blvd Berkeley CA 94708",
    "addr:housenumber":"596",
    "addr:postcode":"94708",
    "addr:street":"Grizzly Peak Blvd",
    "iso:country":"US",
    "sg:address":"596 Grizzly Peak Blvd",
    "sg:city":"Berkeley",
    "sg:classifiers":[
        {
            "category":"Banks & Credit Unions",
            "subcategory":"Investment Brokerage",
            "type":"Services"
        }
    ],
    "sg:phone":"+1 510 527 5308",
    "sg:postcode":"94708",
    "sg:province":"CA",
    "sg:tags":[
        "advisory"
    ],
    "wof:name":"Kelling Investment Advisors",
    "wof:placetype":"venue"
},
  "geometry": {"coordinates":[-122.26721000000001,37.901817],"type":"Point"}
}