{
  "type": "Feature",
  "properties": {
    "iso:country":"US",
    "sg:address":"15000 Lakewood Blvd",
    "sg:city":"Bellflower",
    "sg:classifiers":[
        {
            "category":"Home & Garden",
            "subcategory":"Carpets & Floor Coverings",
            "type":"Retail Goods"
        }
    ],
    "sg:phone":"+1 562 652 8683",
    "sg:postcode":"90706",
    "sg:province":"CA",
    "sg:tags":[
        "mattress"
    ],
    "sg:website":"www.acemattress.com/",
    "wof:name":"Ace Mattress",
    "wof:placetype":"venue"
},
  "geometry": {"coordinates":[-118.142629,33.897286],"type":"Point"}
}