{
  "type": "Feature",
  "properties": {
    "iso:country":"US",
    "sg:address":"5175 Pondorex Rd",
    "sg:city":"Auburn",
    "sg:classifiers":[
        {
            "category":"Wholesale",
            "subcategory":"Groceries",
            "type":"Manufacturing & Wholesale Goods"
        }
    ],
    "sg:phone":"+1 530 888 7540",
    "sg:postcode":"95602",
    "sg:province":"CA",
    "sg:tags":[
        "baker"
    ],
    "wof:name":"Blattler's Fine Foods-Desserts",
    "wof:placetype":"venue"
},
  "geometry": {"coordinates":[-121.05514599999999,38.968426],"type":"Point"}
}