{
  "type": "Feature",
  "properties": {
    "iso:country":"US",
    "sg:address":"20005 Vanowen St",
    "sg:city":"Winnetka",
    "sg:classifiers":[
        {
            "category":"Personal",
            "subcategory":"Psychics & Astrologers",
            "type":"Services"
        }
    ],
    "sg:phone":"+1 818 703 1499",
    "sg:postcode":"91306",
    "sg:province":"CA",
    "sg:website":"www.stephaniepsychicadvisor.com",
    "wof:name":"Stephanie, Psychic",
    "wof:placetype":"venue"
},
  "geometry": {"coordinates":[-118.568985,34.194179],"type":"Point"}
}