{
  "type": "Feature",
  "properties": {
    "addr:full":"7165 Sycamore Rd Atascadero CA 93422",
    "addr:housenumber":"7165",
    "addr:postcode":"93422",
    "addr:street":"Sycamore Rd",
    "iso:country":"US",
    "sg:address":"7165 Sycamore Rd",
    "sg:city":"Atascadero",
    "sg:classifiers":[
        {
            "category":"Building & Trades",
            "subcategory":"Construction",
            "type":"Services"
        }
    ],
    "sg:phone":"+1 805 466 7200",
    "sg:postcode":"93422",
    "sg:province":"CA",
    "sg:tags":[
        "roofing",
        "contractor"
    ],
    "wof:name":"A-1 Roofing",
    "wof:placetype":"venue"
},
  "geometry": {"coordinates":[-120.648715,35.495484],"type":"Point"}
}