{
  "type": "Feature",
  "properties": {
    "iso:country":"US",
    "sg:address":"301 Beach Street",
    "sg:city":"Santa Cruz",
    "sg:classifiers":[
        {
            "category":"Travel",
            "subcategory":"Hotels & Motels",
            "type":"Entertainment"
        }
    ],
    "sg:phone":"+1 831 426 0420",
    "sg:postcode":"95060",
    "sg:province":"CA",
    "sg:website":"www.coastviewinn.com",
    "wof:name":"Coastview Inn",
    "wof:placetype":"venue"
},
  "geometry": {"coordinates":[-122.021078,36.963978],"type":"Point"}
}