{
  "type": "Feature",
  "properties": {
    "iso:country":"US",
    "sg:address":"10635 Atrium Dr",
    "sg:city":"San Diego",
    "sg:classifiers":[
        {
            "category":"Shopping",
            "type":"Retail Goods"
        }
    ],
    "sg:phone":"+1 858 566 4093",
    "sg:postcode":"92131",
    "sg:province":"CA",
    "sg:tags":[
        "miscellaneous",
        "store"
    ],
    "wof:name":"Edges",
    "wof:placetype":"venue"
},
  "geometry": {"coordinates":[-117.103376,32.902347],"type":"Point"}
}