{
  "type": "Feature",
  "properties": {
    "addr:full":"1 Lower Ragsdale Dr Monterey CA 93940",
    "addr:housenumber":"1",
    "addr:postcode":"93940",
    "addr:street":"Lower Ragsdale Dr",
    "iso:country":"US",
    "sg:address":"1 Lower Ragsdale Dr",
    "sg:city":"Monterey",
    "sg:classifiers":[
        {
            "category":"Wholesale",
            "subcategory":"Sporting Goods",
            "type":"Manufacturing & Wholesale Goods"
        }
    ],
    "sg:phone":"+1 831 647 3110",
    "sg:postcode":"93940",
    "sg:province":"CA",
    "sg:tags":[
        "equipment",
        "golf",
        "supply"
    ],
    "sg:website":"www.feelwedges.com",
    "wof:name":"Feel Golf",
    "wof:placetype":"venue"
},
  "geometry": {"coordinates":[-121.814255,36.574846],"type":"Point"}
}