{
  "type": "Feature",
  "properties": {
    "iso:country":"US",
    "sg:address":"510 W Mission Ave",
    "sg:city":"Escondido",
    "sg:classifiers":[
        {
            "category":"Restaurant",
            "type":"Food & Drink"
        }
    ],
    "sg:menulink":"http://www.allmenus.com/ca/oceanside-escondido/9194-dennys/menu/",
    "sg:phone":"+1 760 743 0920",
    "sg:postcode":"92025",
    "sg:province":"CA",
    "sg:tags":[
        "american",
        "diner"
    ],
    "wof:name":"Denny's",
    "wof:placetype":"venue"
},
  "geometry": {"coordinates":[-117.092067,33.128261],"type":"Point"}
}