{
  "type": "Feature",
  "properties": {
    "iso:country":"US",
    "sg:address":"8455 N Millbrook Ave",
    "sg:city":"Fresno",
    "sg:classifiers":[
        {
            "category":"Health Services",
            "subcategory":"Chiropractor",
            "type":"Services"
        }
    ],
    "sg:phone":"+1 559 435 9505",
    "sg:postcode":"93720",
    "sg:province":"CA",
    "sg:tags":[
        "chiropractic"
    ],
    "sg:website":"http://www.swarthoutchiropractic.com",
    "wof:name":"Swarthout Chiropractic",
    "wof:placetype":"venue"
},
  "geometry": {"coordinates":[-119.76577,36.858643],"type":"Point"}
}