{
  "type": "Feature",
  "properties": {
    "addr:full":"20382 Hermana Cir Lake Forest CA 92630",
    "addr:housenumber":"20382",
    "addr:postcode":"92630",
    "addr:street":"Hermana Cir",
    "iso:country":"US",
    "sg:address":"20382 Hermana Cir",
    "sg:city":"Lake Forest",
    "sg:classifiers":[
        {
            "category":"Shopping",
            "subcategory":"Clothing, Apparel, & Fashions",
            "type":"Retail Goods"
        }
    ],
    "sg:phone":"+1 949 240 1418",
    "sg:postcode":"92630",
    "sg:province":"CA",
    "sg:tags":[
        "clothing",
        "women's"
    ],
    "wof:name":"Another Line Inc",
    "wof:placetype":"venue"
},
  "geometry": {"coordinates":[-117.65779000000001,33.666477],"type":"Point"}
}