{
  "type": "Feature",
  "properties": {
    "iso:country":"US",
    "sg:address":"1763 2nd St",
    "sg:city":"Napa",
    "sg:classifiers":[
        {
            "category":"Professional",
            "subcategory":"Accounting & Tax Preparation",
            "type":"Services"
        }
    ],
    "sg:phone":"+1 707 255 1037",
    "sg:postcode":"94559",
    "sg:province":"CA",
    "sg:tags":[
        "accountant"
    ],
    "wof:name":"Joe Hall CPA",
    "wof:placetype":"venue"
},
  "geometry": {"coordinates":[-122.291606,38.29623],"type":"Point"}
}