{
  "type": "Feature",
  "properties": {
    "iso:country":"US",
    "sg:address":"16656 Los Positas Way",
    "sg:city":"Tracy",
    "sg:classifiers":[
        {
            "category":"Freight",
            "type":"Transportation"
        }
    ],
    "sg:phone":"+1 209 839 8238",
    "sg:postcode":"95304",
    "sg:province":"CA",
    "sg:tags":[
        "local",
        "storage",
        "trucking"
    ],
    "wof:name":"Danny Perugi",
    "wof:placetype":"venue"
},
  "geometry": {"coordinates":[-121.513628,37.747609],"type":"Point"}
}