{
  "type": "Feature",
  "properties": {
    "iso:country":"US",
    "sg:address":"2627 N Raymond Ave",
    "sg:city":"Altadena",
    "sg:classifiers":[
        {
            "category":"Shopping",
            "subcategory":"Gifts & Souvenirs",
            "type":"Retail Goods"
        }
    ],
    "sg:phone":"+1 626 794 1545",
    "sg:postcode":"91001",
    "sg:province":"CA",
    "wof:name":"Big Fire Mountain Mfg",
    "wof:placetype":"venue"
},
  "geometry": {"coordinates":[-118.14569299999999,34.18992],"type":"Point"}
}