{
  "type": "Feature",
  "properties": {
    "addr:full":"38019 Peterson Rd Auberry CA 93602",
    "addr:housenumber":"38019",
    "addr:postcode":"93602",
    "addr:street":"Peterson Rd",
    "iso:country":"US",
    "sg:address":"38019 Peterson Rd",
    "sg:city":"Auberry",
    "sg:classifiers":[
        {
            "category":"Home & Garden",
            "subcategory":"Home Furnishings",
            "type":"Retail Goods"
        }
    ],
    "sg:phone":"+1 559 841 8228",
    "sg:postcode":"93602",
    "sg:province":"CA",
    "sg:tags":[
        "utensil",
        "cooking"
    ],
    "wof:name":"Deaton Acres Cntry Products",
    "wof:placetype":"venue"
},
  "geometry": {"coordinates":[-119.32677099999999,37.035551],"type":"Point"}
}