{
  "type": "Feature",
  "properties": {
    "addr:full":"9314 Fern St South El Monte CA 91733",
    "addr:housenumber":"9314",
    "addr:postcode":"91733",
    "addr:street":"Fern St",
    "iso:country":"US",
    "sg:address":"9314 Fern St",
    "sg:city":"South El Monte",
    "sg:classifiers":[
        {
            "category":"Shopping",
            "subcategory":"Clothing, Apparel, & Fashions",
            "type":"Retail Goods"
        }
    ],
    "sg:phone":"+1 626 453 0682",
    "sg:postcode":"91733",
    "sg:province":"CA",
    "wof:name":"Morning Fashion Inc",
    "wof:placetype":"venue"
},
  "geometry": {"coordinates":[-118.066312,34.058977],"type":"Point"}
}