{
  "type": "Feature",
  "properties": {
    "addr:full":"9078 Walker Ct Reedley CA 93654",
    "addr:housenumber":"9078",
    "addr:postcode":"93654",
    "addr:street":"Walker Ct",
    "iso:country":"US",
    "sg:address":"9078 Walker Ct",
    "sg:city":"Reedley",
    "sg:classifiers":[
        {
            "category":"Freight",
            "type":"Transportation"
        }
    ],
    "sg:phone":"+1 559 638 7878",
    "sg:postcode":"93654",
    "sg:province":"CA",
    "wof:name":"H F Magana Transport",
    "wof:placetype":"venue"
},
  "geometry": {"coordinates":[-119.485069,36.602458],"type":"Point"}
}