{
  "type": "Feature",
  "properties": {
    "addr:full":"3265 17th St Ste 404 San Francisco CA 94110",
    "addr:housenumber":"3265",
    "addr:postcode":"94110",
    "addr:street":"17Th St Ste 404",
    "iso:country":"US",
    "sg:address":"3265 17th St Ste 404",
    "sg:city":"San Francisco",
    "sg:classifiers":[
        {
            "category":"Organizations",
            "subcategory":"Non-profit Organization",
            "type":"Services"
        }
    ],
    "sg:phone":"+1 415 437 3990",
    "sg:postcode":"94110",
    "sg:province":"CA",
    "sg:tags":[
        "service/non-profit",
        "community"
    ],
    "sg:website":"www.hcnkids.org",
    "wof:name":"Homeless Children's Network",
    "wof:placetype":"venue"
},
  "geometry": {"coordinates":[-122.41879,37.763463],"type":"Point"}
}