{
  "type": "Feature",
  "properties": {
    "addr:full":"5564 E Vis del Dia Anaheim CA 92807",
    "addr:housenumber":"5564",
    "addr:postcode":"92807",
    "addr:street":"E Vis Del Dia",
    "iso:country":"US",
    "sg:address":"5564 E Vis del Dia",
    "sg:city":"Anaheim",
    "sg:classifiers":[
        {
            "category":"Retail",
            "subcategory":"Animal Services",
            "type":"Services"
        }
    ],
    "sg:phone":"+1 714 279 3923",
    "sg:postcode":"92807",
    "sg:province":"CA",
    "wof:name":"Always Home Pet Sitting",
    "wof:placetype":"venue"
},
  "geometry": {"coordinates":[-117.793729,33.846888],"type":"Point"}
}