{
  "type": "Feature",
  "properties": {
    "addr:full":"5460 55th St San Diego CA 92115",
    "addr:housenumber":"5460",
    "addr:postcode":"92115",
    "addr:street":"55Th St",
    "iso:country":"US",
    "sg:address":"5460 55th St",
    "sg:city":"San Diego",
    "sg:classifiers":[
        {
            "category":"Real Estate",
            "subcategory":"Real Estate Operator",
            "type":"Services"
        }
    ],
    "sg:phone":"+1 619 583 7402",
    "sg:postcode":"92115",
    "sg:province":"CA",
    "sg:tags":[
        "apartment"
    ],
    "wof:name":"Albert's College Apartments",
    "wof:placetype":"venue"
},
  "geometry": {"coordinates":[-117.077044,32.776847],"type":"Point"}
}