{
  "type": "Feature",
  "properties": {
    "iso:country":"US",
    "sg:address":"3501 Civic Center Dr",
    "sg:city":"San Rafael",
    "sg:classifiers":[
        {
            "category":"Shopping",
            "subcategory":"Gifts & Souvenirs",
            "type":"Retail Goods"
        }
    ],
    "sg:phone":"+1 415 472 3325",
    "sg:postcode":"94903",
    "sg:province":"CA",
    "sg:tags":[
        "party",
        "supply"
    ],
    "wof:name":"Pronzini Christmas Trees",
    "wof:placetype":"venue"
},
  "geometry": {"coordinates":[-122.528432,37.996741],"type":"Point"}
}