{
  "type": "Feature",
  "properties": {
    "addr:full":"1343 Tire Alameda CA 94501",
    "addr:postcode":"94501",
    "addr:street":"Alameda",
    "iso:country":"US",
    "sg:address":"1343 Tire",
    "sg:city":"Alameda",
    "sg:classifiers":[
        {
            "category":"Shopping",
            "subcategory":"Antiques",
            "type":"Retail Goods"
        },
        {
            "category":"Home & Garden",
            "subcategory":"Furniture",
            "type":"Retail Goods"
        }
    ],
    "sg:phone":"+1 408 293 8686",
    "sg:postcode":"94501",
    "sg:province":"CA",
    "sg:tags":[
        "store"
    ],
    "wof:name":"Teak House the",
    "wof:placetype":"venue"
},
  "geometry": {"coordinates":[-122.261002,37.768101],"type":"Point"}
}