{
  "type": "Feature",
  "properties": {
    "addr:full":"2769 Las Palmas Ave Escondido CA 92025",
    "addr:housenumber":"2769",
    "addr:postcode":"92025",
    "addr:street":"Las Palmas Ave",
    "iso:country":"US",
    "sg:address":"2769 Las Palmas Ave",
    "sg:city":"Escondido",
    "sg:classifiers":[
        {
            "category":"Health Services",
            "subcategory":"Doctor",
            "type":"Services"
        }
    ],
    "sg:phone":"+1 760 489 0830",
    "sg:postcode":"92025",
    "sg:province":"CA",
    "sg:tags":[
        "physician",
        "surgeon"
    ],
    "wof:name":"A House Call Doctor",
    "wof:placetype":"venue"
},
  "geometry": {"coordinates":[-117.067606,33.087867],"type":"Point"}
}