{
  "type": "Feature",
  "properties": {
    "iso:country":"US",
    "sg:address":"225 Manhattan Beach Blvd",
    "sg:city":"Manhattan Beach",
    "sg:classifiers":[
        {
            "category":"Shopping",
            "subcategory":"Clothing, Apparel, & Fashions",
            "type":"Retail Goods"
        }
    ],
    "sg:phone":"+1 310 939 1250",
    "sg:postcode":"90266",
    "sg:province":"CA",
    "sg:tags":[
        "furnishing"
    ],
    "wof:name":"Jimmy's Fine Mens Clothing",
    "wof:placetype":"venue"
},
  "geometry": {"coordinates":[-118.409745,33.885181],"type":"Point"}
}