{
  "type": "Feature",
  "properties": {
    "addr:full":"4868 Hernandez Dr Guadalupe CA 93434",
    "addr:postcode":"4868;93434",
    "addr:street":"Hernandez Dr",
    "iso:country":"US",
    "sg:address":"4868 Hernandez Dr",
    "sg:city":"Guadalupe",
    "sg:classifiers":[
        {
            "category":"Professional",
            "subcategory":"Business Services",
            "type":"Services"
        }
    ],
    "sg:phone":"+1 805 343 7731",
    "sg:postcode":"93434",
    "sg:province":"CA",
    "sg:tags":[
        "paralegal"
    ],
    "wof:name":"GSI",
    "wof:placetype":"venue"
},
  "geometry": {"coordinates":[-120.57959099999999,34.958933],"type":"Point"}
}