{
  "type": "Feature",
  "properties": {
    "addr:full":"157 E Grand Ave Escondido CA 92025",
    "addr:housenumber":"157",
    "addr:postcode":"92025",
    "addr:street":"E Grand Ave",
    "iso:country":"US",
    "sg:address":"157 E Grand Ave",
    "sg:city":"Escondido",
    "sg:classifiers":[
        {
            "category":"Home & Garden",
            "subcategory":"Home Furnishings",
            "type":"Retail Goods"
        }
    ],
    "sg:phone":"+1 760 480 1777",
    "sg:postcode":"92025",
    "sg:province":"CA",
    "sg:tags":[
        "fixture",
        "lighting"
    ],
    "sg:website":"http://www.lightgalleryplus.com",
    "wof:name":"Light Gallery Plus",
    "wof:placetype":"venue"
},
  "geometry": {"coordinates":[-117.08066700000001,33.122034],"type":"Point"}
}