{
  "type": "Feature",
  "properties": {
    "iso:country":"US",
    "sg:address":"16315 Piuma Ave",
    "sg:city":"Cerritos",
    "sg:classifiers":[
        {
            "category":"Building & Trades",
            "subcategory":"Construction",
            "type":"Services"
        }
    ],
    "sg:phone":"+1 562 809 1532",
    "sg:postcode":"90703",
    "sg:province":"CA",
    "sg:tags":[
        "fire",
        "restoration",
        "damage"
    ],
    "wof:name":"Qwik Response Construction",
    "wof:placetype":"venue"
},
  "geometry": {"coordinates":[-118.105921,33.886819],"type":"Point"}
}