{
  "type": "Feature",
  "properties": {
    "addr:full":"850 El Camino Ave Sacramento CA 95815",
    "addr:housenumber":"850",
    "addr:postcode":"95815",
    "addr:street":"El Camino Ave",
    "iso:country":"US",
    "sg:address":"850 El Camino Ave",
    "sg:city":"Sacramento",
    "sg:classifiers":[
        {
            "category":"Restaurant",
            "type":"Food & Drink"
        }
    ],
    "sg:phone":"+1 916 925 1026",
    "sg:postcode":"95815",
    "sg:province":"CA",
    "sg:tags":[
        "mexican"
    ],
    "wof:name":"El Forastero Mexican Food",
    "wof:placetype":"venue"
},
  "geometry": {"coordinates":[-121.44719600000001,38.611],"type":"Point"}
}