{
  "type": "Feature",
  "properties": {
    "addr:full":"3798 Grand Ave Ste 1 Oakland CA 94610",
    "addr:housenumber":"3798",
    "addr:postcode":"94610",
    "addr:street":"Grand Ave Ste 1",
    "iso:country":"US",
    "sg:address":"3798 Grand Ave Ste 1",
    "sg:city":"Oakland",
    "sg:classifiers":[
        {
            "category":"Social Services",
            "type":"Services"
        }
    ],
    "sg:phone":"+1 510 809 5331",
    "sg:postcode":"94610",
    "sg:province":"CA",
    "sg:tags":[
        "therapist",
        "marriage",
        "family"
    ],
    "wof:name":"Nicole Arkin, MFT",
    "wof:placetype":"venue"
},
  "geometry": {"coordinates":[-122.245114,37.817533],"type":"Point"}
}