{
  "type": "Feature",
  "properties": {
    "iso:country":"US",
    "sg:address":"1298 E 14th Street",
    "sg:city":"San Leandro",
    "sg:classifiers":[
        {
            "category":"Banks & Credit Unions",
            "subcategory":"Bank",
            "type":"Services"
        }
    ],
    "sg:phone":"+1 510 464 2557",
    "sg:postcode":"94577",
    "sg:province":"CA",
    "sg:website":"www.wellsfargo.com",
    "wof:name":"Wells Fargo Bank",
    "wof:placetype":"venue"
},
  "geometry": {"coordinates":[-122.156104,37.724991],"type":"Point"}
}