{
  "type": "Feature",
  "properties": {
    "addr:full":"17247 Main St Hesperia CA 92345",
    "addr:housenumber":"17247",
    "addr:postcode":"92345",
    "addr:street":"Main St",
    "iso:country":"US",
    "sg:address":"17247 Main St",
    "sg:city":"Hesperia",
    "sg:classifiers":[
        {
            "category":"Health Services",
            "subcategory":"Doctor",
            "type":"Services"
        }
    ],
    "sg:phone":"+1 760 244 2625",
    "sg:postcode":"92345",
    "sg:province":"CA",
    "sg:tags":[
        "dentist"
    ],
    "wof:name":"Desert Valley Dental Group",
    "wof:placetype":"venue"
},
  "geometry": {"coordinates":[-117.286564,34.419253],"type":"Point"}
}