{
  "type": "Feature",
  "properties": {
    "addr:full":"3300 Eastside Rd Ukiah CA 95482",
    "addr:housenumber":"3300",
    "addr:postcode":"ca 95482",
    "addr:street":"Eastside Rd",
    "iso:country":"US",
    "sg:address":"3300 Eastside Rd",
    "sg:city":"Ukiah",
    "sg:classifiers":[
        {
            "category":"Professional",
            "subcategory":"Management & Consulting",
            "type":"Services"
        },
        {
            "category":"Farming",
            "subcategory":"Farm & Veterinary Services",
            "type":"Manufacturing & Wholesale Goods"
        }
    ],
    "sg:phone":"+1 707 462 5438",
    "sg:postcode":"95482",
    "sg:province":"CA",
    "sg:tags":[
        "consultant",
        "business"
    ],
    "wof:name":"Chevalier Vineyard Management",
    "wof:placetype":"venue"
},
  "geometry": {"coordinates":[-123.158995,39.115162],"type":"Point"}
}