{
  "type": "Feature",
  "properties": {
    "iso:country":"US",
    "sg:address":"4237 Campus Dr Ste B-159",
    "sg:city":"Irvine",
    "sg:classifiers":[
        {
            "category":"Personal",
            "subcategory":"Massage",
            "type":"Services"
        },
        {
            "category":"Personal",
            "subcategory":"Skin Care",
            "type":"Services"
        }
    ],
    "sg:phone":"+1 949 854 2033",
    "sg:postcode":"92612",
    "sg:province":"CA",
    "sg:website":"www.irvinewhiterosespa.com/",
    "wof:name":"White Rose Spa",
    "wof:placetype":"venue"
},
  "geometry": {"coordinates":[-117.838765,33.650449],"type":"Point"}
}