{
  "type": "Feature",
  "properties": {
    "addr:full":"1618 28th Ave Oakland CA 94601",
    "addr:housenumber":"1618",
    "addr:postcode":"94601",
    "addr:street":"28Th Ave",
    "iso:country":"US",
    "sg:address":"1618 28th Ave",
    "sg:city":"Oakland",
    "sg:classifiers":[
        {
            "category":"Manufacturing",
            "subcategory":"Lumber",
            "type":"Manufacturing & Wholesale Goods"
        }
    ],
    "sg:phone":"+1 510 208 7257",
    "sg:postcode":"94601",
    "sg:province":"CA",
    "sg:tags":[
        "home",
        "mill",
        "garden"
    ],
    "sg:website":"www.earthsourcewood.com",
    "wof:name":"Earthsource Forest Products",
    "wof:placetype":"venue"
},
  "geometry": {"coordinates":[-122.227997,37.781601],"type":"Point"}
}