{
  "type": "Feature",
  "properties": {
    "addr:full":"18382 Bay Ave Tuolumne CA 95379",
    "addr:housenumber":"18382",
    "addr:postcode":"95379",
    "addr:street":"Bay Ave",
    "iso:country":"US",
    "sg:address":"18382 Bay Ave",
    "sg:city":"Tuolumne",
    "sg:classifiers":[
        {
            "category":"Personal",
            "subcategory":"Tattoo Parlor",
            "type":"Services"
        }
    ],
    "sg:phone":"+1 209 928 1968",
    "sg:postcode":"95379",
    "sg:province":"CA",
    "sg:tags":[
        "tattooing"
    ],
    "wof:name":"West Side Ink",
    "wof:placetype":"venue"
},
  "geometry": {"coordinates":[-120.23835200000001,37.961391],"type":"Point"}
}