{
  "type": "Feature",
  "properties": {
    "iso:country":"US",
    "sg:address":"Horton Plaza 324 Horton Plz Ste 261",
    "sg:city":"San Diego",
    "sg:classifiers":[
        {
            "category":"Shopping",
            "type":"Retail Goods"
        }
    ],
    "sg:phone":"+1 619 237 1269",
    "sg:postcode":"92101",
    "sg:province":"CA",
    "sg:website":"www.spirithalloween.com",
    "wof:name":"Spirit Halloween",
    "wof:placetype":"venue"
},
  "geometry": {"coordinates":[-117.162423,32.713668],"type":"Point"}
}