{
  "type": "Feature",
  "properties": {
    "iso:country":"US",
    "sg:address":"12510 Magnolia Ave",
    "sg:city":"Riverside",
    "sg:phone":"+1 951 372 9203",
    "sg:postcode":"92503",
    "sg:province":"CA",
    "wof:name":"L & A Mufflers",
    "wof:placetype":"venue"
},
  "geometry": {"coordinates":[-117.502668,33.888302],"type":"Point"}
}