{
  "type": "Feature",
  "properties": {
    "addr:full":"38905 Rancho Los Cerritos Dr Indio CA 92203",
    "addr:housenumber":"38905",
    "addr:postcode":"92203",
    "addr:street":"Rancho Los Cerritos Dr",
    "iso:country":"US",
    "sg:address":"38905 Rancho Los Cerritos Dr",
    "sg:city":"Indio",
    "sg:classifiers":[
        {
            "category":"Building & Trades",
            "subcategory":"Landscaping Services",
            "type":"Services"
        }
    ],
    "sg:phone":"+1 760 345 5659",
    "sg:postcode":"92203",
    "sg:province":"CA",
    "sg:tags":[
        "landscape",
        "contractor"
    ],
    "wof:name":"Lakewood Landscape",
    "wof:placetype":"venue"
},
  "geometry": {"coordinates":[-116.283191,33.766436],"type":"Point"}
}