{
  "type": "Feature",
  "properties": {
    "addr:full":"3703 Carter Dr South San Francisco CA 94080",
    "addr:housenumber":"3703",
    "addr:postcode":"94080",
    "addr:street":"Carter Dr",
    "iso:country":"US",
    "sg:address":"3703 Carter Dr",
    "sg:city":"South San Francisco",
    "sg:classifiers":[
        {
            "category":"Wholesale",
            "subcategory":"Auto Parts",
            "type":"Manufacturing & Wholesale Goods"
        }
    ],
    "sg:phone":"+1 650 871 7628",
    "sg:postcode":"94080",
    "sg:province":"CA",
    "wof:name":"Mic Company",
    "wof:placetype":"venue"
},
  "geometry": {"coordinates":[-122.466357,37.644613],"type":"Point"}
}