{
  "type": "Feature",
  "properties": {
    "iso:country":"US",
    "sg:address":"204 N Broadway",
    "sg:city":"Santa Ana",
    "sg:classifiers":[
        {
            "category":"Professional",
            "type":"Services"
        }
    ],
    "sg:phone":"+1 714 953 9501",
    "sg:postcode":"92701",
    "sg:province":"CA",
    "sg:tags":[
        "establishment"
    ],
    "wof:name":"An Ideal World",
    "wof:placetype":"venue"
},
  "geometry": {"coordinates":[-117.869815,33.747094],"type":"Point"}
}