{
  "type": "Feature",
  "properties": {
    "iso:country":"US",
    "sg:address":"687 Agua Mansa Rd",
    "sg:city":"Colton",
    "sg:classifiers":[
        {
            "category":"Real Estate",
            "subcategory":"Real Estate Services",
            "type":"Services"
        },
        {
            "category":"Real Estate",
            "subcategory":"Real Estate Agent",
            "type":"Services"
        }
    ],
    "sg:phone":"+1 909 824 3867",
    "sg:postcode":"92324",
    "sg:province":"CA",
    "sg:tags":[
        "management"
    ],
    "wof:name":"Agua Mansa Properties Inc.",
    "wof:placetype":"venue"
},
  "geometry": {"coordinates":[-117.33752200000001,34.053592],"type":"Point"}
}