{
  "type": "Feature",
  "properties": {
    "addr:full":"110 Plymouth Street Santa Cruz CA 95060",
    "addr:housenumber":"110",
    "addr:postcode":"95060",
    "addr:street":"Plymouth Street",
    "iso:country":"US",
    "sg:address":"110 Plymouth Street",
    "sg:city":"Santa Cruz",
    "sg:classifiers":[
        {
            "category":"Travel",
            "subcategory":"Hotels & Motels",
            "type":"Entertainment"
        }
    ],
    "sg:phone":"+1 831 426 2664",
    "sg:postcode":"95060",
    "sg:province":"CA",
    "sg:website":"www.comfortinnsantacruz.com",
    "wof:name":"Santa Cruz Motel Comfort Inn",
    "wof:placetype":"venue"
},
  "geometry": {"coordinates":[-122.022767,36.984765],"type":"Point"}
}