{
  "type": "Feature",
  "properties": {
    "iso:country":"US",
    "sg:address":"2381 Zanker Road Suite 170",
    "sg:city":"San Jose",
    "sg:classifiers":[
        {
            "category":"Professional",
            "subcategory":"Computer Services",
            "type":"Services"
        }
    ],
    "sg:phone":"+1 408 434 9393",
    "sg:postcode":"95131",
    "sg:province":"CA",
    "sg:tags":[
        "repair"
    ],
    "sg:website":"www.networksound.com",
    "wof:name":"Networksound",
    "wof:placetype":"venue"
},
  "geometry": {"coordinates":[-121.920069,37.384209],"type":"Point"}
}