{
  "type": "Feature",
  "properties": {
    "iso:country":"US",
    "sg:address":"5520 South St",
    "sg:city":"Lakewood",
    "sg:classifiers":[
        {
            "category":"Restaurant",
            "type":"Food & Drink"
        }
    ],
    "sg:phone":"+1 562 866 6100",
    "sg:postcode":"90713",
    "sg:province":"CA",
    "sg:tags":[
        "diner"
    ],
    "sg:website":"www.dennys.com",
    "wof:name":"Denny's",
    "wof:placetype":"venue"
},
  "geometry": {"coordinates":[-118.124071,33.859773],"type":"Point"}
}