{
  "type": "Feature",
  "properties": {
    "iso:country":"US",
    "sg:address":"550 S Hope St",
    "sg:city":"Los Angeles",
    "sg:classifiers":[
        {
            "category":"Professional",
            "subcategory":"Lawyer & Legal Services",
            "type":"Services"
        }
    ],
    "sg:phone":"+1 213 892 1800",
    "sg:postcode":"90071",
    "sg:province":"CA",
    "wof:name":"Eliseev Andrew",
    "wof:placetype":"venue"
},
  "geometry": {"coordinates":[-118.25599699999999,34.049702],"type":"Point"}
}