{
  "type": "Feature",
  "properties": {
    "addr:full":"758 Stockton St San Francisco CA 94108",
    "addr:housenumber":"758",
    "addr:postcode":"94108",
    "addr:street":"Stockton St",
    "iso:country":"US",
    "sg:address":"758 Stockton St",
    "sg:city":"San Francisco",
    "sg:classifiers":[
        {
            "category":"Personal",
            "subcategory":"Beauty Salon",
            "type":"Services"
        }
    ],
    "sg:phone":"+1 415 391 0203",
    "sg:postcode":"94108",
    "sg:province":"CA",
    "wof:name":"Ping's Beauty Styling",
    "wof:placetype":"venue"
},
  "geometry": {"coordinates":[-122.407636,37.793086],"type":"Point"}
}