{
  "type": "Feature",
  "properties": {
    "iso:country":"US",
    "sg:address":"8552 Beach Blvd.",
    "sg:city":"Buena Park",
    "sg:classifiers":[
        {
            "category":"Restaurant",
            "type":"Food & Drink"
        }
    ],
    "sg:phone":"+1 714 828 1363",
    "sg:postcode":"90620",
    "sg:province":"CA",
    "sg:tags":[
        "korean"
    ],
    "wof:name":"Dah-Sohm Korean BBQ",
    "wof:placetype":"venue"
},
  "geometry": {"coordinates":[-117.994129,33.836666],"type":"Point"}
}