{
  "type": "Feature",
  "properties": {
    "addr:full":"3200 Bell Rd Auburn CA 95603",
    "addr:housenumber":"3200",
    "addr:postcode":"ca 95603",
    "addr:street":"Bell Rd",
    "iso:country":"US",
    "sg:address":"3200 Bell Rd",
    "sg:city":"Auburn",
    "sg:classifiers":[
        {
            "category":"Health Services",
            "subcategory":"Doctor",
            "type":"Services"
        }
    ],
    "sg:phone":"+1 530 888 7616",
    "sg:postcode":"95603",
    "sg:province":"CA",
    "sg:tags":[
        "physician",
        "pediatrics-emergency",
        "pediatrics",
        "family",
        "cardiology",
        "practice",
        "surgeons",
        "medicine",
        "surgeon"
    ],
    "sg:website":"http://www.sportsmedicine.ucdavis.edu",
    "wof:name":"U C Davis Medical Group",
    "wof:placetype":"venue"
},
  "geometry": {"coordinates":[-121.102727,38.941908],"type":"Point"}
}