{
  "type": "Feature",
  "properties": {
    "iso:country":"US",
    "sg:address":"210 Barstow Ave",
    "sg:city":"Clovis",
    "sg:classifiers":[
        {
            "category":"Social Services",
            "type":"Services"
        }
    ],
    "sg:phone":"+1 559 298 6797",
    "sg:postcode":"93612",
    "sg:province":"CA",
    "sg:tags":[
        "organization",
        "welfare"
    ],
    "sg:website":"www.salvationarmy.org",
    "wof:name":"Salvation Army",
    "wof:placetype":"venue"
},
  "geometry": {"coordinates":[-119.707134,36.815665],"type":"Point"}
}