{
  "type": "Feature",
  "properties": {
    "iso:country":"US",
    "sg:address":"11422 Moorpark St",
    "sg:city":"North Hollywood",
    "sg:classifiers":[
        {
            "category":"Shopping",
            "subcategory":"Used Merchandise",
            "type":"Retail Goods"
        }
    ],
    "sg:phone":"+1 818 755 9559",
    "sg:postcode":"91602",
    "sg:province":"CA",
    "sg:tags":[
        "vintage",
        "clothing",
        "costume",
        "store"
    ],
    "sg:website":"www.vintageplayclothes.com",
    "wof:name":"Playclothes",
    "wof:placetype":"venue"
},
  "geometry": {"coordinates":[-118.379918,34.15008],"type":"Point"}
}