{
  "type": "Feature",
  "properties": {
    "iso:country":"US",
    "sg:address":"345 W Valley Blvd",
    "sg:city":"Colton",
    "sg:classifiers":[
        {
            "category":"Professional",
            "subcategory":"Business Services",
            "type":"Services"
        }
    ],
    "sg:phone":"+1 909 825 6744",
    "sg:postcode":"92324",
    "sg:province":"CA",
    "sg:tags":[
        "recording",
        "studio"
    ],
    "wof:name":"Spectrotape Corp",
    "wof:placetype":"venue"
},
  "geometry": {"coordinates":[-117.328633,34.067638],"type":"Point"}
}