{
  "type": "Feature",
  "properties": {
    "iso:country":"US",
    "sg:address":"37 Washington St",
    "sg:city":"Santa Clara",
    "sg:classifiers":[
        {
            "category":"Retail",
            "subcategory":"Portrait Studio",
            "type":"Services"
        }
    ],
    "sg:phone":"+1 408 264 7523",
    "sg:postcode":"95050",
    "sg:province":"CA",
    "sg:tags":[
        "photographer",
        "wedding"
    ],
    "sg:website":"www.gebelein.com",
    "wof:name":"Gebelein Photographers",
    "wof:placetype":"venue"
},
  "geometry": {"coordinates":[-121.93858,37.33902],"type":"Point"}
}