{
  "type": "Feature",
  "properties": {
    "iso:country":"US",
    "sg:address":"39605 Los Alamos Rd",
    "sg:city":"Murrieta",
    "sg:classifiers":[
        {
            "category":"Shopping",
            "subcategory":"Bicycles & Sporting Goods",
            "type":"Retail Goods"
        }
    ],
    "sg:phone":"+1 951 698 9544",
    "sg:postcode":"92563",
    "sg:province":"CA",
    "sg:tags":[
        "security",
        "system",
        "rack"
    ],
    "wof:name":"I E Bikes Inc.",
    "wof:placetype":"venue"
},
  "geometry": {"coordinates":[-117.178697,33.574012],"type":"Point"}
}