{
  "type": "Feature",
  "properties": {
    "addr:full":"2598 Cherry Ave Signal Hill CA 90755",
    "addr:housenumber":"2598",
    "addr:postcode":"90755",
    "addr:street":"Cherry Ave",
    "iso:country":"US",
    "sg:address":"2598 Cherry Ave",
    "sg:city":"Signal Hill",
    "sg:classifiers":[
        {
            "category":"Banks & Credit Unions",
            "subcategory":"Bank",
            "type":"Services"
        }
    ],
    "sg:phone":"+1 562 492 5260",
    "sg:postcode":"90755",
    "sg:province":"CA",
    "sg:website":"www.wellsfargo.com",
    "wof:name":"Wells Fargo",
    "wof:placetype":"venue"
},
  "geometry": {"coordinates":[-118.16756100000001,33.804333],"type":"Point"}
}