{
  "type": "Feature",
  "properties": {
    "addr:full":"23077 Enadia Way Canoga Park CA 91307",
    "addr:postcode":"23077;91307",
    "addr:street":"Enadia Way",
    "iso:country":"US",
    "sg:address":"23077 Enadia Way",
    "sg:city":"Canoga Park",
    "sg:classifiers":[
        {
            "category":"Wholesale",
            "subcategory":"Vending Machines",
            "type":"Manufacturing & Wholesale Goods"
        }
    ],
    "sg:phone":"+1 818 999 3797",
    "sg:postcode":"91307",
    "sg:province":"CA",
    "sg:tags":[
        "operator"
    ],
    "wof:name":"Davis Vending",
    "wof:placetype":"venue"
},
  "geometry": {"coordinates":[-118.628675,34.200097],"type":"Point"}
}