{
  "type": "Feature",
  "properties": {
    "addr:full":"129 Fillmore St. San Francisco CA 94117",
    "addr:housenumber":"129",
    "addr:postcode":"94117",
    "addr:street":"Fillmore St.",
    "iso:country":"US",
    "sg:address":"129 Fillmore St.",
    "sg:city":"San Francisco",
    "sg:classifiers":[
        {
            "category":"Personal",
            "subcategory":"Massage",
            "type":"Services"
        },
        {
            "category":"Health Services",
            "subcategory":"Health Practitioner",
            "type":"Services"
        }
    ],
    "sg:phone":"+1 415 722 9848",
    "sg:postcode":"94117",
    "sg:province":"CA",
    "sg:tags":[
        "acupuncture"
    ],
    "wof:name":"Anne Perkins, RN, LAc",
    "wof:placetype":"venue"
},
  "geometry": {"coordinates":[-122.430278,37.770764],"type":"Point"}
}