{
  "type": "Feature",
  "properties": {
    "iso:country":"US",
    "sg:address":"926 N Wilmington Blvd",
    "sg:city":"Wilmington",
    "sg:classifiers":[
        {
            "category":"Real Estate",
            "subcategory":"Real Estate Services",
            "type":"Services"
        }
    ],
    "sg:phone":"+1 310 549 0151",
    "sg:postcode":"90744",
    "sg:province":"CA",
    "sg:tags":[
        "management",
        "property"
    ],
    "wof:name":"Swami International",
    "wof:placetype":"venue"
},
  "geometry": {"coordinates":[-118.274144,33.78115],"type":"Point"}
}