{
  "type": "Feature",
  "properties": {
    "iso:country":"US",
    "sg:address":"539 Main St",
    "sg:city":"Woodland",
    "sg:classifiers":[
        {
            "category":"Shopping",
            "subcategory":"Clothing, Apparel, & Fashions",
            "type":"Retail Goods"
        }
    ],
    "sg:phone":"+1 530 662 2754",
    "sg:postcode":"95695",
    "sg:province":"CA",
    "sg:tags":[
        "western"
    ],
    "wof:name":"Diamond-E-Western Shop",
    "wof:placetype":"venue"
},
  "geometry": {"coordinates":[-121.773737,38.677582],"type":"Point"}
}