{
  "type": "Feature",
  "properties": {
    "iso:country":"US",
    "sg:address":"803 Winston Ave",
    "sg:city":"San Marino",
    "sg:classifiers":[
        {
            "category":"Banks & Credit Unions",
            "subcategory":"Investment Brokerage",
            "type":"Services"
        }
    ],
    "sg:phone":"+1 626 793 3761",
    "sg:postcode":"91108",
    "sg:province":"CA",
    "sg:tags":[
        "security"
    ],
    "wof:name":"Shilyansky Mda Professional Co",
    "wof:placetype":"venue"
},
  "geometry": {"coordinates":[-118.10040499999999,34.131669],"type":"Point"}
}