{
  "type": "Feature",
  "properties": {
    "addr:full":"13983 Chicarita Creek Rd San Diego CA 92128",
    "addr:housenumber":"13983",
    "addr:postcode":"92128",
    "addr:street":"Chicarita Creek Rd",
    "iso:country":"US",
    "sg:address":"13983 Chicarita Creek Rd",
    "sg:city":"San Diego",
    "sg:classifiers":[
        {
            "category":"Building & Trades",
            "subcategory":"Construction",
            "type":"Services"
        }
    ],
    "sg:phone":"+1 619 464 7443",
    "sg:postcode":"92128",
    "sg:province":"CA",
    "sg:tags":[
        "coping",
        "plastering",
        "tiling",
        "pool",
        "swimming"
    ],
    "wof:name":"Ocean Blue Pool Svc",
    "wof:placetype":"venue"
},
  "geometry": {"coordinates":[-117.08757300000001,32.974978],"type":"Point"}
}