{
  "type": "Feature",
  "properties": {
    "iso:country":"US",
    "sg:address":"299 14th Ave",
    "sg:city":"San Francisco",
    "sg:classifiers":[
        {
            "category":"Shopping",
            "subcategory":"Computers & Home Electronics",
            "type":"Retail Goods"
        }
    ],
    "sg:phone":"+1 415 752 2326",
    "sg:postcode":"94118",
    "sg:province":"CA",
    "sg:tags":[
        "equipment",
        "dealer"
    ],
    "wof:name":"Ay Computer System",
    "wof:placetype":"venue"
},
  "geometry": {"coordinates":[-122.47312,37.784421],"type":"Point"}
}