{
  "type": "Feature",
  "properties": {
    "addr:full":"14640 Mercado Ave La Mirada CA 90638",
    "addr:housenumber":"14640",
    "addr:postcode":"90638",
    "addr:street":"Mercado Ave",
    "iso:country":"US",
    "sg:address":"14640 Mercado Ave",
    "sg:city":"La Mirada",
    "sg:classifiers":[
        {
            "category":"Building & Trades",
            "subcategory":"Construction",
            "type":"Services"
        }
    ],
    "sg:phone":"+1 714 670 6540",
    "sg:postcode":"90638",
    "sg:province":"CA",
    "sg:tags":[
        "contractor"
    ],
    "wof:name":"USS Cal Builders Inc",
    "wof:placetype":"venue"
},
  "geometry": {"coordinates":[-117.99014200000001,33.899364],"type":"Point"}
}