{
  "type": "Feature",
  "properties": {
    "addr:full":"4475 E Tulare Ave Fresno CA 93702",
    "addr:housenumber":"4475",
    "addr:postcode":"93702",
    "addr:street":"E Tulare Ave",
    "iso:country":"US",
    "sg:address":"4475 E Tulare Ave",
    "sg:city":"Fresno",
    "sg:classifiers":[
        {
            "category":"Government",
            "subcategory":"Post Office",
            "type":"Public Place"
        }
    ],
    "sg:phone":"+1 559 000 1111",
    "sg:postcode":"93702",
    "sg:province":"CA",
    "wof:name":"US Post Office",
    "wof:placetype":"venue"
},
  "geometry": {"coordinates":[-119.75140399999999,36.743216],"type":"Point"}
}