{
  "type": "Feature",
  "properties": {
    "addr:full":"18618 Oxnard St Tarzana CA 91356",
    "addr:housenumber":"18618",
    "addr:postcode":"91356",
    "addr:street":"Oxnard St",
    "iso:country":"US",
    "sg:address":"18618 Oxnard St",
    "sg:city":"Tarzana",
    "sg:classifiers":[
        {
            "category":"Education",
            "subcategory":"College",
            "type":"Public Place"
        }
    ],
    "sg:phone":"+1 818 345 8414",
    "sg:postcode":"91356",
    "sg:province":"CA",
    "sg:tags":[
        "academic",
        "school"
    ],
    "sg:website":"www.columbiacollege.edu",
    "wof:name":"Columbia College",
    "wof:placetype":"venue"
},
  "geometry": {"coordinates":[-118.540181,34.179915],"type":"Point"}
}