{
  "type": "Feature",
  "properties": {
    "addr:full":"2900 Skyway Dr Santa Maria CA 93455",
    "addr:housenumber":"2900",
    "addr:postcode":"93455",
    "addr:street":"Skyway Dr",
    "iso:country":"US",
    "sg:address":"2900 Skyway Dr",
    "sg:city":"Santa Maria",
    "sg:classifiers":[
        {
            "category":"Wholesale",
            "subcategory":"Electrical",
            "type":"Manufacturing & Wholesale Goods"
        }
    ],
    "sg:phone":"+1 805 922 6682",
    "sg:postcode":"93455",
    "sg:province":"CA",
    "sg:tags":[
        "wire",
        "cable"
    ],
    "sg:website":"www.okonite.com",
    "wof:name":"Okonite Co",
    "wof:placetype":"venue"
},
  "geometry": {"coordinates":[-120.454077,34.909495],"type":"Point"}
}