{
  "type": "Feature",
  "properties": {
    "addr:full":"9267 Greenback Ln Orangevale CA 95662",
    "addr:housenumber":"9267",
    "addr:postcode":"95662",
    "addr:street":"Greenback Ln",
    "iso:country":"US",
    "sg:address":"9267 Greenback Ln",
    "sg:city":"Orangevale",
    "sg:classifiers":[
        {
            "category":"Building & Trades",
            "subcategory":"Construction",
            "type":"Services"
        }
    ],
    "sg:phone":"+1 916 791 5935",
    "sg:postcode":"95662",
    "sg:province":"CA",
    "sg:tags":[
        "home",
        "builder"
    ],
    "wof:name":"Beezlees Fine Topiaries & Home",
    "wof:placetype":"venue"
},
  "geometry": {"coordinates":[-121.20791199999999,38.67828],"type":"Point"}
}