{
  "type": "Feature",
  "properties": {
    "addr:full":"5702 Lincoln Ave Cypress CA 90630",
    "addr:housenumber":"5702",
    "addr:postcode":"90630",
    "addr:street":"Lincoln Ave",
    "iso:country":"US",
    "sg:address":"5702 Lincoln Ave",
    "sg:city":"Cypress",
    "sg:classifiers":[
        {
            "category":"Building & Trades",
            "subcategory":"Landscaping Services",
            "type":"Services"
        }
    ],
    "sg:phone":"+1 714 827 9113",
    "sg:postcode":"90630",
    "sg:province":"CA",
    "wof:name":"Cypress Landscape Maintenance",
    "wof:placetype":"venue"
},
  "geometry": {"coordinates":[-118.03231700000001,33.831721],"type":"Point"}
}