{
  "type": "Feature",
  "properties": {
    "iso:country":"US",
    "sg:address":"6838 Cumberland Pl",
    "sg:city":"Stockton",
    "sg:classifiers":[
        {
            "category":"Wholesale",
            "subcategory":"Non-durable Goods",
            "type":"Manufacturing & Wholesale Goods"
        }
    ],
    "sg:phone":"+1 209 951 7550",
    "sg:postcode":"95219",
    "sg:province":"CA",
    "wof:name":"S&L Distributing",
    "wof:placetype":"venue"
},
  "geometry": {"coordinates":[-121.363258,38.010289],"type":"Point"}
}