{
  "type": "Feature",
  "properties": {
    "addr:full":"19121 Ballinger St Northridge CA 91324",
    "addr:housenumber":"19121",
    "addr:postcode":"91324",
    "addr:street":"Ballinger St",
    "iso:country":"US",
    "sg:address":"19121 Ballinger St",
    "sg:city":"Northridge",
    "sg:classifiers":[
        {
            "category":"Shopping",
            "type":"Retail Goods"
        }
    ],
    "sg:phone":"+1 818 886 3037",
    "sg:postcode":"91324",
    "sg:province":"CA",
    "sg:tags":[
        "equipment",
        "medical",
        "supply"
    ],
    "wof:name":"Orange County Medical Sales",
    "wof:placetype":"venue"
},
  "geometry": {"coordinates":[-118.55048600000001,34.243931],"type":"Point"}
}