{
  "type": "Feature",
  "properties": {
    "iso:country":"US",
    "sg:address":"470 S Norfolk Street",
    "sg:city":"San Mateo",
    "sg:classifiers":[
        {
            "category":"Personal",
            "subcategory":"Beauty Salon",
            "type":"Services"
        },
        {
            "category":"Personal",
            "subcategory":"Barber",
            "type":"Services"
        }
    ],
    "sg:phone":"+1 650 347 9704",
    "sg:postcode":"94401",
    "sg:province":"CA",
    "sg:tags":[
        "spa"
    ],
    "wof:name":"Shoreview Barbershop",
    "wof:placetype":"venue"
},
  "geometry": {"coordinates":[-122.310039,37.571704],"type":"Point"}
}