{
  "type": "Feature",
  "properties": {
    "addr:full":"100 N D St Perris CA 92570",
    "addr:housenumber":"100",
    "addr:postcode":"92570",
    "addr:street":"N D St",
    "iso:country":"US",
    "sg:address":"100 N D St",
    "sg:city":"Perris",
    "sg:classifiers":[
        {
            "category":"Social Services",
            "type":"Services"
        }
    ],
    "sg:phone":"+1 951 657 7334",
    "sg:postcode":"92570",
    "sg:province":"CA",
    "sg:tags":[
        "executive"
    ],
    "wof:name":"Perris Senior Citizen Center",
    "wof:placetype":"venue"
},
  "geometry": {"coordinates":[-117.22860300000001,33.789661],"type":"Point"}
}