{
  "type": "Feature",
  "properties": {
    "iso:country":"US",
    "sg:address":"5521 W Commercial St",
    "sg:city":"Chico",
    "sg:classifiers":[
        {
            "category":"Retail",
            "subcategory":"Auto Repair",
            "type":"Services"
        }
    ],
    "sg:phone":"+1 530 899 2600",
    "sg:postcode":"95973",
    "sg:province":"CA",
    "sg:tags":[
        "repairing",
        "automobile"
    ],
    "wof:name":"Nord Garage",
    "wof:placetype":"venue"
},
  "geometry": {"coordinates":[-121.95612300000001,39.778276],"type":"Point"}
}