{
  "type": "Feature",
  "properties": {
    "addr:full":"6398 Del Cerro Boulevard San Diego CA 92120",
    "addr:housenumber":"6398",
    "addr:postcode":"92120",
    "addr:street":"Del Cerro Boulevard",
    "iso:country":"US",
    "sg:address":"6398 Del Cerro Boulevard",
    "sg:city":"San Diego",
    "sg:classifiers":[
        {
            "category":"Professional",
            "subcategory":"Accounting & Tax Preparation",
            "type":"Services"
        }
    ],
    "sg:phone":"+1 619 286 6500",
    "sg:postcode":"92120",
    "sg:province":"CA",
    "sg:tags":[
        "accountant"
    ],
    "wof:name":"McGuire Joseph McGuire CPA",
    "wof:placetype":"venue"
},
  "geometry": {"coordinates":[-117.059111,32.782885],"type":"Point"}
}