{
  "type": "Feature",
  "properties": {
    "addr:full":"500 Lincoln Ave Alameda CA 94501",
    "addr:housenumber":"500",
    "addr:postcode":"94501",
    "addr:street":"Lincoln Ave",
    "iso:country":"US",
    "sg:address":"500 Lincoln Ave",
    "sg:city":"Alameda",
    "sg:classifiers":[
        {
            "category":"Food & Beverages",
            "subcategory":"Groceries & Convenience Stores",
            "type":"Retail Goods"
        }
    ],
    "sg:phone":"+1 510 523 0174",
    "sg:postcode":"94501",
    "sg:province":"CA",
    "wof:name":"Golden Seven Foodstore",
    "wof:placetype":"venue"
},
  "geometry": {"coordinates":[-122.28231700000001,37.775176],"type":"Point"}
}