{
  "type": "Feature",
  "properties": {
    "iso:country":"US",
    "sg:address":"1072 S De Anza Blvd Ste A-208",
    "sg:city":"San Jose",
    "sg:classifiers":[
        {
            "category":"Real Estate",
            "subcategory":"Real Estate Services",
            "type":"Services"
        },
        {
            "category":"Banks & Credit Unions",
            "subcategory":"Financial Services",
            "type":"Services"
        },
        {
            "category":"Real Estate",
            "subcategory":"Real Estate Agent",
            "type":"Services"
        }
    ],
    "sg:phone":"+1 408 387 8080",
    "sg:postcode":"95129",
    "sg:province":"CA",
    "sg:tags":[
        "broker",
        "mortgage"
    ],
    "sg:website":"www.realtorcocotan.com",
    "wof:name":"Baycal Realty and Financial",
    "wof:placetype":"venue"
},
  "geometry": {"coordinates":[-122.032141,37.307149],"type":"Point"}
}