{
  "type": "Feature",
  "properties": {
    "iso:country":"US",
    "sg:address":"2021 The Alameda Ste 275",
    "sg:city":"San Jose",
    "sg:classifiers":[
        {
            "category":"Professional",
            "subcategory":"Lawyer & Legal Services",
            "type":"Services"
        }
    ],
    "sg:phone":"+1 408 297 2277",
    "sg:postcode":"95126",
    "sg:province":"CA",
    "sg:website":"www.bucherlaw.com",
    "wof:name":"Bucher Law Office",
    "wof:placetype":"venue"
},
  "geometry": {"coordinates":[-121.928051,37.342714],"type":"Point"}
}