{
  "type": "Feature",
  "properties": {
    "iso:country":"US",
    "sg:address":"5562 Lenahan Rd",
    "sg:city":"Willows",
    "sg:classifiers":[
        {
            "category":"Real Estate",
            "subcategory":"Real Estate Operator",
            "type":"Services"
        }
    ],
    "sg:phone":"+1 530 438 2447",
    "sg:postcode":"95955",
    "sg:province":"CA",
    "sg:tags":[
        "property",
        "lessor"
    ],
    "wof:name":"McGeoghegan Farm",
    "wof:placetype":"venue"
},
  "geometry": {"coordinates":[-122.178691,39.334381],"type":"Point"}
}