{
  "type": "Feature",
  "properties": {
    "addr:full":"2800 Harbor Boulevard Suite C Costa Mesa CA 92626",
    "addr:housenumber":"2800",
    "addr:postcode":"92626",
    "addr:street":"Harbor Boulevard Suite C",
    "iso:country":"US",
    "sg:address":"2800 Harbor Boulevard Suite C",
    "sg:city":"Costa Mesa",
    "sg:classifiers":[
        {
            "category":"Juice Bar",
            "subcategory":"None",
            "type":"Food & Drink"
        },
        {
            "category":"Coffee & Tea",
            "type":"Food & Drink"
        },
        {
            "category":"Internet Cafe",
            "subcategory":"None",
            "type":"Food & Drink"
        }
    ],
    "sg:phone":"+1 714 444 9757",
    "sg:postcode":"92626",
    "sg:province":"CA",
    "sg:tags":[
        "smoothy"
    ],
    "sg:website":"www.natalecoffeecostamesa.com/",
    "wof:name":"Nata'le Coffee",
    "wof:placetype":"venue"
},
  "geometry": {"coordinates":[-117.919209,33.67339],"type":"Point"}
}