{
  "type": "Feature",
  "properties": {
    "addr:full":"13415 Estelle St Corona CA 92879",
    "addr:housenumber":"13415",
    "addr:postcode":"92879",
    "addr:street":"Estelle St",
    "iso:country":"US",
    "sg:address":"13415 Estelle St",
    "sg:city":"Corona",
    "sg:classifiers":[
        {
            "category":"Manufacturing",
            "subcategory":"Food",
            "type":"Manufacturing & Wholesale Goods"
        },
        {
            "category":"Food & Beverages",
            "subcategory":"Supermarket",
            "type":"Retail Goods"
        }
    ],
    "sg:phone":"+1 951 371 3123",
    "sg:postcode":"92879",
    "sg:province":"CA",
    "sg:tags":[
        "product",
        "processing",
        "super",
        "store"
    ],
    "sg:website":"http://www.pacificafoods.net",
    "wof:name":"Pacifica Foods",
    "wof:placetype":"venue"
},
  "geometry": {"coordinates":[-117.518422,33.881686],"type":"Point"}
}