{
  "type": "Feature",
  "properties": {
    "addr:full":"4719 Greenleaf Ct Modesto CA 95356",
    "addr:housenumber":"4719",
    "addr:postcode":"ca 95356",
    "addr:street":"Greenleaf Ct",
    "iso:country":"US",
    "sg:address":"4719 Greenleaf Ct",
    "sg:city":"Modesto",
    "sg:classifiers":[
        {
            "category":"Banks & Credit Unions",
            "subcategory":"Investment Brokerage",
            "type":"Services"
        }
    ],
    "sg:phone":"+1 209 543 8666",
    "sg:postcode":"95356",
    "sg:province":"CA",
    "sg:tags":[
        "consultant",
        "planning",
        "financial"
    ],
    "wof:name":"Citizens Financial Security",
    "wof:placetype":"venue"
},
  "geometry": {"coordinates":[-121.070803,37.701818],"type":"Point"}
}