{
  "type": "Feature",
  "properties": {
    "addr:full":"715 I St Modesto CA 95354",
    "addr:housenumber":"715",
    "addr:postcode":"ca 95354",
    "addr:street":"I St",
    "iso:country":"US",
    "sg:address":"715 I St",
    "sg:city":"Modesto",
    "sg:classifiers":[
        {
            "category":"Home & Garden",
            "subcategory":"Furniture",
            "type":"Retail Goods"
        }
    ],
    "sg:phone":"+1 209 521 8220",
    "sg:postcode":"95354",
    "sg:province":"CA",
    "wof:name":"Elegant Furniture",
    "wof:placetype":"venue"
},
  "geometry": {"coordinates":[-121.001212,37.638083],"type":"Point"}
}