{
  "type": "Feature",
  "properties": {
    "addr:full":"556 Windward Way Sacramento CA 95831",
    "addr:housenumber":"556",
    "addr:postcode":"95831",
    "addr:street":"Windward Way",
    "iso:country":"US",
    "sg:address":"556 Windward Way",
    "sg:city":"Sacramento",
    "sg:classifiers":[
        {
            "category":"Professional",
            "subcategory":"Management & Consulting",
            "type":"Services"
        },
        {
            "category":"Professional",
            "subcategory":"Advertising",
            "type":"Services"
        }
    ],
    "sg:phone":"+1 916 733 1609",
    "sg:postcode":"95831",
    "sg:province":"CA",
    "sg:tags":[
        "marketing",
        "program",
        "consultant"
    ],
    "wof:name":"Senoj Marketing & Pr",
    "wof:placetype":"venue"
},
  "geometry": {"coordinates":[-121.54178899999999,38.506812],"type":"Point"}
}