{
  "type": "Feature",
  "properties": {
    "iso:country":"US",
    "sg:address":"1098 N Western Avenue",
    "sg:city":"Los Angeles",
    "sg:classifiers":[
        {
            "category":"Shopping",
            "subcategory":"Shoes",
            "type":"Retail Goods"
        }
    ],
    "sg:phone":"+1 323 469 1774",
    "sg:postcode":"90029",
    "sg:province":"CA",
    "sg:tags":[
        "store"
    ],
    "wof:name":"Payless Shoe Source",
    "wof:placetype":"venue"
},
  "geometry": {"coordinates":[-118.30905300000001,34.090581],"type":"Point"}
}