{
  "type": "Feature",
  "properties": {
    "addr:full":"42515 22nd St W Quartz Hill CA 93536",
    "addr:housenumber":"42515",
    "addr:postcode":"93536",
    "addr:street":"22Nd St W Quartz Hill",
    "iso:country":"US",
    "sg:address":"42515 22nd St W",
    "sg:city":"Quartz Hill",
    "sg:classifiers":[
        {
            "category":"Organizations",
            "subcategory":"Religious Organization",
            "type":"Services"
        }
    ],
    "sg:phone":"+1 661 943 1878",
    "sg:postcode":"93536",
    "sg:province":"CA",
    "sg:tags":[
        "church"
    ],
    "wof:name":"Lancaster Missionary Church",
    "wof:placetype":"venue"
},
  "geometry": {"coordinates":[-118.170109,34.6551],"type":"Point"}
}