{
  "type": "Feature",
  "properties": {
    "addr:full":"4528 Utah St San Diego CA 92116",
    "addr:housenumber":"4528",
    "addr:postcode":"92116",
    "addr:street":"Utah St",
    "iso:country":"US",
    "sg:address":"4528 Utah St",
    "sg:city":"San Diego",
    "sg:classifiers":[
        {
            "category":"Education",
            "subcategory":"Special Training",
            "type":"Public Place"
        }
    ],
    "sg:phone":"+1 619 283 0017",
    "sg:postcode":"92116",
    "sg:province":"CA",
    "wof:name":"Freedom Academy Kung Fu School",
    "wof:placetype":"venue"
},
  "geometry": {"coordinates":[-117.132735,32.760479],"type":"Point"}
}