{
  "type": "Feature",
  "properties": {
    "iso:country":"US",
    "sg:address":"1251 N A St",
    "sg:city":"Perris",
    "sg:classifiers":[
        {
            "category":"Organizations",
            "subcategory":"Religious Organization",
            "type":"Services"
        }
    ],
    "sg:phone":"+1 951 943 2110",
    "sg:postcode":"92570",
    "sg:province":"CA",
    "sg:tags":[
        "church"
    ],
    "sg:website":"www.rodpryor.com",
    "wof:name":"Praise Fellowship Christian",
    "wof:placetype":"venue"
},
  "geometry": {"coordinates":[-117.23483,33.796972],"type":"Point"}
}