{
  "type": "Feature",
  "properties": {
    "addr:full":"1945 Noriega St San Francisco CA 94122",
    "addr:housenumber":"1945",
    "addr:postcode":"94122",
    "addr:street":"Noriega St",
    "iso:country":"US",
    "sg:address":"1945 Noriega St",
    "sg:city":"San Francisco",
    "sg:classifiers":[
        {
            "category":"Health Services",
            "subcategory":"Doctor",
            "type":"Services"
        }
    ],
    "sg:phone":"+1 415 731 2260",
    "sg:postcode":"94122",
    "sg:province":"CA",
    "sg:tags":[
        "dentist"
    ],
    "wof:name":"Stanley Hong, DDS",
    "wof:placetype":"venue"
},
  "geometry": {"coordinates":[-122.484864,37.753761],"type":"Point"}
}