{
  "type": "Feature",
  "properties": {
    "iso:country":"US",
    "sg:address":"7357 Round Hill Dr",
    "sg:city":"Lancaster",
    "sg:classifiers":[
        {
            "category":"Retail",
            "subcategory":"Laundry & Dry Cleaning",
            "type":"Services"
        }
    ],
    "sg:phone":"+1 661 266 1360",
    "sg:postcode":"93536",
    "sg:province":"CA",
    "sg:tags":[
        "cleaners",
        "rug",
        "carpet"
    ],
    "wof:name":"A V Top Carpet Cleaning",
    "wof:placetype":"venue"
},
  "geometry": {"coordinates":[-118.260358,34.648644],"type":"Point"}
}