{
  "type": "Feature",
  "properties": {
    "iso:country":"US",
    "sg:address":"137 E Anaheim St",
    "sg:city":"Wilmington",
    "sg:classifiers":[
        {
            "category":"Fast Food",
            "type":"Food & Drink"
        }
    ],
    "sg:phone":"+1 310 549 1342",
    "sg:postcode":"90744",
    "sg:province":"CA",
    "sg:tags":[
        "burger"
    ],
    "sg:website":"www.originaltommys.com",
    "wof:name":"Tommy's Original World Famous Hamburgers",
    "wof:placetype":"venue"
},
  "geometry": {"coordinates":[-118.261002,33.780102],"type":"Point"}
}