{
  "type": "Feature",
  "properties": {
    "addr:full":"5237 Harmony Ave North Hollywood CA 91601",
    "addr:housenumber":"5237",
    "addr:postcode":"91601",
    "addr:street":"Harmony Ave",
    "iso:country":"US",
    "sg:address":"5237 Harmony Ave",
    "sg:city":"North Hollywood",
    "sg:classifiers":[
        {
            "category":"Home & Garden",
            "subcategory":"Building Materials",
            "type":"Retail Goods"
        }
    ],
    "sg:phone":"+1 818 763 0399",
    "sg:postcode":"91601",
    "sg:province":"CA",
    "sg:tags":[
        "lumber"
    ],
    "wof:name":"Lex Hardwood Floraing",
    "wof:placetype":"venue"
},
  "geometry": {"coordinates":[-118.36653099999999,34.168319],"type":"Point"}
}