{
  "type": "Feature",
  "properties": {
    "iso:country":"US",
    "sg:address":"325 Glendale Blvd",
    "sg:city":"Los Angeles",
    "sg:classifiers":[
        {
            "category":"Arts & Performance",
            "subcategory":"Art Gallery",
            "type":"Entertainment"
        },
        {
            "category":"Arts & Performance",
            "subcategory":"Music",
            "type":"Entertainment"
        }
    ],
    "sg:phone":"+1 213 483 7347",
    "sg:postcode":"90026",
    "sg:province":"CA",
    "sg:tags":[
        "venue"
    ],
    "sg:website":"pehrspace.org",
    "wof:name":"Pehrspace",
    "wof:placetype":"venue"
},
  "geometry": {"coordinates":[-118.260617,34.067049],"type":"Point"}
}