{
  "type": "Feature",
  "properties": {
    "addr:full":"840 Capitolio Way San Luis Obispo CA 93401",
    "addr:housenumber":"840",
    "addr:postcode":"93401",
    "addr:street":"Capitolio Way",
    "iso:country":"US",
    "sg:address":"840 Capitolio Way",
    "sg:city":"San Luis Obispo",
    "sg:classifiers":[
        {
            "category":"Manufacturing",
            "subcategory":"Tools & Machinery",
            "type":"Manufacturing & Wholesale Goods"
        }
    ],
    "sg:phone":"+1 714 556 0145",
    "sg:postcode":"93401",
    "sg:province":"CA",
    "sg:tags":[
        "equipment",
        "janitor",
        "supply"
    ],
    "wof:name":"Alfa Kleen",
    "wof:placetype":"venue"
},
  "geometry": {"coordinates":[-120.64339699999999,35.257812],"type":"Point"}
}