{
  "type": "Feature",
  "properties": {
    "iso:country":"US",
    "sg:address":"11780 Woodley Ave",
    "sg:city":"Granada Hills",
    "sg:classifiers":[
        {
            "category":"Shopping",
            "type":"Retail Goods"
        }
    ],
    "sg:phone":"+1 818 243 6942",
    "sg:postcode":"91344",
    "sg:province":"CA",
    "sg:tags":[
        "banner"
    ],
    "wof:name":"Hovsep Krikorian",
    "wof:placetype":"venue"
},
  "geometry": {"coordinates":[-118.484026,34.285351],"type":"Point"}
}