{
  "type": "Feature",
  "properties": {
    "addr:full":"11780 Woodley Ave Granada Hills CA 91344",
    "addr:housenumber":"11780",
    "addr:postcode":"91344",
    "addr:street":"Woodley Ave",
    "iso:country":"US",
    "sg:address":"11780 Woodley Ave",
    "sg:city":"Granada Hills",
    "sg:classifiers":[
        {
            "category":"Shopping",
            "type":"Retail Goods"
        }
    ],
    "sg:phone":"+1 818 243 6942",
    "sg:postcode":"91344",
    "sg:province":"CA",
    "sg:tags":[
        "banner"
    ],
    "wof:name":"Hovsep Krikorian",
    "wof:placetype":"venue"
},
  "geometry": {"coordinates":[-118.484026,34.285351],"type":"Point"}
}