{
  "type": "Feature",
  "properties": {
    "addr:full":"1001 6th St Manhattan Beach CA 90266",
    "addr:housenumber":"1001",
    "addr:postcode":"90266",
    "addr:street":"6Th St",
    "iso:country":"US",
    "sg:address":"1001 6th St",
    "sg:city":"Manhattan Beach",
    "sg:classifiers":[
        {
            "category":"Real Estate",
            "subcategory":"Real Estate Agent",
            "type":"Services"
        }
    ],
    "sg:phone":"+1 310 372 8433",
    "sg:postcode":"90266",
    "sg:province":"CA",
    "sg:tags":[
        "consultant"
    ],
    "wof:name":"Srour & Assoc",
    "wof:placetype":"venue"
},
  "geometry": {"coordinates":[-118.39711800000001,33.882556],"type":"Point"}
}