{
  "type": "Feature",
  "properties": {
    "addr:full":"30262 Crown Valley Pkwy Laguna Niguel CA 92677",
    "addr:housenumber":"30262",
    "addr:postcode":"92677",
    "addr:street":"Crown Valley Pkwy",
    "iso:country":"US",
    "sg:address":"30262 Crown Valley Pkwy",
    "sg:city":"Laguna Niguel",
    "sg:classifiers":[
        {
            "category":"Retail",
            "subcategory":"Laundry & Dry Cleaning",
            "type":"Services"
        }
    ],
    "sg:phone":"+1 949 249 2481",
    "sg:postcode":"92677",
    "sg:province":"CA",
    "sg:tags":[
        "cleaners"
    ],
    "wof:name":"Mall Cleaners",
    "wof:placetype":"venue"
},
  "geometry": {"coordinates":[-117.715558,33.522935],"type":"Point"}
}