{
  "type": "Feature",
  "properties": {
    "addr:full":"1197 S Vanderbilt Cir Manteca CA 95337",
    "addr:housenumber":"1197",
    "addr:postcode":"95337",
    "addr:street":"S Vanderbilt Cir",
    "iso:country":"US",
    "sg:address":"1197 S Vanderbilt Cir",
    "sg:city":"Manteca",
    "sg:classifiers":[
        {
            "category":"Professional",
            "type":"Services"
        },
        {
            "category":"Retail",
            "subcategory":"Auto Repair",
            "type":"Services"
        }
    ],
    "sg:phone":"+1 209 823 8468",
    "sg:postcode":"95337",
    "sg:province":"CA",
    "sg:tags":[
        "glass",
        "coating",
        "tinting"
    ],
    "wof:name":"The Tint Shop",
    "wof:placetype":"venue"
},
  "geometry": {"coordinates":[-121.21171699999999,37.784733],"type":"Point"}
}