{
  "type": "Feature",
  "properties": {
    "iso:country":"US",
    "sg:address":"28219 Agoura Rd",
    "sg:city":"Agoura Hills",
    "sg:classifiers":[
        {
            "category":"Professional",
            "subcategory":"Management & Consulting",
            "type":"Services"
        }
    ],
    "sg:phone":"+1 818 879 8833",
    "sg:postcode":"91301",
    "sg:province":"CA",
    "sg:tags":[
        "consultant",
        "publishing"
    ],
    "wof:name":"Viatech Publishing Solutions",
    "wof:placetype":"venue"
},
  "geometry": {"coordinates":[-118.74061399999999,34.140705],"type":"Point"}
}