{
  "type": "Feature",
  "properties": {
    "iso:country":"US",
    "sg:address":"1560 W Adams Blvd",
    "sg:city":"Los Angeles",
    "sg:classifiers":[
        {
            "category":"Food & Beverages",
            "subcategory":"Specialty",
            "type":"Retail Goods"
        },
        {
            "category":"Professional",
            "subcategory":"Management & Consulting",
            "type":"Services"
        }
    ],
    "sg:phone":"+1 323 731 5259",
    "sg:postcode":"90007",
    "sg:province":"CA",
    "sg:tags":[
        "bulk",
        "water",
        "company",
        "direct",
        "sales"
    ],
    "wof:name":"Waterhouse Purified Drinking W",
    "wof:placetype":"venue"
},
  "geometry": {"coordinates":[-118.296127,34.032669],"type":"Point"}
}