{
  "type": "Feature",
  "properties": {
    "addr:full":"1 College Way South Lake Tahoe CA 96150",
    "addr:housenumber":"1",
    "addr:postcode":"96150",
    "addr:street":"College Way",
    "iso:country":"US",
    "sg:address":"1 College Way",
    "sg:city":"South Lake Tahoe",
    "sg:classifiers":[
        {
            "category":"Education",
            "subcategory":"Junior College",
            "type":"Public Place"
        }
    ],
    "sg:phone":"+1 530 541 4660",
    "sg:postcode":"96150",
    "sg:province":"CA",
    "sg:website":"www.ltcc.edu",
    "wof:name":"Lake Tahoe Community College",
    "wof:placetype":"venue"
},
  "geometry": {"coordinates":[-119.968799,38.928712],"type":"Point"}
}