{
  "type": "Feature",
  "properties": {
    "iso:country":"US",
    "sg:address":"12731 Van Nuys Blvd",
    "sg:city":"Pacoima",
    "sg:classifiers":[
        {
            "category":"Restaurant",
            "type":"Food & Drink"
        }
    ],
    "sg:menulink":"http://www.allmenus.com/ca/san-fernando-valley/87838-little-caesars-pizza/menu/",
    "sg:phone":"+1 818 896 6546",
    "sg:postcode":"91331",
    "sg:province":"CA",
    "sg:tags":[
        "american",
        "pizza"
    ],
    "wof:name":"Little Caesar's Pizza",
    "wof:placetype":"venue"
},
  "geometry": {"coordinates":[-118.410267,34.274909],"type":"Point"}
}