{
  "type": "Feature",
  "properties": {
    "addr:full":"400 Capitol Mall Ste 2000 Sacramento CA 95814",
    "addr:housenumber":"400",
    "addr:postcode":"95814",
    "addr:street":"Capitol Mall Ste 2000",
    "iso:country":"US",
    "sg:address":"400 Capitol Mall Ste 2000",
    "sg:city":"Sacramento",
    "sg:classifiers":[
        {
            "category":"Professional",
            "subcategory":"Accounting & Tax Preparation",
            "type":"Services"
        }
    ],
    "sg:phone":"+1 916 448 1156",
    "sg:postcode":"95814",
    "sg:province":"CA",
    "sg:tags":[
        "bookkeeping",
        "public",
        "accountants-certified"
    ],
    "sg:website":"http://www.rmislab.com",
    "wof:name":"Deloitte & Touche",
    "wof:placetype":"venue"
},
  "geometry": {"coordinates":[-121.502922,38.579029],"type":"Point"}
}