{
  "type": "Feature",
  "properties": {
    "iso:country":"US",
    "sg:address":"764 Palermo Dr",
    "sg:city":"Santa Barbara",
    "sg:classifiers":[
        {
            "category":"Building & Trades",
            "subcategory":"Construction",
            "type":"Services"
        }
    ],
    "sg:phone":"+1 805 682 7403",
    "sg:postcode":"93105",
    "sg:province":"CA",
    "sg:tags":[
        "excavation",
        "contractor"
    ],
    "wof:name":"Santa Barbara Bobcat",
    "wof:placetype":"venue"
},
  "geometry": {"coordinates":[-119.745936,34.42872],"type":"Point"}
}