{
  "type": "Feature",
  "properties": {
    "addr:full":"250 S Broadway Turlock CA 95380",
    "addr:housenumber":"250",
    "addr:postcode":"95380",
    "addr:street":"S Broadway",
    "iso:country":"US",
    "sg:address":"250 S Broadway",
    "sg:city":"Turlock",
    "sg:classifiers":[
        {
            "category":"Government",
            "subcategory":"Office",
            "type":"Public Place"
        }
    ],
    "sg:phone":"+1 209 668 5698",
    "sg:postcode":"95380",
    "sg:province":"CA",
    "sg:tags":[
        "village"
    ],
    "wof:name":"Carnegie Art Ctr",
    "wof:placetype":"venue"
},
  "geometry": {"coordinates":[-120.84616200000001,37.491989],"type":"Point"}
}