{
  "type": "Feature",
  "properties": {
    "addr:full":"1771 Old Highway 4 Arnold CA 95223",
    "addr:housenumber":"1771",
    "addr:postcode":"95223",
    "addr:street":"Old Highway 4",
    "iso:country":"US",
    "sg:address":"1771 Old Highway 4",
    "sg:city":"Arnold",
    "sg:classifiers":[
        {
            "category":"Home & Garden",
            "subcategory":"Home Furnishings",
            "type":"Retail Goods"
        },
        {
            "category":"Building & Trades",
            "subcategory":"Electrical",
            "type":"Services"
        }
    ],
    "sg:phone":"+1 209 795 2529",
    "sg:postcode":"95223",
    "sg:province":"CA",
    "sg:tags":[
        "industrial",
        "electrician",
        "electric",
        "fixture",
        "lighting",
        "contractors-commercial"
    ],
    "sg:website":"http://www.arnoldelectrical.com",
    "wof:name":"Arnold Electrical",
    "wof:placetype":"venue"
},
  "geometry": {"coordinates":[-120.170624,38.393978],"type":"Point"}
}