{
  "type": "Feature",
  "properties": {
    "addr:full":"12712 Dove Creek Dr Bakersfield CA 93312",
    "addr:housenumber":"12712",
    "addr:postcode":"93312",
    "addr:street":"Dove Creek Dr",
    "iso:country":"US",
    "sg:address":"12712 Dove Creek Dr",
    "sg:city":"Bakersfield",
    "sg:classifiers":[
        {
            "category":"Building & Trades",
            "subcategory":"Landscaping Services",
            "type":"Services"
        }
    ],
    "sg:phone":"+1 661 837 8733",
    "sg:postcode":"93312",
    "sg:province":"CA",
    "sg:tags":[
        "landscape",
        "contractor"
    ],
    "wof:name":"Oaks Tree Svc",
    "wof:placetype":"venue"
},
  "geometry": {"coordinates":[-119.144426,35.379311],"type":"Point"}
}