{
  "type": "Feature",
  "properties": {
    "iso:country":"US",
    "sg:address":"1301 Stockton St",
    "sg:city":"San Francisco",
    "sg:classifiers":[
        {
            "category":"Banks & Credit Unions",
            "subcategory":"Investment Brokerage",
            "type":"Services"
        }
    ],
    "sg:phone":"+1 415 981 1260",
    "sg:postcode":"94133",
    "sg:province":"CA",
    "sg:tags":[
        "investing"
    ],
    "wof:name":"Ucb Investment Services",
    "wof:placetype":"venue"
},
  "geometry": {"coordinates":[-122.408773,37.797794],"type":"Point"}
}