{
  "type": "Feature",
  "properties": {
    "addr:full":"9033 Olive Dr Spring Valley CA 91977",
    "addr:housenumber":"9033",
    "addr:postcode":"91977",
    "addr:street":"Olive Dr",
    "iso:country":"US",
    "sg:address":"9033 Olive Dr",
    "sg:city":"Spring Valley",
    "sg:classifiers":[
        {
            "category":"Retail",
            "subcategory":"Auto Repair",
            "type":"Services"
        }
    ],
    "sg:phone":"+1 619 461 3502",
    "sg:postcode":"91977",
    "sg:province":"CA",
    "sg:tags":[
        "automobile",
        "customizing"
    ],
    "wof:name":"Bengels Custom Auto Tin",
    "wof:placetype":"venue"
},
  "geometry": {"coordinates":[-116.99934500000001,32.741949],"type":"Point"}
}