{
  "type": "Feature",
  "properties": {
    "addr:full":"26631 Trabuco Rd Mission Viejo CA 92691",
    "addr:housenumber":"26631",
    "addr:postcode":"92691",
    "addr:street":"Trabuco Rd",
    "iso:country":"US",
    "sg:address":"26631 Trabuco Rd",
    "sg:city":"Mission Viejo",
    "sg:classifiers":[
        {
            "category":"Fast Food",
            "type":"Food & Drink"
        },
        {
            "category":"Restaurant",
            "type":"Food & Drink"
        }
    ],
    "sg:phone":"+1 949 586 9170",
    "sg:postcode":"92691",
    "sg:province":"CA",
    "sg:tags":[
        "mexican"
    ],
    "sg:website":"www.tacobell.com",
    "wof:name":"Taco Bell",
    "wof:placetype":"venue"
},
  "geometry": {"coordinates":[-117.656837,33.613361],"type":"Point"}
}