{
  "type": "Feature",
  "properties": {
    "addr:full":"2140 W Buena Vista Dr Rialto CA 92377",
    "addr:housenumber":"2140",
    "addr:postcode":"92377",
    "addr:street":"W Buena Vista Dr",
    "iso:country":"US",
    "sg:address":"2140 W Buena Vista Dr",
    "sg:city":"Rialto",
    "sg:classifiers":[
        {
            "category":"Education",
            "subcategory":"School",
            "type":"Public Place"
        }
    ],
    "sg:phone":"+1 909 421 7668",
    "sg:postcode":"92377",
    "sg:province":"CA",
    "sg:tags":[
        "middle"
    ],
    "wof:name":"Rialto Unified School District Middle Schools",
    "wof:placetype":"venue"
},
  "geometry": {"coordinates":[-117.416995,34.161196],"type":"Point"}
}