{
  "type": "Feature",
  "properties": {
    "addr:full":"100 Waverly Pl San Francisco CA 94108",
    "addr:housenumber":"100",
    "addr:postcode":"94108",
    "addr:street":"Waverly Pl",
    "iso:country":"US",
    "sg:address":"100 Waverly Pl",
    "sg:city":"San Francisco",
    "sg:classifiers":[
        {
            "category":"Shopping",
            "subcategory":"Gifts & Souvenirs",
            "type":"Retail Goods"
        }
    ],
    "sg:phone":"+1 415 781 1686",
    "sg:postcode":"94108",
    "sg:province":"CA",
    "wof:name":"Blue Heaven Gift Shop",
    "wof:placetype":"venue"
},
  "geometry": {"coordinates":[-122.40700099999999,37.795077],"type":"Point"}
}