{
  "type": "Feature",
  "properties": {
    "addr:full":"3066 Royce Dr Rescue CA 95672",
    "addr:housenumber":"3066",
    "addr:postcode":"95672",
    "addr:street":"Royce Dr",
    "iso:country":"US",
    "sg:address":"3066 Royce Dr",
    "sg:city":"Rescue",
    "sg:classifiers":[
        {
            "category":"Autos & Motor Vehicles",
            "subcategory":"Auto Supplies",
            "type":"Retail Goods"
        }
    ],
    "sg:phone":"+1 530 676 3631",
    "sg:postcode":"95672",
    "sg:province":"CA",
    "sg:tags":[
        "equipment",
        "racing",
        "car",
        "automobile"
    ],
    "wof:name":"Sunoco Racing Fuel",
    "wof:placetype":"venue"
},
  "geometry": {"coordinates":[-120.996905,38.702397],"type":"Point"}
}