{
  "type": "Feature",
  "properties": {
    "iso:country":"US",
    "sg:address":"73 Ashton Ave",
    "sg:city":"San Francisco",
    "sg:classifiers":[
        {
            "category":"Professional",
            "subcategory":"Art Services",
            "type":"Services"
        }
    ],
    "sg:phone":"+1 415 350 5047",
    "sg:postcode":"94112",
    "sg:province":"CA",
    "sg:tags":[
        "photographer"
    ],
    "sg:website":"www.jenniferlow.com",
    "wof:name":"Jennifer Low Photography",
    "wof:placetype":"venue"
},
  "geometry": {"coordinates":[-122.462462,37.719332],"type":"Point"}
}