{
  "type": "Feature",
  "properties": {
    "addr:full":"1710 Plum Ln Redlands CA 92374",
    "addr:housenumber":"1710",
    "addr:postcode":"92374",
    "addr:street":"Plum Ln",
    "iso:country":"US",
    "sg:address":"1710 Plum Ln",
    "sg:city":"Redlands",
    "sg:classifiers":[
        {
            "category":"Insurance",
            "subcategory":"Insurance Agent",
            "type":"Services"
        }
    ],
    "sg:phone":"+1 909 748 0250",
    "sg:postcode":"92374",
    "sg:province":"CA",
    "wof:name":"Select Auto Insurance",
    "wof:placetype":"venue"
},
  "geometry": {"coordinates":[-117.21236,34.069031],"type":"Point"}
}