{
  "type": "Feature",
  "properties": {
    "iso:country":"US",
    "sg:address":"8217 Lankershim Blvd",
    "sg:city":"North Hollywood",
    "sg:classifiers":[
        {
            "category":"Wholesale",
            "subcategory":"Scrap",
            "type":"Manufacturing & Wholesale Goods"
        }
    ],
    "sg:phone":"+1 818 504 1625",
    "sg:postcode":"91605",
    "sg:province":"CA",
    "sg:tags":[
        "salvage",
        "surplus",
        "merchandise"
    ],
    "wof:name":"Blitzer Co",
    "wof:placetype":"venue"
},
  "geometry": {"coordinates":[-118.387854,34.222259],"type":"Point"}
}