{
  "type": "Feature",
  "properties": {
    "addr:full":"724 E Arrow Hwy Pomona CA 91767",
    "addr:housenumber":"724",
    "addr:postcode":"91767",
    "addr:street":"E Arrow Hwy",
    "iso:country":"US",
    "sg:address":"724 E Arrow Hwy",
    "sg:city":"Pomona",
    "sg:classifiers":[
        {
            "category":"Shopping",
            "subcategory":"Clothing, Apparel, & Fashions",
            "type":"Retail Goods"
        }
    ],
    "sg:phone":"+1 909 626 6557",
    "sg:postcode":"91767",
    "sg:province":"CA",
    "sg:tags":[
        "wig",
        "toupee",
        "hairpiece"
    ],
    "wof:name":"Towne Wigs & Gifts",
    "wof:placetype":"venue"
},
  "geometry": {"coordinates":[-117.737044,34.090012],"type":"Point"}
}