{
  "type": "Feature",
  "properties": {
    "iso:country":"US",
    "sg:address":"1800 W Tulare Ave",
    "sg:city":"Visalia",
    "sg:classifiers":[
        {
            "category":"Home & Garden",
            "subcategory":"Building Materials",
            "type":"Retail Goods"
        }
    ],
    "sg:phone":"+1 559 732 1764",
    "sg:postcode":"93277",
    "sg:province":"CA",
    "sg:tags":[
        "paint",
        "improvement"
    ],
    "sg:website":"http://national.citysearch.com/profile/external/731465/visalia_ca/sherwin_williams.html?publisher=yellowpages&reference_id=1&placement=ypwebsitemip",
    "wof:name":"Sherwin-Williams",
    "wof:placetype":"venue"
},
  "geometry": {"coordinates":[-119.312622,36.320202],"type":"Point"}
}