{
  "type": "Feature",
  "properties": {
    "iso:country":"US",
    "sg:address":"940 S Hill St",
    "sg:city":"Los Angeles",
    "sg:classifiers":[
        {
            "category":"Manufacturing",
            "subcategory":"Apparel",
            "type":"Manufacturing & Wholesale Goods"
        }
    ],
    "sg:phone":"+1 213 891 9030",
    "sg:postcode":"90015",
    "sg:province":"CA",
    "sg:tags":[
        "textile",
        "manufacturer"
    ],
    "sg:website":"www.styletex.com",
    "wof:name":"Style Tex",
    "wof:placetype":"venue"
},
  "geometry": {"coordinates":[-118.257955,34.042131],"type":"Point"}
}