{
  "type": "Feature",
  "properties": {
    "iso:country":"US",
    "sg:address":"1307 Esplanade",
    "sg:city":"Chico",
    "sg:classifiers":[
        {
            "category":"Personal",
            "subcategory":"Beauty Salon",
            "type":"Services"
        }
    ],
    "sg:phone":"+1 530 892 8746",
    "sg:postcode":"95926",
    "sg:province":"CA",
    "wof:name":"Mecca Hair & Nail Studio",
    "wof:placetype":"venue"
},
  "geometry": {"coordinates":[-121.847964,39.7409],"type":"Point"}
}