{
  "type": "Feature",
  "properties": {
    "addr:full":"2071 Ringwood Ave San Jose CA 95131",
    "addr:housenumber":"2071",
    "addr:postcode":"95131",
    "addr:street":"Ringwood Ave",
    "iso:country":"US",
    "sg:address":"2071 Ringwood Ave",
    "sg:city":"San Jose",
    "sg:classifiers":[
        {
            "category":"Airline",
            "type":"Transportation"
        }
    ],
    "sg:phone":"+1 408 954 8602",
    "sg:postcode":"95131",
    "sg:province":"CA",
    "sg:tags":[
        "cargo",
        "air"
    ],
    "wof:name":"Tas Air Cargo",
    "wof:placetype":"venue"
},
  "geometry": {"coordinates":[-121.89796699999999,37.396523],"type":"Point"}
}