{
  "type": "Feature",
  "properties": {
    "iso:country":"US",
    "sg:address":"2626 N Bristol St",
    "sg:city":"Santa Ana",
    "sg:classifiers":[
        {
            "category":"Retail",
            "subcategory":"Car Wash",
            "type":"Services"
        }
    ],
    "sg:phone":"+1 714 774 2288",
    "sg:postcode":"92706",
    "sg:province":"CA",
    "sg:tags":[
        "truck",
        "cleaning"
    ],
    "wof:name":"Anaheim Truck Wash",
    "wof:placetype":"venue"
},
  "geometry": {"coordinates":[-117.884815,33.772826],"type":"Point"}
}