{
  "type": "Feature",
  "properties": {
    "iso:country":"US",
    "sg:address":"777 Silver Spur Road",
    "sg:city":"Rolling Hills Estate",
    "sg:classifiers":[
        {
            "category":"Shopping",
            "subcategory":"Jewelry",
            "type":"Retail Goods"
        },
        {
            "category":"Shopping",
            "subcategory":"Gifts & Souvenirs",
            "type":"Retail Goods"
        }
    ],
    "sg:phone":"+1 310 377 1132",
    "sg:postcode":"90274",
    "sg:province":"CA",
    "sg:tags":[
        "flower"
    ],
    "wof:name":"Hundred Fortune Art Center",
    "wof:placetype":"venue"
},
  "geometry": {"coordinates":[-118.368525,33.770455],"type":"Point"}
}