{
  "type": "Feature",
  "properties": {
    "addr:full":"2001 Via Pacifica Aptos CA 95003",
    "addr:housenumber":"2001",
    "addr:postcode":"ca 95003",
    "addr:street":"Via Pacifica",
    "iso:country":"US",
    "sg:address":"2001 Via Pacifica",
    "sg:city":"Aptos",
    "sg:classifiers":[
        {
            "category":"Professional",
            "subcategory":"Business Services",
            "type":"Services"
        }
    ],
    "sg:phone":"+1 831 818 4015",
    "sg:postcode":"95003",
    "sg:province":"CA",
    "sg:tags":[
        "recording",
        "studio"
    ],
    "wof:name":"Synergy Sound Recording",
    "wof:placetype":"venue"
},
  "geometry": {"coordinates":[-121.865236,36.95026],"type":"Point"}
}