{
  "type": "Feature",
  "properties": {
    "addr:full":"123 Mission San Francisco CA 94105",
    "addr:housenumber":"123",
    "addr:postcode":"94105",
    "addr:street":"Mission",
    "iso:country":"US",
    "sg:address":"123 Mission",
    "sg:city":"San Francisco",
    "sg:classifiers":[
        {
            "category":"Coffee & Tea",
            "type":"Food & Drink"
        }
    ],
    "sg:phone":"+1 415 543 1510",
    "sg:postcode":"94105",
    "sg:province":"CA",
    "sg:website":"www.starbucks.com/",
    "wof:name":"Starbucks",
    "wof:placetype":"venue"
},
  "geometry": {"coordinates":[-122.394649,37.792087],"type":"Point"}
}