{
  "type": "Feature",
  "properties": {
    "iso:country":"US",
    "sg:address":"5169 Mission St",
    "sg:city":"San Francisco",
    "sg:classifiers":[
        {
            "category":"Bakery",
            "type":"Food & Drink"
        }
    ],
    "sg:phone":"+1 415 333 0205",
    "sg:postcode":"94112",
    "sg:province":"CA",
    "wof:name":"The Cake House",
    "wof:placetype":"venue"
},
  "geometry": {"coordinates":[-122.441002,37.7159],"type":"Point"}
}