{
  "type": "Feature",
  "properties": {
    "iso:country":"US",
    "sg:address":"15493 Lottie Way",
    "sg:city":"Lathrop",
    "sg:classifiers":[
        {
            "category":"Home & Garden",
            "subcategory":"Household Appliances",
            "type":"Retail Goods"
        }
    ],
    "sg:phone":"+1 209 858 5902",
    "sg:postcode":"95330",
    "sg:province":"CA",
    "wof:name":"R & M Appliance Repair Svc",
    "wof:placetype":"venue"
},
  "geometry": {"coordinates":[-121.289413,37.82153],"type":"Point"}
}