{
  "type": "Feature",
  "properties": {
    "iso:country":"US",
    "sg:address":"19190 State Hwy 18",
    "sg:city":"Apple Valley",
    "sg:classifiers":[
        {
            "category":"Health Services",
            "subcategory":"Doctor",
            "type":"Services"
        }
    ],
    "sg:phone":"+1 760 242 7753",
    "sg:postcode":"92307",
    "sg:province":"CA",
    "sg:tags":[
        "dentist"
    ],
    "wof:name":"Apple Dental Ctr",
    "wof:placetype":"venue"
},
  "geometry": {"coordinates":[-117.245369,34.536892],"type":"Point"}
}