{
  "type": "Feature",
  "properties": {
    "iso:country":"US",
    "sg:address":"813 D St",
    "sg:city":"Modesto",
    "sg:classifiers":[
        {
            "category":"Home & Garden",
            "subcategory":"Furniture",
            "type":"Retail Goods"
        }
    ],
    "sg:phone":"+1 209 577 3221",
    "sg:postcode":"95354",
    "sg:province":"CA",
    "sg:tags":[
        "store"
    ],
    "wof:name":"J S West & Co",
    "wof:placetype":"venue"
},
  "geometry": {"coordinates":[-120.995003,37.633499],"type":"Point"}
}