{
  "type": "Feature",
  "properties": {
    "addr:full":"1666 E Highland Ave San Bernardino CA 92404",
    "addr:housenumber":"1666",
    "addr:postcode":"92404",
    "addr:street":"E Highland Ave",
    "iso:country":"US",
    "sg:address":"1666 E Highland Ave",
    "sg:city":"San Bernardino",
    "sg:classifiers":[
        {
            "category":"Cinema",
            "subcategory":"Movie Rental",
            "type":"Entertainment"
        }
    ],
    "sg:phone":"+1 909 881 4998",
    "sg:postcode":"92404",
    "sg:province":"CA",
    "sg:tags":[
        "leasing",
        "video",
        "disc",
        "tape"
    ],
    "wof:name":"94 Video",
    "wof:placetype":"venue"
},
  "geometry": {"coordinates":[-117.252236,34.135936],"type":"Point"}
}