{
  "type": "Feature",
  "properties": {
    "iso:country":"US",
    "sg:address":"1710 S Redondo Blvd",
    "sg:city":"Los Angeles",
    "sg:classifiers":[
        {
            "category":"Wholesale",
            "subcategory":"Motor Vehicles",
            "type":"Manufacturing & Wholesale Goods"
        }
    ],
    "sg:phone":"+1 818 679 2095",
    "sg:postcode":"90019",
    "sg:province":"CA",
    "wof:name":"Gold Coast Resources USA Inc",
    "wof:placetype":"venue"
},
  "geometry": {"coordinates":[-118.35063700000001,34.04439],"type":"Point"}
}