{
  "type": "Feature",
  "properties": {
    "iso:country":"US",
    "sg:address":"18416 S Santa Fe Ave",
    "sg:city":"Compton",
    "sg:classifiers":[
        {
            "category":"Wholesale",
            "subcategory":"Machinery & Supplies",
            "type":"Manufacturing & Wholesale Goods"
        }
    ],
    "sg:phone":"+1 310 763 3420",
    "sg:postcode":"90221",
    "sg:province":"CA",
    "sg:tags":[
        "abrasive"
    ],
    "wof:name":"Blastrac",
    "wof:placetype":"venue"
},
  "geometry": {"coordinates":[-118.213378,33.863175],"type":"Point"}
}