{
  "type": "Feature",
  "properties": {
    "iso:country":"US",
    "sg:address":"1500 Saviers Rd",
    "sg:city":"Oxnard",
    "sg:classifiers":[
        {
            "category":"Insurance",
            "subcategory":"Insurance Agent",
            "type":"Services"
        }
    ],
    "sg:phone":"+1 805 486 1217",
    "sg:postcode":"93033",
    "sg:province":"CA",
    "wof:name":"Kenton Auto Insurance",
    "wof:placetype":"venue"
},
  "geometry": {"coordinates":[-119.177387,34.183931],"type":"Point"}
}