{
  "type": "Feature",
  "properties": {
    "iso:country":"US",
    "sg:address":"2901 Baker St",
    "sg:city":"San Francisco",
    "sg:classifiers":[
        {
            "category":"Food & Beverages",
            "subcategory":"Groceries & Convenience Stores",
            "type":"Retail Goods"
        }
    ],
    "sg:phone":"+1 415 567 1179",
    "sg:postcode":"94123",
    "sg:province":"CA",
    "wof:name":"Presidio Food Mart",
    "wof:placetype":"venue"
},
  "geometry": {"coordinates":[-122.445975,37.797776],"type":"Point"}
}