{
  "type": "Feature",
  "properties": {
    "iso:country":"US",
    "sg:address":"1466 Yosemite St",
    "sg:city":"Seaside",
    "sg:classifiers":[
        {
            "category":"Real Estate",
            "subcategory":"Real Estate Operator",
            "type":"Services"
        }
    ],
    "sg:phone":"+1 831 394 6685",
    "sg:postcode":"93955",
    "sg:province":"CA",
    "sg:tags":[
        "apartment"
    ],
    "wof:name":"Del Monte Manor Inc",
    "wof:placetype":"venue"
},
  "geometry": {"coordinates":[-121.830214,36.60593],"type":"Point"}
}