{
  "type": "Feature",
  "properties": {
    "addr:full":"2818 MacArthur Blvd Oakland CA 94602",
    "addr:housenumber":"2818",
    "addr:postcode":"94602",
    "addr:street":"Macarthur Blvd",
    "iso:country":"US",
    "sg:address":"2818 MacArthur Blvd",
    "sg:city":"Oakland",
    "sg:classifiers":[
        {
            "category":"Restaurant",
            "type":"Food & Drink"
        }
    ],
    "sg:phone":"+1 510 530 5100",
    "sg:postcode":"94602",
    "sg:province":"CA",
    "sg:tags":[
        "breakfast",
        "brunch"
    ],
    "sg:website":"www.BayCafeToGo.com",
    "wof:name":"The Bay Cafe",
    "wof:placetype":"venue"
},
  "geometry": {"coordinates":[-122.20836799999999,37.798678],"type":"Point"}
}