{
  "type": "Feature",
  "properties": {
    "addr:full":"401 I Street Sacramento CA 95814",
    "addr:housenumber":"401",
    "addr:postcode":"95814",
    "addr:street":"I Street",
    "iso:country":"US",
    "sg:address":"401 I Street",
    "sg:city":"Sacramento",
    "sg:classifiers":[
        {
            "category":"Parking",
            "type":"Transportation"
        }
    ],
    "sg:phone":"+1 916 498 0608",
    "sg:postcode":"95814",
    "sg:province":"CA",
    "wof:name":"Platinum Parking",
    "wof:placetype":"venue"
},
  "geometry": {"coordinates":[-121.492394,38.57756],"type":"Point"}
}