{
  "type": "Feature",
  "properties": {
    "addr:full":"6562 Westminster Blvd Westminster CA 92683",
    "addr:housenumber":"6562",
    "addr:postcode":"92683",
    "addr:street":"Westminster Blvd",
    "iso:country":"US",
    "sg:address":"6562 Westminster Blvd",
    "sg:city":"Westminster",
    "sg:classifiers":[
        {
            "category":"Autos & Motor Vehicles",
            "subcategory":"Auto Supplies",
            "type":"Retail Goods"
        },
        {
            "category":"Wholesale",
            "subcategory":"Auto Parts",
            "type":"Manufacturing & Wholesale Goods"
        }
    ],
    "sg:phone":"+1 714 898 0810",
    "sg:postcode":"92683",
    "sg:province":"CA",
    "sg:tags":[
        "body",
        "automobile",
        "truck",
        "equipment",
        "accessory"
    ],
    "sg:website":"http://www.oreillyauto.com?utm_source=yellowpages&utm_medium=iyp&utm_campaign=2680",
    "wof:name":"Kragen O'ReillyAuto Parts",
    "wof:placetype":"venue"
},
  "geometry": {"coordinates":[-118.014534,33.759062],"type":"Point"}
}