{
  "type": "Feature",
  "properties": {
    "iso:country":"US",
    "sg:address":"2700 Little Mountain Dr",
    "sg:city":"San Bernardino",
    "sg:classifiers":[
        {
            "category":"Banks & Credit Unions",
            "subcategory":"Bank",
            "type":"Services"
        }
    ],
    "sg:phone":"+1 909 882 2211",
    "sg:postcode":"92405",
    "sg:province":"CA",
    "sg:tags":[
        "loan",
        "real estate"
    ],
    "wof:name":"Southwest Coastal Alliance",
    "wof:placetype":"venue"
},
  "geometry": {"coordinates":[-117.31506,34.140698],"type":"Point"}
}