{
  "type": "Feature",
  "properties": {
    "addr:full":"10221 Slater Ave Fountain Valley CA 92708",
    "addr:housenumber":"10221",
    "addr:postcode":"92708",
    "addr:street":"Slater Ave",
    "iso:country":"US",
    "sg:address":"10221 Slater Ave",
    "sg:city":"Fountain Valley",
    "sg:classifiers":[
        {
            "category":"Personal",
            "type":"Services"
        }
    ],
    "sg:phone":"+1 714 752 4025",
    "sg:postcode":"92708",
    "sg:province":"CA",
    "sg:tags":[
        "local"
    ],
    "wof:name":"Practical Bail Bonds",
    "wof:placetype":"venue"
},
  "geometry": {"coordinates":[-117.95067,33.709192],"type":"Point"}
}