{
  "type": "Feature",
  "properties": {
    "addr:full":"17595 Vierra Canyon Rd Salinas CA 93907",
    "addr:housenumber":"17595",
    "addr:postcode":"93907",
    "addr:street":"Vierra Canyon Rd",
    "iso:country":"US",
    "sg:address":"17595 Vierra Canyon Rd",
    "sg:city":"Salinas",
    "sg:classifiers":[
        {
            "category":"Retail",
            "subcategory":"Veterinary Services",
            "type":"Services"
        }
    ],
    "sg:phone":"+1 831 663 4193",
    "sg:postcode":"93907",
    "sg:province":"CA",
    "sg:tags":[
        "veterinarian"
    ],
    "sg:website":"www.montereycountyequine.com",
    "wof:name":"Monterey County Equine Inc",
    "wof:placetype":"venue"
},
  "geometry": {"coordinates":[-121.6652,36.792039],"type":"Point"}
}