{
  "type": "Feature",
  "properties": {
    "addr:full":"1115 Mission St Santa Cruz CA 95060",
    "addr:housenumber":"1115",
    "addr:postcode":"95060",
    "addr:street":"Mission St",
    "iso:country":"US",
    "sg:address":"1115 Mission St",
    "sg:city":"Santa Cruz",
    "sg:classifiers":[
        {
            "category":"Organizations",
            "subcategory":"Non-profit Organization",
            "type":"Services"
        }
    ],
    "sg:phone":"+1 831 423 2263",
    "sg:postcode":"95060",
    "sg:province":"CA",
    "sg:website":"www.ccof.org",
    "wof:name":"California Certified Organic",
    "wof:placetype":"venue"
},
  "geometry": {"coordinates":[-122.037159,36.969669],"type":"Point"}
}