{
  "type": "Feature",
  "properties": {
    "iso:country":"US",
    "sg:address":"2727 Mariposa St",
    "sg:city":"San Francisco",
    "sg:classifiers":[
        {
            "category":"Social Services",
            "type":"Services"
        }
    ],
    "sg:phone":"+1 415 734 9100",
    "sg:postcode":"94110",
    "sg:province":"CA",
    "sg:tags":[
        "organization",
        "welfare"
    ],
    "wof:name":"One Economy Corp",
    "wof:placetype":"venue"
},
  "geometry": {"coordinates":[-122.410999,37.762912],"type":"Point"}
}