{
  "type": "Feature",
  "properties": {
    "iso:country":"US",
    "sg:address":"33509 Mission Blvd",
    "sg:city":"Union City",
    "sg:classifiers":[
        {
            "category":"Recreation",
            "type":"Entertainment"
        }
    ],
    "sg:phone":"+1 510 487 4827",
    "sg:postcode":"94587",
    "sg:province":"CA",
    "sg:tags":[
        "psychic",
        "medium"
    ],
    "wof:name":"Madam Mary Psychic",
    "wof:placetype":"venue"
},
  "geometry": {"coordinates":[-122.017475,37.603875],"type":"Point"}
}