{
  "type": "Feature",
  "properties": {
    "iso:country":"US",
    "sg:address":"2120 Moreing Rd",
    "sg:city":"Stockton",
    "sg:classifiers":[
        {
            "category":"Banks & Credit Unions",
            "subcategory":"Investment Brokerage",
            "type":"Services"
        }
    ],
    "sg:phone":"+1 209 462 8808",
    "sg:postcode":"95204",
    "sg:province":"CA",
    "sg:tags":[
        "trust"
    ],
    "wof:name":"Helena Hutchins Family Lp",
    "wof:placetype":"venue"
},
  "geometry": {"coordinates":[-121.34635,37.958879],"type":"Point"}
}