{
  "type": "Feature",
  "properties": {
    "addr:full":"606 N Escondido Blvd Escondido CA 92025",
    "addr:housenumber":"606",
    "addr:postcode":"92025",
    "addr:street":"N Escondido Blvd",
    "iso:country":"US",
    "sg:address":"606 N Escondido Blvd",
    "sg:city":"Escondido",
    "sg:classifiers":[
        {
            "category":"Shopping",
            "subcategory":"Florist",
            "type":"Retail Goods"
        }
    ],
    "sg:phone":"+1 760 839 2956",
    "sg:postcode":"92025",
    "sg:province":"CA",
    "wof:name":"Floreria Herrera",
    "wof:placetype":"venue"
},
  "geometry": {"coordinates":[-117.088553,33.127316],"type":"Point"}
}