{
  "type": "Feature",
  "properties": {
    "addr:full":"1410 S Winchester Blvd San Jose CA 95128",
    "addr:housenumber":"1410",
    "addr:postcode":"95128",
    "addr:street":"S Winchester Blvd",
    "iso:country":"US",
    "sg:address":"1410 S Winchester Blvd",
    "sg:city":"San Jose",
    "sg:classifiers":[
        {
            "category":"Retail",
            "subcategory":"Auto Repair",
            "type":"Services"
        }
    ],
    "sg:phone":"+1 408 628 0359",
    "sg:postcode":"95128",
    "sg:province":"CA",
    "sg:tags":[
        "repairing",
        "automotive",
        "automobile"
    ],
    "wof:name":"Precision Tune Auto Care",
    "wof:placetype":"venue"
},
  "geometry": {"coordinates":[-121.949809,37.2977],"type":"Point"}
}