{
  "type": "Feature",
  "properties": {
    "addr:full":"11709 Moorpark St Studio City CA 91604",
    "addr:housenumber":"11709",
    "addr:postcode":"91604",
    "addr:street":"Moorpark St",
    "iso:country":"US",
    "sg:address":"11709 Moorpark St",
    "sg:city":"Studio City",
    "sg:classifiers":[
        {
            "category":"Personal",
            "subcategory":"Beauty Salon",
            "type":"Services"
        }
    ],
    "sg:phone":"+1 818 763 6217",
    "sg:postcode":"91604",
    "sg:province":"CA",
    "sg:tags":[
        "nail"
    ],
    "wof:name":"Natural Nails",
    "wof:placetype":"venue"
},
  "geometry": {"coordinates":[-118.38800000000001,34.150299],"type":"Point"}
}