{
  "type": "Feature",
  "properties": {
    "iso:country":"US",
    "sg:address":"6210 Washington Blvd",
    "sg:city":"Livingston",
    "sg:classifiers":[
        {
            "category":"Freight",
            "type":"Transportation"
        }
    ],
    "sg:phone":"+1 209 394 4534",
    "sg:postcode":"95334",
    "sg:province":"CA",
    "sg:tags":[
        "operator",
        "local",
        "trucking"
    ],
    "wof:name":"Charles Koehn Trucking",
    "wof:placetype":"venue"
},
  "geometry": {"coordinates":[-120.759712,37.377916],"type":"Point"}
}