{
  "type": "Feature",
  "properties": {
    "addr:full":"2854 Triunfo Canyon Rd Agoura Hills CA 91301",
    "addr:housenumber":"2854",
    "addr:postcode":"91301",
    "addr:street":"Triunfo Canyon Rd",
    "iso:country":"US",
    "sg:address":"2854 Triunfo Canyon Rd",
    "sg:city":"Agoura Hills",
    "sg:classifiers":[
        {
            "category":"Travel",
            "subcategory":"Campground",
            "type":"Entertainment"
        }
    ],
    "sg:phone":"+1 818 889 2224",
    "sg:postcode":"91301",
    "sg:province":"CA",
    "sg:tags":[
        "camp"
    ],
    "sg:website":"www.campkeystone.com",
    "wof:name":"Camp Keystone",
    "wof:placetype":"venue"
},
  "geometry": {"coordinates":[-118.791619,34.121173],"type":"Point"}
}