{
  "type": "Feature",
  "properties": {
    "addr:full":"2305 Borchard Rd Newbury Park CA 91320",
    "addr:housenumber":"2305",
    "addr:postcode":"91320",
    "addr:street":"Borchard Rd",
    "iso:country":"US",
    "sg:address":"2305 Borchard Rd",
    "sg:city":"Newbury Park",
    "sg:classifiers":[
        {
            "category":"Autos & Motor Vehicles",
            "subcategory":"Fuel & Gas Station",
            "type":"Retail Goods"
        }
    ],
    "sg:phone":"+1 805 499 8585",
    "sg:postcode":"91320",
    "sg:province":"CA",
    "sg:tags":[
        "oil"
    ],
    "wof:name":"Newbury Park Mobil",
    "wof:placetype":"venue"
},
  "geometry": {"coordinates":[-118.92923999999999,34.180641],"type":"Point"}
}