{
  "type": "Feature",
  "properties": {
    "iso:country":"US",
    "sg:address":"17337 Ventura Blvd",
    "sg:city":"Encino",
    "sg:classifiers":[
        {
            "category":"Education",
            "subcategory":"Special Training",
            "type":"Public Place"
        }
    ],
    "sg:phone":"+1 818 728 0773",
    "sg:postcode":"91316",
    "sg:province":"CA",
    "sg:tags":[
        "tutoring"
    ],
    "wof:name":"Renee Lopez Educational",
    "wof:placetype":"venue"
},
  "geometry": {"coordinates":[-118.511008,34.161095],"type":"Point"}
}