{
  "type": "Feature",
  "properties": {
    "addr:full":"4035 Malone Dr Napa CA 94558",
    "addr:housenumber":"4035",
    "addr:postcode":"94558",
    "addr:street":"Malone Dr",
    "iso:country":"US",
    "sg:address":"4035 Malone Dr",
    "sg:city":"Napa",
    "sg:classifiers":[
        {
            "category":"Professional",
            "subcategory":"Computer Services",
            "type":"Services"
        }
    ],
    "sg:phone":"+1 707 224 9852",
    "sg:postcode":"94558",
    "sg:province":"CA",
    "sg:tags":[
        "programing",
        "custom"
    ],
    "sg:website":"www.grapeline.com",
    "wof:name":"Grapeline",
    "wof:placetype":"venue"
},
  "geometry": {"coordinates":[-122.341959,38.308746],"type":"Point"}
}