{
  "type": "Feature",
  "properties": {
    "addr:full":"968 Campbell Cir Woodland CA 95776",
    "addr:housenumber":"968",
    "addr:postcode":"95776",
    "addr:street":"Campbell Cir",
    "iso:country":"US",
    "sg:address":"968 Campbell Cir",
    "sg:city":"Woodland",
    "sg:classifiers":[
        {
            "category":"Recreation",
            "type":"Entertainment"
        }
    ],
    "sg:phone":"+1 530 304 1534",
    "sg:postcode":"95776",
    "sg:province":"CA",
    "sg:tags":[
        "club",
        "membership"
    ],
    "wof:name":"Db Paintball",
    "wof:placetype":"venue"
},
  "geometry": {"coordinates":[-121.74360900000001,38.665671],"type":"Point"}
}