{
  "type": "Feature",
  "properties": {
    "iso:country":"US",
    "sg:address":"6711 Forest Lawn Dr",
    "sg:city":"Los Angeles",
    "sg:classifiers":[
        {
            "category":"Manufacturing",
            "subcategory":"Signs",
            "type":"Manufacturing & Wholesale Goods"
        }
    ],
    "sg:phone":"+1 323 851 7402",
    "sg:postcode":"90068",
    "sg:province":"CA",
    "sg:tags":[
        "specialty",
        "mfg"
    ],
    "wof:name":"Paul Philo Vital Signs",
    "wof:placetype":"venue"
},
  "geometry": {"coordinates":[-118.341211,34.143288],"type":"Point"}
}