{
  "type": "Feature",
  "properties": {
    "iso:country":"US",
    "sg:address":"1007 Washington St",
    "sg:city":"Calistoga",
    "sg:classifiers":[
        {
            "category":"Organizations",
            "subcategory":"Non-profit Organization",
            "type":"Services"
        }
    ],
    "sg:phone":"+1 707 942 4222",
    "sg:postcode":"94515",
    "sg:province":"CA",
    "sg:tags":[
        "fund",
        "counselor",
        "raising"
    ],
    "wof:name":"Napa Valley Classic",
    "wof:placetype":"venue"
},
  "geometry": {"coordinates":[-122.57711,38.578116],"type":"Point"}
}