{
  "type": "Feature",
  "properties": {
    "iso:country":"US",
    "sg:address":"21040 Osborne St",
    "sg:city":"Canoga Park",
    "sg:classifiers":[
        {
            "category":"Autos & Motor Vehicles",
            "subcategory":"Automobile Sales",
            "type":"Retail Goods"
        }
    ],
    "sg:phone":"+1 818 718 1414",
    "sg:postcode":"91304",
    "sg:province":"CA",
    "sg:tags":[
        "equipment",
        "aircraft",
        "parts",
        "supply"
    ],
    "wof:name":"Iln Technologies",
    "wof:placetype":"venue"
},
  "geometry": {"coordinates":[-118.59176600000001,34.232963],"type":"Point"}
}