{
  "type": "Feature",
  "properties": {
    "addr:full":"3745 4th Avenue San Diego CA 92103",
    "addr:housenumber":"3745",
    "addr:postcode":"92103",
    "addr:street":"4Th Avenue",
    "iso:country":"US",
    "sg:address":"3745 4th Avenue",
    "sg:city":"San Diego",
    "sg:classifiers":[
        {
            "category":"Professional",
            "subcategory":"Lawyer & Legal Services",
            "type":"Services"
        }
    ],
    "sg:phone":"+1 619 298 6522",
    "sg:postcode":"92103",
    "sg:province":"CA",
    "wof:name":"Rojogarcia Jose C",
    "wof:placetype":"venue"
},
  "geometry": {"coordinates":[-117.161709,32.745489],"type":"Point"}
}