{
  "type": "Feature",
  "properties": {
    "addr:full":"5416 Ygnacio Valley Rd Ste 30 Concord CA 94521",
    "addr:housenumber":"5416",
    "addr:postcode":"94521",
    "addr:street":"Ygnacio Valley Rd Ste 30",
    "iso:country":"US",
    "sg:address":"5416 Ygnacio Valley Rd Ste 30",
    "sg:city":"Concord",
    "sg:classifiers":[
        {
            "category":"Sports & Exercise",
            "subcategory":"Gym",
            "type":"Entertainment"
        },
        {
            "category":"Arena",
            "subcategory":"Sports Club",
            "type":"Entertainment"
        }
    ],
    "sg:phone":"+1 925 288 9642",
    "sg:postcode":"94521",
    "sg:province":"CA",
    "sg:tags":[
        "health",
        "instruction",
        "yoga"
    ],
    "wof:name":"Sol Yoga",
    "wof:placetype":"venue"
},
  "geometry": {"coordinates":[-121.96024,37.949967],"type":"Point"}
}