{
  "type": "Feature",
  "properties": {
    "addr:full":"5410 70th St Sacramento CA 95820",
    "addr:housenumber":"5410",
    "addr:postcode":"95820",
    "addr:street":"70Th St",
    "iso:country":"US",
    "sg:address":"5410 70th St",
    "sg:city":"Sacramento",
    "sg:classifiers":[
        {
            "category":"Retail",
            "subcategory":"Portrait Studio",
            "type":"Services"
        }
    ],
    "sg:phone":"+1 916 383 5410",
    "sg:postcode":"95820",
    "sg:province":"CA",
    "sg:tags":[
        "photographer"
    ],
    "wof:name":"Kurt Ackerman Photography",
    "wof:placetype":"venue"
},
  "geometry": {"coordinates":[-121.421829,38.525716],"type":"Point"}
}