{
  "type": "Feature",
  "properties": {
    "iso:country":"US",
    "sg:address":"1320 Pine St",
    "sg:city":"Paso Robles",
    "sg:classifiers":[
        {
            "category":"Personal",
            "subcategory":"Beauty Salon",
            "type":"Services"
        }
    ],
    "sg:phone":"+1 805 238 5111",
    "sg:postcode":"93446",
    "sg:province":"CA",
    "wof:name":"Elegant Silhouette",
    "wof:placetype":"venue"
},
  "geometry": {"coordinates":[-120.688926,35.628762],"type":"Point"}
}