{
  "type": "Feature",
  "properties": {
    "addr:full":"5782 S Elm Ave Fresno CA 93706",
    "addr:housenumber":"5782",
    "addr:postcode":"93706",
    "addr:street":"S Elm Ave",
    "iso:country":"US",
    "sg:address":"5782 S Elm Ave",
    "sg:city":"Fresno",
    "sg:classifiers":[
        {
            "category":"Professional",
            "subcategory":"Accounting & Tax Preparation",
            "type":"Services"
        }
    ],
    "sg:phone":"+1 559 486 1025",
    "sg:postcode":"93706",
    "sg:province":"CA",
    "sg:tags":[
        "return",
        "filing"
    ],
    "wof:name":"Stella Ruiz Tax Preparer",
    "wof:placetype":"venue"
},
  "geometry": {"coordinates":[-119.790728,36.652168],"type":"Point"}
}