{
  "type": "Feature",
  "properties": {
    "iso:country":"US",
    "sg:address":"1937 26th Ave Apt 12",
    "sg:city":"Oakland",
    "sg:classifiers":[
        {
            "category":"Building & Trades",
            "subcategory":"Landscaping Services",
            "type":"Services"
        }
    ],
    "sg:phone":"+1 510 535 2551",
    "sg:postcode":"94601",
    "sg:province":"CA",
    "sg:website":"www.dawnlandscaping.com",
    "wof:name":"Dawn Landscaping Inc",
    "wof:placetype":"venue"
},
  "geometry": {"coordinates":[-122.228567,37.785215],"type":"Point"}
}