{
  "type": "Feature",
  "properties": {
    "iso:country":"US",
    "sg:address":"9292 Groton Dr",
    "sg:city":"Huntington Beach",
    "sg:classifiers":[
        {
            "category":"Building & Trades",
            "subcategory":"Construction",
            "type":"Services"
        }
    ],
    "sg:phone":"+1 714 593 0987",
    "sg:postcode":"92646",
    "sg:province":"CA",
    "sg:tags":[
        "contractor"
    ],
    "wof:name":"Tims Fences",
    "wof:placetype":"venue"
},
  "geometry": {"coordinates":[-117.965698,33.675344],"type":"Point"}
}