{
  "type": "Feature",
  "properties": {
    "iso:country":"US",
    "sg:address":"1611 Telegraph Ave",
    "sg:city":"Oakland",
    "sg:classifiers":[
        {
            "category":"Professional",
            "subcategory":"Lawyer & Legal Services",
            "type":"Services"
        }
    ],
    "sg:phone":"+1 510 451 3103",
    "sg:postcode":"94612",
    "sg:province":"CA",
    "wof:name":"Hess Leah",
    "wof:placetype":"venue"
},
  "geometry": {"coordinates":[-122.269997,37.806198],"type":"Point"}
}