{
  "type": "Feature",
  "properties": {
    "iso:country":"US",
    "sg:address":"525 N Andreason Dr",
    "sg:city":"Escondido",
    "sg:classifiers":[
        {
            "category":"Retail",
            "subcategory":"Auto Repair",
            "type":"Services"
        }
    ],
    "sg:phone":"+1 760 743 3484",
    "sg:postcode":"92029",
    "sg:province":"CA",
    "sg:tags":[
        "transmission"
    ],
    "wof:name":"Meca Transmissions",
    "wof:placetype":"venue"
},
  "geometry": {"coordinates":[-117.108186,33.120968],"type":"Point"}
}