{
  "type": "Feature",
  "properties": {
    "iso:country":"US",
    "sg:address":"4811 Chippendale Drive",
    "sg:city":"Sacramento",
    "sg:classifiers":[
        {
            "category":"Real Estate",
            "subcategory":"Real Estate Services",
            "type":"Services"
        }
    ],
    "sg:phone":"+1 916 349 3160",
    "sg:postcode":"95841",
    "sg:province":"CA",
    "sg:tags":[
        "management",
        "property"
    ],
    "sg:website":"www.riversidemanagement.com",
    "wof:name":"Riverside Property Management",
    "wof:placetype":"venue"
},
  "geometry": {"coordinates":[-121.352627,38.662872],"type":"Point"}
}