{
  "type": "Feature",
  "properties": {
    "iso:country":"US",
    "sg:address":"6320 Bethel Island Rd",
    "sg:city":"Bethel Island",
    "sg:classifiers":[
        {
            "category":"Recreation",
            "subcategory":"Marina",
            "type":"Entertainment"
        }
    ],
    "sg:phone":"+1 925 684 3671",
    "sg:postcode":"94511",
    "sg:province":"CA",
    "sg:tags":[
        "repairing",
        "boat"
    ],
    "wof:name":"Perry's Mercury Marine Svc",
    "wof:placetype":"venue"
},
  "geometry": {"coordinates":[-121.64050899999999,38.028099],"type":"Point"}
}