{
  "type": "Feature",
  "properties": {
    "addr:full":"395 del Norte Ave Yuba City CA 95991",
    "addr:housenumber":"395",
    "addr:postcode":"95991",
    "addr:street":"Del Norte Ave",
    "iso:country":"US",
    "sg:address":"395 del Norte Ave",
    "sg:city":"Yuba City",
    "sg:classifiers":[
        {
            "category":"Health Services",
            "subcategory":"Clinic",
            "type":"Services"
        }
    ],
    "sg:phone":"+1 530 755 0856",
    "sg:postcode":"95991",
    "sg:province":"CA",
    "wof:name":"Mountain Health Assoc",
    "wof:placetype":"venue"
},
  "geometry": {"coordinates":[-121.615409,39.145239],"type":"Point"}
}