{
  "type": "Feature",
  "properties": {
    "iso:country":"US",
    "sg:address":"36 Mary Ct",
    "sg:city":"Tracy",
    "sg:classifiers":[
        {
            "category":"Professional",
            "subcategory":"Business Services",
            "type":"Services"
        }
    ],
    "sg:phone":"+1 209 833 3200",
    "sg:postcode":"95376",
    "sg:province":"CA",
    "sg:tags":[
        "decorating",
        "contractor"
    ],
    "wof:name":"Parties R Us",
    "wof:placetype":"venue"
},
  "geometry": {"coordinates":[-121.427143,37.718883],"type":"Point"}
}