{
  "type": "Feature",
  "properties": {
    "addr:full":"5321 Claremont Ave Oakland CA 94618",
    "addr:housenumber":"5321",
    "addr:postcode":"94618",
    "addr:street":"Claremont Ave",
    "iso:country":"US",
    "sg:address":"5321 Claremont Ave",
    "sg:city":"Oakland",
    "sg:classifiers":[
        {
            "category":"Restaurant",
            "type":"Food & Drink"
        },
        {
            "category":"Retail",
            "subcategory":"Event Space",
            "type":"Services"
        }
    ],
    "sg:phone":"+1 510 653 9020",
    "sg:postcode":"94618",
    "sg:province":"CA",
    "sg:tags":[
        "venue",
        "italian"
    ],
    "sg:website":"colomboclub.org/",
    "wof:name":"Colombo Club Inc",
    "wof:placetype":"venue"
},
  "geometry": {"coordinates":[-122.261002,37.839298],"type":"Point"}
}