{
  "type": "Feature",
  "properties": {
    "iso:country":"US",
    "sg:address":"6721 Alturas Ave",
    "sg:city":"Stockton",
    "sg:classifiers":[
        {
            "category":"Building & Trades",
            "subcategory":"Plumbing",
            "type":"Services"
        }
    ],
    "sg:phone":"+1 209 951 2627",
    "sg:postcode":"95207",
    "sg:province":"CA",
    "sg:tags":[
        "air",
        "heating",
        "contractor"
    ],
    "wof:name":"Bobs H V A C-Hting Vntltion A",
    "wof:placetype":"venue"
},
  "geometry": {"coordinates":[-121.313211,38.014039],"type":"Point"}
}