{
  "type": "Feature",
  "properties": {
    "addr:full":"17337 Ventura Blvd Encino CA 91316",
    "addr:housenumber":"17337",
    "addr:postcode":"91316",
    "addr:street":"Ventura Blvd",
    "iso:country":"US",
    "sg:address":"17337 Ventura Blvd",
    "sg:city":"Encino",
    "sg:classifiers":[
        {
            "category":"Insurance",
            "subcategory":"Insurance Agent",
            "type":"Services"
        }
    ],
    "sg:phone":"+1 818 795 8848",
    "sg:postcode":"91316",
    "sg:province":"CA",
    "sg:tags":[
        "audit"
    ],
    "wof:name":"American Insurance Examiners",
    "wof:placetype":"venue"
},
  "geometry": {"coordinates":[-118.511008,34.161095],"type":"Point"}
}