{
  "type": "Feature",
  "properties": {
    "iso:country":"US",
    "sg:address":"335 el Dorado St",
    "sg:city":"Monterey",
    "sg:classifiers":[
        {
            "category":"Banks & Credit Unions",
            "subcategory":"Investment Brokerage",
            "type":"Services"
        }
    ],
    "sg:phone":"+1 831 657 0554",
    "sg:postcode":"93940",
    "sg:province":"CA",
    "sg:tags":[
        "management"
    ],
    "wof:name":"Precious Metals",
    "wof:placetype":"venue"
},
  "geometry": {"coordinates":[-121.89234399999999,36.591673],"type":"Point"}
}