{
  "type": "Feature",
  "properties": {
    "iso:country":"US",
    "sg:address":"1230 Corberosa Dr",
    "sg:city":"Arroyo Grande",
    "sg:classifiers":[
        {
            "category":"Real Estate",
            "subcategory":"Architect",
            "type":"Services"
        }
    ],
    "sg:phone":"+1 805 481 1466",
    "sg:postcode":"93420",
    "sg:province":"CA",
    "wof:name":"Puzzle Tree",
    "wof:placetype":"venue"
},
  "geometry": {"coordinates":[-120.567089,35.149048],"type":"Point"}
}