{
  "type": "Feature",
  "properties": {
    "addr:full":"10824 Glenhaven Way Rancho Cordova CA 95670",
    "addr:housenumber":"10824",
    "addr:postcode":"95670",
    "addr:street":"Glenhaven Way",
    "iso:country":"US",
    "sg:address":"10824 Glenhaven Way",
    "sg:city":"Rancho Cordova",
    "sg:classifiers":[
        {
            "category":"Professional",
            "subcategory":"Business Services",
            "type":"Services"
        }
    ],
    "sg:phone":"+1 916 761 1247",
    "sg:postcode":"95670",
    "sg:province":"CA",
    "sg:tags":[
        "event"
    ],
    "wof:name":"Capitol Valley Conference",
    "wof:placetype":"venue"
},
  "geometry": {"coordinates":[-121.28179,38.603407],"type":"Point"}
}