{
  "type": "Feature",
  "properties": {
    "addr:full":"13436 Lambert Rd Whittier CA 90605",
    "addr:housenumber":"13436",
    "addr:postcode":"90605",
    "addr:street":"Lambert Rd",
    "iso:country":"US",
    "sg:address":"13436 Lambert Rd",
    "sg:city":"Whittier",
    "sg:classifiers":[
        {
            "category":"Retail",
            "subcategory":"Auto Repair",
            "type":"Services"
        }
    ],
    "sg:phone":"+1 562 698 9451",
    "sg:postcode":"90605",
    "sg:province":"CA",
    "sg:tags":[
        "repairing",
        "automobile"
    ],
    "wof:name":"Mickey's Garage",
    "wof:placetype":"venue"
},
  "geometry": {"coordinates":[-118.037589,33.957985],"type":"Point"}
}