{
  "type": "Feature",
  "properties": {
    "addr:full":"16691 Gothard Street Huntington Beach CA 92647",
    "addr:postcode":"16691;92647",
    "addr:street":"Gothard Street",
    "iso:country":"US",
    "sg:address":"16691 Gothard Street",
    "sg:city":"Huntington Beach",
    "sg:classifiers":[
        {
            "category":"Building & Trades",
            "subcategory":"Construction",
            "type":"Services"
        }
    ],
    "sg:phone":"+1 714 375 6468",
    "sg:postcode":"92647",
    "sg:province":"CA",
    "sg:tags":[
        "air",
        "heating",
        "conditioning/hvac"
    ],
    "wof:name":"All Seasons Heating & Air Conditioning",
    "wof:placetype":"venue"
},
  "geometry": {"coordinates":[-118.000169,33.720048],"type":"Point"}
}