{
  "type": "Feature",
  "properties": {
    "iso:country":"US",
    "sg:address":"215 Cotter St",
    "sg:city":"San Francisco",
    "sg:classifiers":[
        {
            "category":"Education",
            "subcategory":"School",
            "type":"Public Place"
        }
    ],
    "sg:phone":"+1 415 584 1729",
    "sg:postcode":"94112",
    "sg:province":"CA",
    "wof:name":"S F Magnet Workshop",
    "wof:placetype":"venue"
},
  "geometry": {"coordinates":[-122.437336,37.729981],"type":"Point"}
}