{
  "type": "Feature",
  "properties": {
    "iso:country":"US",
    "sg:address":"16503 S Figueroa St",
    "sg:city":"Gardena",
    "sg:classifiers":[
        {
            "category":"Autos & Motor Vehicles",
            "subcategory":"Auto Supplies",
            "type":"Retail Goods"
        }
    ],
    "sg:phone":"+1 310 768 8882",
    "sg:postcode":"90248",
    "sg:province":"CA",
    "sg:tags":[
        "tire"
    ],
    "wof:name":"Speedy Tire Svc",
    "wof:placetype":"venue"
},
  "geometry": {"coordinates":[-118.282584,33.880161],"type":"Point"}
}