{
  "type": "Feature",
  "properties": {
    "addr:full":"14855 Oka Rd Los Gatos CA 95032",
    "addr:housenumber":"14855",
    "addr:postcode":"95032",
    "addr:street":"Oka Rd",
    "iso:country":"US",
    "sg:address":"14855 Oka Rd",
    "sg:city":"Los Gatos",
    "sg:classifiers":[
        {
            "category":"Social Services",
            "subcategory":"Child Care",
            "type":"Services"
        },
        {
            "category":"Education",
            "subcategory":"Preschool",
            "type":"Public Place"
        },
        {
            "category":"Sports & Exercise",
            "subcategory":"Sports Center",
            "type":"Entertainment"
        },
        {
            "category":"Education",
            "subcategory":"School",
            "type":"Public Place"
        }
    ],
    "sg:phone":"+1 408 358 3636",
    "sg:postcode":"95032",
    "sg:province":"CA",
    "sg:tags":[
        "elementary",
        "amateur",
        "day",
        "team"
    ],
    "wof:name":"Jewish Community Pre-School-Day Care",
    "wof:placetype":"venue"
},
  "geometry": {"coordinates":[-121.960999,37.2523],"type":"Point"}
}