{
  "type": "Feature",
  "properties": {
    "addr:full":"1262 W Anaheim St Harbor City CA 90710",
    "addr:housenumber":"1262",
    "addr:postcode":"90710",
    "addr:street":"W Anaheim St",
    "iso:country":"US",
    "sg:address":"1262 W Anaheim St",
    "sg:city":"Harbor City",
    "sg:classifiers":[
        {
            "category":"Professional",
            "subcategory":"Management & Consulting",
            "type":"Services"
        }
    ],
    "sg:phone":"+1 310 326 9842",
    "sg:postcode":"90710",
    "sg:province":"CA",
    "sg:tags":[
        "party",
        "planning"
    ],
    "wof:name":"International Events",
    "wof:placetype":"venue"
},
  "geometry": {"coordinates":[-118.298508,33.782585],"type":"Point"}
}