{
  "type": "Feature",
  "properties": {
    "addr:full":"2400 Jefferson St. Torrance CA 90501",
    "addr:housenumber":"2400",
    "addr:postcode":"90501",
    "addr:street":"Jefferson St.",
    "iso:country":"US",
    "sg:address":"2400 Jefferson St.",
    "sg:city":"Torrance",
    "sg:classifiers":[
        {
            "category":"Transit Center",
            "subcategory":"Passenger",
            "type":"Transportation"
        }
    ],
    "sg:postcode":"90501",
    "sg:province":"CA",
    "wof:name":"Hollywood Bowl Shuttle at ?Wilson Park",
    "wof:placetype":"venue"
},
  "geometry": {"coordinates":[-118.32682,33.827624],"type":"Point"}
}