{
  "type": "Feature",
  "properties": {
    "addr:full":"723 Gibbons St Los Angeles CA 90031",
    "addr:housenumber":"723",
    "addr:postcode":"90031",
    "addr:street":"Gibbons St",
    "iso:country":"US",
    "sg:address":"723 Gibbons St",
    "sg:city":"Los Angeles",
    "sg:classifiers":[
        {
            "category":"Wholesale",
            "subcategory":"Wine & Distilled Alcoholic Beverages",
            "type":"Manufacturing & Wholesale Goods"
        }
    ],
    "sg:phone":"+1 323 223 9686",
    "sg:postcode":"90031",
    "sg:province":"CA",
    "sg:tags":[
        "warehouse"
    ],
    "wof:name":"Caltra Corporation",
    "wof:placetype":"venue"
},
  "geometry": {"coordinates":[-118.224858,34.064064],"type":"Point"}
}