{
  "type": "Feature",
  "properties": {
    "iso:country":"US",
    "sg:address":"1135 E Las Tunas Dr",
    "sg:city":"San Gabriel",
    "sg:classifiers":[
        {
            "category":"Personal",
            "subcategory":"Massage",
            "type":"Services"
        }
    ],
    "sg:phone":"+1 626 291 2588",
    "sg:postcode":"91776",
    "sg:province":"CA",
    "sg:website":"hongshengfootmassage.com/",
    "wof:name":"Hong Sheng Foot Massage",
    "wof:placetype":"venue"
},
  "geometry": {"coordinates":[-118.08277699999999,34.103476],"type":"Point"}
}