{
  "type": "Feature",
  "properties": {
    "iso:country":"US",
    "sg:address":"68 Belle Mill Rd",
    "sg:city":"Red Bluff",
    "sg:classifiers":[
        {
            "category":"Food & Beverages",
            "subcategory":"Groceries & Convenience Stores",
            "type":"Retail Goods"
        }
    ],
    "sg:phone":"+1 530 529 1758",
    "sg:postcode":"96080",
    "sg:province":"CA",
    "wof:name":"Friendly Gas Mart",
    "wof:placetype":"venue"
},
  "geometry": {"coordinates":[-122.220034,40.186195],"type":"Point"}
}