{
  "type": "Feature",
  "properties": {
    "iso:country":"US",
    "sg:address":"1700 S Chester Ave",
    "sg:city":"Bakersfield",
    "sg:classifiers":[
        {
            "category":"Food & Beverages",
            "subcategory":"Groceries & Convenience Stores",
            "type":"Retail Goods"
        }
    ],
    "sg:phone":"+1 661 835 7711",
    "sg:postcode":"93304",
    "sg:province":"CA",
    "wof:name":"Snappy Food Store",
    "wof:placetype":"venue"
},
  "geometry": {"coordinates":[-119.018329,35.338699],"type":"Point"}
}