{
  "type": "Feature",
  "properties": {
    "iso:country":"US",
    "sg:address":"1630 W 3rd St",
    "sg:city":"Los Angeles",
    "sg:classifiers":[
        {
            "category":"Taxi",
            "type":"Transportation"
        }
    ],
    "sg:phone":"+1 213 484 8181",
    "sg:postcode":"90017",
    "sg:province":"CA",
    "sg:tags":[
        "taxicab"
    ],
    "wof:name":"Center Cab",
    "wof:placetype":"venue"
},
  "geometry": {"coordinates":[-118.266426,34.060096],"type":"Point"}
}