{
  "type": "Feature",
  "properties": {
    "iso:country":"US",
    "sg:address":"7021 Oak Creek Rd",
    "sg:city":"Mojave",
    "sg:classifiers":[
        {
            "category":"Wholesale",
            "subcategory":"Hardware",
            "type":"Manufacturing & Wholesale Goods"
        }
    ],
    "sg:phone":"+1 661 824 8790",
    "sg:postcode":"93501",
    "sg:province":"CA",
    "sg:tags":[
        "energy",
        "system",
        "wind"
    ],
    "wof:name":"Difko Service Corp",
    "wof:placetype":"venue"
},
  "geometry": {"coordinates":[-118.249804,35.039469],"type":"Point"}
}