{
  "type": "Feature",
  "properties": {
    "addr:full":"8320 Parkway Dr La Mesa CA 91942",
    "addr:housenumber":"8320",
    "addr:postcode":"91942",
    "addr:street":"Parkway Dr",
    "iso:country":"US",
    "sg:address":"8320 Parkway Dr",
    "sg:city":"La Mesa",
    "sg:classifiers":[
        {
            "category":"Wholesale",
            "subcategory":"Books, Periodicals, & Newspapers",
            "type":"Manufacturing & Wholesale Goods"
        }
    ],
    "sg:phone":"+1 619 463 3655",
    "sg:postcode":"91942",
    "sg:province":"CA",
    "sg:tags":[
        "dealer"
    ],
    "wof:name":"Ensign Books",
    "wof:placetype":"venue"
},
  "geometry": {"coordinates":[-117.016899,32.779076],"type":"Point"}
}