{
  "type": "Feature",
  "properties": {
    "addr:full":"9955 Mesa Rim Rd San Diego CA 92121",
    "addr:housenumber":"9955",
    "addr:postcode":"92121",
    "addr:street":"Mesa Rim Rd",
    "iso:country":"US",
    "sg:address":"9955 Mesa Rim Rd",
    "sg:city":"San Diego",
    "sg:classifiers":[
        {
            "category":"Freight",
            "type":"Transportation"
        }
    ],
    "sg:phone":"+1 619 865 8940",
    "sg:postcode":"92121",
    "sg:province":"CA",
    "sg:tags":[
        "general"
    ],
    "wof:name":"Big Box Storage Inc",
    "wof:placetype":"venue"
},
  "geometry": {"coordinates":[-117.17750100000001,32.899922],"type":"Point"}
}