{
  "type": "Feature",
  "properties": {
    "iso:country":"US",
    "sg:address":"3418 Mendocino Ave",
    "sg:city":"Santa Rosa",
    "sg:classifiers":[
        {
            "category":"Real Estate",
            "subcategory":"Real Estate Agent",
            "type":"Services"
        }
    ],
    "sg:phone":"+1 707 576 0700",
    "sg:postcode":"95403",
    "sg:province":"CA",
    "sg:tags":[
        "management"
    ],
    "wof:name":"Sierra West Property Mgmt",
    "wof:placetype":"venue"
},
  "geometry": {"coordinates":[-122.726127,38.472972],"type":"Point"}
}