{
  "type": "Feature",
  "properties": {
    "iso:country":"US",
    "sg:address":"3838 California St",
    "sg:city":"San Francisco",
    "sg:classifiers":[
        {
            "category":"Health Services",
            "subcategory":"Doctor",
            "type":"Services"
        }
    ],
    "sg:phone":"+1 415 668 0411",
    "sg:postcode":"94118",
    "sg:province":"CA",
    "wof:name":"Chung T Phillip MD",
    "wof:placetype":"venue"
},
  "geometry": {"coordinates":[-122.4577,37.786007],"type":"Point"}
}