{
  "type": "Feature",
  "properties": {
    "iso:country":"US",
    "sg:address":"601 N 1st St",
    "sg:city":"San Jose",
    "sg:classifiers":[
        {
            "category":"Utilities",
            "subcategory":"Telephone",
            "type":"Services"
        }
    ],
    "sg:phone":"+1 408 286 6692",
    "sg:postcode":"95112",
    "sg:province":"CA",
    "sg:tags":[
        "communications"
    ],
    "wof:name":"Cnss Inc",
    "wof:placetype":"venue"
},
  "geometry": {"coordinates":[-121.898593,37.346948],"type":"Point"}
}