{
  "type": "Feature",
  "properties": {
    "addr:full":"738 S Fairoaks Ave Sunnyvale CA 94086",
    "addr:housenumber":"738",
    "addr:postcode":"94086",
    "addr:street":"S Fairoaks Ave",
    "iso:country":"US",
    "sg:address":"738 S Fairoaks Ave",
    "sg:city":"Sunnyvale",
    "sg:classifiers":[
        {
            "category":"Restaurant",
            "type":"Food & Drink"
        }
    ],
    "sg:phone":"+1 408 992 1060",
    "sg:postcode":"94086",
    "sg:province":"CA",
    "sg:tags":[
        "mexican"
    ],
    "wof:name":"Garcia's Taqueria",
    "wof:placetype":"venue"
},
  "geometry": {"coordinates":[-122.024002,37.363998],"type":"Point"}
}