{
  "type": "Feature",
  "properties": {
    "iso:country":"US",
    "sg:address":"2976 State Hwy 49",
    "sg:city":"Cool",
    "sg:classifiers":[
        {
            "category":"Personal",
            "subcategory":"Beauty Salon",
            "type":"Services"
        }
    ],
    "sg:phone":"+1 530 823 8331",
    "sg:postcode":"95614",
    "sg:province":"CA",
    "wof:name":"Cher's Hair Salon In Cool",
    "wof:placetype":"venue"
},
  "geometry": {"coordinates":[-121.01588700000001,38.885237],"type":"Point"}
}