{
  "type": "Feature",
  "properties": {
    "addr:full":"1300 Ethan Way Sacramento CA 95825",
    "addr:housenumber":"1300",
    "addr:postcode":"95825",
    "addr:street":"Ethan Way",
    "iso:country":"US",
    "sg:address":"1300 Ethan Way",
    "sg:city":"Sacramento",
    "sg:classifiers":[
        {
            "category":"Professional",
            "subcategory":"Secretarial Services",
            "type":"Services"
        }
    ],
    "sg:phone":"+1 916 921 1397",
    "sg:postcode":"95825",
    "sg:province":"CA",
    "sg:tags":[
        "convention",
        "court",
        "reporter"
    ],
    "wof:name":"Moa Deposition Reporters",
    "wof:placetype":"venue"
},
  "geometry": {"coordinates":[-121.420019,38.593201],"type":"Point"}
}