{
  "type": "Feature",
  "properties": {
    "addr:full":"100 N Tower Sq Tulare CA 93274",
    "addr:housenumber":"100",
    "addr:postcode":"93274",
    "addr:street":"N Tower Sq",
    "iso:country":"US",
    "sg:address":"100 N Tower Sq",
    "sg:city":"Tulare",
    "sg:classifiers":[
        {
            "category":"Restaurant",
            "type":"Food & Drink"
        }
    ],
    "sg:phone":"+1 559 686 3546",
    "sg:postcode":"93274",
    "sg:province":"CA",
    "sg:tags":[
        "mexican"
    ],
    "wof:name":"Taqueria Mi Ranchito",
    "wof:placetype":"venue"
},
  "geometry": {"coordinates":[-119.34760300000001,36.20953],"type":"Point"}
}