{
  "type": "Feature",
  "properties": {
    "addr:full":"5938 N Figueroa St Los Angeles CA 90042",
    "addr:housenumber":"5938",
    "addr:postcode":"90042",
    "addr:street":"N Figueroa St",
    "iso:country":"US",
    "sg:address":"5938 N Figueroa St",
    "sg:city":"Los Angeles",
    "sg:classifiers":[
        {
            "category":"Shopping",
            "subcategory":"Jewelry",
            "type":"Retail Goods"
        }
    ],
    "sg:phone":"+1 323 478 2734",
    "sg:postcode":"90042",
    "sg:province":"CA",
    "wof:name":"Highland Park Jewelry",
    "wof:placetype":"venue"
},
  "geometry": {"coordinates":[-118.189717,34.110946],"type":"Point"}
}