{
  "type": "Feature",
  "properties": {
    "addr:full":"12204 Downey Ave Downey CA 90242",
    "addr:housenumber":"12204",
    "addr:postcode":"90242",
    "addr:street":"Downey Ave",
    "iso:country":"US",
    "sg:address":"12204 Downey Ave",
    "sg:city":"Downey",
    "sg:classifiers":[
        {
            "category":"Manufacturing",
            "subcategory":"Tools & Machinery",
            "type":"Manufacturing & Wholesale Goods"
        }
    ],
    "sg:phone":"+1 562 622 7787",
    "sg:postcode":"90242",
    "sg:province":"CA",
    "sg:tags":[
        "dental",
        "mfg"
    ],
    "wof:name":"Twins Dental Studio",
    "wof:placetype":"venue"
},
  "geometry": {"coordinates":[-118.142551,33.926842],"type":"Point"}
}