{
  "type": "Feature",
  "properties": {
    "iso:country":"US",
    "sg:address":"525 Yorktown Ave",
    "sg:city":"Huntington Beach",
    "sg:classifiers":[
        {
            "category":"Education",
            "subcategory":"School",
            "type":"Public Place"
        }
    ],
    "sg:phone":"+1 714 536 7521",
    "sg:postcode":"92648",
    "sg:province":"CA",
    "sg:tags":[
        "high",
        "middle",
        "elementary"
    ],
    "wof:name":"Huntington Beach Union High School District",
    "wof:placetype":"venue"
},
  "geometry": {"coordinates":[-117.992773,33.679472],"type":"Point"}
}