{
  "type": "Feature",
  "properties": {
    "iso:country":"US",
    "sg:address":"10031 W River St",
    "sg:city":"Truckee",
    "sg:classifiers":[
        {
            "category":"Wholesale",
            "subcategory":"Durable Goods & Equipment",
            "type":"Manufacturing & Wholesale Goods"
        }
    ],
    "sg:phone":"+1 530 550 8216",
    "sg:postcode":"96161",
    "sg:province":"CA",
    "wof:name":"Finnegans Finds",
    "wof:placetype":"venue"
},
  "geometry": {"coordinates":[-120.184185,39.327067],"type":"Point"}
}