{
  "type": "Feature",
  "properties": {
    "addr:full":"1160 23rd St Richmond CA 94804",
    "addr:housenumber":"1160",
    "addr:postcode":"94804",
    "addr:street":"23Rd St",
    "iso:country":"US",
    "sg:address":"1160 23rd St",
    "sg:city":"Richmond",
    "sg:classifiers":[
        {
            "category":"Restaurant",
            "type":"Food & Drink"
        }
    ],
    "sg:phone":"+1 510 215 9159",
    "sg:postcode":"94804",
    "sg:province":"CA",
    "sg:tags":[
        "deli",
        "delicatessen"
    ],
    "wof:name":"Mario's Deli",
    "wof:placetype":"venue"
},
  "geometry": {"coordinates":[-122.34699999999999,37.9505],"type":"Point"}
}