{
  "type": "Feature",
  "properties": {
    "iso:country":"US",
    "sg:address":"3725 Noriega St",
    "sg:city":"San Francisco",
    "sg:classifiers":[
        {
            "category":"Sports & Exercise",
            "subcategory":"Gym",
            "type":"Entertainment"
        }
    ],
    "sg:phone":"+1 415 564 4734",
    "sg:postcode":"94122",
    "sg:province":"CA",
    "sg:tags":[
        "club",
        "health",
        "studio",
        "gymnasium"
    ],
    "sg:website":"www.libertyfitness.com",
    "wof:name":"Liberty Fitness Ctr",
    "wof:placetype":"venue"
},
  "geometry": {"coordinates":[-122.504122,37.752949],"type":"Point"}
}