{
  "type": "Feature",
  "properties": {
    "iso:country":"US",
    "sg:address":"888 Brannan St",
    "sg:city":"San Francisco",
    "sg:classifiers":[
        {
            "category":"Professional",
            "subcategory":"Management & Consulting",
            "type":"Services"
        }
    ],
    "sg:phone":"+1 415 437 3230",
    "sg:postcode":"94103",
    "sg:province":"CA",
    "sg:tags":[
        "consultant",
        "business"
    ],
    "wof:name":"Jim Lauber & Assoc",
    "wof:placetype":"venue"
},
  "geometry": {"coordinates":[-122.40449,37.772337],"type":"Point"}
}