{
  "type": "Feature",
  "properties": {
    "iso:country":"US",
    "sg:address":"11975 el Camino Real",
    "sg:city":"San Diego",
    "sg:classifiers":[
        {
            "category":"Professional",
            "subcategory":"Lawyer & Legal Services",
            "type":"Services"
        }
    ],
    "sg:phone":"+1 858 792 0973",
    "sg:postcode":"92130",
    "sg:province":"CA",
    "sg:tags":[
        "attorney"
    ],
    "wof:name":"Kolodny & Pressman",
    "wof:placetype":"venue"
},
  "geometry": {"coordinates":[-117.237189,32.935062],"type":"Point"}
}