{
  "type": "Feature",
  "properties": {
    "addr:full":"249 W Jefferson Blvd Los Angeles CA 90007",
    "addr:housenumber":"249",
    "addr:postcode":"90007",
    "addr:street":"W Jefferson Blvd",
    "iso:country":"US",
    "sg:address":"249 W Jefferson Blvd",
    "sg:city":"Los Angeles",
    "sg:classifiers":[
        {
            "category":"Professional",
            "subcategory":"Lawyer & Legal Services",
            "type":"Services"
        }
    ],
    "sg:phone":"+1 213 742 0539",
    "sg:postcode":"90007",
    "sg:province":"CA",
    "wof:name":"Elite Attorney Center",
    "wof:placetype":"venue"
},
  "geometry": {"coordinates":[-118.275437,34.004197],"type":"Point"}
}