{
  "type": "Feature",
  "properties": {
    "addr:full":"1420 el Paseo de Saratoga San Jose CA 95130",
    "addr:housenumber":"1420",
    "addr:postcode":"95130",
    "addr:street":"El Paseo De Saratoga",
    "iso:country":"US",
    "sg:address":"1420 el Paseo de Saratoga",
    "sg:city":"San Jose",
    "sg:classifiers":[
        {
            "category":"Shopping",
            "type":"Retail Goods"
        }
    ],
    "sg:phone":"+1 408 866 8669",
    "sg:postcode":"95130",
    "sg:province":"CA",
    "sg:tags":[
        "art",
        "gallery",
        "dealer"
    ],
    "wof:name":"Corners",
    "wof:placetype":"venue"
},
  "geometry": {"coordinates":[-121.99047299999999,37.289533],"type":"Point"}
}