{
  "type": "Feature",
  "properties": {
    "iso:country":"US",
    "sg:address":"3900 Sisk Rd",
    "sg:city":"Modesto",
    "sg:classifiers":[
        {
            "category":"Shopping",
            "subcategory":"Computers & Home Electronics",
            "type":"Retail Goods"
        }
    ],
    "sg:phone":"+1 209 571 1700",
    "sg:postcode":"95356",
    "sg:province":"CA",
    "sg:tags":[
        "equipment",
        "electronic",
        "supply"
    ],
    "wof:name":"Good Guys",
    "wof:placetype":"venue"
},
  "geometry": {"coordinates":[-121.06899799999999,37.698142],"type":"Point"}
}