{
  "type": "Feature",
  "properties": {
    "addr:full":"1278 Alma Ct San Jose CA 95112",
    "addr:housenumber":"1278",
    "addr:postcode":"95112",
    "addr:street":"Alma Ct",
    "iso:country":"US",
    "sg:address":"1278 Alma Ct",
    "sg:city":"San Jose",
    "sg:classifiers":[
        {
            "category":"Food & Beverages",
            "subcategory":"Groceries & Convenience Stores",
            "type":"Retail Goods"
        }
    ],
    "sg:phone":"+1 408 299 0338",
    "sg:postcode":"95112",
    "sg:province":"CA",
    "wof:name":"Water Warehouse",
    "wof:placetype":"venue"
},
  "geometry": {"coordinates":[-121.8724,37.317522],"type":"Point"}
}