{
  "type": "Feature",
  "properties": {
    "iso:country":"US",
    "sg:address":"4695 W State Hwy 140",
    "sg:city":"Merced",
    "sg:classifiers":[
        {
            "category":"Wholesale",
            "subcategory":"Machinery & Supplies",
            "type":"Manufacturing & Wholesale Goods"
        }
    ],
    "sg:phone":"+1 209 383 2919",
    "sg:postcode":"95340",
    "sg:province":"CA",
    "sg:tags":[
        "equipment",
        "dairy"
    ],
    "wof:name":"Central California Silage",
    "wof:placetype":"venue"
},
  "geometry": {"coordinates":[-120.57095700000001,37.302275],"type":"Point"}
}