{
  "type": "Feature",
  "properties": {
    "addr:full":"6003 Monticello Rd Napa CA 94558",
    "addr:housenumber":"6003",
    "addr:postcode":"94558",
    "addr:street":"Monticello Rd",
    "iso:country":"US",
    "sg:address":"6003 Monticello Rd",
    "sg:city":"Napa",
    "sg:classifiers":[
        {
            "category":"Bars & Pubs",
            "type":"Food & Drink"
        }
    ],
    "sg:phone":"+1 707 252 2741",
    "sg:postcode":"94558",
    "sg:province":"CA",
    "wof:name":"Corners",
    "wof:placetype":"venue"
},
  "geometry": {"coordinates":[-122.20545300000001,38.436098],"type":"Point"}
}