{
  "type": "Feature",
  "properties": {
    "addr:full":"299 E San Ysidro Blvd San Ysidro CA 92173",
    "addr:housenumber":"299",
    "addr:postcode":"92173",
    "addr:street":"E San Ysidro Blvd",
    "iso:country":"US",
    "sg:address":"299 E San Ysidro Blvd",
    "sg:city":"San Ysidro",
    "sg:classifiers":[
        {
            "category":"Parking",
            "type":"Transportation"
        }
    ],
    "sg:phone":"+1 619 428 1404",
    "sg:postcode":"92173",
    "sg:province":"CA",
    "sg:tags":[
        "garage"
    ],
    "wof:name":"Sevels Garage",
    "wof:placetype":"venue"
},
  "geometry": {"coordinates":[-117.040611,32.551915],"type":"Point"}
}