{
  "type": "Feature",
  "properties": {
    "addr:full":"8450 Central Ave Newark CA 94560",
    "addr:housenumber":"8450",
    "addr:postcode":"94560",
    "addr:street":"Central Ave",
    "iso:country":"US",
    "sg:address":"8450 Central Ave",
    "sg:city":"Newark",
    "sg:classifiers":[
        {
            "category":"Manufacturing",
            "subcategory":"Electronics",
            "type":"Manufacturing & Wholesale Goods"
        }
    ],
    "sg:phone":"+1 510 797 9600",
    "sg:postcode":"94560",
    "sg:province":"CA",
    "sg:tags":[
        "instrument",
        "electronic"
    ],
    "wof:name":"INET Corp",
    "wof:placetype":"venue"
},
  "geometry": {"coordinates":[-122.039492,37.519591],"type":"Point"}
}