{
  "type": "Feature",
  "properties": {
    "addr:full":"12928 Pioneer Blvd Norwalk CA 90650",
    "addr:housenumber":"12928",
    "addr:postcode":"90650",
    "addr:street":"Pioneer Blvd",
    "iso:country":"US",
    "sg:address":"12928 Pioneer Blvd",
    "sg:city":"Norwalk",
    "sg:classifiers":[
        {
            "category":"Wholesale",
            "subcategory":"Auto Parts",
            "type":"Manufacturing & Wholesale Goods"
        }
    ],
    "sg:phone":"+1 562 868 2008",
    "sg:postcode":"90650",
    "sg:province":"CA",
    "sg:tags":[
        "tire"
    ],
    "wof:name":"Michelin Evaluation Center",
    "wof:placetype":"venue"
},
  "geometry": {"coordinates":[-118.081608,33.912236],"type":"Point"}
}