{
  "type": "Feature",
  "properties": {
    "iso:country":"US",
    "sg:address":"5020 Pedley Rd",
    "sg:city":"Riverside",
    "sg:classifiers":[
        {
            "category":"Wholesale",
            "subcategory":"Plants",
            "type":"Manufacturing & Wholesale Goods"
        },
        {
            "category":"Building & Trades",
            "subcategory":"Landscaping Services",
            "type":"Services"
        }
    ],
    "sg:phone":"+1 951 681 9771",
    "sg:postcode":"92509",
    "sg:province":"CA",
    "sg:tags":[
        "nursery",
        "tree",
        "supply"
    ],
    "wof:name":"Trees Unlimited Inc",
    "wof:placetype":"venue"
},
  "geometry": {"coordinates":[-117.475335,33.996777],"type":"Point"}
}