{
  "type": "Feature",
  "properties": {
    "iso:country":"US",
    "sg:address":"3110 Camino Del Rio S",
    "sg:city":"San Diego",
    "sg:classifiers":[
        {
            "category":"Banks & Credit Unions",
            "subcategory":"Financial Services",
            "type":"Services"
        }
    ],
    "sg:phone":"+1 619 325 0688",
    "sg:postcode":"92108",
    "sg:province":"CA",
    "sg:tags":[
        "broker",
        "mortgage"
    ],
    "wof:name":"E Sage Inc",
    "wof:placetype":"venue"
},
  "geometry": {"coordinates":[-117.12510899999999,32.773556],"type":"Point"}
}