{
  "type": "Feature",
  "properties": {
    "addr:full":"2429 Fairmont Dr Hanford CA 93230",
    "addr:housenumber":"2429",
    "addr:postcode":"ca 93230",
    "addr:street":"Fairmont Dr",
    "iso:country":"US",
    "sg:address":"2429 Fairmont Dr",
    "sg:city":"Hanford",
    "sg:classifiers":[
        {
            "category":"Shopping",
            "subcategory":"Computers & Home Electronics",
            "type":"Retail Goods"
        }
    ],
    "sg:phone":"+1 559 584 9224",
    "sg:postcode":"93230",
    "sg:province":"CA",
    "wof:name":"Jerrys Computers",
    "wof:placetype":"venue"
},
  "geometry": {"coordinates":[-119.639674,36.355624],"type":"Point"}
}