{
  "type": "Feature",
  "properties": {
    "iso:country":"US",
    "sg:address":"1052 E El Camino Real",
    "sg:city":"Sunnyvale",
    "sg:classifiers":[
        {
            "category":"Health Services",
            "subcategory":"Chiropractor",
            "type":"Services"
        }
    ],
    "sg:phone":"+1 408 248 7960",
    "sg:postcode":"94087",
    "sg:province":"CA",
    "sg:website":"www.bellplazachiro.com",
    "wof:name":"Bell Plaza Chiropractic Office",
    "wof:placetype":"venue"
},
  "geometry": {"coordinates":[-122.00700399999999,37.352001],"type":"Point"}
}