{
  "type": "Feature",
  "properties": {
    "addr:full":"710 S Grand Ave Glendora CA 91740",
    "addr:housenumber":"710",
    "addr:postcode":"91740",
    "addr:street":"S Grand Ave",
    "iso:country":"US",
    "sg:address":"710 S Grand Ave",
    "sg:city":"Glendora",
    "sg:phone":"+1 626 914 9126",
    "sg:postcode":"91740",
    "sg:province":"CA",
    "wof:name":"Grand Burger",
    "wof:placetype":"venue"
},
  "geometry": {"coordinates":[-117.87258199999999,34.126544],"type":"Point"}
}