{
  "type": "Feature",
  "properties": {
    "addr:full":"3237 Canonita Dr Fallbrook CA 92028",
    "addr:housenumber":"3237",
    "addr:postcode":"92028",
    "addr:street":"Canonita Dr",
    "iso:country":"US",
    "sg:address":"3237 Canonita Dr",
    "sg:city":"Fallbrook",
    "sg:classifiers":[
        {
            "category":"Communications",
            "type":"Services"
        }
    ],
    "sg:phone":"+1 760 723 8084",
    "sg:postcode":"92028",
    "sg:province":"CA",
    "wof:name":"Coliance Communications",
    "wof:placetype":"venue"
},
  "geometry": {"coordinates":[-117.18901700000001,33.355282],"type":"Point"}
}