{
  "type": "Feature",
  "properties": {
    "addr:full":"106 Beach St Santa Cruz CA 95067",
    "addr:housenumber":"106",
    "addr:postcode":"95067",
    "addr:street":"Beach St",
    "iso:country":"US",
    "sg:address":"106 Beach St",
    "sg:city":"Santa Cruz",
    "sg:classifiers":[
        {
            "category":"Bars & Pubs",
            "type":"Food & Drink"
        },
        {
            "category":"Restaurant",
            "type":"Food & Drink"
        }
    ],
    "sg:phone":"+1 831 423 5271",
    "sg:postcode":"95067",
    "sg:province":"CA",
    "sg:website":"www.idealbarandgrill.com",
    "wof:name":"Ideal Bar & Grill",
    "wof:placetype":"venue"
},
  "geometry": {"coordinates":[-122.014517,36.965329],"type":"Point"}
}