{
  "type": "Feature",
  "properties": {
    "iso:country":"US",
    "sg:address":"3136 W Black Hills Ct",
    "sg:city":"Thousand Oaks",
    "sg:classifiers":[
        {
            "category":"Wholesale",
            "subcategory":"Medical Equipment & Supplies",
            "type":"Manufacturing & Wholesale Goods"
        }
    ],
    "sg:phone":"+1 805 370 0771",
    "sg:postcode":"91362",
    "sg:province":"CA",
    "sg:tags":[
        "process",
        "crystal",
        "oxide",
        "buy",
        "machinery"
    ],
    "wof:name":"Michael Skinnerfield Co",
    "wof:placetype":"venue"
},
  "geometry": {"coordinates":[-118.826048,34.171501],"type":"Point"}
}