{
  "type": "Feature",
  "properties": {
    "addr:full":"444 E Monterey Ave Pomona CA 91767",
    "addr:housenumber":"444",
    "addr:postcode":"91767",
    "addr:street":"E Monterey Ave",
    "iso:country":"US",
    "sg:address":"444 E Monterey Ave",
    "sg:city":"Pomona",
    "sg:classifiers":[
        {
            "category":"Retail",
            "subcategory":"Auto Repair",
            "type":"Services"
        }
    ],
    "sg:phone":"+1 909 620 3848",
    "sg:postcode":"91767",
    "sg:province":"CA",
    "sg:tags":[
        "machine",
        "automobile",
        "shop"
    ],
    "wof:name":"O & M Machine & Auto Repair",
    "wof:placetype":"venue"
},
  "geometry": {"coordinates":[-117.742949,34.060661],"type":"Point"}
}