{
  "type": "Feature",
  "properties": {
    "iso:country":"US",
    "sg:address":"1400 E Katella Ave",
    "sg:city":"Orange",
    "sg:classifiers":[
        {
            "category":"Banks & Credit Unions",
            "subcategory":"Investment Brokerage",
            "type":"Services"
        }
    ],
    "sg:phone":"+1 714 639 1013",
    "sg:postcode":"92867",
    "sg:province":"CA",
    "sg:tags":[
        "investing"
    ],
    "wof:name":"Fourels Investments The",
    "wof:placetype":"venue"
},
  "geometry": {"coordinates":[-117.838707,33.808967],"type":"Point"}
}