{
  "type": "Feature",
  "properties": {
    "addr:full":"8360 Melrose Ave Los Angeles CA 90069",
    "addr:housenumber":"8360",
    "addr:postcode":"90069",
    "addr:street":"Melrose Ave",
    "iso:country":"US",
    "sg:address":"8360 Melrose Ave",
    "sg:city":"Los Angeles",
    "sg:classifiers":[
        {
            "category":"Professional",
            "type":"Services"
        }
    ],
    "sg:phone":"+1 323 951 1050",
    "sg:postcode":"90069",
    "sg:province":"CA",
    "sg:tags":[
        "establishment"
    ],
    "wof:name":"Tricash",
    "wof:placetype":"venue"
},
  "geometry": {"coordinates":[-118.373082,34.083563],"type":"Point"}
}