{
  "type": "Feature",
  "properties": {
    "addr:full":"4922 3rd St San Francisco CA 94124",
    "addr:housenumber":"4922",
    "addr:postcode":"94124",
    "addr:street":"3Rd St",
    "iso:country":"US",
    "sg:address":"4922 3rd St",
    "sg:city":"San Francisco",
    "sg:classifiers":[
        {
            "category":"Shopping",
            "type":"Retail Goods"
        }
    ],
    "sg:phone":"+1 415 822 3803",
    "sg:postcode":"94124",
    "sg:province":"CA",
    "sg:tags":[
        "cosmetic",
        "perfume"
    ],
    "wof:name":"Brighter Image Cosmetics Ctr",
    "wof:placetype":"venue"
},
  "geometry": {"coordinates":[-122.39132499999999,37.733429],"type":"Point"}
}