{
  "type": "Feature",
  "properties": {
    "iso:country":"US",
    "sg:address":"16531 Bolsa Chica St",
    "sg:city":"Huntington Beach",
    "sg:classifiers":[
        {
            "category":"Real Estate",
            "subcategory":"Developer",
            "type":"Services"
        }
    ],
    "sg:phone":"+1 714 625 1305",
    "sg:postcode":"92649",
    "sg:province":"CA",
    "wof:name":"Bonanni Development",
    "wof:placetype":"venue"
},
  "geometry": {"coordinates":[-118.04167700000001,33.722108],"type":"Point"}
}