{
  "type": "Feature",
  "properties": {
    "addr:full":"14305 Firestone Blvd La Mirada CA 90638",
    "addr:housenumber":"14305",
    "addr:postcode":"90638",
    "addr:street":"Firestone Blvd",
    "iso:country":"US",
    "sg:address":"14305 Firestone Blvd",
    "sg:city":"La Mirada",
    "sg:classifiers":[
        {
            "category":"Restaurant",
            "type":"Food & Drink"
        }
    ],
    "sg:phone":"+1 714 739 0331",
    "sg:postcode":"90638",
    "sg:province":"CA",
    "wof:name":"Clearman's Steak'n Stein",
    "wof:placetype":"venue"
},
  "geometry": {"coordinates":[-118.027,33.884399],"type":"Point"}
}