{
  "type": "Feature",
  "properties": {
    "addr:full":"2408 Saybrook Pl Martinez CA 94553",
    "addr:housenumber":"2408",
    "addr:postcode":"94553",
    "addr:street":"Saybrook Pl",
    "iso:country":"US",
    "sg:address":"2408 Saybrook Pl",
    "sg:city":"Martinez",
    "sg:classifiers":[
        {
            "category":"Building & Trades",
            "subcategory":"Landscaping Services",
            "type":"Services"
        }
    ],
    "sg:phone":"+1 925 228 8292",
    "sg:postcode":"94553",
    "sg:province":"CA",
    "sg:tags":[
        "landscape"
    ],
    "wof:name":"Fotheringham Lndscp",
    "wof:placetype":"venue"
},
  "geometry": {"coordinates":[-122.087267,37.999013],"type":"Point"}
}