{
  "type": "Feature",
  "properties": {
    "iso:country":"US",
    "sg:address":"7061 Skokie Pl",
    "sg:city":"Citrus Heights",
    "sg:classifiers":[
        {
            "category":"Professional",
            "type":"Services"
        }
    ],
    "sg:phone":"+1 916 332 6205",
    "sg:postcode":"95621",
    "sg:province":"CA",
    "wof:name":"College Connections Inc",
    "wof:placetype":"venue"
},
  "geometry": {"coordinates":[-121.327223,38.694895],"type":"Point"}
}