{
  "type": "Feature",
  "properties": {
    "iso:country":"US",
    "sg:address":"18619 Oak Park Dr",
    "sg:city":"Riverside",
    "sg:classifiers":[
        {
            "category":"Real Estate",
            "subcategory":"Real Estate Agent",
            "type":"Services"
        }
    ],
    "sg:phone":"+1 951 789 9339",
    "sg:postcode":"92504",
    "sg:province":"CA",
    "wof:name":"Sung Wan",
    "wof:placetype":"venue"
},
  "geometry": {"coordinates":[-117.353059,33.851358],"type":"Point"}
}