{
  "type": "Feature",
  "properties": {
    "iso:country":"US",
    "sg:address":"1720 Border Ave",
    "sg:city":"Torrance",
    "sg:classifiers":[
        {
            "category":"Manufacturing",
            "subcategory":"Tools & Machinery",
            "type":"Manufacturing & Wholesale Goods"
        }
    ],
    "sg:phone":"+1 310 328 2924",
    "sg:postcode":"90501",
    "sg:province":"CA",
    "sg:tags":[
        "industrial",
        "mfg"
    ],
    "wof:name":"Connolly Products",
    "wof:placetype":"venue"
},
  "geometry": {"coordinates":[-118.31292999999999,33.831132],"type":"Point"}
}