{
  "type": "Feature",
  "properties": {
    "addr:full":"2031 White Ln Bakersfield CA 93304",
    "addr:housenumber":"2031",
    "addr:postcode":"93304",
    "addr:street":"White Ln",
    "iso:country":"US",
    "sg:address":"2031 White Ln",
    "sg:city":"Bakersfield",
    "sg:classifiers":[
        {
            "category":"Restaurant",
            "type":"Food & Drink"
        }
    ],
    "sg:menulink":"http://www.allmenus.com/ca/bakersfield/231469-sonic/menu/",
    "sg:phone":"+1 661 396 9100",
    "sg:postcode":"93304",
    "sg:province":"CA",
    "sg:tags":[
        "burger",
        "american"
    ],
    "wof:name":"Sonic",
    "wof:placetype":"venue"
},
  "geometry": {"coordinates":[-119.025766,35.31682],"type":"Point"}
}