{
  "type": "Feature",
  "properties": {
    "iso:country":"US",
    "sg:address":"1151 S Robertson Blvd",
    "sg:city":"Los Angeles",
    "sg:classifiers":[
        {
            "category":"Health Services",
            "subcategory":"Clinic",
            "type":"Services"
        }
    ],
    "sg:phone":"+1 310 246 2399",
    "sg:postcode":"90035",
    "sg:province":"CA",
    "sg:tags":[
        "cannabis"
    ],
    "sg:website":"www.infinitymedical420.com",
    "wof:name":"Infinity Medical Alliance",
    "wof:placetype":"venue"
},
  "geometry": {"coordinates":[-118.383989,34.05565],"type":"Point"}
}