{
  "type": "Feature",
  "properties": {
    "iso:country":"US",
    "sg:address":"657 Foothill Blvd",
    "sg:city":"La Canada Flintridge",
    "sg:classifiers":[
        {
            "category":"Real Estate",
            "subcategory":"Real Estate Agent",
            "type":"Services"
        }
    ],
    "sg:phone":"+1 818 949 5706",
    "sg:postcode":"91011",
    "sg:province":"CA",
    "sg:website":"www.realestatebyjones.com/",
    "wof:name":"Barry Jones - Coldwell Banker",
    "wof:placetype":"venue"
},
  "geometry": {"coordinates":[-118.193175,34.201352],"type":"Point"}
}