{
  "type": "Feature",
  "properties": {
    "iso:country":"US",
    "sg:address":"1516 Oak St",
    "sg:city":"Alameda",
    "sg:classifiers":[
        {
            "category":"Manufacturing",
            "subcategory":"Printing",
            "type":"Manufacturing & Wholesale Goods"
        }
    ],
    "sg:phone":"+1 510 337 1301",
    "sg:postcode":"94501",
    "sg:province":"CA",
    "sg:tags":[
        "printer"
    ],
    "wof:name":"Bay Area Memorials",
    "wof:placetype":"venue"
},
  "geometry": {"coordinates":[-122.242996,37.766293],"type":"Point"}
}