{
  "type": "Feature",
  "properties": {
    "iso:country":"US",
    "sg:address":"3285 Sanctuary Trl",
    "sg:city":"Placerville",
    "sg:classifiers":[
        {
            "category":"Professional",
            "subcategory":"Detective & Security Services",
            "type":"Services"
        }
    ],
    "sg:phone":"+1 530 409 3446",
    "sg:postcode":"95667",
    "sg:province":"CA",
    "sg:tags":[
        "information",
        "bureau"
    ],
    "wof:name":"Blakeman Services",
    "wof:placetype":"venue"
},
  "geometry": {"coordinates":[-120.69712199999999,38.811942],"type":"Point"}
}