{
  "type": "Feature",
  "properties": {
    "addr:full":"229 E Redondo Beach Blvd Gardena CA 90248",
    "addr:housenumber":"229",
    "addr:postcode":"90248",
    "addr:street":"E Redondo Beach Blvd",
    "iso:country":"US",
    "sg:address":"229 E Redondo Beach Blvd",
    "sg:city":"Gardena",
    "sg:classifiers":[
        {
            "category":"Building & Trades",
            "subcategory":"Construction",
            "type":"Services"
        }
    ],
    "sg:phone":"+1 310 523 4348",
    "sg:postcode":"90248",
    "sg:province":"CA",
    "sg:tags":[
        "finishing",
        "wood",
        "refinishing"
    ],
    "wof:name":"Robles Finishing",
    "wof:placetype":"venue"
},
  "geometry": {"coordinates":[-118.26754699999999,33.893239],"type":"Point"}
}