{
  "type": "Feature",
  "properties": {
    "iso:country":"US",
    "sg:address":"25543 Whitworth Dr N",
    "sg:city":"Madera",
    "sg:classifiers":[
        {
            "category":"Wholesale",
            "subcategory":"Machinery & Supplies",
            "type":"Manufacturing & Wholesale Goods"
        }
    ],
    "sg:phone":"+1 559 675 9378",
    "sg:postcode":"93638",
    "sg:province":"CA",
    "sg:tags":[
        "equipment",
        "establishment"
    ],
    "wof:name":"Pasillas Maintenance",
    "wof:placetype":"venue"
},
  "geometry": {"coordinates":[-120.08365000000001,37.01519],"type":"Point"}
}