{
  "type": "Feature",
  "properties": {
    "addr:full":"2541 Grant Ave San Lorenzo CA 94580",
    "addr:housenumber":"2541",
    "addr:postcode":"94580",
    "addr:street":"Grant Ave",
    "iso:country":"US",
    "sg:address":"2541 Grant Ave",
    "sg:city":"San Lorenzo",
    "sg:classifiers":[
        {
            "category":"Restaurant",
            "type":"Food & Drink"
        }
    ],
    "sg:phone":"+1 510 276 8880",
    "sg:postcode":"94580",
    "sg:province":"CA",
    "sg:tags":[
        "peruvian",
        "mexican"
    ],
    "wof:name":"Luisa's Place",
    "wof:placetype":"venue"
},
  "geometry": {"coordinates":[-122.156998,37.669701],"type":"Point"}
}