{
  "type": "Feature",
  "properties": {
    "addr:full":"2075 Lincoln Ave Ste B San Jose CA 95125",
    "addr:housenumber":"2075",
    "addr:postcode":"95125",
    "addr:street":"Lincoln Ave Ste B",
    "iso:country":"US",
    "sg:address":"2075 Lincoln Ave Ste B",
    "sg:city":"San Jose",
    "sg:classifiers":[
        {
            "category":"Personal",
            "subcategory":"Massage",
            "type":"Services"
        },
        {
            "category":"Health Services",
            "subcategory":"Health Practitioner",
            "type":"Services"
        }
    ],
    "sg:phone":"+1 408 269 1888",
    "sg:postcode":"95125",
    "sg:province":"CA",
    "sg:tags":[
        "acupuncture"
    ],
    "wof:name":"Acupuncture & Traditional Chinese Medicine",
    "wof:placetype":"venue"
},
  "geometry": {"coordinates":[-121.89019500000001,37.292762],"type":"Point"}
}