{
  "type": "Feature",
  "properties": {
    "addr:full":"46 Porter Dr Watsonville CA 95076",
    "addr:housenumber":"46",
    "addr:postcode":"95076",
    "addr:street":"Porter Dr",
    "iso:country":"US",
    "sg:address":"46 Porter Dr",
    "sg:city":"Watsonville",
    "sg:classifiers":[
        {
            "category":"Autos & Motor Vehicles",
            "subcategory":"Auto Supplies",
            "type":"Retail Goods"
        }
    ],
    "sg:phone":"+1 831 768 0994",
    "sg:postcode":"95076",
    "sg:province":"CA",
    "wof:name":"Moreno Auto Body Parts",
    "wof:placetype":"venue"
},
  "geometry": {"coordinates":[-121.75071199999999,36.90471],"type":"Point"}
}