{
  "type": "Feature",
  "properties": {
    "iso:country":"US",
    "sg:address":"1652 Oak St",
    "sg:city":"Bakersfield",
    "sg:classifiers":[
        {
            "category":"Restaurant",
            "type":"Food & Drink"
        }
    ],
    "sg:phone":"+1 661 631 8101",
    "sg:postcode":"93301",
    "sg:province":"CA",
    "wof:name":"Taqueria Nuevo Amanecer",
    "wof:placetype":"venue"
},
  "geometry": {"coordinates":[-119.038585,35.372713],"type":"Point"}
}