{
  "type": "Feature",
  "properties": {
    "addr:full":"1645 Arbolado Rd Paso Robles CA 93446",
    "addr:housenumber":"1645",
    "addr:postcode":"93446",
    "addr:street":"Arbolado Rd",
    "iso:country":"US",
    "sg:address":"1645 Arbolado Rd",
    "sg:city":"Paso Robles",
    "sg:classifiers":[
        {
            "category":"Farming",
            "subcategory":"Farm & Veterinary Services",
            "type":"Manufacturing & Wholesale Goods"
        }
    ],
    "sg:phone":"+1 805 238 3370",
    "sg:postcode":"93446",
    "sg:province":"CA",
    "sg:tags":[
        "aerial",
        "applicator"
    ],
    "wof:name":"Sinton Helicopters",
    "wof:placetype":"venue"
},
  "geometry": {"coordinates":[-120.665452,35.600987],"type":"Point"}
}