{
  "type": "Feature",
  "properties": {
    "addr:full":"314 E Live Oak Ave Arcadia CA 91006",
    "addr:housenumber":"314",
    "addr:postcode":"91006",
    "addr:street":"E Live Oak Ave",
    "iso:country":"US",
    "sg:address":"314 E Live Oak Ave",
    "sg:city":"Arcadia",
    "sg:classifiers":[
        {
            "category":"Manufacturing",
            "subcategory":"Metals",
            "type":"Manufacturing & Wholesale Goods"
        }
    ],
    "sg:phone":"+1 626 446 5363",
    "sg:postcode":"91006",
    "sg:province":"CA",
    "sg:tags":[
        "item",
        "gift"
    ],
    "wof:name":"Clockwise Fine Gifts",
    "wof:placetype":"venue"
},
  "geometry": {"coordinates":[-118.021762,34.108534],"type":"Point"}
}