{
  "type": "Feature",
  "properties": {
    "addr:full":"132 Bear Valley Rd Arnold CA 95223",
    "addr:housenumber":"132",
    "addr:postcode":"95223",
    "addr:street":"Bear Valley Rd",
    "iso:country":"US",
    "sg:address":"132 Bear Valley Rd",
    "sg:city":"Arnold",
    "sg:classifiers":[
        {
            "category":"Real Estate",
            "subcategory":"Real Estate Services",
            "type":"Services"
        },
        {
            "category":"Real Estate",
            "subcategory":"Real Estate Agent",
            "type":"Services"
        },
        {
            "category":"Building & Trades",
            "subcategory":"Construction",
            "type":"Services"
        }
    ],
    "sg:phone":"+1 209 753 2551",
    "sg:postcode":"95223",
    "sg:province":"CA",
    "sg:tags":[
        "buyer",
        "management",
        "broker",
        "condominium"
    ],
    "sg:website":"http://www.premierproperties.com",
    "wof:name":"Alpine Condo Mgmnt",
    "wof:placetype":"venue"
},
  "geometry": {"coordinates":[-120.041336,38.462598],"type":"Point"}
}