{
  "type": "Feature",
  "properties": {
    "iso:country":"US",
    "sg:address":"3905 Millican Ct",
    "sg:city":"Sacramento",
    "sg:classifiers":[
        {
            "category":"Building & Trades",
            "subcategory":"Landscaping Services",
            "type":"Services"
        }
    ],
    "sg:phone":"+1 916 364 7092",
    "sg:postcode":"95826",
    "sg:province":"CA",
    "sg:tags":[
        "contractor",
        "landscape",
        "drainage"
    ],
    "wof:name":"Turner's Landscape Svc",
    "wof:placetype":"venue"
},
  "geometry": {"coordinates":[-121.34848,38.548521],"type":"Point"}
}