{
  "type": "Feature",
  "properties": {
    "addr:full":"353 Philip Dr Daly City CA 94015",
    "addr:housenumber":"353",
    "addr:postcode":"94015",
    "addr:street":"Philip Dr",
    "iso:country":"US",
    "sg:address":"353 Philip Dr",
    "sg:city":"Daly City",
    "sg:classifiers":[
        {
            "category":"Real Estate",
            "subcategory":"Real Estate Agent",
            "type":"Services"
        }
    ],
    "sg:phone":"+1 650 755 6300",
    "sg:postcode":"94015",
    "sg:province":"CA",
    "sg:tags":[
        "inspection"
    ],
    "wof:name":"Ameri Spec Home Inspection Svc",
    "wof:placetype":"venue"
},
  "geometry": {"coordinates":[-122.464575,37.669585],"type":"Point"}
}