{
  "type": "Feature",
  "properties": {
    "iso:country":"US",
    "sg:address":"615 California St",
    "sg:city":"Santa Cruz",
    "sg:classifiers":[
        {
            "category":"Manufacturing",
            "subcategory":"Printing",
            "type":"Manufacturing & Wholesale Goods"
        }
    ],
    "sg:phone":"+1 831 457 2298",
    "sg:postcode":"95060",
    "sg:province":"CA",
    "sg:tags":[
        "publisher"
    ],
    "wof:name":"Lemon Tree Press",
    "wof:placetype":"venue"
},
  "geometry": {"coordinates":[-122.034761,36.9697],"type":"Point"}
}