{
  "type": "Feature",
  "properties": {
    "addr:full":"2472 Elm St Live Oak CA 95953",
    "addr:housenumber":"2472",
    "addr:postcode":"95953",
    "addr:street":"Elm St",
    "iso:country":"US",
    "sg:address":"2472 Elm St",
    "sg:city":"Live Oak",
    "sg:classifiers":[
        {
            "category":"Building & Trades",
            "subcategory":"Construction",
            "type":"Services"
        }
    ],
    "sg:phone":"+1 530 695 2632",
    "sg:postcode":"95953",
    "sg:province":"CA",
    "sg:tags":[
        "contractor"
    ],
    "wof:name":"Glycolean Dstr Rchard Vicki He",
    "wof:placetype":"venue"
},
  "geometry": {"coordinates":[-121.658838,39.273337],"type":"Point"}
}