{
  "type": "Feature",
  "properties": {
    "addr:full":"1312 Bruce St Chico CA 95928",
    "addr:housenumber":"1312",
    "addr:postcode":"95928",
    "addr:street":"Bruce St",
    "iso:country":"US",
    "sg:address":"1312 Bruce St",
    "sg:city":"Chico",
    "sg:classifiers":[
        {
            "category":"Farming",
            "subcategory":"Farm & Veterinary Services",
            "type":"Manufacturing & Wholesale Goods"
        }
    ],
    "sg:phone":"+1 530 345 9283",
    "sg:postcode":"95928",
    "sg:province":"CA",
    "wof:name":"TGQ Unlimited Gourd Queen",
    "wof:placetype":"venue"
},
  "geometry": {"coordinates":[-121.819005,39.729977],"type":"Point"}
}