{
  "type": "Feature",
  "properties": {
    "addr:full":"6400 Moraga Ave Oakland CA 94611",
    "addr:housenumber":"6400",
    "addr:postcode":"94611",
    "addr:street":"Moraga Ave",
    "iso:country":"US",
    "sg:address":"6400 Moraga Ave",
    "sg:city":"Oakland",
    "sg:classifiers":[
        {
            "category":"Real Estate",
            "subcategory":"Real Estate Services",
            "type":"Services"
        }
    ],
    "sg:phone":"+1 510 338 0588",
    "sg:postcode":"94611",
    "sg:province":"CA",
    "sg:tags":[
        "management",
        "property"
    ],
    "sg:website":"www.wellingtonpropertyco.com",
    "wof:name":"Wellington Property Company",
    "wof:placetype":"venue"
},
  "geometry": {"coordinates":[-122.21104200000001,37.82721],"type":"Point"}
}