{
  "type": "Feature",
  "properties": {
    "iso:country":"US",
    "sg:address":"3780 22nd St",
    "sg:city":"San Francisco",
    "sg:classifiers":[
        {
            "category":"Education",
            "subcategory":"Special Training",
            "type":"Public Place"
        }
    ],
    "sg:phone":"+1 415 282 5882",
    "sg:postcode":"94114",
    "sg:province":"CA",
    "sg:tags":[
        "school",
        "adult",
        "language"
    ],
    "sg:website":"www.speechskills.com",
    "wof:name":"Speechskills",
    "wof:placetype":"venue"
},
  "geometry": {"coordinates":[-122.431731,37.75467],"type":"Point"}
}