{
  "type": "Feature",
  "properties": {
    "iso:country":"US",
    "sg:address":"3672 Hillsdale Ranch Rd",
    "sg:city":"Chino Hills",
    "sg:classifiers":[
        {
            "category":"Mining & Drilling",
            "type":"Manufacturing & Wholesale Goods"
        }
    ],
    "sg:phone":"+1 909 606 0622",
    "sg:postcode":"91709",
    "sg:province":"CA",
    "sg:tags":[
        "ore",
        "silver"
    ],
    "wof:name":"Argentum Recovery",
    "wof:placetype":"venue"
},
  "geometry": {"coordinates":[-117.72574,33.971421],"type":"Point"}
}