{
  "type": "Feature",
  "properties": {
    "addr:full":"9500 Greenback Ln Ste 26 Folsom CA 95630",
    "addr:housenumber":"9500",
    "addr:postcode":"95630",
    "addr:street":"Greenback Ln Ste 26",
    "iso:country":"US",
    "sg:address":"9500 Greenback Ln Ste 26",
    "sg:city":"Folsom",
    "sg:classifiers":[
        {
            "category":"Retail",
            "subcategory":"Veterinary Services",
            "type":"Services"
        }
    ],
    "sg:phone":"+1 916 989 2190",
    "sg:postcode":"95630",
    "sg:province":"CA",
    "sg:tags":[
        "clinic",
        "hospital"
    ],
    "wof:name":"Cross Roads Vet Clinic",
    "wof:placetype":"venue"
},
  "geometry": {"coordinates":[-121.19678,38.678022],"type":"Point"}
}