{
  "type": "Feature",
  "properties": {
    "addr:full":"2031 I St Apt 7 Sacramento CA 95811",
    "addr:housenumber":"2031;7",
    "addr:postcode":"95811",
    "addr:street":"I St Apt",
    "iso:country":"US",
    "sg:address":"2031 I St Apt 7",
    "sg:city":"Sacramento",
    "sg:classifiers":[
        {
            "category":"Shopping",
            "subcategory":"Bicycles & Sporting Goods",
            "type":"Retail Goods"
        },
        {
            "category":"Wholesale",
            "subcategory":"Sporting Goods",
            "type":"Manufacturing & Wholesale Goods"
        }
    ],
    "sg:phone":"+1 916 442 7220",
    "sg:postcode":"95811",
    "sg:province":"CA",
    "sg:tags":[
        "golf",
        "supply",
        "equipment",
        "supplies-wholesale",
        "manufacturer"
    ],
    "wof:name":"Thomas Marketing Co",
    "wof:placetype":"venue"
},
  "geometry": {"coordinates":[-121.47902999999999,38.57768],"type":"Point"}
}