{
  "type": "Feature",
  "properties": {
    "addr:full":"1757 Grouse Rdg Truckee CA 96161",
    "addr:housenumber":"1757",
    "addr:postcode":"96161",
    "addr:street":"Grouse Rdg",
    "iso:country":"US",
    "sg:address":"1757 Grouse Rdg",
    "sg:city":"Truckee",
    "sg:classifiers":[
        {
            "category":"Real Estate",
            "subcategory":"Real Estate Services",
            "type":"Services"
        },
        {
            "category":"Real Estate",
            "subcategory":"Real Estate Agent",
            "type":"Services"
        }
    ],
    "sg:phone":"+1 530 562 1663",
    "sg:postcode":"96161",
    "sg:province":"CA",
    "sg:tags":[
        "buyer",
        "broker"
    ],
    "wof:name":"Mulloy Realty",
    "wof:placetype":"venue"
},
  "geometry": {"coordinates":[-120.124835,39.277026],"type":"Point"}
}