{
  "type": "Feature",
  "properties": {
    "iso:country":"US",
    "sg:address":"10545 San Pablo Ave",
    "sg:city":"El Cerrito",
    "sg:classifiers":[
        {
            "category":"Shopping",
            "subcategory":"Tobacco",
            "type":"Retail Goods"
        }
    ],
    "sg:phone":"+1 510 525 1661",
    "sg:postcode":"94530",
    "sg:province":"CA",
    "sg:tags":[
        "shop",
        "product",
        "smoke",
        "supply"
    ],
    "wof:name":"Smokers World",
    "wof:placetype":"venue"
},
  "geometry": {"coordinates":[-122.308546,37.911115],"type":"Point"}
}