{
  "type": "Feature",
  "properties": {
    "addr:full":"12909 San Fernando Rd Sylmar CA 91342",
    "addr:housenumber":"12909",
    "addr:postcode":"91342",
    "addr:street":"San Fernando Rd",
    "iso:country":"US",
    "sg:address":"12909 San Fernando Rd",
    "sg:city":"Sylmar",
    "sg:classifiers":[
        {
            "category":"Retail",
            "subcategory":"Auto Repair",
            "type":"Services"
        }
    ],
    "sg:phone":"+1 818 362 5987",
    "sg:postcode":"91342",
    "sg:province":"CA",
    "sg:tags":[
        "repairing",
        "tire"
    ],
    "wof:name":"Castaneda Tire Svc",
    "wof:placetype":"venue"
},
  "geometry": {"coordinates":[-118.46683,34.304913],"type":"Point"}
}