{
  "type": "Feature",
  "properties": {
    "addr:full":"2761 Lone Tree Way Antioch CA 94509",
    "addr:housenumber":"2761",
    "addr:postcode":"ca 94509",
    "addr:street":"Lone Tree Way",
    "iso:country":"US",
    "sg:address":"2761 Lone Tree Way",
    "sg:city":"Antioch",
    "sg:classifiers":[
        {
            "category":"Shopping",
            "type":"Retail Goods"
        }
    ],
    "sg:phone":"+1 925 753 0424",
    "sg:postcode":"94509",
    "sg:province":"CA",
    "sg:tags":[
        "limb",
        "artificial"
    ],
    "wof:name":"Laurence-Farrow Orthotics",
    "wof:placetype":"venue"
},
  "geometry": {"coordinates":[-121.801885,37.976344],"type":"Point"}
}