{
  "type": "Feature",
  "properties": {
    "iso:country":"US",
    "sg:address":"123 Main St",
    "sg:city":"Los Angeles",
    "sg:classifiers":[
        {
            "category":"Shopping",
            "subcategory":"Clothing, Apparel, & Fashions",
            "type":"Retail Goods"
        }
    ],
    "sg:phone":"+1 310 880 5554",
    "sg:postcode":"90012",
    "sg:province":"CA",
    "sg:tags":[
        "clothing",
        "women's"
    ],
    "sg:website":"www.aryafashion.com",
    "wof:name":"Aryana Fashion",
    "wof:placetype":"venue"
},
  "geometry": {"coordinates":[-118.24372700000001,34.051852],"type":"Point"}
}