{
  "type": "Feature",
  "properties": {
    "iso:country":"US",
    "sg:address":"10316 Enloe St",
    "sg:city":"South El Monte",
    "sg:classifiers":[
        {
            "category":"Retail",
            "subcategory":"Repair Shop",
            "type":"Services"
        }
    ],
    "sg:phone":"+1 626 442 8884",
    "sg:postcode":"91733",
    "sg:province":"CA",
    "sg:tags":[
        "related"
    ],
    "wof:name":"S A Sales Co",
    "wof:placetype":"venue"
},
  "geometry": {"coordinates":[-118.04525,34.053581],"type":"Point"}
}