{
  "type": "Feature",
  "properties": {
    "iso:country":"US",
    "sg:address":"940 Rose Ave",
    "sg:city":"Venice",
    "sg:classifiers":[
        {
            "category":"Social Services",
            "subcategory":"Adult Care",
            "type":"Services"
        }
    ],
    "sg:phone":"+1 310 392 3132",
    "sg:postcode":"90291",
    "sg:province":"CA",
    "sg:tags":[
        "residential"
    ],
    "wof:name":"Laila Home Care",
    "wof:placetype":"venue"
},
  "geometry": {"coordinates":[-118.463386,34.003509],"type":"Point"}
}