{
  "type": "Feature",
  "properties": {
    "iso:country":"US",
    "sg:address":"62 S L St",
    "sg:city":"Livermore",
    "sg:classifiers":[
        {
            "category":"Food & Beverages",
            "subcategory":"Liquor & Beverages",
            "type":"Retail Goods"
        }
    ],
    "sg:phone":"+1 925 449 6141",
    "sg:postcode":"94550",
    "sg:province":"CA",
    "wof:name":"Bottle Book & Smoke Shop",
    "wof:placetype":"venue"
},
  "geometry": {"coordinates":[-121.771479,37.681751],"type":"Point"}
}