{
  "type": "Feature",
  "properties": {
    "iso:country":"US",
    "sg:address":"1524 Fairview St",
    "sg:city":"Berkeley",
    "sg:classifiers":[
        {
            "category":"Health Services",
            "subcategory":"Doctor",
            "type":"Services"
        }
    ],
    "sg:phone":"+1 510 771 3000",
    "sg:postcode":"94703",
    "sg:province":"CA",
    "wof:name":"Dr. Dawn Brown Davis",
    "wof:placetype":"venue"
},
  "geometry": {"coordinates":[-122.277134,37.849857],"type":"Point"}
}