{
  "type": "Feature",
  "properties": {
    "iso:country":"US",
    "sg:address":"6572 Oakmont Dr",
    "sg:city":"Santa Rosa",
    "sg:classifiers":[
        {
            "category":"Sports & Exercise",
            "subcategory":"Gym",
            "type":"Entertainment"
        }
    ],
    "sg:phone":"+1 707 537 3030",
    "sg:postcode":"95409",
    "sg:province":"CA",
    "sg:tags":[
        "club",
        "health",
        "studio",
        "gymnasium"
    ],
    "wof:name":"Curves For Women",
    "wof:placetype":"venue"
},
  "geometry": {"coordinates":[-122.605236,38.441888],"type":"Point"}
}