{
  "type": "Feature",
  "properties": {
    "addr:full":"475 Anton Blvd Costa Mesa CA 92626",
    "addr:housenumber":"475",
    "addr:postcode":"92626",
    "addr:street":"Anton Blvd Costa",
    "iso:country":"US",
    "sg:address":"475 Anton Blvd",
    "sg:city":"Costa Mesa",
    "sg:classifiers":[
        {
            "category":"Banks & Credit Unions",
            "subcategory":"Financial Services",
            "type":"Services"
        }
    ],
    "sg:phone":"+1 714 830 7000",
    "sg:postcode":"92626",
    "sg:province":"CA",
    "sg:website":"www.experian.com",
    "wof:name":"Experian",
    "wof:placetype":"venue"
},
  "geometry": {"coordinates":[-117.87422100000001,33.689171],"type":"Point"}
}