{
  "type": "Feature",
  "properties": {
    "addr:full":"43847 Heaton Ave Ste L Lancaster CA 93534",
    "addr:housenumber":"43847",
    "addr:postcode":"93534",
    "addr:street":"Heaton Ave Ste L",
    "iso:country":"US",
    "sg:address":"43847 Heaton Ave Ste L",
    "sg:city":"Lancaster",
    "sg:classifiers":[
        {
            "category":"Health Services",
            "subcategory":"Doctor",
            "type":"Services"
        }
    ],
    "sg:phone":"+1 661 948 5723",
    "sg:postcode":"93534",
    "sg:province":"CA",
    "sg:tags":[
        "physician",
        "pediatrics-emergency",
        "pediatrics",
        "family",
        "practice",
        "surgeons",
        "medicine",
        "surgeon"
    ],
    "wof:name":"Richard W Kling Md",
    "wof:placetype":"venue"
},
  "geometry": {"coordinates":[-118.145729,34.679357],"type":"Point"}
}