{
  "type": "Feature",
  "properties": {
    "iso:country":"US",
    "sg:address":"10515 Ashworth St",
    "sg:city":"Bellflower",
    "sg:classifiers":[
        {
            "category":"Freight",
            "type":"Transportation"
        }
    ],
    "sg:phone":"+1 562 867 4071",
    "sg:postcode":"90706",
    "sg:province":"CA",
    "wof:name":"Vankampen Transportation",
    "wof:placetype":"venue"
},
  "geometry": {"coordinates":[-118.109191,33.868209],"type":"Point"}
}