{
  "type": "Feature",
  "properties": {
    "addr:full":"3340 Revere Ave Oakland CA 94605",
    "addr:housenumber":"3340",
    "addr:postcode":"94605",
    "addr:street":"Revere Ave",
    "iso:country":"US",
    "sg:address":"3340 Revere Ave",
    "sg:city":"Oakland",
    "sg:classifiers":[
        {
            "category":"Farming",
            "subcategory":"Farm",
            "type":"Manufacturing & Wholesale Goods"
        }
    ],
    "sg:phone":"+1 510 638 2666",
    "sg:postcode":"94605",
    "sg:province":"CA",
    "wof:name":"Batteate Livestock",
    "wof:placetype":"venue"
},
  "geometry": {"coordinates":[-122.13350199999999,37.735282],"type":"Point"}
}