{
  "type": "Feature",
  "properties": {
    "iso:country":"US",
    "sg:address":"4787 Sun Valley Rd",
    "sg:city":"Del Mar",
    "sg:classifiers":[
        {
            "category":"Real Estate",
            "subcategory":"Real Estate Agent",
            "type":"Services"
        }
    ],
    "sg:phone":"+1 858 481 5635",
    "sg:postcode":"92014",
    "sg:province":"CA",
    "wof:name":"Denyse Sayler",
    "wof:placetype":"venue"
},
  "geometry": {"coordinates":[-117.236209,32.995332],"type":"Point"}
}