{
  "type": "Feature",
  "properties": {
    "iso:country":"US",
    "sg:address":"12300 Lakewood Blvd",
    "sg:city":"Downey",
    "sg:classifiers":[
        {
            "category":"Retail",
            "subcategory":"Auto Repair",
            "type":"Services"
        }
    ],
    "sg:phone":"+1 562 869 8232",
    "sg:postcode":"90242",
    "sg:province":"CA",
    "sg:website":"www.downeyjagandlandrover.com",
    "wof:name":"Downey Jaguar and Automotive Services, Inc",
    "wof:placetype":"venue"
},
  "geometry": {"coordinates":[-118.134466,33.920911],"type":"Point"}
}