{
  "type": "Feature",
  "properties": {
    "addr:full":"450 N Brand Blvd Ste 800 Glendale CA 91203",
    "addr:housenumber":"450",
    "addr:postcode":"91203",
    "addr:street":"N Brand Blvd Ste 800",
    "iso:country":"US",
    "sg:address":"450 N Brand Blvd Ste 800",
    "sg:city":"Glendale",
    "sg:classifiers":[
        {
            "category":"Insurance",
            "subcategory":"Title Insurance",
            "type":"Services"
        }
    ],
    "sg:phone":"+1 818 247 2917",
    "sg:postcode":"91203",
    "sg:province":"CA",
    "sg:tags":[
        "mortgage"
    ],
    "sg:website":"http://www.oldrepublictitle.com",
    "wof:name":"Old Republic",
    "wof:placetype":"venue"
},
  "geometry": {"coordinates":[-118.254994,34.152378],"type":"Point"}
}