{
  "type": "Feature",
  "properties": {
    "iso:country":"US",
    "sg:address":"3750 Taylor Rd",
    "sg:city":"Loomis",
    "sg:classifiers":[
        {
            "category":"Home & Garden",
            "subcategory":"Garden Supply",
            "type":"Retail Goods"
        }
    ],
    "sg:phone":"+1 916 652 2065",
    "sg:postcode":"95650",
    "sg:province":"CA",
    "sg:tags":[
        "nurseryman"
    ],
    "wof:name":"High Hand Nurseries",
    "wof:placetype":"venue"
},
  "geometry": {"coordinates":[-121.197739,38.817116],"type":"Point"}
}