{
  "type": "Feature",
  "properties": {
    "addr:full":"1327 International Blvd Oakland CA 94606",
    "addr:housenumber":"1327",
    "addr:postcode":"94606",
    "addr:street":"International Blvd",
    "iso:country":"US",
    "sg:address":"1327 International Blvd",
    "sg:city":"Oakland",
    "sg:classifiers":[
        {
            "category":"Professional",
            "subcategory":"Lawyer & Legal Services",
            "type":"Services"
        }
    ],
    "sg:phone":"+1 510 532 7047",
    "sg:postcode":"94606",
    "sg:province":"CA",
    "sg:tags":[
        "attorney"
    ],
    "wof:name":"Nicolas J Gomes Jr",
    "wof:placetype":"venue"
},
  "geometry": {"coordinates":[-122.2465,37.789503],"type":"Point"}
}