{
  "type": "Feature",
  "properties": {
    "addr:full":"8200 Wilshire Blvd Beverly Hills CA 90211",
    "addr:housenumber":"8200",
    "addr:postcode":"90211",
    "addr:street":"Wilshire Blvd",
    "iso:country":"US",
    "sg:address":"8200 Wilshire Blvd",
    "sg:city":"Beverly Hills",
    "sg:classifiers":[
        {
            "category":"Retail",
            "subcategory":"Animal Services",
            "type":"Services"
        }
    ],
    "sg:phone":"+1 310 666 4739",
    "sg:postcode":"90211",
    "sg:province":"CA",
    "sg:tags":[
        "training",
        "dog"
    ],
    "wof:name":"Professional Dog Training Svc",
    "wof:placetype":"venue"
},
  "geometry": {"coordinates":[-118.37300399999999,34.064405],"type":"Point"}
}