{
  "type": "Feature",
  "properties": {
    "addr:full":"304 N Main St Corona CA 92880",
    "addr:housenumber":"304",
    "addr:postcode":"92880",
    "addr:street":"N Main St",
    "iso:country":"US",
    "sg:address":"304 N Main St",
    "sg:city":"Corona",
    "sg:classifiers":[
        {
            "category":"Restaurant",
            "type":"Food & Drink"
        }
    ],
    "sg:phone":"+1 951 737 3787",
    "sg:postcode":"92880",
    "sg:province":"CA",
    "sg:tags":[
        "shop",
        "coffee"
    ],
    "wof:name":"Jitterccinos Coffee Co & Grill",
    "wof:placetype":"venue"
},
  "geometry": {"coordinates":[-117.565213,33.882677],"type":"Point"}
}