{
  "type": "Feature",
  "properties": {
    "addr:full":"242 W 3rd St Chico CA 95928",
    "addr:housenumber":"242",
    "addr:postcode":"95928",
    "addr:street":"W 3Rd St",
    "iso:country":"US",
    "sg:address":"242 W 3rd St",
    "sg:city":"Chico",
    "sg:classifiers":[
        {
            "category":"Travel",
            "subcategory":"Travel Agent",
            "type":"Entertainment"
        }
    ],
    "sg:phone":"+1 530 343 1455",
    "sg:postcode":"95928",
    "sg:province":"CA",
    "sg:tags":[
        "passenger",
        "agency",
        "transportation",
        "arrangement"
    ],
    "wof:name":"Trips & Travel",
    "wof:placetype":"venue"
},
  "geometry": {"coordinates":[-121.84115799999999,39.728724],"type":"Point"}
}