{
  "type": "Feature",
  "properties": {
    "iso:country":"US",
    "sg:address":"300 E 15th Street",
    "sg:city":"Newport Beach",
    "sg:classifiers":[
        {
            "category":"Education",
            "subcategory":"School",
            "type":"Public Place"
        }
    ],
    "sg:phone":"+1 949 515 6970",
    "sg:postcode":"92663",
    "sg:province":"CA",
    "sg:tags":[
        "high",
        "middle",
        "elementary"
    ],
    "sg:website":"www.nmusd.k12.ca.us",
    "wof:name":"Newport Heights Elementary School",
    "wof:placetype":"venue"
},
  "geometry": {"coordinates":[-117.919695,33.626642],"type":"Point"}
}