{
  "type": "Feature",
  "properties": {
    "iso:country":"US",
    "sg:address":"2012 Montrose Ave",
    "sg:city":"Montrose",
    "sg:phone":"+1 818 957 2531",
    "sg:postcode":"91020",
    "sg:province":"CA",
    "wof:name":"Edward James Salon",
    "wof:placetype":"venue"
},
  "geometry": {"coordinates":[-118.22515300000001,34.205162],"type":"Point"}
}