{
  "type": "Feature",
  "properties": {
    "iso:country":"US",
    "sg:address":"1385 Ridgewood Dr",
    "sg:city":"Chico",
    "sg:classifiers":[
        {
            "category":"Real Estate",
            "subcategory":"Real Estate Agent",
            "type":"Services"
        }
    ],
    "sg:phone":"+1 530 894 6627",
    "sg:postcode":"95973",
    "sg:province":"CA",
    "wof:name":"Homelink Real Estate",
    "wof:placetype":"venue"
},
  "geometry": {"coordinates":[-121.840141,39.77475],"type":"Point"}
}