{
  "type": "Feature",
  "properties": {
    "addr:full":"180 Philadelphia St Pomona CA 91766",
    "addr:housenumber":"180",
    "addr:postcode":"91766",
    "addr:street":"Philadelphia St",
    "iso:country":"US",
    "sg:address":"180 Philadelphia St",
    "sg:city":"Pomona",
    "sg:classifiers":[
        {
            "category":"Building & Trades",
            "subcategory":"Landscaping Services",
            "type":"Services"
        }
    ],
    "sg:phone":"+1 909 627 1972",
    "sg:postcode":"91766",
    "sg:province":"CA",
    "wof:name":"Bills Tree Service Inc",
    "wof:placetype":"venue"
},
  "geometry": {"coordinates":[-117.74751999999999,34.03327],"type":"Point"}
}