{
  "type": "Feature",
  "properties": {
    "iso:country":"US",
    "sg:address":"5199 E Pacific Coast Hwy Ph",
    "sg:city":"Long Beach",
    "sg:classifiers":[
        {
            "category":"Professional",
            "subcategory":"Employment Agencies",
            "type":"Services"
        }
    ],
    "sg:phone":"+1 562 498 1546",
    "sg:postcode":"90804",
    "sg:province":"CA",
    "wof:name":"Moore Information",
    "wof:placetype":"venue"
},
  "geometry": {"coordinates":[-118.133003,33.7827],"type":"Point"}
}