{
  "type": "Feature",
  "properties": {
    "iso:country":"US",
    "sg:address":"1701 S Union Ave",
    "sg:city":"Bakersfield",
    "sg:classifiers":[
        {
            "category":"Travel",
            "subcategory":"Hotels & Motels",
            "type":"Entertainment"
        }
    ],
    "sg:phone":"+1 661 834 7184",
    "sg:postcode":"93307",
    "sg:province":"CA",
    "wof:name":"Globe Motel",
    "wof:placetype":"venue"
},
  "geometry": {"coordinates":[-119.003025,35.332997],"type":"Point"}
}