{
  "type": "Feature",
  "properties": {
    "iso:country":"US",
    "sg:address":"447 Sutter St",
    "sg:city":"San Francisco",
    "sg:classifiers":[
        {
            "category":"Travel",
            "subcategory":"Travel Agent",
            "type":"Entertainment"
        }
    ],
    "sg:phone":"+1 415 788 0782",
    "sg:postcode":"94108",
    "sg:province":"CA",
    "sg:tags":[
        "agency"
    ],
    "wof:name":"Genevieve Travel",
    "wof:placetype":"venue"
},
  "geometry": {"coordinates":[-122.407184,37.789348],"type":"Point"}
}