{
  "type": "Feature",
  "properties": {
    "iso:country":"US",
    "sg:address":"2608 Redlands Dr",
    "sg:city":"Costa Mesa",
    "sg:classifiers":[
        {
            "category":"Professional",
            "subcategory":"Business Services",
            "type":"Services"
        }
    ],
    "sg:phone":"+1 949 515 2743",
    "sg:postcode":"92627",
    "sg:province":"CA",
    "sg:tags":[
        "interior",
        "consultant",
        "design",
        "decorator"
    ],
    "wof:name":"Stephanie Chavez Interior Dsgn",
    "wof:placetype":"venue"
},
  "geometry": {"coordinates":[-117.888024,33.658095],"type":"Point"}
}