{
  "type": "Feature",
  "properties": {
    "addr:full":"3850 Barranca Pkwy Irvine CA 92606",
    "addr:housenumber":"3850",
    "addr:postcode":"92606",
    "addr:street":"Barranca Pkwy",
    "iso:country":"US",
    "sg:address":"3850 Barranca Pkwy",
    "sg:city":"Irvine",
    "sg:classifiers":[
        {
            "category":"Shopping",
            "subcategory":"Pets & Pet Supplies",
            "type":"Retail Goods"
        }
    ],
    "sg:phone":"+1 949 551 9909",
    "sg:postcode":"92606",
    "sg:province":"CA",
    "sg:tags":[
        "store"
    ],
    "wof:name":"Puppies At Moon Doggies",
    "wof:placetype":"venue"
},
  "geometry": {"coordinates":[-117.81133800000001,33.686006],"type":"Point"}
}