{
  "type": "Feature",
  "properties": {
    "iso:country":"US",
    "sg:address":"4101 N Bellflower Blvd",
    "sg:city":"Long Beach",
    "sg:classifiers":[
        {
            "category":"Autos & Motor Vehicles",
            "subcategory":"Fuel & Gas Station",
            "type":"Retail Goods"
        }
    ],
    "sg:phone":"+1 562 429 5703",
    "sg:postcode":"90808",
    "sg:province":"CA",
    "sg:tags":[
        "oil"
    ],
    "wof:name":"Carson Mobil",
    "wof:placetype":"venue"
},
  "geometry": {"coordinates":[-118.12513800000001,33.833954],"type":"Point"}
}