{
  "type": "Feature",
  "properties": {
    "addr:full":"851 W San Ysidro Blvd San Ysidro CA 92173",
    "addr:housenumber":"851",
    "addr:postcode":"92173",
    "addr:street":"W San Ysidro Blvd",
    "iso:country":"US",
    "sg:address":"851 W San Ysidro Blvd",
    "sg:city":"San Ysidro",
    "sg:classifiers":[
        {
            "category":"Wholesale",
            "subcategory":"Apparel",
            "type":"Manufacturing & Wholesale Goods"
        }
    ],
    "sg:phone":"+1 619 498 0325",
    "sg:postcode":"92173",
    "sg:province":"CA",
    "sg:tags":[
        "bridal",
        "supply"
    ],
    "wof:name":"Angels Flower & Bridal Shop",
    "wof:placetype":"venue"
},
  "geometry": {"coordinates":[-117.060137,32.558548],"type":"Point"}
}