{
  "type": "Feature",
  "properties": {
    "iso:country":"US",
    "sg:address":"2826 Crescent Moon Ct",
    "sg:city":"Ceres",
    "sg:classifiers":[
        {
            "category":"Freight",
            "type":"Transportation"
        }
    ],
    "sg:phone":"+1 209 538 5874",
    "sg:postcode":"95307",
    "sg:province":"CA",
    "sg:tags":[
        "trucking"
    ],
    "wof:name":"America Express",
    "wof:placetype":"venue"
},
  "geometry": {"coordinates":[-120.977589,37.591831],"type":"Point"}
}