{
  "type": "Feature",
  "properties": {
    "iso:country":"US",
    "sg:address":"20805 Gridley Rd",
    "sg:city":"Lakewood",
    "sg:classifiers":[
        {
            "category":"Building & Trades",
            "subcategory":"Construction",
            "type":"Services"
        }
    ],
    "sg:phone":"+1 562 809 9485",
    "sg:postcode":"90715",
    "sg:province":"CA",
    "sg:tags":[
        "acoustical",
        "insulation",
        "contractor"
    ],
    "wof:name":"A A A Ceiling & Wall Textures",
    "wof:placetype":"venue"
},
  "geometry": {"coordinates":[-118.090689,33.840933],"type":"Point"}
}