{
  "type": "Feature",
  "properties": {
    "addr:full":"240 Caledonium Ave Ben Lomond CA 95005",
    "addr:housenumber":"240",
    "addr:postcode":"95005",
    "addr:street":"Caledonium Ave",
    "iso:country":"US",
    "sg:address":"240 Caledonium Ave",
    "sg:city":"Ben Lomond",
    "sg:classifiers":[
        {
            "category":"Building & Trades",
            "subcategory":"Construction",
            "type":"Services"
        }
    ],
    "sg:phone":"+1 831 336 3137",
    "sg:postcode":"95005",
    "sg:province":"CA",
    "sg:tags":[
        "painter"
    ],
    "wof:name":"R & M Painting",
    "wof:placetype":"venue"
},
  "geometry": {"coordinates":[-122.080454,37.073213],"type":"Point"}
}