{
  "type": "Feature",
  "properties": {
    "addr:full":"610 Industrial Way Benicia CA 94510",
    "addr:housenumber":"610",
    "addr:postcode":"94510",
    "addr:street":"Industrial Way",
    "iso:country":"US",
    "sg:address":"610 Industrial Way",
    "sg:city":"Benicia",
    "sg:classifiers":[
        {
            "category":"Professional",
            "subcategory":"Business Services",
            "type":"Services"
        }
    ],
    "sg:phone":"+1 800 843 3604",
    "sg:postcode":"94510",
    "sg:province":"CA",
    "sg:tags":[
        "environmental",
        "ecological",
        "product"
    ],
    "wof:name":"Chemical Waste Mgmt.",
    "wof:placetype":"venue"
},
  "geometry": {"coordinates":[-122.13045099999999,38.07065],"type":"Point"}
}