{
  "type": "Feature",
  "properties": {
    "addr:full":"2436 Professional Dr Roseville CA 95661",
    "addr:housenumber":"2436",
    "addr:postcode":"95661",
    "addr:street":"Professional Dr",
    "iso:country":"US",
    "sg:address":"2436 Professional Dr",
    "sg:city":"Roseville",
    "sg:classifiers":[
        {
            "category":"Insurance",
            "subcategory":"Insurance Agent",
            "type":"Services"
        }
    ],
    "sg:phone":"+1 916 788 0113",
    "sg:postcode":"95661",
    "sg:province":"CA",
    "wof:name":"AFLAC",
    "wof:placetype":"venue"
},
  "geometry": {"coordinates":[-121.24744800000001,38.74246],"type":"Point"}
}