{
  "type": "Feature",
  "properties": {
    "addr:full":"5214 Diamond Heights Blvd San Francisco CA 94131",
    "addr:housenumber":"5214",
    "addr:postcode":"94131",
    "addr:street":"Diamond Heights Blvd",
    "iso:country":"US",
    "sg:address":"5214 Diamond Heights Blvd",
    "sg:city":"San Francisco",
    "sg:classifiers":[
        {
            "category":"Retail",
            "subcategory":"Animal Services",
            "type":"Services"
        }
    ],
    "sg:phone":"+1 415 647 8000",
    "sg:postcode":"94131",
    "sg:province":"CA",
    "sg:tags":[
        "training",
        "dog"
    ],
    "wof:name":"Perfect Paws",
    "wof:placetype":"venue"
},
  "geometry": {"coordinates":[-122.438087,37.743706],"type":"Point"}
}