{
  "type": "Feature",
  "properties": {
    "iso:country":"US",
    "sg:address":"1475 Long Beach Ave",
    "sg:city":"Los Angeles",
    "sg:classifiers":[
        {
            "category":"Wholesale",
            "subcategory":"Apparel",
            "type":"Manufacturing & Wholesale Goods"
        }
    ],
    "sg:phone":"+1 213 488 8400",
    "sg:postcode":"90021",
    "sg:province":"CA",
    "sg:tags":[
        "clothing"
    ],
    "wof:name":"Hot Kiss Inc",
    "wof:placetype":"venue"
},
  "geometry": {"coordinates":[-118.24178999999999,34.024747],"type":"Point"}
}