{
  "type": "Feature",
  "properties": {
    "iso:country":"US",
    "sg:address":"4341 El Camino Real",
    "sg:city":"Santa Clara",
    "sg:classifiers":[
        {
            "category":"Travel",
            "subcategory":"Hotels & Motels",
            "type":"Entertainment"
        }
    ],
    "sg:phone":"+1 408 244 3366",
    "sg:postcode":"95051",
    "sg:province":"CA",
    "sg:website":"www.bwsantaclara.com",
    "wof:name":"Best Western Inn-Santa Clara",
    "wof:placetype":"venue"
},
  "geometry": {"coordinates":[-122.00099899999999,37.3522],"type":"Point"}
}