{
  "type": "Feature",
  "properties": {
    "iso:country":"US",
    "sg:address":"2425 Vineyard Ave",
    "sg:city":"Escondido",
    "sg:classifiers":[
        {
            "category":"Manufacturing",
            "subcategory":"Metals",
            "type":"Manufacturing & Wholesale Goods"
        }
    ],
    "sg:phone":"+1 760 746 8301",
    "sg:postcode":"92029",
    "sg:province":"CA",
    "sg:tags":[
        "tool",
        "mfg"
    ],
    "wof:name":"Snap-On Tools",
    "wof:placetype":"venue"
},
  "geometry": {"coordinates":[-117.118916,33.124388],"type":"Point"}
}