{
  "type": "Feature",
  "properties": {
    "iso:country":"US",
    "sg:address":"Harding Park Golf Course 99 Harding Rd",
    "sg:city":"San Francisco",
    "sg:classifiers":[
        {
            "category":"Sports & Exercise",
            "subcategory":"Golf",
            "type":"Entertainment"
        }
    ],
    "sg:phone":"+1 415 533 6723",
    "sg:postcode":"94903",
    "sg:province":"CA",
    "sg:website":"www.rosskroeker.com",
    "wof:name":"Ross Kroeker - Golf Instruction",
    "wof:placetype":"venue"
},
  "geometry": {"coordinates":[-122.494891,37.723755],"type":"Point"}
}