{
  "type": "Feature",
  "properties": {
    "iso:country":"US",
    "sg:address":"1371 E 14th St Ste D",
    "sg:city":"San Leandro",
    "sg:classifiers":[
        {
            "category":"Personal",
            "subcategory":"Beauty Salon",
            "type":"Services"
        }
    ],
    "sg:phone":"+1 510 593 9226",
    "sg:postcode":"94577",
    "sg:province":"CA",
    "sg:tags":[
        "hair"
    ],
    "wof:name":"Hair Care by Sheila",
    "wof:placetype":"venue"
},
  "geometry": {"coordinates":[-122.155128,37.724483],"type":"Point"}
}