{
  "type": "Feature",
  "properties": {
    "iso:country":"US",
    "sg:address":"2874 Don Goodwin Dr",
    "sg:city":"Riverside",
    "sg:classifiers":[
        {
            "category":"Restaurant",
            "type":"Food & Drink"
        }
    ],
    "sg:phone":"+1 951 275 0661",
    "sg:postcode":"92507",
    "sg:province":"CA",
    "wof:name":"Amanda's Mexican Food",
    "wof:placetype":"venue"
},
  "geometry": {"coordinates":[-117.332776,33.987914],"type":"Point"}
}