{
  "type": "Feature",
  "properties": {
    "addr:full":"539 Carlsbad Village Dr Carlsbad CA 92008",
    "addr:housenumber":"539",
    "addr:postcode":"92008",
    "addr:street":"Carlsbad Village Dr",
    "iso:country":"US",
    "sg:address":"539 Carlsbad Village Dr",
    "sg:city":"Carlsbad",
    "sg:classifiers":[
        {
            "category":"Retail",
            "subcategory":"Self-service Laundry",
            "type":"Services"
        }
    ],
    "sg:phone":"+1 760 729 5777",
    "sg:postcode":"92008",
    "sg:province":"CA",
    "sg:tags":[
        "swimwear"
    ],
    "wof:name":"Eve Seven",
    "wof:placetype":"venue"
},
  "geometry": {"coordinates":[-117.348069,33.159567],"type":"Point"}
}