{
  "type": "Feature",
  "properties": {
    "iso:country":"US",
    "sg:address":"217 Carol Dr",
    "sg:city":"Ventura",
    "sg:classifiers":[
        {
            "category":"Retail",
            "subcategory":"Laundry & Dry Cleaning",
            "type":"Services"
        }
    ],
    "sg:phone":"+1 805 656 7847",
    "sg:postcode":"93003",
    "sg:province":"CA",
    "sg:tags":[
        "cleaners",
        "rug",
        "carpet"
    ],
    "wof:name":"Century Steam Cleaning",
    "wof:placetype":"venue"
},
  "geometry": {"coordinates":[-119.246047,34.278764],"type":"Point"}
}