{
  "type": "Feature",
  "properties": {
    "addr:full":"3181 Walnut Blvd Walnut Creek CA 94596",
    "addr:housenumber":"3181",
    "addr:postcode":"94596",
    "addr:street":"Walnut Blvd",
    "iso:country":"US",
    "sg:address":"3181 Walnut Blvd",
    "sg:city":"Walnut Creek",
    "sg:classifiers":[
        {
            "category":"Banks & Credit Unions",
            "subcategory":"Investment Brokerage",
            "type":"Services"
        }
    ],
    "sg:phone":"+1 925 935 0537",
    "sg:postcode":"94596",
    "sg:province":"CA",
    "sg:tags":[
        "security"
    ],
    "wof:name":"Giland Enterprises Inc",
    "wof:placetype":"venue"
},
  "geometry": {"coordinates":[-122.042272,37.894503],"type":"Point"}
}