{
  "type": "Feature",
  "properties": {
    "addr:full":"820 32nd St Oakland CA 94608",
    "addr:housenumber":"820",
    "addr:postcode":"94608",
    "addr:street":"32Nd St",
    "iso:country":"US",
    "sg:address":"820 32nd St",
    "sg:city":"Oakland",
    "sg:classifiers":[
        {
            "category":"Taxi",
            "type":"Transportation"
        }
    ],
    "sg:phone":"+1 510 655 9000",
    "sg:postcode":"94608",
    "sg:province":"CA",
    "wof:name":"A 1 Yellow Airport Express Taxi",
    "wof:placetype":"venue"
},
  "geometry": {"coordinates":[-122.273605,37.822155],"type":"Point"}
}