{
  "type": "Feature",
  "properties": {
    "addr:full":"2121 Central Ave South El Monte CA 91733",
    "addr:housenumber":"2121",
    "addr:postcode":"91733",
    "addr:street":"Central Ave",
    "iso:country":"US",
    "sg:address":"2121 Central Ave",
    "sg:city":"South El Monte",
    "sg:classifiers":[
        {
            "category":"Farming",
            "subcategory":"Farm & Veterinary Services",
            "type":"Manufacturing & Wholesale Goods"
        }
    ],
    "sg:phone":"+1 626 279 6982",
    "sg:postcode":"91733",
    "sg:province":"CA",
    "sg:tags":[
        "management"
    ],
    "wof:name":"USLL Group",
    "wof:placetype":"venue"
},
  "geometry": {"coordinates":[-118.04701900000001,34.052633],"type":"Point"}
}