{
  "type": "Feature",
  "properties": {
    "iso:country":"US",
    "sg:address":"1400 W Main St",
    "sg:city":"Turlock",
    "sg:classifiers":[
        {
            "category":"Manufacturing",
            "subcategory":"Food",
            "type":"Manufacturing & Wholesale Goods"
        },
        {
            "category":"Wholesale",
            "subcategory":"Durable Goods & Equipment",
            "type":"Manufacturing & Wholesale Goods"
        }
    ],
    "sg:phone":"+1 209 667 4505",
    "sg:postcode":"95380",
    "sg:province":"CA",
    "sg:tags":[
        "cheese",
        "importer",
        "mfg"
    ],
    "wof:name":"Lactalis USA Turlock Inc",
    "wof:placetype":"venue"
},
  "geometry": {"coordinates":[-120.865351,37.492661],"type":"Point"}
}