{
  "type": "Feature",
  "properties": {
    "iso:country":"US",
    "sg:address":"421 S Magnolia Ave",
    "sg:city":"El Cajon",
    "sg:classifiers":[
        {
            "category":"Building & Trades",
            "subcategory":"Construction",
            "type":"Services"
        }
    ],
    "sg:phone":"+1 619 405 1605",
    "sg:postcode":"92020",
    "sg:province":"CA",
    "sg:tags":[
        "contractor"
    ],
    "wof:name":"Sign Mountain",
    "wof:placetype":"venue"
},
  "geometry": {"coordinates":[-116.962247,32.790721],"type":"Point"}
}