{
  "type": "Feature",
  "properties": {
    "iso:country":"US",
    "sg:address":"253 Knowles Hill Dr",
    "sg:city":"Sonora",
    "sg:classifiers":[
        {
            "category":"Travel",
            "subcategory":"Hotels & Motels",
            "type":"Entertainment"
        }
    ],
    "sg:phone":"+1 209 536 1146",
    "sg:postcode":"95370",
    "sg:province":"CA",
    "sg:tags":[
        "breakfast",
        "accommodation",
        "bed"
    ],
    "sg:website":"www.knowleshillhouse.com",
    "wof:name":"Knowles Hill House",
    "wof:placetype":"venue"
},
  "geometry": {"coordinates":[-120.384727,37.98104],"type":"Point"}
}