{
  "type": "Feature",
  "properties": {
    "addr:full":"95 S Almaden Ave San Jose CA 95113",
    "addr:housenumber":"95",
    "addr:postcode":"95113",
    "addr:street":"S Almaden Ave",
    "iso:country":"US",
    "sg:address":"95 S Almaden Ave",
    "sg:city":"San Jose",
    "sg:classifiers":[
        {
            "category":"Shopping",
            "subcategory":"Clothing, Apparel, & Fashions",
            "type":"Retail Goods"
        },
        {
            "category":"Cinema",
            "subcategory":"Movie Rental",
            "type":"Entertainment"
        },
        {
            "category":"Shopping",
            "subcategory":"Music",
            "type":"Retail Goods"
        }
    ],
    "sg:phone":"+1 408 275 1754",
    "sg:postcode":"95113",
    "sg:province":"CA",
    "sg:tags":[
        "video",
        "game",
        "clothing",
        "dvd's",
        "women's"
    ],
    "wof:name":"Touch of Class",
    "wof:placetype":"venue"
},
  "geometry": {"coordinates":[-121.89243399999999,37.33292],"type":"Point"}
}