{
  "type": "Feature",
  "properties": {
    "addr:full":"2068 Tapo St Simi Valley CA 93063",
    "addr:housenumber":"2068",
    "addr:postcode":"93063",
    "addr:street":"Tapo St",
    "iso:country":"US",
    "sg:address":"2068 Tapo St",
    "sg:city":"Simi Valley",
    "sg:classifiers":[
        {
            "category":"Retail",
            "subcategory":"Car Wash",
            "type":"Services"
        }
    ],
    "sg:phone":"+1 805 526 1448",
    "sg:postcode":"93063",
    "sg:province":"CA",
    "sg:tags":[
        "automobile",
        "detail",
        "clean"
    ],
    "wof:name":"Simi Valley Car Wash",
    "wof:placetype":"venue"
},
  "geometry": {"coordinates":[-118.70886900000001,34.274493],"type":"Point"}
}