{
  "type": "Feature",
  "properties": {
    "iso:country":"US",
    "sg:address":"9158 W Olympic Blvd",
    "sg:city":"Beverly Hills",
    "sg:classifiers":[
        {
            "category":"Fast Food",
            "type":"Food & Drink"
        },
        {
            "category":"Food & Beverages",
            "subcategory":"Bakery",
            "type":"Retail Goods"
        }
    ],
    "sg:phone":"+1 310 859 8542",
    "sg:postcode":"90212",
    "sg:province":"CA",
    "sg:tags":[
        "sandwich"
    ],
    "sg:website":"www.quiznos.com",
    "wof:name":"Quizno's",
    "wof:placetype":"venue"
},
  "geometry": {"coordinates":[-118.391481,34.059378],"type":"Point"}
}