{
  "type": "Feature",
  "properties": {
    "addr:full":"650 Alabama St San Francisco CA 94110",
    "addr:housenumber":"650",
    "addr:postcode":"94110",
    "addr:street":"Alabama St",
    "iso:country":"US",
    "sg:address":"650 Alabama St",
    "sg:city":"San Francisco",
    "sg:classifiers":[
        {
            "category":"Professional",
            "subcategory":"Management & Consulting",
            "type":"Services"
        }
    ],
    "sg:phone":"+1 415 584 0824",
    "sg:postcode":"94110",
    "sg:province":"CA",
    "sg:tags":[
        "business"
    ],
    "wof:name":"Veale Construction Services",
    "wof:placetype":"venue"
},
  "geometry": {"coordinates":[-122.41205100000001,37.761014],"type":"Point"}
}