{
  "type": "Feature",
  "properties": {
    "iso:country":"US",
    "sg:address":"215 9th Ave",
    "sg:city":"La Puente",
    "sg:classifiers":[
        {
            "category":"Retail",
            "subcategory":"Repair Shop",
            "type":"Services"
        }
    ],
    "sg:phone":"+1 626 369 1916",
    "sg:postcode":"91746",
    "sg:province":"CA",
    "sg:tags":[
        "door"
    ],
    "wof:name":"Action Door Repair Corp",
    "wof:placetype":"venue"
},
  "geometry": {"coordinates":[-117.970477,34.02744],"type":"Point"}
}