{
  "type": "Feature",
  "properties": {
    "addr:full":"7056 Milwood Ave Canoga Park CA 91303",
    "addr:postcode":"7056;91303",
    "addr:street":"Milwood Ave",
    "iso:country":"US",
    "sg:address":"7056 Milwood Ave",
    "sg:city":"Canoga Park",
    "sg:classifiers":[
        {
            "category":"Organizations",
            "subcategory":"Religious Organization",
            "type":"Services"
        }
    ],
    "sg:phone":"+1 818 884 4258",
    "sg:postcode":"91303",
    "sg:province":"CA",
    "wof:name":"Iglesia El Shaddai",
    "wof:placetype":"venue"
},
  "geometry": {"coordinates":[-118.594002,34.199001],"type":"Point"}
}