{
  "type": "Feature",
  "properties": {
    "addr:full":"455 E Ocean Blvd Ste 12 Long Beach CA 90802",
    "addr:housenumber":"455",
    "addr:postcode":"90802",
    "addr:street":"E Ocean Blvd Ste 12",
    "iso:country":"US",
    "sg:address":"455 E Ocean Blvd Ste 12",
    "sg:city":"Long Beach",
    "sg:classifiers":[
        {
            "category":"Coffee & Tea",
            "type":"Food & Drink"
        }
    ],
    "sg:phone":"+1 562 432 1965",
    "sg:postcode":"90802",
    "sg:province":"CA",
    "wof:name":"East Village Cafe",
    "wof:placetype":"venue"
},
  "geometry": {"coordinates":[-118.183998,33.7705],"type":"Point"}
}