{
  "type": "Feature",
  "properties": {
    "iso:country":"US",
    "sg:address":"4908 Augusta Way",
    "sg:city":"San Jose",
    "sg:classifiers":[
        {
            "category":"Professional",
            "type":"Services"
        }
    ],
    "sg:phone":"+1 408 863 0515",
    "sg:postcode":"95129",
    "sg:province":"CA",
    "sg:tags":[
        "editorial"
    ],
    "wof:name":"Supreme Intelligence Corp",
    "wof:placetype":"venue"
},
  "geometry": {"coordinates":[-121.98947800000001,37.297354],"type":"Point"}
}