{
  "type": "Feature",
  "properties": {
    "iso:country":"US",
    "sg:address":"3255 Wilshire Boulevard Suite 1805",
    "sg:city":"Los Angeles",
    "sg:classifiers":[
        {
            "category":"Real Estate",
            "subcategory":"Architect",
            "type":"Services"
        }
    ],
    "sg:phone":"+1 213 386 7800",
    "sg:postcode":"90010",
    "sg:province":"CA",
    "wof:name":"Renosys USA",
    "wof:placetype":"venue"
},
  "geometry": {"coordinates":[-118.29302800000001,34.061831],"type":"Point"}
}