{
  "type": "Feature",
  "properties": {
    "addr:full":"6602 Costello Ave Van Nuys CA 91405",
    "addr:housenumber":"6602",
    "addr:postcode":"91405",
    "addr:street":"Costello Ave",
    "iso:country":"US",
    "sg:address":"6602 Costello Ave",
    "sg:city":"Van Nuys",
    "sg:classifiers":[
        {
            "category":"Real Estate",
            "subcategory":"Real Estate Operator",
            "type":"Services"
        }
    ],
    "sg:phone":"+1 818 785 9254",
    "sg:postcode":"91405",
    "sg:province":"CA",
    "sg:tags":[
        "building",
        "nonresidential"
    ],
    "wof:name":"Grinbaum Properties",
    "wof:placetype":"venue"
},
  "geometry": {"coordinates":[-118.437727,34.192998],"type":"Point"}
}