{
  "type": "Feature",
  "properties": {
    "addr:full":"5339 Craner Ave North Hollywood CA 91601",
    "addr:housenumber":"5339",
    "addr:postcode":"91601",
    "addr:street":"Craner Ave",
    "iso:country":"US",
    "sg:address":"5339 Craner Ave",
    "sg:city":"North Hollywood",
    "sg:classifiers":[
        {
            "category":"Wholesale",
            "subcategory":"Machinery & Supplies",
            "type":"Manufacturing & Wholesale Goods"
        }
    ],
    "sg:phone":"+1 818 761 2120",
    "sg:postcode":"91601",
    "sg:province":"CA",
    "sg:tags":[
        "equipment",
        "material",
        "handling"
    ],
    "sg:website":"www.ezeemanufacturing.com",
    "wof:name":"Ezee Manufacturing Inc",
    "wof:placetype":"venue"
},
  "geometry": {"coordinates":[-118.36922300000001,34.167105],"type":"Point"}
}