{
  "type": "Feature",
  "properties": {
    "iso:country":"US",
    "sg:address":"31 Brooks Ave",
    "sg:city":"Venice",
    "sg:classifiers":[
        {
            "category":"Home & Garden",
            "subcategory":"Furniture",
            "type":"Retail Goods"
        }
    ],
    "sg:phone":"+1 310 450 4286",
    "sg:postcode":"90291",
    "sg:province":"CA",
    "sg:tags":[
        "cabinet"
    ],
    "wof:name":"Alta Builders & Cabinetmakers",
    "wof:placetype":"venue"
},
  "geometry": {"coordinates":[-118.475553,33.991533],"type":"Point"}
}