{
  "type": "Feature",
  "properties": {
    "addr:full":"5201 Gage Ave Bell CA 90201",
    "addr:housenumber":"5201",
    "addr:postcode":"90201",
    "addr:street":"Gage Ave",
    "iso:country":"US",
    "sg:address":"5201 Gage Ave",
    "sg:city":"Bell",
    "sg:classifiers":[
        {
            "category":"Professional",
            "subcategory":"Business Services",
            "type":"Services"
        }
    ],
    "sg:phone":"+1 323 773 3282",
    "sg:postcode":"90201",
    "sg:province":"CA",
    "sg:tags":[
        "lecture",
        "bureau",
        "seminar"
    ],
    "wof:name":"Guillermo Vargas",
    "wof:placetype":"venue"
},
  "geometry": {"coordinates":[-118.172493,33.976458],"type":"Point"}
}