{
  "type": "Feature",
  "properties": {
    "iso:country":"US",
    "sg:address":"150 E Olive Ave Suite 307",
    "sg:city":"Burbank",
    "sg:classifiers":[
        {
            "category":"Banks & Credit Unions",
            "subcategory":"Investment Brokerage",
            "type":"Services"
        },
        {
            "category":"Banks & Credit Unions",
            "subcategory":"Bank",
            "type":"Services"
        },
        {
            "category":"Banks & Credit Unions",
            "subcategory":"Financial Services",
            "type":"Services"
        }
    ],
    "sg:phone":"+1 818 641 1863",
    "sg:postcode":"91502",
    "sg:province":"CA",
    "sg:tags":[
        "advisory",
        "mutual",
        "retirement",
        "annuity",
        "broker",
        "fund",
        "planning",
        "plan",
        "consultant",
        "security",
        "bond",
        "insurance",
        "stock"
    ],
    "sg:website":"http://losangeles.citysearch.com/profile/external/604305292/burbank_ca/edward_jones_gary_m_strangis.html?publisher=yellowpages&reference_id=1&placement=ypwebsitemip",
    "wof:name":"Edward Jones - GARY M STRANGIS",
    "wof:placetype":"venue"
},
  "geometry": {"coordinates":[-118.309302,34.180353],"type":"Point"}
}