{
  "type": "Feature",
  "properties": {
    "addr:full":"3037 Foothill Blvd Calistoga CA 94515",
    "addr:housenumber":"3037",
    "addr:postcode":"94515",
    "addr:street":"Foothill Blvd",
    "iso:country":"US",
    "sg:address":"3037 Foothill Blvd",
    "sg:city":"Calistoga",
    "sg:classifiers":[
        {
            "category":"Building & Trades",
            "subcategory":"Locksmith",
            "type":"Services"
        }
    ],
    "sg:phone":"+1 707 942 2632",
    "sg:postcode":"94515",
    "sg:province":"CA",
    "sg:tags":[
        "key"
    ],
    "wof:name":"Beckert's Lock & Key",
    "wof:placetype":"venue"
},
  "geometry": {"coordinates":[-122.604032,38.585753],"type":"Point"}
}