{
  "type": "Feature",
  "properties": {
    "iso:country":"US",
    "sg:address":"27511 Commerce Center Dr",
    "sg:city":"Temecula",
    "sg:classifiers":[
        {
            "category":"Restaurant",
            "type":"Food & Drink"
        }
    ],
    "sg:phone":"+1 951 676 2771",
    "sg:postcode":"92590",
    "sg:province":"CA",
    "sg:tags":[
        "caterer"
    ],
    "wof:name":"Wagon Master Catering",
    "wof:placetype":"venue"
},
  "geometry": {"coordinates":[-117.163382,33.514818],"type":"Point"}
}