{
  "type": "Feature",
  "properties": {
    "iso:country":"US",
    "sg:address":"748 E Arrow Hwy",
    "sg:city":"Pomona",
    "sg:classifiers":[
        {
            "category":"Utilities",
            "subcategory":"Mobile Phone",
            "type":"Services"
        }
    ],
    "sg:phone":"+1 909 625 0095",
    "sg:postcode":"91767",
    "sg:province":"CA",
    "sg:tags":[
        "telephone",
        "cellular"
    ],
    "wof:name":"Pomona 2 Pcs Hq",
    "wof:placetype":"venue"
},
  "geometry": {"coordinates":[-117.737296,34.089983],"type":"Point"}
}