{
  "type": "Feature",
  "properties": {
    "addr:full":"701 N Main St Porterville CA 93257",
    "addr:housenumber":"701",
    "addr:postcode":"93257",
    "addr:street":"N Main St",
    "iso:country":"US",
    "sg:address":"701 N Main St",
    "sg:city":"Porterville",
    "sg:classifiers":[
        {
            "category":"Autos & Motor Vehicles",
            "subcategory":"Automobile Sales",
            "type":"Retail Goods"
        }
    ],
    "sg:phone":"+1 559 784 6000",
    "sg:postcode":"93257",
    "sg:province":"CA",
    "sg:tags":[
        "car",
        "used",
        "truck",
        "dealer",
        "new"
    ],
    "sg:website":"www.clevengerford.com",
    "wof:name":"Clevenger Ford Inc",
    "wof:placetype":"venue"
},
  "geometry": {"coordinates":[-119.01928100000001,36.079578],"type":"Point"}
}