{
  "type": "Feature",
  "properties": {
    "addr:full":"617 Walnut Ave Sonoma CA 95476",
    "addr:housenumber":"617",
    "addr:postcode":"95476",
    "addr:street":"Walnut Ave",
    "iso:country":"US",
    "sg:address":"617 Walnut Ave",
    "sg:city":"Sonoma",
    "sg:classifiers":[
        {
            "category":"Manufacturing",
            "subcategory":"Tools & Machinery",
            "type":"Manufacturing & Wholesale Goods"
        }
    ],
    "sg:phone":"+1 707 996 4946",
    "sg:postcode":"95476",
    "sg:province":"CA",
    "sg:tags":[
        "mfg"
    ],
    "wof:name":"Donald B & Sandra O Geddes",
    "wof:placetype":"venue"
},
  "geometry": {"coordinates":[-122.48572900000001,38.296502],"type":"Point"}
}