{
  "type": "Feature",
  "properties": {
    "addr:full":"100 Sunset Ave Suisun City CA 94585",
    "addr:housenumber":"100",
    "addr:postcode":"94585",
    "addr:street":"Sunset Ave",
    "iso:country":"US",
    "sg:address":"100 Sunset Ave",
    "sg:city":"Suisun City",
    "sg:classifiers":[
        {
            "category":"Personal",
            "subcategory":"Barber",
            "type":"Services"
        }
    ],
    "sg:phone":"+1 707 631 2279",
    "sg:postcode":"94585",
    "sg:province":"CA",
    "wof:name":"Spencers Cuts & Styles",
    "wof:placetype":"venue"
},
  "geometry": {"coordinates":[-122.02030000000001,38.245019],"type":"Point"}
}