{
  "type": "Feature",
  "properties": {
    "iso:country":"US",
    "sg:address":"7710 Balboa Avenue",
    "sg:city":"San Diego",
    "sg:classifiers":[
        {
            "category":"Wholesale",
            "subcategory":"Computers",
            "type":"Manufacturing & Wholesale Goods"
        }
    ],
    "sg:phone":"+1 858 279 4995",
    "sg:postcode":"92111",
    "sg:province":"CA",
    "wof:name":"Pangea Enterprises",
    "wof:placetype":"venue"
},
  "geometry": {"coordinates":[-117.157343,32.821838],"type":"Point"}
}