{
  "type": "Feature",
  "properties": {
    "addr:full":"1256 Bush St San Francisco CA 94109",
    "addr:housenumber":"1256",
    "addr:postcode":"94109",
    "addr:street":"Bush St",
    "iso:country":"US",
    "sg:address":"1256 Bush St",
    "sg:city":"San Francisco",
    "sg:classifiers":[
        {
            "category":"Wholesale",
            "subcategory":"Durable Goods & Equipment",
            "type":"Manufacturing & Wholesale Goods"
        }
    ],
    "sg:phone":"+1 415 776 5614",
    "sg:postcode":"94109",
    "sg:province":"CA",
    "wof:name":"Jerry S Janssen",
    "wof:placetype":"venue"
},
  "geometry": {"coordinates":[-122.41856799999999,37.789],"type":"Point"}
}