{
  "type": "Feature",
  "properties": {
    "addr:full":"1264 S La Cienega Blvd Los Angeles CA 90035",
    "addr:housenumber":"1264",
    "addr:postcode":"90035",
    "addr:street":"S La Cienega Blvd",
    "iso:country":"US",
    "sg:address":"1264 S La Cienega Blvd",
    "sg:city":"Los Angeles",
    "sg:classifiers":[
        {
            "category":"Personal",
            "subcategory":"Nail Salon",
            "type":"Services"
        }
    ],
    "sg:phone":"+1 310 657 3069",
    "sg:postcode":"90035",
    "sg:province":"CA",
    "wof:name":"Perfect Nails",
    "wof:placetype":"venue"
},
  "geometry": {"coordinates":[-118.37599899999999,34.053902],"type":"Point"}
}