{
  "type": "Feature",
  "properties": {
    "addr:full":"102 Via Valencia Redondo Beach CA 90277",
    "addr:housenumber":"102",
    "addr:postcode":"90277",
    "addr:street":"Via Valencia",
    "iso:country":"US",
    "sg:address":"102 Via Valencia",
    "sg:city":"Redondo Beach",
    "sg:classifiers":[
        {
            "category":"Restaurant",
            "type":"Food & Drink"
        }
    ],
    "sg:phone":"+1 310 373 3235",
    "sg:postcode":"90277",
    "sg:province":"CA",
    "wof:name":"Maki Yaki 7",
    "wof:placetype":"venue"
},
  "geometry": {"coordinates":[-118.38544,33.817083],"type":"Point"}
}