{
  "type": "Feature",
  "properties": {
    "iso:country":"US",
    "sg:address":"8889 Etiwanda Ave",
    "sg:city":"Etiwanda",
    "sg:classifiers":[
        {
            "category":"Wholesale",
            "subcategory":"Scrap",
            "type":"Manufacturing & Wholesale Goods"
        }
    ],
    "sg:phone":"+1 951 377 2993",
    "sg:postcode":"91739",
    "sg:province":"CA",
    "sg:tags":[
        "recycling",
        "center"
    ],
    "wof:name":"Recycling Resources",
    "wof:placetype":"venue"
},
  "geometry": {"coordinates":[-117.523901,34.094471],"type":"Point"}
}