{
  "type": "Feature",
  "properties": {
    "addr:full":"2146 Union St San Francisco CA 94123",
    "addr:housenumber":"2146",
    "addr:postcode":"94123",
    "addr:street":"Union St",
    "iso:country":"US",
    "sg:address":"2146 Union St",
    "sg:city":"San Francisco",
    "sg:classifiers":[
        {
            "category":"Personal",
            "type":"Services"
        }
    ],
    "sg:phone":"+1 415 440 7040",
    "sg:postcode":"94123",
    "sg:province":"CA",
    "sg:tags":[
        "home"
    ],
    "sg:website":"www.jetsonsys.com",
    "wof:name":"Jetson Systems",
    "wof:placetype":"venue"
},
  "geometry": {"coordinates":[-122.434618,37.797235],"type":"Point"}
}