{
  "type": "Feature",
  "properties": {
    "addr:full":"8242 W 3rd St Los Angeles CA 90048",
    "addr:housenumber":"8242",
    "addr:postcode":"90048",
    "addr:street":"W 3Rd St",
    "iso:country":"US",
    "sg:address":"8242 W 3rd St",
    "sg:city":"Los Angeles",
    "sg:classifiers":[
        {
            "category":"Manufacturing",
            "subcategory":"Tools & Machinery",
            "type":"Manufacturing & Wholesale Goods"
        }
    ],
    "sg:phone":"+1 323 651 4539",
    "sg:postcode":"90048",
    "sg:province":"CA",
    "sg:tags":[
        "equipment",
        "suntanning",
        "mfg"
    ],
    "wof:name":"Sunvitale",
    "wof:placetype":"venue"
},
  "geometry": {"coordinates":[-118.369861,34.072568],"type":"Point"}
}