{
  "type": "Feature",
  "properties": {
    "addr:full":"2254 S Euclid Ave Ontario CA 91762",
    "addr:housenumber":"2254",
    "addr:postcode":"91762",
    "addr:street":"S Euclid Ave",
    "iso:country":"US",
    "sg:address":"2254 S Euclid Ave",
    "sg:city":"Ontario",
    "sg:classifiers":[
        {
            "category":"Shopping",
            "subcategory":"Shoes",
            "type":"Retail Goods"
        }
    ],
    "sg:phone":"+1 909 984 3745",
    "sg:postcode":"91762",
    "sg:province":"CA",
    "wof:name":"Payless Shoe Source",
    "wof:placetype":"venue"
},
  "geometry": {"coordinates":[-117.650925,34.031834],"type":"Point"}
}