{
  "type": "Feature",
  "properties": {
    "iso:country":"US",
    "sg:address":"3042 W Pico Blvd",
    "sg:city":"Los Angeles",
    "sg:classifiers":[
        {
            "category":"Recreation",
            "type":"Entertainment"
        }
    ],
    "sg:phone":"+1 213 629 0522",
    "sg:postcode":"90006",
    "sg:province":"CA",
    "sg:tags":[
        "psychic",
        "medium"
    ],
    "wof:name":"El Indio Amazonico",
    "wof:placetype":"venue"
},
  "geometry": {"coordinates":[-118.308725,34.047118],"type":"Point"}
}