{
  "type": "Feature",
  "properties": {
    "addr:full":"2189 S Grand Ave Santa Ana CA 92705",
    "addr:housenumber":"2189",
    "addr:postcode":"92705",
    "addr:street":"S Grand Ave",
    "iso:country":"US",
    "sg:address":"2189 S Grand Ave",
    "sg:city":"Santa Ana",
    "sg:classifiers":[
        {
            "category":"Manufacturing",
            "subcategory":"Tools & Machinery",
            "type":"Manufacturing & Wholesale Goods"
        }
    ],
    "sg:phone":"+1 714 979 9987",
    "sg:postcode":"92705",
    "sg:province":"CA",
    "sg:tags":[
        "machine",
        "shop"
    ],
    "wof:name":"Pro-Tech Fabrication",
    "wof:placetype":"venue"
},
  "geometry": {"coordinates":[-117.85048399999999,33.718061],"type":"Point"}
}