{
  "type": "Feature",
  "properties": {
    "addr:full":"9072 Wintergreen Rd Pinon Hills CA 92372",
    "addr:housenumber":"9072",
    "addr:postcode":"92372",
    "addr:street":"Wintergreen Rd",
    "iso:country":"US",
    "sg:address":"9072 Wintergreen Rd",
    "sg:city":"Pinon Hills",
    "sg:classifiers":[
        {
            "category":"Professional",
            "type":"Services"
        }
    ],
    "sg:phone":"+1 760 868 5252",
    "sg:postcode":"92372",
    "sg:province":"CA",
    "wof:name":"Tri State Mini Stockar Racing",
    "wof:placetype":"venue"
},
  "geometry": {"coordinates":[-117.62504800000001,34.415004],"type":"Point"}
}