{
  "type": "Feature",
  "properties": {
    "addr:full":"1705 W Pico Boulevard Los Angeles CA 90015",
    "addr:housenumber":"1705",
    "addr:postcode":"90015",
    "addr:street":"W Pico Boulevard",
    "iso:country":"US",
    "sg:address":"1705 W Pico Boulevard",
    "sg:city":"Los Angeles",
    "sg:classifiers":[
        {
            "category":"Restaurant",
            "type":"Food & Drink"
        }
    ],
    "sg:phone":"+1 213 386 9422",
    "sg:postcode":"90015",
    "sg:province":"CA",
    "sg:tags":[
        "spanish"
    ],
    "wof:name":"Flor Blanca No 3",
    "wof:placetype":"venue"
},
  "geometry": {"coordinates":[-118.278256,34.045118],"type":"Point"}
}