{
  "type": "Feature",
  "properties": {
    "iso:country":"US",
    "sg:address":"3260 J St",
    "sg:city":"Sacramento",
    "sg:classifiers":[
        {
            "category":"Restaurant",
            "type":"Food & Drink"
        }
    ],
    "sg:phone":"+1 916 448 5699",
    "sg:postcode":"95816",
    "sg:province":"CA",
    "sg:tags":[
        "new",
        "american",
        "modern",
        "mediterranean",
        "european"
    ],
    "sg:website":"bestbistrosacramento.com/",
    "wof:name":"Formoli's Bistro",
    "wof:placetype":"venue"
},
  "geometry": {"coordinates":[-121.462408,38.572086],"type":"Point"}
}