{
  "type": "Feature",
  "properties": {
    "addr:full":"301 Lambert St Oxnard CA 93036",
    "addr:housenumber":"301",
    "addr:postcode":"93036",
    "addr:street":"Lambert St",
    "iso:country":"US",
    "sg:address":"301 Lambert St",
    "sg:city":"Oxnard",
    "sg:classifiers":[
        {
            "category":"Autos & Motor Vehicles",
            "subcategory":"Auto Supplies",
            "type":"Retail Goods"
        },
        {
            "category":"Manufacturing",
            "subcategory":"Tools & Machinery",
            "type":"Manufacturing & Wholesale Goods"
        }
    ],
    "sg:phone":"+1 805 981 8775",
    "sg:postcode":"93036",
    "sg:province":"CA",
    "sg:tags":[
        "filter",
        "gas",
        "mfg"
    ],
    "wof:name":"Filter System & Supply",
    "wof:placetype":"venue"
},
  "geometry": {"coordinates":[-119.159896,34.253197],"type":"Point"}
}