{
  "type": "Feature",
  "properties": {
    "addr:full":"4267 Churchill Dr Pleasanton CA 94588",
    "addr:housenumber":"4267",
    "addr:postcode":"94588",
    "addr:street":"Churchill Dr",
    "iso:country":"US",
    "sg:address":"4267 Churchill Dr",
    "sg:city":"Pleasanton",
    "sg:classifiers":[
        {
            "category":"Retail",
            "subcategory":"Laundry & Dry Cleaning",
            "type":"Services"
        }
    ],
    "sg:phone":"+1 925 462 3375",
    "sg:postcode":"94588",
    "sg:province":"CA",
    "sg:tags":[
        "cleaners",
        "rug",
        "carpet"
    ],
    "wof:name":"Newell Carpet & Upholstery",
    "wof:placetype":"venue"
},
  "geometry": {"coordinates":[-121.875085,37.694649],"type":"Point"}
}