{
  "type": "Feature",
  "properties": {
    "addr:full":"150 E Colorado Blvd Pasadena CA 91105",
    "addr:housenumber":"150",
    "addr:postcode":"91105",
    "addr:street":"E Colorado Blvd",
    "iso:country":"US",
    "sg:address":"150 E Colorado Blvd",
    "sg:city":"Pasadena",
    "sg:classifiers":[
        {
            "category":"Professional",
            "subcategory":"Lawyer & Legal Services",
            "type":"Services"
        }
    ],
    "sg:phone":"+1 626 577 4100",
    "sg:postcode":"91105",
    "sg:province":"CA",
    "sg:tags":[
        "attorney",
        "practice",
        "plan"
    ],
    "wof:name":"Stewart & Harris",
    "wof:placetype":"venue"
},
  "geometry": {"coordinates":[-118.14753,34.145802],"type":"Point"}
}