{
  "type": "Feature",
  "properties": {
    "addr:full":"5501 Broadway Sacramento CA 95820",
    "addr:housenumber":"5501",
    "addr:postcode":"95820",
    "addr:street":"Broadway",
    "iso:country":"US",
    "sg:address":"5501 Broadway",
    "sg:city":"Sacramento",
    "sg:classifiers":[
        {
            "category":"Real Estate",
            "subcategory":"Real Estate Services",
            "type":"Services"
        }
    ],
    "sg:phone":"+1 916 455 9822",
    "sg:postcode":"95820",
    "sg:province":"CA",
    "sg:tags":[
        "management",
        "property"
    ],
    "wof:name":"Green Fair HOA",
    "wof:placetype":"venue"
},
  "geometry": {"coordinates":[-121.441682,38.546897],"type":"Point"}
}