{
  "type": "Feature",
  "properties": {
    "iso:country":"US",
    "sg:address":"9454 Wilshire Blvd",
    "sg:city":"Beverly Hills",
    "sg:classifiers":[
        {
            "category":"Shopping",
            "subcategory":"Jewelry",
            "type":"Retail Goods"
        }
    ],
    "sg:phone":"+1 310 276 9941",
    "sg:postcode":"90212",
    "sg:province":"CA",
    "sg:tags":[
        "jade"
    ],
    "wof:name":"Edward Dominik",
    "wof:placetype":"venue"
},
  "geometry": {"coordinates":[-118.398597,34.066982],"type":"Point"}
}