{
  "type": "Feature",
  "properties": {
    "iso:country":"US",
    "sg:address":"3251 20th Ave",
    "sg:city":"San Francisco",
    "sg:classifiers":[
        {
            "category":"Health Services",
            "subcategory":"Optometrist",
            "type":"Services"
        }
    ],
    "sg:phone":"+1 415 564 7785",
    "sg:postcode":"94132",
    "sg:province":"CA",
    "wof:name":"Broadway Eye Works",
    "wof:placetype":"venue"
},
  "geometry": {"coordinates":[-122.47584,37.72887],"type":"Point"}
}