{
  "type": "Feature",
  "properties": {
    "iso:country":"US",
    "sg:address":"633 Elmira Rd",
    "sg:city":"Vacaville",
    "sg:classifiers":[
        {
            "category":"Health Services",
            "subcategory":"Chiropractor",
            "type":"Services"
        }
    ],
    "sg:phone":"+1 707 452 9497",
    "sg:postcode":"95687",
    "sg:province":"CA",
    "sg:tags":[
        "chiropractic"
    ],
    "wof:name":"Kosak Wilson Chiropractic, Inc.",
    "wof:placetype":"venue"
},
  "geometry": {"coordinates":[-121.95065700000001,38.351766],"type":"Point"}
}