{
  "type": "Feature",
  "properties": {
    "addr:full":"922 Fremont Ave Clovis CA 93612",
    "addr:housenumber":"922",
    "addr:postcode":"93612",
    "addr:street":"Fremont Ave",
    "iso:country":"US",
    "sg:address":"922 Fremont Ave",
    "sg:city":"Clovis",
    "sg:classifiers":[
        {
            "category":"Professional",
            "subcategory":"Business Services",
            "type":"Services"
        }
    ],
    "sg:phone":"+1 559 250 3932",
    "sg:postcode":"93612",
    "sg:province":"CA",
    "sg:tags":[
        "inspection"
    ],
    "wof:name":"A Plus Inspection",
    "wof:placetype":"venue"
},
  "geometry": {"coordinates":[-119.69336199999999,36.835264],"type":"Point"}
}