{
  "type": "Feature",
  "properties": {
    "iso:country":"US",
    "sg:address":"3000 Olympic Blvd",
    "sg:city":"Santa Monica",
    "sg:classifiers":[
        {
            "category":"Communications",
            "subcategory":"Film & Video Production",
            "type":"Services"
        }
    ],
    "sg:phone":"+1 310 315 5000",
    "sg:postcode":"90404",
    "sg:province":"CA",
    "sg:tags":[
        "motion",
        "picture",
        "studio",
        "producer"
    ],
    "sg:website":"www.todd-ao.com",
    "wof:name":"TODD Studios West",
    "wof:placetype":"venue"
},
  "geometry": {"coordinates":[-118.46187999999999,34.030682],"type":"Point"}
}