{
  "type": "Feature",
  "properties": {
    "addr:full":"2016 Coombsville Rd Napa CA 94558",
    "addr:postcode":"2016;94558",
    "addr:street":"Coombsville Rd",
    "iso:country":"US",
    "sg:address":"2016 Coombsville Rd",
    "sg:city":"Napa",
    "sg:classifiers":[
        {
            "category":"Shopping",
            "type":"Retail Goods"
        }
    ],
    "sg:phone":"+1 707 529 8799",
    "sg:postcode":"94558",
    "sg:province":"CA",
    "sg:tags":[
        "cosmetic",
        "perfume"
    ],
    "wof:name":"Mary Kay Cosmetics",
    "wof:placetype":"venue"
},
  "geometry": {"coordinates":[-122.25199600000001,38.29541],"type":"Point"}
}