{
  "type": "Feature",
  "properties": {
    "iso:country":"US",
    "sg:address":"2840 Middlefield Rd",
    "sg:city":"Redwood City",
    "sg:classifiers":[
        {
            "category":"Shopping",
            "subcategory":"Clothing, Apparel, & Fashions",
            "type":"Retail Goods"
        }
    ],
    "sg:phone":"+1 650 367 6001",
    "sg:postcode":"94063",
    "sg:province":"CA",
    "wof:name":"Gaby's Shoes & Clothes",
    "wof:placetype":"venue"
},
  "geometry": {"coordinates":[-122.20981399999999,37.475589],"type":"Point"}
}