{
  "type": "Feature",
  "properties": {
    "addr:full":"3620 American River Drive Sacramento CA 95864",
    "addr:housenumber":"3620",
    "addr:postcode":"95864",
    "addr:street":"American River Drive",
    "iso:country":"US",
    "sg:address":"3620 American River Drive",
    "sg:city":"Sacramento",
    "sg:classifiers":[
        {
            "category":"Professional",
            "subcategory":"Lawyer & Legal Services",
            "type":"Services"
        }
    ],
    "sg:phone":"+1 916 488 3616",
    "sg:postcode":"95864",
    "sg:province":"CA",
    "wof:name":"Benjamin Law Offices",
    "wof:placetype":"venue"
},
  "geometry": {"coordinates":[-121.37853,38.570543],"type":"Point"}
}