{
  "type": "Feature",
  "properties": {
    "iso:country":"US",
    "sg:address":"2815 St George St",
    "sg:city":"Los Angeles",
    "sg:classifiers":[
        {
            "category":"Manufacturing",
            "subcategory":"Printing",
            "type":"Manufacturing & Wholesale Goods"
        }
    ],
    "sg:phone":"+1 323 668 0480",
    "sg:postcode":"90027",
    "sg:province":"CA",
    "sg:tags":[
        "publisher"
    ],
    "wof:name":"Wind Whisper Magic",
    "wof:placetype":"venue"
},
  "geometry": {"coordinates":[-118.274069,34.109626],"type":"Point"}
}