{
  "type": "Feature",
  "properties": {
    "iso:country":"US",
    "sg:address":"10930 Long Beach Blvd",
    "sg:city":"Lynwood",
    "sg:classifiers":[
        {
            "category":"Cinema",
            "subcategory":"Movie Rental",
            "type":"Entertainment"
        }
    ],
    "sg:phone":"+1 424 785 5709",
    "sg:postcode":"90262",
    "sg:province":"CA",
    "sg:tags":[
        "game",
        "video"
    ],
    "wof:name":"Disco Tienda Jalisco",
    "wof:placetype":"venue"
},
  "geometry": {"coordinates":[-118.212319,33.933829],"type":"Point"}
}