{
  "type": "Feature",
  "properties": {
    "addr:full":"3834 Bayside Walk San Diego CA 92109",
    "addr:housenumber":"3834",
    "addr:postcode":"92109",
    "addr:street":"Bayside Walk",
    "iso:country":"US",
    "sg:address":"3834 Bayside Walk",
    "sg:city":"San Diego",
    "sg:classifiers":[
        {
            "category":"Retail",
            "subcategory":"Animal Services",
            "type":"Services"
        }
    ],
    "sg:phone":"+1 858 488 7111",
    "sg:postcode":"92109",
    "sg:province":"CA",
    "sg:tags":[
        "training",
        "dog"
    ],
    "wof:name":"Marcia & Assoc",
    "wof:placetype":"venue"
},
  "geometry": {"coordinates":[-117.25223099999999,32.785859],"type":"Point"}
}