{
  "type": "Feature",
  "properties": {
    "addr:full":"3290 Stevens Creek Blvd San Jose CA 95128",
    "addr:housenumber":"3290",
    "addr:postcode":"95128",
    "addr:street":"Stevens Creek Blvd",
    "iso:country":"US",
    "sg:address":"3290 Stevens Creek Blvd",
    "sg:city":"San Jose",
    "sg:classifiers":[
        {
            "category":"Banks & Credit Unions",
            "subcategory":"Bank",
            "type":"Services"
        }
    ],
    "sg:phone":"+1 408 248 8820",
    "sg:postcode":"95128",
    "sg:province":"CA",
    "wof:name":"Union Bank Of CA",
    "wof:placetype":"venue"
},
  "geometry": {"coordinates":[-121.95451300000001,37.323123],"type":"Point"}
}