{
  "type": "Feature",
  "properties": {
    "iso:country":"US",
    "sg:address":"17015 Hawthorne Blvd",
    "sg:city":"Lawndale",
    "sg:classifiers":[
        {
            "category":"Manufacturing",
            "subcategory":"Printing",
            "type":"Manufacturing & Wholesale Goods"
        }
    ],
    "sg:phone":"+1 310 370 1121",
    "sg:postcode":"90260",
    "sg:province":"CA",
    "sg:tags":[
        "printer",
        "lithographic",
        "letterpress"
    ],
    "wof:name":"South Bay Prtg & Lithograph Co",
    "wof:placetype":"venue"
},
  "geometry": {"coordinates":[-118.352428,33.875834],"type":"Point"}
}