{
  "type": "Feature",
  "properties": {
    "addr:full":"87 N Chestnut St Ventura CA 93001",
    "addr:housenumber":"87",
    "addr:postcode":"93001",
    "addr:street":"N Chestnut St",
    "iso:country":"US",
    "sg:address":"87 N Chestnut St",
    "sg:city":"Ventura",
    "sg:classifiers":[
        {
            "category":"Professional",
            "subcategory":"Lawyer & Legal Services",
            "type":"Services"
        }
    ],
    "sg:phone":"+1 805 987 9807",
    "sg:postcode":"93001",
    "sg:province":"CA",
    "sg:tags":[
        "attorney"
    ],
    "wof:name":"James W Marsala Law Office",
    "wof:placetype":"venue"
},
  "geometry": {"coordinates":[-119.29163200000001,34.282703],"type":"Point"}
}