{
  "type": "Feature",
  "properties": {
    "addr:full":"1232 Wrightwood Ct Rosamond CA 93560",
    "addr:housenumber":"1232",
    "addr:postcode":"93560",
    "addr:street":"Wrightwood Ct",
    "iso:country":"US",
    "sg:address":"1232 Wrightwood Ct",
    "sg:city":"Rosamond",
    "sg:classifiers":[
        {
            "category":"Professional",
            "subcategory":"Detective & Security Services",
            "type":"Services"
        }
    ],
    "sg:phone":"+1 661 609 0100",
    "sg:postcode":"93560",
    "sg:province":"CA",
    "sg:tags":[
        "information",
        "bureau"
    ],
    "wof:name":"Pete's",
    "wof:placetype":"venue"
},
  "geometry": {"coordinates":[-118.151618,34.878589],"type":"Point"}
}