{
  "type": "Feature",
  "properties": {
    "iso:country":"US",
    "sg:address":"18539 Topham St",
    "sg:city":"Reseda",
    "sg:classifiers":[
        {
            "category":"Retail",
            "subcategory":"Auto Repair",
            "type":"Services"
        }
    ],
    "sg:phone":"+1 818 342 4999",
    "sg:postcode":"91335",
    "sg:province":"CA",
    "sg:tags":[
        "body",
        "automobile",
        "used",
        "painting",
        "general"
    ],
    "wof:name":"H & R Auto Paint & Body Repair",
    "wof:placetype":"venue"
},
  "geometry": {"coordinates":[-118.539661,34.180822],"type":"Point"}
}