{
  "type": "Feature",
  "properties": {
    "iso:country":"US",
    "sg:address":"16881 Pacific Ave",
    "sg:city":"Sunset Beach",
    "sg:classifiers":[
        {
            "category":"Recreation",
            "type":"Entertainment"
        }
    ],
    "sg:phone":"+1 562 592 7630",
    "sg:postcode":"90742",
    "sg:province":"CA",
    "sg:tags":[
        "guide"
    ],
    "wof:name":"Ultimate Lodging Guide",
    "wof:placetype":"venue"
},
  "geometry": {"coordinates":[-118.06921,33.71611],"type":"Point"}
}