{
  "type": "Feature",
  "properties": {
    "addr:full":"1859 Pinon Ave Anderson CA 96007",
    "addr:housenumber":"1859",
    "addr:postcode":"96007",
    "addr:street":"Pinon Ave",
    "iso:country":"US",
    "sg:address":"1859 Pinon Ave",
    "sg:city":"Anderson",
    "sg:classifiers":[
        {
            "category":"Personal",
            "type":"Services"
        },
        {
            "category":"Professional",
            "subcategory":"Art Services",
            "type":"Services"
        }
    ],
    "sg:phone":"+1 530 339 6588",
    "sg:postcode":"96007",
    "sg:province":"CA",
    "sg:tags":[
        "photography",
        "videography",
        "wedding"
    ],
    "wof:name":"Erin Claassen Photography",
    "wof:placetype":"venue"
},
  "geometry": {"coordinates":[-122.292682,40.438024],"type":"Point"}
}