{
  "type": "Feature",
  "properties": {
    "iso:country":"US",
    "sg:address":"455 N Raymond Ave",
    "sg:city":"Pasadena",
    "sg:classifiers":[
        {
            "category":"Real Estate",
            "subcategory":"Real Estate Operator",
            "type":"Services"
        }
    ],
    "sg:phone":"+1 626 793 0208",
    "sg:postcode":"91103",
    "sg:province":"CA",
    "sg:tags":[
        "apartment"
    ],
    "wof:name":"Holeinwon",
    "wof:placetype":"venue"
},
  "geometry": {"coordinates":[-118.149002,34.155102],"type":"Point"}
}