{
  "type": "Feature",
  "properties": {
    "iso:country":"US",
    "sg:address":"13599 Desmond St",
    "sg:city":"Pacoima",
    "sg:classifiers":[
        {
            "category":"Manufacturing",
            "subcategory":"Rubber & Plastics",
            "type":"Manufacturing & Wholesale Goods"
        }
    ],
    "sg:phone":"+1 818 897 7736",
    "sg:postcode":"91331",
    "sg:province":"CA",
    "sg:tags":[
        "product"
    ],
    "sg:website":"www.phillipsplywood.com",
    "wof:name":"Phillips Plywood Co Inc",
    "wof:placetype":"venue"
},
  "geometry": {"coordinates":[-118.427707,34.275547],"type":"Point"}
}