{
  "type": "Feature",
  "properties": {
    "addr:full":"167 E 6th St Beaumont CA 92223",
    "addr:housenumber":"167",
    "addr:postcode":"92223",
    "addr:street":"E 6Th St",
    "iso:country":"US",
    "sg:address":"167 E 6th St",
    "sg:city":"Beaumont",
    "sg:classifiers":[
        {
            "category":"Organizations",
            "subcategory":"Religious Organization",
            "type":"Services"
        }
    ],
    "sg:phone":"+1 951 845 1908",
    "sg:postcode":"92223",
    "sg:province":"CA",
    "sg:tags":[
        "church"
    ],
    "wof:name":"Life Changers Christian Flwshp",
    "wof:placetype":"venue"
},
  "geometry": {"coordinates":[-116.98052800000001,33.929327],"type":"Point"}
}