{
  "type": "Feature",
  "properties": {
    "addr:full":"1035 Swarthmore Ave Pacific Plsds CA 90272",
    "addr:housenumber":"1035",
    "addr:postcode":"90272",
    "addr:street":"Swarthmore Ave",
    "iso:country":"US",
    "sg:address":"1035 Swarthmore Ave",
    "sg:city":"Pacific Plsds",
    "sg:classifiers":[
        {
            "category":"Restaurant",
            "type":"Food & Drink"
        }
    ],
    "sg:phone":"+1 310 454 5511",
    "sg:postcode":"90272",
    "sg:province":"CA",
    "wof:name":"Mort's Palisades Delicatessen",
    "wof:placetype":"venue"
},
  "geometry": {"coordinates":[-118.52511199999999,34.048163],"type":"Point"}
}