{
  "type": "Feature",
  "properties": {
    "addr:full":"628 W Rosecrans Avenue Compton CA 90222",
    "addr:housenumber":"628",
    "addr:postcode":"90222",
    "addr:street":"W Rosecrans Avenue",
    "iso:country":"US",
    "sg:address":"628 W Rosecrans Avenue",
    "sg:city":"Compton",
    "sg:classifiers":[
        {
            "category":"Retail",
            "subcategory":"Auto Repair",
            "type":"Services"
        }
    ],
    "sg:phone":"+1 310 631 4911",
    "sg:postcode":"90222",
    "sg:province":"CA",
    "wof:name":"Mexicali Auto Service",
    "wof:placetype":"venue"
},
  "geometry": {"coordinates":[-118.234877,33.903252],"type":"Point"}
}