{
  "type": "Feature",
  "properties": {
    "iso:country":"US",
    "sg:address":"8020 Skander Way",
    "sg:city":"Sacramento",
    "sg:classifiers":[
        {
            "category":"Building & Trades",
            "subcategory":"Landscaping Services",
            "type":"Services"
        }
    ],
    "sg:phone":"+1 916 224 5127",
    "sg:postcode":"95828",
    "sg:province":"CA",
    "sg:tags":[
        "lawn",
        "maintenance",
        "grounds"
    ],
    "wof:name":"G & H Gardening Svc",
    "wof:placetype":"venue"
},
  "geometry": {"coordinates":[-121.409308,38.487696],"type":"Point"}
}