{
  "type": "Feature",
  "properties": {
    "iso:country":"US",
    "sg:address":"1835 Grant St",
    "sg:city":"Santa Clara",
    "sg:classifiers":[
        {
            "category":"Freight",
            "type":"Transportation"
        }
    ],
    "sg:phone":"+1 408 969 0300",
    "sg:postcode":"95050",
    "sg:province":"CA",
    "sg:tags":[
        "mover"
    ],
    "wof:name":"Silicon Valley Moving",
    "wof:placetype":"venue"
},
  "geometry": {"coordinates":[-121.94353,37.35728],"type":"Point"}
}