{
  "type": "Feature",
  "properties": {
    "iso:country":"US",
    "sg:address":"2324 Fletcher Dr",
    "sg:city":"Los Angeles",
    "sg:classifiers":[
        {
            "category":"Shopping",
            "subcategory":"Florist",
            "type":"Retail Goods"
        }
    ],
    "sg:phone":"+1 323 660 6298",
    "sg:postcode":"90039",
    "sg:province":"CA",
    "sg:website":"alohaflowersla.com/",
    "wof:name":"Aloha Flowers",
    "wof:placetype":"venue"
},
  "geometry": {"coordinates":[-118.25826000000001,34.10487],"type":"Point"}
}