{
  "type": "Feature",
  "properties": {
    "addr:full":"Brookhurst & Orange Anaheim CA 92804",
    "addr:postcode":"92804",
    "iso:country":"US",
    "sg:address":"Brookhurst & Orange",
    "sg:city":"Anaheim",
    "sg:classifiers":[
        {
            "category":"Restaurant",
            "type":"Food & Drink"
        }
    ],
    "sg:postcode":"92804",
    "sg:province":"CA",
    "sg:tags":[
        "flavor",
        "local"
    ],
    "wof:name":"Little Arabia",
    "wof:placetype":"venue"
},
  "geometry": {"coordinates":[-117.958854,33.825021],"type":"Point"}
}