{
  "type": "Feature",
  "properties": {
    "iso:country":"US",
    "sg:address":"13615 Bowen St",
    "sg:city":"Garden Grove",
    "sg:classifiers":[
        {
            "category":"Local Transit",
            "type":"Transportation"
        }
    ],
    "sg:phone":"+1 714 539 6129",
    "sg:postcode":"92843",
    "sg:province":"CA",
    "sg:tags":[
        "passenger"
    ],
    "wof:name":"Johns Limosine Service",
    "wof:placetype":"venue"
},
  "geometry": {"coordinates":[-117.9507,33.764626],"type":"Point"}
}