{
  "type": "Feature",
  "properties": {
    "addr:full":"3017 High Meadow Ln San Jose CA 95135",
    "addr:housenumber":"3017",
    "addr:postcode":"95135",
    "addr:street":"High Meadow Ln",
    "iso:country":"US",
    "sg:address":"3017 High Meadow Ln",
    "sg:city":"San Jose",
    "sg:classifiers":[
        {
            "category":"Health Services",
            "subcategory":"Clinic",
            "type":"Services"
        },
        {
            "category":"Recreation",
            "type":"Entertainment"
        }
    ],
    "sg:phone":"+1 408 528 8961",
    "sg:postcode":"95135",
    "sg:province":"CA",
    "sg:tags":[
        "active",
        "medical",
        "life"
    ],
    "sg:website":"www.aabs.us.com",
    "wof:name":"aabs Nutrition & Fitness Coaching",
    "wof:placetype":"venue"
},
  "geometry": {"coordinates":[-121.74991199999999,37.280293],"type":"Point"}
}