{
  "type": "Feature",
  "properties": {
    "addr:full":"357 Pine Hill Rd Mill Valley CA 94941",
    "addr:housenumber":"357",
    "addr:postcode":"94941",
    "addr:street":"Pine Hill Rd",
    "iso:country":"US",
    "sg:address":"357 Pine Hill Rd",
    "sg:city":"Mill Valley",
    "sg:classifiers":[
        {
            "category":"Professional",
            "subcategory":"Computer Services",
            "type":"Services"
        }
    ],
    "sg:phone":"+1 415 307 0816",
    "sg:postcode":"94941",
    "sg:province":"CA",
    "sg:tags":[
        "internet"
    ],
    "wof:name":"Decklin's Domain",
    "wof:placetype":"venue"
},
  "geometry": {"coordinates":[-122.533525,37.883231],"type":"Point"}
}