{
  "type": "Feature",
  "properties": {
    "addr:full":"3700 S Susan St Ste 190 Santa Ana CA 92704",
    "addr:housenumber":"3700",
    "addr:postcode":"92704",
    "addr:street":"S Susan St Ste 190",
    "iso:country":"US",
    "sg:address":"3700 S Susan St Ste 190",
    "sg:city":"Santa Ana",
    "sg:classifiers":[
        {
            "category":"Restaurant",
            "type":"Food & Drink"
        }
    ],
    "sg:phone":"+1 714 957 2744",
    "sg:postcode":"92704",
    "sg:province":"CA",
    "wof:name":"Lakeside Cafe",
    "wof:placetype":"venue"
},
  "geometry": {"coordinates":[-117.914001,33.7005],"type":"Point"}
}