{
  "type": "Feature",
  "properties": {
    "iso:country":"US",
    "sg:address":"709 D St",
    "sg:city":"Ramona",
    "sg:classifiers":[
        {
            "category":"Building & Trades",
            "subcategory":"Landscaping Services",
            "type":"Services"
        }
    ],
    "sg:phone":"+1 760 787 9887",
    "sg:postcode":"92065",
    "sg:province":"CA",
    "wof:name":"TLC Landscaping",
    "wof:placetype":"venue"
},
  "geometry": {"coordinates":[-116.864644,33.042991],"type":"Point"}
}