{
  "type": "Feature",
  "properties": {
    "addr:full":"19990 Lakeshore Dr Lakehead CA 96051",
    "addr:housenumber":"19990",
    "addr:postcode":"96051",
    "addr:street":"Lakeshore Dr",
    "iso:country":"US",
    "sg:address":"19990 Lakeshore Dr",
    "sg:city":"Lakehead",
    "sg:classifiers":[
        {
            "category":"Professional",
            "type":"Services"
        }
    ],
    "sg:phone":"+1 530 238 8660",
    "sg:postcode":"96051",
    "sg:province":"CA",
    "wof:name":"David Grey",
    "wof:placetype":"venue"
},
  "geometry": {"coordinates":[-122.395871,40.865112],"type":"Point"}
}