{
  "type": "Feature",
  "properties": {
    "addr:full":"2078 Hayes Street San Francisco CA 94117",
    "addr:housenumber":"2078",
    "addr:postcode":"94117",
    "addr:street":"Hayes Street",
    "iso:country":"US",
    "sg:address":"2078 Hayes Street",
    "sg:city":"San Francisco",
    "sg:classifiers":[
        {
            "category":"Building & Trades",
            "subcategory":"Locksmith",
            "type":"Services"
        }
    ],
    "sg:phone":"+1 415 752 2973",
    "sg:postcode":"94117",
    "sg:province":"CA",
    "sg:tags":[
        "key"
    ],
    "wof:name":"A 24 Hour A Emergency Locksmith",
    "wof:placetype":"venue"
},
  "geometry": {"coordinates":[-122.449997,37.773499],"type":"Point"}
}