{
  "type": "Feature",
  "properties": {
    "iso:country":"US",
    "sg:address":"2930 Eldorado St",
    "sg:city":"Torrance",
    "sg:classifiers":[
        {
            "category":"Organizations",
            "subcategory":"Religious Organization",
            "type":"Services"
        }
    ],
    "sg:phone":"+1 310 328 2820",
    "sg:postcode":"90503",
    "sg:province":"CA",
    "sg:tags":[
        "church"
    ],
    "sg:website":"www.fcctorrance.org",
    "wof:name":"First Christian Church",
    "wof:placetype":"venue"
},
  "geometry": {"coordinates":[-118.33993599999999,33.834245],"type":"Point"}
}