{
  "type": "Feature",
  "properties": {
    "addr:full":"4450 W Lakeside Dr Ste 250 Burbank CA 91505",
    "addr:housenumber":"4450",
    "addr:postcode":"91505",
    "addr:street":"W Lakeside Dr Ste 250",
    "iso:country":"US",
    "sg:address":"4450 W Lakeside Dr Ste 250",
    "sg:city":"Burbank",
    "sg:classifiers":[
        {
            "category":"Professional",
            "subcategory":"Lawyer & Legal Services",
            "type":"Services"
        }
    ],
    "sg:phone":"+1 818 842 1616",
    "sg:postcode":"91505",
    "sg:province":"CA",
    "wof:name":"Walter Lantz Foundation",
    "wof:placetype":"venue"
},
  "geometry": {"coordinates":[-118.341438,34.145609],"type":"Point"}
}