{
  "type": "Feature",
  "properties": {
    "iso:country":"US",
    "sg:address":"2701 Ming Ave",
    "sg:city":"Bakersfield",
    "sg:classifiers":[
        {
            "category":"Shopping",
            "subcategory":"Bicycles & Sporting Goods",
            "type":"Retail Goods"
        }
    ],
    "sg:phone":"+1 661 831 2849",
    "sg:postcode":"93304",
    "sg:province":"CA",
    "sg:tags":[
        "skating",
        "equipment",
        "supply"
    ],
    "wof:name":"White Sands",
    "wof:placetype":"venue"
},
  "geometry": {"coordinates":[-119.03183199999999,35.339383],"type":"Point"}
}