{
  "type": "Feature",
  "properties": {
    "addr:full":"1273 E Imperial Hwy Placentia CA 92870",
    "addr:housenumber":"1273",
    "addr:postcode":"ca 92870",
    "addr:street":"E Imperial Hwy",
    "iso:country":"US",
    "sg:address":"1273 E Imperial Hwy",
    "sg:city":"Placentia",
    "sg:classifiers":[
        {
            "category":"Personal",
            "type":"Services"
        },
        {
            "category":"Sports & Exercise",
            "subcategory":"Gym",
            "type":"Entertainment"
        },
        {
            "category":"Health Services",
            "subcategory":"Health Practitioner",
            "type":"Services"
        },
        {
            "category":"Arena",
            "subcategory":"Sports Club",
            "type":"Entertainment"
        }
    ],
    "sg:phone":"+1 800 615 7352",
    "sg:postcode":"92870",
    "sg:province":"CA",
    "sg:tags":[
        "control",
        "trainer",
        "weight",
        "consultant",
        "program",
        "fitness",
        "physical"
    ],
    "sg:website":"http://orangecounty.citysearch.com/profile/external/37223818/placentia_ca/curves.html?publisher=yellowpages&reference_id=1&placement=ypwebsitemip",
    "wof:name":"Curves",
    "wof:placetype":"venue"
},
  "geometry": {"coordinates":[-117.84074099999999,33.903681],"type":"Point"}
}