{
  "type": "Feature",
  "properties": {
    "addr:full":"333 S Garfield Ave Alhambra CA 91801",
    "addr:housenumber":"333",
    "addr:postcode":"91801",
    "addr:street":"S Garfield Ave",
    "iso:country":"US",
    "sg:address":"333 S Garfield Ave",
    "sg:city":"Alhambra",
    "sg:classifiers":[
        {
            "category":"Health Services",
            "subcategory":"Clinic",
            "type":"Services"
        }
    ],
    "sg:phone":"+1 626 289 3605",
    "sg:postcode":"91801",
    "sg:province":"CA",
    "wof:name":"San Gabriel Valley Management",
    "wof:placetype":"venue"
},
  "geometry": {"coordinates":[-118.12430999999999,34.091434],"type":"Point"}
}