{
  "type": "Feature",
  "properties": {
    "addr:full":"3031 Telegraph Ave Ste 234 Berkeley CA 94705",
    "addr:housenumber":"3031",
    "addr:postcode":"94705",
    "addr:street":"Telegraph Ave Ste 234",
    "iso:country":"US",
    "sg:address":"3031 Telegraph Ave Ste 234",
    "sg:city":"Berkeley",
    "sg:classifiers":[
        {
            "category":"Health Services",
            "subcategory":"Doctor",
            "type":"Services"
        }
    ],
    "sg:phone":"+1 510 548 9114",
    "sg:postcode":"94705",
    "sg:province":"CA",
    "sg:tags":[
        "surgeon",
        "oral"
    ],
    "sg:website":"baysideoralsurgery.com",
    "wof:name":"Bayside Oral Surgery",
    "wof:placetype":"venue"
},
  "geometry": {"coordinates":[-122.259698,37.854807],"type":"Point"}
}