{
  "type": "Feature",
  "properties": {
    "addr:full":"1307 McGee Ave Berkeley CA 94703",
    "addr:housenumber":"1307",
    "addr:postcode":"94703",
    "addr:street":"Mcgee Ave",
    "iso:country":"US",
    "sg:address":"1307 McGee Ave",
    "sg:city":"Berkeley",
    "sg:classifiers":[
        {
            "category":"Personal",
            "subcategory":"Massage",
            "type":"Services"
        }
    ],
    "sg:phone":"+1 510 524 2227",
    "sg:postcode":"94703",
    "sg:province":"CA",
    "wof:name":"Marina Eglevsky, Rosen Method Bodywork, Divining Dance",
    "wof:placetype":"venue"
},
  "geometry": {"coordinates":[-122.280748,37.881879],"type":"Point"}
}