{
  "type": "Feature",
  "properties": {
    "iso:country":"US",
    "sg:address":"6176 Ansdell Way",
    "sg:city":"San Jose",
    "sg:classifiers":[
        {
            "category":"Retail",
            "subcategory":"Laundry & Dry Cleaning",
            "type":"Services"
        }
    ],
    "sg:phone":"+1 408 379 3430",
    "sg:postcode":"95123",
    "sg:province":"CA",
    "sg:tags":[
        "cleaners",
        "rug",
        "carpet"
    ],
    "wof:name":"So Clean",
    "wof:placetype":"venue"
},
  "geometry": {"coordinates":[-121.810979,37.234163],"type":"Point"}
}