{
  "type": "Feature",
  "properties": {
    "addr:full":"2748 Sugarpine Ln Fallbrook CA 92028",
    "addr:housenumber":"2748",
    "addr:postcode":"92028",
    "addr:street":"Sugarpine Ln",
    "iso:country":"US",
    "sg:address":"2748 Sugarpine Ln",
    "sg:city":"Fallbrook",
    "sg:classifiers":[
        {
            "category":"Professional",
            "type":"Services"
        }
    ],
    "sg:phone":"+1 760 728 6291",
    "sg:postcode":"92028",
    "sg:province":"CA",
    "sg:tags":[
        "establishment"
    ],
    "wof:name":"Geddes Co",
    "wof:placetype":"venue"
},
  "geometry": {"coordinates":[-117.189915,33.342366],"type":"Point"}
}