{
  "type": "Feature",
  "properties": {
    "iso:country":"US",
    "sg:address":"1875 Century Park E",
    "sg:city":"Los Angeles",
    "sg:classifiers":[
        {
            "category":"Professional",
            "subcategory":"Lawyer & Legal Services",
            "type":"Services"
        }
    ],
    "sg:phone":"+1 310 550 9050",
    "sg:postcode":"90067",
    "sg:province":"CA",
    "wof:name":"Law Office of James L Pocrass",
    "wof:placetype":"venue"
},
  "geometry": {"coordinates":[-118.414558,34.061079],"type":"Point"}
}