{
  "type": "Feature",
  "properties": {
    "addr:full":"15151 Windover Ct Lake Elsinore CA 92530",
    "addr:postcode":"15151;92530",
    "addr:street":"Windover Ct",
    "iso:country":"US",
    "sg:address":"15151 Windover Ct",
    "sg:city":"Lake Elsinore",
    "sg:classifiers":[
        {
            "category":"Freight",
            "type":"Transportation"
        }
    ],
    "sg:phone":"+1 951 678 1259",
    "sg:postcode":"92530",
    "sg:province":"CA",
    "sg:tags":[
        "local",
        "without",
        "storage",
        "trucking"
    ],
    "wof:name":"John D Perona Jr and Son",
    "wof:placetype":"venue"
},
  "geometry": {"coordinates":[-117.38904700000001,33.668251],"type":"Point"}
}