{
  "type": "Feature",
  "properties": {
    "iso:country":"US",
    "sg:address":"1330 Ross St",
    "sg:city":"Petaluma",
    "sg:classifiers":[
        {
            "category":"Manufacturing",
            "subcategory":"Printing",
            "type":"Manufacturing & Wholesale Goods"
        }
    ],
    "sg:phone":"+1 707 763 9031",
    "sg:postcode":"94954",
    "sg:province":"CA",
    "sg:tags":[
        "commercial"
    ],
    "wof:name":"CCC Enterprises",
    "wof:placetype":"venue"
},
  "geometry": {"coordinates":[-122.66468500000001,38.268471],"type":"Point"}
}