{
  "type": "Feature",
  "properties": {
    "iso:country":"US",
    "sg:address":"1034 E 6th St",
    "sg:city":"Ontario",
    "sg:classifiers":[
        {
            "category":"Professional",
            "type":"Services"
        }
    ],
    "sg:phone":"+1 909 933 9227",
    "sg:postcode":"91764",
    "sg:province":"CA",
    "wof:name":"Oliu Enterprises",
    "wof:placetype":"venue"
},
  "geometry": {"coordinates":[-117.635578,34.085164],"type":"Point"}
}