{
  "type": "Feature",
  "properties": {
    "iso:country":"US",
    "sg:address":"490 Rosvall Dr",
    "sg:city":"Fallbrook",
    "sg:classifiers":[
        {
            "category":"Building & Trades",
            "subcategory":"Construction",
            "type":"Services"
        }
    ],
    "sg:phone":"+1 760 723 9965",
    "sg:postcode":"92028",
    "sg:province":"CA",
    "sg:tags":[
        "contractor"
    ],
    "sg:website":"www.hartbuilt.com",
    "wof:name":"Hartcorn Construction",
    "wof:placetype":"venue"
},
  "geometry": {"coordinates":[-117.254997,33.386002],"type":"Point"}
}