{
  "type": "Feature",
  "properties": {
    "addr:full":"600 23rd St Richmond CA 94804",
    "addr:housenumber":"600",
    "addr:postcode":"94804",
    "addr:street":"23Rd St",
    "iso:country":"US",
    "sg:address":"600 23rd St",
    "sg:city":"Richmond",
    "sg:classifiers":[
        {
            "category":"Retail",
            "subcategory":"Auto Repair",
            "type":"Services"
        }
    ],
    "sg:phone":"+1 510 235 8676",
    "sg:postcode":"94804",
    "sg:province":"CA",
    "sg:tags":[
        "automobile",
        "electric"
    ],
    "wof:name":"S & R Alternators",
    "wof:placetype":"venue"
},
  "geometry": {"coordinates":[-122.347504,37.93996],"type":"Point"}
}