{
  "type": "Feature",
  "properties": {
    "iso:country":"US",
    "sg:address":"68 Edgegate Ct",
    "sg:city":"Danville",
    "sg:classifiers":[
        {
            "category":"Manufacturing",
            "subcategory":"Retail Goods",
            "type":"Manufacturing & Wholesale Goods"
        }
    ],
    "sg:phone":"+1 925 736 6885",
    "sg:postcode":"94506",
    "sg:province":"CA",
    "sg:tags":[
        "candle"
    ],
    "wof:name":"Laramar Designs",
    "wof:placetype":"venue"
},
  "geometry": {"coordinates":[-121.90858299999999,37.793927],"type":"Point"}
}