{
  "type": "Feature",
  "properties": {
    "iso:country":"US",
    "sg:address":"220 Broad Ave",
    "sg:city":"Wilmington",
    "sg:classifiers":[
        {
            "category":"Manufacturing",
            "subcategory":"Metals",
            "type":"Manufacturing & Wholesale Goods"
        }
    ],
    "sg:phone":"+1 310 830 1144",
    "sg:postcode":"90744",
    "sg:province":"CA",
    "sg:tags":[
        "steel"
    ],
    "wof:name":"Le Meur Welding",
    "wof:placetype":"venue"
},
  "geometry": {"coordinates":[-118.26046700000001,33.772503],"type":"Point"}
}