{
  "type": "Feature",
  "properties": {
    "iso:country":"US",
    "sg:address":"1405 W F St",
    "sg:city":"Oakdale",
    "sg:classifiers":[
        {
            "category":"Social Services",
            "subcategory":"Job Training",
            "type":"Services"
        }
    ],
    "sg:phone":"+1 209 848 4241",
    "sg:postcode":"95361",
    "sg:province":"CA",
    "sg:tags":[
        "rehab",
        "government"
    ],
    "wof:name":"Job Service",
    "wof:placetype":"venue"
},
  "geometry": {"coordinates":[-120.86335,37.759741],"type":"Point"}
}