{
  "type": "Feature",
  "properties": {
    "addr:full":"72690 State Rte 70 Portola CA 96122",
    "addr:housenumber":"72690",
    "addr:postcode":"96122",
    "addr:street":"State Rte 70",
    "iso:country":"US",
    "sg:address":"72690 State Rte 70",
    "sg:city":"Portola",
    "sg:classifiers":[
        {
            "category":"Organizations",
            "subcategory":"Religious Organization",
            "type":"Services"
        }
    ],
    "sg:phone":"+1 530 832 4710",
    "sg:postcode":"96122",
    "sg:province":"CA",
    "sg:tags":[
        "church"
    ],
    "wof:name":"New Life Christian Ctr",
    "wof:placetype":"venue"
},
  "geometry": {"coordinates":[-120.517217,39.801286],"type":"Point"}
}