{
  "type": "Feature",
  "properties": {
    "addr:full":"701 S San Gabriel Blvd San Gabriel CA 91776",
    "addr:housenumber":"701",
    "addr:postcode":"91776",
    "addr:street":"S San Gabriel Blvd",
    "iso:country":"US",
    "sg:address":"701 S San Gabriel Blvd",
    "sg:city":"San Gabriel",
    "sg:classifiers":[
        {
            "category":"Professional",
            "subcategory":"Lawyer & Legal Services",
            "type":"Services"
        }
    ],
    "sg:phone":"+1 626 285 2939",
    "sg:postcode":"91776",
    "sg:province":"CA",
    "wof:name":"Law Offices of Espinosa & Associates",
    "wof:placetype":"venue"
},
  "geometry": {"coordinates":[-118.091003,34.0942],"type":"Point"}
}