{
  "type": "Feature",
  "properties": {
    "addr:full":"4400 Swanson Rd Denair CA 95316",
    "addr:housenumber":"4400",
    "addr:postcode":"95316",
    "addr:street":"Swanson Rd",
    "iso:country":"US",
    "sg:address":"4400 Swanson Rd",
    "sg:city":"Denair",
    "sg:classifiers":[
        {
            "category":"Farming",
            "subcategory":"Dairy Farm",
            "type":"Manufacturing & Wholesale Goods"
        }
    ],
    "sg:phone":"+1 209 632 8700",
    "sg:postcode":"95316",
    "sg:province":"CA",
    "wof:name":"George Griggs",
    "wof:placetype":"venue"
},
  "geometry": {"coordinates":[-120.782938,37.578193],"type":"Point"}
}