{
  "type": "Feature",
  "properties": {
    "iso:country":"US",
    "sg:address":"308 W Line St",
    "sg:city":"Bishop",
    "sg:classifiers":[
        {
            "category":"Professional",
            "subcategory":"Lawyer & Legal Services",
            "type":"Services"
        }
    ],
    "sg:phone":"+1 760 873 4756",
    "sg:postcode":"93514",
    "sg:province":"CA",
    "sg:tags":[
        "attorney"
    ],
    "wof:name":"David D Hammon",
    "wof:placetype":"venue"
},
  "geometry": {"coordinates":[-118.397307,37.361283],"type":"Point"}
}