{
  "type": "Feature",
  "properties": {
    "addr:full":"3410 El Camino real Santa Clara CA 95051",
    "addr:housenumber":"3410",
    "addr:postcode":"95051",
    "addr:street":"El Camino Real",
    "iso:country":"US",
    "sg:address":"3410 El Camino real",
    "sg:city":"Santa Clara",
    "sg:classifiers":[
        {
            "category":"Shopping",
            "subcategory":"Clothing, Apparel, & Fashions",
            "type":"Retail Goods"
        }
    ],
    "sg:phone":"+1 408 554 1334",
    "sg:postcode":"95051",
    "sg:province":"CA",
    "sg:tags":[
        "clothing",
        "women's"
    ],
    "sg:website":"www.mystyleholic.com",
    "wof:name":"Mystyle",
    "wof:placetype":"venue"
},
  "geometry": {"coordinates":[-121.98980899999999,37.352265],"type":"Point"}
}