{
  "type": "Feature",
  "properties": {
    "iso:country":"US",
    "sg:address":"898 Luxury Dr",
    "sg:city":"Concord",
    "sg:classifiers":[
        {
            "category":"Shopping",
            "type":"Retail Goods"
        }
    ],
    "sg:phone":"+1 925 676 7511",
    "sg:postcode":"94518",
    "sg:province":"CA",
    "sg:tags":[
        "cosmetic",
        "perfume"
    ],
    "wof:name":"Mary Kay Cosmetics",
    "wof:placetype":"venue"
},
  "geometry": {"coordinates":[-122.022575,37.950473],"type":"Point"}
}