{
  "type": "Feature",
  "properties": {
    "addr:full":"1071 E Capitol Expy San Jose CA 95121",
    "addr:housenumber":"1071",
    "addr:postcode":"95121",
    "addr:street":"E Capitol Expy",
    "iso:country":"US",
    "sg:address":"1071 E Capitol Expy",
    "sg:city":"San Jose",
    "sg:classifiers":[
        {
            "category":"Restaurant",
            "type":"Food & Drink"
        }
    ],
    "sg:phone":"+1 408 226 6235",
    "sg:postcode":"95121",
    "sg:province":"CA",
    "sg:tags":[
        "seafood"
    ],
    "wof:name":"Pacific Lobster & Seafood Restaurant",
    "wof:placetype":"venue"
},
  "geometry": {"coordinates":[-121.822998,37.2994],"type":"Point"}
}