{
  "type": "Feature",
  "properties": {
    "addr:full":"6116 Malburg Way Vernon CA 90058",
    "addr:housenumber":"6116",
    "addr:postcode":"90058",
    "addr:street":"Malburg Way",
    "iso:country":"US",
    "sg:address":"6116 Malburg Way",
    "sg:city":"Vernon",
    "sg:classifiers":[
        {
            "category":"Wholesale",
            "subcategory":"Toys & Hobbies",
            "type":"Manufacturing & Wholesale Goods"
        }
    ],
    "sg:phone":"+1 323 583 7670",
    "sg:postcode":"90058",
    "sg:province":"CA",
    "wof:name":"California Plush Toys",
    "wof:placetype":"venue"
},
  "geometry": {"coordinates":[-118.205236,33.985746],"type":"Point"}
}