{
  "type": "Feature",
  "properties": {
    "addr:full":"2701 Santiago Dr Modesto CA 95354",
    "addr:housenumber":"2701",
    "addr:postcode":"ca 95354",
    "addr:street":"Santiago Dr",
    "iso:country":"US",
    "sg:address":"2701 Santiago Dr",
    "sg:city":"Modesto",
    "sg:classifiers":[
        {
            "category":"Professional",
            "subcategory":"Computer Services",
            "type":"Services"
        }
    ],
    "sg:phone":"+1 209 522 8841",
    "sg:postcode":"95354",
    "sg:province":"CA",
    "sg:tags":[
        "information",
        "consulting",
        "designer",
        "consultant",
        "equipment",
        "technology"
    ],
    "sg:website":"http://www.imabiz.com",
    "wof:name":"Information Management Associates",
    "wof:placetype":"venue"
},
  "geometry": {"coordinates":[-120.94502300000001,37.644718],"type":"Point"}
}