{
  "type": "Feature",
  "properties": {
    "addr:full":"511 Lakeside Pkwy Santa Maria CA 93455",
    "addr:housenumber":"511",
    "addr:postcode":"93455",
    "addr:street":"Lakeside Pkwy",
    "iso:country":"US",
    "sg:address":"511 Lakeside Pkwy",
    "sg:city":"Santa Maria",
    "sg:classifiers":[
        {
            "category":"Government",
            "subcategory":"Office",
            "type":"Public Place"
        }
    ],
    "sg:phone":"+1 805 346 8375",
    "sg:postcode":"93455",
    "sg:province":"CA",
    "wof:name":"Birth Certificate",
    "wof:placetype":"venue"
},
  "geometry": {"coordinates":[-120.427305,34.922913],"type":"Point"}
}