{
  "type": "Feature",
  "properties": {
    "addr:full":"8500 Beverly Boulevard Los Angeles CA 90048",
    "addr:housenumber":"8500",
    "addr:postcode":"90048",
    "addr:street":"Beverly Boulevard",
    "iso:country":"US",
    "sg:address":"8500 Beverly Boulevard",
    "sg:city":"Los Angeles",
    "sg:classifiers":[
        {
            "category":"Shopping",
            "subcategory":"Beauty & Cosmetics",
            "type":"Retail Goods"
        }
    ],
    "sg:phone":"+1 310 659 1041",
    "sg:postcode":"90048",
    "sg:province":"CA",
    "sg:tags":[
        "supply"
    ],
    "wof:name":"Kristy's Beauty Supplies & Salon",
    "wof:placetype":"venue"
},
  "geometry": {"coordinates":[-118.376608,34.075945],"type":"Point"}
}