{
  "type": "Feature",
  "properties": {
    "addr:full":"15460 S Western Ave #101 Gardena CA 90249",
    "addr:housenumber":"15460",
    "addr:postcode":"90249",
    "addr:street":"S Western Ave # 101",
    "iso:country":"US",
    "sg:address":"15460 S Western Ave #101",
    "sg:city":"Gardena",
    "sg:classifiers":[
        {
            "category":"Restaurant",
            "type":"Food & Drink"
        }
    ],
    "sg:phone":"+1 310 327 8494",
    "sg:postcode":"90249",
    "sg:province":"CA",
    "sg:tags":[
        "korean"
    ],
    "wof:name":"S Cafe",
    "wof:placetype":"venue"
},
  "geometry": {"coordinates":[-118.309119,33.890434],"type":"Point"}
}