{
  "type": "Feature",
  "properties": {
    "addr:full":"1126 W 158th St Gardena CA 90247",
    "addr:housenumber":"1126",
    "addr:postcode":"90247",
    "addr:street":"W 158Th St",
    "iso:country":"US",
    "sg:address":"1126 W 158th St",
    "sg:city":"Gardena",
    "sg:classifiers":[
        {
            "category":"Shopping",
            "subcategory":"Optical Goods",
            "type":"Retail Goods"
        }
    ],
    "sg:phone":"+1 310 327 3978",
    "sg:postcode":"90247",
    "sg:province":"CA",
    "wof:name":"Optisight",
    "wof:placetype":"venue"
},
  "geometry": {"coordinates":[-118.29418800000001,33.887792],"type":"Point"}
}