{
  "type": "Feature",
  "properties": {
    "iso:country":"US",
    "sg:address":"8071 Greenback Ln",
    "sg:city":"Citrus Heights",
    "sg:classifiers":[
        {
            "category":"Sports & Exercise",
            "subcategory":"Gym",
            "type":"Entertainment"
        }
    ],
    "sg:phone":"+1 916 729 2878",
    "sg:postcode":"95610",
    "sg:province":"CA",
    "sg:website":"www.curves.com",
    "wof:name":"Curves",
    "wof:placetype":"venue"
},
  "geometry": {"coordinates":[-121.26300000000001,38.678699],"type":"Point"}
}