{
  "type": "Feature",
  "properties": {
    "iso:country":"US",
    "sg:address":"480 Rough and Ready Rd",
    "sg:city":"San Jose",
    "sg:classifiers":[
        {
            "category":"Education",
            "subcategory":"School",
            "type":"Public Place"
        }
    ],
    "sg:phone":"+1 408 928 8800",
    "sg:postcode":"95133",
    "sg:province":"CA",
    "wof:name":"William Sheppard Middle School",
    "wof:placetype":"venue"
},
  "geometry": {"coordinates":[-121.844105,37.375862],"type":"Point"}
}