{
  "type": "Feature",
  "properties": {
    "addr:full":"3015 W Burbank Blvd Burbank CA 91505",
    "addr:housenumber":"3015",
    "addr:postcode":"91505",
    "addr:street":"W Burbank Blvd",
    "iso:country":"US",
    "sg:address":"3015 W Burbank Blvd",
    "sg:city":"Burbank",
    "sg:classifiers":[
        {
            "category":"Wholesale",
            "subcategory":"Electrical",
            "type":"Manufacturing & Wholesale Goods"
        }
    ],
    "sg:phone":"+1 818 842 4666",
    "sg:postcode":"91505",
    "sg:province":"CA",
    "sg:tags":[
        "fire",
        "alarm",
        "system"
    ],
    "wof:name":"Signal Systems Inc",
    "wof:placetype":"venue"
},
  "geometry": {"coordinates":[-118.343861,34.176925],"type":"Point"}
}