{
  "type": "Feature",
  "properties": {
    "addr:full":"7399 San Joaquin St Sacramento CA 95820",
    "addr:housenumber":"7399",
    "addr:postcode":"95820",
    "addr:street":"San Joaquin St",
    "iso:country":"US",
    "sg:address":"7399 San Joaquin St",
    "sg:city":"Sacramento",
    "sg:classifiers":[
        {
            "category":"Shopping",
            "subcategory":"Mobile Phones",
            "type":"Retail Goods"
        }
    ],
    "sg:phone":"+1 916 457 2716",
    "sg:postcode":"95820",
    "sg:province":"CA",
    "wof:name":"SkyTel",
    "wof:placetype":"venue"
},
  "geometry": {"coordinates":[-121.419179,38.544757],"type":"Point"}
}