{
  "type": "Feature",
  "properties": {
    "addr:full":"287 2nd Ave Daly City CA 94014",
    "addr:housenumber":"287",
    "addr:postcode":"94014",
    "addr:street":"2Nd Ave",
    "iso:country":"US",
    "sg:address":"287 2nd Ave",
    "sg:city":"Daly City",
    "sg:classifiers":[
        {
            "category":"Restaurant",
            "type":"Food & Drink"
        }
    ],
    "sg:phone":"+1 650 992 0650",
    "sg:postcode":"94014",
    "sg:province":"CA",
    "sg:tags":[
        "barbecue"
    ],
    "wof:name":"Original Australian Bbq",
    "wof:placetype":"venue"
},
  "geometry": {"coordinates":[-122.46288800000001,37.689234],"type":"Point"}
}