{
  "type": "Feature",
  "properties": {
    "iso:country":"US",
    "sg:address":"1240 Merkley Ave",
    "sg:city":"West Sacramento",
    "sg:classifiers":[
        {
            "category":"Organizations",
            "subcategory":"Religious Organization",
            "type":"Services"
        }
    ],
    "sg:phone":"+1 916 491 5368",
    "sg:postcode":"95691",
    "sg:province":"CA",
    "sg:tags":[
        "church"
    ],
    "wof:name":"Sacrifice Of Praise Christian",
    "wof:placetype":"venue"
},
  "geometry": {"coordinates":[-121.525414,38.579513],"type":"Point"}
}