{
  "type": "Feature",
  "properties": {
    "iso:country":"US",
    "sg:address":"2800 California St",
    "sg:city":"Stockton",
    "sg:classifiers":[
        {
            "category":"Shopping",
            "subcategory":"Pharmacy",
            "type":"Retail Goods"
        }
    ],
    "sg:phone":"+1 209 464 8758",
    "sg:postcode":"95204",
    "sg:province":"CA",
    "wof:name":"Medical Arts Pharmacy",
    "wof:placetype":"venue"
},
  "geometry": {"coordinates":[-121.292281,37.97853],"type":"Point"}
}