{
  "type": "Feature",
  "properties": {
    "addr:full":"8562 Arnett Dr Huntington Beach CA 92647",
    "addr:housenumber":"8562",
    "addr:postcode":"92647",
    "addr:street":"Arnett Dr",
    "iso:country":"US",
    "sg:address":"8562 Arnett Dr",
    "sg:city":"Huntington Beach",
    "sg:classifiers":[
        {
            "category":"Manufacturing",
            "subcategory":"Printing",
            "type":"Manufacturing & Wholesale Goods"
        }
    ],
    "sg:phone":"+1 714 843 0321",
    "sg:postcode":"92647",
    "sg:province":"CA",
    "sg:tags":[
        "publishing"
    ],
    "wof:name":"Jensen Publications",
    "wof:placetype":"venue"
},
  "geometry": {"coordinates":[-117.979789,33.71807],"type":"Point"}
}