{
  "type": "Feature",
  "properties": {
    "addr:full":"8538 Eton Ave Canoga Park CA 91304",
    "addr:housenumber":"8538",
    "addr:postcode":"91304",
    "addr:street":"Eton Ave",
    "iso:country":"US",
    "sg:address":"8538 Eton Ave",
    "sg:city":"Canoga Park",
    "sg:classifiers":[
        {
            "category":"Wholesale",
            "subcategory":"Machinery & Supplies",
            "type":"Manufacturing & Wholesale Goods"
        }
    ],
    "sg:phone":"+1 818 773 0836",
    "sg:postcode":"91304",
    "sg:province":"CA",
    "sg:tags":[
        "equipment",
        "industrial"
    ],
    "wof:name":"Eclipse Retractable Screens",
    "wof:placetype":"venue"
},
  "geometry": {"coordinates":[-118.59499700000001,34.226045],"type":"Point"}
}