{
  "type": "Feature",
  "properties": {
    "addr:full":"21710 Hawthorne Blvd Del Amo Fashion Center Torrance CA 90503",
    "addr:housenumber":"21710",
    "addr:postcode":"90503",
    "addr:street":"Hawthorne Blvd",
    "iso:country":"US",
    "sg:address":"21710 Hawthorne Blvd Del Amo Fashion Center",
    "sg:city":"Torrance",
    "sg:classifiers":[
        {
            "category":"Home & Garden",
            "subcategory":"Home Furnishings",
            "type":"Retail Goods"
        },
        {
            "category":"Home & Garden",
            "subcategory":"Furniture",
            "type":"Retail Goods"
        }
    ],
    "sg:phone":"+1 310 371 4804",
    "sg:postcode":"90503",
    "sg:province":"CA",
    "sg:tags":[
        "decor",
        "store"
    ],
    "sg:website":"www.crateandbarrel.com",
    "wof:name":"Crate & Barrel",
    "wof:placetype":"venue"
},
  "geometry": {"coordinates":[-118.352265,33.830177],"type":"Point"}
}