{
  "type": "Feature",
  "properties": {
    "addr:full":"4601 Wilshire Blvd Los Angeles CA 90010",
    "addr:housenumber":"4601",
    "addr:postcode":"90010",
    "addr:street":"Wilshire Blvd",
    "iso:country":"US",
    "sg:address":"4601 Wilshire Blvd",
    "sg:city":"Los Angeles",
    "sg:classifiers":[
        {
            "category":"Wholesale",
            "subcategory":"Durable Goods & Equipment",
            "type":"Manufacturing & Wholesale Goods"
        }
    ],
    "sg:phone":"+1 323 936 6000",
    "sg:postcode":"90010",
    "sg:province":"CA",
    "sg:tags":[
        "importer"
    ],
    "wof:name":"Maicross Business",
    "wof:placetype":"venue"
},
  "geometry": {"coordinates":[-118.330381,34.061957],"type":"Point"}
}