{
  "type": "Feature",
  "properties": {
    "addr:full":"2357 Glendon Ave Los Angeles CA 90064",
    "addr:housenumber":"2357",
    "addr:postcode":"90064",
    "addr:street":"Glendon Ave",
    "iso:country":"US",
    "sg:address":"2357 Glendon Ave",
    "sg:city":"Los Angeles",
    "sg:classifiers":[
        {
            "category":"Real Estate",
            "subcategory":"Architect",
            "type":"Services"
        }
    ],
    "sg:phone":"+1 310 470 1233",
    "sg:postcode":"90064",
    "sg:province":"CA",
    "wof:name":"R-2 Arch",
    "wof:placetype":"venue"
},
  "geometry": {"coordinates":[-118.428532,34.041886],"type":"Point"}
}