{
  "type": "Feature",
  "properties": {
    "iso:country":"US",
    "sg:address":"3261 N Harbor Blvd",
    "sg:city":"Fullerton",
    "sg:classifiers":[
        {
            "category":"Health Services",
            "subcategory":"Doctor",
            "type":"Services"
        }
    ],
    "sg:phone":"+1 714 870 9445",
    "sg:postcode":"92835",
    "sg:province":"CA",
    "sg:tags":[
        "dentist"
    ],
    "wof:name":"Larson & Larson",
    "wof:placetype":"venue"
},
  "geometry": {"coordinates":[-117.930336,33.907314],"type":"Point"}
}