{
  "type": "Feature",
  "properties": {
    "addr:full":"150 Forest St Boulder Creek CA 95006",
    "addr:housenumber":"150",
    "addr:postcode":"95006",
    "addr:street":"Forest St",
    "iso:country":"US",
    "sg:address":"150 Forest St",
    "sg:city":"Boulder Creek",
    "sg:classifiers":[
        {
            "category":"Shopping",
            "subcategory":"Computers & Home Electronics",
            "type":"Retail Goods"
        }
    ],
    "sg:phone":"+1 831 338 8009",
    "sg:postcode":"95006",
    "sg:province":"CA",
    "wof:name":"B C Computers",
    "wof:placetype":"venue"
},
  "geometry": {"coordinates":[-122.12133900000001,37.124027],"type":"Point"}
}