{
  "type": "Feature",
  "properties": {
    "addr:full":"225 S Civic Dr Palm Springs CA 92262",
    "addr:housenumber":"225",
    "addr:postcode":"92262",
    "addr:street":"S Civic Dr",
    "iso:country":"US",
    "sg:address":"225 S Civic Dr",
    "sg:city":"Palm Springs",
    "sg:classifiers":[
        {
            "category":"Professional",
            "subcategory":"Engineering",
            "type":"Services"
        }
    ],
    "sg:phone":"+1 760 323 1842",
    "sg:postcode":"92262",
    "sg:province":"CA",
    "sg:tags":[
        "engineer"
    ],
    "wof:name":"Fomotor Engineering",
    "wof:placetype":"venue"
},
  "geometry": {"coordinates":[-116.51267199999999,33.822682],"type":"Point"}
}