{
  "type": "Feature",
  "properties": {
    "addr:full":"1450 N. Tustin ave Suite 231 Santa Ana CA 92705",
    "addr:housenumber":"1450",
    "addr:postcode":"92705",
    "addr:street":"N. Tustin Ave Suite 231",
    "iso:country":"US",
    "sg:address":"1450 N. Tustin ave Suite 231",
    "sg:city":"Santa Ana",
    "sg:classifiers":[
        {
            "category":"Insurance",
            "subcategory":"Hazard Insurance",
            "type":"Services"
        }
    ],
    "sg:phone":"+1 714 569 9999",
    "sg:postcode":"92705",
    "sg:province":"CA",
    "sg:website":"jmillerinsurance.com",
    "wof:name":"Farmers Insurance",
    "wof:placetype":"venue"
},
  "geometry": {"coordinates":[-117.83486000000001,33.757635],"type":"Point"}
}