{
  "type": "Feature",
  "properties": {
    "addr:full":"612 W Main St El Centro CA 92243",
    "addr:housenumber":"612",
    "addr:postcode":"92243",
    "addr:street":"W Main St",
    "iso:country":"US",
    "sg:address":"612 W Main St",
    "sg:city":"El Centro",
    "sg:classifiers":[
        {
            "category":"Shopping",
            "subcategory":"Gifts & Souvenirs",
            "type":"Retail Goods"
        }
    ],
    "sg:phone":"+1 760 353 3641",
    "sg:postcode":"92243",
    "sg:province":"CA",
    "sg:tags":[
        "party",
        "supply"
    ],
    "wof:name":"Mr Pinata",
    "wof:placetype":"venue"
},
  "geometry": {"coordinates":[-115.55889500000001,32.792913],"type":"Point"}
}