{
  "type": "Feature",
  "properties": {
    "addr:full":"8961 Mira Mesa Blvd San Diego CA 92126",
    "addr:housenumber":"8961",
    "addr:postcode":"92126",
    "addr:street":"Mira Mesa Blvd",
    "iso:country":"US",
    "sg:address":"8961 Mira Mesa Blvd",
    "sg:city":"San Diego",
    "sg:classifiers":[
        {
            "category":"Personal",
            "subcategory":"Beauty Salon",
            "type":"Services"
        }
    ],
    "sg:phone":"+1 858 695 8765",
    "sg:postcode":"92126",
    "sg:province":"CA",
    "wof:name":"Jeannie's Salon",
    "wof:placetype":"venue"
},
  "geometry": {"coordinates":[-117.131615,32.914641],"type":"Point"}
}