{
  "type": "Feature",
  "properties": {
    "addr:full":"601 E Daily Dr Ste 228 Camarillo CA 93010",
    "addr:housenumber":"601",
    "addr:postcode":"93010",
    "addr:street":"E Daily Dr Ste 228",
    "iso:country":"US",
    "sg:address":"601 E Daily Dr Ste 228",
    "sg:city":"Camarillo",
    "sg:classifiers":[
        {
            "category":"Utilities",
            "type":"Services"
        }
    ],
    "sg:phone":"+1 805 383 1861",
    "sg:postcode":"93010",
    "sg:province":"CA",
    "sg:tags":[
        "provider",
        "internet"
    ],
    "sg:website":"www.dock.net",
    "wof:name":"Dock Net",
    "wof:placetype":"venue"
},
  "geometry": {"coordinates":[-119.062693,34.219216],"type":"Point"}
}