{
  "type": "Feature",
  "properties": {
    "iso:country":"US",
    "sg:address":"8571 N Lake Blvd",
    "sg:city":"Kings Beach",
    "sg:classifiers":[
        {
            "category":"Personal",
            "subcategory":"Massage",
            "type":"Services"
        }
    ],
    "sg:phone":"+1 530 546 3335",
    "sg:postcode":"96143",
    "sg:province":"CA",
    "sg:website":"www.rainbowdoorways.com",
    "wof:name":"Rainbow Doorways",
    "wof:placetype":"venue"
},
  "geometry": {"coordinates":[-120.02250600000001,39.236352],"type":"Point"}
}