{
  "type": "Feature",
  "properties": {
    "addr:full":"769 Morningside Dr Millbrae CA 94030",
    "addr:housenumber":"769",
    "addr:postcode":"94030",
    "addr:street":"Morningside Dr",
    "iso:country":"US",
    "sg:address":"769 Morningside Dr",
    "sg:city":"Millbrae",
    "sg:classifiers":[
        {
            "category":"Wholesale",
            "subcategory":"Drugs",
            "type":"Manufacturing & Wholesale Goods"
        }
    ],
    "sg:phone":"+1 650 697 5831",
    "sg:postcode":"94030",
    "sg:province":"CA",
    "sg:tags":[
        "equipment"
    ],
    "wof:name":"Genlee Corporation",
    "wof:placetype":"venue"
},
  "geometry": {"coordinates":[-122.406729,37.596893],"type":"Point"}
}