{
  "type": "Feature",
  "properties": {
    "iso:country":"US",
    "sg:address":"2815 Cam del Rio S",
    "sg:city":"San Diego",
    "sg:classifiers":[
        {
            "category":"Insurance",
            "subcategory":"Insurance Agent",
            "type":"Services"
        }
    ],
    "sg:phone":"+1 619 681 1111",
    "sg:postcode":"92108",
    "sg:province":"CA",
    "wof:name":"Western-Southern Life Ins Co",
    "wof:placetype":"venue"
},
  "geometry": {"coordinates":[-117.134848,32.770518],"type":"Point"}
}