{
  "type": "Feature",
  "properties": {
    "iso:country":"US",
    "sg:address":"24650 Calabasas Rd",
    "sg:city":"Calabasas",
    "sg:classifiers":[
        {
            "category":"Autos & Motor Vehicles",
            "subcategory":"Automobile Sales",
            "type":"Retail Goods"
        }
    ],
    "sg:phone":"+1 818 222 5555",
    "sg:postcode":"91302",
    "sg:province":"CA",
    "sg:tags":[
        "car",
        "dealer"
    ],
    "wof:name":"Acura 101 West",
    "wof:placetype":"venue"
},
  "geometry": {"coordinates":[-118.665865,34.148931],"type":"Point"}
}