{
  "type": "Feature",
  "properties": {
    "addr:full":"1501 Colorado Blvd. Los Angeles CA 90041",
    "addr:housenumber":"1501",
    "addr:postcode":"90041",
    "addr:street":"Colorado Blvd.",
    "iso:country":"US",
    "sg:address":"1501 Colorado Blvd.",
    "sg:city":"Los Angeles",
    "sg:classifiers":[
        {
            "category":"Health Services",
            "subcategory":"Health Practitioner",
            "type":"Services"
        }
    ],
    "sg:phone":"+1 323 244 1985",
    "sg:postcode":"90041",
    "sg:province":"CA",
    "sg:tags":[
        "acupuncture"
    ],
    "sg:website":"www.everacuwell.com",
    "wof:name":"Evergreen Wellness Center",
    "wof:placetype":"venue"
},
  "geometry": {"coordinates":[-118.19837099999999,34.139593],"type":"Point"}
}