{
  "type": "Feature",
  "properties": {
    "iso:country":"US",
    "sg:address":"1111 W 2nd St",
    "sg:city":"Pomona",
    "sg:classifiers":[
        {
            "category":"Manufacturing",
            "subcategory":"Metals",
            "type":"Manufacturing & Wholesale Goods"
        }
    ],
    "sg:phone":"+1 909 623 1295",
    "sg:postcode":"91766",
    "sg:province":"CA",
    "sg:tags":[
        "ornamental",
        "mfg",
        "work",
        "trade",
        "architectural",
        "contractor",
        "metalwork"
    ],
    "wof:name":"J V Ornamental Iron",
    "wof:placetype":"venue"
},
  "geometry": {"coordinates":[-117.76524000000001,34.057534],"type":"Point"}
}