{
  "type": "Feature",
  "properties": {
    "iso:country":"US",
    "sg:address":"3422 33rd Ave",
    "sg:city":"Sacramento",
    "sg:classifiers":[
        {
            "category":"Retail",
            "subcategory":"Repair Shop",
            "type":"Services"
        }
    ],
    "sg:phone":"+1 916 427 3371",
    "sg:postcode":"95824",
    "sg:province":"CA",
    "sg:tags":[
        "upholsterer"
    ],
    "wof:name":"Universal Upholstery",
    "wof:placetype":"venue"
},
  "geometry": {"coordinates":[-121.470141,38.522351],"type":"Point"}
}