{
  "type": "Feature",
  "properties": {
    "iso:country":"US",
    "sg:address":"27868 Wakefield Rd",
    "sg:city":"Castaic",
    "sg:classifiers":[
        {
            "category":"Professional",
            "type":"Services"
        }
    ],
    "sg:phone":"+1 661 257 2526",
    "sg:postcode":"91384",
    "sg:province":"CA",
    "wof:name":"Cook C&S",
    "wof:placetype":"venue"
},
  "geometry": {"coordinates":[-118.622663,34.452476],"type":"Point"}
}