{
  "type": "Feature",
  "properties": {
    "iso:country":"US",
    "sg:address":"347 N Stimson Ave",
    "sg:city":"La Puente",
    "sg:classifiers":[
        {
            "category":"Freight",
            "type":"Transportation"
        }
    ],
    "sg:phone":"+1 626 855 0761",
    "sg:postcode":"91744",
    "sg:province":"CA",
    "sg:tags":[
        "shipping"
    ],
    "wof:name":"American Bus Logistics LLC",
    "wof:placetype":"venue"
},
  "geometry": {"coordinates":[-117.949078,34.024178],"type":"Point"}
}