{
  "type": "Feature",
  "properties": {
    "addr:full":"18188 Valladares Dr San Diego CA 92127",
    "addr:housenumber":"18188",
    "addr:postcode":"92127",
    "addr:street":"Valladares Dr",
    "iso:country":"US",
    "sg:address":"18188 Valladares Dr",
    "sg:city":"San Diego",
    "sg:classifiers":[
        {
            "category":"Food & Beverages",
            "subcategory":"Bakery",
            "type":"Retail Goods"
        }
    ],
    "sg:phone":"+1 858 487 4868",
    "sg:postcode":"92127",
    "sg:province":"CA",
    "wof:name":"Noras Pastries",
    "wof:placetype":"venue"
},
  "geometry": {"coordinates":[-117.07632700000001,33.039594],"type":"Point"}
}