{
  "type": "Feature",
  "properties": {
    "iso:country":"US",
    "sg:address":"2010 N Imperial Ave",
    "sg:city":"El Centro",
    "sg:classifiers":[
        {
            "category":"Autos & Motor Vehicles",
            "subcategory":"Auto Supplies",
            "type":"Retail Goods"
        }
    ],
    "sg:phone":"+1 760 353 5519",
    "sg:postcode":"92231",
    "sg:province":"CA",
    "sg:tags":[
        "tire"
    ],
    "wof:name":"America's Tire Co",
    "wof:placetype":"venue"
},
  "geometry": {"coordinates":[-115.56997,32.816601],"type":"Point"}
}