{
  "type": "Feature",
  "properties": {
    "addr:full":"930 S Mount Vernon Ave Colton CA 92324",
    "addr:housenumber":"930",
    "addr:postcode":"92324",
    "addr:street":"S Mount Vernon Ave",
    "iso:country":"US",
    "sg:address":"930 S Mount Vernon Ave",
    "sg:city":"Colton",
    "sg:classifiers":[
        {
            "category":"Manufacturing",
            "subcategory":"Printing",
            "type":"Manufacturing & Wholesale Goods"
        }
    ],
    "sg:phone":"+1 909 370 0860",
    "sg:postcode":"92324",
    "sg:province":"CA",
    "sg:tags":[
        "printer"
    ],
    "wof:name":"Minuteman Press",
    "wof:placetype":"venue"
},
  "geometry": {"coordinates":[-117.30918,34.056992],"type":"Point"}
}