{
  "type": "Feature",
  "properties": {
    "iso:country":"US",
    "sg:address":"1800 E Garry Ave Ste 107",
    "sg:city":"Santa Ana",
    "sg:classifiers":[
        {
            "category":"Parking",
            "type":"Transportation"
        }
    ],
    "sg:phone":"+1 949 223 8707",
    "sg:postcode":"92705",
    "sg:province":"CA",
    "wof:name":"Pps Parking Inc",
    "wof:placetype":"venue"
},
  "geometry": {"coordinates":[-117.852997,33.705002],"type":"Point"}
}