{
  "type": "Feature",
  "properties": {
    "addr:full":"3220 Stevens Creek Blvd San Jose CA 95128",
    "addr:housenumber":"3220",
    "addr:postcode":"95128",
    "addr:street":"Stevens Creek Blvd",
    "iso:country":"US",
    "sg:address":"3220 Stevens Creek Blvd",
    "sg:city":"San Jose",
    "sg:classifiers":[
        {
            "category":"Wholesale",
            "subcategory":"Motor Vehicles",
            "type":"Manufacturing & Wholesale Goods"
        }
    ],
    "sg:phone":"+1 408 985 4151",
    "sg:postcode":"95128",
    "sg:province":"CA",
    "wof:name":"Bay Area Auto Center",
    "wof:placetype":"venue"
},
  "geometry": {"coordinates":[-121.954031,37.323124],"type":"Point"}
}