{
  "type": "Feature",
  "properties": {
    "addr:full":"453 Buena Vista Ave Alameda CA 94501",
    "addr:housenumber":"453",
    "addr:postcode":"94501",
    "addr:street":"Buena Vista Ave",
    "iso:country":"US",
    "sg:address":"453 Buena Vista Ave",
    "sg:city":"Alameda",
    "sg:classifiers":[
        {
            "category":"Insurance",
            "subcategory":"Insurance Agent",
            "type":"Services"
        }
    ],
    "sg:phone":"+1 510 337 0229",
    "sg:postcode":"94501",
    "sg:province":"CA",
    "wof:name":"Saleem Insurance",
    "wof:placetype":"venue"
},
  "geometry": {"coordinates":[-122.284209,37.77738],"type":"Point"}
}