{
  "type": "Feature",
  "properties": {
    "addr:full":"1260 Countess Dr Corona CA 92882",
    "addr:housenumber":"1260",
    "addr:postcode":"92882",
    "addr:street":"Countess Dr",
    "iso:country":"US",
    "sg:address":"1260 Countess Dr",
    "sg:city":"Corona",
    "sg:classifiers":[
        {
            "category":"Real Estate",
            "subcategory":"Architect",
            "type":"Services"
        }
    ],
    "sg:phone":"+1 951 739 0700",
    "sg:postcode":"92882",
    "sg:province":"CA",
    "sg:tags":[
        "illustrator",
        "architectural"
    ],
    "wof:name":"Design Concepts",
    "wof:placetype":"venue"
},
  "geometry": {"coordinates":[-117.592364,33.845998],"type":"Point"}
}