{
  "type": "Feature",
  "properties": {
    "addr:full":"16167 Johnson Ave Kingsburg CA 93631",
    "addr:housenumber":"16167",
    "addr:postcode":"93631",
    "addr:street":"Johnson Ave",
    "iso:country":"US",
    "sg:address":"16167 Johnson Ave",
    "sg:city":"Kingsburg",
    "sg:classifiers":[
        {
            "category":"Farming",
            "subcategory":"Crops",
            "type":"Manufacturing & Wholesale Goods"
        }
    ],
    "sg:phone":"+1 559 897 1952",
    "sg:postcode":"93631",
    "sg:province":"CA",
    "sg:tags":[
        "farm"
    ],
    "wof:name":"Hector Perez",
    "wof:placetype":"venue"
},
  "geometry": {"coordinates":[-119.498075,36.550265],"type":"Point"}
}