{
  "type": "Feature",
  "properties": {
    "iso:country":"US",
    "sg:address":"236 N Encinitas Ave",
    "sg:city":"Monrovia",
    "sg:classifiers":[
        {
            "category":"Building & Trades",
            "subcategory":"Electrical",
            "type":"Services"
        }
    ],
    "sg:phone":"+1 626 301 0170",
    "sg:postcode":"91016",
    "sg:province":"CA",
    "sg:tags":[
        "electrician"
    ],
    "wof:name":"Joseph Storey Electrical Contracting",
    "wof:placetype":"venue"
},
  "geometry": {"coordinates":[-117.999959,34.155237],"type":"Point"}
}