{
  "type": "Feature",
  "properties": {
    "addr:full":"804 San Pasqual St San Diego CA 92113",
    "addr:housenumber":"804",
    "addr:postcode":"92113",
    "addr:street":"San Pasqual St",
    "iso:country":"US",
    "sg:address":"804 San Pasqual St",
    "sg:city":"San Diego",
    "sg:classifiers":[
        {
            "category":"Social Services",
            "subcategory":"Child Care",
            "type":"Services"
        }
    ],
    "sg:phone":"+1 619 262 1905",
    "sg:postcode":"92113",
    "sg:province":"CA",
    "wof:name":"First Step Head Start",
    "wof:placetype":"venue"
},
  "geometry": {"coordinates":[-117.103133,32.697367],"type":"Point"}
}