{
  "type": "Feature",
  "properties": {
    "iso:country":"US",
    "sg:address":"1000 Wilshire Blvd",
    "sg:city":"Los Angeles",
    "sg:classifiers":[
        {
            "category":"Professional",
            "subcategory":"Lawyer & Legal Services",
            "type":"Services"
        }
    ],
    "sg:phone":"+1 213 630 2640",
    "sg:postcode":"90017",
    "sg:province":"CA",
    "wof:name":"Faal Edi M O Law Offices of Atty",
    "wof:placetype":"venue"
},
  "geometry": {"coordinates":[-118.261002,34.0508],"type":"Point"}
}