{
  "type": "Feature",
  "properties": {
    "addr:full":"5050 Cohasset Rd Ste 61 Chico CA 95973",
    "addr:housenumber":"5050",
    "addr:postcode":"95973",
    "addr:street":"Cohasset Rd Ste 61",
    "iso:country":"US",
    "sg:address":"5050 Cohasset Rd Ste 61",
    "sg:city":"Chico",
    "sg:classifiers":[
        {
            "category":"Retail",
            "subcategory":"Auto Repair",
            "type":"Services"
        }
    ],
    "sg:phone":"+1 530 521 5199",
    "sg:postcode":"95973",
    "sg:province":"CA",
    "sg:tags":[
        "scooters-repairing",
        "motorcycle",
        "motor"
    ],
    "wof:name":"J T Cyclery",
    "wof:placetype":"venue"
},
  "geometry": {"coordinates":[-121.846542,39.797793],"type":"Point"}
}