{
  "type": "Feature",
  "properties": {
    "iso:country":"US",
    "sg:address":"12261 Airline Hwy",
    "sg:city":"Paicines",
    "sg:classifiers":[
        {
            "category":"Shopping",
            "subcategory":"Discount & Variety Stores",
            "type":"Retail Goods"
        }
    ],
    "sg:phone":"+1 831 628 3293",
    "sg:postcode":"95043",
    "sg:province":"CA",
    "wof:name":"Paicines General Store",
    "wof:placetype":"venue"
},
  "geometry": {"coordinates":[-121.278844,36.729386],"type":"Point"}
}