{
  "type": "Feature",
  "properties": {
    "addr:full":"12261 Airline Hwy Paicines CA 95043",
    "addr:housenumber":"12261",
    "addr:postcode":"paicines ca 95043",
    "addr:street":"Airline Hwy",
    "iso:country":"US",
    "sg:address":"12261 Airline Hwy",
    "sg:city":"Paicines",
    "sg:classifiers":[
        {
            "category":"Shopping",
            "subcategory":"Discount & Variety Stores",
            "type":"Retail Goods"
        }
    ],
    "sg:phone":"+1 831 628 3293",
    "sg:postcode":"95043",
    "sg:province":"CA",
    "wof:name":"Paicines General Store",
    "wof:placetype":"venue"
},
  "geometry": {"coordinates":[-121.27884400000001,36.729386],"type":"Point"}
}