{
  "type": "Feature",
  "properties": {
    "addr:full":"4743 la Puma Ct Camarillo CA 93012",
    "addr:housenumber":"4743",
    "addr:postcode":"93012",
    "addr:street":"La Puma Ct",
    "iso:country":"US",
    "sg:address":"4743 la Puma Ct",
    "sg:city":"Camarillo",
    "sg:classifiers":[
        {
            "category":"Home & Garden",
            "subcategory":"Building Materials",
            "type":"Retail Goods"
        }
    ],
    "sg:phone":"+1 818 631 7515",
    "sg:postcode":"93012",
    "sg:province":"CA",
    "sg:tags":[
        "top",
        "counter"
    ],
    "wof:name":"Olympian Marble And Granite",
    "wof:placetype":"venue"
},
  "geometry": {"coordinates":[-119.00952100000001,34.237672],"type":"Point"}
}