{
  "type": "Feature",
  "properties": {
    "iso:country":"US",
    "sg:address":"855 Rorke Way",
    "sg:city":"Palo Alto",
    "sg:classifiers":[
        {
            "category":"Insurance",
            "subcategory":"Insurance Agent",
            "type":"Services"
        }
    ],
    "sg:phone":"+1 650 494 8533",
    "sg:postcode":"94303",
    "sg:province":"CA",
    "sg:tags":[
        "broker"
    ],
    "wof:name":"James E Hannon",
    "wof:placetype":"venue"
},
  "geometry": {"coordinates":[-122.114586,37.429308],"type":"Point"}
}