{
  "type": "Feature",
  "properties": {
    "addr:full":"2025 Morse Ave Sacramento CA 95825",
    "addr:housenumber":"2025",
    "addr:postcode":"95825",
    "addr:street":"Morse Ave",
    "iso:country":"US",
    "sg:address":"2025 Morse Ave",
    "sg:city":"Sacramento",
    "sg:classifiers":[
        {
            "category":"Health Services",
            "subcategory":"Doctor",
            "type":"Services"
        }
    ],
    "sg:phone":"+1 916 973 7521",
    "sg:postcode":"95825",
    "sg:province":"CA",
    "sg:tags":[
        "physician",
        "surgeon"
    ],
    "wof:name":"Gerald Brody MD",
    "wof:placetype":"venue"
},
  "geometry": {"coordinates":[-121.392279,38.601102],"type":"Point"}
}