{
  "type": "Feature",
  "properties": {
    "iso:country":"US",
    "sg:address":"1147 High St",
    "sg:city":"Auburn",
    "sg:classifiers":[
        {
            "category":"Professional",
            "subcategory":"Business Services",
            "type":"Services"
        }
    ],
    "sg:phone":"+1 530 885 9818",
    "sg:postcode":"95603",
    "sg:province":"CA",
    "sg:tags":[
        "paralegal"
    ],
    "wof:name":"Assisted Divorce & Family Law",
    "wof:placetype":"venue"
},
  "geometry": {"coordinates":[-121.071705,38.896907],"type":"Point"}
}