{
  "type": "Feature",
  "properties": {
    "addr:full":"5054 Newport Ave San Diego CA 92107",
    "addr:housenumber":"5054",
    "addr:postcode":"92107",
    "addr:street":"Newport Ave",
    "iso:country":"US",
    "sg:address":"5054 Newport Ave",
    "sg:city":"San Diego",
    "sg:classifiers":[
        {
            "category":"Shopping",
            "subcategory":"Clothing, Apparel, & Fashions",
            "type":"Retail Goods"
        },
        {
            "category":"Shopping",
            "subcategory":"Shoes",
            "type":"Retail Goods"
        }
    ],
    "sg:phone":"+1 619 223 4836",
    "sg:postcode":"92107",
    "sg:province":"CA",
    "sg:tags":[
        "accessory",
        "clothing",
        "store",
        "women's"
    ],
    "wof:name":"Dreamgirls",
    "wof:placetype":"venue"
},
  "geometry": {"coordinates":[-117.25177600000001,32.74769],"type":"Point"}
}