{
  "type": "Feature",
  "properties": {
    "iso:country":"US",
    "sg:address":"1055 N Orange St",
    "sg:city":"Orange",
    "sg:classifiers":[
        {
            "category":"Social Services",
            "subcategory":"Child Care",
            "type":"Services"
        }
    ],
    "sg:phone":"+1 714 633 3643",
    "sg:postcode":"92867",
    "sg:province":"CA",
    "sg:tags":[
        "day"
    ],
    "wof:name":"Kim's Daycare",
    "wof:placetype":"venue"
},
  "geometry": {"coordinates":[-117.851997,33.805302],"type":"Point"}
}