{
  "type": "Feature",
  "properties": {
    "iso:country":"US",
    "sg:address":"711 Western Ave",
    "sg:city":"Petaluma",
    "sg:classifiers":[
        {
            "category":"Professional",
            "subcategory":"Computer Services",
            "type":"Services"
        }
    ],
    "sg:phone":"+1 707 778 8721",
    "sg:postcode":"94952",
    "sg:province":"CA",
    "sg:website":"www.callcsa.com",
    "wof:name":"CSA Inc",
    "wof:placetype":"venue"
},
  "geometry": {"coordinates":[-122.648352,38.231365],"type":"Point"}
}