{
  "type": "Feature",
  "properties": {
    "addr:full":"4001 Judah St San Francisco CA 94122",
    "addr:housenumber":"4001",
    "addr:postcode":"94122",
    "addr:street":"Judah St",
    "iso:country":"US",
    "sg:address":"4001 Judah St",
    "sg:city":"San Francisco",
    "sg:classifiers":[
        {
            "category":"Restaurant",
            "type":"Food & Drink"
        }
    ],
    "sg:phone":"+1 415 504 7325",
    "sg:postcode":"94122",
    "sg:province":"CA",
    "wof:name":"Feel Real Organically Vegan",
    "wof:placetype":"venue"
},
  "geometry": {"coordinates":[-122.505928,37.760424],"type":"Point"}
}