{
  "type": "Feature",
  "properties": {
    "addr:full":"2318 16th St Sacramento CA 95818",
    "addr:housenumber":"2318",
    "addr:postcode":"95818",
    "addr:street":"16Th St",
    "iso:country":"US",
    "sg:address":"2318 16th St",
    "sg:city":"Sacramento",
    "sg:classifiers":[
        {
            "category":"Freight",
            "type":"Transportation"
        }
    ],
    "sg:phone":"+1 916 442 3231",
    "sg:postcode":"95818",
    "sg:province":"CA",
    "sg:tags":[
        "storage",
        "self",
        "commercial",
        "household"
    ],
    "sg:website":"http://www.reevesmgt.com",
    "wof:name":"Downtown Mini Storage",
    "wof:placetype":"venue"
},
  "geometry": {"coordinates":[-121.491997,38.563801],"type":"Point"}
}