{
  "type": "Feature",
  "properties": {
    "iso:country":"US",
    "sg:address":"1901 Olympic Blvd",
    "sg:city":"Walnut Creek",
    "sg:classifiers":[
        {
            "category":"Banks & Credit Unions",
            "subcategory":"Bank",
            "type":"Services"
        }
    ],
    "sg:phone":"+1 925 945 6112",
    "sg:postcode":"94595",
    "sg:province":"CA",
    "sg:tags":[
        "loan",
        "real estate"
    ],
    "sg:website":"www.dfgwc.com",
    "wof:name":"Diablo Funding Group",
    "wof:placetype":"venue"
},
  "geometry": {"coordinates":[-122.062819,37.895979],"type":"Point"}
}