{
  "type": "Feature",
  "properties": {
    "iso:country":"US",
    "sg:address":"1135 Pine St",
    "sg:city":"Redding",
    "sg:classifiers":[
        {
            "category":"Organizations",
            "subcategory":"Membership Organization",
            "type":"Services"
        }
    ],
    "sg:phone":"+1 530 229 9326",
    "sg:postcode":"96001",
    "sg:province":"CA",
    "wof:name":"Bagley Jean Reading Specialist",
    "wof:placetype":"venue"
},
  "geometry": {"coordinates":[-122.391314,40.588929],"type":"Point"}
}