{
  "type": "Feature",
  "properties": {
    "addr:full":"17291 Irvine Blvd Ste 208 Tustin CA 92780",
    "addr:housenumber":"17291",
    "addr:postcode":"92780",
    "addr:street":"Irvine Blvd Ste 208",
    "iso:country":"US",
    "sg:address":"17291 Irvine Blvd Ste 208",
    "sg:city":"Tustin",
    "sg:classifiers":[
        {
            "category":"Taxi",
            "type":"Transportation"
        },
        {
            "category":"Professional",
            "subcategory":"Business Services",
            "type":"Services"
        }
    ],
    "sg:phone":"+1 714 505 3030",
    "sg:postcode":"92780",
    "sg:province":"CA",
    "sg:tags":[
        "delivery",
        "messenger",
        "courier"
    ],
    "wof:name":"New Port Business Courier Service Inc",
    "wof:placetype":"venue"
},
  "geometry": {"coordinates":[-117.83000199999999,33.748299],"type":"Point"}
}