{
  "type": "Feature",
  "properties": {
    "iso:country":"US",
    "sg:address":"12926 Ave 336",
    "sg:city":"Visalia",
    "sg:classifiers":[
        {
            "category":"Building & Trades",
            "subcategory":"Construction",
            "type":"Services"
        }
    ],
    "sg:phone":"+1 559 635 8632",
    "sg:postcode":"93292",
    "sg:province":"CA",
    "sg:tags":[
        "carpentry",
        "contractor"
    ],
    "wof:name":"New Venture Cabinet Co",
    "wof:placetype":"venue"
},
  "geometry": {"coordinates":[-119.28471399999999,36.39978],"type":"Point"}
}