{
  "type": "Feature",
  "properties": {
    "iso:country":"US",
    "sg:address":"1148 Boxelder Cir",
    "sg:city":"Folsom",
    "sg:classifiers":[
        {
            "category":"Professional",
            "subcategory":"Art Services",
            "type":"Services"
        }
    ],
    "sg:phone":"+1 916 984 0422",
    "sg:postcode":"95630",
    "sg:province":"CA",
    "sg:tags":[
        "interior",
        "designer",
        "decorator"
    ],
    "wof:name":"Morris Kl Designs",
    "wof:placetype":"venue"
},
  "geometry": {"coordinates":[-121.13108800000001,38.677566],"type":"Point"}
}