{
  "type": "Feature",
  "properties": {
    "iso:country":"US",
    "sg:address":"355 Freeman Ave",
    "sg:city":"Long Beach",
    "sg:classifiers":[
        {
            "category":"Communications",
            "subcategory":"News Services",
            "type":"Services"
        }
    ],
    "sg:phone":"+1 562 438 5648",
    "sg:postcode":"90814",
    "sg:province":"CA",
    "sg:tags":[
        "conservation",
        "art"
    ],
    "wof:name":"Art Conservation Services",
    "wof:placetype":"venue"
},
  "geometry": {"coordinates":[-118.155747,33.770705],"type":"Point"}
}