{
  "type": "Feature",
  "properties": {
    "iso:country":"US",
    "sg:address":"13437 Leffingwell Rd",
    "sg:city":"Whittier",
    "sg:classifiers":[
        {
            "category":"Professional",
            "subcategory":"Engineering",
            "type":"Services"
        }
    ],
    "sg:phone":"+1 562 944 8280",
    "sg:postcode":"90605",
    "sg:province":"CA",
    "sg:tags":[
        "engineer"
    ],
    "wof:name":"Taylor Engineering",
    "wof:placetype":"venue"
},
  "geometry": {"coordinates":[-118.044391,33.919309],"type":"Point"}
}