{
  "type": "Feature",
  "properties": {
    "iso:country":"US",
    "sg:address":"12777 Valley View St Ste 252",
    "sg:city":"Garden Grove",
    "sg:classifiers":[
        {
            "category":"Health Services",
            "subcategory":"Doctor",
            "type":"Services"
        }
    ],
    "sg:phone":"+1 714 799 2888",
    "sg:postcode":"92845",
    "sg:province":"CA",
    "sg:tags":[
        "surgeon",
        "oral"
    ],
    "wof:name":"Lies John M DDS",
    "wof:placetype":"venue"
},
  "geometry": {"coordinates":[-118.035004,33.777401],"type":"Point"}
}