{
  "type": "Feature",
  "properties": {
    "addr:full":"16631 Indian Flat Rd Nevada City CA 95959",
    "addr:housenumber":"16631",
    "addr:postcode":"95959",
    "addr:street":"Indian Flat Rd",
    "iso:country":"US",
    "sg:address":"16631 Indian Flat Rd",
    "sg:city":"Nevada City",
    "sg:classifiers":[
        {
            "category":"Professional",
            "subcategory":"Business Services",
            "type":"Services"
        }
    ],
    "sg:phone":"+1 530 265 3131",
    "sg:postcode":"95959",
    "sg:province":"CA",
    "sg:tags":[
        "transcribing",
        "disc"
    ],
    "wof:name":"Med Office Support Svc",
    "wof:placetype":"venue"
},
  "geometry": {"coordinates":[-121.047004,39.269423],"type":"Point"}
}