{
  "type": "Feature",
  "properties": {
    "iso:country":"US",
    "sg:address":"4958 Hidden Dune Ct",
    "sg:city":"San Diego",
    "sg:classifiers":[
        {
            "category":"Professional",
            "subcategory":"Management & Consulting",
            "type":"Services"
        }
    ],
    "sg:phone":"+1 858 481 1984",
    "sg:postcode":"92130",
    "sg:province":"CA",
    "sg:tags":[
        "consultant",
        "business"
    ],
    "wof:name":"Carmel Valley Group",
    "wof:placetype":"venue"
},
  "geometry": {"coordinates":[-117.209272,32.951906],"type":"Point"}
}