{
  "type": "Feature",
  "properties": {
    "addr:full":"27349 Jefferson Ave Temecula CA 92562",
    "addr:housenumber":"27349",
    "addr:postcode":"92562",
    "addr:street":"Jefferson Ave",
    "iso:country":"US",
    "sg:address":"27349 Jefferson Ave",
    "sg:city":"Temecula",
    "sg:classifiers":[
        {
            "category":"Professional",
            "subcategory":"Lawyer & Legal Services",
            "type":"Services"
        }
    ],
    "sg:phone":"+1 951 719 1371",
    "sg:postcode":"92562",
    "sg:province":"CA",
    "sg:tags":[
        "attorney"
    ],
    "wof:name":"Stephen Anderson Atty At Law",
    "wof:placetype":"venue"
},
  "geometry": {"coordinates":[-117.16718,33.52304],"type":"Point"}
}