{
  "type": "Feature",
  "properties": {
    "iso:country":"US",
    "sg:address":"131 S Spring St",
    "sg:city":"Blythe",
    "sg:classifiers":[
        {
            "category":"Shopping",
            "subcategory":"Used Merchandise",
            "type":"Retail Goods"
        }
    ],
    "sg:phone":"+1 760 922 9327",
    "sg:postcode":"92225",
    "sg:province":"CA",
    "sg:tags":[
        "shop",
        "thrift"
    ],
    "wof:name":"Sheltering Wings Thrift Store",
    "wof:placetype":"venue"
},
  "geometry": {"coordinates":[-114.598282,33.609751],"type":"Point"}
}