{
  "type": "Feature",
  "properties": {
    "addr:full":"3101 I St #202 Sacramento CA 95816",
    "addr:housenumber":"3101;202",
    "addr:postcode":"95816",
    "addr:street":"I St #",
    "iso:country":"US",
    "sg:address":"3101 I St #202",
    "sg:city":"Sacramento",
    "sg:classifiers":[
        {
            "category":"Personal",
            "subcategory":"Massage",
            "type":"Services"
        },
        {
            "category":"Health Services",
            "subcategory":"Clinic",
            "type":"Services"
        },
        {
            "category":"Health Services",
            "subcategory":"Health Practitioner",
            "type":"Services"
        }
    ],
    "sg:phone":"+1 916 447 4329",
    "sg:postcode":"95816",
    "sg:province":"CA",
    "sg:tags":[
        "medicine",
        "medical",
        "therapist",
        "alternative"
    ],
    "sg:website":"sacramentorolfing.com",
    "wof:name":"Robert Robinson",
    "wof:placetype":"venue"
},
  "geometry": {"coordinates":[-121.46427799999999,38.574381],"type":"Point"}
}