{
  "type": "Feature",
  "properties": {
    "addr:full":"6th & Manhattan Pl Los Angeles CA 90001",
    "addr:postcode":"90001",
    "addr:street":"Pl",
    "iso:country":"US",
    "sg:address":"6th & Manhattan Pl",
    "sg:city":"Los Angeles",
    "sg:classifiers":[
        {
            "category":"Autos & Motor Vehicles",
            "subcategory":"Fuel & Gas Station",
            "type":"Retail Goods"
        }
    ],
    "sg:phone":"+1 213 383 8397",
    "sg:postcode":"90001",
    "sg:province":"CA",
    "wof:name":"Unocal Dlrs Service Stns",
    "wof:placetype":"venue"
},
  "geometry": {"coordinates":[-118.24900100000001,33.9748],"type":"Point"}
}