{
  "type": "Feature",
  "properties": {
    "addr:full":"13700 Yale Ct Fontana CA 92336",
    "addr:housenumber":"13700",
    "addr:postcode":"92336",
    "addr:street":"Yale Ct",
    "iso:country":"US",
    "sg:address":"13700 Yale Ct",
    "sg:city":"Fontana",
    "sg:classifiers":[
        {
            "category":"Building & Trades",
            "subcategory":"Landscaping Services",
            "type":"Services"
        }
    ],
    "sg:phone":"+1 909 899 0159",
    "sg:postcode":"92336",
    "sg:province":"CA",
    "sg:tags":[
        "landscape",
        "contractor"
    ],
    "wof:name":"Vaughan Landscaping",
    "wof:placetype":"venue"
},
  "geometry": {"coordinates":[-117.50221999999999,34.117451],"type":"Point"}
}