{
  "type": "Feature",
  "properties": {
    "addr:full":"401 N La Cienega Blvd West Hollywood CA 90048",
    "addr:housenumber":"401",
    "addr:postcode":"90048",
    "addr:street":"N La Cienega Blvd",
    "iso:country":"US",
    "sg:address":"401 N La Cienega Blvd",
    "sg:city":"West Hollywood",
    "sg:classifiers":[
        {
            "category":"Restaurant",
            "type":"Food & Drink"
        }
    ],
    "sg:phone":"+1 310 659 7708",
    "sg:postcode":"90048",
    "sg:province":"CA",
    "sg:tags":[
        "french"
    ],
    "sg:website":"www.sonarestaurant.com",
    "wof:name":"Sona Restaurant",
    "wof:placetype":"venue"
},
  "geometry": {"coordinates":[-118.37657299999999,34.078518],"type":"Point"}
}