{
  "type": "Feature",
  "properties": {
    "iso:country":"US",
    "sg:address":"41036 Big Bear Blvd",
    "sg:city":"Big Bear Lake",
    "sg:classifiers":[
        {
            "category":"Retail",
            "subcategory":"Auto Rental",
            "type":"Services"
        }
    ],
    "sg:phone":"+1 909 866 1156",
    "sg:postcode":"92315",
    "sg:province":"CA",
    "sg:tags":[
        "renting",
        "automobile"
    ],
    "wof:name":"Enterprise Rent-A-Car",
    "wof:placetype":"venue"
},
  "geometry": {"coordinates":[-116.90676999999999,34.243549],"type":"Point"}
}