{
  "type": "Feature",
  "properties": {
    "iso:country":"US",
    "sg:address":"3505 Cam del Rio S",
    "sg:city":"San Diego",
    "sg:classifiers":[
        {
            "category":"Insurance",
            "subcategory":"Insurance Agent",
            "type":"Services"
        }
    ],
    "sg:phone":"+1 619 284 8271",
    "sg:postcode":"92108",
    "sg:province":"CA",
    "wof:name":"Barrigan Agency",
    "wof:placetype":"venue"
},
  "geometry": {"coordinates":[-117.11765,32.777804],"type":"Point"}
}