{
  "type": "Feature",
  "properties": {
    "addr:full":"41890 Enterprise Cir S Temecula CA 92590",
    "addr:housenumber":"41890",
    "addr:postcode":"92590",
    "addr:street":"Enterprise Cir S",
    "iso:country":"US",
    "sg:address":"41890 Enterprise Cir S",
    "sg:city":"Temecula",
    "sg:classifiers":[
        {
            "category":"Travel",
            "subcategory":"Travel Agent",
            "type":"Entertainment"
        }
    ],
    "sg:phone":"+1 951 296 2838",
    "sg:postcode":"92590",
    "sg:province":"CA",
    "sg:tags":[
        "agency",
        "bureau"
    ],
    "wof:name":"Cruiseshipcenters",
    "wof:placetype":"venue"
},
  "geometry": {"coordinates":[-117.16760499999999,33.516382],"type":"Point"}
}