{
  "type": "Feature",
  "properties": {
    "iso:country":"US",
    "sg:address":"8864 Frontier St",
    "sg:city":"Hanford",
    "sg:classifiers":[
        {
            "category":"Farming",
            "subcategory":"Farm",
            "type":"Manufacturing & Wholesale Goods"
        }
    ],
    "sg:phone":"+1 559 582 9653",
    "sg:postcode":"93230",
    "sg:province":"CA",
    "sg:tags":[
        "crop",
        "general"
    ],
    "wof:name":"David Noland",
    "wof:placetype":"venue"
},
  "geometry": {"coordinates":[-119.705462,36.345076],"type":"Point"}
}