{
  "type": "Feature",
  "properties": {
    "addr:full":"420 E Los Angeles Ave Moorpark CA 93021",
    "addr:housenumber":"420",
    "addr:postcode":"ca 93021",
    "addr:street":"E Los Angeles Ave",
    "iso:country":"US",
    "sg:address":"420 E Los Angeles Ave",
    "sg:city":"Moorpark",
    "sg:classifiers":[
        {
            "category":"Personal",
            "subcategory":"Beauty Salon",
            "type":"Services"
        }
    ],
    "sg:phone":"+1 805 529 4775",
    "sg:postcode":"93021",
    "sg:province":"CA",
    "wof:name":"Fantasy Hair & Nails",
    "wof:placetype":"venue"
},
  "geometry": {"coordinates":[-118.838869,34.292527],"type":"Point"}
}