{
  "type": "Feature",
  "properties": {
    "addr:full":"9672 Central Ave Montclair CA 91763",
    "addr:housenumber":"9672",
    "addr:postcode":"91763",
    "addr:street":"Central Ave",
    "iso:country":"US",
    "sg:address":"9672 Central Ave",
    "sg:city":"Montclair",
    "sg:classifiers":[
        {
            "category":"Shopping",
            "type":"Retail Goods"
        }
    ],
    "sg:phone":"+1 909 445 1092",
    "sg:postcode":"91763",
    "sg:province":"CA",
    "sg:tags":[
        "telephone",
        "cellular"
    ],
    "wof:name":"Casas Telcel",
    "wof:placetype":"venue"
},
  "geometry": {"coordinates":[-117.689627,34.0809],"type":"Point"}
}