{
  "type": "Feature",
  "properties": {
    "addr:full":"505 Grand Ave Arroyo Grande CA 93420",
    "addr:housenumber":"505",
    "addr:postcode":"93420",
    "addr:street":"Grand Ave",
    "iso:country":"US",
    "sg:address":"505 Grand Ave",
    "sg:city":"Arroyo Grande",
    "sg:classifiers":[
        {
            "category":"Autos & Motor Vehicles",
            "subcategory":"Auto Supplies",
            "type":"Retail Goods"
        }
    ],
    "sg:phone":"+1 805 489 5566",
    "sg:postcode":"93420",
    "sg:province":"CA",
    "sg:tags":[
        "tire"
    ],
    "wof:name":"Wayne's Tire Inc",
    "wof:placetype":"venue"
},
  "geometry": {"coordinates":[-120.587182,35.120085],"type":"Point"}
}