{
  "type": "Feature",
  "properties": {
    "iso:country":"US",
    "sg:address":"2923 Carmel Way",
    "sg:city":"Fairfield",
    "sg:classifiers":[
        {
            "category":"Travel",
            "subcategory":"Travel Agent",
            "type":"Entertainment"
        }
    ],
    "sg:phone":"+1 707 425 8157",
    "sg:postcode":"94534",
    "sg:province":"CA",
    "sg:tags":[
        "agency"
    ],
    "wof:name":"Your Travel Source",
    "wof:placetype":"venue"
},
  "geometry": {"coordinates":[-122.065543,38.271194],"type":"Point"}
}