{
  "type": "Feature",
  "properties": {
    "addr:full":"4954 Van Nuys Blvd Ste 106 Sherman Oaks CA 91403",
    "addr:housenumber":"4954",
    "addr:postcode":"91403",
    "addr:street":"Van Nuys Blvd Ste 106",
    "iso:country":"US",
    "sg:address":"4954 Van Nuys Blvd Ste 106",
    "sg:city":"Sherman Oaks",
    "sg:classifiers":[
        {
            "category":"Personal",
            "subcategory":"Beauty Salon",
            "type":"Services"
        }
    ],
    "sg:phone":"+1 818 907 0254",
    "sg:postcode":"91403",
    "sg:province":"CA",
    "sg:tags":[
        "spa"
    ],
    "wof:name":"Anna's Skin Care",
    "wof:placetype":"venue"
},
  "geometry": {"coordinates":[-118.448216,34.160959],"type":"Point"}
}