{
  "type": "Feature",
  "properties": {
    "addr:full":"2883 E Spring St Ste 150 Long Beach CA 90806",
    "addr:housenumber":"2883",
    "addr:postcode":"90806",
    "addr:street":"E Spring St Ste 150",
    "iso:country":"US",
    "sg:address":"2883 E Spring St Ste 150",
    "sg:city":"Long Beach",
    "sg:classifiers":[
        {
            "category":"Banks & Credit Unions",
            "subcategory":"Financial Services",
            "type":"Services"
        }
    ],
    "sg:phone":"+1 562 989 4900",
    "sg:postcode":"90806",
    "sg:province":"CA",
    "sg:tags":[
        "broker",
        "mortgage"
    ],
    "wof:name":"American Financial Group",
    "wof:placetype":"venue"
},
  "geometry": {"coordinates":[-118.157757,33.811503],"type":"Point"}
}