{
  "type": "Feature",
  "properties": {
    "iso:country":"US",
    "sg:address":"930 W Washington Street Suite 11",
    "sg:city":"San Diego",
    "sg:classifiers":[
        {
            "category":"Real Estate",
            "subcategory":"Real Estate Services",
            "type":"Services"
        }
    ],
    "sg:phone":"+1 619 296 6699",
    "sg:postcode":"92103",
    "sg:province":"CA",
    "sg:tags":[
        "management",
        "property"
    ],
    "wof:name":"Centre City Maintenance Company",
    "wof:placetype":"venue"
},
  "geometry": {"coordinates":[-117.17165900000001,32.749905],"type":"Point"}
}