{
  "type": "Feature",
  "properties": {
    "iso:country":"US",
    "sg:address":"1300 E 223rd St",
    "sg:city":"Carson",
    "sg:classifiers":[
        {
            "category":"Shopping",
            "type":"Retail Goods"
        }
    ],
    "sg:phone":"+1 310 830 4033",
    "sg:postcode":"90745",
    "sg:province":"CA",
    "sg:tags":[
        "telephone",
        "cellular"
    ],
    "wof:name":"Autotect",
    "wof:placetype":"venue"
},
  "geometry": {"coordinates":[-118.244711,33.824197],"type":"Point"}
}