{
  "type": "Feature",
  "properties": {
    "addr:full":"1393 E Walnut St Pasadena CA 91106",
    "addr:housenumber":"1393",
    "addr:postcode":"91106",
    "addr:street":"E Walnut St",
    "iso:country":"US",
    "sg:address":"1393 E Walnut St",
    "sg:city":"Pasadena",
    "sg:classifiers":[
        {
            "category":"Autos & Motor Vehicles",
            "subcategory":"Auto Supplies",
            "type":"Retail Goods"
        }
    ],
    "sg:phone":"+1 626 795 0425",
    "sg:postcode":"91106",
    "sg:province":"CA",
    "sg:tags":[
        "automobile",
        "stereo",
        "radio"
    ],
    "wof:name":"Al & Ed's Auto Sound",
    "wof:placetype":"venue"
},
  "geometry": {"coordinates":[-118.12214,34.149632],"type":"Point"}
}