{
  "type": "Feature",
  "properties": {
    "addr:full":"963 N Point St San Francisco CA 94109",
    "addr:housenumber":"963",
    "addr:postcode":"94109",
    "addr:street":"N Point St",
    "iso:country":"US",
    "sg:address":"963 N Point St",
    "sg:city":"San Francisco",
    "sg:classifiers":[
        {
            "category":"Professional",
            "subcategory":"Business Services",
            "type":"Services"
        }
    ],
    "sg:phone":"+1 415 775 4272",
    "sg:postcode":"94109",
    "sg:province":"CA",
    "sg:tags":[
        "interior",
        "consultant",
        "design",
        "decorator"
    ],
    "sg:website":"www.sandragriswold.com",
    "wof:name":"Sandra Griswold Interior",
    "wof:placetype":"venue"
},
  "geometry": {"coordinates":[-122.422819,37.805345],"type":"Point"}
}