{
  "type": "Feature",
  "properties": {
    "addr:full":"1151 Sloat Blvd San Francisco CA 94132",
    "addr:housenumber":"1151",
    "addr:postcode":"94132",
    "addr:street":"Sloat Blvd",
    "iso:country":"US",
    "sg:address":"1151 Sloat Blvd",
    "sg:city":"San Francisco",
    "sg:classifiers":[
        {
            "category":"Utilities",
            "subcategory":"Mobile Phone",
            "type":"Services"
        }
    ],
    "sg:phone":"+1 415 759 6050",
    "sg:postcode":"94132",
    "sg:province":"CA",
    "sg:tags":[
        "telephone",
        "cellular"
    ],
    "wof:name":"T Mobile",
    "wof:placetype":"venue"
},
  "geometry": {"coordinates":[-122.483548,37.734515],"type":"Point"}
}