{
  "type": "Feature",
  "properties": {
    "addr:full":"6676 Brad Ave Winton CA 95388",
    "addr:housenumber":"6676",
    "addr:postcode":"95388",
    "addr:street":"Brad Ave",
    "iso:country":"US",
    "sg:address":"6676 Brad Ave",
    "sg:city":"Winton",
    "sg:classifiers":[
        {
            "category":"Wholesale",
            "subcategory":"Electrical",
            "type":"Manufacturing & Wholesale Goods"
        }
    ],
    "sg:phone":"+1 209 358 7335",
    "sg:postcode":"95388",
    "sg:province":"CA",
    "sg:tags":[
        "alarm",
        "burglar",
        "system"
    ],
    "wof:name":"Paul Pitchford Alarms",
    "wof:placetype":"venue"
},
  "geometry": {"coordinates":[-120.616575,37.384664],"type":"Point"}
}