{
  "type": "Feature",
  "properties": {
    "iso:country":"US",
    "sg:address":"405 Sycamore St",
    "sg:city":"Gridley",
    "sg:classifiers":[
        {
            "category":"Health Services",
            "subcategory":"Doctor",
            "type":"Services"
        }
    ],
    "sg:phone":"+1 530 846 4756",
    "sg:postcode":"95948",
    "sg:province":"CA",
    "sg:tags":[
        "physician",
        "surgeon"
    ],
    "wof:name":"Donald E Sullivan MD",
    "wof:placetype":"venue"
},
  "geometry": {"coordinates":[-121.691861,39.364541],"type":"Point"}
}