{
  "type": "Feature",
  "properties": {
    "addr:full":"25751 Cross Creek Rd Salinas CA 93908",
    "addr:housenumber":"25751",
    "addr:postcode":"93908",
    "addr:street":"Cross Creek Rd",
    "iso:country":"US",
    "sg:address":"25751 Cross Creek Rd",
    "sg:city":"Salinas",
    "sg:classifiers":[
        {
            "category":"Professional",
            "subcategory":"Accounting & Tax Preparation",
            "type":"Services"
        }
    ],
    "sg:phone":"+1 831 484 9831",
    "sg:postcode":"93908",
    "sg:province":"CA",
    "sg:tags":[
        "accountant"
    ],
    "wof:name":"Riley Financial Advisors",
    "wof:placetype":"venue"
},
  "geometry": {"coordinates":[-121.728234,36.556727],"type":"Point"}
}