{
  "type": "Feature",
  "properties": {
    "iso:country":"US",
    "sg:address":"200 Tamal Vista Blvd",
    "sg:city":"Corte Madera",
    "sg:classifiers":[
        {
            "category":"Building & Trades",
            "subcategory":"Construction",
            "type":"Services"
        }
    ],
    "sg:phone":"+1 415 924 6105",
    "sg:postcode":"94925",
    "sg:province":"CA",
    "sg:tags":[
        "contractor"
    ],
    "wof:name":"Radco & Assoc",
    "wof:placetype":"venue"
},
  "geometry": {"coordinates":[-122.518682,37.938324],"type":"Point"}
}