{
  "type": "Feature",
  "properties": {
    "iso:country":"US",
    "sg:address":"5226 Diamond Heights Blvd",
    "sg:city":"San Francisco",
    "sg:classifiers":[
        {
            "category":"Professional",
            "subcategory":"Lawyer & Legal Services",
            "type":"Services"
        }
    ],
    "sg:phone":"+1 415 641 5577",
    "sg:postcode":"94131",
    "sg:province":"CA",
    "sg:tags":[
        "attorney"
    ],
    "wof:name":"Steven Englander Law Office",
    "wof:placetype":"venue"
},
  "geometry": {"coordinates":[-122.438346,37.743902],"type":"Point"}
}