{
  "type": "Feature",
  "properties": {
    "addr:full":"841 Arnold Dr Martinez CA 94553",
    "addr:housenumber":"841",
    "addr:postcode":"94553",
    "addr:street":"Arnold Dr",
    "iso:country":"US",
    "sg:address":"841 Arnold Dr",
    "sg:city":"Martinez",
    "sg:classifiers":[
        {
            "category":"Professional",
            "subcategory":"Computer Services",
            "type":"Services"
        }
    ],
    "sg:phone":"+1 925 957 1230",
    "sg:postcode":"94553",
    "sg:province":"CA",
    "sg:tags":[
        "consultant",
        "designer"
    ],
    "sg:website":"www.cygnusservices.com",
    "wof:name":"Cygnus Services Corp",
    "wof:placetype":"venue"
},
  "geometry": {"coordinates":[-122.11480899999999,37.997066],"type":"Point"}
}