{
  "type": "Feature",
  "properties": {
    "iso:country":"US",
    "sg:address":"701 Fulton Ave",
    "sg:city":"Sacramento",
    "sg:classifiers":[
        {
            "category":"Professional",
            "subcategory":"Business Services",
            "type":"Services"
        }
    ],
    "sg:phone":"+1 916 487 2080",
    "sg:postcode":"95825",
    "sg:province":"CA",
    "sg:tags":[
        "fire",
        "protection"
    ],
    "wof:name":"Central Pacific Sprinkler",
    "wof:placetype":"venue"
},
  "geometry": {"coordinates":[-121.4015,38.579234],"type":"Point"}
}