{
  "type": "Feature",
  "properties": {
    "addr:full":"649 Factory Stores Dr Napa CA 94558",
    "addr:housenumber":"649",
    "addr:postcode":"94558",
    "addr:street":"Stores Dr",
    "iso:country":"US",
    "sg:address":"649 Factory Stores Dr",
    "sg:city":"Napa",
    "sg:classifiers":[
        {
            "category":"Shopping",
            "subcategory":"Clothing, Apparel, & Fashions",
            "type":"Retail Goods"
        }
    ],
    "sg:phone":"+1 707 224 1641",
    "sg:postcode":"94558",
    "sg:province":"CA",
    "sg:tags":[
        "furnishing"
    ],
    "wof:name":"Zumiez Inc",
    "wof:placetype":"venue"
},
  "geometry": {"coordinates":[-122.302965,38.297969],"type":"Point"}
}