{
  "type": "Feature",
  "properties": {
    "addr:full":"3885 Dividend Dr Shingle Springs CA 95682",
    "addr:housenumber":"3885",
    "addr:postcode":"95682",
    "addr:street":"Dividend Dr",
    "iso:country":"US",
    "sg:address":"3885 Dividend Dr",
    "sg:city":"Shingle Springs",
    "sg:classifiers":[
        {
            "category":"Wholesale",
            "subcategory":"Auto Parts",
            "type":"Manufacturing & Wholesale Goods"
        }
    ],
    "sg:phone":"+1 530 677 8600",
    "sg:postcode":"95682",
    "sg:province":"CA",
    "sg:tags":[
        "automobile",
        "supply"
    ],
    "sg:website":"www.coil-over.com",
    "wof:name":"Ground Control Suspension",
    "wof:placetype":"venue"
},
  "geometry": {"coordinates":[-120.95232900000001,38.649],"type":"Point"}
}