{
  "type": "Feature",
  "properties": {
    "addr:full":"1275 Foothill Blvd La Verne CA 91750",
    "addr:housenumber":"1275",
    "addr:postcode":"91750",
    "addr:street":"Foothill Blvd",
    "iso:country":"US",
    "sg:address":"1275 Foothill Blvd",
    "sg:city":"La Verne",
    "sg:classifiers":[
        {
            "category":"Sports & Exercise",
            "subcategory":"Gym",
            "type":"Entertainment"
        }
    ],
    "sg:phone":"+1 909 392 1063",
    "sg:postcode":"91750",
    "sg:province":"CA",
    "sg:tags":[
        "fitness",
        "physical",
        "facility"
    ],
    "wof:name":"L A Fitness International Inc",
    "wof:placetype":"venue"
},
  "geometry": {"coordinates":[-117.781519,34.118905],"type":"Point"}
}