{
  "type": "Feature",
  "properties": {
    "addr:full":"24520 Outlook Dr Carmel CA 93923",
    "addr:housenumber":"24520",
    "addr:postcode":"93923",
    "addr:street":"Outlook Dr",
    "iso:country":"US",
    "sg:address":"24520 Outlook Dr",
    "sg:city":"Carmel",
    "sg:classifiers":[
        {
            "category":"Professional",
            "type":"Services"
        }
    ],
    "sg:phone":"+1 831 622 0714",
    "sg:postcode":"93923",
    "sg:province":"CA",
    "wof:name":"Ventis Corporation",
    "wof:placetype":"venue"
},
  "geometry": {"coordinates":[-121.906415,36.565409],"type":"Point"}
}