{
  "type": "Feature",
  "properties": {
    "addr:full":"14339 Hamlin St Van Nuys CA 91401",
    "addr:housenumber":"14339",
    "addr:postcode":"91401",
    "addr:street":"Hamlin St",
    "iso:country":"US",
    "sg:address":"14339 Hamlin St",
    "sg:city":"Van Nuys",
    "sg:classifiers":[
        {
            "category":"Organizations",
            "subcategory":"Religious Organization",
            "type":"Services"
        }
    ],
    "sg:phone":"+1 818 785 0575",
    "sg:postcode":"91401",
    "sg:province":"CA",
    "sg:tags":[
        "church"
    ],
    "wof:name":"Community Bible Church",
    "wof:placetype":"venue"
},
  "geometry": {"coordinates":[-118.44583299999999,34.188743],"type":"Point"}
}