{
  "type": "Feature",
  "properties": {
    "iso:country":"US",
    "sg:address":"633 Hidden Lakes Dr",
    "sg:city":"Martinez",
    "sg:classifiers":[
        {
            "category":"Restaurant",
            "type":"Food & Drink"
        }
    ],
    "sg:phone":"+1 925 363 9420",
    "sg:postcode":"94553",
    "sg:province":"CA",
    "wof:name":"B & B Seafood",
    "wof:placetype":"venue"
},
  "geometry": {"coordinates":[-122.081729,37.98073],"type":"Point"}
}