{
  "type": "Feature",
  "properties": {
    "iso:country":"US",
    "sg:address":"5865 Diamond Ridge Dr",
    "sg:city":"Redding",
    "sg:classifiers":[
        {
            "category":"Manufacturing",
            "subcategory":"Tools & Machinery",
            "type":"Manufacturing & Wholesale Goods"
        }
    ],
    "sg:phone":"+1 530 247 4246",
    "sg:postcode":"96003",
    "sg:province":"CA",
    "sg:tags":[
        "machine",
        "mfg"
    ],
    "wof:name":"Jayken Enterprises",
    "wof:placetype":"venue"
},
  "geometry": {"coordinates":[-122.36056000000001,40.622808],"type":"Point"}
}