{
  "type": "Feature",
  "properties": {
    "iso:country":"US",
    "sg:address":"1780 Fourth St",
    "sg:city":"Berkeley",
    "sg:classifiers":[
        {
            "category":"Tea Room",
            "subcategory":"None",
            "type":"Food & Drink"
        },
        {
            "category":"Coffee & Tea",
            "type":"Food & Drink"
        }
    ],
    "sg:phone":"+1 510 524 2832",
    "sg:postcode":"94710",
    "sg:province":"CA",
    "sg:website":"www.teance.com",
    "wof:name":"Teance",
    "wof:placetype":"venue"
},
  "geometry": {"coordinates":[-122.300995,37.870636],"type":"Point"}
}