{
  "type": "Feature",
  "properties": {
    "iso:country":"US",
    "sg:address":"2931 Larkin Ave",
    "sg:city":"Clovis",
    "sg:classifiers":[
        {
            "category":"Building & Trades",
            "subcategory":"Construction",
            "type":"Services"
        }
    ],
    "sg:phone":"+1 559 291 8983",
    "sg:postcode":"93612",
    "sg:province":"CA",
    "sg:tags":[
        "dry wall",
        "contractor"
    ],
    "wof:name":"Pinnacle Construction",
    "wof:placetype":"venue"
},
  "geometry": {"coordinates":[-119.69757799999999,36.799341],"type":"Point"}
}