{
  "type": "Feature",
  "properties": {
    "iso:country":"US",
    "sg:address":"5001 West Pico Blvd",
    "sg:city":"Los Angeles",
    "sg:classifiers":[
        {
            "category":"Ice Cream",
            "type":"Food & Drink"
        }
    ],
    "sg:phone":"+1 323 932 8888",
    "sg:postcode":"90019",
    "sg:province":"CA",
    "sg:tags":[
        "frozen",
        "yogurt"
    ],
    "sg:website":"www.newberryhillfrozenyogurt.com",
    "wof:name":"Newberry Hill Frozen Yogurt Gallery",
    "wof:placetype":"venue"
},
  "geometry": {"coordinates":[-118.345925,34.04804],"type":"Point"}
}