{
  "type": "Feature",
  "properties": {
    "addr:full":"3352 Steiner St San Francisco CA 94123",
    "addr:housenumber":"3352",
    "addr:postcode":"94123",
    "addr:street":"Steiner St",
    "iso:country":"US",
    "sg:address":"3352 Steiner St",
    "sg:city":"San Francisco",
    "sg:classifiers":[
        {
            "category":"Cafe",
            "type":"Food & Drink"
        }
    ],
    "sg:menulink":"http://www.allmenus.com/ca/san-francisco/46697-lettus-cafe-organic/menu/",
    "sg:phone":"+1 415 931 2777",
    "sg:postcode":"94123",
    "sg:province":"CA",
    "sg:tags":[
        "american"
    ],
    "wof:name":"Lettus Cafe Organic",
    "wof:placetype":"venue"
},
  "geometry": {"coordinates":[-122.43783999999999,37.800201],"type":"Point"}
}