{
  "type": "Feature",
  "properties": {
    "iso:country":"US",
    "sg:address":"5966 Warner Avenue",
    "sg:city":"Huntington Beach",
    "sg:classifiers":[
        {
            "category":"Restaurant",
            "type":"Food & Drink"
        }
    ],
    "sg:phone":"+1 714 846 4353",
    "sg:postcode":"92649",
    "sg:province":"CA",
    "sg:website":"www.wienerschnitzel.com",
    "wof:name":"Wienerschnitzel",
    "wof:placetype":"venue"
},
  "geometry": {"coordinates":[-118.02451600000001,33.715281],"type":"Point"}
}