{
  "type": "Feature",
  "properties": {
    "iso:country":"US",
    "sg:address":"7038 Katella Avenue",
    "sg:city":"Stanton",
    "sg:classifiers":[
        {
            "category":"Health Services",
            "subcategory":"Optometrist",
            "type":"Services"
        }
    ],
    "sg:phone":"+1 714 895 4899",
    "sg:postcode":"90680",
    "sg:province":"CA",
    "sg:website":"www.stantonoptometry.com/locatio...",
    "wof:name":"Stanton Optometry",
    "wof:placetype":"venue"
},
  "geometry": {"coordinates":[-118.010046,33.802802],"type":"Point"}
}