{
  "type": "Feature",
  "properties": {
    "iso:country":"US",
    "sg:address":"1312 W Herndon Ave",
    "sg:city":"Fresno",
    "sg:classifiers":[
        {
            "category":"Real Estate",
            "subcategory":"Real Estate Agent",
            "type":"Services"
        }
    ],
    "sg:phone":"+1 559 287 5455",
    "sg:postcode":"93711",
    "sg:province":"CA",
    "wof:name":"J Jones Realty",
    "wof:placetype":"venue"
},
  "geometry": {"coordinates":[-119.81653,36.837945],"type":"Point"}
}