{
  "type": "Feature",
  "properties": {
    "iso:country":"US",
    "sg:address":"7500 14th Ave Ste 7",
    "sg:city":"Sacramento",
    "sg:classifiers":[
        {
            "category":"Social Services",
            "type":"Services"
        }
    ],
    "sg:phone":"+1 916 454 1100",
    "sg:postcode":"95820",
    "sg:province":"CA",
    "sg:tags":[
        "program",
        "services-information",
        "referral"
    ],
    "sg:website":"http://www.aa.org",
    "wof:name":"Alcoholics Anonymous World Services, Inc.",
    "wof:placetype":"venue"
},
  "geometry": {"coordinates":[-121.416791,38.539607],"type":"Point"}
}