{
  "type": "Feature",
  "properties": {
    "addr:full":"14321 Main St Hesperia CA 92345",
    "addr:housenumber":"14321",
    "addr:postcode":"92345",
    "addr:street":"Main St",
    "iso:country":"US",
    "sg:address":"14321 Main St",
    "sg:city":"Hesperia",
    "sg:classifiers":[
        {
            "category":"Banks & Credit Unions",
            "subcategory":"Bank",
            "type":"Services"
        }
    ],
    "sg:phone":"+1 760 244 1760",
    "sg:postcode":"92345",
    "sg:province":"CA",
    "sg:tags":[
        "loan"
    ],
    "wof:name":"California Budget Finance",
    "wof:placetype":"venue"
},
  "geometry": {"coordinates":[-117.34894799999999,34.426723],"type":"Point"}
}