{
  "type": "Feature",
  "properties": {
    "addr:full":"890 Osos St San Luis Obispo CA 93401",
    "addr:housenumber":"890",
    "addr:postcode":"93401",
    "addr:street":"Osos St",
    "iso:country":"US",
    "sg:address":"890 Osos St",
    "sg:city":"San Luis Obispo",
    "sg:classifiers":[
        {
            "category":"Professional",
            "subcategory":"Lawyer & Legal Services",
            "type":"Services"
        }
    ],
    "sg:phone":"+1 805 785 0961",
    "sg:postcode":"93401",
    "sg:province":"CA",
    "sg:tags":[
        "attorney"
    ],
    "wof:name":"John M Carsel",
    "wof:placetype":"venue"
},
  "geometry": {"coordinates":[-120.662159,35.282781],"type":"Point"}
}