{
  "type": "Feature",
  "properties": {
    "iso:country":"US",
    "sg:address":"4109 Glencoe Avenue",
    "sg:city":"Marina Del Rey",
    "sg:classifiers":[
        {
            "category":"Personal",
            "type":"Services"
        }
    ],
    "sg:phone":"+1 818 789 5626",
    "sg:postcode":"90292",
    "sg:province":"CA",
    "sg:tags":[
        "mover"
    ],
    "wof:name":"Action Moving & Storage Company",
    "wof:placetype":"venue"
},
  "geometry": {"coordinates":[-118.442682,33.989968],"type":"Point"}
}