{
  "type": "Feature",
  "properties": {
    "iso:country":"US",
    "sg:address":"1165 N Fountain Way",
    "sg:city":"Anaheim",
    "sg:classifiers":[
        {
            "category":"Retail",
            "subcategory":"Car Wash",
            "type":"Services"
        }
    ],
    "sg:phone":"+1 714 630 4352",
    "sg:postcode":"92806",
    "sg:province":"CA",
    "sg:tags":[
        "polishing",
        "washing"
    ],
    "wof:name":"Armor Polishing",
    "wof:placetype":"venue"
},
  "geometry": {"coordinates":[-117.84364600000001,33.854885],"type":"Point"}
}