{
  "type": "Feature",
  "properties": {
    "addr:full":"144 Encinitas Blvd Encinitas CA 92024",
    "addr:housenumber":"144",
    "addr:postcode":"92024",
    "addr:street":"Encinitas Blvd",
    "iso:country":"US",
    "sg:address":"144 Encinitas Blvd",
    "sg:city":"Encinitas",
    "sg:classifiers":[
        {
            "category":"Coffee & Tea",
            "type":"Food & Drink"
        }
    ],
    "sg:phone":"+1 760 944 7989",
    "sg:postcode":"92024",
    "sg:province":"CA",
    "wof:name":"The Quick Fix Drive-Thru",
    "wof:placetype":"venue"
},
  "geometry": {"coordinates":[-117.289001,33.0485],"type":"Point"}
}