{
  "type": "Feature",
  "properties": {
    "iso:country":"US",
    "sg:address":"1432 W Capitol Avenue",
    "sg:city":"West Sacramento",
    "sg:classifiers":[
        {
            "category":"Travel",
            "subcategory":"Hotels & Motels",
            "type":"Entertainment"
        }
    ],
    "sg:phone":"+1 916 371 3660",
    "sg:postcode":"95691",
    "sg:province":"CA",
    "wof:name":"Best Value",
    "wof:placetype":"venue"
},
  "geometry": {"coordinates":[-121.527075,38.580823],"type":"Point"}
}