{
  "type": "Feature",
  "properties": {
    "iso:country":"US",
    "sg:address":"6003 Bridgehead Rd",
    "sg:city":"Antioch",
    "sg:classifiers":[
        {
            "category":"Building & Trades",
            "subcategory":"Electrical",
            "type":"Services"
        }
    ],
    "sg:phone":"+1 925 706 9800",
    "sg:postcode":"94509",
    "sg:province":"CA",
    "sg:tags":[
        "telecommunication",
        "contractor"
    ],
    "wof:name":"T C Brokers Inc",
    "wof:placetype":"venue"
},
  "geometry": {"coordinates":[-121.750844,38.015568],"type":"Point"}
}