{
  "type": "Feature",
  "properties": {
    "addr:full":"421 Tiffany Dr Santa Maria CA 93454",
    "addr:housenumber":"421",
    "addr:postcode":"93454",
    "addr:street":"Tiffany Dr",
    "iso:country":"US",
    "sg:address":"421 Tiffany Dr",
    "sg:city":"Santa Maria",
    "sg:classifiers":[
        {
            "category":"Building & Trades",
            "subcategory":"Landscaping Services",
            "type":"Services"
        }
    ],
    "sg:phone":"+1 805 925 5855",
    "sg:postcode":"93454",
    "sg:province":"CA",
    "sg:tags":[
        "landscape",
        "contractor"
    ],
    "wof:name":"Williams Landscaping & Mntnc",
    "wof:placetype":"venue"
},
  "geometry": {"coordinates":[-120.416325,34.956681],"type":"Point"}
}