{
  "type": "Feature",
  "properties": {
    "iso:country":"US",
    "sg:address":"301 S Western Ave",
    "sg:city":"Los Angeles",
    "sg:classifiers":[
        {
            "category":"Restaurant",
            "type":"Food & Drink"
        }
    ],
    "sg:phone":"+1 213 480 9890",
    "sg:postcode":"90020",
    "sg:province":"CA",
    "sg:tags":[
        "shop",
        "coffee"
    ],
    "wof:name":"Koffea",
    "wof:placetype":"venue"
},
  "geometry": {"coordinates":[-118.309107,34.067143],"type":"Point"}
}