{
  "type": "Feature",
  "properties": {
    "iso:country":"US",
    "sg:address":"1251 Activity Dr",
    "sg:city":"Vista",
    "sg:classifiers":[
        {
            "category":"Recreation",
            "type":"Entertainment"
        }
    ],
    "sg:phone":"+1 760 727 4487",
    "sg:postcode":"92081",
    "sg:province":"CA",
    "sg:tags":[
        "range",
        "baseball",
        "batting"
    ],
    "wof:name":"Prime Time Sports Academy",
    "wof:placetype":"venue"
},
  "geometry": {"coordinates":[-117.219468,33.142668],"type":"Point"}
}