{
  "type": "Feature",
  "properties": {
    "iso:country":"US",
    "sg:address":"8560 Church St",
    "sg:city":"Gilroy",
    "sg:classifiers":[
        {
            "category":"Health Services",
            "subcategory":"Health Practitioner",
            "type":"Services"
        }
    ],
    "sg:phone":"+1 408 842 4008",
    "sg:postcode":"95020",
    "sg:province":"CA",
    "sg:tags":[
        "therapist",
        "physical"
    ],
    "wof:name":"Parkside Physical Therapy",
    "wof:placetype":"venue"
},
  "geometry": {"coordinates":[-121.579039,37.022023],"type":"Point"}
}