{
  "type": "Feature",
  "properties": {
    "addr:full":"600 N Arrowhead Ave San Bernardino CA 92401",
    "addr:housenumber":"600",
    "addr:postcode":"92401",
    "addr:street":"N Arrowhead Ave",
    "iso:country":"US",
    "sg:address":"600 N Arrowhead Ave",
    "sg:city":"San Bernardino",
    "sg:classifiers":[
        {
            "category":"Professional",
            "subcategory":"Lawyer & Legal Services",
            "type":"Services"
        }
    ],
    "sg:phone":"+1 909 888 5751",
    "sg:postcode":"92401",
    "sg:province":"CA",
    "sg:tags":[
        "attorney"
    ],
    "sg:website":"www.mkp-law.com",
    "wof:name":"Middlebrook Kaiser & Popka",
    "wof:placetype":"venue"
},
  "geometry": {"coordinates":[-117.289666,34.112068],"type":"Point"}
}