{
  "type": "Feature",
  "properties": {
    "iso:country":"US",
    "sg:address":"640 S. Main Ave",
    "sg:city":"Fallbrook",
    "sg:classifiers":[
        {
            "category":"Shopping",
            "type":"Retail Goods"
        }
    ],
    "sg:phone":"+1 760 728 4265",
    "sg:postcode":"92028",
    "sg:province":"CA",
    "wof:name":"Joe's Hardware",
    "wof:placetype":"venue"
},
  "geometry": {"coordinates":[-117.251122,33.377158],"type":"Point"}
}