{
  "type": "Feature",
  "properties": {
    "addr:full":"7051 Clairemont Mesa Blvd San Diego CA 92117",
    "addr:housenumber":"7051",
    "addr:postcode":"92117",
    "addr:street":"Clairemont Mesa Blvd",
    "iso:country":"US",
    "sg:address":"7051 Clairemont Mesa Blvd",
    "sg:city":"San Diego",
    "sg:classifiers":[
        {
            "category":"Personal",
            "subcategory":"Beauty Salon",
            "type":"Services"
        }
    ],
    "sg:phone":"+1 858 560 1212",
    "sg:postcode":"92117",
    "sg:province":"CA",
    "wof:name":"Jun's Park Beauty Lab",
    "wof:placetype":"venue"
},
  "geometry": {"coordinates":[-117.164907,32.832574],"type":"Point"}
}