{
  "type": "Feature",
  "properties": {
    "addr:full":"7683 State Rte 1 Littleriver CA 95456",
    "addr:housenumber":"7683",
    "addr:postcode":"95456",
    "addr:street":"State Rte 1 Littleriver",
    "iso:country":"US",
    "sg:address":"7683 State Rte 1",
    "sg:city":"Littleriver",
    "sg:classifiers":[
        {
            "category":"Retail",
            "subcategory":"Auto Repair",
            "type":"Services"
        }
    ],
    "sg:phone":"+1 707 937 4420",
    "sg:postcode":"95456",
    "sg:province":"CA",
    "sg:tags":[
        "repairing",
        "automobile"
    ],
    "wof:name":"Little River Pump & Supply",
    "wof:placetype":"venue"
},
  "geometry": {"coordinates":[-123.79029199999999,39.273579],"type":"Point"}
}