{
  "type": "Feature",
  "properties": {
    "iso:country":"US",
    "sg:address":"1517 1/2 W 6th St",
    "sg:city":"Los Angeles",
    "sg:classifiers":[
        {
            "category":"Food & Beverages",
            "subcategory":"Groceries & Convenience Stores",
            "type":"Retail Goods"
        }
    ],
    "sg:phone":"+1 213 413 1907",
    "sg:postcode":"90017",
    "sg:province":"CA",
    "sg:website":"www.los-tres-amigos.com",
    "wof:name":"Los Tres Amigos",
    "wof:placetype":"venue"
},
  "geometry": {"coordinates":[-118.268535,34.057044],"type":"Point"}
}