{
  "type": "Feature",
  "properties": {
    "iso:country":"US",
    "sg:address":"3861 Smith St",
    "sg:city":"Union City",
    "sg:classifiers":[
        {
            "category":"Government",
            "subcategory":"Post Office",
            "type":"Public Place"
        }
    ],
    "sg:phone":"+1 510 471 1180",
    "sg:postcode":"94587",
    "sg:province":"CA",
    "sg:tags":[
        "postal",
        "us"
    ],
    "wof:name":"Alvarado Station",
    "wof:placetype":"venue"
},
  "geometry": {"coordinates":[-122.078609,37.596537],"type":"Point"}
}