{
  "type": "Feature",
  "properties": {
    "iso:country":"US",
    "sg:address":"1190 Hillsdale Ave",
    "sg:city":"San Jose",
    "sg:classifiers":[
        {
            "category":"Restaurant",
            "type":"Food & Drink"
        }
    ],
    "sg:phone":"+1 408 978 7188",
    "sg:postcode":"95118",
    "sg:province":"CA",
    "sg:tags":[
        "mongolian"
    ],
    "wof:name":"President Restaurant",
    "wof:placetype":"venue"
},
  "geometry": {"coordinates":[-121.88054200000001,37.274285],"type":"Point"}
}