{
  "type": "Feature",
  "properties": {
    "addr:full":"23150 Lake Center Dr Laguna Hills CA 92653",
    "addr:housenumber":"23150",
    "addr:postcode":"92653",
    "addr:street":"Lake Center Dr",
    "iso:country":"US",
    "sg:address":"23150 Lake Center Dr",
    "sg:city":"Laguna Hills",
    "sg:classifiers":[
        {
            "category":"Travel",
            "subcategory":"Hotels & Motels",
            "type":"Entertainment"
        }
    ],
    "sg:phone":"+1 949 855 1000",
    "sg:postcode":"92653",
    "sg:province":"CA",
    "wof:name":"Best Value Inn",
    "wof:placetype":"venue"
},
  "geometry": {"coordinates":[-117.712997,33.6007],"type":"Point"}
}