{
  "type": "Feature",
  "properties": {
    "iso:country":"US",
    "sg:address":"1493 N Montebello Blvd",
    "sg:city":"Montebello",
    "sg:classifiers":[
        {
            "category":"Restaurant",
            "type":"Food & Drink"
        }
    ],
    "sg:phone":"+1 323 278 0250",
    "sg:postcode":"90640",
    "sg:province":"CA",
    "sg:tags":[
        "traditional",
        "american"
    ],
    "sg:website":"www.applebees.com",
    "wof:name":"Applebee's",
    "wof:placetype":"venue"
},
  "geometry": {"coordinates":[-118.122095,33.983969],"type":"Point"}
}