{
  "type": "Feature",
  "properties": {
    "iso:country":"US",
    "sg:address":"1071 Maverick Ct",
    "sg:city":"Santa Rosa",
    "sg:classifiers":[
        {
            "category":"Banks & Credit Unions",
            "subcategory":"Investment Brokerage",
            "type":"Services"
        }
    ],
    "sg:phone":"+1 707 523 2072",
    "sg:postcode":"95404",
    "sg:province":"CA",
    "sg:tags":[
        "consultant",
        "planning",
        "financial"
    ],
    "wof:name":"Ken Reeder Financial Svc",
    "wof:placetype":"venue"
},
  "geometry": {"coordinates":[-122.724886,38.519753],"type":"Point"}
}