{
  "type": "Feature",
  "properties": {
    "addr:full":"1608 McKee Rd San Jose CA 95116",
    "addr:housenumber":"1608",
    "addr:postcode":"95116",
    "addr:street":"Mckee Rd",
    "iso:country":"US",
    "sg:address":"1608 McKee Rd",
    "sg:city":"San Jose",
    "sg:classifiers":[
        {
            "category":"Professional",
            "subcategory":"Art Services",
            "type":"Services"
        }
    ],
    "sg:phone":"+1 408 923 8589",
    "sg:postcode":"95116",
    "sg:province":"CA",
    "sg:tags":[
        "photographer"
    ],
    "wof:name":"Envy Studio",
    "wof:placetype":"venue"
},
  "geometry": {"coordinates":[-121.863998,37.356098],"type":"Point"}
}