{
  "type": "Feature",
  "properties": {
    "addr:full":"228 Venture St San Marcos CA 92078",
    "addr:housenumber":"228",
    "addr:postcode":"92078",
    "addr:street":"Venture St",
    "iso:country":"US",
    "sg:address":"228 Venture St",
    "sg:city":"San Marcos",
    "sg:classifiers":[
        {
            "category":"Travel",
            "subcategory":"Hotels & Motels",
            "type":"Entertainment"
        }
    ],
    "sg:phone":"+1 760 471 1798",
    "sg:postcode":"92078",
    "sg:province":"CA",
    "sg:tags":[
        "operation"
    ],
    "wof:name":"Strategic Hotel Capital LLC",
    "wof:placetype":"venue"
},
  "geometry": {"coordinates":[-117.15278499999999,33.13584],"type":"Point"}
}