{
  "type": "Feature",
  "properties": {
    "addr:full":"703 Ash St San Diego CA 92101",
    "addr:housenumber":"703",
    "addr:postcode":"92101",
    "addr:street":"Ash St",
    "iso:country":"US",
    "sg:address":"703 Ash St",
    "sg:city":"San Diego",
    "sg:classifiers":[
        {
            "category":"Real Estate",
            "subcategory":"Architect",
            "type":"Services"
        },
        {
            "category":"Professional",
            "type":"Services"
        }
    ],
    "sg:phone":"+1 619 702 6297",
    "sg:postcode":"92101",
    "sg:province":"CA",
    "sg:tags":[
        "establishment"
    ],
    "wof:name":"Khalafi Robertson & Assoc",
    "wof:placetype":"venue"
},
  "geometry": {"coordinates":[-117.157472,32.719821],"type":"Point"}
}