{
  "type": "Feature",
  "properties": {
    "addr:full":"11522 Sutton Way Grass Valley CA 95945",
    "addr:housenumber":"11522",
    "addr:postcode":"95945",
    "addr:street":"Sutton Way",
    "iso:country":"US",
    "sg:address":"11522 Sutton Way",
    "sg:city":"Grass Valley",
    "sg:classifiers":[
        {
            "category":"Shopping",
            "subcategory":"Crafts & Fabrics",
            "type":"Retail Goods"
        }
    ],
    "sg:phone":"+1 530 272 1197",
    "sg:postcode":"95945",
    "sg:province":"CA",
    "sg:tags":[
        "shop"
    ],
    "wof:name":"Fabric Boutique",
    "wof:placetype":"venue"
},
  "geometry": {"coordinates":[-121.034025,39.23442],"type":"Point"}
}