{
  "type": "Feature",
  "properties": {
    "addr:full":"10921 Wilshire Blvd #1112 Los Angeles CA 90024",
    "addr:housenumber":"10921",
    "addr:postcode":"90024",
    "addr:street":"Wilshire Blvd # 1112",
    "iso:country":"US",
    "sg:address":"10921 Wilshire Blvd #1112",
    "sg:city":"Los Angeles",
    "sg:classifiers":[
        {
            "category":"Health Services",
            "subcategory":"Dentist",
            "type":"Services"
        }
    ],
    "sg:phone":"+1 310 208 4084",
    "sg:postcode":"90024",
    "sg:province":"CA",
    "sg:website":"www.westwooddentalsmiles.com",
    "wof:name":"Tomas Anderkvist, DDS",
    "wof:placetype":"venue"
},
  "geometry": {"coordinates":[-118.444869,34.058903],"type":"Point"}
}