{
  "type": "Feature",
  "properties": {
    "addr:full":"1420 Main St Weaverville CA 96093",
    "addr:housenumber":"1420",
    "addr:postcode":"96093",
    "addr:street":"Main St",
    "iso:country":"US",
    "sg:address":"1420 Main St",
    "sg:city":"Weaverville",
    "sg:classifiers":[
        {
            "category":"Shopping",
            "type":"Retail Goods"
        }
    ],
    "sg:phone":"+1 530 623 3613",
    "sg:postcode":"96093",
    "sg:province":"CA",
    "sg:tags":[
        "telephone",
        "cellular"
    ],
    "wof:name":"Air Cellular",
    "wof:placetype":"venue"
},
  "geometry": {"coordinates":[-122.934247,40.726072],"type":"Point"}
}