{
  "type": "Feature",
  "properties": {
    "iso:country":"US",
    "sg:address":"5125 Abbott Rd",
    "sg:city":"Penryn",
    "sg:classifiers":[
        {
            "category":"Building & Trades",
            "subcategory":"Landscaping Services",
            "type":"Services"
        }
    ],
    "sg:phone":"+1 916 663 3305",
    "sg:postcode":"95663",
    "sg:province":"CA",
    "sg:tags":[
        "landscape"
    ],
    "wof:name":"Jennie Nitta Plants & Plans",
    "wof:placetype":"venue"
},
  "geometry": {"coordinates":[-121.202003,38.861314],"type":"Point"}
}