{
  "type": "Feature",
  "properties": {
    "addr:full":"7915 Crest Ave Oakland CA 94605",
    "addr:housenumber":"7915",
    "addr:postcode":"94605",
    "addr:street":"Crest Ave",
    "iso:country":"US",
    "sg:address":"7915 Crest Ave",
    "sg:city":"Oakland",
    "sg:classifiers":[
        {
            "category":"Professional",
            "subcategory":"Engineering",
            "type":"Services"
        }
    ],
    "sg:phone":"+1 510 568 2162",
    "sg:postcode":"94605",
    "sg:province":"CA",
    "sg:tags":[
        "engineer"
    ],
    "wof:name":"Dave Olnes Inc",
    "wof:placetype":"venue"
},
  "geometry": {"coordinates":[-122.158891,37.767434],"type":"Point"}
}