{
  "type": "Feature",
  "properties": {
    "addr:full":"111 Preda St San Leandro CA 94577",
    "addr:housenumber":"111",
    "addr:postcode":"94577",
    "addr:street":"Preda St",
    "iso:country":"US",
    "sg:address":"111 Preda St",
    "sg:city":"San Leandro",
    "sg:classifiers":[
        {
            "category":"Real Estate",
            "subcategory":"Real Estate Operator",
            "type":"Services"
        }
    ],
    "sg:phone":"+1 510 635 5664",
    "sg:postcode":"94577",
    "sg:province":"CA",
    "sg:tags":[
        "apartment"
    ],
    "wof:name":"First Financial",
    "wof:placetype":"venue"
},
  "geometry": {"coordinates":[-122.168989,37.722473],"type":"Point"}
}