{
  "type": "Feature",
  "properties": {
    "addr:full":"1275 Farmington Pl San Marcos CA 92078",
    "addr:housenumber":"1275",
    "addr:postcode":"92078",
    "addr:street":"Farmington Pl",
    "iso:country":"US",
    "sg:address":"1275 Farmington Pl",
    "sg:city":"San Marcos",
    "sg:classifiers":[
        {
            "category":"Manufacturing",
            "subcategory":"Motor Vehicles & Parts",
            "type":"Manufacturing & Wholesale Goods"
        }
    ],
    "sg:phone":"+1 760 727 1217",
    "sg:postcode":"92078",
    "sg:province":"CA",
    "sg:tags":[
        "mfg"
    ],
    "wof:name":"Super Car Coinc",
    "wof:placetype":"venue"
},
  "geometry": {"coordinates":[-117.221169,33.124387],"type":"Point"}
}