{
  "type": "Feature",
  "properties": {
    "addr:full":"20418 E Walnut Dr N Walnut CA 91748",
    "addr:housenumber":"20418",
    "addr:postcode":"91748",
    "addr:street":"E Walnut Dr N",
    "iso:country":"US",
    "sg:address":"20418 E Walnut Dr N",
    "sg:city":"Walnut",
    "sg:classifiers":[
        {
            "category":"Wholesale",
            "subcategory":"Machinery & Supplies",
            "type":"Manufacturing & Wholesale Goods"
        }
    ],
    "sg:phone":"+1 909 468 5650",
    "sg:postcode":"91748",
    "sg:province":"CA",
    "sg:tags":[
        "equipment",
        "industrial"
    ],
    "wof:name":"National Industries",
    "wof:placetype":"venue"
},
  "geometry": {"coordinates":[-117.858648,33.999907],"type":"Point"}
}