{
  "type": "Feature",
  "properties": {
    "addr:full":"611 5th St Santa Rosa CA 95404",
    "addr:housenumber":"611",
    "addr:postcode":"ca 95404",
    "addr:street":"5Th St",
    "iso:country":"US",
    "sg:address":"611 5th St",
    "sg:city":"Santa Rosa",
    "sg:classifiers":[
        {
            "category":"Restaurant",
            "type":"Food & Drink"
        }
    ],
    "sg:menulink":"http://www.allmenus.com/ca/santa-rosa/52871-gary-chus/menu/",
    "sg:phone":"+1 707 526 5840",
    "sg:postcode":"95404",
    "sg:province":"CA",
    "sg:tags":[
        "asian",
        "chinese"
    ],
    "wof:name":"Gary Chu's",
    "wof:placetype":"venue"
},
  "geometry": {"coordinates":[-122.71404,38.441522],"type":"Point"}
}