{
  "type": "Feature",
  "properties": {
    "iso:country":"US",
    "sg:address":"13604 Whittier Blvd",
    "sg:city":"Whittier",
    "sg:classifiers":[
        {
            "category":"Real Estate",
            "subcategory":"Real Estate Agent",
            "type":"Services"
        }
    ],
    "sg:phone":"+1 562 698 0348",
    "sg:postcode":"90605",
    "sg:province":"CA",
    "sg:website":"www.atcornerstonerealty.com",
    "wof:name":"At Cornerstone Realty",
    "wof:placetype":"venue"
},
  "geometry": {"coordinates":[-118.028193,33.960359],"type":"Point"}
}