{
  "type": "Feature",
  "properties": {
    "addr:full":"23635 el Toro Rd El Toro CA 92630",
    "addr:housenumber":"23635",
    "addr:postcode":"92630",
    "addr:street":"El Toro Rd",
    "iso:country":"US",
    "sg:address":"23635 el Toro Rd",
    "sg:city":"El Toro",
    "sg:classifiers":[
        {
            "category":"Wholesale",
            "subcategory":"Sporting Goods",
            "type":"Manufacturing & Wholesale Goods"
        }
    ],
    "sg:phone":"+1 949 581 5830",
    "sg:postcode":"92630",
    "sg:province":"CA",
    "sg:tags":[
        "equipment",
        "billiard",
        "supply"
    ],
    "wof:name":"AAA Billiards Of Orange Cnty",
    "wof:placetype":"venue"
},
  "geometry": {"coordinates":[-117.702455,33.619044],"type":"Point"}
}