{
  "type": "Feature",
  "properties": {
    "iso:country":"US",
    "sg:address":"4461 W 4th St",
    "sg:city":"Los Angeles",
    "sg:classifiers":[
        {
            "category":"Professional",
            "subcategory":"Art Services",
            "type":"Services"
        }
    ],
    "sg:phone":"+1 864 313 8979",
    "sg:postcode":"90020",
    "sg:province":"CA",
    "sg:tags":[
        "photographer"
    ],
    "sg:website":"pinkmemories.com",
    "wof:name":"Pink Memories Photography",
    "wof:placetype":"venue"
},
  "geometry": {"coordinates":[-118.314491,34.067141],"type":"Point"}
}