{
  "type": "Feature",
  "properties": {
    "addr:full":"71703 Highway 111 Rancho Mirage CA 92270",
    "addr:housenumber":"71703",
    "addr:postcode":"92270",
    "addr:street":"Highway 111",
    "iso:country":"US",
    "sg:address":"71703 Highway 111",
    "sg:city":"Rancho Mirage",
    "sg:classifiers":[
        {
            "category":"Banks & Credit Unions",
            "subcategory":"Bank",
            "type":"Services"
        }
    ],
    "sg:phone":"+1 760 568 2694",
    "sg:postcode":"92270",
    "sg:province":"CA",
    "wof:name":"Wells Fargo",
    "wof:placetype":"venue"
},
  "geometry": {"coordinates":[-116.41352999999999,33.742394],"type":"Point"}
}