{
  "type": "Feature",
  "properties": {
    "iso:country":"US",
    "sg:address":"2978 Wilshire Blvd",
    "sg:city":"Los Angeles",
    "sg:classifiers":[
        {
            "category":"Real Estate",
            "subcategory":"Real Estate Agent",
            "type":"Services"
        }
    ],
    "sg:phone":"+1 323 468 1077",
    "sg:postcode":"90010",
    "sg:province":"CA",
    "wof:name":"Happy Realty & Investment Co",
    "wof:placetype":"venue"
},
  "geometry": {"coordinates":[-118.286587,34.061747],"type":"Point"}
}