{
  "type": "Feature",
  "properties": {
    "addr:full":"5721 Lankershim Blvd North Hollywood CA 91601",
    "addr:housenumber":"5721",
    "addr:postcode":"91601",
    "addr:street":"Lankershim Blvd",
    "iso:country":"US",
    "sg:address":"5721 Lankershim Blvd",
    "sg:city":"North Hollywood",
    "sg:classifiers":[
        {
            "category":"Retail",
            "subcategory":"Repair Shop",
            "type":"Services"
        }
    ],
    "sg:phone":"+1 818 985 3200",
    "sg:postcode":"91601",
    "sg:province":"CA",
    "sg:tags":[
        "equipment",
        "conditioning",
        "air"
    ],
    "wof:name":"Feder's",
    "wof:placetype":"venue"
},
  "geometry": {"coordinates":[-118.380493,34.174361],"type":"Point"}
}