{
  "type": "Feature",
  "properties": {
    "iso:country":"US",
    "sg:address":"244 W Canada",
    "sg:city":"San Clemente",
    "sg:classifiers":[
        {
            "category":"Professional",
            "subcategory":"Management & Consulting",
            "type":"Services"
        }
    ],
    "sg:phone":"+1 949 369 8515",
    "sg:postcode":"92672",
    "sg:province":"CA",
    "sg:tags":[
        "retail",
        "direct",
        "sales"
    ],
    "wof:name":"Kats Creations",
    "wof:placetype":"venue"
},
  "geometry": {"coordinates":[-117.62477699999999,33.426547],"type":"Point"}
}