{
  "type": "Feature",
  "properties": {
    "iso:country":"US",
    "sg:address":"3931 Durock Rd",
    "sg:city":"Shingle Springs",
    "sg:classifiers":[
        {
            "category":"Home & Garden",
            "subcategory":"Garden Supply",
            "type":"Retail Goods"
        }
    ],
    "sg:phone":"+1 530 676 6555",
    "sg:postcode":"95682",
    "sg:province":"CA",
    "sg:tags":[
        "nurseryman"
    ],
    "wof:name":"El Dorado Nursery & Garden Inc",
    "wof:placetype":"venue"
},
  "geometry": {"coordinates":[-120.945769,38.659303],"type":"Point"}
}