{
  "type": "Feature",
  "properties": {
    "addr:full":"2855 Lemon Grove Ave Lemon Grove CA 91945",
    "addr:housenumber":"2855",
    "addr:postcode":"91945",
    "addr:street":"Lemon Grove Ave",
    "iso:country":"US",
    "sg:address":"2855 Lemon Grove Ave",
    "sg:city":"Lemon Grove",
    "sg:classifiers":[
        {
            "category":"Professional",
            "type":"Services"
        }
    ],
    "sg:phone":"+1 619 667 5378",
    "sg:postcode":"91945",
    "sg:province":"CA",
    "wof:name":"Selectables",
    "wof:placetype":"venue"
},
  "geometry": {"coordinates":[-117.030732,32.737507],"type":"Point"}
}