{
  "type": "Feature",
  "properties": {
    "addr:full":"11455 Galena St Mira Loma CA 91752",
    "addr:housenumber":"11455",
    "addr:postcode":"91752",
    "addr:street":"Galena St",
    "iso:country":"US",
    "sg:address":"11455 Galena St",
    "sg:city":"Mira Loma",
    "sg:classifiers":[
        {
            "category":"Professional",
            "subcategory":"Business Services",
            "type":"Services"
        }
    ],
    "sg:phone":"+1 951 685 2511",
    "sg:postcode":"91752",
    "sg:province":"CA",
    "sg:tags":[
        "packaging"
    ],
    "wof:name":"Unipak Logistics",
    "wof:placetype":"venue"
},
  "geometry": {"coordinates":[-117.541538,34.004494],"type":"Point"}
}