{
  "type": "Feature",
  "properties": {
    "iso:country":"US",
    "sg:address":"4841 Chino Ave",
    "sg:city":"Chino",
    "sg:classifiers":[
        {
            "category":"Wholesale",
            "subcategory":"Non-durable Goods",
            "type":"Manufacturing & Wholesale Goods"
        }
    ],
    "sg:phone":"+1 909 517 0057",
    "sg:postcode":"91710",
    "sg:province":"CA",
    "sg:tags":[
        "item",
        "gift"
    ],
    "wof:name":"Lu International Company",
    "wof:placetype":"venue"
},
  "geometry": {"coordinates":[-117.700664,34.011667],"type":"Point"}
}