{
  "type": "Feature",
  "properties": {
    "iso:country":"US",
    "sg:address":"1312 Prentice Dr",
    "sg:city":"Healdsburg",
    "sg:classifiers":[
        {
            "category":"Health Services",
            "subcategory":"Doctor",
            "type":"Services"
        }
    ],
    "sg:phone":"+1 707 433 3383",
    "sg:postcode":"95448",
    "sg:province":"CA",
    "sg:tags":[
        "physician",
        "surgeon"
    ],
    "wof:name":"Healdsburg Primary Care",
    "wof:placetype":"venue"
},
  "geometry": {"coordinates":[-122.86666099999999,38.62616],"type":"Point"}
}