{
  "type": "Feature",
  "properties": {
    "addr:full":"28130 Ave Crocker Santa Clarita CA 91355",
    "addr:postcode":"28130;91355",
    "addr:street":"Ave",
    "iso:country":"US",
    "sg:address":"28130 Ave Crocker",
    "sg:city":"Santa Clarita",
    "sg:classifiers":[
        {
            "category":"Building & Trades",
            "subcategory":"Electrical",
            "type":"Services"
        }
    ],
    "sg:phone":"+1 661 257 1574",
    "sg:postcode":"91355",
    "sg:province":"CA",
    "sg:tags":[
        "electric",
        "contractor"
    ],
    "wof:name":"RJS Electric",
    "wof:placetype":"venue"
},
  "geometry": {"coordinates":[-118.587324,34.437309],"type":"Point"}
}