{
  "type": "Feature",
  "properties": {
    "addr:full":"101 S San Mateo Dr Ste 310 San Mateo CA 94401",
    "addr:housenumber":"101",
    "addr:postcode":"94401",
    "addr:street":"S San Mateo Dr Ste 310",
    "iso:country":"US",
    "sg:address":"101 S San Mateo Dr Ste 310",
    "sg:city":"San Mateo",
    "sg:classifiers":[
        {
            "category":"Health Services",
            "subcategory":"Optometrist",
            "type":"Services"
        }
    ],
    "sg:phone":"+1 650 342 7474",
    "sg:postcode":"94401",
    "sg:province":"CA",
    "sg:tags":[
        "ophthalmologist"
    ],
    "sg:website":"www.peneye.com",
    "wof:name":"Dr Michael Drinnan at Peninsula Eye Physicians",
    "wof:placetype":"venue"
},
  "geometry": {"coordinates":[-122.325551,37.565874],"type":"Point"}
}