{
  "type": "Feature",
  "properties": {
    "iso:country":"US",
    "sg:address":"13441 Adrian Dr",
    "sg:city":"Magalia",
    "sg:classifiers":[
        {
            "category":"Health Services",
            "subcategory":"Doctor",
            "type":"Services"
        }
    ],
    "sg:phone":"+1 530 873 8105",
    "sg:postcode":"95954",
    "sg:province":"CA",
    "sg:tags":[
        "physician",
        "surgeon"
    ],
    "wof:name":"Williard H Clark MD",
    "wof:placetype":"venue"
},
  "geometry": {"coordinates":[-121.599001,39.798413],"type":"Point"}
}