{
  "type": "Feature",
  "properties": {
    "addr:full":"9497 Santa Monica Blvd Beverly Hills CA 90210",
    "addr:housenumber":"9497",
    "addr:postcode":"90210",
    "addr:street":"Santa Monica Blvd",
    "iso:country":"US",
    "sg:address":"9497 Santa Monica Blvd",
    "sg:city":"Beverly Hills",
    "sg:classifiers":[
        {
            "category":"Restaurant",
            "type":"Food & Drink"
        }
    ],
    "sg:phone":"+1 310 786 7878",
    "sg:postcode":"90210",
    "sg:province":"CA",
    "wof:name":"Sandbag's Gourmet Sandwiches",
    "wof:placetype":"venue"
},
  "geometry": {"coordinates":[-118.403435,34.071346],"type":"Point"}
}