{
  "type": "Feature",
  "properties": {
    "addr:full":"6617 Fallbrook Ave West Hills CA 91307",
    "addr:housenumber":"6617",
    "addr:postcode":"91307",
    "addr:street":"Fallbrook Ave",
    "iso:country":"US",
    "sg:address":"6617 Fallbrook Ave",
    "sg:city":"West Hills",
    "sg:classifiers":[
        {
            "category":"Personal",
            "subcategory":"Beauty Salon",
            "type":"Services"
        }
    ],
    "sg:phone":"+1 818 347 8700",
    "sg:postcode":"91307",
    "sg:province":"CA",
    "sg:tags":[
        "spa"
    ],
    "sg:website":"www.beyondbeautycentre.com",
    "wof:name":"Beyond Beauty",
    "wof:placetype":"venue"
},
  "geometry": {"coordinates":[-118.623374,34.190711],"type":"Point"}
}