{
  "type": "Feature",
  "properties": {
    "iso:country":"US",
    "sg:address":"77 Miller Ave",
    "sg:city":"Mill Valley",
    "sg:classifiers":[
        {
            "category":"Retail",
            "subcategory":"Laundry & Dry Cleaning",
            "type":"Services"
        }
    ],
    "sg:phone":"+1 415 388 3035",
    "sg:postcode":"94941",
    "sg:province":"CA",
    "sg:tags":[
        "cleaners"
    ],
    "sg:website":"www.voguecleaners.com",
    "wof:name":"Vogue Cleaners Inc",
    "wof:placetype":"venue"
},
  "geometry": {"coordinates":[-122.54688299999999,37.904733],"type":"Point"}
}