{
  "type": "Feature",
  "properties": {
    "addr:full":"621 Tully Rd San Jose CA 95111",
    "addr:housenumber":"621",
    "addr:postcode":"95111",
    "addr:street":"Tully Rd",
    "iso:country":"US",
    "sg:address":"621 Tully Rd",
    "sg:city":"San Jose",
    "sg:classifiers":[
        {
            "category":"Professional",
            "subcategory":"Computer Services",
            "type":"Services"
        }
    ],
    "sg:phone":"+1 408 298 8822",
    "sg:postcode":"95111",
    "sg:province":"CA",
    "sg:tags":[
        "hardware",
        "provider",
        "internet",
        "software"
    ],
    "wof:name":"Gol US",
    "wof:placetype":"venue"
},
  "geometry": {"coordinates":[-121.845411,37.309428],"type":"Point"}
}