{
  "type": "Feature",
  "properties": {
    "addr:full":"724 Clovis Ave Clovis CA 93612",
    "addr:housenumber":"724",
    "addr:postcode":"93612",
    "addr:street":"Clovis Ave",
    "iso:country":"US",
    "sg:address":"724 Clovis Ave",
    "sg:city":"Clovis",
    "sg:classifiers":[
        {
            "category":"Retail",
            "subcategory":"Auto Repair",
            "type":"Services"
        }
    ],
    "sg:phone":"+1 559 324 8300",
    "sg:postcode":"93612",
    "sg:province":"CA",
    "sg:tags":[
        "muffler",
        "exhaust",
        "system"
    ],
    "wof:name":"Performance Exhaust",
    "wof:placetype":"venue"
},
  "geometry": {"coordinates":[-119.700705,36.82106],"type":"Point"}
}