{
  "type": "Feature",
  "properties": {
    "iso:country":"US",
    "sg:address":"3662 Veteran Ave",
    "sg:city":"Los Angeles",
    "sg:classifiers":[
        {
            "category":"Professional",
            "type":"Services"
        },
        {
            "category":"Shopping",
            "subcategory":"Pets & Pet Supplies",
            "type":"Retail Goods"
        }
    ],
    "sg:phone":"+1 310 430 0531",
    "sg:postcode":"90034",
    "sg:province":"CA",
    "sg:website":"www.godscreaturespetsitting.com/",
    "wof:name":"Gods Creatures Pet Sitting",
    "wof:placetype":"venue"
},
  "geometry": {"coordinates":[-118.41419999999999,34.01816],"type":"Point"}
}