{
  "type": "Feature",
  "properties": {
    "iso:country":"US",
    "sg:address":"100 N Santa Cruz Ave",
    "sg:city":"Los Gatos",
    "sg:classifiers":[
        {
            "category":"Shopping",
            "subcategory":"Clothing, Apparel, & Fashions",
            "type":"Retail Goods"
        }
    ],
    "sg:phone":"+1 408 354 5666",
    "sg:postcode":"95030",
    "sg:province":"CA",
    "wof:name":"Leaf & Petal",
    "wof:placetype":"venue"
},
  "geometry": {"coordinates":[-121.98266,37.225159],"type":"Point"}
}