{
  "type": "Feature",
  "properties": {
    "iso:country":"US",
    "sg:address":"27309 Jefferson Ave",
    "sg:city":"Temecula",
    "sg:classifiers":[
        {
            "category":"Personal",
            "type":"Services"
        },
        {
            "category":"Sports & Exercise",
            "subcategory":"Gym",
            "type":"Entertainment"
        }
    ],
    "sg:phone":"+1 951 693 5124",
    "sg:postcode":"92562",
    "sg:province":"CA",
    "sg:tags":[
        "spa",
        "therapist",
        "health",
        "massage"
    ],
    "wof:name":"Escape Day Spa",
    "wof:placetype":"venue"
},
  "geometry": {"coordinates":[-117.168817,33.524406],"type":"Point"}
}