{
  "type": "Feature",
  "properties": {
    "addr:full":"514 Shatto Place Los Angeles CA 90020",
    "addr:housenumber":"514",
    "addr:postcode":"90020",
    "addr:street":"Shatto Place",
    "iso:country":"US",
    "sg:address":"514 Shatto Place",
    "sg:city":"Los Angeles",
    "sg:classifiers":[
        {
            "category":"Banks & Credit Unions",
            "subcategory":"Bank",
            "type":"Services"
        }
    ],
    "sg:phone":"+1 213 487 9887",
    "sg:postcode":"90020",
    "sg:province":"CA",
    "sg:website":"www.lacitycoalition.com",
    "wof:name":"Local 36",
    "wof:placetype":"venue"
},
  "geometry": {"coordinates":[-118.28991499999999,34.064964],"type":"Point"}
}