{
  "type": "Feature",
  "properties": {
    "iso:country":"US",
    "sg:address":"22996 el Toro Rd",
    "sg:city":"Lake Forest",
    "sg:classifiers":[
        {
            "category":"Building & Trades",
            "subcategory":"Construction",
            "type":"Services"
        }
    ],
    "sg:phone":"+1 949 837 7373",
    "sg:postcode":"92630",
    "sg:province":"CA",
    "sg:tags":[
        "home",
        "improvement"
    ],
    "wof:name":"Quality Home Improvements Inc",
    "wof:placetype":"venue"
},
  "geometry": {"coordinates":[-117.62810899999999,33.669998],"type":"Point"}
}