{
  "type": "Feature",
  "properties": {
    "iso:country":"US",
    "sg:address":"44 Montgomery St",
    "sg:city":"San Francisco",
    "sg:classifiers":[
        {
            "category":"Professional",
            "subcategory":"Lawyer & Legal Services",
            "type":"Services"
        }
    ],
    "sg:phone":"+1 415 362 9540",
    "sg:postcode":"94104",
    "sg:province":"CA",
    "wof:name":"Steffen Don Attorney At Law",
    "wof:placetype":"venue"
},
  "geometry": {"coordinates":[-122.402049,37.789642],"type":"Point"}
}