{
  "type": "Feature",
  "properties": {
    "iso:country":"US",
    "sg:address":"825 Post St",
    "sg:city":"San Francisco",
    "sg:classifiers":[
        {
            "category":"Real Estate",
            "subcategory":"Real Estate Operator",
            "type":"Services"
        }
    ],
    "sg:phone":"+1 415 673 6050",
    "sg:postcode":"94109",
    "sg:province":"CA",
    "sg:tags":[
        "apartment"
    ],
    "wof:name":"Matsonia Gardens Apartments",
    "wof:placetype":"venue"
},
  "geometry": {"coordinates":[-122.416309,37.787222],"type":"Point"}
}