{
  "type": "Feature",
  "properties": {
    "iso:country":"US",
    "sg:address":"727 Rock Springs Rd",
    "sg:city":"Escondido",
    "sg:classifiers":[
        {
            "category":"Retail",
            "subcategory":"Auto Repair",
            "type":"Services"
        }
    ],
    "sg:phone":"+1 760 743 5661",
    "sg:postcode":"92025",
    "sg:province":"CA",
    "sg:tags":[
        "body",
        "automobile",
        "painting"
    ],
    "wof:name":"Ah Racing",
    "wof:placetype":"venue"
},
  "geometry": {"coordinates":[-117.097673,33.127213],"type":"Point"}
}