{
  "type": "Feature",
  "properties": {
    "iso:country":"US",
    "sg:address":"2428 N Ontario St",
    "sg:city":"Burbank",
    "sg:classifiers":[
        {
            "category":"Wholesale",
            "subcategory":"Photographic Equipment",
            "type":"Manufacturing & Wholesale Goods"
        }
    ],
    "sg:phone":"+1 818 563 1000",
    "sg:postcode":"91504",
    "sg:province":"CA",
    "sg:tags":[
        "motion",
        "picture",
        "supply"
    ],
    "wof:name":"Sequoia Illumination",
    "wof:placetype":"venue"
},
  "geometry": {"coordinates":[-118.344398,34.196289],"type":"Point"}
}