{
  "type": "Feature",
  "properties": {
    "addr:full":"12131 Beach Blvd Stanton CA 90680",
    "addr:housenumber":"12131",
    "addr:postcode":"ca 90680",
    "addr:street":"Beach Blvd",
    "iso:country":"US",
    "sg:address":"12131 Beach Blvd",
    "sg:city":"Stanton",
    "sg:classifiers":[
        {
            "category":"Shopping",
            "subcategory":"Books",
            "type":"Retail Goods"
        }
    ],
    "sg:phone":"+1 714 891 2826",
    "sg:postcode":"90680",
    "sg:province":"CA",
    "sg:tags":[
        "dealer"
    ],
    "wof:name":"Crown Books Liquidation Ctr",
    "wof:placetype":"venue"
},
  "geometry": {"coordinates":[-117.992987,33.786278],"type":"Point"}
}