{
  "type": "Feature",
  "properties": {
    "addr:full":"4444 Viewridge Ave San Diego CA 92123",
    "addr:housenumber":"4444",
    "addr:postcode":"92123",
    "addr:street":"Viewridge Ave",
    "iso:country":"US",
    "sg:address":"4444 Viewridge Ave",
    "sg:city":"San Diego",
    "sg:classifiers":[
        {
            "category":"Banks & Credit Unions",
            "subcategory":"Financial Services",
            "type":"Services"
        },
        {
            "category":"Wholesale",
            "subcategory":"Chemicals & Plastics",
            "type":"Manufacturing & Wholesale Goods"
        }
    ],
    "sg:phone":"+1 858 565 4472",
    "sg:postcode":"92123",
    "sg:province":"CA",
    "sg:tags":[
        "product",
        "allied",
        "real estate",
        "trust",
        "investment"
    ],
    "sg:website":"www.merryxray.com",
    "wof:name":"Merry X-Ray Chemical Corp",
    "wof:placetype":"venue"
},
  "geometry": {"coordinates":[-117.124596,32.821133],"type":"Point"}
}