{
  "type": "Feature",
  "properties": {
    "addr:full":"2746 Judah St San Francisco CA 94122",
    "addr:housenumber":"2746",
    "addr:postcode":"94122",
    "addr:street":"Judah St",
    "iso:country":"US",
    "sg:address":"2746 Judah St",
    "sg:city":"San Francisco",
    "sg:classifiers":[
        {
            "category":"Personal",
            "subcategory":"Beauty Salon",
            "type":"Services"
        }
    ],
    "sg:phone":"+1 415 661 6866",
    "sg:postcode":"94122",
    "sg:province":"CA",
    "wof:name":"LA Rose Beauty Salon",
    "wof:placetype":"venue"
},
  "geometry": {"coordinates":[-122.491603,37.761137],"type":"Point"}
}