{
  "type": "Feature",
  "properties": {
    "iso:country":"US",
    "sg:address":"3414 Deer Valley Rd",
    "sg:city":"Antioch",
    "sg:classifiers":[
        {
            "category":"Real Estate",
            "subcategory":"Real Estate Agent",
            "type":"Services"
        }
    ],
    "sg:phone":"+1 925 777 9524",
    "sg:postcode":"94531",
    "sg:province":"CA",
    "wof:name":"Better Homes",
    "wof:placetype":"venue"
},
  "geometry": {"coordinates":[-121.785634,37.988302],"type":"Point"}
}