{
  "type": "Feature",
  "properties": {
    "addr:full":"2540 W Shaw Ln Fresno CA 93711",
    "addr:housenumber":"2540",
    "addr:postcode":"93711",
    "addr:street":"W Shaw Ln",
    "iso:country":"US",
    "sg:address":"2540 W Shaw Ln",
    "sg:city":"Fresno",
    "sg:classifiers":[
        {
            "category":"Professional",
            "subcategory":"Lawyer & Legal Services",
            "type":"Services"
        }
    ],
    "sg:phone":"+1 559 449 0571",
    "sg:postcode":"93711",
    "sg:province":"CA",
    "sg:tags":[
        "attorney"
    ],
    "wof:name":"Stammer Mc Knight Barnum",
    "wof:placetype":"venue"
},
  "geometry": {"coordinates":[-119.83832099999999,36.808554],"type":"Point"}
}