{
  "type": "Feature",
  "properties": {
    "addr:full":"967 Torrance Blvd Torrance CA 90502",
    "addr:housenumber":"967",
    "addr:postcode":"90502",
    "addr:street":"Torrance Blvd",
    "iso:country":"US",
    "sg:address":"967 Torrance Blvd",
    "sg:city":"Torrance",
    "sg:classifiers":[
        {
            "category":"Personal",
            "subcategory":"Barber",
            "type":"Services"
        }
    ],
    "sg:phone":"+1 310 532 8617",
    "sg:postcode":"90502",
    "sg:province":"CA",
    "wof:name":"Tony's Hair Cutting Co",
    "wof:placetype":"venue"
},
  "geometry": {"coordinates":[-118.292,33.8419],"type":"Point"}
}