{
  "type": "Feature",
  "properties": {
    "addr:full":"1321 G St Reedley CA 93654",
    "addr:housenumber":"1321",
    "addr:postcode":"93654",
    "addr:street":"G St",
    "iso:country":"US",
    "sg:address":"1321 G St",
    "sg:city":"Reedley",
    "sg:classifiers":[
        {
            "category":"Retail",
            "subcategory":"Auto Repair",
            "type":"Services"
        }
    ],
    "sg:phone":"+1 559 638 2110",
    "sg:postcode":"93654",
    "sg:province":"CA",
    "sg:tags":[
        "automobile",
        "top",
        "upholstery"
    ],
    "wof:name":"Powell's Custom Upholstery",
    "wof:placetype":"venue"
},
  "geometry": {"coordinates":[-119.447968,36.593538],"type":"Point"}
}