{
  "type": "Feature",
  "properties": {
    "addr:full":"11581 Faye Ave Garden Grove CA 92840",
    "addr:housenumber":"11581",
    "addr:postcode":"92840",
    "addr:street":"Faye Ave",
    "iso:country":"US",
    "sg:address":"11581 Faye Ave",
    "sg:city":"Garden Grove",
    "sg:classifiers":[
        {
            "category":"Building & Trades",
            "subcategory":"Plumbing",
            "type":"Services"
        }
    ],
    "sg:phone":"+1 714 637 1770",
    "sg:postcode":"92840",
    "sg:province":"CA",
    "wof:name":"Electronic Pipe Locators",
    "wof:placetype":"venue"
},
  "geometry": {"coordinates":[-117.95169300000001,33.794724],"type":"Point"}
}