{
  "type": "Feature",
  "properties": {
    "iso:country":"US",
    "sg:address":"2400 Valley Blvd",
    "sg:city":"Pomona",
    "sg:classifiers":[
        {
            "category":"Food & Beverages",
            "subcategory":"Groceries & Convenience Stores",
            "type":"Retail Goods"
        }
    ],
    "sg:phone":"+1 909 595 7914",
    "sg:postcode":"91768",
    "sg:province":"CA",
    "sg:tags":[
        "market"
    ],
    "wof:name":"Super West Market",
    "wof:placetype":"venue"
},
  "geometry": {"coordinates":[-117.799446,34.060608],"type":"Point"}
}