{
  "type": "Feature",
  "properties": {
    "addr:full":"1242 School St Stockton CA 95205",
    "addr:housenumber":"1242",
    "addr:postcode":"95205",
    "addr:street":"School St",
    "iso:country":"US",
    "sg:address":"1242 School St",
    "sg:city":"Stockton",
    "sg:classifiers":[
        {
            "category":"Home & Garden",
            "subcategory":"Household Appliances",
            "type":"Retail Goods"
        }
    ],
    "sg:phone":"+1 209 943 7022",
    "sg:postcode":"95205",
    "sg:province":"CA",
    "wof:name":"Jerry's Appliance & Repair",
    "wof:placetype":"venue"
},
  "geometry": {"coordinates":[-121.27420100000001,37.970609],"type":"Point"}
}