{
  "type": "Feature",
  "properties": {
    "iso:country":"US",
    "sg:address":"980 S Arroyo Pkwy Ste 250",
    "sg:city":"Pasadena",
    "sg:classifiers":[
        {
            "category":"Professional",
            "subcategory":"Lawyer & Legal Services",
            "type":"Services"
        }
    ],
    "sg:phone":"+1 626 405 0872",
    "sg:postcode":"91105",
    "sg:province":"CA",
    "wof:name":"Yan James Law Offices",
    "wof:placetype":"venue"
},
  "geometry": {"coordinates":[-118.147003,34.130001],"type":"Point"}
}