{
  "type": "Feature",
  "properties": {
    "addr:full":"1114 Blagen Rd Arnold CA 95223",
    "addr:housenumber":"1114",
    "addr:postcode":"95223",
    "addr:street":"Blagen Rd",
    "iso:country":"US",
    "sg:address":"1114 Blagen Rd",
    "sg:city":"Arnold",
    "sg:classifiers":[
        {
            "category":"Retail",
            "subcategory":"Veterinary Services",
            "type":"Services"
        }
    ],
    "sg:phone":"+1 209 795 4471",
    "sg:postcode":"95223",
    "sg:province":"CA",
    "sg:tags":[
        "hospital",
        "animal"
    ],
    "wof:name":"Arnold Pet Clinic",
    "wof:placetype":"venue"
},
  "geometry": {"coordinates":[-120.342026,38.262226],"type":"Point"}
}