{
  "type": "Feature",
  "properties": {
    "addr:full":"1820 P St Merced CA 95340",
    "addr:housenumber":"1820 p",
    "addr:postcode":"95340",
    "addr:street":"St",
    "iso:country":"US",
    "sg:address":"1820 P St",
    "sg:city":"Merced",
    "sg:classifiers":[
        {
            "category":"Professional",
            "subcategory":"Lawyer & Legal Services",
            "type":"Services"
        }
    ],
    "sg:phone":"+1 209 725 0211",
    "sg:postcode":"95340",
    "sg:province":"CA",
    "sg:tags":[
        "attorney"
    ],
    "wof:name":"Paul C Lo Law Offices",
    "wof:placetype":"venue"
},
  "geometry": {"coordinates":[-120.48827199999999,37.305407],"type":"Point"}
}