{
  "type": "Feature",
  "properties": {
    "addr:full":"103 East 17th St Suite 1 Costa Mesa CA 92627",
    "addr:housenumber":"103",
    "addr:postcode":"92627",
    "addr:street":"East 17Th St Suite 1",
    "iso:country":"US",
    "sg:address":"103 East 17th St Suite 1",
    "sg:city":"Costa Mesa",
    "sg:classifiers":[
        {
            "category":"Arena",
            "subcategory":"Sports Club",
            "type":"Entertainment"
        }
    ],
    "sg:phone":"+1 949 274 9859",
    "sg:postcode":"92627",
    "sg:province":"CA",
    "sg:tags":[
        "martial art"
    ],
    "sg:website":"laboxing7.reachlocal.com/coupon/...",
    "wof:name":"LA Boxing",
    "wof:placetype":"venue"
},
  "geometry": {"coordinates":[-117.922873,33.636162],"type":"Point"}
}