{
  "type": "Feature",
  "properties": {
    "iso:country":"US",
    "sg:address":"1350 Bayshore Hwy Suite 10",
    "sg:city":"Burlingame",
    "sg:classifiers":[
        {
            "category":"Restaurant",
            "type":"Food & Drink"
        }
    ],
    "sg:phone":"+1 650 343 8268",
    "sg:postcode":"94010",
    "sg:province":"CA",
    "wof:name":"Joan's Cafe",
    "wof:placetype":"venue"
},
  "geometry": {"coordinates":[-122.364666,37.594946],"type":"Point"}
}