{
  "type": "Feature",
  "properties": {
    "iso:country":"US",
    "sg:address":"7617 Malta Dr",
    "sg:city":"Roseville",
    "sg:classifiers":[
        {
            "category":"Arts & Performance",
            "subcategory":"Dance",
            "type":"Entertainment"
        }
    ],
    "sg:phone":"+1 916 773 0663",
    "sg:postcode":"95678",
    "sg:province":"CA",
    "sg:tags":[
        "instruction",
        "dancing"
    ],
    "wof:name":"Fontaine Dance",
    "wof:placetype":"venue"
},
  "geometry": {"coordinates":[-121.283114,38.794502],"type":"Point"}
}