{
  "type": "Feature",
  "properties": {
    "addr:full":"11046 Atlantic Avenue Lynwood CA 90262",
    "addr:housenumber":"11046",
    "addr:postcode":"90262",
    "addr:street":"Atlantic Avenue",
    "iso:country":"US",
    "sg:address":"11046 Atlantic Avenue",
    "sg:city":"Lynwood",
    "sg:classifiers":[
        {
            "category":"Building & Trades",
            "subcategory":"Locksmith",
            "type":"Services"
        }
    ],
    "sg:phone":"+1 310 639 3494",
    "sg:postcode":"90262",
    "sg:province":"CA",
    "sg:tags":[
        "key"
    ],
    "sg:website":"www.phillslocksmith.com",
    "wof:name":"Phill's Locksmith Service",
    "wof:placetype":"venue"
},
  "geometry": {"coordinates":[-118.1845,33.928648],"type":"Point"}
}