{
  "type": "Feature",
  "properties": {
    "addr:full":"20929 Ventura Blvd Ste 26 Woodland Hills CA 91364",
    "addr:housenumber":"20929",
    "addr:postcode":"91364",
    "addr:street":"Ventura Blvd Ste 26",
    "iso:country":"US",
    "sg:address":"20929 Ventura Blvd Ste 26",
    "sg:city":"Woodland Hills",
    "sg:classifiers":[
        {
            "category":"Arena",
            "subcategory":"Sports Club",
            "type":"Entertainment"
        }
    ],
    "sg:phone":"+1 818 992 6610",
    "sg:postcode":"91364",
    "sg:province":"CA",
    "sg:tags":[
        "martial art"
    ],
    "wof:name":"Kenpo Karate",
    "wof:placetype":"venue"
},
  "geometry": {"coordinates":[-118.58899700000001,34.1665],"type":"Point"}
}