{
  "type": "Feature",
  "properties": {
    "addr:full":"8600 Utica Ave Rancho Cucamonga CA 91730",
    "addr:housenumber":"8600",
    "addr:postcode":"91730",
    "addr:street":"Utica Ave",
    "iso:country":"US",
    "sg:address":"8600 Utica Ave",
    "sg:city":"Rancho Cucamonga",
    "sg:classifiers":[
        {
            "category":"Real Estate",
            "subcategory":"Real Estate Agent",
            "type":"Services"
        }
    ],
    "sg:phone":"+1 909 945 8576",
    "sg:postcode":"91730",
    "sg:province":"CA",
    "wof:name":"American Elite Properties",
    "wof:placetype":"venue"
},
  "geometry": {"coordinates":[-117.573015,34.097454],"type":"Point"}
}