{
  "type": "Feature",
  "properties": {
    "addr:full":"690 Pennsylvania Ave San Francisco CA 94107",
    "addr:housenumber":"690",
    "addr:postcode":"94107",
    "addr:street":"Pennsylvania Ave",
    "iso:country":"US",
    "sg:address":"690 Pennsylvania Ave",
    "sg:city":"San Francisco",
    "sg:classifiers":[
        {
            "category":"Wholesale",
            "subcategory":"Stationery",
            "type":"Manufacturing & Wholesale Goods"
        }
    ],
    "sg:phone":"+1 415 206 7224",
    "sg:postcode":"94107",
    "sg:province":"CA",
    "sg:tags":[
        "paper"
    ],
    "wof:name":"Rittenhouse Paper Co",
    "wof:placetype":"venue"
},
  "geometry": {"coordinates":[-122.39338100000001,37.760093],"type":"Point"}
}