{
  "type": "Feature",
  "properties": {
    "addr:full":"9912 Guinida Ln Anaheim CA 92804",
    "addr:housenumber":"9912",
    "addr:postcode":"92804",
    "addr:street":"Guinida Ln",
    "iso:country":"US",
    "sg:address":"9912 Guinida Ln",
    "sg:city":"Anaheim",
    "sg:classifiers":[
        {
            "category":"Building & Trades",
            "subcategory":"Landscaping Services",
            "type":"Services"
        }
    ],
    "sg:phone":"+1 714 999 6765",
    "sg:postcode":"92804",
    "sg:province":"CA",
    "sg:tags":[
        "landscape"
    ],
    "wof:name":"J Suarez Landscape",
    "wof:placetype":"venue"
},
  "geometry": {"coordinates":[-117.959379,33.814318],"type":"Point"}
}