{
  "type": "Feature",
  "properties": {
    "addr:full":"3366 W Pomona Blvd Pomona CA 91768",
    "addr:housenumber":"3366",
    "addr:postcode":"91768",
    "addr:street":"W Pomona Blvd",
    "iso:country":"US",
    "sg:address":"3366 W Pomona Blvd",
    "sg:city":"Pomona",
    "sg:classifiers":[
        {
            "category":"Manufacturing",
            "subcategory":"Tools & Machinery",
            "type":"Manufacturing & Wholesale Goods"
        }
    ],
    "sg:phone":"+1 909 598 0102",
    "sg:postcode":"91768",
    "sg:province":"CA",
    "sg:tags":[
        "photographic",
        "supply"
    ],
    "wof:name":"Global Aero Technology",
    "wof:placetype":"venue"
},
  "geometry": {"coordinates":[-117.809697,34.04794],"type":"Point"}
}