{
  "type": "Feature",
  "properties": {
    "iso:country":"US",
    "sg:address":"5131 Monetta Ln",
    "sg:city":"Sacramento",
    "sg:classifiers":[
        {
            "category":"Professional",
            "subcategory":"Computer Services",
            "type":"Services"
        }
    ],
    "sg:phone":"+1 916 419 9815",
    "sg:postcode":"95835",
    "sg:province":"CA",
    "sg:tags":[
        "home",
        "consulting",
        "page",
        "dev",
        "internet"
    ],
    "wof:name":"Webbeyondweb",
    "wof:placetype":"venue"
},
  "geometry": {"coordinates":[-121.547689,38.66409],"type":"Point"}
}