{
  "type": "Feature",
  "properties": {
    "iso:country":"US",
    "sg:address":"5014 Eagle Rock Blvd",
    "sg:city":"Los Angeles",
    "sg:classifiers":[
        {
            "category":"Home & Garden",
            "subcategory":"Carpets & Floor Coverings",
            "type":"Retail Goods"
        }
    ],
    "sg:phone":"+1 323 344 9327",
    "sg:postcode":"90041",
    "sg:province":"CA",
    "sg:tags":[
        "flooring"
    ],
    "wof:name":"Quality & Techniques Flooring",
    "wof:placetype":"venue"
},
  "geometry": {"coordinates":[-118.214115,34.13743],"type":"Point"}
}