{
  "type": "Feature",
  "properties": {
    "iso:country":"US",
    "sg:address":"16254 Ceres Ave",
    "sg:city":"Fontana",
    "sg:classifiers":[
        {
            "category":"Home & Garden",
            "subcategory":"Building Materials",
            "type":"Retail Goods"
        }
    ],
    "sg:phone":"+1 909 350 8090",
    "sg:postcode":"92335",
    "sg:province":"CA",
    "sg:tags":[
        "glass",
        "window",
        "plate"
    ],
    "wof:name":"Ultra Auto Glass",
    "wof:placetype":"venue"
},
  "geometry": {"coordinates":[-117.45209699999999,34.093896],"type":"Point"}
}