{
  "type": "Feature",
  "properties": {
    "addr:full":"11650 Iberia Pl San Diego CA 92128",
    "addr:housenumber":"11650",
    "addr:postcode":"92128",
    "addr:street":"Iberia Pl",
    "iso:country":"US",
    "sg:address":"11650 Iberia Pl",
    "sg:city":"San Diego",
    "sg:classifiers":[
        {
            "category":"Manufacturing",
            "subcategory":"Electronics",
            "type":"Manufacturing & Wholesale Goods"
        }
    ],
    "sg:phone":"+1 858 487 9340",
    "sg:postcode":"92128",
    "sg:province":"CA",
    "sg:tags":[
        "equipment",
        "electronic",
        "supply"
    ],
    "wof:name":"Kamaya Inc",
    "wof:placetype":"venue"
},
  "geometry": {"coordinates":[-117.077445,33.0155],"type":"Point"}
}