{
  "type": "Feature",
  "properties": {
    "iso:country":"US",
    "sg:address":"1102 Sanchez Street",
    "sg:city":"San Francisco",
    "sg:classifiers":[
        {
            "category":"Health Services",
            "subcategory":"Clinic",
            "type":"Services"
        }
    ],
    "sg:phone":"+1 415 282 0433",
    "sg:postcode":"94114",
    "sg:province":"CA",
    "sg:tags":[
        "counseling",
        "mental"
    ],
    "wof:name":"Aguilar Norma Lcsw",
    "wof:placetype":"venue"
},
  "geometry": {"coordinates":[-122.43000000000001,37.751301],"type":"Point"}
}