{
  "type": "Feature",
  "properties": {
    "iso:country":"US",
    "sg:address":"641 Sky Hy Cir",
    "sg:city":"Lafayette",
    "sg:classifiers":[
        {
            "category":"Food & Beverages",
            "subcategory":"Cheese",
            "type":"Retail Goods"
        }
    ],
    "sg:phone":"+1 925 284 4132",
    "sg:postcode":"94549",
    "sg:province":"CA",
    "wof:name":"Leonard M Saputo M D Inc",
    "wof:placetype":"venue"
},
  "geometry": {"coordinates":[-122.118736,37.87487],"type":"Point"}
}