{
  "type": "Feature",
  "properties": {
    "addr:full":"3565 17th St San Francisco CA 94110",
    "addr:housenumber":"3565",
    "addr:postcode":"94110",
    "addr:street":"17Th St",
    "iso:country":"US",
    "sg:address":"3565 17th St",
    "sg:city":"San Francisco",
    "sg:classifiers":[
        {
            "category":"Professional",
            "subcategory":"Management & Consulting",
            "type":"Services"
        }
    ],
    "sg:phone":"+1 415 522 4400",
    "sg:postcode":"94110",
    "sg:province":"CA",
    "sg:tags":[
        "consultant",
        "telephone"
    ],
    "wof:name":"T-Squared Networks",
    "wof:placetype":"venue"
},
  "geometry": {"coordinates":[-122.425678,37.762998],"type":"Point"}
}