{
  "type": "Feature",
  "properties": {
    "addr:full":"4579 Maple Ave Ste 4 La Mesa CA 91941",
    "addr:housenumber":"4579",
    "addr:postcode":"91941",
    "addr:street":"Maple Ave Ste 4",
    "iso:country":"US",
    "sg:address":"4579 Maple Ave Ste 4",
    "sg:city":"La Mesa",
    "sg:classifiers":[
        {
            "category":"Professional",
            "subcategory":"Lawyer & Legal Services",
            "type":"Services"
        }
    ],
    "sg:phone":"+1 619 667 3743",
    "sg:postcode":"91941",
    "sg:province":"CA",
    "wof:name":"Welch David Attorney At Law",
    "wof:placetype":"venue"
},
  "geometry": {"coordinates":[-117.029999,32.761799],"type":"Point"}
}