{
  "type": "Feature",
  "properties": {
    "addr:full":"4810 Telegraph Ave Oakland CA 94609",
    "addr:housenumber":"4810",
    "addr:postcode":"94609",
    "addr:street":"Telegraph Ave",
    "iso:country":"US",
    "sg:address":"4810 Telegraph Ave",
    "sg:city":"Oakland",
    "sg:classifiers":[
        {
            "category":"Shopping",
            "subcategory":"Jewelry",
            "type":"Retail Goods"
        },
        {
            "category":"Home & Garden",
            "subcategory":"Home Furnishings",
            "type":"Retail Goods"
        }
    ],
    "sg:phone":"+1 510 595 1669",
    "sg:postcode":"94609",
    "sg:province":"CA",
    "sg:tags":[
        "decor"
    ],
    "sg:website":"www.desaarts.com",
    "wof:name":"Desa Arts",
    "wof:placetype":"venue"
},
  "geometry": {"coordinates":[-122.262725,37.83498],"type":"Point"}
}