{
  "type": "Feature",
  "properties": {
    "iso:country":"US",
    "sg:address":"1201 Venice Blvd",
    "sg:city":"Los Angeles",
    "sg:classifiers":[
        {
            "category":"Restaurant",
            "type":"Food & Drink"
        }
    ],
    "sg:phone":"+1 213 380 0882",
    "sg:postcode":"90006",
    "sg:province":"CA",
    "sg:tags":[
        "out"
    ],
    "wof:name":"El Tapatio",
    "wof:placetype":"venue"
},
  "geometry": {"coordinates":[-118.28192799999999,34.042811],"type":"Point"}
}