{
  "type": "Feature",
  "properties": {
    "addr:full":"3101 Slaterfield Ave Bakersfield CA 93313",
    "addr:housenumber":"3101",
    "addr:postcode":"93313",
    "addr:street":"Slaterfield Ave",
    "iso:country":"US",
    "sg:address":"3101 Slaterfield Ave",
    "sg:city":"Bakersfield",
    "sg:classifiers":[
        {
            "category":"Health Services",
            "subcategory":"Doctor",
            "type":"Services"
        }
    ],
    "sg:phone":"+1 661 832 1476",
    "sg:postcode":"93313",
    "sg:province":"CA",
    "sg:tags":[
        "physician",
        "surgeon"
    ],
    "wof:name":"Singh A Jagtar Sole Prop",
    "wof:placetype":"venue"
},
  "geometry": {"coordinates":[-119.037324,35.28944],"type":"Point"}
}