{
  "type": "Feature",
  "properties": {
    "addr:full":"2359 Sunningdale Dr Tustin CA 92782",
    "addr:housenumber":"2359",
    "addr:postcode":"92782",
    "addr:street":"Sunningdale Dr",
    "iso:country":"US",
    "sg:address":"2359 Sunningdale Dr",
    "sg:city":"Tustin",
    "sg:classifiers":[
        {
            "category":"Autos & Motor Vehicles",
            "subcategory":"Fuel & Gas Station",
            "type":"Retail Goods"
        }
    ],
    "sg:phone":"+1 714 638 1410",
    "sg:postcode":"92782",
    "sg:province":"CA",
    "wof:name":"Garden Grove Shell No 1 Self Serve & Car Wash",
    "wof:placetype":"venue"
},
  "geometry": {"coordinates":[-117.791,33.738701],"type":"Point"}
}