{
  "type": "Feature",
  "properties": {
    "addr:full":"13 N School St Lodi CA 95240",
    "addr:housenumber":"13",
    "addr:postcode":"95240",
    "addr:street":"N School St",
    "iso:country":"US",
    "sg:address":"13 N School St",
    "sg:city":"Lodi",
    "sg:classifiers":[
        {
            "category":"Personal",
            "subcategory":"Beauty Salon",
            "type":"Services"
        }
    ],
    "sg:phone":"+1 209 365 7191",
    "sg:postcode":"95240",
    "sg:province":"CA",
    "wof:name":"My Little Sister's",
    "wof:placetype":"venue"
},
  "geometry": {"coordinates":[-121.27364799999999,38.13533],"type":"Point"}
}