{
  "type": "Feature",
  "properties": {
    "addr:full":"118 Las Tunas Dr Arcadia CA 91007",
    "addr:housenumber":"118",
    "addr:postcode":"91007",
    "addr:street":"Las Tunas Dr",
    "iso:country":"US",
    "sg:address":"118 Las Tunas Dr",
    "sg:city":"Arcadia",
    "sg:classifiers":[
        {
            "category":"Health Services",
            "subcategory":"Doctor",
            "type":"Services"
        }
    ],
    "sg:phone":"+1 626 821 6566",
    "sg:postcode":"91007",
    "sg:province":"CA",
    "sg:tags":[
        "dentist"
    ],
    "wof:name":"Nice Dental Ctr",
    "wof:placetype":"venue"
},
  "geometry": {"coordinates":[-118.035161,34.107675],"type":"Point"}
}