{
  "type": "Feature",
  "properties": {
    "addr:full":"146 W San Luis St Salinas CA 93901",
    "addr:housenumber":"146",
    "addr:postcode":"93901",
    "addr:street":"W San Luis St",
    "iso:country":"US",
    "sg:address":"146 W San Luis St",
    "sg:city":"Salinas",
    "sg:classifiers":[
        {
            "category":"Personal",
            "subcategory":"Beauty Salon",
            "type":"Services"
        }
    ],
    "sg:phone":"+1 831 753 7343",
    "sg:postcode":"93901",
    "sg:province":"CA",
    "wof:name":"Skin Care By Kristi",
    "wof:placetype":"venue"
},
  "geometry": {"coordinates":[-121.65788499999999,36.671624],"type":"Point"}
}