{
  "type": "Feature",
  "properties": {
    "iso:country":"US",
    "sg:address":"720 Cam de la Reina",
    "sg:city":"San Diego",
    "sg:classifiers":[
        {
            "category":"Freight",
            "type":"Transportation"
        },
        {
            "category":"Local Transit",
            "type":"Transportation"
        }
    ],
    "sg:phone":"+1 619 297 6666",
    "sg:postcode":"92108",
    "sg:province":"CA",
    "sg:tags":[
        "limousine"
    ],
    "wof:name":"Del Mar Transportation",
    "wof:placetype":"venue"
},
  "geometry": {"coordinates":[-117.15573000000001,32.767708],"type":"Point"}
}