{
  "type": "Feature",
  "properties": {
    "iso:country":"US",
    "sg:address":"805 W Avenue I L8 L8 Unit P",
    "sg:city":"Lancaster",
    "sg:classifiers":[
        {
            "category":"Wholesale",
            "subcategory":"Medical Equipment & Supplies",
            "type":"Manufacturing & Wholesale Goods"
        },
        {
            "category":"Health Services",
            "subcategory":"Hospital",
            "type":"Services"
        },
        {
            "category":"Shopping",
            "subcategory":"Pharmacy",
            "type":"Retail Goods"
        }
    ],
    "sg:phone":"+1 661 726 5970",
    "sg:postcode":"93534",
    "sg:province":"CA",
    "sg:tags":[
        "home",
        "care"
    ],
    "wof:name":"Ability Medical Supplies",
    "wof:placetype":"venue"
},
  "geometry": {"coordinates":[-118.145708,34.703942],"type":"Point"}
}