{
  "type": "Feature",
  "properties": {
    "addr:full":"501 29th St Newport Beach CA 92663",
    "addr:housenumber":"501",
    "addr:postcode":"92663",
    "addr:street":"29Th St",
    "iso:country":"US",
    "sg:address":"501 29th St",
    "sg:city":"Newport Beach",
    "sg:classifiers":[
        {
            "category":"Wholesale",
            "subcategory":"Sporting Goods",
            "type":"Manufacturing & Wholesale Goods"
        }
    ],
    "sg:phone":"+1 949 675 8797",
    "sg:postcode":"92663",
    "sg:province":"CA",
    "wof:name":"Pacific Pro",
    "wof:placetype":"venue"
},
  "geometry": {"coordinates":[-117.927879,33.614007],"type":"Point"}
}