{
  "type": "Feature",
  "properties": {
    "iso:country":"US",
    "sg:address":"1665 3rd St",
    "sg:city":"Norco",
    "sg:classifiers":[
        {
            "category":"Insurance",
            "subcategory":"Insurance Agent",
            "type":"Services"
        }
    ],
    "sg:phone":"+1 951 737 2682",
    "sg:postcode":"92860",
    "sg:province":"CA",
    "wof:name":"Louis Grande Insurance",
    "wof:placetype":"venue"
},
  "geometry": {"coordinates":[-117.55797,33.916631],"type":"Point"}
}