{
  "type": "Feature",
  "properties": {
    "addr:full":"27929 Cougar Pass Rd Escondido CA 92026",
    "addr:housenumber":"27929",
    "addr:postcode":"92026",
    "addr:street":"Cougar Pass Rd",
    "iso:country":"US",
    "sg:address":"27929 Cougar Pass Rd",
    "sg:city":"Escondido",
    "sg:classifiers":[
        {
            "category":"Restaurant",
            "type":"Food & Drink"
        }
    ],
    "sg:phone":"+1 760 751 7335",
    "sg:postcode":"92026",
    "sg:province":"CA",
    "sg:tags":[
        "eating"
    ],
    "wof:name":"Tri Nguym",
    "wof:placetype":"venue"
},
  "geometry": {"coordinates":[-117.090109,33.218991],"type":"Point"}
}