{
  "type": "Feature",
  "properties": {
    "iso:country":"US",
    "sg:address":"319 8th Ave",
    "sg:city":"San Francisco",
    "sg:classifiers":[
        {
            "category":"Health Services",
            "subcategory":"Doctor",
            "type":"Services"
        }
    ],
    "sg:phone":"+1 415 387 0123",
    "sg:postcode":"94118",
    "sg:province":"CA",
    "sg:tags":[
        "dentist"
    ],
    "wof:name":"Starfleet Dental",
    "wof:placetype":"venue"
},
  "geometry": {"coordinates":[-122.466522,37.781274],"type":"Point"}
}