{
  "type": "Feature",
  "properties": {
    "addr:full":"2222 Vierra Rd Lathrop CA 95330",
    "addr:housenumber":"2222",
    "addr:postcode":"95330",
    "addr:street":"Vierra Rd",
    "iso:country":"US",
    "sg:address":"2222 Vierra Rd",
    "sg:city":"Lathrop",
    "sg:classifiers":[
        {
            "category":"Building & Trades",
            "subcategory":"Construction",
            "type":"Services"
        }
    ],
    "sg:phone":"+1 209 858 2921",
    "sg:postcode":"95330",
    "sg:province":"CA",
    "sg:tags":[
        "roofing",
        "contractor"
    ],
    "wof:name":"R & R Roofing",
    "wof:placetype":"venue"
},
  "geometry": {"coordinates":[-121.277022,37.7972],"type":"Point"}
}