{
  "type": "Feature",
  "properties": {
    "addr:full":"2995 Tuers Rd San Jose CA 95121",
    "addr:housenumber":"2995",
    "addr:postcode":"95121",
    "addr:street":"Tuers Rd",
    "iso:country":"US",
    "sg:address":"2995 Tuers Rd",
    "sg:city":"San Jose",
    "sg:classifiers":[
        {
            "category":"Sports & Exercise",
            "subcategory":"Golf",
            "type":"Entertainment"
        }
    ],
    "sg:phone":"+1 408 361 0250",
    "sg:postcode":"95121",
    "sg:province":"CA",
    "sg:tags":[
        "course"
    ],
    "sg:website":"www.playloslagos.com",
    "wof:name":"Los Lagos Golf Course",
    "wof:placetype":"venue"
},
  "geometry": {"coordinates":[-121.828003,37.303001],"type":"Point"}
}