{
  "type": "Feature",
  "properties": {
    "iso:country":"US",
    "sg:address":"9530 Cozycroft Ave",
    "sg:city":"Chatsworth",
    "sg:classifiers":[
        {
            "category":"Professional",
            "subcategory":"Advertising",
            "type":"Services"
        }
    ],
    "sg:phone":"+1 818 734 1661",
    "sg:postcode":"91311",
    "sg:province":"CA",
    "sg:tags":[
        "designer",
        "display",
        "producer"
    ],
    "sg:website":"www.tradeshowimages.com",
    "wof:name":"Trade Show Images",
    "wof:placetype":"venue"
},
  "geometry": {"coordinates":[-118.581906,34.245806],"type":"Point"}
}