{
  "type": "Feature",
  "properties": {
    "addr:full":"281 Tank Farm Rd San Luis Obispo CA 93401",
    "addr:housenumber":"281",
    "addr:postcode":"93401",
    "addr:street":"Tank Farm Rd",
    "iso:country":"US",
    "sg:address":"281 Tank Farm Rd",
    "sg:city":"San Luis Obispo",
    "sg:classifiers":[
        {
            "category":"Autos & Motor Vehicles",
            "subcategory":"Auto Supplies",
            "type":"Retail Goods"
        }
    ],
    "sg:phone":"+1 805 543 9509",
    "sg:postcode":"93401",
    "sg:province":"CA",
    "sg:tags":[
        "automobile",
        "parts"
    ],
    "sg:website":"www.sanluisautosalvage.com",
    "wof:name":"San Luis Auto Salvage",
    "wof:placetype":"venue"
},
  "geometry": {"coordinates":[-120.664936,35.246729],"type":"Point"}
}