{
  "type": "Feature",
  "properties": {
    "addr:full":"444 Manor Plz Pacifica CA 94044",
    "addr:housenumber":"444",
    "addr:postcode":"94044",
    "addr:street":"Manor Plz",
    "iso:country":"US",
    "sg:address":"444 Manor Plz",
    "sg:city":"Pacifica",
    "sg:classifiers":[
        {
            "category":"Shopping",
            "subcategory":"Music",
            "type":"Retail Goods"
        }
    ],
    "sg:phone":"+1 650 355 7587",
    "sg:postcode":"94044",
    "sg:province":"CA",
    "sg:tags":[
        "video",
        "disc",
        "tape",
        "cassette"
    ],
    "sg:website":"www.video-plus.com",
    "wof:name":"Video Plus",
    "wof:placetype":"venue"
},
  "geometry": {"coordinates":[-122.491265,37.650291],"type":"Point"}
}