{
  "type": "Feature",
  "properties": {
    "addr:full":"4341 El Cajon Blvd San Diego CA 92105",
    "addr:housenumber":"4341",
    "addr:postcode":"92105",
    "addr:street":"El Cajon Blvd",
    "iso:country":"US",
    "sg:address":"4341 El Cajon Blvd",
    "sg:city":"San Diego",
    "sg:classifiers":[
        {
            "category":"Health Services",
            "subcategory":"Hospital",
            "type":"Services"
        },
        {
            "category":"Shopping",
            "subcategory":"Used Merchandise",
            "type":"Retail Goods"
        }
    ],
    "sg:phone":"+1 619 285 9014",
    "sg:postcode":"92105",
    "sg:province":"CA",
    "sg:tags":[
        "vintage",
        "consignment"
    ],
    "wof:name":"Children's Hospital and Health Center",
    "wof:placetype":"venue"
},
  "geometry": {"coordinates":[-117.100998,32.7551],"type":"Point"}
}