{
  "type": "Feature",
  "properties": {
    "iso:country":"US",
    "sg:address":"132 E 4th St",
    "sg:city":"Los Angeles",
    "sg:classifiers":[
        {
            "category":"Recreation",
            "type":"Entertainment"
        }
    ],
    "sg:phone":"+1 213 972 9145",
    "sg:postcode":"90013",
    "sg:province":"CA",
    "sg:tags":[
        "spa",
        "house",
        "sauna",
        "bath"
    ],
    "wof:name":"KLYT Bath House",
    "wof:placetype":"venue"
},
  "geometry": {"coordinates":[-118.246326,34.047289],"type":"Point"}
}