{
  "type": "Feature",
  "properties": {
    "iso:country":"US",
    "sg:address":"5625 Hollywood Blvd",
    "sg:city":"Los Angeles",
    "sg:classifiers":[
        {
            "category":"Travel",
            "subcategory":"Hotels & Motels",
            "type":"Entertainment"
        }
    ],
    "sg:phone":"+1 323 466 0542",
    "sg:postcode":"90028",
    "sg:province":"CA",
    "sg:website":"www.ichotelsgroup.com/h/d/ex/1/e...",
    "wof:name":"Holiday Inn Express",
    "wof:placetype":"venue"
},
  "geometry": {"coordinates":[-118.311996,34.101601],"type":"Point"}
}