{
  "type": "Feature",
  "properties": {
    "iso:country":"US",
    "sg:address":"611 Hampton Rd",
    "sg:city":"Arcadia",
    "sg:classifiers":[
        {
            "category":"Organizations",
            "subcategory":"Religious Organization",
            "type":"Services"
        }
    ],
    "sg:phone":"+1 626 355 4197",
    "sg:postcode":"91006",
    "sg:province":"CA",
    "sg:website":"www.urantiagroup.com",
    "wof:name":"Urantia Study Group",
    "wof:placetype":"venue"
},
  "geometry": {"coordinates":[-118.115235,34.152201],"type":"Point"}
}