{
  "type": "Feature",
  "properties": {
    "addr:full":"7681 Santa Catalina Ave Stanton CA 90680",
    "addr:housenumber":"7681",
    "addr:postcode":"ca 90680",
    "addr:street":"Santa Catalina Ave",
    "iso:country":"US",
    "sg:address":"7681 Santa Catalina Ave",
    "sg:city":"Stanton",
    "sg:classifiers":[
        {
            "category":"Retail",
            "subcategory":"Auto Repair",
            "type":"Services"
        }
    ],
    "sg:phone":"+1 714 897 0819",
    "sg:postcode":"90680",
    "sg:province":"CA",
    "sg:tags":[
        "wrecker"
    ],
    "wof:name":"Kim's Towing Svc",
    "wof:placetype":"venue"
},
  "geometry": {"coordinates":[-117.997541,33.791938],"type":"Point"}
}