{
  "type": "Feature",
  "properties": {
    "addr:full":"1331 S Harbor Blvd Fullerton CA 92832",
    "addr:housenumber":"1331",
    "addr:postcode":"92832",
    "addr:street":"S Harbor Blvd",
    "iso:country":"US",
    "sg:address":"1331 S Harbor Blvd",
    "sg:city":"Fullerton",
    "sg:classifiers":[
        {
            "category":"Shopping",
            "subcategory":"Department Store",
            "type":"Retail Goods"
        }
    ],
    "sg:phone":"+1 714 773 6266",
    "sg:postcode":"92832",
    "sg:province":"CA",
    "sg:website":"http://www.wards.com",
    "wof:name":"Wards",
    "wof:placetype":"venue"
},
  "geometry": {"coordinates":[-117.924375,33.859022],"type":"Point"}
}