{
  "type": "Feature",
  "properties": {
    "addr:full":"499 N Canon Dr Beverly Hills CA 90210",
    "addr:housenumber":"499",
    "addr:postcode":"90210",
    "addr:street":"N Canon Dr",
    "iso:country":"US",
    "sg:address":"499 N Canon Dr",
    "sg:city":"Beverly Hills",
    "sg:classifiers":[
        {
            "category":"Real Estate",
            "subcategory":"Real Estate Operator",
            "type":"Services"
        }
    ],
    "sg:phone":"+1 310 887 7000",
    "sg:postcode":"90210",
    "sg:province":"CA",
    "sg:tags":[
        "suite",
        "executive"
    ],
    "wof:name":"Barrister Executive Suites",
    "wof:placetype":"venue"
},
  "geometry": {"coordinates":[-118.402536,34.072267],"type":"Point"}
}