{
  "type": "Feature",
  "properties": {
    "addr:full":"734 Chestnut St Santa Cruz CA 95060",
    "addr:housenumber":"734",
    "addr:postcode":"95060",
    "addr:street":"Chestnut St",
    "iso:country":"US",
    "sg:address":"734 Chestnut St",
    "sg:city":"Santa Cruz",
    "sg:classifiers":[
        {
            "category":"Professional",
            "subcategory":"Engineering",
            "type":"Services"
        }
    ],
    "sg:phone":"+1 831 423 4184",
    "sg:postcode":"95060",
    "sg:province":"CA",
    "sg:tags":[
        "engineer"
    ],
    "wof:name":"Minardi Engineering",
    "wof:placetype":"venue"
},
  "geometry": {"coordinates":[-122.028417,36.976312],"type":"Point"}
}