{
  "type": "Feature",
  "properties": {
    "iso:country":"US",
    "sg:address":"13629 Fanshaw Ave",
    "sg:city":"Paramount",
    "sg:classifiers":[
        {
            "category":"Professional",
            "type":"Services"
        }
    ],
    "sg:phone":"+1 562 531 8073",
    "sg:postcode":"90723",
    "sg:province":"CA",
    "wof:name":"Anita Products",
    "wof:placetype":"venue"
},
  "geometry": {"coordinates":[-118.153651,33.908137],"type":"Point"}
}