{
  "type": "Feature",
  "properties": {
    "addr:full":"5732 Pacheco Ln Paradise CA 95969",
    "addr:housenumber":"5732",
    "addr:postcode":"95969",
    "addr:street":"Pacheco Ln",
    "iso:country":"US",
    "sg:address":"5732 Pacheco Ln",
    "sg:city":"Paradise",
    "sg:classifiers":[
        {
            "category":"Building & Trades",
            "subcategory":"Plumbing",
            "type":"Services"
        }
    ],
    "sg:phone":"+1 530 877 8064",
    "sg:postcode":"95969",
    "sg:province":"CA",
    "sg:tags":[
        "tank",
        "septic"
    ],
    "wof:name":"Don Ashbaugh's Septic",
    "wof:placetype":"venue"
},
  "geometry": {"coordinates":[-121.598001,39.755389],"type":"Point"}
}