{
  "type": "Feature",
  "properties": {
    "addr:full":"1319 Sunny Court San Jose CA 95116",
    "addr:housenumber":"1319",
    "addr:postcode":"95116",
    "addr:street":"Sunny Court",
    "iso:country":"US",
    "sg:address":"1319 Sunny Court",
    "sg:city":"San Jose",
    "sg:classifiers":[
        {
            "category":"Real Estate",
            "subcategory":"Real Estate Operator",
            "type":"Services"
        }
    ],
    "sg:phone":"+1 408 294 2813",
    "sg:postcode":"95116",
    "sg:province":"CA",
    "sg:tags":[
        "apartment"
    ],
    "sg:website":"www.NowForRent.com",
    "wof:name":"Sunny Court Apartments",
    "wof:placetype":"venue"
},
  "geometry": {"coordinates":[-121.859128,37.341886],"type":"Point"}
}