{
  "type": "Feature",
  "properties": {
    "addr:full":"3860 Hunters Grove Ct Moorpark CA 93021",
    "addr:housenumber":"3860",
    "addr:postcode":"ca 93021",
    "addr:street":"Hunters Grove Ct",
    "iso:country":"US",
    "sg:address":"3860 Hunters Grove Ct",
    "sg:city":"Moorpark",
    "sg:classifiers":[
        {
            "category":"Professional",
            "subcategory":"Management & Consulting",
            "type":"Services"
        }
    ],
    "sg:phone":"+1 805 552 0745",
    "sg:postcode":"93021",
    "sg:province":"CA",
    "sg:tags":[
        "consultant",
        "educational"
    ],
    "sg:website":"www.servicelearningadventures.com",
    "wof:name":"Service Learning Ctr",
    "wof:placetype":"venue"
},
  "geometry": {"coordinates":[-118.886303,34.261743],"type":"Point"}
}