{
  "type": "Feature",
  "properties": {
    "addr:full":"20948 Corsair Blvd Hayward CA 94545",
    "addr:postcode":"20948;94545",
    "addr:street":"Corsair Blvd",
    "iso:country":"US",
    "sg:address":"20948 Corsair Blvd",
    "sg:city":"Hayward",
    "sg:classifiers":[
        {
            "category":"Shopping",
            "subcategory":"Used Merchandise",
            "type":"Retail Goods"
        }
    ],
    "sg:phone":"+1 510 783 8200",
    "sg:postcode":"94545",
    "sg:province":"CA",
    "wof:name":"Century Treasure Trading Inc",
    "wof:placetype":"venue"
},
  "geometry": {"coordinates":[-122.127726,37.658216],"type":"Point"}
}