{
  "type": "Feature",
  "properties": {
    "addr:full":"1224 31st Ave San Francisco CA 94122",
    "addr:housenumber":"1224",
    "addr:postcode":"94122",
    "addr:street":"31St Ave",
    "iso:country":"US",
    "sg:address":"1224 31st Ave",
    "sg:city":"San Francisco",
    "sg:classifiers":[
        {
            "category":"Freight",
            "type":"Transportation"
        }
    ],
    "sg:phone":"+1 415 753 3224",
    "sg:postcode":"94122",
    "sg:province":"CA",
    "sg:tags":[
        "operator",
        "trucking"
    ],
    "wof:name":"C C & Sons Trucking",
    "wof:placetype":"venue"
},
  "geometry": {"coordinates":[-122.489935,37.763461],"type":"Point"}
}