{
  "type": "Feature",
  "properties": {
    "iso:country":"US",
    "sg:address":"3950 Atlantic Ave",
    "sg:city":"Long Beach",
    "sg:classifiers":[
        {
            "category":"Banks & Credit Unions",
            "subcategory":"Investment Brokerage",
            "type":"Services"
        }
    ],
    "sg:phone":"+1 562 426 5068",
    "sg:postcode":"90807",
    "sg:province":"CA",
    "sg:tags":[
        "advisory",
        "financial"
    ],
    "wof:name":"Stagecoach Financial",
    "wof:placetype":"venue"
},
  "geometry": {"coordinates":[-118.184924,33.829845],"type":"Point"}
}