{
  "type": "Feature",
  "properties": {
    "iso:country":"US",
    "sg:address":"4111 N Blythe Ave",
    "sg:city":"Fresno",
    "sg:classifiers":[
        {
            "category":"Freight",
            "type":"Transportation"
        }
    ],
    "sg:phone":"+1 559 271 1812",
    "sg:postcode":"93722",
    "sg:province":"CA",
    "wof:name":"Baines Transport 126",
    "wof:placetype":"venue"
},
  "geometry": {"coordinates":[-119.87143,36.794666],"type":"Point"}
}