{
  "type": "Feature",
  "properties": {
    "addr:full":"23460 Cinema Dr Ste E Valencia CA 91355",
    "addr:housenumber":"23460",
    "addr:postcode":"91355",
    "addr:street":"Cinema Dr Ste E",
    "iso:country":"US",
    "sg:address":"23460 Cinema Dr Ste E",
    "sg:city":"Valencia",
    "sg:classifiers":[
        {
            "category":"Personal",
            "subcategory":"Nail Salon",
            "type":"Services"
        }
    ],
    "sg:phone":"+1 661 284 3400",
    "sg:postcode":"91355",
    "sg:province":"CA",
    "wof:name":"Hair Pro Beauty Salon",
    "wof:placetype":"venue"
},
  "geometry": {"coordinates":[-118.54499800000001,34.419899],"type":"Point"}
}