{
  "type": "Feature",
  "properties": {
    "iso:country":"US",
    "sg:address":"3934 Coronado Ave",
    "sg:city":"Stockton",
    "sg:classifiers":[
        {
            "category":"Professional",
            "type":"Services"
        }
    ],
    "sg:phone":"+1 209 547 1773",
    "sg:postcode":"95204",
    "sg:province":"CA",
    "wof:name":"John Galbraith",
    "wof:placetype":"venue"
},
  "geometry": {"coordinates":[-121.288093,37.98762],"type":"Point"}
}