{
  "type": "Feature",
  "properties": {
    "addr:full":"9808 Venice Blvd Ste 200 Culver City CA 90232",
    "addr:housenumber":"9808",
    "addr:postcode":"90232",
    "addr:street":"Venice Blvd Ste 200",
    "iso:country":"US",
    "sg:address":"9808 Venice Blvd Ste 200",
    "sg:city":"Culver City",
    "sg:classifiers":[
        {
            "category":"Health Services",
            "subcategory":"Doctor",
            "type":"Services"
        }
    ],
    "sg:phone":"+1 310 287 4000",
    "sg:postcode":"90232",
    "sg:province":"CA",
    "wof:name":"Western Imaging Mri",
    "wof:placetype":"venue"
},
  "geometry": {"coordinates":[-118.398003,34.023701],"type":"Point"}
}