{
  "type": "Feature",
  "properties": {
    "iso:country":"US",
    "sg:address":"555 E Tachevah Dr",
    "sg:city":"Palm Springs",
    "sg:classifiers":[
        {
            "category":"Health Services",
            "subcategory":"Optometrist",
            "type":"Services"
        }
    ],
    "sg:phone":"+1 760 327 1561",
    "sg:postcode":"92262",
    "sg:province":"CA",
    "sg:tags":[
        "ophthalmologist"
    ],
    "sg:website":"www.milauskas-eye.com",
    "wof:name":"Kim John MD",
    "wof:placetype":"venue"
},
  "geometry": {"coordinates":[-116.542,33.837601],"type":"Point"}
}