{
  "type": "Feature",
  "properties": {
    "iso:country":"US",
    "sg:address":"18080 Chatsworth St",
    "sg:city":"Granada Hills",
    "sg:classifiers":[
        {
            "category":"Restaurant",
            "type":"Food & Drink"
        }
    ],
    "sg:menulink":"http://www.allmenus.com/ca/san-fernando-valley/239875-panda-express/menu/",
    "sg:phone":"+1 818 366 8632",
    "sg:postcode":"91344",
    "sg:province":"CA",
    "sg:tags":[
        "asian",
        "chinese"
    ],
    "wof:name":"Panda Express",
    "wof:placetype":"venue"
},
  "geometry": {"coordinates":[-118.525775,34.264536],"type":"Point"}
}