{
  "type": "Feature",
  "properties": {
    "iso:country":"US",
    "sg:address":"301 E Alisal St",
    "sg:city":"Salinas",
    "sg:classifiers":[
        {
            "category":"Restaurant",
            "type":"Food & Drink"
        }
    ],
    "sg:phone":"+1 831 757 4540",
    "sg:postcode":"93901",
    "sg:province":"CA",
    "wof:name":"Don Pepe Taqueria",
    "wof:placetype":"venue"
},
  "geometry": {"coordinates":[-121.64536,36.674714],"type":"Point"}
}