{
  "type": "Feature",
  "properties": {
    "addr:full":"560 1st St Benicia CA 94510",
    "addr:housenumber":"560",
    "addr:postcode":"94510",
    "addr:street":"1St St",
    "iso:country":"US",
    "sg:address":"560 1st St",
    "sg:city":"Benicia",
    "sg:classifiers":[
        {
            "category":"Shopping",
            "type":"Retail Goods"
        }
    ],
    "sg:phone":"+1 707 748 1248",
    "sg:postcode":"94510",
    "sg:province":"CA",
    "sg:tags":[
        "item",
        "boutique"
    ],
    "wof:name":"The Honey Mill Artisans Studio Boutique",
    "wof:placetype":"venue"
},
  "geometry": {"coordinates":[-122.159413,38.048637],"type":"Point"}
}