{
  "type": "Feature",
  "properties": {
    "addr:full":"115 S Doheny Dr West Hollywood CA 90048",
    "addr:housenumber":"115",
    "addr:postcode":"90048",
    "addr:street":"S Doheny Dr",
    "iso:country":"US",
    "sg:address":"115 S Doheny Dr",
    "sg:city":"West Hollywood",
    "sg:classifiers":[
        {
            "category":"Shopping",
            "subcategory":"Gifts & Souvenirs",
            "type":"Retail Goods"
        }
    ],
    "sg:phone":"+1 310 858 0017",
    "sg:postcode":"90048",
    "sg:province":"CA",
    "sg:tags":[
        "shop"
    ],
    "wof:name":"Be Brazil",
    "wof:placetype":"venue"
},
  "geometry": {"coordinates":[-118.389802,34.073718],"type":"Point"}
}