{
  "type": "Feature",
  "properties": {
    "iso:country":"US",
    "sg:address":"8495 W 3rd St",
    "sg:city":"Los Angeles",
    "sg:classifiers":[
        {
            "category":"Shopping",
            "type":"Retail Goods"
        }
    ],
    "sg:phone":"+1 310 659 0775",
    "sg:postcode":"90048",
    "sg:province":"CA",
    "sg:tags":[
        "mobile",
        "phone",
        "telephone",
        "cellular"
    ],
    "wof:name":"Verizon Wireless",
    "wof:placetype":"venue"
},
  "geometry": {"coordinates":[-118.37599899999999,34.073399],"type":"Point"}
}