{
  "type": "Feature",
  "properties": {
    "iso:country":"US",
    "sg:address":"1711 Whittier Ave",
    "sg:city":"Costa Mesa",
    "sg:classifiers":[
        {
            "category":"Manufacturing",
            "subcategory":"Electronics",
            "type":"Manufacturing & Wholesale Goods"
        }
    ],
    "sg:phone":"+1 949 646 7292",
    "sg:postcode":"92627",
    "sg:province":"CA",
    "sg:tags":[
        "telephone",
        "apparatus",
        "telegraph"
    ],
    "sg:website":"www.supply.com",
    "wof:name":"Supply Technology",
    "wof:placetype":"venue"
},
  "geometry": {"coordinates":[-117.940657,33.637363],"type":"Point"}
}