{
  "type": "Feature",
  "properties": {
    "iso:country":"US",
    "sg:address":"25691 Atlantic Ocean Dr",
    "sg:city":"Lake Forest",
    "sg:classifiers":[
        {
            "category":"Real Estate",
            "subcategory":"Architect",
            "type":"Services"
        }
    ],
    "sg:phone":"+1 949 598 9544",
    "sg:postcode":"92630",
    "sg:province":"CA",
    "sg:website":"www.studioiv.com",
    "wof:name":"Studio IV",
    "wof:placetype":"venue"
},
  "geometry": {"coordinates":[-117.681999,33.666599],"type":"Point"}
}