{
  "type": "Feature",
  "properties": {
    "addr:full":"95 San Carlos Way Novato CA 94945",
    "addr:housenumber":"95",
    "addr:postcode":"94945",
    "addr:street":"San Carlos Way",
    "iso:country":"US",
    "sg:address":"95 San Carlos Way",
    "sg:city":"Novato",
    "sg:classifiers":[
        {
            "category":"Manufacturing",
            "subcategory":"Tools & Machinery",
            "type":"Manufacturing & Wholesale Goods"
        }
    ],
    "sg:phone":"+1 415 898 9848",
    "sg:postcode":"94945",
    "sg:province":"CA",
    "sg:tags":[
        "equipment",
        "peripheral",
        "computer",
        "business",
        "mfg"
    ],
    "wof:name":"Concepts By Design",
    "wof:placetype":"venue"
},
  "geometry": {"coordinates":[-122.608858,38.118905],"type":"Point"}
}