{
  "type": "Feature",
  "properties": {
    "addr:full":"1300 8th St Alameda CA 94501",
    "addr:housenumber":"1300",
    "addr:postcode":"94501",
    "addr:street":"8Th St",
    "iso:country":"US",
    "sg:address":"1300 8th St",
    "sg:city":"Alameda",
    "sg:classifiers":[
        {
            "category":"Landmark",
            "subcategory":"Historic",
            "type":"Public Place"
        }
    ],
    "sg:phone":"+1 510 747 7529",
    "sg:postcode":"94501",
    "sg:province":"CA",
    "sg:tags":[
        "building",
        "historical"
    ],
    "wof:name":"Lower Washington Park Tennis Courts",
    "wof:placetype":"venue"
},
  "geometry": {"coordinates":[-122.272865,37.769311],"type":"Point"}
}