{
  "type": "Feature",
  "properties": {
    "iso:country":"US",
    "sg:address":"1240 E 230th St",
    "sg:city":"Carson",
    "sg:classifiers":[
        {
            "category":"Freight",
            "type":"Transportation"
        }
    ],
    "sg:phone":"+1 310 522 7101",
    "sg:postcode":"90745",
    "sg:province":"CA",
    "sg:tags":[
        "photocopying",
        "arrangement"
    ],
    "wof:name":"Vidco-Lax",
    "wof:placetype":"venue"
},
  "geometry": {"coordinates":[-118.250799,33.817134],"type":"Point"}
}