{
  "type": "Feature",
  "properties": {
    "iso:country":"US",
    "sg:address":"4992 Windsor Blvd",
    "sg:city":"Cambria",
    "sg:classifiers":[
        {
            "category":"Building & Trades",
            "subcategory":"Construction",
            "type":"Services"
        }
    ],
    "sg:phone":"+1 805 927 5157",
    "sg:postcode":"93428",
    "sg:province":"CA",
    "sg:tags":[
        "wallcoverings-installation",
        "wallpaper",
        "painting",
        "contractor"
    ],
    "wof:name":"Pelican Painting",
    "wof:placetype":"venue"
},
  "geometry": {"coordinates":[-121.104877,35.560821],"type":"Point"}
}