{
  "type": "Feature",
  "properties": {
    "iso:country":"US",
    "sg:address":"203 N F St",
    "sg:city":"Oxnard",
    "sg:classifiers":[
        {
            "category":"Wholesale",
            "subcategory":"Medical Equipment & Supplies",
            "type":"Manufacturing & Wholesale Goods"
        }
    ],
    "sg:phone":"+1 805 982 9064",
    "sg:postcode":"93030",
    "sg:province":"CA",
    "sg:tags":[
        "hospital",
        "supplies-wholesale",
        "manufacturer"
    ],
    "sg:website":"http://www.cwceqd.com",
    "wof:name":"Cwc Equipment & Design Inc",
    "wof:placetype":"venue"
},
  "geometry": {"coordinates":[-119.185081,34.204042],"type":"Point"}
}