{
  "type": "Feature",
  "properties": {
    "addr:full":"1021 Duryea Ave Irvine CA 92614",
    "addr:housenumber":"1021",
    "addr:postcode":"92614",
    "addr:street":"Duryea Ave",
    "iso:country":"US",
    "sg:address":"1021 Duryea Ave",
    "sg:city":"Irvine",
    "sg:classifiers":[
        {
            "category":"Home & Garden",
            "subcategory":"Household Appliances",
            "type":"Retail Goods"
        },
        {
            "category":"Wholesale",
            "subcategory":"Electrical",
            "type":"Manufacturing & Wholesale Goods"
        },
        {
            "category":"Home & Garden",
            "subcategory":"Hardware",
            "type":"Retail Goods"
        },
        {
            "category":"Shopping",
            "subcategory":"Computers & Home Electronics",
            "type":"Retail Goods"
        }
    ],
    "sg:phone":"+1 949 838 0269",
    "sg:postcode":"92614",
    "sg:province":"CA",
    "sg:tags":[
        "major",
        "electric",
        "supply",
        "appliances-small",
        "equipment",
        "consumer",
        "store"
    ],
    "wof:name":"One Source Distributors",
    "wof:placetype":"venue"
},
  "geometry": {"coordinates":[-117.85563,33.703556],"type":"Point"}
}