{
  "type": "Feature",
  "properties": {
    "addr:full":"834 N White Rd San Jose CA 95127",
    "addr:housenumber":"834",
    "addr:postcode":"95127",
    "addr:street":"N White Rd",
    "iso:country":"US",
    "sg:address":"834 N White Rd",
    "sg:city":"San Jose",
    "sg:classifiers":[
        {
            "category":"Manufacturing",
            "subcategory":"Tools & Machinery",
            "type":"Manufacturing & Wholesale Goods"
        }
    ],
    "sg:phone":"+1 408 464 7431",
    "sg:postcode":"95127",
    "sg:province":"CA",
    "sg:tags":[
        "medical",
        "surgical",
        "devices"
    ],
    "wof:name":"Jt Medical",
    "wof:placetype":"venue"
},
  "geometry": {"coordinates":[-121.84351599999999,37.387277],"type":"Point"}
}