{
  "type": "Feature",
  "properties": {
    "addr:full":"183 Mayfair St Willow Creek CA 95589",
    "addr:housenumber":"183",
    "addr:postcode":"95589",
    "addr:street":"Mayfair St",
    "iso:country":"US",
    "sg:address":"183 Mayfair St",
    "sg:city":"Willow Creek",
    "sg:classifiers":[
        {
            "category":"Professional",
            "subcategory":"Research",
            "type":"Services"
        }
    ],
    "sg:phone":"+1 530 629 2690",
    "sg:postcode":"95589",
    "sg:province":"CA",
    "wof:name":"True Faith Research",
    "wof:placetype":"venue"
},
  "geometry": {"coordinates":[-123.628226,40.939489],"type":"Point"}
}