{
  "type": "Feature",
  "properties": {
    "iso:country":"US",
    "sg:address":"9 Lyndhurst Ct",
    "sg:city":"Belmont",
    "sg:classifiers":[
        {
            "category":"Professional",
            "subcategory":"Business Services",
            "type":"Services"
        }
    ],
    "sg:phone":"+1 650 594 5919",
    "sg:postcode":"94002",
    "sg:province":"CA",
    "sg:tags":[
        "notary"
    ],
    "wof:name":"Thomas D Lewis Notary Public",
    "wof:placetype":"venue"
},
  "geometry": {"coordinates":[-122.280295,37.512041],"type":"Point"}
}