{
  "type": "Feature",
  "properties": {
    "iso:country":"US",
    "sg:address":"2122 S Central Ave",
    "sg:city":"Los Angeles",
    "sg:classifiers":[
        {
            "category":"Wholesale",
            "subcategory":"Fruits & Vegetables",
            "type":"Manufacturing & Wholesale Goods"
        }
    ],
    "sg:phone":"+1 213 627 0362",
    "sg:postcode":"90011",
    "sg:province":"CA",
    "wof:name":"Chino Mozon Produce",
    "wof:placetype":"venue"
},
  "geometry": {"coordinates":[-118.25305,34.021605],"type":"Point"}
}