{
  "type": "Feature",
  "properties": {
    "iso:country":"US",
    "sg:address":"140 H St",
    "sg:city":"Blue Lake",
    "sg:classifiers":[
        {
            "category":"Restaurant",
            "type":"Food & Drink"
        }
    ],
    "sg:phone":"+1 707 668 5994",
    "sg:postcode":"95525",
    "sg:province":"CA",
    "wof:name":"Red Radish",
    "wof:placetype":"venue"
},
  "geometry": {"coordinates":[-123.988525,40.880807],"type":"Point"}
}