{
  "type": "Feature",
  "properties": {
    "addr:full":"33231 Daily Rd Menifee CA 92584",
    "addr:housenumber":"33231",
    "addr:postcode":"92584",
    "addr:street":"Daily Rd",
    "iso:country":"US",
    "sg:address":"33231 Daily Rd",
    "sg:city":"Menifee",
    "sg:classifiers":[
        {
            "category":"Shopping",
            "subcategory":"Clothing, Apparel, & Fashions",
            "type":"Retail Goods"
        }
    ],
    "sg:phone":"+1 909 262 4582",
    "sg:postcode":"92584",
    "sg:province":"CA",
    "sg:tags":[
        "apparel",
        "women's"
    ],
    "wof:name":"Ya Ya Ya Whatever",
    "wof:placetype":"venue"
},
  "geometry": {"coordinates":[-117.20177200000001,33.638532],"type":"Point"}
}