{
  "type": "Feature",
  "properties": {
    "addr:full":"444 Loring St Crockett CA 94525",
    "addr:housenumber":"444",
    "addr:postcode":"94525",
    "addr:street":"Loring St",
    "iso:country":"US",
    "sg:address":"444 Loring St",
    "sg:city":"Crockett",
    "sg:classifiers":[
        {
            "category":"Organizations",
            "subcategory":"Non-profit Organization",
            "type":"Services"
        }
    ],
    "sg:phone":"+1 510 787 9708",
    "sg:postcode":"94525",
    "sg:province":"CA",
    "sg:tags":[
        "charitable",
        "institution"
    ],
    "wof:name":"Crockett Community Foundation",
    "wof:placetype":"venue"
},
  "geometry": {"coordinates":[-122.21269700000001,38.055956],"type":"Point"}
}