{
  "type": "Feature",
  "properties": {
    "iso:country":"US",
    "sg:address":"33751 Zeiders Rd",
    "sg:city":"Sun City",
    "sg:classifiers":[
        {
            "category":"Farming",
            "subcategory":"Farm",
            "type":"Manufacturing & Wholesale Goods"
        }
    ],
    "sg:phone":"+1 951 679 1009",
    "sg:postcode":"92584",
    "sg:province":"CA",
    "wof:name":"Bouris Ranches",
    "wof:placetype":"venue"
},
  "geometry": {"coordinates":[-117.175653,33.630265],"type":"Point"}
}