{
  "type": "Feature",
  "properties": {
    "iso:country":"US",
    "sg:address":"228 E 40th St",
    "sg:city":"San Bernardino",
    "sg:classifiers":[
        {
            "category":"Banks & Credit Unions",
            "subcategory":"Investment Brokerage",
            "type":"Services"
        }
    ],
    "sg:phone":"+1 909 881 1888",
    "sg:postcode":"92404",
    "sg:province":"CA",
    "sg:tags":[
        "advisory",
        "financial"
    ],
    "wof:name":"Nunez Financial",
    "wof:placetype":"venue"
},
  "geometry": {"coordinates":[-117.281785,34.165002],"type":"Point"}
}