{
  "type": "Feature",
  "properties": {
    "iso:country":"US",
    "sg:address":"12051 8th Ave",
    "sg:city":"Hanford",
    "sg:classifiers":[
        {
            "category":"Professional",
            "subcategory":"Business Services",
            "type":"Services"
        }
    ],
    "sg:phone":"+1 559 582 0358",
    "sg:postcode":"93230",
    "sg:province":"CA",
    "sg:tags":[
        "auctioneer"
    ],
    "wof:name":"A & M Livestock Auction",
    "wof:placetype":"venue"
},
  "geometry": {"coordinates":[-119.600665,36.297765],"type":"Point"}
}