{
  "type": "Feature",
  "properties": {
    "iso:country":"US",
    "sg:address":"1146 Bigstone Ln",
    "sg:city":"Ventura",
    "sg:classifiers":[
        {
            "category":"Professional",
            "type":"Services"
        }
    ],
    "sg:phone":"+1 805 647 8449",
    "sg:postcode":"93004",
    "sg:province":"CA",
    "sg:tags":[
        "establishment"
    ],
    "wof:name":"Cadscapes Unlimited",
    "wof:placetype":"venue"
},
  "geometry": {"coordinates":[-119.166855,34.273016],"type":"Point"}
}