{
  "type": "Feature",
  "properties": {
    "iso:country":"US",
    "sg:address":"1447 W Shields Ave",
    "sg:city":"Fresno",
    "sg:classifiers":[
        {
            "category":"Personal",
            "subcategory":"Beauty Salon",
            "type":"Services"
        }
    ],
    "sg:phone":"+1 559 229 8604",
    "sg:postcode":"93705",
    "sg:province":"CA",
    "wof:name":"Whip Appeal Hair Studio",
    "wof:placetype":"venue"
},
  "geometry": {"coordinates":[-119.827367,36.77923],"type":"Point"}
}