{
  "type": "Feature",
  "properties": {
    "addr:full":"12117 Front St Norwalk CA 90650",
    "addr:housenumber":"12117",
    "addr:postcode":"90650",
    "addr:street":"Front St",
    "iso:country":"US",
    "sg:address":"12117 Front St",
    "sg:city":"Norwalk",
    "sg:classifiers":[
        {
            "category":"Professional",
            "subcategory":"Employment Agencies",
            "type":"Services"
        }
    ],
    "sg:phone":"+1 562 406 8608",
    "sg:postcode":"90650",
    "sg:province":"CA",
    "sg:tags":[
        "personal"
    ],
    "wof:name":"House of Nannies Agency",
    "wof:placetype":"venue"
},
  "geometry": {"coordinates":[-118.075176,33.908154],"type":"Point"}
}