{
  "type": "Feature",
  "properties": {
    "iso:country":"US",
    "sg:address":"989 S Glendora Ave",
    "sg:city":"West Covina",
    "sg:classifiers":[
        {
            "category":"Wholesale",
            "subcategory":"Machinery & Supplies",
            "type":"Manufacturing & Wholesale Goods"
        }
    ],
    "sg:phone":"+1 626 814 2299",
    "sg:postcode":"91790",
    "sg:province":"CA",
    "sg:tags":[
        "equipment",
        "establishment"
    ],
    "wof:name":"Famous Beauty Supply",
    "wof:placetype":"venue"
},
  "geometry": {"coordinates":[-117.935464,34.058299],"type":"Point"}
}