{
  "type": "Feature",
  "properties": {
    "iso:country":"US",
    "sg:address":"2157 Ventura Blvd",
    "sg:city":"Camarillo",
    "sg:classifiers":[
        {
            "category":"Restaurant",
            "type":"Food & Drink"
        }
    ],
    "sg:phone":"+1 805 482 0212",
    "sg:postcode":"93010",
    "sg:province":"CA",
    "wof:name":"P J's Boulevard Cafe",
    "wof:placetype":"venue"
},
  "geometry": {"coordinates":[-119.041,34.216801],"type":"Point"}
}