{
  "type": "Feature",
  "properties": {
    "iso:country":"US",
    "sg:address":"741 N Lake St",
    "sg:city":"Burbank",
    "sg:classifiers":[
        {
            "category":"Shopping",
            "subcategory":"Clothing, Apparel, & Fashions",
            "type":"Retail Goods"
        }
    ],
    "sg:phone":"+1 818 840 8844",
    "sg:postcode":"91502",
    "sg:province":"CA",
    "sg:tags":[
        "t"
    ],
    "wof:name":"Wakefield Enterprises",
    "wof:placetype":"venue"
},
  "geometry": {"coordinates":[-118.319417,34.182052],"type":"Point"}
}