{
  "type": "Feature",
  "properties": {
    "addr:full":"4922 East Valencia Dr Orange CA 92869",
    "addr:housenumber":"4922",
    "addr:postcode":"92869",
    "addr:street":"East Valencia Dr",
    "iso:country":"US",
    "sg:address":"4922 East Valencia Dr",
    "sg:city":"Orange",
    "sg:classifiers":[
        {
            "category":"Restaurant",
            "type":"Food & Drink"
        }
    ],
    "sg:phone":"+1 714 639 4868",
    "sg:postcode":"92869",
    "sg:province":"CA",
    "sg:tags":[
        "flavor",
        "local"
    ],
    "sg:website":"topnotchtinting.com/",
    "wof:name":"Tnt By Advantage",
    "wof:placetype":"venue"
},
  "geometry": {"coordinates":[-117.800436,33.807142],"type":"Point"}
}