{
  "type": "Feature",
  "properties": {
    "iso:country":"US",
    "sg:address":"1500 Park St",
    "sg:city":"Alameda",
    "sg:classifiers":[
        {
            "category":"Banks & Credit Unions",
            "subcategory":"Bank",
            "type":"Services"
        }
    ],
    "sg:phone":"+1 510 649 6600",
    "sg:postcode":"94501",
    "sg:province":"CA",
    "sg:tags":[
        "saving",
        "commercial"
    ],
    "sg:website":"www.bofa.com",
    "wof:name":"Bank of America",
    "wof:placetype":"venue"
},
  "geometry": {"coordinates":[-122.241848,37.765368],"type":"Point"}
}