{
  "type": "Feature",
  "properties": {
    "addr:full":"899 Adams St St Helena CA 94574",
    "addr:housenumber":"899",
    "addr:postcode":"94574",
    "addr:street":"Adams St",
    "iso:country":"US",
    "sg:address":"899 Adams St",
    "sg:city":"St Helena",
    "sg:classifiers":[
        {
            "category":"Professional",
            "subcategory":"Testing Lab",
            "type":"Services"
        }
    ],
    "sg:phone":"+1 707 963 4806",
    "sg:postcode":"94574",
    "sg:province":"CA",
    "sg:tags":[
        "laboratory"
    ],
    "wof:name":"ETS Laboratories",
    "wof:placetype":"venue"
},
  "geometry": {"coordinates":[-122.46913000000001,38.506287],"type":"Point"}
}