{
  "type": "Feature",
  "properties": {
    "iso:country":"US",
    "sg:address":"13000 S Figueroa St",
    "sg:city":"Los Angeles",
    "sg:classifiers":[
        {
            "category":"Shopping",
            "subcategory":"Clothing, Apparel, & Fashions",
            "type":"Retail Goods"
        }
    ],
    "sg:phone":"+1 310 808 0006",
    "sg:postcode":"90061",
    "sg:province":"CA",
    "sg:tags":[
        "accessory",
        "clothing",
        "women's"
    ],
    "wof:name":"Diva Worldwide Inc",
    "wof:placetype":"venue"
},
  "geometry": {"coordinates":[-118.282544,33.91436],"type":"Point"}
}