{
  "type": "Feature",
  "properties": {
    "iso:country":"US",
    "sg:address":"3975 Senter Rd",
    "sg:city":"San Jose",
    "sg:classifiers":[
        {
            "category":"Shopping",
            "type":"Retail Goods"
        }
    ],
    "sg:phone":"+1 408 694 0652",
    "sg:postcode":"95111",
    "sg:province":"CA",
    "sg:tags":[
        "telephone",
        "cellular"
    ],
    "wof:name":"Bay Wireless",
    "wof:placetype":"venue"
},
  "geometry": {"coordinates":[-121.824109,37.283416],"type":"Point"}
}