{
  "type": "Feature",
  "properties": {
    "iso:country":"US",
    "sg:address":"414 W Cedar St",
    "sg:city":"San Diego",
    "sg:classifiers":[
        {
            "category":"Food & Beverages",
            "subcategory":"Specialty",
            "type":"Retail Goods"
        }
    ],
    "sg:phone":"+1 619 696 6677",
    "sg:postcode":"92101",
    "sg:province":"CA",
    "sg:tags":[
        "gourmet",
        "shop"
    ],
    "wof:name":"Gone Wild",
    "wof:placetype":"venue"
},
  "geometry": {"coordinates":[-117.16728000000001,32.72202],"type":"Point"}
}