{
  "type": "Feature",
  "properties": {
    "iso:country":"US",
    "sg:address":"125 E H St",
    "sg:city":"Colton",
    "sg:classifiers":[
        {
            "category":"Banks & Credit Unions",
            "subcategory":"Bank",
            "type":"Services"
        }
    ],
    "sg:phone":"+1 909 370 3232",
    "sg:postcode":"92324",
    "sg:province":"CA",
    "wof:name":"Community Trust Deed Svc",
    "wof:placetype":"venue"
},
  "geometry": {"coordinates":[-117.323728,34.06802],"type":"Point"}
}