{
  "type": "Feature",
  "properties": {
    "iso:country":"US",
    "sg:address":"1717 Vine St",
    "sg:city":"Los Angeles",
    "sg:classifiers":[
        {
            "category":"Restaurant",
            "type":"Food & Drink"
        }
    ],
    "sg:phone":"+1 323 962 1711",
    "sg:postcode":"90028",
    "sg:province":"CA",
    "sg:tags":[
        "mediterranean"
    ],
    "sg:website":"www.cleorestaurant.com",
    "wof:name":"Cleo",
    "wof:placetype":"venue"
},
  "geometry": {"coordinates":[-118.327151,34.10238],"type":"Point"}
}