{
  "type": "Feature",
  "properties": {
    "addr:full":"207 W Ave I Lancaster CA 93534",
    "addr:housenumber":"207",
    "addr:postcode":"93534",
    "addr:street":"W Ave I",
    "iso:country":"US",
    "sg:address":"207 W Ave I",
    "sg:city":"Lancaster",
    "sg:classifiers":[
        {
            "category":"Autos & Motor Vehicles",
            "subcategory":"Automobile Sales",
            "type":"Retail Goods"
        }
    ],
    "sg:phone":"+1 661 949 2289",
    "sg:postcode":"93534",
    "sg:province":"CA",
    "sg:tags":[
        "car",
        "dealer"
    ],
    "wof:name":"American Car Connection",
    "wof:placetype":"venue"
},
  "geometry": {"coordinates":[-118.131743,34.704049],"type":"Point"}
}