{
  "type": "Feature",
  "properties": {
    "addr:full":"1363 Lincoln Ave San Rafael CA 94901",
    "addr:housenumber":"1363",
    "addr:postcode":"94901",
    "addr:street":"Lincoln Ave",
    "iso:country":"US",
    "sg:address":"1363 Lincoln Ave",
    "sg:city":"San Rafael",
    "sg:classifiers":[
        {
            "category":"Health Services",
            "subcategory":"Clinic",
            "type":"Services"
        }
    ],
    "sg:phone":"+1 415 457 2256",
    "sg:postcode":"94901",
    "sg:province":"CA",
    "sg:tags":[
        "home"
    ],
    "wof:name":"Health Care Connection",
    "wof:placetype":"venue"
},
  "geometry": {"coordinates":[-122.522789,37.976212],"type":"Point"}
}