{
  "type": "Feature",
  "properties": {
    "addr:full":"42240 Camino Romo Temecula CA 92592",
    "addr:housenumber":"42240",
    "addr:postcode":"92592",
    "addr:street":"Camino Romo",
    "iso:country":"US",
    "sg:address":"42240 Camino Romo",
    "sg:city":"Temecula",
    "sg:classifiers":[
        {
            "category":"Education",
            "subcategory":"School",
            "type":"Public Place"
        }
    ],
    "sg:phone":"+1 951 695 4260",
    "sg:postcode":"92592",
    "sg:province":"CA",
    "sg:tags":[
        "elementary"
    ],
    "wof:name":"Vintage Hills Elementary School",
    "wof:placetype":"venue"
},
  "geometry": {"coordinates":[-117.100026,33.508045],"type":"Point"}
}