{
  "type": "Feature",
  "properties": {
    "addr:full":"10961 Oak Mountain Pl Sunland CA 91040",
    "addr:housenumber":"10961",
    "addr:postcode":"91040",
    "addr:street":"Oak Mountain Pl",
    "iso:country":"US",
    "sg:address":"10961 Oak Mountain Pl",
    "sg:city":"Sunland",
    "sg:classifiers":[
        {
            "category":"Place Of Worship",
            "type":"Public Place"
        }
    ],
    "sg:phone":"+1 818 482 6852",
    "sg:postcode":"91040",
    "sg:province":"CA",
    "sg:tags":[
        "church"
    ],
    "wof:name":"Casa Sobre La Roca",
    "wof:placetype":"venue"
},
  "geometry": {"coordinates":[-118.368439,34.262587],"type":"Point"}
}