{
  "type": "Feature",
  "properties": {
    "iso:country":"US",
    "sg:address":"3809 Plaza Dr Ste 114",
    "sg:city":"Oceanside",
    "sg:classifiers":[
        {
            "category":"Health Services",
            "subcategory":"Doctor",
            "type":"Services"
        }
    ],
    "sg:phone":"+1 760 945 1111",
    "sg:postcode":"92056",
    "sg:province":"CA",
    "sg:tags":[
        "surgeon",
        "oral"
    ],
    "wof:name":"Chang Stuart D DDS",
    "wof:placetype":"venue"
},
  "geometry": {"coordinates":[-117.293999,33.181999],"type":"Point"}
}