{
  "type": "Feature",
  "properties": {
    "iso:country":"US",
    "sg:address":"225 E Badillo St",
    "sg:city":"Covina",
    "sg:classifiers":[
        {
            "category":"Real Estate",
            "subcategory":"Real Estate Agent",
            "type":"Services"
        }
    ],
    "sg:phone":"+1 626 858 0047",
    "sg:postcode":"91723",
    "sg:province":"CA",
    "wof:name":"Westland Realty",
    "wof:placetype":"venue"
},
  "geometry": {"coordinates":[-117.88782,34.086254],"type":"Point"}
}