{
  "type": "Feature",
  "properties": {
    "iso:country":"US",
    "sg:address":"1006 Washington St",
    "sg:city":"Calistoga",
    "sg:classifiers":[
        {
            "category":"Travel",
            "subcategory":"Hotels & Motels",
            "type":"Entertainment"
        }
    ],
    "sg:phone":"+1 707 942 6269",
    "sg:postcode":"94515",
    "sg:province":"CA",
    "sg:website":"www.calistogaspa.com",
    "wof:name":"Calistoga Spa Hot Springs",
    "wof:placetype":"venue"
},
  "geometry": {"coordinates":[-122.57726,38.578852],"type":"Point"}
}