{
  "type": "Feature",
  "properties": {
    "iso:country":"US",
    "sg:address":"231 E St",
    "sg:city":"Davis",
    "sg:classifiers":[
        {
            "category":"Professional",
            "type":"Services"
        }
    ],
    "sg:phone":"+1 530 753 9604",
    "sg:postcode":"95616",
    "sg:province":"CA",
    "wof:name":"Davidson Films Inc",
    "wof:placetype":"venue"
},
  "geometry": {"coordinates":[-121.74140199999999,38.544112],"type":"Point"}
}