{
  "type": "Feature",
  "properties": {
    "addr:full":"640 S 13th St Richmond CA 94804",
    "addr:housenumber":"640",
    "addr:postcode":"94804",
    "addr:street":"S 13Th St",
    "iso:country":"US",
    "sg:address":"640 S 13th St",
    "sg:city":"Richmond",
    "sg:classifiers":[
        {
            "category":"Building & Trades",
            "subcategory":"Construction",
            "type":"Services"
        }
    ],
    "sg:phone":"+1 510 233 2545",
    "sg:postcode":"94804",
    "sg:province":"CA",
    "sg:tags":[
        "contractor"
    ],
    "wof:name":"A Murphy Construction",
    "wof:placetype":"venue"
},
  "geometry": {"coordinates":[-122.356757,37.923459],"type":"Point"}
}