{
  "type": "Feature",
  "properties": {
    "addr:full":"1645 S Bascom Ave Campbell CA 95008",
    "addr:housenumber":"1645",
    "addr:postcode":"95008",
    "addr:street":"S Bascom Ave",
    "iso:country":"US",
    "sg:address":"1645 S Bascom Ave",
    "sg:city":"Campbell",
    "sg:classifiers":[
        {
            "category":"Restaurant",
            "type":"Food & Drink"
        }
    ],
    "sg:menulink":"http://www.allmenus.com/ca/san-jose/45727-fresh-choice/menu/",
    "sg:phone":"+1 408 559 1912",
    "sg:postcode":"95008",
    "sg:province":"CA",
    "sg:tags":[
        "american"
    ],
    "wof:name":"Fresh Choice",
    "wof:placetype":"venue"
},
  "geometry": {"coordinates":[-121.931797,37.293285],"type":"Point"}
}