{
  "type": "Feature",
  "properties": {
    "iso:country":"US",
    "sg:address":"1350 Concord Ave",
    "sg:city":"Concord",
    "sg:classifiers":[
        {
            "category":"Freight",
            "type":"Transportation"
        }
    ],
    "sg:phone":"+1 925 825 4858",
    "sg:postcode":"94520",
    "sg:province":"CA",
    "sg:tags":[
        "commercial",
        "paper",
        "storage",
        "general"
    ],
    "wof:name":"Public Storage Inc",
    "wof:placetype":"venue"
},
  "geometry": {"coordinates":[-122.048056,37.979897],"type":"Point"}
}