{
  "type": "Feature",
  "properties": {
    "iso:country":"US",
    "sg:address":"41166 Cardinal Flower Dr",
    "sg:city":"Murrieta",
    "sg:classifiers":[
        {
            "category":"Building & Trades",
            "subcategory":"Construction",
            "type":"Services"
        }
    ],
    "sg:phone":"+1 951 677 0982",
    "sg:postcode":"92562",
    "sg:province":"CA",
    "sg:tags":[
        "maker",
        "cabinet"
    ],
    "wof:name":"Household Handyman",
    "wof:placetype":"venue"
},
  "geometry": {"coordinates":[-117.221493,33.578599],"type":"Point"}
}