{
  "type": "Feature",
  "properties": {
    "iso:country":"US",
    "sg:address":"3301 N State St",
    "sg:city":"Ukiah",
    "sg:classifiers":[
        {
            "category":"Home & Garden",
            "subcategory":"Furniture",
            "type":"Retail Goods"
        }
    ],
    "sg:phone":"+1 707 462 5225",
    "sg:postcode":"95482",
    "sg:province":"CA",
    "sg:tags":[
        "cabinet"
    ],
    "wof:name":"J D Sissons Cabinet Co",
    "wof:placetype":"venue"
},
  "geometry": {"coordinates":[-123.206717,39.19353],"type":"Point"}
}