{
  "type": "Feature",
  "properties": {
    "addr:full":"1818 W Beverly Blvd Montebello CA 90640",
    "addr:housenumber":"1818",
    "addr:postcode":"90640",
    "addr:street":"W Beverly Blvd",
    "iso:country":"US",
    "sg:address":"1818 W Beverly Blvd",
    "sg:city":"Montebello",
    "sg:classifiers":[
        {
            "category":"Professional",
            "subcategory":"Lawyer & Legal Services",
            "type":"Services"
        }
    ],
    "sg:phone":"+1 323 727 1243",
    "sg:postcode":"90640",
    "sg:province":"CA",
    "wof:name":"Byron Jen Lee Atty",
    "wof:placetype":"venue"
},
  "geometry": {"coordinates":[-118.11799600000001,34.019901],"type":"Point"}
}