{
  "type": "Feature",
  "properties": {
    "addr:full":"17600 Bellflower Blvd Bellflower CA 90706",
    "addr:housenumber":"17600",
    "addr:postcode":"90706",
    "addr:street":"Bellflower Blvd",
    "iso:country":"US",
    "sg:address":"17600 Bellflower Blvd",
    "sg:city":"Bellflower",
    "sg:classifiers":[
        {
            "category":"Restaurant",
            "type":"Food & Drink"
        }
    ],
    "sg:menulink":"http://www.allmenus.com/ca/downey-norwalk/178668-jack-in-the-box/menu/",
    "sg:phone":"+1 562 920 6733",
    "sg:postcode":"90706",
    "sg:province":"CA",
    "sg:tags":[
        "burger",
        "american"
    ],
    "wof:name":"Jack in the Box",
    "wof:placetype":"venue"
},
  "geometry": {"coordinates":[-118.124678,33.872726],"type":"Point"}
}