{
  "type": "Feature",
  "properties": {
    "iso:country":"US",
    "sg:address":"313 Quails Pass Way",
    "sg:city":"Simi Valley",
    "sg:classifiers":[
        {
            "category":"Professional",
            "subcategory":"Management & Consulting",
            "type":"Services"
        }
    ],
    "sg:phone":"+1 805 583 0026",
    "sg:postcode":"93065",
    "sg:province":"CA",
    "sg:tags":[
        "marketing",
        "consultant"
    ],
    "wof:name":"Camelot Marketing",
    "wof:placetype":"venue"
},
  "geometry": {"coordinates":[-118.811604,34.23366],"type":"Point"}
}