{
  "type": "Feature",
  "properties": {
    "addr:full":"23293 Ventura Blvd Woodland Hills CA 91364",
    "addr:housenumber":"23293",
    "addr:postcode":"91364",
    "addr:street":"Ventura Blvd",
    "iso:country":"US",
    "sg:address":"23293 Ventura Blvd",
    "sg:city":"Woodland Hills",
    "sg:classifiers":[
        {
            "category":"Organizations",
            "subcategory":"Non-profit Organization",
            "type":"Services"
        }
    ],
    "sg:phone":"+1 818 224 4250",
    "sg:postcode":"91364",
    "sg:province":"CA",
    "sg:tags":[
        "service/non-profit",
        "community"
    ],
    "wof:name":"Iemanya Oceanica",
    "wof:placetype":"venue"
},
  "geometry": {"coordinates":[-118.63403,34.161547],"type":"Point"}
}