{
  "type": "Feature",
  "properties": {
    "addr:full":"19811 Colima Rd Walnut CA 91748",
    "addr:housenumber":"19811",
    "addr:postcode":"91748",
    "addr:street":"Colima Rd",
    "iso:country":"US",
    "sg:address":"19811 Colima Rd",
    "sg:city":"Walnut",
    "sg:classifiers":[
        {
            "category":"Recreation",
            "type":"Entertainment"
        }
    ],
    "sg:phone":"+1 909 594 7033",
    "sg:postcode":"91748",
    "sg:province":"CA",
    "sg:tags":[
        "martial",
        "arts",
        "instruction"
    ],
    "wof:name":"Brazilian Jiu Jitsu",
    "wof:placetype":"venue"
},
  "geometry": {"coordinates":[-117.869496,33.987044],"type":"Point"}
}