{
  "type": "Feature",
  "properties": {
    "addr:full":"155 Columbus Ave San Francisco CA 94133",
    "addr:housenumber":"155",
    "addr:postcode":"94133",
    "addr:street":"Columbus Ave",
    "iso:country":"US",
    "sg:address":"155 Columbus Ave",
    "sg:city":"San Francisco",
    "sg:classifiers":[
        {
            "category":"Manufacturing",
            "subcategory":"Food",
            "type":"Manufacturing & Wholesale Goods"
        }
    ],
    "sg:phone":"+1 415 434 3344",
    "sg:postcode":"94133",
    "sg:province":"CA",
    "sg:tags":[
        "brewer"
    ],
    "wof:name":"San Francisco Brewing Co",
    "wof:placetype":"venue"
},
  "geometry": {"coordinates":[-122.404956,37.796518],"type":"Point"}
}