{
  "type": "Feature",
  "properties": {
    "addr:full":"1115 Oro Dam Blvd E Oroville CA 95965",
    "addr:housenumber":"1115",
    "addr:postcode":"95965",
    "addr:street":"Oro Dam Blvd E",
    "iso:country":"US",
    "sg:address":"1115 Oro Dam Blvd E",
    "sg:city":"Oroville",
    "sg:classifiers":[
        {
            "category":"Shopping",
            "subcategory":"Florist",
            "type":"Retail Goods"
        }
    ],
    "sg:phone":"+1 530 534 9440",
    "sg:postcode":"95965",
    "sg:province":"CA",
    "sg:website":"www.flowerpot.us",
    "wof:name":"Flower Pot",
    "wof:placetype":"venue"
},
  "geometry": {"coordinates":[-121.563171,39.500335],"type":"Point"}
}