{
  "type": "Feature",
  "properties": {
    "addr:full":"10645 Kearney Ct Smartsville CA 95977",
    "addr:housenumber":"10645",
    "addr:postcode":"95977",
    "addr:street":"Kearney Ct",
    "iso:country":"US",
    "sg:address":"10645 Kearney Ct",
    "sg:city":"Smartsville",
    "sg:classifiers":[
        {
            "category":"Personal",
            "subcategory":"Beauty Salon",
            "type":"Services"
        }
    ],
    "sg:phone":"+1 530 272 2707",
    "sg:postcode":"95977",
    "sg:province":"CA",
    "wof:name":"Alta Sierra Hair Design",
    "wof:placetype":"venue"
},
  "geometry": {"coordinates":[-121.265418,39.195714],"type":"Point"}
}