{
  "type": "Feature",
  "properties": {
    "iso:country":"US",
    "sg:address":"4226 Valley Fair St",
    "sg:city":"Simi Valley",
    "sg:classifiers":[
        {
            "category":"Shopping",
            "subcategory":"Bicycles & Sporting Goods",
            "type":"Retail Goods"
        }
    ],
    "sg:phone":"+1 805 578 0040",
    "sg:postcode":"93063",
    "sg:province":"CA",
    "sg:tags":[
        "equipment",
        "skateboard"
    ],
    "wof:name":"Skate Lab Skatepark",
    "wof:placetype":"venue"
},
  "geometry": {"coordinates":[-118.709551,34.272484],"type":"Point"}
}