{
  "type": "Feature",
  "properties": {
    "iso:country":"US",
    "sg:address":"808 W Newgrove St",
    "sg:city":"Lancaster",
    "sg:classifiers":[
        {
            "category":"Social Services",
            "subcategory":"Child Care",
            "type":"Services"
        }
    ],
    "sg:phone":"+1 661 949 6790",
    "sg:postcode":"93534",
    "sg:province":"CA",
    "sg:tags":[
        "kindergarten",
        "academic",
        "school"
    ],
    "wof:name":"Assistance League-Antelope Vly",
    "wof:placetype":"venue"
},
  "geometry": {"coordinates":[-118.144103,34.693848],"type":"Point"}
}