{
  "type": "Feature",
  "properties": {
    "iso:country":"US",
    "sg:address":"821 S San Pedro St",
    "sg:city":"Los Angeles",
    "sg:classifiers":[
        {
            "category":"Wholesale",
            "subcategory":"Apparel",
            "type":"Manufacturing & Wholesale Goods"
        }
    ],
    "sg:phone":"+1 213 627 4563",
    "sg:postcode":"90014",
    "sg:province":"CA",
    "sg:tags":[
        "fabric"
    ],
    "wof:name":"United Textile",
    "wof:placetype":"venue"
},
  "geometry": {"coordinates":[-118.25017,34.0376],"type":"Point"}
}