{
  "type": "Feature",
  "properties": {
    "addr:full":"602 Jamestown Ave San Francisco CA 94124",
    "addr:housenumber":"602",
    "addr:postcode":"94124",
    "addr:street":"Jamestown Ave",
    "iso:country":"US",
    "sg:address":"602 Jamestown Ave",
    "sg:city":"San Francisco",
    "sg:classifiers":[
        {
            "category":"Arena",
            "subcategory":"Sports Club",
            "type":"Entertainment"
        }
    ],
    "sg:phone":"+1 415 467 1994",
    "sg:postcode":"94124",
    "sg:province":"CA",
    "sg:tags":[
        "athletic",
        "fields",
        "stadium"
    ],
    "sg:website":"www.parks.sfgov.org",
    "wof:name":"Monster Park",
    "wof:placetype":"venue"
},
  "geometry": {"coordinates":[-122.388666,37.714602],"type":"Point"}
}