{
  "type": "Feature",
  "properties": {
    "iso:country":"US",
    "sg:address":"705 Somerset Ln",
    "sg:city":"Foster City",
    "sg:classifiers":[
        {
            "category":"Building & Trades",
            "subcategory":"Electrical",
            "type":"Services"
        }
    ],
    "sg:phone":"+1 650 574 1632",
    "sg:postcode":"94404",
    "sg:province":"CA",
    "sg:tags":[
        "electric",
        "contractor"
    ],
    "wof:name":"Electric Co",
    "wof:placetype":"venue"
},
  "geometry": {"coordinates":[-122.262102,37.541589],"type":"Point"}
}