{
  "type": "Feature",
  "properties": {
    "iso:country":"US",
    "sg:address":"42223 50th St W",
    "sg:city":"Lancaster",
    "sg:classifiers":[
        {
            "category":"Banks & Credit Unions",
            "subcategory":"Financial Services",
            "type":"Services"
        }
    ],
    "sg:phone":"+1 661 943 3646",
    "sg:postcode":"93536",
    "sg:province":"CA",
    "sg:tags":[
        "trust",
        "management"
    ],
    "wof:name":"Reyes & Co Loans & Investments",
    "wof:placetype":"venue"
},
  "geometry": {"coordinates":[-118.21859600000001,34.649673],"type":"Point"}
}