{
  "type": "Feature",
  "properties": {
    "iso:country":"US",
    "sg:address":"3013 D St",
    "sg:city":"Sacramento",
    "sg:classifiers":[
        {
            "category":"Social Services",
            "subcategory":"Adult Care",
            "type":"Services"
        }
    ],
    "sg:phone":"+1 916 444 9694",
    "sg:postcode":"95816",
    "sg:province":"CA",
    "sg:tags":[
        "organization",
        "senior",
        "citizen"
    ],
    "wof:name":"Senior Nutrition Svc",
    "wof:placetype":"venue"
},
  "geometry": {"coordinates":[-121.462458,38.579447],"type":"Point"}
}