{
  "type": "Feature",
  "properties": {
    "addr:full":"4348 Swift Cir Shingle Springs CA 95682",
    "addr:housenumber":"4348",
    "addr:postcode":"95682",
    "addr:street":"Swift Cir",
    "iso:country":"US",
    "sg:address":"4348 Swift Cir",
    "sg:city":"Shingle Springs",
    "sg:classifiers":[
        {
            "category":"Retail",
            "subcategory":"Animal Services",
            "type":"Services"
        }
    ],
    "sg:phone":"+1 530 672 0932",
    "sg:postcode":"95682",
    "sg:province":"CA",
    "wof:name":"Boyajian Equestrians",
    "wof:placetype":"venue"
},
  "geometry": {"coordinates":[-120.979184,38.574112],"type":"Point"}
}