{
  "type": "Feature",
  "properties": {
    "iso:country":"US",
    "sg:address":"10360 State St",
    "sg:city":"Lynwood",
    "sg:classifiers":[
        {
            "category":"Retail",
            "subcategory":"Auto Repair",
            "type":"Services"
        }
    ],
    "sg:phone":"+1 323 566 3377",
    "sg:postcode":"90262",
    "sg:province":"CA",
    "sg:tags":[
        "repairing",
        "automobile"
    ],
    "wof:name":"Palacio's Auto Repair",
    "wof:placetype":"venue"
},
  "geometry": {"coordinates":[-118.21399700000001,33.940899],"type":"Point"}
}