{
  "type": "Feature",
  "properties": {
    "iso:country":"US",
    "sg:address":"5113 Lake Isabella Blvd",
    "sg:city":"Lake Isabella",
    "sg:classifiers":[
        {
            "category":"Autos & Motor Vehicles",
            "subcategory":"Auto Supplies",
            "type":"Retail Goods"
        }
    ],
    "sg:phone":"+1 760 379 3693",
    "sg:postcode":"93240",
    "sg:province":"CA",
    "sg:tags":[
        "automobile",
        "parts"
    ],
    "wof:name":"NAPA Auto Parts",
    "wof:placetype":"venue"
},
  "geometry": {"coordinates":[-118.481742,35.61161],"type":"Point"}
}