{
  "type": "Feature",
  "properties": {
    "addr:full":"1100 Via Curva Palos Vrds Ests CA 90274",
    "addr:housenumber":"1100;palos",
    "addr:postcode":"90274",
    "addr:street":"Via Curva;Ests",
    "iso:country":"US",
    "sg:address":"1100 Via Curva",
    "sg:city":"Palos Vrds Ests",
    "sg:classifiers":[
        {
            "category":"Professional",
            "subcategory":"Computer Services",
            "type":"Services"
        }
    ],
    "sg:phone":"+1 310 791 1916",
    "sg:postcode":"90274",
    "sg:province":"CA",
    "sg:tags":[
        "processing",
        "datum"
    ],
    "wof:name":"Jorgensen & Assoc",
    "wof:placetype":"venue"
},
  "geometry": {"coordinates":[-118.410668,33.780169],"type":"Point"}
}