{
  "type": "Feature",
  "properties": {
    "iso:country":"US",
    "sg:address":"2454 Merritt Ave",
    "sg:city":"San Pablo",
    "sg:classifiers":[
        {
            "category":"Professional",
            "subcategory":"Accounting & Tax Preparation",
            "type":"Services"
        }
    ],
    "sg:phone":"+1 510 237 9846",
    "sg:postcode":"94806",
    "sg:province":"CA",
    "sg:tags":[
        "return",
        "filing"
    ],
    "wof:name":"Community Tax Svc",
    "wof:placetype":"venue"
},
  "geometry": {"coordinates":[-122.349142,37.967152],"type":"Point"}
}