{
  "type": "Feature",
  "properties": {
    "addr:full":"8445 Lindenhurst St Riverside CA 92508",
    "addr:postcode":"8445;92508",
    "addr:street":"Lindenhurst St",
    "iso:country":"US",
    "sg:address":"8445 Lindenhurst St",
    "sg:city":"Riverside",
    "sg:classifiers":[
        {
            "category":"Place Of Worship",
            "subcategory":"Church",
            "type":"Public Place"
        },
        {
            "category":"Place Of Worship",
            "type":"Public Place"
        }
    ],
    "sg:phone":"+1 951 288 2423",
    "sg:postcode":"92508",
    "sg:province":"CA",
    "sg:tags":[
        "churches-baptist-general",
        "churches-baptist"
    ],
    "wof:name":"Glaxosmthkline Hldngs Ame",
    "wof:placetype":"venue"
},
  "geometry": {"coordinates":[-117.319267,33.897408],"type":"Point"}
}