{
  "type": "Feature",
  "properties": {
    "iso:country":"US",
    "sg:address":"1751 Foothill Blvd",
    "sg:city":"La Canada Fltrdg",
    "sg:classifiers":[
        {
            "category":"Personal",
            "type":"Services"
        }
    ],
    "sg:phone":"+1 818 952 7173",
    "sg:postcode":"91011",
    "sg:province":"CA",
    "sg:tags":[
        "program",
        "physical",
        "exercise",
        "fitness"
    ],
    "wof:name":"Sawyer Chiropractic",
    "wof:placetype":"venue"
},
  "geometry": {"coordinates":[-118.214464,34.21106],"type":"Point"}
}