{
  "type": "Feature",
  "properties": {
    "addr:full":"30590 Cochise Cir Murrieta CA 92563",
    "addr:postcode":"30590;92563",
    "addr:street":"Cochise Cir",
    "iso:country":"US",
    "sg:address":"30590 Cochise Cir",
    "sg:city":"Murrieta",
    "sg:classifiers":[
        {
            "category":"Manufacturing",
            "subcategory":"Tools & Machinery",
            "type":"Manufacturing & Wholesale Goods"
        }
    ],
    "sg:phone":"+1 951 926 1212",
    "sg:postcode":"92563",
    "sg:province":"CA",
    "sg:tags":[
        "physician",
        "surgeon"
    ],
    "wof:name":"Boston Scientific/Ivt Tech Ctr",
    "wof:placetype":"venue"
},
  "geometry": {"coordinates":[-117.126977,33.587821],"type":"Point"}
}