{
  "type": "Feature",
  "properties": {
    "iso:country":"US",
    "sg:address":"5545 E Hedges Ave",
    "sg:city":"Fresno",
    "sg:classifiers":[
        {
            "category":"Travel",
            "subcategory":"Campground",
            "type":"Entertainment"
        }
    ],
    "sg:phone":"+1 559 251 6055",
    "sg:postcode":"93727",
    "sg:province":"CA",
    "sg:tags":[
        "camp"
    ],
    "wof:name":"Hume Lake Christian Camps Inc",
    "wof:placetype":"venue"
},
  "geometry": {"coordinates":[-119.703434,36.759274],"type":"Point"}
}