{
  "type": "Feature",
  "properties": {
    "addr:full":"5477 Almond St Paradise CA 95969",
    "addr:housenumber":"5477",
    "addr:postcode":"95969",
    "addr:street":"Almond St",
    "iso:country":"US",
    "sg:address":"5477 Almond St",
    "sg:city":"Paradise",
    "sg:classifiers":[
        {
            "category":"Insurance",
            "subcategory":"Hazard Insurance",
            "type":"Services"
        }
    ],
    "sg:phone":"+1 530 877 1528",
    "sg:postcode":"95969",
    "sg:province":"CA",
    "sg:tags":[
        "commercial",
        "business"
    ],
    "wof:name":"Bankers Management Insurance Services",
    "wof:placetype":"venue"
},
  "geometry": {"coordinates":[-121.626175,39.752053],"type":"Point"}
}