{
  "type": "Feature",
  "properties": {
    "addr:full":"1610 Centre Pointe Dr Milpitas CA 95035",
    "addr:housenumber":"1610",
    "addr:postcode":"95035",
    "addr:street":"Centre Pointe Dr",
    "iso:country":"US",
    "sg:address":"1610 Centre Pointe Dr",
    "sg:city":"Milpitas",
    "sg:classifiers":[
        {
            "category":"Manufacturing",
            "subcategory":"Tools & Machinery",
            "type":"Manufacturing & Wholesale Goods"
        }
    ],
    "sg:phone":"+1 408 719 1826",
    "sg:postcode":"95035",
    "sg:province":"CA",
    "sg:tags":[
        "machine",
        "shop"
    ],
    "wof:name":"H T Precision Inc",
    "wof:placetype":"venue"
},
  "geometry": {"coordinates":[-121.89702800000001,37.410464],"type":"Point"}
}