{
  "type": "Feature",
  "properties": {
    "addr:full":"20271 Kline Dr Newport Beach CA 92660",
    "addr:postcode":"20271;92660",
    "addr:street":"Kline Dr",
    "iso:country":"US",
    "sg:address":"20271 Kline Dr",
    "sg:city":"Newport Beach",
    "sg:classifiers":[
        {
            "category":"Manufacturing",
            "subcategory":"Lumber",
            "type":"Manufacturing & Wholesale Goods"
        }
    ],
    "sg:phone":"+1 714 556 6984",
    "sg:postcode":"92660",
    "sg:province":"CA",
    "sg:tags":[
        "hardwood",
        "mill",
        "flooring"
    ],
    "wof:name":"Von Herzens Hardwood Flooring",
    "wof:placetype":"venue"
},
  "geometry": {"coordinates":[-117.88258,33.661467],"type":"Point"}
}