{
  "type": "Feature",
  "properties": {
    "iso:country":"US",
    "sg:address":"4340 Stevens Creek Blvd",
    "sg:city":"San Jose",
    "sg:classifiers":[
        {
            "category":"Real Estate",
            "subcategory":"Real Estate Services",
            "type":"Services"
        }
    ],
    "sg:phone":"+1 408 261 0631",
    "sg:postcode":"95129",
    "sg:province":"CA",
    "sg:tags":[
        "management",
        "property"
    ],
    "wof:name":"West Valley Executive Park Associates",
    "wof:placetype":"venue"
},
  "geometry": {"coordinates":[-121.97856899999999,37.323002],"type":"Point"}
}