{
  "type": "Feature",
  "properties": {
    "addr:full":"1410 2nd St Santa Monica CA 90401",
    "addr:housenumber":"1410",
    "addr:postcode":"90401",
    "addr:street":"2Nd St",
    "iso:country":"US",
    "sg:address":"1410 2nd St",
    "sg:city":"Santa Monica",
    "sg:classifiers":[
        {
            "category":"Sports & Exercise",
            "subcategory":"Gym",
            "type":"Entertainment"
        }
    ],
    "sg:phone":"+1 310 458 9550",
    "sg:postcode":"90401",
    "sg:province":"CA",
    "sg:tags":[
        "yoga"
    ],
    "sg:website":"www.yogitoes.com",
    "wof:name":"Yogitoes",
    "wof:placetype":"venue"
},
  "geometry": {"coordinates":[-118.496988,34.462993],"type":"Point"}
}