{
  "type": "Feature",
  "properties": {
    "addr:full":"919 Harmon Dr Menlo Park CA 94025",
    "addr:housenumber":"919",
    "addr:postcode":"94025",
    "addr:street":"Harmon Dr",
    "iso:country":"US",
    "sg:address":"919 Harmon Dr",
    "sg:city":"Menlo Park",
    "sg:classifiers":[
        {
            "category":"Professional",
            "subcategory":"Lawyer & Legal Services",
            "type":"Services"
        }
    ],
    "sg:phone":"+1 650 328 2627",
    "sg:postcode":"94025",
    "sg:province":"CA",
    "sg:tags":[
        "attorney"
    ],
    "wof:name":"Jeffrey Y Suto A Pro Corp",
    "wof:placetype":"venue"
},
  "geometry": {"coordinates":[-122.181753,37.477719],"type":"Point"}
}