{
  "type": "Feature",
  "properties": {
    "addr:full":"1936 E Deere Ave Santa Ana CA 92705",
    "addr:housenumber":"1936",
    "addr:postcode":"92705",
    "addr:street":"E Deere Ave",
    "iso:country":"US",
    "sg:address":"1936 E Deere Ave",
    "sg:city":"Santa Ana",
    "sg:classifiers":[
        {
            "category":"Manufacturing",
            "subcategory":"Printing",
            "type":"Manufacturing & Wholesale Goods"
        }
    ],
    "sg:phone":"+1 714 442 0862",
    "sg:postcode":"92705",
    "sg:province":"CA",
    "sg:tags":[
        "publishes",
        "educational",
        "material"
    ],
    "wof:name":"Games To Learn",
    "wof:placetype":"venue"
},
  "geometry": {"coordinates":[-117.848381,33.704349],"type":"Point"}
}