{
  "type": "Feature",
  "properties": {
    "iso:country":"US",
    "sg:address":"3971 Tyler St",
    "sg:city":"Riverside",
    "sg:classifiers":[
        {
            "category":"Shopping",
            "subcategory":"Bicycles & Sporting Goods",
            "type":"Retail Goods"
        }
    ],
    "sg:phone":"+1 951 351 1015",
    "sg:postcode":"92503",
    "sg:province":"CA",
    "sg:tags":[
        "equipment",
        "skateboard"
    ],
    "wof:name":"Board Shops Of America",
    "wof:placetype":"venue"
},
  "geometry": {"coordinates":[-117.463163,33.914057],"type":"Point"}
}