{
  "type": "Feature",
  "properties": {
    "iso:country":"US",
    "sg:address":"1436 W 259th St",
    "sg:city":"Harbor City",
    "sg:classifiers":[
        {
            "category":"Retail",
            "subcategory":"Repair Shop",
            "type":"Services"
        }
    ],
    "sg:phone":"+1 310 326 3466",
    "sg:postcode":"90710",
    "sg:province":"CA",
    "sg:tags":[
        "scooter",
        "motorcycle",
        "motor"
    ],
    "wof:name":"Settle Motorcycle Repair",
    "wof:placetype":"venue"
},
  "geometry": {"coordinates":[-118.302254,33.788115],"type":"Point"}
}