{
  "type": "Feature",
  "properties": {
    "addr:full":"3952 Clairemont Mesa Blvd San Diego CA 92117",
    "addr:housenumber":"3952",
    "addr:postcode":"92117",
    "addr:street":"Clairemont Mesa Blvd",
    "iso:country":"US",
    "sg:address":"3952 Clairemont Mesa Blvd",
    "sg:city":"San Diego",
    "sg:classifiers":[
        {
            "category":"Shopping",
            "subcategory":"Computers & Home Electronics",
            "type":"Retail Goods"
        }
    ],
    "sg:phone":"+1 858 490 1090",
    "sg:postcode":"92117",
    "sg:province":"CA",
    "sg:tags":[
        "game",
        "video"
    ],
    "wof:name":"Game Stop Corp",
    "wof:placetype":"venue"
},
  "geometry": {"coordinates":[-117.202861,32.828091],"type":"Point"}
}