{
  "type": "Feature",
  "properties": {
    "iso:country":"US",
    "sg:address":"21162 S Western Ave",
    "sg:city":"Torrance",
    "sg:classifiers":[
        {
            "category":"Restaurant",
            "type":"Food & Drink"
        }
    ],
    "sg:phone":"+1 310 783 0022",
    "sg:postcode":"90501",
    "sg:province":"CA",
    "wof:name":"Aloha Teriyaki No 3",
    "wof:placetype":"venue"
},
  "geometry": {"coordinates":[-118.308998,33.838001],"type":"Point"}
}