{
  "type": "Feature",
  "properties": {
    "iso:country":"US",
    "sg:address":"1864 E Washington Blvd",
    "sg:city":"Pasadena",
    "sg:classifiers":[
        {
            "category":"Retail",
            "subcategory":"Portrait Studio",
            "type":"Services"
        }
    ],
    "sg:phone":"+1 626 798 2214",
    "sg:postcode":"91104",
    "sg:province":"CA",
    "sg:tags":[
        "photographer"
    ],
    "wof:name":"Ararat Professional Phtgrphy",
    "wof:placetype":"venue"
},
  "geometry": {"coordinates":[-118.112572,34.169067],"type":"Point"}
}