{
  "type": "Feature",
  "properties": {
    "iso:country":"US",
    "sg:address":"5261 Merchant Cir",
    "sg:city":"Placerville",
    "sg:classifiers":[
        {
            "category":"Manufacturing",
            "subcategory":"Metals",
            "type":"Manufacturing & Wholesale Goods"
        }
    ],
    "sg:phone":"+1 530 626 5277",
    "sg:postcode":"95667",
    "sg:province":"CA",
    "sg:tags":[
        "shop",
        "welding"
    ],
    "wof:name":"Canyon Metal Inc",
    "wof:placetype":"venue"
},
  "geometry": {"coordinates":[-120.87931500000001,38.677302],"type":"Point"}
}