{
  "type": "Feature",
  "properties": {
    "addr:full":"22201 Cypress Pl Santa Clarita CA 91390",
    "addr:housenumber":"22201",
    "addr:postcode":"91390",
    "addr:street":"Cypress Pl",
    "iso:country":"US",
    "sg:address":"22201 Cypress Pl",
    "sg:city":"Santa Clarita",
    "sg:classifiers":[
        {
            "category":"Education",
            "subcategory":"School",
            "type":"Public Place"
        }
    ],
    "sg:phone":"+1 661 297 8835",
    "sg:postcode":"91390",
    "sg:province":"CA",
    "sg:tags":[
        "high",
        "middle",
        "elementary"
    ],
    "wof:name":"Mountain View Elementary School",
    "wof:placetype":"venue"
},
  "geometry": {"coordinates":[-118.528999,34.4716],"type":"Point"}
}