{
  "type": "Feature",
  "properties": {
    "iso:country":"US",
    "sg:address":"2318 Potrero Ave",
    "sg:city":"South El Monte",
    "sg:classifiers":[
        {
            "category":"Manufacturing",
            "subcategory":"Apparel",
            "type":"Manufacturing & Wholesale Goods"
        }
    ],
    "sg:phone":"+1 626 579 1361",
    "sg:postcode":"91733",
    "sg:province":"CA",
    "sg:tags":[
        "sewing",
        "contractor"
    ],
    "wof:name":"Estancia Investments Inc",
    "wof:placetype":"venue"
},
  "geometry": {"coordinates":[-118.055566,34.055208],"type":"Point"}
}