{
  "type": "Feature",
  "properties": {
    "iso:country":"US",
    "sg:address":"37120 Fremont Blvd",
    "sg:city":"Fremont",
    "sg:classifiers":[
        {
            "category":"Shopping",
            "subcategory":"Bicycles & Sporting Goods",
            "type":"Retail Goods"
        }
    ],
    "sg:phone":"+1 510 793 0566",
    "sg:postcode":"94536",
    "sg:province":"CA",
    "wof:name":"Start To Finish Bicycles",
    "wof:placetype":"venue"
},
  "geometry": {"coordinates":[-122.01169299999999,37.56059],"type":"Point"}
}