{
  "type": "Feature",
  "properties": {
    "iso:country":"US",
    "sg:address":"8430 Rosedale Hwy",
    "sg:city":"Bakersfield",
    "sg:classifiers":[
        {
            "category":"Personal",
            "subcategory":"Beauty Salon",
            "type":"Services"
        }
    ],
    "sg:phone":"+1 661 589 4922",
    "sg:postcode":"93312",
    "sg:province":"CA",
    "wof:name":"Great Clips",
    "wof:placetype":"venue"
},
  "geometry": {"coordinates":[-119.098376,35.383505],"type":"Point"}
}