{
  "type": "Feature",
  "properties": {
    "addr:full":"2250 Rockefeller Dr Ceres CA 95307",
    "addr:housenumber":"2250",
    "addr:postcode":"95307",
    "addr:street":"Rockefeller Dr",
    "iso:country":"US",
    "sg:address":"2250 Rockefeller Dr",
    "sg:city":"Ceres",
    "sg:classifiers":[
        {
            "category":"Social Services",
            "subcategory":"Child Care",
            "type":"Services"
        }
    ],
    "sg:phone":"+1 209 581 9000",
    "sg:postcode":"95307",
    "sg:province":"CA",
    "sg:tags":[
        "day"
    ],
    "wof:name":"STANISLAUS COUNTY CHILD & INFANT CARE ASSOCIATION INC",
    "wof:placetype":"venue"
},
  "geometry": {"coordinates":[-120.970151,37.596833],"type":"Point"}
}