{
  "type": "Feature",
  "properties": {
    "iso:country":"US",
    "sg:address":"1955 W Slauson Ave",
    "sg:city":"Los Angeles",
    "sg:classifiers":[
        {
            "category":"Food & Beverages",
            "subcategory":"Groceries & Convenience Stores",
            "type":"Retail Goods"
        }
    ],
    "sg:phone":"+1 323 294 2688",
    "sg:postcode":"90047",
    "sg:province":"CA",
    "sg:tags":[
        "grocer"
    ],
    "wof:name":"Johns Sav-Mor Market",
    "wof:placetype":"venue"
},
  "geometry": {"coordinates":[-118.313755,33.989193],"type":"Point"}
}