{
  "type": "Feature",
  "properties": {
    "iso:country":"US",
    "sg:address":"74109 Larrea St",
    "sg:city":"Palm Desert",
    "sg:classifiers":[
        {
            "category":"Organizations",
            "subcategory":"Religious Organization",
            "type":"Services"
        }
    ],
    "sg:phone":"+1 760 568 9901",
    "sg:postcode":"92260",
    "sg:province":"CA",
    "sg:tags":[
        "church"
    ],
    "sg:website":"www.stgeorgeorthodoxchurch.org",
    "wof:name":"Saint George Greek Orthodox Church",
    "wof:placetype":"venue"
},
  "geometry": {"coordinates":[-116.373001,33.718899],"type":"Point"}
}