{
  "type": "Feature",
  "properties": {
    "iso:country":"US",
    "sg:address":"434 N Canal St",
    "sg:city":"S San Francisco",
    "sg:classifiers":[
        {
            "category":"Building & Trades",
            "subcategory":"Construction",
            "type":"Services"
        }
    ],
    "sg:phone":"+1 650 368 6886",
    "sg:postcode":"94080",
    "sg:province":"CA",
    "sg:tags":[
        "specialty"
    ],
    "wof:name":"Alpha West Building Specs",
    "wof:placetype":"venue"
},
  "geometry": {"coordinates":[-122.420077,37.652136],"type":"Point"}
}