{
  "type": "Feature",
  "properties": {
    "addr:full":"605 S Gateway Dr Madera CA 93637",
    "addr:housenumber":"605",
    "addr:postcode":"93637",
    "addr:street":"S Gateway Dr",
    "iso:country":"US",
    "sg:address":"605 S Gateway Dr",
    "sg:city":"Madera",
    "sg:classifiers":[
        {
            "category":"Government",
            "subcategory":"Jail",
            "type":"Public Place"
        }
    ],
    "sg:phone":"+1 559 675 2120",
    "sg:postcode":"93637",
    "sg:province":"CA",
    "sg:tags":[
        "parole",
        "unit"
    ],
    "wof:name":"Parole Unit Office",
    "wof:placetype":"venue"
},
  "geometry": {"coordinates":[-120.055261,36.956266],"type":"Point"}
}