{
  "type": "Feature",
  "properties": {
    "addr:full":"441 Clement St San Francisco CA 94118",
    "addr:housenumber":"441",
    "addr:postcode":"94118",
    "addr:street":"Clement St",
    "iso:country":"US",
    "sg:address":"441 Clement St",
    "sg:city":"San Francisco",
    "sg:classifiers":[
        {
            "category":"Bars & Pubs",
            "type":"Food & Drink"
        },
        {
            "category":"Restaurant",
            "type":"Food & Drink"
        }
    ],
    "sg:menulink":"http://www.allmenus.com/ca/san-francisco/62755-bitter-end/menu/",
    "sg:phone":"+1 415 221 9538",
    "sg:postcode":"94118",
    "sg:province":"CA",
    "sg:tags":[
        "american"
    ],
    "wof:name":"Bitter End",
    "wof:placetype":"venue"
},
  "geometry": {"coordinates":[-122.463843,37.78302],"type":"Point"}
}