{
  "type": "Feature",
  "properties": {
    "iso:country":"US",
    "sg:address":"1031 Poplar Ave",
    "sg:city":"Wasco",
    "sg:classifiers":[
        {
            "category":"Wholesale",
            "subcategory":"Hardware",
            "type":"Manufacturing & Wholesale Goods"
        }
    ],
    "sg:phone":"+1 661 758 8227",
    "sg:postcode":"93280",
    "sg:province":"CA",
    "sg:tags":[
        "refrigeration"
    ],
    "wof:name":"J M Refrigeration Service",
    "wof:placetype":"venue"
},
  "geometry": {"coordinates":[-119.344937,35.59038],"type":"Point"}
}