{
  "type": "Feature",
  "properties": {
    "addr:full":"3020 W Ramsey St Banning CA 92220",
    "addr:housenumber":"3020",
    "addr:postcode":"92220",
    "addr:street":"W Ramsey St",
    "iso:country":"US",
    "sg:address":"3020 W Ramsey St",
    "sg:city":"Banning",
    "sg:classifiers":[
        {
            "category":"Travel",
            "subcategory":"Hotels & Motels",
            "type":"Entertainment"
        },
        {
            "category":"Retail",
            "subcategory":"Event Space",
            "type":"Services"
        }
    ],
    "sg:phone":"+1 800 345 8082",
    "sg:postcode":"92220",
    "sg:province":"CA",
    "sg:tags":[
        "facility",
        "banquet",
        "reception",
        "lodging",
        "corporate",
        "hall"
    ],
    "sg:website":"http://ad.doubleclick.net/clk;222816988;46581822;v?http://www.hiexpress.com/redirect?path=hd&brandCode=ex&hotelCode=banex&_PMID=99601036&cm_mmc=mdpr-_-yellowpages-_-ex-_-banex",
    "wof:name":"Holiday Inn Express Hotel & Suites Banning",
    "wof:placetype":"venue"
},
  "geometry": {"coordinates":[-116.90982099999999,33.925637],"type":"Point"}
}