{
  "type": "Feature",
  "properties": {
    "iso:country":"US",
    "sg:address":"4240 Lost Hills Rd",
    "sg:city":"Agoura",
    "sg:classifiers":[
        {
            "category":"Professional",
            "subcategory":"Computer Services",
            "type":"Services"
        }
    ],
    "sg:phone":"+1 818 880 5505",
    "sg:postcode":"91301",
    "sg:province":"CA",
    "sg:tags":[
        "repair"
    ],
    "wof:name":"Netsys",
    "wof:placetype":"venue"
},
  "geometry": {"coordinates":[-118.706889,34.136158],"type":"Point"}
}