{
  "type": "Feature",
  "properties": {
    "addr:full":"2101 Webster St Ste 1900 Oakland CA 94612",
    "addr:housenumber":"2101",
    "addr:postcode":"94612",
    "addr:street":"Webster St Ste 1900",
    "iso:country":"US",
    "sg:address":"2101 Webster St Ste 1900",
    "sg:city":"Oakland",
    "sg:classifiers":[
        {
            "category":"Professional",
            "subcategory":"Engineering",
            "type":"Services"
        },
        {
            "category":"Real Estate",
            "subcategory":"Architect",
            "type":"Services"
        }
    ],
    "sg:phone":"+1 510 832 5466",
    "sg:postcode":"94612",
    "sg:province":"CA",
    "sg:tags":[
        "consulting",
        "specification",
        "construction",
        "architectural",
        "engineer"
    ],
    "sg:website":"http://www.jwdgroup.com",
    "wof:name":"Jordan Woodman Dobson",
    "wof:placetype":"venue"
},
  "geometry": {"coordinates":[-122.26583100000001,37.809811],"type":"Point"}
}