{
  "type": "Feature",
  "properties": {
    "addr:full":"219 John St Salinas CA 93901",
    "addr:housenumber":"219",
    "addr:postcode":"93901",
    "addr:street":"John St",
    "iso:country":"US",
    "sg:address":"219 John St",
    "sg:city":"Salinas",
    "sg:classifiers":[
        {
            "category":"Travel",
            "subcategory":"Hotels & Motels",
            "type":"Entertainment"
        }
    ],
    "sg:phone":"+1 831 424 8065",
    "sg:postcode":"93901",
    "sg:province":"CA",
    "wof:name":"Budget Inn Motel",
    "wof:placetype":"venue"
},
  "geometry": {"coordinates":[-121.649038,36.669885],"type":"Point"}
}