{
  "type": "Feature",
  "properties": {
    "addr:full":"10041 Hillview Ave Chatsworth CA 91311",
    "addr:housenumber":"10041",
    "addr:postcode":"91311",
    "addr:street":"Hillview Ave",
    "iso:country":"US",
    "sg:address":"10041 Hillview Ave",
    "sg:city":"Chatsworth",
    "sg:classifiers":[
        {
            "category":"Professional",
            "type":"Services"
        }
    ],
    "sg:phone":"+1 818 349 5584",
    "sg:postcode":"91311",
    "sg:province":"CA",
    "wof:name":"Comp X Systems Inc",
    "wof:placetype":"venue"
},
  "geometry": {"coordinates":[-118.603067,34.25296],"type":"Point"}
}