{
  "type": "Feature",
  "properties": {
    "addr:full":"1255 Sacramento St Redding CA 96001",
    "addr:housenumber":"1255",
    "addr:postcode":"96001",
    "addr:street":"Sacramento St",
    "iso:country":"US",
    "sg:address":"1255 Sacramento St",
    "sg:city":"Redding",
    "sg:classifiers":[
        {
            "category":"Professional",
            "subcategory":"Lawyer & Legal Services",
            "type":"Services"
        }
    ],
    "sg:phone":"+1 530 242 8800",
    "sg:postcode":"96001",
    "sg:province":"CA",
    "sg:tags":[
        "attorney"
    ],
    "wof:name":"Wagner Darryl L Atty. at Law",
    "wof:placetype":"venue"
},
  "geometry": {"coordinates":[-122.38769000000001,40.581839],"type":"Point"}
}