{
  "type": "Feature",
  "properties": {
    "iso:country":"US",
    "sg:address":"3080 La Selva St 2nd Fl",
    "sg:city":"San Mateo",
    "sg:classifiers":[
        {
            "category":"Education",
            "subcategory":"Special Training",
            "type":"Public Place"
        }
    ],
    "sg:phone":"+1 650 377 0988",
    "sg:postcode":"94403",
    "sg:province":"CA",
    "sg:tags":[
        "tutoring"
    ],
    "sg:website":"www.monicalearningcenters.com",
    "wof:name":"Monica Learning Center",
    "wof:placetype":"venue"
},
  "geometry": {"coordinates":[-122.28503499999999,37.543741],"type":"Point"}
}