{
  "type": "Feature",
  "properties": {
    "addr:full":"23907 Restive Way Grass Valley CA 95949",
    "addr:housenumber":"23907",
    "addr:postcode":"95949",
    "addr:street":"Restive Way",
    "iso:country":"US",
    "sg:address":"23907 Restive Way",
    "sg:city":"Grass Valley",
    "sg:classifiers":[
        {
            "category":"Insurance",
            "subcategory":"Insurance Agent",
            "type":"Services"
        }
    ],
    "sg:phone":"+1 530 268 6605",
    "sg:postcode":"95949",
    "sg:province":"CA",
    "wof:name":"Life USA",
    "wof:placetype":"venue"
},
  "geometry": {"coordinates":[-121.16978,39.069661],"type":"Point"}
}