{
  "type": "Feature",
  "properties": {
    "addr:full":"2417 Rockefeller Ln Redondo Beach CA 90278",
    "addr:housenumber":"2417",
    "addr:postcode":"90278",
    "addr:street":"Rockefeller Ln",
    "iso:country":"US",
    "sg:address":"2417 Rockefeller Ln",
    "sg:city":"Redondo Beach",
    "sg:classifiers":[
        {
            "category":"Shopping",
            "subcategory":"Clothing, Apparel, & Fashions",
            "type":"Retail Goods"
        }
    ],
    "sg:phone":"+1 949 706 0778",
    "sg:postcode":"90278",
    "sg:province":"CA",
    "sg:tags":[
        "tailor"
    ],
    "wof:name":"Mosley & Co In-Office Custom",
    "wof:placetype":"venue"
},
  "geometry": {"coordinates":[-118.366677,33.870092],"type":"Point"}
}