{
  "type": "Feature",
  "properties": {
    "addr:full":"5305 N Fresno St Fresno CA 93710",
    "addr:housenumber":"5305",
    "addr:postcode":"93710",
    "addr:street":"N Fresno",
    "iso:country":"US",
    "sg:address":"5305 N Fresno St",
    "sg:city":"Fresno",
    "sg:classifiers":[
        {
            "category":"Local Transit",
            "type":"Transportation"
        }
    ],
    "sg:phone":"+1 559 228 1710",
    "sg:postcode":"93710",
    "sg:province":"CA",
    "sg:tags":[
        "limousine"
    ],
    "wof:name":"Celebrity Limousine Svc",
    "wof:placetype":"venue"
},
  "geometry": {"coordinates":[-119.781406,36.815666],"type":"Point"}
}