{
  "type": "Feature",
  "properties": {
    "iso:country":"US",
    "sg:address":"4127 El Camino Real",
    "sg:city":"Palo Alto",
    "sg:classifiers":[
        {
            "category":"Restaurant",
            "type":"Food & Drink"
        }
    ],
    "sg:menulink":"http://www.allmenus.com/ca/san-jose/47014-tofu-house/menu/",
    "sg:phone":"+1 650 424 8805",
    "sg:postcode":"94306",
    "sg:province":"CA",
    "sg:tags":[
        "korean",
        "asian"
    ],
    "wof:name":"Tofu House",
    "wof:placetype":"venue"
},
  "geometry": {"coordinates":[-122.124612,37.412161],"type":"Point"}
}