{
  "type": "Feature",
  "properties": {
    "addr:full":"2237 Union Ridge Rd Placerville CA 95667",
    "addr:housenumber":"2237",
    "addr:postcode":"95667",
    "addr:street":"Union Ridge Rd",
    "iso:country":"US",
    "sg:address":"2237 Union Ridge Rd",
    "sg:city":"Placerville",
    "sg:classifiers":[
        {
            "category":"Building & Trades",
            "subcategory":"Construction",
            "type":"Services"
        }
    ],
    "sg:phone":"+1 530 621 3406",
    "sg:postcode":"95667",
    "sg:province":"CA",
    "sg:tags":[
        "dry wall",
        "contractor"
    ],
    "wof:name":"Mountain Drywall",
    "wof:placetype":"venue"
},
  "geometry": {"coordinates":[-120.750214,38.746457],"type":"Point"}
}