{
  "type": "Feature",
  "properties": {
    "addr:full":"120 Pleasant Hill Ave N Sebastopol CA 95472",
    "addr:housenumber":"120",
    "addr:postcode":"95472",
    "addr:street":"Pleasant Hill Ave N",
    "iso:country":"US",
    "sg:address":"120 Pleasant Hill Ave N",
    "sg:city":"Sebastopol",
    "sg:classifiers":[
        {
            "category":"Health Services",
            "subcategory":"Doctor",
            "type":"Services"
        }
    ],
    "sg:phone":"+1 707 823 3806",
    "sg:postcode":"95472",
    "sg:province":"CA",
    "sg:tags":[
        "psychologist"
    ],
    "wof:name":"Herzig Cori Psy D",
    "wof:placetype":"venue"
},
  "geometry": {"coordinates":[-122.83943600000001,38.398242],"type":"Point"}
}