{
  "type": "Feature",
  "properties": {
    "addr:full":"2300 E 57th St Los Angeles CA 90058",
    "addr:housenumber":"2300",
    "addr:postcode":"90058",
    "addr:street":"E 57Th St",
    "iso:country":"US",
    "sg:address":"2300 E 57th St",
    "sg:city":"Los Angeles",
    "sg:classifiers":[
        {
            "category":"Wholesale",
            "subcategory":"Machinery & Supplies",
            "type":"Manufacturing & Wholesale Goods"
        },
        {
            "category":"Wholesale",
            "subcategory":"Groceries",
            "type":"Manufacturing & Wholesale Goods"
        }
    ],
    "sg:phone":"+1 323 583 0800",
    "sg:postcode":"90058",
    "sg:province":"CA",
    "sg:tags":[
        "meat",
        "food",
        "frozen",
        "beer",
        "fresh",
        "janitor"
    ],
    "wof:name":"Jetro Cash and Carry",
    "wof:placetype":"venue"
},
  "geometry": {"coordinates":[-118.23196,33.991112],"type":"Point"}
}