{
  "type": "Feature",
  "properties": {
    "iso:country":"US",
    "sg:address":"8236 De Soto Ave",
    "sg:city":"Canoga Park",
    "sg:classifiers":[
        {
            "category":"Personal",
            "subcategory":"Nail Salon",
            "type":"Services"
        }
    ],
    "sg:phone":"+1 818 882 0262",
    "sg:postcode":"91304",
    "sg:province":"CA",
    "wof:name":"A Plus Nail",
    "wof:placetype":"venue"
},
  "geometry": {"coordinates":[-118.587997,34.219002],"type":"Point"}
}