{
  "type": "Feature",
  "properties": {
    "iso:country":"US",
    "sg:address":"2560 Wyandotte St",
    "sg:city":"Mountain View",
    "sg:classifiers":[
        {
            "category":"Professional",
            "type":"Services"
        }
    ],
    "sg:phone":"+1 650 962 1568",
    "sg:postcode":"94043",
    "sg:province":"CA",
    "sg:tags":[
        "establishment"
    ],
    "wof:name":"David Findley Co",
    "wof:placetype":"venue"
},
  "geometry": {"coordinates":[-122.100142,37.417001],"type":"Point"}
}