{
  "type": "Feature",
  "properties": {
    "addr:full":"710 Miles Ave Santa Maria CA 93455",
    "addr:housenumber":"710",
    "addr:postcode":"93455",
    "addr:street":"Miles Ave",
    "iso:country":"US",
    "sg:address":"710 Miles Ave",
    "sg:city":"Santa Maria",
    "sg:classifiers":[
        {
            "category":"Building & Trades",
            "subcategory":"Plumbing",
            "type":"Services"
        }
    ],
    "sg:phone":"+1 805 928 4533",
    "sg:postcode":"93455",
    "sg:province":"CA",
    "sg:tags":[
        "plumbing",
        "contractor"
    ],
    "wof:name":"Curt's Plumbing & Heating",
    "wof:placetype":"venue"
},
  "geometry": {"coordinates":[-120.42687100000001,34.894953],"type":"Point"}
}