{
  "type": "Feature",
  "properties": {
    "iso:country":"US",
    "sg:address":"1053 El Camino Real # F",
    "sg:city":"South San Francisco",
    "sg:classifiers":[
        {
            "category":"Retail",
            "subcategory":"Laundry & Dry Cleaning",
            "type":"Services"
        }
    ],
    "sg:phone":"+1 650 588 3599",
    "sg:postcode":"94080",
    "sg:province":"CA",
    "wof:name":"My Cleaners",
    "wof:placetype":"venue"
},
  "geometry": {"coordinates":[-122.435529,37.655865],"type":"Point"}
}