{
  "type": "Feature",
  "properties": {
    "addr:full":"6255 College Ave Oakland CA 94618",
    "addr:housenumber":"6255",
    "addr:postcode":"94618",
    "addr:street":"College Ave",
    "iso:country":"US",
    "sg:address":"6255 College Ave",
    "sg:city":"Oakland",
    "sg:classifiers":[
        {
            "category":"Coffee & Tea",
            "type":"Food & Drink"
        }
    ],
    "sg:phone":"+1 510 653 5453",
    "sg:postcode":"94618",
    "sg:province":"CA",
    "sg:tags":[
        "espresso",
        "restaurant"
    ],
    "sg:website":"www.colecoffee.com",
    "wof:name":"Cole Coffee",
    "wof:placetype":"venue"
},
  "geometry": {"coordinates":[-122.25234399999999,37.850133],"type":"Point"}
}