{
  "type": "Feature",
  "properties": {
    "addr:full":"10 12th St Tracy CA 95376",
    "addr:housenumber":"10",
    "addr:postcode":"95376",
    "addr:street":"12Th St",
    "iso:country":"US",
    "sg:address":"10 12th St",
    "sg:city":"Tracy",
    "sg:classifiers":[
        {
            "category":"Banks & Credit Unions",
            "subcategory":"Bank",
            "type":"Services"
        }
    ],
    "sg:phone":"+1 925 736 1125",
    "sg:postcode":"95376",
    "sg:province":"CA",
    "wof:name":"Wells Fargo Home Mortgage Inc",
    "wof:placetype":"venue"
},
  "geometry": {"coordinates":[-121.425241,37.74059],"type":"Point"}
}