{
  "type": "Feature",
  "properties": {
    "iso:country":"US",
    "sg:address":"22263 S Warren Rd",
    "sg:city":"Ripon",
    "sg:classifiers":[
        {
            "category":"Professional",
            "type":"Services"
        }
    ],
    "sg:phone":"+1 209 599 2365",
    "sg:postcode":"95366",
    "sg:province":"CA",
    "wof:name":"Jay Hoff",
    "wof:placetype":"venue"
},
  "geometry": {"coordinates":[-121.133538,37.755107],"type":"Point"}
}