{
  "type": "Feature",
  "properties": {
    "addr:full":"804 W Manchester Boulevard Inglewood CA 90301",
    "addr:housenumber":"804",
    "addr:postcode":"90301",
    "addr:street":"W Manchester Boulevard",
    "iso:country":"US",
    "sg:address":"804 W Manchester Boulevard",
    "sg:city":"Inglewood",
    "sg:classifiers":[
        {
            "category":"Autos & Motor Vehicles",
            "subcategory":"Fuel & Gas Station",
            "type":"Retail Goods"
        }
    ],
    "sg:phone":"+1 310 342 0470",
    "sg:postcode":"90301",
    "sg:province":"CA",
    "sg:website":"www.shell.com",
    "wof:name":"Shell",
    "wof:placetype":"venue"
},
  "geometry": {"coordinates":[-118.370558,33.961683],"type":"Point"}
}