{
  "type": "Feature",
  "properties": {
    "addr:full":"169 Jackson St San Jose CA 95112",
    "addr:housenumber":"169",
    "addr:postcode":"95112",
    "addr:street":"Jackson St",
    "iso:country":"US",
    "sg:address":"169 Jackson St",
    "sg:city":"San Jose",
    "sg:classifiers":[
        {
            "category":"Personal",
            "subcategory":"Nail Salon",
            "type":"Services"
        }
    ],
    "sg:phone":"+1 408 275 1625",
    "sg:postcode":"95112",
    "sg:province":"CA",
    "sg:website":"www.sakuranailbar.com",
    "wof:name":"Sakura Nail Bar",
    "wof:placetype":"venue"
},
  "geometry": {"coordinates":[-121.89513100000001,37.348811],"type":"Point"}
}