{
  "type": "Feature",
  "properties": {
    "addr:full":"3831 Roeding Rd Ceres CA 95307",
    "addr:housenumber":"3831",
    "addr:postcode":"95307",
    "addr:street":"Roeding Rd",
    "iso:country":"US",
    "sg:address":"3831 Roeding Rd",
    "sg:city":"Ceres",
    "sg:classifiers":[
        {
            "category":"Professional",
            "subcategory":"Lawyer & Legal Services",
            "type":"Services"
        }
    ],
    "sg:phone":"+1 209 538 9795",
    "sg:postcode":"95307",
    "sg:province":"CA",
    "sg:tags":[
        "personal",
        "attorney",
        "injury"
    ],
    "wof:name":"Cousins & Edington Law Offices of",
    "wof:placetype":"venue"
},
  "geometry": {"coordinates":[-120.924004,37.587399],"type":"Point"}
}