{
  "type": "Feature",
  "properties": {
    "iso:country":"US",
    "sg:address":"9501 Atlantic Ave",
    "sg:city":"South Gate",
    "sg:classifiers":[
        {
            "category":"Autos & Motor Vehicles",
            "subcategory":"Auto Supplies",
            "type":"Retail Goods"
        },
        {
            "category":"Retail",
            "subcategory":"Auto Repair",
            "type":"Services"
        }
    ],
    "sg:phone":"+1 323 564 5797",
    "sg:postcode":"90280",
    "sg:province":"CA",
    "sg:tags":[
        "tire"
    ],
    "sg:website":"www.citytireonline.com",
    "wof:name":"City Tire Service",
    "wof:placetype":"venue"
},
  "geometry": {"coordinates":[-118.181267,33.945919],"type":"Point"}
}