{
  "type": "Feature",
  "properties": {
    "iso:country":"US",
    "sg:address":"Hair Studio Janusz 4663 Park Blvd",
    "sg:city":"San Diego",
    "sg:classifiers":[
        {
            "category":"Personal",
            "subcategory":"Beauty Salon",
            "type":"Services"
        }
    ],
    "sg:phone":"+1 619 865 8822",
    "sg:postcode":"92116",
    "sg:province":"CA",
    "sg:tags":[
        "hair"
    ],
    "wof:name":"Stan B",
    "wof:placetype":"venue"
},
  "geometry": {"coordinates":[-117.14627400000001,32.762185],"type":"Point"}
}