{
  "type": "Feature",
  "properties": {
    "addr:full":"17220 Lambert Rd Ione CA 95640",
    "addr:housenumber":"17220",
    "addr:postcode":"ca 95640",
    "addr:street":"Lambert Rd",
    "iso:country":"US",
    "sg:address":"17220 Lambert Rd",
    "sg:city":"Ione",
    "sg:classifiers":[
        {
            "category":"Manufacturing",
            "subcategory":"Tools & Machinery",
            "type":"Manufacturing & Wholesale Goods"
        }
    ],
    "sg:phone":"+1 209 274 4422",
    "sg:postcode":"95640",
    "sg:province":"CA",
    "sg:tags":[
        "machine",
        "shop"
    ],
    "wof:name":"Hovey Machine Products",
    "wof:placetype":"venue"
},
  "geometry": {"coordinates":[-121.011448,38.440737],"type":"Point"}
}