{
  "type": "Feature",
  "properties": {
    "addr:full":"4121 Warda Ave Keyes CA 95328",
    "addr:housenumber":"4121",
    "addr:postcode":"95328",
    "addr:street":"Warda Ave",
    "iso:country":"US",
    "sg:address":"4121 Warda Ave",
    "sg:city":"Keyes",
    "sg:classifiers":[
        {
            "category":"Building & Trades",
            "subcategory":"Cleaning & Sanitation",
            "type":"Services"
        }
    ],
    "sg:phone":"+1 209 669 9182",
    "sg:postcode":"95328",
    "sg:province":"CA",
    "sg:tags":[
        "cleaners-interior"
    ],
    "wof:name":"A1 House Cleaning",
    "wof:placetype":"venue"
},
  "geometry": {"coordinates":[-120.91831999999999,37.559016],"type":"Point"}
}