{
  "type": "Feature",
  "properties": {
    "addr:full":"3101 E Cade St Long Beach CA 90805",
    "addr:housenumber":"3101",
    "addr:postcode":"90805",
    "addr:street":"E Cade St",
    "iso:country":"US",
    "sg:address":"3101 E Cade St",
    "sg:city":"Long Beach",
    "sg:classifiers":[
        {
            "category":"Professional",
            "type":"Services"
        }
    ],
    "sg:phone":"+1 562 422 3903",
    "sg:postcode":"90805",
    "sg:province":"CA",
    "wof:name":"Mavis I Wallen",
    "wof:placetype":"venue"
},
  "geometry": {"coordinates":[-118.156548,33.871793],"type":"Point"}
}