{
  "type": "Feature",
  "properties": {
    "addr:full":"9306 Washington Blvd Pico Rivera CA 90660",
    "addr:housenumber":"9306",
    "addr:postcode":"90660",
    "addr:street":"Washington Blvd",
    "iso:country":"US",
    "sg:address":"9306 Washington Blvd",
    "sg:city":"Pico Rivera",
    "sg:classifiers":[
        {
            "category":"Personal",
            "subcategory":"Beauty Salon",
            "type":"Services"
        }
    ],
    "sg:phone":"+1 562 801 0044",
    "sg:postcode":"90660",
    "sg:province":"CA",
    "wof:name":"Bellizima",
    "wof:placetype":"venue"
},
  "geometry": {"coordinates":[-118.091275,33.979917],"type":"Point"}
}