{
  "type": "Feature",
  "properties": {
    "addr:full":"2577 Guerneville Rd Santa Rosa CA 95401",
    "addr:housenumber":"2577",
    "addr:postcode":"95401",
    "addr:street":"Guerneville Rd",
    "iso:country":"US",
    "sg:address":"2577 Guerneville Rd",
    "sg:city":"Santa Rosa",
    "sg:classifiers":[
        {
            "category":"Social Services",
            "subcategory":"Child Care",
            "type":"Services"
        }
    ],
    "sg:phone":"+1 707 528 6666",
    "sg:postcode":"95401",
    "sg:province":"CA",
    "wof:name":"Woodside West School",
    "wof:placetype":"venue"
},
  "geometry": {"coordinates":[-122.775194,38.452617],"type":"Point"}
}