{
  "type": "Feature",
  "properties": {
    "addr:full":"615 Lindsay Ct Angels Camp CA 95222",
    "addr:housenumber":"615",
    "addr:postcode":"95222",
    "addr:street":"Lindsay Ct",
    "iso:country":"US",
    "sg:address":"615 Lindsay Ct",
    "sg:city":"Angels Camp",
    "sg:classifiers":[
        {
            "category":"Building & Trades",
            "subcategory":"Construction",
            "type":"Services"
        }
    ],
    "sg:phone":"+1 209 483 5243",
    "sg:postcode":"95222",
    "sg:province":"CA",
    "sg:tags":[
        "house"
    ],
    "wof:name":"Jarman Construction",
    "wof:placetype":"venue"
},
  "geometry": {"coordinates":[-120.557709,38.066439],"type":"Point"}
}