{
  "type": "Feature",
  "properties": {
    "addr:full":"300 California St San Francisco CA 94104",
    "addr:housenumber":"300",
    "addr:postcode":"94104",
    "addr:street":"California St",
    "iso:country":"US",
    "sg:address":"300 California St",
    "sg:city":"San Francisco",
    "sg:classifiers":[
        {
            "category":"Coffee & Tea",
            "type":"Food & Drink"
        },
        {
            "category":"Food & Beverages",
            "subcategory":"Bakery",
            "type":"Retail Goods"
        },
        {
            "category":"Bakery",
            "type":"Food & Drink"
        }
    ],
    "sg:phone":"+1 415 362 3332",
    "sg:postcode":"94104",
    "sg:province":"CA",
    "sg:tags":[
        "sandwich"
    ],
    "sg:website":"www.cafemadeleinesf.com",
    "wof:name":"Cafe Madeleine",
    "wof:placetype":"venue"
},
  "geometry": {"coordinates":[-122.399929,37.793275],"type":"Point"}
}