{
  "type": "Feature",
  "properties": {
    "addr:full":"912 41st St Sacramento CA 95819",
    "addr:housenumber":"912",
    "addr:postcode":"95819",
    "addr:street":"41St St",
    "iso:country":"US",
    "sg:address":"912 41st St",
    "sg:city":"Sacramento",
    "sg:classifiers":[
        {
            "category":"Home & Garden",
            "subcategory":"Home Furnishings",
            "type":"Retail Goods"
        },
        {
            "category":"Home & Garden",
            "subcategory":"Building Materials",
            "type":"Retail Goods"
        },
        {
            "category":"Manufacturing",
            "subcategory":"Glass & Minerals",
            "type":"Manufacturing & Wholesale Goods"
        }
    ],
    "sg:phone":"+1 916 457 3633",
    "sg:postcode":"95819",
    "sg:province":"CA",
    "sg:tags":[
        "bathroom",
        "baths-equipment",
        "supply",
        "cabinet",
        "glass-wholesale",
        "shape",
        "fixtures",
        "accessory",
        "circle",
        "special",
        "manufacturer"
    ],
    "wof:name":"Stephen Glass Maron",
    "wof:placetype":"venue"
},
  "geometry": {"coordinates":[-121.45129799999999,38.570134],"type":"Point"}
}