{
  "type": "Feature",
  "properties": {
    "iso:country":"US",
    "sg:address":"2852 Walnut Ave",
    "sg:city":"Tustin",
    "sg:classifiers":[
        {
            "category":"Manufacturing",
            "subcategory":"Electronics",
            "type":"Manufacturing & Wholesale Goods"
        }
    ],
    "sg:phone":"+1 714 508 7484",
    "sg:postcode":"92780",
    "sg:province":"CA",
    "sg:tags":[
        "printed",
        "circuit",
        "etched"
    ],
    "wof:name":"2S2 Inc",
    "wof:placetype":"venue"
},
  "geometry": {"coordinates":[-117.80496,33.713568],"type":"Point"}
}