{
  "type": "Feature",
  "properties": {
    "addr:full":"5101 Imperial Hwy South Gate CA 90280",
    "addr:housenumber":"5101",
    "addr:postcode":"90280",
    "addr:street":"Imperial Hwy;Gate",
    "iso:country":"US",
    "sg:address":"5101 Imperial Hwy",
    "sg:city":"South Gate",
    "sg:classifiers":[
        {
            "category":"Fast Food",
            "type":"Food & Drink"
        }
    ],
    "sg:phone":"+1 310 638 4422",
    "sg:postcode":"90280",
    "sg:province":"CA",
    "wof:name":"Church's Fried Chicken",
    "wof:placetype":"venue"
},
  "geometry": {"coordinates":[-118.18223,33.93089],"type":"Point"}
}