{
  "type": "Feature",
  "properties": {
    "addr:full":"1749 Santa Fe Ave Long Beach CA 90813",
    "addr:housenumber":"1749",
    "addr:postcode":"90813",
    "addr:street":"Santa Fe Ave",
    "iso:country":"US",
    "sg:address":"1749 Santa Fe Ave",
    "sg:city":"Long Beach",
    "sg:classifiers":[
        {
            "category":"Retail",
            "subcategory":"Auto Repair",
            "type":"Services"
        }
    ],
    "sg:phone":"+1 562 495 2585",
    "sg:postcode":"90813",
    "sg:province":"CA",
    "wof:name":"Southside Customs",
    "wof:placetype":"venue"
},
  "geometry": {"coordinates":[-118.215614,33.789007],"type":"Point"}
}