{
  "type": "Feature",
  "properties": {
    "addr:full":"1605 E Palmdale Blvd Palmdale CA 93550",
    "addr:housenumber":"1605",
    "addr:postcode":"ca 93550",
    "addr:street":"E Palmdale Blvd",
    "iso:country":"US",
    "sg:address":"1605 E Palmdale Blvd",
    "sg:city":"Palmdale",
    "sg:classifiers":[
        {
            "category":"Health Services",
            "subcategory":"Health Practitioner",
            "type":"Services"
        }
    ],
    "sg:phone":"+1 661 273 5333",
    "sg:postcode":"93550",
    "sg:province":"CA",
    "sg:tags":[
        "therapist",
        "physical"
    ],
    "wof:name":"Cloughley, Shelly MPT",
    "wof:placetype":"venue"
},
  "geometry": {"coordinates":[-118.10101,34.579651],"type":"Point"}
}