{
  "type": "Feature",
  "properties": {
    "addr:full":"1605 E 4th St National City CA 91950",
    "addr:housenumber":"1605",
    "addr:postcode":"91950",
    "addr:street":"E 4Th St",
    "iso:country":"US",
    "sg:address":"1605 E 4th St",
    "sg:city":"National City",
    "sg:classifiers":[
        {
            "category":"Food & Beverages",
            "subcategory":"Groceries & Convenience Stores",
            "type":"Retail Goods"
        }
    ],
    "sg:phone":"+1 619 477 2374",
    "sg:postcode":"91950",
    "sg:province":"CA",
    "sg:tags":[
        "grocer"
    ],
    "wof:name":"Gama Produce",
    "wof:placetype":"venue"
},
  "geometry": {"coordinates":[-117.090931,32.684221],"type":"Point"}
}