{
  "type": "Feature",
  "properties": {
    "addr:full":"1312 Fulton Ave Sacramento CA 95825",
    "addr:housenumber":"1312",
    "addr:postcode":"95825",
    "addr:street":"Fulton Ave",
    "iso:country":"US",
    "sg:address":"1312 Fulton Ave",
    "sg:city":"Sacramento",
    "sg:classifiers":[
        {
            "category":"Arts & Performance",
            "subcategory":"Music",
            "type":"Entertainment"
        }
    ],
    "sg:phone":"+1 916 652 8970",
    "sg:postcode":"95825",
    "sg:province":"CA",
    "sg:tags":[
        "musician"
    ],
    "wof:name":"Ssgma",
    "wof:placetype":"venue"
},
  "geometry": {"coordinates":[-121.401517,38.588996],"type":"Point"}
}