{
  "type": "Feature",
  "properties": {
    "addr:full":"501 I St Ste 12600 Sacramento CA 95814",
    "addr:housenumber":"501",
    "addr:postcode":"95814",
    "addr:street":"I St Ste 12600",
    "iso:country":"US",
    "sg:address":"501 I St Ste 12600",
    "sg:city":"Sacramento",
    "sg:classifiers":[
        {
            "category":"Government",
            "subcategory":"Court House",
            "type":"Public Place"
        },
        {
            "category":"Government",
            "subcategory":"Office",
            "type":"Public Place"
        }
    ],
    "sg:phone":"+1 916 498 5600",
    "sg:postcode":"95814",
    "sg:province":"CA",
    "sg:tags":[
        "justice",
        "government-united",
        "state"
    ],
    "sg:website":"http://www.house.gov",
    "wof:name":"Congressman Robert T. Matsui",
    "wof:placetype":"venue"
},
  "geometry": {"coordinates":[-121.498833,38.582951],"type":"Point"}
}