{
  "type": "Feature",
  "properties": {
    "addr:full":"7800 Sunrise Blvd Citrus Heights CA 95610",
    "addr:housenumber":"7800",
    "addr:postcode":"95610",
    "addr:street":"Sunrise Blvd",
    "iso:country":"US",
    "sg:address":"7800 Sunrise Blvd",
    "sg:city":"Citrus Heights",
    "sg:classifiers":[
        {
            "category":"Banks & Credit Unions",
            "subcategory":"Bank",
            "type":"Services"
        }
    ],
    "sg:phone":"+1 916 722 3495",
    "sg:postcode":"95610",
    "sg:province":"CA",
    "sg:tags":[
        "cashing",
        "check"
    ],
    "wof:name":"California Check Cashing",
    "wof:placetype":"venue"
},
  "geometry": {"coordinates":[-121.271761,38.709286],"type":"Point"}
}