{
  "type": "Feature",
  "properties": {
    "iso:country":"US",
    "sg:address":"8438 Kirkwood Dr",
    "sg:city":"Los Angeles",
    "sg:classifiers":[
        {
            "category":"Communications",
            "subcategory":"Film & Video Production",
            "type":"Services"
        }
    ],
    "sg:phone":"+1 323 656 5548",
    "sg:postcode":"90046",
    "sg:province":"CA",
    "sg:tags":[
        "motion",
        "picture"
    ],
    "wof:name":"Red Beard Films Inc",
    "wof:placetype":"venue"
},
  "geometry": {"coordinates":[-118.374021,34.103501],"type":"Point"}
}