{
  "type": "Feature",
  "properties": {
    "addr:full":"300 Lakeside Dr Oakland CA 94612",
    "addr:housenumber":"300",
    "addr:postcode":"94612",
    "addr:street":"Lakeside Dr",
    "iso:country":"US",
    "sg:address":"300 Lakeside Dr",
    "sg:city":"Oakland",
    "sg:classifiers":[
        {
            "category":"Education",
            "subcategory":"College",
            "type":"Public Place"
        }
    ],
    "sg:phone":"+1 510 987 0700",
    "sg:postcode":"94612",
    "sg:province":"CA",
    "sg:tags":[
        "university"
    ],
    "wof:name":"Informtion Rsrces Cmmnications",
    "wof:placetype":"venue"
},
  "geometry": {"coordinates":[-122.26378,37.808927],"type":"Point"}
}