{
  "type": "Feature",
  "properties": {
    "iso:country":"US",
    "sg:address":"5890 Sumner Ave",
    "sg:city":"Ontario",
    "sg:classifiers":[
        {
            "category":"Freight",
            "type":"Transportation"
        }
    ],
    "sg:phone":"+1 909 947 3963",
    "sg:postcode":"91762",
    "sg:province":"CA",
    "sg:tags":[
        "trucking"
    ],
    "wof:name":"K B Transportation",
    "wof:placetype":"venue"
},
  "geometry": {"coordinates":[-117.575469,33.983079],"type":"Point"}
}