{
  "type": "Feature",
  "properties": {
    "addr:full":"2715 Grey Fox Dr Weed CA 96094",
    "addr:housenumber":"2715",
    "addr:postcode":"96094",
    "addr:street":"Grey Fox Dr",
    "iso:country":"US",
    "sg:address":"2715 Grey Fox Dr",
    "sg:city":"Weed",
    "sg:classifiers":[
        {
            "category":"Manufacturing",
            "subcategory":"Toys & Sporting Goods",
            "type":"Manufacturing & Wholesale Goods"
        }
    ],
    "sg:phone":"+1 530 938 1941",
    "sg:postcode":"96094",
    "sg:province":"CA",
    "sg:tags":[
        "mfg"
    ],
    "wof:name":"Quetzal Imports",
    "wof:placetype":"venue"
},
  "geometry": {"coordinates":[-122.41627,41.368613],"type":"Point"}
}