{
  "type": "Feature",
  "properties": {
    "addr:full":"216 11th St San Francisco CA 94103",
    "addr:housenumber":"216",
    "addr:postcode":"94103",
    "addr:street":"11Th St",
    "iso:country":"US",
    "sg:address":"216 11th St",
    "sg:city":"San Francisco",
    "sg:classifiers":[
        {
            "category":"Retail",
            "subcategory":"Repair Shop",
            "type":"Services"
        }
    ],
    "sg:phone":"+1 415 621 7088",
    "sg:postcode":"94103",
    "sg:province":"CA",
    "sg:tags":[
        "equipment",
        "industrial"
    ],
    "wof:name":"Enerpac Representive",
    "wof:placetype":"venue"
},
  "geometry": {"coordinates":[-122.415216,37.772761],"type":"Point"}
}