{
  "type": "Feature",
  "properties": {
    "addr:full":"1199 Avenida Acaso Ste F Camarillo CA 93012",
    "addr:housenumber":"1199",
    "addr:postcode":"93012",
    "addr:street":"Avenida Acaso Ste F",
    "iso:country":"US",
    "sg:address":"1199 Avenida Acaso Ste F",
    "sg:city":"Camarillo",
    "sg:classifiers":[
        {
            "category":"Manufacturing",
            "subcategory":"Aerospace",
            "type":"Manufacturing & Wholesale Goods"
        },
        {
            "category":"Autos & Motor Vehicles",
            "subcategory":"Recreational Vehicle Sales",
            "type":"Retail Goods"
        }
    ],
    "sg:phone":"+1 805 482 1334",
    "sg:postcode":"93012",
    "sg:province":"CA",
    "sg:tags":[
        "equipment",
        "aircraft",
        "part",
        "supplies-wholesale",
        "manufacturer"
    ],
    "sg:website":"http://www.pdqeng.com",
    "wof:name":"Pdq Engineering, Inc.",
    "wof:placetype":"venue"
},
  "geometry": {"coordinates":[-119.011869,34.228499],"type":"Point"}
}