{
  "type": "Feature",
  "properties": {
    "iso:country":"US",
    "sg:address":"1657 Eastside Rd",
    "sg:city":"El Cajon",
    "sg:classifiers":[
        {
            "category":"Wholesale",
            "subcategory":"Stationery",
            "type":"Manufacturing & Wholesale Goods"
        }
    ],
    "sg:phone":"+1 619 562 9343",
    "sg:postcode":"92020",
    "sg:province":"CA",
    "sg:tags":[
        "paper"
    ],
    "wof:name":"Universal Packaging",
    "wof:placetype":"venue"
},
  "geometry": {"coordinates":[-116.98337100000001,32.814611],"type":"Point"}
}