{
  "type": "Feature",
  "properties": {
    "iso:country":"US",
    "sg:address":"5529 Sapunor Way",
    "sg:city":"Carmichael",
    "sg:classifiers":[
        {
            "category":"Professional",
            "subcategory":"Lawyer & Legal Services",
            "type":"Services"
        }
    ],
    "sg:phone":"+1 916 628 1293",
    "sg:postcode":"95608",
    "sg:province":"CA",
    "sg:tags":[
        "attorney"
    ],
    "wof:name":"Monson Attorney Support Svc",
    "wof:placetype":"venue"
},
  "geometry": {"coordinates":[-121.323814,38.667283],"type":"Point"}
}