{
  "type": "Feature",
  "properties": {
    "iso:country":"US",
    "sg:address":"5175 E Pacific Coast Hwy Ste 201",
    "sg:city":"Long Beach",
    "sg:classifiers":[
        {
            "category":"Health Services",
            "subcategory":"Dentist",
            "type":"Services"
        }
    ],
    "sg:phone":"+1 562 597 1543",
    "sg:postcode":"90804",
    "sg:province":"CA",
    "sg:website":"www.williamlbarnarddds.com",
    "wof:name":"William L Barnard, DDS",
    "wof:placetype":"venue"
},
  "geometry": {"coordinates":[-118.132793,33.783487],"type":"Point"}
}