{
  "type": "Feature",
  "properties": {
    "iso:country":"US",
    "sg:address":"6996 El Camino Real",
    "sg:city":"Carlsbad",
    "sg:classifiers":[
        {
            "category":"Restaurant",
            "type":"Food & Drink"
        }
    ],
    "sg:menulink":"http://www.allmenus.com/ca/oceanside-escondido/26702-crazy-burrito/menu/",
    "sg:phone":"+1 760 438 3373",
    "sg:postcode":"92009",
    "sg:province":"CA",
    "sg:tags":[
        "mexican"
    ],
    "wof:name":"Crazy Burrito",
    "wof:placetype":"venue"
},
  "geometry": {"coordinates":[-117.266414,33.102448],"type":"Point"}
}