{
  "type": "Feature",
  "properties": {
    "addr:full":"72363 Baker Blvd Baker CA 92309",
    "addr:housenumber":"72363",
    "addr:postcode":"92309",
    "addr:street":"Baker Blvd",
    "iso:country":"US",
    "sg:address":"72363 Baker Blvd",
    "sg:city":"Baker",
    "sg:classifiers":[
        {
            "category":"Autos & Motor Vehicles",
            "subcategory":"Fuel & Gas Station",
            "type":"Retail Goods"
        }
    ],
    "sg:phone":"+1 760 733 4505",
    "sg:postcode":"92309",
    "sg:province":"CA",
    "sg:tags":[
        "oil"
    ],
    "wof:name":"Grewal Business Ctr",
    "wof:placetype":"venue"
},
  "geometry": {"coordinates":[-116.071939,35.267288],"type":"Point"}
}