{
  "type": "Feature",
  "properties": {
    "iso:country":"US",
    "sg:address":"245 Aristotle St",
    "sg:city":"Simi Valley",
    "sg:classifiers":[
        {
            "category":"Manufacturing",
            "subcategory":"Printing",
            "type":"Manufacturing & Wholesale Goods"
        }
    ],
    "sg:phone":"+1 805 582 0772",
    "sg:postcode":"93065",
    "sg:province":"CA",
    "sg:tags":[
        "printer"
    ],
    "wof:name":"KLM Enterprises",
    "wof:placetype":"venue"
},
  "geometry": {"coordinates":[-118.79295500000001,34.276066],"type":"Point"}
}