{
  "type": "Feature",
  "properties": {
    "iso:country":"US",
    "sg:address":"45211 Co Rd 32B",
    "sg:city":"Davis",
    "sg:classifiers":[
        {
            "category":"Organizations",
            "subcategory":"Community Association",
            "type":"Services"
        }
    ],
    "sg:phone":"+1 530 756 7248",
    "sg:postcode":"95616",
    "sg:province":"CA",
    "sg:tags":[
        "environmental",
        "org"
    ],
    "sg:website":"www.yolobasin.org",
    "wof:name":"Yolo Basin Foundation",
    "wof:placetype":"venue"
},
  "geometry": {"coordinates":[-121.674667,38.557038],"type":"Point"}
}