{
  "type": "Feature",
  "properties": {
    "addr:full":"3334 Harrison St Oakland CA 94611",
    "addr:housenumber":"3334",
    "addr:postcode":"94611",
    "addr:street":"Harrison St",
    "iso:country":"US",
    "sg:address":"3334 Harrison St",
    "sg:city":"Oakland",
    "sg:classifiers":[
        {
            "category":"Retail",
            "subcategory":"Laundry & Dry Cleaning",
            "type":"Services"
        },
        {
            "category":"Building & Trades",
            "subcategory":"Cleaning & Sanitation",
            "type":"Services"
        }
    ],
    "sg:phone":"+1 510 452 0101",
    "sg:postcode":"94611",
    "sg:province":"CA",
    "sg:tags":[
        "cleaner",
        "house"
    ],
    "wof:name":"Simone's Cleaning",
    "wof:placetype":"venue"
},
  "geometry": {"coordinates":[-122.255421,37.818617],"type":"Point"}
}