{
  "type": "Feature",
  "properties": {
    "iso:country":"US",
    "sg:address":"1553 W Manchester Ave",
    "sg:city":"Los Angeles",
    "sg:classifiers":[
        {
            "category":"Personal",
            "subcategory":"Nail Salon",
            "type":"Services"
        }
    ],
    "sg:phone":"+1 323 971 8879",
    "sg:postcode":"90047",
    "sg:province":"CA",
    "wof:name":"Lilie Nails",
    "wof:placetype":"venue"
},
  "geometry": {"coordinates":[-118.303617,33.960129],"type":"Point"}
}