{
  "type": "Feature",
  "properties": {
    "addr:full":"14845 Jeffrey Road Irvine CA 92618",
    "addr:housenumber":"14845",
    "addr:postcode":"92618",
    "addr:street":"Jeffrey Road",
    "iso:country":"US",
    "sg:address":"14845 Jeffrey Road",
    "sg:city":"Irvine",
    "sg:classifiers":[
        {
            "category":"Shopping",
            "subcategory":"Mobile Phones",
            "type":"Retail Goods"
        }
    ],
    "sg:phone":"+1 949 651 9988",
    "sg:postcode":"92618",
    "sg:province":"CA",
    "wof:name":"K Plus One Wireless",
    "wof:placetype":"venue"
},
  "geometry": {"coordinates":[-117.771432,33.686805],"type":"Point"}
}