{
  "type": "Feature",
  "properties": {
    "addr:full":"206 S. Robertson Blvd. Beverly Hills CA 90211",
    "addr:housenumber":"206",
    "addr:postcode":"90211",
    "addr:street":"S. Robertson Blvd.",
    "iso:country":"US",
    "sg:address":"206 S. Robertson Blvd.",
    "sg:city":"Beverly Hills",
    "sg:classifiers":[
        {
            "category":"Health Services",
            "subcategory":"Chiropractor",
            "type":"Services"
        }
    ],
    "sg:phone":"+1 310 854 1877",
    "sg:postcode":"90211",
    "sg:province":"CA",
    "sg:website":"www.aaronschiropractic.com",
    "wof:name":"Dr. Aaron Shakarian, D.C.",
    "wof:placetype":"venue"
},
  "geometry": {"coordinates":[-118.38328199999999,34.064683],"type":"Point"}
}