{
  "type": "Feature",
  "properties": {
    "addr:full":"75100 Mayfair Dr Palm Desert CA 92211",
    "addr:housenumber":"75100",
    "addr:postcode":"ca 92211",
    "addr:street":"Mayfair Dr",
    "iso:country":"US",
    "sg:address":"75100 Mayfair Dr",
    "sg:city":"Palm Desert",
    "sg:classifiers":[
        {
            "category":"Wholesale",
            "subcategory":"Sporting Goods",
            "type":"Manufacturing & Wholesale Goods"
        }
    ],
    "sg:phone":"+1 760 568 9661",
    "sg:postcode":"92211",
    "sg:province":"CA",
    "sg:tags":[
        "equipment",
        "pool",
        "swimming"
    ],
    "wof:name":"Superior Pool Products 514",
    "wof:placetype":"venue"
},
  "geometry": {"coordinates":[-116.35484700000001,33.743082],"type":"Point"}
}