{
  "type": "Feature",
  "properties": {
    "iso:country":"US",
    "sg:address":"425 Beck Ave",
    "sg:city":"Fairfield",
    "sg:classifiers":[
        {
            "category":"Utilities",
            "subcategory":"Electric",
            "type":"Services"
        }
    ],
    "sg:phone":"+1 707 436 2872",
    "sg:postcode":"94533",
    "sg:province":"CA",
    "sg:website":"http://www.pge.com",
    "wof:name":"Pg&E",
    "wof:placetype":"venue"
},
  "geometry": {"coordinates":[-122.066238,38.245481],"type":"Point"}
}