{
  "type": "Feature",
  "properties": {
    "addr:full":"1046 California St Calimesa CA 92320",
    "addr:housenumber":"1046",
    "addr:postcode":"92320",
    "addr:street":"California St",
    "iso:country":"US",
    "sg:address":"1046 California St",
    "sg:city":"Calimesa",
    "sg:classifiers":[
        {
            "category":"Social Services",
            "subcategory":"Adult Care",
            "type":"Services"
        }
    ],
    "sg:phone":"+1 909 795 5729",
    "sg:postcode":"92320",
    "sg:province":"CA",
    "sg:tags":[
        "nurses-home"
    ],
    "wof:name":"Better Way Adult Care Assistance",
    "wof:placetype":"venue"
},
  "geometry": {"coordinates":[-117.038849,33.999371],"type":"Point"}
}