{
  "type": "Feature",
  "properties": {
    "addr:full":"1342 East Chapman Ave. Orange CA 92860",
    "addr:housenumber":"1342",
    "addr:postcode":"92860",
    "addr:street":"East Chapman Ave.",
    "iso:country":"US",
    "sg:address":"1342 East Chapman Ave.",
    "sg:city":"Orange",
    "sg:classifiers":[
        {
            "category":"Health Services",
            "subcategory":"Clinic",
            "type":"Services"
        },
        {
            "category":"Community Center",
            "type":"Public Place"
        }
    ],
    "sg:phone":"+1 949 257 3337",
    "sg:postcode":"92860",
    "sg:province":"CA",
    "sg:tags":[
        "counseling",
        "medical",
        "mental"
    ],
    "wof:name":"Witts Inn",
    "wof:placetype":"venue"
},
  "geometry": {"coordinates":[-117.83908099999999,33.787522],"type":"Point"}
}