{
  "type": "Feature",
  "properties": {
    "addr:full":"18421 S Main St Gardena CA 90248",
    "addr:housenumber":"18421",
    "addr:postcode":"90248",
    "addr:street":"S Main St",
    "iso:country":"US",
    "sg:address":"18421 S Main St",
    "sg:city":"Gardena",
    "sg:classifiers":[
        {
            "category":"Wholesale",
            "subcategory":"Non-durable Goods",
            "type":"Manufacturing & Wholesale Goods"
        }
    ],
    "sg:phone":"+1 310 808 0072",
    "sg:postcode":"90248",
    "sg:province":"CA",
    "sg:website":"www.udtinfomax.com",
    "wof:name":"UDT Distribution Corp",
    "wof:placetype":"venue"
},
  "geometry": {"coordinates":[-118.275451,33.863934],"type":"Point"}
}