{
  "type": "Feature",
  "properties": {
    "iso:country":"US",
    "sg:address":"2310 University Ave",
    "sg:city":"San Diego",
    "sg:classifiers":[
        {
            "category":"Professional",
            "subcategory":"Business Services",
            "type":"Services"
        },
        {
            "category":"Shopping",
            "subcategory":"Party Supplies",
            "type":"Retail Goods"
        },
        {
            "category":"Retail",
            "subcategory":"Event Space",
            "type":"Services"
        }
    ],
    "sg:phone":"+1 619 291 2944",
    "sg:postcode":"92104",
    "sg:province":"CA",
    "sg:tags":[
        "delivery",
        "venue",
        "courier"
    ],
    "wof:name":"Carl's Rentals",
    "wof:placetype":"venue"
},
  "geometry": {"coordinates":[-117.139999,32.748299],"type":"Point"}
}