{
  "type": "Feature",
  "properties": {
    "iso:country":"US",
    "sg:address":"2820 Kovr Dr",
    "sg:city":"Broderick",
    "sg:classifiers":[
        {
            "category":"Personal",
            "type":"Services"
        }
    ],
    "sg:phone":"+1 916 374 8333",
    "sg:postcode":"95605",
    "sg:province":"CA",
    "sg:tags":[
        "bureau"
    ],
    "wof:name":"Lavalife",
    "wof:placetype":"venue"
},
  "geometry": {"coordinates":[-121.547821,38.593527],"type":"Point"}
}