{
  "type": "Feature",
  "properties": {
    "addr:full":"850 Airport Rd Monterey CA 93940",
    "addr:housenumber":"850",
    "addr:postcode":"93940",
    "addr:street":"Airport Rd",
    "iso:country":"US",
    "sg:address":"850 Airport Rd",
    "sg:city":"Monterey",
    "sg:classifiers":[
        {
            "category":"Wholesale",
            "subcategory":"Hardware",
            "type":"Manufacturing & Wholesale Goods"
        }
    ],
    "sg:phone":"+1 831 375 7411",
    "sg:postcode":"93940",
    "sg:province":"CA",
    "sg:tags":[
        "heater"
    ],
    "wof:name":"KIRK Ask Heating & Sheet Metal",
    "wof:placetype":"venue"
},
  "geometry": {"coordinates":[-121.85319200000001,36.593616],"type":"Point"}
}