{
  "type": "Feature",
  "properties": {
    "addr:full":"42081 Big Bear Blvd Big Bear Lake CA 92315",
    "addr:housenumber":"42081",
    "addr:postcode":"92315",
    "addr:street":"Big Bear Blvd",
    "iso:country":"US",
    "sg:address":"42081 Big Bear Blvd",
    "sg:city":"Big Bear Lake",
    "sg:phone":"+1 909 866 4480",
    "sg:postcode":"92315",
    "sg:province":"CA",
    "sg:tags":[
        "wholesale"
    ],
    "wof:name":"Ralph W Haupt Inc",
    "wof:placetype":"venue"
},
  "geometry": {"coordinates":[-116.884917,34.24384],"type":"Point"}
}