{
  "type": "Feature",
  "properties": {
    "addr:full":"3106 Mission Blvd San Diego CA 92109",
    "addr:housenumber":"3106",
    "addr:postcode":"92109",
    "addr:street":"Mission Blvd",
    "iso:country":"US",
    "sg:address":"3106 Mission Blvd",
    "sg:city":"San Diego",
    "sg:classifiers":[
        {
            "category":"Shopping",
            "type":"Retail Goods"
        }
    ],
    "sg:phone":"+1 858 539 0994",
    "sg:postcode":"92109",
    "sg:province":"CA",
    "sg:tags":[
        "factory",
        "outlet"
    ],
    "wof:name":"Beach Outlet",
    "wof:placetype":"venue"
},
  "geometry": {"coordinates":[-117.25121300000001,32.769922],"type":"Point"}
}