{
  "type": "Feature",
  "properties": {
    "addr:full":"43454 30th St W Lancaster CA 93536",
    "addr:housenumber":"43454",
    "addr:postcode":"93536",
    "addr:street":"30Th St W",
    "iso:country":"US",
    "sg:address":"43454 30th St W",
    "sg:city":"Lancaster",
    "sg:classifiers":[
        {
            "category":"Health Services",
            "subcategory":"Nursing And Care Facility",
            "type":"Services"
        }
    ],
    "sg:phone":"+1 661 949 2177",
    "sg:postcode":"93536",
    "sg:province":"CA",
    "sg:tags":[
        "home",
        "retirement",
        "community"
    ],
    "sg:website":"www.prestigecare.com",
    "wof:name":"Prestige Assisted Living",
    "wof:placetype":"venue"
},
  "geometry": {"coordinates":[-118.183643,34.67232],"type":"Point"}
}