{
  "type": "Feature",
  "properties": {
    "iso:country":"US",
    "sg:address":"16652 Bartlett Ln",
    "sg:city":"Huntington Beach",
    "sg:classifiers":[
        {
            "category":"Professional",
            "subcategory":"Advertising",
            "type":"Services"
        }
    ],
    "sg:phone":"+1 562 988 8811",
    "sg:postcode":"92647",
    "sg:province":"CA",
    "wof:name":"Advertising Exchange",
    "wof:placetype":"venue"
},
  "geometry": {"coordinates":[-118.005478,33.719768],"type":"Point"}
}