{
  "type": "Feature",
  "properties": {
    "addr:full":"1001 W Whittier Blvd Montebello CA 90640",
    "addr:housenumber":"1001",
    "addr:postcode":"90640",
    "addr:street":"W Whittier Blvd",
    "iso:country":"US",
    "sg:address":"1001 W Whittier Blvd",
    "sg:city":"Montebello",
    "sg:classifiers":[
        {
            "category":"Manufacturing",
            "subcategory":"Glass & Minerals",
            "type":"Manufacturing & Wholesale Goods"
        },
        {
            "category":"Retail",
            "subcategory":"Auto Repair",
            "type":"Services"
        }
    ],
    "sg:phone":"+1 323 594 8078",
    "sg:postcode":"90640",
    "sg:province":"CA",
    "sg:tags":[
        "plate",
        "shape",
        "glass-wholesale",
        "window",
        "special",
        "circle",
        "windshield",
        "glass-auto",
        "manufacturer"
    ],
    "wof:name":"Armor Auto Glass",
    "wof:placetype":"venue"
},
  "geometry": {"coordinates":[-118.110809,34.010632],"type":"Point"}
}