{
  "type": "Feature",
  "properties": {
    "addr:full":"1423 S Grand Ave Los Angeles CA 90015",
    "addr:housenumber":"1423",
    "addr:postcode":"90015",
    "addr:street":"S Grand Ave",
    "iso:country":"US",
    "sg:address":"1423 S Grand Ave",
    "sg:city":"Los Angeles",
    "sg:classifiers":[
        {
            "category":"Banks & Credit Unions",
            "subcategory":"Bank",
            "type":"Services"
        }
    ],
    "sg:phone":"+1 213 742 0389",
    "sg:postcode":"90015",
    "sg:province":"CA",
    "wof:name":"Los Angeles Healthcare Fed Cu",
    "wof:placetype":"venue"
},
  "geometry": {"coordinates":[-118.265844,34.03665],"type":"Point"}
}