{
  "type": "Feature",
  "properties": {
    "addr:full":"2382 Faraday Ave Ste 140 Carlsbad CA 92008",
    "addr:housenumber":"2382",
    "addr:postcode":"92008",
    "addr:street":"Faraday Ave Ste 140",
    "iso:country":"US",
    "sg:address":"2382 Faraday Ave Ste 140",
    "sg:city":"Carlsbad",
    "sg:classifiers":[
        {
            "category":"Utilities",
            "type":"Services"
        }
    ],
    "sg:phone":"+1 760 607 7500",
    "sg:postcode":"92008",
    "sg:province":"CA",
    "sg:tags":[
        "provider",
        "internet"
    ],
    "wof:name":"Ultimate Internet Solutions",
    "wof:placetype":"venue"
},
  "geometry": {"coordinates":[-117.274002,33.136299],"type":"Point"}
}