{
  "type": "Feature",
  "properties": {
    "addr:full":"1401 Chamberlain Rd Pasadena CA 91103",
    "addr:housenumber":"1401",
    "addr:postcode":"91103",
    "addr:street":"Chamberlain Rd",
    "iso:country":"US",
    "sg:address":"1401 Chamberlain Rd",
    "sg:city":"Pasadena",
    "sg:classifiers":[
        {
            "category":"Professional",
            "subcategory":"Management & Consulting",
            "type":"Services"
        }
    ],
    "sg:phone":"+1 626 440 0043",
    "sg:postcode":"91103",
    "sg:province":"CA",
    "sg:tags":[
        "consultant"
    ],
    "wof:name":"Norm Howe & Assoc",
    "wof:placetype":"venue"
},
  "geometry": {"coordinates":[-118.180699,34.168843],"type":"Point"}
}