{
  "type": "Feature",
  "properties": {
    "addr:full":"1329 Old Park Pl San Jose CA 95132",
    "addr:housenumber":"1329",
    "addr:postcode":"95132",
    "addr:street":"Old Park Pl",
    "iso:country":"US",
    "sg:address":"1329 Old Park Pl",
    "sg:city":"San Jose",
    "sg:classifiers":[
        {
            "category":"Shopping",
            "subcategory":"Hobbies, Toys, & Games",
            "type":"Retail Goods"
        }
    ],
    "sg:phone":"+1 408 258 1710",
    "sg:postcode":"95132",
    "sg:province":"CA",
    "wof:name":"Galaxy Hobbies",
    "wof:placetype":"venue"
},
  "geometry": {"coordinates":[-121.867642,37.391403],"type":"Point"}
}