{
  "type": "Feature",
  "properties": {
    "iso:country":"US",
    "sg:address":"1632 Hammatt Ave",
    "sg:city":"Livingston",
    "sg:classifiers":[
        {
            "category":"Food & Beverages",
            "subcategory":"Specialty",
            "type":"Retail Goods"
        }
    ],
    "sg:phone":"+1 209 631 2376",
    "sg:postcode":"95334",
    "sg:province":"CA",
    "sg:tags":[
        "health",
        "diet"
    ],
    "wof:name":"M A Enterprises",
    "wof:placetype":"venue"
},
  "geometry": {"coordinates":[-120.714378,37.375685],"type":"Point"}
}