{
  "type": "Feature",
  "properties": {
    "addr:full":"1662 Shattuck Ave Berkeley CA 94709",
    "addr:housenumber":"1662",
    "addr:postcode":"94709",
    "addr:street":"Shattuck Ave",
    "iso:country":"US",
    "sg:address":"1662 Shattuck Ave",
    "sg:city":"Berkeley",
    "sg:classifiers":[
        {
            "category":"Personal",
            "subcategory":"Beauty Salon",
            "type":"Services"
        }
    ],
    "sg:phone":"+1 510 540 8540",
    "sg:postcode":"94709",
    "sg:province":"CA",
    "sg:tags":[
        "hair",
        "stylist"
    ],
    "wof:name":"Viveur Hair Salon",
    "wof:placetype":"venue"
},
  "geometry": {"coordinates":[-122.26922399999999,37.87714],"type":"Point"}
}