{
  "type": "Feature",
  "properties": {
    "addr:full":"441 E 10th St Pittsburg CA 94565",
    "addr:housenumber":"441",
    "addr:postcode":"94565",
    "addr:street":"E 10Th St",
    "iso:country":"US",
    "sg:address":"441 E 10th St",
    "sg:city":"Pittsburg",
    "sg:classifiers":[
        {
            "category":"Building & Trades",
            "subcategory":"Construction",
            "type":"Services"
        }
    ],
    "sg:phone":"+1 925 432 9540",
    "sg:postcode":"94565",
    "sg:province":"CA",
    "sg:tags":[
        "painter"
    ],
    "wof:name":"Wilson & Wolfe Inc Painting",
    "wof:placetype":"venue"
},
  "geometry": {"coordinates":[-121.878973,38.026524],"type":"Point"}
}