{
  "type": "Feature",
  "properties": {
    "addr:full":"310 S Prospect Ave Redondo Beach CA 90277",
    "addr:housenumber":"310",
    "addr:postcode":"90277",
    "addr:street":"S Prospect Ave",
    "iso:country":"US",
    "sg:address":"310 S Prospect Ave",
    "sg:city":"Redondo Beach",
    "sg:classifiers":[
        {
            "category":"Professional",
            "subcategory":"Management & Consulting",
            "type":"Services"
        }
    ],
    "sg:phone":"+1 310 316 3773",
    "sg:postcode":"90277",
    "sg:province":"CA",
    "sg:tags":[
        "consultant",
        "telecommunication"
    ],
    "wof:name":"TDSC",
    "wof:placetype":"venue"
},
  "geometry": {"coordinates":[-118.376344,33.837084],"type":"Point"}
}