{
  "type": "Feature",
  "properties": {
    "addr:full":"9600 Sommer Pl Oakdale CA 95361",
    "addr:housenumber":"9600",
    "addr:postcode":"95361",
    "addr:street":"Sommer Pl",
    "iso:country":"US",
    "sg:address":"9600 Sommer Pl",
    "sg:city":"Oakdale",
    "sg:classifiers":[
        {
            "category":"Building & Trades",
            "subcategory":"Construction",
            "type":"Services"
        }
    ],
    "sg:phone":"+1 209 605 4124",
    "sg:postcode":"95361",
    "sg:province":"CA",
    "sg:tags":[
        "general",
        "contractor"
    ],
    "wof:name":"Shaw Construction",
    "wof:placetype":"venue"
},
  "geometry": {"coordinates":[-120.797257,37.778186],"type":"Point"}
}