{
  "type": "Feature",
  "properties": {
    "addr:full":"9579 Ross Station Rd Sebastopol CA 95472",
    "addr:housenumber":"9579",
    "addr:postcode":"95472",
    "addr:street":"Ross Station Rd",
    "iso:country":"US",
    "sg:address":"9579 Ross Station Rd",
    "sg:city":"Sebastopol",
    "sg:classifiers":[
        {
            "category":"Building & Trades",
            "subcategory":"Construction",
            "type":"Services"
        }
    ],
    "sg:phone":"+1 707 887 2731",
    "sg:postcode":"95472",
    "sg:province":"CA",
    "sg:tags":[
        "home",
        "builder",
        "operative",
        "family"
    ],
    "wof:name":"Raycon Enterprises",
    "wof:placetype":"venue"
},
  "geometry": {"coordinates":[-122.892003,38.456059],"type":"Point"}
}