{
  "type": "Feature",
  "properties": {
    "iso:country":"US",
    "sg:address":"1149 N Marshall Ave",
    "sg:city":"El Cajon",
    "sg:classifiers":[
        {
            "category":"Wholesale",
            "subcategory":"Hardware",
            "type":"Manufacturing & Wholesale Goods"
        }
    ],
    "sg:phone":"+1 619 596 5600",
    "sg:postcode":"92020",
    "sg:province":"CA",
    "sg:tags":[
        "plumbing",
        "fixture",
        "supply"
    ],
    "sg:website":"www.ferguson.com",
    "wof:name":"Ferguson Enterprises Inc",
    "wof:placetype":"venue"
},
  "geometry": {"coordinates":[-116.975609,32.809813],"type":"Point"}
}