{
  "type": "Feature",
  "properties": {
    "iso:country":"US",
    "sg:address":"500 S Los Angeles St",
    "sg:city":"Los Angeles",
    "sg:classifiers":[
        {
            "category":"Wholesale",
            "subcategory":"Apparel",
            "type":"Manufacturing & Wholesale Goods"
        }
    ],
    "sg:phone":"+1 213 489 2824",
    "sg:postcode":"90013",
    "sg:province":"CA",
    "sg:tags":[
        "clothing"
    ],
    "wof:name":"Unik Sportwear Unlimited",
    "wof:placetype":"venue"
},
  "geometry": {"coordinates":[-118.248997,34.044595],"type":"Point"}
}