{
  "type": "Feature",
  "properties": {
    "iso:country":"US",
    "sg:address":"615 Tyrella Ave",
    "sg:city":"Mountain View",
    "sg:classifiers":[
        {
            "category":"Retail",
            "subcategory":"Animal Services",
            "type":"Services"
        }
    ],
    "sg:phone":"+1 650 996 5999",
    "sg:postcode":"94043",
    "sg:province":"CA",
    "sg:tags":[
        "pet"
    ],
    "wof:name":"Petz Palz & Pawz",
    "wof:placetype":"venue"
},
  "geometry": {"coordinates":[-122.061891,37.40621],"type":"Point"}
}