{
  "type": "Feature",
  "properties": {
    "addr:full":"1011 2nd St Santa Rosa CA 95404",
    "addr:housenumber":"1011",
    "addr:postcode":"ca 95404",
    "addr:street":"2Nd St",
    "iso:country":"US",
    "sg:address":"1011 2nd St",
    "sg:city":"Santa Rosa",
    "sg:classifiers":[
        {
            "category":"Wholesale",
            "subcategory":"Electrical",
            "type":"Manufacturing & Wholesale Goods"
        },
        {
            "category":"Building & Trades",
            "subcategory":"Landscaping Services",
            "type":"Services"
        }
    ],
    "sg:phone":"+1 707 570 2041",
    "sg:postcode":"95404",
    "sg:province":"CA",
    "sg:tags":[
        "equipment",
        "designer",
        "landscape"
    ],
    "wof:name":"D Best Light Specification",
    "wof:placetype":"venue"
},
  "geometry": {"coordinates":[-122.70451199999999,38.442921],"type":"Point"}
}