{
  "type": "Feature",
  "properties": {
    "iso:country":"US",
    "sg:address":"1011 2nd St",
    "sg:city":"Santa Rosa",
    "sg:classifiers":[
        {
            "category":"Wholesale",
            "subcategory":"Electrical",
            "type":"Manufacturing & Wholesale Goods"
        },
        {
            "category":"Building & Trades",
            "subcategory":"Landscaping Services",
            "type":"Services"
        }
    ],
    "sg:phone":"+1 707 570 2041",
    "sg:postcode":"95404",
    "sg:province":"CA",
    "sg:tags":[
        "equipment",
        "designer",
        "landscape"
    ],
    "wof:name":"D Best Light Specification",
    "wof:placetype":"venue"
},
  "geometry": {"coordinates":[-122.704512,38.442921],"type":"Point"}
}