{
  "type": "Feature",
  "properties": {
    "addr:full":"20271 Adrian Cir Huntington Beach CA 92646",
    "addr:housenumber":"20271",
    "addr:postcode":"92646",
    "addr:street":"Adrian Cir",
    "iso:country":"US",
    "sg:address":"20271 Adrian Cir",
    "sg:city":"Huntington Beach",
    "sg:phone":"+1 714 968 5446",
    "sg:postcode":"92646",
    "sg:province":"CA",
    "sg:tags":[
        "farm",
        "nonprofit",
        "management",
        "trust"
    ],
    "wof:name":"Copernicus Ctr Innovatn In Ed",
    "wof:placetype":"venue"
},
  "geometry": {"coordinates":[-117.96545500000001,33.667565],"type":"Point"}
}