{
  "type": "Feature",
  "properties": {
    "iso:country":"US",
    "sg:address":"3723 Haven Ave",
    "sg:city":"Menlo Park",
    "sg:classifiers":[
        {
            "category":"Wholesale",
            "subcategory":"Durable Goods & Equipment",
            "type":"Manufacturing & Wholesale Goods"
        }
    ],
    "sg:phone":"+1 650 980 3322",
    "sg:postcode":"94025",
    "sg:province":"CA",
    "sg:tags":[
        "instrument",
        "scientific",
        "apparatus"
    ],
    "wof:name":"Acaderm",
    "wof:placetype":"venue"
},
  "geometry": {"coordinates":[-122.179773,37.486733],"type":"Point"}
}