{
  "type": "Feature",
  "properties": {
    "addr:full":"15775 Excelsior St Sylmar CA 91342",
    "addr:housenumber":"15775",
    "addr:postcode":"91342",
    "addr:street":"Excelsior St",
    "iso:country":"US",
    "sg:address":"15775 Excelsior St",
    "sg:city":"Sylmar",
    "sg:classifiers":[
        {
            "category":"Professional",
            "type":"Services"
        }
    ],
    "sg:phone":"+1 818 362 9500",
    "sg:postcode":"91342",
    "sg:province":"CA",
    "wof:name":"Steven M Collins",
    "wof:placetype":"venue"
},
  "geometry": {"coordinates":[-118.475803,34.320467],"type":"Point"}
}