{
  "type": "Feature",
  "properties": {
    "addr:full":"112 Madrone Ave Larkspur CA 94939",
    "addr:housenumber":"112",
    "addr:postcode":"94939",
    "addr:street":"Madrone Ave",
    "iso:country":"US",
    "sg:address":"112 Madrone Ave",
    "sg:city":"Larkspur",
    "sg:classifiers":[
        {
            "category":"Personal",
            "type":"Services"
        }
    ],
    "sg:phone":"+1 415 927 2708",
    "sg:postcode":"94939",
    "sg:province":"CA",
    "sg:tags":[
        "mfg",
        "plastic"
    ],
    "wof:name":"Bayer Corporation",
    "wof:placetype":"venue"
},
  "geometry": {"coordinates":[-122.541113,37.931374],"type":"Point"}
}