{
  "type": "Feature",
  "properties": {
    "iso:country":"US",
    "sg:address":"2275 Broadway St",
    "sg:city":"San Francisco",
    "sg:classifiers":[
        {
            "category":"Shopping",
            "subcategory":"Clothing, Apparel, & Fashions",
            "type":"Retail Goods"
        }
    ],
    "sg:phone":"+1 415 922 4747",
    "sg:postcode":"94115",
    "sg:province":"CA",
    "wof:name":"Susan Parrish Designs",
    "wof:placetype":"venue"
},
  "geometry": {"coordinates":[-122.433926,37.794349],"type":"Point"}
}