{
  "type": "Feature",
  "properties": {
    "addr:full":"2740 Mountain View Rd El Monte CA 91732",
    "addr:housenumber":"2740",
    "addr:postcode":"91732",
    "addr:street":"Mountain View Rd",
    "iso:country":"US",
    "sg:address":"2740 Mountain View Rd",
    "sg:city":"El Monte",
    "sg:classifiers":[
        {
            "category":"Organizations",
            "subcategory":"Professional Association",
            "type":"Services"
        }
    ],
    "sg:phone":"+1 626 442 5470",
    "sg:postcode":"91732",
    "sg:province":"CA",
    "wof:name":"Boys & Girls Club-San Gabriel",
    "wof:placetype":"venue"
},
  "geometry": {"coordinates":[-118.024084,34.060733],"type":"Point"}
}