{
  "type": "Feature",
  "properties": {
    "addr:full":"6135 Marguerite Dr Newark CA 94560",
    "addr:housenumber":"6135",
    "addr:postcode":"94560",
    "addr:street":"Marguerite Dr",
    "iso:country":"US",
    "sg:address":"6135 Marguerite Dr",
    "sg:city":"Newark",
    "sg:classifiers":[
        {
            "category":"Professional",
            "subcategory":"Advertising",
            "type":"Services"
        }
    ],
    "sg:phone":"+1 510 713 9133",
    "sg:postcode":"94560",
    "sg:province":"CA",
    "sg:tags":[
        "counselor"
    ],
    "wof:name":"L Neff Graphics & Advertising",
    "wof:placetype":"venue"
},
  "geometry": {"coordinates":[-122.01556100000001,37.525527],"type":"Point"}
}