{
  "type": "Feature",
  "properties": {
    "iso:country":"US",
    "sg:address":"1717 Mill St",
    "sg:city":"Selma",
    "sg:classifiers":[
        {
            "category":"Health Services",
            "subcategory":"Doctor",
            "type":"Services"
        }
    ],
    "sg:phone":"+1 559 896 2752",
    "sg:postcode":"93662",
    "sg:province":"CA",
    "sg:tags":[
        "dentist"
    ],
    "wof:name":"Eugene Ying Inc",
    "wof:placetype":"venue"
},
  "geometry": {"coordinates":[-119.60927100000001,36.567077],"type":"Point"}
}