{
  "type": "Feature",
  "properties": {
    "iso:country":"US",
    "sg:address":"2201 E Valley Pkwy",
    "sg:city":"Escondido",
    "sg:classifiers":[
        {
            "category":"Organizations",
            "subcategory":"Religious Organization",
            "type":"Services"
        }
    ],
    "sg:phone":"+1 760 738 8677",
    "sg:postcode":"92027",
    "sg:province":"CA",
    "sg:tags":[
        "church"
    ],
    "wof:name":"Church Of Jesus Christ-America",
    "wof:placetype":"venue"
},
  "geometry": {"coordinates":[-117.04767200000001,33.139301],"type":"Point"}
}