{
  "type": "Feature",
  "properties": {
    "iso:country":"US",
    "sg:address":"200 Hartnell Ave",
    "sg:city":"Redding",
    "sg:classifiers":[
        {
            "category":"Personal",
            "subcategory":"Shoe Repair & Shine",
            "type":"Services"
        }
    ],
    "sg:phone":"+1 530 222 1342",
    "sg:postcode":"96002",
    "sg:province":"CA",
    "sg:tags":[
        "repairing",
        "boot"
    ],
    "sg:website":"www.shastaboots.com",
    "wof:name":"Shasta Shoe Repair",
    "wof:placetype":"venue"
},
  "geometry": {"coordinates":[-122.36780400000001,40.564817],"type":"Point"}
}