{
  "type": "Feature",
  "properties": {
    "addr:full":"1142 W 79th St Los Angeles CA 90044",
    "addr:housenumber":"1142",
    "addr:postcode":"90044",
    "addr:street":"W 79Th St",
    "iso:country":"US",
    "sg:address":"1142 W 79th St",
    "sg:city":"Los Angeles",
    "sg:classifiers":[
        {
            "category":"Professional",
            "type":"Services"
        }
    ],
    "sg:phone":"+1 323 967 0337",
    "sg:postcode":"90044",
    "sg:province":"CA",
    "sg:tags":[
        "establishment"
    ],
    "wof:name":"M Pact",
    "wof:placetype":"venue"
},
  "geometry": {"coordinates":[-118.294369,33.967208],"type":"Point"}
}