{
  "type": "Feature",
  "properties": {
    "iso:country":"US",
    "sg:address":"17750 Cumana Ter",
    "sg:city":"San Diego",
    "sg:classifiers":[
        {
            "category":"Banks & Credit Unions",
            "subcategory":"Financial Services",
            "type":"Services"
        }
    ],
    "sg:phone":"+1 858 451 3232",
    "sg:postcode":"92128",
    "sg:province":"CA",
    "sg:tags":[
        "trust",
        "management"
    ],
    "wof:name":"Amy B Caldwell Trust",
    "wof:placetype":"venue"
},
  "geometry": {"coordinates":[-117.049679,33.036604],"type":"Point"}
}