{
  "type": "Feature",
  "properties": {
    "addr:full":"707 State Rte 66 Glendora CA 91740",
    "addr:housenumber":"707",
    "addr:postcode":"91740",
    "addr:street":"State Rte 66",
    "iso:country":"US",
    "sg:address":"707 State Rte 66",
    "sg:city":"Glendora",
    "sg:classifiers":[
        {
            "category":"Home & Garden",
            "subcategory":"Furniture",
            "type":"Retail Goods"
        }
    ],
    "sg:phone":"+1 626 852 8898",
    "sg:postcode":"91740",
    "sg:province":"CA",
    "wof:name":"Quality Furniture",
    "wof:placetype":"venue"
},
  "geometry": {"coordinates":[-117.852633,34.128768],"type":"Point"}
}