{
  "type": "Feature",
  "properties": {
    "iso:country":"US",
    "sg:address":"635 Davis St",
    "sg:city":"San Francisco",
    "sg:classifiers":[
        {
            "category":"Retail",
            "subcategory":"Laundry & Dry Cleaning",
            "type":"Services"
        }
    ],
    "sg:phone":"+1 415 397 4654",
    "sg:postcode":"94111",
    "sg:province":"CA",
    "wof:name":"Davis Cleaners",
    "wof:placetype":"venue"
},
  "geometry": {"coordinates":[-122.398561,37.798353],"type":"Point"}
}