{
  "type": "Feature",
  "properties": {
    "iso:country":"US",
    "sg:address":"2255 29th St",
    "sg:city":"Santa Monica",
    "sg:classifiers":[
        {
            "category":"Farming",
            "subcategory":"Fish & Marine Products",
            "type":"Manufacturing & Wholesale Goods"
        }
    ],
    "sg:phone":"+1 310 578 7181",
    "sg:postcode":"90405",
    "sg:province":"CA",
    "sg:tags":[
        "management"
    ],
    "wof:name":"Yutopian Enterprises Inc",
    "wof:placetype":"venue"
},
  "geometry": {"coordinates":[-118.45752,34.022771],"type":"Point"}
}