{
  "type": "Feature",
  "properties": {
    "addr:full":"4500 Tweedy Blvd South Gate CA 90280",
    "addr:housenumber":"4500",
    "addr:postcode":"90280",
    "addr:street":"Tweedy Blvd;Gate",
    "iso:country":"US",
    "sg:address":"4500 Tweedy Blvd",
    "sg:city":"South Gate",
    "sg:classifiers":[
        {
            "category":"Health Services",
            "subcategory":"Doctor",
            "type":"Services"
        }
    ],
    "sg:phone":"+1 323 567 9661",
    "sg:postcode":"90280",
    "sg:province":"CA",
    "wof:name":"Carreon Jorge F MD",
    "wof:placetype":"venue"
},
  "geometry": {"coordinates":[-118.193001,33.942699],"type":"Point"}
}