{
  "type": "Feature",
  "properties": {
    "iso:country":"US",
    "sg:address":"210 W 2nd St",
    "sg:city":"Claremont",
    "sg:classifiers":[
        {
            "category":"Wholesale",
            "subcategory":"Groceries",
            "type":"Manufacturing & Wholesale Goods"
        }
    ],
    "sg:phone":"+1 909 626 6646",
    "sg:postcode":"91711",
    "sg:province":"CA",
    "sg:tags":[
        "cocoa",
        "chocolate"
    ],
    "wof:name":"A Kline Chocolatier",
    "wof:placetype":"venue"
},
  "geometry": {"coordinates":[-117.717002,34.095565],"type":"Point"}
}