{
  "type": "Feature",
  "properties": {
    "addr:full":"524 W Pacheco Blvd Los Banos CA 93635",
    "addr:housenumber":"524",
    "addr:postcode":"93635",
    "addr:street":"W Pacheco Blvd",
    "iso:country":"US",
    "sg:address":"524 W Pacheco Blvd",
    "sg:city":"Los Banos",
    "sg:classifiers":[
        {
            "category":"Real Estate",
            "subcategory":"Real Estate Agent",
            "type":"Services"
        }
    ],
    "sg:phone":"+1 209 826 1600",
    "sg:postcode":"93635",
    "sg:province":"CA",
    "wof:name":"Blossom Valley Realty",
    "wof:placetype":"venue"
},
  "geometry": {"coordinates":[-120.859594,37.056952],"type":"Point"}
}