{
  "type": "Feature",
  "properties": {
    "addr:full":"5146 Arlington Ave Riverside CA 92504",
    "addr:housenumber":"5146",
    "addr:postcode":"92504",
    "addr:street":"Arlington Ave",
    "iso:country":"US",
    "sg:address":"5146 Arlington Ave",
    "sg:city":"Riverside",
    "sg:classifiers":[
        {
            "category":"Shopping",
            "type":"Retail Goods"
        }
    ],
    "sg:phone":"+1 951 637 1464",
    "sg:postcode":"92504",
    "sg:province":"CA",
    "sg:tags":[
        "telephone",
        "cellular"
    ],
    "wof:name":"Radio Shack",
    "wof:placetype":"venue"
},
  "geometry": {"coordinates":[-117.41435199999999,33.946024],"type":"Point"}
}