{
  "type": "Feature",
  "properties": {
    "addr:full":"2807 McGaw Ave Irvine CA 92614",
    "addr:housenumber":"2807",
    "addr:postcode":"92614",
    "addr:street":"Mcgaw Ave",
    "iso:country":"US",
    "sg:address":"2807 McGaw Ave",
    "sg:city":"Irvine",
    "sg:classifiers":[
        {
            "category":"Manufacturing",
            "subcategory":"Tools & Machinery",
            "type":"Manufacturing & Wholesale Goods"
        }
    ],
    "sg:phone":"+1 949 261 2900",
    "sg:postcode":"92614",
    "sg:province":"CA",
    "sg:tags":[
        "physician",
        "surgeon"
    ],
    "sg:website":"www.procolonline.com",
    "wof:name":"Hancock Jaffe Labs",
    "wof:placetype":"venue"
},
  "geometry": {"coordinates":[-117.83376199999999,33.685117],"type":"Point"}
}