{
  "type": "Feature",
  "properties": {
    "iso:country":"US",
    "sg:address":"16 E Holly St",
    "sg:city":"Pasadena",
    "sg:classifiers":[
        {
            "category":"Home & Garden",
            "subcategory":"Furniture",
            "type":"Retail Goods"
        }
    ],
    "sg:phone":"+1 626 405 1926",
    "sg:postcode":"91103",
    "sg:province":"CA",
    "sg:tags":[
        "equipment",
        "kitchen",
        "cabinet"
    ],
    "wof:name":"Kitchen Works",
    "wof:placetype":"venue"
},
  "geometry": {"coordinates":[-118.149931,34.147574],"type":"Point"}
}