{
  "type": "Feature",
  "properties": {
    "iso:country":"US",
    "sg:address":"15916 Bernardo Center Dr",
    "sg:city":"San Diego",
    "sg:classifiers":[
        {
            "category":"Utilities",
            "subcategory":"Telephone",
            "type":"Services"
        }
    ],
    "sg:phone":"+1 858 467 0599",
    "sg:postcode":"92127",
    "sg:province":"CA",
    "sg:tags":[
        "communications"
    ],
    "wof:name":"Sumida America Technologies",
    "wof:placetype":"venue"
},
  "geometry": {"coordinates":[-117.08928899999999,33.00757],"type":"Point"}
}