{
  "type": "Feature",
  "properties": {
    "iso:country":"US",
    "sg:address":"1058 S White Road",
    "sg:city":"San Jose",
    "sg:classifiers":[
        {
            "category":"Shopping",
            "subcategory":"Tobacco",
            "type":"Retail Goods"
        }
    ],
    "sg:phone":"+1 408 259 0170",
    "sg:postcode":"95127",
    "sg:province":"CA",
    "sg:tags":[
        "shop"
    ],
    "wof:name":"B & C Cigarettes & Groceries",
    "wof:placetype":"venue"
},
  "geometry": {"coordinates":[-121.820858,37.357878],"type":"Point"}
}