{
  "type": "Feature",
  "properties": {
    "iso:country":"US",
    "sg:address":"5704 Dry Creek Rd",
    "sg:city":"Rio Linda",
    "sg:classifiers":[
        {
            "category":"Building & Trades",
            "subcategory":"Construction",
            "type":"Services"
        }
    ],
    "sg:phone":"+1 916 992 1200",
    "sg:postcode":"95673",
    "sg:province":"CA",
    "sg:tags":[
        "repairing",
        "remodeling",
        "contractor"
    ],
    "wof:name":"Cornerstone Renovations Inc",
    "wof:placetype":"venue"
},
  "geometry": {"coordinates":[-121.43826199999999,38.670928],"type":"Point"}
}