{
  "type": "Feature",
  "properties": {
    "addr:full":"3000 W Coast Hwy Newport Beach CA 92663",
    "addr:housenumber":"3000",
    "addr:postcode":"92663",
    "addr:street":"W Coast Hwy",
    "iso:country":"US",
    "sg:address":"3000 W Coast Hwy",
    "sg:city":"Newport Beach",
    "sg:classifiers":[
        {
            "category":"Retail",
            "subcategory":"Auto Rental",
            "type":"Services"
        }
    ],
    "sg:phone":"+1 949 722 7306",
    "sg:postcode":"92663",
    "sg:province":"CA",
    "sg:tags":[
        "car"
    ],
    "sg:website":"www.hertz.com",
    "wof:name":"Hertz Rent-A-Car",
    "wof:placetype":"venue"
},
  "geometry": {"coordinates":[-117.92565399999999,33.621171],"type":"Point"}
}