{
  "type": "Feature",
  "properties": {
    "iso:country":"US",
    "sg:address":"11273 Laurel Canyon Blvd",
    "sg:city":"San Fernando",
    "sg:classifiers":[
        {
            "category":"Health Services",
            "subcategory":"Doctor",
            "type":"Services"
        }
    ],
    "sg:phone":"+1 818 365 3978",
    "sg:postcode":"91340",
    "sg:province":"CA",
    "sg:tags":[
        "physician",
        "surgeon"
    ],
    "wof:name":"Robert Flores MD Inc",
    "wof:placetype":"venue"
},
  "geometry": {"coordinates":[-118.449907,34.275361],"type":"Point"}
}