{
  "type": "Feature",
  "properties": {
    "addr:full":"1324 Jason Dr Lompoc CA 93436",
    "addr:housenumber":"1324",
    "addr:postcode":"93436",
    "addr:street":"Jason Dr",
    "iso:country":"US",
    "sg:address":"1324 Jason Dr",
    "sg:city":"Lompoc",
    "sg:classifiers":[
        {
            "category":"Professional",
            "subcategory":"Computer Services",
            "type":"Services"
        }
    ],
    "sg:phone":"+1 805 736 8999",
    "sg:postcode":"93436",
    "sg:province":"CA",
    "sg:tags":[
        "consultant",
        "designer",
        "system"
    ],
    "wof:name":"Katrinas Kollection",
    "wof:placetype":"venue"
},
  "geometry": {"coordinates":[-120.473131,34.659576],"type":"Point"}
}