{
  "type": "Feature",
  "properties": {
    "addr:full":"4847 Humber Pl Newark CA 94560",
    "addr:housenumber":"4847",
    "addr:postcode":"94560",
    "addr:street":"Humber Pl",
    "iso:country":"US",
    "sg:address":"4847 Humber Pl",
    "sg:city":"Newark",
    "sg:classifiers":[
        {
            "category":"Wholesale",
            "subcategory":"Books, Periodicals, & Newspapers",
            "type":"Manufacturing & Wholesale Goods"
        }
    ],
    "sg:phone":"+1 510 366 8749",
    "sg:postcode":"94560",
    "sg:province":"CA",
    "sg:tags":[
        "publisher"
    ],
    "wof:name":"Texbuddy.Com",
    "wof:placetype":"venue"
},
  "geometry": {"coordinates":[-122.035904,37.559398],"type":"Point"}
}