{
  "type": "Feature",
  "properties": {
    "addr:full":"1055 E Anaheim St Long Beach CA 90813",
    "addr:housenumber":"1055",
    "addr:postcode":"90813",
    "addr:street":"E Anaheim St",
    "iso:country":"US",
    "sg:address":"1055 E Anaheim St",
    "sg:city":"Long Beach",
    "sg:classifiers":[
        {
            "category":"Cinema",
            "subcategory":"Movie Rental",
            "type":"Entertainment"
        }
    ],
    "sg:phone":"+1 562 591 7164",
    "sg:postcode":"90813",
    "sg:province":"CA",
    "sg:tags":[
        "video",
        "game",
        "disc",
        "leasing",
        "tape"
    ],
    "wof:name":"Hawaii Video",
    "wof:placetype":"venue"
},
  "geometry": {"coordinates":[-118.18000000000001,33.7827],"type":"Point"}
}