{
  "type": "Feature",
  "properties": {
    "addr:full":"2155 Chanticleer Ave Santa Cruz CA 95062",
    "addr:housenumber":"2155",
    "addr:postcode":"95062",
    "addr:street":"Chanticleer Ave",
    "iso:country":"US",
    "sg:address":"2155 Chanticleer Ave",
    "sg:city":"Santa Cruz",
    "sg:classifiers":[
        {
            "category":"Organizations",
            "subcategory":"Religious Organization",
            "type":"Services"
        }
    ],
    "sg:phone":"+1 831 476 1724",
    "sg:postcode":"95062",
    "sg:province":"CA",
    "sg:tags":[
        "service/non-profit",
        "community",
        "church"
    ],
    "wof:name":"Liberty Baptist Church",
    "wof:placetype":"venue"
},
  "geometry": {"coordinates":[-121.978996,36.9814],"type":"Point"}
}