{
  "type": "Feature",
  "properties": {
    "iso:country":"US",
    "sg:address":"1620 W Base Line St",
    "sg:city":"San Bernardino",
    "sg:classifiers":[
        {
            "category":"Food & Beverages",
            "subcategory":"Groceries & Convenience Stores",
            "type":"Retail Goods"
        }
    ],
    "sg:phone":"+1 909 885 6130",
    "sg:postcode":"92411",
    "sg:province":"CA",
    "sg:tags":[
        "market"
    ],
    "wof:name":"Jimmy's Food Store",
    "wof:placetype":"venue"
},
  "geometry": {"coordinates":[-117.323403,34.121427],"type":"Point"}
}