{
  "type": "Feature",
  "properties": {
    "iso:country":"US",
    "sg:address":"150 E Colorado Blvd Ste 207",
    "sg:city":"Pasadena",
    "sg:classifiers":[
        {
            "category":"Professional",
            "subcategory":"Lawyer & Legal Services",
            "type":"Services"
        }
    ],
    "sg:phone":"+1 626 796 5008",
    "sg:postcode":"91105",
    "sg:province":"CA",
    "wof:name":"McMillan R Wayne Law Offices",
    "wof:placetype":"venue"
},
  "geometry": {"coordinates":[-118.14671199999999,34.145701],"type":"Point"}
}