{
  "type": "Feature",
  "properties": {
    "iso:country":"US",
    "sg:address":"4205 Walnut Grove Ave",
    "sg:city":"Rosemead",
    "sg:classifiers":[
        {
            "category":"Freight",
            "type":"Transportation"
        }
    ],
    "sg:phone":"+1 626 576 7213",
    "sg:postcode":"91770",
    "sg:province":"CA",
    "wof:name":"Hycob Maritime Inc",
    "wof:placetype":"venue"
},
  "geometry": {"coordinates":[-118.08215800000001,34.083738],"type":"Point"}
}