{
  "type": "Feature",
  "properties": {
    "iso:country":"US",
    "sg:address":"300 E. Colorado Blvd.",
    "sg:city":"Pasadena",
    "sg:classifiers":[
        {
            "category":"Bakery",
            "type":"Food & Drink"
        }
    ],
    "sg:postcode":"91101",
    "sg:province":"CA",
    "wof:name":"Euro Pane Bakery",
    "wof:placetype":"venue"
},
  "geometry": {"coordinates":[-118.143673,34.145161],"type":"Point"}
}