{
  "type": "Feature",
  "properties": {
    "addr:full":"300 E. Colorado Blvd. Pasadena CA 91101",
    "addr:housenumber":"300",
    "addr:postcode":"91101",
    "addr:street":"E. Colorado Blvd.",
    "iso:country":"US",
    "sg:address":"300 E. Colorado Blvd.",
    "sg:city":"Pasadena",
    "sg:classifiers":[
        {
            "category":"Bakery",
            "type":"Food & Drink"
        }
    ],
    "sg:postcode":"91101",
    "sg:province":"CA",
    "wof:name":"Euro Pane Bakery",
    "wof:placetype":"venue"
},
  "geometry": {"coordinates":[-118.14367300000001,34.145161],"type":"Point"}
}