{
  "type": "Feature",
  "properties": {
    "addr:full":"2299 Freedom Blvd Watsonville CA 95076",
    "addr:housenumber":"2299",
    "addr:postcode":"95076",
    "addr:street":"Freedom Blvd",
    "iso:country":"US",
    "sg:address":"2299 Freedom Blvd",
    "sg:city":"Watsonville",
    "sg:classifiers":[
        {
            "category":"Retail",
            "subcategory":"Portrait Studio",
            "type":"Services"
        }
    ],
    "sg:phone":"+1 831 722 3027",
    "sg:postcode":"95076",
    "sg:province":"CA",
    "sg:tags":[
        "photographer"
    ],
    "wof:name":"Davis' Photography",
    "wof:placetype":"venue"
},
  "geometry": {"coordinates":[-121.78572200000001,36.943303],"type":"Point"}
}