{
  "type": "Feature",
  "properties": {
    "iso:country":"US",
    "sg:address":"8021 Soquel Dr",
    "sg:city":"Aptos",
    "sg:classifiers":[
        {
            "category":"Personal",
            "subcategory":"Beauty Salon",
            "type":"Services"
        }
    ],
    "sg:phone":"+1 831 818 8578",
    "sg:postcode":"95003",
    "sg:province":"CA",
    "wof:name":"Rebecca's Hair Design",
    "wof:placetype":"venue"
},
  "geometry": {"coordinates":[-121.90022,36.976862],"type":"Point"}
}