{
  "type": "Feature",
  "properties": {
    "iso:country":"US",
    "sg:address":"211 Culver Blvd Ste R",
    "sg:city":"Los Angeles",
    "sg:classifiers":[
        {
            "category":"Professional",
            "subcategory":"Computer Services",
            "type":"Services"
        }
    ],
    "sg:phone":"+1 888 298 3848",
    "sg:postcode":"90293",
    "sg:province":"CA",
    "sg:tags":[
        "repair"
    ],
    "sg:website":"www.futuretrendsIT.com",
    "wof:name":"Future Trends Technology Consulting",
    "wof:placetype":"venue"
},
  "geometry": {"coordinates":[-118.44737600000001,33.959732],"type":"Point"}
}