{
  "type": "Feature",
  "properties": {
    "addr:full":"15735 Amar Rd La Puente CA 91744",
    "addr:housenumber":"15735",
    "addr:postcode":"91744",
    "addr:street":"Amar Rd",
    "iso:country":"US",
    "sg:address":"15735 Amar Rd",
    "sg:city":"La Puente",
    "sg:classifiers":[
        {
            "category":"Restaurant",
            "type":"Food & Drink"
        }
    ],
    "sg:phone":"+1 626 968 2717",
    "sg:postcode":"91744",
    "sg:province":"CA",
    "wof:name":"Durango Restaurant",
    "wof:placetype":"venue"
},
  "geometry": {"coordinates":[-117.941542,34.036611],"type":"Point"}
}