{
  "type": "Feature",
  "properties": {
    "addr:full":"5508 Sawtelle Blvd Culver City CA 90230",
    "addr:housenumber":"5508",
    "addr:postcode":"90230",
    "addr:street":"Sawtelle Blvd",
    "iso:country":"US",
    "sg:address":"5508 Sawtelle Blvd",
    "sg:city":"Culver City",
    "sg:classifiers":[
        {
            "category":"Coffee & Tea",
            "type":"Food & Drink"
        }
    ],
    "sg:phone":"+1 310 398 9019",
    "sg:postcode":"90230",
    "sg:province":"CA",
    "wof:name":"King's Cafe",
    "wof:placetype":"venue"
},
  "geometry": {"coordinates":[-118.396716,33.995102],"type":"Point"}
}