{
  "type": "Feature",
  "properties": {
    "iso:country":"US",
    "sg:address":"424 Tufts Ave",
    "sg:city":"Burbank",
    "sg:classifiers":[
        {
            "category":"Professional",
            "type":"Services"
        }
    ],
    "sg:phone":"+1 818 841 2356",
    "sg:postcode":"91504",
    "sg:province":"CA",
    "wof:name":"Albert Berentsen As Dualee of",
    "wof:placetype":"venue"
},
  "geometry": {"coordinates":[-118.319277,34.19425],"type":"Point"}
}