{
  "type": "Feature",
  "properties": {
    "addr:full":"1044 W Grove Ave Orange CA 92865",
    "addr:housenumber":"1044",
    "addr:postcode":"92865",
    "addr:street":"W Grove Ave",
    "iso:country":"US",
    "sg:address":"1044 W Grove Ave",
    "sg:city":"Orange",
    "sg:classifiers":[
        {
            "category":"Manufacturing",
            "subcategory":"Metals",
            "type":"Manufacturing & Wholesale Goods"
        }
    ],
    "sg:phone":"+1 714 974 2432",
    "sg:postcode":"92865",
    "sg:province":"CA",
    "sg:tags":[
        "product",
        "wire",
        "miscellaneous",
        "fabricated"
    ],
    "wof:name":"Cable Solutions Identified",
    "wof:placetype":"venue"
},
  "geometry": {"coordinates":[-117.86314900000001,33.819007],"type":"Point"}
}