{
  "type": "Feature",
  "properties": {
    "addr:full":"2755 Lombard St San Francisco CA 94123",
    "addr:housenumber":"2755",
    "addr:postcode":"94123",
    "addr:street":"Lombard St",
    "iso:country":"US",
    "sg:address":"2755 Lombard St",
    "sg:city":"San Francisco",
    "sg:classifiers":[
        {
            "category":"Travel",
            "subcategory":"Hotels & Motels",
            "type":"Entertainment"
        }
    ],
    "sg:phone":"+1 415 931 8581",
    "sg:postcode":"94123",
    "sg:province":"CA",
    "sg:website":"www.travelodge.com",
    "wof:name":"Travelodge",
    "wof:placetype":"venue"
},
  "geometry": {"coordinates":[-122.446721,37.798572],"type":"Point"}
}