{
  "type": "Feature",
  "properties": {
    "addr:full":"1173 W Bullard Ave Fresno CA 93711",
    "addr:housenumber":"1173",
    "addr:postcode":"93711",
    "addr:street":"W Bullard Ave",
    "iso:country":"US",
    "sg:address":"1173 W Bullard Ave",
    "sg:city":"Fresno",
    "sg:classifiers":[
        {
            "category":"Wholesale",
            "subcategory":"Office Equipment",
            "type":"Manufacturing & Wholesale Goods"
        }
    ],
    "sg:phone":"+1 559 432 1786",
    "sg:postcode":"93711",
    "sg:province":"CA",
    "sg:tags":[
        "credit",
        "system",
        "card"
    ],
    "wof:name":"EXS Processing",
    "wof:placetype":"venue"
},
  "geometry": {"coordinates":[-119.811984,36.822753],"type":"Point"}
}