{
  "type": "Feature",
  "properties": {
    "addr:full":"Byers Hall Suite 214 1700 4th Street San Francisco CA 94158-2330",
    "addr:housenumber":"suite 214 1700",
    "addr:postcode":"94158-2330",
    "addr:street":"4Th Street",
    "iso:country":"US",
    "sg:address":"Byers Hall Suite 214 1700 4th Street",
    "sg:city":"San Francisco",
    "sg:classifiers":[
        {
            "category":"Professional",
            "subcategory":"Research",
            "type":"Services"
        }
    ],
    "sg:phone":"+1 415 514 9790",
    "sg:postcode":"94158-2330",
    "sg:province":"CA",
    "sg:website":"http://qb3.org",
    "wof:name":"California Institute for Quantitative Biosciences",
    "wof:placetype":"venue"
},
  "geometry": {"coordinates":[-122.393355,37.775787],"type":"Point"}
}