{
  "type": "Feature",
  "properties": {
    "addr:full":"6801 Long Beach Blvd Long Beach CA 90805",
    "addr:housenumber":"6801",
    "addr:postcode":"90805",
    "addr:street":"Long Beach Blvd",
    "iso:country":"US",
    "sg:address":"6801 Long Beach Blvd",
    "sg:city":"Long Beach",
    "sg:classifiers":[
        {
            "category":"Sports & Exercise",
            "subcategory":"Swimming Pool",
            "type":"Entertainment"
        }
    ],
    "sg:phone":"+1 310 537 2224",
    "sg:postcode":"90805",
    "sg:province":"CA",
    "sg:website":"www.californiapoolsofhope.org",
    "wof:name":"California Pools of Hope Inc",
    "wof:placetype":"venue"
},
  "geometry": {"coordinates":[-118.204002,33.8787],"type":"Point"}
}