{
  "type": "Feature",
  "properties": {
    "iso:country":"US",
    "sg:address":"133 Kearny St",
    "sg:city":"San Francisco",
    "sg:classifiers":[
        {
            "category":"Professional",
            "subcategory":"Accounting & Tax Preparation",
            "type":"Services"
        }
    ],
    "sg:phone":"+1 415 362 9915",
    "sg:postcode":"94108",
    "sg:province":"CA",
    "sg:tags":[
        "accountant"
    ],
    "wof:name":"Etax Advisors Inc",
    "wof:placetype":"venue"
},
  "geometry": {"coordinates":[-122.403776,37.78904],"type":"Point"}
}