{
  "type": "Feature",
  "properties": {
    "iso:country":"US",
    "sg:address":"291 W 22nd St",
    "sg:city":"San Pedro",
    "sg:classifiers":[
        {
            "category":"Freight",
            "type":"Transportation"
        }
    ],
    "sg:phone":"+1 310 832 3310",
    "sg:postcode":"90731",
    "sg:province":"CA",
    "sg:tags":[
        "operator",
        "trucking"
    ],
    "wof:name":"Thunder Road Trucking",
    "wof:placetype":"venue"
},
  "geometry": {"coordinates":[-118.282466,33.725025],"type":"Point"}
}