{
  "type": "Feature",
  "properties": {
    "iso:country":"US",
    "sg:address":"2535 E 1st St",
    "sg:city":"Los Angeles",
    "sg:classifiers":[
        {
            "category":"Home & Garden",
            "subcategory":"Furniture",
            "type":"Retail Goods"
        }
    ],
    "sg:phone":"+1 323 780 4043",
    "sg:postcode":"90033",
    "sg:province":"CA",
    "wof:name":"Villa Teocaly Furniture",
    "wof:placetype":"venue"
},
  "geometry": {"coordinates":[-118.207597,34.04286],"type":"Point"}
}