{
  "type": "Feature",
  "properties": {
    "iso:country":"US",
    "sg:address":"1622 Edinger Ave",
    "sg:city":"Tustin",
    "sg:classifiers":[
        {
            "category":"Building & Trades",
            "subcategory":"Plumbing",
            "type":"Services"
        }
    ],
    "sg:phone":"+1 714 566 0399",
    "sg:postcode":"92780",
    "sg:province":"CA",
    "sg:tags":[
        "contractor"
    ],
    "wof:name":"Fire Sprinkler Systems",
    "wof:placetype":"venue"
},
  "geometry": {"coordinates":[-117.82479499999999,33.720413],"type":"Point"}
}