{
  "type": "Feature",
  "properties": {
    "addr:full":"19635 Monteano Ln Yorba Linda CA 92886",
    "addr:housenumber":"19635",
    "addr:postcode":"92886",
    "addr:street":"Monteano Ln",
    "iso:country":"US",
    "sg:address":"19635 Monteano Ln",
    "sg:city":"Yorba Linda",
    "sg:classifiers":[
        {
            "category":"Wholesale",
            "subcategory":"Chemicals & Plastics",
            "type":"Manufacturing & Wholesale Goods"
        }
    ],
    "sg:phone":"+1 714 779 2043",
    "sg:postcode":"92886",
    "sg:province":"CA",
    "sg:tags":[
        "establishment"
    ],
    "wof:name":"Better Enterprises",
    "wof:placetype":"venue"
},
  "geometry": {"coordinates":[-117.79239,33.892881],"type":"Point"}
}