{
  "type": "Feature",
  "properties": {
    "iso:country":"US",
    "sg:address":"4 Stitt Ct",
    "sg:city":"Novato",
    "sg:classifiers":[
        {
            "category":"Building & Trades",
            "subcategory":"Construction",
            "type":"Services"
        }
    ],
    "sg:phone":"+1 415 897 7543",
    "sg:postcode":"94945",
    "sg:province":"CA",
    "sg:tags":[
        "masonry",
        "contractor"
    ],
    "wof:name":"James Nichelini Masonry",
    "wof:placetype":"venue"
},
  "geometry": {"coordinates":[-122.585855,38.110243],"type":"Point"}
}