{
  "type": "Feature",
  "properties": {
    "addr:full":"9115 Beverlywood St Los Angeles CA 90034",
    "addr:housenumber":"9115",
    "addr:postcode":"90034",
    "addr:street":"Beverlywood St",
    "iso:country":"US",
    "sg:address":"9115 Beverlywood St",
    "sg:city":"Los Angeles",
    "sg:classifiers":[
        {
            "category":"Wholesale",
            "subcategory":"Apparel",
            "type":"Manufacturing & Wholesale Goods"
        }
    ],
    "sg:phone":"+1 310 838 0297",
    "sg:postcode":"90034",
    "sg:province":"CA",
    "sg:tags":[
        "mfg",
        "wear",
        "representative"
    ],
    "wof:name":"Sisters",
    "wof:placetype":"venue"
},
  "geometry": {"coordinates":[-118.389995,34.038587],"type":"Point"}
}