{
  "type": "Feature",
  "properties": {
    "addr:full":"720 Taylor St Fairfield CA 94533",
    "addr:housenumber":"720",
    "addr:postcode":"94533",
    "addr:street":"Taylor St",
    "iso:country":"US",
    "sg:address":"720 Taylor St",
    "sg:city":"Fairfield",
    "sg:classifiers":[
        {
            "category":"Personal",
            "subcategory":"Beauty Salon",
            "type":"Services"
        }
    ],
    "sg:phone":"+1 707 425 8305",
    "sg:postcode":"94533",
    "sg:province":"CA",
    "sg:tags":[
        "electrolysis"
    ],
    "wof:name":"Hair Systems",
    "wof:placetype":"venue"
},
  "geometry": {"coordinates":[-122.04720399999999,38.249473],"type":"Point"}
}