{
  "type": "Feature",
  "properties": {
    "iso:country":"US",
    "sg:address":"3300 Irvine Ave",
    "sg:city":"Newport Beach",
    "sg:classifiers":[
        {
            "category":"Professional",
            "subcategory":"Accounting & Tax Preparation",
            "type":"Services"
        }
    ],
    "sg:phone":"+1 949 833 9333",
    "sg:postcode":"92660",
    "sg:province":"CA",
    "sg:tags":[
        "accountant"
    ],
    "sg:website":"www.pjmcpas.com",
    "wof:name":"Paddock Jones Morse Inc",
    "wof:placetype":"venue"
},
  "geometry": {"coordinates":[-117.878167,33.659147],"type":"Point"}
}