{
  "type": "Feature",
  "properties": {
    "iso:country":"US",
    "sg:address":"2817 E Lomita Ave",
    "sg:city":"Orange",
    "sg:classifiers":[
        {
            "category":"Building & Trades",
            "subcategory":"Cleaning & Sanitation",
            "type":"Services"
        }
    ],
    "sg:phone":"+1 714 639 2799",
    "sg:postcode":"92867",
    "sg:province":"CA",
    "sg:tags":[
        "window"
    ],
    "wof:name":"K & M Window Cleaning",
    "wof:placetype":"venue"
},
  "geometry": {"coordinates":[-117.823024,33.800845],"type":"Point"}
}