{
  "type": "Feature",
  "properties": {
    "iso:country":"US",
    "sg:address":"1921 de la Vina St",
    "sg:city":"Santa Barbara",
    "sg:classifiers":[
        {
            "category":"Retail",
            "subcategory":"Animal Services",
            "type":"Services"
        }
    ],
    "sg:phone":"+1 805 687 2083",
    "sg:postcode":"93101",
    "sg:province":"CA",
    "wof:name":"A 1 Laundro Mutt",
    "wof:placetype":"venue"
},
  "geometry": {"coordinates":[-119.71672,34.428413],"type":"Point"}
}