{
  "type": "Feature",
  "properties": {
    "addr:full":"21 Flood Ave San Francisco CA 94131",
    "addr:housenumber":"21",
    "addr:postcode":"94131",
    "addr:street":"Flood Ave",
    "iso:country":"US",
    "sg:address":"21 Flood Ave",
    "sg:city":"San Francisco",
    "sg:classifiers":[
        {
            "category":"Building & Trades",
            "subcategory":"Plumbing",
            "type":"Services"
        }
    ],
    "sg:phone":"+1 415 550 0511",
    "sg:postcode":"94131",
    "sg:province":"CA",
    "sg:tags":[
        "plumbing",
        "contractor"
    ],
    "wof:name":"8a Plumbing",
    "wof:placetype":"venue"
},
  "geometry": {"coordinates":[-122.44179200000001,37.729837],"type":"Point"}
}