{
  "type": "Feature",
  "properties": {
    "addr:full":"7468 Phinney Way San Jose CA 95139",
    "addr:housenumber":"7468",
    "addr:postcode":"95139",
    "addr:street":"Phinney Way",
    "iso:country":"US",
    "sg:address":"7468 Phinney Way",
    "sg:city":"San Jose",
    "sg:classifiers":[
        {
            "category":"Local Transit",
            "type":"Transportation"
        }
    ],
    "sg:phone":"+1 408 225 5466",
    "sg:postcode":"95139",
    "sg:province":"CA",
    "sg:tags":[
        "passenger"
    ],
    "wof:name":"Limousines By Land",
    "wof:placetype":"venue"
},
  "geometry": {"coordinates":[-121.762877,37.220085],"type":"Point"}
}