{
  "type": "Feature",
  "properties": {
    "iso:country":"US",
    "sg:address":"5022 Melrose Avenue",
    "sg:city":"Los Angeles",
    "sg:classifiers":[
        {
            "category":"Coffee & Tea",
            "type":"Food & Drink"
        }
    ],
    "sg:phone":"+1 323 464 4555",
    "sg:postcode":"90038",
    "sg:province":"CA",
    "wof:name":"World of Nuts & Coffee",
    "wof:placetype":"venue"
},
  "geometry": {"coordinates":[-118.310242,34.083626],"type":"Point"}
}