{
  "type": "Feature",
  "properties": {
    "addr:full":"25572 N Ave Stanford Valencia CA 91355",
    "addr:housenumber":"25572",
    "addr:postcode":"91355",
    "addr:street":"N Ave",
    "iso:country":"US",
    "sg:address":"25572 N Ave Stanford",
    "sg:city":"Valencia",
    "sg:classifiers":[
        {
            "category":"Shopping",
            "subcategory":"Computers & Home Electronics",
            "type":"Retail Goods"
        }
    ],
    "sg:phone":"+1 661 294 1300",
    "sg:postcode":"91355",
    "sg:province":"CA",
    "wof:name":"Gen Source Corp",
    "wof:placetype":"venue"
},
  "geometry": {"coordinates":[-118.58732500000001,34.432717],"type":"Point"}
}