{
  "type": "Feature",
  "properties": {
    "addr:full":"2347 Pinturo Way Rancho Cordova CA 95670",
    "addr:housenumber":"2347",
    "addr:postcode":"95670",
    "addr:street":"Pinturo Way",
    "iso:country":"US",
    "sg:address":"2347 Pinturo Way",
    "sg:city":"Rancho Cordova",
    "sg:classifiers":[
        {
            "category":"Building & Trades",
            "subcategory":"Construction",
            "type":"Services"
        }
    ],
    "sg:phone":"+1 916 715 6005",
    "sg:postcode":"95670",
    "sg:province":"CA",
    "sg:tags":[
        "painter"
    ],
    "wof:name":"Time For Painting",
    "wof:placetype":"venue"
},
  "geometry": {"coordinates":[-121.283278,38.60893],"type":"Point"}
}