{
  "type": "Feature",
  "properties": {
    "iso:country":"US",
    "sg:address":"555 Menlo Dr",
    "sg:city":"Rocklin",
    "sg:classifiers":[
        {
            "category":"Manufacturing",
            "subcategory":"Printing",
            "type":"Manufacturing & Wholesale Goods"
        }
    ],
    "sg:phone":"+1 916 774 4000",
    "sg:postcode":"95765",
    "sg:province":"CA",
    "sg:tags":[
        "publisher",
        "software"
    ],
    "wof:name":"Data Control Corp",
    "wof:placetype":"venue"
},
  "geometry": {"coordinates":[-121.29709800000001,38.812606],"type":"Point"}
}