{
  "type": "Feature",
  "properties": {
    "iso:country":"US",
    "sg:address":"6311 N Cedar Ave",
    "sg:city":"Fresno",
    "sg:classifiers":[
        {
            "category":"Building & Trades",
            "subcategory":"Construction",
            "type":"Services"
        }
    ],
    "sg:phone":"+1 559 432 5340",
    "sg:postcode":"93710",
    "sg:province":"CA",
    "sg:tags":[
        "coping",
        "plastering",
        "tiling",
        "pool",
        "swimming"
    ],
    "wof:name":"Petersen's Pool Svc",
    "wof:placetype":"venue"
},
  "geometry": {"coordinates":[-119.75423000000001,36.82906],"type":"Point"}
}