{
  "type": "Feature",
  "properties": {
    "iso:country":"US",
    "sg:address":"990 Temple Ter",
    "sg:city":"Laguna Beach",
    "sg:classifiers":[
        {
            "category":"Organizations",
            "subcategory":"Religious Organization",
            "type":"Services"
        }
    ],
    "sg:phone":"+1 949 494 9701",
    "sg:postcode":"92651",
    "sg:province":"CA",
    "sg:tags":[
        "church"
    ],
    "wof:name":"St Catherine Catholic Church",
    "wof:placetype":"venue"
},
  "geometry": {"coordinates":[-117.771961,33.538222],"type":"Point"}
}