{
  "type": "Feature",
  "properties": {
    "iso:country":"US",
    "sg:address":"10577 Ilex Ave",
    "sg:city":"Pacoima",
    "sg:classifiers":[
        {
            "category":"Place Of Worship",
            "type":"Public Place"
        }
    ],
    "sg:phone":"+1 818 890 9625",
    "sg:postcode":"91331",
    "sg:province":"CA",
    "sg:tags":[
        "church"
    ],
    "wof:name":"Alhambra Hispanic Foursquare Church",
    "wof:placetype":"venue"
},
  "geometry": {"coordinates":[-118.41949,34.262127],"type":"Point"}
}