{
  "type": "Feature",
  "properties": {
    "addr:full":"149 Ardmore Rd Kensington CA 94707",
    "addr:housenumber":"149",
    "addr:postcode":"94707",
    "addr:street":"Ardmore Rd",
    "iso:country":"US",
    "sg:address":"149 Ardmore Rd",
    "sg:city":"Kensington",
    "sg:classifiers":[
        {
            "category":"Wholesale",
            "subcategory":"Non-durable Goods",
            "type":"Manufacturing & Wholesale Goods"
        }
    ],
    "sg:phone":"+1 415 527 4847",
    "sg:postcode":"94707",
    "sg:province":"CA",
    "sg:tags":[
        "dry",
        "goods-wholesale"
    ],
    "wof:name":"Hilltop Building Supp",
    "wof:placetype":"venue"
},
  "geometry": {"coordinates":[-122.279636,37.903704],"type":"Point"}
}