{
  "type": "Feature",
  "properties": {
    "addr:full":"401 W Inyokern Rd Ridgecrest CA 93555",
    "addr:housenumber":"401",
    "addr:postcode":"93555",
    "addr:street":"W Inyokern Rd",
    "iso:country":"US",
    "sg:address":"401 W Inyokern Rd",
    "sg:city":"Ridgecrest",
    "sg:classifiers":[
        {
            "category":"Wholesale",
            "subcategory":"Auto Parts",
            "type":"Manufacturing & Wholesale Goods"
        }
    ],
    "sg:phone":"+1 760 446 5559",
    "sg:postcode":"93555",
    "sg:province":"CA",
    "sg:tags":[
        "automobile",
        "wrecking"
    ],
    "wof:name":"Sierra Auto Recycling",
    "wof:placetype":"venue"
},
  "geometry": {"coordinates":[-117.677393,35.65153],"type":"Point"}
}