{
  "type": "Feature",
  "properties": {
    "addr:full":"6126 Atlantic Blvd Maywood CA 90270",
    "addr:housenumber":"6126",
    "addr:postcode":"90270",
    "addr:street":"Atlantic Blvd",
    "iso:country":"US",
    "sg:address":"6126 Atlantic Blvd",
    "sg:city":"Maywood",
    "sg:classifiers":[
        {
            "category":"Health Services",
            "subcategory":"Clinic",
            "type":"Services"
        },
        {
            "category":"Health Services",
            "subcategory":"Health Practitioner",
            "type":"Services"
        }
    ],
    "sg:phone":"+1 323 560 2683",
    "sg:postcode":"90270",
    "sg:province":"CA",
    "sg:tags":[
        "acupuncture",
        "loss",
        "weight"
    ],
    "wof:name":"Cura Natural Healthcare",
    "wof:placetype":"venue"
},
  "geometry": {"coordinates":[-118.185997,33.9827],"type":"Point"}
}