{
  "type": "Feature",
  "properties": {
    "iso:country":"US",
    "sg:address":"1855 N Orange Olive Rd",
    "sg:city":"Orange",
    "sg:classifiers":[
        {
            "category":"Education",
            "subcategory":"School",
            "type":"Public Place"
        }
    ],
    "sg:phone":"+1 714 998 4852",
    "sg:postcode":"92865",
    "sg:province":"CA",
    "sg:tags":[
        "high",
        "middle",
        "elementary"
    ],
    "wof:name":"Covenant Christian School",
    "wof:placetype":"venue"
},
  "geometry": {"coordinates":[-117.852997,33.8181],"type":"Point"}
}