{
  "type": "Feature",
  "properties": {
    "addr:full":"413 S Riverside Dr Ste A Modesto CA 95354",
    "addr:housenumber":"413",
    "addr:postcode":"ca 95354",
    "addr:street":"S Riverside Dr Ste A",
    "iso:country":"US",
    "sg:address":"413 S Riverside Dr Ste A",
    "sg:city":"Modesto",
    "sg:classifiers":[
        {
            "category":"Food & Beverages",
            "subcategory":"Liquor & Beverages",
            "type":"Retail Goods"
        }
    ],
    "sg:phone":"+1 209 523 1828",
    "sg:postcode":"95354",
    "sg:province":"CA",
    "sg:tags":[
        "beer",
        "spirit",
        "wine"
    ],
    "sg:website":"featherpetro.com",
    "wof:name":"Stop N Save Liquors Corporate Office",
    "wof:placetype":"venue"
},
  "geometry": {"coordinates":[-120.947998,37.634102],"type":"Point"}
}