{
  "type": "Feature",
  "properties": {
    "iso:country":"US",
    "sg:address":"3310 Airport Ave",
    "sg:city":"Santa Monica",
    "sg:classifiers":[
        {
            "category":"Building & Trades",
            "subcategory":"Construction",
            "type":"Services"
        }
    ],
    "sg:phone":"+1 310 390 9666",
    "sg:postcode":"90405",
    "sg:province":"CA",
    "sg:tags":[
        "contractor"
    ],
    "wof:name":"Overview",
    "wof:placetype":"venue"
},
  "geometry": {"coordinates":[-118.44572700000001,34.016059],"type":"Point"}
}