{
  "type": "Feature",
  "properties": {
    "addr:full":"5710 E 2nd St Long Beach CA 90803",
    "addr:housenumber":"5710",
    "addr:postcode":"90803",
    "addr:street":"E 2Nd St",
    "iso:country":"US",
    "sg:address":"5710 E 2nd St",
    "sg:city":"Long Beach",
    "sg:classifiers":[
        {
            "category":"Arts & Performance",
            "subcategory":"Theater",
            "type":"Entertainment"
        }
    ],
    "sg:phone":"+1 562 434 5800",
    "sg:postcode":"90803",
    "sg:province":"CA",
    "sg:tags":[
        "bureau"
    ],
    "wof:name":"Brain Tangent Entertainment",
    "wof:placetype":"venue"
},
  "geometry": {"coordinates":[-118.122291,33.75669],"type":"Point"}
}