{
  "type": "Feature",
  "properties": {
    "addr:full":"2801 L St Sacramento CA 95816",
    "addr:housenumber":"2801",
    "addr:postcode":"95816",
    "addr:street":"L St",
    "iso:country":"US",
    "sg:address":"2801 L St",
    "sg:city":"Sacramento",
    "sg:classifiers":[
        {
            "category":"Coffee & Tea",
            "type":"Food & Drink"
        }
    ],
    "sg:postcode":"95816",
    "sg:province":"CA",
    "wof:name":"Etosha Coffee Bar",
    "wof:placetype":"venue"
},
  "geometry": {"coordinates":[-121.469255,38.572018],"type":"Point"}
}