{
  "type": "Feature",
  "properties": {
    "iso:country":"US",
    "sg:address":"5268 System Dr",
    "sg:city":"Huntington Beach",
    "sg:classifiers":[
        {
            "category":"Wholesale",
            "subcategory":"Machinery & Supplies",
            "type":"Manufacturing & Wholesale Goods"
        }
    ],
    "sg:phone":"+1 714 894 5188",
    "sg:postcode":"92649",
    "sg:province":"CA",
    "sg:tags":[
        "machine",
        "parts"
    ],
    "wof:name":"Palos Verdes Business Entps",
    "wof:placetype":"venue"
},
  "geometry": {"coordinates":[-118.034972,33.730778],"type":"Point"}
}