{
  "type": "Feature",
  "properties": {
    "addr:full":"5000 Valley West Blvd Arcata CA 95521",
    "addr:housenumber":"5000",
    "addr:postcode":"95521",
    "addr:street":"Valley West Blvd",
    "iso:country":"US",
    "sg:address":"5000 Valley West Blvd",
    "sg:city":"Arcata",
    "sg:classifiers":[
        {
            "category":"Professional",
            "subcategory":"Management & Consulting",
            "type":"Services"
        }
    ],
    "sg:phone":"+1 707 822 7313",
    "sg:postcode":"95521",
    "sg:province":"CA",
    "sg:tags":[
        "consultant",
        "safety"
    ],
    "sg:website":"www.norcalsafety.com",
    "wof:name":"Northern Ca Safety Consortium",
    "wof:placetype":"venue"
},
  "geometry": {"coordinates":[-124.083279,40.901264],"type":"Point"}
}