{
  "type": "Feature",
  "properties": {
    "addr:full":"100 Appleton Ave San Francisco CA 94110",
    "addr:housenumber":"100",
    "addr:postcode":"94110",
    "addr:street":"Appleton Ave",
    "iso:country":"US",
    "sg:address":"100 Appleton Ave",
    "sg:city":"San Francisco",
    "sg:classifiers":[
        {
            "category":"Real Estate",
            "subcategory":"Real Estate Agent",
            "type":"Services"
        }
    ],
    "sg:phone":"+1 415 821 1173",
    "sg:postcode":"94110",
    "sg:province":"CA",
    "sg:tags":[
        "authorities",
        "housing"
    ],
    "wof:name":"S F Housing Authority Site Ofc",
    "wof:placetype":"venue"
},
  "geometry": {"coordinates":[-122.42090899999999,37.737611],"type":"Point"}
}