{
  "type": "Feature",
  "properties": {
    "iso:country":"US",
    "sg:address":"162 S Rancho Santa Fe Rd Ste B20",
    "sg:city":"Encinitas",
    "sg:classifiers":[
        {
            "category":"Personal",
            "subcategory":"Barber",
            "type":"Services"
        }
    ],
    "sg:phone":"+1 760 942 8311",
    "sg:postcode":"92024",
    "sg:province":"CA",
    "wof:name":"Stainless",
    "wof:placetype":"venue"
},
  "geometry": {"coordinates":[-117.23699999999999,33.035801],"type":"Point"}
}