{
  "type": "Feature",
  "properties": {
    "addr:full":"371 Palmtag Dr Hollister CA 95023",
    "addr:housenumber":"371",
    "addr:postcode":"hollister ca 95023",
    "addr:street":"Palmtag Dr",
    "iso:country":"US",
    "sg:address":"371 Palmtag Dr",
    "sg:city":"Hollister",
    "sg:classifiers":[
        {
            "category":"Restaurant",
            "type":"Food & Drink"
        }
    ],
    "sg:phone":"+1 831 637 9683",
    "sg:postcode":"95023",
    "sg:province":"CA",
    "wof:name":"Mc Donald's",
    "wof:placetype":"venue"
},
  "geometry": {"coordinates":[-121.404101,36.841106],"type":"Point"}
}