{
  "type": "Feature",
  "properties": {
    "addr:full":"23915 Ventura Blvd Calabasas CA 91302",
    "addr:housenumber":"23915",
    "addr:postcode":"91302",
    "addr:street":"Ventura Blvd",
    "iso:country":"US",
    "sg:address":"23915 Ventura Blvd",
    "sg:city":"Calabasas",
    "sg:classifiers":[
        {
            "category":"Professional",
            "subcategory":"Business Services",
            "type":"Services"
        }
    ],
    "sg:phone":"+1 818 591 3555",
    "sg:postcode":"91302",
    "sg:province":"CA",
    "sg:tags":[
        "inspection"
    ],
    "wof:name":"Accu-Test Engineering Labs Inc",
    "wof:placetype":"venue"
},
  "geometry": {"coordinates":[-118.64784400000001,34.155577],"type":"Point"}
}