{
  "type": "Feature",
  "properties": {
    "iso:country":"US",
    "sg:address":"282 E 7th St",
    "sg:city":"Beaumont",
    "sg:classifiers":[
        {
            "category":"Building & Trades",
            "subcategory":"Electrical",
            "type":"Services"
        }
    ],
    "sg:phone":"+1 951 845 2975",
    "sg:postcode":"92223",
    "sg:province":"CA",
    "sg:tags":[
        "electrician"
    ],
    "wof:name":"Vasquez Electrical",
    "wof:placetype":"venue"
},
  "geometry": {"coordinates":[-116.978797,33.930908],"type":"Point"}
}