{
  "type": "Feature",
  "properties": {
    "addr:full":"39210 State St Fremont CA 94538",
    "addr:housenumber":"39210",
    "addr:postcode":"94538",
    "addr:street":"State St",
    "iso:country":"US",
    "sg:address":"39210 State St",
    "sg:city":"Fremont",
    "sg:classifiers":[
        {
            "category":"Health Services",
            "subcategory":"Clinic",
            "type":"Services"
        }
    ],
    "sg:phone":"+1 510 608 0730",
    "sg:postcode":"94538",
    "sg:province":"CA",
    "sg:tags":[
        "home"
    ],
    "wof:name":"TLC Staff Builders",
    "wof:placetype":"venue"
},
  "geometry": {"coordinates":[-121.98352300000001,37.549536],"type":"Point"}
}