{
  "type": "Feature",
  "properties": {
    "addr:full":"2710 Pinole Valley Rd Pinole CA 94564",
    "addr:housenumber":"2710",
    "addr:postcode":"94564",
    "addr:street":"Pinole Valley Rd",
    "iso:country":"US",
    "sg:address":"2710 Pinole Valley Rd",
    "sg:city":"Pinole",
    "sg:classifiers":[
        {
            "category":"Sports & Exercise",
            "subcategory":"Gym",
            "type":"Entertainment"
        }
    ],
    "sg:phone":"+1 510 758 8800",
    "sg:postcode":"94564",
    "sg:province":"CA",
    "sg:tags":[
        "club",
        "health",
        "studio",
        "gymnasium"
    ],
    "wof:name":"Cuts Fitness For Men",
    "wof:placetype":"venue"
},
  "geometry": {"coordinates":[-122.285759,37.994447],"type":"Point"}
}