{
  "type": "Feature",
  "properties": {
    "iso:country":"US",
    "sg:address":"300 Carlsbad Village Dr Suite 115",
    "sg:city":"Carlsbad",
    "sg:classifiers":[
        {
            "category":"Wholesale",
            "subcategory":"Stationery",
            "type":"Manufacturing & Wholesale Goods"
        }
    ],
    "sg:phone":"+1 760 720 7525",
    "sg:postcode":"92008",
    "sg:province":"CA",
    "sg:tags":[
        "card"
    ],
    "wof:name":"Linda's Gifts",
    "wof:placetype":"venue"
},
  "geometry": {"coordinates":[-117.351021,33.158283],"type":"Point"}
}