{
  "type": "Feature",
  "properties": {
    "iso:country":"US",
    "sg:address":"2557 Los Lomitas Way",
    "sg:city":"Covina",
    "sg:classifiers":[
        {
            "category":"Travel",
            "subcategory":"Travel Agent",
            "type":"Entertainment"
        }
    ],
    "sg:phone":"+1 626 332 8484",
    "sg:postcode":"91724",
    "sg:province":"CA",
    "sg:tags":[
        "agency"
    ],
    "wof:name":"Just Cruising",
    "wof:placetype":"venue"
},
  "geometry": {"coordinates":[-117.86447800000001,34.060839],"type":"Point"}
}