{
  "type": "Feature",
  "properties": {
    "addr:full":"187 Turner Ave Gridley CA 95948",
    "addr:housenumber":"187",
    "addr:postcode":"95948",
    "addr:street":"Turner Ave",
    "iso:country":"US",
    "sg:address":"187 Turner Ave",
    "sg:city":"Gridley",
    "sg:classifiers":[
        {
            "category":"Farming",
            "subcategory":"Farm",
            "type":"Manufacturing & Wholesale Goods"
        }
    ],
    "sg:phone":"+1 530 846 0279",
    "sg:postcode":"95948",
    "sg:province":"CA",
    "sg:tags":[
        "crop",
        "general"
    ],
    "wof:name":"Murrahs Farms",
    "wof:placetype":"venue"
},
  "geometry": {"coordinates":[-121.671527,39.323415],"type":"Point"}
}