{
  "type": "Feature",
  "properties": {
    "iso:country":"US",
    "sg:address":"204 23rd St",
    "sg:city":"Sacramento",
    "sg:classifiers":[
        {
            "category":"Building & Trades",
            "subcategory":"Construction",
            "type":"Services"
        }
    ],
    "sg:phone":"+1 916 448 3535",
    "sg:postcode":"95816",
    "sg:province":"CA",
    "sg:tags":[
        "pipe",
        "line",
        "contractor"
    ],
    "wof:name":"ABC Svc",
    "wof:placetype":"venue"
},
  "geometry": {"coordinates":[-121.47239999999999,38.583901],"type":"Point"}
}