{
  "type": "Feature",
  "properties": {
    "iso:country":"US",
    "sg:address":"1442 E. Lincoln Avenue Suite 463",
    "sg:city":"Orange",
    "sg:classifiers":[
        {
            "category":"Health Services",
            "subcategory":"Clinic",
            "type":"Services"
        }
    ],
    "sg:phone":"+1 714 860 4669",
    "sg:postcode":"92865",
    "sg:province":"CA",
    "sg:tags":[
        "medical"
    ],
    "wof:name":"Rally Round Non-Medical Home Care",
    "wof:placetype":"venue"
},
  "geometry": {"coordinates":[-117.838494,33.833918],"type":"Point"}
}