{
  "type": "Feature",
  "properties": {
    "iso:country":"US",
    "sg:address":"937 S Coast Highway 101 Ste 110",
    "sg:city":"Encinitas",
    "sg:classifiers":[
        {
            "category":"Sports & Exercise",
            "subcategory":"Bicycle Rental",
            "type":"Entertainment"
        }
    ],
    "sg:phone":"+1 760 634 8004",
    "sg:postcode":"92024",
    "sg:province":"CA",
    "sg:tags":[
        "wear"
    ],
    "wof:name":"Max Muscle Sports Nutrition",
    "wof:placetype":"venue"
},
  "geometry": {"coordinates":[-117.292891,33.026982],"type":"Point"}
}