{
  "type": "Feature",
  "properties": {
    "addr:full":"1437 Furneaux Rd Marysville CA 95961",
    "addr:housenumber":"1437",
    "addr:postcode":"95961",
    "addr:street":"Furneaux Rd",
    "iso:country":"US",
    "sg:address":"1437 Furneaux Rd",
    "sg:city":"Marysville",
    "sg:classifiers":[
        {
            "category":"Building & Trades",
            "subcategory":"Construction",
            "type":"Services"
        }
    ],
    "sg:phone":"+1 530 742 7124",
    "sg:postcode":"95961",
    "sg:province":"CA",
    "sg:tags":[
        "heavy",
        "dam",
        "engineering",
        "including",
        "levee"
    ],
    "wof:name":"Nordic Industries Inc",
    "wof:placetype":"venue"
},
  "geometry": {"coordinates":[-121.571727,39.107037],"type":"Point"}
}