{
  "type": "Feature",
  "properties": {
    "iso:country":"US",
    "sg:address":"25787 Mesa Ct",
    "sg:city":"San Bernardino",
    "sg:classifiers":[
        {
            "category":"Social Services",
            "subcategory":"Adult Care",
            "type":"Services"
        }
    ],
    "sg:phone":"+1 909 864 3748",
    "sg:postcode":"92404",
    "sg:province":"CA",
    "sg:tags":[
        "home",
        "group"
    ],
    "wof:name":"Horrigan Enterprises",
    "wof:placetype":"venue"
},
  "geometry": {"coordinates":[-117.241591,34.154422],"type":"Point"}
}