{
  "type": "Feature",
  "properties": {
    "addr:full":"4673 Riverside Dr Chino CA 91710",
    "addr:housenumber":"4673",
    "addr:postcode":"91710",
    "addr:street":"Riverside Dr",
    "iso:country":"US",
    "sg:address":"4673 Riverside Dr",
    "sg:city":"Chino",
    "sg:classifiers":[
        {
            "category":"Restaurant",
            "type":"Food & Drink"
        }
    ],
    "sg:menulink":"http://www.allmenus.com/ca/ontario/87722-little-caesars-pizza/menu/",
    "sg:phone":"+1 909 591 8437",
    "sg:postcode":"91710",
    "sg:province":"CA",
    "sg:tags":[
        "american",
        "pizza"
    ],
    "wof:name":"Little Caesar's Pizza",
    "wof:placetype":"venue"
},
  "geometry": {"coordinates":[-117.702769,34.018527],"type":"Point"}
}