{
  "type": "Feature",
  "properties": {
    "addr:full":"18454 Oxnard St Tarzana CA 91356",
    "addr:housenumber":"18454",
    "addr:postcode":"91356",
    "addr:street":"Oxnard St",
    "iso:country":"US",
    "sg:address":"18454 Oxnard St",
    "sg:city":"Tarzana",
    "sg:classifiers":[
        {
            "category":"Organizations",
            "subcategory":"Community Association",
            "type":"Services"
        }
    ],
    "sg:phone":"+1 818 705 7383",
    "sg:postcode":"91356",
    "sg:province":"CA",
    "sg:tags":[
        "club"
    ],
    "wof:name":"Frisky Kitty",
    "wof:placetype":"venue"
},
  "geometry": {"coordinates":[-118.531982,34.180129],"type":"Point"}
}