{
  "type": "Feature",
  "properties": {
    "addr:full":"4900 Madison Ave Sacramento CA 95841",
    "addr:housenumber":"4900",
    "addr:postcode":"95841",
    "addr:street":"Madison Ave",
    "iso:country":"US",
    "sg:address":"4900 Madison Ave",
    "sg:city":"Sacramento",
    "sg:classifiers":[
        {
            "category":"Professional",
            "subcategory":"Management & Consulting",
            "type":"Services"
        }
    ],
    "sg:phone":"+1 916 344 7290",
    "sg:postcode":"95841",
    "sg:province":"CA",
    "sg:tags":[
        "agricultural",
        "consultant"
    ],
    "wof:name":"Gastronom Kiev Market",
    "wof:placetype":"venue"
},
  "geometry": {"coordinates":[-121.34690000000001,38.660838],"type":"Point"}
}