{
  "type": "Feature",
  "properties": {
    "iso:country":"US",
    "sg:address":"2030 Main St Ste 350",
    "sg:city":"Irvine",
    "sg:classifiers":[
        {
            "category":"Banks & Credit Unions",
            "subcategory":"Financial Services",
            "type":"Services"
        }
    ],
    "sg:phone":"+1 800 790 0736",
    "sg:postcode":"92614",
    "sg:province":"CA",
    "sg:tags":[
        "broker",
        "mortgage"
    ],
    "sg:website":"www.fhafundingpro.com",
    "wof:name":"FHA Funding Pro",
    "wof:placetype":"venue"
},
  "geometry": {"coordinates":[-117.853145,33.683044],"type":"Point"}
}