{
  "type": "Feature",
  "properties": {
    "iso:country":"US",
    "sg:address":"1917 Santa Anita Ave",
    "sg:city":"South El Monte",
    "sg:classifiers":[
        {
            "category":"Shopping",
            "subcategory":"Clothing, Apparel, & Fashions",
            "type":"Retail Goods"
        }
    ],
    "sg:phone":"+1 626 443 2887",
    "sg:postcode":"91733",
    "sg:province":"CA",
    "sg:tags":[
        "sport",
        "wear",
        "sportswear"
    ],
    "wof:name":"Ettex Inc",
    "wof:placetype":"venue"
},
  "geometry": {"coordinates":[-118.04299899999999,34.050701],"type":"Point"}
}