{
  "type": "Feature",
  "properties": {
    "iso:country":"US",
    "sg:address":"1750 Howe Ave",
    "sg:city":"Sacramento",
    "sg:classifiers":[
        {
            "category":"Wholesale",
            "subcategory":"Computers",
            "type":"Manufacturing & Wholesale Goods"
        }
    ],
    "sg:phone":"+1 916 922 6838",
    "sg:postcode":"95825",
    "sg:province":"CA",
    "wof:name":"Computerlands",
    "wof:placetype":"venue"
},
  "geometry": {"coordinates":[-121.41521899999999,38.597182],"type":"Point"}
}