{
  "type": "Feature",
  "properties": {
    "addr:full":"6872 Katella Ave Cypress CA 90630",
    "addr:housenumber":"6872",
    "addr:postcode":"90630",
    "addr:street":"Katella Ave",
    "iso:country":"US",
    "sg:address":"6872 Katella Ave",
    "sg:city":"Cypress",
    "sg:classifiers":[
        {
            "category":"Shopping",
            "type":"Retail Goods"
        }
    ],
    "sg:phone":"+1 714 901 1860",
    "sg:postcode":"90630",
    "sg:province":"CA",
    "sg:tags":[
        "cosmetic",
        "perfume"
    ],
    "wof:name":"Fragrance Shop",
    "wof:placetype":"venue"
},
  "geometry": {"coordinates":[-118.01188399999999,33.80287],"type":"Point"}
}