{
  "type": "Feature",
  "properties": {
    "addr:full":"203 Covina Ave Long Beach CA 90803",
    "addr:housenumber":"203",
    "addr:postcode":"90803",
    "addr:street":"Covina Ave",
    "iso:country":"US",
    "sg:address":"203 Covina Ave",
    "sg:city":"Long Beach",
    "sg:classifiers":[
        {
            "category":"Real Estate",
            "subcategory":"Real Estate Agent",
            "type":"Services"
        }
    ],
    "sg:phone":"+1 562 433 2767",
    "sg:postcode":"90803",
    "sg:province":"CA",
    "wof:name":"Inco Real Estate Co",
    "wof:placetype":"venue"
},
  "geometry": {"coordinates":[-118.13376700000001,33.760174],"type":"Point"}
}