{
  "type": "Feature",
  "properties": {
    "addr:full":"2261 S Carmelina Ave Los Angeles CA 90064",
    "addr:housenumber":"2261",
    "addr:postcode":"90064",
    "addr:street":"S Carmelina Ave",
    "iso:country":"US",
    "sg:address":"2261 S Carmelina Ave",
    "sg:city":"Los Angeles",
    "sg:classifiers":[
        {
            "category":"Wholesale",
            "subcategory":"Durable Goods & Equipment",
            "type":"Manufacturing & Wholesale Goods"
        }
    ],
    "sg:phone":"+1 310 207 6841",
    "sg:postcode":"90064",
    "sg:province":"CA",
    "sg:tags":[
        "luggage"
    ],
    "sg:website":"www.lodis.com",
    "wof:name":"Lodis Corp",
    "wof:placetype":"venue"
},
  "geometry": {"coordinates":[-118.455122,34.03],"type":"Point"}
}