{
  "type": "Feature",
  "properties": {
    "iso:country":"US",
    "sg:address":"21906 Ventura Blvd",
    "sg:city":"Woodland Hills",
    "sg:classifiers":[
        {
            "category":"Shopping",
            "subcategory":"Pets & Pet Supplies",
            "type":"Retail Goods"
        }
    ],
    "sg:phone":"+1 818 716 5933",
    "sg:postcode":"91364",
    "sg:province":"CA",
    "sg:tags":[
        "store"
    ],
    "wof:name":"California Pet Center",
    "wof:placetype":"venue"
},
  "geometry": {"coordinates":[-118.603996,34.168598],"type":"Point"}
}