{
  "type": "Feature",
  "properties": {
    "iso:country":"US",
    "sg:address":"3658 Walnut Grove Ave",
    "sg:city":"Rosemead",
    "sg:classifiers":[
        {
            "category":"Organizations",
            "subcategory":"Religious Organization",
            "type":"Services"
        }
    ],
    "sg:phone":"+1 626 571 5537",
    "sg:postcode":"91770",
    "sg:province":"CA",
    "sg:tags":[
        "church"
    ],
    "wof:name":"First Evangelical Church",
    "wof:placetype":"venue"
},
  "geometry": {"coordinates":[-118.081942,34.074724],"type":"Point"}
}