{
  "type": "Feature",
  "properties": {
    "addr:full":"401 Broadway Oakland CA 94607",
    "addr:housenumber":"401",
    "addr:postcode":"94607",
    "addr:street":"Broadway",
    "iso:country":"US",
    "sg:address":"401 Broadway",
    "sg:city":"Oakland",
    "sg:classifiers":[
        {
            "category":"Professional",
            "subcategory":"Advertising",
            "type":"Services"
        }
    ],
    "sg:phone":"+1 510 832 4669",
    "sg:postcode":"94607",
    "sg:province":"CA",
    "sg:website":"www.aaamobiletechsupport.com",
    "wof:name":"AAAMOBILETECHSUPPORT.COM",
    "wof:placetype":"venue"
},
  "geometry": {"coordinates":[-122.27516900000001,37.798132],"type":"Point"}
}