{
  "type": "Feature",
  "properties": {
    "iso:country":"US",
    "sg:address":"1011 S Los Angeles St",
    "sg:city":"Los Angeles",
    "sg:classifiers":[
        {
            "category":"Wholesale",
            "subcategory":"Durable Goods & Equipment",
            "type":"Manufacturing & Wholesale Goods"
        }
    ],
    "sg:phone":"+1 213 749 1580",
    "sg:postcode":"90015",
    "sg:province":"CA",
    "sg:tags":[
        "importer"
    ],
    "wof:name":"R Tex Industries Inc",
    "wof:placetype":"venue"
},
  "geometry": {"coordinates":[-118.25709000000001,34.0386],"type":"Point"}
}