{
  "type": "Feature",
  "properties": {
    "addr:full":"260 S Fortuna Blvd Fortuna CA 95540",
    "addr:housenumber":"260",
    "addr:postcode":"95540",
    "addr:street":"S Fortuna Blvd",
    "iso:country":"US",
    "sg:address":"260 S Fortuna Blvd",
    "sg:city":"Fortuna",
    "sg:classifiers":[
        {
            "category":"Autos & Motor Vehicles",
            "subcategory":"Auto Supplies",
            "type":"Retail Goods"
        }
    ],
    "sg:phone":"+1 707 725 4120",
    "sg:postcode":"95540",
    "sg:province":"CA",
    "sg:tags":[
        "tire"
    ],
    "wof:name":"Hummel Tire & Wheel",
    "wof:placetype":"venue"
},
  "geometry": {"coordinates":[-124.146722,40.591541],"type":"Point"}
}