{
  "type": "Feature",
  "properties": {
    "iso:country":"US",
    "sg:address":"1490 N Glassell St",
    "sg:city":"Orange",
    "sg:classifiers":[
        {
            "category":"Building & Trades",
            "subcategory":"Construction",
            "type":"Services"
        }
    ],
    "sg:phone":"+1 714 633 0030",
    "sg:postcode":"92867",
    "sg:province":"CA",
    "sg:tags":[
        "roofing",
        "contractor"
    ],
    "wof:name":"Letner Roofing Co",
    "wof:placetype":"venue"
},
  "geometry": {"coordinates":[-117.853031,33.812139],"type":"Point"}
}