{
  "type": "Feature",
  "properties": {
    "iso:country":"US",
    "sg:address":"140 N Akers St",
    "sg:city":"Visalia",
    "sg:classifiers":[
        {
            "category":"Travel",
            "subcategory":"Hotels & Motels",
            "type":"Entertainment"
        }
    ],
    "sg:phone":"+1 559 636 7600",
    "sg:postcode":"93291",
    "sg:province":"CA",
    "wof:name":"Fairfield Inn",
    "wof:placetype":"venue"
},
  "geometry": {"coordinates":[-119.34962299999999,36.329522],"type":"Point"}
}