{
  "type": "Feature",
  "properties": {
    "addr:full":"15440 Beach Blvd Westminster CA 92683",
    "addr:housenumber":"15440",
    "addr:postcode":"92683",
    "addr:street":"Beach Blvd",
    "iso:country":"US",
    "sg:address":"15440 Beach Blvd",
    "sg:city":"Westminster",
    "sg:classifiers":[
        {
            "category":"Communications",
            "type":"Services"
        }
    ],
    "sg:phone":"+1 714 799 3232",
    "sg:postcode":"92683",
    "sg:province":"CA",
    "sg:tags":[
        "carrier",
        "radiotelephone",
        "communications-common"
    ],
    "wof:name":"Sun Wireless",
    "wof:placetype":"venue"
},
  "geometry": {"coordinates":[-117.989301,33.738325],"type":"Point"}
}