{
  "type": "Feature",
  "properties": {
    "iso:country":"US",
    "sg:address":"290 E Easy St",
    "sg:city":"Simi Valley",
    "sg:classifiers":[
        {
            "category":"Manufacturing",
            "subcategory":"Retail Goods",
            "type":"Manufacturing & Wholesale Goods"
        }
    ],
    "sg:phone":"+1 805 527 7511",
    "sg:postcode":"93065",
    "sg:province":"CA",
    "sg:tags":[
        "carbon",
        "mfg",
        "ribbon",
        "general"
    ],
    "wof:name":"Imaging Manufacturers Resource",
    "wof:placetype":"venue"
},
  "geometry": {"coordinates":[-118.79610099999999,34.278129],"type":"Point"}
}