{
  "type": "Feature",
  "properties": {
    "addr:full":"1421 E Chapman Ave Orange CA 92780",
    "addr:housenumber":"1421",
    "addr:postcode":"92780",
    "addr:street":"E Chapman Ave",
    "iso:country":"US",
    "sg:address":"1421 E Chapman Ave",
    "sg:city":"Orange",
    "sg:classifiers":[
        {
            "category":"Professional",
            "subcategory":"Lawyer & Legal Services",
            "type":"Services"
        }
    ],
    "sg:phone":"+1 714 769 1200",
    "sg:postcode":"92780",
    "sg:province":"CA",
    "sg:website":"www.edfloreslaw.com",
    "wof:name":"The Law Offices of Edward R. Flores",
    "wof:placetype":"venue"
},
  "geometry": {"coordinates":[-117.83846200000001,33.788145],"type":"Point"}
}