{
  "type": "Feature",
  "properties": {
    "iso:country":"US",
    "sg:address":"1039 E Santa Anita Ave",
    "sg:city":"Burbank",
    "sg:classifiers":[
        {
            "category":"Restaurant",
            "type":"Food & Drink"
        }
    ],
    "sg:phone":"+1 818 841 1800",
    "sg:postcode":"91501",
    "sg:province":"CA",
    "sg:tags":[
        "pizza"
    ],
    "wof:name":"Chebishian Mkrtich",
    "wof:placetype":"venue"
},
  "geometry": {"coordinates":[-118.293999,34.188499],"type":"Point"}
}