{
  "type": "Feature",
  "properties": {
    "addr:full":"8222 Yarmouth Ave Reseda CA 91335",
    "addr:housenumber":"8222",
    "addr:postcode":"91335",
    "addr:street":"Yarmouth Ave",
    "iso:country":"US",
    "sg:address":"8222 Yarmouth Ave",
    "sg:city":"Reseda",
    "sg:classifiers":[
        {
            "category":"Building & Trades",
            "subcategory":"Landscaping Services",
            "type":"Services"
        }
    ],
    "sg:phone":"+1 818 705 7427",
    "sg:postcode":"91335",
    "sg:province":"CA",
    "wof:name":"Professional Tree Service Inc",
    "wof:placetype":"venue"
},
  "geometry": {"coordinates":[-118.519595,34.220453],"type":"Point"}
}