{
  "type": "Feature",
  "properties": {
    "iso:country":"US",
    "sg:address":"12900 Crossroads Pkwy S",
    "sg:city":"City Of Industry",
    "sg:classifiers":[
        {
            "category":"Manufacturing",
            "subcategory":"Printing",
            "type":"Manufacturing & Wholesale Goods"
        }
    ],
    "sg:phone":"+1 562 908 9990",
    "sg:postcode":"91746",
    "sg:province":"CA",
    "sg:tags":[
        "publisher",
        "guide"
    ],
    "sg:website":"www.ndcpub.com",
    "wof:name":"Yellow Book USA",
    "wof:placetype":"venue"
},
  "geometry": {"coordinates":[-118.023394,34.028707],"type":"Point"}
}