{
  "type": "Feature",
  "properties": {
    "iso:country":"US",
    "sg:address":"100 Inland Center Dr",
    "sg:city":"San Bernardino",
    "sg:classifiers":[
        {
            "category":"Professional",
            "subcategory":"Accounting & Tax Preparation",
            "type":"Services"
        }
    ],
    "sg:phone":"+1 909 885 2825",
    "sg:postcode":"92408",
    "sg:province":"CA",
    "sg:tags":[
        "return",
        "filing"
    ],
    "wof:name":"H & R Block Tax Svc",
    "wof:placetype":"venue"
},
  "geometry": {"coordinates":[-117.295895,34.090382],"type":"Point"}
}