{
  "type": "Feature",
  "properties": {
    "addr:full":"1036 West Capitol Ave. West Sacramento CA 95691",
    "addr:housenumber":"1036",
    "addr:postcode":"95691",
    "addr:street":"West Capitol Ave.",
    "iso:country":"US",
    "sg:address":"1036 West Capitol Ave.",
    "sg:city":"West Sacramento",
    "sg:classifiers":[
        {
            "category":"Restaurant",
            "type":"Food & Drink"
        }
    ],
    "sg:postcode":"95691",
    "sg:province":"CA",
    "sg:tags":[
        "traditional",
        "american"
    ],
    "wof:name":"Blue Blitz",
    "wof:placetype":"venue"
},
  "geometry": {"coordinates":[-121.521609,38.581712],"type":"Point"}
}