{
  "type": "Feature",
  "properties": {
    "iso:country":"US",
    "sg:address":"6501 Lowry St",
    "sg:city":"Bakersfield",
    "sg:classifiers":[
        {
            "category":"Building & Trades",
            "subcategory":"Landscaping Services",
            "type":"Services"
        }
    ],
    "sg:phone":"+1 661 834 7831",
    "sg:postcode":"93307",
    "sg:province":"CA",
    "wof:name":"JC S Lawncare",
    "wof:placetype":"venue"
},
  "geometry": {"coordinates":[-119.009691,35.294585],"type":"Point"}
}