{
  "type": "Feature",
  "properties": {
    "addr:full":"6600 Topanga Canyon Blvd #9034 Canoga Park CA 91303",
    "addr:housenumber":"6600",
    "addr:postcode":"91303",
    "addr:street":"Topanga Canyon Blvd # 9034",
    "iso:country":"US",
    "sg:address":"6600 Topanga Canyon Blvd #9034",
    "sg:city":"Canoga Park",
    "sg:classifiers":[
        {
            "category":"Ice Cream",
            "type":"Food & Drink"
        }
    ],
    "sg:phone":"+1 818 703 0927",
    "sg:postcode":"91303",
    "sg:province":"CA",
    "sg:tags":[
        "frozen",
        "yogurt"
    ],
    "sg:website":"www.pinkberry.com",
    "wof:name":"Pinkberry",
    "wof:placetype":"venue"
},
  "geometry": {"coordinates":[-118.60582700000001,34.189897],"type":"Point"}
}