{
  "type": "Feature",
  "properties": {
    "iso:country":"US",
    "sg:address":"1421 Wilshire Blvd",
    "sg:city":"Santa Monica",
    "sg:classifiers":[
        {
            "category":"Retail",
            "subcategory":"Laundry & Dry Cleaning",
            "type":"Services"
        }
    ],
    "sg:phone":"+1 310 395 7848",
    "sg:postcode":"90403",
    "sg:province":"CA",
    "sg:tags":[
        "cleaners"
    ],
    "wof:name":"Cleaning Land",
    "wof:placetype":"venue"
},
  "geometry": {"coordinates":[-118.48858,34.027071],"type":"Point"}
}