{
  "type": "Feature",
  "properties": {
    "iso:country":"US",
    "sg:address":"3345 S Bristol St",
    "sg:city":"Santa Ana",
    "sg:classifiers":[
        {
            "category":"Coffee & Tea",
            "type":"Food & Drink"
        }
    ],
    "sg:menulink":"http://www.allmenus.com/ca/anaheim-santa-ana-garden-grove/116632-starbucks-coffee/menu/",
    "sg:phone":"+1 714 437 7323",
    "sg:postcode":"92704",
    "sg:province":"CA",
    "sg:tags":[
        "american"
    ],
    "wof:name":"Starbucks Coffee",
    "wof:placetype":"venue"
},
  "geometry": {"coordinates":[-117.88542700000001,33.701988],"type":"Point"}
}