{
  "type": "Feature",
  "properties": {
    "addr:full":"2725 Howard Ct Burbank CA 91504",
    "addr:housenumber":"2725",
    "addr:postcode":"91504",
    "addr:street":"Howard Ct",
    "iso:country":"US",
    "sg:address":"2725 Howard Ct",
    "sg:city":"Burbank",
    "sg:classifiers":[
        {
            "category":"Professional",
            "subcategory":"Lawyer & Legal Services",
            "type":"Services"
        }
    ],
    "sg:phone":"+1 818 972 9230",
    "sg:postcode":"91504",
    "sg:province":"CA",
    "wof:name":"Blas Manuel U Attorney At Law",
    "wof:placetype":"venue"
},
  "geometry": {"coordinates":[-118.31910999999999,34.209713],"type":"Point"}
}