{
  "type": "Feature",
  "properties": {
    "iso:country":"US",
    "sg:address":"9616 Valley Blvd",
    "sg:city":"Rosemead",
    "sg:classifiers":[
        {
            "category":"Manufacturing",
            "subcategory":"Tools & Machinery",
            "type":"Manufacturing & Wholesale Goods"
        }
    ],
    "sg:phone":"+1 626 444 3867",
    "sg:postcode":"91770",
    "sg:province":"CA",
    "sg:tags":[
        "machine",
        "shop"
    ],
    "wof:name":"Ace Specialty Mfg Co",
    "wof:placetype":"venue"
},
  "geometry": {"coordinates":[-118.058503,34.081231],"type":"Point"}
}