{
  "type": "Feature",
  "properties": {
    "addr:full":"2225 Mission St San Francisco CA 94110",
    "addr:housenumber":"2225",
    "addr:postcode":"94110",
    "addr:street":"Mission St",
    "iso:country":"US",
    "sg:address":"2225 Mission St",
    "sg:city":"San Francisco",
    "sg:classifiers":[
        {
            "category":"Home & Garden",
            "subcategory":"Furniture",
            "type":"Retail Goods"
        }
    ],
    "sg:phone":"+1 415 285 3555",
    "sg:postcode":"94110",
    "sg:province":"CA",
    "wof:name":"Today Furniture",
    "wof:placetype":"venue"
},
  "geometry": {"coordinates":[-122.419161,37.760632],"type":"Point"}
}