{
  "type": "Feature",
  "properties": {
    "iso:country":"US",
    "sg:address":"6435 N Hazel Ave",
    "sg:city":"Fresno",
    "sg:classifiers":[
        {
            "category":"Social Services",
            "subcategory":"Child Care",
            "type":"Services"
        }
    ],
    "sg:phone":"+1 559 439 5514",
    "sg:postcode":"93711",
    "sg:province":"CA",
    "wof:name":"Dougherty Daycare",
    "wof:placetype":"venue"
},
  "geometry": {"coordinates":[-119.85042900000001,36.830218],"type":"Point"}
}