{
  "type": "Feature",
  "properties": {
    "addr:full":"9440 Wheatlands Ct Santee CA 92071",
    "addr:housenumber":"9440",
    "addr:postcode":"92071",
    "addr:street":"Wheatlands Ct",
    "iso:country":"US",
    "sg:address":"9440 Wheatlands Ct",
    "sg:city":"Santee",
    "sg:classifiers":[
        {
            "category":"Manufacturing",
            "subcategory":"Signs",
            "type":"Manufacturing & Wholesale Goods"
        }
    ],
    "sg:phone":"+1 619 448 8628",
    "sg:postcode":"92071",
    "sg:province":"CA",
    "sg:tags":[
        "mfg"
    ],
    "wof:name":"Raisedlettercom",
    "wof:placetype":"venue"
},
  "geometry": {"coordinates":[-116.961744,32.846866],"type":"Point"}
}