{
  "type": "Feature",
  "properties": {
    "addr:full":"8150 Beverly Blvd Los Angeles CA 90048",
    "addr:housenumber":"8150",
    "addr:postcode":"90048",
    "addr:street":"Beverly Blvd",
    "iso:country":"US",
    "sg:address":"8150 Beverly Blvd",
    "sg:city":"Los Angeles",
    "sg:classifiers":[
        {
            "category":"Professional",
            "subcategory":"Management & Consulting",
            "type":"Services"
        }
    ],
    "sg:phone":"+1 323 658 1051",
    "sg:postcode":"90048",
    "sg:province":"CA",
    "sg:tags":[
        "marketing",
        "consultant"
    ],
    "wof:name":"MMC Inc",
    "wof:placetype":"venue"
},
  "geometry": {"coordinates":[-118.367954,34.076076],"type":"Point"}
}