{
  "type": "Feature",
  "properties": {
    "iso:country":"US",
    "sg:address":"1710 Freedom Blvd",
    "sg:city":"Freedom",
    "sg:classifiers":[
        {
            "category":"Shopping",
            "subcategory":"Hobbies, Toys, & Games",
            "type":"Retail Goods"
        },
        {
            "category":"Shopping",
            "subcategory":"Gifts & Souvenirs",
            "type":"Retail Goods"
        }
    ],
    "sg:phone":"+1 831 768 0245",
    "sg:postcode":"95019",
    "sg:province":"CA",
    "sg:tags":[
        "shop",
        "craft",
        "supply"
    ],
    "wof:name":"Susan's Lace",
    "wof:placetype":"venue"
},
  "geometry": {"coordinates":[-121.771968,36.933904],"type":"Point"}
}