{
  "type": "Feature",
  "properties": {
    "iso:country":"US",
    "sg:address":"980 9th St",
    "sg:city":"Sacramento",
    "sg:classifiers":[
        {
            "category":"Professional",
            "subcategory":"Advertising",
            "type":"Services"
        },
        {
            "category":"Communications",
            "subcategory":"Newspaper",
            "type":"Services"
        }
    ],
    "sg:phone":"+1 866 208 8189",
    "sg:postcode":"95814",
    "sg:province":"CA",
    "sg:tags":[
        "marketing"
    ],
    "sg:website":"www.salestrainingcalifornia.com",
    "wof:name":"California Sales Training",
    "wof:placetype":"venue"
},
  "geometry": {"coordinates":[-121.49502200000001,38.581145],"type":"Point"}
}