{
  "type": "Feature",
  "properties": {
    "addr:full":"5225 Fiore Ter San Diego CA 92122",
    "addr:housenumber":"5225",
    "addr:postcode":"92122",
    "addr:street":"Fiore Ter",
    "iso:country":"US",
    "sg:address":"5225 Fiore Ter",
    "sg:city":"San Diego",
    "sg:classifiers":[
        {
            "category":"Professional",
            "type":"Services"
        }
    ],
    "sg:phone":"+1 858 587 8808",
    "sg:postcode":"92122",
    "sg:province":"CA",
    "wof:name":"Essys Collection",
    "wof:placetype":"venue"
},
  "geometry": {"coordinates":[-117.203238,32.870398],"type":"Point"}
}