{
  "type": "Feature",
  "properties": {
    "iso:country":"US",
    "sg:address":"823 Random Ln",
    "sg:city":"Duarte",
    "sg:classifiers":[
        {
            "category":"Shopping",
            "subcategory":"Clothing, Apparel, & Fashions",
            "type":"Retail Goods"
        }
    ],
    "sg:phone":"+1 626 358 9799",
    "sg:postcode":"91010",
    "sg:province":"CA",
    "wof:name":"Ann Lizzie Reproduction Clthr",
    "wof:placetype":"venue"
},
  "geometry": {"coordinates":[-117.957375,34.141392],"type":"Point"}
}