{
  "type": "Feature",
  "properties": {
    "iso:country":"US",
    "sg:address":"3034 Hillegass Ave",
    "sg:city":"Berkeley",
    "sg:classifiers":[
        {
            "category":"Insurance",
            "subcategory":"Insurance Agent",
            "type":"Services"
        }
    ],
    "sg:phone":"+1 510 849 1483",
    "sg:postcode":"94705",
    "sg:province":"CA",
    "wof:name":"Reidenbach Insurance",
    "wof:placetype":"venue"
},
  "geometry": {"coordinates":[-122.25495600000001,37.854397],"type":"Point"}
}