{
  "type": "Feature",
  "properties": {
    "iso:country":"US",
    "sg:address":"631 W Main St",
    "sg:city":"El Centro",
    "sg:classifiers":[
        {
            "category":"Organizations",
            "subcategory":"Community Association",
            "type":"Services"
        }
    ],
    "sg:phone":"+1 760 352 1050",
    "sg:postcode":"92243",
    "sg:province":"CA",
    "sg:tags":[
        "fraternal"
    ],
    "wof:name":"Elks Lodge",
    "wof:placetype":"venue"
},
  "geometry": {"coordinates":[-115.558489,32.792761],"type":"Point"}
}