{
  "type": "Feature",
  "properties": {
    "addr:full":"930 West Washington St Suite #2 San Diego CA 92103",
    "addr:housenumber":"930",
    "addr:postcode":"92103",
    "addr:street":"West Washington St Suite # 2",
    "iso:country":"US",
    "sg:address":"930 West Washington St Suite #2",
    "sg:city":"San Diego",
    "sg:classifiers":[
        {
            "category":"Shopping",
            "subcategory":"Beauty & Cosmetics",
            "type":"Retail Goods"
        },
        {
            "category":"Food & Beverages",
            "subcategory":"Specialty",
            "type":"Retail Goods"
        }
    ],
    "sg:phone":"+1 619 296 4047",
    "sg:postcode":"92103",
    "sg:province":"CA",
    "sg:tags":[
        "supply"
    ],
    "wof:name":"Casa Della Bella Italia",
    "wof:placetype":"venue"
},
  "geometry": {"coordinates":[-117.172,32.750112],"type":"Point"}
}