{
  "type": "Feature",
  "properties": {
    "iso:country":"US",
    "sg:address":"595 Avon Way",
    "sg:city":"Los Altos",
    "sg:classifiers":[
        {
            "category":"Health Services",
            "subcategory":"Doctor",
            "type":"Services"
        }
    ],
    "sg:phone":"+1 408 730 4272",
    "sg:postcode":"94024",
    "sg:province":"CA",
    "sg:tags":[
        "physician",
        "surgeon"
    ],
    "sg:website":"www.neurologists.com",
    "wof:name":"J Ronald Hess MD",
    "wof:placetype":"venue"
},
  "geometry": {"coordinates":[-122.100528,37.367084],"type":"Point"}
}