{
  "type": "Feature",
  "properties": {
    "addr:full":"995 Bay Blvd Chula Vista CA 91911",
    "addr:housenumber":"995",
    "addr:postcode":"91911",
    "addr:street":"Bay Blvd",
    "iso:country":"US",
    "sg:address":"995 Bay Blvd",
    "sg:city":"Chula Vista",
    "sg:classifiers":[
        {
            "category":"Manufacturing",
            "subcategory":"Retail Goods",
            "type":"Manufacturing & Wholesale Goods"
        }
    ],
    "sg:phone":"+1 619 628 8516",
    "sg:postcode":"91911",
    "sg:province":"CA",
    "sg:tags":[
        "manufacturer"
    ],
    "wof:name":"Noral Enterprises Inc",
    "wof:placetype":"venue"
},
  "geometry": {"coordinates":[-117.091871,32.61317],"type":"Point"}
}