{
  "type": "Feature",
  "properties": {
    "addr:full":"2654 Jamacha Rd El Cajon CA 92019",
    "addr:housenumber":"2654",
    "addr:postcode":"92019",
    "addr:street":"Jamacha Rd",
    "iso:country":"US",
    "sg:address":"2654 Jamacha Rd",
    "sg:city":"El Cajon",
    "sg:classifiers":[
        {
            "category":"Food & Beverages",
            "subcategory":"Specialty",
            "type":"Retail Goods"
        }
    ],
    "sg:phone":"+1 619 670 7476",
    "sg:postcode":"92019",
    "sg:province":"CA",
    "sg:tags":[
        "tea",
        "coffee"
    ],
    "wof:name":"Coffee Grounds",
    "wof:placetype":"venue"
},
  "geometry": {"coordinates":[-116.93059700000001,32.744502],"type":"Point"}
}