{
  "type": "Feature",
  "properties": {
    "addr:full":"1550 W Adams Blvd Los Angeles CA 90007",
    "addr:housenumber":"1550",
    "addr:postcode":"90007",
    "addr:street":"W Adams Blvd",
    "iso:country":"US",
    "sg:address":"1550 W Adams Blvd",
    "sg:city":"Los Angeles",
    "sg:classifiers":[
        {
            "category":"Food & Beverages",
            "subcategory":"Groceries & Convenience Stores",
            "type":"Retail Goods"
        }
    ],
    "sg:phone":"+1 323 735 5344",
    "sg:postcode":"90007",
    "sg:province":"CA",
    "sg:tags":[
        "grocer"
    ],
    "wof:name":"Adlong Groceries & Produce",
    "wof:placetype":"venue"
},
  "geometry": {"coordinates":[-118.295998,34.032902],"type":"Point"}
}