{
  "type": "Feature",
  "properties": {
    "addr:full":"358 Hillside Ave Piedmont CA 94611",
    "addr:housenumber":"358",
    "addr:postcode":"94611",
    "addr:street":"Hillside Ave",
    "iso:country":"US",
    "sg:address":"358 Hillside Ave",
    "sg:city":"Piedmont",
    "sg:classifiers":[
        {
            "category":"Shopping",
            "subcategory":"Musical Instruments",
            "type":"Retail Goods"
        }
    ],
    "sg:phone":"+1 510 531 3190",
    "sg:postcode":"94611",
    "sg:province":"CA",
    "sg:tags":[
        "guitar",
        "amplifier"
    ],
    "wof:name":"Kindermusik",
    "wof:placetype":"venue"
},
  "geometry": {"coordinates":[-122.23475500000001,37.823672],"type":"Point"}
}