{
  "type": "Feature",
  "properties": {
    "addr:full":"2807 24th St San Francisco CA 94110",
    "addr:housenumber":"2807",
    "addr:postcode":"94110",
    "addr:street":"24Th St",
    "iso:country":"US",
    "sg:address":"2807 24th St",
    "sg:city":"San Francisco",
    "sg:classifiers":[
        {
            "category":"Manufacturing",
            "subcategory":"Printing",
            "type":"Manufacturing & Wholesale Goods"
        }
    ],
    "sg:phone":"+1 415 241 7270",
    "sg:postcode":"94110",
    "sg:province":"CA",
    "sg:tags":[
        "printer"
    ],
    "wof:name":"Madrigal Printing",
    "wof:placetype":"venue"
},
  "geometry": {"coordinates":[-122.409031,37.752728],"type":"Point"}
}