{
  "type": "Feature",
  "properties": {
    "iso:country":"US",
    "sg:address":"3925 2nd Ave",
    "sg:city":"Los Angeles",
    "sg:classifiers":[
        {
            "category":"Building & Trades",
            "subcategory":"Construction",
            "type":"Services"
        }
    ],
    "sg:phone":"+1 213 994 1288",
    "sg:postcode":"90008",
    "sg:province":"CA",
    "sg:tags":[
        "company",
        "demolition",
        "general"
    ],
    "wof:name":"Jarah Construction Co",
    "wof:placetype":"venue"
},
  "geometry": {"coordinates":[-118.319357,34.011264],"type":"Point"}
}