{
  "type": "Feature",
  "properties": {
    "iso:country":"US",
    "sg:address":"6009 Madison Avenue",
    "sg:city":"Carmichael",
    "sg:classifiers":[
        {
            "category":"Building & Trades",
            "subcategory":"Locksmith",
            "type":"Services"
        }
    ],
    "sg:phone":"+1 916 331 3074",
    "sg:postcode":"95608",
    "sg:province":"CA",
    "sg:tags":[
        "key"
    ],
    "wof:name":"Newberry's Mobile Locksmith",
    "wof:placetype":"venue"
},
  "geometry": {"coordinates":[-121.323609,38.661684],"type":"Point"}
}