{
  "type": "Feature",
  "properties": {
    "iso:country":"US",
    "sg:address":"2424 Sepulveda Blvd Ste A",
    "sg:city":"Torrance",
    "sg:classifiers":[
        {
            "category":"Deli",
            "type":"Food & Drink"
        }
    ],
    "sg:phone":"+1 310 891 1229",
    "sg:postcode":"90501",
    "sg:province":"CA",
    "sg:website":"www.thenewyorkdeli.com/home",
    "wof:name":"The New York Deli",
    "wof:placetype":"venue"
},
  "geometry": {"coordinates":[-118.326373,33.821027],"type":"Point"}
}