{
  "type": "Feature",
  "properties": {
    "iso:country":"US",
    "sg:address":"6611 Folsom Auburn Rd M",
    "sg:city":"Folsom",
    "sg:classifiers":[
        {
            "category":"Health Services",
            "subcategory":"Dentist",
            "type":"Services"
        }
    ],
    "sg:phone":"+1 916 988 6684",
    "sg:postcode":"95630",
    "sg:province":"CA",
    "sg:tags":[
        "dental",
        "clinic"
    ],
    "wof:name":"Office Of Katie Demyer Dds",
    "wof:placetype":"venue"
},
  "geometry": {"coordinates":[-121.178994,38.684519],"type":"Point"}
}