{
  "type": "Feature",
  "properties": {
    "addr:full":"101 E Washington St Petaluma CA 94952",
    "addr:housenumber":"101",
    "addr:postcode":"94952",
    "addr:street":"E Washington St",
    "iso:country":"US",
    "sg:address":"101 E Washington St",
    "sg:city":"Petaluma",
    "sg:classifiers":[
        {
            "category":"Home & Garden",
            "subcategory":"Building Materials",
            "type":"Retail Goods"
        }
    ],
    "sg:phone":"+1 707 765 8570",
    "sg:postcode":"94952",
    "sg:province":"CA",
    "wof:name":"Shamrock Materials Inc",
    "wof:placetype":"venue"
},
  "geometry": {"coordinates":[-122.63888799999999,38.236416],"type":"Point"}
}