{
  "type": "Feature",
  "properties": {
    "addr:full":"16333 Ave del Sol Sonora CA 95370",
    "addr:housenumber":"16333",
    "addr:postcode":"95370",
    "addr:street":"Ave Del Sol",
    "iso:country":"US",
    "sg:address":"16333 Ave del Sol",
    "sg:city":"Sonora",
    "sg:classifiers":[
        {
            "category":"Retail",
            "subcategory":"Portrait Studio",
            "type":"Services"
        }
    ],
    "sg:phone":"+1 209 532 0027",
    "sg:postcode":"95370",
    "sg:province":"CA",
    "sg:tags":[
        "photographer"
    ],
    "wof:name":"Diane Conn Photography",
    "wof:placetype":"venue"
},
  "geometry": {"coordinates":[-120.311969,37.989525],"type":"Point"}
}