{
  "type": "Feature",
  "properties": {
    "iso:country":"US",
    "sg:address":"217 7th St",
    "sg:city":"Hollister",
    "sg:classifiers":[
        {
            "category":"Home & Garden",
            "subcategory":"Building Materials",
            "type":"Retail Goods"
        }
    ],
    "sg:phone":"+1 831 637 5767",
    "sg:postcode":"95023",
    "sg:province":"CA",
    "sg:tags":[
        "paint"
    ],
    "wof:name":"Mc Kinnon Lumber Co",
    "wof:placetype":"venue"
},
  "geometry": {"coordinates":[-121.40150300000001,36.849281],"type":"Point"}
}