{
  "type": "Feature",
  "properties": {
    "addr:full":"521 Cortland Ave San Francisco CA 94110",
    "addr:housenumber":"521",
    "addr:postcode":"94110",
    "addr:street":"Cortland Ave",
    "iso:country":"US",
    "sg:address":"521 Cortland Ave",
    "sg:city":"San Francisco",
    "sg:classifiers":[
        {
            "category":"Personal",
            "subcategory":"Beauty Salon",
            "type":"Services"
        }
    ],
    "sg:phone":"+1 415 285 4599",
    "sg:postcode":"94110",
    "sg:province":"CA",
    "wof:name":"Salon Last Resort",
    "wof:placetype":"venue"
},
  "geometry": {"coordinates":[-122.41598999999999,37.739089],"type":"Point"}
}