{
  "type": "Feature",
  "properties": {
    "iso:country":"US",
    "sg:address":"2452 Merced Ave",
    "sg:city":"South El Monte",
    "sg:classifiers":[
        {
            "category":"Professional",
            "subcategory":"Business Services",
            "type":"Services"
        }
    ],
    "sg:phone":"+1 626 442 2090",
    "sg:postcode":"91733",
    "sg:province":"CA",
    "sg:tags":[
        "household",
        "appliance"
    ],
    "wof:name":"N G Sewing Inc",
    "wof:placetype":"venue"
},
  "geometry": {"coordinates":[-118.051207,34.058147],"type":"Point"}
}