{
  "type": "Feature",
  "properties": {
    "iso:country":"US",
    "sg:address":"1155 S Main St",
    "sg:city":"Lakeport",
    "sg:classifiers":[
        {
            "category":"Food & Beverages",
            "subcategory":"Groceries & Convenience Stores",
            "type":"Retail Goods"
        }
    ],
    "sg:phone":"+1 707 263 0316",
    "sg:postcode":"95453",
    "sg:province":"CA",
    "sg:tags":[
        "grocer"
    ],
    "wof:name":"Lakeport Grocery Outlet",
    "wof:placetype":"venue"
},
  "geometry": {"coordinates":[-122.91577599999999,39.034498],"type":"Point"}
}