{
  "type": "Feature",
  "properties": {
    "addr:full":"8873 Villa La Jolla Dr La Jolla CA 92037",
    "addr:housenumber":"8873",
    "addr:postcode":"92037",
    "addr:street":"Villa La Jolla Dr",
    "iso:country":"US",
    "sg:address":"8873 Villa La Jolla Dr",
    "sg:city":"La Jolla",
    "sg:classifiers":[
        {
            "category":"Restaurant",
            "type":"Food & Drink"
        }
    ],
    "sg:menulink":"http://www.allmenus.com/ca/san-diego/35227-bjs-restaurant--brewhouse/menu/",
    "sg:phone":"+1 858 455 0662",
    "sg:postcode":"92037",
    "sg:province":"CA",
    "sg:tags":[
        "new",
        "american",
        "pizza"
    ],
    "wof:name":"BJ's Restaurant & Brewhouse",
    "wof:placetype":"venue"
},
  "geometry": {"coordinates":[-117.23376500000001,32.869644],"type":"Point"}
}