{
  "type": "Feature",
  "properties": {
    "iso:country":"US",
    "sg:address":"1191 W Tennyson Rd",
    "sg:city":"Hayward",
    "sg:classifiers":[
        {
            "category":"Health Services",
            "subcategory":"Doctor",
            "type":"Services"
        }
    ],
    "sg:phone":"+1 510 732 1566",
    "sg:postcode":"94544",
    "sg:province":"CA",
    "sg:tags":[
        "podiatrist"
    ],
    "wof:name":"Waller Marilyn DPM",
    "wof:placetype":"venue"
},
  "geometry": {"coordinates":[-122.078003,37.631401],"type":"Point"}
}