{
  "type": "Feature",
  "properties": {
    "iso:country":"US",
    "sg:address":"1172 S Main St",
    "sg:city":"Salinas",
    "sg:classifiers":[
        {
            "category":"Building & Trades",
            "subcategory":"Equipment Rental",
            "type":"Services"
        }
    ],
    "sg:phone":"+1 831 809 8009",
    "sg:postcode":"93901",
    "sg:province":"CA",
    "sg:tags":[
        "yard",
        "leasing",
        "store"
    ],
    "wof:name":"Flagship Leasing",
    "wof:placetype":"venue"
},
  "geometry": {"coordinates":[-121.65919700000001,36.658343],"type":"Point"}
}