{
  "type": "Feature",
  "properties": {
    "iso:country":"US",
    "sg:address":"7698 Eucalyptus Ave",
    "sg:city":"Chino",
    "sg:classifiers":[
        {
            "category":"Travel",
            "subcategory":"Travel Agent",
            "type":"Entertainment"
        }
    ],
    "sg:phone":"+1 909 393 2936",
    "sg:postcode":"91762",
    "sg:province":"CA",
    "sg:tags":[
        "operator",
        "tour",
        "tours",
        "promoter"
    ],
    "wof:name":"Amy's Farm Tours",
    "wof:placetype":"venue"
},
  "geometry": {"coordinates":[-117.64051000000001,33.99037],"type":"Point"}
}