{
  "type": "Feature",
  "properties": {
    "addr:full":"5019 Golden West Ave Temple City CA 91780",
    "addr:housenumber":"5019",
    "addr:postcode":"91780",
    "addr:street":"Golden West Ave",
    "iso:country":"US",
    "sg:address":"5019 Golden West Ave",
    "sg:city":"Temple City",
    "sg:classifiers":[
        {
            "category":"Professional",
            "subcategory":"Art Services",
            "type":"Services"
        }
    ],
    "sg:phone":"+1 626 286 6656",
    "sg:postcode":"91780",
    "sg:province":"CA",
    "sg:tags":[
        "arts",
        "graphic",
        "design",
        "related"
    ],
    "wof:name":"Komai Designs",
    "wof:placetype":"venue"
},
  "geometry": {"coordinates":[-118.054474,34.094086],"type":"Point"}
}