{
  "type": "Feature",
  "properties": {
    "addr:full":"1975 Pomona Ave Costa Mesa CA 92627",
    "addr:housenumber":"1975",
    "addr:postcode":"92627",
    "addr:street":"Pomona Ave",
    "iso:country":"US",
    "sg:address":"1975 Pomona Ave",
    "sg:city":"Costa Mesa",
    "sg:classifiers":[
        {
            "category":"Wholesale",
            "subcategory":"Machinery & Supplies",
            "type":"Manufacturing & Wholesale Goods"
        }
    ],
    "sg:phone":"+1 949 631 6012",
    "sg:postcode":"92627",
    "sg:province":"CA",
    "sg:tags":[
        "printer",
        "cartridge"
    ],
    "sg:website":"www.inks2go.com",
    "wof:name":"INKS2GO.COM",
    "wof:placetype":"venue"
},
  "geometry": {"coordinates":[-117.92774900000001,33.645311],"type":"Point"}
}