{
  "type": "Feature",
  "properties": {
    "iso:country":"US",
    "sg:address":"1500 S Archibald Ave",
    "sg:city":"Ontario",
    "sg:classifiers":[
        {
            "category":"Freight",
            "type":"Transportation"
        }
    ],
    "sg:phone":"+1 909 605 2029",
    "sg:postcode":"91761",
    "sg:province":"CA",
    "sg:tags":[
        "nonscheduled",
        "arrangement",
        "air"
    ],
    "wof:name":"Airborne",
    "wof:placetype":"venue"
},
  "geometry": {"coordinates":[-117.59335400000001,34.048057],"type":"Point"}
}