{
  "type": "Feature",
  "properties": {
    "iso:country":"US",
    "sg:address":"41 Auto Center Dr",
    "sg:city":"Foothill Ranch",
    "sg:classifiers":[
        {
            "category":"Retail",
            "subcategory":"Laundry & Dry Cleaning",
            "type":"Services"
        }
    ],
    "sg:phone":"+1 949 770 9999",
    "sg:postcode":"92610",
    "sg:province":"CA",
    "wof:name":"Champ Cleaners",
    "wof:placetype":"venue"
},
  "geometry": {"coordinates":[-117.66186399999999,33.675893],"type":"Point"}
}