{
  "type": "Feature",
  "properties": {
    "addr:full":"RE/MAX Star Properties 520 So El Camino Real Ste 100 San Mateo CA 94402",
    "addr:housenumber":"520",
    "addr:postcode":"94402",
    "addr:street":"So El Camino Real Ste 100",
    "iso:country":"US",
    "sg:address":"RE/MAX Star Properties 520 So El Camino Real Ste 100",
    "sg:city":"San Mateo",
    "sg:classifiers":[
        {
            "category":"Real Estate",
            "subcategory":"Real Estate Services",
            "type":"Services"
        }
    ],
    "sg:phone":"+1 650 888 9268",
    "sg:postcode":"94402",
    "sg:province":"CA",
    "sg:website":"www.SanMateoRealEstateBlog.com",
    "wof:name":"Vicki Moore",
    "wof:placetype":"venue"
},
  "geometry": {"coordinates":[-122.324382,37.561091],"type":"Point"}
}