{
  "type": "Feature",
  "properties": {
    "addr:full":"4456 Torrey Pines Dr Chino Hills CA 91709",
    "addr:housenumber":"4456",
    "addr:postcode":"91709",
    "addr:street":"Torrey Pines Dr",
    "iso:country":"US",
    "sg:address":"4456 Torrey Pines Dr",
    "sg:city":"Chino Hills",
    "sg:classifiers":[
        {
            "category":"Shopping",
            "subcategory":"Clothing, Apparel, & Fashions",
            "type":"Retail Goods"
        }
    ],
    "sg:phone":"+1 951 295 7755",
    "sg:postcode":"91709",
    "sg:province":"CA",
    "wof:name":"Adict",
    "wof:placetype":"venue"
},
  "geometry": {"coordinates":[-117.70638,33.960512],"type":"Point"}
}