{
  "type": "Feature",
  "properties": {
    "addr:full":"835 N Barlow Ln Bishop CA 93514",
    "addr:housenumber":"835",
    "addr:postcode":"93514",
    "addr:street":"N Barlow Ln",
    "iso:country":"US",
    "sg:address":"835 N Barlow Ln",
    "sg:city":"Bishop",
    "sg:classifiers":[
        {
            "category":"Autos & Motor Vehicles",
            "subcategory":"Auto Supplies",
            "type":"Retail Goods"
        }
    ],
    "sg:phone":"+1 760 872 8311",
    "sg:postcode":"93514",
    "sg:province":"CA",
    "sg:tags":[
        "tire"
    ],
    "wof:name":"Simpson's Discount Tire & Svc",
    "wof:placetype":"venue"
},
  "geometry": {"coordinates":[-118.423034,37.369189],"type":"Point"}
}