{
  "type": "Feature",
  "properties": {
    "addr:full":"20722 Main St Carson CA 90745",
    "addr:housenumber":"20722",
    "addr:postcode":"90745",
    "addr:street":"Main St",
    "iso:country":"US",
    "sg:address":"20722 Main St",
    "sg:city":"Carson",
    "sg:classifiers":[
        {
            "category":"Building & Trades",
            "subcategory":"Pest Control",
            "type":"Services"
        }
    ],
    "sg:phone":"+1 310 217 2323",
    "sg:postcode":"90745",
    "sg:province":"CA",
    "wof:name":"Mastercare Termite Control",
    "wof:placetype":"venue"
},
  "geometry": {"coordinates":[-118.275308,33.817929],"type":"Point"}
}