{
  "type": "Feature",
  "properties": {
    "addr:full":"1655 Broadway Chula Vista CA 91911",
    "addr:housenumber":"1655",
    "addr:postcode":"91911",
    "addr:street":"Broadway",
    "iso:country":"US",
    "sg:address":"1655 Broadway",
    "sg:city":"Chula Vista",
    "sg:classifiers":[
        {
            "category":"Professional",
            "subcategory":"Accounting & Tax Preparation",
            "type":"Services"
        }
    ],
    "sg:phone":"+1 619 585 3511",
    "sg:postcode":"91911",
    "sg:province":"CA",
    "sg:tags":[
        "return",
        "filing"
    ],
    "wof:name":"Liliana's Tax Svc",
    "wof:placetype":"venue"
},
  "geometry": {"coordinates":[-117.07620900000001,32.597408],"type":"Point"}
}