{
  "type": "Feature",
  "properties": {
    "addr:full":"1461 N Linden Ave Rialto CA 92376",
    "addr:housenumber":"1461",
    "addr:postcode":"92376",
    "addr:street":"N Linden Ave",
    "iso:country":"US",
    "sg:address":"1461 N Linden Ave",
    "sg:city":"Rialto",
    "sg:classifiers":[
        {
            "category":"Manufacturing",
            "subcategory":"Metals",
            "type":"Manufacturing & Wholesale Goods"
        }
    ],
    "sg:phone":"+1 951 809 8764",
    "sg:postcode":"92376",
    "sg:province":"CA",
    "sg:tags":[
        "metalwork",
        "sheet",
        "mfg"
    ],
    "wof:name":"Ludikrs Kustomz",
    "wof:placetype":"venue"
},
  "geometry": {"coordinates":[-117.40098500000001,34.126515],"type":"Point"}
}