{
  "type": "Feature",
  "properties": {
    "addr:full":"8130 2nd St Downey CA 90241",
    "addr:housenumber":"8130",
    "addr:postcode":"90241",
    "addr:street":"2Nd St",
    "iso:country":"US",
    "sg:address":"8130 2nd St",
    "sg:city":"Downey",
    "sg:classifiers":[
        {
            "category":"Professional",
            "subcategory":"Business Services",
            "type":"Services"
        }
    ],
    "sg:phone":"+1 562 862 9000",
    "sg:postcode":"90241",
    "sg:province":"CA",
    "sg:tags":[
        "paralegal"
    ],
    "wof:name":"Associated Services",
    "wof:placetype":"venue"
},
  "geometry": {"coordinates":[-118.134658,33.942173],"type":"Point"}
}