{
  "type": "Feature",
  "properties": {
    "iso:country":"US",
    "sg:address":"1505 Woodside Rd",
    "sg:city":"Redwood City",
    "sg:classifiers":[
        {
            "category":"Professional",
            "type":"Services"
        }
    ],
    "sg:phone":"+1 650 298 8510",
    "sg:postcode":"94061",
    "sg:province":"CA",
    "sg:tags":[
        "establishment"
    ],
    "wof:name":"Transparence Inc",
    "wof:placetype":"venue"
},
  "geometry": {"coordinates":[-122.228044,37.456026],"type":"Point"}
}