{
  "type": "Feature",
  "properties": {
    "addr:full":"15460 Morrison St Sherman Oaks CA 91403",
    "addr:housenumber":"15460",
    "addr:postcode":"91403",
    "addr:street":"Morrison St",
    "iso:country":"US",
    "sg:address":"15460 Morrison St",
    "sg:city":"Sherman Oaks",
    "sg:classifiers":[
        {
            "category":"Health Services",
            "subcategory":"Nursing And Care Facility",
            "type":"Services"
        }
    ],
    "sg:phone":"+1 818 501 7312",
    "sg:postcode":"91403",
    "sg:province":"CA",
    "wof:name":"Villa Aurora",
    "wof:placetype":"venue"
},
  "geometry": {"coordinates":[-118.470894,34.160188],"type":"Point"}
}