{
  "type": "Feature",
  "properties": {
    "addr:full":"1041 E Green St Ste 203 Pasadena CA 91106",
    "addr:housenumber":"1041",
    "addr:postcode":"91106",
    "addr:street":"E Green St Ste 203",
    "iso:country":"US",
    "sg:address":"1041 E Green St Ste 203",
    "sg:city":"Pasadena",
    "sg:classifiers":[
        {
            "category":"Professional",
            "subcategory":"Lawyer & Legal Services",
            "type":"Services"
        }
    ],
    "sg:phone":"+1 626 795 4540",
    "sg:postcode":"91106",
    "sg:province":"CA",
    "wof:name":"Broker Intermediaries",
    "wof:placetype":"venue"
},
  "geometry": {"coordinates":[-118.128688,34.144722],"type":"Point"}
}