{
  "type": "Feature",
  "properties": {
    "addr:full":"1754 N Main St Los Angeles CA 90031",
    "addr:housenumber":"1754",
    "addr:postcode":"90031",
    "addr:street":"N Main St",
    "iso:country":"US",
    "sg:address":"1754 N Main St",
    "sg:city":"Los Angeles",
    "sg:classifiers":[
        {
            "category":"Building & Trades",
            "subcategory":"Electrical",
            "type":"Services"
        }
    ],
    "sg:phone":"+1 323 441 1050",
    "sg:postcode":"90031",
    "sg:province":"CA",
    "sg:tags":[
        "electric",
        "contractor"
    ],
    "wof:name":"Independent Elec Contrs Assn",
    "wof:placetype":"venue"
},
  "geometry": {"coordinates":[-118.222875,34.06713],"type":"Point"}
}