{
  "type": "Feature",
  "properties": {
    "iso:country":"US",
    "sg:address":"72096 Dunham Way",
    "sg:city":"Thousand Palms",
    "sg:classifiers":[
        {
            "category":"Wholesale",
            "subcategory":"Machinery & Supplies",
            "type":"Manufacturing & Wholesale Goods"
        }
    ],
    "sg:phone":"+1 760 343 5666",
    "sg:postcode":"92276",
    "sg:province":"CA",
    "sg:tags":[
        "equipment",
        "industrial",
        "automotive",
        "repair"
    ],
    "wof:name":"Hose Mart",
    "wof:placetype":"venue"
},
  "geometry": {"coordinates":[-116.40406,33.822273],"type":"Point"}
}