{
  "type": "Feature",
  "properties": {
    "iso:country":"US",
    "sg:address":"1214 S Main St",
    "sg:city":"Los Angeles",
    "sg:classifiers":[
        {
            "category":"Manufacturing",
            "subcategory":"Tools & Machinery",
            "type":"Manufacturing & Wholesale Goods"
        }
    ],
    "sg:phone":"+1 213 748 2888",
    "sg:postcode":"90015",
    "sg:province":"CA",
    "sg:tags":[
        "woodworking",
        "mfg"
    ],
    "wof:name":"Scarfland",
    "wof:placetype":"venue"
},
  "geometry": {"coordinates":[-118.260002,34.036695],"type":"Point"}
}