{
  "type": "Feature",
  "properties": {
    "addr:full":"15111 Palmdale Rd Victorville CA 92392",
    "addr:postcode":"15111;92392",
    "addr:street":"Palmdale Rd",
    "iso:country":"US",
    "sg:address":"15111 Palmdale Rd",
    "sg:city":"Victorville",
    "sg:classifiers":[
        {
            "category":"Autos & Motor Vehicles",
            "subcategory":"Automobile Sales",
            "type":"Retail Goods"
        }
    ],
    "sg:phone":"+1 760 241 5500",
    "sg:postcode":"92392",
    "sg:province":"CA",
    "sg:tags":[
        "car",
        "dealer"
    ],
    "wof:name":"Thrifty Car Sales Inc",
    "wof:placetype":"venue"
},
  "geometry": {"coordinates":[-117.333314,34.506794],"type":"Point"}
}