{
  "type": "Feature",
  "properties": {
    "addr:full":"350 Delage Dr Encinitas CA 92024",
    "addr:housenumber":"350",
    "addr:postcode":"92024",
    "addr:street":"Delage Dr",
    "iso:country":"US",
    "sg:address":"350 Delage Dr",
    "sg:city":"Encinitas",
    "sg:classifiers":[
        {
            "category":"Wholesale",
            "subcategory":"Jewelry",
            "type":"Manufacturing & Wholesale Goods"
        }
    ],
    "sg:phone":"+1 760 436 7052",
    "sg:postcode":"92024",
    "sg:province":"CA",
    "sg:tags":[
        "stone"
    ],
    "wof:name":"Temple Trading Co",
    "wof:placetype":"venue"
},
  "geometry": {"coordinates":[-117.257492,33.037305],"type":"Point"}
}