{
  "type": "Feature",
  "properties": {
    "addr:full":"8530 Fruitridge Rd Sacramento CA 95826",
    "addr:housenumber":"8530",
    "addr:postcode":"95826",
    "addr:street":"Fruitridge Rd",
    "iso:country":"US",
    "sg:address":"8530 Fruitridge Rd",
    "sg:city":"Sacramento",
    "sg:classifiers":[
        {
            "category":"Retail",
            "subcategory":"Auto Repair",
            "type":"Services"
        }
    ],
    "sg:phone":"+1 916 386 2222",
    "sg:postcode":"95826",
    "sg:province":"CA",
    "sg:tags":[
        "road"
    ],
    "wof:name":"Quality Towing",
    "wof:placetype":"venue"
},
  "geometry": {"coordinates":[-121.389383,38.525106],"type":"Point"}
}