{
  "type": "Feature",
  "properties": {
    "iso:country":"US",
    "sg:address":"133 S Hudson Ave Ste 2",
    "sg:city":"Pasadena",
    "sg:classifiers":[
        {
            "category":"Personal",
            "subcategory":"Skin Care",
            "type":"Services"
        }
    ],
    "sg:phone":"+1 626 201 5160",
    "sg:postcode":"91101",
    "sg:province":"CA",
    "wof:name":"Skin Savvy",
    "wof:placetype":"venue"
},
  "geometry": {"coordinates":[-118.13385700000001,34.143397],"type":"Point"}
}