{
  "type": "Feature",
  "properties": {
    "addr:full":"1703 Lundy Ave San Jose CA 95131",
    "addr:housenumber":"1703",
    "addr:postcode":"95131",
    "addr:street":"Lundy Ave",
    "iso:country":"US",
    "sg:address":"1703 Lundy Ave",
    "sg:city":"San Jose",
    "sg:classifiers":[
        {
            "category":"Food & Beverages",
            "subcategory":"Fruits & Vegetables",
            "type":"Retail Goods"
        }
    ],
    "sg:phone":"+1 408 272 1477",
    "sg:postcode":"95131",
    "sg:province":"CA",
    "sg:tags":[
        "produce"
    ],
    "wof:name":"Abel Produce",
    "wof:placetype":"venue"
},
  "geometry": {"coordinates":[-121.887182,37.38839],"type":"Point"}
}