{
  "type": "Feature",
  "properties": {
    "addr:full":"2116 Denny St Simi Valley CA 93065",
    "addr:housenumber":"2116",
    "addr:postcode":"93065",
    "addr:street":"Denny St",
    "iso:country":"US",
    "sg:address":"2116 Denny St",
    "sg:city":"Simi Valley",
    "sg:classifiers":[
        {
            "category":"Real Estate",
            "subcategory":"Real Estate Agent",
            "type":"Services"
        }
    ],
    "sg:phone":"+1 805 522 3226",
    "sg:postcode":"93065",
    "sg:province":"CA",
    "wof:name":"Homeworks Real Estate",
    "wof:placetype":"venue"
},
  "geometry": {"coordinates":[-118.757107,34.27004],"type":"Point"}
}