{
  "type": "Feature",
  "properties": {
    "iso:country":"US",
    "sg:address":"1833 W March Ln",
    "sg:city":"Stockton",
    "sg:classifiers":[
        {
            "category":"Real Estate",
            "subcategory":"Real Estate Agent",
            "type":"Services"
        }
    ],
    "sg:phone":"+1 209 952 3661",
    "sg:postcode":"95207",
    "sg:province":"CA",
    "wof:name":"American Properties Management",
    "wof:placetype":"venue"
},
  "geometry": {"coordinates":[-121.328486,37.987437],"type":"Point"}
}