{
  "type": "Feature",
  "properties": {
    "addr:full":"1040 N Imperial Ave El Centro CA 92243",
    "addr:housenumber":"1040",
    "addr:postcode":"92243",
    "addr:street":"N Imperial Ave",
    "iso:country":"US",
    "sg:address":"1040 N Imperial Ave",
    "sg:city":"El Centro",
    "sg:classifiers":[
        {
            "category":"Shopping",
            "subcategory":"Clothing, Apparel, & Fashions",
            "type":"Retail Goods"
        }
    ],
    "sg:phone":"+1 760 353 3800",
    "sg:postcode":"92243",
    "sg:province":"CA",
    "sg:tags":[
        "furnishing"
    ],
    "wof:name":"Miller's Outpost",
    "wof:placetype":"venue"
},
  "geometry": {"coordinates":[-115.56999,32.800361],"type":"Point"}
}