{
  "type": "Feature",
  "properties": {
    "iso:country":"US",
    "sg:address":"2547 W Rosamond Blvd",
    "sg:city":"Rosamond",
    "sg:classifiers":[
        {
            "category":"Food & Beverages",
            "subcategory":"Groceries & Convenience Stores",
            "type":"Retail Goods"
        }
    ],
    "sg:phone":"+1 661 256 0756",
    "sg:postcode":"93560",
    "sg:province":"CA",
    "sg:tags":[
        "grocer"
    ],
    "wof:name":"Albertsons",
    "wof:placetype":"venue"
},
  "geometry": {"coordinates":[-118.176847,34.864355],"type":"Point"}
}