{
  "type": "Feature",
  "properties": {
    "iso:country":"US",
    "sg:address":"29219 Canwood St",
    "sg:city":"Agoura Hills",
    "sg:classifiers":[
        {
            "category":"Health Services",
            "subcategory":"Dentist",
            "type":"Services"
        }
    ],
    "sg:phone":"+1 818 991 2626",
    "sg:postcode":"91301",
    "sg:province":"CA",
    "wof:name":"Shamsian Shahin DDS",
    "wof:placetype":"venue"
},
  "geometry": {"coordinates":[-118.761864,34.147121],"type":"Point"}
}