{
  "type": "Feature",
  "properties": {
    "iso:country":"US",
    "sg:address":"879 Scott Ct",
    "sg:city":"Campbell",
    "sg:classifiers":[
        {
            "category":"Building & Trades",
            "subcategory":"Construction",
            "type":"Services"
        }
    ],
    "sg:phone":"+1 408 374 0314",
    "sg:postcode":"95008",
    "sg:province":"CA",
    "sg:tags":[
        "hanging",
        "contractor"
    ],
    "wof:name":"Elite Painting",
    "wof:placetype":"venue"
},
  "geometry": {"coordinates":[-121.966362,37.268445],"type":"Point"}
}