{
  "type": "Feature",
  "properties": {
    "iso:country":"US",
    "sg:address":"4610 Enterprise Ct",
    "sg:city":"Diamond Springs",
    "sg:classifiers":[
        {
            "category":"Manufacturing",
            "subcategory":"Printing",
            "type":"Manufacturing & Wholesale Goods"
        }
    ],
    "sg:phone":"+1 530 626 3731",
    "sg:postcode":"95619",
    "sg:province":"CA",
    "sg:tags":[
        "label"
    ],
    "sg:website":"www.perfectolabels.com",
    "wof:name":"Perfecto Label Co Inc",
    "wof:placetype":"venue"
},
  "geometry": {"coordinates":[-120.830226,38.694922],"type":"Point"}
}