{
  "type": "Feature",
  "properties": {
    "iso:country":"US",
    "sg:address":"13394 Poway Rd",
    "sg:city":"Poway",
    "sg:classifiers":[
        {
            "category":"Autos & Motor Vehicles",
            "subcategory":"Fuel & Gas Station",
            "type":"Retail Goods"
        }
    ],
    "sg:phone":"+1 858 679 7860",
    "sg:postcode":"92064",
    "sg:province":"CA",
    "sg:tags":[
        "oil"
    ],
    "wof:name":"Golden State Gasoline",
    "wof:placetype":"venue"
},
  "geometry": {"coordinates":[-117.044937,32.956563],"type":"Point"}
}