{
  "type": "Feature",
  "properties": {
    "iso:country":"US",
    "sg:address":"4399 Porter Gulch Rd",
    "sg:city":"Aptos",
    "sg:classifiers":[
        {
            "category":"Building & Trades",
            "subcategory":"Construction",
            "type":"Services"
        }
    ],
    "sg:phone":"+1 831 464 8735",
    "sg:postcode":"95003",
    "sg:province":"CA",
    "sg:tags":[
        "dry wall",
        "contractor"
    ],
    "wof:name":"D R Drywall",
    "wof:placetype":"venue"
},
  "geometry": {"coordinates":[-121.927905,37.003833],"type":"Point"}
}