{
  "type": "Feature",
  "properties": {
    "iso:country":"US",
    "sg:address":"940 E Windsor Cir",
    "sg:city":"Fresno",
    "sg:classifiers":[
        {
            "category":"Real Estate",
            "subcategory":"Real Estate Operator",
            "type":"Services"
        }
    ],
    "sg:phone":"+1 559 434 9520",
    "sg:postcode":"93720",
    "sg:province":"CA",
    "sg:tags":[
        "apartment"
    ],
    "wof:name":"Rental Guide Magazine",
    "wof:placetype":"venue"
},
  "geometry": {"coordinates":[-119.767196,36.878041],"type":"Point"}
}