{
  "type": "Feature",
  "properties": {
    "addr:full":"4651 E Fountain Way Fresno CA 93726",
    "addr:housenumber":"4651",
    "addr:postcode":"93726",
    "addr:street":"E Fountain Way",
    "iso:country":"US",
    "sg:address":"4651 E Fountain Way",
    "sg:city":"Fresno",
    "sg:classifiers":[
        {
            "category":"Building & Trades",
            "subcategory":"Construction",
            "type":"Services"
        }
    ],
    "sg:phone":"+1 559 264 3272",
    "sg:postcode":"93726",
    "sg:province":"CA",
    "sg:tags":[
        "contractor"
    ],
    "wof:name":"Flores Construction",
    "wof:placetype":"venue"
},
  "geometry": {"coordinates":[-119.74078900000001,36.781355],"type":"Point"}
}