{
  "type": "Feature",
  "properties": {
    "addr:full":"4885 Mission Street San Francisco CA 94112",
    "addr:housenumber":"4885",
    "addr:postcode":"94112",
    "addr:street":"Mission Street",
    "iso:country":"US",
    "sg:address":"4885 Mission Street",
    "sg:city":"San Francisco",
    "sg:classifiers":[
        {
            "category":"Retail",
            "subcategory":"Auto Repair",
            "type":"Services"
        },
        {
            "category":"Government",
            "subcategory":"Office",
            "type":"Public Place"
        }
    ],
    "sg:phone":"+1 415 585 8400",
    "sg:postcode":"94112",
    "sg:province":"CA",
    "sg:tags":[
        "smog",
        "check"
    ],
    "wof:name":"Reliance Auto",
    "wof:placetype":"venue"
},
  "geometry": {"coordinates":[-122.43800400000001,37.7201],"type":"Point"}
}