{
  "type": "Feature",
  "properties": {
    "addr:full":"139 W Ridgecrest Blvd Ridgecrest CA 93555",
    "addr:housenumber":"139",
    "addr:postcode":"93555",
    "addr:street":"W Ridgecrest Blvd",
    "iso:country":"US",
    "sg:address":"139 W Ridgecrest Blvd",
    "sg:city":"Ridgecrest",
    "sg:classifiers":[
        {
            "category":"Personal",
            "subcategory":"Beauty Salon",
            "type":"Services"
        }
    ],
    "sg:phone":"+1 760 375 3411",
    "sg:postcode":"93555",
    "sg:province":"CA",
    "wof:name":"Cindy & Co Hair Design",
    "wof:placetype":"venue"
},
  "geometry": {"coordinates":[-117.671683,35.62249],"type":"Point"}
}