{
  "type": "Feature",
  "properties": {
    "addr:full":"1965 Vis de la Montana El Cajon CA 92019",
    "addr:housenumber":"1965",
    "addr:postcode":"92019",
    "addr:street":"Vis De La Montana",
    "iso:country":"US",
    "sg:address":"1965 Vis de la Montana",
    "sg:city":"El Cajon",
    "sg:classifiers":[
        {
            "category":"Professional",
            "subcategory":"Management & Consulting",
            "type":"Services"
        }
    ],
    "sg:phone":"+1 619 659 8933",
    "sg:postcode":"92019",
    "sg:province":"CA",
    "sg:tags":[
        "consultant",
        "security",
        "system"
    ],
    "wof:name":"Custom Survellance Solutions",
    "wof:placetype":"venue"
},
  "geometry": {"coordinates":[-116.839662,32.79231],"type":"Point"}
}