{
  "type": "Feature",
  "properties": {
    "iso:country":"US",
    "sg:address":"2707 Man Beach Boulevard",
    "sg:city":"Hawthorne",
    "sg:classifiers":[
        {
            "category":"Personal",
            "subcategory":"Tanning Parlor",
            "type":"Services"
        },
        {
            "category":"Sports & Exercise",
            "subcategory":"Gym",
            "type":"Entertainment"
        }
    ],
    "sg:phone":"+1 310 643 7909",
    "sg:postcode":"90250",
    "sg:province":"CA",
    "wof:name":"A Cop A Tan Tanning Salon",
    "wof:placetype":"venue"
},
  "geometry": {"coordinates":[-118.345913,33.911993],"type":"Point"}
}