{
  "type": "Feature",
  "properties": {
    "iso:country":"US",
    "sg:address":"13553 Reedley St",
    "sg:city":"Van Nuys",
    "sg:classifiers":[
        {
            "category":"Organizations",
            "subcategory":"Community Association",
            "type":"Services"
        }
    ],
    "sg:phone":"+1 818 781 2261",
    "sg:postcode":"91402",
    "sg:province":"CA",
    "sg:tags":[
        "military"
    ],
    "wof:name":"American Legion",
    "wof:placetype":"venue"
},
  "geometry": {"coordinates":[-118.428109,34.222211],"type":"Point"}
}