{
  "type": "Feature",
  "properties": {
    "iso:country":"US",
    "sg:address":"415 Jackson St",
    "sg:city":"San Francisco",
    "sg:classifiers":[
        {
            "category":"Education",
            "subcategory":"Vocational School",
            "type":"Public Place"
        }
    ],
    "sg:phone":"+1 415 837 0966",
    "sg:postcode":"94111",
    "sg:province":"CA",
    "wof:name":"Miami Ad School",
    "wof:placetype":"venue"
},
  "geometry": {"coordinates":[-122.40223,37.796507],"type":"Point"}
}