{
  "type": "Feature",
  "properties": {
    "addr:full":"5343 Adobe Falls Rd San Diego CA 92120",
    "addr:housenumber":"5343",
    "addr:postcode":"92120",
    "addr:street":"Adobe Falls Rd",
    "iso:country":"US",
    "sg:address":"5343 Adobe Falls Rd",
    "sg:city":"San Diego",
    "sg:classifiers":[
        {
            "category":"Building & Trades",
            "subcategory":"Construction",
            "type":"Services"
        }
    ],
    "sg:phone":"+1 619 287 6109",
    "sg:postcode":"92120",
    "sg:province":"CA",
    "sg:tags":[
        "general",
        "contractor"
    ],
    "wof:name":"Kcmc Inc",
    "wof:placetype":"venue"
},
  "geometry": {"coordinates":[-117.08528099999999,32.782366],"type":"Point"}
}