{
  "type": "Feature",
  "properties": {
    "iso:country":"US",
    "sg:address":"645 Brookside Ave",
    "sg:city":"Redlands",
    "sg:classifiers":[
        {
            "category":"Health Services",
            "subcategory":"Doctor",
            "type":"Services"
        }
    ],
    "sg:phone":"+1 760 568 1799",
    "sg:postcode":"92373",
    "sg:province":"CA",
    "sg:tags":[
        "counseling",
        "clinic"
    ],
    "wof:name":"Rebecca Hyatt",
    "wof:placetype":"venue"
},
  "geometry": {"coordinates":[-117.1901,34.052886],"type":"Point"}
}