{
  "type": "Feature",
  "properties": {
    "addr:full":"2300 White Ln Bakersfield CA 93304",
    "addr:housenumber":"2300",
    "addr:postcode":"93304",
    "addr:street":"White Ln",
    "iso:country":"US",
    "sg:address":"2300 White Ln",
    "sg:city":"Bakersfield",
    "sg:classifiers":[
        {
            "category":"Health Services",
            "subcategory":"Optometrist",
            "type":"Services"
        }
    ],
    "sg:phone":"+1 661 827 9900",
    "sg:postcode":"93304",
    "sg:province":"CA",
    "wof:name":"Visonet Inc",
    "wof:placetype":"venue"
},
  "geometry": {"coordinates":[-119.02781,35.317743],"type":"Point"}
}