{
  "type": "Feature",
  "properties": {
    "iso:country":"US",
    "sg:address":"7628 Valley Wood Dr",
    "sg:city":"Sacramento",
    "sg:phone":"+1 916 682 5827",
    "sg:postcode":"95828",
    "sg:province":"CA",
    "wof:name":"All Air Services",
    "wof:placetype":"venue"
},
  "geometry": {"coordinates":[-121.38386300000001,38.48026],"type":"Point"}
}