{
  "type": "Feature",
  "properties": {
    "addr:full":"42655 Hill Top Dr Banning CA 92220",
    "addr:housenumber":"42655",
    "addr:postcode":"92220",
    "addr:street":"Hill Top Dr",
    "iso:country":"US",
    "sg:address":"42655 Hill Top Dr",
    "sg:city":"Banning",
    "sg:classifiers":[
        {
            "category":"Professional",
            "type":"Services"
        }
    ],
    "sg:phone":"+1 951 922 2000",
    "sg:postcode":"92220",
    "sg:province":"CA",
    "wof:name":"Harold Stewart General Contrac",
    "wof:placetype":"venue"
},
  "geometry": {"coordinates":[-116.91428500000001,33.907035],"type":"Point"}
}