{
  "type": "Feature",
  "properties": {
    "addr:full":"15651 Worthley Dr San Lorenzo CA 94580",
    "addr:housenumber":"15651",
    "addr:postcode":"94580",
    "addr:street":"Worthley Dr",
    "iso:country":"US",
    "sg:address":"15651 Worthley Dr",
    "sg:city":"San Lorenzo",
    "sg:classifiers":[
        {
            "category":"Freight",
            "type":"Transportation"
        }
    ],
    "sg:phone":"+1 510 278 3570",
    "sg:postcode":"94580",
    "sg:province":"CA",
    "sg:tags":[
        "operator",
        "trucking"
    ],
    "wof:name":"Command Delivery Systems Inc",
    "wof:placetype":"venue"
},
  "geometry": {"coordinates":[-122.151839,37.669419],"type":"Point"}
}