{
  "type": "Feature",
  "properties": {
    "iso:country":"US",
    "sg:address":"1270 Pioneer Way",
    "sg:city":"El Cajon",
    "sg:classifiers":[
        {
            "category":"Retail",
            "subcategory":"Car Wash",
            "type":"Services"
        }
    ],
    "sg:phone":"+1 619 579 2352",
    "sg:postcode":"92020",
    "sg:province":"CA",
    "sg:tags":[
        "automobile",
        "detail",
        "clean"
    ],
    "wof:name":"Autosalon Mobile Detailing",
    "wof:placetype":"venue"
},
  "geometry": {"coordinates":[-116.967825,32.811615],"type":"Point"}
}