{
  "type": "Feature",
  "properties": {
    "iso:country":"US",
    "sg:address":"1613 W el Segundo Blvd",
    "sg:city":"Compton",
    "sg:classifiers":[
        {
            "category":"Manufacturing",
            "subcategory":"Metals",
            "type":"Manufacturing & Wholesale Goods"
        }
    ],
    "sg:phone":"+1 310 638 5101",
    "sg:postcode":"90222",
    "sg:province":"CA",
    "sg:tags":[
        "fabricator",
        "sheet"
    ],
    "sg:website":"www.circleindustrial.com",
    "wof:name":"Circle Industrial Mfg Corp",
    "wof:placetype":"venue"
},
  "geometry": {"coordinates":[-118.248924,33.916286],"type":"Point"}
}