{
  "type": "Feature",
  "properties": {
    "iso:country":"US",
    "sg:address":"345 W 9th Ave",
    "sg:city":"Escondido",
    "sg:classifiers":[
        {
            "category":"Professional",
            "subcategory":"Lawyer & Legal Services",
            "type":"Services"
        }
    ],
    "sg:phone":"+1 760 743 5216",
    "sg:postcode":"92025",
    "sg:province":"CA",
    "sg:tags":[
        "attorney"
    ],
    "sg:website":"www.cjlarsen.com",
    "wof:name":"Constance J Larsen",
    "wof:placetype":"venue"
},
  "geometry": {"coordinates":[-117.079857,33.112654],"type":"Point"}
}