{
  "type": "Feature",
  "properties": {
    "iso:country":"US",
    "sg:address":"41745 Rider Way",
    "sg:city":"Temecula",
    "sg:classifiers":[
        {
            "category":"Home & Garden",
            "subcategory":"Carpets & Floor Coverings",
            "type":"Retail Goods"
        }
    ],
    "sg:phone":"+1 951 699 9292",
    "sg:postcode":"92590",
    "sg:province":"CA",
    "sg:tags":[
        "dealer",
        "rug"
    ],
    "wof:name":"Crown Carpet & Draperies",
    "wof:placetype":"venue"
},
  "geometry": {"coordinates":[-117.165446,33.515998],"type":"Point"}
}