{
  "type": "Feature",
  "properties": {
    "addr:full":"9922 Cornerbrook Dr Huntington Beach CA 92646",
    "addr:housenumber":"9922",
    "addr:postcode":"92646",
    "addr:street":"Cornerbrook Dr",
    "iso:country":"US",
    "sg:address":"9922 Cornerbrook Dr",
    "sg:city":"Huntington Beach",
    "sg:classifiers":[
        {
            "category":"Professional",
            "subcategory":"Lawyer & Legal Services",
            "type":"Services"
        }
    ],
    "sg:phone":"+1 714 593 6969",
    "sg:postcode":"92646",
    "sg:province":"CA",
    "wof:name":"Kelton Stanley M Attorney At Law",
    "wof:placetype":"venue"
},
  "geometry": {"coordinates":[-117.95500199999999,33.656502],"type":"Point"}
}