{
  "type": "Feature",
  "properties": {
    "addr:full":"324 Gloria Ave San Jose CA 95127",
    "addr:housenumber":"324",
    "addr:postcode":"95127",
    "addr:street":"Gloria Ave",
    "iso:country":"US",
    "sg:address":"324 Gloria Ave",
    "sg:city":"San Jose",
    "sg:classifiers":[
        {
            "category":"Organizations",
            "subcategory":"Religious Organization",
            "type":"Services"
        }
    ],
    "sg:phone":"+1 408 251 2016",
    "sg:postcode":"95127",
    "sg:province":"CA",
    "sg:tags":[
        "church"
    ],
    "wof:name":"First Samoan Congregational",
    "wof:placetype":"venue"
},
  "geometry": {"coordinates":[-121.81792299999999,37.363749],"type":"Point"}
}