{
  "type": "Feature",
  "properties": {
    "addr:full":"5854 College Avenue Oakland CA 94618",
    "addr:housenumber":"5854",
    "addr:postcode":"94618",
    "addr:street":"College Avenue",
    "iso:country":"US",
    "sg:address":"5854 College Avenue",
    "sg:city":"Oakland",
    "sg:classifiers":[
        {
            "category":"Shopping",
            "subcategory":"Clothing, Apparel, & Fashions",
            "type":"Retail Goods"
        }
    ],
    "sg:phone":"+1 510 594 8380",
    "sg:postcode":"94618",
    "sg:province":"CA",
    "sg:tags":[
        "accessory",
        "clothing",
        "women's"
    ],
    "sg:website":"www.vivadivaboutique.com",
    "wof:name":"Viva Diva Boutique",
    "wof:placetype":"venue"
},
  "geometry": {"coordinates":[-122.251999,37.846699],"type":"Point"}
}