{
  "type": "Feature",
  "properties": {
    "addr:full":"13133 Solvang Way Truckee CA 96161",
    "addr:housenumber":"13133",
    "addr:postcode":"96161",
    "addr:street":"Solvang Way",
    "iso:country":"US",
    "sg:address":"13133 Solvang Way",
    "sg:city":"Truckee",
    "sg:classifiers":[
        {
            "category":"Building & Trades",
            "subcategory":"Plumbing",
            "type":"Services"
        }
    ],
    "sg:phone":"+1 530 587 4588",
    "sg:postcode":"96161",
    "sg:province":"CA",
    "sg:tags":[
        "plumbing",
        "contractor"
    ],
    "wof:name":"Advanced Plumbing",
    "wof:placetype":"venue"
},
  "geometry": {"coordinates":[-120.23986499999999,39.366993],"type":"Point"}
}