{
  "type": "Feature",
  "properties": {
    "addr:full":"1351 24th Ave San Francisco CA 94122",
    "addr:housenumber":"1351",
    "addr:postcode":"94122",
    "addr:street":"24Th Ave",
    "iso:country":"US",
    "sg:address":"1351 24th Ave",
    "sg:city":"San Francisco",
    "sg:classifiers":[
        {
            "category":"Professional",
            "type":"Services"
        }
    ],
    "sg:phone":"+1 415 566 9710",
    "sg:postcode":"94122",
    "sg:province":"CA",
    "sg:tags":[
        "establishment"
    ],
    "wof:name":"Access To End Of Life Care",
    "wof:placetype":"venue"
},
  "geometry": {"coordinates":[-122.482479,37.76241],"type":"Point"}
}