{
  "type": "Feature",
  "properties": {
    "iso:country":"US",
    "sg:address":"9301 Mazatlan Way",
    "sg:city":"Elk Grove",
    "sg:classifiers":[
        {
            "category":"Wholesale",
            "subcategory":"Apparel",
            "type":"Manufacturing & Wholesale Goods"
        }
    ],
    "sg:phone":"+1 916 683 4715",
    "sg:postcode":"95624",
    "sg:province":"CA",
    "sg:tags":[
        "boy",
        "clothing"
    ],
    "wof:name":"Hanson Enterprises",
    "wof:placetype":"venue"
},
  "geometry": {"coordinates":[-121.368113,38.414131],"type":"Point"}
}