{
  "type": "Feature",
  "properties": {
    "addr:full":"457 E Evelyn Avenue Sunnyvale CA 94086",
    "addr:housenumber":"457",
    "addr:postcode":"94086",
    "addr:street":"E Evelyn Avenue",
    "iso:country":"US",
    "sg:address":"457 E Evelyn Avenue",
    "sg:city":"Sunnyvale",
    "sg:classifiers":[
        {
            "category":"Real Estate",
            "subcategory":"Architect",
            "type":"Services"
        }
    ],
    "sg:phone":"+1 408 245 7161",
    "sg:postcode":"94086",
    "sg:province":"CA",
    "wof:name":"Equipment Solutions",
    "wof:placetype":"venue"
},
  "geometry": {"coordinates":[-122.025773,37.376399],"type":"Point"}
}