{
  "type": "Feature",
  "properties": {
    "iso:country":"US",
    "sg:address":"2850 Pio Pico Dr",
    "sg:city":"Carlsbad",
    "sg:classifiers":[
        {
            "category":"Health Services",
            "subcategory":"Health Practitioner",
            "type":"Services"
        }
    ],
    "sg:phone":"+1 619 298 8722",
    "sg:postcode":"92008",
    "sg:province":"CA",
    "wof:name":"Aaron J Reinicke",
    "wof:placetype":"venue"
},
  "geometry": {"coordinates":[-117.343513,33.16692],"type":"Point"}
}