{
  "type": "Feature",
  "properties": {
    "addr:full":"22809 Hawthorne Blvd Torrance CA 90505",
    "addr:housenumber":"22809",
    "addr:postcode":"90505",
    "addr:street":"Hawthorne Blvd",
    "iso:country":"US",
    "sg:address":"22809 Hawthorne Blvd",
    "sg:city":"Torrance",
    "sg:classifiers":[
        {
            "category":"Health Services",
            "subcategory":"Optometrist",
            "type":"Services"
        },
        {
            "category":"Shopping",
            "subcategory":"Optician",
            "type":"Retail Goods"
        }
    ],
    "sg:phone":"+1 310 373 9342",
    "sg:postcode":"90505",
    "sg:province":"CA",
    "sg:tags":[
        "eyewear"
    ],
    "sg:website":"www.advancedfamilyeyecare.net",
    "wof:name":"Advanced Family Eye Care",
    "wof:placetype":"venue"
},
  "geometry": {"coordinates":[-118.35153099999999,33.819956],"type":"Point"}
}