{
  "type": "Feature",
  "properties": {
    "iso:country":"US",
    "sg:address":"2701 Atlantic Ave",
    "sg:city":"Long Beach",
    "sg:classifiers":[
        {
            "category":"Social Services",
            "type":"Services"
        }
    ],
    "sg:phone":"+1 562 933 2998",
    "sg:postcode":"90806",
    "sg:province":"CA",
    "sg:tags":[
        "information",
        "planning",
        "center",
        "family"
    ],
    "wof:name":"Memorial Women's Ctr-Family",
    "wof:placetype":"venue"
},
  "geometry": {"coordinates":[-118.185012,33.807103],"type":"Point"}
}