{
  "type": "Feature",
  "properties": {
    "addr:full":"13452 Grizzly Way Redding CA 96003",
    "addr:housenumber":"13452",
    "addr:postcode":"96003",
    "addr:street":"Grizzly Way",
    "iso:country":"US",
    "sg:address":"13452 Grizzly Way",
    "sg:city":"Redding",
    "sg:classifiers":[
        {
            "category":"Building & Trades",
            "subcategory":"Construction",
            "type":"Services"
        }
    ],
    "sg:phone":"+1 530 275 5358",
    "sg:postcode":"96003",
    "sg:province":"CA",
    "sg:tags":[
        "layer",
        "carpet"
    ],
    "wof:name":"Corky's Carpets",
    "wof:placetype":"venue"
},
  "geometry": {"coordinates":[-122.29937099999999,40.67803],"type":"Point"}
}