{
  "type": "Feature",
  "properties": {
    "iso:country":"US",
    "sg:address":"3140 Canyon St",
    "sg:city":"Carlsbad",
    "sg:classifiers":[
        {
            "category":"Manufacturing",
            "subcategory":"Wood Products",
            "type":"Manufacturing & Wholesale Goods"
        }
    ],
    "sg:phone":"+1 760 729 0467",
    "sg:postcode":"92008",
    "sg:province":"CA",
    "sg:tags":[
        "mfg"
    ],
    "wof:name":"Warren Can Cane",
    "wof:placetype":"venue"
},
  "geometry": {"coordinates":[-117.33225,33.167133],"type":"Point"}
}