{
  "type": "Feature",
  "properties": {
    "iso:country":"US",
    "sg:address":"9191 Towne Centre Dr Ste 390",
    "sg:city":"San Diego",
    "sg:classifiers":[
        {
            "category":"Professional",
            "subcategory":"Lawyer & Legal Services",
            "type":"Services"
        }
    ],
    "sg:phone":"+1 858 678 9448",
    "sg:postcode":"92122",
    "sg:province":"CA",
    "wof:name":"Grancell Lebovitz Stander Barnes & Reubens",
    "wof:placetype":"venue"
},
  "geometry": {"coordinates":[-117.207206,32.873791],"type":"Point"}
}