{
  "type": "Feature",
  "properties": {
    "addr:full":"5677 Gibraltar Dr Pleasanton CA 94588",
    "addr:housenumber":"5677",
    "addr:postcode":"94588",
    "addr:street":"Gibraltar Dr",
    "iso:country":"US",
    "sg:address":"5677 Gibraltar Dr",
    "sg:city":"Pleasanton",
    "sg:classifiers":[
        {
            "category":"Health Services",
            "subcategory":"Doctor",
            "type":"Services"
        }
    ],
    "sg:phone":"+1 925 225 9855",
    "sg:postcode":"94588",
    "sg:province":"CA",
    "sg:tags":[
        "dentist"
    ],
    "wof:name":"Y Dentistry",
    "wof:placetype":"venue"
},
  "geometry": {"coordinates":[-121.89247899999999,37.687455],"type":"Point"}
}