{
  "type": "Feature",
  "properties": {
    "addr:full":"8947 Mills Ave Whittier CA 90605",
    "addr:housenumber":"8947",
    "addr:postcode":"90605",
    "addr:street":"Mills Ave",
    "iso:country":"US",
    "sg:address":"8947 Mills Ave",
    "sg:city":"Whittier",
    "sg:classifiers":[
        {
            "category":"Building & Trades",
            "subcategory":"Construction",
            "type":"Services"
        }
    ],
    "sg:phone":"+1 562 696 5095",
    "sg:postcode":"90605",
    "sg:province":"CA",
    "sg:tags":[
        "contractor"
    ],
    "wof:name":"LJI Commercial Construction",
    "wof:placetype":"venue"
},
  "geometry": {"coordinates":[-118.00976,33.951535],"type":"Point"}
}