{
  "type": "Feature",
  "properties": {
    "addr:full":"2601 W Alameda Ave Ste 410 Burbank CA 91505",
    "addr:housenumber":"2601",
    "addr:postcode":"91505",
    "addr:street":"W Alameda Ave Ste 410",
    "iso:country":"US",
    "sg:address":"2601 W Alameda Ave Ste 410",
    "sg:city":"Burbank",
    "sg:classifiers":[
        {
            "category":"Health Services",
            "subcategory":"Doctor",
            "type":"Services"
        }
    ],
    "sg:phone":"+1 818 729 0014",
    "sg:postcode":"91505",
    "sg:province":"CA",
    "sg:tags":[
        "physician",
        "pediatrics",
        "family",
        "practice",
        "surgeons",
        "medicine",
        "surgeon"
    ],
    "wof:name":"Dr. Alinsod Pediatricia/Family Practice",
    "wof:placetype":"venue"
},
  "geometry": {"coordinates":[-118.32914,34.15789],"type":"Point"}
}