{
  "type": "Feature",
  "properties": {
    "iso:country":"US",
    "sg:address":"2620 Chester Ave",
    "sg:city":"Bakersfield",
    "sg:classifiers":[
        {
            "category":"Shopping",
            "subcategory":"Books",
            "type":"Retail Goods"
        }
    ],
    "sg:phone":"+1 661 324 4243",
    "sg:postcode":"93301",
    "sg:province":"CA",
    "sg:tags":[
        "dealer"
    ],
    "wof:name":"Wildcat Enterprises",
    "wof:placetype":"venue"
},
  "geometry": {"coordinates":[-119.018694,35.38365],"type":"Point"}
}