{
  "type": "Feature",
  "properties": {
    "iso:country":"US",
    "sg:address":"7710 Limonite Ave",
    "sg:city":"Riverside",
    "sg:classifiers":[
        {
            "category":"Retail",
            "subcategory":"Repair Shop",
            "type":"Services"
        },
        {
            "category":"Manufacturing",
            "subcategory":"Tools & Machinery",
            "type":"Manufacturing & Wholesale Goods"
        }
    ],
    "sg:phone":"+1 951 727 8799",
    "sg:postcode":"92509",
    "sg:province":"CA",
    "sg:tags":[
        "home",
        "cleaners",
        "vacuum",
        "parts",
        "mfg"
    ],
    "wof:name":"Kirby Of Riverside",
    "wof:placetype":"venue"
},
  "geometry": {"coordinates":[-117.458312,33.978161],"type":"Point"}
}