{
  "type": "Feature",
  "properties": {
    "addr:full":"2370 E Bidwell St Ste 130 Folsom CA 95630",
    "addr:housenumber":"2370",
    "addr:postcode":"95630",
    "addr:street":"E Bidwell St Ste 130",
    "iso:country":"US",
    "sg:address":"2370 E Bidwell St Ste 130",
    "sg:city":"Folsom",
    "sg:classifiers":[
        {
            "category":"Health Services",
            "subcategory":"Chiropractor",
            "type":"Services"
        }
    ],
    "sg:phone":"+1 916 983 2359",
    "sg:postcode":"95630",
    "sg:province":"CA",
    "sg:tags":[
        "chiropractic"
    ],
    "wof:name":"Shigemoto Chiropractic Inc.",
    "wof:placetype":"venue"
},
  "geometry": {"coordinates":[-121.137745,38.66444],"type":"Point"}
}