{
  "type": "Feature",
  "properties": {
    "addr:full":"1919 B St Marysville CA 95901",
    "addr:housenumber":"1919",
    "addr:postcode":"95901",
    "addr:street":"B St",
    "iso:country":"US",
    "sg:address":"1919 B St",
    "sg:city":"Marysville",
    "sg:classifiers":[
        {
            "category":"Education",
            "subcategory":"School",
            "type":"Public Place"
        }
    ],
    "sg:phone":"+1 530 749 6183",
    "sg:postcode":"95901",
    "sg:province":"CA",
    "wof:name":"Marysville Joint Unified Dist",
    "wof:placetype":"venue"
},
  "geometry": {"coordinates":[-121.588678,39.157356],"type":"Point"}
}