{
  "type": "Feature",
  "properties": {
    "addr:full":"1574 Lower Lake Ct Cardiff By Sea CA 92007",
    "addr:housenumber":"1574",
    "addr:postcode":"92007",
    "addr:street":"Lower Lake Ct",
    "iso:country":"US",
    "sg:address":"1574 Lower Lake Ct",
    "sg:city":"Cardiff By Sea",
    "sg:classifiers":[
        {
            "category":"Local Transit",
            "type":"Transportation"
        }
    ],
    "sg:phone":"+1 760 942 7254",
    "sg:postcode":"92007",
    "sg:province":"CA",
    "sg:tags":[
        "limousine"
    ],
    "wof:name":"Birchfield Transportation",
    "wof:placetype":"venue"
},
  "geometry": {"coordinates":[-117.26740100000001,33.030575],"type":"Point"}
}