{
  "type": "Feature",
  "properties": {
    "addr:full":"6448 E Pine St Lodi CA 95240",
    "addr:housenumber":"6448",
    "addr:postcode":"95240",
    "addr:street":"E Pine St",
    "iso:country":"US",
    "sg:address":"6448 E Pine St",
    "sg:city":"Lodi",
    "sg:classifiers":[
        {
            "category":"Farming",
            "subcategory":"Farm",
            "type":"Manufacturing & Wholesale Goods"
        }
    ],
    "sg:phone":"+1 209 369 6993",
    "sg:postcode":"95240",
    "sg:province":"CA",
    "sg:tags":[
        "crop",
        "general"
    ],
    "wof:name":"Bohnet Farm",
    "wof:placetype":"venue"
},
  "geometry": {"coordinates":[-121.235913,38.134008],"type":"Point"}
}