{
  "type": "Feature",
  "properties": {
    "addr:full":"323 Ocean Front Walk Venice CA 90291",
    "addr:housenumber":"323",
    "addr:postcode":"90291",
    "addr:street":"Ocean Front Walk",
    "iso:country":"US",
    "sg:address":"323 Ocean Front Walk",
    "sg:city":"Venice",
    "sg:classifiers":[
        {
            "category":"Restaurant",
            "type":"Food & Drink"
        }
    ],
    "sg:phone":"+1 310 392 3997",
    "sg:postcode":"90291",
    "sg:province":"CA",
    "wof:name":"Lands End Restaurant",
    "wof:placetype":"venue"
},
  "geometry": {"coordinates":[-118.480041,33.994049],"type":"Point"}
}