{
  "type": "Feature",
  "properties": {
    "iso:country":"US",
    "sg:address":"3160 College Ave Ste 201",
    "sg:city":"Berkeley",
    "sg:classifiers":[
        {
            "category":"Real Estate",
            "subcategory":"Real Estate Services",
            "type":"Services"
        }
    ],
    "sg:phone":"+1 510 541 6728",
    "sg:postcode":"94705",
    "sg:province":"CA",
    "wof:name":"Stephen Bloom - BloomHomes",
    "wof:placetype":"venue"
},
  "geometry": {"coordinates":[-122.252506,37.851718],"type":"Point"}
}