{
  "type": "Feature",
  "properties": {
    "addr:full":"553 N Reservoir St Pomona CA 91767",
    "addr:housenumber":"553",
    "addr:postcode":"91767",
    "addr:street":"N Reservoir St",
    "iso:country":"US",
    "sg:address":"553 N Reservoir St",
    "sg:city":"Pomona",
    "sg:classifiers":[
        {
            "category":"Building & Trades",
            "subcategory":"Plumbing",
            "type":"Services"
        }
    ],
    "sg:phone":"+1 909 865 8477",
    "sg:postcode":"91767",
    "sg:province":"CA",
    "sg:tags":[
        "contractor"
    ],
    "wof:name":"or Refrigeration",
    "wof:placetype":"venue"
},
  "geometry": {"coordinates":[-117.73238000000001,34.063738],"type":"Point"}
}