{
  "type": "Feature",
  "properties": {
    "iso:country":"US",
    "sg:address":"6023 Kester Ave",
    "sg:city":"Van Nuys",
    "sg:classifiers":[
        {
            "category":"Retail",
            "subcategory":"Auto Repair",
            "type":"Services"
        }
    ],
    "sg:phone":"+1 818 780 9433",
    "sg:postcode":"91411",
    "sg:province":"CA",
    "sg:tags":[
        "repairing",
        "automobile"
    ],
    "wof:name":"Classic Car Of Sweden",
    "wof:placetype":"venue"
},
  "geometry": {"coordinates":[-118.457442,34.179385],"type":"Point"}
}