{
  "type": "Feature",
  "properties": {
    "addr:full":"1215 N Beachwood Dr Burbank CA 91506",
    "addr:housenumber":"1215",
    "addr:postcode":"91506",
    "addr:street":"N Beachwood Dr",
    "iso:country":"US",
    "sg:address":"1215 N Beachwood Dr",
    "sg:city":"Burbank",
    "sg:classifiers":[
        {
            "category":"Personal",
            "type":"Services"
        }
    ],
    "sg:phone":"+1 818 218 1601",
    "sg:postcode":"91506",
    "sg:province":"CA",
    "sg:tags":[
        "therapist",
        "massage"
    ],
    "wof:name":"Heres The Rub Massage Therapy",
    "wof:placetype":"venue"
},
  "geometry": {"coordinates":[-118.32725499999999,34.18461],"type":"Point"}
}