{
  "type": "Feature",
  "properties": {
    "addr:full":"202 S Bristol St Santa Ana CA 92703",
    "addr:housenumber":"202",
    "addr:postcode":"92703",
    "addr:street":"S Bristol St",
    "iso:country":"US",
    "sg:address":"202 S Bristol St",
    "sg:city":"Santa Ana",
    "sg:classifiers":[
        {
            "category":"Restaurant",
            "type":"Food & Drink"
        }
    ],
    "sg:phone":"+1 714 972 9115",
    "sg:postcode":"92703",
    "sg:province":"CA",
    "sg:tags":[
        "mexican"
    ],
    "wof:name":"Taqueria Tapatia",
    "wof:placetype":"venue"
},
  "geometry": {"coordinates":[-117.885002,33.744202],"type":"Point"}
}