{
  "type": "Feature",
  "properties": {
    "addr:full":"14829 Pomerado Rd Poway CA 92064",
    "addr:housenumber":"14829",
    "addr:postcode":"ca 92064",
    "addr:street":"Pomerado Rd",
    "iso:country":"US",
    "sg:address":"14829 Pomerado Rd",
    "sg:city":"Poway",
    "sg:classifiers":[
        {
            "category":"Restaurant",
            "type":"Food & Drink"
        }
    ],
    "sg:menulink":"http://www.allmenus.com/ca/san-diego/32421-alibertos-taco-shop/menu/",
    "sg:phone":"+1 858 679 5827",
    "sg:postcode":"92064",
    "sg:province":"CA",
    "sg:tags":[
        "mexican"
    ],
    "wof:name":"Aliberto's Taco Shop",
    "wof:placetype":"venue"
},
  "geometry": {"coordinates":[-117.06217700000001,32.980813],"type":"Point"}
}