{
  "type": "Feature",
  "properties": {
    "addr:full":"633 S Hope Ave Ontario CA 91761",
    "addr:housenumber":"633",
    "addr:postcode":"91761",
    "addr:street":"S Hope Ave",
    "iso:country":"US",
    "sg:address":"633 S Hope Ave",
    "sg:city":"Ontario",
    "sg:classifiers":[
        {
            "category":"Wholesale",
            "subcategory":"Hardware",
            "type":"Manufacturing & Wholesale Goods"
        }
    ],
    "sg:phone":"+1 909 983 9793",
    "sg:postcode":"91761",
    "sg:province":"CA",
    "sg:tags":[
        "tool"
    ],
    "wof:name":"Bill's Industrial Tools Inc",
    "wof:placetype":"venue"
},
  "geometry": {"coordinates":[-117.637736,34.056136],"type":"Point"}
}