{
  "type": "Feature",
  "properties": {
    "addr:full":"1555 Grand Ave San Marcos CA 92078",
    "addr:housenumber":"1555",
    "addr:postcode":"92078",
    "addr:street":"Grand Ave",
    "iso:country":"US",
    "sg:address":"1555 Grand Ave",
    "sg:city":"San Marcos",
    "sg:classifiers":[
        {
            "category":"Building & Trades",
            "subcategory":"Cleaning & Sanitation",
            "type":"Services"
        }
    ],
    "sg:phone":"+1 760 744 5510",
    "sg:postcode":"92078",
    "sg:province":"CA",
    "sg:tags":[
        "window"
    ],
    "wof:name":"Fish Window Cleaning",
    "wof:placetype":"venue"
},
  "geometry": {"coordinates":[-117.19886099999999,33.145528],"type":"Point"}
}