{
  "type": "Feature",
  "properties": {
    "iso:country":"US",
    "sg:address":"10958 Ramona Blvd",
    "sg:city":"El Monte",
    "sg:classifiers":[
        {
            "category":"Health Services",
            "subcategory":"Chiropractor",
            "type":"Services"
        }
    ],
    "sg:phone":"+1 626 442 9922",
    "sg:postcode":"91731",
    "sg:province":"CA",
    "wof:name":"Ramona Urgent Chiropractic",
    "wof:placetype":"venue"
},
  "geometry": {"coordinates":[-118.034763,34.072053],"type":"Point"}
}