{
  "type": "Feature",
  "properties": {
    "addr:full":"10115 San Leandro St Oakland CA 94603",
    "addr:housenumber":"10115",
    "addr:postcode":"94603",
    "addr:street":"San Leandro St",
    "iso:country":"US",
    "sg:address":"10115 San Leandro St",
    "sg:city":"Oakland",
    "sg:classifiers":[
        {
            "category":"Home & Garden",
            "subcategory":"Carpets & Floor Coverings",
            "type":"Retail Goods"
        }
    ],
    "sg:phone":"+1 510 638 3200",
    "sg:postcode":"94603",
    "sg:province":"CA",
    "sg:tags":[
        "flooring",
        "carpeting"
    ],
    "sg:website":"www.capitalflooringanddesign.com",
    "wof:name":"Capital Flooring",
    "wof:placetype":"venue"
},
  "geometry": {"coordinates":[-122.177002,37.7374],"type":"Point"}
}