{
  "type": "Feature",
  "properties": {
    "addr:full":"1411 Walnut St San Gabriel CA 91776",
    "addr:housenumber":"1411",
    "addr:postcode":"91776",
    "addr:street":"Walnut St",
    "iso:country":"US",
    "sg:address":"1411 Walnut St",
    "sg:city":"San Gabriel",
    "sg:classifiers":[
        {
            "category":"Shopping",
            "subcategory":"Used Merchandise",
            "type":"Retail Goods"
        }
    ],
    "sg:phone":"+1 626 572 8299",
    "sg:postcode":"91776",
    "sg:province":"CA",
    "wof:name":"J J United Systems",
    "wof:placetype":"venue"
},
  "geometry": {"coordinates":[-118.094803,34.083375],"type":"Point"}
}