{
  "type": "Feature",
  "properties": {
    "iso:country":"US",
    "sg:address":"8657 Cherry Ave",
    "sg:city":"Fontana",
    "sg:classifiers":[
        {
            "category":"Freight",
            "type":"Transportation"
        }
    ],
    "sg:phone":"+1 909 822 1452",
    "sg:postcode":"92335",
    "sg:province":"CA",
    "sg:tags":[
        "operator",
        "local",
        "trucking"
    ],
    "wof:name":"Empire Charter",
    "wof:placetype":"venue"
},
  "geometry": {"coordinates":[-117.488738,34.096288],"type":"Point"}
}