{
  "type": "Feature",
  "properties": {
    "addr:full":"1327 W 228th St Torrance CA 90501",
    "addr:housenumber":"1327",
    "addr:postcode":"90501",
    "addr:street":"W 228Th St",
    "iso:country":"US",
    "sg:address":"1327 W 228th St",
    "sg:city":"Torrance",
    "sg:classifiers":[
        {
            "category":"Building & Trades",
            "subcategory":"Construction",
            "type":"Services"
        }
    ],
    "sg:phone":"+1 310 320 7333",
    "sg:postcode":"90501",
    "sg:province":"CA",
    "sg:tags":[
        "roofing",
        "contractor"
    ],
    "wof:name":"Butler Roofing Co",
    "wof:placetype":"venue"
},
  "geometry": {"coordinates":[-118.301464,33.819004],"type":"Point"}
}