{
  "type": "Feature",
  "properties": {
    "addr:full":"2090 Foothill Blvd La Verne CA 91750",
    "addr:housenumber":"2090",
    "addr:postcode":"91750",
    "addr:street":"Foothill Blvd",
    "iso:country":"US",
    "sg:address":"2090 Foothill Blvd",
    "sg:city":"La Verne",
    "sg:classifiers":[
        {
            "category":"Food & Beverages",
            "subcategory":"Groceries & Convenience Stores",
            "type":"Retail Goods"
        }
    ],
    "sg:phone":"+1 909 593 1591",
    "sg:postcode":"91750",
    "sg:province":"CA",
    "sg:tags":[
        "supermarket"
    ],
    "wof:name":"Stater Bros Markets",
    "wof:placetype":"venue"
},
  "geometry": {"coordinates":[-117.765479,34.113339],"type":"Point"}
}