{
  "type": "Feature",
  "properties": {
    "iso:country":"US",
    "sg:address":"215 Dore St",
    "sg:city":"San Francisco",
    "sg:classifiers":[
        {
            "category":"Wholesale",
            "subcategory":"Office Equipment",
            "type":"Manufacturing & Wholesale Goods"
        }
    ],
    "sg:phone":"+1 415 345 9077",
    "sg:postcode":"94103",
    "sg:province":"CA",
    "sg:tags":[
        "machine",
        "duplicating",
        "copying"
    ],
    "wof:name":"Bay Area Office Systems",
    "wof:placetype":"venue"
},
  "geometry": {"coordinates":[-122.409255,37.771049],"type":"Point"}
}