{
  "type": "Feature",
  "properties": {
    "addr:full":"6555 Hunter Dr Rohnert Park CA 94928",
    "addr:housenumber":"6555",
    "addr:postcode":"94928",
    "addr:street":"Hunter Dr",
    "iso:country":"US",
    "sg:address":"6555 Hunter Dr",
    "sg:city":"Rohnert Park",
    "sg:classifiers":[
        {
            "category":"Wholesale",
            "subcategory":"Electrical",
            "type":"Manufacturing & Wholesale Goods"
        }
    ],
    "sg:phone":"+1 707 542 1111",
    "sg:postcode":"94928",
    "sg:province":"CA",
    "sg:tags":[
        "alarm",
        "burglar",
        "system"
    ],
    "wof:name":"First Alarm",
    "wof:placetype":"venue"
},
  "geometry": {"coordinates":[-122.70927399999999,38.345739],"type":"Point"}
}