{
  "type": "Feature",
  "properties": {
    "addr:full":"4029 Westerly Pl Newport Beach CA 92660",
    "addr:housenumber":"4029",
    "addr:postcode":"92660",
    "addr:street":"Westerly Pl",
    "iso:country":"US",
    "sg:address":"4029 Westerly Pl",
    "sg:city":"Newport Beach",
    "sg:classifiers":[
        {
            "category":"Professional",
            "subcategory":"Computer Services",
            "type":"Services"
        }
    ],
    "sg:phone":"+1 949 222 0677",
    "sg:postcode":"92660",
    "sg:province":"CA",
    "sg:tags":[
        "repair"
    ],
    "wof:name":"A-Z Logic Systems",
    "wof:placetype":"venue"
},
  "geometry": {"coordinates":[-117.86783800000001,33.663924],"type":"Point"}
}