{
  "type": "Feature",
  "properties": {
    "iso:country":"US",
    "sg:address":"1773 E Palmdale Blvd",
    "sg:city":"Palmdale",
    "sg:classifiers":[
        {
            "category":"Shopping",
            "subcategory":"Jewelry",
            "type":"Retail Goods"
        }
    ],
    "sg:phone":"+1 661 267 0253",
    "sg:postcode":"93550",
    "sg:province":"CA",
    "sg:tags":[
        "jeweler"
    ],
    "wof:name":"Don Roberto Jewelers",
    "wof:placetype":"venue"
},
  "geometry": {"coordinates":[-118.097003,34.579752],"type":"Point"}
}