{
  "type": "Feature",
  "properties": {
    "addr:full":"25800 Carlos Bee Blvd On Cal State Hayward campus Hayward CA 94542",
    "addr:housenumber":"25800",
    "addr:postcode":"94542",
    "addr:street":"Carlos Bee Blvd",
    "iso:country":"US",
    "sg:address":"25800 Carlos Bee Blvd On Cal State Hayward campus",
    "sg:city":"Hayward",
    "sg:classifiers":[
        {
            "category":"Fast Food",
            "type":"Food & Drink"
        },
        {
            "category":"Restaurant",
            "type":"Food & Drink"
        }
    ],
    "sg:phone":"+1 510 885 4733",
    "sg:postcode":"94542",
    "sg:province":"CA",
    "sg:tags":[
        "chinese"
    ],
    "sg:website":"www.pandaexpress.com",
    "wof:name":"Panda Express",
    "wof:placetype":"venue"
},
  "geometry": {"coordinates":[-122.06193500000001,37.658759],"type":"Point"}
}