{
  "type": "Feature",
  "properties": {
    "addr:full":"3600 Wilshire Blvd Ste 2228 Los Angeles CA 90010",
    "addr:housenumber":"3600",
    "addr:postcode":"90010",
    "addr:street":"Wilshire Blvd Ste 2228",
    "iso:country":"US",
    "sg:address":"3600 Wilshire Blvd Ste 2228",
    "sg:city":"Los Angeles",
    "sg:classifiers":[
        {
            "category":"Professional",
            "subcategory":"Lawyer & Legal Services",
            "type":"Services"
        }
    ],
    "sg:phone":"+1 213 487 5700",
    "sg:postcode":"90010",
    "sg:province":"CA",
    "sg:website":"www.waynejoynerlaw.com",
    "wof:name":"Law Office of Wayne Joyner",
    "wof:placetype":"venue"
},
  "geometry": {"coordinates":[-118.303633,34.060664],"type":"Point"}
}