{
  "type": "Feature",
  "properties": {
    "iso:country":"US",
    "sg:address":"30591 Wood Duck Pl",
    "sg:city":"Canyon Lake",
    "sg:classifiers":[
        {
            "category":"Building & Trades",
            "subcategory":"Cleaning & Sanitation",
            "type":"Services"
        }
    ],
    "sg:phone":"+1 951 246 2019",
    "sg:postcode":"92587",
    "sg:province":"CA",
    "sg:tags":[
        "window"
    ],
    "wof:name":"Immaculate Windows",
    "wof:placetype":"venue"
},
  "geometry": {"coordinates":[-117.271511,33.676998],"type":"Point"}
}