{
  "type": "Feature",
  "properties": {
    "addr:full":"2322 Butano Dr Sacramento CA 95825",
    "addr:housenumber":"2322",
    "addr:postcode":"95825",
    "addr:street":"Butano Dr",
    "iso:country":"US",
    "sg:address":"2322 Butano Dr",
    "sg:city":"Sacramento",
    "sg:classifiers":[
        {
            "category":"Organizations",
            "subcategory":"Community Association",
            "type":"Services"
        }
    ],
    "sg:phone":"+1 916 489 6152",
    "sg:postcode":"95825",
    "sg:province":"CA",
    "sg:tags":[
        "club"
    ],
    "wof:name":"Country Club Professional Ctr",
    "wof:placetype":"venue"
},
  "geometry": {"coordinates":[-121.37942,38.607138],"type":"Point"}
}