{
  "type": "Feature",
  "properties": {
    "addr:full":"2902 Rubidoux Blvd Riverside CA 92509",
    "addr:housenumber":"2902",
    "addr:postcode":"92509",
    "addr:street":"Rubidoux Blvd",
    "iso:country":"US",
    "sg:address":"2902 Rubidoux Blvd",
    "sg:city":"Riverside",
    "sg:classifiers":[
        {
            "category":"Professional",
            "subcategory":"Accounting & Tax Preparation",
            "type":"Services"
        }
    ],
    "sg:phone":"+1 951 686 8068",
    "sg:postcode":"92509",
    "sg:province":"CA",
    "sg:tags":[
        "billing"
    ],
    "wof:name":"SCEC Medical Billing Svc",
    "wof:placetype":"venue"
},
  "geometry": {"coordinates":[-117.399568,34.005379],"type":"Point"}
}