{
  "type": "Feature",
  "properties": {
    "iso:country":"US",
    "sg:address":"353 W 9th Ave",
    "sg:city":"Escondido",
    "sg:classifiers":[
        {
            "category":"Real Estate",
            "subcategory":"Real Estate Agent",
            "type":"Services"
        }
    ],
    "sg:phone":"+1 760 741 4146",
    "sg:postcode":"92025",
    "sg:province":"CA",
    "sg:tags":[
        "appraiser"
    ],
    "wof:name":"Anderson & Brabant",
    "wof:placetype":"venue"
},
  "geometry": {"coordinates":[-117.079763,33.11271],"type":"Point"}
}