{
  "type": "Feature",
  "properties": {
    "addr:full":"13 S San Joaquin St Stockton CA 95202",
    "addr:housenumber":"13",
    "addr:postcode":"95202",
    "addr:street":"S San Joaquin St",
    "iso:country":"US",
    "sg:address":"13 S San Joaquin St",
    "sg:city":"Stockton",
    "sg:classifiers":[
        {
            "category":"Restaurant",
            "type":"Food & Drink"
        }
    ],
    "sg:phone":"+1 209 464 8941",
    "sg:postcode":"95202",
    "sg:province":"CA",
    "sg:tags":[
        "eating"
    ],
    "wof:name":"Blackwater Cafe Downtown Anx",
    "wof:placetype":"venue"
},
  "geometry": {"coordinates":[-121.287009,37.952267],"type":"Point"}
}