{
  "type": "Feature",
  "properties": {
    "iso:country":"US",
    "sg:address":"1942 Conifer Ln",
    "sg:city":"San Jose",
    "sg:classifiers":[
        {
            "category":"Freight",
            "type":"Transportation"
        }
    ],
    "sg:phone":"+1 408 205 2302",
    "sg:postcode":"95132",
    "sg:province":"CA",
    "sg:tags":[
        "operator",
        "local",
        "trucking"
    ],
    "wof:name":"Htk Trucking",
    "wof:placetype":"venue"
},
  "geometry": {"coordinates":[-121.863319,37.414237],"type":"Point"}
}