{
  "type": "Feature",
  "properties": {
    "iso:country":"US",
    "sg:address":"6245 N Fresno St",
    "sg:city":"Fresno",
    "sg:classifiers":[
        {
            "category":"Health Services",
            "subcategory":"Doctor",
            "type":"Services"
        }
    ],
    "sg:phone":"+1 559 440 0404",
    "sg:postcode":"93710",
    "sg:province":"CA",
    "sg:tags":[
        "dentist"
    ],
    "wof:name":"My First Tooth",
    "wof:placetype":"venue"
},
  "geometry": {"coordinates":[-119.781378,36.829378],"type":"Point"}
}