{
  "type": "Feature",
  "properties": {
    "addr:full":"611 W 6th St Los Angeles CA 90017",
    "addr:housenumber":"611",
    "addr:postcode":"90017",
    "addr:street":"W 6Th St",
    "iso:country":"US",
    "sg:address":"611 W 6th St",
    "sg:city":"Los Angeles",
    "sg:classifiers":[
        {
            "category":"Travel",
            "subcategory":"Hotels & Motels",
            "type":"Entertainment"
        }
    ],
    "sg:phone":"+1 661 295 9966",
    "sg:postcode":"90017",
    "sg:province":"CA",
    "sg:tags":[
        "management"
    ],
    "wof:name":"Halekulani Hotel",
    "wof:placetype":"venue"
},
  "geometry": {"coordinates":[-118.256203,34.049425],"type":"Point"}
}