{
  "type": "Feature",
  "properties": {
    "addr:full":"9311 Stevens Rd Santee CA 92071",
    "addr:housenumber":"9311",
    "addr:postcode":"92071",
    "addr:street":"Stevens Rd",
    "iso:country":"US",
    "sg:address":"9311 Stevens Rd",
    "sg:city":"Santee",
    "sg:classifiers":[
        {
            "category":"Health Services",
            "subcategory":"Health Practitioner",
            "type":"Services"
        }
    ],
    "sg:phone":"+1 619 596 5475",
    "sg:postcode":"92071",
    "sg:province":"CA",
    "sg:tags":[
        "control",
        "weight"
    ],
    "wof:name":"Kiosk Management Group",
    "wof:placetype":"venue"
},
  "geometry": {"coordinates":[-116.96281,32.844926],"type":"Point"}
}