{
  "type": "Feature",
  "properties": {
    "iso:country":"US",
    "sg:address":"18000 Sonoma Hwy",
    "sg:city":"Sonoma",
    "sg:classifiers":[
        {
            "category":"Building & Trades",
            "subcategory":"Landscaping Services",
            "type":"Services"
        }
    ],
    "sg:phone":"+1 707 568 5350",
    "sg:postcode":"95476",
    "sg:province":"CA",
    "sg:tags":[
        "landscape",
        "contractor"
    ],
    "wof:name":"Gutierrez Landscaping",
    "wof:placetype":"venue"
},
  "geometry": {"coordinates":[-122.481792,38.313912],"type":"Point"}
}