{
  "type": "Feature",
  "properties": {
    "addr:full":"41658 Ivy St Ste 110 Murrieta CA 92562",
    "addr:housenumber":"41658",
    "addr:postcode":"92562",
    "addr:street":"Ivy St Ste 110",
    "iso:country":"US",
    "sg:address":"41658 Ivy St Ste 110",
    "sg:city":"Murrieta",
    "sg:classifiers":[
        {
            "category":"Education",
            "subcategory":"Special Training",
            "type":"Public Place"
        },
        {
            "category":"Arena",
            "subcategory":"Sports Club",
            "type":"Entertainment"
        }
    ],
    "sg:phone":"+1 951 265 3922",
    "sg:postcode":"92562",
    "sg:province":"CA",
    "sg:tags":[
        "instruction",
        "equipment",
        "self defense",
        "martial art"
    ],
    "wof:name":"Southwest Self Defense Systems",
    "wof:placetype":"venue"
},
  "geometry": {"coordinates":[-117.207025,33.554232],"type":"Point"}
}