{
  "type": "Feature",
  "properties": {
    "addr:full":"20800 Homestead Road Ofc Cupertino CA 95014",
    "addr:housenumber":"20800",
    "addr:postcode":"95014",
    "addr:street":"Homestead Road",
    "iso:country":"US",
    "sg:address":"20800 Homestead Road Ofc",
    "sg:city":"Cupertino",
    "sg:classifiers":[
        {
            "category":"Real Estate",
            "subcategory":"Real Estate Operator",
            "type":"Services"
        }
    ],
    "sg:phone":"+1 408 257 1060",
    "sg:postcode":"95014",
    "sg:province":"CA",
    "sg:tags":[
        "apartment"
    ],
    "wof:name":"Villa Serra Garden Apartments",
    "wof:placetype":"venue"
},
  "geometry": {"coordinates":[-122.060756,37.337369],"type":"Point"}
}