{
  "type": "Feature",
  "properties": {
    "addr:full":"1500 E Villa St Pasadena CA 91106",
    "addr:housenumber":"1500",
    "addr:postcode":"91106",
    "addr:street":"E Villa St",
    "iso:country":"US",
    "sg:address":"1500 E Villa St",
    "sg:city":"Pasadena",
    "sg:classifiers":[
        {
            "category":"Education",
            "subcategory":"School",
            "type":"Public Place"
        }
    ],
    "sg:phone":"+1 626 796 8845",
    "sg:postcode":"91106",
    "sg:province":"CA",
    "sg:tags":[
        "high",
        "middle",
        "elementary"
    ],
    "wof:name":"Jefferson Children's Center",
    "wof:placetype":"venue"
},
  "geometry": {"coordinates":[-118.11900300000001,34.154202],"type":"Point"}
}