{
  "type": "Feature",
  "properties": {
    "addr:full":"1653 2nd St San Rafael CA 94901",
    "addr:housenumber":"1653",
    "addr:postcode":"94901",
    "addr:street":"2Nd St",
    "iso:country":"US",
    "sg:address":"1653 2nd St",
    "sg:city":"San Rafael",
    "sg:classifiers":[
        {
            "category":"Building & Trades",
            "subcategory":"Landscaping Services",
            "type":"Services"
        }
    ],
    "sg:phone":"+1 415 456 8706",
    "sg:postcode":"94901",
    "sg:province":"CA",
    "sg:tags":[
        "landscape"
    ],
    "wof:name":"Cole Henry Landscape Architect",
    "wof:placetype":"venue"
},
  "geometry": {"coordinates":[-122.53814,37.972915],"type":"Point"}
}