{
  "type": "Feature",
  "properties": {
    "iso:country":"US",
    "sg:address":"870 N Highway 173",
    "sg:city":"Lake Arrowhead",
    "sg:classifiers":[
        {
            "category":"Restaurant",
            "type":"Food & Drink"
        }
    ],
    "sg:phone":"+1 909 337 7169",
    "sg:postcode":"92352",
    "sg:province":"CA",
    "wof:name":"Nana's On the Lake",
    "wof:placetype":"venue"
},
  "geometry": {"coordinates":[-117.193001,34.268299],"type":"Point"}
}