{
  "type": "Feature",
  "properties": {
    "iso:country":"US",
    "sg:address":"8200 Kern Ave Apt J107",
    "sg:city":"Gilroy",
    "sg:classifiers":[
        {
            "category":"Building & Trades",
            "subcategory":"Construction",
            "type":"Services"
        }
    ],
    "sg:phone":"+1 408 612 7163",
    "sg:postcode":"95020",
    "sg:province":"CA",
    "sg:tags":[
        "system",
        "contractor",
        "air conditioning"
    ],
    "wof:name":"D&D Heat & A/C",
    "wof:placetype":"venue"
},
  "geometry": {"coordinates":[-121.591576,37.016113],"type":"Point"}
}