{
  "type": "Feature",
  "properties": {
    "addr:full":"711 Debra St Livermore CA 94550",
    "addr:housenumber":"711",
    "addr:postcode":"94550",
    "addr:street":"Debra St",
    "iso:country":"US",
    "sg:address":"711 Debra St",
    "sg:city":"Livermore",
    "sg:classifiers":[
        {
            "category":"Building & Trades",
            "subcategory":"Construction",
            "type":"Services"
        }
    ],
    "sg:phone":"+1 925 447 6012",
    "sg:postcode":"94550",
    "sg:province":"CA",
    "sg:tags":[
        "concrete",
        "contractor"
    ],
    "wof:name":"Dunmeyer Concrete",
    "wof:placetype":"venue"
},
  "geometry": {"coordinates":[-121.730458,37.68918],"type":"Point"}
}