{
  "type": "Feature",
  "properties": {
    "iso:country":"US",
    "sg:address":"1170 W 11th St",
    "sg:city":"Tracy",
    "sg:classifiers":[
        {
            "category":"Banks & Credit Unions",
            "subcategory":"Bank",
            "type":"Services"
        }
    ],
    "sg:phone":"+1 209 832 3600",
    "sg:postcode":"95376",
    "sg:province":"CA",
    "sg:tags":[
        "personal",
        "financing",
        "institution"
    ],
    "wof:name":"American General Finance Corp",
    "wof:placetype":"venue"
},
  "geometry": {"coordinates":[-121.440254,37.739633],"type":"Point"}
}