{
  "type": "Feature",
  "properties": {
    "addr:full":"970 Blossom Hill Rd San Jose CA 95123",
    "addr:housenumber":"970",
    "addr:postcode":"95123",
    "addr:street":"Blossom Hill Rd",
    "iso:country":"US",
    "sg:address":"970 Blossom Hill Rd",
    "sg:city":"San Jose",
    "sg:classifiers":[
        {
            "category":"Autos & Motor Vehicles",
            "subcategory":"Auto Supplies",
            "type":"Retail Goods"
        }
    ],
    "sg:phone":"+1 408 226 0745",
    "sg:postcode":"95123",
    "sg:province":"CA",
    "sg:tags":[
        "tire"
    ],
    "wof:name":"Blossom Hill Goodyear",
    "wof:placetype":"venue"
},
  "geometry": {"coordinates":[-121.866997,37.250401],"type":"Point"}
}