{
  "type": "Feature",
  "properties": {
    "addr:full":"9027 Florence Ave Downey CA 90240",
    "addr:housenumber":"9027",
    "addr:postcode":"90240",
    "addr:street":"Florence Ave",
    "iso:country":"US",
    "sg:address":"9027 Florence Ave",
    "sg:city":"Downey",
    "sg:classifiers":[
        {
            "category":"Professional",
            "subcategory":"Management & Consulting",
            "type":"Services"
        }
    ],
    "sg:phone":"+1 562 622 7714",
    "sg:postcode":"90240",
    "sg:province":"CA",
    "sg:tags":[
        "consultant",
        "security",
        "system"
    ],
    "wof:name":"Pacific Security Mgmt",
    "wof:placetype":"venue"
},
  "geometry": {"coordinates":[-118.11626099999999,33.947147],"type":"Point"}
}