{
  "type": "Feature",
  "properties": {
    "addr:full":"125 E Prospect Ave Burbank CA 91502",
    "addr:housenumber":"125",
    "addr:postcode":"91502",
    "addr:street":"E Prospect Ave",
    "iso:country":"US",
    "sg:address":"125 E Prospect Ave",
    "sg:city":"Burbank",
    "sg:classifiers":[
        {
            "category":"Building & Trades",
            "subcategory":"Construction",
            "type":"Services"
        }
    ],
    "sg:phone":"+1 818 972 9605",
    "sg:postcode":"91502",
    "sg:province":"CA",
    "sg:tags":[
        "roofing",
        "contractor"
    ],
    "wof:name":"Robert L Truskett Roofing",
    "wof:placetype":"venue"
},
  "geometry": {"coordinates":[-118.299583,34.173661],"type":"Point"}
}