{
  "type": "Feature",
  "properties": {
    "iso:country":"US",
    "sg:address":"1139 W Brooks St",
    "sg:city":"Ontario",
    "sg:classifiers":[
        {
            "category":"Manufacturing",
            "subcategory":"Metals",
            "type":"Manufacturing & Wholesale Goods"
        }
    ],
    "sg:phone":"+1 909 391 2439",
    "sg:postcode":"91762",
    "sg:province":"CA",
    "sg:tags":[
        "product",
        "wire"
    ],
    "wof:name":"Wire Works Fab",
    "wof:placetype":"venue"
},
  "geometry": {"coordinates":[-117.676372,34.061818],"type":"Point"}
}