{
  "type": "Feature",
  "properties": {
    "addr:full":"3749 Gondar Ave Long Beach CA 90808",
    "addr:housenumber":"3749",
    "addr:postcode":"90808",
    "addr:street":"Gondar Ave",
    "iso:country":"US",
    "sg:address":"3749 Gondar Ave",
    "sg:city":"Long Beach",
    "sg:classifiers":[
        {
            "category":"Education",
            "subcategory":"Vocational School",
            "type":"Public Place"
        }
    ],
    "sg:phone":"+1 562 425 4450",
    "sg:postcode":"90808",
    "sg:province":"CA",
    "sg:tags":[
        "training",
        "computer"
    ],
    "wof:name":"Bolt Computer Training",
    "wof:placetype":"venue"
},
  "geometry": {"coordinates":[-118.11306,33.82608],"type":"Point"}
}