{
  "type": "Feature",
  "properties": {
    "iso:country":"US",
    "sg:address":"30550 Rancho California Rd",
    "sg:city":"Temecula",
    "sg:classifiers":[
        {
            "category":"Personal",
            "subcategory":"Beauty Salon",
            "type":"Services"
        }
    ],
    "sg:phone":"+1 951 676 4845",
    "sg:postcode":"92591",
    "sg:province":"CA",
    "wof:name":"Designers Cut II",
    "wof:placetype":"venue"
},
  "geometry": {"coordinates":[-117.127494,33.508573],"type":"Point"}
}