{
  "type": "Feature",
  "properties": {
    "iso:country":"US",
    "sg:address":"1283 E Main St",
    "sg:city":"El Cajon",
    "sg:classifiers":[
        {
            "category":"Professional",
            "subcategory":"Accounting & Tax Preparation",
            "type":"Services"
        }
    ],
    "sg:phone":"+1 619 447 8800",
    "sg:postcode":"92021",
    "sg:province":"CA",
    "sg:tags":[
        "bookkeeping",
        "general"
    ],
    "wof:name":"Business World",
    "wof:placetype":"venue"
},
  "geometry": {"coordinates":[-116.935964,32.795289],"type":"Point"}
}