{
  "type": "Feature",
  "properties": {
    "addr:full":"3742 N Blackstone Ave Fresno CA 93726",
    "addr:housenumber":"3742",
    "addr:postcode":"93726",
    "addr:street":"N Blackstone Ave",
    "iso:country":"US",
    "sg:address":"3742 N Blackstone Ave",
    "sg:city":"Fresno",
    "sg:classifiers":[
        {
            "category":"Real Estate",
            "subcategory":"Real Estate Operator",
            "type":"Services"
        }
    ],
    "sg:phone":"+1 559 222 9181",
    "sg:postcode":"93726",
    "sg:province":"CA",
    "sg:tags":[
        "mall",
        "shopping",
        "center"
    ],
    "wof:name":"Manchester North Shopping Ctr",
    "wof:placetype":"venue"
},
  "geometry": {"coordinates":[-119.790453,36.785997],"type":"Point"}
}