{
  "type": "Feature",
  "properties": {
    "addr:full":"26980 McCall Blvd Sun City CA 92586",
    "addr:housenumber":"26980",
    "addr:postcode":"92586",
    "addr:street":"Mccall Blvd",
    "iso:country":"US",
    "sg:address":"26980 McCall Blvd",
    "sg:city":"Sun City",
    "sg:classifiers":[
        {
            "category":"Government",
            "subcategory":"Office",
            "type":"Public Place"
        }
    ],
    "sg:phone":"+1 951 672 9886",
    "sg:postcode":"92586",
    "sg:province":"CA",
    "sg:tags":[
        "management"
    ],
    "wof:name":"Cherry Hills Unocal",
    "wof:placetype":"venue"
},
  "geometry": {"coordinates":[-117.18736,33.715196],"type":"Point"}
}