{
  "type": "Feature",
  "properties": {
    "iso:country":"US",
    "sg:address":"646 Marlin Ct",
    "sg:city":"Redwood City",
    "sg:classifiers":[
        {
            "category":"Shopping",
            "subcategory":"Musical Instruments",
            "type":"Retail Goods"
        }
    ],
    "sg:phone":"+1 650 595 4277",
    "sg:postcode":"94065",
    "sg:province":"CA",
    "wof:name":"Safari Harp Music",
    "wof:placetype":"venue"
},
  "geometry": {"coordinates":[-122.249628,37.535487],"type":"Point"}
}