{
  "type": "Feature",
  "properties": {
    "iso:country":"US",
    "sg:address":"713 Seagaze Dr",
    "sg:city":"Oceanside",
    "sg:classifiers":[
        {
            "category":"Health Services",
            "subcategory":"Dentist",
            "type":"Services"
        }
    ],
    "sg:phone":"+1 760 721 1552",
    "sg:postcode":"92054",
    "sg:province":"CA",
    "sg:tags":[
        "orthodontist"
    ],
    "sg:website":"www.minnichorthodontics.com",
    "wof:name":"Minnich Michael D DDS Ms",
    "wof:placetype":"venue"
},
  "geometry": {"coordinates":[-117.376999,33.196301],"type":"Point"}
}