{
  "type": "Feature",
  "properties": {
    "iso:country":"US",
    "sg:address":"319 Rianda St",
    "sg:city":"Salinas",
    "sg:classifiers":[
        {
            "category":"Autos & Motor Vehicles",
            "subcategory":"Automobile Sales",
            "type":"Retail Goods"
        }
    ],
    "sg:phone":"+1 831 422 2122",
    "sg:postcode":"93901",
    "sg:province":"CA",
    "sg:tags":[
        "car",
        "dealer"
    ],
    "wof:name":"Warehouse Auto Sales",
    "wof:placetype":"venue"
},
  "geometry": {"coordinates":[-121.642937,36.675792],"type":"Point"}
}