{
  "type": "Feature",
  "properties": {
    "iso:country":"US",
    "sg:address":"15363 Goldenwest Street",
    "sg:city":"Huntington Beach",
    "sg:classifiers":[
        {
            "category":"Real Estate",
            "subcategory":"Real Estate Operator",
            "type":"Services"
        }
    ],
    "sg:phone":"+1 714 892 5217",
    "sg:postcode":"92647",
    "sg:province":"CA",
    "sg:tags":[
        "apartment"
    ],
    "wof:name":"Hermosa Vista Apts",
    "wof:placetype":"venue"
},
  "geometry": {"coordinates":[-118.006883,33.738275],"type":"Point"}
}