{
  "type": "Feature",
  "properties": {
    "iso:country":"US",
    "sg:address":"7411 Co Rd 25",
    "sg:city":"Orland",
    "sg:classifiers":[
        {
            "category":"Farming",
            "subcategory":"Crops",
            "type":"Manufacturing & Wholesale Goods"
        }
    ],
    "sg:phone":"+1 530 865 2441",
    "sg:postcode":"95963",
    "sg:province":"CA",
    "sg:tags":[
        "grove",
        "nut",
        "tree"
    ],
    "wof:name":"James Coleman",
    "wof:placetype":"venue"
},
  "geometry": {"coordinates":[-122.09576800000001,39.695859],"type":"Point"}
}