{
  "type": "Feature",
  "properties": {
    "iso:country":"US",
    "sg:address":"8 Maison",
    "sg:city":"Irvine",
    "sg:classifiers":[
        {
            "category":"Professional",
            "subcategory":"Computer Services",
            "type":"Services"
        }
    ],
    "sg:phone":"+1 949 458 6400",
    "sg:postcode":"92656",
    "sg:province":"CA",
    "sg:tags":[
        "prepackaged",
        "software"
    ],
    "wof:name":"ONeil Printer Supplies",
    "wof:placetype":"venue"
},
  "geometry": {"coordinates":[-117.734824,33.577531],"type":"Point"}
}