{
  "type": "Feature",
  "properties": {
    "addr:full":"932 E Alosta Ave Azusa CA 91702",
    "addr:housenumber":"932",
    "addr:postcode":"91702",
    "addr:street":"E Alosta Ave",
    "iso:country":"US",
    "sg:address":"932 E Alosta Ave",
    "sg:city":"Azusa",
    "sg:classifiers":[
        {
            "category":"Restaurant",
            "type":"Food & Drink"
        }
    ],
    "sg:phone":"+1 626 969 2181",
    "sg:postcode":"91702",
    "sg:province":"CA",
    "wof:name":"Chinese Taste Azusa",
    "wof:placetype":"venue"
},
  "geometry": {"coordinates":[-117.88575299999999,34.12865],"type":"Point"}
}