{
  "type": "Feature",
  "properties": {
    "addr:full":"329 S Santa Fe Ave Visalia CA 93292",
    "addr:housenumber":"329",
    "addr:postcode":"93292",
    "addr:street":"S Santa Fe Ave",
    "iso:country":"US",
    "sg:address":"329 S Santa Fe Ave",
    "sg:city":"Visalia",
    "sg:classifiers":[
        {
            "category":"Retail",
            "subcategory":"Auto Repair",
            "type":"Services"
        }
    ],
    "sg:phone":"+1 559 625 5699",
    "sg:postcode":"93292",
    "sg:province":"CA",
    "sg:tags":[
        "repairing",
        "automobile"
    ],
    "wof:name":"Omega Auto Repair",
    "wof:placetype":"venue"
},
  "geometry": {"coordinates":[-119.287869,36.327717],"type":"Point"}
}