{
  "type": "Feature",
  "properties": {
    "addr:full":"10201 Blue Sky Dr Ione CA 95640",
    "addr:housenumber":"10201",
    "addr:postcode":"ca 95640",
    "addr:street":"Blue Sky Dr",
    "iso:country":"US",
    "sg:address":"10201 Blue Sky Dr",
    "sg:city":"Ione",
    "sg:classifiers":[
        {
            "category":"Wholesale",
            "subcategory":"Non-durable Goods",
            "type":"Manufacturing & Wholesale Goods"
        },
        {
            "category":"Personal",
            "subcategory":"Barber",
            "type":"Services"
        }
    ],
    "sg:phone":"+1 209 274 0831",
    "sg:postcode":"95640",
    "sg:province":"CA",
    "sg:tags":[
        "beauty",
        "supply",
        "equipment",
        "salons-equipment",
        "supplies-wholesale",
        "manufacturer"
    ],
    "wof:name":"Sally & Kevin Bligh",
    "wof:placetype":"venue"
},
  "geometry": {"coordinates":[-120.878891,38.357712],"type":"Point"}
}