{
  "type": "Feature",
  "properties": {
    "iso:country":"US",
    "sg:address":"21515 S Western Ave",
    "sg:city":"Torrance",
    "sg:classifiers":[
        {
            "category":"Shopping",
            "subcategory":"Books",
            "type":"Retail Goods"
        }
    ],
    "sg:phone":"+1 310 787 0700",
    "sg:postcode":"90501",
    "sg:province":"CA",
    "sg:tags":[
        "bookstore"
    ],
    "wof:name":"Asahiya Book Stores USA Inc",
    "wof:placetype":"venue"
},
  "geometry": {"coordinates":[-118.308998,33.833302],"type":"Point"}
}