{
  "type": "Feature",
  "properties": {
    "iso:country":"US",
    "sg:address":"1111 Baker St",
    "sg:city":"Costa Mesa",
    "sg:classifiers":[
        {
            "category":"Building & Trades",
            "subcategory":"Landscaping Services",
            "type":"Services"
        }
    ],
    "sg:phone":"+1 714 427 6130",
    "sg:postcode":"92626",
    "sg:province":"CA",
    "wof:name":"Silverwood Landscape Construction Inc",
    "wof:placetype":"venue"
},
  "geometry": {"coordinates":[-117.903809,33.679482],"type":"Point"}
}