{
  "type": "Feature",
  "properties": {
    "addr:full":"439 Main St El Segundo CA 90245",
    "addr:housenumber":"439",
    "addr:postcode":"90245",
    "addr:street":"Main St",
    "iso:country":"US",
    "sg:address":"439 Main St",
    "sg:city":"El Segundo",
    "sg:classifiers":[
        {
            "category":"Restaurant",
            "type":"Food & Drink"
        }
    ],
    "sg:phone":"+1 310 322 3163",
    "sg:postcode":"90245",
    "sg:province":"CA",
    "wof:name":"Canton Low Restaurant",
    "wof:placetype":"venue"
},
  "geometry": {"coordinates":[-118.416,33.922199],"type":"Point"}
}