{
  "type": "Feature",
  "properties": {
    "iso:country":"US",
    "sg:address":"6759 Mesa Ridge Rd",
    "sg:city":"San Diego",
    "sg:classifiers":[
        {
            "category":"Wholesale",
            "subcategory":"Electrical",
            "type":"Manufacturing & Wholesale Goods"
        }
    ],
    "sg:phone":"+1 858 200 3100",
    "sg:postcode":"92121",
    "sg:province":"CA",
    "sg:tags":[
        "equipment",
        "or",
        "telephone",
        "telegraphic"
    ],
    "sg:website":"www.daycom.com",
    "wof:name":"Daycom Systems Inc",
    "wof:placetype":"venue"
},
  "geometry": {"coordinates":[-117.17457,32.901637],"type":"Point"}
}