{
  "type": "Feature",
  "properties": {
    "addr:full":"434 N Jennifer Way Porterville CA 93257",
    "addr:housenumber":"434",
    "addr:postcode":"93257",
    "addr:street":"N Jennifer Way",
    "iso:country":"US",
    "sg:address":"434 N Jennifer Way",
    "sg:city":"Porterville",
    "sg:classifiers":[
        {
            "category":"Wholesale",
            "subcategory":"Vending Machines",
            "type":"Manufacturing & Wholesale Goods"
        }
    ],
    "sg:phone":"+1 559 782 1103",
    "sg:postcode":"93257",
    "sg:province":"CA",
    "sg:tags":[
        "operator"
    ],
    "wof:name":"Pop's Vending",
    "wof:placetype":"venue"
},
  "geometry": {"coordinates":[-119.071472,36.073908],"type":"Point"}
}