{
  "type": "Feature",
  "properties": {
    "addr:full":"1590 E Jefferson Ave Reedley CA 93654",
    "addr:housenumber":"1590",
    "addr:postcode":"93654",
    "addr:street":"E Jefferson Ave",
    "iso:country":"US",
    "sg:address":"1590 E Jefferson Ave",
    "sg:city":"Reedley",
    "sg:classifiers":[
        {
            "category":"Freight",
            "type":"Transportation"
        }
    ],
    "sg:phone":"+1 559 638 4257",
    "sg:postcode":"93654",
    "sg:province":"CA",
    "sg:tags":[
        "operator",
        "local",
        "trucking"
    ],
    "wof:name":"Estrada R & L Trucking",
    "wof:placetype":"venue"
},
  "geometry": {"coordinates":[-119.43173400000001,36.592511],"type":"Point"}
}