{
  "type": "Feature",
  "properties": {
    "iso:country":"US",
    "sg:address":"12323 Poway Rd",
    "sg:city":"Poway",
    "sg:classifiers":[
        {
            "category":"Shopping",
            "subcategory":"Clothing, Apparel, & Fashions",
            "type":"Retail Goods"
        }
    ],
    "sg:phone":"+1 858 486 5439",
    "sg:postcode":"92064",
    "sg:province":"CA",
    "sg:tags":[
        "alteration"
    ],
    "wof:name":"Poway Alteration Ctr",
    "wof:placetype":"venue"
},
  "geometry": {"coordinates":[-117.065856,32.951379],"type":"Point"}
}