{
  "type": "Feature",
  "properties": {
    "iso:country":"US",
    "sg:address":"6429 24th St",
    "sg:city":"Rio Linda",
    "sg:classifiers":[
        {
            "category":"Building & Trades",
            "subcategory":"Construction",
            "type":"Services"
        }
    ],
    "sg:phone":"+1 916 991 5292",
    "sg:postcode":"95673",
    "sg:province":"CA",
    "sg:tags":[
        "contractor"
    ],
    "wof:name":"AAA Roofing & Sons",
    "wof:placetype":"venue"
},
  "geometry": {"coordinates":[-121.410687,38.688662],"type":"Point"}
}