{
  "type": "Feature",
  "properties": {
    "iso:country":"US",
    "sg:address":"300 Military W",
    "sg:city":"Benicia",
    "sg:classifiers":[
        {
            "category":"Health Services",
            "subcategory":"Doctor",
            "type":"Services"
        }
    ],
    "sg:phone":"+1 707 745 8344",
    "sg:postcode":"94510",
    "sg:province":"CA",
    "sg:tags":[
        "dentist"
    ],
    "wof:name":"Sean Mong DDS",
    "wof:placetype":"venue"
},
  "geometry": {"coordinates":[-122.16384,38.057572],"type":"Point"}
}