{
  "type": "Feature",
  "properties": {
    "iso:country":"US",
    "sg:address":"827 N Main St",
    "sg:city":"Orange",
    "sg:classifiers":[
        {
            "category":"Manufacturing",
            "subcategory":"Electronics",
            "type":"Manufacturing & Wholesale Goods"
        }
    ],
    "sg:phone":"+1 714 516 1790",
    "sg:postcode":"92868",
    "sg:province":"CA",
    "sg:tags":[
        "electronic",
        "component",
        "mfg"
    ],
    "wof:name":"Covalence Technology Inc",
    "wof:placetype":"venue"
},
  "geometry": {"coordinates":[-117.866506,33.800513],"type":"Point"}
}