{
  "type": "Feature",
  "properties": {
    "addr:full":"13445 Tall Oak Pl Nevada City CA 95959",
    "addr:housenumber":"13445",
    "addr:postcode":"95959",
    "addr:street":"Tall Oak Pl",
    "iso:country":"US",
    "sg:address":"13445 Tall Oak Pl",
    "sg:city":"Nevada City",
    "sg:classifiers":[
        {
            "category":"Manufacturing",
            "subcategory":"Printing",
            "type":"Manufacturing & Wholesale Goods"
        }
    ],
    "sg:phone":"+1 530 265 0236",
    "sg:postcode":"95959",
    "sg:province":"CA",
    "sg:tags":[
        "publisher"
    ],
    "wof:name":"NAP",
    "wof:placetype":"venue"
},
  "geometry": {"coordinates":[-120.939189,39.2833],"type":"Point"}
}