{
  "type": "Feature",
  "properties": {
    "addr:full":"13 Evanswood Cir Oroville CA 95965",
    "addr:housenumber":"13",
    "addr:postcode":"95965",
    "addr:street":"Evanswood Cir",
    "iso:country":"US",
    "sg:address":"13 Evanswood Cir",
    "sg:city":"Oroville",
    "sg:classifiers":[
        {
            "category":"Real Estate",
            "subcategory":"Real Estate Operator",
            "type":"Services"
        }
    ],
    "sg:phone":"+1 530 533 5580",
    "sg:postcode":"95965",
    "sg:province":"CA",
    "sg:tags":[
        "apartment"
    ],
    "wof:name":"Rsc Associates",
    "wof:placetype":"venue"
},
  "geometry": {"coordinates":[-121.566647,39.529762],"type":"Point"}
}