{
  "type": "Feature",
  "properties": {
    "addr:full":"2003 Mission Ave Oceanside CA 92054",
    "addr:housenumber":"2003",
    "addr:postcode":"92054",
    "addr:street":"Mission Ave",
    "iso:country":"US",
    "sg:address":"2003 Mission Ave",
    "sg:city":"Oceanside",
    "sg:classifiers":[
        {
            "category":"Autos & Motor Vehicles",
            "subcategory":"Fuel & Gas Station",
            "type":"Retail Goods"
        },
        {
            "category":"Government",
            "subcategory":"Office",
            "type":"Public Place"
        }
    ],
    "sg:phone":"+1 760 721 3797",
    "sg:postcode":"92054",
    "sg:province":"CA",
    "sg:tags":[
        "smog",
        "check"
    ],
    "wof:name":"Unocal 76",
    "wof:placetype":"venue"
},
  "geometry": {"coordinates":[-117.363998,33.204399],"type":"Point"}
}