{
  "type": "Feature",
  "properties": {
    "iso:country":"US",
    "sg:address":"105 E Jones St",
    "sg:city":"Santa Maria",
    "sg:classifiers":[
        {
            "category":"Shopping",
            "subcategory":"Clothing, Apparel, & Fashions",
            "type":"Retail Goods"
        }
    ],
    "sg:phone":"+1 805 928 2957",
    "sg:postcode":"93454",
    "sg:province":"CA",
    "sg:tags":[
        "alteration"
    ],
    "wof:name":"Santa Maria Alteration",
    "wof:placetype":"venue"
},
  "geometry": {"coordinates":[-120.435226,34.945973],"type":"Point"}
}