{
  "type": "Feature",
  "properties": {
    "iso:country":"US",
    "sg:address":"11052 New River Cir",
    "sg:city":"Rancho Cordova",
    "sg:classifiers":[
        {
            "category":"Social Services",
            "subcategory":"Child Care",
            "type":"Services"
        },
        {
            "category":"Education",
            "subcategory":"Preschool",
            "type":"Public Place"
        },
        {
            "category":"Education",
            "subcategory":"School",
            "type":"Public Place"
        }
    ],
    "sg:phone":"+1 916 635 4085",
    "sg:postcode":"95670",
    "sg:province":"CA",
    "sg:tags":[
        "elementary",
        "day"
    ],
    "wof:name":"THE LEARNING YEARS ACADEMY",
    "wof:placetype":"venue"
},
  "geometry": {"coordinates":[-121.276042,38.617689],"type":"Point"}
}