{
  "type": "Feature",
  "properties": {
    "addr:full":"1400 Webster St Alameda CA 94501",
    "addr:housenumber":"1400",
    "addr:postcode":"94501",
    "addr:street":"Webster St",
    "iso:country":"US",
    "sg:address":"1400 Webster St",
    "sg:city":"Alameda",
    "sg:classifiers":[
        {
            "category":"Restaurant",
            "type":"Food & Drink"
        }
    ],
    "sg:phone":"+1 510 865 6563",
    "sg:postcode":"94501",
    "sg:province":"CA",
    "sg:tags":[
        "pizza"
    ],
    "wof:name":"Croll's Pizza",
    "wof:placetype":"venue"
},
  "geometry": {"coordinates":[-122.276848,37.771431],"type":"Point"}
}