{
  "type": "Feature",
  "properties": {
    "iso:country":"US",
    "sg:address":"1485 E Walnut St",
    "sg:city":"Pasadena",
    "sg:classifiers":[
        {
            "category":"Retail",
            "subcategory":"Auto Repair",
            "type":"Services"
        }
    ],
    "sg:phone":"+1 626 568 3876",
    "sg:postcode":"91106",
    "sg:province":"CA",
    "wof:name":"Euro Motor Group",
    "wof:placetype":"venue"
},
  "geometry": {"coordinates":[-118.11971800000001,34.149668],"type":"Point"}
}