{
  "type": "Feature",
  "properties": {
    "addr:full":"18743 Pioneer Blvd # 203 Artesia CA 90701",
    "addr:housenumber":"18743",
    "addr:postcode":"90701",
    "addr:street":"Pioneer Blvd # 203",
    "iso:country":"US",
    "sg:address":"18743 Pioneer Blvd # 203",
    "sg:city":"Artesia",
    "sg:classifiers":[
        {
            "category":"Health Services",
            "subcategory":"Chiropractor",
            "type":"Services"
        }
    ],
    "sg:phone":"+1 562 860 3183",
    "sg:postcode":"90701",
    "sg:province":"CA",
    "sg:tags":[
        "chiropractic"
    ],
    "wof:name":"Michael Fu Chiropractic",
    "wof:placetype":"venue"
},
  "geometry": {"coordinates":[-118.08213000000001,33.860216],"type":"Point"}
}