{
  "type": "Feature",
  "properties": {
    "addr:full":"503 Spruce St Aptos CA 95003",
    "addr:housenumber":"503",
    "addr:postcode":"ca 95003",
    "addr:street":"Spruce St",
    "iso:country":"US",
    "sg:address":"503 Spruce St",
    "sg:city":"Aptos",
    "sg:classifiers":[
        {
            "category":"Building & Trades",
            "subcategory":"Plumbing",
            "type":"Services"
        }
    ],
    "sg:phone":"+1 831 688 6969",
    "sg:postcode":"95003",
    "sg:province":"CA",
    "sg:tags":[
        "contractor"
    ],
    "wof:name":"Dinnell Plumbing",
    "wof:placetype":"venue"
},
  "geometry": {"coordinates":[-121.91726199999999,36.97802],"type":"Point"}
}