{
  "type": "Feature",
  "properties": {
    "addr:full":"3419 Valle Verde Dr Napa CA 94558",
    "addr:housenumber":"3419",
    "addr:postcode":"94558",
    "addr:street":"Valle Verde Dr",
    "iso:country":"US",
    "sg:address":"3419 Valle Verde Dr",
    "sg:city":"Napa",
    "sg:classifiers":[
        {
            "category":"Health Services",
            "subcategory":"Doctor",
            "type":"Services"
        }
    ],
    "sg:phone":"+1 707 252 1035",
    "sg:postcode":"94558",
    "sg:province":"CA",
    "sg:tags":[
        "physician",
        "surgeon"
    ],
    "wof:name":"M J Harrington MD",
    "wof:placetype":"venue"
},
  "geometry": {"coordinates":[-122.292315,38.325342],"type":"Point"}
}