{
  "type": "Feature",
  "properties": {
    "addr:full":"12538 Chetenham Ln San Diego CA 92128",
    "addr:housenumber":"12538",
    "addr:postcode":"92128",
    "addr:street":"Chetenham Ln",
    "iso:country":"US",
    "sg:address":"12538 Chetenham Ln",
    "sg:city":"San Diego",
    "sg:classifiers":[
        {
            "category":"Professional",
            "subcategory":"Management & Consulting",
            "type":"Services"
        }
    ],
    "sg:phone":"+1 858 675 0004",
    "sg:postcode":"92128",
    "sg:province":"CA",
    "sg:tags":[
        "consultant",
        "business"
    ],
    "wof:name":"Beaulieu Enterprises",
    "wof:placetype":"venue"
},
  "geometry": {"coordinates":[-117.06351600000001,33.047548],"type":"Point"}
}