{
  "type": "Feature",
  "properties": {
    "iso:country":"US",
    "sg:address":"590 3rd Ave",
    "sg:city":"Chula Vista",
    "sg:classifiers":[
        {
            "category":"Government",
            "subcategory":"Office",
            "type":"Public Place"
        }
    ],
    "sg:phone":"+1 619 238 8158",
    "sg:postcode":"91910",
    "sg:province":"CA",
    "wof:name":"San Diego Deed & Document Rcrd",
    "wof:placetype":"venue"
},
  "geometry": {"coordinates":[-117.076445,32.632205],"type":"Point"}
}