{
  "type": "Feature",
  "properties": {
    "addr:full":"590 3rd Ave Chula Vista CA 91910",
    "addr:housenumber":"590",
    "addr:postcode":"91910",
    "addr:street":"3Rd Ave",
    "iso:country":"US",
    "sg:address":"590 3rd Ave",
    "sg:city":"Chula Vista",
    "sg:classifiers":[
        {
            "category":"Government",
            "subcategory":"Office",
            "type":"Public Place"
        }
    ],
    "sg:phone":"+1 619 238 8158",
    "sg:postcode":"91910",
    "sg:province":"CA",
    "wof:name":"San Diego Deed & Document Rcrd",
    "wof:placetype":"venue"
},
  "geometry": {"coordinates":[-117.07644500000001,32.632205],"type":"Point"}
}