{
  "type": "Feature",
  "properties": {
    "iso:country":"US",
    "sg:address":"14661 Lanark St",
    "sg:city":"Van Nuys",
    "sg:classifiers":[
        {
            "category":"Recreation",
            "type":"Entertainment"
        }
    ],
    "sg:phone":"+1 818 786 7922",
    "sg:postcode":"91402",
    "sg:province":"CA",
    "sg:tags":[
        "martial",
        "arts",
        "instruction"
    ],
    "wof:name":"Muay Thai Kick Boxing Gym",
    "wof:placetype":"venue"
},
  "geometry": {"coordinates":[-118.450354,34.218019],"type":"Point"}
}