{
  "type": "Feature",
  "properties": {
    "addr:full":"65 W Rincon Avenue Campbell CA 95008",
    "addr:housenumber":"65",
    "addr:postcode":"95008",
    "addr:street":"W Rincon Avenue",
    "iso:country":"US",
    "sg:address":"65 W Rincon Avenue",
    "sg:city":"Campbell",
    "sg:classifiers":[
        {
            "category":"Organizations",
            "subcategory":"Religious Organization",
            "type":"Services"
        }
    ],
    "sg:phone":"+1 408 378 4445",
    "sg:postcode":"95008",
    "sg:province":"CA",
    "wof:name":"Aids Hotline-Necessities & More.",
    "wof:placetype":"venue"
},
  "geometry": {"coordinates":[-121.95079200000001,37.284774],"type":"Point"}
}