{
  "type": "Feature",
  "properties": {
    "iso:country":"US",
    "sg:address":"8141 2nd Street",
    "sg:city":"Downey",
    "sg:classifiers":[
        {
            "category":"Professional",
            "subcategory":"Accounting & Tax Preparation",
            "type":"Services"
        }
    ],
    "sg:phone":"+1 562 904 1555",
    "sg:postcode":"90241",
    "sg:province":"CA",
    "sg:tags":[
        "accountant"
    ],
    "sg:website":"www.a1businessservice.com",
    "wof:name":"A-1 Business Service",
    "wof:placetype":"venue"
},
  "geometry": {"coordinates":[-118.135203,33.942556],"type":"Point"}
}