{
  "type": "Feature",
  "properties": {
    "addr:full":"7588 Clairemont Mesa Blvd San Diego CA 92117",
    "addr:housenumber":"7588",
    "addr:postcode":"92117",
    "addr:street":"Clairemont Mesa Blvd",
    "iso:country":"US",
    "sg:address":"7588 Clairemont Mesa Blvd",
    "sg:city":"San Diego",
    "sg:classifiers":[
        {
            "category":"Wholesale",
            "subcategory":"Hardware",
            "type":"Manufacturing & Wholesale Goods"
        }
    ],
    "sg:phone":"+1 858 278 9904",
    "sg:postcode":"92117",
    "sg:province":"CA",
    "sg:tags":[
        "equipment",
        "industrial"
    ],
    "wof:name":"Linco",
    "wof:placetype":"venue"
},
  "geometry": {"coordinates":[-117.155818,32.832782],"type":"Point"}
}