{
  "type": "Feature",
  "properties": {
    "iso:country":"US",
    "sg:address":"3230 E Imperial Hwy",
    "sg:city":"Brea",
    "sg:classifiers":[
        {
            "category":"Health Services",
            "subcategory":"Doctor",
            "type":"Services"
        }
    ],
    "sg:phone":"+1 714 924 3310",
    "sg:postcode":"92821",
    "sg:province":"CA",
    "sg:tags":[
        "physician",
        "reconstructive",
        "surgeons",
        "plastic"
    ],
    "wof:name":"National Surgical Care",
    "wof:placetype":"venue"
},
  "geometry": {"coordinates":[-117.853855,33.910483],"type":"Point"}
}