{
  "type": "Feature",
  "properties": {
    "iso:country":"US",
    "sg:address":"1042 Hillendale Ct",
    "sg:city":"Walnut Creek",
    "sg:classifiers":[
        {
            "category":"Building & Trades",
            "subcategory":"Construction",
            "type":"Services"
        }
    ],
    "sg:phone":"+1 925 944 7055",
    "sg:postcode":"94596",
    "sg:province":"CA",
    "sg:tags":[
        "tile",
        "dealer"
    ],
    "wof:name":"Bobans Tiles",
    "wof:placetype":"venue"
},
  "geometry": {"coordinates":[-122.02847199999999,37.880385],"type":"Point"}
}