{
  "type": "Feature",
  "properties": {
    "addr:full":"9700 Fair Oaks Boulevard Ste K Fair Oaks CA 95628",
    "addr:housenumber":"9700",
    "addr:postcode":"95628",
    "addr:street":"Fair Oaks Boulevard Ste K Fair Oaks",
    "iso:country":"US",
    "sg:address":"9700 Fair Oaks Boulevard Ste K",
    "sg:city":"Fair Oaks",
    "sg:classifiers":[
        {
            "category":"Health Services",
            "subcategory":"Clinic",
            "type":"Services"
        }
    ],
    "sg:phone":"+1 916 961 3302",
    "sg:postcode":"95628",
    "sg:province":"CA",
    "sg:tags":[
        "medical"
    ],
    "wof:name":"Better Health Homeopathics",
    "wof:placetype":"venue"
},
  "geometry": {"coordinates":[-121.27789,38.639291],"type":"Point"}
}