{
  "type": "Feature",
  "properties": {
    "addr:full":"241 Concord St Glendale CA 91203",
    "addr:housenumber":"241",
    "addr:postcode":"91203",
    "addr:street":"Concord St",
    "iso:country":"US",
    "sg:address":"241 Concord St",
    "sg:city":"Glendale",
    "sg:classifiers":[
        {
            "category":"Building & Trades",
            "subcategory":"Plumbing",
            "type":"Services"
        }
    ],
    "sg:phone":"+1 818 244 8000",
    "sg:postcode":"91203",
    "sg:province":"CA",
    "sg:tags":[
        "conditioning",
        "air",
        "system",
        "contractor"
    ],
    "wof:name":"G H Refrigeration",
    "wof:placetype":"venue"
},
  "geometry": {"coordinates":[-118.27121699999999,34.149705],"type":"Point"}
}