{
  "type": "Feature",
  "properties": {
    "addr:full":"4121 18th St San Francisco CA 94114",
    "addr:housenumber":"4121",
    "addr:postcode":"94114",
    "addr:street":"18Th St",
    "iso:country":"US",
    "sg:address":"4121 18th St",
    "sg:city":"San Francisco",
    "sg:classifiers":[
        {
            "category":"Bars & Pubs",
            "subcategory":"Gay Bar",
            "type":"Food & Drink"
        },
        {
            "category":"Recreation",
            "subcategory":"Dance Hall",
            "type":"Entertainment"
        }
    ],
    "sg:phone":"+1 415 626 9320",
    "sg:postcode":"94114",
    "sg:province":"CA",
    "sg:tags":[
        "club"
    ],
    "sg:website":"www.sfbadlands.com",
    "wof:name":"SF Badlands",
    "wof:placetype":"venue"
},
  "geometry": {"coordinates":[-122.435479,37.760668],"type":"Point"}
}