{
  "type": "Feature",
  "properties": {
    "addr:full":"805 Vertin Ave Salinas CA 93901",
    "addr:housenumber":"805",
    "addr:postcode":"93901",
    "addr:street":"Vertin Ave",
    "iso:country":"US",
    "sg:address":"805 Vertin Ave",
    "sg:city":"Salinas",
    "sg:classifiers":[
        {
            "category":"Wholesale",
            "subcategory":"Electrical",
            "type":"Manufacturing & Wholesale Goods"
        }
    ],
    "sg:phone":"+1 831 422 7447",
    "sg:postcode":"93901",
    "sg:province":"CA",
    "sg:tags":[
        "electric",
        "motor"
    ],
    "wof:name":"Alsop Electric Motor Shop",
    "wof:placetype":"venue"
},
  "geometry": {"coordinates":[-121.630172,36.658899],"type":"Point"}
}