{
  "type": "Feature",
  "properties": {
    "iso:country":"US",
    "sg:address":"2211 The Alameda",
    "sg:city":"Santa Clara",
    "sg:classifiers":[
        {
            "category":"Shopping",
            "subcategory":"Jewelry",
            "type":"Retail Goods"
        }
    ],
    "sg:phone":"+1 408 985 7296",
    "sg:postcode":"95050",
    "sg:province":"CA",
    "sg:tags":[
        "watch"
    ],
    "wof:name":"Pawn Shop",
    "wof:placetype":"venue"
},
  "geometry": {"coordinates":[-121.931999,37.344398],"type":"Point"}
}