{
  "type": "Feature",
  "properties": {
    "addr:full":"3910 Broad St San Luis Obispo CA 93401",
    "addr:housenumber":"3910",
    "addr:postcode":"93401",
    "addr:street":"Broad St",
    "iso:country":"US",
    "sg:address":"3910 Broad St",
    "sg:city":"San Luis Obispo",
    "sg:classifiers":[
        {
            "category":"Building & Trades",
            "subcategory":"Equipment Rental",
            "type":"Services"
        }
    ],
    "sg:phone":"+1 805 785 0482",
    "sg:postcode":"93401",
    "sg:province":"CA",
    "sg:tags":[
        "player",
        "recorder",
        "video"
    ],
    "wof:name":"Video Choice",
    "wof:placetype":"venue"
},
  "geometry": {"coordinates":[-120.643697,35.249599],"type":"Point"}
}