{
  "type": "Feature",
  "properties": {
    "iso:country":"US",
    "sg:address":"27860 del Rio Rd",
    "sg:city":"Temecula",
    "sg:classifiers":[
        {
            "category":"Retail",
            "subcategory":"Auto Repair",
            "type":"Services"
        }
    ],
    "sg:phone":"+1 951 699 3159",
    "sg:postcode":"92590",
    "sg:province":"CA",
    "sg:tags":[
        "brake"
    ],
    "wof:name":"Precision Alignment & Brake",
    "wof:placetype":"venue"
},
  "geometry": {"coordinates":[-117.158586,33.507721],"type":"Point"}
}