{
  "type": "Feature",
  "properties": {
    "iso:country":"US",
    "sg:address":"13776 Cypress Ave",
    "sg:city":"Chino",
    "sg:classifiers":[
        {
            "category":"Manufacturing",
            "subcategory":"Signs",
            "type":"Manufacturing & Wholesale Goods"
        }
    ],
    "sg:phone":"+1 909 590 8505",
    "sg:postcode":"91710",
    "sg:province":"CA",
    "sg:tags":[
        "specialty",
        "mfg"
    ],
    "wof:name":"Frank N Signs",
    "wof:placetype":"venue"
},
  "geometry": {"coordinates":[-117.662983,34.001564],"type":"Point"}
}