{
  "type": "Feature",
  "properties": {
    "addr:full":"7120 Indiana Ave Riverside CA 92504",
    "addr:housenumber":"7120",
    "addr:postcode":"92504",
    "addr:street":"Indiana Ave",
    "iso:country":"US",
    "sg:address":"7120 Indiana Ave",
    "sg:city":"Riverside",
    "sg:classifiers":[
        {
            "category":"Building & Trades",
            "subcategory":"Construction",
            "type":"Services"
        }
    ],
    "sg:phone":"+1 951 784 1368",
    "sg:postcode":"92504",
    "sg:province":"CA",
    "sg:tags":[
        "contractor"
    ],
    "sg:website":"www.gec-build.com",
    "wof:name":"GEC Svc Inc",
    "wof:placetype":"venue"
},
  "geometry": {"coordinates":[-117.403965,33.935336],"type":"Point"}
}