{
  "type": "Feature",
  "properties": {
    "addr:full":"1456 W Shaw Ave Fresno CA 93711",
    "addr:housenumber":"1456",
    "addr:postcode":"93711",
    "addr:street":"W Shaw Ave",
    "iso:country":"US",
    "sg:address":"1456 W Shaw Ave",
    "sg:city":"Fresno",
    "sg:classifiers":[
        {
            "category":"Building & Trades",
            "subcategory":"Equipment Rental",
            "type":"Services"
        }
    ],
    "sg:phone":"+1 209 243 0626",
    "sg:postcode":"93711",
    "sg:province":"CA",
    "sg:tags":[
        "medical",
        "rent"
    ],
    "wof:name":"ABC Medical Supply Inc",
    "wof:placetype":"venue"
},
  "geometry": {"coordinates":[-119.818039,36.808402],"type":"Point"}
}