{
  "type": "Feature",
  "properties": {
    "iso:country":"US",
    "sg:address":"24214 Hawthorne Blvd",
    "sg:city":"Torrance",
    "sg:classifiers":[
        {
            "category":"Personal",
            "subcategory":"Beauty Salon",
            "type":"Services"
        }
    ],
    "sg:phone":"+1 310 791 8385",
    "sg:postcode":"90505",
    "sg:province":"CA",
    "sg:tags":[
        "hair",
        "removal",
        "treatment",
        "skin"
    ],
    "sg:website":"imageelectrolysis.com",
    "wof:name":"Image Electrolysis",
    "wof:placetype":"venue"
},
  "geometry": {"coordinates":[-118.350998,33.804001],"type":"Point"}
}