{
  "type": "Feature",
  "properties": {
    "addr:full":"333 W San Carlos Street San Jose CA 95110",
    "addr:housenumber":"333",
    "addr:postcode":"95110",
    "addr:street":"W San Carlos Street",
    "iso:country":"US",
    "sg:address":"333 W San Carlos Street",
    "sg:city":"San Jose",
    "sg:classifiers":[
        {
            "category":"Professional",
            "subcategory":"Lawyer & Legal Services",
            "type":"Services"
        }
    ],
    "sg:phone":"+1 408 977 1911",
    "sg:postcode":"95110",
    "sg:province":"CA",
    "wof:name":"Bustamante O'hara & Gagliasso Apc",
    "wof:placetype":"venue"
},
  "geometry": {"coordinates":[-121.89407199999999,37.328291],"type":"Point"}
}