{
  "type": "Feature",
  "properties": {
    "addr:full":"458 Main St Quincy CA 95971",
    "addr:housenumber":"458",
    "addr:postcode":"95971",
    "addr:street":"Main St",
    "iso:country":"US",
    "sg:address":"458 Main St",
    "sg:city":"Quincy",
    "sg:classifiers":[
        {
            "category":"Personal",
            "subcategory":"Beauty Salon",
            "type":"Services"
        }
    ],
    "sg:phone":"+1 530 283 3302",
    "sg:postcode":"95971",
    "sg:province":"CA",
    "wof:name":"Great Northern Hair Co",
    "wof:placetype":"venue"
},
  "geometry": {"coordinates":[-120.94712199999999,39.936643],"type":"Point"}
}