{
  "type": "Feature",
  "properties": {
    "iso:country":"US",
    "sg:address":"701 Marsh Rd",
    "sg:city":"Menlo Park",
    "sg:classifiers":[
        {
            "category":"Retail",
            "subcategory":"Car Wash",
            "type":"Services"
        }
    ],
    "sg:phone":"+1 650 321 1212",
    "sg:postcode":"94025",
    "sg:province":"CA",
    "sg:tags":[
        "automobile",
        "detail",
        "clean"
    ],
    "wof:name":"Shine Masters",
    "wof:placetype":"venue"
},
  "geometry": {"coordinates":[-122.187051,37.47629],"type":"Point"}
}