{
  "type": "Feature",
  "properties": {
    "addr:full":"929 S Meyler St San Pedro CA 90731",
    "addr:housenumber":"929",
    "addr:postcode":"90731",
    "addr:street":"S Meyler St",
    "iso:country":"US",
    "sg:address":"929 S Meyler St",
    "sg:city":"San Pedro",
    "sg:classifiers":[
        {
            "category":"Retail",
            "subcategory":"Laundry & Dry Cleaning",
            "type":"Services"
        }
    ],
    "sg:phone":"+1 310 833 5652",
    "sg:postcode":"90731",
    "sg:province":"CA",
    "sg:tags":[
        "cleaners",
        "rug",
        "carpet"
    ],
    "wof:name":"Marina Carpet Care",
    "wof:placetype":"venue"
},
  "geometry": {"coordinates":[-118.29682699999999,33.735418],"type":"Point"}
}