{
  "type": "Feature",
  "properties": {
    "addr:full":"1416 W Sunset Blvd Los Angeles CA 90026",
    "addr:housenumber":"1416",
    "addr:postcode":"90026",
    "addr:street":"W Sunset Blvd",
    "iso:country":"US",
    "sg:address":"1416 W Sunset Blvd",
    "sg:city":"Los Angeles",
    "sg:classifiers":[
        {
            "category":"Wholesale",
            "subcategory":"Auto Parts",
            "type":"Manufacturing & Wholesale Goods"
        }
    ],
    "sg:phone":"+1 213 250 1802",
    "sg:postcode":"90026",
    "sg:province":"CA",
    "sg:tags":[
        "tire"
    ],
    "wof:name":"Union Eastern Tire Co",
    "wof:placetype":"venue"
},
  "geometry": {"coordinates":[-118.251999,34.074699],"type":"Point"}
}