{
  "type": "Feature",
  "properties": {
    "iso:country":"US",
    "sg:address":"4312 E Cesar E Chavez Ave",
    "sg:city":"Los Angeles",
    "sg:classifiers":[
        {
            "category":"Food & Beverages",
            "subcategory":"Liquor & Beverages",
            "type":"Retail Goods"
        }
    ],
    "sg:phone":"+1 323 268 4408",
    "sg:postcode":"90022",
    "sg:province":"CA",
    "wof:name":"Andy's Liquor",
    "wof:placetype":"venue"
},
  "geometry": {"coordinates":[-118.17160199999999,34.040498],"type":"Point"}
}