{
  "type": "Feature",
  "properties": {
    "addr:full":"23451 Madison Ave Ste 340 Torrance CA 90505",
    "addr:housenumber":"23451",
    "addr:postcode":"90505",
    "addr:street":"Madison Ave Ste 340",
    "iso:country":"US",
    "sg:address":"23451 Madison Ave Ste 340",
    "sg:city":"Torrance",
    "sg:classifiers":[
        {
            "category":"Health Services",
            "subcategory":"Doctor",
            "type":"Services"
        }
    ],
    "sg:phone":"+1 310 373 6864",
    "sg:postcode":"90505",
    "sg:province":"CA",
    "wof:name":"Houman Solomon, MD",
    "wof:placetype":"venue"
},
  "geometry": {"coordinates":[-118.348665,33.812077],"type":"Point"}
}