{
  "type": "Feature",
  "properties": {
    "addr:full":"530 B St Lbby San Diego CA 92101",
    "addr:housenumber":"530",
    "addr:postcode":"92101",
    "addr:street":"B St",
    "iso:country":"US",
    "sg:address":"530 B St Lbby",
    "sg:city":"San Diego",
    "sg:classifiers":[
        {
            "category":"Professional",
            "subcategory":"Lawyer & Legal Services",
            "type":"Services"
        }
    ],
    "sg:phone":"+1 619 238 1900",
    "sg:postcode":"92101",
    "sg:province":"CA",
    "wof:name":"Cory Alec L",
    "wof:placetype":"venue"
},
  "geometry": {"coordinates":[-117.160004,32.7178],"type":"Point"}
}