{
  "type": "Feature",
  "properties": {
    "iso:country":"US",
    "sg:address":"1601 Bayshore Hwy",
    "sg:city":"Burlingame",
    "sg:classifiers":[
        {
            "category":"Social Services",
            "type":"Services"
        },
        {
            "category":"Personal",
            "type":"Services"
        }
    ],
    "sg:phone":"+1 650 692 8990",
    "sg:postcode":"94010",
    "sg:province":"CA",
    "sg:tags":[
        "counseling",
        "family",
        "counselors-licensed",
        "individual",
        "marriage",
        "child",
        "professional",
        "counselor"
    ],
    "sg:website":"http://www.davisdyslexia.com",
    "wof:name":"Dyslexia Correction Center",
    "wof:placetype":"venue"
},
  "geometry": {"coordinates":[-122.367378,37.5993],"type":"Point"}
}