{
  "type": "Feature",
  "properties": {
    "iso:country":"US",
    "sg:address":"2264 Featherhill Rd",
    "sg:city":"Santa Barbara",
    "sg:classifiers":[
        {
            "category":"Social Services",
            "type":"Services"
        }
    ],
    "sg:phone":"+1 805 969 5874",
    "sg:postcode":"93108",
    "sg:province":"CA",
    "sg:tags":[
        "counselor",
        "marriage",
        "family"
    ],
    "wof:name":"Virginia A Larson PHD",
    "wof:placetype":"venue"
},
  "geometry": {"coordinates":[-119.59739,34.440782],"type":"Point"}
}