{
  "type": "Feature",
  "properties": {
    "addr:full":"5121 W Pico Boulevard Los Angeles CA 90019",
    "addr:housenumber":"5121",
    "addr:postcode":"90019",
    "addr:street":"W Pico Boulevard",
    "iso:country":"US",
    "sg:address":"5121 W Pico Boulevard",
    "sg:city":"Los Angeles",
    "sg:classifiers":[
        {
            "category":"Food & Beverages",
            "subcategory":"Liquor & Beverages",
            "type":"Retail Goods"
        }
    ],
    "sg:phone":"+1 323 933 8801",
    "sg:postcode":"90019",
    "sg:province":"CA",
    "sg:tags":[
        "beer",
        "spirit",
        "wine"
    ],
    "wof:name":"Pinchers",
    "wof:placetype":"venue"
},
  "geometry": {"coordinates":[-118.350264,34.047955],"type":"Point"}
}