{
  "type": "Feature",
  "properties": {
    "iso:country":"US",
    "sg:address":"8690 Miramar Rd",
    "sg:city":"San Diego",
    "sg:classifiers":[
        {
            "category":"Retail",
            "subcategory":"Auto Repair",
            "type":"Services"
        }
    ],
    "sg:phone":"+1 858 689 8900",
    "sg:postcode":"92126",
    "sg:province":"CA",
    "sg:tags":[
        "repairing",
        "automobile"
    ],
    "wof:name":"Rover Group",
    "wof:placetype":"venue"
},
  "geometry": {"coordinates":[-117.141254,32.890722],"type":"Point"}
}