{
  "type": "Feature",
  "properties": {
    "iso:country":"US",
    "sg:address":"178 S Victory Blvd",
    "sg:city":"Burbank",
    "sg:classifiers":[
        {
            "category":"Professional",
            "type":"Services"
        }
    ],
    "sg:phone":"+1 818 972 9382",
    "sg:postcode":"91502",
    "sg:province":"CA",
    "sg:tags":[
        "establishment"
    ],
    "wof:name":"Armix",
    "wof:placetype":"venue"
},
  "geometry": {"coordinates":[-118.316237,34.173282],"type":"Point"}
}