{
  "type": "Feature",
  "properties": {
    "addr:full":"2610 E Anaheim St Long Beach CA 90804",
    "addr:housenumber":"2610",
    "addr:postcode":"90804",
    "addr:street":"E Anaheim St",
    "iso:country":"US",
    "sg:address":"2610 E Anaheim St",
    "sg:city":"Long Beach",
    "sg:classifiers":[
        {
            "category":"Food & Beverages",
            "subcategory":"Groceries & Convenience Stores",
            "type":"Retail Goods"
        }
    ],
    "sg:phone":"+1 562 987 1521",
    "sg:postcode":"90804",
    "sg:province":"CA",
    "wof:name":"USA Market",
    "wof:placetype":"venue"
},
  "geometry": {"coordinates":[-118.16100299999999,33.782501],"type":"Point"}
}