{
  "type": "Feature",
  "properties": {
    "addr:full":"12533 Pacato Cir N San Diego CA 92128",
    "addr:housenumber":"12533",
    "addr:postcode":"92128",
    "addr:street":"Pacato Cir N",
    "iso:country":"US",
    "sg:address":"12533 Pacato Cir N",
    "sg:city":"San Diego",
    "sg:classifiers":[
        {
            "category":"Government",
            "subcategory":"Office",
            "type":"Public Place"
        }
    ],
    "sg:phone":"+1 858 485 1696",
    "sg:postcode":"92128",
    "sg:province":"CA",
    "sg:tags":[
        "international",
        "affairs"
    ],
    "wof:name":"Seniors Abroad",
    "wof:placetype":"venue"
},
  "geometry": {"coordinates":[-117.057833,33.02291],"type":"Point"}
}