{
  "type": "Feature",
  "properties": {
    "addr:full":"2079 S Atlantic Blvd Monterey Park CA 91754",
    "addr:housenumber":"2079",
    "addr:postcode":"91754",
    "addr:street":"S Atlantic Blvd",
    "iso:country":"US",
    "sg:address":"2079 S Atlantic Blvd",
    "sg:city":"Monterey Park",
    "sg:classifiers":[
        {
            "category":"Professional",
            "subcategory":"Accounting & Tax Preparation",
            "type":"Services"
        }
    ],
    "sg:phone":"+1 323 268 8200",
    "sg:postcode":"91754",
    "sg:province":"CA",
    "sg:tags":[
        "accountant"
    ],
    "wof:name":"Twanmoh Peng & Associates",
    "wof:placetype":"venue"
},
  "geometry": {"coordinates":[-118.14299800000001,34.039501],"type":"Point"}
}