{
  "type": "Feature",
  "properties": {
    "addr:full":"2650 Griffith Park Boulevard Los Angeles CA 90039",
    "addr:housenumber":"2650",
    "addr:postcode":"90039",
    "addr:street":"Griffith Park Boulevard",
    "iso:country":"US",
    "sg:address":"2650 Griffith Park Boulevard",
    "sg:city":"Los Angeles",
    "sg:classifiers":[
        {
            "category":"Health Services",
            "subcategory":"Dentist",
            "type":"Services"
        }
    ],
    "sg:phone":"+1 323 660 5522",
    "sg:postcode":"90039",
    "sg:province":"CA",
    "wof:name":"Matulian Gayane D D S",
    "wof:placetype":"venue"
},
  "geometry": {"coordinates":[-118.271872,34.106349],"type":"Point"}
}