{
  "type": "Feature",
  "properties": {
    "iso:country":"US",
    "sg:address":"9336 Glenoaks Blvd",
    "sg:city":"Sun Valley",
    "sg:classifiers":[
        {
            "category":"Building & Trades",
            "subcategory":"Construction",
            "type":"Services"
        }
    ],
    "sg:phone":"+1 818 252 7236",
    "sg:postcode":"91352",
    "sg:province":"CA",
    "wof:name":"DAngelo Construction",
    "wof:placetype":"venue"
},
  "geometry": {"coordinates":[-118.376627,34.239432],"type":"Point"}
}