{
  "type": "Feature",
  "properties": {
    "addr:full":"609 2nd St Davis CA 95616",
    "addr:housenumber":"609",
    "addr:postcode":"95616",
    "addr:street":"2Nd St",
    "iso:country":"US",
    "sg:address":"609 2nd St",
    "sg:city":"Davis",
    "sg:classifiers":[
        {
            "category":"Government",
            "subcategory":"Office",
            "type":"Public Place"
        }
    ],
    "sg:phone":"+1 530 756 1104",
    "sg:postcode":"95616",
    "sg:province":"CA",
    "sg:tags":[
        "federal"
    ],
    "wof:name":"US Army Corps Of Engineers",
    "wof:placetype":"venue"
},
  "geometry": {"coordinates":[-121.740084,38.543483],"type":"Point"}
}