{
  "type": "Feature",
  "properties": {
    "addr:full":"800 N Alameda Street Los Angeles CA 90012",
    "addr:housenumber":"800",
    "addr:postcode":"90012",
    "addr:street":"N Alameda Street",
    "iso:country":"US",
    "sg:address":"800 N Alameda Street",
    "sg:city":"Los Angeles",
    "sg:classifiers":[
        {
            "category":"Communications",
            "subcategory":"Newspaper",
            "type":"Services"
        }
    ],
    "sg:phone":"+1 213 617 7653",
    "sg:postcode":"90012",
    "sg:province":"CA",
    "sg:tags":[
        "magazine"
    ],
    "wof:name":"Eastern Newsstands",
    "wof:placetype":"venue"
},
  "geometry": {"coordinates":[-118.23763700000001,34.056142],"type":"Point"}
}