{
  "type": "Feature",
  "properties": {
    "iso:country":"US",
    "sg:address":"2921 W. Burbank Blvd.",
    "sg:city":"Burbank",
    "sg:classifiers":[
        {
            "category":"Professional",
            "subcategory":"Printing & Photocopies",
            "type":"Services"
        }
    ],
    "sg:phone":"+1 818 841 8000",
    "sg:postcode":"91505",
    "sg:province":"CA",
    "sg:website":"www.threerprinting.com/docs/abou...",
    "wof:name":"3R Printing",
    "wof:placetype":"venue"
},
  "geometry": {"coordinates":[-118.34343,34.177267],"type":"Point"}
}