{
  "type": "Feature",
  "properties": {
    "iso:country":"US",
    "sg:address":"600 Pacific Coast Hwy",
    "sg:city":"Hermosa Beach",
    "sg:classifiers":[
        {
            "category":"Personal",
            "subcategory":"Beauty Salon",
            "type":"Services"
        }
    ],
    "sg:phone":"+1 310 372 1131",
    "sg:postcode":"90254",
    "sg:province":"CA",
    "wof:name":"Designs On You Hair",
    "wof:placetype":"venue"
},
  "geometry": {"coordinates":[-118.391677,33.860025],"type":"Point"}
}