{
  "type": "Feature",
  "properties": {
    "iso:country":"US",
    "sg:address":"899 3rd Ave",
    "sg:city":"Chula Vista",
    "sg:classifiers":[
        {
            "category":"Autos & Motor Vehicles",
            "subcategory":"Fuel & Gas Station",
            "type":"Retail Goods"
        }
    ],
    "sg:phone":"+1 619 422 9286",
    "sg:postcode":"91911",
    "sg:province":"CA",
    "sg:tags":[
        "oil"
    ],
    "wof:name":"Chula Vista Svc Ctr",
    "wof:placetype":"venue"
},
  "geometry": {"coordinates":[-117.072262,32.621778],"type":"Point"}
}