{
  "type": "Feature",
  "properties": {
    "iso:country":"US",
    "sg:address":"301 S Milpas St",
    "sg:city":"Santa Barbara",
    "sg:classifiers":[
        {
            "category":"Retail",
            "subcategory":"Auto Repair",
            "type":"Services"
        }
    ],
    "sg:phone":"+1 805 963 3745",
    "sg:postcode":"93103",
    "sg:province":"CA",
    "sg:tags":[
        "repairing",
        "tire"
    ],
    "wof:name":"Dal Pozzo Tire Corp",
    "wof:placetype":"venue"
},
  "geometry": {"coordinates":[-119.674722,34.418663],"type":"Point"}
}