{
  "type": "Feature",
  "properties": {
    "iso:country":"US",
    "sg:address":"13400 Calimesa Blvd",
    "sg:city":"Yucaipa",
    "sg:classifiers":[
        {
            "category":"Recreation",
            "subcategory":"Boat Charter",
            "type":"Entertainment"
        }
    ],
    "sg:phone":"+1 909 795 8584",
    "sg:postcode":"92399",
    "sg:province":"CA",
    "sg:tags":[
        "boating"
    ],
    "wof:name":"Ron's Marine Service Center",
    "wof:placetype":"venue"
},
  "geometry": {"coordinates":[-117.09200300000001,34.0158],"type":"Point"}
}