{
  "type": "Feature",
  "properties": {
    "addr:full":"1739 W San Carlos St San Jose CA 95128",
    "addr:housenumber":"1739",
    "addr:postcode":"95128",
    "addr:street":"W San Carlos St",
    "iso:country":"US",
    "sg:address":"1739 W San Carlos St",
    "sg:city":"San Jose",
    "sg:classifiers":[
        {
            "category":"Retail",
            "subcategory":"Laundry & Dry Cleaning",
            "type":"Services"
        }
    ],
    "sg:phone":"+1 408 298 5206",
    "sg:postcode":"95128",
    "sg:province":"CA",
    "wof:name":"City of Paris Cleaners",
    "wof:placetype":"venue"
},
  "geometry": {"coordinates":[-121.922997,37.323399],"type":"Point"}
}