{
  "type": "Feature",
  "properties": {
    "iso:country":"US",
    "sg:address":"120 E Alder St",
    "sg:city":"Fort Bragg",
    "sg:classifiers":[
        {
            "category":"Banks & Credit Unions",
            "subcategory":"Bank",
            "type":"Services"
        }
    ],
    "sg:phone":"+1 707 961 4444",
    "sg:postcode":"95437",
    "sg:province":"CA",
    "wof:name":"Washington Mutual",
    "wof:placetype":"venue"
},
  "geometry": {"coordinates":[-123.80575,39.442903],"type":"Point"}
}