{
  "type": "Feature",
  "properties": {
    "iso:country":"US",
    "sg:address":"122 E Anaheim St",
    "sg:city":"Wilmington",
    "sg:classifiers":[
        {
            "category":"Travel",
            "subcategory":"Travel Agent",
            "type":"Entertainment"
        }
    ],
    "sg:phone":"+1 310 518 0570",
    "sg:postcode":"90744",
    "sg:province":"CA",
    "sg:tags":[
        "agency"
    ],
    "wof:name":"Unitel Travel Inc",
    "wof:placetype":"venue"
},
  "geometry": {"coordinates":[-118.26116399999999,33.779968],"type":"Point"}
}