{
  "type": "Feature",
  "properties": {
    "addr:full":"4413 Otis Ct Carmichael CA 95608",
    "addr:housenumber":"4413",
    "addr:postcode":"95608",
    "addr:street":"Otis Ct",
    "iso:country":"US",
    "sg:address":"4413 Otis Ct",
    "sg:city":"Carmichael",
    "sg:classifiers":[
        {
            "category":"Professional",
            "subcategory":"Management & Consulting",
            "type":"Services"
        }
    ],
    "sg:phone":"+1 916 966 2963",
    "sg:postcode":"95608",
    "sg:province":"CA",
    "sg:tags":[
        "consultant",
        "wine"
    ],
    "wof:name":"Steve's Fine Wines",
    "wof:placetype":"venue"
},
  "geometry": {"coordinates":[-121.319975,38.643692],"type":"Point"}
}