{
  "type": "Feature",
  "properties": {
    "iso:country":"US",
    "sg:address":"36068 Hidden Springs Rd",
    "sg:city":"Wildomar",
    "sg:classifiers":[
        {
            "category":"Restaurant",
            "type":"Food & Drink"
        }
    ],
    "sg:menulink":"http://www.allmenus.com/ca/murrieta/147134-charo-chicken/menu/",
    "sg:phone":"+1 951 678 1200",
    "sg:postcode":"92595",
    "sg:province":"CA",
    "sg:tags":[
        "american"
    ],
    "wof:name":"CHARO CHICKEN",
    "wof:placetype":"venue"
},
  "geometry": {"coordinates":[-117.248508,33.596949],"type":"Point"}
}