{
  "type": "Feature",
  "properties": {
    "iso:country":"US",
    "sg:address":"3450 Louis Rd",
    "sg:city":"Palo Alto",
    "sg:classifiers":[
        {
            "category":"Social Services",
            "subcategory":"Child Care",
            "type":"Services"
        }
    ],
    "sg:phone":"+1 650 852 9475",
    "sg:postcode":"94303",
    "sg:province":"CA",
    "wof:name":"Palo Verde Kids Club",
    "wof:placetype":"venue"
},
  "geometry": {"coordinates":[-122.114555,37.431881],"type":"Point"}
}