{
  "type": "Feature",
  "properties": {
    "addr:full":"28771 Rio Norte Dr Valencia CA 91354",
    "addr:housenumber":"28771",
    "addr:postcode":"91354",
    "addr:street":"Rio Norte Dr",
    "iso:country":"US",
    "sg:address":"28771 Rio Norte Dr",
    "sg:city":"Valencia",
    "sg:classifiers":[
        {
            "category":"Education",
            "subcategory":"School",
            "type":"Public Place"
        }
    ],
    "sg:phone":"+1 661 295 3700",
    "sg:postcode":"91354",
    "sg:province":"CA",
    "sg:tags":[
        "high",
        "middle",
        "elementary"
    ],
    "sg:website":"www.hart.k12.ca.us",
    "wof:name":"William S Hart Union High School District",
    "wof:placetype":"venue"
},
  "geometry": {"coordinates":[-118.54299899999999,34.4464],"type":"Point"}
}