{
  "type": "Feature",
  "properties": {
    "iso:country":"US",
    "sg:address":"2600 E Bidwell St",
    "sg:city":"Folsom",
    "sg:classifiers":[
        {
            "category":"Social Services",
            "type":"Services"
        },
        {
            "category":"Health Services",
            "subcategory":"Doctor",
            "type":"Services"
        },
        {
            "category":"Personal",
            "type":"Services"
        },
        {
            "category":"Health Services",
            "subcategory":"Health Practitioner",
            "type":"Services"
        }
    ],
    "sg:phone":"+1 800 391 7010",
    "sg:postcode":"95630",
    "sg:province":"CA",
    "sg:tags":[
        "family",
        "psychotherapist",
        "psychologist",
        "therapist",
        "marriage",
        "counseling"
    ],
    "sg:website":"http://www.drscottbrandt.com",
    "wof:name":"Brandt Scott D PhD",
    "wof:placetype":"venue"
},
  "geometry": {"coordinates":[-121.130737,38.66003],"type":"Point"}
}