{
  "type": "Feature",
  "properties": {
    "iso:country":"US",
    "sg:address":"901 Ski Run Blvd",
    "sg:city":"South Lake Tahoe",
    "sg:classifiers":[
        {
            "category":"Professional",
            "subcategory":"Business Services",
            "type":"Services"
        }
    ],
    "sg:phone":"+1 530 541 3568",
    "sg:postcode":"96150",
    "sg:province":"CA",
    "wof:name":"Embassy Vacation Resort",
    "wof:placetype":"venue"
},
  "geometry": {"coordinates":[-119.958224,38.949469],"type":"Point"}
}