{
  "type": "Feature",
  "properties": {
    "addr:full":"5650 Eastgate Mall San Diego CA 92121",
    "addr:housenumber":"5650",
    "addr:postcode":"92121",
    "addr:street":"Eastgate Mall",
    "iso:country":"US",
    "sg:address":"5650 Eastgate Mall",
    "sg:city":"San Diego",
    "sg:classifiers":[
        {
            "category":"Autos & Motor Vehicles",
            "subcategory":"Automobile Sales",
            "type":"Retail Goods"
        }
    ],
    "sg:phone":"+1 858 453 7575",
    "sg:postcode":"92121",
    "sg:province":"CA",
    "sg:tags":[
        "car",
        "dealer"
    ],
    "wof:name":"Online Auto Group",
    "wof:placetype":"venue"
},
  "geometry": {"coordinates":[-117.186295,32.877331],"type":"Point"}
}