{
  "type": "Feature",
  "properties": {
    "addr:full":"22315 Mulholland Hwy Calabasas CA 91302",
    "addr:housenumber":"22315",
    "addr:postcode":"91302",
    "addr:street":"Mulholland Hwy",
    "iso:country":"US",
    "sg:address":"22315 Mulholland Hwy",
    "sg:city":"Calabasas",
    "sg:classifiers":[
        {
            "category":"Professional",
            "subcategory":"Art Services",
            "type":"Services"
        }
    ],
    "sg:phone":"+1 818 224 2448",
    "sg:postcode":"91302",
    "sg:province":"CA",
    "sg:tags":[
        "photographer"
    ],
    "sg:website":"www.amodelmoment.com",
    "wof:name":"A Model Moment",
    "wof:placetype":"venue"
},
  "geometry": {"coordinates":[-118.612754,34.145786],"type":"Point"}
}