{
  "type": "Feature",
  "properties": {
    "addr:full":"1057 Lincoln Ave San Jose CA 95125",
    "addr:housenumber":"1057",
    "addr:postcode":"95125",
    "addr:street":"Lincoln Ave",
    "iso:country":"US",
    "sg:address":"1057 Lincoln Ave",
    "sg:city":"San Jose",
    "sg:classifiers":[
        {
            "category":"Personal",
            "subcategory":"Beauty Salon",
            "type":"Services"
        }
    ],
    "sg:phone":"+1 408 295 4040",
    "sg:postcode":"95125",
    "sg:province":"CA",
    "wof:name":"Hairquarter's Unisex Salon",
    "wof:placetype":"venue"
},
  "geometry": {"coordinates":[-121.902642,37.310558],"type":"Point"}
}