{
  "type": "Feature",
  "properties": {
    "iso:country":"US",
    "sg:address":"321 S California Ave",
    "sg:city":"Palo Alto",
    "sg:classifiers":[
        {
            "category":"Restaurant",
            "type":"Food & Drink"
        }
    ],
    "sg:phone":"+1 650 321 2550",
    "sg:postcode":"94306",
    "sg:province":"CA",
    "wof:name":"Antonio's Nut House",
    "wof:placetype":"venue"
},
  "geometry": {"coordinates":[-122.14444399999999,37.426671],"type":"Point"}
}