{
  "type": "Feature",
  "properties": {
    "iso:country":"US",
    "sg:address":"344 N Sunrise Way",
    "sg:city":"Palm Springs",
    "sg:classifiers":[
        {
            "category":"Social Services",
            "subcategory":"Adult Care",
            "type":"Services"
        }
    ],
    "sg:phone":"+1 760 322 3955",
    "sg:postcode":"92262",
    "sg:province":"CA",
    "sg:tags":[
        "home",
        "residential"
    ],
    "wof:name":"Hallmark Palm Springs",
    "wof:placetype":"venue"
},
  "geometry": {"coordinates":[-116.528153,33.827554],"type":"Point"}
}