{
  "type": "Feature",
  "properties": {
    "addr:full":"1224 S Garfield Ave #206 Alhambra CA 91801",
    "addr:housenumber":"1224;206",
    "addr:postcode":"91801",
    "addr:street":"S Garfield Ave #",
    "iso:country":"US",
    "sg:address":"1224 S Garfield Ave #206",
    "sg:city":"Alhambra",
    "sg:classifiers":[
        {
            "category":"Travel",
            "subcategory":"Travel Agent",
            "type":"Entertainment"
        }
    ],
    "sg:phone":"+1 626 796 8066",
    "sg:postcode":"91801",
    "sg:province":"CA",
    "wof:name":"Coast To Coast Travel",
    "wof:placetype":"venue"
},
  "geometry": {"coordinates":[-118.123058,34.080215],"type":"Point"}
}