{
  "type": "Feature",
  "properties": {
    "iso:country":"US",
    "sg:address":"2826 Harris St",
    "sg:city":"Eureka",
    "sg:classifiers":[
        {
            "category":"Health Services",
            "subcategory":"Doctor",
            "type":"Services"
        }
    ],
    "sg:phone":"+1 707 443 8066",
    "sg:postcode":"95503",
    "sg:province":"CA",
    "sg:tags":[
        "physician",
        "pediatrics-orthopedic",
        "surgeons",
        "orthopedics",
        "surgeon",
        "surgery"
    ],
    "wof:name":"Shishido Nathan MD",
    "wof:placetype":"venue"
},
  "geometry": {"coordinates":[-124.135896,40.780472],"type":"Point"}
}