{
  "type": "Feature",
  "properties": {
    "addr:full":"7131 English Colony Way Penryn CA 95663",
    "addr:housenumber":"7131",
    "addr:postcode":"95663",
    "addr:street":"English Colony Way",
    "iso:country":"US",
    "sg:address":"7131 English Colony Way",
    "sg:city":"Penryn",
    "sg:classifiers":[
        {
            "category":"Professional",
            "type":"Services"
        }
    ],
    "sg:phone":"+1 916 663 3133",
    "sg:postcode":"95663",
    "sg:province":"CA",
    "wof:name":"Fredrick Travnikar",
    "wof:placetype":"venue"
},
  "geometry": {"coordinates":[-121.17022,38.853977],"type":"Point"}
}