{
  "type": "Feature",
  "properties": {
    "addr:full":"3212 Jefferson St. PMB 116 Napa CA 94558-3436",
    "addr:housenumber":"3212;116",
    "addr:postcode":"94558-3436",
    "addr:street":"Jefferson St.",
    "iso:country":"US",
    "sg:address":"3212 Jefferson St. PMB 116",
    "sg:city":"Napa",
    "sg:classifiers":[
        {
            "category":"Professional",
            "subcategory":"Management & Consulting",
            "type":"Services"
        }
    ],
    "sg:phone":"+1 707 815 3963",
    "sg:postcode":"94558-3436",
    "sg:province":"CA",
    "sg:tags":[
        "lotus",
        "ibm",
        "notes",
        "aix",
        "i5os",
        "messaging",
        "collaboration",
        "migration",
        "coexistence"
    ],
    "sg:website":"http://www.msagroup.net",
    "wof:name":"Messaging System Architects",
    "wof:placetype":"venue"
},
  "geometry": {"coordinates":[-122.29908,38.320082],"type":"Point"}
}