{
  "type": "Feature",
  "properties": {
    "addr:full":"1611 Westwood Blvd Los Angeles CA 90024",
    "addr:housenumber":"1611",
    "addr:postcode":"90024",
    "addr:street":"Westwood Blvd",
    "iso:country":"US",
    "sg:address":"1611 Westwood Blvd",
    "sg:city":"Los Angeles",
    "sg:classifiers":[
        {
            "category":"Wholesale",
            "subcategory":"Durable Goods & Equipment",
            "type":"Manufacturing & Wholesale Goods"
        }
    ],
    "sg:phone":"+1 310 473 2529",
    "sg:postcode":"90024",
    "sg:province":"CA",
    "wof:name":"Supplement Star",
    "wof:placetype":"venue"
},
  "geometry": {"coordinates":[-118.438884,34.05191],"type":"Point"}
}