{
  "type": "Feature",
  "properties": {
    "iso:country":"US",
    "sg:address":"3062 Woodside Rd",
    "sg:city":"Woodside",
    "sg:phone":"+1 650 851 8010",
    "sg:postcode":"94062",
    "sg:province":"CA",
    "sg:website":"http://www.buckswoodside.com",
    "wof:name":"Buck's Of Woodside",
    "wof:placetype":"venue"
},
  "geometry": {"coordinates":[-122.254266,37.429642],"type":"Point"}
}