{
  "type": "Feature",
  "properties": {
    "iso:country":"US",
    "sg:address":"2131 Tevis Ave",
    "sg:city":"Long Beach",
    "sg:classifiers":[
        {
            "category":"Wholesale",
            "subcategory":"Sporting Goods",
            "type":"Manufacturing & Wholesale Goods"
        }
    ],
    "sg:phone":"+1 562 596 1801",
    "sg:postcode":"90815",
    "sg:province":"CA",
    "wof:name":"Phoenix Boat Co",
    "wof:placetype":"venue"
},
  "geometry": {"coordinates":[-118.110883,33.794531],"type":"Point"}
}