{
  "type": "Feature",
  "properties": {
    "addr:full":"234 Blue Ridge Dr Martinez CA 94553",
    "addr:housenumber":"234",
    "addr:postcode":"94553",
    "addr:street":"Blue Ridge Dr",
    "iso:country":"US",
    "sg:address":"234 Blue Ridge Dr",
    "sg:city":"Martinez",
    "sg:classifiers":[
        {
            "category":"Building & Trades",
            "subcategory":"Plumbing",
            "type":"Services"
        }
    ],
    "sg:phone":"+1 925 949 0970",
    "sg:postcode":"94553",
    "sg:province":"CA",
    "sg:tags":[
        "conditioning"
    ],
    "wof:name":"Diablo Valley Comfort Systems",
    "wof:placetype":"venue"
},
  "geometry": {"coordinates":[-122.097798,37.959957],"type":"Point"}
}