{
  "type": "Feature",
  "properties": {
    "addr:full":"883 Island Dr Ste 212 Alameda CA 94502",
    "addr:housenumber":"883",
    "addr:postcode":"94502",
    "addr:street":"Island Dr Ste 212",
    "iso:country":"US",
    "sg:address":"883 Island Dr Ste 212",
    "sg:city":"Alameda",
    "sg:classifiers":[
        {
            "category":"Professional",
            "subcategory":"Accounting & Tax Preparation",
            "type":"Services"
        }
    ],
    "sg:phone":"+1 510 865 4238",
    "sg:postcode":"94502",
    "sg:province":"CA",
    "sg:tags":[
        "accountant"
    ],
    "wof:name":"Bishop James L CPA",
    "wof:placetype":"venue"
},
  "geometry": {"coordinates":[-122.24700199999999,37.738098],"type":"Point"}
}