{
  "type": "Feature",
  "properties": {
    "addr:full":"7777 Wren Ave Gilroy CA 95020",
    "addr:housenumber":"7777",
    "addr:postcode":"95020",
    "addr:street":"Wren Ave",
    "iso:country":"US",
    "sg:address":"7777 Wren Ave",
    "sg:city":"Gilroy",
    "sg:classifiers":[
        {
            "category":"Real Estate",
            "subcategory":"Real Estate Services",
            "type":"Services"
        }
    ],
    "sg:phone":"+1 408 848 8722",
    "sg:postcode":"95020",
    "sg:province":"CA",
    "sg:tags":[
        "company",
        "title"
    ],
    "wof:name":"Alliance Title Co",
    "wof:placetype":"venue"
},
  "geometry": {"coordinates":[-121.587068,37.008445],"type":"Point"}
}