{
  "type": "Feature",
  "properties": {
    "addr:full":"24080 Conejo Dr Sun City CA 92587",
    "addr:housenumber":"24080",
    "addr:postcode":"92587",
    "addr:street":"Conejo Dr",
    "iso:country":"US",
    "sg:address":"24080 Conejo Dr",
    "sg:city":"Sun City",
    "sg:classifiers":[
        {
            "category":"Home & Garden",
            "subcategory":"Furniture",
            "type":"Retail Goods"
        }
    ],
    "sg:phone":"+1 951 699 0988",
    "sg:postcode":"92587",
    "sg:province":"CA",
    "wof:name":"Wonderland Garden",
    "wof:placetype":"venue"
},
  "geometry": {"coordinates":[-117.235086,33.692533],"type":"Point"}
}