{
  "type": "Feature",
  "properties": {
    "addr:full":"515 Temple Ave Camarillo CA 93010",
    "addr:housenumber":"515",
    "addr:postcode":"93010",
    "addr:street":"Temple Ave",
    "iso:country":"US",
    "sg:address":"515 Temple Ave",
    "sg:city":"Camarillo",
    "sg:classifiers":[
        {
            "category":"Organizations",
            "subcategory":"Religious Organization",
            "type":"Services"
        }
    ],
    "sg:phone":"+1 805 482 3505",
    "sg:postcode":"93010",
    "sg:province":"CA",
    "sg:tags":[
        "church"
    ],
    "sg:website":"www.camarillochurchofchrist.com",
    "wof:name":"Church Of Christ",
    "wof:placetype":"venue"
},
  "geometry": {"coordinates":[-119.029848,34.221815],"type":"Point"}
}