{
  "type": "Feature",
  "properties": {
    "iso:country":"US",
    "sg:address":"2101 N Rose Ave",
    "sg:city":"Oxnard",
    "sg:classifiers":[
        {
            "category":"Banks & Credit Unions",
            "subcategory":"Bank",
            "type":"Services"
        }
    ],
    "sg:phone":"+1 805 278 0281",
    "sg:postcode":"93036",
    "sg:province":"CA",
    "sg:website":"www.wellsfargo.com",
    "wof:name":"Wells Fargo Bank",
    "wof:placetype":"venue"
},
  "geometry": {"coordinates":[-119.158409,34.222803],"type":"Point"}
}