{
  "type": "Feature",
  "properties": {
    "addr:full":"25830 Floyd Ave Sun City CA 92585",
    "addr:housenumber":"25830",
    "addr:postcode":"92585",
    "addr:street":"Floyd Ave",
    "iso:country":"US",
    "sg:address":"25830 Floyd Ave",
    "sg:city":"Sun City",
    "sg:classifiers":[
        {
            "category":"Building & Trades",
            "subcategory":"Plumbing",
            "type":"Services"
        }
    ],
    "sg:phone":"+1 951 830 4137",
    "sg:postcode":"92585",
    "sg:province":"CA",
    "sg:tags":[
        "contractor"
    ],
    "wof:name":"Jones Plumbing Heating & Air",
    "wof:placetype":"venue"
},
  "geometry": {"coordinates":[-117.209818,33.740405],"type":"Point"}
}