{
  "type": "Feature",
  "properties": {
    "iso:country":"US",
    "sg:address":"2753 E Eastland Ctr Dr",
    "sg:city":"West Covina",
    "sg:classifiers":[
        {
            "category":"Personal",
            "type":"Services"
        }
    ],
    "sg:phone":"+1 626 337 5009",
    "sg:postcode":"91791",
    "sg:province":"CA",
    "sg:tags":[
        "wear",
        "formal"
    ],
    "wof:name":"After Hours Formalwear",
    "wof:placetype":"venue"
},
  "geometry": {"coordinates":[-117.887938,34.073078],"type":"Point"}
}