{
  "type": "Feature",
  "properties": {
    "addr:full":"1000 Ames Avenue Milpitas CA 95035",
    "addr:housenumber":"1000",
    "addr:postcode":"95035",
    "addr:street":"Ames Avenue",
    "iso:country":"US",
    "sg:address":"1000 Ames Avenue",
    "sg:city":"Milpitas",
    "sg:classifiers":[
        {
            "category":"Taxi",
            "type":"Transportation"
        }
    ],
    "sg:phone":"+1 408 395 0100",
    "sg:postcode":"95035",
    "sg:province":"CA",
    "sg:website":"www.losgatoscab.com",
    "wof:name":"Los Gatos Cab",
    "wof:placetype":"venue"
},
  "geometry": {"coordinates":[-121.887272,37.420461],"type":"Point"}
}