{
  "type": "Feature",
  "properties": {
    "addr:full":"141 E. El Camino Mountain View CA 94040",
    "addr:housenumber":"141",
    "addr:postcode":"94040",
    "addr:street":"E. El Camino",
    "iso:country":"US",
    "sg:address":"141 E. El Camino",
    "sg:city":"Mountain View",
    "sg:classifiers":[
        {
            "category":"Shopping",
            "subcategory":"Jewelry",
            "type":"Retail Goods"
        },
        {
            "category":"Home & Garden",
            "subcategory":"Furniture",
            "type":"Retail Goods"
        }
    ],
    "sg:phone":"+1 650 964 7212",
    "sg:postcode":"94040",
    "sg:province":"CA",
    "sg:tags":[
        "store"
    ],
    "sg:website":"www.thehomeconsignmentcenter.com/",
    "wof:name":"Home Consignment Center",
    "wof:placetype":"venue"
},
  "geometry": {"coordinates":[-122.072149,37.37992],"type":"Point"}
}