{
  "type": "Feature",
  "properties": {
    "addr:full":"8431 S Broadway Los Angeles CA 90003",
    "addr:housenumber":"8431",
    "addr:postcode":"90003",
    "addr:street":"S Broadway",
    "iso:country":"US",
    "sg:address":"8431 S Broadway",
    "sg:city":"Los Angeles",
    "sg:classifiers":[
        {
            "category":"Home & Garden",
            "subcategory":"Building Materials",
            "type":"Retail Goods"
        }
    ],
    "sg:phone":"+1 323 778 4089",
    "sg:postcode":"90003",
    "sg:province":"CA",
    "sg:tags":[
        "glass",
        "window",
        "plate"
    ],
    "wof:name":"United Glass & Mirror",
    "wof:placetype":"venue"
},
  "geometry": {"coordinates":[-118.278283,33.961532],"type":"Point"}
}