{
  "type": "Feature",
  "properties": {
    "addr:full":"20 S Abbott Ave Milpitas CA 95035",
    "addr:housenumber":"20",
    "addr:postcode":"95035",
    "addr:street":"S Abbott Ave",
    "iso:country":"US",
    "sg:address":"20 S Abbott Ave",
    "sg:city":"Milpitas",
    "sg:classifiers":[
        {
            "category":"Personal",
            "subcategory":"Beauty Salon",
            "type":"Services"
        }
    ],
    "sg:phone":"+1 408 806 9136",
    "sg:postcode":"95035",
    "sg:province":"CA",
    "wof:name":"Lorna Johnson",
    "wof:placetype":"venue"
},
  "geometry": {"coordinates":[-121.914118,37.42838],"type":"Point"}
}