{
  "type": "Feature",
  "properties": {
    "iso:country":"US",
    "sg:address":"82944 Ave 44",
    "sg:city":"Indio",
    "sg:classifiers":[
        {
            "category":"Retail",
            "subcategory":"Auto Repair",
            "type":"Services"
        }
    ],
    "sg:phone":"+1 760 775 0922",
    "sg:postcode":"92201",
    "sg:province":"CA",
    "sg:tags":[
        "automobile",
        "installation",
        "glass"
    ],
    "wof:name":"Windshield Pros",
    "wof:placetype":"venue"
},
  "geometry": {"coordinates":[-116.216869,33.729555],"type":"Point"}
}