{
  "type": "Feature",
  "properties": {
    "iso:country":"US",
    "sg:address":"1758 Rumrill Blvd",
    "sg:city":"San Pablo",
    "sg:classifiers":[
        {
            "category":"Personal",
            "subcategory":"Beauty Salon",
            "type":"Services"
        }
    ],
    "sg:phone":"+1 510 237 6358",
    "sg:postcode":"94806",
    "sg:province":"CA",
    "wof:name":"Las Camelinas Beauty Salon",
    "wof:placetype":"venue"
},
  "geometry": {"coordinates":[-122.356602,37.958558],"type":"Point"}
}