{
  "type": "Feature",
  "properties": {
    "addr:full":"26371 Santa Rosa Ave Laguna Hills CA 92653",
    "addr:postcode":"26371;92653",
    "addr:street":"Santa Rosa Ave",
    "iso:country":"US",
    "sg:address":"26371 Santa Rosa Ave",
    "sg:city":"Laguna Hills",
    "sg:classifiers":[
        {
            "category":"Manufacturing",
            "subcategory":"Toys & Sporting Goods",
            "type":"Manufacturing & Wholesale Goods"
        }
    ],
    "sg:phone":"+1 949 766 1444",
    "sg:postcode":"92653",
    "sg:province":"CA",
    "sg:tags":[
        "game",
        "vehicle"
    ],
    "wof:name":"Ivey",
    "wof:placetype":"venue"
},
  "geometry": {"coordinates":[-117.70273899999999,33.580396],"type":"Point"}
}