{
  "type": "Feature",
  "properties": {
    "iso:country":"US",
    "sg:address":"503 Waxwing Pl",
    "sg:city":"Davis",
    "sg:classifiers":[
        {
            "category":"Professional",
            "subcategory":"Engineering",
            "type":"Services"
        },
        {
            "category":"Professional",
            "subcategory":"Business Services",
            "type":"Services"
        }
    ],
    "sg:phone":"+1 530 979 6029",
    "sg:postcode":"95616",
    "sg:province":"CA",
    "sg:tags":[
        "consultant",
        "energy",
        "coach",
        "conservation"
    ],
    "wof:name":"Ambiance Building Energy Consulting",
    "wof:placetype":"venue"
},
  "geometry": {"coordinates":[-121.75411200000001,38.574021],"type":"Point"}
}