{
  "type": "Feature",
  "properties": {
    "addr:full":"7636 Fulton Ave North Hollywood CA 91605",
    "addr:housenumber":"7636",
    "addr:postcode":"91605",
    "addr:street":"Fulton Ave",
    "iso:country":"US",
    "sg:address":"7636 Fulton Ave",
    "sg:city":"North Hollywood",
    "sg:classifiers":[
        {
            "category":"Real Estate",
            "subcategory":"Real Estate Operator",
            "type":"Services"
        }
    ],
    "sg:phone":"+1 818 765 1544",
    "sg:postcode":"91605",
    "sg:province":"CA",
    "sg:tags":[
        "apartment"
    ],
    "wof:name":"Fulton Apts",
    "wof:placetype":"venue"
},
  "geometry": {"coordinates":[-118.422504,34.209137],"type":"Point"}
}