{
  "type": "Feature",
  "properties": {
    "iso:country":"US",
    "sg:address":"770 Miraflores",
    "sg:city":"San Pedro",
    "sg:classifiers":[
        {
            "category":"Building & Trades",
            "subcategory":"Construction",
            "type":"Services"
        }
    ],
    "sg:phone":"+1 310 548 7092",
    "sg:postcode":"90731",
    "sg:province":"CA",
    "sg:tags":[
        "contractor"
    ],
    "wof:name":"Covenant Construction",
    "wof:placetype":"venue"
},
  "geometry": {"coordinates":[-118.293656,33.752996],"type":"Point"}
}