{
  "type": "Feature",
  "properties": {
    "addr:full":"3908 Woodruff Ave Long Beach CA 90808",
    "addr:housenumber":"3908",
    "addr:postcode":"90808",
    "addr:street":"Woodruff Ave",
    "iso:country":"US",
    "sg:address":"3908 Woodruff Ave",
    "sg:city":"Long Beach",
    "sg:classifiers":[
        {
            "category":"Organizations",
            "subcategory":"Religious Organization",
            "type":"Services"
        }
    ],
    "sg:phone":"+1 562 425 0034",
    "sg:postcode":"90808",
    "sg:province":"CA",
    "sg:tags":[
        "church"
    ],
    "wof:name":"Woodruff Community Church",
    "wof:placetype":"venue"
},
  "geometry": {"coordinates":[-118.11648099999999,33.829341],"type":"Point"}
}