{
  "type": "Feature",
  "properties": {
    "iso:country":"US",
    "sg:address":"29285 Radio Rd",
    "sg:city":"Barstow",
    "sg:classifiers":[
        {
            "category":"Wholesale",
            "subcategory":"Fruits & Vegetables",
            "type":"Manufacturing & Wholesale Goods"
        }
    ],
    "sg:phone":"+1 760 256 0090",
    "sg:postcode":"92311",
    "sg:province":"CA",
    "wof:name":"Desert Produce",
    "wof:placetype":"venue"
},
  "geometry": {"coordinates":[-117.024272,34.9111],"type":"Point"}
}