{
  "type": "Feature",
  "properties": {
    "iso:country":"US",
    "sg:address":"111 W Ocean Blvd",
    "sg:city":"Long Beach",
    "sg:classifiers":[
        {
            "category":"Insurance",
            "subcategory":"Insurance Agent",
            "type":"Services"
        }
    ],
    "sg:phone":"+1 562 435 6320",
    "sg:postcode":"90802",
    "sg:province":"CA",
    "wof:name":"Northwestern Mutual Financial",
    "wof:placetype":"venue"
},
  "geometry": {"coordinates":[-118.19250700000001,33.767158],"type":"Point"}
}