{
  "type": "Feature",
  "properties": {
    "iso:country":"US",
    "sg:address":"6001 Riza Ave",
    "sg:city":"Sacramento",
    "sg:classifiers":[
        {
            "category":"Real Estate",
            "subcategory":"Real Estate Operator",
            "type":"Services"
        }
    ],
    "sg:phone":"+1 916 424 5624",
    "sg:postcode":"95823",
    "sg:province":"CA",
    "sg:tags":[
        "mobile",
        "home",
        "community"
    ],
    "wof:name":"Preferred Propertys",
    "wof:placetype":"venue"
},
  "geometry": {"coordinates":[-121.434838,38.505395],"type":"Point"}
}