{
  "type": "Feature",
  "properties": {
    "addr:full":"2617 Riverside Boulevard Sacramento CA 95818",
    "addr:housenumber":"2617",
    "addr:postcode":"95818",
    "addr:street":"Riverside Boulevard",
    "iso:country":"US",
    "sg:address":"2617 Riverside Boulevard",
    "sg:city":"Sacramento",
    "sg:classifiers":[
        {
            "category":"Retail",
            "subcategory":"Veterinary Services",
            "type":"Services"
        }
    ],
    "sg:phone":"+1 916 441 4727",
    "sg:postcode":"95818",
    "sg:province":"CA",
    "sg:tags":[
        "veterinarian",
        "specialty"
    ],
    "wof:name":"Lara Anita DVM",
    "wof:placetype":"venue"
},
  "geometry": {"coordinates":[-121.49925500000001,38.561221],"type":"Point"}
}