{
  "type": "Feature",
  "properties": {
    "addr:full":"436 E Florence Ave Los Angeles CA 90003",
    "addr:housenumber":"436",
    "addr:postcode":"90003",
    "addr:street":"E Florence Ave",
    "iso:country":"US",
    "sg:address":"436 E Florence Ave",
    "sg:city":"Los Angeles",
    "sg:classifiers":[
        {
            "category":"Retail",
            "subcategory":"Auto Repair",
            "type":"Services"
        }
    ],
    "sg:phone":"+1 323 778 3446",
    "sg:postcode":"90003",
    "sg:province":"CA",
    "wof:name":"Llamas Auto Repair",
    "wof:placetype":"venue"
},
  "geometry": {"coordinates":[-118.266998,33.974602],"type":"Point"}
}