{
  "type": "Feature",
  "properties": {
    "addr:full":"657 S Rancho Santa Fe Rd San Marcos CA 92078",
    "addr:housenumber":"657",
    "addr:postcode":"92078",
    "addr:street":"S Rancho Santa Fe Rd",
    "iso:country":"US",
    "sg:address":"657 S Rancho Santa Fe Rd",
    "sg:city":"San Marcos",
    "sg:classifiers":[
        {
            "category":"Professional",
            "subcategory":"Management & Consulting",
            "type":"Services"
        }
    ],
    "sg:phone":"+1 760 761 4889",
    "sg:postcode":"92078",
    "sg:province":"CA",
    "sg:tags":[
        "consultant",
        "sport"
    ],
    "wof:name":"Todd Howard",
    "wof:placetype":"venue"
},
  "geometry": {"coordinates":[-117.208094,33.131501],"type":"Point"}
}