{
  "type": "Feature",
  "properties": {
    "iso:country":"US",
    "sg:address":"6107 N el Dorado St",
    "sg:city":"Stockton",
    "sg:classifiers":[
        {
            "category":"Shopping",
            "subcategory":"Clothing, Apparel, & Fashions",
            "type":"Retail Goods"
        }
    ],
    "sg:phone":"+1 209 952 5070",
    "sg:postcode":"95207",
    "sg:province":"CA",
    "wof:name":"98 & Fashion",
    "wof:placetype":"venue"
},
  "geometry": {"coordinates":[-121.30887300000001,38.008435],"type":"Point"}
}