{
  "type": "Feature",
  "properties": {
    "iso:country":"US",
    "sg:address":"121 Adams Ranch Rd",
    "sg:city":"Walnut Creek",
    "sg:classifiers":[
        {
            "category":"Professional",
            "subcategory":"Research",
            "type":"Services"
        }
    ],
    "sg:phone":"+1 925 935 6000",
    "sg:postcode":"94595",
    "sg:province":"CA",
    "sg:tags":[
        "foundation",
        "philanthropic"
    ],
    "wof:name":"National Breast Cancer Rsrch",
    "wof:placetype":"venue"
},
  "geometry": {"coordinates":[-122.061643,37.878523],"type":"Point"}
}