{
  "type": "Feature",
  "properties": {
    "addr:full":"1172 San Pablo Ave Albany CA 94706",
    "addr:housenumber":"1172",
    "addr:postcode":"94706",
    "addr:street":"San Pablo Ave",
    "iso:country":"US",
    "sg:address":"1172 San Pablo Ave",
    "sg:city":"Albany",
    "sg:classifiers":[
        {
            "category":"Professional",
            "subcategory":"Business Services",
            "type":"Services"
        }
    ],
    "sg:phone":"+1 510 559 3456",
    "sg:postcode":"94706",
    "sg:province":"CA",
    "wof:name":"We The People",
    "wof:placetype":"venue"
},
  "geometry": {"coordinates":[-122.296722,37.882792],"type":"Point"}
}