{
  "type": "Feature",
  "properties": {
    "addr:full":"3213 Walnut Ave Fremont CA 94538",
    "addr:housenumber":"3213",
    "addr:postcode":"94538",
    "addr:street":"Walnut Ave",
    "iso:country":"US",
    "sg:address":"3213 Walnut Ave",
    "sg:city":"Fremont",
    "sg:classifiers":[
        {
            "category":"Restaurant",
            "type":"Food & Drink"
        }
    ],
    "sg:phone":"+1 510 792 8945",
    "sg:postcode":"94538",
    "sg:province":"CA",
    "wof:name":"Chili Garden",
    "wof:placetype":"venue"
},
  "geometry": {"coordinates":[-121.978989,37.550517],"type":"Point"}
}