{
  "type": "Feature",
  "properties": {
    "iso:country":"US",
    "sg:address":"19202 S Main Street",
    "sg:city":"Gardena",
    "sg:classifiers":[
        {
            "category":"Home & Garden",
            "subcategory":"Garden Supply",
            "type":"Retail Goods"
        }
    ],
    "sg:phone":"+1 310 527 7750",
    "sg:postcode":"90248",
    "sg:province":"CA",
    "sg:tags":[
        "nursery",
        "gardening"
    ],
    "wof:name":"M B Landscaping & Nursery",
    "wof:placetype":"venue"
},
  "geometry": {"coordinates":[-118.27848299999999,33.855773],"type":"Point"}
}