{
  "type": "Feature",
  "properties": {
    "iso:country":"US",
    "sg:address":"1250 Addison St",
    "sg:city":"Berkeley",
    "sg:classifiers":[
        {
            "category":"Real Estate",
            "subcategory":"Architect",
            "type":"Services"
        }
    ],
    "sg:phone":"+1 510 540 6594",
    "sg:postcode":"94702",
    "sg:province":"CA",
    "sg:tags":[
        "architects'",
        "specification",
        "construction",
        "builders'",
        "architectural"
    ],
    "wof:name":"Starkweather Bondy Architecture Llt",
    "wof:placetype":"venue"
},
  "geometry": {"coordinates":[-122.287308,37.86874],"type":"Point"}
}