{
  "type": "Feature",
  "properties": {
    "addr:full":"15125 Torey Pine Rd Magalia CA 95954",
    "addr:postcode":"15125;95954",
    "addr:street":"Torey Pine Rd",
    "iso:country":"US",
    "sg:address":"15125 Torey Pine Rd",
    "sg:city":"Magalia",
    "sg:classifiers":[
        {
            "category":"Building & Trades",
            "subcategory":"Construction",
            "type":"Services"
        }
    ],
    "sg:phone":"+1 530 873 1835",
    "sg:postcode":"95954",
    "sg:province":"CA",
    "sg:tags":[
        "masonry",
        "contractor"
    ],
    "wof:name":"Cooper Masonry",
    "wof:placetype":"venue"
},
  "geometry": {"coordinates":[-121.60017000000001,39.859871],"type":"Point"}
}