{
  "type": "Feature",
  "properties": {
    "addr:full":"12879 Newtown Rd Redding CA 96003",
    "addr:housenumber":"12879",
    "addr:postcode":"96003",
    "addr:street":"Newtown Rd",
    "iso:country":"US",
    "sg:address":"12879 Newtown Rd",
    "sg:city":"Redding",
    "sg:classifiers":[
        {
            "category":"Building & Trades",
            "subcategory":"Construction",
            "type":"Services"
        },
        {
            "category":"Manufacturing",
            "subcategory":"Lumber",
            "type":"Manufacturing & Wholesale Goods"
        }
    ],
    "sg:phone":"+1 530 275 3273",
    "sg:postcode":"96003",
    "sg:province":"CA",
    "sg:tags":[
        "excavation",
        "logging",
        "contractor"
    ],
    "wof:name":"Petrey Logging Inc.",
    "wof:placetype":"venue"
},
  "geometry": {"coordinates":[-122.39538400000001,40.662576],"type":"Point"}
}