{
  "type": "Feature",
  "properties": {
    "iso:country":"US",
    "sg:address":"3330 Vincent Rd",
    "sg:city":"Pleasant Hill",
    "sg:classifiers":[
        {
            "category":"Building & Trades",
            "subcategory":"Landscaping Services",
            "type":"Services"
        }
    ],
    "sg:phone":"+1 925 933 2862",
    "sg:postcode":"94523",
    "sg:province":"CA",
    "sg:tags":[
        "landscape",
        "contractor"
    ],
    "wof:name":"Plant Decor",
    "wof:placetype":"venue"
},
  "geometry": {"coordinates":[-122.05402,37.94048],"type":"Point"}
}