{
  "type": "Feature",
  "properties": {
    "addr:full":"2326 Bobwhite Ct Fairfield CA 94533",
    "addr:housenumber":"2326",
    "addr:postcode":"94533",
    "addr:street":"Bobwhite Ct",
    "iso:country":"US",
    "sg:address":"2326 Bobwhite Ct",
    "sg:city":"Fairfield",
    "sg:classifiers":[
        {
            "category":"Banks & Credit Unions",
            "subcategory":"Financial Services",
            "type":"Services"
        }
    ],
    "sg:phone":"+1 707 425 2512",
    "sg:postcode":"94533",
    "sg:province":"CA",
    "sg:tags":[
        "trust",
        "management"
    ],
    "wof:name":"Amy L Martin Trust",
    "wof:placetype":"venue"
},
  "geometry": {"coordinates":[-122.010868,38.272019],"type":"Point"}
}