{
  "type": "Feature",
  "properties": {
    "iso:country":"US",
    "sg:address":"12431 Wilshire Blvd",
    "sg:city":"Los Angeles",
    "sg:classifiers":[
        {
            "category":"Real Estate",
            "subcategory":"Real Estate Agent",
            "type":"Services"
        }
    ],
    "sg:phone":"+1 310 207 4000",
    "sg:postcode":"90025",
    "sg:province":"CA",
    "wof:name":"Taylor Co Realtors",
    "wof:placetype":"venue"
},
  "geometry": {"coordinates":[-118.470793,34.041531],"type":"Point"}
}