{
  "type": "Feature",
  "properties": {
    "iso:country":"US",
    "sg:address":"2451 Rockwood Ave",
    "sg:city":"Calexico",
    "sg:classifiers":[
        {
            "category":"Insurance",
            "subcategory":"Insurance Agent",
            "type":"Services"
        },
        {
            "category":"Insurance",
            "subcategory":"Hazard Insurance",
            "type":"Services"
        },
        {
            "category":"Insurance",
            "subcategory":"Title Insurance",
            "type":"Services"
        },
        {
            "category":"Insurance",
            "subcategory":"Life Insurance",
            "type":"Services"
        }
    ],
    "sg:phone":"+1 760 357 9092",
    "sg:postcode":"92231",
    "sg:province":"CA",
    "sg:tags":[
        "business",
        "auto",
        "commercial",
        "homeowner",
        "motorcycle",
        "renter"
    ],
    "wof:name":"Allstate Insurance Company - Lucy Bermudez",
    "wof:placetype":"venue"
},
  "geometry": {"coordinates":[-115.496292,32.69429],"type":"Point"}
}