{
  "type": "Feature",
  "properties": {
    "iso:country":"US",
    "sg:address":"14101 Burbank Blvd",
    "sg:city":"Van Nuys",
    "sg:classifiers":[
        {
            "category":"Shopping",
            "subcategory":"Tobacco",
            "type":"Retail Goods"
        }
    ],
    "sg:phone":"+1 818 786 8255",
    "sg:postcode":"91401",
    "sg:province":"CA",
    "sg:tags":[
        "shop"
    ],
    "wof:name":"Pipeworx Gift & Smoke Shop",
    "wof:placetype":"venue"
},
  "geometry": {"coordinates":[-118.44000200000001,34.172001],"type":"Point"}
}