{
  "type": "Feature",
  "properties": {
    "addr:full":"3530 Bassett St Santa Clara CA 95054",
    "addr:housenumber":"3530",
    "addr:postcode":"95054",
    "addr:street":"Bassett St",
    "iso:country":"US",
    "sg:address":"3530 Bassett St",
    "sg:city":"Santa Clara",
    "sg:classifiers":[
        {
            "category":"Retail",
            "subcategory":"Laundry & Dry Cleaning",
            "type":"Services"
        }
    ],
    "sg:phone":"+1 408 982 0113",
    "sg:postcode":"95054",
    "sg:province":"CA",
    "wof:name":"LSA Clean Part",
    "wof:placetype":"venue"
},
  "geometry": {"coordinates":[-121.951776,37.38369],"type":"Point"}
}