{
  "type": "Feature",
  "properties": {
    "iso:country":"US",
    "sg:address":"391 Taylor Blvd",
    "sg:city":"Pleasant Hill",
    "sg:classifiers":[
        {
            "category":"Insurance",
            "subcategory":"Insurance Agent",
            "type":"Services"
        }
    ],
    "sg:phone":"+1 925 676 0113",
    "sg:postcode":"94523",
    "sg:province":"CA",
    "wof:name":"Allstate Insurance",
    "wof:placetype":"venue"
},
  "geometry": {"coordinates":[-122.070062,37.961213],"type":"Point"}
}