{
  "type": "Feature",
  "properties": {
    "iso:country":"US",
    "sg:address":"337 Locust St",
    "sg:city":"Santa Cruz",
    "sg:classifiers":[
        {
            "category":"Professional",
            "subcategory":"Employment Agencies",
            "type":"Services"
        }
    ],
    "sg:phone":"+1 831 420 5040",
    "sg:postcode":"95060",
    "sg:province":"CA",
    "sg:tags":[
        "executive"
    ],
    "wof:name":"Personnel Dept",
    "wof:placetype":"venue"
},
  "geometry": {"coordinates":[-122.030316,36.974491],"type":"Point"}
}