{
  "type": "Feature",
  "properties": {
    "iso:country":"US",
    "sg:address":"1327 S Maple Ave",
    "sg:city":"Los Angeles",
    "sg:classifiers":[
        {
            "category":"Shopping",
            "subcategory":"Clothing, Apparel, & Fashions",
            "type":"Retail Goods"
        }
    ],
    "sg:postcode":"90015",
    "sg:province":"CA",
    "wof:name":"Lucci",
    "wof:placetype":"venue"
},
  "geometry": {"coordinates":[-118.25781000000001,34.033824],"type":"Point"}
}