{
  "type": "Feature",
  "properties": {
    "iso:country":"US",
    "sg:address":"4228 Giles Ct",
    "sg:city":"Riverside",
    "sg:classifiers":[
        {
            "category":"Building & Trades",
            "subcategory":"Construction",
            "type":"Services"
        }
    ],
    "sg:phone":"+1 951 785 9766",
    "sg:postcode":"92503",
    "sg:province":"CA",
    "sg:tags":[
        "painter"
    ],
    "wof:name":"Park's Professional Painting",
    "wof:placetype":"venue"
},
  "geometry": {"coordinates":[-117.458033,33.923974],"type":"Point"}
}