{
  "type": "Feature",
  "properties": {
    "addr:full":"2100 Metate Ct Placerville CA 95667",
    "addr:housenumber":"2100",
    "addr:postcode":"95667",
    "addr:street":"Metate Ct",
    "iso:country":"US",
    "sg:address":"2100 Metate Ct",
    "sg:city":"Placerville",
    "sg:classifiers":[
        {
            "category":"Transit Center",
            "subcategory":"Freight",
            "type":"Transportation"
        },
        {
            "category":"Freight",
            "type":"Transportation"
        }
    ],
    "sg:phone":"+1 530 622 8116",
    "sg:postcode":"95667",
    "sg:province":"CA",
    "sg:tags":[
        "local",
        "trucking-motor",
        "trucking"
    ],
    "wof:name":"Bill Dunn Trucking",
    "wof:placetype":"venue"
},
  "geometry": {"coordinates":[-120.75353699999999,38.659018],"type":"Point"}
}