{
  "type": "Feature",
  "properties": {
    "iso:country":"US",
    "sg:address":"12111 Buaro St",
    "sg:city":"Garden Grove",
    "sg:classifiers":[
        {
            "category":"Social Services",
            "subcategory":"Child Care",
            "type":"Services"
        },
        {
            "category":"Education",
            "subcategory":"Preschool",
            "type":"Public Place"
        },
        {
            "category":"Education",
            "subcategory":"School",
            "type":"Public Place"
        }
    ],
    "sg:phone":"+1 714 971 5533",
    "sg:postcode":"92840",
    "sg:province":"CA",
    "sg:tags":[
        "high",
        "middle",
        "day",
        "elementary"
    ],
    "wof:name":"Page Summer Camps",
    "wof:placetype":"venue"
},
  "geometry": {"coordinates":[-117.918999,33.787399],"type":"Point"}
}