{
  "type": "Feature",
  "properties": {
    "iso:country":"US",
    "sg:address":"17742 Beach Boulevard Suite 305",
    "sg:city":"Huntington Beach",
    "sg:classifiers":[
        {
            "category":"Health Services",
            "subcategory":"Optometrist",
            "type":"Services"
        }
    ],
    "sg:phone":"+1 714 596 4488",
    "sg:postcode":"92647",
    "sg:province":"CA",
    "wof:name":"Glenda Secor B OD Faao",
    "wof:placetype":"venue"
},
  "geometry": {"coordinates":[-118.00452900000001,33.720618],"type":"Point"}
}