{
  "type": "Feature",
  "properties": {
    "iso:country":"US",
    "sg:address":"605 N 3rd St",
    "sg:city":"El Centro",
    "sg:classifiers":[
        {
            "category":"Freight",
            "type":"Transportation"
        },
        {
            "category":"Wholesale",
            "subcategory":"Chemicals & Plastics",
            "type":"Manufacturing & Wholesale Goods"
        }
    ],
    "sg:phone":"+1 760 353 9116",
    "sg:postcode":"92243",
    "sg:province":"CA",
    "sg:tags":[
        "car",
        "loading",
        "rail",
        "trucking"
    ],
    "wof:name":"Accu Chem Conversion Inc",
    "wof:placetype":"venue"
},
  "geometry": {"coordinates":[-115.54873499999999,32.800173],"type":"Point"}
}