{
  "type": "Feature",
  "properties": {
    "addr:full":"10993 S Central Ave Ontario CA 91762",
    "addr:housenumber":"10993",
    "addr:postcode":"91762",
    "addr:street":"S Central Ave",
    "iso:country":"US",
    "sg:address":"10993 S Central Ave",
    "sg:city":"Ontario",
    "sg:classifiers":[
        {
            "category":"Autos & Motor Vehicles",
            "subcategory":"Automobile Sales",
            "type":"Retail Goods"
        }
    ],
    "sg:phone":"+1 909 591 4116",
    "sg:postcode":"91762",
    "sg:province":"CA",
    "sg:tags":[
        "used",
        "car",
        "dealers-used",
        "new",
        "cars-wholesale"
    ],
    "sg:website":"http://www.randyautosales.com",
    "wof:name":"Randy's Auto Sales",
    "wof:placetype":"venue"
},
  "geometry": {"coordinates":[-117.68925400000001,34.054247],"type":"Point"}
}