{
  "type": "Feature",
  "properties": {
    "iso:country":"US",
    "sg:address":"149 San Miguel Dr",
    "sg:city":"Arcadia",
    "sg:classifiers":[
        {
            "category":"Real Estate",
            "subcategory":"Real Estate Agent",
            "type":"Services"
        }
    ],
    "sg:phone":"+1 626 574 1609",
    "sg:postcode":"91007",
    "sg:province":"CA",
    "wof:name":"Cysco Realty",
    "wof:placetype":"venue"
},
  "geometry": {"coordinates":[-118.03506,34.141436],"type":"Point"}
}