{
  "type": "Feature",
  "properties": {
    "addr:full":"5500 Douglas Blvd Granite Bay CA 95746",
    "addr:housenumber":"5500",
    "addr:postcode":"95746",
    "addr:street":"Douglas Blvd",
    "iso:country":"US",
    "sg:address":"5500 Douglas Blvd",
    "sg:city":"Granite Bay",
    "sg:classifiers":[
        {
            "category":"Professional",
            "type":"Services"
        }
    ],
    "sg:phone":"+1 916 677 2277",
    "sg:postcode":"95746",
    "sg:province":"CA",
    "sg:tags":[
        "establishment"
    ],
    "wof:name":"Luxury Auto Of Calif",
    "wof:placetype":"venue"
},
  "geometry": {"coordinates":[-121.19854100000001,38.744149],"type":"Point"}
}