{
  "type": "Feature",
  "properties": {
    "addr:full":"200 4th St Soledad CA 93960",
    "addr:housenumber":"200",
    "addr:postcode":"93960",
    "addr:street":"4Th St",
    "iso:country":"US",
    "sg:address":"200 4th St",
    "sg:city":"Soledad",
    "sg:classifiers":[
        {
            "category":"Food & Beverages",
            "subcategory":"Groceries & Convenience Stores",
            "type":"Retail Goods"
        }
    ],
    "sg:phone":"+1 831 678 2497",
    "sg:postcode":"93960",
    "sg:province":"CA",
    "sg:tags":[
        "grocer"
    ],
    "wof:name":"Riojas Grocery Store",
    "wof:placetype":"venue"
},
  "geometry": {"coordinates":[-121.31565999999999,36.422531],"type":"Point"}
}