{
  "type": "Feature",
  "properties": {
    "iso:country":"US",
    "sg:address":"2622 Saturn Ave",
    "sg:city":"Huntington Park",
    "sg:classifiers":[
        {
            "category":"Shopping",
            "subcategory":"Clothing, Apparel, & Fashions",
            "type":"Retail Goods"
        }
    ],
    "sg:phone":"+1 323 585 6889",
    "sg:postcode":"90255",
    "sg:province":"CA",
    "sg:tags":[
        "infant",
        "wear"
    ],
    "wof:name":"Royal Star Co",
    "wof:placetype":"venue"
},
  "geometry": {"coordinates":[-118.224956,33.976827],"type":"Point"}
}