{
  "type": "Feature",
  "properties": {
    "addr:full":"3325 Wilshire Blvd Los Angeles CA 90010",
    "addr:housenumber":"3325",
    "addr:postcode":"90010",
    "addr:street":"Wilshire Blvd",
    "iso:country":"US",
    "sg:address":"3325 Wilshire Blvd",
    "sg:city":"Los Angeles",
    "sg:classifiers":[
        {
            "category":"Professional",
            "subcategory":"Business Services",
            "type":"Services"
        }
    ],
    "sg:phone":"+1 213 252 1996",
    "sg:postcode":"90010",
    "sg:province":"CA",
    "sg:tags":[
        "messenger"
    ],
    "wof:name":"M A J's Paralegal Svc & Mssngr",
    "wof:placetype":"venue"
},
  "geometry": {"coordinates":[-118.29469899999999,34.061852],"type":"Point"}
}