{
  "type": "Feature",
  "properties": {
    "addr:full":"1116 Ivar Pl Oxnard CA 93030",
    "addr:housenumber":"1116",
    "addr:postcode":"93030",
    "addr:street":"Ivar Pl",
    "iso:country":"US",
    "sg:address":"1116 Ivar Pl",
    "sg:city":"Oxnard",
    "sg:classifiers":[
        {
            "category":"Arts & Performance",
            "subcategory":"Theater",
            "type":"Entertainment"
        }
    ],
    "sg:phone":"+1 805 386 4467",
    "sg:postcode":"93030",
    "sg:province":"CA",
    "sg:tags":[
        "live",
        "music"
    ],
    "wof:name":"Ambassadors Of Sound",
    "wof:placetype":"venue"
},
  "geometry": {"coordinates":[-119.16935100000001,34.212438],"type":"Point"}
}