{
  "type": "Feature",
  "properties": {
    "iso:country":"US",
    "sg:address":"11769 Kirkwood St",
    "sg:city":"Herald",
    "sg:classifiers":[
        {
            "category":"Farming",
            "subcategory":"Livestock Farm",
            "type":"Manufacturing & Wholesale Goods"
        }
    ],
    "sg:phone":"+1 209 748 2211",
    "sg:postcode":"95638",
    "sg:province":"CA",
    "sg:tags":[
        "specialty",
        "animal"
    ],
    "wof:name":"R Hall & Son Apairies",
    "wof:placetype":"venue"
},
  "geometry": {"coordinates":[-121.145099,38.329053],"type":"Point"}
}