{
  "type": "Feature",
  "properties": {
    "iso:country":"US",
    "sg:address":"5152 Moorpark Ave",
    "sg:city":"San Jose",
    "sg:classifiers":[
        {
            "category":"Bars & Pubs",
            "subcategory":"Lounge",
            "type":"Food & Drink"
        },
        {
            "category":"Bars & Pubs",
            "subcategory":"Dive Bar",
            "type":"Food & Drink"
        }
    ],
    "sg:phone":"+1 408 257 6738",
    "sg:postcode":"95129",
    "sg:province":"CA",
    "wof:name":"Park Lane Lounge",
    "wof:placetype":"venue"
},
  "geometry": {"coordinates":[-121.99400300000001,37.309601],"type":"Point"}
}