{
  "type": "Feature",
  "properties": {
    "addr:full":"10585 Industrial Ave Hanford CA 93230",
    "addr:housenumber":"10585",
    "addr:postcode":"ca 93230",
    "addr:street":"Industrial Ave",
    "iso:country":"US",
    "sg:address":"10585 Industrial Ave",
    "sg:city":"Hanford",
    "sg:classifiers":[
        {
            "category":"Manufacturing",
            "subcategory":"Chemicals & Compounds",
            "type":"Manufacturing & Wholesale Goods"
        }
    ],
    "sg:phone":"+1 559 582 9228",
    "sg:postcode":"93230",
    "sg:province":"CA",
    "sg:tags":[
        "fertilizer"
    ],
    "sg:website":"www.kingminerals.com",
    "wof:name":"Mineral King Minerals",
    "wof:placetype":"venue"
},
  "geometry": {"coordinates":[-119.65158,36.277711],"type":"Point"}
}