{
  "type": "Feature",
  "properties": {
    "iso:country":"US",
    "sg:address":"1894 Freeman Ave.",
    "sg:city":"Signal Hill",
    "sg:classifiers":[
        {
            "category":"Home & Garden",
            "subcategory":"Carpets & Floor Coverings",
            "type":"Retail Goods"
        }
    ],
    "sg:phone":"+1 562 597 4252",
    "sg:postcode":"90755",
    "sg:province":"CA",
    "sg:tags":[
        "flooring"
    ],
    "sg:website":"lukehillerinc.com",
    "wof:name":"Luke Hiller Inc.",
    "wof:placetype":"venue"
},
  "geometry": {"coordinates":[-118.155642,33.790334],"type":"Point"}
}