{
  "type": "Feature",
  "properties": {
    "iso:country":"US",
    "sg:address":"1243 Evelyn Ave",
    "sg:city":"Albany",
    "sg:classifiers":[
        {
            "category":"Professional",
            "type":"Services"
        },
        {
            "category":"Personal",
            "type":"Services"
        }
    ],
    "sg:phone":"+1 510 526 1272",
    "sg:postcode":"94706",
    "sg:province":"CA",
    "sg:tags":[
        "mover",
        "material",
        "moving",
        "services-labor"
    ],
    "wof:name":"Koch Fine Art",
    "wof:placetype":"venue"
},
  "geometry": {"coordinates":[-122.29184600000001,37.88236],"type":"Point"}
}