{
  "type": "Feature",
  "properties": {
    "iso:country":"US",
    "sg:address":"200 Orange Blossom Cir",
    "sg:city":"Folsom",
    "sg:classifiers":[
        {
            "category":"Wholesale",
            "subcategory":"Medical Equipment & Supplies",
            "type":"Manufacturing & Wholesale Goods"
        }
    ],
    "sg:phone":"+1 916 608 9419",
    "sg:postcode":"95630",
    "sg:province":"CA",
    "sg:tags":[
        "physician",
        "surgeon"
    ],
    "wof:name":"Pacific Labeling Plus",
    "wof:placetype":"venue"
},
  "geometry": {"coordinates":[-121.175494,38.645965],"type":"Point"}
}