{
  "type": "Feature",
  "properties": {
    "iso:country":"US",
    "sg:address":"520 S Grand Ave Ste 390",
    "sg:city":"Los Angeles",
    "sg:classifiers":[
        {
            "category":"Professional",
            "subcategory":"Lawyer & Legal Services",
            "type":"Services"
        }
    ],
    "sg:phone":"+1 213 622 9444",
    "sg:postcode":"90071",
    "sg:province":"CA",
    "sg:website":"www.rdcleary.com",
    "wof:name":"Newell Campbell & Roche Llp",
    "wof:placetype":"venue"
},
  "geometry": {"coordinates":[-118.25299800000001,34.050701],"type":"Point"}
}