{
  "type": "Feature",
  "properties": {
    "addr:full":"817 Euclid St Santa Monica CA 90403",
    "addr:housenumber":"817",
    "addr:postcode":"90403",
    "addr:street":"Euclid St",
    "iso:country":"US",
    "sg:address":"817 Euclid St",
    "sg:city":"Santa Monica",
    "sg:classifiers":[
        {
            "category":"Education",
            "subcategory":"Special Training",
            "type":"Public Place"
        }
    ],
    "sg:phone":"+1 310 451 2724",
    "sg:postcode":"90403",
    "sg:province":"CA",
    "sg:tags":[
        "tutoring"
    ],
    "wof:name":"JET Tutoring & Mentoring",
    "wof:placetype":"venue"
},
  "geometry": {"coordinates":[-118.494692,34.030359],"type":"Point"}
}