{
  "type": "Feature",
  "properties": {
    "iso:country":"US",
    "sg:address":"900 E Hamilton Ave",
    "sg:city":"Campbell",
    "sg:classifiers":[
        {
            "category":"Professional",
            "subcategory":"Computer Services",
            "type":"Services"
        },
        {
            "category":"Manufacturing",
            "subcategory":"Printing",
            "type":"Manufacturing & Wholesale Goods"
        }
    ],
    "sg:phone":"+1 408 879 7383",
    "sg:postcode":"95008",
    "sg:province":"CA",
    "sg:tags":[
        "information",
        "site",
        "for",
        "it"
    ],
    "wof:name":"Tech Republic Inc",
    "wof:placetype":"venue"
},
  "geometry": {"coordinates":[-121.935067,37.294242],"type":"Point"}
}