{
  "type": "Feature",
  "properties": {
    "addr:full":"200 Oceangate Ste 1500 Long Beach CA 90802",
    "addr:housenumber":"200",
    "addr:postcode":"90802",
    "addr:street":"Oceangate Ste 1500",
    "iso:country":"US",
    "sg:address":"200 Oceangate Ste 1500",
    "sg:city":"Long Beach",
    "sg:classifiers":[
        {
            "category":"Professional",
            "subcategory":"Lawyer & Legal Services",
            "type":"Services"
        }
    ],
    "sg:phone":"+1 562 901 9800",
    "sg:postcode":"90802",
    "sg:province":"CA",
    "wof:name":"Vosskuhler Derek Attorney At Law",
    "wof:placetype":"venue"
},
  "geometry": {"coordinates":[-118.19899700000001,33.7668],"type":"Point"}
}