{
  "type": "Feature",
  "properties": {
    "iso:country":"US",
    "sg:address":"3800 N State St",
    "sg:city":"Ukiah",
    "sg:classifiers":[
        {
            "category":"Organizations",
            "subcategory":"Religious Organization",
            "type":"Services"
        }
    ],
    "sg:phone":"+1 707 485 8449",
    "sg:postcode":"95482",
    "sg:province":"CA",
    "sg:tags":[
        "church"
    ],
    "wof:name":"Glad Tidings Outreach",
    "wof:placetype":"venue"
},
  "geometry": {"coordinates":[-123.203897,39.200691],"type":"Point"}
}