{
  "type": "Feature",
  "properties": {
    "iso:country":"US",
    "sg:address":"241 N Valley Center Ave",
    "sg:city":"Glendora",
    "sg:classifiers":[
        {
            "category":"Education",
            "subcategory":"School",
            "type":"Public Place"
        }
    ],
    "sg:phone":"+1 626 335 2811",
    "sg:postcode":"91741",
    "sg:province":"CA",
    "sg:tags":[
        "religious"
    ],
    "wof:name":"St Dorothy's CCD",
    "wof:placetype":"venue"
},
  "geometry": {"coordinates":[-117.837391,34.141582],"type":"Point"}
}