{
  "type": "Feature",
  "properties": {
    "addr:full":"2601 W Alameda Ave Ste 302 Burbank CA 91505",
    "addr:housenumber":"2601",
    "addr:postcode":"91505",
    "addr:street":"W Alameda Ave Ste 302",
    "iso:country":"US",
    "sg:address":"2601 W Alameda Ave Ste 302",
    "sg:city":"Burbank",
    "sg:classifiers":[
        {
            "category":"Health Services",
            "subcategory":"Doctor",
            "type":"Services"
        }
    ],
    "sg:phone":"+1 818 729 8548",
    "sg:postcode":"91505",
    "sg:province":"CA",
    "wof:name":"Sanchez Antonio MD",
    "wof:placetype":"venue"
},
  "geometry": {"coordinates":[-118.329002,34.157902],"type":"Point"}
}