{
  "type": "Feature",
  "properties": {
    "addr:full":"117 E Pico Blvd Los Angeles CA 90015",
    "addr:housenumber":"117",
    "addr:postcode":"90015",
    "addr:street":"E Pico Blvd",
    "iso:country":"US",
    "sg:address":"117 E Pico Blvd",
    "sg:city":"Los Angeles",
    "sg:classifiers":[
        {
            "category":"Shopping",
            "subcategory":"Shoes",
            "type":"Retail Goods"
        }
    ],
    "sg:phone":"+1 213 742 0686",
    "sg:postcode":"90015",
    "sg:province":"CA",
    "wof:name":"My Friend Shoes",
    "wof:placetype":"venue"
},
  "geometry": {"coordinates":[-118.259439,34.035892],"type":"Point"}
}