{
  "type": "Feature",
  "properties": {
    "addr:full":"1472 Appalachian Pl Chula Vista CA 91915",
    "addr:housenumber":"1472",
    "addr:postcode":"91915",
    "addr:street":"Appalachian Pl",
    "iso:country":"US",
    "sg:address":"1472 Appalachian Pl",
    "sg:city":"Chula Vista",
    "sg:classifiers":[
        {
            "category":"Building & Trades",
            "subcategory":"Construction",
            "type":"Services"
        }
    ],
    "sg:phone":"+1 619 216 1591",
    "sg:postcode":"91915",
    "sg:province":"CA",
    "sg:tags":[
        "general",
        "contractor"
    ],
    "wof:name":"B Q Construction",
    "wof:placetype":"venue"
},
  "geometry": {"coordinates":[-116.94877099999999,32.633152],"type":"Point"}
}