{
  "type": "Feature",
  "properties": {
    "iso:country":"US",
    "sg:address":"1685 S Hart Rd",
    "sg:city":"Modesto",
    "sg:classifiers":[
        {
            "category":"Farming",
            "subcategory":"Dairy Farm",
            "type":"Manufacturing & Wholesale Goods"
        }
    ],
    "sg:phone":"+1 209 522 6179",
    "sg:postcode":"95358",
    "sg:province":"CA",
    "wof:name":"Meikle Ranch",
    "wof:placetype":"venue"
},
  "geometry": {"coordinates":[-121.122004,37.619903],"type":"Point"}
}