{
  "type": "Feature",
  "properties": {
    "iso:country":"US",
    "sg:address":"19 Son Morell",
    "sg:city":"Laguna Niguel",
    "sg:classifiers":[
        {
            "category":"Manufacturing",
            "subcategory":"Toys & Sporting Goods",
            "type":"Manufacturing & Wholesale Goods"
        }
    ],
    "sg:phone":"+1 949 249 8595",
    "sg:postcode":"92677",
    "sg:province":"CA",
    "sg:tags":[
        "mfg"
    ],
    "wof:name":"Rabbit Magic Company",
    "wof:placetype":"venue"
},
  "geometry": {"coordinates":[-117.702711,33.51873],"type":"Point"}
}