{
  "type": "Feature",
  "properties": {
    "addr:full":"19 Son Morell Laguna Niguel CA 92677",
    "addr:housenumber":"19",
    "addr:postcode":"92677",
    "addr:street":"Son Morell",
    "iso:country":"US",
    "sg:address":"19 Son Morell",
    "sg:city":"Laguna Niguel",
    "sg:classifiers":[
        {
            "category":"Manufacturing",
            "subcategory":"Toys & Sporting Goods",
            "type":"Manufacturing & Wholesale Goods"
        }
    ],
    "sg:phone":"+1 949 249 8595",
    "sg:postcode":"92677",
    "sg:province":"CA",
    "sg:tags":[
        "mfg"
    ],
    "wof:name":"Rabbit Magic Company",
    "wof:placetype":"venue"
},
  "geometry": {"coordinates":[-117.70271099999999,33.51873],"type":"Point"}
}