{
  "type": "Feature",
  "properties": {
    "addr:full":"41780 Christy St Fremont CA 94538",
    "addr:housenumber":"41780",
    "addr:postcode":"94538",
    "addr:street":"Christy St",
    "iso:country":"US",
    "sg:address":"41780 Christy St",
    "sg:city":"Fremont",
    "sg:classifiers":[
        {
            "category":"Manufacturing",
            "subcategory":"Furniture",
            "type":"Manufacturing & Wholesale Goods"
        }
    ],
    "sg:phone":"+1 510 657 7933",
    "sg:postcode":"94538",
    "sg:province":"CA",
    "sg:tags":[
        "wood",
        "mfg"
    ],
    "sg:website":"www.commercialcasework.com",
    "wof:name":"Commercial Casework Inc",
    "wof:placetype":"venue"
},
  "geometry": {"coordinates":[-121.97614799999999,37.509344],"type":"Point"}
}