{
  "type": "Feature",
  "properties": {
    "addr:full":"515 S Landing Rd Crowley Lake CA 93546",
    "addr:housenumber":"515",
    "addr:postcode":"93546",
    "addr:street":"S Landing Rd",
    "iso:country":"US",
    "sg:address":"515 S Landing Rd",
    "sg:city":"Crowley Lake",
    "sg:classifiers":[
        {
            "category":"Real Estate",
            "subcategory":"Real Estate Operator",
            "type":"Services"
        }
    ],
    "sg:phone":"+1 760 935 4221",
    "sg:postcode":"93546",
    "sg:province":"CA",
    "sg:tags":[
        "mobile",
        "home",
        "community"
    ],
    "sg:website":"www.crowleylakerv.com",
    "wof:name":"Crowley Lake Trailer Park",
    "wof:placetype":"venue"
},
  "geometry": {"coordinates":[-118.740576,37.570046],"type":"Point"}
}