{
  "type": "Feature",
  "properties": {
    "iso:country":"US",
    "sg:address":"5159 Fair Oaks Blvd",
    "sg:city":"Carmichael",
    "sg:classifiers":[
        {
            "category":"Banks & Credit Unions",
            "subcategory":"Bank",
            "type":"Services"
        }
    ],
    "sg:phone":"+1 916 488 5106",
    "sg:postcode":"95608",
    "sg:province":"CA",
    "wof:name":"Wells Fargo",
    "wof:placetype":"venue"
},
  "geometry": {"coordinates":[-121.344351,38.597234],"type":"Point"}
}