{
  "type": "Feature",
  "properties": {
    "iso:country":"US",
    "sg:address":"5621 Morse Dr",
    "sg:city":"Oakland",
    "sg:classifiers":[
        {
            "category":"Social Services",
            "subcategory":"Child Care",
            "type":"Services"
        }
    ],
    "sg:phone":"+1 510 533 0516",
    "sg:postcode":"94605",
    "sg:province":"CA",
    "sg:tags":[
        "day"
    ],
    "wof:name":"Marlena's Family Day Care & Preschool",
    "wof:placetype":"venue"
},
  "geometry": {"coordinates":[-122.190735,37.774242],"type":"Point"}
}