{
  "type": "Feature",
  "properties": {
    "iso:country":"US",
    "sg:address":"11355 Barnett Valley Rd",
    "sg:city":"Sebastopol",
    "sg:classifiers":[
        {
            "category":"Banks & Credit Unions",
            "subcategory":"Investment Brokerage",
            "type":"Services"
        }
    ],
    "sg:phone":"+1 707 874 3790",
    "sg:postcode":"95472",
    "sg:province":"CA",
    "sg:tags":[
        "consultant",
        "planning",
        "financial"
    ],
    "wof:name":"Joyce Financial Management",
    "wof:placetype":"venue"
},
  "geometry": {"coordinates":[-122.898029,38.367023],"type":"Point"}
}