{
  "type": "Feature",
  "properties": {
    "iso:country":"US",
    "sg:address":"9841 Airport Blvd",
    "sg:city":"Los Angeles",
    "sg:classifiers":[
        {
            "category":"Banks & Credit Unions",
            "subcategory":"Investment Brokerage",
            "type":"Services"
        }
    ],
    "sg:phone":"+1 310 216 9666",
    "sg:postcode":"90045",
    "sg:province":"CA",
    "sg:tags":[
        "consultant",
        "planning",
        "financial"
    ],
    "wof:name":"Centaurus Financial Inc",
    "wof:placetype":"venue"
},
  "geometry": {"coordinates":[-118.386107,33.945923],"type":"Point"}
}