{
  "type": "Feature",
  "properties": {
    "addr:full":"1674 N Shoreline Blvd Mountain View CA 94043",
    "addr:housenumber":"1674",
    "addr:postcode":"94043",
    "addr:street":"N Shoreline Blvd",
    "iso:country":"US",
    "sg:address":"1674 N Shoreline Blvd",
    "sg:city":"Mountain View",
    "sg:classifiers":[
        {
            "category":"Professional",
            "subcategory":"Detective & Security Services",
            "type":"Services"
        }
    ],
    "sg:phone":"+1 650 941 1962",
    "sg:postcode":"94043",
    "sg:province":"CA",
    "sg:tags":[
        "guard",
        "patrol"
    ],
    "wof:name":"Foothill Securities Inc",
    "wof:placetype":"venue"
},
  "geometry": {"coordinates":[-122.07816,37.416594],"type":"Point"}
}