{
  "type": "Feature",
  "properties": {
    "addr:full":"52 Mason St San Francisco CA 94102",
    "addr:housenumber":"52",
    "addr:postcode":"94102",
    "addr:street":"Mason St",
    "iso:country":"US",
    "sg:address":"52 Mason St",
    "sg:city":"San Francisco",
    "sg:classifiers":[
        {
            "category":"Sports & Exercise",
            "subcategory":"Playing Field",
            "type":"Entertainment"
        }
    ],
    "sg:phone":"+1 415 434 1034",
    "sg:postcode":"94102",
    "sg:province":"CA",
    "sg:tags":[
        "instruction",
        "fitness"
    ],
    "sg:website":"www.straightforwardclub.org",
    "wof:name":"Straight Forward Club Boxing Gym",
    "wof:placetype":"venue"
},
  "geometry": {"coordinates":[-122.409205,37.783787],"type":"Point"}
}