{
  "type": "Feature",
  "properties": {
    "iso:country":"US",
    "sg:address":"10019 Vis Parque",
    "sg:city":"Lakeside",
    "sg:classifiers":[
        {
            "category":"Shopping",
            "subcategory":"Clothing, Apparel, & Fashions",
            "type":"Retail Goods"
        }
    ],
    "sg:phone":"+1 619 838 7434",
    "sg:postcode":"92040",
    "sg:province":"CA",
    "wof:name":"Grind Apparel & Athletics",
    "wof:placetype":"venue"
},
  "geometry": {"coordinates":[-116.904882,32.863448],"type":"Point"}
}