{
  "type": "Feature",
  "properties": {
    "addr:full":"4575 Palm Ave Riverside CA 92501",
    "addr:housenumber":"4575",
    "addr:postcode":"92501",
    "addr:street":"Palm Ave",
    "iso:country":"US",
    "sg:address":"4575 Palm Ave",
    "sg:city":"Riverside",
    "sg:classifiers":[
        {
            "category":"Real Estate",
            "subcategory":"Real Estate Operator",
            "type":"Services"
        }
    ],
    "sg:phone":"+1 951 784 4502",
    "sg:postcode":"92501",
    "sg:province":"CA",
    "sg:tags":[
        "apartment"
    ],
    "wof:name":"Palm Manor",
    "wof:placetype":"venue"
},
  "geometry": {"coordinates":[-117.38915799999999,33.979254],"type":"Point"}
}