{
  "type": "Feature",
  "properties": {
    "addr:full":"1738 Union St San Francisco CA 94123",
    "addr:housenumber":"1738",
    "addr:postcode":"94123",
    "addr:street":"Union St",
    "iso:country":"US",
    "sg:address":"1738 Union St",
    "sg:city":"San Francisco",
    "sg:classifiers":[
        {
            "category":"Shopping",
            "subcategory":"Gifts & Souvenirs",
            "type":"Retail Goods"
        },
        {
            "category":"Shopping",
            "subcategory":"Clothing, Apparel, & Fashions",
            "type":"Retail Goods"
        }
    ],
    "sg:phone":"+1 415 921 0838",
    "sg:postcode":"94123",
    "sg:province":"CA",
    "sg:tags":[
        "shop",
        "bridal",
        "commercial"
    ],
    "wof:name":"Forget-Me-Knots Bridal",
    "wof:placetype":"venue"
},
  "geometry": {"coordinates":[-122.428421,37.79808],"type":"Point"}
}