{
  "type": "Feature",
  "properties": {
    "iso:country":"US",
    "sg:address":"218 W Main St",
    "sg:city":"Visalia",
    "sg:classifiers":[
        {
            "category":"Shopping",
            "subcategory":"Books",
            "type":"Retail Goods"
        }
    ],
    "sg:phone":"+1 559 635 2347",
    "sg:postcode":"93291",
    "sg:province":"CA",
    "sg:tags":[
        "dealer"
    ],
    "wof:name":"Sequoia Natural History Assn",
    "wof:placetype":"venue"
},
  "geometry": {"coordinates":[-119.294393,36.330221],"type":"Point"}
}