{
  "type": "Feature",
  "properties": {
    "iso:country":"US",
    "sg:address":"284 E Arrow Hwy",
    "sg:city":"San Dimas",
    "sg:classifiers":[
        {
            "category":"Professional",
            "subcategory":"Accounting & Tax Preparation",
            "type":"Services"
        }
    ],
    "sg:phone":"+1 909 599 6118",
    "sg:postcode":"91773",
    "sg:province":"CA",
    "sg:tags":[
        "billing"
    ],
    "wof:name":"Accubill Inc",
    "wof:placetype":"venue"
},
  "geometry": {"coordinates":[-117.80675100000001,34.102887],"type":"Point"}
}