{
  "type": "Feature",
  "properties": {
    "addr:full":"2447 E Chapman Ave Fullerton CA 92831",
    "addr:housenumber":"2447",
    "addr:postcode":"92831",
    "addr:street":"E Chapman Ave",
    "iso:country":"US",
    "sg:address":"2447 E Chapman Ave",
    "sg:city":"Fullerton",
    "sg:classifiers":[
        {
            "category":"Personal",
            "subcategory":"Beauty Salon",
            "type":"Services"
        },
        {
            "category":"Personal",
            "subcategory":"Hair Removal",
            "type":"Services"
        },
        {
            "category":"Personal",
            "subcategory":"Skin Care",
            "type":"Services"
        }
    ],
    "sg:phone":"+1 714 398 9730",
    "sg:postcode":"92831",
    "sg:province":"CA",
    "sg:website":"www.myeyebrowthreading.com",
    "wof:name":"Sameera Eyebrow Threading And Full Service Salon",
    "wof:placetype":"venue"
},
  "geometry": {"coordinates":[-117.887981,33.874304],"type":"Point"}
}