{
  "type": "Feature",
  "properties": {
    "addr:full":"4511 Las Posas Rd Camarillo CA 93010",
    "addr:housenumber":"4511",
    "addr:postcode":"93010",
    "addr:street":"Las Posas Rd",
    "iso:country":"US",
    "sg:address":"4511 Las Posas Rd",
    "sg:city":"Camarillo",
    "sg:classifiers":[
        {
            "category":"Restaurant",
            "type":"Food & Drink"
        }
    ],
    "sg:phone":"+1 805 484 8233",
    "sg:postcode":"93010",
    "sg:province":"CA",
    "wof:name":"Jack-In-the-Box Family Restaurants",
    "wof:placetype":"venue"
},
  "geometry": {"coordinates":[-119.012001,34.243099],"type":"Point"}
}