{
  "type": "Feature",
  "properties": {
    "iso:country":"US",
    "sg:address":"4433 53rd St",
    "sg:city":"Sacramento",
    "sg:classifiers":[
        {
            "category":"Building & Trades",
            "subcategory":"Construction",
            "type":"Services"
        }
    ],
    "sg:phone":"+1 916 455 9360",
    "sg:postcode":"95820",
    "sg:province":"CA",
    "sg:tags":[
        "roofing",
        "contractor"
    ],
    "wof:name":"Brace Roofing",
    "wof:placetype":"venue"
},
  "geometry": {"coordinates":[-121.444338,38.533535],"type":"Point"}
}