{
  "type": "Feature",
  "properties": {
    "addr:full":"4433 53rd St Sacramento CA 95820",
    "addr:housenumber":"4433",
    "addr:postcode":"95820",
    "addr:street":"53Rd St",
    "iso:country":"US",
    "sg:address":"4433 53rd St",
    "sg:city":"Sacramento",
    "sg:classifiers":[
        {
            "category":"Building & Trades",
            "subcategory":"Construction",
            "type":"Services"
        }
    ],
    "sg:phone":"+1 916 455 9360",
    "sg:postcode":"95820",
    "sg:province":"CA",
    "sg:tags":[
        "roofing",
        "contractor"
    ],
    "wof:name":"Brace Roofing",
    "wof:placetype":"venue"
},
  "geometry": {"coordinates":[-121.444338,38.533535],"type":"Point"}
}