{
  "type": "Feature",
  "properties": {
    "iso:country":"US",
    "sg:address":"31332 Via Colinas",
    "sg:city":"Westlake Village",
    "sg:classifiers":[
        {
            "category":"Real Estate",
            "subcategory":"Architect",
            "type":"Services"
        }
    ],
    "sg:phone":"+1 805 379 2404",
    "sg:postcode":"91362",
    "sg:province":"CA",
    "wof:name":"Baker Hogan Houx",
    "wof:placetype":"venue"
},
  "geometry": {"coordinates":[-118.80633,34.156505],"type":"Point"}
}