{
  "type": "Feature",
  "properties": {
    "addr:full":"2940 Potomac Ave Bakersfield CA 93307",
    "addr:housenumber":"2940",
    "addr:postcode":"93307",
    "addr:street":"Potomac Ave",
    "iso:country":"US",
    "sg:address":"2940 Potomac Ave",
    "sg:city":"Bakersfield",
    "sg:classifiers":[
        {
            "category":"Organizations",
            "subcategory":"Religious Organization",
            "type":"Services"
        }
    ],
    "sg:phone":"+1 661 327 8944",
    "sg:postcode":"93307",
    "sg:province":"CA",
    "sg:tags":[
        "church"
    ],
    "wof:name":"Centro De Companerismo",
    "wof:placetype":"venue"
},
  "geometry": {"coordinates":[-118.950982,35.365118],"type":"Point"}
}