{
  "type": "Feature",
  "properties": {
    "addr:full":"3835 Cross Creek Rd Malibu CA 90265",
    "addr:housenumber":"3835",
    "addr:postcode":"90265",
    "addr:street":"Cross Creek Rd",
    "iso:country":"US",
    "sg:address":"3835 Cross Creek Rd",
    "sg:city":"Malibu",
    "sg:classifiers":[
        {
            "category":"Restaurant",
            "type":"Food & Drink"
        }
    ],
    "sg:phone":"+1 310 317 9140",
    "sg:postcode":"90265",
    "sg:province":"CA",
    "sg:tags":[
        "eating"
    ],
    "wof:name":"Nobu Malibu",
    "wof:placetype":"venue"
},
  "geometry": {"coordinates":[-118.685574,34.036355],"type":"Point"}
}