{
  "type": "Feature",
  "properties": {
    "iso:country":"US",
    "sg:address":"345 N Maple Dr",
    "sg:city":"Beverly Hills",
    "sg:classifiers":[
        {
            "category":"Professional",
            "type":"Services"
        }
    ],
    "sg:phone":"+1 310 246 1396",
    "sg:postcode":"90210",
    "sg:province":"CA",
    "wof:name":"Murray Ruth Grbin Chrtble Fnda",
    "wof:placetype":"venue"
},
  "geometry": {"coordinates":[-118.39357099999999,34.074865],"type":"Point"}
}