{
  "type": "Feature",
  "properties": {
    "iso:country":"US",
    "sg:address":"1666 20th St",
    "sg:city":"Santa Monica",
    "sg:classifiers":[
        {
            "category":"Real Estate",
            "subcategory":"Developer",
            "type":"Services"
        }
    ],
    "sg:phone":"+1 310 264 1666",
    "sg:postcode":"90404",
    "sg:province":"CA",
    "wof:name":"Shapco Inc",
    "wof:placetype":"venue"
},
  "geometry": {"coordinates":[-118.475542,34.024879],"type":"Point"}
}