{
  "type": "Feature",
  "properties": {
    "iso:country":"US",
    "sg:address":"1278 Sartori Ave",
    "sg:city":"Torrance",
    "sg:classifiers":[
        {
            "category":"Shopping",
            "subcategory":"Used Merchandise",
            "type":"Retail Goods"
        }
    ],
    "sg:phone":"+1 310 782 0534",
    "sg:postcode":"90501",
    "sg:province":"CA",
    "sg:tags":[
        "antique"
    ],
    "wof:name":"Peek Inside",
    "wof:placetype":"venue"
},
  "geometry": {"coordinates":[-118.31631299999999,33.835785],"type":"Point"}
}