{
  "type": "Feature",
  "properties": {
    "addr:full":"3791 Harrison St Oakland CA 94611",
    "addr:housenumber":"3791",
    "addr:postcode":"94611",
    "addr:street":"Harrison St",
    "iso:country":"US",
    "sg:address":"3791 Harrison St",
    "sg:city":"Oakland",
    "sg:classifiers":[
        {
            "category":"Shopping",
            "subcategory":"Hobbies, Toys, & Games",
            "type":"Retail Goods"
        }
    ],
    "sg:phone":"+1 510 658 6515",
    "sg:postcode":"94611",
    "sg:province":"CA",
    "sg:tags":[
        "shop",
        "ceramics-equipment",
        "supply"
    ],
    "wof:name":"J A Cline Ceramics",
    "wof:placetype":"venue"
},
  "geometry": {"coordinates":[-122.252348,37.821028],"type":"Point"}
}