{
  "type": "Feature",
  "properties": {
    "addr:full":"750 Mason St Vacaville CA 95688",
    "addr:housenumber":"750",
    "addr:postcode":"95688",
    "addr:street":"Mason St",
    "iso:country":"US",
    "sg:address":"750 Mason St",
    "sg:city":"Vacaville",
    "sg:classifiers":[
        {
            "category":"Real Estate",
            "subcategory":"Real Estate Services",
            "type":"Services"
        }
    ],
    "sg:phone":"+1 707 446 9575",
    "sg:postcode":"95688",
    "sg:province":"CA",
    "sg:tags":[
        "company",
        "title"
    ],
    "wof:name":"North American Title Co",
    "wof:placetype":"venue"
},
  "geometry": {"coordinates":[-121.98308400000001,38.354983],"type":"Point"}
}