{
  "type": "Feature",
  "properties": {
    "iso:country":"US",
    "sg:address":"8833 Sunset Blvd 3rd Fl",
    "sg:city":"West Hollywood",
    "sg:classifiers":[
        {
            "category":"Personal",
            "type":"Services"
        }
    ],
    "sg:phone":"+1 310 460 4656",
    "sg:postcode":"90046",
    "sg:province":"CA",
    "sg:tags":[
        "party",
        "planning",
        "event"
    ],
    "sg:website":"www.evite.com",
    "wof:name":"Evite",
    "wof:placetype":"venue"
},
  "geometry": {"coordinates":[-118.38408200000001,34.090656],"type":"Point"}
}