{
  "type": "Feature",
  "properties": {
    "addr:full":"10 N Gate Rd Fairfield CA 94598",
    "addr:housenumber":"10",
    "addr:postcode":"94598",
    "addr:street":"N Gate Rd",
    "iso:country":"US",
    "sg:address":"10 N Gate Rd",
    "sg:city":"Fairfield",
    "sg:classifiers":[
        {
            "category":"Building & Trades",
            "subcategory":"Construction",
            "type":"Services"
        }
    ],
    "sg:phone":"+1 707 427 1426",
    "sg:postcode":"94598",
    "sg:province":"CA",
    "sg:tags":[
        "contractor"
    ],
    "wof:name":"Wirth Construction",
    "wof:placetype":"venue"
},
  "geometry": {"coordinates":[-122.00697,37.913601],"type":"Point"}
}