{
  "type": "Feature",
  "properties": {
    "addr:full":"25344 Cypress Ave Hayward CA 94544",
    "addr:housenumber":"25344",
    "addr:postcode":"94544",
    "addr:street":"Cypress Ave",
    "iso:country":"US",
    "sg:address":"25344 Cypress Ave",
    "sg:city":"Hayward",
    "sg:classifiers":[
        {
            "category":"Retail",
            "subcategory":"Auto Repair",
            "type":"Services"
        }
    ],
    "sg:phone":"+1 510 677 6472",
    "sg:postcode":"94544",
    "sg:province":"CA",
    "sg:tags":[
        "wrecker"
    ],
    "wof:name":"Johnny's Towing",
    "wof:placetype":"venue"
},
  "geometry": {"coordinates":[-122.086192,37.65028],"type":"Point"}
}