{
  "type": "Feature",
  "properties": {
    "addr:full":"2433 E Main St Visalia CA 93292",
    "addr:housenumber":"2433",
    "addr:postcode":"93292",
    "addr:street":"E Main St",
    "iso:country":"US",
    "sg:address":"2433 E Main St",
    "sg:city":"Visalia",
    "sg:classifiers":[
        {
            "category":"Autos & Motor Vehicles",
            "subcategory":"Automobile Sales",
            "type":"Retail Goods"
        }
    ],
    "sg:phone":"+1 559 733 3278",
    "sg:postcode":"93292",
    "sg:province":"CA",
    "sg:tags":[
        "car",
        "dealer"
    ],
    "wof:name":"Burns Auto Sales",
    "wof:placetype":"venue"
},
  "geometry": {"coordinates":[-119.265164,36.328671],"type":"Point"}
}