{
  "type": "Feature",
  "properties": {
    "addr:full":"7625 San Luis Ave Atascadero CA 93422",
    "addr:housenumber":"7625",
    "addr:postcode":"93422",
    "addr:street":"San Luis Ave",
    "iso:country":"US",
    "sg:address":"7625 San Luis Ave",
    "sg:city":"Atascadero",
    "sg:classifiers":[
        {
            "category":"Health Services",
            "subcategory":"Doctor",
            "type":"Services"
        },
        {
            "category":"Utilities",
            "subcategory":"Refuse",
            "type":"Services"
        },
        {
            "category":"Utilities",
            "subcategory":"Recycling",
            "type":"Services"
        },
        {
            "category":"Shopping",
            "subcategory":"Discount & Variety Stores",
            "type":"Retail Goods"
        }
    ],
    "sg:phone":"+1 866 684 3139",
    "sg:postcode":"93422",
    "sg:province":"CA",
    "sg:tags":[
        "disposal-medical",
        "surplus",
        "garbage",
        "disposal",
        "collection",
        "equipment",
        "waste",
        "salvage",
        "merchandise"
    ],
    "sg:website":"http://centralcoast.citysearch.com/profile/external/756653/atascadero_ca/waste_management_atascadero_waste_alternatives_inc.html?publisher=yellowpages&reference_id=1&placement=ypwebsitemip",
    "wof:name":"Waste Management - Atascadero Waste Alternatives Inc",
    "wof:placetype":"venue"
},
  "geometry": {"coordinates":[-120.658238,35.477592],"type":"Point"}
}