{
  "type": "Feature",
  "properties": {
    "iso:country":"US",
    "sg:address":"9938 Bolsa Ave",
    "sg:city":"Westminster",
    "sg:classifiers":[
        {
            "category":"Travel",
            "subcategory":"Travel Agent",
            "type":"Entertainment"
        }
    ],
    "sg:phone":"+1 714 531 6492",
    "sg:postcode":"92683",
    "sg:province":"CA",
    "sg:tags":[
        "agency"
    ],
    "wof:name":"Trans Travel",
    "wof:placetype":"venue"
},
  "geometry": {"coordinates":[-117.955429,33.744857],"type":"Point"}
}