{
  "type": "Feature",
  "properties": {
    "addr:full":"24056 Hesperian Blvd Hayward CA 94545",
    "addr:housenumber":"24056",
    "addr:postcode":"94545",
    "addr:street":"Hesperian Blvd",
    "iso:country":"US",
    "sg:address":"24056 Hesperian Blvd",
    "sg:city":"Hayward",
    "sg:classifiers":[
        {
            "category":"Personal",
            "subcategory":"Barber",
            "type":"Services"
        }
    ],
    "sg:phone":"+1 510 783 1087",
    "sg:postcode":"94545",
    "sg:province":"CA",
    "wof:name":"Margarets Beauty Salon",
    "wof:placetype":"venue"
},
  "geometry": {"coordinates":[-122.110001,37.652302],"type":"Point"}
}