{
  "type": "Feature",
  "properties": {
    "iso:country":"US",
    "sg:address":"6155 W 75th Pl",
    "sg:city":"Los Angeles",
    "sg:classifiers":[
        {
            "category":"Arts & Performance",
            "subcategory":"Theater",
            "type":"Entertainment"
        }
    ],
    "sg:phone":"+1 310 670 9100",
    "sg:postcode":"90045",
    "sg:province":"CA",
    "sg:tags":[
        "television",
        "program",
        "producer"
    ],
    "wof:name":"Pacific Coast Productions",
    "wof:placetype":"venue"
},
  "geometry": {"coordinates":[-118.391589,33.972149],"type":"Point"}
}