{
  "type": "Feature",
  "properties": {
    "iso:country":"US",
    "sg:address":"850 Ventura Blvd",
    "sg:city":"Camarillo",
    "sg:classifiers":[
        {
            "category":"Shopping",
            "type":"Retail Goods"
        }
    ],
    "sg:phone":"+1 805 383 6353",
    "sg:postcode":"93010",
    "sg:province":"CA",
    "sg:tags":[
        "factory",
        "outlet"
    ],
    "wof:name":"Polo Ralph Lauren Jeans Co",
    "wof:placetype":"venue"
},
  "geometry": {"coordinates":[-119.06013900000001,34.217933],"type":"Point"}
}