{
  "type": "Feature",
  "properties": {
    "iso:country":"US",
    "sg:address":"4 Westmoreland Pl",
    "sg:city":"Pasadena",
    "sg:classifiers":[
        {
            "category":"Restaurant",
            "type":"Food & Drink"
        },
        {
            "category":"Museum",
            "type":"Entertainment"
        },
        {
            "category":"Landmark",
            "subcategory":"Historic",
            "type":"Public Place"
        },
        {
            "category":"Organizations",
            "subcategory":"Community Association",
            "type":"Services"
        },
        {
            "category":"Government",
            "subcategory":"Office",
            "type":"Public Place"
        }
    ],
    "sg:phone":"+1 626 793 3334",
    "sg:postcode":"91103",
    "sg:province":"CA",
    "sg:tags":[
        "building",
        "local",
        "historical",
        "village",
        "township",
        "government-city",
        "flavor"
    ],
    "sg:website":"www.gamblehouse.org",
    "wof:name":"Gamble House",
    "wof:placetype":"venue"
},
  "geometry": {"coordinates":[-118.16100299999999,34.150799],"type":"Point"}
}