{
  "type": "Feature",
  "properties": {
    "addr:full":"2138 Court St Redding CA 96001",
    "addr:housenumber":"2138",
    "addr:postcode":"96001",
    "addr:street":"Court St",
    "iso:country":"US",
    "sg:address":"2138 Court St",
    "sg:city":"Redding",
    "sg:classifiers":[
        {
            "category":"Health Services",
            "subcategory":"Doctor",
            "type":"Services"
        }
    ],
    "sg:phone":"+1 530 247 7234",
    "sg:postcode":"96001",
    "sg:province":"CA",
    "sg:tags":[
        "physician",
        "surgeon"
    ],
    "wof:name":"Lilly Jamm MD",
    "wof:placetype":"venue"
},
  "geometry": {"coordinates":[-122.392803,40.576054],"type":"Point"}
}