{
  "type": "Feature",
  "properties": {
    "iso:country":"US",
    "sg:address":"230 N Kenwood st.",
    "sg:city":"Burbank",
    "sg:classifiers":[
        {
            "category":"Building & Trades",
            "subcategory":"Construction",
            "type":"Services"
        },
        {
            "category":"Building & Trades",
            "subcategory":"Electrical",
            "type":"Services"
        }
    ],
    "sg:phone":"+1 818 371 1617",
    "sg:postcode":"91505",
    "sg:province":"CA",
    "sg:tags":[
        "electrician",
        "contractor"
    ],
    "wof:name":"Brice James Electrical Services",
    "wof:placetype":"venue"
},
  "geometry": {"coordinates":[-118.34308,34.154854],"type":"Point"}
}