{
  "type": "Feature",
  "properties": {
    "iso:country":"US",
    "sg:address":"2451 Eastman Ave",
    "sg:city":"Oxnard",
    "sg:classifiers":[
        {
            "category":"Manufacturing",
            "subcategory":"Chemicals & Compounds",
            "type":"Manufacturing & Wholesale Goods"
        }
    ],
    "sg:phone":"+1 805 485 1614",
    "sg:postcode":"93030",
    "sg:province":"CA",
    "sg:tags":[
        "mfg"
    ],
    "wof:name":"Decco Cerexagri",
    "wof:placetype":"venue"
},
  "geometry": {"coordinates":[-119.142977,34.199035],"type":"Point"}
}