{
  "type": "Feature",
  "properties": {
    "addr:full":"2440 Bancroft Way Berkeley CA 94704",
    "addr:housenumber":"2440",
    "addr:postcode":"94704",
    "addr:street":"Bancroft Way",
    "iso:country":"US",
    "sg:address":"2440 Bancroft Way",
    "sg:city":"Berkeley",
    "sg:classifiers":[
        {
            "category":"Coffee & Tea",
            "type":"Food & Drink"
        },
        {
            "category":"Food & Beverages",
            "subcategory":"Bakery",
            "type":"Retail Goods"
        }
    ],
    "sg:phone":"+1 510 845 6039",
    "sg:postcode":"94704",
    "sg:province":"CA",
    "sg:tags":[
        "sandwich"
    ],
    "wof:name":"Cafe Espresso Experience",
    "wof:placetype":"venue"
},
  "geometry": {"coordinates":[-122.261002,37.8685],"type":"Point"}
}