{
  "type": "Feature",
  "properties": {
    "iso:country":"US",
    "sg:address":"3821 Victoria Ave",
    "sg:city":"Oxnard",
    "sg:classifiers":[
        {
            "category":"Organizations",
            "subcategory":"Community Association",
            "type":"Services"
        }
    ],
    "sg:phone":"+1 805 984 0211",
    "sg:postcode":"93035",
    "sg:province":"CA",
    "sg:tags":[
        "club"
    ],
    "wof:name":"Anacapa Yacht Club",
    "wof:placetype":"venue"
},
  "geometry": {"coordinates":[-119.221782,34.164428],"type":"Point"}
}