{
  "type": "Feature",
  "properties": {
    "iso:country":"US",
    "sg:address":"9000 Vanalden Ave",
    "sg:city":"Northridge",
    "sg:classifiers":[
        {
            "category":"Arts & Performance",
            "subcategory":"Theater",
            "type":"Entertainment"
        }
    ],
    "sg:phone":"+1 818 886 2386",
    "sg:postcode":"91324",
    "sg:province":"CA",
    "sg:tags":[
        "bureau"
    ],
    "wof:name":"Slam Identity Entertainment",
    "wof:placetype":"venue"
},
  "geometry": {"coordinates":[-118.54919599999999,34.235236],"type":"Point"}
}