{
  "type": "Feature",
  "properties": {
    "iso:country":"US",
    "sg:address":"8416 Pershing Dr",
    "sg:city":"Los Angeles",
    "sg:classifiers":[
        {
            "category":"Personal",
            "subcategory":"Massage",
            "type":"Services"
        }
    ],
    "sg:phone":"+1 310 822 3668",
    "sg:postcode":"90293",
    "sg:province":"CA",
    "wof:name":"Massage For Your Health",
    "wof:placetype":"venue"
},
  "geometry": {"coordinates":[-118.442461,33.956965],"type":"Point"}
}