{
  "type": "Feature",
  "properties": {
    "iso:country":"US",
    "sg:address":"777 E Tahquitz Canyon Way",
    "sg:city":"Palm Springs",
    "sg:classifiers":[
        {
            "category":"Building & Trades",
            "subcategory":"Construction",
            "type":"Services"
        }
    ],
    "sg:phone":"+1 760 416 5172",
    "sg:postcode":"92262",
    "sg:province":"CA",
    "sg:tags":[
        "contractor"
    ],
    "wof:name":"PSI General Contractors",
    "wof:placetype":"venue"
},
  "geometry": {"coordinates":[-116.541535,33.823053],"type":"Point"}
}