{
  "type": "Feature",
  "properties": {
    "iso:country":"US",
    "sg:address":"1312 Laurel St",
    "sg:city":"San Carlos",
    "sg:classifiers":[
        {
            "category":"Shopping",
            "subcategory":"Florist",
            "type":"Retail Goods"
        }
    ],
    "sg:phone":"+1 650 594 9956",
    "sg:postcode":"94070",
    "sg:province":"CA",
    "wof:name":"White Oak Flower Shoppe",
    "wof:placetype":"venue"
},
  "geometry": {"coordinates":[-122.24982799999999,37.497057],"type":"Point"}
}