{
  "type": "Feature",
  "properties": {
    "iso:country":"US",
    "sg:address":"246 Noice Dr",
    "sg:city":"Salinas",
    "sg:classifiers":[
        {
            "category":"Retail",
            "subcategory":"Laundry & Dry Cleaning",
            "type":"Services"
        }
    ],
    "sg:phone":"+1 831 442 0585",
    "sg:postcode":"93906",
    "sg:province":"CA",
    "sg:tags":[
        "cleaners",
        "rug",
        "carpet"
    ],
    "wof:name":"Deering & Sons",
    "wof:placetype":"venue"
},
  "geometry": {"coordinates":[-121.650981,36.700641],"type":"Point"}
}