{
  "type": "Feature",
  "properties": {
    "iso:country":"US",
    "sg:address":"6405 Wilshire Blvd",
    "sg:city":"Los Angeles",
    "sg:classifiers":[
        {
            "category":"Restaurant",
            "type":"Food & Drink"
        }
    ],
    "sg:phone":"+1 323 852 1915",
    "sg:postcode":"90048",
    "sg:province":"CA",
    "sg:website":"www.lagondola.com",
    "wof:name":"LA Gondola",
    "wof:placetype":"venue"
},
  "geometry": {"coordinates":[-118.371328,34.064176],"type":"Point"}
}