{
  "type": "Feature",
  "properties": {
    "iso:country":"US",
    "sg:address":"8 W 6th St",
    "sg:city":"Eureka",
    "sg:classifiers":[
        {
            "category":"Wholesale",
            "subcategory":"Auto Parts",
            "type":"Manufacturing & Wholesale Goods"
        }
    ],
    "sg:phone":"+1 707 443 1723",
    "sg:postcode":"95501",
    "sg:province":"CA",
    "sg:tags":[
        "truck",
        "accessory"
    ],
    "sg:website":"www.redwoodmarine.com",
    "wof:name":"Tri-State Distributing",
    "wof:placetype":"venue"
},
  "geometry": {"coordinates":[-124.171132,40.800396],"type":"Point"}
}