{
  "type": "Feature",
  "properties": {
    "iso:country":"US",
    "sg:address":"1387 Los Angeles Ave",
    "sg:city":"Ventura",
    "sg:classifiers":[
        {
            "category":"Building & Trades",
            "subcategory":"Equipment Rental",
            "type":"Services"
        }
    ],
    "sg:phone":"+1 805 647 9718",
    "sg:postcode":"93004",
    "sg:province":"CA",
    "sg:tags":[
        "contractor"
    ],
    "wof:name":"U Rent Inc",
    "wof:placetype":"venue"
},
  "geometry": {"coordinates":[-119.147302,34.282615],"type":"Point"}
}