{
  "type": "Feature",
  "properties": {
    "iso:country":"US",
    "sg:address":"451 N Rodeo Dr",
    "sg:city":"Beverly Hills",
    "sg:classifiers":[
        {
            "category":"Shopping",
            "subcategory":"Clothing, Apparel, & Fashions",
            "type":"Retail Goods"
        }
    ],
    "sg:phone":"+1 310 385 9343",
    "sg:postcode":"90210",
    "sg:province":"CA",
    "sg:tags":[
        "accessory",
        "clothing",
        "women's"
    ],
    "sg:website":"www.maxmara.com",
    "wof:name":"Maxmara",
    "wof:placetype":"venue"
},
  "geometry": {"coordinates":[-118.404019,34.070088],"type":"Point"}
}