{
  "type": "Feature",
  "properties": {
    "iso:country":"US",
    "sg:address":"5702 S Broadway Ste D",
    "sg:city":"Los Angeles",
    "sg:classifiers":[
        {
            "category":"Government",
            "subcategory":"Office",
            "type":"Public Place"
        }
    ],
    "sg:phone":"+1 323 235 0500",
    "sg:postcode":"90037",
    "sg:province":"CA",
    "sg:tags":[
        "smog",
        "check"
    ],
    "wof:name":"Pro Auto Center",
    "wof:placetype":"venue"
},
  "geometry": {"coordinates":[-118.278015,33.990425],"type":"Point"}
}