{
  "type": "Feature",
  "properties": {
    "iso:country":"US",
    "sg:address":"11800 Wilmington Ave",
    "sg:city":"Los Angeles",
    "sg:classifiers":[
        {
            "category":"Fast Food",
            "type":"Food & Drink"
        }
    ],
    "sg:phone":"+1 323 564 3448",
    "sg:postcode":"90059",
    "sg:province":"CA",
    "sg:website":"www.mcdonalds.com",
    "wof:name":"McDonald's",
    "wof:placetype":"venue"
},
  "geometry": {"coordinates":[-118.239029,33.926014],"type":"Point"}
}