{
  "type": "Feature",
  "properties": {
    "addr:full":"18484 Valley Blvd Bloomington CA 92316",
    "addr:housenumber":"18484",
    "addr:postcode":"92316",
    "addr:street":"Valley Blvd",
    "iso:country":"US",
    "sg:address":"18484 Valley Blvd",
    "sg:city":"Bloomington",
    "sg:classifiers":[
        {
            "category":"Food & Beverages",
            "subcategory":"Groceries & Convenience Stores",
            "type":"Retail Goods"
        }
    ],
    "sg:phone":"+1 909 877 1435",
    "sg:postcode":"92316",
    "sg:province":"CA",
    "wof:name":"Sav-A-Minit Markets Inc",
    "wof:placetype":"venue"
},
  "geometry": {"coordinates":[-117.40210500000001,34.070545],"type":"Point"}
}