{
  "type": "Feature",
  "properties": {
    "addr:full":"16297 Harbor Blvd Fountain Valley CA 92708",
    "addr:housenumber":"16297",
    "addr:postcode":"92708",
    "addr:street":"Harbor Blvd",
    "iso:country":"US",
    "sg:address":"16297 Harbor Blvd",
    "sg:city":"Fountain Valley",
    "sg:classifiers":[
        {
            "category":"Health Services",
            "subcategory":"Dentist",
            "type":"Services"
        }
    ],
    "sg:phone":"+1 714 839 8514",
    "sg:postcode":"92708",
    "sg:province":"CA",
    "sg:website":"www.joechendds.com",
    "wof:name":"Chen Joe J DDS",
    "wof:placetype":"venue"
},
  "geometry": {"coordinates":[-117.91999800000001,33.728298],"type":"Point"}
}