{
  "type": "Feature",
  "properties": {
    "addr:full":"435 Main St Watsonville CA 95076",
    "addr:housenumber":"435",
    "addr:postcode":"95076",
    "addr:street":"Main St",
    "iso:country":"US",
    "sg:address":"435 Main St",
    "sg:city":"Watsonville",
    "sg:classifiers":[
        {
            "category":"Organizations",
            "subcategory":"Community Association",
            "type":"Services"
        }
    ],
    "sg:phone":"+1 831 724 6305",
    "sg:postcode":"95076",
    "sg:province":"CA",
    "sg:tags":[
        "fraternal"
    ],
    "wof:name":"IOOF",
    "wof:placetype":"venue"
},
  "geometry": {"coordinates":[-121.75797300000001,36.911069],"type":"Point"}
}