{
  "type": "Feature",
  "properties": {
    "iso:country":"US",
    "sg:address":"9170 Elk Grove Florin Rd",
    "sg:city":"Elk Grove",
    "sg:classifiers":[
        {
            "category":"Shopping",
            "type":"Retail Goods"
        }
    ],
    "sg:phone":"+1 916 685 4444",
    "sg:postcode":"95624",
    "sg:province":"CA",
    "sg:tags":[
        "telephone",
        "cellular"
    ],
    "wof:name":"Cellular Warehouse",
    "wof:placetype":"venue"
},
  "geometry": {"coordinates":[-121.371669,38.425437],"type":"Point"}
}