{
  "type": "Feature",
  "properties": {
    "addr:full":"3 Wakonda Trabuco Canyon CA 92679",
    "addr:housenumber":"3",
    "addr:postcode":"92679",
    "addr:street":"Wakonda",
    "iso:country":"US",
    "sg:address":"3 Wakonda",
    "sg:city":"Trabuco Canyon",
    "sg:classifiers":[
        {
            "category":"Shopping",
            "subcategory":"Catalog Store",
            "type":"Retail Goods"
        }
    ],
    "sg:phone":"+1 949 888 7585",
    "sg:postcode":"92679",
    "sg:province":"CA",
    "sg:tags":[
        "mail",
        "house"
    ],
    "wof:name":"S2s",
    "wof:placetype":"venue"
},
  "geometry": {"coordinates":[-117.571215,33.63314],"type":"Point"}
}