{
  "type": "Feature",
  "properties": {
    "iso:country":"US",
    "sg:address":"42061 Wagon Wheel Ln",
    "sg:city":"Murrieta",
    "sg:classifiers":[
        {
            "category":"Shopping",
            "type":"Retail Goods"
        }
    ],
    "sg:phone":"+1 951 698 3505",
    "sg:postcode":"92562",
    "sg:province":"CA",
    "sg:tags":[
        "cover"
    ],
    "wof:name":"RJB Enterprise",
    "wof:placetype":"venue"
},
  "geometry": {"coordinates":[-117.232001,33.567012],"type":"Point"}
}