{
  "type": "Feature",
  "properties": {
    "addr:full":"910 N Alpine Dr Beverly Hills CA 90210",
    "addr:housenumber":"910",
    "addr:postcode":"90210",
    "addr:street":"N Alpine Dr",
    "iso:country":"US",
    "sg:address":"910 N Alpine Dr",
    "sg:city":"Beverly Hills",
    "sg:classifiers":[
        {
            "category":"Professional",
            "type":"Services"
        }
    ],
    "sg:phone":"+1 310 274 0681",
    "sg:postcode":"90210",
    "sg:province":"CA",
    "wof:name":"Milan Blanca Roven Foundation",
    "wof:placetype":"venue"
},
  "geometry": {"coordinates":[-118.40855000000001,34.086076],"type":"Point"}
}