{
  "type": "Feature",
  "properties": {
    "iso:country":"US",
    "sg:address":"4931 Durfee Ave",
    "sg:city":"Pico Rivera",
    "sg:classifiers":[
        {
            "category":"Retail",
            "subcategory":"Repair Shop",
            "type":"Services"
        }
    ],
    "sg:phone":"+1 562 695 0019",
    "sg:postcode":"90660",
    "sg:province":"CA",
    "sg:tags":[
        "repairing",
        "piano",
        "refinishing"
    ],
    "wof:name":"John J Gonzales",
    "wof:placetype":"venue"
},
  "geometry": {"coordinates":[-118.078841,34.001203],"type":"Point"}
}