{
  "type": "Feature",
  "properties": {
    "iso:country":"US",
    "sg:address":"4908 Heston Way",
    "sg:city":"Ceres",
    "sg:classifiers":[
        {
            "category":"Shopping",
            "subcategory":"Catalog Store",
            "type":"Retail Goods"
        }
    ],
    "sg:phone":"+1 209 538 5827",
    "sg:postcode":"95307",
    "sg:province":"CA",
    "sg:tags":[
        "mail",
        "house"
    ],
    "wof:name":"Creative Fantasies",
    "wof:placetype":"venue"
},
  "geometry": {"coordinates":[-120.924654,37.566346],"type":"Point"}
}