{
  "type": "Feature",
  "properties": {
    "iso:country":"US",
    "sg:address":"10445 White Oak Ave",
    "sg:city":"Granada Hills",
    "sg:classifiers":[
        {
            "category":"Insurance",
            "subcategory":"Insurance Agent",
            "type":"Services"
        }
    ],
    "sg:phone":"+1 818 366 1818",
    "sg:postcode":"91344",
    "sg:province":"CA",
    "wof:name":"Lewis Greenstein Associates",
    "wof:placetype":"venue"
},
  "geometry": {"coordinates":[-118.519868,34.259071],"type":"Point"}
}