{
  "type": "Feature",
  "properties": {
    "iso:country":"US",
    "sg:address":"1030 Marina Village Pkwy",
    "sg:city":"Alameda",
    "sg:classifiers":[
        {
            "category":"Recreation",
            "subcategory":"Marina",
            "type":"Entertainment"
        }
    ],
    "sg:phone":"+1 510 521 0905",
    "sg:postcode":"94501",
    "sg:province":"CA",
    "sg:website":"http://www.marinavillageharbor.com",
    "wof:name":"Marina Village Yacht Harbor",
    "wof:placetype":"venue"
},
  "geometry": {"coordinates":[-122.27096400000001,37.784225],"type":"Point"}
}