{
  "type": "Feature",
  "properties": {
    "iso:country":"US",
    "sg:address":"10818 State Hwy 99",
    "sg:city":"Los Molinos",
    "sg:classifiers":[
        {
            "category":"Education",
            "subcategory":"School",
            "type":"Public Place"
        }
    ],
    "sg:phone":"+1 530 527 5162",
    "sg:postcode":"96055",
    "sg:province":"CA",
    "sg:website":"www.lvuesd.tehama.k12.ca.us",
    "wof:name":"Lassen View Union Elementary",
    "wof:placetype":"venue"
},
  "geometry": {"coordinates":[-122.107398,40.105013],"type":"Point"}
}