{
  "type": "Feature",
  "properties": {
    "iso:country":"US",
    "sg:address":"17240 Iron Mountain Dr",
    "sg:city":"Poway",
    "sg:classifiers":[
        {
            "category":"Shopping",
            "type":"Retail Goods"
        }
    ],
    "sg:phone":"+1 858 705 3844",
    "sg:postcode":"92064",
    "sg:province":"CA",
    "sg:tags":[
        "merchandise"
    ],
    "wof:name":"Pontsler Emporium",
    "wof:placetype":"venue"
},
  "geometry": {"coordinates":[-116.963605,32.9641],"type":"Point"}
}