{
  "type": "Feature",
  "properties": {
    "addr:full":"4040 Hwy 128 Geyserville CA 95441",
    "addr:housenumber":"4040",
    "addr:postcode":"95441",
    "addr:street":"Hwy 128",
    "iso:country":"US",
    "sg:address":"4040 Hwy 128",
    "sg:city":"Geyserville",
    "sg:classifiers":[
        {
            "category":"Farming",
            "subcategory":"Vineyard",
            "type":"Manufacturing & Wholesale Goods"
        }
    ],
    "sg:phone":"+1 707 857 4232",
    "sg:postcode":"95441",
    "sg:province":"CA",
    "wof:name":"Murphy Ranch Vineyard",
    "wof:placetype":"venue"
},
  "geometry": {"coordinates":[-122.84418599999999,38.688189],"type":"Point"}
}