{
  "type": "Feature",
  "properties": {
    "addr:full":"1309 N Magnolia Ave El Cajon CA 92020",
    "addr:housenumber":"1309",
    "addr:postcode":"92020",
    "addr:street":"N Magnolia Ave",
    "iso:country":"US",
    "sg:address":"1309 N Magnolia Ave",
    "sg:city":"El Cajon",
    "sg:classifiers":[
        {
            "category":"Building & Trades",
            "subcategory":"Equipment Rental",
            "type":"Services"
        }
    ],
    "sg:phone":"+1 619 579 1015",
    "sg:postcode":"92020",
    "sg:province":"CA",
    "wof:name":"Rector Equipment",
    "wof:placetype":"venue"
},
  "geometry": {"coordinates":[-116.96224100000001,32.815766],"type":"Point"}
}