{
  "type": "Feature",
  "properties": {
    "addr:full":"10825 Arrow Rte Rancho Cucamonga CA 91730",
    "addr:housenumber":"10825",
    "addr:postcode":"91730",
    "addr:street":"Arrow Rte",
    "iso:country":"US",
    "sg:address":"10825 Arrow Rte",
    "sg:city":"Rancho Cucamonga",
    "sg:classifiers":[
        {
            "category":"Government",
            "subcategory":"Office",
            "type":"Public Place"
        }
    ],
    "sg:phone":"+1 909 945 0700",
    "sg:postcode":"91730",
    "sg:province":"CA",
    "sg:tags":[
        "county",
        "resource"
    ],
    "wof:name":"San Bernardino Cnty Social Svc",
    "wof:placetype":"venue"
},
  "geometry": {"coordinates":[-117.572557,34.099128],"type":"Point"}
}