{
  "type": "Feature",
  "properties": {
    "iso:country":"US",
    "sg:address":"2826 Octavia St",
    "sg:city":"San Francisco",
    "sg:classifiers":[
        {
            "category":"Professional",
            "type":"Services"
        }
    ],
    "sg:phone":"+1 415 929 7445",
    "sg:postcode":"94123",
    "sg:province":"CA",
    "wof:name":"CK Wong Inc",
    "wof:placetype":"venue"
},
  "geometry": {"coordinates":[-122.428988,37.798622],"type":"Point"}
}