{
  "type": "Feature",
  "properties": {
    "iso:country":"US",
    "sg:address":"47355 Rainbow Canyon Rd",
    "sg:city":"Temecula",
    "sg:classifiers":[
        {
            "category":"Freight",
            "type":"Transportation"
        }
    ],
    "sg:phone":"+1 951 693 2343",
    "sg:postcode":"92592",
    "sg:province":"CA",
    "sg:tags":[
        "general"
    ],
    "wof:name":"A Plus Storage",
    "wof:placetype":"venue"
},
  "geometry": {"coordinates":[-117.135539,33.442553],"type":"Point"}
}