{
  "type": "Feature",
  "properties": {
    "addr:full":"186 E 48th St Los Angeles CA 90011",
    "addr:housenumber":"186",
    "addr:postcode":"90011",
    "addr:street":"E 48Th St",
    "iso:country":"US",
    "sg:address":"186 E 48th St",
    "sg:city":"Los Angeles",
    "sg:classifiers":[
        {
            "category":"Travel",
            "subcategory":"Travel Agent",
            "type":"Entertainment"
        }
    ],
    "sg:phone":"+1 323 233 3872",
    "sg:postcode":"90011",
    "sg:province":"CA",
    "sg:tags":[
        "operator",
        "tour"
    ],
    "wof:name":"V&R Tours",
    "wof:placetype":"venue"
},
  "geometry": {"coordinates":[-118.27337799999999,33.999167],"type":"Point"}
}