{
  "type": "Feature",
  "properties": {
    "addr:full":"570 Westside Rd Healdsburg CA 95448",
    "addr:housenumber":"570",
    "addr:postcode":"95448",
    "addr:street":"Westside Rd",
    "iso:country":"US",
    "sg:address":"570 Westside Rd",
    "sg:city":"Healdsburg",
    "sg:classifiers":[
        {
            "category":"Organizations",
            "subcategory":"Non-profit Organization",
            "type":"Services"
        }
    ],
    "sg:phone":"+1 707 431 3386",
    "sg:postcode":"95448",
    "sg:province":"CA",
    "sg:website":"www.healdsburgshelter.org",
    "wof:name":"Healdsburg Animal Shelter",
    "wof:placetype":"venue"
},
  "geometry": {"coordinates":[-122.881968,38.604472],"type":"Point"}
}