{
  "type": "Feature",
  "properties": {
    "addr:full":"2525 K St Sacramento CA 95816",
    "addr:housenumber":"2525",
    "addr:postcode":"95816",
    "addr:street":"K St",
    "iso:country":"US",
    "sg:address":"2525 K St",
    "sg:city":"Sacramento",
    "sg:classifiers":[
        {
            "category":"Professional",
            "subcategory":"Secretarial Services",
            "type":"Services"
        }
    ],
    "sg:phone":"+1 916 962 6449",
    "sg:postcode":"95816",
    "sg:province":"CA",
    "sg:tags":[
        "answering",
        "telephone"
    ],
    "wof:name":"Jackson If Nq Answer",
    "wof:placetype":"venue"
},
  "geometry": {"coordinates":[-121.473401,38.573742],"type":"Point"}
}