{
  "type": "Feature",
  "properties": {
    "addr:full":"1000 Beacon St Brea CA 92821",
    "addr:housenumber":"1000",
    "addr:postcode":"92821",
    "addr:street":"Beacon",
    "iso:country":"US",
    "sg:address":"1000 Beacon St",
    "sg:city":"Brea",
    "sg:classifiers":[
        {
            "category":"Professional",
            "type":"Services"
        }
    ],
    "sg:phone":"+1 714 533 1944",
    "sg:postcode":"92821",
    "sg:province":"CA",
    "wof:name":"SERVPRO",
    "wof:placetype":"venue"
},
  "geometry": {"coordinates":[-117.91349,33.9266],"type":"Point"}
}