{
  "type": "Feature",
  "properties": {
    "iso:country":"US",
    "sg:address":"6036 Ferguson Dr",
    "sg:city":"Los Angeles",
    "sg:classifiers":[
        {
            "category":"Wholesale",
            "subcategory":"Machinery & Supplies",
            "type":"Manufacturing & Wholesale Goods"
        }
    ],
    "sg:phone":"+1 323 888 6783",
    "sg:postcode":"90022",
    "sg:province":"CA",
    "sg:tags":[
        "equipment",
        "industrial"
    ],
    "wof:name":"3 Aces Forklift Service",
    "wof:placetype":"venue"
},
  "geometry": {"coordinates":[-118.143126,34.009326],"type":"Point"}
}