{
  "type": "Feature",
  "properties": {
    "addr:full":"15420 Brookhurst St Westminster CA 92683",
    "addr:housenumber":"15420",
    "addr:postcode":"92683",
    "addr:street":"Brookhurst St",
    "iso:country":"US",
    "sg:address":"15420 Brookhurst St",
    "sg:city":"Westminster",
    "sg:classifiers":[
        {
            "category":"Restaurant",
            "type":"Food & Drink"
        }
    ],
    "sg:phone":"+1 714 839 9096",
    "sg:postcode":"92683",
    "sg:province":"CA",
    "sg:tags":[
        "vietnamese"
    ],
    "wof:name":"Pho 54",
    "wof:placetype":"venue"
},
  "geometry": {"coordinates":[-117.95500199999999,33.738602],"type":"Point"}
}