{
  "type": "Feature",
  "properties": {
    "addr:full":"1711 McKee Rd San Jose CA 95116",
    "addr:housenumber":"1711",
    "addr:postcode":"95116",
    "addr:street":"Mckee Rd",
    "iso:country":"US",
    "sg:address":"1711 McKee Rd",
    "sg:city":"San Jose",
    "sg:classifiers":[
        {
            "category":"Restaurant",
            "type":"Food & Drink"
        }
    ],
    "sg:phone":"+1 408 876 7724",
    "sg:postcode":"95116",
    "sg:province":"CA",
    "sg:tags":[
        "mexican"
    ],
    "wof:name":"Calle 10 Catering",
    "wof:placetype":"venue"
},
  "geometry": {"coordinates":[-121.860692,37.358902],"type":"Point"}
}