{
  "type": "Feature",
  "properties": {
    "iso:country":"US",
    "sg:address":"2410 Wardlow Rd",
    "sg:city":"Corona",
    "sg:classifiers":[
        {
            "category":"Autos & Motor Vehicles",
            "subcategory":"Motorcycle Sales",
            "type":"Retail Goods"
        }
    ],
    "sg:phone":"+1 951 371 4467",
    "sg:postcode":"92880",
    "sg:province":"CA",
    "sg:tags":[
        "scooter"
    ],
    "wof:name":"Indian Motorcycle",
    "wof:placetype":"venue"
},
  "geometry": {"coordinates":[-117.620957,33.882196],"type":"Point"}
}