{
  "type": "Feature",
  "properties": {
    "iso:country":"US",
    "sg:address":"273 N Cleveland St",
    "sg:city":"Orange",
    "sg:classifiers":[
        {
            "category":"Social Services",
            "subcategory":"Child Care",
            "type":"Services"
        }
    ],
    "sg:phone":"+1 714 289 8977",
    "sg:postcode":"92866",
    "sg:province":"CA",
    "sg:tags":[
        "day"
    ],
    "wof:name":"Old Towne Family Childcare",
    "wof:placetype":"venue"
},
  "geometry": {"coordinates":[-117.848,33.7911],"type":"Point"}
}