{
  "type": "Feature",
  "properties": {
    "addr:full":"9377 E 9th St Rancho Cucamonga CA 91730",
    "addr:housenumber":"9377",
    "addr:postcode":"91730",
    "addr:street":"E 9Th St",
    "iso:country":"US",
    "sg:address":"9377 E 9th St",
    "sg:city":"Rancho Cucamonga",
    "sg:classifiers":[
        {
            "category":"Wholesale",
            "subcategory":"Auto Parts",
            "type":"Manufacturing & Wholesale Goods"
        }
    ],
    "sg:phone":"+1 909 481 3870",
    "sg:postcode":"91730",
    "sg:province":"CA",
    "sg:tags":[
        "body",
        "automobile",
        "shop"
    ],
    "wof:name":"El Monte Auto Paint",
    "wof:placetype":"venue"
},
  "geometry": {"coordinates":[-117.601529,34.095629],"type":"Point"}
}