{
  "type": "Feature",
  "properties": {
    "addr:full":"1950 Naomi Ave Los Angeles CA 90011",
    "addr:housenumber":"1950",
    "addr:postcode":"90011",
    "addr:street":"Naomi Ave",
    "iso:country":"US",
    "sg:address":"1950 Naomi Ave",
    "sg:city":"Los Angeles",
    "sg:classifiers":[
        {
            "category":"Manufacturing",
            "subcategory":"Textiles",
            "type":"Manufacturing & Wholesale Goods"
        }
    ],
    "sg:phone":"+1 213 741 0188",
    "sg:postcode":"90011",
    "sg:province":"CA",
    "sg:tags":[
        "fabric"
    ],
    "sg:website":"www.designtextiles.com",
    "wof:name":"Design Textiles",
    "wof:placetype":"venue"
},
  "geometry": {"coordinates":[-118.248042,34.023027],"type":"Point"}
}