{
  "type": "Feature",
  "properties": {
    "addr:full":"3716 Palo Verde Ave Long Beach CA 90808",
    "addr:housenumber":"3716",
    "addr:postcode":"90808",
    "addr:street":"Palo Verde Ave",
    "iso:country":"US",
    "sg:address":"3716 Palo Verde Ave",
    "sg:city":"Long Beach",
    "sg:classifiers":[
        {
            "category":"Building & Trades",
            "subcategory":"Construction",
            "type":"Services"
        }
    ],
    "sg:phone":"+1 562 425 5444",
    "sg:postcode":"90808",
    "sg:province":"CA",
    "sg:tags":[
        "painting",
        "contractor"
    ],
    "wof:name":"Savalas Painting",
    "wof:placetype":"venue"
},
  "geometry": {"coordinates":[-118.107714,33.826954],"type":"Point"}
}