{
  "type": "Feature",
  "properties": {
    "addr:full":"513 S La Brea Ave Inglewood CA 90301",
    "addr:housenumber":"513",
    "addr:postcode":"90301",
    "addr:street":"S;Brea Ave",
    "iso:country":"US",
    "sg:address":"513 S La Brea Ave",
    "sg:city":"Inglewood",
    "sg:classifiers":[
        {
            "category":"Retail",
            "subcategory":"Auto Repair",
            "type":"Services"
        }
    ],
    "sg:phone":"+1 310 419 7700",
    "sg:postcode":"90301",
    "sg:province":"CA",
    "sg:tags":[
        "body",
        "shop"
    ],
    "wof:name":"Airport Collision Repair Center",
    "wof:placetype":"venue"
},
  "geometry": {"coordinates":[-118.352997,33.957901],"type":"Point"}
}