{
  "type": "Feature",
  "properties": {
    "addr:full":"2699 Florin Rd Sacramento CA 95822",
    "addr:housenumber":"2699",
    "addr:postcode":"95822",
    "addr:street":"Florin Rd",
    "iso:country":"US",
    "sg:address":"2699 Florin Rd",
    "sg:city":"Sacramento",
    "sg:classifiers":[
        {
            "category":"Recreation",
            "type":"Entertainment"
        }
    ],
    "sg:phone":"+1 916 424 5425",
    "sg:postcode":"95822",
    "sg:province":"CA",
    "sg:tags":[
        "martial",
        "arts",
        "instruction"
    ],
    "wof:name":"Robinson's Taekwondo",
    "wof:placetype":"venue"
},
  "geometry": {"coordinates":[-121.48035,38.49577],"type":"Point"}
}