{
  "type": "Feature",
  "properties": {
    "addr:full":"1521 Chico Ave South El Monte CA 91733",
    "addr:housenumber":"1521",
    "addr:postcode":"91733",
    "addr:street":"Chico Ave",
    "iso:country":"US",
    "sg:address":"1521 Chico Ave",
    "sg:city":"South El Monte",
    "sg:classifiers":[
        {
            "category":"Freight",
            "type":"Transportation"
        }
    ],
    "sg:phone":"+1 626 279 7700",
    "sg:postcode":"91733",
    "sg:province":"CA",
    "sg:tags":[
        "trucking"
    ],
    "wof:name":"Met Transport Inc",
    "wof:placetype":"venue"
},
  "geometry": {"coordinates":[-118.060062,34.047167],"type":"Point"}
}