{
  "type": "Feature",
  "properties": {
    "addr:full":"945 S Main Ave Fallbrook CA 92028",
    "addr:housenumber":"945",
    "addr:postcode":"92028",
    "addr:street":"S Main Ave",
    "iso:country":"US",
    "sg:address":"945 S Main Ave",
    "sg:city":"Fallbrook",
    "sg:classifiers":[
        {
            "category":"Restaurant",
            "type":"Food & Drink"
        }
    ],
    "sg:phone":"+1 760 728 8940",
    "sg:postcode":"92028",
    "sg:province":"CA",
    "sg:tags":[
        "mexican"
    ],
    "wof:name":"Pedro's Tacos",
    "wof:placetype":"venue"
},
  "geometry": {"coordinates":[-117.25099899999999,33.3741],"type":"Point"}
}