{
  "type": "Feature",
  "properties": {
    "addr:full":"27070 Baseline St Highland CA 92346",
    "addr:housenumber":"27070",
    "addr:postcode":"92346",
    "addr:street":"Baseline St",
    "iso:country":"US",
    "sg:address":"27070 Baseline St",
    "sg:city":"Highland",
    "sg:classifiers":[
        {
            "category":"Real Estate",
            "subcategory":"Real Estate Operator",
            "type":"Services"
        }
    ],
    "sg:phone":"+1 909 864 2118",
    "sg:postcode":"92346",
    "sg:province":"CA",
    "sg:tags":[
        "apartment"
    ],
    "wof:name":"Base Palm Apartments",
    "wof:placetype":"venue"
},
  "geometry": {"coordinates":[-117.21267400000001,34.121235],"type":"Point"}
}