{
  "type": "Feature",
  "properties": {
    "addr:full":"541 Cowper St Palo Alto CA 94301",
    "addr:housenumber":"541",
    "addr:postcode":"94301",
    "addr:street":"Cowper St",
    "iso:country":"US",
    "sg:address":"541 Cowper St",
    "sg:city":"Palo Alto",
    "sg:classifiers":[
        {
            "category":"Real Estate",
            "subcategory":"Real Estate Agent",
            "type":"Services"
        }
    ],
    "sg:phone":"+1 650 322 4506",
    "sg:postcode":"94301",
    "sg:province":"CA",
    "sg:website":"www.taylorproperties.com",
    "wof:name":"Taylor Properties",
    "wof:placetype":"venue"
},
  "geometry": {"coordinates":[-122.158625,37.448043],"type":"Point"}
}