{
  "type": "Feature",
  "properties": {
    "addr:full":"2440 E Thompson Blvd Ventura CA 93003",
    "addr:housenumber":"2440",
    "addr:postcode":"93003",
    "addr:street":"E Thompson Blvd",
    "iso:country":"US",
    "sg:address":"2440 E Thompson Blvd",
    "sg:city":"Ventura",
    "sg:classifiers":[
        {
            "category":"Autos & Motor Vehicles",
            "subcategory":"Automobile Sales",
            "type":"Retail Goods"
        }
    ],
    "sg:phone":"+1 805 652 6800",
    "sg:postcode":"93003",
    "sg:province":"CA",
    "sg:tags":[
        "car",
        "dealer"
    ],
    "wof:name":"ABC Motors Inc",
    "wof:placetype":"venue"
},
  "geometry": {"coordinates":[-119.264746,34.273217],"type":"Point"}
}