{
  "type": "Feature",
  "properties": {
    "iso:country":"US",
    "sg:address":"541 N Main St",
    "sg:city":"Corona",
    "sg:classifiers":[
        {
            "category":"Professional",
            "subcategory":"Business Services",
            "type":"Services"
        }
    ],
    "sg:phone":"+1 951 734 7708",
    "sg:postcode":"92880",
    "sg:province":"CA",
    "sg:tags":[
        "packaging"
    ],
    "wof:name":"UPS Store",
    "wof:placetype":"venue"
},
  "geometry": {"coordinates":[-117.564875,33.884386],"type":"Point"}
}