{
  "type": "Feature",
  "properties": {
    "iso:country":"US",
    "sg:address":"9033 Santa Monica Blvd",
    "sg:city":"West Hollywood",
    "sg:classifiers":[
        {
            "category":"Home & Garden",
            "subcategory":"Garden Supply",
            "type":"Retail Goods"
        },
        {
            "category":"Shopping",
            "subcategory":"Florist",
            "type":"Retail Goods"
        }
    ],
    "sg:phone":"+1 310 278 1988",
    "sg:postcode":"90069",
    "sg:province":"CA",
    "sg:tags":[
        "nursery",
        "gardening"
    ],
    "sg:website":"www.emptyvase.com",
    "wof:name":"The Empty Vase Florist",
    "wof:placetype":"venue"
},
  "geometry": {"coordinates":[-118.38800000000001,34.082199],"type":"Point"}
}