{
  "type": "Feature",
  "properties": {
    "iso:country":"US",
    "sg:address":"3224 W Florida Ave",
    "sg:city":"Hemet",
    "sg:classifiers":[
        {
            "category":"Shopping",
            "subcategory":"Stationery & Office Supplies",
            "type":"Retail Goods"
        }
    ],
    "sg:phone":"+1 951 766 1050",
    "sg:postcode":"92545",
    "sg:province":"CA",
    "sg:tags":[
        "equipment"
    ],
    "sg:website":"www.cartridgeworld.com",
    "wof:name":"Cartridge World",
    "wof:placetype":"venue"
},
  "geometry": {"coordinates":[-117.739277,33.747518],"type":"Point"}
}