{
  "type": "Feature",
  "properties": {
    "addr:full":"3760 Hatton St San Diego CA 92111",
    "addr:housenumber":"3760",
    "addr:postcode":"92111",
    "addr:street":"Hatton St",
    "iso:country":"US",
    "sg:address":"3760 Hatton St",
    "sg:city":"San Diego",
    "sg:classifiers":[
        {
            "category":"Building & Trades",
            "subcategory":"Construction",
            "type":"Services"
        }
    ],
    "sg:phone":"+1 858 268 9567",
    "sg:postcode":"92111",
    "sg:province":"CA",
    "sg:tags":[
        "contractor"
    ],
    "wof:name":"Carlo Cirioni Construction",
    "wof:placetype":"venue"
},
  "geometry": {"coordinates":[-117.16597400000001,32.812929],"type":"Point"}
}