{
  "type": "Feature",
  "properties": {
    "addr:full":"11822 Downey Avenue Downey CA 90241",
    "addr:housenumber":"11822",
    "addr:postcode":"90241",
    "addr:street":"Downey Avenue",
    "iso:country":"US",
    "sg:address":"11822 Downey Avenue",
    "sg:city":"Downey",
    "sg:classifiers":[
        {
            "category":"Banks & Credit Unions",
            "subcategory":"Financial Services",
            "type":"Services"
        }
    ],
    "sg:phone":"+1 562 862 2102",
    "sg:postcode":"90241",
    "sg:province":"CA",
    "sg:tags":[
        "broker",
        "mortgage"
    ],
    "wof:name":"American Residential Funding",
    "wof:placetype":"venue"
},
  "geometry": {"coordinates":[-118.13814499999999,33.932979],"type":"Point"}
}