{
  "type": "Feature",
  "properties": {
    "iso:country":"US",
    "sg:address":"3005 Acton St",
    "sg:city":"Berkeley",
    "sg:classifiers":[
        {
            "category":"Retail",
            "subcategory":"Repair Shop",
            "type":"Services"
        }
    ],
    "sg:phone":"+1 510 848 4003",
    "sg:postcode":"94702",
    "sg:province":"CA",
    "sg:tags":[
        "repairing",
        "piano",
        "refinishing"
    ],
    "wof:name":"Best Piano Svc",
    "wof:placetype":"venue"
},
  "geometry": {"coordinates":[-122.281193,37.852569],"type":"Point"}
}