{
  "type": "Feature",
  "properties": {
    "iso:country":"US",
    "sg:address":"4725 1st St",
    "sg:city":"Pleasanton",
    "sg:classifiers":[
        {
            "category":"Community Center",
            "subcategory":"Youth",
            "type":"Public Place"
        }
    ],
    "sg:phone":"+1 925 475 6100",
    "sg:postcode":"94566",
    "sg:province":"CA",
    "wof:name":"Tri Valley YMCA",
    "wof:placetype":"venue"
},
  "geometry": {"coordinates":[-121.876221,37.657411],"type":"Point"}
}