{
  "type": "Feature",
  "properties": {
    "addr:full":"15615 Alton Pkwy Irvine CA 92618",
    "addr:housenumber":"15615",
    "addr:postcode":"92618",
    "addr:street":"Alton Pkwy",
    "iso:country":"US",
    "sg:address":"15615 Alton Pkwy",
    "sg:city":"Irvine",
    "sg:classifiers":[
        {
            "category":"Health Services",
            "subcategory":"Doctor",
            "type":"Services"
        }
    ],
    "sg:phone":"+1 800 769 0342",
    "sg:postcode":"92618",
    "sg:province":"CA",
    "sg:tags":[
        "psychologist"
    ],
    "sg:website":"http://www.thebuehlerinstitute.com/",
    "wof:name":"Buehler Institue The",
    "wof:placetype":"venue"
},
  "geometry": {"coordinates":[-117.75288,33.655422],"type":"Point"}
}