{
  "type": "Feature",
  "properties": {
    "iso:country":"US",
    "sg:address":"5396 Elk River Rd",
    "sg:city":"Eureka",
    "sg:classifiers":[
        {
            "category":"Farming",
            "subcategory":"Dairy Farm",
            "type":"Manufacturing & Wholesale Goods"
        }
    ],
    "sg:phone":"+1 707 442 4628",
    "sg:postcode":"95503",
    "sg:province":"CA",
    "sg:tags":[
        "cattle"
    ],
    "wof:name":"Donald A Pedrotti",
    "wof:placetype":"venue"
},
  "geometry": {"coordinates":[-124.185259,40.750581],"type":"Point"}
}