{
  "type": "Feature",
  "properties": {
    "iso:country":"US",
    "sg:address":"2460 Mammoth Dr",
    "sg:city":"San Diego",
    "sg:classifiers":[
        {
            "category":"Banks & Credit Unions",
            "subcategory":"Financial Services",
            "type":"Services"
        }
    ],
    "sg:phone":"+1 858 278 1326",
    "sg:postcode":"92123",
    "sg:province":"CA",
    "sg:tags":[
        "trust",
        "management"
    ],
    "wof:name":"Cravey Family Trust",
    "wof:placetype":"venue"
},
  "geometry": {"coordinates":[-117.12332600000001,32.791112],"type":"Point"}
}