{
  "type": "Feature",
  "properties": {
    "iso:country":"US",
    "sg:address":"424 S Main St",
    "sg:city":"Templeton",
    "sg:classifiers":[
        {
            "category":"Wholesale",
            "subcategory":"Groceries",
            "type":"Manufacturing & Wholesale Goods"
        }
    ],
    "sg:phone":"+1 805 434 3007",
    "sg:postcode":"93465",
    "sg:province":"CA",
    "sg:tags":[
        "cocoa",
        "chocolate"
    ],
    "wof:name":"Herrmann's Chocolate Lab",
    "wof:placetype":"venue"
},
  "geometry": {"coordinates":[-120.70513,35.549648],"type":"Point"}
}