{
  "type": "Feature",
  "properties": {
    "addr:full":"3617 7th Ave Sacramento CA 95817",
    "addr:housenumber":"3617",
    "addr:postcode":"95817",
    "addr:street":"7Th Ave",
    "iso:country":"US",
    "sg:address":"3617 7th Ave",
    "sg:city":"Sacramento",
    "sg:classifiers":[
        {
            "category":"Manufacturing",
            "subcategory":"Buildings",
            "type":"Manufacturing & Wholesale Goods"
        },
        {
            "category":"Building & Trades",
            "subcategory":"Construction",
            "type":"Services"
        }
    ],
    "sg:phone":"+1 800 528 9245",
    "sg:postcode":"95817",
    "sg:province":"CA",
    "sg:tags":[
        "industrial",
        "builder",
        "contractor",
        "contractors-commercial",
        "home"
    ],
    "wof:name":"Aaron Construction",
    "wof:placetype":"venue"
},
  "geometry": {"coordinates":[-121.468084,38.545274],"type":"Point"}
}