{
  "type": "Feature",
  "properties": {
    "iso:country":"US",
    "sg:address":"3355 Dulles Dr",
    "sg:city":"Mira Loma",
    "sg:classifiers":[
        {
            "category":"Freight",
            "type":"Transportation"
        }
    ],
    "sg:phone":"+1 951 360 8310",
    "sg:postcode":"91752",
    "sg:province":"CA",
    "sg:tags":[
        "storage",
        "provides",
        "special",
        "warehousing"
    ],
    "wof:name":"FMI International LLC",
    "wof:placetype":"venue"
},
  "geometry": {"coordinates":[-117.517929,34.026961],"type":"Point"}
}