{
  "type": "Feature",
  "properties": {
    "addr:full":"8001 Canoga Ave Canoga Park CA 91304",
    "addr:housenumber":"8001",
    "addr:postcode":"91304",
    "addr:street":"Canoga Ave",
    "iso:country":"US",
    "sg:address":"8001 Canoga Ave",
    "sg:city":"Canoga Park",
    "sg:classifiers":[
        {
            "category":"Shopping",
            "subcategory":"Hobbies, Toys, & Games",
            "type":"Retail Goods"
        },
        {
            "category":"Bars & Pubs",
            "subcategory":"Sports Bar",
            "type":"Food & Drink"
        }
    ],
    "sg:phone":"+1 818 882 6660",
    "sg:postcode":"91304",
    "sg:province":"CA",
    "sg:tags":[
        "shop",
        "hobby",
        "hall",
        "pool"
    ],
    "wof:name":"Valley Billiards",
    "wof:placetype":"venue"
},
  "geometry": {"coordinates":[-118.598,34.216],"type":"Point"}
}