{
  "type": "Feature",
  "properties": {
    "addr:full":"209 Bassett St King City CA 93930",
    "addr:housenumber":"209",
    "addr:postcode":"93930",
    "addr:street":"Bassett St",
    "iso:country":"US",
    "sg:address":"209 Bassett St",
    "sg:city":"King City",
    "sg:classifiers":[
        {
            "category":"Manufacturing",
            "subcategory":"Buildings",
            "type":"Manufacturing & Wholesale Goods"
        }
    ],
    "sg:phone":"+1 831 385 9280",
    "sg:postcode":"93930",
    "sg:province":"CA",
    "sg:tags":[
        "prefab"
    ],
    "wof:name":"Central Coast Homes",
    "wof:placetype":"venue"
},
  "geometry": {"coordinates":[-121.124318,36.212615],"type":"Point"}
}