{
  "type": "Feature",
  "properties": {
    "iso:country":"US",
    "sg:address":"642 W Arrow Hwy",
    "sg:city":"San Dimas",
    "sg:classifiers":[
        {
            "category":"Food & Beverages",
            "subcategory":"Specialty",
            "type":"Retail Goods"
        }
    ],
    "sg:phone":"+1 909 592 5131",
    "sg:postcode":"91773",
    "sg:province":"CA",
    "sg:tags":[
        "health",
        "diet"
    ],
    "wof:name":"Vitamin City Health Food",
    "wof:placetype":"venue"
},
  "geometry": {"coordinates":[-117.81885200000001,34.105294],"type":"Point"}
}