{
  "type": "Feature",
  "properties": {
    "iso:country":"US",
    "sg:address":"10496 Garvey Ave",
    "sg:city":"El Monte",
    "sg:classifiers":[
        {
            "category":"Health Services",
            "subcategory":"Doctor",
            "type":"Services"
        }
    ],
    "sg:phone":"+1 626 442 5678",
    "sg:postcode":"91733",
    "sg:province":"CA",
    "sg:tags":[
        "surgeon",
        "oral"
    ],
    "wof:name":"Beri Lata DDS",
    "wof:placetype":"venue"
},
  "geometry": {"coordinates":[-118.043999,34.062698],"type":"Point"}
}