{
  "type": "Feature",
  "properties": {
    "addr:full":"2731 Systron Dr Concord CA 94518",
    "addr:housenumber":"2731",
    "addr:postcode":"94518",
    "addr:street":"Systron Dr",
    "iso:country":"US",
    "sg:address":"2731 Systron Dr",
    "sg:city":"Concord",
    "sg:classifiers":[
        {
            "category":"Education",
            "subcategory":"Special Training",
            "type":"Public Place"
        }
    ],
    "sg:phone":"+1 925 521 9280",
    "sg:postcode":"94518",
    "sg:province":"CA",
    "sg:tags":[
        "educational"
    ],
    "wof:name":"Educational Testing Svc",
    "wof:placetype":"venue"
},
  "geometry": {"coordinates":[-122.028587,37.965039],"type":"Point"}
}