{
  "type": "Feature",
  "properties": {
    "iso:country":"US",
    "sg:address":"350 Velasco Ave",
    "sg:city":"San Francisco",
    "sg:classifiers":[
        {
            "category":"Professional",
            "type":"Services"
        }
    ],
    "sg:phone":"+1 415 334 1629",
    "sg:postcode":"94134",
    "sg:province":"CA",
    "wof:name":"Tvnewsjobs Net",
    "wof:placetype":"venue"
},
  "geometry": {"coordinates":[-122.41557,37.708935],"type":"Point"}
}