{
  "type": "Feature",
  "properties": {
    "iso:country":"US",
    "sg:address":"7810 Paisley Ave",
    "sg:city":"Hesperia",
    "sg:classifiers":[
        {
            "category":"Retail",
            "subcategory":"Auto Repair",
            "type":"Services"
        }
    ],
    "sg:phone":"+1 760 949 1787",
    "sg:postcode":"92345",
    "sg:province":"CA",
    "sg:tags":[
        "repairing",
        "automobile"
    ],
    "wof:name":"Carrell's Mobile Automotive",
    "wof:placetype":"venue"
},
  "geometry": {"coordinates":[-117.27077,34.39221],"type":"Point"}
}