{
  "type": "Feature",
  "properties": {
    "addr:full":"6512 Bose Ln San Jose CA 95120",
    "addr:housenumber":"6512",
    "addr:postcode":"95120",
    "addr:street":"Bose Ln",
    "iso:country":"US",
    "sg:address":"6512 Bose Ln",
    "sg:city":"San Jose",
    "sg:classifiers":[
        {
            "category":"Professional",
            "subcategory":"Management & Consulting",
            "type":"Services"
        }
    ],
    "sg:phone":"+1 408 323 1078",
    "sg:postcode":"95120",
    "sg:province":"CA",
    "sg:tags":[
        "consultant",
        "construction"
    ],
    "wof:name":"Sobey Construction Inc",
    "wof:placetype":"venue"
},
  "geometry": {"coordinates":[-121.867293,37.219726],"type":"Point"}
}