{
  "type": "Feature",
  "properties": {
    "iso:country":"US",
    "sg:address":"505 S Vulcan Ave",
    "sg:city":"Encinitas",
    "sg:classifiers":[
        {
            "category":"Recreation",
            "type":"Entertainment"
        }
    ],
    "sg:phone":"+1 760 633 2740",
    "sg:postcode":"92024",
    "sg:province":"CA",
    "sg:tags":[
        "parks"
    ],
    "sg:website":"www.ci.encinitas.ca.us",
    "wof:name":"Encinitas Park & Recreation",
    "wof:placetype":"venue"
},
  "geometry": {"coordinates":[-117.292382,33.044854],"type":"Point"}
}