{
  "type": "Feature",
  "properties": {
    "iso:country":"US",
    "sg:address":"12125 Day St",
    "sg:city":"Moreno Valley",
    "sg:classifiers":[
        {
            "category":"Shopping",
            "subcategory":"Florist",
            "type":"Retail Goods"
        }
    ],
    "sg:phone":"+1 951 784 8497",
    "sg:postcode":"92557",
    "sg:province":"CA",
    "sg:website":"www.morenovalleyflowers.com",
    "wof:name":"Flower Heaven",
    "wof:placetype":"venue"
},
  "geometry": {"coordinates":[-117.279039,33.945909],"type":"Point"}
}