{
  "type": "Feature",
  "properties": {
    "iso:country":"US",
    "sg:address":"632 Teal St",
    "sg:city":"Foster City",
    "sg:classifiers":[
        {
            "category":"Arts & Performance",
            "subcategory":"Theater",
            "type":"Entertainment"
        }
    ],
    "sg:phone":"+1 650 574 3568",
    "sg:postcode":"94404",
    "sg:province":"CA",
    "sg:tags":[
        "entertainer",
        "business"
    ],
    "sg:website":"www.allstarshowgrams.com",
    "wof:name":"All Star Showgrams",
    "wof:placetype":"venue"
},
  "geometry": {"coordinates":[-122.261298,37.570715],"type":"Point"}
}