{
  "type": "Feature",
  "properties": {
    "addr:full":"7870 E Rainview Ct Anaheim CA 92808",
    "addr:housenumber":"7870",
    "addr:postcode":"92808",
    "addr:street":"E Rainview Ct",
    "iso:country":"US",
    "sg:address":"7870 E Rainview Ct",
    "sg:city":"Anaheim",
    "sg:classifiers":[
        {
            "category":"Wholesale",
            "subcategory":"Motor Vehicles",
            "type":"Manufacturing & Wholesale Goods"
        }
    ],
    "sg:phone":"+1 714 357 8782",
    "sg:postcode":"92808",
    "sg:province":"CA",
    "wof:name":"Christopher Co",
    "wof:placetype":"venue"
},
  "geometry": {"coordinates":[-117.739947,33.849365],"type":"Point"}
}