{
  "type": "Feature",
  "properties": {
    "iso:country":"US",
    "sg:address":"206 W Summer St",
    "sg:city":"Ojai",
    "sg:classifiers":[
        {
            "category":"Retail",
            "subcategory":"Repair Shop",
            "type":"Services"
        }
    ],
    "sg:phone":"+1 805 646 4881",
    "sg:postcode":"93023",
    "sg:province":"CA",
    "sg:tags":[
        "welding"
    ],
    "wof:name":"Harry A Johnson Jr Welding",
    "wof:placetype":"venue"
},
  "geometry": {"coordinates":[-119.248795,34.452501],"type":"Point"}
}