{
  "type": "Feature",
  "properties": {
    "iso:country":"US",
    "sg:address":"571 W Ramsey St",
    "sg:city":"Banning",
    "sg:classifiers":[
        {
            "category":"Restaurant",
            "type":"Food & Drink"
        }
    ],
    "sg:phone":"+1 951 922 2836",
    "sg:postcode":"92220",
    "sg:province":"CA",
    "wof:name":"Cortez Restaurants",
    "wof:placetype":"venue"
},
  "geometry": {"coordinates":[-116.882919,33.925501],"type":"Point"}
}