{
  "type": "Feature",
  "properties": {
    "addr:full":"22110 Roscoe Blvd Canoga Park CA 91304",
    "addr:housenumber":"22110",
    "addr:postcode":"91304",
    "addr:street":"Roscoe Blvd",
    "iso:country":"US",
    "sg:address":"22110 Roscoe Blvd",
    "sg:city":"Canoga Park",
    "sg:classifiers":[
        {
            "category":"Health Services",
            "subcategory":"Health Practitioner",
            "type":"Services"
        }
    ],
    "sg:phone":"+1 818 999 6788",
    "sg:postcode":"91304",
    "sg:province":"CA",
    "sg:tags":[
        "acupuncture"
    ],
    "wof:name":"Topanga Acupuncture Clinic",
    "wof:placetype":"venue"
},
  "geometry": {"coordinates":[-118.608002,34.219601],"type":"Point"}
}