{
  "type": "Feature",
  "properties": {
    "iso:country":"US",
    "sg:address":"11745 Rustic Pl",
    "sg:city":"Fontana",
    "sg:classifiers":[
        {
            "category":"Real Estate",
            "subcategory":"Real Estate Agent",
            "type":"Services"
        }
    ],
    "sg:phone":"+1 909 829 2377",
    "sg:postcode":"92337",
    "sg:province":"CA",
    "wof:name":"Jaspman Realty",
    "wof:placetype":"venue"
},
  "geometry": {"coordinates":[-117.48876,34.039599],"type":"Point"}
}