{
  "type": "Feature",
  "properties": {
    "iso:country":"US",
    "sg:address":"15399 E 14th St",
    "sg:city":"San Leandro",
    "sg:classifiers":[
        {
            "category":"Banks & Credit Unions",
            "subcategory":"Bank",
            "type":"Services"
        }
    ],
    "sg:phone":"+1 510 727 1976",
    "sg:postcode":"94578",
    "sg:province":"CA",
    "wof:name":"U S Bank",
    "wof:placetype":"venue"
},
  "geometry": {"coordinates":[-122.12599899999999,37.703602],"type":"Point"}
}