{
  "type": "Feature",
  "properties": {
    "iso:country":"US",
    "sg:address":"1890 Ximeno Ave",
    "sg:city":"Long Beach",
    "sg:classifiers":[
        {
            "category":"Shopping",
            "subcategory":"Pharmacy",
            "type":"Retail Goods"
        }
    ],
    "sg:phone":"+1 562 597 6520",
    "sg:postcode":"90815",
    "sg:province":"CA",
    "sg:tags":[
        "drugstore"
    ],
    "sg:website":"www.riteaid.com",
    "wof:name":"Rite Aid",
    "wof:placetype":"venue"
},
  "geometry": {"coordinates":[-118.138943,33.791316],"type":"Point"}
}