{
  "type": "Feature",
  "properties": {
    "addr:full":"3504 E Imperial Hwy Lynwood CA 90262",
    "addr:housenumber":"3504",
    "addr:postcode":"90262",
    "addr:street":"E Imperial Hwy",
    "iso:country":"US",
    "sg:address":"3504 E Imperial Hwy",
    "sg:city":"Lynwood",
    "sg:classifiers":[
        {
            "category":"Food & Beverages",
            "subcategory":"Groceries & Convenience Stores",
            "type":"Retail Goods"
        }
    ],
    "sg:phone":"+1 310 637 1008",
    "sg:postcode":"90262",
    "sg:province":"CA",
    "wof:name":"Circle K Corporation",
    "wof:placetype":"venue"
},
  "geometry": {"coordinates":[-118.206529,33.93044],"type":"Point"}
}