{
  "type": "Feature",
  "properties": {
    "iso:country":"US",
    "sg:address":"3813 Shenandoah Dr",
    "sg:city":"Bakersfield",
    "sg:classifiers":[
        {
            "category":"Professional",
            "type":"Services"
        }
    ],
    "sg:phone":"+1 661 397 7077",
    "sg:postcode":"93304",
    "sg:province":"CA",
    "wof:name":"Howard Fiske",
    "wof:placetype":"venue"
},
  "geometry": {"coordinates":[-119.01285,35.319741],"type":"Point"}
}