{
  "type": "Feature",
  "properties": {
    "iso:country":"US",
    "sg:address":"15836 Valley Blvd",
    "sg:city":"Fontana",
    "sg:classifiers":[
        {
            "category":"Autos & Motor Vehicles",
            "subcategory":"Automobile Sales",
            "type":"Retail Goods"
        }
    ],
    "sg:phone":"+1 909 355 7223",
    "sg:postcode":"92335",
    "sg:province":"CA",
    "sg:tags":[
        "car",
        "dealer"
    ],
    "wof:name":"Auto Depot",
    "wof:placetype":"venue"
},
  "geometry": {"coordinates":[-117.460714,34.070356],"type":"Point"}
}