{
  "type": "Feature",
  "properties": {
    "iso:country":"US",
    "sg:address":"12601 Padrino St",
    "sg:city":"Victorville",
    "sg:classifiers":[
        {
            "category":"Organizations",
            "subcategory":"Religious Organization",
            "type":"Services"
        }
    ],
    "sg:phone":"+1 760 951 5695",
    "sg:postcode":"92394",
    "sg:province":"CA",
    "wof:name":"Anchor Of Hope Church",
    "wof:placetype":"venue"
},
  "geometry": {"coordinates":[-117.388396,34.523449],"type":"Point"}
}