{
  "type": "Feature",
  "properties": {
    "addr:full":"24243 Valencia Blvd Santa Clarita CA 91355",
    "addr:housenumber":"24243",
    "addr:postcode":"91355",
    "addr:street":"Valencia Blvd",
    "iso:country":"US",
    "sg:address":"24243 Valencia Blvd",
    "sg:city":"Santa Clarita",
    "sg:classifiers":[
        {
            "category":"Real Estate",
            "subcategory":"Real Estate Agent",
            "type":"Services"
        }
    ],
    "sg:phone":"+1 661 255 5800",
    "sg:postcode":"91355",
    "sg:province":"CA",
    "wof:name":"Homefinding Center",
    "wof:placetype":"venue"
},
  "geometry": {"coordinates":[-118.557962,34.413145],"type":"Point"}
}