{
  "type": "Feature",
  "properties": {
    "addr:full":"5138 Waring Rd San Diego CA 92120",
    "addr:housenumber":"5138",
    "addr:postcode":"92120",
    "addr:street":"Waring Rd",
    "iso:country":"US",
    "sg:address":"5138 Waring Rd",
    "sg:city":"San Diego",
    "sg:classifiers":[
        {
            "category":"Recreation",
            "type":"Entertainment"
        }
    ],
    "sg:phone":"+1 619 582 1800",
    "sg:postcode":"92120",
    "sg:province":"CA",
    "sg:tags":[
        "martial",
        "arts",
        "instruction"
    ],
    "wof:name":"Allied Gardens School",
    "wof:placetype":"venue"
},
  "geometry": {"coordinates":[-117.081451,32.791989],"type":"Point"}
}