{
  "type": "Feature",
  "properties": {
    "iso:country":"US",
    "sg:address":"135 Seminary Dr",
    "sg:city":"Mill Valley",
    "sg:classifiers":[
        {
            "category":"Banks & Credit Unions",
            "subcategory":"Investment Brokerage",
            "type":"Services"
        },
        {
            "category":"Banks & Credit Unions",
            "subcategory":"Financial Services",
            "type":"Services"
        }
    ],
    "sg:phone":"+1 415 388 2151",
    "sg:postcode":"94941",
    "sg:province":"CA",
    "sg:tags":[
        "land",
        "trader",
        "royalty",
        "oil",
        "lease"
    ],
    "wof:name":"Starbright Resources Inc",
    "wof:placetype":"venue"
},
  "geometry": {"coordinates":[-122.512827,37.889919],"type":"Point"}
}