{
  "type": "Feature",
  "properties": {
    "iso:country":"US",
    "sg:address":"8668 Pine Creek Rd",
    "sg:city":"Pine Valley",
    "sg:classifiers":[
        {
            "category":"Organizations",
            "subcategory":"Non-profit Organization",
            "type":"Services"
        }
    ],
    "sg:phone":"+1 619 473 8879",
    "sg:postcode":"91962",
    "sg:province":"CA",
    "sg:website":"www.pvbc.net",
    "wof:name":"Pine Valley Bible Conference",
    "wof:placetype":"venue"
},
  "geometry": {"coordinates":[-116.52799400000001,32.843294],"type":"Point"}
}