{
  "type": "Feature",
  "properties": {
    "addr:full":"910 81st Ave Oakland CA 94621",
    "addr:housenumber":"910",
    "addr:postcode":"94621",
    "addr:street":"81St Ave",
    "iso:country":"US",
    "sg:address":"910 81st Ave",
    "sg:city":"Oakland",
    "sg:classifiers":[
        {
            "category":"Shopping",
            "type":"Retail Goods"
        }
    ],
    "sg:phone":"+1 510 632 6795",
    "sg:postcode":"94621",
    "sg:province":"CA",
    "sg:tags":[
        "awning",
        "canopy"
    ],
    "wof:name":"D & V Awning",
    "wof:placetype":"venue"
},
  "geometry": {"coordinates":[-122.192369,37.749676],"type":"Point"}
}