{
  "type": "Feature",
  "properties": {
    "iso:country":"US",
    "sg:address":"4136 Monterey Hwy",
    "sg:city":"San Jose",
    "sg:classifiers":[
        {
            "category":"Food & Beverages",
            "subcategory":"Specialty",
            "type":"Retail Goods"
        }
    ],
    "sg:phone":"+1 408 229 8001",
    "sg:postcode":"95111",
    "sg:province":"CA",
    "sg:tags":[
        "water",
        "bulk",
        "company"
    ],
    "wof:name":"Pure Water & Refreshments",
    "wof:placetype":"venue"
},
  "geometry": {"coordinates":[-121.83574,37.278669],"type":"Point"}
}