{
  "type": "Feature",
  "properties": {
    "addr:full":"2501 Sutter Street San Francisco CA 94115",
    "addr:housenumber":"2501",
    "addr:postcode":"94115",
    "addr:street":"Sutter Street",
    "iso:country":"US",
    "sg:address":"2501 Sutter Street",
    "sg:city":"San Francisco",
    "sg:classifiers":[
        {
            "category":"Real Estate",
            "subcategory":"Real Estate Operator",
            "type":"Services"
        }
    ],
    "sg:phone":"+1 415 567 7918",
    "sg:postcode":"94115",
    "sg:province":"CA",
    "sg:tags":[
        "apartment"
    ],
    "sg:website":"www.sfha.org",
    "wof:name":"Westside Courts",
    "wof:placetype":"venue"
},
  "geometry": {"coordinates":[-122.441563,37.785057],"type":"Point"}
}