{
  "type": "Feature",
  "properties": {
    "addr:full":"3861 Hughes Ave Culver City CA 90232",
    "addr:housenumber":"3861",
    "addr:postcode":"90232",
    "addr:street":"Hughes Ave",
    "iso:country":"US",
    "sg:address":"3861 Hughes Ave",
    "sg:city":"Culver City",
    "sg:classifiers":[
        {
            "category":"Sports & Exercise",
            "subcategory":"Gym",
            "type":"Entertainment"
        }
    ],
    "sg:phone":"+1 310 202 8653",
    "sg:postcode":"90232",
    "sg:province":"CA",
    "sg:tags":[
        "trainer"
    ],
    "sg:website":"www.curvesculvercity.com",
    "wof:name":"Curves Culver City",
    "wof:placetype":"venue"
},
  "geometry": {"coordinates":[-118.39801799999999,34.022329],"type":"Point"}
}