{
  "type": "Feature",
  "properties": {
    "iso:country":"US",
    "sg:address":"2600 Franklin Canyon Dr",
    "sg:city":"Beverly Hills",
    "sg:classifiers":[
        {
            "category":"Park",
            "type":"Public Place"
        }
    ],
    "sg:postcode":"90210",
    "sg:province":"CA",
    "wof:name":"Franklin Canyon",
    "wof:placetype":"venue"
},
  "geometry": {"coordinates":[-118.409952,34.125348],"type":"Point"}
}