{
  "type": "Feature",
  "properties": {
    "iso:country":"US",
    "sg:address":"4351 Orange Ave",
    "sg:city":"Cypress",
    "sg:classifiers":[
        {
            "category":"Education",
            "subcategory":"School",
            "type":"Public Place"
        }
    ],
    "sg:phone":"+1 714 220 4057",
    "sg:postcode":"90630",
    "sg:province":"CA",
    "sg:tags":[
        "high",
        "middle"
    ],
    "wof:name":"Lexington Junior High School",
    "wof:placetype":"venue"
},
  "geometry": {"coordinates":[-118.056999,33.824299],"type":"Point"}
}