{
  "type": "Feature",
  "properties": {
    "iso:country":"US",
    "sg:address":"421 S Van Ness Ave",
    "sg:city":"Los Angeles",
    "sg:classifiers":[
        {
            "category":"Wholesale",
            "subcategory":"Non-durable Goods",
            "type":"Manufacturing & Wholesale Goods"
        }
    ],
    "sg:phone":"+1 213 383 0057",
    "sg:postcode":"90020",
    "sg:province":"CA",
    "wof:name":"Ajou Medics U S A Inc",
    "wof:placetype":"venue"
},
  "geometry": {"coordinates":[-118.315212,34.065695],"type":"Point"}
}