{
  "type": "Feature",
  "properties": {
    "addr:full":"985 Obrien Dr Menlo Park CA 94025",
    "addr:housenumber":"985",
    "addr:postcode":"94025",
    "addr:street":"Obrien Dr",
    "iso:country":"US",
    "sg:address":"985 Obrien Dr",
    "sg:city":"Menlo Park",
    "sg:classifiers":[
        {
            "category":"Home & Garden",
            "subcategory":"Building Materials",
            "type":"Retail Goods"
        }
    ],
    "sg:phone":"+1 650 473 1788",
    "sg:postcode":"94025",
    "sg:province":"CA",
    "sg:tags":[
        "roofing"
    ],
    "wof:name":"Al's Roofing Supply Inc",
    "wof:placetype":"venue"
},
  "geometry": {"coordinates":[-122.151236,37.474997],"type":"Point"}
}