{
  "type": "Feature",
  "properties": {
    "iso:country":"US",
    "sg:address":"5950 Roselle Ave",
    "sg:city":"Riverbank",
    "sg:classifiers":[
        {
            "category":"Wholesale",
            "subcategory":"Machinery & Supplies",
            "type":"Manufacturing & Wholesale Goods"
        }
    ],
    "sg:phone":"+1 209 869 5690",
    "sg:postcode":"95367",
    "sg:province":"CA",
    "sg:tags":[
        "car"
    ],
    "wof:name":"P & S Detailing Products",
    "wof:placetype":"venue"
},
  "geometry": {"coordinates":[-120.940216,37.723578],"type":"Point"}
}