{
  "type": "Feature",
  "properties": {
    "addr:full":"8359 Santero Way Cotati CA 94931",
    "addr:housenumber":"8359",
    "addr:postcode":"94931",
    "addr:street":"Santero Way",
    "iso:country":"US",
    "sg:address":"8359 Santero Way",
    "sg:city":"Cotati",
    "sg:classifiers":[
        {
            "category":"Retail",
            "subcategory":"Auto Repair",
            "type":"Services"
        }
    ],
    "sg:phone":"+1 707 584 7568",
    "sg:postcode":"94931",
    "sg:province":"CA",
    "sg:tags":[
        "wrecker"
    ],
    "wof:name":"North Bay Towing",
    "wof:placetype":"venue"
},
  "geometry": {"coordinates":[-122.691782,38.330598],"type":"Point"}
}