{
  "type": "Feature",
  "properties": {
    "addr:full":"20 W 10th St Antioch CA 94509",
    "addr:housenumber":"20",
    "addr:postcode":"ca 94509",
    "addr:street":"W 10Th St",
    "iso:country":"US",
    "sg:address":"20 W 10th St",
    "sg:city":"Antioch",
    "sg:classifiers":[
        {
            "category":"Shopping",
            "subcategory":"Used Merchandise",
            "type":"Retail Goods"
        }
    ],
    "sg:phone":"+1 925 754 2946",
    "sg:postcode":"94509",
    "sg:province":"CA",
    "sg:tags":[
        "shop",
        "thrift"
    ],
    "wof:name":"Salvation Army",
    "wof:placetype":"venue"
},
  "geometry": {"coordinates":[-121.807303,38.011263],"type":"Point"}
}