{
  "type": "Feature",
  "properties": {
    "iso:country":"US",
    "sg:address":"2382 Faraday Avenue Suite 160",
    "sg:city":"Carlsbad",
    "sg:classifiers":[
        {
            "category":"Real Estate",
            "subcategory":"Real Estate Agent",
            "type":"Services"
        }
    ],
    "sg:phone":"+1 760 213 0879",
    "sg:postcode":"92008",
    "sg:province":"CA",
    "wof:name":"Eliot Rachman, GRI - Century 21 Award Carlsbad",
    "wof:placetype":"venue"
},
  "geometry": {"coordinates":[-117.27504,33.136419],"type":"Point"}
}