{
  "type": "Feature",
  "properties": {
    "iso:country":"US",
    "sg:address":"331 N Sepulveda Blvd",
    "sg:city":"El Segundo",
    "sg:classifiers":[
        {
            "category":"Shopping",
            "subcategory":"Pharmacy",
            "type":"Retail Goods"
        },
        {
            "category":"Food & Beverages",
            "subcategory":"Groceries & Convenience Stores",
            "type":"Retail Goods"
        }
    ],
    "sg:phone":"+1 310 640 9651",
    "sg:postcode":"90245",
    "sg:province":"CA",
    "sg:tags":[
        "drugstore"
    ],
    "sg:website":"www.walgreens.com",
    "wof:name":"Walgreens Drug Store",
    "wof:placetype":"venue"
},
  "geometry": {"coordinates":[-118.396524,33.920443],"type":"Point"}
}