{
  "type": "Feature",
  "properties": {
    "iso:country":"US",
    "sg:address":"2142 Sutter St",
    "sg:city":"San Francisco",
    "sg:classifiers":[
        {
            "category":"Health Services",
            "subcategory":"Clinic",
            "type":"Services"
        }
    ],
    "sg:phone":"+1 415 979 8684",
    "sg:postcode":"94102",
    "sg:province":"CA",
    "sg:tags":[
        "counseling",
        "mental"
    ],
    "wof:name":"Catherine Rose PHD",
    "wof:placetype":"venue"
},
  "geometry": {"coordinates":[-122.435675,37.785808],"type":"Point"}
}