{
  "type": "Feature",
  "properties": {
    "addr:full":"325 E Cordova St Pasadena CA 91101",
    "addr:housenumber":"325",
    "addr:postcode":"91101",
    "addr:street":"E Cordova St",
    "iso:country":"US",
    "sg:address":"325 E Cordova St",
    "sg:city":"Pasadena",
    "sg:classifiers":[
        {
            "category":"Real Estate",
            "subcategory":"Real Estate Operator",
            "type":"Services"
        }
    ],
    "sg:phone":"+1 626 440 0545",
    "sg:postcode":"91101",
    "sg:province":"CA",
    "sg:tags":[
        "apartment"
    ],
    "sg:website":"arpeggioapts.com/",
    "wof:name":"Arpeggio Apartments",
    "wof:placetype":"venue"
},
  "geometry": {"coordinates":[-118.143506,34.142506],"type":"Point"}
}