{
  "type": "Feature",
  "properties": {
    "addr:full":"22801 Bray Rd Willits CA 95490",
    "addr:housenumber":"22801",
    "addr:postcode":"95490",
    "addr:street":"Bray Rd",
    "iso:country":"US",
    "sg:address":"22801 Bray Rd",
    "sg:city":"Willits",
    "sg:classifiers":[
        {
            "category":"Farming",
            "subcategory":"Farm",
            "type":"Manufacturing & Wholesale Goods"
        }
    ],
    "sg:phone":"+1 707 459 5965",
    "sg:postcode":"95490",
    "sg:province":"CA",
    "sg:tags":[
        "primarily",
        "crop",
        "general"
    ],
    "wof:name":"Morgan Hawthorn Farms",
    "wof:placetype":"venue"
},
  "geometry": {"coordinates":[-123.336043,39.412141],"type":"Point"}
}