{
  "type": "Feature",
  "properties": {
    "iso:country":"US",
    "sg:address":"1527 W 13th St",
    "sg:city":"Upland",
    "sg:classifiers":[
        {
            "category":"Building & Trades",
            "subcategory":"Construction",
            "type":"Services"
        }
    ],
    "sg:phone":"+1 909 920 4004",
    "sg:postcode":"91786",
    "sg:province":"CA",
    "sg:tags":[
        "contractor"
    ],
    "wof:name":"Cal West Construction",
    "wof:placetype":"venue"
},
  "geometry": {"coordinates":[-117.68045499999999,34.110601],"type":"Point"}
}