{
  "type": "Feature",
  "properties": {
    "addr:full":"2209 Brega Ln Morgan Hill CA 95037",
    "addr:housenumber":"2209",
    "addr:postcode":"95037",
    "addr:street":"Brega Ln",
    "iso:country":"US",
    "sg:address":"2209 Brega Ln",
    "sg:city":"Morgan Hill",
    "sg:classifiers":[
        {
            "category":"Professional",
            "type":"Services"
        }
    ],
    "sg:phone":"+1 408 779 5808",
    "sg:postcode":"95037",
    "sg:province":"CA",
    "sg:tags":[
        "writer"
    ],
    "wof:name":"Write Stuff",
    "wof:placetype":"venue"
},
  "geometry": {"coordinates":[-121.611891,37.138215],"type":"Point"}
}