{
  "type": "Feature",
  "properties": {
    "iso:country":"US",
    "sg:address":"5465 Santa Monica Boulevard Suite 205",
    "sg:city":"Los Angeles",
    "sg:classifiers":[
        {
            "category":"Education",
            "subcategory":"Kindergarten",
            "type":"Public Place"
        }
    ],
    "sg:phone":"+1 323 461 0434",
    "sg:postcode":"90029",
    "sg:province":"CA",
    "sg:tags":[
        "school",
        "driving"
    ],
    "sg:website":"www.prudentialdriving.com",
    "wof:name":"Prudential Driving and Traffic School",
    "wof:placetype":"venue"
},
  "geometry": {"coordinates":[-118.308558,34.0908],"type":"Point"}
}