{
  "type": "Feature",
  "properties": {
    "iso:country":"US",
    "sg:address":"12320 Meadowbrook Ln",
    "sg:city":"Poway",
    "sg:classifiers":[
        {
            "category":"Social Services",
            "type":"Services"
        }
    ],
    "sg:phone":"+1 619 838 4295",
    "sg:postcode":"92064",
    "sg:province":"CA",
    "sg:tags":[
        "youth",
        "organization",
        "center"
    ],
    "wof:name":"Boys & Girls Clubs United",
    "wof:placetype":"venue"
},
  "geometry": {"coordinates":[-117.066523,32.963425],"type":"Point"}
}