{
  "type": "Feature",
  "properties": {
    "iso:country":"US",
    "sg:address":"2512 Weston Pl",
    "sg:city":"Glendale",
    "sg:classifiers":[
        {
            "category":"Social Services",
            "subcategory":"Child Care",
            "type":"Services"
        },
        {
            "category":"Education",
            "subcategory":"Preschool",
            "type":"Public Place"
        },
        {
            "category":"Education",
            "subcategory":"School",
            "type":"Public Place"
        }
    ],
    "sg:phone":"+1 818 241 7650",
    "sg:postcode":"91208",
    "sg:province":"CA",
    "sg:tags":[
        "elementary",
        "day"
    ],
    "wof:name":"Learning Stars",
    "wof:placetype":"venue"
},
  "geometry": {"coordinates":[-118.229797,34.183144],"type":"Point"}
}