{
  "type": "Feature",
  "properties": {
    "iso:country":"US",
    "sg:address":"590 Merchant St",
    "sg:city":"Vacaville",
    "sg:classifiers":[
        {
            "category":"Personal",
            "type":"Services"
        }
    ],
    "sg:phone":"+1 707 446 9515",
    "sg:postcode":"95688",
    "sg:province":"CA",
    "sg:tags":[
        "therapist",
        "massage"
    ],
    "wof:name":"V & M Massage & Therapy",
    "wof:placetype":"venue"
},
  "geometry": {"coordinates":[-121.991254,38.353813],"type":"Point"}
}