{
  "type": "Feature",
  "properties": {
    "addr:full":"3027 E el Monte Way Fresno CA 93721",
    "addr:housenumber":"3027",
    "addr:postcode":"93721",
    "addr:street":"E El Monte Way",
    "iso:country":"US",
    "sg:address":"3027 E el Monte Way",
    "sg:city":"Fresno",
    "sg:classifiers":[
        {
            "category":"Wholesale",
            "subcategory":"Dairy",
            "type":"Manufacturing & Wholesale Goods"
        }
    ],
    "sg:phone":"+1 559 442 5412",
    "sg:postcode":"93721",
    "sg:province":"CA",
    "sg:tags":[
        "product"
    ],
    "wof:name":"Elias & Sylvia B Ice Crea",
    "wof:placetype":"venue"
},
  "geometry": {"coordinates":[-119.77302,36.734898],"type":"Point"}
}