{
  "type": "Feature",
  "properties": {
    "addr:full":"11022 Santa Monica Blvd Los Angeles CA 90025",
    "addr:housenumber":"11022",
    "addr:postcode":"90025",
    "addr:street":"Santa Monica Blvd",
    "iso:country":"US",
    "sg:address":"11022 Santa Monica Blvd",
    "sg:city":"Los Angeles",
    "sg:classifiers":[
        {
            "category":"Health Services",
            "subcategory":"Health Practitioner",
            "type":"Services"
        }
    ],
    "sg:phone":"+1 310 477 4797",
    "sg:postcode":"90025",
    "sg:province":"CA",
    "sg:tags":[
        "psychologist",
        "doctor"
    ],
    "wof:name":"Andrews Lois E PHD",
    "wof:placetype":"venue"
},
  "geometry": {"coordinates":[-118.442001,34.048199],"type":"Point"}
}