{
  "type": "Feature",
  "properties": {
    "addr:full":"756 E Foothill Blvd San Dimas CA 91773",
    "addr:housenumber":"756",
    "addr:postcode":"91773",
    "addr:street":"E Foothill Blvd",
    "iso:country":"US",
    "sg:address":"756 E Foothill Blvd",
    "sg:city":"San Dimas",
    "sg:classifiers":[
        {
            "category":"Food & Beverages",
            "subcategory":"Specialty",
            "type":"Retail Goods"
        }
    ],
    "sg:phone":"+1 909 592 1253",
    "sg:postcode":"91773",
    "sg:province":"CA",
    "wof:name":"Canyon View Dairy",
    "wof:placetype":"venue"
},
  "geometry": {"coordinates":[-117.79317899999999,34.122227],"type":"Point"}
}