{
  "type": "Feature",
  "properties": {
    "iso:country":"US",
    "sg:address":"1708 N Palm Canyon Dr",
    "sg:city":"Palm Springs",
    "sg:classifiers":[
        {
            "category":"Retail",
            "subcategory":"Auto Repair",
            "type":"Services"
        }
    ],
    "sg:phone":"+1 760 325 8831",
    "sg:postcode":"92262",
    "sg:province":"CA",
    "wof:name":"PALM DESERT SHELL",
    "wof:placetype":"venue"
},
  "geometry": {"coordinates":[-116.546594,33.845613],"type":"Point"}
}