{
  "type": "Feature",
  "properties": {
    "iso:country":"US",
    "sg:address":"2090 Bird St",
    "sg:city":"Oroville",
    "sg:classifiers":[
        {
            "category":"Professional",
            "type":"Services"
        }
    ],
    "sg:phone":"+1 530 534 5862",
    "sg:postcode":"95965",
    "sg:province":"CA",
    "wof:name":"Naacp of Butte County",
    "wof:placetype":"venue"
},
  "geometry": {"coordinates":[-121.554947,39.513275],"type":"Point"}
}