{
  "type": "Feature",
  "properties": {
    "iso:country":"US",
    "sg:address":"2025 N Long Beach Blvd",
    "sg:city":"Compton",
    "sg:classifiers":[
        {
            "category":"Home & Garden",
            "subcategory":"Furniture",
            "type":"Retail Goods"
        }
    ],
    "sg:phone":"+1 310 632 3835",
    "sg:postcode":"90221",
    "sg:province":"CA",
    "wof:name":"Pacific Super Discount Furn",
    "wof:placetype":"venue"
},
  "geometry": {"coordinates":[-118.208958,33.909977],"type":"Point"}
}