{
  "type": "Feature",
  "properties": {
    "iso:country":"US",
    "sg:address":"22336 Meekland Ave",
    "sg:city":"Hayward",
    "sg:classifiers":[
        {
            "category":"Manufacturing",
            "subcategory":"Metals",
            "type":"Manufacturing & Wholesale Goods"
        }
    ],
    "sg:phone":"+1 510 537 8528",
    "sg:postcode":"94541",
    "sg:province":"CA",
    "sg:tags":[
        "production",
        "grinding"
    ],
    "wof:name":"L & S Tool Mfg Co",
    "wof:placetype":"venue"
},
  "geometry": {"coordinates":[-122.100632,37.66859],"type":"Point"}
}