{
  "type": "Feature",
  "properties": {
    "addr:full":"32951 Cll Perfecto San Juan Cpstrno CA 92675",
    "addr:postcode":"32951;92675",
    "addr:street":"Perfecto",
    "iso:country":"US",
    "sg:address":"32951 Cll Perfecto",
    "sg:city":"San Juan Cpstrno",
    "sg:classifiers":[
        {
            "category":"Education",
            "subcategory":"School",
            "type":"Public Place"
        }
    ],
    "sg:phone":"+1 949 489 7100",
    "sg:postcode":"92675",
    "sg:province":"CA",
    "wof:name":"Capistrano Schl Dist Home Tch",
    "wof:placetype":"venue"
},
  "geometry": {"coordinates":[-117.67309,33.483187],"type":"Point"}
}