{
  "type": "Feature",
  "properties": {
    "addr:full":"6325 Topanga Canyon Blvd Ste 303 Woodland Hills CA 91367",
    "addr:housenumber":"6325",
    "addr:postcode":"91367",
    "addr:street":"Topanga Canyon Blvd Ste 303",
    "iso:country":"US",
    "sg:address":"6325 Topanga Canyon Blvd Ste 303",
    "sg:city":"Woodland Hills",
    "sg:classifiers":[
        {
            "category":"Health Services",
            "subcategory":"Dentist",
            "type":"Services"
        }
    ],
    "sg:phone":"+1 818 348 1410",
    "sg:postcode":"91367",
    "sg:province":"CA",
    "wof:name":"Dr. Michael Goldstein DDS",
    "wof:placetype":"venue"
},
  "geometry": {"coordinates":[-118.60681700000001,34.184917],"type":"Point"}
}