{
  "type": "Feature",
  "properties": {
    "addr:full":"525 Midway Ct Martinez CA 94553",
    "addr:housenumber":"525",
    "addr:postcode":"94553",
    "addr:street":"Midway Ct",
    "iso:country":"US",
    "sg:address":"525 Midway Ct",
    "sg:city":"Martinez",
    "sg:classifiers":[
        {
            "category":"Professional",
            "type":"Services"
        }
    ],
    "sg:phone":"+1 925 228 6714",
    "sg:postcode":"94553",
    "sg:province":"CA",
    "wof:name":"Jeans Plus",
    "wof:placetype":"venue"
},
  "geometry": {"coordinates":[-122.091246,37.9966],"type":"Point"}
}