{
  "type": "Feature",
  "properties": {
    "addr:full":"1908 Wellington Ln Vista CA 92081",
    "addr:housenumber":"1908",
    "addr:postcode":"92081",
    "addr:street":"Wellington Ln",
    "iso:country":"US",
    "sg:address":"1908 Wellington Ln",
    "sg:city":"Vista",
    "sg:classifiers":[
        {
            "category":"Professional",
            "type":"Services"
        }
    ],
    "sg:phone":"+1 760 727 6658",
    "sg:postcode":"92081",
    "sg:province":"CA",
    "wof:name":"Safetech Rbs",
    "wof:placetype":"venue"
},
  "geometry": {"coordinates":[-117.223733,33.168574],"type":"Point"}
}