{
  "type": "Feature",
  "properties": {
    "iso:country":"US",
    "sg:address":"5746 Cll Real",
    "sg:city":"Goleta",
    "sg:classifiers":[
        {
            "category":"Restaurant",
            "type":"Food & Drink"
        }
    ],
    "sg:phone":"+1 805 964 9909",
    "sg:postcode":"93117",
    "sg:province":"CA",
    "wof:name":"Sushi Teri",
    "wof:placetype":"venue"
},
  "geometry": {"coordinates":[-119.826037,34.441416],"type":"Point"}
}