{
  "type": "Feature",
  "properties": {
    "iso:country":"US",
    "sg:address":"4827 Geary Blvd",
    "sg:city":"San Francisco",
    "sg:classifiers":[
        {
            "category":"Shopping",
            "subcategory":"Pharmacy",
            "type":"Retail Goods"
        }
    ],
    "sg:phone":"+1 415 664 1100",
    "sg:postcode":"94118",
    "sg:province":"CA",
    "sg:tags":[
        "medical",
        "health"
    ],
    "wof:name":"Bay Area Diabetes Supply Center",
    "wof:placetype":"venue"
},
  "geometry": {"coordinates":[-122.47121,37.780545],"type":"Point"}
}