{
  "type": "Feature",
  "properties": {
    "iso:country":"US",
    "sg:address":"42220 Green Way",
    "sg:city":"Palm Desert",
    "sg:classifiers":[
        {
            "category":"Real Estate",
            "subcategory":"Architect",
            "type":"Services"
        }
    ],
    "sg:phone":"+1 858 759 6919",
    "sg:postcode":"92211",
    "sg:province":"CA",
    "wof:name":"Asaro & Assoc",
    "wof:placetype":"venue"
},
  "geometry": {"coordinates":[-116.355374,33.742321],"type":"Point"}
}