{
  "type": "Feature",
  "properties": {
    "addr:full":"950 Geary St San Francisco CA 94109",
    "addr:housenumber":"950",
    "addr:postcode":"94109",
    "addr:street":"Geary St",
    "iso:country":"US",
    "sg:address":"950 Geary St",
    "sg:city":"San Francisco",
    "sg:classifiers":[
        {
            "category":"Park",
            "type":"Public Place"
        }
    ],
    "sg:phone":"+1 415 440 1453",
    "sg:postcode":"94109",
    "sg:province":"CA",
    "wof:name":"Nae Park",
    "wof:placetype":"venue"
},
  "geometry": {"coordinates":[-122.41895700000001,37.786134],"type":"Point"}
}