{
  "type": "Feature",
  "properties": {
    "addr:full":"2745 W Lincoln Ave Anaheim CA 92801",
    "addr:housenumber":"2745",
    "addr:postcode":"92801",
    "addr:street":"W Lincoln Ave",
    "iso:country":"US",
    "sg:address":"2745 W Lincoln Ave",
    "sg:city":"Anaheim",
    "sg:classifiers":[
        {
            "category":"Food & Beverages",
            "subcategory":"Liquor & Beverages",
            "type":"Retail Goods"
        }
    ],
    "sg:phone":"+1 714 826 0981",
    "sg:postcode":"92801",
    "sg:province":"CA",
    "sg:tags":[
        "beer",
        "spirit",
        "wine"
    ],
    "wof:name":"Papa Joe's Delicatessen",
    "wof:placetype":"venue"
},
  "geometry": {"coordinates":[-117.983002,33.8321],"type":"Point"}
}