{
  "type": "Feature",
  "properties": {
    "iso:country":"US",
    "sg:address":"342 W 31st Street",
    "sg:city":"Los Angeles",
    "sg:classifiers":[
        {
            "category":"Education",
            "subcategory":"Kindergarten",
            "type":"Public Place"
        }
    ],
    "sg:phone":"+1 213 745 6022",
    "sg:postcode":"90007",
    "sg:province":"CA",
    "sg:tags":[
        "school",
        "driving"
    ],
    "wof:name":"Good Safe Fun Traffic School",
    "wof:placetype":"venue"
},
  "geometry": {"coordinates":[-118.276253,34.023228],"type":"Point"}
}