{
  "type": "Feature",
  "properties": {
    "addr:full":"3124 Shattuck Ave Berkeley CA 94705",
    "addr:housenumber":"3124",
    "addr:postcode":"94705",
    "addr:street":"Shattuck Ave",
    "iso:country":"US",
    "sg:address":"3124 Shattuck Ave",
    "sg:city":"Berkeley",
    "sg:classifiers":[
        {
            "category":"Health Services",
            "subcategory":"Clinic",
            "type":"Services"
        },
        {
            "category":"Health Services",
            "subcategory":"Nursing And Care Facility",
            "type":"Services"
        },
        {
            "category":"Health Services",
            "subcategory":"Health Practitioner",
            "type":"Services"
        }
    ],
    "sg:phone":"+1 510 486 1025",
    "sg:postcode":"94705",
    "sg:province":"CA",
    "sg:tags":[
        "home",
        "eldercare-home",
        "welfare"
    ],
    "wof:name":"C B C B",
    "wof:placetype":"venue"
},
  "geometry": {"coordinates":[-122.266209,37.85291],"type":"Point"}
}