{
  "type": "Feature",
  "properties": {
    "iso:country":"US",
    "sg:address":"2709 Alcatraz Ave",
    "sg:city":"Berkeley",
    "sg:classifiers":[
        {
            "category":"Health Services",
            "subcategory":"Clinic",
            "type":"Services"
        }
    ],
    "sg:phone":"+1 415 216 7026",
    "sg:postcode":"94705",
    "sg:province":"CA",
    "sg:tags":[
        "counseling",
        "mental"
    ],
    "sg:website":"www.phonepsychotherapywithseth.com",
    "wof:name":"Phone Psychotherapy with Seth",
    "wof:placetype":"venue"
},
  "geometry": {"coordinates":[-122.252089,37.851593],"type":"Point"}
}