{
  "type": "Feature",
  "properties": {
    "addr:full":"1211 Clinton Rd Sacramento CA 95825",
    "addr:housenumber":"1211",
    "addr:postcode":"95825",
    "addr:street":"Clinton Rd",
    "iso:country":"US",
    "sg:address":"1211 Clinton Rd",
    "sg:city":"Sacramento",
    "sg:classifiers":[
        {
            "category":"Building & Trades",
            "subcategory":"Equipment Rental",
            "type":"Services"
        }
    ],
    "sg:phone":"+1 916 568 6262",
    "sg:postcode":"95825",
    "sg:province":"CA",
    "sg:tags":[
        "party",
        "supply"
    ],
    "wof:name":"Jump Around Jumpers",
    "wof:placetype":"venue"
},
  "geometry": {"coordinates":[-121.40688299999999,38.58861],"type":"Point"}
}