{
  "type": "Feature",
  "properties": {
    "iso:country":"US",
    "sg:address":"303 W Garvey Ave",
    "sg:city":"Monterey Park",
    "sg:classifiers":[
        {
            "category":"Shopping",
            "type":"Retail Goods"
        }
    ],
    "sg:phone":"+1 626 288 6232",
    "sg:postcode":"91754",
    "sg:province":"CA",
    "sg:tags":[
        "merchandise"
    ],
    "wof:name":"Star Trophies & Awards",
    "wof:placetype":"venue"
},
  "geometry": {"coordinates":[-118.127517,34.062611],"type":"Point"}
}