{
  "type": "Feature",
  "properties": {
    "iso:country":"US",
    "sg:address":"54 E Herndon Ave",
    "sg:city":"Fresno",
    "sg:classifiers":[
        {
            "category":"Wholesale",
            "subcategory":"Furniture",
            "type":"Manufacturing & Wholesale Goods"
        }
    ],
    "sg:phone":"+1 559 436 4488",
    "sg:postcode":"93720",
    "sg:province":"CA",
    "wof:name":"Mar-Lynn's Office Furniture",
    "wof:placetype":"venue"
},
  "geometry": {"coordinates":[-119.789018,36.837407],"type":"Point"}
}