{
  "type": "Feature",
  "properties": {
    "addr:full":"5057 Erica Way Livermore CA 94550",
    "addr:housenumber":"5057",
    "addr:postcode":"94550",
    "addr:street":"Erica Way",
    "iso:country":"US",
    "sg:address":"5057 Erica Way",
    "sg:city":"Livermore",
    "sg:classifiers":[
        {
            "category":"Restaurant",
            "type":"Food & Drink"
        }
    ],
    "sg:phone":"+1 925 518 8072",
    "sg:postcode":"94550",
    "sg:province":"CA",
    "sg:tags":[
        "house",
        "steak",
        "barbecue"
    ],
    "wof:name":"You Will Lovett Bbq & Grill",
    "wof:placetype":"venue"
},
  "geometry": {"coordinates":[-121.733496,37.69236],"type":"Point"}
}