{
  "type": "Feature",
  "properties": {
    "iso:country":"US",
    "sg:address":"182 W 5th St",
    "sg:city":"San Bernardino",
    "sg:classifiers":[
        {
            "category":"Retail",
            "subcategory":"Laundry & Dry Cleaning",
            "type":"Services"
        }
    ],
    "sg:phone":"+1 909 384 0792",
    "sg:postcode":"92401",
    "sg:province":"CA",
    "sg:tags":[
        "cleaners"
    ],
    "wof:name":"Continental Cleaners",
    "wof:placetype":"venue"
},
  "geometry": {"coordinates":[-117.285539,34.108403],"type":"Point"}
}