{
  "type": "Feature",
  "properties": {
    "addr:full":"140 Townsend Ln Orcutt CA 93455",
    "addr:housenumber":"140",
    "addr:postcode":"93455",
    "addr:street":"Townsend Ln",
    "iso:country":"US",
    "sg:address":"140 Townsend Ln",
    "sg:city":"Orcutt",
    "sg:classifiers":[
        {
            "category":"Building & Trades",
            "subcategory":"Cleaning & Sanitation",
            "type":"Services"
        }
    ],
    "sg:phone":"+1 805 937 0186",
    "sg:postcode":"93455",
    "sg:province":"CA",
    "sg:tags":[
        "home"
    ],
    "wof:name":"Promaid",
    "wof:placetype":"venue"
},
  "geometry": {"coordinates":[-120.43567899999999,34.889002],"type":"Point"}
}