{
  "type": "Feature",
  "properties": {
    "addr:full":"2832 State St Carlsbad CA 92008",
    "addr:housenumber":"2832",
    "addr:postcode":"92008",
    "addr:street":"State St",
    "iso:country":"US",
    "sg:address":"2832 State St",
    "sg:city":"Carlsbad",
    "sg:classifiers":[
        {
            "category":"Shopping",
            "subcategory":"Jewelry",
            "type":"Retail Goods"
        }
    ],
    "sg:phone":"+1 760 434 9049",
    "sg:postcode":"92008",
    "sg:province":"CA",
    "sg:website":"www.somewhereintimefinejewelry.com",
    "wof:name":"Somewhere In Time Fine Jewelry",
    "wof:placetype":"venue"
},
  "geometry": {"coordinates":[-117.349948,33.161132],"type":"Point"}
}