{
  "type": "Feature",
  "properties": {
    "iso:country":"US",
    "sg:address":"520 N Prospect Ave Ste 103 Suite 208",
    "sg:city":"Redondo Beach",
    "sg:classifiers":[
        {
            "category":"Health Services",
            "subcategory":"Doctor",
            "type":"Services"
        }
    ],
    "sg:phone":"+1 310 376 8816",
    "sg:postcode":"90277",
    "sg:province":"CA",
    "wof:name":"Liu William MD",
    "wof:placetype":"venue"
},
  "geometry": {"coordinates":[-118.379056,33.852109],"type":"Point"}
}