{
  "type": "Feature",
  "properties": {
    "iso:country":"US",
    "sg:address":"725 E Washington St",
    "sg:city":"Petaluma",
    "sg:classifiers":[
        {
            "category":"Insurance",
            "subcategory":"Insurance Agent",
            "type":"Services"
        }
    ],
    "sg:phone":"+1 707 766 8959",
    "sg:postcode":"94952",
    "sg:province":"CA",
    "wof:name":"Martinelli Insurance",
    "wof:placetype":"venue"
},
  "geometry": {"coordinates":[-122.63326600000001,38.2413],"type":"Point"}
}