{
  "type": "Feature",
  "properties": {
    "iso:country":"US",
    "sg:address":"2121 N California Blvd",
    "sg:city":"Walnut Creek",
    "sg:classifiers":[
        {
            "category":"Professional",
            "subcategory":"Management & Consulting",
            "type":"Services"
        }
    ],
    "sg:phone":"+1 925 945 1243",
    "sg:postcode":"94596",
    "sg:province":"CA",
    "sg:tags":[
        "consultant",
        "business"
    ],
    "wof:name":"Alex Sheshunoff",
    "wof:placetype":"venue"
},
  "geometry": {"coordinates":[-122.06632399999999,37.907711],"type":"Point"}
}