{
  "type": "Feature",
  "properties": {
    "addr:full":"11816 Inglewood Ave Hawthorne CA 90250",
    "addr:housenumber":"11816",
    "addr:postcode":"90250",
    "addr:street":"Inglewood Ave",
    "iso:country":"US",
    "sg:address":"11816 Inglewood Ave",
    "sg:city":"Hawthorne",
    "sg:classifiers":[
        {
            "category":"Manufacturing",
            "subcategory":"Metals",
            "type":"Manufacturing & Wholesale Goods"
        }
    ],
    "sg:phone":"+1 310 676 8609",
    "sg:postcode":"90250",
    "sg:province":"CA",
    "sg:tags":[
        "metalwork",
        "sheet",
        "mfg"
    ],
    "wof:name":"Janssen Sheet Metal",
    "wof:placetype":"venue"
},
  "geometry": {"coordinates":[-118.36121900000001,33.926667],"type":"Point"}
}