{
  "type": "Feature",
  "properties": {
    "addr:full":"64 Willow Pl Menlo Park CA 94025",
    "addr:housenumber":"64",
    "addr:postcode":"94025",
    "addr:street":"Willow Pl",
    "iso:country":"US",
    "sg:address":"64 Willow Pl",
    "sg:city":"Menlo Park",
    "sg:classifiers":[
        {
            "category":"Manufacturing",
            "subcategory":"Electronics",
            "type":"Manufacturing & Wholesale Goods"
        }
    ],
    "sg:phone":"+1 650 473 3400",
    "sg:postcode":"94025",
    "sg:province":"CA",
    "sg:tags":[
        "game",
        "video"
    ],
    "sg:website":"www.crystald.com",
    "wof:name":"Crystal Dynamics Inc",
    "wof:placetype":"venue"
},
  "geometry": {"coordinates":[-122.16665399999999,37.451946],"type":"Point"}
}