{
  "type": "Feature",
  "properties": {
    "addr:full":"20630 Leapwood Ave Carson CA 90746",
    "addr:postcode":"20630;90746",
    "addr:street":"Leapwood Ave",
    "iso:country":"US",
    "sg:address":"20630 Leapwood Ave",
    "sg:city":"Carson",
    "sg:classifiers":[
        {
            "category":"Professional",
            "subcategory":"Computer Services",
            "type":"Services"
        }
    ],
    "sg:phone":"+1 310 225 5520",
    "sg:postcode":"90746",
    "sg:province":"CA",
    "sg:tags":[
        "repair"
    ],
    "sg:website":"www.convenientcomputing.com",
    "wof:name":"Convenient Computing",
    "wof:placetype":"venue"
},
  "geometry": {"coordinates":[-118.258442,33.843059],"type":"Point"}
}