{
  "type": "Feature",
  "properties": {
    "iso:country":"US",
    "sg:address":"7337 Trade St",
    "sg:city":"San Diego",
    "sg:classifiers":[
        {
            "category":"Utilities",
            "subcategory":"Telephone",
            "type":"Services"
        }
    ],
    "sg:phone":"+1 858 886 1638",
    "sg:postcode":"92121",
    "sg:province":"CA",
    "sg:tags":[
        "communications"
    ],
    "wof:name":"Pacific Bell",
    "wof:placetype":"venue"
},
  "geometry": {"coordinates":[-117.163509,32.888599],"type":"Point"}
}