{
  "type": "Feature",
  "properties": {
    "iso:country":"US",
    "sg:address":"726 E 12th St",
    "sg:city":"Los Angeles",
    "sg:classifiers":[
        {
            "category":"Shopping",
            "subcategory":"Clothing, Apparel, & Fashions",
            "type":"Retail Goods"
        }
    ],
    "sg:phone":"+1 213 748 4230",
    "sg:postcode":"90021",
    "sg:province":"CA",
    "sg:tags":[
        "designer"
    ],
    "wof:name":"Nina Piu Fashions",
    "wof:placetype":"venue"
},
  "geometry": {"coordinates":[-118.252463,34.033259],"type":"Point"}
}