{
  "type": "Feature",
  "properties": {
    "addr:full":"1171 E Imperial Hwy Placentia CA 92870",
    "addr:housenumber":"1171",
    "addr:postcode":"ca 92870",
    "addr:street":"E Imperial Hwy",
    "iso:country":"US",
    "sg:address":"1171 E Imperial Hwy",
    "sg:city":"Placentia",
    "sg:classifiers":[
        {
            "category":"Restaurant",
            "type":"Food & Drink"
        }
    ],
    "sg:menulink":"http://www.allmenus.com/ca/anaheim-santa-ana-garden-grove/165705-del-taco/menu/",
    "sg:phone":"+1 714 985 9095",
    "sg:postcode":"92870",
    "sg:province":"CA",
    "sg:tags":[
        "american",
        "mexican",
        "tex-mex"
    ],
    "wof:name":"Del Taco",
    "wof:placetype":"venue"
},
  "geometry": {"coordinates":[-117.84251999999999,33.904899],"type":"Point"}
}