{
  "type": "Feature",
  "properties": {
    "iso:country":"US",
    "sg:address":"1131 California Dr",
    "sg:city":"Burlingame",
    "sg:classifiers":[
        {
            "category":"Autos & Motor Vehicles",
            "subcategory":"Auto Supplies",
            "type":"Retail Goods"
        },
        {
            "category":"Retail",
            "subcategory":"Auto Repair",
            "type":"Services"
        }
    ],
    "sg:phone":"+1 650 342 9429",
    "sg:postcode":"94010",
    "sg:province":"CA",
    "sg:tags":[
        "transmission",
        "transmissions-other"
    ],
    "sg:website":"www.united-transmission-inc.com",
    "wof:name":"United Transmission Inc",
    "wof:placetype":"venue"
},
  "geometry": {"coordinates":[-122.36199999999999,37.587002],"type":"Point"}
}