{
  "type": "Feature",
  "properties": {
    "addr:full":"4415 E Greenmeadow Rd Long Beach CA 90808",
    "addr:housenumber":"4415",
    "addr:postcode":"90808",
    "addr:street":"E Greenmeadow Rd",
    "iso:country":"US",
    "sg:address":"4415 E Greenmeadow Rd",
    "sg:city":"Long Beach",
    "sg:classifiers":[
        {
            "category":"Real Estate",
            "subcategory":"Developer",
            "type":"Services"
        }
    ],
    "sg:phone":"+1 562 421 8934",
    "sg:postcode":"90808",
    "sg:province":"CA",
    "wof:name":"Kerry Choppin Development",
    "wof:placetype":"venue"
},
  "geometry": {"coordinates":[-118.137368,33.833426],"type":"Point"}
}