{
  "type": "Feature",
  "properties": {
    "addr:full":"14232 Oxnard St Van Nuys CA 91401",
    "addr:housenumber":"14232",
    "addr:postcode":"91401",
    "addr:street":"Oxnard St",
    "iso:country":"US",
    "sg:address":"14232 Oxnard St",
    "sg:city":"Van Nuys",
    "sg:classifiers":[
        {
            "category":"Retail",
            "subcategory":"Auto Repair",
            "type":"Services"
        }
    ],
    "sg:phone":"+1 818 989 4070",
    "sg:postcode":"91401",
    "sg:province":"CA",
    "sg:tags":[
        "repairing",
        "automobile"
    ],
    "sg:website":"www.sbcglobal.net",
    "wof:name":"British Motors",
    "wof:placetype":"venue"
},
  "geometry": {"coordinates":[-118.443001,34.179501],"type":"Point"}
}