{
  "type": "Feature",
  "properties": {
    "iso:country":"US",
    "sg:address":"2052 Lake Ave",
    "sg:city":"Altadena",
    "sg:classifiers":[
        {
            "category":"Community Center",
            "type":"Public Place"
        }
    ],
    "sg:phone":"+1 626 798 8971",
    "sg:postcode":"91001",
    "sg:province":"CA",
    "sg:tags":[
        "medical"
    ],
    "wof:name":"North Lake Rehabilitation & Medical Center",
    "wof:placetype":"venue"
},
  "geometry": {"coordinates":[-118.131218,34.181003],"type":"Point"}
}