{
  "type": "Feature",
  "properties": {
    "addr:full":"2651 Pleasant Hill Rd Pleasant Hill CA 94523",
    "addr:housenumber":"2651",
    "addr:postcode":"94523",
    "addr:street":"Pleasant Hill Rd",
    "iso:country":"US",
    "sg:address":"2651 Pleasant Hill Rd",
    "sg:city":"Pleasant Hill",
    "sg:classifiers":[
        {
            "category":"Utilities",
            "subcategory":"Telephone",
            "type":"Services"
        }
    ],
    "sg:phone":"+1 925 943 7577",
    "sg:postcode":"94523",
    "sg:province":"CA",
    "sg:tags":[
        "telecommunication"
    ],
    "wof:name":"Forward Technology Group",
    "wof:placetype":"venue"
},
  "geometry": {"coordinates":[-122.088752,37.954591],"type":"Point"}
}