{
  "type": "Feature",
  "properties": {
    "iso:country":"US",
    "sg:address":"2827 W Pomona Blvd",
    "sg:city":"Pomona",
    "sg:classifiers":[
        {
            "category":"Education",
            "subcategory":"School",
            "type":"Public Place"
        }
    ],
    "sg:phone":"+1 909 444 5515",
    "sg:postcode":"91768",
    "sg:province":"CA",
    "wof:name":"Pillars of Faith Christian",
    "wof:placetype":"venue"
},
  "geometry": {"coordinates":[-117.799577,34.055089],"type":"Point"}
}