{
  "type": "Feature",
  "properties": {
    "addr:full":"9255 San Fernando Rd Sun Valley CA 91352",
    "addr:housenumber":"9255",
    "addr:postcode":"91352",
    "addr:street":"San Fernando Rd",
    "iso:country":"US",
    "sg:address":"9255 San Fernando Rd",
    "sg:city":"Sun Valley",
    "sg:classifiers":[
        {
            "category":"Wholesale",
            "subcategory":"Durable Goods & Equipment",
            "type":"Manufacturing & Wholesale Goods"
        }
    ],
    "sg:phone":"+1 818 768 2651",
    "sg:postcode":"91352",
    "sg:province":"CA",
    "sg:tags":[
        "engineering",
        "supply"
    ],
    "wof:name":"Walker Design Inc",
    "wof:placetype":"venue"
},
  "geometry": {"coordinates":[-118.391508,34.236919],"type":"Point"}
}