{
  "type": "Feature",
  "properties": {
    "addr:full":"10913 Hamlow Rd Denair CA 95316",
    "addr:housenumber":"10913",
    "addr:postcode":"95316",
    "addr:street":"Hamlow Rd",
    "iso:country":"US",
    "sg:address":"10913 Hamlow Rd",
    "sg:city":"Denair",
    "sg:classifiers":[
        {
            "category":"Manufacturing",
            "subcategory":"Wood Products",
            "type":"Manufacturing & Wholesale Goods"
        }
    ],
    "sg:phone":"+1 209 632 0163",
    "sg:postcode":"95316",
    "sg:province":"CA",
    "sg:tags":[
        "millwork-wholesale",
        "millwork",
        "manufacturer"
    ],
    "wof:name":"Boulet & Sons Woodworks",
    "wof:placetype":"venue"
},
  "geometry": {"coordinates":[-120.79364700000001,37.558414],"type":"Point"}
}