{
  "type": "Feature",
  "properties": {
    "addr:full":"338 Maple St Lodi CA 95240",
    "addr:housenumber":"338",
    "addr:postcode":"95240",
    "addr:street":"Maple St",
    "iso:country":"US",
    "sg:address":"338 Maple St",
    "sg:city":"Lodi",
    "sg:classifiers":[
        {
            "category":"Professional",
            "type":"Services"
        }
    ],
    "sg:phone":"+1 209 339 1831",
    "sg:postcode":"95240",
    "sg:province":"CA",
    "wof:name":"Trevions Art & Desi",
    "wof:placetype":"venue"
},
  "geometry": {"coordinates":[-121.265922,38.12479],"type":"Point"}
}