{
  "type": "Feature",
  "properties": {
    "iso:country":"US",
    "sg:address":"8652 Macedonian Ct",
    "sg:city":"Elk Grove",
    "sg:classifiers":[
        {
            "category":"Professional",
            "type":"Services"
        }
    ],
    "sg:phone":"+1 916 681 7833",
    "sg:postcode":"95624",
    "sg:province":"CA",
    "sg:tags":[
        "establishment"
    ],
    "wof:name":"I'm Charming",
    "wof:placetype":"venue"
},
  "geometry": {"coordinates":[-121.382887,38.444117],"type":"Point"}
}