{
  "type": "Feature",
  "properties": {
    "iso:country":"US",
    "sg:address":"1301 Palmetto Ave",
    "sg:city":"Pacifica",
    "sg:classifiers":[
        {
            "category":"Restaurant",
            "type":"Food & Drink"
        }
    ],
    "sg:phone":"+1 650 355 1812",
    "sg:postcode":"94044",
    "sg:province":"CA",
    "wof:name":"Mitsu Japanese Restaurant",
    "wof:placetype":"venue"
},
  "geometry": {"coordinates":[-122.492453,37.640039],"type":"Point"}
}