{
  "type": "Feature",
  "properties": {
    "iso:country":"US",
    "sg:address":"54 Linda St",
    "sg:city":"San Francisco",
    "sg:classifiers":[
        {
            "category":"Professional",
            "subcategory":"Computer Services",
            "type":"Services"
        }
    ],
    "sg:phone":"+1 415 830 6368",
    "sg:postcode":"94110",
    "sg:province":"CA",
    "sg:tags":[
        "mobile",
        "iphone",
        "android",
        "mobileweb",
        "consulting",
        "agile"
    ],
    "sg:website":"http://www.spinnakerstudio.com",
    "wof:name":"Spinnaker Studio",
    "wof:placetype":"venue"
},
  "geometry": {"coordinates":[-122.423013,37.760884],"type":"Point"}
}