{
  "type": "Feature",
  "properties": {
    "addr:full":"1995 El Camino Real Suite 202 Santa Clara CA 95050",
    "addr:housenumber":"1995",
    "addr:postcode":"95050",
    "addr:street":"El Camino Real Suite 202",
    "iso:country":"US",
    "sg:address":"1995 El Camino Real Suite 202",
    "sg:city":"Santa Clara",
    "sg:classifiers":[
        {
            "category":"Real Estate",
            "subcategory":"Real Estate Agent",
            "type":"Services"
        }
    ],
    "sg:phone":"+1 408 615 1000",
    "sg:postcode":"95050",
    "sg:province":"CA",
    "sg:website":"www.clickhome.us/default.html",
    "wof:name":"Clickhome",
    "wof:placetype":"venue"
},
  "geometry": {"coordinates":[-121.95908900000001,37.352466],"type":"Point"}
}