{
  "type": "Feature",
  "properties": {
    "addr:full":"1956 S El Camino Real San Mateo CA 94403",
    "addr:housenumber":"1956",
    "addr:postcode":"94403",
    "addr:street":"S El Camino Real",
    "iso:country":"US",
    "sg:address":"1956 S El Camino Real",
    "sg:city":"San Mateo",
    "sg:classifiers":[
        {
            "category":"Food & Beverages",
            "subcategory":"Groceries & Convenience Stores",
            "type":"Retail Goods"
        }
    ],
    "sg:phone":"+1 650 212 7398",
    "sg:postcode":"94403",
    "sg:province":"CA",
    "sg:website":"www.nijiya.com",
    "wof:name":"Nijiya Market",
    "wof:placetype":"venue"
},
  "geometry": {"coordinates":[-122.310411,37.548732],"type":"Point"}
}