{
  "type": "Feature",
  "properties": {
    "addr:full":"980 Woodland Dr Hillsborough CA 94010",
    "addr:housenumber":"980",
    "addr:postcode":"94010",
    "addr:street":"Woodland Dr",
    "iso:country":"US",
    "sg:address":"980 Woodland Dr",
    "sg:city":"Hillsborough",
    "sg:classifiers":[
        {
            "category":"Health Services",
            "subcategory":"Clinic",
            "type":"Services"
        }
    ],
    "sg:phone":"+1 650 571 0959",
    "sg:postcode":"94010",
    "sg:province":"CA",
    "sg:tags":[
        "welfare"
    ],
    "wof:name":"Health And Wellness Educator",
    "wof:placetype":"venue"
},
  "geometry": {"coordinates":[-122.33252,37.550442],"type":"Point"}
}