{
  "type": "Feature",
  "properties": {
    "iso:country":"US",
    "sg:address":"3963 Central Ln",
    "sg:city":"Winters",
    "sg:classifiers":[
        {
            "category":"Building & Trades",
            "subcategory":"Landscaping Services",
            "type":"Services"
        }
    ],
    "sg:phone":"+1 530 795 1517",
    "sg:postcode":"95694",
    "sg:province":"CA",
    "wof:name":"Tree Associates",
    "wof:placetype":"venue"
},
  "geometry": {"coordinates":[-121.994491,38.484428],"type":"Point"}
}