{
  "type": "Feature",
  "properties": {
    "iso:country":"US",
    "sg:address":"15094 E 14th St",
    "sg:city":"San Leandro",
    "sg:classifiers":[
        {
            "category":"Personal",
            "subcategory":"Beauty Salon",
            "type":"Services"
        }
    ],
    "sg:phone":"+1 510 276 7877",
    "sg:postcode":"94578",
    "sg:province":"CA",
    "wof:name":"Hair Revival",
    "wof:placetype":"venue"
},
  "geometry": {"coordinates":[-122.12904899999999,37.705803],"type":"Point"}
}