{
  "type": "Feature",
  "properties": {
    "addr:full":"1739 Crows Landing Rd Ste E Modesto CA 95358",
    "addr:housenumber":"1739",
    "addr:postcode":"ca 95358",
    "addr:street":"Crows Landing Rd Ste E",
    "iso:country":"US",
    "sg:address":"1739 Crows Landing Rd Ste E",
    "sg:city":"Modesto",
    "sg:classifiers":[
        {
            "category":"Personal",
            "subcategory":"Beauty Salon",
            "type":"Services"
        }
    ],
    "sg:phone":"+1 209 538 0870",
    "sg:postcode":"95358",
    "sg:province":"CA",
    "sg:tags":[
        "hair"
    ],
    "wof:name":"Stilos Beauty Salon",
    "wof:placetype":"venue"
},
  "geometry": {"coordinates":[-120.993703,37.604684],"type":"Point"}
}