{
  "type": "Feature",
  "properties": {
    "iso:country":"US",
    "sg:address":"2705 N Grand Ave",
    "sg:city":"Santa Ana",
    "sg:classifiers":[
        {
            "category":"Shopping",
            "subcategory":"Florist",
            "type":"Retail Goods"
        }
    ],
    "sg:phone":"+1 714 997 3228",
    "sg:postcode":"92705",
    "sg:province":"CA",
    "sg:website":"www.serendipityflorists.com",
    "wof:name":"Serendipity Flowers",
    "wof:placetype":"venue"
},
  "geometry": {"coordinates":[-117.852918,33.773599],"type":"Point"}
}