{
  "type": "Feature",
  "properties": {
    "iso:country":"US",
    "sg:address":"217 Rhonda Way",
    "sg:city":"Mill Valley",
    "sg:classifiers":[
        {
            "category":"Building & Trades",
            "subcategory":"Construction",
            "type":"Services"
        }
    ],
    "sg:phone":"+1 415 383 5710",
    "sg:postcode":"94941",
    "sg:province":"CA",
    "sg:tags":[
        "tile",
        "dealer"
    ],
    "wof:name":"Canterbury Tiles",
    "wof:placetype":"venue"
},
  "geometry": {"coordinates":[-122.540318,37.892323],"type":"Point"}
}