{
  "type": "Feature",
  "properties": {
    "addr:full":"13000 Venice Blvd Los Angeles CA 90066",
    "addr:housenumber":"13000",
    "addr:postcode":"90066",
    "addr:street":"Venice Blvd",
    "iso:country":"US",
    "sg:address":"13000 Venice Blvd",
    "sg:city":"Los Angeles",
    "sg:classifiers":[
        {
            "category":"Health Services",
            "subcategory":"Clinic",
            "type":"Services"
        }
    ],
    "sg:phone":"+1 310 308 3189",
    "sg:postcode":"90066",
    "sg:province":"CA",
    "sg:tags":[
        "counseling",
        "mental"
    ],
    "sg:website":"www.hypnotistlosangeles.com",
    "wof:name":"Gregory Stacy, Certified Hypnotist",
    "wof:placetype":"venue"
},
  "geometry": {"coordinates":[-118.442876,33.998892],"type":"Point"}
}