{
  "type": "Feature",
  "properties": {
    "iso:country":"US",
    "sg:address":"5273 Pine Hollow Rd",
    "sg:city":"Concord",
    "sg:classifiers":[
        {
            "category":"Building & Trades",
            "subcategory":"Construction",
            "type":"Services"
        }
    ],
    "sg:phone":"+1 925 672 6606",
    "sg:postcode":"94521",
    "sg:province":"CA",
    "sg:tags":[
        "carpenter"
    ],
    "wof:name":"William Nist",
    "wof:placetype":"venue"
},
  "geometry": {"coordinates":[-121.967125,37.943617],"type":"Point"}
}