{
  "type": "Feature",
  "properties": {
    "addr:full":"1300 W Olympic Blvd Los Angeles CA 90015",
    "addr:housenumber":"1300",
    "addr:postcode":"90015",
    "addr:street":"W Olympic Blvd",
    "iso:country":"US",
    "sg:address":"1300 W Olympic Blvd",
    "sg:city":"Los Angeles",
    "sg:classifiers":[
        {
            "category":"Wholesale",
            "subcategory":"Non-durable Goods",
            "type":"Manufacturing & Wholesale Goods"
        }
    ],
    "sg:phone":"+1 213 382 8249",
    "sg:postcode":"90015",
    "sg:province":"CA",
    "sg:tags":[
        "sporting"
    ],
    "wof:name":"Jimex America",
    "wof:placetype":"venue"
},
  "geometry": {"coordinates":[-118.27113,34.047803],"type":"Point"}
}