{
  "type": "Feature",
  "properties": {
    "iso:country":"US",
    "sg:address":"1033 San Felipe Rd",
    "sg:city":"Hollister",
    "sg:classifiers":[
        {
            "category":"Manufacturing",
            "subcategory":"Electronics",
            "type":"Manufacturing & Wholesale Goods"
        }
    ],
    "sg:phone":"+1 831 638 1096",
    "sg:postcode":"95023",
    "sg:province":"CA",
    "sg:tags":[
        "equipment",
        "mfg",
        "antenna",
        "communication"
    ],
    "wof:name":"Antenna Systems Inc",
    "wof:placetype":"venue"
},
  "geometry": {"coordinates":[-121.400814,36.872963],"type":"Point"}
}