{
  "type": "Feature",
  "properties": {
    "addr:full":"1018 W 14th St Upland CA 91786",
    "addr:housenumber":"1018",
    "addr:postcode":"91786",
    "addr:street":"W 14Th St",
    "iso:country":"US",
    "sg:address":"1018 W 14th St",
    "sg:city":"Upland",
    "sg:classifiers":[
        {
            "category":"Building & Trades",
            "subcategory":"Construction",
            "type":"Services"
        }
    ],
    "sg:phone":"+1 909 920 9943",
    "sg:postcode":"91786",
    "sg:province":"CA",
    "sg:tags":[
        "designer",
        "dealer",
        "pool",
        "swimming"
    ],
    "wof:name":"Mountainstone",
    "wof:placetype":"venue"
},
  "geometry": {"coordinates":[-117.667207,34.11412],"type":"Point"}
}