{
  "type": "Feature",
  "properties": {
    "addr:full":"1498 Isabella St Santa Clara CA 95050",
    "addr:housenumber":"1498",
    "addr:postcode":"95050",
    "addr:street":"Isabella St",
    "iso:country":"US",
    "sg:address":"1498 Isabella St",
    "sg:city":"Santa Clara",
    "sg:classifiers":[
        {
            "category":"Restaurant",
            "type":"Food & Drink"
        }
    ],
    "sg:phone":"+1 408 247 0745",
    "sg:postcode":"95050",
    "sg:province":"CA",
    "sg:tags":[
        "pakistani",
        "indian"
    ],
    "sg:website":"www.kababandcurrys.com",
    "wof:name":"Kabab and Curry's",
    "wof:placetype":"venue"
},
  "geometry": {"coordinates":[-121.955416,37.351369],"type":"Point"}
}