{
  "type": "Feature",
  "properties": {
    "addr:full":"1140 University Dr Menlo Park CA 94025",
    "addr:housenumber":"1140",
    "addr:postcode":"94025",
    "addr:street":"University Dr",
    "iso:country":"US",
    "sg:address":"1140 University Dr",
    "sg:city":"Menlo Park",
    "sg:classifiers":[
        {
            "category":"Personal",
            "subcategory":"Beauty Salon",
            "type":"Services"
        }
    ],
    "sg:phone":"+1 650 327 5136",
    "sg:postcode":"94025",
    "sg:province":"CA",
    "wof:name":"Kenneth Michael Hair Salon",
    "wof:placetype":"venue"
},
  "geometry": {"coordinates":[-122.186905,37.450325],"type":"Point"}
}