{
  "type": "Feature",
  "properties": {
    "addr:full":"26352 Marsala Dr Valencia CA 91355",
    "addr:postcode":"91355",
    "addr:street":"Marsala Dr",
    "iso:country":"US",
    "sg:address":"26352 Marsala Dr",
    "sg:city":"Valencia",
    "sg:classifiers":[
        {
            "category":"Wholesale",
            "subcategory":"Durable Goods & Equipment",
            "type":"Manufacturing & Wholesale Goods"
        }
    ],
    "sg:phone":"+1 661 253 1530",
    "sg:postcode":"91355",
    "sg:province":"CA",
    "wof:name":"Wholesale Distributor Ltd",
    "wof:placetype":"venue"
},
  "geometry": {"coordinates":[-118.56314999999999,34.410603],"type":"Point"}
}