{
  "type": "Feature",
  "properties": {
    "addr:full":"3301 Maple Ave Los Angeles CA 90011",
    "addr:housenumber":"3301",
    "addr:postcode":"90011",
    "addr:street":"Maple Ave",
    "iso:country":"US",
    "sg:address":"3301 Maple Ave",
    "sg:city":"Los Angeles",
    "sg:classifiers":[
        {
            "category":"Wholesale",
            "subcategory":"Electrical",
            "type":"Manufacturing & Wholesale Goods"
        }
    ],
    "sg:phone":"+1 323 235 4194",
    "sg:postcode":"90011",
    "sg:province":"CA",
    "sg:tags":[
        "fixture",
        "component",
        "to",
        "lamp",
        "parts",
        "supplier"
    ],
    "wof:name":"Lighting Parts Inc",
    "wof:placetype":"venue"
},
  "geometry": {"coordinates":[-118.26864,34.018625],"type":"Point"}
}