{
  "type": "Feature",
  "properties": {
    "addr:full":"15423 Bloomfield Ave Norwalk CA 90650",
    "addr:housenumber":"15423",
    "addr:postcode":"90650",
    "addr:street":"Bloomfield Ave",
    "iso:country":"US",
    "sg:address":"15423 Bloomfield Ave",
    "sg:city":"Norwalk",
    "sg:classifiers":[
        {
            "category":"Building & Trades",
            "subcategory":"Cleaning & Sanitation",
            "type":"Services"
        }
    ],
    "sg:phone":"+1 562 404 7408",
    "sg:postcode":"90650",
    "sg:province":"CA",
    "sg:tags":[
        "janitor"
    ],
    "wof:name":"A B Cleaning Svc",
    "wof:placetype":"venue"
},
  "geometry": {"coordinates":[-118.06407,33.889763],"type":"Point"}
}