{
  "type": "Feature",
  "properties": {
    "addr:full":"1390 El Sereno Ave Pasadena CA 91103",
    "addr:housenumber":"1390",
    "addr:postcode":"91103",
    "addr:street":"El Sereno Ave",
    "iso:country":"US",
    "sg:address":"1390 El Sereno Ave",
    "sg:city":"Pasadena",
    "sg:classifiers":[
        {
            "category":"Building & Trades",
            "subcategory":"Landscaping Services",
            "type":"Services"
        }
    ],
    "sg:phone":"+1 626 818 8704",
    "sg:postcode":"91103",
    "sg:province":"CA",
    "sg:website":"www.relevantyellow.com/Landscapi...",
    "wof:name":"West Coast Landscape",
    "wof:placetype":"venue"
},
  "geometry": {"coordinates":[-118.151905,34.169709],"type":"Point"}
}