{
  "type": "Feature",
  "properties": {
    "addr:full":"16484 Beach Blvd Westminster CA 92683",
    "addr:housenumber":"16484",
    "addr:postcode":"92683",
    "addr:street":"Beach Blvd",
    "iso:country":"US",
    "sg:address":"16484 Beach Blvd",
    "sg:city":"Westminster",
    "sg:classifiers":[
        {
            "category":"Personal",
            "subcategory":"Nail Salon",
            "type":"Services"
        }
    ],
    "sg:phone":"+1 714 843 0083",
    "sg:postcode":"92683",
    "sg:province":"CA",
    "wof:name":"Tip Top Nails",
    "wof:placetype":"venue"
},
  "geometry": {"coordinates":[-117.988998,33.723099],"type":"Point"}
}