{
  "type": "Feature",
  "properties": {
    "iso:country":"US",
    "sg:address":"3400 El Camino Real",
    "sg:city":"Santa Clara",
    "sg:classifiers":[
        {
            "category":"Professional",
            "subcategory":"Computer Services",
            "type":"Services"
        }
    ],
    "sg:phone":"+1 408 244 6528",
    "sg:postcode":"95051",
    "sg:province":"CA",
    "sg:tags":[
        "repair"
    ],
    "sg:website":"www.joylap.com",
    "wof:name":"Joylap Computers",
    "wof:placetype":"venue"
},
  "geometry": {"coordinates":[-121.98963500000001,37.351992],"type":"Point"}
}