{
  "type": "Feature",
  "properties": {
    "addr:full":"1190 Bello St Pismo Beach CA 93449",
    "addr:housenumber":"1190",
    "addr:postcode":"93449",
    "addr:street":"Bello St",
    "iso:country":"US",
    "sg:address":"1190 Bello St",
    "sg:city":"Pismo Beach",
    "sg:classifiers":[
        {
            "category":"Organizations",
            "subcategory":"Religious Organization",
            "type":"Services"
        }
    ],
    "sg:phone":"+1 805 773 5944",
    "sg:postcode":"93449",
    "sg:province":"CA",
    "sg:tags":[
        "church"
    ],
    "wof:name":"First Church-Christ Scientist",
    "wof:placetype":"venue"
},
  "geometry": {"coordinates":[-120.64145000000001,35.144791],"type":"Point"}
}