{
  "type": "Feature",
  "properties": {
    "addr:full":"467 Hamilton Ave Palo Alto CA 94301",
    "addr:housenumber":"467",
    "addr:postcode":"94301",
    "addr:street":"Hamilton Ave",
    "iso:country":"US",
    "sg:address":"467 Hamilton Ave",
    "sg:city":"Palo Alto",
    "sg:classifiers":[
        {
            "category":"Insurance",
            "subcategory":"Insurance Agent",
            "type":"Services"
        }
    ],
    "sg:phone":"+1 650 329 1330",
    "sg:postcode":"94301",
    "sg:province":"CA",
    "wof:name":"Dworkin Insurance Services",
    "wof:placetype":"venue"
},
  "geometry": {"coordinates":[-122.158737,37.446731],"type":"Point"}
}