{
  "type": "Feature",
  "properties": {
    "iso:country":"US",
    "sg:address":"5257 Prosperity Ln",
    "sg:city":"San Diego",
    "sg:classifiers":[
        {
            "category":"Banks & Credit Unions",
            "subcategory":"Financial Services",
            "type":"Services"
        }
    ],
    "sg:phone":"+1 619 286 3053",
    "sg:postcode":"92115",
    "sg:province":"CA",
    "sg:tags":[
        "trust",
        "management"
    ],
    "wof:name":"Hallahan Trust",
    "wof:placetype":"venue"
},
  "geometry": {"coordinates":[-117.083457,32.768984],"type":"Point"}
}