{
  "type": "Feature",
  "properties": {
    "addr:full":"16406 Cooper Rd Nevada City CA 95959",
    "addr:housenumber":"16406",
    "addr:postcode":"95959",
    "addr:street":"Cooper Rd",
    "iso:country":"US",
    "sg:address":"16406 Cooper Rd",
    "sg:city":"Nevada City",
    "sg:classifiers":[
        {
            "category":"Shopping",
            "subcategory":"Catalog Store",
            "type":"Retail Goods"
        }
    ],
    "sg:phone":"+1 530 265 5562",
    "sg:postcode":"95959",
    "sg:province":"CA",
    "sg:tags":[
        "e"
    ],
    "wof:name":"Shopping Cart Queen",
    "wof:placetype":"venue"
},
  "geometry": {"coordinates":[-120.983211,39.294245],"type":"Point"}
}