{
  "type": "Feature",
  "properties": {
    "addr:full":"780 Welch Rd Palo Alto CA 94304",
    "addr:housenumber":"780",
    "addr:postcode":"94304",
    "addr:street":"Welch Rd",
    "iso:country":"US",
    "sg:address":"780 Welch Rd",
    "sg:city":"Palo Alto",
    "sg:classifiers":[
        {
            "category":"Health Services",
            "subcategory":"Hospital",
            "type":"Services"
        },
        {
            "category":"Health Services",
            "subcategory":"Clinic",
            "type":"Services"
        }
    ],
    "sg:phone":"+1 650 723 5093",
    "sg:postcode":"94304",
    "sg:province":"CA",
    "sg:tags":[
        "banks",
        "center",
        "blood",
        "general"
    ],
    "wof:name":"Stanford Med Schl Blood Ctr",
    "wof:placetype":"venue"
},
  "geometry": {"coordinates":[-122.174722,37.437246],"type":"Point"}
}