{
  "type": "Feature",
  "properties": {
    "iso:country":"US",
    "sg:address":"17251 Foothill Blvd",
    "sg:city":"Fontana",
    "sg:classifiers":[
        {
            "category":"Shopping",
            "type":"Retail Goods"
        }
    ],
    "sg:phone":"+1 909 463 2392",
    "sg:postcode":"92335",
    "sg:province":"CA",
    "sg:tags":[
        "telephone",
        "cellular"
    ],
    "wof:name":"Cellular Warehouse",
    "wof:placetype":"venue"
},
  "geometry": {"coordinates":[-117.429993,34.106569],"type":"Point"}
}