{
  "type": "Feature",
  "properties": {
    "iso:country":"US",
    "sg:address":"1117 W Ave K",
    "sg:city":"Lancaster",
    "sg:classifiers":[
        {
            "category":"Home & Garden",
            "subcategory":"Furniture",
            "type":"Retail Goods"
        }
    ],
    "sg:phone":"+1 661 948 2220",
    "sg:postcode":"93534",
    "sg:province":"CA",
    "sg:tags":[
        "mattress"
    ],
    "sg:website":"www.getabed.com",
    "wof:name":"Four Day Mattress Store",
    "wof:placetype":"venue"
},
  "geometry": {"coordinates":[-118.150359,34.674945],"type":"Point"}
}