{
  "type": "Feature",
  "properties": {
    "addr:full":"107 S Cedros Ave Ste 220 Solana Beach CA 92075",
    "addr:housenumber":"107",
    "addr:postcode":"92075",
    "addr:street":"S Cedros Ave Ste 220",
    "iso:country":"US",
    "sg:address":"107 S Cedros Ave Ste 220",
    "sg:city":"Solana Beach",
    "sg:classifiers":[
        {
            "category":"Health Services",
            "subcategory":"Clinic",
            "type":"Services"
        }
    ],
    "sg:phone":"+1 858 793 9500",
    "sg:postcode":"92075",
    "sg:province":"CA",
    "sg:tags":[
        "spa",
        "medical",
        "weight",
        "loss"
    ],
    "sg:website":"www.onelifediet.com",
    "wof:name":"One Life",
    "wof:placetype":"venue"
},
  "geometry": {"coordinates":[-117.270827,32.991673],"type":"Point"}
}