{
  "type": "Feature",
  "properties": {
    "iso:country":"US",
    "sg:address":"2524 Seaboard Ave",
    "sg:city":"San Jose",
    "sg:classifiers":[
        {
            "category":"Professional",
            "subcategory":"Art Services",
            "type":"Services"
        }
    ],
    "sg:phone":"+1 408 433 5184",
    "sg:postcode":"95131",
    "sg:province":"CA",
    "sg:tags":[
        "graphic",
        "designer"
    ],
    "wof:name":"Mental Image Design",
    "wof:placetype":"venue"
},
  "geometry": {"coordinates":[-121.938373,37.378437],"type":"Point"}
}