{
  "type": "Feature",
  "properties": {
    "addr:full":"2533 Peralta St Oakland CA 94607",
    "addr:housenumber":"2533",
    "addr:postcode":"94607",
    "addr:street":"Peralta St",
    "iso:country":"US",
    "sg:address":"2533 Peralta St",
    "sg:city":"Oakland",
    "sg:classifiers":[
        {
            "category":"Food & Beverages",
            "subcategory":"Meat & Fish",
            "type":"Retail Goods"
        }
    ],
    "sg:phone":"+1 510 268 8884",
    "sg:postcode":"94607",
    "sg:province":"CA",
    "sg:tags":[
        "seafood",
        "seafood-wholesale",
        "market"
    ],
    "wof:name":"Coast Exports Inc",
    "wof:placetype":"venue"
},
  "geometry": {"coordinates":[-122.28755200000001,37.819363],"type":"Point"}
}