{
  "type": "Feature",
  "properties": {
    "iso:country":"US",
    "sg:address":"2940 Fanshell Walk",
    "sg:city":"Oxnard",
    "sg:classifiers":[
        {
            "category":"Professional",
            "subcategory":"Accounting & Tax Preparation",
            "type":"Services"
        }
    ],
    "sg:phone":"+1 805 985 7195",
    "sg:postcode":"93035",
    "sg:province":"CA",
    "sg:tags":[
        "bookkeeping",
        "billing"
    ],
    "wof:name":"My Bookkeeper",
    "wof:placetype":"venue"
},
  "geometry": {"coordinates":[-119.208907,34.189751],"type":"Point"}
}