{
  "type": "Feature",
  "properties": {
    "iso:country":"US",
    "sg:address":"8723 Dublin Dr",
    "sg:city":"Bakersfield",
    "sg:classifiers":[
        {
            "category":"Building & Trades",
            "subcategory":"Construction",
            "type":"Services"
        }
    ],
    "sg:phone":"+1 661 832 4251",
    "sg:postcode":"93307",
    "sg:province":"CA",
    "sg:tags":[
        "welder"
    ],
    "wof:name":"Ali Y Rey",
    "wof:placetype":"venue"
},
  "geometry": {"coordinates":[-119.014122,35.27731],"type":"Point"}
}