{
  "type": "Feature",
  "properties": {
    "addr:full":"6 N 1st Ave Arcadia CA 91006",
    "addr:housenumber":"6",
    "addr:postcode":"91006",
    "addr:street":"N 1St Ave",
    "iso:country":"US",
    "sg:address":"6 N 1st Ave",
    "sg:city":"Arcadia",
    "sg:classifiers":[
        {
            "category":"Professional",
            "type":"Services"
        }
    ],
    "sg:phone":"+1 626 294 9450",
    "sg:postcode":"91006",
    "sg:province":"CA",
    "wof:name":"Jim Nichols",
    "wof:placetype":"venue"
},
  "geometry": {"coordinates":[-118.02829,34.141141],"type":"Point"}
}