{
  "type": "Feature",
  "properties": {
    "iso:country":"US",
    "sg:address":"4007 W Ave L",
    "sg:city":"Quartz Hill",
    "sg:classifiers":[
        {
            "category":"Autos & Motor Vehicles",
            "subcategory":"Auto Supplies",
            "type":"Retail Goods"
        }
    ],
    "sg:phone":"+1 661 722 4134",
    "sg:postcode":"93536",
    "sg:province":"CA",
    "sg:tags":[
        "automobile",
        "parts"
    ],
    "wof:name":"Autozone",
    "wof:placetype":"venue"
},
  "geometry": {"coordinates":[-118.201437,34.660138],"type":"Point"}
}