{
  "type": "Feature",
  "properties": {
    "iso:country":"US",
    "sg:address":"146 Roosevelt Ave",
    "sg:city":"Redwood City",
    "sg:classifiers":[
        {
            "category":"Building & Trades",
            "subcategory":"Landscaping Services",
            "type":"Services"
        }
    ],
    "sg:phone":"+1 650 207 3628",
    "sg:postcode":"94061",
    "sg:province":"CA",
    "wof:name":"Garcia Martin Gardening Svc",
    "wof:placetype":"venue"
},
  "geometry": {"coordinates":[-122.226257,37.478663],"type":"Point"}
}