{
  "type": "Feature",
  "properties": {
    "addr:full":"20061 Brookhurst St Huntington Beach CA 92646",
    "addr:housenumber":"20061",
    "addr:postcode":"92646",
    "addr:street":"Brookhurst St",
    "iso:country":"US",
    "sg:address":"20061 Brookhurst St",
    "sg:city":"Huntington Beach",
    "sg:classifiers":[
        {
            "category":"Banks & Credit Unions",
            "subcategory":"Bank",
            "type":"Services"
        }
    ],
    "sg:phone":"+1 714 965 6677",
    "sg:postcode":"92646",
    "sg:province":"CA",
    "sg:tags":[
        "national"
    ],
    "sg:website":"www.bankofamerica.com",
    "wof:name":"Bank Of America",
    "wof:placetype":"venue"
},
  "geometry": {"coordinates":[-117.95382600000001,33.668833],"type":"Point"}
}