{
  "type": "Feature",
  "properties": {
    "iso:country":"US",
    "sg:address":"2653 Elm Ave",
    "sg:city":"Long Beach",
    "sg:classifiers":[
        {
            "category":"Health Services",
            "subcategory":"Doctor",
            "type":"Services"
        }
    ],
    "sg:phone":"+1 562 595 7335",
    "sg:postcode":"90806",
    "sg:province":"CA",
    "wof:name":"Blitzer Jonathan B MD",
    "wof:placetype":"venue"
},
  "geometry": {"coordinates":[-118.188004,33.8046],"type":"Point"}
}