{
  "type": "Feature",
  "properties": {
    "iso:country":"US",
    "sg:address":"3742 San Pablo Dam Rd",
    "sg:city":"El Sobrante",
    "sg:classifiers":[
        {
            "category":"Bars & Pubs",
            "type":"Food & Drink"
        }
    ],
    "sg:phone":"+1 510 223 8551",
    "sg:postcode":"94803",
    "sg:province":"CA",
    "sg:tags":[
        "lounge",
        "cocktail"
    ],
    "wof:name":"Clancy's",
    "wof:placetype":"venue"
},
  "geometry": {"coordinates":[-122.317332,37.964249],"type":"Point"}
}