{
  "type": "Feature",
  "properties": {
    "addr:full":"151 E Evelyn Ave Mountain View CA 94041",
    "addr:housenumber":"151",
    "addr:postcode":"94041",
    "addr:street":"E Evelyn Ave",
    "iso:country":"US",
    "sg:address":"151 E Evelyn Ave",
    "sg:city":"Mountain View",
    "sg:classifiers":[
        {
            "category":"Retail",
            "subcategory":"Auto Repair",
            "type":"Services"
        }
    ],
    "sg:phone":"+1 650 210 9080",
    "sg:postcode":"94041",
    "sg:province":"CA",
    "sg:website":"michauxautomotive.streetcarmike....",
    "wof:name":"Michaux Automotive",
    "wof:placetype":"venue"
},
  "geometry": {"coordinates":[-122.064003,37.389702],"type":"Point"}
}