{
  "type": "Feature",
  "properties": {
    "addr:full":"41 Park Ln Brisbane CA 94005",
    "addr:housenumber":"41",
    "addr:postcode":"94005",
    "addr:street":"Park Ln",
    "iso:country":"US",
    "sg:address":"41 Park Ln",
    "sg:city":"Brisbane",
    "sg:classifiers":[
        {
            "category":"Wholesale",
            "subcategory":"Apparel",
            "type":"Manufacturing & Wholesale Goods"
        }
    ],
    "sg:phone":"+1 415 647 8899",
    "sg:postcode":"94005",
    "sg:province":"CA",
    "sg:website":"www.sfoapparel.com",
    "wof:name":"SFO Apparel",
    "wof:placetype":"venue"
},
  "geometry": {"coordinates":[-122.40234,37.686472],"type":"Point"}
}