{
  "type": "Feature",
  "properties": {
    "addr:full":"951 Central Ave Tracy CA 95376",
    "addr:housenumber":"951",
    "addr:postcode":"95376",
    "addr:street":"Central Ave",
    "iso:country":"US",
    "sg:address":"951 Central Ave",
    "sg:city":"Tracy",
    "sg:classifiers":[
        {
            "category":"Banks & Credit Unions",
            "subcategory":"Bank",
            "type":"Services"
        }
    ],
    "sg:phone":"+1 209 832 6450",
    "sg:postcode":"95376",
    "sg:province":"CA",
    "sg:website":"www.tracyfcu.org",
    "wof:name":"Tracy Federal Credit Union",
    "wof:placetype":"venue"
},
  "geometry": {"coordinates":[-121.425996,37.737373],"type":"Point"}
}