{
  "type": "Feature",
  "properties": {
    "iso:country":"US",
    "sg:address":"4869 McGrath St",
    "sg:city":"Ventura",
    "sg:classifiers":[
        {
            "category":"Retail",
            "subcategory":"Repair Shop",
            "type":"Services"
        }
    ],
    "sg:phone":"+1 805 658 6394",
    "sg:postcode":"93003",
    "sg:province":"CA",
    "sg:tags":[
        "welding"
    ],
    "wof:name":"Avenue Welding & Support Svc",
    "wof:placetype":"venue"
},
  "geometry": {"coordinates":[-119.225736,34.254608],"type":"Point"}
}