{
  "type": "Feature",
  "properties": {
    "iso:country":"US",
    "sg:address":"2007 Nordic Ave",
    "sg:city":"Chino Hills",
    "sg:classifiers":[
        {
            "category":"Wholesale",
            "subcategory":"Non-durable Goods",
            "type":"Manufacturing & Wholesale Goods"
        }
    ],
    "sg:phone":"+1 909 393 0808",
    "sg:postcode":"91709",
    "sg:province":"CA",
    "wof:name":"Achamak Trading Inc",
    "wof:placetype":"venue"
},
  "geometry": {"coordinates":[-117.75931,33.98599],"type":"Point"}
}