{
  "type": "Feature",
  "properties": {
    "iso:country":"US",
    "sg:address":"4112 Wells St",
    "sg:city":"Pleasanton",
    "sg:classifiers":[
        {
            "category":"Real Estate",
            "subcategory":"Real Estate Agent",
            "type":"Services"
        }
    ],
    "sg:phone":"+1 925 462 5342",
    "sg:postcode":"94566",
    "sg:province":"CA",
    "wof:name":"Francis Coppin",
    "wof:placetype":"venue"
},
  "geometry": {"coordinates":[-121.871799,37.670458],"type":"Point"}
}