{
  "type": "Feature",
  "properties": {
    "iso:country":"US",
    "sg:address":"214 Harder Rd",
    "sg:city":"Hayward",
    "sg:classifiers":[
        {
            "category":"Restaurant",
            "type":"Food & Drink"
        }
    ],
    "sg:phone":"+1 510 582 4008",
    "sg:postcode":"94544",
    "sg:province":"CA",
    "wof:name":"Casa de los Tamales",
    "wof:placetype":"venue"
},
  "geometry": {"coordinates":[-122.075197,37.649921],"type":"Point"}
}