{
  "type": "Feature",
  "properties": {
    "iso:country":"US",
    "sg:address":"2232 Chelmsford Dr",
    "sg:city":"Modesto",
    "sg:classifiers":[
        {
            "category":"Airport",
            "type":"Transportation"
        }
    ],
    "sg:phone":"+1 209 606 9876",
    "sg:postcode":"95356",
    "sg:province":"CA",
    "wof:name":"Magnuson Aviation",
    "wof:placetype":"venue"
},
  "geometry": {"coordinates":[-121.034623,37.691395],"type":"Point"}
}