{
  "type": "Feature",
  "properties": {
    "addr:full":"4025 W Figarden Dr Fresno CA 93722",
    "addr:housenumber":"4025",
    "addr:postcode":"93722",
    "addr:street":"W Figarden Dr",
    "iso:country":"US",
    "sg:address":"4025 W Figarden Dr",
    "sg:city":"Fresno",
    "sg:classifiers":[
        {
            "category":"Personal",
            "subcategory":"Beauty Salon",
            "type":"Services"
        }
    ],
    "sg:phone":"+1 559 261 1366",
    "sg:postcode":"93722",
    "sg:province":"CA",
    "wof:name":"Hair By Gaela Ash",
    "wof:placetype":"venue"
},
  "geometry": {"coordinates":[-119.868179,36.828331],"type":"Point"}
}