{
  "type": "Feature",
  "properties": {
    "iso:country":"US",
    "sg:address":"8063 Balboa Ave",
    "sg:city":"San Diego",
    "sg:classifiers":[
        {
            "category":"Shopping",
            "subcategory":"Bicycles & Sporting Goods",
            "type":"Retail Goods"
        }
    ],
    "sg:phone":"+1 858 560 9599",
    "sg:postcode":"92111",
    "sg:province":"CA",
    "sg:tags":[
        "equipment",
        "exercise"
    ],
    "wof:name":"Busy Body Home Fitness",
    "wof:placetype":"venue"
},
  "geometry": {"coordinates":[-117.154259,32.821687],"type":"Point"}
}