{
  "type": "Feature",
  "properties": {
    "addr:full":"85 Bolinas Rd Fairfax CA 94930",
    "addr:housenumber":"85",
    "addr:postcode":"94930",
    "addr:street":"Bolinas Rd",
    "iso:country":"US",
    "sg:address":"85 Bolinas Rd",
    "sg:city":"Fairfax",
    "sg:classifiers":[
        {
            "category":"Education",
            "subcategory":"School",
            "type":"Public Place"
        }
    ],
    "sg:phone":"+1 415 456 3469",
    "sg:postcode":"94930",
    "sg:province":"CA",
    "wof:name":"Safe Routes To Schools",
    "wof:placetype":"venue"
},
  "geometry": {"coordinates":[-122.589563,37.985846],"type":"Point"}
}