{
  "type": "Feature",
  "properties": {
    "addr:full":"3030 W Olympic Blvd Los Angeles CA 90006",
    "addr:housenumber":"3030",
    "addr:postcode":"90006",
    "addr:street":"W Olympic Blvd",
    "iso:country":"US",
    "sg:address":"3030 W Olympic Blvd",
    "sg:city":"Los Angeles",
    "sg:classifiers":[
        {
            "category":"Health Services",
            "subcategory":"Doctor",
            "type":"Services"
        }
    ],
    "sg:phone":"+1 213 383 2431",
    "sg:postcode":"90006",
    "sg:province":"CA",
    "sg:tags":[
        "physician",
        "surgeon"
    ],
    "wof:name":"Gene S Han Inc",
    "wof:placetype":"venue"
},
  "geometry": {"coordinates":[-118.301908,34.05254],"type":"Point"}
}