{
  "type": "Feature",
  "properties": {
    "addr:full":"19801 Hamilton Ave Torrance CA 90502",
    "addr:housenumber":"19801",
    "addr:postcode":"90502",
    "addr:street":"Hamilton Ave",
    "iso:country":"US",
    "sg:address":"19801 Hamilton Ave",
    "sg:city":"Torrance",
    "sg:classifiers":[
        {
            "category":"Shopping",
            "subcategory":"Clothing, Apparel, & Fashions",
            "type":"Retail Goods"
        }
    ],
    "sg:phone":"+1 310 464 8770",
    "sg:postcode":"90502",
    "sg:province":"CA",
    "sg:tags":[
        "clothing",
        "women's"
    ],
    "wof:name":"Yukiko Inc",
    "wof:placetype":"venue"
},
  "geometry": {"coordinates":[-118.286205,33.850684],"type":"Point"}
}