{
  "type": "Feature",
  "properties": {
    "iso:country":"US",
    "sg:address":"255 N Market St",
    "sg:city":"San Jose",
    "sg:classifiers":[
        {
            "category":"Professional",
            "subcategory":"Lawyer & Legal Services",
            "type":"Services"
        }
    ],
    "sg:phone":"+1 408 291 8686",
    "sg:postcode":"95110",
    "sg:province":"CA",
    "sg:tags":[
        "attorney"
    ],
    "wof:name":"Lucy S Mc Allister Law Offices",
    "wof:placetype":"venue"
},
  "geometry": {"coordinates":[-121.895342,37.339728],"type":"Point"}
}