{
  "type": "Feature",
  "properties": {
    "iso:country":"US",
    "sg:address":"2969 Sloat Rd",
    "sg:city":"Pebble Beach",
    "sg:classifiers":[
        {
            "category":"Professional",
            "subcategory":"Computer Services",
            "type":"Services"
        }
    ],
    "sg:phone":"+1 831 648 9261",
    "sg:postcode":"93953",
    "sg:province":"CA",
    "sg:tags":[
        "internet"
    ],
    "wof:name":"Net Traffic",
    "wof:placetype":"venue"
},
  "geometry": {"coordinates":[-121.944372,36.599463],"type":"Point"}
}