{
  "type": "Feature",
  "properties": {
    "iso:country":"US",
    "sg:address":"1288 Franklin Ave",
    "sg:city":"Yuba City",
    "sg:classifiers":[
        {
            "category":"Utilities",
            "subcategory":"Telephone",
            "type":"Services"
        },
        {
            "category":"Professional",
            "subcategory":"Computer Services",
            "type":"Services"
        }
    ],
    "sg:phone":"+1 530 755 1544",
    "sg:postcode":"95991",
    "sg:province":"CA",
    "sg:tags":[
        "website",
        "development",
        "domain",
        "networking",
        "hp",
        "hosting",
        "internet"
    ],
    "sg:website":"www.clear-cxn.net",
    "wof:name":"Clear Connections",
    "wof:placetype":"venue"
},
  "geometry": {"coordinates":[-121.633955,39.127232],"type":"Point"}
}