{
  "type": "Feature",
  "properties": {
    "addr:full":"401 Civic Center Dr W Santa Ana CA 92701",
    "addr:housenumber":"401",
    "addr:postcode":"92701",
    "addr:street":"Civic Center Dr W",
    "iso:country":"US",
    "sg:address":"401 Civic Center Dr W",
    "sg:city":"Santa Ana",
    "sg:classifiers":[
        {
            "category":"Professional",
            "subcategory":"Lawyer & Legal Services",
            "type":"Services"
        }
    ],
    "sg:phone":"+1 714 835 8499",
    "sg:postcode":"92701",
    "sg:province":"CA",
    "wof:name":"Rolnicki Rolf J Atty",
    "wof:placetype":"venue"
},
  "geometry": {"coordinates":[-117.87200199999999,33.751598],"type":"Point"}
}