{
  "type": "Feature",
  "properties": {
    "addr:full":"4701 24th Street Sacramento CA 95822",
    "addr:housenumber":"4701",
    "addr:postcode":"95822",
    "addr:street":"24Th Street",
    "iso:country":"US",
    "sg:address":"4701 24th Street",
    "sg:city":"Sacramento",
    "sg:classifiers":[
        {
            "category":"Personal",
            "subcategory":"Beauty Salon",
            "type":"Services"
        }
    ],
    "sg:phone":"+1 916 739 8234",
    "sg:postcode":"95822",
    "sg:province":"CA",
    "sg:tags":[
        "hair"
    ],
    "wof:name":"C and C Hair Studio",
    "wof:placetype":"venue"
},
  "geometry": {"coordinates":[-121.483194,38.532242],"type":"Point"}
}