{
  "type": "Feature",
  "properties": {
    "addr:full":"1814 Redwood Hwy Corte Madera CA 94925",
    "addr:housenumber":"1814",
    "addr:postcode":"94925",
    "addr:street":"Redwood Hwy",
    "iso:country":"US",
    "sg:address":"1814 Redwood Hwy",
    "sg:city":"Corte Madera",
    "sg:classifiers":[
        {
            "category":"Shopping",
            "subcategory":"Shoes",
            "type":"Retail Goods"
        }
    ],
    "sg:phone":"+1 415 924 5877",
    "sg:postcode":"94925",
    "sg:province":"CA",
    "wof:name":"Foot Locker",
    "wof:placetype":"venue"
},
  "geometry": {"coordinates":[-122.51596499999999,37.932744],"type":"Point"}
}