{
  "type": "Feature",
  "properties": {
    "iso:country":"US",
    "sg:address":"2079 Garnet Ave",
    "sg:city":"San Diego",
    "sg:classifiers":[
        {
            "category":"Personal",
            "subcategory":"Piercing",
            "type":"Services"
        }
    ],
    "sg:phone":"+1 858 274 9950",
    "sg:postcode":"92109",
    "sg:province":"CA",
    "sg:website":"www.enigmapropiercing.com",
    "wof:name":"Enigma Professional Piercing Studio",
    "wof:placetype":"venue"
},
  "geometry": {"coordinates":[-117.231792,32.801516],"type":"Point"}
}