{
  "type": "Feature",
  "properties": {
    "iso:country":"US",
    "sg:address":"13242 Pomerado Rd",
    "sg:city":"Poway",
    "sg:classifiers":[
        {
            "category":"Social Services",
            "subcategory":"Child Care",
            "type":"Services"
        },
        {
            "category":"Education",
            "subcategory":"Preschool",
            "type":"Public Place"
        },
        {
            "category":"Education",
            "subcategory":"School",
            "type":"Public Place"
        }
    ],
    "sg:phone":"+1 858 679 1554",
    "sg:postcode":"92064",
    "sg:province":"CA",
    "sg:tags":[
        "kindergarten",
        "nursery",
        "k-",
        "private",
        "day"
    ],
    "wof:name":"Growing Place Montessori Inc",
    "wof:placetype":"venue"
},
  "geometry": {"coordinates":[-117.062476,32.956049],"type":"Point"}
}