{
  "type": "Feature",
  "properties": {
    "addr:full":"377 Laurelwood Rd Santa Clara CA 95054",
    "addr:housenumber":"377",
    "addr:postcode":"95054",
    "addr:street":"Laurelwood Rd",
    "iso:country":"US",
    "sg:address":"377 Laurelwood Rd",
    "sg:city":"Santa Clara",
    "sg:classifiers":[
        {
            "category":"Manufacturing",
            "subcategory":"Signs",
            "type":"Manufacturing & Wholesale Goods"
        }
    ],
    "sg:phone":"+1 408 727 9902",
    "sg:postcode":"95054",
    "sg:province":"CA",
    "sg:tags":[
        "specialty",
        "mfg"
    ],
    "wof:name":"Magic Signs",
    "wof:placetype":"venue"
},
  "geometry": {"coordinates":[-121.94088000000001,37.382254],"type":"Point"}
}