{
  "type": "Feature",
  "properties": {
    "addr:full":"28 N 1st St San Jose CA 95112",
    "addr:housenumber":"28",
    "addr:postcode":"95112",
    "addr:street":"N 1St St",
    "iso:country":"US",
    "sg:address":"28 N 1st St",
    "sg:city":"San Jose",
    "sg:classifiers":[
        {
            "category":"Shopping",
            "subcategory":"Computers & Home Electronics",
            "type":"Retail Goods"
        }
    ],
    "sg:phone":"+1 408 995 0360",
    "sg:postcode":"95112",
    "sg:province":"CA",
    "sg:tags":[
        "software"
    ],
    "wof:name":"Pantone",
    "wof:placetype":"venue"
},
  "geometry": {"coordinates":[-121.891323,37.337292],"type":"Point"}
}