{
  "type": "Feature",
  "properties": {
    "addr:full":"204 Bay St San Francisco CA 94133",
    "addr:housenumber":"204",
    "addr:postcode":"94133",
    "addr:street":"Bay St",
    "iso:country":"US",
    "sg:address":"204 Bay St",
    "sg:city":"San Francisco",
    "sg:classifiers":[
        {
            "category":"Ferry",
            "type":"Transportation"
        }
    ],
    "sg:phone":"+1 415 474 7662",
    "sg:postcode":"94133",
    "sg:province":"CA",
    "sg:tags":[
        "river",
        "trip"
    ],
    "wof:name":"Environmental Traveling Cmpns",
    "wof:placetype":"venue"
},
  "geometry": {"coordinates":[-122.411908,37.805907],"type":"Point"}
}