{
  "type": "Feature",
  "properties": {
    "addr:full":"3333 M St Merced CA 95348",
    "addr:housenumber":"3333",
    "addr:postcode":"95348",
    "addr:street":"M St",
    "iso:country":"US",
    "sg:address":"3333 M St",
    "sg:city":"Merced",
    "sg:classifiers":[
        {
            "category":"Government",
            "subcategory":"Police Station",
            "type":"Public Place"
        }
    ],
    "sg:phone":"+1 209 726 6501",
    "sg:postcode":"95348",
    "sg:province":"CA",
    "sg:tags":[
        "department"
    ],
    "wof:name":"Police Department-Narcotics",
    "wof:placetype":"venue"
},
  "geometry": {"coordinates":[-120.47842799999999,37.323644],"type":"Point"}
}