{
  "type": "Feature",
  "properties": {
    "addr:full":"1114 C St Sacramento CA 95814",
    "addr:housenumber":"1114",
    "addr:postcode":"95814",
    "addr:street":"C St",
    "iso:country":"US",
    "sg:address":"1114 C St",
    "sg:city":"Sacramento",
    "sg:classifiers":[
        {
            "category":"Food & Beverages",
            "subcategory":"Dairy",
            "type":"Retail Goods"
        }
    ],
    "sg:phone":"+1 916 489 0480",
    "sg:postcode":"95814",
    "sg:province":"CA",
    "sg:tags":[
        "products-wholesale"
    ],
    "wof:name":"Glen Wills Distribution",
    "wof:placetype":"venue"
},
  "geometry": {"coordinates":[-121.488617,38.587557],"type":"Point"}
}