{
  "type": "Feature",
  "properties": {
    "addr:full":"17739 Grand Ave Lake Elsinore CA 92530",
    "addr:housenumber":"17739",
    "addr:postcode":"92530",
    "addr:street":"Grand Ave",
    "iso:country":"US",
    "sg:address":"17739 Grand Ave",
    "sg:city":"Lake Elsinore",
    "sg:classifiers":[
        {
            "category":"Shopping",
            "subcategory":"Used Merchandise",
            "type":"Retail Goods"
        }
    ],
    "sg:phone":"+1 951 678 1405",
    "sg:postcode":"92530",
    "sg:province":"CA",
    "sg:tags":[
        "vintage",
        "consignment"
    ],
    "sg:website":"www.theclassycloset.com",
    "wof:name":"The Classy Closet",
    "wof:placetype":"venue"
},
  "geometry": {"coordinates":[-117.342018,33.637174],"type":"Point"}
}