{
  "type": "Feature",
  "properties": {
    "iso:country":"US",
    "sg:address":"23783 Eichler St",
    "sg:city":"Hayward",
    "sg:classifiers":[
        {
            "category":"Wholesale",
            "subcategory":"Auto Parts",
            "type":"Manufacturing & Wholesale Goods"
        }
    ],
    "sg:phone":"+1 510 785 8696",
    "sg:postcode":"94545",
    "sg:province":"CA",
    "sg:tags":[
        "automobile",
        "supply"
    ],
    "wof:name":"Transworld Service",
    "wof:placetype":"venue"
},
  "geometry": {"coordinates":[-122.126881,37.641358],"type":"Point"}
}