{
  "type": "Feature",
  "properties": {
    "addr:full":"12170 Herdal Dr Auburn CA 95603",
    "addr:postcode":"12170;ca 95603",
    "addr:street":"Herdal Dr",
    "iso:country":"US",
    "sg:address":"12170 Herdal Dr",
    "sg:city":"Auburn",
    "sg:classifiers":[
        {
            "category":"Professional",
            "subcategory":"Accounting & Tax Preparation",
            "type":"Services"
        }
    ],
    "sg:phone":"+1 530 887 5400",
    "sg:postcode":"95603",
    "sg:province":"CA",
    "sg:tags":[
        "return"
    ],
    "wof:name":"Casto Richard",
    "wof:placetype":"venue"
},
  "geometry": {"coordinates":[-121.08105399999999,38.878508],"type":"Point"}
}