{
  "type": "Feature",
  "properties": {
    "addr:full":"16723 W Floral Ave Burrel CA 93656",
    "addr:housenumber":"16723",
    "addr:postcode":"93656",
    "addr:street":"W Floral Ave",
    "iso:country":"US",
    "sg:address":"16723 W Floral Ave",
    "sg:city":"Burrel",
    "sg:classifiers":[
        {
            "category":"Wholesale",
            "subcategory":"Groceries",
            "type":"Manufacturing & Wholesale Goods"
        }
    ],
    "sg:phone":"+1 559 866 5647",
    "sg:postcode":"93656",
    "sg:province":"CA",
    "wof:name":"Terranova Ranch",
    "wof:placetype":"venue"
},
  "geometry": {"coordinates":[-120.087129,36.574397],"type":"Point"}
}