{
  "type": "Feature",
  "properties": {
    "addr:full":"2400 Kettner Blvd San Diego CA 92101",
    "addr:housenumber":"2400",
    "addr:postcode":"92101",
    "addr:street":"Kettner Blvd",
    "iso:country":"US",
    "sg:address":"2400 Kettner Blvd",
    "sg:city":"San Diego",
    "sg:classifiers":[
        {
            "category":"Autos & Motor Vehicles",
            "subcategory":"Motorcycle Sales",
            "type":"Retail Goods"
        }
    ],
    "sg:phone":"+1 619 233 6677",
    "sg:postcode":"92101",
    "sg:province":"CA",
    "sg:tags":[
        "scooter"
    ],
    "wof:name":"Buell American Motorcycles",
    "wof:placetype":"venue"
},
  "geometry": {"coordinates":[-117.171976,32.730041],"type":"Point"}
}