{
  "type": "Feature",
  "properties": {
    "iso:country":"US",
    "sg:address":"713 N Avon St",
    "sg:city":"Burbank",
    "sg:classifiers":[
        {
            "category":"Professional",
            "subcategory":"Art Services",
            "type":"Services"
        }
    ],
    "sg:phone":"+1 818 843 7771",
    "sg:postcode":"91505",
    "sg:province":"CA",
    "sg:tags":[
        "commercial",
        "design"
    ],
    "wof:name":"Razdezignz",
    "wof:placetype":"venue"
},
  "geometry": {"coordinates":[-118.342298,34.163348],"type":"Point"}
}