{
  "type": "Feature",
  "properties": {
    "iso:country":"US",
    "sg:address":"1906 W Holt Ave",
    "sg:city":"Pomona",
    "sg:classifiers":[
        {
            "category":"Wholesale",
            "subcategory":"Drugs",
            "type":"Manufacturing & Wholesale Goods"
        },
        {
            "category":"Manufacturing",
            "subcategory":"Food",
            "type":"Manufacturing & Wholesale Goods"
        }
    ],
    "sg:phone":"+1 909 623 4565",
    "sg:postcode":"91768",
    "sg:province":"CA",
    "sg:tags":[
        "grocery",
        "health",
        "product"
    ],
    "wof:name":"Essential Pharmaceutical Corp",
    "wof:placetype":"venue"
},
  "geometry": {"coordinates":[-117.786057,34.06141],"type":"Point"}
}