{
  "type": "Feature",
  "properties": {
    "iso:country":"US",
    "sg:address":"10967 Weyburn Ave",
    "sg:city":"Los Angeles",
    "sg:classifiers":[
        {
            "category":"Personal",
            "subcategory":"Massage",
            "type":"Services"
        },
        {
            "category":"Personal",
            "subcategory":"Skin Care",
            "type":"Services"
        }
    ],
    "sg:phone":"+1 310 443 2150",
    "sg:postcode":"90024",
    "sg:province":"CA",
    "wof:name":"Village Nails",
    "wof:placetype":"venue"
},
  "geometry": {"coordinates":[-118.425686,34.066899],"type":"Point"}
}