{
  "type": "Feature",
  "properties": {
    "iso:country":"US",
    "sg:address":"6320 Clara St",
    "sg:city":"Bell Gardens",
    "sg:classifiers":[
        {
            "category":"Building & Trades",
            "subcategory":"Construction",
            "type":"Services"
        }
    ],
    "sg:phone":"+1 562 928 1200",
    "sg:postcode":"90201",
    "sg:province":"CA",
    "sg:tags":[
        "roofing",
        "contractor"
    ],
    "wof:name":"Royal Roofing",
    "wof:placetype":"venue"
},
  "geometry": {"coordinates":[-118.153745,33.961889],"type":"Point"}
}