{
  "type": "Feature",
  "properties": {
    "addr:full":"5754 Geary Blvd San Francisco CA 94121",
    "addr:housenumber":"5754",
    "addr:postcode":"94121",
    "addr:street":"Geary Blvd",
    "iso:country":"US",
    "sg:address":"5754 Geary Blvd",
    "sg:city":"San Francisco",
    "sg:classifiers":[
        {
            "category":"Retail",
            "subcategory":"Laundry & Dry Cleaning",
            "type":"Services"
        }
    ],
    "sg:phone":"+1 415 668 1175",
    "sg:postcode":"94121",
    "sg:province":"CA",
    "sg:tags":[
        "curtain",
        "drapery",
        "cleaners"
    ],
    "wof:name":"Qualitech Cleaners",
    "wof:placetype":"venue"
},
  "geometry": {"coordinates":[-122.481032,37.780406],"type":"Point"}
}