{
  "type": "Feature",
  "properties": {
    "iso:country":"US",
    "sg:address":"2780 Tapo Canyon Rd",
    "sg:city":"Simi Valley",
    "sg:classifiers":[
        {
            "category":"Shopping",
            "type":"Retail Goods"
        }
    ],
    "sg:phone":"+1 805 306 0744",
    "sg:postcode":"93063",
    "sg:province":"CA",
    "sg:tags":[
        "telephone",
        "cellular"
    ],
    "wof:name":"H & H Wireless",
    "wof:placetype":"venue"
},
  "geometry": {"coordinates":[-118.71767,34.284784],"type":"Point"}
}