{
  "type": "Feature",
  "properties": {
    "iso:country":"US",
    "sg:address":"206 E Victoria St",
    "sg:city":"Santa Barbara",
    "sg:classifiers":[
        {
            "category":"Insurance",
            "subcategory":"Insurance Agent",
            "type":"Services"
        }
    ],
    "sg:phone":"+1 805 568 1188",
    "sg:postcode":"93101",
    "sg:province":"CA",
    "wof:name":"Friedlander & Assoc Insurance",
    "wof:placetype":"venue"
},
  "geometry": {"coordinates":[-119.702349,34.427343],"type":"Point"}
}