{
  "type": "Feature",
  "properties": {
    "addr:full":"2625 W Alameda Ave Suite 116 Burbank CA 91505",
    "addr:housenumber":"2625",
    "addr:postcode":"91505",
    "addr:street":"W Alameda Ave Suite 116",
    "iso:country":"US",
    "sg:address":"2625 W Alameda Ave Suite 116",
    "sg:city":"Burbank",
    "sg:classifiers":[
        {
            "category":"Health Services",
            "subcategory":"Doctor",
            "type":"Services"
        }
    ],
    "sg:phone":"+1 818 481 3936",
    "sg:postcode":"91505",
    "sg:province":"CA",
    "sg:tags":[
        "orthopedist"
    ],
    "sg:website":"www.ossburbank.com",
    "wof:name":"Orthopaedic Surgery Specialists",
    "wof:placetype":"venue"
},
  "geometry": {"coordinates":[-118.329911,34.15795],"type":"Point"}
}