{
  "type": "Feature",
  "properties": {
    "addr:full":"321 S Myrtle Ave Monrovia CA 91016",
    "addr:housenumber":"321",
    "addr:postcode":"91016",
    "addr:street":"S Myrtle Ave",
    "iso:country":"US",
    "sg:address":"321 S Myrtle Ave",
    "sg:city":"Monrovia",
    "sg:classifiers":[
        {
            "category":"Education",
            "subcategory":"Library",
            "type":"Public Place"
        }
    ],
    "sg:phone":"+1 626 256 8274",
    "sg:postcode":"91016",
    "sg:province":"CA",
    "sg:tags":[
        "executive"
    ],
    "wof:name":"Monrovia Public Library",
    "wof:placetype":"venue"
},
  "geometry": {"coordinates":[-118.001097,34.148289],"type":"Point"}
}