{
  "type": "Feature",
  "properties": {
    "addr:full":"1604 Lindbergh Dr Concord CA 94521",
    "addr:housenumber":"1604",
    "addr:postcode":"94521",
    "addr:street":"Lindbergh Dr",
    "iso:country":"US",
    "sg:address":"1604 Lindbergh Dr",
    "sg:city":"Concord",
    "sg:classifiers":[
        {
            "category":"Education",
            "subcategory":"Special Training",
            "type":"Public Place"
        }
    ],
    "sg:phone":"+1 925 798 7464",
    "sg:postcode":"94521",
    "sg:province":"CA",
    "sg:tags":[
        "instruction",
        "music"
    ],
    "wof:name":"Dahlia's Rising Stars",
    "wof:placetype":"venue"
},
  "geometry": {"coordinates":[-121.99603999999999,37.972219],"type":"Point"}
}