{
  "type": "Feature",
  "properties": {
    "addr:full":"2345 S. Santa Fe Ave. Los Angeles CA 90058",
    "addr:housenumber":"2345",
    "addr:postcode":"90058",
    "addr:street":"S. Santa Fe Ave.",
    "iso:country":"US",
    "sg:address":"2345 S. Santa Fe Ave.",
    "sg:city":"Los Angeles",
    "sg:classifiers":[
        {
            "category":"Personal",
            "type":"Services"
        }
    ],
    "sg:phone":"+1 888 244 4449",
    "sg:postcode":"90058",
    "sg:province":"CA",
    "sg:tags":[
        "mover"
    ],
    "wof:name":"Hercules Moving Systems",
    "wof:placetype":"venue"
},
  "geometry": {"coordinates":[-118.23140100000001,34.015868],"type":"Point"}
}