{
  "type": "Feature",
  "properties": {
    "addr:full":"6909 Sacramento Dr Redding CA 96001",
    "addr:housenumber":"6909",
    "addr:postcode":"96001",
    "addr:street":"Sacramento Dr",
    "iso:country":"US",
    "sg:address":"6909 Sacramento Dr",
    "sg:city":"Redding",
    "sg:classifiers":[
        {
            "category":"Travel",
            "subcategory":"Travel Agent",
            "type":"Entertainment"
        }
    ],
    "sg:phone":"+1 530 243 8685",
    "sg:postcode":"96001",
    "sg:province":"CA",
    "wof:name":"Palmer Travel",
    "wof:placetype":"venue"
},
  "geometry": {"coordinates":[-122.363343,40.515898],"type":"Point"}
}