{
  "type": "Feature",
  "properties": {
    "iso:country":"US",
    "sg:address":"12000 Stadium Rd",
    "sg:city":"Adelanto",
    "sg:classifiers":[
        {
            "category":"Professional",
            "type":"Services"
        }
    ],
    "sg:phone":"+1 760 246 0686",
    "sg:postcode":"92301",
    "sg:province":"CA",
    "wof:name":"La Mesa Rv",
    "wof:placetype":"venue"
},
  "geometry": {"coordinates":[-117.40081499999999,34.555861],"type":"Point"}
}