{
  "type": "Feature",
  "properties": {
    "iso:country":"US",
    "sg:address":"1150 N Hellman Ave",
    "sg:city":"Ontario",
    "sg:classifiers":[
        {
            "category":"Retail",
            "subcategory":"Repair Shop",
            "type":"Services"
        }
    ],
    "sg:phone":"+1 909 484 8259",
    "sg:postcode":"91764",
    "sg:province":"CA",
    "sg:tags":[
        "equipment",
        "hydraulic"
    ],
    "wof:name":"TNT Aerial & Crane Repair",
    "wof:placetype":"venue"
},
  "geometry": {"coordinates":[-117.602141,34.078515],"type":"Point"}
}