{
  "type": "Feature",
  "properties": {
    "addr:full":"3627 W McKinley Ave Fresno CA 93722",
    "addr:housenumber":"3627",
    "addr:postcode":"93722",
    "addr:street":"W Mckinley Ave",
    "iso:country":"US",
    "sg:address":"3627 W McKinley Ave",
    "sg:city":"Fresno",
    "sg:classifiers":[
        {
            "category":"Building & Trades",
            "subcategory":"Landscaping Services",
            "type":"Services"
        }
    ],
    "sg:phone":"+1 559 277 9050",
    "sg:postcode":"93722",
    "sg:province":"CA",
    "wof:name":"Horns Tree Service",
    "wof:placetype":"venue"
},
  "geometry": {"coordinates":[-119.859678,36.764559],"type":"Point"}
}