{
  "type": "Feature",
  "properties": {
    "iso:country":"US",
    "sg:address":"345 S Alexandria Ave",
    "sg:city":"Los Angeles",
    "sg:classifiers":[
        {
            "category":"Freight",
            "type":"Transportation"
        }
    ],
    "sg:phone":"+1 213 388 8282",
    "sg:postcode":"90020",
    "sg:province":"CA",
    "sg:tags":[
        "courier"
    ],
    "wof:name":"J J Total Svc",
    "wof:placetype":"venue"
},
  "geometry": {"coordinates":[-118.298013,34.068026],"type":"Point"}
}