{
  "type": "Feature",
  "properties": {
    "addr:full":"3501 San Pablo Ave Ofc Emeryville CA 94608",
    "addr:housenumber":"3501",
    "addr:postcode":"94608",
    "addr:street":"San Pablo Ave",
    "iso:country":"US",
    "sg:address":"3501 San Pablo Ave Ofc",
    "sg:city":"Emeryville",
    "sg:classifiers":[
        {
            "category":"Personal",
            "subcategory":"Massage",
            "type":"Services"
        }
    ],
    "sg:phone":"+1 510 653 8466",
    "sg:postcode":"94608",
    "sg:province":"CA",
    "wof:name":"One Touch Body and Soul",
    "wof:placetype":"venue"
},
  "geometry": {"coordinates":[-122.278999,37.826401],"type":"Point"}
}