{
  "type": "Feature",
  "properties": {
    "iso:country":"US",
    "sg:address":"7433 Hollister Ave",
    "sg:city":"Goleta",
    "sg:classifiers":[
        {
            "category":"Professional",
            "type":"Services"
        }
    ],
    "sg:phone":"+1 805 685 2333",
    "sg:postcode":"93117",
    "sg:province":"CA",
    "wof:name":"Notidiario",
    "wof:placetype":"venue"
},
  "geometry": {"coordinates":[-119.88725599999999,34.429712],"type":"Point"}
}