{
  "type": "Feature",
  "properties": {
    "addr:full":"250 California St Santa Cruz CA 95060",
    "addr:housenumber":"250",
    "addr:postcode":"95060",
    "addr:street":"California St",
    "iso:country":"US",
    "sg:address":"250 California St",
    "sg:city":"Santa Cruz",
    "sg:classifiers":[
        {
            "category":"Education",
            "subcategory":"School",
            "type":"Public Place"
        }
    ],
    "sg:phone":"+1 831 427 2641",
    "sg:postcode":"95060",
    "sg:province":"CA",
    "sg:tags":[
        "elementary"
    ],
    "sg:website":"www.springhillschool.org",
    "wof:name":"Spring Hill",
    "wof:placetype":"venue"
},
  "geometry": {"coordinates":[-122.034544,36.965542],"type":"Point"}
}