{
  "type": "Feature",
  "properties": {
    "addr:full":"9347 Venice Blvd Culver City CA 90232",
    "addr:housenumber":"9347",
    "addr:postcode":"90232",
    "addr:street":"Venice Blvd",
    "iso:country":"US",
    "sg:address":"9347 Venice Blvd",
    "sg:city":"Culver City",
    "sg:classifiers":[
        {
            "category":"Real Estate",
            "subcategory":"Real Estate Agent",
            "type":"Services"
        }
    ],
    "sg:phone":"+1 310 838 4822",
    "sg:postcode":"90232",
    "sg:province":"CA",
    "wof:name":"Coast Realty",
    "wof:placetype":"venue"
},
  "geometry": {"coordinates":[-118.394865,34.025906],"type":"Point"}
}