{
  "type": "Feature",
  "properties": {
    "iso:country":"US",
    "sg:address":"3938 Wilshire Blvd",
    "sg:city":"Los Angeles",
    "sg:classifiers":[
        {
            "category":"Building & Trades",
            "subcategory":"Cleaning & Sanitation",
            "type":"Services"
        }
    ],
    "sg:phone":"+1 213 383 1098",
    "sg:postcode":"90010",
    "sg:province":"CA",
    "sg:tags":[
        "janitor"
    ],
    "wof:name":"Wilshire Commercial",
    "wof:placetype":"venue"
},
  "geometry": {"coordinates":[-118.311379,34.061618],"type":"Point"}
}