{
  "type": "Feature",
  "properties": {
    "iso:country":"US",
    "sg:address":"460 Main St",
    "sg:city":"Ferndale",
    "sg:classifiers":[
        {
            "category":"Restaurant",
            "type":"Food & Drink"
        }
    ],
    "sg:phone":"+1 707 786 4648",
    "sg:postcode":"95536",
    "sg:province":"CA",
    "wof:name":"Restaurant Matias",
    "wof:placetype":"venue"
},
  "geometry": {"coordinates":[-124.263283,40.576625],"type":"Point"}
}