{
  "type": "Feature",
  "properties": {
    "iso:country":"US",
    "sg:address":"1210 S Western Ave",
    "sg:city":"Los Angeles",
    "sg:classifiers":[
        {
            "category":"Travel",
            "subcategory":"Travel Agent",
            "type":"Entertainment"
        }
    ],
    "sg:phone":"+1 323 731 9963",
    "sg:postcode":"90006",
    "sg:province":"CA",
    "sg:tags":[
        "agency",
        "bureau"
    ],
    "wof:name":"Cana Travel",
    "wof:placetype":"venue"
},
  "geometry": {"coordinates":[-118.308963,34.048327],"type":"Point"}
}