{
  "type": "Feature",
  "properties": {
    "iso:country":"US",
    "sg:address":"7557 el Cajon Blvd",
    "sg:city":"La Mesa",
    "sg:classifiers":[
        {
            "category":"Health Services",
            "subcategory":"Doctor",
            "type":"Services"
        }
    ],
    "sg:phone":"+1 619 466 2774",
    "sg:postcode":"91941",
    "sg:province":"CA",
    "sg:tags":[
        "dentist"
    ],
    "wof:name":"TMJ Therapy Ctr",
    "wof:placetype":"venue"
},
  "geometry": {"coordinates":[-117.034062,32.768123],"type":"Point"}
}