{
  "type": "Feature",
  "properties": {
    "iso:country":"US",
    "sg:address":"16689 Foothill Blvd",
    "sg:city":"Fontana",
    "sg:classifiers":[
        {
            "category":"Professional",
            "subcategory":"Management & Consulting",
            "type":"Services"
        }
    ],
    "sg:phone":"+1 909 427 1988",
    "sg:postcode":"92335",
    "sg:province":"CA",
    "sg:tags":[
        "consultant",
        "business"
    ],
    "wof:name":"Mariposa Management Co",
    "wof:placetype":"venue"
},
  "geometry": {"coordinates":[-117.440914,34.106523],"type":"Point"}
}