{
  "type": "Feature",
  "properties": {
    "addr:full":"815 Hamilton St Redwood City CA 94063",
    "addr:housenumber":"815",
    "addr:postcode":"94063",
    "addr:street":"Hamilton St",
    "iso:country":"US",
    "sg:address":"815 Hamilton St",
    "sg:city":"Redwood City",
    "sg:classifiers":[
        {
            "category":"Real Estate",
            "subcategory":"Architect",
            "type":"Services"
        }
    ],
    "sg:phone":"+1 650 298 8150",
    "sg:postcode":"94063",
    "sg:province":"CA",
    "sg:website":"www.watrydesign.com",
    "wof:name":"Watry Design Group",
    "wof:placetype":"venue"
},
  "geometry": {"coordinates":[-122.22996000000001,37.485607],"type":"Point"}
}