{
  "type": "Feature",
  "properties": {
    "iso:country":"US",
    "sg:address":"8740 Calvine Rd",
    "sg:city":"Sacramento",
    "sg:classifiers":[
        {
            "category":"Retail",
            "subcategory":"Storage",
            "type":"Services"
        }
    ],
    "sg:phone":"+1 866 414 0641",
    "sg:postcode":"95828",
    "sg:province":"CA",
    "sg:tags":[
        "self",
        "commercial",
        "household"
    ],
    "sg:website":"http://Calvine-sac-yp.ndmr.com",
    "wof:name":"Calvine StorageKings",
    "wof:placetype":"venue"
},
  "geometry": {"coordinates":[-121.378387,38.45253],"type":"Point"}
}