{
  "type": "Feature",
  "properties": {
    "addr:full":"3380 N Harbor Dr San Diego CA 92101",
    "addr:housenumber":"3380",
    "addr:postcode":"92101",
    "addr:street":"N Harbor Dr",
    "iso:country":"US",
    "sg:address":"3380 N Harbor Dr",
    "sg:city":"San Diego",
    "sg:classifiers":[
        {
            "category":"Government",
            "subcategory":"City Hall",
            "type":"Public Place"
        }
    ],
    "sg:phone":"+1 619 686 6570",
    "sg:postcode":"92101",
    "sg:province":"CA",
    "sg:website":"www.portofsandiego.org/harbor-po...",
    "wof:name":"Unified Port of San Diego Harbor Police",
    "wof:placetype":"venue"
},
  "geometry": {"coordinates":[-117.19548,32.727174],"type":"Point"}
}