{
  "type": "Feature",
  "properties": {
    "iso:country":"US",
    "sg:address":"1061 Serpentine Ln",
    "sg:city":"Pleasanton",
    "sg:classifiers":[
        {
            "category":"Retail",
            "subcategory":"Portrait Studio",
            "type":"Services"
        }
    ],
    "sg:phone":"+1 925 462 7754",
    "sg:postcode":"94566",
    "sg:province":"CA",
    "sg:tags":[
        "photographer"
    ],
    "wof:name":"Designer Portraiture By Kevin",
    "wof:placetype":"venue"
},
  "geometry": {"coordinates":[-121.86755,37.672908],"type":"Point"}
}