{
  "type": "Feature",
  "properties": {
    "addr:full":"521 Monterey St Hollister CA 95023",
    "addr:housenumber":"521",
    "addr:postcode":"hollister ca 95023",
    "addr:street":"Monterey St",
    "iso:country":"US",
    "sg:address":"521 Monterey St",
    "sg:city":"Hollister",
    "sg:classifiers":[
        {
            "category":"Organizations",
            "subcategory":"Religious Organization",
            "type":"Services"
        }
    ],
    "sg:phone":"+1 831 637 4240",
    "sg:postcode":"95023",
    "sg:province":"CA",
    "sg:tags":[
        "churches-united",
        "methodist",
        "church"
    ],
    "wof:name":"Hollister United Methodist Church",
    "wof:placetype":"venue"
},
  "geometry": {"coordinates":[-121.403856,36.851166],"type":"Point"}
}