{
  "type": "Feature",
  "properties": {
    "addr:full":"1137 Village Way Sebastopol CA 95472",
    "addr:housenumber":"1137",
    "addr:postcode":"95472",
    "addr:street":"Village Way",
    "iso:country":"US",
    "sg:address":"1137 Village Way",
    "sg:city":"Sebastopol",
    "sg:classifiers":[
        {
            "category":"Building & Trades",
            "subcategory":"Electrical",
            "type":"Services"
        }
    ],
    "sg:phone":"+1 707 829 3662",
    "sg:postcode":"95472",
    "sg:province":"CA",
    "sg:tags":[
        "industrial",
        "electrician",
        "contractors-commercial",
        "electric"
    ],
    "wof:name":"Houston Elec Telecomm Inc",
    "wof:placetype":"venue"
},
  "geometry": {"coordinates":[-122.8133,38.388408],"type":"Point"}
}