{
  "type": "Feature",
  "properties": {
    "addr:full":"294 Fox Hills Mall Culver City CA 90230",
    "addr:housenumber":"294",
    "addr:postcode":"90230",
    "addr:street":"Fox Hills Mall",
    "iso:country":"US",
    "sg:address":"294 Fox Hills Mall",
    "sg:city":"Culver City",
    "sg:classifiers":[
        {
            "category":"Manufacturing",
            "subcategory":"Signs",
            "type":"Manufacturing & Wholesale Goods"
        }
    ],
    "sg:phone":"+1 310 572 9199",
    "sg:postcode":"90230",
    "sg:province":"CA",
    "wof:name":"A & N Auto Trends",
    "wof:placetype":"venue"
},
  "geometry": {"coordinates":[-118.39078000000001,33.985841],"type":"Point"}
}