{
  "type": "Feature",
  "properties": {
    "iso:country":"US",
    "sg:address":"417 27th Ave",
    "sg:city":"San Mateo",
    "sg:classifiers":[
        {
            "category":"Professional",
            "type":"Services"
        }
    ],
    "sg:phone":"+1 650 577 1004",
    "sg:postcode":"94403",
    "sg:province":"CA",
    "sg:tags":[
        "establishment"
    ],
    "wof:name":"Giant Stride Marketing Group",
    "wof:placetype":"venue"
},
  "geometry": {"coordinates":[-122.312403,37.53874],"type":"Point"}
}