{
  "type": "Feature",
  "properties": {
    "addr:full":"7143 Katella Ave Stanton CA 90680",
    "addr:housenumber":"7143",
    "addr:postcode":"ca 90680",
    "addr:street":"Katella Ave",
    "iso:country":"US",
    "sg:address":"7143 Katella Ave",
    "sg:city":"Stanton",
    "sg:classifiers":[
        {
            "category":"Arena",
            "subcategory":"Sports Club",
            "type":"Entertainment"
        }
    ],
    "sg:phone":"+1 714 229 0613",
    "sg:postcode":"90680",
    "sg:province":"CA",
    "sg:tags":[
        "martial art"
    ],
    "wof:name":"Full Contact Tae Kwon Do",
    "wof:placetype":"venue"
},
  "geometry": {"coordinates":[-118.06434,33.803055],"type":"Point"}
}