{
  "type": "Feature",
  "properties": {
    "iso:country":"US",
    "sg:address":"10613 Owensmouth Ave",
    "sg:city":"Chatsworth",
    "sg:classifiers":[
        {
            "category":"Shopping",
            "subcategory":"Clothing, Apparel, & Fashions",
            "type":"Retail Goods"
        }
    ],
    "sg:phone":"+1 818 576 9875",
    "sg:postcode":"91311",
    "sg:province":"CA",
    "wof:name":"Fashion Textile Inc",
    "wof:placetype":"venue"
},
  "geometry": {"coordinates":[-118.601761,34.261276],"type":"Point"}
}