{
  "type": "Feature",
  "properties": {
    "addr:full":"551 Whiting St Grass Valley CA 95945",
    "addr:housenumber":"551",
    "addr:postcode":"95945",
    "addr:street":"Whiting St",
    "iso:country":"US",
    "sg:address":"551 Whiting St",
    "sg:city":"Grass Valley",
    "sg:classifiers":[
        {
            "category":"Organizations",
            "subcategory":"Non-profit Organization",
            "type":"Services"
        }
    ],
    "sg:phone":"+1 530 273 8132",
    "sg:postcode":"95945",
    "sg:province":"CA",
    "wof:name":"Interfaith Food Ministry",
    "wof:placetype":"venue"
},
  "geometry": {"coordinates":[-121.06589,39.208511],"type":"Point"}
}