{
  "type": "Feature",
  "properties": {
    "addr:full":"2180 Jefferson St Napa CA 94559",
    "addr:housenumber":"2180",
    "addr:postcode":"94559",
    "addr:street":"Jefferson St",
    "iso:country":"US",
    "sg:address":"2180 Jefferson St",
    "sg:city":"Napa",
    "sg:classifiers":[
        {
            "category":"Health Services",
            "subcategory":"Doctor",
            "type":"Services"
        },
        {
            "category":"Health Services",
            "subcategory":"Clinic",
            "type":"Services"
        },
        {
            "category":"Social Services",
            "type":"Services"
        }
    ],
    "sg:phone":"+1 707 252 7811",
    "sg:postcode":"94559",
    "sg:province":"CA",
    "sg:tags":[
        "psychological",
        "psychologist",
        "therapist",
        "marriage",
        "family"
    ],
    "wof:name":"Gregory Matsumoto Psyd",
    "wof:placetype":"venue"
},
  "geometry": {"coordinates":[-122.295277,38.306883],"type":"Point"}
}