{
  "type": "Feature",
  "properties": {
    "addr:full":"10940 Wilshire Boulevard Los Angeles CA 90024",
    "addr:housenumber":"10940",
    "addr:postcode":"90024",
    "addr:street":"Wilshire Boulevard",
    "iso:country":"US",
    "sg:address":"10940 Wilshire Boulevard",
    "sg:city":"Los Angeles",
    "sg:classifiers":[
        {
            "category":"Banks & Credit Unions",
            "subcategory":"Investment Brokerage",
            "type":"Services"
        }
    ],
    "sg:phone":"+1 310 443 4135",
    "sg:postcode":"90024",
    "sg:province":"CA",
    "sg:tags":[
        "investing"
    ],
    "wof:name":"Enterprise Efficiency Solutions",
    "wof:placetype":"venue"
},
  "geometry": {"coordinates":[-118.44523700000001,34.05843],"type":"Point"}
}