{
  "type": "Feature",
  "properties": {
    "addr:full":"8145 Signal Ct Sacramento CA 95824",
    "addr:housenumber":"8145",
    "addr:postcode":"95824",
    "addr:street":"Signal Ct",
    "iso:country":"US",
    "sg:address":"8145 Signal Ct",
    "sg:city":"Sacramento",
    "sg:classifiers":[
        {
            "category":"Freight",
            "type":"Transportation"
        }
    ],
    "sg:phone":"+1 916 386 8181",
    "sg:postcode":"95824",
    "sg:province":"CA",
    "sg:tags":[
        "delivery",
        "storage",
        "intrastate",
        "trucking"
    ],
    "wof:name":"Rodvold Trucking",
    "wof:placetype":"venue"
},
  "geometry": {"coordinates":[-121.40731700000001,38.513529],"type":"Point"}
}