{
  "type": "Feature",
  "properties": {
    "iso:country":"US",
    "sg:address":"1906 Cliff Dr",
    "sg:city":"Santa Barbara",
    "sg:classifiers":[
        {
            "category":"Restaurant",
            "type":"Food & Drink"
        }
    ],
    "sg:menulink":"http://www.allmenus.com/ca/santa-barbara/216140-mcdonalds/menu/",
    "sg:postcode":"93109",
    "sg:province":"CA",
    "sg:tags":[
        "burger",
        "american"
    ],
    "wof:name":"McDonald's",
    "wof:placetype":"venue"
},
  "geometry": {"coordinates":[-119.722261,34.401849],"type":"Point"}
}