{
  "type": "Feature",
  "properties": {
    "addr:full":"148 S Gilbert St Hemet CA 92543",
    "addr:housenumber":"148",
    "addr:postcode":"92543",
    "addr:street":"S Gilbert St",
    "iso:country":"US",
    "sg:address":"148 S Gilbert St",
    "sg:city":"Hemet",
    "sg:phone":"+1 951 652 2622",
    "sg:postcode":"92543",
    "sg:province":"CA",
    "sg:tags":[
        "product",
        "petroleum",
        "oils-petroleum"
    ],
    "wof:name":"Spartan Oil Co",
    "wof:placetype":"venue"
},
  "geometry": {"coordinates":[-116.976007,33.746625],"type":"Point"}
}