{
  "type": "Feature",
  "properties": {
    "iso:country":"US",
    "sg:address":"1140 Triton Dr",
    "sg:city":"San Mateo",
    "sg:classifiers":[
        {
            "category":"Restaurant",
            "type":"Food & Drink"
        }
    ],
    "sg:menulink":"http://www.allmenus.com/ca/san-mateo/170891-carls-jr/menu/",
    "sg:phone":"+1 650 349 2221",
    "sg:postcode":"94404",
    "sg:province":"CA",
    "sg:tags":[
        "burger",
        "american"
    ],
    "wof:name":"Carl's Jr.",
    "wof:placetype":"venue"
},
  "geometry": {"coordinates":[-122.27052999999999,37.563344],"type":"Point"}
}