{
  "type": "Feature",
  "properties": {
    "addr:full":"915 Daly Rd Ojai CA 93023",
    "addr:housenumber":"915",
    "addr:postcode":"93023",
    "addr:street":"Daly Rd",
    "iso:country":"US",
    "sg:address":"915 Daly Rd",
    "sg:city":"Ojai",
    "sg:classifiers":[
        {
            "category":"Building & Trades",
            "subcategory":"Construction",
            "type":"Services"
        }
    ],
    "sg:phone":"+1 805 640 0762",
    "sg:postcode":"93023",
    "sg:province":"CA",
    "sg:tags":[
        "wallcoverings-installation",
        "wallpaper",
        "painting",
        "contractor"
    ],
    "wof:name":"Jeffrey Baron Painting",
    "wof:placetype":"venue"
},
  "geometry": {"coordinates":[-119.241495,34.455776],"type":"Point"}
}