{
  "type": "Feature",
  "properties": {
    "iso:country":"US",
    "sg:address":"1112 Montana Ave",
    "sg:city":"Santa Monica",
    "sg:classifiers":[
        {
            "category":"Retail",
            "subcategory":"Portrait Studio",
            "type":"Services"
        }
    ],
    "sg:phone":"+1 310 770 2676",
    "sg:postcode":"90403",
    "sg:province":"CA",
    "sg:tags":[
        "photographer"
    ],
    "wof:name":"A LA Mode Photo",
    "wof:placetype":"venue"
},
  "geometry": {"coordinates":[-118.497556,34.030148],"type":"Point"}
}