{
  "type": "Feature",
  "properties": {
    "iso:country":"US",
    "sg:address":"1822 E 58th Pl",
    "sg:city":"Los Angeles",
    "sg:classifiers":[
        {
            "category":"Home & Garden",
            "subcategory":"Furniture",
            "type":"Retail Goods"
        }
    ],
    "sg:phone":"+1 323 582 4808",
    "sg:postcode":"90001",
    "sg:province":"CA",
    "sg:tags":[
        "store"
    ],
    "wof:name":"Petterstone Furniture",
    "wof:placetype":"venue"
},
  "geometry": {"coordinates":[-118.240696,33.987991],"type":"Point"}
}