{
  "type": "Feature",
  "properties": {
    "iso:country":"US",
    "sg:address":"6317 Wilshire Boulevard Suite 502",
    "sg:city":"Los Angeles",
    "sg:classifiers":[
        {
            "category":"Real Estate",
            "subcategory":"Real Estate Services",
            "type":"Services"
        }
    ],
    "sg:phone":"+1 323 651 9883",
    "sg:postcode":"90048",
    "sg:province":"CA",
    "sg:tags":[
        "management",
        "property"
    ],
    "wof:name":"Mazaltaf Investments",
    "wof:placetype":"venue"
},
  "geometry": {"coordinates":[-118.365809,34.063505],"type":"Point"}
}