{
  "type": "Feature",
  "properties": {
    "addr:full":"477 N Canyon Pkwy Livermore CA 94551",
    "addr:housenumber":"477",
    "addr:postcode":"94551",
    "addr:street":"N Canyon Pkwy",
    "iso:country":"US",
    "sg:address":"477 N Canyon Pkwy",
    "sg:city":"Livermore",
    "sg:classifiers":[
        {
            "category":"Wholesale",
            "subcategory":"Groceries",
            "type":"Manufacturing & Wholesale Goods"
        }
    ],
    "sg:phone":"+1 925 454 4500",
    "sg:postcode":"94551",
    "sg:province":"CA",
    "sg:tags":[
        "food",
        "product"
    ],
    "wof:name":"Kraft Foods Customer Svc Ctr",
    "wof:placetype":"venue"
},
  "geometry": {"coordinates":[-121.80838,37.705725],"type":"Point"}
}