{
  "type": "Feature",
  "properties": {
    "addr:full":"2434 Webb Ave Alameda CA 94501",
    "addr:housenumber":"2434",
    "addr:postcode":"94501",
    "addr:street":"Webb Ave",
    "iso:country":"US",
    "sg:address":"2434 Webb Ave",
    "sg:city":"Alameda",
    "sg:classifiers":[
        {
            "category":"Manufacturing",
            "subcategory":"Tools & Machinery",
            "type":"Manufacturing & Wholesale Goods"
        },
        {
            "category":"Shopping",
            "subcategory":"Computers & Home Electronics",
            "type":"Retail Goods"
        }
    ],
    "sg:phone":"+1 510 522 3333",
    "sg:postcode":"94501",
    "sg:province":"CA",
    "sg:tags":[
        "photographic",
        "equipment",
        "mfg",
        "electronic",
        "supply"
    ],
    "wof:name":"U S Citizen Sales",
    "wof:placetype":"venue"
},
  "geometry": {"coordinates":[-122.24020899999999,37.765212],"type":"Point"}
}