{
  "type": "Feature",
  "properties": {
    "iso:country":"US",
    "sg:address":"1600 S Main St",
    "sg:city":"Willits",
    "sg:classifiers":[
        {
            "category":"Wholesale",
            "subcategory":"Hardware",
            "type":"Manufacturing & Wholesale Goods"
        },
        {
            "category":"Home & Garden",
            "subcategory":"Garden Supply",
            "type":"Retail Goods"
        },
        {
            "category":"Retail",
            "subcategory":"Repair Shop",
            "type":"Services"
        }
    ],
    "sg:phone":"+1 707 459 6420",
    "sg:postcode":"95490",
    "sg:province":"CA",
    "sg:tags":[
        "renting",
        "lawn",
        "outdoor",
        "power",
        "landscaping",
        "equipment-sales",
        "equipment",
        "saw"
    ],
    "sg:website":"http://www.stihldealer.net/default-dealer-016710.aspx",
    "wof:name":"Willits Power Equipment",
    "wof:placetype":"venue"
},
  "geometry": {"coordinates":[-123.347555,39.392006],"type":"Point"}
}