{
  "type": "Feature",
  "properties": {
    "iso:country":"US",
    "sg:address":"21536 Hawthorne Blvd",
    "sg:city":"Torrance",
    "sg:classifiers":[
        {
            "category":"Health Services",
            "subcategory":"Optometrist",
            "type":"Services"
        }
    ],
    "sg:phone":"+1 310 542 3531",
    "sg:postcode":"90503",
    "sg:province":"CA",
    "wof:name":"Dr. Robert S. Weinstein",
    "wof:placetype":"venue"
},
  "geometry": {"coordinates":[-118.352319,33.830479],"type":"Point"}
}