{
  "type": "Feature",
  "properties": {
    "addr:full":"286 E. Hamilton Ave Ste K Campbell CA 95008",
    "addr:housenumber":"286",
    "addr:postcode":"95008",
    "addr:street":"E. Hamilton Ave Ste K",
    "iso:country":"US",
    "sg:address":"286 E. Hamilton Ave Ste K",
    "sg:city":"Campbell",
    "sg:classifiers":[
        {
            "category":"Personal",
            "subcategory":"Massage",
            "type":"Services"
        },
        {
            "category":"Personal",
            "subcategory":"Beauty Salon",
            "type":"Services"
        },
        {
            "category":"Personal",
            "subcategory":"Skin Care",
            "type":"Services"
        }
    ],
    "sg:phone":"+1 408 796 2329",
    "sg:postcode":"95008",
    "sg:province":"CA",
    "sg:tags":[
        "makeup",
        "artist"
    ],
    "sg:website":"www.biancasessence.com",
    "wof:name":"Bianca's Essence",
    "wof:placetype":"venue"
},
  "geometry": {"coordinates":[-121.94544399999999,37.293748],"type":"Point"}
}