{
  "type": "Feature",
  "properties": {
    "iso:country":"US",
    "sg:address":"14271 Dickens St",
    "sg:city":"Sherman Oaks",
    "sg:classifiers":[
        {
            "category":"Professional",
            "type":"Services"
        }
    ],
    "sg:phone":"+1 818 386 1945",
    "sg:postcode":"91423",
    "sg:province":"CA",
    "wof:name":"Arowana Musik",
    "wof:placetype":"venue"
},
  "geometry": {"coordinates":[-118.44515800000001,34.149318],"type":"Point"}
}