{
  "type": "Feature",
  "properties": {
    "addr:full":"3700 Churn Creek Rd Apt 5 Redding CA 96002",
    "addr:housenumber":"5",
    "addr:postcode":"3700;96002",
    "addr:street":"Churn Creek Rd Apt",
    "iso:country":"US",
    "sg:address":"3700 Churn Creek Rd Apt 5",
    "sg:city":"Redding",
    "sg:classifiers":[
        {
            "category":"Professional",
            "subcategory":"Business Services",
            "type":"Services"
        }
    ],
    "sg:phone":"+1 530 221 7743",
    "sg:postcode":"96002",
    "sg:province":"CA",
    "sg:tags":[
        "auction"
    ],
    "wof:name":"Super Auction Point",
    "wof:placetype":"venue"
},
  "geometry": {"coordinates":[-122.352966,40.553923],"type":"Point"}
}