{
  "type": "Feature",
  "properties": {
    "addr:full":"1006 Junipero Ave Long Beach CA 90804",
    "addr:housenumber":"1006",
    "addr:postcode":"90804",
    "addr:street":"Junipero Ave",
    "iso:country":"US",
    "sg:address":"1006 Junipero Ave",
    "sg:city":"Long Beach",
    "sg:classifiers":[
        {
            "category":"Retail",
            "subcategory":"Auto Repair",
            "type":"Services"
        }
    ],
    "sg:phone":"+1 562 438 8519",
    "sg:postcode":"90804",
    "sg:province":"CA",
    "sg:tags":[
        "body",
        "automobile",
        "painting"
    ],
    "wof:name":"Pon's Auto Body & Repair Ctr",
    "wof:placetype":"venue"
},
  "geometry": {"coordinates":[-118.163231,33.779799],"type":"Point"}
}