{
  "type": "Feature",
  "properties": {
    "addr:full":"16901 Main St Hesperia CA 92345",
    "addr:housenumber":"16901",
    "addr:postcode":"92345",
    "addr:street":"Main St",
    "iso:country":"US",
    "sg:address":"16901 Main St",
    "sg:city":"Hesperia",
    "sg:classifiers":[
        {
            "category":"Home & Garden",
            "subcategory":"Home Furnishings",
            "type":"Retail Goods"
        }
    ],
    "sg:phone":"+1 760 956 3226",
    "sg:postcode":"92345",
    "sg:province":"CA",
    "wof:name":"Direct Drapery & Win Coverings",
    "wof:placetype":"venue"
},
  "geometry": {"coordinates":[-117.295609,34.420594],"type":"Point"}
}