{
  "type": "Feature",
  "properties": {
    "iso:country":"US",
    "sg:address":"13411 Washington Blvd",
    "sg:city":"Marina Del Rey",
    "sg:classifiers":[
        {
            "category":"Shopping",
            "subcategory":"Department Store",
            "type":"Retail Goods"
        }
    ],
    "sg:phone":"+1 310 821 7690",
    "sg:postcode":"90292",
    "sg:province":"CA",
    "sg:website":"www.costco.com",
    "wof:name":"Costco Wholesale Corp",
    "wof:placetype":"venue"
},
  "geometry": {"coordinates":[-118.444844,33.992088],"type":"Point"}
}