{
  "type": "Feature",
  "properties": {
    "iso:country":"US",
    "sg:address":"2718 Kelly St",
    "sg:city":"Hayward",
    "sg:classifiers":[
        {
            "category":"Professional",
            "type":"Services"
        }
    ],
    "sg:phone":"+1 510 581 8782",
    "sg:postcode":"94541",
    "sg:province":"CA",
    "wof:name":"Whatever",
    "wof:placetype":"venue"
},
  "geometry": {"coordinates":[-122.056118,37.68447],"type":"Point"}
}