{
  "type": "Feature",
  "properties": {
    "iso:country":"US",
    "sg:address":"2697 Lavery Ct",
    "sg:city":"Newbury Park",
    "sg:classifiers":[
        {
            "category":"Manufacturing",
            "subcategory":"Tools & Machinery",
            "type":"Manufacturing & Wholesale Goods"
        }
    ],
    "sg:phone":"+1 805 376 0202",
    "sg:postcode":"91320",
    "sg:province":"CA",
    "sg:tags":[
        "machine",
        "shop"
    ],
    "wof:name":"Jonrad Manufacturing",
    "wof:placetype":"venue"
},
  "geometry": {"coordinates":[-118.92921800000001,34.194142],"type":"Point"}
}