{
  "type": "Feature",
  "properties": {
    "iso:country":"US",
    "sg:address":"599 N Valencia Blvd",
    "sg:city":"Woodlake",
    "sg:classifiers":[
        {
            "category":"Organizations",
            "subcategory":"Religious Organization",
            "type":"Services"
        }
    ],
    "sg:phone":"+1 559 564 2647",
    "sg:postcode":"93286",
    "sg:province":"CA",
    "sg:tags":[
        "church"
    ],
    "wof:name":"St Frances Cabrini Catholic",
    "wof:placetype":"venue"
},
  "geometry": {"coordinates":[-119.098868,36.420978],"type":"Point"}
}