{
  "type": "Feature",
  "properties": {
    "addr:full":"1515 63rd St Emeryville CA 94608",
    "addr:housenumber":"1515",
    "addr:postcode":"94608",
    "addr:street":"63Rd St",
    "iso:country":"US",
    "sg:address":"1515 63rd St",
    "sg:city":"Emeryville",
    "sg:classifiers":[
        {
            "category":"Wholesale",
            "subcategory":"Home Furnishings",
            "type":"Manufacturing & Wholesale Goods"
        }
    ],
    "sg:phone":"+1 877 258 3724",
    "sg:postcode":"94608",
    "sg:province":"CA",
    "sg:tags":[
        "blind",
        "shade"
    ],
    "sg:website":"www.bluesage.biz",
    "wof:name":"Blue Sage",
    "wof:placetype":"venue"
},
  "geometry": {"coordinates":[-122.29081100000001,37.843895],"type":"Point"}
}