{
  "type": "Feature",
  "properties": {
    "iso:country":"US",
    "sg:address":"8539 Sunset Blvd #20",
    "sg:city":"West Hollywood",
    "sg:classifiers":[
        {
            "category":"Restaurant",
            "type":"Food & Drink"
        }
    ],
    "sg:phone":"+1 310 652 0523",
    "sg:postcode":"90069",
    "sg:province":"CA",
    "sg:tags":[
        "sushi",
        "bar"
    ],
    "sg:website":"www.sushiparkonsunset.com/",
    "wof:name":"Sushi Park",
    "wof:placetype":"venue"
},
  "geometry": {"coordinates":[-118.377527,34.093628],"type":"Point"}
}