{
  "type": "Feature",
  "properties": {
    "addr:full":"22917 Banyan Pl Santa Clarita CA 91390",
    "addr:housenumber":"22917",
    "addr:postcode":"91390",
    "addr:street":"Banyan Pl",
    "iso:country":"US",
    "sg:address":"22917 Banyan Pl",
    "sg:city":"Santa Clarita",
    "sg:classifiers":[
        {
            "category":"Manufacturing",
            "subcategory":"Apparel",
            "type":"Manufacturing & Wholesale Goods"
        }
    ],
    "sg:phone":"+1 661 478 3271",
    "sg:postcode":"91390",
    "sg:province":"CA",
    "sg:tags":[
        "household",
        "furnishing",
        "mfg"
    ],
    "wof:name":"Mjs House of Pillows",
    "wof:placetype":"venue"
},
  "geometry": {"coordinates":[-118.534459,34.463501],"type":"Point"}
}