{
  "type": "Feature",
  "properties": {
    "addr:full":"17905 Hinton St Hesperia CA 92345",
    "addr:housenumber":"17905",
    "addr:postcode":"92345",
    "addr:street":"Hinton St",
    "iso:country":"US",
    "sg:address":"17905 Hinton St",
    "sg:city":"Hesperia",
    "sg:classifiers":[
        {
            "category":"Home & Garden",
            "subcategory":"Building Materials",
            "type":"Retail Goods"
        },
        {
            "category":"Manufacturing",
            "subcategory":"Building Materials",
            "type":"Manufacturing & Wholesale Goods"
        }
    ],
    "sg:phone":"+1 909 224 4161",
    "sg:postcode":"92345",
    "sg:province":"CA",
    "sg:tags":[
        "materials-wholesale",
        "manufacturer"
    ],
    "wof:name":"The Supply Smith",
    "wof:placetype":"venue"
},
  "geometry": {"coordinates":[-117.2739,34.405442],"type":"Point"}
}