{
  "type": "Feature",
  "properties": {
    "addr:full":"2403 San Carlos Ave Castro Valley CA 94546",
    "addr:housenumber":"2403",
    "addr:postcode":"94546",
    "addr:street":"San Carlos Ave",
    "iso:country":"US",
    "sg:address":"2403 San Carlos Ave",
    "sg:city":"Castro Valley",
    "sg:classifiers":[
        {
            "category":"Professional",
            "type":"Services"
        }
    ],
    "sg:phone":"+1 510 886 1091",
    "sg:postcode":"94546",
    "sg:province":"CA",
    "wof:name":"Newsamerica Dolores Rodri",
    "wof:placetype":"venue"
},
  "geometry": {"coordinates":[-122.091044,37.693979],"type":"Point"}
}