{
  "type": "Feature",
  "properties": {
    "addr:full":"2495 Hilltop Dr Redding CA 96002",
    "addr:housenumber":"2495",
    "addr:postcode":"96002",
    "addr:street":"Hilltop Dr",
    "iso:country":"US",
    "sg:address":"2495 Hilltop Dr",
    "sg:city":"Redding",
    "sg:classifiers":[
        {
            "category":"Restaurant",
            "type":"Food & Drink"
        }
    ],
    "sg:phone":"+1 530 221 5130",
    "sg:postcode":"96002",
    "sg:province":"CA",
    "sg:tags":[
        "style",
        "family",
        "lunch",
        "american",
        "brunch",
        "breakfast"
    ],
    "sg:website":"http://www.ihop.com",
    "wof:name":"Ihop",
    "wof:placetype":"venue"
},
  "geometry": {"coordinates":[-122.358031,40.572081],"type":"Point"}
}