{
  "type": "Feature",
  "properties": {
    "iso:country":"US",
    "sg:address":"501 Deodara Dr",
    "sg:city":"Los Altos",
    "sg:classifiers":[
        {
            "category":"Professional",
            "type":"Services"
        }
    ],
    "sg:phone":"+1 650 964 5339",
    "sg:postcode":"94024",
    "sg:province":"CA",
    "sg:tags":[
        "establishment"
    ],
    "wof:name":"Djpower Intl",
    "wof:placetype":"venue"
},
  "geometry": {"coordinates":[-122.07126,37.339439],"type":"Point"}
}