{
  "type": "Feature",
  "properties": {
    "addr:full":"1343 S Main St Porterville CA 93257",
    "addr:housenumber":"1343",
    "addr:postcode":"93257",
    "addr:street":"S Main St",
    "iso:country":"US",
    "sg:address":"1343 S Main St",
    "sg:city":"Porterville",
    "sg:classifiers":[
        {
            "category":"Wholesale",
            "subcategory":"Machinery & Supplies",
            "type":"Manufacturing & Wholesale Goods"
        }
    ],
    "sg:phone":"+1 559 784 4102",
    "sg:postcode":"93257",
    "sg:province":"CA",
    "sg:tags":[
        "engine",
        "outdoor",
        "power",
        "equipment",
        "parts",
        "distribution"
    ],
    "wof:name":"Billious Inc",
    "wof:placetype":"venue"
},
  "geometry": {"coordinates":[-119.017532,36.041304],"type":"Point"}
}