{
  "type": "Feature",
  "properties": {
    "addr:full":"1376 Lemen Ave Woodland CA 95776",
    "addr:housenumber":"1376",
    "addr:postcode":"95776",
    "addr:street":"Lemen Ave",
    "iso:country":"US",
    "sg:address":"1376 Lemen Ave",
    "sg:city":"Woodland",
    "sg:classifiers":[
        {
            "category":"Manufacturing",
            "subcategory":"Food",
            "type":"Manufacturing & Wholesale Goods"
        }
    ],
    "sg:phone":"+1 530 662 8661",
    "sg:postcode":"95776",
    "sg:province":"CA",
    "sg:tags":[
        "canned",
        "mfg"
    ],
    "wof:name":"Contadina Foods",
    "wof:placetype":"venue"
},
  "geometry": {"coordinates":[-121.756686,38.680266],"type":"Point"}
}