{
  "type": "Feature",
  "properties": {
    "iso:country":"US",
    "sg:address":"8400 Monroe Ave",
    "sg:city":"Stanton",
    "sg:classifiers":[
        {
            "category":"Retail",
            "subcategory":"Auto Repair",
            "type":"Services"
        }
    ],
    "sg:phone":"+1 714 229 9076",
    "sg:postcode":"90680",
    "sg:province":"CA",
    "sg:tags":[
        "scooter",
        "motorcycle",
        "motor"
    ],
    "sg:website":"www.hotrods-n-hogs.com",
    "wof:name":"Hot Rods & Hogs",
    "wof:placetype":"venue"
},
  "geometry": {"coordinates":[-117.986198,33.805455],"type":"Point"}
}