{
  "type": "Feature",
  "properties": {
    "iso:country":"US",
    "sg:address":"2321 Kern St",
    "sg:city":"Fresno",
    "sg:classifiers":[
        {
            "category":"Food & Beverages",
            "subcategory":"Bakery",
            "type":"Retail Goods"
        }
    ],
    "sg:phone":"+1 559 442 1947",
    "sg:postcode":"93721",
    "sg:province":"CA",
    "sg:tags":[
        "cookie",
        "cracker"
    ],
    "wof:name":"Doug-Out Cookies",
    "wof:placetype":"venue"
},
  "geometry": {"coordinates":[-119.78522,36.73572],"type":"Point"}
}