{
  "type": "Feature",
  "properties": {
    "iso:country":"US",
    "sg:address":"226 S Beverly Dr",
    "sg:city":"Beverly Hills",
    "sg:classifiers":[
        {
            "category":"Health Services",
            "subcategory":"Doctor",
            "type":"Services"
        },
        {
            "category":"Health Services",
            "subcategory":"Clinic",
            "type":"Services"
        }
    ],
    "sg:phone":"+1 310 273 4843",
    "sg:postcode":"90212",
    "sg:province":"CA",
    "sg:tags":[
        "counseling",
        "mental"
    ],
    "wof:name":"Kalechstein Ari PHD",
    "wof:placetype":"venue"
},
  "geometry": {"coordinates":[-118.399002,34.064301],"type":"Point"}
}