{
  "type": "Feature",
  "properties": {
    "addr:full":"24215 Fir Ave Moreno Valley CA 92553",
    "addr:housenumber":"24215",
    "addr:postcode":"92553",
    "addr:street":"Fir Ave",
    "iso:country":"US",
    "sg:address":"24215 Fir Ave",
    "sg:city":"Moreno Valley",
    "sg:classifiers":[
        {
            "category":"Organizations",
            "subcategory":"Religious Organization",
            "type":"Services"
        }
    ],
    "sg:phone":"+1 951 924 7474",
    "sg:postcode":"92553",
    "sg:province":"CA",
    "sg:tags":[
        "church"
    ],
    "wof:name":"Moreno Valley Congregational",
    "wof:placetype":"venue"
},
  "geometry": {"coordinates":[-117.238232,33.935358],"type":"Point"}
}