{
  "type": "Feature",
  "properties": {
    "addr:full":"773 E Blithedale Ave Mill Valley CA 94941",
    "addr:housenumber":"773",
    "addr:postcode":"94941",
    "addr:street":"E Blithedale Ave",
    "iso:country":"US",
    "sg:address":"773 E Blithedale Ave",
    "sg:city":"Mill Valley",
    "sg:classifiers":[
        {
            "category":"Food & Beverages",
            "subcategory":"Specialty",
            "type":"Retail Goods"
        }
    ],
    "sg:phone":"+1 415 380 8949",
    "sg:postcode":"94941",
    "sg:province":"CA",
    "sg:tags":[
        "health",
        "diet"
    ],
    "wof:name":"General Nutrition Ctr",
    "wof:placetype":"venue"
},
  "geometry": {"coordinates":[-122.524828,37.901783],"type":"Point"}
}