{
  "type": "Feature",
  "properties": {
    "iso:country":"US",
    "sg:address":"23891 Via Fabricante",
    "sg:city":"Mission Viejo",
    "sg:classifiers":[
        {
            "category":"Health Services",
            "subcategory":"Medical Lab",
            "type":"Services"
        }
    ],
    "sg:phone":"+1 949 462 9822",
    "sg:postcode":"92691",
    "sg:province":"CA",
    "sg:tags":[
        "laboratory"
    ],
    "wof:name":"AFR Labs",
    "wof:placetype":"venue"
},
  "geometry": {"coordinates":[-117.68049600000001,33.615583],"type":"Point"}
}