{
  "type": "Feature",
  "properties": {
    "iso:country":"US",
    "sg:address":"741 N La Cadena Dr",
    "sg:city":"Colton",
    "sg:classifiers":[
        {
            "category":"Education",
            "subcategory":"School",
            "type":"Public Place"
        }
    ],
    "sg:phone":"+1 909 825 8399",
    "sg:postcode":"92324",
    "sg:province":"CA",
    "wof:name":"Botanica La Santa Fe",
    "wof:placetype":"venue"
},
  "geometry": {"coordinates":[-117.32326399999999,34.276457],"type":"Point"}
}