{
  "type": "Feature",
  "properties": {
    "addr:full":"3379 Beard Rd Napa CA 94558",
    "addr:housenumber":"3379",
    "addr:postcode":"94558",
    "addr:street":"Beard Rd",
    "iso:country":"US",
    "sg:address":"3379 Beard Rd",
    "sg:city":"Napa",
    "sg:classifiers":[
        {
            "category":"Health Services",
            "subcategory":"Podiatrist",
            "type":"Services"
        }
    ],
    "sg:phone":"+1 707 224 4800",
    "sg:postcode":"94558",
    "sg:province":"CA",
    "wof:name":"Specialists Foot & Ankle Clnc",
    "wof:placetype":"venue"
},
  "geometry": {"coordinates":[-122.29529100000001,38.32095],"type":"Point"}
}