{
  "type": "Feature",
  "properties": {
    "addr:full":"4141 Jutland Drive Suite 201 San Diego CA 92117",
    "addr:housenumber":"4141",
    "addr:postcode":"92117",
    "addr:street":"Jutland Drive Suite 201",
    "iso:country":"US",
    "sg:address":"4141 Jutland Drive Suite 201",
    "sg:city":"San Diego",
    "sg:classifiers":[
        {
            "category":"Professional",
            "subcategory":"Lawyer & Legal Services",
            "type":"Services"
        }
    ],
    "sg:phone":"+1 858 274 8260",
    "sg:postcode":"92117",
    "sg:province":"CA",
    "sg:website":"www.williamsonbrown.com",
    "wof:name":"Williamson & Brown",
    "wof:placetype":"venue"
},
  "geometry": {"coordinates":[-117.22813499999999,32.824091],"type":"Point"}
}