{
  "type": "Feature",
  "properties": {
    "addr:full":"12251 Tomki Rd Redwood Valley CA 95470",
    "addr:housenumber":"12251",
    "addr:postcode":"95470",
    "addr:street":"Tomki Rd",
    "iso:country":"US",
    "sg:address":"12251 Tomki Rd",
    "sg:city":"Redwood Valley",
    "sg:classifiers":[
        {
            "category":"Retail",
            "subcategory":"Repair Shop",
            "type":"Services"
        }
    ],
    "sg:phone":"+1 707 485 1107",
    "sg:postcode":"95470",
    "sg:province":"CA",
    "sg:tags":[
        "tractor"
    ],
    "wof:name":"Leon's Tractor & Equipment",
    "wof:placetype":"venue"
},
  "geometry": {"coordinates":[-123.222567,39.314741],"type":"Point"}
}