{
  "type": "Feature",
  "properties": {
    "iso:country":"US",
    "sg:address":"3070 Center St",
    "sg:city":"Soquel",
    "sg:classifiers":[
        {
            "category":"Building & Trades",
            "subcategory":"Cleaning & Sanitation",
            "type":"Services"
        }
    ],
    "sg:phone":"+1 831 419 3083",
    "sg:postcode":"95073",
    "sg:province":"CA",
    "sg:tags":[
        "window"
    ],
    "wof:name":"Bay View Window Cleaning",
    "wof:placetype":"venue"
},
  "geometry": {"coordinates":[-121.95326900000001,36.989155],"type":"Point"}
}