{
  "type": "Feature",
  "properties": {
    "iso:country":"US",
    "sg:address":"8710 Avenida De La Fuente",
    "sg:city":"San Diego",
    "sg:classifiers":[
        {
            "category":"Wholesale",
            "subcategory":"Scrap",
            "type":"Manufacturing & Wholesale Goods"
        },
        {
            "category":"Utilities",
            "subcategory":"Recycling",
            "type":"Services"
        }
    ],
    "sg:phone":"+1 619 661 1283",
    "sg:postcode":"92154",
    "sg:province":"CA",
    "sg:tags":[
        "junk",
        "hauling",
        "removal"
    ],
    "sg:website":"www.cactusrecycling.com",
    "wof:name":"Cactus Recycling Inc",
    "wof:placetype":"venue"
},
  "geometry": {"coordinates":[-116.956124,32.556718],"type":"Point"}
}