{
  "type": "Feature",
  "properties": {
    "addr:full":"3137 Jefferson Ave Redwood City CA 94062",
    "addr:housenumber":"3137",
    "addr:postcode":"94062",
    "addr:street":"Jefferson Ave",
    "iso:country":"US",
    "sg:address":"3137 Jefferson Ave",
    "sg:city":"Redwood City",
    "sg:classifiers":[
        {
            "category":"Shopping",
            "subcategory":"Pharmacy",
            "type":"Retail Goods"
        }
    ],
    "sg:phone":"+1 650 366 3784",
    "sg:postcode":"94062",
    "sg:province":"CA",
    "wof:name":"Jefferson Plaza Pharmacy",
    "wof:placetype":"venue"
},
  "geometry": {"coordinates":[-122.246786,37.469849],"type":"Point"}
}