{
  "type": "Feature",
  "properties": {
    "addr:full":"2395 Hamner Ave Norco CA 92860",
    "addr:housenumber":"2395",
    "addr:postcode":"92860",
    "addr:street":"Hamner Ave",
    "iso:country":"US",
    "sg:address":"2395 Hamner Ave",
    "sg:city":"Norco",
    "sg:classifiers":[
        {
            "category":"Shopping",
            "type":"Retail Goods"
        }
    ],
    "sg:phone":"+1 951 736 8552",
    "sg:postcode":"92860",
    "sg:province":"CA",
    "sg:tags":[
        "cards",
        "sport",
        "baseball",
        "memorabilia"
    ],
    "wof:name":"Affordable Cards & Cllctbls",
    "wof:placetype":"venue"
},
  "geometry": {"coordinates":[-117.56021,33.914891],"type":"Point"}
}