{
  "type": "Feature",
  "properties": {
    "iso:country":"US",
    "sg:address":"1101 E Ash Ave Ste H",
    "sg:city":"Fullerton",
    "sg:classifiers":[
        {
            "category":"Autos & Motor Vehicles",
            "subcategory":"Motorcycle Sales",
            "type":"Retail Goods"
        }
    ],
    "sg:phone":"+1 714 447 4636",
    "sg:postcode":"92831",
    "sg:province":"CA",
    "wof:name":"American Indian Specialists",
    "wof:placetype":"venue"
},
  "geometry": {"coordinates":[-117.910004,33.865101],"type":"Point"}
}