{
  "type": "Feature",
  "properties": {
    "iso:country":"US",
    "sg:address":"2569 Dewberry Dr",
    "sg:city":"Redding",
    "sg:classifiers":[
        {
            "category":"Freight",
            "type":"Transportation"
        }
    ],
    "sg:phone":"+1 530 226 0587",
    "sg:postcode":"96003",
    "sg:province":"CA",
    "wof:name":"Yerkes Transportation",
    "wof:placetype":"venue"
},
  "geometry": {"coordinates":[-122.32184100000001,40.583027],"type":"Point"}
}