{
  "type": "Feature",
  "properties": {
    "addr:full":"3712 Mujica Pl Brea CA 92821",
    "addr:housenumber":"3712",
    "addr:postcode":"92821",
    "addr:street":"Mujica Pl",
    "iso:country":"US",
    "sg:address":"3712 Mujica Pl",
    "sg:city":"Brea",
    "sg:classifiers":[
        {
            "category":"Manufacturing",
            "subcategory":"Food",
            "type":"Manufacturing & Wholesale Goods"
        }
    ],
    "sg:phone":"+1 714 630 3088",
    "sg:postcode":"92821",
    "sg:province":"CA",
    "sg:tags":[
        "corn",
        "retail",
        "kettle"
    ],
    "wof:name":"Kettle Masters Inc",
    "wof:placetype":"venue"
},
  "geometry": {"coordinates":[-117.845191,33.907844],"type":"Point"}
}