{
  "type": "Feature",
  "properties": {
    "iso:country":"US",
    "sg:address":"225 6th St",
    "sg:city":"Hollister",
    "sg:classifiers":[
        {
            "category":"Shopping",
            "subcategory":"Catalog Store",
            "type":"Retail Goods"
        }
    ],
    "sg:phone":"+1 831 638 1352",
    "sg:postcode":"95023",
    "sg:province":"CA",
    "sg:tags":[
        "e"
    ],
    "wof:name":"San Benito Com",
    "wof:placetype":"venue"
},
  "geometry": {"coordinates":[-121.401901,36.850326],"type":"Point"}
}