{
  "type": "Feature",
  "properties": {
    "addr:full":"2277 International Blvd Oakland CA 94606",
    "addr:housenumber":"2277",
    "addr:postcode":"94606",
    "addr:street":"International Blvd",
    "iso:country":"US",
    "sg:address":"2277 International Blvd",
    "sg:city":"Oakland",
    "sg:classifiers":[
        {
            "category":"Arts & Performance",
            "subcategory":"Arts Center",
            "type":"Entertainment"
        }
    ],
    "sg:phone":"+1 510 533 6629",
    "sg:postcode":"94606",
    "sg:province":"CA",
    "sg:tags":[
        "performing"
    ],
    "sg:website":"www.eastsideartsalliance.com",
    "wof:name":"Eastside Arts Alliance",
    "wof:placetype":"venue"
},
  "geometry": {"coordinates":[-122.236282,37.783629],"type":"Point"}
}