{
  "type": "Feature",
  "properties": {
    "addr:full":"3605 Market St Riverside CA 92501",
    "addr:housenumber":"3605",
    "addr:postcode":"92501",
    "addr:street":"Market St",
    "iso:country":"US",
    "sg:address":"3605 Market St",
    "sg:city":"Riverside",
    "sg:classifiers":[
        {
            "category":"Shopping",
            "subcategory":"Used Merchandise",
            "type":"Retail Goods"
        }
    ],
    "sg:phone":"+1 951 784 6528",
    "sg:postcode":"92501",
    "sg:province":"CA",
    "sg:tags":[
        "antique"
    ],
    "wof:name":"Maria's Antiques",
    "wof:placetype":"venue"
},
  "geometry": {"coordinates":[-117.37506500000001,33.9836],"type":"Point"}
}