{
  "type": "Feature",
  "properties": {
    "addr:full":"5951 Del AMO Blvd Lakewood CA 90713",
    "addr:housenumber":"5951",
    "addr:postcode":"90713",
    "addr:street":"Del Amo Blvd",
    "iso:country":"US",
    "sg:address":"5951 Del AMO Blvd",
    "sg:city":"Lakewood",
    "sg:classifiers":[
        {
            "category":"Food & Beverages",
            "subcategory":"Groceries & Convenience Stores",
            "type":"Retail Goods"
        }
    ],
    "sg:phone":"+1 562 867 7281",
    "sg:postcode":"90713",
    "sg:province":"CA",
    "wof:name":"Ralphs Grocery Company",
    "wof:placetype":"venue"
},
  "geometry": {"coordinates":[-118.114998,33.847198],"type":"Point"}
}