{
  "type": "Feature",
  "properties": {
    "addr:full":"15620 Sierra Hwy Mojave CA 93501",
    "addr:housenumber":"15620",
    "addr:postcode":"93501",
    "addr:street":"Sierra Hwy",
    "iso:country":"US",
    "sg:address":"15620 Sierra Hwy",
    "sg:city":"Mojave",
    "sg:classifiers":[
        {
            "category":"Travel",
            "subcategory":"Hotels & Motels",
            "type":"Entertainment"
        }
    ],
    "sg:phone":"+1 661 824 4523",
    "sg:postcode":"93501",
    "sg:province":"CA",
    "wof:name":"Best Motel",
    "wof:placetype":"venue"
},
  "geometry": {"coordinates":[-118.172741,35.049541],"type":"Point"}
}