{
  "type": "Feature",
  "properties": {
    "iso:country":"US",
    "sg:address":"320 Rustic Ln",
    "sg:city":"Rohnert Park",
    "sg:classifiers":[
        {
            "category":"Shopping",
            "subcategory":"Beauty & Cosmetics",
            "type":"Retail Goods"
        }
    ],
    "sg:phone":"+1 707 584 1755",
    "sg:postcode":"94928",
    "sg:province":"CA",
    "sg:tags":[
        "merchandise"
    ],
    "wof:name":"Karen Manning Karina",
    "wof:placetype":"venue"
},
  "geometry": {"coordinates":[-122.69819099999999,38.344386],"type":"Point"}
}