{
  "type": "Feature",
  "properties": {
    "addr:full":"The Secret Flower Garden 2164 Union Street San Francisco CA 94123",
    "addr:housenumber":"2164",
    "addr:postcode":"94123",
    "addr:street":"Union Street",
    "iso:country":"US",
    "sg:address":"The Secret Flower Garden 2164 Union Street",
    "sg:city":"San Francisco",
    "sg:classifiers":[
        {
            "category":"Shopping",
            "subcategory":"Beauty & Cosmetics",
            "type":"Retail Goods"
        }
    ],
    "sg:phone":"+1 415 935 9854",
    "sg:postcode":"94123",
    "sg:province":"CA",
    "sg:tags":[
        "supply"
    ],
    "sg:website":"www.shopgreen11.com",
    "wof:name":"Green11",
    "wof:placetype":"venue"
},
  "geometry": {"coordinates":[-122.434918,37.797196],"type":"Point"}
}