{
  "type": "Feature",
  "properties": {
    "iso:country":"US",
    "sg:address":"34231 Rd 144",
    "sg:city":"Visalia",
    "sg:classifiers":[
        {
            "category":"Retail",
            "subcategory":"Auto Repair",
            "type":"Services"
        }
    ],
    "sg:phone":"+1 559 733 0364",
    "sg:postcode":"93292",
    "sg:province":"CA",
    "sg:tags":[
        "truck"
    ],
    "wof:name":"T K Tech",
    "wof:placetype":"venue"
},
  "geometry": {"coordinates":[-119.251282,36.413505],"type":"Point"}
}