{
  "type": "Feature",
  "properties": {
    "iso:country":"US",
    "sg:address":"8512 Santa Monica Blvd West Hollywood",
    "sg:city":"West Hollywood",
    "sg:classifiers":[
        {
            "category":"Restaurant",
            "type":"Food & Drink"
        }
    ],
    "sg:phone":"+1 310 289 0088",
    "sg:postcode":"90069",
    "sg:province":"CA",
    "sg:tags":[
        "mexican"
    ],
    "sg:website":"www.gogomexico.com",
    "wof:name":"Mexico Restaurante Y Barra",
    "wof:placetype":"venue"
},
  "geometry": {"coordinates":[-118.376905,34.088805],"type":"Point"}
}