{
  "type": "Feature",
  "properties": {
    "addr:full":"8341 Kerrnita Rd Bakersfield CA 93307",
    "addr:housenumber":"8341",
    "addr:postcode":"93307",
    "addr:street":"Kerrnita Rd",
    "iso:country":"US",
    "sg:address":"8341 Kerrnita Rd",
    "sg:city":"Bakersfield",
    "sg:classifiers":[
        {
            "category":"Sports & Exercise",
            "subcategory":"Stables",
            "type":"Entertainment"
        },
        {
            "category":"Farming",
            "subcategory":"Livestock Farm",
            "type":"Manufacturing & Wholesale Goods"
        },
        {
            "category":"Arena",
            "subcategory":"Horse Racetrack",
            "type":"Entertainment"
        }
    ],
    "sg:phone":"+1 661 366 6298",
    "sg:postcode":"93307",
    "sg:province":"CA",
    "sg:tags":[
        "breeder"
    ],
    "wof:name":"Double G Appaloosa Ranch",
    "wof:placetype":"venue"
},
  "geometry": {"coordinates":[-118.912691,35.3471],"type":"Point"}
}