{
  "type": "Feature",
  "properties": {
    "addr:full":"2372 Stanwell Cir Concord CA 94520",
    "addr:housenumber":"2372",
    "addr:postcode":"94520",
    "addr:street":"Stanwell Cir",
    "iso:country":"US",
    "sg:address":"2372 Stanwell Cir",
    "sg:city":"Concord",
    "sg:classifiers":[
        {
            "category":"Manufacturing",
            "subcategory":"Tools & Machinery",
            "type":"Manufacturing & Wholesale Goods"
        }
    ],
    "sg:phone":"+1 925 798 2206",
    "sg:postcode":"94520",
    "sg:province":"CA",
    "sg:tags":[
        "equipment",
        "dental",
        "supply"
    ],
    "sg:website":"www.ghartzellandson.com",
    "wof:name":"G Hartzell & Son",
    "wof:placetype":"venue"
},
  "geometry": {"coordinates":[-122.04879200000001,37.981656],"type":"Point"}
}