{
  "type": "Feature",
  "properties": {
    "addr:full":"639 Clement St San Francisco CA 94118",
    "addr:housenumber":"639",
    "addr:postcode":"94118",
    "addr:street":"Clement St",
    "iso:country":"US",
    "sg:address":"639 Clement St",
    "sg:city":"San Francisco",
    "sg:classifiers":[
        {
            "category":"Restaurant",
            "type":"Food & Drink"
        }
    ],
    "sg:menulink":"http://www.allmenus.com/ca/san-francisco/62191-king-of-thai-noodle-house-1/menu/",
    "sg:phone":"+1 415 752 5198",
    "sg:postcode":"94118",
    "sg:province":"CA",
    "sg:tags":[
        "thai",
        "asian"
    ],
    "wof:name":"King Of Thai Noodle House #1",
    "wof:placetype":"venue"
},
  "geometry": {"coordinates":[-122.46597199999999,37.782922],"type":"Point"}
}