{
  "type": "Feature",
  "properties": {
    "iso:country":"US",
    "sg:address":"315 Court St",
    "sg:city":"Jackson",
    "sg:classifiers":[
        {
            "category":"Manufacturing",
            "subcategory":"Glass & Minerals",
            "type":"Manufacturing & Wholesale Goods"
        }
    ],
    "sg:phone":"+1 209 257 1346",
    "sg:postcode":"95642",
    "sg:province":"CA",
    "sg:tags":[
        "product",
        "mfg"
    ],
    "wof:name":"Imaginations",
    "wof:placetype":"venue"
},
  "geometry": {"coordinates":[-120.773025,38.349723],"type":"Point"}
}