{
  "type": "Feature",
  "properties": {
    "addr:full":"11 Knoll Ln Mill Valley CA 94941",
    "addr:housenumber":"11",
    "addr:postcode":"94941",
    "addr:street":"Knoll Ln",
    "iso:country":"US",
    "sg:address":"11 Knoll Ln",
    "sg:city":"Mill Valley",
    "sg:classifiers":[
        {
            "category":"Organizations",
            "subcategory":"Religious Organization",
            "type":"Services"
        }
    ],
    "sg:phone":"+1 415 388 1385",
    "sg:postcode":"94941",
    "sg:province":"CA",
    "sg:tags":[
        "church"
    ],
    "wof:name":"Jehovah's Witnesses",
    "wof:placetype":"venue"
},
  "geometry": {"coordinates":[-122.512381,37.9016],"type":"Point"}
}