{
  "type": "Feature",
  "properties": {
    "addr:full":"4715 S Normandie Ave Los Angeles CA 90037",
    "addr:housenumber":"4715",
    "addr:postcode":"90037",
    "addr:street":"S Normandie Ave",
    "iso:country":"US",
    "sg:address":"4715 S Normandie Ave",
    "sg:city":"Los Angeles",
    "sg:classifiers":[
        {
            "category":"Organizations",
            "subcategory":"Religious Organization",
            "type":"Services"
        }
    ],
    "sg:phone":"+1 323 233 3576",
    "sg:postcode":"90037",
    "sg:province":"CA",
    "sg:tags":[
        "church"
    ],
    "wof:name":"First Zion Travelers Bapt Ch",
    "wof:placetype":"venue"
},
  "geometry": {"coordinates":[-118.300248,34.000787],"type":"Point"}
}