{
  "type": "Feature",
  "properties": {
    "addr:full":"14477 Big Basin Way Saratoga CA 95070",
    "addr:housenumber":"14477",
    "addr:postcode":"95070",
    "addr:street":"Big Basin Way",
    "iso:country":"US",
    "sg:address":"14477 Big Basin Way",
    "sg:city":"Saratoga",
    "sg:classifiers":[
        {
            "category":"Shopping",
            "type":"Retail Goods"
        }
    ],
    "sg:phone":"+1 408 867 3995",
    "sg:postcode":"95070",
    "sg:province":"CA",
    "wof:name":"Echo Shop of St Andrews Church",
    "wof:placetype":"venue"
},
  "geometry": {"coordinates":[-122.03299699999999,37.257702],"type":"Point"}
}