{
  "type": "Feature",
  "properties": {
    "addr:full":"1656 E 118th Street Los Angeles CA 90059",
    "addr:housenumber":"1656",
    "addr:postcode":"90059",
    "addr:street":"E 118Th Street",
    "iso:country":"US",
    "sg:address":"1656 E 118th Street",
    "sg:city":"Los Angeles",
    "sg:classifiers":[
        {
            "category":"Education",
            "subcategory":"School",
            "type":"Public Place"
        }
    ],
    "sg:phone":"+1 323 566 0420",
    "sg:postcode":"90059",
    "sg:province":"CA",
    "sg:tags":[
        "high",
        "middle",
        "elementary"
    ],
    "wof:name":"Los Angeles Unified School District",
    "wof:placetype":"venue"
},
  "geometry": {"coordinates":[-118.24435,33.925898],"type":"Point"}
}