{
  "type": "Feature",
  "properties": {
    "iso:country":"US",
    "sg:address":"9545 Whittier Blvd",
    "sg:city":"Pico Rivera",
    "sg:classifiers":[
        {
            "category":"Restaurant",
            "type":"Food & Drink"
        }
    ],
    "sg:phone":"+1 562 699 4716",
    "sg:postcode":"90660",
    "sg:province":"CA",
    "wof:name":"Steak'n Stein Inn Clearman's",
    "wof:placetype":"venue"
},
  "geometry": {"coordinates":[-118.073997,33.9972],"type":"Point"}
}