{
  "type": "Feature",
  "properties": {
    "iso:country":"US",
    "sg:address":"26 Evergreen Dr",
    "sg:city":"Lodi",
    "sg:classifiers":[
        {
            "category":"Retail",
            "subcategory":"Laundry & Dry Cleaning",
            "type":"Services"
        }
    ],
    "sg:phone":"+1 209 366 1273",
    "sg:postcode":"95242",
    "sg:province":"CA",
    "sg:tags":[
        "cleaner",
        "commercial"
    ],
    "wof:name":"Service Laundry",
    "wof:placetype":"venue"
},
  "geometry": {"coordinates":[-121.31162999999999,38.134761],"type":"Point"}
}