{
  "type": "Feature",
  "properties": {
    "addr:full":"3030 N Maroa Ave Fresno CA 93704",
    "addr:housenumber":"3030",
    "addr:postcode":"93704",
    "addr:street":"N Maroa Ave",
    "iso:country":"US",
    "sg:address":"3030 N Maroa Ave",
    "sg:city":"Fresno",
    "sg:classifiers":[
        {
            "category":"Professional",
            "subcategory":"Advertising",
            "type":"Services"
        }
    ],
    "sg:phone":"+1 559 222 8705",
    "sg:postcode":"93704",
    "sg:province":"CA",
    "wof:name":"A Champion Advertising Special",
    "wof:placetype":"venue"
},
  "geometry": {"coordinates":[-119.79953,36.77828],"type":"Point"}
}