{
  "type": "Feature",
  "properties": {
    "addr:full":"5437 Sunrise Blvd Citrus Heights CA 95610",
    "addr:housenumber":"5437",
    "addr:postcode":"95610",
    "addr:street":"Sunrise Blvd",
    "iso:country":"US",
    "sg:address":"5437 Sunrise Blvd",
    "sg:city":"Citrus Heights",
    "sg:classifiers":[
        {
            "category":"Restaurant",
            "type":"Food & Drink"
        }
    ],
    "sg:phone":"+1 916 965 0770",
    "sg:postcode":"95610",
    "sg:province":"CA",
    "wof:name":"Teriyaki To Go",
    "wof:placetype":"venue"
},
  "geometry": {"coordinates":[-121.272003,38.6646],"type":"Point"}
}