{
  "type": "Feature",
  "properties": {
    "iso:country":"US",
    "sg:address":"1348 el Camino Real",
    "sg:city":"San Carlos",
    "sg:classifiers":[
        {
            "category":"Shopping",
            "subcategory":"Bicycles & Sporting Goods",
            "type":"Retail Goods"
        }
    ],
    "sg:phone":"+1 650 591 2210",
    "sg:postcode":"94070",
    "sg:province":"CA",
    "wof:name":"Velo Club San Carlos",
    "wof:placetype":"venue"
},
  "geometry": {"coordinates":[-122.248938,37.497652],"type":"Point"}
}