{
  "type": "Feature",
  "properties": {
    "iso:country":"US",
    "sg:address":"1098 San Mateo Ave Ste 4",
    "sg:city":"South San Francisco",
    "sg:classifiers":[
        {
            "category":"Building & Trades",
            "subcategory":"Construction",
            "type":"Services"
        }
    ],
    "sg:phone":"+1 650 583 4352",
    "sg:postcode":"94080",
    "sg:province":"CA",
    "sg:tags":[
        "interior",
        "design"
    ],
    "wof:name":"International Upholstery",
    "wof:placetype":"venue"
},
  "geometry": {"coordinates":[-122.41086300000001,37.636954],"type":"Point"}
}