{
  "type": "Feature",
  "properties": {
    "addr:full":"24266 Lyons Ave Newhall CA 91321",
    "addr:housenumber":"24266",
    "addr:postcode":"91321",
    "addr:street":"Lyons Ave",
    "iso:country":"US",
    "sg:address":"24266 Lyons Ave",
    "sg:city":"Newhall",
    "sg:classifiers":[
        {
            "category":"Bakery",
            "type":"Food & Drink"
        }
    ],
    "sg:phone":"+1 661 255 8007",
    "sg:postcode":"91321",
    "sg:province":"CA",
    "wof:name":"S & S Donuts",
    "wof:placetype":"venue"
},
  "geometry": {"coordinates":[-118.560997,34.378502],"type":"Point"}
}