{
  "type": "Feature",
  "properties": {
    "addr:full":"35622 Balsamina Ct Temecula CA 92592",
    "addr:postcode":"35622;92592",
    "addr:street":"Balsamina Ct",
    "iso:country":"US",
    "sg:address":"35622 Balsamina Ct",
    "sg:city":"Temecula",
    "sg:classifiers":[
        {
            "category":"Building & Trades",
            "subcategory":"Construction",
            "type":"Services"
        }
    ],
    "sg:phone":"+1 951 676 1069",
    "sg:postcode":"92592",
    "sg:province":"CA",
    "sg:tags":[
        "resurfacing",
        "laying",
        "refinishing",
        "floor"
    ],
    "wof:name":"R J Hardwood Flooring",
    "wof:placetype":"venue"
},
  "geometry": {"coordinates":[-117.037842,33.549137],"type":"Point"}
}