{
  "type": "Feature",
  "properties": {
    "addr:full":"2175 Lemoyne St Los Angeles CA 90026",
    "addr:housenumber":"2175",
    "addr:postcode":"90026",
    "addr:street":"Lemoyne St",
    "iso:country":"US",
    "sg:address":"2175 Lemoyne St",
    "sg:city":"Los Angeles",
    "sg:classifiers":[
        {
            "category":"Manufacturing",
            "subcategory":"Printing",
            "type":"Manufacturing & Wholesale Goods"
        }
    ],
    "sg:phone":"+1 323 644 3700",
    "sg:postcode":"90026",
    "sg:province":"CA",
    "sg:tags":[
        "multimedia"
    ],
    "sg:website":"www.kmediarelations.com",
    "wof:name":"K Media Relations",
    "wof:placetype":"venue"
},
  "geometry": {"coordinates":[-118.25218,34.090959],"type":"Point"}
}