{
  "type": "Feature",
  "properties": {
    "addr:full":"5735 E La Palma Ave Anaheim CA 92807",
    "addr:housenumber":"5735",
    "addr:postcode":"92807",
    "addr:street":"E La Palma Ave",
    "iso:country":"US",
    "sg:address":"5735 E La Palma Ave",
    "sg:city":"Anaheim",
    "sg:classifiers":[
        {
            "category":"Shopping",
            "subcategory":"Pharmacy",
            "type":"Retail Goods"
        }
    ],
    "sg:phone":"+1 714 779 2483",
    "sg:postcode":"92807",
    "sg:province":"CA",
    "sg:tags":[
        "drugstore"
    ],
    "sg:website":"www.cvs.com",
    "wof:name":"CVS pharmacy",
    "wof:placetype":"venue"
},
  "geometry": {"coordinates":[-117.78923899999999,33.859727],"type":"Point"}
}