{
  "type": "Feature",
  "properties": {
    "iso:country":"US",
    "sg:address":"125 W Westwood Ave",
    "sg:city":"Visalia",
    "sg:classifiers":[
        {
            "category":"Building & Trades",
            "subcategory":"Pest Control",
            "type":"Services"
        }
    ],
    "sg:phone":"+1 559 686 4109",
    "sg:postcode":"93277",
    "sg:province":"CA",
    "wof:name":"Dairymen's Pest Control",
    "wof:placetype":"venue"
},
  "geometry": {"coordinates":[-119.293278,36.300443],"type":"Point"}
}