{
  "type": "Feature",
  "properties": {
    "iso:country":"US",
    "sg:address":"112 Huntington Dr",
    "sg:city":"Vacaville",
    "sg:classifiers":[
        {
            "category":"Professional",
            "subcategory":"Management & Consulting",
            "type":"Services"
        }
    ],
    "sg:phone":"+1 707 449 9249",
    "sg:postcode":"95687",
    "sg:province":"CA",
    "sg:tags":[
        "food",
        "coffee"
    ],
    "sg:website":"www.cheftogocatering.com",
    "wof:name":"Chef To Go",
    "wof:placetype":"venue"
},
  "geometry": {"coordinates":[-121.956884,38.346973],"type":"Point"}
}