{
  "type": "Feature",
  "properties": {
    "addr:full":"14 W Court St Woodland CA 95695",
    "addr:housenumber":"14",
    "addr:postcode":"95695",
    "addr:street":"W Court St",
    "iso:country":"US",
    "sg:address":"14 W Court St",
    "sg:city":"Woodland",
    "sg:classifiers":[
        {
            "category":"Restaurant",
            "type":"Food & Drink"
        }
    ],
    "sg:phone":"+1 530 666 1210",
    "sg:postcode":"95695",
    "sg:province":"CA",
    "wof:name":"China Smorgi Restaurant",
    "wof:placetype":"venue"
},
  "geometry": {"coordinates":[-121.788145,38.678937],"type":"Point"}
}