{
  "type": "Feature",
  "properties": {
    "iso:country":"US",
    "sg:address":"2030 Addison St",
    "sg:city":"Berkeley",
    "sg:classifiers":[
        {
            "category":"Professional",
            "subcategory":"Employment Agencies",
            "type":"Services"
        }
    ],
    "sg:phone":"+1 510 549 4900",
    "sg:postcode":"94704",
    "sg:province":"CA",
    "sg:tags":[
        "opportunity"
    ],
    "wof:name":"Remedy Intelligent Staffing",
    "wof:placetype":"venue"
},
  "geometry": {"coordinates":[-122.26902,37.871004],"type":"Point"}
}