{
  "type": "Feature",
  "properties": {
    "iso:country":"US",
    "sg:address":"5789 E Shields Ave",
    "sg:city":"Fresno",
    "sg:classifiers":[
        {
            "category":"Shopping",
            "subcategory":"Computers & Home Electronics",
            "type":"Retail Goods"
        }
    ],
    "sg:phone":"+1 559 348 0184",
    "sg:postcode":"93727",
    "sg:province":"CA",
    "sg:tags":[
        "television",
        "radio"
    ],
    "wof:name":"Allied Television Svc",
    "wof:placetype":"venue"
},
  "geometry": {"coordinates":[-119.691029,36.779469],"type":"Point"}
}