{
  "type": "Feature",
  "properties": {
    "iso:country":"US",
    "sg:address":"2424 W Victory Blvd",
    "sg:city":"Burbank",
    "sg:classifiers":[
        {
            "category":"Recreation",
            "subcategory":"Playground",
            "type":"Entertainment"
        }
    ],
    "sg:phone":"+1 818 567 9945",
    "sg:postcode":"91506",
    "sg:province":"CA",
    "sg:website":"www.undertheseaindoorplayground.com",
    "wof:name":"Under the Sea Indoor Playground",
    "wof:placetype":"venue"
},
  "geometry": {"coordinates":[-118.338413,34.184576],"type":"Point"}
}