{
  "type": "Feature",
  "properties": {
    "iso:country":"US",
    "sg:address":"275 S Laurel St",
    "sg:city":"Ventura",
    "sg:classifiers":[
        {
            "category":"Professional",
            "subcategory":"Employment Agencies",
            "type":"Services"
        }
    ],
    "sg:phone":"+1 805 653 6004",
    "sg:postcode":"93001",
    "sg:province":"CA",
    "sg:tags":[
        "consultant",
        "search",
        "executive"
    ],
    "wof:name":"CGS Executive Search",
    "wof:placetype":"venue"
},
  "geometry": {"coordinates":[-119.285507,34.277868],"type":"Point"}
}