{
  "type": "Feature",
  "properties": {
    "addr:full":"1241 S Petit Ave Ventura CA 93004",
    "addr:housenumber":"1241",
    "addr:postcode":"93004",
    "addr:street":"S Petit Ave",
    "iso:country":"US",
    "sg:address":"1241 S Petit Ave",
    "sg:city":"Ventura",
    "sg:classifiers":[
        {
            "category":"Real Estate",
            "subcategory":"Real Estate Operator",
            "type":"Services"
        }
    ],
    "sg:phone":"+1 805 647 6680",
    "sg:postcode":"93004",
    "sg:province":"CA",
    "sg:tags":[
        "apartment"
    ],
    "wof:name":"Ventura Pines Apartments",
    "wof:placetype":"venue"
},
  "geometry": {"coordinates":[-119.170383,34.272114],"type":"Point"}
}