{
  "type": "Feature",
  "properties": {
    "iso:country":"US",
    "sg:address":"1166 Geneva Ave",
    "sg:city":"San Francisco",
    "sg:classifiers":[
        {
            "category":"Restaurant",
            "type":"Food & Drink"
        }
    ],
    "sg:phone":"+1 415 586 7000",
    "sg:postcode":"94112",
    "sg:province":"CA",
    "sg:tags":[
        "grocery",
        "eating"
    ],
    "wof:name":"Mom Is Cooking",
    "wof:placetype":"venue"
},
  "geometry": {"coordinates":[-122.436488,37.714222],"type":"Point"}
}