{
  "type": "Feature",
  "properties": {
    "addr:full":"23663 Rockfield Blvd Lake Forest CA 92630",
    "addr:housenumber":"23663",
    "addr:postcode":"92630",
    "addr:street":"Rockfield Blvd",
    "iso:country":"US",
    "sg:address":"23663 Rockfield Blvd",
    "sg:city":"Lake Forest",
    "sg:classifiers":[
        {
            "category":"Retail",
            "subcategory":"Auto Repair",
            "type":"Services"
        }
    ],
    "sg:phone":"+1 949 452 0100",
    "sg:postcode":"92630",
    "sg:province":"CA",
    "sg:tags":[
        "repairing",
        "automobile"
    ],
    "wof:name":"Mercedes Auto Svc",
    "wof:placetype":"venue"
},
  "geometry": {"coordinates":[-117.717945,33.630511],"type":"Point"}
}