{
  "type": "Feature",
  "properties": {
    "iso:country":"US",
    "sg:address":"1130 Burnett Ave",
    "sg:city":"Concord",
    "sg:classifiers":[
        {
            "category":"Manufacturing",
            "subcategory":"Metals",
            "type":"Manufacturing & Wholesale Goods"
        }
    ],
    "sg:phone":"+1 925 374 0173",
    "sg:postcode":"94520",
    "sg:province":"CA",
    "sg:tags":[
        "cable"
    ],
    "wof:name":"Cable Manufacturing Technlgies",
    "wof:placetype":"venue"
},
  "geometry": {"coordinates":[-122.05541599999999,37.97815],"type":"Point"}
}