{
  "type": "Feature",
  "properties": {
    "iso:country":"US",
    "sg:address":"11323 Stewart St",
    "sg:city":"El Monte",
    "sg:classifiers":[
        {
            "category":"Manufacturing",
            "subcategory":"Metals",
            "type":"Manufacturing & Wholesale Goods"
        }
    ],
    "sg:phone":"+1 626 350 3155",
    "sg:postcode":"91731",
    "sg:province":"CA",
    "sg:tags":[
        "mfg",
        "spring",
        "industrial",
        "wire",
        "supply"
    ],
    "wof:name":"Pacific Coils",
    "wof:placetype":"venue"
},
  "geometry": {"coordinates":[-118.02582099999999,34.071831],"type":"Point"}
}