{
  "type": "Feature",
  "properties": {
    "addr:full":"45 E. Julian Street San Jose CA 95112",
    "addr:housenumber":"45",
    "addr:postcode":"95112",
    "addr:street":"E. Julian Street",
    "iso:country":"US",
    "sg:address":"45 E. Julian Street",
    "sg:city":"San Jose",
    "sg:classifiers":[
        {
            "category":"Professional",
            "subcategory":"Lawyer & Legal Services",
            "type":"Services"
        }
    ],
    "sg:phone":"+1 408 286 2808",
    "sg:postcode":"95112",
    "sg:province":"CA",
    "sg:website":"www.tmasonlaw.com",
    "wof:name":"Law Office of Traci S. Mason",
    "wof:placetype":"venue"
},
  "geometry": {"coordinates":[-121.893111,37.341098],"type":"Point"}
}