{
  "type": "Feature",
  "properties": {
    "iso:country":"US",
    "sg:address":"410 W Main St",
    "sg:city":"Merced",
    "sg:classifiers":[
        {
            "category":"Health Services",
            "subcategory":"Hospice",
            "type":"Services"
        },
        {
            "category":"Social Services",
            "subcategory":"Retirement Home",
            "type":"Services"
        }
    ],
    "sg:phone":"+1 209 383 3123",
    "sg:postcode":"95340",
    "sg:province":"CA",
    "sg:tags":[
        "convalescent",
        "nursing"
    ],
    "wof:name":"Hinds Hospice",
    "wof:placetype":"venue"
},
  "geometry": {"coordinates":[-120.48197999999999,37.300926],"type":"Point"}
}