{
  "type": "Feature",
  "properties": {
    "iso:country":"US",
    "sg:address":"368 7th Ave",
    "sg:city":"San Francisco",
    "sg:classifiers":[
        {
            "category":"Shopping",
            "subcategory":"Gifts & Souvenirs",
            "type":"Retail Goods"
        }
    ],
    "sg:phone":"+1 415 666 3826",
    "sg:postcode":"94118",
    "sg:province":"CA",
    "sg:tags":[
        "shop"
    ],
    "wof:name":"Gifts & Bytes",
    "wof:placetype":"venue"
},
  "geometry": {"coordinates":[-122.465354,37.782305],"type":"Point"}
}