{
  "type": "Feature",
  "properties": {
    "iso:country":"US",
    "sg:address":"2366 E. Foothill Blvd.",
    "sg:city":"Pasadena",
    "sg:classifiers":[
        {
            "category":"Banks & Credit Unions",
            "subcategory":"Bureau De Change",
            "type":"Services"
        },
        {
            "category":"Professional",
            "subcategory":"Advertising",
            "type":"Services"
        },
        {
            "category":"Retail",
            "subcategory":"Repair Shop",
            "type":"Services"
        },
        {
            "category":"Professional",
            "subcategory":"Printing & Photocopies",
            "type":"Services"
        },
        {
            "category":"Manufacturing",
            "subcategory":"Signs",
            "type":"Manufacturing & Wholesale Goods"
        }
    ],
    "sg:phone":"+1 626 262 7055",
    "sg:postcode":"91107",
    "sg:province":"CA",
    "sg:tags":[
        "business",
        "marketing",
        "screen",
        "signs-maintenance",
        "internet",
        "card"
    ],
    "sg:website":"http://www.ablazepromotions.com",
    "wof:name":"Ablaze Promotions",
    "wof:placetype":"venue"
},
  "geometry": {"coordinates":[-118.101525,34.149672],"type":"Point"}
}