{
  "type": "Feature",
  "properties": {
    "iso:country":"US",
    "sg:address":"1240 Keystone Way",
    "sg:city":"Vista",
    "sg:classifiers":[
        {
            "category":"Manufacturing",
            "subcategory":"Chemicals & Compounds",
            "type":"Manufacturing & Wholesale Goods"
        }
    ],
    "sg:phone":"+1 760 598 5858",
    "sg:postcode":"92081",
    "sg:province":"CA",
    "sg:tags":[
        "preparation",
        "pharmaceutical",
        "mfg"
    ],
    "wof:name":"Superlife International",
    "wof:placetype":"venue"
},
  "geometry": {"coordinates":[-117.23157,33.136099],"type":"Point"}
}