{
  "type": "Feature",
  "properties": {
    "addr:full":"1622 Emerald St San Diego CA 92109",
    "addr:housenumber":"1622",
    "addr:postcode":"92109",
    "addr:street":"Emerald St",
    "iso:country":"US",
    "sg:address":"1622 Emerald St",
    "sg:city":"San Diego",
    "sg:classifiers":[
        {
            "category":"Communications",
            "subcategory":"Newspaper",
            "type":"Services"
        },
        {
            "category":"Professional",
            "subcategory":"Art Services",
            "type":"Services"
        },
        {
            "category":"Communications",
            "type":"Services"
        }
    ],
    "sg:phone":"+1 858 444 5787",
    "sg:postcode":"92109",
    "sg:province":"CA",
    "sg:tags":[
        "web",
        "graphic",
        "design",
        "advertising"
    ],
    "sg:website":"www.digitalrokket.com",
    "wof:name":"Digital Rokket",
    "wof:placetype":"venue"
},
  "geometry": {"coordinates":[-117.240773,32.801835],"type":"Point"}
}