{
  "type": "Feature",
  "properties": {
    "addr:full":"1410 Beltline Rd Redding CA 96003",
    "addr:housenumber":"1410",
    "addr:postcode":"96003",
    "addr:street":"Beltline Rd",
    "iso:country":"US",
    "sg:address":"1410 Beltline Rd",
    "sg:city":"Redding",
    "sg:classifiers":[
        {
            "category":"Retail",
            "subcategory":"Auto Repair",
            "type":"Services"
        }
    ],
    "sg:phone":"+1 530 247 1549",
    "sg:postcode":"96003",
    "sg:province":"CA",
    "sg:tags":[
        "truck"
    ],
    "wof:name":"Ramirez Truck Repair",
    "wof:placetype":"venue"
},
  "geometry": {"coordinates":[-122.388655,40.62658],"type":"Point"}
}