{
  "type": "Feature",
  "properties": {
    "addr:full":"1040 E Plymouth Way Fresno CA 93720",
    "addr:housenumber":"1040",
    "addr:postcode":"93720",
    "addr:street":"E Plymouth Way",
    "iso:country":"US",
    "sg:address":"1040 E Plymouth Way",
    "sg:city":"Fresno",
    "sg:classifiers":[
        {
            "category":"Education",
            "subcategory":"Special Training",
            "type":"Public Place"
        }
    ],
    "sg:phone":"+1 559 434 6673",
    "sg:postcode":"93720",
    "sg:province":"CA",
    "sg:tags":[
        "instruction",
        "music"
    ],
    "wof:name":"Rhodus Vocal Arts Studios",
    "wof:placetype":"venue"
},
  "geometry": {"coordinates":[-119.763249,36.877422],"type":"Point"}
}