{
  "type": "Feature",
  "properties": {
    "iso:country":"US",
    "sg:address":"23642 Via Potes",
    "sg:city":"Mission Viejo",
    "sg:classifiers":[
        {
            "category":"Building & Trades",
            "subcategory":"Landscaping Services",
            "type":"Services"
        }
    ],
    "sg:phone":"+1 949 859 2416",
    "sg:postcode":"92691",
    "sg:province":"CA",
    "sg:tags":[
        "landscape"
    ],
    "wof:name":"Green World Landscape Design",
    "wof:placetype":"venue"
},
  "geometry": {"coordinates":[-117.658115,33.618833],"type":"Point"}
}