{
  "type": "Feature",
  "properties": {
    "iso:country":"US",
    "sg:address":"4342 Geer Rd",
    "sg:city":"Hughson",
    "sg:classifiers":[
        {
            "category":"Food & Beverages",
            "subcategory":"Bakery",
            "type":"Retail Goods"
        }
    ],
    "sg:phone":"+1 209 883 0100",
    "sg:postcode":"95326",
    "sg:province":"CA",
    "sg:tags":[
        "baker"
    ],
    "wof:name":"Resendiz Family Fruit Barn",
    "wof:placetype":"venue"
},
  "geometry": {"coordinates":[-120.847003,37.579134],"type":"Point"}
}