{
  "type": "Feature",
  "properties": {
    "iso:country":"US",
    "sg:address":"150 Evergreen Lane",
    "sg:city":"Berkeley",
    "sg:classifiers":[
        {
            "category":"Restaurant",
            "type":"Food & Drink"
        },
        {
            "category":"Recreation",
            "type":"Entertainment"
        }
    ],
    "sg:postcode":"94705",
    "sg:province":"CA",
    "sg:tags":[
        "flavor",
        "local",
        "hiking"
    ],
    "sg:website":"ccconservancy.homestead.com/Garb...",
    "wof:name":"Garber Park",
    "wof:placetype":"venue"
},
  "geometry": {"coordinates":[-122.23868299999999,37.860903],"type":"Point"}
}