{
  "type": "Feature",
  "properties": {
    "iso:country":"US",
    "sg:address":"46 Mariposa Ave",
    "sg:city":"Watsonville",
    "sg:classifiers":[
        {
            "category":"Shopping",
            "subcategory":"Florist",
            "type":"Retail Goods"
        }
    ],
    "sg:phone":"+1 831 763 2758",
    "sg:postcode":"95076",
    "sg:province":"CA",
    "wof:name":"Perry's Floral",
    "wof:placetype":"venue"
},
  "geometry": {"coordinates":[-121.76827900000001,36.928175],"type":"Point"}
}