{
  "type": "Feature",
  "properties": {
    "iso:country":"US",
    "sg:address":"5521 Reseda Blvd",
    "sg:city":"Tarzana",
    "sg:classifiers":[
        {
            "category":"Real Estate",
            "subcategory":"Real Estate Agent",
            "type":"Services"
        }
    ],
    "sg:phone":"+1 818 776 9922",
    "sg:postcode":"91356",
    "sg:province":"CA",
    "wof:name":"Mohammad Forourtan Real Estate",
    "wof:placetype":"venue"
},
  "geometry": {"coordinates":[-118.53607599999999,34.172252],"type":"Point"}
}