{
  "type": "Feature",
  "properties": {
    "addr:full":"5520 E Vis del Dia Anaheim CA 92807",
    "addr:housenumber":"5520",
    "addr:postcode":"92807",
    "addr:street":"E Vis Del Dia",
    "iso:country":"US",
    "sg:address":"5520 E Vis del Dia",
    "sg:city":"Anaheim",
    "sg:classifiers":[
        {
            "category":"Professional",
            "type":"Services"
        }
    ],
    "sg:phone":"+1 714 590 1515",
    "sg:postcode":"92807",
    "sg:province":"CA",
    "wof:name":"Armen Oganessian",
    "wof:placetype":"venue"
},
  "geometry": {"coordinates":[-117.79412499999999,33.847533],"type":"Point"}
}