{
  "type": "Feature",
  "properties": {
    "iso:country":"US",
    "sg:address":"8385 Ave 320",
    "sg:city":"Visalia",
    "sg:classifiers":[
        {
            "category":"Professional",
            "type":"Services"
        }
    ],
    "sg:phone":"+1 559 733 9665",
    "sg:postcode":"93291",
    "sg:province":"CA",
    "wof:name":"Sanchez Lupe",
    "wof:placetype":"venue"
},
  "geometry": {"coordinates":[-119.392788,36.370777],"type":"Point"}
}