{
  "type": "Feature",
  "properties": {
    "iso:country":"US",
    "sg:address":"10808 Washington Blvd",
    "sg:city":"Culver City",
    "sg:classifiers":[
        {
            "category":"Health Services",
            "subcategory":"Dentist",
            "type":"Services"
        }
    ],
    "sg:phone":"+1 310 839 6232",
    "sg:postcode":"90232",
    "sg:province":"CA",
    "wof:name":"Cox-Nakamura Kay DDS",
    "wof:placetype":"venue"
},
  "geometry": {"coordinates":[-118.407379,34.494262],"type":"Point"}
}