{
  "type": "Feature",
  "properties": {
    "addr:full":"3435 Camino Del Rio South Suite 212 San Diego CA 92108",
    "addr:housenumber":"3435",
    "addr:postcode":"92108",
    "addr:street":"Camino Del Rio South Suite 212",
    "iso:country":"US",
    "sg:address":"3435 Camino Del Rio South Suite 212",
    "sg:city":"San Diego",
    "sg:classifiers":[
        {
            "category":"Professional",
            "type":"Services"
        }
    ],
    "sg:phone":"+1 619 282 7596",
    "sg:postcode":"92108",
    "sg:province":"CA",
    "sg:website":"www.pinnacleacess.net",
    "wof:name":"Pinnacle Access",
    "wof:placetype":"venue"
},
  "geometry": {"coordinates":[-117.119784,32.776587],"type":"Point"}
}