{
  "type": "Feature",
  "properties": {
    "addr:full":"8205 Santa Monica Blvd West Hollywood CA 90046",
    "addr:housenumber":"8205",
    "addr:postcode":"90046",
    "addr:street":"Santa Monica Blvd",
    "iso:country":"US",
    "sg:address":"8205 Santa Monica Blvd",
    "sg:city":"West Hollywood",
    "sg:classifiers":[
        {
            "category":"Building & Trades",
            "subcategory":"Locksmith",
            "type":"Services"
        }
    ],
    "sg:phone":"+1 323 372 5230",
    "sg:postcode":"90046",
    "sg:province":"CA",
    "sg:tags":[
        "key"
    ],
    "wof:name":"Emergency Garage Doors and Gates",
    "wof:placetype":"venue"
},
  "geometry": {"coordinates":[-118.36759499999999,34.088425],"type":"Point"}
}