{
  "type": "Feature",
  "properties": {
    "addr:full":"9368 Stewart and Gray Rd Downey CA 90241",
    "addr:housenumber":"9368",
    "addr:postcode":"90241",
    "addr:street":"Stewart And Gray Rd",
    "iso:country":"US",
    "sg:address":"9368 Stewart and Gray Rd",
    "sg:city":"Downey",
    "sg:classifiers":[
        {
            "category":"Manufacturing",
            "subcategory":"Paper Products",
            "type":"Manufacturing & Wholesale Goods"
        }
    ],
    "sg:phone":"+1 562 803 4869",
    "sg:postcode":"90241",
    "sg:province":"CA",
    "sg:tags":[
        "plastic",
        "container",
        "cup"
    ],
    "wof:name":"Leadway Plastics Inc",
    "wof:placetype":"venue"
},
  "geometry": {"coordinates":[-118.11981400000001,33.927614],"type":"Point"}
}