{
  "type": "Feature",
  "properties": {
    "addr:full":"10850 Baroque Ln San Diego CA 92124",
    "addr:housenumber":"10850",
    "addr:postcode":"92124",
    "addr:street":"Baroque Ln",
    "iso:country":"US",
    "sg:address":"10850 Baroque Ln",
    "sg:city":"San Diego",
    "sg:classifiers":[
        {
            "category":"Health Services",
            "subcategory":"Doctor",
            "type":"Services"
        }
    ],
    "sg:phone":"+1 858 560 5685",
    "sg:postcode":"92124",
    "sg:province":"CA",
    "sg:tags":[
        "physician",
        "surgeon"
    ],
    "wof:name":"Edwin M Yorobe Inc",
    "wof:placetype":"venue"
},
  "geometry": {"coordinates":[-117.09828899999999,32.819314],"type":"Point"}
}