{
  "type": "Feature",
  "properties": {
    "addr:full":"211 Gough St Ste 205 San Francisco CA 94117",
    "addr:housenumber":"211",
    "addr:postcode":"94117",
    "addr:street":"Gough St Ste 205",
    "iso:country":"US",
    "sg:address":"211 Gough St Ste 205",
    "sg:city":"San Francisco",
    "sg:classifiers":[
        {
            "category":"Personal",
            "subcategory":"Massage",
            "type":"Services"
        }
    ],
    "sg:phone":"+1 917 769 4838",
    "sg:postcode":"94117",
    "sg:province":"CA",
    "sg:website":"www.naomiskoglund.massagetherapy...",
    "wof:name":"Naomi Skoglund, CMT",
    "wof:placetype":"venue"
},
  "geometry": {"coordinates":[-122.422832,37.775315],"type":"Point"}
}