{
  "type": "Feature",
  "properties": {
    "addr:full":"331 Nut Tree Rd Vacaville CA 95687",
    "addr:housenumber":"331",
    "addr:postcode":"95687",
    "addr:street":"Nut Tree Rd",
    "iso:country":"US",
    "sg:address":"331 Nut Tree Rd",
    "sg:city":"Vacaville",
    "sg:classifiers":[
        {
            "category":"Shopping",
            "subcategory":"Clothing, Apparel, & Fashions",
            "type":"Retail Goods"
        }
    ],
    "sg:phone":"+1 707 451 9075",
    "sg:postcode":"95687",
    "sg:province":"CA",
    "sg:tags":[
        "umbrella"
    ],
    "wof:name":"Totes Isotoner",
    "wof:placetype":"venue"
},
  "geometry": {"coordinates":[-121.953288,38.365084],"type":"Point"}
}