{
  "type": "Feature",
  "properties": {
    "addr:full":"13459 Franceska Rd Apple Valley CA 92308",
    "addr:housenumber":"13459",
    "addr:postcode":"92308",
    "addr:street":"Franceska Rd",
    "iso:country":"US",
    "sg:address":"13459 Franceska Rd",
    "sg:city":"Apple Valley",
    "sg:classifiers":[
        {
            "category":"Building & Trades",
            "subcategory":"Construction",
            "type":"Services"
        }
    ],
    "sg:phone":"+1 760 961 0775",
    "sg:postcode":"92308",
    "sg:province":"CA",
    "sg:tags":[
        "painter"
    ],
    "wof:name":"Nuno Painting",
    "wof:placetype":"venue"
},
  "geometry": {"coordinates":[-117.160831,34.496055],"type":"Point"}
}