{
  "type": "Feature",
  "properties": {
    "iso:country":"US",
    "sg:address":"42057 3rd St E",
    "sg:city":"Lancaster",
    "sg:classifiers":[
        {
            "category":"Wholesale",
            "subcategory":"Farm Supplies",
            "type":"Manufacturing & Wholesale Goods"
        }
    ],
    "sg:phone":"+1 661 942 3992",
    "sg:postcode":"93535",
    "sg:province":"CA",
    "sg:tags":[
        "bulk",
        "material",
        "landscape"
    ],
    "wof:name":"California Quarry Products",
    "wof:placetype":"venue"
},
  "geometry": {"coordinates":[-118.125494,34.646904],"type":"Point"}
}