{
  "type": "Feature",
  "properties": {
    "iso:country":"US",
    "sg:address":"26246 Monterey Ln",
    "sg:city":"Laguna Hills",
    "sg:classifiers":[
        {
            "category":"Professional",
            "subcategory":"Business Services",
            "type":"Services"
        }
    ],
    "sg:phone":"+1 949 295 1829",
    "sg:postcode":"92653",
    "sg:province":"CA",
    "sg:tags":[
        "pool",
        "swimming"
    ],
    "wof:name":"Crystal Clear Pool & Spa Svc",
    "wof:placetype":"venue"
},
  "geometry": {"coordinates":[-117.702392,33.581866],"type":"Point"}
}