{
  "type": "Feature",
  "properties": {
    "addr:full":"717 Market St San Francisco CA 94103",
    "addr:housenumber":"717",
    "addr:postcode":"94103",
    "addr:street":"Market St",
    "iso:country":"US",
    "sg:address":"717 Market St",
    "sg:city":"San Francisco",
    "sg:classifiers":[
        {
            "category":"Insurance",
            "subcategory":"Hazard Insurance",
            "type":"Services"
        }
    ],
    "sg:phone":"+1 415 243 2314",
    "sg:postcode":"94103",
    "sg:province":"CA",
    "sg:tags":[
        "carrier",
        "surety"
    ],
    "wof:name":"Carpenter & Moore Insur Svcs",
    "wof:placetype":"venue"
},
  "geometry": {"coordinates":[-122.404177,37.786947],"type":"Point"}
}