{
  "type": "Feature",
  "properties": {
    "addr:full":"200 W Taylor St San Jose CA 95110",
    "addr:housenumber":"200",
    "addr:postcode":"95110",
    "addr:street":"W Taylor St",
    "iso:country":"US",
    "sg:address":"200 W Taylor St",
    "sg:city":"San Jose",
    "sg:classifiers":[
        {
            "category":"Banks & Credit Unions",
            "subcategory":"Bank",
            "type":"Services"
        }
    ],
    "sg:phone":"+1 408 286 3334",
    "sg:postcode":"95110",
    "sg:province":"CA",
    "wof:name":"Citibank",
    "wof:placetype":"venue"
},
  "geometry": {"coordinates":[-121.902764,37.347582],"type":"Point"}
}