{
  "type": "Feature",
  "properties": {
    "iso:country":"US",
    "sg:address":"3090 Benham St",
    "sg:city":"Placerville",
    "sg:classifiers":[
        {
            "category":"Organizations",
            "subcategory":"Religious Organization",
            "type":"Services"
        }
    ],
    "sg:phone":"+1 530 622 7692",
    "sg:postcode":"95667",
    "sg:province":"CA",
    "sg:tags":[
        "church"
    ],
    "wof:name":"St Patrick Faith Formation Ofc",
    "wof:placetype":"venue"
},
  "geometry": {"coordinates":[-120.80163,38.724637],"type":"Point"}
}