{
  "type": "Feature",
  "properties": {
    "addr:full":"901 Dove Street Newport Beach CA 92660",
    "addr:housenumber":"901",
    "addr:postcode":"92660",
    "addr:street":"Dove Street",
    "iso:country":"US",
    "sg:address":"901 Dove Street",
    "sg:city":"Newport Beach",
    "sg:classifiers":[
        {
            "category":"Professional",
            "subcategory":"Lawyer & Legal Services",
            "type":"Services"
        }
    ],
    "sg:phone":"+1 949 752 2727",
    "sg:postcode":"92660",
    "sg:province":"CA",
    "sg:tags":[
        "divorce",
        "law",
        "family"
    ],
    "wof:name":"Lcsw",
    "wof:placetype":"venue"
},
  "geometry": {"coordinates":[-117.864597,33.658155],"type":"Point"}
}