{
  "type": "Feature",
  "properties": {
    "addr:full":"104 S Francisca Ave Redondo Beach CA 90277",
    "addr:housenumber":"104",
    "addr:postcode":"90277",
    "addr:street":"S Francisca Ave",
    "iso:country":"US",
    "sg:address":"104 S Francisca Ave",
    "sg:city":"Redondo Beach",
    "sg:classifiers":[
        {
            "category":"Professional",
            "type":"Services"
        }
    ],
    "sg:phone":"+1 310 542 8850",
    "sg:postcode":"90277",
    "sg:province":"CA",
    "wof:name":"Keepsakes By Janie",
    "wof:placetype":"venue"
},
  "geometry": {"coordinates":[-118.384272,33.840347],"type":"Point"}
}