{
  "type": "Feature",
  "properties": {
    "iso:country":"US",
    "sg:address":"4534 N Sharon Ave",
    "sg:city":"Fresno",
    "sg:classifiers":[
        {
            "category":"Building & Trades",
            "subcategory":"Pest Control",
            "type":"Services"
        }
    ],
    "sg:phone":"+1 559 224 8553",
    "sg:postcode":"93726",
    "sg:province":"CA",
    "wof:name":"Big Foot Pest Control",
    "wof:placetype":"venue"
},
  "geometry": {"coordinates":[-119.756485,36.800082],"type":"Point"}
}