{
  "type": "Feature",
  "properties": {
    "addr:full":"7594 Indiana Ave Riverside CA 92504",
    "addr:housenumber":"7594",
    "addr:postcode":"92504",
    "addr:street":"Indiana Ave",
    "iso:country":"US",
    "sg:address":"7594 Indiana Ave",
    "sg:city":"Riverside",
    "sg:classifiers":[
        {
            "category":"Restaurant",
            "type":"Food & Drink"
        }
    ],
    "sg:phone":"+1 951 689 1806",
    "sg:postcode":"92504",
    "sg:province":"CA",
    "sg:tags":[
        "shop",
        "coffee"
    ],
    "wof:name":"Cruzin Java Inc",
    "wof:placetype":"venue"
},
  "geometry": {"coordinates":[-117.40485,33.934842],"type":"Point"}
}