{
  "type": "Feature",
  "properties": {
    "addr:full":"4471 Santa Ana St Ontario CA 91761",
    "addr:housenumber":"4471",
    "addr:postcode":"91761",
    "addr:street":"Santa Ana St",
    "iso:country":"US",
    "sg:address":"4471 Santa Ana St",
    "sg:city":"Ontario",
    "sg:classifiers":[
        {
            "category":"Wholesale",
            "subcategory":"Construction Materials",
            "type":"Manufacturing & Wholesale Goods"
        }
    ],
    "sg:phone":"+1 909 605 0501",
    "sg:postcode":"91761",
    "sg:province":"CA",
    "sg:tags":[
        "machinery",
        "mfg"
    ],
    "wof:name":"Conac",
    "wof:placetype":"venue"
},
  "geometry": {"coordinates":[-117.557654,34.055566],"type":"Point"}
}