{
  "type": "Feature",
  "properties": {
    "iso:country":"US",
    "sg:address":"2735 W Pacific Coast Hwy",
    "sg:city":"Newport Beach",
    "sg:classifiers":[
        {
            "category":"Restaurant",
            "type":"Food & Drink"
        }
    ],
    "sg:phone":"+1 949 642 3431",
    "sg:postcode":"92663",
    "sg:province":"CA",
    "sg:tags":[
        "seafood"
    ],
    "sg:website":"www.rustypelican.com",
    "wof:name":"Rusty Pelican",
    "wof:placetype":"venue"
},
  "geometry": {"coordinates":[-117.923905,33.620098],"type":"Point"}
}