{
  "type": "Feature",
  "properties": {
    "iso:country":"US",
    "sg:address":"2900 Gordon Ave",
    "sg:city":"Santa Clara",
    "sg:classifiers":[
        {
            "category":"Professional",
            "subcategory":"Engineering",
            "type":"Services"
        }
    ],
    "sg:phone":"+1 408 530 8030",
    "sg:postcode":"95051",
    "sg:province":"CA",
    "sg:tags":[
        "engineer"
    ],
    "wof:name":"QSSR",
    "wof:placetype":"venue"
},
  "geometry": {"coordinates":[-121.99473,37.373979],"type":"Point"}
}