{
  "type": "Feature",
  "properties": {
    "iso:country":"US",
    "sg:address":"4776 El Cajon Boulevard Suite 105",
    "sg:city":"San Diego",
    "sg:classifiers":[
        {
            "category":"Shopping",
            "subcategory":"Pharmacy",
            "type":"Retail Goods"
        }
    ],
    "sg:phone":"+1 619 287 1206",
    "sg:postcode":"92115",
    "sg:province":"CA",
    "sg:tags":[
        "drugstore"
    ],
    "wof:name":"Dawn Pharmacy United Drugs",
    "wof:placetype":"venue"
},
  "geometry": {"coordinates":[-117.09147400000001,32.756207],"type":"Point"}
}