{
  "type": "Feature",
  "properties": {
    "iso:country":"US",
    "sg:address":"308 S Los Angeles St",
    "sg:city":"Los Angeles",
    "sg:classifiers":[
        {
            "category":"Communications",
            "type":"Services"
        }
    ],
    "sg:phone":"+1 213 621 4090",
    "sg:postcode":"90013",
    "sg:province":"CA",
    "wof:name":"Santulli Communications",
    "wof:placetype":"venue"
},
  "geometry": {"coordinates":[-118.2452,34.047935],"type":"Point"}
}