{
  "type": "Feature",
  "properties": {
    "iso:country":"US",
    "sg:address":"79 E Daily Dr",
    "sg:city":"Camarillo",
    "sg:classifiers":[
        {
            "category":"Professional",
            "subcategory":"Employment Agencies",
            "type":"Services"
        }
    ],
    "sg:phone":"+1 805 389 3663",
    "sg:postcode":"93010",
    "sg:province":"CA",
    "wof:name":"Whalen Bryan Inc Legal Placement",
    "wof:placetype":"venue"
},
  "geometry": {"coordinates":[-119.068366,34.221823],"type":"Point"}
}