{
  "type": "Feature",
  "properties": {
    "iso:country":"US",
    "sg:address":"10601 Calle Lee Suite 179",
    "sg:city":"Los Alamitos",
    "sg:classifiers":[
        {
            "category":"Utilities",
            "type":"Services"
        }
    ],
    "sg:phone":"+1 562 983 7880",
    "sg:postcode":"90720",
    "sg:province":"CA",
    "sg:tags":[
        "provider",
        "internet"
    ],
    "sg:website":"www.colorbroadband.com",
    "wof:name":"Color Broadband Communications",
    "wof:placetype":"venue"
},
  "geometry": {"coordinates":[-118.057659,33.808437],"type":"Point"}
}