{
  "type": "Feature",
  "properties": {
    "addr:full":"2580 S Bascom Ave Campbell CA 95124",
    "addr:housenumber":"2580",
    "addr:postcode":"95124",
    "addr:street":"S Bascom Ave",
    "iso:country":"US",
    "sg:address":"2580 S Bascom Ave",
    "sg:city":"Campbell",
    "sg:classifiers":[
        {
            "category":"Building & Trades",
            "subcategory":"Construction",
            "type":"Services"
        }
    ],
    "sg:phone":"+1 408 629 3231",
    "sg:postcode":"95124",
    "sg:province":"CA",
    "sg:tags":[
        "resurfacing",
        "laying",
        "refinishing",
        "floor"
    ],
    "wof:name":"Hardwood Floor Artist",
    "wof:placetype":"venue"
},
  "geometry": {"coordinates":[-121.93362399999999,37.274827],"type":"Point"}
}