{
  "type": "Feature",
  "properties": {
    "addr:full":"1065 E Walnut St Carson CA 90746",
    "addr:housenumber":"1065",
    "addr:postcode":"90746",
    "addr:street":"E Walnut St",
    "iso:country":"US",
    "sg:address":"1065 E Walnut St",
    "sg:city":"Carson",
    "sg:classifiers":[
        {
            "category":"Wholesale",
            "subcategory":"Fruits & Vegetables",
            "type":"Manufacturing & Wholesale Goods"
        }
    ],
    "sg:phone":"+1 310 884 3000",
    "sg:postcode":"90746",
    "sg:province":"CA",
    "sg:tags":[
        "veggie"
    ],
    "wof:name":"Fpd",
    "wof:placetype":"venue"
},
  "geometry": {"coordinates":[-118.25599699999999,33.875401],"type":"Point"}
}