{
  "type": "Feature",
  "properties": {
    "iso:country":"US",
    "sg:address":"472 S Mills Rd",
    "sg:city":"Ventura",
    "sg:classifiers":[
        {
            "category":"Banks & Credit Unions",
            "subcategory":"Bank",
            "type":"Services"
        }
    ],
    "sg:phone":"+1 805 000 1111",
    "sg:postcode":"93003",
    "sg:province":"CA",
    "wof:name":"Cal Fed",
    "wof:placetype":"venue"
},
  "geometry": {"coordinates":[-119.246686,34.268738],"type":"Point"}
}