{
  "type": "Feature",
  "properties": {
    "addr:full":"119 N San Vicente Blvd Beverly Hills CA 90211",
    "addr:housenumber":"119",
    "addr:postcode":"90211",
    "addr:street":"N San Vicente Blvd",
    "iso:country":"US",
    "sg:address":"119 N San Vicente Blvd",
    "sg:city":"Beverly Hills",
    "sg:classifiers":[
        {
            "category":"Health Services",
            "subcategory":"Clinic",
            "type":"Services"
        }
    ],
    "sg:phone":"+1 323 658 6737",
    "sg:postcode":"90211",
    "sg:province":"CA",
    "sg:tags":[
        "holistic",
        "practitioner"
    ],
    "wof:name":"Derushco Inc",
    "wof:placetype":"venue"
},
  "geometry": {"coordinates":[-118.373272,34.065843],"type":"Point"}
}