{
  "type": "Feature",
  "properties": {
    "addr:full":"1601 W Mountain St Glendale CA 91201",
    "addr:housenumber":"1601",
    "addr:postcode":"91201",
    "addr:street":"W Mountain St",
    "iso:country":"US",
    "sg:address":"1601 W Mountain St",
    "sg:city":"Glendale",
    "sg:classifiers":[
        {
            "category":"Landmark",
            "subcategory":"Historic",
            "type":"Public Place"
        },
        {
            "category":"Restaurant",
            "type":"Food & Drink"
        }
    ],
    "sg:phone":"+1 818 548 2000",
    "sg:postcode":"91201",
    "sg:province":"CA",
    "sg:tags":[
        "building",
        "flavor",
        "local",
        "historical"
    ],
    "sg:website":"www.ci.glendale.ca.us/parks/bran...",
    "wof:name":"Brand Park",
    "wof:placetype":"venue"
},
  "geometry": {"coordinates":[-118.277095,34.180354],"type":"Point"}
}