{
  "type": "Feature",
  "properties": {
    "iso:country":"US",
    "sg:address":"10727 Ashton Ave",
    "sg:city":"Los Angeles",
    "sg:classifiers":[
        {
            "category":"Manufacturing",
            "subcategory":"Apparel",
            "type":"Manufacturing & Wholesale Goods"
        }
    ],
    "sg:phone":"+1 310 474 2818",
    "sg:postcode":"90024",
    "sg:province":"CA",
    "sg:tags":[
        "dress",
        "mfg"
    ],
    "wof:name":"Nancy Myers Co",
    "wof:placetype":"venue"
},
  "geometry": {"coordinates":[-118.436508,34.059646],"type":"Point"}
}