{
  "type": "Feature",
  "properties": {
    "addr:full":"3201 Triumph Ln Apt 1 Ontario CA 91764",
    "addr:housenumber":"3201;1",
    "addr:postcode":"91764",
    "addr:street":"Triumph Ln Apt",
    "iso:country":"US",
    "sg:address":"3201 Triumph Ln Apt 1",
    "sg:city":"Ontario",
    "sg:classifiers":[
        {
            "category":"Real Estate",
            "subcategory":"Real Estate Services",
            "type":"Services"
        },
        {
            "category":"Real Estate",
            "subcategory":"Real Estate Operator",
            "type":"Services"
        }
    ],
    "sg:phone":"+1 909 944 1886",
    "sg:postcode":"91764",
    "sg:province":"CA",
    "sg:tags":[
        "vacancy",
        "apartment",
        "rental",
        "listing"
    ],
    "wof:name":"Covington Village",
    "wof:placetype":"venue"
},
  "geometry": {"coordinates":[-117.582588,34.07135],"type":"Point"}
}