{
  "type": "Feature",
  "properties": {
    "iso:country":"US",
    "sg:address":"1128 E 6th St",
    "sg:city":"Corona",
    "sg:classifiers":[
        {
            "category":"Social Services",
            "type":"Services"
        }
    ],
    "sg:phone":"+1 951 734 8831",
    "sg:postcode":"92879",
    "sg:province":"CA",
    "sg:tags":[
        "counseling",
        "counselor",
        "marriage",
        "family"
    ],
    "wof:name":"Center For Family Living",
    "wof:placetype":"venue"
},
  "geometry": {"coordinates":[-117.551878,33.874558],"type":"Point"}
}