{
  "type": "Feature",
  "properties": {
    "acgov:api":"743.0",
    "acgov:type":"ES",
    "addr:full":"13050 Aurora Drive San Leandro CA",
    "wof:categories":[
        "education_and_religion:education=school"
    ],
    "wof:name":"Garfield Elementary",
    "wof:placetype":"venue"
},
  "geometry": {"coordinates":[-122.18604323743411,37.70428545350862],"type":"Point"}
}