{
  "type": "Feature",
  "properties": {
    "iso:country":"US",
    "sg:address":"190 E Crowther Ave",
    "sg:city":"Placentia",
    "sg:classifiers":[
        {
            "category":"Freight",
            "type":"Transportation"
        },
        {
            "category":"Shopping",
            "subcategory":"Clothing, Apparel, & Fashions",
            "type":"Retail Goods"
        }
    ],
    "sg:phone":"+1 714 223 9908",
    "sg:postcode":"92870",
    "sg:province":"CA",
    "sg:tags":[
        "designer",
        "general"
    ],
    "wof:name":"Als Distribution",
    "wof:placetype":"venue"
},
  "geometry": {"coordinates":[-117.86838,33.868495],"type":"Point"}
}