{
  "type": "Feature",
  "properties": {
    "addr:full":"York Blvd at Ave 55 Los Angeles CA 90042",
    "addr:housenumber":"55",
    "addr:postcode":"90042",
    "addr:street":"York Blvd At Ave",
    "iso:country":"US",
    "sg:address":"York Blvd at Ave 55",
    "sg:city":"Los Angeles",
    "sg:classifiers":[
        {
            "category":"Food Court",
            "type":"Food & Drink"
        },
        {
            "category":"Restaurant",
            "type":"Food & Drink"
        }
    ],
    "sg:postcode":"90042",
    "sg:province":"CA",
    "sg:tags":[
        "mexican",
        "stand"
    ],
    "wof:name":"York and Ave 55 Taco Stand",
    "wof:placetype":"venue"
},
  "geometry": {"coordinates":[-118.198168,34.119703],"type":"Point"}
}