{
  "type": "Feature",
  "properties": {
    "addr:full":"111 N Moore Ave Monterey Park CA 91754",
    "addr:housenumber":"111",
    "addr:postcode":"91754",
    "addr:street":"N Moore Ave",
    "iso:country":"US",
    "sg:address":"111 N Moore Ave",
    "sg:city":"Monterey Park",
    "sg:classifiers":[
        {
            "category":"Shopping",
            "subcategory":"Computers & Home Electronics",
            "type":"Retail Goods"
        }
    ],
    "sg:phone":"+1 323 265 8076",
    "sg:postcode":"91754",
    "sg:province":"CA",
    "wof:name":"Amtron Technology",
    "wof:placetype":"venue"
},
  "geometry": {"coordinates":[-118.130696,34.065994],"type":"Point"}
}