{
  "type": "Feature",
  "properties": {
    "addr:full":"1605 Branham Ln San Jose CA 95118",
    "addr:housenumber":"1605",
    "addr:postcode":"95118",
    "addr:street":"Branham Ln",
    "iso:country":"US",
    "sg:address":"1605 Branham Ln",
    "sg:city":"San Jose",
    "sg:classifiers":[
        {
            "category":"Autos & Motor Vehicles",
            "subcategory":"Fuel & Gas Station",
            "type":"Retail Goods"
        }
    ],
    "sg:phone":"+1 408 723 3700",
    "sg:postcode":"95118",
    "sg:province":"CA",
    "sg:tags":[
        "oil"
    ],
    "wof:name":"San Jose Unocal 76",
    "wof:placetype":"venue"
},
  "geometry": {"coordinates":[-121.90478299999999,37.252711],"type":"Point"}
}