{
  "type": "Feature",
  "properties": {
    "addr:full":"624 Harris St Eureka CA 95503",
    "addr:housenumber":"624",
    "addr:postcode":"95503",
    "addr:street":"Harris St",
    "iso:country":"US",
    "sg:address":"624 Harris St",
    "sg:city":"Eureka",
    "sg:classifiers":[
        {
            "category":"Health Services",
            "subcategory":"Doctor",
            "type":"Services"
        }
    ],
    "sg:phone":"+1 707 442 5739",
    "sg:postcode":"95503",
    "sg:province":"CA",
    "sg:tags":[
        "dentist"
    ],
    "wof:name":"Kenneth S Singleton Inc",
    "wof:placetype":"venue"
},
  "geometry": {"coordinates":[-124.16219599999999,40.780313],"type":"Point"}
}