{
  "type": "Feature",
  "properties": {
    "iso:country":"US",
    "sg:address":"1870 Jefferson Street",
    "sg:city":"San Francisco",
    "sg:classifiers":[
        {
            "category":"Professional",
            "subcategory":"Lawyer & Legal Services",
            "type":"Services"
        }
    ],
    "sg:phone":"+1 415 614 9565",
    "sg:postcode":"94123",
    "sg:province":"CA",
    "wof:name":"Moriarty James L Atty",
    "wof:placetype":"venue"
},
  "geometry": {"coordinates":[-122.443001,37.804798],"type":"Point"}
}