{
  "type": "Feature",
  "properties": {
    "addr:full":"560 Olive St Carnelian Bay CA 96140",
    "addr:housenumber":"560",
    "addr:postcode":"96140",
    "addr:street":"Olive St",
    "iso:country":"US",
    "sg:address":"560 Olive St",
    "sg:city":"Carnelian Bay",
    "sg:classifiers":[
        {
            "category":"Retail",
            "subcategory":"Laundry & Dry Cleaning",
            "type":"Services"
        }
    ],
    "sg:phone":"+1 530 546 3756",
    "sg:postcode":"96140",
    "sg:province":"CA",
    "sg:tags":[
        "cleaners",
        "rug",
        "carpet"
    ],
    "sg:website":"www.rankellhomes.com",
    "wof:name":"Calneva Hydro Steam Carpet Cln",
    "wof:placetype":"venue"
},
  "geometry": {"coordinates":[-120.08340200000001,39.227812],"type":"Point"}
}