{
  "type": "Feature",
  "properties": {
    "iso:country":"US",
    "sg:address":"2025 Gateway Pl",
    "sg:city":"San Jose",
    "sg:classifiers":[
        {
            "category":"Banks & Credit Unions",
            "subcategory":"Bank",
            "type":"Services"
        }
    ],
    "sg:phone":"+1 408 451 9388",
    "sg:postcode":"95110",
    "sg:province":"CA",
    "sg:tags":[
        "loan",
        "real estate"
    ],
    "wof:name":"Baycal Financial Corp",
    "wof:placetype":"venue"
},
  "geometry": {"coordinates":[-121.922342,37.370649],"type":"Point"}
}