{
  "type": "Feature",
  "properties": {
    "addr:full":"3300 Voigt Dr La Jolla CA 92037",
    "addr:postcode":"3300;92037",
    "addr:street":"Voigt Dr",
    "iso:country":"US",
    "sg:address":"3300 Voigt Dr",
    "sg:city":"La Jolla",
    "sg:classifiers":[
        {
            "category":"Building & Trades",
            "subcategory":"Construction",
            "type":"Services"
        }
    ],
    "sg:phone":"+1 858 643 9215",
    "sg:postcode":"92037",
    "sg:province":"CA",
    "sg:tags":[
        "general",
        "contractor"
    ],
    "wof:name":"Rudolph & Stetten Construction",
    "wof:placetype":"venue"
},
  "geometry": {"coordinates":[-117.229411,32.881194],"type":"Point"}
}