{
  "type": "Feature",
  "properties": {
    "addr:full":"2498 Roll Dr San Diego CA 92154",
    "addr:housenumber":"2498",
    "addr:postcode":"92154",
    "addr:street":"Roll Dr",
    "iso:country":"US",
    "sg:address":"2498 Roll Dr",
    "sg:city":"San Diego",
    "sg:classifiers":[
        {
            "category":"Freight",
            "type":"Transportation"
        }
    ],
    "sg:phone":"+1 619 671 9788",
    "sg:postcode":"92154",
    "sg:province":"CA",
    "sg:tags":[
        "arrangement"
    ],
    "wof:name":"Ruiz S Transportation",
    "wof:placetype":"venue"
},
  "geometry": {"coordinates":[-116.93769899999999,32.556589],"type":"Point"}
}