{
  "type": "Feature",
  "properties": {
    "addr:full":"355 Oakland Ave Oakland CA 94611",
    "addr:housenumber":"355",
    "addr:postcode":"94611",
    "addr:street":"Oakland Ave",
    "iso:country":"US",
    "sg:address":"355 Oakland Ave",
    "sg:city":"Oakland",
    "sg:phone":"+1 510 717 1675",
    "sg:postcode":"94611",
    "sg:province":"CA",
    "wof:name":"Platinum Dirt Enterprise",
    "wof:placetype":"venue"
},
  "geometry": {"coordinates":[-122.256221,37.817179],"type":"Point"}
}