{
  "type": "Feature",
  "properties": {
    "iso:country":"US",
    "sg:address":"1220 Elm Ave",
    "sg:city":"Torrance",
    "sg:classifiers":[
        {
            "category":"Organizations",
            "subcategory":"Membership Organization",
            "type":"Services"
        }
    ],
    "sg:phone":"+1 310 328 7282",
    "sg:postcode":"90503",
    "sg:province":"CA",
    "sg:tags":[
        "athletic"
    ],
    "wof:name":"South Bay Volleyball Club",
    "wof:placetype":"venue"
},
  "geometry": {"coordinates":[-118.330941,33.834581],"type":"Point"}
}