{
  "type": "Feature",
  "properties": {
    "iso:country":"US",
    "sg:address":"440 N 1st St",
    "sg:city":"San Jose",
    "sg:classifiers":[
        {
            "category":"Professional",
            "type":"Services"
        }
    ],
    "sg:phone":"+1 408 277 0833",
    "sg:postcode":"95112",
    "sg:province":"CA",
    "sg:tags":[
        "establishment"
    ],
    "wof:name":"Get Up & Go",
    "wof:placetype":"venue"
},
  "geometry": {"coordinates":[-121.895948,37.343489],"type":"Point"}
}