{
  "type": "Feature",
  "properties": {
    "addr:full":"224 E 6th St Hanford CA 93230",
    "addr:housenumber":"224",
    "addr:postcode":"ca 93230",
    "addr:street":"E 6Th St",
    "iso:country":"US",
    "sg:address":"224 E 6th St",
    "sg:city":"Hanford",
    "sg:classifiers":[
        {
            "category":"Retail",
            "subcategory":"Auto Repair",
            "type":"Services"
        }
    ],
    "sg:phone":"+1 559 583 6895",
    "sg:postcode":"93230",
    "sg:province":"CA",
    "sg:tags":[
        "body",
        "automobile",
        "painting"
    ],
    "wof:name":"Robert's Collision Ctr LLC",
    "wof:placetype":"venue"
},
  "geometry": {"coordinates":[-119.64257000000001,36.326039],"type":"Point"}
}