{
  "type": "Feature",
  "properties": {
    "addr:full":"16776 Lakeshore Dr Ste G Lake Elsinore CA 92530",
    "addr:housenumber":"16776",
    "addr:postcode":"92530",
    "addr:street":"Lakeshore Dr Ste G",
    "iso:country":"US",
    "sg:address":"16776 Lakeshore Dr Ste G",
    "sg:city":"Lake Elsinore",
    "sg:classifiers":[
        {
            "category":"Retail",
            "subcategory":"Veterinary Services",
            "type":"Services"
        }
    ],
    "sg:phone":"+1 951 674 7866",
    "sg:postcode":"92530",
    "sg:province":"CA",
    "sg:tags":[
        "veterinarian"
    ],
    "wof:name":"Elsinore Pet Clinic",
    "wof:placetype":"venue"
},
  "geometry": {"coordinates":[-117.36799600000001,33.6852],"type":"Point"}
}