{
  "type": "Feature",
  "properties": {
    "addr:full":"421 Holger Dr Montebello CA 90640",
    "addr:housenumber":"421",
    "addr:postcode":"90640",
    "addr:street":"Holger Dr",
    "iso:country":"US",
    "sg:address":"421 Holger Dr",
    "sg:city":"Montebello",
    "sg:classifiers":[
        {
            "category":"Shopping",
            "subcategory":"Beauty & Cosmetics",
            "type":"Retail Goods"
        }
    ],
    "sg:phone":"+1 323 726 1596",
    "sg:postcode":"90640",
    "sg:province":"CA",
    "sg:tags":[
        "merchandise"
    ],
    "wof:name":"Lotus Cosmetics International",
    "wof:placetype":"venue"
},
  "geometry": {"coordinates":[-118.094966,34.016074],"type":"Point"}
}