{
  "type": "Feature",
  "properties": {
    "iso:country":"US",
    "sg:address":"601 el Camino Real",
    "sg:city":"Salinas",
    "sg:classifiers":[
        {
            "category":"Freight",
            "type":"Transportation"
        }
    ],
    "sg:phone":"+1 831 449 9675",
    "sg:postcode":"93907",
    "sg:province":"CA",
    "sg:tags":[
        "operator",
        "trucking"
    ],
    "wof:name":"David & Son Trucking",
    "wof:placetype":"venue"
},
  "geometry": {"coordinates":[-121.659981,36.742194],"type":"Point"}
}