{
  "type": "Feature",
  "properties": {
    "iso:country":"US",
    "sg:address":"1000 Collegeview Dr",
    "sg:city":"Turlock",
    "sg:classifiers":[
        {
            "category":"Manufacturing",
            "subcategory":"Watercraft",
            "type":"Manufacturing & Wholesale Goods"
        }
    ],
    "sg:phone":"+1 209 656 9697",
    "sg:postcode":"95382",
    "sg:province":"CA",
    "wof:name":"Jims Houseboats",
    "wof:placetype":"venue"
},
  "geometry": {"coordinates":[-120.85998600000001,37.530438],"type":"Point"}
}