{
  "type": "Feature",
  "properties": {
    "iso:country":"US",
    "sg:address":"7700 College Town Dr",
    "sg:city":"Sacramento",
    "sg:classifiers":[
        {
            "category":"Real Estate",
            "subcategory":"Developer",
            "type":"Services"
        }
    ],
    "sg:phone":"+1 916 972 7091",
    "sg:postcode":"95826",
    "sg:province":"CA",
    "wof:name":"Econ Developments",
    "wof:placetype":"venue"
},
  "geometry": {"coordinates":[-121.414126,38.554102],"type":"Point"}
}