{
  "type": "Feature",
  "properties": {
    "iso:country":"US",
    "sg:address":"5614 E La Palma Ave",
    "sg:city":"Anaheim",
    "sg:classifiers":[
        {
            "category":"Building & Trades",
            "subcategory":"Construction",
            "type":"Services"
        }
    ],
    "sg:phone":"+1 714 998 0122",
    "sg:postcode":"92807",
    "sg:province":"CA",
    "sg:tags":[
        "contractor"
    ],
    "sg:website":"makooverheaddoor.com",
    "wof:name":"Mako Overhead Door",
    "wof:placetype":"venue"
},
  "geometry": {"coordinates":[-117.792383,33.859783],"type":"Point"}
}