{
  "type": "Feature",
  "properties": {
    "addr:full":"929 W Barkley Ave Orange CA 92868",
    "addr:housenumber":"929",
    "addr:postcode":"92868",
    "addr:street":"W Barkley Ave",
    "iso:country":"US",
    "sg:address":"929 W Barkley Ave",
    "sg:city":"Orange",
    "sg:classifiers":[
        {
            "category":"Arts & Performance",
            "subcategory":"Art Gallery",
            "type":"Entertainment"
        }
    ],
    "sg:phone":"+1 714 639 8310",
    "sg:postcode":"92868",
    "sg:province":"CA",
    "sg:website":"www.artanglesgallery.com",
    "wof:name":"Art Angles",
    "wof:placetype":"venue"
},
  "geometry": {"coordinates":[-117.862238,33.801292],"type":"Point"}
}