{
  "type": "Feature",
  "properties": {
    "iso:country":"US",
    "sg:address":"325 S Main St",
    "sg:city":"Corona",
    "sg:classifiers":[
        {
            "category":"Food & Beverages",
            "subcategory":"Bakery",
            "type":"Retail Goods"
        }
    ],
    "sg:phone":"+1 951 371 8439",
    "sg:postcode":"92882",
    "sg:province":"CA",
    "sg:tags":[
        "baker"
    ],
    "wof:name":"Hostess Cakes",
    "wof:placetype":"venue"
},
  "geometry": {"coordinates":[-117.566158,33.877831],"type":"Point"}
}