{
  "type": "Feature",
  "properties": {
    "iso:country":"US",
    "sg:address":"2613 Illinois Ave",
    "sg:city":"Modesto",
    "sg:classifiers":[
        {
            "category":"Farming",
            "subcategory":"Crops",
            "type":"Manufacturing & Wholesale Goods"
        }
    ],
    "sg:phone":"+1 209 522 6140",
    "sg:postcode":"95358",
    "sg:province":"CA",
    "sg:tags":[
        "grove",
        "tree",
        "nut",
        "grape",
        "vineyard"
    ],
    "wof:name":"Blom Ranch",
    "wof:placetype":"venue"
},
  "geometry": {"coordinates":[-121.066876,37.60107],"type":"Point"}
}