{
  "type": "Feature",
  "properties": {
    "iso:country":"US",
    "sg:address":"1845 Market St",
    "sg:city":"San Francisco",
    "sg:classifiers":[
        {
            "category":"Manufacturing",
            "subcategory":"Printing",
            "type":"Manufacturing & Wholesale Goods"
        }
    ],
    "sg:phone":"+1 415 255 9760",
    "sg:postcode":"94103",
    "sg:province":"CA",
    "sg:tags":[
        "printer"
    ],
    "wof:name":"Sunrise Printing",
    "wof:placetype":"venue"
},
  "geometry": {"coordinates":[-122.42454600000001,37.770854],"type":"Point"}
}