{
  "type": "Feature",
  "properties": {
    "addr:full":"722 Genevieve St Solana Beach CA 92075",
    "addr:housenumber":"722",
    "addr:postcode":"92075",
    "addr:street":"Genevieve St",
    "iso:country":"US",
    "sg:address":"722 Genevieve St",
    "sg:city":"Solana Beach",
    "sg:classifiers":[
        {
            "category":"Personal",
            "subcategory":"Beauty Salon",
            "type":"Services"
        }
    ],
    "sg:phone":"+1 858 481 2772",
    "sg:postcode":"92075",
    "sg:province":"CA",
    "wof:name":"Future Faces Skin Care",
    "wof:placetype":"venue"
},
  "geometry": {"coordinates":[-117.25888399999999,32.989401],"type":"Point"}
}