{
  "type": "Feature",
  "properties": {
    "addr:full":"37 S Jackson Ave San Jose CA 95116",
    "addr:housenumber":"37",
    "addr:postcode":"95116",
    "addr:street":"S Jackson Ave",
    "iso:country":"US",
    "sg:address":"37 S Jackson Ave",
    "sg:city":"San Jose",
    "sg:classifiers":[
        {
            "category":"Professional",
            "type":"Services"
        }
    ],
    "sg:phone":"+1 408 272 7521",
    "sg:postcode":"95116",
    "sg:province":"CA",
    "wof:name":"Unidos Venceremos",
    "wof:placetype":"venue"
},
  "geometry": {"coordinates":[-121.842519,37.357416],"type":"Point"}
}