{
  "type": "Feature",
  "properties": {
    "iso:country":"US",
    "sg:address":"51 Yerba Buena Ln",
    "sg:city":"San Francisco",
    "sg:classifiers":[
        {
            "category":"Museum",
            "type":"Entertainment"
        }
    ],
    "sg:phone":"+1 415 227 4888",
    "sg:postcode":"94103",
    "sg:province":"CA",
    "sg:website":"www.mocfa.org",
    "wof:name":"Museum of Craft & Folk Art",
    "wof:placetype":"venue"
},
  "geometry": {"coordinates":[-122.403971,37.785385],"type":"Point"}
}