{
  "type": "Feature",
  "properties": {
    "addr:city":"San Francisco",
    "addr:full":"51 Yerba Buena Ln San Francisco, Ca 94103-3183",
    "addr:house_number":"51",
    "addr:housenumber":"51",
    "addr:phone":"+1 415-227-4888",
    "addr:postcode":"94103-3183",
    "addr:road":"Yerba Buena Ln",
    "addr:state":"CA",
    "addr:street":"Yerba Buena Ln",
    "iso:country":"US",
    "sg:address":"51 Yerba Buena Ln",
    "sg:city":"San Francisco",
    "sg:classifiers":[
        {
            "category":"Museum",
            "type":"Entertainment"
        }
    ],
    "sg:phone":"+1 415 227 4888",
    "sg:postcode":"94103",
    "sg:province":"CA",
    "sg:website":"www.mocfa.org",
    "wof:airports":[
        102527513,
        102531041
    ],
    "wof:name":"Museum Of Craft & Folk Art",
    "wof:placetype":"venue"
},
  "geometry": {"coordinates":[-122.40089999999999,37.7851],"type":"Point"}
}