{
  "type": "Feature",
  "properties": {
    "iso:country":"US",
    "sg:address":"1625 N Rancho Ave",
    "sg:city":"Colton",
    "sg:classifiers":[
        {
            "category":"Shopping",
            "subcategory":"Used Merchandise",
            "type":"Retail Goods"
        }
    ],
    "sg:phone":"+1 909 854 5245",
    "sg:postcode":"92324",
    "sg:province":"CA",
    "sg:tags":[
        "shop",
        "thrift"
    ],
    "wof:name":"Your Discount Store",
    "wof:placetype":"venue"
},
  "geometry": {"coordinates":[-117.334274,34.086303],"type":"Point"}
}