{
  "type": "Feature",
  "properties": {
    "iso:country":"US",
    "sg:address":"375 Levin St",
    "sg:city":"Milpitas",
    "sg:classifiers":[
        {
            "category":"Taxi",
            "type":"Transportation"
        }
    ],
    "sg:phone":"+1 408 674 3482",
    "sg:postcode":"95035",
    "sg:province":"CA",
    "sg:tags":[
        "taxicab"
    ],
    "wof:name":"Seniors Airporter Shuttle",
    "wof:placetype":"venue"
},
  "geometry": {"coordinates":[-121.904712,37.463482],"type":"Point"}
}