{
  "type": "Feature",
  "properties": {
    "addr:full":"5642 30th St Riverside CA 92509",
    "addr:housenumber":"5642",
    "addr:postcode":"92509",
    "addr:street":"30Th St",
    "iso:country":"US",
    "sg:address":"5642 30th St",
    "sg:city":"Riverside",
    "sg:classifiers":[
        {
            "category":"Restaurant",
            "type":"Food & Drink"
        }
    ],
    "sg:menulink":"http://www.allmenus.com/ca/jurupa/178206-jack-in-the-box/menu/",
    "sg:phone":"+1 951 369 1348",
    "sg:postcode":"92509",
    "sg:province":"CA",
    "sg:tags":[
        "burger",
        "american"
    ],
    "wof:name":"Jack in the Box",
    "wof:placetype":"venue"
},
  "geometry": {"coordinates":[-117.400533,34.005278],"type":"Point"}
}