{
  "type": "Feature",
  "properties": {
    "iso:country":"US",
    "sg:address":"19422 Sierra Luna Rd",
    "sg:city":"Irvine",
    "sg:classifiers":[
        {
            "category":"Professional",
            "type":"Services"
        }
    ],
    "sg:phone":"+1 949 854 0502",
    "sg:postcode":"92603",
    "sg:province":"CA",
    "wof:name":"Irvine Residents For Resp",
    "wof:placetype":"venue"
},
  "geometry": {"coordinates":[-117.817424,33.632285],"type":"Point"}
}