{
  "type": "Feature",
  "properties": {
    "addr:full":"6901 Balcom Ave Reseda CA 91335",
    "addr:housenumber":"6901",
    "addr:postcode":"91335",
    "addr:street":"Balcom Ave",
    "iso:country":"US",
    "sg:address":"6901 Balcom Ave",
    "sg:city":"Reseda",
    "sg:classifiers":[
        {
            "category":"Banks & Credit Unions",
            "subcategory":"Bank",
            "type":"Services"
        }
    ],
    "sg:phone":"+1 818 996 1010",
    "sg:postcode":"91335",
    "sg:province":"CA",
    "sg:tags":[
        "broker",
        "mortgage"
    ],
    "wof:name":"Sunshine Homes & Loans",
    "wof:placetype":"venue"
},
  "geometry": {"coordinates":[-118.520691,34.196113],"type":"Point"}
}