{
  "type": "Feature",
  "properties": {
    "iso:country":"US",
    "sg:address":"2339 Courage Dr",
    "sg:city":"Fairfield",
    "sg:classifiers":[
        {
            "category":"Professional",
            "type":"Services"
        }
    ],
    "sg:phone":"+1 707 402 4700",
    "sg:postcode":"94533",
    "sg:province":"CA",
    "wof:name":"Olive Critelli Oil Inc",
    "wof:placetype":"venue"
},
  "geometry": {"coordinates":[-122.075834,38.234706],"type":"Point"}
}