{
  "type": "Feature",
  "properties": {
    "iso:country":"US",
    "sg:address":"410 W Felicita Ave",
    "sg:city":"Escondido",
    "sg:phone":"+1 760 480 0858",
    "sg:postcode":"92025",
    "sg:province":"CA",
    "sg:website":"http://www.4feetandfeathers.net",
    "wof:name":"4 Feet & Feathers",
    "wof:placetype":"venue"
},
  "geometry": {"coordinates":[-117.074456,33.103973],"type":"Point"}
}