{
  "type": "Feature",
  "properties": {
    "iso:country":"US",
    "sg:address":"2790 Santa Rosa Ave",
    "sg:city":"Santa Rosa",
    "sg:classifiers":[
        {
            "category":"Shopping",
            "subcategory":"Bicycles & Sporting Goods",
            "type":"Retail Goods"
        }
    ],
    "sg:phone":"+1 707 542 4432",
    "sg:postcode":"95407",
    "sg:province":"CA",
    "sg:tags":[
        "tackle",
        "fishing"
    ],
    "wof:name":"Western Sport Shop",
    "wof:placetype":"venue"
},
  "geometry": {"coordinates":[-122.713401,38.409655],"type":"Point"}
}