{
  "type": "Feature",
  "properties": {
    "addr:full":"819 Maple Avenue Los Angeles CA 90014",
    "addr:housenumber":"819",
    "addr:postcode":"90014",
    "addr:street":"Maple Avenue",
    "iso:country":"US",
    "sg:address":"819 Maple Avenue",
    "sg:city":"Los Angeles",
    "sg:classifiers":[
        {
            "category":"Shopping",
            "subcategory":"Florist",
            "type":"Retail Goods"
        }
    ],
    "sg:phone":"+1 213 622 9181",
    "sg:postcode":"90014",
    "sg:province":"CA",
    "wof:name":"Tina's Craft Company",
    "wof:placetype":"venue"
},
  "geometry": {"coordinates":[-118.25157799999999,34.040313],"type":"Point"}
}