{
  "type": "Feature",
  "properties": {
    "addr:full":"101 S Summertree Rd Anaheim CA 92807",
    "addr:housenumber":"101",
    "addr:postcode":"92807",
    "addr:street":"S Summertree Rd",
    "iso:country":"US",
    "sg:address":"101 S Summertree Rd",
    "sg:city":"Anaheim",
    "sg:classifiers":[
        {
            "category":"Professional",
            "type":"Services"
        }
    ],
    "sg:phone":"+1 714 998 6048",
    "sg:postcode":"92807",
    "sg:province":"CA",
    "wof:name":"Sticky Buns Inc",
    "wof:placetype":"venue"
},
  "geometry": {"coordinates":[-117.77746399999999,33.851366],"type":"Point"}
}