{
  "type": "Feature",
  "properties": {
    "iso:country":"US",
    "sg:address":"2160 Palomar Airport Rd",
    "sg:city":"Carlsbad",
    "sg:classifiers":[
        {
            "category":"Shopping",
            "subcategory":"Books",
            "type":"Retail Goods"
        }
    ],
    "sg:phone":"+1 760 431 9777",
    "sg:postcode":"92011",
    "sg:province":"CA",
    "sg:tags":[
        "hardware",
        "merchandise"
    ],
    "wof:name":"Carlsbad Aircraft Pilot Sups",
    "wof:placetype":"venue"
},
  "geometry": {"coordinates":[-117.26676399999999,33.129531],"type":"Point"}
}