{
  "type": "Feature",
  "properties": {
    "addr:full":"1230 J St Sacramento CA 95814",
    "addr:housenumber":"1230",
    "addr:postcode":"95814",
    "addr:street":"J St",
    "iso:country":"US",
    "sg:address":"1230 J St",
    "sg:city":"Sacramento",
    "sg:classifiers":[
        {
            "category":"Government",
            "subcategory":"Office",
            "type":"Public Place"
        }
    ],
    "sg:phone":"+1 916 322 1994",
    "sg:postcode":"95814",
    "sg:province":"CA",
    "sg:tags":[
        "state"
    ],
    "wof:name":"Corporate Filing Div",
    "wof:placetype":"venue"
},
  "geometry": {"coordinates":[-121.489566,38.579222],"type":"Point"}
}