{
  "type": "Feature",
  "properties": {
    "addr:full":"7860 Hwy 116 Forestville CA 95436",
    "addr:housenumber":"7860",
    "addr:postcode":"95436",
    "addr:street":"Hwy 116",
    "iso:country":"US",
    "sg:address":"7860 Hwy 116",
    "sg:city":"Forestville",
    "sg:classifiers":[
        {
            "category":"Wholesale",
            "subcategory":"Construction Materials",
            "type":"Manufacturing & Wholesale Goods"
        }
    ],
    "sg:phone":"+1 707 887 2216",
    "sg:postcode":"95436",
    "sg:province":"CA",
    "sg:tags":[
        "rock"
    ],
    "wof:name":"Mark West Aggregates",
    "wof:placetype":"venue"
},
  "geometry": {"coordinates":[-122.907282,38.473617],"type":"Point"}
}