{
  "type": "Feature",
  "properties": {
    "iso:country":"US",
    "sg:address":"799 North Ave",
    "sg:city":"Vista",
    "sg:classifiers":[
        {
            "category":"Personal",
            "type":"Services"
        },
        {
            "category":"Home & Garden",
            "subcategory":"Home Furnishings",
            "type":"Retail Goods"
        },
        {
            "category":"Building & Trades",
            "subcategory":"Construction",
            "type":"Services"
        },
        {
            "category":"Manufacturing",
            "subcategory":"Building Materials",
            "type":"Manufacturing & Wholesale Goods"
        }
    ],
    "sg:phone":"+1 760 941 9860",
    "sg:postcode":"92083",
    "sg:province":"CA",
    "sg:tags":[
        "industrial",
        "closet",
        "cabinetmakers-commercial",
        "carpenter",
        "cabinet",
        "refacing",
        "resurfacing",
        "designing",
        "contractor",
        "remodeling",
        "maker",
        "cabinets-refinishing",
        "kitchen"
    ],
    "wof:name":"Palomar Casework Inc.",
    "wof:placetype":"venue"
},
  "geometry": {"coordinates":[-117.258923,33.215586],"type":"Point"}
}