{
  "type": "Feature",
  "properties": {
    "addr:full":"1211 Franklin Mall Santa Clara CA 95050",
    "addr:housenumber":"1211",
    "addr:postcode":"95050",
    "addr:street":"Franklin Mall",
    "iso:country":"US",
    "sg:address":"1211 Franklin Mall",
    "sg:city":"Santa Clara",
    "sg:classifiers":[
        {
            "category":"Restaurant",
            "type":"Food & Drink"
        }
    ],
    "sg:phone":"+1 408 246 3943",
    "sg:postcode":"95050",
    "sg:province":"CA",
    "sg:tags":[
        "thai"
    ],
    "sg:website":"www.jasminefinethai.com",
    "wof:name":"Jasmine Fine Thai Cuisine",
    "wof:placetype":"venue"
},
  "geometry": {"coordinates":[-121.94727899999999,37.349338],"type":"Point"}
}