{
  "type": "Feature",
  "properties": {
    "addr:full":"1815 Main St San Diego CA 92113",
    "addr:housenumber":"1815",
    "addr:postcode":"92113",
    "addr:street":"Main St",
    "iso:country":"US",
    "sg:address":"1815 Main St",
    "sg:city":"San Diego",
    "sg:classifiers":[
        {
            "category":"Home & Garden",
            "subcategory":"Furniture",
            "type":"Retail Goods"
        }
    ],
    "sg:phone":"+1 619 236 1819",
    "sg:postcode":"92113",
    "sg:province":"CA",
    "sg:tags":[
        "store"
    ],
    "wof:name":"China Furniture",
    "wof:placetype":"venue"
},
  "geometry": {"coordinates":[-117.147003,32.699699],"type":"Point"}
}