{
  "type": "Feature",
  "properties": {
    "addr:full":"418 Greenwood Beach Rd Belvedere Tibrn CA 94920",
    "addr:housenumber":"418",
    "addr:postcode":"94920",
    "addr:street":"Greenwood Beach Rd",
    "iso:country":"US",
    "sg:address":"418 Greenwood Beach Rd",
    "sg:city":"Belvedere Tibrn",
    "sg:classifiers":[
        {
            "category":"Real Estate",
            "subcategory":"Developer",
            "type":"Services"
        }
    ],
    "sg:phone":"+1 415 383 2900",
    "sg:postcode":"94920",
    "sg:province":"CA",
    "wof:name":"Philip Richardson & Assoc",
    "wof:placetype":"venue"
},
  "geometry": {"coordinates":[-122.495816,37.894493],"type":"Point"}
}