{
  "type": "Feature",
  "properties": {
    "addr:full":"3605 Bouton Dr Lakewood CA 90712",
    "addr:housenumber":"3605",
    "addr:postcode":"90712",
    "addr:street":"Bouton Dr",
    "iso:country":"US",
    "sg:address":"3605 Bouton Dr",
    "sg:city":"Lakewood",
    "sg:classifiers":[
        {
            "category":"Shopping",
            "subcategory":"Computers & Home Electronics",
            "type":"Retail Goods"
        }
    ],
    "sg:phone":"+1 562 421 8400",
    "sg:postcode":"90712",
    "sg:province":"CA",
    "sg:tags":[
        "software"
    ],
    "wof:name":"M Ogawa Computer",
    "wof:placetype":"venue"
},
  "geometry": {"coordinates":[-118.14815,33.841023],"type":"Point"}
}