{
  "type": "Feature",
  "properties": {
    "iso:country":"US",
    "sg:address":"20 Lincoln Ave",
    "sg:city":"San Anselmo",
    "sg:classifiers":[
        {
            "category":"Building & Trades",
            "subcategory":"Construction",
            "type":"Services"
        }
    ],
    "sg:phone":"+1 415 721 7654",
    "sg:postcode":"94960",
    "sg:province":"CA",
    "sg:tags":[
        "contractor"
    ],
    "wof:name":"Domus",
    "wof:placetype":"venue"
},
  "geometry": {"coordinates":[-122.56013900000001,37.975739],"type":"Point"}
}