{
  "type": "Feature",
  "properties": {
    "iso:country":"US",
    "sg:address":"2221 K St",
    "sg:city":"Merced",
    "sg:classifiers":[
        {
            "category":"Manufacturing",
            "subcategory":"Printing",
            "type":"Manufacturing & Wholesale Goods"
        }
    ],
    "sg:phone":"+1 209 383 0433",
    "sg:postcode":"95340",
    "sg:province":"CA",
    "sg:tags":[
        "newspaper"
    ],
    "wof:name":"Merced County Times",
    "wof:placetype":"venue"
},
  "geometry": {"coordinates":[-120.478553,37.306683],"type":"Point"}
}