{
  "type": "Feature",
  "properties": {
    "addr:full":"153 N Vendome St Los Angeles CA 90026",
    "addr:housenumber":"153",
    "addr:postcode":"90026",
    "addr:street":"N Vendome St",
    "iso:country":"US",
    "sg:address":"153 N Vendome St",
    "sg:city":"Los Angeles",
    "sg:classifiers":[
        {
            "category":"Professional",
            "type":"Services"
        }
    ],
    "sg:phone":"+1 213 382 6598",
    "sg:postcode":"90026",
    "sg:province":"CA",
    "sg:tags":[
        "establishment"
    ],
    "wof:name":"Bumagat Redepmtion",
    "wof:placetype":"venue"
},
  "geometry": {"coordinates":[-118.281717,34.072571],"type":"Point"}
}