{
  "type": "Feature",
  "properties": {
    "iso:country":"US",
    "sg:address":"1012 N Euclid St",
    "sg:city":"Anaheim",
    "sg:classifiers":[
        {
            "category":"Shopping",
            "subcategory":"Pharmacy",
            "type":"Retail Goods"
        }
    ],
    "sg:phone":"+1 714 956 3741",
    "sg:postcode":"92801",
    "sg:province":"CA",
    "sg:tags":[
        "drugstore"
    ],
    "wof:name":"Pharmacy Plus",
    "wof:placetype":"venue"
},
  "geometry": {"coordinates":[-117.942001,33.846802],"type":"Point"}
}