{
  "type": "Feature",
  "properties": {
    "addr:full":"316 N Santa Cruz Ave Modesto CA 95354",
    "addr:housenumber":"316",
    "addr:postcode":"ca 95354",
    "addr:street":"N Santa Cruz Ave",
    "iso:country":"US",
    "sg:address":"316 N Santa Cruz Ave",
    "sg:city":"Modesto",
    "sg:classifiers":[
        {
            "category":"Personal",
            "subcategory":"Beauty Salon",
            "type":"Services"
        }
    ],
    "sg:phone":"+1 209 527 6236",
    "sg:postcode":"95354",
    "sg:province":"CA",
    "sg:website":"http://www.deadseaskincarespa.com",
    "wof:name":"Dead Sea Wellness Spa",
    "wof:placetype":"venue"
},
  "geometry": {"coordinates":[-120.974324,37.641706],"type":"Point"}
}