{
  "type": "Feature",
  "properties": {
    "iso:country":"US",
    "sg:address":"1885 California St #55",
    "sg:city":"Mountain View",
    "sg:classifiers":[
        {
            "category":"Professional",
            "subcategory":"Computer Services",
            "type":"Services"
        }
    ],
    "sg:phone":"+1 541143628214",
    "sg:postcode":"94041",
    "sg:province":"CA",
    "sg:website":"http://www.farmsphere.com",
    "wof:name":"Farmsphere",
    "wof:placetype":"venue"
},
  "geometry": {"coordinates":[-122.093316,37.396243],"type":"Point"}
}