{
  "type": "Feature",
  "properties": {
    "iso:country":"US",
    "sg:address":"15111 S Figueroa St",
    "sg:city":"Gardena",
    "sg:classifiers":[
        {
            "category":"Manufacturing",
            "subcategory":"Furniture",
            "type":"Manufacturing & Wholesale Goods"
        }
    ],
    "sg:phone":"+1 310 768 3814",
    "sg:postcode":"90248",
    "sg:province":"CA",
    "wof:name":"Benetti's Italia Inc",
    "wof:placetype":"venue"
},
  "geometry": {"coordinates":[-118.283134,33.893465],"type":"Point"}
}