{
  "type": "Feature",
  "properties": {
    "addr:full":"3608 S Bristol St Santa Ana CA 92704",
    "addr:housenumber":"3608",
    "addr:postcode":"92704",
    "addr:street":"S Bristol St",
    "iso:country":"US",
    "sg:address":"3608 S Bristol St",
    "sg:city":"Santa Ana",
    "sg:classifiers":[
        {
            "category":"Restaurant",
            "type":"Food & Drink"
        }
    ],
    "sg:phone":"+1 714 957 1857",
    "sg:postcode":"92704",
    "sg:province":"CA",
    "sg:tags":[
        "new",
        "american"
    ],
    "wof:name":"South Coast Winery Restaurant",
    "wof:placetype":"venue"
},
  "geometry": {"coordinates":[-117.88558999999999,33.699094],"type":"Point"}
}