{
  "type": "Feature",
  "properties": {
    "iso:country":"US",
    "sg:address":"661 Elliott Rd",
    "sg:city":"Paradise",
    "sg:classifiers":[
        {
            "category":"Freight",
            "type":"Transportation"
        }
    ],
    "sg:phone":"+1 530 872 3930",
    "sg:postcode":"95969",
    "sg:province":"CA",
    "sg:tags":[
        "operator",
        "local",
        "trucking"
    ],
    "wof:name":"Stan Locklair Trucking",
    "wof:placetype":"venue"
},
  "geometry": {"coordinates":[-121.625671,39.759541],"type":"Point"}
}