{
  "type": "Feature",
  "properties": {
    "iso:country":"US",
    "sg:address":"1009 Timber Ridge Rd",
    "sg:city":"Westwood",
    "sg:classifiers":[
        {
            "category":"Shopping",
            "subcategory":"Computers & Home Electronics",
            "type":"Retail Goods"
        }
    ],
    "sg:phone":"+1 530 259 2682",
    "sg:postcode":"96137",
    "sg:province":"CA",
    "sg:tags":[
        "equipment",
        "dealer"
    ],
    "wof:name":"Microconn",
    "wof:placetype":"venue"
},
  "geometry": {"coordinates":[-121.15082,40.249885],"type":"Point"}
}