{
  "type": "Feature",
  "properties": {
    "addr:full":"2642 Gough Street San Francisco CA 94123",
    "addr:housenumber":"2642",
    "addr:postcode":"94123",
    "addr:street":"Gough Street",
    "iso:country":"US",
    "sg:address":"2642 Gough Street",
    "sg:city":"San Francisco",
    "sg:classifiers":[
        {
            "category":"Professional",
            "subcategory":"Lawyer & Legal Services",
            "type":"Services"
        }
    ],
    "sg:phone":"+1 415 885 3310",
    "sg:postcode":"94123",
    "sg:province":"CA",
    "wof:name":"Stegen & Flores Attorneys At Law",
    "wof:placetype":"venue"
},
  "geometry": {"coordinates":[-122.436487,37.80118],"type":"Point"}
}