{
  "type": "Feature",
  "properties": {
    "iso:country":"US",
    "sg:address":"2722 Richter Ave",
    "sg:city":"Oroville",
    "sg:classifiers":[
        {
            "category":"Building & Trades",
            "subcategory":"Construction",
            "type":"Services"
        }
    ],
    "sg:phone":"+1 530 534 6883",
    "sg:postcode":"95966",
    "sg:province":"CA",
    "sg:tags":[
        "steel",
        "fabrication",
        "welding"
    ],
    "wof:name":"Steel By Neal",
    "wof:placetype":"venue"
},
  "geometry": {"coordinates":[-121.554695,39.501624],"type":"Point"}
}