{
  "type": "Feature",
  "properties": {
    "addr:full":"722 Main St Pleasanton CA 94566",
    "addr:housenumber":"722",
    "addr:postcode":"94566",
    "addr:street":"Main St",
    "iso:country":"US",
    "sg:address":"722 Main St",
    "sg:city":"Pleasanton",
    "sg:classifiers":[
        {
            "category":"Personal",
            "subcategory":"Beauty Salon",
            "type":"Services"
        }
    ],
    "sg:phone":"+1 925 600 0080",
    "sg:postcode":"94566",
    "sg:province":"CA",
    "wof:name":"Fusion 3 Salon Spa",
    "wof:placetype":"venue"
},
  "geometry": {"coordinates":[-121.874512,37.663362],"type":"Point"}
}