{
  "type": "Feature",
  "properties": {
    "addr:full":"6091 Jurupa Ave Riverside CA 92504",
    "addr:housenumber":"6091",
    "addr:postcode":"92504",
    "addr:street":"Jurupa Ave",
    "iso:country":"US",
    "sg:address":"6091 Jurupa Ave",
    "sg:city":"Riverside",
    "sg:classifiers":[
        {
            "category":"Manufacturing",
            "subcategory":"Furniture",
            "type":"Manufacturing & Wholesale Goods"
        }
    ],
    "sg:phone":"+1 951 359 5395",
    "sg:postcode":"92504",
    "sg:province":"CA",
    "sg:tags":[
        "mfg",
        "wood",
        "contractor",
        "carpentry"
    ],
    "wof:name":"Kendalls Lminated Plastic Pdts",
    "wof:placetype":"venue"
},
  "geometry": {"coordinates":[-117.43512200000001,33.962998],"type":"Point"}
}