{
  "type": "Feature",
  "properties": {
    "addr:full":"7313 Circle Dr Rohnert Park CA 94928",
    "addr:housenumber":"7313",
    "addr:postcode":"94928",
    "addr:street":"Circle Dr",
    "iso:country":"US",
    "sg:address":"7313 Circle Dr",
    "sg:city":"Rohnert Park",
    "sg:classifiers":[
        {
            "category":"Recreation",
            "type":"Entertainment"
        }
    ],
    "sg:phone":"+1 707 793 9461",
    "sg:postcode":"94928",
    "sg:province":"CA",
    "sg:tags":[
        "psychic",
        "medium"
    ],
    "wof:name":"Divining Room",
    "wof:placetype":"venue"
},
  "geometry": {"coordinates":[-122.69246699999999,38.335196],"type":"Point"}
}