{
  "type": "Feature",
  "properties": {
    "iso:country":"US",
    "sg:address":"314 Harriet Street",
    "sg:city":"San Francisco",
    "sg:classifiers":[
        {
            "category":"Health Services",
            "subcategory":"Clinic",
            "type":"Services"
        }
    ],
    "sg:phone":"+1 415 861 5096",
    "sg:postcode":"94103",
    "sg:province":"CA",
    "sg:tags":[
        "counseling",
        "mental"
    ],
    "wof:name":"Passages Psychological Services",
    "wof:placetype":"venue"
},
  "geometry": {"coordinates":[-122.40300000000001,37.775398],"type":"Point"}
}