{
  "type": "Feature",
  "properties": {
    "addr:full":"4916 Romeo Pl Fremont CA 94555",
    "addr:housenumber":"4916",
    "addr:postcode":"94555",
    "addr:street":"Romeo Pl",
    "iso:country":"US",
    "sg:address":"4916 Romeo Pl",
    "sg:city":"Fremont",
    "sg:classifiers":[
        {
            "category":"Professional",
            "type":"Services"
        }
    ],
    "sg:phone":"+1 510 574 0307",
    "sg:postcode":"94555",
    "sg:province":"CA",
    "wof:name":"Wesley Wingfield",
    "wof:placetype":"venue"
},
  "geometry": {"coordinates":[-122.05734,37.568616],"type":"Point"}
}