{
  "type": "Feature",
  "properties": {
    "iso:country":"US",
    "sg:address":"1400 W 240th St",
    "sg:city":"Harbor City",
    "sg:classifiers":[
        {
            "category":"Health Services",
            "subcategory":"Doctor",
            "type":"Services"
        }
    ],
    "sg:phone":"+1 310 539 6449",
    "sg:postcode":"90710",
    "sg:province":"CA",
    "sg:tags":[
        "clinic"
    ],
    "wof:name":"Medical Accounts Control Inc",
    "wof:placetype":"venue"
},
  "geometry": {"coordinates":[-118.303054,33.807286],"type":"Point"}
}