{
  "type": "Feature",
  "properties": {
    "addr:full":"4901 Pico Ave Bakersfield CA 93306",
    "addr:housenumber":"4901",
    "addr:postcode":"93306",
    "addr:street":"Pico Ave",
    "iso:country":"US",
    "sg:address":"4901 Pico Ave",
    "sg:city":"Bakersfield",
    "sg:classifiers":[
        {
            "category":"Manufacturing",
            "subcategory":"Retail Goods",
            "type":"Manufacturing & Wholesale Goods"
        }
    ],
    "sg:phone":"+1 661 872 1509",
    "sg:postcode":"93306",
    "sg:province":"CA",
    "sg:tags":[
        "product",
        "mfg"
    ],
    "wof:name":"Purple Scents Candle Co",
    "wof:placetype":"venue"
},
  "geometry": {"coordinates":[-118.948263,35.390118],"type":"Point"}
}