{
  "type": "Feature",
  "properties": {
    "addr:full":"782 N 13th St San Jose CA 95112",
    "addr:housenumber":"782",
    "addr:postcode":"95112",
    "addr:street":"N 13Th St",
    "iso:country":"US",
    "sg:address":"782 N 13th St",
    "sg:city":"San Jose",
    "sg:classifiers":[
        {
            "category":"Restaurant",
            "type":"Food & Drink"
        }
    ],
    "sg:phone":"+1 408 295 1471",
    "sg:postcode":"95112",
    "sg:province":"CA",
    "wof:name":"El Caminito Taqueria No 2",
    "wof:placetype":"venue"
},
  "geometry": {"coordinates":[-121.889,37.356602],"type":"Point"}
}