{
  "type": "Feature",
  "properties": {
    "addr:full":"106 Wikiup Dr Santa Rosa CA 95403",
    "addr:housenumber":"106",
    "addr:postcode":"95403",
    "addr:street":"Wikiup Dr",
    "iso:country":"US",
    "sg:address":"106 Wikiup Dr",
    "sg:city":"Santa Rosa",
    "sg:classifiers":[
        {
            "category":"Banks & Credit Unions",
            "subcategory":"Investment Brokerage",
            "type":"Services"
        }
    ],
    "sg:phone":"+1 707 566 6775",
    "sg:postcode":"95403",
    "sg:province":"CA",
    "sg:tags":[
        "consultant",
        "planning",
        "financial"
    ],
    "wof:name":"Kobrin Financial Svc",
    "wof:placetype":"venue"
},
  "geometry": {"coordinates":[-122.75787200000001,38.508464],"type":"Point"}
}