{
  "type": "Feature",
  "properties": {
    "addr:full":"442 E Main St Ventura CA 93001",
    "addr:housenumber":"442",
    "addr:postcode":"93001",
    "addr:street":"E Main St",
    "iso:country":"US",
    "sg:address":"442 E Main St",
    "sg:city":"Ventura",
    "sg:classifiers":[
        {
            "category":"Shopping",
            "subcategory":"Clothing, Apparel, & Fashions",
            "type":"Retail Goods"
        }
    ],
    "sg:phone":"+1 805 641 0515",
    "sg:postcode":"93001",
    "sg:province":"CA",
    "wof:name":"Tiki Lounge",
    "wof:placetype":"venue"
},
  "geometry": {"coordinates":[-119.293655,34.280741],"type":"Point"}
}