{
  "type": "Feature",
  "properties": {
    "iso:country":"US",
    "sg:address":"2409 E Plaza Blvd",
    "sg:city":"National City",
    "sg:classifiers":[
        {
            "category":"Health Services",
            "subcategory":"Doctor",
            "type":"Services"
        }
    ],
    "sg:phone":"+1 619 475 4200",
    "sg:postcode":"91950",
    "sg:province":"CA",
    "sg:tags":[
        "physician",
        "surgeon"
    ],
    "wof:name":"Jacob R Morgan Inc",
    "wof:placetype":"venue"
},
  "geometry": {"coordinates":[-117.080271,32.679852],"type":"Point"}
}