{
  "type": "Feature",
  "properties": {
    "addr:full":"12680 Salmon River Rd San Diego CA 92129",
    "addr:housenumber":"12680",
    "addr:postcode":"92129",
    "addr:street":"Salmon River Rd",
    "iso:country":"US",
    "sg:address":"12680 Salmon River Rd",
    "sg:city":"San Diego",
    "sg:classifiers":[
        {
            "category":"Shopping",
            "subcategory":"Florist",
            "type":"Retail Goods"
        }
    ],
    "sg:phone":"+1 858 484 4203",
    "sg:postcode":"92129",
    "sg:province":"CA",
    "wof:name":"Salud & Alfredo's Epis Orchids",
    "wof:placetype":"venue"
},
  "geometry": {"coordinates":[-117.12323000000001,32.946077],"type":"Point"}
}