{
  "type": "Feature",
  "properties": {
    "addr:full":"12 S Cluff Ave Lodi CA 95240",
    "addr:housenumber":"12",
    "addr:postcode":"95240",
    "addr:street":"S Cluff Ave",
    "iso:country":"US",
    "sg:address":"12 S Cluff Ave",
    "sg:city":"Lodi",
    "sg:classifiers":[
        {
            "category":"Retail",
            "subcategory":"Auto Repair",
            "type":"Services"
        }
    ],
    "sg:phone":"+1 209 333 3763",
    "sg:postcode":"95240",
    "sg:province":"CA",
    "sg:tags":[
        "repairing",
        "automobile",
        "radiator"
    ],
    "wof:name":"Western Radiator Svc Of Lodi",
    "wof:placetype":"venue"
},
  "geometry": {"coordinates":[-121.25234399999999,38.130959],"type":"Point"}
}