{
  "type": "Feature",
  "properties": {
    "iso:country":"US",
    "sg:address":"504 S Orchard Dr",
    "sg:city":"Burbank",
    "sg:classifiers":[
        {
            "category":"Professional",
            "type":"Services"
        }
    ],
    "sg:phone":"+1 818 563 4173",
    "sg:postcode":"91506",
    "sg:province":"CA",
    "wof:name":"Natural High Adventures",
    "wof:placetype":"venue"
},
  "geometry": {"coordinates":[-118.320661,34.160241],"type":"Point"}
}