{
  "type": "Feature",
  "properties": {
    "addr:full":"139 W Portals Ave Clovis CA 93612",
    "addr:housenumber":"139",
    "addr:postcode":"93612",
    "addr:street":"W Portals Ave",
    "iso:country":"US",
    "sg:address":"139 W Portals Ave",
    "sg:city":"Clovis",
    "sg:classifiers":[
        {
            "category":"Real Estate",
            "subcategory":"Real Estate Operator",
            "type":"Services"
        }
    ],
    "sg:phone":"+1 559 298 1977",
    "sg:postcode":"93612",
    "sg:province":"CA",
    "sg:tags":[
        "apartment"
    ],
    "wof:name":"Caza Bella",
    "wof:placetype":"venue"
},
  "geometry": {"coordinates":[-119.71205999999999,36.816655],"type":"Point"}
}