{
  "type": "Feature",
  "properties": {
    "iso:country":"US",
    "sg:address":"2701 Auto Mall Dr",
    "sg:city":"Bakersfield",
    "sg:classifiers":[
        {
            "category":"Autos & Motor Vehicles",
            "subcategory":"Automobile Sales",
            "type":"Retail Goods"
        }
    ],
    "sg:phone":"+1 661 323 8007",
    "sg:postcode":"93313",
    "sg:province":"CA",
    "sg:tags":[
        "new",
        "car"
    ],
    "wof:name":"Stiers Camperland",
    "wof:placetype":"venue"
},
  "geometry": {"coordinates":[-119.033959,35.301023],"type":"Point"}
}