{
  "type": "Feature",
  "properties": {
    "addr:full":"6860 Brockton Ave Riverside CA 92506",
    "addr:housenumber":"6860",
    "addr:postcode":"92506",
    "addr:street":"Brockton Ave",
    "iso:country":"US",
    "sg:address":"6860 Brockton Ave",
    "sg:city":"Riverside",
    "sg:classifiers":[
        {
            "category":"Health Services",
            "subcategory":"Doctor",
            "type":"Services"
        }
    ],
    "sg:phone":"+1 951 686 9255",
    "sg:postcode":"92506",
    "sg:province":"CA",
    "sg:tags":[
        "dentist"
    ],
    "wof:name":"Edward Cowan DDS",
    "wof:placetype":"venue"
},
  "geometry": {"coordinates":[-117.39668,33.949398],"type":"Point"}
}