{
  "type": "Feature",
  "properties": {
    "addr:full":"2015 Main St Julian CA 92036",
    "addr:housenumber":"2015",
    "addr:postcode":"92036",
    "addr:street":"Main St",
    "iso:country":"US",
    "sg:address":"2015 Main St",
    "sg:city":"Julian",
    "sg:classifiers":[
        {
            "category":"Manufacturing",
            "subcategory":"Buildings",
            "type":"Manufacturing & Wholesale Goods"
        }
    ],
    "sg:phone":"+1 760 765 1117",
    "sg:postcode":"92036",
    "sg:province":"CA",
    "sg:tags":[
        "home",
        "log",
        "cabin"
    ],
    "wof:name":"Log Home Castles",
    "wof:placetype":"venue"
},
  "geometry": {"coordinates":[-116.601052,33.077534],"type":"Point"}
}