{
  "type": "Feature",
  "properties": {
    "addr:full":"8150 Broadway Lemon Grove CA 91945",
    "addr:housenumber":"8150",
    "addr:postcode":"91945",
    "addr:street":"Broadway",
    "iso:country":"US",
    "sg:address":"8150 Broadway",
    "sg:city":"Lemon Grove",
    "sg:classifiers":[
        {
            "category":"Real Estate",
            "subcategory":"Real Estate Operator",
            "type":"Services"
        }
    ],
    "sg:phone":"+1 619 466 5354",
    "sg:postcode":"91945",
    "sg:province":"CA",
    "sg:tags":[
        "apartment"
    ],
    "wof:name":"Calexico Plaza Senior Apartments",
    "wof:placetype":"venue"
},
  "geometry": {"coordinates":[-117.021004,32.744202],"type":"Point"}
}