{
  "type": "Feature",
  "properties": {
    "iso:country":"US",
    "sg:address":"4646 Carpinteria Ave",
    "sg:city":"Carpinteria",
    "sg:classifiers":[
        {
            "category":"Home & Garden",
            "subcategory":"Furniture",
            "type":"Retail Goods"
        }
    ],
    "sg:phone":"+1 805 566 9304",
    "sg:postcode":"93013",
    "sg:province":"CA",
    "sg:tags":[
        "builder",
        "custom"
    ],
    "sg:website":"www.milaninteriors.com",
    "wof:name":"Milan Interiors Inc",
    "wof:placetype":"venue"
},
  "geometry": {"coordinates":[-119.522086,34.401536],"type":"Point"}
}