{
  "type": "Feature",
  "properties": {
    "addr:full":"6907 Lankershim Blvd North Hollywood CA 91605",
    "addr:housenumber":"6907",
    "addr:postcode":"91605",
    "addr:street":"Lankershim Blvd",
    "iso:country":"US",
    "sg:address":"6907 Lankershim Blvd",
    "sg:city":"North Hollywood",
    "sg:classifiers":[
        {
            "category":"Restaurant",
            "type":"Food & Drink"
        }
    ],
    "sg:phone":"+1 818 765 0043",
    "sg:postcode":"91605",
    "sg:province":"CA",
    "sg:tags":[
        "caterer"
    ],
    "wof:name":"Le Monge Banquet Hall",
    "wof:placetype":"venue"
},
  "geometry": {"coordinates":[-118.387854,34.194136],"type":"Point"}
}