{
  "type": "Feature",
  "properties": {
    "iso:country":"US",
    "sg:address":"337 3rd St",
    "sg:city":"San Rafael",
    "sg:classifiers":[
        {
            "category":"Food & Beverages",
            "subcategory":"Groceries & Convenience Stores",
            "type":"Retail Goods"
        }
    ],
    "sg:phone":"+1 415 454 9530",
    "sg:postcode":"94901",
    "sg:province":"CA",
    "sg:tags":[
        "grocer"
    ],
    "sg:website":"www.traderjoes.com",
    "wof:name":"Trader Joe's Co",
    "wof:placetype":"venue"
},
  "geometry": {"coordinates":[-122.517307,37.970593],"type":"Point"}
}