{
  "type": "Feature",
  "properties": {
    "addr:full":"1635 S San Gabriel Blvd #b San Gabriel CA 91776",
    "addr:housenumber":"1635",
    "addr:postcode":"91776",
    "addr:street":"S San Gabriel Blvd # B",
    "iso:country":"US",
    "sg:address":"1635 S San Gabriel Blvd #b",
    "sg:city":"San Gabriel",
    "sg:classifiers":[
        {
            "category":"Restaurant",
            "type":"Food & Drink"
        },
        {
            "category":"Ice Cream",
            "type":"Food & Drink"
        }
    ],
    "sg:phone":"+1 626 288 5488",
    "sg:postcode":"91776",
    "sg:province":"CA",
    "sg:tags":[
        "frozen",
        "yogurt"
    ],
    "wof:name":"Snow B Yogurt",
    "wof:placetype":"venue"
},
  "geometry": {"coordinates":[-118.092028,34.078898],"type":"Point"}
}