{
  "type": "Feature",
  "properties": {
    "addr:full":"25019 Pacific Coast Hwy Malibu CA 90265",
    "addr:housenumber":"25019",
    "addr:postcode":"90265",
    "addr:street":"Pacific Coast Hwy",
    "iso:country":"US",
    "sg:address":"25019 Pacific Coast Hwy",
    "sg:city":"Malibu",
    "sg:classifiers":[
        {
            "category":"Farming",
            "subcategory":"Nursery",
            "type":"Manufacturing & Wholesale Goods"
        },
        {
            "category":"Home & Garden",
            "subcategory":"Garden Supply",
            "type":"Retail Goods"
        }
    ],
    "sg:phone":"+1 310 456 6026",
    "sg:postcode":"90265",
    "sg:province":"CA",
    "sg:tags":[
        "nurseryman"
    ],
    "sg:website":"www.mannycosentino.com",
    "wof:name":"Cosentino's",
    "wof:placetype":"venue"
},
  "geometry": {"coordinates":[-118.72032900000001,34.034],"type":"Point"}
}