{
  "type": "Feature",
  "properties": {
    "addr:full":"14323 Cerise Ave Hawthorne CA 90250",
    "addr:housenumber":"14323",
    "addr:postcode":"90250",
    "addr:street":"Cerise Ave",
    "iso:country":"US",
    "sg:address":"14323 Cerise Ave",
    "sg:city":"Hawthorne",
    "sg:classifiers":[
        {
            "category":"Professional",
            "type":"Services"
        }
    ],
    "sg:phone":"+1 310 978 9337",
    "sg:postcode":"90250",
    "sg:province":"CA",
    "wof:name":"December Bolden",
    "wof:placetype":"venue"
},
  "geometry": {"coordinates":[-118.333072,33.901018],"type":"Point"}
}