{
  "type": "Feature",
  "properties": {
    "addr:full":"1471 1st St Calistoga CA 94515",
    "addr:housenumber":"1471",
    "addr:postcode":"94515",
    "addr:street":"1St St",
    "iso:country":"US",
    "sg:address":"1471 1st St",
    "sg:city":"Calistoga",
    "sg:classifiers":[
        {
            "category":"Personal",
            "type":"Services"
        }
    ],
    "sg:phone":"+1 707 942 0903",
    "sg:postcode":"94515",
    "sg:province":"CA",
    "sg:tags":[
        "therapist",
        "massage"
    ],
    "wof:name":"Alchemy Of The Heart",
    "wof:placetype":"venue"
},
  "geometry": {"coordinates":[-122.579701,38.579452],"type":"Point"}
}