{
  "type": "Feature",
  "properties": {
    "addr:full":"1030 Freestone Ranch Rd Valley Ford CA 94922",
    "addr:housenumber":"1030",
    "addr:postcode":"94922",
    "addr:street":"Freestone Ranch Rd",
    "iso:country":"US",
    "sg:address":"1030 Freestone Ranch Rd",
    "sg:city":"Valley Ford",
    "sg:classifiers":[
        {
            "category":"Professional",
            "type":"Services"
        }
    ],
    "sg:phone":"+1 707 876 9276",
    "sg:postcode":"94922",
    "sg:province":"CA",
    "sg:tags":[
        "writer"
    ],
    "wof:name":"Write Cause",
    "wof:placetype":"venue"
},
  "geometry": {"coordinates":[-122.898498,38.35821],"type":"Point"}
}