{
  "type": "Feature",
  "properties": {
    "iso:country":"US",
    "sg:address":"5636 Melrose Ave",
    "sg:city":"Los Angeles",
    "sg:classifiers":[
        {
            "category":"Arts & Performance",
            "subcategory":"Arts Center",
            "type":"Entertainment"
        }
    ],
    "sg:phone":"+1 323 463 7378",
    "sg:postcode":"90038",
    "sg:province":"CA",
    "sg:tags":[
        "performing"
    ],
    "sg:website":"www.sfstheatre.com/",
    "wof:name":"Stephanie Feury Studio Theatre And Acting Conservatory",
    "wof:placetype":"venue"
},
  "geometry": {"coordinates":[-118.323269,34.083446],"type":"Point"}
}