{
  "type": "Feature",
  "properties": {
    "iso:country":"US",
    "sg:address":"322 Pendleton Way",
    "sg:city":"Oakland",
    "sg:classifiers":[
        {
            "category":"Banks & Credit Unions",
            "subcategory":"Bank",
            "type":"Services"
        },
        {
            "category":"Banks & Credit Unions",
            "subcategory":"Financial Services",
            "type":"Services"
        }
    ],
    "sg:phone":"+1 510 614 1211",
    "sg:postcode":"94621",
    "sg:province":"CA",
    "sg:tags":[
        "investment",
        "management",
        "stock",
        "broker",
        "bond"
    ],
    "wof:name":"San Leandro Investment Co.",
    "wof:placetype":"venue"
},
  "geometry": {"coordinates":[-122.200485,37.735849],"type":"Point"}
}