{
  "type": "Feature",
  "properties": {
    "addr:full":"2814 W Martin Luther King Jr Blvd Los Angeles CA 90008",
    "addr:housenumber":"2814",
    "addr:postcode":"90008",
    "addr:street":"W Martin Luther King Jr Blvd",
    "iso:country":"US",
    "sg:address":"2814 W Martin Luther King Jr Blvd",
    "sg:city":"Los Angeles",
    "sg:classifiers":[
        {
            "category":"Wholesale",
            "subcategory":"Motor Vehicles",
            "type":"Manufacturing & Wholesale Goods"
        }
    ],
    "sg:phone":"+1 323 298 0882",
    "sg:postcode":"90008",
    "sg:province":"CA",
    "sg:tags":[
        "automobile",
        "truck",
        "broker"
    ],
    "wof:name":"Trouble Free",
    "wof:placetype":"venue"
},
  "geometry": {"coordinates":[-118.324,34.010795],"type":"Point"}
}