{
  "type": "Feature",
  "properties": {
    "addr:full":"2660 John Montgomery Dr San Jose CA 95148",
    "addr:housenumber":"2660",
    "addr:postcode":"95148",
    "addr:street":"John Montgomery Dr",
    "iso:country":"US",
    "sg:address":"2660 John Montgomery Dr",
    "sg:city":"San Jose",
    "sg:classifiers":[
        {
            "category":"Education",
            "subcategory":"Special Training",
            "type":"Public Place"
        }
    ],
    "sg:phone":"+1 408 729 4359",
    "sg:postcode":"95148",
    "sg:province":"CA",
    "sg:tags":[
        "aircraft",
        "school"
    ],
    "wof:name":"Gary Air",
    "wof:placetype":"venue"
},
  "geometry": {"coordinates":[-121.819435,37.338879],"type":"Point"}
}