{
  "type": "Feature",
  "properties": {
    "iso:country":"US",
    "sg:address":"1122 Folsom St",
    "sg:city":"San Francisco",
    "sg:classifiers":[
        {
            "category":"Restaurant",
            "type":"Food & Drink"
        }
    ],
    "sg:menulink":"http://www.allmenus.com/ca/san-francisco/44531-brainwash/menu/",
    "sg:phone":"+1 415 861 3663",
    "sg:postcode":"94103",
    "sg:province":"CA",
    "sg:tags":[
        "american",
        "sandwich"
    ],
    "wof:name":"Brainwash",
    "wof:placetype":"venue"
},
  "geometry": {"coordinates":[-122.408686,37.776392],"type":"Point"}
}