{
  "type": "Feature",
  "properties": {
    "iso:country":"US",
    "sg:address":"1601 Foxworthy Avenue",
    "sg:city":"San Jose",
    "sg:classifiers":[
        {
            "category":"Sports & Exercise",
            "subcategory":"Sports Center",
            "type":"Entertainment"
        }
    ],
    "sg:phone":"+1 408 269 0214",
    "sg:postcode":"95118",
    "sg:province":"CA",
    "sg:tags":[
        "amateur",
        "team"
    ],
    "wof:name":"San Jose City of",
    "wof:placetype":"venue"
},
  "geometry": {"coordinates":[-121.902722,37.271413],"type":"Point"}
}