{
  "type": "Feature",
  "properties": {
    "addr:full":"2441 Dockery Ave Selma CA 93662",
    "addr:housenumber":"2441",
    "addr:postcode":"93662",
    "addr:street":"Dockery Ave",
    "iso:country":"US",
    "sg:address":"2441 Dockery Ave",
    "sg:city":"Selma",
    "sg:classifiers":[
        {
            "category":"Place Of Worship",
            "subcategory":"Church",
            "type":"Public Place"
        },
        {
            "category":"Place Of Worship",
            "type":"Public Place"
        }
    ],
    "sg:phone":"+1 559 896 1052",
    "sg:postcode":"93662",
    "sg:province":"CA",
    "sg:tags":[
        "catholic",
        "churches-catholic-traditional",
        "churches-roman",
        "churches-catholic"
    ],
    "wof:name":"St Joseph Catholic Church",
    "wof:placetype":"venue"
},
  "geometry": {"coordinates":[-119.60183000000001,36.569193],"type":"Point"}
}