{
  "type": "Feature",
  "properties": {
    "iso:country":"US",
    "sg:address":"6117 Reseda Blvd",
    "sg:city":"Reseda",
    "sg:classifiers":[
        {
            "category":"Wholesale",
            "subcategory":"Medical Equipment & Supplies",
            "type":"Manufacturing & Wholesale Goods"
        }
    ],
    "sg:phone":"+1 818 996 8818",
    "sg:postcode":"91335",
    "sg:province":"CA",
    "sg:tags":[
        "dental"
    ],
    "wof:name":"Best Point USA Inc",
    "wof:placetype":"venue"
},
  "geometry": {"coordinates":[-118.53609,34.181479],"type":"Point"}
}