{
  "type": "Feature",
  "properties": {
    "iso:country":"US",
    "sg:address":"183 Springcreek Dr",
    "sg:city":"Ione",
    "sg:classifiers":[
        {
            "category":"Building & Trades",
            "subcategory":"Plumbing",
            "type":"Services"
        }
    ],
    "sg:phone":"+1 209 274 6101",
    "sg:postcode":"95640",
    "sg:province":"CA",
    "sg:tags":[
        "product",
        "management",
        "energy",
        "system"
    ],
    "wof:name":"Central Sierra Energy Svc",
    "wof:placetype":"venue"
},
  "geometry": {"coordinates":[-120.94109899999999,38.350403],"type":"Point"}
}