{
  "type": "Feature",
  "properties": {
    "iso:country":"US",
    "sg:address":"42166 Rd 62",
    "sg:city":"Reedley",
    "sg:classifiers":[
        {
            "category":"Building & Trades",
            "subcategory":"Construction",
            "type":"Services"
        }
    ],
    "sg:phone":"+1 559 289 3457",
    "sg:postcode":"93654",
    "sg:province":"CA",
    "sg:tags":[
        "contractor"
    ],
    "wof:name":"Alan Eastep & Son Sitework",
    "wof:placetype":"venue"
},
  "geometry": {"coordinates":[-119.434918,36.546421],"type":"Point"}
}