{
  "type": "Feature",
  "properties": {
    "iso:country":"US",
    "sg:address":"1431 Wescott Rd",
    "sg:city":"Colusa",
    "sg:classifiers":[
        {
            "category":"Real Estate",
            "subcategory":"Real Estate Operator",
            "type":"Services"
        }
    ],
    "sg:phone":"+1 530 458 5623",
    "sg:postcode":"95932",
    "sg:province":"CA",
    "sg:tags":[
        "apartment"
    ],
    "wof:name":"Devonshire Apartments",
    "wof:placetype":"venue"
},
  "geometry": {"coordinates":[-122.00578,39.201088],"type":"Point"}
}