{
  "type": "Feature",
  "properties": {
    "addr:full":"19 E Citrus Ave Redlands CA 92373",
    "addr:housenumber":"19",
    "addr:postcode":"92373",
    "addr:street":"E Citrus Ave",
    "iso:country":"US",
    "sg:address":"19 E Citrus Ave",
    "sg:city":"Redlands",
    "sg:classifiers":[
        {
            "category":"Personal",
            "subcategory":"Hair Removal",
            "type":"Services"
        }
    ],
    "sg:phone":"+1 909 793 3563",
    "sg:postcode":"92373",
    "sg:province":"CA",
    "sg:tags":[
        "removing"
    ],
    "wof:name":"Senza Medical Corp",
    "wof:placetype":"venue"
},
  "geometry": {"coordinates":[-117.18161499999999,34.055633],"type":"Point"}
}