{
  "type": "Feature",
  "properties": {
    "iso:country":"US",
    "sg:address":"429 Palm Dr",
    "sg:city":"Glendale",
    "sg:classifiers":[
        {
            "category":"Freight",
            "type":"Transportation"
        }
    ],
    "sg:phone":"+1 818 720 6450",
    "sg:postcode":"91202",
    "sg:province":"CA",
    "sg:tags":[
        "operator",
        "local",
        "trucking"
    ],
    "wof:name":"X Delivery Co",
    "wof:placetype":"venue"
},
  "geometry": {"coordinates":[-118.263956,34.161875],"type":"Point"}
}