{
  "type": "Feature",
  "properties": {
    "addr:full":"429 Palm Dr Glendale CA 91202",
    "addr:housenumber":"429",
    "addr:postcode":"91202",
    "addr:street":"Palm Dr",
    "iso:country":"US",
    "sg:address":"429 Palm Dr",
    "sg:city":"Glendale",
    "sg:classifiers":[
        {
            "category":"Freight",
            "type":"Transportation"
        }
    ],
    "sg:phone":"+1 818 720 6450",
    "sg:postcode":"91202",
    "sg:province":"CA",
    "sg:tags":[
        "operator",
        "local",
        "trucking"
    ],
    "wof:name":"X Delivery Co",
    "wof:placetype":"venue"
},
  "geometry": {"coordinates":[-118.26395599999999,34.161875],"type":"Point"}
}