{
  "type": "Feature",
  "properties": {
    "iso:country":"US",
    "sg:address":"30 Woodland Rd",
    "sg:city":"Fairfax",
    "sg:classifiers":[
        {
            "category":"Manufacturing",
            "subcategory":"Printing",
            "type":"Manufacturing & Wholesale Goods"
        },
        {
            "category":"Shopping",
            "subcategory":"Books",
            "type":"Retail Goods"
        }
    ],
    "sg:phone":"+1 415 457 5223",
    "sg:postcode":"94930",
    "sg:province":"CA",
    "sg:tags":[
        "publisher",
        "music"
    ],
    "wof:name":"Stuart Music Company",
    "wof:placetype":"venue"
},
  "geometry": {"coordinates":[-122.603852,37.97869],"type":"Point"}
}