{
  "type": "Feature",
  "properties": {
    "iso:country":"US",
    "sg:address":"1611 Telegraph Ave",
    "sg:city":"Oakland",
    "sg:classifiers":[
        {
            "category":"Organizations",
            "subcategory":"Community Association",
            "type":"Services"
        }
    ],
    "sg:phone":"+1 510 271 8080",
    "sg:postcode":"94612",
    "sg:province":"CA",
    "sg:tags":[
        "environmental",
        "org"
    ],
    "wof:name":"Corpwatch",
    "wof:placetype":"venue"
},
  "geometry": {"coordinates":[-122.270411,37.806777],"type":"Point"}
}