{
  "type": "Feature",
  "properties": {
    "iso:country":"US",
    "sg:address":"2801 Encinal Ave",
    "sg:city":"Alameda",
    "sg:classifiers":[
        {
            "category":"Home & Garden",
            "subcategory":"Hardware",
            "type":"Retail Goods"
        }
    ],
    "sg:phone":"+1 510 523 4821",
    "sg:postcode":"94501",
    "sg:province":"CA",
    "sg:tags":[
        "store"
    ],
    "wof:name":"True Value",
    "wof:placetype":"venue"
},
  "geometry": {"coordinates":[-122.23835200000001,37.759328],"type":"Point"}
}