{
  "type": "Feature",
  "properties": {
    "addr:full":"4757 Hoen Ave Santa Rosa CA 95405",
    "addr:housenumber":"4757",
    "addr:postcode":"95405",
    "addr:street":"Hoen Ave",
    "iso:country":"US",
    "sg:address":"4757 Hoen Ave",
    "sg:city":"Santa Rosa",
    "sg:classifiers":[
        {
            "category":"Health Services",
            "subcategory":"Doctor",
            "type":"Services"
        }
    ],
    "sg:phone":"+1 707 575 9595",
    "sg:postcode":"95405",
    "sg:province":"CA",
    "sg:tags":[
        "dentist"
    ],
    "wof:name":"Stephen D Davis Inc",
    "wof:placetype":"venue"
},
  "geometry": {"coordinates":[-122.665072,38.441918],"type":"Point"}
}