{
  "type": "Feature",
  "properties": {
    "addr:full":"3438 Mendocino Avenue, Suite A Santa Rosa, CA CA 95403",
    "addr:housenumber":"3438",
    "addr:postcode":"ca ca 95403",
    "addr:street":"Mendocino Avenue Suite A",
    "iso:country":"US",
    "sg:address":"3438 Mendocino Avenue, Suite A",
    "sg:city":"Santa Rosa, CA",
    "sg:classifiers":[
        {
            "category":"Professional",
            "subcategory":"Computer Services",
            "type":"Services"
        }
    ],
    "sg:phone":"+1 408 441 7000",
    "sg:postcode":"95403",
    "sg:province":"CA",
    "sg:website":"http://www.questds.com/",
    "wof:name":"Quest Discovery",
    "wof:placetype":"venue"
},
  "geometry": {"coordinates":[-122.725171,38.47231],"type":"Point"}
}