{
  "type": "Feature",
  "properties": {
    "iso:country":"US",
    "sg:address":"2533 Ocean Avenue",
    "sg:city":"San Francisco",
    "sg:classifiers":[
        {
            "category":"Health Services",
            "subcategory":"Dentist",
            "type":"Services"
        }
    ],
    "sg:phone":"+1 415 333 6000",
    "sg:postcode":"94132",
    "sg:province":"CA",
    "sg:website":"www.gr8hands.com",
    "wof:name":"Karsant George D Jr DDS",
    "wof:placetype":"venue"
},
  "geometry": {"coordinates":[-122.476997,37.719101],"type":"Point"}
}