{
  "type": "Feature",
  "properties": {
    "addr:full":"1010 W 42nd Pl Los Angeles CA 90037",
    "addr:housenumber":"1010",
    "addr:postcode":"90037",
    "addr:street":"W 42Nd Pl",
    "iso:country":"US",
    "sg:address":"1010 W 42nd Pl",
    "sg:city":"Los Angeles",
    "sg:classifiers":[
        {
            "category":"Shopping",
            "subcategory":"Used Merchandise",
            "type":"Retail Goods"
        }
    ],
    "sg:phone":"+1 323 234 7661",
    "sg:postcode":"90037",
    "sg:province":"CA",
    "sg:tags":[
        "second",
        "store",
        "hand"
    ],
    "wof:name":"Segunda Las Gueritas",
    "wof:placetype":"venue"
},
  "geometry": {"coordinates":[-118.29353500000001,34.006325],"type":"Point"}
}