{
  "type": "Feature",
  "properties": {
    "addr:full":"43300 Bus Park Dr Temecula CA 92590",
    "addr:postcode":"43300;92590",
    "addr:street":"Bus Park Dr",
    "iso:country":"US",
    "sg:address":"43300 Bus Park Dr",
    "sg:city":"Temecula",
    "sg:classifiers":[
        {
            "category":"Professional",
            "subcategory":"Business Services",
            "type":"Services"
        }
    ],
    "sg:phone":"+1 951 695 2400",
    "sg:postcode":"92590",
    "sg:province":"CA",
    "sg:tags":[
        "interior",
        "consultant",
        "design",
        "decorator"
    ],
    "wof:name":"Sophisticated Interior Designs",
    "wof:placetype":"venue"
},
  "geometry": {"coordinates":[-117.16356,33.499924],"type":"Point"}
}