{
  "type": "Feature",
  "properties": {
    "addr:full":"230 S Beverly Dr Beverly Hills CA 90212",
    "addr:housenumber":"230",
    "addr:postcode":"90212",
    "addr:street":"S Beverly Dr",
    "iso:country":"US",
    "sg:address":"230 S Beverly Dr",
    "sg:city":"Beverly Hills",
    "sg:classifiers":[
        {
            "category":"Fast Food",
            "type":"Food & Drink"
        },
        {
            "category":"Restaurant",
            "type":"Food & Drink"
        }
    ],
    "sg:phone":"+1 310 248 5211",
    "sg:postcode":"90212",
    "sg:province":"CA",
    "sg:tags":[
        "indian"
    ],
    "sg:website":"www.saffronindia.com/",
    "wof:name":"Saffron",
    "wof:placetype":"venue"
},
  "geometry": {"coordinates":[-118.39892500000001,34.063901],"type":"Point"}
}