{
  "type": "Feature",
  "properties": {
    "addr:full":"14344 Foothill Blvd Sylmar CA 91342",
    "addr:housenumber":"14344",
    "addr:postcode":"91342",
    "addr:street":"Foothill Blvd",
    "iso:country":"US",
    "sg:address":"14344 Foothill Blvd",
    "sg:city":"Sylmar",
    "sg:classifiers":[
        {
            "category":"Shopping",
            "subcategory":"News",
            "type":"Retail Goods"
        }
    ],
    "sg:phone":"+1 818 367 1878",
    "sg:postcode":"91342",
    "sg:province":"CA",
    "sg:tags":[
        "magazine"
    ],
    "wof:name":"Net Directors Co",
    "wof:placetype":"venue"
},
  "geometry": {"coordinates":[-118.444948,34.318377],"type":"Point"}
}