{
  "type": "Feature",
  "properties": {
    "iso:country":"US",
    "sg:address":"199 S Beverly Dr",
    "sg:city":"Beverly Hills",
    "sg:classifiers":[
        {
            "category":"Shopping",
            "subcategory":"Clothing, Apparel, & Fashions",
            "type":"Retail Goods"
        }
    ],
    "sg:phone":"+1 310 271 5423",
    "sg:postcode":"90212",
    "sg:province":"CA",
    "sg:tags":[
        "children's",
        "clothing"
    ],
    "wof:name":"Ragg Tattoo",
    "wof:placetype":"venue"
},
  "geometry": {"coordinates":[-118.399002,34.064999],"type":"Point"}
}