{
  "type": "Feature",
  "properties": {
    "addr:full":"2850 Pio Pico Dr Carlsbad CA 92008",
    "addr:housenumber":"2850",
    "addr:postcode":"92008",
    "addr:street":"Pio Pico Dr",
    "iso:country":"US",
    "sg:address":"2850 Pio Pico Dr",
    "sg:city":"Carlsbad",
    "sg:classifiers":[
        {
            "category":"Professional",
            "subcategory":"Research",
            "type":"Services"
        }
    ],
    "sg:phone":"+1 760 720 0099",
    "sg:postcode":"92008",
    "sg:province":"CA",
    "sg:tags":[
        "development",
        "laboratory"
    ],
    "sg:website":"www.b-alert.com",
    "wof:name":"Advance Brain Monitoring",
    "wof:placetype":"venue"
},
  "geometry": {"coordinates":[-117.343513,33.16692],"type":"Point"}
}