{
  "type": "Feature",
  "properties": {
    "addr:full":"525 S Coast Hwy Oceanside CA 92054",
    "addr:housenumber":"525",
    "addr:postcode":"92054",
    "addr:street":"S Coast Hwy",
    "iso:country":"US",
    "sg:address":"525 S Coast Hwy",
    "sg:city":"Oceanside",
    "sg:classifiers":[
        {
            "category":"Autos & Motor Vehicles",
            "subcategory":"Motorcycle Sales",
            "type":"Retail Goods"
        }
    ],
    "sg:phone":"+1 760 722 7704",
    "sg:postcode":"92054",
    "sg:province":"CA",
    "sg:tags":[
        "scooter"
    ],
    "wof:name":"Aprilia Ducati of Oceanside",
    "wof:placetype":"venue"
},
  "geometry": {"coordinates":[-117.37400100000001,33.189999],"type":"Point"}
}