{
  "type": "Feature",
  "properties": {
    "addr:full":"720 E Main St Visalia CA 93292",
    "addr:housenumber":"720",
    "addr:postcode":"93292",
    "addr:street":"E Main St",
    "iso:country":"US",
    "sg:address":"720 E Main St",
    "sg:city":"Visalia",
    "sg:classifiers":[
        {
            "category":"Shopping",
            "subcategory":"Used Merchandise",
            "type":"Retail Goods"
        }
    ],
    "sg:phone":"+1 559 733 3520",
    "sg:postcode":"93292",
    "sg:province":"CA",
    "sg:tags":[
        "antique"
    ],
    "wof:name":"Grandma's Attic & Friends",
    "wof:placetype":"venue"
},
  "geometry": {"coordinates":[-119.284465,36.330265],"type":"Point"}
}