{
  "type": "Feature",
  "properties": {
    "addr:full":"455 Serramonte Blvd Daly City CA 94014",
    "addr:housenumber":"455",
    "addr:postcode":"94014",
    "addr:street":"Serramonte Blvd",
    "iso:country":"US",
    "sg:address":"455 Serramonte Blvd",
    "sg:city":"Daly City",
    "sg:classifiers":[
        {
            "category":"Professional",
            "type":"Services"
        }
    ],
    "sg:phone":"+1 650 755 2818",
    "sg:postcode":"94014",
    "sg:province":"CA",
    "sg:tags":[
        "establishment"
    ],
    "wof:name":"Serrawonle Mitsubishi",
    "wof:placetype":"venue"
},
  "geometry": {"coordinates":[-122.45757999999999,37.677042],"type":"Point"}
}