{
  "type": "Feature",
  "properties": {
    "iso:country":"US",
    "sg:address":"1319 Olive St",
    "sg:city":"Santa Barbara",
    "sg:classifiers":[
        {
            "category":"Professional",
            "subcategory":"Management & Consulting",
            "type":"Services"
        }
    ],
    "sg:phone":"+1 805 966 0005",
    "sg:postcode":"93101",
    "sg:province":"CA",
    "sg:tags":[
        "marketing",
        "consultant"
    ],
    "sg:website":"www.jhcampbell.com",
    "wof:name":"J H Campbell Marketing",
    "wof:placetype":"venue"
},
  "geometry": {"coordinates":[-119.701213,34.430299],"type":"Point"}
}