{
  "type": "Feature",
  "properties": {
    "iso:country":"US",
    "sg:address":"9136 Ruben St",
    "sg:city":"Lamont",
    "sg:classifiers":[
        {
            "category":"Professional",
            "type":"Services"
        }
    ],
    "sg:phone":"+1 661 845 4151",
    "sg:postcode":"93241",
    "sg:province":"CA",
    "wof:name":"Aguilar Betancourt Salomon",
    "wof:placetype":"venue"
},
  "geometry": {"coordinates":[-118.912912,35.271926],"type":"Point"}
}