{
  "type": "Feature",
  "properties": {
    "addr:full":"9136 Ruben St Lamont CA 93241",
    "addr:housenumber":"9136",
    "addr:postcode":"93241",
    "addr:street":"Ruben St",
    "iso:country":"US",
    "sg:address":"9136 Ruben St",
    "sg:city":"Lamont",
    "sg:classifiers":[
        {
            "category":"Professional",
            "type":"Services"
        }
    ],
    "sg:phone":"+1 661 845 4151",
    "sg:postcode":"93241",
    "sg:province":"CA",
    "wof:name":"Aguilar Betancourt Salomon",
    "wof:placetype":"venue"
},
  "geometry": {"coordinates":[-118.91291200000001,35.271926],"type":"Point"}
}