{
  "type": "Feature",
  "properties": {
    "addr:full":"4938 Zion Ave San Diego CA 92120",
    "addr:housenumber":"4938",
    "addr:postcode":"92120",
    "addr:street":"Zion Ave",
    "iso:country":"US",
    "sg:address":"4938 Zion Ave",
    "sg:city":"San Diego",
    "sg:classifiers":[
        {
            "category":"Shopping",
            "subcategory":"Bicycles & Sporting Goods",
            "type":"Retail Goods"
        }
    ],
    "sg:phone":"+1 619 583 3344",
    "sg:postcode":"92120",
    "sg:province":"CA",
    "wof:name":"Recycled Stuff",
    "wof:placetype":"venue"
},
  "geometry": {"coordinates":[-117.08375100000001,32.79295],"type":"Point"}
}