{
  "type": "Feature",
  "properties": {
    "iso:country":"US",
    "sg:address":"3000 Sand Hill Rd",
    "sg:city":"Menlo Park",
    "sg:classifiers":[
        {
            "category":"Professional",
            "subcategory":"Business Services",
            "type":"Services"
        },
        {
            "category":"Banks & Credit Unions",
            "subcategory":"Financial Services",
            "type":"Services"
        }
    ],
    "sg:phone":"+1 650 233 8250",
    "sg:postcode":"94025",
    "sg:province":"CA",
    "sg:tags":[
        "company",
        "venture",
        "capital"
    ],
    "wof:name":"Celerity Partners",
    "wof:placetype":"venue"
},
  "geometry": {"coordinates":[-122.22002000000001,37.419101],"type":"Point"}
}