{
  "type": "Feature",
  "properties": {
    "iso:country":"US",
    "sg:address":"9454 Wilshire Blvd",
    "sg:city":"Beverly Hills",
    "sg:classifiers":[
        {
            "category":"Wholesale",
            "subcategory":"Stationery",
            "type":"Manufacturing & Wholesale Goods"
        }
    ],
    "sg:phone":"+1 310 734 1950",
    "sg:postcode":"90212",
    "sg:province":"CA",
    "sg:tags":[
        "business",
        "form",
        "system"
    ],
    "sg:website":"www.businesscard.com",
    "wof:name":"Business Card Com",
    "wof:placetype":"venue"
},
  "geometry": {"coordinates":[-118.398597,34.066982],"type":"Point"}
}