{
  "type": "Feature",
  "properties": {
    "addr:full":"20437 Sherman Way Winnetka CA 91306",
    "addr:housenumber":"20437",
    "addr:postcode":"91306",
    "addr:street":"Sherman Way",
    "iso:country":"US",
    "sg:address":"20437 Sherman Way",
    "sg:city":"Winnetka",
    "sg:classifiers":[
        {
            "category":"Banks & Credit Unions",
            "subcategory":"Financial Services",
            "type":"Services"
        }
    ],
    "sg:phone":"+1 818 884 2907",
    "sg:postcode":"91306",
    "sg:province":"CA",
    "sg:tags":[
        "broker",
        "mortgage"
    ],
    "wof:name":"American Mortgage Services",
    "wof:placetype":"venue"
},
  "geometry": {"coordinates":[-118.578003,34.201],"type":"Point"}
}