{
  "type": "Feature",
  "properties": {
    "iso:country":"US",
    "sg:address":"3101 S San Pedro St",
    "sg:city":"Los Angeles",
    "sg:classifiers":[
        {
            "category":"Food & Beverages",
            "subcategory":"Groceries & Convenience Stores",
            "type":"Retail Goods"
        }
    ],
    "sg:phone":"+1 323 232 6627",
    "sg:postcode":"90011",
    "sg:province":"CA",
    "wof:name":"Dania's Mini Market",
    "wof:placetype":"venue"
},
  "geometry": {"coordinates":[-118.26416,34.017087],"type":"Point"}
}