{
  "type": "Feature",
  "properties": {
    "iso:country":"US",
    "sg:address":"2701 Gamble Ct",
    "sg:city":"Hayward",
    "sg:classifiers":[
        {
            "category":"Professional",
            "type":"Services"
        }
    ],
    "sg:phone":"+1 510 537 1592",
    "sg:postcode":"94542",
    "sg:province":"CA",
    "sg:tags":[
        "establishment"
    ],
    "wof:name":"Basf Corp",
    "wof:placetype":"venue"
},
  "geometry": {"coordinates":[-122.040674,37.650181],"type":"Point"}
}