{
  "type": "Feature",
  "properties": {
    "addr:full":"901 H St Suite 200 Sacramento CA 95814",
    "addr:housenumber":"901",
    "addr:postcode":"95814",
    "addr:street":"H St Suite 200",
    "iso:country":"US",
    "sg:address":"901 H St Suite 200",
    "sg:city":"Sacramento",
    "sg:classifiers":[
        {
            "category":"Professional",
            "subcategory":"Lawyer & Legal Services",
            "type":"Services"
        }
    ],
    "sg:phone":"+1 916 498 1776",
    "sg:postcode":"95814",
    "sg:province":"CA",
    "sg:tags":[
        "attorney",
        "criminal",
        "duo",
        "violence",
        "domestic",
        "damage",
        "drug",
        "charge",
        "accident",
        "property",
        "dwi",
        "law"
    ],
    "sg:website":"http://www.brennan-defense.com",
    "wof:name":"Brennan Defense",
    "wof:placetype":"venue"
},
  "geometry": {"coordinates":[-121.49382,38.582859],"type":"Point"}
}