{
  "type": "Feature",
  "properties": {
    "iso:country":"US",
    "sg:address":"6851 Lennox Ave",
    "sg:city":"Van Nuys",
    "sg:classifiers":[
        {
            "category":"Social Services",
            "type":"Services"
        }
    ],
    "sg:phone":"+1 818 989 9214",
    "sg:postcode":"91405",
    "sg:province":"CA",
    "sg:tags":[
        "counselor",
        "marriage",
        "family"
    ],
    "wof:name":"Wrap Family Svc",
    "wof:placetype":"venue"
},
  "geometry": {"coordinates":[-118.445521,34.19483],"type":"Point"}
}