{
  "type": "Feature",
  "properties": {
    "iso:country":"US",
    "sg:address":"7522 Lankershim Blvd",
    "sg:city":"North Hollywood",
    "sg:classifiers":[
        {
            "category":"Personal",
            "subcategory":"Barber",
            "type":"Services"
        }
    ],
    "sg:phone":"+1 818 765 2452",
    "sg:postcode":"91605",
    "sg:province":"CA",
    "wof:name":"Style-Rite Barber Shop",
    "wof:placetype":"venue"
},
  "geometry": {"coordinates":[-118.38800000000001,34.207001],"type":"Point"}
}