{
  "type": "Feature",
  "properties": {
    "addr:full":"20624 Lower Hillview Dr Sonora CA 95370",
    "addr:postcode":"20624;95370",
    "addr:street":"Lower Hillview Dr",
    "iso:country":"US",
    "sg:address":"20624 Lower Hillview Dr",
    "sg:city":"Sonora",
    "sg:classifiers":[
        {
            "category":"Manufacturing",
            "subcategory":"Lumber",
            "type":"Manufacturing & Wholesale Goods"
        }
    ],
    "sg:phone":"+1 209 532 6182",
    "sg:postcode":"95370",
    "sg:province":"CA",
    "sg:tags":[
        "fire",
        "forest"
    ],
    "wof:name":"Forest Fires",
    "wof:placetype":"venue"
},
  "geometry": {"coordinates":[-120.332353,37.999511],"type":"Point"}
}