{
  "type": "Feature",
  "properties": {
    "addr:full":"583 Haight St San Francisco CA 94117",
    "addr:housenumber":"583",
    "addr:postcode":"94117",
    "addr:street":"Haight St",
    "iso:country":"US",
    "sg:address":"583 Haight St",
    "sg:city":"San Francisco",
    "sg:classifiers":[
        {
            "category":"Personal",
            "subcategory":"Beauty Salon",
            "type":"Services"
        }
    ],
    "sg:phone":"+1 415 864 8141",
    "sg:postcode":"94117",
    "sg:province":"CA",
    "sg:tags":[
        "hair"
    ],
    "wof:name":"Blow dry",
    "wof:placetype":"venue"
},
  "geometry": {"coordinates":[-122.431684,37.771944],"type":"Point"}
}