{
  "type": "Feature",
  "properties": {
    "iso:country":"US",
    "sg:address":"418 N La Cienega Boulevard",
    "sg:city":"West Hollywood",
    "sg:classifiers":[
        {
            "category":"Building & Trades",
            "subcategory":"Construction",
            "type":"Services"
        },
        {
            "category":"Home & Garden",
            "subcategory":"Furniture",
            "type":"Retail Goods"
        }
    ],
    "sg:phone":"+1 310 659 8010",
    "sg:postcode":"90048",
    "sg:province":"CA",
    "sg:tags":[
        "interior",
        "design",
        "store"
    ],
    "wof:name":"What",
    "wof:placetype":"venue"
},
  "geometry": {"coordinates":[-118.376438,34.078668],"type":"Point"}
}