{
  "type": "Feature",
  "properties": {
    "addr:full":"1156 High St Santa Cruz CA 95064",
    "addr:housenumber":"1156",
    "addr:postcode":"95064",
    "addr:street":"High St",
    "iso:country":"US",
    "sg:address":"1156 High St",
    "sg:city":"Santa Cruz",
    "sg:classifiers":[
        {
            "category":"Building & Trades",
            "subcategory":"Construction",
            "type":"Services"
        },
        {
            "category":"Real Estate",
            "subcategory":"Real Estate Operator",
            "type":"Services"
        }
    ],
    "sg:phone":"+1 831 425 5370",
    "sg:postcode":"95064",
    "sg:province":"CA",
    "sg:tags":[
        "house",
        "parks"
    ],
    "wof:name":"Physical Science Bldg",
    "wof:placetype":"venue"
},
  "geometry": {"coordinates":[-122.053746,36.977192],"type":"Point"}
}