{
  "type": "Feature",
  "properties": {
    "iso:country":"US",
    "sg:address":"632 Williams Rd",
    "sg:city":"Salinas",
    "sg:classifiers":[
        {
            "category":"Professional",
            "type":"Services"
        }
    ],
    "sg:phone":"+1 831 757 1200",
    "sg:postcode":"93905",
    "sg:province":"CA",
    "sg:tags":[
        "establishment"
    ],
    "wof:name":"Discoteca Exitos Latinos",
    "wof:placetype":"venue"
},
  "geometry": {"coordinates":[-121.605545,36.680305],"type":"Point"}
}