{
  "type": "Feature",
  "properties": {
    "addr:full":"630 Loyola Ave Carson CA 90746",
    "addr:housenumber":"630",
    "addr:postcode":"90746",
    "addr:street":"Loyola Ave",
    "iso:country":"US",
    "sg:address":"630 Loyola Ave",
    "sg:city":"Carson",
    "sg:classifiers":[
        {
            "category":"Real Estate",
            "subcategory":"Real Estate Agent",
            "type":"Services"
        }
    ],
    "sg:phone":"+1 310 769 6222",
    "sg:postcode":"90746",
    "sg:province":"CA",
    "sg:tags":[
        "consultant"
    ],
    "wof:name":"Brown Carter & Assoc LLC",
    "wof:placetype":"venue"
},
  "geometry": {"coordinates":[-118.26374800000001,33.859769],"type":"Point"}
}