{
  "type": "Feature",
  "properties": {
    "addr:full":"490 South Van Ness San Francisco CA 94103",
    "addr:housenumber":"490",
    "addr:postcode":"94103",
    "addr:street":"South Van Ness",
    "iso:country":"US",
    "sg:address":"490 South Van Ness",
    "sg:city":"San Francisco",
    "sg:classifiers":[
        {
            "category":"Retail",
            "subcategory":"Auto Repair",
            "type":"Services"
        }
    ],
    "sg:phone":"+1 415 431 6550",
    "sg:postcode":"94103",
    "sg:province":"CA",
    "wof:name":"Quality Tune 39",
    "wof:placetype":"venue"
},
  "geometry": {"coordinates":[-122.417709,37.7654],"type":"Point"}
}