{
  "type": "Feature",
  "properties": {
    "iso:country":"US",
    "sg:address":"613 Justin Ave",
    "sg:city":"Glendale",
    "sg:classifiers":[
        {
            "category":"Professional",
            "subcategory":"Advertising",
            "type":"Services"
        }
    ],
    "sg:phone":"+1 818 459 0411",
    "sg:postcode":"91201",
    "sg:province":"CA",
    "sg:website":"www.cygnetstamping.com",
    "wof:name":"CYG.NET",
    "wof:placetype":"venue"
},
  "geometry": {"coordinates":[-118.293504,34.164298],"type":"Point"}
}