{
  "type": "Feature",
  "properties": {
    "addr:full":"348 S Cedros Ave Solana Beach CA 92075",
    "addr:housenumber":"348",
    "addr:postcode":"92075",
    "addr:street":"S Cedros Ave",
    "iso:country":"US",
    "sg:address":"348 S Cedros Ave",
    "sg:city":"Solana Beach",
    "sg:classifiers":[
        {
            "category":"Wholesale",
            "subcategory":"Jewelry",
            "type":"Manufacturing & Wholesale Goods"
        }
    ],
    "sg:phone":"+1 760 753 2865",
    "sg:postcode":"92075",
    "sg:province":"CA",
    "sg:tags":[
        "jeweler"
    ],
    "wof:name":"Jewelry By Cini",
    "wof:placetype":"venue"
},
  "geometry": {"coordinates":[-117.27040100000001,32.991374],"type":"Point"}
}