{
  "type": "Feature",
  "properties": {
    "addr:full":"181 N Oak Knoll Ave Pasadena CA 91101",
    "addr:housenumber":"181",
    "addr:postcode":"91101",
    "addr:street":"N Oak Knoll Ave",
    "iso:country":"US",
    "sg:address":"181 N Oak Knoll Ave",
    "sg:city":"Pasadena",
    "sg:classifiers":[
        {
            "category":"Social Services",
            "type":"Services"
        }
    ],
    "sg:phone":"+1 626 796 7994",
    "sg:postcode":"91101",
    "sg:province":"CA",
    "sg:tags":[
        "counselor",
        "marriage",
        "family"
    ],
    "wof:name":"Cathryn Trzeciak",
    "wof:placetype":"venue"
},
  "geometry": {"coordinates":[-118.13544,34.147981],"type":"Point"}
}