{
  "type": "Feature",
  "properties": {
    "iso:country":"US",
    "sg:address":"920 W 18th St",
    "sg:city":"Merced",
    "sg:classifiers":[
        {
            "category":"Retail",
            "subcategory":"Repair Shop",
            "type":"Services"
        }
    ],
    "sg:phone":"+1 209 723 4712",
    "sg:postcode":"95340",
    "sg:province":"CA",
    "sg:tags":[
        "equipment",
        "video"
    ],
    "wof:name":"Moosehead VCR & Stereo Repair",
    "wof:placetype":"venue"
},
  "geometry": {"coordinates":[-120.490106,37.305016],"type":"Point"}
}