{
  "type": "Feature",
  "properties": {
    "addr:full":"1205 Burton Rd Perris CA 92570",
    "addr:housenumber":"1205",
    "addr:postcode":"92570",
    "addr:street":"Burton Rd",
    "iso:country":"US",
    "sg:address":"1205 Burton Rd",
    "sg:city":"Perris",
    "sg:classifiers":[
        {
            "category":"Sports & Exercise",
            "subcategory":"Race Track",
            "type":"Entertainment"
        }
    ],
    "sg:phone":"+1 951 657 7441",
    "sg:postcode":"92570",
    "sg:province":"CA",
    "wof:name":"Perris Raceway",
    "wof:placetype":"venue"
},
  "geometry": {"coordinates":[-117.25666099999999,33.775565],"type":"Point"}
}