{
  "type": "Feature",
  "properties": {
    "iso:country":"US",
    "sg:address":"2717 Rodney St",
    "sg:city":"Newbury Park",
    "sg:classifiers":[
        {
            "category":"Building & Trades",
            "subcategory":"Construction",
            "type":"Services"
        }
    ],
    "sg:phone":"+1 805 375 1950",
    "sg:postcode":"91320",
    "sg:province":"CA",
    "sg:tags":[
        "painter"
    ],
    "wof:name":"Reliable Painting Co",
    "wof:placetype":"venue"
},
  "geometry": {"coordinates":[-118.933936,34.186763],"type":"Point"}
}