{
  "type": "Feature",
  "properties": {
    "iso:country":"US",
    "sg:address":"6512 Painter Ave",
    "sg:city":"Whittier",
    "sg:classifiers":[
        {
            "category":"Health Services",
            "subcategory":"Doctor",
            "type":"Services"
        }
    ],
    "sg:phone":"+1 562 698 9743",
    "sg:postcode":"90601",
    "sg:province":"CA",
    "sg:tags":[
        "physician",
        "surgeon"
    ],
    "wof:name":"Paul F Jacobsen MD",
    "wof:placetype":"venue"
},
  "geometry": {"coordinates":[-118.032605,33.981041],"type":"Point"}
}