{
  "type": "Feature",
  "properties": {
    "addr:full":"411 N Quarantina St Santa Barbara CA 93103",
    "addr:housenumber":"411",
    "addr:postcode":"93103",
    "addr:street":"N Quarantina St",
    "iso:country":"US",
    "sg:address":"411 N Quarantina St",
    "sg:city":"Santa Barbara",
    "sg:classifiers":[
        {
            "category":"Retail",
            "subcategory":"Repair Shop",
            "type":"Services"
        }
    ],
    "sg:phone":"+1 805 965 2710",
    "sg:postcode":"93103",
    "sg:province":"CA",
    "sg:tags":[
        "refinishing",
        "furniture"
    ],
    "wof:name":"Santa Barbara Antique Rstrtn",
    "wof:placetype":"venue"
},
  "geometry": {"coordinates":[-119.686893,34.423581],"type":"Point"}
}