{
  "type": "Feature",
  "properties": {
    "iso:country":"US",
    "sg:address":"8795 Folsom Blvd",
    "sg:city":"Sacramento",
    "sg:classifiers":[
        {
            "category":"Professional",
            "subcategory":"Engineering",
            "type":"Services"
        }
    ],
    "sg:phone":"+1 916 383 6000",
    "sg:postcode":"95826",
    "sg:province":"CA",
    "sg:tags":[
        "engineer"
    ],
    "sg:website":"www.iec-corporation.com",
    "wof:name":"Integrated Engineers & Contr",
    "wof:placetype":"venue"
},
  "geometry": {"coordinates":[-121.375291,38.553078],"type":"Point"}
}