{
  "type": "Feature",
  "properties": {
    "iso:country":"US",
    "sg:address":"750 Nolan Ave",
    "sg:city":"Chula Vista",
    "sg:classifiers":[
        {
            "category":"Wholesale",
            "subcategory":"Groceries",
            "type":"Manufacturing & Wholesale Goods"
        }
    ],
    "sg:phone":"+1 619 427 5851",
    "sg:postcode":"91910",
    "sg:province":"CA",
    "sg:website":"www.cambridgediet.com",
    "wof:name":"Cambridge Diet",
    "wof:placetype":"venue"
},
  "geometry": {"coordinates":[-117.049041,32.633029],"type":"Point"}
}