{
  "type": "Feature",
  "properties": {
    "addr:full":"1757 Barcelona St Livermore CA 94550",
    "addr:housenumber":"1757",
    "addr:postcode":"94550",
    "addr:street":"Barcelona St",
    "iso:country":"US",
    "sg:address":"1757 Barcelona St",
    "sg:city":"Livermore",
    "sg:classifiers":[
        {
            "category":"Travel",
            "subcategory":"Travel Agent",
            "type":"Entertainment"
        }
    ],
    "sg:phone":"+1 925 449 1904",
    "sg:postcode":"94550",
    "sg:province":"CA",
    "sg:tags":[
        "agency",
        "bureau"
    ],
    "wof:name":"D & J Travel",
    "wof:placetype":"venue"
},
  "geometry": {"coordinates":[-121.782106,37.661711],"type":"Point"}
}