{
  "type": "Feature",
  "properties": {
    "addr:full":"6121 El Toro Ct San Jose CA 95109",
    "addr:housenumber":"6121",
    "addr:postcode":"95109",
    "addr:street":"El Toro Ct",
    "iso:country":"US",
    "sg:address":"6121 El Toro Ct",
    "sg:city":"San Jose",
    "sg:classifiers":[
        {
            "category":"Personal",
            "subcategory":"Hair Removal",
            "type":"Services"
        }
    ],
    "sg:phone":"+1 408 281 7023",
    "sg:postcode":"95109",
    "sg:province":"CA",
    "sg:website":"www.abeautifulchange.com",
    "wof:name":"A Beautiful Change",
    "wof:placetype":"venue"
},
  "geometry": {"coordinates":[-121.849121,37.238126],"type":"Point"}
}