{
  "type": "Feature",
  "properties": {
    "addr:full":"2171 Junipero Serra Blvd Daly City CA 94014",
    "addr:housenumber":"2171",
    "addr:postcode":"94014",
    "addr:street":"Junipero Serra Blvd",
    "iso:country":"US",
    "sg:address":"2171 Junipero Serra Blvd",
    "sg:city":"Daly City",
    "sg:classifiers":[
        {
            "category":"Professional",
            "subcategory":"Lawyer & Legal Services",
            "type":"Services"
        }
    ],
    "sg:phone":"+1 650 994 5000",
    "sg:postcode":"94014",
    "sg:province":"CA",
    "wof:name":"Johnson Thomas M Law Offices of",
    "wof:placetype":"venue"
},
  "geometry": {"coordinates":[-122.471001,37.698299],"type":"Point"}
}