{
  "type": "Feature",
  "properties": {
    "iso:country":"US",
    "sg:address":"9478 W Olympic Blvd",
    "sg:city":"Beverly Hills",
    "sg:classifiers":[
        {
            "category":"Shopping",
            "type":"Retail Goods"
        }
    ],
    "sg:phone":"+1 310 286 2030",
    "sg:postcode":"90212",
    "sg:province":"CA",
    "sg:tags":[
        "coin",
        "dealer",
        "supply"
    ],
    "wof:name":"First American Numismatics",
    "wof:placetype":"venue"
},
  "geometry": {"coordinates":[-118.399752,34.059612],"type":"Point"}
}