{
  "type": "Feature",
  "properties": {
    "iso:country":"US",
    "sg:address":"20259 Pso del Prado",
    "sg:city":"Walnut",
    "sg:classifiers":[
        {
            "category":"Manufacturing",
            "subcategory":"Printing",
            "type":"Manufacturing & Wholesale Goods"
        }
    ],
    "sg:phone":"+1 909 595 4386",
    "sg:postcode":"91789",
    "sg:province":"CA",
    "sg:tags":[
        "offset"
    ],
    "wof:name":"Sunset Printing",
    "wof:placetype":"venue"
},
  "geometry": {"coordinates":[-117.859048,34.012663],"type":"Point"}
}