{
  "type": "Feature",
  "properties": {
    "iso:country":"US",
    "sg:address":"23106 Broadmoor Ct",
    "sg:city":"Auburn",
    "sg:classifiers":[
        {
            "category":"Wholesale",
            "subcategory":"Groceries",
            "type":"Manufacturing & Wholesale Goods"
        }
    ],
    "sg:phone":"+1 650 627 9598",
    "sg:postcode":"95602",
    "sg:province":"CA",
    "sg:tags":[
        "food",
        "broker"
    ],
    "wof:name":"Prospect Food Brokerage",
    "wof:placetype":"venue"
},
  "geometry": {"coordinates":[-121.059972,39.045932],"type":"Point"}
}