{
  "type": "Feature",
  "properties": {
    "addr:full":"3040 E Coronado St Anaheim CA 92806",
    "addr:housenumber":"3040",
    "addr:postcode":"92806",
    "addr:street":"E Coronado St",
    "iso:country":"US",
    "sg:address":"3040 E Coronado St",
    "sg:city":"Anaheim",
    "sg:classifiers":[
        {
            "category":"Building & Trades",
            "subcategory":"Construction",
            "type":"Services"
        }
    ],
    "sg:phone":"+1 714 414 0209",
    "sg:postcode":"92806",
    "sg:province":"CA",
    "sg:tags":[
        "contractor"
    ],
    "wof:name":"JLE Contracting Inc",
    "wof:placetype":"venue"
},
  "geometry": {"coordinates":[-117.861059,33.853829],"type":"Point"}
}