{
  "type": "Feature",
  "properties": {
    "addr:full":"747 Camden Ave Campbell CA 95008",
    "addr:housenumber":"747",
    "addr:postcode":"95008",
    "addr:street":"Camden Ave",
    "iso:country":"US",
    "sg:address":"747 Camden Ave",
    "sg:city":"Campbell",
    "sg:classifiers":[
        {
            "category":"Professional",
            "subcategory":"Computer Services",
            "type":"Services"
        }
    ],
    "sg:phone":"+1 408 866 0656",
    "sg:postcode":"95008",
    "sg:province":"CA",
    "sg:website":"www.controlnet.com",
    "wof:name":"Controlnet",
    "wof:placetype":"venue"
},
  "geometry": {"coordinates":[-121.950181,37.276551],"type":"Point"}
}