{
  "type": "Feature",
  "properties": {
    "iso:country":"US",
    "sg:address":"7761 Dancy Rd",
    "sg:city":"San Diego",
    "sg:classifiers":[
        {
            "category":"Building & Trades",
            "subcategory":"Construction",
            "type":"Services"
        }
    ],
    "sg:phone":"+1 858 695 2495",
    "sg:postcode":"92126",
    "sg:province":"CA",
    "sg:tags":[
        "painter"
    ],
    "wof:name":"R C Painting",
    "wof:placetype":"venue"
},
  "geometry": {"coordinates":[-117.157607,32.907867],"type":"Point"}
}