{
  "type": "Feature",
  "properties": {
    "iso:country":"US",
    "sg:address":"4072 Boone St",
    "sg:city":"San Diego",
    "sg:classifiers":[
        {
            "category":"Real Estate",
            "subcategory":"Real Estate Agent",
            "type":"Services"
        }
    ],
    "sg:phone":"+1 858 272 8272",
    "sg:postcode":"92117",
    "sg:province":"CA",
    "wof:name":"Thomas Morton Enterprises",
    "wof:placetype":"venue"
},
  "geometry": {"coordinates":[-117.20319499999999,32.812998],"type":"Point"}
}