{
  "type": "Feature",
  "properties": {
    "addr:full":"1025 S 5th St San Jose CA 95112",
    "addr:housenumber":"1025",
    "addr:postcode":"95112",
    "addr:street":"S 5Th St",
    "iso:country":"US",
    "sg:address":"1025 S 5th St",
    "sg:city":"San Jose",
    "sg:classifiers":[
        {
            "category":"Manufacturing",
            "subcategory":"Apparel",
            "type":"Manufacturing & Wholesale Goods"
        }
    ],
    "sg:phone":"+1 408 287 8945",
    "sg:postcode":"95112",
    "sg:province":"CA",
    "sg:tags":[
        "sewing",
        "contractor"
    ],
    "wof:name":"Western Mountain Sports",
    "wof:placetype":"venue"
},
  "geometry": {"coordinates":[-121.875302,37.323503],"type":"Point"}
}