{
  "type": "Feature",
  "properties": {
    "addr:full":"1500 E Hamilton Ave Campbell CA 95008",
    "addr:housenumber":"1500",
    "addr:postcode":"95008",
    "addr:street":"E Hamilton Ave",
    "iso:country":"US",
    "sg:address":"1500 E Hamilton Ave",
    "sg:city":"Campbell",
    "sg:classifiers":[
        {
            "category":"Real Estate",
            "subcategory":"Real Estate Agent",
            "type":"Services"
        }
    ],
    "sg:phone":"+1 408 879 9393",
    "sg:postcode":"95008",
    "sg:province":"CA",
    "wof:name":"Home Buyers Exchange",
    "wof:placetype":"venue"
},
  "geometry": {"coordinates":[-121.923506,37.294305],"type":"Point"}
}