{
  "type": "Feature",
  "properties": {
    "iso:country":"US",
    "sg:address":"4900 Hopyard Rd",
    "sg:city":"Pleasanton",
    "sg:classifiers":[
        {
            "category":"Professional",
            "subcategory":"Lawyer & Legal Services",
            "type":"Services"
        }
    ],
    "sg:phone":"+1 925 734 9000",
    "sg:postcode":"94588",
    "sg:province":"CA",
    "sg:tags":[
        "divorce",
        "attorney",
        "practice",
        "family",
        "law"
    ],
    "sg:website":"http://www.bhp-law.com",
    "wof:name":"Blaha, Jerome A",
    "wof:placetype":"venue"
},
  "geometry": {"coordinates":[-121.90374799999999,37.69421],"type":"Point"}
}