{
  "type": "Feature",
  "properties": {
    "iso:country":"US",
    "sg:address":"1639 S Hacienda Blvd",
    "sg:city":"Hacienda Heights",
    "sg:classifiers":[
        {
            "category":"Freight",
            "type":"Transportation"
        }
    ],
    "sg:phone":"+1 626 287 7638",
    "sg:postcode":"91745",
    "sg:province":"CA",
    "wof:name":"L & T Freightway",
    "wof:placetype":"venue"
},
  "geometry": {"coordinates":[-117.965715,34.002904],"type":"Point"}
}