{
  "type": "Feature",
  "properties": {
    "addr:full":"4 W 4th St Eureka CA 95501",
    "addr:housenumber":"4",
    "addr:postcode":"95501",
    "addr:street":"W 4Th St",
    "iso:country":"US",
    "sg:address":"4 W 4th St",
    "sg:city":"Eureka",
    "sg:classifiers":[
        {
            "category":"Professional",
            "type":"Services"
        }
    ],
    "sg:phone":"+1 707 476 0418",
    "sg:postcode":"95501",
    "sg:province":"CA",
    "sg:tags":[
        "establishment"
    ],
    "wof:name":"Wax Creatives Co",
    "wof:placetype":"venue"
},
  "geometry": {"coordinates":[-124.171492,40.801937],"type":"Point"}
}