{
  "type": "Feature",
  "properties": {
    "addr:full":"1179 Divisadero St San Francisco CA 94115",
    "addr:housenumber":"1179",
    "addr:postcode":"94115",
    "addr:street":"Divisadero St",
    "iso:country":"US",
    "sg:address":"1179 Divisadero St",
    "sg:city":"San Francisco",
    "sg:classifiers":[
        {
            "category":"Retail",
            "subcategory":"Laundry & Dry Cleaning",
            "type":"Services"
        }
    ],
    "sg:phone":"+1 415 563 5131",
    "sg:postcode":"94115",
    "sg:province":"CA",
    "wof:name":"Divisadero Heights Cleaner",
    "wof:placetype":"venue"
},
  "geometry": {"coordinates":[-122.438965,37.780466],"type":"Point"}
}