{
  "type": "Feature",
  "properties": {
    "addr:full":"1808 Hemlock Ave San Mateo CA 94401",
    "addr:housenumber":"1808",
    "addr:postcode":"94401",
    "addr:street":"Hemlock Ave",
    "iso:country":"US",
    "sg:address":"1808 Hemlock Ave",
    "sg:city":"San Mateo",
    "sg:classifiers":[
        {
            "category":"Arts & Performance",
            "subcategory":"Theater",
            "type":"Entertainment"
        }
    ],
    "sg:phone":"+1 650 458 9218",
    "sg:postcode":"94401",
    "sg:province":"CA",
    "sg:tags":[
        "entertainer"
    ],
    "wof:name":"Hot Teaze Boutique",
    "wof:placetype":"venue"
},
  "geometry": {"coordinates":[-122.30268,37.566873],"type":"Point"}
}