{
  "type": "Feature",
  "properties": {
    "addr:full":"915 L St Sacramento CA 95814",
    "addr:housenumber":"915",
    "addr:postcode":"95814",
    "addr:street":"L St",
    "iso:country":"US",
    "sg:address":"915 L St",
    "sg:city":"Sacramento",
    "sg:classifiers":[
        {
            "category":"Government",
            "subcategory":"Office",
            "type":"Public Place"
        }
    ],
    "sg:phone":"+1 916 323 4071",
    "sg:postcode":"95814",
    "sg:province":"CA",
    "sg:tags":[
        "regulatory",
        "banking"
    ],
    "wof:name":"Dept of Finance",
    "wof:placetype":"venue"
},
  "geometry": {"coordinates":[-121.494545,38.578228],"type":"Point"}
}