{
  "type": "Feature",
  "properties": {
    "addr:full":"26533 Adell St Madera CA 93638",
    "addr:postcode":"26533;93638",
    "addr:street":"Adell St",
    "iso:country":"US",
    "sg:address":"26533 Adell St",
    "sg:city":"Madera",
    "sg:classifiers":[
        {
            "category":"Place Of Worship",
            "subcategory":"Church",
            "type":"Public Place"
        },
        {
            "category":"Place Of Worship",
            "type":"Public Place"
        }
    ],
    "sg:phone":"+1 559 479 8359",
    "sg:postcode":"93638",
    "sg:province":"CA",
    "sg:tags":[
        "christ",
        "churches-community"
    ],
    "wof:name":"Family Community Church Fl",
    "wof:placetype":"venue"
},
  "geometry": {"coordinates":[-120.06398799999999,36.9828],"type":"Point"}
}