{
  "type": "Feature",
  "properties": {
    "addr:full":"1365 S Acacia Ave Fullerton CA 92831",
    "addr:housenumber":"1365",
    "addr:postcode":"92831",
    "addr:street":"S Acacia Ave",
    "iso:country":"US",
    "sg:address":"1365 S Acacia Ave",
    "sg:city":"Fullerton",
    "sg:classifiers":[
        {
            "category":"Wholesale",
            "subcategory":"Medical Equipment & Supplies",
            "type":"Manufacturing & Wholesale Goods"
        }
    ],
    "sg:phone":"+1 949 939 4406",
    "sg:postcode":"92831",
    "sg:province":"CA",
    "sg:tags":[
        "apparatus",
        "x-ray"
    ],
    "wof:name":"Cura Medical Technologies",
    "wof:placetype":"venue"
},
  "geometry": {"coordinates":[-117.898036,33.858066],"type":"Point"}
}