{
  "type": "Feature",
  "properties": {
    "addr:full":"25228 Copa Del Oro Dr Hayward CA 94545",
    "addr:housenumber":"25228",
    "addr:postcode":"94545",
    "addr:street":"Copa Del Oro Dr",
    "iso:country":"US",
    "sg:address":"25228 Copa Del Oro Dr",
    "sg:city":"Hayward",
    "sg:classifiers":[
        {
            "category":"Banks & Credit Unions",
            "subcategory":"Financial Services",
            "type":"Services"
        }
    ],
    "sg:phone":"+1 510 940 2662",
    "sg:postcode":"94545",
    "sg:province":"CA",
    "sg:tags":[
        "broker",
        "mortgage"
    ],
    "wof:name":"Union City Mortgage",
    "wof:placetype":"venue"
},
  "geometry": {"coordinates":[-122.101997,37.644798],"type":"Point"}
}