{
  "type": "Feature",
  "properties": {
    "addr:full":"100 Drakes Landing Rd Greenbrae CA 94904",
    "addr:housenumber":"100",
    "addr:postcode":"94904",
    "addr:street":"Drakes Landing Rd",
    "iso:country":"US",
    "sg:address":"100 Drakes Landing Rd",
    "sg:city":"Greenbrae",
    "sg:classifiers":[
        {
            "category":"Organizations",
            "subcategory":"Membership Organization",
            "type":"Services"
        }
    ],
    "sg:phone":"+1 415 925 1200",
    "sg:postcode":"94904",
    "sg:province":"CA",
    "sg:tags":[
        "automobile",
        "travel",
        "agency"
    ],
    "wof:name":"AAA Travel Agency",
    "wof:placetype":"venue"
},
  "geometry": {"coordinates":[-122.518299,37.943826],"type":"Point"}
}