{
  "type": "Feature",
  "properties": {
    "addr:full":"9560 Cuyamaca St Ste 101 Santee CA 92071",
    "addr:housenumber":"9560",
    "addr:postcode":"92071",
    "addr:street":"Cuyamaca St Ste 101",
    "iso:country":"US",
    "sg:address":"9560 Cuyamaca St Ste 101",
    "sg:city":"Santee",
    "sg:classifiers":[
        {
            "category":"Personal",
            "subcategory":"Massage",
            "type":"Services"
        },
        {
            "category":"Personal",
            "subcategory":"Day Spa",
            "type":"Services"
        }
    ],
    "sg:phone":"+1 619 672 1167",
    "sg:postcode":"92071",
    "sg:province":"CA",
    "wof:name":"Felicity Holistic Healing Center",
    "wof:placetype":"venue"
},
  "geometry": {"coordinates":[-116.98375799999999,32.851427],"type":"Point"}
}