{
  "type": "Feature",
  "properties": {
    "addr:full":"44900 San Pablo Ave Palm Desert CA 92260",
    "addr:housenumber":"44900",
    "addr:postcode":"ca 92260",
    "addr:street":"San Pablo Ave",
    "iso:country":"US",
    "sg:address":"44900 San Pablo Ave",
    "sg:city":"Palm Desert",
    "sg:classifiers":[
        {
            "category":"Shopping",
            "subcategory":"Computers & Home Electronics",
            "type":"Retail Goods"
        }
    ],
    "sg:phone":"+1 760 779 1001",
    "sg:postcode":"92260",
    "sg:province":"CA",
    "sg:tags":[
        "equipment",
        "dealer"
    ],
    "sg:website":"www.computer-gallery.com",
    "wof:name":"Computer Gallery",
    "wof:placetype":"venue"
},
  "geometry": {"coordinates":[-116.38244400000001,33.722137],"type":"Point"}
}