{
  "type": "Feature",
  "properties": {
    "iso:country":"US",
    "sg:address":"28201 Date Palm Dr",
    "sg:city":"Cathedral City",
    "sg:classifiers":[
        {
            "category":"Food & Beverages",
            "subcategory":"Groceries & Convenience Stores",
            "type":"Retail Goods"
        }
    ],
    "sg:phone":"+1 760 320 1546",
    "sg:postcode":"92234",
    "sg:province":"CA",
    "wof:name":"Shell",
    "wof:placetype":"venue"
},
  "geometry": {"coordinates":[-116.458377,33.839475],"type":"Point"}
}