{
  "type": "Feature",
  "properties": {
    "iso:country":"US",
    "sg:address":"2314 W Florence Ave",
    "sg:city":"Los Angeles",
    "sg:classifiers":[
        {
            "category":"Building & Trades",
            "subcategory":"Electrical",
            "type":"Services"
        }
    ],
    "sg:phone":"+1 323 293 3304",
    "sg:postcode":"90043",
    "sg:province":"CA",
    "sg:tags":[
        "electrical",
        "contractor"
    ],
    "wof:name":"McKay Electric",
    "wof:placetype":"venue"
},
  "geometry": {"coordinates":[-118.318734,33.974581],"type":"Point"}
}