{
  "type": "Feature",
  "properties": {
    "addr:full":"1378 E Walnut St Pasadena CA 91106",
    "addr:housenumber":"1378",
    "addr:postcode":"91106",
    "addr:street":"E Walnut St",
    "iso:country":"US",
    "sg:address":"1378 E Walnut St",
    "sg:city":"Pasadena",
    "sg:classifiers":[
        {
            "category":"Building & Trades",
            "subcategory":"Cleaning & Sanitation",
            "type":"Services"
        }
    ],
    "sg:phone":"+1 626 229 9090",
    "sg:postcode":"91106",
    "sg:province":"CA",
    "sg:tags":[
        "home"
    ],
    "sg:website":"www.mollymaid.com/",
    "wof:name":"Molly Maid",
    "wof:placetype":"venue"
},
  "geometry": {"coordinates":[-118.12200199999999,34.149399],"type":"Point"}
}