{
  "type": "Feature",
  "properties": {
    "addr:full":"1961 State Rte 4 Arnold CA 95223",
    "addr:housenumber":"1961",
    "addr:postcode":"95223",
    "addr:street":"State Rte 4",
    "iso:country":"US",
    "sg:address":"1961 State Rte 4",
    "sg:city":"Arnold",
    "sg:classifiers":[
        {
            "category":"Building & Trades",
            "subcategory":"Cleaning & Sanitation",
            "type":"Services"
        }
    ],
    "sg:phone":"+1 209 795 1346",
    "sg:postcode":"95223",
    "sg:province":"CA",
    "sg:tags":[
        "window"
    ],
    "wof:name":"Betts Maintenance & Supply Svc",
    "wof:placetype":"venue"
},
  "geometry": {"coordinates":[-120.358667,38.249924],"type":"Point"}
}