{
  "type": "Feature",
  "properties": {
    "iso:country":"US",
    "sg:address":"233 Gonzalez Dr",
    "sg:city":"San Francisco",
    "sg:classifiers":[
        {
            "category":"Banks & Credit Unions",
            "subcategory":"Bank",
            "type":"Services"
        }
    ],
    "sg:phone":"+1 415 672 2043",
    "sg:postcode":"94132",
    "sg:province":"CA",
    "sg:tags":[
        "mortgage"
    ],
    "wof:name":"Macrocapital",
    "wof:placetype":"venue"
},
  "geometry": {"coordinates":[-122.475695,37.716956],"type":"Point"}
}