{
  "type": "Feature",
  "properties": {
    "iso:country":"US",
    "sg:address":"2150 Marx Way",
    "sg:city":"Anderson",
    "sg:classifiers":[
        {
            "category":"Manufacturing",
            "subcategory":"Metals",
            "type":"Manufacturing & Wholesale Goods"
        }
    ],
    "sg:phone":"+1 530 365 1399",
    "sg:postcode":"96007",
    "sg:province":"CA",
    "sg:tags":[
        "coating",
        "powder"
    ],
    "wof:name":"A C Powder Coating",
    "wof:placetype":"venue"
},
  "geometry": {"coordinates":[-122.29097,40.441569],"type":"Point"}
}