{
  "type": "Feature",
  "properties": {
    "iso:country":"US",
    "sg:address":"5701 H Street",
    "sg:city":"Sacramento",
    "sg:classifiers":[
        {
            "category":"Retail",
            "subcategory":"Veterinary Services",
            "type":"Services"
        }
    ],
    "sg:phone":"+1 916 451 7213",
    "sg:postcode":"95819",
    "sg:province":"CA",
    "sg:tags":[
        "veterinarian"
    ],
    "wof:name":"True Erin DVM",
    "wof:placetype":"venue"
},
  "geometry": {"coordinates":[-121.432807,38.567312],"type":"Point"}
}