{
  "type": "Feature",
  "properties": {
    "addr:full":"303 Gardenia Dr San Jose CA 95123",
    "addr:housenumber":"303",
    "addr:postcode":"95123",
    "addr:street":"Gardenia Dr",
    "iso:country":"US",
    "sg:address":"303 Gardenia Dr",
    "sg:city":"San Jose",
    "sg:classifiers":[
        {
            "category":"Shopping",
            "subcategory":"Department Store",
            "type":"Retail Goods"
        }
    ],
    "sg:phone":"+1 408 265 2364",
    "sg:postcode":"95123",
    "sg:province":"CA",
    "sg:tags":[
        "shop"
    ],
    "wof:name":"Bargain Cigarettes & Beverages",
    "wof:placetype":"venue"
},
  "geometry": {"coordinates":[-121.809541,37.240442],"type":"Point"}
}