{
  "type": "Feature",
  "properties": {
    "iso:country":"US",
    "sg:address":"2650 Cam del Rio N",
    "sg:city":"San Diego",
    "sg:classifiers":[
        {
            "category":"Professional",
            "subcategory":"Lawyer & Legal Services",
            "type":"Services"
        }
    ],
    "sg:phone":"+1 619 542 1010",
    "sg:postcode":"92108",
    "sg:province":"CA",
    "sg:tags":[
        "attorney"
    ],
    "wof:name":"Frank E De Noewer",
    "wof:placetype":"venue"
},
  "geometry": {"coordinates":[-117.133273,32.773108],"type":"Point"}
}