{
  "type": "Feature",
  "properties": {
    "addr:full":"8829 Miner St Los Angeles CA 90002",
    "addr:housenumber":"8829",
    "addr:postcode":"90002",
    "addr:street":"Miner St",
    "iso:country":"US",
    "sg:address":"8829 Miner St",
    "sg:city":"Los Angeles",
    "sg:classifiers":[
        {
            "category":"Wholesale",
            "subcategory":"Metals & Minerals",
            "type":"Manufacturing & Wholesale Goods"
        }
    ],
    "sg:phone":"+1 323 583 1336",
    "sg:postcode":"90002",
    "sg:province":"CA",
    "sg:tags":[
        "steel",
        "warehouse"
    ],
    "wof:name":"Sima Enterprises",
    "wof:placetype":"venue"
},
  "geometry": {"coordinates":[-118.23452899999999,33.956516],"type":"Point"}
}