{
  "type": "Feature",
  "properties": {
    "iso:country":"US",
    "sg:address":"1742 Lancaster Pl",
    "sg:city":"El Dorado Hills",
    "sg:classifiers":[
        {
            "category":"Arts & Performance",
            "subcategory":"Theater",
            "type":"Entertainment"
        }
    ],
    "sg:phone":"+1 916 939 1272",
    "sg:postcode":"95762",
    "sg:province":"CA",
    "sg:tags":[
        "live",
        "music"
    ],
    "sg:website":"www.artistsound.com",
    "wof:name":"Artistsound Entertainment",
    "wof:placetype":"venue"
},
  "geometry": {"coordinates":[-121.083648,38.725297],"type":"Point"}
}