{
  "type": "Feature",
  "properties": {
    "addr:full":"2021 Stewart St Oceanside CA 92054",
    "addr:housenumber":"2021",
    "addr:postcode":"92054",
    "addr:street":"Stewart St",
    "iso:country":"US",
    "sg:address":"2021 Stewart St",
    "sg:city":"Oceanside",
    "sg:classifiers":[
        {
            "category":"Professional",
            "subcategory":"Business Services",
            "type":"Services"
        }
    ],
    "sg:phone":"+1 760 433 2818",
    "sg:postcode":"92054",
    "sg:province":"CA",
    "wof:name":"Retrievers",
    "wof:placetype":"venue"
},
  "geometry": {"coordinates":[-117.353093,33.174878],"type":"Point"}
}