{
  "type": "Feature",
  "properties": {
    "iso:country":"US",
    "sg:address":"1775 Egbert Ave",
    "sg:city":"San Francisco",
    "sg:classifiers":[
        {
            "category":"Retail",
            "subcategory":"Funeral Services",
            "type":"Services"
        }
    ],
    "sg:phone":"+1 415 468 6044",
    "sg:postcode":"94124",
    "sg:province":"CA",
    "sg:tags":[
        "crematory"
    ],
    "wof:name":"Creative Cremains",
    "wof:placetype":"venue"
},
  "geometry": {"coordinates":[-122.398599,37.726611],"type":"Point"}
}