{
  "type": "Feature",
  "properties": {
    "addr:full":"101 Ranport Rd Watsonville CA 95076",
    "addr:housenumber":"101",
    "addr:postcode":"95076",
    "addr:street":"Ranport Rd",
    "iso:country":"US",
    "sg:address":"101 Ranport Rd",
    "sg:city":"Watsonville",
    "sg:classifiers":[
        {
            "category":"Recreation",
            "type":"Entertainment"
        }
    ],
    "sg:phone":"+1 831 761 1671",
    "sg:postcode":"95076",
    "sg:province":"CA",
    "sg:tags":[
        "range",
        "practice",
        "golf"
    ],
    "wof:name":"Airport Driving Range",
    "wof:placetype":"venue"
},
  "geometry": {"coordinates":[-121.80448199999999,36.927082],"type":"Point"}
}