{
  "type": "Feature",
  "properties": {
    "addr:full":"1620 Tennessee St Vallejo CA 94590",
    "addr:housenumber":"1620",
    "addr:postcode":"94590",
    "addr:street":"Tennessee St",
    "iso:country":"US",
    "sg:address":"1620 Tennessee St",
    "sg:city":"Vallejo",
    "sg:classifiers":[
        {
            "category":"Personal",
            "subcategory":"Beauty Salon",
            "type":"Services"
        }
    ],
    "sg:phone":"+1 707 554 2808",
    "sg:postcode":"94590",
    "sg:province":"CA",
    "sg:tags":[
        "manicuring"
    ],
    "wof:name":"Lee's Nails & Beauty Supplies",
    "wof:placetype":"venue"
},
  "geometry": {"coordinates":[-122.238353,38.109848],"type":"Point"}
}