{
  "type": "Feature",
  "properties": {
    "iso:country":"US",
    "sg:address":"148 E St",
    "sg:city":"Wasco",
    "sg:classifiers":[
        {
            "category":"Freight",
            "type":"Transportation"
        }
    ],
    "sg:phone":"+1 661 758 8919",
    "sg:postcode":"93280",
    "sg:province":"CA",
    "sg:tags":[
        "operator",
        "trucking"
    ],
    "wof:name":"M G Trucking",
    "wof:placetype":"venue"
},
  "geometry": {"coordinates":[-119.334943,35.60108],"type":"Point"}
}