{
  "type": "Feature",
  "properties": {
    "addr:full":"6363 Christie Ave Emeryville CA 94608",
    "addr:housenumber":"6363",
    "addr:postcode":"94608",
    "addr:street":"Christie Ave",
    "iso:country":"US",
    "sg:address":"6363 Christie Ave",
    "sg:city":"Emeryville",
    "sg:classifiers":[
        {
            "category":"Wholesale",
            "subcategory":"Computers",
            "type":"Manufacturing & Wholesale Goods"
        }
    ],
    "sg:phone":"+1 925 463 4843",
    "sg:postcode":"94608",
    "sg:province":"CA",
    "wof:name":"Intermec Technologies Corp",
    "wof:placetype":"venue"
},
  "geometry": {"coordinates":[-122.294972,37.839625],"type":"Point"}
}