{
  "type": "Feature",
  "properties": {
    "addr:full":"12930 Ventura Blvd Ste 226 C Studio City CA 91604",
    "addr:housenumber":"12930;c",
    "addr:postcode":"91604",
    "addr:street":"Ventura Blvd Ste 226",
    "iso:country":"US",
    "sg:address":"12930 Ventura Blvd Ste 226 C",
    "sg:city":"Studio City",
    "sg:classifiers":[
        {
            "category":"Health Services",
            "subcategory":"Chiropractor",
            "type":"Services"
        }
    ],
    "sg:phone":"+1 818 995 4472",
    "sg:postcode":"91604",
    "sg:province":"CA",
    "sg:website":"www.DrTraceyReeb.com",
    "wof:name":"Dr Tracey Reeb Chiropractic",
    "wof:placetype":"venue"
},
  "geometry": {"coordinates":[-118.414832,34.145283],"type":"Point"}
}