{
  "type": "Feature",
  "properties": {
    "addr:full":"2415 Noriega Street San Francisco CA 94122",
    "addr:housenumber":"2415",
    "addr:postcode":"94122",
    "addr:street":"Noriega Street",
    "iso:country":"US",
    "sg:address":"2415 Noriega Street",
    "sg:city":"San Francisco",
    "sg:classifiers":[
        {
            "category":"Health Services",
            "subcategory":"Dentist",
            "type":"Services"
        }
    ],
    "sg:phone":"+1 415 682 2415",
    "sg:postcode":"94122",
    "sg:province":"CA",
    "wof:name":"Chan Siu Wan DDS",
    "wof:placetype":"venue"
},
  "geometry": {"coordinates":[-122.489667,37.753571],"type":"Point"}
}