{
  "type": "Feature",
  "properties": {
    "addr:full":"237 Townsite Dr Vista CA 92084",
    "addr:housenumber":"237",
    "addr:postcode":"92084",
    "addr:street":"Townsite Dr",
    "iso:country":"US",
    "sg:address":"237 Townsite Dr",
    "sg:city":"Vista",
    "sg:classifiers":[
        {
            "category":"Arts & Performance",
            "subcategory":"Theater",
            "type":"Entertainment"
        }
    ],
    "sg:phone":"+1 760 945 5517",
    "sg:postcode":"92084",
    "sg:province":"CA",
    "sg:tags":[
        "live",
        "music"
    ],
    "wof:name":"D J Blaze Music",
    "wof:placetype":"venue"
},
  "geometry": {"coordinates":[-117.24234199999999,33.21148],"type":"Point"}
}