{
  "type": "Feature",
  "properties": {
    "iso:country":"US",
    "sg:address":"2850 La Loma Drive",
    "sg:city":"Rancho Cordova",
    "sg:classifiers":[
        {
            "category":"Real Estate",
            "subcategory":"Real Estate Operator",
            "type":"Services"
        }
    ],
    "sg:phone":"+1 916 366 7133",
    "sg:postcode":"95670",
    "sg:province":"CA",
    "sg:tags":[
        "apartment"
    ],
    "wof:name":"Redwoods At Mather Station",
    "wof:placetype":"venue"
},
  "geometry": {"coordinates":[-121.314876,38.585443],"type":"Point"}
}