{
  "type": "Feature",
  "properties": {
    "addr:full":"14201 Foothill Blvd Unit 42 Sylmar CA 91342",
    "addr:housenumber":"14201;42",
    "addr:postcode":"91342",
    "addr:street":"Foothill Blvd Unit",
    "iso:country":"US",
    "sg:address":"14201 Foothill Blvd Unit 42",
    "sg:city":"Sylmar",
    "sg:classifiers":[
        {
            "category":"Personal",
            "subcategory":"Beauty Salon",
            "type":"Services"
        }
    ],
    "sg:phone":"+1 818 364 9948",
    "sg:postcode":"91342",
    "sg:province":"CA",
    "wof:name":"Pilar's Beauty Salon",
    "wof:placetype":"venue"
},
  "geometry": {"coordinates":[-118.44309199999999,34.31736],"type":"Point"}
}