{
  "type": "Feature",
  "properties": {
    "iso:country":"US",
    "sg:address":"13907 Poway Rd",
    "sg:city":"Poway",
    "sg:classifiers":[
        {
            "category":"Retail",
            "subcategory":"Auto Repair",
            "type":"Services"
        }
    ],
    "sg:phone":"+1 858 748 0561",
    "sg:postcode":"92064",
    "sg:province":"CA",
    "sg:tags":[
        "repairing",
        "automobile"
    ],
    "wof:name":"Poway Auto Repair",
    "wof:placetype":"venue"
},
  "geometry": {"coordinates":[-117.028842,32.956213],"type":"Point"}
}