{
  "type": "Feature",
  "properties": {
    "addr:full":"5002 Venice Blvd Los Angeles CA 90019",
    "addr:housenumber":"5002",
    "addr:postcode":"90019",
    "addr:street":"Venice Blvd",
    "iso:country":"US",
    "sg:address":"5002 Venice Blvd",
    "sg:city":"Los Angeles",
    "sg:classifiers":[
        {
            "category":"Professional",
            "subcategory":"Advertising",
            "type":"Services"
        },
        {
            "category":"Home & Garden",
            "subcategory":"Building Materials",
            "type":"Retail Goods"
        }
    ],
    "sg:phone":"+1 323 937 4445",
    "sg:postcode":"90019",
    "sg:province":"CA",
    "sg:tags":[
        "equipment",
        "fixture",
        "lighting",
        "marketing"
    ],
    "sg:website":"www.takotyko.com#cid=yelp",
    "wof:name":"Tako Tyko",
    "wof:placetype":"venue"
},
  "geometry": {"coordinates":[-118.34699999999999,34.0457],"type":"Point"}
}