{
  "type": "Feature",
  "properties": {
    "addr:full":"202 Tank Farm Rd San Luis Obispo CA 93401",
    "addr:housenumber":"202",
    "addr:postcode":"93401",
    "addr:street":"Tank Farm Rd",
    "iso:country":"US",
    "sg:address":"202 Tank Farm Rd",
    "sg:city":"San Luis Obispo",
    "sg:classifiers":[
        {
            "category":"Wholesale",
            "subcategory":"Farm Supplies",
            "type":"Manufacturing & Wholesale Goods"
        }
    ],
    "sg:phone":"+1 805 543 8410",
    "sg:postcode":"93401",
    "sg:province":"CA",
    "sg:tags":[
        "feed"
    ],
    "wof:name":"Double D Feed & Supply",
    "wof:placetype":"venue"
},
  "geometry": {"coordinates":[-120.67366,35.246794],"type":"Point"}
}