{
  "type": "Feature",
  "properties": {
    "addr:full":"3402 Park Blvd Oakland CA 94610",
    "addr:housenumber":"3402",
    "addr:postcode":"94610",
    "addr:street":"Park Blvd",
    "iso:country":"US",
    "sg:address":"3402 Park Blvd",
    "sg:city":"Oakland",
    "sg:classifiers":[
        {
            "category":"Shopping",
            "subcategory":"Computers & Home Electronics",
            "type":"Retail Goods"
        }
    ],
    "sg:phone":"+1 510 261 0690",
    "sg:postcode":"94610",
    "sg:province":"CA",
    "sg:tags":[
        "parts",
        "supply"
    ],
    "wof:name":"Star Office Systems",
    "wof:placetype":"venue"
},
  "geometry": {"coordinates":[-122.23383800000001,37.803926],"type":"Point"}
}