{
  "type": "Feature",
  "properties": {
    "iso:country":"US",
    "sg:address":"8001 Irvine Center Drive Suite 400",
    "sg:city":"Irvine",
    "sg:classifiers":[
        {
            "category":"Professional",
            "subcategory":"Computer Services",
            "type":"Services"
        }
    ],
    "sg:phone":"+1 888 883 9797",
    "sg:postcode":"92618",
    "sg:province":"CA",
    "sg:tags":[
        "business-consulting",
        "financial-management",
        "customer-relationship-management",
        "crm",
        "business-intelligence",
        "network",
        "infrastructure",
        "hosting-and-managed-apps",
        "integration-and-development",
        "learning-solutions"
    ],
    "sg:website":"http://www.epartnersolutions.com",
    "wof:name":"ePartners",
    "wof:placetype":"venue"
},
  "geometry": {"coordinates":[-117.753137,33.661938],"type":"Point"}
}