{
  "type": "Feature",
  "properties": {
    "addr:full":"59 Bruning Ave Rio Vista CA 94571",
    "addr:housenumber":"59",
    "addr:postcode":"94571",
    "addr:street":"Bruning Ave",
    "iso:country":"US",
    "sg:address":"59 Bruning Ave",
    "sg:city":"Rio Vista",
    "sg:classifiers":[
        {
            "category":"Farming",
            "subcategory":"Farm",
            "type":"Manufacturing & Wholesale Goods"
        }
    ],
    "sg:phone":"+1 707 374 2358",
    "sg:postcode":"94571",
    "sg:province":"CA",
    "sg:tags":[
        "crop",
        "general"
    ],
    "wof:name":"Hechtman Farms",
    "wof:placetype":"venue"
},
  "geometry": {"coordinates":[-121.691761,38.153527],"type":"Point"}
}