{
  "type": "Feature",
  "properties": {
    "iso:country":"US",
    "sg:address":"132 Hamerton Ave",
    "sg:city":"San Francisco",
    "sg:classifiers":[
        {
            "category":"Professional",
            "subcategory":"Management & Consulting",
            "type":"Services"
        }
    ],
    "sg:phone":"+1 415 585 2100",
    "sg:postcode":"94131",
    "sg:province":"CA",
    "sg:tags":[
        "counselor",
        "public",
        "relations"
    ],
    "sg:website":"www.pikeandcompany.com",
    "wof:name":"Pike & Co",
    "wof:placetype":"venue"
},
  "geometry": {"coordinates":[-122.437865,37.733463],"type":"Point"}
}