{
  "type": "Feature",
  "properties": {
    "addr:full":"Zephyr Real Estate 215 West Portal Ave San Francisco CA 94127",
    "addr:housenumber":"215",
    "addr:postcode":"94127",
    "addr:street":"West Portal Ave",
    "iso:country":"US",
    "sg:address":"Zephyr Real Estate 215 West Portal Ave",
    "sg:city":"San Francisco",
    "sg:classifiers":[
        {
            "category":"Real Estate",
            "subcategory":"Real Estate Agent",
            "type":"Services"
        }
    ],
    "sg:phone":"+1 415 731 5000",
    "sg:postcode":"94127",
    "sg:province":"CA",
    "sg:website":"www.zephyr-re.com/agent_detail.c...",
    "wof:name":"Cathy Kline Saunders, Real Estate Agent",
    "wof:placetype":"venue"
},
  "geometry": {"coordinates":[-122.468144,37.738707],"type":"Point"}
}