{
  "type": "Feature",
  "properties": {
    "iso:country":"US",
    "sg:address":"8687 Melrose Ave",
    "sg:city":"Los Angeles",
    "sg:classifiers":[
        {
            "category":"Manufacturing",
            "subcategory":"Furniture",
            "type":"Manufacturing & Wholesale Goods"
        }
    ],
    "sg:phone":"+1 310 657 8687",
    "sg:postcode":"90069",
    "sg:province":"CA",
    "sg:website":"www.shelbywilliams.com",
    "wof:name":"Shelby Williams Industries Inc",
    "wof:placetype":"venue"
},
  "geometry": {"coordinates":[-118.383058,34.081384],"type":"Point"}
}