{
  "type": "Feature",
  "properties": {
    "addr:full":"228 el Camino Dr Beverly Hills CA 90212",
    "addr:housenumber":"228",
    "addr:postcode":"90212",
    "addr:street":"El Camino Dr",
    "iso:country":"US",
    "sg:address":"228 el Camino Dr",
    "sg:city":"Beverly Hills",
    "sg:classifiers":[
        {
            "category":"Professional",
            "type":"Services"
        }
    ],
    "sg:phone":"+1 310 278 2322",
    "sg:postcode":"90212",
    "sg:province":"CA",
    "wof:name":"Inovotel",
    "wof:placetype":"venue"
},
  "geometry": {"coordinates":[-118.40009999999999,34.063011],"type":"Point"}
}