{
  "type": "Feature",
  "properties": {
    "addr:full":"155 Parrott St San Leandro CA 94577",
    "addr:housenumber":"155",
    "addr:postcode":"94577",
    "addr:street":"Parrott St",
    "iso:country":"US",
    "sg:address":"155 Parrott St",
    "sg:city":"San Leandro",
    "sg:classifiers":[
        {
            "category":"Shopping",
            "subcategory":"Florist",
            "type":"Retail Goods"
        }
    ],
    "sg:phone":"+1 510 895 2075",
    "sg:postcode":"94577",
    "sg:province":"CA",
    "wof:name":"Accent In Flowers",
    "wof:placetype":"venue"
},
  "geometry": {"coordinates":[-122.153038,37.722455],"type":"Point"}
}