{
  "type": "Feature",
  "properties": {
    "iso:country":"US",
    "sg:address":"3001 Dwight Way",
    "sg:city":"Berkeley",
    "sg:classifiers":[
        {
            "category":"Wholesale",
            "subcategory":"Machinery & Supplies",
            "type":"Manufacturing & Wholesale Goods"
        }
    ],
    "sg:phone":"+1 510 548 8284",
    "sg:postcode":"94704",
    "sg:province":"CA",
    "sg:tags":[
        "instrument",
        "scientific",
        "apparatus"
    ],
    "wof:name":"Rotech Scientific",
    "wof:placetype":"venue"
},
  "geometry": {"coordinates":[-122.246883,37.866156],"type":"Point"}
}