{
  "type": "Feature",
  "properties": {
    "iso:country":"US",
    "sg:address":"660 J St",
    "sg:city":"Sacramento",
    "sg:classifiers":[
        {
            "category":"Government",
            "subcategory":"Office",
            "type":"Public Place"
        }
    ],
    "sg:phone":"+1 916 445 4005",
    "sg:postcode":"95814",
    "sg:province":"CA",
    "sg:tags":[
        "control",
        "liquor",
        "appeal",
        "board",
        "for"
    ],
    "wof:name":"Alcoholic Bev Ctrl Appeals Bd",
    "wof:placetype":"venue"
},
  "geometry": {"coordinates":[-121.49805600000001,38.581504],"type":"Point"}
}