{
  "type": "Feature",
  "properties": {
    "iso:country":"US",
    "sg:address":"582 E Shamrock St",
    "sg:city":"Rialto",
    "sg:classifiers":[
        {
            "category":"Social Services",
            "subcategory":"Child Care",
            "type":"Services"
        }
    ],
    "sg:phone":"+1 909 875 5313",
    "sg:postcode":"92376",
    "sg:province":"CA",
    "wof:name":"Harlow Family Child Care",
    "wof:placetype":"venue"
},
  "geometry": {"coordinates":[-117.360812,34.119178],"type":"Point"}
}