{
  "type": "Feature",
  "properties": {
    "iso:country":"US",
    "sg:address":"472 Utah St",
    "sg:city":"San Francisco",
    "sg:classifiers":[
        {
            "category":"Freight",
            "type":"Transportation"
        }
    ],
    "sg:phone":"+1 415 626 5818",
    "sg:postcode":"94110",
    "sg:province":"CA",
    "wof:name":"Signature Transportation",
    "wof:placetype":"venue"
},
  "geometry": {"coordinates":[-122.406452,37.764199],"type":"Point"}
}