{
  "type": "Feature",
  "properties": {
    "addr:full":"312 E Beach Avenue Inglewood CA 90302",
    "addr:housenumber":"312",
    "addr:postcode":"90302",
    "addr:street":"E Beach Avenue",
    "iso:country":"US",
    "sg:address":"312 E Beach Avenue",
    "sg:city":"Inglewood",
    "sg:classifiers":[
        {
            "category":"Building & Trades",
            "subcategory":"Construction",
            "type":"Services"
        }
    ],
    "sg:phone":"+1 310 672 2955",
    "sg:postcode":"90302",
    "sg:province":"CA",
    "sg:tags":[
        "contractor"
    ],
    "wof:name":"Nsa Construction",
    "wof:placetype":"venue"
},
  "geometry": {"coordinates":[-118.351568,33.968356],"type":"Point"}
}