{
  "type": "Feature",
  "properties": {
    "addr:full":"10722 Palmyra St Adelanto CA 92301",
    "addr:housenumber":"10722",
    "addr:postcode":"92301",
    "addr:street":"Palmyra St",
    "iso:country":"US",
    "sg:address":"10722 Palmyra St",
    "sg:city":"Adelanto",
    "sg:classifiers":[
        {
            "category":"Building & Trades",
            "subcategory":"Construction",
            "type":"Services"
        }
    ],
    "sg:phone":"+1 760 486 5378",
    "sg:postcode":"92301",
    "sg:province":"CA",
    "sg:tags":[
        "information",
        "plastering",
        "coping",
        "bureau",
        "tiling",
        "pool",
        "swimming"
    ],
    "wof:name":"Magic Touch Pool Svc.",
    "wof:placetype":"venue"
},
  "geometry": {"coordinates":[-117.430457,34.516732],"type":"Point"}
}