{
  "type": "Feature",
  "properties": {
    "addr:full":"5103 Cabrillo Pt Discovery Bay CA 94505",
    "addr:housenumber":"5103",
    "addr:postcode":"94505",
    "addr:street":"Cabrillo Pt",
    "iso:country":"US",
    "sg:address":"5103 Cabrillo Pt",
    "sg:city":"Discovery Bay",
    "sg:classifiers":[
        {
            "category":"Banks & Credit Unions",
            "subcategory":"Investment Brokerage",
            "type":"Services"
        }
    ],
    "sg:phone":"+1 925 634 7689",
    "sg:postcode":"94505",
    "sg:province":"CA",
    "sg:tags":[
        "consultant",
        "planning",
        "financial"
    ],
    "wof:name":"E Planining Inc",
    "wof:placetype":"venue"
},
  "geometry": {"coordinates":[-121.603087,37.911454],"type":"Point"}
}