{
  "type": "Feature",
  "properties": {
    "iso:country":"US",
    "sg:address":"3628 Madison Ave",
    "sg:city":"North Highlands",
    "sg:classifiers":[
        {
            "category":"Professional",
            "subcategory":"Testing Lab",
            "type":"Services"
        }
    ],
    "sg:phone":"+1 916 331 6030",
    "sg:postcode":"95660",
    "sg:province":"CA",
    "sg:tags":[
        "laboratory"
    ],
    "sg:website":"www.cte-inc.net",
    "wof:name":"Construction Testing & Eng",
    "wof:placetype":"venue"
},
  "geometry": {"coordinates":[-121.38100900000001,38.660463],"type":"Point"}
}