{
  "type": "Feature",
  "properties": {
    "addr:full":"9419 Timber River Way Elk Grove CA 95624",
    "addr:housenumber":"9419",
    "addr:postcode":"95624",
    "addr:street":"Timber River Way",
    "iso:country":"US",
    "sg:address":"9419 Timber River Way",
    "sg:city":"Elk Grove",
    "sg:classifiers":[
        {
            "category":"Freight",
            "type":"Transportation"
        }
    ],
    "sg:phone":"+1 916 689 3245",
    "sg:postcode":"95624",
    "sg:province":"CA",
    "sg:tags":[
        "logging",
        "transport"
    ],
    "wof:name":"W P Transport",
    "wof:placetype":"venue"
},
  "geometry": {"coordinates":[-121.347871,38.418912],"type":"Point"}
}