{
  "type": "Feature",
  "properties": {
    "addr:full":"51 Fallon Rd Hollister CA 95023",
    "addr:housenumber":"51",
    "addr:postcode":"hollister ca 95023",
    "addr:street":"Fallon Rd",
    "iso:country":"US",
    "sg:address":"51 Fallon Rd",
    "sg:city":"Hollister",
    "sg:classifiers":[
        {
            "category":"Wholesale",
            "subcategory":"Metals & Minerals",
            "type":"Manufacturing & Wholesale Goods"
        }
    ],
    "sg:phone":"+1 831 637 5641",
    "sg:postcode":"95023",
    "sg:province":"CA",
    "sg:tags":[
        "casting"
    ],
    "wof:name":"American Casting Co",
    "wof:placetype":"venue"
},
  "geometry": {"coordinates":[-121.39781499999999,36.886614],"type":"Point"}
}