{
  "type": "Feature",
  "properties": {
    "iso:country":"US",
    "sg:address":"18626 Clarkdale Ave",
    "sg:city":"Artesia",
    "sg:classifiers":[
        {
            "category":"Education",
            "subcategory":"School",
            "type":"Public Place"
        }
    ],
    "sg:phone":"+1 562 865 1621",
    "sg:postcode":"90701",
    "sg:province":"CA",
    "sg:tags":[
        "high",
        "middle",
        "elementary"
    ],
    "sg:website":"www.fatimachargers.com",
    "wof:name":"Our Lady of Fatima School",
    "wof:placetype":"venue"
},
  "geometry": {"coordinates":[-118.078676,33.861493],"type":"Point"}
}