{
  "type": "Feature",
  "properties": {
    "addr:full":"6938 Deering Ave Canoga Park CA 91303",
    "addr:housenumber":"6938",
    "addr:postcode":"91303",
    "addr:street":"Deering Ave",
    "iso:country":"US",
    "sg:address":"6938 Deering Ave",
    "sg:city":"Canoga Park",
    "sg:classifiers":[
        {
            "category":"Manufacturing",
            "subcategory":"Metals",
            "type":"Manufacturing & Wholesale Goods"
        }
    ],
    "sg:phone":"+1 818 347 7232",
    "sg:postcode":"91303",
    "sg:province":"CA",
    "sg:tags":[
        "antique"
    ],
    "wof:name":"Aztec Polishing & Plating",
    "wof:placetype":"venue"
},
  "geometry": {"coordinates":[-118.59699999999999,34.196701],"type":"Point"}
}