{
  "type": "Feature",
  "properties": {
    "addr:full":"6159 Tony Ave Woodland Hills CA 91367",
    "addr:housenumber":"6159",
    "addr:postcode":"91367",
    "addr:street":"Tony Ave",
    "iso:country":"US",
    "sg:address":"6159 Tony Ave",
    "sg:city":"Woodland Hills",
    "sg:classifiers":[
        {
            "category":"Building & Trades",
            "subcategory":"Construction",
            "type":"Services"
        }
    ],
    "sg:postcode":"91367",
    "sg:province":"CA",
    "sg:tags":[
        "interior",
        "design"
    ],
    "wof:name":"Quality & Budget Cabinets, Inc",
    "wof:placetype":"venue"
},
  "geometry": {"coordinates":[-118.645179,34.182557],"type":"Point"}
}