{
  "type": "Feature",
  "properties": {
    "iso:country":"US",
    "sg:address":"4191 Convoy St",
    "sg:city":"San Diego",
    "sg:classifiers":[
        {
            "category":"Retail",
            "subcategory":"Auto Repair",
            "type":"Services"
        }
    ],
    "sg:phone":"+1 858 278 1212",
    "sg:postcode":"92111",
    "sg:province":"CA",
    "sg:tags":[
        "repairing",
        "automobile"
    ],
    "wof:name":"Balboa Automotive Svc",
    "wof:placetype":"venue"
},
  "geometry": {"coordinates":[-117.154911,32.81911],"type":"Point"}
}