{
  "type": "Feature",
  "properties": {
    "addr:full":"740 Oak Ave Carlsbad CA 92008",
    "addr:housenumber":"740",
    "addr:postcode":"92008",
    "addr:street":"Oak Ave",
    "iso:country":"US",
    "sg:address":"740 Oak Ave",
    "sg:city":"Carlsbad",
    "sg:classifiers":[
        {
            "category":"Health Services",
            "subcategory":"Doctor",
            "type":"Services"
        },
        {
            "category":"Health Services",
            "subcategory":"Clinic",
            "type":"Services"
        }
    ],
    "sg:phone":"+1 760 729 1457",
    "sg:postcode":"92008",
    "sg:province":"CA",
    "sg:tags":[
        "counseling",
        "mental"
    ],
    "wof:name":"Shlemmer Richard L PHD",
    "wof:placetype":"venue"
},
  "geometry": {"coordinates":[-117.345001,33.159901],"type":"Point"}
}