{
  "type": "Feature",
  "properties": {
    "iso:country":"US",
    "sg:address":"610 S Main St",
    "sg:city":"Los Angeles",
    "sg:classifiers":[
        {
            "category":"Real Estate",
            "subcategory":"Real Estate Operator",
            "type":"Services"
        }
    ],
    "sg:phone":"+1 213 627 5600",
    "sg:postcode":"90014",
    "sg:province":"CA",
    "sg:tags":[
        "apartment"
    ],
    "sg:website":"www.pacificelectriclofts.com/",
    "wof:name":"Pacific Electric Lofts",
    "wof:placetype":"venue"
},
  "geometry": {"coordinates":[-118.250393,34.044821],"type":"Point"}
}