{
  "type": "Feature",
  "properties": {
    "iso:country":"US",
    "sg:address":"200 Skylane Dr",
    "sg:city":"Hollister",
    "sg:classifiers":[
        {
            "category":"Airport",
            "type":"Transportation"
        }
    ],
    "sg:phone":"+1 831 637 9100",
    "sg:postcode":"95023",
    "sg:province":"CA",
    "wof:name":"Gavilan Aviation",
    "wof:placetype":"venue"
},
  "geometry": {"coordinates":[-121.40260000000001,36.889493],"type":"Point"}
}