{
  "type": "Feature",
  "properties": {
    "addr:full":"c/o The Law Office of Charles Ott PO Box 1332 El Granada CA 94018",
    "addr:housenumber":"/ o;po box 1332",
    "addr:postcode":"94018",
    "addr:street":"C;The",
    "iso:country":"US",
    "sg:address":"c/o The Law Office of Charles Ott PO Box 1332",
    "sg:city":"El Granada",
    "sg:classifiers":[
        {
            "category":"Professional",
            "subcategory":"Computer Services",
            "type":"Services"
        }
    ],
    "sg:postcode":"94018",
    "sg:province":"CA",
    "sg:tags":[
        "advice-network",
        "baby-boomer-generation",
        "baby-boomer-social-networking",
        "ratings-and-reviews"
    ],
    "sg:website":"http://www.boomerater.com",
    "wof:name":"Boomerater",
    "wof:placetype":"venue"
},
  "geometry": {"coordinates":[-122.473404,37.510085],"type":"Point"}
}