{
  "type": "Feature",
  "properties": {
    "addr:full":"156 Stoney Creek Rd Santa Cruz CA 95060",
    "addr:housenumber":"156",
    "addr:postcode":"95060",
    "addr:street":"Stoney Creek Rd",
    "iso:country":"US",
    "sg:address":"156 Stoney Creek Rd",
    "sg:city":"Santa Cruz",
    "sg:classifiers":[
        {
            "category":"Banks & Credit Unions",
            "subcategory":"Bank",
            "type":"Services"
        }
    ],
    "sg:phone":"+1 888 668 8978",
    "sg:postcode":"95060",
    "sg:province":"CA",
    "sg:tags":[
        "broker",
        "mortgage"
    ],
    "wof:name":"Pacific Mortgage Group",
    "wof:placetype":"venue"
},
  "geometry": {"coordinates":[-122.01498599999999,36.98724],"type":"Point"}
}