{
  "type": "Feature",
  "properties": {
    "addr:full":"550 Vermont St San Jose CA 95110",
    "addr:housenumber":"550",
    "addr:postcode":"95110",
    "addr:street":"Vermont St",
    "iso:country":"US",
    "sg:address":"550 Vermont St",
    "sg:city":"San Jose",
    "sg:classifiers":[
        {
            "category":"Manufacturing",
            "subcategory":"Printing",
            "type":"Manufacturing & Wholesale Goods"
        }
    ],
    "sg:phone":"+1 408 298 3210",
    "sg:postcode":"95110",
    "sg:province":"CA",
    "sg:tags":[
        "multimedia"
    ],
    "wof:name":"Media Innovacions",
    "wof:placetype":"venue"
},
  "geometry": {"coordinates":[-121.91820199999999,37.347526],"type":"Point"}
}