{
  "type": "Feature",
  "properties": {
    "iso:country":"US",
    "sg:address":"2115 Highpointe Dr",
    "sg:city":"Corona",
    "sg:classifiers":[
        {
            "category":"Professional",
            "type":"Services"
        }
    ],
    "sg:phone":"+1 714 420 6918",
    "sg:postcode":"92879",
    "sg:province":"CA",
    "wof:name":"American Bright Works",
    "wof:placetype":"venue"
},
  "geometry": {"coordinates":[-117.52167300000001,33.889251],"type":"Point"}
}