{
  "type": "Feature",
  "properties": {
    "addr:full":"145 S Gray St Ste 103 Orcutt CA 93455",
    "addr:housenumber":"145",
    "addr:postcode":"93455",
    "addr:street":"S Gray St Ste 103",
    "iso:country":"US",
    "sg:address":"145 S Gray St Ste 103",
    "sg:city":"Orcutt",
    "sg:classifiers":[
        {
            "category":"Winery",
            "type":"Food & Drink"
        }
    ],
    "sg:phone":"+1 805 937 1600",
    "sg:postcode":"93455",
    "sg:province":"CA",
    "sg:website":"www.corewine.com/",
    "wof:name":"Core Wine Company Tasting Room",
    "wof:placetype":"venue"
},
  "geometry": {"coordinates":[-120.443454,34.864704],"type":"Point"}
}