{
  "type": "Feature",
  "properties": {
    "iso:country":"US",
    "sg:address":"645 San Gabriel Ave",
    "sg:city":"Albany",
    "sg:classifiers":[
        {
            "category":"Professional",
            "subcategory":"Business Services",
            "type":"Services"
        }
    ],
    "sg:phone":"+1 510 524 4714",
    "sg:postcode":"94706",
    "sg:province":"CA",
    "sg:tags":[
        "organizing",
        "services-household"
    ],
    "wof:name":"Management Development Sys",
    "wof:placetype":"venue"
},
  "geometry": {"coordinates":[-122.294622,37.895392],"type":"Point"}
}