{
  "type": "Feature",
  "properties": {
    "addr:full":"2411 Oak Grove Rd Walnut Creek CA 94598",
    "addr:housenumber":"2411",
    "addr:postcode":"94598",
    "addr:street":"Oak Grove Rd",
    "iso:country":"US",
    "sg:address":"2411 Oak Grove Rd",
    "sg:city":"Walnut Creek",
    "sg:classifiers":[
        {
            "category":"Retail",
            "subcategory":"Auto Repair",
            "type":"Services"
        }
    ],
    "sg:phone":"+1 925 939 4848",
    "sg:postcode":"94598",
    "sg:province":"CA",
    "sg:tags":[
        "repairing",
        "automobile"
    ],
    "wof:name":"Rosebery Car Care",
    "wof:placetype":"venue"
},
  "geometry": {"coordinates":[-122.01345000000001,37.92601],"type":"Point"}
}