{
  "type": "Feature",
  "properties": {
    "addr:full":"26118 McClintock Rd Newman CA 95360",
    "addr:housenumber":"26118",
    "addr:postcode":"95360",
    "addr:street":"Mcclintock Rd",
    "iso:country":"US",
    "sg:address":"26118 McClintock Rd",
    "sg:city":"Newman",
    "sg:classifiers":[
        {
            "category":"Farming",
            "subcategory":"Farm & Veterinary Services",
            "type":"Manufacturing & Wholesale Goods"
        }
    ],
    "sg:phone":"+1 209 854 2707",
    "sg:postcode":"95360",
    "sg:province":"CA",
    "sg:tags":[
        "crop",
        "harvesting"
    ],
    "wof:name":"Gustine Harvesting Inc",
    "wof:placetype":"venue"
},
  "geometry": {"coordinates":[-121.004018,37.333755],"type":"Point"}
}