{
  "type": "Feature",
  "properties": {
    "addr:full":"500 Airport Rd Taft CA 93268",
    "addr:housenumber":"500",
    "addr:postcode":"93268",
    "addr:street":"Airport Rd",
    "iso:country":"US",
    "sg:address":"500 Airport Rd",
    "sg:city":"Taft",
    "sg:classifiers":[
        {
            "category":"Recreation",
            "type":"Entertainment"
        }
    ],
    "sg:phone":"+1 661 765 5867",
    "sg:postcode":"93268",
    "sg:province":"CA",
    "sg:tags":[
        "parachute",
        "skydiving",
        "jumping"
    ],
    "sg:website":"www.skydivetaft.com",
    "wof:name":"Skydive Taft",
    "wof:placetype":"venue"
},
  "geometry": {"coordinates":[-119.443606,35.142507],"type":"Point"}
}