{
  "type": "Feature",
  "properties": {
    "addr:full":"2272 Shattuck Ave Berkeley CA 94704",
    "addr:housenumber":"2272",
    "addr:postcode":"94704",
    "addr:street":"Shattuck Ave",
    "iso:country":"US",
    "sg:address":"2272 Shattuck Ave",
    "sg:city":"Berkeley",
    "sg:classifiers":[
        {
            "category":"Restaurant",
            "type":"Food & Drink"
        }
    ],
    "sg:menulink":"http://www.allmenus.com/ca/berkeley/105510-pho-hoa/menu/",
    "sg:phone":"+1 510 540 9228",
    "sg:postcode":"94704",
    "sg:province":"CA",
    "sg:tags":[
        "asian",
        "vietnamese"
    ],
    "wof:name":"Pho Hoa",
    "wof:placetype":"venue"
},
  "geometry": {"coordinates":[-122.267911,37.867941],"type":"Point"}
}