{
  "type": "Feature",
  "properties": {
    "iso:country":"US",
    "sg:address":"505 N Yucca Ridge Rd",
    "sg:city":"Glendora",
    "sg:classifiers":[
        {
            "category":"Arts & Performance",
            "subcategory":"Theater",
            "type":"Entertainment"
        }
    ],
    "sg:phone":"+1 626 969 3032",
    "sg:postcode":"91741",
    "sg:province":"CA",
    "sg:tags":[
        "bureau"
    ],
    "wof:name":"John Wright",
    "wof:placetype":"venue"
},
  "geometry": {"coordinates":[-117.887923,34.145627],"type":"Point"}
}