{
  "type": "Feature",
  "properties": {
    "addr:full":"370 8th Ave Oakland CA 94606",
    "addr:housenumber":"370",
    "addr:postcode":"94606",
    "addr:street":"8Th Ave",
    "iso:country":"US",
    "sg:address":"370 8th Ave",
    "sg:city":"Oakland",
    "sg:classifiers":[
        {
            "category":"Freight",
            "type":"Transportation"
        }
    ],
    "sg:phone":"+1 209 938 0750",
    "sg:postcode":"94606",
    "sg:province":"CA",
    "sg:tags":[
        "trucking"
    ],
    "wof:name":"Keep On Trucking",
    "wof:placetype":"venue"
},
  "geometry": {"coordinates":[-122.25778800000001,37.788652],"type":"Point"}
}