{
  "type": "Feature",
  "properties": {
    "addr:full":"6245 Hollywood Boulevard Los Angeles CA 90028",
    "addr:housenumber":"6245",
    "addr:postcode":"90028",
    "addr:street":"Hollywood Boulevard",
    "iso:country":"US",
    "sg:address":"6245 Hollywood Boulevard",
    "sg:city":"Los Angeles",
    "sg:classifiers":[
        {
            "category":"Bars & Pubs",
            "subcategory":"Nightclub",
            "type":"Food & Drink"
        }
    ],
    "sg:phone":"+1 323 469 3303",
    "sg:postcode":"90028",
    "sg:province":"CA",
    "sg:tags":[
        "nightlife"
    ],
    "wof:name":"Nunley Robert L",
    "wof:placetype":"venue"
},
  "geometry": {"coordinates":[-118.32593300000001,34.101516],"type":"Point"}
}