{
  "type": "Feature",
  "properties": {
    "iso:country":"US",
    "sg:address":"2154 Westwood Blvd",
    "sg:city":"Los Angeles",
    "sg:classifiers":[
        {
            "category":"Personal",
            "subcategory":"Massage",
            "type":"Services"
        }
    ],
    "sg:phone":"+1 310 446 8882",
    "sg:postcode":"90025",
    "sg:province":"CA",
    "sg:website":"www.manhantang.com",
    "wof:name":"Man Han Tang",
    "wof:placetype":"venue"
},
  "geometry": {"coordinates":[-118.43197499999999,34.044667],"type":"Point"}
}