{
  "type": "Feature",
  "properties": {
    "iso:country":"US",
    "sg:address":"1079 Marilyn Dr",
    "sg:city":"Mountain View",
    "sg:classifiers":[
        {
            "category":"Farming",
            "subcategory":"Nursery",
            "type":"Manufacturing & Wholesale Goods"
        }
    ],
    "sg:phone":"+1 650 967 5286",
    "sg:postcode":"94040",
    "sg:province":"CA",
    "sg:tags":[
        "ornamental"
    ],
    "wof:name":"Satake Nursery",
    "wof:placetype":"venue"
},
  "geometry": {"coordinates":[-122.090171,37.380815],"type":"Point"}
}