{
  "type": "Feature",
  "properties": {
    "addr:full":"12811 Chaparral Ave Saratoga CA 95070",
    "addr:housenumber":"12811",
    "addr:postcode":"95070",
    "addr:street":"Chaparral Ave",
    "iso:country":"US",
    "sg:address":"12811 Chaparral Ave",
    "sg:city":"Saratoga",
    "sg:classifiers":[
        {
            "category":"Shopping",
            "type":"Retail Goods"
        }
    ],
    "sg:phone":"+1 408 378 5701",
    "sg:postcode":"95070",
    "sg:province":"CA",
    "sg:tags":[
        "merchandise"
    ],
    "wof:name":"Sunshade Screen & Awnings",
    "wof:placetype":"venue"
},
  "geometry": {"coordinates":[-121.989131,37.283342],"type":"Point"}
}