{
  "type": "Feature",
  "properties": {
    "iso:country":"US",
    "sg:address":"355 S Grand Ave",
    "sg:city":"Los Angeles",
    "sg:classifiers":[
        {
            "category":"Professional",
            "subcategory":"Lawyer & Legal Services",
            "type":"Services"
        }
    ],
    "sg:phone":"+1 213 457 8069",
    "sg:postcode":"90071",
    "sg:province":"CA",
    "sg:tags":[
        "attorney"
    ],
    "wof:name":"Lauren T Diehl Attorney",
    "wof:placetype":"venue"
},
  "geometry": {"coordinates":[-118.252481,34.051783],"type":"Point"}
}