{
  "type": "Feature",
  "properties": {
    "iso:country":"US",
    "sg:address":"1911 Hillhurst Ave",
    "sg:city":"Los Angeles",
    "sg:classifiers":[
        {
            "category":"Utilities",
            "subcategory":"Telephone",
            "type":"Services"
        }
    ],
    "sg:phone":"+1 323 372 3864",
    "sg:postcode":"90027",
    "sg:province":"CA",
    "sg:tags":[
        "web"
    ],
    "wof:name":"Hostextreme Inc",
    "wof:placetype":"venue"
},
  "geometry": {"coordinates":[-118.287493,34.106562],"type":"Point"}
}