{
  "type": "Feature",
  "properties": {
    "addr:full":"335 W Las Tunas Dr San Gabriel CA 91776",
    "addr:housenumber":"335",
    "addr:postcode":"91776",
    "addr:street":"W Las Tunas Dr",
    "iso:country":"US",
    "sg:address":"335 W Las Tunas Dr",
    "sg:city":"San Gabriel",
    "sg:classifiers":[
        {
            "category":"Retail",
            "subcategory":"Auto Rental",
            "type":"Services"
        }
    ],
    "sg:phone":"+1 626 289 1200",
    "sg:postcode":"91776",
    "sg:province":"CA",
    "sg:tags":[
        "renting",
        "automobile"
    ],
    "wof:name":"Enterprise Rent-A-Car",
    "wof:placetype":"venue"
},
  "geometry": {"coordinates":[-118.10459,34.102458],"type":"Point"}
}