{
  "type": "Feature",
  "properties": {
    "iso:country":"US",
    "sg:address":"18645 Pacato Rd",
    "sg:city":"La Puente",
    "sg:classifiers":[
        {
            "category":"Freight",
            "type":"Transportation"
        }
    ],
    "sg:phone":"+1 626 912 0697",
    "sg:postcode":"91744",
    "sg:province":"CA",
    "sg:tags":[
        "operator",
        "trucking"
    ],
    "wof:name":"Giordani Transportation",
    "wof:placetype":"venue"
},
  "geometry": {"coordinates":[-117.896074,34.006173],"type":"Point"}
}