{
  "type": "Feature",
  "properties": {
    "iso:country":"US",
    "sg:address":"16176 Valleyvale Dr",
    "sg:city":"Fontana",
    "sg:classifiers":[
        {
            "category":"Professional",
            "subcategory":"Business Services",
            "type":"Services"
        }
    ],
    "sg:phone":"+1 909 822 4427",
    "sg:postcode":"92337",
    "sg:province":"CA",
    "sg:tags":[
        "notary"
    ],
    "wof:name":"Ellis Charles Rail",
    "wof:placetype":"venue"
},
  "geometry": {"coordinates":[-117.452591,34.045726],"type":"Point"}
}