{
  "type": "Feature",
  "properties": {
    "addr:full":"649 N Carleton Ave Anaheim CA 92801",
    "addr:housenumber":"649",
    "addr:postcode":"92801",
    "addr:street":"N Carleton Ave",
    "iso:country":"US",
    "sg:address":"649 N Carleton Ave",
    "sg:city":"Anaheim",
    "sg:classifiers":[
        {
            "category":"Real Estate",
            "subcategory":"Real Estate Agent",
            "type":"Services"
        }
    ],
    "sg:phone":"+1 714 635 1826",
    "sg:postcode":"92801",
    "sg:province":"CA",
    "wof:name":"A Plus Burke Realty",
    "wof:placetype":"venue"
},
  "geometry": {"coordinates":[-117.930413,33.838834],"type":"Point"}
}