{
  "type": "Feature",
  "properties": {
    "addr:full":"9328 Civic Center Dr Beverly Hills CA 90210",
    "addr:housenumber":"9328",
    "addr:postcode":"90210",
    "addr:street":"Civic Center Dr",
    "iso:country":"US",
    "sg:address":"9328 Civic Center Dr",
    "sg:city":"Beverly Hills",
    "sg:classifiers":[
        {
            "category":"Communications",
            "subcategory":"Film & Video Production",
            "type":"Services"
        }
    ],
    "sg:phone":"+1 310 275 1191",
    "sg:postcode":"90210",
    "sg:province":"CA",
    "sg:tags":[
        "motion",
        "picture",
        "studio",
        "producer"
    ],
    "sg:website":"www.tapestryfilms.com",
    "wof:name":"Tapestry Films",
    "wof:placetype":"venue"
},
  "geometry": {"coordinates":[-118.39678499999999,34.075926],"type":"Point"}
}