{
  "type": "Feature",
  "properties": {
    "iso:country":"US",
    "sg:address":"7232 Maple Ave",
    "sg:city":"Sebastopol",
    "sg:classifiers":[
        {
            "category":"Real Estate",
            "subcategory":"Real Estate Agent",
            "type":"Services"
        }
    ],
    "sg:phone":"+1 707 829 8753",
    "sg:postcode":"95472",
    "sg:province":"CA",
    "sg:tags":[
        "appraiser"
    ],
    "wof:name":"Shoreline Group",
    "wof:placetype":"venue"
},
  "geometry": {"coordinates":[-122.823554,38.397176],"type":"Point"}
}