{
  "type": "Feature",
  "properties": {
    "iso:country":"US",
    "sg:address":"995 Oliver Rd",
    "sg:city":"Fairfield",
    "sg:classifiers":[
        {
            "category":"Personal",
            "subcategory":"Beauty Salon",
            "type":"Services"
        }
    ],
    "sg:phone":"+1 707 428 4477",
    "sg:postcode":"94534",
    "sg:province":"CA",
    "sg:tags":[
        "school"
    ],
    "wof:name":"Cosmo Rents",
    "wof:placetype":"venue"
},
  "geometry": {"coordinates":[-122.067342,38.255285],"type":"Point"}
}