{
  "type": "Feature",
  "properties": {
    "addr:full":"21201 Victory Blvd Ste 140 Canoga Park CA 91303",
    "addr:housenumber":"21201",
    "addr:postcode":"91303",
    "addr:street":"Victory Blvd Ste 140",
    "iso:country":"US",
    "sg:address":"21201 Victory Blvd Ste 140",
    "sg:city":"Canoga Park",
    "sg:classifiers":[
        {
            "category":"Professional",
            "subcategory":"Lawyer & Legal Services",
            "type":"Services"
        }
    ],
    "sg:phone":"+1 818 346 2936",
    "sg:postcode":"91303",
    "sg:province":"CA",
    "wof:name":"Hecht Benjamin L Attorney At Law",
    "wof:placetype":"venue"
},
  "geometry": {"coordinates":[-118.594002,34.1884],"type":"Point"}
}