{
  "type": "Feature",
  "properties": {
    "addr:full":"1030 N Main St Ste B Orange CA 92867",
    "addr:housenumber":"1030",
    "addr:postcode":"92867",
    "addr:street":"N Main St Ste B",
    "iso:country":"US",
    "sg:address":"1030 N Main St Ste B",
    "sg:city":"Orange",
    "sg:classifiers":[
        {
            "category":"Autos & Motor Vehicles",
            "subcategory":"Automobile Sales",
            "type":"Retail Goods"
        }
    ],
    "sg:phone":"+1 714 288 8782",
    "sg:postcode":"92867",
    "sg:province":"CA",
    "sg:tags":[
        "automotive"
    ],
    "wof:name":"Orange Hitch & Trailer Repair",
    "wof:placetype":"venue"
},
  "geometry": {"coordinates":[-117.867656,33.804741],"type":"Point"}
}