{
  "type": "Feature",
  "properties": {
    "addr:full":"797 Saratoga Ave Grover Beach CA 93433",
    "addr:housenumber":"797",
    "addr:postcode":"93433",
    "addr:street":"Saratoga Ave",
    "iso:country":"US",
    "sg:address":"797 Saratoga Ave",
    "sg:city":"Grover Beach",
    "sg:classifiers":[
        {
            "category":"Social Services",
            "subcategory":"Adult Care",
            "type":"Services"
        }
    ],
    "sg:phone":"+1 805 489 9706",
    "sg:postcode":"93433",
    "sg:province":"CA",
    "sg:tags":[
        "home",
        "residential"
    ],
    "wof:name":"Get Total Tender Loving Care",
    "wof:placetype":"venue"
},
  "geometry": {"coordinates":[-120.621371,35.126428],"type":"Point"}
}