{
  "type": "Feature",
  "properties": {
    "addr:full":"5550 Telegraph Rd Ventura CA 93003",
    "addr:housenumber":"5550",
    "addr:postcode":"93003",
    "addr:street":"Telegraph Rd",
    "iso:country":"US",
    "sg:address":"5550 Telegraph Rd",
    "sg:city":"Ventura",
    "sg:classifiers":[
        {
            "category":"Health Services",
            "subcategory":"Chiropractor",
            "type":"Services"
        }
    ],
    "sg:phone":"+1 805 644 4937",
    "sg:postcode":"93003",
    "sg:province":"CA",
    "sg:tags":[
        "chiropractic"
    ],
    "wof:name":"Seaside Chiropractic",
    "wof:placetype":"venue"
},
  "geometry": {"coordinates":[-119.219493,34.277271],"type":"Point"}
}