{
  "type": "Feature",
  "properties": {
    "iso:country":"US",
    "sg:address":"1301 Monterey Blvd",
    "sg:city":"San Francisco",
    "sg:classifiers":[
        {
            "category":"Social Services",
            "type":"Services"
        }
    ],
    "sg:phone":"+1 415 337 7380",
    "sg:postcode":"94127",
    "sg:province":"CA",
    "sg:tags":[
        "counseling"
    ],
    "wof:name":"Luanna L Rodgers Mfcc",
    "wof:placetype":"venue"
},
  "geometry": {"coordinates":[-122.463144,37.730448],"type":"Point"}
}