{
  "type": "Feature",
  "properties": {
    "addr:full":"126 High St Santa Cruz CA 95060",
    "addr:housenumber":"126",
    "addr:postcode":"95060",
    "addr:street":"High St",
    "iso:country":"US",
    "sg:address":"126 High St",
    "sg:city":"Santa Cruz",
    "sg:classifiers":[
        {
            "category":"Shopping",
            "subcategory":"Gifts & Souvenirs",
            "type":"Retail Goods"
        }
    ],
    "sg:phone":"+1 831 426 5686",
    "sg:postcode":"95060",
    "sg:province":"CA",
    "sg:tags":[
        "shop"
    ],
    "wof:name":"Mision Galeria",
    "wof:placetype":"venue"
},
  "geometry": {"coordinates":[-122.030067,36.978422],"type":"Point"}
}