{
  "type": "Feature",
  "properties": {
    "addr:full":"3465 S Chestnut Ave Fresno CA 93725",
    "addr:housenumber":"3465",
    "addr:postcode":"93725",
    "addr:street":"S Chestnut Ave",
    "iso:country":"US",
    "sg:address":"3465 S Chestnut Ave",
    "sg:city":"Fresno",
    "sg:classifiers":[
        {
            "category":"Restaurant",
            "type":"Food & Drink"
        }
    ],
    "sg:phone":"+1 559 268 1477",
    "sg:postcode":"93725",
    "sg:province":"CA",
    "wof:name":"Abe's Happy Subs",
    "wof:placetype":"venue"
},
  "geometry": {"coordinates":[-119.736734,36.685],"type":"Point"}
}