{
  "type": "Feature",
  "properties": {
    "addr:full":"7825 Cll Juela La Jolla CA 92037",
    "addr:housenumber":"7825",
    "addr:postcode":"92037",
    "addr:street":"Cll Juela",
    "iso:country":"US",
    "sg:address":"7825 Cll Juela",
    "sg:city":"La Jolla",
    "sg:classifiers":[
        {
            "category":"Utilities",
            "subcategory":"Telephone",
            "type":"Services"
        }
    ],
    "sg:phone":"+1 858 362 2323",
    "sg:postcode":"92037",
    "sg:province":"CA",
    "sg:tags":[
        "digital",
        "programming",
        "music",
        "t",
        "provides",
        "internet",
        "using"
    ],
    "wof:name":"Trusonic Inc",
    "wof:placetype":"venue"
},
  "geometry": {"coordinates":[-117.254717,32.849643],"type":"Point"}
}