{
  "type": "Feature",
  "properties": {
    "addr:full":"4260 1st St Livermore CA 94550",
    "addr:housenumber":"4260",
    "addr:postcode":"94550",
    "addr:street":"1St St",
    "iso:country":"US",
    "sg:address":"4260 1st St",
    "sg:city":"Livermore",
    "sg:classifiers":[
        {
            "category":"Banks & Credit Unions",
            "subcategory":"Investment Brokerage",
            "type":"Services"
        }
    ],
    "sg:phone":"+1 925 443 8815",
    "sg:postcode":"94550",
    "sg:province":"CA",
    "sg:tags":[
        "trade",
        "barter",
        "exchange"
    ],
    "wof:name":"Barter Jubilee",
    "wof:placetype":"venue"
},
  "geometry": {"coordinates":[-121.743306,37.698],"type":"Point"}
}