{
  "type": "Feature",
  "properties": {
    "iso:country":"US",
    "sg:address":"215 Reservation Rd Ste N",
    "sg:city":"Marina",
    "sg:classifiers":[
        {
            "category":"Fast Food",
            "type":"Food & Drink"
        },
        {
            "category":"Deli",
            "type":"Food & Drink"
        },
        {
            "category":"Restaurant",
            "type":"Food & Drink"
        },
        {
            "category":"Food & Beverages",
            "subcategory":"Bakery",
            "type":"Retail Goods"
        },
        {
            "category":"Food & Beverages",
            "subcategory":"Ethnic Foods",
            "type":"Retail Goods"
        }
    ],
    "sg:phone":"+1 831 384 7821",
    "sg:postcode":"93933",
    "sg:province":"CA",
    "sg:tags":[
        "german",
        "delicatessen",
        "sandwich",
        "take"
    ],
    "wof:name":"Mecca Delicatessen",
    "wof:placetype":"venue"
},
  "geometry": {"coordinates":[-121.797997,36.687199],"type":"Point"}
}