{
  "type": "Feature",
  "properties": {
    "addr:full":"633 S Broadway Los Angeles CA 90014",
    "addr:housenumber":"633",
    "addr:postcode":"90014",
    "addr:street":"S Broadway",
    "iso:country":"US",
    "sg:address":"633 S Broadway",
    "sg:city":"Los Angeles",
    "sg:classifiers":[
        {
            "category":"Home & Garden",
            "subcategory":"Home Furnishings",
            "type":"Retail Goods"
        }
    ],
    "sg:phone":"+1 213 624 6367",
    "sg:postcode":"90014",
    "sg:province":"CA",
    "sg:tags":[
        "mirror"
    ],
    "wof:name":"Professional Mirrors & Glass",
    "wof:placetype":"venue"
},
  "geometry": {"coordinates":[-118.25306500000001,34.045727],"type":"Point"}
}