{
  "type": "Feature",
  "properties": {
    "addr:full":"547 Bryant St Palo Alto CA 94301",
    "addr:housenumber":"547",
    "addr:postcode":"94301",
    "addr:street":"Bryant St",
    "iso:country":"US",
    "sg:address":"547 Bryant St",
    "sg:city":"Palo Alto",
    "sg:classifiers":[
        {
            "category":"Shopping",
            "subcategory":"Clothing, Apparel, & Fashions",
            "type":"Retail Goods"
        }
    ],
    "sg:phone":"+1 650 323 7979",
    "sg:postcode":"94301",
    "sg:province":"CA",
    "sg:tags":[
        "lingerie"
    ],
    "sg:website":"www.gittis-fine-lingerie.com",
    "wof:name":"Gitti's Fine Lingerie",
    "wof:placetype":"venue"
},
  "geometry": {"coordinates":[-122.16080100000001,37.44552],"type":"Point"}
}