{
  "type": "Feature",
  "properties": {
    "iso:country":"US",
    "sg:address":"200 Clock Tower Pl",
    "sg:city":"Carmel",
    "sg:classifiers":[
        {
            "category":"Banks & Credit Unions",
            "subcategory":"Financial Services",
            "type":"Services"
        }
    ],
    "sg:phone":"+1 831 625 3939",
    "sg:postcode":"93923",
    "sg:province":"CA",
    "sg:tags":[
        "broker",
        "mortgage"
    ],
    "sg:website":"www.carmel-mortgage.com",
    "wof:name":"Carmel Mortgage",
    "wof:placetype":"venue"
},
  "geometry": {"coordinates":[-121.905998,36.539799],"type":"Point"}
}