{
  "type": "Feature",
  "properties": {
    "iso:country":"US",
    "sg:address":"924 W Alisal St",
    "sg:city":"Salinas",
    "sg:classifiers":[
        {
            "category":"Real Estate",
            "subcategory":"Real Estate Operator",
            "type":"Services"
        }
    ],
    "sg:phone":"+1 831 424 3775",
    "sg:postcode":"93901",
    "sg:province":"CA",
    "sg:tags":[
        "building",
        "apartment"
    ],
    "wof:name":"Carmelita Apts",
    "wof:placetype":"venue"
},
  "geometry": {"coordinates":[-121.67391499999999,36.66856],"type":"Point"}
}