{
  "type": "Feature",
  "properties": {
    "iso:country":"US",
    "sg:address":"1048 Irvine Ave",
    "sg:city":"Newport Beach",
    "sg:classifiers":[
        {
            "category":"Building & Trades",
            "subcategory":"Landscaping Services",
            "type":"Services"
        }
    ],
    "sg:phone":"+1 949 244 7414",
    "sg:postcode":"92660",
    "sg:province":"CA",
    "sg:tags":[
        "landscape"
    ],
    "wof:name":"Contractors West One",
    "wof:placetype":"venue"
},
  "geometry": {"coordinates":[-117.907651,33.629481],"type":"Point"}
}