{
  "type": "Feature",
  "properties": {
    "iso:country":"US",
    "sg:address":"7165 Clearbrook Way",
    "sg:city":"Sacramento",
    "sg:classifiers":[
        {
            "category":"Building & Trades",
            "subcategory":"Electrical",
            "type":"Services"
        }
    ],
    "sg:phone":"+1 916 682 2956",
    "sg:postcode":"95823",
    "sg:province":"CA",
    "sg:tags":[
        "electrical",
        "contractor"
    ],
    "wof:name":"All Power",
    "wof:placetype":"venue"
},
  "geometry": {"coordinates":[-121.419173,38.442655],"type":"Point"}
}