{
  "type": "Feature",
  "properties": {
    "addr:full":"833 S Western Ave #39 Los Angeles CA 90005",
    "addr:housenumber":"833",
    "addr:postcode":"90005",
    "addr:street":"S Western Ave # 39",
    "iso:country":"US",
    "sg:address":"833 S Western Ave #39",
    "sg:city":"Los Angeles",
    "sg:classifiers":[
        {
            "category":"Restaurant",
            "type":"Food & Drink"
        }
    ],
    "sg:phone":"+1 213 365 1699",
    "sg:postcode":"90005",
    "sg:province":"CA",
    "sg:tags":[
        "korean"
    ],
    "sg:website":"blog.naver.com/xcreative/1201028...",
    "wof:name":"Naeng Myun Nara",
    "wof:placetype":"venue"
},
  "geometry": {"coordinates":[-118.30925000000001,34.05729],"type":"Point"}
}