{
  "type": "Feature",
  "properties": {
    "addr:full":"941 W Mission Blvd Ontario CA 91762",
    "addr:housenumber":"941",
    "addr:postcode":"91762",
    "addr:street":"W Mission Blvd",
    "iso:country":"US",
    "sg:address":"941 W Mission Blvd",
    "sg:city":"Ontario",
    "sg:classifiers":[
        {
            "category":"Travel",
            "subcategory":"Travel Agent",
            "type":"Entertainment"
        }
    ],
    "sg:phone":"+1 909 984 2800",
    "sg:postcode":"91762",
    "sg:province":"CA",
    "sg:tags":[
        "agency",
        "bureau"
    ],
    "wof:name":"Acapulco Travel & Tours Inc",
    "wof:placetype":"venue"
},
  "geometry": {"coordinates":[-117.664945,34.055971],"type":"Point"}
}