{
  "type": "Feature",
  "properties": {
    "addr:full":"216 Ridgevale Ln Pleasant Hill CA 94523",
    "addr:housenumber":"216",
    "addr:postcode":"94523",
    "addr:street":"Ridgevale Ln",
    "iso:country":"US",
    "sg:address":"216 Ridgevale Ln",
    "sg:city":"Pleasant Hill",
    "sg:classifiers":[
        {
            "category":"Professional",
            "subcategory":"Business Services",
            "type":"Services"
        }
    ],
    "sg:phone":"+1 925 945 6511",
    "sg:postcode":"94523",
    "sg:province":"CA",
    "sg:tags":[
        "interior",
        "design"
    ],
    "sg:website":"www.suitedesigns.com",
    "wof:name":"Suite Designs",
    "wof:placetype":"venue"
},
  "geometry": {"coordinates":[-122.08334499999999,37.94122],"type":"Point"}
}