{
  "type": "Feature",
  "properties": {
    "iso:country":"US",
    "sg:address":"3878 S Willow Ave",
    "sg:city":"Fresno",
    "sg:classifiers":[
        {
            "category":"Manufacturing",
            "subcategory":"Retail Goods",
            "type":"Manufacturing & Wholesale Goods"
        }
    ],
    "sg:phone":"+1 559 233 1883",
    "sg:postcode":"93725",
    "sg:province":"CA",
    "sg:tags":[
        "assembly",
        "fabricating"
    ],
    "wof:name":"Fabricated Extrusion Co",
    "wof:placetype":"venue"
},
  "geometry": {"coordinates":[-119.726781,36.680552],"type":"Point"}
}