{
  "type": "Feature",
  "properties": {
    "iso:country":"US",
    "sg:address":"10734 White Oak Ave",
    "sg:city":"Granada Hills",
    "sg:classifiers":[
        {
            "category":"Insurance",
            "subcategory":"Insurance Agent",
            "type":"Services"
        }
    ],
    "sg:phone":"+1 818 360 3315",
    "sg:postcode":"91344",
    "sg:province":"CA",
    "wof:name":"John Cleary",
    "wof:placetype":"venue"
},
  "geometry": {"coordinates":[-118.519659,34.265683],"type":"Point"}
}