{
  "type": "Feature",
  "properties": {
    "addr:full":"130 S Main St Sebastopol CA 95472",
    "addr:housenumber":"130",
    "addr:postcode":"95472",
    "addr:street":"S Main St",
    "iso:country":"US",
    "sg:address":"130 S Main St",
    "sg:city":"Sebastopol",
    "sg:classifiers":[
        {
            "category":"Professional",
            "subcategory":"Computer Services",
            "type":"Services"
        }
    ],
    "sg:phone":"+1 707 829 7242",
    "sg:postcode":"95472",
    "sg:province":"CA",
    "wof:name":"Luminee",
    "wof:placetype":"venue"
},
  "geometry": {"coordinates":[-122.824023,38.40171],"type":"Point"}
}