{
  "type": "Feature",
  "properties": {
    "addr:full":"26626 Western Ave Harbor City CA 90717",
    "addr:housenumber":"26626",
    "addr:postcode":"90717",
    "addr:street":"Western Ave",
    "iso:country":"US",
    "sg:address":"26626 Western Ave",
    "sg:city":"Harbor City",
    "sg:classifiers":[
        {
            "category":"Education",
            "subcategory":"Special Training",
            "type":"Public Place"
        }
    ],
    "sg:phone":"+1 310 325 9777",
    "sg:postcode":"90717",
    "sg:province":"CA",
    "sg:tags":[
        "school",
        "instruction",
        "art"
    ],
    "wof:name":"Artful Minds",
    "wof:placetype":"venue"
},
  "geometry": {"coordinates":[-118.309566,33.779562],"type":"Point"}
}