{
  "type": "Feature",
  "properties": {
    "iso:country":"US",
    "sg:address":"17504 ermanita ave",
    "sg:city":"Torrance",
    "sg:classifiers":[
        {
            "category":"Building & Trades",
            "subcategory":"Construction",
            "type":"Services"
        },
        {
            "category":"Real Estate",
            "subcategory":"Architect",
            "type":"Services"
        }
    ],
    "sg:phone":"+1 310 516 7663",
    "sg:postcode":"90504",
    "sg:province":"CA",
    "sg:tags":[
        "contractor"
    ],
    "sg:website":"www.alsrepairs.com",
    "wof:name":"Al's Repairs & Remodeling",
    "wof:placetype":"venue"
},
  "geometry": {"coordinates":[-118.33199999999999,33.871802],"type":"Point"}
}