{
  "type": "Feature",
  "properties": {
    "addr:full":"860 Hillview Ct Ste 300 Milpitas CA 95035",
    "addr:housenumber":"860",
    "addr:postcode":"95035",
    "addr:street":"Hillview Ct Ste 300",
    "iso:country":"US",
    "sg:address":"860 Hillview Ct Ste 300",
    "sg:city":"Milpitas",
    "sg:classifiers":[
        {
            "category":"Banks & Credit Unions",
            "subcategory":"Financial Services",
            "type":"Services"
        }
    ],
    "sg:phone":"+1 408 941 8333",
    "sg:postcode":"95035",
    "sg:province":"CA",
    "sg:tags":[
        "broker",
        "mortgage"
    ],
    "sg:website":"www.reunionmortgage.com",
    "wof:name":"Reunion Mortgage",
    "wof:placetype":"venue"
},
  "geometry": {"coordinates":[-121.892015,37.436209],"type":"Point"}
}