{
  "type": "Feature",
  "properties": {
    "addr:full":"2480 Clay Bank Rd Fairfield CA 94533",
    "addr:housenumber":"2480",
    "addr:postcode":"94533",
    "addr:street":"Clay Bank Rd",
    "iso:country":"US",
    "sg:address":"2480 Clay Bank Rd",
    "sg:city":"Fairfield",
    "sg:classifiers":[
        {
            "category":"Government",
            "subcategory":"Office",
            "type":"Public Place"
        }
    ],
    "sg:phone":"+1 707 421 7184",
    "sg:postcode":"94533",
    "sg:province":"CA",
    "sg:website":"www.solanocounty.com",
    "wof:name":"Solano County Work Furlough",
    "wof:placetype":"venue"
},
  "geometry": {"coordinates":[-122.006466,38.273607],"type":"Point"}
}