{
  "type": "Feature",
  "properties": {
    "addr:full":"425 S Fairfax Ave Los Angeles CA 90036",
    "addr:housenumber":"425",
    "addr:postcode":"90036",
    "addr:street":"S Fairfax Ave",
    "iso:country":"US",
    "sg:address":"425 S Fairfax Ave",
    "sg:city":"Los Angeles",
    "sg:classifiers":[
        {
            "category":"Professional",
            "type":"Services"
        }
    ],
    "sg:phone":"+1 323 933 7456",
    "sg:postcode":"90036",
    "sg:province":"CA",
    "sg:tags":[
        "establishment"
    ],
    "wof:name":"LA Express Medical",
    "wof:placetype":"venue"
},
  "geometry": {"coordinates":[-118.36147800000001,34.06978],"type":"Point"}
}