{
  "type": "Feature",
  "properties": {
    "addr:full":"1500 Stoneham Way La Habra CA 90631",
    "addr:housenumber":"1500",
    "addr:postcode":"90631",
    "addr:street":"Stoneham Way",
    "iso:country":"US",
    "sg:address":"1500 Stoneham Way",
    "sg:city":"La Habra",
    "sg:classifiers":[
        {
            "category":"Communications",
            "subcategory":"Film & Video Production",
            "type":"Services"
        }
    ],
    "sg:phone":"+1 562 691 2862",
    "sg:postcode":"90631",
    "sg:province":"CA",
    "sg:tags":[
        "taping"
    ],
    "wof:name":"Engle Productions",
    "wof:placetype":"venue"
},
  "geometry": {"coordinates":[-117.963055,33.924033],"type":"Point"}
}