{
  "type": "Feature",
  "properties": {
    "iso:country":"US",
    "sg:address":"34 Argento",
    "sg:city":"Mission Viejo",
    "sg:classifiers":[
        {
            "category":"Shopping",
            "type":"Retail Goods"
        }
    ],
    "sg:phone":"+1 949 588 9888",
    "sg:postcode":"92692",
    "sg:province":"CA",
    "sg:tags":[
        "merchandise"
    ],
    "wof:name":"All Star Collectibles",
    "wof:placetype":"venue"
},
  "geometry": {"coordinates":[-117.646666,33.594032],"type":"Point"}
}