{
  "type": "Feature",
  "properties": {
    "addr:full":"1007 W Foothill Blvd Upland CA 91786",
    "addr:housenumber":"1007",
    "addr:postcode":"91786",
    "addr:street":"W Foothill Blvd",
    "iso:country":"US",
    "sg:address":"1007 W Foothill Blvd",
    "sg:city":"Upland",
    "sg:classifiers":[
        {
            "category":"Food & Beverages",
            "subcategory":"Groceries & Convenience Stores",
            "type":"Retail Goods"
        }
    ],
    "sg:phone":"+1 909 949 4743",
    "sg:postcode":"91786",
    "sg:province":"CA",
    "wof:name":"H Foodmart",
    "wof:placetype":"venue"
},
  "geometry": {"coordinates":[-117.669985,34.107045],"type":"Point"}
}