{
  "type": "Feature",
  "properties": {
    "iso:country":"US",
    "sg:address":"1031 Ohio St",
    "sg:city":"Redlands",
    "sg:classifiers":[
        {
            "category":"Organizations",
            "subcategory":"Religious Organization",
            "type":"Services"
        }
    ],
    "sg:phone":"+1 909 793 8278",
    "sg:postcode":"92374",
    "sg:province":"CA",
    "sg:tags":[
        "church"
    ],
    "wof:name":"Assembly Of God Church",
    "wof:placetype":"venue"
},
  "geometry": {"coordinates":[-117.18585899999999,34.06608],"type":"Point"}
}