{
  "type": "Feature",
  "properties": {
    "addr:full":"6280 Clark Rd Paradise CA 95969",
    "addr:housenumber":"6280",
    "addr:postcode":"95969",
    "addr:street":"Clark Rd",
    "iso:country":"US",
    "sg:address":"6280 Clark Rd",
    "sg:city":"Paradise",
    "sg:classifiers":[
        {
            "category":"Organizations",
            "subcategory":"Religious Organization",
            "type":"Services"
        }
    ],
    "sg:phone":"+1 530 872 2441",
    "sg:postcode":"95969",
    "sg:province":"CA",
    "sg:tags":[
        "church"
    ],
    "wof:name":"Jubilee On The Ridge",
    "wof:placetype":"venue"
},
  "geometry": {"coordinates":[-121.60129000000001,39.766323],"type":"Point"}
}