{
  "type": "Feature",
  "properties": {
    "iso:country":"US",
    "sg:address":"928 Cll Verde",
    "sg:city":"Martinez",
    "sg:classifiers":[
        {
            "category":"Freight",
            "type":"Transportation"
        }
    ],
    "sg:phone":"+1 925 370 2987",
    "sg:postcode":"94553",
    "sg:province":"CA",
    "sg:tags":[
        "operator",
        "local",
        "trucking"
    ],
    "wof:name":"SJV Trucking",
    "wof:placetype":"venue"
},
  "geometry": {"coordinates":[-122.11441000000001,37.956279],"type":"Point"}
}