{
  "type": "Feature",
  "properties": {
    "iso:country":"US",
    "sg:address":"8537 Sunset Blvd Ste 2",
    "sg:city":"West Hollywood",
    "sg:classifiers":[
        {
            "category":"Personal",
            "subcategory":"Skin Care",
            "type":"Services"
        },
        {
            "category":"Personal",
            "subcategory":"Day Spa",
            "type":"Services"
        }
    ],
    "sg:phone":"+1 310 774 1439",
    "sg:postcode":"90069",
    "sg:province":"CA",
    "sg:website":"www.stoneskincare.com/",
    "wof:name":"Stone Skin Care",
    "wof:placetype":"venue"
},
  "geometry": {"coordinates":[-118.377016,34.093989],"type":"Point"}
}