{
  "type": "Feature",
  "properties": {
    "iso:country":"US",
    "sg:address":"40665 Winchester Rd",
    "sg:city":"Temecula",
    "sg:classifiers":[
        {
            "category":"Social Services",
            "subcategory":"Child Care",
            "type":"Services"
        }
    ],
    "sg:phone":"+1 951 296 9456",
    "sg:postcode":"92591",
    "sg:province":"CA",
    "sg:tags":[
        "kindergarten",
        "preschool"
    ],
    "sg:website":"http://www.kidscareclub.com",
    "wof:name":"Kids Care Club",
    "wof:placetype":"venue"
},
  "geometry": {"coordinates":[-117.156493,33.527558],"type":"Point"}
}