{
  "type": "Feature",
  "properties": {
    "iso:country":"US",
    "sg:address":"2301 Cam Ramon",
    "sg:city":"San Ramon",
    "sg:classifiers":[
        {
            "category":"Health Services",
            "subcategory":"Doctor",
            "type":"Services"
        }
    ],
    "sg:phone":"+1 925 806 0322",
    "sg:postcode":"94583",
    "sg:province":"CA",
    "sg:tags":[
        "physician",
        "surgeon"
    ],
    "wof:name":"Pediatrics Dentistry-San Ramon",
    "wof:placetype":"venue"
},
  "geometry": {"coordinates":[-121.967181,37.776902],"type":"Point"}
}