{
  "type": "Feature",
  "properties": {
    "addr:full":"2683 Via de la Valle Del Mar CA 92014",
    "addr:housenumber":"2683",
    "addr:postcode":"92014",
    "addr:street":"Via De La Valle",
    "iso:country":"US",
    "sg:address":"2683 Via de la Valle",
    "sg:city":"Del Mar",
    "sg:classifiers":[
        {
            "category":"Shopping",
            "subcategory":"Jewelry",
            "type":"Retail Goods"
        }
    ],
    "sg:phone":"+1 858 755 1840",
    "sg:postcode":"92014",
    "sg:province":"CA",
    "sg:tags":[
        "designer"
    ],
    "wof:name":"Beget Nuance",
    "wof:placetype":"venue"
},
  "geometry": {"coordinates":[-117.24722199999999,32.981035],"type":"Point"}
}