{
  "type": "Feature",
  "properties": {
    "iso:country":"US",
    "sg:address":"207 E Pennsylvania Ave",
    "sg:city":"Escondido",
    "sg:classifiers":[
        {
            "category":"Manufacturing",
            "subcategory":"Printing",
            "type":"Manufacturing & Wholesale Goods"
        }
    ],
    "sg:phone":"+1 760 839 3333",
    "sg:postcode":"92025",
    "sg:province":"CA",
    "sg:tags":[
        "newspaper"
    ],
    "sg:website":"www.nctimes.com",
    "wof:name":"North County Times",
    "wof:placetype":"venue"
},
  "geometry": {"coordinates":[-117.080057,33.124749],"type":"Point"}
}