{
  "type": "Feature",
  "properties": {
    "iso:country":"US",
    "sg:address":"204 Macaw Ln",
    "sg:city":"Fountain Valley",
    "sg:classifiers":[
        {
            "category":"Shopping",
            "subcategory":"Crafts & Fabrics",
            "type":"Retail Goods"
        }
    ],
    "sg:phone":"+1 714 378 9490",
    "sg:postcode":"92708",
    "sg:province":"CA",
    "sg:tags":[
        "manufacture",
        "pattern",
        "clothing",
        "for"
    ],
    "wof:name":"Z Golden Rule",
    "wof:placetype":"venue"
},
  "geometry": {"coordinates":[-117.965423,33.698591],"type":"Point"}
}