{
  "type": "Feature",
  "properties": {
    "iso:country":"US",
    "sg:address":"5615 Chesbro Ave",
    "sg:city":"San Jose",
    "sg:classifiers":[
        {
            "category":"Insurance",
            "subcategory":"Insurance Agent",
            "type":"Services"
        }
    ],
    "sg:phone":"+1 408 224 6309",
    "sg:postcode":"95123",
    "sg:province":"CA",
    "wof:name":"Farmers Agency Almaden-Blossom",
    "wof:placetype":"venue"
},
  "geometry": {"coordinates":[-121.84259900000001,37.248627],"type":"Point"}
}