{
  "type": "Feature",
  "properties": {
    "iso:country":"US",
    "sg:address":"633 N Azusa Ave",
    "sg:city":"Azusa",
    "sg:classifiers":[
        {
            "category":"Shopping",
            "subcategory":"Music",
            "type":"Retail Goods"
        }
    ],
    "sg:phone":"+1 626 969 0142",
    "sg:postcode":"91702",
    "sg:province":"CA",
    "sg:tags":[
        "video",
        "disc",
        "tape",
        "cassette"
    ],
    "wof:name":"Imagemax Video",
    "wof:placetype":"venue"
},
  "geometry": {"coordinates":[-117.9076,34.13288],"type":"Point"}
}