{
  "type": "Feature",
  "properties": {
    "iso:country":"US",
    "sg:address":"2140 E Main St",
    "sg:city":"Quincy",
    "sg:classifiers":[
        {
            "category":"Retail",
            "subcategory":"Auto Repair",
            "type":"Services"
        }
    ],
    "sg:phone":"+1 530 283 2235",
    "sg:postcode":"95971",
    "sg:province":"CA",
    "sg:tags":[
        "repairing",
        "automobile"
    ],
    "wof:name":"Shadetree Automotive Repair",
    "wof:placetype":"venue"
},
  "geometry": {"coordinates":[-120.89807999999999,39.93384],"type":"Point"}
}