{
  "type": "Feature",
  "properties": {
    "iso:country":"US",
    "sg:address":"217 E Alameda Ave",
    "sg:city":"Burbank",
    "sg:classifiers":[
        {
            "category":"Insurance",
            "subcategory":"Insurance Agent",
            "type":"Services"
        }
    ],
    "sg:phone":"+1 818 846 5550",
    "sg:postcode":"91502",
    "sg:province":"CA",
    "wof:name":"Harry Zenjirjian Insur Agcy",
    "wof:placetype":"venue"
},
  "geometry": {"coordinates":[-118.299758,34.174593],"type":"Point"}
}