{
  "type": "Feature",
  "properties": {
    "addr:full":"1430 W San Carlos St San Jose CA 95110",
    "addr:housenumber":"1430",
    "addr:postcode":"95110",
    "addr:street":"W San Carlos St",
    "iso:country":"US",
    "sg:address":"1430 W San Carlos St",
    "sg:city":"San Jose",
    "sg:classifiers":[
        {
            "category":"Autos & Motor Vehicles",
            "subcategory":"Automobile Sales",
            "type":"Retail Goods"
        }
    ],
    "sg:phone":"+1 408 287 5855",
    "sg:postcode":"95110",
    "sg:province":"CA",
    "sg:tags":[
        "car",
        "dealer"
    ],
    "wof:name":"EBS Auto Oulet",
    "wof:placetype":"venue"
},
  "geometry": {"coordinates":[-121.91437999999999,37.323415],"type":"Point"}
}