{
  "type": "Feature",
  "properties": {
    "addr:full":"7695 Formula Pl San Diego CA 92121",
    "addr:housenumber":"7695",
    "addr:postcode":"92121",
    "addr:street":"Formula Pl",
    "iso:country":"US",
    "sg:address":"7695 Formula Pl",
    "sg:city":"San Diego",
    "sg:classifiers":[
        {
            "category":"Professional",
            "subcategory":"Research",
            "type":"Services"
        }
    ],
    "sg:phone":"+1 858 271 6330",
    "sg:postcode":"92121",
    "sg:province":"CA",
    "sg:tags":[
        "commercial",
        "physical"
    ],
    "sg:website":"www.sterigenics.com",
    "wof:name":"IBA Sterigenics",
    "wof:placetype":"venue"
},
  "geometry": {"coordinates":[-117.156586,32.88782],"type":"Point"}
}