{
  "type": "Feature",
  "properties": {
    "addr:full":"35688 Cathedral Canyon Dr Cathedral City CA 92234",
    "addr:housenumber":"35688",
    "addr:postcode":"92234",
    "addr:street":"Cathedral Canyon Dr",
    "iso:country":"US",
    "sg:address":"35688 Cathedral Canyon Dr",
    "sg:city":"Cathedral City",
    "sg:classifiers":[
        {
            "category":"Building & Trades",
            "subcategory":"Construction",
            "type":"Services"
        }
    ],
    "sg:phone":"+1 760 321 0830",
    "sg:postcode":"92234",
    "sg:province":"CA",
    "sg:tags":[
        "painter"
    ],
    "wof:name":"Valley Urethane Foam Roofing Inc",
    "wof:placetype":"venue"
},
  "geometry": {"coordinates":[-116.46700300000001,33.791],"type":"Point"}
}