{
  "type": "Feature",
  "properties": {
    "iso:country":"US",
    "sg:address":"916 Dr Martin Luther King Jr Blvd",
    "sg:city":"Bakersfield",
    "sg:classifiers":[
        {
            "category":"Restaurant",
            "type":"Food & Drink"
        }
    ],
    "sg:phone":"+1 661 324 4211",
    "sg:postcode":"93307",
    "sg:province":"CA",
    "wof:name":"Las Comadres Restaurant",
    "wof:placetype":"venue"
},
  "geometry": {"coordinates":[-118.985235,35.3666],"type":"Point"}
}