{
  "type": "Feature",
  "properties": {
    "addr:full":"170 Los Altos Ave Los Altos CA 94022",
    "addr:housenumber":"170",
    "addr:postcode":"94022",
    "addr:street":"Los Altos Ave",
    "iso:country":"US",
    "sg:address":"170 Los Altos Ave",
    "sg:city":"Los Altos",
    "sg:classifiers":[
        {
            "category":"Professional",
            "type":"Services"
        }
    ],
    "sg:phone":"+1 650 917 8597",
    "sg:postcode":"94022",
    "sg:province":"CA",
    "wof:name":"Radical Two",
    "wof:placetype":"venue"
},
  "geometry": {"coordinates":[-122.120825,37.384162],"type":"Point"}
}