{
  "type": "Feature",
  "properties": {
    "iso:country":"US",
    "sg:address":"The District at Tustin Legacy 2817 Park Ave",
    "sg:city":"Tustin",
    "sg:classifiers":[
        {
            "category":"Home & Garden",
            "subcategory":"Home Furnishings",
            "type":"Retail Goods"
        }
    ],
    "sg:phone":"+1 714 258 8452",
    "sg:postcode":"92781",
    "sg:province":"CA",
    "sg:tags":[
        "decor"
    ],
    "sg:website":"www.homegoods.com",
    "wof:name":"TJ Maxx's HomeGoods",
    "wof:placetype":"venue"
},
  "geometry": {"coordinates":[-117.82602,33.698071],"type":"Point"}
}