{
  "type": "Feature",
  "properties": {
    "addr:full":"936 Hamlin Court Sunnyvale CA 94089",
    "addr:housenumber":"936",
    "addr:postcode":"94089",
    "addr:street":"Hamlin Court",
    "iso:country":"US",
    "sg:address":"936 Hamlin Court",
    "sg:city":"Sunnyvale",
    "sg:classifiers":[
        {
            "category":"Professional",
            "subcategory":"Business Services",
            "type":"Services"
        }
    ],
    "sg:phone":"+1 408 734 4048",
    "sg:postcode":"94089",
    "sg:province":"CA",
    "wof:name":"Identity Engines",
    "wof:placetype":"venue"
},
  "geometry": {"coordinates":[-122.029802,37.400531],"type":"Point"}
}