{
  "type": "Feature",
  "properties": {
    "iso:country":"US",
    "sg:address":"14400 Bear Valley Rd",
    "sg:city":"Victorville",
    "sg:classifiers":[
        {
            "category":"Fast Food",
            "type":"Food & Drink"
        },
        {
            "category":"Restaurant",
            "type":"Food & Drink"
        },
        {
            "category":"Food & Beverages",
            "subcategory":"Groceries & Convenience Stores",
            "type":"Retail Goods"
        }
    ],
    "sg:phone":"+1 760 951 1484",
    "sg:postcode":"92392",
    "sg:province":"CA",
    "sg:tags":[
        "shop",
        "american",
        "sandwich"
    ],
    "sg:website":"http://www.arbys.com",
    "wof:name":"Arby's",
    "wof:placetype":"venue"
},
  "geometry": {"coordinates":[-117.349081,34.470409],"type":"Point"}
}