{
  "type": "Feature",
  "properties": {
    "iso:country":"US",
    "sg:address":"317 S Mayfair Ave",
    "sg:city":"Daly City",
    "sg:classifiers":[
        {
            "category":"Restaurant",
            "type":"Food & Drink"
        }
    ],
    "sg:menulink":"http://www.allmenus.com/ca/south-san-francisco/235590-una-mas/menu/",
    "sg:phone":"+1 650 755 1756",
    "sg:postcode":"94015",
    "sg:province":"CA",
    "sg:tags":[
        "mexican"
    ],
    "wof:name":"Una Mas",
    "wof:placetype":"venue"
},
  "geometry": {"coordinates":[-122.482028,37.701904],"type":"Point"}
}