{
  "type": "Feature",
  "properties": {
    "addr:full":"13343 Johnson Rd Los Banos CA 93635",
    "addr:housenumber":"13343",
    "addr:postcode":"93635",
    "addr:street":"Johnson Rd",
    "iso:country":"US",
    "sg:address":"13343 Johnson Rd",
    "sg:city":"Los Banos",
    "sg:classifiers":[
        {
            "category":"Professional",
            "subcategory":"Engineering",
            "type":"Services"
        },
        {
            "category":"Building & Trades",
            "subcategory":"Construction",
            "type":"Services"
        }
    ],
    "sg:phone":"+1 209 826 1102",
    "sg:postcode":"93635",
    "sg:province":"CA",
    "sg:tags":[
        "specializing",
        "land",
        "contractor",
        "preparation",
        "sewer",
        "general"
    ],
    "wof:name":"Mc Elvany Inc",
    "wof:placetype":"venue"
},
  "geometry": {"coordinates":[-120.865115,37.094576],"type":"Point"}
}