{
  "type": "Feature",
  "properties": {
    "iso:country":"US",
    "sg:address":"82076 San Jacinto Ave",
    "sg:city":"Indio",
    "sg:classifiers":[
        {
            "category":"Professional",
            "subcategory":"Business Services",
            "type":"Services"
        }
    ],
    "sg:phone":"+1 760 449 8110",
    "sg:postcode":"92201",
    "sg:province":"CA",
    "sg:tags":[
        "notary"
    ],
    "wof:name":"Fonseca Notary & Tax",
    "wof:placetype":"venue"
},
  "geometry": {"coordinates":[-116.233563,33.7229],"type":"Point"}
}