{
  "type": "Feature",
  "properties": {
    "addr:full":"11126 Pala Loma Dr Valley Center CA 92082",
    "addr:housenumber":"11126",
    "addr:postcode":"92082",
    "addr:street":"Pala Loma Dr",
    "iso:country":"US",
    "sg:address":"11126 Pala Loma Dr",
    "sg:city":"Valley Center",
    "sg:classifiers":[
        {
            "category":"Wholesale",
            "subcategory":"Sporting Goods",
            "type":"Manufacturing & Wholesale Goods"
        }
    ],
    "sg:phone":"+1 760 480 2377",
    "sg:postcode":"92082",
    "sg:province":"CA",
    "sg:tags":[
        "equipment",
        "golf",
        "supply"
    ],
    "sg:website":"www.theironfactory.com",
    "wof:name":"Iron Factory",
    "wof:placetype":"venue"
},
  "geometry": {"coordinates":[-117.095522,33.324453],"type":"Point"}
}