{
  "type": "Feature",
  "properties": {
    "addr:full":"11676 Olympic Blvd Los Angeles CA 90064",
    "addr:housenumber":"11676",
    "addr:postcode":"90064",
    "addr:street":"Olympic Blvd",
    "iso:country":"US",
    "sg:address":"11676 Olympic Blvd",
    "sg:city":"Los Angeles",
    "sg:classifiers":[
        {
            "category":"Restaurant",
            "type":"Food & Drink"
        }
    ],
    "sg:phone":"+1 310 477 2111",
    "sg:postcode":"90064",
    "sg:province":"CA",
    "sg:tags":[
        "pizza"
    ],
    "wof:name":"Johnnie's New York",
    "wof:placetype":"venue"
},
  "geometry": {"coordinates":[-118.447547,34.03446],"type":"Point"}
}