{
  "type": "Feature",
  "properties": {
    "addr:full":"533 N Harrison Ave Fresno CA 93728",
    "addr:housenumber":"533",
    "addr:postcode":"93728",
    "addr:street":"N Harrison Ave",
    "iso:country":"US",
    "sg:address":"533 N Harrison Ave",
    "sg:city":"Fresno",
    "sg:classifiers":[
        {
            "category":"Building & Trades",
            "subcategory":"Construction",
            "type":"Services"
        }
    ],
    "sg:phone":"+1 559 442 4918",
    "sg:postcode":"93728",
    "sg:province":"CA",
    "sg:tags":[
        "window",
        "replacement"
    ],
    "wof:name":"Amoruso Enterprises",
    "wof:placetype":"venue"
},
  "geometry": {"coordinates":[-119.810908,36.751895],"type":"Point"}
}