{
  "type": "Feature",
  "properties": {
    "addr:full":"12570 Industry St Garden Grove CA 92841",
    "addr:housenumber":"12570",
    "addr:postcode":"92841",
    "addr:street":"Industry St",
    "iso:country":"US",
    "sg:address":"12570 Industry St",
    "sg:city":"Garden Grove",
    "sg:classifiers":[
        {
            "category":"Manufacturing",
            "subcategory":"Apparel",
            "type":"Manufacturing & Wholesale Goods"
        }
    ],
    "sg:phone":"+1 714 901 4906",
    "sg:postcode":"92841",
    "sg:province":"CA",
    "sg:tags":[
        "clothing"
    ],
    "wof:name":"HOU Inc",
    "wof:placetype":"venue"
},
  "geometry": {"coordinates":[-118.007829,33.785339],"type":"Point"}
}