{
  "type": "Feature",
  "properties": {
    "iso:country":"US",
    "sg:address":"4226 University Ave",
    "sg:city":"San Diego",
    "sg:classifiers":[
        {
            "category":"Shopping",
            "subcategory":"Clothing, Apparel, & Fashions",
            "type":"Retail Goods"
        }
    ],
    "sg:phone":"+1 619 281 5767",
    "sg:postcode":"92105",
    "sg:province":"CA",
    "wof:name":"California Medical Supply Co",
    "wof:placetype":"venue"
},
  "geometry": {"coordinates":[-117.10323200000001,32.749632],"type":"Point"}
}