{
  "type": "Feature",
  "properties": {
    "addr:full":"723 Ocean Front Walk Venice CA 90291",
    "addr:housenumber":"723",
    "addr:postcode":"90291",
    "addr:street":"Ocean Front Walk",
    "iso:country":"US",
    "sg:address":"723 Ocean Front Walk",
    "sg:city":"Venice",
    "sg:classifiers":[
        {
            "category":"Building & Trades",
            "subcategory":"Landscaping Services",
            "type":"Services"
        }
    ],
    "sg:phone":"+1 310 392 2122",
    "sg:postcode":"90291",
    "sg:province":"CA",
    "sg:tags":[
        "landscape"
    ],
    "wof:name":"Galper Schau Assoc",
    "wof:placetype":"venue"
},
  "geometry": {"coordinates":[-118.477682,33.991338],"type":"Point"}
}