{
  "type": "Feature",
  "properties": {
    "addr:full":"16111 Warmington Ln Huntington Beach CA 92649",
    "addr:postcode":"16111;92649",
    "addr:street":"Warmington Ln",
    "iso:country":"US",
    "sg:address":"16111 Warmington Ln",
    "sg:city":"Huntington Beach",
    "sg:classifiers":[
        {
            "category":"Wholesale",
            "subcategory":"Machinery & Supplies",
            "type":"Manufacturing & Wholesale Goods"
        }
    ],
    "sg:phone":"+1 714 846 7008",
    "sg:postcode":"92649",
    "sg:province":"CA",
    "sg:tags":[
        "equipment",
        "industrial"
    ],
    "wof:name":"Stewart Engineered Eqp Co",
    "wof:placetype":"venue"
},
  "geometry": {"coordinates":[-118.05153900000001,33.728041],"type":"Point"}
}