{
  "type": "Feature",
  "properties": {
    "addr:full":"2158 N Pami Cir Orange CA 92867",
    "addr:housenumber":"2158",
    "addr:postcode":"92867",
    "addr:street":"N Pami Cir",
    "iso:country":"US",
    "sg:address":"2158 N Pami Cir",
    "sg:city":"Orange",
    "sg:classifiers":[
        {
            "category":"Professional",
            "subcategory":"Management & Consulting",
            "type":"Services"
        }
    ],
    "sg:phone":"+1 714 305 0500",
    "sg:postcode":"92867",
    "sg:province":"CA",
    "sg:tags":[
        "consultant",
        "business"
    ],
    "wof:name":"QVP Enterprise",
    "wof:placetype":"venue"
},
  "geometry": {"coordinates":[-117.83018,33.823993],"type":"Point"}
}