{
  "type": "Feature",
  "properties": {
    "iso:country":"US",
    "sg:address":"16575 Von Karman Ave",
    "sg:city":"Irvine",
    "sg:classifiers":[
        {
            "category":"Food & Beverages",
            "subcategory":"Bakery",
            "type":"Retail Goods"
        }
    ],
    "sg:phone":"+1 949 724 1170",
    "sg:postcode":"92606",
    "sg:province":"CA",
    "sg:tags":[
        "sandwich"
    ],
    "wof:name":"Blimpie Sub & Salads",
    "wof:placetype":"venue"
},
  "geometry": {"coordinates":[-117.834,33.6978],"type":"Point"}
}