{
  "type": "Feature",
  "properties": {
    "addr:full":"14126 Gannet St Santa Fe Springs CA 90670",
    "addr:housenumber":"14126",
    "addr:postcode":"90670",
    "addr:street":"Gannet St",
    "iso:country":"US",
    "sg:address":"14126 Gannet St",
    "sg:city":"Santa Fe Springs",
    "sg:classifiers":[
        {
            "category":"Wholesale",
            "subcategory":"Photographic Equipment",
            "type":"Manufacturing & Wholesale Goods"
        }
    ],
    "sg:phone":"+1 562 802 3575",
    "sg:postcode":"90670",
    "sg:province":"CA",
    "sg:tags":[
        "supply"
    ],
    "wof:name":"Foto Club",
    "wof:placetype":"venue"
},
  "geometry": {"coordinates":[-118.03039099999999,33.894202],"type":"Point"}
}