{
  "type": "Feature",
  "properties": {
    "addr:full":"8647 Greenleaf Ave Whittier CA 90602",
    "addr:housenumber":"8647",
    "addr:postcode":"90602",
    "addr:street":"Greenleaf Ave",
    "iso:country":"US",
    "sg:address":"8647 Greenleaf Ave",
    "sg:city":"Whittier",
    "sg:classifiers":[
        {
            "category":"Food & Beverages",
            "subcategory":"Specialty",
            "type":"Retail Goods"
        },
        {
            "category":"Food & Beverages",
            "subcategory":"Groceries & Convenience Stores",
            "type":"Retail Goods"
        }
    ],
    "sg:phone":"+1 562 907 0084",
    "sg:postcode":"90602",
    "sg:province":"CA",
    "wof:name":"Tree of Life",
    "wof:placetype":"venue"
},
  "geometry": {"coordinates":[-118.141254,33.961623],"type":"Point"}
}