{
  "type": "Feature",
  "properties": {
    "iso:country":"US",
    "sg:address":"11310 Pleasant Valley Rd",
    "sg:city":"Penn Valley",
    "sg:classifiers":[
        {
            "category":"Real Estate",
            "subcategory":"Developer",
            "type":"Services"
        }
    ],
    "sg:phone":"+1 530 432 2000",
    "sg:postcode":"95946",
    "sg:province":"CA",
    "sg:website":"www.sierragoldcountry.com",
    "wof:name":"Wildwood West Real Estate",
    "wof:placetype":"venue"
},
  "geometry": {"coordinates":[-121.209416,39.225998],"type":"Point"}
}