{
  "type": "Feature",
  "properties": {
    "addr:full":"2232 S Mountain Ave Ontario CA 91762",
    "addr:housenumber":"2232",
    "addr:postcode":"91762",
    "addr:street":"S Mountain Ave",
    "iso:country":"US",
    "sg:address":"2232 S Mountain Ave",
    "sg:city":"Ontario",
    "sg:classifiers":[
        {
            "category":"Health Services",
            "subcategory":"Doctor",
            "type":"Services"
        }
    ],
    "sg:phone":"+1 909 986 4692",
    "sg:postcode":"91762",
    "sg:province":"CA",
    "sg:tags":[
        "physician",
        "surgeon"
    ],
    "wof:name":"United Medical Group",
    "wof:placetype":"venue"
},
  "geometry": {"coordinates":[-117.669709,34.034579],"type":"Point"}
}