{
  "type": "Feature",
  "properties": {
    "iso:country":"US",
    "sg:address":"8902 Red River Ct",
    "sg:city":"Bakersfield",
    "sg:classifiers":[
        {
            "category":"Professional",
            "subcategory":"Advertising",
            "type":"Services"
        }
    ],
    "sg:phone":"+1 661 587 7214",
    "sg:postcode":"93312",
    "sg:province":"CA",
    "sg:tags":[
        "distribution"
    ],
    "wof:name":"Summers Distributing",
    "wof:placetype":"venue"
},
  "geometry": {"coordinates":[-119.101569,35.394595],"type":"Point"}
}