{
  "type": "Feature",
  "properties": {
    "addr:full":"1421 Oakdale Rd # 2 Modesto CA 95355",
    "addr:housenumber":"1421",
    "addr:postcode":"ca 95355",
    "addr:street":"Oakdale Rd # 2",
    "iso:country":"US",
    "sg:address":"1421 Oakdale Rd # 2",
    "sg:city":"Modesto",
    "sg:classifiers":[
        {
            "category":"Health Services",
            "subcategory":"Hospital",
            "type":"Services"
        }
    ],
    "sg:phone":"+1 209 572 2700",
    "sg:postcode":"95355",
    "sg:province":"CA",
    "sg:website":"www.stanislaussurgical.com",
    "wof:name":"Stanislaus Surgical Hospital",
    "wof:placetype":"venue"
},
  "geometry": {"coordinates":[-120.958,37.664799],"type":"Point"}
}