{
  "type": "Feature",
  "properties": {
    "addr:full":"12208 Ventura Blvd Studio City CA 91604",
    "addr:housenumber":"12208",
    "addr:postcode":"91604",
    "addr:street":"Ventura Blvd",
    "iso:country":"US",
    "sg:address":"12208 Ventura Blvd",
    "sg:city":"Studio City",
    "sg:classifiers":[
        {
            "category":"Shopping",
            "subcategory":"Clothing, Apparel, & Fashions",
            "type":"Retail Goods"
        }
    ],
    "sg:phone":"+1 818 760 8919",
    "sg:postcode":"91604",
    "sg:province":"CA",
    "wof:name":"Daniellis",
    "wof:placetype":"venue"
},
  "geometry": {"coordinates":[-118.39753899999999,34.143361],"type":"Point"}
}