{
  "type": "Feature",
  "properties": {
    "iso:country":"US",
    "sg:address":"4020 Campbell Ave",
    "sg:city":"Menlo Park",
    "sg:classifiers":[
        {
            "category":"Manufacturing",
            "subcategory":"Printing",
            "type":"Manufacturing & Wholesale Goods"
        }
    ],
    "sg:phone":"+1 650 328 1500",
    "sg:postcode":"94025",
    "sg:province":"CA",
    "sg:tags":[
        "printer"
    ],
    "sg:website":"www.pfp.net",
    "wof:name":"Pacific Financial Printing",
    "wof:placetype":"venue"
},
  "geometry": {"coordinates":[-122.180034,37.480492],"type":"Point"}
}