{
  "type": "Feature",
  "properties": {
    "iso:country":"US",
    "sg:address":"11847 Valley Blvd",
    "sg:city":"El Monte",
    "sg:classifiers":[
        {
            "category":"Autos & Motor Vehicles",
            "subcategory":"Auto Supplies",
            "type":"Retail Goods"
        },
        {
            "category":"Wholesale",
            "subcategory":"Scrap",
            "type":"Manufacturing & Wholesale Goods"
        }
    ],
    "sg:phone":"+1 626 443 3044",
    "sg:postcode":"91732",
    "sg:province":"CA",
    "sg:tags":[
        "automobile",
        "material",
        "used",
        "parts"
    ],
    "wof:name":"Five Points Auto Salvage",
    "wof:placetype":"venue"
},
  "geometry": {"coordinates":[-118.021587,34.064469],"type":"Point"}
}