{
  "type": "Feature",
  "properties": {
    "addr:full":"9325 San Fernando Rd Sun Valley CA 91352",
    "addr:housenumber":"9325",
    "addr:postcode":"91352",
    "addr:street":"San Fernando Rd",
    "iso:country":"US",
    "sg:address":"9325 San Fernando Rd",
    "sg:city":"Sun Valley",
    "sg:classifiers":[
        {
            "category":"Manufacturing",
            "subcategory":"Signs",
            "type":"Manufacturing & Wholesale Goods"
        }
    ],
    "sg:phone":"+1 818 767 3686",
    "sg:postcode":"91352",
    "sg:province":"CA",
    "sg:tags":[
        "specialty",
        "mfg"
    ],
    "wof:name":"Instant Neon Signs",
    "wof:placetype":"venue"
},
  "geometry": {"coordinates":[-118.393342,34.238704],"type":"Point"}
}