{
  "type": "Feature",
  "properties": {
    "addr:full":"1103 W Perkins St Ukiah CA 95482",
    "addr:housenumber":"1103",
    "addr:postcode":"ca 95482",
    "addr:street":"W Perkins St",
    "iso:country":"US",
    "sg:address":"1103 W Perkins St",
    "sg:city":"Ukiah",
    "sg:classifiers":[
        {
            "category":"Professional",
            "subcategory":"Management & Consulting",
            "type":"Services"
        }
    ],
    "sg:phone":"+1 707 468 1655",
    "sg:postcode":"95482",
    "sg:province":"CA",
    "sg:tags":[
        "consultant",
        "business"
    ],
    "wof:name":"Kiichli & Assoc",
    "wof:placetype":"venue"
},
  "geometry": {"coordinates":[-123.217758,39.148293],"type":"Point"}
}