{
  "type": "Feature",
  "properties": {
    "iso:country":"US",
    "sg:address":"5831 San Leandro St",
    "sg:city":"Oakland",
    "sg:classifiers":[
        {
            "category":"Wholesale",
            "subcategory":"Stationery",
            "type":"Manufacturing & Wholesale Goods"
        }
    ],
    "sg:phone":"+1 510 434 0900",
    "sg:postcode":"94621",
    "sg:province":"CA",
    "sg:tags":[
        "product",
        "paper"
    ],
    "wof:name":"Badger Forest Products",
    "wof:placetype":"venue"
},
  "geometry": {"coordinates":[-122.208742,37.763503],"type":"Point"}
}