{
  "type": "Feature",
  "properties": {
    "addr:full":"1226 Commerce Center Dr Lancaster CA 93534",
    "addr:housenumber":"1226",
    "addr:postcode":"93534",
    "addr:street":"Commerce Center Dr",
    "iso:country":"US",
    "sg:address":"1226 Commerce Center Dr",
    "sg:city":"Lancaster",
    "sg:classifiers":[
        {
            "category":"Shopping",
            "subcategory":"Department Store",
            "type":"Retail Goods"
        }
    ],
    "sg:phone":"+1 661 726 4667",
    "sg:postcode":"93534",
    "sg:province":"CA",
    "wof:name":"Factory 2-U",
    "wof:placetype":"venue"
},
  "geometry": {"coordinates":[-118.152614,34.672185],"type":"Point"}
}