{
  "type": "Feature",
  "properties": {
    "addr:full":"855 Mc Kendrie St San Jose CA 95126",
    "addr:housenumber":"855",
    "addr:postcode":"95126",
    "addr:street":"Mc Kendrie St",
    "iso:country":"US",
    "sg:address":"855 Mc Kendrie St",
    "sg:city":"San Jose",
    "sg:classifiers":[
        {
            "category":"Shopping",
            "subcategory":"Clothing, Apparel, & Fashions",
            "type":"Retail Goods"
        }
    ],
    "sg:phone":"+1 408 243 9824",
    "sg:postcode":"95126",
    "sg:province":"CA",
    "sg:tags":[
        "uniform",
        "supply"
    ],
    "wof:name":"Aramark Uniform Svc",
    "wof:placetype":"venue"
},
  "geometry": {"coordinates":[-121.920654,37.344316],"type":"Point"}
}