{
  "type": "Feature",
  "properties": {
    "addr:full":"10300 N Blaney Avenue Cupertino CA 95014",
    "addr:housenumber":"10300",
    "addr:postcode":"95014",
    "addr:street":"N Blaney Avenue",
    "iso:country":"US",
    "sg:address":"10300 N Blaney Avenue",
    "sg:city":"Cupertino",
    "sg:classifiers":[
        {
            "category":"Social Services",
            "subcategory":"Child Care",
            "type":"Services"
        }
    ],
    "sg:phone":"+1 408 996 1547",
    "sg:postcode":"95014",
    "sg:province":"CA",
    "sg:tags":[
        "day"
    ],
    "wof:name":"Child Development Centers",
    "wof:placetype":"venue"
},
  "geometry": {"coordinates":[-122.023053,37.326976],"type":"Point"}
}