{
  "type": "Feature",
  "properties": {
    "addr:full":"611 N Palm St La Habra CA 90631",
    "addr:housenumber":"611",
    "addr:postcode":"90631",
    "addr:street":"N Palm St",
    "iso:country":"US",
    "sg:address":"611 N Palm St",
    "sg:city":"La Habra",
    "sg:classifiers":[
        {
            "category":"Professional",
            "type":"Services"
        }
    ],
    "sg:phone":"+1 562 691 0802",
    "sg:postcode":"90631",
    "sg:province":"CA",
    "sg:tags":[
        "establishment"
    ],
    "wof:name":"Interior Exterior Designs",
    "wof:placetype":"venue"
},
  "geometry": {"coordinates":[-117.924412,33.937172],"type":"Point"}
}