{
  "type": "Feature",
  "properties": {
    "addr:full":"509 Emory St San Jose CA 95110",
    "addr:housenumber":"509",
    "addr:postcode":"95110",
    "addr:street":"Emory St",
    "iso:country":"US",
    "sg:address":"509 Emory St",
    "sg:city":"San Jose",
    "sg:classifiers":[
        {
            "category":"Organizations",
            "subcategory":"Labor Organization",
            "type":"Services"
        }
    ],
    "sg:phone":"+1 408 297 2620",
    "sg:postcode":"95110",
    "sg:province":"CA",
    "sg:website":"www.local270.com",
    "wof:name":"Laborers Union",
    "wof:placetype":"venue"
},
  "geometry": {"coordinates":[-121.91417199999999,37.34353],"type":"Point"}
}