{
  "type": "Feature",
  "properties": {
    "addr:full":"8215 Waters Rd Moorpark CA 93021",
    "addr:housenumber":"8215",
    "addr:postcode":"ca 93021",
    "addr:street":"Waters Rd",
    "iso:country":"US",
    "sg:address":"8215 Waters Rd",
    "sg:city":"Moorpark",
    "sg:classifiers":[
        {
            "category":"Professional",
            "subcategory":"Testing Lab",
            "type":"Services"
        }
    ],
    "sg:phone":"+1 805 529 1125",
    "sg:postcode":"93021",
    "sg:province":"CA",
    "sg:tags":[
        "correction",
        "radon"
    ],
    "wof:name":"Radon Testing Svc",
    "wof:placetype":"venue"
},
  "geometry": {"coordinates":[-118.946392,34.323097],"type":"Point"}
}