{
  "type": "Feature",
  "properties": {
    "addr:full":"6617 Cherry Ave Long Beach CA 90805",
    "addr:housenumber":"6617",
    "addr:postcode":"90805",
    "addr:street":"Cherry Ave",
    "iso:country":"US",
    "sg:address":"6617 Cherry Ave",
    "sg:city":"Long Beach",
    "sg:classifiers":[
        {
            "category":"Restaurant",
            "type":"Food & Drink"
        }
    ],
    "sg:phone":"+1 562 422 3606",
    "sg:postcode":"90805",
    "sg:province":"CA",
    "wof:name":"L B J's Fine Foods",
    "wof:placetype":"venue"
},
  "geometry": {"coordinates":[-118.16876499999999,33.875359],"type":"Point"}
}