{
  "type": "Feature",
  "properties": {
    "iso:country":"US",
    "sg:address":"6617 Cherry Ave",
    "sg:city":"Long Beach",
    "sg:classifiers":[
        {
            "category":"Restaurant",
            "type":"Food & Drink"
        }
    ],
    "sg:phone":"+1 562 422 3606",
    "sg:postcode":"90805",
    "sg:province":"CA",
    "wof:name":"L B J's Fine Foods",
    "wof:placetype":"venue"
},
  "geometry": {"coordinates":[-118.168765,33.875359],"type":"Point"}
}