{
  "type": "Feature",
  "properties": {
    "iso:country":"US",
    "sg:address":"2216 W Capitol Ave",
    "sg:city":"West Sacramento",
    "sg:classifiers":[
        {
            "category":"Restaurant",
            "type":"Food & Drink"
        }
    ],
    "sg:postcode":"95691",
    "sg:province":"CA",
    "wof:name":"Rosies Country Kitchen",
    "wof:placetype":"venue"
},
  "geometry": {"coordinates":[-121.53882299999999,38.580226],"type":"Point"}
}