{
  "type": "Feature",
  "properties": {
    "iso:country":"US",
    "sg:address":"3984 N Parkway Dr",
    "sg:city":"Fresno",
    "sg:classifiers":[
        {
            "category":"Home & Garden",
            "subcategory":"Building Materials",
            "type":"Retail Goods"
        }
    ],
    "sg:phone":"+1 559 271 9496",
    "sg:postcode":"93722",
    "sg:province":"CA",
    "sg:tags":[
        "door"
    ],
    "wof:name":"Kings River Door",
    "wof:placetype":"venue"
},
  "geometry": {"coordinates":[-119.862467,36.791322],"type":"Point"}
}