{
  "type": "Feature",
  "properties": {
    "iso:country":"US",
    "sg:address":"1908 E 38th St",
    "sg:city":"Oakland",
    "sg:classifiers":[
        {
            "category":"Professional",
            "subcategory":"Computer Services",
            "type":"Services"
        }
    ],
    "sg:phone":"+1 510 484 4288",
    "sg:postcode":"94602",
    "sg:province":"CA",
    "sg:tags":[
        "designer",
        "technical",
        "consultant",
        "assistance",
        "system",
        "support"
    ],
    "wof:name":"San Francisco Bay Area Tech",
    "wof:placetype":"venue"
},
  "geometry": {"coordinates":[-122.219083,37.801488],"type":"Point"}
}