{
  "type": "Feature",
  "properties": {
    "iso:country":"US",
    "sg:address":"4068 S Victoria Ave",
    "sg:city":"Los Angeles",
    "sg:classifiers":[
        {
            "category":"Shopping",
            "subcategory":"Clothing, Apparel, & Fashions",
            "type":"Retail Goods"
        }
    ],
    "sg:phone":"+1 323 296 5333",
    "sg:postcode":"90008",
    "sg:province":"CA",
    "sg:tags":[
        "miscellaneous",
        "store",
        "accessory"
    ],
    "wof:name":"Imperial Wigs",
    "wof:placetype":"venue"
},
  "geometry": {"coordinates":[-118.33837800000001,34.012974],"type":"Point"}
}