{
  "type": "Feature",
  "properties": {
    "addr:full":"1108 de la Vina St Santa Barbara CA 93101",
    "addr:housenumber":"1108",
    "addr:postcode":"93101",
    "addr:street":"De La Vina St",
    "iso:country":"US",
    "sg:address":"1108 de la Vina St",
    "sg:city":"Santa Barbara",
    "sg:classifiers":[
        {
            "category":"Real Estate",
            "subcategory":"Real Estate Agent",
            "type":"Services"
        }
    ],
    "sg:phone":"+1 805 963 8283",
    "sg:postcode":"93101",
    "sg:province":"CA",
    "sg:tags":[
        "consultant"
    ],
    "wof:name":"Frank Thompson Housing Conslnt",
    "wof:placetype":"venue"
},
  "geometry": {"coordinates":[-119.706588,34.421204],"type":"Point"}
}