{
  "type": "Feature",
  "properties": {
    "iso:country":"US",
    "sg:address":"341 E Main St",
    "sg:city":"Turlock",
    "sg:classifiers":[
        {
            "category":"Shopping",
            "type":"Retail Goods"
        }
    ],
    "sg:phone":"+1 209 669 0529",
    "sg:postcode":"95380",
    "sg:province":"CA",
    "sg:tags":[
        "plant",
        "flower",
        "tree",
        "artificial"
    ],
    "wof:name":"Silk Garden",
    "wof:placetype":"venue"
},
  "geometry": {"coordinates":[-120.84484999999999,37.4956],"type":"Point"}
}