{
  "type": "Feature",
  "properties": {
    "iso:country":"US",
    "sg:address":"280 28th St",
    "sg:city":"Oakland",
    "sg:classifiers":[
        {
            "category":"Social Services",
            "subcategory":"Adult Care",
            "type":"Services"
        }
    ],
    "sg:phone":"+1 510 835 2369",
    "sg:postcode":"94611",
    "sg:province":"CA",
    "sg:tags":[
        "organization",
        "senior",
        "citizen"
    ],
    "wof:name":"SSHI Maintenance",
    "wof:placetype":"venue"
},
  "geometry": {"coordinates":[-122.263637,37.816352],"type":"Point"}
}