{
  "type": "Feature",
  "properties": {
    "addr:full":"510 Rigsby St La Habra CA 90631",
    "addr:housenumber":"510",
    "addr:postcode":"90631",
    "addr:street":"Rigsby St",
    "iso:country":"US",
    "sg:address":"510 Rigsby St",
    "sg:city":"La Habra",
    "sg:classifiers":[
        {
            "category":"Building & Trades",
            "subcategory":"Construction",
            "type":"Services"
        }
    ],
    "sg:phone":"+1 562 694 2163",
    "sg:postcode":"90631",
    "sg:province":"CA",
    "sg:tags":[
        "painter"
    ],
    "wof:name":"Heard Quality Painting",
    "wof:placetype":"venue"
},
  "geometry": {"coordinates":[-117.97319400000001,33.93605],"type":"Point"}
}