{
  "type": "Feature",
  "properties": {
    "addr:full":"1327 Oxford Ave Santa Maria CA 93454",
    "addr:housenumber":"1327",
    "addr:postcode":"93454",
    "addr:street":"Oxford Ave",
    "iso:country":"US",
    "sg:address":"1327 Oxford Ave",
    "sg:city":"Santa Maria",
    "sg:classifiers":[
        {
            "category":"Building & Trades",
            "subcategory":"Construction",
            "type":"Services"
        }
    ],
    "sg:phone":"+1 805 349 0032",
    "sg:postcode":"93454",
    "sg:province":"CA",
    "sg:tags":[
        "dry wall",
        "contractor"
    ],
    "wof:name":"Shafer Drywall",
    "wof:placetype":"venue"
},
  "geometry": {"coordinates":[-120.41731900000001,34.965323],"type":"Point"}
}