{
  "type": "Feature",
  "properties": {
    "addr:full":"7021 Jordan Ave Ste 3 Canoga Park CA 91303",
    "addr:housenumber":"7021",
    "addr:postcode":"91303",
    "addr:street":"Jordan Ave Ste 3",
    "iso:country":"US",
    "sg:address":"7021 Jordan Ave Ste 3",
    "sg:city":"Canoga Park",
    "sg:classifiers":[
        {
            "category":"Building & Trades",
            "subcategory":"Cleaning & Sanitation",
            "type":"Services"
        }
    ],
    "sg:phone":"+1 818 288 2411",
    "sg:postcode":"91303",
    "sg:province":"CA",
    "sg:tags":[
        "cleaner",
        "pool"
    ],
    "sg:website":"www.laislandpoolcare.com",
    "wof:name":"LA Island Pool Care",
    "wof:placetype":"venue"
},
  "geometry": {"coordinates":[-118.603257,34.198014],"type":"Point"}
}