{
  "type": "Feature",
  "properties": {
    "iso:country":"US",
    "sg:address":"3279 Trade Center Dr",
    "sg:city":"Riverside",
    "sg:classifiers":[
        {
            "category":"Building & Trades",
            "subcategory":"Cleaning & Sanitation",
            "type":"Services"
        }
    ],
    "sg:phone":"+1 951 782 8404",
    "sg:postcode":"92507",
    "sg:province":"CA",
    "sg:tags":[
        "janitor"
    ],
    "wof:name":"Wurm's Janitorial Svc",
    "wof:placetype":"venue"
},
  "geometry": {"coordinates":[-117.346138,33.983226],"type":"Point"}
}