{
  "type": "Feature",
  "properties": {
    "addr:full":"1021 30th St San Diego CA 92102",
    "addr:housenumber":"1021",
    "addr:postcode":"92102",
    "addr:street":"30Th St",
    "iso:country":"US",
    "sg:address":"1021 30th St",
    "sg:city":"San Diego",
    "sg:classifiers":[
        {
            "category":"Social Services",
            "subcategory":"Child Care",
            "type":"Services"
        }
    ],
    "sg:phone":"+1 619 544 0125",
    "sg:postcode":"92102",
    "sg:province":"CA",
    "wof:name":"Lacy's Baby Boop Child Care",
    "wof:placetype":"venue"
},
  "geometry": {"coordinates":[-117.129509,32.716162],"type":"Point"}
}