{
  "type": "Feature",
  "properties": {
    "iso:country":"US",
    "sg:address":"7620 Tampa Ave",
    "sg:city":"Reseda",
    "sg:classifiers":[
        {
            "category":"Home & Garden",
            "subcategory":"Home Furnishings",
            "type":"Retail Goods"
        }
    ],
    "sg:phone":"+1 818 344 2678",
    "sg:postcode":"91335",
    "sg:province":"CA",
    "sg:tags":[
        "quilt"
    ],
    "wof:name":"Patches",
    "wof:placetype":"venue"
},
  "geometry": {"coordinates":[-118.553458,34.209811],"type":"Point"}
}