{
  "type": "Feature",
  "properties": {
    "iso:country":"US",
    "sg:address":"3999 San Pablo Ave # H",
    "sg:city":"Emeryville",
    "sg:classifiers":[
        {
            "category":"Home & Garden",
            "subcategory":"Home Furnishings",
            "type":"Retail Goods"
        },
        {
            "category":"Home & Garden",
            "subcategory":"Carpets & Floor Coverings",
            "type":"Retail Goods"
        }
    ],
    "sg:phone":"+1 510 547 0258",
    "sg:postcode":"94608",
    "sg:province":"CA",
    "sg:tags":[
        "bedroom",
        "bedding",
        "set",
        "bed",
        "mattress"
    ],
    "sg:website":"http://www.mattressdiscounters.com",
    "wof:name":"Mattress Discounters",
    "wof:placetype":"venue"
},
  "geometry": {"coordinates":[-122.279999,37.830601],"type":"Point"}
}