{
  "type": "Feature",
  "properties": {
    "addr:full":"222 Juanita Way San Francisco CA 94127",
    "addr:housenumber":"222",
    "addr:postcode":"94127",
    "addr:street":"Juanita Way",
    "iso:country":"US",
    "sg:address":"222 Juanita Way",
    "sg:city":"San Francisco",
    "sg:classifiers":[
        {
            "category":"Food & Beverages",
            "subcategory":"Specialty",
            "type":"Retail Goods"
        }
    ],
    "sg:phone":"+1 415 564 3266",
    "sg:postcode":"94127",
    "sg:province":"CA",
    "sg:tags":[
        "merchandise"
    ],
    "wof:name":"Shaklee Distributor",
    "wof:placetype":"venue"
},
  "geometry": {"coordinates":[-122.456957,37.740531],"type":"Point"}
}