{
  "type": "Feature",
  "properties": {
    "iso:country":"US",
    "sg:address":"5659 Bay Street",
    "sg:city":"Emeryville",
    "sg:classifiers":[
        {
            "category":"Shopping",
            "subcategory":"Clothing, Apparel, & Fashions",
            "type":"Retail Goods"
        }
    ],
    "sg:phone":"+1 510 652 2247",
    "sg:postcode":"94608",
    "sg:province":"CA",
    "sg:tags":[
        "accessory",
        "clothing",
        "women's"
    ],
    "sg:website":"www.habitbaystreet.com",
    "wof:name":"Habit",
    "wof:placetype":"venue"
},
  "geometry": {"coordinates":[-122.292388,37.836376],"type":"Point"}
}