{
  "type": "Feature",
  "properties": {
    "addr:full":"40 San Jose Ave San Jose CA 95125",
    "addr:housenumber":"40",
    "addr:postcode":"95125",
    "addr:street":"San Jose Ave",
    "iso:country":"US",
    "sg:address":"40 San Jose Ave",
    "sg:city":"San Jose",
    "sg:classifiers":[
        {
            "category":"Retail",
            "subcategory":"Auto Repair",
            "type":"Services"
        }
    ],
    "sg:phone":"+1 408 288 5039",
    "sg:postcode":"95125",
    "sg:province":"CA",
    "wof:name":"Ator Auto Repair",
    "wof:placetype":"venue"
},
  "geometry": {"coordinates":[-121.870876,37.311904],"type":"Point"}
}