{
  "type": "Feature",
  "properties": {
    "iso:country":"US",
    "sg:address":"950 N Tustin Ave",
    "sg:city":"Anaheim",
    "sg:classifiers":[
        {
            "category":"Professional",
            "subcategory":"Employment Agencies",
            "type":"Services"
        }
    ],
    "sg:phone":"+1 714 238 9292",
    "sg:postcode":"92807",
    "sg:province":"CA",
    "wof:name":"Direct Link Inc.",
    "wof:placetype":"venue"
},
  "geometry": {"coordinates":[-117.83773100000001,33.849989],"type":"Point"}
}