{
  "type": "Feature",
  "properties": {
    "iso:country":"US",
    "sg:address":"656 Taylor Ave",
    "sg:city":"Sunnyvale",
    "sg:classifiers":[
        {
            "category":"Professional",
            "subcategory":"Management & Consulting",
            "type":"Services"
        }
    ],
    "sg:phone":"+1 408 374 4935",
    "sg:postcode":"94085",
    "sg:province":"CA",
    "sg:tags":[
        "product",
        "for",
        "support",
        "compliance",
        "general",
        "permit"
    ],
    "wof:name":"California Compliant com",
    "wof:placetype":"venue"
},
  "geometry": {"coordinates":[-122.016285,37.38307],"type":"Point"}
}