{
  "type": "Feature",
  "properties": {
    "addr:full":"4841 Paoli Loop Rd American Canyon CA 94503",
    "addr:housenumber":"4841",
    "addr:postcode":"94503",
    "addr:street":"Paoli Loop Rd American",
    "iso:country":"US",
    "sg:address":"4841 Paoli Loop Rd",
    "sg:city":"American Canyon",
    "sg:classifiers":[
        {
            "category":"Manufacturing",
            "subcategory":"Metals",
            "type":"Manufacturing & Wholesale Goods"
        }
    ],
    "sg:phone":"+1 707 557 4525",
    "sg:postcode":"94503",
    "sg:province":"CA",
    "sg:tags":[
        "foundry"
    ],
    "wof:name":"D & L Foundry & Supply",
    "wof:placetype":"venue"
},
  "geometry": {"coordinates":[-122.25628399999999,38.19239],"type":"Point"}
}