{
  "type": "Feature",
  "properties": {
    "iso:country":"US",
    "sg:address":"19431 Rue de Valore",
    "sg:city":"El Toro",
    "sg:classifiers":[
        {
            "category":"Professional",
            "type":"Services"
        }
    ],
    "sg:phone":"+1 949 597 0321",
    "sg:postcode":"92610",
    "sg:province":"CA",
    "wof:name":"CT Howard Inc",
    "wof:placetype":"venue"
},
  "geometry": {"coordinates":[-117.652911,33.680036],"type":"Point"}
}