{
  "type": "Feature",
  "properties": {
    "addr:full":"3200 Douglas Blvd Roseville CA 95678",
    "addr:housenumber":"3200",
    "addr:postcode":"95678",
    "addr:street":"Douglas Blvd",
    "iso:country":"US",
    "sg:address":"3200 Douglas Blvd",
    "sg:city":"Roseville",
    "sg:classifiers":[
        {
            "category":"Banks & Credit Unions",
            "subcategory":"Bank",
            "type":"Services"
        }
    ],
    "sg:phone":"+1 916 781 4550",
    "sg:postcode":"95678",
    "sg:province":"CA",
    "sg:tags":[
        "loan",
        "real estate"
    ],
    "wof:name":"Bank Of America",
    "wof:placetype":"venue"
},
  "geometry": {"coordinates":[-121.24038899999999,38.744223],"type":"Point"}
}