{
  "type": "Feature",
  "properties": {
    "iso:country":"US",
    "sg:address":"27916 Seco Canyon Rd",
    "sg:city":"Santa Clarita",
    "sg:classifiers":[
        {
            "category":"Personal",
            "subcategory":"Nail Salon",
            "type":"Services"
        }
    ],
    "sg:phone":"+1 661 263 6814",
    "sg:postcode":"91350",
    "sg:province":"CA",
    "wof:name":"Ocean Nail Spa",
    "wof:placetype":"venue"
},
  "geometry": {"coordinates":[-118.533997,34.458099],"type":"Point"}
}