{
  "type": "Feature",
  "properties": {
    "iso:country":"US",
    "sg:address":"920 E Truxtun Ave",
    "sg:city":"Bakersfield",
    "sg:classifiers":[
        {
            "category":"Manufacturing",
            "subcategory":"Lumber",
            "type":"Manufacturing & Wholesale Goods"
        }
    ],
    "sg:phone":"+1 661 859 2600",
    "sg:postcode":"93305",
    "sg:province":"CA",
    "wof:name":"Stock Market",
    "wof:placetype":"venue"
},
  "geometry": {"coordinates":[-118.98943,35.373315],"type":"Point"}
}