{
  "type": "Feature",
  "properties": {
    "addr:full":"690 Noble St Madera CA 93637",
    "addr:housenumber":"690",
    "addr:postcode":"93637",
    "addr:street":"Noble St",
    "iso:country":"US",
    "sg:address":"690 Noble St",
    "sg:city":"Madera",
    "sg:classifiers":[
        {
            "category":"Professional",
            "subcategory":"Business Services",
            "type":"Services"
        }
    ],
    "sg:phone":"+1 559 662 8612",
    "sg:postcode":"93637",
    "sg:province":"CA",
    "wof:name":"Creative Asphalt Solutions",
    "wof:placetype":"venue"
},
  "geometry": {"coordinates":[-120.070892,36.949744],"type":"Point"}
}