{
  "type": "Feature",
  "properties": {
    "iso:country":"US",
    "sg:address":"861 W 18th St",
    "sg:city":"Costa Mesa",
    "sg:classifiers":[
        {
            "category":"Home & Garden",
            "subcategory":"Home Furnishings",
            "type":"Retail Goods"
        }
    ],
    "sg:phone":"+1 949 673 4508",
    "sg:postcode":"92627",
    "sg:province":"CA",
    "sg:tags":[
        "fireplace"
    ],
    "wof:name":"Newport Mantel & Panel Co",
    "wof:placetype":"venue"
},
  "geometry": {"coordinates":[-117.93391699999999,33.639652],"type":"Point"}
}