{
  "type": "Feature",
  "properties": {
    "addr:full":"223 Plz Serena Ontario CA 91764",
    "addr:housenumber":"223",
    "addr:postcode":"91764",
    "addr:street":"Plz Serena",
    "iso:country":"US",
    "sg:address":"223 Plz Serena",
    "sg:city":"Ontario",
    "sg:classifiers":[
        {
            "category":"Wholesale",
            "subcategory":"Painting Supplies",
            "type":"Manufacturing & Wholesale Goods"
        }
    ],
    "sg:phone":"+1 909 988 4080",
    "sg:postcode":"91764",
    "sg:province":"CA",
    "sg:tags":[
        "equipment",
        "painter"
    ],
    "wof:name":"Painters Direct Supply/Rental",
    "wof:placetype":"venue"
},
  "geometry": {"coordinates":[-117.647531,34.07529],"type":"Point"}
}