{
  "type": "Feature",
  "properties": {
    "iso:country":"US",
    "sg:address":"240 Winston St",
    "sg:city":"Los Angeles",
    "sg:classifiers":[
        {
            "category":"Wholesale",
            "subcategory":"Stationery",
            "type":"Manufacturing & Wholesale Goods"
        }
    ],
    "sg:phone":"+1 213 489 0924",
    "sg:postcode":"90013",
    "sg:province":"CA",
    "sg:tags":[
        "supply"
    ],
    "wof:name":"Eve World",
    "wof:placetype":"venue"
},
  "geometry": {"coordinates":[-118.246088,34.045792],"type":"Point"}
}