{
  "type": "Feature",
  "properties": {
    "addr:full":"3757 Bancroft Dr Spring Valley CA 91977",
    "addr:housenumber":"3757",
    "addr:postcode":"91977",
    "addr:street":"Bancroft Dr",
    "iso:country":"US",
    "sg:address":"3757 Bancroft Dr",
    "sg:city":"Spring Valley",
    "sg:classifiers":[
        {
            "category":"Freight",
            "type":"Transportation"
        }
    ],
    "sg:phone":"+1 619 462 7772",
    "sg:postcode":"91977",
    "sg:province":"CA",
    "sg:tags":[
        "trucking"
    ],
    "wof:name":"Kelly & Assoc Inc",
    "wof:placetype":"venue"
},
  "geometry": {"coordinates":[-117.00296899999999,32.746836],"type":"Point"}
}