{
  "type": "Feature",
  "properties": {
    "iso:country":"US",
    "sg:address":"379 Kidder St",
    "sg:city":"Soledad",
    "sg:classifiers":[
        {
            "category":"Building & Trades",
            "subcategory":"Construction",
            "type":"Services"
        }
    ],
    "sg:phone":"+1 831 678 9000",
    "sg:postcode":"93960",
    "sg:province":"CA",
    "sg:tags":[
        "painter"
    ],
    "wof:name":"Joe Rodriguez Painting",
    "wof:placetype":"venue"
},
  "geometry": {"coordinates":[-121.324837,36.427901],"type":"Point"}
}