{
  "type": "Feature",
  "properties": {
    "iso:country":"US",
    "sg:address":"13850 Francisquito Ave",
    "sg:city":"Baldwin Park",
    "sg:classifiers":[
        {
            "category":"Restaurant",
            "type":"Food & Drink"
        }
    ],
    "sg:menulink":"http://www.allmenus.com/ca/east-san-gabriel-valley/224373-in--out-burger/menu/",
    "sg:postcode":"91706",
    "sg:province":"CA",
    "sg:tags":[
        "burger",
        "american"
    ],
    "wof:name":"In & Out Burger",
    "wof:placetype":"venue"
},
  "geometry": {"coordinates":[-117.973647,34.068261],"type":"Point"}
}