{
  "type": "Feature",
  "properties": {
    "addr:full":"15649 Ridge Estates Rd Nevada City CA 95959",
    "addr:housenumber":"15649",
    "addr:postcode":"95959",
    "addr:street":"Ridge Estates Rd",
    "iso:country":"US",
    "sg:address":"15649 Ridge Estates Rd",
    "sg:city":"Nevada City",
    "sg:classifiers":[
        {
            "category":"Social Services",
            "subcategory":"Child Care",
            "type":"Services"
        }
    ],
    "sg:phone":"+1 530 265 6520",
    "sg:postcode":"95959",
    "sg:province":"CA",
    "wof:name":"Kare Crisis Nursery Inc",
    "wof:placetype":"venue"
},
  "geometry": {"coordinates":[-121.04428,39.24329],"type":"Point"}
}