{
  "type": "Feature",
  "properties": {
    "addr:full":"18548 Parthenia St Northridge CA 91324",
    "addr:housenumber":"18548",
    "addr:postcode":"91324",
    "addr:street":"Parthenia St",
    "iso:country":"US",
    "sg:address":"18548 Parthenia St",
    "sg:city":"Northridge",
    "sg:classifiers":[
        {
            "category":"Retail",
            "subcategory":"Auto Repair",
            "type":"Services"
        }
    ],
    "sg:phone":"+1 818 775 1075",
    "sg:postcode":"91324",
    "sg:province":"CA",
    "sg:tags":[
        "repairing",
        "automobile"
    ],
    "wof:name":"H 2 Auto Repair",
    "wof:placetype":"venue"
},
  "geometry": {"coordinates":[-118.537385,34.22816],"type":"Point"}
}