{
  "type": "Feature",
  "properties": {
    "iso:country":"US",
    "sg:address":"7635 Tangelo Ave",
    "sg:city":"Fontana",
    "sg:classifiers":[
        {
            "category":"Real Estate",
            "subcategory":"Real Estate Agent",
            "type":"Services"
        }
    ],
    "sg:phone":"+1 909 322 3140",
    "sg:postcode":"92336",
    "sg:province":"CA",
    "sg:tags":[
        "management"
    ],
    "wof:name":"Preferred Property Management",
    "wof:placetype":"venue"
},
  "geometry": {"coordinates":[-117.42109000000001,34.11412],"type":"Point"}
}