{
  "type": "Feature",
  "properties": {
    "addr:full":"1375 Ruby Ct Capitola CA 95010",
    "addr:housenumber":"1375",
    "addr:postcode":"95010",
    "addr:street":"Ruby Ct",
    "iso:country":"US",
    "sg:address":"1375 Ruby Ct",
    "sg:city":"Capitola",
    "sg:classifiers":[
        {
            "category":"Professional",
            "type":"Services"
        }
    ],
    "sg:phone":"+1 831 464 8748",
    "sg:postcode":"95010",
    "sg:province":"CA",
    "wof:name":"Enrique A Melendez",
    "wof:placetype":"venue"
},
  "geometry": {"coordinates":[-121.963176,36.970989],"type":"Point"}
}