{
  "type": "Feature",
  "properties": {
    "addr:full":"3831 Hughes Ave Ste 504 Culver City CA 90232",
    "addr:housenumber":"3831",
    "addr:postcode":"90232",
    "addr:street":"Hughes Ave Ste 504",
    "iso:country":"US",
    "sg:address":"3831 Hughes Ave Ste 504",
    "sg:city":"Culver City",
    "sg:classifiers":[
        {
            "category":"Health Services",
            "subcategory":"Doctor",
            "type":"Services"
        },
        {
            "category":"Personal",
            "subcategory":"Hair Removal",
            "type":"Services"
        }
    ],
    "sg:phone":"+1 310 204 3376",
    "sg:postcode":"90232",
    "sg:province":"CA",
    "sg:tags":[
        "dermatologist"
    ],
    "wof:name":"Beach Cities Dermatology Medical Center of W L A",
    "wof:placetype":"venue"
},
  "geometry": {"coordinates":[-118.398003,34.0228],"type":"Point"}
}