{
  "type": "Feature",
  "properties": {
    "addr:full":"4514 Cochran St Simi Valley CA 93063",
    "addr:housenumber":"4514",
    "addr:postcode":"93063",
    "addr:street":"Cochran St",
    "iso:country":"US",
    "sg:address":"4514 Cochran St",
    "sg:city":"Simi Valley",
    "sg:classifiers":[
        {
            "category":"Wholesale",
            "subcategory":"Jewelry",
            "type":"Manufacturing & Wholesale Goods"
        }
    ],
    "sg:phone":"+1 805 526 0331",
    "sg:postcode":"93063",
    "sg:province":"CA",
    "sg:tags":[
        "jeweler",
        "supply"
    ],
    "wof:name":"Marketing Plus",
    "wof:placetype":"venue"
},
  "geometry": {"coordinates":[-118.703622,34.278913],"type":"Point"}
}