{
  "type": "Feature",
  "properties": {
    "addr:full":"21191 Burndale Rd Sonoma CA 95476",
    "addr:housenumber":"21191",
    "addr:postcode":"95476",
    "addr:street":"Burndale Rd",
    "iso:country":"US",
    "sg:address":"21191 Burndale Rd",
    "sg:city":"Sonoma",
    "sg:classifiers":[
        {
            "category":"Building & Trades",
            "subcategory":"Electrical",
            "type":"Services"
        }
    ],
    "sg:phone":"+1 707 939 7811",
    "sg:postcode":"95476",
    "sg:province":"CA",
    "sg:tags":[
        "electric",
        "contractor"
    ],
    "wof:name":"Kroner Electrical Svc Inc",
    "wof:placetype":"venue"
},
  "geometry": {"coordinates":[-122.422438,38.266058],"type":"Point"}
}