{
  "type": "Feature",
  "properties": {
    "addr:full":"951 S Figueroa St Los Angeles CA 90015",
    "addr:housenumber":"951",
    "addr:postcode":"90015",
    "addr:street":"S Figueroa St",
    "iso:country":"US",
    "sg:address":"951 S Figueroa St",
    "sg:city":"Los Angeles",
    "sg:classifiers":[
        {
            "category":"Recreation",
            "type":"Entertainment"
        }
    ],
    "sg:phone":"+1 800 328 4253",
    "sg:postcode":"90015",
    "sg:province":"CA",
    "sg:tags":[
        "ticket",
        "art"
    ],
    "sg:website":"www.viptickets.com",
    "wof:name":"VIP Tickets",
    "wof:placetype":"venue"
},
  "geometry": {"coordinates":[-118.263705,34.045224],"type":"Point"}
}