{
  "type": "Feature",
  "properties": {
    "addr:full":"2005 Evergreen St # 1500 Sacramento CA 95815",
    "addr:housenumber":"2005",
    "addr:postcode":"95815",
    "addr:street":"Evergreen St # 1500",
    "iso:country":"US",
    "sg:address":"2005 Evergreen St # 1500",
    "sg:city":"Sacramento",
    "sg:classifiers":[
        {
            "category":"Building & Trades",
            "subcategory":"Pest Control",
            "type":"Services"
        }
    ],
    "sg:phone":"+1 916 561 8700",
    "sg:postcode":"95815",
    "sg:province":"CA",
    "wof:name":"Ca Structural Pest Control Brd.",
    "wof:placetype":"venue"
},
  "geometry": {"coordinates":[-121.448932,38.605044],"type":"Point"}
}