{
  "type": "Feature",
  "properties": {
    "iso:country":"US",
    "sg:address":"2082 Business Center Drive Suite 200",
    "sg:city":"Irvine",
    "sg:classifiers":[
        {
            "category":"Communications",
            "subcategory":"Film & Video Production",
            "type":"Services"
        }
    ],
    "sg:phone":"+1 949 474 6085",
    "sg:postcode":"92612",
    "sg:province":"CA",
    "sg:tags":[
        "video/film"
    ],
    "sg:website":"www.veassociates.com",
    "wof:name":"VE Associates, Inc.",
    "wof:placetype":"venue"
},
  "geometry": {"coordinates":[-117.85559499999999,33.679238],"type":"Point"}
}