{
  "type": "Feature",
  "properties": {
    "iso:country":"US",
    "sg:address":"4024 E 7th St",
    "sg:city":"Long Beach",
    "sg:classifiers":[
        {
            "category":"Personal",
            "subcategory":"Beauty Salon",
            "type":"Services"
        }
    ],
    "sg:phone":"+1 562 987 1666",
    "sg:postcode":"90804",
    "sg:province":"CA",
    "wof:name":"Modern Beauty Salon",
    "wof:placetype":"venue"
},
  "geometry": {"coordinates":[-118.145019,33.775246],"type":"Point"}
}