{
  "type": "Feature",
  "properties": {
    "addr:full":"2863 Howe Ave Sacramento CA 95821",
    "addr:housenumber":"2863",
    "addr:postcode":"95821",
    "addr:street":"Howe Ave",
    "iso:country":"US",
    "sg:address":"2863 Howe Ave",
    "sg:city":"Sacramento",
    "sg:classifiers":[
        {
            "category":"Retail",
            "subcategory":"Repair Shop",
            "type":"Services"
        }
    ],
    "sg:phone":"+1 916 927 1941",
    "sg:postcode":"95821",
    "sg:province":"CA",
    "sg:tags":[
        "reupholstery",
        "furniture"
    ],
    "wof:name":"Garland Upholstery Fabrics",
    "wof:placetype":"venue"
},
  "geometry": {"coordinates":[-121.415001,38.617699],"type":"Point"}
}