{
  "type": "Feature",
  "properties": {
    "addr:full":"7237 Rosecrans Ave Paramount CA 90723",
    "addr:housenumber":"7237",
    "addr:postcode":"90723",
    "addr:street":"Rosecrans Ave",
    "iso:country":"US",
    "sg:address":"7237 Rosecrans Ave",
    "sg:city":"Paramount",
    "sg:classifiers":[
        {
            "category":"Autos & Motor Vehicles",
            "subcategory":"Recreational Vehicle Sales",
            "type":"Retail Goods"
        }
    ],
    "sg:phone":"+1 562 634 1062",
    "sg:postcode":"90723",
    "sg:province":"CA",
    "sg:tags":[
        "camper",
        "pick"
    ],
    "wof:name":"Paramount Campers",
    "wof:placetype":"venue"
},
  "geometry": {"coordinates":[-118.169375,33.903671],"type":"Point"}
}