{
  "type": "Feature",
  "properties": {
    "addr:full":"8895 Westminster Ave Garden Grove CA 92844",
    "addr:housenumber":"8895",
    "addr:postcode":"92844",
    "addr:street":"Westminster Ave",
    "iso:country":"US",
    "sg:address":"8895 Westminster Ave",
    "sg:city":"Garden Grove",
    "sg:classifiers":[
        {
            "category":"Health Services",
            "subcategory":"Chiropractor",
            "type":"Services"
        }
    ],
    "sg:phone":"+1 714 890 7170",
    "sg:postcode":"92844",
    "sg:province":"CA",
    "wof:name":"Han Tien Vu Chiropractic",
    "wof:placetype":"venue"
},
  "geometry": {"coordinates":[-117.97441999999999,33.759603],"type":"Point"}
}