{
  "type": "Feature",
  "properties": {
    "addr:full":"300 Pine Ave Goleta CA 93117",
    "addr:housenumber":"300",
    "addr:postcode":"93117",
    "addr:street":"Pine Ave",
    "iso:country":"US",
    "sg:address":"300 Pine Ave",
    "sg:city":"Goleta",
    "sg:classifiers":[
        {
            "category":"Retail",
            "subcategory":"Auto Repair",
            "type":"Services"
        }
    ],
    "sg:phone":"+1 805 964 8276",
    "sg:postcode":"93117",
    "sg:province":"CA",
    "sg:tags":[
        "automobile",
        "electric"
    ],
    "wof:name":"A & E Automotive",
    "wof:placetype":"venue"
},
  "geometry": {"coordinates":[-119.826628,34.434349],"type":"Point"}
}