{
  "type": "Feature",
  "properties": {
    "iso:country":"US",
    "sg:address":"24966 Sunnymead Blvd",
    "sg:city":"Moreno Valley",
    "sg:classifiers":[
        {
            "category":"Banks & Credit Unions",
            "subcategory":"Bank",
            "type":"Services"
        }
    ],
    "sg:phone":"+1 951 485 4446",
    "sg:postcode":"92553",
    "sg:province":"CA",
    "sg:tags":[
        "cashing",
        "check"
    ],
    "wof:name":"Popular Cash",
    "wof:placetype":"venue"
},
  "geometry": {"coordinates":[-117.22769599999999,33.939179],"type":"Point"}
}