{
  "type": "Feature",
  "properties": {
    "iso:country":"US",
    "sg:address":"6325 Pacific Blvd Ste 203",
    "sg:city":"Huntington Park",
    "sg:classifiers":[
        {
            "category":"Professional",
            "subcategory":"Lawyer & Legal Services",
            "type":"Services"
        }
    ],
    "sg:phone":"+1 323 587 0602",
    "sg:postcode":"90255",
    "sg:province":"CA",
    "wof:name":"Perez Oscar Law Office Of",
    "wof:placetype":"venue"
},
  "geometry": {"coordinates":[-118.22542,33.983083],"type":"Point"}
}