{
  "type": "Feature",
  "properties": {
    "addr:full":"4870 Barranca Pkwy Ste 220 Irvine CA 92604",
    "addr:housenumber":"4870",
    "addr:postcode":"92604",
    "addr:street":"Barranca Pkwy Ste 220",
    "iso:country":"US",
    "sg:address":"4870 Barranca Pkwy Ste 220",
    "sg:city":"Irvine",
    "sg:classifiers":[
        {
            "category":"Health Services",
            "subcategory":"Doctor",
            "type":"Services"
        },
        {
            "category":"Personal",
            "subcategory":"Hair Removal",
            "type":"Services"
        }
    ],
    "sg:phone":"+1 949 552 4624",
    "sg:postcode":"92604",
    "sg:province":"CA",
    "sg:tags":[
        "obstetrician",
        "practice",
        "laser",
        "family",
        "gynecologist"
    ],
    "wof:name":"Onderdonk Flory Isabel MD",
    "wof:placetype":"venue"
},
  "geometry": {"coordinates":[-117.789001,33.688202],"type":"Point"}
}