{
  "type": "Feature",
  "properties": {
    "iso:country":"US",
    "sg:address":"1020 N Citrus Ave",
    "sg:city":"Covina",
    "sg:classifiers":[
        {
            "category":"Personal",
            "subcategory":"Barber",
            "type":"Services"
        }
    ],
    "sg:phone":"+1 626 974 4778",
    "sg:postcode":"91722",
    "sg:province":"CA",
    "wof:name":"Art's Barbershop",
    "wof:placetype":"venue"
},
  "geometry": {"coordinates":[-117.890126,34.098548],"type":"Point"}
}