{
  "type": "Feature",
  "properties": {
    "addr:full":"21515 Hawthorne Blvd Torrance CA 90503",
    "addr:housenumber":"21515",
    "addr:postcode":"90503",
    "addr:street":"Hawthorne Blvd",
    "iso:country":"US",
    "sg:address":"21515 Hawthorne Blvd",
    "sg:city":"Torrance",
    "sg:classifiers":[
        {
            "category":"Professional",
            "subcategory":"Lawyer & Legal Services",
            "type":"Services"
        }
    ],
    "sg:phone":"+1 310 543 1602",
    "sg:postcode":"90503",
    "sg:province":"CA",
    "sg:tags":[
        "attorney",
        "family",
        "divorce",
        "assistance",
        "violence",
        "domestic",
        "law"
    ],
    "sg:website":"http://www.macksoudlaw.com",
    "wof:name":"Macksoud & Macksoud LLP",
    "wof:placetype":"venue"
},
  "geometry": {"coordinates":[-118.352959,33.832897],"type":"Point"}
}