{
  "type": "Feature",
  "properties": {
    "addr:full":"1602 E Chevy Chase Dr Glendale CA 91206",
    "addr:housenumber":"1602",
    "addr:postcode":"91206",
    "addr:street":"E Chevy Chase Dr",
    "iso:country":"US",
    "sg:address":"1602 E Chevy Chase Dr",
    "sg:city":"Glendale",
    "sg:classifiers":[
        {
            "category":"Real Estate",
            "subcategory":"Real Estate Agent",
            "type":"Services"
        }
    ],
    "sg:phone":"+1 818 246 7800",
    "sg:postcode":"91206",
    "sg:province":"CA",
    "wof:name":"Hoffman Realty Co",
    "wof:placetype":"venue"
},
  "geometry": {"coordinates":[-118.227666,34.154049],"type":"Point"}
}