{
  "type": "Feature",
  "properties": {
    "iso:country":"US",
    "sg:address":"26531 Rd 100",
    "sg:city":"Tulare",
    "sg:classifiers":[
        {
            "category":"Wholesale",
            "subcategory":"Plants",
            "type":"Manufacturing & Wholesale Goods"
        }
    ],
    "sg:phone":"+1 559 687 0985",
    "sg:postcode":"93274",
    "sg:province":"CA",
    "sg:tags":[
        "nursery",
        "tree"
    ],
    "sg:website":"www.ocnursery.com",
    "wof:name":"Orange County Nursery Inc",
    "wof:placetype":"venue"
},
  "geometry": {"coordinates":[-119.349306,36.274105],"type":"Point"}
}