{
  "type": "Feature",
  "properties": {
    "addr:full":"3200 Grand Ave Oakland CA 94610",
    "addr:housenumber":"3200",
    "addr:postcode":"94610",
    "addr:street":"Grand Ave",
    "iso:country":"US",
    "sg:address":"3200 Grand Ave",
    "sg:city":"Oakland",
    "sg:classifiers":[
        {
            "category":"Cinema",
            "subcategory":"Movie Theater",
            "type":"Entertainment"
        }
    ],
    "sg:phone":"+1 510 452 3556",
    "sg:postcode":"94610",
    "sg:province":"CA",
    "sg:website":"www.renaissancerialto.com",
    "wof:name":"Grand Lake Theatre",
    "wof:placetype":"venue"
},
  "geometry": {"coordinates":[-122.248001,37.811401],"type":"Point"}
}