{
  "type": "Feature",
  "properties": {
    "iso:country":"US",
    "sg:address":"34784 Yucaipa Blvd",
    "sg:city":"Yucaipa",
    "sg:classifiers":[
        {
            "category":"Organizations",
            "subcategory":"Religious Organization",
            "type":"Services"
        }
    ],
    "sg:phone":"+1 909 790 1971",
    "sg:postcode":"92399",
    "sg:province":"CA",
    "wof:name":"First Baptist Church of Yucaipa",
    "wof:placetype":"venue"
},
  "geometry": {"coordinates":[-117.045998,34.033798],"type":"Point"}
}