{
  "type": "Feature",
  "properties": {
    "iso:country":"US",
    "sg:address":"3945 Western St",
    "sg:city":"San Diego",
    "sg:classifiers":[
        {
            "category":"Manufacturing",
            "subcategory":"Glass & Minerals",
            "type":"Manufacturing & Wholesale Goods"
        }
    ],
    "sg:phone":"+1 619 889 0475",
    "sg:postcode":"92110",
    "sg:province":"CA",
    "sg:tags":[
        "fabricator",
        "fiber"
    ],
    "wof:name":"Soulo Fiber Glassing",
    "wof:placetype":"venue"
},
  "geometry": {"coordinates":[-117.218962,32.756928],"type":"Point"}
}