{
  "type": "Feature",
  "properties": {
    "iso:country":"US",
    "sg:address":"21801 Plummer St",
    "sg:city":"Chatsworth",
    "sg:classifiers":[
        {
            "category":"Home & Garden",
            "subcategory":"Household Appliances",
            "type":"Retail Goods"
        }
    ],
    "sg:phone":"+1 818 341 6598",
    "sg:postcode":"91311",
    "sg:province":"CA",
    "wof:name":"Hot Rods Plus",
    "wof:placetype":"venue"
},
  "geometry": {"coordinates":[-118.60464899999999,34.242701],"type":"Point"}
}