{
  "type": "Feature",
  "properties": {
    "iso:country":"US",
    "sg:address":"4919 Coliseum Way",
    "sg:city":"Oakland",
    "sg:classifiers":[
        {
            "category":"Professional",
            "subcategory":"Detective & Security Services",
            "type":"Services"
        }
    ],
    "sg:phone":"+1 510 839 8675",
    "sg:postcode":"94601",
    "sg:province":"CA",
    "sg:tags":[
        "guard",
        "patrol"
    ],
    "sg:website":"www.allaboutsecurity1.com",
    "wof:name":"All About Security",
    "wof:placetype":"venue"
},
  "geometry": {"coordinates":[-122.217234,37.765506],"type":"Point"}
}