{
  "type": "Feature",
  "properties": {
    "addr:full":"1085 Ashby Avenue Berkeley CA 94710",
    "addr:housenumber":"1085",
    "addr:postcode":"94710",
    "addr:street":"Ashby Avenue",
    "iso:country":"US",
    "sg:address":"1085 Ashby Avenue",
    "sg:city":"Berkeley",
    "sg:classifiers":[
        {
            "category":"Home & Garden",
            "subcategory":"Home Furnishings",
            "type":"Retail Goods"
        },
        {
            "category":"Home & Garden",
            "subcategory":"Furniture",
            "type":"Retail Goods"
        }
    ],
    "sg:phone":"+1 510 841 1808",
    "sg:postcode":"94710",
    "sg:province":"CA",
    "sg:tags":[
        "decor",
        "store"
    ],
    "sg:website":"www.zentrumfurniture.com",
    "wof:name":"Zentrum Furniture",
    "wof:placetype":"venue"
},
  "geometry": {"coordinates":[-122.28806299999999,37.851891],"type":"Point"}
}