{
  "type": "Feature",
  "properties": {
    "iso:country":"US",
    "sg:address":"210 Cedar Rd",
    "sg:city":"Vista",
    "sg:classifiers":[
        {
            "category":"Real Estate",
            "subcategory":"Real Estate Operator",
            "type":"Services"
        }
    ],
    "sg:phone":"+1 760 941 9684",
    "sg:postcode":"92083",
    "sg:province":"CA",
    "sg:tags":[
        "apartment"
    ],
    "wof:name":"Cedarwoods Apartments",
    "wof:placetype":"venue"
},
  "geometry": {"coordinates":[-117.283997,33.190399],"type":"Point"}
}