{
  "type": "Feature",
  "properties": {
    "addr:full":"1005 Summit Rd Watsonville CA 95076",
    "addr:housenumber":"1005",
    "addr:postcode":"95076",
    "addr:street":"Summit Rd",
    "iso:country":"US",
    "sg:address":"1005 Summit Rd",
    "sg:city":"Watsonville",
    "sg:classifiers":[
        {
            "category":"Utilities",
            "subcategory":"Refuse",
            "type":"Services"
        }
    ],
    "sg:phone":"+1 831 763 0577",
    "sg:postcode":"95076",
    "sg:province":"CA",
    "sg:tags":[
        "system"
    ],
    "wof:name":"Community Recycling",
    "wof:placetype":"venue"
},
  "geometry": {"coordinates":[-121.763706,37.048416],"type":"Point"}
}