{
  "type": "Feature",
  "properties": {
    "addr:full":"1103 Glenwood St Delano CA 93215",
    "addr:housenumber":"1103",
    "addr:postcode":"93215",
    "addr:street":"Glenwood St",
    "iso:country":"US",
    "sg:address":"1103 Glenwood St",
    "sg:city":"Delano",
    "sg:classifiers":[
        {
            "category":"Food & Beverages",
            "subcategory":"Groceries & Convenience Stores",
            "type":"Retail Goods"
        }
    ],
    "sg:phone":"+1 661 725 0190",
    "sg:postcode":"93215",
    "sg:province":"CA",
    "sg:tags":[
        "grocer"
    ],
    "wof:name":"Lindo Michoacan",
    "wof:placetype":"venue"
},
  "geometry": {"coordinates":[-119.24936099999999,35.771184],"type":"Point"}
}