{
  "type": "Feature",
  "properties": {
    "iso:country":"US",
    "sg:address":"2150 Main St",
    "sg:city":"Red Bluff",
    "sg:classifiers":[
        {
            "category":"Health Services",
            "subcategory":"Clinic",
            "type":"Services"
        }
    ],
    "sg:phone":"+1 530 527 7227",
    "sg:postcode":"96080",
    "sg:province":"CA",
    "sg:tags":[
        "home"
    ],
    "wof:name":"Addus Healthcare",
    "wof:placetype":"venue"
},
  "geometry": {"coordinates":[-122.241228,40.19564],"type":"Point"}
}