{
  "type": "Feature",
  "properties": {
    "iso:country":"US",
    "sg:address":"189 W 40th St",
    "sg:city":"San Bernardino",
    "sg:classifiers":[
        {
            "category":"Shopping",
            "subcategory":"Mobile Phones",
            "type":"Retail Goods"
        }
    ],
    "sg:phone":"+1 909 882 5656",
    "sg:postcode":"92407",
    "sg:province":"CA",
    "wof:name":"Omar Wireless",
    "wof:placetype":"venue"
},
  "geometry": {"coordinates":[-117.287036,34.164772],"type":"Point"}
}