{
  "type": "Feature",
  "properties": {
    "iso:country":"US",
    "sg:address":"1302 Soquel Ave",
    "sg:city":"Santa Cruz",
    "sg:classifiers":[
        {
            "category":"Restaurant",
            "type":"Food & Drink"
        }
    ],
    "sg:menulink":"http://www.allmenus.com/ca/santa-cruz/171717-burger-king/menu/",
    "sg:phone":"+1 831 427 1110",
    "sg:postcode":"95062",
    "sg:province":"CA",
    "sg:tags":[
        "burger",
        "american"
    ],
    "wof:name":"Burger King",
    "wof:placetype":"venue"
},
  "geometry": {"coordinates":[-122.00740999999999,36.98076],"type":"Point"}
}