{
  "type": "Feature",
  "properties": {
    "iso:country":"US",
    "sg:address":"28150 Ave Crocker",
    "sg:city":"Valencia",
    "sg:classifiers":[
        {
            "category":"Manufacturing",
            "subcategory":"Signs",
            "type":"Manufacturing & Wholesale Goods"
        }
    ],
    "sg:phone":"+1 661 295 1471",
    "sg:postcode":"91355",
    "sg:province":"CA",
    "sg:tags":[
        "specialty",
        "mfg"
    ],
    "wof:name":"His Hands Sign & Design",
    "wof:placetype":"venue"
},
  "geometry": {"coordinates":[-118.587081,34.437024],"type":"Point"}
}