{
  "type": "Feature",
  "properties": {
    "addr:full":"1137 G St Reedley CA 93654",
    "addr:housenumber":"1137",
    "addr:postcode":"93654",
    "addr:street":"G St",
    "iso:country":"US",
    "sg:address":"1137 G St",
    "sg:city":"Reedley",
    "sg:classifiers":[
        {
            "category":"Insurance",
            "subcategory":"Hazard Insurance",
            "type":"Services"
        }
    ],
    "sg:phone":"+1 559 638 9000",
    "sg:postcode":"93654",
    "sg:province":"CA",
    "sg:tags":[
        "commercial",
        "business"
    ],
    "wof:name":"Central Sierra Insurance Services, Inc",
    "wof:placetype":"venue"
},
  "geometry": {"coordinates":[-119.450473,36.596018],"type":"Point"}
}