{
  "type": "Feature",
  "properties": {
    "addr:full":"23329 Lyons Ave Santa Clarita CA 91355",
    "addr:housenumber":"23329",
    "addr:postcode":"91355",
    "addr:street":"Lyons Ave",
    "iso:country":"US",
    "sg:address":"23329 Lyons Ave",
    "sg:city":"Santa Clarita",
    "sg:classifiers":[
        {
            "category":"Personal",
            "subcategory":"Hair Removal",
            "type":"Services"
        }
    ],
    "sg:phone":"+1 661 296 0625",
    "sg:postcode":"91355",
    "sg:province":"CA",
    "wof:name":"Temptation Electrolysis Full Skin Care",
    "wof:placetype":"venue"
},
  "geometry": {"coordinates":[-118.54200400000001,34.379886],"type":"Point"}
}