{
  "type": "Feature",
  "properties": {
    "iso:country":"US",
    "sg:address":"1527 Mission Ave",
    "sg:city":"Oceanside",
    "sg:classifiers":[
        {
            "category":"Shopping",
            "subcategory":"Clothing, Apparel, & Fashions",
            "type":"Retail Goods"
        }
    ],
    "sg:phone":"+1 760 439 7024",
    "sg:postcode":"92058",
    "sg:province":"CA",
    "sg:tags":[
        "lingerie"
    ],
    "wof:name":"Wonder Wear",
    "wof:placetype":"venue"
},
  "geometry": {"coordinates":[-117.368914,33.201561],"type":"Point"}
}