{
  "type": "Feature",
  "properties": {
    "addr:full":"17301 Beach Blvd Huntington Beach CA 92647",
    "addr:housenumber":"17301",
    "addr:postcode":"92647",
    "addr:street":"Beach Blvd",
    "iso:country":"US",
    "sg:address":"17301 Beach Blvd",
    "sg:city":"Huntington Beach",
    "sg:classifiers":[
        {
            "category":"Wholesale",
            "subcategory":"Computers",
            "type":"Manufacturing & Wholesale Goods"
        }
    ],
    "sg:phone":"+1 714 374 0696",
    "sg:postcode":"92647",
    "sg:province":"CA",
    "sg:tags":[
        "hardware"
    ],
    "wof:name":"Coastline Computer Products",
    "wof:placetype":"venue"
},
  "geometry": {"coordinates":[-117.98903300000001,33.712179],"type":"Point"}
}