{
  "type": "Feature",
  "properties": {
    "addr:full":"1919 O'Farrell St Ste 1 San Mateo CA 94403",
    "addr:housenumber":"1919",
    "addr:postcode":"94403",
    "addr:street":"O'Farrell St Ste 1",
    "iso:country":"US",
    "sg:address":"1919 O'Farrell St Ste 1",
    "sg:city":"San Mateo",
    "sg:classifiers":[
        {
            "category":"Health Services",
            "subcategory":"Dentist",
            "type":"Services"
        }
    ],
    "sg:phone":"+1 650 571 6666",
    "sg:postcode":"94403",
    "sg:province":"CA",
    "sg:website":"wudental.com/",
    "wof:name":"H. John Wu, DDS",
    "wof:placetype":"venue"
},
  "geometry": {"coordinates":[-122.31462000000001,37.548666],"type":"Point"}
}