{
  "type": "Feature",
  "properties": {
    "addr:full":"4 Jean St Valley Springs CA 95252",
    "addr:housenumber":"4",
    "addr:postcode":"95252",
    "addr:street":"Jean St",
    "iso:country":"US",
    "sg:address":"4 Jean St",
    "sg:city":"Valley Springs",
    "sg:classifiers":[
        {
            "category":"Professional",
            "subcategory":"Engineering",
            "type":"Services"
        }
    ],
    "sg:phone":"+1 209 772 2233",
    "sg:postcode":"95252",
    "sg:province":"CA",
    "sg:tags":[
        "engineer"
    ],
    "wof:name":"Tanner Consulting Group",
    "wof:placetype":"venue"
},
  "geometry": {"coordinates":[-120.825519,38.190928],"type":"Point"}
}