{
  "type": "Feature",
  "properties": {
    "addr:full":"5226 Pomona Blvd Los Angeles CA 90022",
    "addr:housenumber":"5226",
    "addr:postcode":"90022",
    "addr:street":"Pomona Blvd",
    "iso:country":"US",
    "sg:address":"5226 Pomona Blvd",
    "sg:city":"Los Angeles",
    "sg:classifiers":[
        {
            "category":"Bars & Pubs",
            "type":"Food & Drink"
        }
    ],
    "sg:phone":"+1 323 722 7992",
    "sg:postcode":"90022",
    "sg:province":"CA",
    "sg:tags":[
        "sport"
    ],
    "wof:name":"T Quilea's Bar & Grill",
    "wof:placetype":"venue"
},
  "geometry": {"coordinates":[-118.15159300000001,34.033081],"type":"Point"}
}