{
  "type": "Feature",
  "properties": {
    "addr:full":"12249 HESPERIA RD VICTORVILLE CA 92395",
    "addr:postcode":"12249;92395",
    "addr:street":"Hesperia Rd",
    "iso:country":"US",
    "sg:address":"12249 HESPERIA RD",
    "sg:city":"VICTORVILLE",
    "sg:classifiers":[
        {
            "category":"Home & Garden",
            "subcategory":"Household Appliances",
            "type":"Retail Goods"
        },
        {
            "category":"Communications",
            "subcategory":"Radio Station",
            "type":"Services"
        },
        {
            "category":"Shopping",
            "subcategory":"Computers & Home Electronics",
            "type":"Retail Goods"
        },
        {
            "category":"Home & Garden",
            "subcategory":"Furniture",
            "type":"Retail Goods"
        }
    ],
    "sg:phone":"+1 760 241 1322",
    "sg:postcode":"92395",
    "sg:province":"CA",
    "sg:tags":[
        "renting",
        "television",
        "leasing",
        "radio-renting",
        "equipment",
        "rental"
    ],
    "sg:website":"http://www.rentacenter.com/",
    "wof:name":"Rent-A-Center",
    "wof:placetype":"venue"
},
  "geometry": {"coordinates":[-117.29158700000001,34.47388],"type":"Point"}
}