{
  "type": "Feature",
  "properties": {
    "addr:full":"1340 Warmlands Ave Vista CA 92084",
    "addr:housenumber":"1340",
    "addr:postcode":"92084",
    "addr:street":"Warmlands Ave",
    "iso:country":"US",
    "sg:address":"1340 Warmlands Ave",
    "sg:city":"Vista",
    "sg:classifiers":[
        {
            "category":"Wholesale",
            "subcategory":"Plants",
            "type":"Manufacturing & Wholesale Goods"
        },
        {
            "category":"Farming",
            "subcategory":"Farm & Veterinary Services",
            "type":"Manufacturing & Wholesale Goods"
        }
    ],
    "sg:phone":"+1 760 758 1350",
    "sg:postcode":"92084",
    "sg:province":"CA",
    "sg:tags":[
        "crop",
        "supply"
    ],
    "wof:name":"Sun Life Growers",
    "wof:placetype":"venue"
},
  "geometry": {"coordinates":[-117.211825,33.217716],"type":"Point"}
}