{
  "type": "Feature",
  "properties": {
    "addr:full":"17603 Ardmore Ave Bellflower CA 90706",
    "addr:housenumber":"17603",
    "addr:postcode":"90706",
    "addr:street":"Ardmore Ave",
    "iso:country":"US",
    "sg:address":"17603 Ardmore Ave",
    "sg:city":"Bellflower",
    "sg:classifiers":[
        {
            "category":"Organizations",
            "subcategory":"Religious Organization",
            "type":"Services"
        }
    ],
    "sg:phone":"+1 562 866 5577",
    "sg:postcode":"90706",
    "sg:province":"CA",
    "sg:tags":[
        "church"
    ],
    "wof:name":"First Christian Reformed Chr",
    "wof:placetype":"venue"
},
  "geometry": {"coordinates":[-118.129109,33.871211],"type":"Point"}
}