{
  "type": "Feature",
  "properties": {
    "iso:country":"US",
    "sg:address":"1329 S State St",
    "sg:city":"Ukiah",
    "sg:classifiers":[
        {
            "category":"Professional",
            "subcategory":"Business Services",
            "type":"Services"
        },
        {
            "category":"Professional",
            "subcategory":"Printing & Photocopies",
            "type":"Services"
        }
    ],
    "sg:phone":"+1 800 463 3339",
    "sg:postcode":"95482",
    "sg:province":"CA",
    "sg:tags":[
        "duplicating",
        "shipping",
        "copying"
    ],
    "sg:website":"http://www.fedex.com",
    "wof:name":"FedEx Express Ship Center",
    "wof:placetype":"venue"
},
  "geometry": {"coordinates":[-123.20456900000001,39.130845],"type":"Point"}
}