{
  "type": "Feature",
  "properties": {
    "addr:full":"6529 E Spring St Long Beach CA 90808",
    "addr:housenumber":"6529",
    "addr:postcode":"90808",
    "addr:street":"E Spring St",
    "iso:country":"US",
    "sg:address":"6529 E Spring St",
    "sg:city":"Long Beach",
    "sg:classifiers":[
        {
            "category":"Personal",
            "subcategory":"Massage",
            "type":"Services"
        }
    ],
    "sg:phone":"+1 562 421 7328",
    "sg:postcode":"90808",
    "sg:province":"CA",
    "wof:name":"Oriental Day Spa",
    "wof:placetype":"venue"
},
  "geometry": {"coordinates":[-118.105654,33.810567],"type":"Point"}
}