{
  "type": "Feature",
  "properties": {
    "addr:full":"2109 Westminster Dr Bakersfield CA 93309",
    "addr:housenumber":"2109",
    "addr:postcode":"93309",
    "addr:street":"Westminster Dr",
    "iso:country":"US",
    "sg:address":"2109 Westminster Dr",
    "sg:city":"Bakersfield",
    "sg:classifiers":[
        {
            "category":"Professional",
            "type":"Services"
        }
    ],
    "sg:phone":"+1 661 833 9972",
    "sg:postcode":"93309",
    "sg:province":"CA",
    "wof:name":"Joesph Litto",
    "wof:placetype":"venue"
},
  "geometry": {"coordinates":[-119.06106800000001,35.335429],"type":"Point"}
}