{
  "type": "Feature",
  "properties": {
    "iso:country":"US",
    "sg:address":"7760 S Central Avenue",
    "sg:city":"Los Angeles",
    "sg:classifiers":[
        {
            "category":"Organizations",
            "subcategory":"Religious Organization",
            "type":"Services"
        }
    ],
    "sg:phone":"+1 323 588 1926",
    "sg:postcode":"90001",
    "sg:province":"CA",
    "wof:name":"Christ Apostolic Church of America",
    "wof:placetype":"venue"
},
  "geometry": {"coordinates":[-118.256534,33.96869],"type":"Point"}
}