{
  "type": "Feature",
  "properties": {
    "iso:country":"US",
    "sg:address":"1225 E Cerritos Ave",
    "sg:city":"Anaheim",
    "sg:classifiers":[
        {
            "category":"Mining & Drilling",
            "type":"Manufacturing & Wholesale Goods"
        }
    ],
    "sg:phone":"+1 714 817 7313",
    "sg:postcode":"92805",
    "sg:province":"CA",
    "sg:tags":[
        "wholesaler",
        "stone",
        "natural"
    ],
    "wof:name":"Corsica Stone Inc",
    "wof:placetype":"venue"
},
  "geometry": {"coordinates":[-117.897715,33.810678],"type":"Point"}
}