{
  "type": "Feature",
  "properties": {
    "addr:full":"5271 Romford Dr San Jose CA 95124",
    "addr:housenumber":"5271",
    "addr:postcode":"95124",
    "addr:street":"Romford Dr",
    "iso:country":"US",
    "sg:address":"5271 Romford Dr",
    "sg:city":"San Jose",
    "sg:classifiers":[
        {
            "category":"Professional",
            "type":"Services"
        }
    ],
    "sg:phone":"+1 408 266 3736",
    "sg:postcode":"95124",
    "sg:province":"CA",
    "wof:name":"Zipadee Do Dog",
    "wof:placetype":"venue"
},
  "geometry": {"coordinates":[-121.91589,37.240986],"type":"Point"}
}