{
  "type": "Feature",
  "properties": {
    "iso:country":"US",
    "sg:address":"46378 W Panoche Rd",
    "sg:city":"Firebaugh",
    "sg:classifiers":[
        {
            "category":"Food & Beverages",
            "subcategory":"Groceries & Convenience Stores",
            "type":"Retail Goods"
        }
    ],
    "sg:phone":"+1 559 659 3947",
    "sg:postcode":"93622",
    "sg:province":"CA",
    "wof:name":"Palms Market",
    "wof:placetype":"venue"
},
  "geometry": {"coordinates":[-120.62645,36.638152],"type":"Point"}
}