{
  "type": "Feature",
  "properties": {
    "iso:country":"US",
    "sg:address":"1216 Broadway Plz",
    "sg:city":"Walnut Creek",
    "sg:classifiers":[
        {
            "category":"Shopping",
            "subcategory":"Clothing, Apparel, & Fashions",
            "type":"Retail Goods"
        }
    ],
    "sg:phone":"+1 925 937 1808",
    "sg:postcode":"94596",
    "sg:province":"CA",
    "sg:tags":[
        "furnishing"
    ],
    "wof:name":"Daskalos European Fashions",
    "wof:placetype":"venue"
},
  "geometry": {"coordinates":[-122.058058,37.895773],"type":"Point"}
}