{
  "type": "Feature",
  "properties": {
    "addr:full":"495 W San Carlos St San Jose CA 95110",
    "addr:housenumber":"495",
    "addr:postcode":"95110",
    "addr:street":"W San Carlos St",
    "iso:country":"US",
    "sg:address":"495 W San Carlos St",
    "sg:city":"San Jose",
    "sg:classifiers":[
        {
            "category":"Professional",
            "subcategory":"Business Services",
            "type":"Services"
        }
    ],
    "sg:phone":"+1 408 294 4303",
    "sg:postcode":"95110",
    "sg:province":"CA",
    "sg:tags":[
        "information",
        "referral"
    ],
    "wof:name":"How To Info",
    "wof:placetype":"venue"
},
  "geometry": {"coordinates":[-121.896522,37.326965],"type":"Point"}
}