{
  "type": "Feature",
  "properties": {
    "iso:country":"US",
    "sg:address":"35 Park St",
    "sg:city":"San Francisco",
    "sg:classifiers":[
        {
            "category":"Communications",
            "type":"Services"
        }
    ],
    "sg:phone":"+1 415 913 7531",
    "sg:postcode":"94110",
    "sg:province":"CA",
    "sg:tags":[
        "web",
        "design"
    ],
    "wof:name":"Rga",
    "wof:placetype":"venue"
},
  "geometry": {"coordinates":[-122.425044,37.736836],"type":"Point"}
}