{
  "type": "Feature",
  "properties": {
    "addr:full":"5191 Sparrow Dr Huntington Beach CA 92649",
    "addr:housenumber":"5191",
    "addr:postcode":"92649",
    "addr:street":"Sparrow Dr",
    "iso:country":"US",
    "sg:address":"5191 Sparrow Dr",
    "sg:city":"Huntington Beach",
    "sg:classifiers":[
        {
            "category":"Professional",
            "subcategory":"Management & Consulting",
            "type":"Services"
        }
    ],
    "sg:phone":"+1 714 899 7866",
    "sg:postcode":"92649",
    "sg:province":"CA",
    "sg:tags":[
        "mate"
    ],
    "wof:name":"Accolade International",
    "wof:placetype":"venue"
},
  "geometry": {"coordinates":[-118.03972,33.731362],"type":"Point"}
}