{
  "type": "Feature",
  "properties": {
    "iso:country":"US",
    "sg:address":"1125 Saratoga Ave",
    "sg:city":"San Jose",
    "sg:classifiers":[
        {
            "category":"Insurance",
            "subcategory":"Hazard Insurance",
            "type":"Services"
        },
        {
            "category":"Banks & Credit Unions",
            "subcategory":"Investment Brokerage",
            "type":"Services"
        },
        {
            "category":"Banks & Credit Unions",
            "subcategory":"Bank",
            "type":"Services"
        }
    ],
    "sg:phone":"+1 408 257 1234",
    "sg:postcode":"95129",
    "sg:province":"CA",
    "sg:tags":[
        "investing"
    ],
    "sg:website":"pin1ins.com/",
    "wof:name":"Varich Robert Insurance Agency",
    "wof:placetype":"venue"
},
  "geometry": {"coordinates":[-121.97928,37.304785],"type":"Point"}
}