{
  "type": "Feature",
  "properties": {
    "addr:full":"1054 E 2nd St Long Beach CA 90802",
    "addr:housenumber":"1054",
    "addr:postcode":"90802",
    "addr:street":"E 2Nd St",
    "iso:country":"US",
    "sg:address":"1054 E 2nd St",
    "sg:city":"Long Beach",
    "sg:classifiers":[
        {
            "category":"Organizations",
            "subcategory":"Professional Association",
            "type":"Services"
        }
    ],
    "sg:phone":"+1 562 590 9979",
    "sg:postcode":"90802",
    "sg:province":"CA",
    "wof:name":"Kotobuki Condos Assn",
    "wof:placetype":"venue"
},
  "geometry": {"coordinates":[-118.180516,33.768305],"type":"Point"}
}