{
  "type": "Feature",
  "properties": {
    "iso:country":"US",
    "sg:address":"2800 N Main St",
    "sg:city":"Santa Ana",
    "sg:classifiers":[
        {
            "category":"Sports & Exercise",
            "subcategory":"Bicycle Rental",
            "type":"Entertainment"
        },
        {
            "category":"Shopping",
            "subcategory":"Shoes",
            "type":"Retail Goods"
        }
    ],
    "sg:phone":"+1 714 550 0277",
    "sg:postcode":"92705",
    "sg:province":"CA",
    "sg:tags":[
        "wear",
        "store"
    ],
    "wof:name":"Finish Line",
    "wof:placetype":"venue"
},
  "geometry": {"coordinates":[-117.867594,33.774851],"type":"Point"}
}