{
  "type": "Feature",
  "properties": {
    "iso:country":"US",
    "sg:address":"5301 Elmer Way",
    "sg:city":"Sacramento",
    "sg:classifiers":[
        {
            "category":"Education",
            "subcategory":"School",
            "type":"Public Place"
        }
    ],
    "sg:phone":"+1 916 264 4350",
    "sg:postcode":"95822",
    "sg:province":"CA",
    "sg:tags":[
        "high",
        "middle"
    ],
    "sg:website":"schools.scusd.edu/sambrannan/",
    "wof:name":"Sam Brannan Middle School",
    "wof:placetype":"venue"
},
  "geometry": {"coordinates":[-121.517225,38.527993],"type":"Point"}
}