{
  "type": "Feature",
  "properties": {
    "addr:full":"4791 Arrow Hwy Montclair CA 91763",
    "addr:housenumber":"4791",
    "addr:postcode":"91763",
    "addr:street":"Arrow Hwy",
    "iso:country":"US",
    "sg:address":"4791 Arrow Hwy",
    "sg:city":"Montclair",
    "sg:classifiers":[
        {
            "category":"Freight",
            "type":"Transportation"
        }
    ],
    "sg:phone":"+1 909 625 9955",
    "sg:postcode":"91763",
    "sg:province":"CA",
    "sg:tags":[
        "trucking"
    ],
    "wof:name":"J M Trucking",
    "wof:placetype":"venue"
},
  "geometry": {"coordinates":[-117.699183,34.092377],"type":"Point"}
}