{
  "type": "Feature",
  "properties": {
    "iso:country":"US",
    "sg:address":"920 Shoreline Dr",
    "sg:city":"San Mateo",
    "sg:classifiers":[
        {
            "category":"Education",
            "subcategory":"Special Training",
            "type":"Public Place"
        }
    ],
    "sg:phone":"+1 650 341 7126",
    "sg:postcode":"94404",
    "sg:province":"CA",
    "sg:tags":[
        "self",
        "motivational",
        "improvement"
    ],
    "wof:name":"MPK Enterprises",
    "wof:placetype":"venue"
},
  "geometry": {"coordinates":[-122.288982,37.55662],"type":"Point"}
}