{
  "type": "Feature",
  "properties": {
    "addr:full":"2010 Main St Santa Clara CA 95050",
    "addr:housenumber":"2010",
    "addr:postcode":"95050",
    "addr:street":"Main St",
    "iso:country":"US",
    "sg:address":"2010 Main St",
    "sg:city":"Santa Clara",
    "sg:classifiers":[
        {
            "category":"Real Estate",
            "subcategory":"Real Estate Operator",
            "type":"Services"
        }
    ],
    "sg:phone":"+1 408 984 5352",
    "sg:postcode":"95050",
    "sg:province":"CA",
    "sg:tags":[
        "apartment"
    ],
    "wof:name":"Main Street Apartments",
    "wof:placetype":"venue"
},
  "geometry": {"coordinates":[-121.950996,37.3596],"type":"Point"}
}