{
  "type": "Feature",
  "properties": {
    "addr:full":"2125 Oak Grove Rd Walnut Creek CA 94598",
    "addr:housenumber":"2125",
    "addr:postcode":"94598",
    "addr:street":"Oak Grove Rd",
    "iso:country":"US",
    "sg:address":"2125 Oak Grove Rd",
    "sg:city":"Walnut Creek",
    "sg:classifiers":[
        {
            "category":"Professional",
            "subcategory":"Engineering",
            "type":"Services"
        }
    ],
    "sg:phone":"+1 925 280 0525",
    "sg:postcode":"94598",
    "sg:province":"CA",
    "sg:tags":[
        "general",
        "contractor"
    ],
    "wof:name":"Integrated Profect Svc",
    "wof:placetype":"venue"
},
  "geometry": {"coordinates":[-122.01854899999999,37.931673],"type":"Point"}
}