{
  "type": "Feature",
  "properties": {
    "iso:country":"US",
    "sg:address":"76 64th Pl",
    "sg:city":"Long Beach",
    "sg:classifiers":[
        {
            "category":"Banks & Credit Unions",
            "subcategory":"Bank",
            "type":"Services"
        }
    ],
    "sg:phone":"+1 562 438 4362",
    "sg:postcode":"90803",
    "sg:province":"CA",
    "sg:tags":[
        "mortgage"
    ],
    "wof:name":"Weber Co The",
    "wof:placetype":"venue"
},
  "geometry": {"coordinates":[-118.121202,33.748227],"type":"Point"}
}