{
  "type": "Feature",
  "properties": {
    "iso:country":"US",
    "sg:address":"412 W 4th St",
    "sg:city":"Santa Ana",
    "sg:classifiers":[
        {
            "category":"Professional",
            "type":"Services"
        }
    ],
    "sg:phone":"+1 714 835 7218",
    "sg:postcode":"92701",
    "sg:province":"CA",
    "sg:tags":[
        "establishment"
    ],
    "wof:name":"Coronado Enterprises",
    "wof:placetype":"venue"
},
  "geometry": {"coordinates":[-117.87236,33.747886],"type":"Point"}
}