{
  "type": "Feature",
  "properties": {
    "iso:country":"US",
    "sg:address":"1979 Monterey Hwy",
    "sg:city":"San Jose",
    "sg:classifiers":[
        {
            "category":"Manufacturing",
            "subcategory":"Food",
            "type":"Manufacturing & Wholesale Goods"
        },
        {
            "category":"Wholesale",
            "subcategory":"Seafood",
            "type":"Manufacturing & Wholesale Goods"
        }
    ],
    "sg:phone":"+1 408 286 1388",
    "sg:postcode":"95112",
    "sg:province":"CA",
    "wof:name":"Seafoods Connection",
    "wof:placetype":"venue"
},
  "geometry": {"coordinates":[-121.861908,37.304259],"type":"Point"}
}