{
  "type": "Feature",
  "properties": {
    "addr:full":"102 N School St Ukiah CA 95482",
    "addr:housenumber":"102",
    "addr:postcode":"ca 95482",
    "addr:street":"N School St",
    "iso:country":"US",
    "sg:address":"102 N School St",
    "sg:city":"Ukiah",
    "sg:classifiers":[
        {
            "category":"Real Estate",
            "subcategory":"Real Estate Services",
            "type":"Services"
        },
        {
            "category":"Real Estate",
            "subcategory":"Real Estate Agent",
            "type":"Services"
        }
    ],
    "sg:phone":"+1 707 468 8008",
    "sg:postcode":"95482",
    "sg:province":"CA",
    "sg:tags":[
        "management"
    ],
    "wof:name":"Peter Davis",
    "wof:placetype":"venue"
},
  "geometry": {"coordinates":[-123.208614,39.149854],"type":"Point"}
}