{
  "type": "Feature",
  "properties": {
    "iso:country":"US",
    "sg:address":"801 S Ham Ln",
    "sg:city":"Lodi",
    "sg:classifiers":[
        {
            "category":"Health Services",
            "subcategory":"Health Practitioner",
            "type":"Services"
        }
    ],
    "sg:phone":"+1 209 333 1324",
    "sg:postcode":"95242",
    "sg:province":"CA",
    "sg:tags":[
        "therapist",
        "physical"
    ],
    "wof:name":"MFR Therapy Group",
    "wof:placetype":"venue"
},
  "geometry": {"coordinates":[-121.28814199999999,38.122782],"type":"Point"}
}