{
  "type": "Feature",
  "properties": {
    "iso:country":"US",
    "sg:address":"713 W Duarte Rd Ste G PMB 172",
    "sg:city":"Arcadia",
    "sg:classifiers":[
        {
            "category":"Communications",
            "type":"Services"
        }
    ],
    "sg:phone":"+1 626 462 0983",
    "sg:postcode":"91007",
    "sg:province":"CA",
    "sg:tags":[
        "web",
        "design"
    ],
    "sg:website":"www.hutdogs.com",
    "wof:name":"Hutdogs",
    "wof:placetype":"venue"
},
  "geometry": {"coordinates":[-118.055669,34.125958],"type":"Point"}
}