{
  "type": "Feature",
  "properties": {
    "addr:full":"2100 Marx Way Anderson CA 96007",
    "addr:housenumber":"2100",
    "addr:postcode":"96007",
    "addr:street":"Marx Way",
    "iso:country":"US",
    "sg:address":"2100 Marx Way",
    "sg:city":"Anderson",
    "sg:classifiers":[
        {
            "category":"Manufacturing",
            "subcategory":"Leather Goods",
            "type":"Manufacturing & Wholesale Goods"
        }
    ],
    "sg:phone":"+1 530 365 6048",
    "sg:postcode":"96007",
    "sg:province":"CA",
    "sg:tags":[
        "bag",
        "traveling",
        "mfg"
    ],
    "wof:name":"Loadmaster Flight Bags",
    "wof:placetype":"venue"
},
  "geometry": {"coordinates":[-122.28989199999999,40.44264],"type":"Point"}
}