{
  "type": "Feature",
  "properties": {
    "addr:full":"4 Embarcadero Center San Francisco CA 94111",
    "addr:housenumber":"4",
    "addr:postcode":"94111",
    "addr:street":"Embarcadero Center",
    "iso:country":"US",
    "sg:address":"4 Embarcadero Center",
    "sg:city":"San Francisco",
    "sg:classifiers":[
        {
            "category":"Professional",
            "subcategory":"Lawyer & Legal Services",
            "type":"Services"
        }
    ],
    "sg:phone":"+1 415 981 1400",
    "sg:postcode":"94111",
    "sg:province":"CA",
    "wof:name":"Schlobohm Dean A Greene Radvosky Maloney Shre Atty",
    "wof:placetype":"venue"
},
  "geometry": {"coordinates":[-122.397003,37.795101],"type":"Point"}
}