{
  "type": "Feature",
  "properties": {
    "iso:country":"US",
    "sg:address":"14360 Rios Canyon Rd",
    "sg:city":"El Cajon",
    "sg:classifiers":[
        {
            "category":"Real Estate",
            "subcategory":"Real Estate Operator",
            "type":"Services"
        }
    ],
    "sg:phone":"+1 619 443 5535",
    "sg:postcode":"92021",
    "sg:province":"CA",
    "sg:tags":[
        "mobile",
        "home",
        "site",
        "community"
    ],
    "wof:name":"Rios Mobile Manor",
    "wof:placetype":"venue"
},
  "geometry": {"coordinates":[-116.87452399999999,32.838721],"type":"Point"}
}