{
  "type": "Feature",
  "properties": {
    "iso:country":"US",
    "sg:address":"4399 Florin Rd",
    "sg:city":"Sacramento",
    "sg:classifiers":[
        {
            "category":"Utilities",
            "subcategory":"Mobile Phone",
            "type":"Services"
        }
    ],
    "sg:phone":"+1 916 393 6500",
    "sg:postcode":"95823",
    "sg:province":"CA",
    "sg:tags":[
        "communication",
        "radiotelephone"
    ],
    "wof:name":"Metro Co Wireless Inc",
    "wof:placetype":"venue"
},
  "geometry": {"coordinates":[-121.457334,38.496027],"type":"Point"}
}