{
  "type": "Feature",
  "properties": {
    "addr:full":"8318 Wilshire Blvd Beverly Hills CA 90211",
    "addr:housenumber":"8318",
    "addr:postcode":"90211",
    "addr:street":"Wilshire Blvd",
    "iso:country":"US",
    "sg:address":"8318 Wilshire Blvd",
    "sg:city":"Beverly Hills",
    "sg:classifiers":[
        {
            "category":"Food & Beverages",
            "subcategory":"Liquor & Beverages",
            "type":"Retail Goods"
        }
    ],
    "sg:phone":"+1 888 472 1376",
    "sg:postcode":"90211",
    "sg:province":"CA",
    "sg:tags":[
        "grocery"
    ],
    "sg:website":"www.beverlyhillsliquorandwine.com/",
    "wof:name":"Beverly Hills Liquor & Wine",
    "wof:placetype":"venue"
},
  "geometry": {"coordinates":[-118.37276900000001,34.064237],"type":"Point"}
}