{
  "type": "Feature",
  "properties": {
    "addr:full":"4508 Avalon Blvd Los Angeles CA 90011",
    "addr:housenumber":"4508",
    "addr:postcode":"90011",
    "addr:street":"Avalon Blvd",
    "iso:country":"US",
    "sg:address":"4508 Avalon Blvd",
    "sg:city":"Los Angeles",
    "sg:classifiers":[
        {
            "category":"Wholesale",
            "subcategory":"Apparel",
            "type":"Manufacturing & Wholesale Goods"
        }
    ],
    "sg:phone":"+1 323 231 6014",
    "sg:postcode":"90011",
    "sg:province":"CA",
    "sg:tags":[
        "textile"
    ],
    "wof:name":"D K Textiles",
    "wof:placetype":"venue"
},
  "geometry": {"coordinates":[-118.265147,34.001672],"type":"Point"}
}