{
  "type": "Feature",
  "properties": {
    "addr:full":"440 Main St Placerville CA 95667",
    "addr:housenumber":"440",
    "addr:postcode":"95667",
    "addr:street":"Main St",
    "iso:country":"US",
    "sg:address":"440 Main St",
    "sg:city":"Placerville",
    "sg:classifiers":[
        {
            "category":"Shopping",
            "type":"Retail Goods"
        }
    ],
    "sg:phone":"+1 530 621 1164",
    "sg:postcode":"95667",
    "sg:province":"CA",
    "sg:tags":[
        "art",
        "gallery",
        "dealer"
    ],
    "wof:name":"Bennett Gallery Inc",
    "wof:placetype":"venue"
},
  "geometry": {"coordinates":[-120.80045800000001,38.729225],"type":"Point"}
}