{
  "type": "Feature",
  "properties": {
    "addr:full":"52 Anza Rd Calexico CA 92231",
    "addr:housenumber":"52",
    "addr:postcode":"92231",
    "addr:street":"Anza Rd",
    "iso:country":"US",
    "sg:address":"52 Anza Rd",
    "sg:city":"Calexico",
    "sg:classifiers":[
        {
            "category":"Home & Garden",
            "subcategory":"Garden Supply",
            "type":"Retail Goods"
        }
    ],
    "sg:phone":"+1 760 357 1695",
    "sg:postcode":"92231",
    "sg:province":"CA",
    "sg:tags":[
        "nurseryman"
    ],
    "wof:name":"Muren's Nursery",
    "wof:placetype":"venue"
},
  "geometry": {"coordinates":[-115.550926,32.66458],"type":"Point"}
}