{
  "type": "Feature",
  "properties": {
    "addr:full":"715 N Termino Ave Long Beach CA 90804",
    "addr:housenumber":"715",
    "addr:postcode":"90804",
    "addr:street":"N Termino Ave",
    "iso:country":"US",
    "sg:address":"715 N Termino Ave",
    "sg:city":"Long Beach",
    "sg:classifiers":[
        {
            "category":"Wholesale",
            "subcategory":"Non-durable Goods",
            "type":"Manufacturing & Wholesale Goods"
        }
    ],
    "sg:phone":"+1 562 433 1882",
    "sg:postcode":"90804",
    "sg:province":"CA",
    "wof:name":"China Pacific Inc",
    "wof:placetype":"venue"
},
  "geometry": {"coordinates":[-118.145967,33.776891],"type":"Point"}
}