{
  "type": "Feature",
  "properties": {
    "iso:country":"US",
    "sg:address":"3123 Madison St",
    "sg:city":"Riverside",
    "sg:classifiers":[
        {
            "category":"Food & Beverages",
            "subcategory":"Groceries & Convenience Stores",
            "type":"Retail Goods"
        }
    ],
    "sg:phone":"+1 951 688 0821",
    "sg:postcode":"92504",
    "sg:province":"CA",
    "sg:tags":[
        "grocer"
    ],
    "wof:name":"LA Mexicana Market",
    "wof:placetype":"venue"
},
  "geometry": {"coordinates":[-117.401918,33.93234],"type":"Point"}
}