{
  "type": "Feature",
  "properties": {
    "addr:full":"892 Oak Valley Pkwy Beaumont CA 92223",
    "addr:housenumber":"892",
    "addr:postcode":"92223",
    "addr:street":"Oak Valley Pkwy",
    "iso:country":"US",
    "sg:address":"892 Oak Valley Pkwy",
    "sg:city":"Beaumont",
    "sg:classifiers":[
        {
            "category":"Restaurant",
            "type":"Food & Drink"
        }
    ],
    "sg:phone":"+1 951 845 4040",
    "sg:postcode":"92223",
    "sg:province":"CA",
    "sg:tags":[
        "mexican"
    ],
    "wof:name":"Tolucas Mexican Food",
    "wof:placetype":"venue"
},
  "geometry": {"coordinates":[-116.970067,33.947094],"type":"Point"}
}