{
  "type": "Feature",
  "properties": {
    "iso:country":"US",
    "sg:address":"2085 N Towne Ave",
    "sg:city":"Pomona",
    "sg:classifiers":[
        {
            "category":"Organizations",
            "subcategory":"Religious Organization",
            "type":"Services"
        }
    ],
    "sg:phone":"+1 909 469 9155",
    "sg:postcode":"91767",
    "sg:province":"CA",
    "sg:tags":[
        "church"
    ],
    "wof:name":"Christ Apostolic Church",
    "wof:placetype":"venue"
},
  "geometry": {"coordinates":[-117.740975,34.07953],"type":"Point"}
}