{
  "type": "Feature",
  "properties": {
    "addr:full":"3762 Atlantic Ave Ste C Long Beach CA 90807",
    "addr:housenumber":"3762",
    "addr:postcode":"90807",
    "addr:street":"Atlantic Ave Ste C",
    "iso:country":"US",
    "sg:address":"3762 Atlantic Ave Ste C",
    "sg:city":"Long Beach",
    "sg:classifiers":[
        {
            "category":"Health Services",
            "subcategory":"Doctor",
            "type":"Services"
        }
    ],
    "sg:phone":"+1 562 595 9206",
    "sg:postcode":"90807",
    "sg:province":"CA",
    "sg:tags":[
        "practice",
        "family"
    ],
    "wof:name":"J Wu Medical Care Inc",
    "wof:placetype":"venue"
},
  "geometry": {"coordinates":[-118.184834,33.825781],"type":"Point"}
}