{
  "type": "Feature",
  "properties": {
    "iso:country":"US",
    "sg:address":"15332 Eucalyptus Ave",
    "sg:city":"Bellflower",
    "sg:classifiers":[
        {
            "category":"Education",
            "subcategory":"School",
            "type":"Public Place"
        }
    ],
    "sg:phone":"+1 562 804 6517",
    "sg:postcode":"90706",
    "sg:province":"CA",
    "sg:tags":[
        "high",
        "elementary",
        "middle"
    ],
    "wof:name":"Bellflower Unified School District",
    "wof:placetype":"venue"
},
  "geometry": {"coordinates":[-118.121882,33.894497],"type":"Point"}
}