{
  "type": "Feature",
  "properties": {
    "addr:full":"719 Sutter St Yuba City CA 95991",
    "addr:housenumber":"719",
    "addr:postcode":"95991",
    "addr:street":"Sutter St",
    "iso:country":"US",
    "sg:address":"719 Sutter St",
    "sg:city":"Yuba City",
    "sg:classifiers":[
        {
            "category":"Shopping",
            "subcategory":"News",
            "type":"Retail Goods"
        }
    ],
    "sg:phone":"+1 530 673 9362",
    "sg:postcode":"95991",
    "sg:province":"CA",
    "sg:tags":[
        "dealer"
    ],
    "sg:website":"www.twincity-news.com",
    "wof:name":"Twin City News",
    "wof:placetype":"venue"
},
  "geometry": {"coordinates":[-121.609497,39.139765],"type":"Point"}
}