{
  "type": "Feature",
  "properties": {
    "addr:full":"630 Ark Way Sacramento CA 95831",
    "addr:housenumber":"630",
    "addr:postcode":"95831",
    "addr:street":"Ark Way",
    "iso:country":"US",
    "sg:address":"630 Ark Way",
    "sg:city":"Sacramento",
    "sg:classifiers":[
        {
            "category":"Health Services",
            "subcategory":"Health Practitioner",
            "type":"Services"
        }
    ],
    "sg:phone":"+1 800 516 3535",
    "sg:postcode":"95831",
    "sg:province":"CA",
    "sg:tags":[
        "control",
        "weight"
    ],
    "sg:website":"http://www.weightwatchers.com/Index.aspx?cid=YP",
    "wof:name":"Weight Watchers - Sacramento",
    "wof:placetype":"venue"
},
  "geometry": {"coordinates":[-121.53811899999999,38.501129],"type":"Point"}
}