{
  "type": "Feature",
  "properties": {
    "iso:country":"US",
    "sg:address":"1675 Willow St",
    "sg:city":"San Jose",
    "sg:classifiers":[
        {
            "category":"Health Services",
            "subcategory":"Dentist",
            "type":"Services"
        }
    ],
    "sg:phone":"+1 408 264 8700",
    "sg:postcode":"95125",
    "sg:province":"CA",
    "sg:website":"willowdentistry.com",
    "wof:name":"Willow Dental Care",
    "wof:placetype":"venue"
},
  "geometry": {"coordinates":[-121.916434,37.303171],"type":"Point"}
}