{
  "type": "Feature",
  "properties": {
    "addr:full":"1844 14th St Santa Monica CA 90404",
    "addr:housenumber":"1844",
    "addr:postcode":"90404",
    "addr:street":"14Th St",
    "iso:country":"US",
    "sg:address":"1844 14th St",
    "sg:city":"Santa Monica",
    "sg:classifiers":[
        {
            "category":"Personal",
            "subcategory":"Massage",
            "type":"Services"
        }
    ],
    "sg:phone":"+1 310 392 6711",
    "sg:postcode":"90404",
    "sg:province":"CA",
    "wof:name":"Golden Spa",
    "wof:placetype":"venue"
},
  "geometry": {"coordinates":[-118.478495,34.017879],"type":"Point"}
}