{
  "type": "Feature",
  "properties": {
    "addr:full":"1758 Taft Ave Los Angeles CA 90028",
    "addr:housenumber":"1758",
    "addr:postcode":"90028",
    "addr:street":"Taft Ave",
    "iso:country":"US",
    "sg:address":"1758 Taft Ave",
    "sg:city":"Los Angeles",
    "sg:classifiers":[
        {
            "category":"Arts & Performance",
            "subcategory":"Theater",
            "type":"Entertainment"
        }
    ],
    "sg:phone":"+1 323 464 3781",
    "sg:postcode":"90028",
    "sg:province":"CA",
    "sg:tags":[
        "television",
        "program",
        "producer"
    ],
    "wof:name":"H D Arends Productions",
    "wof:placetype":"venue"
},
  "geometry": {"coordinates":[-118.31466,34.104234],"type":"Point"}
}