{
  "type": "Feature",
  "properties": {
    "iso:country":"US",
    "sg:address":"1655 S El Camino Real",
    "sg:city":"San Mateo",
    "sg:classifiers":[
        {
            "category":"Banks & Credit Unions",
            "subcategory":"Bank",
            "type":"Services"
        }
    ],
    "sg:phone":"+1 650 312 7900",
    "sg:postcode":"94402",
    "sg:province":"CA",
    "sg:website":"www.usbank.com",
    "wof:name":"U S Bank",
    "wof:placetype":"venue"
},
  "geometry": {"coordinates":[-122.31441100000001,37.55275],"type":"Point"}
}