{
  "type": "Feature",
  "properties": {
    "addr:full":"210 San Antonio Rd Mountain View CA 94040",
    "addr:housenumber":"210",
    "addr:postcode":"94040",
    "addr:street":"San Antonio Rd",
    "iso:country":"US",
    "sg:address":"210 San Antonio Rd",
    "sg:city":"Mountain View",
    "sg:classifiers":[
        {
            "category":"Professional",
            "type":"Services"
        }
    ],
    "sg:phone":"+1 650 947 4942",
    "sg:postcode":"94040",
    "sg:province":"CA",
    "wof:name":"Agresti & Associates Inc",
    "wof:placetype":"venue"
},
  "geometry": {"coordinates":[-122.10891100000001,37.407728],"type":"Point"}
}