{
  "type": "Feature",
  "properties": {
    "iso:country":"US",
    "sg:address":"1915 Soquel Ave",
    "sg:city":"Santa Cruz",
    "sg:classifiers":[
        {
            "category":"Retail",
            "subcategory":"Auto Repair",
            "type":"Services"
        }
    ],
    "sg:phone":"+1 831 454 9388",
    "sg:postcode":"95062",
    "sg:province":"CA",
    "sg:website":"www.aamco.com",
    "wof:name":"AAMCO",
    "wof:placetype":"venue"
},
  "geometry": {"coordinates":[-121.999852,36.98157],"type":"Point"}
}