{
  "type": "Feature",
  "properties": {
    "addr:full":"665 H St Chula Vista CA 91910",
    "addr:housenumber":"665",
    "addr:postcode":"91910",
    "addr:street":"H St",
    "iso:country":"US",
    "sg:address":"665 H St",
    "sg:city":"Chula Vista",
    "sg:classifiers":[
        {
            "category":"Health Services",
            "subcategory":"Health Practitioner",
            "type":"Services"
        }
    ],
    "sg:phone":"+1 619 585 8559",
    "sg:postcode":"91910",
    "sg:province":"CA",
    "sg:tags":[
        "acupuncture"
    ],
    "wof:name":"Park Acupressure",
    "wof:placetype":"venue"
},
  "geometry": {"coordinates":[-117.09240200000001,32.630216],"type":"Point"}
}