{
  "type": "Feature",
  "properties": {
    "iso:country":"US",
    "sg:address":"116 N 3rd Ave",
    "sg:city":"Oakdale",
    "sg:phone":"+1 209 848 3297",
    "sg:postcode":"95361",
    "sg:province":"CA",
    "wof:name":"Days Remembered",
    "wof:placetype":"venue"
},
  "geometry": {"coordinates":[-120.84804699999999,37.766462],"type":"Point"}
}