{
  "type": "Feature",
  "properties": {
    "iso:country":"US",
    "sg:address":"50434 Whitaker Forest Rd",
    "sg:city":"Badger",
    "sg:classifiers":[
        {
            "category":"Restaurant",
            "type":"Food & Drink"
        }
    ],
    "sg:phone":"+1 559 337 0034",
    "sg:postcode":"93603",
    "sg:province":"CA",
    "wof:name":"Sierra Glen Store",
    "wof:placetype":"venue"
},
  "geometry": {"coordinates":[-118.992267,36.656569],"type":"Point"}
}