{
  "type": "Feature",
  "properties": {
    "addr:full":"11345 San Pablo Ave El Cerrito CA 94530",
    "addr:housenumber":"11345",
    "addr:postcode":"94530",
    "addr:street":"San Pablo Ave",
    "iso:country":"US",
    "sg:address":"11345 San Pablo Ave",
    "sg:city":"El Cerrito",
    "sg:classifiers":[
        {
            "category":"Wholesale",
            "subcategory":"Non-durable Goods",
            "type":"Manufacturing & Wholesale Goods"
        }
    ],
    "sg:phone":"+1 510 658 0926",
    "sg:postcode":"94530",
    "sg:province":"CA",
    "sg:tags":[
        "button"
    ],
    "wof:name":"One Inch Round",
    "wof:placetype":"venue"
},
  "geometry": {"coordinates":[-122.315612,37.921161],"type":"Point"}
}