{
  "type": "Feature",
  "properties": {
    "iso:country":"US",
    "sg:address":"1029 K St Ste 25",
    "sg:city":"Sacramento",
    "sg:classifiers":[
        {
            "category":"Professional",
            "subcategory":"Business Services",
            "type":"Services"
        }
    ],
    "sg:phone":"+1 916 444 5551",
    "sg:postcode":"95814",
    "sg:province":"CA",
    "sg:tags":[
        "lobbyist"
    ],
    "wof:name":"Capital Alliance",
    "wof:placetype":"venue"
},
  "geometry": {"coordinates":[-121.493534,38.579109],"type":"Point"}
}