{
  "type": "Feature",
  "properties": {
    "iso:country":"US",
    "sg:address":"17220 Norwalk Blvd",
    "sg:city":"Cerritos",
    "sg:classifiers":[
        {
            "category":"Restaurant",
            "type":"Food & Drink"
        }
    ],
    "sg:phone":"+1 562 924 4600",
    "sg:postcode":"90703",
    "sg:province":"CA",
    "sg:tags":[
        "filipino"
    ],
    "wof:name":"Mabuhay Kitchen",
    "wof:placetype":"venue"
},
  "geometry": {"coordinates":[-118.072575,33.873799],"type":"Point"}
}