{
  "type": "Feature",
  "properties": {
    "addr:full":"1670 Lupton Ave San Jose CA 95125",
    "addr:housenumber":"1670",
    "addr:postcode":"95125",
    "addr:street":"Lupton Ave",
    "iso:country":"US",
    "sg:address":"1670 Lupton Ave",
    "sg:city":"San Jose",
    "sg:classifiers":[
        {
            "category":"Manufacturing",
            "subcategory":"Printing",
            "type":"Manufacturing & Wholesale Goods"
        }
    ],
    "sg:phone":"+1 408 269 9969",
    "sg:postcode":"95125",
    "sg:province":"CA",
    "sg:tags":[
        "book"
    ],
    "wof:name":"Kindred Publishing",
    "wof:placetype":"venue"
},
  "geometry": {"coordinates":[-121.901523,37.295217],"type":"Point"}
}