{
  "type": "Feature",
  "properties": {
    "iso:country":"US",
    "sg:address":"1556 N Cahuenga Blvd",
    "sg:city":"Los Angeles",
    "sg:classifiers":[
        {
            "category":"Restaurant",
            "type":"Food & Drink"
        }
    ],
    "sg:phone":"+1 323 464 6555",
    "sg:postcode":"90028",
    "sg:province":"CA",
    "sg:tags":[
        "eating"
    ],
    "wof:name":"Astoria Restaurant",
    "wof:placetype":"venue"
},
  "geometry": {"coordinates":[-118.32944000000001,34.098754],"type":"Point"}
}