{
  "type": "Feature",
  "properties": {
    "iso:country":"US",
    "sg:address":"3385 Westridge Dr",
    "sg:city":"Kelseyville",
    "sg:classifiers":[
        {
            "category":"Wholesale",
            "subcategory":"Furniture",
            "type":"Manufacturing & Wholesale Goods"
        }
    ],
    "sg:phone":"+1 707 279 2145",
    "sg:postcode":"95451",
    "sg:province":"CA",
    "sg:tags":[
        "furniture-wholesale",
        "manufacturer"
    ],
    "wof:name":"Moe's Wholesale Inc.",
    "wof:placetype":"venue"
},
  "geometry": {"coordinates":[-122.783895,39.002549],"type":"Point"}
}