{
  "type": "Feature",
  "properties": {
    "iso:country":"US",
    "sg:address":"12171 Slate Creek Rd",
    "sg:city":"Nevada City",
    "sg:classifiers":[
        {
            "category":"Autos & Motor Vehicles",
            "subcategory":"Auto Supplies",
            "type":"Retail Goods"
        }
    ],
    "sg:phone":"+1 530 274 3811",
    "sg:postcode":"95959",
    "sg:province":"CA",
    "sg:tags":[
        "automobile",
        "parts"
    ],
    "wof:name":"Mustang Parts By Mr Mustang",
    "wof:placetype":"venue"
},
  "geometry": {"coordinates":[-121.068631,39.244761],"type":"Point"}
}