{
  "type": "Feature",
  "properties": {
    "addr:full":"2425 Vine St Paso Robles CA 93446",
    "addr:housenumber":"2425",
    "addr:postcode":"93446",
    "addr:street":"Vine St",
    "iso:country":"US",
    "sg:address":"2425 Vine St",
    "sg:city":"Paso Robles",
    "sg:classifiers":[
        {
            "category":"Shopping",
            "subcategory":"Gifts & Souvenirs",
            "type":"Retail Goods"
        }
    ],
    "sg:phone":"+1 805 467 0083",
    "sg:postcode":"93446",
    "sg:province":"CA",
    "sg:tags":[
        "shop"
    ],
    "wof:name":"Sassy Gals Gifts & Treasures",
    "wof:placetype":"venue"
},
  "geometry": {"coordinates":[-120.695217,35.641377],"type":"Point"}
}