{
  "type": "Feature",
  "properties": {
    "iso:country":"US",
    "sg:address":"3949 Cochran St",
    "sg:city":"Simi Valley",
    "sg:classifiers":[
        {
            "category":"Retail",
            "subcategory":"Laundry & Dry Cleaning",
            "type":"Services"
        }
    ],
    "sg:phone":"+1 805 522 0955",
    "sg:postcode":"93063",
    "sg:province":"CA",
    "sg:tags":[
        "cleaners"
    ],
    "wof:name":"Tempo Alterations & Dry Clean",
    "wof:placetype":"venue"
},
  "geometry": {"coordinates":[-118.718143,34.279106],"type":"Point"}
}