{
  "type": "Feature",
  "properties": {
    "iso:country":"US",
    "sg:address":"4121 Westerly Pl",
    "sg:city":"Newport Beach",
    "sg:classifiers":[
        {
            "category":"Real Estate",
            "subcategory":"Real Estate Agent",
            "type":"Services"
        }
    ],
    "sg:phone":"+1 949 553 1922",
    "sg:postcode":"92660",
    "sg:province":"CA",
    "wof:name":"Belvedere Properties",
    "wof:placetype":"venue"
},
  "geometry": {"coordinates":[-117.868639,33.662957],"type":"Point"}
}