{
  "type": "Feature",
  "properties": {
    "iso:country":"US",
    "sg:address":"1550 Rimpau Ave",
    "sg:city":"Corona",
    "sg:classifiers":[
        {
            "category":"Farming",
            "subcategory":"Livestock Farm",
            "type":"Manufacturing & Wholesale Goods"
        }
    ],
    "sg:phone":"+1 951 278 8451",
    "sg:postcode":"92881",
    "sg:province":"CA",
    "sg:tags":[
        "hog",
        "or",
        "feedlot"
    ],
    "wof:name":"Bottom Feeder Productions",
    "wof:placetype":"venue"
},
  "geometry": {"coordinates":[-117.544636,33.861751],"type":"Point"}
}