{
  "type": "Feature",
  "properties": {
    "iso:country":"US",
    "sg:address":"385 North Rd",
    "sg:city":"Scotia",
    "sg:classifiers":[
        {
            "category":"Travel",
            "subcategory":"Campground",
            "type":"Entertainment"
        }
    ],
    "sg:phone":"+1 707 764 3416",
    "sg:postcode":"95565",
    "sg:province":"CA",
    "wof:name":"Stafford Rv Park",
    "wof:placetype":"venue"
},
  "geometry": {"coordinates":[-124.05332199999999,40.454415],"type":"Point"}
}