{
  "type": "Feature",
  "properties": {
    "addr:full":"4801 International Blvd Oakland CA 94601",
    "addr:housenumber":"4801",
    "addr:postcode":"94601",
    "addr:street":"International Blvd",
    "iso:country":"US",
    "sg:address":"4801 International Blvd",
    "sg:city":"Oakland",
    "sg:classifiers":[
        {
            "category":"Retail",
            "subcategory":"Repair Shop",
            "type":"Services"
        }
    ],
    "sg:phone":"+1 510 533 3171",
    "sg:postcode":"94601",
    "sg:province":"CA",
    "sg:tags":[
        "sharpening"
    ],
    "wof:name":"East Bay Saw & Knife Works",
    "wof:placetype":"venue"
},
  "geometry": {"coordinates":[-122.20972999999999,37.769997],"type":"Point"}
}