{
  "type": "Feature",
  "properties": {
    "iso:country":"US",
    "sg:address":"5712 Soquel Dr",
    "sg:city":"Soquel",
    "sg:classifiers":[
        {
            "category":"Local Transit",
            "type":"Transportation"
        }
    ],
    "sg:phone":"+1 831 464 1969",
    "sg:postcode":"95073",
    "sg:province":"CA",
    "sg:tags":[
        "airport"
    ],
    "wof:name":"Coastal Express Transportation",
    "wof:placetype":"venue"
},
  "geometry": {"coordinates":[-121.939731,36.987712],"type":"Point"}
}