{
  "type": "Feature",
  "properties": {
    "addr:full":"5712 Soquel Dr Soquel CA 95073",
    "addr:housenumber":"5712",
    "addr:postcode":"95073",
    "addr:street":"Soquel Dr",
    "iso:country":"US",
    "sg:address":"5712 Soquel Dr",
    "sg:city":"Soquel",
    "sg:classifiers":[
        {
            "category":"Local Transit",
            "type":"Transportation"
        }
    ],
    "sg:phone":"+1 831 464 1969",
    "sg:postcode":"95073",
    "sg:province":"CA",
    "sg:tags":[
        "airport"
    ],
    "wof:name":"Coastal Express Transportation",
    "wof:placetype":"venue"
},
  "geometry": {"coordinates":[-121.93973099999999,36.987712],"type":"Point"}
}