{
  "type": "Feature",
  "properties": {
    "iso:country":"US",
    "sg:address":"201 W Collins Ave",
    "sg:city":"Orange",
    "sg:classifiers":[
        {
            "category":"Freight",
            "type":"Transportation"
        }
    ],
    "sg:phone":"+1 714 269 8931",
    "sg:postcode":"92867",
    "sg:province":"CA",
    "sg:tags":[
        "trucking"
    ],
    "wof:name":"Bothwell Trucking",
    "wof:placetype":"venue"
},
  "geometry": {"coordinates":[-117.853103,33.802384],"type":"Point"}
}