{
  "type": "Feature",
  "properties": {
    "addr:full":"2285 Mission St San Francisco CA 94110",
    "addr:housenumber":"2285",
    "addr:postcode":"94110",
    "addr:street":"Mission St",
    "iso:country":"US",
    "sg:address":"2285 Mission St",
    "sg:city":"San Francisco",
    "sg:classifiers":[
        {
            "category":"Shopping",
            "subcategory":"Jewelry",
            "type":"Retail Goods"
        }
    ],
    "sg:phone":"+1 415 648 1136",
    "sg:postcode":"94110",
    "sg:province":"CA",
    "sg:tags":[
        "jeweler"
    ],
    "wof:name":"Ken Jewelry",
    "wof:placetype":"venue"
},
  "geometry": {"coordinates":[-122.419235,37.761612],"type":"Point"}
}