{
  "type": "Feature",
  "properties": {
    "addr:full":"14320 Ventura Blvd Ste 201 Sherman Oaks CA 91423",
    "addr:housenumber":"14320",
    "addr:postcode":"91423",
    "addr:street":"Ventura Blvd Ste 201",
    "iso:country":"US",
    "sg:address":"14320 Ventura Blvd Ste 201",
    "sg:city":"Sherman Oaks",
    "sg:classifiers":[
        {
            "category":"Professional",
            "type":"Services"
        }
    ],
    "sg:phone":"+1 310 512 6077",
    "sg:postcode":"91423",
    "sg:province":"CA",
    "sg:tags":[
        "caterer"
    ],
    "sg:website":"www.artfulfoodscatering.com",
    "wof:name":"Artful Foods Catering Inc",
    "wof:placetype":"venue"
},
  "geometry": {"coordinates":[-118.445273,34.150329],"type":"Point"}
}