{
  "type": "Feature",
  "properties": {
    "iso:country":"US",
    "sg:address":"1300 Barham Dr",
    "sg:city":"San Marcos",
    "sg:classifiers":[
        {
            "category":"Building & Trades",
            "subcategory":"Construction",
            "type":"Services"
        }
    ],
    "sg:phone":"+1 760 741 0996",
    "sg:postcode":"92078",
    "sg:province":"CA",
    "sg:tags":[
        "paving",
        "contractor"
    ],
    "wof:name":"Hogue's Grading & Paving",
    "wof:placetype":"venue"
},
  "geometry": {"coordinates":[-117.132846,33.134804],"type":"Point"}
}