{
  "type": "Feature",
  "properties": {
    "iso:country":"US",
    "sg:address":"17160 Colima Rd",
    "sg:city":"Hacienda Heights",
    "sg:classifiers":[
        {
            "category":"Banks & Credit Unions",
            "subcategory":"Bank",
            "type":"Services"
        }
    ],
    "sg:phone":"+1 626 839 1971",
    "sg:postcode":"91745",
    "sg:province":"CA",
    "sg:website":"www.wamu.com",
    "wof:name":"Washington Mutual",
    "wof:placetype":"venue"
},
  "geometry": {"coordinates":[-117.934563,33.990809],"type":"Point"}
}