{
  "type": "Feature",
  "properties": {
    "iso:country":"US",
    "sg:address":"4900 California Ave",
    "sg:city":"Bakersfield",
    "sg:classifiers":[
        {
            "category":"Mining & Drilling",
            "type":"Manufacturing & Wholesale Goods"
        }
    ],
    "sg:phone":"+1 661 633 4272",
    "sg:postcode":"93309",
    "sg:province":"CA",
    "sg:tags":[
        "field"
    ],
    "wof:name":"Hunting-Vinson",
    "wof:placetype":"venue"
},
  "geometry": {"coordinates":[-119.05573699999999,35.364768],"type":"Point"}
}