{
  "type": "Feature",
  "properties": {
    "addr:full":"22231 Erwin St. Los Angeles CA 91367",
    "addr:housenumber":"22231",
    "addr:postcode":"91367",
    "addr:street":"Erwin St.",
    "iso:country":"US",
    "sg:address":"22231 Erwin St.",
    "sg:city":"Los Angeles",
    "sg:classifiers":[
        {
            "category":"Professional",
            "subcategory":"Lawyer & Legal Services",
            "type":"Services"
        },
        {
            "category":"Professional",
            "subcategory":"Business Services",
            "type":"Services"
        }
    ],
    "sg:phone":"+1 818 917 0598",
    "sg:postcode":"91367",
    "sg:province":"CA",
    "sg:tags":[
        "delivery",
        "notary",
        "courier"
    ],
    "sg:website":"ca.local.yahoo.biz/actiontraveli...",
    "wof:name":"Action Mobile Notary & Finger Printing",
    "wof:placetype":"venue"
},
  "geometry": {"coordinates":[-118.61071099999999,34.182831],"type":"Point"}
}