{
  "type": "Feature",
  "properties": {
    "iso:country":"US",
    "sg:address":"1510 E Caroline St",
    "sg:city":"Ontario",
    "sg:classifiers":[
        {
            "category":"Professional",
            "subcategory":"Business Services",
            "type":"Services"
        }
    ],
    "sg:phone":"+1 909 946 3371",
    "sg:postcode":"91764",
    "sg:province":"CA",
    "sg:tags":[
        "drafting"
    ],
    "wof:name":"Casablanca West",
    "wof:placetype":"venue"
},
  "geometry": {"coordinates":[-117.62272400000001,34.086722],"type":"Point"}
}