{
  "type": "Feature",
  "properties": {
    "addr:full":"5708 E. 7th St. Long Beach CA 90803",
    "addr:housenumber":"5708",
    "addr:postcode":"90803",
    "addr:street":"E. 7Th St.",
    "iso:country":"US",
    "sg:address":"5708 E. 7th St.",
    "sg:city":"Long Beach",
    "sg:classifiers":[
        {
            "category":"Restaurant",
            "type":"Food & Drink"
        }
    ],
    "sg:phone":"+1 562 494 0003",
    "sg:postcode":"90803",
    "sg:province":"CA",
    "sg:tags":[
        "korean"
    ],
    "sg:website":"californiateriyakigrill.com",
    "wof:name":"California Teriyaki Grill",
    "wof:placetype":"venue"
},
  "geometry": {"coordinates":[-118.120825,33.775241],"type":"Point"}
}