{
  "type": "Feature",
  "properties": {
    "addr:full":"1538 E Adams Ave Apt L Orange CA 92867",
    "addr:housenumber":"1538",
    "addr:postcode":"92867",
    "addr:street":"E Adams Ave Apt L",
    "iso:country":"US",
    "sg:address":"1538 E Adams Ave Apt L",
    "sg:city":"Orange",
    "sg:classifiers":[
        {
            "category":"Real Estate",
            "subcategory":"Real Estate Operator",
            "type":"Services"
        }
    ],
    "sg:phone":"+1 714 771 3227",
    "sg:postcode":"92867",
    "sg:province":"CA",
    "sg:tags":[
        "apartment"
    ],
    "wof:name":"Las Verandes Apartments",
    "wof:placetype":"venue"
},
  "geometry": {"coordinates":[-117.83699799999999,33.806599],"type":"Point"}
}