{
  "type": "Feature",
  "properties": {
    "addr:full":"1551 Baker Street Costa Mesa CA 92626",
    "addr:housenumber":"1551",
    "addr:postcode":"92626",
    "addr:street":"Baker Street",
    "iso:country":"US",
    "sg:address":"1551 Baker Street",
    "sg:city":"Costa Mesa",
    "sg:classifiers":[
        {
            "category":"Real Estate",
            "subcategory":"Real Estate Services",
            "type":"Services"
        }
    ],
    "sg:phone":"+1 714 434 2590",
    "sg:postcode":"92626",
    "sg:province":"CA",
    "sg:tags":[
        "management",
        "property"
    ],
    "wof:name":"Gold Crown Real Estate Services",
    "wof:placetype":"venue"
},
  "geometry": {"coordinates":[-117.921254,33.680314],"type":"Point"}
}