{
  "type": "Feature",
  "properties": {
    "addr:full":"2326 W Whittier Blvd Montebello CA 90640",
    "addr:housenumber":"2326",
    "addr:postcode":"90640",
    "addr:street":"W Whittier Blvd",
    "iso:country":"US",
    "sg:address":"2326 W Whittier Blvd",
    "sg:city":"Montebello",
    "sg:classifiers":[
        {
            "category":"Insurance",
            "subcategory":"Insurance Agent",
            "type":"Services"
        }
    ],
    "sg:phone":"+1 323 720 1000",
    "sg:postcode":"90640",
    "sg:province":"CA",
    "wof:name":"Alto Insurance Brokerage",
    "wof:placetype":"venue"
},
  "geometry": {"coordinates":[-118.125739,34.013773],"type":"Point"}
}