{
  "type": "Feature",
  "properties": {
    "addr:full":"2008 Canal Ave Long Beach CA 90810",
    "addr:housenumber":"2008",
    "addr:postcode":"90810",
    "addr:street":"Canal Ave",
    "iso:country":"US",
    "sg:address":"2008 Canal Ave",
    "sg:city":"Long Beach",
    "sg:classifiers":[
        {
            "category":"Building & Trades",
            "subcategory":"Construction",
            "type":"Services"
        }
    ],
    "sg:phone":"+1 562 437 7600",
    "sg:postcode":"90810",
    "sg:province":"CA",
    "sg:tags":[
        "contractor"
    ],
    "wof:name":"Angel Menendez Environ Svc",
    "wof:placetype":"venue"
},
  "geometry": {"coordinates":[-118.21372,33.795156],"type":"Point"}
}