{
  "type": "Feature",
  "properties": {
    "addr:full":"3181 Imperial Hwy Lynwood CA 90262",
    "addr:housenumber":"3181",
    "addr:postcode":"90262",
    "addr:street":"Imperial Hwy",
    "iso:country":"US",
    "sg:address":"3181 Imperial Hwy",
    "sg:city":"Lynwood",
    "sg:classifiers":[
        {
            "category":"Health Services",
            "subcategory":"Health Practitioner",
            "type":"Services"
        }
    ],
    "sg:phone":"+1 310 605 5152",
    "sg:postcode":"90262",
    "sg:province":"CA",
    "sg:tags":[
        "nutritionist"
    ],
    "wof:name":"HNC Ciglo 21",
    "wof:placetype":"venue"
},
  "geometry": {"coordinates":[-118.212699,33.930331],"type":"Point"}
}