{
  "type": "Feature",
  "properties": {
    "iso:country":"US",
    "sg:address":"660 S Fitch Mountain Rd",
    "sg:city":"Healdsburg",
    "sg:classifiers":[
        {
            "category":"Professional",
            "subcategory":"Lawyer & Legal Services",
            "type":"Services"
        }
    ],
    "sg:phone":"+1 707 431 0235",
    "sg:postcode":"95448",
    "sg:province":"CA",
    "sg:tags":[
        "attorney"
    ],
    "wof:name":"Mark D Swendsen",
    "wof:placetype":"venue"
},
  "geometry": {"coordinates":[-122.85701400000001,38.611285],"type":"Point"}
}