{
  "type": "Feature",
  "properties": {
    "iso:country":"US",
    "sg:address":"5175 Linda Vista Rd",
    "sg:city":"San Diego",
    "sg:classifiers":[
        {
            "category":"Restaurant",
            "type":"Food & Drink"
        }
    ],
    "sg:menulink":"http://www.allmenus.com/ca/san-diego/59768-subway/menu/",
    "sg:phone":"+1 619 542 0118",
    "sg:postcode":"92110",
    "sg:province":"CA",
    "sg:tags":[
        "american",
        "sandwich"
    ],
    "wof:name":"Subway",
    "wof:placetype":"venue"
},
  "geometry": {"coordinates":[-117.19732,32.764826],"type":"Point"}
}