{
  "type": "Feature",
  "properties": {
    "addr:full":"2901 25th St Sacramento CA 95818",
    "addr:housenumber":"2901",
    "addr:postcode":"95818",
    "addr:street":"25Th St",
    "iso:country":"US",
    "sg:address":"2901 25th St",
    "sg:city":"Sacramento",
    "sg:classifiers":[
        {
            "category":"Professional",
            "subcategory":"Research",
            "type":"Services"
        }
    ],
    "sg:phone":"+1 916 455 8295",
    "sg:postcode":"95818",
    "sg:province":"CA",
    "sg:tags":[
        "educational"
    ],
    "wof:name":"Applied Educational Research",
    "wof:placetype":"venue"
},
  "geometry": {"coordinates":[-121.48165899999999,38.552502],"type":"Point"}
}