{
  "type": "Feature",
  "properties": {
    "addr:full":"255 S Lakeview Ave Placentia CA 92870",
    "addr:housenumber":"255",
    "addr:postcode":"ca 92870",
    "addr:street":"S Lakeview Ave",
    "iso:country":"US",
    "sg:address":"255 S Lakeview Ave",
    "sg:city":"Placentia",
    "sg:classifiers":[
        {
            "category":"Professional",
            "subcategory":"Lawyer & Legal Services",
            "type":"Services"
        }
    ],
    "sg:phone":"+1 714 572 8694",
    "sg:postcode":"92870",
    "sg:province":"CA",
    "wof:name":"Young Laura E Law Offices",
    "wof:placetype":"venue"
},
  "geometry": {"coordinates":[-117.822998,33.863701],"type":"Point"}
}