{
  "type": "Feature",
  "properties": {
    "addr:full":"516 Ave Teresa San Clemente CA 92672",
    "addr:housenumber":"516",
    "addr:postcode":"92672",
    "addr:street":"Ave Teresa",
    "iso:country":"US",
    "sg:address":"516 Ave Teresa",
    "sg:city":"San Clemente",
    "sg:classifiers":[
        {
            "category":"Building & Trades",
            "subcategory":"Electrical",
            "type":"Services"
        }
    ],
    "sg:phone":"+1 949 498 2059",
    "sg:postcode":"92672",
    "sg:province":"CA",
    "sg:tags":[
        "electrical",
        "contractor"
    ],
    "wof:name":"Pipe Line Electric Inc",
    "wof:placetype":"venue"
},
  "geometry": {"coordinates":[-117.604759,33.434506],"type":"Point"}
}