{
  "type": "Feature",
  "properties": {
    "addr:full":"436 E 17th St Costa Mesa CA 92627",
    "addr:housenumber":"436",
    "addr:postcode":"92627",
    "addr:street":"E 17Th St",
    "iso:country":"US",
    "sg:address":"436 E 17th St",
    "sg:city":"Costa Mesa",
    "sg:classifiers":[
        {
            "category":"Retail",
            "subcategory":"Animal Services",
            "type":"Services"
        }
    ],
    "sg:phone":"+1 949 722 8250",
    "sg:postcode":"92627",
    "sg:province":"CA",
    "wof:name":"CDM Dog Grooming",
    "wof:placetype":"venue"
},
  "geometry": {"coordinates":[-117.909775,33.629343],"type":"Point"}
}