{
  "type": "Feature",
  "properties": {
    "iso:country":"US",
    "sg:address":"12692 Nutwood St Ste A",
    "sg:city":"Garden Grove",
    "sg:classifiers":[
        {
            "category":"Retail",
            "subcategory":"Auto Repair",
            "type":"Services"
        }
    ],
    "sg:phone":"+1 714 636 2867",
    "sg:postcode":"92840",
    "sg:province":"CA",
    "wof:name":"T & V Auto Repair",
    "wof:placetype":"venue"
},
  "geometry": {"coordinates":[-117.949997,33.777802],"type":"Point"}
}