{
  "type": "Feature",
  "properties": {
    "iso:country":"US",
    "sg:address":"1744 Lorry Ln",
    "sg:city":"Escondido",
    "sg:classifiers":[
        {
            "category":"Personal",
            "type":"Services"
        }
    ],
    "sg:phone":"+1 858 775 0530",
    "sg:postcode":"92029",
    "sg:province":"CA",
    "sg:tags":[
        "consultant",
        "glass-wholesale",
        "program",
        "health",
        "fitness",
        "manufacturer"
    ],
    "wof:name":"Bus Logic",
    "wof:placetype":"venue"
},
  "geometry": {"coordinates":[-117.103711,33.100931],"type":"Point"}
}