{
  "type": "Feature",
  "properties": {
    "addr:full":"825 Harrison St Oakland CA 94607",
    "addr:housenumber":"825",
    "addr:postcode":"94607",
    "addr:street":"Harrison St",
    "iso:country":"US",
    "sg:address":"825 Harrison St",
    "sg:city":"Oakland",
    "sg:classifiers":[
        {
            "category":"Personal",
            "subcategory":"Beauty Salon",
            "type":"Services"
        }
    ],
    "sg:phone":"+1 510 208 3322",
    "sg:postcode":"94607",
    "sg:province":"CA",
    "sg:tags":[
        "hair"
    ],
    "wof:name":"David's Hair Design",
    "wof:placetype":"venue"
},
  "geometry": {"coordinates":[-122.269997,37.799301],"type":"Point"}
}