{
  "type": "Feature",
  "properties": {
    "addr:full":"1391 Yosemite Ave Manteca CA 95336",
    "addr:housenumber":"1391",
    "addr:postcode":"95336",
    "addr:street":"Yosemite Ave",
    "iso:country":"US",
    "sg:address":"1391 Yosemite Ave",
    "sg:city":"Manteca",
    "sg:classifiers":[
        {
            "category":"Food & Beverages",
            "subcategory":"Groceries & Convenience Stores",
            "type":"Retail Goods"
        }
    ],
    "sg:phone":"+1 209 823 8915",
    "sg:postcode":"95336",
    "sg:province":"CA",
    "sg:tags":[
        "market"
    ],
    "wof:name":"Big Boy Market",
    "wof:placetype":"venue"
},
  "geometry": {"coordinates":[-121.19701000000001,37.797542],"type":"Point"}
}