{
  "type": "Feature",
  "properties": {
    "iso:country":"US",
    "sg:address":"1391 Yosemite Ave",
    "sg:city":"Manteca",
    "sg:classifiers":[
        {
            "category":"Food & Beverages",
            "subcategory":"Groceries & Convenience Stores",
            "type":"Retail Goods"
        }
    ],
    "sg:phone":"+1 209 823 8915",
    "sg:postcode":"95336",
    "sg:province":"CA",
    "sg:tags":[
        "market"
    ],
    "wof:name":"Big Boy Market",
    "wof:placetype":"venue"
},
  "geometry": {"coordinates":[-121.19701,37.797542],"type":"Point"}
}