{
  "type": "Feature",
  "properties": {
    "addr:full":"800 Centinela Avenue Inglewood CA 90302",
    "addr:housenumber":"800",
    "addr:postcode":"90302",
    "addr:street":"Centinela Avenue",
    "iso:country":"US",
    "sg:address":"800 Centinela Avenue",
    "sg:city":"Inglewood",
    "sg:classifiers":[
        {
            "category":"Retail",
            "subcategory":"Auto Repair",
            "type":"Services"
        }
    ],
    "sg:phone":"+1 310 671 5111",
    "sg:postcode":"90302",
    "sg:province":"CA",
    "wof:name":"Estrada's Auto Repair",
    "wof:placetype":"venue"
},
  "geometry": {"coordinates":[-118.35314099999999,33.975921],"type":"Point"}
}