{
  "type": "Feature",
  "properties": {
    "iso:country":"US",
    "sg:address":"210 Cll Linda",
    "sg:city":"Fallbrook",
    "sg:classifiers":[
        {
            "category":"Professional",
            "type":"Services"
        }
    ],
    "sg:phone":"+1 760 728 6392",
    "sg:postcode":"92028",
    "sg:province":"CA",
    "wof:name":"Wayne E Allen",
    "wof:placetype":"venue"
},
  "geometry": {"coordinates":[-117.246971,33.316026],"type":"Point"}
}