{
  "type": "Feature",
  "properties": {
    "addr:full":"20068 Santa Ana Ave Costa Mesa CA 92626",
    "addr:postcode":"20068;92626",
    "addr:street":"Santa Ana Ave",
    "iso:country":"US",
    "sg:address":"20068 Santa Ana Ave",
    "sg:city":"Costa Mesa",
    "sg:classifiers":[
        {
            "category":"Personal",
            "subcategory":"Massage",
            "type":"Services"
        }
    ],
    "sg:phone":"+1 714 486 2436",
    "sg:postcode":"92626",
    "sg:province":"CA",
    "wof:name":"New Ocean Day Spa",
    "wof:placetype":"venue"
},
  "geometry": {"coordinates":[-117.887601,33.660979],"type":"Point"}
}