{
  "type": "Feature",
  "properties": {
    "addr:full":"383 Bay St San Francisco CA 94133",
    "addr:housenumber":"383",
    "addr:postcode":"94133",
    "addr:street":"Bay St",
    "iso:country":"US",
    "sg:address":"383 Bay St",
    "sg:city":"San Francisco",
    "sg:classifiers":[
        {
            "category":"Professional",
            "type":"Services"
        }
    ],
    "sg:phone":"+1 415 558 8903",
    "sg:postcode":"94133",
    "sg:province":"CA",
    "wof:name":"Asia Pacific Entrmt II LLC",
    "wof:placetype":"venue"
},
  "geometry": {"coordinates":[-122.412498,37.805717],"type":"Point"}
}