{
  "type": "Feature",
  "properties": {
    "addr:full":"5266 Blank Rd Sebastopol CA 95472",
    "addr:housenumber":"5266",
    "addr:postcode":"95472",
    "addr:street":"Blank Rd",
    "iso:country":"US",
    "sg:address":"5266 Blank Rd",
    "sg:city":"Sebastopol",
    "sg:classifiers":[
        {
            "category":"Building & Trades",
            "subcategory":"Construction",
            "type":"Services"
        }
    ],
    "sg:phone":"+1 707 823 3142",
    "sg:postcode":"95472",
    "sg:province":"CA",
    "sg:tags":[
        "contractor"
    ],
    "wof:name":"W S Barnes Construction",
    "wof:placetype":"venue"
},
  "geometry": {"coordinates":[-122.781147,38.338203],"type":"Point"}
}