{
  "type": "Feature",
  "properties": {
    "addr:full":"17901 S Vermont Avenue Gardena CA 90248",
    "addr:housenumber":"17901",
    "addr:postcode":"90248",
    "addr:street":"S Vermont Avenue",
    "iso:country":"US",
    "sg:address":"17901 S Vermont Avenue",
    "sg:city":"Gardena",
    "sg:classifiers":[
        {
            "category":"Shopping",
            "subcategory":"Mobile Phones",
            "type":"Retail Goods"
        }
    ],
    "sg:phone":"+1 310 327 1341",
    "sg:postcode":"90248",
    "sg:province":"CA",
    "wof:name":"S K Wireless",
    "wof:placetype":"venue"
},
  "geometry": {"coordinates":[-118.29047,33.867705],"type":"Point"}
}