{
  "type": "Feature",
  "properties": {
    "iso:country":"US",
    "sg:address":"1707 California St",
    "sg:city":"Stockton",
    "sg:classifiers":[
        {
            "category":"Health Services",
            "subcategory":"Doctor",
            "type":"Services"
        }
    ],
    "sg:phone":"+1 209 466 8546",
    "sg:postcode":"95204",
    "sg:province":"CA",
    "sg:tags":[
        "physician",
        "surgeon"
    ],
    "wof:name":"Gill Obstetrics & Gynecology",
    "wof:placetype":"venue"
},
  "geometry": {"coordinates":[-121.289314,37.970679],"type":"Point"}
}