{
  "type": "Feature",
  "properties": {
    "addr:full":"22 Rolling Green Cir Pleasant Hill CA 94523",
    "addr:housenumber":"22",
    "addr:postcode":"94523",
    "addr:street":"Rolling Green Cir",
    "iso:country":"US",
    "sg:address":"22 Rolling Green Cir",
    "sg:city":"Pleasant Hill",
    "sg:classifiers":[
        {
            "category":"Professional",
            "type":"Services"
        }
    ],
    "sg:phone":"+1 925 363 4802",
    "sg:postcode":"94523",
    "sg:province":"CA",
    "sg:tags":[
        "establishment"
    ],
    "wof:name":"Dianna Rowley Instruction",
    "wof:placetype":"venue"
},
  "geometry": {"coordinates":[-122.076357,37.946461],"type":"Point"}
}