{
  "type": "Feature",
  "properties": {
    "addr:full":"32513 Sheila Way Union City CA 94587",
    "addr:postcode":"32513;94587",
    "addr:street":"Sheila Way",
    "iso:country":"US",
    "sg:address":"32513 Sheila Way",
    "sg:city":"Union City",
    "sg:classifiers":[
        {
            "category":"Freight",
            "type":"Transportation"
        }
    ],
    "sg:phone":"+1 510 489 5286",
    "sg:postcode":"94587",
    "sg:province":"CA",
    "sg:tags":[
        "trucking"
    ],
    "wof:name":"Cam Trucking",
    "wof:placetype":"venue"
},
  "geometry": {"coordinates":[-122.073712,37.575827],"type":"Point"}
}