{
  "type": "Feature",
  "properties": {
    "addr:full":"418 Colyton Street Los Angeles CA 90013",
    "addr:housenumber":"418",
    "addr:postcode":"90013",
    "addr:street":"Colyton Street",
    "iso:country":"US",
    "sg:address":"418 Colyton Street",
    "sg:city":"Los Angeles",
    "sg:classifiers":[
        {
            "category":"Wholesale",
            "subcategory":"Fruits & Vegetables",
            "type":"Manufacturing & Wholesale Goods"
        }
    ],
    "sg:phone":"+1 213 617 0265",
    "sg:postcode":"90013",
    "sg:province":"CA",
    "sg:tags":[
        "veggie"
    ],
    "wof:name":"Soleil Produce",
    "wof:placetype":"venue"
},
  "geometry": {"coordinates":[-118.236566,34.042997],"type":"Point"}
}