{
  "type": "Feature",
  "properties": {
    "addr:full":"1305 S Railroad Ave San Mateo CA 94402",
    "addr:housenumber":"1305",
    "addr:postcode":"94402",
    "addr:street":"S Railroad Ave",
    "iso:country":"US",
    "sg:address":"1305 S Railroad Ave",
    "sg:city":"San Mateo",
    "sg:classifiers":[
        {
            "category":"Professional",
            "subcategory":"Art Services",
            "type":"Services"
        }
    ],
    "sg:phone":"+1 650 525 1920",
    "sg:postcode":"94402",
    "sg:province":"CA",
    "sg:tags":[
        "commercial",
        "marking",
        "design",
        "devices",
        "mfg"
    ],
    "wof:name":"Screend Printz",
    "wof:placetype":"venue"
},
  "geometry": {"coordinates":[-122.313301,37.559206],"type":"Point"}
}