{
  "type": "Feature",
  "properties": {
    "iso:country":"US",
    "sg:address":"10915 Thienes Ave",
    "sg:city":"South El Monte",
    "sg:classifiers":[
        {
            "category":"Wholesale",
            "subcategory":"Auto Parts",
            "type":"Manufacturing & Wholesale Goods"
        }
    ],
    "sg:phone":"+1 626 575 3935",
    "sg:postcode":"91733",
    "sg:province":"CA",
    "sg:tags":[
        "new",
        "vehicle",
        "motor",
        "supply"
    ],
    "wof:name":"J P Q Corp",
    "wof:placetype":"venue"
},
  "geometry": {"coordinates":[-118.037611,34.047224],"type":"Point"}
}