{
  "type": "Feature",
  "properties": {
    "iso:country":"US",
    "sg:address":"11050 Burbank Blvd",
    "sg:city":"North Hollywood",
    "sg:classifiers":[
        {
            "category":"Retail",
            "subcategory":"Auto Repair",
            "type":"Services"
        }
    ],
    "sg:phone":"+1 818 763 5549",
    "sg:postcode":"91601",
    "sg:province":"CA",
    "sg:tags":[
        "automobile",
        "top",
        "upholstery"
    ],
    "wof:name":"Burbank Auto Upholstery",
    "wof:placetype":"venue"
},
  "geometry": {"coordinates":[-118.37301600000001,34.172157],"type":"Point"}
}