{
  "type": "Feature",
  "properties": {
    "iso:country":"US",
    "sg:address":"1071 Shafter St",
    "sg:city":"San Diego",
    "sg:classifiers":[
        {
            "category":"Autos & Motor Vehicles",
            "subcategory":"Automobile Sales",
            "type":"Retail Goods"
        }
    ],
    "sg:phone":"+1 858 344 6112",
    "sg:postcode":"92106",
    "sg:province":"CA",
    "sg:tags":[
        "used"
    ],
    "wof:name":"Fts Auto Sales",
    "wof:placetype":"venue"
},
  "geometry": {"coordinates":[-117.230002,32.719953],"type":"Point"}
}