{
  "type": "Feature",
  "properties": {
    "addr:full":"1045 N Garey Ave Pomona CA 91767",
    "addr:housenumber":"1045",
    "addr:postcode":"91767",
    "addr:street":"N Garey Ave",
    "iso:country":"US",
    "sg:address":"1045 N Garey Ave",
    "sg:city":"Pomona",
    "sg:classifiers":[
        {
            "category":"Food & Beverages",
            "subcategory":"Groceries & Convenience Stores",
            "type":"Retail Goods"
        }
    ],
    "sg:phone":"+1 909 629 9244",
    "sg:postcode":"91767",
    "sg:province":"CA",
    "sg:tags":[
        "grocer"
    ],
    "wof:name":"Stater Bros Markets",
    "wof:placetype":"venue"
},
  "geometry": {"coordinates":[-117.752112,34.068267],"type":"Point"}
}