{
  "type": "Feature",
  "properties": {
    "iso:country":"US",
    "sg:address":"1929 Hollister St",
    "sg:city":"Ceres",
    "sg:classifiers":[
        {
            "category":"Arts & Performance",
            "subcategory":"Theater",
            "type":"Entertainment"
        }
    ],
    "sg:phone":"+1 209 324 6567",
    "sg:postcode":"95307",
    "sg:province":"CA",
    "sg:tags":[
        "live",
        "music"
    ],
    "wof:name":"Nitelife Mobile DJ Entrtn",
    "wof:placetype":"venue"
},
  "geometry": {"coordinates":[-120.95989,37.59906],"type":"Point"}
}