{
  "type": "Feature",
  "properties": {
    "addr:full":"925 W Washington St San Diego CA 92103",
    "addr:housenumber":"925",
    "addr:postcode":"92103",
    "addr:street":"W Washington St",
    "iso:country":"US",
    "sg:address":"925 W Washington St",
    "sg:city":"San Diego",
    "sg:classifiers":[
        {
            "category":"Education",
            "subcategory":"Library",
            "type":"Public Place"
        }
    ],
    "sg:phone":"+1 619 692 4910",
    "sg:postcode":"92103",
    "sg:province":"CA",
    "sg:website":"www.library92103.org",
    "wof:name":"San Diego Public Library Mission HIlls Branch",
    "wof:placetype":"venue"
},
  "geometry": {"coordinates":[-117.171606,32.749769],"type":"Point"}
}