{
  "type": "Feature",
  "properties": {
    "addr:full":"1093 Greta St El Cajon CA 92021",
    "addr:housenumber":"1093",
    "addr:postcode":"92021",
    "addr:street":"Greta St",
    "iso:country":"US",
    "sg:address":"1093 Greta St",
    "sg:city":"El Cajon",
    "sg:classifiers":[
        {
            "category":"Manufacturing",
            "subcategory":"Printing",
            "type":"Manufacturing & Wholesale Goods"
        }
    ],
    "sg:phone":"+1 619 447 6827",
    "sg:postcode":"92021",
    "sg:province":"CA",
    "sg:tags":[
        "publisher"
    ],
    "wof:name":"Know News",
    "wof:placetype":"venue"
},
  "geometry": {"coordinates":[-116.947233,32.817329],"type":"Point"}
}