{
  "type": "Feature",
  "properties": {
    "iso:country":"US",
    "sg:address":"2841 E Lincoln Ave",
    "sg:city":"Anaheim",
    "sg:classifiers":[
        {
            "category":"Real Estate",
            "subcategory":"Real Estate Services",
            "type":"Services"
        },
        {
            "category":"Real Estate",
            "subcategory":"Real Estate Operator",
            "type":"Services"
        }
    ],
    "sg:phone":"+1 714 630 2392",
    "sg:postcode":"92806",
    "sg:province":"CA",
    "sg:tags":[
        "vacancy",
        "apartment",
        "rental",
        "finder",
        "listing"
    ],
    "wof:name":"Campton Place",
    "wof:placetype":"venue"
},
  "geometry": {"coordinates":[-117.86914400000001,33.836825],"type":"Point"}
}