{
  "type": "Feature",
  "properties": {
    "addr:full":"12121 Wilshire Blvd Ste 1200 Los Angeles CA 90025",
    "addr:housenumber":"12121",
    "addr:postcode":"90025",
    "addr:street":"Wilshire Blvd Ste 1200",
    "iso:country":"US",
    "sg:address":"12121 Wilshire Blvd Ste 1200",
    "sg:city":"Los Angeles",
    "sg:classifiers":[
        {
            "category":"Communications",
            "subcategory":"Newspaper",
            "type":"Services"
        }
    ],
    "sg:phone":"+1 310 820 1500",
    "sg:postcode":"90025",
    "sg:province":"CA",
    "sg:tags":[
        "print",
        "medium"
    ],
    "wof:name":"Golf Tips",
    "wof:placetype":"venue"
},
  "geometry": {"coordinates":[-118.467758,34.40643],"type":"Point"}
}