{
  "type": "Feature",
  "properties": {
    "iso:country":"US",
    "sg:address":"313 Moreton Bay Ln",
    "sg:city":"Goleta",
    "sg:classifiers":[
        {
            "category":"Taxi",
            "type":"Transportation"
        }
    ],
    "sg:phone":"+1 805 452 4672",
    "sg:postcode":"93117",
    "sg:province":"CA",
    "sg:website":"http://www.taxisb.com",
    "wof:name":"Taxi Sb Com",
    "wof:placetype":"venue"
},
  "geometry": {"coordinates":[-119.82658499999999,34.444548],"type":"Point"}
}