{
  "type": "Feature",
  "properties": {
    "addr:full":"715 Pearl St La Jolla CA 92037",
    "addr:housenumber":"715",
    "addr:postcode":"92037",
    "addr:street":"Pearl St",
    "iso:country":"US",
    "sg:address":"715 Pearl St",
    "sg:city":"La Jolla",
    "sg:classifiers":[
        {
            "category":"Sports & Exercise",
            "subcategory":"Gym",
            "type":"Entertainment"
        }
    ],
    "sg:phone":"+1 858 729 9901",
    "sg:postcode":"92037",
    "sg:province":"CA",
    "sg:tags":[
        "personal",
        "trainer"
    ],
    "wof:name":"Perfect Workout",
    "wof:placetype":"venue"
},
  "geometry": {"coordinates":[-117.27564700000001,32.839688],"type":"Point"}
}