{
  "type": "Feature",
  "properties": {
    "iso:country":"US",
    "sg:address":"17904 Foothill Blvd",
    "sg:city":"Fontana",
    "sg:classifiers":[
        {
            "category":"Health Services",
            "subcategory":"Medical Lab",
            "type":"Services"
        }
    ],
    "sg:phone":"+1 909 357 6009",
    "sg:postcode":"92335",
    "sg:province":"CA",
    "sg:tags":[
        "laboratory"
    ],
    "wof:name":"Robert Dental Ceramics",
    "wof:placetype":"venue"
},
  "geometry": {"coordinates":[-117.412541,34.106783],"type":"Point"}
}