{
  "type": "Feature",
  "properties": {
    "addr:full":"42251 Sierra Hwy Lancaster CA 93535",
    "addr:housenumber":"42251",
    "addr:postcode":"93535",
    "addr:street":"Sierra Hwy",
    "iso:country":"US",
    "sg:address":"42251 Sierra Hwy",
    "sg:city":"Lancaster",
    "sg:classifiers":[
        {
            "category":"Building & Trades",
            "subcategory":"Construction",
            "type":"Services"
        }
    ],
    "sg:phone":"+1 661 948 2623",
    "sg:postcode":"93535",
    "sg:province":"CA",
    "sg:tags":[
        "ornamental",
        "work-supplies",
        "iron",
        "fence",
        "contractor"
    ],
    "sg:website":"http://www.buildersmart.com",
    "wof:name":"Sav-On Fence Co",
    "wof:placetype":"venue"
},
  "geometry": {"coordinates":[-118.128992,34.650425],"type":"Point"}
}