{
  "type": "Feature",
  "properties": {
    "iso:country":"US",
    "sg:address":"2935 E 2nd St",
    "sg:city":"Los Angeles",
    "sg:classifiers":[
        {
            "category":"Social Services",
            "subcategory":"Adult Care",
            "type":"Services"
        }
    ],
    "sg:phone":"+1 323 261 7295",
    "sg:postcode":"90033",
    "sg:province":"CA",
    "sg:tags":[
        "organization",
        "senior",
        "citizen"
    ],
    "wof:name":"Evergreen Senior Dining Ctr",
    "wof:placetype":"venue"
},
  "geometry": {"coordinates":[-118.202786,34.038768],"type":"Point"}
}