{
  "type": "Feature",
  "properties": {
    "addr:full":"2220 Mari Ln Petaluma CA 94954",
    "addr:housenumber":"2220",
    "addr:postcode":"94954",
    "addr:street":"Mari Ln",
    "iso:country":"US",
    "sg:address":"2220 Mari Ln",
    "sg:city":"Petaluma",
    "sg:classifiers":[
        {
            "category":"Personal",
            "type":"Services"
        },
        {
            "category":"Professional",
            "subcategory":"Art Services",
            "type":"Services"
        }
    ],
    "sg:phone":"+1 707 778 9043",
    "sg:postcode":"94954",
    "sg:province":"CA",
    "sg:tags":[
        "photography",
        "videography",
        "photographers-portrait",
        "wedding"
    ],
    "sg:website":"http://www.maryjeanmurphyphotography.com",
    "wof:name":"Mary Jean Murphy Photography",
    "wof:placetype":"venue"
},
  "geometry": {"coordinates":[-122.616141,38.258142],"type":"Point"}
}