{
  "type": "Feature",
  "properties": {
    "addr:full":"4808 Butternut Hollow Ln Bonita CA 91902",
    "addr:housenumber":"4808",
    "addr:postcode":"91902",
    "addr:street":"Butternut Hollow Ln",
    "iso:country":"US",
    "sg:address":"4808 Butternut Hollow Ln",
    "sg:city":"Bonita",
    "sg:classifiers":[
        {
            "category":"Professional",
            "type":"Services"
        }
    ],
    "sg:phone":"+1 619 267 0096",
    "sg:postcode":"91902",
    "sg:province":"CA",
    "wof:name":"Sawh Vishnu Chandrawatti",
    "wof:placetype":"venue"
},
  "geometry": {"coordinates":[-117.027281,32.673521],"type":"Point"}
}