{
  "type": "Feature",
  "properties": {
    "iso:country":"US",
    "sg:address":"220 W Valley Blvd",
    "sg:city":"San Gabriel",
    "sg:classifiers":[
        {
            "category":"Shopping",
            "subcategory":"Jewelry",
            "type":"Retail Goods"
        }
    ],
    "sg:phone":"+1 626 943 8878",
    "sg:postcode":"91776",
    "sg:province":"CA",
    "sg:tags":[
        "watch"
    ],
    "wof:name":"Swiss Watch & Jewelers",
    "wof:placetype":"venue"
},
  "geometry": {"coordinates":[-118.103111,34.079492],"type":"Point"}
}