{
  "type": "Feature",
  "properties": {
    "iso:country":"US",
    "sg:address":"440 Tamarac Dr",
    "sg:city":"Pasadena",
    "sg:classifiers":[
        {
            "category":"Professional",
            "subcategory":"Engineering",
            "type":"Services"
        }
    ],
    "sg:phone":"+1 323 254 0636",
    "sg:postcode":"91105",
    "sg:province":"CA",
    "sg:tags":[
        "engineer"
    ],
    "wof:name":"George A Padilla",
    "wof:placetype":"venue"
},
  "geometry": {"coordinates":[-118.18118200000001,34.136082],"type":"Point"}
}