{
  "type": "Feature",
  "properties": {
    "addr:full":"2405 S Stockton St Lodi CA 95240",
    "addr:housenumber":"2405",
    "addr:postcode":"95240",
    "addr:street":"S Stockton St",
    "iso:country":"US",
    "sg:address":"2405 S Stockton St",
    "sg:city":"Lodi",
    "sg:classifiers":[
        {
            "category":"Organizations",
            "subcategory":"Non-profit Organization",
            "type":"Services"
        }
    ],
    "sg:phone":"+1 209 334 5900",
    "sg:postcode":"95240",
    "sg:province":"CA",
    "sg:website":"www.cifsjs.org",
    "wof:name":"CIF Sac-Joaquin Section",
    "wof:placetype":"venue"
},
  "geometry": {"coordinates":[-121.269704,38.104423],"type":"Point"}
}