{
  "type": "Feature",
  "properties": {
    "addr:full":"15555 Main St Hesperia CA 92345",
    "addr:housenumber":"15555",
    "addr:postcode":"92345",
    "addr:street":"Main St",
    "iso:country":"US",
    "sg:address":"15555 Main St",
    "sg:city":"Hesperia",
    "sg:classifiers":[
        {
            "category":"Health Services",
            "subcategory":"Health Practitioner",
            "type":"Services"
        }
    ],
    "sg:phone":"+1 760 244 4288",
    "sg:postcode":"92345",
    "sg:province":"CA",
    "sg:tags":[
        "therapist",
        "physical"
    ],
    "wof:name":"Chaparral PT & Sports Med",
    "wof:placetype":"venue"
},
  "geometry": {"coordinates":[-117.323858,34.424767],"type":"Point"}
}