{
  "type": "Feature",
  "properties": {
    "addr:full":"3680 Charter Park Dr Ste E San Jose CA 95136",
    "addr:housenumber":"3680",
    "addr:postcode":"95136",
    "addr:street":"Charter Park Dr Ste E",
    "iso:country":"US",
    "sg:address":"3680 Charter Park Dr Ste E",
    "sg:city":"San Jose",
    "sg:classifiers":[
        {
            "category":"Professional",
            "subcategory":"Accounting & Tax Preparation",
            "type":"Services"
        }
    ],
    "sg:phone":"+1 408 445 6100",
    "sg:postcode":"95136",
    "sg:province":"CA",
    "sg:tags":[
        "accountant"
    ],
    "sg:website":"www.carsoncrew.com",
    "wof:name":"Carson & Crew",
    "wof:placetype":"venue"
},
  "geometry": {"coordinates":[-121.85027700000001,37.278528],"type":"Point"}
}