{
  "type": "Feature",
  "properties": {
    "addr:full":"3320 Alginet Dr Encino CA 91436",
    "addr:postcode":"3320;91436",
    "addr:street":"Alginet Dr",
    "iso:country":"US",
    "sg:address":"3320 Alginet Dr",
    "sg:city":"Encino",
    "sg:classifiers":[
        {
            "category":"Wholesale",
            "subcategory":"Durable Goods & Equipment",
            "type":"Manufacturing & Wholesale Goods"
        }
    ],
    "sg:phone":"+1 323 734 3970",
    "sg:postcode":"91436",
    "sg:province":"CA",
    "sg:tags":[
        "import",
        "bamboo"
    ],
    "wof:name":"Bamboo Imports Inc",
    "wof:placetype":"venue"
},
  "geometry": {"coordinates":[-118.495369,34.130939],"type":"Point"}
}