{
  "type": "Feature",
  "properties": {
    "addr:full":"38018 9th St E Palmdale CA 93550",
    "addr:housenumber":"38018",
    "addr:postcode":"ca 93550",
    "addr:street":"9Th St E",
    "iso:country":"US",
    "sg:address":"38018 9th St E",
    "sg:city":"Palmdale",
    "sg:classifiers":[
        {
            "category":"Autos & Motor Vehicles",
            "subcategory":"Auto Supplies",
            "type":"Retail Goods"
        },
        {
            "category":"Retail",
            "subcategory":"Auto Repair",
            "type":"Services"
        }
    ],
    "sg:phone":"+1 661 947 7838",
    "sg:postcode":"93550",
    "sg:province":"CA",
    "sg:tags":[
        "body",
        "lettering",
        "automobile",
        "truck",
        "painting",
        "repairing"
    ],
    "wof:name":"Palmdale Uni Body & Paint",
    "wof:placetype":"venue"
},
  "geometry": {"coordinates":[-118.11417400000001,34.572834],"type":"Point"}
}