{
  "type": "Feature",
  "properties": {
    "addr:full":"361 E Shaw Ave Fresno CA 93710",
    "addr:housenumber":"361",
    "addr:postcode":"93710",
    "addr:street":"E Shaw Ave",
    "iso:country":"US",
    "sg:address":"361 E Shaw Ave",
    "sg:city":"Fresno",
    "sg:classifiers":[
        {
            "category":"Wholesale",
            "subcategory":"Machinery & Supplies",
            "type":"Manufacturing & Wholesale Goods"
        }
    ],
    "sg:phone":"+1 559 221 9204",
    "sg:postcode":"93710",
    "sg:province":"CA",
    "sg:tags":[
        "salon",
        "beauty"
    ],
    "wof:name":"Cosmo Prof",
    "wof:placetype":"venue"
},
  "geometry": {"coordinates":[-119.78225500000001,36.808479],"type":"Point"}
}