{
  "type": "Feature",
  "properties": {
    "addr:full":"3101 E Carson Carson CA 90745",
    "addr:housenumber":"3101",
    "addr:postcode":"90745",
    "addr:street":"E Carson",
    "iso:country":"US",
    "sg:address":"3101 E Carson",
    "sg:city":"Carson",
    "sg:classifiers":[
        {
            "category":"Sports & Exercise",
            "subcategory":"Golf",
            "type":"Entertainment"
        }
    ],
    "sg:phone":"+1 562 429 9711",
    "sg:postcode":"90745",
    "sg:province":"CA",
    "wof:name":"Lakewood Country Club",
    "wof:placetype":"venue"
},
  "geometry": {"coordinates":[-118.26799800000001,33.821499],"type":"Point"}
}