{
  "type": "Feature",
  "properties": {
    "addr:full":"3016 Coral Ct San Jose CA 95121",
    "addr:housenumber":"3016",
    "addr:postcode":"95121",
    "addr:street":"Coral Ct",
    "iso:country":"US",
    "sg:address":"3016 Coral Ct",
    "sg:city":"San Jose",
    "sg:classifiers":[
        {
            "category":"Building & Trades",
            "subcategory":"Cleaning & Sanitation",
            "type":"Services"
        }
    ],
    "sg:phone":"+1 408 224 1090",
    "sg:postcode":"95121",
    "sg:province":"CA",
    "sg:tags":[
        "house"
    ],
    "wof:name":"Tidy Tony's House Cleaning",
    "wof:placetype":"venue"
},
  "geometry": {"coordinates":[-121.82302,37.303031],"type":"Point"}
}