{
  "type": "Feature",
  "properties": {
    "iso:country":"US",
    "sg:address":"3170 Vista Del Camino",
    "sg:city":"Marina",
    "sg:classifiers":[
        {
            "category":"Real Estate",
            "subcategory":"Real Estate Services",
            "type":"Services"
        }
    ],
    "sg:phone":"+1 831 384 0422",
    "sg:postcode":"93933",
    "sg:province":"CA",
    "sg:tags":[
        "management",
        "property"
    ],
    "wof:name":"Mast Realty",
    "wof:placetype":"venue"
},
  "geometry": {"coordinates":[-121.796997,36.687901],"type":"Point"}
}