{
  "type": "Feature",
  "properties": {
    "addr:full":"3920 Lennane Dr Sacramento CA 95834",
    "addr:housenumber":"3920",
    "addr:postcode":"95834",
    "addr:street":"Lennane Dr",
    "iso:country":"US",
    "sg:address":"3920 Lennane Dr",
    "sg:city":"Sacramento",
    "sg:classifiers":[
        {
            "category":"Professional",
            "type":"Services"
        }
    ],
    "sg:phone":"+1 916 263 0233",
    "sg:postcode":"95834",
    "sg:province":"CA",
    "sg:tags":[
        "establishment"
    ],
    "wof:name":"American Diversified Pharmacie",
    "wof:placetype":"venue"
},
  "geometry": {"coordinates":[-121.49147600000001,38.640981],"type":"Point"}
}