{
  "type": "Feature",
  "properties": {
    "addr:full":"1756 Urna Ave San Jose CA 95124",
    "addr:housenumber":"1756",
    "addr:postcode":"95124",
    "addr:street":"Urna Ave",
    "iso:country":"US",
    "sg:address":"1756 Urna Ave",
    "sg:city":"San Jose",
    "sg:classifiers":[
        {
            "category":"Building & Trades",
            "subcategory":"Construction",
            "type":"Services"
        }
    ],
    "sg:phone":"+1 408 448 4904",
    "sg:postcode":"95124",
    "sg:province":"CA",
    "sg:tags":[
        "fence",
        "contractor"
    ],
    "wof:name":"Bay Pacific Fence Co",
    "wof:placetype":"venue"
},
  "geometry": {"coordinates":[-121.913539,37.270608],"type":"Point"}
}