{
  "type": "Feature",
  "properties": {
    "addr:full":"9708 del Ray Ln Desert Hot Springs CA 92240",
    "addr:housenumber":"9708",
    "addr:postcode":"92240",
    "addr:street":"Del Ray Ln",
    "iso:country":"US",
    "sg:address":"9708 del Ray Ln",
    "sg:city":"Desert Hot Springs",
    "sg:classifiers":[
        {
            "category":"Building & Trades",
            "subcategory":"Electrical",
            "type":"Services"
        }
    ],
    "sg:phone":"+1 760 329 6345",
    "sg:postcode":"92240",
    "sg:province":"CA",
    "sg:tags":[
        "electrical",
        "contractor"
    ],
    "wof:name":"Kern Electric Co",
    "wof:placetype":"venue"
},
  "geometry": {"coordinates":[-116.510794,33.978179],"type":"Point"}
}