{
  "type": "Feature",
  "properties": {
    "iso:country":"US",
    "sg:address":"3133 W 182nd St",
    "sg:city":"Torrance",
    "sg:classifiers":[
        {
            "category":"Shopping",
            "subcategory":"Crafts & Fabrics",
            "type":"Retail Goods"
        }
    ],
    "sg:phone":"+1 310 532 2281",
    "sg:postcode":"90504",
    "sg:province":"CA",
    "sg:tags":[
        "shop"
    ],
    "wof:name":"Gardena Fabric",
    "wof:placetype":"venue"
},
  "geometry": {"coordinates":[-118.329753,33.866125],"type":"Point"}
}