{
  "type": "Feature",
  "properties": {
    "iso:country":"US",
    "sg:address":"27072 Hesperian Blvd",
    "sg:city":"Hayward",
    "sg:classifiers":[
        {
            "category":"Shopping",
            "subcategory":"Tobacco",
            "type":"Retail Goods"
        }
    ],
    "sg:phone":"+1 510 785 2556",
    "sg:postcode":"94545",
    "sg:province":"CA",
    "sg:tags":[
        "shop"
    ],
    "wof:name":"Discount Cigarettes",
    "wof:placetype":"venue"
},
  "geometry": {"coordinates":[-122.094002,37.626801],"type":"Point"}
}