{
  "type": "Feature",
  "properties": {
    "addr:full":"1056 E Philadelphia St Ontario CA 91761",
    "addr:housenumber":"1056 e",
    "addr:postcode":"91761",
    "addr:street":"Philadelphia St",
    "iso:country":"US",
    "sg:address":"1056 E Philadelphia St",
    "sg:city":"Ontario",
    "sg:classifiers":[
        {
            "category":"Education",
            "subcategory":"College",
            "type":"Public Place"
        }
    ],
    "sg:phone":"+1 909 923 5530",
    "sg:postcode":"91761",
    "sg:province":"CA",
    "sg:tags":[
        "academic",
        "school"
    ],
    "wof:name":"Providence Christian College",
    "wof:placetype":"venue"
},
  "geometry": {"coordinates":[-117.633904,34.033849],"type":"Point"}
}