{
  "type": "Feature",
  "properties": {
    "addr:full":"8530 Hayden Pl Culver City CA 90232",
    "addr:housenumber":"8530",
    "addr:postcode":"90232",
    "addr:street":"Hayden Pl",
    "iso:country":"US",
    "sg:address":"8530 Hayden Pl",
    "sg:city":"Culver City",
    "sg:classifiers":[
        {
            "category":"Utilities",
            "subcategory":"Telephone",
            "type":"Services"
        }
    ],
    "sg:phone":"+1 310 841 4600",
    "sg:postcode":"90232",
    "sg:province":"CA",
    "sg:tags":[
        "communication",
        "computer"
    ],
    "wof:name":"Aol",
    "wof:placetype":"venue"
},
  "geometry": {"coordinates":[-118.38253400000001,34.021751],"type":"Point"}
}