{
  "type": "Feature",
  "properties": {
    "iso:country":"US",
    "sg:address":"8530 Hayden Pl",
    "sg:city":"Culver City",
    "sg:classifiers":[
        {
            "category":"Utilities",
            "subcategory":"Telephone",
            "type":"Services"
        }
    ],
    "sg:phone":"+1 310 841 4600",
    "sg:postcode":"90232",
    "sg:province":"CA",
    "sg:tags":[
        "communication",
        "computer"
    ],
    "wof:name":"Aol",
    "wof:placetype":"venue"
},
  "geometry": {"coordinates":[-118.382534,34.021751],"type":"Point"}
}