{
  "type": "Feature",
  "properties": {
    "addr:full":"1401 Lakeside Dr Oakland CA 94612",
    "addr:housenumber":"1401",
    "addr:postcode":"94612",
    "addr:street":"Lakeside Dr",
    "iso:country":"US",
    "sg:address":"1401 Lakeside Dr",
    "sg:city":"Oakland",
    "sg:classifiers":[
        {
            "category":"Government",
            "subcategory":"Office",
            "type":"Public Place"
        }
    ],
    "sg:phone":"+1 510 272 6180",
    "sg:postcode":"94612",
    "sg:province":"CA",
    "wof:name":"Alameda Cnty Victim Assistance",
    "wof:placetype":"venue"
},
  "geometry": {"coordinates":[-122.261217,37.803723],"type":"Point"}
}