{
  "type": "Feature",
  "properties": {
    "addr:full":"2129 W Rosecrans Ave Long Beach CA 90802",
    "addr:housenumber":"2129",
    "addr:postcode":"90802",
    "addr:street":"W Rosecrans Ave",
    "iso:country":"US",
    "sg:address":"2129 W Rosecrans Ave",
    "sg:city":"Long Beach",
    "sg:classifiers":[
        {
            "category":"Taxi",
            "type":"Transportation"
        }
    ],
    "sg:phone":"+1 562 435 6111",
    "sg:postcode":"90802",
    "sg:province":"CA",
    "sg:website":"www.lbyellowcab.com",
    "wof:name":"Long Beach Yellow Cab",
    "wof:placetype":"venue"
},
  "geometry": {"coordinates":[-118.200632,33.903593],"type":"Point"}
}