{
  "type": "Feature",
  "properties": {
    "addr:full":"1585 E 14th St San Leandro CA 94577",
    "addr:housenumber":"1585",
    "addr:postcode":"94577",
    "addr:street":"E 14Th St",
    "iso:country":"US",
    "sg:address":"1585 E 14th St",
    "sg:city":"San Leandro",
    "sg:classifiers":[
        {
            "category":"Banks & Credit Unions",
            "subcategory":"Bank",
            "type":"Services"
        },
        {
            "category":"Banks & Credit Unions",
            "subcategory":"Financial Services",
            "type":"Services"
        }
    ],
    "sg:phone":"+1 510 357 7922",
    "sg:postcode":"94577",
    "sg:province":"CA",
    "sg:tags":[
        "broker",
        "mortgage"
    ],
    "wof:name":"California Savings Bank",
    "wof:placetype":"venue"
},
  "geometry": {"coordinates":[-122.15300000000001,37.723099],"type":"Point"}
}