{
  "type": "Feature",
  "properties": {
    "iso:country":"US",
    "sg:address":"196 Blue Ravine Rd",
    "sg:city":"Folsom",
    "sg:classifiers":[
        {
            "category":"Sports & Exercise",
            "subcategory":"Sports Center",
            "type":"Entertainment"
        }
    ],
    "sg:phone":"+1 916 353 0855",
    "sg:postcode":"95630",
    "sg:province":"CA",
    "wof:name":"Curry Club",
    "wof:placetype":"venue"
},
  "geometry": {"coordinates":[-121.179974,38.654882],"type":"Point"}
}