{
  "type": "Feature",
  "properties": {
    "addr:full":"159 7th Ave La Puente CA 91746",
    "addr:housenumber":"159",
    "addr:postcode":"91746",
    "addr:street":"7Th Ave",
    "iso:country":"US",
    "sg:address":"159 7th Ave",
    "sg:city":"La Puente",
    "sg:classifiers":[
        {
            "category":"Autos & Motor Vehicles",
            "subcategory":"Recreational Vehicle Sales",
            "type":"Retail Goods"
        }
    ],
    "sg:phone":"+1 626 336 1226",
    "sg:postcode":"91746",
    "sg:province":"CA",
    "sg:tags":[
        "parts",
        "trailer"
    ],
    "wof:name":"City Trailer Supply",
    "wof:placetype":"venue"
},
  "geometry": {"coordinates":[-117.975195,34.034401],"type":"Point"}
}