{
  "type": "Feature",
  "properties": {
    "iso:country":"US",
    "sg:address":"1320 Galaxy Way",
    "sg:city":"Concord",
    "sg:classifiers":[
        {
            "category":"Wholesale",
            "subcategory":"Scrap",
            "type":"Manufacturing & Wholesale Goods"
        }
    ],
    "sg:phone":"+1 925 689 3900",
    "sg:postcode":"94520",
    "sg:province":"CA",
    "sg:tags":[
        "recycling",
        "center"
    ],
    "wof:name":"Pleasant Paper Recycling Inc",
    "wof:placetype":"venue"
},
  "geometry": {"coordinates":[-122.048232,37.976269],"type":"Point"}
}