{
  "type": "Feature",
  "properties": {
    "addr:full":"15700 Vanowen St Van Nuys CA 91406",
    "addr:housenumber":"15700",
    "addr:postcode":"91406",
    "addr:street":"Vanowen St",
    "iso:country":"US",
    "sg:address":"15700 Vanowen St",
    "sg:city":"Van Nuys",
    "sg:classifiers":[
        {
            "category":"Wholesale",
            "subcategory":"Plants",
            "type":"Manufacturing & Wholesale Goods"
        },
        {
            "category":"Shopping",
            "subcategory":"Florist",
            "type":"Retail Goods"
        }
    ],
    "sg:phone":"+1 310 989 4656",
    "sg:postcode":"91406",
    "sg:province":"CA",
    "sg:tags":[
        "arranging",
        "flower",
        "supply"
    ],
    "wof:name":"Gloria's Flower Shop",
    "wof:placetype":"venue"
},
  "geometry": {"coordinates":[-118.47721300000001,34.193909],"type":"Point"}
}