{
  "type": "Feature",
  "properties": {
    "addr:full":"4762 Admiralty Way Marina Del Rey CA 90292",
    "addr:housenumber":"4762",
    "addr:postcode":"90292",
    "addr:street":"Admiralty Way",
    "iso:country":"US",
    "sg:address":"4762 Admiralty Way",
    "sg:city":"Marina Del Rey",
    "sg:classifiers":[
        {
            "category":"Travel",
            "subcategory":"Travel Agent",
            "type":"Entertainment"
        }
    ],
    "sg:phone":"+1 310 821 0761",
    "sg:postcode":"90292",
    "sg:province":"CA",
    "sg:tags":[
        "agency"
    ],
    "wof:name":"Marina Travel",
    "wof:placetype":"venue"
},
  "geometry": {"coordinates":[-118.43919,33.978893],"type":"Point"}
}