{
  "type": "Feature",
  "properties": {
    "iso:country":"US",
    "sg:address":"23126 Mariposa Ave",
    "sg:city":"Torrance",
    "sg:classifiers":[
        {
            "category":"Manufacturing",
            "subcategory":"Rubber & Plastics",
            "type":"Manufacturing & Wholesale Goods"
        }
    ],
    "sg:phone":"+1 310 539 1883",
    "sg:postcode":"90502",
    "sg:province":"CA",
    "sg:tags":[
        "gasket"
    ],
    "wof:name":"Molina Gaskets",
    "wof:placetype":"venue"
},
  "geometry": {"coordinates":[-118.29716999999999,33.816185],"type":"Point"}
}