{
  "type": "Feature",
  "properties": {
    "iso:country":"US",
    "sg:address":"5304 Old Redwood Hwy",
    "sg:city":"Petaluma",
    "sg:classifiers":[
        {
            "category":"Restaurant",
            "type":"Food & Drink"
        }
    ],
    "sg:menulink":"http://www.allmenus.com/ca/petaluma/171976-burger-king/menu/",
    "sg:phone":"+1 707 664 9385",
    "sg:postcode":"94954",
    "sg:province":"CA",
    "sg:tags":[
        "burger",
        "american"
    ],
    "wof:name":"Burger King",
    "wof:placetype":"venue"
},
  "geometry": {"coordinates":[-122.669211,38.27581],"type":"Point"}
}