{
  "type": "Feature",
  "properties": {
    "iso:country":"US",
    "sg:address":"2505 Yorba Linda Blvd",
    "sg:city":"Fullerton",
    "sg:classifiers":[
        {
            "category":"Organizations",
            "subcategory":"Religious Organization",
            "type":"Services"
        }
    ],
    "sg:phone":"+1 714 871 6844",
    "sg:postcode":"92831",
    "sg:province":"CA",
    "sg:tags":[
        "christian",
        "church"
    ],
    "sg:website":"www.eastside.com",
    "wof:name":"Eastside Christian Church",
    "wof:placetype":"venue"
},
  "geometry": {"coordinates":[-117.889127,33.888245],"type":"Point"}
}