{
  "type": "Feature",
  "properties": {
    "addr:full":"21945 Old 44 Dr Palo Cedro CA 96073",
    "addr:housenumber":"21945",
    "addr:postcode":"96073",
    "addr:street":"Old 44 Dr",
    "iso:country":"US",
    "sg:address":"21945 Old 44 Dr",
    "sg:city":"Palo Cedro",
    "sg:classifiers":[
        {
            "category":"Education",
            "subcategory":"School",
            "type":"Public Place"
        }
    ],
    "sg:phone":"+1 530 547 3326",
    "sg:postcode":"96073",
    "sg:province":"CA",
    "sg:tags":[
        "catholic",
        "middle"
    ],
    "wof:name":"St Francis Middle School",
    "wof:placetype":"venue"
},
  "geometry": {"coordinates":[-122.238789,40.563695],"type":"Point"}
}