{
  "type": "Feature",
  "properties": {
    "addr:full":"9477 Briar Bush Way Elk Grove CA 95758",
    "addr:housenumber":"9477",
    "addr:postcode":"95758",
    "addr:street":"Briar Bush Way",
    "iso:country":"US",
    "sg:address":"9477 Briar Bush Way",
    "sg:city":"Elk Grove",
    "sg:classifiers":[
        {
            "category":"Wholesale",
            "subcategory":"Furniture",
            "type":"Manufacturing & Wholesale Goods"
        }
    ],
    "sg:phone":"+1 530 673 1212",
    "sg:postcode":"95758",
    "sg:province":"CA",
    "sg:tags":[
        "furnishing",
        "church"
    ],
    "wof:name":"American Baptistry Co",
    "wof:placetype":"venue"
},
  "geometry": {"coordinates":[-121.396079,38.413428],"type":"Point"}
}