{
  "type": "Feature",
  "properties": {
    "addr:full":"2626 San Bruno Ave San Francisco CA 94134",
    "addr:housenumber":"2626",
    "addr:postcode":"94134",
    "addr:street":"San Bruno Ave",
    "iso:country":"US",
    "sg:address":"2626 San Bruno Ave",
    "sg:city":"San Francisco",
    "sg:classifiers":[
        {
            "category":"Restaurant",
            "type":"Food & Drink"
        }
    ],
    "sg:menulink":"http://www.allmenus.com/ca/san-francisco/81783-imperial-garden-seafood-restaurant/menu/",
    "sg:phone":"+1 415 468 9666",
    "sg:postcode":"94134",
    "sg:province":"CA",
    "sg:tags":[
        "asian",
        "chinese"
    ],
    "wof:name":"Imperial Garden Seafood Restaurant",
    "wof:placetype":"venue"
},
  "geometry": {"coordinates":[-122.40396,37.728497],"type":"Point"}
}