{
  "type": "Feature",
  "properties": {
    "addr:full":"4129 Main St Riverside CA 92501",
    "addr:housenumber":"4129",
    "addr:postcode":"92501",
    "addr:street":"Main St",
    "iso:country":"US",
    "sg:address":"4129 Main St",
    "sg:city":"Riverside",
    "sg:classifiers":[
        {
            "category":"Professional",
            "subcategory":"Lawyer & Legal Services",
            "type":"Services"
        }
    ],
    "sg:phone":"+1 951 787 9904",
    "sg:postcode":"92501",
    "sg:province":"CA",
    "sg:tags":[
        "attorney"
    ],
    "wof:name":"Shaffer Lax Mc Naughton & Chan",
    "wof:placetype":"venue"
},
  "geometry": {"coordinates":[-117.376932,33.978394],"type":"Point"}
}