{
  "type": "Feature",
  "properties": {
    "iso:country":"US",
    "sg:address":"2225 Morse Ave",
    "sg:city":"Sacramento",
    "sg:classifiers":[
        {
            "category":"Health Services",
            "subcategory":"Doctor",
            "type":"Services"
        }
    ],
    "sg:phone":"+1 916 614 4040",
    "sg:postcode":"95825",
    "sg:province":"CA",
    "sg:tags":[
        "physician",
        "surgeon"
    ],
    "wof:name":"Kaiser Permanente",
    "wof:placetype":"venue"
},
  "geometry": {"coordinates":[-121.392316,38.605272],"type":"Point"}
}