{
  "type": "Feature",
  "properties": {
    "addr:full":"250 E 1st St Los Angeles CA 90012",
    "addr:housenumber":"250",
    "addr:postcode":"90012",
    "addr:street":"E 1St St",
    "iso:country":"US",
    "sg:address":"250 E 1st St",
    "sg:city":"Los Angeles",
    "sg:classifiers":[
        {
            "category":"Real Estate",
            "subcategory":"Real Estate Agent",
            "type":"Services"
        }
    ],
    "sg:phone":"+1 213 680 1197",
    "sg:postcode":"90012",
    "sg:province":"CA",
    "sg:tags":[
        "management"
    ],
    "wof:name":"Kajima Building",
    "wof:placetype":"venue"
},
  "geometry": {"coordinates":[-118.24137899999999,34.050763],"type":"Point"}
}