{
  "type": "Feature",
  "properties": {
    "addr:full":"354 Andrews St Livermore CA 94551",
    "addr:housenumber":"354",
    "addr:postcode":"94551",
    "addr:street":"Andrews St",
    "iso:country":"US",
    "sg:address":"354 Andrews St",
    "sg:city":"Livermore",
    "sg:classifiers":[
        {
            "category":"Professional",
            "type":"Services"
        }
    ],
    "sg:phone":"+1 925 447 2329",
    "sg:postcode":"94551",
    "sg:province":"CA",
    "wof:name":"Four Dimensions",
    "wof:placetype":"venue"
},
  "geometry": {"coordinates":[-121.78239499999999,37.684346],"type":"Point"}
}