{
  "type": "Feature",
  "properties": {
    "iso:country":"US",
    "sg:address":"1401 21st Street Suite 320",
    "sg:city":"Sacramento",
    "sg:classifiers":[
        {
            "category":"Professional",
            "subcategory":"Lawyer & Legal Services",
            "type":"Services"
        }
    ],
    "sg:phone":"+1 916 325 9777",
    "sg:postcode":"95814",
    "sg:province":"CA",
    "wof:name":"Scott Patrick L Law Offices of",
    "wof:placetype":"venue"
},
  "geometry": {"coordinates":[-121.492394,38.57756],"type":"Point"}
}