{
  "type": "Feature",
  "properties": {
    "iso:country":"US",
    "sg:address":"850 3rd St",
    "sg:city":"Santa Rosa",
    "sg:classifiers":[
        {
            "category":"Professional",
            "type":"Services"
        }
    ],
    "sg:phone":"+1 707 575 1037",
    "sg:postcode":"95404",
    "sg:province":"CA",
    "wof:name":"Cast Kay Tee Inc",
    "wof:placetype":"venue"
},
  "geometry": {"coordinates":[-122.707587,38.442205],"type":"Point"}
}