{
  "type": "Feature",
  "properties": {
    "iso:country":"US",
    "sg:address":"6202 Apache Rd",
    "sg:city":"Westminster",
    "sg:classifiers":[
        {
            "category":"Building & Trades",
            "subcategory":"Construction",
            "type":"Services"
        }
    ],
    "sg:phone":"+1 714 894 6309",
    "sg:postcode":"92683",
    "sg:province":"CA",
    "sg:tags":[
        "floor",
        "installation",
        "contractor"
    ],
    "wof:name":"Jts Flooring Supplies Inc",
    "wof:placetype":"venue"
},
  "geometry": {"coordinates":[-118.020883,33.77251],"type":"Point"}
}