{
  "type": "Feature",
  "properties": {
    "addr:full":"1802 Cll Fortuna Glendale CA 91208",
    "addr:housenumber":"1802",
    "addr:postcode":"91208",
    "addr:street":"Cll Fortuna",
    "iso:country":"US",
    "sg:address":"1802 Cll Fortuna",
    "sg:city":"Glendale",
    "sg:classifiers":[
        {
            "category":"Shopping",
            "subcategory":"Catalog Store",
            "type":"Retail Goods"
        }
    ],
    "sg:phone":"+1 818 500 8824",
    "sg:postcode":"91208",
    "sg:province":"CA",
    "sg:tags":[
        "mail",
        "house"
    ],
    "wof:name":"Topp Knotch Marketing",
    "wof:placetype":"venue"
},
  "geometry": {"coordinates":[-118.215296,34.164611],"type":"Point"}
}