{
  "type": "Feature",
  "properties": {
    "iso:country":"US",
    "sg:address":"1251 W Tennyson Rd Ste 2",
    "sg:city":"Hayward",
    "sg:classifiers":[
        {
            "category":"Education",
            "subcategory":"Special Training",
            "type":"Public Place"
        }
    ],
    "sg:phone":"+1 510 785 6284",
    "sg:postcode":"94544",
    "sg:province":"CA",
    "sg:tags":[
        "tutoring"
    ],
    "sg:website":"www.kumon.com",
    "wof:name":"Kumon Math & Reading Center-Hayward",
    "wof:placetype":"venue"
},
  "geometry": {"coordinates":[-122.079002,37.631401],"type":"Point"}
}