{
  "type": "Feature",
  "properties": {
    "iso:country":"US",
    "sg:address":"110 E 9th St",
    "sg:city":"Los Angeles",
    "sg:classifiers":[
        {
            "category":"Wholesale",
            "subcategory":"Apparel",
            "type":"Manufacturing & Wholesale Goods"
        }
    ],
    "sg:phone":"+1 213 624 5994",
    "sg:postcode":"90015",
    "sg:province":"CA",
    "sg:tags":[
        "underwear",
        "clothing",
        "mfg"
    ],
    "wof:name":"Klein Sherman A",
    "wof:placetype":"venue"
},
  "geometry": {"coordinates":[-118.254773,34.041342],"type":"Point"}
}