{
  "type": "Feature",
  "properties": {
    "iso:country":"US",
    "sg:address":"701 S Franklin St",
    "sg:city":"Fort Bragg",
    "sg:classifiers":[
        {
            "category":"Retail",
            "subcategory":"Auto Repair",
            "type":"Services"
        }
    ],
    "sg:phone":"+1 707 964 7960",
    "sg:postcode":"95437",
    "sg:province":"CA",
    "sg:tags":[
        "transmission"
    ],
    "wof:name":"Fort Bragg Transmission Svc",
    "wof:placetype":"venue"
},
  "geometry": {"coordinates":[-123.804622,39.432685],"type":"Point"}
}