{
  "type": "Feature",
  "properties": {
    "iso:country":"US",
    "sg:address":"21762 Lake Forest Drive",
    "sg:city":"Lake Forest",
    "sg:classifiers":[
        {
            "category":"Autos & Motor Vehicles",
            "subcategory":"Fuel & Gas Station",
            "type":"Retail Goods"
        }
    ],
    "sg:phone":"+1 949 458 6168",
    "sg:postcode":"92630",
    "sg:province":"CA",
    "sg:website":"www.shell.com",
    "wof:name":"M & R Shell",
    "wof:placetype":"venue"
},
  "geometry": {"coordinates":[-117.686153,33.646858],"type":"Point"}
}