{
  "type": "Feature",
  "properties": {
    "iso:country":"US",
    "sg:address":"13610 Imperial Hwy Ste 8",
    "sg:city":"Santa Fe Springs",
    "sg:classifiers":[
        {
            "category":"Shopping",
            "subcategory":"Shoes",
            "type":"Retail Goods"
        }
    ],
    "sg:phone":"+1 562 407 5241",
    "sg:postcode":"90670",
    "sg:province":"CA",
    "sg:tags":[
        "store"
    ],
    "wof:name":"A Plus Shoes",
    "wof:placetype":"venue"
},
  "geometry": {"coordinates":[-118.202571,33.916822],"type":"Point"}
}