{
  "type": "Feature",
  "properties": {
    "iso:country":"US",
    "sg:address":"228 Ruth Ann Way",
    "sg:city":"Arroyo Grande",
    "sg:classifiers":[
        {
            "category":"Professional",
            "type":"Services"
        }
    ],
    "sg:phone":"+1 805 474 0105",
    "sg:postcode":"93420",
    "sg:province":"CA",
    "wof:name":"Five Cities",
    "wof:placetype":"venue"
},
  "geometry": {"coordinates":[-120.602332,35.123616],"type":"Point"}
}