{
  "type": "Feature",
  "properties": {
    "addr:full":"8262 Rancho Real Gilroy CA 95020",
    "addr:housenumber":"8262",
    "addr:postcode":"95020",
    "addr:street":"Rancho Real",
    "iso:country":"US",
    "sg:address":"8262 Rancho Real",
    "sg:city":"Gilroy",
    "sg:classifiers":[
        {
            "category":"Building & Trades",
            "subcategory":"Landscaping Services",
            "type":"Services"
        }
    ],
    "sg:phone":"+1 408 842 0245",
    "sg:postcode":"95020",
    "sg:province":"CA",
    "sg:tags":[
        "architect",
        "landscape"
    ],
    "wof:name":"Aitken Associates",
    "wof:placetype":"venue"
},
  "geometry": {"coordinates":[-121.604308,37.016138],"type":"Point"}
}