{
  "type": "Feature",
  "properties": {
    "addr:full":"1611A S Melrose Dr 17 Vista CA 92081",
    "addr:housenumber":"1611a;17",
    "addr:postcode":"92081",
    "addr:street":"S Melrose Dr",
    "iso:country":"US",
    "sg:address":"1611A S Melrose Dr 17",
    "sg:city":"Vista",
    "sg:classifiers":[
        {
            "category":"Shopping",
            "subcategory":"Pets & Pet Supplies",
            "type":"Retail Goods"
        }
    ],
    "sg:phone":"+1 760 644 8550",
    "sg:postcode":"92081",
    "sg:province":"CA",
    "sg:tags":[
        "furnishing",
        "dog",
        "store",
        "cat"
    ],
    "wof:name":"Jiffy Pet",
    "wof:placetype":"venue"
},
  "geometry": {"coordinates":[-117.246848,33.16626],"type":"Point"}
}