{
  "type": "Feature",
  "properties": {
    "addr:full":"31378 Mackinaw St Union City CA 94587",
    "addr:housenumber":"31378",
    "addr:postcode":"94587",
    "addr:street":"Mackinaw St",
    "iso:country":"US",
    "sg:address":"31378 Mackinaw St",
    "sg:city":"Union City",
    "sg:classifiers":[
        {
            "category":"Professional",
            "type":"Services"
        }
    ],
    "sg:phone":"+1 510 441 0566",
    "sg:postcode":"94587",
    "sg:province":"CA",
    "wof:name":"Silk N Stones",
    "wof:placetype":"venue"
},
  "geometry": {"coordinates":[-122.08226000000001,37.589424],"type":"Point"}
}