{
  "type": "Feature",
  "properties": {
    "addr:full":"31328 Via Colinas Westlake Village CA 91362",
    "addr:housenumber":"31328",
    "addr:postcode":"91362",
    "addr:street":"Via Colinas",
    "iso:country":"US",
    "sg:address":"31328 Via Colinas",
    "sg:city":"Westlake Village",
    "sg:classifiers":[
        {
            "category":"Wholesale",
            "subcategory":"Electrical",
            "type":"Manufacturing & Wholesale Goods"
        }
    ],
    "sg:phone":"+1 818 222 8649",
    "sg:postcode":"91362",
    "sg:province":"CA",
    "sg:tags":[
        "lighting",
        "fixture"
    ],
    "sg:website":"www.lanternmasters.com",
    "wof:name":"Lantern Masters Inc",
    "wof:placetype":"venue"
},
  "geometry": {"coordinates":[-118.806324,34.156403],"type":"Point"}
}