{
  "type": "Feature",
  "properties": {
    "addr:full":"1360 Summitridge Pl Beverly Hills CA 90210",
    "addr:housenumber":"1360",
    "addr:postcode":"90210",
    "addr:street":"Summitridge Pl",
    "iso:country":"US",
    "sg:address":"1360 Summitridge Pl",
    "sg:city":"Beverly Hills",
    "sg:classifiers":[
        {
            "category":"Professional",
            "type":"Services"
        }
    ],
    "sg:phone":"+1 310 276 1600",
    "sg:postcode":"90210",
    "sg:province":"CA",
    "wof:name":"Irving & Jean Stone Foundation",
    "wof:placetype":"venue"
},
  "geometry": {"coordinates":[-118.41989700000001,34.09465],"type":"Point"}
}