{
  "type": "Feature",
  "properties": {
    "addr:full":"11993 Macdonald Dr Ojai CA 93023",
    "addr:housenumber":"11993",
    "addr:postcode":"93023",
    "addr:street":"Macdonald Dr",
    "iso:country":"US",
    "sg:address":"11993 Macdonald Dr",
    "sg:city":"Ojai",
    "sg:classifiers":[
        {
            "category":"Food & Beverages",
            "subcategory":"Farmers Market",
            "type":"Retail Goods"
        }
    ],
    "sg:phone":"+1 805 649 9091",
    "sg:postcode":"93023",
    "sg:province":"CA",
    "sg:tags":[
        "vegetable",
        "fruit"
    ],
    "wof:name":"Db Produce Inc",
    "wof:placetype":"venue"
},
  "geometry": {"coordinates":[-119.31183299999999,34.426421],"type":"Point"}
}