{
  "type": "Feature",
  "properties": {
    "addr:full":"5469 Edgerly Way Carmichael CA 95608",
    "addr:housenumber":"5469",
    "addr:postcode":"95608",
    "addr:street":"Edgerly Way",
    "iso:country":"US",
    "sg:address":"5469 Edgerly Way",
    "sg:city":"Carmichael",
    "sg:classifiers":[
        {
            "category":"Utilities",
            "subcategory":"Telephone",
            "type":"Services"
        }
    ],
    "sg:phone":"+1 916 215 0638",
    "sg:postcode":"95608",
    "sg:province":"CA",
    "sg:tags":[
        "communication"
    ],
    "wof:name":"Mc Telecom",
    "wof:placetype":"venue"
},
  "geometry": {"coordinates":[-121.321214,38.666003],"type":"Point"}
}