{
  "type": "Feature",
  "properties": {
    "iso:country":"US",
    "sg:address":"127 N Garfield Ave",
    "sg:city":"Monterey Park",
    "sg:classifiers":[
        {
            "category":"Shopping",
            "subcategory":"Books",
            "type":"Retail Goods"
        }
    ],
    "sg:phone":"+1 626 572 9629",
    "sg:postcode":"91754",
    "sg:province":"CA",
    "sg:tags":[
        "bookstore"
    ],
    "wof:name":"New World Book Company",
    "wof:placetype":"venue"
},
  "geometry": {"coordinates":[-118.123001,34.062901],"type":"Point"}
}