{
  "type": "Feature",
  "properties": {
    "addr:full":"700 Champagne Ave Coleville CA 96107",
    "addr:housenumber":"700",
    "addr:postcode":"96107",
    "addr:street":"Champagne Ave",
    "iso:country":"US",
    "sg:address":"700 Champagne Ave",
    "sg:city":"Coleville",
    "sg:classifiers":[
        {
            "category":"Real Estate",
            "subcategory":"Real Estate Agent",
            "type":"Services"
        }
    ],
    "sg:phone":"+1 530 495 2607",
    "sg:postcode":"96107",
    "sg:province":"CA",
    "sg:tags":[
        "management"
    ],
    "wof:name":"Camp Pendelton Quantico Hsng",
    "wof:placetype":"venue"
},
  "geometry": {"coordinates":[-119.52008499999999,38.587842],"type":"Point"}
}