{
  "type": "Feature",
  "properties": {
    "addr:full":"208 San Rafael Ave Belvedere Tibrn CA 94920",
    "addr:housenumber":"208",
    "addr:postcode":"94920",
    "addr:street":"San Rafael Ave",
    "iso:country":"US",
    "sg:address":"208 San Rafael Ave",
    "sg:city":"Belvedere Tibrn",
    "sg:classifiers":[
        {
            "category":"Shopping",
            "subcategory":"Used Merchandise",
            "type":"Retail Goods"
        }
    ],
    "sg:phone":"+1 415 435 4764",
    "sg:postcode":"94920",
    "sg:province":"CA",
    "sg:tags":[
        "antique"
    ],
    "wof:name":"Cynthia Shaver",
    "wof:placetype":"venue"
},
  "geometry": {"coordinates":[-122.472227,37.878515],"type":"Point"}
}