{
  "type": "Feature",
  "properties": {
    "iso:country":"US",
    "sg:address":"869 N Fair Oaks Ave",
    "sg:city":"Pasadena",
    "sg:classifiers":[
        {
            "category":"Manufacturing",
            "subcategory":"Building Materials",
            "type":"Manufacturing & Wholesale Goods"
        }
    ],
    "sg:phone":"+1 626 796 1675",
    "sg:postcode":"91103",
    "sg:province":"CA",
    "sg:tags":[
        "mfg",
        "wood",
        "kitchen",
        "cabinet"
    ],
    "wof:name":"George Cabinets",
    "wof:placetype":"venue"
},
  "geometry": {"coordinates":[-118.15068,34.160777],"type":"Point"}
}