{
  "type": "Feature",
  "properties": {
    "iso:country":"US",
    "sg:address":"1442 Franklin St.",
    "sg:city":"Santa Clara",
    "sg:classifiers":[
        {
            "category":"Personal",
            "type":"Services"
        },
        {
            "category":"Retail",
            "subcategory":"Laundry & Dry Cleaning",
            "type":"Services"
        }
    ],
    "sg:phone":"+1 408 247 0919",
    "sg:postcode":"95050",
    "sg:province":"CA",
    "sg:tags":[
        "sewing",
        "alteration"
    ],
    "wof:name":"Sunshine Cleaners and Alterations",
    "wof:placetype":"venue"
},
  "geometry": {"coordinates":[-121.949782,37.347931],"type":"Point"}
}