{
  "type": "Feature",
  "properties": {
    "iso:country":"US",
    "sg:address":"1225 8th Street Suite 450",
    "sg:city":"Sacramento",
    "sg:classifiers":[
        {
            "category":"Professional",
            "subcategory":"Lawyer & Legal Services",
            "type":"Services"
        }
    ],
    "sg:phone":"+1 916 447 1092",
    "sg:postcode":"95814",
    "sg:province":"CA",
    "sg:tags":[
        "divorce",
        "law",
        "family"
    ],
    "wof:name":"Sabo Katherine",
    "wof:placetype":"venue"
},
  "geometry": {"coordinates":[-121.497165,38.578555],"type":"Point"}
}