{
  "type": "Feature",
  "properties": {
    "addr:full":"5959 W Century Blvd Los Angeles CA 90045",
    "addr:housenumber":"5959",
    "addr:postcode":"90045",
    "addr:street":"W Century Blvd",
    "iso:country":"US",
    "sg:address":"5959 W Century Blvd",
    "sg:city":"Los Angeles",
    "sg:classifiers":[
        {
            "category":"Communications",
            "subcategory":"Television Station",
            "type":"Services"
        }
    ],
    "sg:phone":"+1 310 999 6760",
    "sg:postcode":"90045",
    "sg:province":"CA",
    "wof:name":"Carribean Broadcast Television",
    "wof:placetype":"venue"
},
  "geometry": {"coordinates":[-118.387265,33.945726],"type":"Point"}
}