{
  "type": "Feature",
  "properties": {
    "iso:country":"US",
    "sg:address":"777 S Figueroa St",
    "sg:city":"Los Angeles",
    "sg:classifiers":[
        {
            "category":"Banks & Credit Unions",
            "subcategory":"Bank",
            "type":"Services"
        }
    ],
    "sg:phone":"+1 213 488 3700",
    "sg:postcode":"90017",
    "sg:province":"CA",
    "sg:tags":[
        "commercial"
    ],
    "wof:name":"Bank of Tokyo",
    "wof:placetype":"venue"
},
  "geometry": {"coordinates":[-118.260385,34.04911],"type":"Point"}
}