{
  "type": "Feature",
  "properties": {
    "iso:country":"US",
    "sg:address":"5585 Brooks St",
    "sg:city":"Montclair",
    "sg:classifiers":[
        {
            "category":"Wholesale",
            "subcategory":"Computers",
            "type":"Manufacturing & Wholesale Goods"
        }
    ],
    "sg:phone":"+1 909 986 0966",
    "sg:postcode":"91763",
    "sg:province":"CA",
    "wof:name":"V Com Technology Inc",
    "wof:placetype":"venue"
},
  "geometry": {"coordinates":[-117.682503,34.061702],"type":"Point"}
}