{
  "type": "Feature",
  "properties": {
    "addr:full":"1000 S Fremont Ave Alhambra CA 91803",
    "addr:housenumber":"1000",
    "addr:postcode":"91803",
    "addr:street":"S Fremont Ave",
    "iso:country":"US",
    "sg:address":"1000 S Fremont Ave",
    "sg:city":"Alhambra",
    "sg:classifiers":[
        {
            "category":"Health Services",
            "subcategory":"Clinic",
            "type":"Services"
        }
    ],
    "sg:phone":"+1 626 284 4000",
    "sg:postcode":"91803",
    "sg:province":"CA",
    "sg:website":"www.ddfsinc.org",
    "wof:name":"Developmental Dynamics",
    "wof:placetype":"venue"
},
  "geometry": {"coordinates":[-118.151869,34.079329],"type":"Point"}
}