{
  "type": "Feature",
  "properties": {
    "iso:country":"US",
    "sg:address":"952 Eaton Dr",
    "sg:city":"Felton",
    "sg:phone":"+1 831 335 4038",
    "sg:postcode":"95018",
    "sg:province":"CA",
    "sg:tags":[
        "gas"
    ],
    "wof:name":"Pro-Carb",
    "wof:placetype":"venue"
},
  "geometry": {"coordinates":[-122.083955,37.036137],"type":"Point"}
}