{
  "type": "Feature",
  "properties": {
    "iso:country":"US",
    "sg:address":"1505 W Poema Dr",
    "sg:city":"Colton",
    "sg:classifiers":[
        {
            "category":"Health Services",
            "subcategory":"Nursing And Care Facility",
            "type":"Services"
        }
    ],
    "sg:phone":"+1 909 370 4594",
    "sg:postcode":"92324",
    "sg:province":"CA",
    "sg:tags":[
        "home",
        "rest"
    ],
    "wof:name":"Senior Help Board & Care",
    "wof:placetype":"venue"
},
  "geometry": {"coordinates":[-117.351052,34.081918],"type":"Point"}
}