{
  "type": "Feature",
  "properties": {
    "iso:country":"US",
    "sg:address":"2 Monterey Ct",
    "sg:city":"Novato",
    "sg:classifiers":[
        {
            "category":"Real Estate",
            "subcategory":"Real Estate Agent",
            "type":"Services"
        }
    ],
    "sg:phone":"+1 707 935 3792",
    "sg:postcode":"94945",
    "sg:province":"CA",
    "sg:tags":[
        "management"
    ],
    "wof:name":"Fulcrum Property Management",
    "wof:placetype":"venue"
},
  "geometry": {"coordinates":[-122.58130199999999,38.108563],"type":"Point"}
}