{
  "type": "Feature",
  "properties": {
    "addr:full":"18502 S. Normandie Avenue Gardena CA 90248",
    "addr:housenumber":"18502",
    "addr:postcode":"90248",
    "addr:street":"S. Normandie Avenue",
    "iso:country":"US",
    "sg:address":"18502 S. Normandie Avenue",
    "sg:city":"Gardena",
    "sg:classifiers":[
        {
            "category":"Food & Beverages",
            "subcategory":"Groceries & Convenience Stores",
            "type":"Retail Goods"
        }
    ],
    "sg:phone":"+1 310 327 5440",
    "sg:postcode":"90248",
    "sg:province":"CA",
    "wof:name":"T & G Liquor Market",
    "wof:placetype":"venue"
},
  "geometry": {"coordinates":[-118.298869,33.862783],"type":"Point"}
}