{
  "type": "Feature",
  "properties": {
    "addr:full":"922 Elm St Woodland CA 95695",
    "addr:housenumber":"922",
    "addr:postcode":"95695",
    "addr:street":"Elm St",
    "iso:country":"US",
    "sg:address":"922 Elm St",
    "sg:city":"Woodland",
    "sg:classifiers":[
        {
            "category":"Wholesale",
            "subcategory":"Computers",
            "type":"Manufacturing & Wholesale Goods"
        },
        {
            "category":"Shopping",
            "subcategory":"Computers & Home Electronics",
            "type":"Retail Goods"
        }
    ],
    "sg:phone":"+1 530 662 6044",
    "sg:postcode":"95695",
    "sg:province":"CA",
    "sg:tags":[
        "equipment",
        "dealer"
    ],
    "wof:name":"Chris' Computer",
    "wof:placetype":"venue"
},
  "geometry": {"coordinates":[-121.777192,38.668219],"type":"Point"}
}