{
  "type": "Feature",
  "properties": {
    "iso:country":"US",
    "sg:address":"390 Everett Ave",
    "sg:city":"Palo Alto",
    "sg:classifiers":[
        {
            "category":"Shopping",
            "subcategory":"Jewelry",
            "type":"Retail Goods"
        }
    ],
    "sg:phone":"+1 650 322 2514",
    "sg:postcode":"94301",
    "sg:province":"CA",
    "sg:tags":[
        "jeweler"
    ],
    "wof:name":"Fourteen Carrots Hand Crafted",
    "wof:placetype":"venue"
},
  "geometry": {"coordinates":[-122.163912,37.447512],"type":"Point"}
}