{
  "type": "Feature",
  "properties": {
    "addr:full":"16027 M St Mojave CA 93501",
    "addr:housenumber":"16027",
    "addr:postcode":"93501",
    "addr:street":"M St",
    "iso:country":"US",
    "sg:address":"16027 M St",
    "sg:city":"Mojave",
    "sg:classifiers":[
        {
            "category":"Organizations",
            "subcategory":"Religious Organization",
            "type":"Services"
        }
    ],
    "sg:phone":"+1 661 824 4287",
    "sg:postcode":"93501",
    "sg:province":"CA",
    "sg:tags":[
        "church"
    ],
    "wof:name":"Mojave Assembly Of God Church",
    "wof:placetype":"venue"
},
  "geometry": {"coordinates":[-118.170564,35.055384],"type":"Point"}
}