{
  "type": "Feature",
  "properties": {
    "iso:country":"US",
    "sg:address":"4101 Wayside Ln",
    "sg:city":"Carmichael",
    "sg:classifiers":[
        {
            "category":"Professional",
            "subcategory":"Management & Consulting",
            "type":"Services"
        }
    ],
    "sg:phone":"+1 916 972 8246",
    "sg:postcode":"95608",
    "sg:province":"CA",
    "sg:tags":[
        "house",
        "construction"
    ],
    "wof:name":"Aubin Construction",
    "wof:placetype":"venue"
},
  "geometry": {"coordinates":[-121.325619,38.638667],"type":"Point"}
}