{
  "type": "Feature",
  "properties": {
    "iso:country":"US",
    "sg:address":"118 Main St",
    "sg:city":"Watsonville",
    "sg:classifiers":[
        {
            "category":"Bars & Pubs",
            "type":"Food & Drink"
        }
    ],
    "sg:phone":"+1 831 722 3117",
    "sg:postcode":"95076",
    "sg:province":"CA",
    "wof:name":"El Tenampa",
    "wof:placetype":"venue"
},
  "geometry": {"coordinates":[-121.752939,36.906837],"type":"Point"}
}