{
  "type": "Feature",
  "properties": {
    "addr:full":"897 Cotting Ln Vacaville CA 95688",
    "addr:housenumber":"897",
    "addr:postcode":"95688",
    "addr:street":"Cotting Ln",
    "iso:country":"US",
    "sg:address":"897 Cotting Ln",
    "sg:city":"Vacaville",
    "sg:classifiers":[
        {
            "category":"Organizations",
            "subcategory":"Community Association",
            "type":"Services"
        }
    ],
    "sg:phone":"+1 707 448 6824",
    "sg:postcode":"95688",
    "sg:province":"CA",
    "sg:tags":[
        "fraternal"
    ],
    "wof:name":"Masonic Lodge",
    "wof:placetype":"venue"
},
  "geometry": {"coordinates":[-121.957519,38.396882],"type":"Point"}
}