{
  "type": "Feature",
  "properties": {
    "addr:full":"533 W Victoria St Santa Barbara CA 93101",
    "addr:housenumber":"533",
    "addr:postcode":"93101",
    "addr:street":"W Victoria St",
    "iso:country":"US",
    "sg:address":"533 W Victoria St",
    "sg:city":"Santa Barbara",
    "sg:classifiers":[
        {
            "category":"Real Estate",
            "subcategory":"Real Estate Operator",
            "type":"Services"
        }
    ],
    "sg:phone":"+1 805 965 2337",
    "sg:postcode":"93101",
    "sg:province":"CA",
    "sg:tags":[
        "apartment"
    ],
    "wof:name":"Casa Victoria Apartments",
    "wof:placetype":"venue"
},
  "geometry": {"coordinates":[-119.712243,34.418107],"type":"Point"}
}