{
  "type": "Feature",
  "properties": {
    "iso:country":"US",
    "sg:address":"10595 E River St",
    "sg:city":"Truckee",
    "sg:classifiers":[
        {
            "category":"Wholesale",
            "subcategory":"Poultry",
            "type":"Manufacturing & Wholesale Goods"
        }
    ],
    "sg:phone":"+1 530 587 3272",
    "sg:postcode":"96161",
    "sg:province":"CA",
    "sg:tags":[
        "eggs"
    ],
    "wof:name":"Curran Distributing",
    "wof:placetype":"venue"
},
  "geometry": {"coordinates":[-120.18368599999999,39.327296],"type":"Point"}
}