{
  "type": "Feature",
  "properties": {
    "iso:country":"US",
    "sg:address":"373 4th St",
    "sg:city":"Oakland",
    "sg:classifiers":[
        {
            "category":"Insurance",
            "subcategory":"Hazard Insurance",
            "type":"Services"
        }
    ],
    "sg:phone":"+1 510 893 1696",
    "sg:postcode":"94607",
    "sg:province":"CA",
    "sg:tags":[
        "profit",
        "sharing",
        "pension",
        "plan"
    ],
    "wof:name":"Pension Specialist Inc",
    "wof:placetype":"venue"
},
  "geometry": {"coordinates":[-122.27396299999999,37.796724],"type":"Point"}
}