{
  "type": "Feature",
  "properties": {
    "addr:full":"5320 State Rte 49 Mariposa CA 95338",
    "addr:housenumber":"5320",
    "addr:postcode":"95338",
    "addr:street":"State Rte 49",
    "iso:country":"US",
    "sg:address":"5320 State Rte 49",
    "sg:city":"Mariposa",
    "sg:classifiers":[
        {
            "category":"Professional",
            "subcategory":"Lawyer & Legal Services",
            "type":"Services"
        }
    ],
    "sg:phone":"+1 209 966 6111",
    "sg:postcode":"95338",
    "sg:province":"CA",
    "sg:tags":[
        "attorney"
    ],
    "wof:name":"Starchman Law Offices",
    "wof:placetype":"venue"
},
  "geometry": {"coordinates":[-119.984405,37.498713],"type":"Point"}
}