{
  "type": "Feature",
  "properties": {
    "iso:country":"US",
    "sg:address":"4325 Moorpark Ave",
    "sg:city":"San Jose",
    "sg:classifiers":[
        {
            "category":"Health Services",
            "subcategory":"Clinic",
            "type":"Services"
        }
    ],
    "sg:phone":"+1 408 996 0335",
    "sg:postcode":"95129",
    "sg:province":"CA",
    "wof:name":"Maylin Health Ctr",
    "wof:placetype":"venue"
},
  "geometry": {"coordinates":[-121.975994,37.315981],"type":"Point"}
}