{
  "type": "Feature",
  "properties": {
    "addr:full":"1509 N Main St Santa Ana CA 92701",
    "addr:housenumber":"1509",
    "addr:postcode":"92701",
    "addr:street":"N Main St",
    "iso:country":"US",
    "sg:address":"1509 N Main St",
    "sg:city":"Santa Ana",
    "sg:classifiers":[
        {
            "category":"Health Services",
            "subcategory":"Dentist",
            "type":"Services"
        }
    ],
    "sg:phone":"+1 714 542 2224",
    "sg:postcode":"92701",
    "sg:province":"CA",
    "wof:name":"Main Street Dentistry",
    "wof:placetype":"venue"
},
  "geometry": {"coordinates":[-117.86740500000001,33.757928],"type":"Point"}
}