{
  "type": "Feature",
  "properties": {
    "iso:country":"US",
    "sg:address":"3829 Torrance Blvd",
    "sg:city":"Torrance",
    "sg:classifiers":[
        {
            "category":"Fast Food",
            "type":"Food & Drink"
        },
        {
            "category":"Restaurant",
            "type":"Food & Drink"
        }
    ],
    "sg:phone":"+1 310 406 3063",
    "sg:postcode":"90503",
    "sg:province":"CA",
    "sg:tags":[
        "burger"
    ],
    "sg:website":"www.habitburger.com",
    "wof:name":"The Habit Burger Grill",
    "wof:placetype":"venue"
},
  "geometry": {"coordinates":[-118.35414,33.837594],"type":"Point"}
}