{
  "type": "Feature",
  "properties": {
    "iso:country":"US",
    "sg:address":"1433 W 14th St",
    "sg:city":"Long Beach",
    "sg:classifiers":[
        {
            "category":"Manufacturing",
            "subcategory":"Apparel",
            "type":"Manufacturing & Wholesale Goods"
        }
    ],
    "sg:phone":"+1 562 435 0306",
    "sg:postcode":"90813",
    "sg:province":"CA",
    "sg:tags":[
        "clothing"
    ],
    "wof:name":"Crystal Fashions",
    "wof:placetype":"venue"
},
  "geometry": {"coordinates":[-118.211697,33.78384],"type":"Point"}
}