{
  "type": "Feature",
  "properties": {
    "addr:full":"1028 Howard St San Francisco CA 94103",
    "addr:housenumber":"1028",
    "addr:postcode":"94103",
    "addr:street":"Howard St",
    "iso:country":"US",
    "sg:address":"1028 Howard St",
    "sg:city":"San Francisco",
    "sg:classifiers":[
        {
            "category":"Organizations",
            "subcategory":"Political Organization",
            "type":"Services"
        }
    ],
    "sg:phone":"+1 415 701 7090",
    "sg:postcode":"94103",
    "sg:province":"CA",
    "sg:website":"www.sfgreenparty.org",
    "wof:name":"San Francisco Green Party",
    "wof:placetype":"venue"
},
  "geometry": {"coordinates":[-122.408248,37.77899],"type":"Point"}
}