{
  "type": "Feature",
  "properties": {
    "iso:country":"US",
    "sg:address":"13605 Sherman Way",
    "sg:city":"Van Nuys",
    "sg:classifiers":[
        {
            "category":"Retail",
            "subcategory":"Auto Repair",
            "type":"Services"
        }
    ],
    "sg:phone":"+1 818 997 8326",
    "sg:postcode":"91405",
    "sg:province":"CA",
    "wof:name":"Speedy Transmission Center Inc",
    "wof:placetype":"venue"
},
  "geometry": {"coordinates":[-118.43000000000001,34.201099],"type":"Point"}
}