{
  "type": "Feature",
  "properties": {
    "addr:full":"939 Eaglesnest Dr Corona CA 92879",
    "addr:housenumber":"939",
    "addr:postcode":"92879",
    "addr:street":"Eaglesnest Dr",
    "iso:country":"US",
    "sg:address":"939 Eaglesnest Dr",
    "sg:city":"Corona",
    "sg:classifiers":[
        {
            "category":"Professional",
            "type":"Services"
        }
    ],
    "sg:phone":"+1 951 371 6742",
    "sg:postcode":"92879",
    "sg:province":"CA",
    "wof:name":"Mikeel Corporation",
    "wof:placetype":"venue"
},
  "geometry": {"coordinates":[-117.54405300000001,33.896636],"type":"Point"}
}