{
  "type": "Feature",
  "properties": {
    "addr:full":"12982 Homestead Pl Chino CA 91710",
    "addr:housenumber":"12982",
    "addr:postcode":"91710",
    "addr:street":"Homestead Pl",
    "iso:country":"US",
    "sg:address":"12982 Homestead Pl",
    "sg:city":"Chino",
    "sg:classifiers":[
        {
            "category":"Bakery",
            "type":"Food & Drink"
        }
    ],
    "sg:phone":"+1 909 930 2776",
    "sg:postcode":"91710",
    "sg:province":"CA",
    "wof:name":"Grayson Cookie",
    "wof:placetype":"venue"
},
  "geometry": {"coordinates":[-117.700647,34.017687],"type":"Point"}
}