{
  "type": "Feature",
  "properties": {
    "iso:country":"US",
    "sg:address":"14451 Foothill Blvd",
    "sg:city":"Fontana",
    "sg:classifiers":[
        {
            "category":"Health Services",
            "subcategory":"Doctor",
            "type":"Services"
        },
        {
            "category":"Health Services",
            "subcategory":"Dentist",
            "type":"Services"
        }
    ],
    "sg:phone":"+1 909 355 6400",
    "sg:postcode":"92335",
    "sg:province":"CA",
    "sg:tags":[
        "dentists-oral",
        "physician",
        "maxillofacial",
        "surgeons",
        "surgery",
        "oral"
    ],
    "wof:name":"Marilou P Medina Dmd",
    "wof:placetype":"venue"
},
  "geometry": {"coordinates":[-117.48983699999999,34.106561],"type":"Point"}
}