{
  "type": "Feature",
  "properties": {
    "iso:country":"US",
    "sg:address":"1901 Orange Tree Ln # 100",
    "sg:city":"Redlands",
    "sg:classifiers":[
        {
            "category":"Insurance",
            "subcategory":"Insurance Agent",
            "type":"Services"
        },
        {
            "category":"Insurance",
            "subcategory":"Hazard Insurance",
            "type":"Services"
        }
    ],
    "sg:phone":"+1 909 307 6076",
    "sg:postcode":"92374",
    "sg:province":"CA",
    "sg:tags":[
        "auto",
        "commercial",
        "business"
    ],
    "sg:website":"http://www.centralcityinsurance.com",
    "wof:name":"Central City Insurance",
    "wof:placetype":"venue"
},
  "geometry": {"coordinates":[-117.22004699999999,34.067741],"type":"Point"}
}