{
  "type": "Feature",
  "properties": {
    "iso:country":"US",
    "sg:address":"4016 Wayside Ln",
    "sg:city":"Carmichael",
    "sg:classifiers":[
        {
            "category":"Retail",
            "subcategory":"Auto Repair",
            "type":"Services"
        }
    ],
    "sg:phone":"+1 916 971 9438",
    "sg:postcode":"95608",
    "sg:province":"CA",
    "sg:tags":[
        "body",
        "automobile",
        "painting"
    ],
    "wof:name":"Schauffele's Body & Paint",
    "wof:placetype":"venue"
},
  "geometry": {"coordinates":[-121.325653,38.636141],"type":"Point"}
}