{
  "type": "Feature",
  "properties": {
    "addr:full":"2250 Geary Blvd San Francisco CA 94115",
    "addr:housenumber":"2250",
    "addr:postcode":"94115",
    "addr:street":"Geary Blvd",
    "iso:country":"US",
    "sg:address":"2250 Geary Blvd",
    "sg:city":"San Francisco",
    "sg:classifiers":[
        {
            "category":"Manufacturing",
            "subcategory":"Printing",
            "type":"Manufacturing & Wholesale Goods"
        }
    ],
    "sg:phone":"+1 415 563 6033",
    "sg:postcode":"94115",
    "sg:province":"CA",
    "sg:tags":[
        "periodical"
    ],
    "wof:name":"Argonaut Press",
    "wof:placetype":"venue"
},
  "geometry": {"coordinates":[-122.440489,37.783349],"type":"Point"}
}