{
  "type": "Feature",
  "properties": {
    "addr:full":"1515 W Olympic Blvd Los Angeles CA 90015",
    "addr:housenumber":"1515",
    "addr:postcode":"90015",
    "addr:street":"W Olympic Blvd",
    "iso:country":"US",
    "sg:address":"1515 W Olympic Blvd",
    "sg:city":"Los Angeles",
    "sg:classifiers":[
        {
            "category":"Health Services",
            "subcategory":"Doctor",
            "type":"Services"
        }
    ],
    "sg:phone":"+1 213 384 4100",
    "sg:postcode":"90015",
    "sg:province":"CA",
    "sg:tags":[
        "dentist"
    ],
    "wof:name":"Olympic Family Dentistry",
    "wof:placetype":"venue"
},
  "geometry": {"coordinates":[-118.272983,34.048717],"type":"Point"}
}