{
  "type": "Feature",
  "properties": {
    "addr:full":"2551 C Casey Ave Mountain View CA 94043",
    "addr:housenumber":"2551 c",
    "addr:postcode":"94043",
    "addr:street":"Casey Ave",
    "iso:country":"US",
    "sg:address":"2551 C Casey Ave",
    "sg:city":"Mountain View",
    "sg:classifiers":[
        {
            "category":"Professional",
            "subcategory":"Computer Services",
            "type":"Services"
        }
    ],
    "sg:phone":"+1 877 272 6337",
    "sg:postcode":"94043",
    "sg:province":"CA",
    "sg:tags":[
        "sales",
        "marketing",
        "branded-items",
        "promotional-items",
        "promotional-products",
        "corporate-giveaways",
        "corporate-gifts",
        "tradeshow-giveaways"
    ],
    "sg:website":"http://www.branders.com",
    "wof:name":"Branders.com",
    "wof:placetype":"venue"
},
  "geometry": {"coordinates":[-122.09877,37.43214],"type":"Point"}
}