{
  "type": "Feature",
  "properties": {
    "iso:country":"US",
    "sg:address":"1002 Crows Landing Rd",
    "sg:city":"Modesto",
    "sg:classifiers":[
        {
            "category":"Restaurant",
            "type":"Food & Drink"
        }
    ],
    "sg:phone":"+1 209 524 7686",
    "sg:postcode":"95351",
    "sg:province":"CA",
    "sg:tags":[
        "mexican"
    ],
    "wof:name":"Navarro's Produce",
    "wof:placetype":"venue"
},
  "geometry": {"coordinates":[-120.99400300000001,37.614899],"type":"Point"}
}