{
  "type": "Feature",
  "properties": {
    "iso:country":"US",
    "sg:address":"151 87th St",
    "sg:city":"Daly City",
    "sg:classifiers":[
        {
            "category":"Personal",
            "subcategory":"Beauty Salon",
            "type":"Services"
        }
    ],
    "sg:phone":"+1 650 992 7101",
    "sg:postcode":"94015",
    "sg:province":"CA",
    "wof:name":"Jan Four Hair",
    "wof:placetype":"venue"
},
  "geometry": {"coordinates":[-122.471694,37.693183],"type":"Point"}
}