{
  "type": "Feature",
  "properties": {
    "addr:full":"4342 Thornton Ave Fremont CA 94536",
    "addr:housenumber":"4342",
    "addr:postcode":"94536",
    "addr:street":"Thornton Ave",
    "iso:country":"US",
    "sg:address":"4342 Thornton Ave",
    "sg:city":"Fremont",
    "sg:classifiers":[
        {
            "category":"Restaurant",
            "type":"Food & Drink"
        }
    ],
    "sg:menulink":"http://www.allmenus.com/ca/fremont/137769-arianas-kabob-house/menu/",
    "sg:phone":"+1 510 792 6122",
    "sg:postcode":"94536",
    "sg:province":"CA",
    "sg:tags":[
        "middle",
        "eastern"
    ],
    "wof:name":"Ariana's Kabob House",
    "wof:placetype":"venue"
},
  "geometry": {"coordinates":[-122.01463800000001,37.556632],"type":"Point"}
}