{
  "type": "Feature",
  "properties": {
    "iso:country":"US",
    "sg:address":"40218 Holden Cir",
    "sg:city":"Temecula",
    "sg:classifiers":[
        {
            "category":"Wholesale",
            "subcategory":"Medical Equipment & Supplies",
            "type":"Manufacturing & Wholesale Goods"
        }
    ],
    "sg:phone":"+1 951 699 1369",
    "sg:postcode":"92591",
    "sg:province":"CA",
    "wof:name":"Chaparral Medical Products",
    "wof:placetype":"venue"
},
  "geometry": {"coordinates":[-117.125975,33.537094],"type":"Point"}
}