{
  "type": "Feature",
  "properties": {
    "addr:full":"1628 Harbor St Stockton CA 95203",
    "addr:housenumber":"1628",
    "addr:postcode":"95203",
    "addr:street":"Harbor St",
    "iso:country":"US",
    "sg:address":"1628 Harbor St",
    "sg:city":"Stockton",
    "sg:classifiers":[
        {
            "category":"Retail",
            "subcategory":"Auto Rental",
            "type":"Services"
        }
    ],
    "sg:phone":"+1 209 948 1224",
    "sg:postcode":"95203",
    "sg:province":"CA",
    "sg:tags":[
        "renting",
        "truck",
        "leasing"
    ],
    "wof:name":"U-Haul Co",
    "wof:placetype":"venue"
},
  "geometry": {"coordinates":[-121.313084,37.947542],"type":"Point"}
}