{
  "type": "Feature",
  "properties": {
    "addr:full":"833 W Glenoaks Blvd Glendale CA 91202",
    "addr:housenumber":"833",
    "addr:postcode":"91202",
    "addr:street":"W Glenoaks Blvd",
    "iso:country":"US",
    "sg:address":"833 W Glenoaks Blvd",
    "sg:city":"Glendale",
    "sg:classifiers":[
        {
            "category":"Health Services",
            "subcategory":"Chiropractor",
            "type":"Services"
        }
    ],
    "sg:phone":"+1 818 240 0065",
    "sg:postcode":"91202",
    "sg:province":"CA",
    "wof:name":"Ekmekdjian Missak DC",
    "wof:placetype":"venue"
},
  "geometry": {"coordinates":[-118.274002,34.160702],"type":"Point"}
}