{
  "type": "Feature",
  "properties": {
    "iso:country":"US",
    "sg:address":"7522 Clairemont Mesa Blvd",
    "sg:city":"San Diego",
    "sg:classifiers":[
        {
            "category":"Retail",
            "subcategory":"Veterinary Services",
            "type":"Services"
        }
    ],
    "sg:phone":"+1 858 634 5430",
    "sg:postcode":"92111",
    "sg:province":"CA",
    "sg:tags":[
        "veterinarian"
    ],
    "sg:website":"www.vicsd.com",
    "wof:name":"Veterinary Imaging Center of San Diego - VICSD",
    "wof:placetype":"venue"
},
  "geometry": {"coordinates":[-117.15682,32.832821],"type":"Point"}
}