{
  "type": "Feature",
  "properties": {
    "iso:country":"US",
    "sg:address":"218 S Benjamin Dr",
    "sg:city":"Stateline",
    "sg:classifiers":[
        {
            "category":"Wholesale",
            "subcategory":"Vending Machines",
            "type":"Manufacturing & Wholesale Goods"
        }
    ],
    "sg:phone":"+1 775 588 3894",
    "sg:postcode":"89449",
    "sg:province":"CA",
    "wof:name":"F & H Unlimited",
    "wof:placetype":"venue"
},
  "geometry": {"coordinates":[-119.89146,38.973147],"type":"Point"}
}