{
  "type": "Feature",
  "properties": {
    "iso:country":"US",
    "sg:address":"1950 W Corporate Way",
    "sg:city":"Anaheim",
    "sg:classifiers":[
        {
            "category":"Professional",
            "subcategory":"Advertising",
            "type":"Services"
        }
    ],
    "sg:phone":"+1 714 772 3282",
    "sg:postcode":"92801",
    "sg:province":"CA",
    "sg:tags":[
        "mailing",
        "list"
    ],
    "wof:name":"Direct List Technology Inc",
    "wof:placetype":"venue"
},
  "geometry": {"coordinates":[-117.951183,33.837674],"type":"Point"}
}