{
  "type": "Feature",
  "properties": {
    "iso:country":"US",
    "sg:address":"3 Lagoon Dr",
    "sg:city":"Redwood City",
    "sg:classifiers":[
        {
            "category":"Manufacturing",
            "subcategory":"Wood Products",
            "type":"Manufacturing & Wholesale Goods"
        }
    ],
    "sg:phone":"+1 650 631 5195",
    "sg:postcode":"94065",
    "sg:province":"CA",
    "sg:tags":[
        "mfg"
    ],
    "wof:name":"Gei World Co 372 1",
    "wof:placetype":"venue"
},
  "geometry": {"coordinates":[-122.263566,37.526228],"type":"Point"}
}