{
  "type": "Feature",
  "properties": {
    "addr:full":"30993 Huntwood Ave Hayward CA 94544",
    "addr:postcode":"30993;94544",
    "addr:street":"Huntwood Ave",
    "iso:country":"US",
    "sg:address":"30993 Huntwood Ave",
    "sg:city":"Hayward",
    "sg:classifiers":[
        {
            "category":"Retail",
            "subcategory":"Auto Repair",
            "type":"Services"
        }
    ],
    "sg:phone":"+1 510 489 8987",
    "sg:postcode":"94544",
    "sg:province":"CA",
    "sg:tags":[
        "body",
        "automobile",
        "painting",
        "repairing"
    ],
    "wof:name":"Protoquick",
    "wof:placetype":"venue"
},
  "geometry": {"coordinates":[-122.054832,37.611523],"type":"Point"}
}