{
  "type": "Feature",
  "properties": {
    "addr:full":"10053 Judy Ave Cupertino CA 95014",
    "addr:housenumber":"10053",
    "addr:postcode":"95014",
    "addr:street":"Judy Ave",
    "iso:country":"US",
    "sg:address":"10053 Judy Ave",
    "sg:city":"Cupertino",
    "sg:classifiers":[
        {
            "category":"Wholesale",
            "subcategory":"Chemicals & Plastics",
            "type":"Manufacturing & Wholesale Goods"
        }
    ],
    "sg:phone":"+1 408 446 0438",
    "sg:postcode":"95014",
    "sg:province":"CA",
    "wof:name":"Christian Juvan",
    "wof:placetype":"venue"
},
  "geometry": {"coordinates":[-122.00545700000001,37.320189],"type":"Point"}
}