{
  "type": "Feature",
  "properties": {
    "iso:country":"US",
    "sg:address":"3535 California Avenue",
    "sg:city":"San Francisco",
    "sg:classifiers":[
        {
            "category":"Personal",
            "subcategory":"Beauty Salon",
            "type":"Services"
        }
    ],
    "sg:phone":"+1 415 876 0322",
    "sg:postcode":"94118",
    "sg:province":"CA",
    "sg:tags":[
        "hair"
    ],
    "wof:name":"Lawrence Orta",
    "wof:placetype":"venue"
},
  "geometry": {"coordinates":[-122.452286,37.7864],"type":"Point"}
}