{
  "type": "Feature",
  "properties": {
    "addr:full":"4588 Whittier Boulevard Los Angeles CA 90022",
    "addr:housenumber":"4588",
    "addr:postcode":"90022",
    "addr:street":"Whittier Boulevard",
    "iso:country":"US",
    "sg:address":"4588 Whittier Boulevard",
    "sg:city":"Los Angeles",
    "sg:classifiers":[
        {
            "category":"Health Services",
            "subcategory":"Doctor",
            "type":"Services"
        }
    ],
    "sg:phone":"+1 323 265 2917",
    "sg:postcode":"90022",
    "sg:province":"CA",
    "wof:name":"Haro Carlos MD",
    "wof:placetype":"venue"
},
  "geometry": {"coordinates":[-118.168091,34.022577],"type":"Point"}
}