{
  "type": "Feature",
  "properties": {
    "addr:full":"12820 Beach Blvd Stanton CA 90680",
    "addr:housenumber":"12820",
    "addr:postcode":"ca 90680",
    "addr:street":"Beach Blvd",
    "iso:country":"US",
    "sg:address":"12820 Beach Blvd",
    "sg:city":"Stanton",
    "sg:classifiers":[
        {
            "category":"Shopping",
            "subcategory":"Gifts & Souvenirs",
            "type":"Retail Goods"
        }
    ],
    "sg:phone":"+1 714 891 2884",
    "sg:postcode":"90680",
    "sg:province":"CA",
    "wof:name":"Outlet 21 Sangwoo Cho",
    "wof:placetype":"venue"
},
  "geometry": {"coordinates":[-117.992717,33.774988],"type":"Point"}
}