{
  "type": "Feature",
  "properties": {
    "addr:full":"403 Central Ave Shafter CA 93263",
    "addr:housenumber":"403",
    "addr:postcode":"93263",
    "addr:street":"Central Ave",
    "iso:country":"US",
    "sg:address":"403 Central Ave",
    "sg:city":"Shafter",
    "sg:classifiers":[
        {
            "category":"Wholesale",
            "subcategory":"Fruits & Vegetables",
            "type":"Manufacturing & Wholesale Goods"
        }
    ],
    "sg:phone":"+1 661 746 6554",
    "sg:postcode":"93263",
    "sg:province":"CA",
    "sg:tags":[
        "potato"
    ],
    "wof:name":"Gonzales Potato Co",
    "wof:placetype":"venue"
},
  "geometry": {"coordinates":[-119.274063,35.503269],"type":"Point"}
}