{
  "type": "Feature",
  "properties": {
    "iso:country":"US",
    "sg:address":"4410 Glacier Ave",
    "sg:city":"San Diego",
    "sg:classifiers":[
        {
            "category":"Autos & Motor Vehicles",
            "subcategory":"Boat Sales",
            "type":"Retail Goods"
        }
    ],
    "sg:phone":"+1 619 281 8597",
    "sg:postcode":"92120",
    "sg:province":"CA",
    "sg:tags":[
        "equipment",
        "marine",
        "supply"
    ],
    "wof:name":"Automated Logistics Svc",
    "wof:placetype":"venue"
},
  "geometry": {"coordinates":[-117.097715,32.788767],"type":"Point"}
}