{
  "type": "Feature",
  "properties": {
    "iso:country":"US",
    "sg:address":"504 Pleasant Valley Rd",
    "sg:city":"Diamond Springs",
    "sg:classifiers":[
        {
            "category":"Social Services",
            "type":"Services"
        }
    ],
    "sg:phone":"+1 530 306 0625",
    "sg:postcode":"95619",
    "sg:province":"CA",
    "sg:tags":[
        "counselor",
        "marriage",
        "family"
    ],
    "wof:name":"Susan Lewis",
    "wof:placetype":"venue"
},
  "geometry": {"coordinates":[-120.81735399999999,38.69388],"type":"Point"}
}