{
  "type": "Feature",
  "properties": {
    "iso:country":"US",
    "sg:address":"578 Riviera Cir",
    "sg:city":"Larkspur",
    "sg:classifiers":[
        {
            "category":"Professional",
            "type":"Services"
        }
    ],
    "sg:phone":"+1 415 924 2541",
    "sg:postcode":"94939",
    "sg:province":"CA",
    "wof:name":"Darryl Foreman Land Planning",
    "wof:placetype":"venue"
},
  "geometry": {"coordinates":[-122.526624,37.940651],"type":"Point"}
}