{
  "type": "Feature",
  "properties": {
    "iso:country":"US",
    "sg:address":"5545 Laird Rd",
    "sg:city":"Loomis",
    "sg:classifiers":[
        {
            "category":"Professional",
            "type":"Services"
        }
    ],
    "sg:phone":"+1 916 652 4989",
    "sg:postcode":"95650",
    "sg:province":"CA",
    "wof:name":"California Finance Concepts In",
    "wof:placetype":"venue"
},
  "geometry": {"coordinates":[-121.169309,38.787168],"type":"Point"}
}