{
  "type": "Feature",
  "properties": {
    "addr:full":"11438 Kenyon Way Alta Loma CA 91701",
    "addr:housenumber":"11438",
    "addr:postcode":"91701",
    "addr:street":"Kenyon Way",
    "iso:country":"US",
    "sg:address":"11438 Kenyon Way",
    "sg:city":"Alta Loma",
    "sg:classifiers":[
        {
            "category":"Retail",
            "subcategory":"Veterinary Services",
            "type":"Services"
        }
    ],
    "sg:phone":"+1 909 944 8944",
    "sg:postcode":"91701",
    "sg:province":"CA",
    "sg:tags":[
        "hospital",
        "animal"
    ],
    "wof:name":"Victoria Animal Hospital",
    "wof:placetype":"venue"
},
  "geometry": {"coordinates":[-117.555902,34.133926],"type":"Point"}
}