{
  "type": "Feature",
  "properties": {
    "addr:full":"14542 Ventura Blvd Sherman Oaks CA 91403",
    "addr:housenumber":"14542",
    "addr:postcode":"91403",
    "addr:street":"Ventura Blvd",
    "iso:country":"US",
    "sg:address":"14542 Ventura Blvd",
    "sg:city":"Sherman Oaks",
    "sg:classifiers":[
        {
            "category":"Travel",
            "subcategory":"Travel Agent",
            "type":"Entertainment"
        }
    ],
    "sg:phone":"+1 818 990 4995",
    "sg:postcode":"91403",
    "sg:province":"CA",
    "sg:tags":[
        "agency",
        "bureau"
    ],
    "wof:name":"Brasil Tours",
    "wof:placetype":"venue"
},
  "geometry": {"coordinates":[-118.450137,34.151052],"type":"Point"}
}