{
  "type": "Feature",
  "properties": {
    "iso:country":"US",
    "sg:address":"1802 Lake Dr",
    "sg:city":"Cardiff By The Sea",
    "sg:classifiers":[
        {
            "category":"Professional",
            "subcategory":"Management & Consulting",
            "type":"Services"
        }
    ],
    "sg:phone":"+1 760 753 2150",
    "sg:postcode":"92007",
    "sg:province":"CA",
    "sg:tags":[
        "retail",
        "direct",
        "sales"
    ],
    "wof:name":"Helenick Delicacies",
    "wof:placetype":"venue"
},
  "geometry": {"coordinates":[-117.266614,33.022934],"type":"Point"}
}