{
  "type": "Feature",
  "properties": {
    "addr:full":"2623 S Patton Ave San Pedro CA 90731",
    "addr:housenumber":"2623",
    "addr:postcode":"ca 90731",
    "addr:street":"S Patton Ave",
    "iso:country":"US",
    "sg:address":"2623 S Patton Ave",
    "sg:city":"San Pedro",
    "sg:classifiers":[
        {
            "category":"Building & Trades",
            "subcategory":"Construction",
            "type":"Services"
        }
    ],
    "sg:phone":"+1 310 704 3108",
    "sg:postcode":"90731",
    "sg:province":"CA",
    "sg:tags":[
        "contractor"
    ],
    "wof:name":"Giuseppe Pescetti Construction",
    "wof:placetype":"venue"
},
  "geometry": {"coordinates":[-118.305176,33.719493],"type":"Point"}
}