{
  "type": "Feature",
  "properties": {
    "iso:country":"US",
    "sg:address":"1447 Rollins Rd",
    "sg:city":"Burlingame",
    "sg:classifiers":[
        {
            "category":"Wholesale",
            "subcategory":"Machinery & Supplies",
            "type":"Manufacturing & Wholesale Goods"
        }
    ],
    "sg:phone":"+1 650 348 7247",
    "sg:postcode":"94010",
    "sg:province":"CA",
    "sg:tags":[
        "instrument",
        "surveying"
    ],
    "wof:name":"Haselbach Instruments",
    "wof:placetype":"venue"
},
  "geometry": {"coordinates":[-122.370515,37.592942],"type":"Point"}
}