{
  "type": "Feature",
  "properties": {
    "iso:country":"US",
    "sg:address":"2755 E Shaw Ave",
    "sg:city":"Fresno",
    "sg:classifiers":[
        {
            "category":"Professional",
            "subcategory":"Engineering",
            "type":"Services"
        }
    ],
    "sg:phone":"+1 559 294 7485",
    "sg:postcode":"93710",
    "sg:province":"CA",
    "sg:tags":[
        "engineer"
    ],
    "wof:name":"Harbison International Inc",
    "wof:placetype":"venue"
},
  "geometry": {"coordinates":[-119.736884,36.80847],"type":"Point"}
}