{
  "type": "Feature",
  "properties": {
    "addr:full":"26637 Agoura Rd Calabasas CA 91302",
    "addr:housenumber":"26637",
    "addr:postcode":"91302",
    "addr:street":"Agoura Rd",
    "iso:country":"US",
    "sg:address":"26637 Agoura Rd",
    "sg:city":"Calabasas",
    "sg:classifiers":[
        {
            "category":"Banks & Credit Unions",
            "subcategory":"Investment Brokerage",
            "type":"Services"
        }
    ],
    "sg:phone":"+1 818 708 6888",
    "sg:postcode":"91302",
    "sg:province":"CA",
    "sg:tags":[
        "consultant",
        "planning",
        "financial"
    ],
    "wof:name":"Planned Asset Management Inc",
    "wof:placetype":"venue"
},
  "geometry": {"coordinates":[-118.70339199999999,34.141798],"type":"Point"}
}