{
  "type": "Feature",
  "properties": {
    "iso:country":"US",
    "sg:address":"2210 Edelweiss Ave",
    "sg:city":"Oxnard",
    "sg:classifiers":[
        {
            "category":"Organizations",
            "subcategory":"Professional Association",
            "type":"Services"
        }
    ],
    "sg:phone":"+1 805 485 2893",
    "sg:postcode":"93036",
    "sg:province":"CA",
    "wof:name":"Orchard Lane Condominium Assn",
    "wof:placetype":"venue"
},
  "geometry": {"coordinates":[-119.181061,34.226374],"type":"Point"}
}