{
  "type": "Feature",
  "properties": {
    "iso:country":"US",
    "sg:address":"2341 Sunset Blvd",
    "sg:city":"Rocklin",
    "sg:classifiers":[
        {
            "category":"Food & Beverages",
            "subcategory":"Groceries & Convenience Stores",
            "type":"Retail Goods"
        }
    ],
    "sg:phone":"+1 916 632 0180",
    "sg:postcode":"95765",
    "sg:province":"CA",
    "sg:tags":[
        "grocer"
    ],
    "wof:name":"Bel Air Markets",
    "wof:placetype":"venue"
},
  "geometry": {"coordinates":[-121.263861,38.795003],"type":"Point"}
}