{
  "type": "Feature",
  "properties": {
    "iso:country":"US",
    "sg:address":"100 Corson St Lbby",
    "sg:city":"Pasadena",
    "sg:classifiers":[
        {
            "category":"Professional",
            "subcategory":"Accounting & Tax Preparation",
            "type":"Services"
        }
    ],
    "sg:phone":"+1 626 744 5100",
    "sg:postcode":"91103",
    "sg:province":"CA",
    "sg:tags":[
        "accountant"
    ],
    "wof:name":"Drachenberg Ariel E CPA",
    "wof:placetype":"venue"
},
  "geometry": {"coordinates":[-118.149002,34.1511],"type":"Point"}
}