{
  "type": "Feature",
  "properties": {
    "addr:full":"86 W Moltke St Daly City CA 94014",
    "addr:housenumber":"86",
    "addr:postcode":"94014",
    "addr:street":"W Moltke St",
    "iso:country":"US",
    "sg:address":"86 W Moltke St",
    "sg:city":"Daly City",
    "sg:classifiers":[
        {
            "category":"Building & Trades",
            "subcategory":"Plumbing",
            "type":"Services"
        }
    ],
    "sg:phone":"+1 650 755 3636",
    "sg:postcode":"94014",
    "sg:province":"CA",
    "sg:tags":[
        "plumbing",
        "contractor"
    ],
    "wof:name":"Edward's Plumbing Co",
    "wof:placetype":"venue"
},
  "geometry": {"coordinates":[-122.464977,37.694529],"type":"Point"}
}