{
  "type": "Feature",
  "properties": {
    "iso:country":"US",
    "sg:address":"6700 Topanga Canyon Blvd",
    "sg:city":"Canoga Park",
    "sg:classifiers":[
        {
            "category":"Coffee & Tea",
            "type":"Food & Drink"
        }
    ],
    "sg:menulink":"http://www.allmenus.com/ca/san-fernando-valley/117434-starbucks-coffee/menu/",
    "sg:phone":"+1 818 746 9922",
    "sg:postcode":"91303",
    "sg:province":"CA",
    "sg:tags":[
        "american"
    ],
    "wof:name":"Starbucks Coffee",
    "wof:placetype":"venue"
},
  "geometry": {"coordinates":[-118.605853,34.192112],"type":"Point"}
}