{
  "type": "Feature",
  "properties": {
    "addr:full":"2580 E Main St Ventura CA 93003",
    "addr:housenumber":"2580",
    "addr:postcode":"93003",
    "addr:street":"E Main St",
    "iso:country":"US",
    "sg:address":"2580 E Main St",
    "sg:city":"Ventura",
    "sg:classifiers":[
        {
            "category":"Health Services",
            "subcategory":"Health Practitioner",
            "type":"Services"
        }
    ],
    "sg:phone":"+1 805 641 1720",
    "sg:postcode":"93003",
    "sg:province":"CA",
    "sg:tags":[
        "psychologist"
    ],
    "wof:name":"George J Nicastro",
    "wof:placetype":"venue"
},
  "geometry": {"coordinates":[-119.26287499999999,34.275607],"type":"Point"}
}