{
  "type": "Feature",
  "properties": {
    "iso:country":"US",
    "sg:address":"989 E Topeka St",
    "sg:city":"Pasadena",
    "sg:classifiers":[
        {
            "category":"Arts & Performance",
            "subcategory":"Theater",
            "type":"Entertainment"
        }
    ],
    "sg:phone":"+1 626 312 7125",
    "sg:postcode":"91104",
    "sg:province":"CA",
    "sg:tags":[
        "live",
        "music"
    ],
    "wof:name":"Dmads Productions",
    "wof:placetype":"venue"
},
  "geometry": {"coordinates":[-118.131199,34.174664],"type":"Point"}
}