{
  "type": "Feature",
  "properties": {
    "iso:country":"US",
    "sg:address":"2000 E 3rd Ave",
    "sg:city":"San Mateo",
    "sg:classifiers":[
        {
            "category":"Retail",
            "subcategory":"Storage",
            "type":"Services"
        }
    ],
    "sg:phone":"+1 650 342 9595",
    "sg:postcode":"94404",
    "sg:province":"CA",
    "sg:tags":[
        "self"
    ],
    "sg:website":"www.selfstoragesanmateo.com",
    "wof:name":"All American Self Storage",
    "wof:placetype":"venue"
},
  "geometry": {"coordinates":[-122.29772,37.571659],"type":"Point"}
}