{
  "type": "Feature",
  "properties": {
    "addr:full":"440 Main St Huntington Beach CA 92648",
    "addr:housenumber":"440",
    "addr:postcode":"92648",
    "addr:street":"Main St",
    "iso:country":"US",
    "sg:address":"440 Main St",
    "sg:city":"Huntington Beach",
    "sg:classifiers":[
        {
            "category":"Sports & Exercise",
            "subcategory":"Gym",
            "type":"Entertainment"
        }
    ],
    "sg:phone":"+1 714 374 7448",
    "sg:postcode":"92648",
    "sg:province":"CA",
    "sg:website":"www.tspot.org",
    "wof:name":"The T Spot",
    "wof:placetype":"venue"
},
  "geometry": {"coordinates":[-117.998881,33.660778],"type":"Point"}
}