{
  "type": "Feature",
  "properties": {
    "addr:full":"3075 N Fair Oaks Ave Altadena CA 91001",
    "addr:housenumber":"3075",
    "addr:postcode":"91001",
    "addr:street":"N Fair Oaks Ave",
    "iso:country":"US",
    "sg:address":"3075 N Fair Oaks Ave",
    "sg:city":"Altadena",
    "sg:classifiers":[
        {
            "category":"Wholesale",
            "subcategory":"Medical Equipment & Supplies",
            "type":"Manufacturing & Wholesale Goods"
        }
    ],
    "sg:phone":"+1 626 794 3094",
    "sg:postcode":"91001",
    "sg:province":"CA",
    "wof:name":"Prudential Medical Supplies",
    "wof:placetype":"venue"
},
  "geometry": {"coordinates":[-118.145797,34.197844],"type":"Point"}
}