{
  "type": "Feature",
  "properties": {
    "addr:full":"239 Cassady St Vallejo CA 94590",
    "addr:housenumber":"239",
    "addr:postcode":"94590",
    "addr:street":"Cassady St",
    "iso:country":"US",
    "sg:address":"239 Cassady St",
    "sg:city":"Vallejo",
    "sg:classifiers":[
        {
            "category":"Real Estate",
            "subcategory":"Real Estate Agent",
            "type":"Services"
        }
    ],
    "sg:phone":"+1 707 556 3100",
    "sg:postcode":"94590",
    "sg:province":"CA",
    "wof:name":"Magee Real Estate Svc",
    "wof:placetype":"venue"
},
  "geometry": {"coordinates":[-122.23898,38.10734],"type":"Point"}
}