{
  "type": "Feature",
  "properties": {
    "addr:full":"134 Robles Way Vallejo CA 94591",
    "addr:housenumber":"134",
    "addr:postcode":"94591",
    "addr:street":"Robles Way",
    "iso:country":"US",
    "sg:address":"134 Robles Way",
    "sg:city":"Vallejo",
    "sg:phone":"+1 707 552 9700",
    "sg:postcode":"94591",
    "sg:province":"CA",
    "wof:name":"J's Garden",
    "wof:placetype":"venue"
},
  "geometry": {"coordinates":[-122.21097899999999,38.083502],"type":"Point"}
}