{
  "type": "Feature",
  "properties": {
    "addr:full":"10316 Hawley Rd El Cajon CA 92021",
    "addr:housenumber":"10316",
    "addr:postcode":"92021",
    "addr:street":"Hawley Rd",
    "iso:country":"US",
    "sg:address":"10316 Hawley Rd",
    "sg:city":"El Cajon",
    "sg:classifiers":[
        {
            "category":"Building & Trades",
            "subcategory":"Landscaping Services",
            "type":"Services"
        }
    ],
    "sg:phone":"+1 619 561 8826",
    "sg:postcode":"92021",
    "sg:province":"CA",
    "wof:name":"Anderson Landscaping and Con",
    "wof:placetype":"venue"
},
  "geometry": {"coordinates":[-116.834661,32.871074],"type":"Point"}
}