{
  "type": "Feature",
  "properties": {
    "addr:full":"1203 Cecil Ave Delano CA 93215",
    "addr:housenumber":"1203",
    "addr:postcode":"93215",
    "addr:street":"Cecil Ave",
    "iso:country":"US",
    "sg:address":"1203 Cecil Ave",
    "sg:city":"Delano",
    "sg:classifiers":[
        {
            "category":"Retail",
            "subcategory":"Auto Repair",
            "type":"Services"
        }
    ],
    "sg:phone":"+1 661 725 3685",
    "sg:postcode":"93215",
    "sg:province":"CA",
    "sg:tags":[
        "muffler",
        "exhaust",
        "system"
    ],
    "wof:name":"Ramirez Muffler Shop",
    "wof:placetype":"venue"
},
  "geometry": {"coordinates":[-119.243044,35.775937],"type":"Point"}
}