{
  "type": "Feature",
  "properties": {
    "iso:country":"US",
    "sg:address":"2002 E Home Ave",
    "sg:city":"Fresno",
    "sg:classifiers":[
        {
            "category":"Building & Trades",
            "subcategory":"Construction",
            "type":"Services"
        }
    ],
    "sg:phone":"+1 559 233 3033",
    "sg:postcode":"93703",
    "sg:province":"CA",
    "sg:tags":[
        "house"
    ],
    "wof:name":"Garcia & Sons",
    "wof:placetype":"venue"
},
  "geometry": {"coordinates":[-119.787055,36.763054],"type":"Point"}
}