{
  "type": "Feature",
  "properties": {
    "iso:country":"US",
    "sg:address":"561 N Lucerne Blvd",
    "sg:city":"Los Angeles",
    "sg:classifiers":[
        {
            "category":"Building & Trades",
            "subcategory":"Electrical",
            "type":"Services"
        }
    ],
    "sg:phone":"+1 323 462 1023",
    "sg:postcode":"90004",
    "sg:province":"CA",
    "sg:tags":[
        "electrician"
    ],
    "sg:website":"www.bgaddyelectric.com",
    "wof:name":"B. Gaddy Electric",
    "wof:placetype":"venue"
},
  "geometry": {"coordinates":[-118.325192,34.080698],"type":"Point"}
}