{
  "type": "Feature",
  "properties": {
    "iso:country":"US",
    "sg:address":"11127 Davenrich St",
    "sg:city":"Santa Fe Springs",
    "sg:classifiers":[
        {
            "category":"Freight",
            "type":"Transportation"
        }
    ],
    "sg:phone":"+1 562 929 2455",
    "sg:postcode":"90670",
    "sg:province":"CA",
    "sg:tags":[
        "operator",
        "local",
        "trucking"
    ],
    "wof:name":"D E Transport",
    "wof:placetype":"venue"
},
  "geometry": {"coordinates":[-118.094689,33.945754],"type":"Point"}
}