{
  "type": "Feature",
  "properties": {
    "iso:country":"US",
    "sg:address":"2011 10th St",
    "sg:city":"Los Osos",
    "sg:classifiers":[
        {
            "category":"Restaurant",
            "type":"Food & Drink"
        }
    ],
    "sg:phone":"+1 805 528 2011",
    "sg:postcode":"93402",
    "sg:province":"CA",
    "wof:name":"10th Street Grill",
    "wof:placetype":"venue"
},
  "geometry": {"coordinates":[-120.832217,35.314851],"type":"Point"}
}