{
  "type": "Feature",
  "properties": {
    "addr:full":"498 Post St San Francisco CA 94102",
    "addr:housenumber":"498",
    "addr:postcode":"94102",
    "addr:street":"Post St",
    "iso:country":"US",
    "sg:address":"498 Post St",
    "sg:city":"San Francisco",
    "sg:classifiers":[
        {
            "category":"Shopping",
            "subcategory":"Clothing, Apparel, & Fashions",
            "type":"Retail Goods"
        }
    ],
    "sg:phone":"+1 415 781 5777",
    "sg:postcode":"94102",
    "sg:province":"CA",
    "sg:tags":[
        "furnishing"
    ],
    "sg:website":"www.barcelino.com",
    "wof:name":"Barcelino Men's Apparel",
    "wof:placetype":"venue"
},
  "geometry": {"coordinates":[-122.408402,37.788292],"type":"Point"}
}