{
  "type": "Feature",
  "properties": {
    "addr:full":"6305 el Camino Real Carlsbad CA 92009",
    "addr:housenumber":"6305",
    "addr:postcode":"92009",
    "addr:street":"El Camino Real",
    "iso:country":"US",
    "sg:address":"6305 el Camino Real",
    "sg:city":"Carlsbad",
    "sg:classifiers":[
        {
            "category":"Manufacturing",
            "subcategory":"Tools & Machinery",
            "type":"Manufacturing & Wholesale Goods"
        }
    ],
    "sg:phone":"+1 760 931 5500",
    "sg:postcode":"92009",
    "sg:province":"CA",
    "sg:tags":[
        "storage",
        "design",
        "datum",
        "system"
    ],
    "sg:website":"www.sannet.com",
    "wof:name":"Dot Hill Systems Corp",
    "wof:placetype":"venue"
},
  "geometry": {"coordinates":[-117.26884,33.117949],"type":"Point"}
}