{
  "type": "Feature",
  "properties": {
    "addr:full":"422 S Western Ave Los Angeles CA 90020",
    "addr:housenumber":"422",
    "addr:postcode":"90020",
    "addr:street":"S Western Ave",
    "iso:country":"US",
    "sg:address":"422 S Western Ave",
    "sg:city":"Los Angeles",
    "sg:classifiers":[
        {
            "category":"Autos & Motor Vehicles",
            "subcategory":"Fuel & Gas Station",
            "type":"Retail Goods"
        }
    ],
    "sg:phone":"+1 213 383 7063",
    "sg:postcode":"90020",
    "sg:province":"CA",
    "sg:tags":[
        "oil"
    ],
    "wof:name":"K Y Enterprises Inc",
    "wof:placetype":"venue"
},
  "geometry": {"coordinates":[-118.309026,34.065736],"type":"Point"}
}