{
  "type": "Feature",
  "properties": {
    "iso:country":"US",
    "sg:address":"13300 State Hwy 20",
    "sg:city":"Clearlake Oaks",
    "sg:classifiers":[
        {
            "category":"Personal",
            "subcategory":"Tattoo Parlor",
            "type":"Services"
        }
    ],
    "sg:phone":"+1 707 998 3948",
    "sg:postcode":"95423",
    "sg:province":"CA",
    "sg:tags":[
        "tattooing"
    ],
    "wof:name":"Lakeside Tattoo Co",
    "wof:placetype":"venue"
},
  "geometry": {"coordinates":[-122.661226,39.025947],"type":"Point"}
}