{
  "type": "Feature",
  "properties": {
    "iso:country":"US",
    "sg:address":"10137 Riverside Dr",
    "sg:city":"Toluca Lake",
    "sg:classifiers":[
        {
            "category":"Banks & Credit Unions",
            "subcategory":"Bank",
            "type":"Services"
        }
    ],
    "sg:phone":"+1 818 769 0909",
    "sg:postcode":"91602",
    "sg:province":"CA",
    "sg:tags":[
        "loan",
        "real estate"
    ],
    "wof:name":"American Premiere Savings",
    "wof:placetype":"venue"
},
  "geometry": {"coordinates":[-118.352605,34.152279],"type":"Point"}
}