{
  "type": "Feature",
  "properties": {
    "addr:full":"1726 N Spring St Los Angeles CA 90012",
    "addr:housenumber":"1726",
    "addr:postcode":"90012",
    "addr:street":"N Spring St",
    "iso:country":"US",
    "sg:address":"1726 N Spring St",
    "sg:city":"Los Angeles",
    "sg:classifiers":[
        {
            "category":"Wholesale",
            "subcategory":"Durable Goods & Equipment",
            "type":"Manufacturing & Wholesale Goods"
        }
    ],
    "sg:phone":"+1 323 224 0211",
    "sg:postcode":"90012",
    "sg:province":"CA",
    "sg:tags":[
        "importer"
    ],
    "wof:name":"L A Lucky Trading Co",
    "wof:placetype":"venue"
},
  "geometry": {"coordinates":[-118.22729,34.069531],"type":"Point"}
}