{
  "type": "Feature",
  "properties": {
    "addr:full":"1823 Marine Ave Gardena CA 90249",
    "addr:housenumber":"1823",
    "addr:postcode":"90249",
    "addr:street":"Marine Ave",
    "iso:country":"US",
    "sg:address":"1823 Marine Ave",
    "sg:city":"Gardena",
    "sg:classifiers":[
        {
            "category":"Retail",
            "subcategory":"Auto Repair",
            "type":"Services"
        }
    ],
    "sg:phone":"+1 310 327 5383",
    "sg:postcode":"90249",
    "sg:province":"CA",
    "sg:website":"www.jmgrepair.com",
    "wof:name":"JMG Repair",
    "wof:placetype":"venue"
},
  "geometry": {"coordinates":[-118.31010999999999,33.894938],"type":"Point"}
}