{
  "type": "Feature",
  "properties": {
    "iso:country":"US",
    "sg:address":"104 Lyell St",
    "sg:city":"Los Altos",
    "sg:classifiers":[
        {
            "category":"Wholesale",
            "subcategory":"Metals & Minerals",
            "type":"Manufacturing & Wholesale Goods"
        }
    ],
    "sg:phone":"+1 650 947 9334",
    "sg:postcode":"94022",
    "sg:province":"CA",
    "sg:tags":[
        "wire"
    ],
    "wof:name":"ESD & C Inc",
    "wof:placetype":"venue"
},
  "geometry": {"coordinates":[-122.111351,37.375385],"type":"Point"}
}