{
  "type": "Feature",
  "properties": {
    "addr:full":"1071 Avenida Acaso Camarillo CA 93012",
    "addr:housenumber":"1071",
    "addr:postcode":"93012",
    "addr:street":"Avenida Acaso",
    "iso:country":"US",
    "sg:address":"1071 Avenida Acaso",
    "sg:city":"Camarillo",
    "sg:classifiers":[
        {
            "category":"Real Estate",
            "subcategory":"Real Estate Services",
            "type":"Services"
        }
    ],
    "sg:phone":"+1 800 432 1312",
    "sg:postcode":"93012",
    "sg:province":"CA",
    "sg:tags":[
        "management"
    ],
    "wof:name":"Acropolis Investments Inc.",
    "wof:placetype":"venue"
},
  "geometry": {"coordinates":[-119.014229,34.227322],"type":"Point"}
}