{
  "type": "Feature",
  "properties": {
    "addr:full":"2393 Fairgrove Ct San Jose CA 95125",
    "addr:housenumber":"2393",
    "addr:postcode":"95125",
    "addr:street":"Fairgrove Ct",
    "iso:country":"US",
    "sg:address":"2393 Fairgrove Ct",
    "sg:city":"San Jose",
    "sg:classifiers":[
        {
            "category":"Professional",
            "type":"Services"
        }
    ],
    "sg:phone":"+1 408 264 6036",
    "sg:postcode":"95125",
    "sg:province":"CA",
    "sg:tags":[
        "establishment"
    ],
    "wof:name":"At&T Cits",
    "wof:placetype":"venue"
},
  "geometry": {"coordinates":[-121.905209,37.280922],"type":"Point"}
}