{
  "type": "Feature",
  "properties": {
    "iso:country":"US",
    "sg:address":"789 Green Valley Rd",
    "sg:city":"Watsonville",
    "sg:classifiers":[
        {
            "category":"Real Estate",
            "subcategory":"Real Estate Operator",
            "type":"Services"
        }
    ],
    "sg:phone":"+1 831 724 3333",
    "sg:postcode":"95076",
    "sg:province":"CA",
    "sg:tags":[
        "mobile",
        "home",
        "community"
    ],
    "wof:name":"Pinto Lake Mobile Estates",
    "wof:placetype":"venue"
},
  "geometry": {"coordinates":[-121.76505400000001,36.965311],"type":"Point"}
}