{
  "type": "Feature",
  "properties": {
    "addr:full":"3629 E 18th St Antioch CA 94509",
    "addr:housenumber":"3629",
    "addr:postcode":"ca 94509",
    "addr:street":"E 18Th St",
    "iso:country":"US",
    "sg:address":"3629 E 18th St",
    "sg:city":"Antioch",
    "sg:classifiers":[
        {
            "category":"Retail",
            "subcategory":"Auto Rental",
            "type":"Services"
        }
    ],
    "sg:phone":"+1 925 754 5007",
    "sg:postcode":"94509",
    "sg:province":"CA",
    "sg:tags":[
        "renting",
        "truck",
        "leasing"
    ],
    "wof:name":"U-Haul Co",
    "wof:placetype":"venue"
},
  "geometry": {"coordinates":[-121.755262,38.005158],"type":"Point"}
}