{
  "type": "Feature",
  "properties": {
    "iso:country":"US",
    "sg:address":"3115 Sacramento St",
    "sg:city":"West Sacramento",
    "sg:classifiers":[
        {
            "category":"Farming",
            "subcategory":"Nursery",
            "type":"Manufacturing & Wholesale Goods"
        }
    ],
    "sg:phone":"+1 916 803 5441",
    "sg:postcode":"95667",
    "sg:province":"CA",
    "sg:tags":[
        "turf"
    ],
    "wof:name":"TCS Turf",
    "wof:placetype":"venue"
},
  "geometry": {"coordinates":[-120.80530299999999,38.724316],"type":"Point"}
}