{
  "type": "Feature",
  "properties": {
    "addr:full":"3921 4th Avenue San Diego CA 92103",
    "addr:housenumber":"3921",
    "addr:postcode":"92103",
    "addr:street":"4Th Avenue",
    "iso:country":"US",
    "sg:address":"3921 4th Avenue",
    "sg:city":"San Diego",
    "sg:classifiers":[
        {
            "category":"Shopping",
            "subcategory":"Hobbies, Toys, & Games",
            "type":"Retail Goods"
        }
    ],
    "sg:phone":"+1 619 491 0424",
    "sg:postcode":"92103",
    "sg:province":"CA",
    "sg:tags":[
        "shop",
        "hobby"
    ],
    "wof:name":"Flagship Flags",
    "wof:placetype":"venue"
},
  "geometry": {"coordinates":[-117.16173999999999,32.748642],"type":"Point"}
}