{
  "type": "Feature",
  "properties": {
    "iso:country":"US",
    "sg:address":"1717 N Verdugo Rd",
    "sg:city":"Glendale",
    "sg:classifiers":[
        {
            "category":"Real Estate",
            "subcategory":"Real Estate Services",
            "type":"Services"
        }
    ],
    "sg:phone":"+1 888 640 5183",
    "sg:postcode":"91208",
    "sg:province":"CA",
    "sg:tags":[
        "apartment",
        "management",
        "rental",
        "finder"
    ],
    "sg:website":"http://www.forrent.com/apartment-community-profile/1000057530.php?cmp=CAC-CSearchProfile",
    "wof:name":"Verdugo Village",
    "wof:placetype":"venue"
},
  "geometry": {"coordinates":[-118.22663900000001,34.172451],"type":"Point"}
}