{
  "type": "Feature",
  "properties": {
    "iso:country":"US",
    "sg:address":"4035 Country Trl",
    "sg:city":"Bonita",
    "sg:classifiers":[
        {
            "category":"Mining & Drilling",
            "type":"Manufacturing & Wholesale Goods"
        }
    ],
    "sg:phone":"+1 619 482 2274",
    "sg:postcode":"91902",
    "sg:province":"CA",
    "sg:tags":[
        "oil",
        "gas",
        "producer"
    ],
    "wof:name":"KYRO Inc",
    "wof:placetype":"venue"
},
  "geometry": {"coordinates":[-116.999659,32.666888],"type":"Point"}
}