{
  "type": "Feature",
  "properties": {
    "addr:full":"487 Grass Valley Hwy Auburn CA 95603",
    "addr:housenumber":"487",
    "addr:postcode":"ca 95603",
    "addr:street":"Grass Valley Hwy",
    "iso:country":"US",
    "sg:address":"487 Grass Valley Hwy",
    "sg:city":"Auburn",
    "sg:classifiers":[
        {
            "category":"Manufacturing",
            "subcategory":"Tools & Machinery",
            "type":"Manufacturing & Wholesale Goods"
        }
    ],
    "sg:phone":"+1 530 823 2086",
    "sg:postcode":"95603",
    "sg:province":"CA",
    "sg:tags":[
        "machine",
        "shop"
    ],
    "wof:name":"R & S Machine Shop",
    "wof:placetype":"venue"
},
  "geometry": {"coordinates":[-121.07699599999999,38.908387],"type":"Point"}
}