{
  "type": "Feature",
  "properties": {
    "iso:country":"US",
    "sg:address":"3837 10th St",
    "sg:city":"Riverside",
    "sg:classifiers":[
        {
            "category":"Professional",
            "subcategory":"Management & Consulting",
            "type":"Services"
        }
    ],
    "sg:phone":"+1 951 684 7544",
    "sg:postcode":"92501",
    "sg:province":"CA",
    "sg:tags":[
        "marketing",
        "consultant"
    ],
    "wof:name":"Direct Accounting & Consulting",
    "wof:placetype":"venue"
},
  "geometry": {"coordinates":[-117.377775,33.980981],"type":"Point"}
}