{
  "type": "Feature",
  "properties": {
    "addr:full":"358 N Montgomery Street San Jose CA 95110",
    "addr:housenumber":"358",
    "addr:postcode":"95110",
    "addr:street":"N Montgomery Street",
    "iso:country":"US",
    "sg:address":"358 N Montgomery Street",
    "sg:city":"San Jose",
    "sg:classifiers":[
        {
            "category":"Organizations",
            "subcategory":"Non-profit Organization",
            "type":"Services"
        }
    ],
    "sg:phone":"+1 408 881 4900",
    "sg:postcode":"95110",
    "sg:province":"CA",
    "sg:tags":[
        "service/non-profit",
        "community"
    ],
    "wof:name":"Innvision Montgomery Street Inn",
    "wof:placetype":"venue"
},
  "geometry": {"coordinates":[-121.904392,37.336495],"type":"Point"}
}