{
  "type": "Feature",
  "properties": {
    "addr:full":"1113 Garfield Ave Albany CA 94706",
    "addr:housenumber":"1113",
    "addr:postcode":"94706",
    "addr:street":"Garfield Ave",
    "iso:country":"US",
    "sg:address":"1113 Garfield Ave",
    "sg:city":"Albany",
    "sg:classifiers":[
        {
            "category":"Health Services",
            "subcategory":"Dentist",
            "type":"Services"
        }
    ],
    "sg:phone":"+1 510 525 6100",
    "sg:postcode":"94706",
    "sg:province":"CA",
    "wof:name":"Shadan Jabali, DMD",
    "wof:placetype":"venue"
},
  "geometry": {"coordinates":[-122.299758,37.895456],"type":"Point"}
}