{
  "type": "Feature",
  "properties": {
    "iso:country":"US",
    "sg:address":"2121 Golden Centre Ln",
    "sg:city":"Rancho Cordova",
    "sg:classifiers":[
        {
            "category":"Shopping",
            "subcategory":"Jewelry",
            "type":"Retail Goods"
        }
    ],
    "sg:phone":"+1 916 852 7273",
    "sg:postcode":"95670",
    "sg:province":"CA",
    "wof:name":"Mi-Bo's Elegant Jewelry",
    "wof:placetype":"venue"
},
  "geometry": {"coordinates":[-121.264048,38.627015],"type":"Point"}
}