{
  "type": "Feature",
  "properties": {
    "iso:country":"US",
    "sg:address":"6965 el Camino Real",
    "sg:city":"Carlsbad",
    "sg:classifiers":[
        {
            "category":"Wholesale",
            "subcategory":"Office Equipment",
            "type":"Manufacturing & Wholesale Goods"
        }
    ],
    "sg:phone":"+1 858 775 3164",
    "sg:postcode":"92009",
    "sg:province":"CA",
    "wof:name":"Pacific Wholesale Copiers Inc",
    "wof:placetype":"venue"
},
  "geometry": {"coordinates":[-117.26683199999999,33.104012],"type":"Point"}
}