{
  "type": "Feature",
  "properties": {
    "addr:full":"3 Claude Ln San Francisco CA 94108",
    "addr:housenumber":"3",
    "addr:postcode":"94108",
    "addr:street":"Claude Ln",
    "iso:country":"US",
    "sg:address":"3 Claude Ln",
    "sg:city":"San Francisco",
    "sg:classifiers":[
        {
            "category":"Shopping",
            "subcategory":"Clothing, Apparel, & Fashions",
            "type":"Retail Goods"
        }
    ],
    "sg:phone":"+1 415 677 9939",
    "sg:postcode":"94108",
    "sg:province":"CA",
    "wof:name":"Diana Slavin Womenswear",
    "wof:placetype":"venue"
},
  "geometry": {"coordinates":[-122.404471,37.790682],"type":"Point"}
}