{
  "type": "Feature",
  "properties": {
    "addr:full":"1657 Hollenbeck Ave Sunnyvale CA 94087",
    "addr:housenumber":"1657",
    "addr:postcode":"94087",
    "addr:street":"Hollenbeck Ave",
    "iso:country":"US",
    "sg:address":"1657 Hollenbeck Ave",
    "sg:city":"Sunnyvale",
    "sg:classifiers":[
        {
            "category":"Cinema",
            "subcategory":"Movie Rental",
            "type":"Entertainment"
        }
    ],
    "sg:phone":"+1 408 720 8783",
    "sg:postcode":"94087",
    "sg:province":"CA",
    "sg:tags":[
        "game",
        "video"
    ],
    "sg:website":"blockbuster.com",
    "wof:name":"Blockbuster Video",
    "wof:placetype":"venue"
},
  "geometry": {"coordinates":[-122.04149,37.340652],"type":"Point"}
}