{
  "type": "Feature",
  "properties": {
    "addr:full":"353 Sanjon Rd Ventura CA 93001",
    "addr:housenumber":"353",
    "addr:postcode":"93001",
    "addr:street":"Sanjon Rd",
    "iso:country":"US",
    "sg:address":"353 Sanjon Rd",
    "sg:city":"Ventura",
    "sg:classifiers":[
        {
            "category":"Professional",
            "subcategory":"Lawyer & Legal Services",
            "type":"Services"
        }
    ],
    "sg:phone":"+1 805 643 2200",
    "sg:postcode":"93001",
    "sg:province":"CA",
    "sg:tags":[
        "attorney"
    ],
    "sg:website":"www.engleandbride.com",
    "wof:name":"Engle & Bride",
    "wof:placetype":"venue"
},
  "geometry": {"coordinates":[-119.28224,34.2753],"type":"Point"}
}