{
  "type": "Feature",
  "properties": {
    "iso:country":"US",
    "sg:address":"14721 Van Ave",
    "sg:city":"San Leandro",
    "sg:classifiers":[
        {
            "category":"Shopping",
            "subcategory":"Mobile Phones",
            "type":"Retail Goods"
        }
    ],
    "sg:phone":"+1 510 614 8308",
    "sg:postcode":"94578",
    "sg:province":"CA",
    "wof:name":"SkyTel",
    "wof:placetype":"venue"
},
  "geometry": {"coordinates":[-122.12285900000001,37.716055],"type":"Point"}
}