{
  "type": "Feature",
  "properties": {
    "iso:country":"US",
    "sg:address":"10855 Sorrento Valley Rd",
    "sg:city":"San Diego",
    "sg:classifiers":[
        {
            "category":"Retail",
            "subcategory":"Auto Repair",
            "type":"Services"
        }
    ],
    "sg:phone":"+1 858 657 0500",
    "sg:postcode":"92121",
    "sg:province":"CA",
    "sg:tags":[
        "repairing",
        "automobile"
    ],
    "wof:name":"Quigley Motorworks",
    "wof:placetype":"venue"
},
  "geometry": {"coordinates":[-117.22145999999999,32.899464],"type":"Point"}
}