{
  "type": "Feature",
  "properties": {
    "addr:full":"603 S Orange Dr Los Angeles CA 90036",
    "addr:housenumber":"603",
    "addr:postcode":"90036",
    "addr:street":"S Orange Dr",
    "iso:country":"US",
    "sg:address":"603 S Orange Dr",
    "sg:city":"Los Angeles",
    "sg:classifiers":[
        {
            "category":"Building & Trades",
            "subcategory":"Construction",
            "type":"Services"
        }
    ],
    "sg:phone":"+1 323 934 6117",
    "sg:postcode":"90036",
    "sg:province":"CA",
    "sg:tags":[
        "designer",
        "dealer",
        "pool",
        "swimming"
    ],
    "wof:name":"Pacific One Pool & Spa",
    "wof:placetype":"venue"
},
  "geometry": {"coordinates":[-118.34192299999999,34.062897],"type":"Point"}
}