{
  "type": "Feature",
  "properties": {
    "iso:country":"US",
    "sg:address":"14406 Ventura Blvd",
    "sg:city":"Sherman Oaks",
    "sg:classifiers":[
        {
            "category":"Real Estate",
            "subcategory":"Real Estate Agent",
            "type":"Services"
        }
    ],
    "sg:phone":"+1 818 986 0926",
    "sg:postcode":"91423",
    "sg:province":"CA",
    "wof:name":"Properties 2000 Real Estate",
    "wof:placetype":"venue"
},
  "geometry": {"coordinates":[-118.447578,34.15065],"type":"Point"}
}