{
  "type": "Feature",
  "properties": {
    "addr:full":"951 N Louise St Apt 109 Glendale CA 91207",
    "addr:housenumber":"951;109",
    "addr:postcode":"91207",
    "addr:street":"N Louise St Apt",
    "iso:country":"US",
    "sg:address":"951 N Louise St Apt 109",
    "sg:city":"Glendale",
    "sg:classifiers":[
        {
            "category":"Organizations",
            "subcategory":"Religious Organization",
            "type":"Services"
        }
    ],
    "sg:phone":"+1 818 246 5582",
    "sg:postcode":"91207",
    "sg:province":"CA",
    "wof:name":"Together In Christ Catholic Ministry",
    "wof:placetype":"venue"
},
  "geometry": {"coordinates":[-118.25299800000001,34.1595],"type":"Point"}
}