{
  "type": "Feature",
  "properties": {
    "iso:country":"US",
    "sg:address":"3111 Carmino Del Rio N Ste 400",
    "sg:city":"San Diego",
    "sg:classifiers":[
        {
            "category":"Banks & Credit Unions",
            "subcategory":"Atm",
            "type":"Services"
        }
    ],
    "sg:phone":"+1 619 528 2282",
    "sg:postcode":"92802",
    "sg:province":"CA",
    "sg:tags":[
        "bankruptcy"
    ],
    "sg:website":"www.jabroassociates.com",
    "wof:name":"Jabro & Associates APC",
    "wof:placetype":"venue"
},
  "geometry": {"coordinates":[-117.127887,32.774259],"type":"Point"}
}