{
  "type": "Feature",
  "properties": {
    "iso:country":"US",
    "sg:address":"25020 Avenue Stanford Ste 90",
    "sg:city":"Valencia",
    "sg:classifiers":[
        {
            "category":"Professional",
            "subcategory":"Lawyer & Legal Services",
            "type":"Services"
        }
    ],
    "sg:phone":"+1 661 257 3598",
    "sg:postcode":"91355",
    "sg:province":"CA",
    "sg:tags":[
        "notary"
    ],
    "sg:website":"www.kinkos.com",
    "wof:name":"FedEx Office",
    "wof:placetype":"venue"
},
  "geometry": {"coordinates":[-118.573408,34.437866],"type":"Point"}
}