{
  "type": "Feature",
  "properties": {
    "addr:full":"6871 Riverland Dr Redding CA 96002",
    "addr:housenumber":"6871",
    "addr:postcode":"96002",
    "addr:street":"Riverland Dr",
    "iso:country":"US",
    "sg:address":"6871 Riverland Dr",
    "sg:city":"Redding",
    "sg:classifiers":[
        {
            "category":"Retail",
            "subcategory":"Auto Repair",
            "type":"Services"
        }
    ],
    "sg:phone":"+1 530 221 4949",
    "sg:postcode":"96002",
    "sg:province":"CA",
    "sg:tags":[
        "truck"
    ],
    "wof:name":"A & Covert's Mobile Truck Rpr",
    "wof:placetype":"venue"
},
  "geometry": {"coordinates":[-122.333828,40.498273],"type":"Point"}
}