{
  "type": "Feature",
  "properties": {
    "iso:country":"US",
    "sg:address":"70100 Mirage Cove Dr Unit 35",
    "sg:city":"Rancho Mirage",
    "sg:classifiers":[
        {
            "category":"Building & Trades",
            "subcategory":"Construction",
            "type":"Services"
        }
    ],
    "sg:phone":"+1 760 328 6335",
    "sg:postcode":"92270",
    "sg:province":"CA",
    "sg:tags":[
        "interior",
        "design"
    ],
    "wof:name":"Sterkel Kenneth Interior Design",
    "wof:placetype":"venue"
},
  "geometry": {"coordinates":[-116.44231000000001,33.765057],"type":"Point"}
}