{
  "type": "Feature",
  "properties": {
    "iso:country":"US",
    "sg:address":"555 W Tehachapi Blvd",
    "sg:city":"Tehachapi",
    "sg:classifiers":[
        {
            "category":"Autos & Motor Vehicles",
            "subcategory":"Motorcycle Sales",
            "type":"Retail Goods"
        }
    ],
    "sg:phone":"+1 661 822 7016",
    "sg:postcode":"93561",
    "sg:province":"CA",
    "sg:tags":[
        "repair",
        "accessory"
    ],
    "wof:name":"Pingrys Mtcyc & Pro Design",
    "wof:placetype":"venue"
},
  "geometry": {"coordinates":[-118.455865,35.132793],"type":"Point"}
}