{
  "type": "Feature",
  "properties": {
    "addr:full":"3348 4th Ave San Diego CA 92103",
    "addr:housenumber":"3348",
    "addr:postcode":"92103",
    "addr:street":"4Th Ave",
    "iso:country":"US",
    "sg:address":"3348 4th Ave",
    "sg:city":"San Diego",
    "sg:classifiers":[
        {
            "category":"Professional",
            "subcategory":"Lawyer & Legal Services",
            "type":"Services"
        }
    ],
    "sg:phone":"+1 619 543 0798",
    "sg:postcode":"92103",
    "sg:province":"CA",
    "sg:tags":[
        "attorney"
    ],
    "wof:name":"David K Burgess Law Offices",
    "wof:placetype":"venue"
},
  "geometry": {"coordinates":[-117.16134599999999,32.740283],"type":"Point"}
}