{
  "type": "Feature",
  "properties": {
    "iso:country":"US",
    "sg:address":"3348 4th Ave",
    "sg:city":"San Diego",
    "sg:classifiers":[
        {
            "category":"Professional",
            "subcategory":"Lawyer & Legal Services",
            "type":"Services"
        }
    ],
    "sg:phone":"+1 619 543 0798",
    "sg:postcode":"92103",
    "sg:province":"CA",
    "sg:tags":[
        "attorney"
    ],
    "wof:name":"David K Burgess Law Offices",
    "wof:placetype":"venue"
},
  "geometry": {"coordinates":[-117.161346,32.740283],"type":"Point"}
}