{
  "type": "Feature",
  "properties": {
    "addr:full":"505 Avocado Pl Camarillo CA 93010",
    "addr:housenumber":"505",
    "addr:postcode":"93010",
    "addr:street":"Avocado Pl",
    "iso:country":"US",
    "sg:address":"505 Avocado Pl",
    "sg:city":"Camarillo",
    "sg:classifiers":[
        {
            "category":"Professional",
            "subcategory":"Business Services",
            "type":"Services"
        }
    ],
    "sg:phone":"+1 805 484 1244",
    "sg:postcode":"93010",
    "sg:province":"CA",
    "sg:tags":[
        "interior",
        "consultant",
        "design",
        "decorator"
    ],
    "wof:name":"Marti KATZ Designs",
    "wof:placetype":"venue"
},
  "geometry": {"coordinates":[-119.0782,34.241845],"type":"Point"}
}