{
  "type": "Feature",
  "properties": {
    "addr:full":"1 W Blithedale Ave Mill Valley CA 94941",
    "addr:housenumber":"1",
    "addr:postcode":"94941",
    "addr:street":"W Blithedale Ave",
    "iso:country":"US",
    "sg:address":"1 W Blithedale Ave",
    "sg:city":"Mill Valley",
    "sg:classifiers":[
        {
            "category":"Organizations",
            "subcategory":"Community Association",
            "type":"Services"
        }
    ],
    "sg:phone":"+1 415 383 2582",
    "sg:postcode":"94941",
    "sg:province":"CA",
    "sg:tags":[
        "club"
    ],
    "wof:name":"Outdoor Art Club Rental",
    "wof:placetype":"venue"
},
  "geometry": {"coordinates":[-122.54656,37.906932],"type":"Point"}
}