{
  "type": "Feature",
  "properties": {
    "iso:country":"US",
    "sg:address":"8535 Knott Ave",
    "sg:city":"Buena Park",
    "sg:classifiers":[
        {
            "category":"Restaurant",
            "type":"Food & Drink"
        }
    ],
    "sg:phone":"+1 714 484 9292",
    "sg:postcode":"90620",
    "sg:province":"CA",
    "sg:tags":[
        "korean"
    ],
    "wof:name":"BBQ Town Restaurant",
    "wof:placetype":"venue"
},
  "geometry": {"coordinates":[-118.011115,33.838815],"type":"Point"}
}