{
  "type": "Feature",
  "properties": {
    "addr:full":"2690 S White Rd # 200 San Jose CA 95148",
    "addr:housenumber":"2690",
    "addr:postcode":"95148",
    "addr:street":"S White Rd # 200",
    "iso:country":"US",
    "sg:address":"2690 S White Rd # 200",
    "sg:city":"San Jose",
    "sg:classifiers":[
        {
            "category":"Health Services",
            "subcategory":"Doctor",
            "type":"Services"
        }
    ],
    "sg:phone":"+1 408 223 8228",
    "sg:postcode":"95148",
    "sg:province":"CA",
    "sg:tags":[
        "practice",
        "family"
    ],
    "sg:website":"www.evergreendoc.com",
    "wof:name":"Medical Offices of Shashwati Kale, MD",
    "wof:placetype":"venue"
},
  "geometry": {"coordinates":[-121.798197,37.328946],"type":"Point"}
}