{
  "type": "Feature",
  "properties": {
    "iso:country":"US",
    "sg:address":"1409 Sutter St",
    "sg:city":"San Francisco",
    "sg:classifiers":[
        {
            "category":"Real Estate",
            "subcategory":"Real Estate Agent",
            "type":"Services"
        }
    ],
    "sg:phone":"+1 415 885 1827",
    "sg:postcode":"94109",
    "sg:province":"CA",
    "sg:tags":[
        "appraiser"
    ],
    "wof:name":"Thomas A Myers Real Estate",
    "wof:placetype":"venue"
},
  "geometry": {"coordinates":[-122.42492900000001,37.787073],"type":"Point"}
}