{
  "type": "Feature",
  "properties": {
    "addr:full":"391 S Rosemead Blvd Pasadena CA 91107",
    "addr:housenumber":"391",
    "addr:postcode":"91107",
    "addr:street":"S Rosemead Blvd",
    "iso:country":"US",
    "sg:address":"391 S Rosemead Blvd",
    "sg:city":"Pasadena",
    "sg:classifiers":[
        {
            "category":"Autos & Motor Vehicles",
            "subcategory":"Motorcycle Sales",
            "type":"Retail Goods"
        }
    ],
    "sg:phone":"+1 213 817 0990",
    "sg:postcode":"91107",
    "sg:province":"CA",
    "sg:tags":[
        "scooter"
    ],
    "wof:name":"Motorcycle Goodies II",
    "wof:placetype":"venue"
},
  "geometry": {"coordinates":[-118.07338799999999,34.139994],"type":"Point"}
}