{
  "type": "Feature",
  "properties": {
    "iso:country":"US",
    "sg:address":"1402 Monterey Hwy",
    "sg:city":"San Jose",
    "sg:classifiers":[
        {
            "category":"Home & Garden",
            "subcategory":"Building Materials",
            "type":"Retail Goods"
        }
    ],
    "sg:phone":"+1 408 297 9663",
    "sg:postcode":"95110",
    "sg:province":"CA",
    "sg:tags":[
        "supply"
    ],
    "sg:website":"www.southernlumber.com",
    "wof:name":"Southern Lumber",
    "wof:placetype":"venue"
},
  "geometry": {"coordinates":[-121.87400100000001,37.313599],"type":"Point"}
}