{
  "type": "Feature",
  "properties": {
    "iso:country":"US",
    "sg:address":"2990 Travis Blvd",
    "sg:city":"Fairfield",
    "sg:classifiers":[
        {
            "category":"Autos & Motor Vehicles",
            "subcategory":"Fuel & Gas Station",
            "type":"Retail Goods"
        }
    ],
    "sg:phone":"+1 707 427 2990",
    "sg:postcode":"94534",
    "sg:province":"CA",
    "sg:tags":[
        "oil"
    ],
    "wof:name":"Travis Chevron",
    "wof:placetype":"venue"
},
  "geometry": {"coordinates":[-122.064846,38.25838],"type":"Point"}
}