{
  "type": "Feature",
  "properties": {
    "iso:country":"US",
    "sg:address":"13615 Bombay St",
    "sg:city":"San Fernando",
    "sg:classifiers":[
        {
            "category":"Building & Trades",
            "subcategory":"Construction",
            "type":"Services"
        }
    ],
    "sg:phone":"+1 818 365 8102",
    "sg:postcode":"91340",
    "sg:province":"CA",
    "sg:tags":[
        "designer",
        "dealer",
        "pool",
        "swimming"
    ],
    "wof:name":"Rodriguez Pool Plumbing Inc",
    "wof:placetype":"venue"
},
  "geometry": {"coordinates":[-118.430401,34.305661],"type":"Point"}
}