{
  "type": "Feature",
  "properties": {
    "addr:full":"2734 Ceilhunt Ave Los Angeles CA 90064",
    "addr:housenumber":"2734",
    "addr:postcode":"90064",
    "addr:street":"Ceilhunt Ave",
    "iso:country":"US",
    "sg:address":"2734 Ceilhunt Ave",
    "sg:city":"Los Angeles",
    "sg:classifiers":[
        {
            "category":"Arts & Performance",
            "subcategory":"Theater",
            "type":"Entertainment"
        }
    ],
    "sg:phone":"+1 310 444 1488",
    "sg:postcode":"90064",
    "sg:province":"CA",
    "sg:tags":[
        "live",
        "music"
    ],
    "wof:name":"Better Music Svc",
    "wof:placetype":"venue"
},
  "geometry": {"coordinates":[-118.436323,34.025371],"type":"Point"}
}