{
  "type": "Feature",
  "properties": {
    "addr:full":"802 Brentwood Ave Vallejo CA 94591",
    "addr:housenumber":"802",
    "addr:postcode":"94591",
    "addr:street":"Brentwood Ave",
    "iso:country":"US",
    "sg:address":"802 Brentwood Ave",
    "sg:city":"Vallejo",
    "sg:classifiers":[
        {
            "category":"Shopping",
            "subcategory":"Music",
            "type":"Retail Goods"
        }
    ],
    "sg:phone":"+1 707 645 8555",
    "sg:postcode":"94591",
    "sg:province":"CA",
    "wof:name":"Personal Record Sports",
    "wof:placetype":"venue"
},
  "geometry": {"coordinates":[-122.208983,38.103148],"type":"Point"}
}