{
  "type": "Feature",
  "properties": {
    "addr:full":"6340 E Vera Crest Dr Long Beach CA 90815",
    "addr:housenumber":"6340",
    "addr:postcode":"90815",
    "addr:street":"E Vera Crest Dr",
    "iso:country":"US",
    "sg:address":"6340 E Vera Crest Dr",
    "sg:city":"Long Beach",
    "sg:classifiers":[
        {
            "category":"Professional",
            "type":"Services"
        }
    ],
    "sg:phone":"+1 562 594 6447",
    "sg:postcode":"90815",
    "sg:province":"CA",
    "wof:name":"Woodshire Villas 2 Condominium",
    "wof:placetype":"venue"
},
  "geometry": {"coordinates":[-118.11003599999999,33.77902],"type":"Point"}
}