{
  "type": "Feature",
  "properties": {
    "iso:country":"US",
    "sg:address":"1825 N Marshall Ave",
    "sg:city":"El Cajon",
    "sg:classifiers":[
        {
            "category":"Airport",
            "type":"Transportation"
        }
    ],
    "sg:phone":"+1 619 562 9088",
    "sg:postcode":"92020",
    "sg:province":"CA",
    "wof:name":"Max Blue Aviation Service",
    "wof:placetype":"venue"
},
  "geometry": {"coordinates":[-116.975823,32.818741],"type":"Point"}
}