{
  "type": "Feature",
  "properties": {
    "addr:full":"1812 S Shenandoah St Los Angeles CA 90035",
    "addr:housenumber":"1812",
    "addr:postcode":"90035",
    "addr:street":"S Shenandoah St",
    "iso:country":"US",
    "sg:address":"1812 S Shenandoah St",
    "sg:city":"Los Angeles",
    "sg:classifiers":[
        {
            "category":"Professional",
            "subcategory":"Computer Services",
            "type":"Services"
        }
    ],
    "sg:phone":"+1 310 841 6887",
    "sg:postcode":"90035",
    "sg:province":"CA",
    "sg:tags":[
        "consultant",
        "designer"
    ],
    "wof:name":"Lassley's Consulting Svc",
    "wof:placetype":"venue"
},
  "geometry": {"coordinates":[-118.38363,34.044427],"type":"Point"}
}