{
  "type": "Feature",
  "properties": {
    "addr:full":"20 Seminary Cove Dr Mill Valley CA 94941",
    "addr:housenumber":"20",
    "addr:postcode":"94941",
    "addr:street":"Seminary Cove Dr",
    "iso:country":"US",
    "sg:address":"20 Seminary Cove Dr",
    "sg:city":"Mill Valley",
    "sg:classifiers":[
        {
            "category":"Retail",
            "subcategory":"Animal Services",
            "type":"Services"
        }
    ],
    "sg:phone":"+1 415 383 3456",
    "sg:postcode":"94941",
    "sg:province":"CA",
    "wof:name":"Pooch Promenade LLC",
    "wof:placetype":"venue"
},
  "geometry": {"coordinates":[-122.508832,37.884061],"type":"Point"}
}