{
  "type": "Feature",
  "properties": {
    "addr:full":"245 Pala Ave San Jose CA 95127",
    "addr:housenumber":"245",
    "addr:postcode":"95127",
    "addr:street":"Pala Ave",
    "iso:country":"US",
    "sg:address":"245 Pala Ave",
    "sg:city":"San Jose",
    "sg:classifiers":[
        {
            "category":"Real Estate",
            "subcategory":"Real Estate Operator",
            "type":"Services"
        }
    ],
    "sg:phone":"+1 408 272 0821",
    "sg:postcode":"95127",
    "sg:province":"CA",
    "sg:tags":[
        "apartment"
    ],
    "wof:name":"Foothill Manor Apartments",
    "wof:placetype":"venue"
},
  "geometry": {"coordinates":[-121.839096,37.368485],"type":"Point"}
}