{
  "type": "Feature",
  "properties": {
    "iso:country":"US",
    "sg:address":"1456 Stoneridge Mall Rd",
    "sg:city":"Pleasanton",
    "sg:classifiers":[
        {
            "category":"Shopping",
            "subcategory":"Clothing, Apparel, & Fashions",
            "type":"Retail Goods"
        },
        {
            "category":"Shopping",
            "subcategory":"Bicycles & Sporting Goods",
            "type":"Retail Goods"
        },
        {
            "category":"Shopping",
            "subcategory":"Shoes",
            "type":"Retail Goods"
        }
    ],
    "sg:phone":"+1 925 847 0961",
    "sg:postcode":"94588",
    "sg:province":"CA",
    "sg:tags":[
        "clothing",
        "store",
        "sportswear"
    ],
    "sg:website":"http://www.champssports.com",
    "wof:name":"Champs Sports",
    "wof:placetype":"venue"
},
  "geometry": {"coordinates":[-121.93206000000001,37.6958],"type":"Point"}
}