{
  "type": "Feature",
  "properties": {
    "iso:country":"US",
    "sg:address":"18080 Beach Boulevard",
    "sg:city":"Huntington Beach",
    "sg:classifiers":[
        {
            "category":"Health Services",
            "subcategory":"Doctor",
            "type":"Services"
        }
    ],
    "sg:phone":"+1 714 375 3779",
    "sg:postcode":"92648",
    "sg:province":"CA",
    "wof:name":"Beach Surgery Medical Center",
    "wof:placetype":"venue"
},
  "geometry": {"coordinates":[-117.988984,33.699353],"type":"Point"}
}