{
  "type": "Feature",
  "properties": {
    "addr:full":"3499 Manthey Rd Stockton CA 95206",
    "addr:housenumber":"3499",
    "addr:postcode":"95206",
    "addr:street":"Manthey Rd",
    "iso:country":"US",
    "sg:address":"3499 Manthey Rd",
    "sg:city":"Stockton",
    "sg:classifiers":[
        {
            "category":"Government",
            "subcategory":"Fire Station",
            "type":"Public Place"
        }
    ],
    "sg:phone":"+1 209 937 8025",
    "sg:postcode":"95206",
    "sg:province":"CA",
    "sg:tags":[
        "protection"
    ],
    "wof:name":"Stockton Fire Dept",
    "wof:placetype":"venue"
},
  "geometry": {"coordinates":[-121.29413,37.91122],"type":"Point"}
}