{
  "type": "Feature",
  "properties": {
    "addr:full":"910 Meridian Ave San Jose CA 95126",
    "addr:housenumber":"910",
    "addr:postcode":"95126",
    "addr:street":"Meridian Ave",
    "iso:country":"US",
    "sg:address":"910 Meridian Ave",
    "sg:city":"San Jose",
    "sg:classifiers":[
        {
            "category":"Restaurant",
            "type":"Food & Drink"
        }
    ],
    "sg:phone":"+1 408 971 0878",
    "sg:postcode":"95126",
    "sg:province":"CA",
    "sg:tags":[
        "chinese"
    ],
    "wof:name":"Mr Chau's Chinese Fast Food",
    "wof:placetype":"venue"
},
  "geometry": {"coordinates":[-121.914001,37.3078],"type":"Point"}
}