{
  "type": "Feature",
  "properties": {
    "addr:full":"2895 N Main St Walnut Creek CA 94597",
    "addr:housenumber":"2895",
    "addr:postcode":"94597",
    "addr:street":"N Main St",
    "iso:country":"US",
    "sg:address":"2895 N Main St",
    "sg:city":"Walnut Creek",
    "sg:classifiers":[
        {
            "category":"Autos & Motor Vehicles",
            "subcategory":"Fuel & Gas Station",
            "type":"Retail Goods"
        }
    ],
    "sg:phone":"+1 925 938 5640",
    "sg:postcode":"94597",
    "sg:province":"CA",
    "sg:tags":[
        "oil"
    ],
    "wof:name":"Chevron Stations Inc",
    "wof:placetype":"venue"
},
  "geometry": {"coordinates":[-122.06317300000001,37.924761],"type":"Point"}
}