{
  "type": "Feature",
  "properties": {
    "addr:full":"39300 Civic Center Dr Fremont CA 94538",
    "addr:housenumber":"39300",
    "addr:postcode":"94538",
    "addr:street":"Civic Center Dr",
    "iso:country":"US",
    "sg:address":"39300 Civic Center Dr",
    "sg:city":"Fremont",
    "sg:classifiers":[
        {
            "category":"Banks & Credit Unions",
            "subcategory":"Bank",
            "type":"Services"
        }
    ],
    "sg:phone":"+1 510 494 7840",
    "sg:postcode":"94538",
    "sg:province":"CA",
    "sg:tags":[
        "loan",
        "broker"
    ],
    "sg:website":"www.divcap.net",
    "wof:name":"Diversified Capital Funding",
    "wof:placetype":"venue"
},
  "geometry": {"coordinates":[-121.977468,37.555082],"type":"Point"}
}