{
  "type": "Feature",
  "properties": {
    "addr:full":"2535 Camino Del Rio S San Diego CA 92108",
    "addr:housenumber":"2535",
    "addr:postcode":"92108",
    "addr:street":"Camino Del Rio S",
    "iso:country":"US",
    "sg:address":"2535 Camino Del Rio S",
    "sg:city":"San Diego",
    "sg:classifiers":[
        {
            "category":"Shopping",
            "subcategory":"Music",
            "type":"Retail Goods"
        }
    ],
    "sg:phone":"+1 619 243 2520",
    "sg:postcode":"92108",
    "sg:province":"CA",
    "sg:tags":[
        "dvd's"
    ],
    "wof:name":"Integware",
    "wof:placetype":"venue"
},
  "geometry": {"coordinates":[-117.138306,32.768761],"type":"Point"}
}