{
  "type": "Feature",
  "properties": {
    "iso:country":"US",
    "sg:address":"396 Jayne Ave #1",
    "sg:city":"Oakland",
    "sg:classifiers":[
        {
            "category":"Personal",
            "subcategory":"Massage",
            "type":"Services"
        }
    ],
    "sg:phone":"+1 510 260 7100",
    "sg:postcode":"94610",
    "sg:province":"CA",
    "sg:website":"www.healingpause.net",
    "wof:name":"Healing Pause",
    "wof:placetype":"venue"
},
  "geometry": {"coordinates":[-122.253517,37.814671],"type":"Point"}
}