{
  "type": "Feature",
  "properties": {
    "addr:full":"1326 S Main St Los Angeles CA 90015",
    "addr:housenumber":"1326",
    "addr:postcode":"90015",
    "addr:street":"S Main St",
    "iso:country":"US",
    "sg:address":"1326 S Main St",
    "sg:city":"Los Angeles",
    "sg:classifiers":[
        {
            "category":"Wholesale",
            "subcategory":"Apparel",
            "type":"Manufacturing & Wholesale Goods"
        }
    ],
    "sg:phone":"+1 213 747 4955",
    "sg:postcode":"90015",
    "sg:province":"CA",
    "sg:tags":[
        "clothing"
    ],
    "wof:name":"Yoon S Park",
    "wof:placetype":"venue"
},
  "geometry": {"coordinates":[-118.260588,34.035998],"type":"Point"}
}