{
  "type": "Feature",
  "properties": {
    "addr:full":"27150 Hesperian Blvd Hayward CA 94545",
    "addr:housenumber":"27150",
    "addr:postcode":"94545",
    "addr:street":"Hesperian Blvd",
    "iso:country":"US",
    "sg:address":"27150 Hesperian Blvd",
    "sg:city":"Hayward",
    "sg:classifiers":[
        {
            "category":"Restaurant",
            "type":"Food & Drink"
        }
    ],
    "sg:phone":"+1 510 783 9275",
    "sg:postcode":"94545",
    "sg:province":"CA",
    "wof:name":"Caffino",
    "wof:placetype":"venue"
},
  "geometry": {"coordinates":[-122.097718,37.63263],"type":"Point"}
}