{
  "type": "Feature",
  "properties": {
    "addr:full":"244 Verbena Dr Palo Alto CA 94303",
    "addr:housenumber":"244",
    "addr:postcode":"94303",
    "addr:street":"Verbena Dr",
    "iso:country":"US",
    "sg:address":"244 Verbena Dr",
    "sg:city":"Palo Alto",
    "sg:classifiers":[
        {
            "category":"Manufacturing",
            "subcategory":"Retail Goods",
            "type":"Manufacturing & Wholesale Goods"
        }
    ],
    "sg:phone":"+1 650 330 1057",
    "sg:postcode":"94303",
    "sg:province":"CA",
    "sg:tags":[
        "product",
        "mfg"
    ],
    "wof:name":"Heshimas Candles",
    "wof:placetype":"venue"
},
  "geometry": {"coordinates":[-122.12845,37.45796],"type":"Point"}
}