{
  "type": "Feature",
  "properties": {
    "addr:full":"2900 Main St Ste 140D Alameda CA 94501",
    "addr:housenumber":"2900",
    "addr:postcode":"94501",
    "addr:street":"Main St Ste 140D",
    "iso:country":"US",
    "sg:address":"2900 Main St Ste 140D",
    "sg:city":"Alameda",
    "sg:classifiers":[
        {
            "category":"Wholesale",
            "subcategory":"Hardware",
            "type":"Manufacturing & Wholesale Goods"
        }
    ],
    "sg:phone":"+1 510 523 3301",
    "sg:postcode":"94501",
    "sg:province":"CA",
    "sg:tags":[
        "hardware-wholesale",
        "manufacturer"
    ],
    "wof:name":"Industrial Hardware",
    "wof:placetype":"venue"
},
  "geometry": {"coordinates":[-122.292361,37.788008],"type":"Point"}
}