{
  "type": "Feature",
  "properties": {
    "iso:country":"US",
    "sg:address":"27430 Cherry Creek Dr",
    "sg:city":"Valencia",
    "sg:classifiers":[
        {
            "category":"Building & Trades",
            "subcategory":"Cleaning & Sanitation",
            "type":"Services"
        }
    ],
    "sg:phone":"+1 661 297 7298",
    "sg:postcode":"91354",
    "sg:province":"CA",
    "sg:tags":[
        "carpet"
    ],
    "wof:name":"Nice N Neat Services",
    "wof:placetype":"venue"
},
  "geometry": {"coordinates":[-118.535408,34.44896],"type":"Point"}
}