{
  "type": "Feature",
  "properties": {
    "iso:country":"US",
    "sg:address":"540 S Andreasen Dr",
    "sg:city":"Escondido",
    "sg:classifiers":[
        {
            "category":"Professional",
            "type":"Services"
        }
    ],
    "sg:phone":"+1 760 796 4785",
    "sg:postcode":"92029",
    "sg:province":"CA",
    "wof:name":"Home Staging",
    "wof:placetype":"venue"
},
  "geometry": {"coordinates":[-117.113453,33.115724],"type":"Point"}
}