{
  "type": "Feature",
  "properties": {
    "iso:country":"US",
    "sg:address":"10840 Wilshire Blvd",
    "sg:city":"Los Angeles",
    "sg:classifiers":[
        {
            "category":"Cinema",
            "subcategory":"Movie Theater",
            "type":"Entertainment"
        }
    ],
    "sg:phone":"+1 310 475 0711",
    "sg:postcode":"90024",
    "sg:province":"CA",
    "sg:website":"www.amctheatres.com/",
    "wof:name":"AMC Avco Center 4",
    "wof:placetype":"venue"
},
  "geometry": {"coordinates":[-118.44111599999999,34.059414],"type":"Point"}
}