{
  "type": "Feature",
  "properties": {
    "addr:full":"525 Asbury St San Jose CA 95110",
    "addr:housenumber":"525",
    "addr:postcode":"95110",
    "addr:street":"Asbury St",
    "iso:country":"US",
    "sg:address":"525 Asbury St",
    "sg:city":"San Jose",
    "sg:classifiers":[
        {
            "category":"Building & Trades",
            "subcategory":"Electrical",
            "type":"Services"
        }
    ],
    "sg:phone":"+1 408 588 1614",
    "sg:postcode":"95110",
    "sg:province":"CA",
    "sg:tags":[
        "electrical",
        "contractor"
    ],
    "wof:name":"All Bay Electric Inc",
    "wof:placetype":"venue"
},
  "geometry": {"coordinates":[-121.912904,37.342694],"type":"Point"}
}