{
  "type": "Feature",
  "properties": {
    "addr:full":"18525 Sutter Blvd Morgan Hill CA 95037",
    "addr:housenumber":"18525",
    "addr:postcode":"95037",
    "addr:street":"Sutter Blvd",
    "iso:country":"US",
    "sg:address":"18525 Sutter Blvd",
    "sg:city":"Morgan Hill",
    "sg:classifiers":[
        {
            "category":"Real Estate",
            "subcategory":"Real Estate Services",
            "type":"Services"
        }
    ],
    "sg:phone":"+1 408 778 6162",
    "sg:postcode":"95037",
    "sg:province":"CA",
    "sg:tags":[
        "company",
        "title"
    ],
    "wof:name":"Chicago Title Co",
    "wof:placetype":"venue"
},
  "geometry": {"coordinates":[-121.653937,37.146742],"type":"Point"}
}