{
  "type": "Feature",
  "properties": {
    "addr:full":"650 Arroyo Drive South Pasadena CA 91030",
    "addr:housenumber":"650",
    "addr:postcode":"91030",
    "addr:street":"Arroyo Drive",
    "iso:country":"US",
    "sg:address":"650 Arroyo Drive",
    "sg:city":"South Pasadena",
    "sg:classifiers":[
        {
            "category":"Education",
            "subcategory":"Music School",
            "type":"Public Place"
        }
    ],
    "sg:phone":"+1 626 403 4611",
    "sg:postcode":"91030",
    "sg:province":"CA",
    "sg:tags":[
        "instrument",
        "teacher",
        "musical"
    ],
    "sg:website":"StringsProgram.com",
    "wof:name":"South Pasadena Strings Program LLC",
    "wof:placetype":"venue"
},
  "geometry": {"coordinates":[-118.165733,34.117939],"type":"Point"}
}