{
  "type": "Feature",
  "properties": {
    "addr:full":"11861 State Rte 12 Lockeford CA 95237",
    "addr:housenumber":"11861",
    "addr:postcode":"95237",
    "addr:street":"State Rte 12",
    "iso:country":"US",
    "sg:address":"11861 State Rte 12",
    "sg:city":"Lockeford",
    "sg:classifiers":[
        {
            "category":"Building & Trades",
            "subcategory":"Construction",
            "type":"Services"
        }
    ],
    "sg:phone":"+1 209 334 2439",
    "sg:postcode":"95237",
    "sg:province":"CA",
    "sg:tags":[
        "dry wall",
        "contractor"
    ],
    "wof:name":"Drywall Construction",
    "wof:placetype":"venue"
},
  "geometry": {"coordinates":[-121.173721,38.137987],"type":"Point"}
}