{
  "type": "Feature",
  "properties": {
    "iso:country":"US",
    "sg:address":"9921 Horn Rd",
    "sg:city":"Sacramento",
    "sg:classifiers":[
        {
            "category":"Professional",
            "subcategory":"Business Services",
            "type":"Services"
        }
    ],
    "sg:phone":"+1 916 361 6847",
    "sg:postcode":"95827",
    "sg:province":"CA",
    "wof:name":"Private Business Inc",
    "wof:placetype":"venue"
},
  "geometry": {"coordinates":[-121.325221,38.57574],"type":"Point"}
}