{
  "type": "Feature",
  "properties": {
    "iso:country":"US",
    "sg:address":"809 N Main St",
    "sg:city":"Fort Bragg",
    "sg:classifiers":[
        {
            "category":"Manufacturing",
            "subcategory":"Retail Goods",
            "type":"Manufacturing & Wholesale Goods"
        }
    ],
    "sg:phone":"+1 707 964 6980",
    "sg:postcode":"95437",
    "sg:province":"CA",
    "sg:tags":[
        "product",
        "mfg"
    ],
    "wof:name":"Future Craft Productions",
    "wof:placetype":"venue"
},
  "geometry": {"coordinates":[-123.805986,39.450633],"type":"Point"}
}