{
  "type": "Feature",
  "properties": {
    "addr:full":"1100 Scott Boulevard Santa Clara CA 95050",
    "addr:housenumber":"1100",
    "addr:postcode":"95050",
    "addr:street":"Scott Boulevard",
    "iso:country":"US",
    "sg:address":"1100 Scott Boulevard",
    "sg:city":"Santa Clara",
    "sg:classifiers":[
        {
            "category":"Health Services",
            "subcategory":"Dentist",
            "type":"Services"
        }
    ],
    "sg:phone":"+1 408 554 1100",
    "sg:postcode":"95050",
    "sg:province":"CA",
    "wof:name":"Plummer Luann C DDS",
    "wof:placetype":"venue"
},
  "geometry": {"coordinates":[-121.95927500000001,37.346815],"type":"Point"}
}