{
  "type": "Feature",
  "properties": {
    "iso:country":"US",
    "sg:address":"2576 Freedom Blvd",
    "sg:city":"Watsonville",
    "sg:classifiers":[
        {
            "category":"Building & Trades",
            "subcategory":"Construction",
            "type":"Services"
        }
    ],
    "sg:phone":"+1 831 728 4883",
    "sg:postcode":"95076",
    "sg:province":"CA",
    "sg:tags":[
        "carpentry",
        "contractor"
    ],
    "wof:name":"B & M Cabinets",
    "wof:placetype":"venue"
},
  "geometry": {"coordinates":[-121.789106,36.946253],"type":"Point"}
}