{
  "type": "Feature",
  "properties": {
    "addr:full":"701 Grandview Dr S San Francisco CA 94080",
    "addr:housenumber":"701",
    "addr:postcode":"94080",
    "addr:street":"Grandview Dr S",
    "iso:country":"US",
    "sg:address":"701 Grandview Dr",
    "sg:city":"S San Francisco",
    "sg:classifiers":[
        {
            "category":"Building & Trades",
            "subcategory":"Construction",
            "type":"Services"
        }
    ],
    "sg:phone":"+1 650 873 7974",
    "sg:postcode":"94080",
    "sg:province":"CA",
    "sg:tags":[
        "painter"
    ],
    "wof:name":"Paros Painting Co",
    "wof:placetype":"venue"
},
  "geometry": {"coordinates":[-122.382688,37.654483],"type":"Point"}
}