{
  "type": "Feature",
  "properties": {
    "addr:full":"2264 Fair Oaks Blvd Sacramento CA 95825",
    "addr:housenumber":"2264",
    "addr:postcode":"95825",
    "addr:street":"Fair Oaks Blvd",
    "iso:country":"US",
    "sg:address":"2264 Fair Oaks Blvd",
    "sg:city":"Sacramento",
    "sg:classifiers":[
        {
            "category":"Real Estate",
            "subcategory":"Real Estate Services",
            "type":"Services"
        }
    ],
    "sg:phone":"+1 916 920 2150",
    "sg:postcode":"95825",
    "sg:province":"CA",
    "sg:tags":[
        "company",
        "title"
    ],
    "wof:name":"Orange Coast Title Co",
    "wof:placetype":"venue"
},
  "geometry": {"coordinates":[-121.411235,38.574443],"type":"Point"}
}