{
  "type": "Feature",
  "properties": {
    "iso:country":"US",
    "sg:address":"11984 State Hwy 88",
    "sg:city":"Jackson",
    "sg:classifiers":[
        {
            "category":"Shopping",
            "subcategory":"Shoes",
            "type":"Retail Goods"
        }
    ],
    "sg:phone":"+1 209 223 2848",
    "sg:postcode":"95642",
    "sg:province":"CA",
    "wof:name":"Canale's Shoes & Shoe Repair",
    "wof:placetype":"venue"
},
  "geometry": {"coordinates":[-120.799531,38.364661],"type":"Point"}
}