{
  "type": "Feature",
  "properties": {
    "iso:country":"US",
    "sg:address":"2124 Artesia Blvd",
    "sg:city":"Torrance",
    "sg:classifiers":[
        {
            "category":"Retail",
            "subcategory":"Repair Shop",
            "type":"Services"
        },
        {
            "category":"Professional",
            "subcategory":"Computer Services",
            "type":"Services"
        }
    ],
    "sg:phone":"+1 424 201 0060",
    "sg:postcode":"90504",
    "sg:province":"CA",
    "sg:tags":[
        "electronics"
    ],
    "sg:website":"www.digitalclinicweb.com/",
    "wof:name":"Digital Clinic",
    "wof:placetype":"venue"
},
  "geometry": {"coordinates":[-118.316814,33.872564],"type":"Point"}
}