{
  "type": "Feature",
  "properties": {
    "addr:full":"736 Nowita Pl Venice CA 90291",
    "addr:housenumber":"736",
    "addr:postcode":"90291",
    "addr:street":"Nowita Pl",
    "iso:country":"US",
    "sg:address":"736 Nowita Pl",
    "sg:city":"Venice",
    "sg:classifiers":[
        {
            "category":"Building & Trades",
            "subcategory":"Landscaping Services",
            "type":"Services"
        }
    ],
    "sg:phone":"+1 310 823 1274",
    "sg:postcode":"90291",
    "sg:province":"CA",
    "wof:name":"Lordee Land Escapes LLC",
    "wof:placetype":"venue"
},
  "geometry": {"coordinates":[-118.46048999999999,33.993309],"type":"Point"}
}