{
  "type": "Feature",
  "properties": {
    "addr:full":"4656 Calle de Retiro Oceanside CA 92057",
    "addr:housenumber":"4656",
    "addr:postcode":"92057",
    "addr:street":"Calle De Retiro",
    "iso:country":"US",
    "sg:address":"4656 Calle de Retiro",
    "sg:city":"Oceanside",
    "sg:classifiers":[
        {
            "category":"Building & Trades",
            "subcategory":"Plumbing",
            "type":"Services"
        }
    ],
    "sg:phone":"+1 510 387 8708",
    "sg:postcode":"92057",
    "sg:province":"CA",
    "sg:tags":[
        "plumber",
        "industrial",
        "contractors-commercial"
    ],
    "wof:name":"Mclaren Plumbing",
    "wof:placetype":"venue"
},
  "geometry": {"coordinates":[-117.31043200000001,33.249592],"type":"Point"}
}