{
  "type": "Feature",
  "properties": {
    "addr:full":"14832 Beach Blvd La Mirada CA 90638",
    "addr:housenumber":"14832",
    "addr:postcode":"90638",
    "addr:street":"Beach Blvd",
    "iso:country":"US",
    "sg:address":"14832 Beach Blvd",
    "sg:city":"La Mirada",
    "sg:classifiers":[
        {
            "category":"Shopping",
            "subcategory":"Bicycles & Sporting Goods",
            "type":"Retail Goods"
        }
    ],
    "sg:phone":"+1 714 739 2882",
    "sg:postcode":"90638",
    "sg:province":"CA",
    "sg:tags":[
        "surfboard"
    ],
    "wof:name":"Pesce Surfboards",
    "wof:placetype":"venue"
},
  "geometry": {"coordinates":[-117.986414,33.897257],"type":"Point"}
}