{
  "type": "Feature",
  "properties": {
    "iso:country":"US",
    "sg:address":"401 Embarcadero",
    "sg:city":"Oakland",
    "sg:classifiers":[
        {
            "category":"Home & Garden",
            "subcategory":"Building Materials",
            "type":"Retail Goods"
        }
    ],
    "sg:phone":"+1 510 452 4777",
    "sg:postcode":"94606",
    "sg:province":"CA",
    "wof:name":"Mission Valley Rock & Asphalt",
    "wof:placetype":"venue"
},
  "geometry": {"coordinates":[-122.263018,37.790815],"type":"Point"}
}