{
  "type": "Feature",
  "properties": {
    "iso:country":"US",
    "sg:address":"23002 Mariposa Ave",
    "sg:city":"Lomita",
    "sg:classifiers":[
        {
            "category":"Shopping",
            "subcategory":"Bridal",
            "type":"Retail Goods"
        }
    ],
    "sg:phone":"+1 310 325 8160",
    "sg:postcode":"90717",
    "sg:province":"CA",
    "wof:name":"Bel Aire Bridal Accessories",
    "wof:placetype":"venue"
},
  "geometry": {"coordinates":[-118.317001,33.794201],"type":"Point"}
}