{
  "type": "Feature",
  "properties": {
    "addr:full":"144 Holm Rd Spc 72 Watsonville CA 95076",
    "addr:housenumber":"144;72",
    "addr:postcode":"95076",
    "addr:street":"Holm Rd Spc",
    "iso:country":"US",
    "sg:address":"144 Holm Rd Spc 72",
    "sg:city":"Watsonville",
    "sg:classifiers":[
        {
            "category":"Retail",
            "subcategory":"Laundry & Dry Cleaning",
            "type":"Services"
        },
        {
            "category":"Home & Garden",
            "subcategory":"Carpets & Floor Coverings",
            "type":"Retail Goods"
        }
    ],
    "sg:phone":"+1 831 722 3421",
    "sg:postcode":"95076",
    "sg:province":"CA",
    "sg:tags":[
        "cleaner",
        "rug"
    ],
    "wof:name":"Lewis Carpet",
    "wof:placetype":"venue"
},
  "geometry": {"coordinates":[-121.787228,36.92264],"type":"Point"}
}