{
  "type": "Feature",
  "properties": {
    "addr:full":"11600 Riverside Dr Mira Loma CA 91752",
    "addr:housenumber":"11600",
    "addr:postcode":"91752",
    "addr:street":"Riverside Dr",
    "iso:country":"US",
    "sg:address":"11600 Riverside Dr",
    "sg:city":"Mira Loma",
    "sg:classifiers":[
        {
            "category":"Professional",
            "subcategory":"Management & Consulting",
            "type":"Services"
        }
    ],
    "sg:phone":"+1 951 681 0058",
    "sg:postcode":"91752",
    "sg:province":"CA",
    "sg:tags":[
        "consultant",
        "export"
    ],
    "wof:name":"Calexivo Forwarding Of Ca",
    "wof:placetype":"venue"
},
  "geometry": {"coordinates":[-117.53456,34.017374],"type":"Point"}
}