{
  "type": "Feature",
  "properties": {
    "addr:full":"50 W Broadway Glendale CA 91204",
    "addr:housenumber":"50",
    "addr:postcode":"91204",
    "addr:street":"W Broadway",
    "iso:country":"US",
    "sg:address":"50 W Broadway",
    "sg:city":"Glendale",
    "sg:classifiers":[
        {
            "category":"Restaurant",
            "type":"Food & Drink"
        }
    ],
    "sg:phone":"+1 818 247 8499",
    "sg:postcode":"91204",
    "sg:province":"CA",
    "sg:website":"www.todai.com",
    "wof:name":"Todai Restaurant Inc",
    "wof:placetype":"venue"
},
  "geometry": {"coordinates":[-118.256158,34.146268],"type":"Point"}
}