{
  "type": "Feature",
  "properties": {
    "iso:country":"US",
    "sg:address":"1208 W Struck Ave",
    "sg:city":"Orange",
    "sg:classifiers":[
        {
            "category":"Wholesale",
            "subcategory":"Medical Equipment & Supplies",
            "type":"Manufacturing & Wholesale Goods"
        }
    ],
    "sg:phone":"+1 714 997 7735",
    "sg:postcode":"92867",
    "sg:province":"CA",
    "sg:tags":[
        "dental"
    ],
    "wof:name":"Econotek Inc",
    "wof:placetype":"venue"
},
  "geometry": {"coordinates":[-117.866476,33.805966],"type":"Point"}
}