{
  "type": "Feature",
  "properties": {
    "addr:full":"1038 S Glendora Ave West Covina CA 91790",
    "addr:housenumber":"1038",
    "addr:postcode":"91790",
    "addr:street":"S Glendora Ave",
    "iso:country":"US",
    "sg:address":"1038 S Glendora Ave",
    "sg:city":"West Covina",
    "sg:classifiers":[
        {
            "category":"Health Services",
            "subcategory":"Doctor",
            "type":"Services"
        }
    ],
    "sg:phone":"+1 626 814 2766",
    "sg:postcode":"91790",
    "sg:province":"CA",
    "sg:tags":[
        "physician",
        "surgeon"
    ],
    "wof:name":"Mancy Medical Ctr",
    "wof:placetype":"venue"
},
  "geometry": {"coordinates":[-117.93611900000001,34.057532],"type":"Point"}
}