{
  "type": "Feature",
  "properties": {
    "iso:country":"US",
    "sg:address":"2050 Sinaloa Rd",
    "sg:city":"Simi Valley",
    "sg:classifiers":[
        {
            "category":"Retail",
            "subcategory":"Auto Repair",
            "type":"Services"
        }
    ],
    "sg:phone":"+1 805 522 4700",
    "sg:postcode":"93065",
    "sg:province":"CA",
    "sg:tags":[
        "repairing",
        "automobile"
    ],
    "wof:name":"A & D Automotive Inc",
    "wof:placetype":"venue"
},
  "geometry": {"coordinates":[-118.787529,34.272127],"type":"Point"}
}