{
  "type": "Feature",
  "properties": {
    "iso:country":"US",
    "sg:address":"700 E Santa Barbara St",
    "sg:city":"Santa Paula",
    "sg:classifiers":[
        {
            "category":"Organizations",
            "subcategory":"Community Association",
            "type":"Services"
        }
    ],
    "sg:phone":"+1 805 525 7617",
    "sg:postcode":"93060",
    "sg:province":"CA",
    "wof:name":"Lodge 2097 - Santa Paula",
    "wof:placetype":"venue"
},
  "geometry": {"coordinates":[-119.06643699999999,34.35385],"type":"Point"}
}