{
  "type": "Feature",
  "properties": {
    "addr:full":"5180 Convoy Street San Diego CA 92111",
    "addr:housenumber":"5180",
    "addr:postcode":"92111",
    "addr:street":"Convoy Street",
    "iso:country":"US",
    "sg:address":"5180 Convoy Street",
    "sg:city":"San Diego",
    "sg:classifiers":[
        {
            "category":"Government",
            "subcategory":"City Hall",
            "type":"Public Place"
        }
    ],
    "sg:phone":"+1 858 492 6100",
    "sg:postcode":"92111",
    "sg:province":"CA",
    "sg:website":"www.sandiego.gov/environmental-s...",
    "wof:name":"Miramar Landfill",
    "wof:placetype":"venue"
},
  "geometry": {"coordinates":[-117.152277,32.836754],"type":"Point"}
}