{
  "type": "Feature",
  "properties": {
    "iso:country":"US",
    "sg:address":"14043 Whittier Blvd",
    "sg:city":"Whittier",
    "sg:classifiers":[
        {
            "category":"Autos & Motor Vehicles",
            "subcategory":"Motorcycle Sales",
            "type":"Retail Goods"
        }
    ],
    "sg:phone":"+1 562 945 3494",
    "sg:postcode":"90605",
    "sg:province":"CA",
    "sg:tags":[
        "scooter"
    ],
    "wof:name":"Whittier Honda Kawasaki Seadoo",
    "wof:placetype":"venue"
},
  "geometry": {"coordinates":[-118.022753,33.957499],"type":"Point"}
}