{
  "type": "Feature",
  "properties": {
    "iso:country":"US",
    "sg:address":"839 W Palmdale Blvd",
    "sg:city":"Palmdale",
    "sg:classifiers":[
        {
            "category":"Health Services",
            "subcategory":"Chiropractor",
            "type":"Services"
        }
    ],
    "sg:phone":"+1 661 947 7993",
    "sg:postcode":"93551",
    "sg:province":"CA",
    "wof:name":"Hopper Chiropractic Clinic",
    "wof:placetype":"venue"
},
  "geometry": {"coordinates":[-118.146565,34.587118],"type":"Point"}
}