{
  "type": "Feature",
  "properties": {
    "addr:full":"7045 Oak Hill Rd Hesperia CA 92345",
    "addr:housenumber":"7045",
    "addr:postcode":"92345",
    "addr:street":"Oak Hill Rd",
    "iso:country":"US",
    "sg:address":"7045 Oak Hill Rd",
    "sg:city":"Hesperia",
    "sg:classifiers":[
        {
            "category":"Wholesale",
            "subcategory":"Farm Supplies",
            "type":"Manufacturing & Wholesale Goods"
        }
    ],
    "sg:phone":"+1 760 949 2635",
    "sg:postcode":"92345",
    "sg:province":"CA",
    "sg:tags":[
        "livestock"
    ],
    "wof:name":"Eshleman Livestock",
    "wof:placetype":"venue"
},
  "geometry": {"coordinates":[-117.431618,34.375765],"type":"Point"}
}