{
  "type": "Feature",
  "properties": {
    "addr:full":"12125 Folsom Blvd Rancho Cordova CA 95742",
    "addr:housenumber":"12125",
    "addr:postcode":"95742",
    "addr:street":"Folsom Blvd",
    "iso:country":"US",
    "sg:address":"12125 Folsom Blvd",
    "sg:city":"Rancho Cordova",
    "sg:classifiers":[
        {
            "category":"Home & Garden",
            "subcategory":"Furniture",
            "type":"Retail Goods"
        }
    ],
    "sg:phone":"+1 916 351 0227",
    "sg:postcode":"95742",
    "sg:province":"CA",
    "wof:name":"Naturwood Home Furnishings",
    "wof:placetype":"venue"
},
  "geometry": {"coordinates":[-121.230795,38.623673],"type":"Point"}
}