{
  "type": "Feature",
  "properties": {
    "iso:country":"US",
    "sg:address":"512 Main St",
    "sg:city":"Fillmore",
    "sg:classifiers":[
        {
            "category":"Autos & Motor Vehicles",
            "subcategory":"Boat Sales",
            "type":"Retail Goods"
        }
    ],
    "sg:phone":"+1 805 524 9599",
    "sg:postcode":"93015",
    "sg:province":"CA",
    "sg:tags":[
        "dealer",
        "sales"
    ],
    "wof:name":"Carrea Boats West",
    "wof:placetype":"venue"
},
  "geometry": {"coordinates":[-118.91404799999999,34.398985],"type":"Point"}
}