{
  "type": "Feature",
  "properties": {
    "iso:country":"US",
    "sg:address":"2535 E Ventura Blvd",
    "sg:city":"Oxnard",
    "sg:classifiers":[
        {
            "category":"Autos & Motor Vehicles",
            "subcategory":"Automobile Sales",
            "type":"Retail Goods"
        }
    ],
    "sg:phone":"+1 805 988 8899",
    "sg:postcode":"93036",
    "sg:province":"CA",
    "sg:tags":[
        "classic"
    ],
    "sg:website":"www.cars4causes.net",
    "wof:name":"Cars 4 Causes",
    "wof:placetype":"venue"
},
  "geometry": {"coordinates":[-119.16132899999999,34.226182],"type":"Point"}
}