{
  "type": "Feature",
  "properties": {
    "addr:full":"6135 Mariposa Ave Citrus Heights CA 95610",
    "addr:housenumber":"6135",
    "addr:postcode":"95610",
    "addr:street":"Mariposa Ave",
    "iso:country":"US",
    "sg:address":"6135 Mariposa Ave",
    "sg:city":"Citrus Heights",
    "sg:classifiers":[
        {
            "category":"Personal",
            "subcategory":"Beauty Salon",
            "type":"Services"
        }
    ],
    "sg:phone":"+1 916 721 1200",
    "sg:postcode":"95610",
    "sg:province":"CA",
    "wof:name":"Barbara Cruz",
    "wof:placetype":"venue"
},
  "geometry": {"coordinates":[-121.284806,38.677897],"type":"Point"}
}