{
  "type": "Feature",
  "properties": {
    "addr:full":"7070 Fruitridge Rd Sacramento CA 95820",
    "addr:housenumber":"7070",
    "addr:postcode":"95820",
    "addr:street":"Fruitridge Rd",
    "iso:country":"US",
    "sg:address":"7070 Fruitridge Rd",
    "sg:city":"Sacramento",
    "sg:classifiers":[
        {
            "category":"Government",
            "subcategory":"Office",
            "type":"Public Place"
        }
    ],
    "sg:phone":"+1 916 386 2062",
    "sg:postcode":"95820",
    "sg:province":"CA",
    "sg:tags":[
        "smog",
        "check"
    ],
    "wof:name":"Cartagz",
    "wof:placetype":"venue"
},
  "geometry": {"coordinates":[-121.42176000000001,38.524942],"type":"Point"}
}