{
  "type": "Feature",
  "properties": {
    "iso:country":"US",
    "sg:address":"1215 Laurel St",
    "sg:city":"San Carlos",
    "sg:classifiers":[
        {
            "category":"Personal",
            "subcategory":"Barber",
            "type":"Services"
        }
    ],
    "sg:phone":"+1 650 637 1330",
    "sg:postcode":"94070",
    "sg:province":"CA",
    "wof:name":"Kitty's Men's Hairstyling",
    "wof:placetype":"venue"
},
  "geometry": {"coordinates":[-122.251615,37.498612],"type":"Point"}
}