{
  "type": "Feature",
  "properties": {
    "iso:country":"US",
    "sg:address":"1660 Dove St",
    "sg:city":"Newport Beach",
    "sg:classifiers":[
        {
            "category":"Sports & Exercise",
            "subcategory":"Gym",
            "type":"Entertainment"
        }
    ],
    "sg:phone":"+1 949 474 5550",
    "sg:postcode":"92660",
    "sg:province":"CA",
    "sg:tags":[
        "club",
        "health",
        "studio",
        "gymnasium"
    ],
    "wof:name":"Corp Xcel Sport & Fitness Inc",
    "wof:placetype":"venue"
},
  "geometry": {"coordinates":[-117.867264,33.665804],"type":"Point"}
}