{
  "type": "Feature",
  "properties": {
    "addr:full":"1450 Frazee Rd Ste 310 San Diego CA 92108",
    "addr:housenumber":"1450",
    "addr:postcode":"92108",
    "addr:street":"Frazee Rd Ste 310",
    "iso:country":"US",
    "sg:address":"1450 Frazee Rd Ste 310",
    "sg:city":"San Diego",
    "sg:classifiers":[
        {
            "category":"Professional",
            "subcategory":"Accounting & Tax Preparation",
            "type":"Services"
        }
    ],
    "sg:phone":"+1 619 297 9116",
    "sg:postcode":"92108",
    "sg:province":"CA",
    "sg:tags":[
        "accountant"
    ],
    "wof:name":"Proko Uribe & Maynard Llp",
    "wof:placetype":"venue"
},
  "geometry": {"coordinates":[-117.15799699999999,32.773399],"type":"Point"}
}