{
  "type": "Feature",
  "properties": {
    "addr:full":"1329 F St Livingston CA 95334",
    "addr:housenumber":"1329",
    "addr:postcode":"95334",
    "addr:street":"F St",
    "iso:country":"US",
    "sg:address":"1329 F St",
    "sg:city":"Livingston",
    "sg:classifiers":[
        {
            "category":"Professional",
            "type":"Services"
        },
        {
            "category":"Farming",
            "subcategory":"Fish & Marine Products",
            "type":"Manufacturing & Wholesale Goods"
        }
    ],
    "sg:phone":"+1 209 394 7828",
    "sg:postcode":"95334",
    "sg:province":"CA",
    "sg:tags":[
        "harvesting-contract"
    ],
    "wof:name":"Pedro Valencia Labor Contractor",
    "wof:placetype":"venue"
},
  "geometry": {"coordinates":[-120.724153,37.382276],"type":"Point"}
}