{
  "type": "Feature",
  "properties": {
    "addr:full":"715 N Garey Ave Pomona CA 91767",
    "addr:housenumber":"715",
    "addr:postcode":"91767",
    "addr:street":"N Garey Ave",
    "iso:country":"US",
    "sg:address":"715 N Garey Ave",
    "sg:city":"Pomona",
    "sg:classifiers":[
        {
            "category":"Shopping",
            "subcategory":"Florist",
            "type":"Retail Goods"
        }
    ],
    "sg:phone":"+1 909 623 6949",
    "sg:postcode":"91767",
    "sg:province":"CA",
    "wof:name":"Pomona Floral Co",
    "wof:placetype":"venue"
},
  "geometry": {"coordinates":[-117.75148299999999,34.06646],"type":"Point"}
}