{
  "type": "Feature",
  "properties": {
    "iso:country":"US",
    "sg:address":"715 N Garey Ave",
    "sg:city":"Pomona",
    "sg:classifiers":[
        {
            "category":"Shopping",
            "subcategory":"Florist",
            "type":"Retail Goods"
        }
    ],
    "sg:phone":"+1 909 623 6949",
    "sg:postcode":"91767",
    "sg:province":"CA",
    "wof:name":"Pomona Floral Co",
    "wof:placetype":"venue"
},
  "geometry": {"coordinates":[-117.751483,34.06646],"type":"Point"}
}