{
  "type": "Feature",
  "properties": {
    "iso:country":"US",
    "sg:address":"116 S Riverside Ave",
    "sg:city":"Rialto",
    "sg:classifiers":[
        {
            "category":"Professional",
            "subcategory":"Accounting & Tax Preparation",
            "type":"Services"
        }
    ],
    "sg:phone":"+1 909 421 1923",
    "sg:postcode":"92376",
    "sg:province":"CA",
    "sg:tags":[
        "bookkeeping",
        "general"
    ],
    "wof:name":"Empire Business Svc",
    "wof:placetype":"venue"
},
  "geometry": {"coordinates":[-117.370574,34.099191],"type":"Point"}
}