{
  "type": "Feature",
  "properties": {
    "addr:full":"25252 La Paz Rd Laguna Hills CA 92637",
    "addr:housenumber":"25252",
    "addr:postcode":"92637",
    "addr:street":"La Paz Rd",
    "iso:country":"US",
    "sg:address":"25252 La Paz Rd",
    "sg:city":"Laguna Hills",
    "sg:classifiers":[
        {
            "category":"Fast Food",
            "type":"Food & Drink"
        }
    ],
    "sg:phone":"+1 949 458 8000",
    "sg:postcode":"92637",
    "sg:province":"CA",
    "sg:tags":[
        "burger"
    ],
    "wof:name":"Hot Off the Grill",
    "wof:placetype":"venue"
},
  "geometry": {"coordinates":[-117.68000000000001,33.595699],"type":"Point"}
}