{
  "type": "Feature",
  "properties": {
    "addr:full":"379 Mount Madonna Rd Watsonville CA 95076",
    "addr:housenumber":"379",
    "addr:postcode":"95076",
    "addr:street":"Mount Madonna Rd",
    "iso:country":"US",
    "sg:address":"379 Mount Madonna Rd",
    "sg:city":"Watsonville",
    "sg:classifiers":[
        {
            "category":"Retail",
            "subcategory":"Veterinary Services",
            "type":"Services"
        }
    ],
    "sg:phone":"+1 831 768 7148",
    "sg:postcode":"95076",
    "sg:province":"CA",
    "sg:tags":[
        "hospital",
        "animal"
    ],
    "wof:name":"Dentistry For Animals",
    "wof:placetype":"venue"
},
  "geometry": {"coordinates":[-121.737864,36.991277],"type":"Point"}
}