{
  "type": "Feature",
  "properties": {
    "iso:country":"US",
    "sg:address":"2040 Waldon St",
    "sg:city":"Redding",
    "sg:classifiers":[
        {
            "category":"Social Services",
            "type":"Services"
        }
    ],
    "sg:phone":"+1 530 243 7099",
    "sg:postcode":"96001",
    "sg:province":"CA",
    "sg:tags":[
        "care",
        "center",
        "day"
    ],
    "wof:name":"J & B Programs Inc",
    "wof:placetype":"venue"
},
  "geometry": {"coordinates":[-122.390162,40.576341],"type":"Point"}
}