{
  "type": "Feature",
  "properties": {
    "iso:country":"US",
    "sg:address":"4821 Lankershim Blvd.",
    "sg:city":"Los Angeles",
    "sg:classifiers":[
        {
            "category":"Building & Trades",
            "subcategory":"Construction",
            "type":"Services"
        }
    ],
    "sg:phone":"+1 818 767 8707",
    "sg:postcode":"91601",
    "sg:province":"CA",
    "sg:tags":[
        "contractor"
    ],
    "sg:website":"www.osbornebuilding.com",
    "wof:name":"Osborne Building Corporation",
    "wof:placetype":"venue"
},
  "geometry": {"coordinates":[-118.370588,34.15781],"type":"Point"}
}