{
  "type": "Feature",
  "properties": {
    "addr:full":"500 E Remington Dr Suite 19 Sunnyvale CA 94087",
    "addr:housenumber":"500;19",
    "addr:postcode":"94087",
    "addr:street":"E Remington Dr Suite",
    "iso:country":"US",
    "sg:address":"500 E Remington Dr Suite 19",
    "sg:city":"Sunnyvale",
    "sg:classifiers":[
        {
            "category":"Health Services",
            "subcategory":"Dentist",
            "type":"Services"
        }
    ],
    "sg:phone":"+1 408 749 9888",
    "sg:postcode":"94087",
    "sg:province":"CA",
    "sg:tags":[
        "orthodontist",
        "cosmetic"
    ],
    "sg:website":"www.dentalspecialty.com/",
    "wof:name":"Sung J. Hong, DDS, MA",
    "wof:placetype":"venue"
},
  "geometry": {"coordinates":[-122.02791000000001,37.358343],"type":"Point"}
}