{
  "type": "Feature",
  "properties": {
    "iso:country":"US",
    "sg:address":"361 Saddle Ln",
    "sg:city":"Ojai",
    "sg:classifiers":[
        {
            "category":"Shopping",
            "subcategory":"Computers & Home Electronics",
            "type":"Retail Goods"
        }
    ],
    "sg:phone":"+1 805 466 2687",
    "sg:postcode":"93023",
    "sg:province":"CA",
    "sg:tags":[
        "software"
    ],
    "wof:name":"Ojai-Bend Inc",
    "wof:placetype":"venue"
},
  "geometry": {"coordinates":[-119.243861,34.439189],"type":"Point"}
}