{
  "type": "Feature",
  "properties": {
    "addr:full":"7950 Dublin Blvd Dublin CA 94568",
    "addr:housenumber":"7950",
    "addr:postcode":"94568",
    "addr:street":"Dublin Blvd",
    "iso:country":"US",
    "sg:address":"7950 Dublin Blvd",
    "sg:city":"Dublin",
    "sg:classifiers":[
        {
            "category":"Real Estate",
            "subcategory":"Developer",
            "type":"Services"
        }
    ],
    "sg:phone":"+1 925 551 7900",
    "sg:postcode":"94568",
    "sg:province":"CA",
    "wof:name":"Corrie Development Corp",
    "wof:placetype":"venue"
},
  "geometry": {"coordinates":[-121.93552,37.702163],"type":"Point"}
}