{
  "type": "Feature",
  "properties": {
    "iso:country":"US",
    "sg:address":"934 Diablo Ave",
    "sg:city":"Novato",
    "sg:classifiers":[
        {
            "category":"Restaurant",
            "type":"Food & Drink"
        }
    ],
    "sg:phone":"+1 415 897 6720",
    "sg:postcode":"94947",
    "sg:province":"CA",
    "wof:name":"Mario's Italian Subs",
    "wof:placetype":"venue"
},
  "geometry": {"coordinates":[-122.57191899999999,38.104078],"type":"Point"}
}