{
  "type": "Feature",
  "properties": {
    "addr:full":"5150 Fair Oaks Blvd # 108 Carmichael CA 95608",
    "addr:housenumber":"5150;108",
    "addr:postcode":"95608",
    "addr:street":"Fair Oaks Blvd #",
    "iso:country":"US",
    "sg:address":"5150 Fair Oaks Blvd # 108",
    "sg:city":"Carmichael",
    "sg:classifiers":[
        {
            "category":"Restaurant",
            "type":"Food & Drink"
        }
    ],
    "sg:phone":"+1 916 971 9090",
    "sg:postcode":"95608",
    "sg:province":"CA",
    "sg:tags":[
        "italian"
    ],
    "wof:name":"Tavano's Napoli Ristorante",
    "wof:placetype":"venue"
},
  "geometry": {"coordinates":[-121.344002,38.596699],"type":"Point"}
}