{
  "type": "Feature",
  "properties": {
    "iso:country":"US",
    "sg:address":"5175 River View Ct",
    "sg:city":"Fallbrook",
    "sg:classifiers":[
        {
            "category":"Retail",
            "subcategory":"Car Wash",
            "type":"Services"
        }
    ],
    "sg:phone":"+1 760 723 0815",
    "sg:postcode":"92028",
    "sg:province":"CA",
    "sg:tags":[
        "truck",
        "cleaning"
    ],
    "wof:name":"Precision Fleet Washing",
    "wof:placetype":"venue"
},
  "geometry": {"coordinates":[-117.14998900000001,33.33013],"type":"Point"}
}