{
  "type": "Feature",
  "properties": {
    "iso:country":"US",
    "sg:address":"517 2nd St",
    "sg:city":"Santa Rosa",
    "sg:classifiers":[
        {
            "category":"Utilities",
            "subcategory":"Water",
            "type":"Services"
        }
    ],
    "sg:phone":"+1 707 522 8511",
    "sg:postcode":"95401",
    "sg:province":"CA",
    "sg:tags":[
        "company",
        "sewage"
    ],
    "wof:name":"Windsor Water & Sewer",
    "wof:placetype":"venue"
},
  "geometry": {"coordinates":[-122.713655,38.438782],"type":"Point"}
}