{
  "type": "Feature",
  "properties": {
    "iso:country":"US",
    "sg:address":"595 E Calaveras Blvd",
    "sg:city":"Milpitas",
    "sg:classifiers":[
        {
            "category":"Deli",
            "type":"Food & Drink"
        }
    ],
    "sg:menulink":"http://www.allmenus.com/ca/san-jose/20390-eriks-delicafe/menu/",
    "sg:phone":"+1 408 262 7878",
    "sg:postcode":"95035",
    "sg:province":"CA",
    "sg:tags":[
        "american"
    ],
    "wof:name":"Erik's Delicafe",
    "wof:placetype":"venue"
},
  "geometry": {"coordinates":[-121.896837,37.432906],"type":"Point"}
}