{
  "type": "Feature",
  "properties": {
    "addr:full":"9958 Live Oak Ave Fontana CA 92335",
    "addr:housenumber":"9958",
    "addr:postcode":"92335",
    "addr:street":"Live Oak Ave",
    "iso:country":"US",
    "sg:address":"9958 Live Oak Ave",
    "sg:city":"Fontana",
    "sg:classifiers":[
        {
            "category":"Freight",
            "type":"Transportation"
        }
    ],
    "sg:phone":"+1 909 822 0807",
    "sg:postcode":"92335",
    "sg:province":"CA",
    "wof:name":"Alanis Transportation",
    "wof:placetype":"venue"
},
  "geometry": {"coordinates":[-117.480008,34.072982],"type":"Point"}
}