{
  "type": "Feature",
  "properties": {
    "iso:country":"US",
    "sg:address":"11239 Ventura Blvd suite 212 Room 33",
    "sg:city":"Studio CIty",
    "sg:classifiers":[
        {
            "category":"Personal",
            "subcategory":"Beauty Salon",
            "type":"Services"
        }
    ],
    "sg:phone":"+1 818 268 6049",
    "sg:postcode":"91604",
    "sg:province":"CA",
    "sg:tags":[
        "spa"
    ],
    "wof:name":"Styles by Vanessa",
    "wof:placetype":"venue"
},
  "geometry": {"coordinates":[-118.375049,34.141614],"type":"Point"}
}