{
  "type": "Feature",
  "properties": {
    "iso:country":"US",
    "sg:address":"2520 S. Birch St.",
    "sg:city":"Santa Ana",
    "sg:classifiers":[
        {
            "category":"Professional",
            "type":"Services"
        }
    ],
    "sg:postcode":"92707",
    "sg:province":"CA",
    "sg:tags":[
        "caterer"
    ],
    "wof:name":"Oscar Catering",
    "wof:placetype":"venue"
},
  "geometry": {"coordinates":[-117.87121399999999,33.712983],"type":"Point"}
}