{
  "type": "Feature",
  "properties": {
    "iso:country":"US",
    "sg:address":"16641 Akron St",
    "sg:city":"Pacific Plsds",
    "sg:classifiers":[
        {
            "category":"Retail",
            "subcategory":"Laundry & Dry Cleaning",
            "type":"Services"
        }
    ],
    "sg:phone":"+1 310 399 5262",
    "sg:postcode":"90272",
    "sg:province":"CA",
    "sg:tags":[
        "cleaners",
        "rug",
        "carpet"
    ],
    "wof:name":"Dave's Carpet & Upholstery",
    "wof:placetype":"venue"
},
  "geometry": {"coordinates":[-118.54346200000001,34.050495],"type":"Point"}
}