{
  "type": "Feature",
  "properties": {
    "addr:full":"3225 Firestone Blvd South Gate CA 90280",
    "addr:housenumber":"3225",
    "addr:postcode":"90280",
    "addr:street":"Firestone Blvd;Gate",
    "iso:country":"US",
    "sg:address":"3225 Firestone Blvd",
    "sg:city":"South Gate",
    "sg:classifiers":[
        {
            "category":"Government",
            "subcategory":"Office",
            "type":"Public Place"
        }
    ],
    "sg:phone":"+1 323 566 7521",
    "sg:postcode":"90280",
    "sg:province":"CA",
    "sg:tags":[
        "smog",
        "check"
    ],
    "sg:website":"www.firestone.com",
    "wof:name":"Firestone Smog Test Only Center",
    "wof:placetype":"venue"
},
  "geometry": {"coordinates":[-118.21278700000001,33.955021],"type":"Point"}
}