{
  "type": "Feature",
  "properties": {
    "addr:full":"844 Broadway St Chico CA 95928",
    "addr:housenumber":"844",
    "addr:postcode":"95928",
    "addr:street":"Broadway St",
    "iso:country":"US",
    "sg:address":"844 Broadway St",
    "sg:city":"Chico",
    "sg:classifiers":[
        {
            "category":"Retail",
            "subcategory":"Repair Shop",
            "type":"Services"
        }
    ],
    "sg:phone":"+1 530 342 3551",
    "sg:postcode":"95928",
    "sg:province":"CA",
    "sg:tags":[
        "pumps-service"
    ],
    "wof:name":"Byron Jackson Supply",
    "wof:placetype":"venue"
},
  "geometry": {"coordinates":[-121.836251,39.725287],"type":"Point"}
}