{
  "type": "Feature",
  "properties": {
    "addr:full":"719 Hamilton Ln Santa Clara CA 95051",
    "addr:housenumber":"719",
    "addr:postcode":"95051",
    "addr:street":"Hamilton Ln",
    "iso:country":"US",
    "sg:address":"719 Hamilton Ln",
    "sg:city":"Santa Clara",
    "sg:classifiers":[
        {
            "category":"Banks & Credit Unions",
            "subcategory":"Investment Brokerage",
            "type":"Services"
        }
    ],
    "sg:phone":"+1 408 249 2994",
    "sg:postcode":"95051",
    "sg:province":"CA",
    "sg:tags":[
        "all",
        "natural",
        "commodity",
        "dietary",
        "supplement",
        "trading"
    ],
    "wof:name":"George Hand Distilled Products",
    "wof:placetype":"venue"
},
  "geometry": {"coordinates":[-121.980288,37.3364],"type":"Point"}
}