{
  "type": "Feature",
  "properties": {
    "iso:country":"US",
    "sg:address":"5530 Lincoln Ave",
    "sg:city":"Cypress",
    "sg:classifiers":[
        {
            "category":"Shopping",
            "subcategory":"Bicycles & Sporting Goods",
            "type":"Retail Goods"
        }
    ],
    "sg:phone":"+1 714 995 6541",
    "sg:postcode":"90630",
    "sg:province":"CA",
    "sg:tags":[
        "bike"
    ],
    "wof:name":"Bike Land of Cypress",
    "wof:placetype":"venue"
},
  "geometry": {"coordinates":[-118.03600299999999,33.831501],"type":"Point"}
}