{
  "type": "Feature",
  "properties": {
    "addr:full":"39556 Via Montalvo Murrieta CA 92563",
    "addr:housenumber":"39556",
    "addr:postcode":"92563",
    "addr:street":"Via Montalvo",
    "iso:country":"US",
    "sg:address":"39556 Via Montalvo",
    "sg:city":"Murrieta",
    "sg:classifiers":[
        {
            "category":"Professional",
            "subcategory":"Art Services",
            "type":"Services"
        }
    ],
    "sg:phone":"+1 951 677 2265",
    "sg:postcode":"92563",
    "sg:province":"CA",
    "sg:tags":[
        "commercial",
        "artist"
    ],
    "wof:name":"Cats In The Cradle Publications",
    "wof:placetype":"venue"
},
  "geometry": {"coordinates":[-117.16522500000001,33.564399],"type":"Point"}
}