{
  "type": "Feature",
  "properties": {
    "addr:full":"641 S Brookhurst St Anaheim CA 92804",
    "addr:housenumber":"641",
    "addr:postcode":"92804",
    "addr:street":"S Brookhurst St",
    "iso:country":"US",
    "sg:address":"641 S Brookhurst St",
    "sg:city":"Anaheim",
    "sg:classifiers":[
        {
            "category":"Travel",
            "subcategory":"Hotels & Motels",
            "type":"Entertainment"
        }
    ],
    "sg:phone":"+1 714 535 0935",
    "sg:postcode":"92804",
    "sg:province":"CA",
    "wof:name":"Polynesian Motel",
    "wof:placetype":"venue"
},
  "geometry": {"coordinates":[-117.960121,33.823364],"type":"Point"}
}