{
  "type": "Feature",
  "properties": {
    "addr:full":"4761 S Broadway Los Angeles CA 90037",
    "addr:housenumber":"4761",
    "addr:postcode":"90037",
    "addr:street":"S Broadway",
    "iso:country":"US",
    "sg:address":"4761 S Broadway",
    "sg:city":"Los Angeles",
    "sg:classifiers":[
        {
            "category":"Home & Garden",
            "subcategory":"Furniture",
            "type":"Retail Goods"
        }
    ],
    "sg:phone":"+1 323 232 3239",
    "sg:postcode":"90037",
    "sg:province":"CA",
    "sg:tags":[
        "store"
    ],
    "wof:name":"Family Furniture",
    "wof:placetype":"venue"
},
  "geometry": {"coordinates":[-118.278198,33.999692],"type":"Point"}
}