{
  "type": "Feature",
  "properties": {
    "iso:country":"US",
    "sg:address":"5065 Mission Blvd",
    "sg:city":"Montclair",
    "sg:classifiers":[
        {
            "category":"Restaurant",
            "type":"Food & Drink"
        }
    ],
    "sg:phone":"+1 909 628 4852",
    "sg:postcode":"91763",
    "sg:province":"CA",
    "wof:name":"El Nopal",
    "wof:placetype":"venue"
},
  "geometry": {"coordinates":[-117.69511199999999,34.055838],"type":"Point"}
}