{
  "type": "Feature",
  "properties": {
    "addr:full":"417 Gellert Blvd Daly City CA 94015",
    "addr:housenumber":"417",
    "addr:postcode":"94015",
    "addr:street":"Gellert Blvd",
    "iso:country":"US",
    "sg:address":"417 Gellert Blvd",
    "sg:city":"Daly City",
    "sg:classifiers":[
        {
            "category":"Arts & Performance",
            "subcategory":"Theater",
            "type":"Entertainment"
        }
    ],
    "sg:phone":"+1 650 878 9951",
    "sg:postcode":"94015",
    "sg:province":"CA",
    "sg:tags":[
        "karaoke"
    ],
    "wof:name":"Star Express",
    "wof:placetype":"venue"
},
  "geometry": {"coordinates":[-122.469133,37.662393],"type":"Point"}
}