{
  "type": "Feature",
  "properties": {
    "addr:full":"20826 Lassen St Chatsworth CA 91311",
    "addr:housenumber":"20826",
    "addr:postcode":"91311",
    "addr:street":"Lassen St",
    "iso:country":"US",
    "sg:address":"20826 Lassen St",
    "sg:city":"Chatsworth",
    "sg:classifiers":[
        {
            "category":"Manufacturing",
            "subcategory":"Apparel",
            "type":"Manufacturing & Wholesale Goods"
        }
    ],
    "sg:phone":"+1 818 882 1000",
    "sg:postcode":"91311",
    "sg:province":"CA",
    "sg:tags":[
        "work",
        "clothing-wholesale",
        "manufacturer"
    ],
    "sg:website":"http://www.pacificteaze.com",
    "wof:name":"Pacific Teaze",
    "wof:placetype":"venue"
},
  "geometry": {"coordinates":[-118.587738,34.249969],"type":"Point"}
}