{
  "type": "Feature",
  "properties": {
    "iso:country":"US",
    "sg:address":"590 Magnolia Ave",
    "sg:city":"Larkspur",
    "sg:classifiers":[
        {
            "category":"Retail",
            "subcategory":"Laundry & Dry Cleaning",
            "type":"Services"
        }
    ],
    "sg:phone":"+1 415 927 0560",
    "sg:postcode":"94939",
    "sg:province":"CA",
    "sg:tags":[
        "cleaners"
    ],
    "wof:name":"Larkspur Cleaners",
    "wof:placetype":"venue"
},
  "geometry": {"coordinates":[-122.534739,37.937197],"type":"Point"}
}