{
  "type": "Feature",
  "properties": {
    "iso:country":"US",
    "sg:address":"5235 Mission Oaks Blvd #229",
    "sg:city":"Camarillo",
    "sg:classifiers":[
        {
            "category":"Real Estate",
            "subcategory":"Real Estate Services",
            "type":"Services"
        }
    ],
    "sg:phone":"+1 805 388 5507",
    "sg:postcode":"93012",
    "sg:province":"CA",
    "sg:website":"appraiserone.com",
    "wof:name":"Appraiser One Real Estate Network",
    "wof:placetype":"venue"
},
  "geometry": {"coordinates":[-119.000021,34.227731],"type":"Point"}
}