{
  "type": "Feature",
  "properties": {
    "addr:full":"309 Pimlico Dr Walnut Creek CA 94597",
    "addr:housenumber":"309",
    "addr:postcode":"94597",
    "addr:street":"Pimlico Dr",
    "iso:country":"US",
    "sg:address":"309 Pimlico Dr",
    "sg:city":"Walnut Creek",
    "sg:classifiers":[
        {
            "category":"Personal",
            "subcategory":"Beauty Salon",
            "type":"Services"
        }
    ],
    "sg:phone":"+1 925 945 1604",
    "sg:postcode":"94597",
    "sg:province":"CA",
    "sg:tags":[
        "consultant",
        "image",
        "cosmetic"
    ],
    "wof:name":"Color & Design",
    "wof:placetype":"venue"
},
  "geometry": {"coordinates":[-122.061876,37.913044],"type":"Point"}
}