{
  "type": "Feature",
  "properties": {
    "addr:full":"11801 Santa Monica Blvd Los Angeles CA 90025",
    "addr:housenumber":"11801",
    "addr:postcode":"90025",
    "addr:street":"Santa Monica Blvd",
    "iso:country":"US",
    "sg:address":"11801 Santa Monica Blvd",
    "sg:city":"Los Angeles",
    "sg:classifiers":[
        {
            "category":"Building & Trades",
            "subcategory":"Equipment Rental",
            "type":"Services"
        }
    ],
    "sg:phone":"+1 310 481 0701",
    "sg:postcode":"90025",
    "sg:province":"CA",
    "sg:tags":[
        "leasing"
    ],
    "wof:name":"Autostar Leasing",
    "wof:placetype":"venue"
},
  "geometry": {"coordinates":[-118.45918,34.042373],"type":"Point"}
}