{
  "type": "Feature",
  "properties": {
    "addr:full":"5820 Shellmound St Emeryville CA 94608",
    "addr:housenumber":"5820",
    "addr:postcode":"94608",
    "addr:street":"Shellmound St",
    "iso:country":"US",
    "sg:address":"5820 Shellmound St",
    "sg:city":"Emeryville",
    "sg:classifiers":[
        {
            "category":"Travel",
            "subcategory":"Travel Agent",
            "type":"Entertainment"
        }
    ],
    "sg:phone":"+1 510 652 7827",
    "sg:postcode":"94608",
    "sg:province":"CA",
    "sg:tags":[
        "agency"
    ],
    "wof:name":"American Express",
    "wof:placetype":"venue"
},
  "geometry": {"coordinates":[-122.293282,37.838885],"type":"Point"}
}