{
  "type": "Feature",
  "properties": {
    "iso:country":"US",
    "sg:address":"22331 el Toro Rd",
    "sg:city":"Lake Forest",
    "sg:classifiers":[
        {
            "category":"Restaurant",
            "type":"Food & Drink"
        }
    ],
    "sg:phone":"+1 949 380 7808",
    "sg:postcode":"92630",
    "sg:province":"CA",
    "sg:tags":[
        "shop",
        "coffee"
    ],
    "sg:website":"www.starbucks.com",
    "wof:name":"Starbucks",
    "wof:placetype":"venue"
},
  "geometry": {"coordinates":[-117.62729299999999,33.671603],"type":"Point"}
}