{
  "type": "Feature",
  "properties": {
    "iso:country":"US",
    "sg:address":"7548 Sepulveda Blvd",
    "sg:city":"Van Nuys",
    "sg:classifiers":[
        {
            "category":"Travel",
            "subcategory":"Travel Agent",
            "type":"Entertainment"
        }
    ],
    "sg:phone":"+1 818 902 5560",
    "sg:postcode":"91405",
    "sg:province":"CA",
    "sg:tags":[
        "agency",
        "bureau"
    ],
    "wof:name":"Festival Travel & Tour",
    "wof:placetype":"venue"
},
  "geometry": {"coordinates":[-118.46612399999999,34.208205],"type":"Point"}
}