{
  "type": "Feature",
  "properties": {
    "iso:country":"US",
    "sg:address":"3949 Foothill Blvd",
    "sg:city":"La Crescenta",
    "sg:classifiers":[
        {
            "category":"Manufacturing",
            "subcategory":"Metals",
            "type":"Manufacturing & Wholesale Goods"
        }
    ],
    "sg:phone":"+1 818 248 5774",
    "sg:postcode":"91214",
    "sg:province":"CA",
    "sg:tags":[
        "window",
        "door",
        "screen",
        "mfg"
    ],
    "wof:name":"Foothill Window & Screen Co",
    "wof:placetype":"venue"
},
  "geometry": {"coordinates":[-118.265109,34.239777],"type":"Point"}
}