{
  "type": "Feature",
  "properties": {
    "iso:country":"US",
    "sg:address":"570 N Garey Ave",
    "sg:city":"Pomona",
    "sg:classifiers":[
        {
            "category":"Retail",
            "subcategory":"Funeral Services",
            "type":"Services"
        }
    ],
    "sg:phone":"+1 909 622 1217",
    "sg:postcode":"91767",
    "sg:province":"CA",
    "sg:tags":[
        "director"
    ],
    "wof:name":"Todd Memorial Chapel",
    "wof:placetype":"venue"
},
  "geometry": {"coordinates":[-117.750254,34.062699],"type":"Point"}
}