{
  "type": "Feature",
  "properties": {
    "addr:full":"8391 Beverly Blvd Los Angeles CA 90048",
    "addr:housenumber":"8391",
    "addr:postcode":"90048",
    "addr:street":"Beverly Blvd",
    "iso:country":"US",
    "sg:address":"8391 Beverly Blvd",
    "sg:city":"Los Angeles",
    "sg:classifiers":[
        {
            "category":"Home & Garden",
            "subcategory":"Carpets & Floor Coverings",
            "type":"Retail Goods"
        }
    ],
    "sg:phone":"+1 949 496 3528",
    "sg:postcode":"90048",
    "sg:province":"CA",
    "sg:tags":[
        "flooring"
    ],
    "sg:website":"covaltleveling.com",
    "wof:name":"Covalt Floor Leveling",
    "wof:placetype":"venue"
},
  "geometry": {"coordinates":[-118.374188,34.076035],"type":"Point"}
}