{
  "type": "Feature",
  "properties": {
    "iso:country":"US",
    "sg:address":"200 W Church St",
    "sg:city":"Santa Maria",
    "sg:classifiers":[
        {
            "category":"Building & Trades",
            "subcategory":"Plumbing",
            "type":"Services"
        }
    ],
    "sg:phone":"+1 805 346 1725",
    "sg:postcode":"93458",
    "sg:province":"CA",
    "sg:tags":[
        "merchandise"
    ],
    "wof:name":"Valley Plumbing & Heating",
    "wof:placetype":"venue"
},
  "geometry": {"coordinates":[-120.437423,34.95203],"type":"Point"}
}