{
  "type": "Feature",
  "properties": {
    "addr:full":"1533 California Cir Milpitas CA 95035",
    "addr:housenumber":"1533",
    "addr:postcode":"95035",
    "addr:street":"California Cir",
    "iso:country":"US",
    "sg:address":"1533 California Cir",
    "sg:city":"Milpitas",
    "sg:classifiers":[
        {
            "category":"Professional",
            "type":"Services"
        }
    ],
    "sg:phone":"+1 408 935 6000",
    "sg:postcode":"95035",
    "sg:province":"CA",
    "sg:tags":[
        "establishment"
    ],
    "wof:name":"Toolwire Inc",
    "wof:placetype":"venue"
},
  "geometry": {"coordinates":[-121.919247,37.447625],"type":"Point"}
}