{
  "type": "Feature",
  "properties": {
    "addr:full":"2519 W Daphne Pl Fullerton CA 92833",
    "addr:housenumber":"2519",
    "addr:postcode":"92833",
    "addr:street":"W Daphne Pl",
    "iso:country":"US",
    "sg:address":"2519 W Daphne Pl",
    "sg:city":"Fullerton",
    "sg:classifiers":[
        {
            "category":"Professional",
            "type":"Services"
        }
    ],
    "sg:phone":"+1 714 447 8485",
    "sg:postcode":"92833",
    "sg:province":"CA",
    "wof:name":"Youngs Socks",
    "wof:placetype":"venue"
},
  "geometry": {"coordinates":[-117.96789699999999,33.886222],"type":"Point"}
}