{
  "type": "Feature",
  "properties": {
    "iso:country":"US",
    "sg:address":"5745 Arbor Vitae St",
    "sg:city":"Los Angeles",
    "sg:classifiers":[
        {
            "category":"Freight",
            "type":"Transportation"
        }
    ],
    "sg:phone":"+1 310 410 0988",
    "sg:postcode":"90045",
    "sg:province":"CA",
    "sg:tags":[
        "logistics",
        "forwarder",
        "global",
        "provider"
    ],
    "wof:name":"Wings Logistics California",
    "wof:placetype":"venue"
},
  "geometry": {"coordinates":[-118.38470100000001,33.952713],"type":"Point"}
}