{
  "type": "Feature",
  "properties": {
    "addr:full":"254 E 11th St San Bernardino CA 92410",
    "addr:housenumber":"254",
    "addr:postcode":"92410",
    "addr:street":"E 11Th St",
    "iso:country":"US",
    "sg:address":"254 E 11th St",
    "sg:city":"San Bernardino",
    "sg:classifiers":[
        {
            "category":"Shopping",
            "type":"Retail Goods"
        }
    ],
    "sg:phone":"+1 909 889 1981",
    "sg:postcode":"92410",
    "sg:province":"CA",
    "sg:tags":[
        "merchandise"
    ],
    "wof:name":"D & S Arts & Crafts",
    "wof:placetype":"venue"
},
  "geometry": {"coordinates":[-117.279602,34.119593],"type":"Point"}
}