{
  "type": "Feature",
  "properties": {
    "iso:country":"US",
    "sg:address":"3017 Summit St",
    "sg:city":"Oakland",
    "sg:classifiers":[
        {
            "category":"Health Services",
            "subcategory":"Doctor",
            "type":"Services"
        }
    ],
    "sg:phone":"+1 510 465 2759",
    "sg:postcode":"94609",
    "sg:province":"CA",
    "wof:name":"Cangello Vincent W MD",
    "wof:placetype":"venue"
},
  "geometry": {"coordinates":[-122.264999,37.819099],"type":"Point"}
}