{
  "type": "Feature",
  "properties": {
    "addr:full":"7519 Topeka Dr Reseda CA 91335",
    "addr:housenumber":"7519",
    "addr:postcode":"91335",
    "addr:street":"Topeka Dr",
    "iso:country":"US",
    "sg:address":"7519 Topeka Dr",
    "sg:city":"Reseda",
    "sg:classifiers":[
        {
            "category":"Professional",
            "subcategory":"Engineering",
            "type":"Services"
        }
    ],
    "sg:phone":"+1 818 609 0178",
    "sg:postcode":"91335",
    "sg:province":"CA",
    "sg:tags":[
        "engineer",
        "mechanical"
    ],
    "sg:website":"www.diaseng.com",
    "wof:name":"Scan Engineering Inc",
    "wof:placetype":"venue"
},
  "geometry": {"coordinates":[-118.54588699999999,34.2067],"type":"Point"}
}