{
  "type": "Feature",
  "properties": {
    "iso:country":"US",
    "sg:address":"2822 Cebu Ct",
    "sg:city":"Carlsbad",
    "sg:classifiers":[
        {
            "category":"Building & Trades",
            "subcategory":"Landscaping Services",
            "type":"Services"
        }
    ],
    "sg:phone":"+1 760 271 7526",
    "sg:postcode":"92009",
    "sg:province":"CA",
    "sg:tags":[
        "designer",
        "landscape"
    ],
    "wof:name":"A Design For Outdoor Living",
    "wof:placetype":"venue"
},
  "geometry": {"coordinates":[-117.24361,33.10674],"type":"Point"}
}