{
  "type": "Feature",
  "properties": {
    "iso:country":"US",
    "sg:address":"1537 Pacific Ave",
    "sg:city":"Santa Cruz",
    "sg:classifiers":[
        {
            "category":"Shopping",
            "type":"Retail Goods"
        }
    ],
    "sg:phone":"+1 831 688 1836",
    "sg:postcode":"95060",
    "sg:province":"CA",
    "sg:tags":[
        "candle"
    ],
    "wof:name":"Candle Store",
    "wof:placetype":"venue"
},
  "geometry": {"coordinates":[-122.026913,36.976332],"type":"Point"}
}