{
  "type": "Feature",
  "properties": {
    "addr:full":"16633 Ventura Blvd Encino CA 91436",
    "addr:housenumber":"16633",
    "addr:postcode":"91436",
    "addr:street":"Ventura Blvd",
    "iso:country":"US",
    "sg:address":"16633 Ventura Blvd",
    "sg:city":"Encino",
    "sg:classifiers":[
        {
            "category":"Professional",
            "type":"Services"
        }
    ],
    "sg:phone":"+1 818 907 3220",
    "sg:postcode":"91436",
    "sg:province":"CA",
    "wof:name":"Sue Bendavid-Arbiv",
    "wof:placetype":"venue"
},
  "geometry": {"coordinates":[-118.494885,34.15798],"type":"Point"}
}