{
  "type": "Feature",
  "properties": {
    "iso:country":"US",
    "sg:address":"7442 Talbert Avenue",
    "sg:city":"Huntington Beach",
    "sg:classifiers":[
        {
            "category":"Arts & Performance",
            "subcategory":"Music",
            "type":"Entertainment"
        }
    ],
    "sg:phone":"+1 714 698 8250",
    "sg:postcode":"92648",
    "sg:province":"CA",
    "sg:tags":[
        "dj"
    ],
    "sg:website":"www.fbncorp.com",
    "wof:name":"Fbn Audio Visual Services",
    "wof:placetype":"venue"
},
  "geometry": {"coordinates":[-117.998323,33.701038],"type":"Point"}
}