{
  "type": "Feature",
  "properties": {
    "iso:country":"US",
    "sg:address":"527 W Dunton Ave",
    "sg:city":"Orange",
    "sg:classifiers":[
        {
            "category":"Manufacturing",
            "subcategory":"Metals",
            "type":"Manufacturing & Wholesale Goods"
        }
    ],
    "sg:phone":"+1 714 272 4355",
    "sg:postcode":"92865",
    "sg:province":"CA",
    "sg:tags":[
        "steel",
        "distributor",
        "mill",
        "warehouse"
    ],
    "wof:name":"Steel Tree Fabrications",
    "wof:placetype":"venue"
},
  "geometry": {"coordinates":[-117.857788,33.834452],"type":"Point"}
}