{
  "type": "Feature",
  "properties": {
    "addr:full":"115 S School St Lodi CA 95240",
    "addr:housenumber":"115",
    "addr:postcode":"95240",
    "addr:street":"S School St",
    "iso:country":"US",
    "sg:address":"115 S School St",
    "sg:city":"Lodi",
    "sg:classifiers":[
        {
            "category":"Shopping",
            "subcategory":"Stationery & Office Supplies",
            "type":"Retail Goods"
        }
    ],
    "sg:phone":"+1 209 368 7101",
    "sg:postcode":"95240",
    "sg:province":"CA",
    "wof:name":"Office Staples",
    "wof:placetype":"venue"
},
  "geometry": {"coordinates":[-121.273899,38.131962],"type":"Point"}
}