{
  "type": "Feature",
  "properties": {
    "addr:full":"240 Folia Ct Santa Rosa CA 95409",
    "addr:housenumber":"240",
    "addr:postcode":"95409",
    "addr:street":"Folia Ct",
    "iso:country":"US",
    "sg:address":"240 Folia Ct",
    "sg:city":"Santa Rosa",
    "sg:classifiers":[
        {
            "category":"Building & Trades",
            "subcategory":"Construction",
            "type":"Services"
        }
    ],
    "sg:phone":"+1 707 538 5911",
    "sg:postcode":"95409",
    "sg:province":"CA",
    "sg:tags":[
        "handyman"
    ],
    "wof:name":"Good Works",
    "wof:placetype":"venue"
},
  "geometry": {"coordinates":[-122.661165,38.462425],"type":"Point"}
}