{
  "type": "Feature",
  "properties": {
    "iso:country":"US",
    "sg:address":"3433 Royal Rd",
    "sg:city":"Vista",
    "sg:classifiers":[
        {
            "category":"Building & Trades",
            "subcategory":"Electrical",
            "type":"Services"
        }
    ],
    "sg:phone":"+1 619 851 2141",
    "sg:postcode":"92084",
    "sg:province":"CA",
    "sg:tags":[
        "electrician"
    ],
    "wof:name":"Nova Systems",
    "wof:placetype":"venue"
},
  "geometry": {"coordinates":[-117.18501999999999,33.193912],"type":"Point"}
}