{
  "type": "Feature",
  "properties": {
    "iso:country":"US",
    "sg:address":"638 25th St",
    "sg:city":"Richmond",
    "sg:classifiers":[
        {
            "category":"Restaurant",
            "type":"Food & Drink"
        }
    ],
    "sg:phone":"+1 510 234 6143",
    "sg:postcode":"94804",
    "sg:province":"CA",
    "sg:tags":[
        "eating"
    ],
    "wof:name":"Jack Rabbit Caterers & Event P",
    "wof:placetype":"venue"
},
  "geometry": {"coordinates":[-122.344156,37.940756],"type":"Point"}
}