{
  "type": "Feature",
  "properties": {
    "iso:country":"US",
    "sg:address":"5624 Sunfish Ct",
    "sg:city":"Discovery Bay",
    "sg:classifiers":[
        {
            "category":"Shopping",
            "subcategory":"Clothing, Apparel, & Fashions",
            "type":"Retail Goods"
        }
    ],
    "sg:phone":"+1 925 240 9791",
    "sg:postcode":"94505",
    "sg:province":"CA",
    "wof:name":"REK Wholesale Designs",
    "wof:placetype":"venue"
},
  "geometry": {"coordinates":[-121.592376,37.907853],"type":"Point"}
}