{
  "type": "Feature",
  "properties": {
    "iso:country":"US",
    "sg:address":"1459 W Olive Ave",
    "sg:city":"Fresno",
    "sg:classifiers":[
        {
            "category":"Autos & Motor Vehicles",
            "subcategory":"Fuel & Gas Station",
            "type":"Retail Goods"
        }
    ],
    "sg:phone":"+1 559 237 8205",
    "sg:postcode":"93728",
    "sg:province":"CA",
    "sg:tags":[
        "oil"
    ],
    "wof:name":"Parkside Chevron Food Mart",
    "wof:placetype":"venue"
},
  "geometry": {"coordinates":[-119.82845500000001,36.757384],"type":"Point"}
}