{
  "type": "Feature",
  "properties": {
    "iso:country":"US",
    "sg:address":"434 S Grand Ave",
    "sg:city":"Los Angeles",
    "sg:classifiers":[
        {
            "category":"Shopping",
            "subcategory":"Clothing, Apparel, & Fashions",
            "type":"Retail Goods"
        }
    ],
    "sg:phone":"+1 213 622 5114",
    "sg:postcode":"90071",
    "sg:province":"CA",
    "sg:tags":[
        "clothing",
        "women's"
    ],
    "wof:name":"Oxygen Paris",
    "wof:placetype":"venue"
},
  "geometry": {"coordinates":[-118.252934,34.051066],"type":"Point"}
}