{
  "type": "Feature",
  "properties": {
    "iso:country":"US",
    "sg:address":"15760 Ventura Blvd",
    "sg:city":"Encino",
    "sg:classifiers":[
        {
            "category":"Arts & Performance",
            "subcategory":"Theater",
            "type":"Entertainment"
        }
    ],
    "sg:phone":"+1 818 905 3295",
    "sg:postcode":"91436",
    "sg:province":"CA",
    "sg:tags":[
        "talent",
        "agency",
        "casting"
    ],
    "wof:name":"Reigeiz Inc",
    "wof:placetype":"venue"
},
  "geometry": {"coordinates":[-118.475694,34.155168],"type":"Point"}
}