{
  "type": "Feature",
  "properties": {
    "iso:country":"US",
    "sg:address":"1605 Oak Park Blvd",
    "sg:city":"Pleasant Hill",
    "sg:classifiers":[
        {
            "category":"Professional",
            "subcategory":"Management & Consulting",
            "type":"Services"
        }
    ],
    "sg:phone":"+1 925 932 5444",
    "sg:postcode":"94523",
    "sg:province":"CA",
    "sg:tags":[
        "party",
        "planning"
    ],
    "wof:name":"C J's Freelance Design",
    "wof:placetype":"venue"
},
  "geometry": {"coordinates":[-122.06353,37.932945],"type":"Point"}
}