{
  "type": "Feature",
  "properties": {
    "iso:country":"US",
    "sg:address":"3164 Loomis Rd",
    "sg:city":"Stockton",
    "sg:classifiers":[
        {
            "category":"Utilities",
            "subcategory":"Refuse",
            "type":"Services"
        }
    ],
    "sg:phone":"+1 209 933 9640",
    "sg:postcode":"95205",
    "sg:province":"CA",
    "sg:tags":[
        "system"
    ],
    "wof:name":"Shamrock Recycling",
    "wof:placetype":"venue"
},
  "geometry": {"coordinates":[-121.239886,37.929539],"type":"Point"}
}