{
  "type": "Feature",
  "properties": {
    "addr:full":"2321 Stevens Creek Blvd San Jose CA 95128",
    "addr:housenumber":"2321",
    "addr:postcode":"95128",
    "addr:street":"Stevens Creek Blvd",
    "iso:country":"US",
    "sg:address":"2321 Stevens Creek Blvd",
    "sg:city":"San Jose",
    "sg:classifiers":[
        {
            "category":"Shopping",
            "subcategory":"Florist",
            "type":"Retail Goods"
        }
    ],
    "sg:phone":"+1 408 280 0504",
    "sg:postcode":"95128",
    "sg:province":"CA",
    "sg:website":"www.flowerexpress.net",
    "wof:name":"Greenhouse Flowers & Plants",
    "wof:placetype":"venue"
},
  "geometry": {"coordinates":[-121.934848,37.323295],"type":"Point"}
}