{
  "type": "Feature",
  "properties": {
    "iso:country":"US",
    "sg:address":"11440 Sunrise Gold Cir",
    "sg:city":"Rancho Cordova",
    "sg:classifiers":[
        {
            "category":"Building & Trades",
            "subcategory":"Construction",
            "type":"Services"
        },
        {
            "category":"Home & Garden",
            "subcategory":"Furniture",
            "type":"Retail Goods"
        }
    ],
    "sg:phone":"+1 916 638 2903",
    "sg:postcode":"95742",
    "sg:province":"CA",
    "sg:tags":[
        "nonresidential",
        "i",
        "work",
        "custom",
        "cabinet",
        "maker",
        "tenant"
    ],
    "wof:name":"Woodworks",
    "wof:placetype":"venue"
},
  "geometry": {"coordinates":[-121.263695,38.597845],"type":"Point"}
}