{
  "type": "Feature",
  "properties": {
    "addr:full":"1137 25th St San Diego CA 92102",
    "addr:housenumber":"1137",
    "addr:postcode":"92102",
    "addr:street":"25Th St",
    "iso:country":"US",
    "sg:address":"1137 25th St",
    "sg:city":"San Diego",
    "sg:classifiers":[
        {
            "category":"Restaurant",
            "type":"Food & Drink"
        }
    ],
    "sg:phone":"+1 619 233 3309",
    "sg:postcode":"92102",
    "sg:province":"CA",
    "sg:tags":[
        "pizza"
    ],
    "sg:website":"www.pizzerialuigi.com",
    "wof:name":"Pizzeria Luigi",
    "wof:placetype":"venue"
},
  "geometry": {"coordinates":[-117.140289,32.717478],"type":"Point"}
}