{
  "type": "Feature",
  "properties": {
    "iso:country":"US",
    "sg:address":"825 W Henderson Ave",
    "sg:city":"Porterville",
    "sg:classifiers":[
        {
            "category":"Shopping",
            "subcategory":"Department Store",
            "type":"Retail Goods"
        },
        {
            "category":"Shopping",
            "subcategory":"Discount & Variety Stores",
            "type":"Retail Goods"
        }
    ],
    "sg:phone":"+1 559 789 9912",
    "sg:postcode":"93257",
    "sg:province":"CA",
    "sg:website":"http://www.bargainw.com",
    "wof:name":"99 Cents Only Stores",
    "wof:placetype":"venue"
},
  "geometry": {"coordinates":[-119.03515899999999,36.08045],"type":"Point"}
}