{
  "type": "Feature",
  "properties": {
    "addr:full":"4352 Wheatland Rd Wheatland CA 95692",
    "addr:housenumber":"4352",
    "addr:postcode":"95692",
    "addr:street":"Wheatland Rd",
    "iso:country":"US",
    "sg:address":"4352 Wheatland Rd",
    "sg:city":"Wheatland",
    "sg:classifiers":[
        {
            "category":"Wholesale",
            "subcategory":"Groceries",
            "type":"Manufacturing & Wholesale Goods"
        }
    ],
    "sg:phone":"+1 530 633 0306",
    "sg:postcode":"95692",
    "sg:province":"CA",
    "sg:tags":[
        "frozen",
        "foods-wholesale"
    ],
    "wof:name":"Gilbert Orchards",
    "wof:placetype":"venue"
},
  "geometry": {"coordinates":[-121.45544700000001,38.998591],"type":"Point"}
}