{
  "type": "Feature",
  "properties": {
    "iso:country":"US",
    "sg:address":"3484 Pinewood Dr",
    "sg:city":"Hayward",
    "sg:classifiers":[
        {
            "category":"Professional",
            "type":"Services"
        }
    ],
    "sg:phone":"+1 510 728 1912",
    "sg:postcode":"94542",
    "sg:province":"CA",
    "wof:name":"Holt & Arvie Inc",
    "wof:placetype":"venue"
},
  "geometry": {"coordinates":[-122.031221,37.651023],"type":"Point"}
}