{
  "type": "Feature",
  "properties": {
    "iso:country":"US",
    "sg:address":"8947 Sunland Blvd",
    "sg:city":"Sun Valley",
    "sg:classifiers":[
        {
            "category":"Restaurant",
            "type":"Food & Drink"
        }
    ],
    "sg:menulink":"http://www.allmenus.com/ca/san-fernando-valley/64782-papa-johns-pizza/menu/",
    "sg:phone":"+1 818 767 9888",
    "sg:postcode":"91352",
    "sg:province":"CA",
    "sg:tags":[
        "american",
        "pizza"
    ],
    "wof:name":"Papa John's Pizza",
    "wof:placetype":"venue"
},
  "geometry": {"coordinates":[-118.366731,34.231513],"type":"Point"}
}