{
  "type": "Feature",
  "properties": {
    "iso:country":"US",
    "sg:address":"25124 Narbonne Avenue #204",
    "sg:city":"Lomita",
    "sg:classifiers":[
        {
            "category":"Personal",
            "subcategory":"Hair Removal",
            "type":"Services"
        },
        {
            "category":"Personal",
            "subcategory":"Skin Care",
            "type":"Services"
        }
    ],
    "sg:phone":"+1 310 882 1029",
    "sg:postcode":"90717",
    "sg:province":"CA",
    "sg:tags":[
        "laser"
    ],
    "sg:website":"www.sundayrose.biz",
    "wof:name":"Sunday Rose Electrolysis & Skin Care",
    "wof:placetype":"venue"
},
  "geometry": {"coordinates":[-118.31950999999999,33.796045],"type":"Point"}
}