{
  "type": "Feature",
  "properties": {
    "addr:full":"8431 Diane Ct Gilroy CA 95020",
    "addr:housenumber":"8431",
    "addr:postcode":"95020",
    "addr:street":"Diane Ct",
    "iso:country":"US",
    "sg:address":"8431 Diane Ct",
    "sg:city":"Gilroy",
    "sg:classifiers":[
        {
            "category":"Building & Trades",
            "subcategory":"Electrical",
            "type":"Services"
        }
    ],
    "sg:phone":"+1 408 846 9715",
    "sg:postcode":"95020",
    "sg:province":"CA",
    "sg:tags":[
        "electrical",
        "contractor"
    ],
    "wof:name":"Amdahl Corp",
    "wof:placetype":"venue"
},
  "geometry": {"coordinates":[-121.581326,37.018654],"type":"Point"}
}