{
  "type": "Feature",
  "properties": {
    "addr:full":"3723 Balboa Ter San Diego CA 92117",
    "addr:housenumber":"3723",
    "addr:postcode":"92117",
    "addr:street":"Balboa Ter",
    "iso:country":"US",
    "sg:address":"3723 Balboa Ter",
    "sg:city":"San Diego",
    "sg:classifiers":[
        {
            "category":"Shopping",
            "type":"Retail Goods"
        }
    ],
    "sg:phone":"+1 858 483 2273",
    "sg:postcode":"92117",
    "sg:province":"CA",
    "sg:tags":[
        "pet",
        "shop"
    ],
    "wof:name":"Love's Pet Care",
    "wof:placetype":"venue"
},
  "geometry": {"coordinates":[-117.208051,32.80907],"type":"Point"}
}