{
  "type": "Feature",
  "properties": {
    "addr:full":"940 W Industrial St Azusa CA 91702",
    "addr:housenumber":"940",
    "addr:postcode":"91702",
    "addr:street":"W Industrial St",
    "iso:country":"US",
    "sg:address":"940 W Industrial St",
    "sg:city":"Azusa",
    "sg:classifiers":[
        {
            "category":"Home & Garden",
            "subcategory":"Furniture",
            "type":"Retail Goods"
        }
    ],
    "sg:phone":"+1 626 815 0828",
    "sg:postcode":"91702",
    "sg:province":"CA",
    "sg:tags":[
        "store"
    ],
    "wof:name":"California's Furniture Frame",
    "wof:placetype":"venue"
},
  "geometry": {"coordinates":[-117.919691,34.134531],"type":"Point"}
}