{
  "type": "Feature",
  "properties": {
    "iso:country":"US",
    "sg:address":"22048 Sherman Way",
    "sg:city":"Canoga Park",
    "sg:classifiers":[
        {
            "category":"Professional",
            "subcategory":"Lawyer & Legal Services",
            "type":"Services"
        }
    ],
    "sg:phone":"+1 818 781 8400",
    "sg:postcode":"91303",
    "sg:province":"CA",
    "wof:name":"Legal Plan the",
    "wof:placetype":"venue"
},
  "geometry": {"coordinates":[-118.60700199999999,34.201099],"type":"Point"}
}