{
  "type": "Feature",
  "properties": {
    "addr:full":"6801 Deerwood Dr Riverside CA 92506",
    "addr:housenumber":"6801",
    "addr:postcode":"92506",
    "addr:street":"Deerwood Dr",
    "iso:country":"US",
    "sg:address":"6801 Deerwood Dr",
    "sg:city":"Riverside",
    "sg:classifiers":[
        {
            "category":"Professional",
            "subcategory":"Accounting & Tax Preparation",
            "type":"Services"
        }
    ],
    "sg:phone":"+1 951 789 8255",
    "sg:postcode":"92506",
    "sg:province":"CA",
    "sg:tags":[
        "return",
        "filing"
    ],
    "wof:name":"R Y & Assoc",
    "wof:placetype":"venue"
},
  "geometry": {"coordinates":[-117.32221199999999,33.92789],"type":"Point"}
}