{
  "type": "Feature",
  "properties": {
    "addr:full":"1397 S Diamond Bar Blvd Diamond Bar CA 91765",
    "addr:housenumber":"1397",
    "addr:postcode":"91765",
    "addr:street":"S;Blvd",
    "iso:country":"US",
    "sg:address":"1397 S Diamond Bar Blvd",
    "sg:city":"Diamond Bar",
    "sg:classifiers":[
        {
            "category":"Retail",
            "subcategory":"Laundry & Dry Cleaning",
            "type":"Services"
        }
    ],
    "sg:phone":"+1 909 861 0052",
    "sg:postcode":"91765",
    "sg:province":"CA",
    "sg:tags":[
        "cleaners"
    ],
    "wof:name":"Express Plus Cleaners",
    "wof:placetype":"venue"
},
  "geometry": {"coordinates":[-117.815676,33.993611],"type":"Point"}
}