{
  "type": "Feature",
  "properties": {
    "addr:full":"1056 S Seaward Ave Ventura CA 93001",
    "addr:housenumber":"1056",
    "addr:postcode":"93001",
    "addr:street":"S Seaward Ave",
    "iso:country":"US",
    "sg:address":"1056 S Seaward Ave",
    "sg:city":"Ventura",
    "sg:classifiers":[
        {
            "category":"Personal",
            "subcategory":"Beauty Salon",
            "type":"Services"
        }
    ],
    "sg:phone":"+1 805 643 7245",
    "sg:postcode":"93001",
    "sg:province":"CA",
    "wof:name":"Pierpont Beauty Salon",
    "wof:placetype":"venue"
},
  "geometry": {"coordinates":[-119.27323800000001,34.263469],"type":"Point"}
}