{
  "type": "Feature",
  "properties": {
    "iso:country":"US",
    "sg:address":"617 Mountain View Ave",
    "sg:city":"Belmont",
    "sg:classifiers":[
        {
            "category":"Wholesale",
            "subcategory":"Hardware",
            "type":"Manufacturing & Wholesale Goods"
        }
    ],
    "sg:phone":"+1 650 594 2112",
    "sg:postcode":"94002",
    "sg:province":"CA",
    "sg:tags":[
        "equipment",
        "gas"
    ],
    "wof:name":"Charles Burke",
    "wof:placetype":"venue"
},
  "geometry": {"coordinates":[-122.281863,37.527241],"type":"Point"}
}