{
  "type": "Feature",
  "properties": {
    "iso:country":"US",
    "sg:address":"791 Overhill Dr",
    "sg:city":"Hayward",
    "sg:classifiers":[
        {
            "category":"Building & Trades",
            "subcategory":"Landscaping Services",
            "type":"Services"
        }
    ],
    "sg:phone":"+1 510 537 2465",
    "sg:postcode":"94544",
    "sg:province":"CA",
    "wof:name":"Del Sol Gardens Gardening Svc",
    "wof:placetype":"venue"
},
  "geometry": {"coordinates":[-122.046305,37.633152],"type":"Point"}
}