{
  "type": "Feature",
  "properties": {
    "addr:full":"14 Oak Springs Dr San Anselmo CA 94960",
    "addr:housenumber":"14",
    "addr:postcode":"94960",
    "addr:street":"Oak Springs Dr",
    "iso:country":"US",
    "sg:address":"14 Oak Springs Dr",
    "sg:city":"San Anselmo",
    "sg:classifiers":[
        {
            "category":"Banks & Credit Unions",
            "subcategory":"Investment Brokerage",
            "type":"Services"
        }
    ],
    "sg:phone":"+1 415 459 1969",
    "sg:postcode":"94960",
    "sg:province":"CA",
    "sg:tags":[
        "consultant",
        "financing"
    ],
    "wof:name":"Hickman & Assoc",
    "wof:placetype":"venue"
},
  "geometry": {"coordinates":[-122.581462,37.997821],"type":"Point"}
}