{
  "type": "Feature",
  "properties": {
    "addr:full":"28527 Santa Catarina Rd Santa Clarita CA 91350",
    "addr:housenumber":"28527",
    "addr:postcode":"91350",
    "addr:street":"Santa Catarina Rd",
    "iso:country":"US",
    "sg:address":"28527 Santa Catarina Rd",
    "sg:city":"Santa Clarita",
    "sg:classifiers":[
        {
            "category":"Professional",
            "subcategory":"Management & Consulting",
            "type":"Services"
        }
    ],
    "sg:phone":"+1 661 513 0082",
    "sg:postcode":"91350",
    "sg:province":"CA",
    "wof:name":"W L Homes LLC",
    "wof:placetype":"venue"
},
  "geometry": {"coordinates":[-118.483542,34.447481],"type":"Point"}
}