{
  "type": "Feature",
  "properties": {
    "addr:full":"313 N Euclid St Fullerton CA 92832",
    "addr:housenumber":"313",
    "addr:postcode":"92832",
    "addr:street":"N Euclid St",
    "iso:country":"US",
    "sg:address":"313 N Euclid St",
    "sg:city":"Fullerton",
    "sg:classifiers":[
        {
            "category":"Personal",
            "subcategory":"Barber",
            "type":"Services"
        }
    ],
    "sg:phone":"+1 714 773 1047",
    "sg:postcode":"92832",
    "sg:province":"CA",
    "wof:name":"Henry Janine",
    "wof:placetype":"venue"
},
  "geometry": {"coordinates":[-117.94214599999999,33.872373],"type":"Point"}
}