{
  "type": "Feature",
  "properties": {
    "addr:full":"10515 McFadden Ave #101 Garden Grove CA 92843",
    "addr:housenumber":"10515",
    "addr:postcode":"92843",
    "addr:street":"Mcfadden Ave # 101",
    "iso:country":"US",
    "sg:address":"10515 McFadden Ave #101",
    "sg:city":"Garden Grove",
    "sg:classifiers":[
        {
            "category":"Restaurant",
            "type":"Food & Drink"
        }
    ],
    "sg:phone":"+1 714 775 1330",
    "sg:postcode":"92843",
    "sg:province":"CA",
    "sg:tags":[
        "vietnamese"
    ],
    "wof:name":"Queen Egg Rolls Hongloan Food",
    "wof:placetype":"venue"
},
  "geometry": {"coordinates":[-117.945696,33.738252],"type":"Point"}
}