{
  "type": "Feature",
  "properties": {
    "addr:full":"1153 Bordeaux Dr Sunnyvale CA 94089",
    "addr:housenumber":"1153",
    "addr:postcode":"94089",
    "addr:street":"Bordeaux Dr",
    "iso:country":"US",
    "sg:address":"1153 Bordeaux Dr",
    "sg:city":"Sunnyvale",
    "sg:classifiers":[
        {
            "category":"Health Services",
            "subcategory":"Medical Lab",
            "type":"Services"
        }
    ],
    "sg:phone":"+1 408 747 0122",
    "sg:postcode":"94089",
    "sg:province":"CA",
    "sg:tags":[
        "laboratory"
    ],
    "wof:name":"Dencad",
    "wof:placetype":"venue"
},
  "geometry": {"coordinates":[-122.023518,37.408849],"type":"Point"}
}