{
  "type": "Feature",
  "properties": {
    "addr:full":"1386 E Valley Rd Santa Barbara CA 93108",
    "addr:housenumber":"1386",
    "addr:postcode":"93108",
    "addr:street":"E Valley Rd",
    "iso:country":"US",
    "sg:address":"1386 E Valley Rd",
    "sg:city":"Santa Barbara",
    "sg:classifiers":[
        {
            "category":"Professional",
            "subcategory":"Lawyer & Legal Services",
            "type":"Services"
        }
    ],
    "sg:phone":"+1 805 969 5033",
    "sg:postcode":"93108",
    "sg:province":"CA",
    "sg:tags":[
        "attorney"
    ],
    "wof:name":"Leland Crawford Jr",
    "wof:placetype":"venue"
},
  "geometry": {"coordinates":[-119.637148,34.436637],"type":"Point"}
}