{
  "type": "Feature",
  "properties": {
    "iso:country":"US",
    "sg:address":"Near Coast Guard Island 2311 Embarcadero",
    "sg:city":"Oakland",
    "sg:classifiers":[
        {
            "category":"Park",
            "type":"Public Place"
        }
    ],
    "sg:postcode":"94620",
    "sg:province":"CA",
    "sg:website":"www.waterfrontaction.org/learn/p...",
    "wof:name":"Union Point Park",
    "wof:placetype":"venue"
},
  "geometry": {"coordinates":[-122.251064,37.788102],"type":"Point"}
}