{
  "type": "Feature",
  "properties": {
    "iso:country":"US",
    "sg:address":"20212 Redwood Rd",
    "sg:city":"Castro Valley",
    "sg:classifiers":[
        {
            "category":"Real Estate",
            "subcategory":"Real Estate Services",
            "type":"Services"
        }
    ],
    "sg:phone":"+1 510 538 0610",
    "sg:postcode":"94546",
    "sg:province":"CA",
    "sg:tags":[
        "company",
        "title"
    ],
    "wof:name":"Advance Title Research",
    "wof:placetype":"venue"
},
  "geometry": {"coordinates":[-122.07392,37.698312],"type":"Point"}
}