{
  "type": "Feature",
  "properties": {
    "addr:full":"33367 Auberry Rd Auberry CA 93602",
    "addr:postcode":"33367;93602",
    "addr:street":"Auberry Rd",
    "iso:country":"US",
    "sg:address":"33367 Auberry Rd",
    "sg:city":"Auberry",
    "sg:classifiers":[
        {
            "category":"Education",
            "subcategory":"School",
            "type":"Public Place"
        }
    ],
    "sg:phone":"+1 559 855 2442",
    "sg:postcode":"93602",
    "sg:province":"CA",
    "wof:name":"Auberry Elementary School",
    "wof:placetype":"venue"
},
  "geometry": {"coordinates":[-119.48535800000001,37.078404],"type":"Point"}
}