{
  "type": "Feature",
  "properties": {
    "iso:country":"US",
    "sg:address":"1522 W 7th St",
    "sg:city":"Los Angeles",
    "sg:classifiers":[
        {
            "category":"Retail",
            "subcategory":"Repair Shop",
            "type":"Services"
        }
    ],
    "sg:phone":"+1 213 989 1595",
    "sg:postcode":"90017",
    "sg:province":"CA",
    "sg:tags":[
        "refinishing",
        "furniture"
    ],
    "wof:name":"Oswaldo Designers",
    "wof:placetype":"venue"
},
  "geometry": {"coordinates":[-118.270846,34.053648],"type":"Point"}
}