{
  "type": "Feature",
  "properties": {
    "addr:full":"1678 W Broadway Anaheim CA 92802",
    "addr:housenumber":"1678",
    "addr:postcode":"92802",
    "addr:street":"W Broadway",
    "iso:country":"US",
    "sg:address":"1678 W Broadway",
    "sg:city":"Anaheim",
    "sg:classifiers":[
        {
            "category":"Professional",
            "subcategory":"Lawyer & Legal Services",
            "type":"Services"
        }
    ],
    "sg:phone":"+1 714 956 3732",
    "sg:postcode":"92802",
    "sg:province":"CA",
    "wof:name":"McCaffrey Roger Atty",
    "wof:placetype":"venue"
},
  "geometry": {"coordinates":[-117.941002,33.828899],"type":"Point"}
}