{
  "type": "Feature",
  "properties": {
    "addr:full":"1711 Bryden Ln Santa Rosa CA 95404",
    "addr:housenumber":"1711",
    "addr:postcode":"95404",
    "addr:street":"Bryden Ln",
    "iso:country":"US",
    "sg:address":"1711 Bryden Ln",
    "sg:city":"Santa Rosa",
    "sg:classifiers":[
        {
            "category":"Education",
            "subcategory":"School",
            "type":"Public Place"
        }
    ],
    "sg:phone":"+1 707 528 5482",
    "sg:postcode":"95404",
    "sg:province":"CA",
    "sg:tags":[
        "elementary"
    ],
    "wof:name":"Proctor Terrace Elementary",
    "wof:placetype":"venue"
},
  "geometry": {"coordinates":[-122.698598,38.451453],"type":"Point"}
}