{
  "type": "Feature",
  "properties": {
    "iso:country":"US",
    "sg:address":"123 Main St",
    "sg:city":"San Fransisco",
    "sg:classifiers":[
        {
            "category":"Professional",
            "subcategory":"Computer Services",
            "type":"Services"
        }
    ],
    "sg:phone":"+1 301 246 0055",
    "sg:postcode":"94103",
    "sg:province":"CA",
    "sg:tags":[
        "repair"
    ],
    "wof:name":"Rampage Home Computer Services",
    "wof:placetype":"venue"
},
  "geometry": {"coordinates":[-122.394367,37.791404],"type":"Point"}
}