{
  "type": "Feature",
  "properties": {
    "addr:full":"640 S Imperial Ave Calexico CA 92231",
    "addr:housenumber":"640",
    "addr:postcode":"92231",
    "addr:street":"S Imperial Ave",
    "iso:country":"US",
    "sg:address":"640 S Imperial Ave",
    "sg:city":"Calexico",
    "sg:classifiers":[
        {
            "category":"Utilities",
            "subcategory":"Mobile Phone",
            "type":"Services"
        },
        {
            "category":"Wholesale",
            "subcategory":"Electrical",
            "type":"Manufacturing & Wholesale Goods"
        }
    ],
    "sg:phone":"+1 760 357 9960",
    "sg:postcode":"92231",
    "sg:province":"CA",
    "sg:tags":[
        "communication",
        "equipment",
        "paging",
        "computer",
        "radio",
        "signaling"
    ],
    "wof:name":"Compucom",
    "wof:placetype":"venue"
},
  "geometry": {"coordinates":[-115.498656,32.671154],"type":"Point"}
}