{
  "type": "Feature",
  "properties": {
    "iso:country":"US",
    "sg:address":"1011 E Las Tunas Dr",
    "sg:city":"San Gabriel",
    "sg:classifiers":[
        {
            "category":"Insurance",
            "subcategory":"Health Insurance",
            "type":"Services"
        }
    ],
    "sg:phone":"+1 626 292 1998",
    "sg:postcode":"91776",
    "sg:province":"CA",
    "sg:tags":[
        "market"
    ],
    "sg:website":"www.ufreshcenter.com",
    "wof:name":"Ufresh Center",
    "wof:placetype":"venue"
},
  "geometry": {"coordinates":[-118.578138,34.10358],"type":"Point"}
}