{
  "type": "Feature",
  "properties": {
    "addr:full":"23761 Washington Ave Murrieta CA 92562",
    "addr:housenumber":"23761",
    "addr:postcode":"92562",
    "addr:street":"Washington Ave",
    "iso:country":"US",
    "sg:address":"23761 Washington Ave",
    "sg:city":"Murrieta",
    "sg:classifiers":[
        {
            "category":"Restaurant",
            "type":"Food & Drink"
        }
    ],
    "sg:menulink":"http://www.allmenus.com/ca/murrieta/171080-carls-jr/menu/",
    "sg:phone":"+1 951 894 4775",
    "sg:postcode":"92562",
    "sg:province":"CA",
    "sg:tags":[
        "burger",
        "american"
    ],
    "wof:name":"Carl's Jr.",
    "wof:placetype":"venue"
},
  "geometry": {"coordinates":[-117.23465400000001,33.572537],"type":"Point"}
}