{
  "type": "Feature",
  "properties": {
    "iso:country":"US",
    "sg:address":"2021 Ocean Ave",
    "sg:city":"Santa Monica",
    "sg:classifiers":[
        {
            "category":"Utilities",
            "subcategory":"Electric",
            "type":"Services"
        }
    ],
    "sg:phone":"+1 310 664 0656",
    "sg:postcode":"90405",
    "sg:province":"CA",
    "sg:tags":[
        "software"
    ],
    "wof:name":"Membership Systems",
    "wof:placetype":"venue"
},
  "geometry": {"coordinates":[-118.489789,34.005475],"type":"Point"}
}