{
  "type": "Feature",
  "properties": {
    "addr:full":"321 Browning St Upland CA 91784",
    "addr:housenumber":"321",
    "addr:postcode":"91784",
    "addr:street":"Browning St",
    "iso:country":"US",
    "sg:address":"321 Browning St",
    "sg:city":"Upland",
    "sg:classifiers":[
        {
            "category":"Health Services",
            "subcategory":"Doctor",
            "type":"Services"
        }
    ],
    "sg:phone":"+1 909 946 2277",
    "sg:postcode":"91784",
    "sg:province":"CA",
    "sg:tags":[
        "physician",
        "surgeon"
    ],
    "wof:name":"Ricardo J Nieva Inc",
    "wof:placetype":"venue"
},
  "geometry": {"coordinates":[-117.65536,34.149457],"type":"Point"}
}