{
  "type": "Feature",
  "properties": {
    "addr:full":"31 Rio Robles E San Jose CA 95134",
    "addr:housenumber":"31",
    "addr:postcode":"95134",
    "addr:street":"Rio Robles E",
    "iso:country":"US",
    "sg:address":"31 Rio Robles E",
    "sg:city":"San Jose",
    "sg:classifiers":[
        {
            "category":"Coffee & Tea",
            "type":"Food & Drink"
        }
    ],
    "sg:menulink":"http://www.allmenus.com/ca/san-jose/117218-starbucks-coffee/menu/",
    "sg:phone":"+1 408 435 9621",
    "sg:postcode":"95134",
    "sg:province":"CA",
    "sg:tags":[
        "american"
    ],
    "wof:name":"Starbucks Coffee",
    "wof:placetype":"venue"
},
  "geometry": {"coordinates":[-121.942097,37.406255],"type":"Point"}
}