{
  "type": "Feature",
  "properties": {
    "iso:country":"US",
    "sg:address":"711 Santa Clara Avenue",
    "sg:city":"Alameda",
    "sg:classifiers":[
        {
            "category":"Health Services",
            "subcategory":"Chiropractor",
            "type":"Services"
        }
    ],
    "sg:phone":"+1 510 523 5000",
    "sg:postcode":"94501",
    "sg:province":"CA",
    "sg:tags":[
        "chiropractic"
    ],
    "sg:website":"www.backtohealthalameda.com/",
    "wof:name":"Back To Health Chiropractic Center",
    "wof:placetype":"venue"
},
  "geometry": {"coordinates":[-122.275929,37.773777],"type":"Point"}
}