{
  "type": "Feature",
  "properties": {
    "iso:country":"US",
    "sg:address":"100 Montgomery St Suite 2100",
    "sg:city":"San Francisco",
    "sg:classifiers":[
        {
            "category":"Professional",
            "subcategory":"Lawyer & Legal Services",
            "type":"Services"
        }
    ],
    "sg:phone":"+1 415 296 0900",
    "sg:postcode":"94104",
    "sg:province":"CA",
    "sg:website":"www.sheppardlaw.com",
    "wof:name":"Juliana Pisani",
    "wof:placetype":"venue"
},
  "geometry": {"coordinates":[-122.402197,37.790041],"type":"Point"}
}