{
  "type": "Feature",
  "properties": {
    "addr:full":"30025 Alicia Pkwy Laguna Niguel CA 92677",
    "addr:housenumber":"30025",
    "addr:postcode":"92677",
    "addr:street":"Alicia Pkwy",
    "iso:country":"US",
    "sg:address":"30025 Alicia Pkwy",
    "sg:city":"Laguna Niguel",
    "sg:classifiers":[
        {
            "category":"Professional",
            "type":"Services"
        }
    ],
    "sg:phone":"+1 949 481 6326",
    "sg:postcode":"92677",
    "sg:province":"CA",
    "wof:name":"Ride In Style",
    "wof:placetype":"venue"
},
  "geometry": {"coordinates":[-117.716425,33.528196],"type":"Point"}
}