{
  "type": "Feature",
  "properties": {
    "addr:full":"15360 Mandan Rd Apple Valley CA 92307",
    "addr:housenumber":"15360",
    "addr:postcode":"92307",
    "addr:street":"Mandan Rd",
    "iso:country":"US",
    "sg:address":"15360 Mandan Rd",
    "sg:city":"Apple Valley",
    "sg:classifiers":[
        {
            "category":"Manufacturing",
            "subcategory":"Apparel",
            "type":"Manufacturing & Wholesale Goods"
        }
    ],
    "sg:phone":"+1 760 242 7109",
    "sg:postcode":"92307",
    "sg:province":"CA",
    "sg:tags":[
        "clothing"
    ],
    "wof:name":"Funky Productions",
    "wof:placetype":"venue"
},
  "geometry": {"coordinates":[-117.241568,34.531843],"type":"Point"}
}