{
  "type": "Feature",
  "properties": {
    "addr:full":"179 E 19th St Chico CA 95928",
    "addr:housenumber":"179",
    "addr:postcode":"95928",
    "addr:street":"E 19Th St",
    "iso:country":"US",
    "sg:address":"179 E 19th St",
    "sg:city":"Chico",
    "sg:classifiers":[
        {
            "category":"Restaurant",
            "type":"Food & Drink"
        }
    ],
    "sg:phone":"+1 530 345 7787",
    "sg:postcode":"95928",
    "sg:province":"CA",
    "sg:tags":[
        "eating"
    ],
    "wof:name":"Bacio Catering Co",
    "wof:placetype":"venue"
},
  "geometry": {"coordinates":[-121.824175,39.719876],"type":"Point"}
}