{
  "type": "Feature",
  "properties": {
    "addr:full":"29 Birch St Redwood City CA 94062",
    "addr:housenumber":"29",
    "addr:postcode":"94062",
    "addr:street":"Birch St",
    "iso:country":"US",
    "sg:address":"29 Birch St",
    "sg:city":"Redwood City",
    "sg:classifiers":[
        {
            "category":"Health Services",
            "subcategory":"Doctor",
            "type":"Services"
        }
    ],
    "sg:phone":"+1 650 368 6102",
    "sg:postcode":"94062",
    "sg:province":"CA",
    "sg:tags":[
        "dentist"
    ],
    "wof:name":"Gery P Sterling DDS",
    "wof:placetype":"venue"
},
  "geometry": {"coordinates":[-122.240089,37.48804],"type":"Point"}
}