{
  "type": "Feature",
  "properties": {
    "iso:country":"US",
    "sg:address":"1722 San Pablo Ave",
    "sg:city":"Berkeley",
    "sg:classifiers":[
        {
            "category":"Professional",
            "subcategory":"Lawyer & Legal Services",
            "type":"Services"
        }
    ],
    "sg:phone":"+1 510 528 4420",
    "sg:postcode":"94702",
    "sg:province":"CA",
    "sg:tags":[
        "attorney"
    ],
    "wof:name":"James L Lozenski Attorney",
    "wof:placetype":"venue"
},
  "geometry": {"coordinates":[-122.293057,37.871686],"type":"Point"}
}