{
  "type": "Feature",
  "properties": {
    "addr:full":"617 Manhattan Ave Hermosa Beach CA 90254",
    "addr:housenumber":"617",
    "addr:postcode":"90254",
    "addr:street":"Manhattan Ave",
    "iso:country":"US",
    "sg:address":"617 Manhattan Ave",
    "sg:city":"Hermosa Beach",
    "sg:classifiers":[
        {
            "category":"Retail",
            "subcategory":"Repair Shop",
            "type":"Services"
        }
    ],
    "sg:phone":"+1 310 376 2809",
    "sg:postcode":"90254",
    "sg:province":"CA",
    "sg:tags":[
        "bathtub",
        "sink",
        "refinishing"
    ],
    "wof:name":"Rainbow Tubs",
    "wof:placetype":"venue"
},
  "geometry": {"coordinates":[-118.39833400000001,33.859304],"type":"Point"}
}