{
  "type": "Feature",
  "properties": {
    "addr:full":"23881 Newhall Ranch Rd Valencia CA 91355",
    "addr:housenumber":"23881",
    "addr:postcode":"91355",
    "addr:street":"Newhall Ranch Rd",
    "iso:country":"US",
    "sg:address":"23881 Newhall Ranch Rd",
    "sg:city":"Valencia",
    "sg:classifiers":[
        {
            "category":"Shopping",
            "subcategory":"Mobile Phones",
            "type":"Retail Goods"
        }
    ],
    "sg:phone":"+1 661 255 6789",
    "sg:postcode":"91355",
    "sg:province":"CA",
    "wof:name":"Neighborhood Wireless Center",
    "wof:placetype":"venue"
},
  "geometry": {"coordinates":[-118.553375,34.428875],"type":"Point"}
}