{
  "type": "Feature",
  "properties": {
    "iso:country":"US",
    "sg:address":"1205 State Ln",
    "sg:city":"Yountville",
    "sg:classifiers":[
        {
            "category":"Real Estate",
            "subcategory":"Real Estate Agent",
            "type":"Services"
        }
    ],
    "sg:phone":"+1 707 944 2613",
    "sg:postcode":"94599",
    "sg:province":"CA",
    "sg:tags":[
        "management"
    ],
    "wof:name":"HKM Enterprises",
    "wof:placetype":"venue"
},
  "geometry": {"coordinates":[-122.355688,38.431604],"type":"Point"}
}