{
  "type": "Feature",
  "properties": {
    "addr:full":"19100 Von Karman Ave Irvine CA 92612",
    "addr:housenumber":"19100",
    "addr:postcode":"92612",
    "addr:street":"Von Karman Ave",
    "iso:country":"US",
    "sg:address":"19100 Von Karman Ave",
    "sg:city":"Irvine",
    "sg:classifiers":[
        {
            "category":"Banks & Credit Unions",
            "subcategory":"Bank",
            "type":"Services"
        }
    ],
    "sg:phone":"+1 949 720 1776",
    "sg:postcode":"92612",
    "sg:province":"CA",
    "wof:name":"First Regional Bank",
    "wof:placetype":"venue"
},
  "geometry": {"coordinates":[-117.85849399999999,33.670616],"type":"Point"}
}