{
  "type": "Feature",
  "properties": {
    "addr:full":"819 Mitten Rd Burlingame CA 94010",
    "addr:housenumber":"819",
    "addr:postcode":"94010",
    "addr:street":"Mitten Rd",
    "iso:country":"US",
    "sg:address":"819 Mitten Rd",
    "sg:city":"Burlingame",
    "sg:classifiers":[
        {
            "category":"Travel",
            "subcategory":"Travel Agent",
            "type":"Entertainment"
        }
    ],
    "sg:phone":"+1 650 697 8565",
    "sg:postcode":"94010",
    "sg:province":"CA",
    "sg:tags":[
        "agency",
        "bureau"
    ],
    "wof:name":"Philippine Travel",
    "wof:placetype":"venue"
},
  "geometry": {"coordinates":[-122.374645,37.600326],"type":"Point"}
}