{
  "type": "Feature",
  "properties": {
    "iso:country":"US",
    "sg:address":"6474 Patterson Pass Rd",
    "sg:city":"Livermore",
    "sg:classifiers":[
        {
            "category":"Professional",
            "subcategory":"Art Services",
            "type":"Services"
        }
    ],
    "sg:phone":"+1 925 449 6053",
    "sg:postcode":"94550",
    "sg:province":"CA",
    "sg:tags":[
        "development",
        "package",
        "designing"
    ],
    "wof:name":"Baer Enterprises",
    "wof:placetype":"venue"
},
  "geometry": {"coordinates":[-121.710273,37.695858],"type":"Point"}
}