{
  "type": "Feature",
  "properties": {
    "iso:country":"US",
    "sg:address":"442 W Mission Rd",
    "sg:city":"San Marcos",
    "sg:classifiers":[
        {
            "category":"Food & Beverages",
            "subcategory":"Groceries & Convenience Stores",
            "type":"Retail Goods"
        }
    ],
    "sg:phone":"+1 760 940 4125",
    "sg:postcode":"92069",
    "sg:province":"CA",
    "sg:tags":[
        "grocer"
    ],
    "wof:name":"LA Sorpresa Barata",
    "wof:placetype":"venue"
},
  "geometry": {"coordinates":[-117.170468,33.144665],"type":"Point"}
}