{
  "type": "Feature",
  "properties": {
    "addr:full":"317 South Broadway Los Angeles CA 90013",
    "addr:housenumber":"317",
    "addr:postcode":"90013",
    "addr:street":"South Broadway",
    "iso:country":"US",
    "sg:address":"317 South Broadway",
    "sg:city":"Los Angeles",
    "sg:classifiers":[
        {
            "category":"Personal",
            "type":"Services"
        }
    ],
    "sg:phone":"+1 213 769 4043",
    "sg:postcode":"90013",
    "sg:province":"CA",
    "sg:tags":[
        "home"
    ],
    "sg:website":"garagedoorsrepair-newgaragedoors...",
    "wof:name":"Garage Doors Repair+New Garage Doors",
    "wof:placetype":"venue"
},
  "geometry": {"coordinates":[-118.24849399999999,34.050499],"type":"Point"}
}