{
  "type": "Feature",
  "properties": {
    "iso:country":"US",
    "sg:address":"4040 W Washington Blvd",
    "sg:city":"Los Angeles",
    "sg:classifiers":[
        {
            "category":"Shopping",
            "type":"Retail Goods"
        }
    ],
    "sg:phone":"+1 323 737 3068",
    "sg:postcode":"90018",
    "sg:province":"CA",
    "sg:tags":[
        "cosmetic",
        "perfume"
    ],
    "wof:name":"Jennies Cosmetics",
    "wof:placetype":"venue"
},
  "geometry": {"coordinates":[-118.326821,34.039807],"type":"Point"}
}