{
  "type": "Feature",
  "properties": {
    "addr:full":"1270 Lucretia Avenue San Jose CA 95122",
    "addr:housenumber":"1270",
    "addr:postcode":"95122",
    "addr:street":"Lucretia Avenue",
    "iso:country":"US",
    "sg:address":"1270 Lucretia Avenue",
    "sg:city":"San Jose",
    "sg:classifiers":[
        {
            "category":"Organizations",
            "subcategory":"Religious Organization",
            "type":"Services"
        }
    ],
    "sg:phone":"+1 408 294 4834",
    "sg:postcode":"95122",
    "sg:province":"CA",
    "sg:website":"www.ag.org",
    "wof:name":"Samon Community Assembly of God",
    "wof:placetype":"venue"
},
  "geometry": {"coordinates":[-121.85549,37.327969],"type":"Point"}
}