{
  "type": "Feature",
  "properties": {
    "addr:full":"21000 Devonshire St Chatsworth CA 91311",
    "addr:housenumber":"21000",
    "addr:postcode":"91311",
    "addr:street":"Devonshire St",
    "iso:country":"US",
    "sg:address":"21000 Devonshire St",
    "sg:city":"Chatsworth",
    "sg:classifiers":[
        {
            "category":"Insurance",
            "subcategory":"Insurance Agent",
            "type":"Services"
        }
    ],
    "sg:phone":"+1 818 998 5256",
    "sg:postcode":"91311",
    "sg:province":"CA",
    "wof:name":"Farmers Insurance Group",
    "wof:placetype":"venue"
},
  "geometry": {"coordinates":[-118.592939,34.257239],"type":"Point"}
}