{
  "type": "Feature",
  "properties": {
    "addr:full":"4672 University Ave #D San Diego CA 92105",
    "addr:housenumber":"4672",
    "addr:postcode":"92105",
    "addr:street":"University Ave # D",
    "iso:country":"US",
    "sg:address":"4672 University Ave #D",
    "sg:city":"San Diego",
    "sg:classifiers":[
        {
            "category":"Restaurant",
            "type":"Food & Drink"
        }
    ],
    "sg:phone":"+1 619 285 1450",
    "sg:postcode":"92105",
    "sg:province":"CA",
    "sg:tags":[
        "pizza"
    ],
    "sg:website":"SawayasPizza.com",
    "wof:name":"Sawaya's Pizza",
    "wof:placetype":"venue"
},
  "geometry": {"coordinates":[-117.09364600000001,32.749793],"type":"Point"}
}