{
  "type": "Feature",
  "properties": {
    "addr:full":"15466 Los Gatos Blvd Los Gatos CA 95032",
    "addr:housenumber":"15466",
    "addr:postcode":"95032",
    "addr:street":"Los Gatos Blvd",
    "iso:country":"US",
    "sg:address":"15466 Los Gatos Blvd",
    "sg:city":"Los Gatos",
    "sg:classifiers":[
        {
            "category":"Health Services",
            "subcategory":"Chiropractor",
            "type":"Services"
        }
    ],
    "sg:phone":"+1 408 358 9588",
    "sg:postcode":"95032",
    "sg:province":"CA",
    "wof:name":"Community Chiropractic Spine",
    "wof:placetype":"venue"
},
  "geometry": {"coordinates":[-121.959299,37.243507],"type":"Point"}
}