{
  "type": "Feature",
  "properties": {
    "iso:country":"US",
    "sg:address":"254 San Lorenzo Blvd",
    "sg:city":"Santa Cruz",
    "sg:classifiers":[
        {
            "category":"Building & Trades",
            "subcategory":"Landscaping Services",
            "type":"Services"
        }
    ],
    "sg:phone":"+1 831 457 0960",
    "sg:postcode":"95060",
    "sg:province":"CA",
    "sg:tags":[
        "landscape"
    ],
    "wof:name":"Thoughtful Landscaping",
    "wof:placetype":"venue"
},
  "geometry": {"coordinates":[-122.021013,36.969175],"type":"Point"}
}