{
  "type": "Feature",
  "properties": {
    "addr:full":"15312 Hawthorne Blvd Lawndale CA 90260",
    "addr:housenumber":"15312",
    "addr:postcode":"ca 90260",
    "addr:street":"Hawthorne Blvd",
    "iso:country":"US",
    "sg:address":"15312 Hawthorne Blvd",
    "sg:city":"Lawndale",
    "sg:classifiers":[
        {
            "category":"Retail",
            "subcategory":"Auto Rental",
            "type":"Services"
        }
    ],
    "sg:phone":"+1 310 973 7037",
    "sg:postcode":"90260",
    "sg:province":"CA",
    "sg:tags":[
        "renting",
        "truck",
        "leasing"
    ],
    "wof:name":"U-Haul Co",
    "wof:placetype":"venue"
},
  "geometry": {"coordinates":[-118.35229200000001,33.89118],"type":"Point"}
}