{
  "type": "Feature",
  "properties": {
    "addr:full":"625 The City Dr S Orange CA 92868",
    "addr:housenumber":"625",
    "addr:postcode":"92868",
    "addr:street":"The City Dr S",
    "iso:country":"US",
    "sg:address":"625 The City Dr S",
    "sg:city":"Orange",
    "sg:classifiers":[
        {
            "category":"Professional",
            "subcategory":"Employment Agencies",
            "type":"Services"
        }
    ],
    "sg:phone":"+1 714 971 0721",
    "sg:postcode":"92868",
    "sg:province":"CA",
    "wof:name":"Kelly Scientific Resources",
    "wof:placetype":"venue"
},
  "geometry": {"coordinates":[-117.889999,33.776798],"type":"Point"}
}