{
  "type": "Feature",
  "properties": {
    "iso:country":"US",
    "sg:address":"760 Market St Ste 1012",
    "sg:city":"San Francisco",
    "sg:classifiers":[
        {
            "category":"Professional",
            "subcategory":"Accounting & Tax Preparation",
            "type":"Services"
        }
    ],
    "sg:phone":"+1 415 750 1505",
    "sg:postcode":"94102",
    "sg:province":"CA",
    "sg:tags":[
        "accountant"
    ],
    "sg:website":"latetax.com",
    "wof:name":"Downtown Tax Service",
    "wof:placetype":"venue"
},
  "geometry": {"coordinates":[-122.405463,37.786469],"type":"Point"}
}