{
  "type": "Feature",
  "properties": {
    "addr:full":"24950 Redlands Blvd Loma Linda CA 92354",
    "addr:postcode":"24950;92354",
    "addr:street":"Redlands Blvd",
    "iso:country":"US",
    "sg:address":"24950 Redlands Blvd",
    "sg:city":"Loma Linda",
    "sg:classifiers":[
        {
            "category":"Banks & Credit Unions",
            "subcategory":"Bank",
            "type":"Services"
        }
    ],
    "sg:phone":"+1 909 796 8622",
    "sg:postcode":"92354",
    "sg:province":"CA",
    "sg:tags":[
        "depository",
        "money",
        "transfer",
        "banking"
    ],
    "wof:name":"Lucky Money Inc",
    "wof:placetype":"venue"
},
  "geometry": {"coordinates":[-117.260862,34.06314],"type":"Point"}
}