{
  "type": "Feature",
  "properties": {
    "addr:full":"8366 Baisley Ct Elk Grove CA 95624",
    "addr:housenumber":"8366",
    "addr:postcode":"95624",
    "addr:street":"Baisley Ct",
    "iso:country":"US",
    "sg:address":"8366 Baisley Ct",
    "sg:city":"Elk Grove",
    "sg:classifiers":[
        {
            "category":"Building & Trades",
            "subcategory":"Construction",
            "type":"Services"
        }
    ],
    "sg:phone":"+1 916 747 3403",
    "sg:postcode":"95624",
    "sg:province":"CA",
    "sg:tags":[
        "house"
    ],
    "wof:name":"Mj Construction",
    "wof:placetype":"venue"
},
  "geometry": {"coordinates":[-121.39586199999999,38.434228],"type":"Point"}
}