{
  "type": "Feature",
  "properties": {
    "addr:full":"23976 2nd St Hayward CA 94541",
    "addr:housenumber":"23976",
    "addr:postcode":"94541",
    "addr:street":"2Nd St",
    "iso:country":"US",
    "sg:address":"23976 2nd St",
    "sg:city":"Hayward",
    "sg:classifiers":[
        {
            "category":"Real Estate",
            "subcategory":"Real Estate Operator",
            "type":"Services"
        }
    ],
    "sg:phone":"+1 510 733 2631",
    "sg:postcode":"94541",
    "sg:province":"CA",
    "sg:tags":[
        "apartment"
    ],
    "wof:name":"Terrace Towers",
    "wof:placetype":"venue"
},
  "geometry": {"coordinates":[-122.07589299999999,37.671928],"type":"Point"}
}