{
  "type": "Feature",
  "properties": {
    "iso:country":"US",
    "sg:address":"197 Woodland Pkwy",
    "sg:city":"San Marcos",
    "sg:classifiers":[
        {
            "category":"Personal",
            "type":"Services"
        }
    ],
    "sg:phone":"+1 760 744 9648",
    "sg:postcode":"92069",
    "sg:province":"CA",
    "sg:tags":[
        "mail",
        "receiving"
    ],
    "wof:name":"Postal Annex",
    "wof:placetype":"venue"
},
  "geometry": {"coordinates":[-117.137077,33.14285],"type":"Point"}
}