{
  "type": "Feature",
  "properties": {
    "addr:full":"415 Geary St San Francisco CA 94102",
    "addr:housenumber":"415",
    "addr:postcode":"94102",
    "addr:street":"Geary St",
    "iso:country":"US",
    "sg:address":"415 Geary St",
    "sg:city":"San Francisco",
    "sg:classifiers":[
        {
            "category":"Arts & Performance",
            "subcategory":"Theater",
            "type":"Entertainment"
        }
    ],
    "sg:phone":"+1 415 749 2228",
    "sg:postcode":"94102",
    "sg:province":"CA",
    "wof:name":"American Conservatory Theater",
    "wof:placetype":"venue"
},
  "geometry": {"coordinates":[-122.41007,37.787053],"type":"Point"}
}