{
  "type": "Feature",
  "properties": {
    "addr:full":"784 Mimbrera Way Salinas CA 93905",
    "addr:housenumber":"784",
    "addr:postcode":"93905",
    "addr:street":"Mimbrera Way",
    "iso:country":"US",
    "sg:address":"784 Mimbrera Way",
    "sg:city":"Salinas",
    "sg:classifiers":[
        {
            "category":"Restaurant",
            "type":"Food & Drink"
        }
    ],
    "sg:phone":"+1 831 753 7230",
    "sg:postcode":"93905",
    "sg:province":"CA",
    "wof:name":"Italia Cabral",
    "wof:placetype":"venue"
},
  "geometry": {"coordinates":[-121.609831,36.694897],"type":"Point"}
}