{
  "type": "Feature",
  "properties": {
    "iso:country":"US",
    "sg:address":"8627 Venice Blvd",
    "sg:city":"Los Angeles",
    "sg:classifiers":[
        {
            "category":"Building & Trades",
            "subcategory":"Construction",
            "type":"Services"
        }
    ],
    "sg:phone":"+1 310 202 1915",
    "sg:postcode":"90034",
    "sg:province":"CA",
    "sg:tags":[
        "tile",
        "dealer"
    ],
    "wof:name":"Discount Tile Ctr",
    "wof:placetype":"venue"
},
  "geometry": {"coordinates":[-118.380831,34.033924],"type":"Point"}
}