{
  "type": "Feature",
  "properties": {
    "iso:country":"US",
    "sg:address":"14536 Garfield Ave",
    "sg:city":"Paramount",
    "sg:classifiers":[
        {
            "category":"Wholesale",
            "subcategory":"Sporting Goods",
            "type":"Manufacturing & Wholesale Goods"
        }
    ],
    "sg:phone":"+1 562 633 3767",
    "sg:postcode":"90723",
    "sg:province":"CA",
    "sg:tags":[
        "distributor",
        "diving",
        "equipment"
    ],
    "wof:name":"Ocean Ways",
    "wof:placetype":"venue"
},
  "geometry": {"coordinates":[-118.16874900000001,33.901634],"type":"Point"}
}