{
  "type": "Feature",
  "properties": {
    "addr:full":"700 Saratoga Ave San Jose CA 95129",
    "addr:housenumber":"700",
    "addr:postcode":"95129",
    "addr:street":"Saratoga Ave",
    "iso:country":"US",
    "sg:address":"700 Saratoga Ave",
    "sg:city":"San Jose",
    "sg:classifiers":[
        {
            "category":"Personal",
            "subcategory":"Massage",
            "type":"Services"
        },
        {
            "category":"Personal",
            "subcategory":"Hair Removal",
            "type":"Services"
        },
        {
            "category":"Personal",
            "subcategory":"Skin Care",
            "type":"Services"
        }
    ],
    "sg:phone":"+1 408 309 8044",
    "sg:postcode":"95129",
    "sg:province":"CA",
    "sg:website":"heaven-on-earth.net",
    "wof:name":"Heaven On Earth",
    "wof:placetype":"venue"
},
  "geometry": {"coordinates":[-121.976697,37.314315],"type":"Point"}
}