{
  "type": "Feature",
  "properties": {
    "iso:country":"US",
    "sg:address":"1601 Dixon Landing Rd",
    "sg:city":"Milpitas",
    "sg:classifiers":[
        {
            "category":"Utilities",
            "subcategory":"Refuse",
            "type":"Services"
        }
    ],
    "sg:phone":"+1 408 945 2800",
    "sg:postcode":"95035",
    "sg:province":"CA",
    "sg:tags":[
        "landfill",
        "sanitary",
        "operation"
    ],
    "wof:name":"Site L69",
    "wof:placetype":"venue"
},
  "geometry": {"coordinates":[-121.92456900000001,37.453238],"type":"Point"}
}