{
  "type": "Feature",
  "properties": {
    "iso:country":"US",
    "sg:address":"4425 Treat Blvd",
    "sg:city":"Concord",
    "sg:classifiers":[
        {
            "category":"Professional",
            "subcategory":"Computer Services",
            "type":"Services"
        }
    ],
    "sg:phone":"+1 925 689 2697",
    "sg:postcode":"94521",
    "sg:province":"CA",
    "sg:tags":[
        "repair"
    ],
    "wof:name":"Mariner Computers",
    "wof:placetype":"venue"
},
  "geometry": {"coordinates":[-121.993861,37.962885],"type":"Point"}
}