{
  "type": "Feature",
  "properties": {
    "addr:full":"1511 Sycamore Ave Hercules CA 94547",
    "addr:housenumber":"1511",
    "addr:postcode":"94547",
    "addr:street":"Sycamore Ave",
    "iso:country":"US",
    "sg:address":"1511 Sycamore Ave",
    "sg:city":"Hercules",
    "sg:classifiers":[
        {
            "category":"Professional",
            "subcategory":"Advertising",
            "type":"Services"
        }
    ],
    "sg:phone":"+1 510 245 7060",
    "sg:postcode":"94547",
    "sg:province":"CA",
    "sg:tags":[
        "mailing",
        "shipping"
    ],
    "wof:name":"UPS Store",
    "wof:placetype":"venue"
},
  "geometry": {"coordinates":[-122.269841,38.009153],"type":"Point"}
}