{
  "type": "Feature",
  "properties": {
    "iso:country":"US",
    "sg:address":"1917 Palomar Oaks Way Suite 200",
    "sg:city":"Carlsbad",
    "sg:classifiers":[
        {
            "category":"Professional",
            "subcategory":"Computer Services",
            "type":"Services"
        }
    ],
    "sg:phone":"+1 760 692 3700",
    "sg:postcode":"92008",
    "sg:province":"CA",
    "sg:website":"http://www.medsphere.com/",
    "wof:name":"Medsphere Systems",
    "wof:placetype":"venue"
},
  "geometry": {"coordinates":[-117.291281,33.127335],"type":"Point"}
}