{
  "type": "Feature",
  "properties": {
    "addr:full":"7254 Hansen Dr Dublin CA 94568",
    "addr:housenumber":"7254",
    "addr:postcode":"94568",
    "addr:street":"Hansen Dr",
    "iso:country":"US",
    "sg:address":"7254 Hansen Dr",
    "sg:city":"Dublin",
    "sg:classifiers":[
        {
            "category":"Home & Garden",
            "subcategory":"Furniture",
            "type":"Retail Goods"
        }
    ],
    "sg:phone":"+1 925 556 9334",
    "sg:postcode":"94568",
    "sg:province":"CA",
    "sg:tags":[
        "top",
        "counter"
    ],
    "wof:name":"Elegant Surfaces",
    "wof:placetype":"venue"
},
  "geometry": {"coordinates":[-121.941836,37.702544],"type":"Point"}
}