{
  "type": "Feature",
  "properties": {
    "iso:country":"US",
    "sg:address":"15067 E 14th St",
    "sg:city":"San Leandro",
    "sg:classifiers":[
        {
            "category":"Government",
            "subcategory":"Office",
            "type":"Public Place"
        }
    ],
    "sg:phone":"+1 510 782 6606",
    "sg:postcode":"94578",
    "sg:province":"CA",
    "sg:tags":[
        "national",
        "security"
    ],
    "wof:name":"US Recruiting Marine Corps",
    "wof:placetype":"venue"
},
  "geometry": {"coordinates":[-122.12718,37.704279],"type":"Point"}
}