{
  "type": "Feature",
  "properties": {
    "iso:country":"US",
    "sg:address":"510 W Main St",
    "sg:city":"Santa Maria",
    "sg:classifiers":[
        {
            "category":"Shopping",
            "subcategory":"Department Store",
            "type":"Retail Goods"
        }
    ],
    "sg:phone":"+1 805 349 7610",
    "sg:postcode":"93458",
    "sg:province":"CA",
    "wof:name":"$10 Dollar Store",
    "wof:placetype":"venue"
},
  "geometry": {"coordinates":[-120.441577,34.953068],"type":"Point"}
}