{
  "type": "Feature",
  "properties": {
    "addr:full":"26495 20 Mule Team Rd Boron CA 93516",
    "addr:housenumber":"26495",
    "addr:postcode":"93516",
    "addr:street":"20 Mule Team Rd",
    "iso:country":"US",
    "sg:address":"26495 20 Mule Team Rd",
    "sg:city":"Boron",
    "sg:classifiers":[
        {
            "category":"Travel",
            "subcategory":"Hotels & Motels",
            "type":"Entertainment"
        }
    ],
    "sg:phone":"+1 760 762 6700",
    "sg:postcode":"93516",
    "sg:province":"CA",
    "sg:tags":[
        "corporate",
        "lodging"
    ],
    "sg:website":"http://www.budgetinn.com",
    "wof:name":"Budget Inn",
    "wof:placetype":"venue"
},
  "geometry": {"coordinates":[-117.658618,35.00005],"type":"Point"}
}