{
  "type": "Feature",
  "properties": {
    "iso:country":"US",
    "sg:address":"11304 South St",
    "sg:city":"Cerritos",
    "sg:classifiers":[
        {
            "category":"Home & Garden",
            "subcategory":"Furniture",
            "type":"Retail Goods"
        }
    ],
    "sg:phone":"+1 562 924 8649",
    "sg:postcode":"90703",
    "sg:province":"CA",
    "sg:tags":[
        "equipment",
        "repair",
        "kitchen",
        "appliance",
        "cabinet"
    ],
    "wof:name":"Evans Appliances",
    "wof:placetype":"venue"
},
  "geometry": {"coordinates":[-118.094002,33.8582],"type":"Point"}
}