{
  "type": "Feature",
  "properties": {
    "iso:country":"US",
    "sg:address":"19885 State Hwy 88",
    "sg:city":"Pine Grove",
    "sg:classifiers":[
        {
            "category":"Professional",
            "subcategory":"Management & Consulting",
            "type":"Services"
        }
    ],
    "sg:phone":"+1 209 296 4960",
    "sg:postcode":"95665",
    "sg:province":"CA",
    "sg:tags":[
        "consultant",
        "business"
    ],
    "wof:name":"Turner Accountancy",
    "wof:placetype":"venue"
},
  "geometry": {"coordinates":[-120.656639,38.413147],"type":"Point"}
}