{
  "type": "Feature",
  "properties": {
    "iso:country":"US",
    "sg:address":"4724 Guenza Rd",
    "sg:city":"Santa Rosa",
    "sg:classifiers":[
        {
            "category":"Retail",
            "subcategory":"Animal Services",
            "type":"Services"
        }
    ],
    "sg:phone":"+1 707 526 2158",
    "sg:postcode":"95404",
    "sg:province":"CA",
    "sg:tags":[
        "horse",
        "training"
    ],
    "wof:name":"Fulton Farms",
    "wof:placetype":"venue"
},
  "geometry": {"coordinates":[-122.64540700000001,38.380097],"type":"Point"}
}