{
  "type": "Feature",
  "properties": {
    "iso:country":"US",
    "sg:address":"1835 Newport Blvd Ste A109",
    "sg:city":"Costa Mesa",
    "sg:classifiers":[
        {
            "category":"Professional",
            "subcategory":"Lawyer & Legal Services",
            "type":"Services"
        }
    ],
    "sg:phone":"+1 714 752 0977",
    "sg:postcode":"92627",
    "sg:province":"CA",
    "sg:tags":[
        "personal",
        "injury"
    ],
    "wof:name":"Costa Mesa Personal Injury Attorneys",
    "wof:placetype":"venue"
},
  "geometry": {"coordinates":[-117.920052,33.642431],"type":"Point"}
}