{
  "type": "Feature",
  "properties": {
    "addr:full":"932 Shotwell Street San Francisco CA 94110",
    "addr:housenumber":"932",
    "addr:postcode":"94110",
    "addr:street":"Shotwell Street",
    "iso:country":"US",
    "sg:address":"932 Shotwell Street",
    "sg:city":"San Francisco",
    "sg:classifiers":[
        {
            "category":"Building & Trades",
            "subcategory":"Plumbing",
            "type":"Services"
        }
    ],
    "sg:phone":"+1 415 282 5599",
    "sg:postcode":"94110",
    "sg:province":"CA",
    "wof:name":"Peter's Plumbing",
    "wof:placetype":"venue"
},
  "geometry": {"coordinates":[-122.415001,37.753101],"type":"Point"}
}