{
  "type": "Feature",
  "properties": {
    "iso:country":"US",
    "sg:address":"700 Kincheloe Dr",
    "sg:city":"Woodland",
    "sg:classifiers":[
        {
            "category":"Arts & Performance",
            "subcategory":"Theater",
            "type":"Entertainment"
        }
    ],
    "sg:phone":"+1 530 666 3535",
    "sg:postcode":"95776",
    "sg:province":"CA",
    "sg:tags":[
        "live",
        "music"
    ],
    "wof:name":"Sac City DJ",
    "wof:placetype":"venue"
},
  "geometry": {"coordinates":[-121.730866,38.670058],"type":"Point"}
}