{
  "type": "Feature",
  "properties": {
    "iso:country":"US",
    "sg:address":"433 Coyote St",
    "sg:city":"Nevada City",
    "sg:classifiers":[
        {
            "category":"Real Estate",
            "subcategory":"Real Estate Agent",
            "type":"Services"
        }
    ],
    "sg:phone":"+1 530 265 5653",
    "sg:postcode":"95959",
    "sg:province":"CA",
    "sg:tags":[
        "appraiser"
    ],
    "wof:name":"Salvatore & Assoc",
    "wof:placetype":"venue"
},
  "geometry": {"coordinates":[-121.017161,39.265876],"type":"Point"}
}