{
  "type": "Feature",
  "properties": {
    "addr:full":"1089 N Lemoore Ave Lemoore CA 93245",
    "addr:housenumber":"1089",
    "addr:postcode":"93245",
    "addr:street":"N Lemoore Ave",
    "iso:country":"US",
    "sg:address":"1089 N Lemoore Ave",
    "sg:city":"Lemoore",
    "sg:classifiers":[
        {
            "category":"Fast Food",
            "type":"Food & Drink"
        },
        {
            "category":"Restaurant",
            "type":"Food & Drink"
        }
    ],
    "sg:phone":"+1 559 924 5600",
    "sg:postcode":"93245",
    "sg:province":"CA",
    "sg:tags":[
        "hamburger",
        "hot",
        "dog",
        "american",
        "take",
        "chicken"
    ],
    "sg:website":"http://www.mcdonalds.com",
    "wof:name":"McDonald's",
    "wof:placetype":"venue"
},
  "geometry": {"coordinates":[-119.780793,36.313239],"type":"Point"}
}