{
  "type": "Feature",
  "properties": {
    "iso:country":"US",
    "sg:address":"9377 Big Horn Way",
    "sg:city":"Sacramento",
    "sg:classifiers":[
        {
            "category":"Professional",
            "subcategory":"Business Services",
            "type":"Services"
        }
    ],
    "sg:phone":"+1 916 362 2632",
    "sg:postcode":"95827",
    "sg:province":"CA",
    "sg:tags":[
        "recording",
        "studio"
    ],
    "wof:name":"Gemini Records & Entertainment",
    "wof:placetype":"venue"
},
  "geometry": {"coordinates":[-121.349194,38.568222],"type":"Point"}
}