{
  "type": "Feature",
  "properties": {
    "addr:full":"2490 Honolulu Ave Montrose CA 91020",
    "addr:postcode":"2490;91020",
    "addr:street":"Honolulu Ave",
    "iso:country":"US",
    "sg:address":"2490 Honolulu Ave",
    "sg:city":"Montrose",
    "sg:classifiers":[
        {
            "category":"Social Services",
            "type":"Services"
        },
        {
            "category":"Personal",
            "type":"Services"
        }
    ],
    "sg:phone":"+1 818 249 5690",
    "sg:postcode":"91020",
    "sg:province":"CA",
    "sg:tags":[
        "counseling",
        "therapist",
        "marriage",
        "family"
    ],
    "wof:name":"Weingarten Nicole MFT",
    "wof:placetype":"venue"
},
  "geometry": {"coordinates":[-118.233002,34.207273],"type":"Point"}
}