{
  "type": "Feature",
  "properties": {
    "addr:full":"9010 Corbin Ave Northridge CA 91324",
    "addr:housenumber":"9010",
    "addr:postcode":"91324",
    "addr:street":"Corbin Ave",
    "iso:country":"US",
    "sg:address":"9010 Corbin Ave",
    "sg:city":"Northridge",
    "sg:classifiers":[
        {
            "category":"Professional",
            "subcategory":"Accounting & Tax Preparation",
            "type":"Services"
        }
    ],
    "sg:phone":"+1 818 701 7214",
    "sg:postcode":"91324",
    "sg:province":"CA",
    "sg:tags":[
        "return",
        "filing"
    ],
    "wof:name":"Derrico & Assoc",
    "wof:placetype":"venue"
},
  "geometry": {"coordinates":[-118.56223199999999,34.234169],"type":"Point"}
}