{
  "type": "Feature",
  "properties": {
    "addr:full":"40725 Encyclopedia Cir Fremont CA 94538",
    "addr:housenumber":"40725",
    "addr:postcode":"94538",
    "addr:street":"Encyclopedia Cir",
    "iso:country":"US",
    "sg:address":"40725 Encyclopedia Cir",
    "sg:city":"Fremont",
    "sg:classifiers":[
        {
            "category":"Wholesale",
            "subcategory":"Electrical",
            "type":"Manufacturing & Wholesale Goods"
        }
    ],
    "sg:phone":"+1 510 827 5185",
    "sg:postcode":"94538",
    "sg:province":"CA",
    "sg:tags":[
        "control",
        "security",
        "system"
    ],
    "wof:name":"OIC Inc",
    "wof:placetype":"venue"
},
  "geometry": {"coordinates":[-121.990459,37.516142],"type":"Point"}
}