{
  "type": "Feature",
  "properties": {
    "addr:full":"3295 Reche Rd Fallbrook CA 92028",
    "addr:housenumber":"3295",
    "addr:postcode":"92028",
    "addr:street":"Reche Rd",
    "iso:country":"US",
    "sg:address":"3295 Reche Rd",
    "sg:city":"Fallbrook",
    "sg:classifiers":[
        {
            "category":"Professional",
            "subcategory":"Printing & Photocopies",
            "type":"Services"
        }
    ],
    "sg:phone":"+1 760 728 1160",
    "sg:postcode":"92028",
    "sg:province":"CA",
    "sg:tags":[
        "photocopying"
    ],
    "wof:name":"Lason Inc",
    "wof:placetype":"venue"
},
  "geometry": {"coordinates":[-117.19096999999999,33.363803],"type":"Point"}
}