{
  "type": "Feature",
  "properties": {
    "addr:full":"4232 Bonita Rd Bonita CA 91902",
    "addr:housenumber":"4232",
    "addr:postcode":"91902",
    "addr:street":"Bonita Rd",
    "iso:country":"US",
    "sg:address":"4232 Bonita Rd",
    "sg:city":"Bonita",
    "sg:classifiers":[
        {
            "category":"Banks & Credit Unions",
            "subcategory":"Bank",
            "type":"Services"
        }
    ],
    "sg:phone":"+1 619 470 3900",
    "sg:postcode":"91902",
    "sg:province":"CA",
    "sg:tags":[
        "escrow"
    ],
    "wof:name":"Escrow Co Inc",
    "wof:placetype":"venue"
},
  "geometry": {"coordinates":[-117.034254,32.660527],"type":"Point"}
}