{
  "type": "Feature",
  "properties": {
    "iso:country":"US",
    "sg:address":"19900 S Vermont Ave",
    "sg:city":"Torrance",
    "sg:classifiers":[
        {
            "category":"Professional",
            "subcategory":"Management & Consulting",
            "type":"Services"
        },
        {
            "category":"Wholesale",
            "subcategory":"Non-durable Goods",
            "type":"Manufacturing & Wholesale Goods"
        }
    ],
    "sg:phone":"+1 310 327 8095",
    "sg:postcode":"90502",
    "sg:province":"CA",
    "sg:tags":[
        "a",
        "business",
        "consultant",
        "accessory",
        "sportswear",
        "general",
        "merchandise"
    ],
    "wof:name":"Orange Point Inc",
    "wof:placetype":"venue"
},
  "geometry": {"coordinates":[-118.290442,33.853765],"type":"Point"}
}