{
  "type": "Feature",
  "properties": {
    "iso:country":"US",
    "sg:address":"3231 Foothill Blvd",
    "sg:city":"La Crescenta",
    "sg:classifiers":[
        {
            "category":"Personal",
            "subcategory":"Beauty Salon",
            "type":"Services"
        }
    ],
    "sg:phone":"+1 818 957 4100",
    "sg:postcode":"91214",
    "sg:province":"CA",
    "wof:name":"Star Cuts",
    "wof:placetype":"venue"
},
  "geometry": {"coordinates":[-118.250057,34.230536],"type":"Point"}
}