{
  "type": "Feature",
  "properties": {
    "iso:country":"US",
    "sg:address":"15243 Vanowen St",
    "sg:city":"Van Nuys",
    "sg:classifiers":[
        {
            "category":"Personal",
            "type":"Services"
        }
    ],
    "sg:phone":"+1 818 994 5100",
    "sg:postcode":"91405",
    "sg:province":"CA",
    "sg:tags":[
        "control",
        "weight"
    ],
    "wof:name":"JPB Medical Group",
    "wof:placetype":"venue"
},
  "geometry": {"coordinates":[-118.465504,34.193992],"type":"Point"}
}