{
  "type": "Feature",
  "properties": {
    "addr:full":"253 Madonna Rd San Luis Obispo CA 93405",
    "addr:housenumber":"253",
    "addr:postcode":"93405",
    "addr:street":"Madonna Rd",
    "iso:country":"US",
    "sg:address":"253 Madonna Rd",
    "sg:city":"San Luis Obispo",
    "sg:classifiers":[
        {
            "category":"Coffee & Tea",
            "type":"Food & Drink"
        }
    ],
    "sg:menulink":"http://www.allmenus.com/ca/san-luis-obispo/117203-starbucks-coffee/menu/",
    "sg:phone":"+1 805 595 3482",
    "sg:postcode":"93405",
    "sg:province":"CA",
    "sg:tags":[
        "american"
    ],
    "wof:name":"Starbucks Coffee",
    "wof:placetype":"venue"
},
  "geometry": {"coordinates":[-120.678381,35.262504],"type":"Point"}
}