{
  "type": "Feature",
  "properties": {
    "iso:country":"US",
    "sg:address":"9625 Cozycroft Ave",
    "sg:city":"Chatsworth",
    "sg:classifiers":[
        {
            "category":"Home & Garden",
            "subcategory":"Building Materials",
            "type":"Retail Goods"
        }
    ],
    "sg:phone":"+1 818 993 7101",
    "sg:postcode":"91311",
    "sg:province":"CA",
    "sg:tags":[
        "trade",
        "contractor"
    ],
    "wof:name":"Protector Fence Co",
    "wof:placetype":"venue"
},
  "geometry": {"coordinates":[-118.582058,34.244083],"type":"Point"}
}