{
  "type": "Feature",
  "properties": {
    "addr:full":"110 Town Center E Santa Maria CA 93454",
    "addr:housenumber":"110",
    "addr:postcode":"93454",
    "addr:street":"Town Center E",
    "iso:country":"US",
    "sg:address":"110 Town Center E",
    "sg:city":"Santa Maria",
    "sg:classifiers":[
        {
            "category":"Shopping",
            "subcategory":"Clothing, Apparel, & Fashions",
            "type":"Retail Goods"
        }
    ],
    "sg:phone":"+1 805 928 7960",
    "sg:postcode":"93454",
    "sg:province":"CA",
    "sg:tags":[
        "sportswear"
    ],
    "wof:name":"Champs Sports",
    "wof:placetype":"venue"
},
  "geometry": {"coordinates":[-120.433606,34.952465],"type":"Point"}
}