{
  "type": "Feature",
  "properties": {
    "addr:full":"2590 N 1st St San Jose CA 95131",
    "addr:housenumber":"2590",
    "addr:postcode":"95131",
    "addr:street":"N 1St St",
    "iso:country":"US",
    "sg:address":"2590 N 1st St",
    "sg:city":"San Jose",
    "sg:classifiers":[
        {
            "category":"Insurance",
            "subcategory":"Insurance Agent",
            "type":"Services"
        }
    ],
    "sg:phone":"+1 408 503 4400",
    "sg:postcode":"95131",
    "sg:province":"CA",
    "sg:website":"www.statefarm.com",
    "wof:name":"State Farm Insurance",
    "wof:placetype":"venue"
},
  "geometry": {"coordinates":[-121.925324,37.382753],"type":"Point"}
}