{
  "type": "Feature",
  "properties": {
    "addr:full":"17285 Ridge Rd Pine Grove CA 95665",
    "addr:housenumber":"17285",
    "addr:postcode":"95665",
    "addr:street":"Ridge Rd",
    "iso:country":"US",
    "sg:address":"17285 Ridge Rd",
    "sg:city":"Pine Grove",
    "sg:classifiers":[
        {
            "category":"Retail",
            "subcategory":"Veterinary Services",
            "type":"Services"
        }
    ],
    "sg:phone":"+1 209 296 7070",
    "sg:postcode":"95665",
    "sg:province":"CA",
    "wof:name":"Veterinary Clinic",
    "wof:placetype":"venue"
},
  "geometry": {"coordinates":[-120.700495,38.414263],"type":"Point"}
}