{
  "type": "Feature",
  "properties": {
    "iso:country":"US",
    "sg:address":"1100 W Stewart Dr",
    "sg:city":"Orange",
    "sg:classifiers":[
        {
            "category":"Health Services",
            "subcategory":"Hospital",
            "type":"Services"
        }
    ],
    "sg:phone":"+1 714 771 8222",
    "sg:postcode":"92868",
    "sg:province":"CA",
    "wof:name":"Occupational Therapy Saint Joseph Hospital",
    "wof:placetype":"venue"
},
  "geometry": {"coordinates":[-117.864998,33.782501],"type":"Point"}
}