{
  "type": "Feature",
  "properties": {
    "iso:country":"US",
    "sg:address":"1524 Del Paso Blvd",
    "sg:city":"Sacramento",
    "sg:classifiers":[
        {
            "category":"Shopping",
            "subcategory":"Jewelry",
            "type":"Retail Goods"
        },
        {
            "category":"Shopping",
            "subcategory":"Antiques",
            "type":"Retail Goods"
        },
        {
            "category":"Shopping",
            "subcategory":"Pawn Shop",
            "type":"Retail Goods"
        }
    ],
    "sg:phone":"+1 916 568 6669",
    "sg:postcode":"95815",
    "sg:province":"CA",
    "sg:website":"www.CapitalCityLoan.com",
    "wof:name":"Western Loan & Jewelry",
    "wof:placetype":"venue"
},
  "geometry": {"coordinates":[-121.456883,38.606788],"type":"Point"}
}