{
  "type": "Feature",
  "properties": {
    "iso:country":"US",
    "sg:address":"2901 W Coast Hwy Ste 200",
    "sg:city":"Newport Beach",
    "sg:classifiers":[
        {
            "category":"Sports & Exercise",
            "subcategory":"Gym",
            "type":"Entertainment"
        }
    ],
    "sg:phone":"+1 949 258 4325",
    "sg:postcode":"92663",
    "sg:province":"CA",
    "wof:name":"Xttreme Professional Athletic Services",
    "wof:placetype":"venue"
},
  "geometry": {"coordinates":[-117.924845,33.62051],"type":"Point"}
}