{
  "type": "Feature",
  "properties": {
    "addr:full":"2700 E Foothill Blvd Pasadena CA 91107",
    "addr:housenumber":"2700",
    "addr:postcode":"91107",
    "addr:street":"E Foothill Blvd",
    "iso:country":"US",
    "sg:address":"2700 E Foothill Blvd",
    "sg:city":"Pasadena",
    "sg:classifiers":[
        {
            "category":"Health Services",
            "subcategory":"Chiropractor",
            "type":"Services"
        }
    ],
    "sg:phone":"+1 626 449 0510",
    "sg:postcode":"91107",
    "sg:province":"CA",
    "wof:name":"Integrated Healing Ctr",
    "wof:placetype":"venue"
},
  "geometry": {"coordinates":[-118.0949,34.149802],"type":"Point"}
}