{
  "type": "Feature",
  "properties": {
    "addr:full":"1409 Matlick Ln Bishop CA 93514",
    "addr:housenumber":"1409",
    "addr:postcode":"93514",
    "addr:street":"Matlick Ln",
    "iso:country":"US",
    "sg:address":"1409 Matlick Ln",
    "sg:city":"Bishop",
    "sg:classifiers":[
        {
            "category":"Building & Trades",
            "subcategory":"Construction",
            "type":"Services"
        }
    ],
    "sg:phone":"+1 760 873 6072",
    "sg:postcode":"93514",
    "sg:province":"CA",
    "sg:tags":[
        "mobile",
        "home"
    ],
    "wof:name":"Wofford's Mobile Home Svc",
    "wof:placetype":"venue"
},
  "geometry": {"coordinates":[-118.419241,37.377151],"type":"Point"}
}