{
  "type": "Feature",
  "properties": {
    "addr:full":"647 Front St Soledad CA 93960",
    "addr:housenumber":"647",
    "addr:postcode":"93960",
    "addr:street":"Front St",
    "iso:country":"US",
    "sg:address":"647 Front St",
    "sg:city":"Soledad",
    "sg:classifiers":[
        {
            "category":"Shopping",
            "subcategory":"Jewelry",
            "type":"Retail Goods"
        }
    ],
    "sg:phone":"+1 831 678 0655",
    "sg:postcode":"93960",
    "sg:province":"CA",
    "sg:tags":[
        "jeweler"
    ],
    "wof:name":"Joyeria Reynozo Jewelers",
    "wof:placetype":"venue"
},
  "geometry": {"coordinates":[-121.327776,36.425988],"type":"Point"}
}