{
  "type": "Feature",
  "properties": {
    "addr:full":"1941 N San Fernando Rd Los Angeles CA 90065",
    "addr:housenumber":"1941",
    "addr:postcode":"90065",
    "addr:street":"N San Fernando Rd",
    "iso:country":"US",
    "sg:address":"1941 N San Fernando Rd",
    "sg:city":"Los Angeles",
    "sg:classifiers":[
        {
            "category":"Shopping",
            "type":"Retail Goods"
        }
    ],
    "sg:phone":"+1 323 222 8883",
    "sg:postcode":"90065",
    "sg:province":"CA",
    "sg:tags":[
        "equipment",
        "commercial",
        "miscellaneous",
        "store",
        "furniture"
    ],
    "wof:name":"Pepe Rack Systems",
    "wof:placetype":"venue"
},
  "geometry": {"coordinates":[-118.23675,34.101858],"type":"Point"}
}