{
  "type": "Feature",
  "properties": {
    "iso:country":"US",
    "sg:address":"6457 Ellenview Ave",
    "sg:city":"West Hills",
    "sg:classifiers":[
        {
            "category":"Shopping",
            "subcategory":"Computers & Home Electronics",
            "type":"Retail Goods"
        }
    ],
    "sg:phone":"+1 818 888 1339",
    "sg:postcode":"91307",
    "sg:province":"CA",
    "sg:tags":[
        "television",
        "radio"
    ],
    "wof:name":"A Plus TV & VCR Svc",
    "wof:placetype":"venue"
},
  "geometry": {"coordinates":[-118.65757,34.18634],"type":"Point"}
}