{
  "type": "Feature",
  "properties": {
    "iso:country":"US",
    "sg:address":"762 Dolores St",
    "sg:city":"Stanford",
    "sg:classifiers":[
        {
            "category":"Social Services",
            "type":"Services"
        }
    ],
    "sg:phone":"+1 650 326 5126",
    "sg:postcode":"94305",
    "sg:province":"CA",
    "sg:tags":[
        "worker"
    ],
    "wof:name":"Angela E Riccelli Lcsw",
    "wof:placetype":"venue"
},
  "geometry": {"coordinates":[-122.169077,37.415824],"type":"Point"}
}