{
  "type": "Feature",
  "properties": {
    "addr:full":"929 4th Ave San Diego CA 92101",
    "addr:housenumber":"929",
    "addr:postcode":"92101",
    "addr:street":"4Th Ave",
    "iso:country":"US",
    "sg:address":"929 4th Ave",
    "sg:city":"San Diego",
    "sg:classifiers":[
        {
            "category":"Professional",
            "type":"Services"
        }
    ],
    "sg:phone":"+1 619 544 9135",
    "sg:postcode":"92101",
    "sg:province":"CA",
    "wof:name":"Little Brazil",
    "wof:placetype":"venue"
},
  "geometry": {"coordinates":[-117.161005,32.715395],"type":"Point"}
}