{
  "type": "Feature",
  "properties": {
    "addr:full":"640 S Ayon Ave Azusa CA 91702",
    "addr:housenumber":"640",
    "addr:postcode":"91702",
    "addr:street":"S Ayon Ave",
    "iso:country":"US",
    "sg:address":"640 S Ayon Ave",
    "sg:city":"Azusa",
    "sg:classifiers":[
        {
            "category":"Professional",
            "subcategory":"Engineering",
            "type":"Services"
        },
        {
            "category":"Wholesale",
            "subcategory":"Construction Materials",
            "type":"Manufacturing & Wholesale Goods"
        },
        {
            "category":"Home & Garden",
            "subcategory":"Building Materials",
            "type":"Retail Goods"
        }
    ],
    "sg:phone":"+1 626 969 1874",
    "sg:postcode":"91702",
    "sg:province":"CA",
    "sg:tags":[
        "heater",
        "systems-wholesale",
        "system",
        "water",
        "equipment",
        "heating",
        "air conditioning"
    ],
    "sg:website":"http://www.ferguson.com/BusinessGroups/hvac.shtml",
    "wof:name":"Ferguson Heating & Cooling",
    "wof:placetype":"venue"
},
  "geometry": {"coordinates":[-117.928589,34.113937],"type":"Point"}
}