{
  "type": "Feature",
  "properties": {
    "addr:full":"864 Overhill Dr Hayward CA 94544",
    "addr:housenumber":"864",
    "addr:postcode":"94544",
    "addr:street":"Overhill Dr",
    "iso:country":"US",
    "sg:address":"864 Overhill Dr",
    "sg:city":"Hayward",
    "sg:classifiers":[
        {
            "category":"Professional",
            "type":"Services"
        }
    ],
    "sg:phone":"+1 510 537 8064",
    "sg:postcode":"94544",
    "sg:province":"CA",
    "sg:tags":[
        "establishment"
    ],
    "wof:name":"PCDI Inc",
    "wof:placetype":"venue"
},
  "geometry": {"coordinates":[-122.046283,37.631631],"type":"Point"}
}