{
  "type": "Feature",
  "properties": {
    "addr:full":"11722 Enterprise Dr Auburn CA 95603",
    "addr:housenumber":"11722",
    "addr:postcode":"ca 95603",
    "addr:street":"Enterprise Dr",
    "iso:country":"US",
    "sg:address":"11722 Enterprise Dr",
    "sg:city":"Auburn",
    "sg:classifiers":[
        {
            "category":"Government",
            "subcategory":"Office",
            "type":"Public Place"
        }
    ],
    "sg:phone":"+1 530 885 9417",
    "sg:postcode":"95603",
    "sg:province":"CA",
    "sg:tags":[
        "state",
        "program"
    ],
    "sg:website":"www.dmv.ca.gov",
    "wof:name":"Motor Vehicle Dept",
    "wof:placetype":"venue"
},
  "geometry": {"coordinates":[-121.08417799999999,38.907804],"type":"Point"}
}