{
  "type": "Feature",
  "properties": {
    "addr:full":"18921 Portola Dr Salinas CA 93908",
    "addr:housenumber":"18921",
    "addr:postcode":"93908",
    "addr:street":"Portola Dr",
    "iso:country":"US",
    "sg:address":"18921 Portola Dr",
    "sg:city":"Salinas",
    "sg:classifiers":[
        {
            "category":"Professional",
            "subcategory":"Lawyer & Legal Services",
            "type":"Services"
        }
    ],
    "sg:phone":"+1 831 455 1616",
    "sg:postcode":"93908",
    "sg:province":"CA",
    "sg:tags":[
        "attorney"
    ],
    "wof:name":"Stephen H Fredkin Law Offices",
    "wof:placetype":"venue"
},
  "geometry": {"coordinates":[-121.685705,36.622923],"type":"Point"}
}