{
  "type": "Feature",
  "properties": {
    "addr:full":"316 S Santa Fe Ave Empire CA 95319",
    "addr:housenumber":"316",
    "addr:postcode":"95319",
    "addr:street":"S Santa Fe Ave",
    "iso:country":"US",
    "sg:address":"316 S Santa Fe Ave",
    "sg:city":"Empire",
    "sg:classifiers":[
        {
            "category":"Retail",
            "subcategory":"Storage",
            "type":"Services"
        }
    ],
    "sg:phone":"+1 209 576 8300",
    "sg:postcode":"95319",
    "sg:province":"CA",
    "sg:tags":[
        "self"
    ],
    "wof:name":"Empire Mini Storage",
    "wof:placetype":"venue"
},
  "geometry": {"coordinates":[-120.903999,37.641102],"type":"Point"}
}