{
  "type": "Feature",
  "properties": {
    "iso:country":"US",
    "sg:address":"382 Marquette St",
    "sg:city":"Farmersville",
    "sg:classifiers":[
        {
            "category":"Social Services",
            "subcategory":"Child Care",
            "type":"Services"
        }
    ],
    "sg:phone":"+1 559 747 6508",
    "sg:postcode":"93223",
    "sg:province":"CA",
    "wof:name":"Jennifer's Family Daycare",
    "wof:placetype":"venue"
},
  "geometry": {"coordinates":[-119.21034,36.310943],"type":"Point"}
}