{
  "type": "Feature",
  "properties": {
    "iso:country":"US",
    "sg:address":"1545 S Upas St",
    "sg:city":"Escondido",
    "sg:classifiers":[
        {
            "category":"Banks & Credit Unions",
            "subcategory":"Financial Services",
            "type":"Services"
        }
    ],
    "sg:phone":"+1 760 747 3457",
    "sg:postcode":"92025",
    "sg:province":"CA",
    "sg:tags":[
        "trust",
        "management"
    ],
    "wof:name":"Newheiser Family Trust",
    "wof:placetype":"venue"
},
  "geometry": {"coordinates":[-117.084689,33.102149],"type":"Point"}
}