{
  "type": "Feature",
  "properties": {
    "addr:full":"530 S A St Oxnard CA 93030",
    "addr:housenumber":"530",
    "addr:postcode":"93030",
    "addr:street":"S A St",
    "iso:country":"US",
    "sg:address":"530 S A St",
    "sg:city":"Oxnard",
    "sg:classifiers":[
        {
            "category":"Shopping",
            "subcategory":"Clothing, Apparel, & Fashions",
            "type":"Retail Goods"
        }
    ],
    "sg:phone":"+1 805 483 1152",
    "sg:postcode":"93030",
    "sg:province":"CA",
    "sg:tags":[
        "shop",
        "bridal"
    ],
    "wof:name":"Bride's Palace",
    "wof:placetype":"venue"
},
  "geometry": {"coordinates":[-119.17850300000001,34.19725],"type":"Point"}
}