{
  "type": "Feature",
  "properties": {
    "iso:country":"US",
    "sg:address":"90 New Montgomery Street",
    "sg:city":"San Francisco",
    "sg:classifiers":[
        {
            "category":"Professional",
            "subcategory":"Accounting & Tax Preparation",
            "type":"Services"
        }
    ],
    "sg:phone":"+1 415 781 9900",
    "sg:postcode":"94105",
    "sg:province":"CA",
    "sg:tags":[
        "accountant"
    ],
    "wof:name":"Chu Jack W CPA",
    "wof:placetype":"venue"
},
  "geometry": {"coordinates":[-122.40066299999999,37.787672],"type":"Point"}
}