{
  "type": "Feature",
  "properties": {
    "addr:full":"444 28th St Apt 31 Oakland CA 94609",
    "addr:housenumber":"444;31",
    "addr:postcode":"94609",
    "addr:street":"28Th St Apt",
    "iso:country":"US",
    "sg:address":"444 28th St Apt 31",
    "sg:city":"Oakland",
    "sg:classifiers":[
        {
            "category":"Education",
            "subcategory":"Special Training",
            "type":"Public Place"
        }
    ],
    "sg:phone":"+1 510 773 8096",
    "sg:postcode":"94609",
    "sg:province":"CA",
    "sg:tags":[
        "educational"
    ],
    "wof:name":"Urban Girls Inc",
    "wof:placetype":"venue"
},
  "geometry": {"coordinates":[-122.266209,37.816617],"type":"Point"}
}