{
  "type": "Feature",
  "properties": {
    "addr:full":"33 Jennings Ct San Francisco CA 94124",
    "addr:housenumber":"33",
    "addr:postcode":"94124",
    "addr:street":"Jennings Ct",
    "iso:country":"US",
    "sg:address":"33 Jennings Ct",
    "sg:city":"San Francisco",
    "sg:classifiers":[
        {
            "category":"Sports & Exercise",
            "subcategory":"Gym",
            "type":"Entertainment"
        }
    ],
    "sg:phone":"+1 415 468 7898",
    "sg:postcode":"94124",
    "sg:province":"CA",
    "sg:tags":[
        "pilate"
    ],
    "sg:website":"www.pilatessanfrancisco.com/",
    "wof:name":"Pilates-SF",
    "wof:placetype":"venue"
},
  "geometry": {"coordinates":[-122.397886,37.717313],"type":"Point"}
}