{
  "type": "Feature",
  "properties": {
    "iso:country":"US",
    "sg:address":"13332 Mapledale St",
    "sg:city":"Norwalk",
    "sg:classifiers":[
        {
            "category":"Wholesale",
            "subcategory":"Drugs",
            "type":"Manufacturing & Wholesale Goods"
        }
    ],
    "sg:phone":"+1 562 926 4707",
    "sg:postcode":"90650",
    "sg:province":"CA",
    "wof:name":"Para Beauty Inc",
    "wof:placetype":"venue"
},
  "geometry": {"coordinates":[-118.04669,33.898708],"type":"Point"}
}