{
  "type": "Feature",
  "properties": {
    "iso:country":"US",
    "sg:address":"5340 Las Virgenes Rd",
    "sg:city":"Calabasas",
    "sg:classifiers":[
        {
            "category":"Wholesale",
            "subcategory":"Furniture",
            "type":"Manufacturing & Wholesale Goods"
        }
    ],
    "sg:phone":"+1 818 878 0632",
    "sg:postcode":"91302",
    "sg:province":"CA",
    "wof:name":"G Group LLC",
    "wof:placetype":"venue"
},
  "geometry": {"coordinates":[-118.69796599999999,34.154303],"type":"Point"}
}