{
  "type": "Feature",
  "properties": {
    "iso:country":"US",
    "sg:address":"1096 48th St",
    "sg:city":"Emeryville",
    "sg:classifiers":[
        {
            "category":"Organizations",
            "subcategory":"Religious Organization",
            "type":"Services"
        }
    ],
    "sg:phone":"+1 510 428 2515",
    "sg:postcode":"94608",
    "sg:province":"CA",
    "sg:tags":[
        "church"
    ],
    "wof:name":"Church Of Christ",
    "wof:placetype":"venue"
},
  "geometry": {"coordinates":[-122.281434,37.836456],"type":"Point"}
}