{
  "type": "Feature",
  "properties": {
    "iso:country":"US",
    "sg:address":"4112 Geary Blvd",
    "sg:city":"San Francisco",
    "sg:classifiers":[
        {
            "category":"Restaurant",
            "type":"Food & Drink"
        }
    ],
    "sg:menulink":"http://www.allmenus.com/ca/san-francisco/62773-sushi-rock-3/menu/",
    "sg:phone":"+1 415 386 6188",
    "sg:postcode":"94118",
    "sg:province":"CA",
    "sg:tags":[
        "sushi",
        "asian"
    ],
    "wof:name":"Sushi Rock #3",
    "wof:placetype":"venue"
},
  "geometry": {"coordinates":[-122.46345599999999,37.781179],"type":"Point"}
}