{
  "type": "Feature",
  "properties": {
    "addr:full":"5930 Cornerstone Ct San Diego CA 92121",
    "addr:housenumber":"5930",
    "addr:postcode":"92121",
    "addr:street":"Cornerstone Ct",
    "iso:country":"US",
    "sg:address":"5930 Cornerstone Ct",
    "sg:city":"San Diego",
    "sg:classifiers":[
        {
            "category":"Professional",
            "subcategory":"Engineering",
            "type":"Services"
        }
    ],
    "sg:phone":"+1 858 587 6693",
    "sg:postcode":"92121",
    "sg:province":"CA",
    "sg:tags":[
        "engineer"
    ],
    "wof:name":"Lovelace Engineering Inc",
    "wof:placetype":"venue"
},
  "geometry": {"coordinates":[-117.190991,32.895532],"type":"Point"}
}