{
  "type": "Feature",
  "properties": {
    "addr:full":"701 N Long Beach Blvd Compton CA 90221",
    "addr:housenumber":"701",
    "addr:postcode":"90221",
    "addr:street":"N Long Beach Blvd",
    "iso:country":"US",
    "sg:address":"701 N Long Beach Blvd",
    "sg:city":"Compton",
    "sg:classifiers":[
        {
            "category":"Organizations",
            "subcategory":"Religious Organization",
            "type":"Services"
        }
    ],
    "sg:phone":"+1 310 764 4867",
    "sg:postcode":"90221",
    "sg:province":"CA",
    "sg:tags":[
        "churches-baptist",
        "church"
    ],
    "wof:name":"Christ First Baptist Church",
    "wof:placetype":"venue"
},
  "geometry": {"coordinates":[-118.208,33.900902],"type":"Point"}
}