{
  "type": "Feature",
  "properties": {
    "addr:full":"1419 Tiffany Cir Roseville CA 95661",
    "addr:housenumber":"1419",
    "addr:postcode":"95661",
    "addr:street":"Tiffany Cir",
    "iso:country":"US",
    "sg:address":"1419 Tiffany Cir",
    "sg:city":"Roseville",
    "sg:classifiers":[
        {
            "category":"Social Services",
            "subcategory":"Adult Care",
            "type":"Services"
        }
    ],
    "sg:phone":"+1 916 774 6534",
    "sg:postcode":"95661",
    "sg:province":"CA",
    "sg:tags":[
        "home"
    ],
    "wof:name":"Valley Pines At Roseville",
    "wof:placetype":"venue"
},
  "geometry": {"coordinates":[-121.265451,38.735655],"type":"Point"}
}