{
  "type": "Feature",
  "properties": {
    "iso:country":"US",
    "sg:address":"7211 Garden Grove Blvd",
    "sg:city":"Garden Grove",
    "sg:classifiers":[
        {
            "category":"Manufacturing",
            "subcategory":"Tools & Machinery",
            "type":"Manufacturing & Wholesale Goods"
        }
    ],
    "sg:phone":"+1 714 891 8980",
    "sg:postcode":"92841",
    "sg:province":"CA",
    "sg:tags":[
        "industrial",
        "mfg"
    ],
    "wof:name":"Vas Tool & Engineering",
    "wof:placetype":"venue"
},
  "geometry": {"coordinates":[-118.005145,33.773787],"type":"Point"}
}