{
  "type": "Feature",
  "properties": {
    "iso:country":"US",
    "sg:address":"9595 Wilshire Blvd",
    "sg:city":"Beverly Hills",
    "sg:classifiers":[
        {
            "category":"Banks & Credit Unions",
            "subcategory":"Investment Brokerage",
            "type":"Services"
        }
    ],
    "sg:phone":"+1 310 300 8450",
    "sg:postcode":"90212",
    "sg:province":"CA",
    "wof:name":"Wilshire Quinn Capital",
    "wof:placetype":"venue"
},
  "geometry": {"coordinates":[-118.40342200000001,34.067055],"type":"Point"}
}