{
  "type": "Feature",
  "properties": {
    "iso:country":"US",
    "sg:address":"23645 El Toro Rd Ste C",
    "sg:city":"Lake Forest",
    "sg:classifiers":[
        {
            "category":"Shopping",
            "subcategory":"Computers & Home Electronics",
            "type":"Retail Goods"
        }
    ],
    "sg:phone":"+1 949 206 0152",
    "sg:postcode":"92630",
    "sg:province":"CA",
    "sg:website":"www.batteriesplus.com",
    "wof:name":"Batteries Plus",
    "wof:placetype":"venue"
},
  "geometry": {"coordinates":[-117.70345399999999,33.61829],"type":"Point"}
}