{
  "type": "Feature",
  "properties": {
    "addr:full":"1008 15th St San Diego CA 92154",
    "addr:housenumber":"1008",
    "addr:postcode":"92154",
    "addr:street":"15Th St",
    "iso:country":"US",
    "sg:address":"1008 15th St",
    "sg:city":"San Diego",
    "sg:classifiers":[
        {
            "category":"Organizations",
            "subcategory":"Religious Organization",
            "type":"Services"
        }
    ],
    "sg:phone":"+1 619 429 7518",
    "sg:postcode":"92154",
    "sg:province":"CA",
    "sg:tags":[
        "church"
    ],
    "wof:name":"Jehovah's Witnesses Operating",
    "wof:placetype":"venue"
},
  "geometry": {"coordinates":[-117.101403,32.578594],"type":"Point"}
}