{
  "type": "Feature",
  "properties": {
    "iso:country":"US",
    "sg:address":"4542 Florin Rd",
    "sg:city":"Sacramento",
    "sg:classifiers":[
        {
            "category":"Shopping",
            "subcategory":"Books",
            "type":"Retail Goods"
        }
    ],
    "sg:phone":"+1 916 428 0932",
    "sg:postcode":"95823",
    "sg:province":"CA",
    "sg:tags":[
        "dealer"
    ],
    "wof:name":"Bookshelf",
    "wof:placetype":"venue"
},
  "geometry": {"coordinates":[-121.453024,38.495981],"type":"Point"}
}