{
  "type": "Feature",
  "properties": {
    "iso:country":"US",
    "sg:address":"1572 Sycamore Ave",
    "sg:city":"Hercules",
    "sg:classifiers":[
        {
            "category":"Building & Trades",
            "subcategory":"Electrical",
            "type":"Services"
        }
    ],
    "sg:phone":"+1 510 799 4848",
    "sg:postcode":"94547",
    "sg:province":"CA",
    "sg:tags":[
        "electrical",
        "electric",
        "contractor"
    ],
    "wof:name":"Hercules Electric",
    "wof:placetype":"venue"
},
  "geometry": {"coordinates":[-122.27018099999999,38.009064],"type":"Point"}
}