{
  "type": "Feature",
  "properties": {
    "addr:full":"19800 MacArthur Boulevard Irvine CA 92612",
    "addr:housenumber":"19800",
    "addr:postcode":"92612",
    "addr:street":"Macarthur Boulevard",
    "iso:country":"US",
    "sg:address":"19800 MacArthur Boulevard",
    "sg:city":"Irvine",
    "sg:classifiers":[
        {
            "category":"Professional",
            "subcategory":"Lawyer & Legal Services",
            "type":"Services"
        }
    ],
    "sg:phone":"+1 949 263 0004",
    "sg:postcode":"92612",
    "sg:province":"CA",
    "wof:name":"Samuels Green Steel & Adams",
    "wof:placetype":"venue"
},
  "geometry": {"coordinates":[-117.86219199999999,33.655666],"type":"Point"}
}