{
  "type": "Feature",
  "properties": {
    "iso:country":"US",
    "sg:address":"1001 N Beverly Glen Blvd",
    "sg:city":"Los Angeles",
    "sg:classifiers":[
        {
            "category":"Building & Trades",
            "subcategory":"Construction",
            "type":"Services"
        }
    ],
    "sg:phone":"+1 310 475 2704",
    "sg:postcode":"90077",
    "sg:province":"CA",
    "sg:tags":[
        "house"
    ],
    "wof:name":"Stiebinger Const",
    "wof:placetype":"venue"
},
  "geometry": {"coordinates":[-118.440701,34.094563],"type":"Point"}
}