{
  "type": "Feature",
  "properties": {
    "addr:full":"1001 E 1st St Los Angeles CA 90012",
    "addr:housenumber":"1001",
    "addr:postcode":"90012",
    "addr:street":"E 1St St",
    "iso:country":"US",
    "sg:address":"1001 E 1st St",
    "sg:city":"Los Angeles",
    "sg:classifiers":[
        {
            "category":"Professional",
            "subcategory":"Computer Services",
            "type":"Services"
        }
    ],
    "sg:phone":"+1 818 702 8038",
    "sg:postcode":"90012",
    "sg:province":"CA",
    "sg:tags":[
        "website",
        "design"
    ],
    "wof:name":"L A Design Group",
    "wof:placetype":"venue"
},
  "geometry": {"coordinates":[-118.231032,34.048047],"type":"Point"}
}