{
  "type": "Feature",
  "properties": {
    "addr:full":"794 Dorothy St El Cajon CA 92019",
    "addr:housenumber":"794",
    "addr:postcode":"92019",
    "addr:street":"Dorothy St",
    "iso:country":"US",
    "sg:address":"794 Dorothy St",
    "sg:city":"El Cajon",
    "sg:classifiers":[
        {
            "category":"Health Services",
            "subcategory":"Nursing And Care Facility",
            "type":"Services"
        }
    ],
    "sg:phone":"+1 619 444 8270",
    "sg:postcode":"92019",
    "sg:province":"CA",
    "sg:tags":[
        "home",
        "convalescent"
    ],
    "wof:name":"Lo-Har Lodge & Residence",
    "wof:placetype":"venue"
},
  "geometry": {"coordinates":[-116.933694,32.787569],"type":"Point"}
}