{
  "type": "Feature",
  "properties": {
    "iso:country":"US",
    "sg:address":"8325 Arroyo Cir",
    "sg:city":"Gilroy",
    "sg:classifiers":[
        {
            "category":"Shopping",
            "subcategory":"Department Store",
            "type":"Retail Goods"
        },
        {
            "category":"Shopping",
            "subcategory":"Clothing, Apparel, & Fashions",
            "type":"Retail Goods"
        }
    ],
    "sg:phone":"+1 408 842 3696",
    "sg:postcode":"95020",
    "sg:province":"CA",
    "sg:tags":[
        "clothing"
    ],
    "wof:name":"Izod",
    "wof:placetype":"venue"
},
  "geometry": {"coordinates":[-121.562861,37.023158],"type":"Point"}
}