{
  "type": "Feature",
  "properties": {
    "iso:country":"US",
    "sg:address":"1641 E 17th St",
    "sg:city":"Santa Ana",
    "sg:classifiers":[
        {
            "category":"Professional",
            "type":"Services"
        },
        {
            "category":"Real Estate",
            "subcategory":"Real Estate Agent",
            "type":"Services"
        }
    ],
    "sg:phone":"+1 714 973 2272",
    "sg:postcode":"92705",
    "sg:province":"CA",
    "wof:name":"Casa Grande Real Estate",
    "wof:placetype":"venue"
},
  "geometry": {"coordinates":[-117.844593,33.760011],"type":"Point"}
}