{
  "type": "Feature",
  "properties": {
    "addr:full":"826 E Cota St Santa Barbara CA 93103",
    "addr:housenumber":"826",
    "addr:postcode":"93103",
    "addr:street":"E Cota St",
    "iso:country":"US",
    "sg:address":"826 E Cota St",
    "sg:city":"Santa Barbara",
    "sg:classifiers":[
        {
            "category":"Recreation",
            "type":"Entertainment"
        }
    ],
    "sg:phone":"+1 805 962 4741",
    "sg:postcode":"93103",
    "sg:province":"CA",
    "sg:tags":[
        "martial",
        "arts",
        "instruction"
    ],
    "sg:website":"www.aikidoofsantabarbara.org",
    "wof:name":"Aikido Of Santa Barbara",
    "wof:placetype":"venue"
},
  "geometry": {"coordinates":[-119.68680999999999,34.426932],"type":"Point"}
}