{
  "type": "Feature",
  "properties": {
    "addr:full":"307 Natoma St Folsom CA 95630",
    "addr:housenumber":"307",
    "addr:postcode":"95630",
    "addr:street":"Natoma St",
    "iso:country":"US",
    "sg:address":"307 Natoma St",
    "sg:city":"Folsom",
    "sg:classifiers":[
        {
            "category":"Professional",
            "subcategory":"Accounting & Tax Preparation",
            "type":"Services"
        }
    ],
    "sg:phone":"+1 916 985 8962",
    "sg:postcode":"95630",
    "sg:province":"CA",
    "sg:tags":[
        "return",
        "filing"
    ],
    "wof:name":"Tax Connection",
    "wof:placetype":"venue"
},
  "geometry": {"coordinates":[-121.17001,38.67765],"type":"Point"}
}