{
  "type": "Feature",
  "properties": {
    "addr:full":"841 S 46th St Richmond CA 94804",
    "addr:housenumber":"841",
    "addr:postcode":"94804",
    "addr:street":"S 46Th St",
    "iso:country":"US",
    "sg:address":"841 S 46th St",
    "sg:city":"Richmond",
    "sg:classifiers":[
        {
            "category":"Building & Trades",
            "subcategory":"Electrical",
            "type":"Services"
        }
    ],
    "sg:phone":"+1 510 236 9406",
    "sg:postcode":"94804",
    "sg:province":"CA",
    "sg:tags":[
        "electrical",
        "contractor"
    ],
    "wof:name":"Daryl S Electric",
    "wof:placetype":"venue"
},
  "geometry": {"coordinates":[-122.328126,37.919054],"type":"Point"}
}