{
  "type": "Feature",
  "properties": {
    "iso:country":"US",
    "sg:address":"16161 Arena Dr",
    "sg:city":"Ramona",
    "sg:classifiers":[
        {
            "category":"Social Services",
            "subcategory":"Child Care",
            "type":"Services"
        }
    ],
    "sg:phone":"+1 760 789 7601",
    "sg:postcode":"92065",
    "sg:province":"CA",
    "wof:name":"Classic Design Group",
    "wof:placetype":"venue"
},
  "geometry": {"coordinates":[-116.819051,33.008054],"type":"Point"}
}