{
  "type": "Feature",
  "properties": {
    "iso:country":"US",
    "sg:address":"320 N Sheridan Ave",
    "sg:city":"Manteca",
    "sg:classifiers":[
        {
            "category":"Manufacturing",
            "subcategory":"Buildings",
            "type":"Manufacturing & Wholesale Goods"
        },
        {
            "category":"Building & Trades",
            "subcategory":"Construction",
            "type":"Services"
        }
    ],
    "sg:phone":"+1 209 823 2269",
    "sg:postcode":"95336",
    "sg:province":"CA",
    "sg:tags":[
        "home",
        "builder",
        "contractor"
    ],
    "wof:name":"Dias Cesar Home Repair & Improvements",
    "wof:placetype":"venue"
},
  "geometry": {"coordinates":[-121.20634200000001,37.801528],"type":"Point"}
}