{
  "type": "Feature",
  "properties": {
    "addr:full":"1746 Junction Avenue Suite A San Jose CA 95112",
    "addr:housenumber":"1746",
    "addr:postcode":"95112",
    "addr:street":"Junction Avenue Suite A",
    "iso:country":"US",
    "sg:address":"1746 Junction Avenue Suite A",
    "sg:city":"San Jose",
    "sg:classifiers":[
        {
            "category":"Shopping",
            "subcategory":"Stationery & Office Supplies",
            "type":"Retail Goods"
        }
    ],
    "sg:phone":"+1 408 451 6900",
    "sg:postcode":"95112",
    "sg:province":"CA",
    "sg:tags":[
        "equipment"
    ],
    "wof:name":"Hmac Corporate Services",
    "wof:placetype":"venue"
},
  "geometry": {"coordinates":[-121.904189,37.376495],"type":"Point"}
}