{
  "type": "Feature",
  "properties": {
    "addr:full":"4175 Sugar Pine Way Livermore CA 94551",
    "addr:housenumber":"4175",
    "addr:postcode":"94551",
    "addr:street":"Sugar Pine Way",
    "iso:country":"US",
    "sg:address":"4175 Sugar Pine Way",
    "sg:city":"Livermore",
    "sg:classifiers":[
        {
            "category":"Insurance",
            "subcategory":"Insurance Agent",
            "type":"Services"
        }
    ],
    "sg:phone":"+1 925 447 9189",
    "sg:postcode":"94551",
    "sg:province":"CA",
    "wof:name":"Spectrum Insurance & Financial",
    "wof:placetype":"venue"
},
  "geometry": {"coordinates":[-121.74968200000001,37.711582],"type":"Point"}
}