{
  "type": "Feature",
  "properties": {
    "iso:country":"US",
    "sg:address":"6329 Ventura St",
    "sg:city":"Sacramento",
    "sg:classifiers":[
        {
            "category":"Professional",
            "subcategory":"Detective & Security Services",
            "type":"Services"
        }
    ],
    "sg:phone":"+1 916 429 2020",
    "sg:postcode":"95822",
    "sg:province":"CA",
    "sg:tags":[
        "guard",
        "patrol"
    ],
    "wof:name":"Coherent Security Svc Inc",
    "wof:placetype":"venue"
},
  "geometry": {"coordinates":[-121.47900199999999,38.510786],"type":"Point"}
}