{
  "type": "Feature",
  "properties": {
    "addr:full":"7390 Pacific Ave Lemon Grove CA 91945",
    "addr:housenumber":"7390",
    "addr:postcode":"91945",
    "addr:street":"Pacific Ave",
    "iso:country":"US",
    "sg:address":"7390 Pacific Ave",
    "sg:city":"Lemon Grove",
    "sg:classifiers":[
        {
            "category":"Wholesale",
            "subcategory":"Machinery & Supplies",
            "type":"Manufacturing & Wholesale Goods"
        }
    ],
    "sg:phone":"+1 619 464 3444",
    "sg:postcode":"91945",
    "sg:province":"CA",
    "sg:tags":[
        "mach"
    ],
    "wof:name":"Del Cerro Distributors",
    "wof:placetype":"venue"
},
  "geometry": {"coordinates":[-117.03880599999999,32.741691],"type":"Point"}
}