{
  "type": "Feature",
  "properties": {
    "addr:full":"3 Dawes Ct Novato CA 94947",
    "addr:housenumber":"3",
    "addr:postcode":"94947",
    "addr:street":"Dawes Ct",
    "iso:country":"US",
    "sg:address":"3 Dawes Ct",
    "sg:city":"Novato",
    "sg:classifiers":[
        {
            "category":"Professional",
            "subcategory":"Art Services",
            "type":"Services"
        }
    ],
    "sg:phone":"+1 415 893 1416",
    "sg:postcode":"94947",
    "sg:province":"CA",
    "sg:tags":[
        "graphic",
        "designer"
    ],
    "wof:name":"Jewel Graphics",
    "wof:placetype":"venue"
},
  "geometry": {"coordinates":[-122.569542,38.090063],"type":"Point"}
}