{
  "type": "Feature",
  "properties": {
    "addr:full":"2071 Antioch Ct Oakland CA 94611",
    "addr:housenumber":"2071",
    "addr:postcode":"94611",
    "addr:street":"Antioch Ct",
    "iso:country":"US",
    "sg:address":"2071 Antioch Ct",
    "sg:city":"Oakland",
    "sg:classifiers":[
        {
            "category":"Recreation",
            "type":"Entertainment"
        }
    ],
    "sg:phone":"+1 510 339 6421",
    "sg:postcode":"94611",
    "sg:province":"CA",
    "sg:tags":[
        "instruction",
        "yoga"
    ],
    "sg:website":"mountainyoga.org",
    "wof:name":"Mountain Yoga & Massage",
    "wof:placetype":"venue"
},
  "geometry": {"coordinates":[-122.209,37.826],"type":"Point"}
}