{
  "type": "Feature",
  "properties": {
    "addr:full":"1210 66th St Sacramento CA 95819",
    "addr:housenumber":"1210",
    "addr:postcode":"95819",
    "addr:street":"66Th St",
    "iso:country":"US",
    "sg:address":"1210 66th St",
    "sg:city":"Sacramento",
    "sg:classifiers":[
        {
            "category":"Manufacturing",
            "subcategory":"Food",
            "type":"Manufacturing & Wholesale Goods"
        }
    ],
    "sg:phone":"+1 916 455 9630",
    "sg:postcode":"95819",
    "sg:province":"CA",
    "sg:tags":[
        "desert",
        "ice",
        "mfg"
    ],
    "wof:name":"Crystal Cream and Butter",
    "wof:placetype":"venue"
},
  "geometry": {"coordinates":[-121.426265,38.555059],"type":"Point"}
}