{
  "type": "Feature",
  "properties": {
    "iso:country":"US",
    "sg:address":"301 W. Washington Blvd",
    "sg:city":"Los Angeles",
    "sg:classifiers":[
        {
            "category":"Food Court",
            "type":"Food & Drink"
        },
        {
            "category":"Food & Beverages",
            "subcategory":"Ethnic Foods",
            "type":"Retail Goods"
        }
    ],
    "sg:postcode":"90015",
    "sg:province":"CA",
    "sg:tags":[
        "stand"
    ],
    "wof:name":"Bacon Wrapped Hot Dog Cart Guy",
    "wof:placetype":"venue"
},
  "geometry": {"coordinates":[-118.269138,34.033405],"type":"Point"}
}