{
  "type": "Feature",
  "properties": {
    "addr:full":"10114 Shoemaker Ave Santa Fe Springs CA 90670",
    "addr:housenumber":"10114",
    "addr:postcode":"90670",
    "addr:street":"Shoemaker Ave",
    "iso:country":"US",
    "sg:address":"10114 Shoemaker Ave",
    "sg:city":"Santa Fe Springs",
    "sg:classifiers":[
        {
            "category":"Building & Trades",
            "subcategory":"Construction",
            "type":"Services"
        }
    ],
    "sg:phone":"+1 562 906 9002",
    "sg:postcode":"90670",
    "sg:province":"CA",
    "sg:tags":[
        "commercial",
        "painting",
        "sandblasting",
        "waterproofing"
    ],
    "sg:website":"www.robison-prezioso.com",
    "wof:name":"Robison-Prezioso Inc",
    "wof:placetype":"venue"
},
  "geometry": {"coordinates":[-118.05511799999999,33.945125],"type":"Point"}
}