{
  "type": "Feature",
  "properties": {
    "iso:country":"US",
    "sg:address":"8340 Carmel Valley Rd",
    "sg:city":"Carmel",
    "sg:classifiers":[
        {
            "category":"Social Services",
            "subcategory":"Child Care",
            "type":"Services"
        }
    ],
    "sg:phone":"+1 831 625 2968",
    "sg:postcode":"93923",
    "sg:province":"CA",
    "sg:tags":[
        "kindergarten",
        "academic",
        "school"
    ],
    "wof:name":"A Child's View Montessori",
    "wof:placetype":"venue"
},
  "geometry": {"coordinates":[-121.82993999999999,36.529856],"type":"Point"}
}