{
  "type": "Feature",
  "properties": {
    "iso:country":"US",
    "sg:address":"711 S Oxnard Blvd",
    "sg:city":"Oxnard",
    "sg:classifiers":[
        {
            "category":"Banks & Credit Unions",
            "subcategory":"Bank",
            "type":"Services"
        }
    ],
    "sg:phone":"+1 805 486 8610",
    "sg:postcode":"93030",
    "sg:province":"CA",
    "sg:tags":[
        "loan"
    ],
    "wof:name":"Paramount Mortgage",
    "wof:placetype":"venue"
},
  "geometry": {"coordinates":[-119.177488,34.193833],"type":"Point"}
}