{
  "type": "Feature",
  "properties": {
    "iso:country":"US",
    "sg:address":"173 Rowland Ct",
    "sg:city":"Galt",
    "sg:classifiers":[
        {
            "category":"Building & Trades",
            "subcategory":"Construction",
            "type":"Services"
        }
    ],
    "sg:phone":"+1 209 744 8132",
    "sg:postcode":"95632",
    "sg:province":"CA",
    "sg:tags":[
        "contractor"
    ],
    "wof:name":"Bz Roofing",
    "wof:placetype":"venue"
},
  "geometry": {"coordinates":[-121.31307700000001,38.251641],"type":"Point"}
}