{
  "type": "Feature",
  "properties": {
    "addr:full":"1519 P St Sacramento CA 95814",
    "addr:housenumber":"1519 p",
    "addr:postcode":"95814",
    "addr:street":"St",
    "iso:country":"US",
    "sg:address":"1519 P St",
    "sg:city":"Sacramento",
    "sg:classifiers":[
        {
            "category":"Organizations",
            "subcategory":"Community Association",
            "type":"Services"
        }
    ],
    "sg:phone":"+1 916 448 3378",
    "sg:postcode":"95814",
    "sg:province":"CA",
    "wof:name":"Stanford Park Hoa",
    "wof:placetype":"venue"
},
  "geometry": {"coordinates":[-121.489198,38.571773],"type":"Point"}
}