{
  "type": "Feature",
  "properties": {
    "iso:country":"US",
    "sg:address":"7185 Navajo Rd",
    "sg:city":"San Diego",
    "sg:classifiers":[
        {
            "category":"Manufacturing",
            "subcategory":"Buildings",
            "type":"Manufacturing & Wholesale Goods"
        }
    ],
    "sg:phone":"+1 619 460 5714",
    "sg:postcode":"92119",
    "sg:province":"CA",
    "sg:tags":[
        "prefabricated",
        "wood",
        "mfg"
    ],
    "wof:name":"Log Home Castles",
    "wof:placetype":"venue"
},
  "geometry": {"coordinates":[-117.04351800000001,32.804503],"type":"Point"}
}