{
  "type": "Feature",
  "properties": {
    "addr:full":"1316 W Walnut Ave Visalia CA 93277",
    "addr:housenumber":"1316",
    "addr:postcode":"93277",
    "addr:street":"W Walnut Ave",
    "iso:country":"US",
    "sg:address":"1316 W Walnut Ave",
    "sg:city":"Visalia",
    "sg:classifiers":[
        {
            "category":"Retail",
            "subcategory":"Animal Services",
            "type":"Services"
        }
    ],
    "sg:phone":"+1 559 635 7297",
    "sg:postcode":"93277",
    "sg:province":"CA",
    "sg:tags":[
        "pet",
        "grooming",
        "washing"
    ],
    "wof:name":"Cc's Pet Salon",
    "wof:placetype":"venue"
},
  "geometry": {"coordinates":[-119.306882,36.313002],"type":"Point"}
}