{
  "type": "Feature",
  "properties": {
    "addr:full":"526 Marshall Ave Woodland CA 95695",
    "addr:housenumber":"526",
    "addr:postcode":"95695",
    "addr:street":"Marshall Ave",
    "iso:country":"US",
    "sg:address":"526 Marshall Ave",
    "sg:city":"Woodland",
    "sg:classifiers":[
        {
            "category":"Education",
            "subcategory":"Preschool",
            "type":"Public Place"
        }
    ],
    "sg:phone":"+1 530 661 0656",
    "sg:postcode":"95695",
    "sg:province":"CA",
    "sg:tags":[
        "kindergarten"
    ],
    "wof:name":"Flor-Evenstart Preschool Program",
    "wof:placetype":"venue"
},
  "geometry": {"coordinates":[-121.774394,38.667923],"type":"Point"}
}