{
  "type": "Feature",
  "properties": {
    "addr:full":"3500 Carson Road Camino CA 95709",
    "addr:housenumber":"3500",
    "addr:postcode":"95709",
    "addr:street":"Carson Road",
    "iso:country":"US",
    "sg:address":"3500 Carson Road",
    "sg:city":"Camino",
    "sg:classifiers":[
        {
            "category":"Winery",
            "type":"Food & Drink"
        }
    ],
    "sg:phone":"+1 530 647 8466",
    "sg:postcode":"95709",
    "sg:province":"CA",
    "wof:name":"Garnet Sun Winery",
    "wof:placetype":"venue"
},
  "geometry": {"coordinates":[-120.695948,38.740813],"type":"Point"}
}