{
  "type": "Feature",
  "properties": {
    "iso:country":"US",
    "sg:address":"2105 Beverly Blvd",
    "sg:city":"Los Angeles",
    "sg:classifiers":[
        {
            "category":"Health Services",
            "subcategory":"Doctor",
            "type":"Services"
        }
    ],
    "sg:phone":"+1 213 353 3600",
    "sg:postcode":"90057",
    "sg:province":"CA",
    "wof:name":"Lopez Horacio G Dr",
    "wof:placetype":"venue"
},
  "geometry": {"coordinates":[-118.269997,34.0667],"type":"Point"}
}