{
  "type": "Feature",
  "properties": {
    "addr:full":"1348 Jonathan Pl Tracy CA 95377",
    "addr:housenumber":"1348",
    "addr:postcode":"95377",
    "addr:street":"Jonathan Pl",
    "iso:country":"US",
    "sg:address":"1348 Jonathan Pl",
    "sg:city":"Tracy",
    "sg:classifiers":[
        {
            "category":"Building & Trades",
            "subcategory":"Landscaping Services",
            "type":"Services"
        }
    ],
    "sg:phone":"+1 209 835 6722",
    "sg:postcode":"95377",
    "sg:province":"CA",
    "sg:tags":[
        "lawn",
        "garden",
        "maintenance",
        "grounds"
    ],
    "wof:name":"John's Landscape Care",
    "wof:placetype":"venue"
},
  "geometry": {"coordinates":[-121.441166,37.705285],"type":"Point"}
}