{
  "type": "Feature",
  "properties": {
    "iso:country":"US",
    "sg:address":"4221 Wilshire Blvd",
    "sg:city":"Los Angeles",
    "sg:classifiers":[
        {
            "category":"Professional",
            "subcategory":"Secretarial Services",
            "type":"Services"
        }
    ],
    "sg:phone":"+1 323 964 9500",
    "sg:postcode":"90010",
    "sg:province":"CA",
    "sg:tags":[
        "convention",
        "court",
        "reporter"
    ],
    "wof:name":"Professional Court Reporters",
    "wof:placetype":"venue"
},
  "geometry": {"coordinates":[-118.31965,34.061813],"type":"Point"}
}