{
  "type": "Feature",
  "properties": {
    "addr:full":"2611 Deep Canyon Dr Beverly Hills CA 90210",
    "addr:housenumber":"2611",
    "addr:postcode":"90210",
    "addr:street":"Deep Canyon Dr",
    "iso:country":"US",
    "sg:address":"2611 Deep Canyon Dr",
    "sg:city":"Beverly Hills",
    "sg:classifiers":[
        {
            "category":"Professional",
            "type":"Services"
        }
    ],
    "sg:phone":"+1 310 276 0293",
    "sg:postcode":"90210",
    "sg:province":"CA",
    "wof:name":"Dan & Celia Cleary",
    "wof:placetype":"venue"
},
  "geometry": {"coordinates":[-118.431707,34.120366],"type":"Point"}
}