{
  "type": "Feature",
  "properties": {
    "iso:country":"US",
    "sg:address":"25178 Viejas Blvd",
    "sg:city":"Descanso",
    "sg:classifiers":[
        {
            "category":"Professional",
            "subcategory":"Detective & Security Services",
            "type":"Services"
        }
    ],
    "sg:phone":"+1 619 302 9308",
    "sg:postcode":"91916",
    "sg:province":"CA",
    "sg:tags":[
        "information",
        "bureau"
    ],
    "wof:name":"Td Notary Services",
    "wof:placetype":"venue"
},
  "geometry": {"coordinates":[-116.604949,32.85445],"type":"Point"}
}