{
  "type": "Feature",
  "properties": {
    "iso:country":"US",
    "sg:address":"23210 Crenshaw Blvd",
    "sg:city":"Torrance",
    "sg:classifiers":[
        {
            "category":"Building & Trades",
            "subcategory":"Construction",
            "type":"Services"
        }
    ],
    "sg:phone":"+1 310 530 3141",
    "sg:postcode":"90505",
    "sg:province":"CA",
    "sg:tags":[
        "contractor"
    ],
    "wof:name":"Archuleta Construction",
    "wof:placetype":"venue"
},
  "geometry": {"coordinates":[-118.327961,33.814479],"type":"Point"}
}