{
  "type": "Feature",
  "properties": {
    "iso:country":"US",
    "sg:address":"613 4th St",
    "sg:city":"Santa Rosa",
    "sg:classifiers":[
        {
            "category":"Professional",
            "subcategory":"Lawyer & Legal Services",
            "type":"Services"
        }
    ],
    "sg:phone":"+1 707 571 7400",
    "sg:postcode":"95404",
    "sg:province":"CA",
    "sg:tags":[
        "attorney"
    ],
    "wof:name":"Chalk Law Office",
    "wof:placetype":"venue"
},
  "geometry": {"coordinates":[-122.713618,38.440692],"type":"Point"}
}