{
  "type": "Feature",
  "properties": {
    "addr:full":"36445 Rd 172 Visalia CA 93292",
    "addr:postcode":"36445;93292",
    "addr:street":"Rd 172",
    "iso:country":"US",
    "sg:address":"36445 Rd 172",
    "sg:city":"Visalia",
    "sg:classifiers":[
        {
            "category":"Professional",
            "type":"Services"
        }
    ],
    "sg:phone":"+1 559 798 3100",
    "sg:postcode":"93292",
    "sg:province":"CA",
    "sg:tags":[
        "establishment"
    ],
    "wof:name":"Paramount Citrus",
    "wof:placetype":"venue"
},
  "geometry": {"coordinates":[-119.188721,36.4565],"type":"Point"}
}