{
  "type": "Feature",
  "properties": {
    "addr:full":"2031 Alameda Ste 202 Burbank CA 91506",
    "addr:housenumber":"2031",
    "addr:postcode":"91506",
    "addr:street":"Alameda Ste 202",
    "iso:country":"US",
    "sg:address":"2031 Alameda Ste 202",
    "sg:city":"Burbank",
    "sg:classifiers":[
        {
            "category":"Health Services",
            "subcategory":"Clinic",
            "type":"Services"
        }
    ],
    "sg:postcode":"91506",
    "sg:province":"CA",
    "sg:tags":[
        "medical"
    ],
    "wof:name":"Fresenius Dialysis",
    "wof:placetype":"venue"
},
  "geometry": {"coordinates":[-118.323815,34.159976],"type":"Point"}
}