{
  "type": "Feature",
  "properties": {
    "addr:full":"11470 6th St Rancho Cucamonga CA 91730",
    "addr:housenumber":"11470",
    "addr:postcode":"91730",
    "addr:street":"6Th St",
    "iso:country":"US",
    "sg:address":"11470 6th St",
    "sg:city":"Rancho Cucamonga",
    "sg:classifiers":[
        {
            "category":"Professional",
            "type":"Services"
        }
    ],
    "sg:phone":"+1 909 987 6553",
    "sg:postcode":"91730",
    "sg:province":"CA",
    "sg:tags":[
        "establishment"
    ],
    "wof:name":"Light Concern",
    "wof:placetype":"venue"
},
  "geometry": {"coordinates":[-117.55364299999999,34.084659],"type":"Point"}
}