{
  "type": "Feature",
  "properties": {
    "addr:full":"8959 Canoga Ave Canoga Park CA 91304",
    "addr:housenumber":"8959",
    "addr:postcode":"91304",
    "addr:street":"Canoga Ave",
    "iso:country":"US",
    "sg:address":"8959 Canoga Ave",
    "sg:city":"Canoga Park",
    "sg:classifiers":[
        {
            "category":"Wholesale",
            "subcategory":"Construction Materials",
            "type":"Manufacturing & Wholesale Goods"
        }
    ],
    "sg:phone":"+1 818 678 6999",
    "sg:postcode":"91304",
    "sg:province":"CA",
    "sg:tags":[
        "tile"
    ],
    "sg:website":"www.tilecollection.net",
    "wof:name":"Tile Collection",
    "wof:placetype":"venue"
},
  "geometry": {"coordinates":[-118.597606,34.231581],"type":"Point"}
}