{
  "type": "Feature",
  "properties": {
    "iso:country":"US",
    "sg:address":"27350 Valley Center Rd",
    "sg:city":"Valley Center",
    "sg:classifiers":[
        {
            "category":"Shopping",
            "type":"Retail Goods"
        }
    ],
    "sg:phone":"+1 760 749 9328",
    "sg:postcode":"92082",
    "sg:province":"CA",
    "sg:tags":[
        "farm",
        "merchandise",
        "crop",
        "supply"
    ],
    "wof:name":"Terrys Hay and Grain",
    "wof:placetype":"venue"
},
  "geometry": {"coordinates":[-117.033507,33.206652],"type":"Point"}
}