{
  "type": "Feature",
  "properties": {
    "iso:country":"US",
    "sg:address":"31401 Outer Hwy 10 S",
    "sg:city":"Redlands",
    "sg:classifiers":[
        {
            "category":"Farming",
            "subcategory":"Farm",
            "type":"Manufacturing & Wholesale Goods"
        }
    ],
    "sg:phone":"+1 909 794 0600",
    "sg:postcode":"92373",
    "sg:province":"CA",
    "sg:tags":[
        "crop",
        "general"
    ],
    "wof:name":"Dale Daniels",
    "wof:placetype":"venue"
},
  "geometry": {"coordinates":[-117.115282,34.024892],"type":"Point"}
}