{
  "type": "Feature",
  "properties": {
    "addr:full":"3919 Rigali Ave Los Angeles CA 90039",
    "addr:housenumber":"3919",
    "addr:postcode":"90039",
    "addr:street":"Rigali Ave",
    "iso:country":"US",
    "sg:address":"3919 Rigali Ave",
    "sg:city":"Los Angeles",
    "sg:classifiers":[
        {
            "category":"Retail",
            "subcategory":"Animal Services",
            "type":"Services"
        }
    ],
    "sg:phone":"+1 323 664 0006",
    "sg:postcode":"90039",
    "sg:province":"CA",
    "sg:tags":[
        "horse",
        "training"
    ],
    "wof:name":"Renee Baker Performance Horses",
    "wof:placetype":"venue"
},
  "geometry": {"coordinates":[-118.27090800000001,34.128335],"type":"Point"}
}