{
  "type": "Feature",
  "properties": {
    "addr:full":"1400 E Saint Andrew Pl Santa Ana CA 92705",
    "addr:housenumber":"1400",
    "addr:postcode":"92705",
    "addr:street":"E Saint Andrew Pl",
    "iso:country":"US",
    "sg:address":"1400 E Saint Andrew Pl",
    "sg:city":"Santa Ana",
    "sg:classifiers":[
        {
            "category":"Shopping",
            "subcategory":"Used Merchandise",
            "type":"Retail Goods"
        }
    ],
    "sg:phone":"+1 714 540 8152",
    "sg:postcode":"92705",
    "sg:province":"CA",
    "wof:name":"Andina Distributing Co",
    "wof:placetype":"venue"
},
  "geometry": {"coordinates":[-117.852183,33.722882],"type":"Point"}
}