{
  "type": "Feature",
  "properties": {
    "iso:country":"US",
    "sg:address":"2375 Davis St",
    "sg:city":"San Leandro",
    "sg:classifiers":[
        {
            "category":"Wholesale",
            "subcategory":"Hardware",
            "type":"Manufacturing & Wholesale Goods"
        }
    ],
    "sg:phone":"+1 510 777 9037",
    "sg:postcode":"94577",
    "sg:province":"CA",
    "sg:tags":[
        "air",
        "parts",
        "conditioning",
        "supply"
    ],
    "wof:name":"Baker Distributing 600",
    "wof:placetype":"venue"
},
  "geometry": {"coordinates":[-122.19081199999999,37.715109],"type":"Point"}
}