{
  "type": "Feature",
  "properties": {
    "addr:full":"230 S Madison Ave Apt 204 Pasadena CA 91101",
    "addr:housenumber":"230;204",
    "addr:postcode":"91101",
    "addr:street":"S Madison Ave Apt",
    "iso:country":"US",
    "sg:address":"230 S Madison Ave Apt 204",
    "sg:city":"Pasadena",
    "sg:classifiers":[
        {
            "category":"Personal",
            "type":"Services"
        }
    ],
    "sg:phone":"+1 626 440 0270",
    "sg:postcode":"91101",
    "sg:province":"CA",
    "sg:tags":[
        "party",
        "planning",
        "event"
    ],
    "wof:name":"Lucky Star Productions",
    "wof:placetype":"venue"
},
  "geometry": {"coordinates":[-118.13800000000001,34.141899],"type":"Point"}
}