{
  "type": "Feature",
  "properties": {
    "addr:full":"16535 Dam Rd Clearlake CA 95422",
    "addr:housenumber":"16535",
    "addr:postcode":"95422",
    "addr:street":"Dam Rd",
    "iso:country":"US",
    "sg:address":"16535 Dam Rd",
    "sg:city":"Clearlake",
    "sg:classifiers":[
        {
            "category":"Freight",
            "type":"Transportation"
        }
    ],
    "sg:phone":"+1 707 994 6173",
    "sg:postcode":"95422",
    "sg:province":"CA",
    "sg:tags":[
        "mobile",
        "home",
        "general",
        "mfg"
    ],
    "wof:name":"Cache Creek Mobil Home Estates",
    "wof:placetype":"venue"
},
  "geometry": {"coordinates":[-122.60291599999999,38.924831],"type":"Point"}
}