{
  "type": "Feature",
  "properties": {
    "iso:country":"US",
    "sg:address":"1308 Sartori Ave",
    "sg:city":"Torrance",
    "sg:classifiers":[
        {
            "category":"Real Estate",
            "subcategory":"Real Estate Agent",
            "type":"Services"
        }
    ],
    "sg:phone":"+1 310 328 9120",
    "sg:postcode":"90501",
    "sg:province":"CA",
    "wof:name":"Pacific Brokers",
    "wof:placetype":"venue"
},
  "geometry": {"coordinates":[-118.314804,33.834408],"type":"Point"}
}