{
  "type": "Feature",
  "properties": {
    "addr:full":"2039 Harmony Way Vista CA 92081",
    "addr:housenumber":"2039",
    "addr:postcode":"92081",
    "addr:street":"Harmony Way",
    "iso:country":"US",
    "sg:address":"2039 Harmony Way",
    "sg:city":"Vista",
    "sg:classifiers":[
        {
            "category":"Wholesale",
            "subcategory":"Meat",
            "type":"Manufacturing & Wholesale Goods"
        }
    ],
    "sg:phone":"+1 760 598 2362",
    "sg:postcode":"92081",
    "sg:province":"CA",
    "sg:tags":[
        "meat-wholesale"
    ],
    "wof:name":"Fat Cat Consulting Inc",
    "wof:placetype":"venue"
},
  "geometry": {"coordinates":[-117.247978,33.159531],"type":"Point"}
}