{
  "type": "Feature",
  "properties": {
    "iso:country":"US",
    "sg:address":"1430 Mardan Dr",
    "sg:city":"San Jose",
    "sg:classifiers":[
        {
            "category":"Shopping",
            "subcategory":"Computers & Home Electronics",
            "type":"Retail Goods"
        }
    ],
    "sg:phone":"+1 408 960 2030",
    "sg:postcode":"95132",
    "sg:province":"CA",
    "sg:website":"www.dishnetwork.com",
    "wof:name":"DISH Network",
    "wof:placetype":"venue"
},
  "geometry": {"coordinates":[-121.853425,37.405296],"type":"Point"}
}