{
  "type": "Feature",
  "properties": {
    "addr:full":"350 Raleys Towne Ctr Rohnert Park CA 94928",
    "addr:housenumber":"350",
    "addr:postcode":"94928",
    "addr:street":"Raleys Towne Ctr",
    "iso:country":"US",
    "sg:address":"350 Raleys Towne Ctr",
    "sg:city":"Rohnert Park",
    "sg:classifiers":[
        {
            "category":"Restaurant",
            "type":"Food & Drink"
        }
    ],
    "sg:menulink":"http://www.allmenus.com/ca/petaluma/52916-port-of-subs/menu/",
    "sg:phone":"+1 707 584 3839",
    "sg:postcode":"94928",
    "sg:province":"CA",
    "sg:tags":[
        "wrap",
        "american",
        "sandwich"
    ],
    "wof:name":"Port of Subs",
    "wof:placetype":"venue"
},
  "geometry": {"coordinates":[-122.707139,38.347637],"type":"Point"}
}