{
  "type": "Feature",
  "properties": {
    "addr:full":"214 Main St El Segundo CA 90245",
    "addr:housenumber":"214",
    "addr:postcode":"90245",
    "addr:street":"Main St",
    "iso:country":"US",
    "sg:address":"214 Main St",
    "sg:city":"El Segundo",
    "sg:classifiers":[
        {
            "category":"Retail",
            "subcategory":"Auto Repair",
            "type":"Services"
        }
    ],
    "sg:phone":"+1 310 333 0733",
    "sg:postcode":"90245",
    "sg:province":"CA",
    "wof:name":"Kaiser Brothers",
    "wof:placetype":"venue"
},
  "geometry": {"coordinates":[-118.415761,33.918046],"type":"Point"}
}