{
  "type": "Feature",
  "properties": {
    "addr:full":"1257 Tasman Dr Sunnyvale CA 94089",
    "addr:housenumber":"1257",
    "addr:postcode":"94089",
    "addr:street":"Tasman Dr",
    "iso:country":"US",
    "sg:address":"1257 Tasman Dr",
    "sg:city":"Sunnyvale",
    "sg:classifiers":[
        {
            "category":"Manufacturing",
            "subcategory":"Electronics",
            "type":"Manufacturing & Wholesale Goods"
        }
    ],
    "sg:phone":"+1 408 543 0051",
    "sg:postcode":"94089",
    "sg:province":"CA",
    "sg:tags":[
        "equipment",
        "electronic",
        "supply"
    ],
    "wof:name":"Applied Engineering Inc",
    "wof:placetype":"venue"
},
  "geometry": {"coordinates":[-121.99548900000001,37.403254],"type":"Point"}
}