{
  "type": "Feature",
  "properties": {
    "iso:country":"US",
    "sg:address":"1951 Artesia Blvd",
    "sg:city":"Redondo Beach",
    "sg:classifiers":[
        {
            "category":"Home & Garden",
            "subcategory":"Building Materials",
            "type":"Retail Goods"
        }
    ],
    "sg:phone":"+1 310 937 4527",
    "sg:postcode":"90278",
    "sg:province":"CA",
    "sg:tags":[
        "windows"
    ],
    "wof:name":"Hermosa Glass & Mirror",
    "wof:placetype":"venue"
},
  "geometry": {"coordinates":[-118.376942,33.872828],"type":"Point"}
}