{
  "type": "Feature",
  "properties": {
    "iso:country":"US",
    "sg:address":"4335 W Adams Blvd",
    "sg:city":"Los Angeles",
    "sg:classifiers":[
        {
            "category":"Organizations",
            "subcategory":"Religious Organization",
            "type":"Services"
        }
    ],
    "sg:phone":"+1 323 734 3026",
    "sg:postcode":"90018",
    "sg:province":"CA",
    "sg:tags":[
        "church"
    ],
    "wof:name":"Iglesia De Dios Pentecostal",
    "wof:placetype":"venue"
},
  "geometry": {"coordinates":[-118.333047,34.032662],"type":"Point"}
}