{
  "type": "Feature",
  "properties": {
    "addr:full":"3620 Patrick Henry Pl Agoura Hills CA 91301",
    "addr:housenumber":"3620",
    "addr:postcode":"91301",
    "addr:street":"Patrick Henry Pl",
    "iso:country":"US",
    "sg:address":"3620 Patrick Henry Pl",
    "sg:city":"Agoura Hills",
    "sg:classifiers":[
        {
            "category":"Manufacturing",
            "subcategory":"Tools & Machinery",
            "type":"Manufacturing & Wholesale Goods"
        }
    ],
    "sg:phone":"+1 818 707 3226",
    "sg:postcode":"91301",
    "sg:province":"CA",
    "sg:tags":[
        "industry",
        "mfg"
    ],
    "wof:name":"Berke Glass",
    "wof:placetype":"venue"
},
  "geometry": {"coordinates":[-118.72310299999999,34.127479],"type":"Point"}
}