{
  "type": "Feature",
  "properties": {
    "addr:full":"326 E Santa Clara St San Jose CA 95113",
    "addr:housenumber":"326",
    "addr:postcode":"95113",
    "addr:street":"E Santa Clara St",
    "iso:country":"US",
    "sg:address":"326 E Santa Clara St",
    "sg:city":"San Jose",
    "sg:classifiers":[
        {
            "category":"Professional",
            "subcategory":"Printing & Photocopies",
            "type":"Services"
        }
    ],
    "sg:phone":"+1 408 294 6715",
    "sg:postcode":"95113",
    "sg:province":"CA",
    "sg:website":"www.thecopyit.com",
    "wof:name":"Copy It",
    "wof:placetype":"venue"
},
  "geometry": {"coordinates":[-121.883674,37.339436],"type":"Point"}
}