{
  "type": "Feature",
  "properties": {
    "iso:country":"US",
    "sg:address":"1870 El Camino Real",
    "sg:city":"Burlingame",
    "sg:classifiers":[
        {
            "category":"Travel",
            "subcategory":"Travel Agent",
            "type":"Entertainment"
        }
    ],
    "sg:phone":"+1 650 259 8288",
    "sg:postcode":"94010",
    "sg:province":"CA",
    "sg:tags":[
        "agency",
        "services-commercial"
    ],
    "wof:name":"Teamwork Travel Services",
    "wof:placetype":"venue"
},
  "geometry": {"coordinates":[-122.38475800000001,37.596222],"type":"Point"}
}