{
  "type": "Feature",
  "properties": {
    "iso:country":"US",
    "sg:address":"1923 E Hungerford St",
    "sg:city":"Long Beach",
    "sg:classifiers":[
        {
            "category":"Food & Beverages",
            "subcategory":"Groceries & Convenience Stores",
            "type":"Retail Goods"
        }
    ],
    "sg:phone":"+1 562 422 6915",
    "sg:postcode":"90805",
    "sg:province":"CA",
    "sg:tags":[
        "market"
    ],
    "wof:name":"Thai Number 1 Market",
    "wof:placetype":"venue"
},
  "geometry": {"coordinates":[-118.168794,33.862931],"type":"Point"}
}