{
  "type": "Feature",
  "properties": {
    "iso:country":"US",
    "sg:address":"133 S Thompson Ave",
    "sg:city":"Nipomo",
    "sg:phone":"+1 805 931 0273",
    "sg:postcode":"93444",
    "sg:province":"CA",
    "sg:website":"http://www.tahliascucina.com",
    "wof:name":"Tahlia's Cucina",
    "wof:placetype":"venue"
},
  "geometry": {"coordinates":[-120.47537699999999,35.042351],"type":"Point"}
}