{
  "type": "Feature",
  "properties": {
    "addr:full":"3160 Samantha Dr Santa Ynez CA 93460",
    "addr:housenumber":"3160",
    "addr:postcode":"93460",
    "addr:street":"Samantha Dr",
    "iso:country":"US",
    "sg:address":"3160 Samantha Dr",
    "sg:city":"Santa Ynez",
    "sg:classifiers":[
        {
            "category":"Professional",
            "subcategory":"Management & Consulting",
            "type":"Services"
        }
    ],
    "sg:phone":"+1 805 693 0518",
    "sg:postcode":"93460",
    "sg:province":"CA",
    "sg:tags":[
        "fuel"
    ],
    "wof:name":"Ameritrust Capital Management",
    "wof:placetype":"venue"
},
  "geometry": {"coordinates":[-120.094812,34.620048],"type":"Point"}
}