{
  "type": "Feature",
  "properties": {
    "iso:country":"US",
    "sg:address":"6055 University Ave",
    "sg:city":"San Diego",
    "sg:classifiers":[
        {
            "category":"Wholesale",
            "subcategory":"Groceries",
            "type":"Manufacturing & Wholesale Goods"
        }
    ],
    "sg:phone":"+1 619 287 1142",
    "sg:postcode":"92115",
    "sg:province":"CA",
    "sg:tags":[
        "food",
        "broker"
    ],
    "wof:name":"L & A Distrubotrs",
    "wof:placetype":"venue"
},
  "geometry": {"coordinates":[-117.065626,32.752368],"type":"Point"}
}