{
  "type": "Feature",
  "properties": {
    "addr:full":"104 E Olive Ave Redlands CA 92373",
    "addr:housenumber":"104",
    "addr:postcode":"92373",
    "addr:street":"E Olive Ave",
    "iso:country":"US",
    "sg:address":"104 E Olive Ave",
    "sg:city":"Redlands",
    "sg:classifiers":[
        {
            "category":"Banks & Credit Unions",
            "subcategory":"Bank",
            "type":"Services"
        }
    ],
    "sg:phone":"+1 909 307 8621",
    "sg:postcode":"92373",
    "sg:province":"CA",
    "sg:tags":[
        "depository",
        "banking"
    ],
    "wof:name":"Advantage Escrow",
    "wof:placetype":"venue"
},
  "geometry": {"coordinates":[-117.179897,34.054108],"type":"Point"}
}