{
  "type": "Feature",
  "properties": {
    "iso:country":"US",
    "sg:address":"1734 Edgewood Dr",
    "sg:city":"Lodi",
    "sg:classifiers":[
        {
            "category":"Real Estate",
            "subcategory":"Real Estate Agent",
            "type":"Services"
        }
    ],
    "sg:phone":"+1 209 334 0453",
    "sg:postcode":"95240",
    "sg:province":"CA",
    "wof:name":"L K Weeks Inc",
    "wof:placetype":"venue"
},
  "geometry": {"coordinates":[-121.28715,38.150818],"type":"Point"}
}