{
  "type": "Feature",
  "properties": {
    "iso:country":"US",
    "sg:address":"9153 Las Tunas Dr",
    "sg:city":"Temple City",
    "sg:classifiers":[
        {
            "category":"Health Services",
            "subcategory":"Chiropractor",
            "type":"Services"
        }
    ],
    "sg:phone":"+1 626 286 8433",
    "sg:postcode":"91780",
    "sg:province":"CA",
    "wof:name":"Cca-San Gabriel Valley Dist",
    "wof:placetype":"venue"
},
  "geometry": {"coordinates":[-118.069,34.105598],"type":"Point"}
}