{
  "type": "Feature",
  "properties": {
    "iso:country":"US",
    "sg:address":"1615 Via Sage",
    "sg:city":"San Clemente",
    "sg:classifiers":[
        {
            "category":"Professional",
            "type":"Services"
        }
    ],
    "sg:phone":"+1 949 498 5998",
    "sg:postcode":"92673",
    "sg:province":"CA",
    "wof:name":"William Johnson",
    "wof:placetype":"venue"
},
  "geometry": {"coordinates":[-117.62803099999999,33.472618],"type":"Point"}
}