{
  "type": "Feature",
  "properties": {
    "addr:full":"435 Venture St Escondido CA 92029",
    "addr:housenumber":"435",
    "addr:postcode":"92029",
    "addr:street":"Venture St",
    "iso:country":"US",
    "sg:address":"435 Venture St",
    "sg:city":"Escondido",
    "sg:classifiers":[
        {
            "category":"Building & Trades",
            "subcategory":"Construction",
            "type":"Services"
        }
    ],
    "sg:phone":"+1 760 489 7155",
    "sg:postcode":"92029",
    "sg:province":"CA",
    "sg:tags":[
        "wooden",
        "cabinetry",
        "custom",
        "craft",
        "other",
        "manufacturer"
    ],
    "wof:name":"Total Quality Products",
    "wof:placetype":"venue"
},
  "geometry": {"coordinates":[-117.112836,33.123326],"type":"Point"}
}