{
  "type": "Feature",
  "properties": {
    "iso:country":"US",
    "sg:address":"5449 Amigo Ave",
    "sg:city":"Tarzana",
    "sg:classifiers":[
        {
            "category":"Recreation",
            "type":"Entertainment"
        }
    ],
    "sg:phone":"+1 818 996 0964",
    "sg:postcode":"91356",
    "sg:province":"CA",
    "sg:tags":[
        "psychic",
        "medium"
    ],
    "wof:name":"Psychic Reading By Mrs Gray",
    "wof:placetype":"venue"
},
  "geometry": {"coordinates":[-118.538905,34.167164],"type":"Point"}
}