{
  "type": "Feature",
  "properties": {
    "iso:country":"US",
    "sg:address":"1500 Peninsula Dr",
    "sg:city":"Arcata",
    "sg:classifiers":[
        {
            "category":"Building & Trades",
            "subcategory":"Construction",
            "type":"Services"
        }
    ],
    "sg:phone":"+1 707 442 8228",
    "sg:postcode":"95521",
    "sg:province":"CA",
    "sg:tags":[
        "contractor"
    ],
    "wof:name":"Fennell Building",
    "wof:placetype":"venue"
},
  "geometry": {"coordinates":[-124.170999,40.839215],"type":"Point"}
}