{
  "type": "Feature",
  "properties": {
    "addr:full":"18182 State Hwy 18 Apple Valley CA 92307",
    "addr:housenumber":"18182",
    "addr:postcode":"92307",
    "addr:street":"State Hwy 18",
    "iso:country":"US",
    "sg:address":"18182 State Hwy 18",
    "sg:city":"Apple Valley",
    "sg:classifiers":[
        {
            "category":"Health Services",
            "subcategory":"Doctor",
            "type":"Services"
        }
    ],
    "sg:phone":"+1 760 242 1234",
    "sg:postcode":"92307",
    "sg:province":"CA",
    "sg:tags":[
        "clinic"
    ],
    "wof:name":"Sante Fe Family Health",
    "wof:placetype":"venue"
},
  "geometry": {"coordinates":[-117.271905,34.540224],"type":"Point"}
}