{
  "type": "Feature",
  "properties": {
    "iso:country":"US",
    "sg:address":"214 Dufour St",
    "sg:city":"Santa Cruz",
    "sg:classifiers":[
        {
            "category":"Building & Trades",
            "subcategory":"Electrical",
            "type":"Services"
        }
    ],
    "sg:phone":"+1 831 459 8222",
    "sg:postcode":"95060",
    "sg:province":"CA",
    "sg:tags":[
        "electrician"
    ],
    "wof:name":"Dazey Eric Electrcl Contrng",
    "wof:placetype":"venue"
},
  "geometry": {"coordinates":[-122.035004,36.959099],"type":"Point"}
}