{
  "type": "Feature",
  "properties": {
    "iso:country":"US",
    "sg:address":"320 Pepperwood Ct",
    "sg:city":"Tracy",
    "sg:classifiers":[
        {
            "category":"Professional",
            "subcategory":"Business Services",
            "type":"Services"
        }
    ],
    "sg:phone":"+1 209 833 0049",
    "sg:postcode":"95376",
    "sg:province":"CA",
    "sg:tags":[
        "pool",
        "swimming"
    ],
    "wof:name":"Altamont Pool Svc",
    "wof:placetype":"venue"
},
  "geometry": {"coordinates":[-121.449387,37.725865],"type":"Point"}
}