{
  "type": "Feature",
  "properties": {
    "addr:full":"1602 Main St Cambria CA 93428",
    "addr:housenumber":"1602",
    "addr:postcode":"93428",
    "addr:street":"Main St",
    "iso:country":"US",
    "sg:address":"1602 Main St",
    "sg:city":"Cambria",
    "sg:classifiers":[
        {
            "category":"Professional",
            "type":"Services"
        },
        {
            "category":"Bakery",
            "type":"Food & Drink"
        }
    ],
    "sg:phone":"+1 805 927 1501",
    "sg:postcode":"93428",
    "sg:province":"CA",
    "sg:tags":[
        "caterer"
    ],
    "sg:website":"www.alloccos.com",
    "wof:name":"Allocco's Food Products",
    "wof:placetype":"venue"
},
  "geometry": {"coordinates":[-121.08726799999999,35.563065],"type":"Point"}
}