{
  "type": "Feature",
  "properties": {
    "addr:full":"126 Fern St Santa Cruz CA 95060",
    "addr:housenumber":"126",
    "addr:postcode":"95060",
    "addr:street":"Fern St",
    "iso:country":"US",
    "sg:address":"126 Fern St",
    "sg:city":"Santa Cruz",
    "sg:classifiers":[
        {
            "category":"Building & Trades",
            "subcategory":"Construction",
            "type":"Services"
        }
    ],
    "sg:phone":"+1 831 425 5425",
    "sg:postcode":"95060",
    "sg:province":"CA",
    "sg:tags":[
        "contractor"
    ],
    "wof:name":"Slatter Construction Inc",
    "wof:placetype":"venue"
},
  "geometry": {"coordinates":[-122.03146099999999,36.98595],"type":"Point"}
}