{
  "type": "Feature",
  "properties": {
    "addr:full":"5007 Pacific Village Ct Carpinteria CA 93013",
    "addr:housenumber":"5007",
    "addr:postcode":"93013",
    "addr:street":"Pacific Village Ct",
    "iso:country":"US",
    "sg:address":"5007 Pacific Village Ct",
    "sg:city":"Carpinteria",
    "sg:classifiers":[
        {
            "category":"Education",
            "subcategory":"Special Training",
            "type":"Public Place"
        }
    ],
    "sg:phone":"+1 805 881 1028",
    "sg:postcode":"93013",
    "sg:province":"CA",
    "sg:tags":[
        "instruction",
        "music"
    ],
    "wof:name":"Santa Barbara Studio Of Music",
    "wof:placetype":"venue"
},
  "geometry": {"coordinates":[-119.51526200000001,34.40208],"type":"Point"}
}