{
  "type": "Feature",
  "properties": {
    "addr:full":"139 Rome St San Francisco CA 94112",
    "addr:housenumber":"139",
    "addr:postcode":"94112",
    "addr:street":"Rome St",
    "iso:country":"US",
    "sg:address":"139 Rome St",
    "sg:city":"San Francisco",
    "sg:classifiers":[
        {
            "category":"Building & Trades",
            "subcategory":"Construction",
            "type":"Services"
        }
    ],
    "sg:phone":"+1 415 841 9081",
    "sg:postcode":"94112",
    "sg:province":"CA",
    "sg:tags":[
        "resurfacing",
        "laying",
        "refinishing",
        "floor"
    ],
    "wof:name":"Liang's Hardwood Floors",
    "wof:placetype":"venue"
},
  "geometry": {"coordinates":[-122.445961,37.716009],"type":"Point"}
}