{
  "type": "Feature",
  "properties": {
    "addr:full":"3403 10th St Riverside CA 92501",
    "addr:housenumber":"3403",
    "addr:postcode":"92501",
    "addr:street":"10Th St",
    "iso:country":"US",
    "sg:address":"3403 10th St",
    "sg:city":"Riverside",
    "sg:classifiers":[
        {
            "category":"Utilities",
            "subcategory":"Water",
            "type":"Services"
        }
    ],
    "sg:phone":"+1 951 682 9066",
    "sg:postcode":"92501",
    "sg:province":"CA",
    "sg:tags":[
        "supply"
    ],
    "wof:name":"Metropolitn Water Dist Sou Cal",
    "wof:placetype":"venue"
},
  "geometry": {"coordinates":[-117.37338,33.978974],"type":"Point"}
}