{
  "type": "Feature",
  "properties": {
    "iso:country":"US",
    "sg:address":"17823 Evelyn Ave",
    "sg:city":"Gardena",
    "sg:classifiers":[
        {
            "category":"Building & Trades",
            "subcategory":"Construction",
            "type":"Services"
        }
    ],
    "sg:phone":"+1 310 538 0333",
    "sg:postcode":"90248",
    "sg:province":"CA",
    "sg:website":"www.alanprefab.com",
    "wof:name":"Alan Pre-Fab Building Corp",
    "wof:placetype":"venue"
},
  "geometry": {"coordinates":[-118.30264200000001,33.868269],"type":"Point"}
}