{
  "type": "Feature",
  "properties": {
    "iso:country":"US",
    "sg:address":"2200 Marina Blvd",
    "sg:city":"San Leandro",
    "sg:classifiers":[
        {
            "category":"Food & Beverages",
            "subcategory":"Groceries & Convenience Stores",
            "type":"Retail Goods"
        }
    ],
    "sg:postcode":"94577",
    "sg:province":"CA",
    "wof:name":"Los Pericos Market",
    "wof:placetype":"venue"
},
  "geometry": {"coordinates":[-122.180272,37.704783],"type":"Point"}
}