{
  "type": "Feature",
  "properties": {
    "iso:country":"US",
    "sg:address":"13138 Palm Dr",
    "sg:city":"Desert Hot Spgs",
    "sg:classifiers":[
        {
            "category":"Banks & Credit Unions",
            "subcategory":"Bank",
            "type":"Services"
        }
    ],
    "sg:phone":"+1 760 775 3779",
    "sg:postcode":"92240",
    "sg:province":"CA",
    "sg:tags":[
        "cashing",
        "check"
    ],
    "wof:name":"Uncle Cash",
    "wof:placetype":"venue"
},
  "geometry": {"coordinates":[-116.501269,33.953329],"type":"Point"}
}