{
  "type": "Feature",
  "properties": {
    "iso:country":"US",
    "sg:address":"5469 S Elm Ave",
    "sg:city":"Fresno",
    "sg:classifiers":[
        {
            "category":"Retail",
            "subcategory":"Auto Repair",
            "type":"Services"
        }
    ],
    "sg:phone":"+1 559 268 1146",
    "sg:postcode":"93706",
    "sg:province":"CA",
    "sg:tags":[
        "repairing",
        "automobile"
    ],
    "wof:name":"Easton Brake & Lube",
    "wof:placetype":"venue"
},
  "geometry": {"coordinates":[-119.790863,36.662862],"type":"Point"}
}