{
  "type": "Feature",
  "properties": {
    "addr:full":"12141 Lakewood Blvd Downey CA 90242",
    "addr:housenumber":"12141",
    "addr:postcode":"90242",
    "addr:street":"Lakewood Blvd",
    "iso:country":"US",
    "sg:address":"12141 Lakewood Blvd",
    "sg:city":"Downey",
    "sg:classifiers":[
        {
            "category":"Retail",
            "subcategory":"Auto Repair",
            "type":"Services"
        }
    ],
    "sg:phone":"+1 562 869 1568",
    "sg:postcode":"90242",
    "sg:province":"CA",
    "sg:tags":[
        "transmission",
        "general"
    ],
    "wof:name":"Transmission House Co",
    "wof:placetype":"venue"
},
  "geometry": {"coordinates":[-118.131863,33.924851],"type":"Point"}
}