{
  "type": "Feature",
  "properties": {
    "addr:full":"PO Box 6377 Anaheim CA 92816",
    "addr:housenumber":"po",
    "addr:postcode":"92816",
    "addr:street":"Box 6377",
    "iso:country":"US",
    "sg:address":"PO Box 6377",
    "sg:city":"Anaheim",
    "sg:classifiers":[
        {
            "category":"Building & Trades",
            "subcategory":"Construction",
            "type":"Services"
        }
    ],
    "sg:phone":"+1 714 229 5900",
    "sg:postcode":"92816",
    "sg:province":"CA",
    "sg:tags":[
        "painter"
    ],
    "wof:name":"Pilot Painting",
    "wof:placetype":"venue"
},
  "geometry": {"coordinates":[-117.88400300000001,33.839298],"type":"Point"}
}