{
  "type": "Feature",
  "properties": {
    "iso:country":"US",
    "sg:address":"2985 Sierra Hwy",
    "sg:city":"Rosamond",
    "sg:classifiers":[
        {
            "category":"Autos & Motor Vehicles",
            "subcategory":"Automobile Sales",
            "type":"Retail Goods"
        }
    ],
    "sg:phone":"+1 661 256 2811",
    "sg:postcode":"93560",
    "sg:province":"CA",
    "sg:tags":[
        "car",
        "dealer"
    ],
    "wof:name":"Kieffe & Sons Ford Used Cars",
    "wof:placetype":"venue"
},
  "geometry": {"coordinates":[-118.163364,34.864186],"type":"Point"}
}