{
  "type": "Feature",
  "properties": {
    "iso:country":"US",
    "sg:address":"4600 N Pershing Ave",
    "sg:city":"Stockton",
    "sg:classifiers":[
        {
            "category":"Education",
            "subcategory":"Junior College",
            "type":"Public Place"
        }
    ],
    "sg:phone":"+1 209 472 7051",
    "sg:postcode":"95207",
    "sg:province":"CA",
    "sg:tags":[
        "technical",
        "institute"
    ],
    "wof:name":"Institute For Educational Svc",
    "wof:placetype":"venue"
},
  "geometry": {"coordinates":[-121.321121,37.987329],"type":"Point"}
}