{
  "type": "Feature",
  "properties": {
    "addr:full":"2021 Sperry Ave Ventura CA 93003",
    "addr:housenumber":"2021",
    "addr:postcode":"93003",
    "addr:street":"Sperry Ave",
    "iso:country":"US",
    "sg:address":"2021 Sperry Ave",
    "sg:city":"Ventura",
    "sg:classifiers":[
        {
            "category":"Banks & Credit Unions",
            "subcategory":"Investment Brokerage",
            "type":"Services"
        }
    ],
    "sg:phone":"+1 805 642 7506",
    "sg:postcode":"93003",
    "sg:province":"CA",
    "sg:tags":[
        "management"
    ],
    "wof:name":"Cornerstone Asset Management",
    "wof:placetype":"venue"
},
  "geometry": {"coordinates":[-119.21778500000001,34.253744],"type":"Point"}
}