{
  "type": "Feature",
  "properties": {
    "iso:country":"US",
    "sg:address":"3617 W Macarthur Blvd",
    "sg:city":"Santa Ana",
    "sg:classifiers":[
        {
            "category":"Professional",
            "subcategory":"Advertising",
            "type":"Services"
        }
    ],
    "sg:phone":"+1 714 979 7500",
    "sg:postcode":"92704",
    "sg:province":"CA",
    "sg:tags":[
        "distribution"
    ],
    "sg:website":"www.christopherweb.com",
    "wof:name":"Christopher Group",
    "wof:placetype":"venue"
},
  "geometry": {"coordinates":[-117.917019,33.702038],"type":"Point"}
}