{
  "type": "Feature",
  "properties": {
    "addr:full":"1503 S Wright Rd Santa Rosa CA 95407",
    "addr:housenumber":"1503",
    "addr:postcode":"95407",
    "addr:street":"S Wright Rd",
    "iso:country":"US",
    "sg:address":"1503 S Wright Rd",
    "sg:city":"Santa Rosa",
    "sg:classifiers":[
        {
            "category":"Freight",
            "type":"Transportation"
        }
    ],
    "sg:phone":"+1 707 570 1918",
    "sg:postcode":"95407",
    "sg:province":"CA",
    "sg:tags":[
        "operator",
        "local",
        "trucking"
    ],
    "wof:name":"Johnnie Johnson Trucking",
    "wof:placetype":"venue"
},
  "geometry": {"coordinates":[-122.768846,38.411024],"type":"Point"}
}