{
  "type": "Feature",
  "properties": {
    "addr:full":"234 E El Roblar Dr Ojai CA 93023",
    "addr:housenumber":"234",
    "addr:postcode":"93023",
    "addr:street":"E El Roblar Dr",
    "iso:country":"US",
    "sg:address":"234 E El Roblar Dr",
    "sg:city":"Ojai",
    "sg:classifiers":[
        {
            "category":"Shopping Center",
            "type":"Public Place"
        }
    ],
    "sg:phone":"+1 805 640 1875",
    "sg:postcode":"93023",
    "sg:province":"CA",
    "sg:tags":[
        "flea",
        "market"
    ],
    "wof:name":"Hal Friedberg",
    "wof:placetype":"venue"
},
  "geometry": {"coordinates":[-119.27439800000001,34.448015],"type":"Point"}
}