{
  "type": "Feature",
  "properties": {
    "iso:country":"US",
    "sg:address":"481 South Mathilda",
    "sg:city":"Sunnyvale",
    "sg:classifiers":[
        {
            "category":"Professional",
            "subcategory":"Business Services",
            "type":"Services"
        }
    ],
    "sg:phone":"+1 650 380 4740",
    "sg:postcode":"94086",
    "sg:province":"CA",
    "sg:tags":[
        "food",
        "delivery"
    ],
    "wof:name":"Speed Waiters",
    "wof:placetype":"venue"
},
  "geometry": {"coordinates":[-122.036507,37.372371],"type":"Point"}
}