{
  "type": "Feature",
  "properties": {
    "addr:full":"2324 Durfee Ave El Monte CA 91732",
    "addr:postcode":"2324;91732",
    "addr:street":"Durfee Ave",
    "iso:country":"US",
    "sg:address":"2324 Durfee Ave",
    "sg:city":"El Monte",
    "sg:classifiers":[
        {
            "category":"Organizations",
            "subcategory":"Religious Organization",
            "type":"Services"
        }
    ],
    "sg:phone":"+1 626 453 0495",
    "sg:postcode":"91732",
    "sg:province":"CA",
    "sg:tags":[
        "church"
    ],
    "wof:name":"Assembly Pentecostal Church",
    "wof:placetype":"venue"
},
  "geometry": {"coordinates":[-118.025499,34.049167],"type":"Point"}
}