{
  "type": "Feature",
  "properties": {
    "addr:full":"Bernal Heights 1 Mission Street San Francisco CA 94109",
    "addr:housenumber":"1",
    "addr:postcode":"94109",
    "addr:street":"Heights;Mission Street",
    "iso:country":"US",
    "sg:address":"Bernal Heights 1 Mission Street",
    "sg:city":"San Francisco",
    "sg:classifiers":[
        {
            "category":"Home & Garden",
            "subcategory":"Household Appliances",
            "type":"Retail Goods"
        }
    ],
    "sg:phone":"+1 415 379 1234",
    "sg:postcode":"94109",
    "sg:province":"CA",
    "sg:tags":[
        "repair"
    ],
    "wof:name":"Lewis Appliance",
    "wof:placetype":"venue"
},
  "geometry": {"coordinates":[-122.392985,37.793202],"type":"Point"}
}