{
  "type": "Feature",
  "properties": {
    "iso:country":"US",
    "sg:address":"189 The Grove Dr",
    "sg:city":"Los Angeles",
    "sg:classifiers":[
        {
            "category":"Shopping",
            "subcategory":"Clothing, Apparel, & Fashions",
            "type":"Retail Goods"
        }
    ],
    "sg:phone":"+1 323 549 9801",
    "sg:postcode":"90036",
    "sg:province":"CA",
    "sg:tags":[
        "accessory",
        "clothing",
        "women's"
    ],
    "wof:name":"Chico's",
    "wof:placetype":"venue"
},
  "geometry": {"coordinates":[-118.356465,34.108884],"type":"Point"}
}