{
  "type": "Feature",
  "properties": {
    "addr:full":"486 2nd Avenue # 3 San Francisco CA 94118",
    "addr:housenumber":"486",
    "addr:postcode":"94118",
    "addr:street":"2Nd Avenue # 3",
    "iso:country":"US",
    "sg:address":"486 2nd Avenue # 3",
    "sg:city":"San Francisco",
    "sg:classifiers":[
        {
            "category":"Real Estate",
            "subcategory":"Architect",
            "type":"Services"
        }
    ],
    "sg:phone":"+1 415 668 2344",
    "sg:postcode":"94118",
    "sg:province":"CA",
    "wof:name":"Lyon S G Company",
    "wof:placetype":"venue"
},
  "geometry": {"coordinates":[-122.460055,37.779578],"type":"Point"}
}