{
  "type": "Feature",
  "properties": {
    "addr:full":"1270 11th St Imperial Beach CA 91932",
    "addr:housenumber":"1270",
    "addr:postcode":"91932",
    "addr:street":"11Th St",
    "iso:country":"US",
    "sg:address":"1270 11th St",
    "sg:city":"Imperial Beach",
    "sg:classifiers":[
        {
            "category":"Wholesale",
            "subcategory":"Stationery",
            "type":"Manufacturing & Wholesale Goods"
        }
    ],
    "sg:phone":"+1 619 575 3732",
    "sg:postcode":"91932",
    "sg:province":"CA",
    "sg:tags":[
        "for",
        "supply",
        "sales",
        "notary",
        "retail",
        "public"
    ],
    "wof:name":"American Notary Exchange",
    "wof:placetype":"venue"
},
  "geometry": {"coordinates":[-117.11011999999999,32.574185],"type":"Point"}
}