{
  "type": "Feature",
  "properties": {
    "iso:country":"US",
    "sg:address":"430 Mason St",
    "sg:city":"San Francisco",
    "sg:classifiers":[
        {
            "category":"Bars & Pubs",
            "subcategory":"Lounge",
            "type":"Food & Drink"
        },
        {
            "category":"Recreation",
            "subcategory":"Dance Hall",
            "type":"Entertainment"
        }
    ],
    "sg:phone":"+1 415 421 1916",
    "sg:postcode":"94102",
    "sg:province":"CA",
    "sg:tags":[
        "club"
    ],
    "sg:website":"www.slidesf.com",
    "wof:name":"Slide",
    "wof:placetype":"venue"
},
  "geometry": {"coordinates":[-122.409989,37.787627],"type":"Point"}
}