{
  "type": "Feature",
  "properties": {
    "iso:country":"US",
    "sg:address":"3227 Beachwood Dr",
    "sg:city":"Merced",
    "sg:classifiers":[
        {
            "category":"Wholesale",
            "subcategory":"Construction Materials",
            "type":"Manufacturing & Wholesale Goods"
        }
    ],
    "sg:phone":"+1 209 388 9474",
    "sg:postcode":"95348",
    "sg:province":"CA",
    "sg:tags":[
        "pallet",
        "skid"
    ],
    "wof:name":"Golden State Pallet & Crate",
    "wof:placetype":"venue"
},
  "geometry": {"coordinates":[-120.527489,37.33622],"type":"Point"}
}