{
  "type": "Feature",
  "properties": {
    "addr:full":"5283 Darro Rd Woodland Hills CA 91364",
    "addr:housenumber":"5283",
    "addr:postcode":"91364",
    "addr:street":"Darro Rd",
    "iso:country":"US",
    "sg:address":"5283 Darro Rd",
    "sg:city":"Woodland Hills",
    "sg:classifiers":[
        {
            "category":"Professional",
            "subcategory":"Advertising",
            "type":"Services"
        }
    ],
    "sg:phone":"+1 818 992 8383",
    "sg:postcode":"91364",
    "sg:province":"CA",
    "wof:name":"Earth Shaking Promotions",
    "wof:placetype":"venue"
},
  "geometry": {"coordinates":[-118.599896,34.163494],"type":"Point"}
}