{
  "type": "Feature",
  "properties": {
    "addr:full":"1412 E Valley Blvd Alhambra CA 91801",
    "addr:housenumber":"1412",
    "addr:postcode":"91801",
    "addr:street":"E Valley Blvd",
    "iso:country":"US",
    "sg:address":"1412 E Valley Blvd",
    "sg:city":"Alhambra",
    "sg:classifiers":[
        {
            "category":"Restaurant",
            "type":"Food & Drink"
        }
    ],
    "sg:phone":"+1 626 282 8822",
    "sg:postcode":"91801",
    "sg:province":"CA",
    "wof:name":"Siam Express",
    "wof:placetype":"venue"
},
  "geometry": {"coordinates":[-118.110494,34.079122],"type":"Point"}
}