{
  "type": "Feature",
  "properties": {
    "addr:full":"1904 Richland Ave Ceres CA 95307",
    "addr:housenumber":"1904",
    "addr:postcode":"95307",
    "addr:street":"Richland Ave",
    "iso:country":"US",
    "sg:address":"1904 Richland Ave",
    "sg:city":"Ceres",
    "sg:classifiers":[
        {
            "category":"Government",
            "subcategory":"Office",
            "type":"Public Place"
        }
    ],
    "sg:phone":"+1 209 541 2121",
    "sg:postcode":"95307",
    "sg:province":"CA",
    "wof:name":"Stanislaus Recover Ctr",
    "wof:placetype":"venue"
},
  "geometry": {"coordinates":[-120.965902,37.601906],"type":"Point"}
}