{
  "type": "Feature",
  "properties": {
    "addr:full":"2051 Hilltop Dr Redding CA 96002",
    "addr:housenumber":"2051",
    "addr:postcode":"96002",
    "addr:street":"Hilltop Dr",
    "iso:country":"US",
    "sg:address":"2051 Hilltop Dr",
    "sg:city":"Redding",
    "sg:classifiers":[
        {
            "category":"Health Services",
            "subcategory":"Clinic",
            "type":"Services"
        }
    ],
    "sg:phone":"+1 530 223 4411",
    "sg:postcode":"96002",
    "sg:province":"CA",
    "sg:tags":[
        "colonic",
        "irrigation"
    ],
    "wof:name":"Shasta Colon Hydrotherapy",
    "wof:placetype":"venue"
},
  "geometry": {"coordinates":[-122.357731,40.577943],"type":"Point"}
}