{
  "type": "Feature",
  "properties": {
    "addr:full":"1935 Friendship Dr Ste C El Cajon CA 92020",
    "addr:housenumber":"1935",
    "addr:postcode":"92020",
    "addr:street":"Friendship Dr Ste C",
    "iso:country":"US",
    "sg:address":"1935 Friendship Dr Ste C",
    "sg:city":"El Cajon",
    "sg:classifiers":[
        {
            "category":"Communications",
            "type":"Services"
        }
    ],
    "sg:phone":"+1 619 258 1080",
    "sg:postcode":"92020",
    "sg:province":"CA",
    "sg:tags":[
        "recording",
        "rehearsal",
        "studio"
    ],
    "sg:website":"www.hitsinglerecording.com",
    "wof:name":"Hit Single Recording Services",
    "wof:placetype":"venue"
},
  "geometry": {"coordinates":[-116.978996,32.824299],"type":"Point"}
}