{
  "type": "Feature",
  "properties": {
    "iso:country":"US",
    "sg:address":"1206 S Parallel Ave",
    "sg:city":"Fresno",
    "sg:classifiers":[
        {
            "category":"Freight",
            "type":"Transportation"
        }
    ],
    "sg:phone":"+1 559 486 4040",
    "sg:postcode":"93702",
    "sg:province":"CA",
    "sg:tags":[
        "delivery"
    ],
    "wof:name":"CFC Network",
    "wof:placetype":"venue"
},
  "geometry": {"coordinates":[-119.772161,36.730305],"type":"Point"}
}