{
  "type": "Feature",
  "properties": {
    "iso:country":"US",
    "sg:address":"8205 Sierra College Blvd",
    "sg:city":"Roseville",
    "sg:classifiers":[
        {
            "category":"Professional",
            "subcategory":"Advertising",
            "type":"Services"
        }
    ],
    "sg:phone":"+1 916 774 9600",
    "sg:postcode":"95661",
    "sg:province":"CA",
    "sg:tags":[
        "counselor"
    ],
    "wof:name":"Augustine & Assoc",
    "wof:placetype":"venue"
},
  "geometry": {"coordinates":[-121.226231,38.745816],"type":"Point"}
}