{
  "type": "Feature",
  "properties": {
    "addr:full":"1427 Burlingame Ave Burlingame CA 94010",
    "addr:housenumber":"1427",
    "addr:postcode":"94010",
    "addr:street":"Burlingame Ave",
    "iso:country":"US",
    "sg:address":"1427 Burlingame Ave",
    "sg:city":"Burlingame",
    "sg:classifiers":[
        {
            "category":"Retail",
            "subcategory":"Portrait Studio",
            "type":"Services"
        }
    ],
    "sg:phone":"+1 650 343 4844",
    "sg:postcode":"94010",
    "sg:province":"CA",
    "sg:tags":[
        "photographer",
        "photo"
    ],
    "wof:name":"Doerr Photography",
    "wof:placetype":"venue"
},
  "geometry": {"coordinates":[-122.34899900000001,37.577301],"type":"Point"}
}