{
  "type": "Feature",
  "properties": {
    "addr:full":"821 Pollux Ct Foster City CA 94404",
    "addr:housenumber":"821",
    "addr:postcode":"94404",
    "addr:street":"Pollux Ct",
    "iso:country":"US",
    "sg:address":"821 Pollux Ct",
    "sg:city":"Foster City",
    "sg:classifiers":[
        {
            "category":"Professional",
            "type":"Services"
        }
    ],
    "sg:phone":"+1 650 573 5789",
    "sg:postcode":"94404",
    "sg:province":"CA",
    "sg:tags":[
        "arts",
        "artist"
    ],
    "wof:name":"Joe Alvin",
    "wof:placetype":"venue"
},
  "geometry": {"coordinates":[-122.27551800000001,37.5454],"type":"Point"}
}