{
  "type": "Feature",
  "properties": {
    "addr:full":"2580 Marin Ave Berkeley CA 94708",
    "addr:housenumber":"2580",
    "addr:postcode":"94708",
    "addr:street":"Marin Ave",
    "iso:country":"US",
    "sg:address":"2580 Marin Ave",
    "sg:city":"Berkeley",
    "sg:classifiers":[
        {
            "category":"Education",
            "subcategory":"Music School",
            "type":"Public Place"
        }
    ],
    "sg:phone":"+1 510 526 1560",
    "sg:postcode":"94708",
    "sg:province":"CA",
    "sg:tags":[
        "instruction-instrumental"
    ],
    "wof:name":"Japanese Music Institute of America",
    "wof:placetype":"venue"
},
  "geometry": {"coordinates":[-122.262995,37.89619],"type":"Point"}
}