{
  "type": "Feature",
  "properties": {
    "addr:full":"235 E Middlefield Rd Mountain View CA 94043",
    "addr:housenumber":"235",
    "addr:postcode":"94043",
    "addr:street":"E Middlefield Rd",
    "iso:country":"US",
    "sg:address":"235 E Middlefield Rd",
    "sg:city":"Mountain View",
    "sg:classifiers":[
        {
            "category":"Restaurant",
            "type":"Food & Drink"
        }
    ],
    "sg:menulink":"http://www.allmenus.com/ca/san-jose/150369-subway/menu/",
    "sg:phone":"+1 650 969 9100",
    "sg:postcode":"94043",
    "sg:province":"CA",
    "sg:tags":[
        "american",
        "sandwich"
    ],
    "wof:name":"Subway",
    "wof:placetype":"venue"
},
  "geometry": {"coordinates":[-122.061509,37.396995],"type":"Point"}
}