{
  "type": "Feature",
  "properties": {
    "addr:full":"6700 Verner Ave Sacramento CA 95841",
    "addr:postcode":"6700;95841",
    "addr:street":"Verner Ave",
    "iso:country":"US",
    "sg:address":"6700 Verner Ave",
    "sg:city":"Sacramento",
    "sg:classifiers":[
        {
            "category":"Retail",
            "subcategory":"Animal Services",
            "type":"Services"
        }
    ],
    "sg:phone":"+1 916 732 2037",
    "sg:postcode":"95841",
    "sg:province":"CA",
    "sg:tags":[
        "pet",
        "equipment",
        "cemetery",
        "supply"
    ],
    "sg:website":"http://www.eastlawn.com",
    "wof:name":"Sierra Hills Pet Cemetery",
    "wof:placetype":"venue"
},
  "geometry": {"coordinates":[-121.332207,38.685982],"type":"Point"}
}