{
  "type": "Feature",
  "properties": {
    "addr:full":"12 N School St Lodi CA 95240",
    "addr:housenumber":"12",
    "addr:postcode":"95240",
    "addr:street":"N School St",
    "iso:country":"US",
    "sg:address":"12 N School St",
    "sg:city":"Lodi",
    "sg:classifiers":[
        {
            "category":"Personal",
            "type":"Services"
        }
    ],
    "sg:phone":"+1 209 339 8897",
    "sg:postcode":"95240",
    "sg:province":"CA",
    "sg:tags":[
        "wear",
        "formal"
    ],
    "wof:name":"Tuxedos Of Lodi",
    "wof:placetype":"venue"
},
  "geometry": {"coordinates":[-121.27349700000001,38.135348],"type":"Point"}
}