{
  "type": "Feature",
  "properties": {
    "iso:country":"US",
    "sg:address":"5563 Sepulveda Blvd Ste C",
    "sg:city":"Culver City",
    "sg:classifiers":[
        {
            "category":"Insurance",
            "subcategory":"Hazard Insurance",
            "type":"Services"
        }
    ],
    "sg:phone":"+1 310 280 0440",
    "sg:postcode":"90230",
    "sg:province":"CA",
    "sg:website":"www.DavidAChurch.com",
    "wof:name":"David A Church - State Farm",
    "wof:placetype":"venue"
},
  "geometry": {"coordinates":[-118.39575499999999,33.991435],"type":"Point"}
}