{
  "type": "Feature",
  "properties": {
    "iso:country":"US",
    "sg:address":"980 Trancas St",
    "sg:city":"Napa",
    "sg:classifiers":[
        {
            "category":"Health Services",
            "subcategory":"Doctor",
            "type":"Services"
        }
    ],
    "sg:phone":"+1 707 224 8361",
    "sg:postcode":"94558",
    "sg:province":"CA",
    "sg:tags":[
        "physician",
        "surgeon"
    ],
    "wof:name":"Jeanette H Koshar PHD",
    "wof:placetype":"venue"
},
  "geometry": {"coordinates":[-122.294286,38.323976],"type":"Point"}
}