{
  "type": "Feature",
  "properties": {
    "iso:country":"US",
    "sg:address":"825 6th Ave",
    "sg:city":"Oakland",
    "sg:classifiers":[
        {
            "category":"Home & Garden",
            "subcategory":"Hardware",
            "type":"Retail Goods"
        }
    ],
    "sg:phone":"+1 510 835 3828",
    "sg:postcode":"94606",
    "sg:province":"CA",
    "sg:tags":[
        "store"
    ],
    "wof:name":"Ideal Hardware Supply",
    "wof:placetype":"venue"
},
  "geometry": {"coordinates":[-122.256635,37.792608],"type":"Point"}
}