{
  "type": "Feature",
  "properties": {
    "addr:full":"5767 River Run Cir Rocklin CA 95765",
    "addr:housenumber":"5767",
    "addr:postcode":"95765",
    "addr:street":"River Run Cir",
    "iso:country":"US",
    "sg:address":"5767 River Run Cir",
    "sg:city":"Rocklin",
    "sg:classifiers":[
        {
            "category":"Utilities",
            "subcategory":"Telephone",
            "type":"Services"
        }
    ],
    "sg:phone":"+1 916 630 0154",
    "sg:postcode":"95765",
    "sg:province":"CA",
    "sg:tags":[
        "communications"
    ],
    "wof:name":"Silenti Etc Networking",
    "wof:placetype":"venue"
},
  "geometry": {"coordinates":[-121.26265100000001,38.802172],"type":"Point"}
}