{
  "type": "Feature",
  "properties": {
    "iso:country":"US",
    "sg:address":"8856 Rosecrans Avenue",
    "sg:city":"Downey",
    "sg:classifiers":[
        {
            "category":"Building & Trades",
            "subcategory":"Cleaning & Sanitation",
            "type":"Services"
        },
        {
            "category":"Professional",
            "subcategory":"Computer Services",
            "type":"Services"
        }
    ],
    "sg:phone":"+1 562 531 3252",
    "sg:postcode":"90242",
    "sg:province":"CA",
    "sg:tags":[
        "stereo",
        "installation",
        "carpet"
    ],
    "wof:name":"First Class Glass Tint",
    "wof:placetype":"venue"
},
  "geometry": {"coordinates":[-118.144587,33.903762],"type":"Point"}
}