{
  "type": "Feature",
  "properties": {
    "addr:full":"1875 Century Park E Los Angeles CA 90067",
    "addr:housenumber":"1875",
    "addr:postcode":"90067",
    "addr:street":"Century Park E",
    "iso:country":"US",
    "sg:address":"1875 Century Park E",
    "sg:city":"Los Angeles",
    "sg:classifiers":[
        {
            "category":"Professional",
            "subcategory":"Lawyer & Legal Services",
            "type":"Services"
        }
    ],
    "sg:phone":"+1 310 278 6060",
    "sg:postcode":"90067",
    "sg:province":"CA",
    "sg:tags":[
        "attorney"
    ],
    "wof:name":"Compass International Pictures",
    "wof:placetype":"venue"
},
  "geometry": {"coordinates":[-118.41436899999999,34.061239],"type":"Point"}
}