{
  "type": "Feature",
  "properties": {
    "addr:full":"6217 MacArthur Blvd Oakland CA 94605",
    "addr:housenumber":"6217",
    "addr:postcode":"94605",
    "addr:street":"Macarthur Blvd",
    "iso:country":"US",
    "sg:address":"6217 MacArthur Blvd",
    "sg:city":"Oakland",
    "sg:classifiers":[
        {
            "category":"Restaurant",
            "type":"Food & Drink"
        }
    ],
    "sg:phone":"+1 510 430 8771",
    "sg:postcode":"94605",
    "sg:province":"CA",
    "sg:tags":[
        "thai"
    ],
    "wof:name":"Old Weang Ping",
    "wof:placetype":"venue"
},
  "geometry": {"coordinates":[-122.181011,37.774796],"type":"Point"}
}