{
  "type": "Feature",
  "properties": {
    "iso:country":"US",
    "sg:address":"16152 Cohasset St",
    "sg:city":"Van Nuys",
    "sg:classifiers":[
        {
            "category":"Wholesale",
            "subcategory":"Sporting Goods",
            "type":"Manufacturing & Wholesale Goods"
        }
    ],
    "sg:phone":"+1 818 787 1036",
    "sg:postcode":"91406",
    "sg:province":"CA",
    "sg:tags":[
        "equipment",
        "pool",
        "swimming"
    ],
    "wof:name":"TSP LTD",
    "wof:placetype":"venue"
},
  "geometry": {"coordinates":[-118.484909,34.206545],"type":"Point"}
}