{
  "type": "Feature",
  "properties": {
    "addr:full":"1443 Leimert Blvd Oakland CA 94602",
    "addr:housenumber":"1443",
    "addr:postcode":"94602",
    "addr:street":"Leimert Blvd",
    "iso:country":"US",
    "sg:address":"1443 Leimert Blvd",
    "sg:city":"Oakland",
    "sg:classifiers":[
        {
            "category":"Health Services",
            "subcategory":"Dentist",
            "type":"Services"
        }
    ],
    "sg:phone":"+1 510 482 2799",
    "sg:postcode":"94602",
    "sg:province":"CA",
    "wof:name":"Sharp W Thos Jr DDS Inc",
    "wof:placetype":"venue"
},
  "geometry": {"coordinates":[-122.21199799999999,37.811798],"type":"Point"}
}