{
  "type": "Feature",
  "properties": {
    "iso:country":"US",
    "sg:address":"533 E Palmdale Blvd",
    "sg:city":"Palmdale",
    "sg:classifiers":[
        {
            "category":"Home & Garden",
            "subcategory":"Furniture",
            "type":"Retail Goods"
        }
    ],
    "sg:phone":"+1 661 947 0962",
    "sg:postcode":"93550",
    "sg:province":"CA",
    "sg:tags":[
        "mattress"
    ],
    "wof:name":"American Collections Mattress",
    "wof:placetype":"venue"
},
  "geometry": {"coordinates":[-118.119998,34.579715],"type":"Point"}
}