{
  "type": "Feature",
  "properties": {
    "addr:full":"1317 Stockton St San Francisco CA 94133",
    "addr:housenumber":"1317",
    "addr:postcode":"94133",
    "addr:street":"Stockton St",
    "iso:country":"US",
    "sg:address":"1317 Stockton St",
    "sg:city":"San Francisco",
    "sg:classifiers":[
        {
            "category":"Retail",
            "subcategory":"Portrait Studio",
            "type":"Services"
        }
    ],
    "sg:phone":"+1 415 362 2620",
    "sg:postcode":"94133",
    "sg:province":"CA",
    "sg:tags":[
        "photographer"
    ],
    "wof:name":"Jason Studio",
    "wof:placetype":"venue"
},
  "geometry": {"coordinates":[-122.40879,37.798053],"type":"Point"}
}