{
  "type": "Feature",
  "properties": {
    "addr:full":"2640 Bus Park Dr Vista CA 92081",
    "addr:postcode":"2640;92081",
    "addr:street":"Bus Park Dr",
    "iso:country":"US",
    "sg:address":"2640 Bus Park Dr",
    "sg:city":"Vista",
    "sg:classifiers":[
        {
            "category":"Manufacturing",
            "subcategory":"Tools & Machinery",
            "type":"Manufacturing & Wholesale Goods"
        }
    ],
    "sg:phone":"+1 760 727 7006",
    "sg:postcode":"92081",
    "sg:province":"CA",
    "sg:tags":[
        "die",
        "mfg"
    ],
    "wof:name":"Reel Tool and Machine",
    "wof:placetype":"venue"
},
  "geometry": {"coordinates":[-117.232157,33.146972],"type":"Point"}
}