{
  "type": "Feature",
  "properties": {
    "iso:country":"US",
    "sg:address":"15326 Fremont Dr",
    "sg:city":"Adelanto",
    "sg:classifiers":[
        {
            "category":"Shopping",
            "subcategory":"Musical Instruments",
            "type":"Retail Goods"
        }
    ],
    "sg:phone":"+1 760 246 1663",
    "sg:postcode":"92301",
    "sg:province":"CA",
    "wof:name":"Guitar Designs",
    "wof:placetype":"venue"
},
  "geometry": {"coordinates":[-117.405783,34.530053],"type":"Point"}
}