{
  "type": "Feature",
  "properties": {
    "addr:full":"6565 Lincoln Blvd Oroville CA 95966",
    "addr:housenumber":"6565",
    "addr:postcode":"95966",
    "addr:street":"Lincoln Blvd",
    "iso:country":"US",
    "sg:address":"6565 Lincoln Blvd",
    "sg:city":"Oroville",
    "sg:classifiers":[
        {
            "category":"Retail",
            "subcategory":"Laundry & Dry Cleaning",
            "type":"Services"
        }
    ],
    "sg:phone":"+1 530 533 1108",
    "sg:postcode":"95966",
    "sg:province":"CA",
    "sg:tags":[
        "cleaners",
        "rug",
        "carpet"
    ],
    "wof:name":"High Tech Carpet",
    "wof:placetype":"venue"
},
  "geometry": {"coordinates":[-121.54987300000001,39.452634],"type":"Point"}
}