{
  "type": "Feature",
  "properties": {
    "iso:country":"US",
    "sg:address":"2316 Florin Rd",
    "sg:city":"Sacramento",
    "sg:classifiers":[
        {
            "category":"Utilities",
            "subcategory":"Mobile Phone",
            "type":"Services"
        }
    ],
    "sg:phone":"+1 916 391 0111",
    "sg:postcode":"95822",
    "sg:province":"CA",
    "sg:tags":[
        "telephone",
        "cellular"
    ],
    "wof:name":"No Limit Wireless",
    "wof:placetype":"venue"
},
  "geometry": {"coordinates":[-121.484494,38.495763],"type":"Point"}
}