{
  "type": "Feature",
  "properties": {
    "addr:full":"3838 5th Ave San Diego CA 92103",
    "addr:housenumber":"3838",
    "addr:postcode":"92103",
    "addr:street":"5Th Ave",
    "iso:country":"US",
    "sg:address":"3838 5th Ave",
    "sg:city":"San Diego",
    "sg:classifiers":[
        {
            "category":"Shopping",
            "subcategory":"Used Merchandise",
            "type":"Retail Goods"
        }
    ],
    "sg:phone":"+1 619 291 4660",
    "sg:postcode":"92103",
    "sg:province":"CA",
    "sg:tags":[
        "bookstore",
        "rare",
        "book"
    ],
    "wof:name":"5th Avenue Books",
    "wof:placetype":"venue"
},
  "geometry": {"coordinates":[-117.160004,32.747601],"type":"Point"}
}