{
  "type": "Feature",
  "properties": {
    "addr:full":"1833 262nd St Lomita CA 90717",
    "addr:housenumber":"1833",
    "addr:postcode":"90717",
    "addr:street":"262Nd St",
    "iso:country":"US",
    "sg:address":"1833 262nd St",
    "sg:city":"Lomita",
    "sg:classifiers":[
        {
            "category":"Professional",
            "subcategory":"Art Services",
            "type":"Services"
        }
    ],
    "sg:phone":"+1 310 408 9386",
    "sg:postcode":"90717",
    "sg:province":"CA",
    "sg:tags":[
        "designer",
        "display",
        "producer"
    ],
    "wof:name":"Kya Designs Inc.",
    "wof:placetype":"venue"
},
  "geometry": {"coordinates":[-118.31047599999999,33.785198],"type":"Point"}
}