{
  "type": "Feature",
  "properties": {
    "addr:full":"2333 W Washington Blvd Los Angeles CA 90018",
    "addr:housenumber":"2333",
    "addr:postcode":"90018",
    "addr:street":"W Washington Blvd",
    "iso:country":"US",
    "sg:address":"2333 W Washington Blvd",
    "sg:city":"Los Angeles",
    "sg:classifiers":[
        {
            "category":"Food & Beverages",
            "subcategory":"Liquor & Beverages",
            "type":"Retail Goods"
        }
    ],
    "sg:phone":"+1 323 733 6995",
    "sg:postcode":"90018",
    "sg:province":"CA",
    "sg:tags":[
        "beer",
        "spirit",
        "wine"
    ],
    "wof:name":"Three Jays Liquor",
    "wof:placetype":"venue"
},
  "geometry": {"coordinates":[-118.31300400000001,34.039799],"type":"Point"}
}