{
  "type": "Feature",
  "properties": {
    "addr:full":"2520 W 237th St Torrance CA 90505",
    "addr:housenumber":"2520",
    "addr:postcode":"90505",
    "addr:street":"W 237Th St",
    "iso:country":"US",
    "sg:address":"2520 W 237th St",
    "sg:city":"Torrance",
    "sg:classifiers":[
        {
            "category":"Building & Trades",
            "subcategory":"Construction",
            "type":"Services"
        }
    ],
    "sg:phone":"+1 310 530 3107",
    "sg:postcode":"90505",
    "sg:province":"CA",
    "sg:tags":[
        "contractor"
    ],
    "wof:name":"Waveband Corporation",
    "wof:placetype":"venue"
},
  "geometry": {"coordinates":[-118.32799799999999,33.809843],"type":"Point"}
}