{
  "type": "Feature",
  "properties": {
    "iso:country":"US",
    "sg:address":"801 State Rte 46",
    "sg:city":"Wasco",
    "sg:classifiers":[
        {
            "category":"Retail",
            "subcategory":"Auto Repair",
            "type":"Services"
        }
    ],
    "sg:phone":"+1 661 758 2677",
    "sg:postcode":"93280",
    "sg:province":"CA",
    "sg:tags":[
        "repairing",
        "automobile",
        "radiator"
    ],
    "wof:name":"B & L Radiator",
    "wof:placetype":"venue"
},
  "geometry": {"coordinates":[-119.33367200000001,35.601529],"type":"Point"}
}