{
  "type": "Feature",
  "properties": {
    "addr:full":"13832 West St Garden Grove CA 92843",
    "addr:housenumber":"13832",
    "addr:postcode":"92843",
    "addr:street":"West St",
    "iso:country":"US",
    "sg:address":"13832 West St",
    "sg:city":"Garden Grove",
    "sg:classifiers":[
        {
            "category":"Manufacturing",
            "subcategory":"Tools & Machinery",
            "type":"Manufacturing & Wholesale Goods"
        }
    ],
    "sg:phone":"+1 714 265 9600",
    "sg:postcode":"92843",
    "sg:province":"CA",
    "sg:tags":[
        "die",
        "maker"
    ],
    "wof:name":"A A Accuracy Steel Rule Die Co",
    "wof:placetype":"venue"
},
  "geometry": {"coordinates":[-117.923738,33.760693],"type":"Point"}
}