{
  "type": "Feature",
  "properties": {
    "iso:country":"US",
    "sg:address":"225 30th Street",
    "sg:city":"Sacramento",
    "sg:classifiers":[
        {
            "category":"Professional",
            "subcategory":"Lawyer & Legal Services",
            "type":"Services"
        }
    ],
    "sg:phone":"+1 916 441 4874",
    "sg:postcode":"95816",
    "sg:province":"CA",
    "wof:name":"Law Offices of Diane R Dobbs",
    "wof:placetype":"venue"
},
  "geometry": {"coordinates":[-121.46279199999999,38.581523],"type":"Point"}
}