{
  "type": "Feature",
  "properties": {
    "addr:full":"1001 Stoneman Ave Pittsburg CA 94565",
    "addr:housenumber":"1001",
    "addr:postcode":"94565",
    "addr:street":"Stoneman Ave",
    "iso:country":"US",
    "sg:address":"1001 Stoneman Ave",
    "sg:city":"Pittsburg",
    "sg:classifiers":[
        {
            "category":"Social Services",
            "type":"Services"
        }
    ],
    "sg:phone":"+1 925 439 5933",
    "sg:postcode":"94565",
    "sg:province":"CA",
    "sg:tags":[
        "youth",
        "organization",
        "center"
    ],
    "wof:name":"East County Boys & Girls Club",
    "wof:placetype":"venue"
},
  "geometry": {"coordinates":[-121.879199,38.004298],"type":"Point"}
}