{
  "type": "Feature",
  "properties": {
    "iso:country":"US",
    "sg:address":"411 W Ave H",
    "sg:city":"Lancaster",
    "sg:classifiers":[
        {
            "category":"Manufacturing",
            "subcategory":"Glass & Minerals",
            "type":"Manufacturing & Wholesale Goods"
        }
    ],
    "sg:phone":"+1 661 942 6620",
    "sg:postcode":"93536",
    "sg:province":"CA",
    "sg:tags":[
        "ready",
        "mix",
        "mfg",
        "concrete"
    ],
    "wof:name":"Hi-Grade Materials Co",
    "wof:placetype":"venue"
},
  "geometry": {"coordinates":[-118.140613,34.718733],"type":"Point"}
}