{
  "type": "Feature",
  "properties": {
    "iso:country":"US",
    "sg:address":"22821 Lake Forest Dr",
    "sg:city":"Lake Forest",
    "sg:classifiers":[
        {
            "category":"Home & Garden",
            "subcategory":"Building Materials",
            "type":"Retail Goods"
        }
    ],
    "sg:phone":"+1 949 581 2899",
    "sg:postcode":"92630",
    "sg:province":"CA",
    "sg:tags":[
        "windows"
    ],
    "wof:name":"Hardy Replacement Windows Inc",
    "wof:placetype":"venue"
},
  "geometry": {"coordinates":[-117.702083,33.640976],"type":"Point"}
}