{
  "type": "Feature",
  "properties": {
    "iso:country":"US",
    "sg:address":"200 Armona Ave",
    "sg:city":"Avenal",
    "sg:classifiers":[
        {
            "category":"Freight",
            "type":"Transportation"
        }
    ],
    "sg:phone":"+1 559 386 9652",
    "sg:postcode":"93204",
    "sg:province":"CA",
    "sg:tags":[
        "trucking"
    ],
    "wof:name":"Mendoza Trucking",
    "wof:placetype":"venue"
},
  "geometry": {"coordinates":[-120.118969,36.005154],"type":"Point"}
}