{
  "type": "Feature",
  "properties": {
    "iso:country":"US",
    "sg:address":"2003 Story Road Suite 100",
    "sg:city":"San Jose",
    "sg:classifiers":[
        {
            "category":"Restaurant",
            "type":"Food & Drink"
        }
    ],
    "sg:phone":"+1 408 926 8888",
    "sg:postcode":"95122",
    "sg:province":"CA",
    "wof:name":"Dragon Restaurant",
    "wof:placetype":"venue"
},
  "geometry": {"coordinates":[-121.831712,37.339776],"type":"Point"}
}