{
  "type": "Feature",
  "properties": {
    "iso:country":"US",
    "sg:address":"1907 S Euclid Ave",
    "sg:city":"Ontario",
    "sg:classifiers":[
        {
            "category":"Education",
            "subcategory":"School",
            "type":"Public Place"
        }
    ],
    "sg:phone":"+1 909 983 1010",
    "sg:postcode":"91762",
    "sg:province":"CA",
    "sg:tags":[
        "elementary"
    ],
    "sg:website":"http://www.ocschools.org",
    "wof:name":"Ontario Christian Elementary School",
    "wof:placetype":"venue"
},
  "geometry": {"coordinates":[-117.650738,34.038853],"type":"Point"}
}