{
  "type": "Feature",
  "properties": {
    "addr:full":"276 Beach Rd Alameda CA 94502",
    "addr:housenumber":"276",
    "addr:postcode":"94502",
    "addr:street":"Beach Rd",
    "iso:country":"US",
    "sg:address":"276 Beach Rd",
    "sg:city":"Alameda",
    "sg:classifiers":[
        {
            "category":"Retail",
            "subcategory":"Pet Boarding",
            "type":"Services"
        }
    ],
    "sg:phone":"+1 510 523 4786",
    "sg:postcode":"94502",
    "sg:province":"CA",
    "sg:tags":[
        "boarding/pet",
        "sitting"
    ],
    "sg:website":"www.poochpalaceretreat.com",
    "wof:name":"Pooch Palace Retreat",
    "wof:placetype":"venue"
},
  "geometry": {"coordinates":[-122.233138,37.733614],"type":"Point"}
}