{
  "type": "Feature",
  "properties": {
    "addr:full":"620 W 184th Street Gardena CA 90248",
    "addr:housenumber":"620",
    "addr:postcode":"90248",
    "addr:street":"W 184Th Street",
    "iso:country":"US",
    "sg:address":"620 W 184th Street",
    "sg:city":"Gardena",
    "sg:classifiers":[
        {
            "category":"Home & Garden",
            "subcategory":"Home Furnishings",
            "type":"Retail Goods"
        }
    ],
    "sg:phone":"+1 310 324 8944",
    "sg:postcode":"90248",
    "sg:province":"CA",
    "sg:tags":[
        "decor"
    ],
    "wof:name":"US Storage Centers",
    "wof:placetype":"venue"
},
  "geometry": {"coordinates":[-118.28379200000001,33.868884],"type":"Point"}
}