{
  "type": "Feature",
  "properties": {
    "addr:full":"1398 6th St Coachella CA 92236",
    "addr:housenumber":"1398",
    "addr:postcode":"92236",
    "addr:street":"6Th St",
    "iso:country":"US",
    "sg:address":"1398 6th St",
    "sg:city":"Coachella",
    "sg:classifiers":[
        {
            "category":"Banks & Credit Unions",
            "subcategory":"Bank",
            "type":"Services"
        },
        {
            "category":"Home & Garden",
            "subcategory":"Furniture",
            "type":"Retail Goods"
        }
    ],
    "sg:phone":"+1 760 398 2424",
    "sg:postcode":"92236",
    "sg:province":"CA",
    "sg:tags":[
        "second",
        "store",
        "hand"
    ],
    "wof:name":"New Life Thrift Store",
    "wof:placetype":"venue"
},
  "geometry": {"coordinates":[-116.177628,33.678059],"type":"Point"}
}