{
  "type": "Feature",
  "properties": {
    "addr:full":"1298 Kifer Road Sunnyvale CA 94086",
    "addr:housenumber":"1298",
    "addr:postcode":"94086",
    "addr:street":"Kifer Road",
    "iso:country":"US",
    "sg:address":"1298 Kifer Road",
    "sg:city":"Sunnyvale",
    "sg:classifiers":[
        {
            "category":"Health Services",
            "subcategory":"Health Practitioner",
            "type":"Services"
        }
    ],
    "sg:phone":"+1 408 737 0668",
    "sg:postcode":"94086",
    "sg:province":"CA",
    "sg:tags":[
        "acupuncture"
    ],
    "sg:website":"www.shinko.com",
    "wof:name":"Shinko DO",
    "wof:placetype":"venue"
},
  "geometry": {"coordinates":[-121.990482,37.37399],"type":"Point"}
}