{
  "type": "Feature",
  "properties": {
    "iso:country":"US",
    "sg:address":"1815 Prairie City Rd",
    "sg:city":"Folsom",
    "sg:classifiers":[
        {
            "category":"Social Services",
            "subcategory":"Child Care",
            "type":"Services"
        }
    ],
    "sg:phone":"+1 916 985 2883",
    "sg:postcode":"95630",
    "sg:province":"CA",
    "wof:name":"Phoenix Schools",
    "wof:placetype":"venue"
},
  "geometry": {"coordinates":[-121.164769,38.65135],"type":"Point"}
}