{
  "type": "Feature",
  "properties": {
    "iso:country":"US",
    "sg:address":"240 W Pine Ave",
    "sg:city":"Lompoc",
    "sg:classifiers":[
        {
            "category":"Real Estate",
            "subcategory":"Real Estate Operator",
            "type":"Services"
        }
    ],
    "sg:phone":"+1 805 735 1448",
    "sg:postcode":"93436",
    "sg:province":"CA",
    "sg:tags":[
        "building",
        "apartment"
    ],
    "wof:name":"Parkside Garden Apartments",
    "wof:placetype":"venue"
},
  "geometry": {"coordinates":[-120.46142999999999,34.650153],"type":"Point"}
}