{
  "type": "Feature",
  "properties": {
    "addr:full":"5736 Fountain Ave Los Angeles CA 90028",
    "addr:housenumber":"5736",
    "addr:postcode":"90028",
    "addr:street":"Fountain Ave",
    "iso:country":"US",
    "sg:address":"5736 Fountain Ave",
    "sg:city":"Los Angeles",
    "sg:classifiers":[
        {
            "category":"Shopping",
            "type":"Retail Goods"
        }
    ],
    "sg:phone":"+1 323 962 9473",
    "sg:postcode":"90028",
    "sg:province":"CA",
    "sg:tags":[
        "pet",
        "shop"
    ],
    "wof:name":"Cappi's Pet Groming Svc",
    "wof:placetype":"venue"
},
  "geometry": {"coordinates":[-118.315673,34.094645],"type":"Point"}
}