{
  "type": "Feature",
  "properties": {
    "iso:country":"US",
    "sg:address":"777 S Figueroa St",
    "sg:city":"Los Angeles",
    "sg:classifiers":[
        {
            "category":"Banks & Credit Unions",
            "subcategory":"Bank",
            "type":"Services"
        }
    ],
    "sg:phone":"+1 213 623 8042",
    "sg:postcode":"90017",
    "sg:province":"CA",
    "sg:tags":[
        "agency",
        "branch",
        "foreign"
    ],
    "wof:name":"United Overseas Bank LTD",
    "wof:placetype":"venue"
},
  "geometry": {"coordinates":[-118.260385,34.04911],"type":"Point"}
}