{
  "type": "Feature",
  "properties": {
    "addr:full":"22342 Ave Empresa Rancho Santa Margarita CA 92688",
    "addr:housenumber":"22342",
    "addr:postcode":"92688",
    "addr:street":"Ave Empresa",
    "iso:country":"US",
    "sg:address":"22342 Ave Empresa",
    "sg:city":"Rancho Santa Margarita",
    "sg:classifiers":[
        {
            "category":"Manufacturing",
            "subcategory":"Chemicals & Compounds",
            "type":"Manufacturing & Wholesale Goods"
        }
    ],
    "sg:phone":"+1 949 589 5100",
    "sg:postcode":"92688",
    "sg:province":"CA",
    "sg:tags":[
        "pharmaceutical",
        "mfg"
    ],
    "wof:name":"Wyeth Consumer Healthcare",
    "wof:placetype":"venue"
},
  "geometry": {"coordinates":[-117.607185,33.637007],"type":"Point"}
}