{
  "type": "Feature",
  "properties": {
    "iso:country":"US",
    "sg:address":"1813 E Palmdale Blvd",
    "sg:city":"Palmdale",
    "sg:classifiers":[
        {
            "category":"Personal",
            "subcategory":"Beauty Salon",
            "type":"Services"
        }
    ],
    "sg:phone":"+1 661 273 1319",
    "sg:postcode":"93550",
    "sg:province":"CA",
    "sg:tags":[
        "manicuring"
    ],
    "wof:name":"Nail Trendz",
    "wof:placetype":"venue"
},
  "geometry": {"coordinates":[-118.096264,34.579759],"type":"Point"}
}