{
  "type": "Feature",
  "properties": {
    "addr:full":"1813 E Palmdale Blvd Palmdale CA 93550",
    "addr:housenumber":"1813",
    "addr:postcode":"ca 93550",
    "addr:street":"E Palmdale Blvd",
    "iso:country":"US",
    "sg:address":"1813 E Palmdale Blvd",
    "sg:city":"Palmdale",
    "sg:classifiers":[
        {
            "category":"Personal",
            "subcategory":"Beauty Salon",
            "type":"Services"
        }
    ],
    "sg:phone":"+1 661 273 1319",
    "sg:postcode":"93550",
    "sg:province":"CA",
    "sg:tags":[
        "manicuring"
    ],
    "wof:name":"Nail Trendz",
    "wof:placetype":"venue"
},
  "geometry": {"coordinates":[-118.09626400000001,34.579759],"type":"Point"}
}