{
  "type": "Feature",
  "properties": {
    "iso:country":"US",
    "sg:address":"1144 Park Way",
    "sg:city":"Lakeport",
    "sg:classifiers":[
        {
            "category":"Organizations",
            "subcategory":"Religious Organization",
            "type":"Services"
        }
    ],
    "sg:phone":"+1 707 263 6243",
    "sg:postcode":"95453",
    "sg:province":"CA",
    "sg:tags":[
        "church"
    ],
    "wof:name":"First Southern Baptist Church",
    "wof:placetype":"venue"
},
  "geometry": {"coordinates":[-122.924329,39.082924],"type":"Point"}
}