{
  "type": "Feature",
  "properties": {
    "addr:full":"2480 California St Sutter CA 95982",
    "addr:housenumber":"2480",
    "addr:postcode":"ca 95982",
    "addr:street":"California St",
    "iso:country":"US",
    "sg:address":"2480 California St",
    "sg:city":"Sutter",
    "sg:classifiers":[
        {
            "category":"Retail",
            "subcategory":"Repair Shop",
            "type":"Services"
        }
    ],
    "sg:phone":"+1 530 632 6763",
    "sg:postcode":"95982",
    "sg:province":"CA",
    "sg:tags":[
        "machine",
        "sewing"
    ],
    "wof:name":"James Sewing Machine Repair",
    "wof:placetype":"venue"
},
  "geometry": {"coordinates":[-121.748902,39.163337],"type":"Point"}
}