{
  "type": "Feature",
  "properties": {
    "addr:full":"1975 Jamacha Rd El Cajon CA 92019",
    "addr:housenumber":"1975",
    "addr:postcode":"92019",
    "addr:street":"Jamacha Rd",
    "iso:country":"US",
    "sg:address":"1975 Jamacha Rd",
    "sg:city":"El Cajon",
    "sg:classifiers":[
        {
            "category":"Recreation",
            "type":"Entertainment"
        }
    ],
    "sg:phone":"+1 619 441 9275",
    "sg:postcode":"92019",
    "sg:province":"CA",
    "sg:tags":[
        "pond",
        "fishing",
        "lake"
    ],
    "wof:name":"Koi-Koi Living Jewels",
    "wof:placetype":"venue"
},
  "geometry": {"coordinates":[-116.927133,32.754483],"type":"Point"}
}