{
  "type": "Feature",
  "properties": {
    "iso:country":"US",
    "sfac:artist":"Riley, Cheryl",
    "sfac:created_at":"1991-97",
    "sfac:credit_line":"Art enrichment for the Bayview Police Station",
    "sfac:display_dimensions":"11' 6\" H X 66\" (dia)",
    "sfac:location_description":"City Department : Bayview Police Station : 345 Williams",
    "sfac:medium":"Custom pre-cast concrete with integral color, crystals and minerals",
    "sfac:revision":"2-0802de0154539e7760817fe6b749e4f2",
    "sfac:title":"Granary Bobo Bench",
    "wof:name":"Granary Bobo Bench",
    "wof:placetype":"venue"
},
  "geometry": {"coordinates":[-122.3973036,37.7299279],"type":"Point"}
}