{
  "type": "Feature",
  "properties": {
    "iso:country":"US",
    "sg:address":"829 State Rte 66",
    "sg:city":"Glendora",
    "sg:classifiers":[
        {
            "category":"Insurance",
            "subcategory":"Insurance Agent",
            "type":"Services"
        }
    ],
    "sg:phone":"+1 626 914 5420",
    "sg:postcode":"91740",
    "sg:province":"CA",
    "wof:name":"Interwest Insurance Svc",
    "wof:placetype":"venue"
},
  "geometry": {"coordinates":[-117.851361,34.128773],"type":"Point"}
}