{
  "type": "Feature",
  "properties": {
    "addr:full":"1620 Oakland Rd San Jose CA 95131",
    "addr:housenumber":"1620",
    "addr:postcode":"95131",
    "addr:street":"Oakland Rd",
    "iso:country":"US",
    "sg:address":"1620 Oakland Rd",
    "sg:city":"San Jose",
    "sg:classifiers":[
        {
            "category":"Organizations",
            "subcategory":"Religious Organization",
            "type":"Services"
        }
    ],
    "sg:phone":"+1 408 467 9490",
    "sg:postcode":"95131",
    "sg:province":"CA",
    "sg:tags":[
        "church"
    ],
    "wof:name":"San Jose Church Of Christ",
    "wof:placetype":"venue"
},
  "geometry": {"coordinates":[-121.895506,37.379137],"type":"Point"}
}