{
  "type": "Feature",
  "properties": {
    "iso:country":"US",
    "sg:address":"19901 Northridge Rd",
    "sg:city":"Chatsworth",
    "sg:classifiers":[
        {
            "category":"Wholesale",
            "subcategory":"Books, Periodicals, & Newspapers",
            "type":"Manufacturing & Wholesale Goods"
        }
    ],
    "sg:phone":"+1 818 363 7038",
    "sg:postcode":"91311",
    "sg:province":"CA",
    "wof:name":"Show Circuit Magazine LLC",
    "wof:placetype":"venue"
},
  "geometry": {"coordinates":[-118.56681399999999,34.261798],"type":"Point"}
}