{
  "type": "Feature",
  "properties": {
    "addr:full":"1929 Irving St San Francisco CA 94122",
    "addr:housenumber":"1929",
    "addr:postcode":"94122",
    "addr:street":"Irving St",
    "iso:country":"US",
    "sg:address":"1929 Irving St",
    "sg:city":"San Francisco",
    "sg:classifiers":[
        {
            "category":"Education",
            "subcategory":"Special Training",
            "type":"Public Place"
        }
    ],
    "sg:phone":"+1 415 681 7277",
    "sg:postcode":"94122",
    "sg:province":"CA",
    "sg:tags":[
        "instruction",
        "driving"
    ],
    "wof:name":"Excel Driving School",
    "wof:placetype":"venue"
},
  "geometry": {"coordinates":[-122.47902000000001,37.763406],"type":"Point"}
}