{
  "type": "Feature",
  "properties": {
    "addr:full":"902 W Lodi Ave Lodi CA 95240",
    "addr:housenumber":"902",
    "addr:postcode":"95240",
    "addr:street":"W Lodi Ave",
    "iso:country":"US",
    "sg:address":"902 W Lodi Ave",
    "sg:city":"Lodi",
    "sg:classifiers":[
        {
            "category":"Personal",
            "subcategory":"Beauty Salon",
            "type":"Services"
        }
    ],
    "sg:phone":"+1 209 369 0248",
    "sg:postcode":"95240",
    "sg:province":"CA",
    "wof:name":"Styles Hair & Nail Fashions",
    "wof:placetype":"venue"
},
  "geometry": {"coordinates":[-121.28500699999999,38.129893],"type":"Point"}
}