{
  "type": "Feature",
  "properties": {
    "addr:full":"61 Hacienda Carmel Carmel CA 93923",
    "addr:housenumber":"61",
    "addr:postcode":"93923",
    "addr:street":"Hacienda Carmel",
    "iso:country":"US",
    "sg:address":"61 Hacienda Carmel",
    "sg:city":"Carmel",
    "sg:classifiers":[
        {
            "category":"Structure",
            "subcategory":"Office Building",
            "type":"Public Place"
        }
    ],
    "sg:phone":"+1 831 625 7561",
    "sg:postcode":"93923",
    "sg:province":"CA",
    "sg:tags":[
        "park"
    ],
    "wof:name":"St. John Properties",
    "wof:placetype":"venue"
},
  "geometry": {"coordinates":[-121.877284,36.536529],"type":"Point"}
}