{
  "type": "Feature",
  "properties": {
    "addr:full":"2000 5th St Berkeley CA 94710",
    "addr:housenumber":"2000",
    "addr:postcode":"94710",
    "addr:street":"5Th St",
    "iso:country":"US",
    "sg:address":"2000 5th St",
    "sg:city":"Berkeley",
    "sg:classifiers":[
        {
            "category":"Food & Beverages",
            "subcategory":"Groceries & Convenience Stores",
            "type":"Retail Goods"
        }
    ],
    "sg:phone":"+1 510 704 6500",
    "sg:postcode":"94710",
    "sg:province":"CA",
    "sg:tags":[
        "grocer"
    ],
    "wof:name":"Ideal Distributing",
    "wof:placetype":"venue"
},
  "geometry": {"coordinates":[-122.298812,37.867655],"type":"Point"}
}