{
  "type": "Feature",
  "properties": {
    "addr:full":"3295 Avenida la Cima Carlsbad CA 92009",
    "addr:housenumber":"3295",
    "addr:postcode":"92009",
    "addr:street":"Avenida La Cima",
    "iso:country":"US",
    "sg:address":"3295 Avenida la Cima",
    "sg:city":"Carlsbad",
    "sg:classifiers":[
        {
            "category":"Banks & Credit Unions",
            "subcategory":"Investment Brokerage",
            "type":"Services"
        },
        {
            "category":"Insurance",
            "subcategory":"Hazard Insurance",
            "type":"Services"
        }
    ],
    "sg:phone":"+1 760 554 5900",
    "sg:postcode":"92009",
    "sg:province":"CA",
    "sg:tags":[
        "agent",
        "resume"
    ],
    "wof:name":"P Kenny Joseph & Associates Inc",
    "wof:placetype":"venue"
},
  "geometry": {"coordinates":[-117.238677,33.064719],"type":"Point"}
}