{
  "type": "Feature",
  "properties": {
    "iso:country":"US",
    "sg:address":"1243 Woodside Rd",
    "sg:city":"Redwood City",
    "sg:classifiers":[
        {
            "category":"Professional",
            "subcategory":"Accounting & Tax Preparation",
            "type":"Services"
        }
    ],
    "sg:phone":"+1 650 366 3211",
    "sg:postcode":"94061",
    "sg:province":"CA",
    "sg:tags":[
        "accountant"
    ],
    "wof:name":"David E Ringman CPA",
    "wof:placetype":"venue"
},
  "geometry": {"coordinates":[-122.226914,37.458276],"type":"Point"}
}