{
  "type": "Feature",
  "properties": {
    "addr:full":"559 W 18th St San Pedro CA 90731",
    "addr:housenumber":"559",
    "addr:postcode":"90731",
    "addr:street":"W 18Th St",
    "iso:country":"US",
    "sg:address":"559 W 18th St",
    "sg:city":"San Pedro",
    "sg:classifiers":[
        {
            "category":"Building & Trades",
            "subcategory":"Plumbing",
            "type":"Services"
        }
    ],
    "sg:phone":"+1 310 832 3597",
    "sg:postcode":"90731",
    "sg:province":"CA",
    "sg:tags":[
        "contractor"
    ],
    "wof:name":"Adriatic Coast Plumbing & Htg",
    "wof:placetype":"venue"
},
  "geometry": {"coordinates":[-118.289084,33.7278],"type":"Point"}
}