{
  "type": "Feature",
  "properties": {
    "addr:full":"1344 1st Ave Oroville CA 95965",
    "addr:housenumber":"1344",
    "addr:postcode":"95965",
    "addr:street":"1St Ave",
    "iso:country":"US",
    "sg:address":"1344 1st Ave",
    "sg:city":"Oroville",
    "sg:classifiers":[
        {
            "category":"Real Estate",
            "subcategory":"Real Estate Agent",
            "type":"Services"
        }
    ],
    "sg:phone":"+1 530 532 0100",
    "sg:postcode":"95965",
    "sg:province":"CA",
    "sg:tags":[
        "appraiser"
    ],
    "wof:name":"Gold Country Appraisal Svc",
    "wof:placetype":"venue"
},
  "geometry": {"coordinates":[-121.562467,39.51127],"type":"Point"}
}