{
  "type": "Feature",
  "properties": {
    "addr:full":"55 Las Colinas Ln San Jose CA 95119",
    "addr:housenumber":"55",
    "addr:postcode":"95119",
    "addr:street":"Las Colinas Ln",
    "iso:country":"US",
    "sg:address":"55 Las Colinas Ln",
    "sg:city":"San Jose",
    "sg:classifiers":[
        {
            "category":"Manufacturing",
            "subcategory":"Electronics",
            "type":"Manufacturing & Wholesale Goods"
        }
    ],
    "sg:phone":"+1 408 362 4800",
    "sg:postcode":"95119",
    "sg:province":"CA",
    "sg:tags":[
        "manufacture",
        "design",
        "optical",
        "networking",
        "market"
    ],
    "wof:name":"Motorola",
    "wof:placetype":"venue"
},
  "geometry": {"coordinates":[-121.777895,37.238147],"type":"Point"}
}