{
  "type": "Feature",
  "properties": {
    "iso:country":"US",
    "sg:address":"876 Seacoast Dr",
    "sg:city":"Imperial Beach",
    "sg:classifiers":[
        {
            "category":"Food & Beverages",
            "subcategory":"Bakery",
            "type":"Retail Goods"
        }
    ],
    "sg:phone":"+1 619 575 6961",
    "sg:postcode":"91932",
    "sg:province":"CA",
    "sg:tags":[
        "sandwich"
    ],
    "sg:website":"www.subway.com",
    "wof:name":"Subway",
    "wof:placetype":"venue"
},
  "geometry": {"coordinates":[-117.13200399999999,32.580502],"type":"Point"}
}