{
  "type": "Feature",
  "properties": {
    "addr:full":"2118 Meadowview Rd Sacramento CA 95832",
    "addr:housenumber":"2118",
    "addr:postcode":"95832",
    "addr:street":"Meadowview Rd",
    "iso:country":"US",
    "sg:address":"2118 Meadowview Rd",
    "sg:city":"Sacramento",
    "sg:classifiers":[
        {
            "category":"Government",
            "subcategory":"Office",
            "type":"Public Place"
        }
    ],
    "sg:phone":"+1 916 427 0368",
    "sg:postcode":"95832",
    "sg:province":"CA",
    "sg:tags":[
        "government-united",
        "state"
    ],
    "wof:name":"Pta California Congress Of Parents Teachers & Students Inc",
    "wof:placetype":"venue"
},
  "geometry": {"coordinates":[-121.49231,38.481418],"type":"Point"}
}