{
  "type": "Feature",
  "properties": {
    "iso:country":"US",
    "sg:address":"1475 Azalea Dr",
    "sg:city":"Carpinteria",
    "sg:classifiers":[
        {
            "category":"Building & Trades",
            "subcategory":"Construction",
            "type":"Services"
        }
    ],
    "sg:phone":"+1 805 684 8946",
    "sg:postcode":"93013",
    "sg:province":"CA",
    "sg:tags":[
        "remodeling",
        "altering",
        "wallcoverings-installation",
        "wallpaper",
        "contractor",
        "painting"
    ],
    "wof:name":"Pitcock Gary",
    "wof:placetype":"venue"
},
  "geometry": {"coordinates":[-119.520943,34.406248],"type":"Point"}
}