{
  "type": "Feature",
  "properties": {
    "iso:country":"US",
    "sg:address":"7327 State Hwy 29",
    "sg:city":"Kelseyville",
    "sg:classifiers":[
        {
            "category":"Farming",
            "subcategory":"Vineyard",
            "type":"Manufacturing & Wholesale Goods"
        }
    ],
    "sg:phone":"+1 707 944 9265",
    "sg:postcode":"95451",
    "sg:province":"CA",
    "wof:name":"Ladera Vineyards",
    "wof:placetype":"venue"
},
  "geometry": {"coordinates":[-122.827187,38.954405],"type":"Point"}
}