{
  "type": "Feature",
  "properties": {
    "addr:full":"330 E State St Ontario CA 91761",
    "addr:housenumber":"330",
    "addr:postcode":"91761",
    "addr:street":"E State St",
    "iso:country":"US",
    "sg:address":"330 E State St",
    "sg:city":"Ontario",
    "sg:classifiers":[
        {
            "category":"Manufacturing",
            "subcategory":"Metals",
            "type":"Manufacturing & Wholesale Goods"
        }
    ],
    "sg:phone":"+1 909 391 2216",
    "sg:postcode":"91761",
    "sg:province":"CA",
    "sg:tags":[
        "metalwork",
        "architectural",
        "mfg"
    ],
    "wof:name":"Nava Wrought Iron & Ornamental",
    "wof:placetype":"venue"
},
  "geometry": {"coordinates":[-117.647572,34.059991],"type":"Point"}
}