{
  "type": "Feature",
  "properties": {
    "addr:full":"Washington St & The Embarcadero San Francisco CA 94111",
    "addr:postcode":"94111",
    "addr:street":"Washington St & The Embarcadero",
    "iso:country":"US",
    "sg:address":"Washington St & The Embarcadero",
    "sg:city":"San Francisco",
    "sg:classifiers":[
        {
            "category":"Parking",
            "type":"Transportation"
        }
    ],
    "sg:phone":"+1 415 834 9190",
    "sg:postcode":"94111",
    "sg:province":"CA",
    "wof:name":"Ace Parking Management",
    "wof:placetype":"venue"
},
  "geometry": {"coordinates":[-122.39555900000001,37.796625],"type":"Point"}
}