{
  "type": "Feature",
  "properties": {
    "addr:full":"4846 S Eastern Ave City Of Commerce CA 90040",
    "addr:housenumber":"4846",
    "addr:postcode":"90040",
    "addr:street":"S Eastern Ave",
    "iso:country":"US",
    "sg:address":"4846 S Eastern Ave",
    "sg:city":"City Of Commerce",
    "sg:classifiers":[
        {
            "category":"Restaurant",
            "type":"Food & Drink"
        }
    ],
    "sg:phone":"+1 323 728 1444",
    "sg:postcode":"90040",
    "sg:province":"CA",
    "wof:name":"Baja Burrito",
    "wof:placetype":"venue"
},
  "geometry": {"coordinates":[-118.161241,33.990841],"type":"Point"}
}