{
  "type": "Feature",
  "properties": {
    "addr:full":"3550 Pacheco Blvd Martinez CA 94553",
    "addr:housenumber":"3550",
    "addr:postcode":"94553",
    "addr:street":"Pacheco Blvd",
    "iso:country":"US",
    "sg:address":"3550 Pacheco Blvd",
    "sg:city":"Martinez",
    "sg:classifiers":[
        {
            "category":"Retail",
            "subcategory":"Auto Repair",
            "type":"Services"
        }
    ],
    "sg:phone":"+1 925 228 6136",
    "sg:postcode":"94553",
    "sg:province":"CA",
    "sg:tags":[
        "van",
        "conversion",
        "truck",
        "accessory"
    ],
    "wof:name":"Ace Truck Box & Accessories",
    "wof:placetype":"venue"
},
  "geometry": {"coordinates":[-122.106364,38.012301],"type":"Point"}
}