{
  "type": "Feature",
  "properties": {
    "addr:full":"484 Lake Park Ave Oakland CA 94610",
    "addr:housenumber":"484",
    "addr:postcode":"94610",
    "addr:street":"Lake Park Ave",
    "iso:country":"US",
    "sg:address":"484 Lake Park Ave",
    "sg:city":"Oakland",
    "sg:classifiers":[
        {
            "category":"Professional",
            "subcategory":"Management & Consulting",
            "type":"Services"
        }
    ],
    "sg:phone":"+1 510 836 4949",
    "sg:postcode":"94610",
    "sg:province":"CA",
    "sg:tags":[
        "construction"
    ],
    "wof:name":"Construction Clerical Unltd",
    "wof:placetype":"venue"
},
  "geometry": {"coordinates":[-122.2473,37.810829],"type":"Point"}
}