{
  "type": "Feature",
  "properties": {
    "addr:full":"9070 Castillo Dr San Simeon CA 93452",
    "addr:housenumber":"9070",
    "addr:postcode":"93452",
    "addr:street":"Castillo Dr",
    "iso:country":"US",
    "sg:address":"9070 Castillo Dr",
    "sg:city":"San Simeon",
    "sg:classifiers":[
        {
            "category":"Travel",
            "subcategory":"Hotels & Motels",
            "type":"Entertainment"
        }
    ],
    "sg:phone":"+1 805 927 8691",
    "sg:postcode":"93452",
    "sg:province":"CA",
    "wof:name":"Motel 6",
    "wof:placetype":"venue"
},
  "geometry": {"coordinates":[-121.146004,35.615101],"type":"Point"}
}