{
  "type": "Feature",
  "properties": {
    "iso:country":"US",
    "sg:address":"1212 S Atlantic Blvd",
    "sg:city":"Los Angeles",
    "sg:classifiers":[
        {
            "category":"Autos & Motor Vehicles",
            "subcategory":"Automobile Sales",
            "type":"Retail Goods"
        }
    ],
    "sg:phone":"+1 323 264 6400",
    "sg:postcode":"90022",
    "sg:province":"CA",
    "sg:tags":[
        "car",
        "dealer"
    ],
    "wof:name":"Joe's Cars",
    "wof:placetype":"venue"
},
  "geometry": {"coordinates":[-118.158447,34.016122],"type":"Point"}
}