{
  "type": "Feature",
  "properties": {
    "addr:full":"845 92nd Ave Oakland CA 94603",
    "addr:housenumber":"845",
    "addr:postcode":"94603",
    "addr:street":"92Nd Ave",
    "iso:country":"US",
    "sg:address":"845 92nd Ave",
    "sg:city":"Oakland",
    "sg:classifiers":[
        {
            "category":"Wholesale",
            "subcategory":"Machinery & Supplies",
            "type":"Manufacturing & Wholesale Goods"
        }
    ],
    "sg:phone":"+1 510 639 3200",
    "sg:postcode":"94603",
    "sg:province":"CA",
    "sg:tags":[
        "pump"
    ],
    "wof:name":"Sulzer Pumps Houston Inc.",
    "wof:placetype":"venue"
},
  "geometry": {"coordinates":[-122.184061,37.743641],"type":"Point"}
}