{
  "type": "Feature",
  "properties": {
    "iso:country":"US",
    "sg:address":"2075 E Highland Ave",
    "sg:city":"San Bernardino",
    "sg:classifiers":[
        {
            "category":"Restaurant",
            "type":"Food & Drink"
        }
    ],
    "sg:phone":"+1 909 864 2237",
    "sg:postcode":"92404",
    "sg:province":"CA",
    "wof:name":"Tacos Arandas",
    "wof:placetype":"venue"
},
  "geometry": {"coordinates":[-117.240815,34.135936],"type":"Point"}
}