{
  "type": "Feature",
  "properties": {
    "addr:full":"2585 Tuscany Way Fullerton CA 92835",
    "addr:housenumber":"2585",
    "addr:postcode":"92835",
    "addr:street":"Tuscany Way",
    "iso:country":"US",
    "sg:address":"2585 Tuscany Way",
    "sg:city":"Fullerton",
    "sg:classifiers":[
        {
            "category":"Home & Garden",
            "subcategory":"Furniture",
            "type":"Retail Goods"
        }
    ],
    "sg:phone":"+1 951 738 9028",
    "sg:postcode":"92835",
    "sg:province":"CA",
    "wof:name":"Cost Plus World Market",
    "wof:placetype":"venue"
},
  "geometry": {"coordinates":[-117.888988,33.901524],"type":"Point"}
}