{
  "type": "Feature",
  "properties": {
    "addr:full":"251 Shaw Rd S San Francisco CA 94080",
    "addr:housenumber":"251",
    "addr:postcode":"94080",
    "addr:street":"Shaw Rd S",
    "iso:country":"US",
    "sg:address":"251 Shaw Rd",
    "sg:city":"S San Francisco",
    "sg:classifiers":[
        {
            "category":"Wholesale",
            "subcategory":"Auto Parts",
            "type":"Manufacturing & Wholesale Goods"
        }
    ],
    "sg:phone":"+1 650 873 8100",
    "sg:postcode":"94080",
    "sg:province":"CA",
    "sg:tags":[
        "equipment",
        "truck"
    ],
    "wof:name":"Mclellan Equip Inc",
    "wof:placetype":"venue"
},
  "geometry": {"coordinates":[-122.40719799999999,37.64085],"type":"Point"}
}