{
  "type": "Feature",
  "properties": {
    "addr:full":"2450 S Sequoia Dr Compton CA 90220",
    "addr:housenumber":"2450",
    "addr:postcode":"90220",
    "addr:street":"S Sequoia Dr",
    "iso:country":"US",
    "sg:address":"2450 S Sequoia Dr",
    "sg:city":"Compton",
    "sg:classifiers":[
        {
            "category":"Transit Center",
            "subcategory":"Freight",
            "type":"Transportation"
        }
    ],
    "sg:phone":"+1 888 617 6785",
    "sg:postcode":"90220",
    "sg:province":"CA",
    "sg:tags":[
        "forwarding",
        "trucking-motor"
    ],
    "sg:website":"http://etcinternational.rtrk.com/?scid=1749750",
    "wof:name":"International Freight",
    "wof:placetype":"venue"
},
  "geometry": {"coordinates":[-118.241123,33.868063],"type":"Point"}
}