{
  "type": "Feature",
  "properties": {
    "addr:full":"819 W Whittier Blvd Montebello CA 90640",
    "addr:housenumber":"819",
    "addr:postcode":"90640",
    "addr:street":"W Whittier Blvd",
    "iso:country":"US",
    "sg:address":"819 W Whittier Blvd",
    "sg:city":"Montebello",
    "sg:classifiers":[
        {
            "category":"Health Services",
            "subcategory":"Doctor",
            "type":"Services"
        },
        {
            "category":"Health Services",
            "subcategory":"Health Practitioner",
            "type":"Services"
        }
    ],
    "sg:phone":"+1 323 890 2907",
    "sg:postcode":"90640",
    "sg:province":"CA",
    "sg:tags":[
        "physician",
        "surgeons",
        "drug",
        "abuse",
        "medicine",
        "addiction"
    ],
    "wof:name":"C D I F",
    "wof:placetype":"venue"
},
  "geometry": {"coordinates":[-118.108896,34.010221],"type":"Point"}
}