{
  "type": "Feature",
  "properties": {
    "addr:full":"4200 W Capitol Ave West Sacramento CA 95691",
    "addr:housenumber":"4200",
    "addr:postcode":"95691",
    "addr:street":"W Capitol Ave",
    "iso:country":"US",
    "sg:address":"4200 W Capitol Ave",
    "sg:city":"West Sacramento",
    "sg:classifiers":[
        {
            "category":"Freight",
            "type":"Transportation"
        }
    ],
    "sg:phone":"+1 916 371 4555",
    "sg:postcode":"95691",
    "sg:province":"CA",
    "sg:tags":[
        "operator",
        "local",
        "storage",
        "trucking"
    ],
    "wof:name":"Roadway Express Inc",
    "wof:placetype":"venue"
},
  "geometry": {"coordinates":[-121.571743,38.577101],"type":"Point"}
}