{
  "type": "Feature",
  "properties": {
    "addr:full":"356 Grove St Half Moon Bay CA 94019",
    "addr:housenumber":"356",
    "addr:postcode":"94019",
    "addr:street":"Grove St",
    "iso:country":"US",
    "sg:address":"356 Grove St",
    "sg:city":"Half Moon Bay",
    "sg:classifiers":[
        {
            "category":"Professional",
            "type":"Services"
        }
    ],
    "sg:phone":"+1 650 574 4917",
    "sg:postcode":"94019",
    "sg:province":"CA",
    "wof:name":"Hope Worldwide Northern Cal",
    "wof:placetype":"venue"
},
  "geometry": {"coordinates":[-122.43768799999999,37.45448],"type":"Point"}
}