{
  "type": "Feature",
  "properties": {
    "addr:full":"5858 Horton Street Suite 550 Emeryville CA 94608",
    "addr:housenumber":"5858",
    "addr:postcode":"94608",
    "addr:street":"Horton Street Suite 550",
    "iso:country":"US",
    "sg:address":"5858 Horton Street Suite 550",
    "sg:city":"Emeryville",
    "sg:classifiers":[
        {
            "category":"Professional",
            "subcategory":"Research",
            "type":"Services"
        }
    ],
    "sg:phone":"+1 510 420 6700",
    "sg:postcode":"94608",
    "sg:province":"CA",
    "sg:website":"http://www.tethysbio.com",
    "wof:name":"Tethys BioScience",
    "wof:placetype":"venue"
},
  "geometry": {"coordinates":[-122.29116,37.839898],"type":"Point"}
}