{
  "type": "Feature",
  "properties": {
    "addr:full":"1400 Chester Ave Bakersfield CA 93301",
    "addr:housenumber":"1400",
    "addr:postcode":"93301",
    "addr:street":"Chester Ave",
    "iso:country":"US",
    "sg:address":"1400 Chester Ave",
    "sg:city":"Bakersfield",
    "sg:classifiers":[
        {
            "category":"Organizations",
            "subcategory":"Religious Organization",
            "type":"Services"
        }
    ],
    "sg:phone":"+1 661 589 2473",
    "sg:postcode":"93301",
    "sg:province":"CA",
    "sg:tags":[
        "church"
    ],
    "wof:name":"First Vision Church",
    "wof:placetype":"venue"
},
  "geometry": {"coordinates":[-119.018821,35.371389],"type":"Point"}
}