{
  "type": "Feature",
  "properties": {
    "addr:full":"234 Carroll St Sunnyvale CA 94086",
    "addr:housenumber":"234",
    "addr:postcode":"94086",
    "addr:street":"Carroll St",
    "iso:country":"US",
    "sg:address":"234 Carroll St",
    "sg:city":"Sunnyvale",
    "sg:classifiers":[
        {
            "category":"Manufacturing",
            "subcategory":"Printing",
            "type":"Manufacturing & Wholesale Goods"
        }
    ],
    "sg:phone":"+1 408 567 1281",
    "sg:postcode":"94086",
    "sg:province":"CA",
    "sg:tags":[
        "multimedia"
    ],
    "wof:name":"Broad Media",
    "wof:placetype":"venue"
},
  "geometry": {"coordinates":[-122.02857899999999,37.374376],"type":"Point"}
}