{
  "type": "Feature",
  "properties": {
    "addr:full":"19662 Osceola Ct Redding CA 96002",
    "addr:housenumber":"19662",
    "addr:postcode":"96002",
    "addr:street":"Osceola Ct",
    "iso:country":"US",
    "sg:address":"19662 Osceola Ct",
    "sg:city":"Redding",
    "sg:classifiers":[
        {
            "category":"Wholesale",
            "subcategory":"Home Furnishings",
            "type":"Manufacturing & Wholesale Goods"
        }
    ],
    "sg:phone":"+1 530 226 0903",
    "sg:postcode":"96002",
    "sg:province":"CA",
    "wof:name":"Blinds Now",
    "wof:placetype":"venue"
},
  "geometry": {"coordinates":[-122.328311,40.511678],"type":"Point"}
}