{
  "type": "Feature",
  "properties": {
    "iso:country":"US",
    "sg:address":"235 S Mcdowell Blvd",
    "sg:city":"Petaluma",
    "sg:classifiers":[
        {
            "category":"Restaurant",
            "type":"Food & Drink"
        }
    ],
    "sg:phone":"+1 707 762 1843",
    "sg:postcode":"94954",
    "sg:province":"CA",
    "sg:tags":[
        "mexican"
    ],
    "wof:name":"Pueblo Del Sol",
    "wof:placetype":"venue"
},
  "geometry": {"coordinates":[-122.624934,38.248698],"type":"Point"}
}