{
  "type": "Feature",
  "properties": {
    "addr:full":"2309 Santa Clara Ave Alameda CA 94501",
    "addr:housenumber":"2309",
    "addr:postcode":"94501",
    "addr:street":"Santa Clara Ave",
    "iso:country":"US",
    "sg:address":"2309 Santa Clara Ave",
    "sg:city":"Alameda",
    "sg:classifiers":[
        {
            "category":"Insurance",
            "subcategory":"Insurance Agent",
            "type":"Services"
        }
    ],
    "sg:phone":"+1 510 522 4244",
    "sg:postcode":"94501",
    "sg:province":"CA",
    "wof:name":"Thruston Insurance Svc",
    "wof:placetype":"venue"
},
  "geometry": {"coordinates":[-122.243038,37.765868],"type":"Point"}
}