{
  "type": "Feature",
  "properties": {
    "iso:country":"US",
    "sg:address":"1714 N Las Palmas Ave",
    "sg:city":"Los Angeles",
    "sg:classifiers":[
        {
            "category":"Bars & Pubs",
            "subcategory":"Lounge",
            "type":"Food & Drink"
        },
        {
            "category":"Restaurant",
            "type":"Food & Drink"
        },
        {
            "category":"Recreation",
            "subcategory":"Dance Hall",
            "type":"Entertainment"
        }
    ],
    "sg:phone":"+1 323 464 0171",
    "sg:postcode":"90028",
    "sg:province":"CA",
    "sg:tags":[
        "club"
    ],
    "wof:name":"LAX",
    "wof:placetype":"venue"
},
  "geometry": {"coordinates":[-118.336141,34.102029],"type":"Point"}
}