{
  "type": "Feature",
  "properties": {
    "iso:country":"US",
    "sg:address":"222 Winston St",
    "sg:city":"Los Angeles",
    "sg:classifiers":[
        {
            "category":"Shopping",
            "subcategory":"Shoes",
            "type":"Retail Goods"
        }
    ],
    "sg:phone":"+1 213 629 3355",
    "sg:postcode":"90013",
    "sg:province":"CA",
    "sg:tags":[
        "footwear"
    ],
    "wof:name":"Lanovia Shoes",
    "wof:placetype":"venue"
},
  "geometry": {"coordinates":[-118.24570799999999,34.045616],"type":"Point"}
}