{
  "type": "Feature",
  "properties": {
    "addr:full":"1080 Saratoga Ave Grover Beach CA 93433",
    "addr:housenumber":"1080",
    "addr:postcode":"93433",
    "addr:street":"Saratoga Ave",
    "iso:country":"US",
    "sg:address":"1080 Saratoga Ave",
    "sg:city":"Grover Beach",
    "sg:classifiers":[
        {
            "category":"Professional",
            "type":"Services"
        }
    ],
    "sg:phone":"+1 805 489 7855",
    "sg:postcode":"93433",
    "sg:province":"CA",
    "wof:name":"Seaquine Barns Inc",
    "wof:placetype":"venue"
},
  "geometry": {"coordinates":[-120.61785399999999,35.126109],"type":"Point"}
}