{
  "type": "Feature",
  "properties": {
    "iso:country":"US",
    "sg:address":"175 N Main St",
    "sg:city":"Bishop",
    "sg:classifiers":[
        {
            "category":"Bars & Pubs",
            "type":"Food & Drink"
        }
    ],
    "sg:phone":"+1 760 872 7171",
    "sg:postcode":"93514",
    "sg:province":"CA",
    "sg:tags":[
        "lounge",
        "cocktail"
    ],
    "wof:name":"Mc Murry's Bar",
    "wof:placetype":"venue"
},
  "geometry": {"coordinates":[-118.395365,37.361636],"type":"Point"}
}