{
  "type": "Feature",
  "properties": {
    "addr:full":"130 Melville Ave San Anselmo CA 94960",
    "addr:housenumber":"130",
    "addr:postcode":"94960",
    "addr:street":"Melville Ave",
    "iso:country":"US",
    "sg:address":"130 Melville Ave",
    "sg:city":"San Anselmo",
    "sg:classifiers":[
        {
            "category":"Health Services",
            "subcategory":"Doctor",
            "type":"Services"
        }
    ],
    "sg:phone":"+1 415 453 8920",
    "sg:postcode":"94960",
    "sg:province":"CA",
    "sg:tags":[
        "physician",
        "surgeon"
    ],
    "wof:name":"Martin G Blinder MD",
    "wof:placetype":"venue"
},
  "geometry": {"coordinates":[-122.57002199999999,37.971206],"type":"Point"}
}