{
  "type": "Feature",
  "properties": {
    "iso:country":"US",
    "sg:address":"506 S Nevada St",
    "sg:city":"Oceanside",
    "sg:classifiers":[
        {
            "category":"Organizations",
            "subcategory":"Religious Organization",
            "type":"Services"
        }
    ],
    "sg:phone":"+1 760 722 0702",
    "sg:postcode":"92054",
    "sg:province":"CA",
    "sg:tags":[
        "church"
    ],
    "wof:name":"Hope Chapel",
    "wof:placetype":"venue"
},
  "geometry": {"coordinates":[-117.371825,33.191167],"type":"Point"}
}