{
  "type": "Feature",
  "properties": {
    "addr:full":"2721 E Coast Hwy Corona Del Mar CA 92625",
    "addr:housenumber":"2721",
    "addr:postcode":"92625",
    "addr:street":"E Coast Hwy",
    "iso:country":"US",
    "sg:address":"2721 E Coast Hwy",
    "sg:city":"Corona Del Mar",
    "sg:classifiers":[
        {
            "category":"Professional",
            "subcategory":"Lawyer & Legal Services",
            "type":"Services"
        }
    ],
    "sg:phone":"+1 949 675 1033",
    "sg:postcode":"92625",
    "sg:province":"CA",
    "wof:name":"Law Offices Of David Demurjian",
    "wof:placetype":"venue"
},
  "geometry": {"coordinates":[-117.87299,33.601328],"type":"Point"}
}