{
  "type": "Feature",
  "properties": {
    "iso:country":"US",
    "sfac:artist":"Voulkos, Peter",
    "sfac:created_at":"1969-1971",
    "sfac:credit_line":"Commissioned for the Hall of Justice",
    "sfac:display_dimensions":"360 in. x 480 in.",
    "sfac:location_description":"Public Display : Hall of Justice : 850 Bryant at 7th St. : West Corner Lawn",
    "sfac:medium":"Bronze",
    "sfac:revision":"2-683aa19e7430455c339e69f75c9b0e4d",
    "sfac:title":"Untitled",
    "wof:name":"Untitled",
    "wof:placetype":"venue"
},
  "geometry": {"coordinates":[-122.4194155,37.7749295],"type":"Point"}
}