{
  "type": "Feature",
  "properties": {
    "addr:full":"13518 Poway Rd Poway CA 92064",
    "addr:housenumber":"13518",
    "addr:postcode":"ca 92064",
    "addr:street":"Poway Rd",
    "iso:country":"US",
    "sg:address":"13518 Poway Rd",
    "sg:city":"Poway",
    "sg:classifiers":[
        {
            "category":"Banks & Credit Unions",
            "subcategory":"Bank",
            "type":"Services"
        }
    ],
    "sg:phone":"+1 858 748 1675",
    "sg:postcode":"92064",
    "sg:province":"CA",
    "sg:tags":[
        "personal",
        "institution"
    ],
    "wof:name":"Advance America",
    "wof:placetype":"venue"
},
  "geometry": {"coordinates":[-117.038965,32.956491],"type":"Point"}
}