{
  "type": "Feature",
  "properties": {
    "addr:full":"12636 High Bluff Drive Suite 110 San Diego CA 92130",
    "addr:housenumber":"12636",
    "addr:postcode":"92130",
    "addr:street":"High Bluff Drive Suite 110",
    "iso:country":"US",
    "sg:address":"12636 High Bluff Drive Suite 110",
    "sg:city":"San Diego",
    "sg:classifiers":[
        {
            "category":"Professional",
            "subcategory":"Lawyer & Legal Services",
            "type":"Services"
        }
    ],
    "sg:phone":"+1 858 481 4844",
    "sg:postcode":"92130",
    "sg:province":"CA",
    "sg:website":"www.taxlawfirm.net",
    "wof:name":"A Tax Law Firm Net",
    "wof:placetype":"venue"
},
  "geometry": {"coordinates":[-117.240707,32.947354],"type":"Point"}
}