{
  "type": "Feature",
  "properties": {
    "iso:country":"US",
    "sg:address":"1525 Fountain Grove Pkwy",
    "sg:city":"Santa Rosa",
    "sg:classifiers":[
        {
            "category":"Sports & Exercise",
            "subcategory":"Golf",
            "type":"Entertainment"
        }
    ],
    "sg:phone":"+1 707 544 5100",
    "sg:postcode":"95403",
    "sg:province":"CA",
    "sg:tags":[
        "course",
        "public"
    ],
    "wof:name":"Fountain Grove Golf & Athc CLB",
    "wof:placetype":"venue"
},
  "geometry": {"coordinates":[-122.709963,38.487462],"type":"Point"}
}