{
  "type": "Feature",
  "properties": {
    "addr:full":"21112 Anza Ave Torrance CA 90503",
    "addr:housenumber":"21112",
    "addr:postcode":"90503",
    "addr:street":"Anza Ave",
    "iso:country":"US",
    "sg:address":"21112 Anza Ave",
    "sg:city":"Torrance",
    "sg:classifiers":[
        {
            "category":"Restaurant",
            "type":"Food & Drink"
        }
    ],
    "sg:phone":"+1 310 371 1586",
    "sg:postcode":"90503",
    "sg:province":"CA",
    "wof:name":"Carl's Jr Restaurants",
    "wof:placetype":"venue"
},
  "geometry": {"coordinates":[-118.362999,33.8382],"type":"Point"}
}