{
  "type": "Feature",
  "properties": {
    "iso:country":"US",
    "sg:address":"33540 Hayfield Cir",
    "sg:city":"Wildomar",
    "sg:classifiers":[
        {
            "category":"Wholesale",
            "subcategory":"Electrical",
            "type":"Manufacturing & Wholesale Goods"
        }
    ],
    "sg:phone":"+1 951 244 5499",
    "sg:postcode":"92595",
    "sg:province":"CA",
    "wof:name":"Affordable Washer & Dryer Svc",
    "wof:placetype":"venue"
},
  "geometry": {"coordinates":[-117.236904,33.634339],"type":"Point"}
}