{
  "type": "Feature",
  "properties": {
    "iso:country":"US",
    "sg:address":"5690 Aurora Dr",
    "sg:city":"Ventura",
    "sg:classifiers":[
        {
            "category":"Real Estate",
            "subcategory":"Architect",
            "type":"Services"
        }
    ],
    "sg:phone":"+1 805 654 0401",
    "sg:postcode":"93003",
    "sg:province":"CA",
    "wof:name":"DMC Custom Residential Dsgn",
    "wof:placetype":"venue"
},
  "geometry": {"coordinates":[-119.218982,34.276359],"type":"Point"}
}