{
  "type": "Feature",
  "properties": {
    "addr:full":"9340 7th St Rancho Cucamonga CA 91730",
    "addr:housenumber":"9340",
    "addr:postcode":"91730",
    "addr:street":"7Th St",
    "iso:country":"US",
    "sg:address":"9340 7th St",
    "sg:city":"Rancho Cucamonga",
    "sg:classifiers":[
        {
            "category":"Wholesale",
            "subcategory":"Durable Goods & Equipment",
            "type":"Manufacturing & Wholesale Goods"
        }
    ],
    "sg:phone":"+1 909 484 9083",
    "sg:postcode":"91730",
    "sg:province":"CA",
    "sg:tags":[
        "importer"
    ],
    "wof:name":"Terry K Inc",
    "wof:placetype":"venue"
},
  "geometry": {"coordinates":[-117.600661,34.088507],"type":"Point"}
}