{
  "type": "Feature",
  "properties": {
    "addr:full":"2705 Media Center Dr Los Angeles CA 90065",
    "addr:housenumber":"2705",
    "addr:postcode":"90065",
    "addr:street":"Media Center Dr",
    "iso:country":"US",
    "sg:address":"2705 Media Center Dr",
    "sg:city":"Los Angeles",
    "sg:classifiers":[
        {
            "category":"Insurance",
            "subcategory":"Insurance Agent",
            "type":"Services"
        }
    ],
    "sg:phone":"+1 818 545 7007",
    "sg:postcode":"90065",
    "sg:province":"CA",
    "sg:tags":[
        "audit"
    ],
    "sg:website":"www.davidmorse.com",
    "wof:name":"David Morse & Assoc",
    "wof:placetype":"venue"
},
  "geometry": {"coordinates":[-118.24287,34.109316],"type":"Point"}
}