{
  "type": "Feature",
  "properties": {
    "iso:country":"US",
    "sg:address":"725 S Beach Blvd",
    "sg:city":"Anaheim",
    "sg:classifiers":[
        {
            "category":"Manufacturing",
            "subcategory":"Tools & Machinery",
            "type":"Manufacturing & Wholesale Goods"
        },
        {
            "category":"Manufacturing",
            "subcategory":"Motor Vehicles & Parts",
            "type":"Manufacturing & Wholesale Goods"
        }
    ],
    "sg:phone":"+1 714 828 8699",
    "sg:postcode":"92804",
    "sg:province":"CA",
    "sg:tags":[
        "utility-manufacturers",
        "trailers-equipment",
        "parts-wholesale",
        "manufacturer",
        "trailers-automobile"
    ],
    "wof:name":"Jv & Dv Manufacturing Inc.",
    "wof:placetype":"venue"
},
  "geometry": {"coordinates":[-117.99342300000001,33.821442],"type":"Point"}
}