{
  "type": "Feature",
  "properties": {
    "iso:country":"US",
    "sg:address":"1400 Easton Dr",
    "sg:city":"Bakersfield",
    "sg:classifiers":[
        {
            "category":"Restaurant",
            "type":"Food & Drink"
        }
    ],
    "sg:phone":"+1 661 862 5300",
    "sg:postcode":"93309",
    "sg:province":"CA",
    "wof:name":"Four Corners Inc",
    "wof:placetype":"venue"
},
  "geometry": {"coordinates":[-119.04744100000001,35.369973],"type":"Point"}
}