{
  "type": "Feature",
  "properties": {
    "iso:country":"US",
    "sg:address":"1826 W 7th St",
    "sg:city":"Los Angeles",
    "sg:classifiers":[
        {
            "category":"Health Services",
            "subcategory":"Dentist",
            "type":"Services"
        }
    ],
    "sg:phone":"+1 213 484 6660",
    "sg:postcode":"90057",
    "sg:province":"CA",
    "wof:name":"Benyamini Dan Dr",
    "wof:placetype":"venue"
},
  "geometry": {"coordinates":[-118.274002,34.055302],"type":"Point"}
}