{
  "type": "Feature",
  "properties": {
    "addr:full":"1080 Los Viboras Rd Hollister CA 95023",
    "addr:housenumber":"1080",
    "addr:postcode":"hollister ca 95023",
    "addr:street":"Los Viboras Rd",
    "iso:country":"US",
    "sg:address":"1080 Los Viboras Rd",
    "sg:city":"Hollister",
    "sg:classifiers":[
        {
            "category":"Farming",
            "subcategory":"Crops",
            "type":"Manufacturing & Wholesale Goods"
        }
    ],
    "sg:phone":"+1 831 637 3315",
    "sg:postcode":"95023",
    "sg:province":"CA",
    "sg:tags":[
        "grove",
        "nut",
        "tree"
    ],
    "wof:name":"Robert Rose",
    "wof:placetype":"venue"
},
  "geometry": {"coordinates":[-121.35735200000001,36.935042],"type":"Point"}
}