{
  "type": "Feature",
  "properties": {
    "iso:country":"US",
    "sg:address":"1024 White Gate Rd",
    "sg:city":"Alamo",
    "sg:classifiers":[
        {
            "category":"Shopping",
            "subcategory":"Clothing, Apparel, & Fashions",
            "type":"Retail Goods"
        }
    ],
    "sg:phone":"+1 925 831 8167",
    "sg:postcode":"94507",
    "sg:province":"CA",
    "sg:tags":[
        "family"
    ],
    "wof:name":"Off Gear",
    "wof:placetype":"venue"
},
  "geometry": {"coordinates":[-121.973009,37.847592],"type":"Point"}
}