{
  "type": "Feature",
  "properties": {
    "iso:country":"US",
    "sg:address":"7455 Greenback Ln",
    "sg:city":"Citrus Heights",
    "sg:classifiers":[
        {
            "category":"Personal",
            "subcategory":"Beauty Salon",
            "type":"Services"
        }
    ],
    "sg:phone":"+1 916 722 2907",
    "sg:postcode":"95610",
    "sg:province":"CA",
    "sg:tags":[
        "manicuring"
    ],
    "wof:name":"Chernail Salon",
    "wof:placetype":"venue"
},
  "geometry": {"coordinates":[-121.291297,38.678274],"type":"Point"}
}