{
  "type": "Feature",
  "properties": {
    "addr:full":"20 N Sutter St Stockton CA 95202",
    "addr:housenumber":"20",
    "addr:postcode":"95202",
    "addr:street":"N Sutter St",
    "iso:country":"US",
    "sg:address":"20 N Sutter St",
    "sg:city":"Stockton",
    "sg:classifiers":[
        {
            "category":"Professional",
            "subcategory":"Lawyer & Legal Services",
            "type":"Services"
        }
    ],
    "sg:phone":"+1 209 948 0125",
    "sg:postcode":"95202",
    "sg:province":"CA",
    "sg:tags":[
        "attorney"
    ],
    "sg:website":"www.sjcog.org",
    "wof:name":"San Joaquin County Bar Assn",
    "wof:placetype":"venue"
},
  "geometry": {"coordinates":[-121.286039,37.95422],"type":"Point"}
}