{
  "type": "Feature",
  "properties": {
    "addr:full":"250 E Canal Dr Turlock CA 95380",
    "addr:housenumber":"250",
    "addr:postcode":"95380",
    "addr:street":"E Canal Dr",
    "iso:country":"US",
    "sg:address":"250 E Canal Dr",
    "sg:city":"Turlock",
    "sg:classifiers":[
        {
            "category":"Health Services",
            "subcategory":"Medical Lab",
            "type":"Services"
        }
    ],
    "sg:phone":"+1 209 634 6192",
    "sg:postcode":"95380",
    "sg:province":"CA",
    "sg:tags":[
        "laboratory"
    ],
    "wof:name":"L & M Dental Laboratory",
    "wof:placetype":"venue"
},
  "geometry": {"coordinates":[-120.845961,37.50021],"type":"Point"}
}