{
  "type": "Feature",
  "properties": {
    "iso:country":"US",
    "sg:address":"1840 San Miguel Dr",
    "sg:city":"Walnut Creek",
    "sg:classifiers":[
        {
            "category":"Professional",
            "subcategory":"Computer Services",
            "type":"Services"
        }
    ],
    "sg:phone":"+1 925 944 5772",
    "sg:postcode":"94596",
    "sg:province":"CA",
    "sg:tags":[
        "consultant",
        "designer"
    ],
    "wof:name":"Advanced Information Methods",
    "wof:placetype":"venue"
},
  "geometry": {"coordinates":[-122.051772,37.893653],"type":"Point"}
}