{
  "type": "Feature",
  "properties": {
    "addr:full":"8065 Elk Grove Florin Rd Sacramento CA 95829",
    "addr:housenumber":"8065",
    "addr:postcode":"95829",
    "addr:street":"Elk Grove Florin Rd",
    "iso:country":"US",
    "sg:address":"8065 Elk Grove Florin Rd",
    "sg:city":"Sacramento",
    "sg:classifiers":[
        {
            "category":"Health Services",
            "subcategory":"Doctor",
            "type":"Services"
        }
    ],
    "sg:phone":"+1 916 682 2000",
    "sg:postcode":"95829",
    "sg:province":"CA",
    "sg:tags":[
        "dentist"
    ],
    "wof:name":"Vintage Park Dental",
    "wof:placetype":"venue"
},
  "geometry": {"coordinates":[-121.371798,38.466116],"type":"Point"}
}