{
  "type": "Feature",
  "properties": {
    "addr:full":"35645 Lake Summit Dr Temecula CA 92592",
    "addr:housenumber":"35645",
    "addr:postcode":"92592",
    "addr:street":"Lake Summit Dr",
    "iso:country":"US",
    "sg:address":"35645 Lake Summit Dr",
    "sg:city":"Temecula",
    "sg:classifiers":[
        {
            "category":"Professional",
            "subcategory":"Accounting & Tax Preparation",
            "type":"Services"
        }
    ],
    "sg:phone":"+1 951 767 0818",
    "sg:postcode":"92592",
    "sg:province":"CA",
    "sg:tags":[
        "return",
        "filing"
    ],
    "wof:name":"A Lorraine Biron Acctng/Tax",
    "wof:placetype":"venue"
},
  "geometry": {"coordinates":[-117.000784,33.604569],"type":"Point"}
}