{
  "type": "Feature",
  "properties": {
    "addr:full":"10601-G Tierrasanta Blvd Ste 205 San Diego CA 92124",
    "addr:postcode":"92124",
    "addr:street":"10601-G Tierrasanta Blvd Ste 205",
    "iso:country":"US",
    "sg:address":"10601-G Tierrasanta Blvd Ste 205",
    "sg:city":"San Diego",
    "sg:classifiers":[
        {
            "category":"Professional",
            "subcategory":"Art Services",
            "type":"Services"
        },
        {
            "category":"Professional",
            "subcategory":"Printing & Photocopies",
            "type":"Services"
        }
    ],
    "sg:phone":"+1 858 531 1274",
    "sg:postcode":"92124",
    "sg:province":"CA",
    "sg:tags":[
        "graphic",
        "design"
    ],
    "sg:website":"www.zarvox.com/",
    "wof:name":"Zarvox Visual Communications",
    "wof:placetype":"venue"
},
  "geometry": {"coordinates":[-117.10105799999999,32.823042],"type":"Point"}
}