{
  "type": "Feature",
  "properties": {
    "iso:country":"US",
    "sg:address":"16311 Ventura Blvd",
    "sg:city":"Encino",
    "sg:classifiers":[
        {
            "category":"Professional",
            "subcategory":"Lawyer & Legal Services",
            "type":"Services"
        }
    ],
    "sg:phone":"+1 818 986 3888",
    "sg:postcode":"91436",
    "sg:province":"CA",
    "sg:tags":[
        "attorney"
    ],
    "wof:name":"Fred M Law Office",
    "wof:placetype":"venue"
},
  "geometry": {"coordinates":[-118.489954,34.157308],"type":"Point"}
}