{
  "type": "Feature",
  "properties": {
    "iso:country":"US",
    "sg:address":"6860 Lexington Ave",
    "sg:city":"Los Angeles",
    "sg:classifiers":[
        {
            "category":"Communications",
            "subcategory":"Film & Video Production",
            "type":"Services"
        }
    ],
    "sg:phone":"+1 323 957 9393",
    "sg:postcode":"90038",
    "sg:province":"CA",
    "sg:tags":[
        "motion",
        "picture",
        "studio",
        "producer"
    ],
    "wof:name":"Filmpool",
    "wof:placetype":"venue"
},
  "geometry": {"coordinates":[-118.340334,34.092498],"type":"Point"}
}