{
  "type": "Feature",
  "properties": {
    "iso:country":"US",
    "sg:address":"4174 Park Blvd Ste 205",
    "sg:city":"Oakland",
    "sg:classifiers":[
        {
            "category":"Health Services",
            "subcategory":"Dentist",
            "type":"Services"
        }
    ],
    "sg:phone":"+1 510 531 8002",
    "sg:postcode":"94602",
    "sg:province":"CA",
    "wof:name":"Anita Purohit, DDS",
    "wof:placetype":"venue"
},
  "geometry": {"coordinates":[-122.22305900000001,37.806875],"type":"Point"}
}