{
  "type": "Feature",
  "properties": {
    "addr:full":"17865 Sky Park Cir Suite E Irvine CA 92614",
    "addr:housenumber":"17865",
    "addr:postcode":"92614",
    "addr:street":"Sky Park Cir Suite E",
    "iso:country":"US",
    "sg:address":"17865 Sky Park Cir Suite E",
    "sg:city":"Irvine",
    "sg:classifiers":[
        {
            "category":"Health Services",
            "subcategory":"Health Practitioner",
            "type":"Services"
        }
    ],
    "sg:phone":"+1 949 833 2920",
    "sg:postcode":"92614",
    "sg:province":"CA",
    "sg:tags":[
        "nutritionist"
    ],
    "sg:website":"www.homenutrition.com",
    "wof:name":"Lifespring Nutrition",
    "wof:placetype":"venue"
},
  "geometry": {"coordinates":[-117.817215,33.67398],"type":"Point"}
}