{
  "type": "Feature",
  "properties": {
    "addr:full":"35 Vicente St San Francisco CA 94127",
    "addr:housenumber":"35",
    "addr:postcode":"94127",
    "addr:street":"Vicente St",
    "iso:country":"US",
    "sg:address":"35 Vicente St",
    "sg:city":"San Francisco",
    "sg:classifiers":[
        {
            "category":"Professional",
            "subcategory":"Lawyer & Legal Services",
            "type":"Services"
        }
    ],
    "sg:phone":"+1 415 661 9148",
    "sg:postcode":"94127",
    "sg:province":"CA",
    "wof:name":"Hall Christopher Attorney At Law",
    "wof:placetype":"venue"
},
  "geometry": {"coordinates":[-122.46619800000001,37.739166],"type":"Point"}
}