{
  "type": "Feature",
  "properties": {
    "addr:full":"7550 Fay Ave La Jolla CA 92037",
    "addr:housenumber":"7550",
    "addr:postcode":"92037",
    "addr:street":"Fay Ave",
    "iso:country":"US",
    "sg:address":"7550 Fay Ave",
    "sg:city":"La Jolla",
    "sg:classifiers":[
        {
            "category":"Restaurant",
            "type":"Food & Drink"
        }
    ],
    "sg:phone":"+1 858 454 5013",
    "sg:postcode":"92037",
    "sg:province":"CA",
    "sg:website":"www.berninisbistro.com",
    "wof:name":"Bernini's Bistro",
    "wof:placetype":"venue"
},
  "geometry": {"coordinates":[-117.27396899999999,32.841001],"type":"Point"}
}