{
  "type": "Feature",
  "properties": {
    "iso:country":"US",
    "sg:address":"144 Irongate Ct",
    "sg:city":"Alamo",
    "sg:phone":"+1 925 831 9392",
    "sg:postcode":"94507",
    "sg:province":"CA",
    "wof:name":"Terry L Mcdaniel Profit Sharin",
    "wof:placetype":"venue"
},
  "geometry": {"coordinates":[-122.025938,37.834927],"type":"Point"}
}