{
  "type": "Feature",
  "properties": {
    "iso:country":"US",
    "sg:address":"1530 Noriega St Ste 201",
    "sg:city":"San Francisco",
    "sg:classifiers":[
        {
            "category":"Professional",
            "subcategory":"Accounting & Tax Preparation",
            "type":"Services"
        }
    ],
    "sg:phone":"+1 415 731 9773",
    "sg:postcode":"94122",
    "sg:province":"CA",
    "sg:tags":[
        "accountant"
    ],
    "wof:name":"Kwok Tai Li, Tax Preparer",
    "wof:placetype":"venue"
},
  "geometry": {"coordinates":[-122.47649,37.752222],"type":"Point"}
}