{
  "type": "Feature",
  "properties": {
    "iso:country":"US",
    "sg:address":"550 Prairie Way",
    "sg:city":"Perris",
    "sg:classifiers":[
        {
            "category":"Professional",
            "type":"Services"
        }
    ],
    "sg:phone":"+1 951 943 7914",
    "sg:postcode":"92571",
    "sg:province":"CA",
    "wof:name":"Bullet Smiths",
    "wof:placetype":"venue"
},
  "geometry": {"coordinates":[-117.21489,33.813244],"type":"Point"}
}