{
  "type": "Feature",
  "properties": {
    "addr:full":"160 J St Fremont CA 94536",
    "addr:housenumber":"160",
    "addr:postcode":"94536",
    "addr:street":"J St",
    "iso:country":"US",
    "sg:address":"160 J St",
    "sg:city":"Fremont",
    "sg:classifiers":[
        {
            "category":"Government",
            "subcategory":"Post Office",
            "type":"Public Place"
        }
    ],
    "sg:phone":"+1 510 000 1111",
    "sg:postcode":"94536",
    "sg:province":"CA",
    "wof:name":"US Post Office",
    "wof:placetype":"venue"
},
  "geometry": {"coordinates":[-121.97708299999999,37.575482],"type":"Point"}
}