{
  "type": "Feature",
  "properties": {
    "addr:full":"422 W Ave P Palmdale CA 93551",
    "addr:housenumber":"422",
    "addr:postcode":"93551",
    "addr:street":"W Ave P Palmdale",
    "iso:country":"US",
    "sg:address":"422 W Ave P",
    "sg:city":"Palmdale",
    "sg:classifiers":[
        {
            "category":"Restaurant",
            "type":"Food & Drink"
        }
    ],
    "sg:phone":"+1 661 947 2235",
    "sg:postcode":"93551",
    "sg:province":"CA",
    "wof:name":"Primo Burgers",
    "wof:placetype":"venue"
},
  "geometry": {"coordinates":[-118.136043,34.601673],"type":"Point"}
}