{
  "type": "Feature",
  "properties": {
    "iso:country":"US",
    "sg:address":"1528 Montana Ave",
    "sg:city":"Santa Monica",
    "sg:classifiers":[
        {
            "category":"Shopping",
            "subcategory":"Clothing, Apparel, & Fashions",
            "type":"Retail Goods"
        }
    ],
    "sg:phone":"+1 310 451 3699",
    "sg:postcode":"90403",
    "sg:province":"CA",
    "wof:name":"Rebel",
    "wof:placetype":"venue"
},
  "geometry": {"coordinates":[-118.49392400000001,34.033084],"type":"Point"}
}