{
  "type": "Feature",
  "properties": {
    "addr:full":"1301 W Channel Islands Blvd Oxnard CA 93033",
    "addr:housenumber":"1301",
    "addr:postcode":"93033",
    "addr:street":"W Channel Islands Blvd",
    "iso:country":"US",
    "sg:address":"1301 W Channel Islands Blvd",
    "sg:city":"Oxnard",
    "sg:classifiers":[
        {
            "category":"Restaurant",
            "type":"Food & Drink"
        }
    ],
    "sg:phone":"+1 805 240 7888",
    "sg:postcode":"93033",
    "sg:province":"CA",
    "wof:name":"Super Buffet King",
    "wof:placetype":"venue"
},
  "geometry": {"coordinates":[-119.19361499999999,34.175644],"type":"Point"}
}