{
  "type": "Feature",
  "properties": {
    "addr:full":"3121 Harrison Ave South Lake Tahoe CA 96150",
    "addr:housenumber":"3121",
    "addr:postcode":"96150",
    "addr:street":"Harrison Ave",
    "iso:country":"US",
    "sg:address":"3121 Harrison Ave",
    "sg:city":"South Lake Tahoe",
    "sg:classifiers":[
        {
            "category":"Health Services",
            "subcategory":"Chiropractor",
            "type":"Services"
        }
    ],
    "sg:phone":"+1 530 541 5660",
    "sg:postcode":"96150",
    "sg:province":"CA",
    "wof:name":"Tahoe Chiropractic Clinic",
    "wof:placetype":"venue"
},
  "geometry": {"coordinates":[-119.977192,38.942267],"type":"Point"}
}