{
  "type": "Feature",
  "properties": {
    "addr:full":"631 Jefferson St Delano CA 93215",
    "addr:housenumber":"631",
    "addr:postcode":"93215",
    "addr:street":"Jefferson St",
    "iso:country":"US",
    "sg:address":"631 Jefferson St",
    "sg:city":"Delano",
    "sg:classifiers":[
        {
            "category":"Government",
            "subcategory":"Office",
            "type":"Public Place"
        }
    ],
    "sg:phone":"+1 661 725 8408",
    "sg:postcode":"93215",
    "sg:province":"CA",
    "sg:tags":[
        "transportation"
    ],
    "wof:name":"Delano DMV Office",
    "wof:placetype":"venue"
},
  "geometry": {"coordinates":[-119.243403,35.764982],"type":"Point"}
}