{
  "type": "Feature",
  "properties": {
    "iso:country":"US",
    "sg:address":"14865 Houston Ave",
    "sg:city":"Hanford",
    "sg:classifiers":[
        {
            "category":"Farming",
            "subcategory":"Crops",
            "type":"Manufacturing & Wholesale Goods"
        }
    ],
    "sg:phone":"+1 559 584 9552",
    "sg:postcode":"93230",
    "sg:province":"CA",
    "sg:tags":[
        "grove",
        "nut",
        "tree"
    ],
    "wof:name":"Als Farm",
    "wof:placetype":"venue"
},
  "geometry": {"coordinates":[-119.71716000000001,36.298353],"type":"Point"}
}