{
  "type": "Feature",
  "properties": {
    "addr:full":"840 W 76th St Los Angeles CA 90044",
    "addr:housenumber":"840",
    "addr:postcode":"90044",
    "addr:street":"W 76Th St",
    "iso:country":"US",
    "sg:address":"840 W 76th St",
    "sg:city":"Los Angeles",
    "sg:classifiers":[
        {
            "category":"Social Services",
            "subcategory":"Child Care",
            "type":"Services"
        }
    ],
    "sg:phone":"+1 323 759 0968",
    "sg:postcode":"90044",
    "sg:province":"CA",
    "wof:name":"Kimberly's Day Care",
    "wof:placetype":"venue"
},
  "geometry": {"coordinates":[-118.29068100000001,33.97065],"type":"Point"}
}