{
  "type": "Feature",
  "properties": {
    "iso:country":"US",
    "sg:address":"1065 E Hillsdale Blvd",
    "sg:city":"Foster City",
    "sg:classifiers":[
        {
            "category":"Manufacturing",
            "subcategory":"Printing",
            "type":"Manufacturing & Wholesale Goods"
        }
    ],
    "sg:phone":"+1 650 573 1100",
    "sg:postcode":"94403",
    "sg:province":"CA",
    "sg:tags":[
        "publisher",
        "software"
    ],
    "wof:name":"Arty Media Inc",
    "wof:placetype":"venue"
},
  "geometry": {"coordinates":[-122.270429,37.559602],"type":"Point"}
}