{
  "type": "Feature",
  "properties": {
    "addr:full":"1100 N Cypress St La Habra CA 90631",
    "addr:housenumber":"1100",
    "addr:postcode":"90631",
    "addr:street":"N Cypress St",
    "iso:country":"US",
    "sg:address":"1100 N Cypress St",
    "sg:city":"La Habra",
    "sg:classifiers":[
        {
            "category":"Building & Trades",
            "subcategory":"Construction",
            "type":"Services"
        }
    ],
    "sg:phone":"+1 714 526 4073",
    "sg:postcode":"90631",
    "sg:province":"CA",
    "sg:tags":[
        "home",
        "builder"
    ],
    "wof:name":"K Hovananian Co",
    "wof:placetype":"venue"
},
  "geometry": {"coordinates":[-117.941755,33.942123],"type":"Point"}
}