{
  "type": "Feature",
  "properties": {
    "addr:full":"2775 Gomes Ct Tracy CA 95376",
    "addr:housenumber":"2775",
    "addr:postcode":"95376",
    "addr:street":"Gomes Ct",
    "iso:country":"US",
    "sg:address":"2775 Gomes Ct",
    "sg:city":"Tracy",
    "sg:classifiers":[
        {
            "category":"Retail",
            "subcategory":"Auto Repair",
            "type":"Services"
        }
    ],
    "sg:phone":"+1 209 836 5060",
    "sg:postcode":"95376",
    "sg:province":"CA",
    "sg:tags":[
        "repairing",
        "automobile"
    ],
    "wof:name":"Direct Marketing Solutions",
    "wof:placetype":"venue"
},
  "geometry": {"coordinates":[-121.436599,37.757231],"type":"Point"}
}