{
  "type": "Feature",
  "properties": {
    "addr:full":"12522 Moorpark St. #108 Studio City CA 91604",
    "addr:housenumber":"12522;108",
    "addr:postcode":"91604",
    "addr:street":"Moorpark St. #",
    "iso:country":"US",
    "sg:address":"12522 Moorpark St. #108",
    "sg:city":"Studio City",
    "sg:classifiers":[
        {
            "category":"Health Services",
            "subcategory":"Clinic",
            "type":"Services"
        }
    ],
    "sg:phone":"+1 818 570 3362",
    "sg:postcode":"91604",
    "sg:province":"CA",
    "sg:tags":[
        "loss",
        "weight"
    ],
    "sg:website":"www.hcgtreatments.com/",
    "wof:name":"Diet Doc",
    "wof:placetype":"venue"
},
  "geometry": {"coordinates":[-118.406049,34.150085],"type":"Point"}
}