{
  "type": "Feature",
  "properties": {
    "addr:full":"2121 Arlington Ave Los Angeles CA 90018",
    "addr:housenumber":"2121",
    "addr:postcode":"90018",
    "addr:street":"Arlington Ave",
    "iso:country":"US",
    "sg:address":"2121 Arlington Ave",
    "sg:city":"Los Angeles",
    "sg:classifiers":[
        {
            "category":"Autos & Motor Vehicles",
            "subcategory":"Fuel & Gas Station",
            "type":"Retail Goods"
        }
    ],
    "sg:phone":"+1 323 737 6598",
    "sg:postcode":"90018",
    "sg:province":"CA",
    "sg:tags":[
        "oil"
    ],
    "wof:name":"United Oil Station No 50",
    "wof:placetype":"venue"
},
  "geometry": {"coordinates":[-118.318001,34.037399],"type":"Point"}
}