{
  "type": "Feature",
  "properties": {
    "iso:country":"US",
    "sg:address":"200 W Glenoaks Blvd Ste 206",
    "sg:city":"Glendale",
    "sg:classifiers":[
        {
            "category":"Real Estate",
            "subcategory":"Real Estate Services",
            "type":"Services"
        }
    ],
    "sg:phone":"+1 818 243 1151",
    "sg:postcode":"91202",
    "sg:province":"CA",
    "wof:name":"Nelson Norman Real Estate",
    "wof:placetype":"venue"
},
  "geometry": {"coordinates":[-118.256451,34.159301],"type":"Point"}
}