{
  "type": "Feature",
  "properties": {
    "addr:full":"11970 Ventura Blvd Studio City CA 91604",
    "addr:housenumber":"11970",
    "addr:postcode":"91604",
    "addr:street":"Ventura Blvd",
    "iso:country":"US",
    "sg:address":"11970 Ventura Blvd",
    "sg:city":"Studio City",
    "sg:classifiers":[
        {
            "category":"Fast Food",
            "type":"Food & Drink"
        },
        {
            "category":"Restaurant",
            "type":"Food & Drink"
        }
    ],
    "sg:phone":"+1 818 762 8396",
    "sg:postcode":"91604",
    "sg:province":"CA",
    "sg:tags":[
        "burger"
    ],
    "sg:website":"www.mcdonalds.com/",
    "wof:name":"McDonald's",
    "wof:placetype":"venue"
},
  "geometry": {"coordinates":[-118.39289599999999,34.143601],"type":"Point"}
}