{
  "type": "Feature",
  "properties": {
    "iso:country":"US",
    "sg:address":"2225 East Bayshore Road",
    "sg:city":"Palo Alto",
    "sg:classifiers":[
        {
            "category":"Professional",
            "subcategory":"Computer Services",
            "type":"Services"
        }
    ],
    "sg:postcode":"94303",
    "sg:province":"CA",
    "sg:website":"http://webtalk.org",
    "wof:name":"Webtalk",
    "wof:placetype":"venue"
},
  "geometry": {"coordinates":[-122.12766000000001,37.45303],"type":"Point"}
}