{
  "type": "Feature",
  "properties": {
    "addr:full":"401 1st St Richmond CA 94801",
    "addr:housenumber":"401",
    "addr:postcode":"94801",
    "addr:street":"1St St",
    "iso:country":"US",
    "sg:address":"401 1st St",
    "sg:city":"Richmond",
    "sg:classifiers":[
        {
            "category":"Manufacturing",
            "subcategory":"Tools & Machinery",
            "type":"Manufacturing & Wholesale Goods"
        }
    ],
    "sg:phone":"+1 510 307 8300",
    "sg:postcode":"94801",
    "sg:province":"CA",
    "sg:tags":[
        "devices"
    ],
    "sg:website":"www.amot.com",
    "wof:name":"AMOT Controls Corp",
    "wof:placetype":"venue"
},
  "geometry": {"coordinates":[-122.36869299999999,37.938416],"type":"Point"}
}