{
  "type": "Feature",
  "properties": {
    "iso:country":"US",
    "sg:address":"3351 Lake Tahoe Blvd",
    "sg:city":"South Lake Tahoe",
    "sg:classifiers":[
        {
            "category":"Social Services",
            "type":"Services"
        }
    ],
    "sg:phone":"+1 530 542 2409",
    "sg:postcode":"96150",
    "sg:province":"CA",
    "sg:tags":[
        "counselor",
        "marriage",
        "family"
    ],
    "wof:name":"Deborah A Vance",
    "wof:placetype":"venue"
},
  "geometry": {"coordinates":[-119.969294,38.945819],"type":"Point"}
}