{
  "type": "Feature",
  "properties": {
    "iso:country":"US",
    "sg:address":"18420 Hart St",
    "sg:city":"Reseda",
    "sg:classifiers":[
        {
            "category":"Recreation",
            "type":"Entertainment"
        }
    ],
    "sg:phone":"+1 818 705 3951",
    "sg:postcode":"91335",
    "sg:province":"CA",
    "sg:tags":[
        "club",
        "membership"
    ],
    "wof:name":"Mid Vly Racquetball Athletc",
    "wof:placetype":"venue"
},
  "geometry": {"coordinates":[-118.535494,34.197407],"type":"Point"}
}