{
  "type": "Feature",
  "properties": {
    "addr:full":"1000 S Novato Blvd Novato CA 94947",
    "addr:housenumber":"1000",
    "addr:postcode":"94947",
    "addr:street":"S Novato Blvd",
    "iso:country":"US",
    "sg:address":"1000 S Novato Blvd",
    "sg:city":"Novato",
    "sg:classifiers":[
        {
            "category":"Real Estate",
            "subcategory":"Real Estate Operator",
            "type":"Services"
        }
    ],
    "sg:phone":"+1 415 892 3239",
    "sg:postcode":"94947",
    "sg:province":"CA",
    "sg:tags":[
        "apartment"
    ],
    "wof:name":"Cowbarn Apartments",
    "wof:placetype":"venue"
},
  "geometry": {"coordinates":[-122.552109,38.077492],"type":"Point"}
}