{
  "type": "Feature",
  "properties": {
    "iso:country":"US",
    "sg:address":"360 Beach Rd",
    "sg:city":"Burlingame",
    "sg:classifiers":[
        {
            "category":"Building & Trades",
            "subcategory":"Construction",
            "type":"Services"
        }
    ],
    "sg:phone":"+1 650 348 1450",
    "sg:postcode":"94010",
    "sg:province":"CA",
    "sg:tags":[
        "concrete",
        "contractor"
    ],
    "wof:name":"R & W Concrete Contruction Inc",
    "wof:placetype":"venue"
},
  "geometry": {"coordinates":[-122.336367,37.588421],"type":"Point"}
}