{
  "type": "Feature",
  "properties": {
    "iso:country":"US",
    "sg:address":"15640 E 14th St",
    "sg:city":"San Leandro",
    "sg:classifiers":[
        {
            "category":"Autos & Motor Vehicles",
            "subcategory":"Auto Supplies",
            "type":"Retail Goods"
        }
    ],
    "sg:phone":"+1 510 481 6222",
    "sg:postcode":"94578",
    "sg:province":"CA",
    "sg:tags":[
        "automobile",
        "stereo",
        "radio"
    ],
    "wof:name":"Audio & Alarm",
    "wof:placetype":"venue"
},
  "geometry": {"coordinates":[-122.123993,37.702247],"type":"Point"}
}