{
  "type": "Feature",
  "properties": {
    "addr:full":"141 E 162nd Street Gardena CA 90248",
    "addr:housenumber":"141",
    "addr:postcode":"90248",
    "addr:street":"E 162Nd Street",
    "iso:country":"US",
    "sg:address":"141 E 162nd Street",
    "sg:city":"Gardena",
    "sg:classifiers":[
        {
            "category":"Shopping",
            "subcategory":"Crafts & Fabrics",
            "type":"Retail Goods"
        }
    ],
    "sg:phone":"+1 310 771 1960",
    "sg:postcode":"90248",
    "sg:province":"CA",
    "sg:tags":[
        "art",
        "supply"
    ],
    "sg:website":"www.stretchart.com",
    "wof:name":"Stretch Art",
    "wof:placetype":"venue"
},
  "geometry": {"coordinates":[-118.274344,33.884872],"type":"Point"}
}