{
  "type": "Feature",
  "properties": {
    "addr:full":"24144 Beverly St Wildomar CA 92595",
    "addr:housenumber":"24144",
    "addr:postcode":"92595",
    "addr:street":"Beverly St",
    "iso:country":"US",
    "sg:address":"24144 Beverly St",
    "sg:city":"Wildomar",
    "sg:classifiers":[
        {
            "category":"Building & Trades",
            "subcategory":"Construction",
            "type":"Services"
        }
    ],
    "sg:phone":"+1 951 244 4897",
    "sg:postcode":"92595",
    "sg:province":"CA",
    "sg:tags":[
        "contractor"
    ],
    "wof:name":"Busch & Davis Construction",
    "wof:placetype":"venue"
},
  "geometry": {"coordinates":[-117.236605,33.641506],"type":"Point"}
}