{
  "type": "Feature",
  "properties": {
    "iso:country":"US",
    "sg:address":"445 Burgess Dr",
    "sg:city":"Menlo Park",
    "sg:classifiers":[
        {
            "category":"Health Services",
            "subcategory":"Doctor",
            "type":"Services"
        }
    ],
    "sg:phone":"+1 650 329 0886",
    "sg:postcode":"94025",
    "sg:province":"CA",
    "sg:tags":[
        "physician",
        "surgeon"
    ],
    "wof:name":"Counseling & Psychotherapy Ctr",
    "wof:placetype":"venue"
},
  "geometry": {"coordinates":[-122.175044,37.451753],"type":"Point"}
}