{
  "type": "Feature",
  "properties": {
    "addr:full":"3883 Piedmont Ave Oakland CA 94611",
    "addr:housenumber":"3883",
    "addr:postcode":"94611",
    "addr:street":"Piedmont Ave",
    "iso:country":"US",
    "sg:address":"3883 Piedmont Ave",
    "sg:city":"Oakland",
    "sg:classifiers":[
        {
            "category":"Shopping",
            "subcategory":"Gifts & Souvenirs",
            "type":"Retail Goods"
        }
    ],
    "sg:phone":"+1 510 654 7852",
    "sg:postcode":"94611",
    "sg:province":"CA",
    "wof:name":"Collectors Corner",
    "wof:placetype":"venue"
},
  "geometry": {"coordinates":[-122.25488,37.824666],"type":"Point"}
}