{
  "type": "Feature",
  "properties": {
    "addr:full":"307 Mall Dr Hanford CA 93230",
    "addr:housenumber":"307",
    "addr:postcode":"ca 93230",
    "addr:street":"Mall Dr",
    "iso:country":"US",
    "sg:address":"307 Mall Dr",
    "sg:city":"Hanford",
    "sg:classifiers":[
        {
            "category":"Health Services",
            "subcategory":"Clinic",
            "type":"Services"
        }
    ],
    "sg:phone":"+1 559 582 1100",
    "sg:postcode":"93230",
    "sg:province":"CA",
    "wof:name":"Mir Hamid R MD",
    "wof:placetype":"venue"
},
  "geometry": {"coordinates":[-119.668488,36.327384],"type":"Point"}
}