{
  "type": "Feature",
  "properties": {
    "addr:full":"15651 Imperial Hwy Ste 100 La Mirada CA 90638",
    "addr:housenumber":"15651",
    "addr:postcode":"90638",
    "addr:street":"Imperial Hwy Ste 100",
    "iso:country":"US",
    "sg:address":"15651 Imperial Hwy Ste 100",
    "sg:city":"La Mirada",
    "sg:classifiers":[
        {
            "category":"Health Services",
            "subcategory":"Chiropractor",
            "type":"Services"
        }
    ],
    "sg:phone":"+1 714 994 4881",
    "sg:postcode":"90638",
    "sg:province":"CA",
    "wof:name":"Healthways Chiropractic Clinic",
    "wof:placetype":"venue"
},
  "geometry": {"coordinates":[-117.998001,33.9174],"type":"Point"}
}