{
  "type": "Feature",
  "properties": {
    "addr:full":"2225 Roark Dr Alhambra CA 91803",
    "addr:housenumber":"2225",
    "addr:postcode":"91803",
    "addr:street":"Roark Dr",
    "iso:country":"US",
    "sg:address":"2225 Roark Dr",
    "sg:city":"Alhambra",
    "sg:classifiers":[
        {
            "category":"Professional",
            "type":"Services"
        }
    ],
    "sg:phone":"+1 626 282 5601",
    "sg:postcode":"91803",
    "sg:province":"CA",
    "wof:name":"Callaway John",
    "wof:placetype":"venue"
},
  "geometry": {"coordinates":[-118.14021200000001,34.067818],"type":"Point"}
}