{
  "type": "Feature",
  "properties": {
    "addr:full":"416 25th Street # 2 Oakland CA 94612",
    "addr:housenumber":"416",
    "addr:postcode":"94612",
    "addr:street":"25Th Street # 2",
    "iso:country":"US",
    "sg:address":"416 25th Street # 2",
    "sg:city":"Oakland",
    "sg:classifiers":[
        {
            "category":"Education",
            "subcategory":"Music School",
            "type":"Public Place"
        }
    ],
    "sg:phone":"+1 510 268 4084",
    "sg:postcode":"94612",
    "sg:province":"CA",
    "sg:tags":[
        "instrument",
        "teacher",
        "musical"
    ],
    "sg:website":"www.smythesaccordioncenter.com",
    "wof:name":"Smythe's Accordion Center",
    "wof:placetype":"venue"
},
  "geometry": {"coordinates":[-122.264999,37.814301],"type":"Point"}
}