{
  "type": "Feature",
  "properties": {
    "addr:full":"19925 Stevens Creek Blvd Cupertino CA 95014",
    "addr:housenumber":"19925",
    "addr:postcode":"95014",
    "addr:street":"Stevens Creek Blvd",
    "iso:country":"US",
    "sg:address":"19925 Stevens Creek Blvd",
    "sg:city":"Cupertino",
    "sg:classifiers":[
        {
            "category":"Professional",
            "subcategory":"Computer Services",
            "type":"Services"
        }
    ],
    "sg:phone":"+1 888 986 1117",
    "sg:postcode":"95014",
    "sg:province":"CA",
    "sg:tags":[
        "repair"
    ],
    "sg:website":"www.resolvetek.net/content/resol...",
    "wof:name":"ResolveTek Solutions",
    "wof:placetype":"venue"
},
  "geometry": {"coordinates":[-122.021288,37.323019],"type":"Point"}
}