{
  "type": "Feature",
  "properties": {
    "addr:full":"620 Redwood Ave Sacramento CA 95815",
    "addr:housenumber":"620",
    "addr:postcode":"95815",
    "addr:street":"Redwood Ave",
    "iso:country":"US",
    "sg:address":"620 Redwood Ave",
    "sg:city":"Sacramento",
    "sg:classifiers":[
        {
            "category":"Community Center",
            "subcategory":"Youth",
            "type":"Public Place"
        }
    ],
    "sg:phone":"+1 916 821 2025",
    "sg:postcode":"95815",
    "sg:province":"CA",
    "wof:name":"Everybody Got A Story",
    "wof:placetype":"venue"
},
  "geometry": {"coordinates":[-121.45299,38.61024],"type":"Point"}
}