{
  "type": "Feature",
  "properties": {
    "iso:country":"US",
    "sfac:artist":"Labaudt, Lucien",
    "sfac:created_at":"01/01/1970 12:32:16 AM +0000",
    "sfac:credit_line":"WPA Mural Project for the Beach Chalet at Golden Gate Park",
    "sfac:location_description":"Public Display : District 1 : GGP, Beach Chalet",
    "sfac:medium":"Fresco",
    "sfac:revision":"2-53c1f40deee75d392bb086b5feec8d7d",
    "sfac:title":"People and Places of San Francisco",
    "wof:name":"People and Places of San Francisco",
    "wof:placetype":"venue"
},
  "geometry": {"coordinates":[-122.510284,37.767879],"type":"Point"}
}