{
  "type": "Feature",
  "properties": {
    "addr:full":"770 Market Ave Richmond CA 94801",
    "addr:housenumber":"770",
    "addr:postcode":"94801",
    "addr:street":"Market Ave",
    "iso:country":"US",
    "sg:address":"770 Market Ave",
    "sg:city":"Richmond",
    "sg:classifiers":[
        {
            "category":"Manufacturing",
            "subcategory":"Metals",
            "type":"Manufacturing & Wholesale Goods"
        }
    ],
    "sg:phone":"+1 510 233 7629",
    "sg:postcode":"94801",
    "sg:province":"CA",
    "sg:tags":[
        "coating",
        "powder"
    ],
    "sg:website":"www.professionalfinishing.com",
    "wof:name":"Professional Finishing",
    "wof:placetype":"venue"
},
  "geometry": {"coordinates":[-122.36001400000001,37.958585],"type":"Point"}
}