{
  "type": "Feature",
  "properties": {
    "addr:full":"1101 Airport Rd Monterey CA 93940",
    "addr:housenumber":"1101",
    "addr:postcode":"93940",
    "addr:street":"Airport Rd",
    "iso:country":"US",
    "sg:address":"1101 Airport Rd",
    "sg:city":"Monterey",
    "sg:classifiers":[
        {
            "category":"Professional",
            "type":"Services"
        }
    ],
    "sg:phone":"+1 831 642 0800",
    "sg:postcode":"93940",
    "sg:province":"CA",
    "sg:tags":[
        "art",
        "restoring"
    ],
    "wof:name":"Radoman Framing & Restoration",
    "wof:placetype":"venue"
},
  "geometry": {"coordinates":[-121.851552,36.592523],"type":"Point"}
}