{
  "type": "Feature",
  "properties": {
    "iso:country":"US",
    "sg:address":"6732 White Oak Ave",
    "sg:city":"Van Nuys",
    "sg:classifiers":[
        {
            "category":"Personal",
            "subcategory":"Beauty Salon",
            "type":"Services"
        }
    ],
    "sg:phone":"+1 818 344 6877",
    "sg:postcode":"91406",
    "sg:province":"CA",
    "wof:name":"Supra Hair & Nail",
    "wof:placetype":"venue"
},
  "geometry": {"coordinates":[-118.518499,34.193632],"type":"Point"}
}