{
  "type": "Feature",
  "properties": {
    "iso:country":"US",
    "sg:address":"6224 W Manchester Avenue",
    "sg:city":"Los Angeles",
    "sg:classifiers":[
        {
            "category":"Professional",
            "subcategory":"Lawyer & Legal Services",
            "type":"Services"
        }
    ],
    "sg:phone":"+1 310 645 0295",
    "sg:postcode":"90045",
    "sg:province":"CA",
    "wof:name":"The Law Offices of Paul R Hammons",
    "wof:placetype":"venue"
},
  "geometry": {"coordinates":[-118.394088,33.959909],"type":"Point"}
}