{
  "type": "Feature",
  "properties": {
    "iso:country":"US",
    "sg:address":"718 E Manchester Boulevard",
    "sg:city":"Inglewood",
    "sg:classifiers":[
        {
            "category":"Professional",
            "subcategory":"Lawyer & Legal Services",
            "type":"Services"
        }
    ],
    "sg:phone":"+1 310 674 2449",
    "sg:postcode":"90301",
    "sg:province":"CA",
    "sg:tags":[
        "notary"
    ],
    "sg:website":"www.notarypublic.com",
    "wof:name":"Notary Public",
    "wof:placetype":"venue"
},
  "geometry": {"coordinates":[-118.346236,33.959832],"type":"Point"}
}