{
  "type": "Feature",
  "properties": {
    "addr:full":"13804 Shoemaker Ave Norwalk CA 90650",
    "addr:housenumber":"13804",
    "addr:postcode":"90650",
    "addr:street":"Shoemaker Ave",
    "iso:country":"US",
    "sg:address":"13804 Shoemaker Ave",
    "sg:city":"Norwalk",
    "sg:classifiers":[
        {
            "category":"Professional",
            "subcategory":"Business Services",
            "type":"Services"
        }
    ],
    "sg:phone":"+1 562 483 0529",
    "sg:postcode":"90650",
    "sg:province":"CA",
    "sg:tags":[
        "inventory"
    ],
    "wof:name":"Inventory Supply Co",
    "wof:placetype":"venue"
},
  "geometry": {"coordinates":[-118.055233,33.905816],"type":"Point"}
}