{
  "type": "Feature",
  "properties": {
    "addr:full":"732 N Brea Blvd Brea CA 92821",
    "addr:housenumber":"732",
    "addr:postcode":"92821",
    "addr:street":"N Brea Blvd",
    "iso:country":"US",
    "sg:address":"732 N Brea Blvd",
    "sg:city":"Brea",
    "sg:classifiers":[
        {
            "category":"Restaurant",
            "type":"Food & Drink"
        }
    ],
    "sg:menulink":"http://www.allmenus.com/ca/anaheim-santa-ana-garden-grove/75046-round-table-pizza/menu/",
    "sg:phone":"+1 714 671 2821",
    "sg:postcode":"92821",
    "sg:province":"CA",
    "sg:tags":[
        "american",
        "pizza"
    ],
    "wof:name":"Round Table Pizza",
    "wof:placetype":"venue"
},
  "geometry": {"coordinates":[-117.894481,33.930651],"type":"Point"}
}