{
  "type": "Feature",
  "properties": {
    "addr:full":"5004 York Blvd Los Angeles CA 90042",
    "addr:housenumber":"5004",
    "addr:postcode":"90042",
    "addr:street":"York Blvd",
    "iso:country":"US",
    "sg:address":"5004 York Blvd",
    "sg:city":"Los Angeles",
    "sg:classifiers":[
        {
            "category":"Organizations",
            "subcategory":"Community Association",
            "type":"Services"
        }
    ],
    "sg:phone":"+1 323 256 4509",
    "sg:postcode":"90042",
    "sg:province":"CA",
    "sg:tags":[
        "environmental",
        "org"
    ],
    "wof:name":"Ceert",
    "wof:placetype":"venue"
},
  "geometry": {"coordinates":[-118.204848,34.121013],"type":"Point"}
}