{
  "type": "Feature",
  "properties": {
    "addr:full":"3044 Fried Ave San Diego CA 92122",
    "addr:housenumber":"3044",
    "addr:postcode":"92122",
    "addr:street":"Fried Ave",
    "iso:country":"US",
    "sg:address":"3044 Fried Ave",
    "sg:city":"San Diego",
    "sg:classifiers":[
        {
            "category":"Banks & Credit Unions",
            "subcategory":"Financial Services",
            "type":"Services"
        }
    ],
    "sg:phone":"+1 858 453 2904",
    "sg:postcode":"92122",
    "sg:province":"CA",
    "sg:tags":[
        "trust",
        "management"
    ],
    "wof:name":"Bausch Trust",
    "wof:placetype":"venue"
},
  "geometry": {"coordinates":[-117.22075100000001,32.849867],"type":"Point"}
}