{
  "type": "Feature",
  "properties": {
    "iso:country":"US",
    "sg:address":"277 Kapalua Bay Cir",
    "sg:city":"Pittsburg",
    "sg:classifiers":[
        {
            "category":"Restaurant",
            "type":"Food & Drink"
        }
    ],
    "sg:phone":"+1 925 261 1737",
    "sg:postcode":"94565",
    "sg:province":"CA",
    "sg:tags":[
        "style",
        "family"
    ],
    "wof:name":"American Diner",
    "wof:placetype":"venue"
},
  "geometry": {"coordinates":[-121.953041,38.016383],"type":"Point"}
}