{
  "type": "Feature",
  "properties": {
    "addr:full":"2139 Tapo St Simi Valley CA 93063",
    "addr:housenumber":"2139",
    "addr:postcode":"93063",
    "addr:street":"Tapo St",
    "iso:country":"US",
    "sg:address":"2139 Tapo St",
    "sg:city":"Simi Valley",
    "sg:classifiers":[
        {
            "category":"Insurance",
            "subcategory":"Insurance Agent",
            "type":"Services"
        }
    ],
    "sg:phone":"+1 805 579 0680",
    "sg:postcode":"93063",
    "sg:province":"CA",
    "wof:name":"Patronete Insurance",
    "wof:placetype":"venue"
},
  "geometry": {"coordinates":[-118.709018,34.27342],"type":"Point"}
}