{
  "type": "Feature",
  "properties": {
    "addr:full":"6600 Skyview Dr Orangevale CA 95662",
    "addr:housenumber":"6600",
    "addr:postcode":"95662",
    "addr:street":"Skyview Dr",
    "iso:country":"US",
    "sg:address":"6600 Skyview Dr",
    "sg:city":"Orangevale",
    "sg:phone":"+1 916 969 1415",
    "sg:postcode":"95662",
    "sg:province":"CA",
    "sg:tags":[
        "product",
        "petroleum"
    ],
    "wof:name":"Faught Oil Co",
    "wof:placetype":"venue"
},
  "geometry": {"coordinates":[-121.259004,38.685213],"type":"Point"}
}