{
  "type": "Feature",
  "properties": {
    "iso:country":"US",
    "sg:address":"535 Powell St Between Sutter and Bush",
    "sg:city":"San Francisco",
    "sg:classifiers":[
        {
            "category":"Arts & Performance",
            "subcategory":"Art Gallery",
            "type":"Entertainment"
        },
        {
            "category":"Communications",
            "subcategory":"Newspaper",
            "type":"Services"
        },
        {
            "category":"Retail",
            "subcategory":"Event Space",
            "type":"Services"
        }
    ],
    "sg:phone":"+1 415 398 7229",
    "sg:postcode":"94108",
    "sg:province":"CA",
    "sg:tags":[
        "print",
        "medium",
        "venue"
    ],
    "sg:website":"www.meridiangallery.org",
    "wof:name":"Meridian Gallery",
    "wof:placetype":"venue"
},
  "geometry": {"coordinates":[-122.408953,37.789692],"type":"Point"}
}