{
  "type": "Feature",
  "properties": {
    "iso:country":"US",
    "sg:address":"38475 6th St E",
    "sg:city":"Palmdale",
    "sg:classifiers":[
        {
            "category":"Retail",
            "subcategory":"Auto Repair",
            "type":"Services"
        }
    ],
    "sg:phone":"+1 661 266 2751",
    "sg:postcode":"93550",
    "sg:province":"CA",
    "sg:tags":[
        "automobile",
        "smog"
    ],
    "wof:name":"California Smog & Test Only",
    "wof:placetype":"venue"
},
  "geometry": {"coordinates":[-118.118404,34.580021],"type":"Point"}
}