{
  "type": "Feature",
  "properties": {
    "iso:country":"US",
    "sg:address":"10101 Valley View St",
    "sg:city":"Cypress",
    "sg:classifiers":[
        {
            "category":"Fast Food",
            "type":"Food & Drink"
        },
        {
            "category":"Restaurant",
            "type":"Food & Drink"
        },
        {
            "category":"Professional",
            "type":"Services"
        }
    ],
    "sg:phone":"+1 714 995 2422",
    "sg:postcode":"90630",
    "sg:province":"CA",
    "sg:tags":[
        "style",
        "family",
        "delivery",
        "lunch",
        "take",
        "brunch",
        "breakfast",
        "pizza"
    ],
    "sg:website":"www.roundtablepizza.com",
    "wof:name":"Round Table Pizza",
    "wof:placetype":"venue"
},
  "geometry": {"coordinates":[-118.028306,33.81523],"type":"Point"}
}