{
  "type": "Feature",
  "properties": {
    "addr:full":"2720 Yuma Ct Walnut Creek CA 94598",
    "addr:housenumber":"2720",
    "addr:postcode":"94598",
    "addr:street":"Yuma Ct",
    "iso:country":"US",
    "sg:address":"2720 Yuma Ct",
    "sg:city":"Walnut Creek",
    "sg:classifiers":[
        {
            "category":"Home & Garden",
            "subcategory":"Home Furnishings",
            "type":"Retail Goods"
        }
    ],
    "sg:phone":"+1 925 932 4934",
    "sg:postcode":"94598",
    "sg:province":"CA",
    "wof:name":"Spring Tite Inc",
    "wof:placetype":"venue"
},
  "geometry": {"coordinates":[-122.01431100000001,37.909505],"type":"Point"}
}