{
  "type": "Feature",
  "properties": {
    "iso:country":"US",
    "sg:address":"6765 Black Butte Rd",
    "sg:city":"Shingletown",
    "sg:classifiers":[
        {
            "category":"Manufacturing",
            "subcategory":"Metals",
            "type":"Manufacturing & Wholesale Goods"
        }
    ],
    "sg:phone":"+1 530 474 5773",
    "sg:postcode":"96088",
    "sg:province":"CA",
    "sg:tags":[
        "woodwork",
        "cut",
        "saw",
        "scroll",
        "mfg"
    ],
    "wof:name":"High Country Woodcrafts",
    "wof:placetype":"venue"
},
  "geometry": {"coordinates":[-121.998046,40.493958],"type":"Point"}
}