{
  "type": "Feature",
  "properties": {
    "iso:country":"US",
    "sg:address":"196 Technology Dr",
    "sg:city":"Irvine",
    "sg:classifiers":[
        {
            "category":"Travel",
            "subcategory":"Travel Agent",
            "type":"Entertainment"
        }
    ],
    "sg:phone":"+1 949 453 1950",
    "sg:postcode":"92618",
    "sg:province":"CA",
    "sg:tags":[
        "operator",
        "tour"
    ],
    "wof:name":"Solo Sports Excursions",
    "wof:placetype":"venue"
},
  "geometry": {"coordinates":[-117.745817,33.664752],"type":"Point"}
}