{
  "type": "Feature",
  "properties": {
    "iso:country":"US",
    "sg:address":"1935 S del Mar Ave",
    "sg:city":"San Gabriel",
    "sg:classifiers":[
        {
            "category":"Autos & Motor Vehicles",
            "subcategory":"Fuel & Gas Station",
            "type":"Retail Goods"
        }
    ],
    "sg:phone":"+1 626 572 9352",
    "sg:postcode":"91776",
    "sg:province":"CA",
    "sg:tags":[
        "oil"
    ],
    "wof:name":"Trinity Energy Inc",
    "wof:placetype":"venue"
},
  "geometry": {"coordinates":[-118.099615,34.075044],"type":"Point"}
}