{
  "type": "Feature",
  "properties": {
    "addr:full":"1810 Capitol St Vallejo CA 94590",
    "addr:housenumber":"1810",
    "addr:postcode":"94590",
    "addr:street":"Capitol St",
    "iso:country":"US",
    "sg:address":"1810 Capitol St",
    "sg:city":"Vallejo",
    "sg:classifiers":[
        {
            "category":"Organizations",
            "subcategory":"Non-profit Organization",
            "type":"Services"
        }
    ],
    "sg:phone":"+1 707 644 4194",
    "sg:postcode":"94590",
    "sg:province":"CA",
    "wof:name":"Ombudsman Svc Inc",
    "wof:placetype":"venue"
},
  "geometry": {"coordinates":[-122.236844,38.102833],"type":"Point"}
}