{
  "type": "Feature",
  "properties": {
    "iso:country":"US",
    "sg:address":"9415 Hildreth Avenue",
    "sg:city":"South Gate",
    "sg:classifiers":[
        {
            "category":"Real Estate",
            "subcategory":"Real Estate Services",
            "type":"Services"
        }
    ],
    "sg:phone":"+1 323 567 2367",
    "sg:postcode":"90280",
    "sg:province":"CA",
    "wof:name":"Stegmaier Gertrude Rl Est",
    "wof:placetype":"venue"
},
  "geometry": {"coordinates":[-118.187656,33.947058],"type":"Point"}
}