{
  "type": "Feature",
  "properties": {
    "iso:country":"US",
    "sg:address":"1010 W Commonwealth Ave Ste A",
    "sg:city":"Fullerton",
    "sg:classifiers":[
        {
            "category":"Manufacturing",
            "subcategory":"Rubber & Plastics",
            "type":"Manufacturing & Wholesale Goods"
        },
        {
            "category":"Autos & Motor Vehicles",
            "subcategory":"Auto Supplies",
            "type":"Retail Goods"
        },
        {
            "category":"Retail",
            "subcategory":"Auto Repair",
            "type":"Services"
        }
    ],
    "sg:phone":"+1 714 870 4699",
    "sg:postcode":"92833",
    "sg:province":"CA",
    "sg:tags":[
        "wheel",
        "oil",
        "tires-wholesale",
        "tire",
        "lube",
        "retread",
        "recap",
        "servicing-automotive",
        "balancing",
        "axle",
        "wheels-aligning",
        "alignment-frame",
        "brake",
        "manufacturer"
    ],
    "sg:website":"http://www.bigotires.com",
    "wof:name":"Big O Tire Stores",
    "wof:placetype":"venue"
},
  "geometry": {"coordinates":[-117.942001,33.8703],"type":"Point"}
}