{
  "type": "Feature",
  "properties": {
    "iso:country":"US",
    "sg:address":"21849 Arbor Ct",
    "sg:city":"Walnut",
    "sg:classifiers":[
        {
            "category":"Wholesale",
            "subcategory":"Apparel",
            "type":"Manufacturing & Wholesale Goods"
        }
    ],
    "sg:phone":"+1 909 598 1902",
    "sg:postcode":"91789",
    "sg:province":"CA",
    "sg:tags":[
        "infant",
        "wear"
    ],
    "sg:website":"www.mylydia.com",
    "wof:name":"My Lydia Boutique",
    "wof:placetype":"venue"
},
  "geometry": {"coordinates":[-117.832006,34.036491],"type":"Point"}
}