{
  "type": "Feature",
  "properties": {
    "addr:full":"2557 W Winton Ave Hayward CA 94545",
    "addr:housenumber":"2557",
    "addr:postcode":"94545",
    "addr:street":"W Winton Ave",
    "iso:country":"US",
    "sg:address":"2557 W Winton Ave",
    "sg:city":"Hayward",
    "sg:classifiers":[
        {
            "category":"Wholesale",
            "subcategory":"Electrical",
            "type":"Manufacturing & Wholesale Goods"
        }
    ],
    "sg:phone":"+1 510 264 9151",
    "sg:postcode":"94545",
    "sg:province":"CA",
    "sg:tags":[
        "control",
        "security",
        "system"
    ],
    "wof:name":"Arrowvision Technologies Inc",
    "wof:placetype":"venue"
},
  "geometry": {"coordinates":[-122.145195,37.648156],"type":"Point"}
}