{
  "type": "Feature",
  "properties": {
    "addr:full":"256 Commercial St Portola CA 96122",
    "addr:housenumber":"256",
    "addr:postcode":"96122",
    "addr:street":"Commercial St",
    "iso:country":"US",
    "sg:address":"256 Commercial St",
    "sg:city":"Portola",
    "sg:classifiers":[
        {
            "category":"Travel",
            "subcategory":"Hotels & Motels",
            "type":"Entertainment"
        }
    ],
    "sg:phone":"+1 530 832 0107",
    "sg:postcode":"96122",
    "sg:province":"CA",
    "sg:tags":[
        "breakfast",
        "accommodation",
        "bed"
    ],
    "wof:name":"Pullman House Inn",
    "wof:placetype":"venue"
},
  "geometry": {"coordinates":[-120.469829,39.806196],"type":"Point"}
}