{
  "type": "Feature",
  "properties": {
    "addr:full":"11679 Atlantic Ave Lynwood CA 90262",
    "addr:housenumber":"11679",
    "addr:postcode":"90262",
    "addr:street":"Atlantic Ave",
    "iso:country":"US",
    "sg:address":"11679 Atlantic Ave",
    "sg:city":"Lynwood",
    "sg:classifiers":[
        {
            "category":"Shopping",
            "subcategory":"Bicycles & Sporting Goods",
            "type":"Retail Goods"
        }
    ],
    "sg:phone":"+1 310 669 9392",
    "sg:postcode":"90262",
    "sg:province":"CA",
    "wof:name":"Innovations Bike Shop",
    "wof:placetype":"venue"
},
  "geometry": {"coordinates":[-118.189127,33.917557],"type":"Point"}
}