{
  "type": "Feature",
  "properties": {
    "iso:country":"US",
    "sg:address":"402 W Pacheco Blvd",
    "sg:city":"Los Banos",
    "sg:classifiers":[
        {
            "category":"Banks & Credit Unions",
            "subcategory":"Bank",
            "type":"Services"
        }
    ],
    "sg:phone":"+1 209 826 7061",
    "sg:postcode":"93635",
    "sg:province":"CA",
    "sg:tags":[
        "cashing",
        "check"
    ],
    "wof:name":"Money Mart",
    "wof:placetype":"venue"
},
  "geometry": {"coordinates":[-120.85909700000001,37.056952],"type":"Point"}
}