{
  "type": "Feature",
  "properties": {
    "addr:full":"1160 Saratoga Ct Tracy CA 95376",
    "addr:housenumber":"1160",
    "addr:postcode":"95376",
    "addr:street":"Saratoga Ct",
    "iso:country":"US",
    "sg:address":"1160 Saratoga Ct",
    "sg:city":"Tracy",
    "sg:classifiers":[
        {
            "category":"Communications",
            "type":"Services"
        }
    ],
    "sg:phone":"+1 209 830 7223",
    "sg:postcode":"95376",
    "sg:province":"CA",
    "wof:name":"Rodda Communications",
    "wof:placetype":"venue"
},
  "geometry": {"coordinates":[-121.441007,37.722005],"type":"Point"}
}