{
  "type": "Feature",
  "properties": {
    "addr:full":"141 Kansas St Redlands CA 92373",
    "addr:postcode":"92373",
    "addr:street":"141 Kansas St",
    "iso:country":"US",
    "sg:address":"141 Kansas St",
    "sg:city":"Redlands",
    "sg:classifiers":[
        {
            "category":"Building & Trades",
            "subcategory":"Construction",
            "type":"Services"
        }
    ],
    "sg:phone":"+1 909 798 7268",
    "sg:postcode":"92373",
    "sg:province":"CA",
    "sg:tags":[
        "specializing",
        "new",
        "contractor",
        "general"
    ],
    "wof:name":"Current Enterprises Inc",
    "wof:placetype":"venue"
},
  "geometry": {"coordinates":[-117.204457,34.052721],"type":"Point"}
}