{
  "type": "Feature",
  "properties": {
    "iso:country":"US",
    "sg:address":"1714 Stockton St",
    "sg:city":"San Francisco",
    "sg:classifiers":[
        {
            "category":"Professional",
            "subcategory":"Research",
            "type":"Services"
        }
    ],
    "sg:phone":"+1 415 495 5408",
    "sg:postcode":"94133",
    "sg:province":"CA",
    "sg:tags":[
        "foundation",
        "philanthropic"
    ],
    "sg:website":"www.hirschassoc.com",
    "wof:name":"Susan Hirsch & Assoc",
    "wof:placetype":"venue"
},
  "geometry": {"coordinates":[-122.409339,37.801526],"type":"Point"}
}