{
  "type": "Feature",
  "properties": {
    "iso:country":"US",
    "sg:address":"253 S 25th St",
    "sg:city":"Richmond",
    "sg:classifiers":[
        {
            "category":"Professional",
            "type":"Services"
        }
    ],
    "sg:phone":"+1 510 232 3223",
    "sg:postcode":"94804",
    "sg:province":"CA",
    "wof:name":"Paragon Machine Works",
    "wof:placetype":"venue"
},
  "geometry": {"coordinates":[-122.345749,37.928017],"type":"Point"}
}