{
  "type": "Feature",
  "properties": {
    "addr:full":"128 S Salinas St Santa Barbara CA 93103",
    "addr:housenumber":"128",
    "addr:postcode":"93103",
    "addr:street":"S Salinas St",
    "iso:country":"US",
    "sg:address":"128 S Salinas St",
    "sg:city":"Santa Barbara",
    "sg:classifiers":[
        {
            "category":"Food & Beverages",
            "subcategory":"Groceries & Convenience Stores",
            "type":"Retail Goods"
        }
    ],
    "sg:phone":"+1 805 966 6955",
    "sg:postcode":"93103",
    "sg:province":"CA",
    "sg:tags":[
        "grocer"
    ],
    "wof:name":"Fairway Market",
    "wof:placetype":"venue"
},
  "geometry": {"coordinates":[-119.67084199999999,34.424926],"type":"Point"}
}