{
  "type": "Feature",
  "properties": {
    "addr:full":"1612 19th St Bakersfield CA 93301",
    "addr:housenumber":"1612",
    "addr:postcode":"93301",
    "addr:street":"19Th St",
    "iso:country":"US",
    "sg:address":"1612 19th St",
    "sg:city":"Bakersfield",
    "sg:classifiers":[
        {
            "category":"Professional",
            "subcategory":"Computer Services",
            "type":"Services"
        }
    ],
    "sg:phone":"+1 661 392 1328",
    "sg:postcode":"93301",
    "sg:province":"CA",
    "sg:tags":[
        "repair"
    ],
    "wof:name":"Coy Consulting Group",
    "wof:placetype":"venue"
},
  "geometry": {"coordinates":[-119.021072,35.376309],"type":"Point"}
}