{
  "type": "Feature",
  "properties": {
    "addr:full":"5450 Telegraph Rd Ventura CA 93003",
    "addr:housenumber":"5450",
    "addr:postcode":"93003",
    "addr:street":"Telegraph Rd",
    "iso:country":"US",
    "sg:address":"5450 Telegraph Rd",
    "sg:city":"Ventura",
    "sg:classifiers":[
        {
            "category":"Professional",
            "subcategory":"Secretarial Services",
            "type":"Services"
        }
    ],
    "sg:phone":"+1 805 658 2777",
    "sg:postcode":"93003",
    "sg:province":"CA",
    "sg:tags":[
        "convention",
        "court",
        "reporter"
    ],
    "wof:name":"Devine Hall & Assoc Court",
    "wof:placetype":"venue"
},
  "geometry": {"coordinates":[-119.218627,34.277317],"type":"Point"}
}