{
  "type": "Feature",
  "properties": {
    "iso:country":"US",
    "sg:address":"18599 Philo Greenwood Rd",
    "sg:city":"Philo",
    "sg:classifiers":[
        {
            "category":"Recreation",
            "type":"Entertainment"
        }
    ],
    "sg:phone":"+1 707 895 3141",
    "sg:postcode":"95466",
    "sg:province":"CA",
    "sg:tags":[
        "parks"
    ],
    "wof:name":"Parks & Recreation Dept",
    "wof:placetype":"venue"
},
  "geometry": {"coordinates":[-123.484384,39.085955],"type":"Point"}
}