{
  "type": "Feature",
  "properties": {
    "addr:full":"4419 Inglewood Blvd Los Angeles CA 90066",
    "addr:housenumber":"4419",
    "addr:postcode":"90066",
    "addr:street":"Inglewood Blvd",
    "iso:country":"US",
    "sg:address":"4419 Inglewood Blvd",
    "sg:city":"Los Angeles",
    "sg:classifiers":[
        {
            "category":"Government",
            "subcategory":"Office",
            "type":"Public Place"
        }
    ],
    "sg:phone":"+1 310 915 1179",
    "sg:postcode":"90066",
    "sg:province":"CA",
    "sg:tags":[
        "administrative",
        "program",
        "health"
    ],
    "wof:name":"Ivylines Creations Rose Vista",
    "wof:placetype":"venue"
},
  "geometry": {"coordinates":[-118.41932199999999,33.995838],"type":"Point"}
}