{
  "type": "Feature",
  "properties": {
    "iso:country":"US",
    "sg:address":"951 N Rice Ave",
    "sg:city":"Oxnard",
    "sg:classifiers":[
        {
            "category":"Home & Garden",
            "subcategory":"Home Furnishings",
            "type":"Retail Goods"
        }
    ],
    "sg:phone":"+1 805 988 1901",
    "sg:postcode":"93030",
    "sg:province":"CA",
    "sg:tags":[
        "curtain",
        "made",
        "drapery"
    ],
    "wof:name":"Oxnard Interiors",
    "wof:placetype":"venue"
},
  "geometry": {"coordinates":[-119.142094,34.219008],"type":"Point"}
}