{
  "type": "Feature",
  "properties": {
    "iso:country":"US",
    "sg:address":"2326 Rollingwood Dr",
    "sg:city":"San Bruno",
    "sg:classifiers":[
        {
            "category":"Airline",
            "type":"Transportation"
        }
    ],
    "sg:phone":"+1 650 219 7018",
    "sg:postcode":"94066",
    "sg:province":"CA",
    "sg:tags":[
        "courier",
        "air"
    ],
    "wof:name":"Chris Mar International",
    "wof:placetype":"venue"
},
  "geometry": {"coordinates":[-122.442734,37.630153],"type":"Point"}
}