{
  "type": "Feature",
  "properties": {
    "iso:country":"US",
    "sg:address":"12717 Pacific Ave Apt 9",
    "sg:city":"Los Angeles",
    "sg:classifiers":[
        {
            "category":"Retail",
            "subcategory":"Portrait Studio",
            "type":"Services"
        },
        {
            "category":"Shopping",
            "subcategory":"Pharmacy",
            "type":"Retail Goods"
        }
    ],
    "sg:phone":"+1 805 499 4434",
    "sg:postcode":"90066",
    "sg:province":"CA",
    "sg:tags":[
        "photography",
        "drugstore",
        "store"
    ],
    "wof:name":"Longs Drug Store",
    "wof:placetype":"venue"
},
  "geometry": {"coordinates":[-118.437947,34.000471],"type":"Point"}
}