{
  "type": "Feature",
  "properties": {
    "iso:country":"US",
    "sg:address":"5800 Thornton Ave",
    "sg:city":"Newark",
    "sg:classifiers":[
        {
            "category":"Social Services",
            "subcategory":"Adult Care",
            "type":"Services"
        }
    ],
    "sg:phone":"+1 510 744 1097",
    "sg:postcode":"94560",
    "sg:province":"CA",
    "sg:tags":[
        "organization",
        "senior",
        "citizen"
    ],
    "wof:name":"Senior Home Finders",
    "wof:placetype":"venue"
},
  "geometry": {"coordinates":[-122.029701,37.537915],"type":"Point"}
}