{
  "type": "Feature",
  "properties": {
    "iso:country":"US",
    "sg:address":"109 N Almansor St",
    "sg:city":"Alhambra",
    "sg:classifiers":[
        {
            "category":"Wholesale",
            "subcategory":"Chemicals & Plastics",
            "type":"Manufacturing & Wholesale Goods"
        }
    ],
    "sg:phone":"+1 626 282 1200",
    "sg:postcode":"91801",
    "sg:province":"CA",
    "sg:tags":[
        "cleaning",
        "compound"
    ],
    "wof:name":"Roychem",
    "wof:placetype":"venue"
},
  "geometry": {"coordinates":[-118.12138400000001,34.09834],"type":"Point"}
}