{
  "type": "Feature",
  "properties": {
    "addr:full":"580 Cottonwood Drive Milpitas CA 95035",
    "addr:housenumber":"580",
    "addr:postcode":"95035",
    "addr:street":"Cottonwood Drive",
    "iso:country":"US",
    "sg:address":"580 Cottonwood Drive",
    "sg:city":"Milpitas",
    "sg:classifiers":[
        {
            "category":"Professional",
            "subcategory":"Computer Services",
            "type":"Services"
        }
    ],
    "sg:phone":"+1 408 228 1400",
    "sg:postcode":"95035",
    "sg:province":"CA",
    "sg:website":"http://www.promise.com",
    "wof:name":"PROMISE Technology",
    "wof:placetype":"venue"
},
  "geometry": {"coordinates":[-121.91733000000001,37.405339],"type":"Point"}
}