{
  "type": "Feature",
  "properties": {
    "iso:country":"US",
    "sg:address":"442 Tehama St",
    "sg:city":"San Francisco",
    "sg:classifiers":[
        {
            "category":"Wholesale",
            "subcategory":"Wine & Distilled Alcoholic Beverages",
            "type":"Manufacturing & Wholesale Goods"
        }
    ],
    "sg:phone":"+1 415 546 0484",
    "sg:postcode":"94103",
    "sg:province":"CA",
    "sg:tags":[
        "broker"
    ],
    "sg:website":"www.sfwe.com",
    "wof:name":"San Francisco Wine Exchange",
    "wof:placetype":"venue"
},
  "geometry": {"coordinates":[-122.405928,37.780123],"type":"Point"}
}