{
  "type": "Feature",
  "properties": {
    "addr:full":"4430 Telegraph Ave Oakland CA 94609",
    "addr:housenumber":"4430",
    "addr:postcode":"94609",
    "addr:street":"Telegraph Ave",
    "iso:country":"US",
    "sg:address":"4430 Telegraph Ave",
    "sg:city":"Oakland",
    "sg:classifiers":[
        {
            "category":"Shopping",
            "subcategory":"Clothing, Apparel, & Fashions",
            "type":"Retail Goods"
        }
    ],
    "sg:phone":"+1 510 336 3011",
    "sg:postcode":"94609",
    "sg:province":"CA",
    "sg:tags":[
        "suspender",
        "belt"
    ],
    "wof:name":"Invasions",
    "wof:placetype":"venue"
},
  "geometry": {"coordinates":[-122.263518,37.832761],"type":"Point"}
}