{
  "type": "Feature",
  "properties": {
    "iso:country":"US",
    "sg:address":"520 Redondo Ave",
    "sg:city":"Long Beach",
    "sg:classifiers":[
        {
            "category":"Professional",
            "subcategory":"Lawyer & Legal Services",
            "type":"Services"
        },
        {
            "category":"Banks & Credit Unions",
            "subcategory":"Atm",
            "type":"Services"
        }
    ],
    "sg:phone":"+1 562 434 4491",
    "sg:postcode":"90814",
    "sg:province":"CA",
    "sg:tags":[
        "litigation",
        "personal",
        "injury",
        "bankruptcy"
    ],
    "sg:website":"www.lawrmac.com",
    "wof:name":"Law Office of RM Anthonty Cosio",
    "wof:placetype":"venue"
},
  "geometry": {"coordinates":[-118.152069,33.773102],"type":"Point"}
}