{
  "type": "Feature",
  "properties": {
    "iso:country":"US",
    "sg:address":"2602 E Cliff Dr",
    "sg:city":"Santa Cruz",
    "sg:classifiers":[
        {
            "category":"Social Services",
            "subcategory":"Job Training",
            "type":"Services"
        }
    ],
    "sg:phone":"+1 831 477 1054",
    "sg:postcode":"95062",
    "sg:province":"CA",
    "sg:tags":[
        "retardation",
        "disabled",
        "mental",
        "dev"
    ],
    "wof:name":"Beacon Independent Living Svc",
    "wof:placetype":"venue"
},
  "geometry": {"coordinates":[-121.999353,36.962498],"type":"Point"}
}