{
  "type": "Feature",
  "properties": {
    "iso:country":"US",
    "sg:address":"10366 Roselle St",
    "sg:city":"San Diego",
    "sg:classifiers":[
        {
            "category":"Professional",
            "subcategory":"Research",
            "type":"Services"
        }
    ],
    "sg:phone":"+1 858 558 8229",
    "sg:postcode":"92121",
    "sg:province":"CA",
    "sg:tags":[
        "biotechnology",
        "product"
    ],
    "wof:name":"Kanda Met Biotech Ctr",
    "wof:placetype":"venue"
},
  "geometry": {"coordinates":[-117.21850999999999,32.893398],"type":"Point"}
}