{
  "type": "Feature",
  "properties": {
    "addr:full":"1563 Geary Rd Walnut Creek CA 94597",
    "addr:housenumber":"1563",
    "addr:postcode":"94597",
    "addr:street":"Geary Rd",
    "iso:country":"US",
    "sg:address":"1563 Geary Rd",
    "sg:city":"Walnut Creek",
    "sg:classifiers":[
        {
            "category":"Building & Trades",
            "subcategory":"Landscaping Services",
            "type":"Services"
        }
    ],
    "sg:phone":"+1 925 458 6678",
    "sg:postcode":"94597",
    "sg:province":"CA",
    "wof:name":"Jeg Inc",
    "wof:placetype":"venue"
},
  "geometry": {"coordinates":[-122.06574500000001,37.926315],"type":"Point"}
}