{
  "type": "Feature",
  "properties": {
    "iso:country":"US",
    "sg:address":"2902 Grove St",
    "sg:city":"Ventura",
    "sg:classifiers":[
        {
            "category":"Professional",
            "type":"Services"
        }
    ],
    "sg:phone":"+1 805 653 5670",
    "sg:postcode":"93003",
    "sg:province":"CA",
    "sg:tags":[
        "consultant",
        "geological"
    ],
    "wof:name":"Terry A Mayer",
    "wof:placetype":"venue"
},
  "geometry": {"coordinates":[-119.25734300000001,34.279654],"type":"Point"}
}