{
  "type": "Feature",
  "properties": {
    "addr:full":"2450 E Philadelphia St Ontario CA 91761",
    "addr:housenumber":"2450 e",
    "addr:postcode":"91761",
    "addr:street":"Philadelphia St",
    "iso:country":"US",
    "sg:address":"2450 E Philadelphia St",
    "sg:city":"Ontario",
    "sg:classifiers":[
        {
            "category":"Utilities",
            "subcategory":"Water",
            "type":"Services"
        }
    ],
    "sg:phone":"+1 909 947 4131",
    "sg:postcode":"91761",
    "sg:province":"CA",
    "sg:tags":[
        "company",
        "sewage"
    ],
    "sg:website":"www.ieua.org",
    "wof:name":"Inland Empire Utilities Agency",
    "wof:placetype":"venue"
},
  "geometry": {"coordinates":[-117.600876,34.033824],"type":"Point"}
}