{
  "type": "Feature",
  "properties": {
    "iso:country":"US",
    "sg:address":"1001 Stokes Ave",
    "sg:city":"Stockton",
    "sg:classifiers":[
        {
            "category":"Wholesale",
            "subcategory":"Stationery",
            "type":"Manufacturing & Wholesale Goods"
        }
    ],
    "sg:phone":"+1 209 467 6833",
    "sg:postcode":"95215",
    "sg:province":"CA",
    "sg:tags":[
        "packaging",
        "material"
    ],
    "wof:name":"Performance Packaging",
    "wof:placetype":"venue"
},
  "geometry": {"coordinates":[-121.237562,37.97276],"type":"Point"}
}