{
  "type": "Feature",
  "properties": {
    "iso:country":"US",
    "sg:address":"10375 Brunswick Rd",
    "sg:city":"Grass Valley",
    "sg:classifiers":[
        {
            "category":"Health Services",
            "subcategory":"Health Practitioner",
            "type":"Services"
        }
    ],
    "sg:phone":"+1 530 272 4284",
    "sg:postcode":"95945",
    "sg:province":"CA",
    "sg:tags":[
        "therapist",
        "physical"
    ],
    "wof:name":"Sierra Rehabilitation Ctr",
    "wof:placetype":"venue"
},
  "geometry": {"coordinates":[-121.03273799999999,39.234466],"type":"Point"}
}