{
  "type": "Feature",
  "properties": {
    "iso:country":"US",
    "sg:address":"21190 Hawthorne Blvd",
    "sg:city":"Torrance",
    "sg:classifiers":[
        {
            "category":"Autos & Motor Vehicles",
            "subcategory":"Fuel & Gas Station",
            "type":"Retail Goods"
        }
    ],
    "sg:phone":"+1 310 316 9129",
    "sg:postcode":"90503",
    "sg:province":"CA",
    "sg:tags":[
        "oil"
    ],
    "wof:name":"Abe's Chevron",
    "wof:placetype":"venue"
},
  "geometry": {"coordinates":[-118.35352899999999,33.839332],"type":"Point"}
}