{
  "type": "Feature",
  "properties": {
    "iso:country":"US",
    "sg:address":"1755 N Highland Ave",
    "sg:city":"Hollywood",
    "sg:classifiers":[
        {
            "category":"Personal",
            "subcategory":"Day Spa",
            "type":"Services"
        }
    ],
    "sg:phone":"+1 323 491 1376",
    "sg:postcode":"90028",
    "sg:province":"CA",
    "sg:website":"www.spaluce.com",
    "wof:name":"Spa Luce",
    "wof:placetype":"venue"
},
  "geometry": {"coordinates":[-118.33877,34.10316],"type":"Point"}
}