{
  "type": "Feature",
  "properties": {
    "iso:country":"US",
    "sg:address":"9399 Chico Dr",
    "sg:city":"Ventura",
    "sg:classifiers":[
        {
            "category":"Professional",
            "subcategory":"Management & Consulting",
            "type":"Services"
        }
    ],
    "sg:phone":"+1 805 647 7958",
    "sg:postcode":"93004",
    "sg:province":"CA",
    "sg:tags":[
        "fuel"
    ],
    "wof:name":"Tan's Resource Management",
    "wof:placetype":"venue"
},
  "geometry": {"coordinates":[-119.175793,34.279922],"type":"Point"}
}