{
  "type": "Feature",
  "properties": {
    "addr:full":"345 N Canon Dr Beverly Hills CA 90210",
    "addr:housenumber":"345",
    "addr:postcode":"90210",
    "addr:street":"N Canon Dr",
    "iso:country":"US",
    "sg:address":"345 N Canon Dr",
    "sg:city":"Beverly Hills",
    "sg:classifiers":[
        {
            "category":"Arts & Performance",
            "subcategory":"Art Gallery",
            "type":"Entertainment"
        }
    ],
    "sg:phone":"+1 888 838 1881",
    "sg:postcode":"90210",
    "sg:province":"CA",
    "sg:website":"www.thecelebrityvault.com",
    "wof:name":"Celebrity Vault",
    "wof:placetype":"venue"
},
  "geometry": {"coordinates":[-118.400136,34.069857],"type":"Point"}
}