{
  "type": "Feature",
  "properties": {
    "iso:country":"US",
    "sg:address":"13033 Mesa Verde Way",
    "sg:city":"Sylmar",
    "sg:classifiers":[
        {
            "category":"Professional",
            "type":"Services"
        }
    ],
    "sg:phone":"+1 818 790 3638",
    "sg:postcode":"91342",
    "sg:province":"CA",
    "wof:name":"Imax Company Ltd",
    "wof:placetype":"venue"
},
  "geometry": {"coordinates":[-118.406396,34.311929],"type":"Point"}
}