{
  "type": "Feature",
  "properties": {
    "iso:country":"US",
    "sg:address":"4918 Dawes St Suite #1",
    "sg:city":"San Diego",
    "sg:classifiers":[
        {
            "category":"Personal",
            "type":"Services"
        }
    ],
    "sg:phone":"+1 858 382 0330",
    "sg:postcode":"92109",
    "sg:province":"CA",
    "sg:tags":[
        "sewing",
        "alteration"
    ],
    "sg:website":"www.mortonibros.com",
    "wof:name":"Mortonibros LLC",
    "wof:placetype":"venue"
},
  "geometry": {"coordinates":[-117.252409,32.804625],"type":"Point"}
}