{
  "type": "Feature",
  "properties": {
    "iso:country":"US",
    "sg:address":"505 W 20th St",
    "sg:city":"Merced",
    "sg:classifiers":[
        {
            "category":"Health Services",
            "subcategory":"Doctor",
            "type":"Services"
        }
    ],
    "sg:phone":"+1 209 725 2980",
    "sg:postcode":"95340",
    "sg:province":"CA",
    "sg:tags":[
        "dentist"
    ],
    "wof:name":"ABC Dental Group",
    "wof:placetype":"venue"
},
  "geometry": {"coordinates":[-120.483034,37.30501],"type":"Point"}
}