{
  "type": "Feature",
  "properties": {
    "addr:full":"818 N Spring Street Suite 101 Los Angeles CA 90012",
    "addr:housenumber":"818",
    "addr:postcode":"90012",
    "addr:street":"N Spring Street Suite 101",
    "iso:country":"US",
    "sg:address":"818 N Spring Street Suite 101",
    "sg:city":"Los Angeles",
    "sg:classifiers":[
        {
            "category":"Shopping",
            "subcategory":"Computers & Home Electronics",
            "type":"Retail Goods"
        }
    ],
    "sg:phone":"+1 213 625 2335",
    "sg:postcode":"90012",
    "sg:province":"CA",
    "wof:name":"Mtv Wholesale and Retail",
    "wof:placetype":"venue"
},
  "geometry": {"coordinates":[-118.236653,34.062393],"type":"Point"}
}