{
  "type": "Feature",
  "properties": {
    "iso:country":"US",
    "sg:address":"484 Oakmead Pkwy",
    "sg:city":"Sunnyvale",
    "sg:classifiers":[
        {
            "category":"Manufacturing",
            "subcategory":"Tools & Machinery",
            "type":"Manufacturing & Wholesale Goods"
        }
    ],
    "sg:phone":"+1 408 731 2000",
    "sg:postcode":"94085",
    "sg:province":"CA",
    "sg:tags":[
        "computer",
        "mfg",
        "peripheral",
        "trade",
        "printing",
        "e"
    ],
    "sg:website":"www.gmicolor.com",
    "wof:name":"Graphics Microsystems (ca)",
    "wof:placetype":"venue"
},
  "geometry": {"coordinates":[-121.98833999999999,37.384],"type":"Point"}
}