{
  "type": "Feature",
  "properties": {
    "iso:country":"US",
    "sg:address":"2388 Fletcher Pkwy",
    "sg:city":"San Diego",
    "sg:classifiers":[
        {
            "category":"Professional",
            "type":"Services"
        },
        {
            "category":"Restaurant",
            "type":"Food & Drink"
        }
    ],
    "sg:phone":"+1 619 462 5434",
    "sg:postcode":"92020",
    "sg:province":"CA",
    "sg:tags":[
        "barbeque",
        "caterer"
    ],
    "sg:website":"www.thebarbecuepitrestaurant.com",
    "wof:name":"Barbecue Pit",
    "wof:placetype":"venue"
},
  "geometry": {"coordinates":[-116.997208,32.802788],"type":"Point"}
}