{
  "type": "Feature",
  "properties": {
    "iso:country":"US",
    "sg:address":"8949 Reseda Blvd",
    "sg:city":"Northridge",
    "sg:classifiers":[
        {
            "category":"Health Services",
            "subcategory":"Clinic",
            "type":"Services"
        }
    ],
    "sg:phone":"+1 818 709 4805",
    "sg:postcode":"91324",
    "sg:province":"CA",
    "sg:tags":[
        "home"
    ],
    "wof:name":"Family Home Health Care",
    "wof:placetype":"venue"
},
  "geometry": {"coordinates":[-118.53616,34.234611],"type":"Point"}
}