{
  "type": "Feature",
  "properties": {
    "addr:full":"213 N Orange St Glendale CA 91203",
    "addr:housenumber":"213",
    "addr:postcode":"91203",
    "addr:street":"N Orange St",
    "iso:country":"US",
    "sg:address":"213 N Orange St",
    "sg:city":"Glendale",
    "sg:classifiers":[
        {
            "category":"Organizations",
            "subcategory":"Religious Organization",
            "type":"Services"
        }
    ],
    "sg:phone":"+1 818 956 0888",
    "sg:postcode":"91203",
    "sg:province":"CA",
    "sg:website":"www.urimandthummim.com",
    "wof:name":"Urim And Thummim",
    "wof:placetype":"venue"
},
  "geometry": {"coordinates":[-118.256536,34.148273],"type":"Point"}
}