{
  "type": "Feature",
  "properties": {
    "iso:country":"US",
    "sg:address":"7125 Fenwick Ln",
    "sg:city":"Westminster",
    "sg:classifiers":[
        {
            "category":"Building & Trades",
            "subcategory":"Construction",
            "type":"Services"
        }
    ],
    "sg:phone":"+1 714 894 6464",
    "sg:postcode":"92683",
    "sg:province":"CA",
    "sg:tags":[
        "waterproofing",
        "contractor"
    ],
    "wof:name":"Technicoat Pacific Management",
    "wof:placetype":"venue"
},
  "geometry": {"coordinates":[-118.00287299999999,33.746786],"type":"Point"}
}