{
  "type": "Feature",
  "properties": {
    "iso:country":"US",
    "sg:address":"6851 Lennox Ave",
    "sg:city":"Van Nuys",
    "sg:classifiers":[
        {
            "category":"Health Services",
            "subcategory":"Hospital",
            "type":"Services"
        }
    ],
    "sg:phone":"+1 818 994 6747",
    "sg:postcode":"91405",
    "sg:province":"CA",
    "sg:tags":[
        "mental"
    ],
    "wof:name":"Alliance For The Mentally Ill",
    "wof:placetype":"venue"
},
  "geometry": {"coordinates":[-118.445521,34.19483],"type":"Point"}
}