{
  "type": "Feature",
  "properties": {
    "addr:full":"10090 Fall River Ct Fountain Valley CA 92708",
    "addr:housenumber":"10090",
    "addr:postcode":"92708",
    "addr:street":"Fall River Ct",
    "iso:country":"US",
    "sg:address":"10090 Fall River Ct",
    "sg:city":"Fountain Valley",
    "sg:classifiers":[
        {
            "category":"Building & Trades",
            "subcategory":"Equipment Rental",
            "type":"Services"
        }
    ],
    "sg:phone":"+1 714 964 6354",
    "sg:postcode":"92708",
    "sg:province":"CA",
    "wof:name":"Visual Contact Productions",
    "wof:placetype":"venue"
},
  "geometry": {"coordinates":[-117.952517,33.699085],"type":"Point"}
}