{
  "type": "Feature",
  "properties": {
    "addr:full":"6006 Miramar Rd San Diego CA 92121",
    "addr:housenumber":"6006",
    "addr:postcode":"92121",
    "addr:street":"Miramar Rd",
    "iso:country":"US",
    "sg:address":"6006 Miramar Rd",
    "sg:city":"San Diego",
    "sg:classifiers":[
        {
            "category":"Autos & Motor Vehicles",
            "subcategory":"Automobile Sales",
            "type":"Retail Goods"
        }
    ],
    "sg:phone":"+1 858 623 2300",
    "sg:postcode":"92121",
    "sg:province":"CA",
    "sg:tags":[
        "car",
        "dealer"
    ],
    "sg:website":"www.budgetcalifornia.com",
    "wof:name":"Budget Car Sales",
    "wof:placetype":"venue"
},
  "geometry": {"coordinates":[-117.179383,32.877586],"type":"Point"}
}