{
  "type": "Feature",
  "properties": {
    "iso:country":"US",
    "sg:address":"6948 Eastman St",
    "sg:city":"San Diego",
    "sg:classifiers":[
        {
            "category":"Real Estate",
            "subcategory":"Real Estate Operator",
            "type":"Services"
        }
    ],
    "sg:phone":"+1 858 565 0926",
    "sg:postcode":"92111",
    "sg:province":"CA",
    "sg:tags":[
        "apartment"
    ],
    "wof:name":"Village Apartments",
    "wof:placetype":"venue"
},
  "geometry": {"coordinates":[-117.170509,32.788061],"type":"Point"}
}