{
  "type": "Feature",
  "properties": {
    "addr:full":"14456 Big Basin Way Saratoga CA 95070",
    "addr:housenumber":"14456",
    "addr:postcode":"95070",
    "addr:street":"Big Basin Way",
    "iso:country":"US",
    "sg:address":"14456 Big Basin Way",
    "sg:city":"Saratoga",
    "sg:classifiers":[
        {
            "category":"Sports & Exercise",
            "subcategory":"Gym",
            "type":"Entertainment"
        }
    ],
    "sg:phone":"+1 408 872 0799",
    "sg:postcode":"95070",
    "sg:province":"CA",
    "sg:tags":[
        "club",
        "health",
        "studio",
        "gymnasium"
    ],
    "wof:name":"Curves For Women",
    "wof:placetype":"venue"
},
  "geometry": {"coordinates":[-122.032915,37.258283],"type":"Point"}
}