{
  "type": "Feature",
  "properties": {
    "iso:country":"US",
    "sg:address":"600 Temple Ave",
    "sg:city":"Camarillo",
    "sg:classifiers":[
        {
            "category":"Education",
            "subcategory":"School",
            "type":"Public Place"
        }
    ],
    "sg:phone":"+1 805 482 2763",
    "sg:postcode":"93010",
    "sg:province":"CA",
    "sg:tags":[
        "high",
        "middle",
        "elementary"
    ],
    "wof:name":"Pleasant Valley School Dist",
    "wof:placetype":"venue"
},
  "geometry": {"coordinates":[-119.029999,34.223598],"type":"Point"}
}