{
  "type": "Feature",
  "properties": {
    "iso:country":"US",
    "sg:address":"4432 James Ave",
    "sg:city":"Castro Valley",
    "sg:classifiers":[
        {
            "category":"Social Services",
            "subcategory":"Job Training",
            "type":"Services"
        }
    ],
    "sg:phone":"+1 510 881 1389",
    "sg:postcode":"94546",
    "sg:province":"CA",
    "sg:tags":[
        "rehabilitation"
    ],
    "wof:name":"Synergy Rehabilitation Inc",
    "wof:placetype":"venue"
},
  "geometry": {"coordinates":[-122.068707,37.706595],"type":"Point"}
}