{
  "type": "Feature",
  "properties": {
    "addr:full":"6864 F St Tres Pinos CA 95075",
    "addr:housenumber":"6864",
    "addr:postcode":"tres pinos ca 95075",
    "addr:street":"F St",
    "iso:country":"US",
    "sg:address":"6864 F St",
    "sg:city":"Tres Pinos",
    "sg:classifiers":[
        {
            "category":"Farming",
            "subcategory":"Livestock Farm",
            "type":"Manufacturing & Wholesale Goods"
        }
    ],
    "sg:phone":"+1 831 628 3559",
    "sg:postcode":"95075",
    "sg:province":"CA",
    "sg:tags":[
        "ranch"
    ],
    "wof:name":"Peter C Frusetta Ranch",
    "wof:placetype":"venue"
},
  "geometry": {"coordinates":[-121.322845,36.789541],"type":"Point"}
}