{
  "type": "Feature",
  "properties": {
    "addr:full":"2104 Bailey Ct Modesto CA 95355",
    "addr:housenumber":"2104",
    "addr:postcode":"ca 95355",
    "addr:street":"Bailey Ct",
    "iso:country":"US",
    "sg:address":"2104 Bailey Ct",
    "sg:city":"Modesto",
    "sg:classifiers":[
        {
            "category":"Building & Trades",
            "subcategory":"Construction",
            "type":"Services"
        }
    ],
    "sg:phone":"+1 209 551 3420",
    "sg:postcode":"95355",
    "sg:province":"CA",
    "sg:tags":[
        "contractor"
    ],
    "wof:name":"A & J Roofing Co",
    "wof:placetype":"venue"
},
  "geometry": {"coordinates":[-120.953486,37.674039],"type":"Point"}
}