{
  "type": "Feature",
  "properties": {
    "addr:full":"597 E Green St Ste 102 Pasadena CA 91101",
    "addr:housenumber":"597",
    "addr:postcode":"91101",
    "addr:street":"E Green St Ste 102",
    "iso:country":"US",
    "sg:address":"597 E Green St Ste 102",
    "sg:city":"Pasadena",
    "sg:classifiers":[
        {
            "category":"Arts & Performance",
            "subcategory":"Art Gallery",
            "type":"Entertainment"
        }
    ],
    "sg:phone":"+1 626 577 1223",
    "sg:postcode":"91101",
    "sg:province":"CA",
    "sg:website":"www.galeriegabrie.com",
    "wof:name":"Galerie Gabrie",
    "wof:placetype":"venue"
},
  "geometry": {"coordinates":[-118.13808899999999,34.144727],"type":"Point"}
}