{
  "type": "Feature",
  "properties": {
    "addr:full":"388 Townsend St Ste 17 San Francisco CA 94107",
    "addr:housenumber":"388",
    "addr:postcode":"94107",
    "addr:street":"Townsend St Ste 17",
    "iso:country":"US",
    "sg:address":"388 Townsend St Ste 17",
    "sg:city":"San Francisco",
    "sg:classifiers":[
        {
            "category":"Personal",
            "type":"Services"
        },
        {
            "category":"Education",
            "subcategory":"Vocational School",
            "type":"Public Place"
        }
    ],
    "sg:phone":"+1 800 210 4018",
    "sg:postcode":"94107",
    "sg:province":"CA",
    "sg:tags":[
        "planning",
        "party",
        "cooking",
        "event"
    ],
    "sg:website":"www.cookclubparties.com",
    "wof:name":"Cook Club",
    "wof:placetype":"venue"
},
  "geometry": {"coordinates":[-122.397012,37.775873],"type":"Point"}
}