{
  "type": "Feature",
  "properties": {
    "iso:country":"US",
    "sg:address":"1755 Euclid Ave",
    "sg:city":"San Diego",
    "sg:classifiers":[
        {
            "category":"Shopping",
            "subcategory":"Clothing, Apparel, & Fashions",
            "type":"Retail Goods"
        }
    ],
    "sg:phone":"+1 619 263 3112",
    "sg:postcode":"92105",
    "sg:province":"CA",
    "sg:tags":[
        "hosiery"
    ],
    "wof:name":"Captown",
    "wof:placetype":"venue"
},
  "geometry": {"coordinates":[-117.084856,32.724017],"type":"Point"}
}