{
  "type": "Feature",
  "properties": {
    "addr:full":"14603 Woods Valley Rd Valley Center CA 92082",
    "addr:housenumber":"14603",
    "addr:postcode":"92082",
    "addr:street":"Woods Valley Rd",
    "iso:country":"US",
    "sg:address":"14603 Woods Valley Rd",
    "sg:city":"Valley Center",
    "sg:classifiers":[
        {
            "category":"Retail",
            "subcategory":"Animal Services",
            "type":"Services"
        }
    ],
    "sg:phone":"+1 760 751 9335",
    "sg:postcode":"92082",
    "sg:province":"CA",
    "wof:name":"Fraziers Racing Stables",
    "wof:placetype":"venue"
},
  "geometry": {"coordinates":[-117.012885,33.205222],"type":"Point"}
}