{
  "type": "Feature",
  "properties": {
    "addr:full":"45108 Via Quivera Temecula CA 92592",
    "addr:housenumber":"45108",
    "addr:postcode":"92592",
    "addr:street":"Via Quivera",
    "iso:country":"US",
    "sg:address":"45108 Via Quivera",
    "sg:city":"Temecula",
    "sg:classifiers":[
        {
            "category":"Shopping",
            "subcategory":"Beauty & Cosmetics",
            "type":"Retail Goods"
        }
    ],
    "sg:phone":"+1 951 693 0590",
    "sg:postcode":"92592",
    "sg:province":"CA",
    "sg:tags":[
        "merchandise"
    ],
    "wof:name":"Tammy Tarbet",
    "wof:placetype":"venue"
},
  "geometry": {"coordinates":[-117.108085,33.470293],"type":"Point"}
}