{
  "type": "Feature",
  "properties": {
    "iso:country":"US",
    "sg:address":"Venice Blvd. at Culver Blvd.",
    "sg:city":"Culver City",
    "sg:classifiers":[
        {
            "category":"Personal",
            "type":"Services"
        },
        {
            "category":"Arts & Performance",
            "subcategory":"Music",
            "type":"Entertainment"
        }
    ],
    "sg:phone":"+1 310 242 3399",
    "sg:postcode":"90232",
    "sg:province":"CA",
    "sg:tags":[
        "party",
        "planning",
        "dj",
        "event"
    ],
    "sg:website":"www.losangelesaudiorentals.com",
    "wof:name":"Los Angeles Audio Rentals",
    "wof:placetype":"venue"
},
  "geometry": {"coordinates":[-118.39249,34.02692],"type":"Point"}
}