{
  "type": "Feature",
  "properties": {
    "addr:full":"1200 S Hope St Los Angeles CA 90015",
    "addr:housenumber":"1200",
    "addr:postcode":"90015",
    "addr:street":"S Hope St",
    "iso:country":"US",
    "sg:address":"1200 S Hope St",
    "sg:city":"Los Angeles",
    "sg:classifiers":[
        {
            "category":"Manufacturing",
            "subcategory":"Apparel",
            "type":"Manufacturing & Wholesale Goods"
        }
    ],
    "sg:phone":"+1 213 748 2696",
    "sg:postcode":"90015",
    "sg:province":"CA",
    "sg:tags":[
        "mfg",
        "woman",
        "sportswear",
        "suit"
    ],
    "wof:name":"Dolce Company",
    "wof:placetype":"venue"
},
  "geometry": {"coordinates":[-118.26562300000001,34.039491],"type":"Point"}
}