{
  "type": "Feature",
  "properties": {
    "iso:country":"US",
    "sg:address":"8333 Case St Ste B",
    "sg:city":"La Mesa",
    "sg:classifiers":[
        {
            "category":"Retail",
            "subcategory":"Repair Shop",
            "type":"Services"
        }
    ],
    "sg:phone":"+1 619 469 4456",
    "sg:postcode":"91942",
    "sg:province":"CA",
    "sg:tags":[
        "reupholstery",
        "furniture"
    ],
    "wof:name":"Parkway Upholstery",
    "wof:placetype":"venue"
},
  "geometry": {"coordinates":[-117.0206,32.773664],"type":"Point"}
}