{
  "type": "Feature",
  "properties": {
    "addr:full":"534 W Elder St Fallbrook CA 92028",
    "addr:housenumber":"534",
    "addr:postcode":"92028",
    "addr:street":"W Elder St",
    "iso:country":"US",
    "sg:address":"534 W Elder St",
    "sg:city":"Fallbrook",
    "sg:classifiers":[
        {
            "category":"Professional",
            "type":"Services"
        }
    ],
    "sg:phone":"+1 760 731 7556",
    "sg:postcode":"92028",
    "sg:province":"CA",
    "sg:tags":[
        "establishment"
    ],
    "wof:name":"Base X Shelters",
    "wof:placetype":"venue"
},
  "geometry": {"coordinates":[-117.25376799999999,33.380176],"type":"Point"}
}