{
  "type": "Feature",
  "properties": {
    "addr:full":"1437 S Victoria Ave Ventura CA 93003",
    "addr:housenumber":"1437",
    "addr:postcode":"93003",
    "addr:street":"S Victoria Ave",
    "iso:country":"US",
    "sg:address":"1437 S Victoria Ave",
    "sg:city":"Ventura",
    "sg:classifiers":[
        {
            "category":"Retail",
            "subcategory":"Laundry & Dry Cleaning",
            "type":"Services"
        }
    ],
    "sg:phone":"+1 805 644 2363",
    "sg:postcode":"93003",
    "sg:province":"CA",
    "sg:tags":[
        "cleaners"
    ],
    "wof:name":"Victoria Village Cleaners",
    "wof:placetype":"venue"
},
  "geometry": {"coordinates":[-119.211862,34.262476],"type":"Point"}
}