{
  "type": "Feature",
  "properties": {
    "addr:full":"23705 Crenshaw Blvd Torrance CA 90505",
    "addr:housenumber":"23705",
    "addr:postcode":"90505",
    "addr:street":"Crenshaw Blvd",
    "iso:country":"US",
    "sg:address":"23705 Crenshaw Blvd",
    "sg:city":"Torrance",
    "sg:classifiers":[
        {
            "category":"Retail",
            "subcategory":"Repair Shop",
            "type":"Services"
        }
    ],
    "sg:phone":"+1 310 257 8800",
    "sg:postcode":"90505",
    "sg:province":"CA",
    "sg:tags":[
        "plumbing",
        "drain",
        "cleaning",
        "sewer"
    ],
    "wof:name":"Reddy Rooter",
    "wof:placetype":"venue"
},
  "geometry": {"coordinates":[-118.328107,33.812746],"type":"Point"}
}