{
  "type": "Feature",
  "properties": {
    "addr:full":"6480 W Coast Hwy Newport Beach CA 92663",
    "addr:housenumber":"6480",
    "addr:postcode":"92663",
    "addr:street":"W Coast Hwy",
    "iso:country":"US",
    "sg:address":"6480 W Coast Hwy",
    "sg:city":"Newport Beach",
    "sg:classifiers":[
        {
            "category":"Shopping",
            "subcategory":"Party Supplies",
            "type":"Retail Goods"
        }
    ],
    "sg:phone":"+1 877 373 7769",
    "sg:postcode":"92663",
    "sg:province":"CA",
    "sg:website":"www.dressmyparty.com/",
    "wof:name":"Dress My Party",
    "wof:placetype":"venue"
},
  "geometry": {"coordinates":[-117.95038099999999,33.627343],"type":"Point"}
}