{
  "type": "Feature",
  "properties": {
    "iso:country":"US",
    "sg:address":"556 N Hope Ave",
    "sg:city":"Santa Barbara",
    "sg:classifiers":[
        {
            "category":"Organizations",
            "subcategory":"Religious Organization",
            "type":"Services"
        }
    ],
    "sg:phone":"+1 805 687 1115",
    "sg:postcode":"93110",
    "sg:province":"CA",
    "sg:tags":[
        "church"
    ],
    "sg:website":"www.bethanysb.org",
    "wof:name":"Bethany Congregational Church",
    "wof:placetype":"venue"
},
  "geometry": {"coordinates":[-119.746629,34.447888],"type":"Point"}
}