{
  "type": "Feature",
  "properties": {
    "iso:country":"US",
    "sg:address":"3704 23rd Ave",
    "sg:city":"Sacramento",
    "sg:classifiers":[
        {
            "category":"Building & Trades",
            "subcategory":"Construction",
            "type":"Services"
        }
    ],
    "sg:phone":"+1 916 422 9549",
    "sg:postcode":"95820",
    "sg:province":"CA",
    "sg:tags":[
        "downspouts",
        "gutter"
    ],
    "wof:name":"Sacramento Rain Gutters",
    "wof:placetype":"venue"
},
  "geometry": {"coordinates":[-121.464702,38.531824],"type":"Point"}
}