{
  "type": "Feature",
  "properties": {
    "iso:country":"US",
    "sg:address":"1477 Ross Rd",
    "sg:city":"Winterhaven",
    "sg:classifiers":[
        {
            "category":"Government",
            "subcategory":"Office",
            "type":"Public Place"
        }
    ],
    "sg:phone":"+1 760 572 0138",
    "sg:postcode":"92283",
    "sg:province":"CA",
    "wof:name":"Imperial County Road District",
    "wof:placetype":"venue"
},
  "geometry": {"coordinates":[-114.577246,32.781657],"type":"Point"}
}