{
  "type": "Feature",
  "properties": {
    "iso:country":"US",
    "sg:address":"1023 Neptune Ave",
    "sg:city":"Encinitas",
    "sg:classifiers":[
        {
            "category":"Food & Beverages",
            "subcategory":"Groceries & Convenience Stores",
            "type":"Retail Goods"
        }
    ],
    "sg:phone":"+1 760 789 3354",
    "sg:postcode":"92024",
    "sg:province":"CA",
    "sg:tags":[
        "product"
    ],
    "wof:name":"Rosemont Foods",
    "wof:placetype":"venue"
},
  "geometry": {"coordinates":[-117.304871,33.066309],"type":"Point"}
}