{
  "type": "Feature",
  "properties": {
    "addr:full":"79733 Country Club Dr Bermuda Dunes CA 92203",
    "addr:housenumber":"79733",
    "addr:postcode":"92203",
    "addr:street":"Country Club Dr",
    "iso:country":"US",
    "sg:address":"79733 Country Club Dr",
    "sg:city":"Bermuda Dunes",
    "sg:classifiers":[
        {
            "category":"Building & Trades",
            "subcategory":"Cleaning & Sanitation",
            "type":"Services"
        }
    ],
    "sg:phone":"+1 760 345 3830",
    "sg:postcode":"92203",
    "sg:province":"CA",
    "sg:tags":[
        "janitor"
    ],
    "wof:name":"Valley Resource Ctr",
    "wof:placetype":"venue"
},
  "geometry": {"coordinates":[-116.27932699999999,33.751538],"type":"Point"}
}