{
  "type": "Feature",
  "properties": {
    "iso:country":"US",
    "sg:address":"111 Colma Blvd",
    "sg:city":"Daly City",
    "sg:classifiers":[
        {
            "category":"Restaurant",
            "type":"Food & Drink"
        }
    ],
    "sg:menulink":"http://www.allmenus.com/ca/south-san-francisco/172142-burger-king/menu/",
    "sg:phone":"+1 650 994 4367",
    "sg:postcode":"94014",
    "sg:province":"CA",
    "sg:tags":[
        "burger",
        "american"
    ],
    "wof:name":"Burger King",
    "wof:placetype":"venue"
},
  "geometry": {"coordinates":[-122.467,37.677054],"type":"Point"}
}