{
  "type": "Feature",
  "properties": {
    "iso:country":"US",
    "sg:address":"6711 Sierra Ct",
    "sg:city":"Dublin",
    "sg:classifiers":[
        {
            "category":"Manufacturing",
            "subcategory":"Chemicals & Compounds",
            "type":"Manufacturing & Wholesale Goods"
        }
    ],
    "sg:phone":"+1 925 556 1267",
    "sg:postcode":"94568",
    "sg:province":"CA",
    "sg:tags":[
        "preparation",
        "pharmaceutical",
        "mfg"
    ],
    "wof:name":"Amer Pharmaceutical Services",
    "wof:placetype":"venue"
},
  "geometry": {"coordinates":[-121.914689,37.707596],"type":"Point"}
}