{
  "type": "Feature",
  "properties": {
    "addr:full":"470 S Auburn St Grass Valley CA 95945",
    "addr:housenumber":"470",
    "addr:postcode":"95945",
    "addr:street":"S Auburn St",
    "iso:country":"US",
    "sg:address":"470 S Auburn St",
    "sg:city":"Grass Valley",
    "sg:classifiers":[
        {
            "category":"Health Services",
            "subcategory":"Doctor",
            "type":"Services"
        }
    ],
    "sg:phone":"+1 530 274 2880",
    "sg:postcode":"95945",
    "sg:province":"CA",
    "sg:tags":[
        "physician",
        "surgeon"
    ],
    "wof:name":"Gail J Fredericks MD",
    "wof:placetype":"venue"
},
  "geometry": {"coordinates":[-121.061965,39.210728],"type":"Point"}
}