{
  "type": "Feature",
  "properties": {
    "addr:full":"655 Redwood Hwy Mill Valley CA 94941",
    "addr:housenumber":"655",
    "addr:postcode":"94941",
    "addr:street":"Redwood Hwy",
    "iso:country":"US",
    "sg:address":"655 Redwood Hwy",
    "sg:city":"Mill Valley",
    "sg:classifiers":[
        {
            "category":"Real Estate",
            "subcategory":"Real Estate Agent",
            "type":"Services"
        }
    ],
    "sg:phone":"+1 415 380 1863",
    "sg:postcode":"94941",
    "sg:province":"CA",
    "wof:name":"Mc Connell Real Estate",
    "wof:placetype":"venue"
},
  "geometry": {"coordinates":[-122.516463,37.89132],"type":"Point"}
}