{
  "type": "Feature",
  "properties": {
    "addr:full":"80 Grand Ave Oakland CA 94612",
    "addr:housenumber":"80",
    "addr:postcode":"94612",
    "addr:street":"Grand Ave",
    "iso:country":"US",
    "sg:address":"80 Grand Ave",
    "sg:city":"Oakland",
    "sg:classifiers":[
        {
            "category":"Health Services",
            "subcategory":"Doctor",
            "type":"Services"
        }
    ],
    "sg:phone":"+1 510 763 0884",
    "sg:postcode":"94612",
    "sg:province":"CA",
    "sg:tags":[
        "medicine",
        "sport",
        "orthopedist"
    ],
    "wof:name":"Keane Gerald MD",
    "wof:placetype":"venue"
},
  "geometry": {"coordinates":[-122.266159,37.811683],"type":"Point"}
}