{
  "type": "Feature",
  "properties": {
    "addr:full":"2065 E Valley Pkwy Escondido CA 92027",
    "addr:housenumber":"2065",
    "addr:postcode":"92027",
    "addr:street":"E Valley Pkwy",
    "iso:country":"US",
    "sg:address":"2065 E Valley Pkwy",
    "sg:city":"Escondido",
    "sg:classifiers":[
        {
            "category":"Education",
            "subcategory":"School",
            "type":"Public Place"
        }
    ],
    "sg:phone":"+1 760 291 3275",
    "sg:postcode":"92027",
    "sg:province":"CA",
    "wof:name":"Escondo SC Hs Valley Hs",
    "wof:placetype":"venue"
},
  "geometry": {"coordinates":[-117.04990599999999,33.138253],"type":"Point"}
}