{
  "type": "Feature",
  "properties": {
    "addr:full":"1269 18th St Oakland CA 94607",
    "addr:housenumber":"1269",
    "addr:postcode":"94607",
    "addr:street":"18Th St",
    "iso:country":"US",
    "sg:address":"1269 18th St",
    "sg:city":"Oakland",
    "sg:classifiers":[
        {
            "category":"Recreation",
            "type":"Entertainment"
        }
    ],
    "sg:phone":"+1 510 238 2205",
    "sg:postcode":"94607",
    "sg:province":"CA",
    "sg:tags":[
        "pool",
        "swimming"
    ],
    "wof:name":"Swimming Pool",
    "wof:placetype":"venue"
},
  "geometry": {"coordinates":[-122.287818,37.813084],"type":"Point"}
}