{
  "type": "Feature",
  "properties": {
    "iso:country":"US",
    "sg:address":"28910 Robin Hood Ct",
    "sg:city":"Long Barn",
    "sg:classifiers":[
        {
            "category":"Building & Trades",
            "subcategory":"Construction",
            "type":"Services"
        }
    ],
    "sg:phone":"+1 209 965 3249",
    "sg:postcode":"95335",
    "sg:province":"CA",
    "sg:tags":[
        "excavating",
        "contractor"
    ],
    "wof:name":"DAVID Graham Enterprises",
    "wof:placetype":"venue"
},
  "geometry": {"coordinates":[-120.074456,38.146761],"type":"Point"}
}