{
  "type": "Feature",
  "properties": {
    "iso:country":"US",
    "sg:address":"453 E Valley Pkwy",
    "sg:city":"Escondido",
    "sg:classifiers":[
        {
            "category":"Home & Garden",
            "subcategory":"Building Materials",
            "type":"Retail Goods"
        }
    ],
    "sg:phone":"+1 760 480 4527",
    "sg:postcode":"92025",
    "sg:province":"CA",
    "sg:tags":[
        "glass",
        "window",
        "plate"
    ],
    "wof:name":"Joe's Glass Shack",
    "wof:placetype":"venue"
},
  "geometry": {"coordinates":[-117.07804400000001,33.124629],"type":"Point"}
}