{
  "type": "Feature",
  "properties": {
    "addr:full":"4001 Florence Ave Bell CA 90201",
    "addr:housenumber":"4001",
    "addr:postcode":"90201",
    "addr:street":"Florence Ave",
    "iso:country":"US",
    "sg:address":"4001 Florence Ave",
    "sg:city":"Bell",
    "sg:classifiers":[
        {
            "category":"Health Services",
            "subcategory":"Health Practitioner",
            "type":"Services"
        }
    ],
    "sg:phone":"+1 323 771 5200",
    "sg:postcode":"90201",
    "sg:province":"CA",
    "sg:tags":[
        "medicine",
        "alternative"
    ],
    "wof:name":"Tower Orthopedics & Sports",
    "wof:placetype":"venue"
},
  "geometry": {"coordinates":[-118.19381,33.970912],"type":"Point"}
}