{
  "type": "Feature",
  "properties": {
    "addr:full":"3017 Santa Monica Blvd Santa Monica CA 90404",
    "addr:housenumber":"3017",
    "addr:postcode":"90404",
    "addr:street":"Santa Monica Blvd",
    "iso:country":"US",
    "sg:address":"3017 Santa Monica Blvd",
    "sg:city":"Santa Monica",
    "sg:classifiers":[
        {
            "category":"Building & Trades",
            "subcategory":"Construction",
            "type":"Services"
        }
    ],
    "sg:phone":"+1 310 453 1938",
    "sg:postcode":"90404",
    "sg:province":"CA",
    "sg:tags":[
        "contractor"
    ],
    "wof:name":"C H Construction",
    "wof:placetype":"venue"
},
  "geometry": {"coordinates":[-118.469768,34.037047],"type":"Point"}
}