{
  "type": "Feature",
  "properties": {
    "addr:full":"750 N Highland Avenue Los Angeles CA 90038",
    "addr:housenumber":"750",
    "addr:postcode":"90038",
    "addr:street":"N Highland Avenue",
    "iso:country":"US",
    "sg:address":"750 N Highland Avenue",
    "sg:city":"Los Angeles",
    "sg:classifiers":[
        {
            "category":"Health Services",
            "subcategory":"Doctor",
            "type":"Services"
        }
    ],
    "sg:phone":"+1 323 461 1960",
    "sg:postcode":"90038",
    "sg:province":"CA",
    "wof:name":"California Breath Clinic",
    "wof:placetype":"venue"
},
  "geometry": {"coordinates":[-118.338452,34.085011],"type":"Point"}
}