{
  "type": "Feature",
  "properties": {
    "addr:full":"6335 Marindustry Dr San Diego CA 92121",
    "addr:housenumber":"6335",
    "addr:postcode":"92121",
    "addr:street":"Marindustry Dr",
    "iso:country":"US",
    "sg:address":"6335 Marindustry Dr",
    "sg:city":"San Diego",
    "sg:classifiers":[
        {
            "category":"Professional",
            "subcategory":"Management & Consulting",
            "type":"Services"
        }
    ],
    "sg:phone":"+1 858 457 4601",
    "sg:postcode":"92121",
    "sg:province":"CA",
    "sg:tags":[
        "break",
        "coffee",
        "supply"
    ],
    "sg:website":"www.aramark.com",
    "wof:name":"Aramark Refreshment Svc",
    "wof:placetype":"venue"
},
  "geometry": {"coordinates":[-117.177358,32.880045],"type":"Point"}
}