{
  "type": "Feature",
  "properties": {
    "addr:full":"7280 Mission Gorge Rd San Diego CA 92120",
    "addr:housenumber":"7280",
    "addr:postcode":"92120",
    "addr:street":"Mission Gorge Rd",
    "iso:country":"US",
    "sg:address":"7280 Mission Gorge Rd",
    "sg:city":"San Diego",
    "sg:classifiers":[
        {
            "category":"Autos & Motor Vehicles",
            "subcategory":"Auto Supplies",
            "type":"Retail Goods"
        }
    ],
    "sg:phone":"+1 619 582 6415",
    "sg:postcode":"92120",
    "sg:province":"CA",
    "sg:tags":[
        "equipment",
        "racing",
        "car",
        "automobile"
    ],
    "wof:name":"ASA Inc",
    "wof:placetype":"venue"
},
  "geometry": {"coordinates":[-117.08323,32.804876],"type":"Point"}
}