{
  "type": "Feature",
  "properties": {
    "addr:full":"15541 S Western Ave Gardena CA 90249",
    "addr:housenumber":"15541",
    "addr:postcode":"90249",
    "addr:street":"S Western Ave",
    "iso:country":"US",
    "sg:address":"15541 S Western Ave",
    "sg:city":"Gardena",
    "sg:classifiers":[
        {
            "category":"Autos & Motor Vehicles",
            "subcategory":"Automobile Sales",
            "type":"Retail Goods"
        },
        {
            "category":"Autos & Motor Vehicles",
            "subcategory":"Auto Supplies",
            "type":"Retail Goods"
        },
        {
            "category":"Retail",
            "subcategory":"Auto Repair",
            "type":"Services"
        }
    ],
    "sg:phone":"+1 877 590 0001",
    "sg:postcode":"90249",
    "sg:province":"CA",
    "sg:tags":[
        "car",
        "part"
    ],
    "sg:website":"www.gardenahonda.com",
    "wof:name":"DCH Gardena Honda",
    "wof:placetype":"venue"
},
  "geometry": {"coordinates":[-118.30962,33.889262],"type":"Point"}
}