{
  "type": "Feature",
  "properties": {
    "addr:full":"3280 E Foothill Blvd Pasadena CA 91107",
    "addr:housenumber":"3280",
    "addr:postcode":"91107",
    "addr:street":"E Foothill Blvd",
    "iso:country":"US",
    "sg:address":"3280 E Foothill Blvd",
    "sg:city":"Pasadena",
    "sg:classifiers":[
        {
            "category":"Professional",
            "subcategory":"Detective & Security Services",
            "type":"Services"
        }
    ],
    "sg:phone":"+1 626 564 4284",
    "sg:postcode":"91107",
    "sg:province":"CA",
    "sg:tags":[
        "car",
        "armored"
    ],
    "sg:website":"www.atsystemsinc.com",
    "wof:name":"ATI Systems Intl Inc",
    "wof:placetype":"venue"
},
  "geometry": {"coordinates":[-118.084529,34.149957],"type":"Point"}
}