{
  "type": "Feature",
  "properties": {
    "iso:country":"US",
    "sg:address":"29861 Greens Ct",
    "sg:city":"Menifee",
    "sg:classifiers":[
        {
            "category":"Arts & Performance",
            "subcategory":"Theater",
            "type":"Entertainment"
        }
    ],
    "sg:phone":"+1 951 679 0154",
    "sg:postcode":"92584",
    "sg:province":"CA",
    "sg:tags":[
        "musician"
    ],
    "wof:name":"Society For The Preservation",
    "wof:placetype":"venue"
},
  "geometry": {"coordinates":[-117.162657,33.686875],"type":"Point"}
}