{
  "type": "Feature",
  "properties": {
    "iso:country":"US",
    "sg:address":"8301 W Sunset Blvd",
    "sg:city":"West Hollywood",
    "sg:classifiers":[
        {
            "category":"Bars & Pubs",
            "type":"Food & Drink"
        },
        {
            "category":"Restaurant",
            "type":"Food & Drink"
        }
    ],
    "sg:phone":"+1 323 822 7820",
    "sg:postcode":"90069",
    "sg:province":"CA",
    "sg:tags":[
        "mexican"
    ],
    "sg:website":"www.thecabocantina.com/",
    "wof:name":"Cabo Cantina",
    "wof:placetype":"venue"
},
  "geometry": {"coordinates":[-118.37044899999999,34.096648],"type":"Point"}
}