{
  "type": "Feature",
  "properties": {
    "iso:country":"US",
    "sg:address":"1721 Cathay Way",
    "sg:city":"Sacramento",
    "sg:classifiers":[
        {
            "category":"Professional",
            "subcategory":"Art Services",
            "type":"Services"
        }
    ],
    "sg:phone":"+1 916 483 4941",
    "sg:postcode":"95864",
    "sg:province":"CA",
    "sg:tags":[
        "photographer"
    ],
    "wof:name":"Kostyrko Photography",
    "wof:placetype":"venue"
},
  "geometry": {"coordinates":[-121.367851,38.597439],"type":"Point"}
}