{
  "type": "Feature",
  "properties": {
    "iso:country":"US",
    "sg:address":"1036 1st St",
    "sg:city":"Benicia",
    "sg:classifiers":[
        {
            "category":"Manufacturing",
            "subcategory":"Printing",
            "type":"Manufacturing & Wholesale Goods"
        }
    ],
    "sg:phone":"+1 707 557 3177",
    "sg:postcode":"94510",
    "sg:province":"CA",
    "sg:tags":[
        "printer"
    ],
    "wof:name":"B B & B Printing & Publishing",
    "wof:placetype":"venue"
},
  "geometry": {"coordinates":[-122.156338,38.052711],"type":"Point"}
}