{
  "type": "Feature",
  "properties": {
    "iso:country":"US",
    "sg:address":"415 1/2 W Las Tunas Dr",
    "sg:city":"San Gabriel",
    "sg:classifiers":[
        {
            "category":"Personal",
            "type":"Services"
        }
    ],
    "sg:phone":"+1 626 576 0848",
    "sg:postcode":"91776",
    "sg:province":"CA",
    "sg:tags":[
        "sewing",
        "alteration"
    ],
    "wof:name":"Jenny's Tailoring",
    "wof:placetype":"venue"
},
  "geometry": {"coordinates":[-118.10469500000001,34.102603],"type":"Point"}
}