{
  "type": "Feature",
  "properties": {
    "addr:full":"1 Foreman Ln Mill Valley CA 94941",
    "addr:housenumber":"1",
    "addr:postcode":"94941",
    "addr:street":"Foreman Ln",
    "iso:country":"US",
    "sg:address":"1 Foreman Ln",
    "sg:city":"Mill Valley",
    "sg:classifiers":[
        {
            "category":"Professional",
            "type":"Services"
        }
    ],
    "sg:phone":"+1 415 380 8739",
    "sg:postcode":"94941",
    "sg:province":"CA",
    "wof:name":"St Ambrose Mission",
    "wof:placetype":"venue"
},
  "geometry": {"coordinates":[-122.507395,37.888774],"type":"Point"}
}