{
  "type": "Feature",
  "properties": {
    "addr:full":"683 Fremont St Salinas CA 93905",
    "addr:housenumber":"683",
    "addr:postcode":"93905",
    "addr:street":"Fremont St",
    "iso:country":"US",
    "sg:address":"683 Fremont St",
    "sg:city":"Salinas",
    "sg:classifiers":[
        {
            "category":"Recreation",
            "type":"Entertainment"
        }
    ],
    "sg:phone":"+1 831 758 7354",
    "sg:postcode":"93905",
    "sg:province":"CA",
    "sg:tags":[
        "center"
    ],
    "wof:name":"Hebbron Heights Svc Ctr",
    "wof:placetype":"venue"
},
  "geometry": {"coordinates":[-121.632276,36.677607],"type":"Point"}
}