{
  "type": "Feature",
  "properties": {
    "addr:full":"2415 de la Cruz Blvd Santa Clara CA 95050",
    "addr:housenumber":"2415",
    "addr:postcode":"95050",
    "addr:street":"De La Cruz Blvd",
    "iso:country":"US",
    "sg:address":"2415 de la Cruz Blvd",
    "sg:city":"Santa Clara",
    "sg:classifiers":[
        {
            "category":"Professional",
            "type":"Services"
        }
    ],
    "sg:phone":"+1 408 969 0084",
    "sg:postcode":"95050",
    "sg:province":"CA",
    "wof:name":"Picture Element",
    "wof:placetype":"venue"
},
  "geometry": {"coordinates":[-121.941462,37.366184],"type":"Point"}
}