{
  "type": "Feature",
  "properties": {
    "addr:full":"27624 Parker Rd Castaic CA 91384",
    "addr:housenumber":"27624",
    "addr:postcode":"91384",
    "addr:street":"Parker Rd",
    "iso:country":"US",
    "sg:address":"27624 Parker Rd",
    "sg:city":"Castaic",
    "sg:classifiers":[
        {
            "category":"Government",
            "subcategory":"Office",
            "type":"Public Place"
        }
    ],
    "sg:phone":"+1 661 257 4441",
    "sg:postcode":"91384",
    "sg:province":"CA",
    "sg:tags":[
        "transportation"
    ],
    "wof:name":"Public Works Dept of",
    "wof:placetype":"venue"
},
  "geometry": {"coordinates":[-118.623566,34.488961],"type":"Point"}
}