{
  "type": "Feature",
  "properties": {
    "iso:country":"US",
    "sg:address":"24622 Pine St",
    "sg:city":"Santa Clarita",
    "sg:classifiers":[
        {
            "category":"Wholesale",
            "subcategory":"Hardware",
            "type":"Manufacturing & Wholesale Goods"
        }
    ],
    "sg:phone":"+1 661 254 1314",
    "sg:postcode":"91321",
    "sg:province":"CA",
    "sg:tags":[
        "tool"
    ],
    "wof:name":"Mac Tools Inc",
    "wof:placetype":"venue"
},
  "geometry": {"coordinates":[-118.529991,34.384055],"type":"Point"}
}