{
  "type": "Feature",
  "properties": {
    "addr:full":"1265 E Valley Blvd Alhambra CA 91804",
    "addr:housenumber":"1265",
    "addr:postcode":"91804",
    "addr:street":"E Valley Blvd",
    "iso:country":"US",
    "sg:address":"1265 E Valley Blvd",
    "sg:city":"Alhambra",
    "sg:classifiers":[
        {
            "category":"Restaurant",
            "type":"Food & Drink"
        }
    ],
    "sg:phone":"+1 626 281 4836",
    "sg:postcode":"91804",
    "sg:province":"CA",
    "sg:tags":[
        "taiwanese"
    ],
    "wof:name":"Noodle King",
    "wof:placetype":"venue"
},
  "geometry": {"coordinates":[-118.11041899999999,34.07922],"type":"Point"}
}