{
  "type": "Feature",
  "properties": {
    "addr:full":"6045 Madison Ave Carmichael CA 95608",
    "addr:housenumber":"6045",
    "addr:postcode":"95608",
    "addr:street":"Madison Ave",
    "iso:country":"US",
    "sg:address":"6045 Madison Ave",
    "sg:city":"Carmichael",
    "sg:classifiers":[
        {
            "category":"Shopping",
            "type":"Retail Goods"
        }
    ],
    "sg:phone":"+1 916 349 8310",
    "sg:postcode":"95608",
    "sg:province":"CA",
    "sg:tags":[
        "cosmetic",
        "perfume"
    ],
    "wof:name":"Longs Drug",
    "wof:placetype":"venue"
},
  "geometry": {"coordinates":[-121.323928,38.661322],"type":"Point"}
}