{
  "type": "Feature",
  "properties": {
    "iso:country":"US",
    "sg:address":"617 Marin St",
    "sg:city":"Vallejo",
    "sg:classifiers":[
        {
            "category":"Food & Beverages",
            "subcategory":"Specialty",
            "type":"Retail Goods"
        }
    ],
    "sg:phone":"+1 707 557 2530",
    "sg:postcode":"94590",
    "sg:province":"CA",
    "sg:tags":[
        "gourmet",
        "shop"
    ],
    "wof:name":"It's A New Season",
    "wof:placetype":"venue"
},
  "geometry": {"coordinates":[-122.256704,38.101453],"type":"Point"}
}