{
  "type": "Feature",
  "properties": {
    "addr:full":"1801 E Capitol Expy San Jose CA 95121",
    "addr:housenumber":"1801",
    "addr:postcode":"95121",
    "addr:street":"E Capitol Expy",
    "iso:country":"US",
    "sg:address":"1801 E Capitol Expy",
    "sg:city":"San Jose",
    "sg:classifiers":[
        {
            "category":"Professional",
            "subcategory":"Management & Consulting",
            "type":"Services"
        }
    ],
    "sg:phone":"+1 408 274 7572",
    "sg:postcode":"95121",
    "sg:province":"CA",
    "sg:tags":[
        "retail",
        "direct",
        "sales"
    ],
    "wof:name":"Capitol Pure Water",
    "wof:placetype":"venue"
},
  "geometry": {"coordinates":[-121.809755,37.308353],"type":"Point"}
}