{
  "type": "Feature",
  "properties": {
    "addr:full":"2450 Durant Ave Bldg Shed Oakland CA 94603",
    "addr:housenumber":"2450",
    "addr:postcode":"94603",
    "addr:street":"Durant Ave Bldg Shed",
    "iso:country":"US",
    "sg:address":"2450 Durant Ave Bldg Shed",
    "sg:city":"Oakland",
    "sg:classifiers":[
        {
            "category":"Shopping",
            "subcategory":"Florist",
            "type":"Retail Goods"
        }
    ],
    "sg:phone":"+1 510 849 9039",
    "sg:postcode":"94603",
    "sg:province":"CA",
    "wof:name":"Moe's Flowers",
    "wof:placetype":"venue"
},
  "geometry": {"coordinates":[-122.15194700000001,37.739948],"type":"Point"}
}