{
  "type": "Feature",
  "properties": {
    "iso:country":"US",
    "sg:address":"1533 Summitridge Dr",
    "sg:city":"Diamond Bar",
    "sg:classifiers":[
        {
            "category":"Wholesale",
            "subcategory":"Chemicals & Plastics",
            "type":"Manufacturing & Wholesale Goods"
        }
    ],
    "sg:phone":"+1 909 860 7880",
    "sg:postcode":"91765",
    "sg:province":"CA",
    "sg:tags":[
        "adhesive",
        "glue"
    ],
    "wof:name":"K & R Intl",
    "wof:placetype":"venue"
},
  "geometry": {"coordinates":[-117.79799199999999,33.995664],"type":"Point"}
}