{
  "type": "Feature",
  "properties": {
    "iso:country":"US",
    "sg:address":"2554 Yardarm Ave",
    "sg:city":"Port Hueneme",
    "sg:classifiers":[
        {
            "category":"Professional",
            "subcategory":"Computer Services",
            "type":"Services"
        }
    ],
    "sg:phone":"+1 805 939 2036",
    "sg:postcode":"93041",
    "sg:province":"CA",
    "sg:tags":[
        "repair"
    ],
    "wof:name":"Lightspeed Business Svc",
    "wof:placetype":"venue"
},
  "geometry": {"coordinates":[-119.21957399999999,34.179123],"type":"Point"}
}