{
  "type": "Feature",
  "properties": {
    "addr:full":"750 N Escondido Blvd Escondido CA 92025",
    "addr:housenumber":"750",
    "addr:postcode":"92025",
    "addr:street":"N Escondido Blvd",
    "iso:country":"US",
    "sg:address":"750 N Escondido Blvd",
    "sg:city":"Escondido",
    "sg:classifiers":[
        {
            "category":"Retail",
            "subcategory":"Auto Repair",
            "type":"Services"
        }
    ],
    "sg:phone":"+1 760 745 8579",
    "sg:postcode":"92025",
    "sg:province":"CA",
    "sg:tags":[
        "repairing",
        "automobile",
        "grocery",
        "carwash",
        "general"
    ],
    "wof:name":"North County Auto Center",
    "wof:placetype":"venue"
},
  "geometry": {"coordinates":[-117.088984,33.128259],"type":"Point"}
}