{
  "type": "Feature",
  "properties": {
    "addr:full":"60 Dominican Dr San Rafael CA 94901",
    "addr:housenumber":"60",
    "addr:postcode":"94901",
    "addr:street":"Dominican Dr",
    "iso:country":"US",
    "sg:address":"60 Dominican Dr",
    "sg:city":"San Rafael",
    "sg:classifiers":[
        {
            "category":"Professional",
            "type":"Services"
        }
    ],
    "sg:phone":"+1 415 482 8357",
    "sg:postcode":"94901",
    "sg:province":"CA",
    "wof:name":"Poena",
    "wof:placetype":"venue"
},
  "geometry": {"coordinates":[-122.515838,37.986622],"type":"Point"}
}