{
  "type": "Feature",
  "properties": {
    "iso:country":"US",
    "sg:address":"27769 Lagoon Dr",
    "sg:city":"Buttonwillow",
    "sg:classifiers":[
        {
            "category":"Autos & Motor Vehicles",
            "subcategory":"Fuel & Gas Station",
            "type":"Retail Goods"
        }
    ],
    "sg:phone":"+1 661 764 5266",
    "sg:postcode":"93206",
    "sg:province":"CA",
    "sg:tags":[
        "oil"
    ],
    "sg:website":"www.tatravelcenters.com",
    "wof:name":"Travel Centers Of America",
    "wof:placetype":"venue"
},
  "geometry": {"coordinates":[-119.39755,35.40122],"type":"Point"}
}