{
  "type": "Feature",
  "properties": {
    "addr:full":"1051 N Ramona Dr Perris CA 92571",
    "addr:housenumber":"1051",
    "addr:postcode":"92571",
    "addr:street":"N Ramona Dr",
    "iso:country":"US",
    "sg:address":"1051 N Ramona Dr",
    "sg:city":"Perris",
    "sg:classifiers":[
        {
            "category":"Building & Trades",
            "subcategory":"Construction",
            "type":"Services"
        }
    ],
    "sg:phone":"+1 909 227 3832",
    "sg:postcode":"92571",
    "sg:province":"CA",
    "sg:tags":[
        "concrete",
        "contractor"
    ],
    "wof:name":"Sevi Concrete",
    "wof:placetype":"venue"
},
  "geometry": {"coordinates":[-117.22273800000001,33.796486],"type":"Point"}
}