{
  "type": "Feature",
  "properties": {
    "addr:full":"22014 State Hwy 33 Crows Landing CA 95313",
    "addr:housenumber":"22014",
    "addr:postcode":"95313",
    "addr:street":"State Hwy 33",
    "iso:country":"US",
    "sg:address":"22014 State Hwy 33",
    "sg:city":"Crows Landing",
    "sg:classifiers":[
        {
            "category":"Freight",
            "type":"Transportation"
        }
    ],
    "sg:phone":"+1 209 837 4776",
    "sg:postcode":"95313",
    "sg:province":"CA",
    "sg:tags":[
        "bean",
        "elevator"
    ],
    "wof:name":"Kbc Trading and Processing",
    "wof:placetype":"venue"
},
  "geometry": {"coordinates":[-121.07120500000001,37.392772],"type":"Point"}
}