{
  "type": "Feature",
  "properties": {
    "iso:country":"US",
    "sg:address":"61 Via Gatillo",
    "sg:city":"Rancho Santa Margarita",
    "sg:classifiers":[
        {
            "category":"Shopping",
            "subcategory":"Gifts & Souvenirs",
            "type":"Retail Goods"
        }
    ],
    "sg:phone":"+1 949 589 7225",
    "sg:postcode":"92688",
    "sg:province":"CA",
    "wof:name":"Sanrio Suprises",
    "wof:placetype":"venue"
},
  "geometry": {"coordinates":[-117.617989,33.655829],"type":"Point"}
}