{
  "type": "Feature",
  "properties": {
    "addr:full":"1413 Van Dyke Ave San Francisco CA 94124",
    "addr:housenumber":"1413",
    "addr:postcode":"94124",
    "addr:street":"Van Dyke Ave",
    "iso:country":"US",
    "sg:address":"1413 Van Dyke Ave",
    "sg:city":"San Francisco",
    "sg:classifiers":[
        {
            "category":"Manufacturing",
            "subcategory":"Chemicals & Compounds",
            "type":"Manufacturing & Wholesale Goods"
        }
    ],
    "sg:phone":"+1 415 822 9123",
    "sg:postcode":"94124",
    "sg:province":"CA",
    "sg:tags":[
        "preparation",
        "mfg"
    ],
    "wof:name":"Rangsons Inc",
    "wof:placetype":"venue"
},
  "geometry": {"coordinates":[-122.39040900000001,37.727909],"type":"Point"}
}