{
  "type": "Feature",
  "properties": {
    "addr:full":"757 N Euclid St Anaheim CA 92801",
    "addr:housenumber":"757",
    "addr:postcode":"92801",
    "addr:street":"N Euclid St",
    "iso:country":"US",
    "sg:address":"757 N Euclid St",
    "sg:city":"Anaheim",
    "sg:classifiers":[
        {
            "category":"Banks & Credit Unions",
            "subcategory":"Bank",
            "type":"Services"
        }
    ],
    "sg:phone":"+1 714 772 1545",
    "sg:postcode":"92801",
    "sg:province":"CA",
    "sg:tags":[
        "cashing",
        "check"
    ],
    "wof:name":"Advance America",
    "wof:placetype":"venue"
},
  "geometry": {"coordinates":[-117.94168999999999,33.842277],"type":"Point"}
}