{
  "type": "Feature",
  "properties": {
    "addr:full":"808 W Highland Ave San Bernardino CA 92405",
    "addr:housenumber":"808",
    "addr:postcode":"92405",
    "addr:street":"W Highland Ave",
    "iso:country":"US",
    "sg:address":"808 W Highland Ave",
    "sg:city":"San Bernardino",
    "sg:classifiers":[
        {
            "category":"Restaurant",
            "type":"Food & Drink"
        }
    ],
    "sg:menulink":"http://www.allmenus.com/ca/san-bernardino/198191-kfc---kentucky-fried-chicken/menu/",
    "sg:phone":"+1 909 883 9411",
    "sg:postcode":"92405",
    "sg:province":"CA",
    "sg:tags":[
        "american",
        "chicken"
    ],
    "wof:name":"KFC - Kentucky Fried Chicken",
    "wof:placetype":"venue"
},
  "geometry": {"coordinates":[-117.30127,34.136319],"type":"Point"}
}