{
  "type": "Feature",
  "properties": {
    "addr:full":"260 Santa Anna Ct Sunnyvale CA 94085",
    "addr:housenumber":"260",
    "addr:postcode":"94085",
    "addr:street":"Santa Anna Ct",
    "iso:country":"US",
    "sg:address":"260 Santa Anna Ct",
    "sg:city":"Sunnyvale",
    "sg:classifiers":[
        {
            "category":"Manufacturing",
            "subcategory":"Electronics",
            "type":"Manufacturing & Wholesale Goods"
        }
    ],
    "sg:phone":"+1 408 734 9640",
    "sg:postcode":"94085",
    "sg:province":"CA",
    "sg:tags":[
        "equipment",
        "meteorological",
        "mfg",
        "hydrological"
    ],
    "wof:name":"Handar Business Unit",
    "wof:placetype":"venue"
},
  "geometry": {"coordinates":[-122.01048299999999,37.379558],"type":"Point"}
}