{
  "type": "Feature",
  "properties": {
    "iso:country":"US",
    "sg:address":"4233 Peralta Blvd",
    "sg:city":"Fremont",
    "sg:classifiers":[
        {
            "category":"Retail",
            "subcategory":"Auto Repair",
            "type":"Services"
        }
    ],
    "sg:phone":"+1 510 793 3131",
    "sg:postcode":"94536",
    "sg:province":"CA",
    "sg:tags":[
        "repairing",
        "automobile"
    ],
    "wof:name":"A C European",
    "wof:placetype":"venue"
},
  "geometry": {"coordinates":[-122.00888999999999,37.555748],"type":"Point"}
}