{
  "type": "Feature",
  "properties": {
    "addr:full":"2116 Dale St San Diego CA 92104",
    "addr:housenumber":"2116",
    "addr:postcode":"92104",
    "addr:street":"Dale St",
    "iso:country":"US",
    "sg:address":"2116 Dale St",
    "sg:city":"San Diego",
    "sg:classifiers":[
        {
            "category":"Building & Trades",
            "subcategory":"Electrical",
            "type":"Services"
        }
    ],
    "sg:phone":"+1 619 233 1117",
    "sg:postcode":"92104",
    "sg:province":"CA",
    "sg:tags":[
        "electrical",
        "electric",
        "contractor"
    ],
    "wof:name":"Gecko Electric",
    "wof:placetype":"venue"
},
  "geometry": {"coordinates":[-117.131154,32.728442],"type":"Point"}
}