{
  "type": "Feature",
  "properties": {
    "iso:country":"US",
    "sg:address":"24902 Moulton Pkwy Ste 110",
    "sg:city":"Laguna Woods",
    "sg:classifiers":[
        {
            "category":"Shopping",
            "subcategory":"Pharmacy",
            "type":"Retail Goods"
        }
    ],
    "sg:phone":"+1 949 215 8448",
    "sg:postcode":"92637",
    "sg:province":"CA",
    "sg:tags":[
        "drugstore"
    ],
    "sg:website":"www.lagunacompounding.com",
    "wof:name":"Laguna Compounding Pharmacy",
    "wof:placetype":"venue"
},
  "geometry": {"coordinates":[-117.71665900000001,33.601153],"type":"Point"}
}