{
  "type": "Feature",
  "properties": {
    "iso:country":"US",
    "sg:address":"7451 Warner Ave Ste 6",
    "sg:city":"Huntington Beach",
    "sg:classifiers":[
        {
            "category":"Restaurant",
            "type":"Food & Drink"
        }
    ],
    "sg:phone":"+1 714 847 5015",
    "sg:postcode":"92647",
    "sg:province":"CA",
    "sg:tags":[
        "mexican"
    ],
    "sg:website":"tkila.net/",
    "wof:name":"T'kila Mexican Food",
    "wof:placetype":"venue"
},
  "geometry": {"coordinates":[-117.998524,33.716149],"type":"Point"}
}