{
  "type": "Feature",
  "properties": {
    "addr:full":"10444 Twin Cities Rd Galt CA 95632",
    "addr:housenumber":"10444",
    "addr:postcode":"95632",
    "addr:street":"Twin Cities Rd",
    "iso:country":"US",
    "sg:address":"10444 Twin Cities Rd",
    "sg:city":"Galt",
    "sg:classifiers":[
        {
            "category":"Building & Trades",
            "subcategory":"Electrical",
            "type":"Services"
        },
        {
            "category":"Wholesale",
            "subcategory":"Electrical",
            "type":"Manufacturing & Wholesale Goods"
        }
    ],
    "sg:phone":"+1 209 744 9731",
    "sg:postcode":"95632",
    "sg:province":"CA",
    "sg:tags":[
        "fire",
        "alarm",
        "system",
        "contractor"
    ],
    "wof:name":"Guttridge Taylor LLC",
    "wof:placetype":"venue"
},
  "geometry": {"coordinates":[-121.303117,38.291031],"type":"Point"}
}