{
  "type": "Feature",
  "properties": {
    "addr:full":"870 Blossom Hill Rd San Jose CA 95123",
    "addr:housenumber":"870",
    "addr:postcode":"95123",
    "addr:street":"Blossom Hill Rd",
    "iso:country":"US",
    "sg:address":"870 Blossom Hill Rd",
    "sg:city":"San Jose",
    "sg:classifiers":[
        {
            "category":"Professional",
            "subcategory":"Accounting & Tax Preparation",
            "type":"Services"
        }
    ],
    "sg:phone":"+1 408 281 2269",
    "sg:postcode":"95123",
    "sg:province":"CA",
    "sg:tags":[
        "return",
        "filing"
    ],
    "wof:name":"H & R Block Tax Svc",
    "wof:placetype":"venue"
},
  "geometry": {"coordinates":[-121.85637699999999,37.250398],"type":"Point"}
}