{
  "type": "Feature",
  "properties": {
    "iso:country":"US",
    "sg:address":"51 Joaquin Ct",
    "sg:city":"Danville",
    "sg:classifiers":[
        {
            "category":"Professional",
            "subcategory":"Art Services",
            "type":"Services"
        }
    ],
    "sg:phone":"+1 925 837 5150",
    "sg:postcode":"94526",
    "sg:province":"CA",
    "sg:tags":[
        "commercial",
        "design",
        "publishing"
    ],
    "wof:name":"Gg Designs",
    "wof:placetype":"venue"
},
  "geometry": {"coordinates":[-121.972667,37.787452],"type":"Point"}
}