{
  "type": "Feature",
  "properties": {
    "addr:full":"2377 Gold Meadow Way Rancho Cordova CA 95670",
    "addr:housenumber":"2377",
    "addr:postcode":"95670",
    "addr:street":"Gold Meadow Way",
    "iso:country":"US",
    "sg:address":"2377 Gold Meadow Way",
    "sg:city":"Rancho Cordova",
    "sg:classifiers":[
        {
            "category":"Insurance",
            "subcategory":"Life Insurance",
            "type":"Services"
        }
    ],
    "sg:phone":"+1 916 631 1910",
    "sg:postcode":"95670",
    "sg:province":"CA",
    "sg:tags":[
        "carrier"
    ],
    "wof:name":"Reliastar Life Insurance Co",
    "wof:placetype":"venue"
},
  "geometry": {"coordinates":[-121.261115,38.622],"type":"Point"}
}