{
  "type": "Feature",
  "properties": {
    "iso:country":"US",
    "sg:address":"400 Newport Center Dr",
    "sg:city":"Newport Beach",
    "sg:classifiers":[
        {
            "category":"Health Services",
            "subcategory":"Doctor",
            "type":"Services"
        }
    ],
    "sg:phone":"+1 949 640 6699",
    "sg:postcode":"92660",
    "sg:province":"CA",
    "sg:tags":[
        "physician",
        "surgeon"
    ],
    "wof:name":"Barry F Chaitin MD",
    "wof:placetype":"venue"
},
  "geometry": {"coordinates":[-117.872483,33.614758],"type":"Point"}
}