{
  "type": "Feature",
  "properties": {
    "iso:country":"US",
    "sg:address":"275 Battery St",
    "sg:city":"San Francisco",
    "sg:classifiers":[
        {
            "category":"Professional",
            "subcategory":"Lawyer & Legal Services",
            "type":"Services"
        }
    ],
    "sg:phone":"+1 415 875 2300",
    "sg:postcode":"94111",
    "sg:province":"CA",
    "sg:tags":[
        "attorney"
    ],
    "sg:website":"www.fenwick.com",
    "wof:name":"Fenwick & West",
    "wof:placetype":"venue"
},
  "geometry": {"coordinates":[-122.400176,37.793837],"type":"Point"}
}