{
  "type": "Feature",
  "properties": {
    "iso:country":"US",
    "sg:address":"485 S Robertson Blvd",
    "sg:city":"Beverly Hills",
    "sg:classifiers":[
        {
            "category":"Communications",
            "subcategory":"Film & Video Production",
            "type":"Services"
        }
    ],
    "sg:phone":"+1 323 665 8902",
    "sg:postcode":"90211",
    "sg:province":"CA",
    "sg:tags":[
        "taping"
    ],
    "wof:name":"Anamorph Films Inc",
    "wof:placetype":"venue"
},
  "geometry": {"coordinates":[-118.383534,34.062937],"type":"Point"}
}