{
  "type": "Feature",
  "properties": {
    "addr:full":"1400 N Euclid St La Habra CA 90631",
    "addr:housenumber":"1400",
    "addr:postcode":"90631",
    "addr:street":"N Euclid St",
    "iso:country":"US",
    "sg:address":"1400 N Euclid St",
    "sg:city":"La Habra",
    "sg:classifiers":[
        {
            "category":"Communications",
            "subcategory":"Film & Video Production",
            "type":"Services"
        }
    ],
    "sg:phone":"+1 714 446 1165",
    "sg:postcode":"90631",
    "sg:province":"CA",
    "sg:tags":[
        "audio"
    ],
    "wof:name":"Acacia Productions",
    "wof:placetype":"venue"
},
  "geometry": {"coordinates":[-117.945627,33.944898],"type":"Point"}
}