{
  "type": "Feature",
  "properties": {
    "addr:full":"3945 Missouri Flat Rd Placerville CA 95667",
    "addr:housenumber":"3945",
    "addr:postcode":"95667",
    "addr:street":"Missouri Flat Rd",
    "iso:country":"US",
    "sg:address":"3945 Missouri Flat Rd",
    "sg:city":"Placerville",
    "sg:classifiers":[
        {
            "category":"Restaurant",
            "type":"Food & Drink"
        }
    ],
    "sg:menulink":"http://www.allmenus.com/ca/north-el-dorado/178069-jack-in-the-box/menu/",
    "sg:phone":"+1 530 622 7485",
    "sg:postcode":"95667",
    "sg:province":"CA",
    "sg:tags":[
        "burger",
        "american"
    ],
    "wof:name":"Jack in the Box",
    "wof:placetype":"venue"
},
  "geometry": {"coordinates":[-120.84177800000001,38.713013],"type":"Point"}
}