{
  "type": "Feature",
  "properties": {
    "iso:country":"US",
    "sg:address":"1815 Hawthorne Blvd",
    "sg:city":"Redondo Beach",
    "sg:classifiers":[
        {
            "category":"Cinema",
            "subcategory":"Movie Rental",
            "type":"Entertainment"
        }
    ],
    "sg:phone":"+1 310 542 5653",
    "sg:postcode":"90278",
    "sg:province":"CA",
    "sg:tags":[
        "game",
        "video"
    ],
    "sg:website":"www.gamestop.com",
    "wof:name":"GameStop",
    "wof:placetype":"venue"
},
  "geometry": {"coordinates":[-118.35285500000001,33.870689],"type":"Point"}
}