{
  "type": "Feature",
  "properties": {
    "addr:full":"617 S Olive St Los Angeles CA 90014",
    "addr:housenumber":"617",
    "addr:postcode":"90014",
    "addr:street":"S Olive St",
    "iso:country":"US",
    "sg:address":"617 S Olive St",
    "sg:city":"Los Angeles",
    "sg:classifiers":[
        {
            "category":"Professional",
            "subcategory":"Business Services",
            "type":"Services"
        }
    ],
    "sg:phone":"+1 213 627 3710",
    "sg:postcode":"90014",
    "sg:province":"CA",
    "sg:tags":[
        "appraiser"
    ],
    "wof:name":"American Gemologica Appraisals",
    "wof:placetype":"venue"
},
  "geometry": {"coordinates":[-118.25539999999999,34.046881],"type":"Point"}
}