{
  "type": "Feature",
  "properties": {
    "iso:country":"US",
    "sg:address":"850 S Broadway",
    "sg:city":"Los Angeles",
    "sg:classifiers":[
        {
            "category":"Shopping",
            "subcategory":"Clothing, Apparel, & Fashions",
            "type":"Retail Goods"
        }
    ],
    "sg:phone":"+1 213 622 8067",
    "sg:postcode":"90014",
    "sg:province":"CA",
    "wof:name":"Soya USA",
    "wof:placetype":"venue"
},
  "geometry": {"coordinates":[-118.255429,34.04302],"type":"Point"}
}