{
  "type": "Feature",
  "properties": {
    "addr:full":"940 S Placentia Ave Placentia CA 92870",
    "addr:housenumber":"940",
    "addr:postcode":"ca 92870",
    "addr:street":"S Placentia Ave",
    "iso:country":"US",
    "sg:address":"940 S Placentia Ave",
    "sg:city":"Placentia",
    "sg:classifiers":[
        {
            "category":"Wholesale",
            "subcategory":"Home Furnishings",
            "type":"Manufacturing & Wholesale Goods"
        }
    ],
    "sg:phone":"+1 714 630 2770",
    "sg:postcode":"92870",
    "sg:province":"CA",
    "wof:name":"California Precast Surrounds",
    "wof:placetype":"venue"
},
  "geometry": {"coordinates":[-117.883107,33.859603],"type":"Point"}
}