{
  "type": "Feature",
  "properties": {
    "iso:country":"US",
    "sg:address":"6955 Foothill Blvd # 100",
    "sg:city":"Oakland",
    "sg:classifiers":[
        {
            "category":"Government",
            "subcategory":"Office",
            "type":"Public Place"
        }
    ],
    "sg:phone":"+1 510 577 7067",
    "sg:postcode":"94605",
    "sg:province":"CA",
    "sg:tags":[
        "government-united",
        "state"
    ],
    "sg:website":"http://www.bayareaeastshore.com",
    "wof:name":"Social Services Dept",
    "wof:placetype":"venue"
},
  "geometry": {"coordinates":[-122.17552499999999,37.769559],"type":"Point"}
}