{
  "type": "Feature",
  "properties": {
    "addr:full":"26011 Holland Rd Sun City CA 92584",
    "addr:housenumber":"26011",
    "addr:postcode":"92584",
    "addr:street":"Holland Rd",
    "iso:country":"US",
    "sg:address":"26011 Holland Rd",
    "sg:city":"Sun City",
    "sg:classifiers":[
        {
            "category":"Retail",
            "subcategory":"Auto Repair",
            "type":"Services"
        }
    ],
    "sg:phone":"+1 951 679 5741",
    "sg:postcode":"92584",
    "sg:province":"CA",
    "sg:tags":[
        "body",
        "automobile",
        "painting"
    ],
    "wof:name":"Middleton's Body Shop",
    "wof:placetype":"venue"
},
  "geometry": {"coordinates":[-117.20516600000001,33.671469],"type":"Point"}
}