{
  "type": "Feature",
  "properties": {
    "iso:country":"US",
    "sg:address":"515 N Sepulveda Boulevard",
    "sg:city":"Manhattan Beach",
    "sg:classifiers":[
        {
            "category":"Health Services",
            "subcategory":"Chiropractor",
            "type":"Services"
        }
    ],
    "sg:phone":"+1 310 372 2687",
    "sg:postcode":"90266",
    "sg:province":"CA",
    "wof:name":"Leuschen Faith Dr Chiropractc Doctrs",
    "wof:placetype":"venue"
},
  "geometry": {"coordinates":[-118.396146,33.882228],"type":"Point"}
}