{
  "type": "Feature",
  "properties": {
    "iso:country":"US",
    "sg:address":"1296 E Gibson Rd",
    "sg:city":"Woodland",
    "sg:classifiers":[
        {
            "category":"Building & Trades",
            "subcategory":"Construction",
            "type":"Services"
        }
    ],
    "sg:phone":"+1 530 662 4949",
    "sg:postcode":"95776",
    "sg:province":"CA",
    "sg:tags":[
        "grouting",
        "contractor"
    ],
    "wof:name":"Grout Pro",
    "wof:placetype":"venue"
},
  "geometry": {"coordinates":[-121.765343,38.662793],"type":"Point"}
}