{
  "type": "Feature",
  "properties": {
    "iso:country":"US",
    "sg:address":"200 N Maie Ave",
    "sg:city":"Compton",
    "sg:classifiers":[
        {
            "category":"Local Transit",
            "type":"Transportation"
        }
    ],
    "sg:phone":"+1 310 808 2273",
    "sg:postcode":"90220",
    "sg:province":"CA",
    "sg:tags":[
        "public"
    ],
    "wof:name":"L A Dot Bus Pass",
    "wof:placetype":"venue"
},
  "geometry": {"coordinates":[-118.244128,33.896354],"type":"Point"}
}