{
  "type": "Feature",
  "properties": {
    "iso:country":"US",
    "sg:address":"135 Aviation Way",
    "sg:city":"Watsonville",
    "sg:classifiers":[
        {
            "category":"Wholesale",
            "subcategory":"Machinery & Supplies",
            "type":"Manufacturing & Wholesale Goods"
        }
    ],
    "sg:phone":"+1 831 429 8665",
    "sg:postcode":"95076",
    "sg:province":"CA",
    "sg:tags":[
        "tool"
    ],
    "wof:name":"K & H Sales",
    "wof:placetype":"venue"
},
  "geometry": {"coordinates":[-121.789536,36.933177],"type":"Point"}
}