{
  "type": "Feature",
  "properties": {
    "iso:country":"US",
    "sg:address":"1024 Simon Dr",
    "sg:city":"Placerville",
    "sg:classifiers":[
        {
            "category":"Professional",
            "subcategory":"Management & Consulting",
            "type":"Services"
        }
    ],
    "sg:phone":"+1 530 344 1982",
    "sg:postcode":"95667",
    "sg:province":"CA",
    "sg:tags":[
        "consultant"
    ],
    "wof:name":"JVB Consulting",
    "wof:placetype":"venue"
},
  "geometry": {"coordinates":[-120.795706,38.730564],"type":"Point"}
}