{
  "type": "Feature",
  "properties": {
    "addr:full":"15016 S Avalon Blvd Gardena CA 90248",
    "addr:housenumber":"15016",
    "addr:postcode":"90248",
    "addr:street":"S Avalon Blvd",
    "iso:country":"US",
    "sg:address":"15016 S Avalon Blvd",
    "sg:city":"Gardena",
    "sg:classifiers":[
        {
            "category":"Banks & Credit Unions",
            "subcategory":"Investment Brokerage",
            "type":"Services"
        }
    ],
    "sg:phone":"+1 310 327 0110",
    "sg:postcode":"90248",
    "sg:province":"CA",
    "sg:tags":[
        "merger",
        "acquisition"
    ],
    "wof:name":"R W Acquisition Corp",
    "wof:placetype":"venue"
},
  "geometry": {"coordinates":[-118.265202,33.901415],"type":"Point"}
}