{
  "type": "Feature",
  "properties": {
    "iso:country":"US",
    "sg:address":"511 E Gutierrez St",
    "sg:city":"Santa Barbara",
    "sg:classifiers":[
        {
            "category":"Building & Trades",
            "subcategory":"Construction",
            "type":"Services"
        }
    ],
    "sg:phone":"+1 805 965 0007",
    "sg:postcode":"93103",
    "sg:province":"CA",
    "sg:tags":[
        "concrete",
        "contractor"
    ],
    "wof:name":"Trademark Concrete Systems",
    "wof:placetype":"venue"
},
  "geometry": {"coordinates":[-119.687577,34.422144],"type":"Point"}
}