{
  "type": "Feature",
  "properties": {
    "iso:country":"US",
    "sg:address":"135 Kipling Dr",
    "sg:city":"Mill Valley",
    "sg:classifiers":[
        {
            "category":"Manufacturing",
            "subcategory":"Textiles",
            "type":"Manufacturing & Wholesale Goods"
        }
    ],
    "sg:phone":"+1 415 388 6980",
    "sg:postcode":"94941",
    "sg:province":"CA",
    "sg:tags":[
        "knit",
        "mills",
        "outerwear"
    ],
    "wof:name":"Nanknits",
    "wof:placetype":"venue"
},
  "geometry": {"coordinates":[-122.522363,37.898843],"type":"Point"}
}