{
  "type": "Feature",
  "properties": {
    "addr:full":"1451 MacKinnon Ave Cardiff by the Sea CA 92007",
    "addr:housenumber":"1451",
    "addr:postcode":"92007",
    "addr:street":"Mackinnon Ave",
    "iso:country":"US",
    "sg:address":"1451 MacKinnon Ave",
    "sg:city":"Cardiff by the Sea",
    "sg:classifiers":[
        {
            "category":"Education",
            "subcategory":"School",
            "type":"Public Place"
        }
    ],
    "sg:phone":"+1 760 632 9447",
    "sg:postcode":"92007",
    "sg:province":"CA",
    "wof:name":"Classic Youth Theatre Inc. Non Profit",
    "wof:placetype":"venue"
},
  "geometry": {"coordinates":[-117.276804,33.109071],"type":"Point"}
}