{
  "type": "Feature",
  "properties": {
    "addr:full":"11039 Acacia Pkwy Garden Grove CA 92840",
    "addr:housenumber":"11039",
    "addr:postcode":"92840",
    "addr:street":"Acacia Pkwy",
    "iso:country":"US",
    "sg:address":"11039 Acacia Pkwy",
    "sg:city":"Garden Grove",
    "sg:classifiers":[
        {
            "category":"Health Services",
            "subcategory":"Doctor",
            "type":"Services"
        }
    ],
    "sg:phone":"+1 714 534 3366",
    "sg:postcode":"92840",
    "sg:province":"CA",
    "wof:name":"Pang Jason MD",
    "wof:placetype":"venue"
},
  "geometry": {"coordinates":[-117.940273,33.776173],"type":"Point"}
}