{
  "type": "Feature",
  "properties": {
    "addr:full":"7112 de Celis Pl Van Nuys CA 91406",
    "addr:housenumber":"7112",
    "addr:postcode":"91406",
    "addr:street":"De Celis Pl",
    "iso:country":"US",
    "sg:address":"7112 de Celis Pl",
    "sg:city":"Van Nuys",
    "sg:classifiers":[
        {
            "category":"Building & Trades",
            "subcategory":"Electrical",
            "type":"Services"
        }
    ],
    "sg:phone":"+1 818 785 8810",
    "sg:postcode":"91406",
    "sg:province":"CA",
    "sg:tags":[
        "electric",
        "contractor"
    ],
    "wof:name":"PMD Electric",
    "wof:placetype":"venue"
},
  "geometry": {"coordinates":[-118.4945,34.200834],"type":"Point"}
}