{
  "type": "Feature",
  "properties": {
    "addr:full":"311 Mesa Dr Costa Mesa CA 92627",
    "addr:housenumber":"311",
    "addr:postcode":"92627",
    "addr:street":"Mesa Dr",
    "iso:country":"US",
    "sg:address":"311 Mesa Dr",
    "sg:city":"Costa Mesa",
    "sg:classifiers":[
        {
            "category":"Banks & Credit Unions",
            "subcategory":"Investment Brokerage",
            "type":"Services"
        }
    ],
    "sg:phone":"+1 949 515 4404",
    "sg:postcode":"92627",
    "sg:province":"CA",
    "sg:tags":[
        "advisory",
        "financial"
    ],
    "wof:name":"First Class Financial",
    "wof:placetype":"venue"
},
  "geometry": {"coordinates":[-117.886447,33.660164],"type":"Point"}
}