{
  "type": "Feature",
  "properties": {
    "iso:country":"US",
    "sg:address":"4550 Barranca Parkway",
    "sg:city":"Irvine",
    "sg:classifiers":[
        {
            "category":"Retail",
            "subcategory":"Auto Repair",
            "type":"Services"
        }
    ],
    "sg:phone":"+1 949 857 8220",
    "sg:postcode":"92604",
    "sg:province":"CA",
    "sg:tags":[
        "detailing"
    ],
    "wof:name":"Beacon Bay Auto Washes",
    "wof:placetype":"venue"
},
  "geometry": {"coordinates":[-117.80023199999999,33.678681],"type":"Point"}
}