{
  "type": "Feature",
  "properties": {
    "addr:full":"417 W Walnut St Santa Ana CA 92701",
    "addr:housenumber":"417",
    "addr:postcode":"92701",
    "addr:street":"W Walnut St",
    "iso:country":"US",
    "sg:address":"417 W Walnut St",
    "sg:city":"Santa Ana",
    "sg:classifiers":[
        {
            "category":"Education",
            "subcategory":"School",
            "type":"Public Place"
        }
    ],
    "sg:phone":"+1 714 953 3800",
    "sg:postcode":"92701",
    "sg:province":"CA",
    "sg:tags":[
        "high",
        "middle",
        "elementary"
    ],
    "wof:name":"Santa Ana Unified School District",
    "wof:placetype":"venue"
},
  "geometry": {"coordinates":[-117.871106,33.74455],"type":"Point"}
}