{
  "type": "Feature",
  "properties": {
    "iso:country":"US",
    "sg:address":"1831 Industrial Way",
    "sg:city":"Sanger",
    "sg:classifiers":[
        {
            "category":"Manufacturing",
            "subcategory":"Printing",
            "type":"Manufacturing & Wholesale Goods"
        }
    ],
    "sg:phone":"+1 559 876 2170",
    "sg:postcode":"93657",
    "sg:province":"CA",
    "sg:tags":[
        "publisher"
    ],
    "sg:website":"www.quilldriverbooks.com",
    "wof:name":"Quill Driver Books/Word Dancer",
    "wof:placetype":"venue"
},
  "geometry": {"coordinates":[-119.548603,36.691432],"type":"Point"}
}