{
  "type": "Feature",
  "properties": {
    "addr:full":"205 S Citrus Ave Covina CA 91723",
    "addr:housenumber":"205",
    "addr:postcode":"91723",
    "addr:street":"S Citrus Ave",
    "iso:country":"US",
    "sg:address":"205 S Citrus Ave",
    "sg:city":"Covina",
    "sg:classifiers":[
        {
            "category":"Personal",
            "subcategory":"Beauty Salon",
            "type":"Services"
        }
    ],
    "sg:phone":"+1 626 859 2200",
    "sg:postcode":"91723",
    "sg:province":"CA",
    "sg:tags":[
        "hair",
        "stylist"
    ],
    "wof:name":"A'la Bella Hair Studio",
    "wof:placetype":"venue"
},
  "geometry": {"coordinates":[-117.890129,34.085023],"type":"Point"}
}