{
  "type": "Feature",
  "properties": {
    "addr:full":"720 Cherokee Ln Lodi CA 95240",
    "addr:housenumber":"720",
    "addr:postcode":"95240",
    "addr:street":"Cherokee Ln",
    "iso:country":"US",
    "sg:address":"720 Cherokee Ln",
    "sg:city":"Lodi",
    "sg:classifiers":[
        {
            "category":"Banks & Credit Unions",
            "subcategory":"Bank",
            "type":"Services"
        }
    ],
    "sg:phone":"+1 209 333 3320",
    "sg:postcode":"95240",
    "sg:province":"CA",
    "sg:tags":[
        "cashing",
        "check"
    ],
    "wof:name":"Check Into Cash",
    "wof:placetype":"venue"
},
  "geometry": {"coordinates":[-121.26036000000001,38.126712],"type":"Point"}
}