{
  "type": "Feature",
  "properties": {
    "iso:country":"US",
    "sg:address":"17218 Comconex Rd",
    "sg:city":"Manteca",
    "sg:classifiers":[
        {
            "category":"Organizations",
            "subcategory":"Religious Organization",
            "type":"Services"
        }
    ],
    "sg:phone":"+1 209 239 5711",
    "sg:postcode":"95336",
    "sg:province":"CA",
    "sg:tags":[
        "church"
    ],
    "sg:website":"www.newhope4square.org",
    "wof:name":"New Hope Church",
    "wof:placetype":"venue"
},
  "geometry": {"coordinates":[-121.168131,37.797676],"type":"Point"}
}