{
  "type": "Feature",
  "properties": {
    "iso:country":"US",
    "sg:address":"1680 N Main St",
    "sg:city":"Orange",
    "sg:classifiers":[
        {
            "category":"Manufacturing",
            "subcategory":"Rubber & Plastics",
            "type":"Manufacturing & Wholesale Goods"
        },
        {
            "category":"Professional",
            "subcategory":"Testing Lab",
            "type":"Services"
        },
        {
            "category":"Professional",
            "subcategory":"Business Services",
            "type":"Services"
        },
        {
            "category":"Shopping",
            "type":"Retail Goods"
        }
    ],
    "sg:phone":"+1 714 283 2032",
    "sg:postcode":"92867",
    "sg:province":"CA",
    "sg:tags":[
        "polymer",
        "coach",
        "plastics-fabricating",
        "laboratories-plastics",
        "consultant",
        "laboratory",
        "finishing",
        "decorating",
        "merchandise"
    ],
    "wof:name":"Vista Plastic Products Inc",
    "wof:placetype":"venue"
},
  "geometry": {"coordinates":[-117.86739300000001,33.81525],"type":"Point"}
}