{
  "type": "Feature",
  "properties": {
    "addr:full":"8650 Ave Costa Blanca San Diego CA 92154",
    "addr:housenumber":"8650",
    "addr:postcode":"92154",
    "addr:street":"Ave Costa",
    "iso:country":"US",
    "sg:address":"8650 Ave Costa Blanca",
    "sg:city":"San Diego",
    "sg:classifiers":[
        {
            "category":"Food & Beverages",
            "subcategory":"Bakery",
            "type":"Retail Goods"
        }
    ],
    "sg:phone":"+1 619 250 5960",
    "sg:postcode":"92154",
    "sg:province":"CA",
    "wof:name":"Johanns Austrian Bakery",
    "wof:placetype":"venue"
},
  "geometry": {"coordinates":[-116.960424,32.557743],"type":"Point"}
}