{
  "type": "Feature",
  "properties": {
    "iso:country":"US",
    "sg:address":"910 Morro Bay Blvd",
    "sg:city":"Morro Bay",
    "sg:classifiers":[
        {
            "category":"Retail",
            "subcategory":"Auto Repair",
            "type":"Services"
        }
    ],
    "sg:phone":"+1 805 772 6002",
    "sg:postcode":"93442",
    "sg:province":"CA",
    "sg:tags":[
        "automotive",
        "general"
    ],
    "wof:name":"Central Coast Auto Center",
    "wof:placetype":"venue"
},
  "geometry": {"coordinates":[-120.841131,35.366223],"type":"Point"}
}