{
  "type": "Feature",
  "properties": {
    "addr:full":"1665 E 4th St Ste 210 Santa Ana CA 92701",
    "addr:housenumber":"1665",
    "addr:postcode":"92701",
    "addr:street":"E 4Th St Ste 210",
    "iso:country":"US",
    "sg:address":"1665 E 4th St Ste 210",
    "sg:city":"Santa Ana",
    "sg:classifiers":[
        {
            "category":"Real Estate",
            "subcategory":"Real Estate Operator",
            "type":"Services"
        }
    ],
    "sg:phone":"+1 714 835 0406",
    "sg:postcode":"92701",
    "sg:province":"CA",
    "sg:tags":[
        "apartment"
    ],
    "wof:name":"Civic Center Barrio Housing",
    "wof:placetype":"venue"
},
  "geometry": {"coordinates":[-117.845001,33.748199],"type":"Point"}
}