{
  "type": "Feature",
  "properties": {
    "iso:country":"US",
    "sg:address":"14465 Red Hill Ave",
    "sg:city":"Tustin",
    "sg:classifiers":[
        {
            "category":"Real Estate",
            "subcategory":"Real Estate Operator",
            "type":"Services"
        }
    ],
    "sg:phone":"+1 714 832 7040",
    "sg:postcode":"92780",
    "sg:province":"CA",
    "sg:tags":[
        "building",
        "apartment"
    ],
    "wof:name":"Terrace Apartments",
    "wof:placetype":"venue"
},
  "geometry": {"coordinates":[-117.820775,33.728298],"type":"Point"}
}