{
  "type": "Feature",
  "properties": {
    "iso:country":"US",
    "sg:address":"315 Washington Blvd",
    "sg:city":"Roseville",
    "sg:classifiers":[
        {
            "category":"Arts & Performance",
            "subcategory":"Theater",
            "type":"Entertainment"
        }
    ],
    "sg:phone":"+1 916 771 8545",
    "sg:postcode":"95678",
    "sg:province":"CA",
    "sg:tags":[
        "live",
        "music"
    ],
    "wof:name":"River City DJ",
    "wof:placetype":"venue"
},
  "geometry": {"coordinates":[-121.287959,38.752776],"type":"Point"}
}