{
  "type": "Feature",
  "properties": {
    "iso:country":"US",
    "sg:address":"3134 Granville Ave",
    "sg:city":"Los Angeles",
    "sg:classifiers":[
        {
            "category":"Professional",
            "type":"Services"
        }
    ],
    "sg:phone":"+1 310 397 1160",
    "sg:postcode":"90066",
    "sg:province":"CA",
    "wof:name":"Lotte Skura",
    "wof:placetype":"venue"
},
  "geometry": {"coordinates":[-118.4392,34.020822],"type":"Point"}
}