{
  "type": "Feature",
  "properties": {
    "addr:full":"950 E Colorado Blvd Ste 201 Pasadena CA 91106",
    "addr:housenumber":"950",
    "addr:postcode":"91106",
    "addr:street":"E Colorado Blvd Ste 201",
    "iso:country":"US",
    "sg:address":"950 E Colorado Blvd Ste 201",
    "sg:city":"Pasadena",
    "sg:classifiers":[
        {
            "category":"Health Services",
            "subcategory":"Dentist",
            "type":"Services"
        }
    ],
    "sg:phone":"+1 626 431 2930",
    "sg:postcode":"91106",
    "sg:province":"CA",
    "wof:name":"US Dental",
    "wof:placetype":"venue"
},
  "geometry": {"coordinates":[-118.13099699999999,34.145901],"type":"Point"}
}