{
  "type": "Feature",
  "properties": {
    "iso:country":"US",
    "sg:address":"290 N 10th St",
    "sg:city":"Colton",
    "sg:classifiers":[
        {
            "category":"Professional",
            "subcategory":"Accounting & Tax Preparation",
            "type":"Services"
        }
    ],
    "sg:phone":"+1 909 825 8859",
    "sg:postcode":"92324",
    "sg:province":"CA",
    "sg:tags":[
        "return",
        "filing"
    ],
    "wof:name":"Jim Haberbush's Tax Svc",
    "wof:placetype":"venue"
},
  "geometry": {"coordinates":[-117.321106,34.066564],"type":"Point"}
}