{
  "type": "Feature",
  "properties": {
    "addr:full":"14500 Ventura Blvd Sherman Oaks CA 91403",
    "addr:housenumber":"14500",
    "addr:postcode":"91403",
    "addr:street":"Ventura Blvd",
    "iso:country":"US",
    "sg:address":"14500 Ventura Blvd",
    "sg:city":"Sherman Oaks",
    "sg:classifiers":[
        {
            "category":"Restaurant",
            "type":"Food & Drink"
        }
    ],
    "sg:phone":"+1 818 990 7006",
    "sg:postcode":"91403",
    "sg:province":"CA",
    "sg:tags":[
        "middle",
        "eastern"
    ],
    "sg:website":"www.thepitakitchen.com/",
    "wof:name":"Pita Kitchen",
    "wof:placetype":"venue"
},
  "geometry": {"coordinates":[-118.44899700000001,34.151001],"type":"Point"}
}