{
  "type": "Feature",
  "properties": {
    "iso:country":"US",
    "sg:address":"210 Orchard Rd",
    "sg:city":"Felton",
    "sg:classifiers":[
        {
            "category":"Building & Trades",
            "subcategory":"Construction",
            "type":"Services"
        }
    ],
    "sg:phone":"+1 831 335 3368",
    "sg:postcode":"95018",
    "sg:province":"CA",
    "sg:tags":[
        "concrete",
        "contractor"
    ],
    "wof:name":"GWD Concrete",
    "wof:placetype":"venue"
},
  "geometry": {"coordinates":[-122.07834200000001,37.044508],"type":"Point"}
}