{
  "type": "Feature",
  "properties": {
    "iso:country":"US",
    "sg:address":"20 S 37th Pl",
    "sg:city":"Long Beach",
    "sg:classifiers":[
        {
            "category":"Real Estate",
            "subcategory":"Developer",
            "type":"Services"
        }
    ],
    "sg:phone":"+1 562 434 5706",
    "sg:postcode":"90803",
    "sg:province":"CA",
    "wof:name":"C Robert Langslet & Son Inc",
    "wof:placetype":"venue"
},
  "geometry": {"coordinates":[-118.149941,33.760032],"type":"Point"}
}