{
  "type": "Feature",
  "properties": {
    "addr:full":"1768 Parkside Way Roseville CA 95747",
    "addr:housenumber":"1768",
    "addr:postcode":"95747",
    "addr:street":"Parkside Way",
    "iso:country":"US",
    "sg:address":"1768 Parkside Way",
    "sg:city":"Roseville",
    "sg:classifiers":[
        {
            "category":"Health Services",
            "subcategory":"Chiropractor",
            "type":"Services"
        }
    ],
    "sg:phone":"+1 916 408 1908",
    "sg:postcode":"95747",
    "sg:province":"CA",
    "sg:tags":[
        "chiropractic"
    ],
    "wof:name":"Sasine Chiropractic Office",
    "wof:placetype":"venue"
},
  "geometry": {"coordinates":[-121.33709899999999,38.802756],"type":"Point"}
}