{
  "type": "Feature",
  "properties": {
    "addr:full":"3333 Elm Ave Long Beach CA 90807",
    "addr:housenumber":"3333",
    "addr:postcode":"90807",
    "addr:street":"Elm Ave",
    "iso:country":"US",
    "sg:address":"3333 Elm Ave",
    "sg:city":"Long Beach",
    "sg:classifiers":[
        {
            "category":"Building & Trades",
            "subcategory":"Pest Control",
            "type":"Services"
        }
    ],
    "sg:phone":"+1 310 533 0295",
    "sg:postcode":"90807",
    "sg:province":"CA",
    "wof:name":"Exterminetics Of Southern Ca",
    "wof:placetype":"venue"
},
  "geometry": {"coordinates":[-118.18835300000001,33.818405],"type":"Point"}
}