{
  "type": "Feature",
  "properties": {
    "addr:full":"22431 Antonio Pkwy Rancho Santa Margarita CA 92688",
    "addr:housenumber":"22431",
    "addr:postcode":"92688",
    "addr:street":"Antonio Pkwy",
    "iso:country":"US",
    "sg:address":"22431 Antonio Pkwy",
    "sg:city":"Rancho Santa Margarita",
    "sg:classifiers":[
        {
            "category":"Wholesale",
            "subcategory":"Medical Equipment & Supplies",
            "type":"Manufacturing & Wholesale Goods"
        }
    ],
    "sg:phone":"+1 949 459 5364",
    "sg:postcode":"92688",
    "sg:province":"CA",
    "sg:tags":[
        "rep",
        "mfg"
    ],
    "wof:name":"Diverse Technologies",
    "wof:placetype":"venue"
},
  "geometry": {"coordinates":[-117.590664,33.636176],"type":"Point"}
}