{
  "type": "Feature",
  "properties": {
    "iso:country":"US",
    "sg:address":"17715 Country Manor Ln",
    "sg:city":"Riverside",
    "sg:classifiers":[
        {
            "category":"Real Estate",
            "subcategory":"Developer",
            "type":"Services"
        }
    ],
    "sg:phone":"+1 951 780 5318",
    "sg:postcode":"92508",
    "sg:province":"CA",
    "wof:name":"Nickum Development",
    "wof:placetype":"venue"
},
  "geometry": {"coordinates":[-117.35458,33.896228],"type":"Point"}
}