{
  "type": "Feature",
  "properties": {
    "addr:full":"Lakeshore Baptist Church 3534 Lakeshore Ave Oakland CA 94620",
    "addr:housenumber":"3534",
    "addr:postcode":"94620",
    "addr:street":"Lakeshore Ave",
    "iso:country":"US",
    "sg:address":"Lakeshore Baptist Church 3534 Lakeshore Ave",
    "sg:city":"Oakland",
    "sg:classifiers":[
        {
            "category":"Sports & Exercise",
            "subcategory":"Gym",
            "type":"Entertainment"
        }
    ],
    "sg:postcode":"94620",
    "sg:province":"CA",
    "sg:tags":[
        "yoga"
    ],
    "wof:name":"Kundalini Yoga with John Iversen",
    "wof:placetype":"venue"
},
  "geometry": {"coordinates":[-122.24126200000001,37.811999],"type":"Point"}
}