{
  "type": "Feature",
  "properties": {
    "addr:full":"256 Winston St Los Angeles CA 90013",
    "addr:housenumber":"256",
    "addr:postcode":"90013",
    "addr:street":"Winston St",
    "iso:country":"US",
    "sg:address":"256 Winston St",
    "sg:city":"Los Angeles",
    "sg:classifiers":[
        {
            "category":"Wholesale",
            "subcategory":"Toys & Hobbies",
            "type":"Manufacturing & Wholesale Goods"
        }
    ],
    "sg:phone":"+1 213 624 1353",
    "sg:postcode":"90013",
    "sg:province":"CA",
    "wof:name":"Te An",
    "wof:placetype":"venue"
},
  "geometry": {"coordinates":[-118.246385,34.045993],"type":"Point"}
}