{
  "type": "Feature",
  "properties": {
    "addr:full":"1700 California St Ste 470 San Francisco CA 94109",
    "addr:housenumber":"1700",
    "addr:postcode":"94109",
    "addr:street":"California St Ste 470",
    "iso:country":"US",
    "sg:address":"1700 California St Ste 470",
    "sg:city":"San Francisco",
    "sg:classifiers":[
        {
            "category":"Health Services",
            "subcategory":"Doctor",
            "type":"Services"
        },
        {
            "category":"Health Services",
            "subcategory":"Hospital",
            "type":"Services"
        }
    ],
    "sg:phone":"+1 415 963 4431",
    "sg:postcode":"94109",
    "sg:province":"CA",
    "sg:tags":[
        "medicine",
        "urgent",
        "internal",
        "care"
    ],
    "sg:website":"www.mydoctorsf.com/",
    "wof:name":"My Doctor Medical Group",
    "wof:placetype":"venue"
},
  "geometry": {"coordinates":[-122.42303,37.790495],"type":"Point"}
}