{
  "type": "Feature",
  "properties": {
    "addr:full":"1925 Devereaux Dr Burlingame CA 94010",
    "addr:housenumber":"1925",
    "addr:postcode":"94010",
    "addr:street":"Devereaux Dr",
    "iso:country":"US",
    "sg:address":"1925 Devereaux Dr",
    "sg:city":"Burlingame",
    "sg:classifiers":[
        {
            "category":"Building & Trades",
            "subcategory":"Landscaping Services",
            "type":"Services"
        }
    ],
    "sg:phone":"+1 650 697 2310",
    "sg:postcode":"94010",
    "sg:province":"CA",
    "sg:tags":[
        "trimming",
        "tree",
        "removal"
    ],
    "wof:name":"Stump Masters",
    "wof:placetype":"venue"
},
  "geometry": {"coordinates":[-122.378426,37.588987],"type":"Point"}
}