{
  "type": "Feature",
  "properties": {
    "addr:full":"1122 Powell St San Francisco CA 94108",
    "addr:housenumber":"1122",
    "addr:postcode":"94108",
    "addr:street":"Powell St",
    "iso:country":"US",
    "sg:address":"1122 Powell St",
    "sg:city":"San Francisco",
    "sg:classifiers":[
        {
            "category":"Professional",
            "subcategory":"Business Services",
            "type":"Services"
        }
    ],
    "sg:phone":"+1 415 399 1189",
    "sg:postcode":"94108",
    "sg:province":"CA",
    "wof:name":"Global Import & Export Trading",
    "wof:placetype":"venue"
},
  "geometry": {"coordinates":[-122.40979400000001,37.79543],"type":"Point"}
}