{
  "type": "Feature",
  "properties": {
    "addr:full":"3891 Overland Ave Culver City CA 90232",
    "addr:housenumber":"3891",
    "addr:postcode":"90232",
    "addr:street":"Overland Ave",
    "iso:country":"US",
    "sg:address":"3891 Overland Ave",
    "sg:city":"Culver City",
    "sg:classifiers":[
        {
            "category":"Food & Beverages",
            "subcategory":"Fruits & Vegetables",
            "type":"Retail Goods"
        }
    ],
    "sg:phone":"+1 310 838 2332",
    "sg:postcode":"90232",
    "sg:province":"CA",
    "sg:tags":[
        "smoothie",
        "juice",
        "bar"
    ],
    "sg:website":"www.robeks.com",
    "wof:name":"Robeks Juice",
    "wof:placetype":"venue"
},
  "geometry": {"coordinates":[-118.405998,34.0173],"type":"Point"}
}