{
  "type": "Feature",
  "properties": {
    "addr:full":"5740 Thornwood Dr Goleta CA 93117",
    "addr:housenumber":"5740",
    "addr:postcode":"93117",
    "addr:street":"Thornwood Dr",
    "iso:country":"US",
    "sg:address":"5740 Thornwood Dr",
    "sg:city":"Goleta",
    "sg:classifiers":[
        {
            "category":"Manufacturing",
            "subcategory":"Tools & Machinery",
            "type":"Manufacturing & Wholesale Goods"
        }
    ],
    "sg:phone":"+1 805 964 4757",
    "sg:postcode":"93117",
    "sg:province":"CA",
    "sg:tags":[
        "machine",
        "shop"
    ],
    "wof:name":"Acra Enterprises Inc",
    "wof:placetype":"venue"
},
  "geometry": {"coordinates":[-119.825323,34.429468],"type":"Point"}
}