{
  "type": "Feature",
  "properties": {
    "addr:full":"102 W Cabrillo Blvd Santa Barbara CA 93101",
    "addr:housenumber":"102",
    "addr:postcode":"93101",
    "addr:street":"W Cabrillo Blvd",
    "iso:country":"US",
    "sg:address":"102 W Cabrillo Blvd",
    "sg:city":"Santa Barbara",
    "sg:classifiers":[
        {
            "category":"Travel",
            "subcategory":"Hotels & Motels",
            "type":"Entertainment"
        }
    ],
    "sg:phone":"+1 805 962 9208",
    "sg:postcode":"93101",
    "sg:province":"CA",
    "wof:name":"Ala Mar Motel",
    "wof:placetype":"venue"
},
  "geometry": {"coordinates":[-119.691273,34.410587],"type":"Point"}
}