{
  "type": "Feature",
  "properties": {
    "addr:full":"8421 Auburn Blvd Citrus Heights CA 95610",
    "addr:housenumber":"8421",
    "addr:postcode":"95610",
    "addr:street":"Auburn Blvd",
    "iso:country":"US",
    "sg:address":"8421 Auburn Blvd",
    "sg:city":"Citrus Heights",
    "sg:classifiers":[
        {
            "category":"Banks & Credit Unions",
            "subcategory":"Bank",
            "type":"Services"
        }
    ],
    "sg:phone":"+1 916 735 5626",
    "sg:postcode":"95610",
    "sg:province":"CA",
    "sg:tags":[
        "loan",
        "real estate"
    ],
    "wof:name":"First Option Mortgage",
    "wof:placetype":"venue"
},
  "geometry": {"coordinates":[-121.290402,38.718419],"type":"Point"}
}