{
  "type": "Feature",
  "properties": {
    "addr:full":"806 E Haley St Santa Barbara CA 93103",
    "addr:housenumber":"806",
    "addr:postcode":"93103",
    "addr:street":"E Haley St",
    "iso:country":"US",
    "sg:address":"806 E Haley St",
    "sg:city":"Santa Barbara",
    "sg:classifiers":[
        {
            "category":"Building & Trades",
            "subcategory":"Plumbing",
            "type":"Services"
        }
    ],
    "sg:phone":"+1 805 965 9586",
    "sg:postcode":"93103",
    "sg:province":"CA",
    "sg:tags":[
        "plumbing",
        "contractor"
    ],
    "wof:name":"Lee & Sons Plumbing & Htg Inc",
    "wof:placetype":"venue"
},
  "geometry": {"coordinates":[-119.685346,34.426213],"type":"Point"}
}