{
  "type": "Feature",
  "properties": {
    "addr:full":"2025 El Camino Real Santa Clara CA 95050",
    "addr:housenumber":"2025",
    "addr:postcode":"95050",
    "addr:street":"El Camino Real",
    "iso:country":"US",
    "sg:address":"2025 El Camino Real",
    "sg:city":"Santa Clara",
    "sg:classifiers":[
        {
            "category":"Autos & Motor Vehicles",
            "subcategory":"Fuel & Gas Station",
            "type":"Retail Goods"
        }
    ],
    "sg:phone":"+1 408 247 6822",
    "sg:postcode":"95050",
    "sg:province":"CA",
    "wof:name":"Union 76",
    "wof:placetype":"venue"
},
  "geometry": {"coordinates":[-121.960244,37.352597],"type":"Point"}
}