{
  "type": "Feature",
  "properties": {
    "addr:full":"600 N Hoover St Los Angeles CA 90004",
    "addr:housenumber":"600",
    "addr:postcode":"90004",
    "addr:street":"N Hoover St",
    "iso:country":"US",
    "sg:address":"600 N Hoover St",
    "sg:city":"Los Angeles",
    "sg:classifiers":[
        {
            "category":"Travel",
            "subcategory":"Travel Agent",
            "type":"Entertainment"
        }
    ],
    "sg:phone":"+1 323 663 7582",
    "sg:postcode":"90004",
    "sg:province":"CA",
    "sg:tags":[
        "agency"
    ],
    "wof:name":"New Salvador Travel Agency",
    "wof:placetype":"venue"
},
  "geometry": {"coordinates":[-118.284454,34.082437],"type":"Point"}
}