{
  "type": "Feature",
  "properties": {
    "addr:full":"2507 Tully Rd Modesto CA 95350",
    "addr:housenumber":"2507",
    "addr:postcode":"ca 95350",
    "addr:street":"Tully Rd",
    "iso:country":"US",
    "sg:address":"2507 Tully Rd",
    "sg:city":"Modesto",
    "sg:classifiers":[
        {
            "category":"Wholesale",
            "subcategory":"Machinery & Supplies",
            "type":"Manufacturing & Wholesale Goods"
        }
    ],
    "sg:phone":"+1 209 883 4097",
    "sg:postcode":"95350",
    "sg:province":"CA",
    "sg:tags":[
        "farm",
        "equipment"
    ],
    "wof:name":"Hughson Farm Supply",
    "wof:placetype":"venue"
},
  "geometry": {"coordinates":[-121.012438,37.680003],"type":"Point"}
}