{
  "type": "Feature",
  "properties": {
    "iso:country":"US",
    "sg:address":"1802 E Cedar St",
    "sg:city":"Ontario",
    "sg:classifiers":[
        {
            "category":"Building & Trades",
            "subcategory":"Construction",
            "type":"Services"
        }
    ],
    "sg:phone":"+1 909 930 2828",
    "sg:postcode":"91761",
    "sg:province":"CA",
    "sg:tags":[
        "contractor"
    ],
    "wof:name":"Genuine Techniques",
    "wof:placetype":"venue"
},
  "geometry": {"coordinates":[-117.611047,34.037645],"type":"Point"}
}