{
  "type": "Feature",
  "properties": {
    "iso:country":"US",
    "sg:address":"9133 International Blvd",
    "sg:city":"Oakland",
    "sg:classifiers":[
        {
            "category":"Food & Beverages",
            "subcategory":"Candy",
            "type":"Retail Goods"
        }
    ],
    "sg:postcode":"94603",
    "sg:province":"CA",
    "sg:tags":[
        "dessert"
    ],
    "wof:name":"Fresh Hot Churros",
    "wof:placetype":"venue"
},
  "geometry": {"coordinates":[-122.17400600000001,37.748521],"type":"Point"}
}