{
  "type": "Feature",
  "properties": {
    "iso:country":"US",
    "sg:address":"4989 Peabody Rd Ste B",
    "sg:city":"Fairfield",
    "sg:classifiers":[
        {
            "category":"Utilities",
            "subcategory":"Recycling",
            "type":"Services"
        },
        {
            "category":"Shopping",
            "subcategory":"Discount & Variety Stores",
            "type":"Retail Goods"
        }
    ],
    "sg:phone":"+1 707 437 1301",
    "sg:postcode":"94533",
    "sg:province":"CA",
    "sg:tags":[
        "salvage",
        "surplus",
        "merchandise"
    ],
    "sg:website":"http://www.recyclingzone.org",
    "wof:name":"Recycling Zone",
    "wof:placetype":"venue"
},
  "geometry": {"coordinates":[-121.96951900000001,38.289955],"type":"Point"}
}