{
  "type": "Feature",
  "properties": {
    "iso:country":"US",
    "sg:address":"316 Kearny Street",
    "sg:city":"San Francisco",
    "sg:classifiers":[
        {
            "category":"Retail",
            "subcategory":"Laundry & Dry Cleaning",
            "type":"Services"
        }
    ],
    "sg:phone":"+1 415 392 7598",
    "sg:postcode":"94108",
    "sg:province":"CA",
    "wof:name":"Rainbow-2",
    "wof:placetype":"venue"
},
  "geometry": {"coordinates":[-122.403999,37.7911],"type":"Point"}
}