{
  "type": "Feature",
  "properties": {
    "iso:country":"US",
    "sg:address":"5250 Claremont Ave",
    "sg:city":"Stockton",
    "sg:classifiers":[
        {
            "category":"Wholesale",
            "subcategory":"Metals & Minerals",
            "type":"Manufacturing & Wholesale Goods"
        }
    ],
    "sg:phone":"+1 209 472 6015",
    "sg:postcode":"95207",
    "sg:province":"CA",
    "sg:tags":[
        "steel",
        "warehouse"
    ],
    "wof:name":"CCC Steel Inc",
    "wof:placetype":"venue"
},
  "geometry": {"coordinates":[-121.309022,37.994478],"type":"Point"}
}