{
  "type": "Feature",
  "properties": {
    "iso:country":"US",
    "sg:address":"1330 4th St",
    "sg:city":"Santa Monica",
    "sg:classifiers":[
        {
            "category":"Arts & Performance",
            "subcategory":"Theater",
            "type":"Entertainment"
        }
    ],
    "sg:phone":"+1 310 656 4646",
    "sg:postcode":"90401",
    "sg:province":"CA",
    "sg:tags":[
        "television",
        "program",
        "producer"
    ],
    "wof:name":"Reactor Films",
    "wof:placetype":"venue"
},
  "geometry": {"coordinates":[-118.495671,34.016758],"type":"Point"}
}