{
  "type": "Feature",
  "properties": {
    "iso:country":"US",
    "sg:address":"24355 Lyons Ave Ste 130",
    "sg:city":"Newhall",
    "sg:classifiers":[
        {
            "category":"Health Services",
            "subcategory":"Doctor",
            "type":"Services"
        }
    ],
    "sg:phone":"+1 661 255 9355",
    "sg:postcode":"91321",
    "sg:province":"CA",
    "sg:tags":[
        "practice",
        "family"
    ],
    "sg:website":"www.thedoctorsofficescv.com",
    "wof:name":"The Doctors' Office",
    "wof:placetype":"venue"
},
  "geometry": {"coordinates":[-118.56199599999999,34.378399],"type":"Point"}
}