{
  "type": "Feature",
  "properties": {
    "iso:country":"US",
    "sg:address":"1910 California St",
    "sg:city":"Huntington Beach",
    "sg:classifiers":[
        {
            "category":"Shopping",
            "subcategory":"Clothing, Apparel, & Fashions",
            "type":"Retail Goods"
        }
    ],
    "sg:phone":"+1 714 412 9998",
    "sg:postcode":"92648",
    "sg:province":"CA",
    "wof:name":"Stairwell Merchandising",
    "wof:placetype":"venue"
},
  "geometry": {"coordinates":[-117.99402499999999,33.674765],"type":"Point"}
}