{
  "type": "Feature",
  "properties": {
    "addr:full":"7799 Enterprise Dr Newark CA 94560",
    "addr:housenumber":"7799",
    "addr:postcode":"94560",
    "addr:street":"Enterprise Dr",
    "iso:country":"US",
    "sg:address":"7799 Enterprise Dr",
    "sg:city":"Newark",
    "sg:classifiers":[
        {
            "category":"Building & Trades",
            "subcategory":"Construction",
            "type":"Services"
        }
    ],
    "sg:phone":"+1 510 574 0570",
    "sg:postcode":"94560",
    "sg:province":"CA",
    "sg:tags":[
        "concrete",
        "demolition",
        "contractor"
    ],
    "wof:name":"Stomper Co Inc",
    "wof:placetype":"venue"
},
  "geometry": {"coordinates":[-122.03933600000001,37.523545],"type":"Point"}
}