{
  "type": "Feature",
  "properties": {
    "iso:country":"US",
    "sg:address":"96 N 3rd St",
    "sg:city":"San Jose",
    "sg:classifiers":[
        {
            "category":"Wholesale",
            "subcategory":"Electrical",
            "type":"Manufacturing & Wholesale Goods"
        }
    ],
    "sg:phone":"+1 408 278 9008",
    "sg:postcode":"95112",
    "sg:province":"CA",
    "sg:tags":[
        "equipment",
        "electronic",
        "supply"
    ],
    "wof:name":"Worldamerican PCB Intl Inc",
    "wof:placetype":"venue"
},
  "geometry": {"coordinates":[-121.888462,37.337241],"type":"Point"}
}