{
  "type": "Feature",
  "properties": {
    "iso:country":"US",
    "sg:address":"250 N Robertson",
    "sg:city":"Beverly Hills",
    "sg:classifiers":[
        {
            "category":"Health Services",
            "subcategory":"Optometrist",
            "type":"Services"
        }
    ],
    "sg:phone":"+1 310 385 3450",
    "sg:postcode":"90211",
    "sg:province":"CA",
    "sg:website":"www.cedars-sinai.edu",
    "wof:name":"Beverly Hills Vision Center--Cedars Sinai",
    "wof:placetype":"venue"
},
  "geometry": {"coordinates":[-118.383767,34.070039],"type":"Point"}
}