{
  "type": "Feature",
  "properties": {
    "addr:full":"70 Trailview Ct San Ramon CA 94583",
    "addr:housenumber":"70",
    "addr:postcode":"94583",
    "addr:street":"Trailview Ct",
    "iso:country":"US",
    "sg:address":"70 Trailview Ct",
    "sg:city":"San Ramon",
    "sg:classifiers":[
        {
            "category":"Professional",
            "type":"Services"
        }
    ],
    "sg:phone":"+1 925 244 1811",
    "sg:postcode":"94583",
    "sg:province":"CA",
    "wof:name":"Annunziato & Assoc",
    "wof:placetype":"venue"
},
  "geometry": {"coordinates":[-121.964956,37.753976],"type":"Point"}
}