{
  "type": "Feature",
  "properties": {
    "addr:full":"505 E Romie Ln Salinas CA 93901",
    "addr:housenumber":"505",
    "addr:postcode":"93901",
    "addr:street":"E Romie Ln",
    "iso:country":"US",
    "sg:address":"505 E Romie Ln",
    "sg:city":"Salinas",
    "sg:classifiers":[
        {
            "category":"Shopping",
            "subcategory":"Pharmacy",
            "type":"Retail Goods"
        }
    ],
    "sg:phone":"+1 831 424 0395",
    "sg:postcode":"93901",
    "sg:province":"CA",
    "wof:name":"Romie Lane Pharmacy",
    "wof:placetype":"venue"
},
  "geometry": {"coordinates":[-121.644751,36.659708],"type":"Point"}
}