{
  "type": "Feature",
  "properties": {
    "iso:country":"US",
    "sg:address":"430 E 4th St",
    "sg:city":"Hanford",
    "sg:classifiers":[
        {
            "category":"Retail",
            "subcategory":"Auto Repair",
            "type":"Services"
        }
    ],
    "sg:phone":"+1 559 582 3652",
    "sg:postcode":"93230",
    "sg:province":"CA",
    "sg:tags":[
        "wheel",
        "axle",
        "alignment"
    ],
    "wof:name":"Hanford Alignment Svc",
    "wof:placetype":"venue"
},
  "geometry": {"coordinates":[-119.638985,36.324594],"type":"Point"}
}