{
  "type": "Feature",
  "properties": {
    "addr:full":"2025 Airpark Ct Auburn CA 95602",
    "addr:housenumber":"2025",
    "addr:postcode":"ca 95602",
    "addr:street":"Airpark Ct",
    "iso:country":"US",
    "sg:address":"2025 Airpark Ct",
    "sg:city":"Auburn",
    "sg:classifiers":[
        {
            "category":"Wholesale",
            "subcategory":"Construction Materials",
            "type":"Manufacturing & Wholesale Goods"
        }
    ],
    "sg:phone":"+1 530 888 7622",
    "sg:postcode":"95602",
    "sg:province":"CA",
    "sg:tags":[
        "tile"
    ],
    "wof:name":"Dal-Tile",
    "wof:placetype":"venue"
},
  "geometry": {"coordinates":[-121.078,38.951563],"type":"Point"}
}