{
  "type": "Feature",
  "properties": {
    "iso:country":"US",
    "sg:address":"3845 Santa Rosalia Dr",
    "sg:city":"Los Angeles",
    "sg:classifiers":[
        {
            "category":"Restaurant",
            "type":"Food & Drink"
        }
    ],
    "sg:phone":"+1 323 292 3627",
    "sg:postcode":"90008",
    "sg:province":"CA",
    "wof:name":"VIP Fish Market",
    "wof:placetype":"venue"
},
  "geometry": {"coordinates":[-118.340466,34.011188],"type":"Point"}
}