{
  "type": "Feature",
  "properties": {
    "iso:country":"US",
    "sg:address":"6443 Berwickshire Way",
    "sg:city":"San Jose",
    "sg:classifiers":[
        {
            "category":"Wholesale",
            "subcategory":"Electrical",
            "type":"Manufacturing & Wholesale Goods"
        }
    ],
    "sg:phone":"+1 408 293 2290",
    "sg:postcode":"95120",
    "sg:province":"CA",
    "sg:tags":[
        "electronic",
        "business"
    ],
    "wof:name":"Pal-Tech Electronics Inc",
    "wof:placetype":"venue"
},
  "geometry": {"coordinates":[-121.878401,37.223195],"type":"Point"}
}