{
  "type": "Feature",
  "properties": {
    "addr:full":"5357 Renaissance Ave San Diego CA 92122",
    "addr:housenumber":"5357",
    "addr:postcode":"92122",
    "addr:street":"Renaissance Ave",
    "iso:country":"US",
    "sg:address":"5357 Renaissance Ave",
    "sg:city":"San Diego",
    "sg:classifiers":[
        {
            "category":"Professional",
            "subcategory":"Computer Services",
            "type":"Services"
        }
    ],
    "sg:phone":"+1 858 450 9092",
    "sg:postcode":"92122",
    "sg:province":"CA",
    "sg:tags":[
        "consultant",
        "designer"
    ],
    "sg:website":"www.niefert.com",
    "wof:name":"Niefert Certified Solutions",
    "wof:placetype":"venue"
},
  "geometry": {"coordinates":[-117.20333100000001,32.868243],"type":"Point"}
}