{
  "type": "Feature",
  "properties": {
    "addr:full":"19356 Meekland Ave Hayward CA 94541",
    "addr:postcode":"19356;94541",
    "addr:street":"Meekland Ave",
    "iso:country":"US",
    "sg:address":"19356 Meekland Ave",
    "sg:city":"Hayward",
    "sg:classifiers":[
        {
            "category":"Manufacturing",
            "subcategory":"Metals",
            "type":"Manufacturing & Wholesale Goods"
        }
    ],
    "sg:phone":"+1 510 276 3950",
    "sg:postcode":"94541",
    "sg:province":"CA",
    "sg:tags":[
        "steel"
    ],
    "wof:name":"Cordeiro's Welding Svc",
    "wof:placetype":"venue"
},
  "geometry": {"coordinates":[-122.112059,37.679101],"type":"Point"}
}