{
  "type": "Feature",
  "properties": {
    "iso:country":"US",
    "sg:address":"280 Hegenberger Rd Ste 5",
    "sg:city":"Oakland",
    "sg:classifiers":[
        {
            "category":"Taxi",
            "type":"Transportation"
        }
    ],
    "sg:phone":"+1 510 562 4096",
    "sg:postcode":"94621",
    "sg:province":"CA",
    "wof:name":"Blue Sky Cab Co",
    "wof:placetype":"venue"
},
  "geometry": {"coordinates":[-122.19699900000001,37.736401],"type":"Point"}
}