{
  "type": "Feature",
  "properties": {
    "iso:country":"US",
    "sg:address":"668 W Kearney Blvd",
    "sg:city":"Fresno",
    "sg:classifiers":[
        {
            "category":"Manufacturing",
            "subcategory":"Aerospace",
            "type":"Manufacturing & Wholesale Goods"
        }
    ],
    "sg:phone":"+1 559 441 1316",
    "sg:postcode":"93706",
    "sg:province":"CA",
    "sg:tags":[
        "equipment",
        "aircraft",
        "part",
        "supply"
    ],
    "wof:name":"Delta Strut",
    "wof:placetype":"venue"
},
  "geometry": {"coordinates":[-119.804254,36.728261],"type":"Point"}
}