{
  "type": "Feature",
  "properties": {
    "iso:country":"US",
    "sg:address":"30600 Margarita Rd",
    "sg:city":"Temecula",
    "sg:classifiers":[
        {
            "category":"Education",
            "subcategory":"School",
            "type":"Public Place"
        }
    ],
    "sg:phone":"+1 951 695 7370",
    "sg:postcode":"92591",
    "sg:province":"CA",
    "sg:website":"www.tvusd.k12.ca.us",
    "wof:name":"Margarita Middle School",
    "wof:placetype":"venue"
},
  "geometry": {"coordinates":[-117.153705,33.544348],"type":"Point"}
}