{
  "type": "Feature",
  "properties": {
    "iso:country":"US",
    "sg:address":"1206 Broadway",
    "sg:city":"Chula Vista",
    "sg:classifiers":[
        {
            "category":"Restaurant",
            "type":"Food & Drink"
        }
    ],
    "sg:menulink":"http://www.allmenus.com/ca/san-diego/96973-ihop/menu/",
    "sg:phone":"+1 619 585 8600",
    "sg:postcode":"91911",
    "sg:province":"CA",
    "sg:tags":[
        "sandwich",
        "salad",
        "burger",
        "soup",
        "american",
        "steakhouse",
        "wrap"
    ],
    "wof:name":"IHOP",
    "wof:placetype":"venue"
},
  "geometry": {"coordinates":[-117.080164,32.605882],"type":"Point"}
}