{
  "type": "Feature",
  "properties": {
    "iso:country":"US",
    "sg:address":"66 Cumberland St",
    "sg:city":"San Francisco",
    "sg:classifiers":[
        {
            "category":"Professional",
            "subcategory":"Management & Consulting",
            "type":"Services"
        }
    ],
    "sg:phone":"+1 415 824 4360",
    "sg:postcode":"94110",
    "sg:province":"CA",
    "sg:tags":[
        "counselor",
        "public",
        "relations"
    ],
    "wof:name":"Think Ink",
    "wof:placetype":"venue"
},
  "geometry": {"coordinates":[-122.424673,37.759194],"type":"Point"}
}