{
  "type": "Feature",
  "properties": {
    "iso:country":"US",
    "sg:address":"2009 W Slauson Ave",
    "sg:city":"Los Angeles",
    "sg:classifiers":[
        {
            "category":"Wholesale",
            "subcategory":"Construction Materials",
            "type":"Manufacturing & Wholesale Goods"
        }
    ],
    "sg:phone":"+1 323 295 9417",
    "sg:postcode":"90047",
    "sg:province":"CA",
    "wof:name":"Slauson Kitchen Cabinets",
    "wof:placetype":"venue"
},
  "geometry": {"coordinates":[-118.314689,33.989188],"type":"Point"}
}