{
  "type": "Feature",
  "properties": {
    "iso:country":"US",
    "sg:address":"2313 E 1st St",
    "sg:city":"Los Angeles",
    "sg:classifiers":[
        {
            "category":"Food & Beverages",
            "subcategory":"Bakery",
            "type":"Retail Goods"
        }
    ],
    "sg:phone":"+1 323 261 1762",
    "sg:postcode":"90033",
    "sg:province":"CA",
    "sg:tags":[
        "doughnut"
    ],
    "wof:name":"Super Donuts",
    "wof:placetype":"venue"
},
  "geometry": {"coordinates":[-118.209848,34.043834],"type":"Point"}
}