{
  "type": "Feature",
  "properties": {
    "iso:country":"US",
    "sg:address":"3353 Durahart St",
    "sg:city":"Riverside",
    "sg:classifiers":[
        {
            "category":"Arts & Performance",
            "subcategory":"Theater",
            "type":"Entertainment"
        }
    ],
    "sg:phone":"+1 951 788 8205",
    "sg:postcode":"92507",
    "sg:province":"CA",
    "sg:tags":[
        "entertainer",
        "business"
    ],
    "wof:name":"Steven R Simpson Co",
    "wof:placetype":"venue"
},
  "geometry": {"coordinates":[-117.350033,33.982018],"type":"Point"}
}