{
  "type": "Feature",
  "properties": {
    "addr:full":"The Living Arts Counseling Center 4000 Broadway, #401 Oakland CA 94611",
    "addr:housenumber":"4000;# 401",
    "addr:postcode":"94611",
    "addr:street":"Broadway",
    "iso:country":"US",
    "sg:address":"The Living Arts Counseling Center 4000 Broadway, #401",
    "sg:city":"Oakland",
    "sg:classifiers":[
        {
            "category":"Health Services",
            "subcategory":"Clinic",
            "type":"Services"
        }
    ],
    "sg:phone":"+1 415 395 6328",
    "sg:postcode":"94611",
    "sg:province":"CA",
    "sg:tags":[
        "counseling",
        "mental"
    ],
    "sg:website":"www.benriverstherapy.com/",
    "wof:name":"Ben Rivers, Psychotherapy",
    "wof:placetype":"venue"
},
  "geometry": {"coordinates":[-122.25626200000001,37.827586],"type":"Point"}
}