{
  "type": "Feature",
  "properties": {
    "iso:country":"US",
    "sg:address":"492 62nd St",
    "sg:city":"Newport Beach",
    "sg:classifiers":[
        {
            "category":"Professional",
            "type":"Services"
        }
    ],
    "sg:phone":"+1 949 650 6216",
    "sg:postcode":"92663",
    "sg:province":"CA",
    "wof:name":"Thinair Data Corp",
    "wof:placetype":"venue"
},
  "geometry": {"coordinates":[-117.947952,33.629302],"type":"Point"}
}