{
  "type": "Feature",
  "properties": {
    "addr:full":"8363 Sultana Ave Fontana CA 92335",
    "addr:housenumber":"8363",
    "addr:postcode":"92335",
    "addr:street":"Sultana Ave",
    "iso:country":"US",
    "sg:address":"8363 Sultana Ave",
    "sg:city":"Fontana",
    "sg:classifiers":[
        {
            "category":"Manufacturing",
            "subcategory":"Metals",
            "type":"Manufacturing & Wholesale Goods"
        }
    ],
    "sg:phone":"+1 909 829 0906",
    "sg:postcode":"92335",
    "sg:province":"CA",
    "sg:tags":[
        "steel",
        "warehouse",
        "distributor",
        "mill",
        "fabricator"
    ],
    "wof:name":"Level 5 Steel",
    "wof:placetype":"venue"
},
  "geometry": {"coordinates":[-117.468986,34.102284],"type":"Point"}
}