{
  "type": "Feature",
  "properties": {
    "addr:full":"1925 Ruhland Ave Redondo Beach CA 90278",
    "addr:postcode":"1925;90278",
    "addr:street":"Ruhland Ave",
    "iso:country":"US",
    "sg:address":"1925 Ruhland Ave",
    "sg:city":"Redondo Beach",
    "sg:classifiers":[
        {
            "category":"Shopping",
            "type":"Retail Goods"
        }
    ],
    "sg:phone":"+1 310 780 3694",
    "sg:postcode":"90278",
    "sg:province":"CA",
    "sg:tags":[
        "pet",
        "shop"
    ],
    "wof:name":"Lobo's Dog Boutique",
    "wof:placetype":"venue"
},
  "geometry": {"coordinates":[-118.377585,33.875732],"type":"Point"}
}