{
  "type": "Feature",
  "properties": {
    "addr:full":"2525 Springs Rd Vallejo CA 94591",
    "addr:housenumber":"2525",
    "addr:postcode":"94591",
    "addr:street":"Springs Rd",
    "iso:country":"US",
    "sg:address":"2525 Springs Rd",
    "sg:city":"Vallejo",
    "sg:classifiers":[
        {
            "category":"Building & Trades",
            "subcategory":"Construction",
            "type":"Services"
        }
    ],
    "sg:phone":"+1 707 645 9480",
    "sg:postcode":"94591",
    "sg:province":"CA",
    "sg:tags":[
        "contractor"
    ],
    "wof:name":"Window Covering Solutions",
    "wof:placetype":"venue"
},
  "geometry": {"coordinates":[-122.21057999999999,38.105882],"type":"Point"}
}