{
  "type": "Feature",
  "properties": {
    "addr:full":"10 Waynesboro Irvine CA 92620",
    "addr:housenumber":"10",
    "addr:postcode":"92620",
    "addr:street":"Waynesboro",
    "iso:country":"US",
    "sg:address":"10 Waynesboro",
    "sg:city":"Irvine",
    "sg:classifiers":[
        {
            "category":"Banks & Credit Unions",
            "subcategory":"Financial Services",
            "type":"Services"
        }
    ],
    "sg:phone":"+1 949 262 0402",
    "sg:postcode":"92620",
    "sg:province":"CA",
    "sg:tags":[
        "residential",
        "owner",
        "real estate"
    ],
    "wof:name":"Performance Systems Inc",
    "wof:placetype":"venue"
},
  "geometry": {"coordinates":[-117.77040599999999,33.701575],"type":"Point"}
}