{
  "type": "Feature",
  "properties": {
    "iso:country":"US",
    "sg:address":"20528 Carrey Rd",
    "sg:city":"Walnut",
    "sg:classifiers":[
        {
            "category":"Manufacturing",
            "subcategory":"Retail Goods",
            "type":"Manufacturing & Wholesale Goods"
        }
    ],
    "sg:phone":"+1 909 598 3737",
    "sg:postcode":"91789",
    "sg:province":"CA",
    "sg:tags":[
        "giftware's-wholesale",
        "manufacturer"
    ],
    "wof:name":"Hipro Power",
    "wof:placetype":"venue"
},
  "geometry": {"coordinates":[-117.857277,34.015887],"type":"Point"}
}