{
  "type": "Feature",
  "properties": {
    "addr:full":"22265 Newbridge Dr Lake Forest CA 92630",
    "addr:housenumber":"22265",
    "addr:postcode":"92630",
    "addr:street":"Newbridge Dr",
    "iso:country":"US",
    "sg:address":"22265 Newbridge Dr",
    "sg:city":"Lake Forest",
    "sg:classifiers":[
        {
            "category":"Building & Trades",
            "subcategory":"Cleaning & Sanitation",
            "type":"Services"
        }
    ],
    "sg:phone":"+1 949 770 1871",
    "sg:postcode":"92630",
    "sg:province":"CA",
    "sg:tags":[
        "house"
    ],
    "wof:name":"Born To Serve",
    "wof:placetype":"venue"
},
  "geometry": {"coordinates":[-117.67336899999999,33.639985],"type":"Point"}
}