{
  "type": "Feature",
  "properties": {
    "addr:full":"735 E Green St Pasadena CA 91101",
    "addr:housenumber":"735",
    "addr:postcode":"91101",
    "addr:street":"E Green St",
    "iso:country":"US",
    "sg:address":"735 E Green St",
    "sg:city":"Pasadena",
    "sg:classifiers":[
        {
            "category":"Restaurant",
            "type":"Food & Drink"
        }
    ],
    "sg:phone":"+1 626 578 1123",
    "sg:postcode":"91101",
    "sg:province":"CA",
    "sg:tags":[
        "sushi",
        "bar",
        "caterer"
    ],
    "sg:website":"www.sushiofnaples.net",
    "wof:name":"Sushi of Naples",
    "wof:placetype":"venue"
},
  "geometry": {"coordinates":[-118.13534300000001,34.144529],"type":"Point"}
}