{
  "type": "Feature",
  "properties": {
    "addr:full":"15191 S Figueroa St Gardena CA 90248",
    "addr:housenumber":"15191",
    "addr:postcode":"90248",
    "addr:street":"S Figueroa St",
    "iso:country":"US",
    "sg:address":"15191 S Figueroa St",
    "sg:city":"Gardena",
    "sg:classifiers":[
        {
            "category":"Freight",
            "type":"Transportation"
        }
    ],
    "sg:phone":"+1 310 329 2942",
    "sg:postcode":"90248",
    "sg:province":"CA",
    "sg:tags":[
        "general"
    ],
    "wof:name":"WAI",
    "wof:placetype":"venue"
},
  "geometry": {"coordinates":[-118.283168,33.894277],"type":"Point"}
}