{
  "type": "Feature",
  "properties": {
    "iso:country":"US",
    "sg:address":"2090 Fremont St",
    "sg:city":"Monterey",
    "sg:classifiers":[
        {
            "category":"Shopping",
            "type":"Retail Goods"
        }
    ],
    "sg:phone":"+1 831 646 5141",
    "sg:postcode":"93940",
    "sg:province":"CA",
    "sg:tags":[
        "picture",
        "frame"
    ],
    "wof:name":"Beverly Fabrics",
    "wof:placetype":"venue"
},
  "geometry": {"coordinates":[-121.86363,36.595914],"type":"Point"}
}