{
  "type": "Feature",
  "properties": {
    "iso:country":"US",
    "sg:address":"4012 Loma Vista Ave",
    "sg:city":"Oakland",
    "sg:classifiers":[
        {
            "category":"Professional",
            "type":"Services"
        }
    ],
    "sg:phone":"+1 510 530 3207",
    "sg:postcode":"94619",
    "sg:province":"CA",
    "wof:name":"Brock C Drazen",
    "wof:placetype":"venue"
},
  "geometry": {"coordinates":[-122.193161,37.795998],"type":"Point"}
}