{
  "type": "Feature",
  "properties": {
    "addr:full":"312 W Big Bear Blvd Big Bear City CA 92314",
    "addr:housenumber":"312",
    "addr:postcode":"92314",
    "addr:street":"W Big Bear Blvd",
    "iso:country":"US",
    "sg:address":"312 W Big Bear Blvd",
    "sg:city":"Big Bear City",
    "sg:classifiers":[
        {
            "category":"Building & Trades",
            "subcategory":"Construction",
            "type":"Services"
        }
    ],
    "sg:phone":"+1 909 585 2285",
    "sg:postcode":"92314",
    "sg:province":"CA",
    "sg:tags":[
        "contractor"
    ],
    "wof:name":"Eagle Tree Service",
    "wof:placetype":"venue"
},
  "geometry": {"coordinates":[-116.84906599999999,34.261059],"type":"Point"}
}