{
  "type": "Feature",
  "properties": {
    "addr:full":"6632 Stanley Ave Carmichael CA 95608",
    "addr:housenumber":"6632",
    "addr:postcode":"95608",
    "addr:street":"Stanley Ave",
    "iso:country":"US",
    "sg:address":"6632 Stanley Ave",
    "sg:city":"Carmichael",
    "sg:classifiers":[
        {
            "category":"Building & Trades",
            "subcategory":"Construction",
            "type":"Services"
        }
    ],
    "sg:phone":"+1 916 487 6632",
    "sg:postcode":"95608",
    "sg:province":"CA",
    "sg:tags":[
        "roofing",
        "contractor"
    ],
    "wof:name":"Thomas Roofing",
    "wof:placetype":"venue"
},
  "geometry": {"coordinates":[-121.30944700000001,38.621955],"type":"Point"}
}