{
  "type": "Feature",
  "properties": {
    "addr:full":"4235 Pacific St Rocklin CA 95677",
    "addr:housenumber":"4235",
    "addr:postcode":"95677",
    "addr:street":"Pacific St",
    "iso:country":"US",
    "sg:address":"4235 Pacific St",
    "sg:city":"Rocklin",
    "sg:classifiers":[
        {
            "category":"Manufacturing",
            "subcategory":"Printing",
            "type":"Manufacturing & Wholesale Goods"
        }
    ],
    "sg:phone":"+1 916 632 3910",
    "sg:postcode":"95677",
    "sg:province":"CA",
    "sg:tags":[
        "screen"
    ],
    "wof:name":"Big Air Sports",
    "wof:placetype":"venue"
},
  "geometry": {"coordinates":[-121.218462,38.804325],"type":"Point"}
}