{
  "type": "Feature",
  "properties": {
    "iso:country":"US",
    "sg:address":"2105 Forest Ave",
    "sg:city":"San Jose",
    "sg:classifiers":[
        {
            "category":"Health Services",
            "subcategory":"Doctor",
            "type":"Services"
        }
    ],
    "sg:phone":"+1 408 947 2804",
    "sg:postcode":"95128",
    "sg:province":"CA",
    "sg:tags":[
        "physician",
        "surgeon"
    ],
    "wof:name":"Wound Care Ctr-O'Connor Hosp",
    "wof:placetype":"venue"
},
  "geometry": {"coordinates":[-121.93803200000001,37.327126],"type":"Point"}
}