{
  "type": "Feature",
  "properties": {
    "addr:full":"20371 Leutar Ct Saratoga CA 95070",
    "addr:postcode":"20371;95070",
    "addr:street":"Leutar Ct",
    "iso:country":"US",
    "sg:address":"20371 Leutar Ct",
    "sg:city":"Saratoga",
    "sg:classifiers":[
        {
            "category":"Professional",
            "type":"Services"
        }
    ],
    "sg:phone":"+1 408 446 3320",
    "sg:postcode":"95070",
    "sg:province":"CA",
    "wof:name":"Chang Cheung Family Ltd Partnr",
    "wof:placetype":"venue"
},
  "geometry": {"coordinates":[-122.029414,37.287252],"type":"Point"}
}