{
  "type": "Feature",
  "properties": {
    "iso:country":"US",
    "sg:address":"1285 S Lewis St",
    "sg:city":"Anaheim",
    "sg:classifiers":[
        {
            "category":"Building & Trades",
            "subcategory":"Construction",
            "type":"Services"
        }
    ],
    "sg:phone":"+1 714 254 8400",
    "sg:postcode":"92805",
    "sg:province":"CA",
    "sg:tags":[
        "contractor"
    ],
    "sg:website":"www.itxconstruction.com",
    "wof:name":"Itx Construction Consultants",
    "wof:placetype":"venue"
},
  "geometry": {"coordinates":[-117.898003,33.815102],"type":"Point"}
}