{
  "type": "Feature",
  "properties": {
    "addr:full":"2815 Canon St San Diego CA 92106",
    "addr:housenumber":"2815",
    "addr:postcode":"92106",
    "addr:street":"Canon St",
    "iso:country":"US",
    "sg:address":"2815 Canon St",
    "sg:city":"San Diego",
    "sg:classifiers":[
        {
            "category":"Manufacturing",
            "subcategory":"Tools & Machinery",
            "type":"Manufacturing & Wholesale Goods"
        }
    ],
    "sg:phone":"+1 619 224 2070",
    "sg:postcode":"92106",
    "sg:province":"CA",
    "sg:tags":[
        "photographic",
        "mfg"
    ],
    "wof:name":"Adroit Engineering Inc",
    "wof:placetype":"venue"
},
  "geometry": {"coordinates":[-117.230746,32.720724],"type":"Point"}
}