{
  "type": "Feature",
  "properties": {
    "iso:country":"US",
    "sg:address":"309 Wall St",
    "sg:city":"Chico",
    "sg:classifiers":[
        {
            "category":"Communications",
            "subcategory":"Film & Video Production",
            "type":"Services"
        }
    ],
    "sg:phone":"+1 530 891 0315",
    "sg:postcode":"95928",
    "sg:province":"CA",
    "sg:tags":[
        "taping"
    ],
    "wof:name":"Ablaze Video",
    "wof:placetype":"venue"
},
  "geometry": {"coordinates":[-121.837864,39.72968],"type":"Point"}
}