{
  "type": "Feature",
  "properties": {
    "addr:full":"489 Miller Ave Mill Valley CA 94941",
    "addr:housenumber":"489",
    "addr:postcode":"94941",
    "addr:street":"Miller Ave",
    "iso:country":"US",
    "sg:address":"489 Miller Ave",
    "sg:city":"Mill Valley",
    "sg:classifiers":[
        {
            "category":"Retail",
            "subcategory":"Veterinary Services",
            "type":"Services"
        }
    ],
    "sg:phone":"+1 415 380 0500",
    "sg:postcode":"94941",
    "sg:province":"CA",
    "sg:tags":[
        "hospital",
        "animal"
    ],
    "wof:name":"Sams Clinic",
    "wof:placetype":"venue"
},
  "geometry": {"coordinates":[-122.533935,37.895147],"type":"Point"}
}