{
  "type": "Feature",
  "properties": {
    "iso:country":"US",
    "sg:address":"11905 Salem Dr",
    "sg:city":"Granada Hills",
    "sg:classifiers":[
        {
            "category":"Professional",
            "type":"Services"
        }
    ],
    "sg:phone":"+1 818 363 7188",
    "sg:postcode":"91344",
    "sg:province":"CA",
    "wof:name":"Don Markese Prod",
    "wof:placetype":"venue"
},
  "geometry": {"coordinates":[-118.50845099999999,34.288562],"type":"Point"}
}