{
  "type": "Feature",
  "properties": {
    "iso:country":"US",
    "sg:address":"22 Pan Tempo Way",
    "sg:city":"Hollister",
    "sg:classifiers":[
        {
            "category":"Retail",
            "subcategory":"Animal Services",
            "type":"Services"
        }
    ],
    "sg:phone":"+1 831 637 9409",
    "sg:postcode":"95023",
    "sg:province":"CA",
    "wof:name":"Smoky Hills Farm/Morgan Horses",
    "wof:placetype":"venue"
},
  "geometry": {"coordinates":[-121.349985,36.872537],"type":"Point"}
}