{
  "type": "Feature",
  "properties": {
    "iso:country":"US",
    "sg:address":"875 S Westlake Blvd",
    "sg:city":"Westlake Village",
    "sg:classifiers":[
        {
            "category":"Insurance",
            "subcategory":"Insurance Agent",
            "type":"Services"
        }
    ],
    "sg:phone":"+1 805 497 4581",
    "sg:postcode":"91361",
    "sg:province":"CA",
    "wof:name":"EBA & M Corp",
    "wof:placetype":"venue"
},
  "geometry": {"coordinates":[-118.827076,34.155029],"type":"Point"}
}