{
  "type": "Feature",
  "properties": {
    "addr:full":"3435 Wilshire Blvd Ste 123 Los Angeles CA 90010",
    "addr:housenumber":"3435",
    "addr:postcode":"90010",
    "addr:street":"Wilshire Blvd Ste 123",
    "iso:country":"US",
    "sg:address":"3435 Wilshire Blvd Ste 123",
    "sg:city":"Los Angeles",
    "sg:classifiers":[
        {
            "category":"Restaurant",
            "type":"Food & Drink"
        }
    ],
    "sg:phone":"+1 213 385 5600",
    "sg:postcode":"90010",
    "sg:province":"CA",
    "sg:tags":[
        "korean",
        "barbeque"
    ],
    "sg:website":"www.sohyangbbq.com",
    "wof:name":"So Hyang Korean Restaurant",
    "wof:placetype":"venue"
},
  "geometry": {"coordinates":[-118.29857,34.062474],"type":"Point"}
}