{
  "type": "Feature",
  "properties": {
    "addr:full":"1212 Forest Ave Pacific Grove CA 93950",
    "addr:housenumber":"1212",
    "addr:postcode":"93950",
    "addr:street":"Forest Ave",
    "iso:country":"US",
    "sg:address":"1212 Forest Ave",
    "sg:city":"Pacific Grove",
    "sg:classifiers":[
        {
            "category":"Food & Beverages",
            "subcategory":"Groceries & Convenience Stores",
            "type":"Retail Goods"
        }
    ],
    "sg:phone":"+1 831 375 8262",
    "sg:postcode":"93950",
    "sg:province":"CA",
    "wof:name":"Safeway",
    "wof:placetype":"venue"
},
  "geometry": {"coordinates":[-121.920176,36.604061],"type":"Point"}
}