{
  "type": "Feature",
  "properties": {
    "addr:full":"3880 Benatar Way Chico CA 95928",
    "addr:postcode":"3880;95928",
    "addr:street":"Benatar Way",
    "iso:country":"US",
    "sg:address":"3880 Benatar Way",
    "sg:city":"Chico",
    "sg:classifiers":[
        {
            "category":"Retail",
            "subcategory":"Auto Repair",
            "type":"Services"
        }
    ],
    "sg:phone":"+1 530 899 1137",
    "sg:postcode":"95928",
    "sg:province":"CA",
    "sg:tags":[
        "repairing",
        "automobile"
    ],
    "wof:name":"A & E Automotive",
    "wof:placetype":"venue"
},
  "geometry": {"coordinates":[-121.788901,39.713362],"type":"Point"}
}