{
  "type": "Feature",
  "properties": {
    "iso:country":"US",
    "sg:address":"19071 Beach Blvd",
    "sg:city":"Huntington Beach",
    "sg:classifiers":[
        {
            "category":"Retail",
            "subcategory":"Laundry & Dry Cleaning",
            "type":"Services"
        }
    ],
    "sg:phone":"+1 714 847 6862",
    "sg:postcode":"92648",
    "sg:province":"CA",
    "wof:name":"Norton's Port Cleaners",
    "wof:placetype":"venue"
},
  "geometry": {"coordinates":[-117.988998,33.6856],"type":"Point"}
}