{
  "type": "Feature",
  "properties": {
    "iso:country":"US",
    "sg:address":"118 N Irwin St",
    "sg:city":"Hanford",
    "sg:classifiers":[
        {
            "category":"Bars & Pubs",
            "type":"Food & Drink"
        }
    ],
    "sg:phone":"+1 559 582 9945",
    "sg:postcode":"93230",
    "sg:province":"CA",
    "wof:name":"Sequoia Club",
    "wof:placetype":"venue"
},
  "geometry": {"coordinates":[-119.6476,36.32738],"type":"Point"}
}