{
  "type": "Feature",
  "properties": {
    "addr:full":"120 W Maitland St Ontario CA 91762",
    "addr:housenumber":"120",
    "addr:postcode":"91762",
    "addr:street":"W Maitland St",
    "iso:country":"US",
    "sg:address":"120 W Maitland St",
    "sg:city":"Ontario",
    "sg:classifiers":[
        {
            "category":"Building & Trades",
            "subcategory":"Cleaning & Sanitation",
            "type":"Services"
        }
    ],
    "sg:phone":"+1 909 983 1637",
    "sg:postcode":"91762",
    "sg:province":"CA",
    "sg:tags":[
        "janitor"
    ],
    "wof:name":"ARME Cleaning Svc",
    "wof:placetype":"venue"
},
  "geometry": {"coordinates":[-117.653308,34.053677],"type":"Point"}
}