{
  "type": "Feature",
  "properties": {
    "addr:full":"618 Castle Dr Paradise CA 95969",
    "addr:housenumber":"618",
    "addr:postcode":"95969",
    "addr:street":"Castle Dr",
    "iso:country":"US",
    "sg:address":"618 Castle Dr",
    "sg:city":"Paradise",
    "sg:classifiers":[
        {
            "category":"Building & Trades",
            "subcategory":"Plumbing",
            "type":"Services"
        }
    ],
    "sg:phone":"+1 530 872 8338",
    "sg:postcode":"95969",
    "sg:province":"CA",
    "sg:tags":[
        "tank",
        "system",
        "septic"
    ],
    "wof:name":"R E Construction",
    "wof:placetype":"venue"
},
  "geometry": {"coordinates":[-121.62915,39.766804],"type":"Point"}
}