{
  "type": "Feature",
  "properties": {
    "addr:full":"2590 North St Anderson CA 96007",
    "addr:housenumber":"2590",
    "addr:postcode":"96007",
    "addr:street":"North St",
    "iso:country":"US",
    "sg:address":"2590 North St",
    "sg:city":"Anderson",
    "sg:classifiers":[
        {
            "category":"Restaurant",
            "type":"Food & Drink"
        }
    ],
    "sg:phone":"+1 530 365 6595",
    "sg:postcode":"96007",
    "sg:province":"CA",
    "wof:name":"Zuno's Taqueria",
    "wof:placetype":"venue"
},
  "geometry": {"coordinates":[-122.294839,40.456613],"type":"Point"}
}