{
  "type": "Feature",
  "properties": {
    "iso:country":"US",
    "sg:address":"2448 Lillie Avenue",
    "sg:city":"Summerland",
    "sg:classifiers":[
        {
            "category":"Sports & Exercise",
            "subcategory":"Gym",
            "type":"Entertainment"
        }
    ],
    "sg:phone":"+1 805 969 1570",
    "sg:postcode":"93013",
    "sg:province":"CA",
    "sg:website":"www.platinumfitnessonline.com",
    "wof:name":"Platinum Fitness Summerland",
    "wof:placetype":"venue"
},
  "geometry": {"coordinates":[-119.59595299999999,34.420431],"type":"Point"}
}