{
  "type": "Feature",
  "properties": {
    "iso:country":"US",
    "sg:address":"66 Punta Perdido",
    "sg:city":"Monterey",
    "sg:classifiers":[
        {
            "category":"Retail",
            "subcategory":"Portrait Studio",
            "type":"Services"
        }
    ],
    "sg:phone":"+1 831 372 0567",
    "sg:postcode":"93940",
    "sg:province":"CA",
    "sg:tags":[
        "photographer"
    ],
    "wof:name":"Chrysalis Photography",
    "wof:placetype":"venue"
},
  "geometry": {"coordinates":[-121.898225,36.589054],"type":"Point"}
}