{
  "type": "Feature",
  "properties": {
    "addr:full":"1631 N 2nd St El Cajon CA 92021",
    "addr:housenumber":"1631",
    "addr:postcode":"92021",
    "addr:street":"N 2Nd St",
    "iso:country":"US",
    "sg:address":"1631 N 2nd St",
    "sg:city":"El Cajon",
    "sg:classifiers":[
        {
            "category":"Building & Trades",
            "subcategory":"Plumbing",
            "type":"Services"
        }
    ],
    "sg:phone":"+1 619 579 1014",
    "sg:postcode":"92021",
    "sg:province":"CA",
    "sg:tags":[
        "plumbing",
        "contractor"
    ],
    "wof:name":"Sedco Plumbing",
    "wof:placetype":"venue"
},
  "geometry": {"coordinates":[-116.93565,32.817273],"type":"Point"}
}