{
  "type": "Feature",
  "properties": {
    "addr:full":"1695 Watson Way Vista CA 92083",
    "addr:housenumber":"1695",
    "addr:postcode":"92083",
    "addr:street":"Watson Way",
    "iso:country":"US",
    "sg:address":"1695 Watson Way",
    "sg:city":"Vista",
    "sg:classifiers":[
        {
            "category":"Retail",
            "subcategory":"Laundry & Dry Cleaning",
            "type":"Services"
        }
    ],
    "sg:phone":"+1 760 941 4441",
    "sg:postcode":"92083",
    "sg:province":"CA",
    "sg:tags":[
        "cleaners",
        "rug",
        "carpet"
    ],
    "wof:name":"Courtesy Chem-Dry",
    "wof:placetype":"venue"
},
  "geometry": {"coordinates":[-117.22040800000001,33.179406],"type":"Point"}
}