{
  "type": "Feature",
  "properties": {
    "iso:country":"US",
    "sg:address":"4488 N Cornelia Ave",
    "sg:city":"Fresno",
    "sg:classifiers":[
        {
            "category":"Manufacturing",
            "subcategory":"Food",
            "type":"Manufacturing & Wholesale Goods"
        }
    ],
    "sg:phone":"+1 559 277 0790",
    "sg:postcode":"93722",
    "sg:province":"CA",
    "sg:tags":[
        "desert",
        "ice",
        "mfg"
    ],
    "wof:name":"Amrit Ice Cream",
    "wof:placetype":"venue"
},
  "geometry": {"coordinates":[-119.880381,36.801788],"type":"Point"}
}