{
  "type": "Feature",
  "properties": {
    "addr:full":"29000 Foresthill Rd Foresthill CA 95631",
    "addr:postcode":"29000;95631",
    "addr:street":"Foresthill Rd",
    "iso:country":"US",
    "sg:address":"29000 Foresthill Rd",
    "sg:city":"Foresthill",
    "sg:classifiers":[
        {
            "category":"Manufacturing",
            "subcategory":"Lumber",
            "type":"Manufacturing & Wholesale Goods"
        }
    ],
    "sg:phone":"+1 530 367 4704",
    "sg:postcode":"95631",
    "sg:province":"CA",
    "sg:tags":[
        "logging"
    ],
    "sg:website":"http://www.ftcnet.net",
    "wof:name":"Delmue Logging",
    "wof:placetype":"venue"
},
  "geometry": {"coordinates":[-120.757616,39.057832],"type":"Point"}
}