{
  "type": "Feature",
  "properties": {
    "iso:country":"US",
    "sg:address":"7601 Hansom Dr",
    "sg:city":"Oakland",
    "sg:classifiers":[
        {
            "category":"Health Services",
            "subcategory":"Doctor",
            "type":"Services"
        }
    ],
    "sg:phone":"+1 510 839 7292",
    "sg:postcode":"94605",
    "sg:province":"CA",
    "sg:tags":[
        "physician",
        "surgeon"
    ],
    "wof:name":"Edward D Krug MD",
    "wof:placetype":"venue"
},
  "geometry": {"coordinates":[-122.141527,37.777711],"type":"Point"}
}