{
  "type": "Feature",
  "properties": {
    "iso:country":"US",
    "sg:address":"289 Rose Ln",
    "sg:city":"Costa Mesa",
    "sg:classifiers":[
        {
            "category":"Professional",
            "type":"Services"
        }
    ],
    "sg:phone":"+1 949 515 4376",
    "sg:postcode":"92627",
    "sg:province":"CA",
    "sg:tags":[
        "establishment"
    ],
    "wof:name":"Durkin & Durkin",
    "wof:placetype":"venue"
},
  "geometry": {"coordinates":[-117.904383,33.646996],"type":"Point"}
}