{
  "type": "Feature",
  "properties": {
    "addr:full":"6027 San Pablo Ave Emeryville CA 94608",
    "addr:housenumber":"6027",
    "addr:postcode":"94608",
    "addr:street":"San Pablo Ave",
    "iso:country":"US",
    "sg:address":"6027 San Pablo Ave",
    "sg:city":"Emeryville",
    "sg:classifiers":[
        {
            "category":"Manufacturing",
            "subcategory":"Buildings",
            "type":"Manufacturing & Wholesale Goods"
        },
        {
            "category":"Building & Trades",
            "subcategory":"Construction",
            "type":"Services"
        }
    ],
    "sg:phone":"+1 510 548 2638",
    "sg:postcode":"94608",
    "sg:province":"CA",
    "sg:tags":[
        "home",
        "builder",
        "contractor"
    ],
    "wof:name":"N R G Construction Co.",
    "wof:placetype":"venue"
},
  "geometry": {"coordinates":[-122.283886,37.843282],"type":"Point"}
}