{
  "type": "Feature",
  "properties": {
    "addr:full":"234 N Arrowhead Ave San Bernardino CA 92408",
    "addr:housenumber":"234",
    "addr:postcode":"92408",
    "addr:street":"N Arrowhead Ave",
    "iso:country":"US",
    "sg:address":"234 N Arrowhead Ave",
    "sg:city":"San Bernardino",
    "sg:classifiers":[
        {
            "category":"Professional",
            "subcategory":"Engineering",
            "type":"Services"
        }
    ],
    "sg:phone":"+1 909 885 3806",
    "sg:postcode":"92408",
    "sg:province":"CA",
    "sg:tags":[
        "engineer"
    ],
    "sg:website":"www.bonadiman.com",
    "wof:name":"Joseph E Bonadiman & Assoc Inc",
    "wof:placetype":"venue"
},
  "geometry": {"coordinates":[-117.289745,34.103933],"type":"Point"}
}