{
  "type": "Feature",
  "properties": {
    "iso:country":"US",
    "sg:address":"3022 N Hollywood Way",
    "sg:city":"Burbank",
    "sg:classifiers":[
        {
            "category":"Autos & Motor Vehicles",
            "subcategory":"Motorcycle Sales",
            "type":"Retail Goods"
        }
    ],
    "sg:phone":"+1 818 303 8303",
    "sg:postcode":"91505",
    "sg:province":"CA",
    "wof:name":"Moto Dc Inc",
    "wof:placetype":"venue"
},
  "geometry": {"coordinates":[-118.34851399999999,34.203933],"type":"Point"}
}