{
  "type": "Feature",
  "properties": {
    "iso:country":"US",
    "sg:address":"32905 Malinta Ave",
    "sg:city":"Acton",
    "sg:classifiers":[
        {
            "category":"Wholesale",
            "subcategory":"Auto Parts",
            "type":"Manufacturing & Wholesale Goods"
        }
    ],
    "sg:phone":"+1 661 269 9220",
    "sg:postcode":"93510",
    "sg:province":"CA",
    "sg:tags":[
        "automotive",
        "supply"
    ],
    "wof:name":"Harrison Inventory Services",
    "wof:placetype":"venue"
},
  "geometry": {"coordinates":[-118.149718,34.483431],"type":"Point"}
}