{
  "type": "Feature",
  "properties": {
    "iso:country":"US",
    "sg:address":"3771 Arlington Ave",
    "sg:city":"Riverside",
    "sg:classifiers":[
        {
            "category":"Banks & Credit Unions",
            "subcategory":"Financial Services",
            "type":"Services"
        }
    ],
    "sg:phone":"+1 951 683 0504",
    "sg:postcode":"92506",
    "sg:province":"CA",
    "sg:tags":[
        "trust"
    ],
    "wof:name":"Asset Planning & Adm",
    "wof:placetype":"venue"
},
  "geometry": {"coordinates":[-117.400049,33.946304],"type":"Point"}
}