{
  "type": "Feature",
  "properties": {
    "addr:full":"14242 Ventura Blvd Sherman Oaks CA 91423",
    "addr:housenumber":"14242",
    "addr:postcode":"91423",
    "addr:street":"Ventura Blvd",
    "iso:country":"US",
    "sg:address":"14242 Ventura Blvd",
    "sg:city":"Sherman Oaks",
    "sg:classifiers":[
        {
            "category":"Real Estate",
            "subcategory":"Real Estate Agent",
            "type":"Services"
        }
    ],
    "sg:phone":"+1 818 789 7408",
    "sg:postcode":"91423",
    "sg:province":"CA",
    "wof:name":"Matt Epstein & Team 2000",
    "wof:placetype":"venue"
},
  "geometry": {"coordinates":[-118.44112199999999,34.149661],"type":"Point"}
}