{
  "type": "Feature",
  "properties": {
    "addr:full":"901 F St Ste 150 Sacramento CA 95814",
    "addr:housenumber":"901",
    "addr:postcode":"95814",
    "addr:street":"F St Ste 150",
    "iso:country":"US",
    "sg:address":"901 F St Ste 150",
    "sg:city":"Sacramento",
    "sg:classifiers":[
        {
            "category":"Professional",
            "subcategory":"Business Services",
            "type":"Services"
        },
        {
            "category":"Government",
            "subcategory":"Post Office",
            "type":"Public Place"
        }
    ],
    "sg:phone":"+1 916 447 4000",
    "sg:postcode":"95814",
    "sg:province":"CA",
    "sg:tags":[
        "delivery",
        "messenger",
        "courier"
    ],
    "wof:name":"Ace Messenger And Attorney Services",
    "wof:placetype":"venue"
},
  "geometry": {"coordinates":[-121.49288900000001,38.585041],"type":"Point"}
}