{
  "type": "Feature",
  "properties": {
    "addr:full":"381 W Hawkeye Ave Turlock CA 95380",
    "addr:housenumber":"381",
    "addr:postcode":"95380",
    "addr:street":"W Hawkeye Ave",
    "iso:country":"US",
    "sg:address":"381 W Hawkeye Ave",
    "sg:city":"Turlock",
    "sg:classifiers":[
        {
            "category":"Retail",
            "subcategory":"Repair Shop",
            "type":"Services"
        }
    ],
    "sg:phone":"+1 209 586 7452",
    "sg:postcode":"95380",
    "sg:province":"CA",
    "sg:tags":[
        "related"
    ],
    "wof:name":"Vinylman",
    "wof:placetype":"venue"
},
  "geometry": {"coordinates":[-120.853092,37.507295],"type":"Point"}
}