{
  "type": "Feature",
  "properties": {
    "addr:full":"11819 Firestone Blvd Norwalk CA 90650",
    "addr:housenumber":"11819",
    "addr:postcode":"90650",
    "addr:street":"Firestone Blvd",
    "iso:country":"US",
    "sg:address":"11819 Firestone Blvd",
    "sg:city":"Norwalk",
    "sg:classifiers":[
        {
            "category":"Professional",
            "type":"Services"
        }
    ],
    "sg:phone":"+1 562 868 9585",
    "sg:postcode":"90650",
    "sg:province":"CA",
    "wof:name":"Dp Foreclosure Svc Co Inc",
    "wof:placetype":"venue"
},
  "geometry": {"coordinates":[-118.079719,33.911823],"type":"Point"}
}