{
  "type": "Feature",
  "properties": {
    "iso:country":"US",
    "sg:address":"1594 S Lewis St",
    "sg:city":"Anaheim",
    "sg:classifiers":[
        {
            "category":"Wholesale",
            "subcategory":"Machinery & Supplies",
            "type":"Manufacturing & Wholesale Goods"
        }
    ],
    "sg:phone":"+1 714 563 0686",
    "sg:postcode":"92805",
    "sg:province":"CA",
    "sg:tags":[
        "packaging"
    ],
    "wof:name":"Benson Packaging",
    "wof:placetype":"venue"
},
  "geometry": {"coordinates":[-117.897911,33.806872],"type":"Point"}
}