{
  "type": "Feature",
  "properties": {
    "addr:full":"9305 Galston Dr Santee CA 92071",
    "addr:housenumber":"9305",
    "addr:postcode":"92071",
    "addr:street":"Galston Dr",
    "iso:country":"US",
    "sg:address":"9305 Galston Dr",
    "sg:city":"Santee",
    "sg:classifiers":[
        {
            "category":"Building & Trades",
            "subcategory":"Construction",
            "type":"Services"
        }
    ],
    "sg:phone":"+1 619 442 1559",
    "sg:postcode":"92071",
    "sg:province":"CA",
    "sg:tags":[
        "contractor"
    ],
    "wof:name":"Harborside Construction",
    "wof:placetype":"venue"
},
  "geometry": {"coordinates":[-117.000731,32.857375],"type":"Point"}
}