{
  "type": "Feature",
  "properties": {
    "addr:full":"1444 Blue Bird Canyon Dr Laguna Beach CA 92651",
    "addr:housenumber":"1444",
    "addr:postcode":"92651",
    "addr:street":"Blue Bird Canyon Dr",
    "iso:country":"US",
    "sg:address":"1444 Blue Bird Canyon Dr",
    "sg:city":"Laguna Beach",
    "sg:classifiers":[
        {
            "category":"Building & Trades",
            "subcategory":"Construction",
            "type":"Services"
        }
    ],
    "sg:phone":"+1 949 494 5551",
    "sg:postcode":"92651",
    "sg:province":"CA",
    "sg:tags":[
        "house",
        "nonresidential"
    ],
    "wof:name":"Larry W Laird Designer Builder",
    "wof:placetype":"venue"
},
  "geometry": {"coordinates":[-117.76151900000001,33.538597],"type":"Point"}
}