{
  "type": "Feature",
  "properties": {
    "iso:country":"US",
    "sg:address":"80 Cabrillo Hwy N",
    "sg:city":"Half Moon Bay",
    "sg:classifiers":[
        {
            "category":"Retail",
            "subcategory":"Laundry & Dry Cleaning",
            "type":"Services"
        }
    ],
    "sg:phone":"+1 650 726 0208",
    "sg:postcode":"94019",
    "sg:province":"CA",
    "sg:tags":[
        "cleaners"
    ],
    "wof:name":"Greenhouse Cleaners",
    "wof:placetype":"venue"
},
  "geometry": {"coordinates":[-122.433787,37.466257],"type":"Point"}
}