{
  "type": "Feature",
  "properties": {
    "addr:full":"3498 Mt Diablo Blvd Lafayette CA 94549",
    "addr:housenumber":"3498",
    "addr:postcode":"94549",
    "addr:street":"Mt Diablo Blvd",
    "iso:country":"US",
    "sg:address":"3498 Mt Diablo Blvd",
    "sg:city":"Lafayette",
    "sg:classifiers":[
        {
            "category":"Banks & Credit Unions",
            "subcategory":"Bank",
            "type":"Services"
        }
    ],
    "sg:phone":"+1 925 283 1504",
    "sg:postcode":"94549",
    "sg:province":"CA",
    "sg:tags":[
        "federally",
        "chartered"
    ],
    "sg:website":"www.newworldfcu.com",
    "wof:name":"Telesis Community Credit Uni",
    "wof:placetype":"venue"
},
  "geometry": {"coordinates":[-122.113648,37.892713],"type":"Point"}
}