{
  "type": "Feature",
  "properties": {
    "iso:country":"US",
    "sg:address":"6315 Watt Ave",
    "sg:city":"North Highlands",
    "sg:classifiers":[
        {
            "category":"Autos & Motor Vehicles",
            "subcategory":"Auto Supplies",
            "type":"Retail Goods"
        }
    ],
    "sg:phone":"+1 916 344 8100",
    "sg:postcode":"95660",
    "sg:province":"CA",
    "sg:tags":[
        "tire"
    ],
    "wof:name":"Smog & Diagnostic 2000",
    "wof:placetype":"venue"
},
  "geometry": {"coordinates":[-121.38294999999999,38.680674],"type":"Point"}
}