{
  "type": "Feature",
  "properties": {
    "iso:country":"US",
    "sg:address":"6464 W Sunset Blvd",
    "sg:city":"Los Angeles",
    "sg:classifiers":[
        {
            "category":"Arts & Performance",
            "subcategory":"Theater",
            "type":"Entertainment"
        }
    ],
    "sg:phone":"+1 323 962 3686",
    "sg:postcode":"90028",
    "sg:province":"CA",
    "sg:tags":[
        "bureau"
    ],
    "wof:name":"Emerald Talent Group",
    "wof:placetype":"venue"
},
  "geometry": {"coordinates":[-118.33156,34.097986],"type":"Point"}
}