{
  "type": "Feature",
  "properties": {
    "iso:country":"US",
    "sg:address":"158 Kennedy Ln",
    "sg:city":"Healdsburg",
    "sg:classifiers":[
        {
            "category":"Wholesale",
            "subcategory":"Machinery & Supplies",
            "type":"Manufacturing & Wholesale Goods"
        }
    ],
    "sg:phone":"+1 707 431 2888",
    "sg:postcode":"95448",
    "sg:province":"CA",
    "sg:tags":[
        "salon",
        "beauty"
    ],
    "wof:name":"Brandaus' Edgeworks",
    "wof:placetype":"venue"
},
  "geometry": {"coordinates":[-122.862858,38.601071],"type":"Point"}
}