{
  "type": "Feature",
  "properties": {
    "addr:full":"9901 Rosedale Hwy Bakersfield CA 93312",
    "addr:housenumber":"9901",
    "addr:postcode":"93312",
    "addr:street":"Rosedale Hwy",
    "iso:country":"US",
    "sg:address":"9901 Rosedale Hwy",
    "sg:city":"Bakersfield",
    "sg:classifiers":[
        {
            "category":"Health Services",
            "subcategory":"Doctor",
            "type":"Services"
        }
    ],
    "sg:phone":"+1 661 587 9596",
    "sg:postcode":"93312",
    "sg:province":"CA",
    "sg:tags":[
        "dentist"
    ],
    "wof:name":"Calloway Family Dentistry",
    "wof:placetype":"venue"
},
  "geometry": {"coordinates":[-119.113524,35.383401],"type":"Point"}
}