{
  "type": "Feature",
  "properties": {
    "addr:full":"1645 Armstrong Ct Concord CA 94521",
    "addr:housenumber":"1645",
    "addr:postcode":"94521",
    "addr:street":"Armstrong Ct",
    "iso:country":"US",
    "sg:address":"1645 Armstrong Ct",
    "sg:city":"Concord",
    "sg:classifiers":[
        {
            "category":"Communications",
            "type":"Services"
        }
    ],
    "sg:phone":"+1 925 691 7333",
    "sg:postcode":"94521",
    "sg:province":"CA",
    "sg:tags":[
        "communication"
    ],
    "wof:name":"Jat Communications",
    "wof:placetype":"venue"
},
  "geometry": {"coordinates":[-121.98927999999999,37.968023],"type":"Point"}
}