{
  "type": "Feature",
  "properties": {
    "iso:country":"US",
    "sg:address":"933 E Ave",
    "sg:city":"National City",
    "sg:classifiers":[
        {
            "category":"Social Services",
            "subcategory":"Child Care",
            "type":"Services"
        }
    ],
    "sg:phone":"+1 619 474 1670",
    "sg:postcode":"91950",
    "sg:province":"CA",
    "sg:tags":[
        "elementary",
        "kindergarten",
        "school",
        "academic"
    ],
    "wof:name":"Central Preschool",
    "wof:placetype":"venue"
},
  "geometry": {"coordinates":[-117.100998,32.676102],"type":"Point"}
}