{
  "type": "Feature",
  "properties": {
    "addr:full":"28712 Breckenridge Dr Laguna Niguel CA 92677",
    "addr:housenumber":"28712",
    "addr:postcode":"92677",
    "addr:street":"Breckenridge Dr",
    "iso:country":"US",
    "sg:address":"28712 Breckenridge Dr",
    "sg:city":"Laguna Niguel",
    "sg:classifiers":[
        {
            "category":"Banks & Credit Unions",
            "subcategory":"Bank",
            "type":"Services"
        }
    ],
    "sg:phone":"+1 949 521 0537",
    "sg:postcode":"92677",
    "sg:province":"CA",
    "sg:tags":[
        "loan",
        "real estate"
    ],
    "wof:name":"First Continental Mortgage",
    "wof:placetype":"venue"
},
  "geometry": {"coordinates":[-117.687465,33.545999],"type":"Point"}
}