{
  "type": "Feature",
  "properties": {
    "addr:full":"8313 W 3rd St Los Angeles CA 90048",
    "addr:housenumber":"8313",
    "addr:postcode":"90048",
    "addr:street":"W 3Rd St",
    "iso:country":"US",
    "sg:address":"8313 W 3rd St",
    "sg:city":"Los Angeles",
    "sg:classifiers":[
        {
            "category":"Shopping",
            "subcategory":"Used Merchandise",
            "type":"Retail Goods"
        }
    ],
    "sg:phone":"+1 818 500 8383",
    "sg:postcode":"90048",
    "sg:province":"CA",
    "sg:tags":[
        "carpet",
        "dealer",
        "rug"
    ],
    "wof:name":"Joseph Toorian Antique Carpets",
    "wof:placetype":"venue"
},
  "geometry": {"coordinates":[-118.37067500000001,34.072805],"type":"Point"}
}