{
  "type": "Feature",
  "properties": {
    "iso:country":"US",
    "sg:address":"2454 Lincoln Blvd",
    "sg:city":"Venice",
    "sg:classifiers":[
        {
            "category":"Retail",
            "subcategory":"Car Wash",
            "type":"Services"
        }
    ],
    "sg:phone":"+1 310 839 3949",
    "sg:postcode":"90291",
    "sg:province":"CA",
    "sg:tags":[
        "polishing",
        "washing"
    ],
    "wof:name":"Millennium Car Sales & Wash",
    "wof:placetype":"venue"
},
  "geometry": {"coordinates":[-118.45036500000001,33.993],"type":"Point"}
}