{
  "type": "Feature",
  "properties": {
    "addr:full":"138 N Brand Blvd Glendale CA 91203",
    "addr:housenumber":"138",
    "addr:postcode":"91203",
    "addr:street":"N Brand Blvd",
    "iso:country":"US",
    "sg:address":"138 N Brand Blvd",
    "sg:city":"Glendale",
    "sg:classifiers":[
        {
            "category":"Health Services",
            "subcategory":"Doctor",
            "type":"Services"
        }
    ],
    "sg:phone":"+1 818 500 9708",
    "sg:postcode":"91203",
    "sg:province":"CA",
    "wof:name":"Lilit Yegiazaryan MD",
    "wof:placetype":"venue"
},
  "geometry": {"coordinates":[-118.254768,34.14697],"type":"Point"}
}