{
  "type": "Feature",
  "properties": {
    "iso:country":"US",
    "sg:address":"8631 W 3D",
    "sg:city":"Beverly Hills",
    "sg:classifiers":[
        {
            "category":"Health Services",
            "subcategory":"Doctor",
            "type":"Services"
        }
    ],
    "sg:phone":"+1 310 659 9075",
    "sg:postcode":"90210",
    "sg:province":"CA",
    "sg:tags":[
        "dermatologist"
    ],
    "wof:name":"Mekelburg Brian P MD",
    "wof:placetype":"venue"
},
  "geometry": {"coordinates":[-118.408997,34.0993],"type":"Point"}
}