{
  "type": "Feature",
  "properties": {
    "iso:country":"US",
    "sg:address":"1540 S Imperial Ave",
    "sg:city":"El Centro",
    "sg:classifiers":[
        {
            "category":"Health Services",
            "subcategory":"Doctor",
            "type":"Services"
        }
    ],
    "sg:phone":"+1 760 352 2773",
    "sg:postcode":"92243",
    "sg:province":"CA",
    "sg:tags":[
        "dentist"
    ],
    "wof:name":"Clock Tower Dental Care",
    "wof:placetype":"venue"
},
  "geometry": {"coordinates":[-115.569703,32.779902],"type":"Point"}
}