{
  "type": "Feature",
  "properties": {
    "addr:full":"1420 N Glassell St Orange CA 92867",
    "addr:housenumber":"1420",
    "addr:postcode":"92867",
    "addr:street":"N Glassell St",
    "iso:country":"US",
    "sg:address":"1420 N Glassell St",
    "sg:city":"Orange",
    "sg:classifiers":[
        {
            "category":"Wholesale",
            "subcategory":"Machinery & Supplies",
            "type":"Manufacturing & Wholesale Goods"
        }
    ],
    "sg:phone":"+1 714 628 8737",
    "sg:postcode":"92867",
    "sg:province":"CA",
    "sg:tags":[
        "machine",
        "shredding",
        "paper"
    ],
    "wof:name":"Secure Shredders",
    "wof:placetype":"venue"
},
  "geometry": {"coordinates":[-117.853039,33.811568],"type":"Point"}
}