{
  "type": "Feature",
  "properties": {
    "iso:country":"US",
    "sg:address":"23595 Moulton Pkwy",
    "sg:city":"Laguna Hills",
    "sg:classifiers":[
        {
            "category":"Deli",
            "type":"Food & Drink"
        },
        {
            "category":"Restaurant",
            "type":"Food & Drink"
        }
    ],
    "sg:phone":"+1 949 770 1818",
    "sg:postcode":"92653",
    "sg:province":"CA",
    "sg:tags":[
        "kosher"
    ],
    "sg:website":"www.kosherbite.com",
    "wof:name":"Kosher Bite Deli & Meat Market",
    "wof:placetype":"venue"
},
  "geometry": {"coordinates":[-117.731649,33.620101],"type":"Point"}
}