{
  "type": "Feature",
  "properties": {
    "addr:full":"1247 Benton St Santa Clara CA 95050",
    "addr:housenumber":"1247",
    "addr:postcode":"95050",
    "addr:street":"Benton St",
    "iso:country":"US",
    "sg:address":"1247 Benton St",
    "sg:city":"Santa Clara",
    "sg:classifiers":[
        {
            "category":"Social Services",
            "subcategory":"Child Care",
            "type":"Services"
        }
    ],
    "sg:phone":"+1 408 296 7442",
    "sg:postcode":"95050",
    "sg:province":"CA",
    "sg:tags":[
        "day"
    ],
    "wof:name":"Kidsville Preschool & Day Care Center",
    "wof:placetype":"venue"
},
  "geometry": {"coordinates":[-121.947998,37.349499],"type":"Point"}
}