{
  "type": "Feature",
  "properties": {
    "addr:full":"305 Caledonia St Sausalito CA 94965",
    "addr:housenumber":"305",
    "addr:postcode":"94965",
    "addr:street":"Caledonia St",
    "iso:country":"US",
    "sg:address":"305 Caledonia St",
    "sg:city":"Sausalito",
    "sg:classifiers":[
        {
            "category":"Insurance",
            "subcategory":"Insurance Agent",
            "type":"Services"
        },
        {
            "category":"Insurance",
            "subcategory":"Hazard Insurance",
            "type":"Services"
        },
        {
            "category":"Insurance",
            "subcategory":"Title Insurance",
            "type":"Services"
        },
        {
            "category":"Insurance",
            "subcategory":"Life Insurance",
            "type":"Services"
        }
    ],
    "sg:phone":"+1 415 331 5763",
    "sg:postcode":"94965",
    "sg:province":"CA",
    "sg:tags":[
        "business",
        "auto",
        "commercial",
        "homeowner",
        "motorcycle",
        "renter"
    ],
    "wof:name":"Allstate Insurance Company - Tom Ryan",
    "wof:placetype":"venue"
},
  "geometry": {"coordinates":[-122.487134,37.859557],"type":"Point"}
}