{
  "type": "Feature",
  "properties": {
    "iso:country":"US",
    "sg:address":"1199 Bismark Way",
    "sg:city":"Costa Mesa",
    "sg:classifiers":[
        {
            "category":"Social Services",
            "subcategory":"Job Training",
            "type":"Services"
        }
    ],
    "sg:phone":"+1 714 540 6160",
    "sg:postcode":"92626",
    "sg:province":"CA",
    "wof:name":"Communications Works",
    "wof:placetype":"venue"
},
  "geometry": {"coordinates":[-117.90604,33.68456],"type":"Point"}
}