{
  "type": "Feature",
  "properties": {
    "iso:country":"US",
    "sg:address":"4372 Walnut Ave",
    "sg:city":"Long Beach",
    "sg:classifiers":[
        {
            "category":"Professional",
            "type":"Services"
        }
    ],
    "sg:phone":"+1 562 964 0368",
    "sg:postcode":"90807",
    "sg:province":"CA",
    "wof:name":"Xsentrix",
    "wof:placetype":"venue"
},
  "geometry": {"coordinates":[-118.171862,33.837867],"type":"Point"}
}