{
  "type": "Feature",
  "properties": {
    "addr:full":"2131 Lyric Ave Los Angeles CA 90027",
    "addr:housenumber":"2131",
    "addr:postcode":"90027",
    "addr:street":"Lyric Ave",
    "iso:country":"US",
    "sg:address":"2131 Lyric Ave",
    "sg:city":"Los Angeles",
    "sg:classifiers":[
        {
            "category":"Manufacturing",
            "subcategory":"Printing",
            "type":"Manufacturing & Wholesale Goods"
        }
    ],
    "sg:phone":"+1 323 666 3311",
    "sg:postcode":"90027",
    "sg:province":"CA",
    "sg:tags":[
        "book",
        "publishing"
    ],
    "wof:name":"Feral House Inc",
    "wof:placetype":"venue"
},
  "geometry": {"coordinates":[-118.274061,34.101152],"type":"Point"}
}