{
  "type": "Feature",
  "properties": {
    "addr:full":"15151 National Ave Los Gatos CA 95032",
    "addr:housenumber":"15151",
    "addr:postcode":"95032",
    "addr:street":"National Ave",
    "iso:country":"US",
    "sg:address":"15151 National Ave",
    "sg:city":"Los Gatos",
    "sg:classifiers":[
        {
            "category":"Health Services",
            "subcategory":"Doctor",
            "type":"Services"
        }
    ],
    "sg:phone":"+1 408 356 4668",
    "sg:postcode":"95032",
    "sg:province":"CA",
    "wof:name":"Imig Mary MD",
    "wof:placetype":"venue"
},
  "geometry": {"coordinates":[-121.949997,37.245098],"type":"Point"}
}