{
  "type": "Feature",
  "properties": {
    "addr:full":"73877 Amboy Rd Twentynine Palms CA 92277",
    "addr:housenumber":"73877",
    "addr:postcode":"92277",
    "addr:street":"Amboy Rd",
    "iso:country":"US",
    "sg:address":"73877 Amboy Rd",
    "sg:city":"Twentynine Palms",
    "sg:classifiers":[
        {
            "category":"Utilities",
            "subcategory":"Refuse",
            "type":"Services"
        }
    ],
    "sg:phone":"+1 760 367 9168",
    "sg:postcode":"92277",
    "sg:province":"CA",
    "sg:tags":[
        "garbage",
        "collection"
    ],
    "sg:website":"www.wm.com",
    "wof:name":"Sierra Environmental Svc",
    "wof:placetype":"venue"
},
  "geometry": {"coordinates":[-116.046729,34.164769],"type":"Point"}
}