{
  "type": "Feature",
  "properties": {
    "addr:full":"1300 Clay St Suite 600 Oakland CA 94612",
    "addr:housenumber":"1300",
    "addr:postcode":"94612",
    "addr:street":"Clay St Suite 600",
    "iso:country":"US",
    "sg:address":"1300 Clay St Suite 600",
    "sg:city":"Oakland",
    "sg:classifiers":[
        {
            "category":"Professional",
            "subcategory":"Lawyer & Legal Services",
            "type":"Services"
        }
    ],
    "sg:phone":"+1 510 464 8034",
    "sg:postcode":"94612",
    "sg:province":"CA",
    "sg:tags":[
        "litigation",
        "attorney",
        "law",
        "estate",
        "personal",
        "labor",
        "tort",
        "planning",
        "injury",
        "employment",
        "insurance"
    ],
    "wof:name":"Wilde , Daniel P. - Law Offices Of Steve",
    "wof:placetype":"venue"
},
  "geometry": {"coordinates":[-122.274036,37.804586],"type":"Point"}
}