{
  "type": "Feature",
  "properties": {
    "iso:country":"US",
    "sg:address":"4901 Clark Rd",
    "sg:city":"Paradise",
    "sg:classifiers":[
        {
            "category":"Social Services",
            "subcategory":"Adult Care",
            "type":"Services"
        }
    ],
    "sg:phone":"+1 530 872 0350",
    "sg:postcode":"95969",
    "sg:province":"CA",
    "sg:tags":[
        "home",
        "residential"
    ],
    "wof:name":"Gerhardt Care Home",
    "wof:placetype":"venue"
},
  "geometry": {"coordinates":[-121.612852,39.728269],"type":"Point"}
}