{
  "type": "Feature",
  "properties": {
    "iso:country":"US",
    "sg:address":"9795 Bus Park Dr",
    "sg:city":"Sacramento",
    "sg:classifiers":[
        {
            "category":"Real Estate",
            "subcategory":"Real Estate Agent",
            "type":"Services"
        }
    ],
    "sg:phone":"+1 408 252 8124",
    "sg:postcode":"95827",
    "sg:province":"CA",
    "wof:name":"Hillsdale Village",
    "wof:placetype":"venue"
},
  "geometry": {"coordinates":[-121.330043,38.570486],"type":"Point"}
}