{
  "type": "Feature",
  "properties": {
    "iso:country":"US",
    "sg:address":"468 Rivergate Way",
    "sg:city":"Sacramento",
    "sg:classifiers":[
        {
            "category":"Manufacturing",
            "subcategory":"Building Materials",
            "type":"Manufacturing & Wholesale Goods"
        },
        {
            "category":"Home & Garden",
            "subcategory":"Carpets & Floor Coverings",
            "type":"Retail Goods"
        }
    ],
    "sg:phone":"+1 916 752 9977",
    "sg:postcode":"95831",
    "sg:province":"CA",
    "sg:tags":[
        "materials-wholesale",
        "manufacturer"
    ],
    "wof:name":"Ellison Paul Floor Covering",
    "wof:placetype":"venue"
},
  "geometry": {"coordinates":[-121.54404599999999,38.496143],"type":"Point"}
}