{
  "type": "Feature",
  "properties": {
    "iso:country":"US",
    "sg:address":"1535 S Novato Blvd",
    "sg:city":"Novato",
    "sg:classifiers":[
        {
            "category":"Travel",
            "subcategory":"Travel Agent",
            "type":"Entertainment"
        }
    ],
    "sg:phone":"+1 415 897 4405",
    "sg:postcode":"94947",
    "sg:province":"CA",
    "sg:tags":[
        "agency",
        "bureau"
    ],
    "sg:website":"www.travelworks4u.com",
    "wof:name":"Travelworks",
    "wof:placetype":"venue"
},
  "geometry": {"coordinates":[-122.570112,38.097925],"type":"Point"}
}