{
  "type": "Feature",
  "properties": {
    "addr:full":"3049 Wheeler St Berkeley CA 94705",
    "addr:housenumber":"3049",
    "addr:postcode":"94705",
    "addr:street":"Wheeler St",
    "iso:country":"US",
    "sg:address":"3049 Wheeler St",
    "sg:city":"Berkeley",
    "sg:classifiers":[
        {
            "category":"Building & Trades",
            "subcategory":"Construction",
            "type":"Services"
        }
    ],
    "sg:phone":"+1 510 843 3793",
    "sg:postcode":"94705",
    "sg:province":"CA",
    "sg:tags":[
        "house"
    ],
    "wof:name":"Toucan Remodelling",
    "wof:placetype":"venue"
},
  "geometry": {"coordinates":[-122.264118,37.853548],"type":"Point"}
}