{
  "type": "Feature",
  "properties": {
    "iso:country":"US",
    "sg:address":"1815 S Centre City Pkwy",
    "sg:city":"Escondido",
    "sg:classifiers":[
        {
            "category":"Banks & Credit Unions",
            "subcategory":"Bank",
            "type":"Services"
        }
    ],
    "sg:phone":"+1 760 796 6320",
    "sg:postcode":"92025",
    "sg:province":"CA",
    "sg:tags":[
        "escrow"
    ],
    "wof:name":"Pickford Realty Escrow Div",
    "wof:placetype":"venue"
},
  "geometry": {"coordinates":[-117.075435,33.103043],"type":"Point"}
}