{
  "type": "Feature",
  "properties": {
    "iso:country":"US",
    "sg:address":"729 California St",
    "sg:city":"Stockton",
    "sg:classifiers":[
        {
            "category":"Social Services",
            "type":"Services"
        }
    ],
    "sg:phone":"+1 209 929 6700",
    "sg:postcode":"95202",
    "sg:province":"CA",
    "sg:tags":[
        "youth",
        "organization",
        "center"
    ],
    "sg:website":"www.cppainc.org",
    "wof:name":"Center For Positive Prevention",
    "wof:placetype":"venue"
},
  "geometry": {"coordinates":[-121.28673499999999,37.961236],"type":"Point"}
}