{
  "type": "Feature",
  "properties": {
    "addr:full":"14361 State Rte 128 Boonville CA 95415",
    "addr:housenumber":"14361",
    "addr:postcode":"95415",
    "addr:street":"State Rte 128",
    "iso:country":"US",
    "sg:address":"14361 State Rte 128",
    "sg:city":"Boonville",
    "sg:classifiers":[
        {
            "category":"Professional",
            "type":"Services"
        }
    ],
    "sg:phone":"+1 707 895 3426",
    "sg:postcode":"95415",
    "sg:province":"CA",
    "wof:name":"Neil and Kathalene Kephart",
    "wof:placetype":"venue"
},
  "geometry": {"coordinates":[-123.366562,39.008448],"type":"Point"}
}