{
  "type": "Feature",
  "properties": {
    "iso:country":"US",
    "sg:address":"2166 S Atlantic Blvd",
    "sg:city":"City Of Commerce",
    "sg:classifiers":[
        {
            "category":"Government",
            "subcategory":"Office",
            "type":"Public Place"
        }
    ],
    "sg:phone":"+1 323 307 9907",
    "sg:postcode":"90040",
    "sg:province":"CA",
    "sg:tags":[
        "armed",
        "force",
        "recruiting"
    ],
    "wof:name":"Boyd & Assoc",
    "wof:placetype":"venue"
},
  "geometry": {"coordinates":[-118.16285499999999,34.006237],"type":"Point"}
}