{
  "type": "Feature",
  "properties": {
    "addr:full":"755 Sansome St San Francisco CA 94111",
    "addr:housenumber":"755",
    "addr:postcode":"94111",
    "addr:street":"Sansome St",
    "iso:country":"US",
    "sg:address":"755 Sansome St",
    "sg:city":"San Francisco",
    "sg:classifiers":[
        {
            "category":"Professional",
            "subcategory":"Management & Consulting",
            "type":"Services"
        }
    ],
    "sg:phone":"+1 415 956 4300",
    "sg:postcode":"94111",
    "sg:province":"CA",
    "sg:tags":[
        "town",
        "city",
        "regional",
        "planner"
    ],
    "wof:name":"Dyett & Bhatia Urban & Rgnl",
    "wof:placetype":"venue"
},
  "geometry": {"coordinates":[-122.402089,37.797341],"type":"Point"}
}