{
  "type": "Feature",
  "properties": {
    "addr:full":"1607 Michael Ave Stockton CA 95206",
    "addr:housenumber":"1607",
    "addr:postcode":"95206",
    "addr:street":"Michael Ave",
    "iso:country":"US",
    "sg:address":"1607 Michael Ave",
    "sg:city":"Stockton",
    "sg:classifiers":[
        {
            "category":"Place Of Worship",
            "subcategory":"Church",
            "type":"Public Place"
        }
    ],
    "sg:phone":"+1 209 932 1575",
    "sg:postcode":"95206",
    "sg:province":"CA",
    "sg:tags":[
        "churches-non-denominational"
    ],
    "wof:name":"Horton Ministries",
    "wof:placetype":"venue"
},
  "geometry": {"coordinates":[-121.258764,37.923697],"type":"Point"}
}