{
  "type": "Feature",
  "properties": {
    "addr:full":"608 W Hillcrest Blvd Inglewood CA 90301",
    "addr:housenumber":"608",
    "addr:postcode":"90301",
    "addr:street":"W Hillcrest Blvd",
    "iso:country":"US",
    "sg:address":"608 W Hillcrest Blvd",
    "sg:city":"Inglewood",
    "sg:classifiers":[
        {
            "category":"Professional",
            "subcategory":"Management & Consulting",
            "type":"Services"
        }
    ],
    "sg:phone":"+1 310 412 3973",
    "sg:postcode":"90301",
    "sg:province":"CA",
    "sg:tags":[
        "trading",
        "internet"
    ],
    "wof:name":"Santa Monica Bay Trading Co",
    "wof:placetype":"venue"
},
  "geometry": {"coordinates":[-118.366899,33.956486],"type":"Point"}
}