{
  "type": "Feature",
  "properties": {
    "iso:country":"US",
    "sg:address":"24543 Freeport Dr",
    "sg:city":"Moreno Valley",
    "sg:classifiers":[
        {
            "category":"Building & Trades",
            "subcategory":"Cleaning & Sanitation",
            "type":"Services"
        }
    ],
    "sg:phone":"+1 951 485 8229",
    "sg:postcode":"92551",
    "sg:province":"CA",
    "sg:tags":[
        "ventilating",
        "system"
    ],
    "wof:name":"A-1 Air Duct Cleaning",
    "wof:placetype":"venue"
},
  "geometry": {"coordinates":[-117.231575,33.878388],"type":"Point"}
}