{
  "type": "Feature",
  "properties": {
    "addr:full":"345 N la Cadena Dr Colton CA 92324",
    "addr:housenumber":"345",
    "addr:postcode":"92324",
    "addr:street":"N La Cadena Dr",
    "iso:country":"US",
    "sg:address":"345 N la Cadena Dr",
    "sg:city":"Colton",
    "sg:classifiers":[
        {
            "category":"Shopping",
            "subcategory":"Clothing, Apparel, & Fashions",
            "type":"Retail Goods"
        }
    ],
    "sg:phone":"+1 909 825 0868",
    "sg:postcode":"92324",
    "sg:province":"CA",
    "sg:tags":[
        "men's",
        "clothing",
        "boys'"
    ],
    "wof:name":"Gentlemen's Exclusive Men's Wear",
    "wof:placetype":"venue"
},
  "geometry": {"coordinates":[-117.323986,34.068455],"type":"Point"}
}