{
  "type": "Feature",
  "properties": {
    "addr:full":"14540 Sylvan St Van Nuys CA 91411",
    "addr:housenumber":"14540",
    "addr:postcode":"91411",
    "addr:street":"Sylvan St",
    "iso:country":"US",
    "sg:address":"14540 Sylvan St",
    "sg:city":"Van Nuys",
    "sg:classifiers":[
        {
            "category":"Professional",
            "subcategory":"Advertising",
            "type":"Services"
        }
    ],
    "sg:phone":"+1 818 779 8866",
    "sg:postcode":"91411",
    "sg:province":"CA",
    "sg:tags":[
        "mailing",
        "shipping"
    ],
    "wof:name":"BTC Inc",
    "wof:placetype":"venue"
},
  "geometry": {"coordinates":[-118.450159,34.184578],"type":"Point"}
}