{
  "type": "Feature",
  "properties": {
    "iso:country":"US",
    "sg:address":"1150 E 4th St",
    "sg:city":"Long Beach",
    "sg:classifiers":[
        {
            "category":"Government",
            "subcategory":"Office",
            "type":"Public Place"
        }
    ],
    "sg:phone":"+1 562 570 3231",
    "sg:postcode":"90802",
    "sg:province":"CA",
    "sg:tags":[
        "conservation"
    ],
    "wof:name":"Community Outreach",
    "wof:placetype":"venue"
},
  "geometry": {"coordinates":[-118.176539,33.771635],"type":"Point"}
}