{
  "type": "Feature",
  "properties": {
    "iso:country":"US",
    "sg:address":"435 Market St",
    "sg:city":"Colusa",
    "sg:classifiers":[
        {
            "category":"Communications",
            "subcategory":"Radio Station",
            "type":"Services"
        }
    ],
    "sg:phone":"+1 530 458 8851",
    "sg:postcode":"95932",
    "sg:province":"CA",
    "sg:tags":[
        "broadcast"
    ],
    "wof:name":"Ktmx",
    "wof:placetype":"venue"
},
  "geometry": {"coordinates":[-122.007636,39.213878],"type":"Point"}
}