{
  "type": "Feature",
  "properties": {
    "iso:country":"US",
    "sg:address":"7672 Edinger Ave",
    "sg:city":"Huntington Beach",
    "sg:classifiers":[
        {
            "category":"Wholesale",
            "subcategory":"Home Furnishings",
            "type":"Manufacturing & Wholesale Goods"
        }
    ],
    "sg:phone":"+1 714 375 9939",
    "sg:postcode":"92647",
    "sg:province":"CA",
    "sg:tags":[
        "blind",
        "shade"
    ],
    "wof:name":"3 Day Blinds & More",
    "wof:placetype":"venue"
},
  "geometry": {"coordinates":[-117.995003,33.73],"type":"Point"}
}