{
  "type": "Feature",
  "properties": {
    "iso:country":"US",
    "sg:address":"769 S Kern Ave",
    "sg:city":"Los Angeles",
    "sg:classifiers":[
        {
            "category":"Personal",
            "subcategory":"Beauty Salon",
            "type":"Services"
        }
    ],
    "sg:phone":"+1 323 263 2445",
    "sg:postcode":"90022",
    "sg:province":"CA",
    "wof:name":"D'Gala Family Beauty Salon",
    "wof:placetype":"venue"
},
  "geometry": {"coordinates":[-118.165616,34.022958],"type":"Point"}
}