{
  "type": "Feature",
  "properties": {
    "addr:full":"2 Princess St Sausalito CA 94965",
    "addr:housenumber":"2",
    "addr:postcode":"94965",
    "addr:street":"Princess St",
    "iso:country":"US",
    "sg:address":"2 Princess St",
    "sg:city":"Sausalito",
    "sg:classifiers":[
        {
            "category":"Shopping",
            "subcategory":"Jewelry",
            "type":"Retail Goods"
        }
    ],
    "sg:phone":"+1 415 332 8821",
    "sg:postcode":"94965",
    "sg:province":"CA",
    "sg:tags":[
        "watch"
    ],
    "wof:name":"Time After Time",
    "wof:placetype":"venue"
},
  "geometry": {"coordinates":[-122.479434,37.85487],"type":"Point"}
}