{
  "type": "Feature",
  "properties": {
    "addr:full":"7011 Sylvan Rd Citrus Heights CA 95610",
    "addr:housenumber":"7011",
    "addr:postcode":"95610",
    "addr:street":"Sylvan Rd",
    "iso:country":"US",
    "sg:address":"7011 Sylvan Rd",
    "sg:city":"Citrus Heights",
    "sg:classifiers":[
        {
            "category":"Professional",
            "subcategory":"Lawyer & Legal Services",
            "type":"Services"
        }
    ],
    "sg:phone":"+1 916 969 6222",
    "sg:postcode":"95610",
    "sg:province":"CA",
    "wof:name":"Simonetta Lisa A Atty",
    "wof:placetype":"venue"
},
  "geometry": {"coordinates":[-121.29044399999999,38.692986],"type":"Point"}
}