{
  "type": "Feature",
  "properties": {
    "iso:country":"US",
    "sg:address":"12002 Wintercrest Dr",
    "sg:city":"Lakeside",
    "sg:classifiers":[
        {
            "category":"Professional",
            "type":"Services"
        }
    ],
    "sg:phone":"+1 619 334 1100",
    "sg:postcode":"92040",
    "sg:province":"CA",
    "sg:tags":[
        "establishment"
    ],
    "wof:name":"Access Node WNTR Test Line",
    "wof:placetype":"venue"
},
  "geometry": {"coordinates":[-116.932953,32.852199],"type":"Point"}
}