{
  "type": "Feature",
  "properties": {
    "addr:full":"4301 Foster Ave Bakersfield CA 93308",
    "addr:housenumber":"4301",
    "addr:postcode":"93308",
    "addr:street":"Foster Ave",
    "iso:country":"US",
    "sg:address":"4301 Foster Ave",
    "sg:city":"Bakersfield",
    "sg:classifiers":[
        {
            "category":"Home & Garden",
            "subcategory":"Building Materials",
            "type":"Retail Goods"
        }
    ],
    "sg:phone":"+1 661 323 5724",
    "sg:postcode":"93308",
    "sg:province":"CA",
    "wof:name":"Selectcrete Incorporated",
    "wof:placetype":"venue"
},
  "geometry": {"coordinates":[-119.049941,35.40028],"type":"Point"}
}