{
  "type": "Feature",
  "properties": {
    "addr:full":"2409 S Garfield Ave Monterey Park CA 91754",
    "addr:housenumber":"2409",
    "addr:postcode":"91754",
    "addr:street":"S Garfield Ave",
    "iso:country":"US",
    "sg:address":"2409 S Garfield Ave",
    "sg:city":"Monterey Park",
    "sg:classifiers":[
        {
            "category":"Utilities",
            "subcategory":"Mobile Phone",
            "type":"Services"
        }
    ],
    "sg:phone":"+1 323 346 3460",
    "sg:postcode":"91754",
    "sg:province":"CA",
    "sg:tags":[
        "communication",
        "radiotelephone"
    ],
    "wof:name":"J & A Wireless",
    "wof:placetype":"venue"
},
  "geometry": {"coordinates":[-118.130568,34.036503],"type":"Point"}
}