{
  "type": "Feature",
  "properties": {
    "iso:country":"US",
    "sg:address":"845 W El Camino Real",
    "sg:city":"Mountain View",
    "sg:classifiers":[
        {
            "category":"Retail",
            "subcategory":"Auto Repair",
            "type":"Services"
        }
    ],
    "sg:phone":"+1 650 961 0744",
    "sg:postcode":"94040",
    "sg:province":"CA",
    "wof:name":"Auto Experts & Specialists",
    "wof:placetype":"venue"
},
  "geometry": {"coordinates":[-122.084999,37.385799],"type":"Point"}
}