{
  "type": "Feature",
  "properties": {
    "addr:full":"887 Polaris Ave San Mateo CA 94404",
    "addr:housenumber":"887",
    "addr:postcode":"94404",
    "addr:street":"Polaris Ave",
    "iso:country":"US",
    "sg:address":"887 Polaris Ave",
    "sg:city":"San Mateo",
    "sg:classifiers":[
        {
            "category":"Building & Trades",
            "subcategory":"Landscaping Services",
            "type":"Services"
        }
    ],
    "sg:phone":"+1 650 571 8900",
    "sg:postcode":"94404",
    "sg:province":"CA",
    "wof:name":"Garden Service",
    "wof:placetype":"venue"
},
  "geometry": {"coordinates":[-122.276814,37.545548],"type":"Point"}
}