{
  "type": "Feature",
  "properties": {
    "iso:country":"US",
    "sg:address":"239 State St",
    "sg:city":"Los Altos",
    "sg:classifiers":[
        {
            "category":"Shopping",
            "subcategory":"Clothing, Apparel, & Fashions",
            "type":"Retail Goods"
        }
    ],
    "sg:phone":"+1 650 948 1719",
    "sg:postcode":"94022",
    "sg:province":"CA",
    "sg:tags":[
        "riding",
        "equipment"
    ],
    "wof:name":"Tiedown Saddlery",
    "wof:placetype":"venue"
},
  "geometry": {"coordinates":[-122.11694199999999,37.379284],"type":"Point"}
}