{
  "type": "Feature",
  "properties": {
    "sfgov:dept":"7",
    "sfgov:deptname":"SF Unified School District (SFUSD)",
    "sfgov:facility_i":"0000060141",
    "sfgov:school_typ":"Early Education",
    "wof:categories":[
        "education_and_religion:education=school"
    ],
    "wof:name":"Taylor, E.R. Preschool",
    "wof:placetype":"venue"
},
  "geometry": {"coordinates":[-122.40735999833736,37.7274128375933],"type":"Point"}
}