{
  "type": "Feature",
  "properties": {
    "addr:full":"23857 Friar St Woodland Hills CA 91367",
    "addr:postcode":"23857;91367",
    "addr:street":"Friar St",
    "iso:country":"US",
    "sg:address":"23857 Friar St",
    "sg:city":"Woodland Hills",
    "sg:classifiers":[
        {
            "category":"Wholesale",
            "subcategory":"Non-durable Goods",
            "type":"Manufacturing & Wholesale Goods"
        },
        {
            "category":"Shopping",
            "subcategory":"Gifts & Souvenirs",
            "type":"Retail Goods"
        }
    ],
    "sg:phone":"+1 818 883 6771",
    "sg:postcode":"91367",
    "sg:province":"CA",
    "sg:tags":[
        "balloon",
        "durable",
        "artist"
    ],
    "wof:name":"Artistic Balloon & Flowers Co",
    "wof:placetype":"venue"
},
  "geometry": {"coordinates":[-118.645364,34.185663],"type":"Point"}
}