{
  "type": "Feature",
  "properties": {
    "iso:country":"US",
    "sg:address":"1623 3rd St",
    "sg:city":"Escalon",
    "sg:classifiers":[
        {
            "category":"Retail",
            "subcategory":"Auto Repair",
            "type":"Services"
        }
    ],
    "sg:phone":"+1 209 838 2111",
    "sg:postcode":"95320",
    "sg:province":"CA",
    "sg:tags":[
        "wrecker"
    ],
    "sg:website":"www.jjgs.com",
    "wof:name":"Escalon Towing",
    "wof:placetype":"venue"
},
  "geometry": {"coordinates":[-120.990015,37.79449],"type":"Point"}
}