{
  "type": "Feature",
  "properties": {
    "addr:full":"10562 Lowden St Stanton CA 90680",
    "addr:postcode":"10562;ca 90680",
    "addr:street":"Lowden St",
    "iso:country":"US",
    "sg:address":"10562 Lowden St",
    "sg:city":"Stanton",
    "sg:classifiers":[
        {
            "category":"Real Estate",
            "subcategory":"Real Estate Services",
            "type":"Services"
        },
        {
            "category":"Real Estate",
            "subcategory":"Real Estate Operator",
            "type":"Services"
        }
    ],
    "sg:phone":"+1 714 761 0230",
    "sg:postcode":"90680",
    "sg:province":"CA",
    "sg:tags":[
        "vacancy",
        "apartment",
        "rental",
        "listing"
    ],
    "wof:name":"Lowden Arms",
    "wof:placetype":"venue"
},
  "geometry": {"coordinates":[-118.006353,33.809002],"type":"Point"}
}