{
  "type": "Feature",
  "properties": {
    "iso:country":"US",
    "sg:address":"1251 Ave Chelsea",
    "sg:city":"Vista",
    "sg:classifiers":[
        {
            "category":"Wholesale",
            "subcategory":"Non-durable Goods",
            "type":"Manufacturing & Wholesale Goods"
        }
    ],
    "sg:phone":"+1 760 734 5975",
    "sg:postcode":"92081",
    "sg:province":"CA",
    "sg:tags":[
        "basket"
    ],
    "wof:name":"Jenna Baskets",
    "wof:placetype":"venue"
},
  "geometry": {"coordinates":[-117.233301,33.144853],"type":"Point"}
}