{
  "type": "Feature",
  "properties": {
    "addr:full":"68718 Perez Rd Cathedral City CA 92234",
    "addr:housenumber":"68718",
    "addr:postcode":"92234",
    "addr:street":"Perez Rd",
    "iso:country":"US",
    "sg:address":"68718 Perez Rd",
    "sg:city":"Cathedral City",
    "sg:classifiers":[
        {
            "category":"Building & Trades",
            "subcategory":"Cleaning & Sanitation",
            "type":"Services"
        }
    ],
    "sg:phone":"+1 760 324 2833",
    "sg:postcode":"92234",
    "sg:province":"CA",
    "sg:tags":[
        "maintenance"
    ],
    "wof:name":"MFT Products",
    "wof:placetype":"venue"
},
  "geometry": {"coordinates":[-116.46584199999999,33.784728],"type":"Point"}
}