{
  "type": "Feature",
  "properties": {
    "iso:country":"US",
    "sg:address":"15342 Hawthorne Blvd",
    "sg:city":"Lawndale",
    "sg:classifiers":[
        {
            "category":"Professional",
            "subcategory":"Lawyer & Legal Services",
            "type":"Services"
        }
    ],
    "sg:phone":"+1 626 285 8665",
    "sg:postcode":"90260",
    "sg:province":"CA",
    "sg:tags":[
        "attorney"
    ],
    "wof:name":"Legal Relief Remedio Legal",
    "wof:placetype":"venue"
},
  "geometry": {"coordinates":[-118.35229,33.891594],"type":"Point"}
}