{
  "type": "Feature",
  "properties": {
    "addr:full":"23655 Richfield Rd Corning CA 96021",
    "addr:housenumber":"23655",
    "addr:postcode":"96021",
    "addr:street":"Richfield Rd",
    "iso:country":"US",
    "sg:address":"23655 Richfield Rd",
    "sg:city":"Corning",
    "sg:classifiers":[
        {
            "category":"Manufacturing",
            "subcategory":"Buildings",
            "type":"Manufacturing & Wholesale Goods"
        },
        {
            "category":"Building & Trades",
            "subcategory":"Construction",
            "type":"Services"
        }
    ],
    "sg:phone":"+1 530 824 3559",
    "sg:postcode":"96021",
    "sg:province":"CA",
    "sg:tags":[
        "home",
        "builder",
        "contractor"
    ],
    "wof:name":"Earl Moore Construction",
    "wof:placetype":"venue"
},
  "geometry": {"coordinates":[-122.151067,39.971583],"type":"Point"}
}