{
  "type": "Feature",
  "properties": {
    "iso:country":"US",
    "sg:address":"7350 W Melrose Ave",
    "sg:city":"Los Angeles",
    "sg:classifiers":[
        {
            "category":"Ice Cream",
            "type":"Food & Drink"
        }
    ],
    "sg:phone":"+1 323 951 0008",
    "sg:postcode":"90036",
    "sg:province":"CA",
    "sg:tags":[
        "frozen",
        "yogurt"
    ],
    "sg:website":"www.yogotrend.com",
    "wof:name":"Yogo Frozen Yogurt",
    "wof:placetype":"venue"
},
  "geometry": {"coordinates":[-118.349994,34.0833],"type":"Point"}
}