{
  "type": "Feature",
  "properties": {
    "iso:country":"US",
    "sg:address":"1805 W 6th St",
    "sg:city":"Los Angeles",
    "sg:classifiers":[
        {
            "category":"Restaurant",
            "type":"Food & Drink"
        }
    ],
    "sg:phone":"+1 213 484 6252",
    "sg:postcode":"90057",
    "sg:province":"CA",
    "wof:name":"Burger King",
    "wof:placetype":"venue"
},
  "geometry": {"coordinates":[-118.271507,34.058061],"type":"Point"}
}