{
  "type": "Feature",
  "properties": {
    "addr:full":"2020 Christy Ln Del Mar CA 92014",
    "addr:housenumber":"2020",
    "addr:postcode":"92014",
    "addr:street":"Christy Ln",
    "iso:country":"US",
    "sg:address":"2020 Christy Ln",
    "sg:city":"Del Mar",
    "sg:classifiers":[
        {
            "category":"Professional",
            "subcategory":"Advertising",
            "type":"Services"
        }
    ],
    "sg:phone":"+1 858 481 8366",
    "sg:postcode":"92014",
    "sg:province":"CA",
    "sg:tags":[
        "counselor",
        "agency"
    ],
    "wof:name":"Benedict Group The",
    "wof:placetype":"venue"
},
  "geometry": {"coordinates":[-117.26456399999999,32.967764],"type":"Point"}
}