{
  "type": "Feature",
  "properties": {
    "addr:full":"5301 Office Park Dr Bakersfield CA 93309",
    "addr:housenumber":"5301",
    "addr:postcode":"93309",
    "addr:street":"Office Park Dr",
    "iso:country":"US",
    "sg:address":"5301 Office Park Dr",
    "sg:city":"Bakersfield",
    "sg:classifiers":[
        {
            "category":"Professional",
            "subcategory":"Business Services",
            "type":"Services"
        }
    ],
    "sg:phone":"+1 661 324 9998",
    "sg:postcode":"93309",
    "sg:province":"CA",
    "sg:tags":[
        "water",
        "treatment"
    ],
    "sg:website":"www.purifyingsystems.com",
    "wof:name":"Purifying Systems",
    "wof:placetype":"venue"
},
  "geometry": {"coordinates":[-119.060913,35.365847],"type":"Point"}
}