{
  "type": "Feature",
  "properties": {
    "iso:country":"US",
    "sg:address":"1408 Sassafras St",
    "sg:city":"San Diego",
    "sg:classifiers":[
        {
            "category":"Retail",
            "subcategory":"Auto Repair",
            "type":"Services"
        }
    ],
    "sg:phone":"+1 619 269 0365",
    "sg:postcode":"92103",
    "sg:province":"CA",
    "sg:tags":[
        "wrecker"
    ],
    "wof:name":"Aardvark Towing",
    "wof:placetype":"venue"
},
  "geometry": {"coordinates":[-117.176012,32.737426],"type":"Point"}
}