{
  "type": "Feature",
  "properties": {
    "addr:full":"11400 W Olympic Boulevard Los Angeles CA 90064",
    "addr:housenumber":"11400",
    "addr:postcode":"90064",
    "addr:street":"W Olympic Boulevard",
    "iso:country":"US",
    "sg:address":"11400 W Olympic Boulevard",
    "sg:city":"Los Angeles",
    "sg:classifiers":[
        {
            "category":"Professional",
            "subcategory":"Lawyer & Legal Services",
            "type":"Services"
        }
    ],
    "sg:phone":"+1 310 312 9575",
    "sg:postcode":"90064",
    "sg:province":"CA",
    "wof:name":"Hoffman Jeff Law Offices of",
    "wof:placetype":"venue"
},
  "geometry": {"coordinates":[-118.44324,34.037137],"type":"Point"}
}