{
  "type": "Feature",
  "properties": {
    "iso:country":"US",
    "sg:address":"8200 Rosedale Hwy",
    "sg:city":"Bakersfield",
    "sg:classifiers":[
        {
            "category":"Food & Beverages",
            "subcategory":"Groceries & Convenience Stores",
            "type":"Retail Goods"
        }
    ],
    "sg:phone":"+1 661 587 6265",
    "sg:postcode":"93312",
    "sg:province":"CA",
    "sg:tags":[
        "grocer"
    ],
    "wof:name":"Foods Co",
    "wof:placetype":"venue"
},
  "geometry": {"coordinates":[-119.100228,35.383513],"type":"Point"}
}