{
  "type": "Feature",
  "properties": {
    "iso:country":"US",
    "sg:address":"12476 Julian Ave",
    "sg:city":"Lakeside",
    "sg:classifiers":[
        {
            "category":"Autos & Motor Vehicles",
            "subcategory":"Automobile Sales",
            "type":"Retail Goods"
        }
    ],
    "sg:phone":"+1 619 443 2486",
    "sg:postcode":"92040",
    "sg:province":"CA",
    "sg:tags":[
        "dealers-used",
        "car",
        "used",
        "cars-wholesale"
    ],
    "wof:name":"Bear Auto Sales & Vehicle Registration",
    "wof:placetype":"venue"
},
  "geometry": {"coordinates":[-116.921988,32.854969],"type":"Point"}
}