{
  "type": "Feature",
  "properties": {
    "iso:country":"US",
    "sg:address":"341 Tres Pinos Rd",
    "sg:city":"Hollister",
    "sg:classifiers":[
        {
            "category":"Personal",
            "subcategory":"Beauty Salon",
            "type":"Services"
        }
    ],
    "sg:phone":"+1 831 637 5205",
    "sg:postcode":"95023",
    "sg:province":"CA",
    "sg:tags":[
        "manicuring"
    ],
    "wof:name":"Nail Creations By Lorraine",
    "wof:placetype":"venue"
},
  "geometry": {"coordinates":[-121.396482,36.839402],"type":"Point"}
}