{
  "type": "Feature",
  "properties": {
    "iso:country":"US",
    "sg:address":"1310 W Olive Ave",
    "sg:city":"Porterville",
    "sg:classifiers":[
        {
            "category":"Food & Beverages",
            "subcategory":"Specialty",
            "type":"Retail Goods"
        },
        {
            "category":"Food & Beverages",
            "subcategory":"Groceries & Convenience Stores",
            "type":"Retail Goods"
        }
    ],
    "sg:phone":"+1 559 784 6431",
    "sg:postcode":"93257",
    "sg:province":"CA",
    "sg:tags":[
        "grocers-specialty"
    ],
    "wof:name":"Town & Country Market",
    "wof:placetype":"venue"
},
  "geometry": {"coordinates":[-119.047369,36.06589],"type":"Point"}
}