{
  "type": "Feature",
  "properties": {
    "iso:country":"US",
    "sg:address":"1110 S King Rd",
    "sg:city":"San Jose",
    "sg:classifiers":[
        {
            "category":"Shopping",
            "subcategory":"Shoes",
            "type":"Retail Goods"
        }
    ],
    "sg:phone":"+1 408 929 8690",
    "sg:postcode":"95122",
    "sg:province":"CA",
    "sg:tags":[
        "store"
    ],
    "wof:name":"Calzado Andrea Intl",
    "wof:placetype":"venue"
},
  "geometry": {"coordinates":[-121.841917,37.338971],"type":"Point"}
}