{
  "type": "Feature",
  "properties": {
    "iso:country":"US",
    "sg:address":"79 W Daily Dr",
    "sg:city":"Camarillo",
    "sg:classifiers":[
        {
            "category":"Banks & Credit Unions",
            "subcategory":"Bank",
            "type":"Services"
        }
    ],
    "sg:phone":"+1 805 484 5532",
    "sg:postcode":"93010",
    "sg:province":"CA",
    "sg:tags":[
        "broker",
        "mortgage"
    ],
    "wof:name":"Yes To Home Loans",
    "wof:placetype":"venue"
},
  "geometry": {"coordinates":[-119.070742,34.221912],"type":"Point"}
}