{
  "type": "Feature",
  "properties": {
    "iso:country":"US",
    "sg:address":"300 S Atlantic Blvd",
    "sg:city":"Monterey Park",
    "sg:classifiers":[
        {
            "category":"Professional",
            "subcategory":"Lawyer & Legal Services",
            "type":"Services"
        }
    ],
    "sg:phone":"+1 626 289 8299",
    "sg:postcode":"91754",
    "sg:province":"CA",
    "wof:name":"Law Office of Daniel K Y Fong",
    "wof:placetype":"venue"
},
  "geometry": {"coordinates":[-118.13400300000001,34.060001],"type":"Point"}
}