{
  "type": "Feature",
  "properties": {
    "addr:full":"3339 Carlyle Ter Lafayette CA 94549",
    "addr:housenumber":"3339",
    "addr:postcode":"94549",
    "addr:street":"Carlyle Ter",
    "iso:country":"US",
    "sg:address":"3339 Carlyle Ter",
    "sg:city":"Lafayette",
    "sg:classifiers":[
        {
            "category":"Professional",
            "type":"Services"
        }
    ],
    "sg:phone":"+1 925 299 0449",
    "sg:postcode":"94549",
    "sg:province":"CA",
    "wof:name":"Cdr Pigments",
    "wof:placetype":"venue"
},
  "geometry": {"coordinates":[-122.107598,37.878814],"type":"Point"}
}