{
  "type": "Feature",
  "properties": {
    "addr:full":"310 S el Cielo Rd Palm Springs CA 92262",
    "addr:housenumber":"310",
    "addr:postcode":"92262",
    "addr:street":"S El Cielo Rd",
    "iso:country":"US",
    "sg:address":"310 S el Cielo Rd",
    "sg:city":"Palm Springs",
    "sg:classifiers":[
        {
            "category":"Taxi",
            "type":"Transportation"
        }
    ],
    "sg:phone":"+1 760 668 2900",
    "sg:postcode":"92262",
    "sg:province":"CA",
    "sg:tags":[
        "taxicab"
    ],
    "wof:name":"Star Taxi",
    "wof:placetype":"venue"
},
  "geometry": {"coordinates":[-116.51057299999999,33.81975],"type":"Point"}
}