{
  "type": "Feature",
  "properties": {
    "iso:country":"US",
    "sg:address":"131 2nd St",
    "sg:city":"Exeter",
    "sg:phone":"+1 559 592 9485",
    "sg:postcode":"93221",
    "sg:province":"CA",
    "sg:tags":[
        "irrigation",
        "company"
    ],
    "wof:name":"Bowsmith Inc",
    "wof:placetype":"venue"
},
  "geometry": {"coordinates":[-119.130691,36.295774],"type":"Point"}
}