{
  "type": "Feature",
  "properties": {
    "addr:full":"220 Agostino Rd San Gabriel CA 91776",
    "addr:housenumber":"220",
    "addr:postcode":"91776",
    "addr:street":"Agostino Rd",
    "iso:country":"US",
    "sg:address":"220 Agostino Rd",
    "sg:city":"San Gabriel",
    "sg:classifiers":[
        {
            "category":"Personal",
            "type":"Services"
        }
    ],
    "sg:phone":"+1 626 287 9951",
    "sg:postcode":"91776",
    "sg:province":"CA",
    "sg:tags":[
        "towing"
    ],
    "wof:name":"Dickson Motor Service",
    "wof:placetype":"venue"
},
  "geometry": {"coordinates":[-118.09699999999999,34.097801],"type":"Point"}
}