{
  "type": "Feature",
  "properties": {
    "addr:full":"3660 W Benjamin Holt Dr Bldg Gate Stockton CA 95219",
    "addr:housenumber":"3660",
    "addr:postcode":"95219",
    "addr:street":"W Benjamin Holt Dr Bldg Gate",
    "iso:country":"US",
    "sg:address":"3660 W Benjamin Holt Dr Bldg Gate",
    "sg:city":"Stockton",
    "sg:classifiers":[
        {
            "category":"Professional",
            "subcategory":"Employment Agencies",
            "type":"Services"
        }
    ],
    "sg:phone":"+1 209 478 4459",
    "sg:postcode":"95219",
    "sg:province":"CA",
    "sg:tags":[
        "employer"
    ],
    "wof:name":"North Shore Homeowners Office",
    "wof:placetype":"venue"
},
  "geometry": {"coordinates":[-121.36426899999999,38.005128],"type":"Point"}
}