{
  "type": "Feature",
  "properties": {
    "iso:country":"US",
    "sg:address":"9121 Rock Springs Rd",
    "sg:city":"Newcastle",
    "sg:classifiers":[
        {
            "category":"Building & Trades",
            "subcategory":"Construction",
            "type":"Services"
        }
    ],
    "sg:phone":"+1 916 991 2537",
    "sg:postcode":"95658",
    "sg:province":"CA",
    "sg:tags":[
        "clearing",
        "land",
        "leveling"
    ],
    "wof:name":"Obie's Bobcat & Hauling",
    "wof:placetype":"venue"
},
  "geometry": {"coordinates":[-121.133515,38.840104],"type":"Point"}
}