{
  "type": "Feature",
  "properties": {
    "iso:country":"US",
    "sg:address":"6550 Freeport Blvd Ste A",
    "sg:city":"Sacramento",
    "sg:classifiers":[
        {
            "category":"Autos & Motor Vehicles",
            "subcategory":"Auto Supplies",
            "type":"Retail Goods"
        }
    ],
    "sg:phone":"+1 916 392 1196",
    "sg:postcode":"95822",
    "sg:province":"CA",
    "sg:tags":[
        "automobile",
        "parts",
        "accessory",
        "part",
        "accessories-wholesale",
        "manufacturer"
    ],
    "wof:name":"Deluxe Truckin' & Mobility",
    "wof:placetype":"venue"
},
  "geometry": {"coordinates":[-121.503074,38.509284],"type":"Point"}
}