{
  "type": "Feature",
  "properties": {
    "iso:country":"US",
    "sg:address":"5030 E Butler Ave",
    "sg:city":"Fresno",
    "sg:classifiers":[
        {
            "category":"Farming",
            "subcategory":"Orchard",
            "type":"Manufacturing & Wholesale Goods"
        }
    ],
    "sg:phone":"+1 559 251 8766",
    "sg:postcode":"93727",
    "sg:province":"CA",
    "sg:tags":[
        "fruit",
        "tree"
    ],
    "wof:name":"Vy Horn",
    "wof:placetype":"venue"
},
  "geometry": {"coordinates":[-119.723352,36.728575],"type":"Point"}
}