{
  "type": "Feature",
  "properties": {
    "iso:country":"US",
    "sg:address":"4401 Hazel Ave",
    "sg:city":"Fair Oaks",
    "sg:classifiers":[
        {
            "category":"Professional",
            "subcategory":"Engineering",
            "type":"Services"
        }
    ],
    "sg:phone":"+1 916 967 4510",
    "sg:postcode":"95628",
    "sg:province":"CA",
    "sg:tags":[
        "structural",
        "engineer"
    ],
    "wof:name":"Crawford & Associates",
    "wof:placetype":"venue"
},
  "geometry": {"coordinates":[-121.225086,38.636409],"type":"Point"}
}