{
  "type": "Feature",
  "properties": {
    "addr:full":"550 Pleasant Valley Rd Diamond Springs CA 95619",
    "addr:housenumber":"550",
    "addr:postcode":"95619",
    "addr:street":"Pleasant Valley Rd",
    "iso:country":"US",
    "sg:address":"550 Pleasant Valley Rd",
    "sg:city":"Diamond Springs",
    "sg:classifiers":[
        {
            "category":"Social Services",
            "type":"Services"
        }
    ],
    "sg:phone":"+1 530 622 8646",
    "sg:postcode":"95619",
    "sg:province":"CA",
    "sg:tags":[
        "counselor",
        "marriage",
        "family"
    ],
    "wof:name":"Bruce Quinn PHD",
    "wof:placetype":"venue"
},
  "geometry": {"coordinates":[-120.81371799999999,38.694636],"type":"Point"}
}