{
  "type": "Feature",
  "properties": {
    "iso:country":"US",
    "sg:address":"2105 Buchanan St",
    "sg:city":"San Francisco",
    "sg:classifiers":[
        {
            "category":"Shopping",
            "subcategory":"Computers & Home Electronics",
            "type":"Retail Goods"
        }
    ],
    "sg:phone":"+1 415 673 6217",
    "sg:postcode":"94115",
    "sg:province":"CA",
    "sg:tags":[
        "software"
    ],
    "wof:name":"Decision Support Svc",
    "wof:placetype":"venue"
},
  "geometry": {"coordinates":[-122.430805,37.790201],"type":"Point"}
}