{
  "type": "Feature",
  "properties": {
    "addr:full":"2747 S Cochran Ave Los Angeles CA 90016",
    "addr:housenumber":"2747",
    "addr:postcode":"90016",
    "addr:street":"S Cochran Ave",
    "iso:country":"US",
    "sg:address":"2747 S Cochran Ave",
    "sg:city":"Los Angeles",
    "sg:classifiers":[
        {
            "category":"Retail",
            "subcategory":"Repair Shop",
            "type":"Services"
        }
    ],
    "sg:phone":"+1 323 965 0566",
    "sg:postcode":"90016",
    "sg:province":"CA",
    "sg:tags":[
        "reupholstery",
        "furniture"
    ],
    "sg:website":"www.agrefinishing.com",
    "wof:name":"A & G Refinishing",
    "wof:placetype":"venue"
},
  "geometry": {"coordinates":[-118.359919,34.029395],"type":"Point"}
}