{
  "type": "Feature",
  "properties": {
    "addr:full":"145 Bridge St Arroyo Grande CA 93420",
    "addr:housenumber":"145",
    "addr:postcode":"93420",
    "addr:street":"Bridge St",
    "iso:country":"US",
    "sg:address":"145 Bridge St",
    "sg:city":"Arroyo Grande",
    "sg:classifiers":[
        {
            "category":"Health Services",
            "subcategory":"Doctor",
            "type":"Services"
        }
    ],
    "sg:phone":"+1 805 481 3166",
    "sg:postcode":"93420",
    "sg:province":"CA",
    "sg:tags":[
        "physician",
        "surgeon"
    ],
    "wof:name":"Pediatric Specialist Medical",
    "wof:placetype":"venue"
},
  "geometry": {"coordinates":[-120.57857799999999,35.122527],"type":"Point"}
}