{
  "type": "Feature",
  "properties": {
    "iso:country":"US",
    "sg:address":"2133 Mcnell Rd",
    "sg:city":"Ojai",
    "sg:classifiers":[
        {
            "category":"Wholesale",
            "subcategory":"Medical Equipment & Supplies",
            "type":"Manufacturing & Wholesale Goods"
        },
        {
            "category":"Shopping",
            "subcategory":"Pets & Pet Supplies",
            "type":"Retail Goods"
        },
        {
            "category":"Retail",
            "subcategory":"Veterinary Services",
            "type":"Services"
        }
    ],
    "sg:phone":"+1 805 640 1406",
    "sg:postcode":"93023",
    "sg:province":"CA",
    "sg:tags":[
        "health",
        "product",
        "veterinarian",
        "animal",
        "supply-wholesale"
    ],
    "wof:name":"Veterinary Radiographic Co",
    "wof:placetype":"venue"
},
  "geometry": {"coordinates":[-119.197208,34.465049],"type":"Point"}
}