{
  "type": "Feature",
  "properties": {
    "addr:full":"23852 Stagg St Canoga Park CA 91304",
    "addr:housenumber":"23852",
    "addr:postcode":"91304",
    "addr:street":"Stagg St",
    "iso:country":"US",
    "sg:address":"23852 Stagg St",
    "sg:city":"Canoga Park",
    "sg:classifiers":[
        {
            "category":"Professional",
            "subcategory":"Business Services",
            "type":"Services"
        }
    ],
    "sg:phone":"+1 818 702 6455",
    "sg:postcode":"91304",
    "sg:province":"CA",
    "sg:tags":[
        "printing",
        "broker"
    ],
    "wof:name":"International Graphic Art Svc",
    "wof:placetype":"venue"
},
  "geometry": {"coordinates":[-118.647175,34.21063],"type":"Point"}
}