{
  "type": "Feature",
  "properties": {
    "iso:country":"US",
    "sg:address":"632 Williamson Ave",
    "sg:city":"Fullerton",
    "sg:classifiers":[
        {
            "category":"Autos & Motor Vehicles",
            "subcategory":"Automobile Sales",
            "type":"Retail Goods"
        }
    ],
    "sg:phone":"+1 714 469 1042",
    "sg:postcode":"92832",
    "sg:province":"CA",
    "sg:tags":[
        "car",
        "used",
        "dealer",
        "mfg"
    ],
    "wof:name":"Streamline International",
    "wof:placetype":"venue"
},
  "geometry": {"coordinates":[-117.936758,33.869136],"type":"Point"}
}