{
  "type": "Feature",
  "properties": {
    "addr:full":"9863 Pacifico Way Cypress CA 90630",
    "addr:postcode":"9863;90630",
    "addr:street":"Pacifico Way",
    "iso:country":"US",
    "sg:address":"9863 Pacifico Way",
    "sg:city":"Cypress",
    "sg:classifiers":[
        {
            "category":"Wholesale",
            "subcategory":"Machinery & Supplies",
            "type":"Manufacturing & Wholesale Goods"
        }
    ],
    "sg:phone":"+1 714 538 2295",
    "sg:postcode":"90630",
    "sg:province":"CA",
    "sg:tags":[
        "equipment",
        "material",
        "handling"
    ],
    "wof:name":"Industrial Material Handling",
    "wof:placetype":"venue"
},
  "geometry": {"coordinates":[-118.029886,33.818785],"type":"Point"}
}