{
  "type": "Feature",
  "properties": {
    "addr:full":"345 Spear Street Suite 515 San Francisco CA 94105",
    "addr:housenumber":"345",
    "addr:postcode":"94105",
    "addr:street":"Spear Street Suite 515",
    "iso:country":"US",
    "sg:address":"345 Spear Street Suite 515",
    "sg:city":"San Francisco",
    "sg:classifiers":[
        {
            "category":"Manufacturing",
            "subcategory":"Electronics",
            "type":"Manufacturing & Wholesale Goods"
        }
    ],
    "sg:phone":"+1 415 869 7008",
    "sg:postcode":"94105",
    "sg:province":"CA",
    "sg:tags":[
        "hosting",
        "cloud-computing",
        "grid-servers",
        "grid",
        "high-availability-hosting"
    ],
    "sg:website":"http://www.servepath.com",
    "wof:name":"ServePath",
    "wof:placetype":"venue"
},
  "geometry": {"coordinates":[-122.389923,37.789444],"type":"Point"}
}