{
  "type": "Feature",
  "properties": {
    "addr:full":"1046 Mission Ave Oceanside CA 92054",
    "addr:housenumber":"1046",
    "addr:postcode":"92054",
    "addr:street":"Mission Ave",
    "iso:country":"US",
    "sg:address":"1046 Mission Ave",
    "sg:city":"Oceanside",
    "sg:classifiers":[
        {
            "category":"Shopping",
            "subcategory":"Stationery & Office Supplies",
            "type":"Retail Goods"
        }
    ],
    "sg:phone":"+1 760 439 0712",
    "sg:postcode":"92054",
    "sg:province":"CA",
    "sg:tags":[
        "printing"
    ],
    "wof:name":"Office Depot",
    "wof:placetype":"venue"
},
  "geometry": {"coordinates":[-117.375,33.198399],"type":"Point"}
}