{
  "type": "Feature",
  "properties": {
    "iso:country":"US",
    "sg:address":"2319 S La Cienega Boulevard",
    "sg:city":"Los Angeles",
    "sg:classifiers":[
        {
            "category":"Shopping",
            "subcategory":"Antiques",
            "type":"Retail Goods"
        }
    ],
    "sg:phone":"+1 310 202 8956",
    "sg:postcode":"90034",
    "sg:province":"CA",
    "wof:name":"Creative Arts Maker",
    "wof:placetype":"venue"
},
  "geometry": {"coordinates":[-118.377308,34.03731],"type":"Point"}
}