{
  "type": "Feature",
  "properties": {
    "iso:country":"US",
    "sg:address":"402 Georgia St",
    "sg:city":"Vallejo",
    "sg:classifiers":[
        {
            "category":"Restaurant",
            "type":"Food & Drink"
        }
    ],
    "sg:phone":"+1 707 649 8616",
    "sg:postcode":"94590",
    "sg:province":"CA",
    "wof:name":"Bon Chicken & Taqueria",
    "wof:placetype":"venue"
},
  "geometry": {"coordinates":[-122.25496800000001,38.101171],"type":"Point"}
}