{
  "type": "Feature",
  "properties": {
    "iso:country":"US",
    "sg:address":"833 Mahler Rd #10",
    "sg:city":"Burlingame",
    "sg:classifiers":[
        {
            "category":"Deli",
            "type":"Food & Drink"
        }
    ],
    "sg:phone":"+1 650 697 0528",
    "sg:postcode":"94010",
    "sg:province":"CA",
    "wof:name":"3 J's",
    "wof:placetype":"venue"
},
  "geometry": {"coordinates":[-122.36723000000001,37.597217],"type":"Point"}
}