{
  "type": "Feature",
  "properties": {
    "addr:full":"240 E 60th St Los Angeles CA 90003",
    "addr:housenumber":"240",
    "addr:postcode":"90003",
    "addr:street":"E 60Th St",
    "iso:country":"US",
    "sg:address":"240 E 60th St",
    "sg:city":"Los Angeles",
    "sg:classifiers":[
        {
            "category":"Professional",
            "type":"Services"
        }
    ],
    "sg:phone":"+1 323 971 0198",
    "sg:postcode":"90003",
    "sg:province":"CA",
    "wof:name":"Los Angeles Stars",
    "wof:placetype":"venue"
},
  "geometry": {"coordinates":[-118.270304,33.985085],"type":"Point"}
}