{
  "type": "Feature",
  "properties": {
    "iso:country":"US",
    "sg:address":"6110 S Elm Ave",
    "sg:city":"Fresno",
    "sg:classifiers":[
        {
            "category":"Autos & Motor Vehicles",
            "subcategory":"Fuel & Gas Station",
            "type":"Retail Goods"
        }
    ],
    "sg:phone":"+1 559 441 8121",
    "sg:postcode":"93706",
    "sg:province":"CA",
    "sg:tags":[
        "oil"
    ],
    "wof:name":"Shop-N-Quick",
    "wof:placetype":"venue"
},
  "geometry": {"coordinates":[-119.790757,36.646574],"type":"Point"}
}