{
  "type": "Feature",
  "properties": {
    "addr:full":"224 N Oak Dr Reedley CA 93654",
    "addr:housenumber":"224",
    "addr:postcode":"93654",
    "addr:street":"N Oak Dr",
    "iso:country":"US",
    "sg:address":"224 N Oak Dr",
    "sg:city":"Reedley",
    "sg:classifiers":[
        {
            "category":"Building & Trades",
            "subcategory":"Construction",
            "type":"Services"
        }
    ],
    "sg:phone":"+1 559 638 2070",
    "sg:postcode":"93654",
    "sg:province":"CA",
    "sg:tags":[
        "contractor"
    ],
    "wof:name":"Duane Warkentin Construction",
    "wof:placetype":"venue"
},
  "geometry": {"coordinates":[-119.46419,36.597826],"type":"Point"}
}