{
  "type": "Feature",
  "properties": {
    "iso:country":"US",
    "sg:address":"1606 Great Hwy",
    "sg:city":"San Francisco",
    "sg:classifiers":[
        {
            "category":"Shopping",
            "subcategory":"Pets & Pet Supplies",
            "type":"Retail Goods"
        }
    ],
    "sg:phone":"+1 415 850 1307",
    "sg:postcode":"94122",
    "sg:province":"CA",
    "sg:tags":[
        "walker",
        "dog"
    ],
    "sg:website":"www.tiredhappydogs.com/",
    "wof:name":"Tired, Happy Dogs",
    "wof:placetype":"venue"
},
  "geometry": {"coordinates":[-122.50863699999999,37.756318],"type":"Point"}
}