{
  "type": "Feature",
  "properties": {
    "addr:full":"655 Edgeview Dr Sierra Madre CA 91024",
    "addr:housenumber":"655",
    "addr:postcode":"91024",
    "addr:street":"Edgeview Dr",
    "iso:country":"US",
    "sg:address":"655 Edgeview Dr",
    "sg:city":"Sierra Madre",
    "sg:classifiers":[
        {
            "category":"Building & Trades",
            "subcategory":"Electrical",
            "type":"Services"
        }
    ],
    "sg:phone":"+1 626 963 1409",
    "sg:postcode":"91024",
    "sg:province":"CA",
    "sg:tags":[
        "electrician"
    ],
    "wof:name":"Michael Sizer",
    "wof:placetype":"venue"
},
  "geometry": {"coordinates":[-118.066183,34.171695],"type":"Point"}
}