{
  "type": "Feature",
  "properties": {
    "addr:full":"1101 Glenwillow Ln Concord CA 94521",
    "addr:housenumber":"1101",
    "addr:postcode":"94521",
    "addr:street":"Glenwillow Ln",
    "iso:country":"US",
    "sg:address":"1101 Glenwillow Ln",
    "sg:city":"Concord",
    "sg:classifiers":[
        {
            "category":"Communications",
            "type":"Services"
        }
    ],
    "sg:phone":"+1 925 673 9896",
    "sg:postcode":"94521",
    "sg:province":"CA",
    "sg:website":"www.refkin.com",
    "wof:name":"Holtz Communication & Technlgy",
    "wof:placetype":"venue"
},
  "geometry": {"coordinates":[-121.96435099999999,37.938954],"type":"Point"}
}