{
  "type": "Feature",
  "properties": {
    "addr:full":"14 County Center Dr Oroville CA 95965",
    "addr:housenumber":"14",
    "addr:postcode":"95965",
    "addr:street":"County Center Dr",
    "iso:country":"US",
    "sg:address":"14 County Center Dr",
    "sg:city":"Oroville",
    "sg:classifiers":[
        {
            "category":"Government",
            "subcategory":"Office",
            "type":"Public Place"
        }
    ],
    "sg:phone":"+1 530 538 7625",
    "sg:postcode":"95965",
    "sg:province":"CA",
    "wof:name":"Butte County Storeroom",
    "wof:placetype":"venue"
},
  "geometry": {"coordinates":[-121.570667,39.524073],"type":"Point"}
}