{
  "type": "Feature",
  "properties": {
    "addr:full":"16740 W Bernardo Dr San Diego CA 92127",
    "addr:housenumber":"16740",
    "addr:postcode":"92127",
    "addr:street":"W Bernardo Dr",
    "iso:country":"US",
    "sg:address":"16740 W Bernardo Dr",
    "sg:city":"San Diego",
    "sg:classifiers":[
        {
            "category":"Manufacturing",
            "subcategory":"Tools & Machinery",
            "type":"Manufacturing & Wholesale Goods"
        }
    ],
    "sg:phone":"+1 858 618 1500",
    "sg:postcode":"92127",
    "sg:province":"CA",
    "sg:tags":[
        "machine",
        "shop"
    ],
    "wof:name":"Paramount Technology Inc",
    "wof:placetype":"venue"
},
  "geometry": {"coordinates":[-117.089315,33.008517],"type":"Point"}
}