{
  "type": "Feature",
  "properties": {
    "addr:full":"222 North Ocean Ave Cayucos CA 93430",
    "addr:housenumber":"222",
    "addr:postcode":"93430",
    "addr:street":"North Ocean Ave",
    "iso:country":"US",
    "sg:address":"222 North Ocean Ave",
    "sg:city":"Cayucos",
    "sg:classifiers":[
        {
            "category":"Restaurant",
            "type":"Food & Drink"
        },
        {
            "category":"Travel",
            "subcategory":"Bed & Breakfast",
            "type":"Entertainment"
        }
    ],
    "sg:phone":"+1 805 995 3669",
    "sg:postcode":"93430",
    "sg:province":"CA",
    "sg:tags":[
        "new",
        "american",
        "french"
    ],
    "sg:website":"www.casshouseinn.com",
    "wof:name":"Cass House Restaurant & Luxury Inn",
    "wof:placetype":"venue"
},
  "geometry": {"coordinates":[-120.90500400000001,35.449152],"type":"Point"}
}