{
  "type": "Feature",
  "properties": {
    "addr:full":"376 Skander Ln Pleasant Hill CA 94523",
    "addr:housenumber":"376",
    "addr:postcode":"94523",
    "addr:street":"Skander Ln",
    "iso:country":"US",
    "sg:address":"376 Skander Ln",
    "sg:city":"Pleasant Hill",
    "sg:classifiers":[
        {
            "category":"Manufacturing",
            "subcategory":"Apparel",
            "type":"Manufacturing & Wholesale Goods"
        }
    ],
    "sg:phone":"+1 925 691 5344",
    "sg:postcode":"94523",
    "sg:province":"CA",
    "sg:tags":[
        "textile",
        "product",
        "fabricated",
        "mfg"
    ],
    "wof:name":"Party Animals",
    "wof:placetype":"venue"
},
  "geometry": {"coordinates":[-122.081661,37.966567],"type":"Point"}
}