{
  "type": "Feature",
  "properties": {
    "addr:full":"29625 The Old Rd Castaic CA 91384",
    "addr:housenumber":"29625",
    "addr:postcode":"91384",
    "addr:street":"The Old Rd",
    "iso:country":"US",
    "sg:address":"29625 The Old Rd",
    "sg:city":"Castaic",
    "sg:classifiers":[
        {
            "category":"Personal",
            "subcategory":"Nail Salon",
            "type":"Services"
        }
    ],
    "sg:phone":"+1 661 257 9992",
    "sg:postcode":"91384",
    "sg:province":"CA",
    "wof:name":"Tina's Wonder Nail & Spa",
    "wof:placetype":"venue"
},
  "geometry": {"coordinates":[-118.616106,34.452918],"type":"Point"}
}