{
  "type": "Feature",
  "properties": {
    "iso:country":"US",
    "sg:address":"54645 Ave Rubio",
    "sg:city":"La Quinta",
    "sg:classifiers":[
        {
            "category":"Home & Garden",
            "subcategory":"Carpets & Floor Coverings",
            "type":"Retail Goods"
        }
    ],
    "sg:phone":"+1 760 564 4966",
    "sg:postcode":"92253",
    "sg:province":"CA",
    "sg:tags":[
        "material"
    ],
    "wof:name":"Perry's Floors",
    "wof:placetype":"venue"
},
  "geometry": {"coordinates":[-116.315016,33.651788],"type":"Point"}
}