{
  "type": "Feature",
  "properties": {
    "iso:country":"US",
    "sg:address":"15826 Donner Pass Rd",
    "sg:city":"Truckee",
    "sg:classifiers":[
        {
            "category":"Building & Trades",
            "subcategory":"Construction",
            "type":"Services"
        }
    ],
    "sg:phone":"+1 530 582 8174",
    "sg:postcode":"96161",
    "sg:province":"CA",
    "sg:tags":[
        "contractor"
    ],
    "sg:website":"www.mtlincoln.com",
    "wof:name":"M T Lincoln Construction",
    "wof:placetype":"venue"
},
  "geometry": {"coordinates":[-120.288293,39.324334],"type":"Point"}
}