{
  "type": "Feature",
  "properties": {
    "addr:full":"568 E Foothill Blvd Azusa CA 91702",
    "addr:housenumber":"568",
    "addr:postcode":"91702",
    "addr:street":"E Foothill Blvd",
    "iso:country":"US",
    "sg:address":"568 E Foothill Blvd",
    "sg:city":"Azusa",
    "sg:classifiers":[
        {
            "category":"Manufacturing",
            "subcategory":"Printing",
            "type":"Manufacturing & Wholesale Goods"
        }
    ],
    "sg:phone":"+1 626 969 3385",
    "sg:postcode":"91702",
    "sg:province":"CA",
    "sg:tags":[
        "commercial"
    ],
    "wof:name":"Proforma Qlty Printg",
    "wof:placetype":"venue"
},
  "geometry": {"coordinates":[-117.900008,34.133441],"type":"Point"}
}