{
  "type": "Feature",
  "properties": {
    "iso:country":"US",
    "sg:address":"416 N Bedford Dr Ste 209",
    "sg:city":"Beverly Hills",
    "sg:classifiers":[
        {
            "category":"Health Services",
            "subcategory":"Dentist",
            "type":"Services"
        }
    ],
    "sg:phone":"+1 310 248 3607",
    "sg:postcode":"90210",
    "sg:province":"CA",
    "sg:tags":[
        "cosmetic"
    ],
    "sg:website":"www.loveday.com",
    "wof:name":"Clay David Loveday, DMD",
    "wof:placetype":"venue"
},
  "geometry": {"coordinates":[-118.405296,34.068199],"type":"Point"}
}