{
  "type": "Feature",
  "properties": {
    "addr:full":"10030 Adams Ave Huntington Beach CA 92646",
    "addr:housenumber":"10030",
    "addr:postcode":"92646",
    "addr:street":"Adams Ave",
    "iso:country":"US",
    "sg:address":"10030 Adams Ave",
    "sg:city":"Huntington Beach",
    "sg:classifiers":[
        {
            "category":"Banks & Credit Unions",
            "subcategory":"Bank",
            "type":"Services"
        }
    ],
    "sg:phone":"+1 714 968 3655",
    "sg:postcode":"92646",
    "sg:province":"CA",
    "wof:name":"Markwith John M",
    "wof:placetype":"venue"
},
  "geometry": {"coordinates":[-117.952974,33.672181],"type":"Point"}
}