{
  "type": "Feature",
  "properties": {
    "iso:country":"US",
    "sg:address":"23560 Lyons Ave",
    "sg:city":"Newhall",
    "sg:classifiers":[
        {
            "category":"Insurance",
            "subcategory":"Insurance Agent",
            "type":"Services"
        }
    ],
    "sg:phone":"+1 661 254 9953",
    "sg:postcode":"91321",
    "sg:province":"CA",
    "wof:name":"Cal Executive Insurance",
    "wof:placetype":"venue"
},
  "geometry": {"coordinates":[-118.546458,34.379285],"type":"Point"}
}