{
  "type": "Feature",
  "properties": {
    "addr:full":"851 81st Ave Ste E Oakland CA 94621",
    "addr:housenumber":"851",
    "addr:postcode":"94621",
    "addr:street":"81St Ave Ste E",
    "iso:country":"US",
    "sg:address":"851 81st Ave Ste E",
    "sg:city":"Oakland",
    "sg:classifiers":[
        {
            "category":"Education",
            "subcategory":"Music School",
            "type":"Public Place"
        }
    ],
    "sg:phone":"+1 510 301 6951",
    "sg:postcode":"94621",
    "sg:province":"CA",
    "wof:name":"Advanced Music Institute",
    "wof:placetype":"venue"
},
  "geometry": {"coordinates":[-122.192092,37.749926],"type":"Point"}
}