{
  "type": "Feature",
  "properties": {
    "iso:country":"US",
    "sg:address":"13201 Ryans Way",
    "sg:city":"Lakeside",
    "sg:classifiers":[
        {
            "category":"Professional",
            "subcategory":"Art Services",
            "type":"Services"
        }
    ],
    "sg:phone":"+1 619 938 0240",
    "sg:postcode":"92040",
    "sg:province":"CA",
    "sg:tags":[
        "graphic",
        "designer"
    ],
    "sg:website":"www.vectorgraphix.com",
    "wof:name":"Vector Graphix",
    "wof:placetype":"venue"
},
  "geometry": {"coordinates":[-116.90522199999999,32.841806],"type":"Point"}
}