{
  "type": "Feature",
  "properties": {
    "iso:country":"US",
    "sg:address":"647 W Shaw Ave",
    "sg:city":"Fresno",
    "sg:classifiers":[
        {
            "category":"Retail",
            "subcategory":"Portrait Studio",
            "type":"Services"
        }
    ],
    "sg:phone":"+1 559 225 2196",
    "sg:postcode":"93704",
    "sg:province":"CA",
    "sg:tags":[
        "photographer"
    ],
    "wof:name":"Tenney Studios",
    "wof:placetype":"venue"
},
  "geometry": {"coordinates":[-119.804841,36.808329],"type":"Point"}
}