{
  "type": "Feature",
  "properties": {
    "iso:country":"US",
    "sg:address":"900 Searchlight Ranch Rd",
    "sg:city":"Acton",
    "sg:classifiers":[
        {
            "category":"Shopping",
            "subcategory":"Shoes",
            "type":"Retail Goods"
        }
    ],
    "sg:phone":"+1 661 269 8221",
    "sg:postcode":"93510",
    "sg:province":"CA",
    "sg:tags":[
        "store"
    ],
    "wof:name":"Fleet Feet Agility Center",
    "wof:placetype":"venue"
},
  "geometry": {"coordinates":[-118.132081,34.4734],"type":"Point"}
}