{
  "type": "Feature",
  "properties": {
    "addr:full":"3832 Sepulveda Blvd Torrance CA 90505",
    "addr:housenumber":"3832",
    "addr:postcode":"90505",
    "addr:street":"Sepulveda Blvd",
    "iso:country":"US",
    "sg:address":"3832 Sepulveda Blvd",
    "sg:city":"Torrance",
    "sg:classifiers":[
        {
            "category":"Home & Garden",
            "subcategory":"Furniture",
            "type":"Retail Goods"
        }
    ],
    "sg:phone":"+1 310 373 1800",
    "sg:postcode":"90505",
    "sg:province":"CA",
    "wof:name":"Laurel's Fine Furniture",
    "wof:placetype":"venue"
},
  "geometry": {"coordinates":[-118.352262,33.825559],"type":"Point"}
}