{
  "type": "Feature",
  "properties": {
    "iso:country":"US",
    "sg:address":"1570 Rosecrans Ave",
    "sg:city":"Manhattan Beach",
    "sg:classifiers":[
        {
            "category":"Retail",
            "subcategory":"Portrait Studio",
            "type":"Services"
        }
    ],
    "sg:phone":"+1 310 258 0264",
    "sg:postcode":"90266",
    "sg:province":"CA",
    "sg:tags":[
        "photography",
        "store"
    ],
    "wof:name":"Longs Drug Stores",
    "wof:placetype":"venue"
},
  "geometry": {"coordinates":[-118.386002,33.901798],"type":"Point"}
}