{
  "type": "Feature",
  "properties": {
    "iso:country":"US",
    "sg:address":"477 Magladry Rd",
    "sg:city":"Hollister",
    "sg:classifiers":[
        {
            "category":"Retail",
            "subcategory":"Animal Services",
            "type":"Services"
        }
    ],
    "sg:phone":"+1 831 636 0110",
    "sg:postcode":"95023",
    "sg:province":"CA",
    "sg:tags":[
        "breeder",
        "horse"
    ],
    "wof:name":"Wendlee Farm",
    "wof:placetype":"venue"
},
  "geometry": {"coordinates":[-121.35467300000001,36.878105],"type":"Point"}
}