{
  "type": "Feature",
  "properties": {
    "addr:full":"1605 S Hoover Street Los Angeles CA 90006",
    "addr:housenumber":"1605",
    "addr:postcode":"90006",
    "addr:street":"S Hoover Street",
    "iso:country":"US",
    "sg:address":"1605 S Hoover Street",
    "sg:city":"Los Angeles",
    "sg:classifiers":[
        {
            "category":"Banks & Credit Unions",
            "subcategory":"Bank",
            "type":"Services"
        }
    ],
    "sg:phone":"+1 213 745 2800",
    "sg:postcode":"90006",
    "sg:province":"CA",
    "sg:website":"www.westernunion.com",
    "wof:name":"Western Union - PLS Check Cashers",
    "wof:placetype":"venue"
},
  "geometry": {"coordinates":[-118.284555,34.043469],"type":"Point"}
}