{
  "type": "Feature",
  "properties": {
    "iso:country":"US",
    "sg:address":"41 Corporate Park",
    "sg:city":"Irvine",
    "sg:classifiers":[
        {
            "category":"Professional",
            "type":"Services"
        }
    ],
    "sg:phone":"+1 949 474 6983",
    "sg:postcode":"92606",
    "sg:province":"CA",
    "wof:name":"Megan L Wagner",
    "wof:placetype":"venue"
},
  "geometry": {"coordinates":[-117.82854399999999,33.688931],"type":"Point"}
}