{
  "type": "Feature",
  "properties": {
    "iso:country":"US",
    "sg:address":"6555 W Telephone Rd",
    "sg:city":"Ventura",
    "sg:classifiers":[
        {
            "category":"Health Services",
            "subcategory":"Doctor",
            "type":"Services"
        }
    ],
    "sg:phone":"+1 805 642 2790",
    "sg:postcode":"93003",
    "sg:province":"CA",
    "sg:tags":[
        "dentist"
    ],
    "wof:name":"Amerident Group",
    "wof:placetype":"venue"
},
  "geometry": {"coordinates":[-119.203765,34.266684],"type":"Point"}
}