{
  "type": "Feature",
  "properties": {
    "iso:country":"US",
    "sg:address":"587 N Ventu Park Rd",
    "sg:city":"Newbury Park",
    "sg:classifiers":[
        {
            "category":"Wholesale",
            "subcategory":"Durable Goods & Equipment",
            "type":"Manufacturing & Wholesale Goods"
        }
    ],
    "sg:phone":"+1 805 499 4191",
    "sg:postcode":"91320",
    "sg:province":"CA",
    "sg:tags":[
        "representative",
        "manufacturer"
    ],
    "wof:name":"Inner-Link Systems",
    "wof:placetype":"venue"
},
  "geometry": {"coordinates":[-118.91112099999999,34.186735],"type":"Point"}
}