{
  "type": "Feature",
  "properties": {
    "iso:country":"US",
    "sg:address":"335 N Maple Drive Suite 150",
    "sg:city":"Beverly Hills",
    "sg:classifiers":[
        {
            "category":"Banks & Credit Unions",
            "subcategory":"Investment Brokerage",
            "type":"Services"
        }
    ],
    "sg:phone":"+1 310 273 5251",
    "sg:postcode":"90210",
    "sg:province":"CA",
    "sg:tags":[
        "investing"
    ],
    "sg:website":"www.morganstanley.com",
    "wof:name":"Morgan Stanley",
    "wof:placetype":"venue"
},
  "geometry": {"coordinates":[-118.393671,34.073634],"type":"Point"}
}