{
  "type": "Feature",
  "properties": {
    "iso:country":"US",
    "sg:address":"142 E Martin Luther King Jr Blvd",
    "sg:city":"Los Angeles",
    "sg:classifiers":[
        {
            "category":"Health Services",
            "subcategory":"Health Practitioner",
            "type":"Services"
        }
    ],
    "sg:phone":"+1 323 231 5573",
    "sg:postcode":"90011",
    "sg:province":"CA",
    "sg:tags":[
        "nutritionist"
    ],
    "wof:name":"Baby's Delite",
    "wof:placetype":"venue"
},
  "geometry": {"coordinates":[-118.272516,34.011063],"type":"Point"}
}