{
  "type": "Feature",
  "properties": {
    "iso:country":"US",
    "sg:address":"138 E Lemon Ave",
    "sg:city":"Monrovia",
    "sg:classifiers":[
        {
            "category":"Wholesale",
            "subcategory":"Durable Goods & Equipment",
            "type":"Manufacturing & Wholesale Goods"
        }
    ],
    "sg:phone":"+1 626 303 3679",
    "sg:postcode":"91016",
    "sg:province":"CA",
    "sg:tags":[
        "representative",
        "manufacturer"
    ],
    "wof:name":"Pan Pacific Sales Inc",
    "wof:placetype":"venue"
},
  "geometry": {"coordinates":[-117.999376,34.146926],"type":"Point"}
}