{
  "type": "Feature",
  "properties": {
    "iso:country":"US",
    "sg:address":"645 4th St",
    "sg:city":"Santa Rosa",
    "sg:classifiers":[
        {
            "category":"Restaurant",
            "type":"Food & Drink"
        }
    ],
    "sg:menulink":"http://www.allmenus.com/ca/santa-rosa/52887-jojo-sushi/menu/",
    "sg:phone":"+1 707 569 8588",
    "sg:postcode":"95404",
    "sg:province":"CA",
    "sg:tags":[
        "japanese",
        "asian"
    ],
    "wof:name":"JoJo Sushi",
    "wof:placetype":"venue"
},
  "geometry": {"coordinates":[-122.712554,38.441102],"type":"Point"}
}