{
  "type": "Feature",
  "properties": {
    "addr:full":"3505 Long Beach Blvd Suite 2D Long Beach CA 90807",
    "addr:housenumber":"3505",
    "addr:postcode":"90807",
    "addr:street":"Long Beach Blvd Suite 2D",
    "iso:country":"US",
    "sg:address":"3505 Long Beach Blvd Suite 2D",
    "sg:city":"Long Beach",
    "sg:classifiers":[
        {
            "category":"Health Services",
            "subcategory":"Doctor",
            "type":"Services"
        }
    ],
    "sg:phone":"+1 562 427 3897",
    "sg:postcode":"90807",
    "sg:province":"CA",
    "sg:tags":[
        "psychiatrist"
    ],
    "sg:website":"www.awirga.com",
    "wof:name":"Wirga Aleksandra MD",
    "wof:placetype":"venue"
},
  "geometry": {"coordinates":[-118.18974900000001,33.820555],"type":"Point"}
}