{
  "type": "Feature",
  "properties": {
    "addr:full":"8020 W Doe Ave Visalia CA 93291",
    "addr:housenumber":"8020",
    "addr:postcode":"93291",
    "addr:street":"W Doe Ave",
    "iso:country":"US",
    "sg:address":"8020 W Doe Ave",
    "sg:city":"Visalia",
    "sg:classifiers":[
        {
            "category":"Professional",
            "type":"Services"
        }
    ],
    "sg:phone":"+1 559 651 0103",
    "sg:postcode":"93291",
    "sg:province":"CA",
    "sg:tags":[
        "establishment"
    ],
    "sg:website":"www.geilenterprises.com",
    "wof:name":"Geil Enterprises Inc",
    "wof:placetype":"venue"
},
  "geometry": {"coordinates":[-119.376242,36.346098],"type":"Point"}
}