{
  "type": "Feature",
  "properties": {
    "iso:country":"US",
    "sg:address":"26562 Moulton Pkwy Ste C",
    "sg:city":"Laguna Hills",
    "sg:classifiers":[
        {
            "category":"Autos & Motor Vehicles",
            "subcategory":"Auto Supplies",
            "type":"Retail Goods"
        }
    ],
    "sg:phone":"+1 949 831 0434",
    "sg:postcode":"92653",
    "sg:province":"CA",
    "sg:tags":[
        "part"
    ],
    "sg:website":"www.oreillyauto.com",
    "wof:name":"Kragen Auto Parts",
    "wof:placetype":"venue"
},
  "geometry": {"coordinates":[-117.70250900000001,33.577089],"type":"Point"}
}