{
  "type": "Feature",
  "properties": {
    "iso:country":"US",
    "sg:address":"3330 Saviers Rd",
    "sg:city":"Oxnard",
    "sg:classifiers":[
        {
            "category":"Wholesale",
            "subcategory":"Hardware",
            "type":"Manufacturing & Wholesale Goods"
        }
    ],
    "sg:phone":"+1 805 483 0155",
    "sg:postcode":"93033",
    "sg:province":"CA",
    "sg:tags":[
        "plumbing",
        "fixture",
        "supply"
    ],
    "wof:name":"Harbor Plumbing Supply Co",
    "wof:placetype":"venue"
},
  "geometry": {"coordinates":[-119.17755699999999,34.166216],"type":"Point"}
}