{
  "type": "Feature",
  "properties": {
    "iso:country":"US",
    "sg:address":"4751 N Blackstone Ave",
    "sg:city":"Fresno",
    "sg:classifiers":[
        {
            "category":"Shopping",
            "subcategory":"Bicycles & Sporting Goods",
            "type":"Retail Goods"
        }
    ],
    "sg:phone":"+1 559 226 9900",
    "sg:postcode":"93726",
    "sg:province":"CA",
    "sg:tags":[
        "product",
        "sport",
        "metal",
        "tobacco",
        "se"
    ],
    "wof:name":"Kiss My Glass Skate Shop",
    "wof:placetype":"venue"
},
  "geometry": {"coordinates":[-119.790531,36.803997],"type":"Point"}
}