{
  "type": "Feature",
  "properties": {
    "iso:country":"US",
    "sg:address":"12519 Carson St",
    "sg:city":"Hawaiian Gardens",
    "sg:classifiers":[
        {
            "category":"Retail",
            "subcategory":"Portrait Studio",
            "type":"Services"
        }
    ],
    "sg:phone":"+1 562 924 4114",
    "sg:postcode":"90716",
    "sg:province":"CA",
    "sg:tags":[
        "photography",
        "store"
    ],
    "sg:website":"www.modern-color.com",
    "wof:name":"Modern Color",
    "wof:placetype":"venue"
},
  "geometry": {"coordinates":[-118.066002,33.831799],"type":"Point"}
}