{
  "type": "Feature",
  "properties": {
    "addr:full":"143 E Virginia Street San Jose CA 95112",
    "addr:housenumber":"143",
    "addr:postcode":"95112",
    "addr:street":"E Virginia Street",
    "iso:country":"US",
    "sg:address":"143 E Virginia Street",
    "sg:city":"San Jose",
    "sg:classifiers":[
        {
            "category":"Wholesale",
            "subcategory":"Stationery",
            "type":"Manufacturing & Wholesale Goods"
        }
    ],
    "sg:phone":"+1 408 287 2242",
    "sg:postcode":"95112",
    "sg:province":"CA",
    "sg:tags":[
        "card"
    ],
    "wof:name":"Maida Specialties Company.",
    "wof:placetype":"venue"
},
  "geometry": {"coordinates":[-121.879436,37.325051],"type":"Point"}
}