{
  "type": "Feature",
  "properties": {
    "iso:country":"US",
    "sg:address":"700 W 7th St",
    "sg:city":"Los Angeles",
    "sg:classifiers":[
        {
            "category":"Freight",
            "type":"Transportation"
        }
    ],
    "sg:phone":"+1 213 489 9947",
    "sg:postcode":"90017",
    "sg:province":"CA",
    "sg:tags":[
        "operator",
        "trucking"
    ],
    "wof:name":"Coast Runners",
    "wof:placetype":"venue"
},
  "geometry": {"coordinates":[-118.258765,34.048688],"type":"Point"}
}