{
  "type": "Feature",
  "properties": {
    "iso:country":"US",
    "sg:address":"4570 Gage Ave",
    "sg:city":"Bell",
    "sg:classifiers":[
        {
            "category":"Professional",
            "type":"Services"
        }
    ],
    "sg:phone":"+1 323 771 6346",
    "sg:postcode":"90201",
    "sg:province":"CA",
    "sg:tags":[
        "automotive"
    ],
    "wof:name":"Maurice J Sopp",
    "wof:placetype":"venue"
},
  "geometry": {"coordinates":[-118.185098,33.977222],"type":"Point"}
}