{
  "type": "Feature",
  "properties": {
    "iso:country":"US",
    "sg:address":"620 Blossom Hill Rd",
    "sg:city":"Los Gatos",
    "sg:classifiers":[
        {
            "category":"Autos & Motor Vehicles",
            "subcategory":"Automobile Sales",
            "type":"Retail Goods"
        },
        {
            "category":"Autos & Motor Vehicles",
            "subcategory":"Auto Supplies",
            "type":"Retail Goods"
        },
        {
            "category":"Retail",
            "subcategory":"Auto Repair",
            "type":"Services"
        }
    ],
    "sg:phone":"+1 408 354 4000",
    "sg:postcode":"95032",
    "sg:province":"CA",
    "sg:tags":[
        "car",
        "part"
    ],
    "sg:website":"www.losgatosluxcars.com",
    "wof:name":"Los Gatos Luxury Cars",
    "wof:placetype":"venue"
},
  "geometry": {"coordinates":[-121.966109,37.235594],"type":"Point"}
}