{
  "type": "Feature",
  "properties": {
    "iso:country":"US",
    "sg:address":"12859 W Chapman Ave",
    "sg:city":"Garden Grove",
    "sg:classifiers":[
        {
            "category":"Food & Beverages",
            "subcategory":"Bakery",
            "type":"Retail Goods"
        }
    ],
    "sg:phone":"+1 714 750 7675",
    "sg:postcode":"92840",
    "sg:province":"CA",
    "wof:name":"La Abejita",
    "wof:placetype":"venue"
},
  "geometry": {"coordinates":[-117.90727800000001,33.788943],"type":"Point"}
}