{
  "type": "Feature",
  "properties": {
    "iso:country":"US",
    "sg:address":"6501 Crown Blvd Ste 104",
    "sg:city":"San Jose",
    "sg:classifiers":[
        {
            "category":"Health Services",
            "subcategory":"Dentist",
            "type":"Services"
        }
    ],
    "sg:phone":"+1 408 268 5531",
    "sg:postcode":"95120",
    "sg:province":"CA",
    "wof:name":"Almaden Valley Professional Center",
    "wof:placetype":"venue"
},
  "geometry": {"coordinates":[-121.86149,37.218854],"type":"Point"}
}