{
  "type": "Feature",
  "properties": {
    "addr:full":"15374 Lone Eagle St Victorville CA 92395",
    "addr:housenumber":"15374",
    "addr:postcode":"92395",
    "addr:street":"Lone Eagle St",
    "iso:country":"US",
    "sg:address":"15374 Lone Eagle St",
    "sg:city":"Victorville",
    "sg:classifiers":[
        {
            "category":"Shopping",
            "subcategory":"Pets & Pet Supplies",
            "type":"Retail Goods"
        }
    ],
    "sg:phone":"+1 760 241 8795",
    "sg:postcode":"92395",
    "sg:province":"CA",
    "sg:tags":[
        "furnishing",
        "dog",
        "store",
        "cat"
    ],
    "wof:name":"Smiley Girl Pet-Sitting",
    "wof:placetype":"venue"
},
  "geometry": {"coordinates":[-117.328103,34.481563],"type":"Point"}
}