{
  "type": "Feature",
  "properties": {
    "addr:full":"546 W Kelso St Inglewood CA 90301",
    "addr:housenumber":"546",
    "addr:postcode":"90301",
    "addr:street":"W Kelso St",
    "iso:country":"US",
    "sg:address":"546 W Kelso St",
    "sg:city":"Inglewood",
    "sg:classifiers":[
        {
            "category":"Professional",
            "type":"Services"
        }
    ],
    "sg:phone":"+1 310 674 1875",
    "sg:postcode":"90301",
    "sg:province":"CA",
    "sg:tags":[
        "establishment"
    ],
    "wof:name":"Aquatic Image Reefs",
    "wof:placetype":"venue"
},
  "geometry": {"coordinates":[-118.365179,33.958699],"type":"Point"}
}