{
  "type": "Feature",
  "properties": {
    "iso:country":"US",
    "sg:address":"2252 D St",
    "sg:city":"La Verne",
    "sg:classifiers":[
        {
            "category":"Shopping",
            "subcategory":"Florist",
            "type":"Retail Goods"
        }
    ],
    "sg:phone":"+1 909 596 2714",
    "sg:postcode":"91750",
    "sg:province":"CA",
    "wof:name":"LA Verne Florist",
    "wof:placetype":"venue"
},
  "geometry": {"coordinates":[-117.770258,34.099954],"type":"Point"}
}