{
  "type": "Feature",
  "properties": {
    "addr:full":"25647 Whitman St Hayward CA 94544",
    "addr:housenumber":"25647",
    "addr:postcode":"94544",
    "addr:street":"Whitman St",
    "iso:country":"US",
    "sg:address":"25647 Whitman St",
    "sg:city":"Hayward",
    "sg:classifiers":[
        {
            "category":"Manufacturing",
            "subcategory":"Tools & Machinery",
            "type":"Manufacturing & Wholesale Goods"
        }
    ],
    "sg:phone":"+1 510 881 0637",
    "sg:postcode":"94544",
    "sg:province":"CA",
    "sg:tags":[
        "machine",
        "mfg"
    ],
    "wof:name":"Lee Olez Homeworkers Info",
    "wof:placetype":"venue"
},
  "geometry": {"coordinates":[-122.07294,37.653864],"type":"Point"}
}