{
  "type": "Feature",
  "properties": {
    "addr:full":"126 E 36th St Long Beach CA 90807",
    "addr:housenumber":"126",
    "addr:postcode":"90807",
    "addr:street":"E 36Th St",
    "iso:country":"US",
    "sg:address":"126 E 36th St",
    "sg:city":"Long Beach",
    "sg:classifiers":[
        {
            "category":"Building & Trades",
            "subcategory":"Landscaping Services",
            "type":"Services"
        }
    ],
    "sg:phone":"+1 562 426 1115",
    "sg:postcode":"90807",
    "sg:province":"CA",
    "sg:tags":[
        "gardener",
        "landscape",
        "contractor"
    ],
    "wof:name":"Bob & Mimmy's Gardening",
    "wof:placetype":"venue"
},
  "geometry": {"coordinates":[-118.191973,33.822032],"type":"Point"}
}