{
  "type": "Feature",
  "properties": {
    "iso:country":"US",
    "sg:address":"3135 Tyler St",
    "sg:city":"Carlsbad",
    "sg:classifiers":[
        {
            "category":"Building & Trades",
            "subcategory":"Construction",
            "type":"Services"
        }
    ],
    "sg:phone":"+1 760 434 0192",
    "sg:postcode":"92008",
    "sg:province":"CA",
    "sg:tags":[
        "maker",
        "cabinet"
    ],
    "wof:name":"Landco Cabinet Shop",
    "wof:placetype":"venue"
},
  "geometry": {"coordinates":[-117.346766,33.158023],"type":"Point"}
}