{
  "type": "Feature",
  "properties": {
    "iso:country":"US",
    "sg:address":"18431 Wilmington Ave",
    "sg:city":"Carson",
    "sg:classifiers":[
        {
            "category":"Home & Garden",
            "subcategory":"Furniture",
            "type":"Retail Goods"
        }
    ],
    "sg:phone":"+1 310 608 6838",
    "sg:postcode":"90746",
    "sg:province":"CA",
    "sg:tags":[
        "store"
    ],
    "wof:name":"Sit N Sleep",
    "wof:placetype":"venue"
},
  "geometry": {"coordinates":[-118.23699999999999,33.8563],"type":"Point"}
}