{
  "type": "Feature",
  "properties": {
    "addr:full":"298 Skyline Dr Daly City CA 94015",
    "addr:housenumber":"298",
    "addr:postcode":"94015",
    "addr:street":"Skyline Dr",
    "iso:country":"US",
    "sg:address":"298 Skyline Dr",
    "sg:city":"Daly City",
    "sg:classifiers":[
        {
            "category":"Real Estate",
            "subcategory":"Real Estate Agent",
            "type":"Services"
        }
    ],
    "sg:phone":"+1 650 756 1500",
    "sg:postcode":"94015",
    "sg:province":"CA",
    "wof:name":"Burkhead Realty",
    "wof:placetype":"venue"
},
  "geometry": {"coordinates":[-122.492009,37.68908],"type":"Point"}
}