{
  "type": "Feature",
  "properties": {
    "addr:full":"711 Webster St Oakland CA 94607",
    "addr:housenumber":"711",
    "addr:postcode":"94607",
    "addr:street":"Webster St",
    "iso:country":"US",
    "sg:address":"711 Webster St",
    "sg:city":"Oakland",
    "sg:classifiers":[
        {
            "category":"Wholesale",
            "subcategory":"Fruits & Vegetables",
            "type":"Manufacturing & Wholesale Goods"
        },
        {
            "category":"Food & Beverages",
            "subcategory":"Ethnic Foods",
            "type":"Retail Goods"
        }
    ],
    "sg:phone":"+1 510 663 1828",
    "sg:postcode":"94607",
    "sg:province":"CA",
    "sg:tags":[
        "veggie"
    ],
    "wof:name":"Ivy's Food & Trading",
    "wof:placetype":"venue"
},
  "geometry": {"coordinates":[-122.271716,37.79875],"type":"Point"}
}