{
  "type": "Feature",
  "properties": {
    "iso:country":"US",
    "sg:address":"160 Guthrie Ln Ste 3",
    "sg:city":"Brentwood",
    "sg:classifiers":[
        {
            "category":"Banks & Credit Unions",
            "subcategory":"Investment Brokerage",
            "type":"Services"
        },
        {
            "category":"Banks & Credit Unions",
            "subcategory":"Financial Services",
            "type":"Services"
        }
    ],
    "sg:phone":"+1 925 420 5310",
    "sg:postcode":"94513",
    "sg:province":"CA",
    "sg:tags":[
        "advisory",
        "planner"
    ],
    "wof:name":"Ridgewood Power Management",
    "wof:placetype":"venue"
},
  "geometry": {"coordinates":[-121.682671,37.923666],"type":"Point"}
}