{
  "type": "Feature",
  "properties": {
    "iso:country":"US",
    "sg:address":"4221 E Mariposa Rd",
    "sg:city":"Stockton",
    "sg:classifiers":[
        {
            "category":"Professional",
            "subcategory":"Testing Lab",
            "type":"Services"
        }
    ],
    "sg:phone":"+1 209 948 0241",
    "sg:postcode":"95215",
    "sg:province":"CA",
    "sg:tags":[
        "laboratory"
    ],
    "wof:name":"Pacific Coast Laboratory",
    "wof:placetype":"venue"
},
  "geometry": {"coordinates":[-121.221828,37.929979],"type":"Point"}
}