{
  "type": "Feature",
  "properties": {
    "addr:full":"7647 Hornbill Ave San Diego CA 92123",
    "addr:housenumber":"7647",
    "addr:postcode":"92123",
    "addr:street":"Hornbill Ave",
    "iso:country":"US",
    "sg:address":"7647 Hornbill Ave",
    "sg:city":"San Diego",
    "sg:classifiers":[
        {
            "category":"Professional",
            "subcategory":"Management & Consulting",
            "type":"Services"
        }
    ],
    "sg:phone":"+1 858 268 3211",
    "sg:postcode":"92123",
    "sg:province":"CA",
    "sg:tags":[
        "consultant",
        "safety"
    ],
    "wof:name":"Cpr Plus-Safety Training Specs",
    "wof:placetype":"venue"
},
  "geometry": {"coordinates":[-117.161524,32.78151],"type":"Point"}
}