{
  "type": "Feature",
  "properties": {
    "addr:full":"692 Pecos River Ct San Jose CA 95111",
    "addr:housenumber":"692",
    "addr:postcode":"95111",
    "addr:street":"Pecos River Ct",
    "iso:country":"US",
    "sg:address":"692 Pecos River Ct",
    "sg:city":"San Jose",
    "sg:classifiers":[
        {
            "category":"Building & Trades",
            "subcategory":"Landscaping Services",
            "type":"Services"
        }
    ],
    "sg:phone":"+1 408 363 1154",
    "sg:postcode":"95111",
    "sg:province":"CA",
    "wof:name":"Azores Gardening Service",
    "wof:placetype":"venue"
},
  "geometry": {"coordinates":[-121.83497,37.298791],"type":"Point"}
}