{
  "type": "Feature",
  "properties": {
    "addr:full":"3400 E 2nd St Benicia CA 94510",
    "addr:housenumber":"3400",
    "addr:postcode":"94510",
    "addr:street":"E 2Nd St",
    "iso:country":"US",
    "sg:address":"3400 E 2nd St",
    "sg:city":"Benicia",
    "sg:classifiers":[
        {
            "category":"Railroad",
            "type":"Transportation"
        }
    ],
    "sg:phone":"+1 707 745 1530",
    "sg:postcode":"94510",
    "sg:province":"CA",
    "sg:tags":[
        "rail"
    ],
    "wof:name":"Rail Serve",
    "wof:placetype":"venue"
},
  "geometry": {"coordinates":[-122.146332,38.07128],"type":"Point"}
}