{
  "type": "Feature",
  "properties": {
    "iso:country":"US",
    "sg:address":"5533 55th St",
    "sg:city":"Sacramento",
    "sg:classifiers":[
        {
            "category":"Building & Trades",
            "subcategory":"Landscaping Services",
            "type":"Services"
        }
    ],
    "sg:phone":"+1 916 451 3963",
    "sg:postcode":"95820",
    "sg:province":"CA",
    "sg:tags":[
        "lawn",
        "maintenance",
        "grounds"
    ],
    "wof:name":"Robert Pipkens Gardening Svc",
    "wof:placetype":"venue"
},
  "geometry": {"coordinates":[-121.441081,38.526659],"type":"Point"}
}