{
  "type": "Feature",
  "properties": {
    "addr:full":"21044 Sherman Way Canoga Park CA 91303",
    "addr:housenumber":"21044",
    "addr:postcode":"91303",
    "addr:street":"Sherman Way",
    "iso:country":"US",
    "sg:address":"21044 Sherman Way",
    "sg:city":"Canoga Park",
    "sg:classifiers":[
        {
            "category":"Banks & Credit Unions",
            "subcategory":"Bank",
            "type":"Services"
        }
    ],
    "sg:phone":"+1 818 593 4240",
    "sg:postcode":"91303",
    "sg:province":"CA",
    "sg:tags":[
        "cashing",
        "check"
    ],
    "wof:name":"Envious Mi Tierra",
    "wof:placetype":"venue"
},
  "geometry": {"coordinates":[-118.592007,34.200858],"type":"Point"}
}