{
  "type": "Feature",
  "properties": {
    "addr:full":"18791 Rugged Trl Sonora CA 95370",
    "addr:housenumber":"18791",
    "addr:postcode":"95370",
    "addr:street":"Rugged Trl",
    "iso:country":"US",
    "sg:address":"18791 Rugged Trl",
    "sg:city":"Sonora",
    "sg:classifiers":[
        {
            "category":"Professional",
            "type":"Services"
        }
    ],
    "sg:phone":"+1 209 847 2007",
    "sg:postcode":"95370",
    "sg:province":"CA",
    "wof:name":"Oakdale Chapter 1029 Wome",
    "wof:placetype":"venue"
},
  "geometry": {"coordinates":[-120.333866,37.963249],"type":"Point"}
}