{
  "type": "Feature",
  "properties": {
    "iso:country":"US",
    "sg:address":"8008 Melrose Ave",
    "sg:city":"Los Angeles",
    "sg:classifiers":[
        {
            "category":"Shopping",
            "subcategory":"Clothing, Apparel, & Fashions",
            "type":"Retail Goods"
        }
    ],
    "sg:phone":"+1 323 653 6960",
    "sg:postcode":"90046",
    "sg:province":"CA",
    "sg:tags":[
        "theatrical",
        "costume"
    ],
    "wof:name":"Office",
    "wof:placetype":"venue"
},
  "geometry": {"coordinates":[-118.364661,34.08369],"type":"Point"}
}