{
  "type": "Feature",
  "properties": {
    "iso:country":"US",
    "sg:address":"53651 State Hwy 371",
    "sg:city":"Anza",
    "sg:classifiers":[
        {
            "category":"Building & Trades",
            "subcategory":"Landscaping Services",
            "type":"Services"
        }
    ],
    "sg:phone":"+1 951 763 4160",
    "sg:postcode":"92539",
    "sg:province":"CA",
    "sg:tags":[
        "landscape",
        "contractor"
    ],
    "wof:name":"Garden In The Pines",
    "wof:placetype":"venue"
},
  "geometry": {"coordinates":[-116.713826,33.549981],"type":"Point"}
}