{
  "type": "Feature",
  "properties": {
    "addr:full":"4230 Clayton Rd Concord CA 94521",
    "addr:housenumber":"4230",
    "addr:postcode":"94521",
    "addr:street":"Clayton Rd",
    "iso:country":"US",
    "sg:address":"4230 Clayton Rd",
    "sg:city":"Concord",
    "sg:classifiers":[
        {
            "category":"Social Services",
            "subcategory":"Adult Care",
            "type":"Services"
        }
    ],
    "sg:phone":"+1 925 676 3410",
    "sg:postcode":"94521",
    "sg:province":"CA",
    "sg:tags":[
        "home",
        "residential"
    ],
    "wof:name":"Concord Royale",
    "wof:placetype":"venue"
},
  "geometry": {"coordinates":[-121.996267,37.966069],"type":"Point"}
}