{
  "type": "Feature",
  "properties": {
    "addr:full":"308 14th St Oakland CA 94612",
    "addr:housenumber":"308",
    "addr:postcode":"94612",
    "addr:street":"14Th St",
    "iso:country":"US",
    "sg:address":"308 14th St",
    "sg:city":"Oakland",
    "sg:classifiers":[
        {
            "category":"Restaurant",
            "type":"Food & Drink"
        }
    ],
    "sg:phone":"+1 510 839 3998",
    "sg:postcode":"94612",
    "sg:province":"CA",
    "wof:name":"Hyang Won Korean Restaurant",
    "wof:placetype":"venue"
},
  "geometry": {"coordinates":[-122.268608,37.803415],"type":"Point"}
}