{
  "type": "Feature",
  "properties": {
    "addr:full":"108 N Russ Ave King City CA 93930",
    "addr:housenumber":"108",
    "addr:postcode":"93930",
    "addr:street":"N Russ Ave",
    "iso:country":"US",
    "sg:address":"108 N Russ Ave",
    "sg:city":"King City",
    "sg:classifiers":[
        {
            "category":"Insurance",
            "subcategory":"Insurance Agent",
            "type":"Services"
        }
    ],
    "sg:phone":"+1 831 385 6777",
    "sg:postcode":"93930",
    "sg:province":"CA",
    "wof:name":"State Farm Insurance",
    "wof:placetype":"venue"
},
  "geometry": {"coordinates":[-121.129634,36.21232],"type":"Point"}
}