{
  "type": "Feature",
  "properties": {
    "iso:country":"US",
    "sg:address":"50 3rd St",
    "sg:city":"San Francisco",
    "sg:classifiers":[
        {
            "category":"Travel",
            "subcategory":"Hotels & Motels",
            "type":"Entertainment"
        }
    ],
    "sg:phone":"+1 415 974 6400",
    "sg:postcode":"94103",
    "sg:province":"CA",
    "sg:website":"westin.com/marketstreet",
    "wof:name":"The Westin San Francisco Market Street",
    "wof:placetype":"venue"
},
  "geometry": {"coordinates":[-122.402812,37.786695],"type":"Point"}
}