{
  "type": "Feature",
  "properties": {
    "iso:country":"US",
    "sg:address":"4728 W 1st St",
    "sg:city":"Santa Ana",
    "sg:classifiers":[
        {
            "category":"Banks & Credit Unions",
            "subcategory":"Investment Brokerage",
            "type":"Services"
        }
    ],
    "sg:phone":"+1 714 839 4298",
    "sg:postcode":"92703",
    "sg:province":"CA",
    "sg:tags":[
        "advisory",
        "financial"
    ],
    "wof:name":"Best Investment Real Estate",
    "wof:placetype":"venue"
},
  "geometry": {"coordinates":[-117.93134000000001,33.745004],"type":"Point"}
}