{
  "type": "Feature",
  "properties": {
    "iso:country":"US",
    "sg:address":"3411 W Shaw Ave",
    "sg:city":"Fresno",
    "sg:classifiers":[
        {
            "category":"Banks & Credit Unions",
            "subcategory":"Bank",
            "type":"Services"
        }
    ],
    "sg:phone":"+1 559 486 2251",
    "sg:postcode":"93711",
    "sg:province":"CA",
    "sg:tags":[
        "national",
        "commercial"
    ],
    "wof:name":"Bank Of America",
    "wof:placetype":"venue"
},
  "geometry": {"coordinates":[-119.853007,36.808191],"type":"Point"}
}