{
  "type": "Feature",
  "properties": {
    "iso:country":"US",
    "sg:address":"8695 Irvine Center Dr",
    "sg:city":"Irvine",
    "sg:classifiers":[
        {
            "category":"Restaurant",
            "type":"Food & Drink"
        }
    ],
    "sg:phone":"+1 949 727 2150",
    "sg:postcode":"92618",
    "sg:province":"CA",
    "wof:name":"Burger King",
    "wof:placetype":"venue"
},
  "geometry": {"coordinates":[-117.750249,33.659525],"type":"Point"}
}