{
  "type": "Feature",
  "properties": {
    "addr:full":"1872 Java Ln Lemon Grove CA 91945",
    "addr:housenumber":"1872",
    "addr:postcode":"91945",
    "addr:street":"Java Ln",
    "iso:country":"US",
    "sg:address":"1872 Java Ln",
    "sg:city":"Lemon Grove",
    "sg:classifiers":[
        {
            "category":"Professional",
            "type":"Services"
        }
    ],
    "sg:phone":"+1 619 469 4868",
    "sg:postcode":"91945",
    "sg:province":"CA",
    "sg:tags":[
        "establishment"
    ],
    "wof:name":"B Steinstra Inc & Assoc",
    "wof:placetype":"venue"
},
  "geometry": {"coordinates":[-117.02549,32.725939],"type":"Point"}
}