{
  "type": "Feature",
  "properties": {
    "addr:full":"4801 Blue Gum Ave Modesto CA 95358",
    "addr:housenumber":"4801",
    "addr:postcode":"ca 95358",
    "addr:street":"Blue Gum Ave",
    "iso:country":"US",
    "sg:address":"4801 Blue Gum Ave",
    "sg:city":"Modesto",
    "sg:classifiers":[
        {
            "category":"Farming",
            "subcategory":"Crops",
            "type":"Manufacturing & Wholesale Goods"
        }
    ],
    "sg:phone":"+1 209 529 0687",
    "sg:postcode":"95358",
    "sg:province":"CA",
    "sg:tags":[
        "grove",
        "nut",
        "tree"
    ],
    "wof:name":"Dunlop Almond Hulling",
    "wof:placetype":"venue"
},
  "geometry": {"coordinates":[-121.074305,37.660075],"type":"Point"}
}