{
  "type": "Feature",
  "properties": {
    "addr:full":"425 E Manchester Boulevard Inglewood CA 90301",
    "addr:housenumber":"425",
    "addr:postcode":"90301",
    "addr:street":"E Manchester Boulevard",
    "iso:country":"US",
    "sg:address":"425 E Manchester Boulevard",
    "sg:city":"Inglewood",
    "sg:classifiers":[
        {
            "category":"Shopping",
            "subcategory":"Mobile Phones",
            "type":"Retail Goods"
        }
    ],
    "sg:phone":"+1 310 677 6139",
    "sg:postcode":"90301",
    "sg:province":"CA",
    "sg:website":"www.radioshack.com",
    "wof:name":"Radioshack",
    "wof:placetype":"venue"
},
  "geometry": {"coordinates":[-118.349986,33.961821],"type":"Point"}
}