{
  "type": "Feature",
  "properties": {
    "iso:country":"US",
    "sg:address":"1651 Whipple Rd",
    "sg:city":"Hayward",
    "sg:classifiers":[
        {
            "category":"Wholesale",
            "subcategory":"Electrical",
            "type":"Manufacturing & Wholesale Goods"
        }
    ],
    "sg:phone":"+1 510 489 5246",
    "sg:postcode":"94544",
    "sg:province":"CA",
    "sg:tags":[
        "equipment",
        "testing",
        "electronic"
    ],
    "sg:website":"www.44tesla.com",
    "wof:name":"TESLA",
    "wof:placetype":"venue"
},
  "geometry": {"coordinates":[-122.050484,37.605996],"type":"Point"}
}