{
  "type": "Feature",
  "properties": {
    "addr:full":"525 South Dr Mountain View CA 94040",
    "addr:housenumber":"525",
    "addr:postcode":"94040",
    "addr:street":"South Dr",
    "iso:country":"US",
    "sg:address":"525 South Dr",
    "sg:city":"Mountain View",
    "sg:classifiers":[
        {
            "category":"Health Services",
            "subcategory":"Doctor",
            "type":"Services"
        }
    ],
    "sg:phone":"+1 650 967 7471",
    "sg:postcode":"94040",
    "sg:province":"CA",
    "sg:tags":[
        "medicine",
        "sport"
    ],
    "wof:name":"Patel Pravin MD",
    "wof:placetype":"venue"
},
  "geometry": {"coordinates":[-122.084,37.367298],"type":"Point"}
}