{
  "type": "Feature",
  "properties": {
    "iso:country":"US",
    "sg:address":"2901 W Coast Hwy",
    "sg:city":"Newport Beach",
    "sg:classifiers":[
        {
            "category":"Professional",
            "subcategory":"Engineering",
            "type":"Services"
        }
    ],
    "sg:phone":"+1 949 270 2924",
    "sg:postcode":"92663",
    "sg:province":"CA",
    "sg:tags":[
        "engineer"
    ],
    "wof:name":"BCM Consulting LLC",
    "wof:placetype":"venue"
},
  "geometry": {"coordinates":[-117.92790599999999,33.621204],"type":"Point"}
}