{
  "type": "Feature",
  "properties": {
    "addr:full":"2165 Arnold Way Alpine CA 91901",
    "addr:housenumber":"2165",
    "addr:postcode":"91901",
    "addr:street":"Arnold Way",
    "iso:country":"US",
    "sg:address":"2165 Arnold Way",
    "sg:city":"Alpine",
    "sg:classifiers":[
        {
            "category":"Shopping",
            "subcategory":"Computers & Home Electronics",
            "type":"Retail Goods"
        }
    ],
    "sg:phone":"+1 619 659 1414",
    "sg:postcode":"91901",
    "sg:province":"CA",
    "sg:tags":[
        "game",
        "video"
    ],
    "wof:name":"Pizza World",
    "wof:placetype":"venue"
},
  "geometry": {"coordinates":[-116.767078,32.835276],"type":"Point"}
}