{
  "type": "Feature",
  "properties": {
    "addr:full":"414 E Haley St Santa Barbara CA 93101",
    "addr:housenumber":"414",
    "addr:postcode":"93101",
    "addr:street":"E Haley St",
    "iso:country":"US",
    "sg:address":"414 E Haley St",
    "sg:city":"Santa Barbara",
    "sg:classifiers":[
        {
            "category":"Personal",
            "subcategory":"Beauty Salon",
            "type":"Services"
        }
    ],
    "sg:phone":"+1 805 882 2286",
    "sg:postcode":"93101",
    "sg:province":"CA",
    "wof:name":"Renewal Hair Salon",
    "wof:placetype":"venue"
},
  "geometry": {"coordinates":[-119.68992299999999,34.421905],"type":"Point"}
}