{
  "type": "Feature",
  "properties": {
    "iso:country":"US",
    "sg:address":"24640 Town Center Dr",
    "sg:city":"Valencia",
    "sg:classifiers":[
        {
            "category":"Real Estate",
            "subcategory":"Real Estate Operator",
            "type":"Services"
        }
    ],
    "sg:phone":"+1 661 290 2882",
    "sg:postcode":"91355",
    "sg:province":"CA",
    "sg:tags":[
        "apartment"
    ],
    "sg:website":"www.equityapartments.com/Los-Ang...",
    "wof:name":"Montecito",
    "wof:placetype":"venue"
},
  "geometry": {"coordinates":[-118.56564299999999,34.418826],"type":"Point"}
}