{
  "type": "Feature",
  "properties": {
    "iso:country":"US",
    "sg:address":"573 Tully Rd",
    "sg:city":"San Jose",
    "sg:classifiers":[
        {
            "category":"Manufacturing",
            "subcategory":"Printing",
            "type":"Manufacturing & Wholesale Goods"
        }
    ],
    "sg:phone":"+1 408 294 5225",
    "sg:postcode":"95111",
    "sg:province":"CA",
    "sg:tags":[
        "commercial"
    ],
    "wof:name":"T D Printing",
    "wof:placetype":"venue"
},
  "geometry": {"coordinates":[-121.84996,37.30644],"type":"Point"}
}