{
  "type": "Feature",
  "properties": {
    "addr:full":"836 Southampton Rd Benicia CA 94510",
    "addr:housenumber":"836",
    "addr:postcode":"94510",
    "addr:street":"Southampton Rd",
    "iso:country":"US",
    "sg:address":"836 Southampton Rd",
    "sg:city":"Benicia",
    "sg:classifiers":[
        {
            "category":"Personal",
            "type":"Services"
        }
    ],
    "sg:phone":"+1 707 746 7813",
    "sg:postcode":"94510",
    "sg:province":"CA",
    "sg:tags":[
        "mail",
        "receiving"
    ],
    "wof:name":"Mail Place",
    "wof:placetype":"venue"
},
  "geometry": {"coordinates":[-122.16588400000001,38.066839],"type":"Point"}
}