{
  "type": "Feature",
  "properties": {
    "iso:country":"US",
    "sg:address":"2415 Third Street",
    "sg:city":"San Francisco",
    "sg:classifiers":[
        {
            "category":"Professional",
            "subcategory":"Computer Services",
            "type":"Services"
        }
    ],
    "sg:phone":"+1 415 230 2357",
    "sg:postcode":"94107",
    "sg:province":"CA",
    "sg:tags":[
        "social-network",
        "community",
        "management",
        "tribe"
    ],
    "sg:website":"http://www.stribe.com/",
    "wof:name":"Stribe",
    "wof:placetype":"venue"
},
  "geometry": {"coordinates":[-122.388289,37.759418],"type":"Point"}
}