{
  "type": "Feature",
  "properties": {
    "iso:country":"US",
    "sg:address":"101 N Irwin St",
    "sg:city":"Hanford",
    "sg:classifiers":[
        {
            "category":"Professional",
            "type":"Services"
        },
        {
            "category":"Restaurant",
            "type":"Food & Drink"
        }
    ],
    "sg:phone":"+1 559 587 9900",
    "sg:postcode":"93230",
    "sg:province":"CA",
    "wof:name":"Senor Boogies",
    "wof:placetype":"venue"
},
  "geometry": {"coordinates":[-119.647409,36.326907],"type":"Point"}
}