{
  "type": "Feature",
  "properties": {
    "addr:full":"8484 Wilshire Blvd Beverly Hills CA 90211",
    "addr:housenumber":"8484",
    "addr:postcode":"90211",
    "addr:street":"Wilshire Blvd",
    "iso:country":"US",
    "sg:address":"8484 Wilshire Blvd",
    "sg:city":"Beverly Hills",
    "sg:classifiers":[
        {
            "category":"Professional",
            "subcategory":"Management & Consulting",
            "type":"Services"
        }
    ],
    "sg:phone":"+1 323 966 1599",
    "sg:postcode":"90211",
    "sg:province":"CA",
    "sg:tags":[
        "consultant",
        "business"
    ],
    "wof:name":"Management Group Inc",
    "wof:placetype":"venue"
},
  "geometry": {"coordinates":[-118.37554,34.064925],"type":"Point"}
}