{
  "type": "Feature",
  "properties": {
    "iso:country":"US",
    "sg:address":"224 W Santa Maria St",
    "sg:city":"Santa Paula",
    "sg:classifiers":[
        {
            "category":"Freight",
            "type":"Transportation"
        }
    ],
    "sg:phone":"+1 805 525 2111",
    "sg:postcode":"93060",
    "sg:province":"CA",
    "sg:tags":[
        "trucking"
    ],
    "wof:name":"Construction Trucking Svc Inc",
    "wof:placetype":"venue"
},
  "geometry": {"coordinates":[-119.075314,34.341176],"type":"Point"}
}