{
  "type": "Feature",
  "properties": {
    "addr:full":"1331 Garden Hwy Sacramento CA 95833",
    "addr:housenumber":"1331",
    "addr:postcode":"95833",
    "addr:street":"Garden Hwy",
    "iso:country":"US",
    "sg:address":"1331 Garden Hwy",
    "sg:city":"Sacramento",
    "sg:classifiers":[
        {
            "category":"Shopping",
            "subcategory":"Computers & Home Electronics",
            "type":"Retail Goods"
        }
    ],
    "sg:phone":"+1 916 646 5300",
    "sg:postcode":"95833",
    "sg:province":"CA",
    "sg:tags":[
        "equipment",
        "dealer"
    ],
    "wof:name":"Unisys Corp",
    "wof:placetype":"venue"
},
  "geometry": {"coordinates":[-121.499573,38.607863],"type":"Point"}
}