{
  "type": "Feature",
  "properties": {
    "iso:country":"US",
    "sg:address":"3243 Fairmount Ave",
    "sg:city":"San Diego",
    "sg:classifiers":[
        {
            "category":"Food & Beverages",
            "subcategory":"Liquor & Beverages",
            "type":"Retail Goods"
        }
    ],
    "sg:phone":"+1 619 281 1486",
    "sg:postcode":"92105",
    "sg:province":"CA",
    "wof:name":"Maddox Liquor & Grocery",
    "wof:placetype":"venue"
},
  "geometry": {"coordinates":[-117.100886,32.739761],"type":"Point"}
}