{
  "type": "Feature",
  "properties": {
    "addr:full":"2118 Zanker Road San Jose CA 95131",
    "addr:housenumber":"2118",
    "addr:postcode":"95131",
    "addr:street":"Zanker Road",
    "iso:country":"US",
    "sg:address":"2118 Zanker Road",
    "sg:city":"San Jose",
    "sg:classifiers":[
        {
            "category":"Building & Trades",
            "subcategory":"Plumbing",
            "type":"Services"
        },
        {
            "category":"Building & Trades",
            "subcategory":"Construction",
            "type":"Services"
        }
    ],
    "sg:phone":"+1 408 834 1137",
    "sg:postcode":"95131",
    "sg:province":"CA",
    "sg:tags":[
        "contractor"
    ],
    "sg:website":"www.bathfitter.com",
    "wof:name":"Bath Fitter",
    "wof:placetype":"venue"
},
  "geometry": {"coordinates":[-121.915087,37.379384],"type":"Point"}
}