{
  "type": "Feature",
  "properties": {
    "addr:full":"1928 E Edinger Ave Santa Ana CA 92705",
    "addr:housenumber":"1928",
    "addr:postcode":"92705",
    "addr:street":"E Edinger Ave",
    "iso:country":"US",
    "sg:address":"1928 E Edinger Ave",
    "sg:city":"Santa Ana",
    "sg:classifiers":[
        {
            "category":"Building & Trades",
            "subcategory":"Plumbing",
            "type":"Services"
        }
    ],
    "sg:phone":"+1 714 566 0850",
    "sg:postcode":"92705",
    "sg:province":"CA",
    "wof:name":"Network Rooter & Plumbing Inc",
    "wof:placetype":"venue"
},
  "geometry": {"coordinates":[-117.839996,33.726601],"type":"Point"}
}