{
  "type": "Feature",
  "properties": {
    "iso:country":"US",
    "sg:address":"Southland Mall",
    "sg:city":"Hayward",
    "sg:classifiers":[
        {
            "category":"Communications",
            "subcategory":"Newspaper",
            "type":"Services"
        }
    ],
    "sg:phone":"+1 510 783 3722",
    "sg:postcode":"94541",
    "sg:province":"CA",
    "sg:tags":[
        "magazine"
    ],
    "wof:name":"Waldenbooks",
    "wof:placetype":"venue"
},
  "geometry": {"coordinates":[-122.089996,37.6745],"type":"Point"}
}