{
  "type": "Feature",
  "properties": {
    "iso:country":"US",
    "sg:address":"990 Highland Dr",
    "sg:city":"Solana Beach",
    "sg:classifiers":[
        {
            "category":"Professional",
            "subcategory":"Accounting & Tax Preparation",
            "type":"Services"
        }
    ],
    "sg:phone":"+1 858 792 1716",
    "sg:postcode":"92075",
    "sg:province":"CA",
    "sg:tags":[
        "accountant"
    ],
    "wof:name":"K K Quon & Co",
    "wof:placetype":"venue"
},
  "geometry": {"coordinates":[-117.256494,32.983551],"type":"Point"}
}