{
  "type": "Feature",
  "properties": {
    "addr:full":"191 E Yorba Linda Blvd Placentia CA 92870",
    "addr:housenumber":"191",
    "addr:postcode":"ca 92870",
    "addr:street":"E Yorba Linda Blvd",
    "iso:country":"US",
    "sg:address":"191 E Yorba Linda Blvd",
    "sg:city":"Placentia",
    "sg:classifiers":[
        {
            "category":"Banks & Credit Unions",
            "subcategory":"Bank",
            "type":"Services"
        },
        {
            "category":"Banks & Credit Unions",
            "subcategory":"Financial Services",
            "type":"Services"
        }
    ],
    "sg:phone":"+1 800 872 2657",
    "sg:postcode":"92870",
    "sg:province":"CA",
    "sg:tags":[
        "commercial",
        "saving"
    ],
    "sg:website":"http://usbank.com",
    "wof:name":"U.S. Bank ATM",
    "wof:placetype":"venue"
},
  "geometry": {"coordinates":[-117.863579,33.88785],"type":"Point"}
}