{
  "type": "Feature",
  "properties": {
    "addr:full":"4206 E White Ave Fresno CA 93702",
    "addr:housenumber":"4206",
    "addr:postcode":"93702",
    "addr:street":"E White Ave",
    "iso:country":"US",
    "sg:address":"4206 E White Ave",
    "sg:city":"Fresno",
    "sg:classifiers":[
        {
            "category":"Food & Beverages",
            "subcategory":"Groceries & Convenience Stores",
            "type":"Retail Goods"
        }
    ],
    "sg:phone":"+1 559 453 9082",
    "sg:postcode":"93702",
    "sg:province":"CA",
    "sg:tags":[
        "grocer"
    ],
    "wof:name":"Handi Stop Market",
    "wof:placetype":"venue"
},
  "geometry": {"coordinates":[-119.752223,36.751304],"type":"Point"}
}