{
  "type": "Feature",
  "properties": {
    "addr:full":"1275 Market St San Francisco CA 94103",
    "addr:housenumber":"1275",
    "addr:postcode":"94103",
    "addr:street":"Market St",
    "iso:country":"US",
    "sg:address":"1275 Market St",
    "sg:city":"San Francisco",
    "sg:classifiers":[
        {
            "category":"Insurance",
            "subcategory":"Insurance Agent",
            "type":"Services"
        }
    ],
    "sg:phone":"+1 415 565 1234",
    "sg:postcode":"94103",
    "sg:province":"CA",
    "sg:website":"www.scif.org",
    "wof:name":"State Compensation Ins Fund",
    "wof:placetype":"venue"
},
  "geometry": {"coordinates":[-122.41501700000001,37.778581],"type":"Point"}
}