{
  "type": "Feature",
  "properties": {
    "iso:country":"US",
    "sg:address":"3901 Cogswell Rd",
    "sg:city":"El Monte",
    "sg:classifiers":[
        {
            "category":"Professional",
            "type":"Services"
        }
    ],
    "sg:phone":"+1 323 283 3763",
    "sg:postcode":"91732",
    "sg:province":"CA",
    "wof:name":"Citizens For El Monte",
    "wof:placetype":"venue"
},
  "geometry": {"coordinates":[-118.013508,34.073705],"type":"Point"}
}