{
  "type": "Feature",
  "properties": {
    "addr:full":"115 New St Santa Cruz CA 95060",
    "addr:housenumber":"115",
    "addr:postcode":"95060",
    "addr:street":"New St",
    "iso:country":"US",
    "sg:address":"115 New St",
    "sg:city":"Santa Cruz",
    "sg:classifiers":[
        {
            "category":"Shopping",
            "subcategory":"Used Merchandise",
            "type":"Retail Goods"
        }
    ],
    "sg:phone":"+1 831 426 1906",
    "sg:postcode":"95060",
    "sg:province":"CA",
    "sg:tags":[
        "antique"
    ],
    "wof:name":"O'Hearn Toys & Antiques",
    "wof:placetype":"venue"
},
  "geometry": {"coordinates":[-122.029032,36.971319],"type":"Point"}
}