{
  "type": "Feature",
  "properties": {
    "addr:full":"1441 Springcreek Dr Woodland CA 95776",
    "addr:housenumber":"1441",
    "addr:postcode":"95776",
    "addr:street":"Springcreek Dr",
    "iso:country":"US",
    "sg:address":"1441 Springcreek Dr",
    "sg:city":"Woodland",
    "sg:classifiers":[
        {
            "category":"Professional",
            "subcategory":"Computer Services",
            "type":"Services"
        }
    ],
    "sg:phone":"+1 530 681 8938",
    "sg:postcode":"95776",
    "sg:province":"CA",
    "sg:tags":[
        "repair"
    ],
    "wof:name":"Turben's Computer Svc",
    "wof:placetype":"venue"
},
  "geometry": {"coordinates":[-121.7547,38.672054],"type":"Point"}
}