{
  "type": "Feature",
  "properties": {
    "addr:full":"6170 Sunrise Mall Citrus Heights CA 95610",
    "addr:housenumber":"6170",
    "addr:postcode":"95610",
    "addr:street":"Sunrise Mall",
    "iso:country":"US",
    "sg:address":"6170 Sunrise Mall",
    "sg:city":"Citrus Heights",
    "sg:classifiers":[
        {
            "category":"Wholesale",
            "subcategory":"Stationery",
            "type":"Manufacturing & Wholesale Goods"
        }
    ],
    "sg:phone":"+1 916 722 3655",
    "sg:postcode":"95610",
    "sg:province":"CA",
    "sg:tags":[
        "card"
    ],
    "wof:name":"Mark's Hallmark",
    "wof:placetype":"venue"
},
  "geometry": {"coordinates":[-121.271299,38.677771],"type":"Point"}
}