{
  "type": "Feature",
  "properties": {
    "addr:full":"1723 I St Sacramento CA 95814",
    "addr:housenumber":"1723",
    "addr:postcode":"95814",
    "addr:street":"I St",
    "iso:country":"US",
    "sg:address":"1723 I St",
    "sg:city":"Sacramento",
    "sg:classifiers":[
        {
            "category":"Arts & Performance",
            "subcategory":"Art Gallery",
            "type":"Entertainment"
        }
    ],
    "sg:phone":"+1 916 443 4025",
    "sg:postcode":"95814",
    "sg:province":"CA",
    "sg:website":"www.sacartz.com",
    "wof:name":"Barton Gallery",
    "wof:placetype":"venue"
},
  "geometry": {"coordinates":[-121.48200199999999,38.578701],"type":"Point"}
}