{
  "type": "Feature",
  "properties": {
    "iso:country":"US",
    "sg:address":"11311 La Mirada Blvd Ste C",
    "sg:city":"Whittier",
    "sg:classifiers":[
        {
            "category":"Health Services",
            "subcategory":"Dentist",
            "type":"Services"
        }
    ],
    "sg:phone":"+1 562 944 2995",
    "sg:postcode":"90604",
    "sg:province":"CA",
    "wof:name":"ROODZANT GERALD P DDS",
    "wof:placetype":"venue"
},
  "geometry": {"coordinates":[-118.203272,33.928184],"type":"Point"}
}