{
  "type": "Feature",
  "properties": {
    "iso:country":"US",
    "sg:address":"6800 Owensmouth Ave",
    "sg:city":"Canoga Park",
    "sg:classifiers":[
        {
            "category":"Professional",
            "subcategory":"Engineering",
            "type":"Services"
        }
    ],
    "sg:phone":"+1 818 783 6965",
    "sg:postcode":"91303",
    "sg:province":"CA",
    "sg:tags":[
        "engineer"
    ],
    "wof:name":"Tek Engineering Group Inc",
    "wof:placetype":"venue"
},
  "geometry": {"coordinates":[-118.601549,34.195237],"type":"Point"}
}