{
  "type": "Feature",
  "properties": {
    "iso:country":"US",
    "sg:address":"9607 Beverly Rd",
    "sg:city":"Pico Rivera",
    "sg:classifiers":[
        {
            "category":"Autos & Motor Vehicles",
            "subcategory":"Automobile Sales",
            "type":"Retail Goods"
        }
    ],
    "sg:phone":"+1 562 699 8114",
    "sg:postcode":"90660",
    "sg:province":"CA",
    "sg:tags":[
        "car",
        "dealer"
    ],
    "wof:name":"Aztlan Auto Custom",
    "wof:placetype":"venue"
},
  "geometry": {"coordinates":[-118.072967,34.00539],"type":"Point"}
}