{
  "type": "Feature",
  "properties": {
    "iso:country":"US",
    "sfac:artist":"Neri, Manuel",
    "sfac:created_at":"01/01/1970 12:33:05 AM +0000",
    "sfac:credit_line":"Purchased by the San Francisco Art Commission for the San Francisco International Airport",
    "sfac:display_dimensions":"69 3/4\" H X 22 3/4\" W X 10 1/2\" D",
    "sfac:location_description":"Airport : T1 : Boarding Area C : Gate 46",
    "sfac:medium":"Marble",
    "sfac:revision":"2-e8e1da046fc32dd2661311dd80e83646",
    "sfac:title":"Mujer Pagada No.4",
    "wof:name":"Mujer Pagada No.4",
    "wof:placetype":"venue"
},
  "geometry": {"coordinates":[-122.389979,37.615223],"type":"Point"}
}