{
  "type": "Feature",
  "properties": {
    "iso:country":"US",
    "sg:address":"2851 E 44th St",
    "sg:city":"Los Angeles",
    "sg:classifiers":[
        {
            "category":"Food & Beverages",
            "subcategory":"Meat & Fish",
            "type":"Retail Goods"
        }
    ],
    "sg:phone":"+1 323 588 1140",
    "sg:postcode":"90058",
    "sg:province":"CA",
    "wof:name":"Belle River Meat Inc",
    "wof:placetype":"venue"
},
  "geometry": {"coordinates":[-118.214045,34.003829],"type":"Point"}
}