{
  "type": "Feature",
  "properties": {
    "addr:full":"8100 S Western Ave Los Angeles CA 90047",
    "addr:housenumber":"8100",
    "addr:postcode":"90047",
    "addr:street":"S Western Ave",
    "iso:country":"US",
    "sg:address":"8100 S Western Ave",
    "sg:city":"Los Angeles",
    "sg:classifiers":[
        {
            "category":"Shopping",
            "subcategory":"Florist",
            "type":"Retail Goods"
        }
    ],
    "sg:phone":"+1 323 758 0264",
    "sg:postcode":"90047",
    "sg:province":"CA",
    "wof:name":"Michele's Flowers",
    "wof:placetype":"venue"
},
  "geometry": {"coordinates":[-118.30900099999999,33.964574],"type":"Point"}
}