{
  "type": "Feature",
  "properties": {
    "iso:country":"US",
    "sg:address":"1855 Folsom Street Lbby",
    "sg:city":"San Francisco",
    "sg:classifiers":[
        {
            "category":"Health Services",
            "subcategory":"Doctor",
            "type":"Services"
        }
    ],
    "sg:phone":"+1 415 353 3557",
    "sg:postcode":"94103",
    "sg:province":"CA",
    "wof:name":"Barbaro Nicholas M MD",
    "wof:placetype":"venue"
},
  "geometry": {"coordinates":[-122.41555200000001,37.767794],"type":"Point"}
}