{
  "type": "Feature",
  "properties": {
    "iso:country":"US",
    "sg:address":"3554 Beverly Blvd",
    "sg:city":"Los Angeles",
    "sg:classifiers":[
        {
            "category":"Food & Beverages",
            "subcategory":"Liquor & Beverages",
            "type":"Retail Goods"
        }
    ],
    "sg:phone":"+1 213 387 3315",
    "sg:postcode":"90004",
    "sg:province":"CA",
    "sg:tags":[
        "beer",
        "spirit",
        "wine"
    ],
    "sg:website":"www.parkliquor.com",
    "wof:name":"Park Liquor",
    "wof:placetype":"venue"
},
  "geometry": {"coordinates":[-118.286003,34.074299],"type":"Point"}
}