{
  "type": "Feature",
  "properties": {
    "iso:country":"US",
    "sg:address":"39150 State St",
    "sg:city":"Fremont",
    "sg:classifiers":[
        {
            "category":"Personal",
            "subcategory":"Barber",
            "type":"Services"
        }
    ],
    "sg:phone":"+1 510 792 5313",
    "sg:postcode":"94538",
    "sg:province":"CA",
    "wof:name":"Town Fair Barber Salon",
    "wof:placetype":"venue"
},
  "geometry": {"coordinates":[-121.982682,37.549096],"type":"Point"}
}