{
  "type": "Feature",
  "properties": {
    "iso:country":"US",
    "sg:address":"215 Kearny St",
    "sg:city":"San Francisco",
    "sg:classifiers":[
        {
            "category":"Personal",
            "subcategory":"Beauty Salon",
            "type":"Services"
        }
    ],
    "sg:phone":"+1 415 397 3700",
    "sg:postcode":"94108",
    "sg:province":"CA",
    "wof:name":"Skin Fantastik",
    "wof:placetype":"venue"
},
  "geometry": {"coordinates":[-122.403986,37.790141],"type":"Point"}
}