{
  "type": "Feature",
  "properties": {
    "iso:country":"US",
    "sg:address":"2233 S Shore Ctr",
    "sg:city":"Alameda",
    "sg:classifiers":[
        {
            "category":"Shopping",
            "subcategory":"Jewelry",
            "type":"Retail Goods"
        }
    ],
    "sg:phone":"+1 510 499 2994",
    "sg:postcode":"94501",
    "sg:province":"CA",
    "sg:tags":[
        "jeweler"
    ],
    "wof:name":"Ngoc Thi Chau",
    "wof:placetype":"venue"
},
  "geometry": {"coordinates":[-122.252618,37.756696],"type":"Point"}
}