{
  "type": "Feature",
  "properties": {
    "addr:full":"17620 Marygold Ave Bloomington CA 92316",
    "addr:housenumber":"17620",
    "addr:postcode":"92316",
    "addr:street":"Marygold Ave",
    "iso:country":"US",
    "sg:address":"17620 Marygold Ave",
    "sg:city":"Bloomington",
    "sg:classifiers":[
        {
            "category":"Retail",
            "subcategory":"Repair Shop",
            "type":"Services"
        }
    ],
    "sg:phone":"+1 909 879 0108",
    "sg:postcode":"92316",
    "sg:province":"CA",
    "sg:tags":[
        "refrigeration"
    ],
    "wof:name":"Lindsay Air",
    "wof:placetype":"venue"
},
  "geometry": {"coordinates":[-117.41914800000001,34.0741],"type":"Point"}
}