{
  "type": "Feature",
  "properties": {
    "addr:full":"87 N Raymond Ave Ste 650 Pasadena CA 91103",
    "addr:housenumber":"87",
    "addr:postcode":"91103",
    "addr:street":"N Raymond Ave Ste 650",
    "iso:country":"US",
    "sg:address":"87 N Raymond Ave Ste 650",
    "sg:city":"Pasadena",
    "sg:classifiers":[
        {
            "category":"Banks & Credit Unions",
            "subcategory":"Investment Brokerage",
            "type":"Services"
        },
        {
            "category":"Banks & Credit Unions",
            "subcategory":"Financial Services",
            "type":"Services"
        }
    ],
    "sg:phone":"+1 626 449 8347",
    "sg:postcode":"91103",
    "sg:province":"CA",
    "sg:tags":[
        "investing",
        "advising"
    ],
    "sg:website":"www.ameripriseadvisors.com/chris...",
    "wof:name":"Christopher Haydel - Ameriprise Financial Advisor",
    "wof:placetype":"venue"
},
  "geometry": {"coordinates":[-118.149218,34.147404],"type":"Point"}
}