{
  "type": "Feature",
  "properties": {
    "addr:full":"10362 Court Ave Sultana CA 93666",
    "addr:housenumber":"10362",
    "addr:postcode":"93666",
    "addr:street":"Court Ave",
    "iso:country":"US",
    "sg:address":"10362 Court Ave",
    "sg:city":"Sultana",
    "sg:classifiers":[
        {
            "category":"Local Transit",
            "type":"Transportation"
        }
    ],
    "sg:phone":"+1 559 595 9556",
    "sg:postcode":"93666",
    "sg:province":"CA",
    "wof:name":"Shawn-A-Cee's Transportation",
    "wof:placetype":"venue"
},
  "geometry": {"coordinates":[-119.342896,36.545034],"type":"Point"}
}