{
  "type": "Feature",
  "properties": {
    "iso:country":"US",
    "sg:address":"1111 Howe Ave",
    "sg:city":"Sacramento",
    "sg:phone":"+1 916 643 1580",
    "sg:postcode":"95825",
    "sg:province":"CA",
    "wof:name":"Lobel Financial",
    "wof:placetype":"venue"
},
  "geometry": {"coordinates":[-121.415415,38.585784],"type":"Point"}
}