{
  "type": "Feature",
  "properties": {
    "addr:full":"23350 Lyons Ave Santa Clarita CA 91321",
    "addr:housenumber":"23350",
    "addr:postcode":"91321",
    "addr:street":"Lyons Ave",
    "iso:country":"US",
    "sg:address":"23350 Lyons Ave",
    "sg:city":"Santa Clarita",
    "sg:classifiers":[
        {
            "category":"Restaurant",
            "type":"Food & Drink"
        }
    ],
    "sg:phone":"+1 661 222 2290",
    "sg:postcode":"91321",
    "sg:province":"CA",
    "sg:tags":[
        "pizza"
    ],
    "wof:name":"Little Caesars",
    "wof:placetype":"venue"
},
  "geometry": {"coordinates":[-118.541642,34.379522],"type":"Point"}
}