{
  "type": "Feature",
  "properties": {
    "addr:full":"21026 Osborne St Canoga Park CA 91304",
    "addr:housenumber":"21026",
    "addr:postcode":"91304",
    "addr:street":"Osborne St",
    "iso:country":"US",
    "sg:address":"21026 Osborne St",
    "sg:city":"Canoga Park",
    "sg:classifiers":[
        {
            "category":"Shopping",
            "subcategory":"Clothing, Apparel, & Fashions",
            "type":"Retail Goods"
        }
    ],
    "sg:phone":"+1 818 885 1300",
    "sg:postcode":"91304",
    "sg:province":"CA",
    "wof:name":"Athenian Fashions",
    "wof:placetype":"venue"
},
  "geometry": {"coordinates":[-118.591953,34.232963],"type":"Point"}
}