{
  "type": "Feature",
  "properties": {
    "addr:full":"1776 Clear Lake Ave Milpitas CA 95035",
    "addr:housenumber":"1776",
    "addr:postcode":"95035",
    "addr:street":"Clear Lake Ave",
    "iso:country":"US",
    "sg:address":"1776 Clear Lake Ave",
    "sg:city":"Milpitas",
    "sg:classifiers":[
        {
            "category":"Professional",
            "subcategory":"Management & Consulting",
            "type":"Services"
        }
    ],
    "sg:phone":"+1 408 956 0628",
    "sg:postcode":"95035",
    "sg:province":"CA",
    "wof:name":"Sino American Trading Company",
    "wof:placetype":"venue"
},
  "geometry": {"coordinates":[-121.872484,37.418668],"type":"Point"}
}