{
  "type": "Feature",
  "properties": {
    "addr:full":"2220 Bridgepointe Pkwy Foster City CA 94404",
    "addr:housenumber":"2220",
    "addr:postcode":"94404",
    "addr:street":"Bridgepointe Pkwy",
    "iso:country":"US",
    "sg:address":"2220 Bridgepointe Pkwy",
    "sg:city":"Foster City",
    "sg:classifiers":[
        {
            "category":"Shopping",
            "subcategory":"Mobile Phones",
            "type":"Retail Goods"
        }
    ],
    "sg:phone":"+1 650 349 3940",
    "sg:postcode":"94404",
    "sg:province":"CA",
    "wof:name":"RadioShack",
    "wof:placetype":"venue"
},
  "geometry": {"coordinates":[-122.283084,37.560669],"type":"Point"}
}