{
  "type": "Feature",
  "properties": {
    "addr:full":"826 S Atlantic Blvd Monterey Park CA 91754",
    "addr:housenumber":"826",
    "addr:postcode":"91754",
    "addr:street":"S Atlantic Blvd",
    "iso:country":"US",
    "sg:address":"826 S Atlantic Blvd",
    "sg:city":"Monterey Park",
    "sg:classifiers":[
        {
            "category":"Professional",
            "subcategory":"Lawyer & Legal Services",
            "type":"Services"
        }
    ],
    "sg:phone":"+1 626 289 1490",
    "sg:postcode":"91754",
    "sg:province":"CA",
    "wof:name":"Lou Elizabeth Atty",
    "wof:placetype":"venue"
},
  "geometry": {"coordinates":[-118.137001,34.0536],"type":"Point"}
}