{
  "type": "Feature",
  "properties": {
    "addr:full":"1568 6th Ave San Diego CA 92101",
    "addr:housenumber":"1568",
    "addr:postcode":"92101",
    "addr:street":"6Th Ave",
    "iso:country":"US",
    "sg:address":"1568 6th Ave",
    "sg:city":"San Diego",
    "sg:classifiers":[
        {
            "category":"Health Services",
            "subcategory":"Hospital",
            "type":"Services"
        }
    ],
    "sg:phone":"+1 619 235 2600",
    "sg:postcode":"92101",
    "sg:province":"CA",
    "sg:tags":[
        "mental"
    ],
    "wof:name":"Downtown Mental Health Ctr",
    "wof:placetype":"venue"
},
  "geometry": {"coordinates":[-117.15937599999999,32.721257],"type":"Point"}
}