{
  "type": "Feature",
  "properties": {
    "addr:full":"6800 W Coast Hwy Newport Beach CA 92663",
    "addr:housenumber":"6800",
    "addr:postcode":"92663",
    "addr:street":"W Coast Hwy",
    "iso:country":"US",
    "sg:address":"6800 W Coast Hwy",
    "sg:city":"Newport Beach",
    "sg:classifiers":[
        {
            "category":"Professional",
            "type":"Services"
        }
    ],
    "sg:phone":"+1 949 548 7200",
    "sg:postcode":"92663",
    "sg:province":"CA",
    "wof:name":"Grover New Way",
    "wof:placetype":"venue"
},
  "geometry": {"coordinates":[-117.952758,33.628402],"type":"Point"}
}