{
  "type": "Feature",
  "properties": {
    "iso:country":"US",
    "sg:address":"23560 Madison St",
    "sg:city":"Torrance",
    "sg:classifiers":[
        {
            "category":"Health Services",
            "subcategory":"Doctor",
            "type":"Services"
        }
    ],
    "sg:phone":"+1 310 539 8616",
    "sg:postcode":"90505",
    "sg:province":"CA",
    "sg:tags":[
        "dentist"
    ],
    "wof:name":"Terry Wheeler DDS",
    "wof:placetype":"venue"
},
  "geometry": {"coordinates":[-118.347619,33.812133],"type":"Point"}
}