{
  "type": "Feature",
  "properties": {
    "addr:full":"4573 Branciforte Dr Santa Cruz CA 95065",
    "addr:housenumber":"4573",
    "addr:postcode":"95065",
    "addr:street":"Branciforte Dr",
    "iso:country":"US",
    "sg:address":"4573 Branciforte Dr",
    "sg:city":"Santa Cruz",
    "sg:classifiers":[
        {
            "category":"Real Estate",
            "subcategory":"Real Estate Operator",
            "type":"Services"
        }
    ],
    "sg:phone":"+1 831 425 9095",
    "sg:postcode":"95065",
    "sg:province":"CA",
    "sg:tags":[
        "apartment"
    ],
    "wof:name":"Casa Montgomery",
    "wof:placetype":"venue"
},
  "geometry": {"coordinates":[-121.984515,37.040611],"type":"Point"}
}