{
  "type": "Feature",
  "properties": {
    "iso:country":"US",
    "sg:address":"26000 Barton Rd",
    "sg:city":"Loma Linda",
    "sg:classifiers":[
        {
            "category":"Government",
            "subcategory":"Office",
            "type":"Public Place"
        }
    ],
    "sg:phone":"+1 909 799 4410",
    "sg:postcode":"92354",
    "sg:province":"CA",
    "sg:tags":[
        "general"
    ],
    "wof:name":"Public Works- City Maint Yard",
    "wof:placetype":"venue"
},
  "geometry": {"coordinates":[-117.236042,34.048349],"type":"Point"}
}