{
  "type": "Feature",
  "properties": {
    "iso:country":"US",
    "sg:address":"1631 Edinger Ave Ste 104",
    "sg:city":"Tustin",
    "sg:classifiers":[
        {
            "category":"Banks & Credit Unions",
            "subcategory":"Bank",
            "type":"Services"
        }
    ],
    "sg:phone":"+1 714 259 0107",
    "sg:postcode":"92780",
    "sg:province":"CA",
    "wof:name":"Patriots Federal Credit Union",
    "wof:placetype":"venue"
},
  "geometry": {"coordinates":[-117.825441,33.720907],"type":"Point"}
}