{
  "type": "Feature",
  "properties": {
    "addr:full":"5139 Silurian Hills Dr Fort Irwin CA 92310",
    "addr:housenumber":"5139",
    "addr:postcode":"92310",
    "addr:street":"Silurian Hills Dr",
    "iso:country":"US",
    "sg:address":"5139 Silurian Hills Dr",
    "sg:city":"Fort Irwin",
    "sg:classifiers":[
        {
            "category":"Social Services",
            "subcategory":"Child Care",
            "type":"Services"
        }
    ],
    "sg:phone":"+1 760 386 8549",
    "sg:postcode":"92310",
    "sg:province":"CA",
    "sg:tags":[
        "provider"
    ],
    "wof:name":"Adriana Quintana",
    "wof:placetype":"venue"
},
  "geometry": {"coordinates":[-116.70296,35.269653],"type":"Point"}
}