{
  "type": "Feature",
  "properties": {
    "iso:country":"US",
    "sg:address":"3312 Fruitvale Ave",
    "sg:city":"Bakersfield",
    "sg:classifiers":[
        {
            "category":"Professional",
            "type":"Services"
        }
    ],
    "sg:phone":"+1 661 589 9427",
    "sg:postcode":"93308",
    "sg:province":"CA",
    "wof:name":"Mc Gowan Svc",
    "wof:placetype":"venue"
},
  "geometry": {"coordinates":[-119.074282,35.390181],"type":"Point"}
}