{
  "type": "Feature",
  "properties": {
    "iso:country":"US",
    "sg:address":"300 Carlsbad Village Dr Ste 101",
    "sg:city":"Carlsbad",
    "sg:classifiers":[
        {
            "category":"Arts & Performance",
            "subcategory":"Art Gallery",
            "type":"Entertainment"
        }
    ],
    "sg:phone":"+1 760 434 8497",
    "sg:postcode":"92008",
    "sg:province":"CA",
    "wof:name":"Carlsbad-Oceanside Art League",
    "wof:placetype":"venue"
},
  "geometry": {"coordinates":[-117.350998,33.158298],"type":"Point"}
}