{
  "type": "Feature",
  "properties": {
    "addr:full":"20044 E Limecrest Dr Covina CA 91724",
    "addr:housenumber":"20044",
    "addr:postcode":"91724",
    "addr:street":"E Limecrest Dr",
    "iso:country":"US",
    "sg:address":"20044 E Limecrest Dr",
    "sg:city":"Covina",
    "sg:classifiers":[
        {
            "category":"Wholesale",
            "subcategory":"Machinery & Supplies",
            "type":"Manufacturing & Wholesale Goods"
        }
    ],
    "sg:phone":"+1 626 967 0134",
    "sg:postcode":"91724",
    "sg:province":"CA",
    "sg:tags":[
        "equipment",
        "establishment"
    ],
    "wof:name":"Amway Products Distributors",
    "wof:placetype":"venue"
},
  "geometry": {"coordinates":[-117.86178200000001,34.060304],"type":"Point"}
}