{
  "type": "Feature",
  "properties": {
    "iso:country":"US",
    "sg:address":"1127 Santee St",
    "sg:city":"Los Angeles",
    "sg:classifiers":[
        {
            "category":"Wholesale",
            "subcategory":"Durable Goods & Equipment",
            "type":"Manufacturing & Wholesale Goods"
        }
    ],
    "sg:phone":"+1 213 747 4410",
    "sg:postcode":"90015",
    "sg:province":"CA",
    "sg:tags":[
        "exporter"
    ],
    "wof:name":"Salma Fashions",
    "wof:placetype":"venue"
},
  "geometry": {"coordinates":[-118.257128,34.036726],"type":"Point"}
}