{
  "type": "Feature",
  "properties": {
    "iso:country":"US",
    "sg:address":"498 S Airport Blvd",
    "sg:city":"S San Francisco",
    "sg:classifiers":[
        {
            "category":"Freight",
            "type":"Transportation"
        }
    ],
    "sg:phone":"+1 650 872 3600",
    "sg:postcode":"94080",
    "sg:province":"CA",
    "wof:name":"U S Express Inc",
    "wof:placetype":"venue"
},
  "geometry": {"coordinates":[-122.402331,37.641],"type":"Point"}
}