{
  "type": "Feature",
  "properties": {
    "addr:full":"337 N Chevy Chase Dr Glendale CA 91206",
    "addr:housenumber":"337",
    "addr:postcode":"91206",
    "addr:street":"N Chevy Chase Dr",
    "iso:country":"US",
    "sg:address":"337 N Chevy Chase Dr",
    "sg:city":"Glendale",
    "sg:classifiers":[
        {
            "category":"Professional",
            "subcategory":"Computer Services",
            "type":"Services"
        }
    ],
    "sg:phone":"+1 818 546 2885",
    "sg:postcode":"91206",
    "sg:province":"CA",
    "sg:tags":[
        "restaurant",
        "internet"
    ],
    "wof:name":"Garcia Note Locators Self Inst",
    "wof:placetype":"venue"
},
  "geometry": {"coordinates":[-118.237927,34.150714],"type":"Point"}
}