{
  "type": "Feature",
  "properties": {
    "addr:full":"5704 Nomi St Bakersfield CA 93308",
    "addr:postcode":"5704;93308",
    "addr:street":"Nomi St",
    "iso:country":"US",
    "sg:address":"5704 Nomi St",
    "sg:city":"Bakersfield",
    "sg:classifiers":[
        {
            "category":"Freight",
            "type":"Transportation"
        }
    ],
    "sg:phone":"+1 661 397 5608",
    "sg:postcode":"93308",
    "sg:province":"CA",
    "sg:tags":[
        "trucking"
    ],
    "wof:name":"S & R Trucking",
    "wof:placetype":"venue"
},
  "geometry": {"coordinates":[-119.062713,35.409799],"type":"Point"}
}