{
  "type": "Feature",
  "properties": {
    "addr:full":"16756 Superior St North Hills CA 91343",
    "addr:housenumber":"16756",
    "addr:postcode":"91343",
    "addr:street":"Superior St",
    "iso:country":"US",
    "sg:address":"16756 Superior St",
    "sg:city":"North Hills",
    "sg:classifiers":[
        {
            "category":"Building & Trades",
            "subcategory":"Landscaping Services",
            "type":"Services"
        }
    ],
    "sg:phone":"+1 818 920 5893",
    "sg:postcode":"91343",
    "sg:province":"CA",
    "sg:tags":[
        "contract"
    ],
    "wof:name":"Chan Ho Landscaping & Plu",
    "wof:placetype":"venue"
},
  "geometry": {"coordinates":[-118.49608000000001,34.246905],"type":"Point"}
}