{
  "type": "Feature",
  "properties": {
    "iso:country":"US",
    "sg:address":"818 Orange Heights Ln",
    "sg:city":"Corona",
    "sg:classifiers":[
        {
            "category":"Professional",
            "subcategory":"Engineering",
            "type":"Services"
        }
    ],
    "sg:phone":"+1 951 660 6347",
    "sg:postcode":"92882",
    "sg:province":"CA",
    "sg:tags":[
        "engineer"
    ],
    "wof:name":"D Harris & Co Sap Consulting",
    "wof:placetype":"venue"
},
  "geometry": {"coordinates":[-117.581481,33.835054],"type":"Point"}
}