{
  "type": "Feature",
  "properties": {
    "addr:full":"1149 Tama Ln Santa Maria CA 93455",
    "addr:housenumber":"1149",
    "addr:postcode":"93455",
    "addr:street":"Tama Ln",
    "iso:country":"US",
    "sg:address":"1149 Tama Ln",
    "sg:city":"Santa Maria",
    "sg:classifiers":[
        {
            "category":"Retail",
            "subcategory":"Auto Repair",
            "type":"Services"
        }
    ],
    "sg:phone":"+1 805 922 7742",
    "sg:postcode":"93455",
    "sg:province":"CA",
    "sg:website":"www.rizzolisautomotive.com",
    "wof:name":"Rizzoli's Automotive Inc",
    "wof:placetype":"venue"
},
  "geometry": {"coordinates":[-120.454002,34.9193],"type":"Point"}
}