{
  "type": "Feature",
  "properties": {
    "addr:full":"318 S Gateway Dr Madera CA 93637",
    "addr:housenumber":"318",
    "addr:postcode":"93637",
    "addr:street":"S Gateway Dr",
    "iso:country":"US",
    "sg:address":"318 S Gateway Dr",
    "sg:city":"Madera",
    "sg:classifiers":[
        {
            "category":"Restaurant",
            "type":"Food & Drink"
        }
    ],
    "sg:phone":"+1 559 662 0790",
    "sg:postcode":"93637",
    "sg:province":"CA",
    "wof:name":"Jade Garden Chinese Restaurant",
    "wof:placetype":"venue"
},
  "geometry": {"coordinates":[-120.058289,36.959087],"type":"Point"}
}