{
  "type": "Feature",
  "properties": {
    "addr:full":"901 Airport Dr San Luis Obispo CA 93401",
    "addr:housenumber":"901",
    "addr:postcode":"93401",
    "addr:street":"Airport Dr",
    "iso:country":"US",
    "sg:address":"901 Airport Dr",
    "sg:city":"San Luis Obispo",
    "sg:classifiers":[
        {
            "category":"Airline",
            "type":"Transportation"
        }
    ],
    "sg:phone":"+1 805 543 6125",
    "sg:postcode":"93401",
    "sg:province":"CA",
    "sg:tags":[
        "scheduled",
        "passenger",
        "carrier",
        "air"
    ],
    "wof:name":"AMR Eagle",
    "wof:placetype":"venue"
},
  "geometry": {"coordinates":[-120.641187,35.240182],"type":"Point"}
}