{
  "type": "Feature",
  "properties": {
    "iso:country":"US",
    "sg:address":"345 Vidal Dr",
    "sg:city":"San Francisco",
    "sg:classifiers":[
        {
            "category":"Building & Trades",
            "subcategory":"Construction",
            "type":"Services"
        }
    ],
    "sg:phone":"+1 415 337 7233",
    "sg:postcode":"94132",
    "sg:province":"CA",
    "sg:tags":[
        "contractor"
    ],
    "sg:website":"www.peninsula-builders.com",
    "wof:name":"Peninsula Builders",
    "wof:placetype":"venue"
},
  "geometry": {"coordinates":[-122.484566,37.717643],"type":"Point"}
}