{
  "type": "Feature",
  "properties": {
    "addr:full":"7083 Commerce Cir Pleasanton CA 94588",
    "addr:housenumber":"7083",
    "addr:postcode":"94588",
    "addr:street":"Commerce Cir",
    "iso:country":"US",
    "sg:address":"7083 Commerce Cir",
    "sg:city":"Pleasanton",
    "sg:classifiers":[
        {
            "category":"Professional",
            "type":"Services"
        },
        {
            "category":"Manufacturing",
            "subcategory":"Retail Goods",
            "type":"Manufacturing & Wholesale Goods"
        }
    ],
    "sg:phone":"+1 925 416 0200",
    "sg:postcode":"94588",
    "sg:province":"CA",
    "sg:tags":[
        "establishment"
    ],
    "wof:name":"Shademobile LLC",
    "wof:placetype":"venue"
},
  "geometry": {"coordinates":[-121.91572499999999,37.698019],"type":"Point"}
}