{
  "type": "Feature",
  "properties": {
    "addr:full":"1320 Flynn Rd Camarillo CA 93012",
    "addr:housenumber":"1320",
    "addr:postcode":"93012",
    "addr:street":"Flynn Rd",
    "iso:country":"US",
    "sg:address":"1320 Flynn Rd",
    "sg:city":"Camarillo",
    "sg:classifiers":[
        {
            "category":"Professional",
            "type":"Services"
        }
    ],
    "sg:phone":"+1 805 484 9400",
    "sg:postcode":"93012",
    "sg:province":"CA",
    "sg:tags":[
        "establishment"
    ],
    "wof:name":"Websiteasp",
    "wof:placetype":"venue"
},
  "geometry": {"coordinates":[-119.014951,34.231094],"type":"Point"}
}