{
  "type": "Feature",
  "properties": {
    "iso:country":"US",
    "sg:address":"4119 Jonathon St",
    "sg:city":"Oceanside",
    "sg:classifiers":[
        {
            "category":"Professional",
            "subcategory":"Management & Consulting",
            "type":"Services"
        }
    ],
    "sg:phone":"+1 760 724 5061",
    "sg:postcode":"92056",
    "sg:province":"CA",
    "sg:tags":[
        "retail",
        "direct",
        "sales"
    ],
    "wof:name":"Adriana Garduno",
    "wof:placetype":"venue"
},
  "geometry": {"coordinates":[-117.28645,33.196373],"type":"Point"}
}