{
  "type": "Feature",
  "properties": {
    "addr:full":"3838 California St Rm 612 San Francisco CA 94118",
    "addr:housenumber":"3838;612",
    "addr:postcode":"94118",
    "addr:street":"California St Rm",
    "iso:country":"US",
    "sg:address":"3838 California St Rm 612",
    "sg:city":"San Francisco",
    "sg:classifiers":[
        {
            "category":"Health Services",
            "subcategory":"Doctor",
            "type":"Services"
        }
    ],
    "sg:phone":"+1 415 221 7056",
    "sg:postcode":"94118",
    "sg:province":"CA",
    "wof:name":"Nathanson Daniel MD",
    "wof:placetype":"venue"
},
  "geometry": {"coordinates":[-122.4577,37.786007],"type":"Point"}
}