{
  "type": "Feature",
  "properties": {
    "addr:full":"1100 Ralston Ave Belmont CA 94002",
    "addr:housenumber":"1100",
    "addr:postcode":"94002",
    "addr:street":"Ralston Ave",
    "iso:country":"US",
    "sg:address":"1100 Ralston Ave",
    "sg:city":"Belmont",
    "sg:classifiers":[
        {
            "category":"Real Estate",
            "subcategory":"Real Estate Operator",
            "type":"Services"
        }
    ],
    "sg:phone":"+1 650 596 0942",
    "sg:postcode":"94002",
    "sg:province":"CA",
    "sg:tags":[
        "apartment"
    ],
    "wof:name":"Belmont Gardens",
    "wof:placetype":"venue"
},
  "geometry": {"coordinates":[-122.278441,37.517532],"type":"Point"}
}