{
  "type": "Feature",
  "properties": {
    "iso:country":"US",
    "sg:address":"700 2nd St Ste G",
    "sg:city":"Encinitas",
    "sg:classifiers":[
        {
            "category":"Building & Trades",
            "subcategory":"Construction",
            "type":"Services"
        }
    ],
    "sg:phone":"+1 760 944 1842",
    "sg:postcode":"92024",
    "sg:province":"CA",
    "sg:tags":[
        "contractor"
    ],
    "wof:name":"L M Salvo Contracting",
    "wof:placetype":"venue"
},
  "geometry": {"coordinates":[-117.29458200000001,33.325147],"type":"Point"}
}