{
  "type": "Feature",
  "properties": {
    "iso:country":"US",
    "sg:address":"72682 Ramon Rd",
    "sg:city":"Thousand Palms",
    "sg:classifiers":[
        {
            "category":"Wholesale",
            "subcategory":"Construction Materials",
            "type":"Manufacturing & Wholesale Goods"
        }
    ],
    "sg:phone":"+1 760 343 1474",
    "sg:postcode":"92276",
    "sg:province":"CA",
    "sg:tags":[
        "concrete",
        "product"
    ],
    "wof:name":"J & L Ornamental Cement",
    "wof:placetype":"venue"
},
  "geometry": {"coordinates":[-116.393675,33.816481],"type":"Point"}
}