{
  "type": "Feature",
  "properties": {
    "addr:full":"827 del Mar Downs Rd Solana Beach CA 92075",
    "addr:housenumber":"827",
    "addr:postcode":"92075",
    "addr:street":"Del Mar Downs Rd",
    "iso:country":"US",
    "sg:address":"827 del Mar Downs Rd",
    "sg:city":"Solana Beach",
    "sg:classifiers":[
        {
            "category":"Freight",
            "type":"Transportation"
        }
    ],
    "sg:phone":"+1 858 509 0085",
    "sg:postcode":"92075",
    "sg:province":"CA",
    "wof:name":"Skywalker Transportation",
    "wof:placetype":"venue"
},
  "geometry": {"coordinates":[-117.26203099999999,32.980905],"type":"Point"}
}