{
  "type": "Feature",
  "properties": {
    "iso:country":"US",
    "sg:address":"7100 Four Seasons",
    "sg:city":"Carlsbad",
    "sg:classifiers":[
        {
            "category":"Shopping",
            "subcategory":"Jewelry",
            "type":"Retail Goods"
        }
    ],
    "sg:phone":"+1 760 603 9601",
    "sg:postcode":"92011",
    "sg:province":"CA",
    "sg:tags":[
        "jeweler"
    ],
    "wof:name":"Collector Fine Jewelry",
    "wof:placetype":"venue"
},
  "geometry": {"coordinates":[-117.285576,33.102475],"type":"Point"}
}