{
  "type": "Feature",
  "properties": {
    "iso:country":"US",
    "sg:address":"1290 S La Brea Ave",
    "sg:city":"Los Angeles",
    "sg:classifiers":[
        {
            "category":"Shopping",
            "subcategory":"Florist",
            "type":"Retail Goods"
        }
    ],
    "sg:phone":"+1 323 935 5194",
    "sg:postcode":"90019",
    "sg:province":"CA",
    "wof:name":"Bea Flowers",
    "wof:placetype":"venue"
},
  "geometry": {"coordinates":[-118.34403399999999,34.071999],"type":"Point"}
}