{
  "type": "Feature",
  "properties": {
    "iso:country":"US",
    "sg:address":"14908 Sobey Rd",
    "sg:city":"Saratoga",
    "sg:classifiers":[
        {
            "category":"Building & Trades",
            "subcategory":"Construction",
            "type":"Services"
        }
    ],
    "sg:phone":"+1 408 354 8579",
    "sg:postcode":"95070",
    "sg:province":"CA",
    "sg:tags":[
        "contractor"
    ],
    "wof:name":"Anderegg Builders",
    "wof:placetype":"venue"
},
  "geometry": {"coordinates":[-122.000422,37.251884],"type":"Point"}
}