{
  "type": "Feature",
  "properties": {
    "iso:country":"US",
    "sg:address":"18575 Pioneer Blvd",
    "sg:city":"Artesia",
    "sg:classifiers":[
        {
            "category":"Shopping",
            "subcategory":"Crafts & Fabrics",
            "type":"Retail Goods"
        }
    ],
    "sg:phone":"+1 562 403 0170",
    "sg:postcode":"90701",
    "sg:province":"CA",
    "sg:tags":[
        "art",
        "supply"
    ],
    "wof:name":"World Of Handloom & Craft In",
    "wof:placetype":"venue"
},
  "geometry": {"coordinates":[-118.232834,33.863046],"type":"Point"}
}