{
  "type": "Feature",
  "properties": {
    "addr:full":"1228 E 81st St Los Angeles CA 90001",
    "addr:housenumber":"1228",
    "addr:postcode":"90001",
    "addr:street":"E 81St St",
    "iso:country":"US",
    "sg:address":"1228 E 81st St",
    "sg:city":"Los Angeles",
    "sg:classifiers":[
        {
            "category":"Organizations",
            "subcategory":"Religious Organization",
            "type":"Services"
        }
    ],
    "sg:phone":"+1 323 582 2826",
    "sg:postcode":"90001",
    "sg:province":"CA",
    "sg:tags":[
        "monastery",
        "convent"
    ],
    "wof:name":"St Malachy Convent",
    "wof:placetype":"venue"
},
  "geometry": {"coordinates":[-118.25312099999999,33.965577],"type":"Point"}
}