{
  "type": "Feature",
  "properties": {
    "addr:full":"400 University Ave Sacramento CA 95825",
    "addr:housenumber":"400",
    "addr:postcode":"95825",
    "addr:street":"University Ave",
    "iso:country":"US",
    "sg:address":"400 University Ave",
    "sg:city":"Sacramento",
    "sg:classifiers":[
        {
            "category":"Professional",
            "subcategory":"Secretarial Services",
            "type":"Services"
        }
    ],
    "sg:phone":"+1 916 646 3272",
    "sg:postcode":"95825",
    "sg:province":"CA",
    "sg:tags":[
        "convention",
        "court",
        "reporter"
    ],
    "wof:name":"Joann Hipp & Assoc",
    "wof:placetype":"venue"
},
  "geometry": {"coordinates":[-121.41807,38.563433],"type":"Point"}
}