{
  "type": "Feature",
  "properties": {
    "addr:full":"1223 Main St St Helena CA 94574",
    "addr:housenumber":"1223",
    "addr:postcode":"94574",
    "addr:street":"Main St",
    "iso:country":"US",
    "sg:address":"1223 Main St",
    "sg:city":"St Helena",
    "sg:classifiers":[
        {
            "category":"Retail",
            "subcategory":"Laundry & Dry Cleaning",
            "type":"Services"
        },
        {
            "category":"Shopping",
            "subcategory":"Clothing, Apparel, & Fashions",
            "type":"Retail Goods"
        }
    ],
    "sg:phone":"+1 707 968 0638",
    "sg:postcode":"94574",
    "sg:province":"CA",
    "sg:tags":[
        "alteration"
    ],
    "wof:name":"Milena Alternations",
    "wof:placetype":"venue"
},
  "geometry": {"coordinates":[-122.468659,38.504153],"type":"Point"}
}