{
  "type": "Feature",
  "properties": {
    "iso:country":"US",
    "sg:address":"7990 Auto Dr",
    "sg:city":"Riverside",
    "sg:classifiers":[
        {
            "category":"Autos & Motor Vehicles",
            "subcategory":"Automobile Sales",
            "type":"Retail Goods"
        }
    ],
    "sg:phone":"+1 951 687 2121",
    "sg:postcode":"92504",
    "sg:province":"CA",
    "sg:tags":[
        "recreational",
        "mi"
    ],
    "wof:name":"R E F Enterprises",
    "wof:placetype":"venue"
},
  "geometry": {"coordinates":[-117.410934,33.929947],"type":"Point"}
}