{
  "type": "Feature",
  "properties": {
    "iso:country":"US",
    "sg:address":"870 Market St",
    "sg:city":"San Francisco",
    "sg:classifiers":[
        {
            "category":"Communications",
            "type":"Services"
        },
        {
            "category":"Professional",
            "subcategory":"Management & Consulting",
            "type":"Services"
        }
    ],
    "sg:phone":"+1 415 362 4732",
    "sg:postcode":"94102",
    "sg:province":"CA",
    "sg:tags":[
        "communication",
        "printing",
        "consultant"
    ],
    "wof:name":"Amigo Latino",
    "wof:placetype":"venue"
},
  "geometry": {"coordinates":[-122.406645,37.785415],"type":"Point"}
}