{
  "type": "Feature",
  "properties": {
    "iso:country":"US",
    "sg:address":"74057 Hwy 111",
    "sg:city":"Palm Desert",
    "sg:classifiers":[
        {
            "category":"Retail",
            "subcategory":"Repair Shop",
            "type":"Services"
        }
    ],
    "sg:phone":"+1 760 346 6057",
    "sg:postcode":"92260",
    "sg:province":"CA",
    "sg:tags":[
        "equipment",
        "video"
    ],
    "wof:name":"Video Visions Svc",
    "wof:placetype":"venue"
},
  "geometry": {"coordinates":[-116.371831,33.72123],"type":"Point"}
}