{
  "type": "Feature",
  "properties": {
    "addr:full":"5709 Boltres St Orangevale CA 95662",
    "addr:housenumber":"5709",
    "addr:postcode":"95662",
    "addr:street":"Boltres St",
    "iso:country":"US",
    "sg:address":"5709 Boltres St",
    "sg:city":"Orangevale",
    "sg:classifiers":[
        {
            "category":"Freight",
            "type":"Transportation"
        }
    ],
    "sg:phone":"+1 916 966 4166",
    "sg:postcode":"95662",
    "sg:province":"CA",
    "sg:tags":[
        "operator",
        "local",
        "trucking"
    ],
    "wof:name":"Robert J Oby Trucking",
    "wof:placetype":"venue"
},
  "geometry": {"coordinates":[-121.228036,38.670708],"type":"Point"}
}