{
  "type": "Feature",
  "properties": {
    "iso:country":"US",
    "sg:address":"3300 Broadway St",
    "sg:city":"Eureka",
    "sg:classifiers":[
        {
            "category":"Shopping",
            "subcategory":"Clothing, Apparel, & Fashions",
            "type":"Retail Goods"
        }
    ],
    "sg:phone":"+1 707 444 2461",
    "sg:postcode":"95501",
    "sg:province":"CA",
    "wof:name":"Hot Topic",
    "wof:placetype":"venue"
},
  "geometry": {"coordinates":[-124.18653500000001,40.779651],"type":"Point"}
}