{
  "type": "Feature",
  "properties": {
    "iso:country":"US",
    "sg:address":"914 E Via Wanda",
    "sg:city":"Long Beach",
    "sg:classifiers":[
        {
            "category":"Professional",
            "type":"Services"
        }
    ],
    "sg:phone":"+1 562 422 0702",
    "sg:postcode":"90805",
    "sg:province":"CA",
    "sg:tags":[
        "establishment"
    ],
    "wof:name":"Community Development Commissi",
    "wof:placetype":"venue"
},
  "geometry": {"coordinates":[-118.18273,33.851489],"type":"Point"}
}