{
  "type": "Feature",
  "properties": {
    "addr:full":"156 Lily Blossom Ct San Jose CA 95123",
    "addr:housenumber":"156",
    "addr:postcode":"95123",
    "addr:street":"Lily Blossom Ct",
    "iso:country":"US",
    "sg:address":"156 Lily Blossom Ct",
    "sg:city":"San Jose",
    "sg:classifiers":[
        {
            "category":"Professional",
            "type":"Services"
        }
    ],
    "sg:phone":"+1 408 281 2029",
    "sg:postcode":"95123",
    "sg:province":"CA",
    "wof:name":"Thoughtfully Yours",
    "wof:placetype":"venue"
},
  "geometry": {"coordinates":[-121.81392200000001,37.253478],"type":"Point"}
}