{
  "type": "Feature",
  "properties": {
    "iso:country":"US",
    "sg:address":"4152 E Leffngwl Rd",
    "sg:city":"Whittier",
    "sg:classifiers":[
        {
            "category":"Organizations",
            "subcategory":"Religious Organization",
            "type":"Services"
        }
    ],
    "sg:phone":"+1 562 906 2940",
    "sg:postcode":"90601",
    "sg:province":"CA",
    "wof:name":"La Mission De L'esprit Saint",
    "wof:placetype":"venue"
},
  "geometry": {"coordinates":[-118.044998,33.996201],"type":"Point"}
}