{
  "type": "Feature",
  "properties": {
    "iso:country":"US",
    "sg:address":"3660 Wilshire Blvd",
    "sg:city":"Los Angeles",
    "sg:classifiers":[
        {
            "category":"Professional",
            "subcategory":"Lawyer & Legal Services",
            "type":"Services"
        }
    ],
    "sg:phone":"+1 213 380 4166",
    "sg:postcode":"90010",
    "sg:province":"CA",
    "sg:tags":[
        "attorney"
    ],
    "wof:name":"Jerry S Reyes Law Offices",
    "wof:placetype":"venue"
},
  "geometry": {"coordinates":[-118.30448800000001,34.061645],"type":"Point"}
}