{
  "type": "Feature",
  "properties": {
    "addr:full":"11211 Sorrento Valley Rd San Diego CA 92121",
    "addr:housenumber":"11211",
    "addr:postcode":"92121",
    "addr:street":"Sorrento Valley Rd",
    "iso:country":"US",
    "sg:address":"11211 Sorrento Valley Rd",
    "sg:city":"San Diego",
    "sg:classifiers":[
        {
            "category":"Wholesale",
            "subcategory":"Durable Goods & Equipment",
            "type":"Manufacturing & Wholesale Goods"
        }
    ],
    "sg:phone":"+1 760 795 1295",
    "sg:postcode":"92121",
    "sg:province":"CA",
    "sg:tags":[
        "representative",
        "manufacturer"
    ],
    "sg:website":"www.outsourcemanufacturing.com",
    "wof:name":"Meta International Sales Inc",
    "wof:placetype":"venue"
},
  "geometry": {"coordinates":[-117.23413600000001,32.914595],"type":"Point"}
}