{
  "type": "Feature",
  "properties": {
    "addr:full":"1324 Waring St Seaside CA 93955",
    "addr:housenumber":"1324",
    "addr:postcode":"93955",
    "addr:street":"Waring St",
    "iso:country":"US",
    "sg:address":"1324 Waring St",
    "sg:city":"Seaside",
    "sg:classifiers":[
        {
            "category":"Professional",
            "type":"Services"
        }
    ],
    "sg:phone":"+1 831 394 7829",
    "sg:postcode":"93955",
    "sg:province":"CA",
    "sg:tags":[
        "establishment"
    ],
    "wof:name":"Medina Concepcion",
    "wof:placetype":"venue"
},
  "geometry": {"coordinates":[-121.834642,36.605293],"type":"Point"}
}