{
  "type": "Feature",
  "properties": {
    "iso:country":"US",
    "sg:address":"2913 A St",
    "sg:city":"Eureka",
    "sg:classifiers":[
        {
            "category":"Professional",
            "subcategory":"Accounting & Tax Preparation",
            "type":"Services"
        }
    ],
    "sg:phone":"+1 707 443 2053",
    "sg:postcode":"95501",
    "sg:province":"CA",
    "wof:name":"Dockal & Associates",
    "wof:placetype":"venue"
},
  "geometry": {"coordinates":[-124.170232,40.781518],"type":"Point"}
}