{
  "type": "Feature",
  "properties": {
    "iso:country":"US",
    "sg:address":"1485 N Waterman Ave",
    "sg:city":"San Bernardino",
    "sg:classifiers":[
        {
            "category":"Wholesale",
            "subcategory":"Medical Equipment & Supplies",
            "type":"Manufacturing & Wholesale Goods"
        }
    ],
    "sg:phone":"+1 909 889 9944",
    "sg:postcode":"92404",
    "sg:province":"CA",
    "sg:tags":[
        "physician",
        "surgeon"
    ],
    "wof:name":"Golden Medical Svc",
    "wof:placetype":"venue"
},
  "geometry": {"coordinates":[-117.278729,34.123902],"type":"Point"}
}