{
  "type": "Feature",
  "properties": {
    "addr:full":"2340 Ashland Ave Santa Monica CA 90405",
    "addr:housenumber":"2340",
    "addr:postcode":"90405",
    "addr:street":"Ashland Ave",
    "iso:country":"US",
    "sg:address":"2340 Ashland Ave",
    "sg:city":"Santa Monica",
    "sg:classifiers":[
        {
            "category":"Professional",
            "subcategory":"Lawyer & Legal Services",
            "type":"Services"
        }
    ],
    "sg:phone":"+1 310 452 7280",
    "sg:postcode":"90405",
    "sg:province":"CA",
    "sg:tags":[
        "attorney"
    ],
    "wof:name":"Daniel Colner",
    "wof:placetype":"venue"
},
  "geometry": {"coordinates":[-118.457847,34.013882],"type":"Point"}
}