{
  "type": "Feature",
  "properties": {
    "iso:country":"US",
    "sg:address":"4675 Mack Rd",
    "sg:city":"Sacramento",
    "sg:classifiers":[
        {
            "category":"Retail",
            "subcategory":"Veterinary Services",
            "type":"Services"
        }
    ],
    "sg:phone":"+1 916 391 6050",
    "sg:postcode":"95823",
    "sg:province":"CA",
    "sg:tags":[
        "clinic",
        "hospital"
    ],
    "wof:name":"Fisher Kristi DVM",
    "wof:placetype":"venue"
},
  "geometry": {"coordinates":[-121.446956,38.474369],"type":"Point"}
}