{
  "type": "Feature",
  "properties": {
    "iso:country":"US",
    "sg:address":"2182 Avenida De La Playa Suite B",
    "sg:city":"La Jolla",
    "sg:classifiers":[
        {
            "category":"Personal",
            "subcategory":"Beauty Salon",
            "type":"Services"
        }
    ],
    "sg:phone":"+1 858 456 8196",
    "sg:postcode":"92037",
    "sg:province":"CA",
    "sg:tags":[
        "hair",
        "makeup",
        "artist"
    ],
    "sg:website":"www.bellasalonlajolla.com",
    "wof:name":"Bella Salon, A Michel Benaroch Salon",
    "wof:placetype":"venue"
},
  "geometry": {"coordinates":[-117.25601899999999,32.854063],"type":"Point"}
}