{
  "type": "Feature",
  "properties": {
    "iso:country":"US",
    "sg:address":"6850 Brockton Ave",
    "sg:city":"Riverside",
    "sg:classifiers":[
        {
            "category":"Health Services",
            "subcategory":"Doctor",
            "type":"Services"
        }
    ],
    "sg:phone":"+1 951 686 5301",
    "sg:postcode":"92506",
    "sg:province":"CA",
    "sg:tags":[
        "dentist"
    ],
    "wof:name":"C Douglas Fowler DDS",
    "wof:placetype":"venue"
},
  "geometry": {"coordinates":[-117.39667900000001,33.949267],"type":"Point"}
}