{
  "type": "Feature",
  "properties": {
    "iso:country":"US",
    "sg:address":"2491 San Ramon Valley Blvd",
    "sg:city":"San Ramon",
    "sg:classifiers":[
        {
            "category":"Banks & Credit Unions",
            "subcategory":"Bank",
            "type":"Services"
        }
    ],
    "sg:phone":"+1 925 355 1618",
    "sg:postcode":"94583",
    "sg:province":"CA",
    "sg:tags":[
        "loan",
        "real estate"
    ],
    "wof:name":"United Investments",
    "wof:placetype":"venue"
},
  "geometry": {"coordinates":[-121.975814,37.774326],"type":"Point"}
}