{
  "type": "Feature",
  "properties": {
    "addr:full":"2651 University Ave Riverside CA 92507",
    "addr:housenumber":"2651",
    "addr:postcode":"92507",
    "addr:street":"University Ave",
    "iso:country":"US",
    "sg:address":"2651 University Ave",
    "sg:city":"Riverside",
    "sg:classifiers":[
        {
            "category":"Retail",
            "subcategory":"Auto Repair",
            "type":"Services"
        }
    ],
    "sg:phone":"+1 951 786 7586",
    "sg:postcode":"92507",
    "sg:province":"CA",
    "sg:tags":[
        "repairing",
        "automobile"
    ],
    "wof:name":"R C Auto Clinic",
    "wof:placetype":"venue"
},
  "geometry": {"coordinates":[-117.361824,33.976076],"type":"Point"}
}