{
  "type": "Feature",
  "properties": {
    "iso:country":"US",
    "sg:address":"160 Eddy Street",
    "sg:city":"San Francisco",
    "sg:classifiers":[
        {
            "category":"Travel",
            "subcategory":"Hotels & Motels",
            "type":"Entertainment"
        }
    ],
    "sg:phone":"+1 415 775 5373",
    "sg:postcode":"94102",
    "sg:province":"CA",
    "wof:name":"Wm Penn Residence",
    "wof:placetype":"venue"
},
  "geometry": {"coordinates":[-122.41020399999999,37.784284],"type":"Point"}
}