{
  "type": "Feature",
  "properties": {
    "addr:full":"613 D St Marysville CA 95901",
    "addr:housenumber":"613",
    "addr:postcode":"95901",
    "addr:street":"D St",
    "iso:country":"US",
    "sg:address":"613 D St",
    "sg:city":"Marysville",
    "sg:classifiers":[
        {
            "category":"Professional",
            "subcategory":"Lawyer & Legal Services",
            "type":"Services"
        }
    ],
    "sg:phone":"+1 530 743 5641",
    "sg:postcode":"95901",
    "sg:province":"CA",
    "sg:tags":[
        "attorney"
    ],
    "wof:name":"James R Vasquez",
    "wof:placetype":"venue"
},
  "geometry": {"coordinates":[-121.58923299999999,39.142427],"type":"Point"}
}