{
  "type": "Feature",
  "properties": {
    "addr:full":"2412 Ramada Plz Fullerton CA 92833",
    "addr:housenumber":"2412",
    "addr:postcode":"92833",
    "addr:street":"Ramada Plz",
    "iso:country":"US",
    "sg:address":"2412 Ramada Plz",
    "sg:city":"Fullerton",
    "sg:classifiers":[
        {
            "category":"Building & Trades",
            "subcategory":"Landscaping Services",
            "type":"Services"
        }
    ],
    "sg:phone":"+1 714 773 5989",
    "sg:postcode":"92833",
    "sg:province":"CA",
    "wof:name":"CTI Landscaping",
    "wof:placetype":"venue"
},
  "geometry": {"coordinates":[-117.968701,33.879675],"type":"Point"}
}