{
  "type": "Feature",
  "properties": {
    "addr:full":"17 Throckmorton Ave Mill Valley CA 94941",
    "addr:housenumber":"17",
    "addr:postcode":"94941",
    "addr:street":"Throckmorton Ave",
    "iso:country":"US",
    "sg:address":"17 Throckmorton Ave",
    "sg:city":"Mill Valley",
    "sg:classifiers":[
        {
            "category":"Restaurant",
            "type":"Food & Drink"
        }
    ],
    "sg:menulink":"http://www.allmenus.com/ca/southeast-marin/21385-el-paseo/menu/",
    "sg:phone":"+1 415 388 0741",
    "sg:postcode":"94941",
    "sg:province":"CA",
    "sg:tags":[
        "french"
    ],
    "wof:name":"El Paseo",
    "wof:placetype":"venue"
},
  "geometry": {"coordinates":[-122.546573,37.906623],"type":"Point"}
}