{
  "type": "Feature",
  "properties": {
    "addr:full":"15525 Broadway Center St Gardena CA 90248",
    "addr:housenumber":"15525",
    "addr:postcode":"90248",
    "addr:street":"Broadway Center St",
    "iso:country":"US",
    "sg:address":"15525 Broadway Center St",
    "sg:city":"Gardena",
    "sg:classifiers":[
        {
            "category":"Building & Trades",
            "subcategory":"Construction",
            "type":"Services"
        }
    ],
    "sg:phone":"+1 310 767 4900",
    "sg:postcode":"90248",
    "sg:province":"CA",
    "sg:tags":[
        "contractor"
    ],
    "sg:website":"www.1stent-const.com",
    "wof:name":"First Enterprise",
    "wof:placetype":"venue"
},
  "geometry": {"coordinates":[-118.279893,33.889905],"type":"Point"}
}