{
  "type": "Feature",
  "properties": {
    "iso:country":"US",
    "sg:address":"4329 el Camino Real",
    "sg:city":"Palo Alto",
    "sg:classifiers":[
        {
            "category":"Sports & Exercise",
            "subcategory":"Bowling",
            "type":"Entertainment"
        }
    ],
    "sg:phone":"+1 650 948 1031",
    "sg:postcode":"94306",
    "sg:province":"CA",
    "sg:tags":[
        "center"
    ],
    "wof:name":"Bowling Management Group",
    "wof:placetype":"venue"
},
  "geometry": {"coordinates":[-122.11865299999999,37.405062],"type":"Point"}
}