{
  "type": "Feature",
  "properties": {
    "iso:country":"US",
    "sg:address":"263 Petrified Forest Rd",
    "sg:city":"Calistoga",
    "sg:classifiers":[
        {
            "category":"Wholesale",
            "subcategory":"Fruits & Vegetables",
            "type":"Manufacturing & Wholesale Goods"
        }
    ],
    "sg:phone":"+1 707 942 0120",
    "sg:postcode":"94515",
    "sg:province":"CA",
    "wof:name":"Lazy Susan Ranch",
    "wof:placetype":"venue"
},
  "geometry": {"coordinates":[-122.624312,38.57312],"type":"Point"}
}