{
  "type": "Feature",
  "properties": {
    "addr:full":"14011 Midland Rd Poway CA 92064",
    "addr:housenumber":"14011",
    "addr:postcode":"ca 92064",
    "addr:street":"Midland Rd",
    "iso:country":"US",
    "sg:address":"14011 Midland Rd",
    "sg:city":"Poway",
    "sg:classifiers":[
        {
            "category":"Personal",
            "subcategory":"Beauty Salon",
            "type":"Services"
        }
    ],
    "sg:phone":"+1 858 748 1225",
    "sg:postcode":"92064",
    "sg:province":"CA",
    "wof:name":"Jojo's Hair Salon",
    "wof:placetype":"venue"
},
  "geometry": {"coordinates":[-117.036073,32.969021],"type":"Point"}
}