{
  "type": "Feature",
  "properties": {
    "iso:country":"US",
    "sg:address":"2996 Freeport Blvd",
    "sg:city":"Sacramento",
    "sg:classifiers":[
        {
            "category":"Shopping",
            "subcategory":"Computers & Home Electronics",
            "type":"Retail Goods"
        }
    ],
    "sg:phone":"+1 916 447 2290",
    "sg:postcode":"95818",
    "sg:province":"CA",
    "sg:tags":[
        "television",
        "radio"
    ],
    "wof:name":"E Channel",
    "wof:placetype":"venue"
},
  "geometry": {"coordinates":[-121.488806,38.551264],"type":"Point"}
}