{
  "type": "Feature",
  "properties": {
    "iso:country":"US",
    "sg:address":"1164 Monroe St",
    "sg:city":"Salinas",
    "sg:classifiers":[
        {
            "category":"Banks & Credit Unions",
            "subcategory":"Investment Brokerage",
            "type":"Services"
        }
    ],
    "sg:phone":"+1 831 444 9255",
    "sg:postcode":"93906",
    "sg:province":"CA",
    "sg:tags":[
        "advisory",
        "financial"
    ],
    "wof:name":"Fabian's Financial Svc",
    "wof:placetype":"venue"
},
  "geometry": {"coordinates":[-121.661385,36.696645],"type":"Point"}
}