{
  "type": "Feature",
  "properties": {
    "iso:country":"US",
    "sg:address":"3403 Cesar Chavez Ste 3",
    "sg:city":"San Francisco",
    "sg:classifiers":[
        {
            "category":"Professional",
            "subcategory":"Art Services",
            "type":"Services"
        }
    ],
    "sg:phone":"+1 415 845 8553",
    "sg:postcode":"94110",
    "sg:province":"CA",
    "sg:tags":[
        "photographer"
    ],
    "sg:website":"petethompsonphoto.com/weddings",
    "wof:name":"Pete Thompson Photography",
    "wof:placetype":"venue"
},
  "geometry": {"coordinates":[-122.418339,37.748079],"type":"Point"}
}