{
  "type": "Feature",
  "properties": {
    "iso:country":"US",
    "sg:address":"533 Airport Blvd",
    "sg:city":"Burlingame",
    "sg:classifiers":[
        {
            "category":"Professional",
            "subcategory":"Employment Agencies",
            "type":"Services"
        }
    ],
    "sg:phone":"+1 650 373 2033",
    "sg:postcode":"94010",
    "sg:province":"CA",
    "sg:tags":[
        "opportunity"
    ],
    "wof:name":"Position Filler",
    "wof:placetype":"venue"
},
  "geometry": {"coordinates":[-122.347466,37.589554],"type":"Point"}
}