{
  "type": "Feature",
  "properties": {
    "iso:country":"US",
    "sg:address":"1056 El Mirador Dr",
    "sg:city":"Fullerton",
    "sg:classifiers":[
        {
            "category":"Shopping",
            "subcategory":"Books",
            "type":"Retail Goods"
        },
        {
            "category":"Wholesale",
            "subcategory":"Books, Periodicals, & Newspapers",
            "type":"Manufacturing & Wholesale Goods"
        }
    ],
    "sg:phone":"+1 714 990 0199",
    "sg:postcode":"92835",
    "sg:province":"CA",
    "sg:tags":[
        "books-wholesale",
        "store",
        "manufacturer"
    ],
    "wof:name":"Lion & Lamb Publications",
    "wof:placetype":"venue"
},
  "geometry": {"coordinates":[-117.90855000000001,33.905618],"type":"Point"}
}