{
  "type": "Feature",
  "properties": {
    "iso:country":"US",
    "sg:address":"1940 University Ave",
    "sg:city":"Riverside",
    "sg:classifiers":[
        {
            "category":"Retail",
            "subcategory":"Self-service Laundry",
            "type":"Services"
        }
    ],
    "sg:phone":"+1 951 787 0952",
    "sg:postcode":"92507",
    "sg:province":"CA",
    "wof:name":"Launderland Coin-Op Laundry",
    "wof:placetype":"venue"
},
  "geometry": {"coordinates":[-117.35313,33.975581],"type":"Point"}
}