{
  "type": "Feature",
  "properties": {
    "iso:country":"US",
    "sg:address":"12395 el Camino Real",
    "sg:city":"San Diego",
    "sg:classifiers":[
        {
            "category":"Health Services",
            "subcategory":"Doctor",
            "type":"Services"
        }
    ],
    "sg:phone":"+1 858 481 3391",
    "sg:postcode":"92130",
    "sg:province":"CA",
    "sg:tags":[
        "physician",
        "surgeon"
    ],
    "wof:name":"Del Mar Ob/Gyn",
    "wof:placetype":"venue"
},
  "geometry": {"coordinates":[-117.23667500000001,32.93389],"type":"Point"}
}