{
  "type": "Feature",
  "properties": {
    "iso:country":"US",
    "sg:address":"4214 Horner St",
    "sg:city":"Union City",
    "sg:classifiers":[
        {
            "category":"Organizations",
            "subcategory":"Religious Organization",
            "type":"Services"
        }
    ],
    "sg:phone":"+1 510 441 2339",
    "sg:postcode":"94587",
    "sg:province":"CA",
    "wof:name":"Vietnamese Alliance Church Of Union City",
    "wof:placetype":"venue"
},
  "geometry": {"coordinates":[-122.26414200000001,37.595362],"type":"Point"}
}