{
  "type": "Feature",
  "properties": {
    "iso:country":"US",
    "sg:address":"41 W Yokuts Ave",
    "sg:city":"Stockton",
    "sg:classifiers":[
        {
            "category":"Wholesale",
            "subcategory":"Machinery & Supplies",
            "type":"Manufacturing & Wholesale Goods"
        }
    ],
    "sg:phone":"+1 209 473 0386",
    "sg:postcode":"95207",
    "sg:province":"CA",
    "sg:tags":[
        "engine"
    ],
    "wof:name":"Cummins West Inc",
    "wof:placetype":"venue"
},
  "geometry": {"coordinates":[-121.309755,37.997879],"type":"Point"}
}