{
  "type": "Feature",
  "properties": {
    "iso:country":"US",
    "sg:address":"46333 Burroweed Ln",
    "sg:city":"Palm Desert",
    "sg:classifiers":[
        {
            "category":"Building & Trades",
            "subcategory":"Construction",
            "type":"Services"
        }
    ],
    "sg:phone":"+1 760 341 4916",
    "sg:postcode":"92260",
    "sg:province":"CA",
    "sg:tags":[
        "contractor"
    ],
    "wof:name":"D & F Development",
    "wof:placetype":"venue"
},
  "geometry": {"coordinates":[-116.382562,33.714032],"type":"Point"}
}