{
  "type": "Feature",
  "properties": {
    "iso:country":"US",
    "sg:address":"24361 el Toro Rd",
    "sg:city":"Laguna Woods",
    "sg:classifiers":[
        {
            "category":"Manufacturing",
            "subcategory":"Petroleum Products",
            "type":"Manufacturing & Wholesale Goods"
        }
    ],
    "sg:phone":"+1 949 460 8300",
    "sg:postcode":"92637",
    "sg:province":"CA",
    "wof:name":"Reserve Petroleum",
    "wof:placetype":"venue"
},
  "geometry": {"coordinates":[-117.72746100000001,33.609314],"type":"Point"}
}