{
  "type": "Feature",
  "properties": {
    "iso:country":"US",
    "sg:address":"8636 S Sepulveda Blvd",
    "sg:city":"Westchester",
    "sg:classifiers":[
        {
            "category":"Restaurant",
            "type":"Food & Drink"
        }
    ],
    "sg:phone":"+1 310 642 0013",
    "sg:postcode":"90045",
    "sg:province":"CA",
    "sg:tags":[
        "mexican"
    ],
    "sg:website":"www.bajafresh.com/",
    "wof:name":"Baja Fresh Mexican Grill",
    "wof:placetype":"venue"
},
  "geometry": {"coordinates":[-118.396034,33.959244],"type":"Point"}
}