{
  "type": "Feature",
  "properties": {
    "addr:full":"2100 Pleasant Hill Rd Sebastopol CA 95472",
    "addr:housenumber":"2100",
    "addr:postcode":"95472",
    "addr:street":"Pleasant Hill Rd",
    "iso:country":"US",
    "sg:address":"2100 Pleasant Hill Rd",
    "sg:city":"Sebastopol",
    "sg:classifiers":[
        {
            "category":"Wholesale",
            "subcategory":"Plants",
            "type":"Manufacturing & Wholesale Goods"
        }
    ],
    "sg:phone":"+1 707 824 6868",
    "sg:postcode":"95472",
    "sg:province":"CA",
    "sg:tags":[
        "supply"
    ],
    "wof:name":"Cal Nor Growers",
    "wof:placetype":"venue"
},
  "geometry": {"coordinates":[-122.83206800000001,38.371489],"type":"Point"}
}