{
  "type": "Feature",
  "properties": {
    "iso:country":"US",
    "sg:address":"1500 W Houston Ave",
    "sg:city":"Visalia",
    "sg:classifiers":[
        {
            "category":"Food & Beverages",
            "subcategory":"Groceries & Convenience Stores",
            "type":"Retail Goods"
        }
    ],
    "sg:phone":"+1 559 732 3893",
    "sg:postcode":"93291",
    "sg:province":"CA",
    "wof:name":"Double D Mini Mart",
    "wof:placetype":"venue"
},
  "geometry": {"coordinates":[-119.308949,36.341893],"type":"Point"}
}