{
  "type": "Feature",
  "properties": {
    "addr:full":"114 N El Camino Real Encinitas CA 92024",
    "addr:housenumber":"114",
    "addr:postcode":"92024",
    "addr:street":"N El Camino Real",
    "iso:country":"US",
    "sg:address":"114 N El Camino Real",
    "sg:city":"Encinitas",
    "sg:classifiers":[
        {
            "category":"Deli",
            "type":"Food & Drink"
        },
        {
            "category":"Food & Beverages",
            "subcategory":"Meat & Fish",
            "type":"Retail Goods"
        }
    ],
    "sg:phone":"+1 760 436 9202",
    "sg:postcode":"92024",
    "sg:province":"CA",
    "sg:tags":[
        "shop"
    ],
    "wof:name":"Golden Baked Hams",
    "wof:placetype":"venue"
},
  "geometry": {"coordinates":[-117.260002,33.046501],"type":"Point"}
}