{
  "type": "Feature",
  "properties": {
    "addr:full":"4529 Cedros Ave Sherman Oaks CA 91403",
    "addr:housenumber":"4529",
    "addr:postcode":"91403",
    "addr:street":"Cedros Ave",
    "iso:country":"US",
    "sg:address":"4529 Cedros Ave",
    "sg:city":"Sherman Oaks",
    "sg:classifiers":[
        {
            "category":"Professional",
            "type":"Services"
        }
    ],
    "sg:phone":"+1 818 788 9057",
    "sg:postcode":"91403",
    "sg:province":"CA",
    "wof:name":"Ameripix Studios Inc",
    "wof:placetype":"venue"
},
  "geometry": {"coordinates":[-118.453059,34.154765],"type":"Point"}
}