{
  "type": "Feature",
  "properties": {
    "iso:country":"US",
    "sg:address":"1510 S Central Ave Ste 300",
    "sg:city":"Glendale",
    "sg:classifiers":[
        {
            "category":"Health Services",
            "subcategory":"Doctor",
            "type":"Services"
        }
    ],
    "sg:phone":"+1 818 254 1500",
    "sg:postcode":"91204",
    "sg:province":"CA",
    "wof:name":"Knox Rozella S MD",
    "wof:placetype":"venue"
},
  "geometry": {"coordinates":[-118.258003,34.127499],"type":"Point"}
}