{
  "type": "Feature",
  "properties": {
    "iso:country":"US",
    "sg:address":"2249 S El Camino Real",
    "sg:city":"Oceanside",
    "sg:classifiers":[
        {
            "category":"Insurance",
            "subcategory":"Health Insurance",
            "type":"Services"
        }
    ],
    "sg:phone":"+1 760 721 3465",
    "sg:postcode":"92054",
    "sg:province":"CA",
    "sg:tags":[
        "market"
    ],
    "wof:name":"Max Muscle",
    "wof:placetype":"venue"
},
  "geometry": {"coordinates":[-117.328003,33.185001],"type":"Point"}
}