{
  "type": "Feature",
  "properties": {
    "addr:full":"1308 Borregas Ave Sunnyvale CA 94089",
    "addr:housenumber":"1308",
    "addr:postcode":"94089",
    "addr:street":"Borregas Ave",
    "iso:country":"US",
    "sg:address":"1308 Borregas Ave",
    "sg:city":"Sunnyvale",
    "sg:phone":"+1 408 541 9162",
    "sg:postcode":"94089",
    "sg:province":"CA",
    "sg:tags":[
        "wireless",
        "software",
        "developer"
    ],
    "sg:website":"www.futuredial.com",
    "wof:name":"Future Dial Inc",
    "wof:placetype":"venue"
},
  "geometry": {"coordinates":[-122.01700200000001,37.414806],"type":"Point"}
}