{
  "type": "Feature",
  "properties": {
    "iso:country":"US",
    "sg:address":"3488 Foothill Blvd",
    "sg:city":"Oroville",
    "sg:classifiers":[
        {
            "category":"Organizations",
            "subcategory":"Religious Organization",
            "type":"Services"
        }
    ],
    "sg:phone":"+1 530 534 3516",
    "sg:postcode":"95966",
    "sg:province":"CA",
    "sg:tags":[
        "spiritualist"
    ],
    "wof:name":"Sharron Hope Spiritual Cnsltnt",
    "wof:placetype":"venue"
},
  "geometry": {"coordinates":[-121.499455,39.479202],"type":"Point"}
}