{
  "type": "Feature",
  "properties": {
    "addr:full":"74 Moraga Way Orinda CA 94563",
    "addr:housenumber":"74",
    "addr:postcode":"94563",
    "addr:street":"Moraga Way",
    "iso:country":"US",
    "sg:address":"74 Moraga Way",
    "sg:city":"Orinda",
    "sg:classifiers":[
        {
            "category":"Restaurant",
            "type":"Food & Drink"
        }
    ],
    "sg:phone":"+1 925 258 9049",
    "sg:postcode":"94563",
    "sg:province":"CA",
    "sg:tags":[
        "mexican"
    ],
    "wof:name":"Maya Mexican Grill",
    "wof:placetype":"venue"
},
  "geometry": {"coordinates":[-122.180542,37.877815],"type":"Point"}
}