{
  "type": "Feature",
  "properties": {
    "addr:full":"12439 S East Ave Fresno CA 93725",
    "addr:housenumber":"12439",
    "addr:postcode":"93725",
    "addr:street":"S East",
    "iso:country":"US",
    "sg:address":"12439 S East Ave",
    "sg:city":"Fresno",
    "sg:classifiers":[
        {
            "category":"Farming",
            "subcategory":"Livestock Farm",
            "type":"Manufacturing & Wholesale Goods"
        }
    ],
    "sg:phone":"+1 559 834 2393",
    "sg:postcode":"93725",
    "sg:province":"CA",
    "sg:tags":[
        "animal",
        "general"
    ],
    "wof:name":"Craig Rogue Farms",
    "wof:placetype":"venue"
},
  "geometry": {"coordinates":[-119.772948,36.561001],"type":"Point"}
}