{
  "type": "Feature",
  "properties": {
    "addr:full":"112 E 9th St Los Angeles CA 90015",
    "addr:housenumber":"112",
    "addr:postcode":"90015",
    "addr:street":"E 9Th St",
    "iso:country":"US",
    "sg:address":"112 E 9th St",
    "sg:city":"Los Angeles",
    "sg:classifiers":[
        {
            "category":"Manufacturing",
            "subcategory":"Apparel",
            "type":"Manufacturing & Wholesale Goods"
        }
    ],
    "sg:phone":"+1 213 622 8690",
    "sg:postcode":"90015",
    "sg:province":"CA",
    "wof:name":"Jet Fashions",
    "wof:placetype":"venue"
},
  "geometry": {"coordinates":[-118.254813,34.041395],"type":"Point"}
}