{
  "type": "Feature",
  "properties": {
    "addr:full":"2222 Torrance Blvd Torrance CA 90501",
    "addr:housenumber":"2222",
    "addr:postcode":"90501",
    "addr:street":"Torrance Blvd",
    "iso:country":"US",
    "sg:address":"2222 Torrance Blvd",
    "sg:city":"Torrance",
    "sg:classifiers":[
        {
            "category":"Professional",
            "subcategory":"Accounting & Tax Preparation",
            "type":"Services"
        }
    ],
    "sg:phone":"+1 310 212 3134",
    "sg:postcode":"90501",
    "sg:province":"CA",
    "sg:tags":[
        "accountant"
    ],
    "wof:name":"Takata Eri Accounting",
    "wof:placetype":"venue"
},
  "geometry": {"coordinates":[-118.322051,33.836334],"type":"Point"}
}