{
  "type": "Feature",
  "properties": {
    "addr:full":"1126 W Church St Santa Maria CA 93458",
    "addr:housenumber":"1126",
    "addr:postcode":"93458",
    "addr:street":"W Church St",
    "iso:country":"US",
    "sg:address":"1126 W Church St",
    "sg:city":"Santa Maria",
    "sg:classifiers":[
        {
            "category":"Retail",
            "subcategory":"Auto Repair",
            "type":"Services"
        }
    ],
    "sg:phone":"+1 805 925 6265",
    "sg:postcode":"93458",
    "sg:province":"CA",
    "sg:tags":[
        "automobile",
        "electric"
    ],
    "wof:name":"J & E Auto Electric",
    "wof:placetype":"venue"
},
  "geometry": {"coordinates":[-120.45202,34.951964],"type":"Point"}
}