{
  "type": "Feature",
  "properties": {
    "addr:full":"517 N Alvarado St Los Angeles CA 90026",
    "addr:housenumber":"517",
    "addr:postcode":"90026",
    "addr:street":"N Alvarado St",
    "iso:country":"US",
    "sg:address":"517 N Alvarado St",
    "sg:city":"Los Angeles",
    "sg:classifiers":[
        {
            "category":"Real Estate",
            "subcategory":"Real Estate Agent",
            "type":"Services"
        }
    ],
    "sg:phone":"+1 213 989 0454",
    "sg:postcode":"90026",
    "sg:province":"CA",
    "wof:name":"Your Team Realty",
    "wof:placetype":"venue"
},
  "geometry": {"coordinates":[-118.26643900000001,34.07287],"type":"Point"}
}