{
  "type": "Feature",
  "properties": {
    "addr:full":"420 South San Pedro St Ste 314 Los Angeles CA 90013",
    "addr:housenumber":"420",
    "addr:postcode":"90013",
    "addr:street":"South San Pedro St Ste 314",
    "iso:country":"US",
    "sg:address":"420 South San Pedro St Ste 314",
    "sg:city":"Los Angeles",
    "sg:classifiers":[
        {
            "category":"Sports & Exercise",
            "subcategory":"Gym",
            "type":"Entertainment"
        }
    ],
    "sg:phone":"+1 617 863 7336",
    "sg:postcode":"90013",
    "sg:province":"CA",
    "sg:tags":[
        "trainer"
    ],
    "sg:website":"www.tempestfreerunning.com",
    "wof:name":"Tempest Freerunning",
    "wof:placetype":"venue"
},
  "geometry": {"coordinates":[-118.24264700000001,34.044858],"type":"Point"}
}