{
  "type": "Feature",
  "properties": {
    "addr:full":"1201 Commercial Ave Oxnard CA 93030",
    "addr:housenumber":"1201",
    "addr:postcode":"93030",
    "addr:street":"Commercial Ave",
    "iso:country":"US",
    "sg:address":"1201 Commercial Ave",
    "sg:city":"Oxnard",
    "sg:classifiers":[
        {
            "category":"Health Services",
            "subcategory":"Clinic",
            "type":"Services"
        }
    ],
    "sg:phone":"+1 805 486 8833",
    "sg:postcode":"93030",
    "sg:province":"CA",
    "sg:tags":[
        "specialty",
        "outpatient"
    ],
    "wof:name":"Fe Ye Esperanza",
    "wof:placetype":"venue"
},
  "geometry": {"coordinates":[-119.171164,34.188551],"type":"Point"}
}