{
  "type": "Feature",
  "properties": {
    "addr:full":"141 S San Fernando Blvd Burbank CA 91502",
    "addr:housenumber":"141",
    "addr:postcode":"91502",
    "addr:street":"S San Fernando Blvd",
    "iso:country":"US",
    "sg:address":"141 S San Fernando Blvd",
    "sg:city":"Burbank",
    "sg:classifiers":[
        {
            "category":"Banks & Credit Unions",
            "subcategory":"Bureau De Change",
            "type":"Services"
        },
        {
            "category":"Wholesale",
            "subcategory":"Office Equipment",
            "type":"Manufacturing & Wholesale Goods"
        },
        {
            "category":"Professional",
            "subcategory":"Business Services",
            "type":"Services"
        },
        {
            "category":"Professional",
            "subcategory":"Printing & Photocopies",
            "type":"Services"
        },
        {
            "category":"Shopping",
            "subcategory":"Computers & Home Electronics",
            "type":"Retail Goods"
        }
    ],
    "sg:phone":"+1 818 841 2686",
    "sg:postcode":"91502",
    "sg:province":"CA",
    "sg:tags":[
        "scanning",
        "printer",
        "form",
        "supply",
        "services-commercial",
        "duplicating",
        "shipping",
        "printers-business",
        "copying",
        "mail",
        "plotting",
        "card"
    ],
    "sg:website":"http://www.kwikkopy.com",
    "wof:name":"Kwik Kopy Printing",
    "wof:placetype":"venue"
},
  "geometry": {"coordinates":[-118.308303,34.180562],"type":"Point"}
}