{
  "type": "Feature",
  "properties": {
    "iso:country":"US",
    "sg:address":"691 E Bidwell St",
    "sg:city":"Folsom",
    "sg:classifiers":[
        {
            "category":"Shopping",
            "subcategory":"Books",
            "type":"Retail Goods"
        }
    ],
    "sg:phone":"+1 916 984 0703",
    "sg:postcode":"95630",
    "sg:province":"CA",
    "sg:tags":[
        "dealer"
    ],
    "wof:name":"Family Christian Book Store",
    "wof:placetype":"venue"
},
  "geometry": {"coordinates":[-121.15408600000001,38.669489],"type":"Point"}
}