{
  "type": "Feature",
  "properties": {
    "iso:country":"US",
    "sg:address":"2912 Mission Blvd",
    "sg:city":"San Diego",
    "sg:classifiers":[
        {
            "category":"Restaurant",
            "type":"Food & Drink"
        }
    ],
    "sg:phone":"+1 858 488 4010",
    "sg:postcode":"92109",
    "sg:province":"CA",
    "sg:tags":[
        "pizza"
    ],
    "wof:name":"Gabbiano Pizza",
    "wof:placetype":"venue"
},
  "geometry": {"coordinates":[-117.251411,32.765881],"type":"Point"}
}