{
  "type": "Feature",
  "properties": {
    "iso:country":"US",
    "sg:address":"11292 Coloma Rd",
    "sg:city":"Gold River",
    "sg:classifiers":[
        {
            "category":"Building & Trades",
            "subcategory":"Plumbing",
            "type":"Services"
        }
    ],
    "sg:phone":"+1 916 852 1816",
    "sg:postcode":"95670",
    "sg:province":"CA",
    "sg:tags":[
        "conditioning",
        "air",
        "system",
        "contractor"
    ],
    "wof:name":"All Weather Air Comfort",
    "wof:placetype":"venue"
},
  "geometry": {"coordinates":[-121.263363,38.619187],"type":"Point"}
}