{
  "type": "Feature",
  "properties": {
    "addr:full":"275 E Hillcrest Dr Thousand Oaks CA 91360",
    "addr:housenumber":"275",
    "addr:postcode":"91360",
    "addr:street":"E Hillcrest Dr",
    "iso:country":"US",
    "sg:address":"275 E Hillcrest Dr",
    "sg:city":"Thousand Oaks",
    "sg:classifiers":[
        {
            "category":"Building & Trades",
            "subcategory":"Landscaping Services",
            "type":"Services"
        }
    ],
    "sg:phone":"+1 805 494 8155",
    "sg:postcode":"91360",
    "sg:province":"CA",
    "sg:tags":[
        "landscape"
    ],
    "wof:name":"Landmark Design",
    "wof:placetype":"venue"
},
  "geometry": {"coordinates":[-118.870183,34.181273],"type":"Point"}
}