{
  "type": "Feature",
  "properties": {
    "addr:full":"1595 S Mission Rd Fallbrook CA 92028",
    "addr:housenumber":"1595",
    "addr:postcode":"92028",
    "addr:street":"S Mission Rd",
    "iso:country":"US",
    "sg:address":"1595 S Mission Rd",
    "sg:city":"Fallbrook",
    "sg:classifiers":[
        {
            "category":"Real Estate",
            "subcategory":"Real Estate Services",
            "type":"Services"
        }
    ],
    "sg:phone":"+1 760 723 2353",
    "sg:postcode":"92028",
    "sg:province":"CA",
    "sg:website":"www.willisallen.com",
    "wof:name":"Willis Allen Real Estate",
    "wof:placetype":"venue"
},
  "geometry": {"coordinates":[-117.249743,33.364064],"type":"Point"}
}