{
  "type": "Feature",
  "properties": {
    "addr:full":"13100 Kirkham Way Suite 204 Poway CA 92064",
    "addr:housenumber":"13100",
    "addr:postcode":"ca 92064",
    "addr:street":"Kirkham Way Suite 204",
    "iso:country":"US",
    "sg:address":"13100 Kirkham Way Suite 204",
    "sg:city":"Poway",
    "sg:classifiers":[
        {
            "category":"Building & Trades",
            "subcategory":"Cleaning & Sanitation",
            "type":"Services"
        },
        {
            "category":"Professional",
            "subcategory":"Art Services",
            "type":"Services"
        },
        {
            "category":"Building & Trades",
            "subcategory":"Construction",
            "type":"Services"
        }
    ],
    "sg:phone":"+1 858 538 2100",
    "sg:postcode":"92064",
    "sg:province":"CA",
    "sg:tags":[
        "plastering",
        "washing",
        "power",
        "wallcoverings-installation",
        "wallpaper",
        "contractor",
        "drywall",
        "faux",
        "finishing",
        "painting"
    ],
    "sg:website":"http://www.servicemagic.com/rated.AppliedPainting.14118365.AllCats.html?m=cahscitysrchxm&entry_point_id=479710",
    "wof:name":"Applied Painting",
    "wof:placetype":"venue"
},
  "geometry": {"coordinates":[-117.043015,32.93488],"type":"Point"}
}