{
  "type": "Feature",
  "properties": {
    "addr:full":"16800 S Broadway Street Gardena CA 90248",
    "addr:housenumber":"16800",
    "addr:postcode":"90248",
    "addr:street":"S Broadway Street",
    "iso:country":"US",
    "sg:address":"16800 S Broadway Street",
    "sg:city":"Gardena",
    "sg:classifiers":[
        {
            "category":"Retail",
            "subcategory":"Auto Repair",
            "type":"Services"
        }
    ],
    "sg:phone":"+1 310 769 0800",
    "sg:postcode":"90248",
    "sg:province":"CA",
    "wof:name":"Broadway Auto Center",
    "wof:placetype":"venue"
},
  "geometry": {"coordinates":[-118.278235,33.878622],"type":"Point"}
}