{
  "type": "Feature",
  "properties": {
    "addr:full":"4379 Convoy St San Diego CA 92111",
    "addr:housenumber":"4379",
    "addr:postcode":"92111",
    "addr:street":"Convoy St",
    "iso:country":"US",
    "sg:address":"4379 Convoy St",
    "sg:city":"San Diego",
    "sg:classifiers":[
        {
            "category":"Personal",
            "subcategory":"Beauty Salon",
            "type":"Services"
        }
    ],
    "sg:phone":"+1 858 492 9880",
    "sg:postcode":"92111",
    "sg:province":"CA",
    "wof:name":"Lolita Balbuena",
    "wof:placetype":"venue"
},
  "geometry": {"coordinates":[-117.154757,32.817334],"type":"Point"}
}