{
  "type": "Feature",
  "properties": {
    "addr:full":"7 Pazzi Irvine CA 92614",
    "addr:postcode":"92614",
    "addr:street":"Pazzi",
    "iso:country":"US",
    "sg:address":"7 Pazzi",
    "sg:city":"Irvine",
    "sg:classifiers":[
        {
            "category":"Shopping",
            "subcategory":"Beauty & Cosmetics",
            "type":"Retail Goods"
        }
    ],
    "sg:phone":"+1 949 474 7725",
    "sg:postcode":"92614",
    "sg:province":"CA",
    "sg:tags":[
        "merchandise"
    ],
    "wof:name":"Elsereine California",
    "wof:placetype":"venue"
},
  "geometry": {"coordinates":[-117.814207,33.679234],"type":"Point"}
}