{
  "type": "Feature",
  "properties": {
    "iso:country":"US",
    "sg:address":"530 N Rio Vista Ave",
    "sg:city":"Sanger",
    "sg:classifiers":[
        {
            "category":"Farming",
            "subcategory":"Vineyard",
            "type":"Manufacturing & Wholesale Goods"
        }
    ],
    "sg:phone":"+1 559 787 3311",
    "sg:postcode":"93657",
    "sg:province":"CA",
    "sg:tags":[
        "grape"
    ],
    "wof:name":"William Domoto",
    "wof:placetype":"venue"
},
  "geometry": {"coordinates":[-119.474884,36.74181],"type":"Point"}
}