{
  "type": "Feature",
  "properties": {
    "iso:country":"US",
    "sg:address":"1343 Rollins Dr",
    "sg:city":"Los Angeles",
    "sg:classifiers":[
        {
            "category":"Retail",
            "subcategory":"Photofinishing",
            "type":"Services"
        }
    ],
    "sg:phone":"+1 323 268 2854",
    "sg:postcode":"90063",
    "sg:province":"CA",
    "sg:tags":[
        "photo",
        "finishing"
    ],
    "wof:name":"Bongo-Logic Photo-Design",
    "wof:placetype":"venue"
},
  "geometry": {"coordinates":[-118.169399,34.054891],"type":"Point"}
}