{
  "type": "Feature",
  "properties": {
    "iso:country":"US",
    "sg:address":"19105 S Figueroa St",
    "sg:city":"Gardena",
    "sg:classifiers":[
        {
            "category":"Home & Garden",
            "subcategory":"Building Materials",
            "type":"Retail Goods"
        }
    ],
    "sg:phone":"+1 310 217 9152",
    "sg:postcode":"90248",
    "sg:province":"CA",
    "wof:name":"ABC Supply Co",
    "wof:placetype":"venue"
},
  "geometry": {"coordinates":[-118.281521,33.857442],"type":"Point"}
}