{
  "type": "Feature",
  "properties": {
    "addr:full":"3822 Campus Drive Suite 215 Newport Beach CA 92660",
    "addr:housenumber":"3822",
    "addr:postcode":"92660",
    "addr:street":"Campus Drive Suite 215",
    "iso:country":"US",
    "sg:address":"3822 Campus Drive Suite 215",
    "sg:city":"Newport Beach",
    "sg:classifiers":[
        {
            "category":"Real Estate",
            "subcategory":"Architect",
            "type":"Services"
        }
    ],
    "sg:phone":"+1 949 724 9650",
    "sg:postcode":"92660",
    "sg:province":"CA",
    "wof:name":"Architectural Design Solu",
    "wof:placetype":"venue"
},
  "geometry": {"coordinates":[-117.873375,33.663969],"type":"Point"}
}