{
  "type": "Feature",
  "properties": {
    "iso:country":"US",
    "sg:address":"17995 Wisteria St",
    "sg:city":"Hesperia",
    "sg:classifiers":[
        {
            "category":"Retail",
            "subcategory":"Repair Shop",
            "type":"Services"
        }
    ],
    "sg:phone":"+1 760 948 5397",
    "sg:postcode":"92345",
    "sg:province":"CA",
    "sg:tags":[
        "lock",
        "locksmith"
    ],
    "wof:name":"A & D Desert Lock & Key",
    "wof:placetype":"venue"
},
  "geometry": {"coordinates":[-117.270435,34.443809],"type":"Point"}
}