{
  "type": "Feature",
  "properties": {
    "addr:full":"14061 Chestnut St Westminster CA 92683",
    "addr:housenumber":"14061",
    "addr:postcode":"92683",
    "addr:street":"Chestnut St",
    "iso:country":"US",
    "sg:address":"14061 Chestnut St",
    "sg:city":"Westminster",
    "sg:classifiers":[
        {
            "category":"Organizations",
            "subcategory":"Religious Organization",
            "type":"Services"
        }
    ],
    "sg:phone":"+1 714 373 4679",
    "sg:postcode":"92683",
    "sg:province":"CA",
    "wof:name":"Iglesia Siloe De Westminster",
    "wof:placetype":"venue"
},
  "geometry": {"coordinates":[-118.00299800000001,33.758099],"type":"Point"}
}