{
  "type": "Feature",
  "properties": {
    "addr:full":"203 S Verdugo Rd Glendale CA 91205",
    "addr:housenumber":"203",
    "addr:postcode":"91205",
    "addr:street":"S Verdugo Rd",
    "iso:country":"US",
    "sg:address":"203 S Verdugo Rd",
    "sg:city":"Glendale",
    "sg:classifiers":[
        {
            "category":"Professional",
            "subcategory":"Computer Services",
            "type":"Services"
        }
    ],
    "sg:phone":"+1 818 637 8500",
    "sg:postcode":"91205",
    "sg:province":"CA",
    "sg:tags":[
        "repair"
    ],
    "wof:name":"Global Netcom",
    "wof:placetype":"venue"
},
  "geometry": {"coordinates":[-118.234382,34.143651],"type":"Point"}
}