{
  "type": "Feature",
  "properties": {
    "addr:full":"12520 Magnolia Blvd Ste 212 Valley Village CA 91607",
    "addr:housenumber":"12520",
    "addr:postcode":"91607",
    "addr:street":"Magnolia Blvd Ste 212",
    "iso:country":"US",
    "sg:address":"12520 Magnolia Blvd Ste 212",
    "sg:city":"Valley Village",
    "sg:classifiers":[
        {
            "category":"Professional",
            "subcategory":"Accounting & Tax Preparation",
            "type":"Services"
        }
    ],
    "sg:phone":"+1 818 980 7867",
    "sg:postcode":"91607",
    "sg:province":"CA",
    "sg:tags":[
        "accountant"
    ],
    "wof:name":"Soule Thomas R CPA",
    "wof:placetype":"venue"
},
  "geometry": {"coordinates":[-118.405998,34.164902],"type":"Point"}
}