{
  "type": "Feature",
  "properties": {
    "iso:country":"US",
    "sg:address":"7000 S Center Dr",
    "sg:city":"Clearlake",
    "sg:classifiers":[
        {
            "category":"Government",
            "subcategory":"Office",
            "type":"Public Place"
        }
    ],
    "sg:phone":"+1 707 994 6494",
    "sg:postcode":"95422",
    "sg:province":"CA",
    "wof:name":"Lake County Alcohol & Drug Svc",
    "wof:placetype":"venue"
},
  "geometry": {"coordinates":[-122.61788799999999,38.933608],"type":"Point"}
}