{
  "type": "Feature",
  "properties": {
    "iso:country":"US",
    "sg:address":"39 Mission Ridge Ct",
    "sg:city":"Fremont",
    "sg:classifiers":[
        {
            "category":"Professional",
            "subcategory":"Management & Consulting",
            "type":"Services"
        }
    ],
    "sg:phone":"+1 510 659 1690",
    "sg:postcode":"94539",
    "sg:province":"CA",
    "sg:tags":[
        "jewelry"
    ],
    "wof:name":"S&J Creation Inc",
    "wof:placetype":"venue"
},
  "geometry": {"coordinates":[-121.934061,37.546799],"type":"Point"}
}