{
  "type": "Feature",
  "properties": {
    "addr:full":"604 E El Camino Real Sunnyvale CA 94087",
    "addr:housenumber":"604",
    "addr:postcode":"94087",
    "addr:street":"E El Camino Real",
    "iso:country":"US",
    "sg:address":"604 E El Camino Real",
    "sg:city":"Sunnyvale",
    "sg:classifiers":[
        {
            "category":"Fast Food",
            "type":"Food & Drink"
        }
    ],
    "sg:phone":"+1 800 786 1000",
    "sg:postcode":"94087",
    "sg:province":"CA",
    "sg:tags":[
        "burger"
    ],
    "sg:website":"www.in-n-out.com",
    "wof:name":"In-N-Out Burger",
    "wof:placetype":"venue"
},
  "geometry": {"coordinates":[-122.025002,37.361401],"type":"Point"}
}