{
  "type": "Feature",
  "properties": {
    "iso:country":"US",
    "sg:address":"23615 el Toro Rd",
    "sg:city":"Lake Forest",
    "sg:classifiers":[
        {
            "category":"Retail",
            "subcategory":"Repair Shop",
            "type":"Services"
        }
    ],
    "sg:phone":"+1 949 586 5397",
    "sg:postcode":"92630",
    "sg:province":"CA",
    "sg:tags":[
        "lock",
        "locksmith"
    ],
    "wof:name":"Surfside Lock & Key Inc",
    "wof:placetype":"venue"
},
  "geometry": {"coordinates":[-117.700863,33.62038],"type":"Point"}
}