{
  "type": "Feature",
  "properties": {
    "addr:full":"11231 Culver Ct El Cajon CA 92020",
    "addr:housenumber":"11231",
    "addr:postcode":"92020",
    "addr:street":"Culver Ct",
    "iso:country":"US",
    "sg:address":"11231 Culver Ct",
    "sg:city":"El Cajon",
    "sg:classifiers":[
        {
            "category":"Building & Trades",
            "subcategory":"Construction",
            "type":"Services"
        }
    ],
    "sg:phone":"+1 619 447 1374",
    "sg:postcode":"92020",
    "sg:province":"CA",
    "sg:tags":[
        "contractor"
    ],
    "wof:name":"Lamesa Roofing & Construction",
    "wof:placetype":"venue"
},
  "geometry": {"coordinates":[-116.955309,32.763717],"type":"Point"}
}