{
  "type": "Feature",
  "properties": {
    "iso:country":"US",
    "sg:address":"11931 Washington Blvd",
    "sg:city":"Whittier",
    "sg:classifiers":[
        {
            "category":"Organizations",
            "subcategory":"Religious Organization",
            "type":"Services"
        }
    ],
    "sg:phone":"+1 562 696 6213",
    "sg:postcode":"90606",
    "sg:province":"CA",
    "sg:tags":[
        "church"
    ],
    "wof:name":"Good Samaritan MCC",
    "wof:placetype":"venue"
},
  "geometry": {"coordinates":[-118.056685,33.968644],"type":"Point"}
}