{
  "type": "Feature",
  "properties": {
    "iso:country":"US",
    "sg:address":"1565 Reliance Way",
    "sg:city":"Fremont",
    "sg:classifiers":[
        {
            "category":"Manufacturing",
            "subcategory":"Tools & Machinery",
            "type":"Manufacturing & Wholesale Goods"
        }
    ],
    "sg:phone":"+1 510 651 8886",
    "sg:postcode":"94539",
    "sg:province":"CA",
    "sg:tags":[
        "computer"
    ],
    "wof:name":"Amax Engineering Corp",
    "wof:placetype":"venue"
},
  "geometry": {"coordinates":[-121.929984,37.500978],"type":"Point"}
}