{
  "type": "Feature",
  "properties": {
    "iso:country":"US",
    "sg:address":"107 Pebbly Beach Rd",
    "sg:city":"Avalon",
    "sg:classifiers":[
        {
            "category":"Recreation",
            "subcategory":"Boat Charter",
            "type":"Entertainment"
        }
    ],
    "sg:phone":"+1 310 510 0087",
    "sg:postcode":"90704",
    "sg:province":"CA",
    "sg:tags":[
        "boat-rental"
    ],
    "wof:name":"Catalina Wild Thing",
    "wof:placetype":"venue"
},
  "geometry": {"coordinates":[-118.323826,33.342815],"type":"Point"}
}