{
  "type": "Feature",
  "properties": {
    "iso:country":"US",
    "sg:address":"3371 Adams Ave",
    "sg:city":"San Diego",
    "sg:classifiers":[
        {
            "category":"Building & Trades",
            "subcategory":"Plumbing",
            "type":"Services"
        }
    ],
    "sg:phone":"+1 619 282 8172",
    "sg:postcode":"92116",
    "sg:province":"CA",
    "sg:tags":[
        "plumbing",
        "heating",
        "contractor"
    ],
    "wof:name":"Riling R E Plumbing",
    "wof:placetype":"venue"
},
  "geometry": {"coordinates":[-117.121056,32.763274],"type":"Point"}
}