{
  "type": "Feature",
  "properties": {
    "addr:full":"4961 La Palma La Palma CA 90623",
    "addr:housenumber":"4961",
    "addr:postcode":"90623",
    "addr:street":"La Palma",
    "iso:country":"US",
    "sg:address":"4961 La Palma",
    "sg:city":"La Palma",
    "sg:classifiers":[
        {
            "category":"Restaurant",
            "type":"Food & Drink"
        }
    ],
    "sg:phone":"+1 562 924 8289",
    "sg:postcode":"90623",
    "sg:province":"CA",
    "sg:tags":[
        "korean"
    ],
    "wof:name":"Soy Tofu",
    "wof:placetype":"venue"
},
  "geometry": {"coordinates":[-118.04637099999999,33.84737],"type":"Point"}
}