{
  "type": "Feature",
  "properties": {
    "addr:full":"130 N Larchmont Blvd Los Angeles CA 90004",
    "addr:housenumber":"130",
    "addr:postcode":"90004",
    "addr:street":"N Larchmont Blvd",
    "iso:country":"US",
    "sg:address":"130 N Larchmont Blvd",
    "sg:city":"Los Angeles",
    "sg:classifiers":[
        {
            "category":"Shopping",
            "subcategory":"Gifts & Souvenirs",
            "type":"Retail Goods"
        }
    ],
    "sg:phone":"+1 323 467 3755",
    "sg:postcode":"90004",
    "sg:province":"CA",
    "wof:name":"Wee Forest Folk Collectors Hav",
    "wof:placetype":"venue"
},
  "geometry": {"coordinates":[-118.323465,34.075724],"type":"Point"}
}