{
  "type": "Feature",
  "properties": {
    "iso:country":"US",
    "sg:address":"13201 Dog Bar Rd",
    "sg:city":"Grass Valley",
    "sg:classifiers":[
        {
            "category":"Professional",
            "subcategory":"Computer Services",
            "type":"Services"
        }
    ],
    "sg:phone":"+1 530 274 8945",
    "sg:postcode":"95949",
    "sg:province":"CA",
    "wof:name":"RAI Systems",
    "wof:placetype":"venue"
},
  "geometry": {"coordinates":[-121.044895,39.171843],"type":"Point"}
}