{
  "type": "Feature",
  "properties": {
    "addr:full":"497 Silverado Trl N St Helena CA 94574",
    "addr:housenumber":"497",
    "addr:postcode":"94574",
    "addr:street":"Silverado Trl N",
    "iso:country":"US",
    "sg:address":"497 Silverado Trl N",
    "sg:city":"St Helena",
    "sg:classifiers":[
        {
            "category":"Real Estate",
            "subcategory":"Architect",
            "type":"Services"
        }
    ],
    "sg:phone":"+1 707 963 3013",
    "sg:postcode":"94574",
    "sg:province":"CA",
    "wof:name":"Bouligny & Assoc",
    "wof:placetype":"venue"
},
  "geometry": {"coordinates":[-122.46581399999999,38.518217],"type":"Point"}
}