{
  "type": "Feature",
  "properties": {
    "iso:country":"US",
    "sg:address":"268 Clara St",
    "sg:city":"San Francisco",
    "sg:classifiers":[
        {
            "category":"Home & Garden",
            "subcategory":"Furniture",
            "type":"Retail Goods"
        }
    ],
    "sg:phone":"+1 415 495 6364",
    "sg:postcode":"94107",
    "sg:province":"CA",
    "sg:tags":[
        "equipment",
        "kitchen",
        "cabinet"
    ],
    "wof:name":"Peter Beecher",
    "wof:placetype":"venue"
},
  "geometry": {"coordinates":[-122.403437,37.778973],"type":"Point"}
}