{
  "type": "Feature",
  "properties": {
    "iso:country":"US",
    "sg:address":"569 W Covina Blvd",
    "sg:city":"San Dimas",
    "sg:classifiers":[
        {
            "category":"Wholesale",
            "subcategory":"Electrical",
            "type":"Manufacturing & Wholesale Goods"
        }
    ],
    "sg:phone":"+1 909 599 4412",
    "sg:postcode":"91773",
    "sg:province":"CA",
    "sg:tags":[
        "equipment",
        "electronic",
        "representative",
        "for"
    ],
    "wof:name":"A-F Sales Engineering",
    "wof:placetype":"venue"
},
  "geometry": {"coordinates":[-117.816398,34.099427],"type":"Point"}
}