{
  "type": "Feature",
  "properties": {
    "iso:country":"US",
    "sg:address":"45410 Enfield Rd",
    "sg:city":"King City",
    "sg:classifiers":[
        {
            "category":"Freight",
            "type":"Transportation"
        }
    ],
    "sg:phone":"+1 831 443 3776",
    "sg:postcode":"93930",
    "sg:province":"CA",
    "sg:tags":[
        "trucking"
    ],
    "wof:name":"Stockfeld Trucking",
    "wof:placetype":"venue"
},
  "geometry": {"coordinates":[-121.147545,36.188846],"type":"Point"}
}