{
  "type": "Feature",
  "properties": {
    "iso:country":"US",
    "sg:address":"6321 E Monte Vista Ave",
    "sg:city":"Denair",
    "sg:classifiers":[
        {
            "category":"Farming",
            "subcategory":"Dairy Farm",
            "type":"Manufacturing & Wholesale Goods"
        }
    ],
    "sg:phone":"+1 209 634 6629",
    "sg:postcode":"95316",
    "sg:province":"CA",
    "wof:name":"Foster Dairy Farms",
    "wof:placetype":"venue"
},
  "geometry": {"coordinates":[-120.785832,37.521743],"type":"Point"}
}