{
  "type": "Feature",
  "properties": {
    "addr:full":"40 Kentucky Ave Woodland CA 95695",
    "addr:housenumber":"40",
    "addr:postcode":"95695",
    "addr:street":"Kentucky Ave",
    "iso:country":"US",
    "sg:address":"40 Kentucky Ave",
    "sg:city":"Woodland",
    "sg:classifiers":[
        {
            "category":"Wholesale",
            "subcategory":"Machinery & Supplies",
            "type":"Manufacturing & Wholesale Goods"
        }
    ],
    "sg:phone":"+1 530 662 1051",
    "sg:postcode":"95695",
    "sg:province":"CA",
    "sg:tags":[
        "transmission",
        "equipment",
        "power"
    ],
    "wof:name":"Chase",
    "wof:placetype":"venue"
},
  "geometry": {"coordinates":[-121.782479,38.69192],"type":"Point"}
}