{
  "type": "Feature",
  "properties": {
    "iso:country":"US",
    "sg:address":"895 E Fremont Avenue",
    "sg:city":"Sunnyvale",
    "sg:classifiers":[
        {
            "category":"Health Services",
            "subcategory":"Doctor",
            "type":"Services"
        }
    ],
    "sg:phone":"+1 408 773 9700",
    "sg:postcode":"94087",
    "sg:province":"CA",
    "wof:name":"Cho Chang H MD",
    "wof:placetype":"venue"
},
  "geometry": {"coordinates":[-122.014535,37.352229],"type":"Point"}
}