{
  "type": "Feature",
  "properties": {
    "addr:full":"11965 Venice Blvd Los Angeles CA 90066",
    "addr:housenumber":"11965",
    "addr:postcode":"90066",
    "addr:street":"Venice Blvd",
    "iso:country":"US",
    "sg:address":"11965 Venice Blvd",
    "sg:city":"Los Angeles",
    "sg:classifiers":[
        {
            "category":"Communications",
            "subcategory":"Film & Video Production",
            "type":"Services"
        }
    ],
    "sg:phone":"+1 310 578 6599",
    "sg:postcode":"90066",
    "sg:province":"CA",
    "sg:tags":[
        "motion",
        "picture",
        "studio",
        "producer"
    ],
    "sg:website":"www.filmmates.net",
    "wof:name":"Film Mates Corp",
    "wof:placetype":"venue"
},
  "geometry": {"coordinates":[-118.427871,34.007127],"type":"Point"}
}