{
  "type": "Feature",
  "properties": {
    "iso:country":"US",
    "sg:address":"803 Wright Ave",
    "sg:city":"Richmond",
    "sg:classifiers":[
        {
            "category":"Manufacturing",
            "subcategory":"Tools & Machinery",
            "type":"Manufacturing & Wholesale Goods"
        }
    ],
    "sg:phone":"+1 510 741 5218",
    "sg:postcode":"94804",
    "sg:province":"CA",
    "sg:tags":[
        "pr",
        "instrumentation",
        "mfg",
        "research",
        "analytical",
        "diagnostic"
    ],
    "wof:name":"Bio-RAD Laboratories Inc",
    "wof:placetype":"venue"
},
  "geometry": {"coordinates":[-122.360074,37.92127],"type":"Point"}
}