{
  "type": "Feature",
  "properties": {
    "iso:country":"US",
    "sg:address":"6801 Hollywood Boulevard",
    "sg:city":"Los Angeles",
    "sg:classifiers":[
        {
            "category":"Professional",
            "type":"Services"
        }
    ],
    "sg:phone":"+1 310 559 6777",
    "sg:postcode":"90028",
    "sg:province":"CA",
    "sg:tags":[
        "caterer"
    ],
    "wof:name":"Gai Klass Catering",
    "wof:placetype":"venue"
},
  "geometry": {"coordinates":[-118.338668,34.101584],"type":"Point"}
}