{
  "type": "Feature",
  "properties": {
    "addr:full":"19 Elm St Stockton CA 95204",
    "addr:housenumber":"19",
    "addr:postcode":"95204",
    "addr:street":"Elm St",
    "iso:country":"US",
    "sg:address":"19 Elm St",
    "sg:city":"Stockton",
    "sg:classifiers":[
        {
            "category":"Utilities",
            "subcategory":"Telephone",
            "type":"Services"
        }
    ],
    "sg:phone":"+1 209 464 1268",
    "sg:postcode":"95204",
    "sg:province":"CA",
    "sg:tags":[
        "communications"
    ],
    "wof:name":"Nahvi Legorreta",
    "wof:placetype":"venue"
},
  "geometry": {"coordinates":[-121.29444100000001,37.96854],"type":"Point"}
}