{
  "type": "Feature",
  "properties": {
    "iso:country":"US",
    "sg:address":"9532 Shannon Ave",
    "sg:city":"Garden Grove",
    "sg:classifiers":[
        {
            "category":"Retail",
            "subcategory":"Repair Shop",
            "type":"Services"
        }
    ],
    "sg:phone":"+1 714 292 9124",
    "sg:postcode":"92841",
    "sg:province":"CA",
    "sg:tags":[
        "related"
    ],
    "wof:name":"JAM Golf Cars",
    "wof:placetype":"venue"
},
  "geometry": {"coordinates":[-117.967178,33.792547],"type":"Point"}
}