{
  "type": "Feature",
  "properties": {
    "iso:country":"US",
    "sg:address":"1544 E 4th St",
    "sg:city":"Long Beach",
    "sg:classifiers":[
        {
            "category":"Personal",
            "subcategory":"Beauty Salon",
            "type":"Services"
        }
    ],
    "sg:phone":"+1 562 437 7720",
    "sg:postcode":"90802",
    "sg:province":"CA",
    "wof:name":"Twist N Shout",
    "wof:placetype":"venue"
},
  "geometry": {"coordinates":[-118.172911,33.771633],"type":"Point"}
}