{
  "type": "Feature",
  "properties": {
    "iso:country":"US",
    "sg:address":"17700 Pioneer Blvd",
    "sg:city":"Artesia",
    "sg:classifiers":[
        {
            "category":"Health Services",
            "subcategory":"Doctor",
            "type":"Services"
        }
    ],
    "sg:phone":"+1 562 865 0013",
    "sg:postcode":"90701",
    "sg:province":"CA",
    "sg:tags":[
        "dentist"
    ],
    "wof:name":"Samuel R Maehara Inc",
    "wof:placetype":"venue"
},
  "geometry": {"coordinates":[-118.08217,33.870227],"type":"Point"}
}