{
  "type": "Feature",
  "properties": {
    "iso:country":"US",
    "sg:address":"5825 Dover St",
    "sg:city":"Oakland",
    "sg:classifiers":[
        {
            "category":"Wholesale",
            "subcategory":"Sporting Goods",
            "type":"Manufacturing & Wholesale Goods"
        }
    ],
    "sg:phone":"+1 510 652 9387",
    "sg:postcode":"94609",
    "sg:province":"CA",
    "sg:tags":[
        "tackle",
        "fishing"
    ],
    "wof:name":"Evets & Co",
    "wof:placetype":"venue"
},
  "geometry": {"coordinates":[-122.26825,37.844536],"type":"Point"}
}