{
  "type": "Feature",
  "properties": {
    "addr:full":"2001 W Maxzim Ave Fullerton CA 92833",
    "addr:housenumber":"2001",
    "addr:postcode":"92833",
    "addr:street":"W Maxzim Ave",
    "iso:country":"US",
    "sg:address":"2001 W Maxzim Ave",
    "sg:city":"Fullerton",
    "sg:classifiers":[
        {
            "category":"Home & Garden",
            "subcategory":"Building Materials",
            "type":"Retail Goods"
        }
    ],
    "sg:phone":"+1 714 441 1107",
    "sg:postcode":"92833",
    "sg:province":"CA",
    "sg:tags":[
        "door",
        "gate",
        "operating",
        "devices"
    ],
    "wof:name":"Accent Automated Gates Inc",
    "wof:placetype":"venue"
},
  "geometry": {"coordinates":[-117.96641,33.85619],"type":"Point"}
}