{
  "type": "Feature",
  "properties": {
    "addr:full":"1725 Oakdell Dr Menlo Park CA 94025",
    "addr:housenumber":"1725",
    "addr:postcode":"94025",
    "addr:street":"Oakdell Dr",
    "iso:country":"US",
    "sg:address":"1725 Oakdell Dr",
    "sg:city":"Menlo Park",
    "sg:classifiers":[
        {
            "category":"Professional",
            "subcategory":"Engineering",
            "type":"Services"
        }
    ],
    "sg:phone":"+1 650 321 1079",
    "sg:postcode":"94025",
    "sg:province":"CA",
    "sg:tags":[
        "engineer"
    ],
    "wof:name":"W B Barnes Inc",
    "wof:placetype":"venue"
},
  "geometry": {"coordinates":[-122.19128600000001,37.435339],"type":"Point"}
}