{
  "type": "Feature",
  "properties": {
    "addr:full":"123 S 1st St La Puente CA 91744",
    "addr:housenumber":"123",
    "addr:postcode":"91744",
    "addr:street":"S 1St St",
    "iso:country":"US",
    "sg:address":"123 S 1st St",
    "sg:city":"La Puente",
    "sg:classifiers":[
        {
            "category":"Shopping",
            "subcategory":"Books",
            "type":"Retail Goods"
        }
    ],
    "sg:phone":"+1 626 918 6252",
    "sg:postcode":"91744",
    "sg:province":"CA",
    "sg:tags":[
        "dealer"
    ],
    "wof:name":"A Great Read",
    "wof:placetype":"venue"
},
  "geometry": {"coordinates":[-117.952696,34.019825],"type":"Point"}
}