{
  "type": "Feature",
  "properties": {
    "addr:full":"4673 Clayton Rd Concord CA 94521",
    "addr:housenumber":"4673",
    "addr:postcode":"94521",
    "addr:street":"Clayton Rd",
    "iso:country":"US",
    "sg:address":"4673 Clayton Rd",
    "sg:city":"Concord",
    "sg:classifiers":[
        {
            "category":"Shopping",
            "subcategory":"Department Store",
            "type":"Retail Goods"
        }
    ],
    "sg:phone":"+1 925 686 3418",
    "sg:postcode":"94521",
    "sg:province":"CA",
    "wof:name":"T J Maxx",
    "wof:placetype":"venue"
},
  "geometry": {"coordinates":[-121.982725,37.961307],"type":"Point"}
}