{
  "type": "Feature",
  "properties": {
    "addr:full":"2300 Portola Dr Santa Cruz CA 95062",
    "addr:housenumber":"2300",
    "addr:postcode":"95062",
    "addr:street":"Portola Dr",
    "iso:country":"US",
    "sg:address":"2300 Portola Dr",
    "sg:city":"Santa Cruz",
    "sg:classifiers":[
        {
            "category":"Communications",
            "subcategory":"Radio Station",
            "type":"Services"
        }
    ],
    "sg:phone":"+1 831 475 1080",
    "sg:postcode":"95062",
    "sg:province":"CA",
    "wof:name":"Ksco Am 1080 Red Hot News Talk Radio",
    "wof:placetype":"venue"
},
  "geometry": {"coordinates":[-121.978996,36.9632],"type":"Point"}
}