{
  "type": "Feature",
  "properties": {
    "addr:full":"1831 Solano Ave 714 Berkeley CA 94707",
    "addr:housenumber":"1831;714",
    "addr:postcode":"94707",
    "addr:street":"Solano Ave",
    "iso:country":"US",
    "sg:address":"1831 Solano Ave 714",
    "sg:city":"Berkeley",
    "sg:classifiers":[
        {
            "category":"Professional",
            "subcategory":"Engineering",
            "type":"Services"
        }
    ],
    "sg:phone":"+1 510 524 1494",
    "sg:postcode":"94707",
    "sg:province":"CA",
    "sg:tags":[
        "consulting",
        "engineer"
    ],
    "sg:website":"http://www.calengineering.com",
    "wof:name":"Cal Engineering",
    "wof:placetype":"venue"
},
  "geometry": {"coordinates":[-122.279116,37.891375],"type":"Point"}
}