{
  "type": "Feature",
  "properties": {
    "iso:country":"US",
    "sg:address":"32940 Wishing Well Trl",
    "sg:city":"Cathedral City",
    "sg:classifiers":[
        {
            "category":"Manufacturing",
            "subcategory":"Tools & Machinery",
            "type":"Manufacturing & Wholesale Goods"
        }
    ],
    "sg:phone":"+1 760 321 5152",
    "sg:postcode":"92234",
    "sg:province":"CA",
    "sg:tags":[
        "industry",
        "mfg"
    ],
    "wof:name":"Aqua Inpery",
    "wof:placetype":"venue"
},
  "geometry": {"coordinates":[-116.465687,33.81189],"type":"Point"}
}