{
  "type": "Feature",
  "properties": {
    "iso:country":"US",
    "sg:address":"1530 W Cowles St",
    "sg:city":"Long Beach",
    "sg:classifiers":[
        {
            "category":"Retail",
            "subcategory":"Auto Repair",
            "type":"Services"
        }
    ],
    "sg:phone":"+1 562 436 1521",
    "sg:postcode":"90813",
    "sg:province":"CA",
    "sg:tags":[
        "repairing",
        "automobile"
    ],
    "wof:name":"Long Beach Truck Sales",
    "wof:placetype":"venue"
},
  "geometry": {"coordinates":[-118.212997,33.784801],"type":"Point"}
}