{
  "type": "Feature",
  "properties": {
    "addr:full":"54415 Pinon Dr Yucca Valley CA 92284",
    "addr:housenumber":"54415",
    "addr:postcode":"92284",
    "addr:street":"Pinon Dr Yucca",
    "iso:country":"US",
    "sg:address":"54415 Pinon Dr",
    "sg:city":"Yucca Valley",
    "sg:classifiers":[
        {
            "category":"Real Estate",
            "subcategory":"Real Estate Agent",
            "type":"Services"
        }
    ],
    "sg:phone":"+1 760 365 7130",
    "sg:postcode":"92284",
    "sg:province":"CA",
    "sg:tags":[
        "management"
    ],
    "wof:name":"Desert Talking Homes",
    "wof:placetype":"venue"
},
  "geometry": {"coordinates":[-116.475585,34.116006],"type":"Point"}
}