{
  "type": "Feature",
  "properties": {
    "iso:country":"US",
    "sg:address":"242 Laurel Street",
    "sg:city":"San Francisco",
    "sg:classifiers":[
        {
            "category":"Real Estate",
            "subcategory":"Architect",
            "type":"Services"
        }
    ],
    "sg:phone":"+1 415 391 1726",
    "sg:postcode":"94118",
    "sg:province":"CA",
    "wof:name":"Gordon Hall & Associates Residential Design",
    "wof:placetype":"venue"
},
  "geometry": {"coordinates":[-122.45074099999999,37.78917],"type":"Point"}
}