{
  "type": "Feature",
  "properties": {
    "addr:full":"5273 Hollywood Blvd Los Angeles CA 90027",
    "addr:housenumber":"5273",
    "addr:postcode":"90027",
    "addr:street":"Hollywood Blvd",
    "iso:country":"US",
    "sg:address":"5273 Hollywood Blvd",
    "sg:city":"Los Angeles",
    "sg:classifiers":[
        {
            "category":"Restaurant",
            "type":"Food & Drink"
        }
    ],
    "sg:phone":"+1 323 466 3894",
    "sg:postcode":"90027",
    "sg:province":"CA",
    "sg:tags":[
        "thai"
    ],
    "wof:name":"Thai Patio",
    "wof:placetype":"venue"
},
  "geometry": {"coordinates":[-118.305311,34.101753],"type":"Point"}
}