{
  "type": "Feature",
  "properties": {
    "addr:full":"30301 Golden Lantern Laguna Niguel CA 92677",
    "addr:housenumber":"30301",
    "addr:postcode":"92677",
    "addr:street":"Golden Lantern",
    "iso:country":"US",
    "sg:address":"30301 Golden Lantern",
    "sg:city":"Laguna Niguel",
    "sg:classifiers":[
        {
            "category":"Ice Cream",
            "type":"Food & Drink"
        }
    ],
    "sg:menulink":"http://www.allmenus.com/ca/south-coast/208880-tcby/menu/",
    "sg:phone":"+1 949 363 1454",
    "sg:postcode":"92677",
    "sg:province":"CA",
    "sg:tags":[
        "smoothy",
        "juice",
        "american"
    ],
    "wof:name":"TCBY",
    "wof:placetype":"venue"
},
  "geometry": {"coordinates":[-117.686345,33.523996],"type":"Point"}
}