{
  "type": "Feature",
  "properties": {
    "iso:country":"US",
    "sg:address":"1001 5th St. Suite C",
    "sg:city":"Modesto",
    "sg:classifiers":[
        {
            "category":"Retail",
            "subcategory":"Auto Repair",
            "type":"Services"
        }
    ],
    "sg:phone":"+1 209 576 8080",
    "sg:postcode":"95351",
    "sg:province":"CA",
    "wof:name":"Jett Transmission",
    "wof:placetype":"venue"
},
  "geometry": {"coordinates":[-121.00549599999999,37.636868],"type":"Point"}
}