{
  "type": "Feature",
  "properties": {
    "addr:full":"24177 Postal Ave Moreno Valley CA 92553",
    "addr:postcode":"24177;92553",
    "addr:street":"Postal Ave",
    "iso:country":"US",
    "sg:address":"24177 Postal Ave",
    "sg:city":"Moreno Valley",
    "sg:classifiers":[
        {
            "category":"Organizations",
            "subcategory":"Religious Organization",
            "type":"Services"
        }
    ],
    "sg:phone":"+1 951 924 7545",
    "sg:postcode":"92553",
    "sg:province":"CA",
    "sg:tags":[
        "church"
    ],
    "wof:name":"Spiritual Uplift Church",
    "wof:placetype":"venue"
},
  "geometry": {"coordinates":[-117.243037,33.939975],"type":"Point"}
}