{
  "type": "Feature",
  "properties": {
    "iso:country":"US",
    "sg:address":"3812 Park Blvd",
    "sg:city":"San Diego",
    "sg:classifiers":[
        {
            "category":"Real Estate",
            "subcategory":"Real Estate Services",
            "type":"Services"
        }
    ],
    "sg:postcode":"92103",
    "sg:province":"CA",
    "wof:name":"The Egyptian Condos",
    "wof:placetype":"venue"
},
  "geometry": {"coordinates":[-117.146708,32.747972],"type":"Point"}
}