{
  "type": "Feature",
  "properties": {
    "addr:full":"234 Main St Alleghany CA 95910",
    "addr:housenumber":"234",
    "addr:postcode":"95910",
    "addr:street":"Main St",
    "iso:country":"US",
    "sg:address":"234 Main St",
    "sg:city":"Alleghany",
    "sg:classifiers":[
        {
            "category":"Bars & Pubs",
            "type":"Food & Drink"
        },
        {
            "category":"Restaurant",
            "type":"Food & Drink"
        },
        {
            "category":"Bars & Pubs",
            "subcategory":"Lounge",
            "type":"Food & Drink"
        }
    ],
    "sg:phone":"+1 530 287 9809",
    "sg:postcode":"95910",
    "sg:province":"CA",
    "sg:tags":[
        "cocktail"
    ],
    "wof:name":"Casey's Place",
    "wof:placetype":"venue"
},
  "geometry": {"coordinates":[-120.851021,39.464512],"type":"Point"}
}