{
  "type": "Feature",
  "properties": {
    "iso:country":"US",
    "sg:address":"195 W Valley Blvd",
    "sg:city":"Colton",
    "sg:classifiers":[
        {
            "category":"Restaurant",
            "type":"Food & Drink"
        }
    ],
    "sg:phone":"+1 909 370 2980",
    "sg:postcode":"92324",
    "sg:province":"CA",
    "wof:name":"Hall Of Fame Sports Bar",
    "wof:placetype":"venue"
},
  "geometry": {"coordinates":[-117.324421,34.067029],"type":"Point"}
}