{
  "type": "Feature",
  "properties": {
    "addr:full":"301 S Ham Ln Lodi CA 95242",
    "addr:housenumber":"301",
    "addr:postcode":"95242",
    "addr:street":"S Ham Ln",
    "iso:country":"US",
    "sg:address":"301 S Ham Ln",
    "sg:city":"Lodi",
    "sg:classifiers":[
        {
            "category":"Banks & Credit Unions",
            "subcategory":"Bank",
            "type":"Services"
        }
    ],
    "sg:phone":"+1 209 367 4232",
    "sg:postcode":"95242",
    "sg:province":"CA",
    "sg:tags":[
        "broker",
        "mortgage"
    ],
    "wof:name":"Capitol Mortgage Corporation",
    "wof:placetype":"venue"
},
  "geometry": {"coordinates":[-121.288186,38.126377],"type":"Point"}
}