{
  "type": "Feature",
  "properties": {
    "addr:full":"1531 E Lincoln Ave Anaheim CA 92805",
    "addr:housenumber":"1531",
    "addr:postcode":"92805",
    "addr:street":"E Lincoln Ave",
    "iso:country":"US",
    "sg:address":"1531 E Lincoln Ave",
    "sg:city":"Anaheim",
    "sg:classifiers":[
        {
            "category":"Home & Garden",
            "subcategory":"Building Materials",
            "type":"Retail Goods"
        }
    ],
    "sg:phone":"+1 714 635 9350",
    "sg:postcode":"92805",
    "sg:province":"CA",
    "sg:tags":[
        "glass",
        "window",
        "plate"
    ],
    "wof:name":"Glass Doctor",
    "wof:placetype":"venue"
},
  "geometry": {"coordinates":[-117.89695,33.839466],"type":"Point"}
}