{
  "type": "Feature",
  "properties": {
    "iso:country":"US",
    "sg:address":"1505 Soquel Dr",
    "sg:city":"Santa Cruz",
    "sg:classifiers":[
        {
            "category":"Health Services",
            "subcategory":"Doctor",
            "type":"Services"
        }
    ],
    "sg:phone":"+1 831 476 4230",
    "sg:postcode":"95065",
    "sg:province":"CA",
    "sg:tags":[
        "physician",
        "surgeon"
    ],
    "wof:name":"Gordon Lee MD",
    "wof:placetype":"venue"
},
  "geometry": {"coordinates":[-121.984124,36.988313],"type":"Point"}
}