{
  "type": "Feature",
  "properties": {
    "addr:full":"26 Belle Ave San Anselmo CA 94960",
    "addr:housenumber":"26",
    "addr:postcode":"94960",
    "addr:street":"Belle Ave",
    "iso:country":"US",
    "sg:address":"26 Belle Ave",
    "sg:city":"San Anselmo",
    "sg:classifiers":[
        {
            "category":"Banks & Credit Unions",
            "subcategory":"Bank",
            "type":"Services"
        }
    ],
    "sg:phone":"+1 415 456 1112",
    "sg:postcode":"94960",
    "sg:province":"CA",
    "sg:tags":[
        "national",
        "commercial"
    ],
    "wof:name":"Halau NA Pua O Kala Akia",
    "wof:placetype":"venue"
},
  "geometry": {"coordinates":[-122.563513,37.969758],"type":"Point"}
}