{
  "type": "Feature",
  "properties": {
    "iso:country":"US",
    "sg:address":"3213 Fond Dr",
    "sg:city":"Encino",
    "sg:classifiers":[
        {
            "category":"Wholesale",
            "subcategory":"Groceries",
            "type":"Manufacturing & Wholesale Goods"
        }
    ],
    "sg:phone":"+1 818 788 5579",
    "sg:postcode":"91436",
    "sg:province":"CA",
    "sg:tags":[
        "grocers-wholesale"
    ],
    "wof:name":"San Diego Pizza Distributors",
    "wof:placetype":"venue"
},
  "geometry": {"coordinates":[-118.48374200000001,34.133132],"type":"Point"}
}