{
  "type": "Feature",
  "properties": {
    "addr:full":"3722 W Pico Blvd Los Angeles CA 90019",
    "addr:housenumber":"3722",
    "addr:postcode":"90019",
    "addr:street":"W Pico Blvd",
    "iso:country":"US",
    "sg:address":"3722 W Pico Blvd",
    "sg:city":"Los Angeles",
    "sg:classifiers":[
        {
            "category":"Building & Trades",
            "subcategory":"Plumbing",
            "type":"Services"
        }
    ],
    "sg:phone":"+1 323 732 1448",
    "sg:postcode":"90019",
    "sg:province":"CA",
    "sg:tags":[
        "contractor"
    ],
    "wof:name":"Union Refrigeration Inc",
    "wof:placetype":"venue"
},
  "geometry": {"coordinates":[-118.322245,34.047335],"type":"Point"}
}