{
  "type": "Feature",
  "properties": {
    "addr:full":"12011 Victory Blvd Ste 104 North Hollywood CA 91606",
    "addr:housenumber":"12011",
    "addr:postcode":"91606",
    "addr:street":"Victory Blvd Ste 104",
    "iso:country":"US",
    "sg:address":"12011 Victory Blvd Ste 104",
    "sg:city":"North Hollywood",
    "sg:classifiers":[
        {
            "category":"Shopping",
            "subcategory":"Mobile Phones",
            "type":"Retail Goods"
        }
    ],
    "sg:phone":"+1 818 506 5658",
    "sg:postcode":"91606",
    "sg:province":"CA",
    "wof:name":"Phones R US",
    "wof:placetype":"venue"
},
  "geometry": {"coordinates":[-118.394997,34.186699],"type":"Point"}
}