{
  "type": "Feature",
  "properties": {
    "iso:country":"US",
    "sg:address":"930 G St",
    "sg:city":"Los Banos",
    "sg:classifiers":[
        {
            "category":"Retail",
            "subcategory":"Auto Repair",
            "type":"Services"
        }
    ],
    "sg:phone":"+1 209 826 0410",
    "sg:postcode":"93635",
    "sg:province":"CA",
    "sg:tags":[
        "body",
        "automobile",
        "painting"
    ],
    "wof:name":"Lino's Auto Body Shop",
    "wof:placetype":"venue"
},
  "geometry": {"coordinates":[-120.84177099999999,37.060883],"type":"Point"}
}