{
  "type": "Feature",
  "properties": {
    "iso:country":"US",
    "sg:address":"4314 Duquesne Ave",
    "sg:city":"Culver City",
    "sg:classifiers":[
        {
            "category":"Home & Garden",
            "subcategory":"Furniture",
            "type":"Retail Goods"
        }
    ],
    "sg:phone":"+1 310 558 3378",
    "sg:postcode":"90232",
    "sg:province":"CA",
    "sg:tags":[
        "via",
        "internet"
    ],
    "wof:name":"Just Fine",
    "wof:placetype":"venue"
},
  "geometry": {"coordinates":[-118.389649,34.017726],"type":"Point"}
}