{
  "type": "Feature",
  "properties": {
    "addr:full":"8047 Old Redwood Hwy Cotati CA 94931",
    "addr:housenumber":"8047",
    "addr:postcode":"94931",
    "addr:street":"Old Redwood Hwy",
    "iso:country":"US",
    "sg:address":"8047 Old Redwood Hwy",
    "sg:city":"Cotati",
    "sg:classifiers":[
        {
            "category":"Travel",
            "subcategory":"Travel Agent",
            "type":"Entertainment"
        }
    ],
    "sg:phone":"+1 707 795 7919",
    "sg:postcode":"94931",
    "sg:province":"CA",
    "sg:tags":[
        "agency",
        "bureau"
    ],
    "wof:name":"Gravenstein Cotati Travel",
    "wof:placetype":"venue"
},
  "geometry": {"coordinates":[-122.707475,38.327771],"type":"Point"}
}