{
  "type": "Feature",
  "properties": {
    "addr:full":"4388 Central Ave Camarillo CA 93010",
    "addr:housenumber":"4388",
    "addr:postcode":"93010",
    "addr:street":"Central Ave",
    "iso:country":"US",
    "sg:address":"4388 Central Ave",
    "sg:city":"Camarillo",
    "sg:classifiers":[
        {
            "category":"Arts & Performance",
            "subcategory":"Music",
            "type":"Entertainment"
        }
    ],
    "sg:phone":"+1 805 988 9970",
    "sg:postcode":"93010",
    "sg:province":"CA",
    "sg:tags":[
        "jockey",
        "disc"
    ],
    "wof:name":"After 7 Dj & Karaoke",
    "wof:placetype":"venue"
},
  "geometry": {"coordinates":[-119.10382199999999,34.224037],"type":"Point"}
}