{
  "type": "Feature",
  "properties": {
    "iso:country":"US",
    "sg:address":"160 Donahue St",
    "sg:city":"Sausalito",
    "sg:classifiers":[
        {
            "category":"Personal",
            "subcategory":"Beauty Salon",
            "type":"Services"
        }
    ],
    "sg:phone":"+1 415 332 6625",
    "sg:postcode":"94965",
    "sg:province":"CA",
    "wof:name":"Gateway Beauty Supply",
    "wof:placetype":"venue"
},
  "geometry": {"coordinates":[-122.511779,37.873247],"type":"Point"}
}