{
  "type": "Feature",
  "properties": {
    "addr:full":"750 31st Ave San Francisco CA 94121",
    "addr:housenumber":"750",
    "addr:postcode":"94121",
    "addr:street":"31St Ave",
    "iso:country":"US",
    "sg:address":"750 31st Ave",
    "sg:city":"San Francisco",
    "sg:classifiers":[
        {
            "category":"Social Services",
            "subcategory":"Child Care",
            "type":"Services"
        }
    ],
    "sg:phone":"+1 415 668 6539",
    "sg:postcode":"94121",
    "sg:province":"CA",
    "wof:name":"Cross Cultural Family Ctr",
    "wof:placetype":"venue"
},
  "geometry": {"coordinates":[-122.490731,37.775098],"type":"Point"}
}