{
  "type": "Feature",
  "properties": {
    "iso:country":"US",
    "sg:address":"122 W 4th St",
    "sg:city":"Los Angeles",
    "sg:classifiers":[
        {
            "category":"Restaurant",
            "type":"Food & Drink"
        }
    ],
    "sg:phone":"+1 213 617 2600",
    "sg:postcode":"90013",
    "sg:province":"CA",
    "wof:name":"Quiznos Sub",
    "wof:placetype":"venue"
},
  "geometry": {"coordinates":[-118.24758,34.048253],"type":"Point"}
}