{
  "type": "Feature",
  "properties": {
    "iso:country":"US",
    "sg:address":"1305 66th St",
    "sg:city":"Emeryville",
    "sg:classifiers":[
        {
            "category":"Airline",
            "type":"Transportation"
        }
    ],
    "sg:phone":"+1 510 585 1499",
    "sg:postcode":"94608",
    "sg:province":"CA",
    "sg:tags":[
        "shuttle",
        "airport"
    ],
    "wof:name":"Thunder Shuttle",
    "wof:placetype":"venue"
},
  "geometry": {"coordinates":[-122.29100200000001,37.847969],"type":"Point"}
}