{
  "type": "Feature",
  "properties": {
    "iso:country":"US",
    "sg:address":"1841 Reynolds Way",
    "sg:city":"Sacramento",
    "sg:classifiers":[
        {
            "category":"Building & Trades",
            "subcategory":"Construction",
            "type":"Services"
        }
    ],
    "sg:phone":"+1 916 334 5200",
    "sg:postcode":"95838",
    "sg:province":"CA",
    "sg:tags":[
        "fence",
        "contractor"
    ],
    "wof:name":"Holliday Fence Co",
    "wof:placetype":"venue"
},
  "geometry": {"coordinates":[-121.424984,38.65273],"type":"Point"}
}