{
  "type": "Feature",
  "properties": {
    "iso:country":"US",
    "sg:address":"468 Fisher Cir",
    "sg:city":"Folsom",
    "sg:classifiers":[
        {
            "category":"Professional",
            "subcategory":"Management & Consulting",
            "type":"Services"
        }
    ],
    "sg:phone":"+1 916 983 6796",
    "sg:postcode":"95630",
    "sg:province":"CA",
    "sg:tags":[
        "retail",
        "direct",
        "sales"
    ],
    "wof:name":"Tango Salsa",
    "wof:placetype":"venue"
},
  "geometry": {"coordinates":[-121.16497099999999,38.656752],"type":"Point"}
}