{
  "type": "Feature",
  "properties": {
    "iso:country":"US",
    "sg:address":"1506 Sproule Ave",
    "sg:city":"Sacramento",
    "sg:classifiers":[
        {
            "category":"Government",
            "subcategory":"Office",
            "type":"Public Place"
        }
    ],
    "sg:phone":"+1 916 498 8510",
    "sg:postcode":"95811",
    "sg:province":"CA",
    "sg:tags":[
        "consultation",
        "sales"
    ],
    "wof:name":"Silent Knights SEC & Per Safet",
    "wof:placetype":"venue"
},
  "geometry": {"coordinates":[-121.480033,38.592307],"type":"Point"}
}