{
  "type": "Feature",
  "properties": {
    "iso:country":"US",
    "sg:address":"2509 Coronado Ave",
    "sg:city":"San Diego",
    "sg:classifiers":[
        {
            "category":"Food & Beverages",
            "subcategory":"Groceries & Convenience Stores",
            "type":"Retail Goods"
        }
    ],
    "sg:phone":"+1 619 424 8475",
    "sg:postcode":"92154",
    "sg:province":"CA",
    "wof:name":"7-Eleven",
    "wof:placetype":"venue"
},
  "geometry": {"coordinates":[-117.078958,32.576403],"type":"Point"}
}