{
  "type": "Feature",
  "properties": {
    "iso:country":"US",
    "sg:address":"75101 Sego Ln",
    "sg:city":"Palm Desert",
    "sg:classifiers":[
        {
            "category":"Home & Garden",
            "subcategory":"Furniture",
            "type":"Retail Goods"
        }
    ],
    "sg:phone":"+1 760 341 7220",
    "sg:postcode":"92211",
    "sg:province":"CA",
    "wof:name":"Changes",
    "wof:placetype":"venue"
},
  "geometry": {"coordinates":[-116.35545999999999,33.741258],"type":"Point"}
}