{
  "type": "Feature",
  "properties": {
    "addr:full":"3700 Easton Dr Bakersfield CA 93309",
    "addr:housenumber":"3700",
    "addr:postcode":"93309",
    "addr:street":"Easton Dr",
    "iso:country":"US",
    "sg:address":"3700 Easton Dr",
    "sg:city":"Bakersfield",
    "sg:classifiers":[
        {
            "category":"Professional",
            "type":"Services"
        }
    ],
    "sg:phone":"+1 661 323 4044",
    "sg:postcode":"93309",
    "sg:province":"CA",
    "sg:tags":[
        "establishment"
    ],
    "wof:name":"Incontrol",
    "wof:placetype":"venue"
},
  "geometry": {"coordinates":[-119.04464400000001,35.368251],"type":"Point"}
}