{
  "type": "Feature",
  "properties": {
    "iso:country":"US",
    "sg:address":"511 Wilbur Ave Ste B1",
    "sg:city":"Antioch",
    "sg:classifiers":[
        {
            "category":"Retail",
            "subcategory":"Auto Repair",
            "type":"Services"
        }
    ],
    "sg:phone":"+1 925 890 3375",
    "sg:postcode":"94509",
    "sg:province":"CA",
    "sg:tags":[
        "body",
        "painting",
        "repairing",
        "automobile"
    ],
    "wof:name":"Darryls Collision Center",
    "wof:placetype":"venue"
},
  "geometry": {"coordinates":[-121.79568999999999,38.012266],"type":"Point"}
}