{
  "type": "Feature",
  "properties": {
    "iso:country":"US",
    "sg:address":"41701 US Hwy 101",
    "sg:city":"Laytonville",
    "sg:classifiers":[
        {
            "category":"Building & Trades",
            "subcategory":"Landscaping Services",
            "type":"Services"
        }
    ],
    "sg:phone":"+1 707 984 6629",
    "sg:postcode":"95490",
    "sg:province":"CA",
    "sg:tags":[
        "tree"
    ],
    "wof:name":"Family Tree Svc",
    "wof:placetype":"venue"
},
  "geometry": {"coordinates":[-123.476105,39.666195],"type":"Point"}
}