{
  "type": "Feature",
  "properties": {
    "iso:country":"US",
    "sg:address":"312 N Anaheim Blvd",
    "sg:city":"Anaheim",
    "sg:classifiers":[
        {
            "category":"Shopping",
            "subcategory":"Crafts & Fabrics",
            "type":"Retail Goods"
        },
        {
            "category":"Retail",
            "subcategory":"Auto Repair",
            "type":"Services"
        }
    ],
    "sg:phone":"+1 714 635 5557",
    "sg:postcode":"92805",
    "sg:province":"CA",
    "sg:tags":[
        "body",
        "shop",
        "art",
        "supply"
    ],
    "sg:website":"www.coastairbrush.com/",
    "wof:name":"Coast Airbrush",
    "wof:placetype":"venue"
},
  "geometry": {"coordinates":[-117.915001,33.838299],"type":"Point"}
}