{
  "type": "Feature",
  "properties": {
    "addr:full":"13158 Van Nuys Blvd Pacoima CA 91331",
    "addr:housenumber":"13158",
    "addr:postcode":"91331",
    "addr:street":"Van Nuys Blvd",
    "iso:country":"US",
    "sg:address":"13158 Van Nuys Blvd",
    "sg:city":"Pacoima",
    "sg:classifiers":[
        {
            "category":"Food & Beverages",
            "subcategory":"Groceries & Convenience Stores",
            "type":"Retail Goods"
        }
    ],
    "sg:phone":"+1 818 896 6618",
    "sg:postcode":"91331",
    "sg:province":"CA",
    "sg:tags":[
        "supermarket"
    ],
    "wof:name":"Tresierras Market 1",
    "wof:placetype":"venue"
},
  "geometry": {"coordinates":[-118.420102,34.267477],"type":"Point"}
}