{
  "type": "Feature",
  "properties": {
    "iso:country":"US",
    "sg:address":"837 W Christopher St",
    "sg:city":"West Covina",
    "sg:classifiers":[
        {
            "category":"Real Estate",
            "subcategory":"Developer",
            "type":"Services"
        }
    ],
    "sg:phone":"+1 626 814 9097",
    "sg:postcode":"91790",
    "sg:province":"CA",
    "wof:name":"Alturas Homes",
    "wof:placetype":"venue"
},
  "geometry": {"coordinates":[-117.92889700000001,34.06542],"type":"Point"}
}