{
  "type": "Feature",
  "properties": {
    "iso:country":"US",
    "sg:address":"450 S Western Ave",
    "sg:city":"Los Angeles",
    "sg:classifiers":[
        {
            "category":"Retail",
            "subcategory":"Portrait Studio",
            "type":"Services"
        }
    ],
    "sg:phone":"+1 213 385 4242",
    "sg:postcode":"90020",
    "sg:province":"CA",
    "sg:tags":[
        "photography",
        "store"
    ],
    "wof:name":"Han Nam One Hour Photo",
    "wof:placetype":"venue"
},
  "geometry": {"coordinates":[-118.308463,34.065767],"type":"Point"}
}