{
  "type": "Feature",
  "properties": {
    "iso:country":"US",
    "sg:address":"44 Montgomery St",
    "sg:city":"San Francisco",
    "sg:classifiers":[
        {
            "category":"Utilities",
            "subcategory":"Cable",
            "type":"Services"
        }
    ],
    "sg:phone":"+1 415 262 9933",
    "sg:postcode":"94104",
    "sg:province":"CA",
    "sg:tags":[
        "television"
    ],
    "wof:name":"DCA Cablevision",
    "wof:placetype":"venue"
},
  "geometry": {"coordinates":[-122.40204900000001,37.789642],"type":"Point"}
}