{
  "type": "Feature",
  "properties": {
    "addr:full":"735 W Duarte Rd Arcadia CA 91007",
    "addr:housenumber":"735",
    "addr:postcode":"91007",
    "addr:street":"W Duarte Rd",
    "iso:country":"US",
    "sg:address":"735 W Duarte Rd",
    "sg:city":"Arcadia",
    "sg:classifiers":[
        {
            "category":"Banks & Credit Unions",
            "subcategory":"Investment Brokerage",
            "type":"Services"
        }
    ],
    "sg:phone":"+1 626 446 5243",
    "sg:postcode":"91007",
    "sg:province":"CA",
    "sg:tags":[
        "investing"
    ],
    "wof:name":"Ho Tim Cfp",
    "wof:placetype":"venue"
},
  "geometry": {"coordinates":[-118.056,34.125999],"type":"Point"}
}