{
  "type": "Feature",
  "properties": {
    "addr:full":"620 W F St Oakdale CA 95361",
    "addr:housenumber":"620",
    "addr:postcode":"95361",
    "addr:street":"W F St",
    "iso:country":"US",
    "sg:address":"620 W F St",
    "sg:city":"Oakdale",
    "sg:classifiers":[
        {
            "category":"Organizations",
            "subcategory":"Religious Organization",
            "type":"Services"
        }
    ],
    "sg:phone":"+1 209 847 2268",
    "sg:postcode":"95361",
    "sg:province":"CA",
    "sg:tags":[
        "church"
    ],
    "wof:name":"Church Of Christ",
    "wof:placetype":"venue"
},
  "geometry": {"coordinates":[-120.85441299999999,37.763706],"type":"Point"}
}