{
  "type": "Feature",
  "properties": {
    "iso:country":"US",
    "sg:address":"620 W F St",
    "sg:city":"Oakdale",
    "sg:classifiers":[
        {
            "category":"Organizations",
            "subcategory":"Religious Organization",
            "type":"Services"
        }
    ],
    "sg:phone":"+1 209 847 2268",
    "sg:postcode":"95361",
    "sg:province":"CA",
    "sg:tags":[
        "church"
    ],
    "wof:name":"Church Of Christ",
    "wof:placetype":"venue"
},
  "geometry": {"coordinates":[-120.854413,37.763706],"type":"Point"}
}