{
  "type": "Feature",
  "properties": {
    "addr:full":"300 N Santa Anita Ave Arcadia CA 91006",
    "addr:housenumber":"300",
    "addr:postcode":"91006",
    "addr:street":"N Santa Anita Ave",
    "iso:country":"US",
    "sg:address":"300 N Santa Anita Ave",
    "sg:city":"Arcadia",
    "sg:classifiers":[
        {
            "category":"Building & Trades",
            "subcategory":"Plumbing",
            "type":"Services"
        }
    ],
    "sg:phone":"+1 626 446 5117",
    "sg:postcode":"91006",
    "sg:province":"CA",
    "sg:tags":[
        "plumbing",
        "contractor"
    ],
    "wof:name":"Arroyo Plumbing",
    "wof:placetype":"venue"
},
  "geometry": {"coordinates":[-118.031403,34.142291],"type":"Point"}
}