{
  "type": "Feature",
  "properties": {
    "addr:full":"29000 Hesperian Blvd Hayward CA 94545",
    "addr:housenumber":"29000",
    "addr:postcode":"94545",
    "addr:street":"Hesperian Blvd",
    "iso:country":"US",
    "sg:address":"29000 Hesperian Blvd",
    "sg:city":"Hayward",
    "sg:classifiers":[
        {
            "category":"Manufacturing",
            "subcategory":"Food",
            "type":"Manufacturing & Wholesale Goods"
        }
    ],
    "sg:phone":"+1 510 781 3756",
    "sg:postcode":"94545",
    "sg:province":"CA",
    "sg:tags":[
        "drink",
        "soft",
        "mfg"
    ],
    "wof:name":"Pepsico",
    "wof:placetype":"venue"
},
  "geometry": {"coordinates":[-122.086555,37.614204],"type":"Point"}
}