{
  "type": "Feature",
  "properties": {
    "addr:full":"1327 Crows Landing Rd Modesto CA 95351",
    "addr:housenumber":"1327",
    "addr:postcode":"ca 95351",
    "addr:street":"Crows Landing Rd",
    "iso:country":"US",
    "sg:address":"1327 Crows Landing Rd",
    "sg:city":"Modesto",
    "sg:classifiers":[
        {
            "category":"Home & Garden",
            "subcategory":"Household Appliances",
            "type":"Retail Goods"
        }
    ],
    "sg:phone":"+1 209 522 4485",
    "sg:postcode":"95351",
    "sg:province":"CA",
    "sg:tags":[
        "repair"
    ],
    "wof:name":"Perez Appliance",
    "wof:placetype":"venue"
},
  "geometry": {"coordinates":[-120.99299600000001,37.611],"type":"Point"}
}