{
  "type": "Feature",
  "properties": {
    "addr:full":"532 Badger Ln Big Bear Lake CA 92315",
    "addr:housenumber":"532",
    "addr:postcode":"92315",
    "addr:street":"Badger Ln",
    "iso:country":"US",
    "sg:address":"532 Badger Ln",
    "sg:city":"Big Bear Lake",
    "sg:classifiers":[
        {
            "category":"Home & Garden",
            "subcategory":"Home Furnishings",
            "type":"Retail Goods"
        }
    ],
    "sg:phone":"+1 909 878 4080",
    "sg:postcode":"92315",
    "sg:province":"CA",
    "sg:tags":[
        "lighting",
        "fixture"
    ],
    "wof:name":"Exciting Lighting & Home Decor",
    "wof:placetype":"venue"
},
  "geometry": {"coordinates":[-116.91422900000001,34.242765],"type":"Point"}
}