{
  "type": "Feature",
  "properties": {
    "addr:full":"255 Kingsbury Grade Rd Stateline CA 89449",
    "addr:housenumber":"255",
    "addr:postcode":"89449",
    "addr:street":"Kingsbury Grade Rd",
    "iso:country":"US",
    "sg:address":"255 Kingsbury Grade Rd",
    "sg:city":"Stateline",
    "sg:classifiers":[
        {
            "category":"Retail",
            "subcategory":"Repair Shop",
            "type":"Services"
        }
    ],
    "sg:phone":"+1 775 588 7215",
    "sg:postcode":"89449",
    "sg:province":"CA",
    "sg:tags":[
        "pipe",
        "leak",
        "locating"
    ],
    "wof:name":"American Leak Detection",
    "wof:placetype":"venue"
},
  "geometry": {"coordinates":[-119.929551,38.968288],"type":"Point"}
}