{
  "type": "Feature",
  "properties": {
    "iso:country":"US",
    "sg:address":"424 S Beverly Drive",
    "sg:city":"Beverly Hills",
    "sg:classifiers":[
        {
            "category":"Professional",
            "subcategory":"Lawyer & Legal Services",
            "type":"Services"
        }
    ],
    "sg:phone":"+1 310 557 1556",
    "sg:postcode":"90212",
    "sg:province":"CA",
    "wof:name":"Lasry Eric Atty At Law",
    "wof:placetype":"venue"
},
  "geometry": {"coordinates":[-118.397926,34.058551],"type":"Point"}
}