{
  "type": "Feature",
  "properties": {
    "addr:full":"3740 W. Sunset Blvd. 2nd Floor Los Angeles CA 90026",
    "addr:housenumber":"3740",
    "addr:postcode":"90026",
    "addr:street":"W. Sunset Blvd. 2Nd Floor",
    "iso:country":"US",
    "sg:address":"3740 W. Sunset Blvd. 2nd Floor",
    "sg:city":"Los Angeles",
    "sg:classifiers":[
        {
            "category":"Health Services",
            "subcategory":"Clinic",
            "type":"Services"
        }
    ],
    "sg:phone":"+1 323 913 0668",
    "sg:postcode":"90026",
    "sg:province":"CA",
    "sg:tags":[
        "cannabis"
    ],
    "sg:website":"www.MGC420.com",
    "wof:name":"Mr Greens Collective",
    "wof:placetype":"venue"
},
  "geometry": {"coordinates":[-118.27862,34.09084],"type":"Point"}
}