{
  "type": "Feature",
  "properties": {
    "addr:full":"9330 Jersey Blvd Rancho Cucamonga CA 91730",
    "addr:housenumber":"9330",
    "addr:postcode":"91730",
    "addr:street":"Jersey Blvd",
    "iso:country":"US",
    "sg:address":"9330 Jersey Blvd",
    "sg:city":"Rancho Cucamonga",
    "sg:classifiers":[
        {
            "category":"Retail",
            "subcategory":"Repair Shop",
            "type":"Services"
        }
    ],
    "sg:phone":"+1 909 930 5166",
    "sg:postcode":"91730",
    "sg:province":"CA",
    "sg:tags":[
        "equipment",
        "medical"
    ],
    "sg:website":"www.redmed.net",
    "wof:name":"Redmed Co Inc",
    "wof:placetype":"venue"
},
  "geometry": {"coordinates":[-117.601488,34.094708],"type":"Point"}
}