{
  "type": "Feature",
  "properties": {
    "addr:full":"1102 Jamestown Drive Sunnyvale CA 94087",
    "addr:housenumber":"1102",
    "addr:postcode":"94087",
    "addr:street":"Jamestown Drive",
    "iso:country":"US",
    "sg:address":"1102 Jamestown Drive",
    "sg:city":"Sunnyvale",
    "sg:classifiers":[
        {
            "category":"Building & Trades",
            "subcategory":"Plumbing",
            "type":"Services"
        }
    ],
    "sg:phone":"+1 408 821 8100",
    "sg:postcode":"94087",
    "sg:province":"CA",
    "wof:name":"T A Slack Plumbing Inc.",
    "wof:placetype":"venue"
},
  "geometry": {"coordinates":[-122.055949,37.364621],"type":"Point"}
}