{
  "type": "Feature",
  "properties": {
    "iso:country":"US",
    "sg:address":"18835 Beach Blvd",
    "sg:city":"Huntington Beach",
    "sg:classifiers":[
        {
            "category":"Autos & Motor Vehicles",
            "subcategory":"Automobile Sales",
            "type":"Retail Goods"
        },
        {
            "category":"Autos & Motor Vehicles",
            "subcategory":"Auto Supplies",
            "type":"Retail Goods"
        }
    ],
    "sg:phone":"+1 888 694 1460",
    "sg:postcode":"92648",
    "sg:province":"CA",
    "sg:tags":[
        "car",
        "part"
    ],
    "wof:name":"Car Pros Kia",
    "wof:placetype":"venue"
},
  "geometry": {"coordinates":[-117.989251,33.689085],"type":"Point"}
}