{
  "type": "Feature",
  "properties": {
    "addr:full":"7182 Healdsburg Ave Sebastopol CA 95472",
    "addr:postcode":"7182;95472",
    "addr:street":"Healdsburg Ave",
    "iso:country":"US",
    "sg:address":"7182 Healdsburg Ave",
    "sg:city":"Sebastopol",
    "sg:classifiers":[
        {
            "category":"Professional",
            "subcategory":"Lawyer & Legal Services",
            "type":"Services"
        }
    ],
    "sg:phone":"+1 707 823 8593",
    "sg:postcode":"95472",
    "sg:province":"CA",
    "sg:tags":[
        "attorney"
    ],
    "wof:name":"Tate Birnie",
    "wof:placetype":"venue"
},
  "geometry": {"coordinates":[-122.82659099999999,38.405311],"type":"Point"}
}