{
  "type": "Feature",
  "properties": {
    "addr:full":"23241 Ventura Blvd Woodland Hills CA 91364",
    "addr:housenumber":"23241",
    "addr:postcode":"91364",
    "addr:street":"Ventura Blvd",
    "iso:country":"US",
    "sg:address":"23241 Ventura Blvd",
    "sg:city":"Woodland Hills",
    "sg:classifiers":[
        {
            "category":"Shopping",
            "subcategory":"Clothing, Apparel, & Fashions",
            "type":"Retail Goods"
        }
    ],
    "sg:phone":"+1 818 876 9188",
    "sg:postcode":"91364",
    "sg:province":"CA",
    "sg:tags":[
        "clothing",
        "women's"
    ],
    "wof:name":"Hirsch Michele",
    "wof:placetype":"venue"
},
  "geometry": {"coordinates":[-118.63205600000001,34.162099],"type":"Point"}
}