{
  "type": "Feature",
  "properties": {
    "iso:country":"US",
    "sg:address":"425 N Main St",
    "sg:city":"Manteca",
    "sg:classifiers":[
        {
            "category":"Restaurant",
            "type":"Food & Drink"
        }
    ],
    "sg:phone":"+1 209 824 7766",
    "sg:postcode":"95336",
    "sg:province":"CA",
    "wof:name":"El Patio Restaurant",
    "wof:placetype":"venue"
},
  "geometry": {"coordinates":[-121.21685600000001,37.803781],"type":"Point"}
}