{
  "type": "Feature",
  "properties": {
    "addr:full":"16829 S Western Ave Gardena CA 90247",
    "addr:housenumber":"16829",
    "addr:postcode":"90247",
    "addr:street":"S Western Ave",
    "iso:country":"US",
    "sg:address":"16829 S Western Ave",
    "sg:city":"Gardena",
    "sg:classifiers":[
        {
            "category":"Manufacturing",
            "subcategory":"Printing",
            "type":"Manufacturing & Wholesale Goods"
        }
    ],
    "sg:phone":"+1 310 719 7377",
    "sg:postcode":"90247",
    "sg:province":"CA",
    "sg:tags":[
        "printer"
    ],
    "wof:name":"Minuteman Press",
    "wof:placetype":"venue"
},
  "geometry": {"coordinates":[-118.309207,33.878555],"type":"Point"}
}