{
  "type": "Feature",
  "properties": {
    "iso:country":"US",
    "sg:address":"806 Sylvandale Ave",
    "sg:city":"San Jose",
    "sg:classifiers":[
        {
            "category":"Professional",
            "subcategory":"Accounting & Tax Preparation",
            "type":"Services"
        }
    ],
    "sg:phone":"+1 408 365 1040",
    "sg:postcode":"95111",
    "sg:province":"CA",
    "sg:tags":[
        "return",
        "filing"
    ],
    "wof:name":"S & S Tax Svc",
    "wof:placetype":"venue"
},
  "geometry": {"coordinates":[-121.81864,37.287974],"type":"Point"}
}