{
  "type": "Feature",
  "properties": {
    "addr:full":"17 Laird Dr Moraga CA 94556",
    "addr:housenumber":"17",
    "addr:postcode":"94556",
    "addr:street":"Laird Dr",
    "iso:country":"US",
    "sg:address":"17 Laird Dr",
    "sg:city":"Moraga",
    "sg:classifiers":[
        {
            "category":"Building & Trades",
            "subcategory":"Construction",
            "type":"Services"
        }
    ],
    "sg:phone":"+1 925 376 0676",
    "sg:postcode":"94556",
    "sg:province":"CA",
    "sg:tags":[
        "floor",
        "laying",
        "contractor"
    ],
    "wof:name":"Berkley Floor Company",
    "wof:placetype":"venue"
},
  "geometry": {"coordinates":[-122.130621,37.856034],"type":"Point"}
}