{
  "type": "Feature",
  "properties": {
    "iso:country":"US",
    "sg:address":"10428 Foothill Blvd",
    "sg:city":"Rancho Cucamonga",
    "sg:classifiers":[
        {
            "category":"Wholesale",
            "subcategory":"Construction Materials",
            "type":"Manufacturing & Wholesale Goods"
        }
    ],
    "sg:phone":"+1 909 466 5271",
    "sg:postcode":"91730",
    "sg:province":"CA",
    "sg:tags":[
        "concrete",
        "product"
    ],
    "wof:name":"Boral Material",
    "wof:placetype":"venue"
},
  "geometry": {"coordinates":[-117.577278,34.106617],"type":"Point"}
}