{
  "type": "Feature",
  "properties": {
    "iso:country":"US",
    "sg:address":"1532 San Pablo Ave",
    "sg:city":"Oakland",
    "sg:classifiers":[
        {
            "category":"Restaurant",
            "type":"Food & Drink"
        }
    ],
    "sg:phone":"+1 510 834 4800",
    "sg:postcode":"94601",
    "sg:province":"CA",
    "wof:name":"Juice Joint Eatery",
    "wof:placetype":"venue"
},
  "geometry": {"coordinates":[-122.294185,37.875211],"type":"Point"}
}