{
  "type": "Feature",
  "properties": {
    "addr:full":"26752 Alicante Dr Mission Viejo CA 92691",
    "addr:postcode":"26752;92691",
    "addr:street":"Alicante Dr",
    "iso:country":"US",
    "sg:address":"26752 Alicante Dr",
    "sg:city":"Mission Viejo",
    "sg:classifiers":[
        {
            "category":"Social Services",
            "subcategory":"Adult Care",
            "type":"Services"
        }
    ],
    "sg:phone":"+1 949 587 1077",
    "sg:postcode":"92691",
    "sg:province":"CA",
    "sg:tags":[
        "residential",
        "facility"
    ],
    "wof:name":"Exsertus Assist",
    "wof:placetype":"venue"
},
  "geometry": {"coordinates":[-117.662192,33.604691],"type":"Point"}
}