{
  "type": "Feature",
  "properties": {
    "iso:country":"US",
    "sg:address":"1874 Verne Roberts Cir",
    "sg:city":"Antioch",
    "sg:classifiers":[
        {
            "category":"Building & Trades",
            "subcategory":"Construction",
            "type":"Services"
        }
    ],
    "sg:phone":"+1 925 755 9913",
    "sg:postcode":"94509",
    "sg:province":"CA",
    "sg:tags":[
        "masonry",
        "contractor"
    ],
    "wof:name":"John Jackson Masonry",
    "wof:placetype":"venue"
},
  "geometry": {"coordinates":[-121.838412,38.009987],"type":"Point"}
}