{
  "type": "Feature",
  "properties": {
    "addr:full":"634 S Normandie Ave Los Angeles CA 90005",
    "addr:housenumber":"634",
    "addr:postcode":"90005",
    "addr:street":"S Normandie Ave",
    "iso:country":"US",
    "sg:address":"634 S Normandie Ave",
    "sg:city":"Los Angeles",
    "sg:classifiers":[
        {
            "category":"Organizations",
            "subcategory":"Religious Organization",
            "type":"Services"
        }
    ],
    "sg:phone":"+1 213 384 4272",
    "sg:postcode":"90005",
    "sg:province":"CA",
    "sg:tags":[
        "church"
    ],
    "wof:name":"Korean Wilshire Christian Chr",
    "wof:placetype":"venue"
},
  "geometry": {"coordinates":[-118.300359,34.061743],"type":"Point"}
}