{
  "type": "Feature",
  "properties": {
    "iso:country":"US",
    "sg:address":"7597 Westminster Blvd",
    "sg:city":"Westminster",
    "sg:classifiers":[
        {
            "category":"Personal",
            "type":"Services"
        }
    ],
    "sg:phone":"+1 714 894 2200",
    "sg:postcode":"92683",
    "sg:province":"CA",
    "sg:tags":[
        "sewing",
        "alteration"
    ],
    "wof:name":"La Rose Alterations",
    "wof:placetype":"venue"
},
  "geometry": {"coordinates":[-117.99655799999999,33.759267],"type":"Point"}
}