{
  "type": "Feature",
  "properties": {
    "addr:full":"21926 S Vermont Ave Torrance CA 90502",
    "addr:housenumber":"21926",
    "addr:postcode":"90502",
    "addr:street":"S Vermont Ave",
    "iso:country":"US",
    "sg:address":"21926 S Vermont Ave",
    "sg:city":"Torrance",
    "sg:classifiers":[
        {
            "category":"Real Estate",
            "subcategory":"Real Estate Operator",
            "type":"Services"
        }
    ],
    "sg:phone":"+1 310 618 1740",
    "sg:postcode":"90502",
    "sg:province":"CA",
    "sg:tags":[
        "mobile",
        "home",
        "site"
    ],
    "wof:name":"Starlite Trailer Park",
    "wof:placetype":"venue"
},
  "geometry": {"coordinates":[-118.290198,33.828369],"type":"Point"}
}