{
  "type": "Feature",
  "properties": {
    "addr:full":"2408 S Broadway Los Angeles CA 90007",
    "addr:housenumber":"2408",
    "addr:postcode":"90007",
    "addr:street":"S Broadway",
    "iso:country":"US",
    "sg:address":"2408 S Broadway",
    "sg:city":"Los Angeles",
    "sg:classifiers":[
        {
            "category":"Sports & Exercise",
            "subcategory":"Bicycle Rental",
            "type":"Entertainment"
        },
        {
            "category":"Sports & Exercise",
            "subcategory":"Gym",
            "type":"Entertainment"
        }
    ],
    "sg:phone":"+1 213 747 2591",
    "sg:postcode":"90007",
    "sg:province":"CA",
    "sg:tags":[
        "yoga",
        "wear"
    ],
    "sg:website":"www.kosusa.com",
    "wof:name":"KOSUSA",
    "wof:placetype":"venue"
},
  "geometry": {"coordinates":[-118.268869,34.026948],"type":"Point"}
}