{
  "type": "Feature",
  "properties": {
    "addr:full":"21800 Belshire Ave Hawaiian Gardens CA 90716",
    "addr:housenumber":"21800",
    "addr:postcode":"90716",
    "addr:street":"Belshire Ave",
    "iso:country":"US",
    "sg:address":"21800 Belshire Ave",
    "sg:city":"Hawaiian Gardens",
    "sg:classifiers":[
        {
            "category":"Retail",
            "subcategory":"Auto Repair",
            "type":"Services"
        }
    ],
    "sg:phone":"+1 562 938 8836",
    "sg:postcode":"90716",
    "sg:province":"CA",
    "sg:tags":[
        "body",
        "shop"
    ],
    "sg:website":"cypressautobody.com",
    "wof:name":"Cypress Auto Body & Paint Inc",
    "wof:placetype":"venue"
},
  "geometry": {"coordinates":[-118.06999999999999,33.8302],"type":"Point"}
}