{
  "type": "Feature",
  "properties": {
    "iso:country":"US",
    "sg:address":"5831 Overhill Drive",
    "sg:city":"Los Angeles",
    "sg:classifiers":[
        {
            "category":"Health Services",
            "subcategory":"Dentist",
            "type":"Services"
        }
    ],
    "sg:phone":"+1 323 296 6180",
    "sg:postcode":"90043",
    "sg:province":"CA",
    "sg:website":"www.overhilldental.com",
    "wof:name":"Overhill Dental",
    "wof:placetype":"venue"
},
  "geometry": {"coordinates":[-118.354148,33.987821],"type":"Point"}
}