{
  "type": "Feature",
  "properties": {
    "addr:full":"904 S Gaffey St San Pedro CA 90731",
    "addr:housenumber":"904",
    "addr:postcode":"90731",
    "addr:street":"S Gaffey St",
    "iso:country":"US",
    "sg:address":"904 S Gaffey St",
    "sg:city":"San Pedro",
    "sg:classifiers":[
        {
            "category":"Banks & Credit Unions",
            "subcategory":"Bank",
            "type":"Services"
        }
    ],
    "sg:phone":"+1 310 547 2050",
    "sg:postcode":"90731",
    "sg:province":"CA",
    "sg:tags":[
        "cashing",
        "check"
    ],
    "wof:name":"Speedy Cash Inc",
    "wof:placetype":"venue"
},
  "geometry": {"coordinates":[-118.29226199999999,33.736499],"type":"Point"}
}