{
  "type": "Feature",
  "properties": {
    "addr:full":"1010 S Victory Blvd Burbank CA 91502",
    "addr:housenumber":"1010",
    "addr:postcode":"91502",
    "addr:street":"S Victory Blvd",
    "iso:country":"US",
    "sg:address":"1010 S Victory Blvd",
    "sg:city":"Burbank",
    "sg:classifiers":[
        {
            "category":"Retail",
            "subcategory":"Auto Repair",
            "type":"Services"
        }
    ],
    "sg:phone":"+1 818 841 1881",
    "sg:postcode":"91502",
    "sg:province":"CA",
    "sg:tags":[
        "repairing",
        "automobile"
    ],
    "wof:name":"EXECUTIVE Towing",
    "wof:placetype":"venue"
},
  "geometry": {"coordinates":[-118.30700400000001,34.166204],"type":"Point"}
}