{
  "type": "Feature",
  "properties": {
    "addr:full":"1503 Adelia Ave South El Monte CA 91733",
    "addr:housenumber":"1503",
    "addr:postcode":"91733",
    "addr:street":"Adelia Ave",
    "iso:country":"US",
    "sg:address":"1503 Adelia Ave",
    "sg:city":"South El Monte",
    "sg:classifiers":[
        {
            "category":"Manufacturing",
            "subcategory":"Retail Goods",
            "type":"Manufacturing & Wholesale Goods"
        }
    ],
    "sg:phone":"+1 626 579 5308",
    "sg:postcode":"91733",
    "sg:province":"CA",
    "sg:tags":[
        "manufacturer"
    ],
    "wof:name":"Plus Mfg Co",
    "wof:placetype":"venue"
},
  "geometry": {"coordinates":[-118.057896,34.048172],"type":"Point"}
}