{
  "type": "Feature",
  "properties": {
    "addr:full":"501 Cesar Chavez St San Francisco CA 94124",
    "addr:housenumber":"501",
    "addr:postcode":"94124",
    "addr:street":"Cesar Chavez St",
    "iso:country":"US",
    "sg:address":"501 Cesar Chavez St",
    "sg:city":"San Francisco",
    "sg:classifiers":[
        {
            "category":"Freight",
            "type":"Transportation"
        }
    ],
    "sg:phone":"+1 415 970 8812",
    "sg:postcode":"94124",
    "sg:province":"CA",
    "sg:tags":[
        "forwarding"
    ],
    "wof:name":"SF Enterprises",
    "wof:placetype":"venue"
},
  "geometry": {"coordinates":[-122.38432400000001,37.750407],"type":"Point"}
}