{
  "type": "Feature",
  "properties": {
    "iso:country":"US",
    "sg:address":"35640 Fremont Blvd",
    "sg:city":"Fremont",
    "sg:classifiers":[
        {
            "category":"Professional",
            "subcategory":"Business Services",
            "type":"Services"
        }
    ],
    "sg:phone":"+1 510 797 5997",
    "sg:postcode":"94536",
    "sg:province":"CA",
    "sg:tags":[
        "packaging"
    ],
    "wof:name":"Postnet",
    "wof:placetype":"venue"
},
  "geometry": {"coordinates":[-122.025445,37.567431],"type":"Point"}
}