{
  "type": "Feature",
  "properties": {
    "addr:full":"2860 Jefferson Blvd West Sacramento CA 95691",
    "addr:housenumber":"2860",
    "addr:postcode":"95691",
    "addr:street":"Jefferson Blvd",
    "iso:country":"US",
    "sg:address":"2860 Jefferson Blvd",
    "sg:city":"West Sacramento",
    "sg:classifiers":[
        {
            "category":"Organizations",
            "subcategory":"Religious Organization",
            "type":"Services"
        }
    ],
    "sg:phone":"+1 916 372 6570",
    "sg:postcode":"95691",
    "sg:province":"CA",
    "sg:tags":[
        "church"
    ],
    "wof:name":"West Sacromento SDA Church",
    "wof:placetype":"venue"
},
  "geometry": {"coordinates":[-121.544735,38.54506],"type":"Point"}
}