{
  "type": "Feature",
  "properties": {
    "addr:full":"3545 Del Mar Heights Rd San Diego CA 92130",
    "addr:housenumber":"3545",
    "addr:postcode":"92130",
    "addr:street":"Del Mar Heights Rd",
    "iso:country":"US",
    "sg:address":"3545 Del Mar Heights Rd",
    "sg:city":"San Diego",
    "sg:classifiers":[
        {
            "category":"Shopping",
            "subcategory":"Mobile Phones",
            "type":"Retail Goods"
        }
    ],
    "sg:phone":"+1 858 793 6708",
    "sg:postcode":"92130",
    "sg:province":"CA",
    "wof:name":"Radioshack",
    "wof:placetype":"venue"
},
  "geometry": {"coordinates":[-117.231003,32.955002],"type":"Point"}
}