{
  "type": "Feature",
  "properties": {
    "iso:country":"US",
    "sg:address":"36399 Cathedral Canyon Dr",
    "sg:city":"Cathedral City",
    "sg:classifiers":[
        {
            "category":"Wholesale",
            "subcategory":"Apparel",
            "type":"Manufacturing & Wholesale Goods"
        }
    ],
    "sg:phone":"+1 760 324 5045",
    "sg:postcode":"92234",
    "sg:province":"CA",
    "sg:tags":[
        "piece"
    ],
    "wof:name":"Drapery 1",
    "wof:placetype":"venue"
},
  "geometry": {"coordinates":[-116.466905,33.783884],"type":"Point"}
}