{
  "type": "Feature",
  "properties": {
    "iso:country":"US",
    "sg:address":"44933 Yucca Ave",
    "sg:city":"Lancaster",
    "sg:classifiers":[
        {
            "category":"Shopping",
            "subcategory":"Discount & Variety Stores",
            "type":"Retail Goods"
        }
    ],
    "sg:phone":"+1 661 945 0907",
    "sg:postcode":"93534",
    "sg:province":"CA",
    "sg:tags":[
        "merchandise",
        "general"
    ],
    "wof:name":"Desert Industrial Supply",
    "wof:placetype":"venue"
},
  "geometry": {"coordinates":[-118.135227,34.699157],"type":"Point"}
}