{
  "type": "Feature",
  "properties": {
    "iso:country":"US",
    "sg:address":"1416 9th St",
    "sg:city":"Sacramento",
    "sg:classifiers":[
        {
            "category":"Professional",
            "subcategory":"Management & Consulting",
            "type":"Services"
        }
    ],
    "sg:phone":"+1 916 653 8120",
    "sg:postcode":"95814",
    "sg:province":"CA",
    "sg:tags":[
        "testing"
    ],
    "wof:name":"Department Fish Game Tstg Off",
    "wof:placetype":"venue"
},
  "geometry": {"coordinates":[-121.496968,38.575899],"type":"Point"}
}