{
  "type": "Feature",
  "properties": {
    "iso:country":"US",
    "sg:address":"87 N San Pedro St",
    "sg:city":"San Jose",
    "sg:classifiers":[
        {
            "category":"Food & Beverages",
            "subcategory":"Farmers Market",
            "type":"Retail Goods"
        }
    ],
    "sg:phone":"+1 408 813 5984",
    "sg:postcode":"95110",
    "sg:province":"CA",
    "wof:name":"San Pedro Square Market",
    "wof:placetype":"venue"
},
  "geometry": {"coordinates":[-121.89432100000001,37.336514],"type":"Point"}
}