{
  "type": "Feature",
  "properties": {
    "iso:country":"US",
    "sg:address":"13650 Marina Pointe Dr Unit 304",
    "sg:city":"Marina Del Rey",
    "sg:classifiers":[
        {
            "category":"Organizations",
            "subcategory":"Non-profit Organization",
            "type":"Services"
        }
    ],
    "sg:phone":"+1 310 306 6181",
    "sg:postcode":"90292",
    "sg:province":"CA",
    "sg:tags":[
        "service/non-profit",
        "community"
    ],
    "wof:name":"Cove Community Association",
    "wof:placetype":"venue"
},
  "geometry": {"coordinates":[-118.44408199999999,33.985003],"type":"Point"}
}