{
  "type": "Feature",
  "properties": {
    "iso:country":"US",
    "sg:address":"2615 Camino Del Rio S",
    "sg:city":"San Diego",
    "sg:classifiers":[
        {
            "category":"Education",
            "subcategory":"Special Training",
            "type":"Public Place"
        }
    ],
    "sg:phone":"+1 619 297 9448",
    "sg:postcode":"92108",
    "sg:province":"CA",
    "sg:tags":[
        "tutoring"
    ],
    "wof:name":"Atlantis Center For Educational Enrichment",
    "wof:placetype":"venue"
},
  "geometry": {"coordinates":[-117.13800000000001,32.769299],"type":"Point"}
}