{
  "type": "Feature",
  "properties": {
    "addr:full":"5449 Monte Vista Rd Anderson CA 96007",
    "addr:housenumber":"5449",
    "addr:postcode":"96007",
    "addr:street":"Monte Vista Rd",
    "iso:country":"US",
    "sg:address":"5449 Monte Vista Rd",
    "sg:city":"Anderson",
    "sg:classifiers":[
        {
            "category":"Professional",
            "type":"Services"
        }
    ],
    "sg:phone":"+1 530 357 3215",
    "sg:postcode":"96007",
    "sg:province":"CA",
    "wof:name":"John Churchwell Jr",
    "wof:placetype":"venue"
},
  "geometry": {"coordinates":[-122.426405,40.446273],"type":"Point"}
}