{
  "type": "Feature",
  "properties": {
    "addr:full":"2911 E Huntington Blvd Fresno CA 93721",
    "addr:housenumber":"2911",
    "addr:postcode":"93721",
    "addr:street":"E Huntington Blvd",
    "iso:country":"US",
    "sg:address":"2911 E Huntington Blvd",
    "sg:city":"Fresno",
    "sg:classifiers":[
        {
            "category":"Real Estate",
            "subcategory":"Real Estate Operator",
            "type":"Services"
        }
    ],
    "sg:phone":"+1 559 485 6485",
    "sg:postcode":"93721",
    "sg:province":"CA",
    "sg:tags":[
        "apartment"
    ],
    "wof:name":"Rafael Apartments",
    "wof:placetype":"venue"
},
  "geometry": {"coordinates":[-119.77588900000001,36.739523],"type":"Point"}
}