{
  "type": "Feature",
  "properties": {
    "iso:country":"US",
    "sg:address":"7978 Hollywood Blvd",
    "sg:city":"West Hollywood",
    "sg:classifiers":[
        {
            "category":"Personal",
            "subcategory":"Beauty Salon",
            "type":"Services"
        }
    ],
    "sg:phone":"+1 323 848 8088",
    "sg:postcode":"90046",
    "sg:province":"CA",
    "wof:name":"Aveda Concept Beauty Salon",
    "wof:placetype":"venue"
},
  "geometry": {"coordinates":[-118.362488,34.101227],"type":"Point"}
}