{
  "type": "Feature",
  "properties": {
    "addr:full":"902 Carmel Avenue Albany CA 94706",
    "addr:housenumber":"902",
    "addr:postcode":"94706",
    "addr:street":"Carmel Avenue",
    "iso:country":"US",
    "sg:address":"902 Carmel Avenue",
    "sg:city":"Albany",
    "sg:classifiers":[
        {
            "category":"Health Services",
            "subcategory":"Clinic",
            "type":"Services"
        }
    ],
    "sg:phone":"+1 510 527 4064",
    "sg:postcode":"94706",
    "sg:province":"CA",
    "sg:tags":[
        "counseling",
        "mental"
    ],
    "wof:name":"Wise Joanna Lcsw",
    "wof:placetype":"venue"
},
  "geometry": {"coordinates":[-122.290001,37.890499],"type":"Point"}
}