{
  "type": "Feature",
  "properties": {
    "iso:country":"US",
    "sg:address":"6611 Preston Ave Ste C",
    "sg:city":"Livermore",
    "sg:classifiers":[
        {
            "category":"Manufacturing",
            "subcategory":"Paper Products",
            "type":"Manufacturing & Wholesale Goods"
        }
    ],
    "sg:phone":"+1 925 373 1135",
    "sg:postcode":"94551",
    "sg:province":"CA",
    "sg:tags":[
        "molding"
    ],
    "sg:website":"http://www.cardinalshower.com",
    "wof:name":"Cardinal Shower Enclosures",
    "wof:placetype":"venue"
},
  "geometry": {"coordinates":[-121.716865,37.708641],"type":"Point"}
}