{
  "type": "Feature",
  "properties": {
    "iso:country":"US",
    "sg:address":"4528 E Washington Blvd",
    "sg:city":"City Of Commerce",
    "sg:classifiers":[
        {
            "category":"Wholesale",
            "subcategory":"Farm Supplies",
            "type":"Manufacturing & Wholesale Goods"
        }
    ],
    "sg:phone":"+1 323 260 7457",
    "sg:postcode":"90040",
    "sg:province":"CA",
    "sg:tags":[
        "grain"
    ],
    "wof:name":"Granpa Po's Nutra Nuts Inc",
    "wof:placetype":"venue"
},
  "geometry": {"coordinates":[-118.176134,34.005763],"type":"Point"}
}