{
  "type": "Feature",
  "properties": {
    "iso:country":"US",
    "sg:address":"122 Calistoga Rd",
    "sg:city":"Santa Rosa",
    "sg:classifiers":[
        {
            "category":"Communications",
            "subcategory":"Film & Video Production",
            "type":"Services"
        }
    ],
    "sg:phone":"+1 707 833 2727",
    "sg:postcode":"95409",
    "sg:province":"CA",
    "sg:tags":[
        "taping"
    ],
    "sg:website":"www.cogentcomm.biz",
    "wof:name":"Cogent Communications",
    "wof:placetype":"venue"
},
  "geometry": {"coordinates":[-122.653389,38.4658],"type":"Point"}
}