{
  "type": "Feature",
  "properties": {
    "iso:country":"US",
    "sg:address":"151 N Main St",
    "sg:city":"Manteca",
    "sg:classifiers":[
        {
            "category":"Home & Garden",
            "subcategory":"Building Materials",
            "type":"Retail Goods"
        }
    ],
    "sg:phone":"+1 209 823 7678",
    "sg:postcode":"95336",
    "sg:province":"CA",
    "sg:tags":[
        "glass",
        "window",
        "plate"
    ],
    "sg:website":"www.donsmobileglass.com",
    "wof:name":"Don's Mobile Glass",
    "wof:placetype":"venue"
},
  "geometry": {"coordinates":[-121.216597,37.798718],"type":"Point"}
}