{
  "type": "Feature",
  "properties": {
    "iso:country":"US",
    "sg:address":"1755 Euclid Ave",
    "sg:city":"San Diego",
    "sg:classifiers":[
        {
            "category":"Shopping",
            "type":"Retail Goods"
        }
    ],
    "sg:phone":"+1 619 264 8244",
    "sg:postcode":"92105",
    "sg:province":"CA",
    "sg:tags":[
        "pet",
        "food",
        "supply"
    ],
    "wof:name":"Mike's Aquarium & Pet Ctr",
    "wof:placetype":"venue"
},
  "geometry": {"coordinates":[-117.084856,32.724017],"type":"Point"}
}