{
  "type": "Feature",
  "properties": {
    "iso:country":"US",
    "sg:address":"516 W Shaw Ave",
    "sg:city":"Fresno",
    "sg:classifiers":[
        {
            "category":"Utilities",
            "subcategory":"Water",
            "type":"Services"
        }
    ],
    "sg:phone":"+1 559 221 2505",
    "sg:postcode":"93711",
    "sg:province":"CA",
    "sg:tags":[
        "management",
        "district",
        "fa",
        "treatment",
        "waste",
        "sewage"
    ],
    "wof:name":"Eco Resources Inc",
    "wof:placetype":"venue"
},
  "geometry": {"coordinates":[-119.801357,36.8085],"type":"Point"}
}