{
  "type": "Feature",
  "properties": {
    "iso:country":"US",
    "sg:address":"24452 Health Center Dr",
    "sg:city":"Laguna Hills",
    "sg:classifiers":[
        {
            "category":"Health Services",
            "subcategory":"Nursing And Care Facility",
            "type":"Services"
        }
    ],
    "sg:phone":"+1 949 837 8000",
    "sg:postcode":"92653",
    "sg:province":"CA",
    "sg:tags":[
        "home",
        "convalescent"
    ],
    "wof:name":"Country Villa Laguna Hills Ctr",
    "wof:placetype":"venue"
},
  "geometry": {"coordinates":[-117.708002,33.608062],"type":"Point"}
}