{
  "type": "Feature",
  "properties": {
    "addr:full":"7175 Rosecliff Ct Pleasanton CA 94566",
    "addr:housenumber":"7175",
    "addr:postcode":"94566",
    "addr:street":"Rosecliff Ct",
    "iso:country":"US",
    "sg:address":"7175 Rosecliff Ct",
    "sg:city":"Pleasanton",
    "sg:classifiers":[
        {
            "category":"Manufacturing",
            "subcategory":"Pet Food",
            "type":"Manufacturing & Wholesale Goods"
        },
        {
            "category":"Shopping",
            "subcategory":"Pets & Pet Supplies",
            "type":"Retail Goods"
        }
    ],
    "sg:phone":"+1 925 846 0984",
    "sg:postcode":"94566",
    "sg:province":"CA",
    "sg:tags":[
        "manufacturer",
        "store",
        "foods-wholesale"
    ],
    "wof:name":"Low Cost Pet Supply Co",
    "wof:placetype":"venue"
},
  "geometry": {"coordinates":[-121.899006,37.650933],"type":"Point"}
}