{
  "type": "Feature",
  "properties": {
    "iso:country":"US",
    "sg:address":"273 E Evan Hewes Hwy",
    "sg:city":"El Centro",
    "sg:classifiers":[
        {
            "category":"Organizations",
            "subcategory":"Non-profit Organization",
            "type":"Services"
        }
    ],
    "sg:phone":"+1 760 352 0807",
    "sg:postcode":"92243",
    "sg:province":"CA",
    "sg:tags":[
        "information",
        "alcoholism",
        "treatment"
    ],
    "wof:name":"Alcoholics Anonymous",
    "wof:placetype":"venue"
},
  "geometry": {"coordinates":[-115.515254,32.795972],"type":"Point"}
}