{
  "type": "Feature",
  "properties": {
    "iso:country":"US",
    "sg:address":"3729 Cahuenga Blvd W",
    "sg:city":"North Hollywood",
    "sg:classifiers":[
        {
            "category":"Communications",
            "subcategory":"Radio Station",
            "type":"Services"
        }
    ],
    "sg:phone":"+1 818 985 2711",
    "sg:postcode":"91604",
    "sg:province":"CA",
    "sg:website":"www.kpfk.org",
    "wof:name":"KPFK 90.7 FM",
    "wof:placetype":"venue"
},
  "geometry": {"coordinates":[-118.361754,34.135508],"type":"Point"}
}