{
  "type": "Feature",
  "properties": {
    "iso:country":"US",
    "sg:address":"170 Broadmoor Dr",
    "sg:city":"San Francisco",
    "sg:classifiers":[
        {
            "category":"Manufacturing",
            "subcategory":"Apparel",
            "type":"Manufacturing & Wholesale Goods"
        }
    ],
    "sg:phone":"+1 415 334 1781",
    "sg:postcode":"94132",
    "sg:province":"CA",
    "sg:tags":[
        "woven",
        "hand"
    ],
    "wof:name":"Carli Ssan Handwoven Originals",
    "wof:placetype":"venue"
},
  "geometry": {"coordinates":[-122.47338499999999,37.726439],"type":"Point"}
}