{
  "type": "Feature",
  "properties": {
    "iso:country":"US",
    "sg:address":"1447 Taraval St",
    "sg:city":"San Francisco",
    "sg:classifiers":[
        {
            "category":"Manufacturing",
            "subcategory":"Food",
            "type":"Manufacturing & Wholesale Goods"
        }
    ],
    "sg:phone":"+1 415 731 2833",
    "sg:postcode":"94116",
    "sg:province":"CA",
    "sg:tags":[
        "frozen",
        "dessert",
        "yogurt",
        "ice",
        "cream"
    ],
    "wof:name":"Marco Polo Italian Ice Cream",
    "wof:placetype":"venue"
},
  "geometry": {"coordinates":[-122.48183,37.742677],"type":"Point"}
}