{
  "type": "Feature",
  "properties": {
    "iso:country":"US",
    "sg:address":"14002 Palawan Way",
    "sg:city":"Marina Del Rey",
    "sg:classifiers":[
        {
            "category":"Real Estate",
            "subcategory":"Architect",
            "type":"Services"
        }
    ],
    "sg:phone":"+1 310 822 1718",
    "sg:postcode":"90292",
    "sg:province":"CA",
    "sg:tags":[
        "engineering",
        "construction",
        "architectural"
    ],
    "wof:name":"Schwartz Romano & Assoc Inc",
    "wof:placetype":"venue"
},
  "geometry": {"coordinates":[-118.457441,33.983334],"type":"Point"}
}