{
  "type": "Feature",
  "properties": {
    "iso:country":"US",
    "sg:address":"1403 Shotwell St",
    "sg:city":"San Francisco",
    "sg:classifiers":[
        {
            "category":"Professional",
            "subcategory":"Art Services",
            "type":"Services"
        }
    ],
    "sg:phone":"+1 415 550 6369",
    "sg:postcode":"94110",
    "sg:province":"CA",
    "sg:tags":[
        "photographer"
    ],
    "wof:name":"Cesar Rubio Photography",
    "wof:placetype":"venue"
},
  "geometry": {"coordinates":[-122.414945,37.746083],"type":"Point"}
}