{
  "type": "Feature",
  "properties": {
    "iso:country":"US",
    "sg:address":"1908 S Mariposa Ave",
    "sg:city":"Los Angeles",
    "sg:classifiers":[
        {
            "category":"Manufacturing",
            "subcategory":"Signs",
            "type":"Manufacturing & Wholesale Goods"
        }
    ],
    "sg:phone":"+1 323 735 7775",
    "sg:postcode":"90007",
    "sg:province":"CA",
    "wof:name":"Triple Seven Signs",
    "wof:placetype":"venue"
},
  "geometry": {"coordinates":[-118.298278,34.039319],"type":"Point"}
}