{
  "type": "Feature",
  "properties": {
    "addr:full":"16655 Hill Dr Madera CA 93638",
    "addr:housenumber":"16655",
    "addr:postcode":"93638",
    "addr:street":"Hill Dr",
    "iso:country":"US",
    "sg:address":"16655 Hill Dr",
    "sg:city":"Madera",
    "sg:classifiers":[
        {
            "category":"Professional",
            "subcategory":"Accounting & Tax Preparation",
            "type":"Services"
        }
    ],
    "sg:phone":"+1 559 674 8513",
    "sg:postcode":"93638",
    "sg:province":"CA",
    "sg:tags":[
        "bookkeeping",
        "general"
    ],
    "wof:name":"P S Business Svc",
    "wof:placetype":"venue"
},
  "geometry": {"coordinates":[-120.075355,36.99151],"type":"Point"}
}