{
  "type": "Feature",
  "properties": {
    "addr:full":"1036 Haight Street San Francisco CA 94117",
    "addr:housenumber":"1036",
    "addr:postcode":"94117",
    "addr:street":"Haight Street",
    "iso:country":"US",
    "sg:address":"1036 Haight Street",
    "sg:city":"San Francisco",
    "sg:classifiers":[
        {
            "category":"Restaurant",
            "type":"Food & Drink"
        }
    ],
    "sg:phone":"+1 415 824 2666",
    "sg:postcode":"94117",
    "sg:province":"CA",
    "sg:tags":[
        "flavor",
        "local"
    ],
    "sg:website":"victorianalliance.org/",
    "wof:name":"Victorian Alliance",
    "wof:placetype":"venue"
},
  "geometry": {"coordinates":[-122.439494,37.771245],"type":"Point"}
}