{
  "type": "Feature",
  "properties": {
    "addr:full":"1027 San Felipe Rd Hollister CA 95023",
    "addr:housenumber":"1027",
    "addr:postcode":"hollister ca 95023",
    "addr:street":"San Felipe Rd",
    "iso:country":"US",
    "sg:address":"1027 San Felipe Rd",
    "sg:city":"Hollister",
    "sg:classifiers":[
        {
            "category":"Wholesale",
            "subcategory":"Hardware",
            "type":"Manufacturing & Wholesale Goods"
        }
    ],
    "sg:phone":"+1 831 635 0368",
    "sg:postcode":"95023",
    "sg:province":"CA",
    "sg:tags":[
        "refrigerating"
    ],
    "wof:name":"Martin & Tom's Refrig & Eqpt",
    "wof:placetype":"venue"
},
  "geometry": {"coordinates":[-121.40081000000001,36.873045],"type":"Point"}
}