{
  "type": "Feature",
  "properties": {
    "iso:country":"US",
    "sg:address":"2667 Yerba St",
    "sg:city":"Selma",
    "sg:classifiers":[
        {
            "category":"Professional",
            "type":"Services"
        }
    ],
    "sg:phone":"+1 559 891 9076",
    "sg:postcode":"93662",
    "sg:province":"CA",
    "wof:name":"Liborio D Palacios",
    "wof:placetype":"venue"
},
  "geometry": {"coordinates":[-119.623093,36.558379],"type":"Point"}
}