{
  "type": "Feature",
  "properties": {
    "iso:country":"US",
    "sg:address":"330 E Queen St",
    "sg:city":"Inglewood",
    "sg:classifiers":[
        {
            "category":"Organizations",
            "subcategory":"Professional Association",
            "type":"Services"
        }
    ],
    "sg:phone":"+1 310 677 1121",
    "sg:postcode":"90301",
    "sg:province":"CA",
    "sg:tags":[
        "chambers",
        "commerce"
    ],
    "wof:name":"Inglewood Chamber Of Commerce",
    "wof:placetype":"venue"
},
  "geometry": {"coordinates":[-118.35154799999999,33.962897],"type":"Point"}
}