{
  "type": "Feature",
  "properties": {
    "addr:full":"1517 20th St Santa Monica CA 90404",
    "addr:housenumber":"1517",
    "addr:postcode":"90404",
    "addr:street":"20Th St",
    "iso:country":"US",
    "sg:address":"1517 20th St",
    "sg:city":"Santa Monica",
    "sg:classifiers":[
        {
            "category":"Communications",
            "subcategory":"Film & Video Production",
            "type":"Services"
        }
    ],
    "sg:phone":"+1 310 264 3000",
    "sg:postcode":"90404",
    "sg:province":"CA",
    "sg:tags":[
        "television",
        "producer"
    ],
    "wof:name":"Hungry Man",
    "wof:placetype":"venue"
},
  "geometry": {"coordinates":[-118.477063,34.026281],"type":"Point"}
}