{
  "type": "Feature",
  "properties": {
    "iso:country":"US",
    "sg:address":"40144 Enterprise Dr",
    "sg:city":"Oakhurst",
    "sg:classifiers":[
        {
            "category":"Retail",
            "subcategory":"Auto Repair",
            "type":"Services"
        }
    ],
    "sg:phone":"+1 559 683 2377",
    "sg:postcode":"93644",
    "sg:province":"CA",
    "sg:tags":[
        "repairing",
        "automobile"
    ],
    "wof:name":"Mountain Auto Clinic",
    "wof:placetype":"venue"
},
  "geometry": {"coordinates":[-119.662417,37.332497],"type":"Point"}
}