{
  "type": "Feature",
  "properties": {
    "iso:country":"US",
    "sg:address":"1623 Terrace Way",
    "sg:city":"Santa Rosa",
    "sg:classifiers":[
        {
            "category":"Real Estate",
            "subcategory":"Real Estate Agent",
            "type":"Services"
        }
    ],
    "sg:phone":"+1 707 284 3636",
    "sg:postcode":"95404",
    "sg:province":"CA",
    "wof:name":"Vintage Square Properties",
    "wof:placetype":"venue"
},
  "geometry": {"coordinates":[-122.70293100000001,38.456225],"type":"Point"}
}