{
  "type": "Feature",
  "properties": {
    "iso:country":"US",
    "sg:address":"1 Main St",
    "sg:city":"Belvedere Tibrn",
    "sg:classifiers":[
        {
            "category":"Restaurant",
            "type":"Food & Drink"
        }
    ],
    "sg:phone":"+1 415 435 8515",
    "sg:postcode":"94920",
    "sg:province":"CA",
    "sg:tags":[
        "shop",
        "coffee"
    ],
    "wof:name":"Caffe Acri",
    "wof:placetype":"venue"
},
  "geometry": {"coordinates":[-122.456816,37.873118],"type":"Point"}
}