{
  "type": "Feature",
  "properties": {
    "addr:full":"800 S Broadway Walnut Creek CA 94596",
    "addr:housenumber":"800",
    "addr:postcode":"94596",
    "addr:street":"S Broadway",
    "iso:country":"US",
    "sg:address":"800 S Broadway",
    "sg:city":"Walnut Creek",
    "sg:classifiers":[
        {
            "category":"Organizations",
            "subcategory":"Membership Organization",
            "type":"Services"
        }
    ],
    "sg:phone":"+1 925 932 4411",
    "sg:postcode":"94596",
    "sg:province":"CA",
    "sg:tags":[
        "athletic"
    ],
    "sg:website":"www.pac-10.org",
    "wof:name":"Pacific-10 Conference",
    "wof:placetype":"venue"
},
  "geometry": {"coordinates":[-122.05868599999999,37.894199],"type":"Point"}
}