{
  "type": "Feature",
  "properties": {
    "addr:full":"28292 Zarza Mission Viejo CA 92692",
    "addr:postcode":"28292;92692",
    "addr:street":"Zarza",
    "iso:country":"US",
    "sg:address":"28292 Zarza",
    "sg:city":"Mission Viejo",
    "sg:classifiers":[
        {
            "category":"Professional",
            "type":"Services"
        }
    ],
    "sg:phone":"+1 949 716 4788",
    "sg:postcode":"92692",
    "sg:province":"CA",
    "wof:name":"Cruz N Notary",
    "wof:placetype":"venue"
},
  "geometry": {"coordinates":[-117.63661399999999,33.618279],"type":"Point"}
}