{
  "type": "Feature",
  "properties": {
    "addr:full":"13755 Roscoe Blvd Panorama City CA 91402",
    "addr:housenumber":"13755",
    "addr:postcode":"91402",
    "addr:street":"Roscoe Blvd",
    "iso:country":"US",
    "sg:address":"13755 Roscoe Blvd",
    "sg:city":"Panorama City",
    "sg:classifiers":[
        {
            "category":"Autos & Motor Vehicles",
            "subcategory":"Automobile Sales",
            "type":"Retail Goods"
        }
    ],
    "sg:phone":"+1 818 892 3900",
    "sg:postcode":"91402",
    "sg:province":"CA",
    "sg:tags":[
        "car",
        "dealer"
    ],
    "wof:name":"Auto Bank Warehouse",
    "wof:placetype":"venue"
},
  "geometry": {"coordinates":[-118.43403499999999,34.22173],"type":"Point"}
}