{
  "type": "Feature",
  "properties": {
    "iso:country":"US",
    "sg:address":"2153 View Crest Glen",
    "sg:city":"Escondido",
    "sg:classifiers":[
        {
            "category":"Manufacturing",
            "subcategory":"Chemicals & Compounds",
            "type":"Manufacturing & Wholesale Goods"
        }
    ],
    "sg:phone":"+1 760 752 9582",
    "sg:postcode":"92026",
    "sg:province":"CA",
    "sg:tags":[
        "product",
        "mfg"
    ],
    "wof:name":"P P G",
    "wof:placetype":"venue"
},
  "geometry": {"coordinates":[-117.13054700000001,33.167072],"type":"Point"}
}