{
  "type": "Feature",
  "properties": {
    "iso:country":"US",
    "sg:address":"8768 E 9th St",
    "sg:city":"Rancho Cucamonga",
    "sg:classifiers":[
        {
            "category":"Manufacturing",
            "subcategory":"Pet Food",
            "type":"Manufacturing & Wholesale Goods"
        },
        {
            "category":"Organizations",
            "subcategory":"Professional Association",
            "type":"Services"
        }
    ],
    "sg:phone":"+1 909 981 4804",
    "sg:postcode":"91730",
    "sg:province":"CA",
    "sg:tags":[
        "feed",
        "mfg",
        "sales",
        "relations",
        "prepared",
        "public"
    ],
    "wof:name":"Tropical Fish Food",
    "wof:placetype":"venue"
},
  "geometry": {"coordinates":[-117.614276,34.095806],"type":"Point"}
}