{
  "type": "Feature",
  "properties": {
    "addr:full":"41701 Corporate Way Palm Desert CA 92260",
    "addr:housenumber":"41701",
    "addr:postcode":"ca 92260",
    "addr:street":"Corporate Way",
    "iso:country":"US",
    "sg:address":"41701 Corporate Way",
    "sg:city":"Palm Desert",
    "sg:classifiers":[
        {
            "category":"Professional",
            "subcategory":"Business Services",
            "type":"Services"
        }
    ],
    "sg:phone":"+1 760 779 5221",
    "sg:postcode":"92260",
    "sg:province":"CA",
    "sg:tags":[
        "interior",
        "consultant",
        "design",
        "decorator"
    ],
    "wof:name":"Ernie Rubin & Co",
    "wof:placetype":"venue"
},
  "geometry": {"coordinates":[-116.362447,33.745847],"type":"Point"}
}