{
  "type": "Feature",
  "properties": {
    "addr:full":"708 Gravenstein Hwy N Sebastopol CA 95472",
    "addr:housenumber":"708",
    "addr:postcode":"95472",
    "addr:street":"Gravenstein Hwy N",
    "iso:country":"US",
    "sg:address":"708 Gravenstein Hwy N",
    "sg:city":"Sebastopol",
    "sg:classifiers":[
        {
            "category":"Communications",
            "subcategory":"Film & Video Production",
            "type":"Services"
        }
    ],
    "sg:phone":"+1 707 823 2361",
    "sg:postcode":"95472",
    "sg:province":"CA",
    "sg:tags":[
        "taping"
    ],
    "sg:website":"www.spectrum-inc.org",
    "wof:name":"Spectrum Inc",
    "wof:placetype":"venue"
},
  "geometry": {"coordinates":[-122.839834,38.408671],"type":"Point"}
}