{
  "type": "Feature",
  "properties": {
    "addr:full":"170 Selby Ln. Atherton, Ca 94027",
    "wof:categories":[
        "education_and_religion:education=school"
    ],
    "wof:name":"Selby Lane Elementary School",
    "wof:placetype":"venue"
},
  "geometry": {"coordinates":[-122.21900566690427,37.45821844628189],"type":"Point"}
}