{
  "type": "Feature",
  "properties": {
    "iso:country":"US",
    "sg:address":"240 Miller Ave",
    "sg:city":"Mill Valley",
    "sg:classifiers":[
        {
            "category":"Health Services",
            "subcategory":"Health Practitioner",
            "type":"Services"
        }
    ],
    "sg:phone":"+1 415 383 1857",
    "sg:postcode":"94941",
    "sg:province":"CA",
    "sg:tags":[
        "psychologist"
    ],
    "wof:name":"Robert L Kaufman PHD",
    "wof:placetype":"venue"
},
  "geometry": {"coordinates":[-122.541784,37.901661],"type":"Point"}
}