{
  "type": "Feature",
  "properties": {
    "iso:country":"US",
    "sg:address":"3051 Fulton Ave",
    "sg:city":"Sacramento",
    "sg:classifiers":[
        {
            "category":"Personal",
            "subcategory":"Beauty Salon",
            "type":"Services"
        },
        {
            "category":"Personal",
            "subcategory":"Day Spa",
            "type":"Services"
        },
        {
            "category":"Personal",
            "subcategory":"Nail Salon",
            "type":"Services"
        }
    ],
    "sg:phone":"+1 916 289 1724",
    "sg:postcode":"95821",
    "sg:province":"CA",
    "sg:tags":[
        "hair"
    ],
    "sg:website":"www.StyledByMarissa.com",
    "wof:name":"Styled By Marissa",
    "wof:placetype":"venue"
},
  "geometry": {"coordinates":[-121.401691,38.620384],"type":"Point"}
}