{
  "type": "Feature",
  "properties": {
    "iso:country":"US",
    "sg:address":"7985 Sage Ave",
    "sg:city":"Yucca Valley",
    "sg:classifiers":[
        {
            "category":"Freight",
            "type":"Transportation"
        }
    ],
    "sg:phone":"+1 760 365 8431",
    "sg:postcode":"92284",
    "sg:province":"CA",
    "sg:tags":[
        "operator",
        "local",
        "trucking"
    ],
    "wof:name":"Richard Thompson",
    "wof:placetype":"venue"
},
  "geometry": {"coordinates":[-116.423526,34.106723],"type":"Point"}
}