{
  "type": "Feature",
  "properties": {
    "iso:country":"US",
    "sg:address":"3725 Talbot St",
    "sg:city":"San Diego",
    "sg:classifiers":[
        {
            "category":"Professional",
            "type":"Services"
        }
    ],
    "sg:phone":"+1 619 222 2245",
    "sg:postcode":"92106",
    "sg:province":"CA",
    "sg:tags":[
        "establishment"
    ],
    "sg:website":"www.novonics.com",
    "wof:name":"Novonics Corp",
    "wof:placetype":"venue"
},
  "geometry": {"coordinates":[-117.244463,32.722366],"type":"Point"}
}