{
  "type": "Feature",
  "properties": {
    "iso:country":"US",
    "sg:address":"12841 S Atlantic Ave",
    "sg:city":"Compton",
    "sg:classifiers":[
        {
            "category":"Manufacturing",
            "subcategory":"Food",
            "type":"Manufacturing & Wholesale Goods"
        },
        {
            "category":"Wholesale",
            "subcategory":"Groceries",
            "type":"Manufacturing & Wholesale Goods"
        }
    ],
    "sg:phone":"+1 310 635 5664",
    "sg:postcode":"90221",
    "sg:province":"CA",
    "sg:tags":[
        "fr",
        "mfg",
        "frozen",
        "packaged",
        "preparation",
        "processor"
    ],
    "sg:website":"www.mcifoods.com",
    "wof:name":"M C I Foods Inc-Los Cabos",
    "wof:placetype":"venue"
},
  "geometry": {"coordinates":[-118.194019,33.90547],"type":"Point"}
}