{
  "type": "Feature",
  "properties": {
    "iso:country":"US",
    "sg:address":"1211 Mercantile St",
    "sg:city":"Oxnard",
    "sg:classifiers":[
        {
            "category":"Arts & Performance",
            "subcategory":"Theater",
            "type":"Entertainment"
        }
    ],
    "sg:phone":"+1 805 247 1164",
    "sg:postcode":"93030",
    "sg:province":"CA",
    "sg:tags":[
        "production",
        "musical"
    ],
    "wof:name":"Phil Burke Rigging Inc",
    "wof:placetype":"venue"
},
  "geometry": {"coordinates":[-119.169585,34.189337],"type":"Point"}
}