{
  "type": "Feature",
  "properties": {
    "addr:full":"9885 Mesa Rim Rd San Diego CA 92121",
    "addr:housenumber":"9885",
    "addr:postcode":"92121",
    "addr:street":"Mesa Rim Rd",
    "iso:country":"US",
    "sg:address":"9885 Mesa Rim Rd",
    "sg:city":"San Diego",
    "sg:classifiers":[
        {
            "category":"Building & Trades",
            "subcategory":"Construction",
            "type":"Services"
        }
    ],
    "sg:phone":"+1 858 558 1455",
    "sg:postcode":"92121",
    "sg:province":"CA",
    "sg:tags":[
        "maker",
        "cabinet"
    ],
    "wof:name":"Adrian Woodworks",
    "wof:placetype":"venue"
},
  "geometry": {"coordinates":[-117.177379,32.901203],"type":"Point"}
}