{
  "type": "Feature",
  "properties": {
    "iso:country":"US",
    "sg:address":"480 S Canyon Ridge Dr",
    "sg:city":"Anaheim",
    "sg:classifiers":[
        {
            "category":"Professional",
            "subcategory":"Management & Consulting",
            "type":"Services"
        }
    ],
    "sg:phone":"+1 714 281 7363",
    "sg:postcode":"92807",
    "sg:province":"CA",
    "sg:tags":[
        "fuel"
    ],
    "wof:name":"Sgs Enterprises",
    "wof:placetype":"venue"
},
  "geometry": {"coordinates":[-117.766251,33.851601],"type":"Point"}
}