{
  "type": "Feature",
  "properties": {
    "iso:country":"US",
    "sg:address":"12190 Perris Blvd",
    "sg:city":"Moreno Valley",
    "sg:classifiers":[
        {
            "category":"Arts & Performance",
            "subcategory":"Theater",
            "type":"Entertainment"
        }
    ],
    "sg:phone":"+1 951 943 6542",
    "sg:postcode":"92557",
    "sg:province":"CA",
    "sg:tags":[
        "bureau"
    ],
    "wof:name":"Knock Knock Entertainment",
    "wof:placetype":"venue"
},
  "geometry": {"coordinates":[-117.226311,33.945744],"type":"Point"}
}