{
  "type": "Feature",
  "properties": {
    "iso:country":"US",
    "sg:address":"2001 Hwy 1",
    "sg:city":"Bodega Bay",
    "sg:classifiers":[
        {
            "category":"Real Estate",
            "subcategory":"Real Estate Agent",
            "type":"Services"
        }
    ],
    "sg:phone":"+1 707 875 3200",
    "sg:postcode":"94923",
    "sg:province":"CA",
    "wof:name":"Adams Realty",
    "wof:placetype":"venue"
},
  "geometry": {"coordinates":[-123.048065,38.340652],"type":"Point"}
}