{
  "type": "Feature",
  "properties": {
    "iso:country":"US",
    "sg:address":"1016 S Almansor St",
    "sg:city":"Alhambra",
    "sg:phone":"+1 626 457 5322",
    "sg:postcode":"91801",
    "sg:province":"CA",
    "sg:tags":[
        "marketing"
    ],
    "wof:name":"Sanmtz Inc",
    "wof:placetype":"venue"
},
  "geometry": {"coordinates":[-118.116856,34.083064],"type":"Point"}
}