{
  "type": "Feature",
  "properties": {
    "addr:full":"250 Whitmore St Oakland CA 94611",
    "addr:housenumber":"250",
    "addr:postcode":"94611",
    "addr:street":"Whitmore St",
    "iso:country":"US",
    "sg:address":"250 Whitmore St",
    "sg:city":"Oakland",
    "sg:classifiers":[
        {
            "category":"Arts & Performance",
            "subcategory":"Theater",
            "type":"Entertainment"
        }
    ],
    "sg:phone":"+1 510 451 9238",
    "sg:postcode":"94611",
    "sg:province":"CA",
    "sg:tags":[
        "television",
        "program",
        "producer"
    ],
    "wof:name":"Glorious Communications",
    "wof:placetype":"venue"
},
  "geometry": {"coordinates":[-122.251518,37.833237],"type":"Point"}
}