{
  "type": "Feature",
  "properties": {
    "iso:country":"US",
    "sg:address":"17240 Olive Street, Hesperia, Ca",
    "sg:city":"Hesperia",
    "sg:classifiers":[
        {
            "category":"Autos & Motor Vehicles",
            "subcategory":"Auto Supplies",
            "type":"Retail Goods"
        },
        {
            "category":"Retail",
            "subcategory":"Auto Repair",
            "type":"Services"
        }
    ],
    "sg:phone":"+1 760 403 8918",
    "sg:postcode":"92345",
    "sg:province":"CA",
    "sg:tags":[
        "recap",
        "retread",
        "tire"
    ],
    "sg:website":"http://www.mbktires.com",
    "wof:name":"MBK's Mobile Tire Repair - 24 Hours",
    "wof:placetype":"venue"
},
  "geometry": {"coordinates":[-117.289939,34.416203],"type":"Point"}
}