{
  "type": "Feature",
  "properties": {
    "iso:country":"US",
    "sg:address":"8777 Bell Rd",
    "sg:city":"Windsor",
    "sg:classifiers":[
        {
            "category":"Wholesale",
            "subcategory":"Groceries",
            "type":"Manufacturing & Wholesale Goods"
        }
    ],
    "sg:phone":"+1 707 838 3800",
    "sg:postcode":"95492",
    "sg:province":"CA",
    "sg:tags":[
        "confectionery",
        "candy"
    ],
    "wof:name":"Sid Kurlander & Son",
    "wof:placetype":"venue"
},
  "geometry": {"coordinates":[-122.80276499999999,38.534769],"type":"Point"}
}