{
  "type": "Feature",
  "properties": {
    "iso:country":"US",
    "sg:address":"43759 15th St W",
    "sg:city":"Lancaster",
    "sg:classifiers":[
        {
            "category":"Professional",
            "subcategory":"Accounting & Tax Preparation",
            "type":"Services"
        }
    ],
    "sg:phone":"+1 661 946 6543",
    "sg:postcode":"93534",
    "sg:province":"CA",
    "sg:tags":[
        "consultant"
    ],
    "wof:name":"Dan Randall & Assoc",
    "wof:placetype":"venue"
},
  "geometry": {"coordinates":[-118.156808,34.68009],"type":"Point"}
}