{
  "type": "Feature",
  "properties": {
    "iso:country":"US",
    "sg:address":"4672 Plumosa Dr",
    "sg:city":"Yorba Linda",
    "sg:classifiers":[
        {
            "category":"Wholesale",
            "subcategory":"Stationery",
            "type":"Manufacturing & Wholesale Goods"
        }
    ],
    "sg:phone":"+1 714 777 7005",
    "sg:postcode":"92886",
    "sg:province":"CA",
    "sg:tags":[
        "box",
        "fiber"
    ],
    "wof:name":"Better Box Plan",
    "wof:placetype":"venue"
},
  "geometry": {"coordinates":[-117.81573,33.89354],"type":"Point"}
}