{
  "type": "Feature",
  "properties": {
    "addr:full":"4467 N Terrace Meadow Ct Moorpark CA 93021",
    "addr:housenumber":"4467",
    "addr:postcode":"ca 93021",
    "addr:street":"N Terrace Meadow Ct",
    "iso:country":"US",
    "sg:address":"4467 N Terrace Meadow Ct",
    "sg:city":"Moorpark",
    "sg:classifiers":[
        {
            "category":"Wholesale",
            "subcategory":"Computers",
            "type":"Manufacturing & Wholesale Goods"
        }
    ],
    "sg:phone":"+1 805 529 5743",
    "sg:postcode":"93021",
    "sg:province":"CA",
    "wof:name":"Page International Marketing",
    "wof:placetype":"venue"
},
  "geometry": {"coordinates":[-118.90445699999999,34.27433],"type":"Point"}
}