{
  "type": "Feature",
  "properties": {
    "addr:full":"1276 Vicente Dr Sunnyvale CA 94086",
    "addr:housenumber":"1276",
    "addr:postcode":"94086",
    "addr:street":"Vicente Dr",
    "iso:country":"US",
    "sg:address":"1276 Vicente Dr",
    "sg:city":"Sunnyvale",
    "sg:classifiers":[
        {
            "category":"Manufacturing",
            "subcategory":"Electronics",
            "type":"Manufacturing & Wholesale Goods"
        }
    ],
    "sg:phone":"+1 408 986 0930",
    "sg:postcode":"94086",
    "sg:province":"CA",
    "sg:tags":[
        "semiconductor",
        "related",
        "devices"
    ],
    "wof:name":"California Contacts",
    "wof:placetype":"venue"
},
  "geometry": {"coordinates":[-122.056392,37.375891],"type":"Point"}
}