{
  "type": "Feature",
  "properties": {
    "addr:full":"5323 W Hillsdale Ave Visalia CA 93291",
    "addr:housenumber":"5323",
    "addr:postcode":"93291",
    "addr:street":"W Hillsdale Ave",
    "iso:country":"US",
    "sg:address":"5323 W Hillsdale Ave",
    "sg:city":"Visalia",
    "sg:classifiers":[
        {
            "category":"Professional",
            "subcategory":"Business Services",
            "type":"Services"
        }
    ],
    "sg:phone":"+1 559 735 3100",
    "sg:postcode":"93291",
    "sg:province":"CA",
    "sg:tags":[
        "broker"
    ],
    "wof:name":"Pro Citrus Network",
    "wof:placetype":"venue"
},
  "geometry": {"coordinates":[-119.351073,36.329469],"type":"Point"}
}