{
  "type": "Feature",
  "properties": {
    "addr:full":"9766 Chapman Ave Garden Grove CA 92841",
    "addr:housenumber":"9766",
    "addr:postcode":"92841",
    "addr:street":"Chapman Ave",
    "iso:country":"US",
    "sg:address":"9766 Chapman Ave",
    "sg:city":"Garden Grove",
    "sg:classifiers":[
        {
            "category":"Retail",
            "subcategory":"Veterinary Services",
            "type":"Services"
        }
    ],
    "sg:phone":"+1 714 638 2452",
    "sg:postcode":"92841",
    "sg:province":"CA",
    "sg:tags":[
        "veterinarian"
    ],
    "wof:name":"Icare",
    "wof:placetype":"venue"
},
  "geometry": {"coordinates":[-117.962524,33.788366],"type":"Point"}
}