{
  "type": "Feature",
  "properties": {
    "iso:country":"US",
    "sg:address":"1791 Arastradero Rd",
    "sg:city":"Palo Alto",
    "sg:classifiers":[
        {
            "category":"Professional",
            "subcategory":"Research",
            "type":"Services"
        }
    ],
    "sg:phone":"+1 650 493 3550",
    "sg:postcode":"94304",
    "sg:province":"CA",
    "sg:tags":[
        "development",
        "noncommercial",
        "commercial",
        "human",
        "factor",
        "organization"
    ],
    "sg:website":"www.air.org",
    "wof:name":"American Institute Research",
    "wof:placetype":"venue"
},
  "geometry": {"coordinates":[-122.17932999999999,37.38628],"type":"Point"}
}