{
  "type": "Feature",
  "properties": {
    "addr:full":"685 Tahos Rd Orinda CA 94563",
    "addr:housenumber":"685",
    "addr:postcode":"94563",
    "addr:street":"Tahos Rd",
    "iso:country":"US",
    "sg:address":"685 Tahos Rd",
    "sg:city":"Orinda",
    "sg:classifiers":[
        {
            "category":"Professional",
            "subcategory":"Business Services",
            "type":"Services"
        }
    ],
    "sg:phone":"+1 925 254 2180",
    "sg:postcode":"94563",
    "sg:province":"CA",
    "sg:tags":[
        "labeling"
    ],
    "wof:name":"Dmc Sales",
    "wof:placetype":"venue"
},
  "geometry": {"coordinates":[-122.163543,37.881642],"type":"Point"}
}