{
  "type": "Feature",
  "properties": {
    "addr:full":"2544 Soquel Ave Ste 112 Santa Cruz CA 95062",
    "addr:housenumber":"2544",
    "addr:postcode":"95062",
    "addr:street":"Soquel Ave Ste 112",
    "iso:country":"US",
    "sg:address":"2544 Soquel Ave Ste 112",
    "sg:city":"Santa Cruz",
    "sg:classifiers":[
        {
            "category":"Arena",
            "subcategory":"Sports Club",
            "type":"Entertainment"
        }
    ],
    "sg:phone":"+1 831 476 7575",
    "sg:postcode":"95062",
    "sg:province":"CA",
    "sg:tags":[
        "martial art"
    ],
    "sg:website":"www.kungfusantacruz.com",
    "wof:name":"Kung Fu Santa Cruz",
    "wof:placetype":"venue"
},
  "geometry": {"coordinates":[-121.99151999999999,36.984601],"type":"Point"}
}