{
  "type": "Feature",
  "properties": {
    "iso:country":"US",
    "sg:address":"1243 Florida St",
    "sg:city":"Vallejo",
    "sg:classifiers":[
        {
            "category":"Real Estate",
            "subcategory":"Real Estate Agent",
            "type":"Services"
        }
    ],
    "sg:phone":"+1 707 643 3120",
    "sg:postcode":"94590",
    "sg:province":"CA",
    "wof:name":"Zangara Real Estate",
    "wof:placetype":"venue"
},
  "geometry": {"coordinates":[-122.24552,38.104846],"type":"Point"}
}