{
  "type": "Feature",
  "properties": {
    "addr:full":"7111 Saranac St San Diego CA 92115",
    "addr:housenumber":"7111",
    "addr:postcode":"92115",
    "addr:street":"Saranac St",
    "iso:country":"US",
    "sg:address":"7111 Saranac St",
    "sg:city":"San Diego",
    "sg:classifiers":[
        {
            "category":"Banks & Credit Unions",
            "subcategory":"Financial Services",
            "type":"Services"
        }
    ],
    "sg:phone":"+1 619 698 6307",
    "sg:postcode":"92115",
    "sg:province":"CA",
    "sg:tags":[
        "trust",
        "management"
    ],
    "wof:name":"Anderson Living Trust 03",
    "wof:placetype":"venue"
},
  "geometry": {"coordinates":[-117.04288099999999,32.770821],"type":"Point"}
}