{
  "type": "Feature",
  "properties": {
    "addr:full":"14147 Twin Peaks Rd Poway CA 92064",
    "addr:housenumber":"14147",
    "addr:postcode":"ca 92064",
    "addr:street":"Twin Peaks Rd",
    "iso:country":"US",
    "sg:address":"14147 Twin Peaks Rd",
    "sg:city":"Poway",
    "sg:classifiers":[
        {
            "category":"Food & Beverages",
            "subcategory":"Groceries & Convenience Stores",
            "type":"Retail Goods"
        }
    ],
    "sg:phone":"+1 858 486 0730",
    "sg:postcode":"92064",
    "sg:province":"CA",
    "sg:website":"www.circlek.com",
    "wof:name":"Circle K",
    "wof:placetype":"venue"
},
  "geometry": {"coordinates":[-117.02423899999999,32.97805],"type":"Point"}
}