{
  "type": "Feature",
  "properties": {
    "iso:country":"US",
    "sg:address":"14147 Twin Peaks Rd",
    "sg:city":"Poway",
    "sg:classifiers":[
        {
            "category":"Food & Beverages",
            "subcategory":"Groceries & Convenience Stores",
            "type":"Retail Goods"
        }
    ],
    "sg:phone":"+1 858 486 0730",
    "sg:postcode":"92064",
    "sg:province":"CA",
    "sg:website":"www.circlek.com",
    "wof:name":"Circle K",
    "wof:placetype":"venue"
},
  "geometry": {"coordinates":[-117.024239,32.97805],"type":"Point"}
}