{
  "type": "Feature",
  "properties": {
    "iso:country":"US",
    "sg:address":"19935 Ventura Blvd",
    "sg:city":"Woodland Hills",
    "sg:classifiers":[
        {
            "category":"Professional",
            "subcategory":"Lawyer & Legal Services",
            "type":"Services"
        }
    ],
    "sg:phone":"+1 818 986 6176",
    "sg:postcode":"91364",
    "sg:province":"CA",
    "sg:tags":[
        "attorney"
    ],
    "wof:name":"Adler & Stauffer",
    "wof:placetype":"venue"
},
  "geometry": {"coordinates":[-118.56262,34.172653],"type":"Point"}
}