{
  "type": "Feature",
  "properties": {
    "addr:full":"2550 Saturn Ave Huntington Park CA 90255",
    "addr:housenumber":"2550",
    "addr:postcode":"90255",
    "addr:street":"Saturn Ave;Park",
    "iso:country":"US",
    "sg:address":"2550 Saturn Ave",
    "sg:city":"Huntington Park",
    "sg:classifiers":[
        {
            "category":"Food & Beverages",
            "subcategory":"Meat & Fish",
            "type":"Retail Goods"
        }
    ],
    "sg:phone":"+1 323 582 6937",
    "sg:postcode":"90255",
    "sg:province":"CA",
    "sg:tags":[
        "market"
    ],
    "wof:name":"Toaster's Market",
    "wof:placetype":"venue"
},
  "geometry": {"coordinates":[-118.225865,33.976896],"type":"Point"}
}