{
  "type": "Feature",
  "properties": {
    "addr:full":"18540 Sherman Way Reseda CA 91335",
    "addr:housenumber":"18540",
    "addr:postcode":"91335",
    "addr:street":"Sherman Way",
    "iso:country":"US",
    "sg:address":"18540 Sherman Way",
    "sg:city":"Reseda",
    "sg:classifiers":[
        {
            "category":"Health Services",
            "subcategory":"Doctor",
            "type":"Services"
        }
    ],
    "sg:phone":"+1 818 344 0446",
    "sg:postcode":"91335",
    "sg:province":"CA",
    "sg:tags":[
        "dentist"
    ],
    "wof:name":"Dio Family Dental Care",
    "wof:placetype":"venue"
},
  "geometry": {"coordinates":[-118.53846799999999,34.200985],"type":"Point"}
}