{
  "type": "Feature",
  "properties": {
    "iso:country":"US",
    "sg:address":"1300 Trancas St",
    "sg:city":"Napa",
    "sg:classifiers":[
        {
            "category":"Food & Beverages",
            "subcategory":"Groceries & Convenience Stores",
            "type":"Retail Goods"
        }
    ],
    "sg:phone":"+1 707 255 6288",
    "sg:postcode":"94558",
    "sg:province":"CA",
    "wof:name":"Tesoro Refining & Marketing Co",
    "wof:placetype":"venue"
},
  "geometry": {"coordinates":[-122.302931,38.322291],"type":"Point"}
}