{
  "type": "Feature",
  "properties": {
    "addr:full":"3097 Moorpark Avenue San Jose CA 95128",
    "addr:housenumber":"3097",
    "addr:postcode":"95128",
    "addr:street":"Moorpark Avenue",
    "iso:country":"US",
    "sg:address":"3097 Moorpark Avenue",
    "sg:city":"San Jose",
    "sg:classifiers":[
        {
            "category":"Professional",
            "subcategory":"Accounting & Tax Preparation",
            "type":"Services"
        }
    ],
    "sg:phone":"+1 408 423 9320",
    "sg:postcode":"95128",
    "sg:province":"CA",
    "sg:tags":[
        "accountant"
    ],
    "wof:name":"Kim Steve CPA",
    "wof:placetype":"venue"
},
  "geometry": {"coordinates":[-121.94968,37.316123],"type":"Point"}
}