{
  "type": "Feature",
  "properties": {
    "addr:full":"6021 N Figueroa Street Suite B Los Angeles CA 90042",
    "addr:housenumber":"6021",
    "addr:postcode":"90042",
    "addr:street":"N Figueroa Street Suite B",
    "iso:country":"US",
    "sg:address":"6021 N Figueroa Street Suite B",
    "sg:city":"Los Angeles",
    "sg:classifiers":[
        {
            "category":"Cinema",
            "subcategory":"Movie Rental",
            "type":"Entertainment"
        }
    ],
    "sg:phone":"+1 323 258 5208",
    "sg:postcode":"90042",
    "sg:province":"CA",
    "sg:tags":[
        "game",
        "video"
    ],
    "wof:name":"Video Hut",
    "wof:placetype":"venue"
},
  "geometry": {"coordinates":[-118.18894,34.111449],"type":"Point"}
}