{
  "type": "Feature",
  "properties": {
    "addr:full":"6201 Coliseum Way Oakland CA 94621",
    "addr:housenumber":"6201",
    "addr:postcode":"94621",
    "addr:street":"Coliseum Way",
    "iso:country":"US",
    "sg:address":"6201 Coliseum Way",
    "sg:city":"Oakland",
    "sg:classifiers":[
        {
            "category":"Shopping",
            "subcategory":"Party Supplies",
            "type":"Retail Goods"
        },
        {
            "category":"Building & Trades",
            "subcategory":"Equipment Rental",
            "type":"Services"
        }
    ],
    "sg:phone":"+1 510 632 6868",
    "sg:postcode":"94621",
    "sg:province":"CA",
    "sg:tags":[
        "leasing",
        "yard",
        "equipment-renting",
        "store",
        "furniture"
    ],
    "sg:website":"www.tinsing.com",
    "wof:name":"Tin Sing Company Inc",
    "wof:placetype":"venue"
},
  "geometry": {"coordinates":[-122.208164,37.757724],"type":"Point"}
}