{
  "type": "Feature",
  "properties": {
    "addr:full":"10 E Vine St Redlands CA 92373",
    "addr:housenumber":"10",
    "addr:postcode":"92373",
    "addr:street":"E Vine St",
    "iso:country":"US",
    "sg:address":"10 E Vine St",
    "sg:city":"Redlands",
    "sg:classifiers":[
        {
            "category":"Health Services",
            "subcategory":"Doctor",
            "type":"Services"
        }
    ],
    "sg:phone":"+1 909 335 3443",
    "sg:postcode":"92373",
    "sg:province":"CA",
    "sg:tags":[
        "medical",
        "imaging"
    ],
    "wof:name":"Fetal Foto",
    "wof:placetype":"venue"
},
  "geometry": {"coordinates":[-117.181518,34.054564],"type":"Point"}
}