{
  "type": "Feature",
  "properties": {
    "iso:country":"US",
    "sg:address":"11701 Broadway",
    "sg:city":"Whittier",
    "sg:classifiers":[
        {
            "category":"Professional",
            "subcategory":"Business Services",
            "type":"Services"
        }
    ],
    "sg:phone":"+1 562 908 1044",
    "sg:postcode":"90601",
    "sg:province":"CA",
    "sg:tags":[
        "textile",
        "representative"
    ],
    "wof:name":"Charles V Cramer Textiles",
    "wof:placetype":"venue"
},
  "geometry": {"coordinates":[-118.051981,33.98635],"type":"Point"}
}