{
  "type": "Feature",
  "properties": {
    "addr:full":"956 Creston Rd Berkeley CA 94708",
    "addr:housenumber":"956",
    "addr:postcode":"94708",
    "addr:street":"Creston Rd",
    "iso:country":"US",
    "sg:address":"956 Creston Rd",
    "sg:city":"Berkeley",
    "sg:classifiers":[
        {
            "category":"Professional",
            "subcategory":"Detective & Security Services",
            "type":"Services"
        }
    ],
    "sg:phone":"+1 510 524 2687",
    "sg:postcode":"94708",
    "sg:province":"CA",
    "sg:tags":[
        "investigator"
    ],
    "wof:name":"Cathryn Yost",
    "wof:placetype":"venue"
},
  "geometry": {"coordinates":[-122.25846,37.895024],"type":"Point"}
}