{
  "type": "Feature",
  "properties": {
    "addr:full":"17373 Francisco Dr San Diego CA 92128",
    "addr:housenumber":"17373",
    "addr:postcode":"92128",
    "addr:street":"Francisco Dr",
    "iso:country":"US",
    "sg:address":"17373 Francisco Dr",
    "sg:city":"San Diego",
    "sg:classifiers":[
        {
            "category":"Banks & Credit Unions",
            "subcategory":"Financial Services",
            "type":"Services"
        }
    ],
    "sg:phone":"+1 858 485 1285",
    "sg:postcode":"92128",
    "sg:province":"CA",
    "sg:tags":[
        "trust",
        "management"
    ],
    "wof:name":"Brown Trust",
    "wof:placetype":"venue"
},
  "geometry": {"coordinates":[-117.067403,33.02811],"type":"Point"}
}