{
  "type": "Feature",
  "properties": {
    "addr:full":"549 W 23rd St Los Angeles CA 90007",
    "addr:housenumber":"549",
    "addr:postcode":"90007",
    "addr:street":"W 23Rd St",
    "iso:country":"US",
    "sg:address":"549 W 23rd St",
    "sg:city":"Los Angeles",
    "sg:classifiers":[
        {
            "category":"Shopping",
            "subcategory":"Crafts & Fabrics",
            "type":"Retail Goods"
        }
    ],
    "sg:phone":"+1 213 747 6100",
    "sg:postcode":"90007",
    "sg:province":"CA",
    "sg:tags":[
        "art",
        "supply"
    ],
    "wof:name":"Roark Graphic Supplies",
    "wof:placetype":"venue"
},
  "geometry": {"coordinates":[-118.27362100000001,34.030621],"type":"Point"}
}