{
  "type": "Feature",
  "properties": {
    "iso:country":"US",
    "sg:address":"631 Main St",
    "sg:city":"Brawley",
    "sg:classifiers":[
        {
            "category":"Professional",
            "subcategory":"Accounting & Tax Preparation",
            "type":"Services"
        }
    ],
    "sg:phone":"+1 760 344 6081",
    "sg:postcode":"92227",
    "sg:province":"CA",
    "sg:tags":[
        "return",
        "filing"
    ],
    "sg:website":"www.hrblock.com",
    "wof:name":"H & R Block Tax Svc",
    "wof:placetype":"venue"
},
  "geometry": {"coordinates":[-115.530933,32.978721],"type":"Point"}
}