{
  "type": "Feature",
  "properties": {
    "addr:full":"128 N Palm Dr Blythe CA 92225",
    "addr:housenumber":"128",
    "addr:postcode":"92225",
    "addr:street":"N Palm Dr",
    "iso:country":"US",
    "sg:address":"128 N Palm Dr",
    "sg:city":"Blythe",
    "sg:classifiers":[
        {
            "category":"Retail",
            "subcategory":"Auto Repair",
            "type":"Services"
        }
    ],
    "sg:phone":"+1 760 922 5000",
    "sg:postcode":"92225",
    "sg:province":"CA",
    "sg:tags":[
        "repairing",
        "automobile"
    ],
    "wof:name":"Texaco Xpress Lube",
    "wof:placetype":"venue"
},
  "geometry": {"coordinates":[-114.603269,33.610331],"type":"Point"}
}