{
  "type": "Feature",
  "properties": {
    "iso:country":"US",
    "sg:address":"8068 Palm Ave",
    "sg:city":"Highland",
    "sg:classifiers":[
        {
            "category":"Retail",
            "subcategory":"Veterinary Services",
            "type":"Services"
        }
    ],
    "sg:phone":"+1 909 862 5111",
    "sg:postcode":"92346",
    "sg:province":"CA",
    "sg:tags":[
        "hospital",
        "animal"
    ],
    "wof:name":"Ala-Palm Animal Hospital",
    "wof:placetype":"venue"
},
  "geometry": {"coordinates":[-117.208898,34.106377],"type":"Point"}
}