{
  "type": "Feature",
  "properties": {
    "addr:full":"3059 Denice Way Cottonwood CA 96022",
    "addr:housenumber":"3059",
    "addr:postcode":"96022",
    "addr:street":"Denice Way",
    "iso:country":"US",
    "sg:address":"3059 Denice Way",
    "sg:city":"Cottonwood",
    "sg:classifiers":[
        {
            "category":"Building & Trades",
            "subcategory":"Construction",
            "type":"Services"
        }
    ],
    "sg:phone":"+1 530 347 5244",
    "sg:postcode":"96022",
    "sg:province":"CA",
    "sg:tags":[
        "contractor"
    ],
    "wof:name":"Thermo Sheild Rv Roof Coatings",
    "wof:placetype":"venue"
},
  "geometry": {"coordinates":[-122.338731,40.376529],"type":"Point"}
}