{
  "type": "Feature",
  "properties": {
    "iso:country":"US",
    "sg:address":"160 Harbern Way",
    "sg:city":"Hollister",
    "sg:classifiers":[
        {
            "category":"Manufacturing",
            "subcategory":"Glass & Minerals",
            "type":"Manufacturing & Wholesale Goods"
        }
    ],
    "sg:phone":"+1 831 637 2189",
    "sg:postcode":"95023",
    "sg:province":"CA",
    "sg:tags":[
        "product",
        "nonmetallic",
        "mfg"
    ],
    "wof:name":"Designs By Jx",
    "wof:placetype":"venue"
},
  "geometry": {"coordinates":[-121.347376,36.81749],"type":"Point"}
}