{
  "type": "Feature",
  "properties": {
    "addr:full":"510 62nd St Oakland CA 94609",
    "addr:housenumber":"510",
    "addr:postcode":"94609",
    "addr:street":"62Nd St",
    "iso:country":"US",
    "sg:address":"510 62nd St",
    "sg:city":"Oakland",
    "sg:classifiers":[
        {
            "category":"Building & Trades",
            "subcategory":"Landscaping Services",
            "type":"Services"
        }
    ],
    "sg:phone":"+1 510 654 8242",
    "sg:postcode":"94609",
    "sg:province":"CA",
    "sg:tags":[
        "landscape"
    ],
    "wof:name":"Carson Tamar Landscaping",
    "wof:placetype":"venue"
},
  "geometry": {"coordinates":[-122.262023,37.8479],"type":"Point"}
}