{
  "type": "Feature",
  "properties": {
    "iso:country":"US",
    "sg:address":"11350 W Olympic Blvd",
    "sg:city":"Los Angeles",
    "sg:classifiers":[
        {
            "category":"Retail",
            "subcategory":"Car Wash",
            "type":"Services"
        }
    ],
    "sg:phone":"+1 310 575 8988",
    "sg:postcode":"90064",
    "sg:province":"CA",
    "sg:tags":[
        "polishing",
        "washing"
    ],
    "wof:name":"West L A Car Wash & Deli Mart",
    "wof:placetype":"venue"
},
  "geometry": {"coordinates":[-118.443001,34.037498],"type":"Point"}
}