{
  "type": "Feature",
  "properties": {
    "iso:country":"US",
    "sg:address":"13622 Inglewood Ave",
    "sg:city":"Hawthorne",
    "sg:classifiers":[
        {
            "category":"Retail",
            "subcategory":"Auto Repair",
            "type":"Services"
        }
    ],
    "sg:phone":"+1 310 675 2162",
    "sg:postcode":"90250",
    "sg:province":"CA",
    "sg:tags":[
        "repairing",
        "automobile"
    ],
    "wof:name":"King Bear Of South Bay",
    "wof:placetype":"venue"
},
  "geometry": {"coordinates":[-118.361194,33.908033],"type":"Point"}
}