{
  "type": "Feature",
  "properties": {
    "addr:full":"2150 Bell Ave Ste 185 Sacramento CA 95838",
    "addr:housenumber":"2150",
    "addr:postcode":"95838",
    "addr:street":"Bell Ave Ste 185",
    "iso:country":"US",
    "sg:address":"2150 Bell Ave Ste 185",
    "sg:city":"Sacramento",
    "sg:classifiers":[
        {
            "category":"Coffee & Tea",
            "type":"Food & Drink"
        }
    ],
    "sg:phone":"+1 916 929 1681",
    "sg:postcode":"95838",
    "sg:province":"CA",
    "sg:tags":[
        "espresso",
        "restaurant"
    ],
    "wof:name":"Terranova Roasting Coffee Inc",
    "wof:placetype":"venue"
},
  "geometry": {"coordinates":[-121.416642,38.647193],"type":"Point"}
}