{
  "type": "Feature",
  "properties": {
    "iso:country":"US",
    "sg:address":"1111 Broadway",
    "sg:city":"Oakland",
    "sg:classifiers":[
        {
            "category":"Professional",
            "subcategory":"Lawyer & Legal Services",
            "type":"Services"
        }
    ],
    "sg:phone":"+1 510 834 6600",
    "sg:postcode":"94607",
    "sg:province":"CA",
    "wof:name":"Bratton Eric Wendel Rosen Black & Dean Llp",
    "wof:placetype":"venue"
},
  "geometry": {"coordinates":[-122.272003,37.8022],"type":"Point"}
}