{
  "type": "Feature",
  "properties": {
    "addr:full":"5060 83rd St Sacramento CA 95826",
    "addr:housenumber":"5060",
    "addr:postcode":"95826",
    "addr:street":"83Rd St",
    "iso:country":"US",
    "sg:address":"5060 83rd St",
    "sg:city":"Sacramento",
    "sg:classifiers":[
        {
            "category":"Manufacturing",
            "subcategory":"Chemicals & Compounds",
            "type":"Manufacturing & Wholesale Goods"
        }
    ],
    "sg:phone":"+1 916 388 5800",
    "sg:postcode":"95826",
    "sg:province":"CA",
    "sg:tags":[
        "paint"
    ],
    "wof:name":"Valspar Corp",
    "wof:placetype":"venue"
},
  "geometry": {"coordinates":[-121.399092,38.525819],"type":"Point"}
}