{
  "type": "Feature",
  "properties": {
    "addr:full":"520 S El Camino Real San Mateo CA 94402",
    "addr:housenumber":"520",
    "addr:postcode":"94402",
    "addr:street":"S El Camino Real",
    "iso:country":"US",
    "sg:address":"520 S El Camino Real",
    "sg:city":"San Mateo",
    "sg:classifiers":[
        {
            "category":"Professional",
            "subcategory":"Lawyer & Legal Services",
            "type":"Services"
        }
    ],
    "sg:phone":"+1 415 982 2877",
    "sg:postcode":"94402",
    "sg:province":"CA",
    "wof:name":"Henry R Hu Law Offices",
    "wof:placetype":"venue"
},
  "geometry": {"coordinates":[-122.324062,37.561124],"type":"Point"}
}