{
  "type": "Feature",
  "properties": {
    "iso:country":"US",
    "sg:address":"6117 S Broadway",
    "sg:city":"Los Angeles",
    "sg:classifiers":[
        {
            "category":"Shopping",
            "subcategory":"Used Merchandise",
            "type":"Retail Goods"
        }
    ],
    "sg:phone":"+1 323 753 9241",
    "sg:postcode":"90003",
    "sg:province":"CA",
    "sg:tags":[
        "appliance"
    ],
    "wof:name":"Barca LA Appliances",
    "wof:placetype":"venue"
},
  "geometry": {"coordinates":[-118.278372,33.983442],"type":"Point"}
}