{
  "type": "Feature",
  "properties": {
    "addr:full":"350 S Maple St Ste D Corona CA 92880",
    "addr:housenumber":"350",
    "addr:postcode":"92880",
    "addr:street":"S Maple St Ste D",
    "iso:country":"US",
    "sg:address":"350 S Maple St Ste D",
    "sg:city":"Corona",
    "sg:classifiers":[
        {
            "category":"Wholesale",
            "subcategory":"Meat",
            "type":"Manufacturing & Wholesale Goods"
        },
        {
            "category":"Restaurant",
            "type":"Food & Drink"
        },
        {
            "category":"Food & Beverages",
            "subcategory":"Groceries & Convenience Stores",
            "type":"Retail Goods"
        }
    ],
    "sg:phone":"+1 909 862 4682",
    "sg:postcode":"92880",
    "sg:province":"CA",
    "sg:tags":[
        "meat-wholesale"
    ],
    "wof:name":"Diamond Wholesale National Meat Company",
    "wof:placetype":"venue"
},
  "geometry": {"coordinates":[-117.603352,33.882556],"type":"Point"}
}