{
  "type": "Feature",
  "properties": {
    "iso:country":"US",
    "sg:address":"39453 Fremont Blvd",
    "sg:city":"Fremont",
    "sg:classifiers":[
        {
            "category":"Health Services",
            "subcategory":"Doctor",
            "type":"Services"
        }
    ],
    "sg:phone":"+1 510 657 8907",
    "sg:postcode":"94538",
    "sg:province":"CA",
    "sg:tags":[
        "dentist"
    ],
    "wof:name":"De Ala Dental Care",
    "wof:placetype":"venue"
},
  "geometry": {"coordinates":[-121.98093,37.54462],"type":"Point"}
}