{
  "type": "Feature",
  "properties": {
    "iso:country":"US",
    "sg:address":"6507 N Pleasant Ave",
    "sg:city":"Fresno",
    "sg:classifiers":[
        {
            "category":"Freight",
            "type":"Transportation"
        }
    ],
    "sg:phone":"+1 559 432 1816",
    "sg:postcode":"93711",
    "sg:province":"CA",
    "sg:tags":[
        "lu",
        "general",
        "sup"
    ],
    "wof:name":"Plantmobile",
    "wof:placetype":"venue"
},
  "geometry": {"coordinates":[-119.83949,36.830198],"type":"Point"}
}