{
  "type": "Feature",
  "properties": {
    "addr:full":"7220 Avenida Encinas Suite #206 Carlsbad CA 92011",
    "addr:housenumber":"7220",
    "addr:postcode":"92011",
    "addr:street":"Avenida Encinas Suite # 206",
    "iso:country":"US",
    "sg:address":"7220 Avenida Encinas Suite #206",
    "sg:city":"Carlsbad",
    "sg:classifiers":[
        {
            "category":"Health Services",
            "subcategory":"Health Practitioner",
            "type":"Services"
        }
    ],
    "sg:postcode":"92011",
    "sg:province":"CA",
    "sg:tags":[
        "therapy",
        "physical"
    ],
    "wof:name":"Jon Kern",
    "wof:placetype":"venue"
},
  "geometry": {"coordinates":[-117.309268,33.099757],"type":"Point"}
}