{
  "type": "Feature",
  "properties": {
    "addr:full":"21680 Flores Ave Red Bluff CA 96080",
    "addr:postcode":"21680;96080",
    "addr:street":"Flores Ave",
    "iso:country":"US",
    "sg:address":"21680 Flores Ave",
    "sg:city":"Red Bluff",
    "sg:classifiers":[
        {
            "category":"Utilities",
            "subcategory":"Water",
            "type":"Services"
        }
    ],
    "sg:phone":"+1 530 528 8604",
    "sg:postcode":"96080",
    "sg:province":"CA",
    "sg:tags":[
        "system",
        "supply"
    ],
    "wof:name":"Proberta Water District",
    "wof:placetype":"venue"
},
  "geometry": {"coordinates":[-122.23017400000001,40.084291],"type":"Point"}
}