{
  "type": "Feature",
  "properties": {
    "addr:full":"1617 N el Centro Ave Los Angeles CA 90028",
    "addr:housenumber":"1617",
    "addr:postcode":"90028",
    "addr:street":"N El Centro Ave",
    "iso:country":"US",
    "sg:address":"1617 N el Centro Ave",
    "sg:city":"Los Angeles",
    "sg:classifiers":[
        {
            "category":"Professional",
            "type":"Services"
        }
    ],
    "sg:phone":"+1 323 469 2477",
    "sg:postcode":"90028",
    "sg:province":"CA",
    "sg:tags":[
        "establishment"
    ],
    "sg:website":"www.shoppingla.net",
    "wof:name":"Shopping LA",
    "wof:placetype":"venue"
},
  "geometry": {"coordinates":[-118.32381100000001,34.099993],"type":"Point"}
}