{
  "type": "Feature",
  "properties": {
    "addr:full":"1131 Back Bay Dr Newport Beach CA 92623",
    "addr:housenumber":"1131",
    "addr:postcode":"92623",
    "addr:street":"Back Bay Dr",
    "iso:country":"US",
    "sg:address":"1131 Back Bay Dr",
    "sg:city":"Newport Beach",
    "sg:classifiers":[
        {
            "category":"Taxi",
            "type":"Transportation"
        }
    ],
    "sg:phone":"+1 949 640 1480",
    "sg:postcode":"92623",
    "sg:province":"CA",
    "sg:tags":[
        "taxicab"
    ],
    "wof:name":"Yellow Cab",
    "wof:placetype":"venue"
},
  "geometry": {"coordinates":[-117.890612,33.616776],"type":"Point"}
}