{
  "type": "Feature",
  "properties": {
    "iso:country":"US",
    "sg:address":"1460 Santee Dr",
    "sg:city":"San Jose",
    "sg:classifiers":[
        {
            "category":"Manufacturing",
            "subcategory":"Tools & Machinery",
            "type":"Manufacturing & Wholesale Goods"
        }
    ],
    "sg:phone":"+1 408 971 9840",
    "sg:postcode":"95122",
    "sg:province":"CA",
    "sg:tags":[
        "mfg"
    ],
    "wof:name":"Accel Mail Equipment",
    "wof:placetype":"venue"
},
  "geometry": {"coordinates":[-121.846574,37.329265],"type":"Point"}
}