{
  "type": "Feature",
  "properties": {
    "addr:full":"1501 Broadway St Redwood City CA 94063",
    "addr:housenumber":"1501",
    "addr:postcode":"94063",
    "addr:street":"Broadway St",
    "iso:country":"US",
    "sg:address":"1501 Broadway St",
    "sg:city":"Redwood City",
    "sg:classifiers":[
        {
            "category":"Shopping",
            "subcategory":"Department Store",
            "type":"Retail Goods"
        }
    ],
    "sg:phone":"+1 650 568 0116",
    "sg:postcode":"94063",
    "sg:province":"CA",
    "sg:tags":[
        "shop"
    ],
    "sg:website":"www.biglots.com",
    "wof:name":"Big Lots",
    "wof:placetype":"venue"
},
  "geometry": {"coordinates":[-122.21464,37.486927],"type":"Point"}
}