{
  "type": "Feature",
  "properties": {
    "addr:full":"8443 Warner Dr Culver City CA 90232",
    "addr:housenumber":"8443",
    "addr:postcode":"90232",
    "addr:street":"Warner Dr",
    "iso:country":"US",
    "sg:address":"8443 Warner Dr",
    "sg:city":"Culver City",
    "sg:classifiers":[
        {
            "category":"Professional",
            "subcategory":"Art Services",
            "type":"Services"
        }
    ],
    "sg:phone":"+1 310 202 8451",
    "sg:postcode":"90232",
    "sg:province":"CA",
    "sg:tags":[
        "photographer"
    ],
    "wof:name":"Iizuka Sawako Photography",
    "wof:placetype":"venue"
},
  "geometry": {"coordinates":[-118.3811,34.02354],"type":"Point"}
}