{
  "type": "Feature",
  "properties": {
    "addr:full":"300 Frank H. Ogawa Plaza Suite 600 Oakland CA 94612",
    "addr:housenumber":"300",
    "addr:postcode":"94612",
    "addr:street":"Frank H. Ogawa Plaza Suite 600",
    "iso:country":"US",
    "sg:address":"300 Frank H. Ogawa Plaza Suite 600",
    "sg:city":"Oakland",
    "sg:classifiers":[
        {
            "category":"Professional",
            "subcategory":"Computer Services",
            "type":"Services"
        }
    ],
    "sg:phone":"+1 888 665 9707",
    "sg:postcode":"94612",
    "sg:province":"CA",
    "sg:website":"http://www.scilearnglobal.com",
    "wof:name":"Scientific Learning Corporation",
    "wof:placetype":"venue"
},
  "geometry": {"coordinates":[-122.27127400000001,37.804361],"type":"Point"}
}