{
  "type": "Feature",
  "properties": {
    "iso:country":"US",
    "sg:address":"3801 Crowell Rd",
    "sg:city":"Turlock",
    "sg:classifiers":[
        {
            "category":"Food & Beverages",
            "subcategory":"Groceries & Convenience Stores",
            "type":"Retail Goods"
        }
    ],
    "sg:phone":"+1 209 664 1403",
    "sg:postcode":"95382",
    "sg:province":"CA",
    "sg:tags":[
        "grocer",
        "shopping"
    ],
    "wof:name":"Campus Vista Market",
    "wof:placetype":"venue"
},
  "geometry": {"coordinates":[-120.862977,37.526387],"type":"Point"}
}