{
  "type": "Feature",
  "properties": {
    "addr:full":"1249 Quarry Ln Pleasanton CA 94566",
    "addr:housenumber":"1249",
    "addr:postcode":"94566",
    "addr:street":"Quarry Ln",
    "iso:country":"US",
    "sg:address":"1249 Quarry Ln",
    "sg:city":"Pleasanton",
    "sg:classifiers":[
        {
            "category":"Wholesale",
            "subcategory":"Medical Equipment & Supplies",
            "type":"Manufacturing & Wholesale Goods"
        }
    ],
    "sg:phone":"+1 925 249 8131",
    "sg:postcode":"94566",
    "sg:province":"CA",
    "sg:tags":[
        "hospital"
    ],
    "wof:name":"Lumenis Inc",
    "wof:placetype":"venue"
},
  "geometry": {"coordinates":[-121.86558599999999,37.673671],"type":"Point"}
}