{
  "type": "Feature",
  "properties": {
    "iso:country":"US",
    "sg:address":"900 Jamieson Ct",
    "sg:city":"Redding",
    "sg:classifiers":[
        {
            "category":"Retail",
            "subcategory":"Repair Shop",
            "type":"Services"
        }
    ],
    "sg:phone":"+1 530 221 9218",
    "sg:postcode":"96003",
    "sg:province":"CA",
    "sg:tags":[
        "lock",
        "locksmith"
    ],
    "wof:name":"Absolute Lock & Security",
    "wof:placetype":"venue"
},
  "geometry": {"coordinates":[-122.353476,40.591125],"type":"Point"}
}