{
  "type": "Feature",
  "properties": {
    "addr:full":"322 E Hillcrest Dr Thousand Oaks CA 91360",
    "addr:housenumber":"322",
    "addr:postcode":"91360",
    "addr:street":"E Hillcrest Dr",
    "iso:country":"US",
    "sg:address":"322 E Hillcrest Dr",
    "sg:city":"Thousand Oaks",
    "sg:classifiers":[
        {
            "category":"Restaurant",
            "type":"Food & Drink"
        }
    ],
    "sg:phone":"+1 805 778 0780",
    "sg:postcode":"91360",
    "sg:province":"CA",
    "wof:name":"Johnny Rockets",
    "wof:placetype":"venue"
},
  "geometry": {"coordinates":[-118.87041600000001,34.181135],"type":"Point"}
}