{
  "type": "Feature",
  "properties": {
    "iso:country":"US",
    "sg:address":"2682 Temple Ave",
    "sg:city":"Long Beach",
    "sg:classifiers":[
        {
            "category":"Professional",
            "subcategory":"Art Services",
            "type":"Services"
        }
    ],
    "sg:phone":"+1 562 424 6822",
    "sg:postcode":"90806",
    "sg:province":"CA",
    "sg:tags":[
        "photographer"
    ],
    "wof:name":"Timothy Baur Photography",
    "wof:placetype":"venue"
},
  "geometry": {"coordinates":[-118.15885900000001,33.806553],"type":"Point"}
}