{
  "type": "Feature",
  "properties": {
    "addr:full":"3162 16th St San Francisco CA 94103",
    "addr:housenumber":"3162",
    "addr:postcode":"94103",
    "addr:street":"16Th St",
    "iso:country":"US",
    "sg:address":"3162 16th St",
    "sg:city":"San Francisco",
    "sg:classifiers":[
        {
            "category":"Shopping",
            "subcategory":"Used Merchandise",
            "type":"Retail Goods"
        }
    ],
    "sg:phone":"+1 415 255 9959",
    "sg:postcode":"94103",
    "sg:province":"CA",
    "wof:name":"Idol Vintage",
    "wof:placetype":"venue"
},
  "geometry": {"coordinates":[-122.42277799999999,37.76494],"type":"Point"}
}