{
  "type": "Feature",
  "properties": {
    "addr:full":"314 W 6th St Los Angeles CA 90014",
    "addr:housenumber":"314",
    "addr:postcode":"90014",
    "addr:street":"W 6Th St",
    "iso:country":"US",
    "sg:address":"314 W 6th St",
    "sg:city":"Los Angeles",
    "sg:classifiers":[
        {
            "category":"Manufacturing",
            "subcategory":"Jewelry",
            "type":"Manufacturing & Wholesale Goods"
        }
    ],
    "sg:phone":"+1 213 612 0284",
    "sg:postcode":"90014",
    "sg:province":"CA",
    "sg:tags":[
        "precious",
        "metal",
        "mfg"
    ],
    "wof:name":"Jansezians Jewelry",
    "wof:placetype":"venue"
},
  "geometry": {"coordinates":[-118.252229,34.046633],"type":"Point"}
}