{
  "type": "Feature",
  "properties": {
    "addr:full":"310 N Indian Hill Blvd Claremont CA 91711",
    "addr:housenumber":"310",
    "addr:postcode":"91711",
    "addr:street":"N Indian Hill Blvd",
    "iso:country":"US",
    "sg:address":"310 N Indian Hill Blvd",
    "sg:city":"Claremont",
    "sg:classifiers":[
        {
            "category":"Wholesale",
            "subcategory":"Electrical",
            "type":"Manufacturing & Wholesale Goods"
        }
    ],
    "sg:phone":"+1 909 941 1214",
    "sg:postcode":"91711",
    "sg:province":"CA",
    "sg:tags":[
        "alarm",
        "burglar",
        "system"
    ],
    "wof:name":"Total Home & Business Systems",
    "wof:placetype":"venue"
},
  "geometry": {"coordinates":[-117.719219,34.097503],"type":"Point"}
}