{
  "type": "Feature",
  "properties": {
    "addr:full":"16364 E Ballentine Pl Covina CA 91722",
    "addr:housenumber":"16364",
    "addr:postcode":"91722",
    "addr:street":"E Ballentine Pl",
    "iso:country":"US",
    "sg:address":"16364 E Ballentine Pl",
    "sg:city":"Covina",
    "sg:classifiers":[
        {
            "category":"Professional",
            "subcategory":"Printing & Photocopies",
            "type":"Services"
        }
    ],
    "sg:phone":"+1 626 482 5483",
    "sg:postcode":"91722",
    "sg:province":"CA",
    "sg:tags":[
        "lithographer"
    ],
    "wof:name":"Aaa Printing Service",
    "wof:placetype":"venue"
},
  "geometry": {"coordinates":[-117.9268,34.091799],"type":"Point"}
}