{
  "type": "Feature",
  "properties": {
    "iso:country":"US",
    "sg:address":"4580 Alvarado Canyon Rd",
    "sg:city":"San Diego",
    "sg:classifiers":[
        {
            "category":"Manufacturing",
            "subcategory":"Paper Products",
            "type":"Manufacturing & Wholesale Goods"
        },
        {
            "category":"Manufacturing",
            "subcategory":"Tools & Machinery",
            "type":"Manufacturing & Wholesale Goods"
        }
    ],
    "sg:phone":"+1 619 563 3616",
    "sg:postcode":"92120",
    "sg:province":"CA",
    "sg:tags":[
        "die",
        "cutting",
        "mfg"
    ],
    "wof:name":"Die Cutting Unlimited",
    "wof:placetype":"venue"
},
  "geometry": {"coordinates":[-117.099838,32.779955],"type":"Point"}
}