{
  "type": "Feature",
  "properties": {
    "addr:full":"512 W Route 66 Glendora CA 91740",
    "addr:housenumber":"512",
    "addr:postcode":"91740",
    "addr:street":"W Route 66",
    "iso:country":"US",
    "sg:address":"512 W Route 66",
    "sg:city":"Glendora",
    "sg:classifiers":[
        {
            "category":"Retail",
            "subcategory":"Emissions Testing",
            "type":"Services"
        },
        {
            "category":"Autos & Motor Vehicles",
            "subcategory":"Fuel & Gas Station",
            "type":"Retail Goods"
        }
    ],
    "sg:phone":"+1 626 914 9404",
    "sg:postcode":"91740",
    "sg:province":"CA",
    "sg:tags":[
        "automobile",
        "inspection"
    ],
    "wof:name":"Glendora Smog Test Only Center",
    "wof:placetype":"venue"
},
  "geometry": {"coordinates":[-117.87142900000001,34.128689],"type":"Point"}
}