{
  "type": "Feature",
  "properties": {
    "iso:country":"US",
    "sg:address":"13859 Carmel Valley Rd",
    "sg:city":"San Diego",
    "sg:classifiers":[
        {
            "category":"Restaurant",
            "type":"Food & Drink"
        }
    ],
    "sg:phone":"+1 858 780 8880",
    "sg:postcode":"92130",
    "sg:province":"CA",
    "wof:name":"Extreme Pizza",
    "wof:placetype":"venue"
},
  "geometry": {"coordinates":[-117.201615,32.952045],"type":"Point"}
}