{
  "type": "Feature",
  "properties": {
    "addr:full":"3212 Barmouth Dr Antioch CA 94509",
    "addr:housenumber":"3212",
    "addr:postcode":"ca 94509",
    "addr:street":"Barmouth Dr",
    "iso:country":"US",
    "sg:address":"3212 Barmouth Dr",
    "sg:city":"Antioch",
    "sg:classifiers":[
        {
            "category":"Building & Trades",
            "subcategory":"Landscaping Services",
            "type":"Services"
        }
    ],
    "sg:phone":"+1 925 757 6022",
    "sg:postcode":"94509",
    "sg:province":"CA",
    "wof:name":"Second Wind Landscape Services",
    "wof:placetype":"venue"
},
  "geometry": {"coordinates":[-121.788804,37.990504],"type":"Point"}
}