{
  "type": "Feature",
  "properties": {
    "addr:full":"8608 Cassieri Cir Sacramento CA 95828",
    "addr:housenumber":"8608",
    "addr:postcode":"95828",
    "addr:street":"Cassieri Cir",
    "iso:country":"US",
    "sg:address":"8608 Cassieri Cir",
    "sg:city":"Sacramento",
    "sg:classifiers":[
        {
            "category":"Real Estate",
            "subcategory":"Real Estate Agent",
            "type":"Services"
        }
    ],
    "sg:phone":"+1 916 470 2058",
    "sg:postcode":"95828",
    "sg:province":"CA",
    "wof:name":"Rosemond Properties",
    "wof:placetype":"venue"
},
  "geometry": {"coordinates":[-121.38371600000001,38.495209],"type":"Point"}
}