{
  "type": "Feature",
  "properties": {
    "iso:country":"US",
    "sg:address":"1205 N 2nd St",
    "sg:city":"El Cajon",
    "sg:classifiers":[
        {
            "category":"Manufacturing",
            "subcategory":"Printing",
            "type":"Manufacturing & Wholesale Goods"
        }
    ],
    "sg:phone":"+1 619 442 0804",
    "sg:postcode":"92021",
    "sg:province":"CA",
    "sg:tags":[
        "lithographic",
        "commercial"
    ],
    "wof:name":"Parker Systems Printing",
    "wof:placetype":"venue"
},
  "geometry": {"coordinates":[-116.935648,32.813295],"type":"Point"}
}