{
  "type": "Feature",
  "properties": {
    "addr:full":"8071 Elk Grove Florin Rd Sacramento CA 95829",
    "addr:housenumber":"8071",
    "addr:postcode":"95829",
    "addr:street":"Elk Grove Florin Rd",
    "iso:country":"US",
    "sg:address":"8071 Elk Grove Florin Rd",
    "sg:city":"Sacramento",
    "sg:classifiers":[
        {
            "category":"Restaurant",
            "type":"Food & Drink"
        }
    ],
    "sg:menulink":"http://www.allmenus.com/ca/elk-grove/213262-taco-bell/menu/",
    "sg:phone":"+1 916 681 4890",
    "sg:postcode":"95829",
    "sg:province":"CA",
    "sg:tags":[
        "mexican"
    ],
    "wof:name":"Taco Bell",
    "wof:placetype":"venue"
},
  "geometry": {"coordinates":[-121.37171600000001,38.464868],"type":"Point"}
}