{
  "type": "Feature",
  "properties": {
    "iso:country":"US",
    "sg:address":"1715 Chester Ave",
    "sg:city":"Bakersfield",
    "sg:classifiers":[
        {
            "category":"Government",
            "subcategory":"Fire Station",
            "type":"Public Place"
        }
    ],
    "sg:phone":"+1 661 326 3951",
    "sg:postcode":"93301",
    "sg:province":"CA",
    "sg:tags":[
        "protection"
    ],
    "wof:name":"City of Bkersfld Fre Prevtn AR",
    "wof:placetype":"venue"
},
  "geometry": {"coordinates":[-119.018894,35.374567],"type":"Point"}
}