{
  "type": "Feature",
  "properties": {
    "iso:country":"US",
    "sg:address":"8929 University Center Ln",
    "sg:city":"San Diego",
    "sg:classifiers":[
        {
            "category":"Health Services",
            "subcategory":"Doctor",
            "type":"Services"
        }
    ],
    "sg:phone":"+1 858 202 1546",
    "sg:postcode":"92122",
    "sg:province":"CA",
    "sg:tags":[
        "physician",
        "surgeon"
    ],
    "wof:name":"Paincare Of San Diego A Mdcl",
    "wof:placetype":"venue"
},
  "geometry": {"coordinates":[-117.228627,32.868805],"type":"Point"}
}