{
  "type": "Feature",
  "properties": {
    "addr:full":"501 E Citrus Ave Redlands CA 92373",
    "addr:housenumber":"501",
    "addr:postcode":"92373",
    "addr:street":"E Citrus Ave",
    "iso:country":"US",
    "sg:address":"501 E Citrus Ave",
    "sg:city":"Redlands",
    "sg:classifiers":[
        {
            "category":"Personal",
            "subcategory":"Barber",
            "type":"Services"
        }
    ],
    "sg:phone":"+1 909 307 8753",
    "sg:postcode":"92373",
    "sg:province":"CA",
    "wof:name":"Eric's Barber Shop",
    "wof:placetype":"venue"
},
  "geometry": {"coordinates":[-117.175701,34.055524],"type":"Point"}
}