{
  "type": "Feature",
  "properties": {
    "iso:country":"US",
    "sg:address":"1500 Quail St",
    "sg:city":"Newport Beach",
    "sg:classifiers":[
        {
            "category":"Real Estate",
            "subcategory":"Real Estate Agent",
            "type":"Services"
        }
    ],
    "sg:phone":"+1 949 852 0651",
    "sg:postcode":"92660",
    "sg:province":"CA",
    "sg:tags":[
        "management"
    ],
    "wof:name":"Nikko Capital Corp",
    "wof:placetype":"venue"
},
  "geometry": {"coordinates":[-117.869524,33.661813],"type":"Point"}
}