{
  "type": "Feature",
  "properties": {
    "addr:full":"1215 Howe Ave Suite 130 Sacramento CA 95825",
    "addr:housenumber":"1215",
    "addr:postcode":"95825",
    "addr:street":"Howe Ave Suite 130",
    "iso:country":"US",
    "sg:address":"1215 Howe Ave Suite 130",
    "sg:city":"Sacramento",
    "sg:classifiers":[
        {
            "category":"Building & Trades",
            "subcategory":"Construction",
            "type":"Services"
        }
    ],
    "sg:phone":"+1 916 779 8008",
    "sg:postcode":"95825",
    "sg:province":"CA",
    "sg:tags":[
        "contractor"
    ],
    "wof:name":"Tricorp Construction",
    "wof:placetype":"venue"
},
  "geometry": {"coordinates":[-121.415661,38.587628],"type":"Point"}
}