{
  "type": "Feature",
  "properties": {
    "iso:country":"US",
    "sg:address":"217 Cll Campana",
    "sg:city":"Walnut",
    "sg:classifiers":[
        {
            "category":"Shopping",
            "subcategory":"Florist",
            "type":"Retail Goods"
        }
    ],
    "sg:phone":"+1 909 594 1193",
    "sg:postcode":"91789",
    "sg:province":"CA",
    "wof:name":"Greenleaves",
    "wof:placetype":"venue"
},
  "geometry": {"coordinates":[-117.877881,34.013926],"type":"Point"}
}