{
  "type": "Feature",
  "properties": {
    "iso:country":"US",
    "sg:address":"4701 D St",
    "sg:city":"Sacramento",
    "sg:classifiers":[
        {
            "category":"Building & Trades",
            "subcategory":"Plumbing",
            "type":"Services"
        }
    ],
    "sg:phone":"+1 916 731 5529",
    "sg:postcode":"95819",
    "sg:province":"CA",
    "sg:tags":[
        "plumber",
        "industrial",
        "contractors-commercial"
    ],
    "wof:name":"Schor & Co Plumbing",
    "wof:placetype":"venue"
},
  "geometry": {"coordinates":[-121.44201700000001,38.573799],"type":"Point"}
}