{
  "type": "Feature",
  "properties": {
    "iso:country":"US",
    "sg:address":"1340 Otay Valley Rd",
    "sg:city":"San Diego",
    "sg:classifiers":[
        {
            "category":"Wholesale",
            "subcategory":"Auto Parts",
            "type":"Manufacturing & Wholesale Goods"
        }
    ],
    "sg:phone":"+1 619 710 2511",
    "sg:postcode":"92154",
    "sg:province":"CA",
    "sg:tags":[
        "automobile"
    ],
    "wof:name":"Jalisco Auto Wrecking",
    "wof:placetype":"venue"
},
  "geometry": {"coordinates":[-116.998492,32.571996],"type":"Point"}
}