{
  "type": "Feature",
  "properties": {
    "iso:country":"US",
    "sg:address":"1056 Terven Ave Ste A",
    "sg:city":"Salinas",
    "sg:classifiers":[
        {
            "category":"Manufacturing",
            "subcategory":"Building Materials",
            "type":"Manufacturing & Wholesale Goods"
        },
        {
            "category":"Home & Garden",
            "subcategory":"Home Furnishings",
            "type":"Retail Goods"
        },
        {
            "category":"Home & Garden",
            "subcategory":"Building Materials",
            "type":"Retail Goods"
        },
        {
            "category":"Manufacturing",
            "subcategory":"Glass & Minerals",
            "type":"Manufacturing & Wholesale Goods"
        },
        {
            "category":"Retail",
            "subcategory":"Auto Repair",
            "type":"Services"
        }
    ],
    "sg:phone":"+1 831 757 6574",
    "sg:postcode":"93901",
    "sg:province":"CA",
    "sg:tags":[
        "plate",
        "bathroom",
        "windshield",
        "door",
        "baths-equipment",
        "supply",
        "glazier",
        "glass-auto",
        "cabinet",
        "shower",
        "window",
        "fixtures",
        "accessory",
        "enclosure",
        "replacement"
    ],
    "wof:name":"AA Glass",
    "wof:placetype":"venue"
},
  "geometry": {"coordinates":[-121.627431,36.662804],"type":"Point"}
}