{
  "type": "Feature",
  "properties": {
    "iso:country":"US",
    "sg:address":"13752 Ventura Blvd",
    "sg:city":"Sherman Oaks",
    "sg:classifiers":[
        {
            "category":"Sports & Exercise",
            "subcategory":"Playing Field",
            "type":"Entertainment"
        }
    ],
    "sg:phone":"+1 818 817 3643",
    "sg:postcode":"91423",
    "sg:province":"CA",
    "sg:tags":[
        "instruction",
        "fitness"
    ],
    "sg:website":"www.scotmendelson.net/FIT.html",
    "wof:name":"F.I.T",
    "wof:placetype":"venue"
},
  "geometry": {"coordinates":[-118.43274599999999,34.148282],"type":"Point"}
}