{
  "type": "Feature",
  "properties": {
    "addr:full":"5820 Bellflower Blvd Lakewood CA 90713",
    "addr:housenumber":"5820",
    "addr:postcode":"90713",
    "addr:street":"Bellflower Blvd",
    "iso:country":"US",
    "sg:address":"5820 Bellflower Blvd",
    "sg:city":"Lakewood",
    "sg:classifiers":[
        {
            "category":"Restaurant",
            "type":"Food & Drink"
        }
    ],
    "sg:phone":"+1 800 786 1000",
    "sg:postcode":"90713",
    "sg:province":"CA",
    "sg:tags":[
        "fast"
    ],
    "sg:website":"www.in-n-out.com",
    "wof:name":"In-N-Out Burger",
    "wof:placetype":"venue"
},
  "geometry": {"coordinates":[-118.124878,33.860794],"type":"Point"}
}