{
  "type": "Feature",
  "properties": {
    "iso:country":"US",
    "sg:address":"2318 Fay Ave",
    "sg:city":"Modesto",
    "sg:classifiers":[
        {
            "category":"Shopping",
            "subcategory":"Gifts & Souvenirs",
            "type":"Retail Goods"
        }
    ],
    "sg:phone":"+1 209 572 1909",
    "sg:postcode":"95350",
    "sg:province":"CA",
    "wof:name":"Three Basketeers",
    "wof:placetype":"venue"
},
  "geometry": {"coordinates":[-121.014739,37.676901],"type":"Point"}
}