{
  "type": "Feature",
  "properties": {
    "addr:full":"2318 Fay Ave Modesto CA 95350",
    "addr:housenumber":"2318",
    "addr:postcode":"ca 95350",
    "addr:street":"Fay Ave",
    "iso:country":"US",
    "sg:address":"2318 Fay Ave",
    "sg:city":"Modesto",
    "sg:classifiers":[
        {
            "category":"Shopping",
            "subcategory":"Gifts & Souvenirs",
            "type":"Retail Goods"
        }
    ],
    "sg:phone":"+1 209 572 1909",
    "sg:postcode":"95350",
    "sg:province":"CA",
    "wof:name":"Three Basketeers",
    "wof:placetype":"venue"
},
  "geometry": {"coordinates":[-121.01473900000001,37.676901],"type":"Point"}
}