{
  "type": "Feature",
  "properties": {
    "addr:full":"3641 Sacramento St Ste G San Francisco CA 94118",
    "addr:housenumber":"3641",
    "addr:postcode":"94118",
    "addr:street":"Sacramento St Ste G",
    "iso:country":"US",
    "sg:address":"3641 Sacramento St Ste G",
    "sg:city":"San Francisco",
    "sg:classifiers":[
        {
            "category":"Personal",
            "subcategory":"Hair Removal",
            "type":"Services"
        },
        {
            "category":"Personal",
            "subcategory":"Skin Care",
            "type":"Services"
        }
    ],
    "sg:phone":"+1 415 571 9784",
    "sg:postcode":"94118",
    "sg:province":"CA",
    "sg:website":"www.aestheticsbyveronica.com",
    "wof:name":"Aesthetics by Veronica",
    "wof:placetype":"venue"
},
  "geometry": {"coordinates":[-122.452581,37.787194],"type":"Point"}
}