{
  "type": "Feature",
  "properties": {
    "addr:full":"4848 Pepperwood Way San Jose CA 95124",
    "addr:housenumber":"4848",
    "addr:postcode":"95124",
    "addr:street":"Pepperwood Way",
    "iso:country":"US",
    "sg:address":"4848 Pepperwood Way",
    "sg:city":"San Jose",
    "sg:classifiers":[
        {
            "category":"Building & Trades",
            "subcategory":"Construction",
            "type":"Services"
        }
    ],
    "sg:phone":"+1 408 379 3004",
    "sg:postcode":"95124",
    "sg:province":"CA",
    "sg:tags":[
        "weather",
        "stripping",
        "contractor"
    ],
    "wof:name":"A-1 Weatherstrip Co",
    "wof:placetype":"venue"
},
  "geometry": {"coordinates":[-121.918441,37.249222],"type":"Point"}
}