{
  "type": "Feature",
  "properties": {
    "iso:country":"US",
    "sg:address":"711 E Walnut St Ste 214",
    "sg:city":"Pasadena",
    "sg:classifiers":[
        {
            "category":"Health Services",
            "subcategory":"Health Practitioner",
            "type":"Services"
        }
    ],
    "sg:phone":"+1 626 793 8142",
    "sg:postcode":"91101",
    "sg:province":"CA",
    "sg:tags":[
        "acupuncture"
    ],
    "wof:name":"Thomas Lee Care",
    "wof:placetype":"venue"
},
  "geometry": {"coordinates":[-118.135805,34.149714],"type":"Point"}
}