{
  "type": "Feature",
  "properties": {
    "iso:country":"US",
    "sg:address":"8730 Wilshire Blvd Suite 412",
    "sg:city":"Beverly Hills",
    "sg:classifiers":[
        {
            "category":"Professional",
            "type":"Services"
        }
    ],
    "sg:phone":"+1 888 409 1819",
    "sg:postcode":"90049",
    "sg:province":"CA",
    "wof:name":"iDentityPi",
    "wof:placetype":"venue"
},
  "geometry": {"coordinates":[-118.382256,34.06673],"type":"Point"}
}