{
  "type": "Feature",
  "properties": {
    "addr:full":"4470 Redwood Hwy San Rafael CA 94903",
    "addr:housenumber":"4470",
    "addr:postcode":"94903",
    "addr:street":"Redwood Hwy",
    "iso:country":"US",
    "sg:address":"4470 Redwood Hwy",
    "sg:city":"San Rafael",
    "sg:classifiers":[
        {
            "category":"Travel",
            "subcategory":"Campground",
            "type":"Entertainment"
        },
        {
            "category":"Recreation",
            "type":"Entertainment"
        }
    ],
    "sg:phone":"+1 415 459 0459",
    "sg:postcode":"94903",
    "sg:province":"CA",
    "sg:tags":[
        "camp",
        "agency"
    ],
    "wof:name":"Tahoe Tennis Camp",
    "wof:placetype":"venue"
},
  "geometry": {"coordinates":[-122.539666,38.018135],"type":"Point"}
}