{
  "type": "Feature",
  "properties": {
    "addr:full":"676 Draco Dr Petaluma CA 94954",
    "addr:housenumber":"676",
    "addr:postcode":"94954",
    "addr:street":"Draco Dr",
    "iso:country":"US",
    "sg:address":"676 Draco Dr",
    "sg:city":"Petaluma",
    "sg:classifiers":[
        {
            "category":"Building & Trades",
            "subcategory":"Construction",
            "type":"Services"
        }
    ],
    "sg:phone":"+1 415 383 9663",
    "sg:postcode":"94954",
    "sg:province":"CA",
    "sg:tags":[
        "contractor"
    ],
    "wof:name":"Lawrence Precision Builders",
    "wof:placetype":"venue"
},
  "geometry": {"coordinates":[-122.638948,38.26418],"type":"Point"}
}