{
  "type": "Feature",
  "properties": {
    "iso:country":"US",
    "sg:address":"2152 Elsinore Rd",
    "sg:city":"Riverside",
    "sg:classifiers":[
        {
            "category":"Professional",
            "subcategory":"Management & Consulting",
            "type":"Services"
        }
    ],
    "sg:phone":"+1 951 788 9180",
    "sg:postcode":"92506",
    "sg:province":"CA",
    "sg:tags":[
        "consultant",
        "business"
    ],
    "wof:name":"Empire Quality Svc",
    "wof:placetype":"venue"
},
  "geometry": {"coordinates":[-117.358344,33.956843],"type":"Point"}
}