{
  "type": "Feature",
  "properties": {
    "iso:country":"US",
    "sg:address":"3412 Westminster Ave",
    "sg:city":"Santa Ana",
    "sg:classifiers":[
        {
            "category":"Restaurant",
            "type":"Food & Drink"
        }
    ],
    "sg:phone":"+1 714 554 4950",
    "sg:postcode":"92703",
    "sg:province":"CA",
    "sg:tags":[
        "mexican"
    ],
    "wof:name":"Fonda Los Hermanos Mata",
    "wof:placetype":"venue"
},
  "geometry": {"coordinates":[-117.91536499999999,33.759622],"type":"Point"}
}