{
  "type": "Feature",
  "properties": {
    "iso:country":"US",
    "sg:address":"3053 Rancho Vista Blvd",
    "sg:city":"Palmdale",
    "sg:classifiers":[
        {
            "category":"Retail",
            "subcategory":"Portrait Studio",
            "type":"Services"
        }
    ],
    "sg:phone":"+1 661 272 1849",
    "sg:postcode":"93551",
    "sg:province":"CA",
    "sg:tags":[
        "photographer"
    ],
    "wof:name":"L A Images Photography",
    "wof:placetype":"venue"
},
  "geometry": {"coordinates":[-118.18925,34.604709],"type":"Point"}
}