{
  "type": "Feature",
  "properties": {
    "addr:full":"10358 White Crane Rd Atwater CA 95301",
    "addr:housenumber":"10358",
    "addr:postcode":"95301",
    "addr:street":"White Crane Rd",
    "iso:country":"US",
    "sg:address":"10358 White Crane Rd",
    "sg:city":"Atwater",
    "sg:classifiers":[
        {
            "category":"Farming",
            "subcategory":"Farm",
            "type":"Manufacturing & Wholesale Goods"
        }
    ],
    "sg:phone":"+1 209 394 8305",
    "sg:postcode":"95301",
    "sg:province":"CA",
    "wof:name":"Jorge Antonio & Stella",
    "wof:placetype":"venue"
},
  "geometry": {"coordinates":[-120.67780399999999,37.3169],"type":"Point"}
}