{
  "type": "Feature",
  "properties": {
    "addr:full":"115 Capitola Ave Capitola CA 95010",
    "addr:housenumber":"115",
    "addr:postcode":"95010",
    "addr:street":"Capitola Ave",
    "iso:country":"US",
    "sg:address":"115 Capitola Ave",
    "sg:city":"Capitola",
    "sg:classifiers":[
        {
            "category":"Shopping",
            "subcategory":"Jewelry",
            "type":"Retail Goods"
        }
    ],
    "sg:phone":"+1 831 464 0318",
    "sg:postcode":"95010",
    "sg:province":"CA",
    "wof:name":"Capitola Reef",
    "wof:placetype":"venue"
},
  "geometry": {"coordinates":[-121.950996,36.972801],"type":"Point"}
}