{
  "type": "Feature",
  "properties": {
    "addr:full":"151 Kalmus Dr Ste 250 Costa Mesa CA 92626",
    "addr:housenumber":"151",
    "addr:postcode":"92626",
    "addr:street":"Kalmus Dr Ste 250",
    "iso:country":"US",
    "sg:address":"151 Kalmus Dr Ste 250",
    "sg:city":"Costa Mesa",
    "sg:classifiers":[
        {
            "category":"Real Estate",
            "subcategory":"Real Estate Services",
            "type":"Services"
        },
        {
            "category":"Organizations",
            "subcategory":"Non-profit Organization",
            "type":"Services"
        }
    ],
    "sg:phone":"+1 866 254 6868",
    "sg:postcode":"92626",
    "sg:province":"CA",
    "sg:tags":[
        "community",
        "service/non-profit"
    ],
    "wof:name":"National Home Advocacy Group",
    "wof:placetype":"venue"
},
  "geometry": {"coordinates":[-117.881573,33.672104],"type":"Point"}
}