{
  "type": "Feature",
  "properties": {
    "iso:country":"US",
    "sg:address":"1825 E Main St",
    "sg:city":"Visalia",
    "sg:classifiers":[
        {
            "category":"Real Estate",
            "subcategory":"Real Estate Agent",
            "type":"Services"
        }
    ],
    "sg:phone":"+1 559 733 9791",
    "sg:postcode":"93292",
    "sg:province":"CA",
    "sg:tags":[
        "appraiser"
    ],
    "wof:name":"Waterman & Assoc",
    "wof:placetype":"venue"
},
  "geometry": {"coordinates":[-119.269328,36.330131],"type":"Point"}
}