{
  "type": "Feature",
  "properties": {
    "iso:country":"US",
    "sg:address":"527 California Ter",
    "sg:city":"Pasadena",
    "sg:classifiers":[
        {
            "category":"Shopping",
            "type":"Retail Goods"
        }
    ],
    "sg:phone":"+1 626 449 7072",
    "sg:postcode":"91105",
    "sg:province":"CA",
    "sg:tags":[
        "art",
        "gallery",
        "dealer"
    ],
    "wof:name":"Metropolitan Fine Art Assoc",
    "wof:placetype":"venue"
},
  "geometry": {"coordinates":[-118.164861,34.137352],"type":"Point"}
}