{
  "type": "Feature",
  "properties": {
    "addr:full":"255 N El Cielo Rd Ste 140 Palm Springs CA 92262",
    "addr:housenumber":"255",
    "addr:postcode":"92262",
    "addr:street":"N El Cielo Rd Ste 140",
    "iso:country":"US",
    "sg:address":"255 N El Cielo Rd Ste 140",
    "sg:city":"Palm Springs",
    "sg:classifiers":[
        {
            "category":"Real Estate",
            "subcategory":"Real Estate Services",
            "type":"Services"
        }
    ],
    "sg:phone":"+1 760 320 2217",
    "sg:postcode":"92262",
    "sg:province":"CA",
    "sg:tags":[
        "management",
        "property"
    ],
    "wof:name":"James & Associates Inc",
    "wof:placetype":"venue"
},
  "geometry": {"coordinates":[-116.510775,33.825299],"type":"Point"}
}