{
  "type": "Feature",
  "properties": {
    "iso:country":"US",
    "sg:address":"255 W Napa St",
    "sg:city":"Sonoma",
    "sg:classifiers":[
        {
            "category":"Insurance",
            "subcategory":"Insurance Agent",
            "type":"Services"
        }
    ],
    "sg:phone":"+1 707 938 4998",
    "sg:postcode":"95476",
    "sg:province":"CA",
    "wof:name":"Christa Granton Insurance Svc",
    "wof:placetype":"venue"
},
  "geometry": {"coordinates":[-122.46231,38.29228],"type":"Point"}
}