{
  "type": "Feature",
  "properties": {
    "addr:full":"260 S California Ave Palo Alto CA 94306",
    "addr:housenumber":"260",
    "addr:postcode":"94306",
    "addr:street":"S California Ave",
    "iso:country":"US",
    "sg:address":"260 S California Ave",
    "sg:city":"Palo Alto",
    "sg:classifiers":[
        {
            "category":"Restaurant",
            "type":"Food & Drink"
        }
    ],
    "sg:menulink":"http://www.allmenus.com/ca/san-jose/48904-illusions-fayrouz-dining--entertainment/menu/",
    "sg:phone":"+1 650 321 6464",
    "sg:postcode":"94306",
    "sg:province":"CA",
    "sg:tags":[
        "middle",
        "eastern"
    ],
    "wof:name":"Illusions Fayrouz Dining & Entertainment",
    "wof:placetype":"venue"
},
  "geometry": {"coordinates":[-122.143579,37.427842],"type":"Point"}
}