{
  "type": "Feature",
  "properties": {
    "iso:country":"US",
    "sg:address":"912 W 223rd St",
    "sg:city":"Torrance",
    "sg:classifiers":[
        {
            "category":"Building & Trades",
            "subcategory":"Construction",
            "type":"Services"
        }
    ],
    "sg:phone":"+1 310 212 7111",
    "sg:postcode":"90502",
    "sg:province":"CA",
    "sg:tags":[
        "contractor"
    ],
    "wof:name":"P J Hindle Construction",
    "wof:placetype":"venue"
},
  "geometry": {"coordinates":[-118.29186900000001,33.824386],"type":"Point"}
}