{
  "type": "Feature",
  "properties": {
    "iso:country":"US",
    "sg:address":"3558 Round Barn Blvd",
    "sg:city":"Santa Rosa",
    "sg:classifiers":[
        {
            "category":"Professional",
            "subcategory":"Lawyer & Legal Services",
            "type":"Services"
        }
    ],
    "sg:phone":"+1 707 542 4200",
    "sg:postcode":"95403",
    "sg:province":"CA",
    "sg:tags":[
        "attorney"
    ],
    "wof:name":"Rachel M Dollar",
    "wof:placetype":"venue"
},
  "geometry": {"coordinates":[-122.72836599999999,38.4785],"type":"Point"}
}