{
  "type": "Feature",
  "properties": {
    "addr:full":"2540 A St San Diego CA 92102",
    "addr:housenumber":"2540",
    "addr:postcode":"92102",
    "addr:street":"A St",
    "iso:country":"US",
    "sg:address":"2540 A St",
    "sg:city":"San Diego",
    "sg:classifiers":[
        {
            "category":"Real Estate",
            "subcategory":"Real Estate Agent",
            "type":"Services"
        }
    ],
    "sg:phone":"+1 619 338 0100",
    "sg:postcode":"92102",
    "sg:province":"CA",
    "wof:name":"E G Chapman",
    "wof:placetype":"venue"
},
  "geometry": {"coordinates":[-117.138379,32.719027],"type":"Point"}
}