{
  "type": "Feature",
  "properties": {
    "addr:full":"1412 Rutsey Ct Folsom CA 95630",
    "addr:housenumber":"1412",
    "addr:postcode":"95630",
    "addr:street":"Rutsey Ct",
    "iso:country":"US",
    "sg:address":"1412 Rutsey Ct",
    "sg:city":"Folsom",
    "sg:classifiers":[
        {
            "category":"Manufacturing",
            "subcategory":"Printing",
            "type":"Manufacturing & Wholesale Goods"
        }
    ],
    "sg:phone":"+1 916 922 6155",
    "sg:postcode":"95630",
    "sg:province":"CA",
    "sg:tags":[
        "broker"
    ],
    "wof:name":"Form Source",
    "wof:placetype":"venue"
},
  "geometry": {"coordinates":[-121.128833,38.651457],"type":"Point"}
}