{
  "type": "Feature",
  "properties": {
    "addr:full":"415 Rolling Oaks Dr Thousand Oaks CA 91361",
    "addr:housenumber":"415",
    "addr:postcode":"91361",
    "addr:street":"Rolling Oaks Dr",
    "iso:country":"US",
    "sg:address":"415 Rolling Oaks Dr",
    "sg:city":"Thousand Oaks",
    "sg:classifiers":[
        {
            "category":"Health Services",
            "subcategory":"Podiatrist",
            "type":"Services"
        }
    ],
    "sg:phone":"+1 805 496 2383",
    "sg:postcode":"91361",
    "sg:province":"CA",
    "wof:name":"Feet First Podiatry",
    "wof:placetype":"venue"
},
  "geometry": {"coordinates":[-118.86688599999999,34.17456],"type":"Point"}
}