{
  "type": "Feature",
  "properties": {
    "iso:country":"US",
    "sg:address":"23700 Aetna St",
    "sg:city":"Woodland Hills",
    "sg:classifiers":[
        {
            "category":"Professional",
            "subcategory":"Employment Agencies",
            "type":"Services"
        }
    ],
    "sg:phone":"+1 818 597 1772",
    "sg:postcode":"91367",
    "sg:province":"CA",
    "sg:tags":[
        "opportunity"
    ],
    "wof:name":"Fine Resources",
    "wof:placetype":"venue"
},
  "geometry": {"coordinates":[-118.644301,34.180206],"type":"Point"}
}