{
  "type": "Feature",
  "properties": {
    "addr:full":"1053 E El Camino Real Sunnyvale CA 94087",
    "addr:housenumber":"1053",
    "addr:postcode":"94087",
    "addr:street":"E El Camino Real",
    "iso:country":"US",
    "sg:address":"1053 E El Camino Real",
    "sg:city":"Sunnyvale",
    "sg:classifiers":[
        {
            "category":"Shopping",
            "subcategory":"Jewelry",
            "type":"Retail Goods"
        }
    ],
    "sg:phone":"+1 408 249 3898",
    "sg:postcode":"94087",
    "sg:province":"CA",
    "wof:name":"Manisha Jewelers & Travels",
    "wof:placetype":"venue"
},
  "geometry": {"coordinates":[-122.00405600000001,37.352144],"type":"Point"}
}