{
  "type": "Feature",
  "properties": {
    "iso:country":"US",
    "sg:address":"12510 Lakeshore Dr",
    "sg:city":"Lakeside",
    "sg:classifiers":[
        {
            "category":"Restaurant",
            "type":"Food & Drink"
        }
    ],
    "sg:phone":"+1 619 443 0243",
    "sg:postcode":"92040",
    "sg:province":"CA",
    "wof:name":"Mi Cabana Mexican Food",
    "wof:placetype":"venue"
},
  "geometry": {"coordinates":[-116.92160800000001,32.859908],"type":"Point"}
}