{
  "type": "Feature",
  "properties": {
    "iso:country":"US",
    "sg:address":"3232 E 19th St",
    "sg:city":"Long Beach",
    "sg:classifiers":[
        {
            "category":"Professional",
            "type":"Services"
        }
    ],
    "sg:phone":"+1 562 498 9914",
    "sg:postcode":"90755",
    "sg:province":"CA",
    "wof:name":"Mother Land Connection",
    "wof:placetype":"venue"
},
  "geometry": {"coordinates":[-118.153409,33.791654],"type":"Point"}
}