{
  "type": "Feature",
  "properties": {
    "addr:full":"1212 E Main St Alhambra CA 91801",
    "addr:housenumber":"1212",
    "addr:postcode":"91801",
    "addr:street":"E Main St",
    "iso:country":"US",
    "sg:address":"1212 E Main St",
    "sg:city":"Alhambra",
    "sg:classifiers":[
        {
            "category":"Health Services",
            "subcategory":"Clinic",
            "type":"Services"
        }
    ],
    "sg:phone":"+1 626 451 9990",
    "sg:postcode":"91801",
    "sg:province":"CA",
    "sg:tags":[
        "home"
    ],
    "wof:name":"New Dimension Home Care",
    "wof:placetype":"venue"
},
  "geometry": {"coordinates":[-118.113966,34.101179],"type":"Point"}
}