{
  "type": "Feature",
  "properties": {
    "addr:full":"6854 Airport Rd Redding CA 96002",
    "addr:housenumber":"6854",
    "addr:postcode":"96002",
    "addr:street":"Airport Rd",
    "iso:country":"US",
    "sg:address":"6854 Airport Rd",
    "sg:city":"Redding",
    "sg:classifiers":[
        {
            "category":"Building & Trades",
            "subcategory":"Construction",
            "type":"Services"
        }
    ],
    "sg:phone":"+1 530 223 9150",
    "sg:postcode":"96002",
    "sg:province":"CA",
    "sg:tags":[
        "contractor"
    ],
    "wof:name":"Metz Hoyum Construction",
    "wof:placetype":"venue"
},
  "geometry": {"coordinates":[-122.302762,40.504505],"type":"Point"}
}