{
  "type": "Feature",
  "properties": {
    "addr:full":"SOMA San Francisco CA 94103",
    "addr:postcode":"94103",
    "iso:country":"US",
    "sg:address":"SOMA",
    "sg:city":"San Francisco",
    "sg:classifiers":[
        {
            "category":"Shopping",
            "subcategory":"Pets & Pet Supplies",
            "type":"Retail Goods"
        }
    ],
    "sg:phone":"+1 415 939 7214",
    "sg:postcode":"94103",
    "sg:province":"CA",
    "sg:tags":[
        "walker",
        "dog"
    ],
    "sg:website":"walkindogs@aol.com",
    "wof:name":"Dog Gone Walkin",
    "wof:placetype":"venue"
},
  "geometry": {"coordinates":[-122.40054000000001,37.777453],"type":"Point"}
}