{
  "type": "Feature",
  "properties": {
    "addr:full":"1530 E Washington St Long Beach CA 90805",
    "addr:housenumber":"1530",
    "addr:postcode":"90805",
    "addr:street":"E Washington St",
    "iso:country":"US",
    "sg:address":"1530 E Washington St",
    "sg:city":"Long Beach",
    "sg:classifiers":[
        {
            "category":"Wholesale",
            "subcategory":"Hardware",
            "type":"Manufacturing & Wholesale Goods"
        }
    ],
    "sg:phone":"+1 562 428 1277",
    "sg:postcode":"90805",
    "sg:province":"CA",
    "wof:name":"Danrick Fasteners",
    "wof:placetype":"venue"
},
  "geometry": {"coordinates":[-118.176062,33.855133],"type":"Point"}
}