{
  "type": "Feature",
  "properties": {
    "iso:country":"US",
    "sg:address":"3429 W Pomona Blvd",
    "sg:city":"Pomona",
    "sg:classifiers":[
        {
            "category":"Home & Garden",
            "subcategory":"Building Materials",
            "type":"Retail Goods"
        }
    ],
    "sg:phone":"+1 909 594 9194",
    "sg:postcode":"91768",
    "sg:province":"CA",
    "sg:tags":[
        "marble"
    ],
    "wof:name":"AED Arts & Floor",
    "wof:placetype":"venue"
},
  "geometry": {"coordinates":[-117.811913,34.046551],"type":"Point"}
}