{
  "type": "Feature",
  "properties": {
    "addr:full":"786 Foxwood Dr Oceanside CA 92057",
    "addr:housenumber":"786",
    "addr:postcode":"92057",
    "addr:street":"Foxwood Dr",
    "iso:country":"US",
    "sg:address":"786 Foxwood Dr",
    "sg:city":"Oceanside",
    "sg:classifiers":[
        {
            "category":"Professional",
            "subcategory":"Management & Consulting",
            "type":"Services"
        }
    ],
    "sg:phone":"+1 760 721 7866",
    "sg:postcode":"92057",
    "sg:province":"CA",
    "sg:tags":[
        "marketing",
        "who",
        "sales",
        "palm",
        "preserved",
        "distribution"
    ],
    "wof:name":"Forever Preserved",
    "wof:placetype":"venue"
},
  "geometry": {"coordinates":[-117.319227,33.248653],"type":"Point"}
}