{
  "type": "Feature",
  "properties": {
    "addr:full":"2701 Maxwell Way Fairfield CA 94534",
    "addr:housenumber":"2701",
    "addr:postcode":"94534",
    "addr:street":"Maxwell Way",
    "iso:country":"US",
    "sg:address":"2701 Maxwell Way",
    "sg:city":"Fairfield",
    "sg:classifiers":[
        {
            "category":"Freight",
            "type":"Transportation"
        }
    ],
    "sg:phone":"+1 707 421 2052",
    "sg:postcode":"94534",
    "sg:province":"CA",
    "sg:tags":[
        "warehouse",
        "self",
        "storage"
    ],
    "wof:name":"ASAP Warehouse",
    "wof:placetype":"venue"
},
  "geometry": {"coordinates":[-122.079942,38.231021],"type":"Point"}
}