{
  "type": "Feature",
  "properties": {
    "addr:full":"1250 Churchill Downs Ave Woodland CA 95776",
    "addr:housenumber":"1250",
    "addr:postcode":"95776",
    "addr:street":"Churchill Downs Ave",
    "iso:country":"US",
    "sg:address":"1250 Churchill Downs Ave",
    "sg:city":"Woodland",
    "sg:classifiers":[
        {
            "category":"Wholesale",
            "subcategory":"Meat",
            "type":"Manufacturing & Wholesale Goods"
        }
    ],
    "sg:phone":"+1 530 662 4298",
    "sg:postcode":"95776",
    "sg:province":"CA",
    "wof:name":"Afc",
    "wof:placetype":"venue"
},
  "geometry": {"coordinates":[-121.759094,38.698748],"type":"Point"}
}