{
  "type": "Feature",
  "properties": {
    "iso:country":"US",
    "sg:address":"1606 Davis St",
    "sg:city":"Chico",
    "sg:classifiers":[
        {
            "category":"Building & Trades",
            "subcategory":"Electrical",
            "type":"Services"
        }
    ],
    "sg:phone":"+1 530 345 8734",
    "sg:postcode":"95928",
    "sg:province":"CA",
    "sg:tags":[
        "electrical"
    ],
    "wof:name":"Villanueva Elec Cnstr Inc",
    "wof:placetype":"venue"
},
  "geometry": {"coordinates":[-121.821951,39.726119],"type":"Point"}
}