{
  "type": "Feature",
  "properties": {
    "addr:full":"410 Elm Ave Larkspur CA 94939",
    "addr:housenumber":"410",
    "addr:postcode":"94939",
    "addr:street":"Elm Ave",
    "iso:country":"US",
    "sg:address":"410 Elm Ave",
    "sg:city":"Larkspur",
    "sg:classifiers":[
        {
            "category":"Professional",
            "subcategory":"Testing Lab",
            "type":"Services"
        }
    ],
    "sg:phone":"+1 415 927 9038",
    "sg:postcode":"94939",
    "sg:province":"CA",
    "sg:tags":[
        "asbestos"
    ],
    "wof:name":"Monte Deignan & Assoc",
    "wof:placetype":"venue"
},
  "geometry": {"coordinates":[-122.52915900000001,37.932722],"type":"Point"}
}