{
  "type": "Feature",
  "properties": {
    "iso:country":"US",
    "sg:address":"1036 Maple Ave",
    "sg:city":"Los Angeles",
    "sg:classifiers":[
        {
            "category":"Freight",
            "type":"Transportation"
        },
        {
            "category":"Wholesale",
            "subcategory":"Non-durable Goods",
            "type":"Manufacturing & Wholesale Goods"
        }
    ],
    "sg:phone":"+1 213 748 7975",
    "sg:postcode":"90015",
    "sg:province":"CA",
    "wof:name":"M Y Cargo Express",
    "wof:placetype":"venue"
},
  "geometry": {"coordinates":[-118.254758,34.037558],"type":"Point"}
}