{
  "type": "Feature",
  "properties": {
    "addr:full":"552 W 182nd St Gardena CA 90248",
    "addr:housenumber":"552",
    "addr:postcode":"90248",
    "addr:street":"W 182Nd St",
    "iso:country":"US",
    "sg:address":"552 W 182nd St",
    "sg:city":"Gardena",
    "sg:classifiers":[
        {
            "category":"Wholesale",
            "subcategory":"Stationery",
            "type":"Manufacturing & Wholesale Goods"
        }
    ],
    "sg:phone":"+1 323 321 6826",
    "sg:postcode":"90248",
    "sg:province":"CA",
    "sg:tags":[
        "packaging",
        "material"
    ],
    "wof:name":"Custo-Pak",
    "wof:placetype":"venue"
},
  "geometry": {"coordinates":[-118.28363400000001,33.869785],"type":"Point"}
}