{
  "type": "Feature",
  "properties": {
    "addr:full":"2313 Meadowbrook Rd Sacramento CA 95825",
    "addr:housenumber":"2313",
    "addr:postcode":"95825",
    "addr:street":"Meadowbrook Rd",
    "iso:country":"US",
    "sg:address":"2313 Meadowbrook Rd",
    "sg:city":"Sacramento",
    "sg:classifiers":[
        {
            "category":"Structure",
            "subcategory":"Office Building",
            "type":"Public Place"
        }
    ],
    "sg:phone":"+1 916 483 0501",
    "sg:postcode":"95825",
    "sg:province":"CA",
    "sg:tags":[
        "park"
    ],
    "wof:name":"Olson Properties",
    "wof:placetype":"venue"
},
  "geometry": {"coordinates":[-121.39506,38.607364],"type":"Point"}
}