{
  "type": "Feature",
  "properties": {
    "addr:full":"940 Hilltop Dr Chula Vista CA 91911",
    "addr:housenumber":"940",
    "addr:postcode":"91911",
    "addr:street":"Hilltop Dr",
    "iso:country":"US",
    "sg:address":"940 Hilltop Dr",
    "sg:city":"Chula Vista",
    "sg:classifiers":[
        {
            "category":"Social Services",
            "subcategory":"Child Care",
            "type":"Services"
        },
        {
            "category":"Organizations",
            "subcategory":"Religious Organization",
            "type":"Services"
        }
    ],
    "sg:phone":"+1 619 426 2292",
    "sg:postcode":"91911",
    "sg:province":"CA",
    "sg:tags":[
        "kindergarten",
        "academic",
        "school",
        "elementary",
        "church"
    ],
    "sg:website":"www.cvpres.org",
    "wof:name":"Chula Vista Presbyterian Preschool",
    "wof:placetype":"venue"
},
  "geometry": {"coordinates":[-117.059195,32.623027],"type":"Point"}
}