{
  "type": "Feature",
  "properties": {
    "addr:full":"7610 Hazard Center Dr San Diego CA 92108",
    "addr:housenumber":"7610",
    "addr:postcode":"92108",
    "addr:street":"Hazard Center Dr",
    "iso:country":"US",
    "sg:address":"7610 Hazard Center Dr",
    "sg:city":"San Diego",
    "sg:classifiers":[
        {
            "category":"Restaurant",
            "type":"Food & Drink"
        }
    ],
    "sg:menulink":"http://www.allmenus.com/ca/san-diego/25278-joes-crab-shack/menu/",
    "sg:phone":"+1 619 574 8617",
    "sg:postcode":"92108",
    "sg:province":"CA",
    "sg:tags":[
        "seafood",
        "american"
    ],
    "wof:name":"Joe's Crab Shack",
    "wof:placetype":"venue"
},
  "geometry": {"coordinates":[-117.15715299999999,32.770831],"type":"Point"}
}