{
  "type": "Feature",
  "properties": {
    "iso:country":"US",
    "sg:address":"14241 Ventura Blvd Ste 104",
    "sg:city":"Sherman Oaks",
    "sg:classifiers":[
        {
            "category":"Wholesale",
            "subcategory":"Home Furnishings",
            "type":"Manufacturing & Wholesale Goods"
        },
        {
            "category":"Home & Garden",
            "subcategory":"Building Materials",
            "type":"Retail Goods"
        },
        {
            "category":"Building & Trades",
            "subcategory":"Construction",
            "type":"Services"
        },
        {
            "category":"Home & Garden",
            "subcategory":"Carpets & Floor Coverings",
            "type":"Retail Goods"
        }
    ],
    "sg:phone":"+1 818 986 4772",
    "sg:postcode":"91423",
    "sg:province":"CA",
    "sg:tags":[
        "blind",
        "fixture",
        "mattress",
        "equipment",
        "lighting",
        "shade",
        "interior",
        "design"
    ],
    "wof:name":"Goochey's Furnishing & Lighting",
    "wof:placetype":"venue"
},
  "geometry": {"coordinates":[-118.443001,34.150002],"type":"Point"}
}