{
  "type": "Feature",
  "properties": {
    "addr:full":"8300 Rex Rd Pico Rivera CA 90660",
    "addr:housenumber":"8300",
    "addr:postcode":"90660",
    "addr:street":"Rex Rd",
    "iso:country":"US",
    "sg:address":"8300 Rex Rd",
    "sg:city":"Pico Rivera",
    "sg:classifiers":[
        {
            "category":"Professional",
            "subcategory":"Business Services",
            "type":"Services"
        }
    ],
    "sg:phone":"+1 562 948 1288",
    "sg:postcode":"90660",
    "sg:province":"CA",
    "sg:tags":[
        "management"
    ],
    "wof:name":"Avid Corporation",
    "wof:placetype":"venue"
},
  "geometry": {"coordinates":[-118.110874,33.982589],"type":"Point"}
}