{
  "type": "Feature",
  "properties": {
    "iso:country":"US",
    "sg:address":"1400 Bell St",
    "sg:city":"Sacramento",
    "sg:classifiers":[
        {
            "category":"Education",
            "subcategory":"School",
            "type":"Public Place"
        }
    ],
    "sg:phone":"+1 916 971 7015",
    "sg:postcode":"95825",
    "sg:province":"CA",
    "wof:name":"Sierra Nueva Continuation",
    "wof:placetype":"venue"
},
  "geometry": {"coordinates":[-121.410645,38.589731],"type":"Point"}
}