{
  "type": "Feature",
  "properties": {
    "iso:country":"US",
    "sg:address":"12925 Orangeburg Ave",
    "sg:city":"San Diego",
    "sg:classifiers":[
        {
            "category":"Professional",
            "subcategory":"Accounting & Tax Preparation",
            "type":"Services"
        }
    ],
    "sg:phone":"+1 858 780 1889",
    "sg:postcode":"92129",
    "sg:province":"CA",
    "sg:tags":[
        "bookkeeping",
        "general"
    ],
    "wof:name":"Fong & Assoc Inc",
    "wof:placetype":"venue"
},
  "geometry": {"coordinates":[-117.119763,32.954353],"type":"Point"}
}