{
  "type": "Feature",
  "properties": {
    "iso:country":"US",
    "sg:address":"40 Mitchell Blvd",
    "sg:city":"San Rafael",
    "sg:classifiers":[
        {
            "category":"Professional",
            "subcategory":"Computer Services",
            "type":"Services"
        }
    ],
    "sg:phone":"+1 415 492 0120",
    "sg:postcode":"94903",
    "sg:province":"CA",
    "sg:tags":[
        "processing",
        "datum"
    ],
    "sg:website":"www.betabreakers.com",
    "wof:name":"Beta Breakers",
    "wof:placetype":"venue"
},
  "geometry": {"coordinates":[-122.538898,38.01698],"type":"Point"}
}