{
  "type": "Feature",
  "properties": {
    "addr:full":"2408 Gosford Rd Bakersfield CA 93309",
    "addr:housenumber":"2408",
    "addr:postcode":"93309",
    "addr:street":"Gosford Rd",
    "iso:country":"US",
    "sg:address":"2408 Gosford Rd",
    "sg:city":"Bakersfield",
    "sg:classifiers":[
        {
            "category":"Real Estate",
            "subcategory":"Real Estate Operator",
            "type":"Services"
        }
    ],
    "sg:phone":"+1 661 836 3055",
    "sg:postcode":"93309",
    "sg:province":"CA",
    "sg:tags":[
        "apartment"
    ],
    "wof:name":"Peppermill II",
    "wof:placetype":"venue"
},
  "geometry": {"coordinates":[-119.092091,35.331153],"type":"Point"}
}