{
  "type": "Feature",
  "properties": {
    "addr:full":"4900 Triggs St Commerce CA 90022",
    "addr:postcode":"4900;90022",
    "addr:street":"Triggs St",
    "iso:country":"US",
    "sg:address":"4900 Triggs St",
    "sg:city":"Commerce",
    "sg:classifiers":[
        {
            "category":"Home & Garden",
            "subcategory":"Furniture",
            "type":"Retail Goods"
        }
    ],
    "sg:phone":"+1 323 526 9030",
    "sg:postcode":"90022",
    "sg:province":"CA",
    "sg:tags":[
        "store"
    ],
    "wof:name":"Leaders Centro Del Hogar",
    "wof:placetype":"venue"
},
  "geometry": {"coordinates":[-118.163089,34.011864],"type":"Point"}
}