{
  "type": "Feature",
  "properties": {
    "addr:full":"42 N Lake Cir Antioch CA 94509",
    "addr:housenumber":"42",
    "addr:postcode":"ca 94509",
    "addr:street":"N Lake Cir",
    "iso:country":"US",
    "sg:address":"42 N Lake Cir",
    "sg:city":"Antioch",
    "sg:classifiers":[
        {
            "category":"Professional",
            "subcategory":"Management & Consulting",
            "type":"Services"
        }
    ],
    "sg:phone":"+1 925 757 0705",
    "sg:postcode":"94509",
    "sg:province":"CA",
    "sg:tags":[
        "consultant"
    ],
    "wof:name":"GEM Consulting",
    "wof:placetype":"venue"
},
  "geometry": {"coordinates":[-121.793707,38.009506],"type":"Point"}
}