{
  "type": "Feature",
  "properties": {
    "iso:country":"US",
    "sg:address":"310 Orange Dr",
    "sg:city":"Vacaville",
    "sg:classifiers":[
        {
            "category":"Professional",
            "subcategory":"Management & Consulting",
            "type":"Services"
        }
    ],
    "sg:phone":"+1 707 451 2367",
    "sg:postcode":"95687",
    "sg:province":"CA",
    "sg:tags":[
        "consultant"
    ],
    "wof:name":"URS Consultants",
    "wof:placetype":"venue"
},
  "geometry": {"coordinates":[-121.954036,38.370651],"type":"Point"}
}