{
  "type": "Feature",
  "properties": {
    "iso:country":"US",
    "sg:address":"231 N Glendale Ave",
    "sg:city":"Glendale",
    "sg:classifiers":[
        {
            "category":"Shopping",
            "subcategory":"Pets & Pet Supplies",
            "type":"Retail Goods"
        }
    ],
    "sg:phone":"+1 818 548 0411",
    "sg:postcode":"91206",
    "sg:province":"CA",
    "sg:tags":[
        "store"
    ],
    "wof:name":"Petco",
    "wof:placetype":"venue"
},
  "geometry": {"coordinates":[-118.246002,34.148701],"type":"Point"}
}