{
  "type": "Feature",
  "properties": {
    "iso:country":"US",
    "sg:address":"9555 N Woodrow Ave",
    "sg:city":"Fresno",
    "sg:classifiers":[
        {
            "category":"Building & Trades",
            "subcategory":"Plumbing",
            "type":"Services"
        }
    ],
    "sg:phone":"+1 559 433 1879",
    "sg:postcode":"93720",
    "sg:province":"CA",
    "sg:tags":[
        "plumbing",
        "contractor"
    ],
    "wof:name":"Plumbing Co",
    "wof:placetype":"venue"
},
  "geometry": {"coordinates":[-119.745282,36.874162],"type":"Point"}
}