{
  "type": "Feature",
  "properties": {
    "iso:country":"US",
    "sg:address":"1039 E. Valley Blvd Ste B106",
    "sg:city":"San Gabriel",
    "sg:classifiers":[
        {
            "category":"Health Services",
            "subcategory":"Clinic",
            "type":"Services"
        },
        {
            "category":"Health Services",
            "subcategory":"Health Practitioner",
            "type":"Services"
        }
    ],
    "sg:phone":"+1 626 569 1800",
    "sg:postcode":"91776",
    "sg:province":"CA",
    "sg:tags":[
        "acupuncture",
        "loss",
        "weight"
    ],
    "sg:website":"www.cyyacupuncture.com",
    "wof:name":"C Y Y Acupuncture & Herbs Clinic",
    "wof:placetype":"venue"
},
  "geometry": {"coordinates":[-118.085286,34.080405],"type":"Point"}
}