{
  "type": "Feature",
  "properties": {
    "addr:full":"1238 Wall St Los Angeles CA 90015",
    "addr:housenumber":"1238",
    "addr:postcode":"90015",
    "addr:street":"Wall St",
    "iso:country":"US",
    "sg:address":"1238 Wall St",
    "sg:city":"Los Angeles",
    "sg:classifiers":[
        {
            "category":"Wholesale",
            "subcategory":"Apparel",
            "type":"Manufacturing & Wholesale Goods"
        }
    ],
    "sg:phone":"+1 213 746 9858",
    "sg:postcode":"90015",
    "sg:province":"CA",
    "sg:tags":[
        "clothing",
        "women's"
    ],
    "wof:name":"Heero Kids",
    "wof:placetype":"venue"
},
  "geometry": {"coordinates":[-118.25599699999999,34.0341],"type":"Point"}
}