{
  "type": "Feature",
  "properties": {
    "iso:country":"US",
    "sg:address":"10340 Orr & Day Road",
    "sg:city":"Santa Fe Springs",
    "sg:classifiers":[
        {
            "category":"Sports & Exercise",
            "subcategory":"Tennis Court",
            "type":"Entertainment"
        }
    ],
    "sg:phone":"+1 562 929 6341",
    "sg:postcode":"90670",
    "sg:province":"CA",
    "wof:name":"Center Court",
    "wof:placetype":"venue"
},
  "geometry": {"coordinates":[-118.090608,33.918523],"type":"Point"}
}