{
  "type": "Feature",
  "properties": {
    "addr:full":"775 Allen Dr Corona CA 92879",
    "addr:housenumber":"775",
    "addr:postcode":"92879",
    "addr:street":"Allen Dr",
    "iso:country":"US",
    "sg:address":"775 Allen Dr",
    "sg:city":"Corona",
    "sg:classifiers":[
        {
            "category":"Professional",
            "subcategory":"Management & Consulting",
            "type":"Services"
        }
    ],
    "sg:phone":"+1 951 735 5107",
    "sg:postcode":"92879",
    "sg:province":"CA",
    "sg:tags":[
        "consultant"
    ],
    "wof:name":"Biran's Foot Consulting Inc",
    "wof:placetype":"venue"
},
  "geometry": {"coordinates":[-117.54365799999999,33.893078],"type":"Point"}
}