{
  "type": "Feature",
  "properties": {
    "addr:full":"1255 Allston Way Berkeley CA 94702",
    "addr:housenumber":"1255",
    "addr:postcode":"94702",
    "addr:street":"Allston Way",
    "iso:country":"US",
    "sg:address":"1255 Allston Way",
    "sg:city":"Berkeley",
    "sg:classifiers":[
        {
            "category":"Professional",
            "type":"Services"
        }
    ],
    "sg:phone":"+1 510 845 3499",
    "sg:postcode":"94702",
    "sg:province":"CA",
    "sg:tags":[
        "establishment"
    ],
    "wof:name":"In Dulci Jubilo Inc",
    "wof:placetype":"venue"
},
  "geometry": {"coordinates":[-122.286648,37.867085],"type":"Point"}
}