{
  "type": "Feature",
  "properties": {
    "iso:country":"US",
    "sg:address":"787 N Palm Canyon Dr",
    "sg:city":"Palm Springs",
    "sg:classifiers":[
        {
            "category":"Restaurant",
            "type":"Food & Drink"
        }
    ],
    "sg:phone":"+1 760 323 4527",
    "sg:postcode":"92262",
    "sg:province":"CA",
    "wof:name":"Thai Kitchen II",
    "wof:placetype":"venue"
},
  "geometry": {"coordinates":[-116.546837,33.833874],"type":"Point"}
}