{
  "type": "Feature",
  "properties": {
    "addr:full":"6565 Trigo Rd Isla Vista CA 93117",
    "addr:housenumber":"6565",
    "addr:postcode":"93117",
    "addr:street":"Trigo Rd Isla",
    "iso:country":"US",
    "sg:address":"6565 Trigo Rd",
    "sg:city":"Isla Vista",
    "sg:classifiers":[
        {
            "category":"Shopping",
            "type":"Retail Goods"
        }
    ],
    "sg:phone":"+1 805 968 0424",
    "sg:postcode":"93117",
    "sg:province":"CA",
    "sg:tags":[
        "pet",
        "shop"
    ],
    "wof:name":"Ultimate Aquarium",
    "wof:placetype":"venue"
},
  "geometry": {"coordinates":[-119.85833,34.411064],"type":"Point"}
}