{
  "type": "Feature",
  "properties": {
    "iso:country":"US",
    "sg:address":"2415 E Washington Blvd",
    "sg:city":"Los Angeles",
    "sg:classifiers":[
        {
            "category":"Retail",
            "subcategory":"Auto Repair",
            "type":"Services"
        }
    ],
    "sg:phone":"+1 323 588 7025",
    "sg:postcode":"90021",
    "sg:province":"CA",
    "sg:tags":[
        "body",
        "shop",
        "paint"
    ],
    "wof:name":"Quality Fleet & Truck Centers",
    "wof:placetype":"venue"
},
  "geometry": {"coordinates":[-118.22808499999999,34.018565],"type":"Point"}
}