{
  "type": "Feature",
  "properties": {
    "iso:country":"US",
    "sg:address":"1345 N Dynamics St",
    "sg:city":"Anaheim",
    "sg:classifiers":[
        {
            "category":"Professional",
            "subcategory":"Testing Lab",
            "type":"Services"
        }
    ],
    "sg:phone":"+1 714 524 5588",
    "sg:postcode":"92806",
    "sg:province":"CA",
    "sg:tags":[
        "biological",
        "laboratory"
    ],
    "wof:name":"Nutralab",
    "wof:placetype":"venue"
},
  "geometry": {"coordinates":[-117.85216800000001,33.860493],"type":"Point"}
}