{
  "type": "Feature",
  "properties": {
    "addr:full":"8070 Soquel Dr Aptos CA 95003",
    "addr:housenumber":"8070",
    "addr:postcode":"ca 95003",
    "addr:street":"Soquel Dr",
    "iso:country":"US",
    "sg:address":"8070 Soquel Dr",
    "sg:city":"Aptos",
    "sg:classifiers":[
        {
            "category":"Real Estate",
            "subcategory":"Real Estate Services",
            "type":"Services"
        }
    ],
    "sg:phone":"+1 831 688 6878",
    "sg:postcode":"95003",
    "sg:province":"CA",
    "sg:tags":[
        "company",
        "title"
    ],
    "wof:name":"Old Republic Title Co",
    "wof:placetype":"venue"
},
  "geometry": {"coordinates":[-121.899287,36.976049],"type":"Point"}
}