{
  "type": "Feature",
  "properties": {
    "iso:country":"US",
    "sg:address":"250 Old Ranch Rd",
    "sg:city":"City Of Industry",
    "sg:classifiers":[
        {
            "category":"Wholesale",
            "subcategory":"Durable Goods & Equipment",
            "type":"Manufacturing & Wholesale Goods"
        }
    ],
    "sg:phone":"+1 909 839 0018",
    "sg:postcode":"91789",
    "sg:province":"CA",
    "sg:tags":[
        "importer"
    ],
    "wof:name":"Gemini Food Corp",
    "wof:placetype":"venue"
},
  "geometry": {"coordinates":[-117.837843,34.018327],"type":"Point"}
}