{
  "type": "Feature",
  "properties": {
    "iso:country":"US",
    "sg:address":"13235 Paramount Blvd",
    "sg:city":"South Gate",
    "sg:classifiers":[
        {
            "category":"Fast Food",
            "type":"Food & Drink"
        }
    ],
    "sg:phone":"+1 562 531 7775",
    "sg:postcode":"90280",
    "sg:province":"CA",
    "sg:tags":[
        "burger"
    ],
    "sg:website":"www.petes.sg.menuclub.com",
    "wof:name":"Pete's Burger",
    "wof:placetype":"venue"
},
  "geometry": {"coordinates":[-118.158645,33.915154],"type":"Point"}
}