{
  "type": "Feature",
  "properties": {
    "addr:full":"1474 Encinitas Blvd Encinitas CA 92024",
    "addr:housenumber":"1474",
    "addr:postcode":"92024",
    "addr:street":"Encinitas Blvd",
    "iso:country":"US",
    "sg:address":"1474 Encinitas Blvd",
    "sg:city":"Encinitas",
    "sg:classifiers":[
        {
            "category":"Sports & Exercise",
            "subcategory":"Gym",
            "type":"Entertainment"
        }
    ],
    "sg:phone":"+1 760 634 0343",
    "sg:postcode":"92024",
    "sg:province":"CA",
    "sg:tags":[
        "personal",
        "trainer"
    ],
    "wof:name":"Nutrifitt Fitness & Nutrition",
    "wof:placetype":"venue"
},
  "geometry": {"coordinates":[-117.259562,33.045916],"type":"Point"}
}