{
  "type": "Feature",
  "properties": {
    "iso:country":"US",
    "sg:address":"134 Rhoades Way",
    "sg:city":"Folsom",
    "sg:classifiers":[
        {
            "category":"Building & Trades",
            "subcategory":"Construction",
            "type":"Services"
        }
    ],
    "sg:phone":"+1 916 203 2663",
    "sg:postcode":"95630",
    "sg:province":"CA",
    "sg:tags":[
        "management"
    ],
    "wof:name":"Boyer Construction Management Group",
    "wof:placetype":"venue"
},
  "geometry": {"coordinates":[-121.135099,38.68153],"type":"Point"}
}