{
  "type": "Feature",
  "properties": {
    "addr:full":"568 66th St Oakland CA 94609",
    "addr:housenumber":"568",
    "addr:postcode":"94609",
    "addr:street":"66Th St",
    "iso:country":"US",
    "sg:address":"568 66th St",
    "sg:city":"Oakland",
    "sg:classifiers":[
        {
            "category":"Organizations",
            "subcategory":"Non-profit Organization",
            "type":"Services"
        }
    ],
    "sg:phone":"+1 510 547 9004",
    "sg:postcode":"94609",
    "sg:province":"CA",
    "sg:tags":[
        "information",
        "alcoholism",
        "treatment"
    ],
    "wof:name":"Universal Blossom Of The Aged",
    "wof:placetype":"venue"
},
  "geometry": {"coordinates":[-122.262826,37.851788],"type":"Point"}
}