{
  "type": "Feature",
  "properties": {
    "addr:full":"7107 Alabama Ave Canoga Park CA 91303",
    "addr:housenumber":"7107",
    "addr:postcode":"91303",
    "addr:street":"Alabama Ave",
    "iso:country":"US",
    "sg:address":"7107 Alabama Ave",
    "sg:city":"Canoga Park",
    "sg:classifiers":[
        {
            "category":"Building & Trades",
            "subcategory":"Construction",
            "type":"Services"
        }
    ],
    "sg:phone":"+1 818 347 1941",
    "sg:postcode":"91303",
    "sg:province":"CA",
    "sg:tags":[
        "roofing",
        "contractor"
    ],
    "wof:name":"Falcone West Valley Roofers",
    "wof:placetype":"venue"
},
  "geometry": {"coordinates":[-118.59909399999999,34.200913],"type":"Point"}
}