{
  "type": "Feature",
  "properties": {
    "iso:country":"US",
    "sg:address":"7107 Alabama Ave",
    "sg:city":"Canoga Park",
    "sg:classifiers":[
        {
            "category":"Building & Trades",
            "subcategory":"Construction",
            "type":"Services"
        }
    ],
    "sg:phone":"+1 818 347 1941",
    "sg:postcode":"91303",
    "sg:province":"CA",
    "sg:tags":[
        "roofing",
        "contractor"
    ],
    "wof:name":"Falcone West Valley Roofers",
    "wof:placetype":"venue"
},
  "geometry": {"coordinates":[-118.599094,34.200913],"type":"Point"}
}