{
  "type": "Feature",
  "properties": {
    "iso:country":"US",
    "sg:address":"30 Otis St",
    "sg:city":"San Francisco",
    "sg:classifiers":[
        {
            "category":"Restaurant",
            "type":"Food & Drink"
        }
    ],
    "sg:phone":"+1 530 577 0599",
    "sg:postcode":"94103",
    "sg:province":"CA",
    "sg:tags":[
        "cafe"
    ],
    "wof:name":"Cafe Glace",
    "wof:placetype":"venue"
},
  "geometry": {"coordinates":[-122.418823,37.77306],"type":"Point"}
}