{
  "type": "Feature",
  "properties": {
    "addr:full":"14915 Olympic Dr Clearlake CA 95422",
    "addr:housenumber":"14915",
    "addr:postcode":"95422",
    "addr:street":"Olympic Dr",
    "iso:country":"US",
    "sg:address":"14915 Olympic Dr",
    "sg:city":"Clearlake",
    "sg:classifiers":[
        {
            "category":"Professional",
            "type":"Services"
        }
    ],
    "sg:phone":"+1 707 994 3879",
    "sg:postcode":"95422",
    "sg:province":"CA",
    "sg:tags":[
        "establishment"
    ],
    "wof:name":"Autocon Mixing Systems",
    "wof:placetype":"venue"
},
  "geometry": {"coordinates":[-122.632685,38.961745],"type":"Point"}
}