{
  "type": "Feature",
  "properties": {
    "addr:full":"232 E Carson St Colusa CA 95932",
    "addr:housenumber":"232",
    "addr:postcode":"95932",
    "addr:street":"E Carson St",
    "iso:country":"US",
    "sg:address":"232 E Carson St",
    "sg:city":"Colusa",
    "sg:classifiers":[
        {
            "category":"Real Estate",
            "subcategory":"Real Estate Operator",
            "type":"Services"
        }
    ],
    "sg:phone":"+1 530 458 4960",
    "sg:postcode":"95932",
    "sg:province":"CA",
    "sg:tags":[
        "apartment"
    ],
    "wof:name":"Frank Eskaton Jaconetti Manor",
    "wof:placetype":"venue"
},
  "geometry": {"coordinates":[-122.007666,39.206214],"type":"Point"}
}