{
  "type": "Feature",
  "properties": {
    "iso:country":"US",
    "sg:address":"2022 Cliff Dr",
    "sg:city":"Santa Barbara",
    "sg:classifiers":[
        {
            "category":"Personal",
            "type":"Services"
        }
    ],
    "sg:phone":"+1 805 683 0845",
    "sg:postcode":"93109",
    "sg:province":"CA",
    "sg:tags":[
        "therapist",
        "massage"
    ],
    "wof:name":"Protouch",
    "wof:placetype":"venue"
},
  "geometry": {"coordinates":[-119.725838,34.402455],"type":"Point"}
}