{
  "type": "Feature",
  "properties": {
    "iso:country":"US",
    "sg:address":"2310 W Cleveland Ave",
    "sg:city":"Madera",
    "sg:classifiers":[
        {
            "category":"Restaurant",
            "type":"Food & Drink"
        }
    ],
    "sg:menulink":"http://www.allmenus.com/ca/madera/163516-rallys/menu/",
    "sg:phone":"+1 559 666 2137",
    "sg:postcode":"93637",
    "sg:province":"CA",
    "sg:tags":[
        "sandwich",
        "dog",
        "burger",
        "hot",
        "wrap",
        "american"
    ],
    "wof:name":"Rally's",
    "wof:placetype":"venue"
},
  "geometry": {"coordinates":[-120.086257,36.974517],"type":"Point"}
}