{
  "type": "Feature",
  "properties": {
    "iso:country":"US",
    "sg:address":"800 S White Rd",
    "sg:city":"San Jose",
    "sg:classifiers":[
        {
            "category":"Real Estate",
            "subcategory":"Real Estate Agent",
            "type":"Services"
        }
    ],
    "sg:phone":"+1 408 928 5770",
    "sg:postcode":"95127",
    "sg:province":"CA",
    "wof:name":"Continental Real Estate",
    "wof:placetype":"venue"
},
  "geometry": {"coordinates":[-121.82240400000001,37.359839],"type":"Point"}
}