{
  "type": "Feature",
  "properties": {
    "iso:country":"US",
    "sg:address":"6454 Stockton Boulevard",
    "sg:city":"Sacramento",
    "sg:classifiers":[
        {
            "category":"Personal",
            "subcategory":"Skin Care",
            "type":"Services"
        }
    ],
    "sg:phone":"+1 916 421 7836",
    "sg:postcode":"95823",
    "sg:province":"CA",
    "wof:name":"Mai's Facial",
    "wof:placetype":"venue"
},
  "geometry": {"coordinates":[-121.43489,38.508415],"type":"Point"}
}