{
  "type": "Feature",
  "properties": {
    "iso:country":"US",
    "sg:address":"13310 Amargosa Rd",
    "sg:city":"Victorville",
    "sg:classifiers":[
        {
            "category":"Building & Trades",
            "subcategory":"Construction",
            "type":"Services"
        }
    ],
    "sg:phone":"+1 760 241 6161",
    "sg:postcode":"92392",
    "sg:province":"CA",
    "sg:tags":[
        "home",
        "general",
        "family",
        "contractor"
    ],
    "wof:name":"Pacific-Star Development Corp",
    "wof:placetype":"venue"
},
  "geometry": {"coordinates":[-117.33024500000001,34.494353],"type":"Point"}
}