{
  "type": "Feature",
  "properties": {
    "addr:full":"1116 Bradford Cir Corona CA 92882",
    "addr:housenumber":"1116",
    "addr:postcode":"92882",
    "addr:street":"Bradford Cir",
    "iso:country":"US",
    "sg:address":"1116 Bradford Cir",
    "sg:city":"Corona",
    "sg:classifiers":[
        {
            "category":"Manufacturing",
            "subcategory":"Furniture",
            "type":"Manufacturing & Wholesale Goods"
        }
    ],
    "sg:phone":"+1 951 278 0300",
    "sg:postcode":"92882",
    "sg:province":"CA",
    "sg:tags":[
        "upholstered",
        "wood"
    ],
    "sg:website":"www.maywoodshops.com",
    "wof:name":"Maywood Shops Inc",
    "wof:placetype":"venue"
},
  "geometry": {"coordinates":[-117.582773,33.885287],"type":"Point"}
}