{
  "type": "Feature",
  "properties": {
    "iso:country":"US",
    "sg:address":"425 Main St",
    "sg:city":"Placerville",
    "sg:classifiers":[
        {
            "category":"Restaurant",
            "type":"Food & Drink"
        }
    ],
    "sg:phone":"+1 530 626 1091",
    "sg:postcode":"95667",
    "sg:province":"CA",
    "wof:name":"Powell Brothers Steamer Co",
    "wof:placetype":"venue"
},
  "geometry": {"coordinates":[-120.800235,38.729485],"type":"Point"}
}