{
  "type": "Feature",
  "properties": {
    "iso:country":"US",
    "sg:address":"320 W Temple St",
    "sg:city":"Los Angeles",
    "sg:classifiers":[
        {
            "category":"Government",
            "subcategory":"Office",
            "type":"Public Place"
        }
    ],
    "sg:phone":"+1 213 974 1065",
    "sg:postcode":"90026",
    "sg:province":"CA",
    "sg:tags":[
        "general"
    ],
    "wof:name":"Internal Service Dept",
    "wof:placetype":"venue"
},
  "geometry": {"coordinates":[-118.24438499999999,34.056283],"type":"Point"}
}