{
  "type": "Feature",
  "properties": {
    "iso:country":"US",
    "sg:address":"9300 W Stockton Blvd",
    "sg:city":"Elk Grove",
    "sg:classifiers":[
        {
            "category":"Real Estate",
            "subcategory":"Real Estate Agent",
            "type":"Services"
        }
    ],
    "sg:phone":"+1 916 691 0820",
    "sg:postcode":"95758",
    "sg:province":"CA",
    "wof:name":"White Dove Financial Realty",
    "wof:placetype":"venue"
},
  "geometry": {"coordinates":[-121.39328399999999,38.418082],"type":"Point"}
}