{
  "type": "Feature",
  "properties": {
    "iso:country":"US",
    "sg:address":"15 20th Ave",
    "sg:city":"Venice",
    "sg:classifiers":[
        {
            "category":"Professional",
            "type":"Services"
        }
    ],
    "sg:phone":"+1 310 306 6992",
    "sg:postcode":"90291",
    "sg:province":"CA",
    "wof:name":"Swftech",
    "wof:placetype":"venue"
},
  "geometry": {"coordinates":[-118.47058800000001,33.985599],"type":"Point"}
}