{
  "type": "Feature",
  "properties": {
    "addr:full":"1018 Chestnut St San Jose CA 95110",
    "addr:housenumber":"1018",
    "addr:postcode":"95110",
    "addr:street":"Chestnut St",
    "iso:country":"US",
    "sg:address":"1018 Chestnut St",
    "sg:city":"San Jose",
    "sg:classifiers":[
        {
            "category":"Building & Trades",
            "subcategory":"Electrical",
            "type":"Services"
        }
    ],
    "sg:phone":"+1 408 280 7884",
    "sg:postcode":"95110",
    "sg:province":"CA",
    "sg:tags":[
        "electric",
        "contractor"
    ],
    "wof:name":"J P Mark Electric",
    "wof:placetype":"venue"
},
  "geometry": {"coordinates":[-121.918786,37.347657],"type":"Point"}
}