{
  "type": "Feature",
  "properties": {
    "addr:full":"11829 Alondra Blvd Norwalk CA 90650",
    "addr:housenumber":"11829",
    "addr:postcode":"90650",
    "addr:street":"Alondra Blvd",
    "iso:country":"US",
    "sg:address":"11829 Alondra Blvd",
    "sg:city":"Norwalk",
    "sg:classifiers":[
        {
            "category":"Food & Beverages",
            "subcategory":"Liquor & Beverages",
            "type":"Retail Goods"
        }
    ],
    "sg:phone":"+1 562 864 8982",
    "sg:postcode":"90650",
    "sg:province":"CA",
    "sg:tags":[
        "beer",
        "spirit",
        "wine"
    ],
    "wof:name":"Happy Liquor Store",
    "wof:placetype":"venue"
},
  "geometry": {"coordinates":[-118.08140299999999,33.887888],"type":"Point"}
}