{
  "type": "Feature",
  "properties": {
    "addr:full":"11541 Clover Rd Tracy CA 95304",
    "addr:housenumber":"11541",
    "addr:postcode":"95304",
    "addr:street":"Clover Rd",
    "iso:country":"US",
    "sg:address":"11541 Clover Rd",
    "sg:city":"Tracy",
    "sg:classifiers":[
        {
            "category":"Farming",
            "subcategory":"Farm & Veterinary Services",
            "type":"Manufacturing & Wholesale Goods"
        }
    ],
    "sg:phone":"+1 209 836 3370",
    "sg:postcode":"95304",
    "sg:province":"CA",
    "sg:tags":[
        "livestock"
    ],
    "wof:name":"Kc Ranch",
    "wof:placetype":"venue"
},
  "geometry": {"coordinates":[-121.45058,37.76146],"type":"Point"}
}