{
  "type": "Feature",
  "properties": {
    "addr:full":"8575 Commerce Avenue San Diego CA 92121",
    "addr:housenumber":"8575",
    "addr:postcode":"92121",
    "addr:street":"Commerce Avenue",
    "iso:country":"US",
    "sg:address":"8575 Commerce Avenue",
    "sg:city":"San Diego",
    "sg:classifiers":[
        {
            "category":"Professional",
            "type":"Services"
        }
    ],
    "sg:phone":"+1 858 530 1885",
    "sg:postcode":"92121",
    "sg:province":"CA",
    "sg:tags":[
        "caterer"
    ],
    "sg:website":"www.cateringspecialist.com",
    "wof:name":"Culinary Concepts",
    "wof:placetype":"venue"
},
  "geometry": {"coordinates":[-117.167824,32.880804],"type":"Point"}
}