{
  "type": "Feature",
  "properties": {
    "addr:full":"11000 Garden Grove Blvd Garden Grove CA 92843",
    "addr:housenumber":"11000",
    "addr:postcode":"92843",
    "addr:street":"Garden Grove Blvd",
    "iso:country":"US",
    "sg:address":"11000 Garden Grove Blvd",
    "sg:city":"Garden Grove",
    "sg:classifiers":[
        {
            "category":"Autos & Motor Vehicles",
            "subcategory":"Fuel & Gas Station",
            "type":"Retail Goods"
        }
    ],
    "sg:phone":"+1 714 638 6308",
    "sg:postcode":"92843",
    "sg:province":"CA",
    "sg:website":"www.costco.com",
    "wof:name":"Costco Gasoline",
    "wof:placetype":"venue"
},
  "geometry": {"coordinates":[-117.94076099999999,33.772932],"type":"Point"}
}