{
  "type": "Feature",
  "properties": {
    "addr:full":"148 S Spruce Ave S San Francisco CA 94080",
    "addr:housenumber":"148",
    "addr:postcode":"94080",
    "addr:street":"S Spruce Ave S",
    "iso:country":"US",
    "sg:address":"148 S Spruce Ave",
    "sg:city":"S San Francisco",
    "sg:classifiers":[
        {
            "category":"Freight",
            "type":"Transportation"
        }
    ],
    "sg:phone":"+1 650 737 1616",
    "sg:postcode":"94080",
    "sg:province":"CA",
    "sg:tags":[
        "delivery"
    ],
    "wof:name":"Primetime Express Inc",
    "wof:placetype":"venue"
},
  "geometry": {"coordinates":[-122.418235,37.650533],"type":"Point"}
}