{
  "type": "Feature",
  "properties": {
    "addr:full":"451 Chaucer St Palo Alto CA 94301",
    "addr:housenumber":"451",
    "addr:postcode":"94301",
    "addr:street":"Chaucer St",
    "iso:country":"US",
    "sg:address":"451 Chaucer St",
    "sg:city":"Palo Alto",
    "sg:classifiers":[
        {
            "category":"Health Services",
            "subcategory":"Doctor",
            "type":"Services"
        }
    ],
    "sg:phone":"+1 650 289 9500",
    "sg:postcode":"94301",
    "sg:province":"CA",
    "sg:tags":[
        "physician",
        "surgeon"
    ],
    "wof:name":"William Riley MD",
    "wof:placetype":"venue"
},
  "geometry": {"coordinates":[-122.152537,37.456046],"type":"Point"}
}