{
  "type": "Feature",
  "properties": {
    "addr:full":"1635 Faraday Ave Carlsbad CA 92008",
    "addr:housenumber":"1635",
    "addr:postcode":"92008",
    "addr:street":"Faraday Ave",
    "iso:country":"US",
    "sg:address":"1635 Faraday Ave",
    "sg:city":"Carlsbad",
    "sg:classifiers":[
        {
            "category":"Government",
            "subcategory":"Office",
            "type":"Public Place"
        }
    ],
    "sg:phone":"+1 760 602 2490",
    "sg:postcode":"92008",
    "sg:province":"CA",
    "sg:tags":[
        "city"
    ],
    "wof:name":"City of Carlsbad",
    "wof:placetype":"venue"
},
  "geometry": {"coordinates":[-117.29096800000001,33.138403],"type":"Point"}
}