{
  "type": "Feature",
  "properties": {
    "addr:full":"13364 Marlay Ave Fontana CA 92337",
    "addr:housenumber":"13364",
    "addr:postcode":"92337",
    "addr:street":"Marlay Ave",
    "iso:country":"US",
    "sg:address":"13364 Marlay Ave",
    "sg:city":"Fontana",
    "sg:classifiers":[
        {
            "category":"Freight",
            "type":"Transportation"
        }
    ],
    "sg:phone":"+1 951 685 1244",
    "sg:postcode":"92337",
    "sg:province":"CA",
    "sg:tags":[
        "trucking"
    ],
    "sg:website":"www.con-way.com",
    "wof:name":"Con-Way Western Express",
    "wof:placetype":"venue"
},
  "geometry": {"coordinates":[-117.515389,34.040885],"type":"Point"}
}