{
  "type": "Feature",
  "properties": {
    "iso:country":"US",
    "sg:address":"17337 Ventura Blvd",
    "sg:city":"Encino",
    "sg:classifiers":[
        {
            "category":"Real Estate",
            "subcategory":"Real Estate Agent",
            "type":"Services"
        }
    ],
    "sg:phone":"+1 818 995 1818",
    "sg:postcode":"91316",
    "sg:province":"CA",
    "sg:tags":[
        "management"
    ],
    "wof:name":"Encino Gardens",
    "wof:placetype":"venue"
},
  "geometry": {"coordinates":[-118.511008,34.161095],"type":"Point"}
}