{
  "type": "Feature",
  "properties": {
    "iso:country":"US",
    "sg:address":"19214 Arminta St",
    "sg:city":"Reseda",
    "sg:classifiers":[
        {
            "category":"Building & Trades",
            "subcategory":"Construction",
            "type":"Services"
        }
    ],
    "sg:phone":"+1 818 886 2340",
    "sg:postcode":"91335",
    "sg:province":"CA",
    "sg:tags":[
        "concrete",
        "contractor"
    ],
    "wof:name":"Rance Sanders & Co",
    "wof:placetype":"venue"
},
  "geometry": {"coordinates":[-118.55145899999999,34.213737],"type":"Point"}
}