{
  "type": "Feature",
  "properties": {
    "iso:country":"US",
    "sg:address":"14108 Crenshaw Blvd",
    "sg:city":"Gardena",
    "sg:classifiers":[
        {
            "category":"Communications",
            "type":"Services"
        }
    ],
    "sg:phone":"+1 310 538 4077",
    "sg:postcode":"90249",
    "sg:province":"CA",
    "sg:tags":[
        "communication"
    ],
    "wof:name":"Ontime Communications",
    "wof:placetype":"venue"
},
  "geometry": {"coordinates":[-118.326427,33.904456],"type":"Point"}
}