{
  "type": "Feature",
  "properties": {
    "addr:full":"130 W Main St Turlock CA 95380",
    "addr:housenumber":"130",
    "addr:postcode":"95380",
    "addr:street":"W Main St",
    "iso:country":"US",
    "sg:address":"130 W Main St",
    "sg:city":"Turlock",
    "sg:classifiers":[
        {
            "category":"Personal",
            "subcategory":"Beauty Salon",
            "type":"Services"
        }
    ],
    "sg:phone":"+1 209 634 4010",
    "sg:postcode":"95380",
    "sg:province":"CA",
    "sg:tags":[
        "spa",
        "day"
    ],
    "wof:name":"Fontis Spa & Salon",
    "wof:placetype":"venue"
},
  "geometry": {"coordinates":[-120.847427,37.493582],"type":"Point"}
}