{
  "type": "Feature",
  "properties": {
    "addr:full":"345 6th St Hollister CA 95023",
    "addr:housenumber":"345",
    "addr:postcode":"hollister ca 95023",
    "addr:street":"6Th St",
    "iso:country":"US",
    "sg:address":"345 6th St",
    "sg:city":"Hollister",
    "sg:classifiers":[
        {
            "category":"Professional",
            "subcategory":"Lawyer & Legal Services",
            "type":"Services"
        }
    ],
    "sg:phone":"+1 831 635 0833",
    "sg:postcode":"95023",
    "sg:province":"CA",
    "sg:tags":[
        "attorney"
    ],
    "wof:name":"Marie Brown Law Offices",
    "wof:placetype":"venue"
},
  "geometry": {"coordinates":[-121.402186,36.85041],"type":"Point"}
}