{
  "type": "Feature",
  "properties": {
    "iso:country":"US",
    "sg:address":"4709 Olanda St",
    "sg:city":"Lynwood",
    "sg:classifiers":[
        {
            "category":"Real Estate",
            "subcategory":"Real Estate Services",
            "type":"Services"
        },
        {
            "category":"Real Estate",
            "subcategory":"Real Estate Agent",
            "type":"Services"
        }
    ],
    "sg:phone":"+1 310 516 0776",
    "sg:postcode":"90262",
    "sg:province":"CA",
    "sg:tags":[
        "buyer",
        "broker"
    ],
    "wof:name":"Proman Realty",
    "wof:placetype":"venue"
},
  "geometry": {"coordinates":[-118.189774,33.90733],"type":"Point"}
}