{
  "type": "Feature",
  "properties": {
    "addr:full":"234 Escuela Ave Mountain View CA 94040",
    "addr:housenumber":"234",
    "addr:postcode":"94040",
    "addr:street":"Escuela Ave",
    "iso:country":"US",
    "sg:address":"234 Escuela Ave",
    "sg:city":"Mountain View",
    "sg:classifiers":[
        {
            "category":"Professional",
            "type":"Services"
        }
    ],
    "sg:phone":"+1 650 967 4429",
    "sg:postcode":"94040",
    "sg:province":"CA",
    "wof:name":"3rd Person LLC",
    "wof:placetype":"venue"
},
  "geometry": {"coordinates":[-122.09374200000001,37.39746],"type":"Point"}
}