{
  "type": "Feature",
  "properties": {
    "addr:full":"225 Bush Street Suite 1470 San Francisco CA 94104",
    "addr:housenumber":"225",
    "addr:postcode":"94104",
    "addr:street":"Bush Street Suite 1470",
    "iso:country":"US",
    "sg:address":"225 Bush Street Suite 1470",
    "sg:city":"San Francisco",
    "sg:classifiers":[
        {
            "category":"Real Estate",
            "subcategory":"Real Estate Services",
            "type":"Services"
        }
    ],
    "sg:phone":"+1 415 835 0225",
    "sg:postcode":"94104",
    "sg:province":"CA",
    "sg:tags":[
        "management",
        "property"
    ],
    "wof:name":"Flynn Properties",
    "wof:placetype":"venue"
},
  "geometry": {"coordinates":[-122.40100099999999,37.791199],"type":"Point"}
}