{
  "type": "Feature",
  "properties": {
    "addr:full":"450 Mill St Ione CA 95630",
    "addr:housenumber":"450",
    "addr:postcode":"ca 95630",
    "addr:street":"Mill St",
    "iso:country":"US",
    "sg:address":"450 Mill St",
    "sg:city":"Ione",
    "sg:classifiers":[
        {
            "category":"Education",
            "subcategory":"School",
            "type":"Public Place"
        }
    ],
    "sg:phone":"+1 209 274 2491",
    "sg:postcode":"95630",
    "sg:province":"CA",
    "wof:name":"Ione Junior High School",
    "wof:placetype":"venue"
},
  "geometry": {"coordinates":[-121.168532,38.680122],"type":"Point"}
}