{
  "type": "Feature",
  "properties": {
    "iso:country":"US",
    "sg:address":"14759 Bessemer St",
    "sg:city":"Van Nuys",
    "sg:classifiers":[
        {
            "category":"Building & Trades",
            "subcategory":"Construction",
            "type":"Services"
        }
    ],
    "sg:phone":"+1 818 786 5211",
    "sg:postcode":"91411",
    "sg:province":"CA",
    "sg:tags":[
        "maker",
        "cabinet"
    ],
    "wof:name":"Creative Cabinet Co",
    "wof:placetype":"venue"
},
  "geometry": {"coordinates":[-118.456385,34.180871],"type":"Point"}
}