{
  "type": "Feature",
  "properties": {
    "addr:full":"8000 International Blvd Oakland CA 94621",
    "addr:housenumber":"8000",
    "addr:postcode":"94621",
    "addr:street":"International Blvd",
    "iso:country":"US",
    "sg:address":"8000 International Blvd",
    "sg:city":"Oakland",
    "sg:classifiers":[
        {
            "category":"Education",
            "subcategory":"School",
            "type":"Public Place"
        }
    ],
    "sg:phone":"+1 510 568 0500",
    "sg:postcode":"94621",
    "sg:province":"CA",
    "wof:name":"Growing Children",
    "wof:placetype":"venue"
},
  "geometry": {"coordinates":[-122.18052299999999,37.756152],"type":"Point"}
}