{
  "type": "Feature",
  "properties": {
    "addr:full":"77564 Country Club Dr Palm Desert CA 92211",
    "addr:housenumber":"77564",
    "addr:postcode":"ca 92211",
    "addr:street":"Country Club Dr",
    "iso:country":"US",
    "sg:address":"77564 Country Club Dr",
    "sg:city":"Palm Desert",
    "sg:classifiers":[
        {
            "category":"Shopping",
            "subcategory":"Clothing, Apparel, & Fashions",
            "type":"Retail Goods"
        }
    ],
    "sg:phone":"+1 760 200 5765",
    "sg:postcode":"92211",
    "sg:province":"CA",
    "sg:tags":[
        "sportswear"
    ],
    "wof:name":"American Continental Claim",
    "wof:placetype":"venue"
},
  "geometry": {"coordinates":[-116.31610000000001,33.758352],"type":"Point"}
}