{
  "type": "Feature",
  "properties": {
    "addr:full":"615 Ginkgo Ct Santa Maria CA 93458",
    "addr:housenumber":"615",
    "addr:postcode":"93458",
    "addr:street":"Ginkgo Ct",
    "iso:country":"US",
    "sg:address":"615 Ginkgo Ct",
    "sg:city":"Santa Maria",
    "sg:classifiers":[
        {
            "category":"Education",
            "subcategory":"Special Training",
            "type":"Public Place"
        }
    ],
    "sg:phone":"+1 805 925 5211",
    "sg:postcode":"93458",
    "sg:province":"CA",
    "sg:tags":[
        "program"
    ],
    "wof:name":"Pax Programs",
    "wof:placetype":"venue"
},
  "geometry": {"coordinates":[-120.44301400000001,34.987167],"type":"Point"}
}