{
  "type": "Feature",
  "properties": {
    "iso:country":"US",
    "sg:address":"868 N Broadway",
    "sg:city":"Escondido",
    "sg:classifiers":[
        {
            "category":"Home & Garden",
            "subcategory":"Building Materials",
            "type":"Retail Goods"
        }
    ],
    "sg:phone":"+1 760 746 1615",
    "sg:postcode":"92025",
    "sg:province":"CA",
    "sg:tags":[
        "glass",
        "window",
        "plate"
    ],
    "wof:name":"Escondido Glass Co Inc",
    "wof:placetype":"venue"
},
  "geometry": {"coordinates":[-117.086224,33.132498],"type":"Point"}
}