{
  "type": "Feature",
  "properties": {
    "addr:full":"121 E Cotati Ave Cotati CA 94931",
    "addr:housenumber":"121",
    "addr:postcode":"94931",
    "addr:street":"E Cotati Ave",
    "iso:country":"US",
    "sg:address":"121 E Cotati Ave",
    "sg:city":"Cotati",
    "sg:classifiers":[
        {
            "category":"Shopping",
            "subcategory":"Hobbies, Toys, & Games",
            "type":"Retail Goods"
        }
    ],
    "sg:phone":"+1 707 664 8343",
    "sg:postcode":"94931",
    "sg:province":"CA",
    "sg:tags":[
        "mail"
    ],
    "sg:website":"www.whimbeads.com",
    "wof:name":"Out On A Whim",
    "wof:placetype":"venue"
},
  "geometry": {"coordinates":[-122.704829,38.326942],"type":"Point"}
}