{
  "type": "Feature",
  "properties": {
    "addr:full":"2219 W Olive Ave Burbank CA 91506",
    "addr:housenumber":"2219",
    "addr:postcode":"91506",
    "addr:street":"W Olive Ave",
    "iso:country":"US",
    "sg:address":"2219 W Olive Ave",
    "sg:city":"Burbank",
    "sg:classifiers":[
        {
            "category":"Manufacturing",
            "subcategory":"Printing",
            "type":"Manufacturing & Wholesale Goods"
        }
    ],
    "sg:phone":"+1 818 848 2891",
    "sg:postcode":"91506",
    "sg:province":"CA",
    "sg:tags":[
        "engraver",
        "wood"
    ],
    "wof:name":"Plasti-Graph Products",
    "wof:placetype":"venue"
},
  "geometry": {"coordinates":[-118.32777400000001,34.16292],"type":"Point"}
}