{
  "type": "Feature",
  "properties": {
    "iso:country":"US",
    "sg:address":"12100 Valley Blvd",
    "sg:city":"El Monte",
    "sg:classifiers":[
        {
            "category":"Health Services",
            "subcategory":"Doctor",
            "type":"Services"
        }
    ],
    "sg:phone":"+1 626 443 7929",
    "sg:postcode":"91732",
    "sg:province":"CA",
    "sg:tags":[
        "dentist"
    ],
    "wof:name":"Gutierrez Dental Office",
    "wof:placetype":"venue"
},
  "geometry": {"coordinates":[-118.01532,34.060787],"type":"Point"}
}