{
  "type": "Feature",
  "properties": {
    "iso:country":"US",
    "sg:address":"2515 Santa Clara Ave Ste 200",
    "sg:city":"Alameda",
    "sg:classifiers":[
        {
            "category":"Banks & Credit Unions",
            "subcategory":"Investment Brokerage",
            "type":"Services"
        },
        {
            "category":"Insurance",
            "subcategory":"Hazard Insurance",
            "type":"Services"
        }
    ],
    "sg:phone":"+1 510 522 2090",
    "sg:postcode":"94501",
    "sg:province":"CA",
    "sg:tags":[
        "commercial",
        "agent",
        "business",
        "resume"
    ],
    "wof:name":"Alameda Associates Insurance",
    "wof:placetype":"venue"
},
  "geometry": {"coordinates":[-122.239864,37.764277],"type":"Point"}
}