{
  "type": "Feature",
  "properties": {
    "addr:full":"2317 Sharon Way Modesto CA 95350",
    "addr:housenumber":"2317",
    "addr:postcode":"ca 95350",
    "addr:street":"Sharon Way",
    "iso:country":"US",
    "sg:address":"2317 Sharon Way",
    "sg:city":"Modesto",
    "sg:classifiers":[
        {
            "category":"Manufacturing",
            "subcategory":"Retail Goods",
            "type":"Manufacturing & Wholesale Goods"
        }
    ],
    "sg:phone":"+1 209 578 9974",
    "sg:postcode":"95350",
    "sg:province":"CA",
    "sg:tags":[
        "product",
        "mfg"
    ],
    "wof:name":"Jennys Creative Crafts",
    "wof:placetype":"venue"
},
  "geometry": {"coordinates":[-121.03746099999999,37.674702],"type":"Point"}
}