{
  "type": "Feature",
  "properties": {
    "addr:full":"4790 Irvine Blvd Ste 105 Irvine CA 92620",
    "addr:housenumber":"4790",
    "addr:postcode":"92620",
    "addr:street":"Irvine Blvd Ste 105",
    "iso:country":"US",
    "sg:address":"4790 Irvine Blvd Ste 105",
    "sg:city":"Irvine",
    "sg:classifiers":[
        {
            "category":"Real Estate",
            "subcategory":"Real Estate Services",
            "type":"Services"
        },
        {
            "category":"Real Estate",
            "subcategory":"Real Estate Agent",
            "type":"Services"
        }
    ],
    "sg:phone":"+1 714 838 5215",
    "sg:postcode":"92620",
    "sg:province":"CA",
    "sg:tags":[
        "buyer",
        "broker"
    ],
    "wof:name":"New Life Realty Group",
    "wof:placetype":"venue"
},
  "geometry": {"coordinates":[-117.76019100000001,33.713765],"type":"Point"}
}