{
  "type": "Feature",
  "properties": {
    "iso:country":"US",
    "sg:address":"2751 Monument Blvd",
    "sg:city":"Concord",
    "sg:classifiers":[
        {
            "category":"Building & Trades",
            "subcategory":"Cleaning & Sanitation",
            "type":"Services"
        }
    ],
    "sg:phone":"+1 925 798 9764",
    "sg:postcode":"94520",
    "sg:province":"CA",
    "sg:tags":[
        "janitor"
    ],
    "wof:name":"All American Janitorial Svc",
    "wof:placetype":"venue"
},
  "geometry": {"coordinates":[-122.031713,37.964083],"type":"Point"}
}