{
  "type": "Feature",
  "properties": {
    "addr:full":"12825 S Normandie Ave Gardena CA 90249",
    "addr:housenumber":"12825",
    "addr:postcode":"90249",
    "addr:street":"S Normandie Ave",
    "iso:country":"US",
    "sg:address":"12825 S Normandie Ave",
    "sg:city":"Gardena",
    "sg:classifiers":[
        {
            "category":"Shopping",
            "subcategory":"Party Supplies",
            "type":"Retail Goods"
        },
        {
            "category":"Shopping",
            "subcategory":"Gifts & Souvenirs",
            "type":"Retail Goods"
        }
    ],
    "sg:phone":"+1 310 329 3389",
    "sg:postcode":"90249",
    "sg:province":"CA",
    "sg:tags":[
        "shop",
        "favors",
        "decoration"
    ],
    "wof:name":"Rainbow Party Supply",
    "wof:placetype":"venue"
},
  "geometry": {"coordinates":[-118.300387,33.915956],"type":"Point"}
}