{
  "type": "Feature",
  "properties": {
    "iso:country":"US",
    "sg:address":"701 Palomar Airport Rd",
    "sg:city":"Carlsbad",
    "sg:classifiers":[
        {
            "category":"Professional",
            "subcategory":"Management & Consulting",
            "type":"Services"
        }
    ],
    "sg:phone":"+1 949 300 0212",
    "sg:postcode":"92008",
    "sg:province":"CA",
    "sg:tags":[
        "research"
    ],
    "wof:name":"Cadre Environmental",
    "wof:placetype":"venue"
},
  "geometry": {"coordinates":[-117.32387199999999,33.122203],"type":"Point"}
}