{
  "type": "Feature",
  "properties": {
    "addr:full":"1126 Lawrence Way Oxnard CA 93035",
    "addr:housenumber":"1126",
    "addr:postcode":"93035",
    "addr:street":"Lawrence Way",
    "iso:country":"US",
    "sg:address":"1126 Lawrence Way",
    "sg:city":"Oxnard",
    "sg:classifiers":[
        {
            "category":"Professional",
            "subcategory":"Computer Services",
            "type":"Services"
        }
    ],
    "sg:phone":"+1 805 984 8982",
    "sg:postcode":"93035",
    "sg:province":"CA",
    "sg:tags":[
        "internet"
    ],
    "wof:name":"Internet Website Advertising",
    "wof:placetype":"venue"
},
  "geometry": {"coordinates":[-119.205123,34.18893],"type":"Point"}
}