{
  "type": "Feature",
  "properties": {
    "iso:country":"US",
    "sg:address":"12777 Valley View St",
    "sg:city":"Garden Grove",
    "sg:classifiers":[
        {
            "category":"Health Services",
            "subcategory":"Chiropractor",
            "type":"Services"
        }
    ],
    "sg:phone":"+1 714 899 0103",
    "sg:postcode":"92845",
    "sg:province":"CA",
    "wof:name":"Terry Bruce J DC",
    "wof:placetype":"venue"
},
  "geometry": {"coordinates":[-118.035004,33.777401],"type":"Point"}
}