{
  "type": "Feature",
  "properties": {
    "addr:full":"5100 Gasoline Alley Dr Bakersfield CA 93313",
    "addr:housenumber":"5100",
    "addr:postcode":"93313",
    "addr:street":"Gasoline Alley Dr",
    "iso:country":"US",
    "sg:address":"5100 Gasoline Alley Dr",
    "sg:city":"Bakersfield",
    "sg:classifiers":[
        {
            "category":"Autos & Motor Vehicles",
            "subcategory":"Auto Supplies",
            "type":"Retail Goods"
        }
    ],
    "sg:phone":"+1 866 754 9062",
    "sg:postcode":"93313",
    "sg:province":"CA",
    "sg:tags":[
        "body",
        "part"
    ],
    "sg:website":"http://www.billrighttoyota.com",
    "wof:name":"Bill Wright Toyota INC",
    "wof:placetype":"venue"
},
  "geometry": {"coordinates":[-119.0355,35.308801],"type":"Point"}
}