{
  "type": "Feature",
  "properties": {
    "addr:full":"2011 Artesia Blvd Redondo Beach CA 90278",
    "addr:housenumber":"2011",
    "addr:postcode":"90278",
    "addr:street":"Artesia Blvd",
    "iso:country":"US",
    "sg:address":"2011 Artesia Blvd",
    "sg:city":"Redondo Beach",
    "sg:classifiers":[
        {
            "category":"Organizations",
            "subcategory":"Religious Organization",
            "type":"Services"
        }
    ],
    "sg:phone":"+1 310 374 9045",
    "sg:postcode":"90278",
    "sg:province":"CA",
    "wof:name":"Merino John",
    "wof:placetype":"venue"
},
  "geometry": {"coordinates":[-118.37599899999999,33.873001],"type":"Point"}
}