{
  "type": "Feature",
  "properties": {
    "iso:country":"US",
    "sg:address":"2349 Fletcher Pkwy",
    "sg:city":"El Cajon",
    "sg:classifiers":[
        {
            "category":"Shopping",
            "subcategory":"Pets & Pet Supplies",
            "type":"Retail Goods"
        }
    ],
    "sg:phone":"+1 619 464 4383",
    "sg:postcode":"92020",
    "sg:province":"CA",
    "wof:name":"Suds N Paws",
    "wof:placetype":"venue"
},
  "geometry": {"coordinates":[-116.996691,32.802588],"type":"Point"}
}