{
  "type": "Feature",
  "properties": {
    "iso:country":"US",
    "sg:address":"1525 E 17th St Ste C",
    "sg:city":"Santa Ana",
    "sg:classifiers":[
        {
            "category":"Professional",
            "subcategory":"Lawyer & Legal Services",
            "type":"Services"
        }
    ],
    "sg:phone":"+1 714 543 8885",
    "sg:postcode":"92705",
    "sg:province":"CA",
    "wof:name":"Sutherland Mark D Atty",
    "wof:placetype":"venue"
},
  "geometry": {"coordinates":[-117.846598,33.760265],"type":"Point"}
}