{
  "type": "Feature",
  "properties": {
    "iso:country":"US",
    "sg:address":"13012 Midway Pl",
    "sg:city":"Cerritos",
    "sg:classifiers":[
        {
            "category":"Manufacturing",
            "subcategory":"Tools & Machinery",
            "type":"Manufacturing & Wholesale Goods"
        }
    ],
    "sg:phone":"+1 310 333 4077",
    "sg:postcode":"90703",
    "sg:province":"CA",
    "sg:tags":[
        "photographic",
        "mfg"
    ],
    "wof:name":"Xerox",
    "wof:placetype":"venue"
},
  "geometry": {"coordinates":[-118.051624,33.885352],"type":"Point"}
}