{
  "type": "Feature",
  "properties": {
    "iso:country":"US",
    "sg:address":"2323 Hawthorne Blvd",
    "sg:city":"Redondo Beach",
    "sg:classifiers":[
        {
            "category":"Shopping",
            "subcategory":"Bicycles & Sporting Goods",
            "type":"Retail Goods"
        }
    ],
    "sg:phone":"+1 909 590 7425",
    "sg:postcode":"90278",
    "sg:province":"CA",
    "wof:name":"Turner's Outdoorsman",
    "wof:placetype":"venue"
},
  "geometry": {"coordinates":[-118.352345,33.873614],"type":"Point"}
}