{
  "type": "Feature",
  "properties": {
    "iso:country":"US",
    "sg:address":"2390 Telegraph Ave",
    "sg:city":"Berkeley",
    "sg:classifiers":[
        {
            "category":"Shopping",
            "subcategory":"Jewelry",
            "type":"Retail Goods"
        }
    ],
    "sg:phone":"+1 510 848 5303",
    "sg:postcode":"94704",
    "sg:province":"CA",
    "sg:tags":[
        "jeweler"
    ],
    "wof:name":"Sather Gate Jewelers",
    "wof:placetype":"venue"
},
  "geometry": {"coordinates":[-122.25884600000001,37.867119],"type":"Point"}
}