{
  "type": "Feature",
  "properties": {
    "addr:full":"2740 Cochran St Simi Valley CA 93065",
    "addr:housenumber":"2740",
    "addr:postcode":"93065",
    "addr:street":"Cochran St",
    "iso:country":"US",
    "sg:address":"2740 Cochran St",
    "sg:city":"Simi Valley",
    "sg:classifiers":[
        {
            "category":"Banks & Credit Unions",
            "subcategory":"Bank",
            "type":"Services"
        }
    ],
    "sg:phone":"+1 805 583 0607",
    "sg:postcode":"93065",
    "sg:province":"CA",
    "sg:website":"www.wellsfargo.com",
    "wof:name":"Wells Fargo Bank",
    "wof:placetype":"venue"
},
  "geometry": {"coordinates":[-118.74263999999999,34.278919],"type":"Point"}
}