{
  "type": "Feature",
  "properties": {
    "iso:country":"US",
    "sg:address":"1605 W 6th St",
    "sg:city":"Los Angeles",
    "sg:classifiers":[
        {
            "category":"Food & Beverages",
            "subcategory":"Groceries & Convenience Stores",
            "type":"Retail Goods"
        }
    ],
    "sg:phone":"+1 213 483 8500",
    "sg:postcode":"90017",
    "sg:province":"CA",
    "sg:tags":[
        "grocer"
    ],
    "wof:name":"J Mart",
    "wof:placetype":"venue"
},
  "geometry": {"coordinates":[-118.268972,34.056998],"type":"Point"}
}