{
  "type": "Feature",
  "properties": {
    "addr:full":"545 W Los Angeles Ave Moorpark CA 93021",
    "addr:housenumber":"545",
    "addr:postcode":"ca 93021",
    "addr:street":"W Los Angeles Ave",
    "iso:country":"US",
    "sg:address":"545 W Los Angeles Ave",
    "sg:city":"Moorpark",
    "sg:classifiers":[
        {
            "category":"Health Services",
            "subcategory":"Health Practitioner",
            "type":"Services"
        }
    ],
    "sg:phone":"+1 805 530 3838",
    "sg:postcode":"93021",
    "sg:province":"CA",
    "sg:tags":[
        "therapist",
        "physical"
    ],
    "wof:name":"Moorpark Physical Therapy",
    "wof:placetype":"venue"
},
  "geometry": {"coordinates":[-118.819126,34.286414],"type":"Point"}
}