{
  "type": "Feature",
  "properties": {
    "iso:country":"US",
    "sg:address":"23480 Rider St",
    "sg:city":"Perris",
    "sg:classifiers":[
        {
            "category":"Wholesale",
            "subcategory":"Poultry",
            "type":"Manufacturing & Wholesale Goods"
        }
    ],
    "sg:phone":"+1 951 657 3987",
    "sg:postcode":"92570",
    "sg:province":"CA",
    "sg:tags":[
        "eggs"
    ],
    "wof:name":"Mc Anally Egg Enterprises Inc",
    "wof:placetype":"venue"
},
  "geometry": {"coordinates":[-117.252702,33.830307],"type":"Point"}
}