{
  "type": "Feature",
  "properties": {
    "iso:country":"US",
    "sg:address":"1930 Wilshire Blvd Ste 208",
    "sg:city":"Los Angeles",
    "sg:classifiers":[
        {
            "category":"Professional",
            "subcategory":"Lawyer & Legal Services",
            "type":"Services"
        }
    ],
    "sg:phone":"+1 213 385 8112",
    "sg:postcode":"90057",
    "sg:province":"CA",
    "sg:website":"www.evictiondefensenetwork.org",
    "wof:name":"Eviction Defense Network",
    "wof:placetype":"venue"
},
  "geometry": {"coordinates":[-118.273945,34.057031],"type":"Point"}
}