{
  "type": "Feature",
  "properties": {
    "addr:full":"4345 Oakwood Ave La Canada Fltrdg CA 91011",
    "addr:housenumber":"4345",
    "addr:postcode":"91011",
    "addr:street":"Oakwood Ave La",
    "iso:country":"US",
    "sg:address":"4345 Oakwood Ave",
    "sg:city":"La Canada Fltrdg",
    "sg:classifiers":[
        {
            "category":"Insurance",
            "subcategory":"Insurance Agent",
            "type":"Services"
        }
    ],
    "sg:phone":"+1 818 790 8222",
    "sg:postcode":"91011",
    "sg:province":"CA",
    "wof:name":"Flintridge Benefits Group",
    "wof:placetype":"venue"
},
  "geometry": {"coordinates":[-118.193804,34.196301],"type":"Point"}
}