{
  "type": "Feature",
  "properties": {
    "iso:country":"US",
    "sg:address":"1331 S 46th St",
    "sg:city":"Richmond",
    "sg:classifiers":[
        {
            "category":"Government",
            "subcategory":"Office",
            "type":"Public Place"
        }
    ],
    "sg:phone":"+1 510 237 0641",
    "sg:postcode":"94804",
    "sg:province":"CA",
    "sg:tags":[
        "conservation"
    ],
    "wof:name":"Conservation Corps CA",
    "wof:placetype":"venue"
},
  "geometry": {"coordinates":[-122.331602,37.915516],"type":"Point"}
}