{
  "type": "Feature",
  "properties": {
    "iso:country":"US",
    "sg:address":"110 E 9th St Ste A1175",
    "sg:city":"Los Angeles",
    "sg:classifiers":[
        {
            "category":"Shopping",
            "subcategory":"Department Store",
            "type":"Retail Goods"
        },
        {
            "category":"Shopping",
            "subcategory":"Discount & Variety Stores",
            "type":"Retail Goods"
        }
    ],
    "sg:phone":"+1 213 488 1153",
    "sg:postcode":"90079",
    "sg:province":"CA",
    "sg:tags":[
        "wholesale"
    ],
    "sg:website":"www.fashiondistrict.org/",
    "wof:name":"LA Fashion District",
    "wof:placetype":"venue"
},
  "geometry": {"coordinates":[-118.255388,34.040588],"type":"Point"}
}