{
  "type": "Feature",
  "properties": {
    "iso:country":"US",
    "sg:address":"5040 International Blvd",
    "sg:city":"Oakland",
    "sg:classifiers":[
        {
            "category":"Retail",
            "subcategory":"Laundry & Dry Cleaning",
            "type":"Services"
        }
    ],
    "sg:phone":"+1 510 698 4882",
    "sg:postcode":"94601",
    "sg:province":"CA",
    "sg:tags":[
        "laundries-self"
    ],
    "wof:name":"Birdies Coin Laundries",
    "wof:placetype":"venue"
},
  "geometry": {"coordinates":[-122.208366,37.769287],"type":"Point"}
}