{
  "type": "Feature",
  "properties": {
    "addr:full":"79 Sylvan Dr San Francisco CA 94132",
    "addr:housenumber":"79",
    "addr:postcode":"94132",
    "addr:street":"Sylvan Dr",
    "iso:country":"US",
    "sg:address":"79 Sylvan Dr",
    "sg:city":"San Francisco",
    "sg:classifiers":[
        {
            "category":"Shopping",
            "subcategory":"Gifts & Souvenirs",
            "type":"Retail Goods"
        }
    ],
    "sg:phone":"+1 415 753 1233",
    "sg:postcode":"94132",
    "sg:province":"CA",
    "sg:tags":[
        "pottery",
        "product",
        "mfg"
    ],
    "wof:name":"Goldenberg Designs",
    "wof:placetype":"venue"
},
  "geometry": {"coordinates":[-122.485552,37.733798],"type":"Point"}
}