{
  "type": "Feature",
  "properties": {
    "iso:country":"US",
    "sg:address":"8932 Beverly Rd",
    "sg:city":"Pico Rivera",
    "sg:classifiers":[
        {
            "category":"Insurance",
            "subcategory":"Insurance Agent",
            "type":"Services"
        }
    ],
    "sg:phone":"+1 562 463 8111",
    "sg:postcode":"90660",
    "sg:province":"CA",
    "wof:name":"J Garcia Insurance Ctr",
    "wof:placetype":"venue"
},
  "geometry": {"coordinates":[-118.082275,34.007961],"type":"Point"}
}