{
  "type": "Feature",
  "properties": {
    "addr:full":"2040 Pacific Coast Hwy Lomita CA 90717",
    "addr:housenumber":"2040",
    "addr:postcode":"90717",
    "addr:street":"Pacific Coast Hwy",
    "iso:country":"US",
    "sg:address":"2040 Pacific Coast Hwy",
    "sg:city":"Lomita",
    "sg:classifiers":[
        {
            "category":"Personal",
            "subcategory":"Beauty Salon",
            "type":"Services"
        },
        {
            "category":"Personal",
            "subcategory":"Nail Salon",
            "type":"Services"
        }
    ],
    "sg:phone":"+1 310 326 6647",
    "sg:postcode":"90717",
    "sg:province":"CA",
    "wof:name":"Life Style Nail Spa",
    "wof:placetype":"venue"
},
  "geometry": {"coordinates":[-118.315652,33.789362],"type":"Point"}
}