{
  "type": "Feature",
  "properties": {
    "addr:full":"3328 Buck Owens Blvd Bakersfield CA 93308",
    "addr:housenumber":"3328",
    "addr:postcode":"93308",
    "addr:street":"Buck Owens Blvd",
    "iso:country":"US",
    "sg:address":"3328 Buck Owens Blvd",
    "sg:city":"Bakersfield",
    "sg:classifiers":[
        {
            "category":"Wholesale",
            "subcategory":"Hardware",
            "type":"Manufacturing & Wholesale Goods"
        },
        {
            "category":"Home & Garden",
            "subcategory":"Garden Supply",
            "type":"Retail Goods"
        },
        {
            "category":"Retail",
            "subcategory":"Repair Shop",
            "type":"Services"
        }
    ],
    "sg:phone":"+1 661 327 8876",
    "sg:postcode":"93308",
    "sg:province":"CA",
    "sg:tags":[
        "renting",
        "lawn",
        "outdoor",
        "power",
        "landscaping",
        "equipment-sales",
        "equipment",
        "saw"
    ],
    "sg:website":"http://www.stihlusa.com/",
    "wof:name":"Garden World",
    "wof:placetype":"venue"
},
  "geometry": {"coordinates":[-119.043159,35.39005],"type":"Point"}
}