{
  "type": "Feature",
  "properties": {
    "addr:full":"1300 Clay Street Suite 600 Oakland CA 94612",
    "addr:housenumber":"1300",
    "addr:postcode":"94612",
    "addr:street":"Clay Street Suite 600",
    "iso:country":"US",
    "sg:address":"1300 Clay Street Suite 600",
    "sg:city":"Oakland",
    "sg:classifiers":[
        {
            "category":"Professional",
            "subcategory":"Accounting & Tax Preparation",
            "type":"Services"
        },
        {
            "category":"Professional",
            "subcategory":"Lawyer & Legal Services",
            "type":"Services"
        },
        {
            "category":"Banks & Credit Unions",
            "subcategory":"Financial Services",
            "type":"Services"
        }
    ],
    "sg:phone":"+1 800 896 5536",
    "sg:postcode":"94612",
    "sg:province":"CA",
    "sg:tags":[
        "attorney",
        "return",
        "taxes-consultants",
        "accountant",
        "representative",
        "advising"
    ],
    "sg:website":"www.JKHarris.com",
    "wof:name":"JK Harris & Company",
    "wof:placetype":"venue"
},
  "geometry": {"coordinates":[-122.273819,37.804715],"type":"Point"}
}