{
  "type": "Feature",
  "properties": {
    "addr:full":"6510 Quakertown Ave Woodland Hills CA 91367",
    "addr:postcode":"6510;91367",
    "addr:street":"Quakertown Ave",
    "iso:country":"US",
    "sg:address":"6510 Quakertown Ave",
    "sg:city":"Woodland Hills",
    "sg:classifiers":[
        {
            "category":"Organizations",
            "subcategory":"Religious Organization",
            "type":"Services"
        }
    ],
    "sg:phone":"+1 818 703 6133",
    "sg:postcode":"91367",
    "sg:province":"CA",
    "sg:tags":[
        "science",
        "christian",
        "practitioner"
    ],
    "wof:name":"Marguerite Pfeiffer",
    "wof:placetype":"venue"
},
  "geometry": {"coordinates":[-118.569811,34.188179],"type":"Point"}
}