{
  "type": "Feature",
  "properties": {
    "iso:country":"US",
    "sg:address":"420 S Grand Ave",
    "sg:city":"Los Angeles",
    "sg:classifiers":[
        {
            "category":"Professional",
            "type":"Services"
        }
    ],
    "sg:phone":"+1 323 299 0928",
    "sg:postcode":"90071",
    "sg:province":"CA",
    "sg:tags":[
        "establishment"
    ],
    "wof:name":"Renaissance RUNNERS-LA",
    "wof:placetype":"venue"
},
  "geometry": {"coordinates":[-118.25307599999999,34.050991],"type":"Point"}
}