{
  "type": "Feature",
  "properties": {
    "iso:country":"US",
    "sg:address":"4525 Montgomery Dr",
    "sg:city":"Santa Rosa",
    "sg:classifiers":[
        {
            "category":"Organizations",
            "subcategory":"Non-profit Organization",
            "type":"Services"
        }
    ],
    "sg:phone":"+1 707 539 3848",
    "sg:postcode":"95409",
    "sg:province":"CA",
    "wof:name":"Adult Literacy League",
    "wof:placetype":"venue"
},
  "geometry": {"coordinates":[-122.671172,38.457538],"type":"Point"}
}