{
  "type": "Feature",
  "properties": {
    "addr:full":"11720 Education St Auburn CA 95602",
    "addr:housenumber":"11720",
    "addr:postcode":"ca 95602",
    "addr:street":"Education St",
    "iso:country":"US",
    "sg:address":"11720 Education St",
    "sg:city":"Auburn",
    "sg:classifiers":[
        {
            "category":"Health Services",
            "subcategory":"Clinic",
            "type":"Services"
        }
    ],
    "sg:phone":"+1 530 823 0676",
    "sg:postcode":"95602",
    "sg:province":"CA",
    "sg:tags":[
        "medical"
    ],
    "wof:name":"Gambro Healthcare Inc",
    "wof:placetype":"venue"
},
  "geometry": {"coordinates":[-121.101812,38.94444],"type":"Point"}
}