{
  "type": "Feature",
  "properties": {
    "iso:country":"US",
    "sg:address":"1808 W Foothill Blvd",
    "sg:city":"Upland",
    "sg:classifiers":[
        {
            "category":"Autos & Motor Vehicles",
            "subcategory":"Automobile Sales",
            "type":"Retail Goods"
        }
    ],
    "sg:phone":"+1 909 982 7746",
    "sg:postcode":"91786",
    "sg:province":"CA",
    "sg:tags":[
        "car",
        "dealer"
    ],
    "wof:name":"Sierra Motors",
    "wof:placetype":"venue"
},
  "geometry": {"coordinates":[-117.68895500000001,34.1067],"type":"Point"}
}