{
  "type": "Feature",
  "properties": {
    "addr:full":"1999 Monterey Hwy San Jose CA 95112",
    "addr:housenumber":"1999",
    "addr:postcode":"95112",
    "addr:street":"Monterey Hwy",
    "iso:country":"US",
    "sg:address":"1999 Monterey Hwy",
    "sg:city":"San Jose",
    "sg:classifiers":[
        {
            "category":"Professional",
            "subcategory":"Lawyer & Legal Services",
            "type":"Services"
        }
    ],
    "sg:phone":"+1 408 298 4888",
    "sg:postcode":"95112",
    "sg:province":"CA",
    "sg:tags":[
        "plan"
    ],
    "wof:name":"Viemy Multi Network",
    "wof:placetype":"venue"
},
  "geometry": {"coordinates":[-121.86270500000001,37.305266],"type":"Point"}
}