{
  "type": "Feature",
  "properties": {
    "iso:country":"US",
    "sg:address":"1045 Cass St",
    "sg:city":"Monterey",
    "sg:classifiers":[
        {
            "category":"Personal",
            "subcategory":"Beauty Salon",
            "type":"Services"
        }
    ],
    "sg:phone":"+1 831 373 4323",
    "sg:postcode":"93940",
    "sg:province":"CA",
    "wof:name":"Rejuvenation",
    "wof:placetype":"venue"
},
  "geometry": {"coordinates":[-121.89762500000001,36.588889],"type":"Point"}
}