{
  "type": "Feature",
  "properties": {
    "addr:full":"7734 Herschel Ave Ste A La Jolla CA 92037",
    "addr:housenumber":"7734",
    "addr:postcode":"92037",
    "addr:street":"Herschel Ave Ste A",
    "iso:country":"US",
    "sg:address":"7734 Herschel Ave Ste A",
    "sg:city":"La Jolla",
    "sg:classifiers":[
        {
            "category":"Real Estate",
            "subcategory":"Real Estate Services",
            "type":"Services"
        }
    ],
    "sg:phone":"+1 858 551 1600",
    "sg:postcode":"92037",
    "sg:province":"CA",
    "sg:tags":[
        "management",
        "property"
    ],
    "wof:name":"Klein Real Estate",
    "wof:placetype":"venue"
},
  "geometry": {"coordinates":[-117.27260200000001,32.844349],"type":"Point"}
}