{
  "type": "Feature",
  "properties": {
    "addr:full":"5480 Thomas Rd Sebastopol CA 95472",
    "addr:housenumber":"5480",
    "addr:postcode":"95472",
    "addr:street":"Thomas Rd",
    "iso:country":"US",
    "sg:address":"5480 Thomas Rd",
    "sg:city":"Sebastopol",
    "sg:classifiers":[
        {
            "category":"Farming",
            "subcategory":"Livestock Farm",
            "type":"Manufacturing & Wholesale Goods"
        }
    ],
    "sg:phone":"+1 707 823 6246",
    "sg:postcode":"95472",
    "sg:province":"CA",
    "sg:tags":[
        "eating"
    ],
    "wof:name":"Redwood Hill Farm Goat Dairy",
    "wof:placetype":"venue"
},
  "geometry": {"coordinates":[-122.90479000000001,38.454486],"type":"Point"}
}