{
  "type": "Feature",
  "properties": {
    "iso:country":"US",
    "sg:address":"1595 N Mount Vernon Ave",
    "sg:city":"San Bernardino",
    "sg:classifiers":[
        {
            "category":"Personal",
            "subcategory":"Beauty Salon",
            "type":"Services"
        }
    ],
    "sg:phone":"+1 909 885 2926",
    "sg:postcode":"92411",
    "sg:province":"CA",
    "wof:name":"Style & Grace",
    "wof:placetype":"venue"
},
  "geometry": {"coordinates":[-117.313754,34.127954],"type":"Point"}
}