{
  "type": "Feature",
  "properties": {
    "addr:full":"1341 Stockton St San Francisco CA 94133",
    "addr:housenumber":"1341",
    "addr:postcode":"94133",
    "addr:street":"Stockton St",
    "iso:country":"US",
    "sg:address":"1341 Stockton St",
    "sg:city":"San Francisco",
    "sg:classifiers":[
        {
            "category":"Health Services",
            "subcategory":"Health Practitioner",
            "type":"Services"
        }
    ],
    "sg:phone":"+1 415 398 2208",
    "sg:postcode":"94133",
    "sg:province":"CA",
    "sg:tags":[
        "acupuncture"
    ],
    "wof:name":"Nature Herbal Line",
    "wof:placetype":"venue"
},
  "geometry": {"coordinates":[-122.408861,37.797983],"type":"Point"}
}