{
  "type": "Feature",
  "properties": {
    "iso:country":"US",
    "sg:address":"612 N Vermont Ave",
    "sg:city":"Los Angeles",
    "sg:classifiers":[
        {
            "category":"Personal",
            "subcategory":"Massage",
            "type":"Services"
        }
    ],
    "sg:phone":"+1 323 662 6767",
    "sg:postcode":"90004",
    "sg:province":"CA",
    "wof:name":"Natural Therapeutic Hot Oil Massage Spa",
    "wof:placetype":"venue"
},
  "geometry": {"coordinates":[-118.291403,34.082192],"type":"Point"}
}