{
  "type": "Feature",
  "properties": {
    "iso:country":"US",
    "sg:address":"260 Cedar Rd",
    "sg:city":"Vista",
    "sg:classifiers":[
        {
            "category":"Education",
            "subcategory":"School",
            "type":"Public Place"
        }
    ],
    "sg:phone":"+1 760 724 8442",
    "sg:postcode":"92083",
    "sg:province":"CA",
    "sg:tags":[
        "high",
        "middle",
        "elementary"
    ],
    "sg:website":"www.vusd.k12.ca.us",
    "wof:name":"Casita Center For Tech Science & Math",
    "wof:placetype":"venue"
},
  "geometry": {"coordinates":[-117.283997,33.1912],"type":"Point"}
}