{
  "type": "Feature",
  "properties": {
    "iso:country":"US",
    "sg:address":"80 Grand Ave Ste 700",
    "sg:city":"Oakland",
    "sg:classifiers":[
        {
            "category":"Health Services",
            "subcategory":"Optometrist",
            "type":"Services"
        }
    ],
    "sg:phone":"+1 510 893 4318",
    "sg:postcode":"94612",
    "sg:province":"CA",
    "sg:tags":[
        "ophthalmologist"
    ],
    "wof:name":"Shapiro James S MD",
    "wof:placetype":"venue"
},
  "geometry": {"coordinates":[-122.266159,37.811683],"type":"Point"}
}