{
  "type": "Feature",
  "properties": {
    "iso:country":"US",
    "sg:address":"449 Gaven St",
    "sg:city":"San Francisco",
    "sg:classifiers":[
        {
            "category":"Real Estate",
            "subcategory":"Real Estate Services",
            "type":"Services"
        }
    ],
    "sg:phone":"+1 415 841 1326",
    "sg:postcode":"94134",
    "sg:province":"CA",
    "sg:tags":[
        "management",
        "property"
    ],
    "wof:name":"JL Management Group Inc",
    "wof:placetype":"venue"
},
  "geometry": {"coordinates":[-122.413877,37.731797],"type":"Point"}
}