{
  "type": "Feature",
  "properties": {
    "iso:country":"US",
    "sg:address":"1555 Sepulveda Blvd",
    "sg:city":"Torrance",
    "sg:classifiers":[
        {
            "category":"Bars & Pubs",
            "subcategory":"Lounge",
            "type":"Food & Drink"
        }
    ],
    "sg:phone":"+1 310 325 4408",
    "sg:postcode":"90501",
    "sg:province":"CA",
    "sg:tags":[
        "karaoke"
    ],
    "wof:name":"Muse Karaoke",
    "wof:placetype":"venue"
},
  "geometry": {"coordinates":[-118.305295,33.815767],"type":"Point"}
}