{
  "type": "Feature",
  "properties": {
    "iso:country":"US",
    "sg:address":"1309 W Magnolia Blvd",
    "sg:city":"Burbank",
    "sg:classifiers":[
        {
            "category":"Communications",
            "subcategory":"Film & Video Production",
            "type":"Services"
        }
    ],
    "sg:phone":"+1 818 563 5537",
    "sg:postcode":"91506",
    "sg:province":"CA",
    "sg:tags":[
        "motion",
        "picture",
        "studio",
        "producer"
    ],
    "wof:name":"Pure Light Images",
    "wof:placetype":"venue"
},
  "geometry": {"coordinates":[-118.32348399999999,34.1758],"type":"Point"}
}