{
  "type": "Feature",
  "properties": {
    "addr:full":"290 W Hamilton Avenue Campbell CA 95008",
    "addr:housenumber":"290",
    "addr:postcode":"95008",
    "addr:street":"W Hamilton Avenue",
    "iso:country":"US",
    "sg:address":"290 W Hamilton Avenue",
    "sg:city":"Campbell",
    "sg:classifiers":[
        {
            "category":"Health Services",
            "subcategory":"Optometrist",
            "type":"Services"
        }
    ],
    "sg:phone":"+1 408 374 7000",
    "sg:postcode":"95008",
    "sg:province":"CA",
    "sg:website":"www.eyefocus.com/",
    "wof:name":"Dr. Raymond Umeda, OD",
    "wof:placetype":"venue"
},
  "geometry": {"coordinates":[-121.955765,37.294007],"type":"Point"}
}