{
  "type": "Feature",
  "properties": {
    "iso:country":"US",
    "sg:address":"401 W 4th St",
    "sg:city":"San Bernardino",
    "sg:classifiers":[
        {
            "category":"Banks & Credit Unions",
            "subcategory":"Bank",
            "type":"Services"
        }
    ],
    "sg:phone":"+1 909 383 8100",
    "sg:postcode":"92401",
    "sg:province":"CA",
    "sg:tags":[
        "loan"
    ],
    "wof:name":"San Bernardino Loan & Jewelry",
    "wof:placetype":"venue"
},
  "geometry": {"coordinates":[-117.29281400000001,34.106441],"type":"Point"}
}