{
  "type": "Feature",
  "properties": {
    "addr:full":"15737 Rd 204 Madera CA 93636",
    "addr:housenumber":"15737",
    "addr:postcode":"93636",
    "addr:street":"Rd 204",
    "iso:country":"US",
    "sg:address":"15737 Rd 204",
    "sg:city":"Madera",
    "sg:classifiers":[
        {
            "category":"Farming",
            "subcategory":"Crops",
            "type":"Manufacturing & Wholesale Goods"
        }
    ],
    "sg:phone":"+1 559 822 2800",
    "sg:postcode":"93636",
    "sg:province":"CA",
    "sg:tags":[
        "farm",
        "pistachio"
    ],
    "wof:name":"Central Green Co A Ltd Partnr",
    "wof:placetype":"venue"
},
  "geometry": {"coordinates":[-119.783719,36.959559],"type":"Point"}
}