{
  "type": "Feature",
  "properties": {
    "addr:full":"2102 Commerce Dr San Jose CA 95131",
    "addr:housenumber":"2102",
    "addr:postcode":"95131",
    "addr:street":"Commerce Dr",
    "iso:country":"US",
    "sg:address":"2102 Commerce Dr",
    "sg:city":"San Jose",
    "sg:classifiers":[
        {
            "category":"Communications",
            "subcategory":"Television Station",
            "type":"Services"
        }
    ],
    "sg:phone":"+1 415 398 3636",
    "sg:postcode":"95131",
    "sg:province":"CA",
    "wof:name":"Kicu Tv Channel 36",
    "wof:placetype":"venue"
},
  "geometry": {"coordinates":[-121.89099899999999,37.394199],"type":"Point"}
}