{
  "type": "Feature",
  "properties": {
    "iso:country":"US",
    "sg:address":"23743 Monument Canyon Dr",
    "sg:city":"Diamond Bar",
    "sg:classifiers":[
        {
            "category":"Wholesale",
            "subcategory":"Durable Goods & Equipment",
            "type":"Manufacturing & Wholesale Goods"
        }
    ],
    "sg:phone":"+1 909 861 4286",
    "sg:postcode":"91765",
    "sg:province":"CA",
    "sg:tags":[
        "representative",
        "manufacturer"
    ],
    "wof:name":"Hoffman Enterprises",
    "wof:placetype":"venue"
},
  "geometry": {"coordinates":[-117.803785,34.002018],"type":"Point"}
}