{
  "type": "Feature",
  "properties": {
    "addr:full":"8020 East Dr Roseville CA 95747",
    "addr:housenumber":"8020",
    "addr:postcode":"95747",
    "addr:street":"East Dr",
    "iso:country":"US",
    "sg:address":"8020 East Dr",
    "sg:city":"Roseville",
    "sg:classifiers":[
        {
            "category":"Real Estate",
            "subcategory":"Real Estate Agent",
            "type":"Services"
        }
    ],
    "sg:phone":"+1 916 782 4565",
    "sg:postcode":"95747",
    "sg:province":"CA",
    "wof:name":"WEBB Realty",
    "wof:placetype":"venue"
},
  "geometry": {"coordinates":[-121.318708,38.751641],"type":"Point"}
}