{
  "type": "Feature",
  "properties": {
    "iso:country":"US",
    "sg:address":"5698 E Beverly Blvd",
    "sg:city":"Los Angeles",
    "sg:classifiers":[
        {
            "category":"Building & Trades",
            "subcategory":"Construction",
            "type":"Services"
        }
    ],
    "sg:phone":"+1 323 724 2804",
    "sg:postcode":"90022",
    "sg:province":"CA",
    "sg:tags":[
        "contractor"
    ],
    "wof:name":"Edward F Salaises Constr Co",
    "wof:placetype":"venue"
},
  "geometry": {"coordinates":[-118.14547899999999,34.027246],"type":"Point"}
}