{
  "type": "Feature",
  "properties": {
    "iso:country":"US",
    "sg:address":"735 E Church Ave",
    "sg:city":"Fresno",
    "sg:classifiers":[
        {
            "category":"Education",
            "subcategory":"School",
            "type":"Public Place"
        }
    ],
    "sg:phone":"+1 559 233 5477",
    "sg:postcode":"93706",
    "sg:province":"CA",
    "wof:name":"Kipp Academy Fresno",
    "wof:placetype":"venue"
},
  "geometry": {"coordinates":[-119.80006299999999,36.714198],"type":"Point"}
}