{
  "type": "Feature",
  "properties": {
    "iso:country":"US",
    "sg:address":"19725 Sherman Way",
    "sg:city":"Winnetka",
    "sg:classifiers":[
        {
            "category":"Banks & Credit Unions",
            "subcategory":"Bank",
            "type":"Services"
        }
    ],
    "sg:phone":"+1 818 773 9066",
    "sg:postcode":"91306",
    "sg:province":"CA",
    "sg:tags":[
        "escrow"
    ],
    "wof:name":"Highland Estates Escrow Inc",
    "wof:placetype":"venue"
},
  "geometry": {"coordinates":[-118.5634,34.201149],"type":"Point"}
}