{
  "type": "Feature",
  "properties": {
    "addr:full":"28519 Highpoint Ave Moreno Valley CA 92555",
    "addr:housenumber":"28519",
    "addr:postcode":"92555",
    "addr:street":"Highpoint Ave",
    "iso:country":"US",
    "sg:address":"28519 Highpoint Ave",
    "sg:city":"Moreno Valley",
    "sg:classifiers":[
        {
            "category":"Professional",
            "subcategory":"Management & Consulting",
            "type":"Services"
        }
    ],
    "sg:phone":"+1 951 247 1558",
    "sg:postcode":"92555",
    "sg:province":"CA",
    "sg:tags":[
        "business"
    ],
    "wof:name":"Kezar & Associates",
    "wof:placetype":"venue"
},
  "geometry": {"coordinates":[-117.164671,33.909564],"type":"Point"}
}