{
  "type": "Feature",
  "properties": {
    "addr:full":"41 Admiral Callaghan Ln Vallejo CA 94591",
    "addr:housenumber":"41",
    "addr:postcode":"94591",
    "addr:street":"Admiral Callaghan Ln",
    "iso:country":"US",
    "sg:address":"41 Admiral Callaghan Ln",
    "sg:city":"Vallejo",
    "sg:classifiers":[
        {
            "category":"Health Services",
            "subcategory":"Doctor",
            "type":"Services"
        }
    ],
    "sg:phone":"+1 707 552 5644",
    "sg:postcode":"94591",
    "sg:province":"CA",
    "sg:tags":[
        "dentist"
    ],
    "wof:name":"Neal Roth Inc",
    "wof:placetype":"venue"
},
  "geometry": {"coordinates":[-122.228489,38.110492],"type":"Point"}
}