{
  "type": "Feature",
  "properties": {
    "iso:country":"US",
    "sg:address":"11050 Santa Monica Blvd",
    "sg:city":"Los Angeles",
    "sg:classifiers":[
        {
            "category":"Professional",
            "subcategory":"Accounting & Tax Preparation",
            "type":"Services"
        }
    ],
    "sg:phone":"+1 310 477 0030",
    "sg:postcode":"90025",
    "sg:province":"CA",
    "sg:tags":[
        "accountant"
    ],
    "wof:name":"Jackman Saul CPA",
    "wof:placetype":"venue"
},
  "geometry": {"coordinates":[-118.442763,34.047676],"type":"Point"}
}