{
  "type": "Feature",
  "properties": {
    "addr:full":"7665 Redwood Blvd Novato CA 94945",
    "addr:housenumber":"7665",
    "addr:postcode":"94945",
    "addr:street":"Redwood Blvd",
    "iso:country":"US",
    "sg:address":"7665 Redwood Blvd",
    "sg:city":"Novato",
    "sg:classifiers":[
        {
            "category":"Professional",
            "subcategory":"Advertising",
            "type":"Services"
        }
    ],
    "sg:phone":"+1 415 892 9988",
    "sg:postcode":"94945",
    "sg:province":"CA",
    "wof:name":"ZLAND.COM",
    "wof:placetype":"venue"
},
  "geometry": {"coordinates":[-122.56708500000001,38.118559],"type":"Point"}
}