{
  "type": "Feature",
  "properties": {
    "iso:country":"US",
    "sg:address":"5911 Fresca Dr",
    "sg:city":"La Palma",
    "sg:classifiers":[
        {
            "category":"Home & Garden",
            "subcategory":"Home Furnishings",
            "type":"Retail Goods"
        }
    ],
    "sg:phone":"+1 714 367 2430",
    "sg:postcode":"90623",
    "sg:province":"CA",
    "sg:tags":[
        "window",
        "covering"
    ],
    "wof:name":"Custom Craft Co",
    "wof:placetype":"venue"
},
  "geometry": {"coordinates":[-118.029304,33.862802],"type":"Point"}
}