{
  "type": "Feature",
  "properties": {
    "iso:country":"US",
    "sg:address":"1920 Lake Ave Suite 100",
    "sg:city":"Altadena",
    "sg:classifiers":[
        {
            "category":"Banks & Credit Unions",
            "subcategory":"Financial Services",
            "type":"Services"
        }
    ],
    "sg:phone":"+1 626 398 7200",
    "sg:postcode":"91001",
    "sg:province":"CA",
    "sg:tags":[
        "financing",
        "cashing",
        "money",
        "loan",
        "check",
        "payday",
        "order"
    ],
    "sg:website":"http://ad.doubleclick.net/clk;225053199;48888911;w?http://www.checkngo.com?source=yellowpages&cat=TLs&AfsCampaignId=642",
    "wof:name":"Check 'n Go",
    "wof:placetype":"venue"
},
  "geometry": {"coordinates":[-118.131804,34.17874],"type":"Point"}
}