{
  "type": "Feature",
  "properties": {
    "addr:full":"Fitzgerald Abbott & Beardsley LLP 1221 Broadway 21st Fl Oakland CA 94612",
    "addr:housenumber":"1221",
    "addr:postcode":"94612",
    "addr:street":"Broadway 21St",
    "iso:country":"US",
    "sg:address":"Fitzgerald Abbott & Beardsley LLP 1221 Broadway 21st Fl",
    "sg:city":"Oakland",
    "sg:classifiers":[
        {
            "category":"Professional",
            "subcategory":"Lawyer & Legal Services",
            "type":"Services"
        }
    ],
    "sg:phone":"+1 510 451 3300",
    "sg:postcode":"94612",
    "sg:province":"CA",
    "sg:website":"www.fablaw.com",
    "wof:name":"Fatima Brunson Evans",
    "wof:placetype":"venue"
},
  "geometry": {"coordinates":[-122.272383,37.803492],"type":"Point"}
}