{
  "type": "Feature",
  "properties": {
    "addr:full":"655 N Puente Ave La Puente CA 91746",
    "addr:housenumber":"655",
    "addr:postcode":"91746",
    "addr:street":"N Puente Ave",
    "iso:country":"US",
    "sg:address":"655 N Puente Ave",
    "sg:city":"La Puente",
    "sg:classifiers":[
        {
            "category":"Manufacturing",
            "subcategory":"Motor Vehicles & Parts",
            "type":"Manufacturing & Wholesale Goods"
        }
    ],
    "sg:phone":"+1 626 961 5600",
    "sg:postcode":"91746",
    "sg:province":"CA",
    "sg:tags":[
        "body",
        "truck"
    ],
    "wof:name":"Perfection Truck Bodies & Eqpt",
    "wof:placetype":"venue"
},
  "geometry": {"coordinates":[-117.98028499999999,34.052122],"type":"Point"}
}