{
  "type": "Feature",
  "properties": {
    "iso:country":"US",
    "sg:address":"655 N Puente Ave",
    "sg:city":"La Puente",
    "sg:classifiers":[
        {
            "category":"Manufacturing",
            "subcategory":"Motor Vehicles & Parts",
            "type":"Manufacturing & Wholesale Goods"
        }
    ],
    "sg:phone":"+1 626 961 5600",
    "sg:postcode":"91746",
    "sg:province":"CA",
    "sg:tags":[
        "body",
        "truck"
    ],
    "wof:name":"Perfection Truck Bodies & Eqpt",
    "wof:placetype":"venue"
},
  "geometry": {"coordinates":[-117.980285,34.052122],"type":"Point"}
}