{
  "type": "Feature",
  "properties": {
    "addr:full":"15744 Creswick Dr La Mirada CA 90638",
    "addr:housenumber":"15744",
    "addr:postcode":"90638",
    "addr:street":"Creswick Dr",
    "iso:country":"US",
    "sg:address":"15744 Creswick Dr",
    "sg:city":"La Mirada",
    "sg:classifiers":[
        {
            "category":"Professional",
            "type":"Services"
        }
    ],
    "sg:phone":"+1 562 943 0083",
    "sg:postcode":"90638",
    "sg:province":"CA",
    "wof:name":"Kay Krahling Designs",
    "wof:placetype":"venue"
},
  "geometry": {"coordinates":[-117.99508899999999,33.923686],"type":"Point"}
}