{
  "type": "Feature",
  "properties": {
    "iso:country":"US",
    "sg:address":"10621 Beach Blvd",
    "sg:city":"Stanton",
    "sg:classifiers":[
        {
            "category":"Shopping",
            "subcategory":"Computers & Home Electronics",
            "type":"Retail Goods"
        }
    ],
    "sg:phone":"+1 714 530 2200",
    "sg:postcode":"90680",
    "sg:province":"CA",
    "sg:tags":[
        "equipment",
        "dealer"
    ],
    "wof:name":"Speedy Office Svc",
    "wof:placetype":"venue"
},
  "geometry": {"coordinates":[-117.993064,33.80721],"type":"Point"}
}