{
  "type": "Feature",
  "properties": {
    "iso:country":"US",
    "sg:address":"2128 S Central Ave",
    "sg:city":"Los Angeles",
    "sg:classifiers":[
        {
            "category":"Shopping",
            "subcategory":"Clothing, Apparel, & Fashions",
            "type":"Retail Goods"
        }
    ],
    "sg:phone":"+1 213 744 1989",
    "sg:postcode":"90011",
    "sg:province":"CA",
    "wof:name":"Victoria Clothing",
    "wof:placetype":"venue"
},
  "geometry": {"coordinates":[-118.253027,34.021636],"type":"Point"}
}