{
  "type": "Feature",
  "properties": {
    "addr:full":"10632 Knott Ave Stanton CA 90680",
    "addr:housenumber":"10632",
    "addr:postcode":"ca 90680",
    "addr:street":"Knott Ave",
    "iso:country":"US",
    "sg:address":"10632 Knott Ave",
    "sg:city":"Stanton",
    "sg:classifiers":[
        {
            "category":"Real Estate",
            "subcategory":"Real Estate Services",
            "type":"Services"
        },
        {
            "category":"Real Estate",
            "subcategory":"Real Estate Operator",
            "type":"Services"
        }
    ],
    "sg:phone":"+1 714 236 9285",
    "sg:postcode":"90680",
    "sg:province":"CA",
    "sg:tags":[
        "vacancy",
        "apartment",
        "rental",
        "listing"
    ],
    "wof:name":"Villa Vista Apartments",
    "wof:placetype":"venue"
},
  "geometry": {"coordinates":[-118.010687,33.808307],"type":"Point"}
}