{
  "type": "Feature",
  "properties": {
    "addr:full":"4720 Amblebrook Way Sacramento CA 95823",
    "addr:housenumber":"4720",
    "addr:postcode":"95823",
    "addr:street":"Amblebrook Way",
    "iso:country":"US",
    "sg:address":"4720 Amblebrook Way",
    "sg:city":"Sacramento",
    "sg:classifiers":[
        {
            "category":"Shopping",
            "subcategory":"Gifts & Souvenirs",
            "type":"Retail Goods"
        }
    ],
    "sg:phone":"+1 916 424 4011",
    "sg:postcode":"95823",
    "sg:province":"CA",
    "sg:tags":[
        "party",
        "supply"
    ],
    "wof:name":"All For Fun",
    "wof:placetype":"venue"
},
  "geometry": {"coordinates":[-121.44607499999999,38.470448],"type":"Point"}
}