{
  "type": "Feature",
  "properties": {
    "iso:country":"US",
    "sg:address":"45 Hickory Ave",
    "sg:city":"Corte Madera",
    "sg:classifiers":[
        {
            "category":"Professional",
            "subcategory":"Art Services",
            "type":"Services"
        }
    ],
    "sg:phone":"+1 415 924 1975",
    "sg:postcode":"94925",
    "sg:province":"CA",
    "sg:tags":[
        "graphic",
        "designer"
    ],
    "sg:website":"www.mckinleymedia.com",
    "wof:name":"Mc Kinley Media",
    "wof:placetype":"venue"
},
  "geometry": {"coordinates":[-122.522359,37.929554],"type":"Point"}
}