{
  "type": "Feature",
  "properties": {
    "iso:country":"US",
    "sg:address":"2520 W 6th St",
    "sg:city":"Los Angeles",
    "sg:classifiers":[
        {
            "category":"Health Services",
            "subcategory":"Nursing And Care Facility",
            "type":"Services"
        }
    ],
    "sg:phone":"+1 213 382 3835",
    "sg:postcode":"90057",
    "sg:province":"CA",
    "sg:tags":[
        "hospice",
        "skilled"
    ],
    "wof:name":"Pacific Hospice Care Corporati",
    "wof:placetype":"venue"
},
  "geometry": {"coordinates":[-118.280314,34.061875],"type":"Point"}
}