{
  "type": "Feature",
  "properties": {
    "addr:full":"13468 Astoria St Sylmar CA 91342",
    "addr:housenumber":"13468",
    "addr:postcode":"91342",
    "addr:street":"Astoria St",
    "iso:country":"US",
    "sg:address":"13468 Astoria St",
    "sg:city":"Sylmar",
    "sg:classifiers":[
        {
            "category":"Shopping",
            "subcategory":"Clothing, Apparel, & Fashions",
            "type":"Retail Goods"
        }
    ],
    "sg:phone":"+1 818 367 2662",
    "sg:postcode":"91342",
    "sg:province":"CA",
    "sg:tags":[
        "family"
    ],
    "wof:name":"Cathys Creations & Treasures",
    "wof:placetype":"venue"
},
  "geometry": {"coordinates":[-118.42676,34.322258],"type":"Point"}
}