{
  "type": "Feature",
  "properties": {
    "addr:full":"1827 E Chapman Ave Orange CA 92866",
    "addr:housenumber":"1827",
    "addr:postcode":"92866",
    "addr:street":"E Chapman Ave",
    "iso:country":"US",
    "sg:address":"1827 E Chapman Ave",
    "sg:city":"Orange",
    "sg:classifiers":[
        {
            "category":"Wholesale",
            "subcategory":"Medical Equipment & Supplies",
            "type":"Manufacturing & Wholesale Goods"
        },
        {
            "category":"Shopping",
            "type":"Retail Goods"
        }
    ],
    "sg:phone":"+1 714 516 2222",
    "sg:postcode":"92866",
    "sg:province":"CA",
    "sg:tags":[
        "physician",
        "surgeon",
        "merchandise"
    ],
    "wof:name":"Alpha Medical Supplies Inc",
    "wof:placetype":"venue"
},
  "geometry": {"coordinates":[-117.83469599999999,33.787902],"type":"Point"}
}