{
  "type": "Feature",
  "properties": {
    "addr:full":"4260 Nobel Dr San Diego CA 92122",
    "addr:housenumber":"4260",
    "addr:postcode":"92122",
    "addr:street":"Nobel Dr",
    "iso:country":"US",
    "sg:address":"4260 Nobel Dr",
    "sg:city":"San Diego",
    "sg:classifiers":[
        {
            "category":"Restaurant",
            "type":"Food & Drink"
        }
    ],
    "sg:menulink":"http://www.allmenus.com/ca/san-diego/216446-mcdonalds/menu/",
    "sg:postcode":"92122",
    "sg:province":"CA",
    "sg:tags":[
        "burger",
        "american"
    ],
    "wof:name":"McDonald's",
    "wof:placetype":"venue"
},
  "geometry": {"coordinates":[-117.214912,32.867716],"type":"Point"}
}