{
  "type": "Feature",
  "properties": {
    "addr:full":"2550 Valley Rd Sacramento CA 95821",
    "addr:housenumber":"2550",
    "addr:postcode":"95821",
    "addr:street":"Valley Rd",
    "iso:country":"US",
    "sg:address":"2550 Valley Rd",
    "sg:city":"Sacramento",
    "sg:classifiers":[
        {
            "category":"Professional",
            "subcategory":"Lawyer & Legal Services",
            "type":"Services"
        }
    ],
    "sg:phone":"+1 916 971 9159",
    "sg:postcode":"95821",
    "sg:province":"CA",
    "sg:tags":[
        "attorney"
    ],
    "wof:name":"John R Harrison",
    "wof:placetype":"venue"
},
  "geometry": {"coordinates":[-121.40187,38.620107],"type":"Point"}
}