{
  "type": "Feature",
  "properties": {
    "addr:full":"576 Wesley Ave Oakland CA 94606",
    "addr:housenumber":"576",
    "addr:postcode":"94606",
    "addr:street":"Wesley Ave",
    "iso:country":"US",
    "sg:address":"576 Wesley Ave",
    "sg:city":"Oakland",
    "sg:classifiers":[
        {
            "category":"Professional",
            "type":"Services"
        }
    ],
    "sg:phone":"+1 510 444 5584",
    "sg:postcode":"94606",
    "sg:province":"CA",
    "sg:tags":[
        "establishment"
    ],
    "wof:name":"EOD",
    "wof:placetype":"venue"
},
  "geometry": {"coordinates":[-122.245769,37.807707],"type":"Point"}
}