{
  "type": "Feature",
  "properties": {
    "iso:country":"US",
    "sg:address":"545 Bryant Street",
    "sg:city":"Palo Alto",
    "sg:classifiers":[
        {
            "category":"Professional",
            "subcategory":"Business Services",
            "type":"Services"
        }
    ],
    "sg:phone":"+1 650 561 3037",
    "sg:postcode":"94301",
    "sg:province":"CA",
    "sg:tags":[
        "telecom",
        "qos",
        "broadband"
    ],
    "sg:website":"http://razoom.com",
    "wof:name":"Razoom",
    "wof:placetype":"venue"
},
  "geometry": {"coordinates":[-122.160781,37.445504],"type":"Point"}
}