{
  "type": "Feature",
  "properties": {
    "iso:country":"US",
    "sg:address":"27531 White Fir Ln",
    "sg:city":"Mission Viejo",
    "sg:classifiers":[
        {
            "category":"Manufacturing",
            "subcategory":"Lumber",
            "type":"Manufacturing & Wholesale Goods"
        }
    ],
    "sg:phone":"+1 949 462 9394",
    "sg:postcode":"92691",
    "sg:province":"CA",
    "sg:tags":[
        "hardwood",
        "mill"
    ],
    "wof:name":"Dm Hardwood Design",
    "wof:placetype":"venue"
},
  "geometry": {"coordinates":[-117.648651,33.657458],"type":"Point"}
}