{
  "type": "Feature",
  "properties": {
    "iso:country":"US",
    "sg:address":"2785 Pacific Coast Hwy # 356",
    "sg:city":"Torrance",
    "sg:classifiers":[
        {
            "category":"Social Services",
            "type":"Services"
        },
        {
            "category":"Education",
            "subcategory":"School",
            "type":"Public Place"
        }
    ],
    "sg:phone":"+1 310 984 6847",
    "sg:postcode":"90505",
    "sg:province":"CA",
    "sg:tags":[
        "human"
    ],
    "wof:name":"Never Ignore Kids Education",
    "wof:placetype":"venue"
},
  "geometry": {"coordinates":[-118.335252,33.793788],"type":"Point"}
}