{
  "type": "Feature",
  "properties": {
    "iso:country":"US",
    "sg:address":"134 E Colorado Blvd",
    "sg:city":"Monrovia",
    "sg:phone":"+1 626 359 2212",
    "sg:postcode":"91016",
    "sg:province":"CA",
    "wof:name":"La Adelita Mexican Restaurant",
    "wof:placetype":"venue"
},
  "geometry": {"coordinates":[-118.000174,34.1459],"type":"Point"}
}