{
  "type": "Feature",
  "properties": {
    "addr:full":"36600 Co Rd 24 Woodland CA 95695",
    "addr:housenumber":"36600;24",
    "addr:postcode":"95695",
    "addr:street":"Co Rd",
    "iso:country":"US",
    "sg:address":"36600 Co Rd 24",
    "sg:city":"Woodland",
    "sg:classifiers":[
        {
            "category":"Personal",
            "type":"Services"
        }
    ],
    "sg:phone":"+1 530 666 1738",
    "sg:postcode":"95695",
    "sg:province":"CA",
    "sg:tags":[
        "electrolysis"
    ],
    "wof:name":"Jeanne Vaughn",
    "wof:placetype":"venue"
},
  "geometry": {"coordinates":[-121.82702999999999,38.663304],"type":"Point"}
}