{
  "type": "Feature",
  "properties": {
    "addr:full":"261 E Vernon Avenue Los Angeles CA 90011",
    "addr:housenumber":"261",
    "addr:postcode":"90011",
    "addr:street":"E Vernon Avenue",
    "iso:country":"US",
    "sg:address":"261 E Vernon Avenue",
    "sg:city":"Los Angeles",
    "sg:classifiers":[
        {
            "category":"Restaurant",
            "type":"Food & Drink"
        }
    ],
    "sg:phone":"+1 323 846 8738",
    "sg:postcode":"90011",
    "sg:province":"CA",
    "wof:name":"Church's Fried Chicken",
    "wof:placetype":"venue"
},
  "geometry": {"coordinates":[-118.270009,34.003965],"type":"Point"}
}