{
  "type": "Feature",
  "properties": {
    "iso:country":"US",
    "sg:address":"17000 S. Vermont Ave. Ste A",
    "sg:city":"Gardena",
    "sg:classifiers":[
        {
            "category":"Communications",
            "subcategory":"Newspaper",
            "type":"Services"
        }
    ],
    "sg:phone":"+1 310 769 4913",
    "sg:postcode":"90247",
    "sg:province":"CA",
    "sg:tags":[
        "print",
        "medium"
    ],
    "sg:website":"www.audreymagazine.com/index.asp",
    "wof:name":"Audrey Magazine",
    "wof:placetype":"venue"
},
  "geometry": {"coordinates":[-118.291,33.876701],"type":"Point"}
}