{
  "type": "Feature",
  "properties": {
    "iso:country":"US",
    "sg:address":"11035 Dexter Rd",
    "sg:city":"Coulterville",
    "sg:classifiers":[
        {
            "category":"Retail",
            "subcategory":"Portrait Studio",
            "type":"Services"
        }
    ],
    "sg:phone":"+1 209 599 9390",
    "sg:postcode":"95311",
    "sg:province":"CA",
    "sg:tags":[
        "photographer"
    ],
    "wof:name":"Ripon Photography",
    "wof:placetype":"venue"
},
  "geometry": {"coordinates":[-120.17910000000001,37.771969],"type":"Point"}
}