{
  "type": "Feature",
  "properties": {
    "iso:country":"US",
    "sg:address":"6382 Pleasant Valley Rd",
    "sg:city":"El Dorado",
    "sg:classifiers":[
        {
            "category":"Building & Trades",
            "subcategory":"Construction",
            "type":"Services"
        }
    ],
    "sg:phone":"+1 530 622 2229",
    "sg:postcode":"95623",
    "sg:province":"CA",
    "sg:tags":[
        "tile",
        "dealer"
    ],
    "wof:name":"Elegant Tile",
    "wof:placetype":"venue"
},
  "geometry": {"coordinates":[-120.84006599999999,38.68209],"type":"Point"}
}