{
  "type": "Feature",
  "properties": {
    "addr:full":"3580 Wilshire Blvd Los Angeles CA 90010",
    "addr:housenumber":"3580",
    "addr:postcode":"90010",
    "addr:street":"Wilshire Blvd",
    "iso:country":"US",
    "sg:address":"3580 Wilshire Blvd",
    "sg:city":"Los Angeles",
    "sg:classifiers":[
        {
            "category":"Professional",
            "subcategory":"Computer Services",
            "type":"Services"
        }
    ],
    "sg:phone":"+1 213 384 0400",
    "sg:postcode":"90010",
    "sg:province":"CA",
    "sg:tags":[
        "internet"
    ],
    "wof:name":"D M Express Inc",
    "wof:placetype":"venue"
},
  "geometry": {"coordinates":[-118.30306400000001,34.061652],"type":"Point"}
}