{
  "type": "Feature",
  "properties": {
    "iso:country":"US",
    "sg:address":"1600 El Camino Real",
    "sg:city":"Belmont",
    "sg:classifiers":[
        {
            "category":"Health Services",
            "subcategory":"Dentist",
            "type":"Services"
        }
    ],
    "sg:phone":"+1 650 508 1668",
    "sg:postcode":"94002",
    "sg:province":"CA",
    "wof:name":"Schwartz Marc DDS",
    "wof:placetype":"venue"
},
  "geometry": {"coordinates":[-122.26927499999999,37.514791],"type":"Point"}
}