{
  "type": "Feature",
  "properties": {
    "iso:country":"US",
    "sg:address":"5121 Keystone Dr",
    "sg:city":"Fremont",
    "sg:classifiers":[
        {
            "category":"Professional",
            "type":"Services"
        }
    ],
    "sg:phone":"+1 510 796 0118",
    "sg:postcode":"94536",
    "sg:province":"CA",
    "wof:name":"Pro Planners",
    "wof:placetype":"venue"
},
  "geometry": {"coordinates":[-122.01244,37.541479],"type":"Point"}
}