{
  "type": "Feature",
  "properties": {
    "addr:full":"800 Daffodil Dr Riverside CA 92507",
    "addr:housenumber":"800",
    "addr:postcode":"92507",
    "addr:street":"Daffodil Dr",
    "iso:country":"US",
    "sg:address":"800 Daffodil Dr",
    "sg:city":"Riverside",
    "sg:classifiers":[
        {
            "category":"Professional",
            "subcategory":"Management & Consulting",
            "type":"Services"
        }
    ],
    "sg:phone":"+1 951 653 0585",
    "sg:postcode":"92507",
    "sg:province":"CA",
    "sg:tags":[
        "consultant",
        "medical"
    ],
    "wof:name":"Certus Corp",
    "wof:placetype":"venue"
},
  "geometry": {"coordinates":[-117.326899,33.955467],"type":"Point"}
}