{
  "type": "Feature",
  "properties": {
    "iso:country":"US",
    "sg:address":"1210 E 6th St",
    "sg:city":"Corona",
    "sg:classifiers":[
        {
            "category":"Utilities",
            "type":"Services"
        }
    ],
    "sg:phone":"+1 951 273 7420",
    "sg:postcode":"92879",
    "sg:province":"CA",
    "sg:tags":[
        "fueling",
        "system",
        "construct"
    ],
    "wof:name":"Roma Sales Company Inc",
    "wof:placetype":"venue"
},
  "geometry": {"coordinates":[-117.550034,33.874565],"type":"Point"}
}