{
  "type": "Feature",
  "properties": {
    "iso:country":"US",
    "sg:address":"2855 Senter Rd",
    "sg:city":"San Jose",
    "sg:classifiers":[
        {
            "category":"Shopping",
            "subcategory":"Clothing, Apparel, & Fashions",
            "type":"Retail Goods"
        }
    ],
    "sg:phone":"+1 408 365 7492",
    "sg:postcode":"95111",
    "sg:province":"CA",
    "sg:tags":[
        "accessory",
        "clothing",
        "women's"
    ],
    "wof:name":"N C Fashion's",
    "wof:placetype":"venue"
},
  "geometry": {"coordinates":[-121.839996,37.2999],"type":"Point"}
}