{
  "type": "Feature",
  "properties": {
    "iso:country":"US",
    "sg:address":"13273 Ventura Blvd",
    "sg:city":"Studio City",
    "sg:classifiers":[
        {
            "category":"Education",
            "subcategory":"Special Training",
            "type":"Public Place"
        }
    ],
    "sg:phone":"+1 818 783 0016",
    "sg:postcode":"91604",
    "sg:province":"CA",
    "sg:tags":[
        "dramatic",
        "instruction"
    ],
    "wof:name":"Feinstein Tuerpe Acting",
    "wof:placetype":"venue"
},
  "geometry": {"coordinates":[-118.42199,34.146548],"type":"Point"}
}