{
  "type": "Feature",
  "properties": {
    "addr:full":"2072 Antioch Ct Oakland CA 94611",
    "addr:housenumber":"2072",
    "addr:postcode":"94611",
    "addr:street":"Antioch Ct",
    "iso:country":"US",
    "sg:address":"2072 Antioch Ct",
    "sg:city":"Oakland",
    "sg:classifiers":[
        {
            "category":"Social Services",
            "type":"Services"
        }
    ],
    "sg:phone":"+1 510 339 1830",
    "sg:postcode":"94611",
    "sg:province":"CA",
    "sg:tags":[
        "counseling",
        "counselor",
        "marriage",
        "family"
    ],
    "wof:name":"Deborah L Blackburn Ma Mfcc",
    "wof:placetype":"venue"
},
  "geometry": {"coordinates":[-122.209029,37.826084],"type":"Point"}
}