{
  "type": "Feature",
  "properties": {
    "iso:country":"US",
    "sg:address":"12920 Chukar Cir",
    "sg:city":"Sonora",
    "sg:classifiers":[
        {
            "category":"Professional",
            "subcategory":"Advertising",
            "type":"Services"
        }
    ],
    "sg:phone":"+1 209 536 5922",
    "sg:postcode":"95370",
    "sg:province":"CA",
    "sg:tags":[
        "guide"
    ],
    "wof:name":"Minority Business Professional",
    "wof:placetype":"venue"
},
  "geometry": {"coordinates":[-120.364501,37.991406],"type":"Point"}
}