{
  "type": "Feature",
  "properties": {
    "addr:full":"299 E McGlincey Ln Campbell CA 95008",
    "addr:housenumber":"299",
    "addr:postcode":"95008",
    "addr:street":"E Mcglincey Ln",
    "iso:country":"US",
    "sg:address":"299 E McGlincey Ln",
    "sg:city":"Campbell",
    "sg:classifiers":[
        {
            "category":"Retail",
            "subcategory":"Auto Repair",
            "type":"Services"
        }
    ],
    "sg:phone":"+1 408 371 2500",
    "sg:postcode":"95008",
    "sg:province":"CA",
    "sg:tags":[
        "repairing",
        "automobile"
    ],
    "wof:name":"Speed Werks",
    "wof:placetype":"venue"
},
  "geometry": {"coordinates":[-121.944081,37.275484],"type":"Point"}
}