{
  "type": "Feature",
  "properties": {
    "iso:country":"US",
    "sg:address":"435 N Roxbury Drive",
    "sg:city":"Beverly Hills",
    "sg:classifiers":[
        {
            "category":"Health Services",
            "subcategory":"Doctor",
            "type":"Services"
        }
    ],
    "sg:phone":"+1 310 278 3746",
    "sg:postcode":"90210",
    "sg:province":"CA",
    "wof:name":"Rosenthal Richard J MD",
    "wof:placetype":"venue"
},
  "geometry": {"coordinates":[-118.406704,34.067858],"type":"Point"}
}