{
  "type": "Feature",
  "properties": {
    "addr:full":"21212 Bake Pkwy Ste G Lake Forest CA 92630",
    "addr:housenumber":"21212",
    "addr:postcode":"92630",
    "addr:street":"Bake Pkwy Ste G",
    "iso:country":"US",
    "sg:address":"21212 Bake Pkwy Ste G",
    "sg:city":"Lake Forest",
    "sg:classifiers":[
        {
            "category":"Restaurant",
            "type":"Food & Drink"
        }
    ],
    "sg:phone":"+1 949 454 8312",
    "sg:postcode":"92630",
    "sg:province":"CA",
    "wof:name":"El Pollo Loco",
    "wof:placetype":"venue"
},
  "geometry": {"coordinates":[-117.702777,33.654453],"type":"Point"}
}