{
  "type": "Feature",
  "properties": {
    "iso:country":"US",
    "sg:address":"1983 Main St",
    "sg:city":"San Diego",
    "sg:classifiers":[
        {
            "category":"Building & Trades",
            "subcategory":"Construction",
            "type":"Services"
        }
    ],
    "sg:phone":"+1 619 235 9933",
    "sg:postcode":"92113",
    "sg:province":"CA",
    "sg:tags":[
        "heavy"
    ],
    "wof:name":"Stockholm Enterprises",
    "wof:placetype":"venue"
},
  "geometry": {"coordinates":[-117.146444,32.698826],"type":"Point"}
}