{
  "type": "Feature",
  "properties": {
    "addr:full":"922 E Holt Ave Pomona CA 91767",
    "addr:housenumber":"922",
    "addr:postcode":"91767",
    "addr:street":"E Holt Ave",
    "iso:country":"US",
    "sg:address":"922 E Holt Ave",
    "sg:city":"Pomona",
    "sg:classifiers":[
        {
            "category":"Shopping",
            "subcategory":"Clothing, Apparel, & Fashions",
            "type":"Retail Goods"
        }
    ],
    "sg:phone":"+1 909 622 9791",
    "sg:postcode":"91767",
    "sg:province":"CA",
    "wof:name":"J's Clothing",
    "wof:placetype":"venue"
},
  "geometry": {"coordinates":[-117.73216499999999,34.062746],"type":"Point"}
}