{
  "type": "Feature",
  "properties": {
    "iso:country":"US",
    "sg:address":"11272 Magnolia Blvd",
    "sg:city":"North Hollywood",
    "sg:classifiers":[
        {
            "category":"Building & Trades",
            "subcategory":"Construction",
            "type":"Services"
        }
    ],
    "sg:phone":"+1 818 769 9156",
    "sg:postcode":"91601",
    "sg:province":"CA",
    "sg:tags":[
        "contractor"
    ],
    "wof:name":"J S N Construction",
    "wof:placetype":"venue"
},
  "geometry": {"coordinates":[-118.376621,34.164773],"type":"Point"}
}