{
  "type": "Feature",
  "properties": {
    "addr:full":"388 9th St Ste 157 Oakland CA 94607",
    "addr:housenumber":"388",
    "addr:postcode":"94607",
    "addr:street":"9Th St Ste 157",
    "iso:country":"US",
    "sg:address":"388 9th St Ste 157",
    "sg:city":"Oakland",
    "sg:classifiers":[
        {
            "category":"Health Services",
            "subcategory":"Optometrist",
            "type":"Services"
        }
    ],
    "sg:phone":"+1 510 268 9600",
    "sg:postcode":"94607",
    "sg:province":"CA",
    "sg:website":"www.ebvc.com",
    "wof:name":"East Bay Vision Center Optometry, Oakland ?Chinatown Branch",
    "wof:placetype":"venue"
},
  "geometry": {"coordinates":[-122.271857,37.800317],"type":"Point"}
}