{
  "type": "Feature",
  "properties": {
    "iso:country":"US",
    "sg:address":"6061 N Figarden Dr",
    "sg:city":"Fresno",
    "sg:classifiers":[
        {
            "category":"Personal",
            "subcategory":"Beauty Salon",
            "type":"Services"
        }
    ],
    "sg:phone":"+1 559 275 6972",
    "sg:postcode":"93722",
    "sg:province":"CA",
    "sg:tags":[
        "nail",
        "manicuring"
    ],
    "wof:name":"Leslies Nails",
    "wof:placetype":"venue"
},
  "geometry": {"coordinates":[-119.87058,36.824338],"type":"Point"}
}