{
  "type": "Feature",
  "properties": {
    "addr:full":"24338 el Toro Rd Laguna Woods CA 92637",
    "addr:housenumber":"24338",
    "addr:postcode":"92637",
    "addr:street":"El Toro Rd",
    "iso:country":"US",
    "sg:address":"24338 el Toro Rd",
    "sg:city":"Laguna Woods",
    "sg:classifiers":[
        {
            "category":"Professional",
            "subcategory":"Art Services",
            "type":"Services"
        }
    ],
    "sg:phone":"+1 949 586 6685",
    "sg:postcode":"92637",
    "sg:province":"CA",
    "sg:tags":[
        "graphic",
        "designer"
    ],
    "wof:name":"Debbie Hamilton Project Mgmt",
    "wof:placetype":"venue"
},
  "geometry": {"coordinates":[-117.729297,33.609077],"type":"Point"}
}