{
  "type": "Feature",
  "properties": {
    "iso:country":"US",
    "sg:address":"139 Stanford Shopping Center",
    "sg:city":"Palo Alto",
    "sg:classifiers":[
        {
            "category":"Shopping",
            "subcategory":"Clothing, Apparel, & Fashions",
            "type":"Retail Goods"
        }
    ],
    "sg:phone":"+1 650 328 0574",
    "sg:postcode":"94304",
    "sg:province":"CA",
    "sg:tags":[
        "lingerie"
    ],
    "wof:name":"Victoria's Secret",
    "wof:placetype":"venue"
},
  "geometry": {"coordinates":[-122.17130899999999,37.444821],"type":"Point"}
}