{
  "type": "Feature",
  "properties": {
    "iso:country":"US",
    "sg:address":"1805 Las Plumas Ave",
    "sg:city":"San Jose",
    "sg:classifiers":[
        {
            "category":"Food & Beverages",
            "subcategory":"Fruits & Vegetables",
            "type":"Retail Goods"
        }
    ],
    "sg:phone":"+1 408 254 5800",
    "sg:postcode":"95133",
    "sg:province":"CA",
    "sg:tags":[
        "juice"
    ],
    "sg:website":"www.odwalla.com",
    "wof:name":"Odwalla Inc",
    "wof:placetype":"venue"
},
  "geometry": {"coordinates":[-121.863657,37.363448],"type":"Point"}
}