{
  "type": "Feature",
  "properties": {
    "addr:full":"11070 Oak St El Monte CA 91731",
    "addr:housenumber":"11070",
    "addr:postcode":"91731",
    "addr:street":"Oak St",
    "iso:country":"US",
    "sg:address":"11070 Oak St",
    "sg:city":"El Monte",
    "sg:classifiers":[
        {
            "category":"Organizations",
            "subcategory":"Religious Organization",
            "type":"Services"
        }
    ],
    "sg:phone":"+1 626 442 3438",
    "sg:postcode":"91731",
    "sg:province":"CA",
    "sg:tags":[
        "church"
    ],
    "sg:website":"www.tjc.org",
    "wof:name":"True Jesus Church In Sthrn Cal",
    "wof:placetype":"venue"
},
  "geometry": {"coordinates":[-118.03425,34.069968],"type":"Point"}
}