{
  "type": "Feature",
  "properties": {
    "addr:full":"2198 6th St Ste 100 Berkeley CA 94710",
    "addr:housenumber":"2198",
    "addr:postcode":"94710",
    "addr:street":"6Th St Ste 100",
    "iso:country":"US",
    "sg:address":"2198 6th St Ste 100",
    "sg:city":"Berkeley",
    "sg:classifiers":[
        {
            "category":"Health Services",
            "subcategory":"Medical Lab",
            "type":"Services"
        },
        {
            "category":"Insurance",
            "subcategory":"Health Insurance",
            "type":"Services"
        }
    ],
    "sg:phone":"+1 510 848 1112",
    "sg:postcode":"94710",
    "sg:province":"CA",
    "sg:tags":[
        "maintenance"
    ],
    "wof:name":"National Resource Center For P",
    "wof:placetype":"venue"
},
  "geometry": {"coordinates":[-122.296791,37.865261],"type":"Point"}
}