{
  "type": "Feature",
  "properties": {
    "addr:full":"1619 S Main St Milpitas CA 95035",
    "addr:housenumber":"1619",
    "addr:postcode":"95035",
    "addr:street":"S Main St",
    "iso:country":"US",
    "sg:address":"1619 S Main St",
    "sg:city":"Milpitas",
    "sg:classifiers":[
        {
            "category":"Professional",
            "type":"Services"
        }
    ],
    "sg:phone":"+1 408 934 9614",
    "sg:postcode":"95035",
    "sg:province":"CA",
    "sg:tags":[
        "establishment"
    ],
    "sg:website":"www.pagegenie.com",
    "wof:name":"Paravision",
    "wof:placetype":"venue"
},
  "geometry": {"coordinates":[-121.902985,37.405767],"type":"Point"}
}