{
  "type": "Feature",
  "properties": {
    "iso:country":"US",
    "sg:address":"27482 Tiara Dr.",
    "sg:city":"Mission Viejo",
    "sg:classifiers":[
        {
            "category":"Building & Trades",
            "subcategory":"Construction",
            "type":"Services"
        }
    ],
    "sg:phone":"+1 949 293 2692",
    "sg:postcode":"92692",
    "sg:province":"CA",
    "sg:tags":[
        "contractor"
    ],
    "wof:name":"Amercon California Inc",
    "wof:placetype":"venue"
},
  "geometry": {"coordinates":[-117.650194,33.590557],"type":"Point"}
}