{
  "type": "Feature",
  "properties": {
    "addr:full":"911 E Chestnut Ave Lompoc CA 93436",
    "addr:housenumber":"911",
    "addr:postcode":"93436",
    "addr:street":"E Chestnut Ave",
    "iso:country":"US",
    "sg:address":"911 E Chestnut Ave",
    "sg:city":"Lompoc",
    "sg:classifiers":[
        {
            "category":"Retail",
            "subcategory":"Auto Repair",
            "type":"Services"
        }
    ],
    "sg:phone":"+1 805 736 9858",
    "sg:postcode":"93436",
    "sg:province":"CA",
    "sg:tags":[
        "repairing",
        "automobile"
    ],
    "wof:name":"Wessex Motors Inc",
    "wof:placetype":"venue"
},
  "geometry": {"coordinates":[-120.447166,34.642225],"type":"Point"}
}