{
  "type": "Feature",
  "properties": {
    "iso:country":"US",
    "sg:address":"1450 W 228th St Ste 22",
    "sg:city":"Torrance",
    "sg:classifiers":[
        {
            "category":"Cinema",
            "subcategory":"Movie Rental",
            "type":"Entertainment"
        }
    ],
    "sg:phone":"+1 310 530 1243",
    "sg:postcode":"90501",
    "sg:province":"CA",
    "sg:tags":[
        "game",
        "video"
    ],
    "wof:name":"Audio Video Plus Inc",
    "wof:placetype":"venue"
},
  "geometry": {"coordinates":[-118.302594,33.818872],"type":"Point"}
}