{
  "type": "Feature",
  "properties": {
    "addr:full":"1215 S St Andrews Pl Los Angeles CA 90019",
    "addr:housenumber":"1215",
    "addr:postcode":"90019",
    "addr:street":"S St;Pl",
    "iso:country":"US",
    "sg:address":"1215 S St Andrews Pl",
    "sg:city":"Los Angeles",
    "sg:classifiers":[
        {
            "category":"Shopping",
            "subcategory":"Jewelry",
            "type":"Retail Goods"
        }
    ],
    "sg:phone":"+1 323 734 1873",
    "sg:postcode":"90019",
    "sg:province":"CA",
    "wof:name":"Devas Devine Designs",
    "wof:placetype":"venue"
},
  "geometry": {"coordinates":[-118.311672,34.047508],"type":"Point"}
}