{
  "type": "Feature",
  "properties": {
    "addr:full":"5875 Mission Blvd Riverside CA 92509",
    "addr:housenumber":"5875",
    "addr:postcode":"92509",
    "addr:street":"Mission Blvd",
    "iso:country":"US",
    "sg:address":"5875 Mission Blvd",
    "sg:city":"Riverside",
    "sg:classifiers":[
        {
            "category":"Real Estate",
            "subcategory":"Real Estate Operator",
            "type":"Services"
        }
    ],
    "sg:phone":"+1 951 276 9529",
    "sg:postcode":"92509",
    "sg:province":"CA",
    "sg:tags":[
        "apartment"
    ],
    "wof:name":"Mission Palms Apartments",
    "wof:placetype":"venue"
},
  "geometry": {"coordinates":[-117.414906,34.187651],"type":"Point"}
}