{
  "type": "Feature",
  "properties": {
    "addr:full":"938 Podva Rd Danville CA 94526",
    "addr:housenumber":"938",
    "addr:postcode":"94526",
    "addr:street":"Podva Rd",
    "iso:country":"US",
    "sg:address":"938 Podva Rd",
    "sg:city":"Danville",
    "sg:classifiers":[
        {
            "category":"Banks & Credit Unions",
            "subcategory":"Bank",
            "type":"Services"
        }
    ],
    "sg:phone":"+1 925 457 7600",
    "sg:postcode":"94526",
    "sg:province":"CA",
    "sg:tags":[
        "loan",
        "real estate"
    ],
    "wof:name":"Golden West Mortgage Svc",
    "wof:placetype":"venue"
},
  "geometry": {"coordinates":[-121.99365,37.808393],"type":"Point"}
}