{
  "type": "Feature",
  "properties": {
    "iso:country":"US",
    "sg:address":"2453 Huntington Dr",
    "sg:city":"San Marino",
    "sg:classifiers":[
        {
            "category":"Health Services",
            "subcategory":"Dentist",
            "type":"Services"
        }
    ],
    "sg:phone":"+1 626 486 0700",
    "sg:postcode":"91108",
    "sg:province":"CA",
    "sg:website":"www.peterlamdds.com",
    "wof:name":"Lam Peter",
    "wof:placetype":"venue"
},
  "geometry": {"coordinates":[-118.102446,34.12353],"type":"Point"}
}