{
  "type": "Feature",
  "properties": {
    "iso:country":"US",
    "sg:address":"12365 Evensong Dr",
    "sg:city":"Los Angeles",
    "sg:classifiers":[
        {
            "category":"Wholesale",
            "subcategory":"Hardware",
            "type":"Manufacturing & Wholesale Goods"
        }
    ],
    "sg:phone":"+1 310 450 4323",
    "sg:postcode":"90064",
    "sg:province":"CA",
    "sg:tags":[
        "equipment",
        "refrigeration"
    ],
    "wof:name":"Reliance Marketing and Sales",
    "wof:placetype":"venue"
},
  "geometry": {"coordinates":[-118.446987,34.022976],"type":"Point"}
}