{
  "type": "Feature",
  "properties": {
    "addr:full":"19600 Almaden Rd San Jose CA 95120",
    "addr:postcode":"19600;95120",
    "addr:street":"Almaden Rd",
    "iso:country":"US",
    "sg:address":"19600 Almaden Rd",
    "sg:city":"San Jose",
    "sg:classifiers":[
        {
            "category":"Recreation",
            "type":"Entertainment"
        }
    ],
    "sg:phone":"+1 408 268 1272",
    "sg:postcode":"95120",
    "sg:province":"CA",
    "sg:tags":[
        "instruction",
        "gymnastic"
    ],
    "wof:name":"Almaden Valley Gymnastic Club",
    "wof:placetype":"venue"
},
  "geometry": {"coordinates":[-121.829551,37.196027],"type":"Point"}
}