{
  "type": "Feature",
  "properties": {
    "addr:full":"12328 Carmenita Rd Whittier CA 90605",
    "addr:housenumber":"12328",
    "addr:postcode":"90605",
    "addr:street":"Carmenita Rd",
    "iso:country":"US",
    "sg:address":"12328 Carmenita Rd",
    "sg:city":"Whittier",
    "sg:classifiers":[
        {
            "category":"Autos & Motor Vehicles",
            "subcategory":"Auto Supplies",
            "type":"Retail Goods"
        }
    ],
    "sg:phone":"+1 562 941 9419",
    "sg:postcode":"90605",
    "sg:province":"CA",
    "sg:tags":[
        "tire"
    ],
    "wof:name":"Isla's Tires",
    "wof:placetype":"venue"
},
  "geometry": {"coordinates":[-118.046997,33.919102],"type":"Point"}
}