{
  "type": "Feature",
  "properties": {
    "iso:country":"US",
    "sg:address":"833 S Western Ave, Ste #38",
    "sg:city":"Los Angeles",
    "sg:classifiers":[
        {
            "category":"Food & Beverages",
            "subcategory":"Candy",
            "type":"Retail Goods"
        },
        {
            "category":"Restaurant",
            "type":"Food & Drink"
        }
    ],
    "sg:phone":"+1 213 384 1999",
    "sg:postcode":"90005",
    "sg:province":"CA",
    "sg:tags":[
        "dessert",
        "korean"
    ],
    "wof:name":"Patisserie Eguchi",
    "wof:placetype":"venue"
},
  "geometry": {"coordinates":[-118.309067,34.057071],"type":"Point"}
}