{
  "type": "Feature",
  "properties": {
    "iso:country":"US",
    "sg:address":"40577 Albrae St",
    "sg:city":"Fremont",
    "sg:classifiers":[
        {
            "category":"Freight",
            "type":"Transportation"
        }
    ],
    "sg:phone":"+1 510 440 1758",
    "sg:postcode":"94538",
    "sg:province":"CA",
    "sg:tags":[
        "general"
    ],
    "wof:name":"Sears Fixture Warehouse",
    "wof:placetype":"venue"
},
  "geometry": {"coordinates":[-121.982122,37.518613],"type":"Point"}
}