{
  "type": "Feature",
  "properties": {
    "iso:country":"US",
    "sg:address":"6264 Ferris Sq",
    "sg:city":"San Diego",
    "sg:classifiers":[
        {
            "category":"Autos & Motor Vehicles",
            "subcategory":"Auto Supplies",
            "type":"Retail Goods"
        }
    ],
    "sg:phone":"+1 858 546 1818",
    "sg:postcode":"92121",
    "sg:province":"CA",
    "sg:tags":[
        "equipment",
        "racing",
        "car",
        "automobile"
    ],
    "wof:name":"Innovon",
    "wof:placetype":"venue"
},
  "geometry": {"coordinates":[-117.180593,32.889896],"type":"Point"}
}