{
  "type": "Feature",
  "properties": {
    "iso:country":"US",
    "sg:address":"8864 Ahmed Ave",
    "sg:city":"Elk Grove",
    "sg:classifiers":[
        {
            "category":"Building & Trades",
            "subcategory":"Construction",
            "type":"Services"
        }
    ],
    "sg:phone":"+1 916 686 8332",
    "sg:postcode":"95624",
    "sg:province":"CA",
    "sg:tags":[
        "home",
        "builder"
    ],
    "wof:name":"Home Owner Building",
    "wof:placetype":"venue"
},
  "geometry": {"coordinates":[-121.375121,38.404387],"type":"Point"}
}