{
  "type": "Feature",
  "properties": {
    "addr:full":"7320 Monterey St Gilroy CA 95020",
    "addr:housenumber":"7320",
    "addr:postcode":"95020",
    "addr:street":"Monterey St",
    "iso:country":"US",
    "sg:address":"7320 Monterey St",
    "sg:city":"Gilroy",
    "sg:classifiers":[
        {
            "category":"Retail",
            "subcategory":"Repair Shop",
            "type":"Services"
        }
    ],
    "sg:phone":"+1 408 842 4093",
    "sg:postcode":"95020",
    "sg:province":"CA",
    "sg:tags":[
        "upholsterer"
    ],
    "wof:name":"Banning Upholstery",
    "wof:placetype":"venue"
},
  "geometry": {"coordinates":[-121.56867099999999,37.006756],"type":"Point"}
}