{
  "type": "Feature",
  "properties": {
    "iso:country":"US",
    "sg:address":"673 S Waterman Ave",
    "sg:city":"San Bernardino",
    "sg:classifiers":[
        {
            "category":"Professional",
            "subcategory":"Business Services",
            "type":"Services"
        }
    ],
    "sg:phone":"+1 909 890 9014",
    "sg:postcode":"92408",
    "sg:province":"CA",
    "wof:name":"Secure Info Imaging",
    "wof:placetype":"venue"
},
  "geometry": {"coordinates":[-117.278686,34.091752],"type":"Point"}
}