{
  "type": "Feature",
  "properties": {
    "addr:full":"800 East Colorado Blvd., Suite 450 Pasadena CA 91101",
    "addr:housenumber":"800",
    "addr:postcode":"91101",
    "addr:street":"East Colorado Blvd. Suite 450",
    "iso:country":"US",
    "sg:address":"800 East Colorado Blvd., Suite 450",
    "sg:city":"Pasadena",
    "sg:classifiers":[
        {
            "category":"Health Services",
            "subcategory":"Clinic",
            "type":"Services"
        }
    ],
    "sg:phone":"+1 626 289 2223",
    "sg:postcode":"91101",
    "sg:province":"CA",
    "sg:tags":[
        "medical"
    ],
    "sg:website":"www.pasadena-eye.com",
    "wof:name":"David D. Richardson, MD, Inc.",
    "wof:placetype":"venue"
},
  "geometry": {"coordinates":[-118.133369,34.145557],"type":"Point"}
}