{
  "type": "Feature",
  "properties": {
    "iso:country":"US",
    "sg:address":"219 N Isabel St",
    "sg:city":"Glendale",
    "sg:classifiers":[
        {
            "category":"Building & Trades",
            "subcategory":"Construction",
            "type":"Services"
        }
    ],
    "sg:phone":"+1 818 507 6340",
    "sg:postcode":"91206",
    "sg:province":"CA",
    "sg:tags":[
        "contractor"
    ],
    "wof:name":"Karwoski Construction Cob",
    "wof:placetype":"venue"
},
  "geometry": {"coordinates":[-118.248937,34.149602],"type":"Point"}
}