{
  "type": "Feature",
  "properties": {
    "addr:full":"3803 W 6th Street Los Angeles CA 90020",
    "addr:housenumber":"3803",
    "addr:postcode":"90020",
    "addr:street":"W 6Th Street",
    "iso:country":"US",
    "sg:address":"3803 W 6th Street",
    "sg:city":"Los Angeles",
    "sg:classifiers":[
        {
            "category":"Shopping",
            "subcategory":"Beauty & Cosmetics",
            "type":"Retail Goods"
        }
    ],
    "sg:phone":"+1 213 389 3849",
    "sg:postcode":"90020",
    "sg:province":"CA",
    "sg:tags":[
        "supply"
    ],
    "wof:name":"Cosmetic City",
    "wof:placetype":"venue"
},
  "geometry": {"coordinates":[-118.30545600000001,34.063434],"type":"Point"}
}