{
  "type": "Feature",
  "properties": {
    "addr:full":"651 Via Alondra Camarillo CA 93012",
    "addr:housenumber":"651",
    "addr:postcode":"93012",
    "addr:street":"Via Alondra",
    "iso:country":"US",
    "sg:address":"651 Via Alondra",
    "sg:city":"Camarillo",
    "sg:classifiers":[
        {
            "category":"Shopping",
            "subcategory":"Computers & Home Electronics",
            "type":"Retail Goods"
        }
    ],
    "sg:phone":"+1 805 388 6068",
    "sg:postcode":"93012",
    "sg:province":"CA",
    "sg:tags":[
        "equipment",
        "dealer"
    ],
    "wof:name":"G & C Technologies",
    "wof:placetype":"venue"
},
  "geometry": {"coordinates":[-119.02544899999999,34.223478],"type":"Point"}
}