{
  "type": "Feature",
  "properties": {
    "addr:full":"12881 State Hwy 145 Madera CA 93637",
    "addr:housenumber":"12881",
    "addr:postcode":"93637",
    "addr:street":"State Hwy 145",
    "iso:country":"US",
    "sg:address":"12881 State Hwy 145",
    "sg:city":"Madera",
    "sg:classifiers":[
        {
            "category":"Professional",
            "type":"Services"
        }
    ],
    "sg:phone":"+1 559 674 2401",
    "sg:postcode":"93637",
    "sg:province":"CA",
    "wof:name":"I Access Center",
    "wof:placetype":"venue"
},
  "geometry": {"coordinates":[-120.055949,36.936965],"type":"Point"}
}