{
  "type": "Feature",
  "properties": {
    "iso:country":"US",
    "sg:address":"8000 Haskell Ave",
    "sg:city":"Van Nuys",
    "sg:classifiers":[
        {
            "category":"Professional",
            "subcategory":"Computer Services",
            "type":"Services"
        }
    ],
    "sg:phone":"+1 310 575 4440",
    "sg:postcode":"91406",
    "sg:province":"CA",
    "sg:tags":[
        "printing",
        "direct-mail",
        "graphic-design"
    ],
    "sg:website":"http://www.uprinting.com",
    "wof:name":"UPrinting",
    "wof:placetype":"venue"
},
  "geometry": {"coordinates":[-118.47493900000001,34.216696],"type":"Point"}
}