{
  "type": "Feature",
  "properties": {
    "addr:full":"925 Blossom Hill Rd Ste 100 San Jose CA 95123",
    "addr:housenumber":"925",
    "addr:postcode":"95123",
    "addr:street":"Blossom Hill Rd Ste 100",
    "iso:country":"US",
    "sg:address":"925 Blossom Hill Rd Ste 100",
    "sg:city":"San Jose",
    "sg:classifiers":[
        {
            "category":"Personal",
            "subcategory":"Nail Salon",
            "type":"Services"
        }
    ],
    "sg:phone":"+1 408 972 8882",
    "sg:postcode":"95123",
    "sg:province":"CA",
    "wof:name":"Fantasy Beauty Spa",
    "wof:placetype":"venue"
},
  "geometry": {"coordinates":[-121.863415,37.250458],"type":"Point"}
}