{
  "type": "Feature",
  "properties": {
    "iso:country":"US",
    "sg:address":"9614 Cozycroft Ave",
    "sg:city":"Chatsworth",
    "sg:classifiers":[
        {
            "category":"Wholesale",
            "subcategory":"Machinery & Supplies",
            "type":"Manufacturing & Wholesale Goods"
        }
    ],
    "sg:phone":"+1 818 998 7646",
    "sg:postcode":"91311",
    "sg:province":"CA",
    "sg:tags":[
        "equipment",
        "industry",
        "industrial",
        "mfg"
    ],
    "wof:name":"Corintre",
    "wof:placetype":"venue"
},
  "geometry": {"coordinates":[-118.581907,34.244266],"type":"Point"}
}