{
  "type": "Feature",
  "properties": {
    "iso:country":"US",
    "sg:address":"2736 Bechelli Ln",
    "sg:city":"Redding",
    "sg:classifiers":[
        {
            "category":"Home & Garden",
            "subcategory":"Household Appliances",
            "type":"Retail Goods"
        }
    ],
    "sg:phone":"+1 530 223 1970",
    "sg:postcode":"96002",
    "sg:province":"CA",
    "sg:tags":[
        "machine",
        "sewing"
    ],
    "wof:name":"Hokema's Appliance Parts",
    "wof:placetype":"venue"
},
  "geometry": {"coordinates":[-122.362798,40.567485],"type":"Point"}
}