{
  "type": "Feature",
  "properties": {
    "addr:full":"340 G St Davis CA 95616",
    "addr:housenumber":"340",
    "addr:postcode":"95616",
    "addr:street":"G St",
    "iso:country":"US",
    "sg:address":"340 G St",
    "sg:city":"Davis",
    "sg:classifiers":[
        {
            "category":"Organizations",
            "subcategory":"Non-profit Organization",
            "type":"Services"
        }
    ],
    "sg:phone":"+1 530 757 4495",
    "sg:postcode":"95616",
    "sg:province":"CA",
    "wof:name":"Public Service Skills",
    "wof:placetype":"venue"
},
  "geometry": {"coordinates":[-121.739405,38.545695],"type":"Point"}
}