{
  "type": "Feature",
  "properties": {
    "addr:full":"12909 Cantara St North Hollywood CA 91605",
    "addr:housenumber":"12909",
    "addr:postcode":"91605",
    "addr:street":"Cantara St",
    "iso:country":"US",
    "sg:address":"12909 Cantara St",
    "sg:city":"North Hollywood",
    "sg:classifiers":[
        {
            "category":"Organizations",
            "subcategory":"Religious Organization",
            "type":"Services"
        }
    ],
    "sg:phone":"+1 818 997 9657",
    "sg:postcode":"91605",
    "sg:province":"CA",
    "wof:name":"Wat Thai Theravada Buddist Center",
    "wof:placetype":"venue"
},
  "geometry": {"coordinates":[-118.415001,34.2197],"type":"Point"}
}