{
  "type": "Feature",
  "properties": {
    "iso:country":"US",
    "sg:address":"3222 Geary Blvd",
    "sg:city":"San Francisco",
    "sg:classifiers":[
        {
            "category":"Shopping",
            "subcategory":"Mobile Phones",
            "type":"Retail Goods"
        },
        {
            "category":"Utilities",
            "type":"Services"
        }
    ],
    "sg:phone":"+1 415 680 1022",
    "sg:postcode":"94118",
    "sg:province":"CA",
    "sg:tags":[
        "provider",
        "internet"
    ],
    "sg:website":"www.evo2inc.com",
    "wof:name":"Verizon Wireless EVO Stores",
    "wof:placetype":"venue"
},
  "geometry": {"coordinates":[-122.453732,37.781831],"type":"Point"}
}