{
  "type": "Feature",
  "properties": {
    "iso:country":"US",
    "sg:address":"1600 Sacramento Ave",
    "sg:city":"West Sacramento",
    "sg:classifiers":[
        {
            "category":"Personal",
            "subcategory":"Barber",
            "type":"Services"
        }
    ],
    "sg:phone":"+1 916 371 3065",
    "sg:postcode":"95605",
    "sg:province":"CA",
    "wof:name":"River City Barbers",
    "wof:placetype":"venue"
},
  "geometry": {"coordinates":[-121.53985,38.591101],"type":"Point"}
}