{
  "type": "Feature",
  "properties": {
    "iso:country":"US",
    "sg:address":"1401 Merkley Ave",
    "sg:city":"West Sacramento",
    "sg:classifiers":[
        {
            "category":"Banks & Credit Unions",
            "subcategory":"Bank",
            "type":"Services"
        }
    ],
    "sg:phone":"+1 916 371 1010",
    "sg:postcode":"95691",
    "sg:province":"CA",
    "wof:name":"U S Bank",
    "wof:placetype":"venue"
},
  "geometry": {"coordinates":[-121.52600099999999,38.579201],"type":"Point"}
}