{
  "type": "Feature",
  "properties": {
    "iso:country":"US",
    "sg:address":"1410 S Orange Grove Ave",
    "sg:city":"Los Angeles",
    "sg:classifiers":[
        {
            "category":"Shopping",
            "subcategory":"Clothing, Apparel, & Fashions",
            "type":"Retail Goods"
        }
    ],
    "sg:phone":"+1 323 930 4822",
    "sg:postcode":"90019",
    "sg:province":"CA",
    "sg:tags":[
        "clothing",
        "women's"
    ],
    "wof:name":"Hari Casuals",
    "wof:placetype":"venue"
},
  "geometry": {"coordinates":[-118.365597,34.050848],"type":"Point"}
}