{
  "type": "Feature",
  "properties": {
    "iso:country":"US",
    "sg:address":"2638 E Vernon Ave",
    "sg:city":"Vernon",
    "sg:classifiers":[
        {
            "category":"Manufacturing",
            "subcategory":"Food",
            "type":"Manufacturing & Wholesale Goods"
        }
    ],
    "sg:phone":"+1 323 585 6599",
    "sg:postcode":"90058",
    "sg:province":"CA",
    "sg:tags":[
        "frozen",
        "dinner",
        "mexican",
        "mfg"
    ],
    "sg:website":"http://www.crfoods.com",
    "wof:name":"Camino Real Foods Inc",
    "wof:placetype":"venue"
},
  "geometry": {"coordinates":[-118.225662,34.005339],"type":"Point"}
}