{
  "type": "Feature",
  "properties": {
    "iso:country":"US",
    "sg:address":"22665 Macfarlane Dr",
    "sg:city":"Woodland Hills",
    "sg:classifiers":[
        {
            "category":"Professional",
            "type":"Services"
        }
    ],
    "sg:phone":"+1 818 597 4300",
    "sg:postcode":"91364",
    "sg:province":"CA",
    "sg:tags":[
        "establishment"
    ],
    "wof:name":"Intelligent Dispensing Systems",
    "wof:placetype":"venue"
},
  "geometry": {"coordinates":[-118.620032,34.162638],"type":"Point"}
}