{
  "type": "Feature",
  "properties": {
    "iso:country":"US",
    "sg:address":"1508 Emery Ave",
    "sg:city":"Bakersfield",
    "sg:classifiers":[
        {
            "category":"Freight",
            "type":"Transportation"
        }
    ],
    "sg:phone":"+1 805 501 3007",
    "sg:postcode":"93304",
    "sg:province":"CA",
    "sg:tags":[
        "hauling",
        "trucking"
    ],
    "wof:name":"Sweetpea Trucking",
    "wof:placetype":"venue"
},
  "geometry": {"coordinates":[-119.01800900000001,35.321673],"type":"Point"}
}