{
  "type": "Feature",
  "properties": {
    "iso:country":"US",
    "sg:address":"912 Drake Dr",
    "sg:city":"Davis",
    "sg:classifiers":[
        {
            "category":"Building & Trades",
            "subcategory":"Construction",
            "type":"Services"
        }
    ],
    "sg:phone":"+1 530 792 7176",
    "sg:postcode":"95616",
    "sg:province":"CA",
    "sg:tags":[
        "tile-contractors"
    ],
    "wof:name":"C V S Tile & Stone",
    "wof:placetype":"venue"
},
  "geometry": {"coordinates":[-121.760769,38.560003],"type":"Point"}
}