{
  "type": "Feature",
  "properties": {
    "addr:full":"6211 Breckinridge Ln Chino CA 91710",
    "addr:housenumber":"6211",
    "addr:postcode":"91710",
    "addr:street":"Breckinridge Ln",
    "iso:country":"US",
    "sg:address":"6211 Breckinridge Ln",
    "sg:city":"Chino",
    "sg:classifiers":[
        {
            "category":"Professional",
            "subcategory":"Business Services",
            "type":"Services"
        }
    ],
    "sg:phone":"+1 909 628 5637",
    "sg:postcode":"91710",
    "sg:province":"CA",
    "sg:tags":[
        "interior",
        "consultant",
        "design",
        "decorator"
    ],
    "wof:name":"Cap I Interiors",
    "wof:placetype":"venue"
},
  "geometry": {"coordinates":[-117.668171,34.007326],"type":"Point"}
}