{
  "type": "Feature",
  "properties": {
    "iso:country":"US",
    "sg:address":"2200 Beacon Hill Pl",
    "sg:city":"El Dorado Hills",
    "sg:classifiers":[
        {
            "category":"Building & Trades",
            "subcategory":"Landscaping Services",
            "type":"Services"
        }
    ],
    "sg:phone":"+1 916 933 5974",
    "sg:postcode":"95762",
    "sg:province":"CA",
    "sg:tags":[
        "designer",
        "landscape"
    ],
    "wof:name":"Daydreams Landscape Design",
    "wof:placetype":"venue"
},
  "geometry": {"coordinates":[-121.089932,38.723203],"type":"Point"}
}