{
  "type": "Feature",
  "properties": {
    "iso:country":"US",
    "sg:address":"12500 Riverside Dr",
    "sg:city":"Studio City",
    "sg:classifiers":[
        {
            "category":"Freight",
            "type":"Transportation"
        }
    ],
    "sg:phone":"+1 818 623 8400",
    "sg:postcode":"91607",
    "sg:province":"CA",
    "sg:tags":[
        "delivery"
    ],
    "sg:website":"www.usaexpressinc.com",
    "wof:name":"USA Express",
    "wof:placetype":"venue"
},
  "geometry": {"coordinates":[-118.40944500000001,34.157616],"type":"Point"}
}