{
  "type": "Feature",
  "properties": {
    "iso:country":"US",
    "sg:address":"9 2nd Ave",
    "sg:city":"Chula Vista",
    "sg:classifiers":[
        {
            "category":"Professional",
            "subcategory":"Lawyer & Legal Services",
            "type":"Services"
        }
    ],
    "sg:phone":"+1 619 425 1300",
    "sg:postcode":"91910",
    "sg:province":"CA",
    "sg:tags":[
        "attorney"
    ],
    "wof:name":"Linda R Navarro Law Offices",
    "wof:placetype":"venue"
},
  "geometry": {"coordinates":[-117.079412,32.651952],"type":"Point"}
}