{
  "type": "Feature",
  "properties": {
    "addr:full":"4610 Pelleur St Lynwood CA 90262",
    "addr:housenumber":"4610",
    "addr:postcode":"90262",
    "addr:street":"Pelleur St",
    "iso:country":"US",
    "sg:address":"4610 Pelleur St",
    "sg:city":"Lynwood",
    "sg:classifiers":[
        {
            "category":"Place Of Worship",
            "type":"Public Place"
        }
    ],
    "sg:phone":"+1 310 637 6205",
    "sg:postcode":"90262",
    "sg:province":"CA",
    "sg:tags":[
        "church"
    ],
    "wof:name":"New Haven Church Of God In Christ",
    "wof:placetype":"venue"
},
  "geometry": {"coordinates":[-118.188941,33.909882],"type":"Point"}
}