{
  "type": "Feature",
  "properties": {
    "addr:full":"1514 W 259th St Harbor City CA 90710",
    "addr:housenumber":"1514",
    "addr:postcode":"90710",
    "addr:street":"W 259Th St",
    "iso:country":"US",
    "sg:address":"1514 W 259th St",
    "sg:city":"Harbor City",
    "sg:classifiers":[
        {
            "category":"Building & Trades",
            "subcategory":"Equipment Rental",
            "type":"Services"
        }
    ],
    "sg:phone":"+1 310 539 5348",
    "sg:postcode":"90710",
    "sg:province":"CA",
    "sg:tags":[
        "scaffolding"
    ],
    "wof:name":"Allrite Scaffolding",
    "wof:placetype":"venue"
},
  "geometry": {"coordinates":[-118.304095,33.78812],"type":"Point"}
}