{
  "type": "Feature",
  "properties": {
    "iso:country":"US",
    "sg:address":"701 Bath St",
    "sg:city":"Santa Barbara",
    "sg:classifiers":[
        {
            "category":"Food & Beverages",
            "subcategory":"Groceries & Convenience Stores",
            "type":"Retail Goods"
        }
    ],
    "sg:phone":"+1 805 965 5455",
    "sg:postcode":"93101",
    "sg:province":"CA",
    "sg:tags":[
        "grocer"
    ],
    "wof:name":"Little Corner Store",
    "wof:placetype":"venue"
},
  "geometry": {"coordinates":[-119.702702,34.416409],"type":"Point"}
}