{
  "type": "Feature",
  "properties": {
    "addr:full":"14801 Keswick St Van Nuys CA 91405",
    "addr:housenumber":"14801",
    "addr:postcode":"91405",
    "addr:street":"Keswick St",
    "iso:country":"US",
    "sg:address":"14801 Keswick St",
    "sg:city":"Van Nuys",
    "sg:classifiers":[
        {
            "category":"Manufacturing",
            "subcategory":"Metals",
            "type":"Manufacturing & Wholesale Goods"
        }
    ],
    "sg:phone":"+1 818 780 3563",
    "sg:postcode":"91405",
    "sg:province":"CA",
    "sg:tags":[
        "stamping"
    ],
    "wof:name":"Aristo-Craft Metal Products Co",
    "wof:placetype":"venue"
},
  "geometry": {"coordinates":[-118.453598,34.210343],"type":"Point"}
}