{
  "type": "Feature",
  "properties": {
    "iso:country":"US",
    "sg:address":"9011 Stinson Beach Way",
    "sg:city":"Elk Grove",
    "sg:classifiers":[
        {
            "category":"Social Services",
            "subcategory":"Adult Care",
            "type":"Services"
        }
    ],
    "sg:phone":"+1 916 422 8500",
    "sg:postcode":"95758",
    "sg:province":"CA",
    "sg:tags":[
        "residential"
    ],
    "wof:name":"A Senior Solution",
    "wof:placetype":"venue"
},
  "geometry": {"coordinates":[-121.451492,38.427344],"type":"Point"}
}