{
  "type": "Feature",
  "properties": {
    "addr:full":"3937 Stratton Dr Riverside CA 92505",
    "addr:housenumber":"3937",
    "addr:postcode":"92505",
    "addr:street":"Stratton Dr",
    "iso:country":"US",
    "sg:address":"3937 Stratton Dr",
    "sg:city":"Riverside",
    "sg:classifiers":[
        {
            "category":"Wholesale",
            "subcategory":"Non-durable Goods",
            "type":"Manufacturing & Wholesale Goods"
        }
    ],
    "sg:phone":"+1 951 354 8560",
    "sg:postcode":"92505",
    "sg:province":"CA",
    "wof:name":"Duecker Distribution",
    "wof:placetype":"venue"
},
  "geometry": {"coordinates":[-117.48245300000001,33.903635],"type":"Point"}
}