{
  "type": "Feature",
  "properties": {
    "addr:full":"11865 Inglewood Ave Hawthorne CA 90250",
    "addr:housenumber":"11865",
    "addr:postcode":"90250",
    "addr:street":"Inglewood Ave",
    "iso:country":"US",
    "sg:address":"11865 Inglewood Ave",
    "sg:city":"Hawthorne",
    "sg:classifiers":[
        {
            "category":"Health Services",
            "subcategory":"Doctor",
            "type":"Services"
        }
    ],
    "sg:phone":"+1 310 349 8338",
    "sg:postcode":"90250",
    "sg:province":"CA",
    "sg:tags":[
        "clinic"
    ],
    "wof:name":"San Jose Community Clinic",
    "wof:placetype":"venue"
},
  "geometry": {"coordinates":[-118.361296,33.926399],"type":"Point"}
}