{
  "type": "Feature",
  "properties": {
    "iso:country":"US",
    "sg:address":"3621 E Olympic Boulevard",
    "sg:city":"Los Angeles",
    "sg:classifiers":[
        {
            "category":"Retail",
            "subcategory":"Auto Repair",
            "type":"Services"
        }
    ],
    "sg:phone":"+1 323 266 3765",
    "sg:postcode":"90023",
    "sg:province":"CA",
    "wof:name":"Rivera's Transmissions",
    "wof:placetype":"venue"
},
  "geometry": {"coordinates":[-118.200484,34.018929],"type":"Point"}
}