{
  "type": "Feature",
  "properties": {
    "iso:country":"US",
    "sg:address":"15050 Cholla Rd",
    "sg:city":"White Water",
    "sg:classifiers":[
        {
            "category":"Building & Trades",
            "subcategory":"Construction",
            "type":"Services"
        }
    ],
    "sg:phone":"+1 760 251 5113",
    "sg:postcode":"92282",
    "sg:province":"CA",
    "sg:tags":[
        "paving",
        "contractor"
    ],
    "wof:name":"Zoltan's Grading & Paving Inc",
    "wof:placetype":"venue"
},
  "geometry": {"coordinates":[-116.687051,33.925978],"type":"Point"}
}