{
  "type": "Feature",
  "properties": {
    "iso:country":"US",
    "sg:address":"747 N Twin Oaks Valley Rd",
    "sg:city":"San Marcos",
    "sg:classifiers":[
        {
            "category":"Building & Trades",
            "subcategory":"Construction",
            "type":"Services"
        }
    ],
    "sg:phone":"+1 760 751 1138",
    "sg:postcode":"92069",
    "sg:province":"CA",
    "sg:tags":[
        "contractor"
    ],
    "wof:name":"Screenmobile The",
    "wof:placetype":"venue"
},
  "geometry": {"coordinates":[-117.16164000000001,33.15107],"type":"Point"}
}