{
  "type": "Feature",
  "properties": {
    "addr:full":"795 Valencia St San Francisco CA 94110",
    "addr:housenumber":"795",
    "addr:postcode":"94110",
    "addr:street":"Valencia St",
    "iso:country":"US",
    "sg:address":"795 Valencia St",
    "sg:city":"San Francisco",
    "sg:classifiers":[
        {
            "category":"Cafe",
            "type":"Food & Drink"
        },
        {
            "category":"Bars & Pubs",
            "subcategory":"Wine Bar",
            "type":"Food & Drink"
        }
    ],
    "sg:menulink":"http://www.allmenus.com/ca/san-francisco/63239-parea-wine-bar-and-cafe/menu/",
    "sg:phone":"+1 415 255 2102",
    "sg:postcode":"94110",
    "sg:province":"CA",
    "sg:tags":[
        "mediterranean"
    ],
    "wof:name":"Parea Wine Bar And Cafe",
    "wof:placetype":"venue"
},
  "geometry": {"coordinates":[-122.421477,37.760311],"type":"Point"}
}