{
  "type": "Feature",
  "properties": {
    "iso:country":"US",
    "sg:address":"161 W 25th Ave",
    "sg:city":"San Mateo",
    "sg:classifiers":[
        {
            "category":"Professional",
            "subcategory":"Accounting & Tax Preparation",
            "type":"Services"
        }
    ],
    "sg:phone":"+1 650 349 4240",
    "sg:postcode":"94403",
    "sg:province":"CA",
    "sg:tags":[
        "return",
        "filing"
    ],
    "wof:name":"Anne M Wilson",
    "wof:placetype":"venue"
},
  "geometry": {"coordinates":[-122.307992,37.543534],"type":"Point"}
}