{
  "type": "Feature",
  "properties": {
    "addr:full":"810 4th Ave San Diego CA 92101",
    "addr:housenumber":"810",
    "addr:postcode":"92101",
    "addr:street":"4Th Ave",
    "iso:country":"US",
    "sg:address":"810 4th Ave",
    "sg:city":"San Diego",
    "sg:classifiers":[
        {
            "category":"Restaurant",
            "type":"Food & Drink"
        }
    ],
    "sg:phone":"+1 619 702 7967",
    "sg:postcode":"92101",
    "sg:province":"CA",
    "sg:tags":[
        "indian"
    ],
    "sg:website":"www.gourmet-india.us",
    "wof:name":"Gourmet India",
    "wof:placetype":"venue"
},
  "geometry": {"coordinates":[-117.16106499999999,32.71349],"type":"Point"}
}