{
  "type": "Feature",
  "properties": {
    "addr:full":"625 E Main St Santa Paula CA 93060",
    "addr:housenumber":"625",
    "addr:postcode":"93060",
    "addr:street":"E Main St",
    "iso:country":"US",
    "sg:address":"625 E Main St",
    "sg:city":"Santa Paula",
    "sg:classifiers":[
        {
            "category":"Organizations",
            "subcategory":"Non-profit Organization",
            "type":"Services"
        }
    ],
    "sg:phone":"+1 805 525 4669",
    "sg:postcode":"93060",
    "sg:province":"CA",
    "sg:tags":[
        "info",
        "addiction",
        "abuse",
        "treatment",
        "drug"
    ],
    "wof:name":"Aegis Medica Systems Inc",
    "wof:placetype":"venue"
},
  "geometry": {"coordinates":[-119.06796900000001,34.351466],"type":"Point"}
}