{
  "type": "Feature",
  "properties": {
    "iso:country":"US",
    "sg:address":"1507 S Oxnard Blvd",
    "sg:city":"Oxnard",
    "sg:classifiers":[
        {
            "category":"Utilities",
            "subcategory":"Mobile Phone",
            "type":"Services"
        }
    ],
    "sg:phone":"+1 805 240 9112",
    "sg:postcode":"93030",
    "sg:province":"CA",
    "sg:tags":[
        "communication",
        "radiotelephone"
    ],
    "wof:name":"All In One Wireless",
    "wof:placetype":"venue"
},
  "geometry": {"coordinates":[-119.171919,34.185359],"type":"Point"}
}