{
  "type": "Feature",
  "properties": {
    "addr:full":"2043 Westcliff Dr Newport Beach CA 92660",
    "addr:housenumber":"2043",
    "addr:postcode":"92660",
    "addr:street":"Westcliff Dr",
    "iso:country":"US",
    "sg:address":"2043 Westcliff Dr",
    "sg:city":"Newport Beach",
    "sg:classifiers":[
        {
            "category":"Professional",
            "subcategory":"Detective & Security Services",
            "type":"Services"
        }
    ],
    "sg:phone":"+1 949 642 1243",
    "sg:postcode":"92660",
    "sg:province":"CA",
    "sg:tags":[
        "investigator"
    ],
    "wof:name":"G W Finck & Assoc",
    "wof:placetype":"venue"
},
  "geometry": {"coordinates":[-117.907422,33.627331],"type":"Point"}
}