{
  "type": "Feature",
  "properties": {
    "iso:country":"US",
    "sg:address":"19023 S Reyes Ave",
    "sg:city":"Compton",
    "sg:classifiers":[
        {
            "category":"Retail",
            "subcategory":"Auto Repair",
            "type":"Services"
        }
    ],
    "sg:phone":"+1 310 639 7693",
    "sg:postcode":"90221",
    "sg:province":"CA",
    "sg:tags":[
        "truck"
    ],
    "wof:name":"South Coast Svc",
    "wof:placetype":"venue"
},
  "geometry": {"coordinates":[-118.210596,33.857024],"type":"Point"}
}