{
  "type": "Feature",
  "properties": {
    "addr:full":"1275 Minnesota St San Francisco CA 94107",
    "addr:housenumber":"1275",
    "addr:postcode":"94107",
    "addr:street":"Minnesota St",
    "iso:country":"US",
    "sg:address":"1275 Minnesota St",
    "sg:city":"San Francisco",
    "sg:classifiers":[
        {
            "category":"Professional",
            "type":"Services"
        }
    ],
    "sg:phone":"+1 415 970 9481",
    "sg:postcode":"94107",
    "sg:province":"CA",
    "wof:name":"Dimensional Science LLC",
    "wof:placetype":"venue"
},
  "geometry": {"coordinates":[-122.38986199999999,37.754964],"type":"Point"}
}