{
  "type": "Feature",
  "properties": {
    "addr:full":"1920 South Coast Hwy Ste A Oceanside CA 92154",
    "addr:housenumber":"1920",
    "addr:postcode":"92154",
    "addr:street":"South Coast Hwy Ste A",
    "iso:country":"US",
    "sg:address":"1920 South Coast Hwy Ste A",
    "sg:city":"Oceanside",
    "sg:classifiers":[
        {
            "category":"Personal",
            "type":"Services"
        },
        {
            "category":"Health Services",
            "subcategory":"Health Practitioner",
            "type":"Services"
        }
    ],
    "sg:phone":"+1 760 579 0850",
    "sg:postcode":"92154",
    "sg:province":"CA",
    "sg:tags":[
        "home",
        "care"
    ],
    "sg:website":"www.reliantseniorcare.com",
    "wof:name":"Reliant Senior Care",
    "wof:placetype":"venue"
},
  "geometry": {"coordinates":[-117.36018900000001,33.173065],"type":"Point"}
}