{
  "type": "Feature",
  "properties": {
    "iso:country":"US",
    "sg:address":"1264 S Waterman Ave",
    "sg:city":"San Bernardino",
    "sg:classifiers":[
        {
            "category":"Wholesale",
            "subcategory":"Machinery & Supplies",
            "type":"Manufacturing & Wholesale Goods"
        }
    ],
    "sg:phone":"+1 909 388 9260",
    "sg:postcode":"92408",
    "sg:province":"CA",
    "sg:tags":[
        "equipment",
        "industrial"
    ],
    "wof:name":"Proyectos E Instrumentos",
    "wof:placetype":"venue"
},
  "geometry": {"coordinates":[-117.278803,34.07833],"type":"Point"}
}