{
  "type": "Feature",
  "properties": {
    "iso:country":"US",
    "sg:address":"635 S Hill St",
    "sg:city":"Los Angeles",
    "sg:classifiers":[
        {
            "category":"Shopping",
            "subcategory":"Jewelry",
            "type":"Retail Goods"
        }
    ],
    "sg:phone":"+1 213 627 5447",
    "sg:postcode":"90014",
    "sg:province":"CA",
    "sg:tags":[
        "designer"
    ],
    "wof:name":"Gold Panther Jewelry",
    "wof:placetype":"venue"
},
  "geometry": {"coordinates":[-118.254122,34.046453],"type":"Point"}
}