{
  "type": "Feature",
  "properties": {
    "addr:full":"411 1st St Gilroy CA 95020",
    "addr:housenumber":"411",
    "addr:postcode":"95020",
    "addr:street":"1St St",
    "iso:country":"US",
    "sg:address":"411 1st St",
    "sg:city":"Gilroy",
    "sg:classifiers":[
        {
            "category":"Personal",
            "subcategory":"Beauty Salon",
            "type":"Services"
        }
    ],
    "sg:phone":"+1 408 848 2580",
    "sg:postcode":"95020",
    "sg:province":"CA",
    "wof:name":"New Image Beauty Salon",
    "wof:placetype":"venue"
},
  "geometry": {"coordinates":[-121.578716,37.013429],"type":"Point"}
}