{
  "type": "Feature",
  "properties": {
    "addr:full":"1542 W Carson St Torrance CA 90501",
    "addr:housenumber":"1542",
    "addr:postcode":"90501",
    "addr:street":"W Carson St",
    "iso:country":"US",
    "sg:address":"1542 W Carson St",
    "sg:city":"Torrance",
    "sg:classifiers":[
        {
            "category":"Restaurant",
            "type":"Food & Drink"
        }
    ],
    "sg:phone":"+1 310 320 0200",
    "sg:postcode":"90501",
    "sg:province":"CA",
    "sg:tags":[
        "eating",
        "sushi",
        "bar"
    ],
    "wof:name":"Kantaro Sushi",
    "wof:placetype":"venue"
},
  "geometry": {"coordinates":[-118.306,33.8316],"type":"Point"}
}