{
  "type": "Feature",
  "properties": {
    "addr:full":"2973 16th St. San Francisco CA 94103",
    "addr:housenumber":"2973",
    "addr:postcode":"94103",
    "addr:street":"16Th St.",
    "iso:country":"US",
    "sg:address":"2973 16th St.",
    "sg:city":"San Francisco",
    "sg:classifiers":[
        {
            "category":"Professional",
            "subcategory":"Computer Services",
            "type":"Services"
        }
    ],
    "sg:phone":"+1 800 965 1977",
    "sg:postcode":"94103",
    "sg:province":"CA",
    "sg:tags":[
        "moped",
        "powersports",
        "mofa",
        "transportation"
    ],
    "sg:website":"http://www.1977mopeds.com",
    "wof:name":"1977 Mopeds",
    "wof:placetype":"venue"
},
  "geometry": {"coordinates":[-122.41931099999999,37.765003],"type":"Point"}
}