{
  "type": "Feature",
  "properties": {
    "addr:full":"2971 Wildhaven Cir Santa Maria CA 93454",
    "addr:housenumber":"2971",
    "addr:postcode":"93454",
    "addr:street":"Wildhaven Cir",
    "iso:country":"US",
    "sg:address":"2971 Wildhaven Cir",
    "sg:city":"Santa Maria",
    "sg:classifiers":[
        {
            "category":"Retail",
            "subcategory":"Animal Services",
            "type":"Services"
        }
    ],
    "sg:phone":"+1 805 922 1470",
    "sg:postcode":"93454",
    "sg:province":"CA",
    "wof:name":"Intara Arabians",
    "wof:placetype":"venue"
},
  "geometry": {"coordinates":[-120.395949,34.90461],"type":"Point"}
}