{
  "type": "Feature",
  "properties": {
    "addr:full":"651 E Ave de Las Flores Thousand Oaks CA 91360",
    "addr:housenumber":"651",
    "addr:postcode":"91360",
    "addr:street":"E Ave De Las Flores",
    "iso:country":"US",
    "sg:address":"651 E Ave de Las Flores",
    "sg:city":"Thousand Oaks",
    "sg:classifiers":[
        {
            "category":"Building & Trades",
            "subcategory":"Landscaping Services",
            "type":"Services"
        }
    ],
    "sg:phone":"+1 805 371 9437",
    "sg:postcode":"91360",
    "sg:province":"CA",
    "wof:name":"Pineda Miguel A",
    "wof:placetype":"venue"
},
  "geometry": {"coordinates":[-118.86393099999999,34.208541],"type":"Point"}
}