{
  "type": "Feature",
  "properties": {
    "iso:country":"US",
    "sg:address":"1809 S Street, Suite 102",
    "sg:city":"Sacramento",
    "sg:classifiers":[
        {
            "category":"Autos & Motor Vehicles",
            "subcategory":"Automobile Sales",
            "type":"Retail Goods"
        }
    ],
    "sg:phone":"+1 916 747 7497",
    "sg:postcode":"95811",
    "sg:province":"CA",
    "sg:tags":[
        "limo"
    ],
    "sg:website":"www.starlitelimousine.com/",
    "wof:name":"Starlite Limousine",
    "wof:placetype":"venue"
},
  "geometry": {"coordinates":[-121.486448,38.567737],"type":"Point"}
}