{
  "type": "Feature",
  "properties": {
    "iso:country":"US",
    "sg:address":"1886 El Dorado Ave",
    "sg:city":"Brentwood",
    "sg:classifiers":[
        {
            "category":"Real Estate",
            "subcategory":"Real Estate Services",
            "type":"Services"
        },
        {
            "category":"Real Estate",
            "subcategory":"Real Estate Agent",
            "type":"Services"
        }
    ],
    "sg:phone":"+1 925 392 8403",
    "sg:postcode":"94513",
    "sg:province":"CA",
    "sg:tags":[
        "buyer",
        "broker"
    ],
    "wof:name":"Panda Group Realty Inc",
    "wof:placetype":"venue"
},
  "geometry": {"coordinates":[-121.739249,37.953137],"type":"Point"}
}