{
  "type": "Feature",
  "properties": {
    "addr:full":"13325 Tobiasson Rd Poway CA 92064",
    "addr:housenumber":"13325",
    "addr:postcode":"ca 92064",
    "addr:street":"Tobiasson Rd",
    "iso:country":"US",
    "sg:address":"13325 Tobiasson Rd",
    "sg:city":"Poway",
    "sg:classifiers":[
        {
            "category":"Professional",
            "subcategory":"Management & Consulting",
            "type":"Services"
        }
    ],
    "sg:phone":"+1 858 679 9230",
    "sg:postcode":"92064",
    "sg:province":"CA",
    "sg:tags":[
        "consultant",
        "publishing"
    ],
    "wof:name":"K P Data Concepts",
    "wof:placetype":"venue"
},
  "geometry": {"coordinates":[-117.059946,32.962706],"type":"Point"}
}