{
  "type": "Feature",
  "properties": {
    "addr:full":"308 Wilson St Santa Rosa CA 95401",
    "addr:housenumber":"308",
    "addr:postcode":"ca 95401",
    "addr:street":"Wilson St",
    "iso:country":"US",
    "sg:address":"308 Wilson St",
    "sg:city":"Santa Rosa",
    "sg:classifiers":[
        {
            "category":"Bars & Pubs",
            "type":"Food & Drink"
        }
    ],
    "sg:menulink":"http://www.allmenus.com/ca/santa-rosa/52826-josefs-restaurant--bar/menu/",
    "sg:phone":"+1 707 571 8664",
    "sg:postcode":"95401",
    "sg:province":"CA",
    "sg:tags":[
        "french"
    ],
    "wof:name":"Josef's Restaurant & Bar",
    "wof:placetype":"venue"
},
  "geometry": {"coordinates":[-122.72079600000001,38.437953],"type":"Point"}
}