{
  "type": "Feature",
  "properties": {
    "addr:full":"398 S Green Valley Rd Watsonville CA 95076",
    "addr:housenumber":"398",
    "addr:postcode":"95076",
    "addr:street":"S Green Valley Rd",
    "iso:country":"US",
    "sg:address":"398 S Green Valley Rd",
    "sg:city":"Watsonville",
    "sg:classifiers":[
        {
            "category":"Health Services",
            "subcategory":"Doctor",
            "type":"Services"
        }
    ],
    "sg:phone":"+1 831 722 8123",
    "sg:postcode":"95076",
    "sg:province":"CA",
    "sg:tags":[
        "physician",
        "surgeon"
    ],
    "wof:name":"Edward Bradbury Inc",
    "wof:placetype":"venue"
},
  "geometry": {"coordinates":[-121.775614,36.932887],"type":"Point"}
}