{
  "type": "Feature",
  "properties": {
    "iso:country":"US",
    "sg:address":"213 Shadowrun Ct",
    "sg:city":"Redding",
    "sg:classifiers":[
        {
            "category":"Health Services",
            "subcategory":"Doctor",
            "type":"Services"
        }
    ],
    "sg:phone":"+1 530 246 1590",
    "sg:postcode":"96003",
    "sg:province":"CA",
    "sg:tags":[
        "physician",
        "surgeon"
    ],
    "wof:name":"N P Housecalls Medical Corp",
    "wof:placetype":"venue"
},
  "geometry": {"coordinates":[-122.398343,40.604293],"type":"Point"}
}