{
  "type": "Feature",
  "properties": {
    "addr:full":"5411 Madison Ave Sacramento CA 95841",
    "addr:housenumber":"5411",
    "addr:postcode":"95841",
    "addr:street":"Madison Ave",
    "iso:country":"US",
    "sg:address":"5411 Madison Ave",
    "sg:city":"Sacramento",
    "sg:classifiers":[
        {
            "category":"Freight",
            "type":"Transportation"
        },
        {
            "category":"Travel",
            "subcategory":"Travel Agent",
            "type":"Entertainment"
        }
    ],
    "sg:phone":"+1 916 338 6600",
    "sg:postcode":"95841",
    "sg:province":"CA",
    "sg:tags":[
        "operator",
        "tour",
        "arrangement"
    ],
    "wof:name":"Creative Transportation",
    "wof:placetype":"venue"
},
  "geometry": {"coordinates":[-121.340023,38.660756],"type":"Point"}
}