{
  "type": "Feature",
  "properties": {
    "iso:country":"US",
    "sg:address":"553 Martin Ave",
    "sg:city":"Rohnert Park",
    "sg:classifiers":[
        {
            "category":"Home & Garden",
            "subcategory":"Home Furnishings",
            "type":"Retail Goods"
        }
    ],
    "sg:phone":"+1 707 206 0879",
    "sg:postcode":"94928",
    "sg:province":"CA",
    "sg:tags":[
        "lighting",
        "fixture"
    ],
    "wof:name":"Designer Lighting Outlet",
    "wof:placetype":"venue"
},
  "geometry": {"coordinates":[-122.722328,38.354797],"type":"Point"}
}