{
  "type": "Feature",
  "properties": {
    "addr:full":"640 W 20th St Merced CA 95340",
    "addr:housenumber":"640",
    "addr:postcode":"95340",
    "addr:street":"W 20Th St",
    "iso:country":"US",
    "sg:address":"640 W 20th St",
    "sg:city":"Merced",
    "sg:classifiers":[
        {
            "category":"Professional",
            "subcategory":"Lawyer & Legal Services",
            "type":"Services"
        }
    ],
    "sg:phone":"+1 209 723 2990",
    "sg:postcode":"95340",
    "sg:province":"CA",
    "sg:tags":[
        "attorney"
    ],
    "wof:name":"Geraldine Brown Law Office",
    "wof:placetype":"venue"
},
  "geometry": {"coordinates":[-120.48418100000001,37.305228],"type":"Point"}
}