{
  "type": "Feature",
  "properties": {
    "iso:country":"US",
    "sg:address":"745 Parkway Plz",
    "sg:city":"El Cajon",
    "sg:classifiers":[
        {
            "category":"Sports & Exercise",
            "subcategory":"Bicycle Rental",
            "type":"Entertainment"
        }
    ],
    "sg:phone":"+1 619 579 6535",
    "sg:postcode":"92020",
    "sg:province":"CA",
    "sg:tags":[
        "wear"
    ],
    "sg:website":"www.champssports.com",
    "wof:name":"Champs",
    "wof:placetype":"venue"
},
  "geometry": {"coordinates":[-116.969002,32.8036],"type":"Point"}
}