{
  "type": "Feature",
  "properties": {
    "addr:full":"1859 Kentucky St Bakersfield CA 93305",
    "addr:housenumber":"1859",
    "addr:postcode":"93305",
    "addr:street":"Kentucky St",
    "iso:country":"US",
    "sg:address":"1859 Kentucky St",
    "sg:city":"Bakersfield",
    "sg:classifiers":[
        {
            "category":"Taxi",
            "type":"Transportation"
        }
    ],
    "sg:phone":"+1 661 363 0408",
    "sg:postcode":"93305",
    "sg:province":"CA",
    "sg:tags":[
        "taxicab"
    ],
    "wof:name":"Sinaloa Taxi Cab Svc",
    "wof:placetype":"venue"
},
  "geometry": {"coordinates":[-118.971915,35.373927],"type":"Point"}
}