{
  "type": "Feature",
  "properties": {
    "addr:full":"3100 Mowry Ave Fremont CA 94538",
    "addr:housenumber":"3100",
    "addr:postcode":"94538",
    "addr:street":"Mowry Ave",
    "iso:country":"US",
    "sg:address":"3100 Mowry Ave",
    "sg:city":"Fremont",
    "sg:classifiers":[
        {
            "category":"Insurance",
            "subcategory":"Insurance Agent",
            "type":"Services"
        },
        {
            "category":"Insurance",
            "subcategory":"Hazard Insurance",
            "type":"Services"
        },
        {
            "category":"Insurance",
            "subcategory":"Health Insurance",
            "type":"Services"
        }
    ],
    "sg:phone":"+1 510 739 1960",
    "sg:postcode":"94538",
    "sg:province":"CA",
    "sg:tags":[
        "employee",
        "auto",
        "benefit",
        "commercial",
        "business"
    ],
    "sg:website":"http://www.farmersagent.com/pcartacai",
    "wof:name":"Farmers Insurance",
    "wof:placetype":"venue"
},
  "geometry": {"coordinates":[-121.984329,37.553519],"type":"Point"}
}