{
  "type": "Feature",
  "properties": {
    "addr:full":"3451 Firestone Boulevard South Gate CA 90280",
    "addr:housenumber":"3451",
    "addr:postcode":"90280",
    "addr:street":"Firestone Boulevard;Gate",
    "iso:country":"US",
    "sg:address":"3451 Firestone Boulevard",
    "sg:city":"South Gate",
    "sg:classifiers":[
        {
            "category":"Government",
            "subcategory":"Office",
            "type":"Public Place"
        }
    ],
    "sg:phone":"+1 323 566 0300",
    "sg:postcode":"90280",
    "sg:province":"CA",
    "sg:tags":[
        "smog",
        "check"
    ],
    "wof:name":"Southgate Smog Test Only Center",
    "wof:placetype":"venue"
},
  "geometry": {"coordinates":[-118.20704600000001,33.954388],"type":"Point"}
}