{
  "type": "Feature",
  "properties": {
    "addr:full":"2701 Cipriani Boulevard Belmont CA 94002",
    "addr:housenumber":"2701",
    "addr:postcode":"94002",
    "addr:street":"Cipriani Boulevard",
    "iso:country":"US",
    "sg:address":"2701 Cipriani Boulevard",
    "sg:city":"Belmont",
    "sg:classifiers":[
        {
            "category":"Government",
            "subcategory":"City Hall",
            "type":"Public Place"
        }
    ],
    "sg:phone":"+1 650 802 4315",
    "sg:postcode":"94002",
    "sg:province":"CA",
    "sg:website":"www.bsfd.org",
    "wof:name":"Belmont Fire Station Number 15",
    "wof:placetype":"venue"
},
  "geometry": {"coordinates":[-122.303973,37.512873],"type":"Point"}
}