{
  "type": "Feature",
  "properties": {
    "iso:country":"US",
    "sg:address":"342 Chestnut Ln",
    "sg:city":"Escondido",
    "sg:classifiers":[
        {
            "category":"Building & Trades",
            "subcategory":"Construction",
            "type":"Services"
        }
    ],
    "sg:phone":"+1 760 489 6931",
    "sg:postcode":"92025",
    "sg:province":"CA",
    "sg:tags":[
        "carpentry",
        "contractor"
    ],
    "wof:name":"Reoh Overhead Door Co",
    "wof:placetype":"venue"
},
  "geometry": {"coordinates":[-117.06838999999999,33.112533],"type":"Point"}
}