{
  "type": "Feature",
  "properties": {
    "iso:country":"US",
    "sg:address":"4461 Salmon Falls Rd",
    "sg:city":"Pilot Hill",
    "sg:classifiers":[
        {
            "category":"Retail",
            "subcategory":"Car Wash",
            "type":"Services"
        }
    ],
    "sg:phone":"+1 530 889 8861",
    "sg:postcode":"95664",
    "sg:province":"CA",
    "sg:tags":[
        "automobile",
        "detail",
        "clean"
    ],
    "wof:name":"Get Wet Auto Detail",
    "wof:placetype":"venue"
},
  "geometry": {"coordinates":[-121.016004,38.840732],"type":"Point"}
}