{
  "type": "Feature",
  "properties": {
    "iso:country":"US",
    "sg:address":"5081 Pharlap Ave",
    "sg:city":"San Jose",
    "sg:classifiers":[
        {
            "category":"Shopping",
            "subcategory":"Hobbies, Toys, & Games",
            "type":"Retail Goods"
        }
    ],
    "sg:phone":"+1 408 629 1116",
    "sg:postcode":"95111",
    "sg:province":"CA",
    "sg:tags":[
        "craft"
    ],
    "wof:name":"Cabin Crafts",
    "wof:placetype":"venue"
},
  "geometry": {"coordinates":[-121.80916,37.265536],"type":"Point"}
}