{
  "type": "Feature",
  "properties": {
    "iso:country":"US",
    "sg:address":"1820 Fruitvale Ave",
    "sg:city":"South El Monte",
    "sg:classifiers":[
        {
            "category":"Building & Trades",
            "subcategory":"Construction",
            "type":"Services"
        }
    ],
    "sg:phone":"+1 626 444 8252",
    "sg:postcode":"91733",
    "sg:province":"CA",
    "sg:tags":[
        "concrete",
        "contractor"
    ],
    "wof:name":"J&J Concrete Inc",
    "wof:placetype":"venue"
},
  "geometry": {"coordinates":[-118.02967,34.042456],"type":"Point"}
}