{
  "type": "Feature",
  "properties": {
    "iso:country":"US",
    "sg:address":"151 W 30th St",
    "sg:city":"Los Angeles",
    "sg:classifiers":[
        {
            "category":"Education",
            "subcategory":"School",
            "type":"Public Place"
        }
    ],
    "sg:phone":"+1 213 744 1502",
    "sg:postcode":"90007",
    "sg:province":"CA",
    "sg:tags":[
        "high",
        "middle",
        "elementary"
    ],
    "wof:name":"Adams Jr High School",
    "wof:placetype":"venue"
},
  "geometry": {"coordinates":[-118.273003,34.022499],"type":"Point"}
}