{
  "type": "Feature",
  "properties": {
    "addr:full":"2899 Loma Vista Rd Ventura CA 93003",
    "addr:housenumber":"2899",
    "addr:postcode":"93003",
    "addr:street":"Loma Vista Rd",
    "iso:country":"US",
    "sg:address":"2899 Loma Vista Rd",
    "sg:city":"Ventura",
    "sg:classifiers":[
        {
            "category":"Health Services",
            "subcategory":"Doctor",
            "type":"Services"
        }
    ],
    "sg:phone":"+1 805 643 4726",
    "sg:postcode":"93003",
    "sg:province":"CA",
    "sg:tags":[
        "dentist"
    ],
    "wof:name":"Janice Mazurek DDS",
    "wof:placetype":"venue"
},
  "geometry": {"coordinates":[-119.257671,34.275341],"type":"Point"}
}