{
  "type": "Feature",
  "properties": {
    "iso:country":"US",
    "sg:address":"6722 Pacific Blvd",
    "sg:city":"Huntington Park",
    "sg:classifiers":[
        {
            "category":"Shopping",
            "subcategory":"Jewelry",
            "type":"Retail Goods"
        }
    ],
    "sg:phone":"+1 323 589 1318",
    "sg:postcode":"90255",
    "sg:province":"CA",
    "sg:tags":[
        "jeweler"
    ],
    "wof:name":"Lao Jewelers",
    "wof:placetype":"venue"
},
  "geometry": {"coordinates":[-118.224998,33.978001],"type":"Point"}
}