{
  "type": "Feature",
  "properties": {
    "addr:full":"115 Alta Ave Oakland CA 94611",
    "addr:housenumber":"115",
    "addr:postcode":"94611",
    "addr:street":"Alta Ave",
    "iso:country":"US",
    "sg:address":"115 Alta Ave",
    "sg:city":"Oakland",
    "sg:classifiers":[
        {
            "category":"Professional",
            "subcategory":"Computer Services",
            "type":"Services"
        }
    ],
    "sg:phone":"+1 510 653 9296",
    "sg:postcode":"94611",
    "sg:province":"CA",
    "sg:tags":[
        "research"
    ],
    "wof:name":"Singapore National Computer Bd",
    "wof:placetype":"venue"
},
  "geometry": {"coordinates":[-122.22823,37.828771],"type":"Point"}
}