{
  "type": "Feature",
  "properties": {
    "addr:full":"14327 Woodruff Ave Bellflower CA 90706",
    "addr:housenumber":"14327",
    "addr:postcode":"90706",
    "addr:street":"Woodruff Ave",
    "iso:country":"US",
    "sg:address":"14327 Woodruff Ave",
    "sg:city":"Bellflower",
    "sg:classifiers":[
        {
            "category":"Personal",
            "subcategory":"Shoe Repair & Shine",
            "type":"Services"
        }
    ],
    "sg:phone":"+1 562 866 9357",
    "sg:postcode":"90706",
    "sg:province":"CA",
    "sg:tags":[
        "repairing",
        "boot"
    ],
    "wof:name":"Rosewood Shoe Repair",
    "wof:placetype":"venue"
},
  "geometry": {"coordinates":[-118.116997,33.901798],"type":"Point"}
}