{
  "type": "Feature",
  "properties": {
    "addr:full":"46871 Warm Springs Blvd Fremont CA 94539",
    "addr:housenumber":"46871",
    "addr:postcode":"94539",
    "addr:street":"Warm Springs Blvd",
    "iso:country":"US",
    "sg:address":"46871 Warm Springs Blvd",
    "sg:city":"Fremont",
    "sg:classifiers":[
        {
            "category":"Shopping",
            "subcategory":"Books",
            "type":"Retail Goods"
        }
    ],
    "sg:phone":"+1 510 657 7743",
    "sg:postcode":"94539",
    "sg:province":"CA",
    "sg:tags":[
        "dealer"
    ],
    "wof:name":"World Journal Book Store",
    "wof:placetype":"venue"
},
  "geometry": {"coordinates":[-121.928867,37.488517],"type":"Point"}
}