{
  "type": "Feature",
  "properties": {
    "iso:country":"US",
    "sg:address":"11722 Sorrento Valley Rd",
    "sg:city":"San Diego",
    "sg:classifiers":[
        {
            "category":"Professional",
            "subcategory":"Computer Services",
            "type":"Services"
        }
    ],
    "sg:phone":"+1 858 259 9194",
    "sg:postcode":"92121",
    "sg:province":"CA",
    "sg:tags":[
        "related"
    ],
    "wof:name":"Cyberdux Electronics Mfg",
    "wof:placetype":"venue"
},
  "geometry": {"coordinates":[-117.228152,32.906142],"type":"Point"}
}