{
  "type": "Feature",
  "properties": {
    "iso:country":"US",
    "sg:address":"47200 Bayside Pkwy",
    "sg:city":"Fremont",
    "sg:classifiers":[
        {
            "category":"Utilities",
            "subcategory":"Mobile Phone",
            "type":"Services"
        }
    ],
    "sg:phone":"+1 510 668 1638",
    "sg:postcode":"94538",
    "sg:province":"CA",
    "sg:tags":[
        "communication",
        "radiotelephone"
    ],
    "wof:name":"At Road Inc",
    "wof:placetype":"venue"
},
  "geometry": {"coordinates":[-121.93365900000001,37.47256],"type":"Point"}
}