{
  "type": "Feature",
  "properties": {
    "iso:country":"US",
    "sg:address":"2330 Pacific Coast Hwy",
    "sg:city":"Lomita",
    "sg:classifiers":[
        {
            "category":"Home & Garden",
            "subcategory":"Building Materials",
            "type":"Retail Goods"
        }
    ],
    "sg:phone":"+1 310 539 1000",
    "sg:postcode":"90717",
    "sg:province":"CA",
    "sg:tags":[
        "supply"
    ],
    "sg:website":"www.marbleexpo.com",
    "wof:name":"Marble Expo",
    "wof:placetype":"venue"
},
  "geometry": {"coordinates":[-118.32399700000001,33.7896],"type":"Point"}
}