{
  "type": "Feature",
  "properties": {
    "addr:full":"4711 Exposition Blvd Los Angeles CA 90016",
    "addr:housenumber":"4711",
    "addr:postcode":"90016",
    "addr:street":"Exposition Blvd",
    "iso:country":"US",
    "sg:address":"4711 Exposition Blvd",
    "sg:city":"Los Angeles",
    "sg:classifiers":[
        {
            "category":"Manufacturing",
            "subcategory":"Printing",
            "type":"Manufacturing & Wholesale Goods"
        }
    ],
    "sg:phone":"+1 323 733 8882",
    "sg:postcode":"90016",
    "sg:province":"CA",
    "sg:tags":[
        "rehearsal",
        "music",
        "storage",
        "publishing"
    ],
    "wof:name":"Synical Optimism Studios",
    "wof:placetype":"venue"
},
  "geometry": {"coordinates":[-118.34824500000001,34.024384],"type":"Point"}
}