{
  "type": "Feature",
  "properties": {
    "addr:full":"5404 Whitsett Ave Valley Village CA 91607",
    "addr:housenumber":"5404",
    "addr:postcode":"91607",
    "addr:street":"Whitsett Ave",
    "iso:country":"US",
    "sg:address":"5404 Whitsett Ave",
    "sg:city":"Valley Village",
    "sg:classifiers":[
        {
            "category":"Utilities",
            "subcategory":"Mobile Phone",
            "type":"Services"
        }
    ],
    "sg:phone":"+1 818 920 9200",
    "sg:postcode":"91607",
    "sg:province":"CA",
    "sg:tags":[
        "communication",
        "radiotelephone"
    ],
    "wof:name":"Net Page LLC",
    "wof:placetype":"venue"
},
  "geometry": {"coordinates":[-118.405168,34.169394],"type":"Point"}
}