{
  "type": "Feature",
  "properties": {
    "iso:country":"US",
    "sg:address":"125 Bernal Rd",
    "sg:city":"San Jose",
    "sg:classifiers":[
        {
            "category":"Coffee & Tea",
            "type":"Food & Drink"
        }
    ],
    "sg:menulink":"http://www.allmenus.com/ca/san-jose/117144-starbucks-coffee/menu/",
    "sg:phone":"+1 408 362 1129",
    "sg:postcode":"95119",
    "sg:province":"CA",
    "sg:tags":[
        "american"
    ],
    "wof:name":"Starbucks Coffee",
    "wof:placetype":"venue"
},
  "geometry": {"coordinates":[-121.775611,37.231677],"type":"Point"}
}