{
  "type": "Feature",
  "properties": {
    "addr:full":"4222 N Milburn Ave Fresno CA 93722",
    "addr:housenumber":"4222",
    "addr:postcode":"93722",
    "addr:street":"N Milburn Ave",
    "iso:country":"US",
    "sg:address":"4222 N Milburn Ave",
    "sg:city":"Fresno",
    "sg:classifiers":[
        {
            "category":"Social Services",
            "subcategory":"Adult Care",
            "type":"Services"
        }
    ],
    "sg:phone":"+1 559 276 7606",
    "sg:postcode":"93722",
    "sg:province":"CA",
    "sg:tags":[
        "residential"
    ],
    "wof:name":"Garrett Group Homes Inc",
    "wof:placetype":"venue"
},
  "geometry": {"coordinates":[-119.876268,36.797803],"type":"Point"}
}