{
  "type": "Feature",
  "properties": {
    "addr:full":"1247 148th Ave San Leandro CA 94578",
    "addr:housenumber":"1247",
    "addr:postcode":"94578",
    "addr:street":"148Th Ave",
    "iso:country":"US",
    "sg:address":"1247 148th Ave",
    "sg:city":"San Leandro",
    "sg:classifiers":[
        {
            "category":"Building & Trades",
            "subcategory":"Construction",
            "type":"Services"
        },
        {
            "category":"Home & Garden",
            "subcategory":"Carpets & Floor Coverings",
            "type":"Retail Goods"
        }
    ],
    "sg:phone":"+1 510 352 9960",
    "sg:postcode":"94578",
    "sg:province":"CA",
    "sg:tags":[
        "dealer",
        "cleaning",
        "laying",
        "rug",
        "contractor"
    ],
    "wof:name":"London Carpet Cleaners & Maint",
    "wof:placetype":"venue"
},
  "geometry": {"coordinates":[-122.13614699999999,37.706487],"type":"Point"}
}