{
  "type": "Feature",
  "properties": {
    "addr:full":"2126 O'Nel Dr San Jose CA 95131",
    "addr:housenumber":"2126",
    "addr:postcode":"95131",
    "addr:street":"O'Nel Dr",
    "iso:country":"US",
    "sg:address":"2126 O'Nel Dr",
    "sg:city":"San Jose",
    "sg:classifiers":[
        {
            "category":"Building & Trades",
            "subcategory":"Construction",
            "type":"Services"
        }
    ],
    "sg:phone":"+1 408 933 3400",
    "sg:postcode":"95131",
    "sg:province":"CA",
    "sg:tags":[
        "company"
    ],
    "wof:name":"DPR Construction Inc",
    "wof:placetype":"venue"
},
  "geometry": {"coordinates":[-121.89889700000001,37.286147],"type":"Point"}
}