{
  "type": "Feature",
  "properties": {
    "iso:country":"US",
    "sg:address":"1043 S Lilac Ave",
    "sg:city":"Rialto",
    "sg:classifiers":[
        {
            "category":"Retail",
            "subcategory":"Animal Services",
            "type":"Services"
        }
    ],
    "sg:phone":"+1 909 873 8737",
    "sg:postcode":"92376",
    "sg:province":"CA",
    "wof:name":"Crossroads Kennels",
    "wof:placetype":"venue"
},
  "geometry": {"coordinates":[-117.378956,34.084177],"type":"Point"}
}