{
  "type": "Feature",
  "properties": {
    "addr:full":"3937 Santa Rosa Ave Santa Rosa CA 95407",
    "addr:housenumber":"3937",
    "addr:postcode":"95407",
    "addr:street":"Santa Rosa Ave",
    "iso:country":"US",
    "sg:address":"3937 Santa Rosa Ave",
    "sg:city":"Santa Rosa",
    "sg:classifiers":[
        {
            "category":"Freight",
            "type":"Transportation"
        }
    ],
    "sg:phone":"+1 707 584 1111",
    "sg:postcode":"95407",
    "sg:province":"CA",
    "sg:tags":[
        "commercial",
        "storage"
    ],
    "wof:name":"Mini U Storage",
    "wof:placetype":"venue"
},
  "geometry": {"coordinates":[-122.71359200000001,38.382237],"type":"Point"}
}