{
  "type": "Feature",
  "properties": {
    "iso:country":"US",
    "sg:address":"1001 Oak Hill Rd",
    "sg:city":"Lafayette",
    "sg:classifiers":[
        {
            "category":"Personal",
            "subcategory":"Beauty Salon",
            "type":"Services"
        }
    ],
    "sg:phone":"+1 925 962 1802",
    "sg:postcode":"94549",
    "sg:province":"CA",
    "sg:tags":[
        "manicuring"
    ],
    "wof:name":"Kim Style Nails",
    "wof:placetype":"venue"
},
  "geometry": {"coordinates":[-122.12072000000001,37.893415],"type":"Point"}
}