{
  "type": "Feature",
  "properties": {
    "addr:full":"409 E Fallbrook St Fallbrook CA 92028",
    "addr:housenumber":"409",
    "addr:postcode":"92028",
    "addr:street":"E Fallbrook St",
    "iso:country":"US",
    "sg:address":"409 E Fallbrook St",
    "sg:city":"Fallbrook",
    "sg:classifiers":[
        {
            "category":"Social Services",
            "subcategory":"Child Care",
            "type":"Services"
        },
        {
            "category":"Education",
            "subcategory":"Preschool",
            "type":"Public Place"
        },
        {
            "category":"Education",
            "subcategory":"School",
            "type":"Public Place"
        }
    ],
    "sg:phone":"+1 760 728 7600",
    "sg:postcode":"92028",
    "sg:province":"CA",
    "sg:tags":[
        "elementary",
        "day"
    ],
    "wof:name":"A Creative Beginning Pre-School",
    "wof:placetype":"venue"
},
  "geometry": {"coordinates":[-117.248001,33.376701],"type":"Point"}
}