{
  "type": "Feature",
  "properties": {
    "iso:country":"US",
    "sg:address":"11297 Trade Center Dr",
    "sg:city":"Rancho Cordova",
    "sg:classifiers":[
        {
            "category":"Retail",
            "subcategory":"Storage",
            "type":"Services"
        }
    ],
    "sg:phone":"+1 916 638 1900",
    "sg:postcode":"95670",
    "sg:province":"CA",
    "sg:tags":[
        "self"
    ],
    "wof:name":"Load-N-Lock",
    "wof:placetype":"venue"
},
  "geometry": {"coordinates":[-121.26473,38.606679],"type":"Point"}
}