{
  "type": "Feature",
  "properties": {
    "addr:full":"2275 Michael Faraday Dr San Diego CA 92154",
    "addr:housenumber":"2275",
    "addr:postcode":"92154",
    "addr:street":"Michael Faraday Dr",
    "iso:country":"US",
    "sg:address":"2275 Michael Faraday Dr",
    "sg:city":"San Diego",
    "sg:classifiers":[
        {
            "category":"Freight",
            "type":"Transportation"
        }
    ],
    "sg:phone":"+1 619 671 0250",
    "sg:postcode":"92154",
    "sg:province":"CA",
    "sg:tags":[
        "broker",
        "customs"
    ],
    "wof:name":"Brokerage & Logistics Solution",
    "wof:placetype":"venue"
},
  "geometry": {"coordinates":[-116.932062,32.55932],"type":"Point"}
}