{
  "type": "Feature",
  "properties": {
    "addr:full":"2717 Tanager Ave City Of Commerce CA 90040",
    "addr:housenumber":"2717",
    "addr:postcode":"90040",
    "addr:street":"Tanager Ave",
    "iso:country":"US",
    "sg:address":"2717 Tanager Ave",
    "sg:city":"City Of Commerce",
    "sg:classifiers":[
        {
            "category":"Manufacturing",
            "subcategory":"Textiles",
            "type":"Manufacturing & Wholesale Goods"
        },
        {
            "category":"Wholesale",
            "subcategory":"Apparel",
            "type":"Manufacturing & Wholesale Goods"
        }
    ],
    "sg:phone":"+1 323 728 2059",
    "sg:postcode":"90040",
    "sg:province":"CA",
    "sg:tags":[
        "knitted",
        "fabric",
        "mfg"
    ],
    "wof:name":"Global Textile Inc",
    "wof:placetype":"venue"
},
  "geometry": {"coordinates":[-118.128922,33.99105],"type":"Point"}
}