{
  "type": "Feature",
  "properties": {
    "iso:country":"US",
    "sg:address":"12908 Main St",
    "sg:city":"Garden Grove",
    "sg:classifiers":[
        {
            "category":"Coffee & Tea",
            "type":"Food & Drink"
        }
    ],
    "sg:phone":"+1 714 534 1265",
    "sg:postcode":"92840",
    "sg:province":"CA",
    "wof:name":"Yaba Java",
    "wof:placetype":"venue"
},
  "geometry": {"coordinates":[-117.941002,33.777599],"type":"Point"}
}