{
  "type": "Feature",
  "properties": {
    "iso:country":"US",
    "sg:address":"3055 Bechelli Ln",
    "sg:city":"Redding",
    "sg:classifiers":[
        {
            "category":"Shopping",
            "subcategory":"Clothing, Apparel, & Fashions",
            "type":"Retail Goods"
        }
    ],
    "sg:phone":"+1 530 221 1583",
    "sg:postcode":"96002",
    "sg:province":"CA",
    "wof:name":"Double D Divas",
    "wof:placetype":"venue"
},
  "geometry": {"coordinates":[-122.36244499999999,40.562654],"type":"Point"}
}