{
  "type": "Feature",
  "properties": {
    "addr:full":"11995 Shenandoah Rd Middletown CA 95461",
    "addr:housenumber":"11995",
    "addr:postcode":"95461",
    "addr:street":"Shenandoah Rd",
    "iso:country":"US",
    "sg:address":"11995 Shenandoah Rd",
    "sg:city":"Middletown",
    "sg:classifiers":[
        {
            "category":"Communications",
            "subcategory":"Film & Video Production",
            "type":"Services"
        }
    ],
    "sg:phone":"+1 707 928 0333",
    "sg:postcode":"95461",
    "sg:province":"CA",
    "sg:tags":[
        "taping"
    ],
    "wof:name":"Anthem RA Productions",
    "wof:placetype":"venue"
},
  "geometry": {"coordinates":[-122.68356300000001,38.868949],"type":"Point"}
}