{
  "type": "Feature",
  "properties": {
    "iso:country":"US",
    "sg:address":"611 Begonia Ave",
    "sg:city":"Corona Del Mar",
    "sg:classifiers":[
        {
            "category":"Professional",
            "subcategory":"Accounting & Tax Preparation",
            "type":"Services"
        }
    ],
    "sg:phone":"+1 949 261 7478",
    "sg:postcode":"92625",
    "sg:province":"CA",
    "sg:tags":[
        "accountant"
    ],
    "wof:name":"Patricia L Bell",
    "wof:placetype":"venue"
},
  "geometry": {"coordinates":[-117.875227,33.603657],"type":"Point"}
}