{
  "type": "Feature",
  "properties": {
    "addr:full":"5233 Lemona Ave Sherman Oaks CA 91411",
    "addr:housenumber":"5233",
    "addr:postcode":"91411",
    "addr:street":"Lemona Ave",
    "iso:country":"US",
    "sg:address":"5233 Lemona Ave",
    "sg:city":"Sherman Oaks",
    "sg:classifiers":[
        {
            "category":"Education",
            "subcategory":"Special Training",
            "type":"Public Place"
        }
    ],
    "sg:phone":"+1 818 784 7214",
    "sg:postcode":"91411",
    "sg:province":"CA",
    "sg:tags":[
        "instruction",
        "music"
    ],
    "wof:name":"Suzuki Music Program Of LA",
    "wof:placetype":"venue"
},
  "geometry": {"coordinates":[-118.459689,34.166633],"type":"Point"}
}