{
  "type": "Feature",
  "properties": {
    "iso:country":"US",
    "sg:address":"1212 E Lincoln Ave",
    "sg:city":"Anaheim",
    "sg:classifiers":[
        {
            "category":"Shopping",
            "subcategory":"Books",
            "type":"Retail Goods"
        }
    ],
    "sg:phone":"+1 714 533 2311",
    "sg:postcode":"92805",
    "sg:province":"CA",
    "sg:tags":[
        "bookstore"
    ],
    "wof:name":"Learning Light Metaphysical Foundation",
    "wof:placetype":"venue"
},
  "geometry": {"coordinates":[-117.902,33.838001],"type":"Point"}
}