{
  "type": "Feature",
  "properties": {
    "iso:country":"US",
    "sg:address":"7103 Sutherland Way",
    "sg:city":"Elk Grove",
    "sg:classifiers":[
        {
            "category":"Utilities",
            "subcategory":"Telephone",
            "type":"Services"
        }
    ],
    "sg:phone":"+1 916 684 3290",
    "sg:postcode":"95758",
    "sg:province":"CA",
    "sg:tags":[
        "communications"
    ],
    "wof:name":"Mommys Little Helper",
    "wof:placetype":"venue"
},
  "geometry": {"coordinates":[-121.419134,38.41404],"type":"Point"}
}