{
  "type": "Feature",
  "properties": {
    "addr:full":"17017 Big Falls Trl Sonora CA 95370",
    "addr:housenumber":"17017",
    "addr:postcode":"95370",
    "addr:street":"Big Falls Trl",
    "iso:country":"US",
    "sg:address":"17017 Big Falls Trl",
    "sg:city":"Sonora",
    "sg:classifiers":[
        {
            "category":"Shopping",
            "subcategory":"Gifts & Souvenirs",
            "type":"Retail Goods"
        }
    ],
    "sg:phone":"+1 209 586 2145",
    "sg:postcode":"95370",
    "sg:province":"CA",
    "sg:tags":[
        "shop"
    ],
    "wof:name":"Cedar Cottage",
    "wof:placetype":"venue"
},
  "geometry": {"coordinates":[-120.26755199999999,38.030454],"type":"Point"}
}