{
  "type": "Feature",
  "properties": {
    "iso:country":"US",
    "sg:address":"17017 Big Falls Trl",
    "sg:city":"Sonora",
    "sg:classifiers":[
        {
            "category":"Shopping",
            "subcategory":"Gifts & Souvenirs",
            "type":"Retail Goods"
        }
    ],
    "sg:phone":"+1 209 586 2145",
    "sg:postcode":"95370",
    "sg:province":"CA",
    "sg:tags":[
        "shop"
    ],
    "wof:name":"Cedar Cottage",
    "wof:placetype":"venue"
},
  "geometry": {"coordinates":[-120.267552,38.030454],"type":"Point"}
}