{
  "type": "Feature",
  "properties": {
    "addr:full":"3330 Cahuenga Blvd W Los Angeles CA 90068",
    "addr:housenumber":"3330",
    "addr:postcode":"90068",
    "addr:street":"Cahuenga Blvd W",
    "iso:country":"US",
    "sg:address":"3330 Cahuenga Blvd W",
    "sg:city":"Los Angeles",
    "sg:classifiers":[
        {
            "category":"Professional",
            "subcategory":"Research",
            "type":"Services"
        }
    ],
    "sg:phone":"+1 323 876 9909",
    "sg:postcode":"90068",
    "sg:province":"CA",
    "sg:tags":[
        "market",
        "analysis"
    ],
    "wof:name":"Schlesinger Associates West",
    "wof:placetype":"venue"
},
  "geometry": {"coordinates":[-118.351876,34.131611],"type":"Point"}
}