{
  "type": "Feature",
  "properties": {
    "iso:country":"US",
    "sg:address":"301 Hartz Ave",
    "sg:city":"Danville",
    "sg:classifiers":[
        {
            "category":"Shopping",
            "type":"Retail Goods"
        }
    ],
    "sg:phone":"+1 925 314 0055",
    "sg:postcode":"94526",
    "sg:province":"CA",
    "sg:tags":[
        "coin",
        "dealer",
        "supply"
    ],
    "wof:name":"Coinamania",
    "wof:placetype":"venue"
},
  "geometry": {"coordinates":[-122.000844,37.822589],"type":"Point"}
}