{
  "type": "Feature",
  "properties": {
    "iso:country":"US",
    "sg:address":"111 W Beverly Blvd",
    "sg:city":"Montebello",
    "sg:classifiers":[
        {
            "category":"Health Services",
            "subcategory":"Medical Lab",
            "type":"Services"
        }
    ],
    "sg:phone":"+1 323 887 0674",
    "sg:postcode":"90640",
    "sg:province":"CA",
    "sg:tags":[
        "laboratory"
    ],
    "wof:name":"Unilab Quest Diagnostics",
    "wof:placetype":"venue"
},
  "geometry": {"coordinates":[-118.099583,34.015753],"type":"Point"}
}