{
  "type": "Feature",
  "properties": {
    "iso:country":"US",
    "sg:address":"1077 Main St",
    "sg:city":"Ramona",
    "sg:classifiers":[
        {
            "category":"Retail",
            "subcategory":"Repair Shop",
            "type":"Services"
        }
    ],
    "sg:phone":"+1 760 788 9911",
    "sg:postcode":"92065",
    "sg:province":"CA",
    "sg:tags":[
        "scooter",
        "motorcycle",
        "motor"
    ],
    "wof:name":"Del Sol Cycles",
    "wof:placetype":"venue"
},
  "geometry": {"coordinates":[-116.86913800000001,33.0419],"type":"Point"}
}