{
  "type": "Feature",
  "properties": {
    "iso:country":"US",
    "sg:address":"235 W 9th St",
    "sg:city":"San Pedro",
    "sg:classifiers":[
        {
            "category":"Organizations",
            "subcategory":"Non-profit Organization",
            "type":"Services"
        }
    ],
    "sg:phone":"+1 310 831 9411",
    "sg:postcode":"90731",
    "sg:province":"CA",
    "sg:tags":[
        "information",
        "alcoholism",
        "treatment"
    ],
    "sg:website":"www.houseofhopesp.org",
    "wof:name":"House Of Hope Foundation",
    "wof:placetype":"venue"
},
  "geometry": {"coordinates":[-118.283019,33.735943],"type":"Point"}
}