{
  "type": "Feature",
  "properties": {
    "iso:country":"US",
    "sg:address":"1436 N Niagara St",
    "sg:city":"Burbank",
    "sg:classifiers":[
        {
            "category":"Sports & Exercise",
            "subcategory":"Gym",
            "type":"Entertainment"
        }
    ],
    "sg:phone":"+1 818 843 6617",
    "sg:postcode":"91505",
    "sg:province":"CA",
    "sg:tags":[
        "fitness",
        "program",
        "physical"
    ],
    "wof:name":"My New Image Fitness Center",
    "wof:placetype":"venue"
},
  "geometry": {"coordinates":[-118.34277299999999,34.179718],"type":"Point"}
}