{
  "type": "Feature",
  "properties": {
    "addr:full":"4448 Sisk Rd Modesto CA 95356",
    "addr:housenumber":"4448",
    "addr:postcode":"ca 95356",
    "addr:street":"Sisk Rd",
    "iso:country":"US",
    "sg:address":"4448 Sisk Rd",
    "sg:city":"Modesto",
    "sg:classifiers":[
        {
            "category":"Manufacturing",
            "subcategory":"Apparel",
            "type":"Manufacturing & Wholesale Goods"
        }
    ],
    "sg:phone":"+1 209 545 6150",
    "sg:postcode":"95356",
    "sg:province":"CA",
    "sg:tags":[
        "awning",
        "canopy"
    ],
    "sg:website":"www.modestotentandawning.com",
    "wof:name":"Modesto Tent & Awning Inc",
    "wof:placetype":"venue"
},
  "geometry": {"coordinates":[-121.073251,37.702836],"type":"Point"}
}