{
  "type": "Feature",
  "properties": {
    "addr:full":"13480 Van Nuys Blvd Pacoima CA 91331",
    "addr:housenumber":"13480",
    "addr:postcode":"91331",
    "addr:street":"Van Nuys Blvd",
    "iso:country":"US",
    "sg:address":"13480 Van Nuys Blvd",
    "sg:city":"Pacoima",
    "sg:classifiers":[
        {
            "category":"Shopping",
            "subcategory":"Computers & Home Electronics",
            "type":"Retail Goods"
        }
    ],
    "sg:phone":"+1 818 899 0525",
    "sg:postcode":"91331",
    "sg:province":"CA",
    "wof:name":"Daniels TV Service",
    "wof:placetype":"venue"
},
  "geometry": {"coordinates":[-118.426785,34.262634],"type":"Point"}
}