{
  "type": "Feature",
  "properties": {
    "iso:country":"US",
    "sg:address":"303 W Sierra Madre Blvd",
    "sg:city":"Sierra Madre",
    "sg:classifiers":[
        {
            "category":"Food & Beverages",
            "subcategory":"Liquor & Beverages",
            "type":"Retail Goods"
        }
    ],
    "sg:phone":"+1 626 355 6341",
    "sg:postcode":"91024",
    "sg:province":"CA",
    "sg:tags":[
        "beer",
        "spirit",
        "wine"
    ],
    "wof:name":"Highlander Jr Market & Liquor",
    "wof:placetype":"venue"
},
  "geometry": {"coordinates":[-118.058998,34.161701],"type":"Point"}
}