{
  "type": "Feature",
  "properties": {
    "addr:full":"1827 Brookstone St Redlands CA 92374",
    "addr:housenumber":"1827",
    "addr:postcode":"92374",
    "addr:street":"Brookstone St",
    "iso:country":"US",
    "sg:address":"1827 Brookstone St",
    "sg:city":"Redlands",
    "sg:classifiers":[
        {
            "category":"Personal",
            "type":"Services"
        }
    ],
    "sg:phone":"+1 909 792 4755",
    "sg:postcode":"92374",
    "sg:province":"CA",
    "sg:tags":[
        "miscellaneous"
    ],
    "wof:name":"Buddy Systems",
    "wof:placetype":"venue"
},
  "geometry": {"coordinates":[-117.177508,34.083063],"type":"Point"}
}