{
  "type": "Feature",
  "properties": {
    "addr:full":"2538 3rd St San Francisco CA 94107",
    "addr:housenumber":"2538",
    "addr:postcode":"94107",
    "addr:street":"3Rd St",
    "iso:country":"US",
    "sg:address":"2538 3rd St",
    "sg:city":"San Francisco",
    "sg:classifiers":[
        {
            "category":"Professional",
            "type":"Services"
        }
    ],
    "sg:phone":"+1 415 285 6003",
    "sg:postcode":"94107",
    "sg:province":"CA",
    "wof:name":"Scott Jenerik",
    "wof:placetype":"venue"
},
  "geometry": {"coordinates":[-122.38819100000001,37.755858],"type":"Point"}
}