{
  "type": "Feature",
  "properties": {
    "iso:country":"US",
    "sg:address":"1690 E Hillcrest Dr",
    "sg:city":"Thousand Oaks",
    "sg:classifiers":[
        {
            "category":"Real Estate",
            "subcategory":"Real Estate Operator",
            "type":"Services"
        }
    ],
    "sg:phone":"+1 805 497 8778",
    "sg:postcode":"91362",
    "sg:province":"CA",
    "sg:tags":[
        "apartment"
    ],
    "wof:name":"Oak Manor Apartments",
    "wof:placetype":"venue"
},
  "geometry": {"coordinates":[-118.851094,34.182568],"type":"Point"}
}