{
  "type": "Feature",
  "properties": {
    "iso:country":"US",
    "sg:address":"14515 Valley View Ave",
    "sg:city":"Santa Fe Springs",
    "sg:classifiers":[
        {
            "category":"Insurance",
            "subcategory":"Insurance Agent",
            "type":"Services"
        }
    ],
    "sg:phone":"+1 562 699 1956",
    "sg:postcode":"90670",
    "sg:province":"CA",
    "wof:name":"Allstate Insurance",
    "wof:placetype":"venue"
},
  "geometry": {"coordinates":[-118.029089,33.899074],"type":"Point"}
}