{
  "type": "Feature",
  "properties": {
    "iso:country":"US",
    "sg:address":"1508 S Gaffey St",
    "sg:city":"San Pedro",
    "sg:classifiers":[
        {
            "category":"Food & Beverages",
            "subcategory":"Specialty",
            "type":"Retail Goods"
        },
        {
            "category":"Professional",
            "subcategory":"Management & Consulting",
            "type":"Services"
        }
    ],
    "sg:phone":"+1 310 832 4285",
    "sg:postcode":"90731",
    "sg:province":"CA",
    "sg:tags":[
        "water",
        "company",
        "direct",
        "sales",
        "bulk",
        "drinking"
    ],
    "wof:name":"L A Drinking Water",
    "wof:placetype":"venue"
},
  "geometry": {"coordinates":[-118.292287,33.731438],"type":"Point"}
}