{
  "type": "Feature",
  "properties": {
    "iso:country":"US",
    "sg:address":"4113 Avalon Blvd",
    "sg:city":"Los Angeles",
    "sg:classifiers":[
        {
            "category":"Manufacturing",
            "subcategory":"Tools & Machinery",
            "type":"Manufacturing & Wholesale Goods"
        }
    ],
    "sg:phone":"+1 323 846 5555",
    "sg:postcode":"90011",
    "sg:province":"CA",
    "sg:tags":[
        "pattern",
        "maker"
    ],
    "wof:name":"Just Right Marking & Grading",
    "wof:placetype":"venue"
},
  "geometry": {"coordinates":[-118.265317,34.008302],"type":"Point"}
}