{
  "type": "Feature",
  "properties": {
    "iso:country":"US",
    "sg:address":"14270 Valley Ford Rd",
    "sg:city":"Valley Ford",
    "sg:classifiers":[
        {
            "category":"Social Services",
            "type":"Services"
        }
    ],
    "sg:phone":"+1 707 876 3100",
    "sg:postcode":"94922",
    "sg:province":"CA",
    "sg:tags":[
        "counselor",
        "marriage",
        "family"
    ],
    "wof:name":"Leadership Works",
    "wof:placetype":"venue"
},
  "geometry": {"coordinates":[-122.920013,38.31835],"type":"Point"}
}