{
  "type": "Feature",
  "properties": {
    "addr:full":"3043 W Lincoln Ave Anaheim CA 92801",
    "addr:housenumber":"3043",
    "addr:postcode":"92801",
    "addr:street":"W Lincoln Ave",
    "iso:country":"US",
    "sg:address":"3043 W Lincoln Ave",
    "sg:city":"Anaheim",
    "sg:classifiers":[
        {
            "category":"Home & Garden",
            "subcategory":"Home Furnishings",
            "type":"Retail Goods"
        }
    ],
    "sg:phone":"+1 714 588 4221",
    "sg:postcode":"92801",
    "sg:province":"CA",
    "wof:name":"Premier Lightings",
    "wof:placetype":"venue"
},
  "geometry": {"coordinates":[-117.994551,33.832125],"type":"Point"}
}