{
  "type": "Feature",
  "properties": {
    "addr:full":"1007 7th St Ste 619 Sacramento CA 95814",
    "addr:housenumber":"1007",
    "addr:postcode":"95814",
    "addr:street":"7Th St Ste 619",
    "iso:country":"US",
    "sg:address":"1007 7th St Ste 619",
    "sg:city":"Sacramento",
    "sg:classifiers":[
        {
            "category":"Professional",
            "subcategory":"Lawyer & Legal Services",
            "type":"Services"
        }
    ],
    "sg:phone":"+1 916 444 9675",
    "sg:postcode":"95814",
    "sg:province":"CA",
    "wof:name":"Muller David L",
    "wof:placetype":"venue"
},
  "geometry": {"coordinates":[-121.49720600000001,38.581011],"type":"Point"}
}