{
  "type": "Feature",
  "properties": {
    "iso:country":"US",
    "sg:address":"198 S King Rd",
    "sg:city":"San Jose",
    "sg:classifiers":[
        {
            "category":"Retail",
            "subcategory":"Repair Shop",
            "type":"Services"
        }
    ],
    "sg:phone":"+1 408 729 7939",
    "sg:postcode":"95116",
    "sg:province":"CA",
    "sg:tags":[
        "lock",
        "locksmith"
    ],
    "wof:name":"JAC Locksmith Svc",
    "wof:placetype":"venue"
},
  "geometry": {"coordinates":[-121.85339,37.350569],"type":"Point"}
}