{
  "type": "Feature",
  "properties": {
    "iso:country":"US",
    "sg:address":"15173 Valley Blvd",
    "sg:city":"Fontana",
    "sg:classifiers":[
        {
            "category":"Professional",
            "subcategory":"Detective & Security Services",
            "type":"Services"
        }
    ],
    "sg:phone":"+1 909 829 2781",
    "sg:postcode":"92335",
    "sg:province":"CA",
    "sg:tags":[
        "guard",
        "patrol"
    ],
    "wof:name":"Villa Private Security",
    "wof:placetype":"venue"
},
  "geometry": {"coordinates":[-117.472699,34.070163],"type":"Point"}
}