{
  "type": "Feature",
  "properties": {
    "addr:full":"223 N Douty St Hanford CA 93230",
    "addr:housenumber":"223",
    "addr:postcode":"ca 93230",
    "addr:street":"N Douty St",
    "iso:country":"US",
    "sg:address":"223 N Douty St",
    "sg:city":"Hanford",
    "sg:classifiers":[
        {
            "category":"Recreation",
            "type":"Entertainment"
        }
    ],
    "sg:phone":"+1 559 584 3026",
    "sg:postcode":"93230",
    "sg:province":"CA",
    "sg:tags":[
        "hall",
        "auditorium"
    ],
    "wof:name":"Masonic Temple",
    "wof:placetype":"venue"
},
  "geometry": {"coordinates":[-119.64576599999999,36.327256],"type":"Point"}
}