{
  "type": "Feature",
  "properties": {
    "iso:country":"US",
    "sg:address":"2905 Geneva Ave",
    "sg:city":"Daly City",
    "sg:classifiers":[
        {
            "category":"Wholesale",
            "subcategory":"Machinery & Supplies",
            "type":"Manufacturing & Wholesale Goods"
        }
    ],
    "sg:phone":"+1 415 467 2826",
    "sg:postcode":"94014",
    "sg:province":"CA",
    "sg:tags":[
        "equipment",
        "laundry"
    ],
    "wof:name":"Geneva Laundry Mat",
    "wof:placetype":"venue"
},
  "geometry": {"coordinates":[-122.413225,37.706471],"type":"Point"}
}