{
  "type": "Feature",
  "properties": {
    "addr:full":"20020 Hawthorne Blvd Torrance CA 90503",
    "addr:housenumber":"20020",
    "addr:postcode":"90503",
    "addr:street":"Hawthorne Blvd",
    "iso:country":"US",
    "sg:address":"20020 Hawthorne Blvd",
    "sg:city":"Torrance",
    "sg:classifiers":[
        {
            "category":"Shopping",
            "subcategory":"Shoes",
            "type":"Retail Goods"
        }
    ],
    "sg:phone":"+1 310 370 8773",
    "sg:postcode":"90503",
    "sg:province":"CA",
    "sg:tags":[
        "store"
    ],
    "wof:name":"Payless Shoesource",
    "wof:placetype":"venue"
},
  "geometry": {"coordinates":[-118.353996,33.8507],"type":"Point"}
}