{
  "type": "Feature",
  "properties": {
    "iso:country":"US",
    "sg:address":"44489 Town Center Way",
    "sg:city":"Palm Desert",
    "sg:classifiers":[
        {
            "category":"Building & Trades",
            "subcategory":"Landscaping Services",
            "type":"Services"
        }
    ],
    "sg:phone":"+1 760 328 9639",
    "sg:postcode":"92260",
    "sg:province":"CA",
    "sg:tags":[
        "designer",
        "landscape"
    ],
    "wof:name":"Abextra",
    "wof:placetype":"venue"
},
  "geometry": {"coordinates":[-116.398397,33.728512],"type":"Point"}
}