{
  "type": "Feature",
  "properties": {
    "addr:full":"One Rincon Center 101 Spear St B07 San Francisco CA 94105",
    "addr:housenumber":"101",
    "addr:postcode":"b07;94105",
    "addr:street":"Spear St",
    "iso:country":"US",
    "sg:address":"One Rincon Center 101 Spear St B07",
    "sg:city":"San Francisco",
    "sg:classifiers":[
        {
            "category":"Bars & Pubs",
            "subcategory":"Lounge",
            "type":"Food & Drink"
        }
    ],
    "sg:postcode":"94105",
    "sg:province":"CA",
    "sg:website":"www.martinipark.com",
    "wof:name":"Martini Park",
    "wof:placetype":"venue"
},
  "geometry": {"coordinates":[-122.395611,37.793814],"type":"Point"}
}