{
  "type": "Feature",
  "properties": {
    "addr:full":"43145 Bus Center Pkwy Lancaster CA 93535",
    "addr:postcode":"43145;93535",
    "addr:street":"Center Pkwy",
    "iso:country":"US",
    "sg:address":"43145 Bus Center Pkwy",
    "sg:city":"Lancaster",
    "sg:classifiers":[
        {
            "category":"Home & Garden",
            "subcategory":"Furniture",
            "type":"Retail Goods"
        }
    ],
    "sg:phone":"+1 661 951 3939",
    "sg:postcode":"93535",
    "sg:province":"CA",
    "sg:tags":[
        "bed"
    ],
    "wof:name":"Beds 4 Less",
    "wof:placetype":"venue"
},
  "geometry": {"coordinates":[-118.12891,34.666449],"type":"Point"}
}