{
  "type": "Feature",
  "properties": {
    "iso:country":"US",
    "sg:address":"8430 Central Ave",
    "sg:city":"Newark",
    "sg:classifiers":[
        {
            "category":"Utilities",
            "subcategory":"Telephone",
            "type":"Services"
        }
    ],
    "sg:phone":"+1 510 574 1800",
    "sg:postcode":"94560",
    "sg:province":"CA",
    "sg:tags":[
        "telecommunication"
    ],
    "wof:name":"Wes Tel System Inc",
    "wof:placetype":"venue"
},
  "geometry": {"coordinates":[-122.039695,37.519414],"type":"Point"}
}