{
  "type": "Feature",
  "properties": {
    "iso:country":"US",
    "sg:address":"1140 Centre Dr",
    "sg:city":"Walnut",
    "sg:classifiers":[
        {
            "category":"Building & Trades",
            "subcategory":"Construction",
            "type":"Services"
        }
    ],
    "sg:phone":"+1 909 594 5076",
    "sg:postcode":"91789",
    "sg:province":"CA",
    "sg:tags":[
        "contractor"
    ],
    "wof:name":"Ray Ban II",
    "wof:placetype":"venue"
},
  "geometry": {"coordinates":[-117.871869,33.993908],"type":"Point"}
}