{
  "type": "Feature",
  "properties": {
    "iso:country":"US",
    "sg:address":"1615 Continental St",
    "sg:city":"Redding",
    "sg:classifiers":[
        {
            "category":"Insurance",
            "subcategory":"Health Insurance",
            "type":"Services"
        }
    ],
    "sg:phone":"+1 530 247 7145",
    "sg:postcode":"96001",
    "sg:province":"CA",
    "sg:tags":[
        "plan"
    ],
    "wof:name":"Cornerstone America",
    "wof:placetype":"venue"
},
  "geometry": {"coordinates":[-122.384726,40.583853],"type":"Point"}
}