{
  "type": "Feature",
  "properties": {
    "addr:full":"6537 Crows Landing Rd Ceres CA 95307",
    "addr:housenumber":"6537",
    "addr:postcode":"95307",
    "addr:street":"Crows Landing Rd",
    "iso:country":"US",
    "sg:address":"6537 Crows Landing Rd",
    "sg:city":"Ceres",
    "sg:classifiers":[
        {
            "category":"Utilities",
            "subcategory":"Recycling",
            "type":"Services"
        },
        {
            "category":"Food & Beverages",
            "subcategory":"Specialty",
            "type":"Retail Goods"
        }
    ],
    "sg:phone":"+1 209 537 2506",
    "sg:postcode":"95307",
    "sg:province":"CA",
    "sg:tags":[
        "nuts-edible-wholesale",
        "processing",
        "nuts-edible"
    ],
    "wof:name":"Norman, Hyer",
    "wof:placetype":"venue"
},
  "geometry": {"coordinates":[-120.9935,37.541113],"type":"Point"}
}