{
  "type": "Feature",
  "properties": {
    "addr:full":"8572 National Blvd Culver City CA 90232",
    "addr:housenumber":"8572",
    "addr:postcode":"90232",
    "addr:street":"National Blvd",
    "iso:country":"US",
    "sg:address":"8572 National Blvd",
    "sg:city":"Culver City",
    "sg:classifiers":[
        {
            "category":"Restaurant",
            "type":"Food & Drink"
        },
        {
            "category":"Retail",
            "subcategory":"Event Space",
            "type":"Services"
        }
    ],
    "sg:phone":"+1 310 841 0939",
    "sg:postcode":"90232",
    "sg:province":"CA",
    "sg:tags":[
        "new",
        "american",
        "venue"
    ],
    "sg:website":"www.bluebirdcafela.com",
    "wof:name":"Bluebird Cafe",
    "wof:placetype":"venue"
},
  "geometry": {"coordinates":[-118.381691,34.027143],"type":"Point"}
}