{
  "type": "Feature",
  "properties": {
    "addr:full":"4375 Capitola Rd Capitola CA 95010",
    "addr:housenumber":"4375",
    "addr:postcode":"95010",
    "addr:street":"Capitola Rd",
    "iso:country":"US",
    "sg:address":"4375 Capitola Rd",
    "sg:city":"Capitola",
    "sg:classifiers":[
        {
            "category":"Restaurant",
            "type":"Food & Drink"
        }
    ],
    "sg:phone":"+1 408 262 7878",
    "sg:postcode":"95010",
    "sg:province":"CA",
    "sg:website":"www.eriksdelicafe.com",
    "wof:name":"Erik's Delicafe",
    "wof:placetype":"venue"
},
  "geometry": {"coordinates":[-121.96148100000001,36.973802],"type":"Point"}
}