{
  "type": "Feature",
  "properties": {
    "iso:country":"US",
    "sg:address":"1160 Homestead Rd",
    "sg:city":"Santa Clara",
    "sg:classifiers":[
        {
            "category":"Government",
            "subcategory":"City Hall",
            "type":"Public Place"
        }
    ],
    "sg:phone":"+1 408 379 4700",
    "sg:postcode":"95050",
    "sg:province":"CA",
    "sg:website":"www.hasslefreeprocess.com",
    "wof:name":"Hassle Free Process Service",
    "wof:placetype":"venue"
},
  "geometry": {"coordinates":[-121.945761,37.347967],"type":"Point"}
}