{
  "type": "Feature",
  "properties": {
    "addr:full":"310 W Lexington Dr Glendale CA 91203",
    "addr:housenumber":"310",
    "addr:postcode":"91203",
    "addr:street":"W Lexington Dr",
    "iso:country":"US",
    "sg:address":"310 W Lexington Dr",
    "sg:city":"Glendale",
    "sg:phone":"+1 818 244 8141",
    "sg:postcode":"91203",
    "sg:province":"CA",
    "sg:website":"http://www.statefarm.com",
    "wof:name":"State Farm Insurance",
    "wof:placetype":"venue"
},
  "geometry": {"coordinates":[-118.258267,34.151697],"type":"Point"}
}