{
  "type": "Feature",
  "properties": {
    "addr:full":"10766 Dabney Dr San Diego CA 92126",
    "addr:housenumber":"10766",
    "addr:postcode":"92126",
    "addr:street":"Dabney Dr",
    "iso:country":"US",
    "sg:address":"10766 Dabney Dr",
    "sg:city":"San Diego",
    "sg:classifiers":[
        {
            "category":"Professional",
            "type":"Services"
        }
    ],
    "sg:phone":"+1 858 353 5523",
    "sg:postcode":"92126",
    "sg:province":"CA",
    "wof:name":"Enkad Sciences",
    "wof:placetype":"venue"
},
  "geometry": {"coordinates":[-117.162088,32.910412],"type":"Point"}
}