{
  "type": "Feature",
  "properties": {
    "iso:country":"US",
    "sg:address":"707 Dead Cat Aly",
    "sg:city":"Woodland",
    "sg:classifiers":[
        {
            "category":"Personal",
            "type":"Services"
        }
    ],
    "sg:phone":"+1 530 661 3112",
    "sg:postcode":"95695",
    "sg:province":"CA",
    "sg:tags":[
        "therapist",
        "massage"
    ],
    "wof:name":"Body Kneads",
    "wof:placetype":"venue"
},
  "geometry": {"coordinates":[-121.770654,38.678187],"type":"Point"}
}