{
  "type": "Feature",
  "properties": {
    "addr:full":"40639 Vernay St Murrieta CA 92562",
    "addr:postcode":"40639;92562",
    "addr:street":"Vernay St",
    "iso:country":"US",
    "sg:address":"40639 Vernay St",
    "sg:city":"Murrieta",
    "sg:classifiers":[
        {
            "category":"Shopping",
            "subcategory":"Bicycles & Sporting Goods",
            "type":"Retail Goods"
        }
    ],
    "sg:phone":"+1 951 677 9623",
    "sg:postcode":"92562",
    "sg:province":"CA",
    "wof:name":"Maggies Gift & Goods",
    "wof:placetype":"venue"
},
  "geometry": {"coordinates":[-117.201122,33.569165],"type":"Point"}
}