{
  "type": "Feature",
  "properties": {
    "iso:country":"US",
    "sg:address":"1626 Mary C Dr",
    "sg:city":"Napa",
    "sg:classifiers":[
        {
            "category":"Retail",
            "subcategory":"Auto Repair",
            "type":"Services"
        }
    ],
    "sg:phone":"+1 707 257 1203",
    "sg:postcode":"94558",
    "sg:province":"CA",
    "sg:tags":[
        "repairing",
        "automobile"
    ],
    "wof:name":"John's Mobile Repair",
    "wof:placetype":"venue"
},
  "geometry": {"coordinates":[-122.31492299999999,38.318022],"type":"Point"}
}