{
  "type": "Feature",
  "properties": {
    "addr:full":"20108 Scobey Ave Carson CA 90746",
    "addr:postcode":"20108;90746",
    "addr:street":"Scobey Ave",
    "iso:country":"US",
    "sg:address":"20108 Scobey Ave",
    "sg:city":"Carson",
    "sg:classifiers":[
        {
            "category":"Building & Trades",
            "subcategory":"Construction",
            "type":"Services"
        }
    ],
    "sg:phone":"+1 310 717 1698",
    "sg:postcode":"90746",
    "sg:province":"CA",
    "sg:tags":[
        "contractor"
    ],
    "wof:name":"Sace Contractors",
    "wof:placetype":"venue"
},
  "geometry": {"coordinates":[-118.254346,33.849188],"type":"Point"}
}