{
  "type": "Feature",
  "properties": {
    "addr:full":"2259 Market St San Francisco CA 94114",
    "addr:housenumber":"2259",
    "addr:postcode":"94114",
    "addr:street":"Market St",
    "iso:country":"US",
    "sg:address":"2259 Market St",
    "sg:city":"San Francisco",
    "sg:classifiers":[
        {
            "category":"Building & Trades",
            "subcategory":"Plumbing",
            "type":"Services"
        }
    ],
    "sg:phone":"+1 415 322 3366",
    "sg:postcode":"94114",
    "sg:province":"CA",
    "wof:name":"Plumber In The San Francisco VIP",
    "wof:placetype":"venue"
},
  "geometry": {"coordinates":[-122.432126,37.76489],"type":"Point"}
}