{
  "type": "Feature",
  "properties": {
    "addr:full":"1 Miguel St San Francisco CA 94131",
    "addr:housenumber":"1",
    "addr:postcode":"94131",
    "addr:street":"Miguel St",
    "iso:country":"US",
    "sg:address":"1 Miguel St",
    "sg:city":"San Francisco",
    "sg:classifiers":[
        {
            "category":"Professional",
            "type":"Services"
        }
    ],
    "sg:phone":"+1 415 821 2121",
    "sg:postcode":"94131",
    "sg:province":"CA",
    "wof:name":"James H Stein",
    "wof:placetype":"venue"
},
  "geometry": {"coordinates":[-122.42872800000001,37.738502],"type":"Point"}
}