{
  "type": "Feature",
  "properties": {
    "addr:full":"13100 S Broadway Los Angeles CA 90061",
    "addr:housenumber":"13100",
    "addr:postcode":"90061",
    "addr:street":"S Broadway",
    "iso:country":"US",
    "sg:address":"13100 S Broadway",
    "sg:city":"Los Angeles",
    "sg:classifiers":[
        {
            "category":"Manufacturing",
            "subcategory":"Chemicals & Compounds",
            "type":"Manufacturing & Wholesale Goods"
        }
    ],
    "sg:phone":"+1 310 768 8899",
    "sg:postcode":"90061",
    "sg:province":"CA",
    "sg:tags":[
        "mfg",
        "plastic"
    ],
    "wof:name":"Kc Enterprise",
    "wof:placetype":"venue"
},
  "geometry": {"coordinates":[-118.278339,33.91231],"type":"Point"}
}