{
  "type": "Feature",
  "properties": {
    "addr:full":"1971 Port Locksleigh Pl Newport Beach CA 92660",
    "addr:housenumber":"1971",
    "addr:postcode":"92660",
    "addr:street":"Port Locksleigh Pl",
    "iso:country":"US",
    "sg:address":"1971 Port Locksleigh Pl",
    "sg:city":"Newport Beach",
    "sg:classifiers":[
        {
            "category":"Banks & Credit Unions",
            "subcategory":"Financial Services",
            "type":"Services"
        }
    ],
    "sg:phone":"+1 949 759 3779",
    "sg:postcode":"92660",
    "sg:province":"CA",
    "sg:tags":[
        "investment",
        "closed"
    ],
    "wof:name":"1601 15th Place LLC",
    "wof:placetype":"venue"
},
  "geometry": {"coordinates":[-117.856818,33.618381],"type":"Point"}
}