{
  "type": "Feature",
  "properties": {
    "addr:full":"1252 Surf Ave Pacific Grove CA 93950",
    "addr:housenumber":"1252",
    "addr:postcode":"93950",
    "addr:street":"Surf Ave",
    "iso:country":"US",
    "sg:address":"1252 Surf Ave",
    "sg:city":"Pacific Grove",
    "sg:classifiers":[
        {
            "category":"Building & Trades",
            "subcategory":"Construction",
            "type":"Services"
        }
    ],
    "sg:phone":"+1 831 372 5600",
    "sg:postcode":"93950",
    "sg:province":"CA",
    "sg:tags":[
        "painter"
    ],
    "wof:name":"R C Painting Co",
    "wof:placetype":"venue"
},
  "geometry": {"coordinates":[-121.931031,36.635661],"type":"Point"}
}