{
  "type": "Feature",
  "properties": {
    "iso:country":"US",
    "sg:address":"4621 Arabian Way",
    "sg:city":"Antioch",
    "sg:classifiers":[
        {
            "category":"Professional",
            "subcategory":"Management & Consulting",
            "type":"Services"
        }
    ],
    "sg:phone":"+1 925 757 0836",
    "sg:postcode":"94531",
    "sg:province":"CA",
    "sg:tags":[
        "consultant",
        "business"
    ],
    "wof:name":"P W Meikle Consultants",
    "wof:placetype":"venue"
},
  "geometry": {"coordinates":[-121.75388700000001,37.970792],"type":"Point"}
}