{
  "type": "Feature",
  "properties": {
    "iso:country":"US",
    "sg:address":"11201 National Blvd",
    "sg:city":"Los Angeles",
    "sg:classifiers":[
        {
            "category":"Banks & Credit Unions",
            "subcategory":"Bank",
            "type":"Services"
        }
    ],
    "sg:phone":"+1 310 473 5565",
    "sg:postcode":"90064",
    "sg:province":"CA",
    "sg:tags":[
        "cashing",
        "check"
    ],
    "wof:name":"Popular Cash Express",
    "wof:placetype":"venue"
},
  "geometry": {"coordinates":[-118.42958400000001,34.026993],"type":"Point"}
}