{
  "type": "Feature",
  "properties": {
    "addr:full":"3878 W Carson St Torrance CA 90503",
    "addr:housenumber":"3878",
    "addr:postcode":"90503",
    "addr:street":"W Carson St",
    "iso:country":"US",
    "sg:address":"3878 W Carson St",
    "sg:city":"Torrance",
    "sg:classifiers":[
        {
            "category":"Professional",
            "subcategory":"Management & Consulting",
            "type":"Services"
        }
    ],
    "sg:phone":"+1 310 543 4746",
    "sg:postcode":"90503",
    "sg:province":"CA",
    "sg:tags":[
        "consultant",
        "energy",
        "conservation"
    ],
    "wof:name":"Mark Resources Inc",
    "wof:placetype":"venue"
},
  "geometry": {"coordinates":[-118.35577499999999,33.831119],"type":"Point"}
}