{
  "type": "Feature",
  "properties": {
    "iso:country":"US",
    "sg:address":"2651 Willow St",
    "sg:city":"Oakland",
    "sg:classifiers":[
        {
            "category":"Home & Garden",
            "subcategory":"Household Appliances",
            "type":"Retail Goods"
        },
        {
            "category":"Home & Garden",
            "subcategory":"Building Materials",
            "type":"Retail Goods"
        }
    ],
    "sg:phone":"+1 510 652 4100",
    "sg:postcode":"94607",
    "sg:province":"CA",
    "sg:tags":[
        "repair",
        "supply"
    ],
    "sg:website":"www.tksdesign.com",
    "wof:name":"Turn Key Systems",
    "wof:placetype":"venue"
},
  "geometry": {"coordinates":[-122.289542,37.82144],"type":"Point"}
}