{
  "type": "Feature",
  "properties": {
    "iso:country":"US",
    "sg:address":"20701 Beach Blvd",
    "sg:city":"Huntington Beach",
    "sg:classifiers":[
        {
            "category":"Building & Trades",
            "subcategory":"Plumbing",
            "type":"Services"
        }
    ],
    "sg:phone":"+1 714 960 0208",
    "sg:postcode":"92648",
    "sg:province":"CA",
    "sg:tags":[
        "contractor"
    ],
    "wof:name":"Crocodile Dundee",
    "wof:placetype":"venue"
},
  "geometry": {"coordinates":[-117.988411,33.664716],"type":"Point"}
}