{
  "type": "Feature",
  "properties": {
    "addr:full":"177 Pelton Center Way San Leandro CA 94577",
    "addr:housenumber":"177",
    "addr:postcode":"94577",
    "addr:street":"Pelton Center Way",
    "iso:country":"US",
    "sg:address":"177 Pelton Center Way",
    "sg:city":"San Leandro",
    "sg:classifiers":[
        {
            "category":"Shopping",
            "subcategory":"Used Merchandise",
            "type":"Retail Goods"
        }
    ],
    "sg:phone":"+1 510 483 3405",
    "sg:postcode":"94577",
    "sg:province":"CA",
    "wof:name":"Nelsons Antiques",
    "wof:placetype":"venue"
},
  "geometry": {"coordinates":[-122.154437,37.722734],"type":"Point"}
}