{
  "type": "Feature",
  "properties": {
    "addr:full":"561 Valencia St San Francisco CA 94110",
    "addr:housenumber":"561",
    "addr:postcode":"94110",
    "addr:street":"Valencia St",
    "iso:country":"US",
    "sg:address":"561 Valencia St",
    "sg:city":"San Francisco",
    "sg:classifiers":[
        {
            "category":"Restaurant",
            "type":"Food & Drink"
        },
        {
            "category":"Bars & Pubs",
            "subcategory":"Wine Bar",
            "type":"Food & Drink"
        }
    ],
    "sg:phone":"+1 415 487 1600",
    "sg:postcode":"94110",
    "sg:province":"CA",
    "sg:tags":[
        "new",
        "american",
        "brunch",
        "breakfast"
    ],
    "sg:website":"bartartine.com",
    "wof:name":"Bar Tartine",
    "wof:placetype":"venue"
},
  "geometry": {"coordinates":[-122.42177599999999,37.763971],"type":"Point"}
}