{
  "type": "Feature",
  "properties": {
    "iso:country":"US",
    "sg:address":"710 Bancroft Way",
    "sg:city":"Berkeley",
    "sg:classifiers":[
        {
            "category":"Home & Garden",
            "subcategory":"Building Materials",
            "type":"Retail Goods"
        },
        {
            "category":"Building & Trades",
            "subcategory":"Construction",
            "type":"Services"
        }
    ],
    "sg:phone":"+1 510 647 3767",
    "sg:postcode":"94710",
    "sg:province":"CA",
    "sg:tags":[
        "interior",
        "design",
        "supply"
    ],
    "sg:website":"www.ecwoodworking.net",
    "wof:name":"El Cerrito Woodworking Inc",
    "wof:placetype":"venue"
},
  "geometry": {"coordinates":[-122.299115,37.86291],"type":"Point"}
}