{
  "type": "Feature",
  "properties": {
    "iso:country":"US",
    "sg:address":"122 Sylvia Ave",
    "sg:city":"Milpitas",
    "sg:classifiers":[
        {
            "category":"Insurance",
            "subcategory":"Hazard Insurance",
            "type":"Services"
        }
    ],
    "sg:phone":"+1 408 263 1550",
    "sg:postcode":"95035",
    "sg:province":"CA",
    "sg:website":"http://statefarm.mqgroup.com/url.asp?usr=056990",
    "wof:name":"State Farm Insurance Agent-Carl Murrell",
    "wof:placetype":"venue"
},
  "geometry": {"coordinates":[-121.907843,37.42384],"type":"Point"}
}