{
  "type": "Feature",
  "properties": {
    "addr:full":"159 H St Bakersfield CA 93304",
    "addr:housenumber":"159",
    "addr:postcode":"93304",
    "addr:street":"H St",
    "iso:country":"US",
    "sg:address":"159 H St",
    "sg:city":"Bakersfield",
    "sg:classifiers":[
        {
            "category":"Shopping",
            "subcategory":"Hobbies, Toys, & Games",
            "type":"Retail Goods"
        }
    ],
    "sg:phone":"+1 661 324 3233",
    "sg:postcode":"93304",
    "sg:province":"CA",
    "sg:tags":[
        "doll",
        "clothing",
        "accessory"
    ],
    "wof:name":"Daddy's Little Angel",
    "wof:placetype":"venue"
},
  "geometry": {"coordinates":[-119.021376,35.356711],"type":"Point"}
}