{
  "type": "Feature",
  "properties": {
    "addr:full":"111 N Jackson St Ste 220 Glendale CA 91206",
    "addr:housenumber":"111",
    "addr:postcode":"91206",
    "addr:street":"N Jackson St Ste 220",
    "iso:country":"US",
    "sg:address":"111 N Jackson St Ste 220",
    "sg:city":"Glendale",
    "sg:classifiers":[
        {
            "category":"Banks & Credit Unions",
            "subcategory":"Financial Services",
            "type":"Services"
        }
    ],
    "sg:phone":"+1 818 241 9000",
    "sg:postcode":"91206",
    "sg:province":"CA",
    "sg:tags":[
        "broker",
        "mortgage"
    ],
    "wof:name":"Discover Realty Inc",
    "wof:placetype":"venue"
},
  "geometry": {"coordinates":[-118.25,34.146599],"type":"Point"}
}