{
  "type": "Feature",
  "properties": {
    "addr:full":"1326 Kifer Road Sunnyvale CA 94086",
    "addr:housenumber":"1326",
    "addr:postcode":"94086",
    "addr:street":"Kifer Road",
    "iso:country":"US",
    "sg:address":"1326 Kifer Road",
    "sg:city":"Sunnyvale",
    "sg:classifiers":[
        {
            "category":"Personal",
            "type":"Services"
        }
    ],
    "sg:phone":"+1 408 275 0660",
    "sg:postcode":"94086",
    "sg:province":"CA",
    "sg:tags":[
        "mover"
    ],
    "wof:name":"North American Van Lines Agent-Valley Relocation & Storage",
    "wof:placetype":"venue"
},
  "geometry": {"coordinates":[-121.989588,37.373891],"type":"Point"}
}