{
  "type": "Feature",
  "properties": {
    "addr:full":"820 McAllister St San Francisco CA 94102",
    "addr:housenumber":"820",
    "addr:postcode":"94102",
    "addr:street":"Mcallister St",
    "iso:country":"US",
    "sg:address":"820 McAllister St",
    "sg:city":"San Francisco",
    "sg:classifiers":[
        {
            "category":"Real Estate",
            "subcategory":"Real Estate Operator",
            "type":"Services"
        }
    ],
    "sg:phone":"+1 415 929 1011",
    "sg:postcode":"94102",
    "sg:province":"CA",
    "sg:tags":[
        "apartment"
    ],
    "wof:name":"Freedom West Homes",
    "wof:placetype":"venue"
},
  "geometry": {"coordinates":[-122.426525,37.779382],"type":"Point"}
}