{
  "type": "Feature",
  "properties": {
    "addr:full":"345 S A St Oxnard CA 93030",
    "addr:housenumber":"345",
    "addr:postcode":"93030",
    "addr:street":"S A St",
    "iso:country":"US",
    "sg:address":"345 S A St",
    "sg:city":"Oxnard",
    "sg:classifiers":[
        {
            "category":"Health Services",
            "subcategory":"Doctor",
            "type":"Services"
        },
        {
            "category":"Health Services",
            "subcategory":"Clinic",
            "type":"Services"
        },
        {
            "category":"Health Services",
            "subcategory":"Health Practitioner",
            "type":"Services"
        },
        {
            "category":"Health Services",
            "subcategory":"Chiropractor",
            "type":"Services"
        }
    ],
    "sg:phone":"+1 805 487 7200",
    "sg:postcode":"93030",
    "sg:province":"CA",
    "sg:tags":[
        "physician",
        "chiropractic",
        "surgeons",
        "therapist",
        "therapy",
        "medicine",
        "surgeon",
        "rehabilitation",
        "physical"
    ],
    "wof:name":"Omega Solution In Rehab",
    "wof:placetype":"venue"
},
  "geometry": {"coordinates":[-119.178569,34.199745],"type":"Point"}
}