{
  "type": "Feature",
  "properties": {
    "addr:full":"11628 Santa Monica Blvd Los Angeles CA 90025",
    "addr:housenumber":"11628",
    "addr:postcode":"90025",
    "addr:street":"Santa Monica Blvd",
    "iso:country":"US",
    "sg:address":"11628 Santa Monica Blvd",
    "sg:city":"Los Angeles",
    "sg:classifiers":[
        {
            "category":"Communications",
            "subcategory":"Newspaper",
            "type":"Services"
        }
    ],
    "sg:phone":"+1 310 826 5242",
    "sg:postcode":"90025",
    "sg:province":"CA",
    "sg:tags":[
        "print",
        "medium"
    ],
    "wof:name":"West Coast Newsstand",
    "wof:placetype":"venue"
},
  "geometry": {"coordinates":[-118.454549,34.427691],"type":"Point"}
}