{
  "type": "Feature",
  "properties": {
    "addr:full":"8641 On The Mall Buena Park CA 90620",
    "addr:postcode":"90620",
    "addr:street":"The Mall",
    "iso:country":"US",
    "sg:address":"8641 On The Mall",
    "sg:city":"Buena Park",
    "sg:classifiers":[
        {
            "category":"Restaurant",
            "type":"Food & Drink"
        }
    ],
    "sg:menulink":"http://www.allmenus.com/ca/anaheim-santa-ana-garden-grove/223079-edo-japan/menu/",
    "sg:phone":"+1 714 761 5188",
    "sg:postcode":"90620",
    "sg:province":"CA",
    "sg:tags":[
        "japanese",
        "asian"
    ],
    "wof:name":"Edo Japan",
    "wof:placetype":"venue"
},
  "geometry": {"coordinates":[-117.990595,33.845912],"type":"Point"}
}