{
  "type": "Feature",
  "properties": {
    "iso:country":"US",
    "sg:address":"509 W Weber Ave",
    "sg:city":"Stockton",
    "sg:classifiers":[
        {
            "category":"Communications",
            "subcategory":"Television Station",
            "type":"Services"
        }
    ],
    "sg:phone":"+1 209 941 2358",
    "sg:postcode":"95203",
    "sg:province":"CA",
    "sg:tags":[
        "broadcasting",
        "co"
    ],
    "wof:name":"KMAX TV",
    "wof:placetype":"venue"
},
  "geometry": {"coordinates":[-121.298021,37.952401],"type":"Point"}
}