{
  "type": "Feature",
  "properties": {
    "addr:full":"38740 Sky Canyon Dr Murrieta CA 92563",
    "addr:housenumber":"38740",
    "addr:postcode":"92563",
    "addr:street":"Sky Canyon Dr",
    "iso:country":"US",
    "sg:address":"38740 Sky Canyon Dr",
    "sg:city":"Murrieta",
    "sg:classifiers":[
        {
            "category":"Real Estate",
            "subcategory":"Architect",
            "type":"Services"
        }
    ],
    "sg:phone":"+1 951 698 4313",
    "sg:postcode":"92563",
    "sg:province":"CA",
    "sg:tags":[
        "building",
        "construction"
    ],
    "wof:name":"Temecula Valley Developers",
    "wof:placetype":"venue"
},
  "geometry": {"coordinates":[-117.130155,33.580743],"type":"Point"}
}