{
  "type": "Feature",
  "properties": {
    "iso:country":"US",
    "sg:address":"240 West St",
    "sg:city":"San Diego",
    "sg:classifiers":[
        {
            "category":"Professional",
            "type":"Services"
        }
    ],
    "sg:phone":"+1 619 263 9137",
    "sg:postcode":"92113",
    "sg:province":"CA",
    "wof:name":"Daniel Ledezma",
    "wof:placetype":"venue"
},
  "geometry": {"coordinates":[-117.096981,32.703021],"type":"Point"}
}