{
  "type": "Feature",
  "properties": {
    "addr:full":"23476 Kidder St Hayward CA 94545",
    "addr:postcode":"23476;94545",
    "addr:street":"Kidder St",
    "iso:country":"US",
    "sg:address":"23476 Kidder St",
    "sg:city":"Hayward",
    "sg:classifiers":[
        {
            "category":"Farming",
            "subcategory":"Fish & Marine Products",
            "type":"Manufacturing & Wholesale Goods"
        },
        {
            "category":"Recreation",
            "subcategory":"Fishing",
            "type":"Entertainment"
        }
    ],
    "sg:phone":"+1 510 785 4311",
    "sg:postcode":"94545",
    "sg:province":"CA",
    "sg:tags":[
        "tackle",
        "manufacturer",
        "fishermen's",
        "tackle-wholesale",
        "supply"
    ],
    "sg:website":"http://www.haywardfishingsupplies.com",
    "wof:name":"Hayward Fishing Supplies",
    "wof:placetype":"venue"
},
  "geometry": {"coordinates":[-122.13509000000001,37.640732],"type":"Point"}
}