{
  "type": "Feature",
  "properties": {
    "addr:full":"876 Kaynyne St Redwood City CA 94063",
    "addr:housenumber":"876",
    "addr:postcode":"94063",
    "addr:street":"Kaynyne St",
    "iso:country":"US",
    "sg:address":"876 Kaynyne St",
    "sg:city":"Redwood City",
    "sg:classifiers":[
        {
            "category":"Retail",
            "subcategory":"Auto Repair",
            "type":"Services"
        }
    ],
    "sg:phone":"+1 650 367 8517",
    "sg:postcode":"94063",
    "sg:province":"CA",
    "sg:tags":[
        "repairing",
        "automobile"
    ],
    "wof:name":"Autoquest",
    "wof:placetype":"venue"
},
  "geometry": {"coordinates":[-122.210933,37.484688],"type":"Point"}
}