{
  "type": "Feature",
  "properties": {
    "iso:country":"US",
    "sg:address":"1102 Main St",
    "sg:city":"Brawley",
    "sg:classifiers":[
        {
            "category":"Retail",
            "subcategory":"Self-service Laundry",
            "type":"Services"
        }
    ],
    "sg:phone":"+1 760 344 4382",
    "sg:postcode":"92227",
    "sg:province":"CA",
    "wof:name":"Glamis Way Auto Sales",
    "wof:placetype":"venue"
},
  "geometry": {"coordinates":[-115.52435699999999,32.978568],"type":"Point"}
}