{
  "type": "Feature",
  "properties": {
    "addr:full":"24318 Hemlock Ave Moreno Valley CA 92557",
    "addr:housenumber":"24318",
    "addr:postcode":"92557",
    "addr:street":"Hemlock Ave",
    "iso:country":"US",
    "sg:address":"24318 Hemlock Ave",
    "sg:city":"Moreno Valley",
    "sg:classifiers":[
        {
            "category":"Restaurant",
            "type":"Food & Drink"
        }
    ],
    "sg:phone":"+1 951 243 1231",
    "sg:postcode":"92557",
    "sg:province":"CA",
    "wof:name":"Yoshinoya Beef Bowl Restaurant",
    "wof:placetype":"venue"
},
  "geometry": {"coordinates":[-117.23674699999999,33.941788],"type":"Point"}
}