{
  "type": "Feature",
  "properties": {
    "addr:full":"1167 Huntington Dr Duarte CA 91010",
    "addr:housenumber":"1167",
    "addr:postcode":"91010",
    "addr:street":"Huntington Dr",
    "iso:country":"US",
    "sg:address":"1167 Huntington Dr",
    "sg:city":"Duarte",
    "sg:classifiers":[
        {
            "category":"Restaurant",
            "type":"Food & Drink"
        }
    ],
    "sg:phone":"+1 626 359 0980",
    "sg:postcode":"91010",
    "sg:province":"CA",
    "sg:tags":[
        "asian",
        "chinese",
        "pan"
    ],
    "wof:name":"Magic Wok",
    "wof:placetype":"venue"
},
  "geometry": {"coordinates":[-117.979517,34.139671],"type":"Point"}
}