{
  "type": "Feature",
  "properties": {
    "addr:full":"8707 Cayucos Way San Diego CA 92129",
    "addr:housenumber":"8707",
    "addr:postcode":"92129",
    "addr:street":"Cayucos Way",
    "iso:country":"US",
    "sg:address":"8707 Cayucos Way",
    "sg:city":"San Diego",
    "sg:classifiers":[
        {
            "category":"Manufacturing",
            "subcategory":"Printing",
            "type":"Manufacturing & Wholesale Goods"
        }
    ],
    "sg:phone":"+1 858 538 1030",
    "sg:postcode":"92129",
    "sg:province":"CA",
    "sg:tags":[
        "printer"
    ],
    "wof:name":"Imaging Co",
    "wof:placetype":"venue"
},
  "geometry": {"coordinates":[-117.138448,32.970034],"type":"Point"}
}