{
  "type": "Feature",
  "properties": {
    "iso:country":"US",
    "sg:address":"2100 Webster Street",
    "sg:city":"San Francisco",
    "sg:classifiers":[
        {
            "category":"Health Services",
            "subcategory":"Clinic",
            "type":"Services"
        }
    ],
    "sg:phone":"+1 415 600 7880",
    "sg:postcode":"94115",
    "sg:province":"CA",
    "sg:tags":[
        "medical"
    ],
    "wof:name":"King-Stephens David MD",
    "wof:placetype":"venue"
},
  "geometry": {"coordinates":[-122.435592,37.785819],"type":"Point"}
}