{
  "type": "Feature",
  "properties": {
    "iso:country":"US",
    "sg:address":"4101 Middle Two Rock Rd",
    "sg:city":"Petaluma",
    "sg:classifiers":[
        {
            "category":"Professional",
            "subcategory":"Management & Consulting",
            "type":"Services"
        }
    ],
    "sg:phone":"+1 707 778 6505",
    "sg:postcode":"94952",
    "sg:province":"CA",
    "sg:tags":[
        "consultant",
        "business"
    ],
    "wof:name":"Rancho Strozzi Institute",
    "wof:placetype":"venue"
},
  "geometry": {"coordinates":[-122.73913400000001,38.253575],"type":"Point"}
}