{
  "type": "Feature",
  "properties": {
    "iso:country":"US",
    "sg:address":"1220 Pacific Hwy",
    "sg:city":"San Diego",
    "sg:classifiers":[
        {
            "category":"Professional",
            "subcategory":"Engineering",
            "type":"Services"
        }
    ],
    "sg:phone":"+1 619 532 2317",
    "sg:postcode":"92101",
    "sg:province":"CA",
    "wof:name":"Naval Fclties Engnring Command",
    "wof:placetype":"venue"
},
  "geometry": {"coordinates":[-117.17112,32.718701],"type":"Point"}
}