{
  "type": "Feature",
  "properties": {
    "iso:country":"US",
    "sg:address":"5203 S Downey Rd",
    "sg:city":"Los Angeles",
    "sg:classifiers":[
        {
            "category":"Manufacturing",
            "subcategory":"Apparel",
            "type":"Manufacturing & Wholesale Goods"
        }
    ],
    "sg:phone":"+1 323 588 9399",
    "sg:postcode":"90058",
    "sg:province":"CA",
    "sg:tags":[
        "sewing",
        "contractor"
    ],
    "wof:name":"Mola Sewing Inc",
    "wof:placetype":"venue"
},
  "geometry": {"coordinates":[-118.204615,33.990956],"type":"Point"}
}