{
  "type": "Feature",
  "properties": {
    "addr:full":"886 Green St Palo Alto CA 94303",
    "addr:housenumber":"886",
    "addr:postcode":"94303",
    "addr:street":"Green St",
    "iso:country":"US",
    "sg:address":"886 Green St",
    "sg:city":"Palo Alto",
    "sg:classifiers":[
        {
            "category":"Organizations",
            "subcategory":"Religious Organization",
            "type":"Services"
        }
    ],
    "sg:phone":"+1 650 853 9758",
    "sg:postcode":"94303",
    "sg:province":"CA",
    "sg:tags":[
        "church"
    ],
    "wof:name":"Church Of Angels",
    "wof:placetype":"venue"
},
  "geometry": {"coordinates":[-122.137839,37.464139],"type":"Point"}
}