{
  "type": "Feature",
  "properties": {
    "iso:country":"US",
    "sg:address":"5049 College Oak Dr",
    "sg:city":"Sacramento",
    "sg:classifiers":[
        {
            "category":"Shopping",
            "type":"Retail Goods"
        }
    ],
    "sg:phone":"+1 916 331 3537",
    "sg:postcode":"95841",
    "sg:province":"CA",
    "sg:tags":[
        "limb",
        "artificial"
    ],
    "wof:name":"Professional Orthopedic Systs",
    "wof:placetype":"venue"
},
  "geometry": {"coordinates":[-121.350606,38.660249],"type":"Point"}
}