{
  "type": "Feature",
  "properties": {
    "iso:country":"US",
    "sg:address":"2410 E 38th St",
    "sg:city":"Los Angeles",
    "sg:classifiers":[
        {
            "category":"Shopping",
            "type":"Retail Goods"
        }
    ],
    "sg:phone":"+1 323 267 1802",
    "sg:postcode":"90058",
    "sg:province":"CA",
    "sg:tags":[
        "wholesale",
        "candle"
    ],
    "wof:name":"Maxs Wholesale Export Import",
    "wof:placetype":"venue"
},
  "geometry": {"coordinates":[-118.228072,34.00857],"type":"Point"}
}