{
  "type": "Feature",
  "properties": {
    "iso:country":"US",
    "sg:address":"9727 Carmenita Rd",
    "sg:city":"Whittier",
    "sg:classifiers":[
        {
            "category":"Food & Beverages",
            "subcategory":"Groceries & Convenience Stores",
            "type":"Retail Goods"
        }
    ],
    "sg:phone":"+1 562 693 2150",
    "sg:postcode":"90605",
    "sg:province":"CA",
    "wof:name":"7-Eleven Food Stores",
    "wof:placetype":"venue"
},
  "geometry": {"coordinates":[-118.045998,33.948299],"type":"Point"}
}