{
  "type": "Feature",
  "properties": {
    "addr:full":"605 13th St Paso Robles CA 93446",
    "addr:housenumber":"605",
    "addr:postcode":"93446",
    "addr:street":"13Th St",
    "iso:country":"US",
    "sg:address":"605 13th St",
    "sg:city":"Paso Robles",
    "sg:classifiers":[
        {
            "category":"Professional",
            "subcategory":"Lawyer & Legal Services",
            "type":"Services"
        }
    ],
    "sg:phone":"+1 805 238 7066",
    "sg:postcode":"93446",
    "sg:province":"CA",
    "sg:tags":[
        "attorney"
    ],
    "wof:name":"Frank Kocs",
    "wof:placetype":"venue"
},
  "geometry": {"coordinates":[-120.692061,35.627707],"type":"Point"}
}