{
  "type": "Feature",
  "properties": {
    "iso:country":"US",
    "sg:address":"422 6th St",
    "sg:city":"Wheatland",
    "sg:classifiers":[
        {
            "category":"Structure",
            "subcategory":"Warehouse",
            "type":"Public Place"
        },
        {
            "category":"Retail",
            "subcategory":"Storage",
            "type":"Services"
        }
    ],
    "sg:phone":"+1 530 633 2595",
    "sg:postcode":"95692",
    "sg:province":"CA",
    "sg:tags":[
        "self",
        "warehouses-public-commercial"
    ],
    "wof:name":"Wheatland Mini Storage",
    "wof:placetype":"venue"
},
  "geometry": {"coordinates":[-121.421539,39.009729],"type":"Point"}
}