{
  "type": "Feature",
  "properties": {
    "iso:country":"US",
    "sg:address":"2566 Bay Rd",
    "sg:city":"Redwood City",
    "sg:classifiers":[
        {
            "category":"Autos & Motor Vehicles",
            "subcategory":"Automobile Sales",
            "type":"Retail Goods"
        }
    ],
    "sg:phone":"+1 650 261 1045",
    "sg:postcode":"94063",
    "sg:province":"CA",
    "sg:tags":[
        "car",
        "dealer"
    ],
    "wof:name":"Auto Works Ctr Inc",
    "wof:placetype":"venue"
},
  "geometry": {"coordinates":[-122.209211,37.484466],"type":"Point"}
}