{
  "type": "Feature",
  "properties": {
    "iso:country":"US",
    "sg:address":"7323 S Western Ave",
    "sg:city":"Los Angeles",
    "sg:classifiers":[
        {
            "category":"Organizations",
            "subcategory":"Religious Organization",
            "type":"Services"
        }
    ],
    "sg:phone":"+1 323 778 5388",
    "sg:postcode":"90047",
    "sg:province":"CA",
    "sg:tags":[
        "church"
    ],
    "wof:name":"Full Christian Fellowship Ctr",
    "wof:placetype":"venue"
},
  "geometry": {"coordinates":[-118.309049,33.972957],"type":"Point"}
}