{
  "type": "Feature",
  "properties": {
    "iso:country":"US",
    "sg:address":"700 S Oxnard Blvd",
    "sg:city":"Oxnard",
    "sg:classifiers":[
        {
            "category":"Autos & Motor Vehicles",
            "subcategory":"Fuel & Gas Station",
            "type":"Retail Goods"
        }
    ],
    "sg:phone":"+1 805 486 5759",
    "sg:postcode":"93030",
    "sg:province":"CA",
    "sg:tags":[
        "oil"
    ],
    "wof:name":"Oxnard Self Svc",
    "wof:placetype":"venue"
},
  "geometry": {"coordinates":[-119.177414,34.193697],"type":"Point"}
}