{
  "type": "Feature",
  "properties": {
    "iso:country":"US",
    "sg:address":"4955 Felspar St",
    "sg:city":"Riverside",
    "sg:classifiers":[
        {
            "category":"Restaurant",
            "type":"Food & Drink"
        }
    ],
    "sg:phone":"+1 951 681 0347",
    "sg:postcode":"92509",
    "sg:province":"CA",
    "sg:tags":[
        "out"
    ],
    "wof:name":"Big Burrito",
    "wof:placetype":"venue"
},
  "geometry": {"coordinates":[-117.484224,34.003738],"type":"Point"}
}