{
  "type": "Feature",
  "properties": {
    "iso:country":"US",
    "sg:address":"4820 International Blvd",
    "sg:city":"Oakland",
    "sg:classifiers":[
        {
            "category":"Shopping",
            "subcategory":"Clothing, Apparel, & Fashions",
            "type":"Retail Goods"
        }
    ],
    "sg:phone":"+1 510 261 7915",
    "sg:postcode":"94601",
    "sg:province":"CA",
    "sg:tags":[
        "consignment"
    ],
    "wof:name":"Second Best Consignment",
    "wof:placetype":"venue"
},
  "geometry": {"coordinates":[-122.209343,37.76976],"type":"Point"}
}