{
  "type": "Feature",
  "properties": {
    "addr:full":"1460 Washington Blvd Concord CA 94521",
    "addr:housenumber":"1460",
    "addr:postcode":"94521",
    "addr:street":"Washington Blvd",
    "iso:country":"US",
    "sg:address":"1460 Washington Blvd",
    "sg:city":"Concord",
    "sg:classifiers":[
        {
            "category":"Professional",
            "subcategory":"Business Services",
            "type":"Services"
        }
    ],
    "sg:phone":"+1 925 672 9490",
    "sg:postcode":"94521",
    "sg:province":"CA",
    "sg:tags":[
        "interior",
        "consultant",
        "design",
        "decorator"
    ],
    "wof:name":"Interiors Panache",
    "wof:placetype":"venue"
},
  "geometry": {"coordinates":[-121.95635299999999,37.951101],"type":"Point"}
}