{
  "type": "Feature",
  "properties": {
    "addr:full":"4906 Melrose Ave Los Angeles CA 90029",
    "addr:housenumber":"4906",
    "addr:postcode":"90029",
    "addr:street":"Melrose Ave",
    "iso:country":"US",
    "sg:address":"4906 Melrose Ave",
    "sg:city":"Los Angeles",
    "sg:classifiers":[
        {
            "category":"Shopping",
            "subcategory":"Computers & Home Electronics",
            "type":"Retail Goods"
        }
    ],
    "sg:phone":"+1 323 962 7795",
    "sg:postcode":"90029",
    "sg:province":"CA",
    "sg:tags":[
        "equipment",
        "satellite",
        "system"
    ],
    "wof:name":"Satellites Express",
    "wof:placetype":"venue"
},
  "geometry": {"coordinates":[-118.30745899999999,34.083443],"type":"Point"}
}