{
  "type": "Feature",
  "properties": {
    "iso:country":"US",
    "sg:address":"1601 S Grand Ave",
    "sg:city":"Santa Ana",
    "sg:classifiers":[
        {
            "category":"Health Services",
            "subcategory":"Doctor",
            "type":"Services"
        }
    ],
    "sg:phone":"+1 714 558 1600",
    "sg:postcode":"92705",
    "sg:province":"CA",
    "wof:name":"Kids Nutrition R Us",
    "wof:placetype":"venue"
},
  "geometry": {"coordinates":[-117.85030500000001,33.726709],"type":"Point"}
}