{
  "type": "Feature",
  "properties": {
    "addr:full":"5200 Bassi Rd Lotus CA 95651",
    "addr:housenumber":"5200",
    "addr:postcode":"95651",
    "addr:street":"Bassi Rd",
    "iso:country":"US",
    "sg:address":"5200 Bassi Rd",
    "sg:city":"Lotus",
    "sg:classifiers":[
        {
            "category":"Building & Trades",
            "subcategory":"Construction",
            "type":"Services"
        }
    ],
    "sg:phone":"+1 530 344 0281",
    "sg:postcode":"95651",
    "sg:province":"CA",
    "sg:tags":[
        "excavation",
        "contractor"
    ],
    "wof:name":"Morgan Trenching",
    "wof:placetype":"venue"
},
  "geometry": {"coordinates":[-120.91077199999999,38.797922],"type":"Point"}
}