{
  "type": "Feature",
  "properties": {
    "iso:country":"US",
    "sg:address":"13851 Danielson St",
    "sg:city":"Poway",
    "sg:classifiers":[
        {
            "category":"Utilities",
            "subcategory":"Telephone",
            "type":"Services"
        }
    ],
    "sg:phone":"+1 858 560 7400",
    "sg:postcode":"92064",
    "sg:province":"CA",
    "sg:tags":[
        "telecommunication"
    ],
    "sg:website":"www.goprotel.com",
    "wof:name":"Pro Tel Communications Inc",
    "wof:placetype":"venue"
},
  "geometry": {"coordinates":[-117.033115,32.939436],"type":"Point"}
}