{
  "type": "Feature",
  "properties": {
    "addr:full":"9810 Variel Ave Chatsworth CA 91311",
    "addr:housenumber":"9810",
    "addr:postcode":"91311",
    "addr:street":"Variel Ave",
    "iso:country":"US",
    "sg:address":"9810 Variel Ave",
    "sg:city":"Chatsworth",
    "sg:classifiers":[
        {
            "category":"Utilities",
            "subcategory":"Cable",
            "type":"Services"
        }
    ],
    "sg:phone":"+1 323 882 0553",
    "sg:postcode":"91311",
    "sg:province":"CA",
    "sg:tags":[
        "television"
    ],
    "wof:name":"Condor Wire & Cable Inc",
    "wof:placetype":"venue"
},
  "geometry": {"coordinates":[-118.592851,34.247963],"type":"Point"}
}