{
  "type": "Feature",
  "properties": {
    "addr:full":"1584 Branham Ln San Jose CA 95118",
    "addr:housenumber":"1584",
    "addr:postcode":"95118",
    "addr:street":"Branham Ln",
    "iso:country":"US",
    "sg:address":"1584 Branham Ln",
    "sg:city":"San Jose",
    "sg:classifiers":[
        {
            "category":"Shopping",
            "subcategory":"Department Store",
            "type":"Retail Goods"
        }
    ],
    "sg:phone":"+1 408 265 6031",
    "sg:postcode":"95118",
    "sg:province":"CA",
    "wof:name":"Desi India Bazaar",
    "wof:placetype":"venue"
},
  "geometry": {"coordinates":[-121.90082,37.254079],"type":"Point"}
}