{
  "type": "Feature",
  "properties": {
    "addr:full":"615 Coon St Kings Beach CA 96143",
    "addr:housenumber":"615",
    "addr:postcode":"96143",
    "addr:street":"Coon St",
    "iso:country":"US",
    "sg:address":"615 Coon St",
    "sg:city":"Kings Beach",
    "sg:classifiers":[
        {
            "category":"Building & Trades",
            "subcategory":"Construction",
            "type":"Services"
        }
    ],
    "sg:phone":"+1 530 546 5979",
    "sg:postcode":"96143",
    "sg:province":"CA",
    "sg:tags":[
        "maker",
        "cabinet"
    ],
    "wof:name":"Alpine Cabinet & Furniture",
    "wof:placetype":"venue"
},
  "geometry": {"coordinates":[-120.02181299999999,39.24328],"type":"Point"}
}