{
  "type": "Feature",
  "properties": {
    "addr:full":"1620 5th Ave Lbby San Diego CA 92101",
    "addr:housenumber":"1620",
    "addr:postcode":"92101",
    "addr:street":"5Th Ave",
    "iso:country":"US",
    "sg:address":"1620 5th Ave Lbby",
    "sg:city":"San Diego",
    "sg:classifiers":[
        {
            "category":"Professional",
            "subcategory":"Lawyer & Legal Services",
            "type":"Services"
        }
    ],
    "sg:phone":"+1 619 232 7384",
    "sg:postcode":"92101",
    "sg:province":"CA",
    "sg:tags":[
        "divorce",
        "law",
        "family"
    ],
    "wof:name":"Da Silva Angela",
    "wof:placetype":"venue"
},
  "geometry": {"coordinates":[-117.160004,32.722],"type":"Point"}
}