{
  "type": "Feature",
  "properties": {
    "iso:country":"US",
    "sg:address":"437 El Cajon Blvd",
    "sg:city":"El Cajon",
    "sg:classifiers":[
        {
            "category":"Retail",
            "subcategory":"Portrait Studio",
            "type":"Services"
        },
        {
            "category":"Professional",
            "subcategory":"Art Services",
            "type":"Services"
        }
    ],
    "sg:phone":"+1 619 447 4064",
    "sg:postcode":"92020",
    "sg:province":"CA",
    "sg:tags":[
        "photographer",
        "photography",
        "store"
    ],
    "wof:name":"Affordable Photography & Video Service",
    "wof:placetype":"venue"
},
  "geometry": {"coordinates":[-116.97125800000001,32.791013],"type":"Point"}
}