{
  "type": "Feature",
  "properties": {
    "iso:country":"US",
    "sg:address":"20508 Old River Rd",
    "sg:city":"West Sacramento",
    "sg:classifiers":[
        {
            "category":"Farming",
            "subcategory":"Crops",
            "type":"Manufacturing & Wholesale Goods"
        }
    ],
    "sg:phone":"+1 916 371 1260",
    "sg:postcode":"95691",
    "sg:province":"CA",
    "sg:tags":[
        "grove",
        "nut",
        "tree"
    ],
    "wof:name":"Matthew Borman",
    "wof:placetype":"venue"
},
  "geometry": {"coordinates":[-121.57196999999999,38.646721],"type":"Point"}
}