{
  "type": "Feature",
  "properties": {
    "addr:full":"1111 W La Palma Ave Anaheim CA 92801",
    "addr:housenumber":"1111",
    "addr:postcode":"92801",
    "addr:street":"W La Palma Ave",
    "iso:country":"US",
    "sg:address":"1111 W La Palma Ave",
    "sg:city":"Anaheim",
    "sg:classifiers":[
        {
            "category":"Health Services",
            "subcategory":"Hospital",
            "type":"Services"
        }
    ],
    "sg:phone":"+1 714 999 5153",
    "sg:postcode":"92801",
    "sg:province":"CA",
    "sg:website":"www.anaheimregionalmc.com/",
    "wof:name":"Anaheim Regional Medical Center",
    "wof:placetype":"venue"
},
  "geometry": {"coordinates":[-117.93580799999999,33.847611],"type":"Point"}
}