{
  "type": "Feature",
  "properties": {
    "iso:country":"US",
    "sg:address":"2310 Westgate Rd Ste 1",
    "sg:city":"Santa Maria",
    "sg:classifiers":[
        {
            "category":"Retail",
            "subcategory":"Auto Repair",
            "type":"Services"
        }
    ],
    "sg:phone":"+1 805 922 6888",
    "sg:postcode":"93455",
    "sg:province":"CA",
    "wof:name":"High Tech Automobile Service",
    "wof:placetype":"venue"
},
  "geometry": {"coordinates":[-120.46061,34.919663],"type":"Point"}
}