{
  "type": "Feature",
  "properties": {
    "addr:full":"3540 Norwood Avenue Sacramento CA 95838",
    "addr:housenumber":"3540",
    "addr:postcode":"95838",
    "addr:street":"Norwood Avenue",
    "iso:country":"US",
    "sg:address":"3540 Norwood Avenue",
    "sg:city":"Sacramento",
    "sg:classifiers":[
        {
            "category":"Cinema",
            "subcategory":"Movie Rental",
            "type":"Entertainment"
        }
    ],
    "sg:phone":"+1 916 641 6451",
    "sg:postcode":"95838",
    "sg:province":"CA",
    "sg:tags":[
        "game",
        "video"
    ],
    "wof:name":"Cm Video and Fashion",
    "wof:placetype":"venue"
},
  "geometry": {"coordinates":[-121.456928,38.631689],"type":"Point"}
}