{
  "type": "Feature",
  "properties": {
    "addr:full":"2850 Ingleton Ln Sacramento CA 95835",
    "addr:housenumber":"2850",
    "addr:postcode":"95835",
    "addr:street":"Ingleton Ln",
    "iso:country":"US",
    "sg:address":"2850 Ingleton Ln",
    "sg:city":"Sacramento",
    "sg:classifiers":[
        {
            "category":"Travel",
            "subcategory":"Travel Agent",
            "type":"Entertainment"
        }
    ],
    "sg:phone":"+1 916 391 7800",
    "sg:postcode":"95835",
    "sg:province":"CA",
    "sg:tags":[
        "agency"
    ],
    "wof:name":"Trinity World Travel",
    "wof:placetype":"venue"
},
  "geometry": {"coordinates":[-121.525002,38.681468],"type":"Point"}
}