{
  "type": "Feature",
  "properties": {
    "iso:country":"US",
    "sg:address":"7590 Fay Ave Ste 204",
    "sg:city":"La Jolla",
    "sg:classifiers":[
        {
            "category":"Travel",
            "subcategory":"Travel Agent",
            "type":"Entertainment"
        }
    ],
    "sg:phone":"+1 858 551 4000",
    "sg:postcode":"92037",
    "sg:province":"CA",
    "sg:website":"www.traveldynamicsgroup.com",
    "wof:name":"Travel Dynamics Group",
    "wof:placetype":"venue"
},
  "geometry": {"coordinates":[-117.274597,32.841779],"type":"Point"}
}