{
  "type": "Feature",
  "properties": {
    "iso:country":"US",
    "sg:address":"18213 Via Dicha",
    "sg:city":"Rowland Heights",
    "sg:classifiers":[
        {
            "category":"Wholesale",
            "subcategory":"Non-durable Goods",
            "type":"Manufacturing & Wholesale Goods"
        }
    ],
    "sg:phone":"+1 626 581 4551",
    "sg:postcode":"91748",
    "sg:province":"CA",
    "sg:tags":[
        "tropical",
        "fish"
    ],
    "wof:name":"Starfish Imports",
    "wof:placetype":"venue"
},
  "geometry": {"coordinates":[-117.908007,33.98516],"type":"Point"}
}