{
  "type": "Feature",
  "properties": {
    "addr:full":"6267 Citracado Cir Carlsbad CA 92009",
    "addr:housenumber":"6267",
    "addr:postcode":"92009",
    "addr:street":"Citracado Cir",
    "iso:country":"US",
    "sg:address":"6267 Citracado Cir",
    "sg:city":"Carlsbad",
    "sg:classifiers":[
        {
            "category":"Real Estate",
            "subcategory":"Architect",
            "type":"Services"
        }
    ],
    "sg:phone":"+1 760 918 9220",
    "sg:postcode":"92009",
    "sg:province":"CA",
    "wof:name":"Architectural Crown Mouldings",
    "wof:placetype":"venue"
},
  "geometry": {"coordinates":[-117.243376,33.127511],"type":"Point"}
}