{
  "type": "Feature",
  "properties": {
    "addr:full":"929 Broadway Wasco CA 93280",
    "addr:housenumber":"929",
    "addr:postcode":"ca 93280",
    "addr:street":"Broadway",
    "iso:country":"US",
    "sg:address":"929 Broadway",
    "sg:city":"Wasco",
    "sg:classifiers":[
        {
            "category":"Social Services",
            "subcategory":"Child Care",
            "type":"Services"
        }
    ],
    "sg:phone":"+1 661 758 6829",
    "sg:postcode":"93280",
    "sg:province":"CA",
    "sg:tags":[
        "kindergarten",
        "academic",
        "school"
    ],
    "wof:name":"St John's Pre-School & Infant",
    "wof:placetype":"venue"
},
  "geometry": {"coordinates":[-119.33826999999999,35.59129],"type":"Point"}
}