{
  "type": "Feature",
  "properties": {
    "iso:country":"US",
    "sg:address":"1421 California Cir",
    "sg:city":"Milpitas",
    "sg:classifiers":[
        {
            "category":"Manufacturing",
            "subcategory":"Tools & Machinery",
            "type":"Manufacturing & Wholesale Goods"
        }
    ],
    "sg:phone":"+1 408 635 4300",
    "sg:postcode":"95035",
    "sg:province":"CA",
    "sg:tags":[
        "testing",
        "apparatus"
    ],
    "wof:name":"Credence Systems Corp",
    "wof:placetype":"venue"
},
  "geometry": {"coordinates":[-121.919237,37.450657],"type":"Point"}
}