{
  "type": "Feature",
  "properties": {
    "iso:country":"US",
    "sg:address":"655 W Tennyson Rd",
    "sg:city":"Hayward",
    "sg:classifiers":[
        {
            "category":"Shopping",
            "subcategory":"Jewelry",
            "type":"Retail Goods"
        }
    ],
    "sg:phone":"+1 510 785 7111",
    "sg:postcode":"94544",
    "sg:province":"CA",
    "sg:tags":[
        "jeweler"
    ],
    "wof:name":"Espinosa Jewelry & Boutique",
    "wof:placetype":"venue"
},
  "geometry": {"coordinates":[-122.068277,37.632234],"type":"Point"}
}