{
  "type": "Feature",
  "properties": {
    "iso:country":"US",
    "sg:address":"1479 Salmon Way",
    "sg:city":"Hayward",
    "sg:classifiers":[
        {
            "category":"Professional",
            "subcategory":"Management & Consulting",
            "type":"Services"
        }
    ],
    "sg:phone":"+1 510 249 1480",
    "sg:postcode":"94544",
    "sg:province":"CA",
    "sg:tags":[
        "consultant",
        "business"
    ],
    "wof:name":"Manex",
    "wof:placetype":"venue"
},
  "geometry": {"coordinates":[-122.05656399999999,37.610142],"type":"Point"}
}