{
  "type": "Feature",
  "properties": {
    "iso:country":"US",
    "sg:address":"1919 Irving St",
    "sg:city":"San Francisco",
    "sg:classifiers":[
        {
            "category":"Food & Beverages",
            "subcategory":"Candy",
            "type":"Retail Goods"
        }
    ],
    "sg:phone":"+1 415 759 1081",
    "sg:postcode":"94122",
    "sg:province":"CA",
    "sg:tags":[
        "dessert"
    ],
    "wof:name":"88 Dessert",
    "wof:placetype":"venue"
},
  "geometry": {"coordinates":[-122.47851300000001,37.763221],"type":"Point"}
}