{
  "type": "Feature",
  "properties": {
    "addr:full":"1060 N 5th St San Jose CA 95112",
    "addr:housenumber":"1060",
    "addr:postcode":"95112",
    "addr:street":"N 5Th St",
    "iso:country":"US",
    "sg:address":"1060 N 5th St",
    "sg:city":"San Jose",
    "sg:classifiers":[
        {
            "category":"Wholesale",
            "subcategory":"Construction Materials",
            "type":"Manufacturing & Wholesale Goods"
        }
    ],
    "sg:phone":"+1 408 279 6432",
    "sg:postcode":"95112",
    "sg:province":"CA",
    "sg:tags":[
        "equipment",
        "roofing",
        "supply"
    ],
    "sg:website":"www.so-lite.com",
    "wof:name":"So-Lite Manufacturing",
    "wof:placetype":"venue"
},
  "geometry": {"coordinates":[-121.901884,37.359136],"type":"Point"}
}