{
  "type": "Feature",
  "properties": {
    "iso:country":"US",
    "sg:address":"842 River Rd",
    "sg:city":"Salinas",
    "sg:classifiers":[
        {
            "category":"Building & Trades",
            "subcategory":"Construction",
            "type":"Services"
        }
    ],
    "sg:phone":"+1 831 455 2288",
    "sg:postcode":"93908",
    "sg:province":"CA",
    "sg:tags":[
        "house"
    ],
    "wof:name":"G H Construction",
    "wof:placetype":"venue"
},
  "geometry": {"coordinates":[-121.571342,36.570543],"type":"Point"}
}