{
  "type": "Feature",
  "properties": {
    "addr:full":"970 Sunrise Ave Roseville CA 95661",
    "addr:housenumber":"970",
    "addr:postcode":"95661",
    "addr:street":"Sunrise Ave",
    "iso:country":"US",
    "sg:address":"970 Sunrise Ave",
    "sg:city":"Roseville",
    "sg:classifiers":[
        {
            "category":"Utilities",
            "type":"Services"
        }
    ],
    "sg:phone":"+1 916 780 9900",
    "sg:postcode":"95661",
    "sg:province":"CA",
    "sg:tags":[
        "sanitary"
    ],
    "wof:name":"National Medical Services",
    "wof:placetype":"venue"
},
  "geometry": {"coordinates":[-121.27213500000001,38.731421],"type":"Point"}
}