{
  "type": "Feature",
  "properties": {
    "addr:full":"847 Shell Ave Martinez CA 94553",
    "addr:housenumber":"847",
    "addr:postcode":"94553",
    "addr:street":"Shell Ave",
    "iso:country":"US",
    "sg:address":"847 Shell Ave",
    "sg:city":"Martinez",
    "sg:classifiers":[
        {
            "category":"Professional",
            "subcategory":"Business Services",
            "type":"Services"
        }
    ],
    "sg:phone":"+1 925 372 8733",
    "sg:postcode":"94553",
    "sg:province":"CA",
    "sg:tags":[
        "notary",
        "public"
    ],
    "wof:name":"Patricia Monte Notary Publ",
    "wof:placetype":"venue"
},
  "geometry": {"coordinates":[-122.123169,38.007408],"type":"Point"}
}