{
  "type": "Feature",
  "properties": {
    "iso:country":"US",
    "sg:address":"2500 W Olympic Boulevard",
    "sg:city":"Los Angeles",
    "sg:classifiers":[
        {
            "category":"Retail",
            "subcategory":"Auto Repair",
            "type":"Services"
        }
    ],
    "sg:phone":"+1 213 365 6600",
    "sg:postcode":"90006",
    "sg:province":"CA",
    "wof:name":"Korea Auto Body Shop",
    "wof:placetype":"venue"
},
  "geometry": {"coordinates":[-118.284594,34.052519],"type":"Point"}
}