{
  "type": "Feature",
  "properties": {
    "iso:country":"US",
    "sg:address":"3201 W Benjamin Holt Dr",
    "sg:city":"Stockton",
    "sg:classifiers":[
        {
            "category":"Restaurant",
            "type":"Food & Drink"
        }
    ],
    "sg:menulink":"http://www.allmenus.com/ca/stockton/149382-subway/menu/",
    "sg:phone":"+1 209 952 8873",
    "sg:postcode":"95219",
    "sg:province":"CA",
    "sg:tags":[
        "american",
        "sandwich"
    ],
    "wof:name":"Subway",
    "wof:placetype":"venue"
},
  "geometry": {"coordinates":[-121.353914,38.005159],"type":"Point"}
}