{
  "type": "Feature",
  "properties": {
    "addr:full":"19411 McLaren Ln Huntington Beach CA 92646",
    "addr:housenumber":"19411",
    "addr:postcode":"92646",
    "addr:street":"Mclaren Ln",
    "iso:country":"US",
    "sg:address":"19411 McLaren Ln",
    "sg:city":"Huntington Beach",
    "sg:classifiers":[
        {
            "category":"Shopping",
            "subcategory":"Computers & Home Electronics",
            "type":"Retail Goods"
        }
    ],
    "sg:phone":"+1 714 717 1759",
    "sg:postcode":"92646",
    "sg:province":"CA",
    "sg:tags":[
        "equipment",
        "satellite",
        "system"
    ],
    "wof:name":"Ad Satellite Svc",
    "wof:placetype":"venue"
},
  "geometry": {"coordinates":[-117.970522,33.679896],"type":"Point"}
}