{
  "type": "Feature",
  "properties": {
    "addr:full":"17010 Farwell St Fontana CA 92336",
    "addr:housenumber":"17010",
    "addr:postcode":"92336",
    "addr:street":"Farwell St",
    "iso:country":"US",
    "sg:address":"17010 Farwell St",
    "sg:city":"Fontana",
    "sg:classifiers":[
        {
            "category":"Banks & Credit Unions",
            "subcategory":"Financial Services",
            "type":"Services"
        }
    ],
    "sg:phone":"+1 909 355 1561",
    "sg:postcode":"92336",
    "sg:province":"CA",
    "sg:tags":[
        "trust",
        "management"
    ],
    "wof:name":"Vansant Survivors Trust 0",
    "wof:placetype":"venue"
},
  "geometry": {"coordinates":[-117.431911,34.131982],"type":"Point"}
}