{
  "type": "Feature",
  "properties": {
    "addr:full":"3494 N Valley Rd Greenville CA 95947",
    "addr:housenumber":"3494",
    "addr:postcode":"95947",
    "addr:street":"N Valley Rd",
    "iso:country":"US",
    "sg:address":"3494 N Valley Rd",
    "sg:city":"Greenville",
    "sg:classifiers":[
        {
            "category":"Manufacturing",
            "subcategory":"Tools & Machinery",
            "type":"Manufacturing & Wholesale Goods"
        }
    ],
    "sg:phone":"+1 530 284 7134",
    "sg:postcode":"95947",
    "sg:province":"CA",
    "sg:tags":[
        "pattern",
        "industrial",
        "mfg"
    ],
    "wof:name":"Heidi Marsh Patterns",
    "wof:placetype":"venue"
},
  "geometry": {"coordinates":[-120.895397,40.145341],"type":"Point"}
}