{
  "type": "Feature",
  "properties": {
    "iso:country":"US",
    "sg:address":"14411 Shannon Rd",
    "sg:city":"Los Gatos",
    "sg:classifiers":[
        {
            "category":"Retail",
            "subcategory":"Animal Services",
            "type":"Services"
        }
    ],
    "sg:phone":"+1 408 356 3560",
    "sg:postcode":"95032",
    "sg:province":"CA",
    "sg:tags":[
        "horse",
        "training"
    ],
    "wof:name":"Full Bridle Farms LLC",
    "wof:placetype":"venue"
},
  "geometry": {"coordinates":[-121.918413,37.219039],"type":"Point"}
}