{
  "type": "Feature",
  "properties": {
    "addr:full":"900 Newville Rd Orland CA 95963",
    "addr:housenumber":"900",
    "addr:postcode":"95963",
    "addr:street":"Newville Rd",
    "iso:country":"US",
    "sg:address":"900 Newville Rd",
    "sg:city":"Orland",
    "sg:classifiers":[
        {
            "category":"Restaurant",
            "type":"Food & Drink"
        }
    ],
    "sg:phone":"+1 530 865 8484",
    "sg:postcode":"95963",
    "sg:province":"CA",
    "wof:name":"Berry Patch Restaurant",
    "wof:placetype":"venue"
},
  "geometry": {"coordinates":[-122.200428,39.748622],"type":"Point"}
}