{
  "type": "Feature",
  "properties": {
    "addr:full":"45120 Oasis St Indio CA 92201",
    "addr:housenumber":"45120",
    "addr:postcode":"92201",
    "addr:street":"Oasis St",
    "iso:country":"US",
    "sg:address":"45120 Oasis St",
    "sg:city":"Indio",
    "sg:classifiers":[
        {
            "category":"Education",
            "subcategory":"Vocational School",
            "type":"Public Place"
        }
    ],
    "sg:phone":"+1 760 775 5333",
    "sg:postcode":"92201",
    "sg:province":"CA",
    "wof:name":"Computer Skills Ctr",
    "wof:placetype":"venue"
},
  "geometry": {"coordinates":[-116.220703,33.719458],"type":"Point"}
}