{
  "type": "Feature",
  "properties": {
    "iso:country":"US",
    "sg:address":"14906 Dickens St",
    "sg:city":"Sherman Oaks",
    "sg:classifiers":[
        {
            "category":"Professional",
            "subcategory":"Management & Consulting",
            "type":"Services"
        }
    ],
    "sg:phone":"+1 818 501 3977",
    "sg:postcode":"91403",
    "sg:province":"CA",
    "sg:tags":[
        "consultant",
        "business"
    ],
    "wof:name":"Magic Boy Productions",
    "wof:placetype":"venue"
},
  "geometry": {"coordinates":[-118.46086099999999,34.15157],"type":"Point"}
}