{
  "type": "Feature",
  "properties": {
    "addr:full":"665 Fairview Ave Arcadia CA 91007",
    "addr:housenumber":"665",
    "addr:postcode":"91007",
    "addr:street":"Fairview Ave",
    "iso:country":"US",
    "sg:address":"665 Fairview Ave",
    "sg:city":"Arcadia",
    "sg:classifiers":[
        {
            "category":"Retail",
            "subcategory":"Laundry & Dry Cleaning",
            "type":"Services"
        }
    ],
    "sg:phone":"+1 626 446 5412",
    "sg:postcode":"91007",
    "sg:province":"CA",
    "sg:tags":[
        "cleaners"
    ],
    "wof:name":"Continental Dry Cleaners",
    "wof:placetype":"venue"
},
  "geometry": {"coordinates":[-118.05342899999999,34.129154],"type":"Point"}
}