{
  "type": "Feature",
  "properties": {
    "iso:country":"US",
    "sg:address":"3775 Via Nona Marie",
    "sg:city":"Carmel",
    "sg:classifiers":[
        {
            "category":"Banks & Credit Unions",
            "subcategory":"Financial Services",
            "type":"Services"
        }
    ],
    "sg:phone":"+1 831 622 2526",
    "sg:postcode":"93923",
    "sg:province":"CA",
    "sg:tags":[
        "broker",
        "mortgage"
    ],
    "wof:name":"Butler Peter Coldwell Banker Del Monte Realty",
    "wof:placetype":"venue"
},
  "geometry": {"coordinates":[-121.905998,36.539299],"type":"Point"}
}