{
  "type": "Feature",
  "properties": {
    "addr:full":"4110 E Patero Way Long Beach CA 90815",
    "addr:housenumber":"4110",
    "addr:postcode":"90815",
    "addr:street":"E Patero Way",
    "iso:country":"US",
    "sg:address":"4110 E Patero Way",
    "sg:city":"Long Beach",
    "sg:classifiers":[
        {
            "category":"Government",
            "subcategory":"Office",
            "type":"Public Place"
        }
    ],
    "sg:phone":"+1 562 985 3362",
    "sg:postcode":"90815",
    "sg:province":"CA",
    "sg:tags":[
        "management"
    ],
    "sg:website":"www.swrrn.com",
    "wof:name":"SWR Resource Network Inc",
    "wof:placetype":"venue"
},
  "geometry": {"coordinates":[-118.14341,33.794988],"type":"Point"}
}