{
  "type": "Feature",
  "properties": {
    "addr:full":"760 E Capitol Ave Milpitas CA 95035",
    "addr:housenumber":"760",
    "addr:postcode":"95035",
    "addr:street":"E Capitol Ave",
    "iso:country":"US",
    "sg:address":"760 E Capitol Ave",
    "sg:city":"Milpitas",
    "sg:classifiers":[
        {
            "category":"Building & Trades",
            "subcategory":"Construction",
            "type":"Services"
        }
    ],
    "sg:phone":"+1 408 719 9950",
    "sg:postcode":"95035",
    "sg:province":"CA",
    "sg:tags":[
        "excavating",
        "contractor"
    ],
    "wof:name":"Doyle's Work Co Inc",
    "wof:placetype":"venue"
},
  "geometry": {"coordinates":[-121.88947,37.407851],"type":"Point"}
}