{
  "type": "Feature",
  "properties": {
    "iso:country":"US",
    "sg:address":"20440 Brown St",
    "sg:city":"Perris",
    "sg:classifiers":[
        {
            "category":"Retail",
            "subcategory":"Animal Services",
            "type":"Services"
        }
    ],
    "sg:phone":"+1 951 940 0026",
    "sg:postcode":"92570",
    "sg:province":"CA",
    "sg:website":"www.countscovekennels.com",
    "wof:name":"Counts Cove Kennels",
    "wof:placetype":"venue"
},
  "geometry": {"coordinates":[-117.296166,33.823045],"type":"Point"}
}