{
  "type": "Feature",
  "properties": {
    "addr:full":"11151 1st Ave Whittier CA 90603",
    "addr:housenumber":"11151",
    "addr:postcode":"90603",
    "addr:street":"1St Ave",
    "iso:country":"US",
    "sg:address":"11151 1st Ave",
    "sg:city":"Whittier",
    "sg:classifiers":[
        {
            "category":"Shopping",
            "subcategory":"Pets & Pet Supplies",
            "type":"Retail Goods"
        },
        {
            "category":"Retail",
            "subcategory":"Animal Services",
            "type":"Services"
        }
    ],
    "sg:phone":"+1 562 902 5700",
    "sg:postcode":"90603",
    "sg:province":"CA",
    "sg:tags":[
        "grooming",
        "store",
        "groomers"
    ],
    "sg:website":"www.healthypawsstore.com",
    "wof:name":"Healthy Paws",
    "wof:placetype":"venue"
},
  "geometry": {"coordinates":[-117.985468,33.931386],"type":"Point"}
}