{
  "type": "Feature",
  "properties": {
    "addr:full":"107 E 9th St Los Angeles CA 90015",
    "addr:housenumber":"107",
    "addr:postcode":"90015",
    "addr:street":"E 9Th St",
    "iso:country":"US",
    "sg:address":"107 E 9th St",
    "sg:city":"Los Angeles",
    "sg:classifiers":[
        {
            "category":"Retail",
            "subcategory":"Photofinishing",
            "type":"Services"
        }
    ],
    "sg:phone":"+1 213 683 1997",
    "sg:postcode":"90015",
    "sg:province":"CA",
    "sg:tags":[
        "photo",
        "finishing"
    ],
    "wof:name":"Nice Photo & Color Copy Inc",
    "wof:placetype":"venue"
},
  "geometry": {"coordinates":[-118.254589,34.041345],"type":"Point"}
}