{
  "type": "Feature",
  "properties": {
    "iso:country":"US",
    "sg:address":"23 Orinda Way",
    "sg:city":"Orinda",
    "sg:classifiers":[
        {
            "category":"Health Services",
            "subcategory":"Doctor",
            "type":"Services"
        }
    ],
    "sg:phone":"+1 925 254 0700",
    "sg:postcode":"94563",
    "sg:province":"CA",
    "sg:tags":[
        "physician",
        "family",
        "practice",
        "surgeons",
        "medicine",
        "surgeon"
    ],
    "wof:name":"Bertram Lynn MD",
    "wof:placetype":"venue"
},
  "geometry": {"coordinates":[-122.188154,37.88174],"type":"Point"}
}