{
  "type": "Feature",
  "properties": {
    "addr:full":"3352 Goodway Ct Soquel CA 95073",
    "addr:housenumber":"3352",
    "addr:postcode":"95073",
    "addr:street":"Goodway Ct",
    "iso:country":"US",
    "sg:address":"3352 Goodway Ct",
    "sg:city":"Soquel",
    "sg:classifiers":[
        {
            "category":"Professional",
            "subcategory":"Computer Services",
            "type":"Services"
        }
    ],
    "sg:phone":"+1 831 462 5744",
    "sg:postcode":"95073",
    "sg:province":"CA",
    "sg:tags":[
        "repair"
    ],
    "wof:name":"A-Plus Computer Repair",
    "wof:placetype":"venue"
},
  "geometry": {"coordinates":[-121.947085,36.991024],"type":"Point"}
}