{
  "type": "Feature",
  "properties": {
    "iso:country":"US",
    "sg:address":"899 Ellis St",
    "sg:city":"San Francisco",
    "sg:classifiers":[
        {
            "category":"Organizations",
            "subcategory":"Professional Association",
            "type":"Services"
        }
    ],
    "sg:phone":"+1 415 673 2450",
    "sg:postcode":"94109",
    "sg:province":"CA",
    "sg:tags":[
        "global",
        "assoc"
    ],
    "wof:name":"Institute For Interntl Crimin",
    "wof:placetype":"venue"
},
  "geometry": {"coordinates":[-122.419364,37.784029],"type":"Point"}
}