{
  "type": "Feature",
  "properties": {
    "iso:country":"US",
    "sg:address":"3001 Zinfandel Dr",
    "sg:city":"Rancho Cordova",
    "sg:classifiers":[
        {
            "category":"Retail",
            "subcategory":"Auto Repair",
            "type":"Services"
        }
    ],
    "sg:phone":"+1 916 635 2626",
    "sg:postcode":"95670",
    "sg:province":"CA",
    "sg:website":"www.chevron.com",
    "wof:name":"Bill Wood Chevron",
    "wof:placetype":"venue"
},
  "geometry": {"coordinates":[-121.287195,38.593279],"type":"Point"}
}