{
  "type": "Feature",
  "properties": {
    "iso:country":"US",
    "sg:address":"801 W Center Ave",
    "sg:city":"Visalia",
    "sg:classifiers":[
        {
            "category":"Health Services",
            "subcategory":"Doctor",
            "type":"Services"
        }
    ],
    "sg:phone":"+1 559 737 4700",
    "sg:postcode":"93291",
    "sg:province":"CA",
    "sg:tags":[
        "clinic"
    ],
    "wof:name":"Family Healthcare Network",
    "wof:placetype":"venue"
},
  "geometry": {"coordinates":[-119.301059,36.331016],"type":"Point"}
}