{
  "type": "Feature",
  "properties": {
    "addr:full":"4699 Mercury St San Diego CA 92111",
    "addr:housenumber":"4699",
    "addr:postcode":"92111",
    "addr:street":"Mercury St",
    "iso:country":"US",
    "sg:address":"4699 Mercury St",
    "sg:city":"San Diego",
    "sg:classifiers":[
        {
            "category":"Home & Garden",
            "subcategory":"Building Materials",
            "type":"Retail Goods"
        }
    ],
    "sg:phone":"+1 858 974 5100",
    "sg:postcode":"92111",
    "sg:province":"CA",
    "sg:tags":[
        "plumbing",
        "bath",
        "kitchen",
        "fixture",
        "supply"
    ],
    "sg:website":"www.ferguson.com",
    "wof:name":"Ferguson Enterprises, Inc.",
    "wof:placetype":"venue"
},
  "geometry": {"coordinates":[-117.148843,32.825995],"type":"Point"}
}