{
  "type": "Feature",
  "properties": {
    "iso:country":"US",
    "sg:address":"7171 Firestone Boulevard",
    "sg:city":"Downey",
    "sg:classifiers":[
        {
            "category":"Shopping",
            "subcategory":"Clothing, Apparel, & Fashions",
            "type":"Retail Goods"
        },
        {
            "category":"Shopping",
            "subcategory":"Party Supplies",
            "type":"Retail Goods"
        }
    ],
    "sg:phone":"+1 562 927 4660",
    "sg:postcode":"90241",
    "sg:province":"CA",
    "sg:tags":[
        "costume"
    ],
    "wof:name":"Party City",
    "wof:placetype":"venue"
},
  "geometry": {"coordinates":[-118.152942,33.947515],"type":"Point"}
}