{
  "type": "Feature",
  "properties": {
    "addr:full":"5454 Jillson St Los Angeles CA 90040",
    "addr:postcode":"5454;90040",
    "addr:street":"Jillson St",
    "iso:country":"US",
    "sg:address":"5454 Jillson St",
    "sg:city":"Los Angeles",
    "sg:classifiers":[
        {
            "category":"Retail",
            "subcategory":"Portrait Studio",
            "type":"Services"
        }
    ],
    "sg:phone":"+1 323 726 1431",
    "sg:postcode":"90040",
    "sg:province":"CA",
    "sg:tags":[
        "photographer"
    ],
    "wof:name":"Roberts Studio Of Photography",
    "wof:placetype":"venue"
},
  "geometry": {"coordinates":[-118.16248,34.002144],"type":"Point"}
}