{
  "type": "Feature",
  "properties": {
    "iso:country":"US",
    "sg:address":"1021 El Camino Real",
    "sg:city":"Santa Clara",
    "sg:classifiers":[
        {
            "category":"Autos & Motor Vehicles",
            "subcategory":"Automobile Sales",
            "type":"Retail Goods"
        }
    ],
    "sg:phone":"+1 408 554 8326",
    "sg:postcode":"95050",
    "sg:province":"CA",
    "sg:tags":[
        "automotive"
    ],
    "wof:name":"5 Star Auto Services",
    "wof:placetype":"venue"
},
  "geometry": {"coordinates":[-121.94759500000001,37.354596],"type":"Point"}
}