{
  "type": "Feature",
  "properties": {
    "iso:country":"US",
    "sg:address":"2779 Aborn Rd",
    "sg:city":"San Jose",
    "sg:classifiers":[
        {
            "category":"Banks & Credit Unions",
            "subcategory":"Bank",
            "type":"Services"
        }
    ],
    "sg:phone":"+1 408 496 4800",
    "sg:postcode":"95121",
    "sg:province":"CA",
    "wof:name":"Bank Of Santa Clara",
    "wof:placetype":"venue"
},
  "geometry": {"coordinates":[-121.793753,37.313715],"type":"Point"}
}