{
  "type": "Feature",
  "properties": {
    "addr:full":"2155 Encinal Ave Alameda CA 94501",
    "addr:housenumber":"2155",
    "addr:postcode":"94501",
    "addr:street":"Encinal Ave",
    "iso:country":"US",
    "sg:address":"2155 Encinal Ave",
    "sg:city":"Alameda",
    "sg:classifiers":[
        {
            "category":"Retail",
            "subcategory":"Laundry & Dry Cleaning",
            "type":"Services"
        }
    ],
    "sg:phone":"+1 510 484 8178",
    "sg:postcode":"94501",
    "sg:province":"CA",
    "wof:name":"Smartlaundry",
    "wof:placetype":"venue"
},
  "geometry": {"coordinates":[-122.249571,37.764988],"type":"Point"}
}