{
  "type": "Feature",
  "properties": {
    "iso:country":"US",
    "sg:address":"131 Russ St",
    "sg:city":"San Francisco",
    "sg:classifiers":[
        {
            "category":"Manufacturing",
            "subcategory":"Food",
            "type":"Manufacturing & Wholesale Goods"
        }
    ],
    "sg:phone":"+1 415 861 2680",
    "sg:postcode":"94103",
    "sg:province":"CA",
    "sg:tags":[
        "product",
        "fountain",
        "mfg"
    ],
    "wof:name":"Eng-Skell Company",
    "wof:placetype":"venue"
},
  "geometry": {"coordinates":[-122.407045,37.778059],"type":"Point"}
}