{
  "type": "Feature",
  "properties": {
    "iso:country":"US",
    "sg:address":"250 E Caroline St",
    "sg:city":"San Bernardino",
    "sg:classifiers":[
        {
            "category":"Health Services",
            "subcategory":"Doctor",
            "type":"Services"
        }
    ],
    "sg:phone":"+1 909 783 9400",
    "sg:postcode":"92408",
    "sg:province":"CA",
    "sg:tags":[
        "physician",
        "surgeon"
    ],
    "wof:name":"Hospitality Health Ctr",
    "wof:placetype":"venue"
},
  "geometry": {"coordinates":[-117.279347,34.061573],"type":"Point"}
}