{
  "type": "Feature",
  "properties": {
    "iso:country":"US",
    "sg:address":"20194 Hidden Acres Rd",
    "sg:city":"Sonora",
    "sg:classifiers":[
        {
            "category":"Building & Trades",
            "subcategory":"Electrical",
            "type":"Services"
        }
    ],
    "sg:phone":"+1 209 532 2342",
    "sg:postcode":"95370",
    "sg:province":"CA",
    "sg:tags":[
        "equipment"
    ],
    "wof:name":"S & E Advanced Systems",
    "wof:placetype":"venue"
},
  "geometry": {"coordinates":[-120.28022199999999,37.988887],"type":"Point"}
}