{
  "type": "Feature",
  "properties": {
    "iso:country":"US",
    "sg:address":"1812 S Pacific Ave",
    "sg:city":"San Pedro",
    "sg:classifiers":[
        {
            "category":"Retail",
            "subcategory":"Auto Repair",
            "type":"Services"
        }
    ],
    "sg:phone":"+1 310 833 5644",
    "sg:postcode":"90731",
    "sg:province":"CA",
    "sg:tags":[
        "body",
        "automobile",
        "painting"
    ],
    "wof:name":"Automotive Specialities",
    "wof:placetype":"venue"
},
  "geometry": {"coordinates":[-118.287953,33.728778],"type":"Point"}
}