{
  "type": "Feature",
  "properties": {
    "iso:country":"US",
    "sg:address":"44503 Old Stage Rd",
    "sg:city":"Posey",
    "sg:classifiers":[
        {
            "category":"Travel",
            "subcategory":"Campground",
            "type":"Entertainment"
        }
    ],
    "sg:phone":"+1 661 536 9323",
    "sg:postcode":"93260",
    "sg:province":"CA",
    "sg:tags":[
        "camp"
    ],
    "wof:name":"Sierra Christian Svc Camp",
    "wof:placetype":"venue"
},
  "geometry": {"coordinates":[-118.66662599999999,35.805653],"type":"Point"}
}