{
  "type": "Feature",
  "properties": {
    "addr:full":"1201 Wellington Dr Modesto CA 95350",
    "addr:housenumber":"1201",
    "addr:postcode":"ca 95350",
    "addr:street":"Wellington Dr",
    "iso:country":"US",
    "sg:address":"1201 Wellington Dr",
    "sg:city":"Modesto",
    "sg:classifiers":[
        {
            "category":"Professional",
            "subcategory":"Engineering",
            "type":"Services"
        }
    ],
    "sg:phone":"+1 209 579 8756",
    "sg:postcode":"95350",
    "sg:province":"CA",
    "sg:tags":[
        "engineer"
    ],
    "wof:name":"Follette Engineering Inc",
    "wof:placetype":"venue"
},
  "geometry": {"coordinates":[-121.010834,37.682871],"type":"Point"}
}