{
  "type": "Feature",
  "properties": {
    "addr:full":"135 S Jackson St Glendale CA 91205",
    "addr:housenumber":"135",
    "addr:postcode":"91205",
    "addr:street":"S Jackson St",
    "iso:country":"US",
    "sg:address":"135 S Jackson St",
    "sg:city":"Glendale",
    "sg:classifiers":[
        {
            "category":"Professional",
            "subcategory":"Lawyer & Legal Services",
            "type":"Services"
        }
    ],
    "sg:phone":"+1 818 246 6300",
    "sg:postcode":"91205",
    "sg:province":"CA",
    "sg:tags":[
        "attorney"
    ],
    "wof:name":"Scott Solis Law Offices",
    "wof:placetype":"venue"
},
  "geometry": {"coordinates":[-118.25014899999999,34.145138],"type":"Point"}
}