{
  "type": "Feature",
  "properties": {
    "addr:full":"Valencia Mall 24201 Valencia Blvd, Ste 3537 Valencia CA 91355",
    "addr:housenumber":"24201",
    "addr:postcode":"91355",
    "addr:street":"Valencia Blvd Ste 3537",
    "iso:country":"US",
    "sg:address":"Valencia Mall 24201 Valencia Blvd, Ste 3537",
    "sg:city":"Valencia",
    "sg:classifiers":[
        {
            "category":"Shopping",
            "subcategory":"Clothing, Apparel, & Fashions",
            "type":"Retail Goods"
        }
    ],
    "sg:postcode":"91355",
    "sg:province":"CA",
    "sg:tags":[
        "accessory"
    ],
    "wof:name":"Francesca's Collection",
    "wof:placetype":"venue"
},
  "geometry": {"coordinates":[-118.557666,34.416061],"type":"Point"}
}