{
  "type": "Feature",
  "properties": {
    "iso:country":"US",
    "sg:address":"155 Terraza Ct",
    "sg:city":"Costa Mesa",
    "sg:classifiers":[
        {
            "category":"Retail",
            "subcategory":"Auto Repair",
            "type":"Services"
        }
    ],
    "sg:phone":"+1 949 642 9786",
    "sg:postcode":"92627",
    "sg:province":"CA",
    "sg:tags":[
        "repairing",
        "automobile"
    ],
    "wof:name":"R M Auto",
    "wof:placetype":"venue"
},
  "geometry": {"coordinates":[-117.899715,33.656883],"type":"Point"}
}