{
  "type": "Feature",
  "properties": {
    "iso:country":"US",
    "sg:address":"4999 Sullivan St",
    "sg:city":"Ventura",
    "sg:classifiers":[
        {
            "category":"Retail",
            "subcategory":"Laundry & Dry Cleaning",
            "type":"Services"
        }
    ],
    "sg:phone":"+1 805 258 2010",
    "sg:postcode":"93003",
    "sg:province":"CA",
    "sg:tags":[
        "cleaners",
        "rug",
        "carpet"
    ],
    "wof:name":"Beaker's Carpet & Upholstery",
    "wof:placetype":"venue"
},
  "geometry": {"coordinates":[-119.225501,34.265305],"type":"Point"}
}