{
  "type": "Feature",
  "properties": {
    "iso:country":"US",
    "sg:address":"5783 N Palm Ave",
    "sg:city":"Fresno",
    "sg:classifiers":[
        {
            "category":"Food & Beverages",
            "subcategory":"Groceries & Convenience Stores",
            "type":"Retail Goods"
        }
    ],
    "sg:phone":"+1 559 439 3368",
    "sg:postcode":"93704",
    "sg:province":"CA",
    "wof:name":"Beacon",
    "wof:placetype":"venue"
},
  "geometry": {"coordinates":[-119.808376,36.82272],"type":"Point"}
}