{
  "type": "Feature",
  "properties": {
    "iso:country":"US",
    "sg:address":"13117 Aerospace Dr",
    "sg:city":"Victorville",
    "sg:classifiers":[
        {
            "category":"Freight",
            "type":"Transportation"
        }
    ],
    "sg:phone":"+1 760 246 5724",
    "sg:postcode":"92394",
    "sg:province":"CA",
    "sg:tags":[
        "trucking"
    ],
    "wof:name":"Apollo Truck Ctr",
    "wof:placetype":"venue"
},
  "geometry": {"coordinates":[-117.378986,34.579677],"type":"Point"}
}