{
  "type": "Feature",
  "properties": {
    "iso:country":"US",
    "sg:address":"3412 Egmont Way",
    "sg:city":"Sacramento",
    "sg:classifiers":[
        {
            "category":"Retail",
            "subcategory":"Auto Repair",
            "type":"Services"
        }
    ],
    "sg:phone":"+1 916 821 9985",
    "sg:postcode":"95827",
    "sg:province":"CA",
    "sg:tags":[
        "repairing",
        "automobile"
    ],
    "wof:name":"Advanced Auto Air & Repair",
    "wof:placetype":"venue"
},
  "geometry": {"coordinates":[-121.331678,38.56337],"type":"Point"}
}