{
  "type": "Feature",
  "properties": {
    "addr:full":"3150 El Camino Real Palo Alto CA 94306",
    "addr:housenumber":"3150",
    "addr:postcode":"94306",
    "addr:street":"El Camino Real",
    "iso:country":"US",
    "sg:address":"3150 El Camino Real",
    "sg:city":"Palo Alto",
    "sg:classifiers":[
        {
            "category":"Restaurant",
            "type":"Food & Drink"
        }
    ],
    "sg:menulink":"http://www.allmenus.com/ca/san-jose/20348-the-fish-market/menu/",
    "sg:phone":"+1 650 493 9188",
    "sg:postcode":"94306",
    "sg:province":"CA",
    "sg:tags":[
        "seafood",
        "american"
    ],
    "wof:name":"The Fish Market",
    "wof:placetype":"venue"
},
  "geometry": {"coordinates":[-122.13888300000001,37.421311],"type":"Point"}
}