{
  "type": "Feature",
  "properties": {
    "iso:country":"US",
    "sg:address":"7240 E Southgate Dr",
    "sg:city":"Sacramento",
    "sg:classifiers":[
        {
            "category":"Shopping",
            "subcategory":"Pharmacy",
            "type":"Retail Goods"
        }
    ],
    "sg:phone":"+1 916 393 5961",
    "sg:postcode":"95823",
    "sg:province":"CA",
    "wof:name":"Mai Pharmacy",
    "wof:placetype":"venue"
},
  "geometry": {"coordinates":[-121.43779000000001,38.494035],"type":"Point"}
}