{
  "type": "Feature",
  "properties": {
    "iso:country":"US",
    "sg:address":"19711 Hemmingway St",
    "sg:city":"Winnetka",
    "sg:classifiers":[
        {
            "category":"Building & Trades",
            "subcategory":"Landscaping Services",
            "type":"Services"
        }
    ],
    "sg:phone":"+1 818 709 8002",
    "sg:postcode":"91306",
    "sg:province":"CA",
    "wof:name":"Valley Lawn Service",
    "wof:placetype":"venue"
},
  "geometry": {"coordinates":[-118.56300400000001,34.213902],"type":"Point"}
}