{
  "type": "Feature",
  "properties": {
    "addr:full":"4224 California Street Suite 105 San Francisco CA 94118",
    "addr:housenumber":"4224",
    "addr:postcode":"94118",
    "addr:street":"California Street Suite 105",
    "iso:country":"US",
    "sg:address":"4224 California Street Suite 105",
    "sg:city":"San Francisco",
    "sg:classifiers":[
        {
            "category":"Banks & Credit Unions",
            "subcategory":"Financial Services",
            "type":"Services"
        }
    ],
    "sg:phone":"+1 415 668 4040",
    "sg:postcode":"94118",
    "sg:province":"CA",
    "sg:tags":[
        "broker",
        "mortgage"
    ],
    "wof:name":"Royal Reserve Financial",
    "wof:placetype":"venue"
},
  "geometry": {"coordinates":[-122.459999,37.7812],"type":"Point"}
}