{
  "type": "Feature",
  "properties": {
    "addr:full":"833 W 22nd St Merced CA 95340",
    "addr:housenumber":"833",
    "addr:postcode":"95340",
    "addr:street":"W 22Nd St",
    "iso:country":"US",
    "sg:address":"833 W 22nd St",
    "sg:city":"Merced",
    "sg:classifiers":[
        {
            "category":"Professional",
            "subcategory":"Business Services",
            "type":"Services"
        }
    ],
    "sg:phone":"+1 209 383 3233",
    "sg:postcode":"95340",
    "sg:province":"CA",
    "sg:tags":[
        "process",
        "server"
    ],
    "wof:name":"Attorney Services Of Merced",
    "wof:placetype":"venue"
},
  "geometry": {"coordinates":[-120.486096,37.308526],"type":"Point"}
}