{
  "type": "Feature",
  "properties": {
    "iso:country":"US",
    "sg:address":"1011 Cam del Mar",
    "sg:city":"Del Mar",
    "sg:classifiers":[
        {
            "category":"Professional",
            "subcategory":"Accounting & Tax Preparation",
            "type":"Services"
        }
    ],
    "sg:phone":"+1 858 793 1411",
    "sg:postcode":"92014",
    "sg:province":"CA",
    "sg:tags":[
        "accountant"
    ],
    "wof:name":"Shaban Accountancy",
    "wof:placetype":"venue"
},
  "geometry": {"coordinates":[-117.086288,33.144888],"type":"Point"}
}