{
  "type": "Feature",
  "properties": {
    "addr:full":"1405 Woodruff Ave Los Angeles CA 90024",
    "addr:housenumber":"1405",
    "addr:postcode":"90024",
    "addr:street":"Woodruff Ave",
    "iso:country":"US",
    "sg:address":"1405 Woodruff Ave",
    "sg:city":"Los Angeles",
    "sg:classifiers":[
        {
            "category":"Professional",
            "subcategory":"Business Services",
            "type":"Services"
        }
    ],
    "sg:phone":"+1 310 441 1231",
    "sg:postcode":"90024",
    "sg:province":"CA",
    "wof:name":"Dworsky Group LLC",
    "wof:placetype":"venue"
},
  "geometry": {"coordinates":[-118.427226,34.060486],"type":"Point"}
}