{
  "type": "Feature",
  "properties": {
    "iso:country":"US",
    "sg:address":"CSULB Arts Ticket Office 6200 Atherton St",
    "sg:city":"Long Beach",
    "sg:classifiers":[
        {
            "category":"Arts & Performance",
            "subcategory":"Arts Center",
            "type":"Entertainment"
        }
    ],
    "sg:phone":"+1 562 985 7000",
    "sg:postcode":"90815",
    "sg:province":"CA",
    "sg:tags":[
        "performing"
    ],
    "sg:website":"www.csulb.edu/~dance/performance...",
    "wof:name":"Martha Knoebel Dance Theatre",
    "wof:placetype":"venue"
},
  "geometry": {"coordinates":[-118.11174,33.788658],"type":"Point"}
}