{
  "type": "Feature",
  "properties": {
    "addr:full":"9767 Glenoaks Blvd Sun Valley CA 91352",
    "addr:housenumber":"9767",
    "addr:postcode":"91352",
    "addr:street":"Glenoaks Blvd",
    "iso:country":"US",
    "sg:address":"9767 Glenoaks Blvd",
    "sg:city":"Sun Valley",
    "sg:classifiers":[
        {
            "category":"Manufacturing",
            "subcategory":"Tools & Machinery",
            "type":"Manufacturing & Wholesale Goods"
        }
    ],
    "sg:phone":"+1 818 768 8982",
    "sg:postcode":"91352",
    "sg:province":"CA",
    "sg:tags":[
        "mfg"
    ],
    "wof:name":"Pashas Cutting Die Co",
    "wof:placetype":"venue"
},
  "geometry": {"coordinates":[-118.386478,34.248591],"type":"Point"}
}