{
  "type": "Feature",
  "properties": {
    "addr:full":"8224 Ronson Rd San Diego CA 92111",
    "addr:housenumber":"8224",
    "addr:postcode":"92111",
    "addr:street":"Ronson Rd",
    "iso:country":"US",
    "sg:address":"8224 Ronson Rd",
    "sg:city":"San Diego",
    "sg:classifiers":[
        {
            "category":"Manufacturing",
            "subcategory":"Tools & Machinery",
            "type":"Manufacturing & Wholesale Goods"
        }
    ],
    "sg:phone":"+1 858 496 5252",
    "sg:postcode":"92111",
    "sg:province":"CA",
    "sg:tags":[
        "forming",
        "metal"
    ],
    "sg:website":"www.magneform.com",
    "wof:name":"Maxwell-Magneform",
    "wof:placetype":"venue"
},
  "geometry": {"coordinates":[-117.148663,32.829157],"type":"Point"}
}