{
  "type": "Feature",
  "properties": {
    "iso:country":"US",
    "sg:address":"14 Skylark Dr Apt 208",
    "sg:city":"Larkspur",
    "sg:classifiers":[
        {
            "category":"Autos & Motor Vehicles",
            "subcategory":"Automobile Sales",
            "type":"Retail Goods"
        }
    ],
    "sg:phone":"+1 415 533 8380",
    "sg:postcode":"94939",
    "sg:province":"CA",
    "sg:tags":[
        "new",
        "car"
    ],
    "wof:name":"Gavilan Honda",
    "wof:placetype":"venue"
},
  "geometry": {"coordinates":[-122.54353399999999,37.9441],"type":"Point"}
}