{
  "type": "Feature",
  "properties": {
    "addr:full":"1408 Nathan Ln Ventura CA 93001",
    "addr:housenumber":"1408",
    "addr:postcode":"93001",
    "addr:street":"Nathan Ln",
    "iso:country":"US",
    "sg:address":"1408 Nathan Ln",
    "sg:city":"Ventura",
    "sg:classifiers":[
        {
            "category":"Recreation",
            "type":"Entertainment"
        }
    ],
    "sg:phone":"+1 805 654 3951",
    "sg:postcode":"93001",
    "sg:province":"CA",
    "sg:tags":[
        "parks"
    ],
    "wof:name":"Hobson Beach Park",
    "wof:placetype":"venue"
},
  "geometry": {"coordinates":[-119.268956,34.255595],"type":"Point"}
}