{
  "type": "Feature",
  "properties": {
    "addr:full":"733 3rd St Mc Farland CA 93250",
    "addr:housenumber":"733",
    "addr:postcode":"93250",
    "addr:street":"3Rd St Mc Farland",
    "iso:country":"US",
    "sg:address":"733 3rd St",
    "sg:city":"Mc Farland",
    "sg:classifiers":[
        {
            "category":"Health Services",
            "subcategory":"Doctor",
            "type":"Services"
        }
    ],
    "sg:phone":"+1 661 792 3097",
    "sg:postcode":"93250",
    "sg:province":"CA",
    "sg:tags":[
        "physician",
        "surgeon"
    ],
    "wof:name":"Singh Medical Clinic",
    "wof:placetype":"venue"
},
  "geometry": {"coordinates":[-119.23101200000001,35.6847],"type":"Point"}
}