{
  "type": "Feature",
  "properties": {
    "iso:country":"US",
    "sg:address":"528 Green St",
    "sg:city":"San Francisco",
    "sg:classifiers":[
        {
            "category":"Education",
            "subcategory":"Preschool",
            "type":"Public Place"
        }
    ],
    "sg:phone":"+1 415 673 2393",
    "sg:postcode":"94133",
    "sg:province":"CA",
    "sg:website":"www.globalanguages.com",
    "wof:name":"Globalanguages Language Center",
    "wof:placetype":"venue"
},
  "geometry": {"coordinates":[-122.40790800000001,37.799647],"type":"Point"}
}