{
  "type": "Feature",
  "properties": {
    "addr:full":"80 W Sierra Madre Blvd Ste 219 Sierra Madre CA 91024",
    "addr:housenumber":"80",
    "addr:postcode":"91024",
    "addr:street":"W Sierra Madre Blvd Ste 219;Madre",
    "iso:country":"US",
    "sg:address":"80 W Sierra Madre Blvd Ste 219",
    "sg:city":"Sierra Madre",
    "sg:classifiers":[
        {
            "category":"Building & Trades",
            "subcategory":"Construction",
            "type":"Services"
        }
    ],
    "sg:phone":"+1 626 277 3419",
    "sg:postcode":"91024",
    "sg:province":"CA",
    "sg:tags":[
        "handyman"
    ],
    "wof:name":"Sgv Handyman",
    "wof:placetype":"venue"
},
  "geometry": {"coordinates":[-118.054429,34.161621],"type":"Point"}
}