{
  "type": "Feature",
  "properties": {
    "iso:country":"US",
    "sg:address":"431 Linda Ave",
    "sg:city":"Piedmont",
    "sg:classifiers":[
        {
            "category":"Science Facility",
            "type":"Public Place"
        }
    ],
    "sg:phone":"+1 510 759 4865",
    "sg:postcode":"94611",
    "sg:province":"CA",
    "sg:tags":[
        "development",
        "laboratories-research"
    ],
    "wof:name":"Berkeley Materials Research",
    "wof:placetype":"venue"
},
  "geometry": {"coordinates":[-122.24478000000001,37.821792],"type":"Point"}
}