{
  "type": "Feature",
  "properties": {
    "addr:full":"1265 Alabama St Redlands CA 92374",
    "addr:housenumber":"1265",
    "addr:postcode":"92374",
    "addr:street":"Alabama St",
    "iso:country":"US",
    "sg:address":"1265 Alabama St",
    "sg:city":"Redlands",
    "sg:classifiers":[
        {
            "category":"Coffee & Tea",
            "type":"Food & Drink"
        }
    ],
    "sg:menulink":"http://www.allmenus.com/ca/san-bernardino/108174-starbucks-coffee/menu/",
    "sg:phone":"+1 909 798 1426",
    "sg:postcode":"92374",
    "sg:province":"CA",
    "sg:tags":[
        "american"
    ],
    "wof:name":"Starbucks Coffee",
    "wof:placetype":"venue"
},
  "geometry": {"coordinates":[-117.209164,34.069266],"type":"Point"}
}