{
  "type": "Feature",
  "properties": {
    "addr:full":"815 Hyde St San Francisco CA 94109",
    "addr:housenumber":"815",
    "addr:postcode":"94109",
    "addr:street":"Hyde St",
    "iso:country":"US",
    "sg:address":"815 Hyde St",
    "sg:city":"San Francisco",
    "sg:classifiers":[
        {
            "category":"Health Services",
            "subcategory":"Doctor",
            "type":"Services"
        }
    ],
    "sg:phone":"+1 415 749 6800",
    "sg:postcode":"94109",
    "sg:province":"CA",
    "sg:tags":[
        "physician",
        "surgeon"
    ],
    "wof:name":"William Kwan MD",
    "wof:placetype":"venue"
},
  "geometry": {"coordinates":[-122.41707,37.788965],"type":"Point"}
}