{
  "type": "Feature",
  "properties": {
    "iso:country":"US",
    "sg:address":"4260 Broadway",
    "sg:city":"Eureka",
    "sg:classifiers":[
        {
            "category":"Travel",
            "subcategory":"Hotels & Motels",
            "type":"Entertainment"
        }
    ],
    "sg:phone":"+1 707 445 9161",
    "sg:postcode":"95503",
    "sg:province":"CA",
    "wof:name":"Patel Shailesh",
    "wof:placetype":"venue"
},
  "geometry": {"coordinates":[-124.191615,40.767181],"type":"Point"}
}