{
  "type": "Feature",
  "properties": {
    "addr:full":"25015 Newhall Ave Newhall CA 91321",
    "addr:housenumber":"25015",
    "addr:postcode":"91321",
    "addr:street":"Newhall Ave",
    "iso:country":"US",
    "sg:address":"25015 Newhall Ave",
    "sg:city":"Newhall",
    "sg:classifiers":[
        {
            "category":"Education",
            "subcategory":"School",
            "type":"Public Place"
        }
    ],
    "sg:phone":"+1 661 259 1551",
    "sg:postcode":"91321",
    "sg:province":"CA",
    "sg:tags":[
        "high",
        "middle",
        "elementary"
    ],
    "wof:name":"William S Hart Union High School District",
    "wof:placetype":"venue"
},
  "geometry": {"coordinates":[-118.539001,34.387901],"type":"Point"}
}