{
  "type": "Feature",
  "properties": {
    "addr:full":"2391 Butano Dr Sacramento CA 95825",
    "addr:housenumber":"2391",
    "addr:postcode":"95825",
    "addr:street":"Butano Dr",
    "iso:country":"US",
    "sg:address":"2391 Butano Dr",
    "sg:city":"Sacramento",
    "sg:classifiers":[
        {
            "category":"Food & Beverages",
            "subcategory":"Bakery",
            "type":"Retail Goods"
        }
    ],
    "sg:phone":"+1 916 338 7770",
    "sg:postcode":"95825",
    "sg:province":"CA",
    "sg:tags":[
        "cookie",
        "cracker"
    ],
    "wof:name":"Mrs Field's Original Cookies",
    "wof:placetype":"venue"
},
  "geometry": {"coordinates":[-121.38221299999999,38.606705],"type":"Point"}
}