{
  "type": "Feature",
  "properties": {
    "iso:country":"US",
    "sg:address":"12199 Broadway",
    "sg:city":"Whittier",
    "sg:classifiers":[
        {
            "category":"Park",
            "type":"Public Place"
        }
    ],
    "sg:postcode":"90601",
    "sg:province":"CA",
    "wof:name":"Founders Memorial Park",
    "wof:placetype":"venue"
},
  "geometry": {"coordinates":[-118.047038,33.986356],"type":"Point"}
}