{
  "type": "Feature",
  "properties": {
    "iso:country":"US",
    "sg:address":"10625 Valley Dr",
    "sg:city":"Plymouth",
    "sg:classifiers":[
        {
            "category":"Food & Beverages",
            "subcategory":"Farmers Market",
            "type":"Retail Goods"
        }
    ],
    "sg:phone":"+1 209 245 4161",
    "sg:postcode":"95669",
    "sg:province":"CA",
    "sg:tags":[
        "vegetable",
        "fruit",
        "shipper",
        "grower"
    ],
    "wof:name":"Carl Hangebrauk",
    "wof:placetype":"venue"
},
  "geometry": {"coordinates":[-120.82755899999999,38.5235],"type":"Point"}
}