{
  "type": "Feature",
  "properties": {
    "iso:country":"US",
    "sg:address":"3617-A Pacific Coast Hwy",
    "sg:city":"Torrance",
    "sg:classifiers":[
        {
            "category":"Shopping",
            "subcategory":"Florist",
            "type":"Retail Goods"
        }
    ],
    "sg:phone":"+1 866 375 2491",
    "sg:postcode":"90505",
    "sg:province":"CA",
    "sg:website":"www.louisgardensflorist.com",
    "wof:name":"Louis Gardens Florist",
    "wof:placetype":"venue"
},
  "geometry": {"coordinates":[-118.348394,33.804815],"type":"Point"}
}