{
  "type": "Feature",
  "properties": {
    "iso:country":"US",
    "sg:address":"519 E Greenway Ave",
    "sg:city":"Turlock",
    "sg:classifiers":[
        {
            "category":"Professional",
            "type":"Services"
        }
    ],
    "sg:phone":"+1 209 634 6882",
    "sg:postcode":"95380",
    "sg:province":"CA",
    "sg:tags":[
        "establishment"
    ],
    "wof:name":"Hanger 8",
    "wof:placetype":"venue"
},
  "geometry": {"coordinates":[-120.833392,37.467404],"type":"Point"}
}