{
  "type": "Feature",
  "properties": {
    "iso:country":"US",
    "sg:address":"5401 Stockdale Hwy",
    "sg:city":"Bakersfield",
    "sg:classifiers":[
        {
            "category":"Autos & Motor Vehicles",
            "subcategory":"Fuel & Gas Station",
            "type":"Retail Goods"
        }
    ],
    "sg:phone":"+1 661 832 9928",
    "sg:postcode":"93309",
    "sg:province":"CA",
    "sg:tags":[
        "oil"
    ],
    "wof:name":"Stockton Mobil",
    "wof:placetype":"venue"
},
  "geometry": {"coordinates":[-119.06643800000001,35.354265],"type":"Point"}
}