{
  "type": "Feature",
  "properties": {
    "addr:full":"525 Cypress Ave Hermosa Beach CA 90254",
    "addr:housenumber":"525",
    "addr:postcode":"90254",
    "addr:street":"Cypress Ave",
    "iso:country":"US",
    "sg:address":"525 Cypress Ave",
    "sg:city":"Hermosa Beach",
    "sg:classifiers":[
        {
            "category":"Retail",
            "subcategory":"Auto Repair",
            "type":"Services"
        }
    ],
    "sg:phone":"+1 310 379 6636",
    "sg:postcode":"90254",
    "sg:province":"CA",
    "sg:tags":[
        "brake"
    ],
    "wof:name":"Johnsons Brake Supply",
    "wof:placetype":"venue"
},
  "geometry": {"coordinates":[-118.395335,33.858281],"type":"Point"}
}