{
  "type": "Feature",
  "properties": {
    "addr:full":"310 Santa Fe Dr Encinitas CA 92024",
    "addr:housenumber":"310",
    "addr:postcode":"92024",
    "addr:street":"Santa Fe Dr",
    "iso:country":"US",
    "sg:address":"310 Santa Fe Dr",
    "sg:city":"Encinitas",
    "sg:classifiers":[
        {
            "category":"Health Services",
            "subcategory":"Medical Lab",
            "type":"Services"
        }
    ],
    "sg:phone":"+1 760 753 9359",
    "sg:postcode":"92024",
    "sg:province":"CA",
    "sg:tags":[
        "laboratory"
    ],
    "wof:name":"Laboratory Corporation America",
    "wof:placetype":"venue"
},
  "geometry": {"coordinates":[-117.28504700000001,33.036309],"type":"Point"}
}