{
  "type": "Feature",
  "properties": {
    "addr:full":"215 Carnelian Bay Ave Carnelian Bay CA 96140",
    "addr:housenumber":"215",
    "addr:postcode":"96140",
    "addr:street":"Carnelian Bay Ave",
    "iso:country":"US",
    "sg:address":"215 Carnelian Bay Ave",
    "sg:city":"Carnelian Bay",
    "sg:classifiers":[
        {
            "category":"Health Services",
            "subcategory":"Health Practitioner",
            "type":"Services"
        }
    ],
    "sg:phone":"+1 530 546 7581",
    "sg:postcode":"96140",
    "sg:province":"CA",
    "sg:tags":[
        "therapist",
        "physical"
    ],
    "wof:name":"Carnelian Bay Physical Therapy",
    "wof:placetype":"venue"
},
  "geometry": {"coordinates":[-120.082441,39.227391],"type":"Point"}
}