{
  "type": "Feature",
  "properties": {
    "addr:full":"22314 Avis Ct Torrance CA 90505",
    "addr:postcode":"22314;90505",
    "addr:street":"Avis Ct",
    "iso:country":"US",
    "sg:address":"22314 Avis Ct",
    "sg:city":"Torrance",
    "sg:classifiers":[
        {
            "category":"Building & Trades",
            "subcategory":"Construction",
            "type":"Services"
        }
    ],
    "sg:phone":"+1 310 326 5992",
    "sg:postcode":"90505",
    "sg:province":"CA",
    "sg:tags":[
        "roofing",
        "industrial",
        "contractors-commercial",
        "contractor"
    ],
    "wof:name":"Hodne Construction Incorporated",
    "wof:placetype":"venue"
},
  "geometry": {"coordinates":[-118.34528400000001,33.824674],"type":"Point"}
}