{
  "type": "Feature",
  "properties": {
    "addr:full":"24196 Alicia Pkwy Ste A Mission Viejo CA 92691",
    "addr:housenumber":"24196",
    "addr:postcode":"92691",
    "addr:street":"Alicia Pkwy Ste A",
    "iso:country":"US",
    "sg:address":"24196 Alicia Pkwy Ste A",
    "sg:city":"Mission Viejo",
    "sg:classifiers":[
        {
            "category":"Place Of Worship",
            "subcategory":"Church",
            "type":"Public Place"
        }
    ],
    "sg:phone":"+1 949 586 4510",
    "sg:postcode":"92691",
    "sg:province":"CA",
    "sg:website":"www.missionhillschurch.com",
    "wof:name":"Mission Hills Church",
    "wof:placetype":"venue"
},
  "geometry": {"coordinates":[-117.689385,33.607739],"type":"Point"}
}