{
  "type": "Feature",
  "properties": {
    "addr:full":"43524 Kirkland Ave Lancaster CA 93535",
    "addr:housenumber":"43524",
    "addr:postcode":"93535",
    "addr:street":"Kirkland Ave",
    "iso:country":"US",
    "sg:address":"43524 Kirkland Ave",
    "sg:city":"Lancaster",
    "sg:classifiers":[
        {
            "category":"Professional",
            "subcategory":"Printing & Photocopies",
            "type":"Services"
        }
    ],
    "sg:phone":"+1 661 726 0890",
    "sg:postcode":"93535",
    "sg:province":"CA",
    "sg:tags":[
        "duplicating",
        "copying"
    ],
    "wof:name":"A A Integrity Tech",
    "wof:placetype":"venue"
},
  "geometry": {"coordinates":[-118.124459,34.674586],"type":"Point"}
}