{
  "type": "Feature",
  "properties": {
    "addr:full":"1844 Quiet Brook Ct Manteca CA 95337",
    "addr:housenumber":"1844",
    "addr:postcode":"95337",
    "addr:street":"Quiet Brook Ct",
    "iso:country":"US",
    "sg:address":"1844 Quiet Brook Ct",
    "sg:city":"Manteca",
    "sg:classifiers":[
        {
            "category":"Retail",
            "subcategory":"Laundry & Dry Cleaning",
            "type":"Services"
        },
        {
            "category":"Building & Trades",
            "subcategory":"Cleaning & Sanitation",
            "type":"Services"
        }
    ],
    "sg:phone":"+1 209 922 1989",
    "sg:postcode":"95337",
    "sg:province":"CA",
    "sg:tags":[
        "cleaner",
        "upholstery",
        "fabric",
        "rug",
        "protection",
        "furniture",
        "carpet"
    ],
    "wof:name":"Central Carpet Cleaning",
    "wof:placetype":"venue"
},
  "geometry": {"coordinates":[-121.247248,37.787695],"type":"Point"}
}