{
  "type": "Feature",
  "properties": {
    "addr:full":"1040 Stoneridge Dr Pasadena CA 91105",
    "addr:housenumber":"1040",
    "addr:postcode":"91105",
    "addr:street":"Stoneridge Dr",
    "iso:country":"US",
    "sg:address":"1040 Stoneridge Dr",
    "sg:city":"Pasadena",
    "sg:classifiers":[
        {
            "category":"Building & Trades",
            "subcategory":"Landscaping Services",
            "type":"Services"
        }
    ],
    "sg:phone":"+1 626 799 9514",
    "sg:postcode":"91105",
    "sg:province":"CA",
    "sg:tags":[
        "designer",
        "landscape"
    ],
    "wof:name":"Tongg Clarke & Mc Celvey",
    "wof:placetype":"venue"
},
  "geometry": {"coordinates":[-118.160701,34.127814],"type":"Point"}
}