{
  "type": "Feature",
  "properties": {
    "addr:full":"2289 Main St Cambria CA 93428",
    "addr:housenumber":"2289",
    "addr:postcode":"93428",
    "addr:street":"Main St",
    "iso:country":"US",
    "sg:address":"2289 Main St",
    "sg:city":"Cambria",
    "sg:classifiers":[
        {
            "category":"Arts & Performance",
            "subcategory":"Art Gallery",
            "type":"Entertainment"
        }
    ],
    "sg:phone":"+1 805 927 1800",
    "sg:postcode":"93428",
    "sg:province":"CA",
    "wof:name":"Sunfire Gallery",
    "wof:placetype":"venue"
},
  "geometry": {"coordinates":[-121.07399700000001,35.565601],"type":"Point"}
}