{
  "type": "Feature",
  "properties": {
    "iso:country":"US",
    "sg:address":"747 American St",
    "sg:city":"Stockton",
    "sg:classifiers":[
        {
            "category":"Insurance",
            "subcategory":"Insurance Agent",
            "type":"Services"
        }
    ],
    "sg:phone":"+1 209 942 3366",
    "sg:postcode":"95202",
    "sg:province":"CA",
    "wof:name":"Collage Services Inc",
    "wof:placetype":"venue"
},
  "geometry": {"coordinates":[-121.285404,37.961277],"type":"Point"}
}