{
  "type": "Feature",
  "properties": {
    "iso:country":"US",
    "sg:address":"1599 Haight St",
    "sg:city":"San Francisco",
    "sg:classifiers":[
        {
            "category":"Personal",
            "subcategory":"Tattoo Parlor",
            "type":"Services"
        },
        {
            "category":"Personal",
            "subcategory":"Piercing",
            "type":"Services"
        }
    ],
    "sg:phone":"+1 415 552 3444",
    "sg:postcode":"94117",
    "sg:province":"CA",
    "sg:website":"www.soulpatchtattoo.com",
    "wof:name":"Soul Patch",
    "wof:placetype":"venue"
},
  "geometry": {"coordinates":[-122.448577,37.769836],"type":"Point"}
}