{
  "type": "Feature",
  "properties": {
    "addr:full":"4045 Piccadilly Ln San Mateo CA 94403",
    "addr:housenumber":"4045",
    "addr:postcode":"94403",
    "addr:street":"Piccadilly Ln",
    "iso:country":"US",
    "sg:address":"4045 Piccadilly Ln",
    "sg:city":"San Mateo",
    "sg:classifiers":[
        {
            "category":"Personal",
            "subcategory":"Beauty Salon",
            "type":"Services"
        }
    ],
    "sg:phone":"+1 650 356 0966",
    "sg:postcode":"94403",
    "sg:province":"CA",
    "sg:tags":[
        "spa",
        "day"
    ],
    "wof:name":"Naturally A Day Spa",
    "wof:placetype":"venue"
},
  "geometry": {"coordinates":[-122.290847,37.529785],"type":"Point"}
}