{
  "type": "Feature",
  "properties": {
    "addr:full":"655 Vermont Ave Turlock CA 95380",
    "addr:housenumber":"655",
    "addr:postcode":"95380",
    "addr:street":"Vermont Ave",
    "iso:country":"US",
    "sg:address":"655 Vermont Ave",
    "sg:city":"Turlock",
    "sg:classifiers":[
        {
            "category":"Professional",
            "type":"Services"
        }
    ],
    "sg:phone":"+1 209 613 7948",
    "sg:postcode":"95380",
    "sg:province":"CA",
    "wof:name":"Simply Spas of California",
    "wof:placetype":"venue"
},
  "geometry": {"coordinates":[-120.855994,37.488033],"type":"Point"}
}