{
  "type": "Feature",
  "properties": {
    "addr:full":"4515 Ord Ferry Rd Chico CA 95928",
    "addr:housenumber":"4515",
    "addr:postcode":"95928",
    "addr:street":"Ord Ferry Rd",
    "iso:country":"US",
    "sg:address":"4515 Ord Ferry Rd",
    "sg:city":"Chico",
    "sg:classifiers":[
        {
            "category":"Building & Trades",
            "subcategory":"Construction",
            "type":"Services"
        }
    ],
    "sg:phone":"+1 530 892 2551",
    "sg:postcode":"95928",
    "sg:province":"CA",
    "sg:tags":[
        "house"
    ],
    "wof:name":"Duisenberg Construction",
    "wof:placetype":"venue"
},
  "geometry": {"coordinates":[-121.90307300000001,39.638077],"type":"Point"}
}