{
  "type": "Feature",
  "properties": {
    "addr:full":"598 S Washington St Sonora CA 95370",
    "addr:housenumber":"598",
    "addr:postcode":"95370",
    "addr:street":"S Washington St",
    "iso:country":"US",
    "sg:address":"598 S Washington St",
    "sg:city":"Sonora",
    "sg:classifiers":[
        {
            "category":"Autos & Motor Vehicles",
            "subcategory":"Auto Supplies",
            "type":"Retail Goods"
        }
    ],
    "sg:phone":"+1 209 532 7439",
    "sg:postcode":"95370",
    "sg:province":"CA",
    "sg:tags":[
        "automobile",
        "parts"
    ],
    "wof:name":"Sonora Auto Parts",
    "wof:placetype":"venue"
},
  "geometry": {"coordinates":[-120.380424,37.977616],"type":"Point"}
}