{
  "type": "Feature",
  "properties": {
    "iso:country":"US",
    "sg:address":"2199 Pantages Cir",
    "sg:city":"Rancho Cordova",
    "sg:classifiers":[
        {
            "category":"Professional",
            "subcategory":"Business Services",
            "type":"Services"
        }
    ],
    "sg:phone":"+1 916 635 5530",
    "sg:postcode":"95670",
    "sg:province":"CA",
    "sg:tags":[
        "drafting"
    ],
    "wof:name":"Galvez & Assoc Inc",
    "wof:placetype":"venue"
},
  "geometry": {"coordinates":[-121.29448,38.612228],"type":"Point"}
}