{
  "type": "Feature",
  "properties": {
    "iso:country":"US",
    "sg:address":"725 Valentina Dr",
    "sg:city":"Oxnard",
    "sg:classifiers":[
        {
            "category":"Professional",
            "type":"Services"
        }
    ],
    "sg:phone":"+1 805 988 0624",
    "sg:postcode":"93030",
    "sg:province":"CA",
    "wof:name":"Coronado Sassy",
    "wof:placetype":"venue"
},
  "geometry": {"coordinates":[-119.160085,34.208376],"type":"Point"}
}