{
  "type": "Feature",
  "properties": {
    "addr:full":"714 W Olympic Boulevard Los Angeles CA 90015",
    "addr:housenumber":"714",
    "addr:postcode":"90015",
    "addr:street":"W Olympic Boulevard",
    "iso:country":"US",
    "sg:address":"714 W Olympic Boulevard",
    "sg:city":"Los Angeles",
    "sg:classifiers":[
        {
            "category":"Building & Trades",
            "subcategory":"Construction",
            "type":"Services"
        }
    ],
    "sg:phone":"+1 213 741 8737",
    "sg:postcode":"90015",
    "sg:province":"CA",
    "sg:tags":[
        "contractor"
    ],
    "wof:name":"Swinerton Builders",
    "wof:placetype":"venue"
},
  "geometry": {"coordinates":[-118.26297099999999,34.044452],"type":"Point"}
}