{
  "type": "Feature",
  "properties": {
    "addr:full":"1146 Margarita Ave Grover Beach CA 93433",
    "addr:housenumber":"1146",
    "addr:postcode":"93433",
    "addr:street":"Margarita Ave",
    "iso:country":"US",
    "sg:address":"1146 Margarita Ave",
    "sg:city":"Grover Beach",
    "sg:classifiers":[
        {
            "category":"Real Estate",
            "subcategory":"Real Estate Agent",
            "type":"Services"
        }
    ],
    "sg:phone":"+1 805 481 7139",
    "sg:postcode":"93433",
    "sg:province":"CA",
    "sg:tags":[
        "appraiser"
    ],
    "wof:name":"KCR Appraisals",
    "wof:placetype":"venue"
},
  "geometry": {"coordinates":[-120.615488,35.130013],"type":"Point"}
}