{
  "type": "Feature",
  "properties": {
    "iso:country":"US",
    "sg:address":"1639 Orchard St",
    "sg:city":"Santa Rosa",
    "sg:classifiers":[
        {
            "category":"Manufacturing",
            "subcategory":"Tools & Machinery",
            "type":"Manufacturing & Wholesale Goods"
        }
    ],
    "sg:phone":"+1 707 578 3441",
    "sg:postcode":"95404",
    "sg:province":"CA",
    "sg:tags":[
        "electrical",
        "mfg"
    ],
    "wof:name":"Curtis Electric",
    "wof:placetype":"venue"
},
  "geometry": {"coordinates":[-122.712912,38.456436],"type":"Point"}
}