{
  "type": "Feature",
  "properties": {
    "addr:full":"4037 Phelan Rd Ste A101 Phelan CA 92371",
    "addr:housenumber":"4037",
    "addr:postcode":"92371",
    "addr:street":"Phelan Rd Ste A101",
    "iso:country":"US",
    "sg:address":"4037 Phelan Rd Ste A101",
    "sg:city":"Phelan",
    "sg:classifiers":[
        {
            "category":"Home & Garden",
            "subcategory":"Building Materials",
            "type":"Retail Goods"
        }
    ],
    "sg:phone":"+1 760 868 9200",
    "sg:postcode":"92371",
    "sg:province":"CA",
    "sg:tags":[
        "concrete",
        "reinforcement"
    ],
    "sg:website":"http://www.getapup.com",
    "wof:name":"L Bar M Ranch",
    "wof:placetype":"venue"
},
  "geometry": {"coordinates":[-117.57393399999999,34.426316],"type":"Point"}
}