{
  "type": "Feature",
  "properties": {
    "addr:full":"2955 Ryan Rd Concord CA 94518",
    "addr:housenumber":"2955",
    "addr:postcode":"94518",
    "addr:street":"Ryan Rd",
    "iso:country":"US",
    "sg:address":"2955 Ryan Rd",
    "sg:city":"Concord",
    "sg:classifiers":[
        {
            "category":"Real Estate",
            "subcategory":"Real Estate Agent",
            "type":"Services"
        }
    ],
    "sg:phone":"+1 925 969 0946",
    "sg:postcode":"94518",
    "sg:province":"CA",
    "sg:tags":[
        "appraiser"
    ],
    "wof:name":"Diablo Valley Appraisal",
    "wof:placetype":"venue"
},
  "geometry": {"coordinates":[-122.017478,37.948236],"type":"Point"}
}