{
  "type": "Feature",
  "properties": {
    "addr:full":"4721 N Orchard St Fresno CA 93726",
    "addr:housenumber":"4721",
    "addr:postcode":"93726",
    "addr:street":"N Orchard St",
    "iso:country":"US",
    "sg:address":"4721 N Orchard St",
    "sg:city":"Fresno",
    "sg:classifiers":[
        {
            "category":"Insurance",
            "subcategory":"Insurance Agent",
            "type":"Services"
        }
    ],
    "sg:phone":"+1 559 226 1993",
    "sg:postcode":"93726",
    "sg:province":"CA",
    "wof:name":"Stanley I Ryan",
    "wof:placetype":"venue"
},
  "geometry": {"coordinates":[-119.77509999999999,36.803858],"type":"Point"}
}