{
  "type": "Feature",
  "properties": {
    "iso:country":"US",
    "sg:address":"1535 Landess",
    "sg:city":"Milpitas",
    "sg:classifiers":[
        {
            "category":"Bakery",
            "type":"Food & Drink"
        }
    ],
    "sg:phone":"+1 408 935 8881",
    "sg:postcode":"95035",
    "sg:province":"CA",
    "sg:website":"www.goldilocks-usa.com",
    "wof:name":"Goldilocks",
    "wof:placetype":"venue"
},
  "geometry": {"coordinates":[-121.877076,37.416693],"type":"Point"}
}