{
  "type": "Feature",
  "properties": {
    "iso:country":"US",
    "sg:address":"928 Hidden Cove Way",
    "sg:city":"Suisun City",
    "sg:classifiers":[
        {
            "category":"Recreation",
            "type":"Entertainment"
        }
    ],
    "sg:phone":"+1 707 486 8378",
    "sg:postcode":"94585",
    "sg:province":"CA",
    "sg:tags":[
        "concessionaire"
    ],
    "wof:name":"Food Concession Unlimited",
    "wof:placetype":"venue"
},
  "geometry": {"coordinates":[-122.005273,38.251023],"type":"Point"}
}