{
  "type": "Feature",
  "properties": {
    "iso:country":"US",
    "sg:address":"24225 Main St",
    "sg:city":"Newhall",
    "sg:classifiers":[
        {
            "category":"Professional",
            "subcategory":"Employment Agencies",
            "type":"Services"
        }
    ],
    "sg:phone":"+1 661 260 3650",
    "sg:postcode":"91321",
    "sg:province":"CA",
    "sg:website":"www.laborready.com",
    "wof:name":"Labor Ready",
    "wof:placetype":"venue"
},
  "geometry": {"coordinates":[-118.52691299999999,34.377187],"type":"Point"}
}