{
  "type": "Feature",
  "properties": {
    "iso:country":"US",
    "sg:address":"1240 Pear Ave. Unit Q",
    "sg:city":"Mountain View",
    "sg:classifiers":[
        {
            "category":"Autos & Motor Vehicles",
            "subcategory":"Automobile Sales",
            "type":"Retail Goods"
        },
        {
            "category":"Professional",
            "type":"Services"
        }
    ],
    "sg:phone":"+1 408 830 9595",
    "sg:postcode":"94043",
    "sg:province":"CA",
    "sg:tags":[
        "automotive"
    ],
    "sg:website":"www.collisionconsulting.com",
    "wof:name":"Collision Consulting of Northern California",
    "wof:placetype":"venue"
},
  "geometry": {"coordinates":[-122.07450300000001,37.41632],"type":"Point"}
}