{
  "type": "Feature",
  "properties": {
    "iso:country":"US",
    "sg:address":"3551 Front St",
    "sg:city":"San Diego",
    "sg:classifiers":[
        {
            "category":"Social Services",
            "type":"Services"
        }
    ],
    "sg:phone":"+1 619 543 1222",
    "sg:postcode":"92103",
    "sg:province":"CA",
    "sg:tags":[
        "worker"
    ],
    "wof:name":"Dory Beatrice",
    "wof:placetype":"venue"
},
  "geometry": {"coordinates":[-117.164867,32.742355],"type":"Point"}
}