{
  "type": "Feature",
  "properties": {
    "addr:full":"17937 MacArthur Boulevard Irvine CA 92614",
    "addr:housenumber":"17937",
    "addr:postcode":"92614",
    "addr:street":"Macarthur Boulevard",
    "iso:country":"US",
    "sg:address":"17937 MacArthur Boulevard",
    "sg:city":"Irvine",
    "sg:classifiers":[
        {
            "category":"Food & Beverages",
            "subcategory":"Groceries & Convenience Stores",
            "type":"Retail Goods"
        }
    ],
    "sg:phone":"+1 949 955 9230",
    "sg:postcode":"92614",
    "sg:province":"CA",
    "wof:name":"McArthur Sq Market",
    "wof:placetype":"venue"
},
  "geometry": {"coordinates":[-117.855023,33.686113],"type":"Point"}
}