{
  "type": "Feature",
  "properties": {
    "addr:full":"17028 Ventura Blvd Encino CA 91316",
    "addr:housenumber":"17028",
    "addr:postcode":"91316",
    "addr:street":"Ventura Blvd",
    "iso:country":"US",
    "sg:address":"17028 Ventura Blvd",
    "sg:city":"Encino",
    "sg:classifiers":[
        {
            "category":"Shopping",
            "subcategory":"Clothing, Apparel, & Fashions",
            "type":"Retail Goods"
        }
    ],
    "sg:phone":"+1 818 784 1609",
    "sg:postcode":"91316",
    "sg:province":"CA",
    "wof:name":"Covys Encino",
    "wof:placetype":"venue"
},
  "geometry": {"coordinates":[-118.503621,34.159732],"type":"Point"}
}