{
  "type": "Feature",
  "properties": {
    "iso:country":"US",
    "sg:address":"4550 Norris Canyon Rd",
    "sg:city":"San Ramon",
    "sg:classifiers":[
        {
            "category":"Professional",
            "type":"Services"
        }
    ],
    "sg:phone":"+1 925 785 7737",
    "sg:postcode":"94583",
    "sg:province":"CA",
    "wof:name":"Leica Geosystems LLC",
    "wof:placetype":"venue"
},
  "geometry": {"coordinates":[-121.967707,37.773432],"type":"Point"}
}