{
  "type": "Feature",
  "properties": {
    "iso:country":"US",
    "sg:address":"1800 Adobe St",
    "sg:city":"Concord",
    "sg:classifiers":[
        {
            "category":"Health Services",
            "subcategory":"Clinic",
            "type":"Services"
        }
    ],
    "sg:phone":"+1 925 405 0106",
    "sg:postcode":"94520",
    "sg:province":"CA",
    "wof:name":"Ocadian Care Ctr",
    "wof:placetype":"venue"
},
  "geometry": {"coordinates":[-122.03815400000001,37.976988],"type":"Point"}
}