{
  "type": "Feature",
  "properties": {
    "addr:full":"2115 S Tremont St Oceanside CA 92054",
    "addr:housenumber":"2115",
    "addr:postcode":"92054",
    "addr:street":"S Tremont St",
    "iso:country":"US",
    "sg:address":"2115 S Tremont St",
    "sg:city":"Oceanside",
    "sg:classifiers":[
        {
            "category":"Communications",
            "type":"Services"
        }
    ],
    "sg:phone":"+1 760 421 2500",
    "sg:postcode":"92054",
    "sg:province":"CA",
    "sg:tags":[
        "communication"
    ],
    "wof:name":"Keystone Communication",
    "wof:placetype":"venue"
},
  "geometry": {"coordinates":[-117.358806,33.169796],"type":"Point"}
}