{
  "type": "Feature",
  "properties": {
    "addr:full":"915 Black Diamond Way Lodi CA 95240",
    "addr:housenumber":"915",
    "addr:postcode":"95240",
    "addr:street":"Black Diamond Way",
    "iso:country":"US",
    "sg:address":"915 Black Diamond Way",
    "sg:city":"Lodi",
    "sg:classifiers":[
        {
            "category":"Recreation",
            "type":"Entertainment"
        }
    ],
    "sg:phone":"+1 209 369 2436",
    "sg:postcode":"95240",
    "sg:province":"CA",
    "sg:tags":[
        "instruction",
        "gymnastic"
    ],
    "wof:name":"Gymweavers Gymnastic Ctr",
    "wof:placetype":"venue"
},
  "geometry": {"coordinates":[-121.253953,38.140206],"type":"Point"}
}