{
  "type": "Feature",
  "properties": {
    "addr:full":"13605 Fairview St Garden Grove CA 92843",
    "addr:housenumber":"13605",
    "addr:postcode":"92843",
    "addr:street":"Fairview St",
    "iso:country":"US",
    "sg:address":"13605 Fairview St",
    "sg:city":"Garden Grove",
    "sg:classifiers":[
        {
            "category":"Building & Trades",
            "subcategory":"Landscaping Services",
            "type":"Services"
        }
    ],
    "sg:phone":"+1 714 750 4511",
    "sg:postcode":"92843",
    "sg:province":"CA",
    "sg:tags":[
        "landscape"
    ],
    "wof:name":"K Motodera Landscape",
    "wof:placetype":"venue"
},
  "geometry": {"coordinates":[-117.903002,33.765938],"type":"Point"}
}