{
  "type": "Feature",
  "properties": {
    "iso:country":"US",
    "sg:address":"336 International Blvd",
    "sg:city":"Oakland",
    "sg:classifiers":[
        {
            "category":"Real Estate",
            "subcategory":"Real Estate Services",
            "type":"Services"
        }
    ],
    "sg:phone":"+1 510 663 7900",
    "sg:postcode":"94606",
    "sg:province":"CA",
    "sg:tags":[
        "consultant"
    ],
    "wof:name":"Adamson Jack-Farmers Insurance",
    "wof:placetype":"venue"
},
  "geometry": {"coordinates":[-122.255117,37.796892],"type":"Point"}
}