{
  "type": "Feature",
  "properties": {
    "iso:country":"US",
    "sg:address":"3640 N el Dorado St",
    "sg:city":"Stockton",
    "sg:classifiers":[
        {
            "category":"Health Services",
            "subcategory":"Doctor",
            "type":"Services"
        }
    ],
    "sg:phone":"+1 209 942 3559",
    "sg:postcode":"95204",
    "sg:province":"CA",
    "sg:tags":[
        "dentist"
    ],
    "wof:name":"Abraham Corpuz DDS",
    "wof:placetype":"venue"
},
  "geometry": {"coordinates":[-121.300427,37.983038],"type":"Point"}
}