{
  "type": "Feature",
  "properties": {
    "iso:country":"US",
    "sg:address":"14951 Catalina St",
    "sg:city":"San Leandro",
    "sg:classifiers":[
        {
            "category":"Manufacturing",
            "subcategory":"Tools & Machinery",
            "type":"Manufacturing & Wholesale Goods"
        }
    ],
    "sg:phone":"+1 510 352 0123",
    "sg:postcode":"94577",
    "sg:province":"CA",
    "sg:tags":[
        "construction"
    ],
    "sg:website":"www.peets.com",
    "wof:name":"Coast Crane Co",
    "wof:placetype":"venue"
},
  "geometry": {"coordinates":[-122.171571,37.693418],"type":"Point"}
}