{
  "type": "Feature",
  "properties": {
    "iso:country":"US",
    "sg:address":"4958 Holt Blvd",
    "sg:city":"Montclair",
    "sg:classifiers":[
        {
            "category":"Personal",
            "subcategory":"Beauty Salon",
            "type":"Services"
        }
    ],
    "sg:phone":"+1 909 625 0396",
    "sg:postcode":"91763",
    "sg:province":"CA",
    "wof:name":"Sally's Beauty Salon",
    "wof:placetype":"venue"
},
  "geometry": {"coordinates":[-117.690663,34.063319],"type":"Point"}
}