{
  "type": "Feature",
  "properties": {
    "iso:country":"US",
    "sg:address":"35700 Trabuco Dr",
    "sg:city":"Lake Elsinore",
    "sg:classifiers":[
        {
            "category":"Wholesale",
            "subcategory":"Electrical",
            "type":"Manufacturing & Wholesale Goods"
        }
    ],
    "sg:phone":"+1 951 678 1028",
    "sg:postcode":"92530",
    "sg:province":"CA",
    "sg:tags":[
        "control",
        "security",
        "system"
    ],
    "wof:name":"Gateway Security & Comms",
    "wof:placetype":"venue"
},
  "geometry": {"coordinates":[-117.377837,33.6567],"type":"Point"}
}