{
  "type": "Feature",
  "properties": {
    "addr:full":"1901 W Sunset Blvd Los Angeles CA 90026",
    "addr:housenumber":"1901",
    "addr:postcode":"90026",
    "addr:street":"W Sunset Blvd",
    "iso:country":"US",
    "sg:address":"1901 W Sunset Blvd",
    "sg:city":"Los Angeles",
    "sg:classifiers":[
        {
            "category":"Shopping",
            "subcategory":"Florist",
            "type":"Retail Goods"
        }
    ],
    "sg:phone":"+1 213 353 0381",
    "sg:postcode":"90026",
    "sg:province":"CA",
    "wof:name":"Medina's Flowers & Gifts",
    "wof:placetype":"venue"
},
  "geometry": {"coordinates":[-118.26066299999999,34.078086],"type":"Point"}
}