{
  "type": "Feature",
  "properties": {
    "addr:full":"7019 Katherine Ave Van Nuys CA 91405",
    "addr:housenumber":"7019",
    "addr:postcode":"91405",
    "addr:street":"Katherine Ave",
    "iso:country":"US",
    "sg:address":"7019 Katherine Ave",
    "sg:city":"Van Nuys",
    "sg:classifiers":[
        {
            "category":"Retail",
            "subcategory":"Repair Shop",
            "type":"Services"
        }
    ],
    "sg:phone":"+1 818 782 2146",
    "sg:postcode":"91405",
    "sg:province":"CA",
    "sg:tags":[
        "equipment"
    ],
    "wof:name":"Cori's Repair Svc",
    "wof:placetype":"venue"
},
  "geometry": {"coordinates":[-118.44333899999999,34.199016],"type":"Point"}
}