{
  "type": "Feature",
  "properties": {
    "iso:country":"US",
    "sg:address":"236 W East Ave",
    "sg:city":"Chico",
    "sg:classifiers":[
        {
            "category":"Health Services",
            "subcategory":"Doctor",
            "type":"Services"
        }
    ],
    "sg:phone":"+1 530 892 1218",
    "sg:postcode":"95926",
    "sg:province":"CA",
    "sg:tags":[
        "dentist"
    ],
    "wof:name":"Chico Dental Assoc",
    "wof:placetype":"venue"
},
  "geometry": {"coordinates":[-121.863618,39.755291],"type":"Point"}
}