{
  "type": "Feature",
  "properties": {
    "iso:country":"US",
    "sg:address":"2620 Augustine Dr",
    "sg:city":"Santa Clara",
    "sg:classifiers":[
        {
            "category":"Manufacturing",
            "subcategory":"Printing",
            "type":"Manufacturing & Wholesale Goods"
        }
    ],
    "sg:phone":"+1 408 844 8800",
    "sg:postcode":"95054",
    "sg:province":"CA",
    "sg:tags":[
        "publisher",
        "software"
    ],
    "wof:name":"Boniva Software",
    "wof:placetype":"venue"
},
  "geometry": {"coordinates":[-121.973765,37.382256],"type":"Point"}
}