{
  "type": "Feature",
  "properties": {
    "addr:full":"3540 Fashion Ave Long Beach CA 90810",
    "addr:housenumber":"3540",
    "addr:postcode":"90810",
    "addr:street":"Fashion Ave",
    "iso:country":"US",
    "sg:address":"3540 Fashion Ave",
    "sg:city":"Long Beach",
    "sg:classifiers":[
        {
            "category":"Home & Garden",
            "subcategory":"Building Materials",
            "type":"Retail Goods"
        }
    ],
    "sg:phone":"+1 562 235 6791",
    "sg:postcode":"90810",
    "sg:province":"CA",
    "sg:tags":[
        "glass",
        "window",
        "plate"
    ],
    "wof:name":"A-California Installs Glass",
    "wof:placetype":"venue"
},
  "geometry": {"coordinates":[-118.209306,33.821579],"type":"Point"}
}