{
  "type": "Feature",
  "properties": {
    "iso:country":"US",
    "sg:address":"706 Capitola Ave Ste A",
    "sg:city":"Capitola",
    "sg:classifiers":[
        {
            "category":"Restaurant",
            "type":"Food & Drink"
        }
    ],
    "sg:phone":"+1 831 476 5519",
    "sg:postcode":"95010",
    "sg:province":"CA",
    "wof:name":"Cook House the",
    "wof:placetype":"venue"
},
  "geometry": {"coordinates":[-121.953003,36.979099],"type":"Point"}
}