{
  "type": "Feature",
  "properties": {
    "addr:full":"1155 E Main St El Cajon CA 92021",
    "addr:housenumber":"1155",
    "addr:postcode":"92021",
    "addr:street":"E Main St",
    "iso:country":"US",
    "sg:address":"1155 E Main St",
    "sg:city":"El Cajon",
    "sg:classifiers":[
        {
            "category":"Autos & Motor Vehicles",
            "subcategory":"Recreational Vehicle Sales",
            "type":"Retail Goods"
        }
    ],
    "sg:phone":"+1 619 442 7709",
    "sg:postcode":"92021",
    "sg:province":"CA",
    "sg:tags":[
        "camper",
        "pick"
    ],
    "wof:name":"Bill's Trailerland Sales Co",
    "wof:placetype":"venue"
},
  "geometry": {"coordinates":[-116.941608,32.794842],"type":"Point"}
}