{
  "type": "Feature",
  "properties": {
    "iso:country":"US",
    "sg:address":"4750 Quail Lakes Dr",
    "sg:city":"Stockton",
    "sg:classifiers":[
        {
            "category":"Banks & Credit Unions",
            "subcategory":"Investment Brokerage",
            "type":"Services"
        }
    ],
    "sg:phone":"+1 209 474 1602",
    "sg:postcode":"95207",
    "sg:province":"CA",
    "sg:tags":[
        "stock",
        "bond"
    ],
    "wof:name":"Smith & Gatschet Financial Grp",
    "wof:placetype":"venue"
},
  "geometry": {"coordinates":[-121.339877,37.984812],"type":"Point"}
}