{
  "type": "Feature",
  "properties": {
    "addr:full":"6036 Ball Rd. Buena Park CA 90620",
    "addr:housenumber":"6036",
    "addr:postcode":"90620",
    "addr:street":"Ball Rd.",
    "iso:country":"US",
    "sg:address":"6036 Ball Rd.",
    "sg:city":"Buena Park",
    "sg:classifiers":[
        {
            "category":"Personal",
            "subcategory":"Nail Salon",
            "type":"Services"
        }
    ],
    "sg:phone":"+1 714 229 9241",
    "sg:postcode":"90620",
    "sg:province":"CA",
    "wof:name":"American Spa and Nails",
    "wof:placetype":"venue"
},
  "geometry": {"coordinates":[-118.01887000000001,33.817161],"type":"Point"}
}