{
  "type": "Feature",
  "properties": {
    "iso:country":"US",
    "sg:address":"1725 Mariposa Dr",
    "sg:city":"Santa Rosa",
    "sg:classifiers":[
        {
            "category":"Home & Garden",
            "subcategory":"Furniture",
            "type":"Retail Goods"
        }
    ],
    "sg:phone":"+1 707 545 0459",
    "sg:postcode":"95405",
    "sg:province":"CA",
    "wof:name":"Gene Bell Enterprises",
    "wof:placetype":"venue"
},
  "geometry": {"coordinates":[-122.667438,38.437965],"type":"Point"}
}