{
  "type": "Feature",
  "properties": {
    "iso:country":"US",
    "sg:address":"2236 Burnham Rd",
    "sg:city":"Ojai",
    "sg:classifiers":[
        {
            "category":"Insurance",
            "subcategory":"Insurance Agent",
            "type":"Services"
        }
    ],
    "sg:phone":"+1 805 649 3700",
    "sg:postcode":"93023",
    "sg:province":"CA",
    "wof:name":"Mercury Insurance Group",
    "wof:placetype":"venue"
},
  "geometry": {"coordinates":[-119.304986,34.422713],"type":"Point"}
}