{
  "type": "Feature",
  "properties": {
    "iso:country":"US",
    "sg:address":"4320 Elverta Rd",
    "sg:city":"Antelope",
    "sg:classifiers":[
        {
            "category":"Personal",
            "subcategory":"Beauty Salon",
            "type":"Services"
        }
    ],
    "sg:phone":"+1 916 721 9497",
    "sg:postcode":"95843",
    "sg:province":"CA",
    "wof:name":"Great Clips",
    "wof:placetype":"venue"
},
  "geometry": {"coordinates":[-121.36052,38.712714],"type":"Point"}
}