{
  "type": "Feature",
  "properties": {
    "iso:country":"US",
    "sg:address":"2 Dinkelspiel Station Ln",
    "sg:city":"Atherton",
    "sg:classifiers":[
        {
            "category":"Education",
            "subcategory":"Library",
            "type":"Public Place"
        }
    ],
    "sg:phone":"+1 650 328 2422",
    "sg:postcode":"94027",
    "sg:province":"CA",
    "wof:name":"Atherton Library",
    "wof:placetype":"venue"
},
  "geometry": {"coordinates":[-122.197231,37.463736],"type":"Point"}
}