{
  "type": "Feature",
  "properties": {
    "addr:full":"300 Corporate Pointe Walk Culver City CA 90230",
    "addr:housenumber":"300",
    "addr:postcode":"90230",
    "addr:street":"Corporate Pointe Walk",
    "iso:country":"US",
    "sg:address":"300 Corporate Pointe Walk",
    "sg:city":"Culver City",
    "sg:classifiers":[
        {
            "category":"Real Estate",
            "subcategory":"Real Estate Agent",
            "type":"Services"
        }
    ],
    "sg:phone":"+1 310 645 7038",
    "sg:postcode":"90230",
    "sg:province":"CA",
    "sg:tags":[
        "management"
    ],
    "wof:name":"Birtcher Property Svc",
    "wof:placetype":"venue"
},
  "geometry": {"coordinates":[-118.38548,33.988059],"type":"Point"}
}