{
  "type": "Feature",
  "properties": {
    "addr:full":"620 S Andreasen Dr Escondido CA 92029",
    "addr:housenumber":"620",
    "addr:postcode":"92029",
    "addr:street":"S Andreasen Dr",
    "iso:country":"US",
    "sg:address":"620 S Andreasen Dr",
    "sg:city":"Escondido",
    "sg:classifiers":[
        {
            "category":"Organizations",
            "subcategory":"Religious Organization",
            "type":"Services"
        }
    ],
    "sg:phone":"+1 760 480 6233",
    "sg:postcode":"92029",
    "sg:province":"CA",
    "sg:tags":[
        "church"
    ],
    "sg:website":"www.lifechristianchurch.com",
    "wof:name":"Life Christian Church",
    "wof:placetype":"venue"
},
  "geometry": {"coordinates":[-117.11386,33.115279],"type":"Point"}
}