{
  "type": "Feature",
  "properties": {
    "iso:country":"US",
    "sg:address":"1500 W El Monte Way",
    "sg:city":"Dinuba",
    "sg:classifiers":[
        {
            "category":"Autos & Motor Vehicles",
            "subcategory":"Automobile Sales",
            "type":"Retail Goods"
        }
    ],
    "sg:phone":"+1 866 330 0420",
    "sg:postcode":"93618",
    "sg:province":"CA",
    "sg:tags":[
        "new",
        "used",
        "car"
    ],
    "sg:website":"http://local.ingenio.com/Listings/Details.aspx?NUM=a%3a10119542%3a13%3a4859924%3a14%3a0%3a7",
    "wof:name":"Ed Dena's Auto Center",
    "wof:placetype":"venue"
},
  "geometry": {"coordinates":[-119.410622,36.546082],"type":"Point"}
}