{
  "type": "Feature",
  "properties": {
    "addr:full":"3460 Ocean View Blvd Ste D Glendale CA 91208",
    "addr:housenumber":"3460",
    "addr:postcode":"91208",
    "addr:street":"Ocean View Blvd Ste D",
    "iso:country":"US",
    "sg:address":"3460 Ocean View Blvd Ste D",
    "sg:city":"Glendale",
    "sg:classifiers":[
        {
            "category":"Sports & Exercise",
            "subcategory":"Gym",
            "type":"Entertainment"
        }
    ],
    "sg:phone":"+1 818 957 7356",
    "sg:postcode":"91208",
    "sg:province":"CA",
    "sg:tags":[
        "trainer"
    ],
    "wof:name":"Barefoot Body Works Pilates",
    "wof:placetype":"venue"
},
  "geometry": {"coordinates":[-118.227997,34.201401],"type":"Point"}
}