{
  "type": "Feature",
  "properties": {
    "addr:full":"410 12th St Sacramento CA 95814",
    "addr:housenumber":"410",
    "addr:postcode":"95814",
    "addr:street":"12Th St",
    "iso:country":"US",
    "sg:address":"410 12th St",
    "sg:city":"Sacramento",
    "sg:classifiers":[
        {
            "category":"Professional",
            "subcategory":"Lawyer & Legal Services",
            "type":"Services"
        }
    ],
    "sg:phone":"+1 916 442 4921",
    "sg:postcode":"95814",
    "sg:province":"CA",
    "sg:tags":[
        "attorney"
    ],
    "wof:name":"David Negri",
    "wof:placetype":"venue"
},
  "geometry": {"coordinates":[-121.48821599999999,38.585756],"type":"Point"}
}