{
  "type": "Feature",
  "properties": {
    "iso:country":"US",
    "sg:address":"2530 N Miami Ave",
    "sg:city":"Fresno",
    "sg:classifiers":[
        {
            "category":"Manufacturing",
            "subcategory":"Chemicals & Compounds",
            "type":"Manufacturing & Wholesale Goods"
        }
    ],
    "sg:phone":"+1 559 347 6990",
    "sg:postcode":"93727",
    "sg:province":"CA",
    "sg:tags":[
        "mfg",
        "soil",
        "supplement",
        "biological"
    ],
    "wof:name":"B I O",
    "wof:placetype":"venue"
},
  "geometry": {"coordinates":[-119.68986200000001,36.773485],"type":"Point"}
}