{
  "type": "Feature",
  "properties": {
    "addr:full":"4035 Adolfo Rd Ste D Camarillo CA 93012",
    "addr:housenumber":"4035",
    "addr:postcode":"93012",
    "addr:street":"Adolfo Rd Ste D",
    "iso:country":"US",
    "sg:address":"4035 Adolfo Rd Ste D",
    "sg:city":"Camarillo",
    "sg:classifiers":[
        {
            "category":"Restaurant",
            "type":"Food & Drink"
        }
    ],
    "sg:phone":"+1 805 484 7827",
    "sg:postcode":"93012",
    "sg:province":"CA",
    "wof:name":"Blimpie Subs & Salads",
    "wof:placetype":"venue"
},
  "geometry": {"coordinates":[-119.001999,34.2169],"type":"Point"}
}