{
  "type": "Feature",
  "properties": {
    "iso:country":"US",
    "sg:address":"1120 Granville Ave",
    "sg:city":"Los Angeles",
    "sg:classifiers":[
        {
            "category":"Professional",
            "subcategory":"Management & Consulting",
            "type":"Services"
        }
    ],
    "sg:phone":"+1 310 826 5858",
    "sg:postcode":"90049",
    "sg:province":"CA",
    "sg:tags":[
        "field"
    ],
    "wof:name":"M M Witte",
    "wof:placetype":"venue"
},
  "geometry": {"coordinates":[-118.463504,34.049387],"type":"Point"}
}