{
  "type": "Feature",
  "properties": {
    "addr:full":"5494 Gala Ave San Diego CA 92120",
    "addr:housenumber":"5494",
    "addr:postcode":"92120",
    "addr:street":"Gala Ave",
    "iso:country":"US",
    "sg:address":"5494 Gala Ave",
    "sg:city":"San Diego",
    "sg:classifiers":[
        {
            "category":"Building & Trades",
            "subcategory":"Plumbing",
            "type":"Services"
        }
    ],
    "sg:phone":"+1 619 449 6212",
    "sg:postcode":"92120",
    "sg:province":"CA",
    "sg:tags":[
        "conditioning",
        "air",
        "system",
        "contractor"
    ],
    "wof:name":"Mauzy Heating & AC",
    "wof:placetype":"venue"
},
  "geometry": {"coordinates":[-117.070975,32.800774],"type":"Point"}
}