{
  "type": "Feature",
  "properties": {
    "iso:country":"US",
    "sg:address":"1516 Cravens Ave",
    "sg:city":"Torrance",
    "sg:classifiers":[
        {
            "category":"Manufacturing",
            "subcategory":"Signs",
            "type":"Manufacturing & Wholesale Goods"
        }
    ],
    "sg:phone":"+1 310 328 2838",
    "sg:postcode":"90501",
    "sg:province":"CA",
    "wof:name":"Nickelneon",
    "wof:placetype":"venue"
},
  "geometry": {"coordinates":[-118.316353,33.833359],"type":"Point"}
}