{
  "type": "Feature",
  "properties": {
    "addr:full":"4680 Tarantella Ln San Diego CA 92130",
    "addr:housenumber":"4680",
    "addr:postcode":"92130",
    "addr:street":"Tarantella Ln",
    "iso:country":"US",
    "sg:address":"4680 Tarantella Ln",
    "sg:city":"San Diego",
    "sg:classifiers":[
        {
            "category":"Shopping",
            "type":"Retail Goods"
        }
    ],
    "sg:phone":"+1 858 259 8870",
    "sg:postcode":"92130",
    "sg:province":"CA",
    "sg:tags":[
        "merchandise"
    ],
    "wof:name":"Healthy Chats",
    "wof:placetype":"venue"
},
  "geometry": {"coordinates":[-117.216618,32.946756],"type":"Point"}
}