{
  "type": "Feature",
  "properties": {
    "iso:country":"US",
    "sg:address":"3430 Brickway Blvd",
    "sg:city":"Santa Rosa",
    "sg:classifiers":[
        {
            "category":"Manufacturing",
            "subcategory":"Wood Products",
            "type":"Manufacturing & Wholesale Goods"
        }
    ],
    "sg:phone":"+1 707 523 1900",
    "sg:postcode":"95403",
    "sg:province":"CA",
    "sg:tags":[
        "pallet",
        "skid"
    ],
    "wof:name":"Chick Packaging Of Santa Rosa",
    "wof:placetype":"venue"
},
  "geometry": {"coordinates":[-122.792902,38.509099],"type":"Point"}
}