{
  "type": "Feature",
  "properties": {
    "iso:country":"US",
    "sg:address":"10661 Chestnut Ave",
    "sg:city":"Stanton",
    "sg:classifiers":[
        {
            "category":"Manufacturing",
            "subcategory":"Metals",
            "type":"Manufacturing & Wholesale Goods"
        }
    ],
    "sg:phone":"+1 714 226 3051",
    "sg:postcode":"90680",
    "sg:province":"CA",
    "sg:tags":[
        "product",
        "wire",
        "fabricated",
        "mfg"
    ],
    "wof:name":"South Coast Fabrication",
    "wof:placetype":"venue"
},
  "geometry": {"coordinates":[-117.992249,33.808026],"type":"Point"}
}