{
  "type": "Feature",
  "properties": {
    "iso:country":"US",
    "sg:address":"910 Lincoln Way",
    "sg:city":"Auburn",
    "sg:classifiers":[
        {
            "category":"Professional",
            "subcategory":"Advertising",
            "type":"Services"
        }
    ],
    "sg:phone":"+1 530 888 1115",
    "sg:postcode":"95603",
    "sg:province":"CA",
    "sg:tags":[
        "medium",
        "interactive"
    ],
    "wof:name":"Guestline USA",
    "wof:placetype":"venue"
},
  "geometry": {"coordinates":[-121.069394,38.899846],"type":"Point"}
}