{
  "type": "Feature",
  "properties": {
    "iso:country":"US",
    "sg:address":"2355 Paragon Dr",
    "sg:city":"San Jose",
    "sg:classifiers":[
        {
            "category":"Building & Trades",
            "subcategory":"Construction",
            "type":"Services"
        }
    ],
    "sg:phone":"+1 408 392 9973",
    "sg:postcode":"95131",
    "sg:province":"CA",
    "sg:tags":[
        "contractor"
    ],
    "wof:name":"THD Contract Mfg",
    "wof:placetype":"venue"
},
  "geometry": {"coordinates":[-121.90860600000001,37.387157],"type":"Point"}
}