{
  "type": "Feature",
  "properties": {
    "iso:country":"US",
    "sg:address":"1955 Altura Dr",
    "sg:city":"Concord",
    "sg:classifiers":[
        {
            "category":"Building & Trades",
            "subcategory":"Construction",
            "type":"Services"
        }
    ],
    "sg:phone":"+1 925 429 3814",
    "sg:postcode":"94519",
    "sg:province":"CA",
    "sg:tags":[
        "contractor"
    ],
    "wof:name":"Construction Altura",
    "wof:placetype":"venue"
},
  "geometry": {"coordinates":[-122.020255,37.982585],"type":"Point"}
}