{
  "type": "Feature",
  "properties": {
    "iso:country":"US",
    "sg:address":"509 E 4th St",
    "sg:city":"Santa Ana",
    "sg:classifiers":[
        {
            "category":"Building & Trades",
            "subcategory":"Construction",
            "type":"Services"
        }
    ],
    "sg:phone":"+1 714 537 0561",
    "sg:postcode":"92701",
    "sg:province":"CA",
    "sg:tags":[
        "contractor"
    ],
    "wof:name":"V-H Electrical General Mntnc",
    "wof:placetype":"venue"
},
  "geometry": {"coordinates":[-117.862579,33.748085],"type":"Point"}
}