{
  "type": "Feature",
  "properties": {
    "addr:full":"4320 Elverta Rd Antelope CA 95843",
    "addr:housenumber":"4320",
    "addr:postcode":"95843",
    "addr:street":"Elverta Rd",
    "iso:country":"US",
    "sg:address":"4320 Elverta Rd",
    "sg:city":"Antelope",
    "sg:classifiers":[
        {
            "category":"Restaurant",
            "type":"Food & Drink"
        }
    ],
    "sg:phone":"+1 916 723 5250",
    "sg:postcode":"95843",
    "sg:province":"CA",
    "wof:name":"Subway Sandwiches & Salads",
    "wof:placetype":"venue"
},
  "geometry": {"coordinates":[-121.36051999999999,38.712714],"type":"Point"}
}