{
  "type": "Feature",
  "properties": {
    "iso:country":"US",
    "sg:address":"1840 Quivira Way",
    "sg:city":"San Diego",
    "sg:classifiers":[
        {
            "category":"Autos & Motor Vehicles",
            "subcategory":"Boat Sales",
            "type":"Retail Goods"
        }
    ],
    "sg:phone":"+1 619 226 6258",
    "sg:postcode":"92109",
    "sg:province":"CA",
    "sg:tags":[
        "yacht"
    ],
    "wof:name":"Argo Yacht",
    "wof:placetype":"venue"
},
  "geometry": {"coordinates":[-117.237274,32.758964],"type":"Point"}
}