{
  "type": "Feature",
  "properties": {
    "iso:country":"US",
    "sg:address":"1377 S Dora St",
    "sg:city":"Ukiah",
    "sg:classifiers":[
        {
            "category":"Health Services",
            "subcategory":"Doctor",
            "type":"Services"
        }
    ],
    "sg:phone":"+1 707 462 3875",
    "sg:postcode":"95482",
    "sg:province":"CA",
    "sg:tags":[
        "dentist"
    ],
    "wof:name":"Saucedo-Ortega Family Dntstry",
    "wof:placetype":"venue"
},
  "geometry": {"coordinates":[-123.208663,39.12963],"type":"Point"}
}