{
  "type": "Feature",
  "properties": {
    "iso:country":"US",
    "sg:address":"1340 Irving St",
    "sg:city":"San Francisco",
    "sg:classifiers":[
        {
            "category":"Coffee & Tea",
            "type":"Food & Drink"
        },
        {
            "category":"Bars & Pubs",
            "subcategory":"Hookah Bar",
            "type":"Food & Drink"
        }
    ],
    "sg:phone":"+1 415 681 1910",
    "sg:postcode":"94122",
    "sg:province":"CA",
    "sg:website":"www.oldjerusalemcafe.com",
    "wof:name":"Old Jerusalem Cafe",
    "wof:placetype":"venue"
},
  "geometry": {"coordinates":[-122.472364,37.76387],"type":"Point"}
}