{
  "type": "Feature",
  "properties": {
    "addr:full":"28062 Thompson Mission Viejo CA 92692",
    "addr:housenumber":"28062",
    "addr:postcode":"92692",
    "addr:street":"Thompson",
    "iso:country":"US",
    "sg:address":"28062 Thompson",
    "sg:city":"Mission Viejo",
    "sg:classifiers":[
        {
            "category":"Professional",
            "subcategory":"Business Services",
            "type":"Services"
        }
    ],
    "sg:phone":"+1 949 412 5538",
    "sg:postcode":"92692",
    "sg:province":"CA",
    "sg:tags":[
        "pool",
        "swimming"
    ],
    "wof:name":"At Pool & Spa Filter Cleaning",
    "wof:placetype":"venue"
},
  "geometry": {"coordinates":[-117.64094799999999,33.649809],"type":"Point"}
}