{
  "type": "Feature",
  "properties": {
    "iso:country":"US",
    "sg:address":"19959 Almaden Rd",
    "sg:city":"San Jose",
    "sg:classifiers":[
        {
            "category":"Real Estate",
            "subcategory":"Real Estate Agent",
            "type":"Services"
        }
    ],
    "sg:phone":"+1 408 268 5497",
    "sg:postcode":"95120",
    "sg:province":"CA",
    "wof:name":"Oakmont Terrace",
    "wof:placetype":"venue"
},
  "geometry": {"coordinates":[-121.826702,37.193997],"type":"Point"}
}