{
  "type": "Feature",
  "properties": {
    "addr:full":"4101 Birch St Newport Beach CA 92660",
    "addr:housenumber":"4101",
    "addr:postcode":"92660",
    "addr:street":"Birch St",
    "iso:country":"US",
    "sg:address":"4101 Birch St",
    "sg:city":"Newport Beach",
    "sg:classifiers":[
        {
            "category":"Banks & Credit Unions",
            "subcategory":"Bank",
            "type":"Services"
        }
    ],
    "sg:phone":"+1 949 724 9557",
    "sg:postcode":"92660",
    "sg:province":"CA",
    "sg:tags":[
        "loan"
    ],
    "wof:name":"Calstar Lending",
    "wof:placetype":"venue"
},
  "geometry": {"coordinates":[-117.87008,33.66428],"type":"Point"}
}