{
  "type": "Feature",
  "properties": {
    "iso:country":"US",
    "sg:address":"155 E Liberty Ave",
    "sg:city":"Anaheim",
    "sg:classifiers":[
        {
            "category":"Manufacturing",
            "subcategory":"Printing",
            "type":"Manufacturing & Wholesale Goods"
        }
    ],
    "sg:phone":"+1 714 441 0023",
    "sg:postcode":"92801",
    "sg:province":"CA",
    "sg:tags":[
        "commercial"
    ],
    "wof:name":"McKillip Industries",
    "wof:placetype":"venue"
},
  "geometry": {"coordinates":[-117.919577,33.86106],"type":"Point"}
}