{
  "type": "Feature",
  "properties": {
    "iso:country":"US",
    "sg:address":"1443 W Sample Ave",
    "sg:city":"Fresno",
    "sg:classifiers":[
        {
            "category":"Farming",
            "subcategory":"Farm",
            "type":"Manufacturing & Wholesale Goods"
        }
    ],
    "sg:phone":"+1 559 431 0902",
    "sg:postcode":"93711",
    "sg:province":"CA",
    "sg:tags":[
        "crop",
        "general"
    ],
    "sg:website":"www.burfordranch.com",
    "wof:name":"Burford Ranch",
    "wof:placetype":"venue"
},
  "geometry": {"coordinates":[-119.818686,36.827255],"type":"Point"}
}