{
  "type": "Feature",
  "properties": {
    "addr:full":"2991 Auto Center Cir Stockton CA 95212",
    "addr:housenumber":"2991",
    "addr:postcode":"95212",
    "addr:street":"Auto Center Cir",
    "iso:country":"US",
    "sg:address":"2991 Auto Center Cir",
    "sg:city":"Stockton",
    "sg:classifiers":[
        {
            "category":"Autos & Motor Vehicles",
            "subcategory":"Automobile Sales",
            "type":"Retail Goods"
        }
    ],
    "sg:phone":"+1 209 956 9505",
    "sg:postcode":"95212",
    "sg:province":"CA",
    "sg:tags":[
        "car",
        "dealer"
    ],
    "wof:name":"Saturn",
    "wof:placetype":"venue"
},
  "geometry": {"coordinates":[-121.277187,38.018096],"type":"Point"}
}