{
  "type": "Feature",
  "properties": {
    "iso:country":"US",
    "sg:address":"3310 E Chapman Ave",
    "sg:city":"Orange",
    "sg:classifiers":[
        {
            "category":"Personal",
            "subcategory":"Beauty Salon",
            "type":"Services"
        }
    ],
    "sg:phone":"+1 714 628 9906",
    "sg:postcode":"92869",
    "sg:province":"CA",
    "sg:tags":[
        "hair"
    ],
    "sg:website":"www.californiakidshairstyling.com/",
    "wof:name":"California Kids Hairstyling",
    "wof:placetype":"venue"
},
  "geometry": {"coordinates":[-117.818001,33.787701],"type":"Point"}
}