{
  "type": "Feature",
  "properties": {
    "addr:full":"13011 Century Blvd Garden Grove CA 92843",
    "addr:housenumber":"13011",
    "addr:postcode":"92843",
    "addr:street":"Century Blvd",
    "iso:country":"US",
    "sg:address":"13011 Century Blvd",
    "sg:city":"Garden Grove",
    "sg:classifiers":[
        {
            "category":"Health Services",
            "subcategory":"Dentist",
            "type":"Services"
        }
    ],
    "sg:phone":"+1 714 534 7020",
    "sg:postcode":"92843",
    "sg:province":"CA",
    "sg:website":"centurygrovedentalcare.com",
    "wof:name":"Century Grove Dental Care",
    "wof:placetype":"venue"
},
  "geometry": {"coordinates":[-117.945427,33.773742],"type":"Point"}
}