{
  "type": "Feature",
  "properties": {
    "addr:full":"16400 Sierra Hwy Mojave CA 93501",
    "addr:housenumber":"16400",
    "addr:postcode":"93501",
    "addr:street":"Sierra Hwy",
    "iso:country":"US",
    "sg:address":"16400 Sierra Hwy",
    "sg:city":"Mojave",
    "sg:classifiers":[
        {
            "category":"Autos & Motor Vehicles",
            "subcategory":"Automobile Sales",
            "type":"Retail Goods"
        }
    ],
    "sg:phone":"+1 661 824 2477",
    "sg:postcode":"93501",
    "sg:province":"CA",
    "sg:tags":[
        "car",
        "dealer"
    ],
    "sg:website":"www.kieffeandsons.com",
    "wof:name":"Kieffe & Sons Ford",
    "wof:placetype":"venue"
},
  "geometry": {"coordinates":[-118.17600899999999,35.059458],"type":"Point"}
}