{
  "type": "Feature",
  "properties": {
    "addr:full":"7700 Orangethorpe Ave Buena Park CA 90621",
    "addr:housenumber":"7700",
    "addr:postcode":"90621",
    "addr:street":"Orangethorpe Ave",
    "iso:country":"US",
    "sg:address":"7700 Orangethorpe Ave",
    "sg:city":"Buena Park",
    "sg:classifiers":[
        {
            "category":"Insurance",
            "subcategory":"Insurance Agent",
            "type":"Services"
        }
    ],
    "sg:phone":"+1 714 521 9900",
    "sg:postcode":"90621",
    "sg:province":"CA",
    "wof:name":"Farmers Insurance",
    "wof:placetype":"venue"
},
  "geometry": {"coordinates":[-117.99906,33.858822],"type":"Point"}
}