{
  "type": "Feature",
  "properties": {
    "iso:country":"US",
    "sg:address":"18843 Tulsa St",
    "sg:city":"Northridge",
    "sg:classifiers":[
        {
            "category":"Wholesale",
            "subcategory":"Electrical",
            "type":"Manufacturing & Wholesale Goods"
        }
    ],
    "sg:phone":"+1 818 368 1871",
    "sg:postcode":"91326",
    "sg:province":"CA",
    "sg:tags":[
        "electronic"
    ],
    "wof:name":"Fujii International Inc",
    "wof:placetype":"venue"
},
  "geometry": {"coordinates":[-118.543346,34.267905],"type":"Point"}
}