{
  "type": "Feature",
  "properties": {
    "addr:full":"33868 Mission Trl Wildomar CA 92595",
    "addr:housenumber":"33868",
    "addr:postcode":"92595",
    "addr:street":"Mission Trl",
    "iso:country":"US",
    "sg:address":"33868 Mission Trl",
    "sg:city":"Wildomar",
    "sg:classifiers":[
        {
            "category":"Retail",
            "subcategory":"Storage",
            "type":"Services"
        }
    ],
    "sg:phone":"+1 951 245 1855",
    "sg:postcode":"92595",
    "sg:province":"CA",
    "sg:tags":[
        "self"
    ],
    "wof:name":"Southwest Shelter Corp",
    "wof:placetype":"venue"
},
  "geometry": {"coordinates":[-117.290001,33.6287],"type":"Point"}
}