{
  "type": "Feature",
  "properties": {
    "iso:country":"US",
    "sg:address":"41945 Boardwalk",
    "sg:city":"Palm Desert",
    "sg:classifiers":[
        {
            "category":"Professional",
            "subcategory":"Engineering",
            "type":"Services"
        }
    ],
    "sg:phone":"+1 760 346 3250",
    "sg:postcode":"92211",
    "sg:province":"CA",
    "sg:tags":[
        "engineer"
    ],
    "wof:name":"NRO Engineering",
    "wof:placetype":"venue"
},
  "geometry": {"coordinates":[-116.355102,33.744621],"type":"Point"}
}