{
  "type": "Feature",
  "properties": {
    "iso:country":"US",
    "sg:address":"123 E Acacia Ave",
    "sg:city":"Glendale",
    "sg:classifiers":[
        {
            "category":"Professional",
            "type":"Services"
        }
    ],
    "sg:phone":"+1 818 545 9672",
    "sg:postcode":"91205",
    "sg:province":"CA",
    "wof:name":"Reyes Brothers Custom Pai",
    "wof:placetype":"venue"
},
  "geometry": {"coordinates":[-118.251922,34.134845],"type":"Point"}
}