{
  "type": "Feature",
  "properties": {
    "addr:full":"2721 E Spring St Long Beach CA 90806",
    "addr:housenumber":"2721",
    "addr:postcode":"90806",
    "addr:street":"E Spring St",
    "iso:country":"US",
    "sg:address":"2721 E Spring St",
    "sg:city":"Long Beach",
    "sg:classifiers":[
        {
            "category":"Wholesale",
            "subcategory":"Machinery & Supplies",
            "type":"Manufacturing & Wholesale Goods"
        }
    ],
    "sg:phone":"+1 562 424 2211",
    "sg:postcode":"90806",
    "sg:province":"CA",
    "sg:tags":[
        "aircraft",
        "broker"
    ],
    "wof:name":"Atisjets Acquisitions & Tax",
    "wof:placetype":"venue"
},
  "geometry": {"coordinates":[-118.15997,33.811736],"type":"Point"}
}