{
  "type": "Feature",
  "properties": {
    "iso:country":"US",
    "sg:address":"3317 State Rte 132",
    "sg:city":"La Grange",
    "sg:classifiers":[
        {
            "category":"Real Estate",
            "subcategory":"Real Estate Agent",
            "type":"Services"
        }
    ],
    "sg:phone":"+1 209 852 2027",
    "sg:postcode":"95329",
    "sg:province":"CA",
    "wof:name":"Tri County Realty",
    "wof:placetype":"venue"
},
  "geometry": {"coordinates":[-120.33253000000001,37.680523],"type":"Point"}
}