{
  "type": "Feature",
  "properties": {
    "addr:full":"1119 Hillside Blvd Daly City CA 94014",
    "addr:housenumber":"1119",
    "addr:postcode":"94014",
    "addr:street":"Hillside Blvd",
    "iso:country":"US",
    "sg:address":"1119 Hillside Blvd",
    "sg:city":"Daly City",
    "sg:classifiers":[
        {
            "category":"Building & Trades",
            "subcategory":"Construction",
            "type":"Services"
        }
    ],
    "sg:phone":"+1 415 587 4107",
    "sg:postcode":"94014",
    "sg:province":"CA",
    "sg:tags":[
        "maker",
        "cabinet"
    ],
    "wof:name":"G & T Woodworking",
    "wof:placetype":"venue"
},
  "geometry": {"coordinates":[-122.46036100000001,37.687521],"type":"Point"}
}