{
  "type": "Feature",
  "properties": {
    "addr:full":"2352 Canyon Dr Costa Mesa CA 92627",
    "addr:housenumber":"2352",
    "addr:postcode":"92627",
    "addr:street":"Canyon Dr",
    "iso:country":"US",
    "sg:address":"2352 Canyon Dr",
    "sg:city":"Costa Mesa",
    "sg:classifiers":[
        {
            "category":"Social Services",
            "subcategory":"Child Care",
            "type":"Services"
        }
    ],
    "sg:phone":"+1 949 631 6603",
    "sg:postcode":"92627",
    "sg:province":"CA",
    "sg:tags":[
        "kindergarten",
        "academic",
        "school"
    ],
    "wof:name":"Orange County Head Start Inc",
    "wof:placetype":"venue"
},
  "geometry": {"coordinates":[-117.94074500000001,33.658427],"type":"Point"}
}