{
  "type": "Feature",
  "properties": {
    "addr:full":"1613 S Main St Milpitas CA 95035",
    "addr:housenumber":"1613",
    "addr:postcode":"95035",
    "addr:street":"S Main St",
    "iso:country":"US",
    "sg:address":"1613 S Main St",
    "sg:city":"Milpitas",
    "sg:classifiers":[
        {
            "category":"Professional",
            "subcategory":"Computer Services",
            "type":"Services"
        }
    ],
    "sg:phone":"+1 408 934 1888",
    "sg:postcode":"95035",
    "sg:province":"CA",
    "sg:tags":[
        "electronics"
    ],
    "wof:name":"Peace Of Land Com",
    "wof:placetype":"venue"
},
  "geometry": {"coordinates":[-121.902985,37.405687],"type":"Point"}
}