{
  "type": "Feature",
  "properties": {
    "addr:full":"12808 Rancho Penasquitos Blvd San Diego CA 92129",
    "addr:housenumber":"12808",
    "addr:postcode":"92129",
    "addr:street":"Rancho Penasquitos Blvd",
    "iso:country":"US",
    "sg:address":"12808 Rancho Penasquitos Blvd",
    "sg:city":"San Diego",
    "sg:classifiers":[
        {
            "category":"Restaurant",
            "type":"Food & Drink"
        }
    ],
    "sg:menulink":"http://www.allmenus.com/ca/san-diego/215959-mcdonalds/menu/",
    "sg:postcode":"92129",
    "sg:province":"CA",
    "sg:tags":[
        "burger",
        "american"
    ],
    "wof:name":"McDonald's",
    "wof:placetype":"venue"
},
  "geometry": {"coordinates":[-117.107726,32.95018],"type":"Point"}
}