{
  "type": "Feature",
  "properties": {
    "iso:country":"US",
    "sg:address":"1814 Franklin Street Fourth Floor",
    "sg:city":"Oakland",
    "sg:classifiers":[
        {
            "category":"Professional",
            "type":"Services"
        },
        {
            "category":"Food & Beverages",
            "subcategory":"Specialty",
            "type":"Retail Goods"
        }
    ],
    "sg:phone":"+1 510 613 0330",
    "sg:postcode":"94612",
    "sg:province":"CA",
    "sg:tags":[
        "caterer"
    ],
    "sg:website":"www.mealsforchange.com",
    "wof:name":"Meals for Change",
    "wof:placetype":"venue"
},
  "geometry": {"coordinates":[-122.26751,37.806911],"type":"Point"}
}