{
  "type": "Feature",
  "properties": {
    "addr:full":"12047 Donner Pass Rd Truckee CA 96161",
    "addr:housenumber":"12047",
    "addr:postcode":"96161",
    "addr:street":"Donner Pass Rd",
    "iso:country":"US",
    "sg:address":"12047 Donner Pass Rd",
    "sg:city":"Truckee",
    "sg:classifiers":[
        {
            "category":"Shopping",
            "subcategory":"Music",
            "type":"Retail Goods"
        }
    ],
    "sg:phone":"+1 530 550 9934",
    "sg:postcode":"96161",
    "sg:province":"CA",
    "sg:tags":[
        "video",
        "disc",
        "tape",
        "cassette"
    ],
    "wof:name":"Superstar Video",
    "wof:placetype":"venue"
},
  "geometry": {"coordinates":[-120.22247299999999,39.325411],"type":"Point"}
}