{
  "type": "Feature",
  "properties": {
    "addr:full":"1736 S Sepulveda Blvd Los Angeles CA 90025",
    "addr:housenumber":"1736",
    "addr:postcode":"90025",
    "addr:street":"S Sepulveda Blvd",
    "iso:country":"US",
    "sg:address":"1736 S Sepulveda Blvd",
    "sg:city":"Los Angeles",
    "sg:classifiers":[
        {
            "category":"Retail",
            "subcategory":"Veterinary Services",
            "type":"Services"
        },
        {
            "category":"Professional",
            "subcategory":"Management & Consulting",
            "type":"Services"
        }
    ],
    "sg:phone":"+1 310 478 5915",
    "sg:postcode":"90025",
    "sg:province":"CA",
    "sg:tags":[
        "hospital",
        "veterinarian",
        "animal"
    ],
    "wof:name":"California Animal Hospital",
    "wof:placetype":"venue"
},
  "geometry": {"coordinates":[-118.444256,34.047693],"type":"Point"}
}