{
  "type": "Feature",
  "properties": {
    "addr:full":"773 Market St San Francisco CA 94103",
    "addr:housenumber":"773",
    "addr:postcode":"94103",
    "addr:street":"Market St",
    "iso:country":"US",
    "sg:address":"773 Market St",
    "sg:city":"San Francisco",
    "sg:classifiers":[
        {
            "category":"Coffee & Tea",
            "type":"Food & Drink"
        }
    ],
    "sg:phone":"+1 415 896 5029",
    "sg:postcode":"94103",
    "sg:province":"CA",
    "sg:website":"www.coffeebean.com",
    "wof:name":"The Coffee Bean & Tea Leaf",
    "wof:placetype":"venue"
},
  "geometry": {"coordinates":[-122.405248,37.786046],"type":"Point"}
}