{
  "type": "Feature",
  "properties": {
    "iso:country":"US",
    "sg:address":"75 Bellam Blvd",
    "sg:city":"San Rafael",
    "sg:classifiers":[
        {
            "category":"Autos & Motor Vehicles",
            "subcategory":"Auto Supplies",
            "type":"Retail Goods"
        }
    ],
    "sg:phone":"+1 415 454 5881",
    "sg:postcode":"94901",
    "sg:province":"CA",
    "sg:tags":[
        "automobile",
        "parts"
    ],
    "wof:name":"Kragen Auto Parts",
    "wof:placetype":"venue"
},
  "geometry": {"coordinates":[-122.50773599999999,37.958559],"type":"Point"}
}