{
  "type": "Feature",
  "properties": {
    "addr:full":"1296 Diamond Mountain Rd Calistoga CA 94515",
    "addr:housenumber":"1296",
    "addr:postcode":"94515",
    "addr:street":"Diamond Mountain Rd",
    "iso:country":"US",
    "sg:address":"1296 Diamond Mountain Rd",
    "sg:city":"Calistoga",
    "sg:classifiers":[
        {
            "category":"Recreation",
            "type":"Entertainment"
        }
    ],
    "sg:phone":"+1 707 942 0719",
    "sg:postcode":"94515",
    "sg:province":"CA",
    "sg:tags":[
        "animal"
    ],
    "wof:name":"Diamond Mountain Stables",
    "wof:placetype":"venue"
},
  "geometry": {"coordinates":[-122.56355600000001,38.566463],"type":"Point"}
}