{
  "type": "Feature",
  "properties": {
    "iso:country":"US",
    "sg:address":"23127 Lyons Ave",
    "sg:city":"Santa Clarita",
    "sg:classifiers":[
        {
            "category":"Shopping",
            "subcategory":"Gifts & Souvenirs",
            "type":"Retail Goods"
        }
    ],
    "sg:phone":"+1 661 287 9950",
    "sg:postcode":"91321",
    "sg:province":"CA",
    "sg:tags":[
        "flower"
    ],
    "wof:name":"Rooms And Blooms",
    "wof:placetype":"venue"
},
  "geometry": {"coordinates":[-118.537094,34.380182],"type":"Point"}
}