{
  "type": "Feature",
  "properties": {
    "iso:country":"US",
    "sg:address":"405 Sumner St",
    "sg:city":"Bakersfield",
    "sg:classifiers":[
        {
            "category":"Retail",
            "subcategory":"Auto Repair",
            "type":"Services"
        }
    ],
    "sg:phone":"+1 661 325 4763",
    "sg:postcode":"93305",
    "sg:province":"CA",
    "sg:tags":[
        "automobile",
        "customizing"
    ],
    "wof:name":"Hot Rod Specialties",
    "wof:placetype":"venue"
},
  "geometry": {"coordinates":[-118.996041,35.377589],"type":"Point"}
}