{
  "type": "Feature",
  "properties": {
    "iso:country":"US",
    "sg:address":"850 Sequoia Ave",
    "sg:city":"Sanger",
    "sg:classifiers":[
        {
            "category":"Freight",
            "type":"Transportation"
        }
    ],
    "sg:phone":"+1 559 469 3140",
    "sg:postcode":"93657",
    "sg:province":"CA",
    "sg:tags":[
        "trucking"
    ],
    "wof:name":"Mendez Trucking",
    "wof:placetype":"venue"
},
  "geometry": {"coordinates":[-119.548655,36.716976],"type":"Point"}
}