{
  "type": "Feature",
  "properties": {
    "addr:full":"22692 Mission Blvd Hayward CA 94541",
    "addr:housenumber":"22692",
    "addr:postcode":"94541",
    "addr:street":"Mission Blvd",
    "iso:country":"US",
    "sg:address":"22692 Mission Blvd",
    "sg:city":"Hayward",
    "sg:classifiers":[
        {
            "category":"Personal",
            "subcategory":"Beauty Salon",
            "type":"Services"
        }
    ],
    "sg:phone":"+1 510 881 8637",
    "sg:postcode":"94541",
    "sg:province":"CA",
    "sg:tags":[
        "manicuring"
    ],
    "wof:name":"Lotus Toetus Nails",
    "wof:placetype":"venue"
},
  "geometry": {"coordinates":[-122.083755,37.672115],"type":"Point"}
}