{
  "type": "Feature",
  "properties": {
    "addr:full":"3250 N Chatwin Ave Long Beach CA 90808",
    "addr:housenumber":"3250",
    "addr:postcode":"90808",
    "addr:street":"N Chatwin Ave",
    "iso:country":"US",
    "sg:address":"3250 N Chatwin Ave",
    "sg:city":"Long Beach",
    "sg:classifiers":[
        {
            "category":"Farming",
            "subcategory":"Fish & Marine Products",
            "type":"Manufacturing & Wholesale Goods"
        }
    ],
    "sg:phone":"+1 562 421 0219",
    "sg:postcode":"90808",
    "sg:province":"CA",
    "sg:tags":[
        "squid",
        "commercial",
        "fishing"
    ],
    "wof:name":"Carnage Fish Company Inc",
    "wof:placetype":"venue"
},
  "geometry": {"coordinates":[-118.12316,33.816281],"type":"Point"}
}