{
  "type": "Feature",
  "properties": {
    "iso:country":"US",
    "sg:address":"1221 S Main St",
    "sg:city":"Santa Ana",
    "sg:classifiers":[
        {
            "category":"Shopping",
            "subcategory":"Florist",
            "type":"Retail Goods"
        }
    ],
    "sg:phone":"+1 714 571 0506",
    "sg:postcode":"92707",
    "sg:province":"CA",
    "sg:tags":[
        "nursery",
        "gardening",
        "supply"
    ],
    "sg:website":"www.oncampusbooks.com",
    "wof:name":"Alta Vista Nursery",
    "wof:placetype":"venue"
},
  "geometry": {"coordinates":[-117.86799600000001,33.732498],"type":"Point"}
}