{
  "type": "Feature",
  "properties": {
    "iso:country":"US",
    "sg:address":"18411 Gothard St",
    "sg:city":"Huntington Beach",
    "sg:classifiers":[
        {
            "category":"Shopping",
            "subcategory":"Computers & Home Electronics",
            "type":"Retail Goods"
        }
    ],
    "sg:phone":"+1 714 596 5642",
    "sg:postcode":"92647",
    "sg:province":"CA",
    "sg:tags":[
        "parts",
        "supply"
    ],
    "wof:name":"Applied Computer",
    "wof:placetype":"venue"
},
  "geometry": {"coordinates":[-117.999894,33.695355],"type":"Point"}
}