{
  "type": "Feature",
  "properties": {
    "addr:full":"725 W Raymond St Compton CA 90220",
    "addr:housenumber":"725",
    "addr:postcode":"90220",
    "addr:street":"W Raymond St",
    "iso:country":"US",
    "sg:address":"725 W Raymond St",
    "sg:city":"Compton",
    "sg:classifiers":[
        {
            "category":"Social Services",
            "subcategory":"Child Care",
            "type":"Services"
        },
        {
            "category":"Education",
            "subcategory":"Preschool",
            "type":"Public Place"
        },
        {
            "category":"Education",
            "subcategory":"School",
            "type":"Public Place"
        }
    ],
    "sg:phone":"+1 310 933 0760",
    "sg:postcode":"90220",
    "sg:province":"CA",
    "sg:tags":[
        "kindergarten",
        "elementary",
        "nursery",
        "day"
    ],
    "wof:name":"CDI Head Start",
    "wof:placetype":"venue"
},
  "geometry": {"coordinates":[-118.235804,33.887306],"type":"Point"}
}