{
  "type": "Feature",
  "properties": {
    "addr:full":"12812 Palm St Garden Grove CA 92840",
    "addr:housenumber":"12812",
    "addr:postcode":"92840",
    "addr:street":"Palm St",
    "iso:country":"US",
    "sg:address":"12812 Palm St",
    "sg:city":"Garden Grove",
    "sg:classifiers":[
        {
            "category":"Travel",
            "subcategory":"Hotels & Motels",
            "type":"Entertainment"
        }
    ],
    "sg:phone":"+1 714 537 8008",
    "sg:postcode":"92840",
    "sg:province":"CA",
    "wof:name":"Harbor Motel",
    "wof:placetype":"venue"
},
  "geometry": {"coordinates":[-117.915001,33.7761],"type":"Point"}
}