{
  "type": "Feature",
  "properties": {
    "iso:country":"US",
    "sg:address":"5430 Bellingham Ave",
    "sg:city":"Valley Village",
    "sg:classifiers":[
        {
            "category":"Professional",
            "subcategory":"Management & Consulting",
            "type":"Services"
        }
    ],
    "sg:phone":"+1 818 755 3933",
    "sg:postcode":"91607",
    "sg:province":"CA",
    "sg:tags":[
        "public",
        "relations"
    ],
    "wof:name":"Creative Advertising Services",
    "wof:placetype":"venue"
},
  "geometry": {"coordinates":[-118.39914,34.169825],"type":"Point"}
}