{
  "type": "Feature",
  "properties": {
    "addr:full":"57121 Sunnyslope Dr Yucca Valley CA 92284",
    "addr:postcode":"57121;92284",
    "addr:street":"Sunnyslope Dr Yucca",
    "iso:country":"US",
    "sg:address":"57121 Sunnyslope Dr",
    "sg:city":"Yucca Valley",
    "sg:classifiers":[
        {
            "category":"Social Services",
            "type":"Services"
        }
    ],
    "sg:phone":"+1 760 365 9661",
    "sg:postcode":"92284",
    "sg:province":"CA",
    "sg:tags":[
        "senior",
        "citizen"
    ],
    "wof:name":"Morongo Basin Adult Health Svc",
    "wof:placetype":"venue"
},
  "geometry": {"coordinates":[-116.417691,34.127802],"type":"Point"}
}