{
  "type": "Feature",
  "properties": {
    "iso:country":"US",
    "sg:address":"1979 Peabody Rd",
    "sg:city":"Vacaville",
    "sg:classifiers":[
        {
            "category":"Coffee & Tea",
            "type":"Food & Drink"
        }
    ],
    "sg:menulink":"http://www.allmenus.com/ca/vacaville/118498-starbucks-coffee/menu/",
    "sg:phone":"+1 707 452 0991",
    "sg:postcode":"95687",
    "sg:province":"CA",
    "sg:tags":[
        "american"
    ],
    "wof:name":"Starbucks Coffee",
    "wof:placetype":"venue"
},
  "geometry": {"coordinates":[-121.969267,38.336215],"type":"Point"}
}