{
  "type": "Feature",
  "properties": {
    "iso:country":"US",
    "sg:address":"350 S Figueroa St",
    "sg:city":"Los Angeles",
    "sg:classifiers":[
        {
            "category":"Real Estate",
            "subcategory":"Developer",
            "type":"Services"
        }
    ],
    "sg:phone":"+1 213 625 2100",
    "sg:postcode":"90071",
    "sg:province":"CA",
    "wof:name":"Olympic Development Inc",
    "wof:placetype":"venue"
},
  "geometry": {"coordinates":[-118.255226,34.054327],"type":"Point"}
}