{
  "type": "Feature",
  "properties": {
    "addr:full":"13060 Marlette Dr La Mirada CA 90638",
    "addr:postcode":"13060;90638",
    "addr:street":"Marlette Dr",
    "iso:country":"US",
    "sg:address":"13060 Marlette Dr",
    "sg:city":"La Mirada",
    "sg:classifiers":[
        {
            "category":"Health Services",
            "subcategory":"Chiropractor",
            "type":"Services"
        }
    ],
    "sg:phone":"+1 714 498 0008",
    "sg:postcode":"90638",
    "sg:province":"CA",
    "wof:name":"Performance Chiropractic",
    "wof:placetype":"venue"
},
  "geometry": {"coordinates":[-118.028599,33.909813],"type":"Point"}
}