{
  "type": "Feature",
  "properties": {
    "addr:full":"1637 S Oaks Ave Ontario CA 91762",
    "addr:housenumber":"1637",
    "addr:postcode":"91762",
    "addr:street":"S Oaks Ave",
    "iso:country":"US",
    "sg:address":"1637 S Oaks Ave",
    "sg:city":"Ontario",
    "sg:classifiers":[
        {
            "category":"Real Estate",
            "subcategory":"Real Estate Operator",
            "type":"Services"
        }
    ],
    "sg:phone":"+1 909 633 6840",
    "sg:postcode":"91762",
    "sg:province":"CA",
    "sg:tags":[
        "apartment"
    ],
    "wof:name":"Jlg Apartments",
    "wof:placetype":"venue"
},
  "geometry": {"coordinates":[-117.676462,34.043613],"type":"Point"}
}