{
  "type": "Feature",
  "properties": {
    "addr:full":"1631 Highland Way Brentwood CA 94513",
    "addr:housenumber":"1631",
    "addr:postcode":"ca 94513",
    "addr:street":"Highland Way",
    "iso:country":"US",
    "sg:address":"1631 Highland Way",
    "sg:city":"Brentwood",
    "sg:classifiers":[
        {
            "category":"Professional",
            "type":"Services"
        }
    ],
    "sg:phone":"+1 925 516 8253",
    "sg:postcode":"94513",
    "sg:province":"CA",
    "wof:name":"Norcalprepscores Com",
    "wof:placetype":"venue"
},
  "geometry": {"coordinates":[-121.72628899999999,37.941988],"type":"Point"}
}