{
  "type": "Feature",
  "properties": {
    "iso:country":"US",
    "sg:address":"269 N Park Ave",
    "sg:city":"Pomona",
    "sg:classifiers":[
        {
            "category":"Wholesale",
            "subcategory":"Fruits & Vegetables",
            "type":"Manufacturing & Wholesale Goods"
        }
    ],
    "sg:phone":"+1 909 623 9711",
    "sg:postcode":"91768",
    "sg:province":"CA",
    "wof:name":"J & G Produce",
    "wof:placetype":"venue"
},
  "geometry": {"coordinates":[-117.754655,34.059816],"type":"Point"}
}