{
  "type": "Feature",
  "properties": {
    "addr:full":"1317 Muscat Ct Brentwood CA 94513",
    "addr:housenumber":"1317",
    "addr:postcode":"94513",
    "addr:street":"Muscat Ct",
    "iso:country":"US",
    "sg:address":"1317 Muscat Ct",
    "sg:city":"Brentwood",
    "sg:classifiers":[
        {
            "category":"Building & Trades",
            "subcategory":"Construction",
            "type":"Services"
        }
    ],
    "sg:phone":"+1 925 240 6224",
    "sg:postcode":"94513",
    "sg:province":"CA",
    "sg:tags":[
        "resurfacing",
        "laying",
        "refinishing",
        "floor"
    ],
    "wof:name":"Floors Of Wood",
    "wof:placetype":"venue"
},
  "geometry": {"coordinates":[-121.708336,37.943661],"type":"Point"}
}