{
  "type": "Feature",
  "properties": {
    "iso:country":"US",
    "sg:address":"4301 3rd St",
    "sg:city":"San Francisco",
    "sg:classifiers":[
        {
            "category":"Health Services",
            "subcategory":"Hospital",
            "type":"Services"
        }
    ],
    "sg:phone":"+1 415 648 5785",
    "sg:postcode":"94124",
    "sg:province":"CA",
    "sg:tags":[
        "mental"
    ],
    "wof:name":"Bayview Hunters Point Fndtn",
    "wof:placetype":"venue"
},
  "geometry": {"coordinates":[-122.38958700000001,37.737955],"type":"Point"}
}