{
  "type": "Feature",
  "properties": {
    "addr:full":"3245 Monika Ln Hayward CA 94541",
    "addr:housenumber":"3245",
    "addr:postcode":"94541",
    "addr:street":"Monika Ln",
    "iso:country":"US",
    "sg:address":"3245 Monika Ln",
    "sg:city":"Hayward",
    "sg:classifiers":[
        {
            "category":"Professional",
            "subcategory":"Business Services",
            "type":"Services"
        }
    ],
    "sg:phone":"+1 510 582 5298",
    "sg:postcode":"94541",
    "sg:province":"CA",
    "sg:tags":[
        "interior",
        "consultant",
        "design",
        "decorator"
    ],
    "wof:name":"Hamlet Design",
    "wof:placetype":"venue"
},
  "geometry": {"coordinates":[-122.053186,37.688697],"type":"Point"}
}