{
  "type": "Feature",
  "properties": {
    "addr:full":"8102 Kelley Dr Stockton CA 95209",
    "addr:housenumber":"8102",
    "addr:postcode":"95209",
    "addr:street":"Kelley Dr",
    "iso:country":"US",
    "sg:address":"8102 Kelley Dr",
    "sg:city":"Stockton",
    "sg:classifiers":[
        {
            "category":"Personal",
            "subcategory":"Massage",
            "type":"Services"
        },
        {
            "category":"Health Services",
            "subcategory":"Clinic",
            "type":"Services"
        },
        {
            "category":"Health Services",
            "subcategory":"Health Practitioner",
            "type":"Services"
        }
    ],
    "sg:phone":"+1 209 931 6610",
    "sg:postcode":"95209",
    "sg:province":"CA",
    "sg:tags":[
        "therapist",
        "therapy",
        "physical"
    ],
    "wof:name":"Ambers Massage Therapy",
    "wof:placetype":"venue"
},
  "geometry": {"coordinates":[-121.35666000000001,38.023043],"type":"Point"}
}