{
  "type": "Feature",
  "properties": {
    "iso:country":"US",
    "sg:address":"2000 Van Ness Avenue",
    "sg:city":"San Francisco",
    "sg:classifiers":[
        {
            "category":"Health Services",
            "subcategory":"Doctor",
            "type":"Services"
        }
    ],
    "sg:phone":"+1 800 743 4247",
    "sg:postcode":"94109",
    "sg:province":"CA",
    "sg:website":"www.rosanelli.com",
    "wof:name":"Rosanelli Medical Associates",
    "wof:placetype":"venue"
},
  "geometry": {"coordinates":[-122.422967,37.793991],"type":"Point"}
}