{
  "type": "Feature",
  "properties": {
    "addr:full":"1137 Walnut St Inglewood CA 90301",
    "addr:housenumber":"1137",
    "addr:postcode":"90301",
    "addr:street":"Walnut St",
    "iso:country":"US",
    "sg:address":"1137 Walnut St",
    "sg:city":"Inglewood",
    "sg:classifiers":[
        {
            "category":"Building & Trades",
            "subcategory":"Equipment Rental",
            "type":"Services"
        }
    ],
    "sg:phone":"+1 310 672 1452",
    "sg:postcode":"90301",
    "sg:province":"CA",
    "wof:name":"Jump Paradise",
    "wof:placetype":"venue"
},
  "geometry": {"coordinates":[-118.356004,33.94794],"type":"Point"}
}