{
  "type": "Feature",
  "properties": {
    "iso:country":"US",
    "sg:address":"1705 Sabre Street",
    "sg:city":"Hayward",
    "sg:classifiers":[
        {
            "category":"Building & Trades",
            "subcategory":"Construction",
            "type":"Services"
        }
    ],
    "sg:phone":"+1 866 558 4240",
    "sg:postcode":"94545",
    "sg:province":"CA",
    "sg:tags":[
        "contractor"
    ],
    "sg:website":"www.segalebros.com",
    "wof:name":"Segale Bros Wood Products",
    "wof:placetype":"venue"
},
  "geometry": {"coordinates":[-122.127393,37.656486],"type":"Point"}
}