{
  "type": "Feature",
  "properties": {
    "addr:full":"1318 Vis Colina San Marcos CA 92078",
    "addr:housenumber":"1318",
    "addr:postcode":"92078",
    "addr:street":"Vis Colina",
    "iso:country":"US",
    "sg:address":"1318 Vis Colina",
    "sg:city":"San Marcos",
    "sg:classifiers":[
        {
            "category":"Building & Trades",
            "subcategory":"Construction",
            "type":"Services"
        }
    ],
    "sg:phone":"+1 760 471 5111",
    "sg:postcode":"92078",
    "sg:province":"CA",
    "sg:tags":[
        "contractor"
    ],
    "wof:name":"Castillero Design & Constr",
    "wof:placetype":"venue"
},
  "geometry": {"coordinates":[-117.188275,33.119358],"type":"Point"}
}