{
  "type": "Feature",
  "properties": {
    "addr:full":"3355 Sacramento St San Francisco CA 94118",
    "addr:housenumber":"3355",
    "addr:postcode":"94118",
    "addr:street":"Sacramento St",
    "iso:country":"US",
    "sg:address":"3355 Sacramento St",
    "sg:city":"San Francisco",
    "sg:classifiers":[
        {
            "category":"Professional",
            "type":"Services"
        }
    ],
    "sg:phone":"+1 415 921 4070",
    "sg:postcode":"94118",
    "sg:province":"CA",
    "sg:tags":[
        "establishment"
    ],
    "wof:name":"Mikveh Society Of Sf",
    "wof:placetype":"venue"
},
  "geometry": {"coordinates":[-122.447912,37.788018],"type":"Point"}
}