{
  "type": "Feature",
  "properties": {
    "addr:full":"13658 Hawthorne Blvd Ste 208 Hawthorne CA 90250",
    "addr:housenumber":"13658",
    "addr:postcode":"90250",
    "addr:street":"Hawthorne Blvd Ste 208",
    "iso:country":"US",
    "sg:address":"13658 Hawthorne Blvd Ste 208",
    "sg:city":"Hawthorne",
    "sg:classifiers":[
        {
            "category":"Wholesale",
            "subcategory":"Office Equipment",
            "type":"Manufacturing & Wholesale Goods"
        },
        {
            "category":"Professional",
            "subcategory":"Printing & Photocopies",
            "type":"Services"
        },
        {
            "category":"Shopping",
            "subcategory":"Computers & Home Electronics",
            "type":"Retail Goods"
        }
    ],
    "sg:phone":"+1 310 978 9510",
    "sg:postcode":"90250",
    "sg:province":"CA",
    "sg:tags":[
        "scanning",
        "printer",
        "plotting",
        "supply"
    ],
    "wof:name":"Menace Studios",
    "wof:placetype":"venue"
},
  "geometry": {"coordinates":[-118.35240899999999,33.908098],"type":"Point"}
}