{
  "type": "Feature",
  "properties": {
    "iso:country":"US",
    "sg:address":"1524 Lynn Ave",
    "sg:city":"Modesto",
    "sg:classifiers":[
        {
            "category":"Restaurant",
            "type":"Food & Drink"
        }
    ],
    "sg:phone":"+1 209 579 7655",
    "sg:postcode":"95358",
    "sg:province":"CA",
    "wof:name":"Cinnamon Cafe",
    "wof:placetype":"venue"
},
  "geometry": {"coordinates":[-121.032668,37.620768],"type":"Point"}
}