{
  "type": "Feature",
  "properties": {
    "addr:full":"6384 Lancaster Dr Paradise CA 95969",
    "addr:housenumber":"6384",
    "addr:postcode":"95969",
    "addr:street":"Lancaster Dr",
    "iso:country":"US",
    "sg:address":"6384 Lancaster Dr",
    "sg:city":"Paradise",
    "sg:classifiers":[
        {
            "category":"Farming",
            "subcategory":"Livestock Farm",
            "type":"Manufacturing & Wholesale Goods"
        }
    ],
    "sg:phone":"+1 530 877 9654",
    "sg:postcode":"95969",
    "sg:province":"CA",
    "sg:tags":[
        "specialty",
        "animal"
    ],
    "wof:name":"Lens Apiaries",
    "wof:placetype":"venue"
},
  "geometry": {"coordinates":[-121.591055,39.771313],"type":"Point"}
}