{
  "type": "Feature",
  "properties": {
    "iso:country":"US",
    "sg:address":"1414 Mission St",
    "sg:city":"South Pasadena",
    "sg:classifiers":[
        {
            "category":"Government",
            "subcategory":"Office",
            "type":"Public Place"
        }
    ],
    "sg:phone":"+1 626 403 7200",
    "sg:postcode":"91030",
    "sg:province":"CA",
    "sg:tags":[
        "city",
        "village"
    ],
    "wof:name":"South Pasadena City Council",
    "wof:placetype":"venue"
},
  "geometry": {"coordinates":[-118.151754,34.115897],"type":"Point"}
}