{
  "type": "Feature",
  "properties": {
    "addr:full":"381 S Lexington Dr Folsom CA 95630",
    "addr:housenumber":"381",
    "addr:postcode":"95630",
    "addr:street":"S Lexington Dr",
    "iso:country":"US",
    "sg:address":"381 S Lexington Dr",
    "sg:city":"Folsom",
    "sg:classifiers":[
        {
            "category":"Professional",
            "subcategory":"Lawyer & Legal Services",
            "type":"Services"
        }
    ],
    "sg:phone":"+1 916 983 2997",
    "sg:postcode":"95630",
    "sg:province":"CA",
    "sg:tags":[
        "attorney"
    ],
    "wof:name":"L Michelle Chavis Atty At Law",
    "wof:placetype":"venue"
},
  "geometry": {"coordinates":[-121.134624,38.666472],"type":"Point"}
}