{
  "type": "Feature",
  "properties": {
    "addr:full":"950 Hotel Cir N San Diego CA 92108",
    "addr:housenumber":"950",
    "addr:postcode":"92108",
    "addr:street":"Hotel Cir N",
    "iso:country":"US",
    "sg:address":"950 Hotel Cir N",
    "sg:city":"San Diego",
    "sg:classifiers":[
        {
            "category":"Travel",
            "subcategory":"Hotels & Motels",
            "type":"Entertainment"
        }
    ],
    "sg:phone":"+1 619 298 0511",
    "sg:postcode":"92108",
    "sg:province":"CA",
    "sg:website":"www.handlery.com/sd/yelp/",
    "wof:name":"Handlery Hotel And Resort",
    "wof:placetype":"venue"
},
  "geometry": {"coordinates":[-117.172472,32.760392],"type":"Point"}
}