{
  "type": "Feature",
  "properties": {
    "addr:full":"2970 S. Winchester Blvd. Campbell CA 95008",
    "addr:housenumber":"2970",
    "addr:postcode":"95008",
    "addr:street":"S. Winchester Blvd.",
    "iso:country":"US",
    "sg:address":"2970 S. Winchester Blvd.",
    "sg:city":"Campbell",
    "sg:classifiers":[
        {
            "category":"Retail",
            "subcategory":"Auto Repair",
            "type":"Services"
        }
    ],
    "sg:phone":"+1 408 370 0810",
    "sg:postcode":"95008",
    "sg:province":"CA",
    "wof:name":"South Bay Auto Repair",
    "wof:placetype":"venue"
},
  "geometry": {"coordinates":[-121.95486699999999,37.270772],"type":"Point"}
}