{
  "type": "Feature",
  "properties": {
    "iso:country":"US",
    "sg:address":"4620 Convoy St #C",
    "sg:city":"San Diego",
    "sg:classifiers":[
        {
            "category":"Bars & Pubs",
            "type":"Food & Drink"
        },
        {
            "category":"Restaurant",
            "type":"Food & Drink"
        },
        {
            "category":"Bars & Pubs",
            "subcategory":"Lounge",
            "type":"Food & Drink"
        }
    ],
    "sg:phone":"+1 858 560 8168",
    "sg:postcode":"92111",
    "sg:province":"CA",
    "sg:tags":[
        "korean",
        "karaoke"
    ],
    "wof:name":"Min Sok Chon",
    "wof:placetype":"venue"
},
  "geometry": {"coordinates":[-117.15572299999999,32.824258],"type":"Point"}
}