{
  "type": "Feature",
  "properties": {
    "addr:full":"770 Menlo Ave Menlo Park CA 94025",
    "addr:housenumber":"770",
    "addr:postcode":"94025",
    "addr:street":"Menlo Ave",
    "iso:country":"US",
    "sg:address":"770 Menlo Ave",
    "sg:city":"Menlo Park",
    "sg:classifiers":[
        {
            "category":"Insurance",
            "subcategory":"Insurance Agent",
            "type":"Services"
        }
    ],
    "sg:phone":"+1 650 328 6299",
    "sg:postcode":"94025",
    "sg:province":"CA",
    "wof:name":"Claire Liversidge Chfc",
    "wof:placetype":"venue"
},
  "geometry": {"coordinates":[-122.183817,37.450649],"type":"Point"}
}