{
  "type": "Feature",
  "properties": {
    "iso:country":"US",
    "sg:address":"1025 5th St",
    "sg:city":"Novato",
    "sg:classifiers":[
        {
            "category":"Social Services",
            "type":"Services"
        }
    ],
    "sg:phone":"+1 415 883 4360",
    "sg:postcode":"94945",
    "sg:province":"CA",
    "sg:tags":[
        "counselor",
        "marriage",
        "family"
    ],
    "wof:name":"Charlene Kelzer",
    "wof:placetype":"venue"
},
  "geometry": {"coordinates":[-122.57547,38.110244],"type":"Point"}
}