{
  "type": "Feature",
  "properties": {
    "addr:full":"4472 Esto Ave El Monte CA 91731",
    "addr:housenumber":"4472",
    "addr:postcode":"91731",
    "addr:street":"Esto Ave",
    "iso:country":"US",
    "sg:address":"4472 Esto Ave",
    "sg:city":"El Monte",
    "sg:classifiers":[
        {
            "category":"Travel",
            "subcategory":"Travel Agent",
            "type":"Entertainment"
        }
    ],
    "sg:phone":"+1 626 289 7000",
    "sg:postcode":"91731",
    "sg:province":"CA",
    "sg:tags":[
        "agency"
    ],
    "wof:name":"Ay S Tham",
    "wof:placetype":"venue"
},
  "geometry": {"coordinates":[-118.039484,34.086342],"type":"Point"}
}