{
  "type": "Feature",
  "properties": {
    "iso:country":"US",
    "sg:address":"1635 Sweetwater Rd",
    "sg:city":"National City",
    "sg:classifiers":[
        {
            "category":"Travel",
            "subcategory":"Travel Agent",
            "type":"Entertainment"
        }
    ],
    "sg:phone":"+1 619 474 9301",
    "sg:postcode":"91950",
    "sg:province":"CA",
    "sg:tags":[
        "agency",
        "bureau"
    ],
    "wof:name":"Rainbow World Travel",
    "wof:placetype":"venue"
},
  "geometry": {"coordinates":[-117.083789,32.661221],"type":"Point"}
}