{
  "type": "Feature",
  "properties": {
    "iso:country":"US",
    "sg:address":"6428 Stockton Blvd",
    "sg:city":"Sacramento",
    "sg:classifiers":[
        {
            "category":"Food & Beverages",
            "subcategory":"Ethnic Foods",
            "type":"Retail Goods"
        },
        {
            "category":"Food & Beverages",
            "subcategory":"Groceries & Convenience Stores",
            "type":"Retail Goods"
        }
    ],
    "sg:postcode":"95823",
    "sg:province":"CA",
    "wof:name":"New Asia Supermarket",
    "wof:placetype":"venue"
},
  "geometry": {"coordinates":[-121.435626,38.51001],"type":"Point"}
}