{
  "type": "Feature",
  "properties": {
    "iso:country":"US",
    "sg:address":"43 Tesla",
    "sg:city":"Irvine",
    "sg:classifiers":[
        {
            "category":"Education",
            "subcategory":"Kindergarten",
            "type":"Public Place"
        }
    ],
    "sg:phone":"+1 949 753 0831",
    "sg:postcode":"92618",
    "sg:province":"CA",
    "sg:tags":[
        "school",
        "driving"
    ],
    "wof:name":"Nexiant Driving Mro Excellence",
    "wof:placetype":"venue"
},
  "geometry": {"coordinates":[-117.736802,33.633453],"type":"Point"}
}