{
  "type": "Feature",
  "properties": {
    "iso:country":"US",
    "sg:address":"1181 Chess Dr",
    "sg:city":"San Mateo",
    "sg:classifiers":[
        {
            "category":"Shopping",
            "type":"Retail Goods"
        }
    ],
    "sg:phone":"+1 650 372 1030",
    "sg:postcode":"94404",
    "sg:province":"CA",
    "sg:tags":[
        "merchandise"
    ],
    "wof:name":"Phone Masters",
    "wof:placetype":"venue"
},
  "geometry": {"coordinates":[-122.274529,37.564988],"type":"Point"}
}