{
  "type": "Feature",
  "properties": {
    "iso:country":"US",
    "sg:address":"4321 Esto Ave",
    "sg:city":"El Monte",
    "sg:classifiers":[
        {
            "category":"Manufacturing",
            "subcategory":"Textiles",
            "type":"Manufacturing & Wholesale Goods"
        }
    ],
    "sg:phone":"+1 626 279 1394",
    "sg:postcode":"91731",
    "sg:province":"CA",
    "sg:tags":[
        "silk",
        "screening"
    ],
    "wof:name":"Feathered Serpent",
    "wof:placetype":"venue"
},
  "geometry": {"coordinates":[-118.040459,34.084417],"type":"Point"}
}