{
  "type": "Feature",
  "properties": {
    "addr:full":"51 W Shoshone St Ventura CA 93001",
    "addr:housenumber":"51",
    "addr:postcode":"93001",
    "addr:street":"W Shoshone St",
    "iso:country":"US",
    "sg:address":"51 W Shoshone St",
    "sg:city":"Ventura",
    "sg:classifiers":[
        {
            "category":"Real Estate",
            "subcategory":"Real Estate Services",
            "type":"Services"
        }
    ],
    "sg:phone":"+1 805 588 9085",
    "sg:postcode":"93001",
    "sg:province":"CA",
    "sg:tags":[
        "vacancy",
        "apartment",
        "rental",
        "finder",
        "listing"
    ],
    "wof:name":"Moontech Studios",
    "wof:placetype":"venue"
},
  "geometry": {"coordinates":[-119.294673,34.304076],"type":"Point"}
}