{
  "type": "Feature",
  "properties": {
    "addr:full":"312 E 1st St Los Angeles CA 90012",
    "addr:housenumber":"312",
    "addr:postcode":"90012",
    "addr:street":"E 1St St",
    "iso:country":"US",
    "sg:address":"312 E 1st St",
    "sg:city":"Los Angeles",
    "sg:classifiers":[
        {
            "category":"Real Estate",
            "subcategory":"Real Estate Agent",
            "type":"Services"
        }
    ],
    "sg:phone":"+1 213 626 8008",
    "sg:postcode":"90012",
    "sg:province":"CA",
    "wof:name":"WEG LLC",
    "wof:placetype":"venue"
},
  "geometry": {"coordinates":[-118.24060299999999,34.05015],"type":"Point"}
}