{
  "type": "Feature",
  "properties": {
    "addr:full":"12228 Venice Blvd Los Angeles CA 90066",
    "addr:housenumber":"12228",
    "addr:postcode":"90066",
    "addr:street":"Venice Blvd",
    "iso:country":"US",
    "sg:address":"12228 Venice Blvd",
    "sg:city":"Los Angeles",
    "sg:classifiers":[
        {
            "category":"Professional",
            "subcategory":"Lawyer & Legal Services",
            "type":"Services"
        }
    ],
    "sg:phone":"+1 310 397 2905",
    "sg:postcode":"90066",
    "sg:province":"CA",
    "sg:tags":[
        "notary"
    ],
    "wof:name":"Mar Vista Mailboxes",
    "wof:placetype":"venue"
},
  "geometry": {"coordinates":[-118.431999,34.004501],"type":"Point"}
}