{
  "type": "Feature",
  "properties": {
    "addr:full":"9706 Fair Oaks Blvd Fair Oaks CA 95628",
    "addr:housenumber":"9706",
    "addr:postcode":"95628",
    "addr:street":"Fair Oaks Blvd",
    "iso:country":"US",
    "sg:address":"9706 Fair Oaks Blvd",
    "sg:city":"Fair Oaks",
    "sg:classifiers":[
        {
            "category":"Real Estate",
            "subcategory":"Real Estate Agent",
            "type":"Services"
        }
    ],
    "sg:phone":"+1 916 967 6142",
    "sg:postcode":"95628",
    "sg:province":"CA",
    "wof:name":"Mid Valley Funding & Invstmnt",
    "wof:placetype":"venue"
},
  "geometry": {"coordinates":[-121.273505,38.639157],"type":"Point"}
}