{
  "type": "Feature",
  "properties": {
    "iso:country":"US",
    "sg:address":"68225 Ramon Rd",
    "sg:city":"Cathedral City",
    "sg:classifiers":[
        {
            "category":"Arena",
            "subcategory":"Sports Club",
            "type":"Entertainment"
        }
    ],
    "sg:phone":"+1 760 568 0961",
    "sg:postcode":"92234",
    "sg:province":"CA",
    "sg:tags":[
        "martial art"
    ],
    "sg:website":"www.isshinryu-karate.com",
    "wof:name":"ISSHINRYU KARATE SANDUBRAE",
    "wof:placetype":"venue"
},
  "geometry": {"coordinates":[-116.471682,33.815722],"type":"Point"}
}