{
  "type": "Feature",
  "properties": {
    "iso:country":"US",
    "sg:address":"3095 Richmond Pkwy",
    "sg:city":"Richmond",
    "sg:classifiers":[
        {
            "category":"Professional",
            "type":"Services"
        }
    ],
    "sg:phone":"+1 510 222 0131",
    "sg:postcode":"94806",
    "sg:province":"CA",
    "sg:tags":[
        "establishment"
    ],
    "wof:name":"Keyspan",
    "wof:placetype":"venue"
},
  "geometry": {"coordinates":[-122.328887,37.990037],"type":"Point"}
}