{
  "type": "Feature",
  "properties": {
    "iso:country":"US",
    "sg:address":"1150 W Hillsdale Blvd",
    "sg:city":"San Mateo",
    "sg:classifiers":[
        {
            "category":"Organizations",
            "subcategory":"Non-profit Organization",
            "type":"Services"
        }
    ],
    "sg:phone":"+1 650 595 9555",
    "sg:postcode":"94403",
    "sg:province":"CA",
    "sg:tags":[
        "human"
    ],
    "sg:website":"www.facesforkids.org",
    "wof:name":"Foundation For Autistic Chldhd",
    "wof:placetype":"venue"
},
  "geometry": {"coordinates":[-122.327535,37.533025],"type":"Point"}
}