{
  "type": "Feature",
  "properties": {
    "addr:full":"2647 Gateway Rd Ste 104 Carlsbad CA 92009",
    "addr:housenumber":"2647",
    "addr:postcode":"92009",
    "addr:street":"Gateway Rd Ste 104",
    "iso:country":"US",
    "sg:address":"2647 Gateway Rd Ste 104",
    "sg:city":"Carlsbad",
    "sg:classifiers":[
        {
            "category":"Shopping",
            "subcategory":"Baby Store",
            "type":"Retail Goods"
        }
    ],
    "sg:phone":"+1 760 579 0332",
    "sg:postcode":"92009",
    "sg:province":"CA",
    "sg:tags":[
        "gear",
        "furniture"
    ],
    "wof:name":"Ollie & Me",
    "wof:placetype":"venue"
},
  "geometry": {"coordinates":[-117.248345,33.129571],"type":"Point"}
}