{
  "type": "Feature",
  "properties": {
    "iso:country":"US",
    "sg:address":"1252 Norman Ave",
    "sg:city":"Santa Clara",
    "sg:classifiers":[
        {
            "category":"Real Estate",
            "subcategory":"Real Estate Agent",
            "type":"Services"
        }
    ],
    "sg:phone":"+1 408 988 0505",
    "sg:postcode":"95054",
    "sg:province":"CA",
    "sg:tags":[
        "management"
    ],
    "wof:name":"Amaral & Blanco",
    "wof:placetype":"venue"
},
  "geometry": {"coordinates":[-121.95308799999999,37.386376],"type":"Point"}
}