{
  "type": "Feature",
  "properties": {
    "iso:country":"US",
    "sg:address":"3500 Fulton Ave",
    "sg:city":"Sacramento",
    "sg:classifiers":[
        {
            "category":"Bars & Pubs",
            "subcategory":"Sports Bar",
            "type":"Food & Drink"
        }
    ],
    "sg:phone":"+1 916 978 9916",
    "sg:postcode":"95821",
    "sg:province":"CA",
    "sg:tags":[
        "hall",
        "pool"
    ],
    "wof:name":"T C's Billiard & Dart Club",
    "wof:placetype":"venue"
},
  "geometry": {"coordinates":[-121.401447,38.628552],"type":"Point"}
}