{
  "type": "Feature",
  "properties": {
    "iso:country":"US",
    "sg:address":"9137 Elm Ave",
    "sg:city":"Orangevale",
    "sg:classifiers":[
        {
            "category":"Shopping",
            "type":"Retail Goods"
        }
    ],
    "sg:phone":"+1 916 987 1809",
    "sg:postcode":"95662",
    "sg:province":"CA",
    "sg:tags":[
        "product",
        "wood"
    ],
    "wof:name":"Garth's Woodcrafts",
    "wof:placetype":"venue"
},
  "geometry": {"coordinates":[-121.21346200000001,38.69293],"type":"Point"}
}