{
  "type": "Feature",
  "properties": {
    "iso:country":"US",
    "sg:address":"18 Crow Canyon Ct",
    "sg:city":"San Ramon",
    "sg:classifiers":[
        {
            "category":"Professional",
            "subcategory":"Accounting & Tax Preparation",
            "type":"Services"
        }
    ],
    "sg:phone":"+1 925 314 9176",
    "sg:postcode":"94583",
    "sg:province":"CA",
    "sg:tags":[
        "accountant"
    ],
    "wof:name":"Allen M Dutra CPA",
    "wof:placetype":"venue"
},
  "geometry": {"coordinates":[-121.981413,37.777229],"type":"Point"}
}