{
  "type": "Feature",
  "properties": {
    "addr:full":"651 Broadway Gilroy CA 95020",
    "addr:housenumber":"651",
    "addr:postcode":"95020",
    "addr:street":"Broadway",
    "iso:country":"US",
    "sg:address":"651 Broadway",
    "sg:city":"Gilroy",
    "sg:classifiers":[
        {
            "category":"Education",
            "subcategory":"School",
            "type":"Public Place"
        }
    ],
    "sg:phone":"+1 408 847 3932",
    "sg:postcode":"95020",
    "sg:province":"CA",
    "wof:name":"Harmony Christian Preschool",
    "wof:placetype":"venue"
},
  "geometry": {"coordinates":[-121.581265,37.014505],"type":"Point"}
}