{
  "type": "Feature",
  "properties": {
    "iso:country":"US",
    "sg:address":"315 S Beverly Dr",
    "sg:city":"Beverly Hills",
    "sg:classifiers":[
        {
            "category":"Professional",
            "subcategory":"Lawyer & Legal Services",
            "type":"Services"
        }
    ],
    "sg:phone":"+1 310 277 1848",
    "sg:postcode":"90212",
    "sg:province":"CA",
    "sg:tags":[
        "attorney"
    ],
    "wof:name":"Mitchell R Miller",
    "wof:placetype":"venue"
},
  "geometry": {"coordinates":[-118.399156,34.060968],"type":"Point"}
}