{
  "type": "Feature",
  "properties": {
    "iso:country":"US",
    "sg:address":"819 E Anaheim St",
    "sg:city":"Long Beach",
    "sg:classifiers":[
        {
            "category":"Shopping",
            "subcategory":"Shoes",
            "type":"Retail Goods"
        }
    ],
    "sg:phone":"+1 562 218 9328",
    "sg:postcode":"90813",
    "sg:province":"CA",
    "sg:tags":[
        "store"
    ],
    "wof:name":"La Bodega Shoe Store",
    "wof:placetype":"venue"
},
  "geometry": {"coordinates":[-118.182447,33.782737],"type":"Point"}
}