{
  "type": "Feature",
  "properties": {
    "addr:full":"100 Aviation Way Watsonville CA 95076",
    "addr:housenumber":"100",
    "addr:postcode":"95076",
    "addr:street":"Aviation Way",
    "iso:country":"US",
    "sg:address":"100 Aviation Way",
    "sg:city":"Watsonville",
    "sg:classifiers":[
        {
            "category":"Airport",
            "type":"Transportation"
        }
    ],
    "sg:phone":"+1 831 728 6075",
    "sg:postcode":"95076",
    "sg:province":"CA",
    "wof:name":"Watsonville Airport",
    "wof:placetype":"venue"
},
  "geometry": {"coordinates":[-121.788302,36.933844],"type":"Point"}
}