{
  "type": "Feature",
  "properties": {
    "iso:country":"US",
    "sg:address":"4119 Campus Dr",
    "sg:city":"Irvine",
    "sg:classifiers":[
        {
            "category":"Professional",
            "subcategory":"Management & Consulting",
            "type":"Services"
        }
    ],
    "sg:phone":"+1 949 679 2588",
    "sg:postcode":"92612",
    "sg:province":"CA",
    "sg:tags":[
        "consultant",
        "business"
    ],
    "wof:name":"8 A Technologies",
    "wof:placetype":"venue"
},
  "geometry": {"coordinates":[-117.836353,33.64784],"type":"Point"}
}