{
  "type": "Feature",
  "properties": {
    "iso:country":"US",
    "sg:address":"8739 Elk Grove Blvd",
    "sg:city":"Elk Grove",
    "sg:classifiers":[
        {
            "category":"Insurance",
            "subcategory":"Insurance Agent",
            "type":"Services"
        }
    ],
    "sg:phone":"+1 916 686 3773",
    "sg:postcode":"95624",
    "sg:province":"CA",
    "wof:name":"Citizens Insurance Svc Inc",
    "wof:placetype":"venue"
},
  "geometry": {"coordinates":[-121.381557,38.409063],"type":"Point"}
}