{
  "type": "Feature",
  "properties": {
    "iso:country":"US",
    "sg:address":"29170 Heathercliff Rd",
    "sg:city":"Malibu",
    "sg:classifiers":[
        {
            "category":"Organizations",
            "subcategory":"Community Association",
            "type":"Services"
        }
    ],
    "sg:phone":"+1 310 589 2233",
    "sg:postcode":"90265",
    "sg:province":"CA",
    "sg:tags":[
        "environmental",
        "org"
    ],
    "wof:name":"Childrens Health Environmental",
    "wof:placetype":"venue"
},
  "geometry": {"coordinates":[-118.808746,34.021547],"type":"Point"}
}