{
  "type": "Feature",
  "properties": {
    "addr:full":"73712 Alessandro Dr Palm Desert CA 92260",
    "addr:housenumber":"73712",
    "addr:postcode":"ca 92260",
    "addr:street":"Alessandro Dr",
    "iso:country":"US",
    "sg:address":"73712 Alessandro Dr",
    "sg:city":"Palm Desert",
    "sg:classifiers":[
        {
            "category":"Real Estate",
            "subcategory":"Real Estate Agent",
            "type":"Services"
        }
    ],
    "sg:phone":"+1 760 773 3310",
    "sg:postcode":"92260",
    "sg:province":"CA",
    "sg:website":"www.baxleyproperties.com",
    "wof:name":"Baxley Properties",
    "wof:placetype":"venue"
},
  "geometry": {"coordinates":[-116.379508,33.7221],"type":"Point"}
}