{
  "type": "Feature",
  "properties": {
    "iso:country":"US",
    "sg:address":"529 Martin Ave",
    "sg:city":"Rohnert Park",
    "sg:classifiers":[
        {
            "category":"Manufacturing",
            "subcategory":"Printing",
            "type":"Manufacturing & Wholesale Goods"
        }
    ],
    "sg:phone":"+1 707 586 9122",
    "sg:postcode":"94928",
    "sg:province":"CA",
    "sg:tags":[
        "printer"
    ],
    "sg:website":"www.goldenpacificsystems.com",
    "wof:name":"Golden Pacific Systems Inc",
    "wof:placetype":"venue"
},
  "geometry": {"coordinates":[-122.722328,38.354797],"type":"Point"}
}