{
  "type": "Feature",
  "properties": {
    "iso:country":"US",
    "sg:address":"12109 Ventura Pl",
    "sg:city":"Studio City",
    "sg:classifiers":[
        {
            "category":"Shopping",
            "subcategory":"Hobbies, Toys, & Games",
            "type":"Retail Goods"
        },
        {
            "category":"Shopping",
            "subcategory":"Crafts & Fabrics",
            "type":"Retail Goods"
        }
    ],
    "sg:phone":"+1 818 509 9739",
    "sg:postcode":"91604",
    "sg:province":"CA",
    "sg:tags":[
        "shop",
        "hobby",
        "art",
        "supply"
    ],
    "sg:website":"www.kitkraft.biz/customer/home.php",
    "wof:name":"Kit Kraft Inc",
    "wof:placetype":"venue"
},
  "geometry": {"coordinates":[-118.39547399999999,34.145004],"type":"Point"}
}