{
  "type": "Feature",
  "properties": {
    "addr:full":"4255 Park Rd Benicia CA 94510",
    "addr:housenumber":"4255",
    "addr:postcode":"94510",
    "addr:street":"Park Rd",
    "iso:country":"US",
    "sg:address":"4255 Park Rd",
    "sg:city":"Benicia",
    "sg:classifiers":[
        {
            "category":"Shopping",
            "subcategory":"Used Merchandise",
            "type":"Retail Goods"
        }
    ],
    "sg:phone":"+1 707 745 3810",
    "sg:postcode":"94510",
    "sg:province":"CA",
    "sg:tags":[
        "computer"
    ],
    "wof:name":"It Global Solutions, Inc.",
    "wof:placetype":"venue"
},
  "geometry": {"coordinates":[-122.124657,38.072783],"type":"Point"}
}