{
  "type": "Feature",
  "properties": {
    "addr:full":"1670 Cienega Rd Hollister CA 95023",
    "addr:housenumber":"1670",
    "addr:postcode":"hollister ca 95023",
    "addr:street":"Cienega Rd",
    "iso:country":"US",
    "sg:address":"1670 Cienega Rd",
    "sg:city":"Hollister",
    "sg:classifiers":[
        {
            "category":"Place Of Worship",
            "subcategory":"Church",
            "type":"Public Place"
        },
        {
            "category":"Place Of Worship",
            "type":"Public Place"
        }
    ],
    "sg:phone":"+1 831 637 4917",
    "sg:postcode":"95023",
    "sg:province":"CA",
    "sg:tags":[
        "jesus",
        "churches-church",
        "christ",
        "saint",
        "latter-day"
    ],
    "sg:website":"http://www.lds.org",
    "wof:name":"Church of Jesus Christ of Latter-Day Saints",
    "wof:placetype":"venue"
},
  "geometry": {"coordinates":[-121.40069800000001,36.836887],"type":"Point"}
}