{
  "type": "Feature",
  "properties": {
    "sfgov:dept":"7",
    "sfgov:deptname":"SF Unified School District (SFUSD)",
    "sfgov:facility_i":"0000003231",
    "sfgov:school_typ":"High School",
    "wof:categories":[
        "education_and_religion:education=school"
    ],
    "wof:name":"International Studies Academy",
    "wof:placetype":"venue"
},
  "geometry": {"coordinates":[-122.4008049714524,37.76182550083592],"type":"Point"}
}