{
  "type": "Feature",
  "properties": {
    "addr:full":"285 Van Buren Ave #4 Oakland CA 94610",
    "addr:housenumber":"285",
    "addr:postcode":"94610",
    "addr:street":"Van Buren Ave # 4",
    "iso:country":"US",
    "sg:address":"285 Van Buren Ave #4",
    "sg:city":"Oakland",
    "sg:classifiers":[
        {
            "category":"Professional",
            "type":"Services"
        }
    ],
    "sg:phone":"+1 510 435 0703",
    "sg:postcode":"94610",
    "sg:province":"CA",
    "sg:tags":[
        "caterer"
    ],
    "sg:website":"swankycatering.com",
    "wof:name":"Swanky Catering and Events",
    "wof:placetype":"venue"
},
  "geometry": {"coordinates":[-122.269722,37.804444],"type":"Point"}
}