{
  "type": "Feature",
  "properties": {
    "addr:full":"1905 San Pablo Ave Oakland CA 94612",
    "addr:housenumber":"1905",
    "addr:postcode":"94612",
    "addr:street":"San Pablo Ave",
    "iso:country":"US",
    "sg:address":"1905 San Pablo Ave",
    "sg:city":"Oakland",
    "sg:classifiers":[
        {
            "category":"Restaurant",
            "type":"Food & Drink"
        }
    ],
    "sg:phone":"+1 510 406 7319",
    "sg:postcode":"94612",
    "sg:province":"CA",
    "sg:tags":[
        "barbeque"
    ],
    "wof:name":"Up Town Bbq",
    "wof:placetype":"venue"
},
  "geometry": {"coordinates":[-122.273048,37.809132],"type":"Point"}
}