{
  "type": "Feature",
  "properties": {
    "addr:full":"402 Virginia St Vallejo CA 94590",
    "addr:housenumber":"402",
    "addr:postcode":"94590",
    "addr:street":"Virginia St",
    "iso:country":"US",
    "sg:address":"402 Virginia St",
    "sg:city":"Vallejo",
    "sg:classifiers":[
        {
            "category":"Personal",
            "subcategory":"Shoe Repair & Shine",
            "type":"Services"
        }
    ],
    "sg:phone":"+1 707 642 6780",
    "sg:postcode":"94590",
    "sg:province":"CA",
    "sg:tags":[
        "repairing",
        "boot"
    ],
    "wof:name":"Johnson Deluxe Shoe Svc",
    "wof:placetype":"venue"
},
  "geometry": {"coordinates":[-122.25494500000001,38.102164],"type":"Point"}
}