{
  "type": "Feature",
  "properties": {
    "iso:country":"US",
    "sg:address":"1046 Coast Village Rd",
    "sg:city":"Santa Barbara",
    "sg:classifiers":[
        {
            "category":"Shopping",
            "subcategory":"Clothing, Apparel, & Fashions",
            "type":"Retail Goods"
        }
    ],
    "sg:phone":"+1 805 969 1515",
    "sg:postcode":"93108",
    "sg:province":"CA",
    "sg:website":"www.antoinette.com",
    "wof:name":"Antoinette",
    "wof:placetype":"venue"
},
  "geometry": {"coordinates":[-119.65123800000001,34.421929],"type":"Point"}
}