{
  "type": "Feature",
  "properties": {
    "iso:country":"US",
    "sg:address":"1151 E 10th St",
    "sg:city":"Long Beach",
    "sg:classifiers":[
        {
            "category":"Cinema",
            "subcategory":"Movie Rental",
            "type":"Entertainment"
        }
    ],
    "sg:phone":"+1 562 218 0703",
    "sg:postcode":"90813",
    "sg:province":"CA",
    "sg:tags":[
        "leasing",
        "video",
        "disc",
        "tape"
    ],
    "wof:name":"Trc Video Rental",
    "wof:placetype":"venue"
},
  "geometry": {"coordinates":[-118.17742200000001,33.779041],"type":"Point"}
}