{
  "type": "Feature",
  "properties": {
    "addr:full":"4001 Judah Street, San Francisco, CA, USA",
    "addr:housenumber":4001,
    "addr:phone":"415-661-6140",
    "addr:postcode":"94122",
    "addr:street":"Judah Street",
    "addr:website":"http://outerlandssf.com/",
    "iso:country":"US",
    "name:eng_x_preferred":[
        "Outerlands"
    ],
    "wof:name":"Outerlands",
    "wof:placetype":"venue"
},
  "geometry": {"coordinates":[-122.50500599999999,37.76035],"type":"Point"}
}