{
  "type": "Feature",
  "properties": {
    "addr:full":"2727 Newport Blvd Ste 300 Newport Beach CA 92663",
    "addr:housenumber":"2727",
    "addr:postcode":"92663",
    "addr:street":"Newport Blvd Ste 300",
    "iso:country":"US",
    "sg:address":"2727 Newport Blvd Ste 300",
    "sg:city":"Newport Beach",
    "sg:classifiers":[
        {
            "category":"Donuts",
            "subcategory":"None",
            "type":"Food & Drink"
        }
    ],
    "sg:phone":"+1 949 295 3747",
    "sg:postcode":"92663",
    "sg:province":"CA",
    "wof:name":"Citi Donut",
    "wof:placetype":"venue"
},
  "geometry": {"coordinates":[-117.92996599999999,33.612264],"type":"Point"}
}