{
  "type": "Feature",
  "properties": {
    "addr:full":"2044 N Mount Vernon Ave San Bernardino CA 92411",
    "addr:housenumber":"2044",
    "addr:postcode":"92411",
    "addr:street":"N Mount Vernon Ave",
    "iso:country":"US",
    "sg:address":"2044 N Mount Vernon Ave",
    "sg:city":"San Bernardino",
    "sg:classifiers":[
        {
            "category":"Retail",
            "subcategory":"Auto Repair",
            "type":"Services"
        }
    ],
    "sg:phone":"+1 909 880 3966",
    "sg:postcode":"92411",
    "sg:province":"CA",
    "sg:tags":[
        "wrecker"
    ],
    "wof:name":"Sea Towing",
    "wof:placetype":"venue"
},
  "geometry": {"coordinates":[-117.313907,34.133038],"type":"Point"}
}