{
  "type": "Feature",
  "properties": {
    "addr:full":"350 S Washington St Sonora CA 95370",
    "addr:housenumber":"350",
    "addr:postcode":"95370",
    "addr:street":"S Washington St",
    "iso:country":"US",
    "sg:address":"350 S Washington St",
    "sg:city":"Sonora",
    "sg:classifiers":[
        {
            "category":"Travel",
            "subcategory":"Hotels & Motels",
            "type":"Entertainment"
        }
    ],
    "sg:phone":"+1 209 532 3633",
    "sg:postcode":"95370",
    "sg:province":"CA",
    "sg:tags":[
        "lodging"
    ],
    "sg:website":"http://www.sonorainnsofcalifornia.com",
    "wof:name":"Inns Of California",
    "wof:placetype":"venue"
},
  "geometry": {"coordinates":[-120.38163400000001,37.980243],"type":"Point"}
}