{
  "type": "Feature",
  "properties": {
    "iso:country":"US",
    "sg:address":"201 Vallecito Ln",
    "sg:city":"Walnut Creek",
    "sg:classifiers":[
        {
            "category":"Professional",
            "subcategory":"Management & Consulting",
            "type":"Services"
        }
    ],
    "sg:phone":"+1 925 930 9436",
    "sg:postcode":"94596",
    "sg:province":"CA",
    "sg:tags":[
        "consultant",
        "business"
    ],
    "wof:name":"Silver Bullet Group Inc",
    "wof:placetype":"venue"
},
  "geometry": {"coordinates":[-122.03684199999999,37.887481],"type":"Point"}
}