{
  "type": "Feature",
  "properties": {
    "addr:full":"540 Ashbury Ave El Cerrito CA 94530",
    "addr:housenumber":"540",
    "addr:postcode":"94530",
    "addr:street":"Ashbury Ave",
    "iso:country":"US",
    "sg:address":"540 Ashbury Ave",
    "sg:city":"El Cerrito",
    "sg:classifiers":[
        {
            "category":"Education",
            "subcategory":"School",
            "type":"Public Place"
        }
    ],
    "sg:phone":"+1 510 528 7088",
    "sg:postcode":"94530",
    "sg:province":"CA",
    "sg:website":"www.techfutures.org",
    "wof:name":"Whittier Education Foundation",
    "wof:placetype":"venue"
},
  "geometry": {"coordinates":[-122.29387699999999,37.906669],"type":"Point"}
}