{
  "type": "Feature",
  "properties": {
    "addr:full":"7835 Rio Linda Blvd Elverta CA 95626",
    "addr:housenumber":"7835",
    "addr:postcode":"ca 95626",
    "addr:street":"Rio Linda Blvd",
    "iso:country":"US",
    "sg:address":"7835 Rio Linda Blvd",
    "sg:city":"Elverta",
    "sg:classifiers":[
        {
            "category":"Food & Beverages",
            "subcategory":"Groceries & Convenience Stores",
            "type":"Retail Goods"
        }
    ],
    "sg:phone":"+1 916 991 3241",
    "sg:postcode":"95626",
    "sg:province":"CA",
    "sg:tags":[
        "grocer"
    ],
    "wof:name":"Elverta Market",
    "wof:placetype":"venue"
},
  "geometry": {"coordinates":[-121.460971,38.709994],"type":"Point"}
}