{
  "type": "Feature",
  "properties": {
    "addr:full":"19053 Ingomar St Reseda CA 91335",
    "addr:postcode":"19053;91335",
    "addr:street":"Ingomar St",
    "iso:country":"US",
    "sg:address":"19053 Ingomar St",
    "sg:city":"Reseda",
    "sg:classifiers":[
        {
            "category":"Organizations",
            "subcategory":"Religious Organization",
            "type":"Services"
        }
    ],
    "sg:phone":"+1 818 885 8300",
    "sg:postcode":"91335",
    "sg:province":"CA",
    "sg:tags":[
        "church"
    ],
    "wof:name":"Christadelphian Ecclesia",
    "wof:placetype":"venue"
},
  "geometry": {"coordinates":[-118.547526,34.212077],"type":"Point"}
}