{
  "type": "Feature",
  "properties": {
    "addr:full":"1632 Edgeworth Ave Daly City CA 94015",
    "addr:housenumber":"1632",
    "addr:postcode":"94015",
    "addr:street":"Edgeworth Ave",
    "iso:country":"US",
    "sg:address":"1632 Edgeworth Ave",
    "sg:city":"Daly City",
    "sg:classifiers":[
        {
            "category":"Wholesale",
            "subcategory":"Plants",
            "type":"Manufacturing & Wholesale Goods"
        }
    ],
    "sg:phone":"+1 650 755 4364",
    "sg:postcode":"94015",
    "sg:province":"CA",
    "sg:tags":[
        "nursery",
        "tree"
    ],
    "wof:name":"John's Nursery",
    "wof:placetype":"venue"
},
  "geometry": {"coordinates":[-122.474374,37.68663],"type":"Point"}
}