{
  "type": "Feature",
  "properties": {
    "addr:full":"2415 Creston Dr Los Angeles CA 90068",
    "addr:housenumber":"2415",
    "addr:postcode":"90068",
    "addr:street":"Creston Dr",
    "iso:country":"US",
    "sg:address":"2415 Creston Dr",
    "sg:city":"Los Angeles",
    "sg:classifiers":[
        {
            "category":"Shopping",
            "subcategory":"Florist",
            "type":"Retail Goods"
        }
    ],
    "sg:phone":"+1 310 837 4173",
    "sg:postcode":"90068",
    "sg:province":"CA",
    "wof:name":"Floral Works",
    "wof:placetype":"venue"
},
  "geometry": {"coordinates":[-118.324856,34.114299],"type":"Point"}
}