{
  "type": "Feature",
  "properties": {
    "addr:full":"1900 W Slauson Ave Los Angeles CA 90047",
    "addr:housenumber":"1900",
    "addr:postcode":"90047",
    "addr:street":"W Slauson Ave",
    "iso:country":"US",
    "sg:address":"1900 W Slauson Ave",
    "sg:city":"Los Angeles",
    "sg:classifiers":[
        {
            "category":"Wholesale",
            "subcategory":"Groceries",
            "type":"Manufacturing & Wholesale Goods"
        }
    ],
    "sg:phone":"+1 323 298 4828",
    "sg:postcode":"90047",
    "sg:province":"CA",
    "wof:name":"Kraft Foods",
    "wof:placetype":"venue"
},
  "geometry": {"coordinates":[-118.31259,33.989121],"type":"Point"}
}