{
  "type": "Feature",
  "properties": {
    "iso:country":"US",
    "sg:address":"2117 Stoneridge Mall Rd",
    "sg:city":"Pleasanton",
    "sg:classifiers":[
        {
            "category":"Shopping",
            "subcategory":"Shoes",
            "type":"Retail Goods"
        }
    ],
    "sg:phone":"+1 925 463 2877",
    "sg:postcode":"94588",
    "sg:province":"CA",
    "wof:name":"Lady Foot Locker",
    "wof:placetype":"venue"
},
  "geometry": {"coordinates":[-121.929682,37.698011],"type":"Point"}
}