{
  "type": "Feature",
  "properties": {
    "iso:country":"US",
    "sg:address":"374 University Ave",
    "sg:city":"Palo Alto",
    "sg:classifiers":[
        {
            "category":"Professional",
            "type":"Services"
        }
    ],
    "sg:phone":"+1 650 321 8108",
    "sg:postcode":"94301",
    "sg:province":"CA",
    "wof:name":"Voshan",
    "wof:placetype":"venue"
},
  "geometry": {"coordinates":[-122.160587,37.446753],"type":"Point"}
}