{
  "type": "Feature",
  "properties": {
    "addr:full":"215 E Daily Dr Camarillo CA 93010",
    "addr:housenumber":"215",
    "addr:postcode":"93010",
    "addr:street":"E Daily Dr",
    "iso:country":"US",
    "sg:address":"215 E Daily Dr",
    "sg:city":"Camarillo",
    "sg:classifiers":[
        {
            "category":"Personal",
            "subcategory":"Nail Salon",
            "type":"Services"
        }
    ],
    "sg:phone":"+1 805 482 4106",
    "sg:postcode":"93010",
    "sg:province":"CA",
    "wof:name":"Mystical Nails",
    "wof:placetype":"venue"
},
  "geometry": {"coordinates":[-119.06698799999999,34.220268],"type":"Point"}
}