{
  "type": "Feature",
  "properties": {
    "addr:full":"1201 Truman St San Fernando CA 91340",
    "addr:housenumber":"1201",
    "addr:postcode":"91340",
    "addr:street":"Truman St",
    "iso:country":"US",
    "sg:address":"1201 Truman St",
    "sg:city":"San Fernando",
    "sg:classifiers":[
        {
            "category":"Banks & Credit Unions",
            "subcategory":"Bank",
            "type":"Services"
        }
    ],
    "sg:phone":"+1 818 408 3100",
    "sg:postcode":"91340",
    "sg:province":"CA",
    "sg:tags":[
        "financing"
    ],
    "wof:name":"Olympic Funding",
    "wof:placetype":"venue"
},
  "geometry": {"coordinates":[-118.444945,34.286848],"type":"Point"}
}