{
  "type": "Feature",
  "properties": {
    "iso:country":"US",
    "sg:address":"981 S Saticoy Ave",
    "sg:city":"Ventura",
    "sg:classifiers":[
        {
            "category":"Building & Trades",
            "subcategory":"Construction",
            "type":"Services"
        }
    ],
    "sg:phone":"+1 805 647 0503",
    "sg:postcode":"93004",
    "sg:province":"CA",
    "sg:tags":[
        "nonresidential"
    ],
    "wof:name":"Prestige Heavy Equipment",
    "wof:placetype":"venue"
},
  "geometry": {"coordinates":[-119.15983199999999,34.28123],"type":"Point"}
}