{
  "type": "Feature",
  "properties": {
    "iso:country":"US",
    "sg:address":"9863 Pacific Heights Blvd",
    "sg:city":"San Diego",
    "sg:classifiers":[
        {
            "category":"Professional",
            "subcategory":"Research",
            "type":"Services"
        }
    ],
    "sg:phone":"+1 858 625 0441",
    "sg:postcode":"92121",
    "sg:province":"CA",
    "sg:tags":[
        "laboratory"
    ],
    "wof:name":"A & A Lab",
    "wof:placetype":"venue"
},
  "geometry": {"coordinates":[-117.188574,32.898217],"type":"Point"}
}