{
  "type": "Feature",
  "properties": {
    "iso:country":"US",
    "sg:address":"720 Pacific Coast Hwy",
    "sg:city":"Huntington Beach",
    "sg:classifiers":[
        {
            "category":"Travel",
            "subcategory":"Hotels & Motels",
            "type":"Entertainment"
        }
    ],
    "sg:phone":"+1 714 536 2444",
    "sg:postcode":"92648",
    "sg:province":"CA",
    "sg:website":"www.huntingtonsurfinn.com",
    "wof:name":"Huntington Surf Inn",
    "wof:placetype":"venue"
},
  "geometry": {"coordinates":[-118.004853,33.659399],"type":"Point"}
}