{
  "type": "Feature",
  "properties": {
    "iso:country":"US",
    "sg:address":"2003 20th St",
    "sg:city":"Bakersfield",
    "sg:classifiers":[
        {
            "category":"Professional",
            "subcategory":"Engineering",
            "type":"Services"
        }
    ],
    "sg:phone":"+1 661 326 1543",
    "sg:postcode":"93301",
    "sg:province":"CA",
    "sg:tags":[
        "engineer"
    ],
    "wof:name":"Jerry L Hendricks Consulting",
    "wof:placetype":"venue"
},
  "geometry": {"coordinates":[-119.02582099999999,35.377142],"type":"Point"}
}