{
  "type": "Feature",
  "properties": {
    "addr:full":"1527 E Washington Blvd Pasadena CA 91104",
    "addr:housenumber":"1527",
    "addr:postcode":"91104",
    "addr:street":"E Washington Blvd",
    "iso:country":"US",
    "sg:address":"1527 E Washington Blvd",
    "sg:city":"Pasadena",
    "sg:classifiers":[
        {
            "category":"Shopping",
            "subcategory":"Computers & Home Electronics",
            "type":"Retail Goods"
        }
    ],
    "sg:phone":"+1 626 794 2027",
    "sg:postcode":"91104",
    "sg:province":"CA",
    "sg:tags":[
        "repair",
        "television",
        "appliance",
        "radio"
    ],
    "wof:name":"Jack's Tv Repair",
    "wof:placetype":"venue"
},
  "geometry": {"coordinates":[-118.11900300000001,34.169201],"type":"Point"}
}