{
  "type": "Feature",
  "properties": {
    "addr:full":"160 Cll Magdalena Encinitas CA 92024",
    "addr:housenumber":"160",
    "addr:postcode":"92024",
    "addr:street":"Cll Magdalena",
    "iso:country":"US",
    "sg:address":"160 Cll Magdalena",
    "sg:city":"Encinitas",
    "sg:classifiers":[
        {
            "category":"Autos & Motor Vehicles",
            "subcategory":"Automobile Sales",
            "type":"Retail Goods"
        },
        {
            "category":"Autos & Motor Vehicles",
            "subcategory":"Auto Supplies",
            "type":"Retail Goods"
        }
    ],
    "sg:phone":"+1 760 942 1717",
    "sg:postcode":"92024",
    "sg:province":"CA",
    "sg:tags":[
        "new",
        "used",
        "parts"
    ],
    "sg:website":"www.mossy.com",
    "wof:name":"Mossy Chevrolet Inc",
    "wof:placetype":"venue"
},
  "geometry": {"coordinates":[-117.283992,33.046874],"type":"Point"}
}