{
  "type": "Feature",
  "properties": {
    "addr:full":"33025 Rd 159 Ivanhoe CA 93235",
    "addr:postcode":"33025;93235",
    "addr:street":"Rd 159",
    "iso:country":"US",
    "sg:address":"33025 Rd 159",
    "sg:city":"Ivanhoe",
    "sg:classifiers":[
        {
            "category":"Health Services",
            "subcategory":"Doctor",
            "type":"Services"
        }
    ],
    "sg:phone":"+1 559 798 1877",
    "sg:postcode":"93235",
    "sg:province":"CA",
    "sg:tags":[
        "medical"
    ],
    "wof:name":"Family Healthcare Network",
    "wof:placetype":"venue"
},
  "geometry": {"coordinates":[-119.218053,36.389289],"type":"Point"}
}