{
  "type": "Feature",
  "properties": {
    "addr:full":"1019 6th St Los Banos CA 93635",
    "addr:housenumber":"1019",
    "addr:postcode":"93635",
    "addr:street":"6Th St",
    "iso:country":"US",
    "sg:address":"1019 6th St",
    "sg:city":"Los Banos",
    "sg:classifiers":[
        {
            "category":"Shopping",
            "subcategory":"Jewelry",
            "type":"Retail Goods"
        }
    ],
    "sg:phone":"+1 209 826 4840",
    "sg:postcode":"93635",
    "sg:province":"CA",
    "sg:tags":[
        "jeweler"
    ],
    "wof:name":"Pereira Jewelers",
    "wof:placetype":"venue"
},
  "geometry": {"coordinates":[-120.84874000000001,37.05983],"type":"Point"}
}