{
  "type": "Feature",
  "properties": {
    "iso:country":"US",
    "sg:address":"859 Shore Breeze Dr",
    "sg:city":"Sacramento",
    "sg:classifiers":[
        {
            "category":"Organizations",
            "subcategory":"Membership Organization",
            "type":"Services"
        }
    ],
    "sg:phone":"+1 916 393 1377",
    "sg:postcode":"95831",
    "sg:province":"CA",
    "sg:tags":[
        "athletic"
    ],
    "wof:name":"Warlords Basketball Program",
    "wof:placetype":"venue"
},
  "geometry": {"coordinates":[-121.524416,38.478974],"type":"Point"}
}