{
  "type": "Feature",
  "properties": {
    "addr:full":"1448 15th St Santa Monica CA 90404",
    "addr:housenumber":"1448",
    "addr:postcode":"90404",
    "addr:street":"15Th St",
    "iso:country":"US",
    "sg:address":"1448 15th St",
    "sg:city":"Santa Monica",
    "sg:classifiers":[
        {
            "category":"Health Services",
            "subcategory":"Health Practitioner",
            "type":"Services"
        }
    ],
    "sg:phone":"+1 310 451 2107",
    "sg:postcode":"90404",
    "sg:province":"CA",
    "sg:tags":[
        "psychologist"
    ],
    "wof:name":"Ocean Psychological Svc",
    "wof:placetype":"venue"
},
  "geometry": {"coordinates":[-118.483902,34.024121],"type":"Point"}
}