{
  "type": "Feature",
  "properties": {
    "iso:country":"US",
    "sg:address":"9970 Bell Ranch Dr",
    "sg:city":"Santa Fe Springs",
    "sg:classifiers":[
        {
            "category":"Professional",
            "subcategory":"Advertising",
            "type":"Services"
        },
        {
            "category":"Manufacturing",
            "subcategory":"Printing",
            "type":"Manufacturing & Wholesale Goods"
        }
    ],
    "sg:phone":"+1 562 777 7162",
    "sg:postcode":"90670",
    "sg:province":"CA",
    "sg:tags":[
        "consulting",
        "periodical",
        "business"
    ],
    "wof:name":"Trader Publishing Company",
    "wof:placetype":"venue"
},
  "geometry": {"coordinates":[-118.063913,33.947635],"type":"Point"}
}