{
  "type": "Feature",
  "properties": {
    "addr:full":"The Uptown 1928 Telegraph Ave Oakland CA 94612",
    "addr:housenumber":"1928",
    "addr:postcode":"94612",
    "addr:street":"Telegraph Ave",
    "iso:country":"US",
    "sg:address":"The Uptown 1928 Telegraph Ave",
    "sg:city":"Oakland",
    "sg:classifiers":[
        {
            "category":"Bars & Pubs",
            "subcategory":"Nightclub",
            "type":"Food & Drink"
        }
    ],
    "sg:postcode":"94612",
    "sg:province":"CA",
    "sg:tags":[
        "nightlife"
    ],
    "sg:website":"hellagayoakland.com/",
    "wof:name":"Hella Gay Dance Party",
    "wof:placetype":"venue"
},
  "geometry": {"coordinates":[-122.269848,37.80848],"type":"Point"}
}