{
  "type": "Feature",
  "properties": {
    "iso:country":"US",
    "sg:address":"2981 Michelson Dr",
    "sg:city":"Irvine",
    "sg:classifiers":[
        {
            "category":"Restaurant",
            "type":"Food & Drink"
        }
    ],
    "sg:phone":"+1 949 251 0555",
    "sg:postcode":"92612",
    "sg:province":"CA",
    "sg:tags":[
        "japanese"
    ],
    "sg:website":"www.mizukirestaurant.com/",
    "wof:name":"Mizuki Japanese Cuisine & Noodles",
    "wof:placetype":"venue"
},
  "geometry": {"coordinates":[-117.844748,33.670974],"type":"Point"}
}