{
  "type": "Feature",
  "properties": {
    "addr:full":"21658 Sedco Heights Rd Wildomar CA 92595",
    "addr:postcode":"21658;92595",
    "addr:street":"Sedco Heights Rd",
    "iso:country":"US",
    "sg:address":"21658 Sedco Heights Rd",
    "sg:city":"Wildomar",
    "sg:classifiers":[
        {
            "category":"Building & Trades",
            "subcategory":"Equipment Rental",
            "type":"Services"
        }
    ],
    "sg:phone":"+1 951 245 6388",
    "sg:postcode":"92595",
    "sg:province":"CA",
    "sg:tags":[
        "contractor"
    ],
    "wof:name":"K E Patterson Co",
    "wof:placetype":"venue"
},
  "geometry": {"coordinates":[-117.27802200000001,33.651435],"type":"Point"}
}