{
  "type": "Feature",
  "properties": {
    "addr:full":"25798 N Mooney Blvd Tulare CA 93274",
    "addr:housenumber":"25798",
    "addr:postcode":"93274",
    "addr:street":"N Mooney Blvd",
    "iso:country":"US",
    "sg:address":"25798 N Mooney Blvd",
    "sg:city":"Tulare",
    "sg:classifiers":[
        {
            "category":"Professional",
            "type":"Services"
        }
    ],
    "sg:phone":"+1 559 687 8305",
    "sg:postcode":"93274",
    "sg:province":"CA",
    "wof:name":"Grow Quest",
    "wof:placetype":"venue"
},
  "geometry": {"coordinates":[-119.313007,36.258552],"type":"Point"}
}