{
  "type": "Feature",
  "properties": {
    "addr:full":"990 S 4th St Kerman CA 93630",
    "addr:housenumber":"990",
    "addr:postcode":"93630",
    "addr:street":"S 4Th St",
    "iso:country":"US",
    "sg:address":"990 S 4th St",
    "sg:city":"Kerman",
    "sg:classifiers":[
        {
            "category":"Place Of Worship",
            "subcategory":"Church",
            "type":"Public Place"
        },
        {
            "category":"Place Of Worship",
            "type":"Public Place"
        },
        {
            "category":"Organizations",
            "subcategory":"Religious Organization",
            "type":"Services"
        }
    ],
    "sg:phone":"+1 559 846 3644",
    "sg:postcode":"93630",
    "sg:province":"CA",
    "sg:tags":[
        "god",
        "denomination",
        "churches-church",
        "churches-pentecostal",
        "churches-interdenominational",
        "churches-various"
    ],
    "sg:website":"http://www.cogop.org",
    "wof:name":"Church Of God Of Prophecy State Office",
    "wof:placetype":"venue"
},
  "geometry": {"coordinates":[-120.061605,36.720712],"type":"Point"}
}