{
  "type": "Feature",
  "properties": {
    "addr:full":"16019 E Foothill Blvd Irwindale CA 91702",
    "addr:housenumber":"16019",
    "addr:postcode":"91702",
    "addr:street":"E Foothill Blvd",
    "iso:country":"US",
    "sg:address":"16019 E Foothill Blvd",
    "sg:city":"Irwindale",
    "sg:classifiers":[
        {
            "category":"Manufacturing",
            "subcategory":"Tools & Machinery",
            "type":"Manufacturing & Wholesale Goods"
        }
    ],
    "sg:phone":"+1 626 969 7647",
    "sg:postcode":"91702",
    "sg:province":"CA",
    "sg:tags":[
        "electrical",
        "apparatus"
    ],
    "wof:name":"Reliance Electric",
    "wof:placetype":"venue"
},
  "geometry": {"coordinates":[-117.892747,34.133528],"type":"Point"}
}