{
  "type": "Feature",
  "properties": {
    "iso:country":"US",
    "sg:address":"1169 N Riverside Ave",
    "sg:city":"Rialto",
    "sg:classifiers":[
        {
            "category":"Restaurant",
            "type":"Food & Drink"
        }
    ],
    "sg:phone":"+1 909 421 2001",
    "sg:postcode":"92376",
    "sg:province":"CA",
    "wof:name":"Mexico Viejo",
    "wof:placetype":"venue"
},
  "geometry": {"coordinates":[-117.370412,34.118095],"type":"Point"}
}