{
  "type": "Feature",
  "properties": {
    "addr:full":"2959 Summit Dr Escondido CA 92025",
    "addr:housenumber":"2959",
    "addr:postcode":"92025",
    "addr:street":"Summit Dr",
    "iso:country":"US",
    "sg:address":"2959 Summit Dr",
    "sg:city":"Escondido",
    "sg:classifiers":[
        {
            "category":"Building & Trades",
            "subcategory":"Equipment Rental",
            "type":"Services"
        }
    ],
    "sg:phone":"+1 760 747 5787",
    "sg:postcode":"92025",
    "sg:province":"CA",
    "sg:tags":[
        "contractor"
    ],
    "wof:name":"America's Finest Backhoe Svc",
    "wof:placetype":"venue"
},
  "geometry": {"coordinates":[-117.038115,33.093677],"type":"Point"}
}