{
  "type": "Feature",
  "properties": {
    "addr:full":"804 1/2 Park Ave Newport Beach CA 92662",
    "addr:housenumber":"804 1 / 2",
    "addr:postcode":"92662",
    "addr:street":"Park Ave",
    "iso:country":"US",
    "sg:address":"804 1/2 Park Ave",
    "sg:city":"Newport Beach",
    "sg:classifiers":[
        {
            "category":"Personal",
            "type":"Services"
        }
    ],
    "sg:phone":"+1 714 724 4243",
    "sg:postcode":"92662",
    "sg:province":"CA",
    "sg:tags":[
        "party",
        "planning",
        "event"
    ],
    "wof:name":"The Blooming Branch",
    "wof:placetype":"venue"
},
  "geometry": {"coordinates":[-117.893686,33.605808],"type":"Point"}
}