{
  "type": "Feature",
  "properties": {
    "iso:country":"US",
    "sg:address":"14315 Pipeline Ave",
    "sg:city":"Chino",
    "sg:classifiers":[
        {
            "category":"Personal",
            "type":"Services"
        }
    ],
    "sg:phone":"+1 209 824 8877",
    "sg:postcode":"91710",
    "sg:province":"CA",
    "sg:tags":[
        "car",
        "loading",
        "unloading"
    ],
    "wof:name":"Dirksen Transportation",
    "wof:placetype":"venue"
},
  "geometry": {"coordinates":[-117.715175,33.992676],"type":"Point"}
}