{
  "type": "Feature",
  "properties": {
    "iso:country":"US",
    "sg:address":"2250 W Main St",
    "sg:city":"Visalia",
    "sg:classifiers":[
        {
            "category":"Professional",
            "type":"Services"
        }
    ],
    "sg:phone":"+1 559 625 8081",
    "sg:postcode":"93291",
    "sg:province":"CA",
    "sg:tags":[
        "establishment"
    ],
    "wof:name":"DAP Mueller & Assoc Inc",
    "wof:placetype":"venue"
},
  "geometry": {"coordinates":[-119.31632999999999,36.329815],"type":"Point"}
}