{
  "type": "Feature",
  "properties": {
    "addr:full":"2206 Wedgewood Way Livermore CA 94550",
    "addr:housenumber":"2206",
    "addr:postcode":"94550",
    "addr:street":"Wedgewood Way",
    "iso:country":"US",
    "sg:address":"2206 Wedgewood Way",
    "sg:city":"Livermore",
    "sg:classifiers":[
        {
            "category":"Manufacturing",
            "subcategory":"Electronics",
            "type":"Manufacturing & Wholesale Goods"
        }
    ],
    "sg:phone":"+1 925 449 6084",
    "sg:postcode":"94550",
    "sg:province":"CA",
    "sg:tags":[
        "printed",
        "circuit",
        "etched"
    ],
    "wof:name":"Cordova Printed Circuits",
    "wof:placetype":"venue"
},
  "geometry": {"coordinates":[-121.77597900000001,37.657963],"type":"Point"}
}