{
  "type": "Feature",
  "properties": {
    "iso:country":"US",
    "sg:address":"2237 Park Avenue",
    "sg:city":"Tustin",
    "sg:classifiers":[
        {
            "category":"Shopping",
            "subcategory":"Pets & Pet Supplies",
            "type":"Retail Goods"
        }
    ],
    "sg:phone":"+1 714 258 8564",
    "sg:postcode":"92782",
    "sg:province":"CA",
    "sg:tags":[
        "store"
    ],
    "sg:website":"www.petsmart.com",
    "wof:name":"Petsmart",
    "wof:placetype":"venue"
},
  "geometry": {"coordinates":[-117.761208,33.716377],"type":"Point"}
}