{
  "type": "Feature",
  "properties": {
    "addr:full":"6350 Winter Park Ct Phelan CA 92371",
    "addr:housenumber":"6350",
    "addr:postcode":"92371",
    "addr:street":"Winter Park Ct",
    "iso:country":"US",
    "sg:address":"6350 Winter Park Ct",
    "sg:city":"Phelan",
    "sg:classifiers":[
        {
            "category":"Professional",
            "subcategory":"Detective & Security Services",
            "type":"Services"
        }
    ],
    "sg:phone":"+1 760 868 0020",
    "sg:postcode":"92371",
    "sg:province":"CA",
    "sg:tags":[
        "investigator"
    ],
    "wof:name":"Tenancious Investigative Svc",
    "wof:placetype":"venue"
},
  "geometry": {"coordinates":[-117.52412200000001,34.421825],"type":"Point"}
}