{
  "type": "Feature",
  "properties": {
    "addr:full":"1018 Trent Lane Kings Beach CA 96148",
    "addr:housenumber":"1018",
    "addr:postcode":"96148",
    "addr:street":"Trent Lane",
    "iso:country":"US",
    "sg:address":"1018 Trent Lane",
    "sg:city":"Kings Beach",
    "sg:classifiers":[
        {
            "category":"Travel",
            "subcategory":"Hotels & Motels",
            "type":"Entertainment"
        }
    ],
    "sg:phone":"+1 707 865 1572",
    "sg:postcode":"96148",
    "sg:province":"CA",
    "sg:tags":[
        "house",
        "guest"
    ],
    "sg:website":"www.sterba.com/river/trent/",
    "wof:name":"The Trent House",
    "wof:placetype":"venue"
},
  "geometry": {"coordinates":[-120.031988,39.254401],"type":"Point"}
}