{
  "type": "Feature",
  "properties": {
    "iso:country":"US",
    "sg:address":"2289 Bonifacio St",
    "sg:city":"Concord",
    "sg:classifiers":[
        {
            "category":"Real Estate",
            "subcategory":"Architect",
            "type":"Services"
        }
    ],
    "sg:phone":"+1 925 692 5888",
    "sg:postcode":"94520",
    "sg:province":"CA",
    "wof:name":"Arete Inc",
    "wof:placetype":"venue"
},
  "geometry": {"coordinates":[-122.034829,37.979912],"type":"Point"}
}