{
  "type": "Feature",
  "properties": {
    "addr:full":"872 Navaronne Way Concord CA 94518",
    "addr:housenumber":"872",
    "addr:postcode":"94518",
    "addr:street":"Navaronne Way",
    "iso:country":"US",
    "sg:address":"872 Navaronne Way",
    "sg:city":"Concord",
    "sg:classifiers":[
        {
            "category":"Building & Trades",
            "subcategory":"Electrical",
            "type":"Services"
        }
    ],
    "sg:phone":"+1 925 363 5358",
    "sg:postcode":"94518",
    "sg:province":"CA",
    "sg:tags":[
        "electric",
        "contractor"
    ],
    "wof:name":"Inter Electric",
    "wof:placetype":"venue"
},
  "geometry": {"coordinates":[-122.01621799999999,37.949387],"type":"Point"}
}