{
  "type": "Feature",
  "properties": {
    "addr:full":"4941 Whitsett Ave Valley Village CA 91607",
    "addr:housenumber":"4941",
    "addr:postcode":"91607",
    "addr:street":"Whitsett Ave",
    "iso:country":"US",
    "sg:address":"4941 Whitsett Ave",
    "sg:city":"Valley Village",
    "sg:classifiers":[
        {
            "category":"Social Services",
            "subcategory":"Child Care",
            "type":"Services"
        }
    ],
    "sg:phone":"+1 818 760 4161",
    "sg:postcode":"91607",
    "sg:province":"CA",
    "sg:tags":[
        "day"
    ],
    "wof:name":"Tiny Clock Productions Inc",
    "wof:placetype":"venue"
},
  "geometry": {"coordinates":[-118.405305,34.159803],"type":"Point"}
}