{
  "type": "Feature",
  "properties": {
    "addr:full":"3810 W Verdugo Ave Burbank CA 91505",
    "addr:housenumber":"3810",
    "addr:postcode":"91505",
    "addr:street":"W Verdugo Ave",
    "iso:country":"US",
    "sg:address":"3810 W Verdugo Ave",
    "sg:city":"Burbank",
    "sg:classifiers":[
        {
            "category":"Personal",
            "subcategory":"Shoe Repair & Shine",
            "type":"Services"
        }
    ],
    "sg:phone":"+1 818 845 4213",
    "sg:postcode":"91505",
    "sg:province":"CA",
    "wof:name":"Victor's Shoe Repair",
    "wof:placetype":"venue"
},
  "geometry": {"coordinates":[-118.344763,34.160609],"type":"Point"}
}