{
  "type": "Feature",
  "properties": {
    "iso:country":"US",
    "sg:address":"74020 Alessandro Dr",
    "sg:city":"Palm Desert",
    "sg:classifiers":[
        {
            "category":"Health Services",
            "subcategory":"Doctor",
            "type":"Services"
        }
    ],
    "sg:phone":"+1 760 773 3737",
    "sg:postcode":"92260",
    "sg:province":"CA",
    "wof:name":"Sanford Michael A MD",
    "wof:placetype":"venue"
},
  "geometry": {"coordinates":[-116.37400100000001,33.722099],"type":"Point"}
}