{
  "type": "Feature",
  "properties": {
    "addr:full":"1412 Fair Way Calistoga CA 94515",
    "addr:housenumber":"1412",
    "addr:postcode":"94515",
    "addr:street":"Fair Way",
    "iso:country":"US",
    "sg:address":"1412 Fair Way",
    "sg:city":"Calistoga",
    "sg:classifiers":[
        {
            "category":"Travel",
            "subcategory":"Hotels & Motels",
            "type":"Entertainment"
        }
    ],
    "sg:phone":"+1 707 942 4108",
    "sg:postcode":"94515",
    "sg:province":"CA",
    "wof:name":"Hideaway Cottages",
    "wof:placetype":"venue"
},
  "geometry": {"coordinates":[-122.581001,38.581902],"type":"Point"}
}