{
  "type": "Feature",
  "properties": {
    "addr:full":"27 Mildenhall St Novato CA 94949",
    "addr:housenumber":"27",
    "addr:postcode":"94949",
    "addr:street":"Mildenhall St",
    "iso:country":"US",
    "sg:address":"27 Mildenhall St",
    "sg:city":"Novato",
    "sg:classifiers":[
        {
            "category":"Professional",
            "subcategory":"Management & Consulting",
            "type":"Services"
        }
    ],
    "sg:phone":"+1 415 235 4323",
    "sg:postcode":"94949",
    "sg:province":"CA",
    "sg:tags":[
        "consultant"
    ],
    "wof:name":"Aviation Consulting Svc",
    "wof:placetype":"venue"
},
  "geometry": {"coordinates":[-122.51364,38.055319],"type":"Point"}
}