{
  "type": "Feature",
  "properties": {
    "addr:full":"1567 N Mahan St Ridgecrest CA 93555",
    "addr:housenumber":"1567",
    "addr:postcode":"93555",
    "addr:street":"N Mahan St",
    "iso:country":"US",
    "sg:address":"1567 N Mahan St",
    "sg:city":"Ridgecrest",
    "sg:classifiers":[
        {
            "category":"Wholesale",
            "subcategory":"Auto Parts",
            "type":"Manufacturing & Wholesale Goods"
        },
        {
            "category":"Wholesale",
            "subcategory":"Scrap",
            "type":"Manufacturing & Wholesale Goods"
        }
    ],
    "sg:phone":"+1 760 446 4592",
    "sg:postcode":"93555",
    "sg:province":"CA",
    "sg:tags":[
        "automobile",
        "material",
        "wrecking"
    ],
    "wof:name":"Speedway Auto Dismanteling",
    "wof:placetype":"venue"
},
  "geometry": {"coordinates":[-117.69668900000001,35.649263],"type":"Point"}
}