{
  "type": "Feature",
  "properties": {
    "iso:country":"US",
    "sg:address":"312 Abbott St",
    "sg:city":"Salinas",
    "sg:classifiers":[
        {
            "category":"Retail",
            "subcategory":"Repair Shop",
            "type":"Services"
        }
    ],
    "sg:phone":"+1 831 757 0109",
    "sg:postcode":"93901",
    "sg:province":"CA",
    "sg:tags":[
        "welding"
    ],
    "wof:name":"Fx Mckenna Welding & Mechanica",
    "wof:placetype":"venue"
},
  "geometry": {"coordinates":[-121.64444899999999,36.666115],"type":"Point"}
}