{
  "type": "Feature",
  "properties": {
    "iso:country":"US",
    "sg:address":"929 N Las Palmas Ave",
    "sg:city":"Los Angeles",
    "sg:classifiers":[
        {
            "category":"Education",
            "subcategory":"School",
            "type":"Public Place"
        }
    ],
    "sg:phone":"+1 323 464 3174",
    "sg:postcode":"90038",
    "sg:province":"CA",
    "sg:tags":[
        "high",
        "middle",
        "elementary"
    ],
    "wof:name":"Bancroft Junior High School",
    "wof:placetype":"venue"
},
  "geometry": {"coordinates":[-118.335999,34.0881],"type":"Point"}
}