{
  "type": "Feature",
  "properties": {
    "addr:full":"293 W Noble Ave Visalia CA 93277",
    "addr:housenumber":"293",
    "addr:postcode":"93277",
    "addr:street":"W Noble Ave",
    "iso:country":"US",
    "sg:address":"293 W Noble Ave",
    "sg:city":"Visalia",
    "sg:classifiers":[
        {
            "category":"Home & Garden",
            "subcategory":"Garden Supply",
            "type":"Retail Goods"
        }
    ],
    "sg:phone":"+1 559 635 7833",
    "sg:postcode":"93277",
    "sg:province":"CA",
    "sg:tags":[
        "landscaping",
        "equipment"
    ],
    "wof:name":"Stone Yard",
    "wof:placetype":"venue"
},
  "geometry": {"coordinates":[-119.293477,36.326354],"type":"Point"}
}