{
  "type": "Feature",
  "properties": {
    "iso:country":"US",
    "sg:address":"7741 Fay Ave",
    "sg:city":"La Jolla",
    "sg:classifiers":[
        {
            "category":"Wholesale",
            "subcategory":"Construction Materials",
            "type":"Manufacturing & Wholesale Goods"
        }
    ],
    "sg:phone":"+1 858 551 9951",
    "sg:postcode":"92037",
    "sg:province":"CA",
    "wof:name":"American State",
    "wof:placetype":"venue"
},
  "geometry": {"coordinates":[-117.274956,32.844216],"type":"Point"}
}