{
  "type": "Feature",
  "properties": {
    "iso:country":"US",
    "sg:address":"26433 Katharin St",
    "sg:city":"Hemet",
    "sg:classifiers":[
        {
            "category":"Bakery",
            "type":"Food & Drink"
        }
    ],
    "sg:phone":"+1 951 925 9209",
    "sg:postcode":"92544",
    "sg:province":"CA",
    "wof:name":"D&S Bread Distributor",
    "wof:placetype":"venue"
},
  "geometry": {"coordinates":[-116.94729100000001,33.737673],"type":"Point"}
}