{
  "type": "Feature",
  "properties": {
    "addr:full":"1847 E Walnut St Pasadena CA 91107",
    "addr:housenumber":"1847",
    "addr:postcode":"91107",
    "addr:street":"E Walnut St",
    "iso:country":"US",
    "sg:address":"1847 E Walnut St",
    "sg:city":"Pasadena",
    "sg:phone":"+1 626 689 4082",
    "sg:postcode":"91107",
    "sg:province":"CA",
    "sg:website":"http://clickserve.dartsearch.net/link/click?lid=43000000313870023&ds_s_kwgid=58000000006820725&ds_e_matchtype={MatchType}&ds_e_kwdid={OrderItemId}&ds_e_adid={AdId}&ds_url_v=2",
    "wof:name":"Spence & Frye Co.",
    "wof:placetype":"venue"
},
  "geometry": {"coordinates":[-118.11221399999999,34.149553],"type":"Point"}
}