{
  "type": "Feature",
  "properties": {
    "addr:full":"3577 7th Ave San Diego CA 92103",
    "addr:housenumber":"3577",
    "addr:postcode":"92103",
    "addr:street":"7Th Ave",
    "iso:country":"US",
    "sg:address":"3577 7th Ave",
    "sg:city":"San Diego",
    "sg:classifiers":[
        {
            "category":"Health Services",
            "subcategory":"Medical Lab",
            "type":"Services"
        }
    ],
    "sg:phone":"+1 619 299 3475",
    "sg:postcode":"92103",
    "sg:province":"CA",
    "sg:tags":[
        "laboratory"
    ],
    "sg:website":"www.dentaldog.com",
    "wof:name":"Berwick Dental Lab",
    "wof:placetype":"venue"
},
  "geometry": {"coordinates":[-117.158305,32.741798],"type":"Point"}
}