{
  "type": "Feature",
  "properties": {
    "iso:country":"US",
    "sg:address":"6318 Page Ln",
    "sg:city":"El Dorado",
    "sg:classifiers":[
        {
            "category":"Building & Trades",
            "subcategory":"Construction",
            "type":"Services"
        }
    ],
    "sg:phone":"+1 530 621 3506",
    "sg:postcode":"95623",
    "sg:province":"CA",
    "sg:tags":[
        "contractor"
    ],
    "wof:name":"Slightam Construction Clean Up",
    "wof:placetype":"venue"
},
  "geometry": {"coordinates":[-120.843237,38.679547],"type":"Point"}
}