{
  "type": "Feature",
  "properties": {
    "iso:country":"US",
    "sg:address":"1734 W Loma Linda Ave",
    "sg:city":"Fresno",
    "sg:classifiers":[
        {
            "category":"Shopping",
            "type":"Retail Goods"
        }
    ],
    "sg:phone":"+1 559 446 0565",
    "sg:postcode":"93711",
    "sg:province":"CA",
    "sg:tags":[
        "art",
        "gallery",
        "dealer"
    ],
    "wof:name":"Studio Gallery",
    "wof:placetype":"venue"
},
  "geometry": {"coordinates":[-119.825078,36.846304],"type":"Point"}
}