{
  "type": "Feature",
  "properties": {
    "addr:full":"138 E Lake St Salinas CA 93901",
    "addr:housenumber":"138",
    "addr:postcode":"93901",
    "addr:street":"E Lake St",
    "iso:country":"US",
    "sg:address":"138 E Lake St",
    "sg:city":"Salinas",
    "sg:classifiers":[
        {
            "category":"Home & Garden",
            "subcategory":"Building Materials",
            "type":"Retail Goods"
        }
    ],
    "sg:phone":"+1 831 424 9049",
    "sg:postcode":"93901",
    "sg:province":"CA",
    "sg:tags":[
        "windows"
    ],
    "wof:name":"Out Of The Woods",
    "wof:placetype":"venue"
},
  "geometry": {"coordinates":[-121.652208,36.679813],"type":"Point"}
}