{
  "type": "Feature",
  "properties": {
    "addr:full":"2535 Foothill Blvd La Crescenta CA 91214",
    "addr:housenumber":"2535",
    "addr:postcode":"91214",
    "addr:street":"Foothill Blvd",
    "iso:country":"US",
    "sg:address":"2535 Foothill Blvd",
    "sg:city":"La Crescenta",
    "sg:classifiers":[
        {
            "category":"Health Services",
            "subcategory":"Dentist",
            "type":"Services"
        }
    ],
    "sg:phone":"+1 818 248 0124",
    "sg:postcode":"91214",
    "sg:province":"CA",
    "wof:name":"Kwon J Orthodontic Center",
    "wof:placetype":"venue"
},
  "geometry": {"coordinates":[-118.234185,34.220766],"type":"Point"}
}