{
  "type": "Feature",
  "properties": {
    "addr:full":"6331 Viola Ter Chino Hills CA 91709",
    "addr:housenumber":"6331",
    "addr:postcode":"91709",
    "addr:street":"Viola Ter",
    "iso:country":"US",
    "sg:address":"6331 Viola Ter",
    "sg:city":"Chino Hills",
    "sg:classifiers":[
        {
            "category":"Banks & Credit Unions",
            "subcategory":"Investment Brokerage",
            "type":"Services"
        }
    ],
    "sg:phone":"+1 909 393 7262",
    "sg:postcode":"91709",
    "sg:province":"CA",
    "sg:tags":[
        "advisory",
        "financial"
    ],
    "wof:name":"Jd's Financial Network",
    "wof:placetype":"venue"
},
  "geometry": {"coordinates":[-117.667112,33.930564],"type":"Point"}
}