{
  "type": "Feature",
  "properties": {
    "iso:country":"US",
    "sg:address":"6615 Passons Blvd",
    "sg:city":"Pico Rivera",
    "sg:classifiers":[
        {
            "category":"Government",
            "subcategory":"Office",
            "type":"Public Place"
        }
    ],
    "sg:phone":"+1 562 801 4389",
    "sg:postcode":"90660",
    "sg:province":"CA",
    "sg:tags":[
        "city"
    ],
    "wof:name":"Pico Rivera City Clerk",
    "wof:placetype":"venue"
},
  "geometry": {"coordinates":[-118.088103,33.982405],"type":"Point"}
}