{
  "type": "Feature",
  "properties": {
    "addr:full":"8745 Conway Dr Riverside CA 92503",
    "addr:housenumber":"8745",
    "addr:postcode":"92503",
    "addr:street":"Conway Dr",
    "iso:country":"US",
    "sg:address":"8745 Conway Dr",
    "sg:city":"Riverside",
    "sg:classifiers":[
        {
            "category":"Home & Garden",
            "subcategory":"Building Materials",
            "type":"Retail Goods"
        },
        {
            "category":"Building & Trades",
            "subcategory":"Construction",
            "type":"Services"
        }
    ],
    "sg:phone":"+1 951 785 6765",
    "sg:postcode":"92503",
    "sg:province":"CA",
    "sg:tags":[
        "wallcoverings-installation",
        "wallpaper",
        "wallcoverings",
        "painting",
        "contractor"
    ],
    "wof:name":"Watson Painting Corp",
    "wof:placetype":"venue"
},
  "geometry": {"coordinates":[-117.443816,33.941978],"type":"Point"}
}