{
  "type": "Feature",
  "properties": {
    "iso:country":"US",
    "sg:address":"1672 W Ave J",
    "sg:city":"Lancaster",
    "sg:classifiers":[
        {
            "category":"Health Services",
            "subcategory":"Health Practitioner",
            "type":"Services"
        }
    ],
    "sg:phone":"+1 661 940 3484",
    "sg:postcode":"93534",
    "sg:province":"CA",
    "sg:tags":[
        "psychotherapist"
    ],
    "wof:name":"Sharyn Sebastin",
    "wof:placetype":"venue"
},
  "geometry": {"coordinates":[-118.160666,34.689267],"type":"Point"}
}