{
  "type": "Feature",
  "properties": {
    "addr:full":"1612 Haight St San Francisco CA 94117",
    "addr:housenumber":"1612",
    "addr:postcode":"94117",
    "addr:street":"Haight St",
    "iso:country":"US",
    "sg:address":"1612 Haight St",
    "sg:city":"San Francisco",
    "sg:classifiers":[
        {
            "category":"Shopping",
            "subcategory":"Clothing, Apparel, & Fashions",
            "type":"Retail Goods"
        }
    ],
    "sg:phone":"+1 415 551 7883",
    "sg:postcode":"94117",
    "sg:province":"CA",
    "wof:name":"STUF",
    "wof:placetype":"venue"
},
  "geometry": {"coordinates":[-122.44944599999999,37.76977],"type":"Point"}
}