{
  "type": "Feature",
  "properties": {
    "addr:full":"2061 Cerro Gordo St Los Angeles CA 90039",
    "addr:housenumber":"2061",
    "addr:postcode":"90039",
    "addr:street":"Cerro Gordo St",
    "iso:country":"US",
    "sg:address":"2061 Cerro Gordo St",
    "sg:city":"Los Angeles",
    "sg:classifiers":[
        {
            "category":"Social Services",
            "subcategory":"Child Care",
            "type":"Services"
        }
    ],
    "sg:phone":"+1 323 644 1104",
    "sg:postcode":"90039",
    "sg:province":"CA",
    "sg:tags":[
        "day"
    ],
    "wof:name":"Childhood Day Care",
    "wof:placetype":"venue"
},
  "geometry": {"coordinates":[-118.25299800000001,34.092201],"type":"Point"}
}