{
  "type": "Feature",
  "properties": {
    "iso:country":"US",
    "sg:address":"11615 Sterling Ave",
    "sg:city":"Riverside",
    "sg:classifiers":[
        {
            "category":"Utilities",
            "subcategory":"Water",
            "type":"Services"
        }
    ],
    "sg:phone":"+1 951 785 5411",
    "sg:postcode":"92503",
    "sg:province":"CA",
    "sg:tags":[
        "product",
        "conservation"
    ],
    "sg:website":"www.sawpa.org",
    "wof:name":"Santa Ana Watershed Project",
    "wof:placetype":"venue"
},
  "geometry": {"coordinates":[-117.483909,33.896194],"type":"Point"}
}