{
  "type": "Feature",
  "properties": {
    "addr:full":"750 W Fir St Ste 105 San Diego CA 92101",
    "addr:housenumber":"750",
    "addr:postcode":"92101",
    "addr:street":"W Fir St Ste 105",
    "iso:country":"US",
    "sg:address":"750 W Fir St Ste 105",
    "sg:city":"San Diego",
    "sg:classifiers":[
        {
            "category":"Coffee & Tea",
            "type":"Food & Drink"
        },
        {
            "category":"Food & Beverages",
            "subcategory":"Bakery",
            "type":"Retail Goods"
        },
        {
            "category":"Bagels",
            "subcategory":"None",
            "type":"Food & Drink"
        }
    ],
    "sg:phone":"+1 619 255 0735",
    "sg:postcode":"92101",
    "sg:province":"CA",
    "sg:tags":[
        "sandwich"
    ],
    "sg:website":"www.influxcafe.com",
    "wof:name":"Influx",
    "wof:placetype":"venue"
},
  "geometry": {"coordinates":[-117.169461,32.724178],"type":"Point"}
}