{
  "type": "Feature",
  "properties": {
    "iso:country":"US",
    "sg:address":"5631 Lincoln Ave",
    "sg:city":"Cypress",
    "sg:classifiers":[
        {
            "category":"Travel",
            "subcategory":"Travel Agent",
            "type":"Entertainment"
        }
    ],
    "sg:phone":"+1 714 252 9072",
    "sg:postcode":"90630",
    "sg:province":"CA",
    "sg:tags":[
        "tours",
        "promoter"
    ],
    "wof:name":"Cultural Folk Tours",
    "wof:placetype":"venue"
},
  "geometry": {"coordinates":[-118.033581,33.831853],"type":"Point"}
}