{
  "type": "Feature",
  "properties": {
    "addr:full":"4418 Ensign Ave North Hollywood CA 91602",
    "addr:housenumber":"4418",
    "addr:postcode":"91602",
    "addr:street":"Ensign Ave",
    "iso:country":"US",
    "sg:address":"4418 Ensign Ave",
    "sg:city":"North Hollywood",
    "sg:classifiers":[
        {
            "category":"Building & Trades",
            "subcategory":"Construction",
            "type":"Services"
        }
    ],
    "sg:phone":"+1 818 716 7665",
    "sg:postcode":"91602",
    "sg:province":"CA",
    "sg:tags":[
        "water",
        "restoration",
        "damage",
        "contractor"
    ],
    "wof:name":"Westside Global Care & Restora",
    "wof:placetype":"venue"
},
  "geometry": {"coordinates":[-118.37108499999999,34.150844],"type":"Point"}
}