{
  "type": "Feature",
  "properties": {
    "iso:country":"US",
    "sg:address":"506 Main St",
    "sg:city":"Woodland",
    "sg:classifiers":[
        {
            "category":"Bars & Pubs",
            "type":"Food & Drink"
        }
    ],
    "sg:phone":"+1 530 668 8373",
    "sg:postcode":"95695",
    "sg:province":"CA",
    "wof:name":"Stag",
    "wof:placetype":"venue"
},
  "geometry": {"coordinates":[-121.773241,38.677417],"type":"Point"}
}