{
  "type": "Feature",
  "properties": {
    "addr:full":"1915 Sunwood Ln Anaheim CA 92807",
    "addr:housenumber":"1915",
    "addr:postcode":"92807",
    "addr:street":"Sunwood Ln",
    "iso:country":"US",
    "sg:address":"1915 Sunwood Ln",
    "sg:city":"Anaheim",
    "sg:classifiers":[
        {
            "category":"Professional",
            "subcategory":"Advertising",
            "type":"Services"
        }
    ],
    "sg:phone":"+1 714 701 9773",
    "sg:postcode":"92807",
    "sg:province":"CA",
    "sg:tags":[
        "distribution"
    ],
    "wof:name":"Strategic Maketing",
    "wof:placetype":"venue"
},
  "geometry": {"coordinates":[-117.796072,33.868548],"type":"Point"}
}