{
  "type": "Feature",
  "properties": {
    "addr:full":"36 Brown Dr Novato CA 94947",
    "addr:housenumber":"36",
    "addr:postcode":"94947",
    "addr:street":"Brown Dr",
    "iso:country":"US",
    "sg:address":"36 Brown Dr",
    "sg:city":"Novato",
    "sg:classifiers":[
        {
            "category":"Professional",
            "type":"Services"
        }
    ],
    "sg:phone":"+1 415 892 8972",
    "sg:postcode":"94947",
    "sg:province":"CA",
    "sg:tags":[
        "establishment"
    ],
    "wof:name":"Exodus Inc",
    "wof:placetype":"venue"
},
  "geometry": {"coordinates":[-122.575684,38.085009],"type":"Point"}
}