{
  "type": "Feature",
  "properties": {
    "iso:country":"US",
    "sg:address":"1001 W Whittier Blvd #C",
    "sg:city":"Montebello",
    "sg:classifiers":[
        {
            "category":"Personal",
            "subcategory":"Day Spa",
            "type":"Services"
        },
        {
            "category":"Personal",
            "subcategory":"Nail Salon",
            "type":"Services"
        }
    ],
    "sg:phone":"+1 323 888 9193",
    "sg:postcode":"90640",
    "sg:province":"CA",
    "wof:name":"Diamond Nails & Spa",
    "wof:placetype":"venue"
},
  "geometry": {"coordinates":[-118.110821,34.010645],"type":"Point"}
}