{
  "type": "Feature",
  "properties": {
    "addr:full":"31726 S Coast Hwy Laguna Beach CA 92651",
    "addr:housenumber":"31726",
    "addr:postcode":"92651",
    "addr:street":"S Coast Hwy",
    "iso:country":"US",
    "sg:address":"31726 S Coast Hwy",
    "sg:city":"Laguna Beach",
    "sg:classifiers":[
        {
            "category":"Manufacturing",
            "subcategory":"Tools & Machinery",
            "type":"Manufacturing & Wholesale Goods"
        }
    ],
    "sg:phone":"+1 949 499 4503",
    "sg:postcode":"92651",
    "sg:province":"CA",
    "sg:tags":[
        "bearing"
    ],
    "sg:website":"www.mic-inc.net",
    "wof:name":"Miniature Instrument Cmpnts",
    "wof:placetype":"venue"
},
  "geometry": {"coordinates":[-117.743234,33.500958],"type":"Point"}
}