{
  "type": "Feature",
  "properties": {
    "addr:full":"20630 John Dr Castro Valley CA 94546",
    "addr:housenumber":"20630",
    "addr:postcode":"94546",
    "addr:street":"John Dr",
    "iso:country":"US",
    "sg:address":"20630 John Dr",
    "sg:city":"Castro Valley",
    "sg:classifiers":[
        {
            "category":"Personal",
            "type":"Services"
        }
    ],
    "sg:phone":"+1 510 888 1843",
    "sg:postcode":"94546",
    "sg:province":"CA",
    "sg:tags":[
        "mover"
    ],
    "wof:name":"U-Haul",
    "wof:placetype":"venue"
},
  "geometry": {"coordinates":[-122.091207,37.692989],"type":"Point"}
}