{
  "type": "Feature",
  "properties": {
    "addr:full":"9448 Toucan Ave Fountain Valley CA 92708",
    "addr:housenumber":"9448",
    "addr:postcode":"92708",
    "addr:street":"Toucan Ave",
    "iso:country":"US",
    "sg:address":"9448 Toucan Ave",
    "sg:city":"Fountain Valley",
    "sg:classifiers":[
        {
            "category":"Professional",
            "subcategory":"Computer Services",
            "type":"Services"
        }
    ],
    "sg:phone":"+1 714 968 9437",
    "sg:postcode":"92708",
    "sg:province":"CA",
    "sg:tags":[
        "prepackaged",
        "software"
    ],
    "wof:name":"Wwwdaviaconsultcom",
    "wof:placetype":"venue"
},
  "geometry": {"coordinates":[-117.96369199999999,33.697225],"type":"Point"}
}