{
  "type": "Feature",
  "properties": {
    "iso:country":"US",
    "sg:address":"396 Robinson Dr",
    "sg:city":"Tustin",
    "sg:classifiers":[
        {
            "category":"Manufacturing",
            "subcategory":"Retail Goods",
            "type":"Manufacturing & Wholesale Goods"
        }
    ],
    "sg:phone":"+1 714 544 0590",
    "sg:postcode":"92782",
    "sg:province":"CA",
    "sg:tags":[
        "carbon",
        "ribbon",
        "mfg"
    ],
    "wof:name":"Lalani Hadi",
    "wof:placetype":"venue"
},
  "geometry": {"coordinates":[-117.784319,33.735622],"type":"Point"}
}