{
  "type": "Feature",
  "properties": {
    "iso:country":"US",
    "sg:address":"10801 Washington Boulevard",
    "sg:city":"Culver City",
    "sg:classifiers":[
        {
            "category":"Shopping",
            "subcategory":"Florist",
            "type":"Retail Goods"
        }
    ],
    "sg:phone":"+1 310 838 9630",
    "sg:postcode":"90232",
    "sg:province":"CA",
    "sg:website":"www.culvercityflowershop.com/",
    "wof:name":"Culver City Flower",
    "wof:placetype":"venue"
},
  "geometry": {"coordinates":[-118.407282,34.015086],"type":"Point"}
}