{
  "type": "Feature",
  "properties": {
    "addr:full":"415 Laurel St San Diego CA 92101",
    "addr:housenumber":"415",
    "addr:postcode":"92101",
    "addr:street":"Laurel St",
    "iso:country":"US",
    "sg:address":"415 Laurel St",
    "sg:city":"San Diego",
    "sg:classifiers":[
        {
            "category":"Education",
            "subcategory":"Special Training",
            "type":"Public Place"
        }
    ],
    "sg:phone":"+1 619 955 8884",
    "sg:postcode":"92101",
    "sg:province":"CA",
    "sg:tags":[
        "school",
        "specialty"
    ],
    "sg:website":"www.winesmarties.com/",
    "wof:name":"Wine Smarties",
    "wof:placetype":"venue"
},
  "geometry": {"coordinates":[-117.161078,32.731367],"type":"Point"}
}