{
  "type": "Feature",
  "properties": {
    "addr:full":"810 Davis St Vacaville CA 95687",
    "addr:housenumber":"810",
    "addr:postcode":"95687",
    "addr:street":"Davis St",
    "iso:country":"US",
    "sg:address":"810 Davis St",
    "sg:city":"Vacaville",
    "sg:classifiers":[
        {
            "category":"Autos & Motor Vehicles",
            "subcategory":"Auto Supplies",
            "type":"Retail Goods"
        },
        {
            "category":"Manufacturing",
            "subcategory":"Motor Vehicles & Parts",
            "type":"Manufacturing & Wholesale Goods"
        }
    ],
    "sg:phone":"+1 707 452 9998",
    "sg:postcode":"95687",
    "sg:province":"CA",
    "sg:tags":[
        "automobile",
        "mfg"
    ],
    "wof:name":"Family Adventure Outfitters",
    "wof:placetype":"venue"
},
  "geometry": {"coordinates":[-121.98632000000001,38.349214],"type":"Point"}
}