{
  "type": "Feature",
  "properties": {
    "addr:full":"2050 Bullrush Ln Cardiff By Sea CA 92007",
    "addr:housenumber":"2050",
    "addr:postcode":"92007",
    "addr:street":"Bullrush Ln",
    "iso:country":"US",
    "sg:address":"2050 Bullrush Ln",
    "sg:city":"Cardiff By Sea",
    "sg:classifiers":[
        {
            "category":"Building & Trades",
            "subcategory":"Landscaping Services",
            "type":"Services"
        }
    ],
    "sg:phone":"+1 760 436 1169",
    "sg:postcode":"92007",
    "sg:province":"CA",
    "sg:tags":[
        "landscape",
        "contractor"
    ],
    "wof:name":"LA Costa Landscape & Mntnc Co",
    "wof:placetype":"venue"
},
  "geometry": {"coordinates":[-117.270445,33.020396],"type":"Point"}
}