{
  "type": "Feature",
  "properties": {
    "iso:country":"US",
    "sg:address":"486 Suisse Dr",
    "sg:city":"San Jose",
    "sg:classifiers":[
        {
            "category":"Professional",
            "type":"Services"
        }
    ],
    "sg:phone":"+1 408 445 1501",
    "sg:postcode":"95123",
    "sg:province":"CA",
    "wof:name":"Lsp",
    "wof:placetype":"venue"
},
  "geometry": {"coordinates":[-121.825391,37.234164],"type":"Point"}
}