{
  "type": "Feature",
  "properties": {
    "addr:full":"726 Nina Ln Foster City CA 94404",
    "addr:housenumber":"726",
    "addr:postcode":"94404",
    "addr:street":"Nina Ln",
    "iso:country":"US",
    "sg:address":"726 Nina Ln",
    "sg:city":"Foster City",
    "sg:classifiers":[
        {
            "category":"Shopping",
            "subcategory":"Computers & Home Electronics",
            "type":"Retail Goods"
        }
    ],
    "sg:phone":"+1 650 571 5566",
    "sg:postcode":"94404",
    "sg:province":"CA",
    "sg:tags":[
        "software"
    ],
    "wof:name":"Riverledge Inc",
    "wof:placetype":"venue"
},
  "geometry": {"coordinates":[-122.261983,37.56099],"type":"Point"}
}