{
  "type": "Feature",
  "properties": {
    "addr:full":"554 W 43rd Pl Los Angeles CA 90037",
    "addr:housenumber":"554",
    "addr:postcode":"90037",
    "addr:street":"W 43Rd Pl",
    "iso:country":"US",
    "sg:address":"554 W 43rd Pl",
    "sg:city":"Los Angeles",
    "sg:classifiers":[
        {
            "category":"Shopping",
            "subcategory":"Used Merchandise",
            "type":"Retail Goods"
        }
    ],
    "sg:phone":"+1 323 235 6080",
    "sg:postcode":"90037",
    "sg:province":"CA",
    "sg:tags":[
        "appliance"
    ],
    "wof:name":"Acapulco Appliance",
    "wof:placetype":"venue"
},
  "geometry": {"coordinates":[-118.287132,34.004614],"type":"Point"}
}