{
  "type": "Feature",
  "properties": {
    "iso:country":"US",
    "sg:address":"8723 Sierra College Blvd",
    "sg:city":"Roseville",
    "sg:classifiers":[
        {
            "category":"Health Services",
            "subcategory":"Doctor",
            "type":"Services"
        }
    ],
    "sg:phone":"+1 916 791 0797",
    "sg:postcode":"95661",
    "sg:province":"CA",
    "sg:tags":[
        "physician",
        "surgeon"
    ],
    "wof:name":"Allergy & Asthma Pro Group",
    "wof:placetype":"venue"
},
  "geometry": {"coordinates":[-121.225922,38.739492],"type":"Point"}
}