{
  "type": "Feature",
  "properties": {
    "addr:full":"6500 Tesla Rd Livermore CA 94550",
    "addr:housenumber":"6500",
    "addr:postcode":"94550",
    "addr:street":"Tesla Rd",
    "iso:country":"US",
    "sg:address":"6500 Tesla Rd",
    "sg:city":"Livermore",
    "sg:classifiers":[
        {
            "category":"Wholesale",
            "subcategory":"Stationery",
            "type":"Manufacturing & Wholesale Goods"
        }
    ],
    "sg:phone":"+1 925 443 8421",
    "sg:postcode":"94550",
    "sg:province":"CA",
    "sg:tags":[
        "supply"
    ],
    "wof:name":"M S R Cabinet",
    "wof:placetype":"venue"
},
  "geometry": {"coordinates":[-121.718767,37.665001],"type":"Point"}
}