{
  "type": "Feature",
  "properties": {
    "addr:full":"1669 N Mountain Ave Upland CA 91784",
    "addr:housenumber":"1669",
    "addr:postcode":"91784",
    "addr:street":"N Mountain Ave",
    "iso:country":"US",
    "sg:address":"1669 N Mountain Ave",
    "sg:city":"Upland",
    "sg:classifiers":[
        {
            "category":"Banks & Credit Unions",
            "subcategory":"Bank",
            "type":"Services"
        }
    ],
    "sg:phone":"+1 909 000 1111",
    "sg:postcode":"91784",
    "sg:province":"CA",
    "wof:name":"Pff Bank & Trust",
    "wof:placetype":"venue"
},
  "geometry": {"coordinates":[-117.670376,34.121936],"type":"Point"}
}