{
  "type": "Feature",
  "properties": {
    "addr:full":"567 Cam Mercado Arroyo Grande CA 93420",
    "addr:housenumber":"567",
    "addr:postcode":"93420",
    "addr:street":"Cam Mercado",
    "iso:country":"US",
    "sg:address":"567 Cam Mercado",
    "sg:city":"Arroyo Grande",
    "sg:classifiers":[
        {
            "category":"Manufacturing",
            "subcategory":"Paper Products",
            "type":"Manufacturing & Wholesale Goods"
        }
    ],
    "sg:phone":"+1 805 473 7200",
    "sg:postcode":"93420",
    "sg:province":"CA",
    "sg:tags":[
        "plastic",
        "container",
        "cup"
    ],
    "wof:name":"Orbis Container Svc",
    "wof:placetype":"venue"
},
  "geometry": {"coordinates":[-120.598809,35.130062],"type":"Point"}
}