{
  "type": "Feature",
  "properties": {
    "iso:country":"US",
    "sg:address":"9095 Rio San Diego Dr Ste 195",
    "sg:city":"San Diego",
    "sg:classifiers":[
        {
            "category":"Real Estate",
            "subcategory":"Real Estate Services",
            "type":"Services"
        }
    ],
    "sg:phone":"+1 619 278 0086",
    "sg:postcode":"92108",
    "sg:province":"CA",
    "sg:website":"www.actfortitle.com/contactsd.shtml",
    "wof:name":"American Coast Title",
    "wof:placetype":"venue"
},
  "geometry": {"coordinates":[-117.135651,32.775512],"type":"Point"}
}