{
  "type": "Feature",
  "properties": {
    "iso:country":"US",
    "sg:address":"5310 Lakewood Blvd",
    "sg:city":"Lakewood",
    "sg:classifiers":[
        {
            "category":"Fast Food",
            "type":"Food & Drink"
        },
        {
            "category":"Restaurant",
            "type":"Food & Drink"
        }
    ],
    "sg:phone":"+1 562 790 8729",
    "sg:postcode":"90712",
    "sg:province":"CA",
    "sg:tags":[
        "tex-mex"
    ],
    "sg:website":"www.chipotle.com",
    "wof:name":"Chipotle Mexican Grill",
    "wof:placetype":"venue"
},
  "geometry": {"coordinates":[-118.142403,33.853943],"type":"Point"}
}