{
  "type": "Feature",
  "properties": {
    "iso:country":"US",
    "sg:address":"5 Casa Grande Rd",
    "sg:city":"Petaluma",
    "sg:classifiers":[
        {
            "category":"Professional",
            "type":"Services"
        }
    ],
    "sg:phone":"+1 707 763 5679",
    "sg:postcode":"94954",
    "sg:province":"CA",
    "sg:tags":[
        "establishment"
    ],
    "wof:name":"Flame Stop Of Northern Ca",
    "wof:placetype":"venue"
},
  "geometry": {"coordinates":[-122.606914,38.231351],"type":"Point"}
}