{
  "type": "Feature",
  "properties": {
    "addr:full":"7121 Firestone Blvd #6627 Downey CA 90241",
    "addr:housenumber":"7121",
    "addr:postcode":"90241",
    "addr:street":"Firestone Blvd # 6627",
    "iso:country":"US",
    "sg:address":"7121 Firestone Blvd #6627",
    "sg:city":"Downey",
    "sg:classifiers":[
        {
            "category":"Home & Garden",
            "subcategory":"Hardware",
            "type":"Retail Goods"
        },
        {
            "category":"Home & Garden",
            "subcategory":"Building Materials",
            "type":"Retail Goods"
        }
    ],
    "sg:phone":"+1 562 776 2200",
    "sg:postcode":"90241",
    "sg:province":"CA",
    "sg:tags":[
        "store",
        "supply"
    ],
    "sg:website":"www.thehomedepot.com",
    "wof:name":"The Home Depot",
    "wof:placetype":"venue"
},
  "geometry": {"coordinates":[-118.15566699999999,33.949285],"type":"Point"}
}