{
  "type": "Feature",
  "properties": {
    "iso:country":"US",
    "sg:address":"12380 Palm Dr",
    "sg:city":"Desert Hot Spgs",
    "sg:classifiers":[
        {
            "category":"Real Estate",
            "subcategory":"Real Estate Agent",
            "type":"Services"
        }
    ],
    "sg:phone":"+1 760 329 4600",
    "sg:postcode":"92240",
    "sg:province":"CA",
    "wof:name":"Masters Financial Group",
    "wof:placetype":"venue"
},
  "geometry": {"coordinates":[-116.501279,33.958658],"type":"Point"}
}