{
  "type": "Feature",
  "properties": {
    "addr:full":"1016 Reno Ave Modesto CA 95351",
    "addr:housenumber":"1016",
    "addr:postcode":"ca 95351",
    "addr:street":"Reno Ave",
    "iso:country":"US",
    "sg:address":"1016 Reno Ave",
    "sg:city":"Modesto",
    "sg:classifiers":[
        {
            "category":"Professional",
            "subcategory":"Art Services",
            "type":"Services"
        }
    ],
    "sg:phone":"+1 209 544 0961",
    "sg:postcode":"95351",
    "sg:province":"CA",
    "sg:tags":[
        "portrait",
        "school",
        "studio",
        "for"
    ],
    "wof:name":"Lifetouch",
    "wof:placetype":"venue"
},
  "geometry": {"coordinates":[-121.027861,37.649242],"type":"Point"}
}