{
  "type": "Feature",
  "properties": {
    "iso:country":"US",
    "sg:address":"1816 Cecil Ave",
    "sg:city":"Delano",
    "sg:classifiers":[
        {
            "category":"Organizations",
            "subcategory":"Non-profit Organization",
            "type":"Services"
        }
    ],
    "sg:phone":"+1 661 725 0803",
    "sg:postcode":"93215",
    "sg:province":"CA",
    "sg:website":"www.proteusinc.com",
    "wof:name":"Proteus Inc",
    "wof:placetype":"venue"
},
  "geometry": {"coordinates":[-119.227773,35.775789],"type":"Point"}
}