{
  "type": "Feature",
  "properties": {
    "addr:full":"4362 Coldwater Canyon Ave Studio City CA 91604",
    "addr:housenumber":"4362",
    "addr:postcode":"91604",
    "addr:street":"Coldwater Canyon Ave",
    "iso:country":"US",
    "sg:address":"4362 Coldwater Canyon Ave",
    "sg:city":"Studio City",
    "sg:classifiers":[
        {
            "category":"Retail",
            "subcategory":"Laundry & Dry Cleaning",
            "type":"Services"
        }
    ],
    "sg:phone":"+1 818 761 0129",
    "sg:postcode":"91604",
    "sg:province":"CA",
    "wof:name":"Coldwater Cleaners",
    "wof:placetype":"venue"
},
  "geometry": {"coordinates":[-118.414001,34.1497],"type":"Point"}
}