{
  "type": "Feature",
  "properties": {
    "iso:country":"US",
    "sg:address":"1250 Quintara St",
    "sg:city":"San Francisco",
    "sg:classifiers":[
        {
            "category":"Organizations",
            "subcategory":"Religious Organization",
            "type":"Services"
        }
    ],
    "sg:phone":"+1 415 661 3383",
    "sg:postcode":"94116",
    "sg:province":"CA",
    "sg:tags":[
        "synagogue"
    ],
    "wof:name":"Congregation Ner Tamid",
    "wof:placetype":"venue"
},
  "geometry": {"coordinates":[-122.478868,37.748603],"type":"Point"}
}