{
  "type": "Feature",
  "properties": {
    "iso:country":"US",
    "sg:address":"16 Dove Ct",
    "sg:city":"Brentwood",
    "sg:classifiers":[
        {
            "category":"Building & Trades",
            "subcategory":"Construction",
            "type":"Services"
        }
    ],
    "sg:phone":"+1 925 513 3240",
    "sg:postcode":"94513",
    "sg:province":"CA",
    "sg:tags":[
        "acoustical",
        "flooring",
        "contractor"
    ],
    "wof:name":"Floor To Ceilings",
    "wof:placetype":"venue"
},
  "geometry": {"coordinates":[-121.709999,37.939098],"type":"Point"}
}