{
  "type": "Feature",
  "properties": {
    "addr:full":"1035 Anoka Pl Pacific Plsds CA 90272",
    "addr:housenumber":"1035",
    "addr:postcode":"90272",
    "addr:street":"Anoka Pl",
    "iso:country":"US",
    "sg:address":"1035 Anoka Pl",
    "sg:city":"Pacific Plsds",
    "sg:classifiers":[
        {
            "category":"Professional",
            "type":"Services"
        }
    ],
    "sg:phone":"+1 310 459 3757",
    "sg:postcode":"90272",
    "sg:province":"CA",
    "sg:tags":[
        "establishment"
    ],
    "wof:name":"Pacific Enterprises",
    "wof:placetype":"venue"
},
  "geometry": {"coordinates":[-118.5347,34.052806],"type":"Point"}
}