{
  "type": "Feature",
  "properties": {
    "iso:country":"US",
    "sg:address":"506 W Tennyson Rd",
    "sg:city":"Hayward",
    "sg:classifiers":[
        {
            "category":"Professional",
            "subcategory":"Management & Consulting",
            "type":"Services"
        }
    ],
    "sg:phone":"+1 510 784 9804",
    "sg:postcode":"94544",
    "sg:province":"CA",
    "sg:tags":[
        "support",
        "library"
    ],
    "wof:name":"Esbeida Maldonado",
    "wof:placetype":"venue"
},
  "geometry": {"coordinates":[-122.067857,37.632244],"type":"Point"}
}