{
  "type": "Feature",
  "properties": {
    "addr:full":"1111 Harris St San Bernardino CA 92411",
    "addr:housenumber":"1111",
    "addr:postcode":"92411",
    "addr:street":"Harris St",
    "iso:country":"US",
    "sg:address":"1111 Harris St",
    "sg:city":"San Bernardino",
    "sg:classifiers":[
        {
            "category":"Manufacturing",
            "subcategory":"Tools & Machinery",
            "type":"Manufacturing & Wholesale Goods"
        }
    ],
    "sg:phone":"+1 909 888 9888",
    "sg:postcode":"92411",
    "sg:province":"CA",
    "sg:tags":[
        "industrial",
        "mfg"
    ],
    "wof:name":"Southland Machine",
    "wof:placetype":"venue"
},
  "geometry": {"coordinates":[-117.303738,34.120392],"type":"Point"}
}