{
  "type": "Feature",
  "properties": {
    "iso:country":"US",
    "sg:address":"13039 Victory Blvd",
    "sg:city":"North Hollywood",
    "sg:classifiers":[
        {
            "category":"Shopping",
            "subcategory":"Shoes",
            "type":"Retail Goods"
        }
    ],
    "sg:phone":"+1 818 762 6021",
    "sg:postcode":"91606",
    "sg:province":"CA",
    "sg:tags":[
        "store"
    ],
    "wof:name":"Fashion Q Shoes",
    "wof:placetype":"venue"
},
  "geometry": {"coordinates":[-118.416899,34.186827],"type":"Point"}
}