{
  "type": "Feature",
  "properties": {
    "addr:full":"3246 Sepulveda Blvd Torrance CA 90505",
    "addr:housenumber":"3246",
    "addr:postcode":"90505",
    "addr:street":"Sepulveda Blvd",
    "iso:country":"US",
    "sg:address":"3246 Sepulveda Blvd",
    "sg:city":"Torrance",
    "sg:classifiers":[
        {
            "category":"Professional",
            "subcategory":"Employment Agencies",
            "type":"Services"
        }
    ],
    "sg:phone":"+1 310 326 6700",
    "sg:postcode":"90505",
    "sg:province":"CA",
    "wof:name":"Helpmates Staffing Services",
    "wof:placetype":"venue"
},
  "geometry": {"coordinates":[-118.343665,33.824896],"type":"Point"}
}