{
  "type": "Feature",
  "properties": {
    "addr:full":"8929 Terman Ct San Diego CA 92121",
    "addr:housenumber":"8929",
    "addr:postcode":"92121",
    "addr:street":"Terman Ct",
    "iso:country":"US",
    "sg:address":"8929 Terman Ct",
    "sg:city":"San Diego",
    "sg:classifiers":[
        {
            "category":"Shopping",
            "subcategory":"Computers & Home Electronics",
            "type":"Retail Goods"
        }
    ],
    "sg:phone":"+1 800 683 2778",
    "sg:postcode":"92121",
    "sg:province":"CA",
    "sg:tags":[
        "professional",
        "equipment"
    ],
    "sg:website":"www.sdcr.com/",
    "wof:name":"SDCR Business Systems",
    "wof:placetype":"venue"
},
  "geometry": {"coordinates":[-117.16539,32.886002],"type":"Point"}
}