{
  "type": "Feature",
  "properties": {
    "addr:full":"622 W State St El Centro CA 92243",
    "addr:housenumber":"622",
    "addr:postcode":"92243",
    "addr:street":"W State St",
    "iso:country":"US",
    "sg:address":"622 W State St",
    "sg:city":"El Centro",
    "sg:classifiers":[
        {
            "category":"Restaurant",
            "type":"Food & Drink"
        }
    ],
    "sg:phone":"+1 760 352 4595",
    "sg:postcode":"92243",
    "sg:province":"CA",
    "wof:name":"Bashas New York Deli",
    "wof:placetype":"venue"
},
  "geometry": {"coordinates":[-115.55864099999999,32.791861],"type":"Point"}
}