{
  "type": "Feature",
  "properties": {
    "iso:country":"US",
    "sg:address":"423 S Westmoreland Avenue",
    "sg:city":"Los Angeles",
    "sg:classifiers":[
        {
            "category":"Real Estate",
            "subcategory":"Real Estate Operator",
            "type":"Services"
        }
    ],
    "sg:phone":"+1 213 380 9004",
    "sg:postcode":"90020",
    "sg:province":"CA",
    "sg:tags":[
        "apartment"
    ],
    "wof:name":"The Westminster Apartments",
    "wof:placetype":"venue"
},
  "geometry": {"coordinates":[-118.288459,34.0664],"type":"Point"}
}