{
  "type": "Feature",
  "properties": {
    "iso:country":"US",
    "sg:address":"96 Carter Ave",
    "sg:city":"Fowler",
    "sg:classifiers":[
        {
            "category":"Retail",
            "subcategory":"Laundry & Dry Cleaning",
            "type":"Services"
        }
    ],
    "sg:phone":"+1 559 834 6666",
    "sg:postcode":"93625",
    "sg:province":"CA",
    "sg:tags":[
        "cleaners",
        "rug",
        "carpet"
    ],
    "wof:name":"A Plus Carpet Cleaning",
    "wof:placetype":"venue"
},
  "geometry": {"coordinates":[-119.685667,36.637833],"type":"Point"}
}