{
  "type": "Feature",
  "properties": {
    "iso:country":"US",
    "sg:address":"7366 El Cajon Blvd",
    "sg:city":"La Mesa",
    "sg:classifiers":[
        {
            "category":"Bars & Pubs",
            "type":"Food & Drink"
        },
        {
            "category":"Bars & Pubs",
            "subcategory":"Sports Bar",
            "type":"Food & Drink"
        }
    ],
    "sg:phone":"+1 619 465 4190",
    "sg:postcode":"91941",
    "sg:province":"CA",
    "sg:tags":[
        "hall",
        "pool"
    ],
    "sg:website":"www.chicoclub1940.com",
    "wof:name":"Chico Club",
    "wof:placetype":"venue"
},
  "geometry": {"coordinates":[-117.03880700000001,32.769136],"type":"Point"}
}