{
  "type": "Feature",
  "properties": {
    "addr:full":"4916 Manzanita Ave Carmichael CA 95608",
    "addr:housenumber":"4916",
    "addr:postcode":"95608",
    "addr:street":"Manzanita Ave",
    "iso:country":"US",
    "sg:address":"4916 Manzanita Ave",
    "sg:city":"Carmichael",
    "sg:classifiers":[
        {
            "category":"Building & Trades",
            "subcategory":"Construction",
            "type":"Services"
        }
    ],
    "sg:phone":"+1 916 332 2316",
    "sg:postcode":"95608",
    "sg:province":"CA",
    "sg:tags":[
        "grading",
        "paving",
        "contractor"
    ],
    "wof:name":"Gospodnetich Construction",
    "wof:placetype":"venue"
},
  "geometry": {"coordinates":[-121.32747500000001,38.655059],"type":"Point"}
}