{
  "type": "Feature",
  "properties": {
    "addr:full":"10985 Ballico Ave Ballico CA 95303",
    "addr:housenumber":"10985",
    "addr:postcode":"95303",
    "addr:street":"Ballico Ave",
    "iso:country":"US",
    "sg:address":"10985 Ballico Ave",
    "sg:city":"Ballico",
    "sg:classifiers":[
        {
            "category":"Wholesale",
            "subcategory":"Farm Supplies",
            "type":"Manufacturing & Wholesale Goods"
        }
    ],
    "sg:phone":"+1 209 667 6013",
    "sg:postcode":"95303",
    "sg:province":"CA",
    "sg:tags":[
        "chemical",
        "agricultural"
    ],
    "wof:name":"Simplot Soilbuilders",
    "wof:placetype":"venue"
},
  "geometry": {"coordinates":[-120.70137200000001,37.448063],"type":"Point"}
}