{
  "type": "Feature",
  "properties": {
    "addr:full":"1232 Los Vallecitos Blvd San Marcos CA 92069",
    "addr:housenumber":"1232",
    "addr:postcode":"92069",
    "addr:street":"Los Vallecitos Blvd",
    "iso:country":"US",
    "sg:address":"1232 Los Vallecitos Blvd",
    "sg:city":"San Marcos",
    "sg:classifiers":[
        {
            "category":"Manufacturing",
            "subcategory":"Wood Products",
            "type":"Manufacturing & Wholesale Goods"
        },
        {
            "category":"Building & Trades",
            "subcategory":"Construction",
            "type":"Services"
        }
    ],
    "sg:phone":"+1 760 761 4960",
    "sg:postcode":"92069",
    "sg:province":"CA",
    "sg:tags":[
        "mfg",
        "woodworker"
    ],
    "wof:name":"Architectural Woodworks",
    "wof:placetype":"venue"
},
  "geometry": {"coordinates":[-117.186612,33.14169],"type":"Point"}
}