{
  "type": "Feature",
  "properties": {
    "iso:country":"US",
    "sg:address":"301 Dodini Ct",
    "sg:city":"Suisun City",
    "sg:classifiers":[
        {
            "category":"Recreation",
            "type":"Entertainment"
        }
    ],
    "sg:phone":"+1 707 426 9852",
    "sg:postcode":"94585",
    "sg:province":"CA",
    "sg:tags":[
        "charter",
        "boat"
    ],
    "wof:name":"Inflatables Etc",
    "wof:placetype":"venue"
},
  "geometry": {"coordinates":[-121.999781,38.240922],"type":"Point"}
}