{
  "type": "Feature",
  "properties": {
    "iso:country":"US",
    "sg:address":"357 N Oak St",
    "sg:city":"Inglewood",
    "sg:classifiers":[
        {
            "category":"Wholesale",
            "subcategory":"Durable Goods & Equipment",
            "type":"Manufacturing & Wholesale Goods"
        }
    ],
    "sg:phone":"+1 310 672 5353",
    "sg:postcode":"90302",
    "sg:province":"CA",
    "sg:tags":[
        "exporter"
    ],
    "wof:name":"C & C Export Import",
    "wof:placetype":"venue"
},
  "geometry": {"coordinates":[-118.366753,33.966855],"type":"Point"}
}