{
  "type": "Feature",
  "properties": {
    "addr:full":"2428 Montecito Rd Ramona CA 92065",
    "addr:housenumber":"2428",
    "addr:postcode":"92065",
    "addr:street":"Montecito Rd",
    "iso:country":"US",
    "sg:address":"2428 Montecito Rd",
    "sg:city":"Ramona",
    "sg:classifiers":[
        {
            "category":"Airport",
            "type":"Transportation"
        }
    ],
    "sg:phone":"+1 760 789 8020",
    "sg:postcode":"92065",
    "sg:province":"CA",
    "sg:tags":[
        "retail",
        "craft",
        "maintains",
        "air"
    ],
    "sg:website":"www.cruiseairav.com",
    "wof:name":"Cruiseair Aviation Inc",
    "wof:placetype":"venue"
},
  "geometry": {"coordinates":[-116.907428,33.040385],"type":"Point"}
}