{
  "type": "Feature",
  "properties": {
    "addr:full":"41892 Enterprise Cir S Temecula CA 92590",
    "addr:housenumber":"41892",
    "addr:postcode":"92590",
    "addr:street":"Enterprise Cir S",
    "iso:country":"US",
    "sg:address":"41892 Enterprise Cir S",
    "sg:city":"Temecula",
    "sg:classifiers":[
        {
            "category":"Professional",
            "subcategory":"Computer Services",
            "type":"Services"
        }
    ],
    "sg:phone":"+1 951 296 0200",
    "sg:postcode":"92590",
    "sg:province":"CA",
    "sg:tags":[
        "repair"
    ],
    "wof:name":"Temecula Valley Laser Repair",
    "wof:placetype":"venue"
},
  "geometry": {"coordinates":[-117.16761700000001,33.516362],"type":"Point"}
}