{
  "type": "Feature",
  "properties": {
    "iso:country":"US",
    "sg:address":"476 Mendocino Ave",
    "sg:city":"Santa Rosa",
    "sg:classifiers":[
        {
            "category":"Sports & Exercise",
            "subcategory":"Gym",
            "type":"Entertainment"
        }
    ],
    "sg:phone":"+1 707 571 1080",
    "sg:postcode":"95401",
    "sg:province":"CA",
    "sg:tags":[
        "personal",
        "trainer"
    ],
    "wof:name":"Force Fitness",
    "wof:placetype":"venue"
},
  "geometry": {"coordinates":[-122.715447,38.442517],"type":"Point"}
}