{
  "type": "Feature",
  "properties": {
    "addr:full":"3836 Pestana Way Livermore CA 94550",
    "addr:housenumber":"3836",
    "addr:postcode":"94550",
    "addr:street":"Pestana Way",
    "iso:country":"US",
    "sg:address":"3836 Pestana Way",
    "sg:city":"Livermore",
    "sg:classifiers":[
        {
            "category":"Banks & Credit Unions",
            "subcategory":"Investment Brokerage",
            "type":"Services"
        }
    ],
    "sg:phone":"+1 925 455 4920",
    "sg:postcode":"94550",
    "sg:province":"CA",
    "sg:tags":[
        "consultant",
        "planning",
        "financial"
    ],
    "wof:name":"Meadows Financial Planning",
    "wof:placetype":"venue"
},
  "geometry": {"coordinates":[-121.752893,37.68437],"type":"Point"}
}