{
  "type": "Feature",
  "properties": {
    "iso:country":"US",
    "sg:address":"1001 Franklin St",
    "sg:city":"San Francisco",
    "sg:classifiers":[
        {
            "category":"Insurance",
            "subcategory":"Insurance Agent",
            "type":"Services"
        }
    ],
    "sg:phone":"+1 415 771 1008",
    "sg:postcode":"94109",
    "sg:province":"CA",
    "wof:name":"William F Anderson",
    "wof:placetype":"venue"
},
  "geometry": {"coordinates":[-122.422744,37.784084],"type":"Point"}
}