{
  "type": "Feature",
  "properties": {
    "iso:country":"US",
    "sg:address":"1616 W Pine Ave",
    "sg:city":"Fresno",
    "sg:classifiers":[
        {
            "category":"Manufacturing",
            "subcategory":"Metals",
            "type":"Manufacturing & Wholesale Goods"
        }
    ],
    "sg:phone":"+1 559 441 0789",
    "sg:postcode":"93728",
    "sg:province":"CA",
    "sg:tags":[
        "anodizing"
    ],
    "wof:name":"Pacific Coast Anodizing",
    "wof:placetype":"venue"
},
  "geometry": {"coordinates":[-119.828615,36.762056],"type":"Point"}
}