{
  "type": "Feature",
  "properties": {
    "iso:country":"US",
    "sg:address":"12947 Lompoc Rd",
    "sg:city":"Apple Valley",
    "sg:classifiers":[
        {
            "category":"Building & Trades",
            "subcategory":"Landscaping Services",
            "type":"Services"
        }
    ],
    "sg:phone":"+1 760 240 8449",
    "sg:postcode":"92308",
    "sg:province":"CA",
    "sg:tags":[
        "landscape"
    ],
    "wof:name":"HI Desert Landscaping & Custom",
    "wof:placetype":"venue"
},
  "geometry": {"coordinates":[-117.237776,34.486586],"type":"Point"}
}