{
  "type": "Feature",
  "properties": {
    "iso:country":"US",
    "sg:address":"12016 Old River School Rd",
    "sg:city":"Downey",
    "sg:classifiers":[
        {
            "category":"Freight",
            "type":"Transportation"
        }
    ],
    "sg:phone":"+1 213 272 1201",
    "sg:postcode":"90242",
    "sg:province":"CA",
    "wof:name":"Cedars Transportation Services",
    "wof:placetype":"venue"
},
  "geometry": {"coordinates":[-118.155761,33.937553],"type":"Point"}
}