{
  "type": "Feature",
  "properties": {
    "addr:full":"9454 Wilshire Blvd Beverly Hills CA 90212",
    "addr:housenumber":"9454",
    "addr:postcode":"90212",
    "addr:street":"Wilshire Blvd",
    "iso:country":"US",
    "sg:address":"9454 Wilshire Blvd",
    "sg:city":"Beverly Hills",
    "sg:classifiers":[
        {
            "category":"Personal",
            "type":"Services"
        }
    ],
    "sg:phone":"+1 310 556 7767",
    "sg:postcode":"90212",
    "sg:province":"CA",
    "sg:tags":[
        "mover"
    ],
    "sg:website":"www.northstarmoving.com/",
    "wof:name":"Northstar Moving Corp",
    "wof:placetype":"venue"
},
  "geometry": {"coordinates":[-118.39885099999999,34.066872],"type":"Point"}
}