{
  "type": "Feature",
  "properties": {
    "iso:country":"US",
    "sg:address":"4102 19th St",
    "sg:city":"San Francisco",
    "sg:classifiers":[
        {
            "category":"Personal",
            "subcategory":"Barber",
            "type":"Services"
        }
    ],
    "sg:phone":"+1 415 552 5101",
    "sg:postcode":"94114",
    "sg:province":"CA",
    "sg:website":"www.daddysbarbershop.com",
    "wof:name":"Daddy's Barbershop",
    "wof:placetype":"venue"
},
  "geometry": {"coordinates":[-122.435147,37.7594],"type":"Point"}
}