{
  "type": "Feature",
  "properties": {
    "addr:full":"1701 Long Beach Blvd Long Beach CA 90813",
    "addr:housenumber":"1701",
    "addr:postcode":"90813",
    "addr:street":"Long Beach Blvd",
    "iso:country":"US",
    "sg:address":"1701 Long Beach Blvd",
    "sg:city":"Long Beach",
    "sg:classifiers":[
        {
            "category":"Retail",
            "subcategory":"Auto Repair",
            "type":"Services"
        }
    ],
    "sg:phone":"+1 562 591 2280",
    "sg:postcode":"90813",
    "sg:province":"CA",
    "sg:website":"www.high-flow-mufflers.com",
    "wof:name":"Hi-Flow Mufflers",
    "wof:placetype":"venue"
},
  "geometry": {"coordinates":[-118.19000200000001,33.788799],"type":"Point"}
}