{
  "type": "Feature",
  "properties": {
    "iso:country":"US",
    "sg:address":"321 Isabel Ct",
    "sg:city":"Mc Farland",
    "sg:classifiers":[
        {
            "category":"Farming",
            "subcategory":"Farm & Veterinary Services",
            "type":"Manufacturing & Wholesale Goods"
        }
    ],
    "sg:phone":"+1 661 792 3647",
    "sg:postcode":"93250",
    "sg:province":"CA",
    "sg:tags":[
        "labor",
        "contractor"
    ],
    "wof:name":"Nunez Victor M FIC",
    "wof:placetype":"venue"
},
  "geometry": {"coordinates":[-119.223679,35.682763],"type":"Point"}
}