{
  "type": "Feature",
  "properties": {
    "iso:country":"US",
    "sg:address":"2041 S Santa Fe Ave",
    "sg:city":"Los Angeles",
    "sg:classifiers":[
        {
            "category":"Manufacturing",
            "subcategory":"Apparel",
            "type":"Manufacturing & Wholesale Goods"
        }
    ],
    "sg:phone":"+1 213 622 0811",
    "sg:postcode":"90021",
    "sg:province":"CA",
    "sg:tags":[
        "clothing"
    ],
    "wof:name":"R & J Co",
    "wof:placetype":"venue"
},
  "geometry": {"coordinates":[-118.230343,34.018958],"type":"Point"}
}