{
  "type": "Feature",
  "properties": {
    "iso:country":"US",
    "sg:address":"1160 Hargus Ave",
    "sg:city":"Vallejo",
    "sg:classifiers":[
        {
            "category":"Manufacturing",
            "subcategory":"Paper Products",
            "type":"Manufacturing & Wholesale Goods"
        }
    ],
    "sg:phone":"+1 707 642 3779",
    "sg:postcode":"94591",
    "sg:province":"CA",
    "sg:tags":[
        "bamboo"
    ],
    "wof:name":"Living Earth Gardens",
    "wof:placetype":"venue"
},
  "geometry": {"coordinates":[-122.212975,38.093723],"type":"Point"}
}