{
  "type": "Feature",
  "properties": {
    "addr:full":"529 N Adams St Dixon CA 95620",
    "addr:housenumber":"529",
    "addr:postcode":"95620",
    "addr:street":"N Adams St",
    "iso:country":"US",
    "sg:address":"529 N Adams St",
    "sg:city":"Dixon",
    "sg:classifiers":[
        {
            "category":"Shopping",
            "subcategory":"Gifts & Souvenirs",
            "type":"Retail Goods"
        }
    ],
    "sg:phone":"+1 707 678 8914",
    "sg:postcode":"95620",
    "sg:province":"CA",
    "sg:tags":[
        "shop"
    ],
    "wof:name":"Scholl's Heavenly Gifts",
    "wof:placetype":"venue"
},
  "geometry": {"coordinates":[-121.826098,38.450362],"type":"Point"}
}