{
  "type": "Feature",
  "properties": {
    "addr:full":"2536 Stonehaven Dr Sacramento CA 95827",
    "addr:housenumber":"2536",
    "addr:postcode":"95827",
    "addr:street":"Stonehaven Dr",
    "iso:country":"US",
    "sg:address":"2536 Stonehaven Dr",
    "sg:city":"Sacramento",
    "sg:classifiers":[
        {
            "category":"Bars & Pubs",
            "type":"Food & Drink"
        }
    ],
    "sg:phone":"+1 916 791 1717",
    "sg:postcode":"95827",
    "sg:province":"CA",
    "sg:tags":[
        "drinking"
    ],
    "wof:name":"Shady Bradys Tavern",
    "wof:placetype":"venue"
},
  "geometry": {"coordinates":[-121.34228299999999,38.576227],"type":"Point"}
}