{
  "type": "Feature",
  "properties": {
    "addr:full":"1761 California Ave Corona CA 92881",
    "addr:housenumber":"1761",
    "addr:postcode":"92881",
    "addr:street":"California Ave",
    "iso:country":"US",
    "sg:address":"1761 California Ave",
    "sg:city":"Corona",
    "sg:classifiers":[
        {
            "category":"Wholesale",
            "subcategory":"Plants",
            "type":"Manufacturing & Wholesale Goods"
        }
    ],
    "sg:phone":"+1 951 582 0944",
    "sg:postcode":"92881",
    "sg:province":"CA",
    "sg:tags":[
        "supply"
    ],
    "wof:name":"G S I Homestyles",
    "wof:placetype":"venue"
},
  "geometry": {"coordinates":[-117.538949,33.858875],"type":"Point"}
}