{
  "type": "Feature",
  "properties": {
    "addr:full":"1420 Curci Dr San Jose CA 95126",
    "addr:housenumber":"1420",
    "addr:postcode":"95126",
    "addr:street":"Curci Dr",
    "iso:country":"US",
    "sg:address":"1420 Curci Dr",
    "sg:city":"San Jose",
    "sg:classifiers":[
        {
            "category":"Social Services",
            "subcategory":"Retirement Home",
            "type":"Services"
        }
    ],
    "sg:phone":"+1 408 457 7315",
    "sg:postcode":"95126",
    "sg:province":"CA",
    "sg:website":"www.merrillgardens.com/assisted_...",
    "wof:name":"Merrill Gardens at Willow Glen",
    "wof:placetype":"venue"
},
  "geometry": {"coordinates":[-121.91415600000001,37.307848],"type":"Point"}
}