{
  "type": "Feature",
  "properties": {
    "addr:full":"4120 185th St Torrance CA 90504",
    "addr:housenumber":"4120",
    "addr:postcode":"90504",
    "addr:street":"185Th St",
    "iso:country":"US",
    "sg:address":"4120 185th St",
    "sg:city":"Torrance",
    "sg:classifiers":[
        {
            "category":"Social Services",
            "subcategory":"Child Care",
            "type":"Services"
        }
    ],
    "sg:phone":"+1 310 787 3010",
    "sg:postcode":"90504",
    "sg:province":"CA",
    "wof:name":"Childrens's Center",
    "wof:placetype":"venue"
},
  "geometry": {"coordinates":[-118.346844,33.862628],"type":"Point"}
}