{
  "type": "Feature",
  "properties": {
    "addr:full":"5 Journey Ste 250 Aliso Viejo CA 92656",
    "addr:housenumber":"5",
    "addr:postcode":"92656",
    "addr:street":"Journey Ste 250",
    "iso:country":"US",
    "sg:address":"5 Journey Ste 250",
    "sg:city":"Aliso Viejo",
    "sg:classifiers":[
        {
            "category":"Health Services",
            "subcategory":"Dentist",
            "type":"Services"
        }
    ],
    "sg:phone":"+1 949 360 1021",
    "sg:postcode":"92656",
    "sg:province":"CA",
    "sg:tags":[
        "cosmetic"
    ],
    "sg:website":"www.southcoastdentistry.com",
    "wof:name":"South Coast Dentistry",
    "wof:placetype":"venue"
},
  "geometry": {"coordinates":[-117.728398,33.569996],"type":"Point"}
}