{
  "type": "Feature",
  "properties": {
    "addr:full":"121 S Canyon Crest Dr Anaheim CA 92808",
    "addr:housenumber":"121",
    "addr:postcode":"92808",
    "addr:street":"S Canyon Crest Dr",
    "iso:country":"US",
    "sg:address":"121 S Canyon Crest Dr",
    "sg:city":"Anaheim",
    "sg:classifiers":[
        {
            "category":"Building & Trades",
            "subcategory":"Construction",
            "type":"Services"
        }
    ],
    "sg:phone":"+1 714 974 4280",
    "sg:postcode":"92808",
    "sg:province":"CA",
    "sg:tags":[
        "contractor"
    ],
    "wof:name":"Secrest Of Calif",
    "wof:placetype":"venue"
},
  "geometry": {"coordinates":[-117.76405699999999,33.861931],"type":"Point"}
}