{
  "type": "Feature",
  "properties": {
    "iso:country":"US",
    "sg:address":"703 Condor Pl",
    "sg:city":"Clayton",
    "sg:classifiers":[
        {
            "category":"Professional",
            "type":"Services"
        }
    ],
    "sg:phone":"+1 925 689 2039",
    "sg:postcode":"94517",
    "sg:province":"CA",
    "sg:tags":[
        "establishment"
    ],
    "wof:name":"Institute For Photometry & Rad",
    "wof:placetype":"venue"
},
  "geometry": {"coordinates":[-121.931645,37.95315],"type":"Point"}
}