{
  "type": "Feature",
  "properties": {
    "iso:country":"US",
    "sfac:artist":"Huang, Arlan",
    "sfac:created_at":"01/01/1970 12:33:27 AM +0000",
    "sfac:location_description":"City Department : Laguna Honda : North Residence : L4 : Northeast Wall",
    "sfac:medium":"Blown and laminated glass",
    "sfac:revision":"2-e9409de241129960fa14bfde629c08ad",
    "sfac:title":"Untitled [glass panels]",
    "wof:name":"Untitled [glass panels]",
    "wof:placetype":"venue"
},
  "geometry": {"coordinates":[-122.4556651,37.7478586],"type":"Point"}
}