{
  "type": "Feature",
  "properties": {
    "addr:full":"2435 E Valley Oaks Dr Visalia CA 93292",
    "addr:housenumber":"2435",
    "addr:postcode":"93292",
    "addr:street":"E Valley Oaks Dr",
    "iso:country":"US",
    "sg:address":"2435 E Valley Oaks Dr",
    "sg:city":"Visalia",
    "sg:classifiers":[
        {
            "category":"Building & Trades",
            "subcategory":"Construction",
            "type":"Services"
        }
    ],
    "sg:phone":"+1 559 635 9637",
    "sg:postcode":"93292",
    "sg:province":"CA",
    "sg:tags":[
        "designer",
        "dealer",
        "pool",
        "swimming"
    ],
    "sg:website":"www.paradisepool.com",
    "wof:name":"Paradise Pools Aquatech",
    "wof:placetype":"venue"
},
  "geometry": {"coordinates":[-119.264661,36.330227],"type":"Point"}
}