{
  "type": "Feature",
  "properties": {
    "iso:country":"US",
    "sg:address":"713 S Academy Ave",
    "sg:city":"Sanger",
    "sg:classifiers":[
        {
            "category":"Organizations",
            "subcategory":"Religious Organization",
            "type":"Services"
        }
    ],
    "sg:phone":"+1 559 875 2470",
    "sg:postcode":"93657",
    "sg:province":"CA",
    "wof:name":"Christian Outreach",
    "wof:placetype":"venue"
},
  "geometry": {"coordinates":[-119.556394,36.734969],"type":"Point"}
}