{
  "type": "Feature",
  "properties": {
    "addr:full":"368 S California Ave Palo Alto CA 94306",
    "addr:housenumber":"368",
    "addr:postcode":"94306",
    "addr:street":"S California Ave",
    "iso:country":"US",
    "sg:address":"368 S California Ave",
    "sg:city":"Palo Alto",
    "sg:classifiers":[
        {
            "category":"Health Services",
            "subcategory":"Chiropractor",
            "type":"Services"
        }
    ],
    "sg:phone":"+1 650 328 9400",
    "sg:postcode":"94306",
    "sg:province":"CA",
    "wof:name":"Body Therapy Ctr",
    "wof:placetype":"venue"
},
  "geometry": {"coordinates":[-122.14429800000001,37.42717],"type":"Point"}
}