{
  "type": "Feature",
  "properties": {
    "iso:country":"US",
    "sg:address":"368 S California Ave",
    "sg:city":"Palo Alto",
    "sg:classifiers":[
        {
            "category":"Health Services",
            "subcategory":"Chiropractor",
            "type":"Services"
        }
    ],
    "sg:phone":"+1 650 328 9400",
    "sg:postcode":"94306",
    "sg:province":"CA",
    "wof:name":"Body Therapy Ctr",
    "wof:placetype":"venue"
},
  "geometry": {"coordinates":[-122.144298,37.42717],"type":"Point"}
}