{
  "type": "Feature",
  "properties": {
    "iso:country":"US",
    "sg:address":"1390 Lead Hill Blvd",
    "sg:city":"Roseville",
    "sg:classifiers":[
        {
            "category":"Utilities",
            "subcategory":"Telephone",
            "type":"Services"
        }
    ],
    "sg:phone":"+1 916 677 3000",
    "sg:postcode":"95678",
    "sg:province":"CA",
    "sg:tags":[
        "communications",
        "company"
    ],
    "sg:website":"www.xo.com",
    "wof:name":"X O Communications Inc",
    "wof:placetype":"venue"
},
  "geometry": {"coordinates":[-121.253703,38.74821],"type":"Point"}
}