{
  "type": "Feature",
  "properties": {
    "addr:full":"2736 S King Rd San Jose CA 95122",
    "addr:housenumber":"2736",
    "addr:postcode":"95122",
    "addr:street":"S King Rd",
    "iso:country":"US",
    "sg:address":"2736 S King Rd",
    "sg:city":"San Jose",
    "sg:classifiers":[
        {
            "category":"Manufacturing",
            "subcategory":"Motor Vehicles & Parts",
            "type":"Manufacturing & Wholesale Goods"
        }
    ],
    "sg:phone":"+1 408 828 5402",
    "sg:postcode":"95122",
    "sg:province":"CA",
    "sg:tags":[
        "mfg"
    ],
    "wof:name":"Carlos Wire Wheels",
    "wof:placetype":"venue"
},
  "geometry": {"coordinates":[-121.81922400000001,37.315373],"type":"Point"}
}