{
  "type": "Feature",
  "properties": {
    "iso:country":"US",
    "sg:address":"5015 W Ave L",
    "sg:city":"Lancaster",
    "sg:classifiers":[
        {
            "category":"Utilities",
            "subcategory":"Water",
            "type":"Services"
        }
    ],
    "sg:phone":"+1 661 943 9001",
    "sg:postcode":"93536",
    "sg:province":"CA",
    "sg:tags":[
        "system",
        "supply"
    ],
    "wof:name":"California Water Service Co",
    "wof:placetype":"venue"
},
  "geometry": {"coordinates":[-118.219028,34.660322],"type":"Point"}
}