{
  "type": "Feature",
  "properties": {
    "addr:full":"5015 W Ave L Lancaster CA 93536",
    "addr:housenumber":"5015",
    "addr:postcode":"93536",
    "addr:street":"W Ave L",
    "iso:country":"US",
    "sg:address":"5015 W Ave L",
    "sg:city":"Lancaster",
    "sg:classifiers":[
        {
            "category":"Utilities",
            "subcategory":"Water",
            "type":"Services"
        }
    ],
    "sg:phone":"+1 661 943 9001",
    "sg:postcode":"93536",
    "sg:province":"CA",
    "sg:tags":[
        "system",
        "supply"
    ],
    "wof:name":"California Water Service Co",
    "wof:placetype":"venue"
},
  "geometry": {"coordinates":[-118.21902799999999,34.660322],"type":"Point"}
}