{
  "type": "Feature",
  "properties": {
    "iso:country":"US",
    "sg:address":"3112 Goodview Trl",
    "sg:city":"Los Angeles",
    "sg:classifiers":[
        {
            "category":"Personal",
            "type":"Services"
        }
    ],
    "sg:phone":"+1 310 922 7825",
    "sg:postcode":"90068",
    "sg:province":"CA",
    "sg:tags":[
        "local"
    ],
    "wof:name":"Bernard Alexander Piano Service",
    "wof:placetype":"venue"
},
  "geometry": {"coordinates":[-118.348753,34.12458],"type":"Point"}
}