{
  "type": "Feature",
  "properties": {
    "addr:full":"33654 Couser Canyon Rd Valley Center CA 92082",
    "addr:housenumber":"33654",
    "addr:postcode":"92082",
    "addr:street":"Couser Canyon Rd",
    "iso:country":"US",
    "sg:address":"33654 Couser Canyon Rd",
    "sg:city":"Valley Center",
    "sg:classifiers":[
        {
            "category":"Farming",
            "subcategory":"Livestock Farm",
            "type":"Manufacturing & Wholesale Goods"
        }
    ],
    "sg:phone":"+1 760 742 0477",
    "sg:postcode":"92082",
    "sg:province":"CA",
    "sg:tags":[
        "animal",
        "general"
    ],
    "wof:name":"Ortiz Ranch",
    "wof:placetype":"venue"
},
  "geometry": {"coordinates":[-117.11500700000001,33.326718],"type":"Point"}
}