{
  "type": "Feature",
  "properties": {
    "addr:full":"6300 White Ln Bakersfield CA 93309",
    "addr:housenumber":"6300",
    "addr:postcode":"93309",
    "addr:street":"White Ln",
    "iso:country":"US",
    "sg:address":"6300 White Ln",
    "sg:city":"Bakersfield",
    "sg:classifiers":[
        {
            "category":"Wholesale",
            "subcategory":"Machinery & Supplies",
            "type":"Manufacturing & Wholesale Goods"
        }
    ],
    "sg:phone":"+1 661 834 8550",
    "sg:postcode":"93309",
    "sg:province":"CA",
    "sg:tags":[
        "equipment",
        "safety",
        "clothing"
    ],
    "wof:name":"Red Wing Shoe Store",
    "wof:placetype":"venue"
},
  "geometry": {"coordinates":[-119.073154,35.318265],"type":"Point"}
}