{
  "type": "Feature",
  "properties": {
    "iso:country":"US",
    "sg:address":"9816 Blue Lake Dr",
    "sg:city":"Folsom",
    "sg:classifiers":[
        {
            "category":"Building & Trades",
            "subcategory":"Construction",
            "type":"Services"
        }
    ],
    "sg:phone":"+1 916 988 2499",
    "sg:postcode":"95630",
    "sg:province":"CA",
    "sg:tags":[
        "concrete",
        "contractor"
    ],
    "wof:name":"Ben Jones Concrete",
    "wof:placetype":"venue"
},
  "geometry": {"coordinates":[-121.18037,38.69593],"type":"Point"}
}