{
  "type": "Feature",
  "properties": {
    "iso:country":"US",
    "sg:address":"150 N Lincoln Way",
    "sg:city":"Galt",
    "sg:classifiers":[
        {
            "category":"Real Estate",
            "subcategory":"Real Estate Agent",
            "type":"Services"
        }
    ],
    "sg:phone":"+1 209 744 7610",
    "sg:postcode":"95632",
    "sg:province":"CA",
    "sg:website":"www.realtyexecutivesgalt.com",
    "wof:name":"Realty Executives GB & Assoc",
    "wof:placetype":"venue"
},
  "geometry": {"coordinates":[-121.300399,38.256006],"type":"Point"}
}