{
  "type": "Feature",
  "properties": {
    "addr:full":"4641 Telegraph Rd Los Angeles CA 90022",
    "addr:housenumber":"4641",
    "addr:postcode":"90022",
    "addr:street":"Telegraph Rd",
    "iso:country":"US",
    "sg:address":"4641 Telegraph Rd",
    "sg:city":"Los Angeles",
    "sg:classifiers":[
        {
            "category":"Manufacturing",
            "subcategory":"Metals",
            "type":"Manufacturing & Wholesale Goods"
        }
    ],
    "sg:phone":"+1 323 263 0028",
    "sg:postcode":"90022",
    "sg:province":"CA",
    "sg:tags":[
        "plating"
    ],
    "wof:name":"F Nicholas Retinning Co",
    "wof:placetype":"venue"
},
  "geometry": {"coordinates":[-118.170524,34.015926],"type":"Point"}
}