{
  "type": "Feature",
  "properties": {
    "iso:country":"US",
    "sg:address":"2451 Eastman Ave Ste 6",
    "sg:city":"Oxnard",
    "sg:classifiers":[
        {
            "category":"Wholesale",
            "subcategory":"Office Equipment",
            "type":"Manufacturing & Wholesale Goods"
        },
        {
            "category":"Professional",
            "subcategory":"Printing & Photocopies",
            "type":"Services"
        },
        {
            "category":"Shopping",
            "subcategory":"Computers & Home Electronics",
            "type":"Retail Goods"
        }
    ],
    "sg:phone":"+1 805 981 2282",
    "sg:postcode":"93030",
    "sg:province":"CA",
    "sg:tags":[
        "scanning",
        "printer",
        "form",
        "supply",
        "services-commercial",
        "printers-business",
        "plotting"
    ],
    "wof:name":"Flyerweb Printing",
    "wof:placetype":"venue"
},
  "geometry": {"coordinates":[-119.143366,34.198986],"type":"Point"}
}