{
  "type": "Feature",
  "properties": {
    "iso:country":"US",
    "sg:address":"124 Petaluma Blvd S",
    "sg:city":"Petaluma",
    "sg:classifiers":[
        {
            "category":"Autos & Motor Vehicles",
            "subcategory":"Fuel & Gas Station",
            "type":"Retail Goods"
        },
        {
            "category":"Banks & Credit Unions",
            "subcategory":"Financial Services",
            "type":"Services"
        },
        {
            "category":"Banks & Credit Unions",
            "subcategory":"Atm",
            "type":"Services"
        },
        {
            "category":"Food & Beverages",
            "subcategory":"Groceries & Convenience Stores",
            "type":"Retail Goods"
        }
    ],
    "sg:phone":"+1 707 778 3448",
    "sg:postcode":"94952",
    "sg:province":"CA",
    "sg:tags":[
        "money",
        "location",
        "order"
    ],
    "sg:website":"http://www.7-eleven.com",
    "wof:name":"7-Eleven",
    "wof:placetype":"venue"
},
  "geometry": {"coordinates":[-122.63775099999999,38.23283],"type":"Point"}
}