{
  "type": "Feature",
  "properties": {
    "addr:full":"234 H St Bakersfield CA 93304",
    "addr:housenumber":"234",
    "addr:postcode":"93304",
    "addr:street":"H St",
    "iso:country":"US",
    "sg:address":"234 H St",
    "sg:city":"Bakersfield",
    "sg:classifiers":[
        {
            "category":"Professional",
            "subcategory":"Engineering",
            "type":"Services"
        }
    ],
    "sg:phone":"+1 661 326 8294",
    "sg:postcode":"93304",
    "sg:province":"CA",
    "sg:tags":[
        "engineer"
    ],
    "wof:name":"W W Engineering",
    "wof:placetype":"venue"
},
  "geometry": {"coordinates":[-119.021207,35.358862],"type":"Point"}
}