{
  "type": "Feature",
  "properties": {
    "addr:full":"14760 Excelsior Dr La Mirada CA 90638",
    "addr:housenumber":"14760",
    "addr:postcode":"90638",
    "addr:street":"Excelsior Dr",
    "iso:country":"US",
    "sg:address":"14760 Excelsior Dr",
    "sg:city":"La Mirada",
    "sg:classifiers":[
        {
            "category":"Wholesale",
            "subcategory":"Construction Materials",
            "type":"Manufacturing & Wholesale Goods"
        }
    ],
    "sg:phone":"+1 714 521 8649",
    "sg:postcode":"90638",
    "sg:province":"CA",
    "sg:tags":[
        "repair",
        "drywall",
        "kit"
    ],
    "wof:name":"Cascade Development",
    "wof:placetype":"venue"
},
  "geometry": {"coordinates":[-118.016051,33.894273],"type":"Point"}
}