{
  "type": "Feature",
  "properties": {
    "addr:full":"161 Erie St San Francisco CA 94103",
    "addr:housenumber":"161",
    "addr:postcode":"94103",
    "addr:street":"Erie St",
    "iso:country":"US",
    "sg:address":"161 Erie St",
    "sg:city":"San Francisco",
    "sg:classifiers":[
        {
            "category":"Banks & Credit Unions",
            "subcategory":"Financial Services",
            "type":"Services"
        }
    ],
    "sg:phone":"+1 415 934 6000",
    "sg:postcode":"94103",
    "sg:province":"CA",
    "sg:tags":[
        "company",
        "holding"
    ],
    "wof:name":"Erie Street Holding",
    "wof:placetype":"venue"
},
  "geometry": {"coordinates":[-122.419489,37.769017],"type":"Point"}
}