{
  "type": "Feature",
  "properties": {
    "iso:country":"US",
    "sg:address":"73350 el Paseo",
    "sg:city":"Palm Desert",
    "sg:classifiers":[
        {
            "category":"Building & Trades",
            "subcategory":"Landscaping Services",
            "type":"Services"
        }
    ],
    "sg:phone":"+1 760 340 6255",
    "sg:postcode":"92260",
    "sg:province":"CA",
    "sg:tags":[
        "landscape"
    ],
    "wof:name":"Ae Design",
    "wof:placetype":"venue"
},
  "geometry": {"coordinates":[-116.386127,33.719847],"type":"Point"}
}