{
  "type": "Feature",
  "properties": {
    "addr:full":"20254 Vista Ct Cupertino CA 95014",
    "addr:housenumber":"20254",
    "addr:postcode":"95014",
    "addr:street":"Vista Ct",
    "iso:country":"US",
    "sg:address":"20254 Vista Ct",
    "sg:city":"Cupertino",
    "sg:classifiers":[
        {
            "category":"Wholesale",
            "subcategory":"Machinery & Supplies",
            "type":"Manufacturing & Wholesale Goods"
        }
    ],
    "sg:phone":"+1 408 446 3804",
    "sg:postcode":"95014",
    "sg:province":"CA",
    "sg:tags":[
        "equipment",
        "industrial"
    ],
    "wof:name":"Foamlinx",
    "wof:placetype":"venue"
},
  "geometry": {"coordinates":[-122.027939,37.325075],"type":"Point"}
}