{
  "type": "Feature",
  "properties": {
    "iso:country":"US",
    "sg:address":"18182 Riverside Cir",
    "sg:city":"Huntington Beach",
    "sg:classifiers":[
        {
            "category":"Wholesale",
            "subcategory":"Non-durable Goods",
            "type":"Manufacturing & Wholesale Goods"
        }
    ],
    "sg:phone":"+1 714 848 6114",
    "sg:postcode":"92648",
    "sg:province":"CA",
    "wof:name":"Southeast Distributors",
    "wof:placetype":"venue"
},
  "geometry": {"coordinates":[-118.01967500000001,33.698471],"type":"Point"}
}