{
  "type": "Feature",
  "properties": {
    "iso:country":"US",
    "sg:address":"11738 San Marino Dr",
    "sg:city":"Rancho Cucamonga",
    "sg:classifiers":[
        {
            "category":"Manufacturing",
            "subcategory":"Metals",
            "type":"Manufacturing & Wholesale Goods"
        }
    ],
    "sg:phone":"+1 909 466 0700",
    "sg:postcode":"91730",
    "sg:province":"CA",
    "sg:tags":[
        "hardware"
    ],
    "wof:name":"Crown Metal Mfg Co",
    "wof:placetype":"venue"
},
  "geometry": {"coordinates":[-117.54686100000001,34.083367],"type":"Point"}
}