{
  "type": "Feature",
  "properties": {
    "addr:full":"2070 Feliz Rd Novato CA 94945",
    "addr:postcode":"2070;94945",
    "addr:street":"Feliz Rd",
    "iso:country":"US",
    "sg:address":"2070 Feliz Rd",
    "sg:city":"Novato",
    "sg:classifiers":[
        {
            "category":"Professional",
            "type":"Services"
        }
    ],
    "sg:phone":"+1 415 246 5055",
    "sg:postcode":"94945",
    "sg:province":"CA",
    "wof:name":"Staging By Cynthia",
    "wof:placetype":"venue"
},
  "geometry": {"coordinates":[-122.591915,38.117123],"type":"Point"}
}