{
  "type": "Feature",
  "properties": {
    "addr:full":"2316 Via Pinale Palos Vrds Ests CA 90274",
    "addr:housenumber":"2316",
    "addr:postcode":"90274",
    "addr:street":"Via Pinale Palos Vrds Ests",
    "iso:country":"US",
    "sg:address":"2316 Via Pinale",
    "sg:city":"Palos Vrds Ests",
    "sg:classifiers":[
        {
            "category":"Health Services",
            "subcategory":"Doctor",
            "type":"Services"
        }
    ],
    "sg:phone":"+1 310 375 8011",
    "sg:postcode":"90274",
    "sg:province":"CA",
    "sg:tags":[
        "physician",
        "surgeon"
    ],
    "wof:name":"Rita R Rogers MD",
    "wof:placetype":"venue"
},
  "geometry": {"coordinates":[-118.389161,33.79818],"type":"Point"}
}