{
  "type": "Feature",
  "properties": {
    "addr:full":"3960 Normal St. San Diego CA 92103",
    "addr:housenumber":"3960",
    "addr:postcode":"92103",
    "addr:street":"Normal St.",
    "iso:country":"US",
    "sg:address":"3960 Normal St.",
    "sg:city":"San Diego",
    "sg:classifiers":[
        {
            "category":"Personal",
            "subcategory":"Beauty Salon",
            "type":"Services"
        }
    ],
    "sg:postcode":"92103",
    "sg:province":"CA",
    "sg:tags":[
        "spa"
    ],
    "sg:website":"www.bokujoy.com",
    "wof:name":"Boku Joy",
    "wof:placetype":"venue"
},
  "geometry": {"coordinates":[-117.14903200000001,32.750388],"type":"Point"}
}