{
  "type": "Feature",
  "properties": {
    "addr:full":"8604 Willow Dr Rancho Cucamonga CA 91730",
    "addr:housenumber":"8604",
    "addr:postcode":"91730",
    "addr:street":"Willow Dr",
    "iso:country":"US",
    "sg:address":"8604 Willow Dr",
    "sg:city":"Rancho Cucamonga",
    "sg:classifiers":[
        {
            "category":"Professional",
            "subcategory":"Management & Consulting",
            "type":"Services"
        }
    ],
    "sg:phone":"+1 909 484 0751",
    "sg:postcode":"91730",
    "sg:province":"CA",
    "sg:tags":[
        "consultant"
    ],
    "wof:name":"Valle Consulting",
    "wof:placetype":"venue"
},
  "geometry": {"coordinates":[-117.588717,34.09653],"type":"Point"}
}