{
  "type": "Feature",
  "properties": {
    "addr:full":"1101 Broadway Burlingame CA 94010",
    "addr:housenumber":"1101",
    "addr:postcode":"94010",
    "addr:street":"Broadway",
    "iso:country":"US",
    "sg:address":"1101 Broadway",
    "sg:city":"Burlingame",
    "sg:classifiers":[
        {
            "category":"Autos & Motor Vehicles",
            "subcategory":"Fuel & Gas Station",
            "type":"Retail Goods"
        }
    ],
    "sg:phone":"+1 650 579 5508",
    "sg:postcode":"94010",
    "sg:province":"CA",
    "wof:name":"Chevron Stations",
    "wof:placetype":"venue"
},
  "geometry": {"coordinates":[-122.36354900000001,37.587223],"type":"Point"}
}