{
  "type": "Feature",
  "properties": {
    "iso:country":"US",
    "sg:address":"49470 Ave Vista Bonita",
    "sg:city":"La Quinta",
    "sg:classifiers":[
        {
            "category":"Freight",
            "type":"Transportation"
        }
    ],
    "sg:phone":"+1 760 564 3277",
    "sg:postcode":"92253",
    "sg:province":"CA",
    "sg:tags":[
        "general"
    ],
    "wof:name":"Dsw Distribution",
    "wof:placetype":"venue"
},
  "geometry": {"coordinates":[-116.316157,33.683978],"type":"Point"}
}