{
  "type": "Feature",
  "properties": {
    "addr:full":"13945 Poway Rd Poway CA 92064",
    "addr:housenumber":"13945",
    "addr:postcode":"ca 92064",
    "addr:street":"Poway Rd",
    "iso:country":"US",
    "sg:address":"13945 Poway Rd",
    "sg:city":"Poway",
    "sg:classifiers":[
        {
            "category":"Retail",
            "subcategory":"Auto Repair",
            "type":"Services"
        }
    ],
    "sg:phone":"+1 858 748 6766",
    "sg:postcode":"92064",
    "sg:province":"CA",
    "sg:tags":[
        "transmission",
        "general"
    ],
    "wof:name":"Mike's Transmissions",
    "wof:placetype":"venue"
},
  "geometry": {"coordinates":[-117.02804500000001,32.956279],"type":"Point"}
}