{
  "type": "Feature",
  "properties": {
    "addr:full":"1091 Palomino Rd Santa Barbara CA 93105",
    "addr:housenumber":"1091",
    "addr:postcode":"93105",
    "addr:street":"Palomino Rd",
    "iso:country":"US",
    "sg:address":"1091 Palomino Rd",
    "sg:city":"Santa Barbara",
    "sg:classifiers":[
        {
            "category":"Wholesale",
            "subcategory":"Electrical",
            "type":"Manufacturing & Wholesale Goods"
        }
    ],
    "sg:phone":"+1 805 682 4833",
    "sg:postcode":"93105",
    "sg:province":"CA",
    "sg:tags":[
        "alarm",
        "sprinkler",
        "system"
    ],
    "wof:name":"Santa Barbara Fire Protection",
    "wof:placetype":"venue"
},
  "geometry": {"coordinates":[-119.715785,34.455144],"type":"Point"}
}