{
  "type": "Feature",
  "properties": {
    "iso:country":"US",
    "sg:address":"6690 Mission Gorge Rd",
    "sg:city":"San Diego",
    "sg:classifiers":[
        {
            "category":"Wholesale",
            "subcategory":"Medical Equipment & Supplies",
            "type":"Manufacturing & Wholesale Goods"
        }
    ],
    "sg:phone":"+1 619 584 8369",
    "sg:postcode":"92120",
    "sg:province":"CA",
    "sg:tags":[
        "physician",
        "surgeon"
    ],
    "wof:name":"Pro Uniforms",
    "wof:placetype":"venue"
},
  "geometry": {"coordinates":[-117.096198,32.794949],"type":"Point"}
}