{
  "type": "Feature",
  "properties": {
    "iso:country":"US",
    "sg:address":"1500 7th St",
    "sg:city":"Sacramento",
    "sg:classifiers":[
        {
            "category":"Professional",
            "type":"Services"
        }
    ],
    "sg:phone":"+1 916 444 8811",
    "sg:postcode":"95814",
    "sg:province":"CA",
    "sg:tags":[
        "establishment"
    ],
    "wof:name":"EBOB LTD",
    "wof:placetype":"venue"
},
  "geometry": {"coordinates":[-121.499374,38.57693],"type":"Point"}
}