{
  "type": "Feature",
  "properties": {
    "addr:full":"19430 Bridgewater Ln Riverside CA 92508",
    "addr:housenumber":"19430",
    "addr:postcode":"92508",
    "addr:street":"Bridgewater Ln",
    "iso:country":"US",
    "sg:address":"19430 Bridgewater Ln",
    "sg:city":"Riverside",
    "sg:classifiers":[
        {
            "category":"Shopping",
            "subcategory":"Gifts & Souvenirs",
            "type":"Retail Goods"
        }
    ],
    "sg:phone":"+1 951 780 5921",
    "sg:postcode":"92508",
    "sg:province":"CA",
    "wof:name":"Blurayns Boutique",
    "wof:placetype":"venue"
},
  "geometry": {"coordinates":[-117.323048,33.881054],"type":"Point"}
}