{
  "type": "Feature",
  "properties": {
    "addr:full":"531 W Lodi Ave Lodi CA 95240",
    "addr:housenumber":"531",
    "addr:postcode":"95240",
    "addr:street":"W Lodi Ave",
    "iso:country":"US",
    "sg:address":"531 W Lodi Ave",
    "sg:city":"Lodi",
    "sg:classifiers":[
        {
            "category":"Shopping",
            "subcategory":"Clothing, Apparel, & Fashions",
            "type":"Retail Goods"
        }
    ],
    "sg:phone":"+1 209 369 7343",
    "sg:postcode":"95240",
    "sg:province":"CA",
    "sg:tags":[
        "uniform"
    ],
    "wof:name":"Uniformity",
    "wof:placetype":"venue"
},
  "geometry": {"coordinates":[-121.279365,38.130019],"type":"Point"}
}