{
  "type": "Feature",
  "properties": {
    "iso:country":"US",
    "sg:address":"8444 Wilshire Blvd",
    "sg:city":"Beverly Hills",
    "sg:classifiers":[
        {
            "category":"Professional",
            "subcategory":"Art Services",
            "type":"Services"
        }
    ],
    "sg:phone":"+1 323 655 6944",
    "sg:postcode":"90211",
    "sg:province":"CA",
    "sg:tags":[
        "artist"
    ],
    "wof:name":"88 Phases",
    "wof:placetype":"venue"
},
  "geometry": {"coordinates":[-118.376167,34.065175],"type":"Point"}
}