{
  "type": "Feature",
  "properties": {
    "addr:full":"8402 Hermosa Dr Riverside CA 92504",
    "addr:housenumber":"8402",
    "addr:postcode":"92504",
    "addr:street":"Hermosa Dr",
    "iso:country":"US",
    "sg:address":"8402 Hermosa Dr",
    "sg:city":"Riverside",
    "sg:classifiers":[
        {
            "category":"Building & Trades",
            "subcategory":"Electrical",
            "type":"Services"
        }
    ],
    "sg:phone":"+1 951 789 8929",
    "sg:postcode":"92504",
    "sg:province":"CA",
    "sg:tags":[
        "electric",
        "contractor"
    ],
    "wof:name":"Windsor Heights Electric",
    "wof:placetype":"venue"
},
  "geometry": {"coordinates":[-117.400156,33.901517],"type":"Point"}
}