{
  "type": "Feature",
  "properties": {
    "addr:full":"13227 Aubrey St Poway CA 92064",
    "addr:housenumber":"13227",
    "addr:postcode":"ca 92064",
    "addr:street":"Aubrey St",
    "iso:country":"US",
    "sg:address":"13227 Aubrey St",
    "sg:city":"Poway",
    "sg:classifiers":[
        {
            "category":"Professional",
            "type":"Services"
        }
    ],
    "sg:phone":"+1 858 748 5072",
    "sg:postcode":"92064",
    "sg:province":"CA",
    "wof:name":"Wcas Inc",
    "wof:placetype":"venue"
},
  "geometry": {"coordinates":[-117.043947,32.971477],"type":"Point"}
}