{
  "type": "Feature",
  "properties": {
    "addr:full":"2434 Dayton Rd Chico CA 95928",
    "addr:housenumber":"2434",
    "addr:postcode":"95928",
    "addr:street":"Dayton Rd",
    "iso:country":"US",
    "sg:address":"2434 Dayton Rd",
    "sg:city":"Chico",
    "sg:classifiers":[
        {
            "category":"Building & Trades",
            "subcategory":"Construction",
            "type":"Services"
        }
    ],
    "sg:phone":"+1 530 894 2439",
    "sg:postcode":"95928",
    "sg:province":"CA",
    "sg:tags":[
        "designer",
        "marine",
        "contractor"
    ],
    "wof:name":"On Mark Marine",
    "wof:placetype":"venue"
},
  "geometry": {"coordinates":[-121.852777,39.691421],"type":"Point"}
}