{
  "type": "Feature",
  "properties": {
    "addr:full":"121 Hacienda Dr Calexico CA 92231",
    "addr:housenumber":"121",
    "addr:postcode":"92231",
    "addr:street":"Hacienda Dr",
    "iso:country":"US",
    "sg:address":"121 Hacienda Dr",
    "sg:city":"Calexico",
    "sg:classifiers":[
        {
            "category":"Shopping",
            "type":"Retail Goods"
        }
    ],
    "sg:phone":"+1 760 357 3222",
    "sg:postcode":"92231",
    "sg:province":"CA",
    "sg:tags":[
        "plant",
        "flower",
        "tree",
        "artificial"
    ],
    "wof:name":"Floreria Karina By Luis & Pily",
    "wof:placetype":"venue"
},
  "geometry": {"coordinates":[-115.49992,32.682569],"type":"Point"}
}