{
  "type": "Feature",
  "properties": {
    "iso:country":"US",
    "sg:address":"345 Encino Dr",
    "sg:city":"Vista",
    "sg:classifiers":[
        {
            "category":"Retail",
            "subcategory":"Portrait Studio",
            "type":"Services"
        }
    ],
    "sg:phone":"+1 760 941 9628",
    "sg:postcode":"92083",
    "sg:province":"CA",
    "sg:tags":[
        "photographer"
    ],
    "wof:name":"Mike Shriver Photography",
    "wof:placetype":"venue"
},
  "geometry": {"coordinates":[-117.252956,33.224319],"type":"Point"}
}