{
  "type": "Feature",
  "properties": {
    "iso:country":"US",
    "sg:address":"355 E Park Ave",
    "sg:city":"El Cajon",
    "sg:classifiers":[
        {
            "category":"Professional",
            "subcategory":"Lawyer & Legal Services",
            "type":"Services"
        }
    ],
    "sg:phone":"+1 619 440 0190",
    "sg:postcode":"92020",
    "sg:province":"CA",
    "sg:tags":[
        "attorney"
    ],
    "wof:name":"David Estes Attorney At Law",
    "wof:placetype":"venue"
},
  "geometry": {"coordinates":[-116.959481,32.797419],"type":"Point"}
}