{
  "type": "Feature",
  "properties": {
    "addr:full":"1700 Space Park Dr Santa Clara CA 95054",
    "addr:housenumber":"1700",
    "addr:postcode":"95054",
    "addr:street":"Space Park Dr",
    "iso:country":"US",
    "sg:address":"1700 Space Park Dr",
    "sg:city":"Santa Clara",
    "sg:classifiers":[
        {
            "category":"Building & Trades",
            "subcategory":"Construction",
            "type":"Services"
        }
    ],
    "sg:phone":"+1 559 645 4523",
    "sg:postcode":"95054",
    "sg:province":"CA",
    "sg:tags":[
        "contractor"
    ],
    "wof:name":"Maywood Banquet Hall",
    "wof:placetype":"venue"
},
  "geometry": {"coordinates":[-121.959,37.3764],"type":"Point"}
}