{
  "type": "Feature",
  "properties": {
    "iso:country":"US",
    "sg:address":"657 W Sierra Ave",
    "sg:city":"Fresno",
    "sg:classifiers":[
        {
            "category":"Real Estate",
            "subcategory":"Real Estate Operator",
            "type":"Services"
        }
    ],
    "sg:phone":"+1 559 431 0166",
    "sg:postcode":"93704",
    "sg:province":"CA",
    "sg:tags":[
        "building",
        "apartment"
    ],
    "wof:name":"Rancho Sierra Apartments",
    "wof:placetype":"venue"
},
  "geometry": {"coordinates":[-119.804794,36.83001],"type":"Point"}
}