{
  "type": "Feature",
  "properties": {
    "iso:country":"US",
    "sg:address":"455 Main St",
    "sg:city":"Newcastle",
    "sg:classifiers":[
        {
            "category":"Professional",
            "type":"Services"
        }
    ],
    "sg:phone":"+1 916 663 5053",
    "sg:postcode":"95658",
    "sg:province":"CA",
    "sg:tags":[
        "establishment"
    ],
    "wof:name":"Capstone Planning & Control",
    "wof:placetype":"venue"
},
  "geometry": {"coordinates":[-121.13382900000001,38.874802],"type":"Point"}
}