{
  "type": "Feature",
  "properties": {
    "addr:full":"570 Chapman Dr Corte Madera CA 94925",
    "addr:housenumber":"570",
    "addr:postcode":"94925",
    "addr:street":"Chapman Dr",
    "iso:country":"US",
    "sg:address":"570 Chapman Dr",
    "sg:city":"Corte Madera",
    "sg:classifiers":[
        {
            "category":"Wholesale",
            "subcategory":"Durable Goods & Equipment",
            "type":"Manufacturing & Wholesale Goods"
        }
    ],
    "sg:phone":"+1 415 927 7130",
    "sg:postcode":"94925",
    "sg:province":"CA",
    "sg:tags":[
        "laboratory",
        "supply"
    ],
    "sg:website":"www.booksonnet.com",
    "wof:name":"Genesis Enterprises",
    "wof:placetype":"venue"
},
  "geometry": {"coordinates":[-122.524188,37.921121],"type":"Point"}
}