{
  "type": "Feature",
  "properties": {
    "addr:full":"3517 Marconi Ave Sacramento CA 95821",
    "addr:housenumber":"3517",
    "addr:postcode":"95821",
    "addr:street":"Marconi Ave",
    "iso:country":"US",
    "sg:address":"3517 Marconi Ave",
    "sg:city":"Sacramento",
    "sg:classifiers":[
        {
            "category":"Real Estate",
            "subcategory":"Real Estate Operator",
            "type":"Services"
        }
    ],
    "sg:phone":"+1 916 487 4693",
    "sg:postcode":"95821",
    "sg:province":"CA",
    "sg:tags":[
        "building",
        "nonresidential"
    ],
    "wof:name":"Phelan Helen",
    "wof:placetype":"venue"
},
  "geometry": {"coordinates":[-121.380781,38.617841],"type":"Point"}
}