{
  "type": "Feature",
  "properties": {
    "addr:full":"1409 Broadway Chula Vista CA 91911",
    "addr:housenumber":"1409",
    "addr:postcode":"91911",
    "addr:street":"Broadway",
    "iso:country":"US",
    "sg:address":"1409 Broadway",
    "sg:city":"Chula Vista",
    "sg:classifiers":[
        {
            "category":"Autos & Motor Vehicles",
            "subcategory":"Auto Supplies",
            "type":"Retail Goods"
        }
    ],
    "sg:phone":"+1 619 426 1100",
    "sg:postcode":"91911",
    "sg:province":"CA",
    "sg:tags":[
        "automobile",
        "stereo",
        "radio"
    ],
    "wof:name":"Higher Level",
    "wof:placetype":"venue"
},
  "geometry": {"coordinates":[-117.07805,32.602055],"type":"Point"}
}