{
  "type": "Feature",
  "properties": {
    "addr:full":"201 S Kinneloa Ave Pasadena CA 91107",
    "addr:housenumber":"201",
    "addr:postcode":"91107",
    "addr:street":"S Kinneloa Ave",
    "iso:country":"US",
    "sg:address":"201 S Kinneloa Ave",
    "sg:city":"Pasadena",
    "sg:classifiers":[
        {
            "category":"Manufacturing",
            "subcategory":"Retail Goods",
            "type":"Manufacturing & Wholesale Goods"
        }
    ],
    "sg:phone":"+1 626 449 5662",
    "sg:postcode":"91107",
    "sg:province":"CA",
    "sg:tags":[
        "assembly",
        "fabricating"
    ],
    "wof:name":"Ability First Work Ctr",
    "wof:placetype":"venue"
},
  "geometry": {"coordinates":[-118.085629,34.142323],"type":"Point"}
}