{
  "type": "Feature",
  "properties": {
    "addr:full":"1608 Snyder Ave Modesto CA 95356",
    "addr:housenumber":"1608",
    "addr:postcode":"ca 95356",
    "addr:street":"Snyder Ave",
    "iso:country":"US",
    "sg:address":"1608 Snyder Ave",
    "sg:city":"Modesto",
    "sg:classifiers":[
        {
            "category":"Building & Trades",
            "subcategory":"Plumbing",
            "type":"Services"
        }
    ],
    "sg:phone":"+1 209 530 9805",
    "sg:postcode":"95356",
    "sg:province":"CA",
    "sg:tags":[
        "contractor"
    ],
    "wof:name":"Temp-Tech Heating and AC",
    "wof:placetype":"venue"
},
  "geometry": {"coordinates":[-121.020841,37.697427],"type":"Point"}
}