{
  "type": "Feature",
  "properties": {
    "iso:country":"US",
    "sg:address":"1825 Douglas Blvd",
    "sg:city":"Roseville",
    "sg:classifiers":[
        {
            "category":"Restaurant",
            "type":"Food & Drink"
        }
    ],
    "sg:phone":"+1 916 782 2745",
    "sg:postcode":"95661",
    "sg:province":"CA",
    "wof:name":"Sweet Basil Thai Cuisine",
    "wof:placetype":"venue"
},
  "geometry": {"coordinates":[-121.257378,38.744298],"type":"Point"}
}