{
  "type": "Feature",
  "properties": {
    "iso:country":"US",
    "sg:address":"4725 Lankershim Blvd",
    "sg:city":"North Hollywood",
    "sg:classifiers":[
        {
            "category":"Health Services",
            "subcategory":"Dentist",
            "type":"Services"
        }
    ],
    "sg:phone":"+1 818 766 3775",
    "sg:postcode":"91602",
    "sg:province":"CA",
    "wof:name":"Chrn Jennifer",
    "wof:placetype":"venue"
},
  "geometry": {"coordinates":[-118.36900300000001,34.1558],"type":"Point"}
}