{
  "type": "Feature",
  "properties": {
    "addr:full":"9304 Bolsa Ave Westminster CA 92683",
    "addr:housenumber":"9304",
    "addr:postcode":"92683",
    "addr:street":"Bolsa Ave",
    "iso:country":"US",
    "sg:address":"9304 Bolsa Ave",
    "sg:city":"Westminster",
    "sg:classifiers":[
        {
            "category":"Shopping",
            "type":"Retail Goods"
        }
    ],
    "sg:phone":"+1 714 901 6922",
    "sg:postcode":"92683",
    "sg:province":"CA",
    "sg:tags":[
        "communication",
        "radiotelephone",
        "merchandise"
    ],
    "wof:name":"Wireless Citi Inc",
    "wof:placetype":"venue"
},
  "geometry": {"coordinates":[-117.966336,33.744715],"type":"Point"}
}