{
  "type": "Feature",
  "properties": {
    "addr:full":"7529 Sunset Ave Suite K & L Fair Oaks CA 95628",
    "addr:housenumber":"7529",
    "addr:postcode":"95628",
    "addr:street":"Sunset Ave Suite K & L Fair",
    "iso:country":"US",
    "sg:address":"7529 Sunset Ave Suite K & L",
    "sg:city":"Fair Oaks",
    "sg:classifiers":[
        {
            "category":"Health Services",
            "subcategory":"Clinic",
            "type":"Services"
        },
        {
            "category":"Personal",
            "subcategory":"Day Spa",
            "type":"Services"
        }
    ],
    "sg:phone":"+1 916 847 0096",
    "sg:postcode":"95628",
    "sg:province":"CA",
    "sg:tags":[
        "counseling",
        "mental"
    ],
    "sg:website":"www.elementalhealings.com",
    "wof:name":"Elemental Holistic Healings Wellness Center & Studio",
    "wof:placetype":"venue"
},
  "geometry": {"coordinates":[-121.28864,38.653187],"type":"Point"}
}