{
  "type": "Feature",
  "properties": {
    "addr:full":"1939 Harrison St Ste 921 Oakland CA 94612",
    "addr:housenumber":"1939",
    "addr:postcode":"94612",
    "addr:street":"Harrison St Ste 921",
    "iso:country":"US",
    "sg:address":"1939 Harrison St Ste 921",
    "sg:city":"Oakland",
    "sg:classifiers":[
        {
            "category":"Health Services",
            "subcategory":"Doctor",
            "type":"Services"
        },
        {
            "category":"Health Services",
            "subcategory":"Clinic",
            "type":"Services"
        }
    ],
    "sg:phone":"+1 510 785 1777",
    "sg:postcode":"94612",
    "sg:province":"CA",
    "sg:tags":[
        "psychological",
        "psychologist"
    ],
    "wof:name":"Bay Area Collaborative Psychology Group Inc",
    "wof:placetype":"venue"
},
  "geometry": {"coordinates":[-122.26503700000001,37.807025],"type":"Point"}
}