{
  "type": "Feature",
  "properties": {
    "addr:full":"573 Dolores St San Francisco CA 94110",
    "addr:housenumber":"573",
    "addr:postcode":"94110",
    "addr:street":"Dolores St",
    "iso:country":"US",
    "sg:address":"573 Dolores St",
    "sg:city":"San Francisco",
    "sg:classifiers":[
        {
            "category":"Organizations",
            "subcategory":"Religious Organization",
            "type":"Services"
        }
    ],
    "sg:phone":"+1 415 861 1372",
    "sg:postcode":"94110",
    "sg:province":"CA",
    "wof:name":"Society Of St Francis",
    "wof:placetype":"venue"
},
  "geometry": {"coordinates":[-122.425853,37.761023],"type":"Point"}
}