{
  "type": "Feature",
  "properties": {
    "iso:country":"US",
    "sg:address":"423 Hindry Ave",
    "sg:city":"Inglewood",
    "sg:classifiers":[
        {
            "category":"Airline",
            "type":"Transportation"
        }
    ],
    "sg:phone":"+1 310 337 1830",
    "sg:postcode":"90301",
    "sg:province":"CA",
    "sg:tags":[
        "courier",
        "air"
    ],
    "wof:name":"Couriers International",
    "wof:placetype":"venue"
},
  "geometry": {"coordinates":[-118.37363,33.956748],"type":"Point"}
}