{
  "type": "Feature",
  "properties": {
    "addr:full":"350 Main St Murphys CA 95247",
    "addr:housenumber":"350",
    "addr:postcode":"95247",
    "addr:street":"Main St",
    "iso:country":"US",
    "sg:address":"350 Main St",
    "sg:city":"Murphys",
    "sg:classifiers":[
        {
            "category":"Shopping",
            "subcategory":"Used Merchandise",
            "type":"Retail Goods"
        }
    ],
    "sg:phone":"+1 209 728 9148",
    "sg:postcode":"95247",
    "sg:province":"CA",
    "sg:tags":[
        "antique"
    ],
    "wof:name":"Sue's Antiques & Gifts",
    "wof:placetype":"venue"
},
  "geometry": {"coordinates":[-120.463348,38.137578],"type":"Point"}
}