{
  "type": "Feature",
  "properties": {
    "addr:full":"520 S El Camino Real Suite 418 San Mateo CA 94402",
    "addr:housenumber":"520",
    "addr:postcode":"94402",
    "addr:street":"S El Camino Real Suite 418",
    "iso:country":"US",
    "sg:address":"520 S El Camino Real Suite 418",
    "sg:city":"San Mateo",
    "sg:classifiers":[
        {
            "category":"Professional",
            "type":"Services"
        },
        {
            "category":"Shopping",
            "subcategory":"Bicycles & Sporting Goods",
            "type":"Retail Goods"
        },
        {
            "category":"Sports & Exercise",
            "subcategory":"Golf",
            "type":"Entertainment"
        }
    ],
    "sg:phone":"+1 877 513 1037",
    "sg:postcode":"94402",
    "sg:province":"CA",
    "sg:tags":[
        "planning",
        "event"
    ],
    "sg:website":"www.golfinaroundevents.com",
    "wof:name":"Golfin' Around",
    "wof:placetype":"venue"
},
  "geometry": {"coordinates":[-122.324153,37.561069],"type":"Point"}
}