{
  "type": "Feature",
  "properties": {
    "addr:full":"41800 Enterprise Cir S Temecula CA 92590",
    "addr:housenumber":"41800",
    "addr:postcode":"92590",
    "addr:street":"Enterprise Cir S",
    "iso:country":"US",
    "sg:address":"41800 Enterprise Cir S",
    "sg:city":"Temecula",
    "sg:classifiers":[
        {
            "category":"Real Estate",
            "subcategory":"Developer",
            "type":"Services"
        }
    ],
    "sg:phone":"+1 951 695 2355",
    "sg:postcode":"92590",
    "sg:province":"CA",
    "wof:name":"Wenland A Calif Gen Partnership",
    "wof:placetype":"venue"
},
  "geometry": {"coordinates":[-117.167793,33.5163],"type":"Point"}
}