{
  "type": "Feature",
  "properties": {
    "iso:country":"US",
    "sg:address":"1105 S Wilson Dr",
    "sg:city":"West Covina",
    "sg:classifiers":[
        {
            "category":"Freight",
            "type":"Transportation"
        }
    ],
    "sg:phone":"+1 626 918 6856",
    "sg:postcode":"91791",
    "sg:province":"CA",
    "wof:name":"Cargo Transport & Service",
    "wof:placetype":"venue"
},
  "geometry": {"coordinates":[-117.915648,34.05396],"type":"Point"}
}