{
  "type": "Feature",
  "properties": {
    "addr:full":"4628 Harmony Ln Santa Maria CA 93455",
    "addr:housenumber":"4628",
    "addr:postcode":"93455",
    "addr:street":"Harmony Ln",
    "iso:country":"US",
    "sg:address":"4628 Harmony Ln",
    "sg:city":"Santa Maria",
    "sg:classifiers":[
        {
            "category":"Recreation",
            "type":"Entertainment"
        }
    ],
    "sg:phone":"+1 805 937 9435",
    "sg:postcode":"93455",
    "sg:province":"CA",
    "sg:tags":[
        "club",
        "membership"
    ],
    "wof:name":"Pacific Bonsai Club",
    "wof:placetype":"venue"
},
  "geometry": {"coordinates":[-120.405838,34.870395],"type":"Point"}
}