{
  "type": "Feature",
  "properties": {
    "addr:full":"1145 Artesia Blvd Manhattan Beach CA 90266",
    "addr:housenumber":"1145",
    "addr:postcode":"90266",
    "addr:street":"Artesia Blvd",
    "iso:country":"US",
    "sg:address":"1145 Artesia Blvd",
    "sg:city":"Manhattan Beach",
    "sg:classifiers":[
        {
            "category":"Restaurant",
            "type":"Food & Drink"
        }
    ],
    "sg:menulink":"http://www.allmenus.com/ca/south-bay-cities/150661-subway/menu/",
    "sg:phone":"+1 310 379 1130",
    "sg:postcode":"90266",
    "sg:province":"CA",
    "sg:tags":[
        "american",
        "sandwich"
    ],
    "wof:name":"Subway",
    "wof:placetype":"venue"
},
  "geometry": {"coordinates":[-118.394217,33.873368],"type":"Point"}
}