{
  "type": "Feature",
  "properties": {
    "iso:country":"US",
    "sg:address":"5935 Kanan Rd",
    "sg:city":"Agoura Hills",
    "sg:classifiers":[
        {
            "category":"Professional",
            "type":"Services"
        }
    ],
    "sg:phone":"+1 818 706 1657",
    "sg:postcode":"91301",
    "sg:province":"CA",
    "sg:tags":[
        "establishment"
    ],
    "wof:name":"Colonial Works",
    "wof:placetype":"venue"
},
  "geometry": {"coordinates":[-118.756403,34.158639],"type":"Point"}
}