{
  "type": "Feature",
  "properties": {
    "iso:country":"US",
    "sg:address":"14006 Riverside Dr",
    "sg:city":"Sherman Oaks",
    "sg:classifiers":[
        {
            "category":"Shopping",
            "type":"Retail Goods"
        }
    ],
    "sg:postcode":"91423",
    "sg:province":"CA",
    "sg:website":"www.shopdivine.com",
    "wof:name":"Divine Boutique",
    "wof:placetype":"venue"
},
  "geometry": {"coordinates":[-118.43220100000001,34.156129],"type":"Point"}
}