{
  "type": "Feature",
  "properties": {
    "addr:full":"13341 Cambridge St Santa Fe Springs CA 90670",
    "addr:housenumber":"13341",
    "addr:postcode":"90670",
    "addr:street":"Cambridge St",
    "iso:country":"US",
    "sg:address":"13341 Cambridge St",
    "sg:city":"Santa Fe Springs",
    "sg:classifiers":[
        {
            "category":"Manufacturing",
            "subcategory":"Paper Products",
            "type":"Manufacturing & Wholesale Goods"
        }
    ],
    "sg:phone":"+1 562 802 1305",
    "sg:postcode":"90670",
    "sg:province":"CA",
    "sg:tags":[
        "mfg",
        "envelope",
        "supply"
    ],
    "wof:name":"Cenveo Corporation",
    "wof:placetype":"venue"
},
  "geometry": {"coordinates":[-118.04711,33.906816],"type":"Point"}
}