{
  "type": "Feature",
  "properties": {
    "iso:country":"US",
    "sg:address":"311 California St",
    "sg:city":"San Francisco",
    "sg:classifiers":[
        {
            "category":"Organizations",
            "subcategory":"Community Association",
            "type":"Services"
        }
    ],
    "sg:phone":"+1 415 544 0790",
    "sg:postcode":"94104",
    "sg:province":"CA",
    "sg:tags":[
        "environmental",
        "org"
    ],
    "wof:name":"Bluewater Network",
    "wof:placetype":"venue"
},
  "geometry": {"coordinates":[-122.40102,37.793001],"type":"Point"}
}