{
  "type": "Feature",
  "properties": {
    "iso:country":"US",
    "sg:address":"961 S Bascom Ave",
    "sg:city":"San Jose",
    "sg:classifiers":[
        {
            "category":"Banks & Credit Unions",
            "subcategory":"Bank",
            "type":"Services"
        }
    ],
    "sg:phone":"+1 408 294 7762",
    "sg:postcode":"95128",
    "sg:province":"CA",
    "sg:tags":[
        "cashing",
        "check"
    ],
    "wof:name":"A & D Money Market",
    "wof:placetype":"venue"
},
  "geometry": {"coordinates":[-121.931849,37.30841],"type":"Point"}
}