{
  "type": "Feature",
  "properties": {
    "iso:country":"US",
    "sg:address":"993 N Broadway",
    "sg:city":"Los Angeles",
    "sg:classifiers":[
        {
            "category":"Organizations",
            "subcategory":"Professional Association",
            "type":"Services"
        }
    ],
    "sg:phone":"+1 213 624 5712",
    "sg:postcode":"90012",
    "sg:province":"CA",
    "wof:name":"Soo Yuen Fraternal Assn Inc",
    "wof:placetype":"venue"
},
  "geometry": {"coordinates":[-118.236098,34.066479],"type":"Point"}
}