{
  "type": "Feature",
  "properties": {
    "addr:full":"5805 Cahalan Ave San Jose CA 95123",
    "addr:housenumber":"5805",
    "addr:postcode":"95123",
    "addr:street":"Cahalan Ave",
    "iso:country":"US",
    "sg:address":"5805 Cahalan Ave",
    "sg:city":"San Jose",
    "sg:classifiers":[
        {
            "category":"Education",
            "subcategory":"Preschool",
            "type":"Public Place"
        },
        {
            "category":"Education",
            "subcategory":"School",
            "type":"Public Place"
        }
    ],
    "sg:phone":"+1 408 225 7211",
    "sg:postcode":"95123",
    "sg:province":"CA",
    "sg:tags":[
        "elementary"
    ],
    "sg:website":"www.appsonline.org",
    "wof:name":"Almaden Parents Preschool",
    "wof:placetype":"venue"
},
  "geometry": {"coordinates":[-121.847756,37.247201],"type":"Point"}
}