{
  "type": "Feature",
  "properties": {
    "addr:full":"303 N Orange Ave Fallbrook CA 92028",
    "addr:housenumber":"303",
    "addr:postcode":"92028",
    "addr:street":"N Orange Ave",
    "iso:country":"US",
    "sg:address":"303 N Orange Ave",
    "sg:city":"Fallbrook",
    "sg:classifiers":[
        {
            "category":"Social Services",
            "type":"Services"
        }
    ],
    "sg:phone":"+1 760 728 5550",
    "sg:postcode":"92028",
    "sg:province":"CA",
    "sg:tags":[
        "youth",
        "organization",
        "center"
    ],
    "wof:name":"Felipe Jimenez Immigration",
    "wof:placetype":"venue"
},
  "geometry": {"coordinates":[-117.24924,33.384596],"type":"Point"}
}