{
  "type": "Feature",
  "properties": {
    "iso:country":"US",
    "sg:address":"888 Brannan St",
    "sg:city":"San Francisco",
    "sg:classifiers":[
        {
            "category":"Wholesale",
            "subcategory":"Non-durable Goods",
            "type":"Manufacturing & Wholesale Goods"
        }
    ],
    "sg:phone":"+1 415 861 8502",
    "sg:postcode":"94103",
    "sg:province":"CA",
    "wof:name":"David Y Lei",
    "wof:placetype":"venue"
},
  "geometry": {"coordinates":[-122.40449,37.772337],"type":"Point"}
}