{
  "type": "Feature",
  "properties": {
    "addr:full":"42767 Rd 80 Dinuba CA 93618",
    "addr:postcode":"42767;93618",
    "addr:street":"Rd 80",
    "iso:country":"US",
    "sg:address":"42767 Rd 80",
    "sg:city":"Dinuba",
    "sg:classifiers":[
        {
            "category":"Retail",
            "subcategory":"Auto Repair",
            "type":"Services"
        }
    ],
    "sg:phone":"+1 559 591 1535",
    "sg:postcode":"93618",
    "sg:province":"CA",
    "sg:tags":[
        "body",
        "automobile",
        "painting"
    ],
    "wof:name":"Backyard Customs",
    "wof:placetype":"venue"
},
  "geometry": {"coordinates":[-119.39518700000001,36.566417],"type":"Point"}
}