{
  "type": "Feature",
  "properties": {
    "addr:full":"165 N Redwood Dr San Rafael CA 94903",
    "addr:housenumber":"165",
    "addr:postcode":"94903",
    "addr:street":"N Redwood Dr",
    "iso:country":"US",
    "sg:address":"165 N Redwood Dr",
    "sg:city":"San Rafael",
    "sg:classifiers":[
        {
            "category":"Government",
            "subcategory":"Office",
            "type":"Public Place"
        }
    ],
    "sg:phone":"+1 415 446 4409",
    "sg:postcode":"94903",
    "sg:province":"CA",
    "wof:name":"Marin LAFCO",
    "wof:placetype":"venue"
},
  "geometry": {"coordinates":[-122.535839,38.024205],"type":"Point"}
}