{
  "type": "Feature",
  "properties": {
    "addr:full":"373 Bear Mountain Blvd Arvin CA 93203",
    "addr:housenumber":"373",
    "addr:postcode":"93203",
    "addr:street":"Bear Mountain Blvd",
    "iso:country":"US",
    "sg:address":"373 Bear Mountain Blvd",
    "sg:city":"Arvin",
    "sg:classifiers":[
        {
            "category":"Restaurant",
            "type":"Food & Drink"
        }
    ],
    "sg:phone":"+1 661 854 4375",
    "sg:postcode":"93203",
    "sg:province":"CA",
    "wof:name":"Los Jarritos",
    "wof:placetype":"venue"
},
  "geometry": {"coordinates":[-118.828034,35.209022],"type":"Point"}
}