{
  "type": "Feature",
  "properties": {
    "addr:full":"9150 Lariat Ct Fair Oaks CA 95628",
    "addr:housenumber":"9150",
    "addr:postcode":"95628",
    "addr:street":"Lariat Ct",
    "iso:country":"US",
    "sg:address":"9150 Lariat Ct",
    "sg:city":"Fair Oaks",
    "sg:classifiers":[
        {
            "category":"Manufacturing",
            "subcategory":"Glass & Minerals",
            "type":"Manufacturing & Wholesale Goods"
        }
    ],
    "sg:phone":"+1 916 987 0937",
    "sg:postcode":"95628",
    "sg:province":"CA",
    "sg:tags":[
        "mfg"
    ],
    "wof:name":"Bohemia House Imports",
    "wof:placetype":"venue"
},
  "geometry": {"coordinates":[-121.21370400000001,38.662286],"type":"Point"}
}