{
  "type": "Feature",
  "properties": {
    "addr:full":"3277 Sacramento St San Francisco CA 94115",
    "addr:housenumber":"3277",
    "addr:postcode":"94115",
    "addr:street":"Sacramento St",
    "iso:country":"US",
    "sg:address":"3277 Sacramento St",
    "sg:city":"San Francisco",
    "sg:classifiers":[
        {
            "category":"Professional",
            "type":"Services"
        }
    ],
    "sg:phone":"+1 415 771 5030",
    "sg:postcode":"94115",
    "sg:province":"CA",
    "wof:name":"Forza Diluna Inc",
    "wof:placetype":"venue"
},
  "geometry": {"coordinates":[-122.446113,37.78825],"type":"Point"}
}