{
  "type": "Feature",
  "properties": {
    "addr:full":"16377 Lakeshore Dr Lake Elsinore CA 92530",
    "addr:housenumber":"16377",
    "addr:postcode":"92530",
    "addr:street":"Lakeshore Dr",
    "iso:country":"US",
    "sg:address":"16377 Lakeshore Dr",
    "sg:city":"Lake Elsinore",
    "sg:classifiers":[
        {
            "category":"Real Estate",
            "subcategory":"Real Estate Operator",
            "type":"Services"
        }
    ],
    "sg:phone":"+1 951 245 2915",
    "sg:postcode":"92530",
    "sg:province":"CA",
    "sg:tags":[
        "apartment"
    ],
    "wof:name":"Michka",
    "wof:placetype":"venue"
},
  "geometry": {"coordinates":[-117.375,33.6898],"type":"Point"}
}