{
  "type": "Feature",
  "properties": {
    "addr:full":"1200 E Colorado Blvd Pasadena CA 91106",
    "addr:housenumber":"1200",
    "addr:postcode":"91106",
    "addr:street":"E Colorado Blvd",
    "iso:country":"US",
    "sg:address":"1200 E Colorado Blvd",
    "sg:city":"Pasadena",
    "sg:classifiers":[
        {
            "category":"Home & Garden",
            "subcategory":"Building Materials",
            "type":"Retail Goods"
        }
    ],
    "sg:phone":"+1 626 685 9690",
    "sg:postcode":"91106",
    "sg:province":"CA",
    "sg:tags":[
        "plate",
        "window",
        "auto",
        "glass"
    ],
    "wof:name":"Tv Auto Glass & Tire",
    "wof:placetype":"venue"
},
  "geometry": {"coordinates":[-118.12599899999999,34.145802],"type":"Point"}
}