{
  "type": "Feature",
  "properties": {
    "iso:country":"US",
    "sg:address":"2592 Mercantile Way Ste B",
    "sg:city":"Barstow",
    "sg:classifiers":[
        {
            "category":"Manufacturing",
            "subcategory":"Leather Goods",
            "type":"Manufacturing & Wholesale Goods"
        },
        {
            "category":"Shopping",
            "subcategory":"Luggage & Leather Goods",
            "type":"Retail Goods"
        }
    ],
    "sg:phone":"+1 760 253 5424",
    "sg:postcode":"92311",
    "sg:province":"CA",
    "wof:name":"Celini Leather And Luggage",
    "wof:placetype":"venue"
},
  "geometry": {"coordinates":[-117.081492,34.848639],"type":"Point"}
}