{
  "type": "Feature",
  "properties": {
    "addr:full":"3220 W Shaw Ave Fresno CA 93711",
    "addr:housenumber":"3220",
    "addr:postcode":"93711",
    "addr:street":"W Shaw Ave",
    "iso:country":"US",
    "sg:address":"3220 W Shaw Ave",
    "sg:city":"Fresno",
    "sg:classifiers":[
        {
            "category":"Retail",
            "subcategory":"Veterinary Services",
            "type":"Services"
        }
    ],
    "sg:phone":"+1 559 271 0437",
    "sg:postcode":"93711",
    "sg:province":"CA",
    "wof:name":"Banfield The Pet Hospital",
    "wof:placetype":"venue"
},
  "geometry": {"coordinates":[-119.849563,36.808354],"type":"Point"}
}