{
  "type": "Feature",
  "properties": {
    "iso:country":"US",
    "sg:address":"3220 W Shaw Ave",
    "sg:city":"Fresno",
    "sg:classifiers":[
        {
            "category":"Retail",
            "subcategory":"Veterinary Services",
            "type":"Services"
        }
    ],
    "sg:phone":"+1 559 271 0437",
    "sg:postcode":"93711",
    "sg:province":"CA",
    "wof:name":"Banfield The Pet Hospital",
    "wof:placetype":"venue"
},
  "geometry": {"coordinates":[-119.849563,36.808354],"type":"Point"}
}