{
  "type": "Feature",
  "properties": {
    "addr:full":"49295 Ave Fernando La Quinta CA 92253",
    "addr:housenumber":"49295",
    "addr:postcode":"92253",
    "addr:street":"Ave Fernando;Quinta",
    "iso:country":"US",
    "sg:address":"49295 Ave Fernando",
    "sg:city":"La Quinta",
    "sg:classifiers":[
        {
            "category":"Farming",
            "subcategory":"Farm",
            "type":"Manufacturing & Wholesale Goods"
        }
    ],
    "sg:phone":"+1 760 564 1540",
    "sg:postcode":"92253",
    "sg:province":"CA",
    "wof:name":"Fausel Farms",
    "wof:placetype":"venue"
},
  "geometry": {"coordinates":[-116.30629399999999,33.68994],"type":"Point"}
}