{
  "type": "Feature",
  "properties": {
    "iso:country":"US",
    "sg:address":"49295 Ave Fernando",
    "sg:city":"La Quinta",
    "sg:classifiers":[
        {
            "category":"Farming",
            "subcategory":"Farm",
            "type":"Manufacturing & Wholesale Goods"
        }
    ],
    "sg:phone":"+1 760 564 1540",
    "sg:postcode":"92253",
    "sg:province":"CA",
    "wof:name":"Fausel Farms",
    "wof:placetype":"venue"
},
  "geometry": {"coordinates":[-116.306294,33.68994],"type":"Point"}
}