{
  "type": "Feature",
  "properties": {
    "addr:full":"620 E Washington St Petaluma CA 94952",
    "addr:housenumber":"620",
    "addr:postcode":"94952",
    "addr:street":"E Washington St",
    "iso:country":"US",
    "sg:address":"620 E Washington St",
    "sg:city":"Petaluma",
    "sg:classifiers":[
        {
            "category":"Travel",
            "subcategory":"Travel Agent",
            "type":"Entertainment"
        }
    ],
    "sg:phone":"+1 707 778 0877",
    "sg:postcode":"94952",
    "sg:province":"CA",
    "sg:tags":[
        "tours",
        "promoter"
    ],
    "wof:name":"San Miguel Travel",
    "wof:placetype":"venue"
},
  "geometry": {"coordinates":[-122.634045,38.240195],"type":"Point"}
}