{
  "type": "Feature",
  "properties": {
    "iso:country":"US",
    "sg:address":"338 N Canal St",
    "sg:city":"S San Francisco",
    "sg:classifiers":[
        {
            "category":"Airline",
            "type":"Transportation"
        }
    ],
    "sg:phone":"+1 650 837 9900",
    "sg:postcode":"94080",
    "sg:province":"CA",
    "sg:tags":[
        "cargo",
        "air"
    ],
    "wof:name":"Bellair Expediting",
    "wof:placetype":"venue"
},
  "geometry": {"coordinates":[-122.415651,37.651152],"type":"Point"}
}