{
  "type": "Feature",
  "properties": {
    "iso:country":"US",
    "sg:address":"1880 Humboldt Rd",
    "sg:city":"Chico",
    "sg:classifiers":[
        {
            "category":"Professional",
            "subcategory":"Accounting & Tax Preparation",
            "type":"Services"
        }
    ],
    "sg:phone":"+1 530 893 9569",
    "sg:postcode":"95928",
    "sg:province":"CA",
    "sg:tags":[
        "bookkeeping",
        "general"
    ],
    "wof:name":"C P Bookkeeping Svc",
    "wof:placetype":"venue"
},
  "geometry": {"coordinates":[-121.81582,39.735175],"type":"Point"}
}