{
  "type": "Feature",
  "properties": {
    "addr:full":"5531 Meadow Ln Mariposa CA 95338",
    "addr:housenumber":"5531",
    "addr:postcode":"95338",
    "addr:street":"Meadow Ln",
    "iso:country":"US",
    "sg:address":"5531 Meadow Ln",
    "sg:city":"Mariposa",
    "sg:classifiers":[
        {
            "category":"Building & Trades",
            "subcategory":"Electrical",
            "type":"Services"
        }
    ],
    "sg:phone":"+1 209 742 2164",
    "sg:postcode":"95338",
    "sg:province":"CA",
    "sg:tags":[
        "electrical",
        "contractor"
    ],
    "wof:name":"Hager Electric",
    "wof:placetype":"venue"
},
  "geometry": {"coordinates":[-119.83247,37.500358],"type":"Point"}
}