{
  "type": "Feature",
  "properties": {
    "addr:full":"3238 Sullivan Ave Rosemead CA 91770",
    "addr:housenumber":"3238",
    "addr:postcode":"91770",
    "addr:street":"Sullivan Ave",
    "iso:country":"US",
    "sg:address":"3238 Sullivan Ave",
    "sg:city":"Rosemead",
    "sg:classifiers":[
        {
            "category":"Freight",
            "type":"Transportation"
        }
    ],
    "sg:phone":"+1 626 340 4072",
    "sg:postcode":"91770",
    "sg:province":"CA",
    "sg:tags":[
        "trucking"
    ],
    "wof:name":"Giant Tigers Transport Co",
    "wof:placetype":"venue"
},
  "geometry": {"coordinates":[-118.07171200000001,34.067141],"type":"Point"}
}