{
  "type": "Feature",
  "properties": {
    "iso:country":"US",
    "sg:address":"1952 W Don Pedro Rd",
    "sg:city":"Modesto",
    "sg:classifiers":[
        {
            "category":"Professional",
            "type":"Services"
        }
    ],
    "sg:phone":"+1 209 581 9707",
    "sg:postcode":"95358",
    "sg:province":"CA",
    "wof:name":"DV Silveira/Son",
    "wof:placetype":"venue"
},
  "geometry": {"coordinates":[-121.021992,37.584056],"type":"Point"}
}