{
  "type": "Feature",
  "properties": {
    "addr:full":"2390 Pine St Napa CA 94559",
    "addr:housenumber":"2390",
    "addr:postcode":"94559",
    "addr:street":"Pine St",
    "iso:country":"US",
    "sg:address":"2390 Pine St",
    "sg:city":"Napa",
    "sg:classifiers":[
        {
            "category":"Building & Trades",
            "subcategory":"Construction",
            "type":"Services"
        }
    ],
    "sg:phone":"+1 707 226 5044",
    "sg:postcode":"94559",
    "sg:province":"CA",
    "sg:tags":[
        "designer",
        "dealer",
        "pool",
        "swimming"
    ],
    "wof:name":"Aztech Pool Plastering",
    "wof:placetype":"venue"
},
  "geometry": {"coordinates":[-122.301157,38.291271],"type":"Point"}
}