{
  "type": "Feature",
  "properties": {
    "addr:full":"3325 Division St Los Angeles CA 90065",
    "addr:housenumber":"3325",
    "addr:postcode":"90065",
    "addr:street":"Division St",
    "iso:country":"US",
    "sg:address":"3325 Division St",
    "sg:city":"Los Angeles",
    "sg:classifiers":[
        {
            "category":"Health Services",
            "subcategory":"Doctor",
            "type":"Services"
        }
    ],
    "sg:phone":"+1 323 224 0408",
    "sg:postcode":"90065",
    "sg:province":"CA",
    "sg:tags":[
        "clinic"
    ],
    "wof:name":"Glass America",
    "wof:placetype":"venue"
},
  "geometry": {"coordinates":[-118.22969399999999,34.104939],"type":"Point"}
}