{
  "type": "Feature",
  "properties": {
    "addr:full":"1320 W Base Line Rd Rialto CA 92376",
    "addr:housenumber":"1320",
    "addr:postcode":"92376",
    "addr:street":"W Base Line Rd",
    "iso:country":"US",
    "sg:address":"1320 W Base Line Rd",
    "sg:city":"Rialto",
    "sg:classifiers":[
        {
            "category":"Restaurant",
            "type":"Food & Drink"
        }
    ],
    "sg:menulink":"http://www.allmenus.com/ca/san-bernardino/175087-popeyes-chicken--biscuits/menu/",
    "sg:phone":"+1 909 421 1234",
    "sg:postcode":"92376",
    "sg:province":"CA",
    "sg:tags":[
        "american",
        "wing"
    ],
    "wof:name":"Popeyes Chicken & Biscuits",
    "wof:placetype":"venue"
},
  "geometry": {"coordinates":[-117.397525,34.121842],"type":"Point"}
}