{
  "type": "Feature",
  "properties": {
    "iso:country":"US",
    "sg:address":"6005 Seashore Dr",
    "sg:city":"Newport Beach",
    "sg:classifiers":[
        {
            "category":"Local Transit",
            "type":"Transportation"
        }
    ],
    "sg:phone":"+1 714 556 9999",
    "sg:postcode":"92663",
    "sg:province":"CA",
    "sg:tags":[
        "passenger"
    ],
    "wof:name":"Gold Key Limosine",
    "wof:placetype":"venue"
},
  "geometry": {"coordinates":[-117.948717,33.625557],"type":"Point"}
}