{
  "type": "Feature",
  "properties": {
    "addr:full":"4416 Coliseum Way Oakland CA 94601",
    "addr:housenumber":"4416",
    "addr:postcode":"94601",
    "addr:street":"Coliseum Way",
    "iso:country":"US",
    "sg:address":"4416 Coliseum Way",
    "sg:city":"Oakland",
    "sg:classifiers":[
        {
            "category":"Manufacturing",
            "subcategory":"Metals",
            "type":"Manufacturing & Wholesale Goods"
        }
    ],
    "sg:phone":"+1 510 261 8126",
    "sg:postcode":"94601",
    "sg:province":"CA",
    "sg:tags":[
        "work",
        "iron"
    ],
    "wof:name":"Ornamental Iron Work",
    "wof:placetype":"venue"
},
  "geometry": {"coordinates":[-122.219216,37.76733],"type":"Point"}
}