{
  "type": "Feature",
  "properties": {
    "addr:full":"1430 Buena Vista Dr Vista CA 92081",
    "addr:housenumber":"1430",
    "addr:postcode":"92081",
    "addr:street":"Buena Vista Dr",
    "iso:country":"US",
    "sg:address":"1430 Buena Vista Dr",
    "sg:city":"Vista",
    "sg:classifiers":[
        {
            "category":"Wholesale",
            "subcategory":"Plants",
            "type":"Manufacturing & Wholesale Goods"
        }
    ],
    "sg:phone":"+1 760 726 7786",
    "sg:postcode":"92081",
    "sg:province":"CA",
    "sg:tags":[
        "nursery",
        "tree"
    ],
    "wof:name":"Rancho Vista Cacti & Succulent",
    "wof:placetype":"venue"
},
  "geometry": {"coordinates":[-117.245586,33.171431],"type":"Point"}
}