{
  "type": "Feature",
  "properties": {
    "addr:full":"2667 Tapo St Simi Valley CA 93063",
    "addr:housenumber":"2667",
    "addr:postcode":"93063",
    "addr:street":"Tapo St",
    "iso:country":"US",
    "sg:address":"2667 Tapo St",
    "sg:city":"Simi Valley",
    "sg:classifiers":[
        {
            "category":"Building & Trades",
            "subcategory":"Landscaping Services",
            "type":"Services"
        }
    ],
    "sg:phone":"+1 805 522 1584",
    "sg:postcode":"93063",
    "sg:province":"CA",
    "sg:tags":[
        "landscape",
        "contractor"
    ],
    "sg:website":"www.dreamscapepools.com",
    "wof:name":"Dreamscape Landscape Constr",
    "wof:placetype":"venue"
},
  "geometry": {"coordinates":[-118.709011,34.282009],"type":"Point"}
}