{
  "type": "Feature",
  "properties": {
    "iso:country":"US",
    "sg:address":"3225 Oro Dam Blvd E",
    "sg:city":"Oroville",
    "sg:classifiers":[
        {
            "category":"Health Services",
            "subcategory":"Doctor",
            "type":"Services"
        }
    ],
    "sg:phone":"+1 530 533 7400",
    "sg:postcode":"95966",
    "sg:province":"CA",
    "sg:tags":[
        "dentist"
    ],
    "wof:name":"Tyler Faulkner Inc",
    "wof:placetype":"venue"
},
  "geometry": {"coordinates":[-121.538168,39.514587],"type":"Point"}
}