{
  "type": "Feature",
  "properties": {
    "addr:full":"6605 Llano Rd Atascadero CA 93422",
    "addr:housenumber":"6605",
    "addr:postcode":"93422",
    "addr:street":"Llano Rd",
    "iso:country":"US",
    "sg:address":"6605 Llano Rd",
    "sg:city":"Atascadero",
    "sg:classifiers":[
        {
            "category":"Building & Trades",
            "subcategory":"Construction",
            "type":"Services"
        }
    ],
    "sg:phone":"+1 805 466 2883",
    "sg:postcode":"93422",
    "sg:province":"CA",
    "sg:tags":[
        "contractor"
    ],
    "wof:name":"D J & Son Construction Co",
    "wof:placetype":"venue"
},
  "geometry": {"coordinates":[-120.713318,35.482574],"type":"Point"}
}