{
  "type": "Feature",
  "properties": {
    "addr:full":"23 Odom Ct Sacramento CA 95823",
    "addr:housenumber":"23",
    "addr:postcode":"95823",
    "addr:street":"Odom Ct",
    "iso:country":"US",
    "sg:address":"23 Odom Ct",
    "sg:city":"Sacramento",
    "sg:classifiers":[
        {
            "category":"Social Services",
            "subcategory":"Child Care",
            "type":"Services"
        }
    ],
    "sg:phone":"+1 916 395 8745",
    "sg:postcode":"95823",
    "sg:province":"CA",
    "sg:tags":[
        "sitting"
    ],
    "wof:name":"Cozy Court Home Day Care",
    "wof:placetype":"venue"
},
  "geometry": {"coordinates":[-121.44528699999999,38.469285],"type":"Point"}
}