{
  "type": "Feature",
  "properties": {
    "iso:country":"US",
    "sg:address":"1814 Commercenter Ct",
    "sg:city":"San Bernardino",
    "sg:classifiers":[
        {
            "category":"Professional",
            "type":"Services"
        }
    ],
    "sg:phone":"+1 909 884 2510",
    "sg:postcode":"92408",
    "sg:province":"CA",
    "sg:tags":[
        "establishment"
    ],
    "wof:name":"Rockcreek Inc",
    "wof:placetype":"venue"
},
  "geometry": {"coordinates":[-117.28234,34.068464],"type":"Point"}
}