{
  "type": "Feature",
  "properties": {
    "iso:country":"US",
    "sg:address":"7330 Lincoln Way",
    "sg:city":"Garden Grove",
    "sg:classifiers":[
        {
            "category":"Building & Trades",
            "subcategory":"Construction",
            "type":"Services"
        }
    ],
    "sg:phone":"+1 714 891 1906",
    "sg:postcode":"92841",
    "sg:province":"CA",
    "sg:tags":[
        "equipment",
        "aircraft",
        "parts",
        "mfg"
    ],
    "wof:name":"C & D Aerospace Inc",
    "wof:placetype":"venue"
},
  "geometry": {"coordinates":[-118.00388599999999,33.798208],"type":"Point"}
}