{
  "type": "Feature",
  "properties": {
    "addr:full":"51701 US Hwy 111 Coachella CA 92236",
    "addr:postcode":"51701;92236",
    "addr:street":"Us Hwy 111",
    "iso:country":"US",
    "sg:address":"51701 US Hwy 111",
    "sg:city":"Coachella",
    "sg:classifiers":[
        {
            "category":"Wholesale",
            "subcategory":"Machinery & Supplies",
            "type":"Manufacturing & Wholesale Goods"
        }
    ],
    "sg:phone":"+1 760 391 9456",
    "sg:postcode":"92236",
    "sg:province":"CA",
    "sg:tags":[
        "agricultural",
        "industrial"
    ],
    "wof:name":"C V Industrial & AG Supply",
    "wof:placetype":"venue"
},
  "geometry": {"coordinates":[-116.167007,33.671887],"type":"Point"}
}