{
  "type": "Feature",
  "properties": {
    "addr:full":"5521 Alleghany St San Diego CA 92139",
    "addr:housenumber":"5521",
    "addr:postcode":"92139",
    "addr:street":"Alleghany St",
    "iso:country":"US",
    "sg:address":"5521 Alleghany St",
    "sg:city":"San Diego",
    "sg:classifiers":[
        {
            "category":"Utilities",
            "subcategory":"Telephone",
            "type":"Services"
        }
    ],
    "sg:phone":"+1 619 472 1024",
    "sg:postcode":"92139",
    "sg:province":"CA",
    "sg:tags":[
        "communications"
    ],
    "wof:name":"Make Your Life Vivid",
    "wof:placetype":"venue"
},
  "geometry": {"coordinates":[-117.06961800000001,32.678553],"type":"Point"}
}