{
  "type": "Feature",
  "properties": {
    "iso:country":"US",
    "sg:address":"2702 Maher Ave",
    "sg:city":"Crescent City",
    "sg:classifiers":[
        {
            "category":"Organizations",
            "subcategory":"Religious Organization",
            "type":"Services"
        }
    ],
    "sg:phone":"+1 707 465 3622",
    "sg:postcode":"95531",
    "sg:province":"CA",
    "sg:tags":[
        "clergy"
    ],
    "wof:name":"David Kaupang",
    "wof:placetype":"venue"
},
  "geometry": {"coordinates":[-124.150647,41.748592],"type":"Point"}
}