{
  "type": "Feature",
  "properties": {
    "iso:country":"US",
    "sg:address":"165 Little Corral Way",
    "sg:city":"Watsonville",
    "sg:classifiers":[
        {
            "category":"Exhibition Hall",
            "type":"Public Place"
        }
    ],
    "sg:phone":"+1 831 761 5839",
    "sg:postcode":"95076",
    "sg:province":"CA",
    "sg:tags":[
        "halls",
        "ballroom",
        "auditorium"
    ],
    "wof:name":"Corralitos Grange Hall",
    "wof:placetype":"venue"
},
  "geometry": {"coordinates":[-121.80901299999999,36.987696],"type":"Point"}
}