{
  "type": "Feature",
  "properties": {
    "iso:country":"US",
    "sg:address":"13561 Desmond St",
    "sg:city":"Pacoima",
    "sg:classifiers":[
        {
            "category":"Real Estate",
            "subcategory":"Real Estate Agent",
            "type":"Services"
        }
    ],
    "sg:phone":"+1 818 897 6377",
    "sg:postcode":"91331",
    "sg:province":"CA",
    "sg:tags":[
        "management"
    ],
    "wof:name":"Golden View Properties",
    "wof:placetype":"venue"
},
  "geometry": {"coordinates":[-118.428101,34.2752],"type":"Point"}
}