{
  "type": "Feature",
  "properties": {
    "addr:full":"2491 Bull Canyon Rd Santa Maria CA 93454",
    "addr:housenumber":"2491",
    "addr:postcode":"93454",
    "addr:street":"Bull Canyon Rd",
    "iso:country":"US",
    "sg:address":"2491 Bull Canyon Rd",
    "sg:city":"Santa Maria",
    "sg:classifiers":[
        {
            "category":"Farming",
            "subcategory":"Farm",
            "type":"Manufacturing & Wholesale Goods"
        }
    ],
    "sg:phone":"+1 805 925 6650",
    "sg:postcode":"93454",
    "sg:province":"CA",
    "sg:tags":[
        "agricultural"
    ],
    "wof:name":"Newhall Land and Farming Co",
    "wof:placetype":"venue"
},
  "geometry": {"coordinates":[-120.387806,34.987543],"type":"Point"}
}