{
  "type": "Feature",
  "properties": {
    "addr:full":"4644 W Jennifer Ave Fresno CA 93722",
    "addr:housenumber":"4644",
    "addr:postcode":"93722",
    "addr:street":"W Jennifer Ave",
    "iso:country":"US",
    "sg:address":"4644 W Jennifer Ave",
    "sg:city":"Fresno",
    "sg:classifiers":[
        {
            "category":"Shopping",
            "subcategory":"Jewelry",
            "type":"Retail Goods"
        }
    ],
    "sg:phone":"+1 559 275 2800",
    "sg:postcode":"93722",
    "sg:province":"CA",
    "sg:tags":[
        "jeweler"
    ],
    "wof:name":"Josten's",
    "wof:placetype":"venue"
},
  "geometry": {"coordinates":[-119.87930799999999,36.812134],"type":"Point"}
}