{
  "type": "Feature",
  "properties": {
    "addr:full":"142 N La Brea Ave Los Angeles CA 90036",
    "addr:housenumber":"142",
    "addr:postcode":"90036",
    "addr:street":"N La Brea Ave",
    "iso:country":"US",
    "sg:address":"142 N La Brea Ave",
    "sg:city":"Los Angeles",
    "sg:classifiers":[
        {
            "category":"Home & Garden",
            "subcategory":"Furniture",
            "type":"Retail Goods"
        }
    ],
    "sg:phone":"+1 323 935 9955",
    "sg:postcode":"90036",
    "sg:province":"CA",
    "sg:tags":[
        "store"
    ],
    "sg:website":"www.silhofurniture.com",
    "wof:name":"Silho Furniture",
    "wof:placetype":"venue"
},
  "geometry": {"coordinates":[-118.344002,34.074902],"type":"Point"}
}