{
  "type": "Feature",
  "properties": {
    "iso:country":"US",
    "sg:address":"111 Heatherwood Ct",
    "sg:city":"Porterville",
    "sg:classifiers":[
        {
            "category":"Personal",
            "subcategory":"Beauty Salon",
            "type":"Services"
        }
    ],
    "sg:phone":"+1 559 784 5891",
    "sg:postcode":"93257",
    "sg:province":"CA",
    "wof:name":"Loretta's Beauty Shop",
    "wof:placetype":"venue"
},
  "geometry": {"coordinates":[-119.01832,36.082945],"type":"Point"}
}