{
  "type": "Feature",
  "properties": {
    "addr:full":"131 N Vine St Fallbrook CA 92028",
    "addr:housenumber":"131",
    "addr:postcode":"92028",
    "addr:street":"N Vine St",
    "iso:country":"US",
    "sg:address":"131 N Vine St",
    "sg:city":"Fallbrook",
    "sg:classifiers":[
        {
            "category":"Health Services",
            "subcategory":"Optometrist",
            "type":"Services"
        }
    ],
    "sg:phone":"+1 760 723 8417",
    "sg:postcode":"92028",
    "sg:province":"CA",
    "wof:name":"George Bruce D OD",
    "wof:placetype":"venue"
},
  "geometry": {"coordinates":[-117.25,33.382301],"type":"Point"}
}