{
  "type": "Feature",
  "properties": {
    "addr:full":"20061 Old Santa Cruz Hwy Los Gatos CA 95033",
    "addr:housenumber":"20061",
    "addr:postcode":"95033",
    "addr:street":"Old Santa Cruz Hwy",
    "iso:country":"US",
    "sg:address":"20061 Old Santa Cruz Hwy",
    "sg:city":"Los Gatos",
    "sg:classifiers":[
        {
            "category":"Building & Trades",
            "subcategory":"Construction",
            "type":"Services"
        }
    ],
    "sg:phone":"+1 408 353 4285",
    "sg:postcode":"95033",
    "sg:province":"CA",
    "sg:tags":[
        "contractor"
    ],
    "wof:name":"Fairburn Industries",
    "wof:placetype":"venue"
},
  "geometry": {"coordinates":[-121.988013,37.171698],"type":"Point"}
}