{
  "type": "Feature",
  "properties": {
    "iso:country":"US",
    "sg:address":"645 Brookside Ave",
    "sg:city":"Redlands",
    "sg:classifiers":[
        {
            "category":"Social Services",
            "type":"Services"
        }
    ],
    "sg:phone":"+1 909 793 3031",
    "sg:postcode":"92373",
    "sg:province":"CA",
    "sg:tags":[
        "counselor",
        "marriage",
        "family"
    ],
    "wof:name":"Siddons Norris & Assoc",
    "wof:placetype":"venue"
},
  "geometry": {"coordinates":[-117.1901,34.052886],"type":"Point"}
}