{
  "type": "Feature",
  "properties": {
    "iso:country":"US",
    "sg:address":"2366 N Glassell St",
    "sg:city":"Orange",
    "sg:classifiers":[
        {
            "category":"Arts & Performance",
            "subcategory":"Music",
            "type":"Entertainment"
        }
    ],
    "sg:phone":"+1 714 282 1687",
    "sg:postcode":"92865",
    "sg:province":"CA",
    "sg:tags":[
        "sheet"
    ],
    "wof:name":"Oc Music Supply",
    "wof:placetype":"venue"
},
  "geometry": {"coordinates":[-117.852913,33.826759],"type":"Point"}
}