{
  "type": "Feature",
  "properties": {
    "iso:country":"US",
    "sg:address":"725 White Oak Dr",
    "sg:city":"Santa Rosa",
    "sg:classifiers":[
        {
            "category":"Organizations",
            "subcategory":"Community Association",
            "type":"Services"
        }
    ],
    "sg:phone":"+1 707 539 0538",
    "sg:postcode":"95409",
    "sg:province":"CA",
    "wof:name":"405th Fighter Group Assn",
    "wof:placetype":"venue"
},
  "geometry": {"coordinates":[-122.609539,38.438287],"type":"Point"}
}