{
  "type": "Feature",
  "properties": {
    "addr:full":"6755 N Cedar Ave Fresno CA 93710",
    "addr:housenumber":"6755",
    "addr:postcode":"93710",
    "addr:street":"N Cedar Ave",
    "iso:country":"US",
    "sg:address":"6755 N Cedar Ave",
    "sg:city":"Fresno",
    "sg:classifiers":[
        {
            "category":"Personal",
            "subcategory":"Beauty Salon",
            "type":"Services"
        }
    ],
    "sg:phone":"+1 559 438 7752",
    "sg:postcode":"93710",
    "sg:province":"CA",
    "wof:name":"Hair N Motion",
    "wof:placetype":"venue"
},
  "geometry": {"coordinates":[-119.75416,36.837348],"type":"Point"}
}