{
  "type": "Feature",
  "properties": {
    "iso:country":"US",
    "sg:address":"3537 Chablis Cir",
    "sg:city":"San Jose",
    "sg:classifiers":[
        {
            "category":"Home & Garden",
            "subcategory":"Hardware",
            "type":"Retail Goods"
        }
    ],
    "sg:phone":"+1 408 259 4775",
    "sg:postcode":"95132",
    "sg:province":"CA",
    "wof:name":"Arvin A Brackmann Snap On",
    "wof:placetype":"venue"
},
  "geometry": {"coordinates":[-121.837991,37.40089],"type":"Point"}
}