{
  "type": "Feature",
  "properties": {
    "iso:country":"US",
    "sg:address":"4750 E Cornell Ave",
    "sg:city":"Fresno",
    "sg:classifiers":[
        {
            "category":"Building & Trades",
            "subcategory":"Cleaning & Sanitation",
            "type":"Services"
        }
    ],
    "sg:phone":"+1 559 255 4729",
    "sg:postcode":"93703",
    "sg:province":"CA",
    "sg:tags":[
        "construction",
        "site-clean-up"
    ],
    "wof:name":"Eric Lopez Trash Removal",
    "wof:placetype":"venue"
},
  "geometry": {"coordinates":[-119.737448,36.776899],"type":"Point"}
}