{
  "type": "Feature",
  "properties": {
    "addr:full":"255 E March Ln Stockton CA 95207",
    "addr:housenumber":"255",
    "addr:postcode":"95207",
    "addr:street":"E March Ln",
    "iso:country":"US",
    "sg:address":"255 E March Ln",
    "sg:city":"Stockton",
    "sg:classifiers":[
        {
            "category":"Food & Beverages",
            "subcategory":"Groceries & Convenience Stores",
            "type":"Retail Goods"
        }
    ],
    "sg:phone":"+1 209 957 4920",
    "sg:postcode":"95207",
    "sg:province":"CA",
    "wof:name":"Food 4 Less",
    "wof:placetype":"venue"
},
  "geometry": {"coordinates":[-121.30143,37.999143],"type":"Point"}
}