{
  "type": "Feature",
  "properties": {
    "addr:full":"20571 Hatteras St Woodland Hills CA 91367",
    "addr:postcode":"20571;91367",
    "addr:street":"Hatteras St",
    "iso:country":"US",
    "sg:address":"20571 Hatteras St",
    "sg:city":"Woodland Hills",
    "sg:classifiers":[
        {
            "category":"Insurance",
            "subcategory":"Insurance Agent",
            "type":"Services"
        }
    ],
    "sg:phone":"+1 818 598 8368",
    "sg:postcode":"91367",
    "sg:province":"CA",
    "wof:name":"Porter Brokerage Svc",
    "wof:placetype":"venue"
},
  "geometry": {"coordinates":[-118.579863,34.175287],"type":"Point"}
}