{
  "type": "Feature",
  "properties": {
    "addr:full":"5815 Market St Oakland CA 94608",
    "addr:housenumber":"5815",
    "addr:postcode":"94608",
    "addr:street":"Market St",
    "iso:country":"US",
    "sg:address":"5815 Market St",
    "sg:city":"Oakland",
    "sg:classifiers":[
        {
            "category":"Retail",
            "subcategory":"Car Wash",
            "type":"Services"
        }
    ],
    "sg:phone":"+1 510 655 6512",
    "sg:postcode":"94608",
    "sg:province":"CA",
    "sg:tags":[
        "automobile",
        "detail",
        "clean"
    ],
    "wof:name":"Jimmy's House of Sparkles",
    "wof:placetype":"venue"
},
  "geometry": {"coordinates":[-122.275002,37.843201],"type":"Point"}
}