{
  "type": "Feature",
  "properties": {
    "addr:full":"Westwide Pavillion 10800 W Pico Blvd Los Angeles CA 90189",
    "addr:housenumber":"10800",
    "addr:postcode":"90189",
    "addr:street":"W Pico Blvd",
    "iso:country":"US",
    "sg:address":"Westwide Pavillion 10800 W Pico Blvd",
    "sg:city":"Los Angeles",
    "sg:classifiers":[
        {
            "category":"Shopping",
            "subcategory":"Clothing, Apparel, & Fashions",
            "type":"Retail Goods"
        }
    ],
    "sg:phone":"+1 310 470 3300",
    "sg:postcode":"90189",
    "sg:province":"CA",
    "sg:tags":[
        "clothing",
        "women's"
    ],
    "wof:name":"ANGL",
    "wof:placetype":"venue"
},
  "geometry": {"coordinates":[-118.426919,34.04034],"type":"Point"}
}