{
  "type": "Feature",
  "properties": {
    "addr:full":"135 Mason Ct Crescent City CA 95531",
    "addr:housenumber":"135",
    "addr:postcode":"95531",
    "addr:street":"Mason Ct Crescent",
    "iso:country":"US",
    "sg:address":"135 Mason Ct",
    "sg:city":"Crescent City",
    "sg:classifiers":[
        {
            "category":"Social Services",
            "subcategory":"Child Care",
            "type":"Services"
        }
    ],
    "sg:phone":"+1 707 465 4434",
    "sg:postcode":"95531",
    "sg:province":"CA",
    "wof:name":"Gracie's Family Child Care",
    "wof:placetype":"venue"
},
  "geometry": {"coordinates":[-124.203326,41.768339],"type":"Point"}
}