{
  "type": "Feature",
  "properties": {
    "addr:full":"329 S Coast Hwy Laguna Beach CA 92651",
    "addr:housenumber":"329",
    "addr:postcode":"92651",
    "addr:street":"S Coast Hwy",
    "iso:country":"US",
    "sg:address":"329 S Coast Hwy",
    "sg:city":"Laguna Beach",
    "sg:classifiers":[
        {
            "category":"Restaurant",
            "type":"Food & Drink"
        }
    ],
    "sg:phone":"+1 949 494 0361",
    "sg:postcode":"92651",
    "sg:province":"CA",
    "wof:name":"Greeter's Corner Restaurant",
    "wof:placetype":"venue"
},
  "geometry": {"coordinates":[-117.78525,33.542638],"type":"Point"}
}