{
  "type": "Feature",
  "properties": {
    "addr:full":"421 N Brookhurst St Anaheim CA 92801",
    "addr:housenumber":"421",
    "addr:postcode":"92801",
    "addr:street":"N Brookhurst St",
    "iso:country":"US",
    "sg:address":"421 N Brookhurst St",
    "sg:city":"Anaheim",
    "sg:classifiers":[
        {
            "category":"Shopping",
            "type":"Retail Goods"
        }
    ],
    "sg:phone":"+1 714 635 8697",
    "sg:postcode":"92801",
    "sg:province":"CA",
    "sg:tags":[
        "cosmetic",
        "perfume"
    ],
    "wof:name":"Avon Products",
    "wof:placetype":"venue"
},
  "geometry": {"coordinates":[-117.95911099999999,33.83914],"type":"Point"}
}