{
  "type": "Feature",
  "properties": {
    "iso:country":"US",
    "sg:address":"3341 Graybar Ct",
    "sg:city":"Oceanside",
    "sg:classifiers":[
        {
            "category":"Personal",
            "subcategory":"Massage",
            "type":"Services"
        }
    ],
    "sg:phone":"+1 760 310 9915",
    "sg:postcode":"92056",
    "sg:province":"CA",
    "wof:name":"A Absolute Massage Therapy",
    "wof:placetype":"venue"
},
  "geometry": {"coordinates":[-117.313509,33.197056],"type":"Point"}
}