{
  "type": "Feature",
  "properties": {
    "addr:full":"137 Jordan Ave San Francisco CA 94118",
    "addr:housenumber":"137",
    "addr:postcode":"94118",
    "addr:street":"Jordan Ave",
    "iso:country":"US",
    "sg:address":"137 Jordan Ave",
    "sg:city":"San Francisco",
    "sg:classifiers":[
        {
            "category":"Freight",
            "type":"Transportation"
        }
    ],
    "sg:phone":"+1 415 386 3577",
    "sg:postcode":"94118",
    "sg:province":"CA",
    "sg:tags":[
        "operator",
        "trucking"
    ],
    "wof:name":"Covenant Transport Service",
    "wof:placetype":"venue"
},
  "geometry": {"coordinates":[-122.456757,37.782349],"type":"Point"}
}