{
  "type": "Feature",
  "properties": {
    "iso:country":"US",
    "sg:address":"1042 Santee St",
    "sg:city":"Los Angeles",
    "sg:classifiers":[
        {
            "category":"Shopping",
            "subcategory":"Clothing, Apparel, & Fashions",
            "type":"Retail Goods"
        }
    ],
    "sg:phone":"+1 213 746 1301",
    "sg:postcode":"90015",
    "sg:province":"CA",
    "sg:tags":[
        "clothing",
        "women's"
    ],
    "wof:name":"Cantata",
    "wof:placetype":"venue"
},
  "geometry": {"coordinates":[-118.255997,34.037998],"type":"Point"}
}