{
  "type": "Feature",
  "properties": {
    "addr:full":"7015 Bohn Blvd Anderson CA 96007",
    "addr:housenumber":"7015",
    "addr:postcode":"96007",
    "addr:street":"Bohn Blvd",
    "iso:country":"US",
    "sg:address":"7015 Bohn Blvd",
    "sg:city":"Anderson",
    "sg:classifiers":[
        {
            "category":"Professional",
            "subcategory":"Accounting & Tax Preparation",
            "type":"Services"
        }
    ],
    "sg:phone":"+1 530 365 6232",
    "sg:postcode":"96007",
    "sg:province":"CA",
    "sg:tags":[
        "bookkeeping",
        "general"
    ],
    "wof:name":"Innovative Accounting",
    "wof:placetype":"venue"
},
  "geometry": {"coordinates":[-122.42080900000001,40.489838],"type":"Point"}
}