{
  "type": "Feature",
  "properties": {
    "addr:full":"5250 Bonsai St Moorpark CA 93021",
    "addr:postcode":"5250;ca 93021",
    "addr:street":"Bonsai St",
    "iso:country":"US",
    "sg:address":"5250 Bonsai St",
    "sg:city":"Moorpark",
    "sg:classifiers":[
        {
            "category":"Manufacturing",
            "subcategory":"Tools & Machinery",
            "type":"Manufacturing & Wholesale Goods"
        }
    ],
    "sg:phone":"+1 805 553 9670",
    "sg:postcode":"93021",
    "sg:province":"CA",
    "sg:tags":[
        "machine",
        "shop"
    ],
    "wof:name":"TND Precision Inc",
    "wof:placetype":"venue"
},
  "geometry": {"coordinates":[-118.89407300000001,34.281561],"type":"Point"}
}