{
  "type": "Feature",
  "properties": {
    "addr:full":"5687 Indian Ave San Jose CA 95123",
    "addr:housenumber":"5687",
    "addr:postcode":"95123",
    "addr:street":"Indian Ave",
    "iso:country":"US",
    "sg:address":"5687 Indian Ave",
    "sg:city":"San Jose",
    "sg:classifiers":[
        {
            "category":"Home & Garden",
            "subcategory":"Building Materials",
            "type":"Retail Goods"
        }
    ],
    "sg:phone":"+1 408 629 6929",
    "sg:postcode":"95123",
    "sg:province":"CA",
    "sg:tags":[
        "equipment",
        "fixture",
        "lighting"
    ],
    "wof:name":"Baro Lights USA",
    "wof:placetype":"venue"
},
  "geometry": {"coordinates":[-121.841003,37.2481],"type":"Point"}
}