{
  "type": "Feature",
  "properties": {
    "iso:country":"US",
    "sg:address":"116 State Rte 66",
    "sg:city":"Glendora",
    "sg:classifiers":[
        {
            "category":"Restaurant",
            "type":"Food & Drink"
        }
    ],
    "sg:phone":"+1 626 963 2616",
    "sg:postcode":"91740",
    "sg:province":"CA",
    "wof:name":"Taco Bell",
    "wof:placetype":"venue"
},
  "geometry": {"coordinates":[-117.86275999999999,34.128603],"type":"Point"}
}