{
  "type": "Feature",
  "properties": {
    "iso:country":"US",
    "sg:address":"1142 N Chinowth St",
    "sg:city":"Visalia",
    "sg:classifiers":[
        {
            "category":"Health Services",
            "subcategory":"Doctor",
            "type":"Services"
        }
    ],
    "sg:phone":"+1 559 636 7424",
    "sg:postcode":"93291",
    "sg:province":"CA",
    "sg:tags":[
        "dentist"
    ],
    "wof:name":"David Mayeda DDS",
    "wof:placetype":"venue"
},
  "geometry": {"coordinates":[-119.336257,36.338656],"type":"Point"}
}