{
  "type": "Feature",
  "properties": {
    "addr:full":"3426 Blackhawk Plaza Cir Danville CA 94506",
    "addr:housenumber":"3426",
    "addr:postcode":"94506",
    "addr:street":"Blackhawk Plaza Cir",
    "iso:country":"US",
    "sg:address":"3426 Blackhawk Plaza Cir",
    "sg:city":"Danville",
    "sg:classifiers":[
        {
            "category":"Manufacturing",
            "subcategory":"Furniture",
            "type":"Manufacturing & Wholesale Goods"
        }
    ],
    "sg:phone":"+1 925 648 2102",
    "sg:postcode":"94506",
    "sg:province":"CA",
    "wof:name":"2casabonita Inc",
    "wof:placetype":"venue"
},
  "geometry": {"coordinates":[-121.91713799999999,37.799677],"type":"Point"}
}