{
  "type": "Feature",
  "properties": {
    "iso:country":"US",
    "sg:address":"6055 E Washington Boulevard",
    "sg:city":"Los Angeles",
    "sg:classifiers":[
        {
            "category":"Professional",
            "subcategory":"Accounting & Tax Preparation",
            "type":"Services"
        }
    ],
    "sg:phone":"+1 323 726 2411",
    "sg:postcode":"90040",
    "sg:province":"CA",
    "sg:tags":[
        "accountant"
    ],
    "wof:name":"Traynor Paul CPA",
    "wof:placetype":"venue"
},
  "geometry": {"coordinates":[-118.148392,33.996482],"type":"Point"}
}