{
  "type": "Feature",
  "properties": {
    "addr:full":"1360 White Oaks Rd Ste C Campbell CA 95008",
    "addr:housenumber":"1360",
    "addr:postcode":"95008",
    "addr:street":"White Oaks Rd Ste C",
    "iso:country":"US",
    "sg:address":"1360 White Oaks Rd Ste C",
    "sg:city":"Campbell",
    "sg:classifiers":[
        {
            "category":"Retail",
            "subcategory":"Auto Repair",
            "type":"Services"
        }
    ],
    "sg:phone":"+1 408 371 6372",
    "sg:postcode":"95008",
    "sg:province":"CA",
    "wof:name":"White Oaks Mercedes",
    "wof:placetype":"venue"
},
  "geometry": {"coordinates":[-121.94699900000001,37.268101],"type":"Point"}
}