{
  "type": "Feature",
  "properties": {
    "addr:full":"2531 E Whitmore Ave Ceres CA 95307",
    "addr:housenumber":"2531",
    "addr:postcode":"95307",
    "addr:street":"E Whitmore Ave",
    "iso:country":"US",
    "sg:address":"2531 E Whitmore Ave",
    "sg:city":"Ceres",
    "sg:classifiers":[
        {
            "category":"Food & Beverages",
            "subcategory":"Groceries & Convenience Stores",
            "type":"Retail Goods"
        }
    ],
    "sg:phone":"+1 209 537 3500",
    "sg:postcode":"95307",
    "sg:province":"CA",
    "wof:name":"Richland Markets",
    "wof:placetype":"venue"
},
  "geometry": {"coordinates":[-120.94899700000001,37.5947],"type":"Point"}
}