{
  "type": "Feature",
  "properties": {
    "addr:full":"8320 Iowa St Downey CA 90241",
    "addr:housenumber":"8320",
    "addr:postcode":"90241",
    "addr:street":"Iowa St",
    "iso:country":"US",
    "sg:address":"8320 Iowa St",
    "sg:city":"Downey",
    "sg:classifiers":[
        {
            "category":"Health Services",
            "subcategory":"Hospital",
            "type":"Services"
        }
    ],
    "sg:phone":"+1 562 904 4815",
    "sg:postcode":"90241",
    "sg:province":"CA",
    "sg:tags":[
        "mental"
    ],
    "wof:name":"Community Family",
    "wof:placetype":"venue"
},
  "geometry": {"coordinates":[-118.133374,33.937074],"type":"Point"}
}