{
  "type": "Feature",
  "properties": {
    "addr:full":"23 Picket Ln Aliso Viejo CA 92656",
    "addr:housenumber":"23",
    "addr:postcode":"92656",
    "addr:street":"Picket Ln",
    "iso:country":"US",
    "sg:address":"23 Picket Ln",
    "sg:city":"Aliso Viejo",
    "sg:classifiers":[
        {
            "category":"Professional",
            "type":"Services"
        }
    ],
    "sg:phone":"+1 949 215 6211",
    "sg:postcode":"92656",
    "sg:province":"CA",
    "wof:name":"Fruitnowcom Corporation",
    "wof:placetype":"venue"
},
  "geometry": {"coordinates":[-117.73174,33.57338],"type":"Point"}
}