{
  "type": "Feature",
  "properties": {
    "addr:full":"4450 E Commerce Way Sacramento CA 95834",
    "addr:housenumber":"4450",
    "addr:postcode":"95834",
    "addr:street":"E Commerce Way",
    "iso:country":"US",
    "sg:address":"4450 E Commerce Way",
    "sg:city":"Sacramento",
    "sg:classifiers":[
        {
            "category":"Professional",
            "subcategory":"Computer Services",
            "type":"Services"
        }
    ],
    "sg:phone":"+1 866 804 3504",
    "sg:postcode":"95834",
    "sg:province":"CA",
    "sg:tags":[
        "technical",
        "assistance",
        "support"
    ],
    "sg:website":"http://www.comcast.com",
    "wof:name":"Comcast Sportsnet West, Inc.",
    "wof:placetype":"venue"
},
  "geometry": {"coordinates":[-121.52572499999999,38.652888],"type":"Point"}
}