{
  "type": "Feature",
  "properties": {
    "addr:full":"140 S Whisman Road Mountain View CA 94041",
    "addr:housenumber":"140",
    "addr:postcode":"94041",
    "addr:street":"S Whisman Road",
    "iso:country":"US",
    "sg:address":"140 S Whisman Road",
    "sg:city":"Mountain View",
    "sg:classifiers":[
        {
            "category":"Retail",
            "subcategory":"Auto Repair",
            "type":"Services"
        }
    ],
    "sg:phone":"+1 650 390 9367",
    "sg:postcode":"94041",
    "sg:province":"CA",
    "wof:name":"Zinola's Machine Shop",
    "wof:placetype":"venue"
},
  "geometry": {"coordinates":[-122.07760399999999,37.391452],"type":"Point"}
}