{
  "type": "Feature",
  "properties": {
    "iso:country":"US",
    "sg:address":"1739 Berkeley St",
    "sg:city":"Santa Monica",
    "sg:classifiers":[
        {
            "category":"Professional",
            "subcategory":"Lawyer & Legal Services",
            "type":"Services"
        }
    ],
    "sg:phone":"+1 310 828 3703",
    "sg:postcode":"90404",
    "sg:province":"CA",
    "sg:tags":[
        "attorney"
    ],
    "wof:name":"Susan Kaiser Law Offices",
    "wof:placetype":"venue"
},
  "geometry": {"coordinates":[-118.463602,34.032488],"type":"Point"}
}