{
  "type": "Feature",
  "properties": {
    "iso:country":"US",
    "sg:address":"21053 Devonshire St # 102",
    "sg:city":"Chatsworth",
    "sg:classifiers":[
        {
            "category":"Professional",
            "subcategory":"Testing Lab",
            "type":"Services"
        },
        {
            "category":"Health Services",
            "subcategory":"Medical Lab",
            "type":"Services"
        }
    ],
    "sg:phone":"+1 818 882 2621",
    "sg:postcode":"91311",
    "sg:province":"CA",
    "sg:tags":[
        "laboratory",
        "dental"
    ],
    "wof:name":"Sepulveda Dental Laboratory",
    "wof:placetype":"venue"
},
  "geometry": {"coordinates":[-118.59191300000001,34.257246],"type":"Point"}
}