{
  "type": "Feature",
  "properties": {
    "addr:full":"3134 Glendale Blvd Los Angeles CA 90039",
    "addr:housenumber":"3134",
    "addr:postcode":"90039",
    "addr:street":"Glendale Blvd",
    "iso:country":"US",
    "sg:address":"3134 Glendale Blvd",
    "sg:city":"Los Angeles",
    "sg:classifiers":[
        {
            "category":"Restaurant",
            "type":"Food & Drink"
        }
    ],
    "sg:phone":"+1 323 664 7386",
    "sg:postcode":"90039",
    "sg:province":"CA",
    "wof:name":"Revo Cafe",
    "wof:placetype":"venue"
},
  "geometry": {"coordinates":[-118.262304,34.116465],"type":"Point"}
}