{
  "type": "Feature",
  "properties": {
    "addr:full":"44180 Palm Ave Hemet CA 92544",
    "addr:housenumber":"44180",
    "addr:postcode":"92544",
    "addr:street":"Palm Ave",
    "iso:country":"US",
    "sg:address":"44180 Palm Ave",
    "sg:city":"Hemet",
    "sg:classifiers":[
        {
            "category":"Building & Trades",
            "subcategory":"Landscaping Services",
            "type":"Services"
        }
    ],
    "sg:phone":"+1 951 927 3402",
    "sg:postcode":"92544",
    "sg:province":"CA",
    "sg:tags":[
        "tree"
    ],
    "wof:name":"A 1 Tree Svc",
    "wof:placetype":"venue"
},
  "geometry": {"coordinates":[-116.89112799999999,33.751554],"type":"Point"}
}