{
  "type": "Feature",
  "properties": {
    "addr:full":"1230 N Main St Fort Bragg CA 95437",
    "addr:housenumber":"1230",
    "addr:postcode":"95437",
    "addr:street":"N Main St",
    "iso:country":"US",
    "sg:address":"1230 N Main St",
    "sg:city":"Fort Bragg",
    "sg:classifiers":[
        {
            "category":"Retail",
            "subcategory":"Repair Shop",
            "type":"Services"
        }
    ],
    "sg:phone":"+1 707 964 6820",
    "sg:postcode":"95437",
    "sg:province":"CA",
    "sg:tags":[
        "welding"
    ],
    "wof:name":"Woody's Weld-All",
    "wof:placetype":"venue"
},
  "geometry": {"coordinates":[-123.804258,39.46607],"type":"Point"}
}