{
  "type": "Feature",
  "properties": {
    "addr:full":"28004 Whitestone Ct Hayward CA 94542",
    "addr:postcode":"28004;94542",
    "addr:street":"Ct",
    "iso:country":"US",
    "sg:address":"28004 Whitestone Ct",
    "sg:city":"Hayward",
    "sg:classifiers":[
        {
            "category":"Professional",
            "type":"Services"
        }
    ],
    "sg:phone":"+1 510 728 1551",
    "sg:postcode":"94542",
    "sg:province":"CA",
    "wof:name":"Camelback Manor Ltd LP",
    "wof:placetype":"venue"
},
  "geometry": {"coordinates":[-122.03742,37.652168],"type":"Point"}
}