{
  "type": "Feature",
  "properties": {
    "iso:country":"US",
    "sg:address":"5798 Penland Rd",
    "sg:city":"Hidden Hills",
    "sg:classifiers":[
        {
            "category":"Professional",
            "type":"Services"
        }
    ],
    "sg:phone":"+1 818 348 2651",
    "sg:postcode":"91302",
    "sg:province":"CA",
    "sg:tags":[
        "establishment"
    ],
    "wof:name":"Tanda Productions Inc",
    "wof:placetype":"venue"
},
  "geometry": {"coordinates":[-118.652028,34.164989],"type":"Point"}
}