{
  "type": "Feature",
  "properties": {
    "iso:country":"US",
    "sg:address":"627 Capitola Ave",
    "sg:city":"Capitola",
    "sg:classifiers":[
        {
            "category":"Personal",
            "subcategory":"Beauty Salon",
            "type":"Services"
        }
    ],
    "sg:phone":"+1 831 475 1691",
    "sg:postcode":"95010",
    "sg:province":"CA",
    "wof:name":"Mimi's Hair Design",
    "wof:placetype":"venue"
},
  "geometry": {"coordinates":[-121.953318,36.978008],"type":"Point"}
}