{
  "type": "Feature",
  "properties": {
    "addr:full":"16721 Burl Ln Occidental CA 95465",
    "addr:housenumber":"16721",
    "addr:postcode":"95465",
    "addr:street":"Burl Ln",
    "iso:country":"US",
    "sg:address":"16721 Burl Ln",
    "sg:city":"Occidental",
    "sg:classifiers":[
        {
            "category":"Real Estate",
            "subcategory":"Architect",
            "type":"Services"
        }
    ],
    "sg:phone":"+1 707 876 3515",
    "sg:postcode":"95465",
    "sg:province":"CA",
    "wof:name":"Benson Rhen A Architect",
    "wof:placetype":"venue"
},
  "geometry": {"coordinates":[-122.965491,38.368865],"type":"Point"}
}