{
  "type": "Feature",
  "properties": {
    "addr:full":"444 17th St Oakland CA 94612",
    "addr:housenumber":"444",
    "addr:postcode":"94612",
    "addr:street":"17Th St",
    "iso:country":"US",
    "sg:address":"444 17th St",
    "sg:city":"Oakland",
    "sg:classifiers":[
        {
            "category":"Real Estate",
            "subcategory":"Architect",
            "type":"Services"
        }
    ],
    "sg:phone":"+1 510 465 1284",
    "sg:postcode":"94612",
    "sg:province":"CA",
    "sg:website":"www.PGAdesign.com",
    "wof:name":"PGAdesign Inc",
    "wof:placetype":"venue"
},
  "geometry": {"coordinates":[-122.269323,37.806561],"type":"Point"}
}