{
  "type": "Feature",
  "properties": {
    "iso:country":"US",
    "sg:address":"7638 Monterey St",
    "sg:city":"Gilroy",
    "sg:classifiers":[
        {
            "category":"Food & Beverages",
            "subcategory":"Groceries & Convenience Stores",
            "type":"Retail Goods"
        }
    ],
    "sg:phone":"+1 408 842 3659",
    "sg:postcode":"95020",
    "sg:province":"CA",
    "sg:tags":[
        "grocer"
    ],
    "wof:name":"El Charrito Market",
    "wof:placetype":"venue"
},
  "geometry": {"coordinates":[-121.57056,37.010985],"type":"Point"}
}