{
  "type": "Feature",
  "properties": {
    "addr:full":"3800 Gilmore Ave Bakersfield CA 93308",
    "addr:housenumber":"3800",
    "addr:postcode":"93308",
    "addr:street":"Gilmore Ave",
    "iso:country":"US",
    "sg:address":"3800 Gilmore Ave",
    "sg:city":"Bakersfield",
    "sg:classifiers":[
        {
            "category":"Building & Trades",
            "subcategory":"Construction",
            "type":"Services"
        }
    ],
    "sg:phone":"+1 661 323 5904",
    "sg:postcode":"93308",
    "sg:province":"CA",
    "sg:tags":[
        "product",
        "asphalt"
    ],
    "wof:name":"VSS Emultech",
    "wof:placetype":"venue"
},
  "geometry": {"coordinates":[-119.05316999999999,35.389601],"type":"Point"}
}