{
  "type": "Feature",
  "properties": {
    "iso:country":"US",
    "sg:address":"777 Hwy 101",
    "sg:city":"Solana Beach",
    "sg:classifiers":[
        {
            "category":"Real Estate",
            "subcategory":"Developer",
            "type":"Services"
        }
    ],
    "sg:phone":"+1 858 350 0585",
    "sg:postcode":"92075",
    "sg:province":"CA",
    "sg:website":"www.orlandocompany.com",
    "wof:name":"Orlando Co",
    "wof:placetype":"venue"
},
  "geometry": {"coordinates":[-117.269817,32.984014],"type":"Point"}
}