{
  "type": "Feature",
  "properties": {
    "addr:full":"9101 Ventura Ct Hesperia CA 92344",
    "addr:housenumber":"9101",
    "addr:postcode":"92344",
    "addr:street":"Ventura Ct",
    "iso:country":"US",
    "sg:address":"9101 Ventura Ct",
    "sg:city":"Hesperia",
    "sg:classifiers":[
        {
            "category":"Shopping",
            "subcategory":"Computers & Home Electronics",
            "type":"Retail Goods"
        }
    ],
    "sg:phone":"+1 760 244 9487",
    "sg:postcode":"92344",
    "sg:province":"CA",
    "sg:tags":[
        "equipment",
        "dealer"
    ],
    "wof:name":"Hillside Cad Drafting Computer",
    "wof:placetype":"venue"
},
  "geometry": {"coordinates":[-117.347054,34.415056],"type":"Point"}
}