{
  "type": "Feature",
  "properties": {
    "iso:country":"US",
    "sg:address":"4764 Voltaire Street",
    "sg:city":"San Diego",
    "sg:classifiers":[
        {
            "category":"Personal",
            "subcategory":"Skin Care",
            "type":"Services"
        }
    ],
    "sg:phone":"+1 619 222 7546",
    "sg:postcode":"92107",
    "sg:province":"CA",
    "wof:name":"Skin Clinique",
    "wof:placetype":"venue"
},
  "geometry": {"coordinates":[-117.24282100000001,32.749813],"type":"Point"}
}