{
  "type": "Feature",
  "properties": {
    "addr:full":"1637 W Imola Ave Napa CA 94559",
    "addr:housenumber":"1637",
    "addr:postcode":"94559",
    "addr:street":"W Imola Ave",
    "iso:country":"US",
    "sg:address":"1637 W Imola Ave",
    "sg:city":"Napa",
    "sg:classifiers":[
        {
            "category":"Sports & Exercise",
            "subcategory":"Gym",
            "type":"Entertainment"
        }
    ],
    "sg:phone":"+1 707 226 6200",
    "sg:postcode":"94559",
    "sg:province":"CA",
    "sg:tags":[
        "club",
        "health",
        "studio",
        "gymnasium"
    ],
    "sg:website":"www.ladyofnapa.com",
    "wof:name":"Lady Of America",
    "wof:placetype":"venue"
},
  "geometry": {"coordinates":[-122.289706,38.281685],"type":"Point"}
}