{
  "type": "Feature",
  "properties": {
    "iso:country":"US",
    "sg:address":"924 E Pacific Coast Hwy",
    "sg:city":"Long Beach",
    "sg:classifiers":[
        {
            "category":"Food & Beverages",
            "subcategory":"Bakery",
            "type":"Retail Goods"
        }
    ],
    "sg:phone":"+1 562 591 2275",
    "sg:postcode":"90806",
    "sg:province":"CA",
    "sg:tags":[
        "donut",
        "eating"
    ],
    "wof:name":"P & B Donut Shop",
    "wof:placetype":"venue"
},
  "geometry": {"coordinates":[-118.181,33.7897],"type":"Point"}
}