{
  "type": "Feature",
  "properties": {
    "addr:full":"4460 Santa Monica Boulevard Los Angeles CA 90029",
    "addr:housenumber":"4460",
    "addr:postcode":"90029",
    "addr:street":"Santa Monica Boulevard",
    "iso:country":"US",
    "sg:address":"4460 Santa Monica Boulevard",
    "sg:city":"Los Angeles",
    "sg:classifiers":[
        {
            "category":"Food & Beverages",
            "subcategory":"Groceries & Convenience Stores",
            "type":"Retail Goods"
        }
    ],
    "sg:phone":"+1 323 665 1701",
    "sg:postcode":"90029",
    "sg:province":"CA",
    "wof:name":"7-Eleven Food Stores",
    "wof:placetype":"venue"
},
  "geometry": {"coordinates":[-118.28630699999999,34.090973],"type":"Point"}
}