{
  "type": "Feature",
  "properties": {
    "addr:full":"1360 W 6th St San Pedro CA 90732",
    "addr:housenumber":"1360",
    "addr:postcode":"90732",
    "addr:street":"W 6Th St",
    "iso:country":"US",
    "sg:address":"1360 W 6th St",
    "sg:city":"San Pedro",
    "sg:classifiers":[
        {
            "category":"Health Services",
            "subcategory":"Doctor",
            "type":"Services"
        }
    ],
    "sg:phone":"+1 310 831 8127",
    "sg:postcode":"90732",
    "sg:province":"CA",
    "sg:tags":[
        "physician",
        "surgeon"
    ],
    "wof:name":"Peninsula Pain Management",
    "wof:placetype":"venue"
},
  "geometry": {"coordinates":[-118.308097,33.738423],"type":"Point"}
}