{
  "type": "Feature",
  "properties": {
    "addr:full":"8040 Greenback Lane Citrus Heights CA 95610",
    "addr:housenumber":"8040",
    "addr:postcode":"95610",
    "addr:street":"Greenback Lane",
    "iso:country":"US",
    "sg:address":"8040 Greenback Lane",
    "sg:city":"Citrus Heights",
    "sg:classifiers":[
        {
            "category":"Arena",
            "subcategory":"Sports Club",
            "type":"Entertainment"
        }
    ],
    "sg:phone":"+1 916 721 3997",
    "sg:postcode":"95610",
    "sg:province":"CA",
    "sg:tags":[
        "martial art"
    ],
    "sg:website":"www.sac-taekukmusul.com",
    "wof:name":"Tae Kuk Mu Sul",
    "wof:placetype":"venue"
},
  "geometry": {"coordinates":[-121.264235,38.678449],"type":"Point"}
}