{
  "type": "Feature",
  "properties": {
    "iso:country":"US",
    "sg:address":"3300 Webster St Suite 1105",
    "sg:city":"Oakland",
    "sg:classifiers":[
        {
            "category":"Travel",
            "subcategory":"Travel Agent",
            "type":"Entertainment"
        }
    ],
    "sg:phone":"+1 510 763 5336",
    "sg:postcode":"94609",
    "sg:province":"CA",
    "sg:website":"www.thetraveldoctor.net",
    "wof:name":"The Travel Doctor",
    "wof:placetype":"venue"
},
  "geometry": {"coordinates":[-122.262114,37.821201],"type":"Point"}
}