{
  "type": "Feature",
  "properties": {
    "addr:full":"17360 Norwalk Blvd Cerritos CA 90703",
    "addr:housenumber":"17360",
    "addr:postcode":"ca 90703",
    "addr:street":"Norwalk Blvd",
    "iso:country":"US",
    "sg:address":"17360 Norwalk Blvd",
    "sg:city":"Cerritos",
    "sg:classifiers":[
        {
            "category":"Health Services",
            "subcategory":"Dentist",
            "type":"Services"
        }
    ],
    "sg:phone":"+1 562 402 8899",
    "sg:postcode":"90703",
    "sg:province":"CA",
    "wof:name":"Srivivatanakul Jirawan",
    "wof:placetype":"venue"
},
  "geometry": {"coordinates":[-118.233226,33.873351],"type":"Point"}
}