{
  "type": "Feature",
  "properties": {
    "iso:country":"US",
    "sg:address":"2959 E Pacific Commerce Dr",
    "sg:city":"Compton",
    "sg:classifiers":[
        {
            "category":"Professional",
            "subcategory":"Testing Lab",
            "type":"Services"
        }
    ],
    "sg:phone":"+1 310 763 2374",
    "sg:postcode":"90221",
    "sg:province":"CA",
    "sg:tags":[
        "asbestos"
    ],
    "wof:name":"Forensic Analytical",
    "wof:placetype":"venue"
},
  "geometry": {"coordinates":[-118.207544,33.849747],"type":"Point"}
}