{
  "type": "Feature",
  "properties": {
    "iso:country":"US",
    "sg:address":"2535 Cam del Rio S",
    "sg:city":"San Diego",
    "sg:classifiers":[
        {
            "category":"Health Services",
            "subcategory":"Chiropractor",
            "type":"Services"
        }
    ],
    "sg:phone":"+1 619 681 1919",
    "sg:postcode":"92108",
    "sg:province":"CA",
    "wof:name":"Deters Chiropractic Ctr",
    "wof:placetype":"venue"
},
  "geometry": {"coordinates":[-117.137294,32.769521],"type":"Point"}
}