{
  "type": "Feature",
  "properties": {
    "addr:full":"20122 Village Green Dr Lakewood CA 90715",
    "addr:housenumber":"20122",
    "addr:postcode":"90715",
    "addr:street":"Village Green Dr",
    "iso:country":"US",
    "sg:address":"20122 Village Green Dr",
    "sg:city":"Lakewood",
    "sg:classifiers":[
        {
            "category":"Travel",
            "subcategory":"Travel Agent",
            "type":"Entertainment"
        }
    ],
    "sg:phone":"+1 562 402 9370",
    "sg:postcode":"90715",
    "sg:province":"CA",
    "sg:tags":[
        "operator",
        "tour"
    ],
    "wof:name":"Walker Tours",
    "wof:placetype":"venue"
},
  "geometry": {"coordinates":[-118.08319,33.84776],"type":"Point"}
}