{
  "type": "Feature",
  "properties": {
    "iso:country":"US",
    "sg:address":"271 Jefferson St",
    "sg:city":"San Francisco",
    "sg:classifiers":[
        {
            "category":"Wholesale",
            "subcategory":"Jewelry",
            "type":"Manufacturing & Wholesale Goods"
        }
    ],
    "sg:phone":"+1 415 928 0961",
    "sg:postcode":"94133",
    "sg:province":"CA",
    "wof:name":"Crown Pearls International",
    "wof:placetype":"venue"
},
  "geometry": {"coordinates":[-122.416507,37.808082],"type":"Point"}
}