{
  "type": "Feature",
  "properties": {
    "addr:full":"620 N Doheny Dr West Hollywood CA 90069",
    "addr:housenumber":"620",
    "addr:postcode":"90069",
    "addr:street":"N Doheny Dr",
    "iso:country":"US",
    "sg:address":"620 N Doheny Dr",
    "sg:city":"West Hollywood",
    "sg:classifiers":[
        {
            "category":"Travel",
            "subcategory":"Travel Agent",
            "type":"Entertainment"
        }
    ],
    "sg:phone":"+1 310 275 1933",
    "sg:postcode":"90069",
    "sg:province":"CA",
    "sg:tags":[
        "agency"
    ],
    "wof:name":"Alliannce Travel Group",
    "wof:placetype":"venue"
},
  "geometry": {"coordinates":[-118.389669,34.081958],"type":"Point"}
}