{
  "type": "Feature",
  "properties": {
    "iso:country":"US",
    "sg:address":"1004 Magnolia Ave",
    "sg:city":"Modesto",
    "sg:classifiers":[
        {
            "category":"Real Estate",
            "subcategory":"Architect",
            "type":"Services"
        }
    ],
    "sg:phone":"+1 209 529 6136",
    "sg:postcode":"95350",
    "sg:province":"CA",
    "wof:name":"Sample Sharon Architect",
    "wof:placetype":"venue"
},
  "geometry": {"coordinates":[-120.99700199999999,37.657902],"type":"Point"}
}