{
  "type": "Feature",
  "properties": {
    "addr:full":"8749 Merrill Ave Chino CA 91710",
    "addr:housenumber":"8749",
    "addr:postcode":"91710",
    "addr:street":"Merrill Ave",
    "iso:country":"US",
    "sg:address":"8749 Merrill Ave",
    "sg:city":"Chino",
    "sg:classifiers":[
        {
            "category":"Wholesale",
            "subcategory":"Dairy",
            "type":"Manufacturing & Wholesale Goods"
        }
    ],
    "sg:phone":"+1 909 923 1170",
    "sg:postcode":"91710",
    "sg:province":"CA",
    "sg:tags":[
        "product"
    ],
    "wof:name":"Fagundes Family Farm",
    "wof:placetype":"venue"
},
  "geometry": {"coordinates":[-117.620166,33.983168],"type":"Point"}
}