{
  "type": "Feature",
  "properties": {
    "addr:full":"1961 Pruneridge Avenue Santa Clara CA 95050",
    "addr:housenumber":"1961",
    "addr:postcode":"95050",
    "addr:street":"Pruneridge Avenue",
    "iso:country":"US",
    "sg:address":"1961 Pruneridge Avenue",
    "sg:city":"Santa Clara",
    "sg:classifiers":[
        {
            "category":"Health Services",
            "subcategory":"Dentist",
            "type":"Services"
        }
    ],
    "sg:phone":"+1 408 248 3384",
    "sg:postcode":"95050",
    "sg:province":"CA",
    "wof:name":"Sumida Steven DDS",
    "wof:placetype":"venue"
},
  "geometry": {"coordinates":[-121.95371,37.329979],"type":"Point"}
}