{
  "type": "Feature",
  "properties": {
    "iso:country":"US",
    "sg:address":"1300 Lincoln Rd E",
    "sg:city":"Vallejo",
    "sg:classifiers":[
        {
            "category":"Real Estate",
            "subcategory":"Real Estate Operator",
            "type":"Services"
        }
    ],
    "sg:phone":"+1 707 554 2084",
    "sg:postcode":"94591",
    "sg:province":"CA",
    "sg:tags":[
        "mobile",
        "home",
        "community"
    ],
    "wof:name":"Sunset Trailer Park",
    "wof:placetype":"venue"
},
  "geometry": {"coordinates":[-122.229445,38.099191],"type":"Point"}
}