{
  "type": "Feature",
  "properties": {
    "addr:full":"5827 West 77th Place Los Angeles CA 90045",
    "addr:housenumber":"5827",
    "addr:postcode":"90045",
    "addr:street":"West 77Th Place",
    "iso:country":"US",
    "sg:address":"5827 West 77th Place",
    "sg:city":"Los Angeles",
    "sg:classifiers":[
        {
            "category":"Building & Trades",
            "subcategory":"Construction",
            "type":"Services"
        }
    ],
    "sg:phone":"+1 424 227 9512",
    "sg:postcode":"90045",
    "sg:province":"CA",
    "sg:tags":[
        "contractor"
    ],
    "wof:name":"White Oak",
    "wof:placetype":"venue"
},
  "geometry": {"coordinates":[-118.38429600000001,33.970438],"type":"Point"}
}