{
  "type": "Feature",
  "properties": {
    "iso:country":"US",
    "sg:address":"2857 Hamner Ave",
    "sg:city":"Norco",
    "sg:classifiers":[
        {
            "category":"Recreation",
            "type":"Entertainment"
        }
    ],
    "sg:phone":"+1 951 898 0332",
    "sg:postcode":"92860",
    "sg:province":"CA",
    "sg:tags":[
        "martial",
        "arts",
        "instruction"
    ],
    "wof:name":"United Submission Academy",
    "wof:placetype":"venue"
},
  "geometry": {"coordinates":[-117.55891,33.923296],"type":"Point"}
}