{
  "type": "Feature",
  "properties": {
    "addr:full":"4409 E Los Coyotes Diagonal Long Beach CA 90815",
    "addr:housenumber":"4409",
    "addr:postcode":"90815",
    "addr:street":"E Los Coyotes Diagonal",
    "iso:country":"US",
    "sg:address":"4409 E Los Coyotes Diagonal",
    "sg:city":"Long Beach",
    "sg:classifiers":[
        {
            "category":"Health Services",
            "subcategory":"Optometrist",
            "type":"Services"
        }
    ],
    "sg:phone":"+1 562 630 8630",
    "sg:postcode":"90815",
    "sg:province":"CA",
    "wof:name":"Tomlin Luelinda OD",
    "wof:placetype":"venue"
},
  "geometry": {"coordinates":[-118.141998,33.790501],"type":"Point"}
}