{
  "type": "Feature",
  "properties": {
    "addr:full":"7326 Stockton Blvd Sacramento CA 95823",
    "addr:housenumber":"7326",
    "addr:postcode":"95823",
    "addr:street":"Stockton Blvd",
    "iso:country":"US",
    "sg:address":"7326 Stockton Blvd",
    "sg:city":"Sacramento",
    "sg:classifiers":[
        {
            "category":"Real Estate",
            "subcategory":"Real Estate Operator",
            "type":"Services"
        }
    ],
    "sg:phone":"+1 916 424 3977",
    "sg:postcode":"95823",
    "sg:province":"CA",
    "sg:tags":[
        "apartment"
    ],
    "wof:name":"Briarwood Apartments",
    "wof:placetype":"venue"
},
  "geometry": {"coordinates":[-121.42737099999999,38.492381],"type":"Point"}
}