{
  "type": "Feature",
  "properties": {
    "addr:full":"5614 Bay St Ste 220 Emeryville CA 94608",
    "addr:housenumber":"5614",
    "addr:postcode":"94608",
    "addr:street":"Bay St Ste 220",
    "iso:country":"US",
    "sg:address":"5614 Bay St Ste 220",
    "sg:city":"Emeryville",
    "sg:classifiers":[
        {
            "category":"Cinema",
            "subcategory":"Movie Theater",
            "type":"Entertainment"
        }
    ],
    "sg:phone":"+1 888 262 4386",
    "sg:postcode":"94608",
    "sg:province":"CA",
    "sg:website":"www.movietickets.com/house_detai...",
    "wof:name":"AMC Bay Street 16",
    "wof:placetype":"venue"
},
  "geometry": {"coordinates":[-122.292416,37.833615],"type":"Point"}
}