{
  "type": "Feature",
  "properties": {
    "addr:full":"8712 S Main St San Joaquin CA 93660",
    "addr:housenumber":"8712",
    "addr:postcode":"93660",
    "addr:street":"S Main St",
    "iso:country":"US",
    "sg:address":"8712 S Main St",
    "sg:city":"San Joaquin",
    "sg:classifiers":[
        {
            "category":"Food & Beverages",
            "subcategory":"Groceries & Convenience Stores",
            "type":"Retail Goods"
        }
    ],
    "sg:phone":"+1 559 693 4496",
    "sg:postcode":"93660",
    "sg:province":"CA",
    "sg:tags":[
        "grocer"
    ],
    "wof:name":"Food Land San Joaquin",
    "wof:placetype":"venue"
},
  "geometry": {"coordinates":[-120.186031,36.607813],"type":"Point"}
}