{
  "type": "Feature",
  "properties": {
    "addr:full":"1244 Hearst Ave Berkeley CA 94702",
    "addr:housenumber":"1244",
    "addr:postcode":"94702",
    "addr:street":"Hearst Ave",
    "iso:country":"US",
    "sg:address":"1244 Hearst Ave",
    "sg:city":"Berkeley",
    "sg:classifiers":[
        {
            "category":"Professional",
            "subcategory":"Computer Services",
            "type":"Services"
        }
    ],
    "sg:phone":"+1 510 526 4621",
    "sg:postcode":"94702",
    "sg:province":"CA",
    "sg:tags":[
        "software"
    ],
    "wof:name":"Imaja Software",
    "wof:placetype":"venue"
},
  "geometry": {"coordinates":[-122.28855,37.871061],"type":"Point"}
}