{
  "type": "Feature",
  "properties": {
    "iso:country":"US",
    "sg:address":"21818 Kilburn Rd",
    "sg:city":"Crows Landing",
    "sg:classifiers":[
        {
            "category":"Farming",
            "subcategory":"Crops",
            "type":"Manufacturing & Wholesale Goods"
        }
    ],
    "sg:phone":"+1 209 837 4369",
    "sg:postcode":"95313",
    "sg:province":"CA",
    "sg:tags":[
        "grove",
        "nut",
        "tree"
    ],
    "wof:name":"Mk Crow & Sons",
    "wof:placetype":"venue"
},
  "geometry": {"coordinates":[-121.03665700000001,37.402425],"type":"Point"}
}