{
  "type": "Feature",
  "properties": {
    "addr:full":"2031 Mission Street San Francisco CA 94110",
    "addr:housenumber":"2031",
    "addr:postcode":"94110",
    "addr:street":"Mission Street",
    "iso:country":"US",
    "sg:address":"2031 Mission Street",
    "sg:city":"San Francisco",
    "sg:classifiers":[
        {
            "category":"Professional",
            "subcategory":"Accounting & Tax Preparation",
            "type":"Services"
        }
    ],
    "sg:phone":"+1 415 626 9012",
    "sg:postcode":"94110",
    "sg:province":"CA",
    "sg:tags":[
        "accountant"
    ],
    "wof:name":"Carlos M Loucel Accounting & Tax Preparation",
    "wof:placetype":"venue"
},
  "geometry": {"coordinates":[-122.418999,37.7645],"type":"Point"}
}