{
  "type": "Feature",
  "properties": {
    "iso:country":"US",
    "sg:address":"2ndFloor,512 2nd Street",
    "sg:city":"San Francisco",
    "sg:classifiers":[
        {
            "category":"Professional",
            "type":"Services"
        }
    ],
    "sg:phone":"+1 415 713 7113",
    "sg:postcode":"94107",
    "sg:province":"CA",
    "wof:name":"VirtuOz, Inc.",
    "wof:placetype":"venue"
},
  "geometry": {"coordinates":[-122.39358,37.782714],"type":"Point"}
}