{
  "type": "Feature",
  "properties": {
    "addr:full":"3756 Santa Rosalia Dr Los Angeles CA 90008",
    "addr:housenumber":"3756",
    "addr:postcode":"90008",
    "addr:street":"Santa Rosalia Dr",
    "iso:country":"US",
    "sg:address":"3756 Santa Rosalia Dr",
    "sg:city":"Los Angeles",
    "sg:classifiers":[
        {
            "category":"Health Services",
            "subcategory":"Dentist",
            "type":"Services"
        }
    ],
    "sg:phone":"+1 323 299 2994",
    "sg:postcode":"90008",
    "sg:province":"CA",
    "wof:name":"Lee Emily DDS Family Dentistry",
    "wof:placetype":"venue"
},
  "geometry": {"coordinates":[-118.33899700000001,34.008499],"type":"Point"}
}