{
  "type": "Feature",
  "properties": {
    "addr:full":"730 Carolina St Vallejo CA 94590",
    "addr:housenumber":"730",
    "addr:postcode":"94590",
    "addr:street":"Carolina St",
    "iso:country":"US",
    "sg:address":"730 Carolina St",
    "sg:city":"Vallejo",
    "sg:classifiers":[
        {
            "category":"Manufacturing",
            "subcategory":"Buildings",
            "type":"Manufacturing & Wholesale Goods"
        },
        {
            "category":"Retail",
            "subcategory":"Repair Shop",
            "type":"Services"
        },
        {
            "category":"Building & Trades",
            "subcategory":"Construction",
            "type":"Services"
        }
    ],
    "sg:phone":"+1 707 554 1413",
    "sg:postcode":"94590",
    "sg:province":"CA",
    "sg:tags":[
        "builder",
        "handyman",
        "contractor",
        "fix-it",
        "maintenance",
        "home"
    ],
    "wof:name":"Smitty's Handyman Mobile Service",
    "wof:placetype":"venue"
},
  "geometry": {"coordinates":[-122.25271100000001,38.104025],"type":"Point"}
}