{
  "type": "Feature",
  "properties": {
    "addr:full":"2537 Winchester Blvd Campbell CA 95008",
    "addr:housenumber":"2537",
    "addr:postcode":"95008",
    "addr:street":"Winchester Blvd",
    "iso:country":"US",
    "sg:address":"2537 Winchester Blvd",
    "sg:city":"Campbell",
    "sg:classifiers":[
        {
            "category":"Retail",
            "subcategory":"Auto Repair",
            "type":"Services"
        }
    ],
    "sg:phone":"+1 408 489 0657",
    "sg:postcode":"95008",
    "sg:province":"CA",
    "wof:name":"Jay's Auto Repair",
    "wof:placetype":"venue"
},
  "geometry": {"coordinates":[-121.950098,37.277194],"type":"Point"}
}