{
  "type": "Feature",
  "properties": {
    "iso:country":"US",
    "sg:address":"1411 Secret Ravine Pkwy # 100",
    "sg:city":"Roseville",
    "sg:classifiers":[
        {
            "category":"Health Services",
            "subcategory":"Doctor",
            "type":"Services"
        }
    ],
    "sg:phone":"+1 916 622 4479",
    "sg:postcode":"95661",
    "sg:province":"CA",
    "sg:tags":[
        "physician",
        "pediatrics-orthopedic",
        "surgeons",
        "orthopedics",
        "surgery",
        "surgeon"
    ],
    "wof:name":"Hilton Kevin R Md Orthopedic Surgeon",
    "wof:placetype":"venue"
},
  "geometry": {"coordinates":[-121.244159,38.764136],"type":"Point"}
}