{
  "type": "Feature",
  "properties": {
    "addr:full":"13101 Hesby St Sherman Oaks CA 91423",
    "addr:housenumber":"13101",
    "addr:postcode":"91423",
    "addr:street":"Hesby St",
    "iso:country":"US",
    "sg:address":"13101 Hesby St",
    "sg:city":"Sherman Oaks",
    "sg:classifiers":[
        {
            "category":"Professional",
            "type":"Services"
        }
    ],
    "sg:phone":"+1 310 306 5599",
    "sg:postcode":"91423",
    "sg:province":"CA",
    "wof:name":"Challenge Detail",
    "wof:placetype":"venue"
},
  "geometry": {"coordinates":[-118.422505,34.162147],"type":"Point"}
}