{
  "type": "Feature",
  "properties": {
    "iso:country":"US",
    "sg:address":"2115 Selby Ave",
    "sg:city":"Los Angeles",
    "sg:classifiers":[
        {
            "category":"Professional",
            "subcategory":"Lawyer & Legal Services",
            "type":"Services"
        }
    ],
    "sg:phone":"+1 310 441 2226",
    "sg:postcode":"90025",
    "sg:province":"CA",
    "wof:name":"Lauer Bernard Attorney At Law",
    "wof:placetype":"venue"
},
  "geometry": {"coordinates":[-118.43,34.046501],"type":"Point"}
}