{
  "type": "Feature",
  "properties": {
    "iso:country":"US",
    "sg:address":"2260 Oak Grove Rd",
    "sg:city":"Walnut Creek",
    "sg:classifiers":[
        {
            "category":"Education",
            "subcategory":"Dance Studio",
            "type":"Public Place"
        }
    ],
    "sg:phone":"+1 925 938 3390",
    "sg:postcode":"94598",
    "sg:province":"CA",
    "sg:tags":[
        "instruction",
        "dancing"
    ],
    "wof:name":"Solad Dance Ctr",
    "wof:placetype":"venue"
},
  "geometry": {"coordinates":[-122.016369,37.92947],"type":"Point"}
}