{
  "type": "Feature",
  "properties": {
    "iso:country":"US",
    "sg:address":"6900 Danyeur Rd",
    "sg:city":"Redding",
    "sg:classifiers":[
        {
            "category":"Wholesale",
            "subcategory":"Machinery & Supplies",
            "type":"Manufacturing & Wholesale Goods"
        }
    ],
    "sg:phone":"+1 530 244 3868",
    "sg:postcode":"96001",
    "sg:province":"CA",
    "sg:tags":[
        "equipment",
        "laundry"
    ],
    "wof:name":"Bidoco Laundry Sales & Svc",
    "wof:placetype":"venue"
},
  "geometry": {"coordinates":[-122.377718,40.513064],"type":"Point"}
}