{
  "type": "Feature",
  "properties": {
    "addr:full":"2520 Artesia Blvd Redondo Beach CA 90278",
    "addr:housenumber":"2520",
    "addr:postcode":"90278",
    "addr:street":"Artesia Blvd",
    "iso:country":"US",
    "sg:address":"2520 Artesia Blvd",
    "sg:city":"Redondo Beach",
    "sg:classifiers":[
        {
            "category":"Organizations",
            "subcategory":"Religious Organization",
            "type":"Services"
        }
    ],
    "sg:phone":"+1 310 318 6054",
    "sg:postcode":"90278",
    "sg:province":"CA",
    "sg:website":"www.johrei-fellowship.com",
    "wof:name":"Johrei Fellowship",
    "wof:placetype":"venue"
},
  "geometry": {"coordinates":[-118.36601,33.872662],"type":"Point"}
}