{
  "type": "Feature",
  "properties": {
    "addr:full":"110 Newport Center Dr Ste 200 Newport Beach CA 92660",
    "addr:housenumber":"110",
    "addr:postcode":"92660",
    "addr:street":"Newport Center Dr Ste 200",
    "iso:country":"US",
    "sg:address":"110 Newport Center Dr Ste 200",
    "sg:city":"Newport Beach",
    "sg:classifiers":[
        {
            "category":"Shopping",
            "subcategory":"Bicycles & Sporting Goods",
            "type":"Retail Goods"
        }
    ],
    "sg:phone":"+1 949 719 1143",
    "sg:postcode":"92660",
    "sg:province":"CA",
    "wof:name":"Trade Globe Sports",
    "wof:placetype":"venue"
},
  "geometry": {"coordinates":[-117.87681000000001,33.612704],"type":"Point"}
}