{
  "type": "Feature",
  "properties": {
    "addr:full":"22705 White Ave Strathmore CA 93267",
    "addr:housenumber":"22705",
    "addr:postcode":"93267",
    "addr:street":"White Ave",
    "iso:country":"US",
    "sg:address":"22705 White Ave",
    "sg:city":"Strathmore",
    "sg:classifiers":[
        {
            "category":"Building & Trades",
            "subcategory":"Construction",
            "type":"Services"
        }
    ],
    "sg:phone":"+1 559 239 5567",
    "sg:postcode":"93267",
    "sg:province":"CA",
    "sg:tags":[
        "altering",
        "remodeling",
        "contractor"
    ],
    "wof:name":"Ron Hepner Plumbing And Home Repair",
    "wof:placetype":"venue"
},
  "geometry": {"coordinates":[-119.065489,36.14671],"type":"Point"}
}