{
  "type": "Feature",
  "properties": {
    "iso:country":"US",
    "sg:address":"36827 33rd St E",
    "sg:city":"Palmdale",
    "sg:classifiers":[
        {
            "category":"Building & Trades",
            "subcategory":"Cleaning & Sanitation",
            "type":"Services"
        }
    ],
    "sg:phone":"+1 661 263 6358",
    "sg:postcode":"93550",
    "sg:province":"CA",
    "sg:tags":[
        "fireplace",
        "chimney"
    ],
    "wof:name":"Chimney Sweep",
    "wof:placetype":"venue"
},
  "geometry": {"coordinates":[-118.07025400000001,34.55077],"type":"Point"}
}