{
  "type": "Feature",
  "properties": {
    "iso:country":"US",
    "sg:address":"7340 Alondra Blvd",
    "sg:city":"Paramount",
    "sg:classifiers":[
        {
            "category":"Wholesale",
            "subcategory":"Apparel",
            "type":"Manufacturing & Wholesale Goods"
        }
    ],
    "sg:phone":"+1 562 602 0400",
    "sg:postcode":"90723",
    "sg:province":"CA",
    "sg:tags":[
        "clothing"
    ],
    "wof:name":"Ghacham Inc",
    "wof:placetype":"venue"
},
  "geometry": {"coordinates":[-118.170428,33.889012],"type":"Point"}
}