{
  "type": "Feature",
  "properties": {
    "iso:country":"US",
    "sg:address":"3805 University Ave",
    "sg:city":"San Diego",
    "sg:classifiers":[
        {
            "category":"Food & Beverages",
            "subcategory":"Groceries & Convenience Stores",
            "type":"Retail Goods"
        }
    ],
    "sg:phone":"+1 619 283 2471",
    "sg:postcode":"92105",
    "sg:province":"CA",
    "sg:tags":[
        "grocer"
    ],
    "wof:name":"38th Street Market",
    "wof:placetype":"venue"
},
  "geometry": {"coordinates":[-117.111294,32.749626],"type":"Point"}
}