{
  "type": "Feature",
  "properties": {
    "iso:country":"US",
    "sg:address":"413 Tate St",
    "sg:city":"Bakersfield",
    "sg:classifiers":[
        {
            "category":"Building & Trades",
            "subcategory":"Construction",
            "type":"Services"
        }
    ],
    "sg:phone":"+1 661 204 1933",
    "sg:postcode":"93306",
    "sg:province":"CA",
    "sg:tags":[
        "wallcoverings-installation",
        "wallpaper",
        "painting",
        "contractor"
    ],
    "wof:name":"Brians Painting",
    "wof:placetype":"venue"
},
  "geometry": {"coordinates":[-118.947509,35.368714],"type":"Point"}
}