{
  "type": "Feature",
  "properties": {
    "addr:full":"323 N Prairie Ave Inglewood CA 90301",
    "addr:housenumber":"323",
    "addr:postcode":"90301",
    "addr:street":"N Prairie Ave",
    "iso:country":"US",
    "sg:address":"323 N Prairie Ave",
    "sg:city":"Inglewood",
    "sg:classifiers":[
        {
            "category":"Health Services",
            "subcategory":"Doctor",
            "type":"Services"
        }
    ],
    "sg:phone":"+1 310 419 8250",
    "sg:postcode":"90301",
    "sg:province":"CA",
    "wof:name":"Wound Care Center the",
    "wof:placetype":"venue"
},
  "geometry": {"coordinates":[-118.344002,33.966999],"type":"Point"}
}