{
  "type": "Feature",
  "properties": {
    "addr:full":"42536 Fern Cir Fremont CA 94538",
    "addr:housenumber":"42536",
    "addr:postcode":"94538",
    "addr:street":"Fern Cir",
    "iso:country":"US",
    "sg:address":"42536 Fern Cir",
    "sg:city":"Fremont",
    "sg:classifiers":[
        {
            "category":"Wholesale",
            "subcategory":"Chemicals & Plastics",
            "type":"Manufacturing & Wholesale Goods"
        }
    ],
    "sg:phone":"+1 510 657 1774",
    "sg:postcode":"94538",
    "sg:province":"CA",
    "wof:name":"Silicstar Industries Inc",
    "wof:placetype":"venue"
},
  "geometry": {"coordinates":[-121.96347799999999,37.52017],"type":"Point"}
}