{
  "type": "Feature",
  "properties": {
    "addr:full":"572 Quail Run Cir Tracy CA 95377",
    "addr:housenumber":"572",
    "addr:postcode":"95377",
    "addr:street":"Quail Run Cir",
    "iso:country":"US",
    "sg:address":"572 Quail Run Cir",
    "sg:city":"Tracy",
    "sg:classifiers":[
        {
            "category":"Social Services",
            "subcategory":"Child Care",
            "type":"Services"
        }
    ],
    "sg:phone":"+1 209 814 8806",
    "sg:postcode":"95377",
    "sg:province":"CA",
    "sg:tags":[
        "nursery",
        "day"
    ],
    "wof:name":"Love Bugs Child Care",
    "wof:placetype":"venue"
},
  "geometry": {"coordinates":[-121.420653,37.707868],"type":"Point"}
}