{
  "type": "Feature",
  "properties": {
    "iso:country":"US",
    "sg:address":"21432 High Country Dr",
    "sg:city":"Trabuco Canyon",
    "sg:classifiers":[
        {
            "category":"Professional",
            "type":"Services"
        }
    ],
    "sg:phone":"+1 949 713 6666",
    "sg:postcode":"92679",
    "sg:province":"CA",
    "wof:name":"Kittyglitter",
    "wof:placetype":"venue"
},
  "geometry": {"coordinates":[-117.56900899999999,33.650211],"type":"Point"}
}