{
  "type": "Feature",
  "properties": {
    "iso:country":"US",
    "sg:address":"1340 Meridian Ave",
    "sg:city":"San Jose",
    "sg:classifiers":[
        {
            "category":"Health Services",
            "subcategory":"Clinic",
            "type":"Services"
        }
    ],
    "sg:phone":"+1 408 448 4798",
    "sg:postcode":"95125",
    "sg:province":"CA",
    "sg:tags":[
        "cannabis"
    ],
    "sg:website":"www.medileaf.net",
    "wof:name":"MediLeaf",
    "wof:placetype":"venue"
},
  "geometry": {"coordinates":[-121.913161,37.301358],"type":"Point"}
}