{
  "type": "Feature",
  "properties": {
    "addr:full":"459 Willow Street San Jose CA 95125",
    "addr:housenumber":"459",
    "addr:postcode":"95125",
    "addr:street":"Willow Street",
    "iso:country":"US",
    "sg:address":"459 Willow Street",
    "sg:city":"San Jose",
    "sg:classifiers":[
        {
            "category":"Real Estate",
            "subcategory":"Real Estate Operator",
            "type":"Services"
        }
    ],
    "sg:phone":"+1 408 279 2103",
    "sg:postcode":"95125",
    "sg:province":"CA",
    "sg:tags":[
        "apartment"
    ],
    "sg:website":"www.willow-manor.com",
    "wof:name":"Willow Manor",
    "wof:placetype":"venue"
},
  "geometry": {"coordinates":[-121.889653,37.314588],"type":"Point"}
}