{
  "type": "Feature",
  "properties": {
    "addr:full":"582 W Valley Blvd Colton CA 92324",
    "addr:housenumber":"582",
    "addr:postcode":"92324",
    "addr:street":"W Valley Blvd",
    "iso:country":"US",
    "sg:address":"582 W Valley Blvd",
    "sg:city":"Colton",
    "sg:classifiers":[
        {
            "category":"Professional",
            "subcategory":"Computer Services",
            "type":"Services"
        }
    ],
    "sg:phone":"+1 909 783 4200",
    "sg:postcode":"92324",
    "sg:province":"CA",
    "sg:tags":[
        "consultant",
        "designer"
    ],
    "wof:name":"Ye Olde Computer Shoppe",
    "wof:placetype":"venue"
},
  "geometry": {"coordinates":[-117.330842,34.067816],"type":"Point"}
}