{
  "type": "Feature",
  "properties": {
    "iso:country":"US",
    "sg:address":"881 E Hamilton Ave",
    "sg:city":"Campbell",
    "sg:classifiers":[
        {
            "category":"Sports & Exercise",
            "subcategory":"Bicycle Rental",
            "type":"Entertainment"
        },
        {
            "category":"Shopping",
            "subcategory":"Shoes",
            "type":"Retail Goods"
        }
    ],
    "sg:phone":"+1 408 879 0522",
    "sg:postcode":"95008",
    "sg:province":"CA",
    "sg:tags":[
        "wear",
        "store"
    ],
    "sg:website":"bdsweb.ballroom.com/bdsmall.htm",
    "wof:name":"Ballroom Dance Supply",
    "wof:placetype":"venue"
},
  "geometry": {"coordinates":[-121.93499799999999,37.294498],"type":"Point"}
}