{
  "type": "Feature",
  "properties": {
    "addr:full":"717 Bridge St Yuba City CA 95991",
    "addr:housenumber":"717",
    "addr:postcode":"95991",
    "addr:street":"Bridge St",
    "iso:country":"US",
    "sg:address":"717 Bridge St",
    "sg:city":"Yuba City",
    "sg:classifiers":[
        {
            "category":"Freight",
            "type":"Transportation"
        }
    ],
    "sg:phone":"+1 530 671 2811",
    "sg:postcode":"95991",
    "sg:province":"CA",
    "sg:tags":[
        "mover"
    ],
    "wof:name":"Atlas Van Lines",
    "wof:placetype":"venue"
},
  "geometry": {"coordinates":[-121.62039900000001,39.133655],"type":"Point"}
}