{
  "type": "Feature",
  "properties": {
    "iso:country":"US",
    "sg:address":"6121 Santa Monica Blvd Suite 201",
    "sg:city":"Los Angeles",
    "sg:classifiers":[
        {
            "category":"Arts & Performance",
            "subcategory":"Arts Center",
            "type":"Entertainment"
        }
    ],
    "sg:phone":"+1 323 464 7767",
    "sg:postcode":"90038",
    "sg:province":"CA",
    "sg:website":"www.mirrorfilms.tv",
    "wof:name":"Mirror Films",
    "wof:placetype":"venue"
},
  "geometry": {"coordinates":[-118.322948,34.091035],"type":"Point"}
}