{
  "type": "Feature",
  "properties": {
    "addr:full":"19815 S Lake Rd Taft CA 93268",
    "addr:housenumber":"19815",
    "addr:postcode":"93268",
    "addr:street":"S Lake Rd",
    "iso:country":"US",
    "sg:address":"19815 S Lake Rd",
    "sg:city":"Taft",
    "sg:classifiers":[
        {
            "category":"Manufacturing",
            "subcategory":"Chemicals & Compounds",
            "type":"Manufacturing & Wholesale Goods"
        },
        {
            "category":"Shopping",
            "subcategory":"Pharmacy",
            "type":"Retail Goods"
        }
    ],
    "sg:phone":"+1 661 763 1528",
    "sg:postcode":"93268",
    "sg:province":"CA",
    "sg:tags":[
        "medicines-patent",
        "manufacturer",
        "proprietary",
        "chemicals-wholesale"
    ],
    "wof:name":"Baker Petrolite Corporation",
    "wof:placetype":"venue"
},
  "geometry": {"coordinates":[-119.23943300000001,35.147133],"type":"Point"}
}