{
  "type": "Feature",
  "properties": {
    "addr:full":"11552 Monarch St Garden Grove CA 92841",
    "addr:housenumber":"11552",
    "addr:postcode":"92841",
    "addr:street":"Monarch St",
    "iso:country":"US",
    "sg:address":"11552 Monarch St",
    "sg:city":"Garden Grove",
    "sg:classifiers":[
        {
            "category":"Wholesale",
            "subcategory":"Hardware",
            "type":"Manufacturing & Wholesale Goods"
        }
    ],
    "sg:phone":"+1 714 893 1936",
    "sg:postcode":"92841",
    "sg:province":"CA",
    "sg:tags":[
        "plumbing",
        "fixture",
        "supply"
    ],
    "sg:website":"www.ferguson.com",
    "wof:name":"Ferguson Bath & Kitchen Gallery",
    "wof:placetype":"venue"
},
  "geometry": {"coordinates":[-118.00700399999999,33.793999],"type":"Point"}
}