{
  "type": "Feature",
  "properties": {
    "addr:full":"545 Athol Ave Oakland CA 94606",
    "addr:housenumber":"545",
    "addr:postcode":"94606",
    "addr:street":"Athol Ave",
    "iso:country":"US",
    "sg:address":"545 Athol Ave",
    "sg:city":"Oakland",
    "sg:classifiers":[
        {
            "category":"Wholesale",
            "subcategory":"Hardware",
            "type":"Manufacturing & Wholesale Goods"
        }
    ],
    "sg:phone":"+1 510 834 4206",
    "sg:postcode":"94606",
    "sg:province":"CA",
    "sg:tags":[
        "construction"
    ],
    "wof:name":"National Door Control",
    "wof:placetype":"venue"
},
  "geometry": {"coordinates":[-122.24557,37.803774],"type":"Point"}
}