{
  "type": "Feature",
  "properties": {
    "addr:full":"13005 Magnolia Blvd Sherman Oaks CA 91423",
    "addr:housenumber":"13005",
    "addr:postcode":"91423",
    "addr:street":"Magnolia Blvd",
    "iso:country":"US",
    "sg:address":"13005 Magnolia Blvd",
    "sg:city":"Sherman Oaks",
    "sg:classifiers":[
        {
            "category":"Shopping",
            "subcategory":"Antiques",
            "type":"Retail Goods"
        }
    ],
    "sg:phone":"+1 818 995 1082",
    "sg:postcode":"91423",
    "sg:province":"CA",
    "wof:name":"American Farm House Collections",
    "wof:placetype":"venue"
},
  "geometry": {"coordinates":[-118.416,34.164799],"type":"Point"}
}