{
  "type": "Feature",
  "properties": {
    "iso:country":"US",
    "sg:address":"16429 Sierra Hwy",
    "sg:city":"Canyon Country",
    "sg:classifiers":[
        {
            "category":"Retail",
            "subcategory":"Auto Repair",
            "type":"Services"
        }
    ],
    "sg:phone":"+1 661 251 5133",
    "sg:postcode":"91351",
    "sg:province":"CA",
    "sg:tags":[
        "wrecker"
    ],
    "wof:name":"Don Lalo Towing Co",
    "wof:placetype":"venue"
},
  "geometry": {"coordinates":[-118.42391000000001,34.449525],"type":"Point"}
}