{
  "type": "Feature",
  "properties": {
    "iso:country":"US",
    "sg:address":"36839 Bankside Dr",
    "sg:city":"Cathedral City",
    "sg:classifiers":[
        {
            "category":"Retail",
            "subcategory":"Auto Repair",
            "type":"Services"
        }
    ],
    "sg:phone":"+1 760 328 6906",
    "sg:postcode":"92234",
    "sg:province":"CA",
    "wof:name":"Sentinel Car Service",
    "wof:placetype":"venue"
},
  "geometry": {"coordinates":[-116.471001,33.7813],"type":"Point"}
}