{
  "type": "Feature",
  "properties": {
    "addr:full":"973 Calimesa Blvd Calimesa CA 92320",
    "addr:housenumber":"973",
    "addr:postcode":"92320",
    "addr:street":"Calimesa Blvd",
    "iso:country":"US",
    "sg:address":"973 Calimesa Blvd",
    "sg:city":"Calimesa",
    "sg:classifiers":[
        {
            "category":"Insurance",
            "subcategory":"Insurance Agent",
            "type":"Services"
        }
    ],
    "sg:phone":"+1 909 795 9755",
    "sg:postcode":"92320",
    "sg:province":"CA",
    "wof:name":"Robert Jablonski Insurance",
    "wof:placetype":"venue"
},
  "geometry": {"coordinates":[-117.060074,33.999441],"type":"Point"}
}