{
  "type": "Feature",
  "properties": {
    "addr:full":"1490 W Shaw Ave Fresno CA 93711",
    "addr:housenumber":"1490",
    "addr:postcode":"93711",
    "addr:street":"W Shaw Ave",
    "iso:country":"US",
    "sg:address":"1490 W Shaw Ave",
    "sg:city":"Fresno",
    "sg:classifiers":[
        {
            "category":"Real Estate",
            "subcategory":"Real Estate Agent",
            "type":"Services"
        }
    ],
    "sg:phone":"+1 559 229 0900",
    "sg:postcode":"93711",
    "sg:province":"CA",
    "sg:tags":[
        "management"
    ],
    "wof:name":"Universal Property Mgmt",
    "wof:placetype":"venue"
},
  "geometry": {"coordinates":[-119.819503,36.808408],"type":"Point"}
}