{
  "type": "Feature",
  "properties": {
    "iso:country":"US",
    "sg:address":"3030 Thorntree Dr",
    "sg:city":"Chico",
    "sg:classifiers":[
        {
            "category":"Manufacturing",
            "subcategory":"Toys & Sporting Goods",
            "type":"Manufacturing & Wholesale Goods"
        }
    ],
    "sg:phone":"+1 530 896 0801",
    "sg:postcode":"95973",
    "sg:province":"CA",
    "sg:tags":[
        "laser",
        "supply",
        "mfg",
        "kit",
        "cutting",
        "hobby",
        "model"
    ],
    "sg:website":"www.nesm.com",
    "wof:name":"Northeastern Scale Models Inc",
    "wof:placetype":"venue"
},
  "geometry": {"coordinates":[-121.83641900000001,39.783431],"type":"Point"}
}