{
  "type": "Feature",
  "properties": {
    "addr:full":"6477 Almaden Expy San Jose CA 95120",
    "addr:housenumber":"6477",
    "addr:postcode":"95120",
    "addr:street":"Almaden Expy",
    "iso:country":"US",
    "sg:address":"6477 Almaden Expy",
    "sg:city":"San Jose",
    "sg:classifiers":[
        {
            "category":"Professional",
            "subcategory":"Advertising",
            "type":"Services"
        }
    ],
    "sg:phone":"+1 408 323 9567",
    "sg:postcode":"95120",
    "sg:province":"CA",
    "sg:tags":[
        "counselor"
    ],
    "wof:name":"Apex Promotion",
    "wof:placetype":"venue"
},
  "geometry": {"coordinates":[-121.860029,37.219939],"type":"Point"}
}