{
  "type": "Feature",
  "properties": {
    "addr:full":"1025 44th Ave Oakland CA 94601",
    "addr:housenumber":"1025",
    "addr:postcode":"94601",
    "addr:street":"44Th Ave",
    "iso:country":"US",
    "sg:address":"1025 44th Ave",
    "sg:city":"Oakland",
    "sg:classifiers":[
        {
            "category":"Building & Trades",
            "subcategory":"Landscaping Services",
            "type":"Services"
        }
    ],
    "sg:phone":"+1 510 436 0635",
    "sg:postcode":"94601",
    "sg:province":"CA",
    "wof:name":"Tavares Tree Service",
    "wof:placetype":"venue"
},
  "geometry": {"coordinates":[-122.216206,37.770227],"type":"Point"}
}