{
  "type": "Feature",
  "properties": {
    "addr:full":"350 Union Street San Francisco CA 94133",
    "addr:housenumber":"350",
    "addr:postcode":"94133",
    "addr:street":"Union Street",
    "iso:country":"US",
    "sg:address":"350 Union Street",
    "sg:city":"San Francisco",
    "sg:classifiers":[
        {
            "category":"Real Estate",
            "subcategory":"Real Estate Services",
            "type":"Services"
        }
    ],
    "sg:phone":"+1 415 421 4333",
    "sg:postcode":"94133",
    "sg:province":"CA",
    "sg:tags":[
        "management",
        "property"
    ],
    "wof:name":"Trinity Management Services",
    "wof:placetype":"venue"
},
  "geometry": {"coordinates":[-122.404999,37.800999],"type":"Point"}
}