{
  "type": "Feature",
  "properties": {
    "iso:country":"US",
    "sg:address":"622 S Baranca Ave",
    "sg:city":"Covina",
    "sg:classifiers":[
        {
            "category":"Home & Garden",
            "subcategory":"Mobile Homes",
            "type":"Retail Goods"
        }
    ],
    "sg:phone":"+1 626 938 1344",
    "sg:postcode":"91723",
    "sg:province":"CA",
    "wof:name":"South Hills Mobile Home",
    "wof:placetype":"venue"
},
  "geometry": {"coordinates":[-117.881234,34.078322],"type":"Point"}
}