{
  "type": "Feature",
  "properties": {
    "addr:full":"622 S Baranca Ave Covina CA 91723",
    "addr:housenumber":"622",
    "addr:postcode":"91723",
    "addr:street":"S Baranca Ave",
    "iso:country":"US",
    "sg:address":"622 S Baranca Ave",
    "sg:city":"Covina",
    "sg:classifiers":[
        {
            "category":"Home & Garden",
            "subcategory":"Mobile Homes",
            "type":"Retail Goods"
        }
    ],
    "sg:phone":"+1 626 938 1344",
    "sg:postcode":"91723",
    "sg:province":"CA",
    "wof:name":"South Hills Mobile Home",
    "wof:placetype":"venue"
},
  "geometry": {"coordinates":[-117.88123400000001,34.078322],"type":"Point"}
}