{
  "type": "Feature",
  "properties": {
    "addr:full":"1799 N Waterman Ave San Bernardino CA 92404",
    "addr:housenumber":"1799",
    "addr:postcode":"92404",
    "addr:street":"N Waterman Ave",
    "iso:country":"US",
    "sg:address":"1799 N Waterman Ave",
    "sg:city":"San Bernardino",
    "sg:classifiers":[
        {
            "category":"Health Services",
            "subcategory":"Medical Lab",
            "type":"Services"
        }
    ],
    "sg:phone":"+1 909 886 5042",
    "sg:postcode":"92404",
    "sg:province":"CA",
    "sg:tags":[
        "laboratory"
    ],
    "wof:name":"Beamans Radiographic Labs",
    "wof:placetype":"venue"
},
  "geometry": {"coordinates":[-117.27878699999999,34.130092],"type":"Point"}
}