{
  "type": "Feature",
  "properties": {
    "iso:country":"US",
    "sg:address":"13246 Fiji Way",
    "sg:city":"Marina Del Rey",
    "sg:classifiers":[
        {
            "category":"Communications",
            "subcategory":"Newspaper",
            "type":"Services"
        }
    ],
    "sg:phone":"+1 310 410 1000",
    "sg:postcode":"90292",
    "sg:province":"CA",
    "sg:tags":[
        "magazine"
    ],
    "wof:name":"News Media Services Inc",
    "wof:placetype":"venue"
},
  "geometry": {"coordinates":[-118.434752,33.979541],"type":"Point"}
}