{
  "type": "Feature",
  "properties": {
    "addr:full":"15814 Winchester Blvd Los Gatos CA 95030",
    "addr:housenumber":"15814",
    "addr:postcode":"95030",
    "addr:street":"Winchester Blvd",
    "iso:country":"US",
    "sg:address":"15814 Winchester Blvd",
    "sg:city":"Los Gatos",
    "sg:classifiers":[
        {
            "category":"Professional",
            "subcategory":"Management & Consulting",
            "type":"Services"
        }
    ],
    "sg:phone":"+1 408 395 9541",
    "sg:postcode":"95030",
    "sg:province":"CA",
    "sg:tags":[
        "consultant",
        "business"
    ],
    "sg:website":"www.lauridsengroup.com",
    "wof:name":"Lauridsen Assoc",
    "wof:placetype":"venue"
},
  "geometry": {"coordinates":[-121.97692600000001,37.238534],"type":"Point"}
}