{
  "type": "Feature",
  "properties": {
    "addr:full":"1903 W San Marcos Blvd Vista CA 92083",
    "addr:housenumber":"1903",
    "addr:postcode":"92083",
    "addr:street":"W San Marcos Blvd",
    "iso:country":"US",
    "sg:address":"1903 W San Marcos Blvd",
    "sg:city":"Vista",
    "sg:classifiers":[
        {
            "category":"Arena",
            "subcategory":"Sports Club",
            "type":"Entertainment"
        }
    ],
    "sg:phone":"+1 760 598 9707",
    "sg:postcode":"92083",
    "sg:province":"CA",
    "sg:tags":[
        "martial art"
    ],
    "wof:name":"Manahaim Tae Kwon Do",
    "wof:placetype":"venue"
},
  "geometry": {"coordinates":[-117.24900100000001,33.201801],"type":"Point"}
}