{
  "type": "Feature",
  "properties": {
    "addr:full":"19681 State Hwy 88 Pine Grove CA 95665",
    "addr:housenumber":"19681",
    "addr:postcode":"95665",
    "addr:street":"State Hwy 88;Grove",
    "iso:country":"US",
    "sg:address":"19681 State Hwy 88",
    "sg:city":"Pine Grove",
    "sg:classifiers":[
        {
            "category":"Health Services",
            "subcategory":"Doctor",
            "type":"Services"
        }
    ],
    "sg:phone":"+1 209 296 4210",
    "sg:postcode":"95665",
    "sg:province":"CA",
    "sg:tags":[
        "physician",
        "surgeon"
    ],
    "wof:name":"Henry Fuller Family Practice",
    "wof:placetype":"venue"
},
  "geometry": {"coordinates":[-120.661945,38.413795],"type":"Point"}
}