{
  "type": "Feature",
  "properties": {
    "iso:country":"US",
    "sg:address":"3901 Q St",
    "sg:city":"Bakersfield",
    "sg:classifiers":[
        {
            "category":"Real Estate",
            "subcategory":"Real Estate Operator",
            "type":"Services"
        }
    ],
    "sg:phone":"+1 661 323 1131",
    "sg:postcode":"93301",
    "sg:province":"CA",
    "sg:tags":[
        "apartment"
    ],
    "wof:name":"Pacific Village Apartments",
    "wof:placetype":"venue"
},
  "geometry": {"coordinates":[-119.010508,35.395438],"type":"Point"}
}