{
  "type": "Feature",
  "properties": {
    "addr:full":"The Block at Orange 20 City Boulevard West Orange CA 92868",
    "addr:housenumber":"20",
    "addr:postcode":"92868",
    "addr:street":"City Boulevard",
    "iso:country":"US",
    "sg:address":"The Block at Orange 20 City Boulevard West",
    "sg:city":"Orange",
    "sg:classifiers":[
        {
            "category":"Shopping",
            "subcategory":"Clothing, Apparel, & Fashions",
            "type":"Retail Goods"
        }
    ],
    "sg:phone":"+1 714 634 4594",
    "sg:postcode":"92868",
    "sg:province":"CA",
    "sg:tags":[
        "men's",
        "clothing"
    ],
    "sg:website":"www.shopecko.com",
    "wof:name":"Ecko Unlimted Outlet",
    "wof:placetype":"venue"
},
  "geometry": {"coordinates":[-117.895278,33.781306],"type":"Point"}
}