{
  "type": "Feature",
  "properties": {
    "iso:country":"US",
    "sg:address":"1736 Lindo St",
    "sg:city":"Benicia",
    "sg:classifiers":[
        {
            "category":"Professional",
            "type":"Services"
        }
    ],
    "sg:phone":"+1 707 747 5901",
    "sg:postcode":"94510",
    "sg:province":"CA",
    "wof:name":"G & S Motorsports",
    "wof:placetype":"venue"
},
  "geometry": {"coordinates":[-122.14344699999999,38.052735],"type":"Point"}
}