{
  "type": "Feature",
  "properties": {
    "iso:country":"US",
    "sg:address":"6054 Chesebro Rd",
    "sg:city":"Agoura Hills",
    "sg:classifiers":[
        {
            "category":"Building & Trades",
            "subcategory":"Equipment Rental",
            "type":"Services"
        }
    ],
    "sg:phone":"+1 818 991 6655",
    "sg:postcode":"91301",
    "sg:province":"CA",
    "sg:tags":[
        "contractor"
    ],
    "wof:name":"Buzza Backhoe Svc",
    "wof:placetype":"venue"
},
  "geometry": {"coordinates":[-118.734395,34.15828],"type":"Point"}
}