{
  "type": "Feature",
  "properties": {
    "iso:country":"US",
    "sg:address":"10316 Slater Ave",
    "sg:city":"Fountain Valley",
    "sg:classifiers":[
        {
            "category":"Education",
            "subcategory":"Preschool",
            "type":"Public Place"
        },
        {
            "category":"Education",
            "subcategory":"School",
            "type":"Public Place"
        }
    ],
    "sg:phone":"+1 714 962 2799",
    "sg:postcode":"92708",
    "sg:province":"CA",
    "sg:tags":[
        "elementary"
    ],
    "sg:website":"www.slatermontessoriacademy.com",
    "wof:name":"Slater Montessori Academy",
    "wof:placetype":"venue"
},
  "geometry": {"coordinates":[-117.949269,33.708852],"type":"Point"}
}