{
  "type": "Feature",
  "properties": {
    "iso:country":"US",
    "sg:address":"25655 Springbrook Ave",
    "sg:city":"Santa Clarita",
    "sg:classifiers":[
        {
            "category":"Building & Trades",
            "subcategory":"Electrical",
            "type":"Services"
        }
    ],
    "sg:phone":"+1 661 259 1593",
    "sg:postcode":"91350",
    "sg:province":"CA",
    "sg:tags":[
        "electric",
        "contractor"
    ],
    "wof:name":"Western Electric",
    "wof:placetype":"venue"
},
  "geometry": {"coordinates":[-118.538347,34.407632],"type":"Point"}
}