{
  "type": "Feature",
  "properties": {
    "iso:country":"US",
    "sg:address":"2355 Broadway",
    "sg:city":"Oakland",
    "sg:classifiers":[
        {
            "category":"Food & Beverages",
            "subcategory":"Candy",
            "type":"Retail Goods"
        },
        {
            "category":"Bars & Pubs",
            "subcategory":"Champagne Bar",
            "type":"Food & Drink"
        },
        {
            "category":"Bars & Pubs",
            "subcategory":"Lounge",
            "type":"Food & Drink"
        }
    ],
    "sg:postcode":"94612",
    "sg:province":"CA",
    "sg:tags":[
        "dessert"
    ],
    "sg:website":"mimosachampagnelounge.com",
    "wof:name":"Mimosa Champagne Lounge",
    "wof:placetype":"venue"
},
  "geometry": {"coordinates":[-122.26573,37.813259],"type":"Point"}
}