{
  "type": "Feature",
  "properties": {
    "iso:country":"US",
    "sg:address":"2126 Cotner Ave",
    "sg:city":"Los Angeles",
    "sg:classifiers":[
        {
            "category":"Building & Trades",
            "subcategory":"Construction",
            "type":"Services"
        }
    ],
    "sg:phone":"+1 310 478 1511",
    "sg:postcode":"90025",
    "sg:province":"CA",
    "sg:tags":[
        "contractor"
    ],
    "wof:name":"H A Lewis Inc",
    "wof:placetype":"venue"
},
  "geometry": {"coordinates":[-118.439554,34.039733],"type":"Point"}
}