{
  "type": "Feature",
  "properties": {
    "iso:country":"US",
    "sg:address":"151 S Wineville Ave",
    "sg:city":"Ontario",
    "sg:classifiers":[
        {
            "category":"Building & Trades",
            "subcategory":"Electrical",
            "type":"Services"
        },
        {
            "category":"Professional",
            "type":"Services"
        }
    ],
    "sg:phone":"+1 909 974 0035",
    "sg:postcode":"91761",
    "sg:province":"CA",
    "sg:tags":[
        "electric",
        "contractor"
    ],
    "wof:name":"Creative Electric & Theater",
    "wof:placetype":"venue"
},
  "geometry": {"coordinates":[-117.541116,34.055721],"type":"Point"}
}