{
  "type": "Feature",
  "properties": {
    "addr:full":"311 River Rd Modesto CA 95351",
    "addr:housenumber":"311",
    "addr:postcode":"ca 95351",
    "addr:street":"River Rd",
    "iso:country":"US",
    "sg:address":"311 River Rd",
    "sg:city":"Modesto",
    "sg:classifiers":[
        {
            "category":"Home & Garden",
            "subcategory":"Building Materials",
            "type":"Retail Goods"
        }
    ],
    "sg:phone":"+1 209 492 0988",
    "sg:postcode":"95351",
    "sg:province":"CA",
    "sg:tags":[
        "door"
    ],
    "wof:name":"Door Tech Inc",
    "wof:placetype":"venue"
},
  "geometry": {"coordinates":[-120.98941000000001,37.626259],"type":"Point"}
}