{
  "type": "Feature",
  "properties": {
    "iso:country":"US",
    "sg:address":"6849 Federal Blvd",
    "sg:city":"Lemon Grove",
    "sg:classifiers":[
        {
            "category":"Insurance",
            "subcategory":"Insurance Agent",
            "type":"Services"
        }
    ],
    "sg:phone":"+1 619 582 2300",
    "sg:postcode":"91945",
    "sg:province":"CA",
    "wof:name":"Bud Watkins Insurance",
    "wof:placetype":"venue"
},
  "geometry": {"coordinates":[-117.049735,32.740937],"type":"Point"}
}