{
  "type": "Feature",
  "properties": {
    "addr:full":"3436 College Ave San Diego CA 92115",
    "addr:housenumber":"3436",
    "addr:postcode":"92115",
    "addr:street":"College Ave",
    "iso:country":"US",
    "sg:address":"3436 College Ave",
    "sg:city":"San Diego",
    "sg:classifiers":[
        {
            "category":"Coffee & Tea",
            "type":"Food & Drink"
        }
    ],
    "sg:menulink":"http://www.allmenus.com/ca/san-diego/108914-starbucks-coffee/menu/",
    "sg:phone":"+1 619 229 0738",
    "sg:postcode":"92115",
    "sg:province":"CA",
    "sg:tags":[
        "american"
    ],
    "wof:name":"Starbucks Coffee",
    "wof:placetype":"venue"
},
  "geometry": {"coordinates":[-117.052013,32.74313],"type":"Point"}
}