{
  "type": "Feature",
  "properties": {
    "iso:country":"US",
    "sg:address":"9351 E Belmont Ave",
    "sg:city":"Sanger",
    "sg:classifiers":[
        {
            "category":"Farming",
            "subcategory":"Farm",
            "type":"Manufacturing & Wholesale Goods"
        }
    ],
    "sg:phone":"+1 559 452 9901",
    "sg:postcode":"93657",
    "sg:province":"CA",
    "wof:name":"M & P Farms",
    "wof:placetype":"venue"
},
  "geometry": {"coordinates":[-119.613545,36.750115],"type":"Point"}
}