{
  "type": "Feature",
  "properties": {
    "iso:country":"US",
    "sg:address":"461 Redbud Ln",
    "sg:city":"Hayward",
    "sg:classifiers":[
        {
            "category":"Building & Trades",
            "subcategory":"Electrical",
            "type":"Services"
        }
    ],
    "sg:phone":"+1 650 464 8091",
    "sg:postcode":"94541",
    "sg:province":"CA",
    "sg:tags":[
        "electrician"
    ],
    "wof:name":"W L Electrical",
    "wof:placetype":"venue"
},
  "geometry": {"coordinates":[-122.10374299999999,37.662253],"type":"Point"}
}