{
  "type": "Feature",
  "properties": {
    "iso:country":"US",
    "sg:address":"428 S Fernwood St",
    "sg:city":"West Covina",
    "sg:classifiers":[
        {
            "category":"Professional",
            "type":"Services"
        }
    ],
    "sg:phone":"+1 626 339 5150",
    "sg:postcode":"91791",
    "sg:province":"CA",
    "wof:name":"Viracom",
    "wof:placetype":"venue"
},
  "geometry": {"coordinates":[-117.910741,34.066457],"type":"Point"}
}