{
  "type": "Feature",
  "properties": {
    "addr:full":"3300 South Lakewood CA 90712",
    "addr:housenumber":"3300",
    "addr:postcode":"90712",
    "addr:street":"South",
    "iso:country":"US",
    "sg:address":"3300 South",
    "sg:city":"Lakewood",
    "sg:classifiers":[
        {
            "category":"Health Services",
            "subcategory":"Doctor",
            "type":"Services"
        }
    ],
    "sg:phone":"+1 562 790 8454",
    "sg:postcode":"90712",
    "sg:province":"CA",
    "wof:name":"Hamer Edgar E MD",
    "wof:placetype":"venue"
},
  "geometry": {"coordinates":[-118.153615,33.859511],"type":"Point"}
}