{
  "type": "Feature",
  "properties": {
    "addr:full":"716 S Vail Ave Montebello CA 90640",
    "addr:housenumber":"716",
    "addr:postcode":"90640",
    "addr:street":"S Vail Ave",
    "iso:country":"US",
    "sg:address":"716 S Vail Ave",
    "sg:city":"Montebello",
    "sg:classifiers":[
        {
            "category":"Wholesale",
            "subcategory":"Home Furnishings",
            "type":"Manufacturing & Wholesale Goods"
        }
    ],
    "sg:phone":"+1 323 278 1115",
    "sg:postcode":"90640",
    "sg:province":"CA",
    "sg:tags":[
        "housewares"
    ],
    "wof:name":"Euro-Cuisine",
    "wof:placetype":"venue"
},
  "geometry": {"coordinates":[-118.123982,34.002933],"type":"Point"}
}