{
  "type": "Feature",
  "properties": {
    "iso:country":"US",
    "sg:address":"2222 M St",
    "sg:city":"Merced",
    "sg:classifiers":[
        {
            "category":"Government",
            "subcategory":"Office",
            "type":"Public Place"
        }
    ],
    "sg:phone":"+1 209 385 7690",
    "sg:postcode":"95340",
    "sg:province":"CA",
    "sg:tags":[
        "county",
        "general"
    ],
    "wof:name":"General Services Dept",
    "wof:placetype":"venue"
},
  "geometry": {"coordinates":[-120.481417,37.307712],"type":"Point"}
}