{
  "type": "Feature",
  "properties": {
    "iso:country":"US",
    "sg:address":"12821 Harbor Blvd",
    "sg:city":"Garden Grove",
    "sg:classifiers":[
        {
            "category":"Restaurant",
            "type":"Food & Drink"
        }
    ],
    "sg:phone":"+1 714 530 4606",
    "sg:postcode":"92840",
    "sg:province":"CA",
    "wof:name":"Mon Cheri",
    "wof:placetype":"venue"
},
  "geometry": {"coordinates":[-117.91525,33.777234],"type":"Point"}
}