{
  "type": "Feature",
  "properties": {
    "addr:full":"350 30th St suite 320 Oakland CA 94609",
    "addr:housenumber":"350",
    "addr:postcode":"94609",
    "addr:street":"30Th St Suite 320",
    "iso:country":"US",
    "sg:address":"350 30th St suite 320",
    "sg:city":"Oakland",
    "sg:classifiers":[
        {
            "category":"Health Services",
            "subcategory":"Doctor",
            "type":"Services"
        }
    ],
    "sg:phone":"+1 510 465 6700",
    "sg:postcode":"94609",
    "sg:province":"CA",
    "sg:tags":[
        "physician",
        "surgeon"
    ],
    "sg:website":"www.aimmg.com",
    "wof:name":"Young-Lee Katy MD",
    "wof:placetype":"venue"
},
  "geometry": {"coordinates":[-122.263651,37.818935],"type":"Point"}
}