{
  "type": "Feature",
  "properties": {
    "addr:full":"8330 Starr Rd Windsor CA 95492",
    "addr:housenumber":"8330",
    "addr:postcode":"95492",
    "addr:street":"Starr Rd",
    "iso:country":"US",
    "sg:address":"8330 Starr Rd",
    "sg:city":"Windsor",
    "sg:classifiers":[
        {
            "category":"Restaurant",
            "type":"Food & Drink"
        }
    ],
    "sg:phone":"+1 707 838 2348",
    "sg:postcode":"95492",
    "sg:province":"CA",
    "sg:tags":[
        "caterer"
    ],
    "wof:name":"Simply Service",
    "wof:placetype":"venue"
},
  "geometry": {"coordinates":[-122.825898,38.534266],"type":"Point"}
}