{
  "type": "Feature",
  "properties": {
    "iso:country":"US",
    "sg:address":"915 E Main St",
    "sg:city":"Barstow",
    "sg:classifiers":[
        {
            "category":"Insurance",
            "subcategory":"Insurance Agent",
            "type":"Services"
        }
    ],
    "sg:phone":"+1 760 256 2514",
    "sg:postcode":"92311",
    "sg:province":"CA",
    "wof:name":"State Farm Insurance",
    "wof:placetype":"venue"
},
  "geometry": {"coordinates":[-117.014003,34.898614],"type":"Point"}
}