{
  "type": "Feature",
  "properties": {
    "iso:country":"US",
    "sg:address":"1101 W 10th St",
    "sg:city":"Antioch",
    "sg:classifiers":[
        {
            "category":"Autos & Motor Vehicles",
            "subcategory":"Automobile Sales",
            "type":"Retail Goods"
        }
    ],
    "sg:phone":"+1 925 778 0341",
    "sg:postcode":"94509",
    "sg:province":"CA",
    "sg:tags":[
        "car",
        "dealer"
    ],
    "wof:name":"Auto One Sales",
    "wof:placetype":"venue"
},
  "geometry": {"coordinates":[-121.822051,38.011209],"type":"Point"}
}