{
  "type": "Feature",
  "properties": {
    "addr:full":"6694 Amador Plaza Rd Dublin CA 94568",
    "addr:housenumber":"6694",
    "addr:postcode":"94568",
    "addr:street":"Amador Plaza Rd",
    "iso:country":"US",
    "sg:address":"6694 Amador Plaza Rd",
    "sg:city":"Dublin",
    "sg:classifiers":[
        {
            "category":"Home & Garden",
            "subcategory":"Home Furnishings",
            "type":"Retail Goods"
        }
    ],
    "sg:phone":"+1 925 875 0745",
    "sg:postcode":"94568",
    "sg:province":"CA",
    "sg:tags":[
        "bathroom",
        "fixture",
        "accessory"
    ],
    "wof:name":"Douglah Designs",
    "wof:placetype":"venue"
},
  "geometry": {"coordinates":[-121.92639699999999,37.703601],"type":"Point"}
}