{
  "type": "Feature",
  "properties": {
    "addr:full":"3098 W Bullard Ave Fresno CA 93711",
    "addr:housenumber":"3098",
    "addr:postcode":"93711",
    "addr:street":"W Bullard Ave",
    "iso:country":"US",
    "sg:address":"3098 W Bullard Ave",
    "sg:city":"Fresno",
    "sg:classifiers":[
        {
            "category":"Retail",
            "subcategory":"Animal Services",
            "type":"Services"
        }
    ],
    "sg:phone":"+1 559 431 3937",
    "sg:postcode":"93711",
    "sg:province":"CA",
    "wof:name":"Academy Dog Training",
    "wof:placetype":"venue"
},
  "geometry": {"coordinates":[-119.844599,36.822723],"type":"Point"}
}