{
  "type": "Feature",
  "properties": {
    "iso:country":"US",
    "sg:address":"820 San Fernando Rd",
    "sg:city":"San Fernando",
    "sg:classifiers":[
        {
            "category":"Shopping",
            "subcategory":"Clothing, Apparel, & Fashions",
            "type":"Retail Goods"
        }
    ],
    "sg:phone":"+1 818 332 1639",
    "sg:postcode":"91340",
    "sg:province":"CA",
    "sg:tags":[
        "shop",
        "bridal"
    ],
    "wof:name":"Bridal Center",
    "wof:placetype":"venue"
},
  "geometry": {"coordinates":[-118.439243,34.280766],"type":"Point"}
}