{
  "type": "Feature",
  "properties": {
    "addr:full":"5641 Bay St Emeryville CA 94608",
    "addr:housenumber":"5641",
    "addr:postcode":"94608",
    "addr:street":"Bay St",
    "iso:country":"US",
    "sg:address":"5641 Bay St",
    "sg:city":"Emeryville",
    "sg:classifiers":[
        {
            "category":"Manufacturing",
            "subcategory":"Leather Goods",
            "type":"Manufacturing & Wholesale Goods"
        }
    ],
    "sg:phone":"+1 510 547 8001",
    "sg:postcode":"94608",
    "sg:province":"CA",
    "wof:name":"Coach Store",
    "wof:placetype":"venue"
},
  "geometry": {"coordinates":[-122.292,37.836601],"type":"Point"}
}