{
  "type": "Feature",
  "properties": {
    "iso:country":"US",
    "sg:address":"539 Valencia Dr Unit C",
    "sg:city":"Fullerton",
    "sg:classifiers":[
        {
            "category":"Retail",
            "subcategory":"Auto Repair",
            "type":"Services"
        }
    ],
    "sg:phone":"+1 714 525 7744",
    "sg:postcode":"92832",
    "sg:province":"CA",
    "sg:tags":[
        "body",
        "shop"
    ],
    "wof:name":"Lennie's International Auto Creations",
    "wof:placetype":"venue"
},
  "geometry": {"coordinates":[-117.91458799999999,33.866336],"type":"Point"}
}