{
  "type": "Feature",
  "properties": {
    "addr:full":"PO Box 2754 Solana Beach CA 92075",
    "addr:housenumber":"po",
    "addr:postcode":"92075",
    "addr:street":"Box 2754",
    "iso:country":"US",
    "sg:address":"PO Box 2754",
    "sg:city":"Solana Beach",
    "sg:classifiers":[
        {
            "category":"Building & Trades",
            "subcategory":"Pest Control",
            "type":"Services"
        }
    ],
    "sg:phone":"+1 858 792 5231",
    "sg:postcode":"92075",
    "sg:province":"CA",
    "wof:name":"Holdsworth Pest Control",
    "wof:placetype":"venue"
},
  "geometry": {"coordinates":[-117.261002,32.9893],"type":"Point"}
}