{
  "type": "Feature",
  "properties": {
    "iso:country":"US",
    "sg:address":"79 Florence St",
    "sg:city":"Daly City",
    "sg:classifiers":[
        {
            "category":"Education",
            "subcategory":"Preschool",
            "type":"Public Place"
        },
        {
            "category":"Education",
            "subcategory":"School",
            "type":"Public Place"
        }
    ],
    "sg:phone":"+1 650 756 4737",
    "sg:postcode":"94014",
    "sg:province":"CA",
    "sg:tags":[
        "high",
        "middle",
        "elementary"
    ],
    "wof:name":"Hilldale School",
    "wof:placetype":"venue"
},
  "geometry": {"coordinates":[-122.458,37.697701],"type":"Point"}
}