{
  "type": "Feature",
  "properties": {
    "addr:full":"3609 Dawn Rd Rosamond CA 93560",
    "addr:housenumber":"3609",
    "addr:postcode":"93560",
    "addr:street":"Dawn Rd",
    "iso:country":"US",
    "sg:address":"3609 Dawn Rd",
    "sg:city":"Rosamond",
    "sg:classifiers":[
        {
            "category":"Wholesale",
            "subcategory":"Hardware",
            "type":"Manufacturing & Wholesale Goods"
        }
    ],
    "sg:phone":"+1 661 256 7530",
    "sg:postcode":"93560",
    "sg:province":"CA",
    "sg:tags":[
        "purifying",
        "cleaning",
        "air"
    ],
    "wof:name":"Enviro Pur",
    "wof:placetype":"venue"
},
  "geometry": {"coordinates":[-118.188615,34.907734],"type":"Point"}
}