{
  "type": "Feature",
  "properties": {
    "addr:full":"541 Ramona St Palo Alto CA 94301",
    "addr:housenumber":"541",
    "addr:postcode":"94301",
    "addr:street":"Ramona St",
    "iso:country":"US",
    "sg:address":"541 Ramona St",
    "sg:city":"Palo Alto",
    "sg:classifiers":[
        {
            "category":"Restaurant",
            "type":"Food & Drink"
        }
    ],
    "sg:menulink":"http://www.allmenus.com/ca/san-jose/19800-old-pro/menu/",
    "sg:phone":"+1 650 326 1446",
    "sg:postcode":"94301",
    "sg:province":"CA",
    "sg:tags":[
        "american"
    ],
    "wof:name":"Old Pro",
    "wof:placetype":"venue"
},
  "geometry": {"coordinates":[-122.161658,37.444949],"type":"Point"}
}