{
  "type": "Feature",
  "properties": {
    "addr:full":"1081 N Tustin Ave Ste 113 Anaheim CA 92807",
    "addr:housenumber":"1081",
    "addr:postcode":"92807",
    "addr:street":"N Tustin Ave Ste 113",
    "iso:country":"US",
    "sg:address":"1081 N Tustin Ave Ste 113",
    "sg:city":"Anaheim",
    "sg:classifiers":[
        {
            "category":"Health Services",
            "subcategory":"Optometrist",
            "type":"Services"
        }
    ],
    "sg:phone":"+1 714 632 1616",
    "sg:postcode":"92807",
    "sg:province":"CA",
    "wof:name":"Nguyen Kari OD",
    "wof:placetype":"venue"
},
  "geometry": {"coordinates":[-117.837997,33.853901],"type":"Point"}
}