{
  "type": "Feature",
  "properties": {
    "addr:full":"4150 17th St San Francisco CA 94114",
    "addr:housenumber":"4150",
    "addr:postcode":"94114",
    "addr:street":"17Th St",
    "iso:country":"US",
    "sg:address":"4150 17th St",
    "sg:city":"San Francisco",
    "sg:classifiers":[
        {
            "category":"Building & Trades",
            "subcategory":"Construction",
            "type":"Services"
        }
    ],
    "sg:phone":"+1 415 864 1059",
    "sg:postcode":"94114",
    "sg:province":"CA",
    "sg:tags":[
        "hanging",
        "contractor"
    ],
    "wof:name":"Savard Color",
    "wof:placetype":"venue"
},
  "geometry": {"coordinates":[-122.437984,37.762399],"type":"Point"}
}