{
  "type": "Feature",
  "properties": {
    "addr:full":"556 Las Posas Rd Camarillo CA 93010",
    "addr:housenumber":"556",
    "addr:postcode":"93010",
    "addr:street":"Las Posas Rd",
    "iso:country":"US",
    "sg:address":"556 Las Posas Rd",
    "sg:city":"Camarillo",
    "sg:classifiers":[
        {
            "category":"Personal",
            "subcategory":"Nail Salon",
            "type":"Services"
        }
    ],
    "sg:phone":"+1 805 987 0992",
    "sg:postcode":"93010",
    "sg:province":"CA",
    "wof:name":"Nail Perfection",
    "wof:placetype":"venue"
},
  "geometry": {"coordinates":[-119.06300400000001,34.230499],"type":"Point"}
}