{
  "type": "Feature",
  "properties": {
    "addr:full":"700 W Mission Ave Escondido CA 92025",
    "addr:housenumber":"700",
    "addr:postcode":"92025",
    "addr:street":"W Mission Ave",
    "iso:country":"US",
    "sg:address":"700 W Mission Ave",
    "sg:city":"Escondido",
    "sg:classifiers":[
        {
            "category":"Restaurant",
            "type":"Food & Drink"
        }
    ],
    "sg:phone":"+1 760 741 3910",
    "sg:postcode":"92025",
    "sg:province":"CA",
    "wof:name":"El Mexicano Taco Shop",
    "wof:placetype":"venue"
},
  "geometry": {"coordinates":[-117.095714,33.127228],"type":"Point"}
}