{
  "type": "Feature",
  "properties": {
    "addr:full":"16137 Sherman Way Van Nuys CA 91406",
    "addr:housenumber":"16137",
    "addr:postcode":"91406",
    "addr:street":"Sherman Way",
    "iso:country":"US",
    "sg:address":"16137 Sherman Way",
    "sg:city":"Van Nuys",
    "sg:classifiers":[
        {
            "category":"Health Services",
            "subcategory":"Chiropractor",
            "type":"Services"
        }
    ],
    "sg:phone":"+1 818 781 2225",
    "sg:postcode":"91406",
    "sg:province":"CA",
    "wof:name":"Grigorian Chiropractic Inc",
    "wof:placetype":"venue"
},
  "geometry": {"coordinates":[-118.48518,34.201125],"type":"Point"}
}