{
  "type": "Feature",
  "properties": {
    "addr:full":"865 Noyes Rd Arroyo Grande CA 93420",
    "addr:housenumber":"865",
    "addr:postcode":"93420",
    "addr:street":"Noyes Rd",
    "iso:country":"US",
    "sg:address":"865 Noyes Rd",
    "sg:city":"Arroyo Grande",
    "sg:classifiers":[
        {
            "category":"Building & Trades",
            "subcategory":"Construction",
            "type":"Services"
        }
    ],
    "sg:phone":"+1 805 489 7341",
    "sg:postcode":"93420",
    "sg:province":"CA",
    "sg:tags":[
        "concrete",
        "cutting",
        "breaking",
        "sawing"
    ],
    "wof:name":"Arroyo Breaking & Cutting",
    "wof:placetype":"venue"
},
  "geometry": {"coordinates":[-120.597711,35.143173],"type":"Point"}
}