{
  "type": "Feature",
  "properties": {
    "addr:full":"23252 S Olive Ave Ripon CA 95366",
    "addr:housenumber":"23252",
    "addr:postcode":"ca 95366",
    "addr:street":"S Olive Ave",
    "iso:country":"US",
    "sg:address":"23252 S Olive Ave",
    "sg:city":"Ripon",
    "sg:classifiers":[
        {
            "category":"Farming",
            "subcategory":"Farm",
            "type":"Manufacturing & Wholesale Goods"
        }
    ],
    "sg:phone":"+1 209 599 2957",
    "sg:postcode":"95366",
    "sg:province":"CA",
    "sg:tags":[
        "crop",
        "general"
    ],
    "wof:name":"Robert Weststeyn",
    "wof:placetype":"venue"
},
  "geometry": {"coordinates":[-121.155995,37.752314],"type":"Point"}
}