{
  "type": "Feature",
  "properties": {
    "addr:full":"8000 Andora Way Sacramento CA 95824",
    "addr:postcode":"8000;95824",
    "addr:street":"Andora Way",
    "iso:country":"US",
    "sg:address":"8000 Andora Way",
    "sg:city":"Sacramento",
    "sg:classifiers":[
        {
            "category":"Education",
            "subcategory":"Special Training",
            "type":"Public Place"
        }
    ],
    "sg:phone":"+1 916 879 5053",
    "sg:postcode":"95824",
    "sg:province":"CA",
    "sg:tags":[
        "educational"
    ],
    "wof:name":"Progressive Missionary Baptist Association Of Northern California",
    "wof:placetype":"venue"
},
  "geometry": {"coordinates":[-121.41118299999999,38.512545],"type":"Point"}
}