{
  "type": "Feature",
  "properties": {
    "iso:country":"US",
    "sg:address":"14140 Live Oak Ave",
    "sg:city":"Baldwin Park",
    "sg:classifiers":[
        {
            "category":"Wholesale",
            "subcategory":"Durable Goods & Equipment",
            "type":"Manufacturing & Wholesale Goods"
        }
    ],
    "sg:phone":"+1 626 939 0404",
    "sg:postcode":"91706",
    "sg:province":"CA",
    "sg:tags":[
        "importer"
    ],
    "wof:name":"Cho Kwang USA Inc",
    "wof:placetype":"venue"
},
  "geometry": {"coordinates":[-117.968004,34.106692],"type":"Point"}
}