{
  "type": "Feature",
  "properties": {
    "addr:full":"490 Post St Ste 404 San Francisco CA 94102",
    "addr:housenumber":"490",
    "addr:postcode":"94102",
    "addr:street":"Post St Ste 404",
    "iso:country":"US",
    "sg:address":"490 Post St Ste 404",
    "sg:city":"San Francisco",
    "sg:classifiers":[
        {
            "category":"Health Services",
            "subcategory":"Dentist",
            "type":"Services"
        }
    ],
    "sg:phone":"+1 415 362 1102",
    "sg:postcode":"94102",
    "sg:province":"CA",
    "sg:website":"www.drzabek.com",
    "wof:name":"Zabek Gregory DDS",
    "wof:placetype":"venue"
},
  "geometry": {"coordinates":[-122.409757,37.788407],"type":"Point"}
}