{
  "type": "Feature",
  "properties": {
    "addr:full":"17902 E Renwick Rd Azusa CA 91702",
    "addr:housenumber":"17902",
    "addr:postcode":"91702",
    "addr:street":"E Renwick Rd",
    "iso:country":"US",
    "sg:address":"17902 E Renwick Rd",
    "sg:city":"Azusa",
    "sg:classifiers":[
        {
            "category":"Building & Trades",
            "subcategory":"Construction",
            "type":"Services"
        }
    ],
    "sg:phone":"+1 626 969 3943",
    "sg:postcode":"91702",
    "sg:province":"CA",
    "sg:tags":[
        "general",
        "contractor"
    ],
    "wof:name":"E A Pacific",
    "wof:placetype":"venue"
},
  "geometry": {"coordinates":[-117.89928999999999,34.110961],"type":"Point"}
}