{
  "type": "Feature",
  "properties": {
    "iso:country":"US",
    "sg:address":"1461 G St",
    "sg:city":"Reedley",
    "sg:classifiers":[
        {
            "category":"Retail",
            "subcategory":"Auto Repair",
            "type":"Services"
        }
    ],
    "sg:phone":"+1 559 638 8500",
    "sg:postcode":"93654",
    "sg:province":"CA",
    "sg:tags":[
        "repairing",
        "automobile"
    ],
    "wof:name":"Joe's Automotive Repair",
    "wof:placetype":"venue"
},
  "geometry": {"coordinates":[-119.447266,36.592943],"type":"Point"}
}