{
  "type": "Feature",
  "properties": {
    "addr:full":"1128 Tanglewood Way San Mateo CA 94403",
    "addr:housenumber":"1128",
    "addr:postcode":"94403",
    "addr:street":"Tanglewood Way",
    "iso:country":"US",
    "sg:address":"1128 Tanglewood Way",
    "sg:city":"San Mateo",
    "sg:classifiers":[
        {
            "category":"Manufacturing",
            "subcategory":"Printing",
            "type":"Manufacturing & Wholesale Goods"
        }
    ],
    "sg:phone":"+1 650 349 6946",
    "sg:postcode":"94403",
    "sg:province":"CA",
    "sg:tags":[
        "publishing"
    ],
    "wof:name":"Der Bay",
    "wof:placetype":"venue"
},
  "geometry": {"coordinates":[-122.27854600000001,37.529326],"type":"Point"}
}