{
  "type": "Feature",
  "properties": {
    "iso:country":"US",
    "sg:address":"25935 Rolling Hills Rd",
    "sg:city":"Lomita",
    "sg:classifiers":[
        {
            "category":"Real Estate",
            "subcategory":"Real Estate Operator",
            "type":"Services"
        }
    ],
    "sg:phone":"+1 310 325 2634",
    "sg:postcode":"90717",
    "sg:province":"CA",
    "sg:tags":[
        "apartment"
    ],
    "wof:name":"Rolling Hills Apartments",
    "wof:placetype":"venue"
},
  "geometry": {"coordinates":[-118.317001,33.794201],"type":"Point"}
}