{
  "type": "Feature",
  "properties": {
    "addr:full":"24218 Hawthorne Blvd Torrance CA 90505",
    "addr:housenumber":"24218",
    "addr:postcode":"90505",
    "addr:street":"Hawthorne Blvd",
    "iso:country":"US",
    "sg:address":"24218 Hawthorne Blvd",
    "sg:city":"Torrance",
    "sg:classifiers":[
        {
            "category":"Personal",
            "subcategory":"Beauty Salon",
            "type":"Services"
        }
    ],
    "sg:phone":"+1 310 375 9933",
    "sg:postcode":"90505",
    "sg:province":"CA",
    "sg:tags":[
        "barber"
    ],
    "wof:name":"Holiday Hair Stylist",
    "wof:placetype":"venue"
},
  "geometry": {"coordinates":[-118.350998,33.8036],"type":"Point"}
}