{
  "type": "Feature",
  "properties": {
    "iso:country":"US",
    "sg:address":"28125 Bradley Rd",
    "sg:city":"Sun City",
    "sg:classifiers":[
        {
            "category":"Health Services",
            "subcategory":"Medical Lab",
            "type":"Services"
        }
    ],
    "sg:phone":"+1 951 672 0221",
    "sg:postcode":"92586",
    "sg:province":"CA",
    "sg:tags":[
        "testing"
    ],
    "wof:name":"Quest",
    "wof:placetype":"venue"
},
  "geometry": {"coordinates":[-117.190899,33.716211],"type":"Point"}
}