{
  "type": "Feature",
  "properties": {
    "iso:country":"US",
    "sg:address":"743 California Ave",
    "sg:city":"Simi Valley",
    "sg:classifiers":[
        {
            "category":"Retail",
            "subcategory":"Repair Shop",
            "type":"Services"
        }
    ],
    "sg:phone":"+1 805 584 9798",
    "sg:postcode":"93065",
    "sg:province":"CA",
    "sg:tags":[
        "hospital",
        "refinishing"
    ],
    "wof:name":"RLT Medical Gas Svc",
    "wof:placetype":"venue"
},
  "geometry": {"coordinates":[-118.782872,34.270786],"type":"Point"}
}