{
  "type": "Feature",
  "properties": {
    "addr:full":"5120 Ralston St Ventura CA 93003",
    "addr:housenumber":"5120",
    "addr:postcode":"93003",
    "addr:street":"Ralston St",
    "iso:country":"US",
    "sg:address":"5120 Ralston St",
    "sg:city":"Ventura",
    "sg:classifiers":[
        {
            "category":"Professional",
            "type":"Services"
        }
    ],
    "sg:phone":"+1 805 658 1702",
    "sg:postcode":"93003",
    "sg:province":"CA",
    "sg:tags":[
        "establishment"
    ],
    "wof:name":"Rocket Parts",
    "wof:placetype":"venue"
},
  "geometry": {"coordinates":[-119.222739,34.260394],"type":"Point"}
}