{
  "type": "Feature",
  "properties": {
    "addr:full":"16625 S Normandie Ave Gardena CA 90247",
    "addr:housenumber":"16625",
    "addr:postcode":"90247",
    "addr:street":"S Normandie Ave",
    "iso:country":"US",
    "sg:address":"16625 S Normandie Ave",
    "sg:city":"Gardena",
    "sg:classifiers":[
        {
            "category":"Shopping",
            "type":"Retail Goods"
        },
        {
            "category":"Retail",
            "subcategory":"Auto Repair",
            "type":"Services"
        }
    ],
    "sg:phone":"+1 310 679 5500",
    "sg:postcode":"90247",
    "sg:province":"CA",
    "sg:tags":[
        "glass",
        "window",
        "coating",
        "tinting"
    ],
    "wof:name":"Paradise Tinting",
    "wof:placetype":"venue"
},
  "geometry": {"coordinates":[-118.29990100000001,33.879655],"type":"Point"}
}