{
  "type": "Feature",
  "properties": {
    "iso:country":"US",
    "sg:address":"6230 E Marina View Dr",
    "sg:city":"Long Beach",
    "sg:classifiers":[
        {
            "category":"Real Estate",
            "subcategory":"Developer",
            "type":"Services"
        }
    ],
    "sg:phone":"+1 562 431 4132",
    "sg:postcode":"90803",
    "sg:province":"CA",
    "sg:tags":[
        "mobile",
        "home"
    ],
    "wof:name":"Belmont Shore Mobile Estates",
    "wof:placetype":"venue"
},
  "geometry": {"coordinates":[-118.113252,33.766795],"type":"Point"}
}