{
  "type": "Feature",
  "properties": {
    "addr:full":"1632 Seabright Ave Santa Cruz CA 95062",
    "addr:housenumber":"1632",
    "addr:postcode":"95062",
    "addr:street":"Seabright Ave",
    "iso:country":"US",
    "sg:address":"1632 Seabright Ave",
    "sg:city":"Santa Cruz",
    "sg:classifiers":[
        {
            "category":"Restaurant",
            "type":"Food & Drink"
        }
    ],
    "sg:phone":"+1 831 427 2559",
    "sg:postcode":"95062",
    "sg:province":"CA",
    "sg:tags":[
        "thai"
    ],
    "wof:name":"Real Thai Kitchen",
    "wof:placetype":"venue"
},
  "geometry": {"coordinates":[-122.010002,36.979599],"type":"Point"}
}