{
  "type": "Feature",
  "properties": {
    "addr:full":"190 Teloma Dr Ventura CA 93003",
    "addr:housenumber":"190",
    "addr:postcode":"93003",
    "addr:street":"Teloma Dr",
    "iso:country":"US",
    "sg:address":"190 Teloma Dr",
    "sg:city":"Ventura",
    "sg:classifiers":[
        {
            "category":"Health Services",
            "subcategory":"Health Practitioner",
            "type":"Services"
        }
    ],
    "sg:phone":"+1 805 650 0655",
    "sg:postcode":"93003",
    "sg:province":"CA",
    "sg:tags":[
        "psychologist"
    ],
    "wof:name":"Christina Griffin PHD",
    "wof:placetype":"venue"
},
  "geometry": {"coordinates":[-119.223923,34.276794],"type":"Point"}
}