{
  "type": "Feature",
  "properties": {
    "addr:full":"8545 Unsworth Avenue Sacramento CA 95828",
    "addr:housenumber":"8545",
    "addr:postcode":"95828",
    "addr:street":"Unsworth Avenue",
    "iso:country":"US",
    "sg:address":"8545 Unsworth Avenue",
    "sg:city":"Sacramento",
    "sg:classifiers":[
        {
            "category":"Government",
            "subcategory":"Office",
            "type":"Public Place"
        }
    ],
    "sg:phone":"+1 916 383 4144",
    "sg:postcode":"95828",
    "sg:province":"CA",
    "sg:tags":[
        "smog",
        "check"
    ],
    "wof:name":"Kb Smog Center",
    "wof:placetype":"venue"
},
  "geometry": {"coordinates":[-121.390613,38.521624],"type":"Point"}
}