{
  "type": "Feature",
  "properties": {
    "iso:country":"US",
    "sg:address":"9262 Magnolia Ave",
    "sg:city":"Riverside",
    "sg:classifiers":[
        {
            "category":"Freight",
            "type":"Transportation"
        }
    ],
    "sg:phone":"+1 951 324 8030",
    "sg:postcode":"92503",
    "sg:province":"CA",
    "sg:tags":[
        "delivery"
    ],
    "wof:name":"Dedicated Express",
    "wof:placetype":"venue"
},
  "geometry": {"coordinates":[-117.442477,33.922609],"type":"Point"}
}