{
  "type": "Feature",
  "properties": {
    "addr:full":"3901 Irvine Blvd Irvine CA 92602",
    "addr:housenumber":"3901",
    "addr:postcode":"92602",
    "addr:street":"Irvine Blvd",
    "iso:country":"US",
    "sg:address":"3901 Irvine Blvd",
    "sg:city":"Irvine",
    "sg:classifiers":[
        {
            "category":"Food & Beverages",
            "subcategory":"Candy",
            "type":"Retail Goods"
        },
        {
            "category":"Restaurant",
            "type":"Food & Drink"
        },
        {
            "category":"Bakery",
            "type":"Food & Drink"
        }
    ],
    "sg:phone":"+1 714 573 4667",
    "sg:postcode":"92602",
    "sg:province":"CA",
    "sg:tags":[
        "dessert",
        "french"
    ],
    "sg:website":"www.champagnebakery.com/",
    "wof:name":"Champagne French Bakery",
    "wof:placetype":"venue"
},
  "geometry": {"coordinates":[-117.771531,33.721894],"type":"Point"}
}