{
  "type": "Feature",
  "properties": {
    "iso:country":"US",
    "sg:address":"225 W Hospitality Ln",
    "sg:city":"San Bernardino",
    "sg:classifiers":[
        {
            "category":"Professional",
            "subcategory":"Lawyer & Legal Services",
            "type":"Services"
        }
    ],
    "sg:phone":"+1 909 885 0040",
    "sg:postcode":"92408",
    "sg:province":"CA",
    "sg:tags":[
        "attorney"
    ],
    "wof:name":"Cheryl Houde",
    "wof:placetype":"venue"
},
  "geometry": {"coordinates":[-117.288431,34.065909],"type":"Point"}
}