{
  "type": "Feature",
  "properties": {
    "addr:full":"358 Kanan Rd Oak Park CA 91377",
    "addr:housenumber":"358",
    "addr:postcode":"91377",
    "addr:street":"Kanan Rd",
    "iso:country":"US",
    "sg:address":"358 Kanan Rd",
    "sg:city":"Oak Park",
    "sg:classifiers":[
        {
            "category":"Health Services",
            "subcategory":"Doctor",
            "type":"Services"
        }
    ],
    "sg:phone":"+1 818 707 0046",
    "sg:postcode":"91377",
    "sg:province":"CA",
    "wof:name":"Matthew Andrew M MD Inc Faap",
    "wof:placetype":"venue"
},
  "geometry": {"coordinates":[-118.760002,34.176399],"type":"Point"}
}