{
  "type": "Feature",
  "properties": {
    "addr:full":"920 Via del Castille Morgan Hill CA 95037",
    "addr:housenumber":"920",
    "addr:postcode":"95037",
    "addr:street":"Via Del Castille",
    "iso:country":"US",
    "sg:address":"920 Via del Castille",
    "sg:city":"Morgan Hill",
    "sg:classifiers":[
        {
            "category":"Building & Trades",
            "subcategory":"Landscaping Services",
            "type":"Services"
        }
    ],
    "sg:phone":"+1 408 778 1231",
    "sg:postcode":"95037",
    "sg:province":"CA",
    "sg:tags":[
        "landscape"
    ],
    "wof:name":"Hovig Landscape",
    "wof:placetype":"venue"
},
  "geometry": {"coordinates":[-121.64744899999999,37.098851],"type":"Point"}
}