{
  "type": "Feature",
  "properties": {
    "addr:full":"414 Alta Ave Rohnert Park CA 94928",
    "addr:housenumber":"414",
    "addr:postcode":"94928",
    "addr:street":"Alta Ave",
    "iso:country":"US",
    "sg:address":"414 Alta Ave",
    "sg:city":"Rohnert Park",
    "sg:classifiers":[
        {
            "category":"Retail",
            "subcategory":"Laundry & Dry Cleaning",
            "type":"Services"
        }
    ],
    "sg:phone":"+1 707 794 9917",
    "sg:postcode":"94928",
    "sg:province":"CA",
    "sg:tags":[
        "cleaners",
        "rug",
        "carpet"
    ],
    "wof:name":"D & J Carpet Cleaners",
    "wof:placetype":"venue"
},
  "geometry": {"coordinates":[-122.70175500000001,38.339257],"type":"Point"}
}