{
  "type": "Feature",
  "properties": {
    "addr:full":"1250 Cll Suerte Camarillo CA 93012",
    "addr:housenumber":"1250",
    "addr:postcode":"93012",
    "addr:street":"Cll Suerte",
    "iso:country":"US",
    "sg:address":"1250 Cll Suerte",
    "sg:city":"Camarillo",
    "sg:classifiers":[
        {
            "category":"Manufacturing",
            "subcategory":"Tools & Machinery",
            "type":"Manufacturing & Wholesale Goods"
        }
    ],
    "sg:phone":"+1 805 484 7713",
    "sg:postcode":"93012",
    "sg:province":"CA",
    "sg:tags":[
        "lighting",
        "fixture"
    ],
    "wof:name":"Cooper Lighting",
    "wof:placetype":"venue"
},
  "geometry": {"coordinates":[-119.014624,34.228157],"type":"Point"}
}