{
  "type": "Feature",
  "properties": {
    "iso:country":"US",
    "sg:address":"578 Magnolia Ave",
    "sg:city":"Larkspur",
    "sg:classifiers":[
        {
            "category":"Restaurant",
            "type":"Food & Drink"
        }
    ],
    "sg:phone":"+1 415 924 3353",
    "sg:postcode":"94939",
    "sg:province":"CA",
    "wof:name":"Shin Japanese Restaurant",
    "wof:placetype":"venue"
},
  "geometry": {"coordinates":[-122.534671,37.937457],"type":"Point"}
}