{
  "type": "Feature",
  "properties": {
    "addr:full":"733 N Pastoria Ave Sunnyvale CA 94085",
    "addr:housenumber":"733",
    "addr:postcode":"94085",
    "addr:street":"N Pastoria Ave",
    "iso:country":"US",
    "sg:address":"733 N Pastoria Ave",
    "sg:city":"Sunnyvale",
    "sg:classifiers":[
        {
            "category":"Manufacturing",
            "subcategory":"Chemicals & Compounds",
            "type":"Manufacturing & Wholesale Goods"
        },
        {
            "category":"Professional",
            "subcategory":"Business Services",
            "type":"Services"
        },
        {
            "category":"Building & Trades",
            "subcategory":"Pest Control",
            "type":"Services"
        }
    ],
    "sg:phone":"+1 408 338 0976",
    "sg:postcode":"94085",
    "sg:province":"CA",
    "sg:tags":[
        "industrial",
        "supply",
        "services-commercial",
        "termite",
        "bee",
        "equipment",
        "repellent",
        "mothproofing",
        "barriers",
        "removal",
        "inspection",
        "bird"
    ],
    "sg:website":"http://www.terminix.com",
    "wof:name":"Terminix",
    "wof:placetype":"venue"
},
  "geometry": {"coordinates":[-122.03260400000001,37.395991],"type":"Point"}
}