{
  "type": "Feature",
  "properties": {
    "addr:full":"1095 Eleanor Ave Rohnert Park CA 94928",
    "addr:housenumber":"1095",
    "addr:postcode":"94928",
    "addr:street":"Eleanor Ave",
    "iso:country":"US",
    "sg:address":"1095 Eleanor Ave",
    "sg:city":"Rohnert Park",
    "sg:classifiers":[
        {
            "category":"Wholesale",
            "subcategory":"Electrical",
            "type":"Manufacturing & Wholesale Goods"
        }
    ],
    "sg:phone":"+1 707 584 0894",
    "sg:postcode":"94928",
    "sg:province":"CA",
    "sg:tags":[
        "alarm",
        "burglar",
        "system"
    ],
    "wof:name":"On-Guard Security",
    "wof:placetype":"venue"
},
  "geometry": {"coordinates":[-122.687687,38.361702],"type":"Point"}
}