{
  "type": "Feature",
  "properties": {
    "iso:country":"US",
    "sg:address":"4454 Van Nuys Blvd Ste D",
    "sg:city":"Sherman Oaks",
    "sg:classifiers":[
        {
            "category":"Personal",
            "type":"Services"
        }
    ],
    "sg:phone":"+1 818 995 6868",
    "sg:postcode":"91403",
    "sg:province":"CA",
    "sg:tags":[
        "sewing",
        "alteration"
    ],
    "wof:name":"Tailors of Sherman Oaks",
    "wof:placetype":"venue"
},
  "geometry": {"coordinates":[-118.44899700000001,34.152302],"type":"Point"}
}