{
  "type": "Feature",
  "properties": {
    "iso:country":"US",
    "sg:address":"200 S 4th St",
    "sg:city":"Montague",
    "sg:classifiers":[
        {
            "category":"Social Services",
            "subcategory":"Adult Care",
            "type":"Services"
        }
    ],
    "sg:phone":"+1 530 459 5800",
    "sg:postcode":"96064",
    "sg:province":"CA",
    "sg:tags":[
        "home",
        "residential"
    ],
    "wof:name":"Barker's Residential Care",
    "wof:placetype":"venue"
},
  "geometry": {"coordinates":[-122.51900999999999,41.723372],"type":"Point"}
}