{
  "type": "Feature",
  "properties": {
    "iso:country":"US",
    "sg:address":"15503 Ave 240",
    "sg:city":"Tulare",
    "sg:classifiers":[
        {
            "category":"Farming",
            "subcategory":"Dairy Farm",
            "type":"Manufacturing & Wholesale Goods"
        }
    ],
    "sg:phone":"+1 559 687 1325",
    "sg:postcode":"93274",
    "sg:province":"CA",
    "wof:name":"Alden Highstreet",
    "wof:placetype":"venue"
},
  "geometry": {"coordinates":[-119.228145,36.225304],"type":"Point"}
}