{
  "type": "Feature",
  "properties": {
    "addr:full":"280 E Hamilton Ave Campbell CA 95008",
    "addr:housenumber":"280",
    "addr:postcode":"95008",
    "addr:street":"E Hamilton Ave",
    "iso:country":"US",
    "sg:address":"280 E Hamilton Ave",
    "sg:city":"Campbell",
    "sg:classifiers":[
        {
            "category":"Communications",
            "type":"Services"
        }
    ],
    "sg:phone":"+1 408 370 9562",
    "sg:postcode":"95008",
    "sg:province":"CA",
    "sg:tags":[
        "pathologist",
        "speech-language"
    ],
    "wof:name":"Brown Connie MS CCC-SLP & Associates",
    "wof:placetype":"venue"
},
  "geometry": {"coordinates":[-121.94498299999999,37.29428],"type":"Point"}
}