{
  "type": "Feature",
  "properties": {
    "iso:country":"US",
    "sg:address":"2211 San Ramon Valley Blvd",
    "sg:city":"San Ramon",
    "sg:classifiers":[
        {
            "category":"Restaurant",
            "type":"Food & Drink"
        }
    ],
    "sg:phone":"+1 925 838 9600",
    "sg:postcode":"94583",
    "sg:province":"CA",
    "wof:name":"Three Brothers From China",
    "wof:placetype":"venue"
},
  "geometry": {"coordinates":[-121.978008,37.780149],"type":"Point"}
}