{
  "type": "Feature",
  "properties": {
    "iso:country":"US",
    "sg:address":"15475 Jeffrey Road",
    "sg:city":"Irvine",
    "sg:classifiers":[
        {
            "category":"Health Services",
            "subcategory":"Dentist",
            "type":"Services"
        }
    ],
    "sg:phone":"+1 949 733 3339",
    "sg:postcode":"92618",
    "sg:province":"CA",
    "sg:tags":[
        "orthodontist"
    ],
    "wof:name":"Amara Crandall DDS MSD",
    "wof:placetype":"venue"
},
  "geometry": {"coordinates":[-117.759771,33.661823],"type":"Point"}
}