{
  "type": "Feature",
  "properties": {
    "addr:full":"224 E Dexter St Covina CA 91723",
    "addr:housenumber":"224",
    "addr:postcode":"91723",
    "addr:street":"E Dexter St",
    "iso:country":"US",
    "sg:address":"224 E Dexter St",
    "sg:city":"Covina",
    "sg:classifiers":[
        {
            "category":"Manufacturing",
            "subcategory":"Tools & Machinery",
            "type":"Manufacturing & Wholesale Goods"
        }
    ],
    "sg:phone":"+1 626 967 7828",
    "sg:postcode":"91723",
    "sg:province":"CA",
    "sg:tags":[
        "mfg",
        "printing",
        "trade"
    ],
    "wof:name":"Ralph Sprung Mfrs Rprsentative",
    "wof:placetype":"venue"
},
  "geometry": {"coordinates":[-117.886222,34.083773],"type":"Point"}
}