{
  "type": "Feature",
  "properties": {
    "iso:country":"US",
    "sg:address":"1929 Webster St",
    "sg:city":"Alameda",
    "sg:classifiers":[
        {
            "category":"Home & Garden",
            "subcategory":"Garden Supply",
            "type":"Retail Goods"
        }
    ],
    "sg:phone":"+1 510 865 2441",
    "sg:postcode":"94501",
    "sg:province":"CA",
    "sg:tags":[
        "tree",
        "christmas"
    ],
    "wof:name":"Crystal Christmas Trees",
    "wof:placetype":"venue"
},
  "geometry": {"coordinates":[-122.276571,37.778618],"type":"Point"}
}