{
  "type": "Feature",
  "properties": {
    "iso:country":"US",
    "sg:address":"9367 Narnia Dr",
    "sg:city":"Riverside",
    "sg:classifiers":[
        {
            "category":"Wholesale",
            "subcategory":"Computers",
            "type":"Manufacturing & Wholesale Goods"
        }
    ],
    "sg:phone":"+1 951 785 6077",
    "sg:postcode":"92503",
    "sg:province":"CA",
    "sg:tags":[
        "equipment",
        "peripheral",
        "used"
    ],
    "wof:name":"C D S",
    "wof:placetype":"venue"
},
  "geometry": {"coordinates":[-117.437664,33.915202],"type":"Point"}
}