{
  "type": "Feature",
  "properties": {
    "iso:country":"US",
    "sg:address":"6310 San Vicente Blvd",
    "sg:city":"Los Angeles",
    "sg:classifiers":[
        {
            "category":"Banks & Credit Unions",
            "subcategory":"Bank",
            "type":"Services"
        }
    ],
    "sg:phone":"+1 323 930 0440",
    "sg:postcode":"90048",
    "sg:province":"CA",
    "sg:tags":[
        "mortgage",
        "loan",
        "broker",
        "real estate"
    ],
    "sg:website":"www.sterlingmtg.com",
    "wof:name":"Sterling Equity Mortgage Inc",
    "wof:placetype":"venue"
},
  "geometry": {"coordinates":[-118.367333,34.060786],"type":"Point"}
}