{
  "type": "Feature",
  "properties": {
    "iso:country":"US",
    "sg:address":"2000 E 4th St",
    "sg:city":"Santa Ana",
    "sg:classifiers":[
        {
            "category":"Professional",
            "subcategory":"Lawyer & Legal Services",
            "type":"Services"
        }
    ],
    "sg:phone":"+1 714 567 0025",
    "sg:postcode":"92705",
    "sg:province":"CA",
    "wof:name":"Hegel Edward J Jr Atty",
    "wof:placetype":"venue"
},
  "geometry": {"coordinates":[-117.83899700000001,33.7481],"type":"Point"}
}