{
  "type": "Feature",
  "properties": {
    "addr:full":"2504 E Chapman Ave Fullerton CA 92831",
    "addr:housenumber":"2504",
    "addr:postcode":"92831",
    "addr:street":"E Chapman Ave",
    "iso:country":"US",
    "sg:address":"2504 E Chapman Ave",
    "sg:city":"Fullerton",
    "sg:classifiers":[
        {
            "category":"Banks & Credit Unions",
            "subcategory":"Bank",
            "type":"Services"
        }
    ],
    "sg:phone":"+1 714 871 9600",
    "sg:postcode":"92831",
    "sg:province":"CA",
    "sg:tags":[
        "financing"
    ],
    "wof:name":"American General Finance Inc",
    "wof:placetype":"venue"
},
  "geometry": {"coordinates":[-117.88897299999999,33.874159],"type":"Point"}
}