{
  "type": "Feature",
  "properties": {
    "iso:country":"US",
    "sg:address":"8895 Towne Centre Dr Ste 100A",
    "sg:city":"San Diego",
    "sg:classifiers":[
        {
            "category":"Restaurant",
            "type":"Food & Drink"
        }
    ],
    "sg:phone":"+1 858 457 4455",
    "sg:postcode":"92122",
    "sg:province":"CA",
    "sg:tags":[
        "sushi",
        "bar"
    ],
    "wof:name":"Edo Sushi",
    "wof:placetype":"venue"
},
  "geometry": {"coordinates":[-117.206186,32.867398],"type":"Point"}
}