{
  "type": "Feature",
  "properties": {
    "addr:full":"2705 Delta Rd Brentwood CA 94513",
    "addr:housenumber":"2705",
    "addr:postcode":"ca 94513",
    "addr:street":"Delta Rd",
    "iso:country":"US",
    "sg:address":"2705 Delta Rd",
    "sg:city":"Brentwood",
    "sg:classifiers":[
        {
            "category":"Professional",
            "type":"Services"
        }
    ],
    "sg:phone":"+1 925 625 0311",
    "sg:postcode":"94513",
    "sg:province":"CA",
    "wof:name":"Morriss David & Susan",
    "wof:placetype":"venue"
},
  "geometry": {"coordinates":[-121.643545,37.968741],"type":"Point"}
}