{
  "type": "Feature",
  "properties": {
    "addr:full":"9235 Venice Blvd Los Angeles CA 90034",
    "addr:housenumber":"9235",
    "addr:postcode":"90034",
    "addr:street":"Venice Blvd",
    "iso:country":"US",
    "sg:address":"9235 Venice Blvd",
    "sg:city":"Los Angeles",
    "sg:classifiers":[
        {
            "category":"Banks & Credit Unions",
            "subcategory":"Bank",
            "type":"Services"
        }
    ],
    "sg:phone":"+1 310 838 9897",
    "sg:postcode":"90034",
    "sg:province":"CA",
    "sg:tags":[
        "cashing",
        "check"
    ],
    "wof:name":"A-1 Financial",
    "wof:placetype":"venue"
},
  "geometry": {"coordinates":[-118.39405600000001,34.026355],"type":"Point"}
}