{
  "type": "Feature",
  "properties": {
    "iso:country":"US",
    "sg:address":"9815 Lurline Ave",
    "sg:city":"Chatsworth",
    "sg:classifiers":[
        {
            "category":"Manufacturing",
            "subcategory":"Tools & Machinery",
            "type":"Manufacturing & Wholesale Goods"
        }
    ],
    "sg:phone":"+1 818 993 4324",
    "sg:postcode":"91311",
    "sg:province":"CA",
    "sg:tags":[
        "machine",
        "shop"
    ],
    "wof:name":"Sickles Engineering",
    "wof:placetype":"venue"
},
  "geometry": {"coordinates":[-118.584256,34.249713],"type":"Point"}
}