{
  "type": "Feature",
  "properties": {
    "iso:country":"US",
    "sg:address":"44404 16th St W",
    "sg:city":"Lancaster",
    "sg:classifiers":[
        {
            "category":"Shopping",
            "type":"Retail Goods"
        }
    ],
    "sg:phone":"+1 661 949 0504",
    "sg:postcode":"93534",
    "sg:province":"CA",
    "sg:tags":[
        "limb",
        "artificial"
    ],
    "wof:name":"Valley Institute Prosthetics",
    "wof:placetype":"venue"
},
  "geometry": {"coordinates":[-118.158413,34.691337],"type":"Point"}
}