{
  "type": "Feature",
  "properties": {
    "iso:country":"US",
    "sg:address":"981 Lake Tahoe Blvd",
    "sg:city":"South Lake Tahoe",
    "sg:classifiers":[
        {
            "category":"Government",
            "subcategory":"Office",
            "type":"Public Place"
        }
    ],
    "sg:phone":"+1 530 573 3273",
    "sg:postcode":"96150",
    "sg:province":"CA",
    "sg:tags":[
        "program",
        "administrative"
    ],
    "wof:name":"Social Svcs Employment Svcs",
    "wof:placetype":"venue"
},
  "geometry": {"coordinates":[-120.032693,38.88685],"type":"Point"}
}