{
  "type": "Feature",
  "properties": {
    "iso:country":"US",
    "sg:address":"47 4th St",
    "sg:city":"Gonzales",
    "sg:classifiers":[
        {
            "category":"Food & Beverages",
            "subcategory":"Groceries & Convenience Stores",
            "type":"Retail Goods"
        }
    ],
    "sg:phone":"+1 831 675 3466",
    "sg:postcode":"93926",
    "sg:province":"CA",
    "sg:tags":[
        "grocer"
    ],
    "wof:name":"Jalisco Market",
    "wof:placetype":"venue"
},
  "geometry": {"coordinates":[-121.444739,36.506748],"type":"Point"}
}