{
  "type": "Feature",
  "properties": {
    "iso:country":"US",
    "sg:address":"20755 E Crest Ln",
    "sg:city":"Walnut",
    "sg:classifiers":[
        {
            "category":"Wholesale",
            "subcategory":"Non-durable Goods",
            "type":"Manufacturing & Wholesale Goods"
        }
    ],
    "sg:phone":"+1 951 323 6173",
    "sg:postcode":"91789",
    "sg:province":"CA",
    "wof:name":"Msr Trading Co",
    "wof:placetype":"venue"
},
  "geometry": {"coordinates":[-117.852656,33.980756],"type":"Point"}
}