{
  "type": "Feature",
  "properties": {
    "iso:country":"US",
    "sg:address":"108 Pacifica",
    "sg:city":"Irvine",
    "sg:classifiers":[
        {
            "category":"Banks & Credit Unions",
            "subcategory":"Bank",
            "type":"Services"
        }
    ],
    "sg:phone":"+1 949 699 1200",
    "sg:postcode":"92618",
    "sg:province":"CA",
    "sg:tags":[
        "loan",
        "broker"
    ],
    "wof:name":"Radford Financial",
    "wof:placetype":"venue"
},
  "geometry": {"coordinates":[-117.753861,33.660729],"type":"Point"}
}