{
  "type": "Feature",
  "properties": {
    "iso:country":"US",
    "sg:address":"1820 Fullerton Ave",
    "sg:city":"Corona",
    "sg:classifiers":[
        {
            "category":"Social Services",
            "type":"Services"
        },
        {
            "category":"Personal",
            "type":"Services"
        }
    ],
    "sg:phone":"+1 951 736 6611",
    "sg:postcode":"92881",
    "sg:province":"CA",
    "sg:tags":[
        "counseling",
        "therapist",
        "marriage",
        "family"
    ],
    "wof:name":"Rosen Mitchell Marriage & Family Therapist",
    "wof:placetype":"venue"
},
  "geometry": {"coordinates":[-117.550325,33.859686],"type":"Point"}
}