{
  "type": "Feature",
  "properties": {
    "addr:full":"1141 Main St St Helena CA 94574",
    "addr:housenumber":"1141",
    "addr:postcode":"94574",
    "addr:street":"Main St",
    "iso:country":"US",
    "sg:address":"1141 Main St",
    "sg:city":"St Helena",
    "sg:classifiers":[
        {
            "category":"Retail",
            "subcategory":"Laundry & Dry Cleaning",
            "type":"Services"
        }
    ],
    "sg:phone":"+1 707 963 2811",
    "sg:postcode":"94574",
    "sg:province":"CA",
    "sg:tags":[
        "cleaners"
    ],
    "wof:name":"Klass Cleaners",
    "wof:placetype":"venue"
},
  "geometry": {"coordinates":[-122.46765600000001,38.503541],"type":"Point"}
}