{
  "type": "Feature",
  "properties": {
    "addr:full":"10391 48th St Mira Loma CA 91752",
    "addr:housenumber":"10391",
    "addr:postcode":"91752",
    "addr:street":"48Th St",
    "iso:country":"US",
    "sg:address":"10391 48th St",
    "sg:city":"Mira Loma",
    "sg:classifiers":[
        {
            "category":"Building & Trades",
            "subcategory":"Construction",
            "type":"Services"
        }
    ],
    "sg:phone":"+1 951 681 4262",
    "sg:postcode":"91752",
    "sg:province":"CA",
    "sg:tags":[
        "horse",
        "shelter",
        "corral",
        "fabricates",
        "feeder",
        "barn"
    ],
    "wof:name":"Edward Zambrano",
    "wof:placetype":"venue"
},
  "geometry": {"coordinates":[-117.511723,34.000044],"type":"Point"}
}