{
  "type": "Feature",
  "properties": {
    "iso:country":"US",
    "sg:address":"25 5th St",
    "sg:city":"Hermosa Beach",
    "sg:classifiers":[
        {
            "category":"Manufacturing",
            "subcategory":"Paper Products",
            "type":"Manufacturing & Wholesale Goods"
        }
    ],
    "sg:phone":"+1 310 374 8898",
    "sg:postcode":"90254",
    "sg:province":"CA",
    "sg:tags":[
        "wholesaler",
        "bag",
        "printed",
        "custom"
    ],
    "wof:name":"Bags 4 Show",
    "wof:placetype":"venue"
},
  "geometry": {"coordinates":[-118.399801,33.85689],"type":"Point"}
}