{
  "type": "Feature",
  "properties": {
    "addr:full":"3855 Sepulveda Blvd Torrance CA 90505",
    "addr:housenumber":"3855",
    "addr:postcode":"90505",
    "addr:street":"Sepulveda Blvd",
    "iso:country":"US",
    "sg:address":"3855 Sepulveda Blvd",
    "sg:city":"Torrance",
    "sg:classifiers":[
        {
            "category":"Retail",
            "subcategory":"Animal Services",
            "type":"Services"
        }
    ],
    "sg:phone":"+1 310 316 9047",
    "sg:postcode":"90505",
    "sg:province":"CA",
    "sg:tags":[
        "pet",
        "training"
    ],
    "sg:website":"www.petsmart.com",
    "wof:name":"Petsmart",
    "wof:placetype":"venue"
},
  "geometry": {"coordinates":[-118.353996,33.8256],"type":"Point"}
}