{
  "type": "Feature",
  "properties": {
    "addr:full":"217 Arneill Rd Camarillo CA 93010",
    "addr:housenumber":"217",
    "addr:postcode":"93010",
    "addr:street":"Arneill Rd",
    "iso:country":"US",
    "sg:address":"217 Arneill Rd",
    "sg:city":"Camarillo",
    "sg:classifiers":[
        {
            "category":"Restaurant",
            "type":"Food & Drink"
        }
    ],
    "sg:phone":"+1 805 482 8009",
    "sg:postcode":"93010",
    "sg:province":"CA",
    "wof:name":"Sawadee Restaurant",
    "wof:placetype":"venue"
},
  "geometry": {"coordinates":[-119.039001,34.218399],"type":"Point"}
}