{
  "type": "Feature",
  "properties": {
    "iso:country":"US",
    "sg:address":"1212 Franklin St",
    "sg:city":"Oakland",
    "sg:classifiers":[
        {
            "category":"Professional",
            "subcategory":"Detective & Security Services",
            "type":"Services"
        }
    ],
    "sg:phone":"+1 510 834 1030",
    "sg:postcode":"94612",
    "sg:province":"CA",
    "sg:tags":[
        "car"
    ],
    "wof:name":"J P Morgan Invest LLC",
    "wof:placetype":"venue"
},
  "geometry": {"coordinates":[-122.270392,37.803038],"type":"Point"}
}