{
  "type": "Feature",
  "properties": {
    "iso:country":"US",
    "sg:address":"350 E St",
    "sg:city":"Redwood City",
    "sg:classifiers":[
        {
            "category":"Wholesale",
            "subcategory":"Electrical",
            "type":"Manufacturing & Wholesale Goods"
        }
    ],
    "sg:phone":"+1 650 367 7690",
    "sg:postcode":"94063",
    "sg:province":"CA",
    "sg:tags":[
        "electronic"
    ],
    "wof:name":"Puzon Crtv Co Phllpnes & Frnce",
    "wof:placetype":"venue"
},
  "geometry": {"coordinates":[-122.239287,37.495674],"type":"Point"}
}