{
  "type": "Feature",
  "properties": {
    "iso:country":"US",
    "sg:address":"1045 Atlantic Ave Ste 801",
    "sg:city":"Long Beach",
    "sg:classifiers":[
        {
            "category":"Health Services",
            "subcategory":"Doctor",
            "type":"Services"
        },
        {
            "category":"Health Services",
            "subcategory":"Clinic",
            "type":"Services"
        }
    ],
    "sg:phone":"+1 562 590 5594",
    "sg:postcode":"90813",
    "sg:province":"CA",
    "sg:tags":[
        "counseling",
        "mental"
    ],
    "wof:name":"Dushenko Terrance W PHD",
    "wof:placetype":"venue"
},
  "geometry": {"coordinates":[-118.184998,33.7799],"type":"Point"}
}