{
  "type": "Feature",
  "properties": {
    "iso:country":"US",
    "sg:address":"13882 Newport Ave Ste G",
    "sg:city":"Tustin",
    "sg:classifiers":[
        {
            "category":"Restaurant",
            "type":"Food & Drink"
        }
    ],
    "sg:phone":"+1 714 669 1011",
    "sg:postcode":"92780",
    "sg:province":"CA",
    "sg:tags":[
        "pakistani",
        "indian"
    ],
    "wof:name":"Haveli Indian Restaurant",
    "wof:placetype":"venue"
},
  "geometry": {"coordinates":[-117.820519,33.739119],"type":"Point"}
}