{
  "type": "Feature",
  "properties": {
    "addr:full":"695 Town Center Dr Costa Mesa CA 92626",
    "addr:housenumber":"695",
    "addr:postcode":"92626",
    "addr:street":"Town Center Dr",
    "iso:country":"US",
    "sg:address":"695 Town Center Dr",
    "sg:city":"Costa Mesa",
    "sg:classifiers":[
        {
            "category":"Professional",
            "subcategory":"Lawyer & Legal Services",
            "type":"Services"
        }
    ],
    "sg:phone":"+1 714 668 6200",
    "sg:postcode":"92626",
    "sg:province":"CA",
    "wof:name":"Paul Hstngs Jnfsky Walker LLP",
    "wof:placetype":"venue"
},
  "geometry": {"coordinates":[-117.883426,33.692485],"type":"Point"}
}