{
  "type": "Feature",
  "properties": {
    "iso:country":"US",
    "sg:address":"603 Madsen Dr",
    "sg:city":"Ripon",
    "sg:classifiers":[
        {
            "category":"Professional",
            "subcategory":"Management & Consulting",
            "type":"Services"
        }
    ],
    "sg:phone":"+1 209 599 9659",
    "sg:postcode":"95366",
    "sg:province":"CA",
    "sg:tags":[
        "house",
        "construction"
    ],
    "wof:name":"Total Solutions & Hardware",
    "wof:placetype":"venue"
},
  "geometry": {"coordinates":[-121.13675499999999,37.733599],"type":"Point"}
}