{
  "type": "Feature",
  "properties": {
    "addr:full":"1561 Los Angeles Ave Ventura CA 93004",
    "addr:housenumber":"1561",
    "addr:postcode":"93004",
    "addr:street":"Los Angeles Ave",
    "iso:country":"US",
    "sg:address":"1561 Los Angeles Ave",
    "sg:city":"Ventura",
    "sg:phone":"+1 805 290 4320",
    "sg:postcode":"93004",
    "sg:province":"CA",
    "wof:name":"Dependable Car Care Auto Repair",
    "wof:placetype":"venue"
},
  "geometry": {"coordinates":[-119.143612,34.280094],"type":"Point"}
}