{
  "type": "Feature",
  "properties": {
    "addr:full":"32 Gentry Irvine CA 92620",
    "addr:housenumber":"32",
    "addr:postcode":"92620",
    "addr:street":"Gentry",
    "iso:country":"US",
    "sg:address":"32 Gentry",
    "sg:city":"Irvine",
    "sg:classifiers":[
        {
            "category":"Professional",
            "subcategory":"Computer Services",
            "type":"Services"
        }
    ],
    "sg:phone":"+1 949 552 1596",
    "sg:postcode":"92620",
    "sg:province":"CA",
    "sg:tags":[
        "repair"
    ],
    "wof:name":"ISOPC",
    "wof:placetype":"venue"
},
  "geometry": {"coordinates":[-117.750135,33.705101],"type":"Point"}
}