{
  "type": "Feature",
  "properties": {
    "addr:full":"3120 Main St San Diego CA 92113",
    "addr:housenumber":"3120",
    "addr:postcode":"92113",
    "addr:street":"Main St",
    "iso:country":"US",
    "sg:address":"3120 Main St",
    "sg:city":"San Diego",
    "sg:classifiers":[
        {
            "category":"Manufacturing",
            "subcategory":"Metals",
            "type":"Manufacturing & Wholesale Goods"
        }
    ],
    "sg:phone":"+1 619 263 4063",
    "sg:postcode":"92113",
    "sg:province":"CA",
    "sg:tags":[
        "polishing"
    ],
    "wof:name":"San Diego Wheel Polishing",
    "wof:placetype":"venue"
},
  "geometry": {"coordinates":[-117.125579,32.69268],"type":"Point"}
}