{
  "type": "Feature",
  "properties": {
    "iso:country":"US",
    "sg:address":"30901 Timberline Rd",
    "sg:city":"Willits",
    "sg:classifiers":[
        {
            "category":"Shopping",
            "subcategory":"Stationery & Office Supplies",
            "type":"Retail Goods"
        },
        {
            "category":"Manufacturing",
            "subcategory":"Retail Goods",
            "type":"Manufacturing & Wholesale Goods"
        }
    ],
    "sg:phone":"+1 707 459 9124",
    "sg:postcode":"95490",
    "sg:province":"CA",
    "sg:tags":[
        "toy",
        "art",
        "mfg",
        "stamp",
        "plastic",
        "rubber",
        "wooden",
        "paper"
    ],
    "sg:website":"www.rubberstampgoods.com",
    "wof:name":"Good Stamps and Stamp Goods",
    "wof:placetype":"venue"
},
  "geometry": {"coordinates":[-123.43454199999999,39.490191],"type":"Point"}
}