{
  "type": "Feature",
  "properties": {
    "iso:country":"US",
    "sg:address":"6025 Mariposa Ave",
    "sg:city":"Citrus Heights",
    "sg:classifiers":[
        {
            "category":"Building & Trades",
            "subcategory":"Construction",
            "type":"Services"
        }
    ],
    "sg:phone":"+1 916 837 5858",
    "sg:postcode":"95610",
    "sg:province":"CA",
    "sg:tags":[
        "repairing",
        "remodeling",
        "contractor"
    ],
    "wof:name":"N S Construction",
    "wof:placetype":"venue"
},
  "geometry": {"coordinates":[-121.284793,38.676877],"type":"Point"}
}