{
  "type": "Feature",
  "properties": {
    "addr:full":"181 N Encinal Ave Ojai CA 93023",
    "addr:housenumber":"181",
    "addr:postcode":"93023",
    "addr:street":"N Encinal Ave",
    "iso:country":"US",
    "sg:address":"181 N Encinal Ave",
    "sg:city":"Ojai",
    "sg:classifiers":[
        {
            "category":"Building & Trades",
            "subcategory":"Construction",
            "type":"Services"
        }
    ],
    "sg:phone":"+1 805 646 0744",
    "sg:postcode":"93023",
    "sg:province":"CA",
    "sg:tags":[
        "contractor"
    ],
    "wof:name":"Lowry SD Construction",
    "wof:placetype":"venue"
},
  "geometry": {"coordinates":[-119.278937,34.449511],"type":"Point"}
}