{
  "type": "Feature",
  "properties": {
    "addr:full":"188 E 3rd St Chico CA 95928",
    "addr:housenumber":"188",
    "addr:postcode":"95928",
    "addr:street":"E 3Rd St",
    "iso:country":"US",
    "sg:address":"188 E 3rd St",
    "sg:city":"Chico",
    "sg:classifiers":[
        {
            "category":"Organizations",
            "subcategory":"Religious Organization",
            "type":"Services"
        }
    ],
    "sg:phone":"+1 530 342 1545",
    "sg:postcode":"95928",
    "sg:province":"CA",
    "wof:name":"Christian Science Reading Room",
    "wof:placetype":"venue"
},
  "geometry": {"coordinates":[-121.839122,39.729941],"type":"Point"}
}