{
  "type": "Feature",
  "properties": {
    "addr:full":"1400 Bridge St Yuba City CA 95993",
    "addr:housenumber":"1400",
    "addr:postcode":"95993",
    "addr:street":"Bridge St",
    "iso:country":"US",
    "sg:address":"1400 Bridge St",
    "sg:city":"Yuba City",
    "sg:classifiers":[
        {
            "category":"Wholesale",
            "subcategory":"Groceries",
            "type":"Manufacturing & Wholesale Goods"
        }
    ],
    "sg:phone":"+1 530 751 1085",
    "sg:postcode":"95993",
    "sg:province":"CA",
    "sg:tags":[
        "general"
    ],
    "wof:name":"Smart & Final Stores Corp",
    "wof:placetype":"venue"
},
  "geometry": {"coordinates":[-121.639292,39.132358],"type":"Point"}
}