{
  "type": "Feature",
  "properties": {
    "addr:full":"2333 Creekwood Ct Santa Rosa CA 95409",
    "addr:housenumber":"2333",
    "addr:postcode":"95409",
    "addr:street":"Creekwood Ct",
    "iso:country":"US",
    "sg:address":"2333 Creekwood Ct",
    "sg:city":"Santa Rosa",
    "sg:classifiers":[
        {
            "category":"Building & Trades",
            "subcategory":"Construction",
            "type":"Services"
        }
    ],
    "sg:phone":"+1 707 538 0814",
    "sg:postcode":"95409",
    "sg:province":"CA",
    "sg:tags":[
        "contractor"
    ],
    "wof:name":"Kevin D Champie Construction",
    "wof:placetype":"venue"
},
  "geometry": {"coordinates":[-122.677089,38.474934],"type":"Point"}
}