{
  "type": "Feature",
  "properties": {
    "iso:country":"US",
    "sg:address":"44802 Date Ave",
    "sg:city":"Lancaster",
    "sg:classifiers":[
        {
            "category":"Retail",
            "subcategory":"Funeral Services",
            "type":"Services"
        }
    ],
    "sg:phone":"+1 661 945 3892",
    "sg:postcode":"93534",
    "sg:province":"CA",
    "sg:tags":[
        "director"
    ],
    "wof:name":"Funeral Reference Svc",
    "wof:placetype":"venue"
},
  "geometry": {"coordinates":[-118.140399,34.696185],"type":"Point"}
}