{
  "type": "Feature",
  "properties": {
    "iso:country":"US",
    "sg:address":"969 E 12th St",
    "sg:city":"Los Angeles",
    "sg:classifiers":[
        {
            "category":"Wholesale",
            "subcategory":"Apparel",
            "type":"Manufacturing & Wholesale Goods"
        }
    ],
    "sg:phone":"+1 213 629 4777",
    "sg:postcode":"90021",
    "sg:province":"CA",
    "sg:tags":[
        "textile"
    ],
    "sg:website":"www.liagol.com",
    "wof:name":"Lia Gol Textile Inc",
    "wof:placetype":"venue"
},
  "geometry": {"coordinates":[-118.248333,34.031579],"type":"Point"}
}