{
  "type": "Feature",
  "properties": {
    "iso:country":"US",
    "sg:address":"35 Mitchell Blvd",
    "sg:city":"San Rafael",
    "sg:classifiers":[
        {
            "category":"Insurance",
            "subcategory":"Insurance Agent",
            "type":"Services"
        }
    ],
    "sg:phone":"+1 415 472 8622",
    "sg:postcode":"94903",
    "sg:province":"CA",
    "wof:name":"Imperial Industries",
    "wof:placetype":"venue"
},
  "geometry": {"coordinates":[-122.538659,38.017081],"type":"Point"}
}