{
  "type": "Feature",
  "properties": {
    "iso:country":"US",
    "sg:address":"68031 Ramon Rd",
    "sg:city":"Cathedral City",
    "sg:classifiers":[
        {
            "category":"Shopping",
            "subcategory":"Tobacco",
            "type":"Retail Goods"
        }
    ],
    "sg:phone":"+1 760 202 1500",
    "sg:postcode":"92234",
    "sg:province":"CA",
    "sg:tags":[
        "shop"
    ],
    "wof:name":"111 Smoke +",
    "wof:placetype":"venue"
},
  "geometry": {"coordinates":[-116.47588,33.815732],"type":"Point"}
}