{
  "type": "Feature",
  "properties": {
    "addr:full":"1745 Banff Dr Sunnyvale CA 94087",
    "addr:housenumber":"1745",
    "addr:postcode":"94087",
    "addr:street":"Banff Dr",
    "iso:country":"US",
    "sg:address":"1745 Banff Dr",
    "sg:city":"Sunnyvale",
    "sg:classifiers":[
        {
            "category":"Communications",
            "type":"Services"
        }
    ],
    "sg:phone":"+1 408 732 1300",
    "sg:postcode":"94087",
    "sg:province":"CA",
    "sg:tags":[
        "communication"
    ],
    "wof:name":"Axcel Communications",
    "wof:placetype":"venue"
},
  "geometry": {"coordinates":[-122.057755,37.336172],"type":"Point"}
}