{
  "type": "Feature",
  "properties": {
    "iso:country":"US",
    "sg:address":"11608 Carmel Mountain Rd",
    "sg:city":"San Diego",
    "sg:classifiers":[
        {
            "category":"Autos & Motor Vehicles",
            "subcategory":"Auto Supplies",
            "type":"Retail Goods"
        }
    ],
    "sg:phone":"+1 858 675 2000",
    "sg:postcode":"92129",
    "sg:province":"CA",
    "sg:tags":[
        "automobile",
        "stereo",
        "radio"
    ],
    "wof:name":"Al & Ed's Autosound",
    "wof:placetype":"venue"
},
  "geometry": {"coordinates":[-117.078338,32.980348],"type":"Point"}
}