{
  "type": "Feature",
  "properties": {
    "addr:full":"4473 Sepulveda Blvd Culver City CA 90230",
    "addr:housenumber":"4473",
    "addr:postcode":"90230",
    "addr:street":"Sepulveda Blvd",
    "iso:country":"US",
    "sg:address":"4473 Sepulveda Blvd",
    "sg:city":"Culver City",
    "sg:classifiers":[
        {
            "category":"Health Services",
            "subcategory":"Chiropractor",
            "type":"Services"
        }
    ],
    "sg:phone":"+1 310 398 5733",
    "sg:postcode":"90230",
    "sg:province":"CA",
    "sg:website":"www.thebackdoctor.com",
    "wof:name":"William S Nojima, DC",
    "wof:placetype":"venue"
},
  "geometry": {"coordinates":[-118.40586500000001,34.002336],"type":"Point"}
}