{
  "type": "Feature",
  "properties": {
    "iso:country":"US",
    "sg:address":"2705 Samarkand Dr",
    "sg:city":"Santa Barbara",
    "sg:classifiers":[
        {
            "category":"Building & Trades",
            "subcategory":"Construction",
            "type":"Services"
        }
    ],
    "sg:phone":"+1 805 682 2348",
    "sg:postcode":"93105",
    "sg:province":"CA",
    "sg:tags":[
        "tile",
        "dealer"
    ],
    "wof:name":"Paul Piacentini",
    "wof:placetype":"venue"
},
  "geometry": {"coordinates":[-119.730514,34.433349],"type":"Point"}
}