{
  "type": "Feature",
  "properties": {
    "addr:full":"103 Central Ave Island Heights CA 95476",
    "addr:housenumber":"103",
    "addr:postcode":"95476",
    "addr:street":"Central Ave Island",
    "iso:country":"US",
    "sg:address":"103 Central Ave",
    "sg:city":"Island Heights",
    "sg:classifiers":[
        {
            "category":"Organizations",
            "subcategory":"Religious Organization",
            "type":"Services"
        }
    ],
    "sg:phone":"+1 732 288 0036",
    "sg:postcode":"95476",
    "sg:province":"CA",
    "sg:tags":[
        "church"
    ],
    "wof:name":"St Gertrude's Mission Church",
    "wof:placetype":"venue"
},
  "geometry": {"coordinates":[-122.417007,38.246553],"type":"Point"}
}