{
  "type": "Feature",
  "properties": {
    "addr:full":"4978 Antioch Loop Union City CA 94587",
    "addr:housenumber":"4978",
    "addr:postcode":"94587",
    "addr:street":"Antioch Loop",
    "iso:country":"US",
    "sg:address":"4978 Antioch Loop",
    "sg:city":"Union City",
    "sg:classifiers":[
        {
            "category":"Building & Trades",
            "subcategory":"Construction",
            "type":"Services"
        }
    ],
    "sg:phone":"+1 510 487 1460",
    "sg:postcode":"94587",
    "sg:province":"CA",
    "sg:tags":[
        "maintenance",
        "contractor"
    ],
    "wof:name":"California Maintenance & Bynd",
    "wof:placetype":"venue"
},
  "geometry": {"coordinates":[-122.072772,37.571394],"type":"Point"}
}