{
  "type": "Feature",
  "properties": {
    "addr:full":"1467 Marion St Kingsburg CA 93631",
    "addr:housenumber":"1467",
    "addr:postcode":"93631",
    "addr:street":"Marion St",
    "iso:country":"US",
    "sg:address":"1467 Marion St",
    "sg:city":"Kingsburg",
    "sg:classifiers":[
        {
            "category":"Manufacturing",
            "subcategory":"Printing",
            "type":"Manufacturing & Wholesale Goods"
        }
    ],
    "sg:phone":"+1 559 897 2993",
    "sg:postcode":"93631",
    "sg:province":"CA",
    "sg:tags":[
        "newspaper"
    ],
    "wof:name":"Kingsburg Recorder",
    "wof:placetype":"venue"
},
  "geometry": {"coordinates":[-119.552284,36.514041],"type":"Point"}
}