{
  "type": "Feature",
  "properties": {
    "addr:full":"8576 Saint Helena Hwy Rutherford CA 94573",
    "addr:housenumber":"8576",
    "addr:postcode":"94573",
    "addr:street":"Saint Helena Hwy",
    "iso:country":"US",
    "sg:address":"8576 Saint Helena Hwy",
    "sg:city":"Rutherford",
    "sg:classifiers":[
        {
            "category":"Manufacturing",
            "subcategory":"Food",
            "type":"Manufacturing & Wholesale Goods"
        }
    ],
    "sg:phone":"+1 707 967 1003",
    "sg:postcode":"94573",
    "sg:province":"CA",
    "sg:tags":[
        "olive",
        "oil"
    ],
    "sg:website":"www.sholiveoil.com",
    "wof:name":"St Helena OLIVE Oil Co",
    "wof:placetype":"venue"
},
  "geometry": {"coordinates":[-122.42134799999999,38.457128],"type":"Point"}
}