{
  "type": "Feature",
  "properties": {
    "addr:full":"5055 Almaden Expy San Jose CA 95118",
    "addr:housenumber":"5055",
    "addr:postcode":"95118",
    "addr:street":"Almaden Expy",
    "iso:country":"US",
    "sg:address":"5055 Almaden Expy",
    "sg:city":"San Jose",
    "sg:classifiers":[
        {
            "category":"Restaurant",
            "type":"Food & Drink"
        }
    ],
    "sg:phone":"+1 408 269 2900",
    "sg:postcode":"95118",
    "sg:province":"CA",
    "sg:tags":[
        "breakfast",
        "brunch"
    ],
    "sg:website":"www.scramblz.com",
    "wof:name":"Scramblz",
    "wof:placetype":"venue"
},
  "geometry": {"coordinates":[-121.87616199999999,37.257421],"type":"Point"}
}