{
  "type": "Feature",
  "properties": {
    "addr:full":"9775 Date St Fontana CA 92335",
    "addr:housenumber":"9775",
    "addr:postcode":"92335",
    "addr:street":"Date St",
    "iso:country":"US",
    "sg:address":"9775 Date St",
    "sg:city":"Fontana",
    "sg:classifiers":[
        {
            "category":"Freight",
            "type":"Transportation"
        }
    ],
    "sg:phone":"+1 909 356 2113",
    "sg:postcode":"92335",
    "sg:province":"CA",
    "sg:tags":[
        "operator",
        "local",
        "trucking"
    ],
    "wof:name":"A & G Trucking",
    "wof:placetype":"venue"
},
  "geometry": {"coordinates":[-117.44683000000001,34.076612],"type":"Point"}
}