{
  "type": "Feature",
  "properties": {
    "addr:full":"5073 Hollister Ave Santa Barbara CA 93111",
    "addr:housenumber":"5073",
    "addr:postcode":"93111",
    "addr:street":"Hollister Ave",
    "iso:country":"US",
    "sg:address":"5073 Hollister Ave",
    "sg:city":"Santa Barbara",
    "sg:classifiers":[
        {
            "category":"Organizations",
            "subcategory":"Religious Organization",
            "type":"Services"
        }
    ],
    "sg:phone":"+1 805 964 9966",
    "sg:postcode":"93111",
    "sg:province":"CA",
    "sg:tags":[
        "church"
    ],
    "sg:website":"www.ctkreconcilers.org",
    "wof:name":"Christ The King Episcopal Chr",
    "wof:placetype":"venue"
},
  "geometry": {"coordinates":[-119.798514,34.434781],"type":"Point"}
}