{
  "type": "Feature",
  "properties": {
    "iso:country":"US",
    "sg:address":"882 2nd St",
    "sg:city":"Santa Rosa",
    "sg:classifiers":[
        {
            "category":"Social Services",
            "type":"Services"
        }
    ],
    "sg:phone":"+1 707 524 8876",
    "sg:postcode":"95404",
    "sg:province":"CA",
    "sg:tags":[
        "counselor",
        "marriage",
        "family"
    ],
    "wof:name":"Mind Body & Spirit",
    "wof:placetype":"venue"
},
  "geometry": {"coordinates":[-122.707679,38.441344],"type":"Point"}
}