{
  "type": "Feature",
  "properties": {
    "addr:full":"396 Sandalwood Dr Calimesa CA 92320",
    "addr:housenumber":"396",
    "addr:postcode":"92320",
    "addr:street":"Sandalwood Dr",
    "iso:country":"US",
    "sg:address":"396 Sandalwood Dr",
    "sg:city":"Calimesa",
    "sg:classifiers":[
        {
            "category":"Building & Trades",
            "subcategory":"Landscaping Services",
            "type":"Services"
        }
    ],
    "sg:phone":"+1 909 795 8436",
    "sg:postcode":"92320",
    "sg:province":"CA",
    "sg:tags":[
        "aged",
        "homes-institutional"
    ],
    "wof:name":"Country Hearts Manor",
    "wof:placetype":"venue"
},
  "geometry": {"coordinates":[-117.05122,33.994416],"type":"Point"}
}