{
  "type": "Feature",
  "properties": {
    "addr:full":"120 Dillon Ave Campbell CA 95008",
    "addr:housenumber":"120",
    "addr:postcode":"95008",
    "addr:street":"Dillon Ave",
    "iso:country":"US",
    "sg:address":"120 Dillon Ave",
    "sg:city":"Campbell",
    "sg:classifiers":[
        {
            "category":"Manufacturing",
            "subcategory":"Leather Goods",
            "type":"Manufacturing & Wholesale Goods"
        }
    ],
    "sg:phone":"+1 408 379 7337",
    "sg:postcode":"95008",
    "sg:province":"CA",
    "sg:tags":[
        "handbag",
        "mfg"
    ],
    "wof:name":"Leather Guild of California",
    "wof:placetype":"venue"
},
  "geometry": {"coordinates":[-121.941002,37.286201],"type":"Point"}
}