{
  "type": "Feature",
  "properties": {
    "addr:full":"8788 Elk Grove Blvd Elk Grove CA 95624",
    "addr:housenumber":"8788",
    "addr:postcode":"95624",
    "addr:street":"Elk Grove Blvd",
    "iso:country":"US",
    "sg:address":"8788 Elk Grove Blvd",
    "sg:city":"Elk Grove",
    "sg:classifiers":[
        {
            "category":"Professional",
            "subcategory":"Accounting & Tax Preparation",
            "type":"Services"
        }
    ],
    "sg:phone":"+1 916 685 9568",
    "sg:postcode":"95624",
    "sg:province":"CA",
    "sg:tags":[
        "accountant"
    ],
    "wof:name":"Joseph W Mc Ginley CPA",
    "wof:placetype":"venue"
},
  "geometry": {"coordinates":[-121.378443,38.408989],"type":"Point"}
}