{
  "type": "Feature",
  "properties": {
    "iso:country":"US",
    "sg:address":"27315 Parklane Way",
    "sg:city":"Valencia",
    "sg:classifiers":[
        {
            "category":"Personal",
            "subcategory":"Beauty Salon",
            "type":"Services"
        }
    ],
    "sg:phone":"+1 661 255 9298",
    "sg:postcode":"91354",
    "sg:province":"CA",
    "wof:name":"Tech Styles",
    "wof:placetype":"venue"
},
  "geometry": {"coordinates":[-118.554134,34.43449],"type":"Point"}
}