{
  "type": "Feature",
  "properties": {
    "iso:country":"US",
    "sg:address":"305 Lincoln St",
    "sg:city":"Calexico",
    "sg:classifiers":[
        {
            "category":"Freight",
            "type":"Transportation"
        }
    ],
    "sg:phone":"+1 760 357 8663",
    "sg:postcode":"92231",
    "sg:province":"CA",
    "sg:tags":[
        "operator",
        "local",
        "trucking"
    ],
    "wof:name":"Rolys Trucking Logistic",
    "wof:placetype":"venue"
},
  "geometry": {"coordinates":[-115.501443,32.675144],"type":"Point"}
}