{
  "type": "Feature",
  "properties": {
    "iso:country":"US",
    "sg:address":"1065 E Hillsdale Blvd",
    "sg:city":"San Mateo",
    "sg:classifiers":[
        {
            "category":"Freight",
            "type":"Transportation"
        }
    ],
    "sg:phone":"+1 650 377 0736",
    "sg:postcode":"94403",
    "sg:province":"CA",
    "sg:tags":[
        "courier"
    ],
    "wof:name":"Fedex",
    "wof:placetype":"venue"
},
  "geometry": {"coordinates":[-122.27042899999999,37.559602],"type":"Point"}
}