{
  "type": "Feature",
  "properties": {
    "iso:country":"US",
    "sg:address":"2245 Cooley Pl",
    "sg:city":"Pasadena",
    "sg:classifiers":[
        {
            "category":"Food & Beverages",
            "subcategory":"Specialty",
            "type":"Retail Goods"
        }
    ],
    "sg:phone":"+1 626 792 3189",
    "sg:postcode":"91104",
    "sg:province":"CA",
    "sg:tags":[
        "health",
        "supplement",
        "nutritional",
        "store"
    ],
    "wof:name":"Super Nutri Doc",
    "wof:placetype":"venue"
},
  "geometry": {"coordinates":[-118.10520099999999,34.163445],"type":"Point"}
}