{
  "type": "Feature",
  "properties": {
    "iso:country":"US",
    "sg:address":"220 W Grand Ave",
    "sg:city":"El Segundo",
    "sg:classifiers":[
        {
            "category":"Banks & Credit Unions",
            "subcategory":"Investment Brokerage",
            "type":"Services"
        }
    ],
    "sg:phone":"+1 310 322 6420",
    "sg:postcode":"90245",
    "sg:province":"CA",
    "sg:tags":[
        "investing",
        "advisory"
    ],
    "wof:name":"Valdes and Associates",
    "wof:placetype":"venue"
},
  "geometry": {"coordinates":[-118.41799899999999,33.919102],"type":"Point"}
}