{
  "type": "Feature",
  "properties": {
    "iso:country":"US",
    "sg:address":"1200 Arizona St",
    "sg:city":"Redlands",
    "sg:classifiers":[
        {
            "category":"Autos & Motor Vehicles",
            "subcategory":"Auto Supplies",
            "type":"Retail Goods"
        },
        {
            "category":"Wholesale",
            "subcategory":"Auto Parts",
            "type":"Manufacturing & Wholesale Goods"
        }
    ],
    "sg:phone":"+1 909 793 3681",
    "sg:postcode":"92374",
    "sg:province":"CA",
    "sg:tags":[
        "equipment",
        "racing",
        "car",
        "automobile"
    ],
    "wof:name":"Bottlefed Racing",
    "wof:placetype":"venue"
},
  "geometry": {"coordinates":[-117.207521,34.068445],"type":"Point"}
}