{
  "type": "Feature",
  "properties": {
    "iso:country":"US",
    "sg:address":"6540 Lusk Blvd",
    "sg:city":"San Diego",
    "sg:classifiers":[
        {
            "category":"Real Estate",
            "subcategory":"Real Estate Agent",
            "type":"Services"
        }
    ],
    "sg:phone":"+1 858 452 5501",
    "sg:postcode":"92121",
    "sg:province":"CA",
    "wof:name":"Real Estate Consulting Group",
    "wof:placetype":"venue"
},
  "geometry": {"coordinates":[-117.20263199999999,32.901527],"type":"Point"}
}