{
  "type": "Feature",
  "properties": {
    "iso:country":"US",
    "sg:address":"10084 Lode Line Way",
    "sg:city":"Grass Valley",
    "sg:classifiers":[
        {
            "category":"Building & Trades",
            "subcategory":"Construction",
            "type":"Services"
        }
    ],
    "sg:phone":"+1 530 477 1470",
    "sg:postcode":"95949",
    "sg:province":"CA",
    "sg:tags":[
        "mobile",
        "home"
    ],
    "wof:name":"Walkers Mobile Home Mntnc",
    "wof:placetype":"venue"
},
  "geometry": {"coordinates":[-121.058938,39.166276],"type":"Point"}
}