{
  "type": "Feature",
  "properties": {
    "iso:country":"US",
    "sg:address":"165 E Wilson St",
    "sg:city":"Costa Mesa",
    "sg:classifiers":[
        {
            "category":"Building & Trades",
            "subcategory":"Construction",
            "type":"Services"
        }
    ],
    "sg:phone":"+1 949 678 6208",
    "sg:postcode":"92627",
    "sg:province":"CA",
    "sg:tags":[
        "product",
        "asphalt"
    ],
    "wof:name":"Acme Asphalt & Concrete",
    "wof:placetype":"venue"
},
  "geometry": {"coordinates":[-117.900838,33.654088],"type":"Point"}
}