{
  "type": "Feature",
  "properties": {
    "iso:country":"US",
    "sg:address":"195 S C St",
    "sg:city":"Tustin",
    "sg:classifiers":[
        {
            "category":"Professional",
            "subcategory":"Management & Consulting",
            "type":"Services"
        }
    ],
    "sg:phone":"+1 714 832 9368",
    "sg:postcode":"92780",
    "sg:province":"CA",
    "wof:name":"Honeywell",
    "wof:placetype":"venue"
},
  "geometry": {"coordinates":[-117.824834,33.745598],"type":"Point"}
}