{
  "type": "Feature",
  "properties": {
    "iso:country":"US",
    "sg:address":"11925 Woodside Ave",
    "sg:city":"Lakeside",
    "sg:classifiers":[
        {
            "category":"Building & Trades",
            "subcategory":"Equipment Rental",
            "type":"Services"
        }
    ],
    "sg:phone":"+1 619 561 7845",
    "sg:postcode":"92040",
    "sg:province":"CA",
    "sg:tags":[
        "yard"
    ],
    "wof:name":"Lakeside Equipment Sales Inc",
    "wof:placetype":"venue"
},
  "geometry": {"coordinates":[-116.935878,32.855321],"type":"Point"}
}