{
  "type": "Feature",
  "properties": {
    "addr:full":"441 N Livermore Ave Livermore CA 94551",
    "addr:housenumber":"441",
    "addr:postcode":"94551",
    "addr:street":"N Livermore Ave",
    "iso:country":"US",
    "sg:address":"441 N Livermore Ave",
    "sg:city":"Livermore",
    "sg:classifiers":[
        {
            "category":"Freight",
            "type":"Transportation"
        }
    ],
    "sg:phone":"+1 925 443 9900",
    "sg:postcode":"94551",
    "sg:province":"CA",
    "sg:tags":[
        "trucking"
    ],
    "wof:name":"Open Wings Transportation Inc",
    "wof:placetype":"venue"
},
  "geometry": {"coordinates":[-121.77129499999999,37.686915],"type":"Point"}
}