{
  "type": "Feature",
  "properties": {
    "addr:full":"2880 Atlantic Ave Ste 100 Long Beach CA 90806",
    "addr:housenumber":"2880",
    "addr:postcode":"90806",
    "addr:street":"Atlantic Ave Ste 100",
    "iso:country":"US",
    "sg:address":"2880 Atlantic Ave Ste 100",
    "sg:city":"Long Beach",
    "sg:classifiers":[
        {
            "category":"Health Services",
            "subcategory":"Doctor",
            "type":"Services"
        }
    ],
    "sg:phone":"+1 562 595 5421",
    "sg:postcode":"90806",
    "sg:province":"CA",
    "wof:name":"Patel Kalpana G MD",
    "wof:placetype":"venue"
},
  "geometry": {"coordinates":[-118.18499799999999,33.809502],"type":"Point"}
}