{
  "type": "Feature",
  "properties": {
    "iso:country":"US",
    "sg:address":"222 N Virgil Ave",
    "sg:city":"Los Angeles",
    "sg:classifiers":[
        {
            "category":"Education",
            "subcategory":"School",
            "type":"Public Place"
        }
    ],
    "sg:phone":"+1 213 480 4200",
    "sg:postcode":"90004",
    "sg:province":"CA",
    "sg:tags":[
        "religious"
    ],
    "sg:website":"www.seacharter.org",
    "wof:name":"SEA Charter School",
    "wof:placetype":"venue"
},
  "geometry": {"coordinates":[-118.28672299999999,34.074914],"type":"Point"}
}