{
  "type": "Feature",
  "properties": {
    "iso:country":"US",
    "sg:address":"2020 S Mesa St",
    "sg:city":"San Pedro",
    "sg:classifiers":[
        {
            "category":"Building & Trades",
            "subcategory":"Plumbing",
            "type":"Services"
        }
    ],
    "sg:phone":"+1 310 831 0737",
    "sg:postcode":"90731",
    "sg:province":"CA",
    "sg:tags":[
        "plumbing",
        "contractor"
    ],
    "wof:name":"Pete Fer & Son Plbg & Supl Co",
    "wof:placetype":"venue"
},
  "geometry": {"coordinates":[-118.28569,33.725245],"type":"Point"}
}