{
  "type": "Feature",
  "properties": {
    "iso:country":"US",
    "sg:address":"603 N H St",
    "sg:city":"Lompoc",
    "sg:classifiers":[
        {
            "category":"Food & Beverages",
            "subcategory":"Groceries & Convenience Stores",
            "type":"Retail Goods"
        }
    ],
    "sg:phone":"+1 805 735 4653",
    "sg:postcode":"93436",
    "sg:province":"CA",
    "wof:name":"Vons Fuel Station",
    "wof:placetype":"venue"
},
  "geometry": {"coordinates":[-120.457922,34.64844],"type":"Point"}
}