{
  "type": "Feature",
  "properties": {
    "iso:country":"US",
    "sg:address":"811 N Broadway",
    "sg:city":"Santa Ana",
    "sg:classifiers":[
        {
            "category":"Freight",
            "type":"Transportation"
        }
    ],
    "sg:phone":"+1 714 542 3664",
    "sg:postcode":"92701",
    "sg:province":"CA",
    "sg:tags":[
        "special"
    ],
    "wof:name":"L J P A Company",
    "wof:placetype":"venue"
},
  "geometry": {"coordinates":[-117.869634,33.752619],"type":"Point"}
}