{
  "type": "Feature",
  "properties": {
    "addr:full":"414 Grass Valley Hwy Auburn CA 95603",
    "addr:housenumber":"414",
    "addr:postcode":"ca 95603",
    "addr:street":"Grass Valley Hwy",
    "iso:country":"US",
    "sg:address":"414 Grass Valley Hwy",
    "sg:city":"Auburn",
    "sg:classifiers":[
        {
            "category":"Food & Beverages",
            "subcategory":"Groceries & Convenience Stores",
            "type":"Retail Goods"
        }
    ],
    "sg:phone":"+1 530 885 0250",
    "sg:postcode":"95603",
    "sg:province":"CA",
    "sg:tags":[
        "grocer"
    ],
    "wof:name":"Grocery Outlet",
    "wof:placetype":"venue"
},
  "geometry": {"coordinates":[-121.07635500000001,38.904448],"type":"Point"}
}