{
  "type": "Feature",
  "properties": {
    "iso:country":"US",
    "sg:address":"5051 Commerce Dr",
    "sg:city":"Baldwin Park",
    "sg:classifiers":[
        {
            "category":"Professional",
            "subcategory":"Advertising",
            "type":"Services"
        }
    ],
    "sg:phone":"+1 626 813 6127",
    "sg:postcode":"91706",
    "sg:province":"CA",
    "sg:tags":[
        "distribution"
    ],
    "wof:name":"Campos Distribution",
    "wof:placetype":"venue"
},
  "geometry": {"coordinates":[-117.97806799999999,34.101709],"type":"Point"}
}