{
  "type": "Feature",
  "properties": {
    "iso:country":"US",
    "sg:address":"5056 Eagle Rock Blvd",
    "sg:city":"Los Angeles",
    "sg:classifiers":[
        {
            "category":"Restaurant",
            "type":"Food & Drink"
        }
    ],
    "sg:phone":"+1 323 478 1440",
    "sg:postcode":"90041",
    "sg:province":"CA",
    "sg:tags":[
        "new",
        "american"
    ],
    "wof:name":"Armon's Restaurant",
    "wof:placetype":"venue"
},
  "geometry": {"coordinates":[-118.21399700000001,34.138599],"type":"Point"}
}