{
  "type": "Feature",
  "properties": {
    "addr:full":"4190 Bonita Rd Ste 101 Bonita CA 91902",
    "addr:housenumber":"4190",
    "addr:postcode":"91902",
    "addr:street":"Bonita Rd Ste 101",
    "iso:country":"US",
    "sg:address":"4190 Bonita Rd Ste 101",
    "sg:city":"Bonita",
    "sg:classifiers":[
        {
            "category":"Shopping",
            "subcategory":"Pharmacy",
            "type":"Retail Goods"
        }
    ],
    "sg:phone":"+1 619 475 4112",
    "sg:postcode":"91902",
    "sg:province":"CA",
    "sg:tags":[
        "drugstore"
    ],
    "wof:name":"Bonita Pharmacy",
    "wof:placetype":"venue"
},
  "geometry": {"coordinates":[-117.03600299999999,32.660702],"type":"Point"}
}