{
  "type": "Feature",
  "properties": {
    "iso:country":"US",
    "sg:address":"800 Rockview Dr",
    "sg:city":"Walnut Creek",
    "sg:classifiers":[
        {
            "category":"Home & Garden",
            "subcategory":"Garden Supply",
            "type":"Retail Goods"
        }
    ],
    "sg:phone":"+1 925 952 4966",
    "sg:postcode":"94595",
    "sg:province":"CA",
    "sg:tags":[
        "fountain",
        "display"
    ],
    "wof:name":"Golden Rain Foundation",
    "wof:placetype":"venue"
},
  "geometry": {"coordinates":[-122.069945,37.868997],"type":"Point"}
}