{
  "type": "Feature",
  "properties": {
    "addr:full":"6985 Karen Ln Riverside CA 92509",
    "addr:housenumber":"6985",
    "addr:postcode":"92509",
    "addr:street":"Karen Ln",
    "iso:country":"US",
    "sg:address":"6985 Karen Ln",
    "sg:city":"Riverside",
    "sg:classifiers":[
        {
            "category":"Real Estate",
            "subcategory":"Real Estate Services",
            "type":"Services"
        },
        {
            "category":"Real Estate",
            "subcategory":"Surveying",
            "type":"Services"
        }
    ],
    "sg:phone":"+1 951 360 1277",
    "sg:postcode":"92509",
    "sg:province":"CA",
    "sg:tags":[
        "industrial",
        "appraisers-commercial",
        "appraiser"
    ],
    "wof:name":"Appraisal Service For Material",
    "wof:placetype":"venue"
},
  "geometry": {"coordinates":[-117.425484,34.026885],"type":"Point"}
}