{
  "type": "Feature",
  "properties": {
    "iso:country":"US",
    "sg:address":"428 Old Newport Boulevard",
    "sg:city":"Newport Beach",
    "sg:classifiers":[
        {
            "category":"Professional",
            "subcategory":"Lawyer & Legal Services",
            "type":"Services"
        }
    ],
    "sg:phone":"+1 949 515 0807",
    "sg:postcode":"92663",
    "sg:province":"CA",
    "wof:name":"Stewart Brian P Law Offices of",
    "wof:placetype":"venue"
},
  "geometry": {"coordinates":[-117.926605,33.626045],"type":"Point"}
}