{
  "type": "Feature",
  "properties": {
    "addr:full":"1821 Davenport Dr Modesto CA 95356",
    "addr:housenumber":"1821",
    "addr:postcode":"ca 95356",
    "addr:street":"Davenport Dr",
    "iso:country":"US",
    "sg:address":"1821 Davenport Dr",
    "sg:city":"Modesto",
    "sg:classifiers":[
        {
            "category":"Social Services",
            "subcategory":"Child Care",
            "type":"Services"
        }
    ],
    "sg:phone":"+1 209 238 3393",
    "sg:postcode":"95356",
    "sg:province":"CA",
    "wof:name":"All About Kids",
    "wof:placetype":"venue"
},
  "geometry": {"coordinates":[-121.025282,37.697678],"type":"Point"}
}