{
  "type": "Feature",
  "properties": {
    "iso:country":"US",
    "sg:address":"1262 Humboldt Ave",
    "sg:city":"Chico",
    "sg:classifiers":[
        {
            "category":"Shopping",
            "subcategory":"Clothing, Apparel, & Fashions",
            "type":"Retail Goods"
        }
    ],
    "sg:phone":"+1 530 343 8725",
    "sg:postcode":"95928",
    "sg:province":"CA",
    "sg:tags":[
        "t"
    ],
    "sg:website":"www.5sun.com",
    "wof:name":"Gonzales Enterprises Inc",
    "wof:placetype":"venue"
},
  "geometry": {"coordinates":[-121.821522,39.732164],"type":"Point"}
}