{
  "type": "Feature",
  "properties": {
    "iso:country":"US",
    "sg:address":"12821 W Jefferson Blvd",
    "sg:city":"Los Angeles",
    "sg:classifiers":[
        {
            "category":"Retail",
            "subcategory":"Storage",
            "type":"Services"
        }
    ],
    "sg:phone":"+1 310 301 7867",
    "sg:postcode":"90066",
    "sg:province":"CA",
    "sg:tags":[
        "self"
    ],
    "sg:website":"www.storquest.com/self_storage/P...",
    "wof:name":"StorQuest Self Storage",
    "wof:placetype":"venue"
},
  "geometry": {"coordinates":[-118.41937,33.976911],"type":"Point"}
}