{
  "type": "Feature",
  "properties": {
    "addr:full":"2033 Gateway Place, Suite 500, San Jose, CA 95110",
    "addr:housenumber":"2033",
    "addr:postcode":"95110",
    "addr:street":"Gateway Place Suite 500",
    "iso:country":"US",
    "sg:address":"2033 Gateway Place, Suite 500,",
    "sg:city":"San Jose,",
    "sg:classifiers":[
        {
            "category":"Professional",
            "subcategory":"Computer Services",
            "type":"Services"
        }
    ],
    "sg:phone":"+1 919898021433",
    "sg:postcode":"95110",
    "sg:province":"CA",
    "sg:tags":[
        "web-application-development",
        "mobile-application-development",
        "software-development",
        "web-development",
        "web-design",
        "iphone-application-development",
        "offshore",
        "outsourcing",
        "portal-development",
        "ecommerce-solutions"
    ],
    "sg:website":"http://www.hiddenbrains.com/",
    "wof:name":"HiddenBrains InfoTech Pvt Ltd. ",
    "wof:placetype":"venue"
},
  "geometry": {"coordinates":[-121.92272800000001,37.370632],"type":"Point"}
}