{
  "type": "Feature",
  "properties": {
    "addr:full":"3069 Alamo Dr #174 Vacaville CA 95687",
    "addr:housenumber":"3069",
    "addr:postcode":"95687",
    "addr:street":"Alamo Dr # 174",
    "iso:country":"US",
    "sg:address":"3069 Alamo Dr #174",
    "sg:city":"Vacaville",
    "sg:classifiers":[
        {
            "category":"Manufacturing",
            "subcategory":"Glass & Minerals",
            "type":"Manufacturing & Wholesale Goods"
        },
        {
            "category":"Retail",
            "subcategory":"Auto Repair",
            "type":"Services"
        }
    ],
    "sg:phone":"+1 877 858 0969",
    "sg:postcode":"95687",
    "sg:province":"CA",
    "sg:tags":[
        "plate",
        "window",
        "windshield",
        "glass-auto"
    ],
    "sg:website":"http://local.ingenio.com/Listings/Details.aspx?NUM=a%3a10138940%3a13%3a4859924%3a14%3a0%3a7",
    "wof:name":"D's Auto Glass Repair",
    "wof:placetype":"venue"
},
  "geometry": {"coordinates":[-121.954661,38.335334],"type":"Point"}
}