{
  "type": "Feature",
  "properties": {
    "addr:full":"891 Daffodil Ct Simi Valley CA 93065",
    "addr:housenumber":"891",
    "addr:postcode":"93065",
    "addr:street":"Daffodil Ct",
    "iso:country":"US",
    "sg:address":"891 Daffodil Ct",
    "sg:city":"Simi Valley",
    "sg:classifiers":[
        {
            "category":"Professional",
            "type":"Services"
        }
    ],
    "sg:phone":"+1 805 578 0509",
    "sg:postcode":"93065",
    "sg:province":"CA",
    "wof:name":"Pocketime",
    "wof:placetype":"venue"
},
  "geometry": {"coordinates":[-118.78684199999999,34.25398],"type":"Point"}
}