{
  "type": "Feature",
  "properties": {
    "iso:country":"US",
    "sg:address":"891 Daffodil Ct",
    "sg:city":"Simi Valley",
    "sg:classifiers":[
        {
            "category":"Professional",
            "type":"Services"
        }
    ],
    "sg:phone":"+1 805 578 0509",
    "sg:postcode":"93065",
    "sg:province":"CA",
    "wof:name":"Pocketime",
    "wof:placetype":"venue"
},
  "geometry": {"coordinates":[-118.786842,34.25398],"type":"Point"}
}