{
  "type": "Feature",
  "properties": {
    "iso:country":"US",
    "sg:address":"2884 W Grant Line Rd",
    "sg:city":"Tracy",
    "sg:classifiers":[
        {
            "category":"Home & Garden",
            "subcategory":"Furniture",
            "type":"Retail Goods"
        },
        {
            "category":"Home & Garden",
            "subcategory":"Carpets & Floor Coverings",
            "type":"Retail Goods"
        }
    ],
    "sg:phone":"+1 209 835 7800",
    "sg:postcode":"95304",
    "sg:province":"CA",
    "sg:tags":[
        "store",
        "mattress"
    ],
    "wof:name":"Mancini's Sleepworld",
    "wof:placetype":"venue"
},
  "geometry": {"coordinates":[-121.47028400000001,37.75406],"type":"Point"}
}