{
  "type": "Feature",
  "properties": {
    "addr:full":"1135 W Barkley Ave Orange CA 92868",
    "addr:housenumber":"1135",
    "addr:postcode":"92868",
    "addr:street":"W Barkley Ave",
    "iso:country":"US",
    "sg:address":"1135 W Barkley Ave",
    "sg:city":"Orange",
    "sg:classifiers":[
        {
            "category":"Retail",
            "subcategory":"Auto Repair",
            "type":"Services"
        }
    ],
    "sg:phone":"+1 714 639 2526",
    "sg:postcode":"92868",
    "sg:province":"CA",
    "wof:name":"Mmc Auto Care",
    "wof:placetype":"venue"
},
  "geometry": {"coordinates":[-117.864998,33.801102],"type":"Point"}
}