{
  "type": "Feature",
  "properties": {
    "addr:full":"10875 N Butte Rd Live Oak CA 95953",
    "addr:housenumber":"10875",
    "addr:postcode":"95953",
    "addr:street":"N Butte Rd",
    "iso:country":"US",
    "sg:address":"10875 N Butte Rd",
    "sg:city":"Live Oak",
    "sg:phone":"+1 530 695 2431",
    "sg:postcode":"95953",
    "sg:province":"CA",
    "sg:tags":[
        "orchard",
        "farm",
        "nut",
        "tree",
        "grove",
        "fruit",
        "rice"
    ],
    "wof:name":"Rudd Farming Inc",
    "wof:placetype":"venue"
},
  "geometry": {"coordinates":[-121.817001,39.296409],"type":"Point"}
}