{
  "type": "Feature",
  "properties": {
    "addr:full":"31967 Ellis Way North Fork CA 93643",
    "addr:housenumber":"31967",
    "addr:postcode":"93643",
    "addr:street":"Ellis Way",
    "iso:country":"US",
    "sg:address":"31967 Ellis Way",
    "sg:city":"North Fork",
    "sg:classifiers":[
        {
            "category":"Building & Trades",
            "subcategory":"Construction",
            "type":"Services"
        }
    ],
    "sg:phone":"+1 559 877 4496",
    "sg:postcode":"93643",
    "sg:province":"CA",
    "sg:tags":[
        "excavating",
        "contractor"
    ],
    "wof:name":"Mark L Rohrbaugh Backhoe Svc",
    "wof:placetype":"venue"
},
  "geometry": {"coordinates":[-119.534272,37.211257],"type":"Point"}
}