{
  "type": "Feature",
  "properties": {
    "addr:full":"2525 Eighth St Berkeley CA 94710",
    "addr:housenumber":"2525",
    "addr:postcode":"94710",
    "addr:street":"Eighth St",
    "iso:country":"US",
    "sg:address":"2525 Eighth St",
    "sg:city":"Berkeley",
    "sg:classifiers":[
        {
            "category":"Recreation",
            "type":"Entertainment"
        }
    ],
    "sg:postcode":"94710",
    "sg:province":"CA",
    "sg:tags":[
        "active",
        "life"
    ],
    "wof:name":"Studio 12 Flys",
    "wof:placetype":"venue"
},
  "geometry": {"coordinates":[-122.292766,37.859955],"type":"Point"}
}