{
  "type": "Feature",
  "properties": {
    "iso:country":"US",
    "sg:address":"8100 Garden Grove Blvd",
    "sg:city":"Garden Grove",
    "sg:classifiers":[
        {
            "category":"Organizations",
            "subcategory":"Religious Organization",
            "type":"Services"
        }
    ],
    "sg:phone":"+1 714 899 0015",
    "sg:postcode":"92844",
    "sg:province":"CA",
    "wof:name":"Day of Salvation the",
    "wof:placetype":"venue"
},
  "geometry": {"coordinates":[-117.989998,33.773602],"type":"Point"}
}