{
  "type": "Feature",
  "properties": {
    "iso:country":"US",
    "sg:address":"360 San Miguel Dr Ste 204",
    "sg:city":"Newport Beach",
    "sg:classifiers":[
        {
            "category":"Health Services",
            "subcategory":"Dentist",
            "type":"Services"
        }
    ],
    "sg:phone":"+1 949 644 2455",
    "sg:postcode":"92660",
    "sg:province":"CA",
    "wof:name":"Sheets & Paquette Dental Practice",
    "wof:placetype":"venue"
},
  "geometry": {"coordinates":[-117.8717,33.612624],"type":"Point"}
}