{
  "type": "Feature",
  "properties": {
    "addr:full":"3028 Alta Vista Dr Fallbrook CA 92028",
    "addr:housenumber":"3028",
    "addr:postcode":"92028",
    "addr:street":"Alta Vista Dr",
    "iso:country":"US",
    "sg:address":"3028 Alta Vista Dr",
    "sg:city":"Fallbrook",
    "sg:classifiers":[
        {
            "category":"Freight",
            "type":"Transportation"
        }
    ],
    "sg:phone":"+1 760 728 1181",
    "sg:postcode":"92028",
    "sg:province":"CA",
    "sg:tags":[
        "hauling",
        "contract"
    ],
    "wof:name":"Howard W Kutz",
    "wof:placetype":"venue"
},
  "geometry": {"coordinates":[-117.21726700000001,33.336699],"type":"Point"}
}