{
  "type": "Feature",
  "properties": {
    "addr:full":"5494 W Centinela Avenue Los Angeles CA 90045",
    "addr:housenumber":"5494",
    "addr:postcode":"90045",
    "addr:street":"W Centinela Avenue",
    "iso:country":"US",
    "sg:address":"5494 W Centinela Avenue",
    "sg:city":"Los Angeles",
    "sg:classifiers":[
        {
            "category":"Personal",
            "subcategory":"Barber",
            "type":"Services"
        }
    ],
    "sg:phone":"+1 310 649 2537",
    "sg:postcode":"90045",
    "sg:province":"CA",
    "wof:name":"Chuck Taylor Barber & Hair",
    "wof:placetype":"venue"
},
  "geometry": {"coordinates":[-118.376491,33.977127],"type":"Point"}
}