{
  "type": "Feature",
  "properties": {
    "addr:full":"5700 Greenville Rd Livermore CA 94550",
    "addr:housenumber":"5700",
    "addr:postcode":"94550",
    "addr:street":"Greenville Rd",
    "iso:country":"US",
    "sg:address":"5700 Greenville Rd",
    "sg:city":"Livermore",
    "sg:classifiers":[
        {
            "category":"Farming",
            "subcategory":"Farm & Veterinary Services",
            "type":"Manufacturing & Wholesale Goods"
        }
    ],
    "sg:phone":"+1 925 371 6551",
    "sg:postcode":"94550",
    "sg:province":"CA",
    "sg:tags":[
        "management"
    ],
    "wof:name":"Casa Blanca Vineyard",
    "wof:placetype":"venue"
},
  "geometry": {"coordinates":[-121.696607,37.650596],"type":"Point"}
}