{
  "type": "Feature",
  "properties": {
    "addr:full":"788 East Ave Chico CA 95926",
    "addr:housenumber":"788",
    "addr:postcode":"95926",
    "addr:street":"East Ave",
    "iso:country":"US",
    "sg:address":"788 East Ave",
    "sg:city":"Chico",
    "sg:classifiers":[
        {
            "category":"Restaurant",
            "type":"Food & Drink"
        }
    ],
    "sg:phone":"+1 530 895 3600",
    "sg:postcode":"95926",
    "sg:province":"CA",
    "sg:tags":[
        "sandwich",
        "eating"
    ],
    "wof:name":"Moe's To Go",
    "wof:placetype":"venue"
},
  "geometry": {"coordinates":[-121.848626,39.76095],"type":"Point"}
}