{
  "type": "Feature",
  "properties": {
    "iso:country":"US",
    "sg:address":"5517 Satsuma Ave",
    "sg:city":"North Hollywood",
    "sg:classifiers":[
        {
            "category":"Airport",
            "type":"Transportation"
        }
    ],
    "sg:phone":"+1 323 877 3049",
    "sg:postcode":"91601",
    "sg:province":"CA",
    "wof:name":"Sam Bernstein",
    "wof:placetype":"venue"
},
  "geometry": {"coordinates":[-118.367605,34.171044],"type":"Point"}
}