{
  "type": "Feature",
  "properties": {
    "iso:country":"US",
    "sg:address":"208 San Jose Ave",
    "sg:city":"Capitola",
    "sg:classifiers":[
        {
            "category":"Professional",
            "type":"Services"
        }
    ],
    "sg:phone":"+1 831 464 2899",
    "sg:postcode":"95010",
    "sg:province":"CA",
    "wof:name":"Michael B Hines",
    "wof:placetype":"venue"
},
  "geometry": {"coordinates":[-121.951172,36.973221],"type":"Point"}
}