{
  "type": "Feature",
  "properties": {
    "addr:full":"3016 Brookfield Ave Oakland CA 94605",
    "addr:housenumber":"3016",
    "addr:postcode":"94605",
    "addr:street":"Brookfield Ave",
    "iso:country":"US",
    "sg:address":"3016 Brookfield Ave",
    "sg:city":"Oakland",
    "sg:classifiers":[
        {
            "category":"Manufacturing",
            "subcategory":"Apparel",
            "type":"Manufacturing & Wholesale Goods"
        }
    ],
    "sg:phone":"+1 510 562 4405",
    "sg:postcode":"94605",
    "sg:province":"CA",
    "wof:name":"Finishing Touch",
    "wof:placetype":"venue"
},
  "geometry": {"coordinates":[-122.13806700000001,37.73335],"type":"Point"}
}