{
  "type": "Feature",
  "properties": {
    "iso:country":"US",
    "sg:address":"3016 Brookfield Ave",
    "sg:city":"Oakland",
    "sg:classifiers":[
        {
            "category":"Manufacturing",
            "subcategory":"Apparel",
            "type":"Manufacturing & Wholesale Goods"
        }
    ],
    "sg:phone":"+1 510 562 4405",
    "sg:postcode":"94605",
    "sg:province":"CA",
    "wof:name":"Finishing Touch",
    "wof:placetype":"venue"
},
  "geometry": {"coordinates":[-122.138067,37.73335],"type":"Point"}
}