{
  "type": "Feature",
  "properties": {
    "iso:country":"US",
    "sg:address":"7528 Greenback Ln",
    "sg:city":"Citrus Heights",
    "sg:classifiers":[
        {
            "category":"Restaurant",
            "type":"Food & Drink"
        }
    ],
    "sg:phone":"+1 916 722 7272",
    "sg:postcode":"95610",
    "sg:province":"CA",
    "sg:tags":[
        "pizza"
    ],
    "wof:name":"Papa Murphy's Take'n'bake Pizza",
    "wof:placetype":"venue"
},
  "geometry": {"coordinates":[-121.28800200000001,38.678101],"type":"Point"}
}