{
  "type": "Feature",
  "properties": {
    "iso:country":"US",
    "sg:address":"213 Benton Ct",
    "sg:city":"Suisun City",
    "sg:classifiers":[
        {
            "category":"Professional",
            "type":"Services"
        }
    ],
    "sg:phone":"+1 707 427 2287",
    "sg:postcode":"94585",
    "sg:province":"CA",
    "sg:website":"www.xtremecyclez.com",
    "wof:name":"Xtreme Cyclez",
    "wof:placetype":"venue"
},
  "geometry": {"coordinates":[-122.042547,38.240131],"type":"Point"}
}