{
  "type": "Feature",
  "properties": {
    "addr:full":"1050 Chestnut St Menlo Park CA 94025",
    "addr:housenumber":"1050",
    "addr:postcode":"94025",
    "addr:street":"Chestnut St",
    "iso:country":"US",
    "sg:address":"1050 Chestnut St",
    "sg:city":"Menlo Park",
    "sg:classifiers":[
        {
            "category":"Real Estate",
            "subcategory":"Real Estate Agent",
            "type":"Services"
        }
    ],
    "sg:phone":"+1 650 329 9022",
    "sg:postcode":"94025",
    "sg:province":"CA",
    "sg:tags":[
        "management"
    ],
    "wof:name":"Classic Property Svc",
    "wof:placetype":"venue"
},
  "geometry": {"coordinates":[-122.184062,37.45126],"type":"Point"}
}