{
  "type": "Feature",
  "properties": {
    "iso:country":"US",
    "sg:address":"974 Mangrove Ave",
    "sg:city":"Chico",
    "sg:classifiers":[
        {
            "category":"Shopping",
            "subcategory":"Clothing, Apparel, & Fashions",
            "type":"Retail Goods"
        }
    ],
    "sg:phone":"+1 530 895 8788",
    "sg:postcode":"95926",
    "sg:province":"CA",
    "wof:name":"Woman Beautiful Apparel",
    "wof:placetype":"venue"
},
  "geometry": {"coordinates":[-121.837151,39.739994],"type":"Point"}
}