{
  "type": "Feature",
  "properties": {
    "addr:full":"3748 Grace Ave Baldwin Park CA 91706",
    "addr:housenumber":"3748",
    "addr:postcode":"91706",
    "addr:street":"Grace Ave",
    "iso:country":"US",
    "sg:address":"3748 Grace Ave",
    "sg:city":"Baldwin Park",
    "sg:classifiers":[
        {
            "category":"Health Services",
            "subcategory":"Nursing And Care Facility",
            "type":"Services"
        }
    ],
    "sg:phone":"+1 626 962 8022",
    "sg:postcode":"91706",
    "sg:province":"CA",
    "sg:tags":[
        "home",
        "convalescent"
    ],
    "wof:name":"Kay's Guest Home",
    "wof:placetype":"venue"
},
  "geometry": {"coordinates":[-117.97819699999999,34.080036],"type":"Point"}
}