{
  "type": "Feature",
  "properties": {
    "addr:full":"5129 Garfield St La Mesa CA 91941",
    "addr:housenumber":"5129",
    "addr:postcode":"91941",
    "addr:street":"Garfield St",
    "iso:country":"US",
    "sg:address":"5129 Garfield St",
    "sg:city":"La Mesa",
    "sg:classifiers":[
        {
            "category":"Health Services",
            "subcategory":"Doctor",
            "type":"Services"
        }
    ],
    "sg:phone":"+1 619 464 5174",
    "sg:postcode":"91941",
    "sg:province":"CA",
    "sg:tags":[
        "physician",
        "surgeon"
    ],
    "wof:name":"Arjun Reddy MD",
    "wof:placetype":"venue"
},
  "geometry": {"coordinates":[-117.005813,32.771305],"type":"Point"}
}