{
  "type": "Feature",
  "properties": {
    "addr:full":"126 Azucar Ave San Jose CA 95111",
    "addr:housenumber":"126",
    "addr:postcode":"95111",
    "addr:street":"Azucar Ave",
    "iso:country":"US",
    "sg:address":"126 Azucar Ave",
    "sg:city":"San Jose",
    "sg:classifiers":[
        {
            "category":"Professional",
            "type":"Services"
        }
    ],
    "sg:phone":"+1 408 229 2117",
    "sg:postcode":"95111",
    "sg:province":"CA",
    "wof:name":"Pham Kiem D & Tran Thuo",
    "wof:placetype":"venue"
},
  "geometry": {"coordinates":[-121.80691400000001,37.261487],"type":"Point"}
}