{
  "type": "Feature",
  "properties": {
    "addr:full":"239 E Alameda Ave Burbank CA 91502",
    "addr:housenumber":"239",
    "addr:postcode":"91502",
    "addr:street":"E Alameda Ave",
    "iso:country":"US",
    "sg:address":"239 E Alameda Ave",
    "sg:city":"Burbank",
    "sg:classifiers":[
        {
            "category":"Building & Trades",
            "subcategory":"Electrical",
            "type":"Services"
        },
        {
            "category":"Wholesale",
            "subcategory":"Electrical",
            "type":"Manufacturing & Wholesale Goods"
        }
    ],
    "sg:phone":"+1 818 557 6461",
    "sg:postcode":"91502",
    "sg:province":"CA",
    "sg:tags":[
        "television",
        "contractor"
    ],
    "sg:website":"www.cbscctv.com",
    "wof:name":"Crime Busters Surveillance",
    "wof:placetype":"venue"
},
  "geometry": {"coordinates":[-118.29765399999999,34.176629],"type":"Point"}
}