{
  "type": "Feature",
  "properties": {
    "addr:full":"8690 Aero Dr San Diego CA 92123",
    "addr:housenumber":"8690",
    "addr:postcode":"92123",
    "addr:street":"Aero Dr",
    "iso:country":"US",
    "sg:address":"8690 Aero Dr",
    "sg:city":"San Diego",
    "sg:classifiers":[
        {
            "category":"Utilities",
            "subcategory":"Telephone",
            "type":"Services"
        }
    ],
    "sg:phone":"+1 619 640 4358",
    "sg:postcode":"92123",
    "sg:province":"CA",
    "sg:tags":[
        "web",
        "design"
    ],
    "wof:name":"Right Connection",
    "wof:placetype":"venue"
},
  "geometry": {"coordinates":[-117.143731,32.809724],"type":"Point"}
}