{
  "type": "Feature",
  "properties": {
    "addr:full":"880 De Long Ave Novato CA 94945",
    "addr:housenumber":"880",
    "addr:postcode":"94945",
    "addr:street":"De Long Ave",
    "iso:country":"US",
    "sg:address":"880 De Long Ave",
    "sg:city":"Novato",
    "sg:classifiers":[
        {
            "category":"Coffee & Tea",
            "type":"Food & Drink"
        }
    ],
    "sg:menulink":"http://www.allmenus.com/ca/northeast-marin/118786-starbucks-coffee/menu/",
    "sg:phone":"+1 415 893 9356",
    "sg:postcode":"94945",
    "sg:province":"CA",
    "sg:tags":[
        "american"
    ],
    "wof:name":"Starbucks Coffee",
    "wof:placetype":"venue"
},
  "geometry": {"coordinates":[-122.569773,38.106082],"type":"Point"}
}