{
  "type": "Feature",
  "properties": {
    "addr:full":"13191 Jurupa Ave Fontana CA 92337",
    "addr:housenumber":"13191",
    "addr:postcode":"92337",
    "addr:street":"Jurupa Ave",
    "iso:country":"US",
    "sg:address":"13191 Jurupa Ave",
    "sg:city":"Fontana",
    "sg:classifiers":[
        {
            "category":"Manufacturing",
            "subcategory":"Rubber & Plastics",
            "type":"Manufacturing & Wholesale Goods"
        }
    ],
    "sg:phone":"+1 951 360 0456",
    "sg:postcode":"92337",
    "sg:province":"CA",
    "sg:tags":[
        "blister",
        "packing",
        "for",
        "mfg"
    ],
    "wof:name":"Alloyd Co of De Kalb Inc",
    "wof:placetype":"venue"
},
  "geometry": {"coordinates":[-117.518658,34.04716],"type":"Point"}
}