{
  "type": "Feature",
  "properties": {
    "iso:country":"US",
    "sg:address":"21100 Pacific Coast Hwy",
    "sg:city":"Huntington Beach",
    "sg:classifiers":[
        {
            "category":"Wholesale",
            "subcategory":"Photographic Equipment",
            "type":"Manufacturing & Wholesale Goods"
        }
    ],
    "sg:phone":"+1 714 969 6902",
    "sg:postcode":"92648",
    "sg:province":"CA",
    "sg:tags":[
        "photo"
    ],
    "wof:name":"Audio Visual Innovations Inc",
    "wof:placetype":"venue"
},
  "geometry": {"coordinates":[-117.99940599999999,33.655468],"type":"Point"}
}