{
  "type": "Feature",
  "properties": {
    "addr:full":"3760 Inland Empire Blvd Ontario CA 91764",
    "addr:postcode":"3760;91764",
    "addr:street":"Empire Blvd",
    "iso:country":"US",
    "sg:address":"3760 Inland Empire Blvd",
    "sg:city":"Ontario",
    "sg:classifiers":[
        {
            "category":"Restaurant",
            "type":"Food & Drink"
        }
    ],
    "sg:menulink":"http://www.allmenus.com/ca/ontario/217090-benihana/menu/",
    "sg:phone":"+1 909 483 0937",
    "sg:postcode":"91764",
    "sg:province":"CA",
    "sg:tags":[
        "american",
        "steakhouse",
        "japanese",
        "asian"
    ],
    "wof:name":"Benihana",
    "wof:placetype":"venue"
},
  "geometry": {"coordinates":[-117.57029300000001,34.068325],"type":"Point"}
}