{
  "type": "Feature",
  "properties": {
    "addr:full":"10795 Wilshire Blvd Los Angeles CA 90024",
    "addr:housenumber":"10795",
    "addr:postcode":"90024",
    "addr:street":"Wilshire Blvd",
    "iso:country":"US",
    "sg:address":"10795 Wilshire Blvd",
    "sg:city":"Los Angeles",
    "sg:classifiers":[
        {
            "category":"Wholesale",
            "subcategory":"Medical Equipment & Supplies",
            "type":"Manufacturing & Wholesale Goods"
        }
    ],
    "sg:phone":"+1 310 253 9197",
    "sg:postcode":"90024",
    "sg:province":"CA",
    "sg:tags":[
        "physician",
        "surgeon"
    ],
    "wof:name":"Oxy-Tech Home Medical Equip",
    "wof:placetype":"venue"
},
  "geometry": {"coordinates":[-118.438411,34.06038],"type":"Point"}
}