{
  "type": "Feature",
  "properties": {
    "addr:full":"4888 Ronson Ct San Diego CA 92111",
    "addr:housenumber":"4888",
    "addr:postcode":"92111",
    "addr:street":"Ronson Ct",
    "iso:country":"US",
    "sg:address":"4888 Ronson Ct",
    "sg:city":"San Diego",
    "sg:classifiers":[
        {
            "category":"Retail",
            "subcategory":"Laundry & Dry Cleaning",
            "type":"Services"
        }
    ],
    "sg:phone":"+1 858 565 6501",
    "sg:postcode":"92111",
    "sg:province":"CA",
    "sg:tags":[
        "cleaners",
        "rug",
        "carpet"
    ],
    "wof:name":"Smitty's LA Jolla Carpet Clnng",
    "wof:placetype":"venue"
},
  "geometry": {"coordinates":[-117.146035,32.829321],"type":"Point"}
}