{
  "type": "Feature",
  "properties": {
    "addr:full":"575 S Main St Bishop CA 93514",
    "addr:housenumber":"575",
    "addr:postcode":"93514",
    "addr:street":"S Main St",
    "iso:country":"US",
    "sg:address":"575 S Main St",
    "sg:city":"Bishop",
    "sg:classifiers":[
        {
            "category":"Restaurant",
            "type":"Food & Drink"
        }
    ],
    "sg:menulink":"http://www.allmenus.com/ca/bishop/178211-jack-in-the-box/menu/",
    "sg:phone":"+1 760 872 1190",
    "sg:postcode":"93514",
    "sg:province":"CA",
    "sg:tags":[
        "burger",
        "american"
    ],
    "wof:name":"Jack in the Box",
    "wof:placetype":"venue"
},
  "geometry": {"coordinates":[-118.39521999999999,37.355914],"type":"Point"}
}