{
  "type": "Feature",
  "properties": {
    "addr:full":"1515 Mountain View Ave Oxnard CA 93030",
    "addr:housenumber":"1515",
    "addr:postcode":"93030",
    "addr:street":"Mountain View Ave",
    "iso:country":"US",
    "sg:address":"1515 Mountain View Ave",
    "sg:city":"Oxnard",
    "sg:classifiers":[
        {
            "category":"Autos & Motor Vehicles",
            "subcategory":"Automobile Sales",
            "type":"Retail Goods"
        },
        {
            "category":"Wholesale",
            "subcategory":"Scrap",
            "type":"Manufacturing & Wholesale Goods"
        },
        {
            "category":"Personal",
            "type":"Services"
        },
        {
            "category":"Retail",
            "subcategory":"Auto Repair",
            "type":"Services"
        },
        {
            "category":"Autos & Motor Vehicles",
            "subcategory":"Auto Supplies",
            "type":"Retail Goods"
        }
    ],
    "sg:phone":"+1 805 483 2276",
    "sg:postcode":"93030",
    "sg:province":"CA",
    "sg:tags":[
        "wrecking",
        "part",
        "towing",
        "truck",
        "salvage",
        "road",
        "service-automotive"
    ],
    "sg:website":"http://oxnardrvstorage.com",
    "wof:name":"Bob's Towing",
    "wof:placetype":"venue"
},
  "geometry": {"coordinates":[-119.164548,34.193459],"type":"Point"}
}