{
  "type": "Feature",
  "properties": {
    "iso:country":"US",
    "sg:address":"14167 Hawthorne Blvd",
    "sg:city":"Hawthorne",
    "sg:classifiers":[
        {
            "category":"Professional",
            "subcategory":"Lawyer & Legal Services",
            "type":"Services"
        }
    ],
    "sg:phone":"+1 310 675 1191",
    "sg:postcode":"90250",
    "sg:province":"CA",
    "sg:tags":[
        "attorney"
    ],
    "wof:name":"Kenneth R Gordon Law Offices",
    "wof:placetype":"venue"
},
  "geometry": {"coordinates":[-118.352373,33.902777],"type":"Point"}
}