{
  "type": "Feature",
  "properties": {
    "iso:country":"US",
    "sg:address":"1801 E Whitmore Ave",
    "sg:city":"Ceres",
    "sg:classifiers":[
        {
            "category":"Retail",
            "subcategory":"Funeral Services",
            "type":"Services"
        }
    ],
    "sg:phone":"+1 209 537 9013",
    "sg:postcode":"95307",
    "sg:province":"CA",
    "sg:tags":[
        "cemetery"
    ],
    "wof:name":"Ceres Cemetery Assn",
    "wof:placetype":"venue"
},
  "geometry": {"coordinates":[-120.962997,37.594799],"type":"Point"}
}