{
  "type": "Feature",
  "properties": {
    "addr:full":"21436 Geyserville Ave Geyserville CA 95441",
    "addr:housenumber":"21436",
    "addr:postcode":"95441",
    "addr:street":"Geyserville Ave",
    "iso:country":"US",
    "sg:address":"21436 Geyserville Ave",
    "sg:city":"Geyserville",
    "sg:classifiers":[
        {
            "category":"Building & Trades",
            "subcategory":"Landscaping Services",
            "type":"Services"
        }
    ],
    "sg:phone":"+1 707 857 3350",
    "sg:postcode":"95441",
    "sg:province":"CA",
    "sg:tags":[
        "tree"
    ],
    "wof:name":"Mahoney's Tree Service",
    "wof:placetype":"venue"
},
  "geometry": {"coordinates":[-122.890862,38.697029],"type":"Point"}
}