{
  "type": "Feature",
  "properties": {
    "addr:full":"14340 Elsworth St Moreno Valley CA 92553",
    "addr:postcode":"14340;92553",
    "addr:street":"Elsworth St",
    "iso:country":"US",
    "sg:address":"14340 Elsworth St",
    "sg:city":"Moreno Valley",
    "sg:classifiers":[
        {
            "category":"Banks & Credit Unions",
            "subcategory":"Financial Services",
            "type":"Services"
        }
    ],
    "sg:phone":"+1 951 653 7710",
    "sg:postcode":"92553",
    "sg:province":"CA",
    "sg:tags":[
        "company",
        "holding"
    ],
    "wof:name":"Wayne Holdings",
    "wof:placetype":"venue"
},
  "geometry": {"coordinates":[-117.270126,33.910168],"type":"Point"}
}