{
  "type": "Feature",
  "properties": {
    "addr:full":"1246 Chrysolite Ave Mentone CA 92359",
    "addr:housenumber":"1246",
    "addr:postcode":"92359",
    "addr:street":"Chrysolite Ave",
    "iso:country":"US",
    "sg:address":"1246 Chrysolite Ave",
    "sg:city":"Mentone",
    "sg:classifiers":[
        {
            "category":"Professional",
            "subcategory":"Business Services",
            "type":"Services"
        }
    ],
    "sg:phone":"+1 951 545 9343",
    "sg:postcode":"92359",
    "sg:province":"CA",
    "sg:tags":[
        "drafting"
    ],
    "wof:name":"Kilday Specialties",
    "wof:placetype":"venue"
},
  "geometry": {"coordinates":[-117.137494,34.069555],"type":"Point"}
}