{
  "type": "Feature",
  "properties": {
    "iso:country":"US",
    "sg:address":"2433 Country Club Blvd",
    "sg:city":"Stockton",
    "sg:classifiers":[
        {
            "category":"Real Estate",
            "subcategory":"Real Estate Operator",
            "type":"Services"
        }
    ],
    "sg:phone":"+1 209 465 2087",
    "sg:postcode":"95204",
    "sg:province":"CA",
    "sg:tags":[
        "apartment"
    ],
    "wof:name":"Krystal Springs Estates",
    "wof:placetype":"venue"
},
  "geometry": {"coordinates":[-121.333465,37.964957],"type":"Point"}
}