{
  "type": "Feature",
  "properties": {
    "addr:full":"175 N Jackson Ave San Jose CA 95116",
    "addr:housenumber":"175",
    "addr:postcode":"95116",
    "addr:street":"N Jackson Ave",
    "iso:country":"US",
    "sg:address":"175 N Jackson Ave",
    "sg:city":"San Jose",
    "sg:classifiers":[
        {
            "category":"Health Services",
            "subcategory":"Doctor",
            "type":"Services"
        }
    ],
    "sg:phone":"+1 408 729 1881",
    "sg:postcode":"95116",
    "sg:province":"CA",
    "sg:tags":[
        "physician",
        "surgeon"
    ],
    "wof:name":"Felix K Tam MD",
    "wof:placetype":"venue"
},
  "geometry": {"coordinates":[-121.84699500000001,37.361797],"type":"Point"}
}