{
  "type": "Feature",
  "properties": {
    "iso:country":"US",
    "sg:address":"14011 Ventura Blvd Ste 406",
    "sg:city":"Sherman Oaks",
    "sg:classifiers":[
        {
            "category":"Professional",
            "subcategory":"Lawyer & Legal Services",
            "type":"Services"
        }
    ],
    "sg:phone":"+1 818 501 0133",
    "sg:postcode":"91423",
    "sg:province":"CA",
    "sg:website":"www.carealestateexpert.com",
    "wof:name":"Wallace Alan D Law Offices of",
    "wof:placetype":"venue"
},
  "geometry": {"coordinates":[-118.43699599999999,34.149101],"type":"Point"}
}