{
  "type": "Feature",
  "properties": {
    "iso:country":"US",
    "sg:address":"12011 Aclare St",
    "sg:city":"Cerritos",
    "sg:classifiers":[
        {
            "category":"Building & Trades",
            "subcategory":"Construction",
            "type":"Services"
        }
    ],
    "sg:phone":"+1 562 924 6741",
    "sg:postcode":"90703",
    "sg:province":"CA",
    "sg:tags":[
        "company"
    ],
    "wof:name":"Pinnacle Construction",
    "wof:placetype":"venue"
},
  "geometry": {"coordinates":[-118.077028,33.874442],"type":"Point"}
}