{
  "type": "Feature",
  "properties": {
    "addr:full":"2728 Cogswell Rd El Monte CA 91732",
    "addr:housenumber":"2728",
    "addr:postcode":"91732",
    "addr:street":"Cogswell Rd",
    "iso:country":"US",
    "sg:address":"2728 Cogswell Rd",
    "sg:city":"El Monte",
    "sg:classifiers":[
        {
            "category":"Professional",
            "type":"Services"
        }
    ],
    "sg:phone":"+1 626 444 2296",
    "sg:postcode":"91732",
    "sg:province":"CA",
    "wof:name":"Maria Garcia",
    "wof:placetype":"venue"
},
  "geometry": {"coordinates":[-118.02306299999999,34.058787],"type":"Point"}
}