{
  "type": "Feature",
  "properties": {
    "iso:country":"US",
    "sg:address":"200 Harrison St",
    "sg:city":"Oakland",
    "sg:classifiers":[
        {
            "category":"Government",
            "subcategory":"City Hall",
            "type":"Public Place"
        },
        {
            "category":"Organizations",
            "subcategory":"Non-profit Organization",
            "type":"Services"
        }
    ],
    "sg:phone":"+1 510 379 1010",
    "sg:postcode":"94607",
    "sg:province":"CA",
    "sg:tags":[
        "community",
        "service/non-profit"
    ],
    "sg:website":"www.covdove.org",
    "wof:name":"Covenant House California",
    "wof:placetype":"venue"
},
  "geometry": {"coordinates":[-122.27233699999999,37.794691],"type":"Point"}
}