{
  "type": "Feature",
  "properties": {
    "iso:country":"US",
    "sg:address":"255 S Pepper Ave",
    "sg:city":"Rialto",
    "sg:classifiers":[
        {
            "category":"Manufacturing",
            "subcategory":"Motor Vehicles & Parts",
            "type":"Manufacturing & Wholesale Goods"
        }
    ],
    "sg:phone":"+1 909 873 3777",
    "sg:postcode":"92376",
    "sg:province":"CA",
    "sg:tags":[
        "travel",
        "mfg"
    ],
    "wof:name":"Forest River Inc",
    "wof:placetype":"venue"
},
  "geometry": {"coordinates":[-117.352845,34.096002],"type":"Point"}
}