{
  "type": "Feature",
  "properties": {
    "iso:country":"US",
    "sg:address":"3021 4th St",
    "sg:city":"Ceres",
    "sg:classifiers":[
        {
            "category":"Autos & Motor Vehicles",
            "subcategory":"Fuel & Gas Station",
            "type":"Retail Goods"
        }
    ],
    "sg:phone":"+1 209 538 4253",
    "sg:postcode":"95307",
    "sg:province":"CA",
    "sg:tags":[
        "oil"
    ],
    "wof:name":"Griffin Shell Food Mart",
    "wof:placetype":"venue"
},
  "geometry": {"coordinates":[-120.95341000000001,37.589421],"type":"Point"}
}