{
  "type": "Feature",
  "properties": {
    "addr:full":"900 34th St Emeryville CA 94608",
    "addr:housenumber":"900",
    "addr:postcode":"94608",
    "addr:street":"34Th St",
    "iso:country":"US",
    "sg:address":"900 34th St",
    "sg:city":"Emeryville",
    "sg:classifiers":[
        {
            "category":"Organizations",
            "subcategory":"Religious Organization",
            "type":"Services"
        }
    ],
    "sg:phone":"+1 510 655 8700",
    "sg:postcode":"94608",
    "sg:province":"CA",
    "sg:tags":[
        "church"
    ],
    "wof:name":"Seventh-Day Adventist Church",
    "wof:placetype":"venue"
},
  "geometry": {"coordinates":[-122.277987,37.825278],"type":"Point"}
}