{
  "type": "Feature",
  "properties": {
    "iso:country":"US",
    "sg:address":"2929 Tapo Canyon Rd",
    "sg:city":"Simi Valley",
    "sg:classifiers":[
        {
            "category":"Building & Trades",
            "subcategory":"Construction",
            "type":"Services"
        }
    ],
    "sg:phone":"+1 805 583 6786",
    "sg:postcode":"93063",
    "sg:province":"CA",
    "sg:tags":[
        "marking",
        "maintenance",
        "parking"
    ],
    "sg:website":"www.simivalley.org",
    "wof:name":"Simi Valley Public Works Dept",
    "wof:placetype":"venue"
},
  "geometry": {"coordinates":[-118.71775700000001,34.288402],"type":"Point"}
}