{
  "type": "Feature",
  "properties": {
    "addr:full":"934 Coral Dr Rodeo CA 94572",
    "addr:housenumber":"934",
    "addr:postcode":"94572",
    "addr:street":"Coral Dr",
    "iso:country":"US",
    "sg:address":"934 Coral Dr",
    "sg:city":"Rodeo",
    "sg:classifiers":[
        {
            "category":"Food & Beverages",
            "subcategory":"Specialty",
            "type":"Retail Goods"
        }
    ],
    "sg:phone":"+1 510 313 0189",
    "sg:postcode":"94572",
    "sg:province":"CA",
    "sg:tags":[
        "sauce",
        "condiment"
    ],
    "wof:name":"Jt Bbq Sauce",
    "wof:placetype":"venue"
},
  "geometry": {"coordinates":[-122.248419,38.023804],"type":"Point"}
}