{
  "type": "Feature",
  "properties": {
    "iso:country":"US",
    "sg:address":"1412 21st St",
    "sg:city":"Sacramento",
    "sg:classifiers":[
        {
            "category":"Shopping",
            "subcategory":"Crafts & Fabrics",
            "type":"Retail Goods"
        }
    ],
    "sg:phone":"+1 916 448 8884",
    "sg:postcode":"95811",
    "sg:province":"CA",
    "sg:tags":[
        "art",
        "supply"
    ],
    "wof:name":"Yellowrock Art Inc",
    "wof:placetype":"venue"
},
  "geometry": {"coordinates":[-121.480769,38.571559],"type":"Point"}
}