{
  "type": "Feature",
  "properties": {
    "addr:full":"4006 Santa Monica Blvd Los Angeles CA 90029",
    "addr:housenumber":"4006",
    "addr:postcode":"90029",
    "addr:street":"Santa Monica Blvd",
    "iso:country":"US",
    "sg:address":"4006 Santa Monica Blvd",
    "sg:city":"Los Angeles",
    "sg:classifiers":[
        {
            "category":"Shopping",
            "subcategory":"Musical Instruments",
            "type":"Retail Goods"
        }
    ],
    "sg:phone":"+1 323 906 9566",
    "sg:postcode":"90029",
    "sg:province":"CA",
    "wof:name":"Silverlake Guitar Shop",
    "wof:placetype":"venue"
},
  "geometry": {"coordinates":[-118.28148400000001,34.092354],"type":"Point"}
}