{
  "type": "Feature",
  "properties": {
    "iso:country":"US",
    "sg:address":"8626 Twana Dr",
    "sg:city":"Garden Grove",
    "sg:classifiers":[
        {
            "category":"Professional",
            "type":"Services"
        }
    ],
    "sg:phone":"+1 714 590 1201",
    "sg:postcode":"92841",
    "sg:province":"CA",
    "wof:name":"Toledo Services",
    "wof:placetype":"venue"
},
  "geometry": {"coordinates":[-117.981392,33.792185],"type":"Point"}
}