{
  "type": "Feature",
  "properties": {
    "iso:country":"US",
    "sg:address":"1302 E Dakota Ave",
    "sg:city":"Fresno",
    "sg:classifiers":[
        {
            "category":"Education",
            "subcategory":"School",
            "type":"Public Place"
        }
    ],
    "sg:phone":"+1 559 248 7100",
    "sg:postcode":"93704",
    "sg:province":"CA",
    "wof:name":"Fort Miller Middle School",
    "wof:placetype":"venue"
},
  "geometry": {"coordinates":[-119.792808,36.786695],"type":"Point"}
}