{
  "type": "Feature",
  "properties": {
    "addr:full":"2394 Big Ranch Rd Napa CA 94558",
    "addr:housenumber":"2394",
    "addr:postcode":"94558",
    "addr:street":"Big Ranch Rd",
    "iso:country":"US",
    "sg:address":"2394 Big Ranch Rd",
    "sg:city":"Napa",
    "sg:classifiers":[
        {
            "category":"Home & Garden",
            "subcategory":"Home Furnishings",
            "type":"Retail Goods"
        }
    ],
    "sg:phone":"+1 707 255 5495",
    "sg:postcode":"94558",
    "sg:province":"CA",
    "wof:name":"Karen Winograde Pottery",
    "wof:placetype":"venue"
},
  "geometry": {"coordinates":[-122.29693899999999,38.34055],"type":"Point"}
}