{
  "type": "Feature",
  "properties": {
    "addr:full":"326 W Main St Santa Maria CA 93458",
    "addr:housenumber":"326",
    "addr:postcode":"93458",
    "addr:street":"W Main St",
    "iso:country":"US",
    "sg:address":"326 W Main St",
    "sg:city":"Santa Maria",
    "sg:classifiers":[
        {
            "category":"Health Services",
            "subcategory":"Doctor",
            "type":"Services"
        }
    ],
    "sg:phone":"+1 805 349 0748",
    "sg:postcode":"93458",
    "sg:province":"CA",
    "sg:tags":[
        "dentist"
    ],
    "wof:name":"Mathilde Houser DDS",
    "wof:placetype":"venue"
},
  "geometry": {"coordinates":[-120.439291,34.953034],"type":"Point"}
}