{
  "type": "Feature",
  "properties": {
    "iso:country":"US",
    "sg:address":"3006 E Coronado St",
    "sg:city":"Anaheim",
    "sg:classifiers":[
        {
            "category":"Manufacturing",
            "subcategory":"Buildings",
            "type":"Manufacturing & Wholesale Goods"
        },
        {
            "category":"Manufacturing",
            "subcategory":"Metals",
            "type":"Manufacturing & Wholesale Goods"
        },
        {
            "category":"Building & Trades",
            "subcategory":"Construction",
            "type":"Services"
        }
    ],
    "sg:phone":"+1 323 567 2255",
    "sg:postcode":"92806",
    "sg:province":"CA",
    "sg:tags":[
        "steel",
        "industrial",
        "contractors-commercial",
        "erectors"
    ],
    "wof:name":"Pre-Fab Erectors Inc",
    "wof:placetype":"venue"
},
  "geometry": {"coordinates":[-117.86234399999999,33.853627],"type":"Point"}
}