{
  "type": "Feature",
  "properties": {
    "iso:country":"US",
    "sg:address":"6576 Trigo Rd",
    "sg:city":"Goleta",
    "sg:classifiers":[
        {
            "category":"Restaurant",
            "type":"Food & Drink"
        }
    ],
    "sg:phone":"+1 805 685 1183",
    "sg:postcode":"93117",
    "sg:province":"CA",
    "wof:name":"Cafe Nirvana",
    "wof:placetype":"venue"
},
  "geometry": {"coordinates":[-119.857915,34.411218],"type":"Point"}
}