{
  "type": "Feature",
  "properties": {
    "addr:full":"835 Mead Ave Oakland CA 94607",
    "addr:housenumber":"835",
    "addr:postcode":"94607",
    "addr:street":"Mead Ave",
    "iso:country":"US",
    "sg:address":"835 Mead Ave",
    "sg:city":"Oakland",
    "sg:classifiers":[
        {
            "category":"Place Of Worship",
            "subcategory":"Church",
            "type":"Public Place"
        },
        {
            "category":"Place Of Worship",
            "type":"Public Place"
        }
    ],
    "sg:phone":"+1 510 251 9700",
    "sg:postcode":"94607",
    "sg:province":"CA",
    "sg:tags":[
        "churches-interdenominational",
        "churches-various",
        "denomination"
    ],
    "wof:name":"First Mongolian Christian Church",
    "wof:placetype":"venue"
},
  "geometry": {"coordinates":[-122.277545,37.815974],"type":"Point"}
}