{
  "type": "Feature",
  "properties": {
    "iso:country":"US",
    "sg:address":"3263 E Thousand Oaks Blvd",
    "sg:city":"Thousand Oaks",
    "sg:classifiers":[
        {
            "category":"Banks & Credit Unions",
            "subcategory":"Bank",
            "type":"Services"
        }
    ],
    "sg:phone":"+1 805 494 1027",
    "sg:postcode":"91362",
    "sg:province":"CA",
    "sg:tags":[
        "escrow"
    ],
    "wof:name":"All Valley Escrow",
    "wof:placetype":"venue"
},
  "geometry": {"coordinates":[-118.835498,34.168805],"type":"Point"}
}