{
  "type": "Feature",
  "properties": {
    "addr:full":"20944 Bloomfield Ave Lakewood CA 90715",
    "addr:housenumber":"20944",
    "addr:postcode":"90715",
    "addr:street":"Bloomfield Ave",
    "iso:country":"US",
    "sg:address":"20944 Bloomfield Ave",
    "sg:city":"Lakewood",
    "sg:classifiers":[
        {
            "category":"Retail",
            "subcategory":"Laundry & Dry Cleaning",
            "type":"Services"
        }
    ],
    "sg:phone":"+1 562 865 3398",
    "sg:postcode":"90715",
    "sg:province":"CA",
    "wof:name":"Town Cleaners",
    "wof:placetype":"venue"
},
  "geometry": {"coordinates":[-118.06300400000001,33.839001],"type":"Point"}
}