{
  "type": "Feature",
  "properties": {
    "addr:full":"524 San Anselmo Ave San Anselmo CA 94960",
    "addr:housenumber":"524",
    "addr:postcode":"94960",
    "addr:street":"San Anselmo Ave",
    "iso:country":"US",
    "sg:address":"524 San Anselmo Ave",
    "sg:city":"San Anselmo",
    "sg:classifiers":[
        {
            "category":"Professional",
            "type":"Services"
        }
    ],
    "sg:phone":"+1 415 459 1224",
    "sg:postcode":"94960",
    "sg:province":"CA",
    "wof:name":"Vicki Barth Planning",
    "wof:placetype":"venue"
},
  "geometry": {"coordinates":[-122.562271,37.974303],"type":"Point"}
}