{
  "type": "Feature",
  "properties": {
    "iso:country":"US",
    "sg:address":"1190 Miraloma Way Ste N",
    "sg:city":"Sunnyvale",
    "sg:classifiers":[
        {
            "category":"Wholesale",
            "subcategory":"Medical Equipment & Supplies",
            "type":"Manufacturing & Wholesale Goods"
        }
    ],
    "sg:phone":"+1 408 733 4337",
    "sg:postcode":"94085",
    "sg:province":"CA",
    "sg:tags":[
        "machine",
        "discharge",
        "electrical"
    ],
    "wof:name":"J & L E D M",
    "wof:placetype":"venue"
},
  "geometry": {"coordinates":[-121.99748099999999,37.378617],"type":"Point"}
}