{
  "type": "Feature",
  "properties": {
    "addr:full":"1094 Seely Pl Simi Valley CA 93065",
    "addr:housenumber":"1094",
    "addr:postcode":"93065",
    "addr:street":"Seely Pl",
    "iso:country":"US",
    "sg:address":"1094 Seely Pl",
    "sg:city":"Simi Valley",
    "sg:classifiers":[
        {
            "category":"Personal",
            "subcategory":"Beauty Salon",
            "type":"Services"
        }
    ],
    "sg:phone":"+1 805 955 0831",
    "sg:postcode":"93065",
    "sg:province":"CA",
    "sg:tags":[
        "consultant",
        "health"
    ],
    "wof:name":"Avon By Deanna",
    "wof:placetype":"venue"
},
  "geometry": {"coordinates":[-118.77873200000001,34.250984],"type":"Point"}
}