{
  "type": "Feature",
  "properties": {
    "addr:full":"440 Westlake Ctr Daly City CA 94015",
    "addr:housenumber":"440",
    "addr:postcode":"94015",
    "addr:street":"Westlake Ctr",
    "iso:country":"US",
    "sg:address":"440 Westlake Ctr",
    "sg:city":"Daly City",
    "sg:classifiers":[
        {
            "category":"Health Services",
            "subcategory":"Optometrist",
            "type":"Services"
        }
    ],
    "sg:phone":"+1 650 756 4000",
    "sg:postcode":"94015",
    "sg:province":"CA",
    "wof:name":"Respicio S Gabriel O D",
    "wof:placetype":"venue"
},
  "geometry": {"coordinates":[-122.48305999999999,37.700887],"type":"Point"}
}