{
  "type": "Feature",
  "properties": {
    "iso:country":"US",
    "sg:address":"700 Larkspur Landing Cir",
    "sg:city":"Larkspur",
    "sg:classifiers":[
        {
            "category":"Professional",
            "subcategory":"Lawyer & Legal Services",
            "type":"Services"
        }
    ],
    "sg:phone":"+1 415 464 2000",
    "sg:postcode":"94939",
    "sg:province":"CA",
    "sg:tags":[
        "attorney"
    ],
    "wof:name":"Buell & Berner",
    "wof:placetype":"venue"
},
  "geometry": {"coordinates":[-122.507913,37.947638],"type":"Point"}
}