{
  "type": "Feature",
  "properties": {
    "iso:country":"US",
    "sg:address":"2375 Moorpark Ave",
    "sg:city":"San Jose",
    "sg:classifiers":[
        {
            "category":"Shopping",
            "subcategory":"Computers & Home Electronics",
            "type":"Retail Goods"
        }
    ],
    "sg:phone":"+1 408 568 2233",
    "sg:postcode":"95128",
    "sg:province":"CA",
    "sg:tags":[
        "equipment",
        "satellite",
        "system"
    ],
    "wof:name":"Stargate Satellite",
    "wof:placetype":"venue"
},
  "geometry": {"coordinates":[-121.935132,37.316184],"type":"Point"}
}