{
  "type": "Feature",
  "properties": {
    "iso:country":"US",
    "sg:address":"650 W 5th St",
    "sg:city":"Los Angeles",
    "sg:classifiers":[
        {
            "category":"Food & Beverages",
            "subcategory":"Farmers Market",
            "type":"Retail Goods"
        }
    ],
    "sg:phone":"+1 818 591 8161",
    "sg:postcode":"90189",
    "sg:province":"CA",
    "sg:website":"www.ccfm.com",
    "wof:name":"Downtown Los Angeles Farmer's Market",
    "wof:placetype":"venue"
},
  "geometry": {"coordinates":[-118.254467,34.050537],"type":"Point"}
}