{
  "type": "Feature",
  "properties": {
    "iso:country":"US",
    "sg:address":"29814 Hasley Canyon Rd",
    "sg:city":"Santa Clarita",
    "sg:classifiers":[
        {
            "category":"Education",
            "subcategory":"Kindergarten",
            "type":"Public Place"
        }
    ],
    "sg:phone":"+1 661 799 3312",
    "sg:postcode":"91384",
    "sg:province":"CA",
    "sg:tags":[
        "school",
        "driving"
    ],
    "wof:name":"Alltime Traffic School",
    "wof:placetype":"venue"
},
  "geometry": {"coordinates":[-118.65512200000001,34.46024],"type":"Point"}
}