{
  "type": "Feature",
  "properties": {
    "addr:full":"6521 Simson St Oakland CA 94605",
    "addr:postcode":"6521;94605",
    "addr:street":"Simson St",
    "iso:country":"US",
    "sg:address":"6521 Simson St",
    "sg:city":"Oakland",
    "sg:classifiers":[
        {
            "category":"Shopping",
            "subcategory":"Luggage & Leather Goods",
            "type":"Retail Goods"
        }
    ],
    "sg:phone":"+1 510 635 9620",
    "sg:postcode":"94605",
    "sg:province":"CA",
    "sg:tags":[
        "case"
    ],
    "wof:name":"Mango Productions Inc",
    "wof:placetype":"venue"
},
  "geometry": {"coordinates":[-122.173996,37.776573],"type":"Point"}
}