{
  "type": "Feature",
  "properties": {
    "iso:country":"US",
    "sg:address":"3200 College Ave",
    "sg:city":"Berkeley",
    "sg:classifiers":[
        {
            "category":"Social Services",
            "type":"Services"
        },
        {
            "category":"Professional",
            "subcategory":"Employment Agencies",
            "type":"Services"
        }
    ],
    "sg:phone":"+1 510 428 1400",
    "sg:postcode":"94705",
    "sg:province":"CA",
    "sg:tags":[
        "workers'",
        "placement",
        "volunteer"
    ],
    "wof:name":"The Richard Diebenkorn Foundation",
    "wof:placetype":"venue"
},
  "geometry": {"coordinates":[-122.252472,37.851269],"type":"Point"}
}