{
  "type": "Feature",
  "properties": {
    "addr:full":"12815 Imperial Hwy Santa Fe Springs CA 90650",
    "addr:housenumber":"12815",
    "addr:postcode":"90650",
    "addr:street":"Imperial Hwy",
    "iso:country":"US",
    "sg:address":"12815 Imperial Hwy",
    "sg:city":"Santa Fe Springs",
    "sg:classifiers":[
        {
            "category":"Utilities",
            "subcategory":"Refuse",
            "type":"Services"
        }
    ],
    "sg:phone":"+1 562 906 5223",
    "sg:postcode":"90650",
    "sg:province":"CA",
    "sg:tags":[
        "recycling"
    ],
    "wof:name":"GREENCYCLE",
    "wof:placetype":"venue"
},
  "geometry": {"coordinates":[-118.05849600000001,33.917125],"type":"Point"}
}