{
  "type": "Feature",
  "properties": {
    "addr:full":"3020 N Pacific Ave Stockton CA 95204",
    "addr:housenumber":"3020",
    "addr:postcode":"95204",
    "addr:street":"N Pacific Ave",
    "iso:country":"US",
    "sg:address":"3020 N Pacific Ave",
    "sg:city":"Stockton",
    "sg:classifiers":[
        {
            "category":"Health Services",
            "subcategory":"Doctor",
            "type":"Services"
        }
    ],
    "sg:phone":"+1 209 943 0323",
    "sg:postcode":"95204",
    "sg:province":"CA",
    "sg:tags":[
        "dentist"
    ],
    "wof:name":"Dale E Stocking DDS",
    "wof:placetype":"venue"
},
  "geometry": {"coordinates":[-121.305317,37.978285],"type":"Point"}
}