{
  "type": "Feature",
  "properties": {
    "iso:country":"US",
    "sg:address":"1721 S Broadway",
    "sg:city":"Santa Maria",
    "sg:classifiers":[
        {
            "category":"Wholesale",
            "subcategory":"Groceries",
            "type":"Manufacturing & Wholesale Goods"
        }
    ],
    "sg:phone":"+1 805 925 6730",
    "sg:postcode":"93454",
    "sg:province":"CA",
    "sg:tags":[
        "grocer"
    ],
    "sg:website":"www.smartandfinal.com",
    "wof:name":"Smart & Final",
    "wof:placetype":"venue"
},
  "geometry": {"coordinates":[-120.436189,34.929261],"type":"Point"}
}