{
  "type": "Feature",
  "properties": {
    "iso:country":"US",
    "sg:address":"35430 Rd 124",
    "sg:city":"Visalia",
    "sg:classifiers":[
        {
            "category":"Farming",
            "subcategory":"Farm & Veterinary Services",
            "type":"Manufacturing & Wholesale Goods"
        }
    ],
    "sg:phone":"+1 559 732 2992",
    "sg:postcode":"93291",
    "sg:province":"CA",
    "sg:tags":[
        "crop",
        "harvesting"
    ],
    "wof:name":"Joe Giannandrea",
    "wof:placetype":"venue"
},
  "geometry": {"coordinates":[-119.295735,36.433217],"type":"Point"}
}