{
  "type": "Feature",
  "properties": {
    "addr:full":"1701 Bush St #3 San Francisco CA 94109",
    "addr:housenumber":"1701",
    "addr:postcode":"94109",
    "addr:street":"Bush St # 3",
    "iso:country":"US",
    "sg:address":"1701 Bush St #3",
    "sg:city":"San Francisco",
    "sg:classifiers":[
        {
            "category":"Building & Trades",
            "subcategory":"Construction",
            "type":"Services"
        }
    ],
    "sg:phone":"+1 415 902 6991",
    "sg:postcode":"94109",
    "sg:province":"CA",
    "sg:tags":[
        "painter"
    ],
    "sg:website":"bruceparsley@mac.com",
    "wof:name":"Bruce Parsley",
    "wof:placetype":"venue"
},
  "geometry": {"coordinates":[-122.425558,37.787873],"type":"Point"}
}