{
  "type": "Feature",
  "properties": {
    "addr:full":"2125 Anda Lucia Way Oceanside CA 92056",
    "addr:housenumber":"2125",
    "addr:postcode":"92056",
    "addr:street":"Anda Lucia Way",
    "iso:country":"US",
    "sg:address":"2125 Anda Lucia Way",
    "sg:city":"Oceanside",
    "sg:classifiers":[
        {
            "category":"Manufacturing",
            "subcategory":"Retail Goods",
            "type":"Manufacturing & Wholesale Goods"
        }
    ],
    "sg:phone":"+1 760 722 4648",
    "sg:postcode":"92056",
    "sg:province":"CA",
    "sg:tags":[
        "product",
        "mfg"
    ],
    "wof:name":"Krt Industries",
    "wof:placetype":"venue"
},
  "geometry": {"coordinates":[-117.311752,33.192427],"type":"Point"}
}