{
  "type": "Feature",
  "properties": {
    "addr:full":"107 S Garfield Ave Alhambra CA 91801",
    "addr:housenumber":"107",
    "addr:postcode":"91801",
    "addr:street":"S Garfield Ave",
    "iso:country":"US",
    "sg:address":"107 S Garfield Ave",
    "sg:city":"Alhambra",
    "sg:classifiers":[
        {
            "category":"Recreation",
            "type":"Entertainment"
        }
    ],
    "sg:phone":"+1 626 289 5151",
    "sg:postcode":"91801",
    "sg:province":"CA",
    "sg:tags":[
        "gym",
        "instruction",
        "gymnastic"
    ],
    "sg:website":"www.paykegymnastics.com",
    "wof:name":"Payke Gymnastics Academy",
    "wof:placetype":"venue"
},
  "geometry": {"coordinates":[-118.12599899999999,34.094101],"type":"Point"}
}