{
  "type": "Feature",
  "properties": {
    "addr:full":"923 Valencia St San Francisco CA 94110",
    "addr:housenumber":"923",
    "addr:postcode":"94110",
    "addr:street":"Valencia St",
    "iso:country":"US",
    "sg:address":"923 Valencia St",
    "sg:city":"San Francisco",
    "sg:classifiers":[
        {
            "category":"Retail",
            "subcategory":"Auto Repair",
            "type":"Services"
        }
    ],
    "sg:phone":"+1 415 285 1547",
    "sg:postcode":"94110",
    "sg:province":"CA",
    "sg:tags":[
        "body",
        "shop"
    ],
    "wof:name":"Consumers Auto Body & Repair",
    "wof:placetype":"venue"
},
  "geometry": {"coordinates":[-122.420931,37.758115],"type":"Point"}
}