{
  "type": "Feature",
  "properties": {
    "iso:country":"US",
    "sg:address":"2417 E Main St",
    "sg:city":"Visalia",
    "sg:classifiers":[
        {
            "category":"Restaurant",
            "type":"Food & Drink"
        }
    ],
    "sg:phone":"+1 559 679 4254",
    "sg:postcode":"93292",
    "sg:province":"CA",
    "sg:tags":[
        "barbecue"
    ],
    "wof:name":"Piggin Out Southern Bbq",
    "wof:placetype":"venue"
},
  "geometry": {"coordinates":[-119.265044,36.328562],"type":"Point"}
}