{
  "type": "Feature",
  "properties": {
    "addr:full":"1130 N Main St Orange CA 92867",
    "addr:housenumber":"1130",
    "addr:postcode":"92867",
    "addr:street":"N Main St",
    "iso:country":"US",
    "sg:address":"1130 N Main St",
    "sg:city":"Orange",
    "sg:classifiers":[
        {
            "category":"Manufacturing",
            "subcategory":"Printing",
            "type":"Manufacturing & Wholesale Goods"
        }
    ],
    "sg:phone":"+1 714 997 7390",
    "sg:postcode":"92867",
    "sg:province":"CA",
    "sg:tags":[
        "commercial"
    ],
    "sg:website":"www.wedographics.com",
    "wof:name":"We Do Graphics",
    "wof:placetype":"venue"
},
  "geometry": {"coordinates":[-117.867133,33.808206],"type":"Point"}
}