{
  "type": "Feature",
  "properties": {
    "addr:full":"3203 Del Mar Ave Suite #B-2 Rosemead CA 91770",
    "addr:housenumber":"3203",
    "addr:postcode":"91770",
    "addr:street":"Del Mar Ave Suite # B-2",
    "iso:country":"US",
    "sg:address":"3203 Del Mar Ave Suite #B-2",
    "sg:city":"Rosemead",
    "sg:classifiers":[
        {
            "category":"Professional",
            "subcategory":"Accounting & Tax Preparation",
            "type":"Services"
        }
    ],
    "sg:phone":"+1 626 288 0982",
    "sg:postcode":"91770",
    "sg:province":"CA",
    "sg:tags":[
        "accountant"
    ],
    "wof:name":"Acer Tax & Accounting",
    "wof:placetype":"venue"
},
  "geometry": {"coordinates":[-118.09979800000001,34.066422],"type":"Point"}
}