{
  "type": "Feature",
  "properties": {
    "iso:country":"US",
    "sg:address":"1424 N Market Blvd",
    "sg:city":"Sacramento",
    "sg:classifiers":[
        {
            "category":"Wholesale",
            "subcategory":"Construction Materials",
            "type":"Manufacturing & Wholesale Goods"
        }
    ],
    "sg:phone":"+1 916 419 4560",
    "sg:postcode":"95834",
    "sg:province":"CA",
    "sg:tags":[
        "marketing",
        "lumber"
    ],
    "wof:name":"Merillat Industries Inc",
    "wof:placetype":"venue"
},
  "geometry": {"coordinates":[-121.502106,38.646558],"type":"Point"}
}