{
  "type": "Feature",
  "properties": {
    "iso:country":"US",
    "sg:address":"1049 Cam del Mar",
    "sg:city":"Del Mar",
    "sg:classifiers":[
        {
            "category":"Shopping",
            "subcategory":"Clothing, Apparel, & Fashions",
            "type":"Retail Goods"
        }
    ],
    "sg:phone":"+1 858 755 1312",
    "sg:postcode":"92014",
    "sg:province":"CA",
    "sg:tags":[
        "tailor"
    ],
    "wof:name":"Golden Needle Tailors",
    "wof:placetype":"venue"
},
  "geometry": {"coordinates":[-117.086276,33.144889],"type":"Point"}
}