{
  "type": "Feature",
  "properties": {
    "iso:country":"US",
    "sg:address":"8829 National Blvd",
    "sg:city":"Culver City",
    "sg:classifiers":[
        {
            "category":"Professional",
            "subcategory":"Management & Consulting",
            "type":"Services"
        }
    ],
    "sg:phone":"+1 310 839 0308",
    "sg:postcode":"90232",
    "sg:province":"CA",
    "sg:tags":[
        "consultant",
        "business"
    ],
    "wof:name":"Leo Wolf Consultants",
    "wof:placetype":"venue"
},
  "geometry": {"coordinates":[-118.38776,34.029064],"type":"Point"}
}