{
  "type": "Feature",
  "properties": {
    "iso:country":"US",
    "sg:address":"2686 Hilltop Dr",
    "sg:city":"Redding",
    "sg:classifiers":[
        {
            "category":"Home & Garden",
            "subcategory":"Building Materials",
            "type":"Retail Goods"
        }
    ],
    "sg:phone":"+1 530 221 8629",
    "sg:postcode":"96002",
    "sg:province":"CA",
    "sg:tags":[
        "paint"
    ],
    "wof:name":"Kelley-Moore Paint Co",
    "wof:placetype":"venue"
},
  "geometry": {"coordinates":[-122.35818399999999,40.570433],"type":"Point"}
}