{
  "type": "Feature",
  "properties": {
    "iso:country":"US",
    "sg:address":"2165A Union St",
    "sg:city":"San Francisco",
    "sg:classifiers":[
        {
            "category":"Personal",
            "subcategory":"Hair Removal",
            "type":"Services"
        },
        {
            "category":"Personal",
            "subcategory":"Skin Care",
            "type":"Services"
        },
        {
            "category":"Personal",
            "subcategory":"Day Spa",
            "type":"Services"
        }
    ],
    "sg:phone":"+1 415 931 7318",
    "sg:postcode":"94123",
    "sg:province":"CA",
    "sg:website":"www.gunillaskinbutik.com",
    "wof:name":"Gunilla Skin Butik",
    "wof:placetype":"venue"
},
  "geometry": {"coordinates":[-122.434952,37.797139],"type":"Point"}
}