{
  "type": "Feature",
  "properties": {
    "addr:full":"12875 Mountain Ave Chino CA 91710",
    "addr:housenumber":"12875",
    "addr:postcode":"91710",
    "addr:street":"Mountain Ave",
    "iso:country":"US",
    "sg:address":"12875 Mountain Ave",
    "sg:city":"Chino",
    "sg:classifiers":[
        {
            "category":"Health Services",
            "subcategory":"Doctor",
            "type":"Services"
        }
    ],
    "sg:phone":"+1 909 591 0316",
    "sg:postcode":"91710",
    "sg:province":"CA",
    "sg:tags":[
        "dentist"
    ],
    "wof:name":"Chino Family Dental Practice",
    "wof:placetype":"venue"
},
  "geometry": {"coordinates":[-117.667478,34.020943],"type":"Point"}
}