{
  "type": "Feature",
  "properties": {
    "iso:country":"US",
    "sg:address":"150 3rd St",
    "sg:city":"Lakeport",
    "sg:classifiers":[
        {
            "category":"Real Estate",
            "subcategory":"Surveying",
            "type":"Services"
        }
    ],
    "sg:phone":"+1 707 263 5512",
    "sg:postcode":"95453",
    "sg:province":"CA",
    "sg:tags":[
        "surveyor"
    ],
    "wof:name":"Conser Land Surveying",
    "wof:placetype":"venue"
},
  "geometry": {"coordinates":[-122.91567499999999,39.043978],"type":"Point"}
}