{
  "type": "Feature",
  "properties": {
    "addr:full":"5431 Auburn Blvd Ste 161 Sacramento CA 95841",
    "addr:housenumber":"5431",
    "addr:postcode":"95841",
    "addr:street":"Auburn Blvd Ste 161",
    "iso:country":"US",
    "sg:address":"5431 Auburn Blvd Ste 161",
    "sg:city":"Sacramento",
    "sg:classifiers":[
        {
            "category":"Building & Trades",
            "subcategory":"Construction",
            "type":"Services"
        }
    ],
    "sg:phone":"+1 916 271 4328",
    "sg:postcode":"95841",
    "sg:province":"CA",
    "sg:tags":[
        "roofing",
        "contractor"
    ],
    "sg:website":"www.miketheroofguy.com",
    "wof:name":"Kemp Construction",
    "wof:placetype":"venue"
},
  "geometry": {"coordinates":[-121.338521,38.667722],"type":"Point"}
}