{
  "type": "Feature",
  "properties": {
    "iso:country":"US",
    "sg:address":"2669 Triangle Rd",
    "sg:city":"Mariposa",
    "sg:classifiers":[
        {
            "category":"Travel",
            "subcategory":"Hotels & Motels",
            "type":"Entertainment"
        }
    ],
    "sg:phone":"+1 209 966 3843",
    "sg:postcode":"95338",
    "sg:province":"CA",
    "sg:tags":[
        "breakfast",
        "accommodation",
        "bed"
    ],
    "wof:name":"Meadow Creek Ranch Bed & Bkfst",
    "wof:placetype":"venue"
},
  "geometry": {"coordinates":[-119.80654800000001,37.474759],"type":"Point"}
}