{
  "type": "Feature",
  "properties": {
    "iso:country":"US",
    "sg:address":"5747 Hoback Glen Rd",
    "sg:city":"Hidden Hills",
    "sg:classifiers":[
        {
            "category":"Professional",
            "subcategory":"Lawyer & Legal Services",
            "type":"Services"
        }
    ],
    "sg:phone":"+1 818 226 4040",
    "sg:postcode":"91302",
    "sg:province":"CA",
    "sg:tags":[
        "attorney"
    ],
    "wof:name":"Michael T Stoller Law Offices",
    "wof:placetype":"venue"
},
  "geometry": {"coordinates":[-118.659254,34.163858],"type":"Point"}
}