{
  "type": "Feature",
  "properties": {
    "addr:full":"529 W Bardsley Ave Tulare CA 93274",
    "addr:housenumber":"529",
    "addr:postcode":"93274",
    "addr:street":"W Bardsley Ave",
    "iso:country":"US",
    "sg:address":"529 W Bardsley Ave",
    "sg:city":"Tulare",
    "sg:classifiers":[
        {
            "category":"Professional",
            "subcategory":"Accounting & Tax Preparation",
            "type":"Services"
        },
        {
            "category":"Banks & Credit Unions",
            "subcategory":"Financial Services",
            "type":"Services"
        }
    ],
    "sg:phone":"+1 559 686 3209",
    "sg:postcode":"93274",
    "sg:province":"CA",
    "sg:tags":[
        "return",
        "preparation-business",
        "taxes-consultants",
        "loan",
        "reporting",
        "representative",
        "alternative",
        "bookkeeping"
    ],
    "sg:website":"http://www.hrblock.com",
    "wof:name":"H&R Block",
    "wof:placetype":"venue"
},
  "geometry": {"coordinates":[-119.35377099999999,36.196477],"type":"Point"}
}