{
  "type": "Feature",
  "properties": {
    "iso:country":"US",
    "sg:address":"3350 East 7th Street",
    "sg:city":"Long Beach",
    "sg:classifiers":[
        {
            "category":"Building & Trades",
            "subcategory":"Construction",
            "type":"Services"
        }
    ],
    "sg:phone":"+1 562 382 6191",
    "sg:postcode":"90804",
    "sg:province":"CA",
    "sg:tags":[
        "contractor"
    ],
    "wof:name":"Garage Door Company Long Beach",
    "wof:placetype":"venue"
},
  "geometry": {"coordinates":[-118.152629,33.775317],"type":"Point"}
}