{
  "type": "Feature",
  "properties": {
    "addr:full":"4405 Rocky Canyon Rd Atascadero CA 93422",
    "addr:housenumber":"4405",
    "addr:postcode":"93422",
    "addr:street":"Rocky Canyon Rd",
    "iso:country":"US",
    "sg:address":"4405 Rocky Canyon Rd",
    "sg:city":"Atascadero",
    "sg:classifiers":[
        {
            "category":"Farming",
            "subcategory":"Livestock Farm",
            "type":"Manufacturing & Wholesale Goods"
        }
    ],
    "sg:phone":"+1 805 466 2774",
    "sg:postcode":"93422",
    "sg:province":"CA",
    "sg:tags":[
        "equine"
    ],
    "wof:name":"Rolling A Ranch",
    "wof:placetype":"venue"
},
  "geometry": {"coordinates":[-120.644667,35.493837],"type":"Point"}
}