{
  "type": "Feature",
  "properties": {
    "iso:country":"US",
    "sg:address":"1010 W Whitesbridge Ave",
    "sg:city":"Fresno",
    "sg:classifiers":[
        {
            "category":"Professional",
            "subcategory":"Engineering",
            "type":"Services"
        }
    ],
    "sg:phone":"+1 559 265 4711",
    "sg:postcode":"93706",
    "sg:province":"CA",
    "sg:tags":[
        "general",
        "contractor"
    ],
    "wof:name":"Vulcan Construction & Mntce",
    "wof:placetype":"venue"
},
  "geometry": {"coordinates":[-119.826364,36.735868],"type":"Point"}
}