{
  "type": "Feature",
  "properties": {
    "iso:country":"US",
    "sg:address":"1501 5th St",
    "sg:city":"Oakland",
    "sg:classifiers":[
        {
            "category":"Personal",
            "subcategory":"Beauty Salon",
            "type":"Services"
        }
    ],
    "sg:phone":"+1 510 986 1686",
    "sg:postcode":"94607",
    "sg:province":"CA",
    "wof:name":"Theresa's Beauty Salon",
    "wof:placetype":"venue"
},
  "geometry": {"coordinates":[-122.297535,37.80459],"type":"Point"}
}