{
  "type": "Feature",
  "properties": {
    "addr:full":"8331 Wheatland Ave Sun Valley CA 91352",
    "addr:housenumber":"8331",
    "addr:postcode":"91352",
    "addr:street":"Wheatland Ave",
    "iso:country":"US",
    "sg:address":"8331 Wheatland Ave",
    "sg:city":"Sun Valley",
    "sg:classifiers":[
        {
            "category":"Utilities",
            "subcategory":"Refuse",
            "type":"Services"
        }
    ],
    "sg:phone":"+1 818 768 5734",
    "sg:postcode":"91352",
    "sg:province":"CA",
    "sg:tags":[
        "garbage",
        "collection"
    ],
    "sg:website":"www.larrytherubbishman.com",
    "wof:name":"Larry-The Rubbish Man",
    "wof:placetype":"venue"
},
  "geometry": {"coordinates":[-118.361844,34.222774],"type":"Point"}
}