{
  "type": "Feature",
  "properties": {
    "addr:full":"13947 Foothill Blvd Sylmar CA 91342",
    "addr:housenumber":"13947",
    "addr:postcode":"91342",
    "addr:street":"Foothill Blvd",
    "iso:country":"US",
    "sg:address":"13947 Foothill Blvd",
    "sg:city":"Sylmar",
    "sg:classifiers":[
        {
            "category":"Personal",
            "subcategory":"Beauty Salon",
            "type":"Services"
        }
    ],
    "sg:phone":"+1 818 367 6731",
    "sg:postcode":"91342",
    "sg:province":"CA",
    "sg:tags":[
        "manicuring"
    ],
    "wof:name":"Beautiful Nails",
    "wof:placetype":"venue"
},
  "geometry": {"coordinates":[-118.440774,34.315552],"type":"Point"}
}