{
  "type": "Feature",
  "properties": {
    "addr:full":"7230 Medical Center Dr West Hills CA 91307",
    "addr:housenumber":"7230",
    "addr:postcode":"91307",
    "addr:street":"Medical Center Dr",
    "iso:country":"US",
    "sg:address":"7230 Medical Center Dr",
    "sg:city":"West Hills",
    "sg:classifiers":[
        {
            "category":"Health Services",
            "subcategory":"Health Practitioner",
            "type":"Services"
        }
    ],
    "sg:phone":"+1 818 715 9517",
    "sg:postcode":"91307",
    "sg:province":"CA",
    "sg:tags":[
        "nutritionist"
    ],
    "wof:name":"Kimberly Shapira",
    "wof:placetype":"venue"
},
  "geometry": {"coordinates":[-118.62938699999999,34.203036],"type":"Point"}
}