{
  "type": "Feature",
  "properties": {
    "addr:full":"338 W 40th St San Bernardino CA 92405",
    "addr:housenumber":"338",
    "addr:postcode":"92405",
    "addr:street":"W 40Th St",
    "iso:country":"US",
    "sg:address":"338 W 40th St",
    "sg:city":"San Bernardino",
    "sg:classifiers":[
        {
            "category":"Building & Trades",
            "subcategory":"Cleaning & Sanitation",
            "type":"Services"
        }
    ],
    "sg:phone":"+1 909 708 4341",
    "sg:postcode":"92405",
    "sg:province":"CA",
    "sg:tags":[
        "home"
    ],
    "sg:website":"www.crimescenecleanupsanbernardi...",
    "wof:name":"Crime Scene Clean Up",
    "wof:placetype":"venue"
},
  "geometry": {"coordinates":[-117.289782,34.16468],"type":"Point"}
}