{
  "type": "Feature",
  "properties": {
    "addr:full":"1455 School House Rd Santa Barbara CA 93108",
    "addr:housenumber":"1455",
    "addr:postcode":"93108",
    "addr:street":"School House Rd",
    "iso:country":"US",
    "sg:address":"1455 School House Rd",
    "sg:city":"Santa Barbara",
    "sg:classifiers":[
        {
            "category":"Real Estate",
            "subcategory":"Real Estate Agent",
            "type":"Services"
        }
    ],
    "sg:phone":"+1 805 969 6666",
    "sg:postcode":"93108",
    "sg:province":"CA",
    "wof:name":"Jck Realty",
    "wof:placetype":"venue"
},
  "geometry": {"coordinates":[-119.6328,34.434166],"type":"Point"}
}