{
  "type": "Feature",
  "properties": {
    "iso:country":"US",
    "sg:address":"4111 Clipper Ct",
    "sg:city":"Fremont",
    "sg:classifiers":[
        {
            "category":"Wholesale",
            "subcategory":"Machinery & Supplies",
            "type":"Manufacturing & Wholesale Goods"
        }
    ],
    "sg:phone":"+1 510 770 9811",
    "sg:postcode":"94538",
    "sg:province":"CA",
    "sg:tags":[
        "equipment",
        "material",
        "handling"
    ],
    "wof:name":"Daifuku AMERICA Corp",
    "wof:placetype":"venue"
},
  "geometry": {"coordinates":[-121.946437,37.479686],"type":"Point"}
}