{
  "type": "Feature",
  "properties": {
    "iso:country":"US",
    "sg:address":"788 8th Ave",
    "sg:city":"San Francisco",
    "sg:classifiers":[
        {
            "category":"Real Estate",
            "subcategory":"Real Estate Agent",
            "type":"Services"
        }
    ],
    "sg:phone":"+1 415 668 4023",
    "sg:postcode":"94118",
    "sg:province":"CA",
    "wof:name":"Heritage Properties Real Est",
    "wof:placetype":"venue"
},
  "geometry": {"coordinates":[-122.46590399999999,37.775084],"type":"Point"}
}