{
  "type": "Feature",
  "properties": {
    "addr:full":"25077 Viejas Blvd Descanso CA 91916",
    "addr:housenumber":"25077",
    "addr:postcode":"91916",
    "addr:street":"Viejas Blvd",
    "iso:country":"US",
    "sg:address":"25077 Viejas Blvd",
    "sg:city":"Descanso",
    "sg:classifiers":[
        {
            "category":"Shopping",
            "subcategory":"Bicycles & Sporting Goods",
            "type":"Retail Goods"
        }
    ],
    "sg:phone":"+1 619 445 3946",
    "sg:postcode":"91916",
    "sg:province":"CA",
    "sg:tags":[
        "saddlery",
        "harness"
    ],
    "sg:website":"www.mcclintocksaddles.com",
    "wof:name":"Mc Clintock Saddle Works",
    "wof:placetype":"venue"
},
  "geometry": {"coordinates":[-116.60641200000001,32.856391],"type":"Point"}
}