{
  "type": "Feature",
  "properties": {
    "iso:country":"US",
    "sg:address":"7631 Canoga Ave.",
    "sg:city":"San Fernando Valley",
    "sg:classifiers":[
        {
            "category":"Building & Trades",
            "subcategory":"Construction",
            "type":"Services"
        }
    ],
    "sg:phone":"+1 818 704 9222",
    "sg:postcode":"91304",
    "sg:province":"CA",
    "sg:tags":[
        "contractor"
    ],
    "sg:website":"www.westsidetile.com",
    "wof:name":"Westside Tile and Stone, Inc.",
    "wof:placetype":"venue"
},
  "geometry": {"coordinates":[-118.597937,34.209354],"type":"Point"}
}