{
  "type": "Feature",
  "properties": {
    "addr:full":"204 American St Stockton CA 95202",
    "addr:housenumber":"204",
    "addr:postcode":"95202",
    "addr:street":"American St",
    "iso:country":"US",
    "sg:address":"204 American St",
    "sg:city":"Stockton",
    "sg:classifiers":[
        {
            "category":"Retail",
            "subcategory":"Repair Shop",
            "type":"Services"
        }
    ],
    "sg:phone":"+1 209 941 9515",
    "sg:postcode":"95202",
    "sg:province":"CA",
    "sg:tags":[
        "furniture"
    ],
    "wof:name":"A A Basler Property Care",
    "wof:placetype":"venue"
},
  "geometry": {"coordinates":[-121.28400000000001,37.956774],"type":"Point"}
}