{
  "type": "Feature",
  "properties": {
    "addr:full":"5732 Red River Dr San Diego CA 92120",
    "addr:housenumber":"5732",
    "addr:postcode":"92120",
    "addr:street":"Red River Dr",
    "iso:country":"US",
    "sg:address":"5732 Red River Dr",
    "sg:city":"San Diego",
    "sg:classifiers":[
        {
            "category":"Professional",
            "subcategory":"Art Services",
            "type":"Services"
        }
    ],
    "sg:phone":"+1 619 287 0768",
    "sg:postcode":"92120",
    "sg:province":"CA",
    "sg:tags":[
        "artist"
    ],
    "wof:name":"Carolyn's Color",
    "wof:placetype":"venue"
},
  "geometry": {"coordinates":[-117.074111,32.805141],"type":"Point"}
}