{
  "type": "Feature",
  "properties": {
    "addr:full":"925 N Garey Ave Pomona CA 91767",
    "addr:housenumber":"925",
    "addr:postcode":"91767",
    "addr:street":"N Garey Ave",
    "iso:country":"US",
    "sg:address":"925 N Garey Ave",
    "sg:city":"Pomona",
    "sg:classifiers":[
        {
            "category":"Professional",
            "subcategory":"Accounting & Tax Preparation",
            "type":"Services"
        }
    ],
    "sg:phone":"+1 909 620 8213",
    "sg:postcode":"91767",
    "sg:province":"CA",
    "sg:tags":[
        "return",
        "filing"
    ],
    "wof:name":"Quintero-Bautista Tax Svc",
    "wof:placetype":"venue"
},
  "geometry": {"coordinates":[-117.75200100000001,34.067429],"type":"Point"}
}