{
  "type": "Feature",
  "properties": {
    "iso:country":"US",
    "sg:address":"508 2nd St",
    "sg:city":"Davis",
    "sg:classifiers":[
        {
            "category":"Banks & Credit Unions",
            "subcategory":"Bank",
            "type":"Services"
        }
    ],
    "sg:phone":"+1 530 756 6208",
    "sg:postcode":"95616",
    "sg:province":"CA",
    "wof:name":"Investment and Brokerage Services",
    "wof:placetype":"venue"
},
  "geometry": {"coordinates":[-121.742063,38.543065],"type":"Point"}
}