{
  "type": "Feature",
  "properties": {
    "addr:full":"9603 S Vermont Ave Los Angeles CA 90044",
    "addr:housenumber":"9603",
    "addr:postcode":"90044",
    "addr:street":"S Vermont Ave",
    "iso:country":"US",
    "sg:address":"9603 S Vermont Ave",
    "sg:city":"Los Angeles",
    "sg:classifiers":[
        {
            "category":"Shopping",
            "subcategory":"Used Merchandise",
            "type":"Retail Goods"
        }
    ],
    "sg:phone":"+1 323 757 7691",
    "sg:postcode":"90044",
    "sg:province":"CA",
    "sg:tags":[
        "shop",
        "thrift"
    ],
    "wof:name":"Haja's Thrift Shop",
    "wof:placetype":"venue"
},
  "geometry": {"coordinates":[-118.291892,33.948183],"type":"Point"}
}