{
  "type": "Feature",
  "properties": {
    "addr:full":"242 Magnolia Ave Larkspur CA 94939",
    "addr:housenumber":"242",
    "addr:postcode":"94939",
    "addr:street":"Magnolia Ave",
    "iso:country":"US",
    "sg:address":"242 Magnolia Ave",
    "sg:city":"Larkspur",
    "sg:classifiers":[
        {
            "category":"Real Estate",
            "subcategory":"Real Estate Agent",
            "type":"Services"
        }
    ],
    "sg:phone":"+1 415 924 3714",
    "sg:postcode":"94939",
    "sg:province":"CA",
    "sg:tags":[
        "management"
    ],
    "wof:name":"ABX Assoc",
    "wof:placetype":"venue"
},
  "geometry": {"coordinates":[-122.535816,37.932076],"type":"Point"}
}