{
  "type": "Feature",
  "properties": {
    "addr:full":"2643 Saviers Rd Oxnard CA 93033",
    "addr:postcode":"2643;93033",
    "addr:street":"Saviers Rd",
    "iso:country":"US",
    "sg:address":"2643 Saviers Rd",
    "sg:city":"Oxnard",
    "sg:classifiers":[
        {
            "category":"Shopping",
            "subcategory":"Shoes",
            "type":"Retail Goods"
        }
    ],
    "sg:phone":"+1 805 240 9620",
    "sg:postcode":"93033",
    "sg:province":"CA",
    "sg:tags":[
        "boot"
    ],
    "wof:name":"Mora's Boots",
    "wof:placetype":"venue"
},
  "geometry": {"coordinates":[-119.17761299999999,34.174899],"type":"Point"}
}