{
  "type": "Feature",
  "properties": {
    "iso:country":"US",
    "sg:address":"125 Burney St",
    "sg:city":"Modesto",
    "sg:classifiers":[
        {
            "category":"Retail",
            "subcategory":"Auto Repair",
            "type":"Services"
        },
        {
            "category":"Government",
            "subcategory":"Office",
            "type":"Public Place"
        }
    ],
    "sg:phone":"+1 209 523 0452",
    "sg:postcode":"95354",
    "sg:province":"CA",
    "sg:tags":[
        "smog",
        "check"
    ],
    "wof:name":"Smog Shop the",
    "wof:placetype":"venue"
},
  "geometry": {"coordinates":[-120.988998,37.639],"type":"Point"}
}