{
  "type": "Feature",
  "properties": {
    "iso:country":"US",
    "sg:address":"14020 Pioneer Blvd",
    "sg:city":"Norwalk",
    "sg:classifiers":[
        {
            "category":"Autos & Motor Vehicles",
            "subcategory":"Auto Supplies",
            "type":"Retail Goods"
        }
    ],
    "sg:phone":"+1 562 863 8741",
    "sg:postcode":"90650",
    "sg:province":"CA",
    "sg:tags":[
        "tire"
    ],
    "wof:name":"One Stop Goodyear",
    "wof:placetype":"venue"
},
  "geometry": {"coordinates":[-118.082447,33.903141],"type":"Point"}
}