{
  "type": "Feature",
  "properties": {
    "addr:full":"10701 Cedar Ave Bloomington CA 92316",
    "addr:housenumber":"10701",
    "addr:postcode":"92316",
    "addr:street":"Cedar Ave",
    "iso:country":"US",
    "sg:address":"10701 Cedar Ave",
    "sg:city":"Bloomington",
    "sg:classifiers":[
        {
            "category":"Social Services",
            "subcategory":"Child Care",
            "type":"Services"
        }
    ],
    "sg:phone":"+1 909 875 3131",
    "sg:postcode":"92316",
    "sg:province":"CA",
    "wof:name":"Ezzell Family Child Care",
    "wof:placetype":"venue"
},
  "geometry": {"coordinates":[-117.39634700000001,34.060571],"type":"Point"}
}