{
  "type": "Feature",
  "properties": {
    "iso:country":"US",
    "sg:address":"19147 Mayall St",
    "sg:city":"Northridge",
    "sg:classifiers":[
        {
            "category":"Building & Trades",
            "subcategory":"Construction",
            "type":"Services"
        }
    ],
    "sg:phone":"+1 818 998 1641",
    "sg:postcode":"91324",
    "sg:province":"CA",
    "sg:tags":[
        "fence",
        "contractor"
    ],
    "wof:name":"Pick It Fences By Stanco",
    "wof:placetype":"venue"
},
  "geometry": {"coordinates":[-118.55088600000001,34.254139],"type":"Point"}
}