{
  "type": "Feature",
  "properties": {
    "iso:country":"US",
    "sg:address":"2149 E Portland Ave",
    "sg:city":"Fresno",
    "sg:classifiers":[
        {
            "category":"Professional",
            "type":"Services"
        }
    ],
    "sg:phone":"+1 559 299 4106",
    "sg:postcode":"93720",
    "sg:province":"CA",
    "wof:name":"Stitch Master Custom Embroider",
    "wof:placetype":"venue"
},
  "geometry": {"coordinates":[-119.745595,36.85632],"type":"Point"}
}