{
  "type": "Feature",
  "properties": {
    "addr:full":"13841 Roswell Ave Chino CA 91710",
    "addr:housenumber":"13841",
    "addr:postcode":"91710",
    "addr:street":"Roswell Ave",
    "iso:country":"US",
    "sg:address":"13841 Roswell Ave",
    "sg:city":"Chino",
    "sg:classifiers":[
        {
            "category":"Wholesale",
            "subcategory":"Medical Equipment & Supplies",
            "type":"Manufacturing & Wholesale Goods"
        }
    ],
    "sg:phone":"+1 909 590 0797",
    "sg:postcode":"91710",
    "sg:province":"CA",
    "sg:tags":[
        "physician",
        "surgeon"
    ],
    "wof:name":"Medical Network Resource",
    "wof:placetype":"venue"
},
  "geometry": {"coordinates":[-117.721706,34.003429],"type":"Point"}
}