{
  "type": "Feature",
  "properties": {
    "addr:full":"619 E Pacific Coast Hwy Long Beach CA 90806",
    "addr:housenumber":"619",
    "addr:postcode":"90806",
    "addr:street":"E Pacific Coast Hwy",
    "iso:country":"US",
    "sg:address":"619 E Pacific Coast Hwy",
    "sg:city":"Long Beach",
    "sg:classifiers":[
        {
            "category":"Professional",
            "subcategory":"Business Services",
            "type":"Services"
        }
    ],
    "sg:phone":"+1 562 218 8096",
    "sg:postcode":"90806",
    "sg:province":"CA",
    "sg:tags":[
        "operator",
        "local",
        "trucking"
    ],
    "wof:name":"David Roseles Zelada Express",
    "wof:placetype":"venue"
},
  "geometry": {"coordinates":[-118.184651,33.789926],"type":"Point"}
}