{
  "type": "Feature",
  "properties": {
    "iso:country":"US",
    "sg:address":"2421 10th Ave",
    "sg:city":"Los Angeles",
    "sg:classifiers":[
        {
            "category":"Health Services",
            "subcategory":"Nursing And Care Facility",
            "type":"Services"
        }
    ],
    "sg:phone":"+1 323 731 6213",
    "sg:postcode":"90018",
    "sg:province":"CA",
    "sg:tags":[
        "intermediate"
    ],
    "wof:name":"Ov Home For Aged",
    "wof:placetype":"venue"
},
  "geometry": {"coordinates":[-118.328451,34.034511],"type":"Point"}
}