{
  "type": "Feature",
  "properties": {
    "iso:country":"US",
    "sg:address":"7 E Poplar Ave",
    "sg:city":"San Mateo",
    "sg:classifiers":[
        {
            "category":"Shopping",
            "subcategory":"Pets & Pet Supplies",
            "type":"Retail Goods"
        },
        {
            "category":"Professional",
            "subcategory":"Art Services",
            "type":"Services"
        }
    ],
    "sg:phone":"+1 510 432 0371",
    "sg:postcode":"94401",
    "sg:province":"CA",
    "sg:tags":[
        "photographer"
    ],
    "sg:website":"fifilovesfido.com",
    "wof:name":"Fifi Loves Fido",
    "wof:placetype":"venue"
},
  "geometry": {"coordinates":[-122.334992,37.57019],"type":"Point"}
}