{
  "type": "Feature",
  "properties": {
    "addr:full":"793 Redwood Dr Garberville CA 95542",
    "addr:housenumber":"793",
    "addr:postcode":"95542",
    "addr:street":"Redwood Dr",
    "iso:country":"US",
    "sg:address":"793 Redwood Dr",
    "sg:city":"Garberville",
    "sg:classifiers":[
        {
            "category":"Banks & Credit Unions",
            "subcategory":"Bank",
            "type":"Services"
        }
    ],
    "sg:phone":"+1 707 923 2152",
    "sg:postcode":"95542",
    "sg:province":"CA",
    "wof:name":"Six Rivers Bank",
    "wof:placetype":"venue"
},
  "geometry": {"coordinates":[-123.79505,40.100221],"type":"Point"}
}