{
  "type": "Feature",
  "properties": {
    "addr:full":"42 W Campbell Ave Ste 101 Campbell CA 95008",
    "addr:housenumber":"42",
    "addr:postcode":"95008",
    "addr:street":"W Campbell Ave Ste 101",
    "iso:country":"US",
    "sg:address":"42 W Campbell Ave Ste 101",
    "sg:city":"Campbell",
    "sg:classifiers":[
        {
            "category":"Professional",
            "subcategory":"Accounting & Tax Preparation",
            "type":"Services"
        }
    ],
    "sg:phone":"+1 408 898 4625",
    "sg:postcode":"95008",
    "sg:province":"CA",
    "sg:tags":[
        "accountant"
    ],
    "sg:website":"www.macielcpa.com",
    "wof:name":"Maciel & Wong Certified Public Accountants",
    "wof:placetype":"venue"
},
  "geometry": {"coordinates":[-121.95068000000001,37.28666],"type":"Point"}
}