{
  "type": "Feature",
  "properties": {
    "addr:full":"1247 S Buena Vista St San Jacinto CA 92583",
    "addr:housenumber":"1247",
    "addr:postcode":"92583",
    "addr:street":"S Buena Vista St",
    "iso:country":"US",
    "sg:address":"1247 S Buena Vista St",
    "sg:city":"San Jacinto",
    "sg:classifiers":[
        {
            "category":"Autos & Motor Vehicles",
            "subcategory":"Auto Supplies",
            "type":"Retail Goods"
        }
    ],
    "sg:phone":"+1 951 654 3610",
    "sg:postcode":"92583",
    "sg:province":"CA",
    "wof:name":"Fast Track Racg For Kids Only",
    "wof:placetype":"venue"
},
  "geometry": {"coordinates":[-116.967353,33.778145],"type":"Point"}
}