{
  "type": "Feature",
  "properties": {
    "addr:full":"2735 Miradero Dr Santa Barbara CA 93105",
    "addr:postcode":"2735;93105",
    "addr:street":"Miradero Dr",
    "iso:country":"US",
    "sg:address":"2735 Miradero Dr",
    "sg:city":"Santa Barbara",
    "sg:classifiers":[
        {
            "category":"Personal",
            "subcategory":"Beauty Salon",
            "type":"Services"
        }
    ],
    "sg:phone":"+1 805 898 7858",
    "sg:postcode":"93105",
    "sg:province":"CA",
    "wof:name":"Viva Davinci",
    "wof:placetype":"venue"
},
  "geometry": {"coordinates":[-119.723685,34.439621],"type":"Point"}
}