{
  "type": "Feature",
  "properties": {
    "addr:full":"1428 E Katella Ave Orange CA 92867",
    "addr:housenumber":"1428",
    "addr:postcode":"92867",
    "addr:street":"E Katella Ave",
    "iso:country":"US",
    "sg:address":"1428 E Katella Ave",
    "sg:city":"Orange",
    "sg:classifiers":[
        {
            "category":"Retail",
            "subcategory":"Photofinishing",
            "type":"Services"
        }
    ],
    "sg:phone":"+1 714 633 6035",
    "sg:postcode":"92867",
    "sg:province":"CA",
    "sg:tags":[
        "photography",
        "photographic",
        "darkroom",
        "store"
    ],
    "sg:website":"www.kaniscamera.com/",
    "wof:name":"Kani's Camera",
    "wof:placetype":"venue"
},
  "geometry": {"coordinates":[-117.837997,33.808998],"type":"Point"}
}