{
  "type": "Feature",
  "properties": {
    "addr:full":"11110 Los Alamitos Blvd Los Alamitos CA 90720",
    "addr:housenumber":"11110",
    "addr:postcode":"90720",
    "addr:street":"Los Alamitos Blvd",
    "iso:country":"US",
    "sg:address":"11110 Los Alamitos Blvd",
    "sg:city":"Los Alamitos",
    "sg:classifiers":[
        {
            "category":"Professional",
            "type":"Services"
        },
        {
            "category":"Professional",
            "subcategory":"Art Services",
            "type":"Services"
        }
    ],
    "sg:phone":"+1 714 745 0111",
    "sg:postcode":"90720",
    "sg:province":"CA",
    "sg:tags":[
        "photographer"
    ],
    "sg:website":"www.MiaDolcePhotography.com",
    "wof:name":"Mia Dolce Photography, LLC",
    "wof:placetype":"venue"
},
  "geometry": {"coordinates":[-118.071489,33.801517],"type":"Point"}
}