{
  "type": "Feature",
  "properties": {
    "addr:full":"19363 del Rio Dr Woodbridge CA 95258",
    "addr:housenumber":"19363",
    "addr:postcode":"95258",
    "addr:street":"Del Rio Dr",
    "iso:country":"US",
    "sg:address":"19363 del Rio Dr",
    "sg:city":"Woodbridge",
    "sg:classifiers":[
        {
            "category":"Manufacturing",
            "subcategory":"Rubber & Plastics",
            "type":"Manufacturing & Wholesale Goods"
        }
    ],
    "sg:phone":"+1 209 339 4947",
    "sg:postcode":"95258",
    "sg:province":"CA",
    "sg:tags":[
        "product",
        "mfg"
    ],
    "wof:name":"Plas-Tech Mold",
    "wof:placetype":"venue"
},
  "geometry": {"coordinates":[-121.307954,38.157592],"type":"Point"}
}