{
  "type": "Feature",
  "properties": {
    "iso:country":"US",
    "sg:address":"4334 Matilija Ave",
    "sg:city":"Sherman Oaks",
    "sg:classifiers":[
        {
            "category":"Real Estate",
            "subcategory":"Real Estate Agent",
            "type":"Services"
        }
    ],
    "sg:phone":"+1 818 986 3543",
    "sg:postcode":"91423",
    "sg:province":"CA",
    "sg:tags":[
        "management"
    ],
    "wof:name":"Ig Properties",
    "wof:placetype":"venue"
},
  "geometry": {"coordinates":[-118.43395599999999,34.149703],"type":"Point"}
}