{
  "type": "Feature",
  "properties": {
    "addr:full":"1080 S Fairfax Avenue Los Angeles CA 90019",
    "addr:housenumber":"1080",
    "addr:postcode":"90019",
    "addr:street":"S Fairfax Avenue",
    "iso:country":"US",
    "sg:address":"1080 S Fairfax Avenue",
    "sg:city":"Los Angeles",
    "sg:classifiers":[
        {
            "category":"Building & Trades",
            "subcategory":"Locksmith",
            "type":"Services"
        }
    ],
    "sg:phone":"+1 323 653 7137",
    "sg:postcode":"90019",
    "sg:province":"CA",
    "sg:tags":[
        "key"
    ],
    "wof:name":"Fairfax Lock & Key Service",
    "wof:placetype":"venue"
},
  "geometry": {"coordinates":[-118.364903,34.056125],"type":"Point"}
}