{
  "type": "Feature",
  "properties": {
    "iso:country":"US",
    "sg:address":"2108 24th St",
    "sg:city":"Bakersfield",
    "sg:classifiers":[
        {
            "category":"Insurance",
            "subcategory":"Insurance Agent",
            "type":"Services"
        }
    ],
    "sg:phone":"+1 661 324 9322",
    "sg:postcode":"93301",
    "sg:province":"CA",
    "wof:name":"WEBB Insurance Group",
    "wof:placetype":"venue"
},
  "geometry": {"coordinates":[-119.026905,35.381106],"type":"Point"}
}