{
  "type": "Feature",
  "properties": {
    "addr:full":"4227 Myerwood Dr Redding CA 96003",
    "addr:housenumber":"4227",
    "addr:postcode":"96003",
    "addr:street":"Myerwood Dr",
    "iso:country":"US",
    "sg:address":"4227 Myerwood Dr",
    "sg:city":"Redding",
    "sg:classifiers":[
        {
            "category":"Manufacturing",
            "subcategory":"Wood Products",
            "type":"Manufacturing & Wholesale Goods"
        }
    ],
    "sg:phone":"+1 530 221 3160",
    "sg:postcode":"96003",
    "sg:province":"CA",
    "sg:tags":[
        "millwork-wholesale",
        "millwork",
        "manufacturer"
    ],
    "wof:name":"Baldwin Woodworking",
    "wof:placetype":"venue"
},
  "geometry": {"coordinates":[-122.294174,40.560308],"type":"Point"}
}