{
  "type": "Feature",
  "properties": {
    "iso:country":"US",
    "sg:address":"20445 Yorba Linda Blvd",
    "sg:city":"Yorba Linda",
    "sg:classifiers":[
        {
            "category":"Food & Beverages",
            "subcategory":"Groceries & Convenience Stores",
            "type":"Retail Goods"
        }
    ],
    "sg:phone":"+1 714 777 0781",
    "sg:postcode":"92886",
    "sg:province":"CA",
    "wof:name":"Vons 3069",
    "wof:placetype":"venue"
},
  "geometry": {"coordinates":[-117.779356,33.891055],"type":"Point"}
}