{
  "type": "Feature",
  "properties": {
    "addr:full":"953 Industrial Ave Palo Alto CA 94303",
    "addr:housenumber":"953",
    "addr:postcode":"94303",
    "addr:street":"Industrial Ave",
    "iso:country":"US",
    "sg:address":"953 Industrial Ave",
    "sg:city":"Palo Alto",
    "sg:classifiers":[
        {
            "category":"Professional",
            "subcategory":"Computer Services",
            "type":"Services"
        }
    ],
    "sg:phone":"+1 650 812 1100",
    "sg:postcode":"94303",
    "sg:province":"CA",
    "sg:tags":[
        "consultant",
        "designer"
    ],
    "wof:name":"Finnovative",
    "wof:placetype":"venue"
},
  "geometry": {"coordinates":[-122.098654,37.422286],"type":"Point"}
}