{
  "type": "Feature",
  "properties": {
    "iso:country":"US",
    "sg:address":"259 N Capitol Ave",
    "sg:city":"San Jose",
    "sg:classifiers":[
        {
            "category":"Real Estate",
            "subcategory":"Real Estate Agent",
            "type":"Services"
        }
    ],
    "sg:phone":"+1 408 561 6481",
    "sg:postcode":"95127",
    "sg:province":"CA",
    "wof:name":"Do Your Own Listing",
    "wof:placetype":"venue"
},
  "geometry": {"coordinates":[-121.841679,37.368475],"type":"Point"}
}