{
  "type": "Feature",
  "properties": {
    "iso:country":"US",
    "sg:address":"1515 N Mahan St",
    "sg:city":"Ridgecrest",
    "sg:classifiers":[
        {
            "category":"Retail",
            "subcategory":"Repair Shop",
            "type":"Services"
        }
    ],
    "sg:phone":"+1 760 446 0357",
    "sg:postcode":"93555",
    "sg:province":"CA",
    "sg:tags":[
        "welding"
    ],
    "wof:name":"Thomas Brothers Welding",
    "wof:placetype":"venue"
},
  "geometry": {"coordinates":[-117.696681,35.648309],"type":"Point"}
}