{
  "type": "Feature",
  "properties": {
    "addr:full":"627 Shaw Ave Ferndale CA 95536",
    "addr:housenumber":"627",
    "addr:postcode":"95536",
    "addr:street":"Shaw Ave",
    "iso:country":"US",
    "sg:address":"627 Shaw Ave",
    "sg:city":"Ferndale",
    "sg:classifiers":[
        {
            "category":"Personal",
            "subcategory":"Beauty Salon",
            "type":"Services"
        }
    ],
    "sg:phone":"+1 707 786 9030",
    "sg:postcode":"95536",
    "sg:province":"CA",
    "wof:name":"Else Like Nobody",
    "wof:placetype":"venue"
},
  "geometry": {"coordinates":[-124.262097,40.577674],"type":"Point"}
}