{
  "type": "Feature",
  "properties": {
    "addr:full":"186 Virginia Pl Costa Mesa CA 92627",
    "addr:housenumber":"186",
    "addr:postcode":"92627",
    "addr:street":"Virginia Pl",
    "iso:country":"US",
    "sg:address":"186 Virginia Pl",
    "sg:city":"Costa Mesa",
    "sg:classifiers":[
        {
            "category":"Building & Trades",
            "subcategory":"Construction",
            "type":"Services"
        }
    ],
    "sg:phone":"+1 949 642 3899",
    "sg:postcode":"92627",
    "sg:province":"CA",
    "sg:tags":[
        "general",
        "contractor"
    ],
    "wof:name":"OEG Construction & Mntnc",
    "wof:placetype":"venue"
},
  "geometry": {"coordinates":[-117.905158,33.650932],"type":"Point"}
}