{
  "type": "Feature",
  "properties": {
    "addr:full":"5500 Madison Avenue Sacramento CA 95841",
    "addr:housenumber":"5500",
    "addr:postcode":"95841",
    "addr:street":"Madison Avenue",
    "iso:country":"US",
    "sg:address":"5500 Madison Avenue",
    "sg:city":"Sacramento",
    "sg:classifiers":[
        {
            "category":"Retail",
            "subcategory":"Laundry & Dry Cleaning",
            "type":"Services"
        }
    ],
    "sg:phone":"+1 916 332 1067",
    "sg:postcode":"95841",
    "sg:province":"CA",
    "sg:website":"www.saveoncleaner.com",
    "wof:name":"Save On Cleaners",
    "wof:placetype":"venue"
},
  "geometry": {"coordinates":[-121.337249,38.660773],"type":"Point"}
}