{
  "type": "Feature",
  "properties": {
    "addr:full":"19914 Ray Cir Cerritos CA 90703",
    "addr:housenumber":"19914",
    "addr:postcode":"ca 90703",
    "addr:street":"Ray Cir",
    "iso:country":"US",
    "sg:address":"19914 Ray Cir",
    "sg:city":"Cerritos",
    "sg:classifiers":[
        {
            "category":"Home & Garden",
            "subcategory":"Furniture",
            "type":"Retail Goods"
        }
    ],
    "sg:phone":"+1 562 402 5363",
    "sg:postcode":"90703",
    "sg:province":"CA",
    "wof:name":"Sharons Blankets",
    "wof:placetype":"venue"
},
  "geometry": {"coordinates":[-118.080039,33.848783],"type":"Point"}
}