{
  "type": "Feature",
  "properties": {
    "addr:full":"17395 Indian Springs Ranch Rd Grass Valley CA 95949",
    "addr:housenumber":"17395",
    "addr:postcode":"95949",
    "addr:street":"Indian Springs Ranch Rd",
    "iso:country":"US",
    "sg:address":"17395 Indian Springs Ranch Rd",
    "sg:city":"Grass Valley",
    "sg:classifiers":[
        {
            "category":"Building & Trades",
            "subcategory":"Landscaping Services",
            "type":"Services"
        }
    ],
    "sg:phone":"+1 530 273 1501",
    "sg:postcode":"95949",
    "sg:province":"CA",
    "sg:tags":[
        "landscape",
        "contractor"
    ],
    "wof:name":"Braga Brothers Landscape Co",
    "wof:placetype":"venue"
},
  "geometry": {"coordinates":[-121.11779199999999,39.149352],"type":"Point"}
}