{
  "type": "Feature",
  "properties": {
    "addr:full":"1005 40th St Sacramento CA 95819",
    "addr:housenumber":"1005",
    "addr:postcode":"95819",
    "addr:street":"40Th St",
    "iso:country":"US",
    "sg:address":"1005 40th St",
    "sg:city":"Sacramento",
    "sg:classifiers":[
        {
            "category":"Health Services",
            "subcategory":"Doctor",
            "type":"Services"
        }
    ],
    "sg:phone":"+1 916 739 0984",
    "sg:postcode":"95819",
    "sg:province":"CA",
    "sg:tags":[
        "physician",
        "surgeon"
    ],
    "wof:name":"40th Group",
    "wof:placetype":"venue"
},
  "geometry": {"coordinates":[-121.453817,38.566757],"type":"Point"}
}