{
  "type": "Feature",
  "properties": {
    "iso:country":"US",
    "sg:address":"40477 Cll Roxanne",
    "sg:city":"Fallbrook",
    "sg:classifiers":[
        {
            "category":"Farming",
            "subcategory":"Crops",
            "type":"Manufacturing & Wholesale Goods"
        }
    ],
    "sg:phone":"+1 760 728 9096",
    "sg:postcode":"92028",
    "sg:province":"CA",
    "sg:tags":[
        "citrus",
        "grove",
        "avocado"
    ],
    "wof:name":"ACW Medical Products Inc",
    "wof:placetype":"venue"
},
  "geometry": {"coordinates":[-117.331727,33.44471],"type":"Point"}
}