{
  "type": "Feature",
  "properties": {
    "addr:full":"12517 Chandler Blvd Valley Village CA 91607",
    "addr:housenumber":"12517",
    "addr:postcode":"91607",
    "addr:street":"Chandler Blvd",
    "iso:country":"US",
    "sg:address":"12517 Chandler Blvd",
    "sg:city":"Valley Village",
    "sg:classifiers":[
        {
            "category":"Education",
            "subcategory":"School",
            "type":"Public Place"
        }
    ],
    "sg:phone":"+1 818 505 7999",
    "sg:postcode":"91607",
    "sg:province":"CA",
    "wof:name":"Valley Torah School",
    "wof:placetype":"venue"
},
  "geometry": {"coordinates":[-118.409137,34.168757],"type":"Point"}
}