{
  "type": "Feature",
  "properties": {
    "iso:country":"US",
    "sg:address":"929 E Foothill Blvd",
    "sg:city":"Upland",
    "sg:classifiers":[
        {
            "category":"Shopping",
            "type":"Retail Goods"
        }
    ],
    "sg:phone":"+1 909 935 8250",
    "sg:postcode":"91786",
    "sg:province":"CA",
    "sg:tags":[
        "candle"
    ],
    "wof:name":"D's Wax Designs",
    "wof:placetype":"venue"
},
  "geometry": {"coordinates":[-117.638472,34.10713],"type":"Point"}
}