{
  "type": "Feature",
  "properties": {
    "iso:country":"US",
    "sg:address":"1605 N Spurgeon St",
    "sg:city":"Santa Ana",
    "sg:classifiers":[
        {
            "category":"Education",
            "subcategory":"Special Training",
            "type":"Public Place"
        }
    ],
    "sg:phone":"+1 714 263 0303",
    "sg:postcode":"92701",
    "sg:province":"CA",
    "sg:tags":[
        "school",
        "language"
    ],
    "wof:name":"Logos Language",
    "wof:placetype":"venue"
},
  "geometry": {"coordinates":[-117.865124,33.759981],"type":"Point"}
}