{
  "type": "Feature",
  "properties": {
    "addr:full":"21255 Burbank Blvd Woodland Hills CA 91367",
    "addr:housenumber":"21255",
    "addr:postcode":"91367",
    "addr:street":"Burbank Blvd",
    "iso:country":"US",
    "sg:address":"21255 Burbank Blvd",
    "sg:city":"Woodland Hills",
    "sg:classifiers":[
        {
            "category":"Banks & Credit Unions",
            "subcategory":"Bank",
            "type":"Services"
        }
    ],
    "sg:phone":"+1 818 595 3940",
    "sg:postcode":"91367",
    "sg:province":"CA",
    "wof:name":"Wells Fargo Commercial Bank Na",
    "wof:placetype":"venue"
},
  "geometry": {"coordinates":[-118.593192,34.173437],"type":"Point"}
}