{
  "type": "Feature",
  "properties": {
    "addr:full":"5934 8th Ave Los Angeles CA 90043",
    "addr:housenumber":"5934",
    "addr:postcode":"90043",
    "addr:street":"8Th Ave",
    "iso:country":"US",
    "sg:address":"5934 8th Ave",
    "sg:city":"Los Angeles",
    "sg:classifiers":[
        {
            "category":"Building & Trades",
            "subcategory":"Construction",
            "type":"Services"
        }
    ],
    "sg:phone":"+1 323 291 9955",
    "sg:postcode":"90043",
    "sg:province":"CA",
    "sg:tags":[
        "general",
        "contractor"
    ],
    "wof:name":"Five Star Constr & Properties",
    "wof:placetype":"venue"
},
  "geometry": {"coordinates":[-118.32635999999999,33.986939],"type":"Point"}
}