{
  "type": "Feature",
  "properties": {
    "addr:full":"364 Cardona Cir San Ramon CA 94583",
    "addr:housenumber":"364",
    "addr:postcode":"94583",
    "addr:street":"Cardona Cir",
    "iso:country":"US",
    "sg:address":"364 Cardona Cir",
    "sg:city":"San Ramon",
    "sg:classifiers":[
        {
            "category":"Travel",
            "subcategory":"Travel Agent",
            "type":"Entertainment"
        }
    ],
    "sg:phone":"+1 925 736 2681",
    "sg:postcode":"94583",
    "sg:province":"CA",
    "sg:tags":[
        "agency"
    ],
    "wof:name":"Welcome Travel & Tour",
    "wof:placetype":"venue"
},
  "geometry": {"coordinates":[-121.96887099999999,37.760107],"type":"Point"}
}