{
  "type": "Feature",
  "properties": {
    "iso:country":"US",
    "sg:address":"2965 Flores Ln",
    "sg:city":"Lemon Grove",
    "sg:classifiers":[
        {
            "category":"Building & Trades",
            "subcategory":"Landscaping Services",
            "type":"Services"
        }
    ],
    "sg:phone":"+1 619 582 1323",
    "sg:postcode":"91945",
    "sg:province":"CA",
    "sg:tags":[
        "tree"
    ],
    "wof:name":"Flores David Tree & Shrub S Er",
    "wof:placetype":"venue"
},
  "geometry": {"coordinates":[-117.05042,32.738039],"type":"Point"}
}