{
  "type": "Feature",
  "properties": {
    "addr:full":"23349 Mulholland Dr Woodland Hills CA 91364",
    "addr:housenumber":"23349",
    "addr:postcode":"91364",
    "addr:street":"Mulholland Dr",
    "iso:country":"US",
    "sg:address":"23349 Mulholland Dr",
    "sg:city":"Woodland Hills",
    "sg:classifiers":[
        {
            "category":"Shopping",
            "subcategory":"Gifts & Souvenirs",
            "type":"Retail Goods"
        }
    ],
    "sg:phone":"+1 818 222 6164",
    "sg:postcode":"91364",
    "sg:province":"CA",
    "sg:tags":[
        "shop"
    ],
    "wof:name":"Handle With Care Gifts",
    "wof:placetype":"venue"
},
  "geometry": {"coordinates":[-118.632042,34.153336],"type":"Point"}
}