{
  "type": "Feature",
  "properties": {
    "iso:country":"US",
    "sg:address":"3200 S. Grand Ave.",
    "sg:city":"Los Angeles",
    "sg:classifiers":[
        {
            "category":"Shopping",
            "subcategory":"Bicycles & Sporting Goods",
            "type":"Retail Goods"
        }
    ],
    "sg:phone":"+1 213 742 0666",
    "sg:postcode":"90007",
    "sg:province":"CA",
    "sg:tags":[
        "outdoor",
        "gear"
    ],
    "sg:website":"www.rddusa.com/",
    "wof:name":"RDD USA Military Surplus and Army Navy Store",
    "wof:placetype":"venue"
},
  "geometry": {"coordinates":[-118.275012,34.021259],"type":"Point"}
}