{
  "type": "Feature",
  "properties": {
    "addr:full":"120 San Lucar Ct Sunnyvale CA 94086",
    "addr:housenumber":"120",
    "addr:postcode":"94086",
    "addr:street":"San Lucar Ct",
    "iso:country":"US",
    "sg:address":"120 San Lucar Ct",
    "sg:city":"Sunnyvale",
    "sg:classifiers":[
        {
            "category":"Professional",
            "type":"Services"
        }
    ],
    "sg:phone":"+1 408 835 7800",
    "sg:postcode":"94086",
    "sg:province":"CA",
    "wof:name":"Business Interiors",
    "wof:placetype":"venue"
},
  "geometry": {"coordinates":[-122.011336,37.373392],"type":"Point"}
}