{
  "type": "Feature",
  "properties": {
    "iso:country":"US",
    "sg:address":"4200 Easton Dr",
    "sg:city":"Bakersfield",
    "sg:classifiers":[
        {
            "category":"Real Estate",
            "subcategory":"Real Estate Operator",
            "type":"Services"
        }
    ],
    "sg:phone":"+1 661 323 4641",
    "sg:postcode":"93309",
    "sg:province":"CA",
    "sg:tags":[
        "field",
        "property",
        "lessor"
    ],
    "wof:name":"Fuller Oil Company",
    "wof:placetype":"venue"
},
  "geometry": {"coordinates":[-119.054283,35.366461],"type":"Point"}
}