{
  "type": "Feature",
  "properties": {
    "iso:country":"US",
    "sg:address":"12381 Ave 416",
    "sg:city":"Orosi",
    "sg:classifiers":[
        {
            "category":"Restaurant",
            "type":"Food & Drink"
        }
    ],
    "sg:phone":"+1 559 528 3696",
    "sg:postcode":"93647",
    "sg:province":"CA",
    "sg:tags":[
        "delicatessen"
    ],
    "wof:name":"Orosi Mart & Deli",
    "wof:placetype":"venue"
},
  "geometry": {"coordinates":[-119.29643,36.544875],"type":"Point"}
}