{
  "type": "Feature",
  "properties": {
    "addr:full":"622 S Flower St Burbank CA 91502",
    "addr:housenumber":"622",
    "addr:postcode":"91502",
    "addr:street":"S Flower St",
    "iso:country":"US",
    "sg:address":"622 S Flower St",
    "sg:city":"Burbank",
    "sg:classifiers":[
        {
            "category":"Insurance",
            "subcategory":"Insurance Agent",
            "type":"Services"
        }
    ],
    "sg:phone":"+1 818 841 1993",
    "sg:postcode":"91502",
    "sg:province":"CA",
    "sg:website":"www.metricspecialties.com",
    "wof:name":"Allstate Insurance",
    "wof:placetype":"venue"
},
  "geometry": {"coordinates":[-118.30463,34.172649],"type":"Point"}
}