{
  "type": "Feature",
  "properties": {
    "iso:country":"US",
    "sg:address":"11350 South St",
    "sg:city":"Cerritos",
    "sg:classifiers":[
        {
            "category":"Banks & Credit Unions",
            "subcategory":"Bank",
            "type":"Services"
        }
    ],
    "sg:phone":"+1 562 924 4437",
    "sg:postcode":"90703",
    "sg:province":"CA",
    "sg:website":"www.downeysavings.com/",
    "wof:name":"US Bank",
    "wof:placetype":"venue"
},
  "geometry": {"coordinates":[-118.093002,33.8582],"type":"Point"}
}