{
  "type": "Feature",
  "properties": {
    "iso:country":"US",
    "sg:address":"3615 Gilmore Ave",
    "sg:city":"Bakersfield",
    "sg:classifiers":[
        {
            "category":"Professional",
            "subcategory":"Research",
            "type":"Services"
        }
    ],
    "sg:phone":"+1 661 324 1830",
    "sg:postcode":"93308",
    "sg:province":"CA",
    "sg:tags":[
        "development",
        "laboratory"
    ],
    "wof:name":"American Biofuels Corp",
    "wof:placetype":"venue"
},
  "geometry": {"coordinates":[-119.055436,35.389514],"type":"Point"}
}