{
  "type": "Feature",
  "properties": {
    "addr:full":"476 W Los Angeles Ave Moorpark CA 93021",
    "addr:housenumber":"476",
    "addr:postcode":"ca 93021",
    "addr:street":"W Los Angeles Ave",
    "iso:country":"US",
    "sg:address":"476 W Los Angeles Ave",
    "sg:city":"Moorpark",
    "sg:classifiers":[
        {
            "category":"Restaurant",
            "type":"Food & Drink"
        }
    ],
    "sg:phone":"+1 805 523 3145",
    "sg:postcode":"93021",
    "sg:province":"CA",
    "sg:tags":[
        "delicatessen"
    ],
    "wof:name":"Cafe Espresso",
    "wof:placetype":"venue"
},
  "geometry": {"coordinates":[-118.811176,34.286294],"type":"Point"}
}