{
  "type": "Feature",
  "properties": {
    "addr:full":"16152 Beach Blvd Ste 173 Huntington Beach CA 92647",
    "addr:housenumber":"16152",
    "addr:postcode":"92647",
    "addr:street":"Beach Blvd Ste 173",
    "iso:country":"US",
    "sg:address":"16152 Beach Blvd Ste 173",
    "sg:city":"Huntington Beach",
    "sg:classifiers":[
        {
            "category":"Health Services",
            "subcategory":"Optometrist",
            "type":"Services"
        }
    ],
    "sg:phone":"+1 714 841 5051",
    "sg:postcode":"92647",
    "sg:province":"CA",
    "wof:name":"Fennema Byron M OD Inc",
    "wof:placetype":"venue"
},
  "geometry": {"coordinates":[-117.988998,33.728298],"type":"Point"}
}