{
  "type": "Feature",
  "properties": {
    "addr:full":"13093 Fescue Ct Corona CA 92883",
    "addr:housenumber":"13093",
    "addr:postcode":"92883",
    "addr:street":"Fescue Ct",
    "iso:country":"US",
    "sg:address":"13093 Fescue Ct",
    "sg:city":"Corona",
    "sg:classifiers":[
        {
            "category":"Wholesale",
            "subcategory":"Machinery & Supplies",
            "type":"Manufacturing & Wholesale Goods"
        }
    ],
    "sg:phone":"+1 951 808 4330",
    "sg:postcode":"92883",
    "sg:province":"CA",
    "sg:tags":[
        "equipment",
        "industrial"
    ],
    "wof:name":"Pressure Champion Products",
    "wof:placetype":"venue"
},
  "geometry": {"coordinates":[-117.431937,33.726527],"type":"Point"}
}