{
  "type": "Feature",
  "properties": {
    "iso:country":"US",
    "sg:address":"1326 Broadway",
    "sg:city":"Sacramento",
    "sg:classifiers":[
        {
            "category":"Banks & Credit Unions",
            "subcategory":"Bank",
            "type":"Services"
        }
    ],
    "sg:phone":"+1 916 732 2922",
    "sg:postcode":"95818",
    "sg:province":"CA",
    "wof:name":"The Golden Credit Union",
    "wof:placetype":"venue"
},
  "geometry": {"coordinates":[-121.496002,38.562401],"type":"Point"}
}