{
  "type": "Feature",
  "properties": {
    "iso:country":"US",
    "sg:address":"1012 San Fernando Rd",
    "sg:city":"San Fernando",
    "sg:classifiers":[
        {
            "category":"Home & Garden",
            "subcategory":"Furniture",
            "type":"Retail Goods"
        }
    ],
    "sg:phone":"+1 818 837 3737",
    "sg:postcode":"91340",
    "sg:province":"CA",
    "wof:name":"Electra Plus",
    "wof:placetype":"venue"
},
  "geometry": {"coordinates":[-118.440845,34.282202],"type":"Point"}
}