{
  "type": "Feature",
  "properties": {
    "addr:full":"3491 Butler Ave Los Angeles CA 90066",
    "addr:housenumber":"3491",
    "addr:postcode":"90066",
    "addr:street":"Butler Ave",
    "iso:country":"US",
    "sg:address":"3491 Butler Ave",
    "sg:city":"Los Angeles",
    "sg:classifiers":[
        {
            "category":"Freight",
            "type":"Transportation"
        }
    ],
    "sg:phone":"+1 310 397 3607",
    "sg:postcode":"90066",
    "sg:province":"CA",
    "sg:tags":[
        "operator",
        "mover",
        "trucking"
    ],
    "wof:name":"Tom's Marathon Movers",
    "wof:placetype":"venue"
},
  "geometry": {"coordinates":[-118.42704500000001,34.015646],"type":"Point"}
}