{
  "type": "Feature",
  "properties": {
    "iso:country":"US",
    "sfac:artist":"deSoto, Lewis",
    "sfac:created_at":"2004-2010",
    "sfac:credit_line":"Collection of the City and County of San Francisco. Commissioned for Laguna Honda Hospital and Rehabilitation Center by the San Francisco Arts Commission",
    "sfac:display_dimensions":"80 1/2 in. x 119 1/2 in.",
    "sfac:location_description":"City Department : Laguna Honda Hospital  : Historic Lobby",
    "sfac:medium":"Tapestry",
    "sfac:revision":"2-579ed367809b4bfa5200dd8ee4e115a3",
    "sfac:title":"1947-1954: University of California . . .",
    "wof:name":"1947-1954: University of California . . .",
    "wof:placetype":"venue"
},
  "geometry": {"coordinates":[-122.4556651,37.7478586],"type":"Point"}
}