{
  "type": "Feature",
  "properties": {
    "addr:full":"800 Polaris Ave Foster City CA 94404",
    "addr:housenumber":"800",
    "addr:postcode":"94404",
    "addr:street":"Polaris Ave",
    "iso:country":"US",
    "sg:address":"800 Polaris Ave",
    "sg:city":"Foster City",
    "sg:classifiers":[
        {
            "category":"Park",
            "type":"Public Place"
        },
        {
            "category":"Sports & Exercise",
            "subcategory":"Tennis Court",
            "type":"Entertainment"
        }
    ],
    "sg:postcode":"94404",
    "sg:province":"CA",
    "wof:name":"Edgewater Park",
    "wof:placetype":"venue"
},
  "geometry": {"coordinates":[-122.27624,37.54898],"type":"Point"}
}