{
  "type": "Feature",
  "properties": {
    "iso:country":"US",
    "sg:address":"800 Polaris Ave",
    "sg:city":"Foster City",
    "sg:classifiers":[
        {
            "category":"Park",
            "type":"Public Place"
        },
        {
            "category":"Sports & Exercise",
            "subcategory":"Tennis Court",
            "type":"Entertainment"
        }
    ],
    "sg:postcode":"94404",
    "sg:province":"CA",
    "wof:name":"Edgewater Park",
    "wof:placetype":"venue"
},
  "geometry": {"coordinates":[-122.27624,37.54898],"type":"Point"}
}