{
  "type": "Feature",
  "properties": {
    "iso:country":"US",
    "sg:address":"43389 Ellsworth St",
    "sg:city":"Fremont",
    "sg:classifiers":[
        {
            "category":"Personal",
            "subcategory":"Beauty Salon",
            "type":"Services"
        },
        {
            "category":"Personal",
            "subcategory":"Skin Care",
            "type":"Services"
        }
    ],
    "sg:phone":"+1 510 659 1934",
    "sg:postcode":"94539",
    "sg:province":"CA",
    "wof:name":"Facial Plus",
    "wof:placetype":"venue"
},
  "geometry": {"coordinates":[-121.921091,37.531817],"type":"Point"}
}