{
  "type": "Feature",
  "properties": {
    "addr:full":"PO Box 1468 Temple City CA 91780",
    "addr:housenumber":"po;1468",
    "addr:postcode":"91780",
    "addr:street":"Box",
    "iso:country":"US",
    "sg:address":"PO Box 1468",
    "sg:city":"Temple City",
    "sg:classifiers":[
        {
            "category":"Professional",
            "subcategory":"Computer Services",
            "type":"Services"
        }
    ],
    "sg:postcode":"91780",
    "sg:province":"CA",
    "sg:website":"http://www.emalinemediagroup.com",
    "wof:name":"Emaline Media Group",
    "wof:placetype":"venue"
},
  "geometry": {"coordinates":[-118.05785,34.10723],"type":"Point"}
}