{
  "type": "Feature",
  "properties": {
    "addr:full":"1900 Wardrobe Ave Merced CA 95341",
    "addr:housenumber":"1900",
    "addr:postcode":"95341",
    "addr:street":"Wardrobe Ave",
    "iso:country":"US",
    "sg:address":"1900 Wardrobe Ave",
    "sg:city":"Merced",
    "sg:classifiers":[
        {
            "category":"Manufacturing",
            "subcategory":"Paper Products",
            "type":"Manufacturing & Wholesale Goods"
        }
    ],
    "sg:phone":"+1 209 722 2787",
    "sg:postcode":"95341",
    "sg:province":"CA",
    "sg:tags":[
        "converted",
        "prod"
    ],
    "wof:name":"Rock-Tenn Co",
    "wof:placetype":"venue"
},
  "geometry": {"coordinates":[-120.513604,37.295531],"type":"Point"}
}