{
  "type": "Feature",
  "properties": {
    "iso:country":"US",
    "sg:address":"34112 Doheny Park Rd",
    "sg:city":"Capistrano Beach",
    "sg:classifiers":[
        {
            "category":"Wholesale",
            "subcategory":"Sporting Goods",
            "type":"Manufacturing & Wholesale Goods"
        }
    ],
    "sg:phone":"+1 949 496 6009",
    "sg:postcode":"92624",
    "sg:province":"CA",
    "wof:name":"Sea Wolf Canvas",
    "wof:placetype":"venue"
},
  "geometry": {"coordinates":[-117.678001,33.465797],"type":"Point"}
}