{
  "type": "Feature",
  "properties": {
    "iso:country":"US",
    "sg:address":"200 9th St",
    "sg:city":"Lakeport",
    "sg:classifiers":[
        {
            "category":"Professional",
            "subcategory":"Business Services",
            "type":"Services"
        }
    ],
    "sg:phone":"+1 707 263 8686",
    "sg:postcode":"95453",
    "sg:province":"CA",
    "sg:tags":[
        "arbitration"
    ],
    "wof:name":"Andrew M Rossoff Mediator",
    "wof:placetype":"venue"
},
  "geometry": {"coordinates":[-122.917016,39.047644],"type":"Point"}
}