{
  "type": "Feature",
  "properties": {
    "addr:full":"111 N 1st St Ste 100 Burbank CA 91502",
    "addr:housenumber":"111",
    "addr:postcode":"91502",
    "addr:street":"N 1St St Ste 100",
    "iso:country":"US",
    "sg:address":"111 N 1st St Ste 100",
    "sg:city":"Burbank",
    "sg:classifiers":[
        {
            "category":"Education",
            "subcategory":"School",
            "type":"Public Place"
        }
    ],
    "sg:phone":"+1 818 559 7699",
    "sg:postcode":"91502",
    "sg:province":"CA",
    "sg:tags":[
        "high",
        "middle",
        "elementary"
    ],
    "wof:name":"PUC Schools",
    "wof:placetype":"venue"
},
  "geometry": {"coordinates":[-118.310214,34.179697],"type":"Point"}
}