{
  "type": "Feature",
  "properties": {
    "addr:full":"2400 Harrison St San Francisco CA 94110",
    "addr:housenumber":"2400",
    "addr:postcode":"94110",
    "addr:street":"Harrison St",
    "iso:country":"US",
    "sg:address":"2400 Harrison St",
    "sg:city":"San Francisco",
    "sg:classifiers":[
        {
            "category":"Organizations",
            "subcategory":"Community Association",
            "type":"Services"
        }
    ],
    "sg:phone":"+1 415 824 4125",
    "sg:postcode":"94110",
    "sg:province":"CA",
    "sg:tags":[
        "club"
    ],
    "wof:name":"T Twenty Four Hundred Club",
    "wof:placetype":"venue"
},
  "geometry": {"coordinates":[-122.41234799999999,37.75743],"type":"Point"}
}