{
  "type": "Feature",
  "properties": {
    "addr:full":"2055 Westwood Dr Carlsbad CA 92008",
    "addr:housenumber":"2055",
    "addr:postcode":"92008",
    "addr:street":"Westwood Dr",
    "iso:country":"US",
    "sg:address":"2055 Westwood Dr",
    "sg:city":"Carlsbad",
    "sg:classifiers":[
        {
            "category":"Professional",
            "subcategory":"Art Services",
            "type":"Services"
        },
        {
            "category":"Communications",
            "type":"Services"
        }
    ],
    "sg:phone":"+1 760 729 8205",
    "sg:postcode":"92008",
    "sg:province":"CA",
    "sg:tags":[
        "web",
        "graphic",
        "design"
    ],
    "sg:website":"www.studio2055.com",
    "wof:name":"Studio 2055",
    "wof:placetype":"venue"
},
  "geometry": {"coordinates":[-117.329853,33.167684],"type":"Point"}
}