{
  "type": "Feature",
  "properties": {
    "addr:full":"6275 Thornton Ave Newark CA 94560",
    "addr:housenumber":"6275",
    "addr:postcode":"94560",
    "addr:street":"Thornton Ave",
    "iso:country":"US",
    "sg:address":"6275 Thornton Ave",
    "sg:city":"Newark",
    "sg:classifiers":[
        {
            "category":"Health Services",
            "subcategory":"Doctor",
            "type":"Services"
        }
    ],
    "sg:phone":"+1 510 791 7014",
    "sg:postcode":"94560",
    "sg:province":"CA",
    "sg:tags":[
        "physician",
        "surgeon"
    ],
    "wof:name":"Norma V Paragas MD",
    "wof:placetype":"venue"
},
  "geometry": {"coordinates":[-122.031617,37.535839],"type":"Point"}
}