{
  "type": "Feature",
  "properties": {
    "iso:country":"US",
    "sg:address":"1449 Park Avenue",
    "sg:city":"San Jose",
    "sg:classifiers":[
        {
            "category":"Health Services",
            "subcategory":"Dentist",
            "type":"Services"
        }
    ],
    "sg:phone":"+1 408 282 1660",
    "sg:postcode":"95126",
    "sg:province":"CA",
    "wof:name":"International Dental Ceramic",
    "wof:placetype":"venue"
},
  "geometry": {"coordinates":[-121.919111,37.329817],"type":"Point"}
}