{
  "type": "Feature",
  "properties": {
    "addr:full":"14502 Pioneer Blvd Norwalk CA 90650",
    "addr:housenumber":"14502",
    "addr:postcode":"90650",
    "addr:street":"Pioneer Blvd",
    "iso:country":"US",
    "sg:address":"14502 Pioneer Blvd",
    "sg:city":"Norwalk",
    "sg:classifiers":[
        {
            "category":"Professional",
            "subcategory":"Computer Services",
            "type":"Services"
        }
    ],
    "sg:phone":"+1 562 868 1849",
    "sg:postcode":"90650",
    "sg:province":"CA",
    "sg:tags":[
        "stereo",
        "installation"
    ],
    "wof:name":"Best Stereo",
    "wof:placetype":"venue"
},
  "geometry": {"coordinates":[-118.083,33.899101],"type":"Point"}
}