{
  "type": "Feature",
  "properties": {
    "addr:full":"41908 Via San Luis Rey Fremont CA 94539",
    "addr:housenumber":"41908",
    "addr:postcode":"94539",
    "addr:street":"Via San Luis Rey",
    "iso:country":"US",
    "sg:address":"41908 Via San Luis Rey",
    "sg:city":"Fremont",
    "sg:classifiers":[
        {
            "category":"Professional",
            "subcategory":"Management & Consulting",
            "type":"Services"
        }
    ],
    "sg:phone":"+1 510 498 8264",
    "sg:postcode":"94539",
    "sg:province":"CA",
    "sg:tags":[
        "consultant"
    ],
    "wof:name":"The Hansen Network",
    "wof:placetype":"venue"
},
  "geometry": {"coordinates":[-121.931085,37.541635],"type":"Point"}
}