{
  "type": "Feature",
  "properties": {
    "addr:full":"5120 Mowry Ave Fremont CA 94538",
    "addr:housenumber":"5120",
    "addr:postcode":"94538",
    "addr:street":"Mowry Ave",
    "iso:country":"US",
    "sg:address":"5120 Mowry Ave",
    "sg:city":"Fremont",
    "sg:classifiers":[
        {
            "category":"Banks & Credit Unions",
            "subcategory":"Bank",
            "type":"Services"
        }
    ],
    "sg:phone":"+1 510 791 0763",
    "sg:postcode":"94538",
    "sg:province":"CA",
    "wof:name":"Bank Of The West",
    "wof:placetype":"venue"
},
  "geometry": {"coordinates":[-121.99994100000001,37.534603],"type":"Point"}
}