{
  "type": "Feature",
  "properties": {
    "iso:country":"US",
    "sg:address":"667 Lytton Ave",
    "sg:city":"Palo Alto",
    "sg:classifiers":[
        {
            "category":"Social Services",
            "type":"Services"
        }
    ],
    "sg:phone":"+1 650 324 4343",
    "sg:postcode":"94301",
    "sg:province":"CA",
    "sg:tags":[
        "counselor",
        "marriage",
        "family"
    ],
    "wof:name":"Eva W Maiden",
    "wof:placetype":"venue"
},
  "geometry": {"coordinates":[-122.15837999999999,37.451307],"type":"Point"}
}