{
  "type": "Feature",
  "properties": {
    "addr:full":"401 I St Arcata CA 95521",
    "addr:housenumber":"401",
    "addr:postcode":"95521",
    "addr:street":"I St",
    "iso:country":"US",
    "sg:address":"401 I St",
    "sg:city":"Arcata",
    "sg:classifiers":[
        {
            "category":"Personal",
            "subcategory":"Beauty Salon",
            "type":"Services"
        }
    ],
    "sg:phone":"+1 707 822 3912",
    "sg:postcode":"95521",
    "sg:province":"CA",
    "wof:name":"Arcata Hair Shop",
    "wof:placetype":"venue"
},
  "geometry": {"coordinates":[-124.089043,40.866081],"type":"Point"}
}