{
  "type": "Feature",
  "properties": {
    "iso:country":"US",
    "sg:address":"16120 Valley Blvd",
    "sg:city":"Fontana",
    "sg:classifiers":[
        {
            "category":"Restaurant",
            "type":"Food & Drink"
        }
    ],
    "sg:phone":"+1 909 355 0241",
    "sg:postcode":"92335",
    "sg:province":"CA",
    "sg:tags":[
        "out"
    ],
    "wof:name":"LA Picosita Mexican Food",
    "wof:placetype":"venue"
},
  "geometry": {"coordinates":[-117.449154,34.070401],"type":"Point"}
}