{
  "type": "Feature",
  "properties": {
    "addr:full":"2252 Lincoln Ave San Jose CA 95125",
    "addr:housenumber":"2252",
    "addr:postcode":"95125",
    "addr:street":"Lincoln Ave",
    "iso:country":"US",
    "sg:address":"2252 Lincoln Ave",
    "sg:city":"San Jose",
    "sg:classifiers":[
        {
            "category":"Autos & Motor Vehicles",
            "subcategory":"Fuel & Gas Station",
            "type":"Retail Goods"
        }
    ],
    "sg:phone":"+1 408 266 9470",
    "sg:postcode":"95125",
    "sg:province":"CA",
    "wof:name":"Chevron Stations",
    "wof:placetype":"venue"
},
  "geometry": {"coordinates":[-121.88800000000001,37.2897],"type":"Point"}
}