{
  "type": "Feature",
  "properties": {
    "iso:country":"US",
    "sg:address":"821 Bubb Road",
    "sg:city":"Cupertino",
    "sg:classifiers":[
        {
            "category":"Education",
            "subcategory":"School",
            "type":"Public Place"
        }
    ],
    "sg:phone":"+1 408 253 1525",
    "sg:postcode":"95014",
    "sg:province":"CA",
    "sg:tags":[
        "high",
        "middle",
        "elementary"
    ],
    "sg:website":"www.cupertino.k12.ca.us",
    "wof:name":"Cupertino Union School District",
    "wof:placetype":"venue"
},
  "geometry": {"coordinates":[-122.050316,37.313193],"type":"Point"}
}