{
  "type": "Feature",
  "properties": {
    "iso:country":"US",
    "sg:address":"308 Southland Mall",
    "sg:city":"Hayward",
    "sg:classifiers":[
        {
            "category":"Shopping",
            "subcategory":"Clothing, Apparel, & Fashions",
            "type":"Retail Goods"
        },
        {
            "category":"Shopping",
            "subcategory":"Shoes",
            "type":"Retail Goods"
        }
    ],
    "sg:phone":"+1 510 782 2734",
    "sg:postcode":"94545",
    "sg:province":"CA",
    "sg:tags":[
        "apparel",
        "sportswear",
        "store",
        "women's"
    ],
    "sg:website":"http://www.ladyfootlocker.com/",
    "wof:name":"Lady Foot Locker",
    "wof:placetype":"venue"
},
  "geometry": {"coordinates":[-122.101074,37.654454],"type":"Point"}
}