{
  "type": "Feature",
  "properties": {
    "addr:full":"1337 Lincoln Ave San Jose CA 95125",
    "addr:housenumber":"1337",
    "addr:postcode":"95125",
    "addr:street":"Lincoln Ave",
    "iso:country":"US",
    "sg:address":"1337 Lincoln Ave",
    "sg:city":"San Jose",
    "sg:classifiers":[
        {
            "category":"Shopping",
            "subcategory":"Clothing, Apparel, & Fashions",
            "type":"Retail Goods"
        }
    ],
    "sg:phone":"+1 408 289 1844",
    "sg:postcode":"95125",
    "sg:province":"CA",
    "sg:tags":[
        "children's",
        "clothing"
    ],
    "wof:name":"Pink Lemonade",
    "wof:placetype":"venue"
},
  "geometry": {"coordinates":[-121.89805800000001,37.304441],"type":"Point"}
}