{
  "type": "Feature",
  "properties": {
    "iso:country":"US",
    "sg:address":"1 Bush St",
    "sg:city":"San Francisco",
    "sg:classifiers":[
        {
            "category":"Banks & Credit Unions",
            "subcategory":"Investment Brokerage",
            "type":"Services"
        }
    ],
    "sg:phone":"+1 415 274 6800",
    "sg:postcode":"94104",
    "sg:province":"CA",
    "sg:tags":[
        "security",
        "bond",
        "banker",
        "stock"
    ],
    "sg:website":"www.pacificgrowth.com",
    "wof:name":"Pacific Growth Equities Inc",
    "wof:placetype":"venue"
},
  "geometry": {"coordinates":[-122.39957200000001,37.791326],"type":"Point"}
}