{
  "type": "Feature",
  "properties": {
    "iso:country":"US",
    "sg:address":"3615 Madison Ave",
    "sg:city":"North Highlands",
    "sg:classifiers":[
        {
            "category":"Building & Trades",
            "subcategory":"Electrical",
            "type":"Services"
        }
    ],
    "sg:phone":"+1 916 648 8485",
    "sg:postcode":"95660",
    "sg:province":"CA",
    "sg:tags":[
        "communications",
        "contractor"
    ],
    "sg:website":"www.ever-green.com",
    "wof:name":"Ever-Green Communications",
    "wof:placetype":"venue"
},
  "geometry": {"coordinates":[-121.38066,38.660926],"type":"Point"}
}