{
  "type": "Feature",
  "properties": {
    "iso:country":"US",
    "sg:address":"1490 S Park Victoria Dr",
    "sg:city":"Milpitas",
    "sg:classifiers":[
        {
            "category":"Autos & Motor Vehicles",
            "subcategory":"Fuel & Gas Station",
            "type":"Retail Goods"
        }
    ],
    "sg:phone":"+1 408 263 2318",
    "sg:postcode":"95035",
    "sg:province":"CA",
    "wof:name":"Chevron Stations",
    "wof:placetype":"venue"
},
  "geometry": {"coordinates":[-121.875,37.416199],"type":"Point"}
}