{
  "type": "Feature",
  "properties": {
    "iso:country":"US",
    "sg:address":"1040 Los Osos Valley Rd",
    "sg:city":"Los Osos",
    "sg:classifiers":[
        {
            "category":"Building & Trades",
            "subcategory":"Construction",
            "type":"Services"
        }
    ],
    "sg:phone":"+1 805 528 7986",
    "sg:postcode":"93402",
    "sg:province":"CA",
    "sg:tags":[
        "repairing",
        "remodeling",
        "contractor"
    ],
    "wof:name":"Shong & Sons Construction Co",
    "wof:placetype":"venue"
},
  "geometry": {"coordinates":[-120.831676,35.311044],"type":"Point"}
}