{
  "type": "Feature",
  "properties": {
    "addr:full":"25592 Via del Rey San Juan Capistrano CA 92675",
    "addr:housenumber":"25592",
    "addr:postcode":"92675",
    "addr:street":"Via Del Rey",
    "iso:country":"US",
    "sg:address":"25592 Via del Rey",
    "sg:city":"San Juan Capistrano",
    "sg:classifiers":[
        {
            "category":"Banks & Credit Unions",
            "subcategory":"Bank",
            "type":"Services"
        }
    ],
    "sg:phone":"+1 949 496 9584",
    "sg:postcode":"92675",
    "sg:province":"CA",
    "sg:tags":[
        "broker",
        "mortgage"
    ],
    "wof:name":"Home Loan Network Services",
    "wof:placetype":"venue"
},
  "geometry": {"coordinates":[-117.68351699999999,33.48391],"type":"Point"}
}