{
  "type": "Feature",
  "properties": {
    "addr:full":"1481 Christine Ln Lemoore CA 93245",
    "addr:housenumber":"1481",
    "addr:postcode":"93245",
    "addr:street":"Christine Ln",
    "iso:country":"US",
    "sg:address":"1481 Christine Ln",
    "sg:city":"Lemoore",
    "sg:classifiers":[
        {
            "category":"Professional",
            "type":"Services"
        }
    ],
    "sg:phone":"+1 559 925 8317",
    "sg:postcode":"93245",
    "sg:province":"CA",
    "sg:tags":[
        "establishment"
    ],
    "wof:name":"California Correctional Peace",
    "wof:placetype":"venue"
},
  "geometry": {"coordinates":[-119.800443,36.291275],"type":"Point"}
}