{
  "type": "Feature",
  "properties": {
    "iso:country":"US",
    "sg:address":"1414 Center Ave",
    "sg:city":"Los Banos",
    "sg:classifiers":[
        {
            "category":"Home & Garden",
            "subcategory":"Hardware",
            "type":"Retail Goods"
        }
    ],
    "sg:phone":"+1 209 826 4492",
    "sg:postcode":"93635",
    "sg:province":"CA",
    "wof:name":"Sorensen's True Value Rental",
    "wof:placetype":"venue"
},
  "geometry": {"coordinates":[-120.854061,37.0558],"type":"Point"}
}