{
  "type": "Feature",
  "properties": {
    "addr:full":"1426 Burlingame Ave Burlingame CA 94010",
    "addr:housenumber":"1426",
    "addr:postcode":"94010",
    "addr:street":"Burlingame Ave",
    "iso:country":"US",
    "sg:address":"1426 Burlingame Ave",
    "sg:city":"Burlingame",
    "sg:classifiers":[
        {
            "category":"Shopping",
            "subcategory":"Clothing, Apparel, & Fashions",
            "type":"Retail Goods"
        }
    ],
    "sg:phone":"+1 650 347 2191",
    "sg:postcode":"94010",
    "sg:province":"CA",
    "sg:tags":[
        "furnishing"
    ],
    "sg:website":"www.malouf.net",
    "wof:name":"Malouf's",
    "wof:placetype":"venue"
},
  "geometry": {"coordinates":[-122.349673,37.576856],"type":"Point"}
}