{
  "type": "Feature",
  "properties": {
    "addr:full":"8101 Ruthwood Way Orangevale CA 95662",
    "addr:housenumber":"8101",
    "addr:postcode":"95662",
    "addr:street":"Ruthwood Way",
    "iso:country":"US",
    "sg:address":"8101 Ruthwood Way",
    "sg:city":"Orangevale",
    "sg:classifiers":[
        {
            "category":"Building & Trades",
            "subcategory":"Construction",
            "type":"Services"
        }
    ],
    "sg:phone":"+1 916 628 0900",
    "sg:postcode":"95662",
    "sg:province":"CA",
    "sg:tags":[
        "fence",
        "contractor"
    ],
    "wof:name":"Ryno Industries",
    "wof:placetype":"venue"
},
  "geometry": {"coordinates":[-121.25736000000001,38.691984],"type":"Point"}
}