{
  "type": "Feature",
  "properties": {
    "iso:country":"US",
    "sg:address":"12024 Lakewood Blvd",
    "sg:city":"Downey",
    "sg:classifiers":[
        {
            "category":"Ice Cream",
            "type":"Food & Drink"
        }
    ],
    "sg:menulink":"http://www.allmenus.com/ca/downey-norwalk/183815-cold-stone-creamery/menu/",
    "sg:phone":"+1 562 803 7848",
    "sg:postcode":"90242",
    "sg:province":"CA",
    "sg:tags":[
        "smoothy",
        "juice",
        "american"
    ],
    "wof:name":"Cold Stone Creamery",
    "wof:placetype":"venue"
},
  "geometry": {"coordinates":[-118.129796,33.927518],"type":"Point"}
}