{
  "type": "Feature",
  "properties": {
    "addr:full":"16415 Colima Rd Hacienda Heights CA 91745",
    "addr:housenumber":"16415",
    "addr:postcode":"91745",
    "addr:street":"Colima Rd",
    "iso:country":"US",
    "sg:address":"16415 Colima Rd",
    "sg:city":"Hacienda Heights",
    "sg:classifiers":[
        {
            "category":"Insurance",
            "subcategory":"Insurance Agent",
            "type":"Services"
        }
    ],
    "sg:phone":"+1 626 820 0234",
    "sg:postcode":"91745",
    "sg:province":"CA",
    "wof:name":"Farmers Insurance Group",
    "wof:placetype":"venue"
},
  "geometry": {"coordinates":[-117.94936800000001,33.987497],"type":"Point"}
}