{
  "type": "Feature",
  "properties": {
    "addr:full":"525 S Olive Street Los Angeles CA 90013",
    "addr:housenumber":"525",
    "addr:postcode":"90013",
    "addr:street":"S Olive Street",
    "iso:country":"US",
    "sg:address":"525 S Olive Street",
    "sg:city":"Los Angeles",
    "sg:classifiers":[
        {
            "category":"Health Services",
            "subcategory":"Dentist",
            "type":"Services"
        }
    ],
    "sg:phone":"+1 213 624 3333",
    "sg:postcode":"90013",
    "sg:province":"CA",
    "wof:name":"Levon Solak Dental Corporation",
    "wof:placetype":"venue"
},
  "geometry": {"coordinates":[-118.253333,34.048783],"type":"Point"}
}