{
  "type": "Feature",
  "properties": {
    "iso:country":"US",
    "sg:address":"2023 Foothill Blvd",
    "sg:city":"La Verne",
    "sg:classifiers":[
        {
            "category":"Food & Beverages",
            "subcategory":"Bakery",
            "type":"Retail Goods"
        }
    ],
    "sg:phone":"+1 909 593 4397",
    "sg:postcode":"91750",
    "sg:province":"CA",
    "sg:tags":[
        "doughnut"
    ],
    "wof:name":"Grand Donuts",
    "wof:placetype":"venue"
},
  "geometry": {"coordinates":[-117.766103,34.113708],"type":"Point"}
}