{
  "type": "Feature",
  "properties": {
    "iso:country":"US",
    "sg:address":"5755 Amarillo Ave",
    "sg:city":"La Mesa",
    "sg:classifiers":[
        {
            "category":"Food & Beverages",
            "subcategory":"Specialty",
            "type":"Retail Goods"
        }
    ],
    "sg:phone":"+1 619 458 7950",
    "sg:postcode":"91942",
    "sg:province":"CA",
    "wof:name":"Women Health Natural Solutions",
    "wof:placetype":"venue"
},
  "geometry": {"coordinates":[-117.01386100000001,32.783266],"type":"Point"}
}