{
  "type": "Feature",
  "properties": {
    "addr:full":"100 W Harvard Blvd Santa Paula CA 93060",
    "addr:housenumber":"100",
    "addr:postcode":"93060",
    "addr:street":"W Harvard Blvd",
    "iso:country":"US",
    "sg:address":"100 W Harvard Blvd",
    "sg:city":"Santa Paula",
    "sg:classifiers":[
        {
            "category":"Professional",
            "type":"Services"
        }
    ],
    "sg:phone":"+1 805 933 0899",
    "sg:postcode":"93060",
    "sg:province":"CA",
    "wof:name":"Arturo Alvarado",
    "wof:placetype":"venue"
},
  "geometry": {"coordinates":[-119.07287700000001,34.345988],"type":"Point"}
}