{
  "type": "Feature",
  "properties": {
    "addr:full":"4125 Kenway Ave Los Angeles CA 90008",
    "addr:housenumber":"4125",
    "addr:postcode":"90008",
    "addr:street":"Kenway Ave",
    "iso:country":"US",
    "sg:address":"4125 Kenway Ave",
    "sg:city":"Los Angeles",
    "sg:classifiers":[
        {
            "category":"Building & Trades",
            "subcategory":"Construction",
            "type":"Services"
        }
    ],
    "sg:phone":"+1 323 296 0916",
    "sg:postcode":"90008",
    "sg:province":"CA",
    "sg:tags":[
        "company"
    ],
    "wof:name":"Phoenician Construction",
    "wof:placetype":"venue"
},
  "geometry": {"coordinates":[-118.344144,34.00329],"type":"Point"}
}