{
  "type": "Feature",
  "properties": {
    "iso:country":"US",
    "sg:address":"7146 Topanga Canyon Blvd",
    "sg:city":"Canoga Park",
    "sg:classifiers":[
        {
            "category":"Utilities",
            "subcategory":"Mobile Phone",
            "type":"Services"
        }
    ],
    "sg:phone":"+1 818 888 8078",
    "sg:postcode":"91303",
    "sg:province":"CA",
    "sg:tags":[
        "stereo",
        "installation",
        "satellite"
    ],
    "wof:name":"No Static",
    "wof:placetype":"venue"
},
  "geometry": {"coordinates":[-118.606003,34.200199],"type":"Point"}
}