{
  "type": "Feature",
  "properties": {
    "addr:full":"6731 Five Star Blvd Rocklin CA 95677",
    "addr:housenumber":"6731",
    "addr:postcode":"95677",
    "addr:street":"Five Star Blvd",
    "iso:country":"US",
    "sg:address":"6731 Five Star Blvd",
    "sg:city":"Rocklin",
    "sg:classifiers":[
        {
            "category":"Building & Trades",
            "subcategory":"Landscaping Services",
            "type":"Services"
        }
    ],
    "sg:phone":"+1 916 632 0700",
    "sg:postcode":"95677",
    "sg:province":"CA",
    "sg:tags":[
        "landscape",
        "contractor"
    ],
    "wof:name":"Curb-It",
    "wof:placetype":"venue"
},
  "geometry": {"coordinates":[-121.264064,38.781042],"type":"Point"}
}