{
  "type": "Feature",
  "properties": {
    "iso:country":"US",
    "sg:address":"15720 Ventura Blvd",
    "sg:city":"Encino",
    "sg:classifiers":[
        {
            "category":"Health Services",
            "subcategory":"Health Practitioner",
            "type":"Services"
        }
    ],
    "sg:phone":"+1 818 788 2290",
    "sg:postcode":"91436",
    "sg:province":"CA",
    "sg:tags":[
        "nutritionist"
    ],
    "wof:name":"Jacob Hoban",
    "wof:placetype":"venue"
},
  "geometry": {"coordinates":[-118.47662,34.155322],"type":"Point"}
}