{
  "type": "Feature",
  "properties": {
    "iso:country":"US",
    "sg:address":"12183 Front St",
    "sg:city":"Norwalk",
    "sg:classifiers":[
        {
            "category":"Shopping",
            "subcategory":"Gifts & Souvenirs",
            "type":"Retail Goods"
        }
    ],
    "sg:phone":"+1 562 868 4418",
    "sg:postcode":"90650",
    "sg:province":"CA",
    "wof:name":"Balloons For Fun",
    "wof:placetype":"venue"
},
  "geometry": {"coordinates":[-118.074229,33.907644],"type":"Point"}
}