{
  "type": "Feature",
  "properties": {
    "addr:full":"1012 Swarthmore Ave Pacific Plsds CA 90272",
    "addr:housenumber":"1012",
    "addr:postcode":"90272",
    "addr:street":"Swarthmore Ave",
    "iso:country":"US",
    "sg:address":"1012 Swarthmore Ave",
    "sg:city":"Pacific Plsds",
    "sg:classifiers":[
        {
            "category":"Banks & Credit Unions",
            "subcategory":"Bank",
            "type":"Services"
        }
    ],
    "sg:phone":"+1 310 454 0972",
    "sg:postcode":"90272",
    "sg:province":"CA",
    "sg:website":"www.wellsfargo.com",
    "wof:name":"Wells Fargo Bank",
    "wof:placetype":"venue"
},
  "geometry": {"coordinates":[-118.524641,34.048101],"type":"Point"}
}