{
  "type": "Feature",
  "properties": {
    "addr:full":"29710 Watson Rd Romoland CA 92585",
    "addr:housenumber":"29710",
    "addr:postcode":"92585",
    "addr:street":"Watson Rd",
    "iso:country":"US",
    "sg:address":"29710 Watson Rd",
    "sg:city":"Romoland",
    "sg:classifiers":[
        {
            "category":"Retail",
            "subcategory":"Animal Services",
            "type":"Services"
        }
    ],
    "sg:phone":"+1 951 928 0307",
    "sg:postcode":"92585",
    "sg:province":"CA",
    "sg:tags":[
        "breeder",
        "horse"
    ],
    "wof:name":"C & L Paint Horses",
    "wof:placetype":"venue"
},
  "geometry": {"coordinates":[-117.144887,33.750511],"type":"Point"}
}