{
  "type": "Feature",
  "properties": {
    "iso:country":"US",
    "sg:address":"724 Almond St",
    "sg:city":"Yuba City",
    "sg:classifiers":[
        {
            "category":"Professional",
            "type":"Services"
        }
    ],
    "sg:phone":"+1 530 673 0112",
    "sg:postcode":"95991",
    "sg:province":"CA",
    "sg:tags":[
        "establishment"
    ],
    "wof:name":"American Porcelain",
    "wof:placetype":"venue"
},
  "geometry": {"coordinates":[-121.618997,39.136205],"type":"Point"}
}