{
  "type": "Feature",
  "properties": {
    "iso:country":"US",
    "sg:address":"2640 S La Cienega Blvd",
    "sg:city":"Los Angeles",
    "sg:classifiers":[
        {
            "category":"Retail",
            "subcategory":"Repair Shop",
            "type":"Services"
        }
    ],
    "sg:phone":"+1 323 931 3240",
    "sg:postcode":"90034",
    "sg:province":"CA",
    "sg:tags":[
        "reupholstery",
        "furniture"
    ],
    "wof:name":"Prestigio Custom Furniture-Upholstery",
    "wof:placetype":"venue"
},
  "geometry": {"coordinates":[-118.376999,34.0341],"type":"Point"}
}