{
  "type": "Feature",
  "properties": {
    "addr:full":"10172 Florin Ln Anaheim CA 92804",
    "addr:housenumber":"10172",
    "addr:postcode":"92804",
    "addr:street":"Florin Ln",
    "iso:country":"US",
    "sg:address":"10172 Florin Ln",
    "sg:city":"Anaheim",
    "sg:classifiers":[
        {
            "category":"Professional",
            "type":"Services"
        }
    ],
    "sg:phone":"+1 714 974 2320",
    "sg:postcode":"92804",
    "sg:province":"CA",
    "wof:name":"Sean Vin Corp",
    "wof:placetype":"venue"
},
  "geometry": {"coordinates":[-117.966667,33.815025],"type":"Point"}
}