{
  "type": "Feature",
  "properties": {
    "iso:country":"US",
    "sg:address":"4838 Carfax Ave",
    "sg:city":"Lakewood",
    "sg:classifiers":[
        {
            "category":"Retail",
            "subcategory":"Repair Shop",
            "type":"Services"
        }
    ],
    "sg:phone":"+1 562 496 1524",
    "sg:postcode":"90713",
    "sg:province":"CA",
    "sg:tags":[
        "lock",
        "locksmith"
    ],
    "wof:name":"Security Lock & Key",
    "wof:placetype":"venue"
},
  "geometry": {"coordinates":[-118.10957000000001,33.844288],"type":"Point"}
}