{
  "type": "Feature",
  "properties": {
    "addr:full":"918 Clement St San Francisco CA 94118",
    "addr:housenumber":"918",
    "addr:postcode":"94118",
    "addr:street":"Clement St",
    "iso:country":"US",
    "sg:address":"918 Clement St",
    "sg:city":"San Francisco",
    "sg:classifiers":[
        {
            "category":"Insurance",
            "subcategory":"Insurance Agent",
            "type":"Services"
        }
    ],
    "sg:phone":"+1 415 668 8801",
    "sg:postcode":"94118",
    "sg:province":"CA",
    "wof:name":"William Wong Insurance Agency",
    "wof:placetype":"venue"
},
  "geometry": {"coordinates":[-122.46962000000001,37.782786],"type":"Point"}
}