{
  "type": "Feature",
  "properties": {
    "addr:full":"10801 Alandale Way Rancho Cordova CA 95670",
    "addr:housenumber":"10801",
    "addr:postcode":"95670",
    "addr:street":"Alandale Way",
    "iso:country":"US",
    "sg:address":"10801 Alandale Way",
    "sg:city":"Rancho Cordova",
    "sg:classifiers":[
        {
            "category":"Building & Trades",
            "subcategory":"Cleaning & Sanitation",
            "type":"Services"
        }
    ],
    "sg:phone":"+1 916 638 9313",
    "sg:postcode":"95670",
    "sg:province":"CA",
    "sg:tags":[
        "janitor"
    ],
    "wof:name":"Lucky Don Cleaning",
    "wof:placetype":"venue"
},
  "geometry": {"coordinates":[-121.283058,38.60201],"type":"Point"}
}