{
  "type": "Feature",
  "properties": {
    "iso:country":"US",
    "sg:address":"1338 Trouville Ave",
    "sg:city":"Grover Beach",
    "sg:classifiers":[
        {
            "category":"Shopping",
            "subcategory":"Bicycles & Sporting Goods",
            "type":"Retail Goods"
        }
    ],
    "sg:phone":"+1 805 489 8332",
    "sg:postcode":"93433",
    "sg:province":"CA",
    "sg:tags":[
        "tackle",
        "fishing"
    ],
    "wof:name":"Bob's Tackle Too",
    "wof:placetype":"venue"
},
  "geometry": {"coordinates":[-120.615309,35.116028],"type":"Point"}
}