{
  "type": "Feature",
  "properties": {
    "iso:country":"US",
    "sg:address":"9550 Bolsa Ave Ste 107",
    "sg:city":"Westminster",
    "sg:classifiers":[
        {
            "category":"Education",
            "subcategory":"Music School",
            "type":"Public Place"
        }
    ],
    "sg:phone":"+1 714 839 5178",
    "sg:postcode":"92683",
    "sg:province":"CA",
    "sg:tags":[
        "instrument",
        "teacher",
        "musical"
    ],
    "wof:name":"U Play Musical Instruments",
    "wof:placetype":"venue"
},
  "geometry": {"coordinates":[-117.962997,33.7449],"type":"Point"}
}