{
  "type": "Feature",
  "properties": {
    "iso:country":"US",
    "sg:address":"17684 River Run Rd",
    "sg:city":"Salinas",
    "sg:classifiers":[
        {
            "category":"Retail",
            "subcategory":"Repair Shop",
            "type":"Services"
        }
    ],
    "sg:phone":"+1 831 455 9479",
    "sg:postcode":"93908",
    "sg:province":"CA",
    "sg:tags":[
        "upholsterer"
    ],
    "wof:name":"Reborn Upholstery",
    "wof:placetype":"venue"
},
  "geometry": {"coordinates":[-121.664619,36.620247],"type":"Point"}
}