{
  "type": "Feature",
  "properties": {
    "addr:full":"1 California Street San Francisco CA 94111",
    "addr:housenumber":"1",
    "addr:postcode":"94111",
    "addr:street":"California Street",
    "iso:country":"US",
    "sg:address":"1 California Street",
    "sg:city":"San Francisco",
    "sg:classifiers":[
        {
            "category":"Professional",
            "subcategory":"Lawyer & Legal Services",
            "type":"Services"
        }
    ],
    "sg:phone":"+1 415 693 5566",
    "sg:postcode":"94111",
    "sg:province":"CA",
    "sg:website":"www.fdw-law.com",
    "wof:name":"Peterson L Faye",
    "wof:placetype":"venue"
},
  "geometry": {"coordinates":[-122.396434,37.79356],"type":"Point"}
}