{
  "type": "Feature",
  "properties": {
    "iso:country":"US",
    "sg:address":"4650 Udell Rd",
    "sg:city":"Vacaville",
    "sg:classifiers":[
        {
            "category":"Retail",
            "subcategory":"Animal Services",
            "type":"Services"
        }
    ],
    "sg:phone":"+1 707 449 8776",
    "sg:postcode":"95688",
    "sg:province":"CA",
    "sg:tags":[
        "personal",
        "pet",
        "grooming",
        "washing"
    ],
    "wof:name":"Jackie's Grooming",
    "wof:placetype":"venue"
},
  "geometry": {"coordinates":[-121.960062,38.434881],"type":"Point"}
}