{
  "type": "Feature",
  "properties": {
    "addr:full":"11 San Gabriel Dr Chico CA 95973",
    "addr:housenumber":"11",
    "addr:postcode":"95973",
    "addr:street":"San Gabriel Dr",
    "iso:country":"US",
    "sg:address":"11 San Gabriel Dr",
    "sg:city":"Chico",
    "sg:classifiers":[
        {
            "category":"Building & Trades",
            "subcategory":"Electrical",
            "type":"Services"
        }
    ],
    "sg:phone":"+1 530 343 9282",
    "sg:postcode":"95973",
    "sg:province":"CA",
    "sg:tags":[
        "electrical",
        "contractor"
    ],
    "wof:name":"Voelker Electric",
    "wof:placetype":"venue"
},
  "geometry": {"coordinates":[-121.85766099999999,39.769655],"type":"Point"}
}