{
  "type": "Feature",
  "properties": {
    "addr:full":"2200 E California Ave Bakersfield CA 93307",
    "addr:housenumber":"2200",
    "addr:postcode":"93307",
    "addr:street":"E California Ave",
    "iso:country":"US",
    "sg:address":"2200 E California Ave",
    "sg:city":"Bakersfield",
    "sg:classifiers":[
        {
            "category":"Autos & Motor Vehicles",
            "subcategory":"Auto Supplies",
            "type":"Retail Goods"
        }
    ],
    "sg:phone":"+1 661 324 7039",
    "sg:postcode":"93307",
    "sg:province":"CA",
    "sg:tags":[
        "tire"
    ],
    "wof:name":"Gutierrez New & Used Tires",
    "wof:placetype":"venue"
},
  "geometry": {"coordinates":[-118.9653,35.368609],"type":"Point"}
}