{
  "type": "Feature",
  "properties": {
    "iso:country":"US",
    "sg:address":"1400 Goodrich Blvd",
    "sg:city":"Los Angeles",
    "sg:classifiers":[
        {
            "category":"Health Services",
            "subcategory":"Health Practitioner",
            "type":"Services"
        }
    ],
    "sg:phone":"+1 323 724 1799",
    "sg:postcode":"90022",
    "sg:province":"CA",
    "sg:tags":[
        "nurse",
        "registry"
    ],
    "wof:name":"B & R Nursing School",
    "wof:placetype":"venue"
},
  "geometry": {"coordinates":[-118.15812,34.011764],"type":"Point"}
}