{
  "type": "Feature",
  "properties": {
    "addr:full":"721 The Alameda Berkeley CA 94707",
    "addr:housenumber":"721",
    "addr:postcode":"94707",
    "addr:street":"The Alameda",
    "iso:country":"US",
    "sg:address":"721 The Alameda",
    "sg:city":"Berkeley",
    "sg:classifiers":[
        {
            "category":"Professional",
            "subcategory":"Research",
            "type":"Services"
        },
        {
            "category":"Education",
            "subcategory":"Library",
            "type":"Public Place"
        }
    ],
    "sg:phone":"+1 510 527 2634",
    "sg:postcode":"94707",
    "sg:province":"CA",
    "wof:name":"Feldenkrais Movement Institute",
    "wof:placetype":"venue"
},
  "geometry": {"coordinates":[-122.277939,37.895248],"type":"Point"}
}