{
  "type": "Feature",
  "properties": {
    "addr:full":"18400 Von Karman Avenue Suite 800 Irvine CA 92612",
    "addr:housenumber":"18400",
    "addr:postcode":"92612",
    "addr:street":"Von Karman Avenue Suite 800",
    "iso:country":"US",
    "sg:address":"18400 Von Karman Avenue Suite 800",
    "sg:city":"Irvine",
    "sg:classifiers":[
        {
            "category":"Professional",
            "subcategory":"Lawyer & Legal Services",
            "type":"Services"
        }
    ],
    "sg:phone":"+1 949 760 1121",
    "sg:postcode":"92612",
    "sg:province":"CA",
    "wof:name":"Buchalter Nemer A Professional Corporation",
    "wof:placetype":"venue"
},
  "geometry": {"coordinates":[-117.829486,33.662148],"type":"Point"}
}