{
  "type": "Feature",
  "properties": {
    "addr:full":"1030 Carolyn Ave San Jose CA 95125",
    "addr:housenumber":"1030",
    "addr:postcode":"95125",
    "addr:street":"Carolyn Ave",
    "iso:country":"US",
    "sg:address":"1030 Carolyn Ave",
    "sg:city":"San Jose",
    "sg:classifiers":[
        {
            "category":"Farming",
            "subcategory":"Farm & Veterinary Services",
            "type":"Manufacturing & Wholesale Goods"
        }
    ],
    "sg:phone":"+1 408 286 4686",
    "sg:postcode":"95125",
    "sg:province":"CA",
    "sg:tags":[
        "preparation",
        "crop",
        "for",
        "market"
    ],
    "wof:name":"Kafka & Assoc Business Comm",
    "wof:placetype":"venue"
},
  "geometry": {"coordinates":[-121.906273,37.30892],"type":"Point"}
}