{
  "type": "Feature",
  "properties": {
    "addr:full":"3114 Del Monte Blvd Marina CA 93933",
    "addr:housenumber":"3114",
    "addr:postcode":"93933",
    "addr:street":"Del Monte Blvd",
    "iso:country":"US",
    "sg:address":"3114 Del Monte Blvd",
    "sg:city":"Marina",
    "sg:classifiers":[
        {
            "category":"Restaurant",
            "type":"Food & Drink"
        }
    ],
    "sg:phone":"+1 831 384 6665",
    "sg:postcode":"93933",
    "sg:province":"CA",
    "sg:tags":[
        "japanese"
    ],
    "wof:name":"Michi Japanese Restaurant",
    "wof:placetype":"venue"
},
  "geometry": {"coordinates":[-121.801768,36.685259],"type":"Point"}
}