{
  "type": "Feature",
  "properties": {
    "iso:country":"US",
    "sg:address":"4871 Lankershim Blvd",
    "sg:city":"North Hollywood",
    "sg:classifiers":[
        {
            "category":"Building & Trades",
            "subcategory":"Construction",
            "type":"Services"
        }
    ],
    "sg:phone":"+1 818 754 0331",
    "sg:postcode":"91601",
    "sg:province":"CA",
    "sg:tags":[
        "erectors",
        "machinery"
    ],
    "wof:name":"All Day Inc",
    "wof:placetype":"venue"
},
  "geometry": {"coordinates":[-118.370896,34.158722],"type":"Point"}
}