{
  "type": "Feature",
  "properties": {
    "addr:full":"19741 Hwy 78 Ramona CA 92065",
    "addr:housenumber":"19741",
    "addr:postcode":"92065",
    "addr:street":"Hwy 78",
    "iso:country":"US",
    "sg:address":"19741 Hwy 78",
    "sg:city":"Ramona",
    "sg:classifiers":[
        {
            "category":"Building & Trades",
            "subcategory":"Construction",
            "type":"Services"
        }
    ],
    "sg:phone":"+1 760 788 8920",
    "sg:postcode":"92065",
    "sg:province":"CA",
    "sg:tags":[
        "grading",
        "contractor"
    ],
    "wof:name":"Greg Garner Grading",
    "wof:placetype":"venue"
},
  "geometry": {"coordinates":[-116.902884,33.075447],"type":"Point"}
}