{
  "type": "Feature",
  "properties": {
    "addr:full":"330 Sausalito Blvd Sausalito CA 94965",
    "addr:housenumber":"330",
    "addr:postcode":"94965",
    "addr:street":"Sausalito Blvd",
    "iso:country":"US",
    "sg:address":"330 Sausalito Blvd",
    "sg:city":"Sausalito",
    "sg:classifiers":[
        {
            "category":"Professional",
            "type":"Services"
        }
    ],
    "sg:phone":"+1 415 332 9562",
    "sg:postcode":"94965",
    "sg:province":"CA",
    "wof:name":"Rls Systems Inc",
    "wof:placetype":"venue"
},
  "geometry": {"coordinates":[-122.483814,37.848038],"type":"Point"}
}