{
  "type": "Feature",
  "properties": {
    "addr:full":"720 S Rampart Boulevard Los Angeles CA 90057",
    "addr:housenumber":"720",
    "addr:postcode":"90057",
    "addr:street":"S Rampart Boulevard",
    "iso:country":"US",
    "sg:address":"720 S Rampart Boulevard",
    "sg:city":"Los Angeles",
    "sg:classifiers":[
        {
            "category":"Health Services",
            "subcategory":"Hospital",
            "type":"Services"
        }
    ],
    "sg:phone":"+1 213 381 2931",
    "sg:postcode":"90057",
    "sg:province":"CA",
    "wof:name":"St Anne's",
    "wof:placetype":"venue"
},
  "geometry": {"coordinates":[-118.28367900000001,34.058873],"type":"Point"}
}