{
  "type": "Feature",
  "properties": {
    "iso:country":"US",
    "sg:address":"2608 San Juan Rd",
    "sg:city":"Aromas",
    "sg:classifiers":[
        {
            "category":"Farming",
            "subcategory":"Farm",
            "type":"Manufacturing & Wholesale Goods"
        }
    ],
    "sg:phone":"+1 831 726 2583",
    "sg:postcode":"95004",
    "sg:province":"CA",
    "sg:tags":[
        "crop",
        "general"
    ],
    "wof:name":"Vincent Matulich Farms",
    "wof:placetype":"venue"
},
  "geometry": {"coordinates":[-121.65720399999999,36.861514],"type":"Point"}
}