{
  "type": "Feature",
  "properties": {
    "addr:full":"7166 Amethyst Ave Alta Loma CA 91701",
    "addr:housenumber":"7166",
    "addr:postcode":"91701",
    "addr:street":"Amethyst Ave",
    "iso:country":"US",
    "sg:address":"7166 Amethyst Ave",
    "sg:city":"Alta Loma",
    "sg:classifiers":[
        {
            "category":"Wholesale",
            "subcategory":"Farm Supplies",
            "type":"Manufacturing & Wholesale Goods"
        }
    ],
    "sg:phone":"+1 909 466 2555",
    "sg:postcode":"91701",
    "sg:province":"CA",
    "sg:tags":[
        "feed"
    ],
    "wof:name":"Alta Loma Feed & Tack",
    "wof:placetype":"venue"
},
  "geometry": {"coordinates":[-117.598263,34.123577],"type":"Point"}
}