{
  "type": "Feature",
  "properties": {
    "addr:full":"10801 National Blvd Ste 340 Los Angeles CA 90064",
    "addr:housenumber":"10801",
    "addr:postcode":"90064",
    "addr:street":"National Blvd Ste 340",
    "iso:country":"US",
    "sg:address":"10801 National Blvd Ste 340",
    "sg:city":"Los Angeles",
    "sg:classifiers":[
        {
            "category":"Health Services",
            "subcategory":"Chiropractor",
            "type":"Services"
        }
    ],
    "sg:phone":"+1 310 470 1225",
    "sg:postcode":"90064",
    "sg:province":"CA",
    "sg:website":"fayechiro.chiroweb.com",
    "wof:name":"Faye & Faye Chiropractic",
    "wof:placetype":"venue"
},
  "geometry": {"coordinates":[-118.420362,34.031294],"type":"Point"}
}