{
  "type": "Feature",
  "properties": {
    "iso:country":"US",
    "sg:address":"4053 8th Avenue",
    "sg:city":"San Diego",
    "sg:classifiers":[
        {
            "category":"Real Estate",
            "subcategory":"Real Estate Operator",
            "type":"Services"
        }
    ],
    "sg:phone":"+1 619 297 0269",
    "sg:postcode":"92103",
    "sg:province":"CA",
    "sg:tags":[
        "apartment"
    ],
    "wof:name":"Melrose Canyon Apartments",
    "wof:placetype":"venue"
},
  "geometry": {"coordinates":[-117.157433,32.750629],"type":"Point"}
}