{
  "type": "Feature",
  "properties": {
    "iso:country":"US",
    "sg:address":"766 N 2nd St",
    "sg:city":"El Cajon",
    "sg:classifiers":[
        {
            "category":"Professional",
            "subcategory":"Accounting & Tax Preparation",
            "type":"Services"
        }
    ],
    "sg:phone":"+1 619 444 2055",
    "sg:postcode":"92021",
    "sg:province":"CA",
    "sg:tags":[
        "return",
        "filing"
    ],
    "wof:name":"King Tax Svc",
    "wof:placetype":"venue"
},
  "geometry": {"coordinates":[-116.935816,32.804346],"type":"Point"}
}