{
  "type": "Feature",
  "properties": {
    "addr:full":"425 W Valley Blvd San Gabriel CA 91776",
    "addr:housenumber":"425",
    "addr:postcode":"91776",
    "addr:street":"W Valley Blvd",
    "iso:country":"US",
    "sg:address":"425 W Valley Blvd",
    "sg:city":"San Gabriel",
    "sg:classifiers":[
        {
            "category":"Retail",
            "subcategory":"Photofinishing",
            "type":"Services"
        }
    ],
    "sg:phone":"+1 626 576 5496",
    "sg:postcode":"91776",
    "sg:province":"CA",
    "sg:tags":[
        "photo",
        "finishing"
    ],
    "wof:name":"Qian Xi Photography Studio",
    "wof:placetype":"venue"
},
  "geometry": {"coordinates":[-118.106419,34.079487],"type":"Point"}
}