{
  "type": "Feature",
  "properties": {
    "iso:country":"US",
    "sg:address":"10820 Beverly Blvd",
    "sg:city":"Whittier",
    "sg:classifiers":[
        {
            "category":"Freight",
            "type":"Transportation"
        }
    ],
    "sg:phone":"+1 562 692 0991",
    "sg:postcode":"90601",
    "sg:province":"CA",
    "sg:tags":[
        "shipping",
        "agent"
    ],
    "wof:name":"Mailroom",
    "wof:placetype":"venue"
},
  "geometry": {"coordinates":[-118.054644,33.997503],"type":"Point"}
}