{
  "type": "Feature",
  "properties": {
    "addr:full":"1675 E Mariposa Rd Stockton CA 95205",
    "addr:housenumber":"1675",
    "addr:postcode":"95205",
    "addr:street":"E Mariposa Rd",
    "iso:country":"US",
    "sg:address":"1675 E Mariposa Rd",
    "sg:city":"Stockton",
    "sg:classifiers":[
        {
            "category":"Restaurant",
            "type":"Food & Drink"
        }
    ],
    "sg:phone":"+1 209 463 9044",
    "sg:postcode":"95205",
    "sg:province":"CA",
    "sg:tags":[
        "mexican"
    ],
    "wof:name":"Garibaldi Restaurant",
    "wof:placetype":"venue"
},
  "geometry": {"coordinates":[-121.251801,37.942776],"type":"Point"}
}