{
  "type": "Feature",
  "properties": {
    "iso:country":"US",
    "sg:address":"851 Burlway Rd",
    "sg:city":"Burlingame",
    "sg:classifiers":[
        {
            "category":"Professional",
            "subcategory":"Management & Consulting",
            "type":"Services"
        }
    ],
    "sg:phone":"+1 650 347 7747",
    "sg:postcode":"94010",
    "sg:province":"CA",
    "sg:tags":[
        "consultant"
    ],
    "wof:name":"MHG Consulting Co",
    "wof:placetype":"venue"
},
  "geometry": {"coordinates":[-122.366412,37.595366],"type":"Point"}
}