{
  "type": "Feature",
  "properties": {
    "addr:full":"205 E Pine St Fort Bragg CA 95437",
    "addr:housenumber":"205",
    "addr:postcode":"95437",
    "addr:street":"E Pine St",
    "iso:country":"US",
    "sg:address":"205 E Pine St",
    "sg:city":"Fort Bragg",
    "sg:classifiers":[
        {
            "category":"Health Services",
            "subcategory":"Optometrist",
            "type":"Services"
        }
    ],
    "sg:phone":"+1 707 961 1037",
    "sg:postcode":"95437",
    "sg:province":"CA",
    "wof:name":"Lynette Kline OD",
    "wof:placetype":"venue"
},
  "geometry": {"coordinates":[-123.804483,39.446826],"type":"Point"}
}