{
  "type": "Feature",
  "properties": {
    "iso:country":"US",
    "sg:address":"550 Nelson Ln",
    "sg:city":"Lincoln",
    "sg:classifiers":[
        {
            "category":"Professional",
            "subcategory":"Management & Consulting",
            "type":"Services"
        }
    ],
    "sg:phone":"+1 916 645 1477",
    "sg:postcode":"95648",
    "sg:province":"CA",
    "sg:tags":[
        "consultant",
        "business"
    ],
    "wof:name":"RDP Assoc",
    "wof:placetype":"venue"
},
  "geometry": {"coordinates":[-121.340155,38.878641],"type":"Point"}
}