{
  "type": "Feature",
  "properties": {
    "addr:full":"1 H St San Rafael CA 94901",
    "addr:housenumber":"1",
    "addr:postcode":"94901",
    "addr:street":"H St",
    "iso:country":"US",
    "sg:address":"1 H St",
    "sg:city":"San Rafael",
    "sg:classifiers":[
        {
            "category":"Wholesale",
            "subcategory":"Office Equipment",
            "type":"Manufacturing & Wholesale Goods"
        }
    ],
    "sg:phone":"+1 415 456 6740",
    "sg:postcode":"94901",
    "sg:province":"CA",
    "sg:tags":[
        "credit",
        "system",
        "card"
    ],
    "wof:name":"Zairecords",
    "wof:placetype":"venue"
},
  "geometry": {"coordinates":[-122.538432,37.97518],"type":"Point"}
}