{
  "type": "Feature",
  "properties": {
    "addr:full":"122 E Oak St Stockton CA 95202",
    "addr:housenumber":"122",
    "addr:postcode":"95202",
    "addr:street":"E Oak St",
    "iso:country":"US",
    "sg:address":"122 E Oak St",
    "sg:city":"Stockton",
    "sg:classifiers":[
        {
            "category":"Restaurant",
            "type":"Food & Drink"
        }
    ],
    "sg:phone":"+1 209 941 0881",
    "sg:postcode":"95202",
    "sg:province":"CA",
    "wof:name":"Mr D's Pizza & Sports Club",
    "wof:placetype":"venue"
},
  "geometry": {"coordinates":[-121.290328,37.958791],"type":"Point"}
}