{
  "type": "Feature",
  "properties": {
    "addr:full":"3692 Beechwood Pl Riverside CA 92506",
    "addr:housenumber":"3692",
    "addr:postcode":"92506",
    "addr:street":"Beechwood Pl",
    "iso:country":"US",
    "sg:address":"3692 Beechwood Pl",
    "sg:city":"Riverside",
    "sg:classifiers":[
        {
            "category":"Professional",
            "subcategory":"Accounting & Tax Preparation",
            "type":"Services"
        }
    ],
    "sg:phone":"+1 951 787 0491",
    "sg:postcode":"92506",
    "sg:province":"CA",
    "sg:tags":[
        "accountant"
    ],
    "wof:name":"William D Winchell CPA",
    "wof:placetype":"venue"
},
  "geometry": {"coordinates":[-117.38581499999999,33.96746],"type":"Point"}
}