{
  "type": "Feature",
  "properties": {
    "iso:country":"US",
    "sg:address":"3692 Beechwood Pl",
    "sg:city":"Riverside",
    "sg:classifiers":[
        {
            "category":"Professional",
            "subcategory":"Accounting & Tax Preparation",
            "type":"Services"
        }
    ],
    "sg:phone":"+1 951 787 0491",
    "sg:postcode":"92506",
    "sg:province":"CA",
    "sg:tags":[
        "accountant"
    ],
    "wof:name":"William D Winchell CPA",
    "wof:placetype":"venue"
},
  "geometry": {"coordinates":[-117.385815,33.96746],"type":"Point"}
}