{
  "type": "Feature",
  "properties": {
    "iso:country":"US",
    "sg:address":"Jasmine Ave",
    "sg:city":"Los Angeles",
    "sg:classifiers":[
        {
            "category":"Professional",
            "subcategory":"Art Services",
            "type":"Services"
        },
        {
            "category":"Retail",
            "subcategory":"Animal Services",
            "type":"Services"
        }
    ],
    "sg:postcode":"90034",
    "sg:province":"CA",
    "sg:tags":[
        "pet",
        "photographer"
    ],
    "sg:website":"www.shinepetphotos.com",
    "wof:name":"Shine Pet Photos",
    "wof:placetype":"venue"
},
  "geometry": {"coordinates":[-118.404388,34.024941],"type":"Point"}
}