{
  "type": "Feature",
  "properties": {
    "iso:country":"US",
    "sg:address":"469 Pioneer Ave",
    "sg:city":"Woodland",
    "sg:classifiers":[
        {
            "category":"Restaurant",
            "type":"Food & Drink"
        }
    ],
    "sg:phone":"+1 530 666 7474",
    "sg:postcode":"95776",
    "sg:province":"CA",
    "sg:tags":[
        "asian",
        "pan",
        "japanese"
    ],
    "wof:name":"I Love Teriyaki",
    "wof:placetype":"venue"
},
  "geometry": {"coordinates":[-121.746408,38.674098],"type":"Point"}
}