{
  "type": "Feature",
  "properties": {
    "iso:country":"US",
    "sg:address":"520 W Main Ave",
    "sg:city":"Crows Landing",
    "sg:classifiers":[
        {
            "category":"Building & Trades",
            "subcategory":"Construction",
            "type":"Services"
        }
    ],
    "sg:phone":"+1 209 634 6018",
    "sg:postcode":"95313",
    "sg:province":"CA",
    "sg:tags":[
        "pond",
        "supply"
    ],
    "wof:name":"Central Valley Koi",
    "wof:placetype":"venue"
},
  "geometry": {"coordinates":[-120.99809999999999,37.492931],"type":"Point"}
}