{
  "type": "Feature",
  "properties": {
    "addr:full":"2000 Ralston Avenue Belmont CA 94002",
    "addr:housenumber":"2000",
    "addr:postcode":"94002",
    "addr:street":"Ralston Avenue",
    "iso:country":"US",
    "sg:address":"2000 Ralston Avenue",
    "sg:city":"Belmont",
    "sg:classifiers":[
        {
            "category":"Retail",
            "subcategory":"Auto Repair",
            "type":"Services"
        }
    ],
    "sg:phone":"+1 650 592 3637",
    "sg:postcode":"94002",
    "sg:province":"CA",
    "sg:website":"www.shell.com",
    "wof:name":"Belmont Shell",
    "wof:placetype":"venue"
},
  "geometry": {"coordinates":[-122.293643,37.512488],"type":"Point"}
}