{
  "type": "Feature",
  "properties": {
    "iso:country":"US",
    "sg:address":"7853 Pearblossom Hwy",
    "sg:city":"Littlerock",
    "sg:classifiers":[
        {
            "category":"Retail",
            "subcategory":"Auto Repair",
            "type":"Services"
        }
    ],
    "sg:phone":"+1 661 944 6118",
    "sg:postcode":"93543",
    "sg:province":"CA",
    "sg:tags":[
        "repairing",
        "automobile"
    ],
    "wof:name":"Monreal Auto Repair",
    "wof:placetype":"venue"
},
  "geometry": {"coordinates":[-117.990668,34.521149],"type":"Point"}
}