{
  "type": "Feature",
  "properties": {
    "iso:country":"US",
    "sg:address":"10565 Portsmouth Ct",
    "sg:city":"Riverside",
    "sg:classifiers":[
        {
            "category":"Freight",
            "type":"Transportation"
        }
    ],
    "sg:phone":"+1 951 359 0851",
    "sg:postcode":"92503",
    "sg:province":"CA",
    "sg:tags":[
        "operator",
        "local",
        "trucking"
    ],
    "wof:name":"Als Trucking",
    "wof:placetype":"venue"
},
  "geometry": {"coordinates":[-117.46093999999999,33.901282],"type":"Point"}
}