{
  "type": "Feature",
  "properties": {
    "addr:full":"4743 Slauson Ave Maywood CA 90270",
    "addr:housenumber":"4743",
    "addr:postcode":"90270",
    "addr:street":"Slauson Ave",
    "iso:country":"US",
    "sg:address":"4743 Slauson Ave",
    "sg:city":"Maywood",
    "sg:classifiers":[
        {
            "category":"Education",
            "subcategory":"Preschool",
            "type":"Public Place"
        },
        {
            "category":"Education",
            "subcategory":"School",
            "type":"Public Place"
        }
    ],
    "sg:phone":"+1 323 562 4776",
    "sg:postcode":"90270",
    "sg:province":"CA",
    "sg:tags":[
        "elementary"
    ],
    "wof:name":"Tri-City Headstart",
    "wof:placetype":"venue"
},
  "geometry": {"coordinates":[-118.18014100000001,33.986822],"type":"Point"}
}