{
  "type": "Feature",
  "properties": {
    "addr:full":"203 Redwood Shores Parkway Suite 280 Redwood City CA 94065",
    "addr:housenumber":"203",
    "addr:postcode":"94065",
    "addr:street":"Redwood Shores Parkway Suite 280",
    "iso:country":"US",
    "sg:address":"203 Redwood Shores Parkway Suite 280",
    "sg:city":"Redwood City",
    "sg:classifiers":[
        {
            "category":"Professional",
            "subcategory":"Computer Services",
            "type":"Services"
        }
    ],
    "sg:phone":"+1 650 264 5900",
    "sg:postcode":"94065",
    "sg:province":"CA",
    "sg:tags":[
        "enterprise-cloud-management",
        "private-cloud",
        "cloud-management",
        "open-source",
        "cloud-computing",
        "virtualization",
        "ddp",
        "m2m",
        "virtual-to-virtual",
        "v2v"
    ],
    "sg:website":"http://www.abiquo.com",
    "wof:name":"Abiquo",
    "wof:placetype":"venue"
},
  "geometry": {"coordinates":[-122.25250200000001,37.518999],"type":"Point"}
}