{
  "type": "Feature",
  "properties": {
    "iso:country":"US",
    "sg:address":"32053 McCabe Rd",
    "sg:city":"Gustine",
    "sg:classifiers":[
        {
            "category":"Government",
            "subcategory":"Office",
            "type":"Public Place"
        }
    ],
    "sg:phone":"+1 209 854 1040",
    "sg:postcode":"95322",
    "sg:province":"CA",
    "wof:name":"San Joaquin Valley National",
    "wof:placetype":"venue"
},
  "geometry": {"coordinates":[-121.06769199999999,37.121146],"type":"Point"}
}