{
  "type": "Feature",
  "properties": {
    "addr:full":"33566 Pecan Ave Yucaipa CA 92399",
    "addr:housenumber":"33566",
    "addr:postcode":"92399",
    "addr:street":"Pecan Ave",
    "iso:country":"US",
    "sg:address":"33566 Pecan Ave",
    "sg:city":"Yucaipa",
    "sg:classifiers":[
        {
            "category":"Professional",
            "subcategory":"Lawyer & Legal Services",
            "type":"Services"
        }
    ],
    "sg:phone":"+1 909 790 3704",
    "sg:postcode":"92399",
    "sg:province":"CA",
    "sg:tags":[
        "plan"
    ],
    "wof:name":"Pre-Paid Legal Svc Inc",
    "wof:placetype":"venue"
},
  "geometry": {"coordinates":[-117.071523,34.027369],"type":"Point"}
}