{
  "type": "Feature",
  "properties": {
    "iso:country":"US",
    "sg:address":"20507 E Walnut Dr N",
    "sg:city":"Walnut",
    "sg:classifiers":[
        {
            "category":"Shopping",
            "subcategory":"Pharmacy",
            "type":"Retail Goods"
        }
    ],
    "sg:phone":"+1 909 468 9215",
    "sg:postcode":"91789",
    "sg:province":"CA",
    "sg:tags":[
        "product",
        "health",
        "care"
    ],
    "sg:website":"www.longstarinc.com",
    "wof:name":"Long Star Intl",
    "wof:placetype":"venue"
},
  "geometry": {"coordinates":[-117.85646,34.001356],"type":"Point"}
}