{
  "type": "Feature",
  "properties": {
    "iso:country":"US",
    "sg:address":"10640 Woodbine St # 104",
    "sg:city":"Los Angeles",
    "sg:classifiers":[
        {
            "category":"Restaurant",
            "type":"Food & Drink"
        }
    ],
    "sg:phone":"+1 310 837 3544",
    "sg:postcode":"90034",
    "sg:province":"CA",
    "sg:tags":[
        "barbeque"
    ],
    "wof:name":"Western Smoke House",
    "wof:placetype":"venue"
},
  "geometry": {"coordinates":[-118.412049,34.026338],"type":"Point"}
}