{
  "type": "Feature",
  "properties": {
    "iso:country":"US",
    "sg:address":"335 Adeline St",
    "sg:city":"Oakland",
    "sg:classifiers":[
        {
            "category":"Bakery",
            "type":"Food & Drink"
        }
    ],
    "sg:phone":"+1 510 834 5035",
    "sg:postcode":"94607",
    "sg:province":"CA",
    "wof:name":"Svenhards Swedish Bakery",
    "wof:placetype":"venue"
},
  "geometry": {"coordinates":[-122.289001,37.801498],"type":"Point"}
}