{
  "type": "Feature",
  "properties": {
    "iso:country":"US",
    "sg:address":"2929 Harbor Blvd",
    "sg:city":"Costa Mesa",
    "sg:classifiers":[
        {
            "category":"Autos & Motor Vehicles",
            "subcategory":"Automobile Sales",
            "type":"Retail Goods"
        },
        {
            "category":"Retail",
            "subcategory":"Auto Rental",
            "type":"Services"
        },
        {
            "category":"Retail",
            "subcategory":"Auto Repair",
            "type":"Services"
        }
    ],
    "sg:phone":"+1 714 549 8023",
    "sg:postcode":"92626",
    "sg:province":"CA",
    "sg:tags":[
        "car"
    ],
    "wof:name":"Chrysler Orange Coast",
    "wof:placetype":"venue"
},
  "geometry": {"coordinates":[-117.92006600000001,33.678249],"type":"Point"}
}