{
  "type": "Feature",
  "properties": {
    "addr:full":"5956 Glen St Stockton CA 95207",
    "addr:housenumber":"5956",
    "addr:postcode":"95207",
    "addr:street":"Glen St",
    "iso:country":"US",
    "sg:address":"5956 Glen St",
    "sg:city":"Stockton",
    "sg:classifiers":[
        {
            "category":"Health Services",
            "subcategory":"Nursing And Care Facility",
            "type":"Services"
        }
    ],
    "sg:phone":"+1 209 478 8995",
    "sg:postcode":"95207",
    "sg:province":"CA",
    "sg:tags":[
        "home",
        "retirement",
        "community"
    ],
    "wof:name":"Shepherd Homes",
    "wof:placetype":"venue"
},
  "geometry": {"coordinates":[-121.324358,38.002205],"type":"Point"}
}