{
  "type": "Feature",
  "properties": {
    "addr:full":"5950 Entrada Ave Atascadero CA 93422",
    "addr:housenumber":"5950",
    "addr:postcode":"93422",
    "addr:street":"Entrada Ave",
    "iso:country":"US",
    "sg:address":"5950 Entrada Ave",
    "sg:city":"Atascadero",
    "sg:classifiers":[
        {
            "category":"Professional",
            "subcategory":"Lawyer & Legal Services",
            "type":"Services"
        }
    ],
    "sg:phone":"+1 805 466 4680",
    "sg:postcode":"93422",
    "sg:province":"CA",
    "sg:tags":[
        "attorney"
    ],
    "wof:name":"Lawrence Larson Law Office",
    "wof:placetype":"venue"
},
  "geometry": {"coordinates":[-120.669094,35.489597],"type":"Point"}
}