{
  "type": "Feature",
  "properties": {
    "iso:country":"US",
    "sg:address":"1045 N Howard Ave",
    "sg:city":"Kerman",
    "sg:classifiers":[
        {
            "category":"Manufacturing",
            "subcategory":"Buildings",
            "type":"Manufacturing & Wholesale Goods"
        },
        {
            "category":"Building & Trades",
            "subcategory":"Construction",
            "type":"Services"
        }
    ],
    "sg:phone":"+1 559 816 6292",
    "sg:postcode":"93630",
    "sg:province":"CA",
    "sg:tags":[
        "home",
        "builder",
        "contractor"
    ],
    "wof:name":"Admire General Contracting",
    "wof:placetype":"venue"
},
  "geometry": {"coordinates":[-120.024325,36.750202],"type":"Point"}
}