{
  "type": "Feature",
  "properties": {
    "iso:country":"US",
    "sg:address":"4249 Verdugo Rd",
    "sg:city":"Los Angeles",
    "sg:classifiers":[
        {
            "category":"Freight",
            "type":"Transportation"
        }
    ],
    "sg:phone":"+1 323 478 8344",
    "sg:postcode":"90065",
    "sg:province":"CA",
    "wof:name":"Ernesto S Aguillon & Frt Co",
    "wof:placetype":"venue"
},
  "geometry": {"coordinates":[-118.232478,34.12826],"type":"Point"}
}