{
  "type": "Feature",
  "properties": {
    "addr:full":"27211 Henry Mayo Dr Valencia CA 91355",
    "addr:housenumber":"27211",
    "addr:postcode":"91355",
    "addr:street":"Henry Mayo Dr",
    "iso:country":"US",
    "sg:address":"27211 Henry Mayo Dr",
    "sg:city":"Valencia",
    "sg:classifiers":[
        {
            "category":"Organizations",
            "subcategory":"Non-profit Organization",
            "type":"Services"
        }
    ],
    "sg:phone":"+1 661 294 1394",
    "sg:postcode":"91355",
    "sg:province":"CA",
    "sg:tags":[
        "camps-recreational"
    ],
    "sg:website":"http://www.pylescamp.com",
    "wof:name":"R M Pyles Boys Camp",
    "wof:placetype":"venue"
},
  "geometry": {"coordinates":[-118.60989499999999,34.438929],"type":"Point"}
}