{
  "type": "Feature",
  "properties": {
    "addr:full":"5444 Albright St Oceanside CA 92057",
    "addr:housenumber":"5444",
    "addr:postcode":"92057",
    "addr:street":"Albright St",
    "iso:country":"US",
    "sg:address":"5444 Albright St",
    "sg:city":"Oceanside",
    "sg:classifiers":[
        {
            "category":"Manufacturing",
            "subcategory":"Jewelry",
            "type":"Manufacturing & Wholesale Goods"
        }
    ],
    "sg:phone":"+1 760 940 2715",
    "sg:postcode":"92057",
    "sg:province":"CA",
    "sg:tags":[
        "precious",
        "metal",
        "mfg"
    ],
    "wof:name":"SA Splendour Inc",
    "wof:placetype":"venue"
},
  "geometry": {"coordinates":[-117.266851,33.245334],"type":"Point"}
}