{
  "type": "Feature",
  "properties": {
    "addr:full":"460 Main St Placerville CA 95667",
    "addr:housenumber":"460",
    "addr:postcode":"95667",
    "addr:street":"Main St",
    "iso:country":"US",
    "sg:address":"460 Main St",
    "sg:city":"Placerville",
    "sg:classifiers":[
        {
            "category":"Shopping",
            "subcategory":"Clothing, Apparel, & Fashions",
            "type":"Retail Goods"
        }
    ],
    "sg:phone":"+1 530 622 4681",
    "sg:postcode":"95667",
    "sg:province":"CA",
    "sg:tags":[
        "vintage",
        "clothing-collectible",
        "period"
    ],
    "wof:name":"La Cottage",
    "wof:placetype":"venue"
},
  "geometry": {"coordinates":[-120.80072699999999,38.729205],"type":"Point"}
}