{
  "type": "Feature",
  "properties": {
    "addr:full":"3555 Rosecrans Ave San Diego CA 92110",
    "addr:housenumber":"3555",
    "addr:postcode":"92110",
    "addr:street":"Rosecrans Ave",
    "iso:country":"US",
    "sg:address":"3555 Rosecrans Ave",
    "sg:city":"San Diego",
    "sg:classifiers":[
        {
            "category":"Coffee & Tea",
            "type":"Food & Drink"
        },
        {
            "category":"Restaurant",
            "type":"Food & Drink"
        }
    ],
    "sg:phone":"+1 619 226 7866",
    "sg:postcode":"92110",
    "sg:province":"CA",
    "sg:tags":[
        "vegetarian"
    ],
    "sg:website":"thenakedcafe.com",
    "wof:name":"The Naked Cafe",
    "wof:placetype":"venue"
},
  "geometry": {"coordinates":[-117.205077,32.749823],"type":"Point"}
}