{
  "type": "Feature",
  "properties": {
    "iso:country":"US",
    "sg:address":"2400 W 54th St",
    "sg:city":"Los Angeles",
    "sg:classifiers":[
        {
            "category":"Education",
            "subcategory":"School",
            "type":"Public Place"
        }
    ],
    "sg:phone":"+1 323 292 4783",
    "sg:postcode":"90043",
    "sg:province":"CA",
    "wof:name":"Los Angeles Unified School Dst",
    "wof:placetype":"venue"
},
  "geometry": {"coordinates":[-118.320345,33.993195],"type":"Point"}
}