{
  "type": "Feature",
  "properties": {
    "addr:full":"1107 S Broadway Santa Maria CA 93454",
    "addr:housenumber":"1107",
    "addr:postcode":"93454",
    "addr:street":"S Broadway",
    "iso:country":"US",
    "sg:address":"1107 S Broadway",
    "sg:city":"Santa Maria",
    "sg:classifiers":[
        {
            "category":"Social Services",
            "type":"Services"
        }
    ],
    "sg:phone":"+1 805 922 2989",
    "sg:postcode":"93454",
    "sg:province":"CA",
    "sg:tags":[
        "counselor",
        "marriage",
        "family"
    ],
    "wof:name":"Frank J Schlosser Inc",
    "wof:placetype":"venue"
},
  "geometry": {"coordinates":[-120.43611900000001,34.940335],"type":"Point"}
}