{
  "type": "Feature",
  "properties": {
    "addr:full":"5244 University Pkwy Ste H San Bernardino CA 92407",
    "addr:housenumber":"5244",
    "addr:postcode":"92407",
    "addr:street":"University Pkwy Ste H",
    "iso:country":"US",
    "sg:address":"5244 University Pkwy Ste H",
    "sg:city":"San Bernardino",
    "sg:classifiers":[
        {
            "category":"Restaurant",
            "type":"Food & Drink"
        }
    ],
    "sg:phone":"+1 909 473 3775",
    "sg:postcode":"92407",
    "sg:province":"CA",
    "sg:tags":[
        "pizza",
        "italian"
    ],
    "sg:website":"www.redbrickpizza.com/home.php",
    "wof:name":"Red Brick Pizza",
    "wof:placetype":"venue"
},
  "geometry": {"coordinates":[-117.33033500000001,34.177175],"type":"Point"}
}