{
  "type": "Feature",
  "properties": {
    "addr:full":"7804 Lankershim Blvd North Hollywood CA 91605",
    "addr:housenumber":"7804",
    "addr:postcode":"91605",
    "addr:street":"Lankershim Blvd",
    "iso:country":"US",
    "sg:address":"7804 Lankershim Blvd",
    "sg:city":"North Hollywood",
    "sg:classifiers":[
        {
            "category":"Retail",
            "subcategory":"Auto Repair",
            "type":"Services"
        }
    ],
    "sg:phone":"+1 818 764 2650",
    "sg:postcode":"91605",
    "sg:province":"CA",
    "sg:tags":[
        "body",
        "shop"
    ],
    "wof:name":"Empire Collision Repairs",
    "wof:placetype":"venue"
},
  "geometry": {"coordinates":[-118.38800000000001,34.212399],"type":"Point"}
}