{
  "type": "Feature",
  "properties": {
    "addr:full":"5 Dawn Pl Mill Valley CA 94941",
    "addr:housenumber":"5",
    "addr:postcode":"94941",
    "addr:street":"Dawn Pl",
    "iso:country":"US",
    "sg:address":"5 Dawn Pl",
    "sg:city":"Mill Valley",
    "sg:classifiers":[
        {
            "category":"Banks & Credit Unions",
            "subcategory":"Investment Brokerage",
            "type":"Services"
        }
    ],
    "sg:phone":"+1 415 388 5342",
    "sg:postcode":"94941",
    "sg:province":"CA",
    "sg:tags":[
        "advisory",
        "financial"
    ],
    "sg:website":"www.trendtrac.com",
    "wof:name":"Trend Trac",
    "wof:placetype":"venue"
},
  "geometry": {"coordinates":[-122.53450599999999,37.91596],"type":"Point"}
}