{
  "type": "Feature",
  "properties": {
    "iso:country":"US",
    "sg:address":"105 N Clovis Ave",
    "sg:city":"Fresno",
    "sg:classifiers":[
        {
            "category":"Autos & Motor Vehicles",
            "subcategory":"Fuel & Gas Station",
            "type":"Retail Goods"
        }
    ],
    "sg:phone":"+1 559 456 4778",
    "sg:postcode":"93727",
    "sg:province":"CA",
    "sg:tags":[
        "oil"
    ],
    "wof:name":"Lucky Exxon",
    "wof:placetype":"venue"
},
  "geometry": {"coordinates":[-119.69997600000001,36.744013],"type":"Point"}
}