{
  "type": "Feature",
  "properties": {
    "iso:country":"US",
    "sg:address":"600 Allerton St",
    "sg:city":"Redwood City",
    "sg:classifiers":[
        {
            "category":"Professional",
            "subcategory":"Lawyer & Legal Services",
            "type":"Services"
        }
    ],
    "sg:phone":"+1 650 365 2125",
    "sg:postcode":"94063",
    "sg:province":"CA",
    "sg:tags":[
        "attorney"
    ],
    "wof:name":"Jeffrey D Manos Attorney",
    "wof:placetype":"venue"
},
  "geometry": {"coordinates":[-122.23273500000001,37.489613],"type":"Point"}
}