{
  "type": "Feature",
  "properties": {
    "addr:full":"2030 E 4th St Santa Ana CA 92705",
    "addr:housenumber":"2030",
    "addr:postcode":"92705",
    "addr:street":"E 4Th St",
    "iso:country":"US",
    "sg:address":"2030 E 4th St",
    "sg:city":"Santa Ana",
    "sg:classifiers":[
        {
            "category":"Professional",
            "subcategory":"Lawyer & Legal Services",
            "type":"Services"
        }
    ],
    "sg:phone":"+1 714 558 2860",
    "sg:postcode":"92705",
    "sg:province":"CA",
    "wof:name":"Langton Keith D Atty",
    "wof:placetype":"venue"
},
  "geometry": {"coordinates":[-117.837997,33.7481],"type":"Point"}
}