{
  "type": "Feature",
  "properties": {
    "addr:full":"6489 E Pacific Coast Hwy Long Beach CA 90803",
    "addr:housenumber":"6489",
    "addr:postcode":"90803",
    "addr:street":"E Pacific Coast Hwy",
    "iso:country":"US",
    "sg:address":"6489 E Pacific Coast Hwy",
    "sg:city":"Long Beach",
    "sg:classifiers":[
        {
            "category":"Shopping",
            "subcategory":"Hobbies, Toys, & Games",
            "type":"Retail Goods"
        }
    ],
    "sg:phone":"+1 562 594 5979",
    "sg:postcode":"90803",
    "sg:province":"CA",
    "wof:name":"Child's Play",
    "wof:placetype":"venue"
},
  "geometry": {"coordinates":[-118.11319,33.760583],"type":"Point"}
}