{
  "type": "Feature",
  "properties": {
    "iso:country":"US",
    "sg:address":"490 E Duarte Rd",
    "sg:city":"Monrovia",
    "sg:classifiers":[
        {
            "category":"Manufacturing",
            "subcategory":"Glass & Minerals",
            "type":"Manufacturing & Wholesale Goods"
        }
    ],
    "sg:phone":"+1 626 358 2465",
    "sg:postcode":"91016",
    "sg:province":"CA",
    "sg:tags":[
        "tile"
    ],
    "wof:name":"Western Quarry Tile By WQT",
    "wof:placetype":"venue"
},
  "geometry": {"coordinates":[-117.99190299999999,34.132161],"type":"Point"}
}