{
  "type": "Feature",
  "properties": {
    "iso:country":"US",
    "sg:address":"2815 W Sunset Blvd",
    "sg:city":"Los Angeles",
    "sg:classifiers":[
        {
            "category":"Banks & Credit Unions",
            "subcategory":"Bank",
            "type":"Services"
        }
    ],
    "sg:phone":"+1 213 483 6533",
    "sg:postcode":"90026",
    "sg:province":"CA",
    "sg:tags":[
        "money",
        "order"
    ],
    "wof:name":"Lucky Money",
    "wof:placetype":"venue"
},
  "geometry": {"coordinates":[-118.2722,34.08213],"type":"Point"}
}