{
  "type": "Feature",
  "properties": {
    "addr:full":"575 High Street Suite 310 Palo Alto CA 94301",
    "addr:housenumber":"575",
    "addr:postcode":"94301",
    "addr:street":"High Street Suite 310",
    "iso:country":"US",
    "sg:address":"575 High Street Suite 310",
    "sg:city":"Palo Alto",
    "sg:classifiers":[
        {
            "category":"Professional",
            "subcategory":"Computer Services",
            "type":"Services"
        }
    ],
    "sg:postcode":"94301",
    "sg:province":"CA",
    "sg:tags":[
        "health2-0",
        "healthcare",
        "health",
        "data"
    ],
    "sg:website":"http://www.healthtap.com",
    "wof:name":"HealthTap",
    "wof:placetype":"venue"
},
  "geometry": {"coordinates":[-122.162958,37.44393],"type":"Point"}
}