{
  "type": "Feature",
  "properties": {
    "addr:full":"3401 W 3rd St Los Angeles CA 90020",
    "addr:housenumber":"3401",
    "addr:postcode":"90020",
    "addr:street":"W 3Rd St",
    "iso:country":"US",
    "sg:address":"3401 W 3rd St",
    "sg:city":"Los Angeles",
    "sg:classifiers":[
        {
            "category":"Social Services",
            "subcategory":"Child Care",
            "type":"Services"
        }
    ],
    "sg:phone":"+1 213 389 1035",
    "sg:postcode":"90020",
    "sg:province":"CA",
    "wof:name":"Mid-Wilshire Christian School",
    "wof:placetype":"venue"
},
  "geometry": {"coordinates":[-118.291662,34.069052],"type":"Point"}
}