{
  "type": "Feature",
  "properties": {
    "iso:country":"US",
    "sg:address":"330 41st Street",
    "sg:city":"Oakland",
    "sg:classifiers":[
        {
            "category":"Health Services",
            "subcategory":"Health Practitioner",
            "type":"Services"
        }
    ],
    "sg:phone":"+1 510 654 7040",
    "sg:postcode":"94609",
    "sg:province":"CA",
    "sg:tags":[
        "acupuncture"
    ],
    "sg:website":"www.brianbarlay.com",
    "wof:name":"Brian Barlay, L Ac",
    "wof:placetype":"venue"
},
  "geometry": {"coordinates":[-122.256962,37.828847],"type":"Point"}
}