{
  "type": "Feature",
  "properties": {
    "addr:full":"8082 E Santa Ana Canyon Rd Anaheim Hills CA 92808",
    "addr:housenumber":"8082",
    "addr:postcode":"92808",
    "addr:street":"E Santa Ana Canyon Rd",
    "iso:country":"US",
    "sg:address":"8082 E Santa Ana Canyon Rd",
    "sg:city":"Anaheim Hills",
    "sg:classifiers":[
        {
            "category":"Health Services",
            "subcategory":"Clinic",
            "type":"Services"
        },
        {
            "category":"Personal",
            "subcategory":"Hair Removal",
            "type":"Services"
        },
        {
            "category":"Personal",
            "subcategory":"Skin Care",
            "type":"Services"
        }
    ],
    "sg:phone":"+1 714 283 1433",
    "sg:postcode":"92808",
    "sg:province":"CA",
    "sg:tags":[
        "spa",
        "medical",
        "laser"
    ],
    "sg:website":"www.skinnirvana.com",
    "wof:name":"Skin Nirvana Cosmetic and Laser Medical",
    "wof:placetype":"venue"
},
  "geometry": {"coordinates":[-117.766104,33.861124],"type":"Point"}
}