{
  "type": "Feature",
  "properties": {
    "iso:country":"US",
    "sg:address":"9025 Atlanta Avenue",
    "sg:city":"Huntington Beach",
    "sg:classifiers":[
        {
            "category":"Personal",
            "subcategory":"Barber",
            "type":"Services"
        }
    ],
    "sg:phone":"+1 714 378 8688",
    "sg:postcode":"92646",
    "sg:province":"CA",
    "wof:name":"Great Clips For Hair",
    "wof:placetype":"venue"
},
  "geometry": {"coordinates":[-117.970674,33.657825],"type":"Point"}
}