{
  "type": "Feature",
  "properties": {
    "iso:country":"US",
    "sg:address":"2639 Cll Reynoso",
    "sg:city":"Pleasanton",
    "sg:classifiers":[
        {
            "category":"Shopping",
            "subcategory":"Clothing, Apparel, & Fashions",
            "type":"Retail Goods"
        }
    ],
    "sg:phone":"+1 925 462 2820",
    "sg:postcode":"94566",
    "sg:province":"CA",
    "wof:name":"Chicas Designs",
    "wof:placetype":"venue"
},
  "geometry": {"coordinates":[-121.901843,37.665077],"type":"Point"}
}