{
  "type": "Feature",
  "properties": {
    "addr:full":"1300 W San Carlos St San Jose CA 95126",
    "addr:housenumber":"1300",
    "addr:postcode":"95126",
    "addr:street":"W San Carlos St",
    "iso:country":"US",
    "sg:address":"1300 W San Carlos St",
    "sg:city":"San Jose",
    "sg:classifiers":[
        {
            "category":"Food & Beverages",
            "subcategory":"Groceries & Convenience Stores",
            "type":"Retail Goods"
        }
    ],
    "sg:phone":"+1 408 882 0999",
    "sg:postcode":"95126",
    "sg:province":"CA",
    "sg:website":"www.safeway.com",
    "wof:name":"Safeway",
    "wof:placetype":"venue"
},
  "geometry": {"coordinates":[-121.91253,37.322892],"type":"Point"}
}