{
  "type": "Feature",
  "properties": {
    "iso:country":"US",
    "sg:address":"2319 Merced Ave",
    "sg:city":"South El Monte",
    "sg:classifiers":[
        {
            "category":"Wholesale",
            "subcategory":"Apparel",
            "type":"Manufacturing & Wholesale Goods"
        }
    ],
    "sg:phone":"+1 626 448 7677",
    "sg:postcode":"91733",
    "sg:province":"CA",
    "sg:tags":[
        "clothing"
    ],
    "wof:name":"Harvest Moon",
    "wof:placetype":"venue"
},
  "geometry": {"coordinates":[-118.051354,34.052567],"type":"Point"}
}