{
  "type": "Feature",
  "properties": {
    "iso:country":"US",
    "sg:address":"2696 Loomis Dr",
    "sg:city":"San Jose",
    "sg:classifiers":[
        {
            "category":"Professional",
            "subcategory":"Art Services",
            "type":"Services"
        }
    ],
    "sg:phone":"+1 408 226 8485",
    "sg:postcode":"95121",
    "sg:province":"CA",
    "sg:tags":[
        "artist"
    ],
    "wof:name":"Raygoza Designs",
    "wof:placetype":"venue"
},
  "geometry": {"coordinates":[-121.830265,37.311271],"type":"Point"}
}