{
  "type": "Feature",
  "properties": {
    "iso:country":"US",
    "sg:address":"1039 Geary St",
    "sg:city":"San Francisco",
    "sg:classifiers":[
        {
            "category":"Restaurant",
            "type":"Food & Drink"
        }
    ],
    "sg:phone":"+1 415 756 4215",
    "sg:postcode":"94109",
    "sg:province":"CA",
    "wof:name":"Gulliver's Travel Shop & Cafe",
    "wof:placetype":"venue"
},
  "geometry": {"coordinates":[-122.420874,37.785692],"type":"Point"}
}