{
  "type": "Feature",
  "properties": {
    "iso:country":"US",
    "sg:address":"3715 Old Santa Rita Rd",
    "sg:city":"Pleasanton",
    "sg:classifiers":[
        {
            "category":"Building & Trades",
            "subcategory":"Plumbing",
            "type":"Services"
        }
    ],
    "sg:phone":"+1 925 463 3200",
    "sg:postcode":"94588",
    "sg:province":"CA",
    "sg:tags":[
        "contractor"
    ],
    "wof:name":"Solano Heating & Air Condition",
    "wof:placetype":"venue"
},
  "geometry": {"coordinates":[-121.87889199999999,37.700233],"type":"Point"}
}