{
  "type": "Feature",
  "properties": {
    "iso:country":"US",
    "sg:address":"55 Sadowa St",
    "sg:city":"San Francisco",
    "sg:classifiers":[
        {
            "category":"Organizations",
            "subcategory":"Non-profit Organization",
            "type":"Services"
        }
    ],
    "sg:phone":"+1 415 586 3449",
    "sg:postcode":"94112",
    "sg:province":"CA",
    "sg:tags":[
        "charitable",
        "institution"
    ],
    "wof:name":"Missionaries Of Charity",
    "wof:placetype":"venue"
},
  "geometry": {"coordinates":[-122.455443,37.712251],"type":"Point"}
}