{
  "type": "Feature",
  "properties": {
    "iso:country":"US",
    "sg:address":"1850 Williams St",
    "sg:city":"San Leandro",
    "sg:classifiers":[
        {
            "category":"Building & Trades",
            "subcategory":"Electrical",
            "type":"Services"
        }
    ],
    "sg:phone":"+1 510 351 4612",
    "sg:postcode":"94577",
    "sg:province":"CA",
    "sg:tags":[
        "electrician"
    ],
    "wof:name":"Anderson W F Electric Co Inc",
    "wof:placetype":"venue"
},
  "geometry": {"coordinates":[-122.172997,37.712399],"type":"Point"}
}