{
  "type": "Feature",
  "properties": {
    "addr:full":"5500 Campanile Dr San Diego CA 92182",
    "addr:housenumber":"5500",
    "addr:postcode":"92182",
    "addr:street":"Campanile Dr",
    "iso:country":"US",
    "sg:address":"5500 Campanile Dr",
    "sg:city":"San Diego",
    "sg:classifiers":[
        {
            "category":"Education",
            "subcategory":"Library",
            "type":"Public Place"
        }
    ],
    "sg:postcode":"92182",
    "sg:province":"CA",
    "sg:website":"infodome.sdsu.edu",
    "wof:name":"SDSU Love Library",
    "wof:placetype":"venue"
},
  "geometry": {"coordinates":[-117.072028,32.77256],"type":"Point"}
}