{
  "type": "Feature",
  "properties": {
    "addr:full":"1028 S Garfield Ave Alhambra CA 91801",
    "addr:housenumber":"1028",
    "addr:postcode":"91801",
    "addr:street":"S Garfield Ave",
    "iso:country":"US",
    "sg:address":"1028 S Garfield Ave",
    "sg:city":"Alhambra",
    "sg:classifiers":[
        {
            "category":"Health Services",
            "subcategory":"Doctor",
            "type":"Services"
        }
    ],
    "sg:phone":"+1 626 289 5161",
    "sg:postcode":"91801",
    "sg:province":"CA",
    "sg:tags":[
        "surgeon",
        "oral"
    ],
    "wof:name":"Gardner David S DDS",
    "wof:placetype":"venue"
},
  "geometry": {"coordinates":[-118.123001,34.0835],"type":"Point"}
}