{
  "type": "Feature",
  "properties": {
    "iso:country":"US",
    "sg:address":"1084 Carbon Canyon Rd",
    "sg:city":"Chino Hills",
    "sg:classifiers":[
        {
            "category":"Food & Beverages",
            "subcategory":"Liquor & Beverages",
            "type":"Retail Goods"
        }
    ],
    "sg:phone":"+1 714 996 9120",
    "sg:postcode":"91709",
    "sg:province":"CA",
    "wof:name":"Party House Liquor 2",
    "wof:placetype":"venue"
},
  "geometry": {"coordinates":[-117.776557,33.94974],"type":"Point"}
}