{
  "type": "Feature",
  "properties": {
    "addr:full":"17291 Irvine Blvd Tustin CA 92780",
    "addr:housenumber":"17291",
    "addr:postcode":"92780",
    "addr:street":"Irvine Blvd",
    "iso:country":"US",
    "sg:address":"17291 Irvine Blvd",
    "sg:city":"Tustin",
    "sg:classifiers":[
        {
            "category":"Banks & Credit Unions",
            "subcategory":"Bank",
            "type":"Services"
        }
    ],
    "sg:phone":"+1 714 505 1532",
    "sg:postcode":"92780",
    "sg:province":"CA",
    "sg:tags":[
        "escrow"
    ],
    "wof:name":"BCM Escrow Inc",
    "wof:placetype":"venue"
},
  "geometry": {"coordinates":[-117.831098,33.748207],"type":"Point"}
}