{
  "type": "Feature",
  "properties": {
    "addr:full":"2245 Park Towne Cir Sacramento CA 95825",
    "addr:housenumber":"2245",
    "addr:postcode":"95825",
    "addr:street":"Park Towne Cir",
    "iso:country":"US",
    "sg:address":"2245 Park Towne Cir",
    "sg:city":"Sacramento",
    "sg:classifiers":[
        {
            "category":"Professional",
            "subcategory":"Computer Services",
            "type":"Services"
        }
    ],
    "sg:phone":"+1 916 485 0321",
    "sg:postcode":"95825",
    "sg:province":"CA",
    "sg:tags":[
        "internet"
    ],
    "wof:name":"PDQNET Internet Svc",
    "wof:placetype":"venue"
},
  "geometry": {"coordinates":[-121.384124,38.605867],"type":"Point"}
}