{
  "type": "Feature",
  "properties": {
    "addr:full":"820 34th St Bakersfield CA 93301",
    "addr:housenumber":"820",
    "addr:postcode":"93301",
    "addr:street":"34Th St",
    "iso:country":"US",
    "sg:address":"820 34th St",
    "sg:city":"Bakersfield",
    "sg:classifiers":[
        {
            "category":"Health Services",
            "subcategory":"Doctor",
            "type":"Services"
        }
    ],
    "sg:phone":"+1 661 326 8989",
    "sg:postcode":"93301",
    "sg:province":"CA",
    "sg:tags":[
        "medicine",
        "physician",
        "practice",
        "surgeons",
        "family"
    ],
    "wof:name":"Johnson Jung Md",
    "wof:placetype":"venue"
},
  "geometry": {"coordinates":[-119.01078800000001,35.390501],"type":"Point"}
}