{
  "type": "Feature",
  "properties": {
    "addr:full":"11905 Borg Ct Bakersfield CA 93306",
    "addr:housenumber":"11905",
    "addr:postcode":"93306",
    "addr:street":"Borg Ct",
    "iso:country":"US",
    "sg:address":"11905 Borg Ct",
    "sg:city":"Bakersfield",
    "sg:classifiers":[
        {
            "category":"Home & Garden",
            "subcategory":"Building Materials",
            "type":"Retail Goods"
        }
    ],
    "sg:phone":"+1 661 872 5725",
    "sg:postcode":"93306",
    "sg:province":"CA",
    "sg:tags":[
        "energy",
        "conservation",
        "prod"
    ],
    "wof:name":"Peggy's Concern",
    "wof:placetype":"venue"
},
  "geometry": {"coordinates":[-118.87213199999999,35.430922],"type":"Point"}
}