{
  "type": "Feature",
  "properties": {
    "addr:full":"139 E Victoria St Carson CA 90746",
    "addr:housenumber":"139",
    "addr:postcode":"90746",
    "addr:street":"E Victoria St",
    "iso:country":"US",
    "sg:address":"139 E Victoria St",
    "sg:city":"Carson",
    "sg:classifiers":[
        {
            "category":"Wholesale",
            "subcategory":"Machinery & Supplies",
            "type":"Manufacturing & Wholesale Goods"
        }
    ],
    "sg:phone":"+1 310 515 1800",
    "sg:postcode":"90746",
    "sg:province":"CA",
    "sg:tags":[
        "tool"
    ],
    "wof:name":"Fejes Tools Inc",
    "wof:placetype":"venue"
},
  "geometry": {"coordinates":[-118.274242,33.866063],"type":"Point"}
}