{
  "type": "Feature",
  "properties": {
    "addr:full":"10680 Katella Ave Anaheim CA 92804",
    "addr:housenumber":"10680",
    "addr:postcode":"92804",
    "addr:street":"Katella Ave",
    "iso:country":"US",
    "sg:address":"10680 Katella Ave",
    "sg:city":"Anaheim",
    "sg:classifiers":[
        {
            "category":"Personal",
            "subcategory":"Tattoo Parlor",
            "type":"Services"
        }
    ],
    "sg:phone":"+1 714 780 0386",
    "sg:postcode":"92804",
    "sg:province":"CA",
    "wof:name":"Aztec Inkferno Tattoo's",
    "wof:placetype":"venue"
},
  "geometry": {"coordinates":[-117.946843,33.802942],"type":"Point"}
}