{
  "type": "Feature",
  "properties": {
    "addr:full":"760 98th Ave Oakland CA 94603",
    "addr:housenumber":"760",
    "addr:postcode":"94603",
    "addr:street":"98Th Ave",
    "iso:country":"US",
    "sg:address":"760 98th Ave",
    "sg:city":"Oakland",
    "sg:classifiers":[
        {
            "category":"Building & Trades",
            "subcategory":"Construction",
            "type":"Services"
        }
    ],
    "sg:phone":"+1 510 633 3055",
    "sg:postcode":"94603",
    "sg:province":"CA",
    "sg:tags":[
        "demolition",
        "contractor"
    ],
    "wof:name":"E & F Demolition Inc.",
    "wof:placetype":"venue"
},
  "geometry": {"coordinates":[-122.181443,37.737754],"type":"Point"}
}