{
  "type": "Feature",
  "properties": {
    "iso:country":"US",
    "sg:address":"2390 Crenshaw Blvd",
    "sg:city":"Torrance",
    "sg:classifiers":[
        {
            "category":"Shopping",
            "subcategory":"Computers & Home Electronics",
            "type":"Retail Goods"
        }
    ],
    "sg:phone":"+1 310 320 4263",
    "sg:postcode":"90501",
    "sg:province":"CA",
    "sg:tags":[
        "game",
        "video"
    ],
    "wof:name":"Game House",
    "wof:placetype":"venue"
},
  "geometry": {"coordinates":[-118.328319,33.823258],"type":"Point"}
}