{
  "type": "Feature",
  "properties": {
    "iso:country":"US",
    "sg:address":"1736 Holmes St",
    "sg:city":"Livermore",
    "sg:classifiers":[
        {
            "category":"Insurance",
            "subcategory":"Insurance Agent",
            "type":"Services"
        }
    ],
    "sg:phone":"+1 925 447 1744",
    "sg:postcode":"94550",
    "sg:province":"CA",
    "wof:name":"Mc Gann Agency",
    "wof:placetype":"venue"
},
  "geometry": {"coordinates":[-121.780259,37.663633],"type":"Point"}
}