{
  "type": "Feature",
  "properties": {
    "iso:country":"US",
    "sg:address":"4460 Cavitt Stallman Rd",
    "sg:city":"Granite Bay",
    "sg:classifiers":[
        {
            "category":"Retail",
            "subcategory":"Portrait Studio",
            "type":"Services"
        }
    ],
    "sg:phone":"+1 916 791 5336",
    "sg:postcode":"95746",
    "sg:province":"CA",
    "sg:tags":[
        "photographer"
    ],
    "wof:name":"Winter Photography",
    "wof:placetype":"venue"
},
  "geometry": {"coordinates":[-121.219394,38.759017],"type":"Point"}
}