{
  "type": "Feature",
  "properties": {
    "addr:full":"406 W 8th St Alturas CA 96101",
    "addr:housenumber":"406",
    "addr:postcode":"96101",
    "addr:street":"W 8Th St",
    "iso:country":"US",
    "sg:address":"406 W 8th St",
    "sg:city":"Alturas",
    "sg:classifiers":[
        {
            "category":"Wholesale",
            "subcategory":"Petroleum",
            "type":"Manufacturing & Wholesale Goods"
        }
    ],
    "sg:phone":"+1 530 233 2610",
    "sg:postcode":"96101",
    "sg:province":"CA",
    "sg:tags":[
        "bulk",
        "terminal"
    ],
    "sg:website":"www.edstaub.com",
    "wof:name":"Ed Staub & Sons Petroleum Inc",
    "wof:placetype":"venue"
},
  "geometry": {"coordinates":[-120.546909,41.491015],"type":"Point"}
}