{
  "type": "Feature",
  "properties": {
    "iso:country":"US",
    "sg:address":"41842 Ione Rd",
    "sg:city":"Orosi",
    "sg:classifiers":[
        {
            "category":"Utilities",
            "subcategory":"Water",
            "type":"Services"
        }
    ],
    "sg:phone":"+1 559 528 2726",
    "sg:postcode":"93647",
    "sg:province":"CA",
    "sg:tags":[
        "company",
        "sewage"
    ],
    "wof:name":"East Orosi Community Svc Dist",
    "wof:placetype":"venue"
},
  "geometry": {"coordinates":[-119.26044899999999,36.548184],"type":"Point"}
}