{
  "type": "Feature",
  "properties": {
    "addr:full":"1659 N Capitol Ave San Jose CA 95132",
    "addr:housenumber":"1659",
    "addr:postcode":"95132",
    "addr:street":"N Capitol Ave",
    "iso:country":"US",
    "sg:address":"1659 N Capitol Ave",
    "sg:city":"San Jose",
    "sg:classifiers":[
        {
            "category":"Manufacturing",
            "subcategory":"Tools & Machinery",
            "type":"Manufacturing & Wholesale Goods"
        }
    ],
    "sg:phone":"+1 408 254 8821",
    "sg:postcode":"95132",
    "sg:province":"CA",
    "sg:tags":[
        "computer"
    ],
    "sg:website":"www.hollyintl.com",
    "wof:name":"Holly Electronic",
    "wof:placetype":"venue"
},
  "geometry": {"coordinates":[-121.871725,37.396703],"type":"Point"}
}