{
  "type": "Feature",
  "properties": {
    "addr:full":"7217 Owensmouth Ave Canoga Park CA 91303",
    "addr:housenumber":"7217",
    "addr:postcode":"91303",
    "addr:street":"Owensmouth Ave",
    "iso:country":"US",
    "sg:address":"7217 Owensmouth Ave",
    "sg:city":"Canoga Park",
    "sg:classifiers":[
        {
            "category":"Insurance",
            "subcategory":"Insurance Agent",
            "type":"Services"
        }
    ],
    "sg:phone":"+1 818 888 1771",
    "sg:postcode":"91303",
    "sg:province":"CA",
    "wof:name":"Green Line Insurance Svc",
    "wof:placetype":"venue"
},
  "geometry": {"coordinates":[-118.601645,34.202546],"type":"Point"}
}