{
  "type": "Feature",
  "properties": {
    "iso:country":"US",
    "sg:address":"11570 Lower Azusa Rd",
    "sg:city":"El Monte",
    "sg:classifiers":[
        {
            "category":"Personal",
            "subcategory":"Barber",
            "type":"Services"
        }
    ],
    "sg:phone":"+1 626 448 0464",
    "sg:postcode":"91732",
    "sg:province":"CA",
    "wof:name":"Bob's Barber Shop",
    "wof:placetype":"venue"
},
  "geometry": {"coordinates":[-118.014707,34.090887],"type":"Point"}
}