{
  "type": "Feature",
  "properties": {
    "iso:country":"US",
    "sg:address":"1355 W Rowland Ave",
    "sg:city":"West Covina",
    "sg:classifiers":[
        {
            "category":"Education",
            "subcategory":"School",
            "type":"Public Place"
        }
    ],
    "sg:phone":"+1 626 974 4701",
    "sg:postcode":"91790",
    "sg:province":"CA",
    "wof:name":"Rowland Avenue Elementary Schl",
    "wof:placetype":"venue"
},
  "geometry": {"coordinates":[-117.93401,34.079116],"type":"Point"}
}