{
  "type": "Feature",
  "properties": {
    "addr:full":"20800 Belshaw Ave Carson CA 90746",
    "addr:postcode":"20800;90746",
    "addr:street":"Belshaw Ave",
    "iso:country":"US",
    "sg:address":"20800 Belshaw Ave",
    "sg:city":"Carson",
    "sg:phone":"+1 310 547 3787",
    "sg:postcode":"90746",
    "sg:province":"CA",
    "wof:name":"Bob Williams Moving",
    "wof:placetype":"venue"
},
  "geometry": {"coordinates":[-118.25541699999999,33.841446],"type":"Point"}
}