{
  "type": "Feature",
  "properties": {
    "addr:full":"7340 Hollister Ave Goleta CA 93117",
    "addr:housenumber":"7340",
    "addr:postcode":"93117",
    "addr:street":"Hollister Ave",
    "iso:country":"US",
    "sg:address":"7340 Hollister Ave",
    "sg:city":"Goleta",
    "sg:classifiers":[
        {
            "category":"Manufacturing",
            "subcategory":"Printing",
            "type":"Manufacturing & Wholesale Goods"
        }
    ],
    "sg:phone":"+1 805 968 1020",
    "sg:postcode":"93117",
    "sg:province":"CA",
    "sg:tags":[
        "book"
    ],
    "wof:name":"World Wide Witness For Chri St",
    "wof:placetype":"venue"
},
  "geometry": {"coordinates":[-119.882678,34.430084],"type":"Point"}
}