{
  "type": "Feature",
  "properties": {
    "addr:full":"10945 Wagner St Culver City CA 90230",
    "addr:housenumber":"10945",
    "addr:postcode":"90230",
    "addr:street":"Wagner St",
    "iso:country":"US",
    "sg:address":"10945 Wagner St",
    "sg:city":"Culver City",
    "sg:classifiers":[
        {
            "category":"Shopping",
            "type":"Retail Goods"
        }
    ],
    "sg:phone":"+1 310 876 7028",
    "sg:postcode":"90230",
    "sg:province":"CA",
    "sg:tags":[
        "merchandise"
    ],
    "wof:name":"See Spot Shop",
    "wof:placetype":"venue"
},
  "geometry": {"coordinates":[-118.40568,34.008615],"type":"Point"}
}