{
  "type": "Feature",
  "properties": {
    "iso:country":"US",
    "sg:address":"8536 Kern Canyon Rd Ofc",
    "sg:city":"Bakersfield",
    "sg:classifiers":[
        {
            "category":"Banks & Credit Unions",
            "subcategory":"Investment Brokerage",
            "type":"Services"
        }
    ],
    "sg:phone":"+1 661 366 3021",
    "sg:postcode":"93306",
    "sg:province":"CA",
    "sg:tags":[
        "trust"
    ],
    "wof:name":"Beesley Living Trust",
    "wof:placetype":"venue"
},
  "geometry": {"coordinates":[-118.909302,35.376961],"type":"Point"}
}