{
  "type": "Feature",
  "properties": {
    "addr:full":"10263 Vincent Rd Delhi CA 95315",
    "addr:housenumber":"10263",
    "addr:postcode":"95315",
    "addr:street":"Vincent Rd",
    "iso:country":"US",
    "sg:address":"10263 Vincent Rd",
    "sg:city":"Delhi",
    "sg:classifiers":[
        {
            "category":"Freight",
            "type":"Transportation"
        }
    ],
    "sg:phone":"+1 209 668 1214",
    "sg:postcode":"95315",
    "sg:province":"CA",
    "sg:tags":[
        "operator",
        "local",
        "trucking"
    ],
    "wof:name":"Delaney Trucking",
    "wof:placetype":"venue"
},
  "geometry": {"coordinates":[-120.77669400000001,37.436522],"type":"Point"}
}