{
  "type": "Feature",
  "properties": {
    "iso:country":"US",
    "sg:address":"4300 Anthony Ct",
    "sg:city":"Rocklin",
    "sg:classifiers":[
        {
            "category":"Shopping",
            "subcategory":"Florist",
            "type":"Retail Goods"
        }
    ],
    "sg:phone":"+1 916 652 8448",
    "sg:postcode":"95677",
    "sg:province":"CA",
    "wof:name":"Flower Works",
    "wof:placetype":"venue"
},
  "geometry": {"coordinates":[-121.21490300000001,38.804316],"type":"Point"}
}