{
  "type": "Feature",
  "properties": {
    "iso:country":"US",
    "sg:address":"455 Hudson St",
    "sg:city":"Healdsburg",
    "sg:classifiers":[
        {
            "category":"Health Services",
            "subcategory":"Doctor",
            "type":"Services"
        }
    ],
    "sg:phone":"+1 707 473 0782",
    "sg:postcode":"95448",
    "sg:province":"CA",
    "sg:tags":[
        "physician",
        "surgeon"
    ],
    "wof:name":"Psychstrategies Inc",
    "wof:placetype":"venue"
},
  "geometry": {"coordinates":[-122.863111,38.606465],"type":"Point"}
}