{
  "type": "Feature",
  "properties": {
    "iso:country":"US",
    "sg:address":"9041 Central Ave",
    "sg:city":"Orangevale",
    "sg:classifiers":[
        {
            "category":"Place Of Worship",
            "subcategory":"Church",
            "type":"Public Place"
        }
    ],
    "sg:phone":"+1 916 987 9191",
    "sg:postcode":"95662",
    "sg:province":"CA",
    "sg:tags":[
        "churches-united",
        "methodist"
    ],
    "wof:name":"Cho-Un Korean United Methodist Church Of Sac",
    "wof:placetype":"venue"
},
  "geometry": {"coordinates":[-121.218705,38.685656],"type":"Point"}
}