{
  "type": "Feature",
  "properties": {
    "iso:country":"US",
    "sg:address":"249 S Ave 55",
    "sg:city":"Los Angeles",
    "sg:classifiers":[
        {
            "category":"Building & Trades",
            "subcategory":"Construction",
            "type":"Services"
        }
    ],
    "sg:phone":"+1 323 256 0292",
    "sg:postcode":"90042",
    "sg:province":"CA",
    "sg:tags":[
        "home",
        "remodeling"
    ],
    "wof:name":"H S General Contractor",
    "wof:placetype":"venue"
},
  "geometry": {"coordinates":[-118.194388,34.103855],"type":"Point"}
}