{
  "type": "Feature",
  "properties": {
    "iso:country":"US",
    "sg:address":"3540 Wilshire Blvd",
    "sg:city":"Los Angeles",
    "sg:classifiers":[
        {
            "category":"Professional",
            "subcategory":"Accounting & Tax Preparation",
            "type":"Services"
        }
    ],
    "sg:phone":"+1 213 389 2652",
    "sg:postcode":"90010",
    "sg:province":"CA",
    "sg:tags":[
        "return",
        "filing"
    ],
    "wof:name":"J & E Income Tax Svc",
    "wof:placetype":"venue"
},
  "geometry": {"coordinates":[-118.301928,34.061659],"type":"Point"}
}