{
  "type": "Feature",
  "properties": {
    "iso:country":"US",
    "sg:address":"23111 Ventura Blvd Ste 204",
    "sg:city":"Woodland Hills",
    "sg:classifiers":[
        {
            "category":"Health Services",
            "subcategory":"Doctor",
            "type":"Services"
        }
    ],
    "sg:phone":"+1 818 225 1630",
    "sg:postcode":"91364",
    "sg:province":"CA",
    "sg:tags":[
        "surgeon",
        "oral"
    ],
    "sg:website":"www.driragrose.com",
    "wof:name":"Baca Bruce A DDS",
    "wof:placetype":"venue"
},
  "geometry": {"coordinates":[-118.628998,34.1637],"type":"Point"}
}