{
  "type": "Feature",
  "properties": {
    "iso:country":"US",
    "sg:address":"915 Cam Caballo",
    "sg:city":"Nipomo",
    "sg:classifiers":[
        {
            "category":"Social Services",
            "subcategory":"Adult Care",
            "type":"Services"
        }
    ],
    "sg:phone":"+1 805 929 6914",
    "sg:postcode":"93444",
    "sg:province":"CA",
    "sg:tags":[
        "home",
        "residential"
    ],
    "wof:name":"Sacred Heart Residential Care",
    "wof:placetype":"venue"
},
  "geometry": {"coordinates":[-120.512688,35.034987],"type":"Point"}
}