{
  "type": "Feature",
  "properties": {
    "iso:country":"US",
    "sg:address":"605 N Garfield Ave",
    "sg:city":"Monterey Park",
    "sg:classifiers":[
        {
            "category":"Health Services",
            "subcategory":"Doctor",
            "type":"Services"
        }
    ],
    "sg:phone":"+1 626 571 6729",
    "sg:postcode":"91754",
    "sg:province":"CA",
    "sg:website":"www.beverlyoncology.com",
    "wof:name":"Sevilla John L MD",
    "wof:placetype":"venue"
},
  "geometry": {"coordinates":[-118.123001,34.069698],"type":"Point"}
}