{
  "type": "Feature",
  "properties": {
    "iso:country":"US",
    "sg:address":"1158 E Washington Ave",
    "sg:city":"Escondido",
    "sg:classifiers":[
        {
            "category":"Autos & Motor Vehicles",
            "subcategory":"Fuel & Gas Station",
            "type":"Retail Goods"
        },
        {
            "category":"Utilities",
            "subcategory":"Fuel Oil & Lpg",
            "type":"Services"
        }
    ],
    "sg:phone":"+1 760 839 2745",
    "sg:postcode":"92025",
    "sg:province":"CA",
    "sg:tags":[
        "bulk",
        "petroleum-bottled",
        "gas-liquefied"
    ],
    "wof:name":"Ronco Gas",
    "wof:placetype":"venue"
},
  "geometry": {"coordinates":[-117.068585,33.132772],"type":"Point"}
}