{
  "type": "Feature",
  "properties": {
    "addr:full":"3525 4th Ave San Diego CA 92103",
    "addr:housenumber":"3525",
    "addr:postcode":"92103",
    "addr:street":"4Th Ave",
    "iso:country":"US",
    "sg:address":"3525 4th Ave",
    "sg:city":"San Diego",
    "sg:classifiers":[
        {
            "category":"Real Estate",
            "subcategory":"Real Estate Services",
            "type":"Services"
        }
    ],
    "sg:phone":"+1 619 293 7123",
    "sg:postcode":"92103",
    "sg:province":"CA",
    "wof:name":"Western Commercial Real Estate Brokerage",
    "wof:placetype":"venue"
},
  "geometry": {"coordinates":[-117.162003,32.7416],"type":"Point"}
}