{
  "type": "Feature",
  "properties": {
    "iso:country":"US",
    "sg:address":"4425 E Airport Dr",
    "sg:city":"Ontario",
    "sg:classifiers":[
        {
            "category":"Professional",
            "type":"Services"
        },
        {
            "category":"Professional",
            "subcategory":"Business Services",
            "type":"Services"
        }
    ],
    "sg:phone":"+1 909 390 9404",
    "sg:postcode":"91761",
    "sg:province":"CA",
    "sg:tags":[
        "establishment"
    ],
    "wof:name":"Quality Driver Solutions Inc",
    "wof:placetype":"venue"
},
  "geometry": {"coordinates":[-117.55652600000001,34.062683],"type":"Point"}
}