{
  "type": "Feature",
  "properties": {
    "addr:full":"208 S Beverly Dr Beverly Hills CA 90212",
    "addr:housenumber":"208",
    "addr:postcode":"90212",
    "addr:street":"S Beverly Dr",
    "iso:country":"US",
    "sg:address":"208 S Beverly Dr",
    "sg:city":"Beverly Hills",
    "sg:classifiers":[
        {
            "category":"Arts & Performance",
            "subcategory":"Theater",
            "type":"Entertainment"
        }
    ],
    "sg:phone":"+1 310 285 1974",
    "sg:postcode":"90212",
    "sg:province":"CA",
    "sg:tags":[
        "bureau"
    ],
    "wof:name":"Fatty Girl Entertainment",
    "wof:placetype":"venue"
},
  "geometry": {"coordinates":[-118.39899800000001,34.062441],"type":"Point"}
}