{
  "type": "Feature",
  "properties": {
    "iso:country":"US",
    "sg:address":"1407 J St",
    "sg:city":"Sacramento",
    "sg:classifiers":[
        {
            "category":"Professional",
            "subcategory":"Lawyer & Legal Services",
            "type":"Services"
        }
    ],
    "sg:phone":"+1 916 325 0500",
    "sg:postcode":"95814",
    "sg:province":"CA",
    "sg:tags":[
        "notary"
    ],
    "sg:website":"www.goldcountrybail.com",
    "wof:name":"Gold Country Bail Bonds",
    "wof:placetype":"venue"
},
  "geometry": {"coordinates":[-121.48777,38.578939],"type":"Point"}
}