{
  "type": "Feature",
  "properties": {
    "addr:full":"6119 Niles St Bakersfield CA 93306",
    "addr:housenumber":"6119",
    "addr:postcode":"93306",
    "addr:street":"Niles St",
    "iso:country":"US",
    "sg:address":"6119 Niles St",
    "sg:city":"Bakersfield",
    "sg:classifiers":[
        {
            "category":"Restaurant",
            "type":"Food & Drink"
        }
    ],
    "sg:menulink":"http://www.allmenus.com/ca/bakersfield/214145-taco-bell/menu/",
    "sg:phone":"+1 661 366 3179",
    "sg:postcode":"93306",
    "sg:province":"CA",
    "sg:tags":[
        "mexican"
    ],
    "wof:name":"Taco Bell",
    "wof:placetype":"venue"
},
  "geometry": {"coordinates":[-118.935941,35.375724],"type":"Point"}
}