{
  "type": "Feature",
  "properties": {
    "addr:full":"4374 Bonita Rd Bonita CA 91902",
    "addr:housenumber":"4374",
    "addr:postcode":"91902",
    "addr:street":"Bonita Rd",
    "iso:country":"US",
    "sg:address":"4374 Bonita Rd",
    "sg:city":"Bonita",
    "sg:classifiers":[
        {
            "category":"Banks & Credit Unions",
            "subcategory":"Bank",
            "type":"Services"
        }
    ],
    "sg:phone":"+1 800 500 6328",
    "sg:postcode":"91902",
    "sg:province":"CA",
    "wof:name":"Mission Federal Credit Union",
    "wof:placetype":"venue"
},
  "geometry": {"coordinates":[-117.03338100000001,32.660625],"type":"Point"}
}