{
  "type": "Feature",
  "properties": {
    "addr:full":"22175 Cmt Tasquillo Laguna Hills CA 92653",
    "addr:postcode":"22175;92653",
    "addr:street":"Cmt",
    "iso:country":"US",
    "sg:address":"22175 Cmt Tasquillo",
    "sg:city":"Laguna Hills",
    "sg:classifiers":[
        {
            "category":"Building & Trades",
            "subcategory":"Landscaping Services",
            "type":"Services"
        }
    ],
    "sg:phone":"+1 949 859 9828",
    "sg:postcode":"92653",
    "sg:province":"CA",
    "sg:tags":[
        "designer",
        "landscape"
    ],
    "wof:name":"Laguna Hills Landscape Svcs",
    "wof:placetype":"venue"
},
  "geometry": {"coordinates":[-117.74337300000001,33.624015],"type":"Point"}
}