{
  "type": "Feature",
  "properties": {
    "addr:full":"19002 Ventura Blvd Tarzana CA 91356",
    "addr:housenumber":"19002",
    "addr:postcode":"91356",
    "addr:street":"Ventura Blvd",
    "iso:country":"US",
    "sg:address":"19002 Ventura Blvd",
    "sg:city":"Tarzana",
    "sg:classifiers":[
        {
            "category":"Shopping",
            "subcategory":"Tobacco",
            "type":"Retail Goods"
        }
    ],
    "sg:phone":"+1 818 345 8921",
    "sg:postcode":"91356",
    "sg:province":"CA",
    "sg:tags":[
        "cigarette",
        "cigar",
        "dealer"
    ],
    "wof:name":"Smart Pick",
    "wof:placetype":"venue"
},
  "geometry": {"coordinates":[-118.54831299999999,34.172443],"type":"Point"}
}