{
  "type": "Feature",
  "properties": {
    "iso:country":"US",
    "sg:address":"1202 E Hunter Ave",
    "sg:city":"Santa Ana",
    "sg:classifiers":[
        {
            "category":"Building & Trades",
            "subcategory":"Construction",
            "type":"Services"
        }
    ],
    "sg:phone":"+1 714 835 8572",
    "sg:postcode":"92705",
    "sg:province":"CA",
    "sg:tags":[
        "contractor"
    ],
    "wof:name":"Baker Company Constructors",
    "wof:placetype":"venue"
},
  "geometry": {"coordinates":[-117.852711,33.738354],"type":"Point"}
}