{
  "type": "Feature",
  "properties": {
    "iso:country":"US",
    "sg:address":"1219 E Ave R-7",
    "sg:city":"Palmdale",
    "sg:classifiers":[
        {
            "category":"Social Services",
            "subcategory":"Adult Care",
            "type":"Services"
        }
    ],
    "sg:phone":"+1 661 274 0236",
    "sg:postcode":"93550",
    "sg:province":"CA",
    "sg:tags":[
        "home",
        "group"
    ],
    "wof:name":"Murrells Community Svc Agency",
    "wof:placetype":"venue"
},
  "geometry": {"coordinates":[-118.10606199999999,34.566781],"type":"Point"}
}