{
  "type": "Feature",
  "properties": {
    "iso:country":"US",
    "sg:address":"205 Alpine Meadows Rd",
    "sg:city":"Alpine Meadows",
    "sg:classifiers":[
        {
            "category":"Real Estate",
            "subcategory":"Real Estate Agent",
            "type":"Services"
        }
    ],
    "sg:phone":"+1 530 581 3263",
    "sg:postcode":"96146",
    "sg:province":"CA",
    "sg:tags":[
        "rental",
        "vacation"
    ],
    "wof:name":"Tahoe Real Estate & Rentals",
    "wof:placetype":"venue"
},
  "geometry": {"coordinates":[-120.196851,39.187174],"type":"Point"}
}