{
  "type": "Feature",
  "properties": {
    "iso:country":"US",
    "sg:address":"1016 Pleasant View Ave",
    "sg:city":"Venice",
    "sg:classifiers":[
        {
            "category":"Social Services",
            "type":"Services"
        }
    ],
    "sg:phone":"+1 310 664 8893",
    "sg:postcode":"90291",
    "sg:province":"CA",
    "sg:tags":[
        "organization",
        "welfare"
    ],
    "wof:name":"Neighborhood Youth Assn Inc",
    "wof:placetype":"venue"
},
  "geometry": {"coordinates":[-118.462898,33.99561],"type":"Point"}
}