{
  "type": "Feature",
  "properties": {
    "addr:full":"1285 Parkside Dr Walnut Creek CA 94596",
    "addr:housenumber":"1285",
    "addr:postcode":"94596",
    "addr:street":"Parkside Dr",
    "iso:country":"US",
    "sg:address":"1285 Parkside Dr",
    "sg:city":"Walnut Creek",
    "sg:classifiers":[
        {
            "category":"Retail",
            "subcategory":"Auto Repair",
            "type":"Services"
        }
    ],
    "sg:phone":"+1 925 939 7346",
    "sg:postcode":"94596",
    "sg:province":"CA",
    "sg:tags":[
        "machine",
        "automobile",
        "shop"
    ],
    "wof:name":"Morgan's Machine & Marine",
    "wof:placetype":"venue"
},
  "geometry": {"coordinates":[-122.06322900000001,37.911624],"type":"Point"}
}