{
  "type": "Feature",
  "properties": {
    "iso:country":"US",
    "sg:address":"6633 Telephone Rd Ste 100",
    "sg:city":"Ventura",
    "sg:classifiers":[
        {
            "category":"Professional",
            "subcategory":"Employment Agencies",
            "type":"Services"
        }
    ],
    "sg:phone":"+1 805 477 2800",
    "sg:postcode":"93003",
    "sg:province":"CA",
    "sg:tags":[
        "opportunity",
        "contractor"
    ],
    "sg:website":"http://www.kellyservices.com",
    "wof:name":"Kelly Services",
    "wof:placetype":"venue"
},
  "geometry": {"coordinates":[-119.20413000000001,34.266635],"type":"Point"}
}