{
  "type": "Feature",
  "properties": {
    "iso:country":"US",
    "sg:address":"969 Garnet Ave",
    "sg:city":"San Diego",
    "sg:classifiers":[
        {
            "category":"Personal",
            "subcategory":"Beauty Salon",
            "type":"Services"
        }
    ],
    "sg:phone":"+1 858 270 9975",
    "sg:postcode":"92109",
    "sg:province":"CA",
    "sg:tags":[
        "hair"
    ],
    "sg:website":"www.robertcromeans.com",
    "wof:name":"A Robert Cromeans Salon",
    "wof:placetype":"venue"
},
  "geometry": {"coordinates":[-117.25214800000001,32.797287],"type":"Point"}
}