{
  "type": "Feature",
  "properties": {
    "addr:full":"3330 Pierce St San Francisco CA 94123",
    "addr:housenumber":"3330",
    "addr:postcode":"94123",
    "addr:street":"Pierce St",
    "iso:country":"US",
    "sg:address":"3330 Pierce St",
    "sg:city":"San Francisco",
    "sg:classifiers":[
        {
            "category":"Banks & Credit Unions",
            "subcategory":"Investment Brokerage",
            "type":"Services"
        }
    ],
    "sg:phone":"+1 415 921 8408",
    "sg:postcode":"94123",
    "sg:province":"CA",
    "sg:tags":[
        "security"
    ],
    "wof:name":"Formichi Virginia J",
    "wof:placetype":"venue"
},
  "geometry": {"coordinates":[-122.439463,37.800645],"type":"Point"}
}