{
  "type": "Feature",
  "properties": {
    "iso:country":"US",
    "sg:address":"12310 Four Winds Way",
    "sg:city":"Victorville",
    "sg:classifiers":[
        {
            "category":"Shopping",
            "subcategory":"Hobbies, Toys, & Games",
            "type":"Retail Goods"
        },
        {
            "category":"Shopping",
            "subcategory":"Crafts & Fabrics",
            "type":"Retail Goods"
        }
    ],
    "sg:phone":"+1 760 983 5079",
    "sg:postcode":"92392",
    "sg:province":"CA",
    "sg:tags":[
        "shop",
        "hobby",
        "model",
        "supply"
    ],
    "wof:name":"Tat's Embroidery & Crafts",
    "wof:placetype":"venue"
},
  "geometry": {"coordinates":[-117.395009,34.474391],"type":"Point"}
}