{
  "type": "Feature",
  "properties": {
    "iso:country":"US",
    "sg:address":"28951 Falcon Ridge Rd",
    "sg:city":"Salinas",
    "sg:classifiers":[
        {
            "category":"Professional",
            "subcategory":"Management & Consulting",
            "type":"Services"
        }
    ],
    "sg:phone":"+1 831 484 4834",
    "sg:postcode":"93908",
    "sg:province":"CA",
    "sg:tags":[
        "agricultural",
        "consultant"
    ],
    "wof:name":"Rush Marcroft & Associates",
    "wof:placetype":"venue"
},
  "geometry": {"coordinates":[-121.715327,36.549123],"type":"Point"}
}