{
  "type": "Feature",
  "properties": {
    "addr:full":"8306 W 3rd St Los Angeles CA 90048",
    "addr:housenumber":"8306",
    "addr:postcode":"90048",
    "addr:street":"W 3Rd St",
    "iso:country":"US",
    "sg:address":"8306 W 3rd St",
    "sg:city":"Los Angeles",
    "sg:classifiers":[
        {
            "category":"Personal",
            "subcategory":"Beauty Salon",
            "type":"Services"
        }
    ],
    "sg:phone":"+1 323 651 0831",
    "sg:postcode":"90048",
    "sg:province":"CA",
    "wof:name":"Miwa's Beauty Salon",
    "wof:placetype":"venue"
},
  "geometry": {"coordinates":[-118.37088300000001,34.072681],"type":"Point"}
}