{
  "type": "Feature",
  "properties": {
    "addr:full":"11742 E Imperial Hwy Norwalk CA 90651",
    "addr:housenumber":"11742",
    "addr:postcode":"90651",
    "addr:street":"E Imperial Hwy",
    "iso:country":"US",
    "sg:address":"11742 E Imperial Hwy",
    "sg:city":"Norwalk",
    "sg:classifiers":[
        {
            "category":"Retail",
            "subcategory":"Auto Repair",
            "type":"Services"
        }
    ],
    "sg:phone":"+1 562 807 2266",
    "sg:postcode":"90651",
    "sg:province":"CA",
    "sg:website":"www.toplineautorepair.com",
    "wof:name":"Top Line Automotive",
    "wof:placetype":"venue"
},
  "geometry": {"coordinates":[-118.083072,33.91702],"type":"Point"}
}