{
  "type": "Feature",
  "properties": {
    "iso:country":"US",
    "sg:address":"915 L St Bsmt",
    "sg:city":"Sacramento",
    "sg:classifiers":[
        {
            "category":"Social Services",
            "type":"Services"
        },
        {
            "category":"Health Services",
            "subcategory":"Clinic",
            "type":"Services"
        }
    ],
    "sg:phone":"+1 520 749 6908",
    "sg:postcode":"95814",
    "sg:province":"CA",
    "sg:tags":[
        "welfare"
    ],
    "wof:name":"California Blood Bank Society",
    "wof:placetype":"venue"
},
  "geometry": {"coordinates":[-121.49555599999999,38.578438],"type":"Point"}
}