{
  "type": "Feature",
  "properties": {
    "addr:full":"428 Otsego Ave San Francisco CA 94112",
    "addr:housenumber":"428",
    "addr:postcode":"94112",
    "addr:street":"Otsego Ave",
    "iso:country":"US",
    "sg:address":"428 Otsego Ave",
    "sg:city":"San Francisco",
    "sg:classifiers":[
        {
            "category":"Home & Garden",
            "subcategory":"Carpets & Floor Coverings",
            "type":"Retail Goods"
        }
    ],
    "sg:phone":"+1 415 699 8778",
    "sg:postcode":"94112",
    "sg:province":"CA",
    "wof:name":"Architecutural Floors",
    "wof:placetype":"venue"
},
  "geometry": {"coordinates":[-122.442043,37.721944],"type":"Point"}
}