{
  "type": "Feature",
  "properties": {
    "iso:country":"US",
    "sg:address":"1018 N H St",
    "sg:city":"Lompoc",
    "sg:classifiers":[
        {
            "category":"Personal",
            "subcategory":"Beauty Salon",
            "type":"Services"
        }
    ],
    "sg:phone":"+1 805 736 4662",
    "sg:postcode":"93436",
    "sg:province":"CA",
    "sg:website":"www.kizmetstudios.com",
    "wof:name":"Kizmet Studios",
    "wof:placetype":"venue"
},
  "geometry": {"coordinates":[-120.457499,34.656796],"type":"Point"}
}