{
  "type": "Feature",
  "properties": {
    "addr:full":"6445 Skyway Rd Paradise CA 95969",
    "addr:housenumber":"6445",
    "addr:postcode":"95969",
    "addr:street":"Skyway Rd",
    "iso:country":"US",
    "sg:address":"6445 Skyway Rd",
    "sg:city":"Paradise",
    "sg:classifiers":[
        {
            "category":"Education",
            "subcategory":"School",
            "type":"Public Place"
        }
    ],
    "sg:phone":"+1 530 872 1171",
    "sg:postcode":"95969",
    "sg:province":"CA",
    "sg:website":"www.hometech.org",
    "wof:name":"Home Tech Charter School",
    "wof:placetype":"venue"
},
  "geometry": {"coordinates":[-121.624565,39.758565],"type":"Point"}
}