{
  "type": "Feature",
  "properties": {
    "iso:country":"US",
    "sg:address":"6600 Riata Way",
    "sg:city":"Angels Camp",
    "sg:classifiers":[
        {
            "category":"Personal",
            "subcategory":"Beauty Salon",
            "type":"Services"
        }
    ],
    "sg:phone":"+1 209 785 2368",
    "sg:postcode":"95222",
    "sg:province":"CA",
    "wof:name":"Gloria's House Of Beauty",
    "wof:placetype":"venue"
},
  "geometry": {"coordinates":[-120.683036,38.11247],"type":"Point"}
}