{
  "type": "Feature",
  "properties": {
    "addr:full":"1800 Pelican Ave San Pedro CA 90732",
    "addr:housenumber":"1800",
    "addr:postcode":"90732",
    "addr:street":"Pelican Ave",
    "iso:country":"US",
    "sg:address":"1800 Pelican Ave",
    "sg:city":"San Pedro",
    "sg:classifiers":[
        {
            "category":"Manufacturing",
            "subcategory":"Furniture",
            "type":"Manufacturing & Wholesale Goods"
        }
    ],
    "sg:phone":"+1 310 519 8771",
    "sg:postcode":"90732",
    "sg:province":"CA",
    "sg:tags":[
        "wood",
        "mfg"
    ],
    "wof:name":"Pelican Chair Co",
    "wof:placetype":"venue"
},
  "geometry": {"coordinates":[-118.31643099999999,33.727128],"type":"Point"}
}