{
  "type": "Feature",
  "properties": {
    "iso:country":"US",
    "sg:address":"1800 Pelican Ave",
    "sg:city":"San Pedro",
    "sg:classifiers":[
        {
            "category":"Manufacturing",
            "subcategory":"Furniture",
            "type":"Manufacturing & Wholesale Goods"
        }
    ],
    "sg:phone":"+1 310 519 8771",
    "sg:postcode":"90732",
    "sg:province":"CA",
    "sg:tags":[
        "wood",
        "mfg"
    ],
    "wof:name":"Pelican Chair Co",
    "wof:placetype":"venue"
},
  "geometry": {"coordinates":[-118.316431,33.727128],"type":"Point"}
}