{
  "type": "Feature",
  "properties": {
    "addr:full":"4818 E 2nd St Long Beach CA 90803",
    "addr:housenumber":"4818",
    "addr:postcode":"90803",
    "addr:street":"E 2Nd St",
    "iso:country":"US",
    "sg:address":"4818 E 2nd St",
    "sg:city":"Long Beach",
    "sg:classifiers":[
        {
            "category":"Shopping",
            "subcategory":"Gifts & Souvenirs",
            "type":"Retail Goods"
        }
    ],
    "sg:phone":"+1 562 433 0707",
    "sg:postcode":"90803",
    "sg:province":"CA",
    "sg:tags":[
        "shop"
    ],
    "wof:name":"Wiskers",
    "wof:placetype":"venue"
},
  "geometry": {"coordinates":[-118.137434,33.761293],"type":"Point"}
}