{
  "type": "Feature",
  "properties": {
    "addr:full":"18593 Main Street Huntington Beach CA 92648",
    "addr:housenumber":"18593",
    "addr:postcode":"92648",
    "addr:street":"Main Street",
    "iso:country":"US",
    "sg:address":"18593 Main Street",
    "sg:city":"Huntington Beach",
    "sg:classifiers":[
        {
            "category":"Shopping Center",
            "type":"Public Place"
        }
    ],
    "sg:phone":"+1 714 841 0036",
    "sg:postcode":"92648",
    "sg:province":"CA",
    "wof:name":"Five Points Plaza Mgmt",
    "wof:placetype":"venue"
},
  "geometry": {"coordinates":[-117.99040599999999,33.692893],"type":"Point"}
}