{
  "type": "Feature",
  "properties": {
    "iso:country":"US",
    "sg:address":"406 Yosemite Ave",
    "sg:city":"Manteca",
    "sg:classifiers":[
        {
            "category":"Retail",
            "subcategory":"Veterinary Services",
            "type":"Services"
        }
    ],
    "sg:phone":"+1 209 239 4607",
    "sg:postcode":"95337",
    "sg:province":"CA",
    "sg:tags":[
        "clinic"
    ],
    "wof:name":"Animal Clinic",
    "wof:placetype":"venue"
},
  "geometry": {"coordinates":[-121.221773,37.797335],"type":"Point"}
}