{
  "type": "Feature",
  "properties": {
    "iso:country":"US",
    "sg:address":"2963 E Landen St",
    "sg:city":"Camarillo",
    "sg:classifiers":[
        {
            "category":"Professional",
            "subcategory":"Engineering",
            "type":"Services"
        }
    ],
    "sg:phone":"+1 805 388 9995",
    "sg:postcode":"93010",
    "sg:province":"CA",
    "sg:tags":[
        "engineer"
    ],
    "wof:name":"Creative Data Devices",
    "wof:placetype":"venue"
},
  "geometry": {"coordinates":[-119.029749,34.238358],"type":"Point"}
}