{
  "type": "Feature",
  "properties": {
    "iso:country":"US",
    "sg:address":"210 Julie Dr",
    "sg:city":"Yuba City",
    "sg:classifiers":[
        {
            "category":"Shopping",
            "type":"Retail Goods"
        }
    ],
    "sg:phone":"+1 530 673 5257",
    "sg:postcode":"95991",
    "sg:province":"CA",
    "sg:tags":[
        "wedding",
        "supply"
    ],
    "wof:name":"Bridesupplier Com",
    "wof:placetype":"venue"
},
  "geometry": {"coordinates":[-121.623099,39.123047],"type":"Point"}
}