{
  "type": "Feature",
  "properties": {
    "addr:full":"8771 Adah St Garden Grove CA 92841",
    "addr:housenumber":"8771",
    "addr:postcode":"92841",
    "addr:street":"Adah St",
    "iso:country":"US",
    "sg:address":"8771 Adah St",
    "sg:city":"Garden Grove",
    "sg:classifiers":[
        {
            "category":"Building & Trades",
            "subcategory":"Electrical",
            "type":"Services"
        }
    ],
    "sg:phone":"+1 714 539 4986",
    "sg:postcode":"92841",
    "sg:province":"CA",
    "sg:tags":[
        "electric",
        "contractor"
    ],
    "wof:name":"Perkins Electric",
    "wof:placetype":"venue"
},
  "geometry": {"coordinates":[-117.98092200000001,33.801349],"type":"Point"}
}