{
  "type": "Feature",
  "properties": {
    "iso:country":"US",
    "sg:address":"701 Seagaze Dr",
    "sg:city":"Oceanside",
    "sg:classifiers":[
        {
            "category":"Recreation",
            "type":"Entertainment"
        }
    ],
    "sg:phone":"+1 760 754 6803",
    "sg:postcode":"92054",
    "sg:province":"CA",
    "sg:tags":[
        "trainer",
        "instruction",
        "yoga"
    ],
    "sg:website":"www.bikramencinitas.com/",
    "wof:name":"Bikram's Yoga College of India",
    "wof:placetype":"venue"
},
  "geometry": {"coordinates":[-117.376999,33.196201],"type":"Point"}
}