{
  "type": "Feature",
  "properties": {
    "addr:full":"355 Chestnut Ave Palo Alto CA 94306",
    "addr:housenumber":"355",
    "addr:postcode":"94306",
    "addr:street":"Chestnut Ave",
    "iso:country":"US",
    "sg:address":"355 Chestnut Ave",
    "sg:city":"Palo Alto",
    "sg:classifiers":[
        {
            "category":"Travel",
            "subcategory":"Travel Agent",
            "type":"Entertainment"
        }
    ],
    "sg:phone":"+1 650 213 9179",
    "sg:postcode":"94306",
    "sg:province":"CA",
    "sg:tags":[
        "agency"
    ],
    "wof:name":"Ddmht",
    "wof:placetype":"venue"
},
  "geometry": {"coordinates":[-122.13460499999999,37.4219],"type":"Point"}
}