{
  "type": "Feature",
  "properties": {
    "addr:full":"17026 Ventura Blvd Encino CA 91316",
    "addr:housenumber":"17026",
    "addr:postcode":"91316",
    "addr:street":"Ventura Blvd",
    "iso:country":"US",
    "sg:address":"17026 Ventura Blvd",
    "sg:city":"Encino",
    "sg:classifiers":[
        {
            "category":"Professional",
            "subcategory":"Business Services",
            "type":"Services"
        }
    ],
    "sg:phone":"+1 818 906 3740",
    "sg:postcode":"91316",
    "sg:province":"CA",
    "sg:tags":[
        "interior",
        "consultant",
        "design",
        "decorator"
    ],
    "wof:name":"Carole Frederick Wallcoverings",
    "wof:placetype":"venue"
},
  "geometry": {"coordinates":[-118.503682,34.159749],"type":"Point"}
}