{
  "type": "Feature",
  "properties": {
    "iso:country":"US",
    "sg:address":"12017 Venice Blvd",
    "sg:city":"Los Angeles",
    "sg:classifiers":[
        {
            "category":"Shopping",
            "subcategory":"Adult",
            "type":"Retail Goods"
        },
        {
            "category":"Recreation",
            "subcategory":"Dance Hall",
            "type":"Entertainment"
        }
    ],
    "sg:phone":"+1 310 397 8292",
    "sg:postcode":"90066",
    "sg:province":"CA",
    "sg:tags":[
        "club"
    ],
    "sg:website":"www.venicebikinibar.com",
    "wof:name":"El Zacatecas Venice Bikini Bar",
    "wof:placetype":"venue"
},
  "geometry": {"coordinates":[-118.429695,34.006173],"type":"Point"}
}