{
  "type": "Feature",
  "properties": {
    "iso:country":"US",
    "sg:address":"10727 White Oak Ave",
    "sg:city":"Granada Hills",
    "sg:classifiers":[
        {
            "category":"Professional",
            "subcategory":"Accounting & Tax Preparation",
            "type":"Services"
        }
    ],
    "sg:phone":"+1 818 363 7227",
    "sg:postcode":"91344",
    "sg:province":"CA",
    "sg:tags":[
        "accountant"
    ],
    "wof:name":"Mike Pailet Public Accountant",
    "wof:placetype":"venue"
},
  "geometry": {"coordinates":[-118.519808,34.265785],"type":"Point"}
}