{
  "type": "Feature",
  "properties": {
    "addr:full":"7005 Southfront Rd Livermore CA 94551",
    "addr:housenumber":"7005",
    "addr:postcode":"94551",
    "addr:street":"Southfront Rd",
    "iso:country":"US",
    "sg:address":"7005 Southfront Rd",
    "sg:city":"Livermore",
    "sg:classifiers":[
        {
            "category":"Manufacturing",
            "subcategory":"Electronics",
            "type":"Manufacturing & Wholesale Goods"
        }
    ],
    "sg:phone":"+1 925 290 4000",
    "sg:postcode":"94551",
    "sg:province":"CA",
    "sg:tags":[
        "semiconductor",
        "devices"
    ],
    "sg:website":"www.formfactor.com",
    "wof:name":"Form Factor Inc",
    "wof:placetype":"venue"
},
  "geometry": {"coordinates":[-121.70954500000001,37.714493],"type":"Point"}
}