{
  "type": "Feature",
  "properties": {
    "iso:country":"US",
    "sg:address":"28059 Bradley Rd",
    "sg:city":"Sun City",
    "sg:classifiers":[
        {
            "category":"Shopping",
            "subcategory":"Clothing, Apparel, & Fashions",
            "type":"Retail Goods"
        }
    ],
    "sg:phone":"+1 951 679 2218",
    "sg:postcode":"92586",
    "sg:province":"CA",
    "sg:tags":[
        "accessory"
    ],
    "wof:name":"Dee's Fashion Outlet",
    "wof:placetype":"venue"
},
  "geometry": {"coordinates":[-117.189809,33.717823],"type":"Point"}
}