{
  "type": "Feature",
  "properties": {
    "addr:full":"231 Avocado St Costa Mesa CA 92627",
    "addr:housenumber":"231",
    "addr:postcode":"92627",
    "addr:street":"Avocado St",
    "iso:country":"US",
    "sg:address":"231 Avocado St",
    "sg:city":"Costa Mesa",
    "sg:classifiers":[
        {
            "category":"Building & Trades",
            "subcategory":"Construction",
            "type":"Services"
        }
    ],
    "sg:phone":"+1 949 646 6701",
    "sg:postcode":"92627",
    "sg:province":"CA",
    "sg:tags":[
        "tile",
        "dealer"
    ],
    "wof:name":"Terra Firma Tile Co",
    "wof:placetype":"venue"
},
  "geometry": {"coordinates":[-117.90772699999999,33.654394],"type":"Point"}
}