{
  "type": "Feature",
  "properties": {
    "addr:full":"1434 University Ave Berkeley CA 94702",
    "addr:housenumber":"1434",
    "addr:postcode":"94702",
    "addr:street":"University Ave",
    "iso:country":"US",
    "sg:address":"1434 University Ave",
    "sg:city":"Berkeley",
    "sg:classifiers":[
        {
            "category":"Shopping",
            "subcategory":"Computers & Home Electronics",
            "type":"Retail Goods"
        }
    ],
    "sg:phone":"+1 510 526 5891",
    "sg:postcode":"94702",
    "sg:province":"CA",
    "sg:tags":[
        "software"
    ],
    "sg:website":"www.trafficware.com",
    "wof:name":"Trafficware",
    "wof:placetype":"venue"
},
  "geometry": {"coordinates":[-122.28430899999999,37.870083],"type":"Point"}
}