{
  "type": "Feature",
  "properties": {
    "addr:full":"380 Beach St San Francisco CA 94133",
    "addr:housenumber":"380",
    "addr:postcode":"94133",
    "addr:street":"Beach St",
    "iso:country":"US",
    "sg:address":"380 Beach St",
    "sg:city":"San Francisco",
    "sg:classifiers":[
        {
            "category":"Building & Trades",
            "subcategory":"Construction",
            "type":"Services"
        }
    ],
    "sg:phone":"+1 650 343 8233",
    "sg:postcode":"94133",
    "sg:province":"CA",
    "sg:tags":[
        "contractor"
    ],
    "wof:name":"Svala Construction",
    "wof:placetype":"venue"
},
  "geometry": {"coordinates":[-122.414569,37.807519],"type":"Point"}
}