{
  "type": "Feature",
  "properties": {
    "iso:country":"US",
    "sg:address":"304 S Blanche St",
    "sg:city":"Ojai",
    "sg:classifiers":[
        {
            "category":"Shopping",
            "subcategory":"Musical Instruments",
            "type":"Retail Goods"
        }
    ],
    "sg:phone":"+1 805 646 9843",
    "sg:postcode":"93023",
    "sg:province":"CA",
    "wof:name":"Eichelbaum Guitars",
    "wof:placetype":"venue"
},
  "geometry": {"coordinates":[-119.247954,34.445674],"type":"Point"}
}