{
  "type": "Feature",
  "properties": {
    "addr:full":"1402 S Main St Los Angeles CA 90015",
    "addr:housenumber":"1402",
    "addr:postcode":"90015",
    "addr:street":"S Main St",
    "iso:country":"US",
    "sg:address":"1402 S Main St",
    "sg:city":"Los Angeles",
    "sg:classifiers":[
        {
            "category":"Sports & Exercise",
            "subcategory":"Bicycle Rental",
            "type":"Entertainment"
        }
    ],
    "sg:phone":"+1 213 746 9963",
    "sg:postcode":"90015",
    "sg:province":"CA",
    "sg:tags":[
        "wear"
    ],
    "wof:name":"Sky Sportswear",
    "wof:placetype":"venue"
},
  "geometry": {"coordinates":[-118.26143999999999,34.034936],"type":"Point"}
}