{
  "type": "Feature",
  "properties": {
    "iso:country":"US",
    "sg:address":"709 Sandoval Way",
    "sg:city":"Hayward",
    "sg:classifiers":[
        {
            "category":"Wholesale",
            "subcategory":"Electrical",
            "type":"Manufacturing & Wholesale Goods"
        }
    ],
    "sg:phone":"+1 510 477 0921",
    "sg:postcode":"94544",
    "sg:province":"CA",
    "sg:tags":[
        "semiconductor"
    ],
    "wof:name":"Rise Tech Precision LLC",
    "wof:placetype":"venue"
},
  "geometry": {"coordinates":[-122.05429100000001,37.621646],"type":"Point"}
}