{
  "type": "Feature",
  "properties": {
    "iso:country":"US",
    "sg:address":"3337 Foothill Blvd",
    "sg:city":"Oakland",
    "sg:classifiers":[
        {
            "category":"Shopping",
            "subcategory":"Clothing, Apparel, & Fashions",
            "type":"Retail Goods"
        }
    ],
    "sg:phone":"+1 510 534 0107",
    "sg:postcode":"94601",
    "sg:province":"CA",
    "sg:tags":[
        "accessory",
        "clothing",
        "women's"
    ],
    "wof:name":"Sheik Model",
    "wof:placetype":"venue"
},
  "geometry": {"coordinates":[-122.221142,37.783061],"type":"Point"}
}