{
  "type": "Feature",
  "properties": {
    "iso:country":"US",
    "sg:address":"16640 Spruce St",
    "sg:city":"Hesperia",
    "sg:classifiers":[
        {
            "category":"Retail",
            "subcategory":"Repair Shop",
            "type":"Services"
        }
    ],
    "sg:phone":"+1 760 948 4601",
    "sg:postcode":"92345",
    "sg:province":"CA",
    "sg:tags":[
        "commercial",
        "welding"
    ],
    "wof:name":"A & G Welding",
    "wof:placetype":"venue"
},
  "geometry": {"coordinates":[-117.299757,34.424256],"type":"Point"}
}