{
  "type": "Feature",
  "properties": {
    "iso:country":"US",
    "sg:address":"685 State St",
    "sg:city":"Hemet",
    "sg:classifiers":[
        {
            "category":"Real Estate",
            "subcategory":"Real Estate Operator",
            "type":"Services"
        }
    ],
    "sg:phone":"+1 951 925 2152",
    "sg:postcode":"92543",
    "sg:province":"CA",
    "sg:tags":[
        "mobile",
        "home",
        "community"
    ],
    "wof:name":"Town & Country Mobilehome Park",
    "wof:placetype":"venue"
},
  "geometry": {"coordinates":[-116.971831,33.75817],"type":"Point"}
}