{
  "type": "Feature",
  "properties": {
    "addr:full":"4730 Fleming Ave Oakland CA 94619",
    "addr:housenumber":"4730",
    "addr:postcode":"94619",
    "addr:street":"Fleming Ave",
    "iso:country":"US",
    "sg:address":"4730 Fleming Ave",
    "sg:city":"Oakland",
    "sg:classifiers":[
        {
            "category":"Education",
            "subcategory":"School",
            "type":"Public Place"
        }
    ],
    "sg:phone":"+1 510 879 1390",
    "sg:postcode":"94619",
    "sg:province":"CA",
    "sg:tags":[
        "k-",
        "private"
    ],
    "wof:name":"Oakland Public Schools",
    "wof:placetype":"venue"
},
  "geometry": {"coordinates":[-122.19794899999999,37.780309],"type":"Point"}
}