{
  "type": "Feature",
  "properties": {
    "addr:full":"2075 N Oxnard Blvd Oxnard CA 93036",
    "addr:housenumber":"2075",
    "addr:postcode":"93036",
    "addr:street":"N Oxnard Blvd",
    "iso:country":"US",
    "sg:address":"2075 N Oxnard Blvd",
    "sg:city":"Oxnard",
    "sg:classifiers":[
        {
            "category":"Restaurant",
            "type":"Food & Drink"
        }
    ],
    "sg:phone":"+1 805 981 8100",
    "sg:postcode":"93036",
    "sg:province":"CA",
    "wof:name":"Yokozuna",
    "wof:placetype":"venue"
},
  "geometry": {"coordinates":[-119.17718600000001,34.219192],"type":"Point"}
}