{
  "type": "Feature",
  "properties": {
    "addr:full":"1622 Sonoma Blvd Vallejo CA 94590",
    "addr:housenumber":"1622",
    "addr:postcode":"94590",
    "addr:street":"Sonoma Blvd",
    "iso:country":"US",
    "sg:address":"1622 Sonoma Blvd",
    "sg:city":"Vallejo",
    "sg:classifiers":[
        {
            "category":"Shopping",
            "subcategory":"Florist",
            "type":"Retail Goods"
        }
    ],
    "sg:phone":"+1 707 647 2250",
    "sg:postcode":"94590",
    "sg:province":"CA",
    "wof:name":"Carol's Flower Designs",
    "wof:placetype":"venue"
},
  "geometry": {"coordinates":[-122.25490000000001,38.100371],"type":"Point"}
}