{
  "type": "Feature",
  "properties": {
    "addr:full":"12056 Paramount Blvd Downey CA 90242",
    "addr:housenumber":"12056",
    "addr:postcode":"90242",
    "addr:street":"Paramount Blvd",
    "iso:country":"US",
    "sg:address":"12056 Paramount Blvd",
    "sg:city":"Downey",
    "sg:classifiers":[
        {
            "category":"Restaurant",
            "type":"Food & Drink"
        }
    ],
    "sg:phone":"+1 562 869 2001",
    "sg:postcode":"90242",
    "sg:province":"CA",
    "wof:name":"Salvatore's Pasta House",
    "wof:placetype":"venue"
},
  "geometry": {"coordinates":[-118.14594700000001,33.931852],"type":"Point"}
}