{
  "type": "Feature",
  "properties": {
    "addr:full":"6930 Almaden Expy San Jose CA 95120",
    "addr:housenumber":"6930",
    "addr:postcode":"95120",
    "addr:street":"Almaden Expy",
    "iso:country":"US",
    "sg:address":"6930 Almaden Expy",
    "sg:city":"San Jose",
    "sg:classifiers":[
        {
            "category":"Personal",
            "subcategory":"Beauty Salon",
            "type":"Services"
        }
    ],
    "sg:phone":"+1 408 323 0757",
    "sg:postcode":"95120",
    "sg:province":"CA",
    "wof:name":"Aesthetics By Lydia",
    "wof:placetype":"venue"
},
  "geometry": {"coordinates":[-121.8477,37.210948],"type":"Point"}
}