{
  "type": "Feature",
  "properties": {
    "addr:full":"6465 Sierra Ln Dublin CA 94568",
    "addr:housenumber":"6465",
    "addr:postcode":"94568",
    "addr:street":"Sierra Ln",
    "iso:country":"US",
    "sg:address":"6465 Sierra Ln",
    "sg:city":"Dublin",
    "sg:classifiers":[
        {
            "category":"Shopping",
            "type":"Retail Goods"
        }
    ],
    "sg:phone":"+1 925 426 9013",
    "sg:postcode":"94568",
    "sg:province":"CA",
    "sg:tags":[
        "wedding",
        "supply"
    ],
    "sg:website":"www.bradkinney.com",
    "wof:name":"Brad Kinney Productions",
    "wof:placetype":"venue"
},
  "geometry": {"coordinates":[-121.913708,37.70587],"type":"Point"}
}