{
  "type": "Feature",
  "properties": {
    "iso:country":"US",
    "sg:address":"7087 N Thorne Ave",
    "sg:city":"Fresno",
    "sg:classifiers":[
        {
            "category":"Real Estate",
            "subcategory":"Real Estate Services",
            "type":"Services"
        }
    ],
    "sg:phone":"+1 866 294 2671",
    "sg:postcode":"93650",
    "sg:province":"CA",
    "sg:tags":[
        "apartment",
        "management",
        "rental",
        "finder"
    ],
    "sg:website":"http://www.forrent.com/apartment-community-profile/912003162.php?cmp=CAC-CSearchProfile",
    "wof:name":"Windemere Apts.....Think Service!",
    "wof:placetype":"venue"
},
  "geometry": {"coordinates":[-119.812849,36.840403],"type":"Point"}
}