{
  "type": "Feature",
  "properties": {
    "iso:country":"US",
    "sg:address":"79 N Grove Ave",
    "sg:city":"Upland",
    "sg:classifiers":[
        {
            "category":"Personal",
            "subcategory":"Beauty Salon",
            "type":"Services"
        }
    ],
    "sg:phone":"+1 909 931 1353",
    "sg:postcode":"91786",
    "sg:province":"CA",
    "wof:name":"Celeste's Magic Cuts",
    "wof:placetype":"venue"
},
  "geometry": {"coordinates":[-117.628558,34.095064],"type":"Point"}
}