{
  "type": "Feature",
  "properties": {
    "addr:full":"1627 E Valley Pkwy Escondido CA 92027",
    "addr:housenumber":"1627",
    "addr:postcode":"92027",
    "addr:street":"E Valley Pkwy",
    "iso:country":"US",
    "sg:address":"1627 E Valley Pkwy",
    "sg:city":"Escondido",
    "sg:classifiers":[
        {
            "category":"Restaurant",
            "type":"Food & Drink"
        }
    ],
    "sg:phone":"+1 760 480 0222",
    "sg:postcode":"92027",
    "sg:province":"CA",
    "sg:website":"www.sorrentinospizza.com",
    "wof:name":"Sorrentino's",
    "wof:placetype":"venue"
},
  "geometry": {"coordinates":[-117.057436,33.134825],"type":"Point"}
}