{
  "type": "Feature",
  "properties": {
    "addr:full":"2401 Rampart St Oakland CA 94602",
    "addr:housenumber":"2401",
    "addr:postcode":"94602",
    "addr:street":"Rampart St",
    "iso:country":"US",
    "sg:address":"2401 Rampart St",
    "sg:city":"Oakland",
    "sg:classifiers":[
        {
            "category":"Education",
            "subcategory":"Special Training",
            "type":"Public Place"
        }
    ],
    "sg:phone":"+1 510 325 3389",
    "sg:postcode":"94602",
    "sg:province":"CA",
    "sg:tags":[
        "school",
        "language"
    ],
    "wof:name":"Mariposa Academy",
    "wof:placetype":"venue"
},
  "geometry": {"coordinates":[-122.20608799999999,37.803858],"type":"Point"}
}