{
  "type": "Feature",
  "properties": {
    "iso:country":"US",
    "sg:address":"20 Willard Ln",
    "sg:city":"Hillsborough",
    "sg:classifiers":[
        {
            "category":"Banks & Credit Unions",
            "subcategory":"Investment Brokerage",
            "type":"Services"
        }
    ],
    "sg:phone":"+1 650 342 1432",
    "sg:postcode":"94010",
    "sg:province":"CA",
    "sg:tags":[
        "advisory"
    ],
    "wof:name":"Winters Family Investments Lp",
    "wof:placetype":"venue"
},
  "geometry": {"coordinates":[-122.34954,37.555407],"type":"Point"}
}