{
  "type": "Feature",
  "properties": {
    "iso:country":"US",
    "sg:address":"940 Cll Amanecer",
    "sg:city":"San Clemente",
    "sg:classifiers":[
        {
            "category":"Wholesale",
            "subcategory":"Medical Equipment & Supplies",
            "type":"Manufacturing & Wholesale Goods"
        }
    ],
    "sg:phone":"+1 949 218 0092",
    "sg:postcode":"92673",
    "sg:province":"CA",
    "sg:tags":[
        "hospital"
    ],
    "wof:name":"Heartsine Technologies",
    "wof:placetype":"venue"
},
  "geometry": {"coordinates":[-117.60522,33.449709],"type":"Point"}
}