{
  "type": "Feature",
  "properties": {
    "addr:full":"2375 Pso de Las Americas San Diego CA 92154",
    "addr:housenumber":"2375",
    "addr:postcode":"92154",
    "addr:street":"Pso De Las Americas",
    "iso:country":"US",
    "sg:address":"2375 Pso de Las Americas",
    "sg:city":"San Diego",
    "sg:classifiers":[
        {
            "category":"Wholesale",
            "subcategory":"Durable Goods & Equipment",
            "type":"Manufacturing & Wholesale Goods"
        }
    ],
    "sg:phone":"+1 619 661 0401",
    "sg:postcode":"92154",
    "sg:province":"CA",
    "sg:tags":[
        "importer"
    ],
    "wof:name":"Mart Import",
    "wof:placetype":"venue"
},
  "geometry": {"coordinates":[-116.935856,32.556223],"type":"Point"}
}