{
  "type": "Feature",
  "properties": {
    "iso:country":"US",
    "sg:address":"PO Box 543",
    "sg:city":"San Francisco",
    "sg:classifiers":[
        {
            "category":"Professional",
            "subcategory":"Art Services",
            "type":"Services"
        }
    ],
    "sg:phone":"+1 800 392 9939",
    "sg:postcode":"94101",
    "sg:province":"CA",
    "sg:tags":[
        "photographer"
    ],
    "sg:website":"www.mikedanen.com",
    "wof:name":"Mike Danen Photography",
    "wof:placetype":"venue"
},
  "geometry": {"coordinates":[-122.4186,37.7753],"type":"Point"}
}