{
  "type": "Feature",
  "properties": {
    "addr:full":"13560 Thistle St Victorville CA 92392",
    "addr:housenumber":"13560",
    "addr:postcode":"92392",
    "addr:street":"Thistle St",
    "iso:country":"US",
    "sg:address":"13560 Thistle St",
    "sg:city":"Victorville",
    "sg:classifiers":[
        {
            "category":"Professional",
            "subcategory":"Advertising",
            "type":"Services"
        }
    ],
    "sg:phone":"+1 760 243 9774",
    "sg:postcode":"92392",
    "sg:province":"CA",
    "sg:tags":[
        "mail"
    ],
    "sg:website":"www.mjmadv.com",
    "wof:name":"Mjm Advertising",
    "wof:placetype":"venue"
},
  "geometry": {"coordinates":[-117.367215,34.479935],"type":"Point"}
}