{
  "type": "Feature",
  "properties": {
    "iso:country":"US",
    "sg:address":"1050-B El Camino Real",
    "sg:city":"Belmont",
    "sg:classifiers":[
        {
            "category":"Shopping",
            "subcategory":"Jewelry",
            "type":"Retail Goods"
        }
    ],
    "sg:phone":"+1 650 594 1215",
    "sg:postcode":"94002",
    "sg:province":"CA",
    "sg:website":"www.whitedovejewelry.com",
    "wof:name":"White Dove Jewelry",
    "wof:placetype":"venue"
},
  "geometry": {"coordinates":[-122.27555099999999,37.520019],"type":"Point"}
}