{
  "type": "Feature",
  "properties": {
    "iso:country":"US",
    "sg:address":"779 Caprice Way",
    "sg:city":"Chico",
    "sg:classifiers":[
        {
            "category":"Professional",
            "type":"Services"
        }
    ],
    "sg:phone":"+1 530 343 2270",
    "sg:postcode":"95973",
    "sg:province":"CA",
    "wof:name":"Shay Shay Inc",
    "wof:placetype":"venue"
},
  "geometry": {"coordinates":[-121.854471,39.770323],"type":"Point"}
}