{
  "type": "Feature",
  "properties": {
    "iso:country":"US",
    "sg:address":"601 N McPherson St",
    "sg:city":"La Habra",
    "sg:classifiers":[
        {
            "category":"Professional",
            "subcategory":"Management & Consulting",
            "type":"Services"
        }
    ],
    "sg:phone":"+1 562 691 9674",
    "sg:postcode":"90631",
    "sg:province":"CA",
    "sg:tags":[
        "fuel"
    ],
    "wof:name":"Winner Fire Management",
    "wof:placetype":"venue"
},
  "geometry": {"coordinates":[-117.938363,33.935758],"type":"Point"}
}