{
  "type": "Feature",
  "properties": {
    "iso:country":"US",
    "sg:address":"1447 Morgan Rd",
    "sg:city":"San Bernardino",
    "sg:classifiers":[
        {
            "category":"Arts & Performance",
            "subcategory":"Theater",
            "type":"Entertainment"
        }
    ],
    "sg:phone":"+1 909 991 9060",
    "sg:postcode":"92407",
    "sg:province":"CA",
    "sg:tags":[
        "bureau"
    ],
    "wof:name":"Teen Music Connection Live",
    "wof:placetype":"venue"
},
  "geometry": {"coordinates":[-117.317463,34.168018],"type":"Point"}
}