{
  "type": "Feature",
  "properties": {
    "iso:country":"US",
    "sg:address":"20767 4th St",
    "sg:city":"Cottonwood",
    "sg:classifiers":[
        {
            "category":"Real Estate",
            "subcategory":"Real Estate Agent",
            "type":"Services"
        }
    ],
    "sg:phone":"+1 530 347 3703",
    "sg:postcode":"96022",
    "sg:province":"CA",
    "wof:name":"Deese Realtors",
    "wof:placetype":"venue"
},
  "geometry": {"coordinates":[-122.28507999999999,40.38932],"type":"Point"}
}