{
  "type": "Feature",
  "properties": {
    "iso:country":"US",
    "sg:address":"2755 Dawson Ave",
    "sg:city":"Signal Hill",
    "sg:classifiers":[
        {
            "category":"Manufacturing",
            "subcategory":"Tools & Machinery",
            "type":"Manufacturing & Wholesale Goods"
        }
    ],
    "sg:phone":"+1 562 595 7363",
    "sg:postcode":"90755",
    "sg:province":"CA",
    "sg:tags":[
        "oil",
        "gas"
    ],
    "wof:name":"John M Phillips Oilfield",
    "wof:placetype":"venue"
},
  "geometry": {"coordinates":[-118.165488,33.807025],"type":"Point"}
}