{
  "type": "Feature",
  "properties": {
    "addr:full":"6309 W 6th St Rio Linda CA 95673",
    "addr:housenumber":"6309",
    "addr:postcode":"95673",
    "addr:street":"W 6Th St",
    "iso:country":"US",
    "sg:address":"6309 W 6th St",
    "sg:city":"Rio Linda",
    "sg:classifiers":[
        {
            "category":"Shopping",
            "subcategory":"Hobbies, Toys, & Games",
            "type":"Retail Goods"
        }
    ],
    "sg:phone":"+1 916 991 4676",
    "sg:postcode":"95673",
    "sg:province":"CA",
    "wof:name":"Treasure Box Toys & More",
    "wof:placetype":"venue"
},
  "geometry": {"coordinates":[-121.475449,38.683466],"type":"Point"}
}