{
  "type": "Feature",
  "properties": {
    "iso:country":"US",
    "sg:address":"15404 Valley Blvd",
    "sg:city":"City Of Industry",
    "sg:classifiers":[
        {
            "category":"Autos & Motor Vehicles",
            "subcategory":"Auto Supplies",
            "type":"Retail Goods"
        }
    ],
    "sg:phone":"+1 626 336 5600",
    "sg:postcode":"91746",
    "sg:province":"CA",
    "sg:tags":[
        "automobile",
        "parts"
    ],
    "wof:name":"Kuruma Motoring Inc",
    "wof:placetype":"venue"
},
  "geometry": {"coordinates":[-117.962668,34.026013],"type":"Point"}
}