{
  "type": "Feature",
  "properties": {
    "addr:full":"5944 Stockton Blvd Sacramento CA 95824",
    "addr:housenumber":"5944",
    "addr:postcode":"95824",
    "addr:street":"Stockton Blvd",
    "iso:country":"US",
    "sg:address":"5944 Stockton Blvd",
    "sg:city":"Sacramento",
    "sg:classifiers":[
        {
            "category":"Shopping",
            "subcategory":"Jewelry",
            "type":"Retail Goods"
        }
    ],
    "sg:phone":"+1 916 391 3039",
    "sg:postcode":"95824",
    "sg:province":"CA",
    "wof:name":"Tim Thanh Jewelry",
    "wof:placetype":"venue"
},
  "geometry": {"coordinates":[-121.439622,38.518387],"type":"Point"}
}