{
  "type": "Feature",
  "properties": {
    "addr:full":"1811 State St Santa Barbara CA 93101",
    "addr:housenumber":"1811",
    "addr:postcode":"93101",
    "addr:street":"State St",
    "iso:country":"US",
    "sg:address":"1811 State St",
    "sg:city":"Santa Barbara",
    "sg:classifiers":[
        {
            "category":"Professional",
            "subcategory":"Secretarial Services",
            "type":"Services"
        }
    ],
    "sg:phone":"+1 805 687 4885",
    "sg:postcode":"93101",
    "sg:province":"CA",
    "sg:tags":[
        "processing",
        "word"
    ],
    "wof:name":"Resume Etc",
    "wof:placetype":"venue"
},
  "geometry": {"coordinates":[-119.713347,34.429752],"type":"Point"}
}