{
  "type": "Feature",
  "properties": {
    "addr:full":"2241 Monument Blvd Concord CA 94520",
    "addr:housenumber":"2241",
    "addr:postcode":"94520",
    "addr:street":"Monument Blvd",
    "iso:country":"US",
    "sg:address":"2241 Monument Blvd",
    "sg:city":"Concord",
    "sg:classifiers":[
        {
            "category":"Retail",
            "subcategory":"Auto Repair",
            "type":"Services"
        }
    ],
    "sg:phone":"+1 925 689 8444",
    "sg:postcode":"94520",
    "sg:province":"CA",
    "sg:tags":[
        "body",
        "automobile",
        "painting"
    ],
    "wof:name":"R K Collision",
    "wof:placetype":"venue"
},
  "geometry": {"coordinates":[-122.036243,37.958308],"type":"Point"}
}