{
  "type": "Feature",
  "properties": {
    "iso:country":"US",
    "sg:address":"2593 S. King Rd Ste 11",
    "sg:city":"San Jose",
    "sg:classifiers":[
        {
            "category":"Health Services",
            "subcategory":"Doctor",
            "type":"Services"
        }
    ],
    "sg:phone":"+1 408 274 2880",
    "sg:postcode":"95122",
    "sg:province":"CA",
    "sg:tags":[
        "practice",
        "family"
    ],
    "wof:name":"Rosalinda Mandreza, MD",
    "wof:placetype":"venue"
},
  "geometry": {"coordinates":[-121.82328099999999,37.318532],"type":"Point"}
}