{
  "type": "Feature",
  "properties": {
    "addr:full":"12490 Magnolia Ave Riverside CA 92503",
    "addr:housenumber":"12490",
    "addr:postcode":"92503",
    "addr:street":"Magnolia Ave",
    "iso:country":"US",
    "sg:address":"12490 Magnolia Ave",
    "sg:city":"Riverside",
    "sg:classifiers":[
        {
            "category":"Building & Trades",
            "subcategory":"Construction",
            "type":"Services"
        }
    ],
    "sg:phone":"+1 951 372 9116",
    "sg:postcode":"92503",
    "sg:province":"CA",
    "sg:tags":[
        "maker",
        "cabinet"
    ],
    "wof:name":"Godinez Cabinets",
    "wof:placetype":"venue"
},
  "geometry": {"coordinates":[-117.50194,33.888971],"type":"Point"}
}