{
  "type": "Feature",
  "properties": {
    "addr:full":"6759 Brockton Ave Riverside CA 92506",
    "addr:housenumber":"6759",
    "addr:postcode":"92506",
    "addr:street":"Brockton Ave",
    "iso:country":"US",
    "sg:address":"6759 Brockton Ave",
    "sg:city":"Riverside",
    "sg:classifiers":[
        {
            "category":"Professional",
            "type":"Services"
        }
    ],
    "sg:phone":"+1 951 787 6851",
    "sg:postcode":"92506",
    "sg:province":"CA",
    "sg:tags":[
        "establishment"
    ],
    "wof:name":"Brockton Enterprises",
    "wof:placetype":"venue"
},
  "geometry": {"coordinates":[-117.396828,33.95098],"type":"Point"}
}