{
  "type": "Feature",
  "properties": {
    "addr:full":"5420 York Blvd Los Angeles CA 90042",
    "addr:housenumber":"5420",
    "addr:postcode":"90042",
    "addr:street":"York Blvd",
    "iso:country":"US",
    "sg:address":"5420 York Blvd",
    "sg:city":"Los Angeles",
    "sg:classifiers":[
        {
            "category":"Shopping",
            "subcategory":"Books",
            "type":"Retail Goods"
        }
    ],
    "sg:phone":"+1 323 982 9334",
    "sg:postcode":"90042",
    "sg:province":"CA",
    "sg:tags":[
        "merchandise"
    ],
    "wof:name":"Botanica Acharba",
    "wof:placetype":"venue"
},
  "geometry": {"coordinates":[-118.19835999999999,34.119704],"type":"Point"}
}