{
  "type": "Feature",
  "properties": {
    "addr:full":"1404 Ilexey Ave San Diego CA 92154",
    "addr:housenumber":"1404",
    "addr:postcode":"92154",
    "addr:street":"Ilexey Ave",
    "iso:country":"US",
    "sg:address":"1404 Ilexey Ave",
    "sg:city":"San Diego",
    "sg:classifiers":[
        {
            "category":"Manufacturing",
            "subcategory":"Signs",
            "type":"Manufacturing & Wholesale Goods"
        }
    ],
    "sg:phone":"+1 619 934 3836",
    "sg:postcode":"92154",
    "sg:province":"CA",
    "sg:tags":[
        "specialty",
        "mfg"
    ],
    "wof:name":"A & G Signs",
    "wof:placetype":"venue"
},
  "geometry": {"coordinates":[-117.044551,32.571889],"type":"Point"}
}