{
  "type": "Feature",
  "properties": {
    "iso:country":"US",
    "sg:address":"3878 Alder Pl",
    "sg:city":"Chino Hills",
    "sg:classifiers":[
        {
            "category":"Education",
            "subcategory":"Special Training",
            "type":"Public Place"
        }
    ],
    "sg:phone":"+1 909 393 5261",
    "sg:postcode":"91709",
    "sg:province":"CA",
    "sg:tags":[
        "instruction",
        "driving"
    ],
    "wof:name":"Ace Driving School",
    "wof:placetype":"venue"
},
  "geometry": {"coordinates":[-117.720888,33.985921],"type":"Point"}
}