{
  "type": "Feature",
  "properties": {
    "addr:full":"7222 Church St Yucca Valley CA 92284",
    "addr:housenumber":"7222",
    "addr:postcode":"92284",
    "addr:street":"Church St",
    "iso:country":"US",
    "sg:address":"7222 Church St",
    "sg:city":"Yucca Valley",
    "sg:classifiers":[
        {
            "category":"Freight",
            "type":"Transportation"
        }
    ],
    "sg:phone":"+1 760 365 0093",
    "sg:postcode":"92284",
    "sg:province":"CA",
    "sg:tags":[
        "general"
    ],
    "wof:name":"Grand Central Storage",
    "wof:placetype":"venue"
},
  "geometry": {"coordinates":[-116.436606,34.122233],"type":"Point"}
}