{
  "type": "Feature",
  "properties": {
    "addr:full":"10835 Santa Monica Blvd # Bi Los Angeles CA 90025",
    "addr:housenumber":"10835",
    "addr:postcode":"90025",
    "addr:street":"Santa Monica Blvd # Bi",
    "iso:country":"US",
    "sg:address":"10835 Santa Monica Blvd # Bi",
    "sg:city":"Los Angeles",
    "sg:classifiers":[
        {
            "category":"Real Estate",
            "subcategory":"Real Estate Services",
            "type":"Services"
        }
    ],
    "sg:phone":"+1 310 475 1906",
    "sg:postcode":"90025",
    "sg:province":"CA",
    "sg:tags":[
        "management",
        "property"
    ],
    "wof:name":"Bank Dick",
    "wof:placetype":"venue"
},
  "geometry": {"coordinates":[-118.43641700000001,34.003362],"type":"Point"}
}