{
  "type": "Feature",
  "properties": {
    "addr:full":"6550 Moraga Ave Piedmont CA 94611",
    "addr:housenumber":"6550",
    "addr:postcode":"94611",
    "addr:street":"Moraga Ave",
    "iso:country":"US",
    "sg:address":"6550 Moraga Ave",
    "sg:city":"Piedmont",
    "sg:classifiers":[
        {
            "category":"Retail",
            "subcategory":"Auto Repair",
            "type":"Services"
        },
        {
            "category":"Government",
            "subcategory":"Office",
            "type":"Public Place"
        }
    ],
    "sg:phone":"+1 510 339 1064",
    "sg:postcode":"94611",
    "sg:province":"CA",
    "sg:tags":[
        "smog",
        "check"
    ],
    "wof:name":"Betts Ken Service Centers",
    "wof:placetype":"venue"
},
  "geometry": {"coordinates":[-122.219002,37.832802],"type":"Point"}
}