{
  "type": "Feature",
  "properties": {
    "iso:country":"US",
    "sg:address":"300 Lynn Dr",
    "sg:city":"Ventura",
    "sg:classifiers":[
        {
            "category":"Education",
            "subcategory":"School",
            "type":"Public Place"
        }
    ],
    "sg:phone":"+1 805 641 5443",
    "sg:postcode":"93003",
    "sg:province":"CA",
    "wof:name":"Loma Vista Elementary School",
    "wof:placetype":"venue"
},
  "geometry": {"coordinates":[-119.250165,34.277744],"type":"Point"}
}