{
  "type": "Feature",
  "properties": {
    "addr:full":"1555 Ivar Avenue Hollywood CA 90028",
    "addr:housenumber":"1555",
    "addr:postcode":"90028",
    "addr:street":"Ivar Avenue",
    "iso:country":"US",
    "sg:address":"1555 Ivar Avenue",
    "sg:city":"Hollywood",
    "sg:classifiers":[
        {
            "category":"Restaurant",
            "type":"Food & Drink"
        }
    ],
    "sg:phone":"+1 310 691 2410",
    "sg:postcode":"90028",
    "sg:province":"CA",
    "sg:tags":[
        "flavor",
        "local"
    ],
    "sg:website":"www.stolihotel.com/",
    "wof:name":"Stoli Hotel",
    "wof:placetype":"venue"
},
  "geometry": {"coordinates":[-118.328631,34.099021],"type":"Point"}
}