{
  "type": "Feature",
  "properties": {
    "addr:full":"1994 Banda Ave Calexico CA 92231",
    "addr:housenumber":"1994",
    "addr:postcode":"92231",
    "addr:street":"Banda Ave",
    "iso:country":"US",
    "sg:address":"1994 Banda Ave",
    "sg:city":"Calexico",
    "sg:classifiers":[
        {
            "category":"Wholesale",
            "subcategory":"Non-durable Goods",
            "type":"Manufacturing & Wholesale Goods"
        }
    ],
    "sg:phone":"+1 760 357 3007",
    "sg:postcode":"92231",
    "sg:province":"CA",
    "wof:name":"V & G Exporters",
    "wof:placetype":"venue"
},
  "geometry": {"coordinates":[-115.48323000000001,32.687883],"type":"Point"}
}