{
  "type": "Feature",
  "properties": {
    "iso:country":"US",
    "sg:address":"225 Frederick St",
    "sg:city":"San Francisco",
    "sg:classifiers":[
        {
            "category":"Food & Beverages",
            "subcategory":"Groceries & Convenience Stores",
            "type":"Retail Goods"
        }
    ],
    "sg:phone":"+1 415 664 2300",
    "sg:postcode":"94117",
    "sg:province":"CA",
    "wof:name":"Frederick Street Super Market",
    "wof:placetype":"venue"
},
  "geometry": {"coordinates":[-122.44699900000001,37.766998],"type":"Point"}
}