{
  "type": "Feature",
  "properties": {
    "iso:country":"US",
    "sg:address":"1551 Industrial Pkwy W",
    "sg:city":"Hayward",
    "sg:classifiers":[
        {
            "category":"Wholesale",
            "subcategory":"Motor Vehicles",
            "type":"Manufacturing & Wholesale Goods"
        }
    ],
    "sg:phone":"+1 510 264 1869",
    "sg:postcode":"94544",
    "sg:province":"CA",
    "sg:tags":[
        "automobile",
        "transporter"
    ],
    "wof:name":"Bay Area Auto Delivery",
    "wof:placetype":"venue"
},
  "geometry": {"coordinates":[-122.06324600000001,37.618042],"type":"Point"}
}