{
  "type": "Feature",
  "properties": {
    "iso:country":"US",
    "sg:address":"100 Ucla Medical Plz",
    "sg:city":"Los Angeles",
    "sg:classifiers":[
        {
            "category":"Health Services",
            "subcategory":"Hospital",
            "type":"Services"
        }
    ],
    "sg:phone":"+1 310 443 0447",
    "sg:postcode":"90024",
    "sg:province":"CA",
    "wof:name":"Ucla Hematology-Oncology",
    "wof:placetype":"venue"
},
  "geometry": {"coordinates":[-118.445,34.070999],"type":"Point"}
}