{
  "type": "Feature",
  "properties": {
    "iso:country":"US",
    "sg:address":"4960 Holt Blvd",
    "sg:city":"Montclair",
    "sg:classifiers":[
        {
            "category":"Shopping",
            "subcategory":"Gifts & Souvenirs",
            "type":"Retail Goods"
        }
    ],
    "sg:phone":"+1 909 447 4154",
    "sg:postcode":"91763",
    "sg:province":"CA",
    "sg:tags":[
        "party",
        "supply"
    ],
    "wof:name":"Angie's Party Supplies",
    "wof:placetype":"venue"
},
  "geometry": {"coordinates":[-117.690699,34.063319],"type":"Point"}
}