{
  "type": "Feature",
  "properties": {
    "iso:country":"US",
    "sg:address":"410 S Santa Fe Ave",
    "sg:city":"Vista",
    "sg:classifiers":[
        {
            "category":"Building & Trades",
            "subcategory":"Construction",
            "type":"Services"
        }
    ],
    "sg:phone":"+1 760 726 1444",
    "sg:postcode":"92084",
    "sg:province":"CA",
    "sg:tags":[
        "contractor"
    ],
    "wof:name":"J C Hilly Co",
    "wof:placetype":"venue"
},
  "geometry": {"coordinates":[-117.23985399999999,33.197591],"type":"Point"}
}