{
  "type": "Feature",
  "properties": {
    "iso:country":"US",
    "sg:address":"12121 Wilshire Blvd",
    "sg:city":"Los Angeles",
    "sg:classifiers":[
        {
            "category":"Professional",
            "subcategory":"Accounting & Tax Preparation",
            "type":"Services"
        }
    ],
    "sg:phone":"+1 310 979 8600",
    "sg:postcode":"90025",
    "sg:province":"CA",
    "sg:tags":[
        "accountant"
    ],
    "wof:name":"Morgan H Mc Nenny CPA",
    "wof:placetype":"venue"
},
  "geometry": {"coordinates":[-118.468221,34.043614],"type":"Point"}
}