{
  "type": "Feature",
  "properties": {
    "addr:full":"2221 Stockton Blvd Sacramento CA 95817",
    "addr:housenumber":"2221",
    "addr:postcode":"95817",
    "addr:street":"Stockton Blvd",
    "iso:country":"US",
    "sg:address":"2221 Stockton Blvd",
    "sg:city":"Sacramento",
    "sg:classifiers":[
        {
            "category":"Health Services",
            "subcategory":"Hospital",
            "type":"Services"
        }
    ],
    "sg:phone":"+1 916 734 2737",
    "sg:postcode":"95817",
    "sg:province":"CA",
    "sg:tags":[
        "children's"
    ],
    "wof:name":"U C Davis Medical Center & Children's Hospital",
    "wof:placetype":"venue"
},
  "geometry": {"coordinates":[-121.45927399999999,38.556115],"type":"Point"}
}