{
  "type": "Feature",
  "properties": {
    "iso:country":"US",
    "sg:address":"9205 Aguas Frias Rd",
    "sg:city":"Chico",
    "sg:classifiers":[
        {
            "category":"Farming",
            "subcategory":"Farm",
            "type":"Manufacturing & Wholesale Goods"
        }
    ],
    "sg:phone":"+1 530 891 4324",
    "sg:postcode":"95928",
    "sg:province":"CA",
    "sg:tags":[
        "crop",
        "general"
    ],
    "wof:name":"Webster E Gilberts Farms",
    "wof:placetype":"venue"
},
  "geometry": {"coordinates":[-121.861804,39.6482],"type":"Point"}
}