{
  "type": "Feature",
  "properties": {
    "iso:country":"US",
    "sg:address":"8831 Exposition Blvd",
    "sg:city":"Culver City",
    "sg:classifiers":[
        {
            "category":"Professional",
            "type":"Services"
        }
    ],
    "sg:phone":"+1 310 559 5799",
    "sg:postcode":"90232",
    "sg:province":"CA",
    "wof:name":"Idom",
    "wof:placetype":"venue"
},
  "geometry": {"coordinates":[-118.388504,34.028286],"type":"Point"}
}