{
  "type": "Feature",
  "properties": {
    "addr:full":"500 Mart Ave Waterford CA 95386",
    "addr:housenumber":"500",
    "addr:postcode":"95386",
    "addr:street":"Mart Ave",
    "iso:country":"US",
    "sg:address":"500 Mart Ave",
    "sg:city":"Waterford",
    "sg:classifiers":[
        {
            "category":"Farming",
            "subcategory":"Crops",
            "type":"Manufacturing & Wholesale Goods"
        }
    ],
    "sg:phone":"+1 209 522 7858",
    "sg:postcode":"95386",
    "sg:province":"CA",
    "sg:tags":[
        "grove",
        "nut",
        "tree"
    ],
    "wof:name":"Martin Farms Inc",
    "wof:placetype":"venue"
},
  "geometry": {"coordinates":[-120.806386,37.642082],"type":"Point"}
}