{
  "type": "Feature",
  "properties": {
    "addr:full":"1000 Francisco St Torrance CA 90502",
    "addr:housenumber":"1000",
    "addr:postcode":"90502",
    "addr:street":"Francisco St",
    "iso:country":"US",
    "sg:address":"1000 Francisco St",
    "sg:city":"Torrance",
    "sg:classifiers":[
        {
            "category":"Professional",
            "subcategory":"Employment Agencies",
            "type":"Services"
        }
    ],
    "sg:phone":"+1 310 538 4137",
    "sg:postcode":"90502",
    "sg:province":"CA",
    "wof:name":"On Call Staffing",
    "wof:placetype":"venue"
},
  "geometry": {"coordinates":[-118.293263,33.849692],"type":"Point"}
}