{
  "type": "Feature",
  "properties": {
    "iso:country":"US",
    "sg:address":"8689 el Camino Real",
    "sg:city":"Atascadero",
    "sg:classifiers":[
        {
            "category":"Banks & Credit Unions",
            "subcategory":"Bank",
            "type":"Services"
        }
    ],
    "sg:phone":"+1 805 466 5455",
    "sg:postcode":"93422",
    "sg:province":"CA",
    "sg:tags":[
        "loan",
        "real estate"
    ],
    "wof:name":"Loanmax Home Loan Ctr Inc",
    "wof:placetype":"venue"
},
  "geometry": {"coordinates":[-120.653731,35.472683],"type":"Point"}
}