{
  "type": "Feature",
  "properties": {
    "iso:country":"US",
    "sg:address":"18840 Ventura Blvd",
    "sg:city":"Tarzana",
    "sg:classifiers":[
        {
            "category":"Shopping",
            "type":"Retail Goods"
        }
    ],
    "sg:phone":"+1 818 345 5600",
    "sg:postcode":"91356",
    "sg:province":"CA",
    "sg:tags":[
        "telephone",
        "cellular"
    ],
    "wof:name":"USA Distributors Wireless",
    "wof:placetype":"venue"
},
  "geometry": {"coordinates":[-118.544062,34.171897],"type":"Point"}
}