{
  "type": "Feature",
  "properties": {
    "addr:full":"10011 Garden Grove Blvd Garden Grove CA 92844",
    "addr:housenumber":"10011",
    "addr:postcode":"92844",
    "addr:street":"Garden Grove Blvd",
    "iso:country":"US",
    "sg:address":"10011 Garden Grove Blvd",
    "sg:city":"Garden Grove",
    "sg:classifiers":[
        {
            "category":"Shopping",
            "subcategory":"Bicycles & Sporting Goods",
            "type":"Retail Goods"
        }
    ],
    "sg:phone":"+1 949 752 1313",
    "sg:postcode":"92844",
    "sg:province":"CA",
    "sg:tags":[
        "equipment",
        "golf",
        "supply"
    ],
    "wof:name":"Genuin Golf & Dress",
    "wof:placetype":"venue"
},
  "geometry": {"coordinates":[-117.955237,33.774117],"type":"Point"}
}