{
  "type": "Feature",
  "properties": {
    "iso:country":"US",
    "sg:address":"5701 College Ave",
    "sg:city":"Oakland",
    "sg:classifiers":[
        {
            "category":"Restaurant",
            "type":"Food & Drink"
        }
    ],
    "sg:phone":"+1 510 428 2100",
    "sg:postcode":"94618",
    "sg:province":"CA",
    "wof:name":"Jucy's",
    "wof:placetype":"venue"
},
  "geometry": {"coordinates":[-122.251999,37.843102],"type":"Point"}
}