{
  "type": "Feature",
  "properties": {
    "iso:country":"US",
    "sg:address":"2796 Sycamore Dr",
    "sg:city":"Simi Valley",
    "sg:classifiers":[
        {
            "category":"Health Services",
            "subcategory":"Doctor",
            "type":"Services"
        }
    ],
    "sg:phone":"+1 805 522 7955",
    "sg:postcode":"93065",
    "sg:province":"CA",
    "sg:tags":[
        "physician",
        "surgeon"
    ],
    "wof:name":"Harry Loo Corp",
    "wof:placetype":"venue"
},
  "geometry": {"coordinates":[-118.743731,34.284932],"type":"Point"}
}