{
  "type": "Feature",
  "properties": {
    "addr:full":"13130 Burbank Blvd Sherman Oaks CA 91401",
    "addr:housenumber":"13130",
    "addr:postcode":"91401",
    "addr:street":"Burbank Blvd",
    "iso:country":"US",
    "sg:address":"13130 Burbank Blvd",
    "sg:city":"Sherman Oaks",
    "sg:classifiers":[
        {
            "category":"Education",
            "subcategory":"Special Training",
            "type":"Public Place"
        }
    ],
    "sg:phone":"+1 818 781 0360",
    "sg:postcode":"91401",
    "sg:province":"CA",
    "sg:tags":[
        "tutoring"
    ],
    "wof:name":"Summit View School",
    "wof:placetype":"venue"
},
  "geometry": {"coordinates":[-118.418999,34.172298],"type":"Point"}
}