{
  "type": "Feature",
  "properties": {
    "addr:full":"4138 Lincoln Ave Cypress CA 90630",
    "addr:housenumber":"4138",
    "addr:postcode":"90630",
    "addr:street":"Lincoln Ave",
    "iso:country":"US",
    "sg:address":"4138 Lincoln Ave",
    "sg:city":"Cypress",
    "sg:classifiers":[
        {
            "category":"Health Services",
            "subcategory":"Medical Lab",
            "type":"Services"
        }
    ],
    "sg:phone":"+1 714 821 4880",
    "sg:postcode":"90630",
    "sg:province":"CA",
    "sg:tags":[
        "laboratory"
    ],
    "wof:name":"Dentronix Dental Laboratory",
    "wof:placetype":"venue"
},
  "geometry": {"coordinates":[-118.060906,33.831618],"type":"Point"}
}