{
  "type": "Feature",
  "properties": {
    "iso:country":"US",
    "sg:address":"Sheraton Cerritos Hotel 12725 Center Court Dr",
    "sg:city":"Cerritos",
    "sg:classifiers":[
        {
            "category":"Restaurant",
            "type":"Food & Drink"
        },
        {
            "category":"Bars & Pubs",
            "subcategory":"Nightclub",
            "type":"Food & Drink"
        }
    ],
    "sg:phone":"+1 562 403 2029",
    "sg:postcode":"90703",
    "sg:province":"CA",
    "sg:tags":[
        "traditional",
        "american",
        "brunch",
        "nightlife",
        "breakfast"
    ],
    "sg:website":"www.starwoodhotels.com/sheraton/...",
    "wof:name":"Grille 91",
    "wof:placetype":"venue"
},
  "geometry": {"coordinates":[-118.06032999999999,33.868711],"type":"Point"}
}