{
  "type": "Feature",
  "properties": {
    "iso:country":"US",
    "sg:address":"1225 Senwood Way",
    "sg:city":"Fallbrook",
    "sg:classifiers":[
        {
            "category":"Travel",
            "subcategory":"Travel Agent",
            "type":"Entertainment"
        }
    ],
    "sg:phone":"+1 760 723 8705",
    "sg:postcode":"92028",
    "sg:province":"CA",
    "sg:tags":[
        "agency"
    ],
    "wof:name":"New Odyssey Travel LLC",
    "wof:placetype":"venue"
},
  "geometry": {"coordinates":[-117.247105,33.371374],"type":"Point"}
}