{
  "type": "Feature",
  "properties": {
    "addr:full":"5001 El Segundo Blvd Hawthorne CA 90250",
    "addr:housenumber":"5001",
    "addr:postcode":"90250",
    "addr:street":"El Segundo Blvd",
    "iso:country":"US",
    "sg:address":"5001 El Segundo Blvd",
    "sg:city":"Hawthorne",
    "sg:classifiers":[
        {
            "category":"Sports & Exercise",
            "subcategory":"Gym",
            "type":"Entertainment"
        }
    ],
    "sg:phone":"+1 310 263 7520",
    "sg:postcode":"90250",
    "sg:province":"CA",
    "sg:tags":[
        "trainer"
    ],
    "sg:website":"www.ballyfitness.com",
    "wof:name":"Bally Total Fitness",
    "wof:placetype":"venue"
},
  "geometry": {"coordinates":[-118.36695400000001,33.916819],"type":"Point"}
}