{
  "type": "Feature",
  "properties": {
    "iso:country":"US",
    "sg:address":"1525 U St",
    "sg:city":"Sacramento",
    "sg:classifiers":[
        {
            "category":"Professional",
            "subcategory":"Computer Services",
            "type":"Services"
        }
    ],
    "sg:phone":"+1 916 440 8046",
    "sg:postcode":"95818",
    "sg:province":"CA",
    "sg:tags":[
        "graphics"
    ],
    "wof:name":"Color Craft Precision Drum",
    "wof:placetype":"venue"
},
  "geometry": {"coordinates":[-121.490692,38.566158],"type":"Point"}
}