{
  "type": "Feature",
  "properties": {
    "addr:full":"424 S Main St Suite 0 Orange CA 92868",
    "addr:housenumber":"424",
    "addr:postcode":"92868",
    "addr:street":"S Main St Suite 0",
    "iso:country":"US",
    "sg:address":"424 S Main St Suite 0",
    "sg:city":"Orange",
    "sg:classifiers":[
        {
            "category":"Personal",
            "subcategory":"Beauty Salon",
            "type":"Services"
        },
        {
            "category":"Personal",
            "subcategory":"Hair Removal",
            "type":"Services"
        }
    ],
    "sg:phone":"+1 714 704 0025",
    "sg:postcode":"92868",
    "sg:province":"CA",
    "sg:website":"www.facebook.com/pages/Orange-CA...",
    "wof:name":"C Salon",
    "wof:placetype":"venue"
},
  "geometry": {"coordinates":[-117.86742099999999,33.781941],"type":"Point"}
}