{
  "type": "Feature",
  "properties": {
    "iso:country":"US",
    "sg:address":"385 N Coast Hwy",
    "sg:city":"Laguna Beach",
    "sg:classifiers":[
        {
            "category":"Health Services",
            "subcategory":"Doctor",
            "type":"Services"
        }
    ],
    "sg:phone":"+1 949 494 7115",
    "sg:postcode":"92651",
    "sg:province":"CA",
    "sg:tags":[
        "dentist"
    ],
    "wof:name":"Martin P Kruger DDS",
    "wof:placetype":"venue"
},
  "geometry": {"coordinates":[-117.78868,33.543897],"type":"Point"}
}