{
  "type": "Feature",
  "properties": {
    "addr:full":"3717 Torrey View Ct San Diego CA 92130",
    "addr:housenumber":"3717",
    "addr:postcode":"92130",
    "addr:street":"Torrey View Ct",
    "iso:country":"US",
    "sg:address":"3717 Torrey View Ct",
    "sg:city":"San Diego",
    "sg:classifiers":[
        {
            "category":"Manufacturing",
            "subcategory":"Tools & Machinery",
            "type":"Manufacturing & Wholesale Goods"
        }
    ],
    "sg:phone":"+1 619 778 7540",
    "sg:postcode":"92130",
    "sg:province":"CA",
    "sg:tags":[
        "control",
        "remote",
        "for",
        "mfg",
        "electronics",
        "consumer"
    ],
    "wof:name":"Kyung In America Inc",
    "wof:placetype":"venue"
},
  "geometry": {"coordinates":[-117.233299,32.919812],"type":"Point"}
}