{
  "type": "Feature",
  "properties": {
    "addr:full":"29720 Rancho California Rd Temecula CA 92591",
    "addr:housenumber":"29720",
    "addr:postcode":"92591",
    "addr:street":"Rancho California Rd",
    "iso:country":"US",
    "sg:address":"29720 Rancho California Rd",
    "sg:city":"Temecula",
    "sg:classifiers":[
        {
            "category":"Home & Garden",
            "subcategory":"Home Furnishings",
            "type":"Retail Goods"
        }
    ],
    "sg:phone":"+1 951 506 3010",
    "sg:postcode":"92591",
    "sg:province":"CA",
    "sg:tags":[
        "lighting",
        "fixture"
    ],
    "wof:name":"Gallery Light",
    "wof:placetype":"venue"
},
  "geometry": {"coordinates":[-117.143278,33.506394],"type":"Point"}
}