{
  "type": "Feature",
  "properties": {
    "addr:full":"907 Sir Francis Drake Blvd #216 Kentfield CA 94904",
    "addr:housenumber":"907",
    "addr:postcode":"94904",
    "addr:street":"Sir Francis Drake Blvd # 216",
    "iso:country":"US",
    "sg:address":"907 Sir Francis Drake Blvd #216",
    "sg:city":"Kentfield",
    "sg:classifiers":[
        {
            "category":"Real Estate",
            "subcategory":"Real Estate Services",
            "type":"Services"
        },
        {
            "category":"Real Estate",
            "subcategory":"Real Estate Agent",
            "type":"Services"
        }
    ],
    "sg:phone":"+1 415 447 2061",
    "sg:postcode":"94904",
    "sg:province":"CA",
    "sg:tags":[
        "apartment",
        "management",
        "rental",
        "finder"
    ],
    "wof:name":"AMSI",
    "wof:placetype":"venue"
},
  "geometry": {"coordinates":[-122.54498,37.953746],"type":"Point"}
}