{
  "type": "Feature",
  "properties": {
    "iso:country":"US",
    "sg:address":"1642 N Vista St",
    "sg:city":"Los Angeles",
    "sg:classifiers":[
        {
            "category":"Wholesale",
            "subcategory":"Durable Goods & Equipment",
            "type":"Manufacturing & Wholesale Goods"
        }
    ],
    "sg:phone":"+1 323 876 0946",
    "sg:postcode":"90046",
    "sg:province":"CA",
    "wof:name":"West Coast Broom Supply Co",
    "wof:placetype":"venue"
},
  "geometry": {"coordinates":[-118.351797,34.101395],"type":"Point"}
}