{
  "type": "Feature",
  "properties": {
    "addr:full":"15545 Bellflower Blvd Bellflower CA 90706",
    "addr:housenumber":"15545",
    "addr:postcode":"90706",
    "addr:street":"Bellflower Blvd",
    "iso:country":"US",
    "sg:address":"15545 Bellflower Blvd",
    "sg:city":"Bellflower",
    "sg:classifiers":[
        {
            "category":"Banks & Credit Unions",
            "subcategory":"Financial Services",
            "type":"Services"
        }
    ],
    "sg:phone":"+1 562 461 2012",
    "sg:postcode":"90706",
    "sg:province":"CA",
    "sg:tags":[
        "broker",
        "mortgage"
    ],
    "wof:name":"Excelsis",
    "wof:placetype":"venue"
},
  "geometry": {"coordinates":[-118.125445,33.891346],"type":"Point"}
}