{
  "type": "Feature",
  "properties": {
    "addr:full":"816 S Main St Santa Ana CA 92701",
    "addr:housenumber":"816",
    "addr:postcode":"92701",
    "addr:street":"S Main St",
    "iso:country":"US",
    "sg:address":"816 S Main St",
    "sg:city":"Santa Ana",
    "sg:classifiers":[
        {
            "category":"Shopping",
            "subcategory":"Bridal",
            "type":"Retail Goods"
        }
    ],
    "sg:phone":"+1 714 542 5533",
    "sg:postcode":"92701",
    "sg:province":"CA",
    "wof:name":"Romantic Bridal",
    "wof:placetype":"venue"
},
  "geometry": {"coordinates":[-117.86799600000001,33.7374],"type":"Point"}
}