{
  "type": "Feature",
  "properties": {
    "addr:full":"4772 Candleberry Ave Seal Beach CA 90740",
    "addr:housenumber":"4772",
    "addr:postcode":"90740",
    "addr:street":"Candleberry Ave",
    "iso:country":"US",
    "sg:address":"4772 Candleberry Ave",
    "sg:city":"Seal Beach",
    "sg:classifiers":[
        {
            "category":"Home & Garden",
            "subcategory":"Home Furnishings",
            "type":"Retail Goods"
        }
    ],
    "sg:phone":"+1 562 598 3213",
    "sg:postcode":"90740",
    "sg:province":"CA",
    "wof:name":"Harry Bernard Draperies",
    "wof:placetype":"venue"
},
  "geometry": {"coordinates":[-118.047146,33.776643],"type":"Point"}
}