{
  "type": "Feature",
  "properties": {
    "addr:full":"710 Dolliver St Pismo Beach CA 93449",
    "addr:housenumber":"710",
    "addr:postcode":"93449",
    "addr:street":"Dolliver St",
    "iso:country":"US",
    "sg:address":"710 Dolliver St",
    "sg:city":"Pismo Beach",
    "sg:classifiers":[
        {
            "category":"Wholesale",
            "subcategory":"Fruits & Vegetables",
            "type":"Manufacturing & Wholesale Goods"
        }
    ],
    "sg:phone":"+1 805 773 1799",
    "sg:postcode":"93449",
    "sg:province":"CA",
    "wof:name":"G W Palmer & Co Inc",
    "wof:placetype":"venue"
},
  "geometry": {"coordinates":[-120.64196699999999,35.141253],"type":"Point"}
}