{
  "type": "Feature",
  "properties": {
    "iso:country":"US",
    "sg:address":"1211 Carlsbad St",
    "sg:city":"Spring Valley",
    "sg:classifiers":[
        {
            "category":"Insurance",
            "subcategory":"Hazard Insurance",
            "type":"Services"
        }
    ],
    "sg:phone":"+1 619 465 9360",
    "sg:postcode":"91977",
    "sg:province":"CA",
    "sg:tags":[
        "carrier"
    ],
    "wof:name":"Firemans Fund",
    "wof:placetype":"venue"
},
  "geometry": {"coordinates":[-117.022476,32.716736],"type":"Point"}
}