{
  "type": "Feature",
  "properties": {
    "addr:full":"2422 Belmont Ave Long Beach CA 90815",
    "addr:housenumber":"2422",
    "addr:postcode":"90815",
    "addr:street":"Belmont Ave",
    "iso:country":"US",
    "sg:address":"2422 Belmont Ave",
    "sg:city":"Long Beach",
    "sg:classifiers":[
        {
            "category":"Shopping",
            "subcategory":"Gifts & Souvenirs",
            "type":"Retail Goods"
        }
    ],
    "sg:phone":"+1 562 426 7167",
    "sg:postcode":"90815",
    "sg:province":"CA",
    "wof:name":"La Tienda",
    "wof:placetype":"venue"
},
  "geometry": {"coordinates":[-118.144284,33.80069],"type":"Point"}
}