{
  "type": "Feature",
  "properties": {
    "addr:full":"4045 Peachy Canyon Rd Paso Robles CA 93446",
    "addr:housenumber":"4045",
    "addr:postcode":"93446",
    "addr:street":"Peachy Canyon Rd",
    "iso:country":"US",
    "sg:address":"4045 Peachy Canyon Rd",
    "sg:city":"Paso Robles",
    "sg:classifiers":[
        {
            "category":"Wholesale",
            "subcategory":"Machinery & Supplies",
            "type":"Manufacturing & Wholesale Goods"
        }
    ],
    "sg:phone":"+1 805 238 7571",
    "sg:postcode":"93446",
    "sg:province":"CA",
    "sg:tags":[
        "vineyard",
        "product"
    ],
    "wof:name":"Minassian Young Vineyard",
    "wof:placetype":"venue"
},
  "geometry": {"coordinates":[-120.77395799999999,35.625972],"type":"Point"}
}