{
  "type": "Feature",
  "properties": {
    "addr:full":"1107 S Mission Rd Fallbrook CA 92028",
    "addr:housenumber":"1107",
    "addr:postcode":"92028",
    "addr:street":"S Mission Rd",
    "iso:country":"US",
    "sg:address":"1107 S Mission Rd",
    "sg:city":"Fallbrook",
    "sg:classifiers":[
        {
            "category":"Shopping",
            "subcategory":"Jewelry",
            "type":"Retail Goods"
        }
    ],
    "sg:phone":"+1 760 723 1234",
    "sg:postcode":"92028",
    "sg:province":"CA",
    "sg:tags":[
        "jeweler"
    ],
    "wof:name":"Hallman's Family Jewelers",
    "wof:placetype":"venue"
},
  "geometry": {"coordinates":[-117.25248999999999,33.371265],"type":"Point"}
}