{
  "type": "Feature",
  "properties": {
    "iso:country":"US",
    "sg:address":"956 J St",
    "sg:city":"Crescent City",
    "sg:classifiers":[
        {
            "category":"Local Transit",
            "type":"Transportation"
        }
    ],
    "sg:phone":"+1 707 464 9551",
    "sg:postcode":"95531",
    "sg:province":"CA",
    "sg:tags":[
        "ambulance"
    ],
    "wof:name":"Ambulance",
    "wof:placetype":"venue"
},
  "geometry": {"coordinates":[-124.200317,41.757391],"type":"Point"}
}