{
  "type": "Feature",
  "properties": {
    "iso:country":"US",
    "sg:address":"73325 Highway 111",
    "sg:city":"Palm Desert",
    "sg:classifiers":[
        {
            "category":"Restaurant",
            "type":"Food & Drink"
        }
    ],
    "sg:phone":"+1 760 836 9028",
    "sg:postcode":"92260",
    "sg:province":"CA",
    "sg:tags":[
        "mexican"
    ],
    "sg:website":"www.serenatagrill.com",
    "wof:name":"Serenata Mexican Bar and Grill",
    "wof:placetype":"venue"
},
  "geometry": {"coordinates":[-116.385485,33.721022],"type":"Point"}
}