{
  "type": "Feature",
  "properties": {
    "addr:full":"44221 Surfwood Dr Mendocino CA 95460",
    "addr:postcode":"44221;95460",
    "addr:street":"Surfwood Dr",
    "iso:country":"US",
    "sg:address":"44221 Surfwood Dr",
    "sg:city":"Mendocino",
    "sg:classifiers":[
        {
            "category":"Professional",
            "subcategory":"Engineering",
            "type":"Services"
        }
    ],
    "sg:phone":"+1 707 937 2042",
    "sg:postcode":"95460",
    "sg:province":"CA",
    "sg:tags":[
        "engineer"
    ],
    "wof:name":"Rappaport & Assoc",
    "wof:placetype":"venue"
},
  "geometry": {"coordinates":[-123.79300000000001,39.326376],"type":"Point"}
}