{
  "type": "Feature",
  "properties": {
    "iso:country":"US",
    "sg:address":"2950 State St",
    "sg:city":"Santa Barbara",
    "sg:classifiers":[
        {
            "category":"Professional",
            "subcategory":"Computer Services",
            "type":"Services"
        }
    ],
    "sg:phone":"+1 805 687 3515",
    "sg:postcode":"93105",
    "sg:province":"CA",
    "sg:tags":[
        "website",
        "design"
    ],
    "wof:name":"New Media Studio",
    "wof:placetype":"venue"
},
  "geometry": {"coordinates":[-119.725458,34.439003],"type":"Point"}
}