{
  "type": "Feature",
  "properties": {
    "iso:country":"US",
    "sg:address":"2001 Union Street",
    "sg:city":"San Francisco",
    "sg:classifiers":[
        {
            "category":"Health Services",
            "subcategory":"Optometrist",
            "type":"Services"
        }
    ],
    "sg:phone":"+1 415 563 3900",
    "sg:postcode":"94123",
    "sg:province":"CA",
    "sg:tags":[
        "ophthalmologist"
    ],
    "wof:name":"Jerrold C Bocci MD Facs",
    "wof:placetype":"venue"
},
  "geometry": {"coordinates":[-122.432486,37.797184],"type":"Point"}
}