{
  "type": "Feature",
  "properties": {
    "addr:full":"1354 Broadway El Cajon CA 92021",
    "addr:housenumber":"1354",
    "addr:postcode":"92021",
    "addr:street":"Broadway",
    "iso:country":"US",
    "sg:address":"1354 Broadway",
    "sg:city":"El Cajon",
    "sg:classifiers":[
        {
            "category":"Building & Trades",
            "subcategory":"Construction",
            "type":"Services"
        }
    ],
    "sg:phone":"+1 619 444 4874",
    "sg:postcode":"92021",
    "sg:province":"CA",
    "sg:tags":[
        "roofing",
        "contractor"
    ],
    "wof:name":"El Cajon Roofing Inc",
    "wof:placetype":"venue"
},
  "geometry": {"coordinates":[-116.931473,32.80778],"type":"Point"}
}