{
  "type": "Feature",
  "properties": {
    "addr:full":"13269 Altaridge Cir Victorville CA 92392",
    "addr:housenumber":"13269",
    "addr:postcode":"92392",
    "addr:street":"Altaridge Cir",
    "iso:country":"US",
    "sg:address":"13269 Altaridge Cir",
    "sg:city":"Victorville",
    "sg:classifiers":[
        {
            "category":"Professional",
            "type":"Services"
        }
    ],
    "sg:phone":"+1 760 951 7963",
    "sg:postcode":"92392",
    "sg:province":"CA",
    "wof:name":"Exceptional Youth Foundation",
    "wof:placetype":"venue"
},
  "geometry": {"coordinates":[-117.373739,34.476957],"type":"Point"}
}