{
  "type": "Feature",
  "properties": {
    "iso:country":"US",
    "sg:address":"100 Hermosa Ave",
    "sg:city":"Long Beach",
    "sg:classifiers":[
        {
            "category":"Organizations",
            "subcategory":"Professional Association",
            "type":"Services"
        }
    ],
    "sg:phone":"+1 562 436 5195",
    "sg:postcode":"90802",
    "sg:province":"CA",
    "wof:name":"100 Hermosa Assn",
    "wof:placetype":"venue"
},
  "geometry": {"coordinates":[-118.169786,33.766914],"type":"Point"}
}