{
  "type": "Feature",
  "properties": {
    "iso:country":"US",
    "sg:address":"79607 Country Club Dr",
    "sg:city":"Bermuda Dunes",
    "sg:classifiers":[
        {
            "category":"Building & Trades",
            "subcategory":"Construction",
            "type":"Services"
        }
    ],
    "sg:phone":"+1 760 200 3605",
    "sg:postcode":"92203",
    "sg:province":"CA",
    "sg:tags":[
        "dry wall",
        "contractor"
    ],
    "wof:name":"Arrowhead Drywall",
    "wof:placetype":"venue"
},
  "geometry": {"coordinates":[-116.28048200000001,33.752276],"type":"Point"}
}