{
  "type": "Feature",
  "properties": {
    "iso:country":"US",
    "sg:address":"3408 Hillview Avenue Suite 150",
    "sg:city":"Palo Alto",
    "sg:classifiers":[
        {
            "category":"Professional",
            "subcategory":"Computer Services",
            "type":"Services"
        }
    ],
    "sg:phone":"+1 650 493 6010",
    "sg:postcode":"94304",
    "sg:province":"CA",
    "wof:name":"netZentry",
    "wof:placetype":"venue"
},
  "geometry": {"coordinates":[-122.145346,37.401298],"type":"Point"}
}