{
  "type": "Feature",
  "properties": {
    "iso:country":"US",
    "sg:address":"108 Green Valley Rd Ste A",
    "sg:city":"Freedom",
    "sg:classifiers":[
        {
            "category":"Wholesale",
            "subcategory":"Medical Equipment & Supplies",
            "type":"Manufacturing & Wholesale Goods"
        }
    ],
    "sg:phone":"+1 831 724 9449",
    "sg:postcode":"95019",
    "sg:province":"CA",
    "sg:tags":[
        "assistive",
        "aid",
        "device",
        "hearing"
    ],
    "sg:website":"http://www.physicianshearing.org",
    "wof:name":"Physician's Hearing Aid Ctr Inc.",
    "wof:placetype":"venue"
},
  "geometry": {"coordinates":[-121.77238199999999,36.936263],"type":"Point"}
}