{
  "type": "Feature",
  "properties": {
    "addr:full":"239 Utah Ave S San Francisco CA 94080",
    "addr:housenumber":"239",
    "addr:postcode":"94080",
    "addr:street":"Utah Ave S",
    "iso:country":"US",
    "sg:address":"239 Utah Ave",
    "sg:city":"S San Francisco",
    "sg:classifiers":[
        {
            "category":"Shopping",
            "subcategory":"Gifts & Souvenirs",
            "type":"Retail Goods"
        }
    ],
    "sg:phone":"+1 650 244 4970",
    "sg:postcode":"94080",
    "sg:province":"CA",
    "sg:tags":[
        "shop"
    ],
    "wof:name":"Clay Art Studio",
    "wof:placetype":"venue"
},
  "geometry": {"coordinates":[-122.397205,37.647258],"type":"Point"}
}