{
  "type": "Feature",
  "properties": {
    "iso:country":"US",
    "sg:address":"4370 Jutland Dr",
    "sg:city":"San Diego",
    "sg:classifiers":[
        {
            "category":"Manufacturing",
            "subcategory":"Rubber & Plastics",
            "type":"Manufacturing & Wholesale Goods"
        }
    ],
    "sg:phone":"+1 858 273 1212",
    "sg:postcode":"92117",
    "sg:province":"CA",
    "sg:tags":[
        "mfg",
        "gd",
        "g",
        "mechanical"
    ],
    "sg:website":"www.accurateelastomer.com",
    "wof:name":"Accurate Elastomer Products",
    "wof:placetype":"venue"
},
  "geometry": {"coordinates":[-117.228359,32.823975],"type":"Point"}
}