{
  "type": "Feature",
  "properties": {
    "addr:full":"5608 San Vicente Boulevard Los Angeles CA 90019",
    "addr:housenumber":"5608",
    "addr:postcode":"90019",
    "addr:street":"San Vicente Boulevard",
    "iso:country":"US",
    "sg:address":"5608 San Vicente Boulevard",
    "sg:city":"Los Angeles",
    "sg:classifiers":[
        {
            "category":"Retail",
            "subcategory":"Laundry & Dry Cleaning",
            "type":"Services"
        }
    ],
    "sg:phone":"+1 323 937 8628",
    "sg:postcode":"90019",
    "sg:province":"CA",
    "wof:name":"Crown Cleaners & Laundry",
    "wof:placetype":"venue"
},
  "geometry": {"coordinates":[-118.355177,34.054187],"type":"Point"}
}