{
  "type": "Feature",
  "properties": {
    "addr:full":"11701 Old River Rd Bakersfield CA 93311",
    "addr:housenumber":"11701",
    "addr:postcode":"93311",
    "addr:street":"Old River Rd",
    "iso:country":"US",
    "sg:address":"11701 Old River Rd",
    "sg:city":"Bakersfield",
    "sg:classifiers":[
        {
            "category":"Farming",
            "subcategory":"Dairy Farm",
            "type":"Manufacturing & Wholesale Goods"
        }
    ],
    "sg:phone":"+1 661 832 3901",
    "sg:postcode":"93311",
    "sg:province":"CA",
    "wof:name":"Wilgenburg Dairy Farm",
    "wof:placetype":"venue"
},
  "geometry": {"coordinates":[-119.109798,35.260394],"type":"Point"}
}