{
  "type": "Feature",
  "properties": {
    "addr:full":"752 Northport Dr West Sacramento CA 95691",
    "addr:housenumber":"752",
    "addr:postcode":"95691",
    "addr:street":"Northport Dr",
    "iso:country":"US",
    "sg:address":"752 Northport Dr",
    "sg:city":"West Sacramento",
    "sg:classifiers":[
        {
            "category":"Home & Garden",
            "subcategory":"Household Appliances",
            "type":"Retail Goods"
        }
    ],
    "sg:phone":"+1 916 371 2021",
    "sg:postcode":"95691",
    "sg:province":"CA",
    "sg:tags":[
        "cleaners",
        "vacuum"
    ],
    "wof:name":"G O Distributing",
    "wof:placetype":"venue"
},
  "geometry": {"coordinates":[-121.562408,38.580274],"type":"Point"}
}