{
  "type": "Feature",
  "properties": {
    "addr:full":"2106 San Miguel Canyon Rd Salinas CA 93907",
    "addr:housenumber":"2106",
    "addr:postcode":"93907",
    "addr:street":"San Miguel Canyon Rd",
    "iso:country":"US",
    "sg:address":"2106 San Miguel Canyon Rd",
    "sg:city":"Salinas",
    "sg:classifiers":[
        {
            "category":"Professional",
            "subcategory":"Art Services",
            "type":"Services"
        }
    ],
    "sg:phone":"+1 831 240 3478",
    "sg:postcode":"93907",
    "sg:province":"CA",
    "sg:tags":[
        "interior",
        "designer",
        "decorator"
    ],
    "wof:name":"Berkheimer Custom Painting And Decorating",
    "wof:placetype":"venue"
},
  "geometry": {"coordinates":[-121.67359999999999,36.811296],"type":"Point"}
}