{
  "type": "Feature",
  "properties": {
    "iso:country":"US",
    "sg:address":"1100 Draper St",
    "sg:city":"Kingsburg",
    "sg:classifiers":[
        {
            "category":"Organizations",
            "subcategory":"Religious Organization",
            "type":"Services"
        }
    ],
    "sg:phone":"+1 559 897 5165",
    "sg:postcode":"93631",
    "sg:province":"CA",
    "sg:tags":[
        "church"
    ],
    "wof:name":"Calvary Chapel Kingsburg",
    "wof:placetype":"venue"
},
  "geometry": {"coordinates":[-119.555713,36.512747],"type":"Point"}
}