{
  "type": "Feature",
  "properties": {
    "addr:full":"205 W Mission Ave Escondido CA 92025",
    "addr:housenumber":"205",
    "addr:postcode":"92025",
    "addr:street":"W Mission Ave",
    "iso:country":"US",
    "sg:address":"205 W Mission Ave",
    "sg:city":"Escondido",
    "sg:classifiers":[
        {
            "category":"Wholesale",
            "subcategory":"Machinery & Supplies",
            "type":"Manufacturing & Wholesale Goods"
        }
    ],
    "sg:phone":"+1 760 745 1804",
    "sg:postcode":"92025",
    "sg:province":"CA",
    "sg:tags":[
        "salon",
        "beauty"
    ],
    "wof:name":"Armstrong Mc Call Beauty Supl",
    "wof:placetype":"venue"
},
  "geometry": {"coordinates":[-117.087459,33.129687],"type":"Point"}
}