{
  "type": "Feature",
  "properties": {
    "iso:country":"US",
    "sg:address":"8352 Minuet Pl",
    "sg:city":"Panorama City",
    "sg:classifiers":[
        {
            "category":"Freight",
            "type":"Transportation"
        }
    ],
    "sg:phone":"+1 818 894 1939",
    "sg:postcode":"91402",
    "sg:province":"CA",
    "sg:tags":[
        "operator",
        "local",
        "trucking"
    ],
    "wof:name":"Quality Trucking",
    "wof:placetype":"venue"
},
  "geometry": {"coordinates":[-118.43350599999999,34.22586],"type":"Point"}
}