{
  "type": "Feature",
  "properties": {
    "addr:full":"2072 Rigoletto Dr San Jose CA 95122",
    "addr:postcode":"2072;95122",
    "addr:street":"Rigoletto Dr",
    "iso:country":"US",
    "sg:address":"2072 Rigoletto Dr",
    "sg:city":"San Jose",
    "sg:classifiers":[
        {
            "category":"Communications",
            "type":"Services"
        }
    ],
    "sg:phone":"+1 408 238 2456",
    "sg:postcode":"95122",
    "sg:province":"CA",
    "wof:name":"Global Communications & Eqpt",
    "wof:placetype":"venue"
},
  "geometry": {"coordinates":[-121.816137,37.322292],"type":"Point"}
}