{
  "type": "Feature",
  "properties": {
    "iso:country":"US",
    "sg:address":"8020 Vera Ave",
    "sg:city":"Bakersfield",
    "sg:classifiers":[
        {
            "category":"Building & Trades",
            "subcategory":"Landscaping Services",
            "type":"Services"
        }
    ],
    "sg:phone":"+1 661 364 0143",
    "sg:postcode":"93307",
    "sg:province":"CA",
    "sg:tags":[
        "tree"
    ],
    "wof:name":"Lorenzo Garcia's Tree Trim",
    "wof:placetype":"venue"
},
  "geometry": {"coordinates":[-118.917181,35.338657],"type":"Point"}
}