{
  "type": "Feature",
  "properties": {
    "iso:country":"US",
    "sg:address":"1380 Lead Hill Blvd",
    "sg:city":"Roseville",
    "sg:classifiers":[
        {
            "category":"Real Estate",
            "subcategory":"Surveying",
            "type":"Services"
        }
    ],
    "sg:phone":"+1 916 454 2990",
    "sg:postcode":"95678",
    "sg:province":"CA",
    "sg:tags":[
        "surveyor"
    ],
    "wof:name":"Towill Inc",
    "wof:placetype":"venue"
},
  "geometry": {"coordinates":[-121.253571,38.748212],"type":"Point"}
}