{
  "type": "Feature",
  "properties": {
    "iso:country":"US",
    "sg:address":"4309 Marconi Ave",
    "sg:city":"Sacramento",
    "sg:classifiers":[
        {
            "category":"Home & Garden",
            "subcategory":"Carpets & Floor Coverings",
            "type":"Retail Goods"
        }
    ],
    "sg:phone":"+1 916 485 0893",
    "sg:postcode":"95821",
    "sg:province":"CA",
    "sg:tags":[
        "installation"
    ],
    "wof:name":"Floorcraft",
    "wof:placetype":"venue"
},
  "geometry": {"coordinates":[-121.363756,38.617644],"type":"Point"}
}