{
  "type": "Feature",
  "properties": {
    "iso:country":"US",
    "sg:address":"3795 Ardilla Rd",
    "sg:city":"Atascadero",
    "sg:classifiers":[
        {
            "category":"Retail",
            "subcategory":"Repair Shop",
            "type":"Services"
        }
    ],
    "sg:phone":"+1 805 462 1141",
    "sg:postcode":"93422",
    "sg:province":"CA",
    "sg:tags":[
        "lock",
        "locksmith"
    ],
    "wof:name":"Atascadero Locksmith Shop",
    "wof:placetype":"venue"
},
  "geometry": {"coordinates":[-120.68785,35.490626],"type":"Point"}
}