{
  "type": "Feature",
  "properties": {
    "iso:country":"US",
    "sg:address":"301 E Hendy Ave",
    "sg:city":"La Honda",
    "sg:classifiers":[
        {
            "category":"Professional",
            "subcategory":"Testing Lab",
            "type":"Services"
        }
    ],
    "sg:phone":"+1 650 747 0334",
    "sg:postcode":"94086",
    "sg:province":"CA",
    "sg:tags":[
        "x",
        "inspection"
    ],
    "wof:name":"William A Johnson Consulting",
    "wof:placetype":"venue"
},
  "geometry": {"coordinates":[-122.02678899999999,37.377631],"type":"Point"}
}