{
  "type": "Feature",
  "properties": {
    "addr:full":"22693 Hesperian Blvd Hayward CA 94541",
    "addr:housenumber":"22693",
    "addr:postcode":"94541",
    "addr:street":"Hesperian Blvd",
    "iso:country":"US",
    "sg:address":"22693 Hesperian Blvd",
    "sg:city":"Hayward",
    "sg:classifiers":[
        {
            "category":"Health Services",
            "subcategory":"Clinic",
            "type":"Services"
        }
    ],
    "sg:phone":"+1 510 259 1962",
    "sg:postcode":"94541",
    "sg:province":"CA",
    "sg:tags":[
        "home"
    ],
    "wof:name":"Addus Healthcare",
    "wof:placetype":"venue"
},
  "geometry": {"coordinates":[-122.11277800000001,37.656717],"type":"Point"}
}