{
  "type": "Feature",
  "properties": {
    "addr:full":"3500 N Sepulveda Blvd Ste E Manhattan Beach CA 90266",
    "addr:housenumber":"3500",
    "addr:postcode":"90266",
    "addr:street":"N Sepulveda Blvd Ste E",
    "iso:country":"US",
    "sg:address":"3500 N Sepulveda Blvd Ste E",
    "sg:city":"Manhattan Beach",
    "sg:classifiers":[
        {
            "category":"Banks & Credit Unions",
            "subcategory":"Financial Services",
            "type":"Services"
        }
    ],
    "sg:phone":"+1 310 796 5600",
    "sg:postcode":"90266",
    "sg:province":"CA",
    "sg:tags":[
        "broker",
        "mortgage"
    ],
    "wof:name":"Platinum Capital Group",
    "wof:placetype":"venue"
},
  "geometry": {"coordinates":[-118.395781,33.899891],"type":"Point"}
}