{
  "type": "Feature",
  "properties": {
    "iso:country":"US",
    "sg:address":"1551 W Redondo Beach Blvd",
    "sg:city":"Gardena",
    "sg:classifiers":[
        {
            "category":"Wholesale",
            "subcategory":"Non-durable Goods",
            "type":"Manufacturing & Wholesale Goods"
        }
    ],
    "sg:phone":"+1 310 768 3891",
    "sg:postcode":"90247",
    "sg:province":"CA",
    "sg:tags":[
        "advertising"
    ],
    "wof:name":"Premiums West Company",
    "wof:placetype":"venue"
},
  "geometry": {"coordinates":[-118.303459,33.890491],"type":"Point"}
}