{
  "type": "Feature",
  "properties": {
    "iso:country":"US",
    "sg:address":"19348 Columbine Ct",
    "sg:city":"Saratoga",
    "sg:classifiers":[
        {
            "category":"Professional",
            "subcategory":"Engineering",
            "type":"Services"
        }
    ],
    "sg:phone":"+1 408 446 9783",
    "sg:postcode":"95070",
    "sg:province":"CA",
    "sg:tags":[
        "engineer",
        "integration",
        "system"
    ],
    "sg:website":"http://www.data-time.com",
    "wof:name":"Data Time International",
    "wof:placetype":"venue"
},
  "geometry": {"coordinates":[-122.00901500000001,37.281511],"type":"Point"}
}