{
  "type": "Feature",
  "properties": {
    "iso:country":"US",
    "sg:address":"2002 3rd St",
    "sg:city":"Selma",
    "sg:classifiers":[
        {
            "category":"Autos & Motor Vehicles",
            "subcategory":"Auto Supplies",
            "type":"Retail Goods"
        }
    ],
    "sg:phone":"+1 559 891 8222",
    "sg:postcode":"93662",
    "sg:province":"CA",
    "sg:tags":[
        "automobile",
        "stereo",
        "radio"
    ],
    "wof:name":"American Audio",
    "wof:placetype":"venue"
},
  "geometry": {"coordinates":[-119.6097,36.566214],"type":"Point"}
}