{
  "type": "Feature",
  "properties": {
    "iso:country":"US",
    "sg:address":"370 W Line St",
    "sg:city":"Bishop",
    "sg:classifiers":[
        {
            "category":"Real Estate",
            "subcategory":"Real Estate Agent",
            "type":"Services"
        }
    ],
    "sg:phone":"+1 760 873 4264",
    "sg:postcode":"93514",
    "sg:province":"CA",
    "sg:tags":[
        "buyer",
        "broker"
    ],
    "sg:website":"http://www.coldwellbanker.com",
    "wof:name":"Coldwell Banker",
    "wof:placetype":"venue"
},
  "geometry": {"coordinates":[-118.397617,37.361392],"type":"Point"}
}