{
  "type": "Feature",
  "properties": {
    "addr:full":"203 5th St Eureka CA 95501",
    "addr:housenumber":"203",
    "addr:postcode":"95501",
    "addr:street":"5Th St",
    "iso:country":"US",
    "sg:address":"203 5th St",
    "sg:city":"Eureka",
    "sg:classifiers":[
        {
            "category":"Autos & Motor Vehicles",
            "subcategory":"Auto Supplies",
            "type":"Retail Goods"
        }
    ],
    "sg:phone":"+1 707 445 9447",
    "sg:postcode":"95501",
    "sg:province":"CA",
    "sg:tags":[
        "automobile",
        "stereo",
        "radio"
    ],
    "wof:name":"Humboldt Audio & Video",
    "wof:placetype":"venue"
},
  "geometry": {"coordinates":[-124.16811,40.80168],"type":"Point"}
}