{
  "type": "Feature",
  "properties": {
    "addr:full":"2723 Main St Santa Monica CA 90405",
    "addr:housenumber":"2723",
    "addr:postcode":"90405",
    "addr:street":"Main St",
    "iso:country":"US",
    "sg:address":"2723 Main St",
    "sg:city":"Santa Monica",
    "sg:classifiers":[
        {
            "category":"Shopping",
            "subcategory":"Gifts & Souvenirs",
            "type":"Retail Goods"
        }
    ],
    "sg:phone":"+1 310 452 9111",
    "sg:postcode":"90405",
    "sg:province":"CA",
    "sg:tags":[
        "shop"
    ],
    "wof:name":"Cal Image",
    "wof:placetype":"venue"
},
  "geometry": {"coordinates":[-118.481166,33.999738],"type":"Point"}
}