{
  "type": "Feature",
  "properties": {
    "iso:country":"US",
    "sg:address":"26111 Antonio Pkwy",
    "sg:city":"Rancho Santa Margarita",
    "sg:classifiers":[
        {
            "category":"Government",
            "subcategory":"Office",
            "type":"Public Place"
        }
    ],
    "sg:phone":"+1 949 459 6688",
    "sg:postcode":"92688",
    "sg:province":"CA",
    "sg:tags":[
        "management"
    ],
    "wof:name":"Permit Assistance Ctr-S Orange",
    "wof:placetype":"venue"
},
  "geometry": {"coordinates":[-117.631198,33.581221],"type":"Point"}
}