{
  "type": "Feature",
  "properties": {
    "addr:full":"3932 el Portal Dr Redding CA 96002",
    "addr:housenumber":"3932",
    "addr:postcode":"96002",
    "addr:street":"El Portal Dr",
    "iso:country":"US",
    "sg:address":"3932 el Portal Dr",
    "sg:city":"Redding",
    "sg:classifiers":[
        {
            "category":"Health Services",
            "subcategory":"Clinic",
            "type":"Services"
        }
    ],
    "sg:phone":"+1 530 222 5548",
    "sg:postcode":"96002",
    "sg:province":"CA",
    "sg:tags":[
        "home"
    ],
    "wof:name":"Jan's Place",
    "wof:placetype":"venue"
},
  "geometry": {"coordinates":[-122.355969,40.549748],"type":"Point"}
}