{
  "type": "Feature",
  "properties": {
    "addr:full":"145 N La Brea Avenue Los Angeles CA 90036",
    "addr:housenumber":"145",
    "addr:postcode":"90036",
    "addr:street":"N La Brea Avenue",
    "iso:country":"US",
    "sg:address":"145 N La Brea Avenue",
    "sg:city":"Los Angeles",
    "sg:classifiers":[
        {
            "category":"Arts & Performance",
            "subcategory":"Art Gallery",
            "type":"Entertainment"
        }
    ],
    "sg:phone":"+1 323 857 5588",
    "sg:postcode":"90036",
    "sg:province":"CA",
    "wof:name":"Silk Roads Design Gallery",
    "wof:placetype":"venue"
},
  "geometry": {"coordinates":[-118.344031,34.07471],"type":"Point"}
}