{
  "type": "Feature",
  "properties": {
    "addr:full":"2717 Cottage Way Sacramento CA 95825",
    "addr:housenumber":"2717",
    "addr:postcode":"95825",
    "addr:street":"Cottage Way",
    "iso:country":"US",
    "sg:address":"2717 Cottage Way",
    "sg:city":"Sacramento",
    "sg:classifiers":[
        {
            "category":"Travel",
            "subcategory":"Travel Agent",
            "type":"Entertainment"
        }
    ],
    "sg:phone":"+1 916 484 1447",
    "sg:postcode":"95825",
    "sg:province":"CA",
    "sg:tags":[
        "agency",
        "cruise"
    ],
    "wof:name":"Ariana Tours & Travels",
    "wof:placetype":"venue"
},
  "geometry": {"coordinates":[-121.397797,38.603445],"type":"Point"}
}