{
  "type": "Feature",
  "properties": {
    "addr:full":"1024 36th St Sacramento CA 95816",
    "addr:housenumber":"1024",
    "addr:postcode":"95816",
    "addr:street":"36Th St",
    "iso:country":"US",
    "sg:address":"1024 36th St",
    "sg:city":"Sacramento",
    "sg:classifiers":[
        {
            "category":"Social Services",
            "subcategory":"Job Training",
            "type":"Services"
        }
    ],
    "sg:phone":"+1 916 731 5960",
    "sg:postcode":"95816",
    "sg:province":"CA",
    "sg:tags":[
        "sale"
    ],
    "wof:name":"Chris Mitchell",
    "wof:placetype":"venue"
},
  "geometry": {"coordinates":[-121.458417,38.570647],"type":"Point"}
}