{
  "type": "Feature",
  "properties": {
    "iso:country":"US",
    "sg:address":"1600 W Maple Ave Apt 38",
    "sg:city":"Orange",
    "sg:classifiers":[
        {
            "category":"Health Services",
            "subcategory":"Nursing And Care Facility",
            "type":"Services"
        }
    ],
    "sg:phone":"+1 714 261 0021",
    "sg:postcode":"92868",
    "sg:province":"CA",
    "sg:tags":[
        "nurse"
    ],
    "wof:name":"Westways",
    "wof:placetype":"venue"
},
  "geometry": {"coordinates":[-117.86718,33.78968],"type":"Point"}
}