{
  "type": "Feature",
  "properties": {
    "addr:full":"607 S Los Angeles St Los Angeles CA 90014",
    "addr:housenumber":"607",
    "addr:postcode":"90014",
    "addr:street":"S Los Angeles St",
    "iso:country":"US",
    "sg:address":"607 S Los Angeles St",
    "sg:city":"Los Angeles",
    "sg:classifiers":[
        {
            "category":"Travel",
            "subcategory":"Travel Agent",
            "type":"Entertainment"
        }
    ],
    "sg:phone":"+1 213 892 8485",
    "sg:postcode":"90014",
    "sg:province":"CA",
    "sg:tags":[
        "operator",
        "tour"
    ],
    "wof:name":"Cal Mex Tours",
    "wof:placetype":"venue"
},
  "geometry": {"coordinates":[-118.25039700000001,34.043391],"type":"Point"}
}