{
  "type": "Feature",
  "properties": {
    "iso:country":"US",
    "sg:address":"250 W 3rd St",
    "sg:city":"Perris",
    "sg:classifiers":[
        {
            "category":"Education",
            "subcategory":"School",
            "type":"Public Place"
        }
    ],
    "sg:phone":"+1 951 657 5226",
    "sg:postcode":"92570",
    "sg:province":"CA",
    "wof:name":"St James School",
    "wof:placetype":"venue"
},
  "geometry": {"coordinates":[-117.231026,33.783484],"type":"Point"}
}