{
  "type": "Feature",
  "properties": {
    "addr:full":"1575 E 14th St San Leandro CA 94577",
    "addr:housenumber":"1575",
    "addr:postcode":"94577",
    "addr:street":"E 14Th St",
    "iso:country":"US",
    "sg:address":"1575 E 14th St",
    "sg:city":"San Leandro",
    "sg:classifiers":[
        {
            "category":"Health Services",
            "subcategory":"Optometrist",
            "type":"Services"
        }
    ],
    "sg:phone":"+1 510 483 4770",
    "sg:postcode":"94577",
    "sg:province":"CA",
    "wof:name":"Revelli Edward J OD",
    "wof:placetype":"venue"
},
  "geometry": {"coordinates":[-122.15300000000001,37.723202],"type":"Point"}
}