{
  "type": "Feature",
  "properties": {
    "addr:full":"2161 Shattuck Ave Berkeley CA 94704",
    "addr:housenumber":"2161",
    "addr:postcode":"94704",
    "addr:street":"Shattuck Ave",
    "iso:country":"US",
    "sg:address":"2161 Shattuck Ave",
    "sg:city":"Berkeley",
    "sg:classifiers":[
        {
            "category":"Professional",
            "subcategory":"Secretarial Services",
            "type":"Services"
        }
    ],
    "sg:phone":"+1 510 486 0700",
    "sg:postcode":"94704",
    "sg:province":"CA",
    "sg:tags":[
        "convention",
        "court",
        "reporter"
    ],
    "sg:website":"www.clarkdepos.com",
    "wof:name":"Clark Reporting",
    "wof:placetype":"venue"
},
  "geometry": {"coordinates":[-122.267962,37.86948],"type":"Point"}
}