{
  "type": "Feature",
  "properties": {
    "addr:full":"501 E Redlands Blvd Redlands CA 92373",
    "addr:housenumber":"501",
    "addr:postcode":"92373",
    "addr:street":"E Redlands Blvd",
    "iso:country":"US",
    "sg:address":"501 E Redlands Blvd",
    "sg:city":"Redlands",
    "sg:classifiers":[
        {
            "category":"Shopping",
            "subcategory":"Computers & Home Electronics",
            "type":"Retail Goods"
        }
    ],
    "sg:phone":"+1 909 335 2230",
    "sg:postcode":"92373",
    "sg:province":"CA",
    "sg:tags":[
        "equipment",
        "dealer"
    ],
    "wof:name":"Hubbard Computer Sales & Svc",
    "wof:placetype":"venue"
},
  "geometry": {"coordinates":[-117.176453,34.056411],"type":"Point"}
}