{
  "type": "Feature",
  "properties": {
    "addr:full":"1336 W Willow St Ste 104 Long Beach CA 90810",
    "addr:housenumber":"1336",
    "addr:postcode":"90810",
    "addr:street":"W Willow St Ste 104",
    "iso:country":"US",
    "sg:address":"1336 W Willow St Ste 104",
    "sg:city":"Long Beach",
    "sg:classifiers":[
        {
            "category":"Personal",
            "subcategory":"Beauty Salon",
            "type":"Services"
        },
        {
            "category":"Personal",
            "subcategory":"Nail Salon",
            "type":"Services"
        }
    ],
    "sg:phone":"+1 562 426 3776",
    "sg:postcode":"90810",
    "sg:province":"CA",
    "sg:tags":[
        "hair"
    ],
    "wof:name":"Famous Hair & Nail Salon",
    "wof:placetype":"venue"
},
  "geometry": {"coordinates":[-118.209999,33.804298],"type":"Point"}
}