{
  "type": "Feature",
  "properties": {
    "iso:country":"US",
    "sg:address":"11809 Slauson Ave",
    "sg:city":"Santa Fe Springs",
    "sg:classifiers":[
        {
            "category":"Manufacturing",
            "subcategory":"Metals",
            "type":"Manufacturing & Wholesale Goods"
        }
    ],
    "sg:phone":"+1 562 907 7686",
    "sg:postcode":"90670",
    "sg:province":"CA",
    "sg:tags":[
        "screw"
    ],
    "wof:name":"Graham Fasteners Inc",
    "wof:placetype":"venue"
},
  "geometry": {"coordinates":[-118.06141100000001,33.964137],"type":"Point"}
}