{
  "type": "Feature",
  "properties": {
    "iso:country":"US",
    "sg:address":"124 S Cloverdale Blvd",
    "sg:city":"Cloverdale",
    "sg:classifiers":[
        {
            "category":"Retail",
            "subcategory":"Repair Shop",
            "type":"Services"
        }
    ],
    "sg:phone":"+1 707 894 4987",
    "sg:postcode":"95425",
    "sg:province":"CA",
    "sg:tags":[
        "upholsterer"
    ],
    "wof:name":"Jonie's Upholstery",
    "wof:placetype":"venue"
},
  "geometry": {"coordinates":[-123.016829,38.804969],"type":"Point"}
}