{
  "type": "Feature",
  "properties": {
    "addr:full":"4000 Fruitridge Rd Sacramento CA 95820",
    "addr:housenumber":"4000",
    "addr:postcode":"95820",
    "addr:street":"Fruitridge Rd",
    "iso:country":"US",
    "sg:address":"4000 Fruitridge Rd",
    "sg:city":"Sacramento",
    "sg:classifiers":[
        {
            "category":"Recreation",
            "subcategory":"Amusement Park",
            "type":"Entertainment"
        },
        {
            "category":"Sports & Exercise",
            "subcategory":"Sports Center",
            "type":"Entertainment"
        },
        {
            "category":"Retail",
            "subcategory":"Event Space",
            "type":"Services"
        }
    ],
    "sg:phone":"+1 916 422 7610",
    "sg:postcode":"95820",
    "sg:province":"CA",
    "sg:tags":[
        "venue",
        "amateur",
        "team"
    ],
    "wof:name":"Southgate Recreation & Park District",
    "wof:placetype":"venue"
},
  "geometry": {"coordinates":[-121.459999,38.524799],"type":"Point"}
}