{
  "type": "Feature",
  "properties": {
    "addr:full":"641 S 15th St Richmond CA 94804",
    "addr:housenumber":"641",
    "addr:postcode":"94804",
    "addr:street":"S 15Th St",
    "iso:country":"US",
    "sg:address":"641 S 15th St",
    "sg:city":"Richmond",
    "sg:classifiers":[
        {
            "category":"Professional",
            "subcategory":"Management & Consulting",
            "type":"Services"
        }
    ],
    "sg:phone":"+1 510 234 1518",
    "sg:postcode":"94804",
    "sg:province":"CA",
    "sg:tags":[
        "communications",
        "consultant"
    ],
    "wof:name":"Coach Ken Carter Foundation",
    "wof:placetype":"venue"
},
  "geometry": {"coordinates":[-122.35486400000001,37.923148],"type":"Point"}
}