{
  "type": "Feature",
  "properties": {
    "iso:country":"US",
    "sg:address":"4221 Wilshire Blvd",
    "sg:city":"Los Angeles",
    "sg:classifiers":[
        {
            "category":"Professional",
            "subcategory":"Detective & Security Services",
            "type":"Services"
        }
    ],
    "sg:phone":"+1 323 931 0189",
    "sg:postcode":"90010",
    "sg:province":"CA",
    "sg:tags":[
        "guard",
        "patrol"
    ],
    "wof:name":"Mbs Security",
    "wof:placetype":"venue"
},
  "geometry": {"coordinates":[-118.31965,34.061813],"type":"Point"}
}