{
  "type": "Feature",
  "properties": {
    "iso:country":"US",
    "sg:address":"895 Napa Ave",
    "sg:city":"Morro Bay",
    "sg:classifiers":[
        {
            "category":"Social Services",
            "type":"Services"
        }
    ],
    "sg:phone":"+1 805 772 7151",
    "sg:postcode":"93442",
    "sg:province":"CA",
    "sg:tags":[
        "counselor",
        "marriage",
        "family"
    ],
    "wof:name":"Megan Mc Green",
    "wof:placetype":"venue"
},
  "geometry": {"coordinates":[-120.84777,35.366911],"type":"Point"}
}