{
  "type": "Feature",
  "properties": {
    "iso:country":"US",
    "sg:address":"808 River St",
    "sg:city":"Fillmore",
    "sg:classifiers":[
        {
            "category":"Organizations",
            "subcategory":"Religious Organization",
            "type":"Services"
        }
    ],
    "sg:phone":"+1 805 524 0246",
    "sg:postcode":"93015",
    "sg:province":"CA",
    "sg:tags":[
        "church"
    ],
    "wof:name":"Church Of Religious Science",
    "wof:placetype":"venue"
},
  "geometry": {"coordinates":[-118.920271,34.393901],"type":"Point"}
}