{
  "type": "Feature",
  "properties": {
    "iso:country":"US",
    "sg:address":"8135 Telegraph Rd",
    "sg:city":"Pico Rivera",
    "sg:classifiers":[
        {
            "category":"Retail",
            "subcategory":"Laundry & Dry Cleaning",
            "type":"Services"
        }
    ],
    "sg:phone":"+1 562 776 8580",
    "sg:postcode":"90660",
    "sg:province":"CA",
    "sg:tags":[
        "cleaners"
    ],
    "wof:name":"Top Cleaners",
    "wof:placetype":"venue"
},
  "geometry": {"coordinates":[-118.115781,33.967075],"type":"Point"}
}