{
  "type": "Feature",
  "properties": {
    "addr:full":"33 Almond Tree Ln Irvine CA 92612",
    "addr:housenumber":"33",
    "addr:postcode":"92612",
    "addr:street":"Almond Tree Ln",
    "iso:country":"US",
    "sg:address":"33 Almond Tree Ln",
    "sg:city":"Irvine",
    "sg:classifiers":[
        {
            "category":"Building & Trades",
            "subcategory":"Construction",
            "type":"Services"
        }
    ],
    "sg:phone":"+1 949 786 7440",
    "sg:postcode":"92612",
    "sg:province":"CA",
    "sg:tags":[
        "wallcoverings-installation",
        "wallpaper",
        "painting",
        "contractor"
    ],
    "wof:name":"New World Painting",
    "wof:placetype":"venue"
},
  "geometry": {"coordinates":[-117.81017199999999,33.664487],"type":"Point"}
}