{
  "type": "Feature",
  "properties": {
    "iso:country":"US",
    "sg:address":"23804 Lake Dr",
    "sg:city":"Crestline",
    "sg:classifiers":[
        {
            "category":"Retail",
            "subcategory":"Auto Repair",
            "type":"Services"
        },
        {
            "category":"Government",
            "subcategory":"Office",
            "type":"Public Place"
        }
    ],
    "sg:phone":"+1 909 967 0866",
    "sg:postcode":"92325",
    "sg:province":"CA",
    "sg:tags":[
        "smog",
        "check"
    ],
    "wof:name":"ALL SEASONS SMOG",
    "wof:placetype":"venue"
},
  "geometry": {"coordinates":[-117.28393199999999,34.243126],"type":"Point"}
}