{
  "type": "Feature",
  "properties": {
    "iso:country":"US",
    "sg:address":"33105 Santiago Rd Spc 74",
    "sg:city":"Acton",
    "sg:classifiers":[
        {
            "category":"Professional",
            "subcategory":"Lawyer & Legal Services",
            "type":"Services"
        }
    ],
    "sg:phone":"+1 661 269 8877",
    "sg:postcode":"93510",
    "sg:province":"CA",
    "sg:tags":[
        "trust",
        "living",
        "planning",
        "probate",
        "estate"
    ],
    "wof:name":"Tlc",
    "wof:placetype":"venue"
},
  "geometry": {"coordinates":[-118.164958,34.484322],"type":"Point"}
}