{
  "type": "Feature",
  "properties": {
    "addr:full":"1424 W 7th St Upland CA 91786",
    "addr:housenumber":"1424",
    "addr:postcode":"91786",
    "addr:street":"W 7Th St",
    "iso:country":"US",
    "sg:address":"1424 W 7th St",
    "sg:city":"Upland",
    "sg:classifiers":[
        {
            "category":"Personal",
            "subcategory":"Beauty Salon",
            "type":"Services"
        },
        {
            "category":"Personal",
            "subcategory":"Nail Salon",
            "type":"Services"
        }
    ],
    "sg:phone":"+1 909 949 0643",
    "sg:postcode":"91786",
    "sg:province":"CA",
    "wof:name":"Elegant Nail and Spa",
    "wof:placetype":"venue"
},
  "geometry": {"coordinates":[-117.675399,34.088749],"type":"Point"}
}