{
  "type": "Feature",
  "properties": {
    "iso:country":"US",
    "sg:address":"24065 Arthur Rd",
    "sg:city":"Escalon",
    "sg:classifiers":[
        {
            "category":"Farming",
            "subcategory":"Dairy Farm",
            "type":"Manufacturing & Wholesale Goods"
        }
    ],
    "sg:phone":"+1 209 838 1479",
    "sg:postcode":"95320",
    "sg:province":"CA",
    "wof:name":"James Bylsma Dairy",
    "wof:placetype":"venue"
},
  "geometry": {"coordinates":[-121.00103,37.805251],"type":"Point"}
}