{
  "type": "Feature",
  "properties": {
    "iso:country":"US",
    "sg:address":"674 County Square Dr",
    "sg:city":"Ventura",
    "sg:classifiers":[
        {
            "category":"Organizations",
            "subcategory":"Labor Organization",
            "type":"Services"
        }
    ],
    "sg:phone":"+1 805 644 4453",
    "sg:postcode":"93003",
    "sg:province":"CA",
    "wof:name":"Communications Workers-America",
    "wof:placetype":"venue"
},
  "geometry": {"coordinates":[-119.215096,34.268932],"type":"Point"}
}