{
  "type": "Feature",
  "properties": {
    "addr:full":"16270 Mustang Dr Springville CA 93265",
    "addr:housenumber":"16270",
    "addr:postcode":"93265",
    "addr:street":"Mustang Dr",
    "iso:country":"US",
    "sg:address":"16270 Mustang Dr",
    "sg:city":"Springville",
    "sg:classifiers":[
        {
            "category":"Freight",
            "type":"Transportation"
        }
    ],
    "sg:phone":"+1 559 539 2589",
    "sg:postcode":"93265",
    "sg:province":"CA",
    "sg:tags":[
        "log",
        "hauling"
    ],
    "wof:name":"Mark Winton Trucking",
    "wof:placetype":"venue"
},
  "geometry": {"coordinates":[-118.843316,36.082981],"type":"Point"}
}