{
  "type": "Feature",
  "properties": {
    "iso:country":"US",
    "sg:address":"5125 Convoy St",
    "sg:city":"San Diego",
    "sg:classifiers":[
        {
            "category":"Banks & Credit Unions",
            "subcategory":"Bank",
            "type":"Services"
        }
    ],
    "sg:phone":"+1 858 268 1390",
    "sg:postcode":"92111",
    "sg:province":"CA",
    "sg:tags":[
        "loan"
    ],
    "wof:name":"Freedom Lending",
    "wof:placetype":"venue"
},
  "geometry": {"coordinates":[-117.152391,32.835336],"type":"Point"}
}