{
  "type": "Feature",
  "properties": {
    "iso:country":"US",
    "sg:address":"645 Morro Ave",
    "sg:city":"Morro Bay",
    "sg:classifiers":[
        {
            "category":"Real Estate",
            "subcategory":"Real Estate Agent",
            "type":"Services"
        }
    ],
    "sg:phone":"+1 805 772 7335",
    "sg:postcode":"93442",
    "sg:province":"CA",
    "sg:website":"www.beachsiderentals.com",
    "wof:name":"Sea Harbor Villas",
    "wof:placetype":"venue"
},
  "geometry": {"coordinates":[-120.851219,35.364547],"type":"Point"}
}