{
  "type": "Feature",
  "properties": {
    "iso:country":"US",
    "sg:address":"239 Main St",
    "sg:city":"Salinas",
    "sg:classifiers":[
        {
            "category":"Shopping",
            "subcategory":"Gifts & Souvenirs",
            "type":"Retail Goods"
        }
    ],
    "sg:phone":"+1 831 757 4038",
    "sg:postcode":"93901",
    "sg:province":"CA",
    "sg:tags":[
        "shop"
    ],
    "wof:name":"Alcalas Gifts & More",
    "wof:placetype":"venue"
},
  "geometry": {"coordinates":[-121.655047,36.675266],"type":"Point"}
}