{
  "type": "Feature",
  "properties": {
    "addr:full":"2418 Stirrup Rd Borrego Springs CA 92004",
    "addr:housenumber":"2418",
    "addr:postcode":"92004",
    "addr:street":"Stirrup Rd",
    "iso:country":"US",
    "sg:address":"2418 Stirrup Rd",
    "sg:city":"Borrego Springs",
    "sg:classifiers":[
        {
            "category":"Building & Trades",
            "subcategory":"Construction",
            "type":"Services"
        }
    ],
    "sg:phone":"+1 760 767 0039",
    "sg:postcode":"92004",
    "sg:province":"CA",
    "sg:tags":[
        "contractor"
    ],
    "wof:name":"A&K Pools",
    "wof:placetype":"venue"
},
  "geometry": {"coordinates":[-116.371317,33.259548],"type":"Point"}
}