{
  "type": "Feature",
  "properties": {
    "addr:full":"1833 E 17th St Ste 318 Santa Ana CA 92705",
    "addr:housenumber":"1833",
    "addr:postcode":"92705",
    "addr:street":"E 17Th St Ste 318",
    "iso:country":"US",
    "sg:address":"1833 E 17th St Ste 318",
    "sg:city":"Santa Ana",
    "sg:classifiers":[
        {
            "category":"Health Services",
            "subcategory":"Health Practitioner",
            "type":"Services"
        }
    ],
    "sg:phone":"+1 714 550 7600",
    "sg:postcode":"92705",
    "sg:province":"CA",
    "sg:tags":[
        "home",
        "care"
    ],
    "sg:website":"www.healthyathome24-7.org",
    "wof:name":"Healthy at Home",
    "wof:placetype":"venue"
},
  "geometry": {"coordinates":[-117.840968,33.760435],"type":"Point"}
}