{
  "type": "Feature",
  "properties": {
    "iso:country":"US",
    "sg:address":"115 S Golden State Blvd",
    "sg:city":"Turlock",
    "sg:classifiers":[
        {
            "category":"Organizations",
            "subcategory":"Professional Association",
            "type":"Services"
        }
    ],
    "sg:phone":"+1 209 632 2221",
    "sg:postcode":"95380",
    "sg:province":"CA",
    "sg:tags":[
        "chambers",
        "commerce"
    ],
    "wof:name":"Turlock Chamber Of Commerce",
    "wof:placetype":"venue"
},
  "geometry": {"coordinates":[-120.845233,37.493917],"type":"Point"}
}