{
  "type": "Feature",
  "properties": {
    "addr:full":"405 W College Ave Santa Rosa CA 95401",
    "addr:housenumber":"405",
    "addr:postcode":"95401",
    "addr:street":"W College Ave",
    "iso:country":"US",
    "sg:address":"405 W College Ave",
    "sg:city":"Santa Rosa",
    "sg:classifiers":[
        {
            "category":"Professional",
            "subcategory":"Engineering",
            "type":"Services"
        }
    ],
    "sg:phone":"+1 707 575 0911",
    "sg:postcode":"95401",
    "sg:province":"CA",
    "sg:tags":[
        "engineer"
    ],
    "wof:name":"Johnson De Bois & Forrest",
    "wof:placetype":"venue"
},
  "geometry": {"coordinates":[-122.73147400000001,38.445843],"type":"Point"}
}