{
  "type": "Feature",
  "properties": {
    "iso:country":"US",
    "sg:address":"1201 Broadway Ave",
    "sg:city":"Millbrae",
    "sg:classifiers":[
        {
            "category":"Social Services",
            "subcategory":"Retirement Home",
            "type":"Services"
        }
    ],
    "sg:phone":"+1 650 742 9150",
    "sg:postcode":"94030",
    "sg:province":"CA",
    "sg:website":"www.greenhillsretirement.com",
    "wof:name":"Marymount Greenhills Retirement Center",
    "wof:placetype":"venue"
},
  "geometry": {"coordinates":[-122.400696,37.607427],"type":"Point"}
}