{
  "type": "Feature",
  "properties": {
    "addr:full":"751 7th Ave San Diego CA 92101",
    "addr:housenumber":"751",
    "addr:postcode":"92101",
    "addr:street":"7Th Ave",
    "iso:country":"US",
    "sg:address":"751 7th Ave",
    "sg:city":"San Diego",
    "sg:classifiers":[
        {
            "category":"Real Estate",
            "subcategory":"Real Estate Agent",
            "type":"Services"
        },
        {
            "category":"Shopping",
            "subcategory":"Catalog Store",
            "type":"Retail Goods"
        }
    ],
    "sg:phone":"+1 619 232 1121",
    "sg:postcode":"92101",
    "sg:province":"CA",
    "sg:tags":[
        "house",
        "order",
        "buying",
        "mail"
    ],
    "wof:name":"Golden Opportunities",
    "wof:placetype":"venue"
},
  "geometry": {"coordinates":[-117.158252,32.713096],"type":"Point"}
}