{
  "type": "Feature",
  "properties": {
    "addr:full":"930 N Franklin St Fort Bragg CA 95437",
    "addr:housenumber":"930",
    "addr:postcode":"95437",
    "addr:street":"N Franklin St",
    "iso:country":"US",
    "sg:address":"930 N Franklin St",
    "sg:city":"Fort Bragg",
    "sg:classifiers":[
        {
            "category":"Retail",
            "subcategory":"Laundry & Dry Cleaning",
            "type":"Services"
        }
    ],
    "sg:phone":"+1 707 964 3293",
    "sg:postcode":"95437",
    "sg:province":"CA",
    "sg:tags":[
        "cleaners"
    ],
    "wof:name":"Polly Cleaners & Laundry",
    "wof:placetype":"venue"
},
  "geometry": {"coordinates":[-123.80442600000001,39.45266],"type":"Point"}
}