{
  "type": "Feature",
  "properties": {
    "iso:country":"US",
    "sg:address":"4821 Ming Ave",
    "sg:city":"Bakersfield",
    "sg:classifiers":[
        {
            "category":"Shopping",
            "subcategory":"Bicycles & Sporting Goods",
            "type":"Retail Goods"
        }
    ],
    "sg:phone":"+1 661 831 3307",
    "sg:postcode":"93309",
    "sg:province":"CA",
    "wof:name":"Copeland Sports",
    "wof:placetype":"venue"
},
  "geometry": {"coordinates":[-119.055716,35.339503],"type":"Point"}
}