{
  "type": "Feature",
  "properties": {
    "iso:country":"US",
    "sg:address":"15540 Fairgrove Ave",
    "sg:city":"La Puente",
    "sg:classifiers":[
        {
            "category":"Education",
            "subcategory":"School",
            "type":"Public Place"
        }
    ],
    "sg:phone":"+1 626 855 3120",
    "sg:postcode":"91744",
    "sg:province":"CA",
    "wof:name":"Hacienda LA Puente School Dist",
    "wof:placetype":"venue"
},
  "geometry": {"coordinates":[-117.947835,34.041913],"type":"Point"}
}