{
  "type": "Feature",
  "properties": {
    "iso:country":"US",
    "sg:address":"4211 Sierra College Blvd",
    "sg:city":"Rocklin",
    "sg:classifiers":[
        {
            "category":"Autos & Motor Vehicles",
            "subcategory":"Fuel & Gas Station",
            "type":"Retail Goods"
        }
    ],
    "sg:phone":"+1 916 660 0590",
    "sg:postcode":"95677",
    "sg:province":"CA",
    "sg:tags":[
        "oil"
    ],
    "wof:name":"Chevron",
    "wof:placetype":"venue"
},
  "geometry": {"coordinates":[-121.205353,38.809534],"type":"Point"}
}