{
  "type": "Feature",
  "properties": {
    "iso:country":"US",
    "sg:address":"416 N Bedford Dr Suite 204",
    "sg:city":"Beverly Hills",
    "sg:classifiers":[
        {
            "category":"Personal",
            "subcategory":"Skin Care",
            "type":"Services"
        }
    ],
    "sg:phone":"+1 310 278 2122",
    "sg:postcode":"90210",
    "sg:province":"CA",
    "sg:website":"www.vitalityinstitute.com",
    "wof:name":"Vitality Institute",
    "wof:placetype":"venue"
},
  "geometry": {"coordinates":[-118.40499699999999,34.068374],"type":"Point"}
}