{
  "type": "Feature",
  "properties": {
    "addr:full":"35 Jordan St San Rafael CA 94901",
    "addr:housenumber":"35",
    "addr:postcode":"94901",
    "addr:street":"Jordan St",
    "iso:country":"US",
    "sg:address":"35 Jordan St",
    "sg:city":"San Rafael",
    "sg:classifiers":[
        {
            "category":"Building & Trades",
            "subcategory":"Construction",
            "type":"Services"
        }
    ],
    "sg:phone":"+1 415 454 7140",
    "sg:postcode":"94901",
    "sg:province":"CA",
    "sg:tags":[
        "plastering",
        "contractor"
    ],
    "wof:name":"Nichelini Plastering & Constr",
    "wof:placetype":"venue"
},
  "geometry": {"coordinates":[-122.52327,37.965368],"type":"Point"}
}