{
  "type": "Feature",
  "properties": {
    "addr:full":"1458 3rd St Santa Monica CA 90401",
    "addr:housenumber":"1458",
    "addr:postcode":"90401",
    "addr:street":"3Rd St",
    "iso:country":"US",
    "sg:address":"1458 3rd St",
    "sg:city":"Santa Monica",
    "sg:classifiers":[
        {
            "category":"Shopping",
            "subcategory":"Stationery & Office Supplies",
            "type":"Retail Goods"
        }
    ],
    "sg:phone":"+1 310 393 4749",
    "sg:postcode":"90401",
    "sg:province":"CA",
    "sg:tags":[
        "stationer"
    ],
    "wof:name":"Papyrus",
    "wof:placetype":"venue"
},
  "geometry": {"coordinates":[-118.49544299999999,34.015065],"type":"Point"}
}