{
  "type": "Feature",
  "properties": {
    "addr:full":"1155 California Dr Burlingame CA 94010",
    "addr:housenumber":"1155",
    "addr:postcode":"94010",
    "addr:street":"California Dr",
    "iso:country":"US",
    "sg:address":"1155 California Dr",
    "sg:city":"Burlingame",
    "sg:classifiers":[
        {
            "category":"Banks & Credit Unions",
            "subcategory":"Bank",
            "type":"Services"
        }
    ],
    "sg:phone":"+1 650 579 2888",
    "sg:postcode":"94010",
    "sg:province":"CA",
    "sg:website":"firstrepublic.com",
    "wof:name":"First Republic",
    "wof:placetype":"venue"
},
  "geometry": {"coordinates":[-122.363041,37.58707],"type":"Point"}
}