{
  "type": "Feature",
  "properties": {
    "addr:full":"1702 N Main St Ste 201 Santa Ana CA 92706",
    "addr:housenumber":"1702",
    "addr:postcode":"92706",
    "addr:street":"N Main St Ste 201",
    "iso:country":"US",
    "sg:address":"1702 N Main St Ste 201",
    "sg:city":"Santa Ana",
    "sg:classifiers":[
        {
            "category":"Professional",
            "subcategory":"Lawyer & Legal Services",
            "type":"Services"
        }
    ],
    "sg:phone":"+1 714 953 9561",
    "sg:postcode":"92706",
    "sg:province":"CA",
    "wof:name":"Rosenberg Jas Atty",
    "wof:placetype":"venue"
},
  "geometry": {"coordinates":[-117.867902,33.760376],"type":"Point"}
}