{
  "type": "Feature",
  "properties": {
    "addr:full":"1561 Via Vis Fallbrook CA 92028",
    "addr:housenumber":"1561",
    "addr:postcode":"92028",
    "addr:street":"Via Vis",
    "iso:country":"US",
    "sg:address":"1561 Via Vis",
    "sg:city":"Fallbrook",
    "sg:classifiers":[
        {
            "category":"Building & Trades",
            "subcategory":"Construction",
            "type":"Services"
        }
    ],
    "sg:phone":"+1 760 723 1232",
    "sg:postcode":"92028",
    "sg:province":"CA",
    "sg:tags":[
        "sandblasting"
    ],
    "wof:name":"Fallbrook Sandblasting",
    "wof:placetype":"venue"
},
  "geometry": {"coordinates":[-117.201454,33.361476],"type":"Point"}
}