{
  "type": "Feature",
  "properties": {
    "addr:full":"245 W Tujunga Ave Burbank CA 91502",
    "addr:housenumber":"245",
    "addr:postcode":"91502",
    "addr:street":"W Tujunga Ave",
    "iso:country":"US",
    "sg:address":"245 W Tujunga Ave",
    "sg:city":"Burbank",
    "sg:classifiers":[
        {
            "category":"Professional",
            "subcategory":"Computer Services",
            "type":"Services"
        }
    ],
    "sg:phone":"+1 818 205 5300",
    "sg:postcode":"91502",
    "sg:province":"CA",
    "wof:name":"Mercury Network Solutions",
    "wof:placetype":"venue"
},
  "geometry": {"coordinates":[-118.314792,34.171857],"type":"Point"}
}