{
  "type": "Feature",
  "properties": {
    "addr:full":"Highland Avenue at Magnolia Avenue Piedmont Park Piedmont CA 94611",
    "addr:postcode":"94611",
    "addr:street":"Highland Avenue At Magnolia",
    "iso:country":"US",
    "sg:address":"Highland Avenue at Magnolia Avenue Piedmont Park",
    "sg:city":"Piedmont",
    "sg:classifiers":[
        {
            "category":"Park",
            "type":"Public Place"
        }
    ],
    "sg:phone":"+1 510 420 3075",
    "sg:postcode":"94611",
    "sg:province":"CA",
    "wof:name":"Exedra Arch",
    "wof:placetype":"venue"
},
  "geometry": {"coordinates":[-122.25099899999999,37.827499],"type":"Point"}
}