{
  "type": "Feature",
  "properties": {
    "addr:full":"1132 Benicia Rd Vallejo CA 94591",
    "addr:housenumber":"1132",
    "addr:postcode":"94591",
    "addr:street":"Benicia Rd",
    "iso:country":"US",
    "sg:address":"1132 Benicia Rd",
    "sg:city":"Vallejo",
    "sg:classifiers":[
        {
            "category":"Retail",
            "subcategory":"Auto Repair",
            "type":"Services"
        }
    ],
    "sg:phone":"+1 707 554 4988",
    "sg:postcode":"94591",
    "sg:province":"CA",
    "sg:tags":[
        "repairing",
        "automobile"
    ],
    "wof:name":"Duncan Motors",
    "wof:placetype":"venue"
},
  "geometry": {"coordinates":[-122.21408,38.091279],"type":"Point"}
}