{
  "type": "Feature",
  "properties": {
    "addr:full":"1500 Sycamore Ave Ste B6 Hercules CA 94547",
    "addr:housenumber":"1500",
    "addr:postcode":"94547",
    "addr:street":"Sycamore Ave Ste B6",
    "iso:country":"US",
    "sg:address":"1500 Sycamore Ave Ste B6",
    "sg:city":"Hercules",
    "sg:classifiers":[
        {
            "category":"Food & Beverages",
            "subcategory":"Specialty",
            "type":"Retail Goods"
        },
        {
            "category":"Restaurant",
            "type":"Food & Drink"
        },
        {
            "category":"Food & Beverages",
            "subcategory":"Groceries & Convenience Stores",
            "type":"Retail Goods"
        }
    ],
    "sg:phone":"+1 510 799 7808",
    "sg:postcode":"94547",
    "sg:province":"CA",
    "sg:tags":[
        "grocers-specialty"
    ],
    "wof:name":"Rsm Oriental Food Mart",
    "wof:placetype":"venue"
},
  "geometry": {"coordinates":[-122.27216300000001,38.01012],"type":"Point"}
}