{
  "type": "Feature",
  "properties": {
    "iso:country":"US",
    "sg:address":"28200 Hwy 189 Ste B-230",
    "sg:city":"Lake Arrowhead",
    "sg:classifiers":[
        {
            "category":"Shopping",
            "subcategory":"Clothing, Apparel, & Fashions",
            "type":"Retail Goods"
        },
        {
            "category":"Manufacturing",
            "subcategory":"Leather Goods",
            "type":"Manufacturing & Wholesale Goods"
        }
    ],
    "sg:phone":"+1 909 336 6747",
    "sg:postcode":"92352",
    "sg:province":"CA",
    "sg:tags":[
        "accessory"
    ],
    "sg:website":"www.coach.com",
    "wof:name":"Coach",
    "wof:placetype":"venue"
},
  "geometry": {"coordinates":[-117.189915,34.249443],"type":"Point"}
}