{
  "type": "Feature",
  "properties": {
    "addr:full":"2595 E Ventura Blvd Oxnard CA 93036",
    "addr:housenumber":"2595",
    "addr:postcode":"93036",
    "addr:street":"E Ventura Blvd",
    "iso:country":"US",
    "sg:address":"2595 E Ventura Blvd",
    "sg:city":"Oxnard",
    "sg:classifiers":[
        {
            "category":"Home & Garden",
            "subcategory":"Building Materials",
            "type":"Retail Goods"
        }
    ],
    "sg:phone":"+1 805 482 4088",
    "sg:postcode":"93036",
    "sg:province":"CA",
    "sg:tags":[
        "paint",
        "wallpaper",
        "store",
        "glass"
    ],
    "wof:name":"Summit Builders",
    "wof:placetype":"venue"
},
  "geometry": {"coordinates":[-119.161388,34.226199],"type":"Point"}
}