{
  "type": "Feature",
  "properties": {
    "addr:full":"7565 Irvine Center Dr Irvine CA 92618",
    "addr:housenumber":"7565",
    "addr:postcode":"92618",
    "addr:street":"Irvine Center Dr",
    "iso:country":"US",
    "sg:address":"7565 Irvine Center Dr",
    "sg:city":"Irvine",
    "sg:classifiers":[
        {
            "category":"Shopping",
            "subcategory":"Computers & Home Electronics",
            "type":"Retail Goods"
        },
        {
            "category":"Wholesale",
            "subcategory":"Computers",
            "type":"Manufacturing & Wholesale Goods"
        }
    ],
    "sg:phone":"+1 949 753 0971",
    "sg:postcode":"92618",
    "sg:province":"CA",
    "sg:website":"www.gateway.com",
    "wof:name":"Gateway Computers Inc",
    "wof:placetype":"venue"
},
  "geometry": {"coordinates":[-117.751446,33.660713],"type":"Point"}
}