{
  "type": "Feature",
  "properties": {
    "iso:country":"US",
    "sg:address":"1212 E Ave S",
    "sg:city":"Palmdale",
    "sg:classifiers":[
        {
            "category":"Professional",
            "subcategory":"Management & Consulting",
            "type":"Services"
        }
    ],
    "sg:phone":"+1 661 575 1078",
    "sg:postcode":"93550",
    "sg:province":"CA",
    "sg:tags":[
        "educational"
    ],
    "wof:name":"Welcome Center",
    "wof:placetype":"venue"
},
  "geometry": {"coordinates":[-118.105085,34.558006],"type":"Point"}
}