{
  "type": "Feature",
  "properties": {
    "addr:full":"1775 Monte Vista Ave Claremont CA 91711",
    "addr:housenumber":"1775",
    "addr:postcode":"91711",
    "addr:street":"Monte Vista Ave",
    "iso:country":"US",
    "sg:address":"1775 Monte Vista Ave",
    "sg:city":"Claremont",
    "sg:classifiers":[
        {
            "category":"Health Services",
            "subcategory":"Health Practitioner",
            "type":"Services"
        }
    ],
    "sg:phone":"+1 909 621 7956",
    "sg:postcode":"91711",
    "sg:province":"CA",
    "sg:tags":[
        "therapist",
        "physical"
    ],
    "wof:name":"Physical Therapy Facility",
    "wof:placetype":"venue"
},
  "geometry": {"coordinates":[-117.69850599999999,34.113167],"type":"Point"}
}