{
  "type": "Feature",
  "properties": {
    "iso:country":"US",
    "sg:address":"746 Market Ct",
    "sg:city":"Los Angeles",
    "sg:classifiers":[
        {
            "category":"Food & Beverages",
            "subcategory":"Groceries & Convenience Stores",
            "type":"Retail Goods"
        }
    ],
    "sg:phone":"+1 213 689 9814",
    "sg:postcode":"90021",
    "sg:province":"CA",
    "sg:tags":[
        "grocer"
    ],
    "wof:name":"Soco Choppy's Produce",
    "wof:placetype":"venue"
},
  "geometry": {"coordinates":[-118.240439,34.036266],"type":"Point"}
}