{
  "type": "Feature",
  "properties": {
    "iso:country":"US",
    "sg:address":"1455 N Dutton Ave",
    "sg:city":"Santa Rosa",
    "sg:classifiers":[
        {
            "category":"Travel",
            "subcategory":"Travel Agent",
            "type":"Entertainment"
        }
    ],
    "sg:phone":"+1 707 546 9888",
    "sg:postcode":"95401",
    "sg:province":"CA",
    "sg:tags":[
        "agency",
        "bureau"
    ],
    "sg:website":"www.flyingdutchmen.com",
    "wof:name":"Skylink Travel",
    "wof:placetype":"venue"
},
  "geometry": {"coordinates":[-122.734659,38.450835],"type":"Point"}
}