{
  "type": "Feature",
  "properties": {
    "iso:country":"US",
    "sg:address":"2455 Chanticleer Avenue",
    "sg:city":"Santa Cruz",
    "sg:classifiers":[
        {
            "category":"Autos & Motor Vehicles",
            "subcategory":"Auto Supplies",
            "type":"Retail Goods"
        }
    ],
    "sg:phone":"+1 831 477 1000",
    "sg:postcode":"95062",
    "sg:province":"CA",
    "sg:tags":[
        "glass"
    ],
    "wof:name":"Pro Vision Glass & Window",
    "wof:placetype":"venue"
},
  "geometry": {"coordinates":[-121.97910899999999,36.984236],"type":"Point"}
}