{
  "type": "Feature",
  "properties": {
    "iso:country":"US",
    "sg:address":"3055 25th Ave",
    "sg:city":"San Francisco",
    "sg:classifiers":[
        {
            "category":"Building & Trades",
            "subcategory":"Construction",
            "type":"Services"
        }
    ],
    "sg:phone":"+1 415 378 4904",
    "sg:postcode":"94132",
    "sg:province":"CA",
    "sg:tags":[
        "interior",
        "design"
    ],
    "sg:website":"www.celedoninteriors.com",
    "wof:name":"Celedon Interiors",
    "wof:placetype":"venue"
},
  "geometry": {"coordinates":[-122.481208,37.731696],"type":"Point"}
}