{
  "type": "Feature",
  "properties": {
    "iso:country":"US",
    "sg:address":"5057 Greencraig Way",
    "sg:city":"San Diego",
    "sg:classifiers":[
        {
            "category":"Freight",
            "type":"Transportation"
        }
    ],
    "sg:phone":"+1 858 569 7799",
    "sg:postcode":"92123",
    "sg:province":"CA",
    "sg:tags":[
        "general"
    ],
    "wof:name":"Mesa Storage",
    "wof:placetype":"venue"
},
  "geometry": {"coordinates":[-117.12301600000001,32.827907],"type":"Point"}
}