{
  "type": "Feature",
  "properties": {
    "iso:country":"US",
    "sg:address":"166 Canyon Rd",
    "sg:city":"Fairfax",
    "sg:classifiers":[
        {
            "category":"Professional",
            "type":"Services"
        }
    ],
    "sg:phone":"+1 415 457 2961",
    "sg:postcode":"94930",
    "sg:province":"CA",
    "wof:name":"Pippits & Wagtails",
    "wof:placetype":"venue"
},
  "geometry": {"coordinates":[-122.611811,37.976694],"type":"Point"}
}