{
  "type": "Feature",
  "properties": {
    "iso:country":"US",
    "sg:address":"4903 E Kings Canyon Rd",
    "sg:city":"Fresno",
    "sg:classifiers":[
        {
            "category":"Shopping",
            "type":"Retail Goods"
        }
    ],
    "sg:phone":"+1 559 255 1147",
    "sg:postcode":"93727",
    "sg:province":"CA",
    "sg:tags":[
        "cards",
        "sport",
        "baseball",
        "memorabilia"
    ],
    "wof:name":"Pure Luck Cards & Collectibles",
    "wof:placetype":"venue"
},
  "geometry": {"coordinates":[-119.727474,36.735963],"type":"Point"}
}