{
  "type": "Feature",
  "properties": {
    "addr:full":"300 Capitol Mall Sacramento CA 95814",
    "addr:housenumber":"300",
    "addr:postcode":"95814",
    "addr:street":"Capitol Mall",
    "iso:country":"US",
    "sg:address":"300 Capitol Mall",
    "sg:city":"Sacramento",
    "sg:classifiers":[
        {
            "category":"Banks & Credit Unions",
            "subcategory":"Bank",
            "type":"Services"
        }
    ],
    "sg:phone":"+1 916 444 5274",
    "sg:postcode":"95814",
    "sg:province":"CA",
    "sg:tags":[
        "broker",
        "foreign",
        "dealer",
        "exchange"
    ],
    "wof:name":"Thomas Cook Foreign Exchange",
    "wof:placetype":"venue"
},
  "geometry": {"coordinates":[-121.502854,38.579097],"type":"Point"}
}