{
  "type": "Feature",
  "properties": {
    "addr:full":"7241 Boulder Ave Highland CA 92346",
    "addr:housenumber":"7241",
    "addr:postcode":"92346",
    "addr:street":"Boulder Ave",
    "iso:country":"US",
    "sg:address":"7241 Boulder Ave",
    "sg:city":"Highland",
    "sg:classifiers":[
        {
            "category":"Shopping",
            "subcategory":"Pharmacy",
            "type":"Retail Goods"
        }
    ],
    "sg:phone":"+1 909 425 1296",
    "sg:postcode":"92346",
    "sg:province":"CA",
    "sg:tags":[
        "laboratory",
        "store",
        "variety"
    ],
    "wof:name":"Longs Drugs 313",
    "wof:placetype":"venue"
},
  "geometry": {"coordinates":[-117.195466,34.125054],"type":"Point"}
}