{
  "type": "Feature",
  "properties": {
    "addr:full":"21271 Old Sonora Columbia Rd Sonora CA 95370",
    "addr:housenumber":"21271",
    "addr:postcode":"95370",
    "addr:street":"Old Sonora Columbia Rd",
    "iso:country":"US",
    "sg:address":"21271 Old Sonora Columbia Rd",
    "sg:city":"Sonora",
    "sg:classifiers":[
        {
            "category":"Building & Trades",
            "subcategory":"Construction",
            "type":"Services"
        }
    ],
    "sg:phone":"+1 209 532 8718",
    "sg:postcode":"95370",
    "sg:province":"CA",
    "sg:tags":[
        "excavating",
        "contractor"
    ],
    "wof:name":"Simunaci Construction",
    "wof:placetype":"venue"
},
  "geometry": {"coordinates":[-120.387107,38.006717],"type":"Point"}
}