{
  "type": "Feature",
  "properties": {
    "iso:country":"US",
    "sg:address":"290 W Olive Ave",
    "sg:city":"Turlock",
    "sg:classifiers":[
        {
            "category":"Place Of Worship",
            "subcategory":"Church",
            "type":"Public Place"
        },
        {
            "category":"Place Of Worship",
            "type":"Public Place"
        }
    ],
    "sg:phone":"+1 209 668 9846",
    "sg:postcode":"95380",
    "sg:province":"CA",
    "sg:tags":[
        "churches-missionary"
    ],
    "wof:name":"Turlock Gospel Mission",
    "wof:placetype":"venue"
},
  "geometry": {"coordinates":[-120.85132900000001,37.493741],"type":"Point"}
}