{
  "type": "Feature",
  "properties": {
    "addr:full":"430 W King St Banning CA 92220",
    "addr:housenumber":"430",
    "addr:postcode":"92220",
    "addr:street":"W King St",
    "iso:country":"US",
    "sg:address":"430 W King St",
    "sg:city":"Banning",
    "sg:classifiers":[
        {
            "category":"Freight",
            "type":"Transportation"
        }
    ],
    "sg:phone":"+1 951 840 0286",
    "sg:postcode":"92220",
    "sg:province":"CA",
    "sg:tags":[
        "operator",
        "trucking"
    ],
    "wof:name":"D&B Transport",
    "wof:placetype":"venue"
},
  "geometry": {"coordinates":[-116.885428,33.935253],"type":"Point"}
}