{
  "type": "Feature",
  "properties": {
    "iso:country":"US",
    "sg:address":"1919 Clement Ave",
    "sg:city":"Alameda",
    "sg:classifiers":[
        {
            "category":"Professional",
            "subcategory":"Detective & Security Services",
            "type":"Services"
        }
    ],
    "sg:phone":"+1 510 995 8921",
    "sg:postcode":"94501",
    "sg:province":"CA",
    "sg:tags":[
        "access",
        "control",
        "system"
    ],
    "wof:name":"ALX Technology",
    "wof:placetype":"venue"
},
  "geometry": {"coordinates":[-122.249358,37.774663],"type":"Point"}
}