{
  "type": "Feature",
  "properties": {
    "iso:country":"US",
    "sg:address":"903 W Lucas Rd",
    "sg:city":"Lodi",
    "sg:classifiers":[
        {
            "category":"Professional",
            "subcategory":"Engineering",
            "type":"Services"
        }
    ],
    "sg:phone":"+1 209 333 3328",
    "sg:postcode":"95242",
    "sg:province":"CA",
    "sg:tags":[
        "engineer"
    ],
    "wof:name":"Pollution Solutions Inc",
    "wof:placetype":"venue"
},
  "geometry": {"coordinates":[-121.333713,38.156582],"type":"Point"}
}