{
  "type": "Feature",
  "properties": {
    "iso:country":"US",
    "sg:address":"2824 Park Ave",
    "sg:city":"Merced",
    "sg:classifiers":[
        {
            "category":"Real Estate",
            "subcategory":"Real Estate Agent",
            "type":"Services"
        }
    ],
    "sg:phone":"+1 209 383 6869",
    "sg:postcode":"95348",
    "sg:province":"CA",
    "sg:tags":[
        "management"
    ],
    "wof:name":"Salvadori Property Management",
    "wof:placetype":"venue"
},
  "geometry": {"coordinates":[-120.47134200000001,37.312288],"type":"Point"}
}