{
  "type": "Feature",
  "properties": {
    "iso:country":"US",
    "sg:address":"12155 Magnolia Ave",
    "sg:city":"Riverside",
    "sg:classifiers":[
        {
            "category":"Real Estate",
            "subcategory":"Developer",
            "type":"Services"
        }
    ],
    "sg:phone":"+1 951 359 0162",
    "sg:postcode":"92503",
    "sg:province":"CA",
    "wof:name":"Rancho Sierra Ind Park",
    "wof:placetype":"venue"
},
  "geometry": {"coordinates":[-117.494562,33.893559],"type":"Point"}
}