{
  "type": "Feature",
  "properties": {
    "addr:full":"213 Highland Ave National City CA 91950",
    "addr:housenumber":"213",
    "addr:postcode":"91950",
    "addr:street":"Highland Ave",
    "iso:country":"US",
    "sg:address":"213 Highland Ave",
    "sg:city":"National City",
    "sg:classifiers":[
        {
            "category":"Restaurant",
            "type":"Food & Drink"
        }
    ],
    "sg:phone":"+1 619 477 4446",
    "sg:postcode":"91950",
    "sg:province":"CA",
    "wof:name":"San Jose Tortilla Factory & Restaurant",
    "wof:placetype":"venue"
},
  "geometry": {"coordinates":[-117.099998,32.682899],"type":"Point"}
}