{
  "type": "Feature",
  "properties": {
    "addr:full":"1340 State Rte 66 Glendora CA 91740",
    "addr:housenumber":"1340",
    "addr:postcode":"91740",
    "addr:street":"State Rte 66",
    "iso:country":"US",
    "sg:address":"1340 State Rte 66",
    "sg:city":"Glendora",
    "sg:classifiers":[
        {
            "category":"Professional",
            "subcategory":"Detective & Security Services",
            "type":"Services"
        }
    ],
    "sg:phone":"+1 626 857 5599",
    "sg:postcode":"91740",
    "sg:province":"CA",
    "sg:tags":[
        "investigator"
    ],
    "sg:website":"www.wfi-inc.com",
    "wof:name":"Western Field Investigations",
    "wof:placetype":"venue"
},
  "geometry": {"coordinates":[-117.838035,34.128954],"type":"Point"}
}