{
  "type": "Feature",
  "properties": {
    "addr:full":"110 E 9th St Los Angeles CA 90079",
    "addr:housenumber":"110",
    "addr:postcode":"90079",
    "addr:street":"E 9Th St",
    "iso:country":"US",
    "sg:address":"110 E 9th St",
    "sg:city":"Los Angeles",
    "sg:classifiers":[
        {
            "category":"Wholesale",
            "subcategory":"Non-durable Goods",
            "type":"Manufacturing & Wholesale Goods"
        },
        {
            "category":"Wholesale",
            "subcategory":"Apparel",
            "type":"Manufacturing & Wholesale Goods"
        }
    ],
    "sg:phone":"+1 213 627 3303",
    "sg:postcode":"90079",
    "sg:province":"CA",
    "sg:tags":[
        "clothing",
        "women's"
    ],
    "wof:name":"Cornell Trading",
    "wof:placetype":"venue"
},
  "geometry": {"coordinates":[-118.254997,34.041302],"type":"Point"}
}