{
  "type": "Feature",
  "properties": {
    "addr:full":"14662 Newport Ave Tustin CA 92780",
    "addr:housenumber":"14662",
    "addr:postcode":"92780",
    "addr:street":"Newport Ave",
    "iso:country":"US",
    "sg:address":"14662 Newport Ave",
    "sg:city":"Tustin",
    "sg:classifiers":[
        {
            "category":"Health Services",
            "subcategory":"Hospital",
            "type":"Services"
        }
    ],
    "sg:phone":"+1 714 838 9600",
    "sg:postcode":"92780",
    "sg:province":"CA",
    "sg:tags":[
        "psychiatric",
        "general"
    ],
    "wof:name":"Tustin Hospital & Medical Ctr",
    "wof:placetype":"venue"
},
  "geometry": {"coordinates":[-117.829322,33.730846],"type":"Point"}
}