{
  "type": "Feature",
  "properties": {
    "iso:country":"US",
    "sg:address":"12226 Osborne Pl Apt 7",
    "sg:city":"Pacoima",
    "sg:classifiers":[
        {
            "category":"Real Estate",
            "subcategory":"Real Estate Operator",
            "type":"Services"
        }
    ],
    "sg:phone":"+1 818 686 1645",
    "sg:postcode":"91331",
    "sg:province":"CA",
    "sg:tags":[
        "apartment"
    ],
    "wof:name":"Osborne Properties",
    "wof:placetype":"venue"
},
  "geometry": {"coordinates":[-118.400392,34.260749],"type":"Point"}
}