{
  "type": "Feature",
  "properties": {
    "iso:country":"US",
    "sg:address":"158 San Lazaro Avenue",
    "sg:city":"Sunnyvale",
    "sg:classifiers":[
        {
            "category":"Retail",
            "subcategory":"Veterinary Services",
            "type":"Services"
        },
        {
            "category":"Retail",
            "subcategory":"Pet Boarding",
            "type":"Services"
        }
    ],
    "sg:phone":"+1 408 739 2688",
    "sg:postcode":"94086",
    "sg:province":"CA",
    "sg:tags":[
        "veterinarian",
        "boarding/pet",
        "sitting"
    ],
    "sg:website":"www.petsfriendsunnyvale.com",
    "wof:name":"Muth Jill DVM",
    "wof:placetype":"venue"
},
  "geometry": {"coordinates":[-122.01203599999999,37.375809],"type":"Point"}
}