{
  "type": "Feature",
  "properties": {
    "addr:full":"4704 E Mountain View Dr San Diego CA 92116",
    "addr:housenumber":"4704",
    "addr:postcode":"92116",
    "addr:street":"E Mountain View Dr",
    "iso:country":"US",
    "sg:address":"4704 E Mountain View Dr",
    "sg:city":"San Diego",
    "sg:classifiers":[
        {
            "category":"Recreation",
            "type":"Entertainment"
        }
    ],
    "sg:phone":"+1 619 226 2202",
    "sg:postcode":"92116",
    "sg:province":"CA",
    "sg:tags":[
        "instruction",
        "yoga"
    ],
    "sg:website":"www.sandiegoyoga.com",
    "wof:name":"BKS Iyengar Yoga Ctr",
    "wof:placetype":"venue"
},
  "geometry": {"coordinates":[-117.112306,32.76351],"type":"Point"}
}