{
  "type": "Feature",
  "properties": {
    "addr:full":"1480 S White Rd San Jose CA 95127",
    "addr:housenumber":"1480",
    "addr:postcode":"95127",
    "addr:street":"S White Rd",
    "iso:country":"US",
    "sg:address":"1480 S White Rd",
    "sg:city":"San Jose",
    "sg:classifiers":[
        {
            "category":"Restaurant",
            "type":"Food & Drink"
        }
    ],
    "sg:phone":"+1 408 258 0118",
    "sg:postcode":"95127",
    "sg:province":"CA",
    "sg:tags":[
        "mexican"
    ],
    "wof:name":"La Birrieria",
    "wof:placetype":"venue"
},
  "geometry": {"coordinates":[-121.81332500000001,37.349822],"type":"Point"}
}