{
  "type": "Feature",
  "properties": {
    "addr:full":"6974 Saroni Dr Oakland CA 94116",
    "addr:housenumber":"6974",
    "addr:postcode":"94116",
    "addr:street":"Saroni Dr",
    "iso:country":"US",
    "sg:address":"6974 Saroni Dr",
    "sg:city":"Oakland",
    "sg:classifiers":[
        {
            "category":"Building & Trades",
            "subcategory":"Construction",
            "type":"Services"
        }
    ],
    "sg:phone":"+1 510 601 1167",
    "sg:postcode":"94116",
    "sg:province":"CA",
    "sg:tags":[
        "contractor"
    ],
    "sg:website":"www.amjswan.com",
    "wof:name":"AMJ Swan",
    "wof:placetype":"venue"
},
  "geometry": {"coordinates":[-122.197017,37.834922],"type":"Point"}
}