{
  "type": "Feature",
  "properties": {
    "addr:full":"18021 Cowan Irvine CA 92614",
    "addr:housenumber":"18021",
    "addr:postcode":"92614",
    "addr:street":"Cowan",
    "iso:country":"US",
    "sg:address":"18021 Cowan",
    "sg:city":"Irvine",
    "sg:classifiers":[
        {
            "category":"Communications",
            "subcategory":"Television Station",
            "type":"Services"
        }
    ],
    "sg:phone":"+1 949 442 9800",
    "sg:postcode":"92614",
    "sg:province":"CA",
    "wof:name":"Kdoc Tv Channel 56",
    "wof:placetype":"venue"
},
  "geometry": {"coordinates":[-117.864998,33.691601],"type":"Point"}
}