{
  "type": "Feature",
  "properties": {
    "addr:full":"4849 Amblebrook Way Sacramento CA 95823",
    "addr:housenumber":"4849",
    "addr:postcode":"95823",
    "addr:street":"Amblebrook Way",
    "iso:country":"US",
    "sg:address":"4849 Amblebrook Way",
    "sg:city":"Sacramento",
    "sg:classifiers":[
        {
            "category":"Health Services",
            "subcategory":"Clinic",
            "type":"Services"
        }
    ],
    "sg:phone":"+1 916 798 0170",
    "sg:postcode":"95823",
    "sg:province":"CA",
    "sg:tags":[
        "home"
    ],
    "wof:name":"Human Compassion",
    "wof:placetype":"venue"
},
  "geometry": {"coordinates":[-121.443551,38.470238],"type":"Point"}
}