{
  "type": "Feature",
  "properties": {
    "iso:country":"US",
    "sg:address":"2270 Balfour Blvd",
    "sg:city":"Brentwood",
    "sg:classifiers":[
        {
            "category":"Restaurant",
            "type":"Food & Drink"
        }
    ],
    "sg:phone":"+1 925 240 1765",
    "sg:postcode":"94513",
    "sg:province":"CA",
    "sg:tags":[
        "steakhouse"
    ],
    "sg:website":"www.vicstewarts.com",
    "wof:name":"Vic Stewart's",
    "wof:placetype":"venue"
},
  "geometry": {"coordinates":[-121.698548,37.925452],"type":"Point"}
}