{
  "type": "Feature",
  "properties": {
    "addr:full":"2817 Crow Canyon Rd San Ramon CA 94583",
    "addr:housenumber":"2817",
    "addr:postcode":"ca 94583",
    "addr:street":"Crow Canyon Rd",
    "iso:country":"US",
    "sg:address":"2817 Crow Canyon Rd",
    "sg:city":"San Ramon",
    "sg:classifiers":[
        {
            "category":"Professional",
            "subcategory":"Accounting & Tax Preparation",
            "type":"Services"
        }
    ],
    "sg:phone":"+1 925 838 9894",
    "sg:postcode":"94583",
    "sg:province":"CA",
    "sg:tags":[
        "accountant"
    ],
    "wof:name":"Dan D Hawkley CPA",
    "wof:placetype":"venue"
},
  "geometry": {"coordinates":[-121.98240800000001,37.774402],"type":"Point"}
}