{
  "type": "Feature",
  "properties": {
    "iso:country":"US",
    "sg:address":"1565 W 19th St",
    "sg:city":"Long Beach",
    "sg:classifiers":[
        {
            "category":"Building & Trades",
            "subcategory":"Landscaping Services",
            "type":"Services"
        }
    ],
    "sg:phone":"+1 562 437 3929",
    "sg:postcode":"90810",
    "sg:province":"CA",
    "sg:tags":[
        "landscape"
    ],
    "wof:name":"Villegas Guadalupe",
    "wof:placetype":"venue"
},
  "geometry": {"coordinates":[-118.212913,33.791756],"type":"Point"}
}