{
  "type": "Feature",
  "properties": {
    "iso:country":"US",
    "sg:address":"28485 Gonzaga Rd",
    "sg:city":"Gustine",
    "sg:classifiers":[
        {
            "category":"Travel",
            "subcategory":"Campground",
            "type":"Entertainment"
        }
    ],
    "sg:phone":"+1 209 826 5542",
    "sg:postcode":"95322",
    "sg:province":"CA",
    "wof:name":"San Luis Rv Resort",
    "wof:placetype":"venue"
},
  "geometry": {"coordinates":[-121.049088,37.057696],"type":"Point"}
}