{
  "type": "Feature",
  "properties": {
    "iso:country":"US",
    "sg:address":"7070 Summit Valley Rd",
    "sg:city":"Hesperia",
    "sg:classifiers":[
        {
            "category":"Airline",
            "type":"Transportation"
        }
    ],
    "sg:phone":"+1 800 433 7300",
    "sg:postcode":"92345",
    "sg:province":"CA",
    "sg:website":"http://national.citysearch.com/profile/external/603486282/hesperia_ca/american_airlines.html?publisher=yellowpages&reference_id=1&placement=ypwebsitemip",
    "wof:name":"American Airlines",
    "wof:placetype":"venue"
},
  "geometry": {"coordinates":[-117.31178300000001,34.381171],"type":"Point"}
}