{
  "type": "Feature",
  "properties": {
    "addr:full":"5777 W. Century Blvd., Suite 232 Los Angeles CA 90045",
    "addr:housenumber":"5777",
    "addr:postcode":"90045",
    "addr:street":"W. Century Blvd. Suite 232",
    "iso:country":"US",
    "sg:address":"5777 W. Century Blvd., Suite 232",
    "sg:city":"Los Angeles",
    "sg:classifiers":[
        {
            "category":"Education",
            "subcategory":"School",
            "type":"Public Place"
        },
        {
            "category":"Organizations",
            "subcategory":"Non-profit Organization",
            "type":"Services"
        }
    ],
    "sg:phone":"+1 310 348 9991",
    "sg:postcode":"90045",
    "sg:province":"CA",
    "sg:tags":[
        "service/non-profit",
        "community"
    ],
    "sg:website":"www.everybodywinsla.org",
    "wof:name":"Everybody Wins LA",
    "wof:placetype":"venue"
},
  "geometry": {"coordinates":[-118.382685,33.946942],"type":"Point"}
}