{
  "type": "Feature",
  "properties": {
    "iso:country":"US",
    "sg:address":"3001 Northstar Dr",
    "sg:city":"Truckee",
    "sg:classifiers":[
        {
            "category":"Food & Beverages",
            "subcategory":"Specialty",
            "type":"Retail Goods"
        },
        {
            "category":"Home & Garden",
            "subcategory":"Home Furnishings",
            "type":"Retail Goods"
        },
        {
            "category":"Food & Beverages",
            "subcategory":"Groceries & Convenience Stores",
            "type":"Retail Goods"
        }
    ],
    "sg:phone":"+1 530 562 8756",
    "sg:postcode":"96161",
    "sg:province":"CA",
    "sg:tags":[
        "kitchen",
        "bath"
    ],
    "sg:website":"www.oliviernapavalley.com",
    "wof:name":"Olivier Napa Valley",
    "wof:placetype":"venue"
},
  "geometry": {"coordinates":[-120.11427,39.281554],"type":"Point"}
}