{
  "type": "Feature",
  "properties": {
    "addr:full":"513 Via Gorrion Palos Verdes Peninsula CA 90274",
    "addr:housenumber":"513",
    "addr:postcode":"verdes;90274",
    "addr:street":"Via Gorrion",
    "iso:country":"US",
    "sg:address":"513 Via Gorrion",
    "sg:city":"Palos Verdes Peninsula",
    "sg:classifiers":[
        {
            "category":"Shopping",
            "subcategory":"Gifts & Souvenirs",
            "type":"Retail Goods"
        }
    ],
    "sg:phone":"+1 310 373 2922",
    "sg:postcode":"90274",
    "sg:province":"CA",
    "wof:name":"Callies",
    "wof:placetype":"venue"
},
  "geometry": {"coordinates":[-118.360021,33.797943],"type":"Point"}
}