{
  "type": "Feature",
  "properties": {
    "iso:country":"US",
    "sg:address":"4507 Conchita Way",
    "sg:city":"Tarzana",
    "sg:classifiers":[
        {
            "category":"Insurance",
            "subcategory":"Hazard Insurance",
            "type":"Services"
        }
    ],
    "sg:phone":"+1 818 757 2030",
    "sg:postcode":"91356",
    "sg:province":"CA",
    "wof:name":"Newton Bing S Clu Chfc",
    "wof:placetype":"venue"
},
  "geometry": {"coordinates":[-118.558998,34.152302],"type":"Point"}
}