{
  "type": "Feature",
  "properties": {
    "addr:full":"1114 Buena Vista Ave Escondido CA 92027",
    "addr:housenumber":"1114",
    "addr:postcode":"92027",
    "addr:street":"Buena Vista Ave",
    "iso:country":"US",
    "sg:address":"1114 Buena Vista Ave",
    "sg:city":"Escondido",
    "sg:classifiers":[
        {
            "category":"Wholesale",
            "subcategory":"Vending Machines",
            "type":"Manufacturing & Wholesale Goods"
        }
    ],
    "sg:phone":"+1 760 746 9899",
    "sg:postcode":"92027",
    "sg:province":"CA",
    "wof:name":"Aamerican Vending",
    "wof:placetype":"venue"
},
  "geometry": {"coordinates":[-117.076785,33.146237],"type":"Point"}
}