{
  "type": "Feature",
  "properties": {
    "addr:full":"2111 S Anne St Santa Ana CA 92704",
    "addr:housenumber":"2111",
    "addr:postcode":"92704",
    "addr:street":"S Anne St",
    "iso:country":"US",
    "sg:address":"2111 S Anne St",
    "sg:city":"Santa Ana",
    "sg:classifiers":[
        {
            "category":"Personal",
            "subcategory":"Nail Salon",
            "type":"Services"
        }
    ],
    "sg:phone":"+1 714 862 2080",
    "sg:postcode":"92704",
    "sg:province":"CA",
    "wof:name":"Premium Nail Concepts",
    "wof:placetype":"venue"
},
  "geometry": {"coordinates":[-117.910965,33.71866],"type":"Point"}
}