{
  "type": "Feature",
  "properties": {
    "addr:full":"980 Minnesota St San Francisco CA 94107",
    "addr:housenumber":"980",
    "addr:postcode":"94107",
    "addr:street":"Minnesota St",
    "iso:country":"US",
    "sg:address":"980 Minnesota St",
    "sg:city":"San Francisco",
    "sg:classifiers":[
        {
            "category":"Real Estate",
            "subcategory":"Real Estate Agent",
            "type":"Services"
        }
    ],
    "sg:phone":"+1 415 824 3514",
    "sg:postcode":"94107",
    "sg:province":"CA",
    "wof:name":"Real Estate Insurance Svc",
    "wof:placetype":"venue"
},
  "geometry": {"coordinates":[-122.390455,37.760111],"type":"Point"}
}