{
  "type": "Feature",
  "properties": {
    "iso:country":"US",
    "sg:address":"1315 2nd St",
    "sg:city":"Crescent City",
    "sg:classifiers":[
        {
            "category":"Autos & Motor Vehicles",
            "subcategory":"Boat Sales",
            "type":"Retail Goods"
        }
    ],
    "sg:phone":"+1 707 464 3516",
    "sg:postcode":"95531",
    "sg:province":"CA",
    "sg:tags":[
        "equipment",
        "marine",
        "supply"
    ],
    "wof:name":"Northcoast Marine Electronics",
    "wof:placetype":"venue"
},
  "geometry": {"coordinates":[-124.191925,41.754236],"type":"Point"}
}