{
  "type": "Feature",
  "properties": {
    "iso:country":"US",
    "sg:address":"124 N Euclid St",
    "sg:city":"Fullerton",
    "sg:classifiers":[
        {
            "category":"Restaurant",
            "type":"Food & Drink"
        }
    ],
    "sg:phone":"+1 714 447 1515",
    "sg:postcode":"92832",
    "sg:province":"CA",
    "sg:tags":[
        "new",
        "american"
    ],
    "sg:website":"www.cafegreenhouse.com",
    "wof:name":"Greenhouse Caf?",
    "wof:placetype":"venue"
},
  "geometry": {"coordinates":[-117.941956,33.870497],"type":"Point"}
}