{
  "type": "Feature",
  "properties": {
    "addr:full":"15452 Cabrito Rd Van Nuys CA 91406",
    "addr:housenumber":"15452",
    "addr:postcode":"91406",
    "addr:street":"Cabrito Rd",
    "iso:country":"US",
    "sg:address":"15452 Cabrito Rd",
    "sg:city":"Van Nuys",
    "sg:classifiers":[
        {
            "category":"Professional",
            "subcategory":"Management & Consulting",
            "type":"Services"
        }
    ],
    "sg:phone":"+1 818 909 9471",
    "sg:postcode":"91406",
    "sg:province":"CA",
    "sg:tags":[
        "marketing",
        "consultant"
    ],
    "wof:name":"Le Bain",
    "wof:placetype":"venue"
},
  "geometry": {"coordinates":[-118.471985,34.217118],"type":"Point"}
}