{
  "type": "Feature",
  "properties": {
    "addr:full":"3872 Hunter Crest Ct Moorpark CA 93021",
    "addr:housenumber":"3872",
    "addr:postcode":"ca 93021",
    "addr:street":"Hunter Crest Ct",
    "iso:country":"US",
    "sg:address":"3872 Hunter Crest Ct",
    "sg:city":"Moorpark",
    "sg:classifiers":[
        {
            "category":"Wholesale",
            "subcategory":"Drugs",
            "type":"Manufacturing & Wholesale Goods"
        }
    ],
    "sg:phone":"+1 805 523 1943",
    "sg:postcode":"93021",
    "sg:province":"CA",
    "wof:name":"Pharmacia & Upjohn Company",
    "wof:placetype":"venue"
},
  "geometry": {"coordinates":[-118.89158500000001,34.261501],"type":"Point"}
}