{
  "type": "Feature",
  "properties": {
    "addr:full":"7958 Cam Alvaro Carlsbad CA 92009",
    "addr:housenumber":"7958",
    "addr:postcode":"92009",
    "addr:street":"Cam Alvaro",
    "iso:country":"US",
    "sg:address":"7958 Cam Alvaro",
    "sg:city":"Carlsbad",
    "sg:classifiers":[
        {
            "category":"Manufacturing",
            "subcategory":"Retail Goods",
            "type":"Manufacturing & Wholesale Goods"
        }
    ],
    "sg:phone":"+1 760 436 7645",
    "sg:postcode":"92009",
    "sg:province":"CA",
    "sg:tags":[
        "product",
        "mfg"
    ],
    "wof:name":"Sandiegowedding Com",
    "wof:placetype":"venue"
},
  "geometry": {"coordinates":[-117.247478,33.069841],"type":"Point"}
}