{
  "type": "Feature",
  "properties": {
    "addr:full":"23340 Volcano Way Red Bluff CA 96080",
    "addr:housenumber":"23340",
    "addr:postcode":"96080",
    "addr:street":"Volcano Way",
    "iso:country":"US",
    "sg:address":"23340 Volcano Way",
    "sg:city":"Red Bluff",
    "sg:classifiers":[
        {
            "category":"Wholesale",
            "subcategory":"Toys & Hobbies",
            "type":"Manufacturing & Wholesale Goods"
        }
    ],
    "sg:phone":"+1 530 527 4064",
    "sg:postcode":"96080",
    "sg:province":"CA",
    "wof:name":"Barbaras Doll House",
    "wof:placetype":"venue"
},
  "geometry": {"coordinates":[-122.16658,40.193019],"type":"Point"}
}