{
  "type": "Feature",
  "properties": {
    "addr:full":"256 Shoreline Hwy Mill Valley CA 94941",
    "addr:housenumber":"256",
    "addr:postcode":"94941",
    "addr:street":"Shoreline Hwy",
    "iso:country":"US",
    "sg:address":"256 Shoreline Hwy",
    "sg:city":"Mill Valley",
    "sg:classifiers":[
        {
            "category":"Restaurant",
            "type":"Food & Drink"
        }
    ],
    "sg:menulink":"http://www.allmenus.com/ca/southwest-marin/150496-subway/menu/",
    "sg:phone":"+1 415 384 0215",
    "sg:postcode":"94941",
    "sg:province":"CA",
    "sg:tags":[
        "american",
        "sandwich"
    ],
    "wof:name":"Subway",
    "wof:placetype":"venue"
},
  "geometry": {"coordinates":[-122.600891,37.876649],"type":"Point"}
}