{
  "type": "Feature",
  "properties": {
    "addr:full":"1199 S Van Ness Avenue San Francisco CA 94110",
    "addr:housenumber":"1199",
    "addr:postcode":"94110",
    "addr:street":"S Van Ness Avenue",
    "iso:country":"US",
    "sg:address":"1199 S Van Ness Avenue",
    "sg:city":"San Francisco",
    "sg:classifiers":[
        {
            "category":"Coffee & Tea",
            "type":"Food & Drink"
        }
    ],
    "sg:phone":"+1 415 550 1800",
    "sg:postcode":"94110",
    "sg:province":"CA",
    "wof:name":"The Little Spot Cafe",
    "wof:placetype":"venue"
},
  "geometry": {"coordinates":[-122.416,37.7542],"type":"Point"}
}