{
  "type": "Feature",
  "properties": {
    "addr:full":"118 Winston St Los Angeles CA 90013",
    "addr:housenumber":"118",
    "addr:postcode":"90013",
    "addr:street":"Winston St",
    "iso:country":"US",
    "sg:address":"118 Winston St",
    "sg:city":"Los Angeles",
    "sg:classifiers":[
        {
            "category":"Shopping",
            "subcategory":"Hobbies, Toys, & Games",
            "type":"Retail Goods"
        }
    ],
    "sg:phone":"+1 213 622 6345",
    "sg:postcode":"90013",
    "sg:province":"CA",
    "sg:tags":[
        "craft",
        "supply"
    ],
    "wof:name":"Richie's Gifts & Craft Supls",
    "wof:placetype":"venue"
},
  "geometry": {"coordinates":[-118.247039,34.046657],"type":"Point"}
}