{
  "type": "Feature",
  "properties": {
    "addr:full":"1300 N Vermont Ave Los Angeles CA 90027",
    "addr:housenumber":"1300",
    "addr:postcode":"90027",
    "addr:street":"N Vermont Ave",
    "iso:country":"US",
    "sg:address":"1300 N Vermont Ave",
    "sg:city":"Los Angeles",
    "sg:classifiers":[
        {
            "category":"Health Services",
            "subcategory":"Health Practitioner",
            "type":"Services"
        }
    ],
    "sg:phone":"+1 323 665 9550",
    "sg:postcode":"90027",
    "sg:province":"CA",
    "sg:tags":[
        "acupuncture"
    ],
    "wof:name":"Yoo Elizabeth MD Neurology Acupuncture & Herbs",
    "wof:placetype":"venue"
},
  "geometry": {"coordinates":[-118.292,34.096001],"type":"Point"}
}