{
  "type": "Feature",
  "properties": {
    "iso:country":"US",
    "sg:address":"4500 Great America Pkwy",
    "sg:city":"Santa Clara",
    "sg:classifiers":[
        {
            "category":"Professional",
            "subcategory":"Computer Services",
            "type":"Services"
        }
    ],
    "sg:phone":"+1 408 748 4300",
    "sg:postcode":"95054",
    "sg:province":"CA",
    "sg:tags":[
        "design",
        "system"
    ],
    "wof:name":"Plexus Software",
    "wof:placetype":"venue"
},
  "geometry": {"coordinates":[-121.977889,37.395199],"type":"Point"}
}