{
  "type": "Feature",
  "properties": {
    "addr:full":"19582 Beach Blvd Huntington Beach CA 92648",
    "addr:housenumber":"19582",
    "addr:postcode":"92648",
    "addr:street":"Beach Blvd",
    "iso:country":"US",
    "sg:address":"19582 Beach Blvd",
    "sg:city":"Huntington Beach",
    "sg:classifiers":[
        {
            "category":"Health Services",
            "subcategory":"Doctor",
            "type":"Services"
        }
    ],
    "sg:phone":"+1 714 378 2410",
    "sg:postcode":"92648",
    "sg:province":"CA",
    "wof:name":"WITTE WENDELL C MD",
    "wof:placetype":"venue"
},
  "geometry": {"coordinates":[-117.988355,33.677921],"type":"Point"}
}