{
  "type": "Feature",
  "properties": {
    "addr:full":"625 W Katella Ave Orange CA 92867",
    "addr:housenumber":"625",
    "addr:postcode":"92867",
    "addr:street":"W Katella Ave",
    "iso:country":"US",
    "sg:address":"625 W Katella Ave",
    "sg:city":"Orange",
    "sg:classifiers":[
        {
            "category":"Wholesale",
            "subcategory":"Durable Goods & Equipment",
            "type":"Manufacturing & Wholesale Goods"
        }
    ],
    "sg:phone":"+1 714 288 9682",
    "sg:postcode":"92867",
    "sg:province":"CA",
    "sg:tags":[
        "laboratory",
        "biological",
        "supply"
    ],
    "sg:website":"www.zymoresearch.com",
    "wof:name":"Zymo Research",
    "wof:placetype":"venue"
},
  "geometry": {"coordinates":[-117.85789200000001,33.809106],"type":"Point"}
}