{
  "type": "Feature",
  "properties": {
    "iso:country":"US",
    "sg:address":"625 W Katella Ave",
    "sg:city":"Orange",
    "sg:classifiers":[
        {
            "category":"Wholesale",
            "subcategory":"Durable Goods & Equipment",
            "type":"Manufacturing & Wholesale Goods"
        }
    ],
    "sg:phone":"+1 714 288 9682",
    "sg:postcode":"92867",
    "sg:province":"CA",
    "sg:tags":[
        "laboratory",
        "biological",
        "supply"
    ],
    "sg:website":"www.zymoresearch.com",
    "wof:name":"Zymo Research",
    "wof:placetype":"venue"
},
  "geometry": {"coordinates":[-117.857892,33.809106],"type":"Point"}
}