{
  "type": "Feature",
  "properties": {
    "addr:full":"3010 W Grant Line Rd Tracy CA 95304",
    "addr:housenumber":"3010",
    "addr:postcode":"95304",
    "addr:street":"W Grant Line Rd",
    "iso:country":"US",
    "sg:address":"3010 W Grant Line Rd",
    "sg:city":"Tracy",
    "sg:postcode":"95304",
    "sg:province":"CA",
    "sg:website":"http://www.walmart.com",
    "wof:name":"Wal-Mart - Vision Center",
    "wof:placetype":"venue"
},
  "geometry": {"coordinates":[-121.46829200000001,37.754082],"type":"Point"}
}