{
  "type": "Feature",
  "properties": {
    "addr:full":"245 Ygnacio Valley Rd Walnut Creek CA 94596",
    "addr:housenumber":"245",
    "addr:postcode":"94596",
    "addr:street":"Valley Rd",
    "iso:country":"US",
    "sg:address":"245 Ygnacio Valley Rd",
    "sg:city":"Walnut Creek",
    "sg:classifiers":[
        {
            "category":"Real Estate",
            "subcategory":"Architect",
            "type":"Services"
        }
    ],
    "sg:phone":"+1 925 944 1626",
    "sg:postcode":"94596",
    "sg:province":"CA",
    "sg:website":"www.loving-campos.com",
    "wof:name":"Loving & Campos Architects Inc",
    "wof:placetype":"venue"
},
  "geometry": {"coordinates":[-122.066562,37.904695],"type":"Point"}
}