{
  "type": "Feature",
  "properties": {
    "addr:full":"39355 California St Fremont CA 94538",
    "addr:housenumber":"39355",
    "addr:postcode":"94538",
    "addr:street":"California St",
    "iso:country":"US",
    "sg:address":"39355 California St",
    "sg:city":"Fremont",
    "sg:classifiers":[
        {
            "category":"Social Services",
            "type":"Services"
        }
    ],
    "sg:phone":"+1 510 796 3689",
    "sg:postcode":"94538",
    "sg:province":"CA",
    "sg:tags":[
        "counselor",
        "marriage",
        "family"
    ],
    "wof:name":"Donna Parsons",
    "wof:placetype":"venue"
},
  "geometry": {"coordinates":[-121.982328,37.547577],"type":"Point"}
}