{
  "type": "Feature",
  "properties": {
    "iso:country":"US",
    "sg:address":"1748 Victory Blvd",
    "sg:city":"Glendale",
    "sg:classifiers":[
        {
            "category":"Banks & Credit Unions",
            "subcategory":"Financial Services",
            "type":"Services"
        }
    ],
    "sg:phone":"+1 818 242 4777",
    "sg:postcode":"91201",
    "sg:province":"CA",
    "sg:tags":[
        "broker",
        "mortgage"
    ],
    "wof:name":"California Finance Group",
    "wof:placetype":"venue"
},
  "geometry": {"coordinates":[-118.30200600000001,34.162097],"type":"Point"}
}