{
  "type": "Feature",
  "properties": {
    "addr:full":"7754 Arjons Dr San Diego CA 92126",
    "addr:housenumber":"7754",
    "addr:postcode":"92126",
    "addr:street":"Arjons Dr",
    "iso:country":"US",
    "sg:address":"7754 Arjons Dr",
    "sg:city":"San Diego",
    "sg:classifiers":[
        {
            "category":"Manufacturing",
            "subcategory":"Tools & Machinery",
            "type":"Manufacturing & Wholesale Goods"
        }
    ],
    "sg:phone":"+1 858 549 2393",
    "sg:postcode":"92126",
    "sg:province":"CA",
    "sg:tags":[
        "bulb",
        "lamp"
    ],
    "sg:website":"www.americanlightingsupply.com",
    "wof:name":"American Lighting Supply",
    "wof:placetype":"venue"
},
  "geometry": {"coordinates":[-117.152477,32.893926],"type":"Point"}
}