{
  "type": "Feature",
  "properties": {
    "addr:full":"1955 Ave Plaza Real Oceanside CA 92056",
    "addr:postcode":"92056",
    "addr:street":"1955 Ave Plaza Real",
    "iso:country":"US",
    "sg:address":"1955 Ave Plaza Real",
    "sg:city":"Oceanside",
    "sg:classifiers":[
        {
            "category":"Home & Garden",
            "subcategory":"Building Materials",
            "type":"Retail Goods"
        }
    ],
    "sg:phone":"+1 760 630 4868",
    "sg:postcode":"92056",
    "sg:province":"CA",
    "sg:tags":[
        "equipment",
        "electric",
        "supply"
    ],
    "sg:website":"www.filtekfilters.com",
    "wof:name":"Filtek",
    "wof:placetype":"venue"
},
  "geometry": {"coordinates":[-117.289782,33.209918],"type":"Point"}
}