{
  "type": "Feature",
  "properties": {
    "iso:country":"US",
    "sg:address":"6204 Saint Helena Hwy",
    "sg:city":"Yountville",
    "sg:classifiers":[
        {
            "category":"Manufacturing",
            "subcategory":"Food",
            "type":"Manufacturing & Wholesale Goods"
        }
    ],
    "sg:phone":"+1 707 944 0675",
    "sg:postcode":"94558",
    "sg:province":"CA",
    "sg:tags":[
        "winery"
    ],
    "wof:name":"Noah Vineryards",
    "wof:placetype":"venue"
},
  "geometry": {"coordinates":[-122.368671,38.406082],"type":"Point"}
}