{
  "type": "Feature",
  "properties": {
    "addr:full":"6204 Saint Helena Hwy Yountville CA 94558",
    "addr:housenumber":"6204",
    "addr:postcode":"ca 94558",
    "addr:street":"Saint Helena Hwy",
    "iso:country":"US",
    "sg:address":"6204 Saint Helena Hwy",
    "sg:city":"Yountville",
    "sg:classifiers":[
        {
            "category":"Manufacturing",
            "subcategory":"Food",
            "type":"Manufacturing & Wholesale Goods"
        }
    ],
    "sg:phone":"+1 707 944 0675",
    "sg:postcode":"94558",
    "sg:province":"CA",
    "sg:tags":[
        "winery"
    ],
    "wof:name":"Noah Vineryards",
    "wof:placetype":"venue"
},
  "geometry": {"coordinates":[-122.36867100000001,38.406082],"type":"Point"}
}