{
  "type": "Feature",
  "properties": {
    "addr:full":"2991 Shattuck Ave Ste 303 Berkeley CA 94705",
    "addr:housenumber":"2991",
    "addr:postcode":"94705",
    "addr:street":"Shattuck Ave Ste 303",
    "iso:country":"US",
    "sg:address":"2991 Shattuck Ave Ste 303",
    "sg:city":"Berkeley",
    "sg:classifiers":[
        {
            "category":"Health Services",
            "subcategory":"Clinic",
            "type":"Services"
        },
        {
            "category":"Personal",
            "subcategory":"Psychics & Astrologers",
            "type":"Services"
        }
    ],
    "sg:phone":"+1 510 495 7116",
    "sg:postcode":"94705",
    "sg:province":"CA",
    "sg:tags":[
        "counseling",
        "mental"
    ],
    "sg:website":"destinyreadingsbysuzanne.net/",
    "wof:name":"Destiny Readings by Suzanne",
    "wof:placetype":"venue"
},
  "geometry": {"coordinates":[-122.266505,37.855541],"type":"Point"}
}