{
  "type": "Feature",
  "properties": {
    "addr:full":"18419 Avenida Bonita N Sonora CA 95370",
    "addr:housenumber":"18419",
    "addr:postcode":"95370",
    "addr:street":"Avenida Bonita N",
    "iso:country":"US",
    "sg:address":"18419 Avenida Bonita N",
    "sg:city":"Sonora",
    "sg:classifiers":[
        {
            "category":"Professional",
            "subcategory":"Art Services",
            "type":"Services"
        }
    ],
    "sg:phone":"+1 209 536 9999",
    "sg:postcode":"95370",
    "sg:province":"CA",
    "sg:tags":[
        "graphic",
        "designer"
    ],
    "sg:website":"http://www.teshingraphics.com",
    "wof:name":"Alexander Teshin Associates",
    "wof:placetype":"venue"
},
  "geometry": {"coordinates":[-120.378226,37.959829],"type":"Point"}
}