{
  "type": "Feature",
  "properties": {
    "addr:full":"5012 Brayton Ave Long Beach CA 90807",
    "addr:housenumber":"5012",
    "addr:postcode":"90807",
    "addr:street":"Brayton Ave",
    "iso:country":"US",
    "sg:address":"5012 Brayton Ave",
    "sg:city":"Long Beach",
    "sg:classifiers":[
        {
            "category":"Building & Trades",
            "subcategory":"Construction",
            "type":"Services"
        }
    ],
    "sg:phone":"+1 562 422 9836",
    "sg:postcode":"90807",
    "sg:province":"CA",
    "sg:tags":[
        "dry wall",
        "contractor"
    ],
    "wof:name":"Ed's Drywall & Patching",
    "wof:placetype":"venue"
},
  "geometry": {"coordinates":[-118.175721,33.848855],"type":"Point"}
}