{
  "type": "Feature",
  "properties": {
    "iso:country":"US",
    "sg:address":"6920 Miramar Rd",
    "sg:city":"San Diego",
    "sg:classifiers":[
        {
            "category":"Home & Garden",
            "subcategory":"Building Materials",
            "type":"Retail Goods"
        }
    ],
    "sg:phone":"+1 858 564 0710",
    "sg:postcode":"92121",
    "sg:province":"CA",
    "sg:tags":[
        "windows"
    ],
    "wof:name":"All American Windows & Hm",
    "wof:placetype":"venue"
},
  "geometry": {"coordinates":[-117.167292,32.878348],"type":"Point"}
}