{
  "type": "Feature",
  "properties": {
    "iso:country":"US",
    "sg:address":"5967 W 3rd St",
    "sg:city":"Los Angeles",
    "sg:classifiers":[
        {
            "category":"Professional",
            "type":"Services"
        }
    ],
    "sg:phone":"+1 323 937 1068",
    "sg:postcode":"90036",
    "sg:province":"CA",
    "wof:name":"Samuey Min Haayin Inc",
    "wof:placetype":"venue"
},
  "geometry": {"coordinates":[-118.350703,34.069913],"type":"Point"}
}