{
  "type": "Feature",
  "properties": {
    "iso:country":"US",
    "sg:address":"51350 Desert Club Dr",
    "sg:city":"La Quinta",
    "sg:classifiers":[
        {
            "category":"Real Estate",
            "subcategory":"Real Estate Agent",
            "type":"Services"
        }
    ],
    "sg:phone":"+1 760 564 2770",
    "sg:postcode":"92253",
    "sg:province":"CA",
    "wof:name":"Desert Club Properties",
    "wof:placetype":"venue"
},
  "geometry": {"coordinates":[-116.301424,33.67594],"type":"Point"}
}