{
  "type": "Feature",
  "properties": {
    "addr:full":"10641 Prospect Ave Santee CA 92071",
    "addr:housenumber":"10641",
    "addr:postcode":"92071",
    "addr:street":"Prospect Ave",
    "iso:country":"US",
    "sg:address":"10641 Prospect Ave",
    "sg:city":"Santee",
    "sg:classifiers":[
        {
            "category":"Wholesale",
            "subcategory":"Construction Materials",
            "type":"Manufacturing & Wholesale Goods"
        }
    ],
    "sg:phone":"+1 619 449 0333",
    "sg:postcode":"92071",
    "sg:province":"CA",
    "sg:tags":[
        "fence"
    ],
    "wof:name":"Builders Fence Co Inc",
    "wof:placetype":"venue"
},
  "geometry": {"coordinates":[-116.966544,32.83102],"type":"Point"}
}