{
  "type": "Feature",
  "properties": {
    "addr:full":"13415 Carmenita Rd Santa Fe Springs CA 90670",
    "addr:housenumber":"13415",
    "addr:postcode":"90670",
    "addr:street":"Carmenita Rd",
    "iso:country":"US",
    "sg:address":"13415 Carmenita Rd",
    "sg:city":"Santa Fe Springs",
    "sg:classifiers":[
        {
            "category":"Professional",
            "type":"Services"
        }
    ],
    "sg:phone":"+1 562 921 7002",
    "sg:postcode":"90670",
    "sg:province":"CA",
    "sg:tags":[
        "establishment"
    ],
    "wof:name":"Golden West Refining Co",
    "wof:placetype":"venue"
},
  "geometry": {"coordinates":[-118.046645,33.908283],"type":"Point"}
}