{
  "type": "Feature",
  "properties": {
    "iso:country":"US",
    "sg:address":"149 Ave Granada",
    "sg:city":"San Clemente",
    "sg:classifiers":[
        {
            "category":"Building & Trades",
            "subcategory":"Landscaping Services",
            "type":"Services"
        }
    ],
    "sg:phone":"+1 949 661 5087",
    "sg:postcode":"92672",
    "sg:province":"CA",
    "sg:tags":[
        "landscape",
        "contractor"
    ],
    "sg:website":"www.boulderscapeinc.com",
    "wof:name":"Boulderscape",
    "wof:placetype":"venue"
},
  "geometry": {"coordinates":[-117.613325,33.426223],"type":"Point"}
}