{
  "type": "Feature",
  "properties": {
    "addr:full":"338 N Canon Dr Beverly Hills CA 90210",
    "addr:housenumber":"338",
    "addr:postcode":"90210",
    "addr:street":"N Canon Dr",
    "iso:country":"US",
    "sg:address":"338 N Canon Dr",
    "sg:city":"Beverly Hills",
    "sg:classifiers":[
        {
            "category":"Shopping",
            "subcategory":"Clothing, Apparel, & Fashions",
            "type":"Retail Goods"
        }
    ],
    "sg:phone":"+1 310 550 0861",
    "sg:postcode":"90210",
    "sg:province":"CA",
    "sg:tags":[
        "children's",
        "clothing"
    ],
    "sg:website":"www.fashionologyla.com",
    "wof:name":"Fashionology LA",
    "wof:placetype":"venue"
},
  "geometry": {"coordinates":[-118.400153,34.070045],"type":"Point"}
}