{
  "type": "Feature",
  "properties": {
    "iso:country":"US",
    "sg:address":"1615 Andalusia Ave",
    "sg:city":"Venice",
    "sg:classifiers":[
        {
            "category":"Manufacturing",
            "subcategory":"Apparel",
            "type":"Manufacturing & Wholesale Goods"
        }
    ],
    "sg:phone":"+1 310 401 0228",
    "sg:postcode":"90291",
    "sg:province":"CA",
    "sg:tags":[
        "outerwear",
        "mfg"
    ],
    "wof:name":"Petit Bee Inc",
    "wof:placetype":"venue"
},
  "geometry": {"coordinates":[-118.467409,33.989044],"type":"Point"}
}