{
  "type": "Feature",
  "properties": {
    "addr:full":"855 Olive St Morro Bay CA 93442",
    "addr:housenumber":"855",
    "addr:postcode":"93442",
    "addr:street":"Olive St",
    "iso:country":"US",
    "sg:address":"855 Olive St",
    "sg:city":"Morro Bay",
    "sg:classifiers":[
        {
            "category":"Building & Trades",
            "subcategory":"Construction",
            "type":"Services"
        }
    ],
    "sg:phone":"+1 805 772 9090",
    "sg:postcode":"93442",
    "sg:province":"CA",
    "sg:tags":[
        "painter"
    ],
    "wof:name":"Primetime Painting",
    "wof:placetype":"venue"
},
  "geometry": {"coordinates":[-120.84332000000001,35.36064],"type":"Point"}
}