{
  "type": "Feature",
  "properties": {
    "iso:country":"US",
    "sg:address":"5010 Cass St",
    "sg:city":"San Diego",
    "sg:classifiers":[
        {
            "category":"Utilities",
            "subcategory":"Mobile Phone",
            "type":"Services"
        },
        {
            "category":"Professional",
            "type":"Services"
        }
    ],
    "sg:phone":"+1 858 272 1185",
    "sg:postcode":"92109",
    "sg:province":"CA",
    "sg:tags":[
        "telephone",
        "cellular"
    ],
    "wof:name":"Mobile Maniac",
    "wof:placetype":"venue"
},
  "geometry": {"coordinates":[-117.254723,32.806545],"type":"Point"}
}