{
  "type": "Feature",
  "properties": {
    "addr:full":"2617 N San Fernando Blvd Burbank CA 91504",
    "addr:housenumber":"2617",
    "addr:postcode":"91504",
    "addr:street":"N San Fernando Blvd",
    "iso:country":"US",
    "sg:address":"2617 N San Fernando Blvd",
    "sg:city":"Burbank",
    "sg:classifiers":[
        {
            "category":"Organizations",
            "subcategory":"Religious Organization",
            "type":"Services"
        }
    ],
    "sg:phone":"+1 818 562 3303",
    "sg:postcode":"91504",
    "sg:province":"CA",
    "wof:name":"Gideons Interntl the",
    "wof:placetype":"venue"
},
  "geometry": {"coordinates":[-118.339996,34.199001],"type":"Point"}
}