{
  "type": "Feature",
  "properties": {
    "iso:country":"US",
    "sg:address":"1329 3rd Ave",
    "sg:city":"Sacramento",
    "sg:classifiers":[
        {
            "category":"Organizations",
            "subcategory":"Non-profit Organization",
            "type":"Services"
        }
    ],
    "sg:phone":"+1 916 930 1999",
    "sg:postcode":"95818",
    "sg:province":"CA",
    "sg:tags":[
        "fund",
        "counselor",
        "raising"
    ],
    "sg:website":"www.fundraisinginfo.com",
    "wof:name":"FUNDRAISINGINFO.COM",
    "wof:placetype":"venue"
},
  "geometry": {"coordinates":[-121.497561,38.55445],"type":"Point"}
}