{
  "type": "Feature",
  "properties": {
    "addr:full":"1634 E 23rd St Los Angeles CA 90011",
    "addr:housenumber":"1634",
    "addr:postcode":"90011",
    "addr:street":"E 23Rd St",
    "iso:country":"US",
    "sg:address":"1634 E 23rd St",
    "sg:city":"Los Angeles",
    "sg:classifiers":[
        {
            "category":"Professional",
            "subcategory":"Business Services",
            "type":"Services"
        }
    ],
    "sg:phone":"+1 323 231 8096",
    "sg:postcode":"90011",
    "sg:province":"CA",
    "sg:tags":[
        "embroidery"
    ],
    "wof:name":"Naima Embroidery",
    "wof:placetype":"venue"
},
  "geometry": {"coordinates":[-118.24412599999999,34.015906],"type":"Point"}
}