{
  "type": "Feature",
  "properties": {
    "addr:full":"2386 Fruitridge Rd Sacramento CA 95822",
    "addr:housenumber":"2386",
    "addr:postcode":"95822",
    "addr:street":"Fruitridge Rd",
    "iso:country":"US",
    "sg:address":"2386 Fruitridge Rd",
    "sg:city":"Sacramento",
    "sg:classifiers":[
        {
            "category":"Restaurant",
            "type":"Food & Drink"
        }
    ],
    "sg:phone":"+1 916 393 7471",
    "sg:postcode":"95822",
    "sg:province":"CA",
    "wof:name":"El Hurradero Mexican Rstrnt",
    "wof:placetype":"venue"
},
  "geometry": {"coordinates":[-121.483638,38.524732],"type":"Point"}
}