{
  "type": "Feature",
  "properties": {
    "iso:country":"US",
    "sg:address":"3833 Peralta Blvd",
    "sg:city":"Fremont",
    "sg:classifiers":[
        {
            "category":"Real Estate",
            "subcategory":"Real Estate Agent",
            "type":"Services"
        }
    ],
    "sg:phone":"+1 510 742 0782",
    "sg:postcode":"94536",
    "sg:province":"CA",
    "wof:name":"Maxim Realty & Loans",
    "wof:placetype":"venue"
},
  "geometry": {"coordinates":[-122.005609,37.55918],"type":"Point"}
}