{
  "type": "Feature",
  "properties": {
    "iso:country":"US",
    "sg:address":"1024 J St",
    "sg:city":"Modesto",
    "sg:classifiers":[
        {
            "category":"Professional",
            "subcategory":"Computer Services",
            "type":"Services"
        }
    ],
    "sg:phone":"+1 209 544 1926",
    "sg:postcode":"95354",
    "sg:province":"CA",
    "sg:tags":[
        "consultant",
        "designer"
    ],
    "wof:name":"Unique Data Solutions",
    "wof:placetype":"venue"
},
  "geometry": {"coordinates":[-120.9995,37.641005],"type":"Point"}
}