{
  "type": "Feature",
  "properties": {
    "addr:full":"333 S Brea Blvd Brea CA 92821",
    "addr:housenumber":"333",
    "addr:postcode":"92821",
    "addr:street":"S Brea Blvd",
    "iso:country":"US",
    "sg:address":"333 S Brea Blvd",
    "sg:city":"Brea",
    "sg:classifiers":[
        {
            "category":"Personal",
            "subcategory":"Beauty Salon",
            "type":"Services"
        }
    ],
    "sg:phone":"+1 714 257 0357",
    "sg:postcode":"92821",
    "sg:province":"CA",
    "wof:name":"Bernardo's Hair Studio",
    "wof:placetype":"venue"
},
  "geometry": {"coordinates":[-117.901038,33.915438],"type":"Point"}
}