{
  "type": "Feature",
  "properties": {
    "iso:country":"US",
    "sg:address":"1527 W Lewis St",
    "sg:city":"San Diego",
    "sg:classifiers":[
        {
            "category":"Social Services",
            "type":"Services"
        }
    ],
    "sg:phone":"+1 619 291 3324",
    "sg:postcode":"92103",
    "sg:province":"CA",
    "sg:tags":[
        "counselor",
        "marriage",
        "family"
    ],
    "wof:name":"Peg Le Blanc",
    "wof:placetype":"venue"
},
  "geometry": {"coordinates":[-117.177455,32.751676],"type":"Point"}
}