{
  "type": "Feature",
  "properties": {
    "iso:country":"US",
    "sg:address":"24220 Gunther Rd",
    "sg:city":"Romoland",
    "sg:classifiers":[
        {
            "category":"Building & Trades",
            "subcategory":"Construction",
            "type":"Services"
        }
    ],
    "sg:phone":"+1 951 928 0913",
    "sg:postcode":"92585",
    "sg:province":"CA",
    "sg:tags":[
        "repairing",
        "remodeling",
        "contractor"
    ],
    "wof:name":"Creighton Construction",
    "wof:placetype":"venue"
},
  "geometry": {"coordinates":[-117.149483,33.768701],"type":"Point"}
}