{
  "type": "Feature",
  "properties": {
    "iso:country":"US",
    "sg:address":"505 N Court St",
    "sg:city":"Visalia",
    "sg:classifiers":[
        {
            "category":"Government",
            "subcategory":"Office",
            "type":"Public Place"
        }
    ],
    "sg:phone":"+1 559 734 6751",
    "sg:postcode":"93291",
    "sg:province":"CA",
    "sg:tags":[
        "program",
        "administrative"
    ],
    "wof:name":"Social Security Administration",
    "wof:placetype":"venue"
},
  "geometry": {"coordinates":[-119.29245,36.335274],"type":"Point"}
}