{
  "type": "Feature",
  "properties": {
    "iso:country":"US",
    "sg:address":"231 E Market St",
    "sg:city":"Stockton",
    "sg:classifiers":[
        {
            "category":"Insurance",
            "subcategory":"Hazard Insurance",
            "type":"Services"
        }
    ],
    "sg:phone":"+1 209 941 0798",
    "sg:postcode":"95205",
    "sg:province":"CA",
    "sg:tags":[
        "bond"
    ],
    "wof:name":"A France Laceys Bail Bonds",
    "wof:placetype":"venue"
},
  "geometry": {"coordinates":[-121.28724099999999,37.952169],"type":"Point"}
}