{
  "type": "Feature",
  "properties": {
    "iso:country":"US",
    "sg:address":"11137 Culver Boulevard",
    "sg:city":"Culver City",
    "sg:classifiers":[
        {
            "category":"Organizations",
            "subcategory":"Religious Organization",
            "type":"Services"
        }
    ],
    "sg:phone":"+1 310 836 8714",
    "sg:postcode":"90230",
    "sg:province":"CA",
    "wof:name":"Resurrection Free Will Baptist Church",
    "wof:placetype":"venue"
},
  "geometry": {"coordinates":[-118.408839,34.006303],"type":"Point"}
}