{
  "type": "Feature",
  "properties": {
    "addr:full":"625 N 9th St Chowchilla CA 93610",
    "addr:housenumber":"625",
    "addr:postcode":"93610",
    "addr:street":"N 9Th St",
    "iso:country":"US",
    "sg:address":"625 N 9th St",
    "sg:city":"Chowchilla",
    "sg:classifiers":[
        {
            "category":"Building & Trades",
            "subcategory":"Plumbing",
            "type":"Services"
        }
    ],
    "sg:phone":"+1 559 665 3629",
    "sg:postcode":"93610",
    "sg:province":"CA",
    "sg:tags":[
        "contractor"
    ],
    "wof:name":"Noain Plumbing",
    "wof:placetype":"venue"
},
  "geometry": {"coordinates":[-120.27103099999999,37.12206],"type":"Point"}
}