{
  "type": "Feature",
  "properties": {
    "iso:country":"US",
    "sg:address":"28914 Roadside Dr",
    "sg:city":"Agoura Hills",
    "sg:classifiers":[
        {
            "category":"Insurance",
            "subcategory":"Insurance Agent",
            "type":"Services"
        }
    ],
    "sg:phone":"+1 818 991 6400",
    "sg:postcode":"91301",
    "sg:province":"CA",
    "wof:name":"Larry Krietzberg Insurance Svc",
    "wof:placetype":"venue"
},
  "geometry": {"coordinates":[-118.755261,34.144825],"type":"Point"}
}