{
  "type": "Feature",
  "properties": {
    "addr:full":"3444 Broderick Street San Francisco CA 94123",
    "addr:housenumber":"3444",
    "addr:postcode":"94123",
    "addr:street":"Broderick Street",
    "iso:country":"US",
    "sg:address":"3444 Broderick Street",
    "sg:city":"San Francisco",
    "sg:classifiers":[
        {
            "category":"Real Estate",
            "subcategory":"Architect",
            "type":"Services"
        }
    ],
    "sg:phone":"+1 415 441 0848",
    "sg:postcode":"94123",
    "sg:province":"CA",
    "wof:name":"Architects II",
    "wof:placetype":"venue"
},
  "geometry": {"coordinates":[-122.44499999999999,37.802399],"type":"Point"}
}