{
  "type": "Feature",
  "properties": {
    "addr:full":"1631 Claudia Dr Sacramento CA 95822",
    "addr:housenumber":"1631",
    "addr:postcode":"95822",
    "addr:street":"Claudia Dr",
    "iso:country":"US",
    "sg:address":"1631 Claudia Dr",
    "sg:city":"Sacramento",
    "sg:classifiers":[
        {
            "category":"Banks & Credit Unions",
            "subcategory":"Bank",
            "type":"Services"
        }
    ],
    "sg:phone":"+1 916 569 5400",
    "sg:postcode":"95822",
    "sg:province":"CA",
    "wof:name":"Schools Financial Credit Union",
    "wof:placetype":"venue"
},
  "geometry": {"coordinates":[-121.49900100000001,38.523201],"type":"Point"}
}