{
  "type": "Feature",
  "properties": {
    "iso:country":"US",
    "sg:address":"701 E Arrow Hwy",
    "sg:city":"Azusa",
    "sg:classifiers":[
        {
            "category":"Retail",
            "subcategory":"Auto Repair",
            "type":"Services"
        }
    ],
    "sg:phone":"+1 626 339 4441",
    "sg:postcode":"91702",
    "sg:province":"CA",
    "sg:tags":[
        "body",
        "automobile",
        "painting"
    ],
    "wof:name":"Star Body & Paint",
    "wof:placetype":"venue"
},
  "geometry": {"coordinates":[-117.89168100000001,34.106795],"type":"Point"}
}