{
  "type": "Feature",
  "properties": {
    "iso:country":"US",
    "sg:address":"2060 Ringwood Ave",
    "sg:city":"San Jose",
    "sg:classifiers":[
        {
            "category":"Manufacturing",
            "subcategory":"Electronics",
            "type":"Manufacturing & Wholesale Goods"
        }
    ],
    "sg:phone":"+1 408 432 3222",
    "sg:postcode":"95131",
    "sg:province":"CA",
    "sg:tags":[
        "vendor",
        "boards",
        "mfg",
        "turnkey",
        "circuit",
        "printed"
    ],
    "sg:website":"www.bestronicsinc.com",
    "wof:name":"Bestronics",
    "wof:placetype":"venue"
},
  "geometry": {"coordinates":[-121.897903,37.396725],"type":"Point"}
}