{
  "type": "Feature",
  "properties": {
    "iso:country":"US",
    "sg:address":"3100 W Ave K",
    "sg:city":"Lancaster",
    "sg:classifiers":[
        {
            "category":"Organizations",
            "subcategory":"Religious Organization",
            "type":"Services"
        }
    ],
    "sg:phone":"+1 661 943 2280",
    "sg:postcode":"93536",
    "sg:province":"CA",
    "sg:tags":[
        "church"
    ],
    "sg:website":"www.bbc-av.org",
    "wof:name":"Bethel Baptist Church",
    "wof:placetype":"venue"
},
  "geometry": {"coordinates":[-118.185241,34.674783],"type":"Point"}
}