{
  "type": "Feature",
  "properties": {
    "iso:country":"US",
    "sg:address":"800 E Colorado Blvd",
    "sg:city":"Pasadena",
    "sg:classifiers":[
        {
            "category":"Professional",
            "subcategory":"Management & Consulting",
            "type":"Services"
        }
    ],
    "sg:phone":"+1 626 795 7707",
    "sg:postcode":"91106",
    "sg:province":"CA",
    "sg:tags":[
        "consultant",
        "business"
    ],
    "wof:name":"DBM Inc",
    "wof:placetype":"venue"
},
  "geometry": {"coordinates":[-118.13235299999999,34.1459],"type":"Point"}
}