{
  "type": "Feature",
  "properties": {
    "addr:full":"3556 Sacramento St San Francisco CA 94118",
    "addr:housenumber":"3556",
    "addr:postcode":"94118",
    "addr:street":"Sacramento St",
    "iso:country":"US",
    "sg:address":"3556 Sacramento St",
    "sg:city":"San Francisco",
    "sg:classifiers":[
        {
            "category":"Sports & Exercise",
            "subcategory":"Gym",
            "type":"Entertainment"
        }
    ],
    "sg:phone":"+1 415 353 5616",
    "sg:postcode":"94118",
    "sg:province":"CA",
    "sg:tags":[
        "personal",
        "trainer"
    ],
    "wof:name":"Strong Heart Strong Body",
    "wof:placetype":"venue"
},
  "geometry": {"coordinates":[-122.451215,37.787748],"type":"Point"}
}