{
  "type": "Feature",
  "properties": {
    "iso:country":"US",
    "sg:address":"13950 Rosecrans Ave",
    "sg:city":"Santa Fe Springs",
    "sg:classifiers":[
        {
            "category":"Manufacturing",
            "subcategory":"Aerospace",
            "type":"Manufacturing & Wholesale Goods"
        }
    ],
    "sg:phone":"+1 562 623 9443",
    "sg:postcode":"90670",
    "sg:province":"CA",
    "sg:tags":[
        "aircraft",
        "mfg"
    ],
    "wof:name":"West Coast Forming",
    "wof:placetype":"venue"
},
  "geometry": {"coordinates":[-118.034308,33.90249],"type":"Point"}
}