{
  "type": "Feature",
  "properties": {
    "addr:full":"108 The Crossroads Carmel CA 93923",
    "addr:housenumber":"108",
    "addr:postcode":"93923",
    "addr:street":"The Crossroads",
    "iso:country":"US",
    "sg:address":"108 The Crossroads",
    "sg:city":"Carmel",
    "sg:classifiers":[
        {
            "category":"Shopping",
            "subcategory":"Computers & Home Electronics",
            "type":"Retail Goods"
        }
    ],
    "sg:phone":"+1 831 625 8620",
    "sg:postcode":"93923",
    "sg:province":"CA",
    "wof:name":"Triad Home Theater & Audio",
    "wof:placetype":"venue"
},
  "geometry": {"coordinates":[-121.908997,36.5383],"type":"Point"}
}