{
  "type": "Feature",
  "properties": {
    "addr:full":"4985 Cummings Rd Eureka CA 95503",
    "addr:housenumber":"4985",
    "addr:postcode":"95503",
    "addr:street":"Cummings Rd",
    "iso:country":"US",
    "sg:address":"4985 Cummings Rd",
    "sg:city":"Eureka",
    "sg:classifiers":[
        {
            "category":"Professional",
            "type":"Services"
        }
    ],
    "sg:phone":"+1 707 443 9996",
    "sg:postcode":"95503",
    "sg:province":"CA",
    "wof:name":"David McGinty",
    "wof:placetype":"venue"
},
  "geometry": {"coordinates":[-124.105757,40.775211],"type":"Point"}
}