{
  "type": "Feature",
  "properties": {
    "addr:full":"2131 The Alameda San Jose CA 95126",
    "addr:housenumber":"2131",
    "addr:postcode":"95126",
    "addr:street":"The Alameda",
    "iso:country":"US",
    "sg:address":"2131 The Alameda",
    "sg:city":"San Jose",
    "sg:classifiers":[
        {
            "category":"Home & Garden",
            "subcategory":"Carpets & Floor Coverings",
            "type":"Retail Goods"
        }
    ],
    "sg:phone":"+1 408 204 3769",
    "sg:postcode":"95126",
    "sg:province":"CA",
    "sg:tags":[
        "carpeting"
    ],
    "sg:website":"carpetofficials.com",
    "wof:name":"Carpet Officials",
    "wof:placetype":"venue"
},
  "geometry": {"coordinates":[-121.929665,37.343276],"type":"Point"}
}