{
  "type": "Feature",
  "properties": {
    "addr:full":"8511 Delta Dr Gilroy CA 95020",
    "addr:housenumber":"8511",
    "addr:postcode":"95020",
    "addr:street":"Delta Dr",
    "iso:country":"US",
    "sg:address":"8511 Delta Dr",
    "sg:city":"Gilroy",
    "sg:classifiers":[
        {
            "category":"Manufacturing",
            "subcategory":"Wood Products",
            "type":"Manufacturing & Wholesale Goods"
        }
    ],
    "sg:phone":"+1 408 310 9925",
    "sg:postcode":"95020",
    "sg:province":"CA",
    "sg:tags":[
        "millwork"
    ],
    "wof:name":"Charles Anthony Millworks",
    "wof:placetype":"venue"
},
  "geometry": {"coordinates":[-121.59984799999999,37.017875],"type":"Point"}
}