{
  "type": "Feature",
  "properties": {
    "iso:country":"US",
    "sg:address":"2761 Marine Way",
    "sg:city":"Mountain View",
    "sg:classifiers":[
        {
            "category":"Manufacturing",
            "subcategory":"Signs",
            "type":"Manufacturing & Wholesale Goods"
        }
    ],
    "sg:phone":"+1 650 564 9060",
    "sg:postcode":"94043",
    "sg:province":"CA",
    "sg:tags":[
        "specialty",
        "mfg"
    ],
    "wof:name":"24-7 Media Inc",
    "wof:placetype":"venue"
},
  "geometry": {"coordinates":[-122.09885199999999,37.431207],"type":"Point"}
}