{
  "type": "Feature",
  "properties": {
    "iso:country":"US",
    "sg:address":"3707 W 190th St",
    "sg:city":"Torrance",
    "sg:classifiers":[
        {
            "category":"Autos & Motor Vehicles",
            "subcategory":"Auto Supplies",
            "type":"Retail Goods"
        }
    ],
    "sg:phone":"+1 310 538 0928",
    "sg:postcode":"90504",
    "sg:province":"CA",
    "sg:tags":[
        "tire"
    ],
    "wof:name":"Torrance Tires",
    "wof:placetype":"venue"
},
  "geometry": {"coordinates":[-118.337417,33.858399],"type":"Point"}
}