{
  "type": "Feature",
  "properties": {
    "addr:full":"1053 S Vermont Ave Los Angeles CA 90006",
    "addr:housenumber":"1053",
    "addr:postcode":"90006",
    "addr:street":"S Vermont Ave",
    "iso:country":"US",
    "sg:address":"1053 S Vermont Ave",
    "sg:city":"Los Angeles",
    "sg:classifiers":[
        {
            "category":"Retail",
            "subcategory":"Auto Rental",
            "type":"Services"
        }
    ],
    "sg:phone":"+1 213 382 0232",
    "sg:postcode":"90006",
    "sg:province":"CA",
    "sg:tags":[
        "car"
    ],
    "wof:name":"Jnj Auto Rent Car Inc",
    "wof:placetype":"venue"
},
  "geometry": {"coordinates":[-118.291,34.051399],"type":"Point"}
}