{
  "type": "Feature",
  "properties": {
    "iso:country":"US",
    "sg:address":"46336 McKittrick Hwy",
    "sg:city":"Buttonwillow",
    "sg:classifiers":[
        {
            "category":"Farming",
            "subcategory":"Livestock Farm",
            "type":"Manufacturing & Wholesale Goods"
        }
    ],
    "sg:phone":"+1 661 764 5871",
    "sg:postcode":"93206",
    "sg:province":"CA",
    "sg:tags":[
        "animal",
        "general"
    ],
    "wof:name":"Chicca-Twin Inc",
    "wof:placetype":"venue"
},
  "geometry": {"coordinates":[-119.520102,35.399519],"type":"Point"}
}