{
  "type": "Feature",
  "properties": {
    "addr:full":"46336 McKittrick Hwy Buttonwillow CA 93206",
    "addr:housenumber":"46336",
    "addr:postcode":"93206",
    "addr:street":"Mckittrick Hwy",
    "iso:country":"US",
    "sg:address":"46336 McKittrick Hwy",
    "sg:city":"Buttonwillow",
    "sg:classifiers":[
        {
            "category":"Farming",
            "subcategory":"Livestock Farm",
            "type":"Manufacturing & Wholesale Goods"
        }
    ],
    "sg:phone":"+1 661 764 5871",
    "sg:postcode":"93206",
    "sg:province":"CA",
    "sg:tags":[
        "animal",
        "general"
    ],
    "wof:name":"Chicca-Twin Inc",
    "wof:placetype":"venue"
},
  "geometry": {"coordinates":[-119.52010199999999,35.399519],"type":"Point"}
}