{
  "type": "Feature",
  "properties": {
    "addr:full":"24752 Toledo Lane Lake Forest CA 92630",
    "addr:housenumber":"24752",
    "addr:postcode":"92630",
    "addr:street":"Toledo Lane",
    "iso:country":"US",
    "sg:address":"24752 Toledo Lane",
    "sg:city":"Lake Forest",
    "sg:classifiers":[
        {
            "category":"Shopping",
            "subcategory":"Bicycles & Sporting Goods",
            "type":"Retail Goods"
        }
    ],
    "sg:phone":"+1 949 859 6914",
    "sg:postcode":"92630",
    "sg:province":"CA",
    "wof:name":"Lake Forest Sun & Sail Pro Shop",
    "wof:placetype":"venue"
},
  "geometry": {"coordinates":[-117.69994800000001,33.643919],"type":"Point"}
}