{
  "type": "Feature",
  "properties": {
    "addr:full":"82 N Fair Oaks Ave Pasadena CA 91103",
    "addr:housenumber":"82",
    "addr:postcode":"91103",
    "addr:street":"N Fair Oaks Ave",
    "iso:country":"US",
    "sg:address":"82 N Fair Oaks Ave",
    "sg:city":"Pasadena",
    "sg:classifiers":[
        {
            "category":"Restaurant",
            "type":"Food & Drink"
        }
    ],
    "sg:menulink":"http://www.allmenus.com/ca/pasadena/22200-la-maschera/menu/",
    "sg:phone":"+1 626 304 0004",
    "sg:postcode":"91103",
    "sg:province":"CA",
    "sg:tags":[
        "italian"
    ],
    "wof:name":"La Maschera",
    "wof:placetype":"venue"
},
  "geometry": {"coordinates":[-118.15053399999999,34.147242],"type":"Point"}
}