{
  "type": "Feature",
  "properties": {
    "addr:full":"1355 Valencia St San Francisco CA 94110",
    "addr:housenumber":"1355",
    "addr:postcode":"94110",
    "addr:street":"Valencia St",
    "iso:country":"US",
    "sg:address":"1355 Valencia St",
    "sg:city":"San Francisco",
    "sg:classifiers":[
        {
            "category":"Real Estate",
            "subcategory":"Real Estate Agent",
            "type":"Services"
        }
    ],
    "sg:phone":"+1 415 648 4000",
    "sg:postcode":"94110",
    "sg:province":"CA",
    "sg:tags":[
        "management"
    ],
    "wof:name":"Murphy Investments",
    "wof:placetype":"venue"
},
  "geometry": {"coordinates":[-122.420501,37.751392],"type":"Point"}
}