{
  "type": "Feature",
  "properties": {
    "addr:full":"19812 Ahwanee Ln Northridge CA 91326",
    "addr:housenumber":"19812",
    "addr:postcode":"91326",
    "addr:street":"Ahwanee Ln",
    "iso:country":"US",
    "sg:address":"19812 Ahwanee Ln",
    "sg:city":"Northridge",
    "sg:classifiers":[
        {
            "category":"Professional",
            "type":"Services"
        }
    ],
    "sg:phone":"+1 310 472 9720",
    "sg:postcode":"91326",
    "sg:province":"CA",
    "wof:name":"West & East Coast",
    "wof:placetype":"venue"
},
  "geometry": {"coordinates":[-118.567815,34.282563],"type":"Point"}
}