{
  "type": "Feature",
  "properties": {
    "addr:full":"455 S Pine St Madera CA 93637",
    "addr:housenumber":"455",
    "addr:postcode":"93637",
    "addr:street":"S Pine St",
    "iso:country":"US",
    "sg:address":"455 S Pine St",
    "sg:city":"Madera",
    "sg:classifiers":[
        {
            "category":"Building & Trades",
            "subcategory":"Plumbing",
            "type":"Services"
        }
    ],
    "sg:phone":"+1 559 661 0900",
    "sg:postcode":"93637",
    "sg:province":"CA",
    "sg:tags":[
        "sheet",
        "work",
        "metal",
        "contractor"
    ],
    "wof:name":"King Curb",
    "wof:placetype":"venue"
},
  "geometry": {"coordinates":[-120.073897,36.951848],"type":"Point"}
}