{
  "type": "Feature",
  "properties": {
    "iso:country":"US",
    "sg:address":"6563 Dehesa Rd",
    "sg:city":"El Cajon",
    "sg:classifiers":[
        {
            "category":"Building & Trades",
            "subcategory":"Construction",
            "type":"Services"
        }
    ],
    "sg:phone":"+1 619 445 7722",
    "sg:postcode":"92019",
    "sg:province":"CA",
    "sg:tags":[
        "nonresidential"
    ],
    "wof:name":"Dean Younker Construction Spc",
    "wof:placetype":"venue"
},
  "geometry": {"coordinates":[-116.806622,32.80618],"type":"Point"}
}