{
  "type": "Feature",
  "properties": {
    "iso:country":"US",
    "sg:address":"7300 Avalon Blvd",
    "sg:city":"Los Angeles",
    "sg:classifiers":[
        {
            "category":"Retail",
            "subcategory":"Auto Repair",
            "type":"Services"
        }
    ],
    "sg:phone":"+1 323 261 9495",
    "sg:postcode":"90003",
    "sg:province":"CA",
    "sg:tags":[
        "wrecker"
    ],
    "wof:name":"W & J Towing",
    "wof:placetype":"venue"
},
  "geometry": {"coordinates":[-118.26515999999999,33.972984],"type":"Point"}
}