{
  "type": "Feature",
  "properties": {
    "addr:full":"2421 4th St Berkeley CA 94710",
    "addr:housenumber":"2421",
    "addr:postcode":"94710",
    "addr:street":"4Th St",
    "iso:country":"US",
    "sg:address":"2421 4th St",
    "sg:city":"Berkeley",
    "sg:classifiers":[
        {
            "category":"Health Services",
            "subcategory":"Health Practitioner",
            "type":"Services"
        }
    ],
    "sg:phone":"+1 510 845 8282",
    "sg:postcode":"94710",
    "sg:province":"CA",
    "sg:tags":[
        "acupuncture"
    ],
    "sg:website":"www.michellebullard.com",
    "wof:name":"Michelle Bullard, MS, LAc",
    "wof:placetype":"venue"
},
  "geometry": {"coordinates":[-122.29729,37.860603],"type":"Point"}
}