{
  "type": "Feature",
  "properties": {
    "addr:full":"1957B Union Street San Francisco CA 94123",
    "addr:housenumber":"1957b",
    "addr:postcode":"94123",
    "addr:street":"Union Street",
    "iso:country":"US",
    "sg:address":"1957B Union Street",
    "sg:city":"San Francisco",
    "sg:classifiers":[
        {
            "category":"Personal",
            "subcategory":"Beauty Salon",
            "type":"Services"
        }
    ],
    "sg:phone":"+1 415 563 6140",
    "sg:postcode":"94123",
    "sg:province":"CA",
    "sg:tags":[
        "hair"
    ],
    "sg:website":"www.robbschallerhairstylist.blog...",
    "wof:name":"Robb Schaller, Hairstylist",
    "wof:placetype":"venue"
},
  "geometry": {"coordinates":[-122.431595,37.797436],"type":"Point"}
}