{
  "type": "Feature",
  "properties": {
    "iso:country":"US",
    "sg:address":"710 W 16th St",
    "sg:city":"Merced",
    "sg:classifiers":[
        {
            "category":"Local Transit",
            "type":"Transportation"
        }
    ],
    "sg:phone":"+1 209 725 3813",
    "sg:postcode":"95340",
    "sg:province":"CA",
    "sg:tags":[
        "bus",
        "line"
    ],
    "wof:name":"Merced Transpo Ctr",
    "wof:placetype":"venue"
},
  "geometry": {"coordinates":[-120.488381,37.30196],"type":"Point"}
}