{
  "type": "Feature",
  "properties": {
    "addr:full":"835 N Todd Ave Azusa CA 91702",
    "addr:housenumber":"835",
    "addr:postcode":"91702",
    "addr:street":"N Todd Ave",
    "iso:country":"US",
    "sg:address":"835 N Todd Ave",
    "sg:city":"Azusa",
    "sg:classifiers":[
        {
            "category":"Food & Beverages",
            "subcategory":"Specialty",
            "type":"Retail Goods"
        }
    ],
    "sg:phone":"+1 626 969 2006",
    "sg:postcode":"91702",
    "sg:province":"CA",
    "sg:tags":[
        "american",
        "latin",
        "mexican",
        "product"
    ],
    "wof:name":"Seyma Products",
    "wof:placetype":"venue"
},
  "geometry": {"coordinates":[-117.924958,34.137106],"type":"Point"}
}