{
  "type": "Feature",
  "properties": {
    "addr:full":"911 E Cota St Santa Barbara CA 93103",
    "addr:housenumber":"911",
    "addr:postcode":"93103",
    "addr:street":"E Cota St",
    "iso:country":"US",
    "sg:address":"911 E Cota St",
    "sg:city":"Santa Barbara",
    "sg:classifiers":[
        {
            "category":"Professional",
            "subcategory":"Advertising",
            "type":"Services"
        }
    ],
    "sg:phone":"+1 805 692 1684",
    "sg:postcode":"93103",
    "sg:province":"CA",
    "sg:tags":[
        "mail"
    ],
    "wof:name":"Direct Mail Enterprises",
    "wof:placetype":"venue"
},
  "geometry": {"coordinates":[-119.685652,34.428257],"type":"Point"}
}