{
  "type": "Feature",
  "properties": {
    "addr:full":"4100 Melrose Ave Los Angeles CA 90029",
    "addr:housenumber":"4100",
    "addr:postcode":"90029",
    "addr:street":"Melrose Ave",
    "iso:country":"US",
    "sg:address":"4100 Melrose Ave",
    "sg:city":"Los Angeles",
    "sg:classifiers":[
        {
            "category":"Autos & Motor Vehicles",
            "subcategory":"Auto Supplies",
            "type":"Retail Goods"
        }
    ],
    "sg:phone":"+1 323 912 9201",
    "sg:postcode":"90029",
    "sg:province":"CA",
    "sg:tags":[
        "tire"
    ],
    "wof:name":"Amigos Tires",
    "wof:placetype":"venue"
},
  "geometry": {"coordinates":[-118.290515,34.083589],"type":"Point"}
}