{
  "type": "Feature",
  "properties": {
    "iso:country":"US",
    "sg:address":"201 Pine Ave",
    "sg:city":"Long Beach",
    "sg:classifiers":[
        {
            "category":"Shopping",
            "subcategory":"Jewelry",
            "type":"Retail Goods"
        }
    ],
    "sg:phone":"+1 562 436 3224",
    "sg:postcode":"90802",
    "sg:province":"CA",
    "sg:tags":[
        "jeweler"
    ],
    "wof:name":"Rothbart's Jewelry",
    "wof:placetype":"venue"
},
  "geometry": {"coordinates":[-118.192544,33.769289],"type":"Point"}
}