{
  "type": "Feature",
  "properties": {
    "iso:country":"US",
    "sg:address":"3843 12th St",
    "sg:city":"Riverside",
    "sg:classifiers":[
        {
            "category":"Health Services",
            "subcategory":"Clinic",
            "type":"Services"
        }
    ],
    "sg:phone":"+1 951 684 3938",
    "sg:postcode":"92501",
    "sg:province":"CA",
    "sg:tags":[
        "colonic",
        "irrigation"
    ],
    "wof:name":"Inner Health Care",
    "wof:placetype":"venue"
},
  "geometry": {"coordinates":[-117.378985,33.979039],"type":"Point"}
}