{
  "type": "Feature",
  "properties": {
    "addr:full":"999 Paso Robles St Paso Robles CA 93446",
    "addr:housenumber":"999",
    "addr:postcode":"93446",
    "addr:street":"Paso Robles St",
    "iso:country":"US",
    "sg:address":"999 Paso Robles St",
    "sg:city":"Paso Robles",
    "sg:classifiers":[
        {
            "category":"Wholesale",
            "subcategory":"Machinery & Supplies",
            "type":"Manufacturing & Wholesale Goods"
        }
    ],
    "sg:phone":"+1 805 238 2800",
    "sg:postcode":"93446",
    "sg:province":"CA",
    "sg:tags":[
        "equipment",
        "irrigation",
        "system"
    ],
    "wof:name":"Cal Coast Irrigation Inc",
    "wof:placetype":"venue"
},
  "geometry": {"coordinates":[-120.68554899999999,35.625878],"type":"Point"}
}