{
  "type": "Feature",
  "properties": {
    "addr:full":"4552 Brickell Privado Ontario CA 91761",
    "addr:housenumber":"4552",
    "addr:postcode":"91761",
    "iso:country":"US",
    "sg:address":"4552 Brickell Privado",
    "sg:city":"Ontario",
    "sg:classifiers":[
        {
            "category":"Manufacturing",
            "subcategory":"Metals",
            "type":"Manufacturing & Wholesale Goods"
        }
    ],
    "sg:phone":"+1 909 390 4510",
    "sg:postcode":"91761",
    "sg:province":"CA",
    "sg:tags":[
        "reel"
    ],
    "sg:website":"www.mossbergind.com",
    "wof:name":"Mossberg Industries Inc",
    "wof:placetype":"venue"
},
  "geometry": {"coordinates":[-117.55053700000001,34.059829],"type":"Point"}
}