{
  "type": "Feature",
  "properties": {
    "addr:full":"298 Harbor Dr Sausalito CA 94965",
    "addr:housenumber":"298",
    "addr:postcode":"94965",
    "addr:street":"Harbor Dr",
    "iso:country":"US",
    "sg:address":"298 Harbor Dr",
    "sg:city":"Sausalito",
    "sg:classifiers":[
        {
            "category":"Autos & Motor Vehicles",
            "subcategory":"Boat Sales",
            "type":"Retail Goods"
        },
        {
            "category":"Marine",
            "type":"Transportation"
        }
    ],
    "sg:phone":"+1 415 331 3166",
    "sg:postcode":"94965",
    "sg:province":"CA",
    "sg:tags":[
        "equipment",
        "electronics",
        "supply"
    ],
    "wof:name":"Johnson Hicks Marine Electronics",
    "wof:placetype":"venue"
},
  "geometry": {"coordinates":[-122.499161,37.86797],"type":"Point"}
}