{
  "type": "Feature",
  "properties": {
    "iso:country":"US",
    "sg:address":"716 S Olive Street",
    "sg:city":"Los Angeles",
    "sg:classifiers":[
        {
            "category":"Shopping",
            "subcategory":"Jewelry",
            "type":"Retail Goods"
        }
    ],
    "sg:phone":"+1 213 627 1206",
    "sg:postcode":"90014",
    "sg:province":"CA",
    "wof:name":"Sassounian Jewelry Tool & Su",
    "wof:placetype":"venue"
},
  "geometry": {"coordinates":[-118.256058,34.046197],"type":"Point"}
}