{
  "type": "Feature",
  "properties": {
    "addr:full":"17732 Saddle Dr Tuolumne CA 95379",
    "addr:housenumber":"17732",
    "addr:postcode":"95379",
    "addr:street":"Saddle Dr",
    "iso:country":"US",
    "sg:address":"17732 Saddle Dr",
    "sg:city":"Tuolumne",
    "sg:classifiers":[
        {
            "category":"Organizations",
            "subcategory":"Religious Organization",
            "type":"Services"
        }
    ],
    "sg:phone":"+1 209 928 1312",
    "sg:postcode":"95379",
    "sg:province":"CA",
    "sg:tags":[
        "house",
        "retreat"
    ],
    "wof:name":"Shepherd's Hill",
    "wof:placetype":"venue"
},
  "geometry": {"coordinates":[-120.267664,37.947416],"type":"Point"}
}