{
  "type": "Feature",
  "properties": {
    "iso:country":"US",
    "sg:address":"2096 Harbor Blvd",
    "sg:city":"Costa Mesa",
    "sg:classifiers":[
        {
            "category":"Retail",
            "subcategory":"Auto Rental",
            "type":"Services"
        }
    ],
    "sg:phone":"+1 949 548 9163",
    "sg:postcode":"92627",
    "sg:province":"CA",
    "sg:tags":[
        "passenger",
        "car"
    ],
    "wof:name":"Enterprise Rent-A-Car",
    "wof:placetype":"venue"
},
  "geometry": {"coordinates":[-117.91896699999999,33.649876],"type":"Point"}
}