{
  "type": "Feature",
  "properties": {
    "iso:country":"US",
    "sg:address":"100 Los Gatos Saratoga Rd",
    "sg:city":"Los Gatos",
    "sg:classifiers":[
        {
            "category":"Real Estate",
            "subcategory":"Real Estate Agent",
            "type":"Services"
        }
    ],
    "sg:phone":"+1 650 654 7776",
    "sg:postcode":"95032",
    "sg:province":"CA",
    "sg:website":"www.pertria.com",
    "wof:name":"Betty Rooker - Pertria",
    "wof:placetype":"venue"
},
  "geometry": {"coordinates":[-121.978995,37.228183],"type":"Point"}
}