{
  "type": "Feature",
  "properties": {
    "addr:full":"1 Spectrum Pointe Dr Lake Forest CA 92630",
    "addr:housenumber":"1",
    "addr:postcode":"92630",
    "addr:street":"Spectrum Pointe Dr",
    "iso:country":"US",
    "sg:address":"1 Spectrum Pointe Dr",
    "sg:city":"Lake Forest",
    "sg:classifiers":[
        {
            "category":"Professional",
            "type":"Services"
        }
    ],
    "sg:phone":"+1 949 215 9122",
    "sg:postcode":"92630",
    "sg:province":"CA",
    "wof:name":"Ipayables",
    "wof:placetype":"venue"
},
  "geometry": {"coordinates":[-117.69132999999999,33.66103],"type":"Point"}
}