{
  "type": "Feature",
  "properties": {
    "iso:country":"US",
    "sg:address":"845 Lazo Ct",
    "sg:city":"Chula Vista",
    "sg:classifiers":[
        {
            "category":"Sports & Exercise",
            "subcategory":"Bowling",
            "type":"Entertainment"
        }
    ],
    "sg:phone":"+1 619 421 4801",
    "sg:postcode":"91910",
    "sg:province":"CA",
    "sg:tags":[
        "center"
    ],
    "sg:website":"www.brunswick.com",
    "wof:name":"Brunswick Premier Lanes",
    "wof:placetype":"venue"
},
  "geometry": {"coordinates":[-117.02672200000001,32.637405],"type":"Point"}
}