{
  "type": "Feature",
  "properties": {
    "iso:country":"US",
    "sg:address":"136 W Green St",
    "sg:city":"Pasadena",
    "sg:classifiers":[
        {
            "category":"Professional",
            "subcategory":"Management & Consulting",
            "type":"Services"
        }
    ],
    "sg:phone":"+1 323 681 9675",
    "sg:postcode":"91123",
    "sg:province":"CA",
    "sg:tags":[
        "consultant"
    ],
    "wof:name":"Motorcar Brokerage Consultants",
    "wof:placetype":"venue"
},
  "geometry": {"coordinates":[-118.153353,34.14442],"type":"Point"}
}