{
  "type": "Feature",
  "properties": {
    "addr:full":"612 S Western Ave Los Angeles CA 90005",
    "addr:housenumber":"612",
    "addr:postcode":"90005",
    "addr:street":"S Western Ave",
    "iso:country":"US",
    "sg:address":"612 S Western Ave",
    "sg:city":"Los Angeles",
    "sg:classifiers":[
        {
            "category":"Manufacturing",
            "subcategory":"Food",
            "type":"Manufacturing & Wholesale Goods"
        }
    ],
    "sg:phone":"+1 213 384 0985",
    "sg:postcode":"90005",
    "sg:province":"CA",
    "sg:tags":[
        "product",
        "retail",
        "bakery",
        "mfg"
    ],
    "wof:name":"P N Donut",
    "wof:placetype":"venue"
},
  "geometry": {"coordinates":[-118.309015,34.062809],"type":"Point"}
}