{
  "type": "Feature",
  "properties": {
    "addr:full":"1335 Guerrero St San Francisco CA 94110",
    "addr:housenumber":"1335",
    "addr:postcode":"94110",
    "addr:street":"Guerrero St",
    "iso:country":"US",
    "sg:address":"1335 Guerrero St",
    "sg:city":"San Francisco",
    "sg:classifiers":[
        {
            "category":"Education",
            "subcategory":"Preschool",
            "type":"Public Place"
        },
        {
            "category":"Education",
            "subcategory":"School",
            "type":"Public Place"
        }
    ],
    "sg:phone":"+1 415 821 1434",
    "sg:postcode":"94110",
    "sg:province":"CA",
    "sg:tags":[
        "elementary"
    ],
    "sg:website":"www.katherinemichielsschool.org/",
    "wof:name":"Katherine Michiels School",
    "wof:placetype":"venue"
},
  "geometry": {"coordinates":[-122.42231,37.749818],"type":"Point"}
}