{
  "type": "Feature",
  "properties": {
    "addr:full":"785 Palm Canyon Dr Borrego Springs CA 92004",
    "addr:housenumber":"785",
    "addr:postcode":"92004",
    "addr:street":"Palm Canyon Dr",
    "iso:country":"US",
    "sg:address":"785 Palm Canyon Dr",
    "sg:city":"Borrego Springs",
    "sg:classifiers":[
        {
            "category":"Home & Garden",
            "subcategory":"Hardware",
            "type":"Retail Goods"
        }
    ],
    "sg:phone":"+1 760 767 5001",
    "sg:postcode":"92004",
    "sg:province":"CA",
    "wof:name":"De Anza True Value Hardware",
    "wof:placetype":"venue"
},
  "geometry": {"coordinates":[-116.37187900000001,33.256534],"type":"Point"}
}