{
  "type": "Feature",
  "properties": {
    "acgov:api":"806.0",
    "acgov:type":"ES",
    "addr:full":"39450 Royal Palm Drive Fremont CA",
    "wof:categories":[
        "education_and_religion:education=school"
    ],
    "wof:name":"Joseph Azevada Elementary",
    "wof:placetype":"venue"
},
  "geometry": {"coordinates":[-121.99410093672059,37.53103106456397],"type":"Point"}
}