{
  "type": "Feature",
  "properties": {
    "iso:country":"US",
    "sg:address":"6301 N State St",
    "sg:city":"Ukiah",
    "sg:classifiers":[
        {
            "category":"Wholesale",
            "subcategory":"Construction Materials",
            "type":"Manufacturing & Wholesale Goods"
        }
    ],
    "sg:phone":"+1 707 485 8781",
    "sg:postcode":"95482",
    "sg:province":"CA",
    "sg:tags":[
        "lumber"
    ],
    "wof:name":"Piedmont Lumber Co",
    "wof:placetype":"venue"
},
  "geometry": {"coordinates":[-123.202497,39.235669],"type":"Point"}
}