{
  "type": "Feature",
  "properties": {
    "iso:country":"US",
    "sg:address":"1770 N 10th Ave",
    "sg:city":"Hanford",
    "sg:classifiers":[
        {
            "category":"Restaurant",
            "type":"Food & Drink"
        }
    ],
    "sg:phone":"+1 559 582 4489",
    "sg:postcode":"93230",
    "sg:province":"CA",
    "wof:name":"Boston House Of Pizza",
    "wof:placetype":"venue"
},
  "geometry": {"coordinates":[-119.637135,36.343128],"type":"Point"}
}