{
  "type": "Feature",
  "properties": {
    "addr:full":"3732 Mt Diablo Blvd Lafayette CA 94549",
    "addr:housenumber":"3732",
    "addr:postcode":"94549",
    "addr:street":"Mt Diablo Blvd",
    "iso:country":"US",
    "sg:address":"3732 Mt Diablo Blvd",
    "sg:city":"Lafayette",
    "sg:classifiers":[
        {
            "category":"Wholesale",
            "subcategory":"Durable Goods & Equipment",
            "type":"Manufacturing & Wholesale Goods"
        }
    ],
    "sg:phone":"+1 925 299 8555",
    "sg:postcode":"94549",
    "sg:province":"CA",
    "sg:tags":[
        "representative",
        "manufacturer"
    ],
    "wof:name":"Incremental Sales",
    "wof:placetype":"venue"
},
  "geometry": {"coordinates":[-122.129198,37.890491],"type":"Point"}
}