{
  "type": "Feature",
  "properties": {
    "iso:country":"US",
    "sg:address":"1412 N Cherry St",
    "sg:city":"Chico",
    "sg:classifiers":[
        {
            "category":"Professional",
            "subcategory":"Business Services",
            "type":"Services"
        }
    ],
    "sg:phone":"+1 530 879 9165",
    "sg:postcode":"95926",
    "sg:province":"CA",
    "sg:tags":[
        "interior",
        "consultant",
        "design",
        "decorator"
    ],
    "wof:name":"Christine Muratore Freelance",
    "wof:placetype":"venue"
},
  "geometry": {"coordinates":[-121.858569,39.739269],"type":"Point"}
}