{
  "type": "Feature",
  "properties": {
    "addr:full":"4233 Santa Anita Ave El Monte CA 91731",
    "addr:housenumber":"4233",
    "addr:postcode":"91731",
    "addr:street":"Santa Anita Ave",
    "iso:country":"US",
    "sg:address":"4233 Santa Anita Ave",
    "sg:city":"El Monte",
    "sg:classifiers":[
        {
            "category":"Banks & Credit Unions",
            "subcategory":"Bank",
            "type":"Services"
        }
    ],
    "sg:phone":"+1 626 279 6853",
    "sg:postcode":"91731",
    "sg:province":"CA",
    "sg:tags":[
        "personal",
        "mortgage"
    ],
    "wof:name":"American Southwest Financial",
    "wof:placetype":"venue"
},
  "geometry": {"coordinates":[-118.03295199999999,34.083546],"type":"Point"}
}