{
  "type": "Feature",
  "properties": {
    "addr:full":"149 New Montgomery St San Francisco CA 94105",
    "addr:housenumber":"149",
    "addr:postcode":"94105",
    "addr:street":"New Montgomery St",
    "iso:country":"US",
    "sg:address":"149 New Montgomery St",
    "sg:city":"San Francisco",
    "sg:classifiers":[
        {
            "category":"Cafe",
            "type":"Food & Drink"
        },
        {
            "category":"Restaurant",
            "type":"Food & Drink"
        },
        {
            "category":"Bakery",
            "type":"Food & Drink"
        }
    ],
    "sg:menulink":"http://www.allmenus.com/ca/san-francisco/45383-cafe-madeleine/menu/",
    "sg:phone":"+1 415 227 4077",
    "sg:postcode":"94105",
    "sg:province":"CA",
    "sg:tags":[
        "dessert",
        "bakery",
        "american",
        "french",
        "pastry"
    ],
    "wof:name":"Cafe Madeleine",
    "wof:placetype":"venue"
},
  "geometry": {"coordinates":[-122.39948,37.786701],"type":"Point"}
}