{
  "type": "Feature",
  "properties": {
    "iso:country":"US",
    "sg:address":"866 Cinnamon Ln",
    "sg:city":"Duarte",
    "sg:classifiers":[
        {
            "category":"Building & Trades",
            "subcategory":"Construction",
            "type":"Services"
        }
    ],
    "sg:phone":"+1 626 303 4532",
    "sg:postcode":"91010",
    "sg:province":"CA",
    "sg:tags":[
        "contractor"
    ],
    "wof:name":"Heliopolis Builders",
    "wof:placetype":"venue"
},
  "geometry": {"coordinates":[-117.987738,34.127566],"type":"Point"}
}