{
  "type": "Feature",
  "properties": {
    "addr:full":"5312 Navajo Way Antioch CA 94531",
    "addr:housenumber":"5312",
    "addr:postcode":"ca 94531",
    "addr:street":"Navajo Way",
    "iso:country":"US",
    "sg:address":"5312 Navajo Way",
    "sg:city":"Antioch",
    "sg:classifiers":[
        {
            "category":"Wholesale",
            "subcategory":"Vending Machines",
            "type":"Manufacturing & Wholesale Goods"
        }
    ],
    "sg:phone":"+1 925 978 9928",
    "sg:postcode":"94531",
    "sg:province":"CA",
    "sg:tags":[
        "operator"
    ],
    "wof:name":"Snackerrs Vending Service",
    "wof:placetype":"venue"
},
  "geometry": {"coordinates":[-121.772672,37.954688],"type":"Point"}
}