{
  "type": "Feature",
  "properties": {
    "iso:country":"US",
    "sg:address":"2684 Middlefield Rd",
    "sg:city":"Redwood City",
    "sg:classifiers":[
        {
            "category":"Building & Trades",
            "subcategory":"Plumbing",
            "type":"Services"
        }
    ],
    "sg:phone":"+1 650 363 8883",
    "sg:postcode":"94063",
    "sg:province":"CA",
    "sg:tags":[
        "plumbing",
        "contractor"
    ],
    "wof:name":"Service On Demand",
    "wof:placetype":"venue"
},
  "geometry": {"coordinates":[-122.211901,37.47696],"type":"Point"}
}