{
  "type": "Feature",
  "properties": {
    "iso:country":"US",
    "sg:address":"1511 S Pomona Ave",
    "sg:city":"Fullerton",
    "sg:classifiers":[
        {
            "category":"Shopping",
            "subcategory":"Hobbies, Toys, & Games",
            "type":"Retail Goods"
        }
    ],
    "sg:phone":"+1 714 473 6522",
    "sg:postcode":"92832",
    "sg:province":"CA",
    "wof:name":"Le Bella Cosa",
    "wof:placetype":"venue"
},
  "geometry": {"coordinates":[-117.92226100000001,33.854757],"type":"Point"}
}