{
  "type": "Feature",
  "properties": {
    "addr:full":"918 N Mountain View Ave San Bernardino CA 92410",
    "addr:housenumber":"918",
    "addr:postcode":"92410",
    "addr:street":"N Mountain View Ave",
    "iso:country":"US",
    "sg:address":"918 N Mountain View Ave",
    "sg:city":"San Bernardino",
    "sg:classifiers":[
        {
            "category":"Organizations",
            "subcategory":"Religious Organization",
            "type":"Services"
        }
    ],
    "sg:phone":"+1 909 885 6726",
    "sg:postcode":"92410",
    "sg:province":"CA",
    "wof:name":"7th Day Advnt Spanish Chrch",
    "wof:placetype":"venue"
},
  "geometry": {"coordinates":[-117.28751200000001,34.117328],"type":"Point"}
}