{
  "type": "Feature",
  "properties": {
    "iso:country":"US",
    "sg:address":"340 East Ave",
    "sg:city":"Chico",
    "sg:classifiers":[
        {
            "category":"Health Services",
            "subcategory":"Health Practitioner",
            "type":"Services"
        }
    ],
    "sg:phone":"+1 530 332 6110",
    "sg:postcode":"95926",
    "sg:province":"CA",
    "sg:tags":[
        "therapist",
        "physical"
    ],
    "wof:name":"Enloe Outpatient Rehab Svc",
    "wof:placetype":"venue"
},
  "geometry": {"coordinates":[-121.860582,39.756925],"type":"Point"}
}