{
  "type": "Feature",
  "properties": {
    "iso:country":"US",
    "sg:address":"32 E Main St",
    "sg:city":"Winters",
    "sg:classifiers":[
        {
            "category":"Real Estate",
            "subcategory":"Real Estate Operator",
            "type":"Services"
        }
    ],
    "sg:phone":"+1 530 795 4940",
    "sg:postcode":"95694",
    "sg:province":"CA",
    "sg:tags":[
        "apartment"
    ],
    "wof:name":"Creekside Apartments",
    "wof:placetype":"venue"
},
  "geometry": {"coordinates":[-121.965036,38.523147],"type":"Point"}
}