{
  "type": "Feature",
  "properties": {
    "addr:full":"4115 Concord Blvd Concord CA 94519",
    "addr:housenumber":"4115",
    "addr:postcode":"94519",
    "addr:street":"Concord Blvd",
    "iso:country":"US",
    "sg:address":"4115 Concord Blvd",
    "sg:city":"Concord",
    "sg:classifiers":[
        {
            "category":"Shopping",
            "subcategory":"Discount & Variety Stores",
            "type":"Retail Goods"
        },
        {
            "category":"Wholesale",
            "subcategory":"Non-durable Goods",
            "type":"Manufacturing & Wholesale Goods"
        }
    ],
    "sg:phone":"+1 925 676 3200",
    "sg:postcode":"94519",
    "sg:province":"CA",
    "wof:name":"Dollar House",
    "wof:placetype":"venue"
},
  "geometry": {"coordinates":[-121.992266,37.97768],"type":"Point"}
}