{
  "type": "Feature",
  "properties": {
    "iso:country":"US",
    "sg:address":"13785 Tulare Ct",
    "sg:city":"Fontana",
    "sg:classifiers":[
        {
            "category":"Home & Garden",
            "subcategory":"Home Furnishings",
            "type":"Retail Goods"
        }
    ],
    "sg:phone":"+1 909 646 9084",
    "sg:postcode":"92336",
    "sg:province":"CA",
    "sg:tags":[
        "venetian",
        "blind"
    ],
    "wof:name":"Tomorrow Blinds & Water Fltrs",
    "wof:placetype":"venue"
},
  "geometry": {"coordinates":[-117.501473,34.110219],"type":"Point"}
}