{
  "type": "Feature",
  "properties": {
    "addr:full":"8419 Canoga Ave Canoga Park CA 91304",
    "addr:housenumber":"8419",
    "addr:postcode":"91304",
    "addr:street":"Canoga Ave",
    "iso:country":"US",
    "sg:address":"8419 Canoga Ave",
    "sg:city":"Canoga Park",
    "sg:classifiers":[
        {
            "category":"Retail",
            "subcategory":"Repair Shop",
            "type":"Services"
        }
    ],
    "sg:phone":"+1 818 727 7214",
    "sg:postcode":"91304",
    "sg:province":"CA",
    "sg:tags":[
        "refinishing",
        "furniture"
    ],
    "wof:name":"Finished By Design",
    "wof:placetype":"venue"
},
  "geometry": {"coordinates":[-118.597618,34.223892],"type":"Point"}
}