{
  "type": "Feature",
  "properties": {
    "iso:country":"US",
    "sg:address":"725 Greenwich Street",
    "sg:city":"San Francisco",
    "sg:classifiers":[
        {
            "category":"Professional",
            "subcategory":"Lawyer & Legal Services",
            "type":"Services"
        }
    ],
    "sg:phone":"+1 415 986 0460",
    "sg:postcode":"94133",
    "sg:province":"CA",
    "wof:name":"Sugiyama Glenn Law Offices of",
    "wof:placetype":"venue"
},
  "geometry": {"coordinates":[-122.411598,37.802021],"type":"Point"}
}