{
  "type": "Feature",
  "properties": {
    "addr:full":"444 S Glenoaks Blvd Burbank CA 91502",
    "addr:housenumber":"444",
    "addr:postcode":"91502",
    "addr:street":"S Glenoaks Blvd",
    "iso:country":"US",
    "sg:address":"444 S Glenoaks Blvd",
    "sg:city":"Burbank",
    "sg:classifiers":[
        {
            "category":"Retail",
            "subcategory":"Car Wash",
            "type":"Services"
        }
    ],
    "sg:phone":"+1 818 841 5000",
    "sg:postcode":"91502",
    "sg:province":"CA",
    "sg:tags":[
        "polishing",
        "washing"
    ],
    "wof:name":"Glenoaks Car Wash",
    "wof:placetype":"venue"
},
  "geometry": {"coordinates":[-118.30300099999999,34.180599],"type":"Point"}
}