{
  "type": "Feature",
  "properties": {
    "iso:country":"US",
    "sg:address":"22744 Clarendon St",
    "sg:city":"Woodland Hills",
    "sg:classifiers":[
        {
            "category":"Social Services",
            "subcategory":"Adult Care",
            "type":"Services"
        }
    ],
    "sg:phone":"+1 818 716 5904",
    "sg:postcode":"91367",
    "sg:province":"CA",
    "sg:tags":[
        "home",
        "residential"
    ],
    "wof:name":"Clarendon Assisted Living",
    "wof:placetype":"venue"
},
  "geometry": {"coordinates":[-118.622497,34.169128],"type":"Point"}
}