{
  "type": "Feature",
  "properties": {
    "addr:full":"10382 Whirlaway St Cypress CA 90630",
    "addr:postcode":"10382;90630",
    "addr:street":"Whirlaway St",
    "iso:country":"US",
    "sg:address":"10382 Whirlaway St",
    "sg:city":"Cypress",
    "sg:classifiers":[
        {
            "category":"Building & Trades",
            "subcategory":"Cleaning & Sanitation",
            "type":"Services"
        }
    ],
    "sg:phone":"+1 714 821 3390",
    "sg:postcode":"90630",
    "sg:province":"CA",
    "sg:tags":[
        "window"
    ],
    "wof:name":"Wizard Window Cleaning",
    "wof:placetype":"venue"
},
  "geometry": {"coordinates":[-118.03985,33.811952],"type":"Point"}
}