{
  "type": "Feature",
  "properties": {
    "addr:full":"9302 Glendon Way Rosemead CA 91770",
    "addr:housenumber":"9302",
    "addr:postcode":"91770",
    "addr:street":"Glendon Way",
    "iso:country":"US",
    "sg:address":"9302 Glendon Way",
    "sg:city":"Rosemead",
    "sg:classifiers":[
        {
            "category":"Home & Garden",
            "subcategory":"Building Materials",
            "type":"Retail Goods"
        }
    ],
    "sg:phone":"+1 626 569 9450",
    "sg:postcode":"91770",
    "sg:province":"CA",
    "sg:tags":[
        "energy",
        "conservation",
        "prod"
    ],
    "wof:name":"ACN Energy",
    "wof:placetype":"venue"
},
  "geometry": {"coordinates":[-118.065978,34.074076],"type":"Point"}
}