{
  "type": "Feature",
  "properties": {
    "iso:country":"US",
    "sg:address":"2205 Kelso Peak Ave",
    "sg:city":"Bakersfield",
    "sg:classifiers":[
        {
            "category":"Professional",
            "subcategory":"Accounting & Tax Preparation",
            "type":"Services"
        }
    ],
    "sg:phone":"+1 661 834 9149",
    "sg:postcode":"93304",
    "sg:province":"CA",
    "sg:tags":[
        "bookkeeping",
        "general"
    ],
    "wof:name":"Diversified Services",
    "wof:placetype":"venue"
},
  "geometry": {"coordinates":[-119.027236,35.310835],"type":"Point"}
}