{
  "type": "Feature",
  "properties": {
    "addr:full":"12555 Mariposa Rd Victorville CA 92395",
    "addr:housenumber":"12555",
    "addr:postcode":"92395",
    "addr:street":"Mariposa Rd",
    "iso:country":"US",
    "sg:address":"12555 Mariposa Rd",
    "sg:city":"Victorville",
    "sg:classifiers":[
        {
            "category":"Home & Garden",
            "subcategory":"Home Furnishings",
            "type":"Retail Goods"
        },
        {
            "category":"Building & Trades",
            "subcategory":"Construction",
            "type":"Services"
        },
        {
            "category":"Home & Garden",
            "subcategory":"Carpets & Floor Coverings",
            "type":"Retail Goods"
        }
    ],
    "sg:phone":"+1 760 241 0141",
    "sg:postcode":"92395",
    "sg:province":"CA",
    "sg:tags":[
        "draperies",
        "material",
        "rug",
        "window",
        "treatment",
        "tile-contractors",
        "curtain",
        "linoleum"
    ],
    "sg:website":"http://www.carpetclub.net",
    "wof:name":"Carpet Club",
    "wof:placetype":"venue"
},
  "geometry": {"coordinates":[-117.33879899999999,34.479363],"type":"Point"}
}