{
  "type": "Feature",
  "properties": {
    "iso:country":"US",
    "sg:address":"11101 Ventura Blvd",
    "sg:city":"Studio City",
    "sg:classifiers":[
        {
            "category":"Retail",
            "subcategory":"Auto Repair",
            "type":"Services"
        }
    ],
    "sg:phone":"+1 818 980 2353",
    "sg:postcode":"91604",
    "sg:province":"CA",
    "sg:tags":[
        "repairing",
        "automotive",
        "automobile",
        "radiator",
        "general"
    ],
    "wof:name":"All City Radiator",
    "wof:placetype":"venue"
},
  "geometry": {"coordinates":[-118.37163099999999,34.141039],"type":"Point"}
}