{
  "type": "Feature",
  "properties": {
    "iso:country":"US",
    "sg:address":"27026 Victoria Ln",
    "sg:city":"Santa Clarita",
    "sg:classifiers":[
        {
            "category":"Manufacturing",
            "subcategory":"Printing",
            "type":"Manufacturing & Wholesale Goods"
        }
    ],
    "sg:phone":"+1 661 799 9611",
    "sg:postcode":"91355",
    "sg:province":"CA",
    "sg:tags":[
        "publisher",
        "software"
    ],
    "wof:name":"Sales Explosion Inc",
    "wof:placetype":"venue"
},
  "geometry": {"coordinates":[-118.560006,34.430033],"type":"Point"}
}