{
  "type": "Feature",
  "properties": {
    "addr:full":"5793 Delta Ave Tracy CA 95304",
    "addr:housenumber":"5793",
    "addr:postcode":"95304",
    "addr:street":"Delta Ave",
    "iso:country":"US",
    "sg:address":"5793 Delta Ave",
    "sg:city":"Tracy",
    "sg:classifiers":[
        {
            "category":"Professional",
            "type":"Services"
        }
    ],
    "sg:phone":"+1 209 835 1549",
    "sg:postcode":"95304",
    "sg:province":"CA",
    "sg:tags":[
        "establishment"
    ],
    "wof:name":"Jensen Karl& Sons Inc",
    "wof:placetype":"venue"
},
  "geometry": {"coordinates":[-121.37361,37.795657],"type":"Point"}
}