{
  "type": "Feature",
  "properties": {
    "addr:full":"1344 S Reservoir St Pomona CA 91766",
    "addr:housenumber":"1344",
    "addr:postcode":"91766",
    "addr:street":"S Reservoir St",
    "iso:country":"US",
    "sg:address":"1344 S Reservoir St",
    "sg:city":"Pomona",
    "sg:classifiers":[
        {
            "category":"Professional",
            "type":"Services"
        }
    ],
    "sg:phone":"+1 323 751 6000",
    "sg:postcode":"91766",
    "sg:province":"CA",
    "wof:name":"F & B Pro Iron Work",
    "wof:placetype":"venue"
},
  "geometry": {"coordinates":[-117.73220600000001,34.047109],"type":"Point"}
}