{
  "type": "Feature",
  "properties": {
    "addr:full":"50 Alessandro Pl Ste 140 Pasadena CA 91105",
    "addr:housenumber":"50",
    "addr:postcode":"91105",
    "addr:street":"Alessandro Pl Ste 140",
    "iso:country":"US",
    "sg:address":"50 Alessandro Pl Ste 140",
    "sg:city":"Pasadena",
    "sg:classifiers":[
        {
            "category":"Health Services",
            "subcategory":"Doctor",
            "type":"Services"
        }
    ],
    "sg:phone":"+1 626 793 0580",
    "sg:postcode":"91105",
    "sg:province":"CA",
    "wof:name":"Sax Barbara F MD",
    "wof:placetype":"venue"
},
  "geometry": {"coordinates":[-118.166,34.136501],"type":"Point"}
}