{
  "type": "Feature",
  "properties": {
    "iso:country":"US",
    "sg:address":"600 S Lake Ave Ste 300",
    "sg:city":"Pasadena",
    "sg:classifiers":[
        {
            "category":"Professional",
            "subcategory":"Accounting & Tax Preparation",
            "type":"Services"
        }
    ],
    "sg:phone":"+1 626 795 0256",
    "sg:postcode":"91106",
    "sg:province":"CA",
    "sg:tags":[
        "accountant"
    ],
    "wof:name":"Willis Thomas L Guill Blankenbaker & Lawson CPA",
    "wof:placetype":"venue"
},
  "geometry": {"coordinates":[-118.13200399999999,34.135502],"type":"Point"}
}