{
  "type": "Feature",
  "properties": {
    "addr:full":"500 State Hwy 1 Davenport CA 95017",
    "addr:housenumber":"500",
    "addr:postcode":"95017",
    "addr:street":"State Hwy 1",
    "iso:country":"US",
    "sg:address":"500 State Hwy 1",
    "sg:city":"Davenport",
    "sg:classifiers":[
        {
            "category":"Government",
            "subcategory":"Post Office",
            "type":"Public Place"
        }
    ],
    "sg:phone":"+1 831 426 9533",
    "sg:postcode":"95017",
    "sg:province":"CA",
    "wof:name":"US Post Office",
    "wof:placetype":"venue"
},
  "geometry": {"coordinates":[-122.195425,37.011359],"type":"Point"}
}