{
  "type": "Feature",
  "properties": {
    "addr:full":"5090 Goldman Ave Moorpark CA 93021",
    "addr:housenumber":"5090",
    "addr:postcode":"ca 93021",
    "addr:street":"Goldman Ave",
    "iso:country":"US",
    "sg:address":"5090 Goldman Ave",
    "sg:city":"Moorpark",
    "sg:classifiers":[
        {
            "category":"Retail",
            "subcategory":"Auto Repair",
            "type":"Services"
        }
    ],
    "sg:phone":"+1 805 529 9529",
    "sg:postcode":"93021",
    "sg:province":"CA",
    "sg:tags":[
        "body",
        "automobile",
        "painting"
    ],
    "wof:name":"Studebaker Services Auto Body",
    "wof:placetype":"venue"
},
  "geometry": {"coordinates":[-118.893242,34.279748],"type":"Point"}
}