{
  "type": "Feature",
  "properties": {
    "addr:full":"1727 Cosmic Way Glendale CA 91201",
    "addr:housenumber":"1727",
    "addr:postcode":"91201",
    "addr:street":"Cosmic Way",
    "iso:country":"US",
    "sg:address":"1727 Cosmic Way",
    "sg:city":"Glendale",
    "sg:classifiers":[
        {
            "category":"Food & Beverages",
            "subcategory":"Specialty",
            "type":"Retail Goods"
        }
    ],
    "sg:phone":"+1 818 790 1776",
    "sg:postcode":"91201",
    "sg:province":"CA",
    "sg:tags":[
        "vitamin"
    ],
    "wof:name":"Health USA",
    "wof:placetype":"venue"
},
  "geometry": {"coordinates":[-118.297748,34.166277],"type":"Point"}
}