{
  "type": "Feature",
  "properties": {
    "addr:full":"17802 Irvine Blvd Ste A121 Tustin CA 92780",
    "addr:housenumber":"17802",
    "addr:postcode":"92780",
    "addr:street":"Irvine Blvd Ste A121",
    "iso:country":"US",
    "sg:address":"17802 Irvine Blvd Ste A121",
    "sg:city":"Tustin",
    "sg:classifiers":[
        {
            "category":"Insurance",
            "subcategory":"Hazard Insurance",
            "type":"Services"
        }
    ],
    "sg:phone":"+1 714 544 2558",
    "sg:postcode":"92780",
    "sg:province":"CA",
    "sg:website":"online2.statefarm.com/b2c/sf/age...",
    "wof:name":"Chris Barr - State Farm Insurance",
    "wof:placetype":"venue"
},
  "geometry": {"coordinates":[-117.82133,33.747966],"type":"Point"}
}