{
  "type": "Feature",
  "properties": {
    "addr:full":"78450 Ave 41 Bermuda Dunes CA 92203",
    "addr:housenumber":"41",
    "addr:postcode":"78450;92203",
    "addr:street":"Ave",
    "iso:country":"US",
    "sg:address":"78450 Ave 41",
    "sg:city":"Bermuda Dunes",
    "sg:classifiers":[
        {
            "category":"Building & Trades",
            "subcategory":"Construction",
            "type":"Services"
        }
    ],
    "sg:phone":"+1 760 772 9459",
    "sg:postcode":"92203",
    "sg:province":"CA",
    "sg:tags":[
        "contractor"
    ],
    "wof:name":"Desert Palms Design & Constr",
    "wof:placetype":"venue"
},
  "geometry": {"coordinates":[-116.29795300000001,33.751032],"type":"Point"}
}