{
  "type": "Feature",
  "properties": {
    "addr:full":"16501 Ventura Boulevard Suite 615 Encino CA 91436",
    "addr:housenumber":"16501",
    "addr:postcode":"91436",
    "addr:street":"Ventura Boulevard Suite 615",
    "iso:country":"US",
    "sg:address":"16501 Ventura Boulevard Suite 615",
    "sg:city":"Encino",
    "sg:classifiers":[
        {
            "category":"Professional",
            "subcategory":"Computer Services",
            "type":"Services"
        }
    ],
    "sg:phone":"+1 818 817 9225",
    "sg:postcode":"91436",
    "sg:province":"CA",
    "sg:website":"http://www.americanlegalnet.com",
    "wof:name":"American LegalNet",
    "wof:placetype":"venue"
},
  "geometry": {"coordinates":[-118.494285,34.15783],"type":"Point"}
}