{
  "type": "Feature",
  "properties": {
    "iso:country":"US",
    "sg:address":"17200 Ventura Blvd # 125",
    "sg:city":"Encino",
    "sg:classifiers":[
        {
            "category":"Real Estate",
            "subcategory":"Real Estate Services",
            "type":"Services"
        },
        {
            "category":"Real Estate",
            "subcategory":"Real Estate Agent",
            "type":"Services"
        }
    ],
    "sg:phone":"+1 818 981 6700",
    "sg:postcode":"91316",
    "sg:province":"CA",
    "sg:tags":[
        "management"
    ],
    "sg:website":"http://www.pacificrealty.com",
    "wof:name":"Pacific Realty Partners",
    "wof:placetype":"venue"
},
  "geometry": {"coordinates":[-118.507623,34.160537],"type":"Point"}
}