{
  "type": "Feature",
  "properties": {
    "addr:full":"100 Castro St Mountain View CA 95035",
    "addr:housenumber":"100",
    "addr:postcode":"95035",
    "addr:street":"Castro St",
    "iso:country":"US",
    "sg:address":"100 Castro St",
    "sg:city":"Mountain View",
    "sg:classifiers":[
        {
            "category":"Taxi",
            "type":"Transportation"
        }
    ],
    "sg:phone":"+1 650 669 0101",
    "sg:postcode":"95035",
    "sg:province":"CA",
    "sg:website":"www.bluecabco.com",
    "wof:name":"Blue Cab Co",
    "wof:placetype":"venue"
},
  "geometry": {"coordinates":[-122.078236,37.3951],"type":"Point"}
}