{
  "type": "Feature",
  "properties": {
    "addr:full":"7424 E Mott Ave Fowler CA 93625",
    "addr:housenumber":"7424",
    "addr:postcode":"93625",
    "addr:street":"E Mott Ave",
    "iso:country":"US",
    "sg:address":"7424 E Mott Ave",
    "sg:city":"Fowler",
    "sg:classifiers":[
        {
            "category":"Farming",
            "subcategory":"Vineyard",
            "type":"Manufacturing & Wholesale Goods"
        }
    ],
    "sg:phone":"+1 559 834 5257",
    "sg:postcode":"93625",
    "sg:province":"CA",
    "sg:tags":[
        "grape"
    ],
    "wof:name":"S & M Mooradian Ranch",
    "wof:placetype":"venue"
},
  "geometry": {"coordinates":[-119.65378200000001,36.623599],"type":"Point"}
}