{
  "type": "Feature",
  "properties": {
    "iso:country":"US",
    "sg:address":"531 W 6th St",
    "sg:city":"Los Angeles",
    "sg:classifiers":[
        {
            "category":"Restaurant",
            "type":"Food & Drink"
        }
    ],
    "sg:phone":"+1 213 624 1288",
    "sg:postcode":"90014",
    "sg:province":"CA",
    "sg:tags":[
        "new",
        "american"
    ],
    "wof:name":"La Baguette",
    "wof:placetype":"venue"
},
  "geometry": {"coordinates":[-118.254504,34.048282],"type":"Point"}
}