{
  "type": "Feature",
  "properties": {
    "addr:full":"1020 Pasadena Ave Fillmore CA 93015",
    "addr:housenumber":"1020",
    "addr:postcode":"93015",
    "addr:street":"Pasadena Ave",
    "iso:country":"US",
    "sg:address":"1020 Pasadena Ave",
    "sg:city":"Fillmore",
    "sg:classifiers":[
        {
            "category":"Farming",
            "subcategory":"Orchard",
            "type":"Manufacturing & Wholesale Goods"
        }
    ],
    "sg:phone":"+1 805 524 4377",
    "sg:postcode":"93015",
    "sg:province":"CA",
    "sg:tags":[
        "citrus",
        "grove",
        "fruit"
    ],
    "wof:name":"Williowgrove Ranch",
    "wof:placetype":"venue"
},
  "geometry": {"coordinates":[-118.922298,34.37509],"type":"Point"}
}