{
  "type": "Feature",
  "properties": {
    "addr:full":"12009 Foundation Pl Gold River CA 95670",
    "addr:housenumber":"12009",
    "addr:postcode":"95670",
    "addr:street":"Foundation Pl",
    "iso:country":"US",
    "sg:address":"12009 Foundation Pl",
    "sg:city":"Gold River",
    "sg:classifiers":[
        {
            "category":"Banks & Credit Unions",
            "subcategory":"Investment Brokerage",
            "type":"Services"
        }
    ],
    "sg:phone":"+1 916 294 4400",
    "sg:postcode":"95670",
    "sg:province":"CA",
    "sg:tags":[
        "consultant",
        "planning",
        "financial"
    ],
    "sg:website":"www.axa-advisors.com",
    "wof:name":"Axa Advisors",
    "wof:placetype":"venue"
},
  "geometry": {"coordinates":[-121.224069,38.627731],"type":"Point"}
}