{
  "type": "Feature",
  "properties": {
    "addr:full":"2910 Stevens Creek Blvd Ste 207 San Jose CA 95128",
    "addr:housenumber":"2910",
    "addr:postcode":"95128",
    "addr:street":"Stevens Creek Blvd Ste 207",
    "iso:country":"US",
    "sg:address":"2910 Stevens Creek Blvd Ste 207",
    "sg:city":"San Jose",
    "sg:classifiers":[
        {
            "category":"Professional",
            "subcategory":"Employment Agencies",
            "type":"Services"
        }
    ],
    "sg:phone":"+1 408 296 8414",
    "sg:postcode":"95128",
    "sg:province":"CA",
    "wof:name":"Adecco Employment Services",
    "wof:placetype":"venue"
},
  "geometry": {"coordinates":[-121.945999,37.323299],"type":"Point"}
}