{
  "type": "Feature",
  "properties": {
    "addr:full":"38750 Sky Canyon Dr Murrieta CA 92563",
    "addr:housenumber":"38750",
    "addr:postcode":"92563",
    "addr:street":"Sky Canyon Dr",
    "iso:country":"US",
    "sg:address":"38750 Sky Canyon Dr",
    "sg:city":"Murrieta",
    "sg:classifiers":[
        {
            "category":"Insurance",
            "subcategory":"Insurance Agent",
            "type":"Services"
        }
    ],
    "sg:phone":"+1 951 698 7337",
    "sg:postcode":"92563",
    "sg:province":"CA",
    "wof:name":"Ward Insurance Svc",
    "wof:placetype":"venue"
},
  "geometry": {"coordinates":[-117.130211,33.580593],"type":"Point"}
}