{
  "type": "Feature",
  "properties": {
    "addr:full":"27102 Manzano Mission Viejo CA 92692",
    "addr:postcode":"27102;92692",
    "iso:country":"US",
    "sg:address":"27102 Manzano",
    "sg:city":"Mission Viejo",
    "sg:classifiers":[
        {
            "category":"Wholesale",
            "subcategory":"Drugs",
            "type":"Manufacturing & Wholesale Goods"
        }
    ],
    "sg:phone":"+1 949 365 0570",
    "sg:postcode":"92692",
    "sg:province":"CA",
    "wof:name":"Bayat Nomad International",
    "wof:placetype":"venue"
},
  "geometry": {"coordinates":[-117.655483,33.567133],"type":"Point"}
}