{
  "type": "Feature",
  "properties": {
    "iso:country":"US",
    "sg:address":"1930 Vine St",
    "sg:city":"Berkeley",
    "sg:classifiers":[
        {
            "category":"Retail",
            "subcategory":"Repair Shop",
            "type":"Services"
        }
    ],
    "sg:phone":"+1 510 528 0224",
    "sg:postcode":"94709",
    "sg:province":"CA",
    "sg:tags":[
        "fix"
    ],
    "wof:name":"Home Talent Maintenance Co",
    "wof:placetype":"venue"
},
  "geometry": {"coordinates":[-122.271663,37.879814],"type":"Point"}
}