{
  "type": "Feature",
  "properties": {
    "addr:full":"32368 Derby St Union City CA 94587",
    "addr:housenumber":"32368",
    "addr:postcode":"94587",
    "addr:street":"Derby St",
    "iso:country":"US",
    "sg:address":"32368 Derby St",
    "sg:city":"Union City",
    "sg:classifiers":[
        {
            "category":"Shopping",
            "subcategory":"Jewelry",
            "type":"Retail Goods"
        }
    ],
    "sg:phone":"+1 510 477 9166",
    "sg:postcode":"94587",
    "sg:province":"CA",
    "wof:name":"Diamond Source",
    "wof:placetype":"venue"
},
  "geometry": {"coordinates":[-122.051928,37.596287],"type":"Point"}
}