{
  "type": "Feature",
  "properties": {
    "addr:full":"14006 Riverside Dr Ste 216 Sherman Oaks CA 91423",
    "addr:housenumber":"14006",
    "addr:postcode":"91423",
    "addr:street":"Riverside Dr Ste 216",
    "iso:country":"US",
    "sg:address":"14006 Riverside Dr Ste 216",
    "sg:city":"Sherman Oaks",
    "sg:classifiers":[
        {
            "category":"Personal",
            "subcategory":"Beauty Salon",
            "type":"Services"
        }
    ],
    "sg:phone":"+1 818 907 5475",
    "sg:postcode":"91423",
    "sg:province":"CA",
    "sg:tags":[
        "hair"
    ],
    "wof:name":"Hair Makeover",
    "wof:placetype":"venue"
},
  "geometry": {"coordinates":[-118.432957,34.156146],"type":"Point"}
}