{
  "type": "Feature",
  "properties": {
    "addr:full":"5642 Armitos Ave Goleta CA 93117",
    "addr:housenumber":"5642",
    "addr:postcode":"93117",
    "addr:street":"Armitos Ave",
    "iso:country":"US",
    "sg:address":"5642 Armitos Ave",
    "sg:city":"Goleta",
    "sg:classifiers":[
        {
            "category":"Building & Trades",
            "subcategory":"Construction",
            "type":"Services"
        }
    ],
    "sg:phone":"+1 805 845 5394",
    "sg:postcode":"93117",
    "sg:province":"CA",
    "sg:tags":[
        "wallcoverings-installation",
        "wallpaper",
        "painting",
        "contractor"
    ],
    "wof:name":"Mark Anthony Rodriguez Painting",
    "wof:placetype":"venue"
},
  "geometry": {"coordinates":[-119.822031,34.438438],"type":"Point"}
}