{
  "type": "Feature",
  "properties": {
    "iso:country":"US",
    "sg:address":"1864 E 1st St",
    "sg:city":"Los Angeles",
    "sg:classifiers":[
        {
            "category":"Travel",
            "subcategory":"Travel Agent",
            "type":"Entertainment"
        }
    ],
    "sg:phone":"+1 323 268 5567",
    "sg:postcode":"90033",
    "sg:province":"CA",
    "sg:tags":[
        "agency"
    ],
    "wof:name":"Mexitours Travel",
    "wof:placetype":"venue"
},
  "geometry": {"coordinates":[-118.217924,34.046723],"type":"Point"}
}