{
  "type": "Feature",
  "properties": {
    "iso:country":"US",
    "sg:address":"4046 Baldwin Ln",
    "sg:city":"Carlsbad",
    "sg:classifiers":[
        {
            "category":"Shopping",
            "subcategory":"Gifts & Souvenirs",
            "type":"Retail Goods"
        }
    ],
    "sg:phone":"+1 760 729 2597",
    "sg:postcode":"92008",
    "sg:province":"CA",
    "wof:name":"La Gallerie De Joy",
    "wof:placetype":"venue"
},
  "geometry": {"coordinates":[-117.33701000000001,33.148815],"type":"Point"}
}