{
  "type": "Feature",
  "properties": {
    "iso:country":"US",
    "sg:address":"317 E Mission Rd",
    "sg:city":"Fallbrook",
    "sg:classifiers":[
        {
            "category":"Taxi",
            "type":"Transportation"
        }
    ],
    "sg:phone":"+1 760 728 9626",
    "sg:postcode":"92028",
    "sg:province":"CA",
    "sg:tags":[
        "taxicab"
    ],
    "wof:name":"Fallbrook Taxi Cab",
    "wof:placetype":"venue"
},
  "geometry": {"coordinates":[-117.248783,33.384533],"type":"Point"}
}