{
  "type": "Feature",
  "properties": {
    "iso:country":"US",
    "sg:address":"95 Enterprise",
    "sg:city":"Aliso Viejo",
    "sg:classifiers":[
        {
            "category":"Manufacturing",
            "subcategory":"Electronics",
            "type":"Manufacturing & Wholesale Goods"
        }
    ],
    "sg:phone":"+1 949 349 1620",
    "sg:postcode":"92656",
    "sg:province":"CA",
    "sg:tags":[
        "semiconductor",
        "related",
        "devices"
    ],
    "wof:name":"Cypress Semiconductor Corp",
    "wof:placetype":"venue"
},
  "geometry": {"coordinates":[-117.726832,33.581454],"type":"Point"}
}