{
  "type": "Feature",
  "properties": {
    "addr:full":"4333 California St San Francisco CA 94118",
    "addr:housenumber":"4333",
    "addr:postcode":"94118",
    "addr:street":"California St",
    "iso:country":"US",
    "sg:address":"4333 California St",
    "sg:city":"San Francisco",
    "sg:classifiers":[
        {
            "category":"Social Services",
            "type":"Services"
        }
    ],
    "sg:phone":"+1 415 978 9105",
    "sg:postcode":"94118",
    "sg:province":"CA",
    "sg:tags":[
        "counselor",
        "marriage",
        "family"
    ],
    "wof:name":"Thompson Peter Mft",
    "wof:placetype":"venue"
},
  "geometry": {"coordinates":[-122.46428400000001,37.784965],"type":"Point"}
}