{
  "type": "Feature",
  "properties": {
    "addr:full":"400 30th St Ste 403 Oakland CA 94609",
    "addr:housenumber":"400",
    "addr:postcode":"94609",
    "addr:street":"30Th St Ste 403",
    "iso:country":"US",
    "sg:address":"400 30th St Ste 403",
    "sg:city":"Oakland",
    "sg:classifiers":[
        {
            "category":"Health Services",
            "subcategory":"Doctor",
            "type":"Services"
        }
    ],
    "sg:phone":"+1 510 832 4197",
    "sg:postcode":"94609",
    "sg:province":"CA",
    "sg:tags":[
        "podiatrist"
    ],
    "wof:name":"Pill Hill Podiatry",
    "wof:placetype":"venue"
},
  "geometry": {"coordinates":[-122.264999,37.819],"type":"Point"}
}