{
  "type": "Feature",
  "properties": {
    "addr:full":"5365 Ensenada Ave Atascadero CA 93422",
    "addr:housenumber":"5365",
    "addr:postcode":"93422",
    "addr:street":"Ensenada Ave",
    "iso:country":"US",
    "sg:address":"5365 Ensenada Ave",
    "sg:city":"Atascadero",
    "sg:classifiers":[
        {
            "category":"Professional",
            "subcategory":"Art Services",
            "type":"Services"
        }
    ],
    "sg:phone":"+1 805 462 0287",
    "sg:postcode":"93422",
    "sg:province":"CA",
    "sg:tags":[
        "commercial",
        "design"
    ],
    "wof:name":"Norfleet Design",
    "wof:placetype":"venue"
},
  "geometry": {"coordinates":[-120.664526,35.497215],"type":"Point"}
}