{
  "type": "Feature",
  "properties": {
    "iso:country":"US",
    "sg:address":"272 Villanova Rd",
    "sg:city":"Costa Mesa",
    "sg:classifiers":[
        {
            "category":"Professional",
            "type":"Services"
        }
    ],
    "sg:phone":"+1 714 546 5267",
    "sg:postcode":"92626",
    "sg:province":"CA",
    "wof:name":"Access Control Inc",
    "wof:placetype":"venue"
},
  "geometry": {"coordinates":[-117.910608,33.661927],"type":"Point"}
}