{
  "type": "Feature",
  "properties": {
    "iso:country":"US",
    "sg:address":"10901 Sherman Way",
    "sg:city":"Sun Valley",
    "sg:classifiers":[
        {
            "category":"Wholesale",
            "subcategory":"Auto Parts",
            "type":"Manufacturing & Wholesale Goods"
        }
    ],
    "sg:phone":"+1 818 765 1300",
    "sg:postcode":"91352",
    "sg:province":"CA",
    "sg:tags":[
        "automobile",
        "wrecking"
    ],
    "wof:name":"Apollo European Auto Parts",
    "wof:placetype":"venue"
},
  "geometry": {"coordinates":[-118.368432,34.201271],"type":"Point"}
}