{
  "type": "Feature",
  "properties": {
    "iso:country":"US",
    "sg:address":"8355 Sahara Rd",
    "sg:city":"Phelan",
    "sg:classifiers":[
        {
            "category":"Professional",
            "subcategory":"Advertising",
            "type":"Services"
        }
    ],
    "sg:phone":"+1 760 868 8886",
    "sg:postcode":"92397",
    "sg:province":"CA",
    "wof:name":"CHEAPRINT.COM",
    "wof:placetype":"venue"
},
  "geometry": {"coordinates":[-117.57049000000001,34.404334],"type":"Point"}
}