{
  "type": "Feature",
  "properties": {
    "iso:country":"US",
    "sg:address":"1788 S San Gabriel Blvd",
    "sg:city":"San Gabriel",
    "sg:classifiers":[
        {
            "category":"Health Services",
            "subcategory":"Doctor",
            "type":"Services"
        }
    ],
    "sg:phone":"+1 626 300 8515",
    "sg:postcode":"91776",
    "sg:province":"CA",
    "sg:tags":[
        "dentist"
    ],
    "wof:name":"Thanh Nguyen-Vu DDS",
    "wof:placetype":"venue"
},
  "geometry": {"coordinates":[-118.0907,34.080008],"type":"Point"}
}