{
  "type": "Feature",
  "properties": {
    "addr:full":"1530 W Winton Ave Hayward CA 94545",
    "addr:housenumber":"1530",
    "addr:postcode":"94545",
    "addr:street":"W Winton Ave",
    "iso:country":"US",
    "sg:address":"1530 W Winton Ave",
    "sg:city":"Hayward",
    "sg:classifiers":[
        {
            "category":"Wholesale",
            "subcategory":"Chemicals & Plastics",
            "type":"Manufacturing & Wholesale Goods"
        }
    ],
    "sg:phone":"+1 510 786 3100",
    "sg:postcode":"94545",
    "sg:province":"CA",
    "wof:name":"Allied Foam Corp",
    "wof:placetype":"venue"
},
  "geometry": {"coordinates":[-122.12201399999999,37.653065],"type":"Point"}
}