{
  "type": "Feature",
  "properties": {
    "iso:country":"US",
    "sg:address":"632 E Ave P",
    "sg:city":"Palmdale",
    "sg:classifiers":[
        {
            "category":"Professional",
            "subcategory":"Computer Services",
            "type":"Services"
        }
    ],
    "sg:phone":"+1 661 274 1888",
    "sg:postcode":"93550",
    "sg:province":"CA",
    "sg:tags":[
        "electronics"
    ],
    "sg:website":"www.ectecinc.com",
    "wof:name":"Ectec Inc",
    "wof:placetype":"venue"
},
  "geometry": {"coordinates":[-118.11950400000001,34.601759],"type":"Point"}
}