{
  "type": "Feature",
  "properties": {
    "iso:country":"US",
    "sg:address":"6735 32nd St",
    "sg:city":"North Highlands",
    "sg:classifiers":[
        {
            "category":"Building & Trades",
            "subcategory":"Construction",
            "type":"Services"
        }
    ],
    "sg:phone":"+1 916 332 1902",
    "sg:postcode":"95660",
    "sg:province":"CA",
    "sg:tags":[
        "contractor"
    ],
    "wof:name":"Kersey Construction Company",
    "wof:placetype":"venue"
},
  "geometry": {"coordinates":[-121.392191,38.691458],"type":"Point"}
}