{
  "type": "Feature",
  "properties": {
    "addr:full":"31650 Riverside Dr Lake Elsinore CA 92530",
    "addr:housenumber":"31650",
    "addr:postcode":"92530",
    "addr:street":"Riverside Dr",
    "iso:country":"US",
    "sg:address":"31650 Riverside Dr",
    "sg:city":"Lake Elsinore",
    "sg:classifiers":[
        {
            "category":"Restaurant",
            "type":"Food & Drink"
        }
    ],
    "sg:menulink":"http://www.allmenus.com/ca/elsinore-valley/178001-jack-in-the-box/menu/",
    "sg:phone":"+1 951 674 7656",
    "sg:postcode":"92530",
    "sg:province":"CA",
    "sg:tags":[
        "burger",
        "american"
    ],
    "wof:name":"Jack in the Box",
    "wof:placetype":"venue"
},
  "geometry": {"coordinates":[-117.371415,33.678341],"type":"Point"}
}