{
  "type": "Feature",
  "properties": {
    "iso:country":"US",
    "sg:address":"21820 Burbank Blvd Ste 155",
    "sg:city":"Woodland Hills",
    "sg:classifiers":[
        {
            "category":"Retail",
            "subcategory":"Portrait Studio",
            "type":"Services"
        }
    ],
    "sg:phone":"+1 818 703 5122",
    "sg:postcode":"91367",
    "sg:province":"CA",
    "sg:tags":[
        "photography",
        "store"
    ],
    "wof:name":"Graphic Computer Services",
    "wof:placetype":"venue"
},
  "geometry": {"coordinates":[-118.603996,34.172298],"type":"Point"}
}