{
  "type": "Feature",
  "properties": {
    "addr:full":"2272 Alisal Rd Salinas CA 93908",
    "addr:postcode":"2272;93908",
    "addr:street":"Alisal Rd",
    "iso:country":"US",
    "sg:address":"2272 Alisal Rd",
    "sg:city":"Salinas",
    "sg:classifiers":[
        {
            "category":"Professional",
            "subcategory":"Advertising",
            "type":"Services"
        }
    ],
    "sg:phone":"+1 831 757 9057",
    "sg:postcode":"93908",
    "sg:province":"CA",
    "sg:tags":[
        "distributing",
        "sample"
    ],
    "wof:name":"Monterey Organics Inc",
    "wof:placetype":"venue"
},
  "geometry": {"coordinates":[-121.57898,36.647854],"type":"Point"}
}