{
  "type": "Feature",
  "properties": {
    "iso:country":"US",
    "sg:address":"2221 Oakland Rd",
    "sg:city":"San Jose",
    "sg:classifiers":[
        {
            "category":"Professional",
            "type":"Services"
        }
    ],
    "sg:phone":"+1 408 456 0993",
    "sg:postcode":"95131",
    "sg:province":"CA",
    "wof:name":"Dubuglo LLC",
    "wof:placetype":"venue"
},
  "geometry": {"coordinates":[-121.902759,37.399689],"type":"Point"}
}