{
  "type": "Feature",
  "properties": {
    "addr:full":"4838 Rolando Blvd San Diego CA 92115",
    "addr:housenumber":"4838",
    "addr:postcode":"92115",
    "addr:street":"Rolando Blvd",
    "iso:country":"US",
    "sg:address":"4838 Rolando Blvd",
    "sg:city":"San Diego",
    "sg:classifiers":[
        {
            "category":"Arts & Performance",
            "subcategory":"Art Gallery",
            "type":"Entertainment"
        }
    ],
    "sg:phone":"+1 619 582 0434",
    "sg:postcode":"92115",
    "sg:province":"CA",
    "sg:website":"www.tribaldecor.com",
    "wof:name":"Tribal Hut",
    "wof:placetype":"venue"
},
  "geometry": {"coordinates":[-117.056999,32.766899],"type":"Point"}
}