{
  "type": "Feature",
  "properties": {
    "iso:country":"US",
    "sg:address":"1635 E 23rd St",
    "sg:city":"Los Angeles",
    "sg:classifiers":[
        {
            "category":"Shopping",
            "subcategory":"Clothing, Apparel, & Fashions",
            "type":"Retail Goods"
        }
    ],
    "sg:phone":"+1 213 746 6256",
    "sg:postcode":"90011",
    "sg:province":"CA",
    "sg:tags":[
        "handbag"
    ],
    "wof:name":"Four Seasons Handbags",
    "wof:placetype":"venue"
},
  "geometry": {"coordinates":[-118.244068,34.016044],"type":"Point"}
}