{
  "type": "Feature",
  "properties": {
    "iso:country":"US",
    "sg:address":"4840 Irvine Blvd",
    "sg:city":"Irvine",
    "sg:classifiers":[
        {
            "category":"Wholesale",
            "subcategory":"Stationery",
            "type":"Manufacturing & Wholesale Goods"
        }
    ],
    "sg:phone":"+1 714 734 8780",
    "sg:postcode":"92620",
    "sg:province":"CA",
    "sg:tags":[
        "r",
        "supply"
    ],
    "wof:name":"Learning Trails",
    "wof:placetype":"venue"
},
  "geometry": {"coordinates":[-117.759777,33.713696],"type":"Point"}
}