{
  "type": "Feature",
  "properties": {
    "addr:full":"17770 Rowland St Rowland Heights CA 91748",
    "addr:housenumber":"17770",
    "addr:postcode":"91748",
    "addr:street":"Rowland St",
    "iso:country":"US",
    "sg:address":"17770 Rowland St",
    "sg:city":"Rowland Heights",
    "sg:classifiers":[
        {
            "category":"Shopping",
            "type":"Retail Goods"
        }
    ],
    "sg:phone":"+1 626 965 4958",
    "sg:postcode":"91748",
    "sg:province":"CA",
    "sg:tags":[
        "plastic"
    ],
    "wof:name":"Tru Form Plastics",
    "wof:placetype":"venue"
},
  "geometry": {"coordinates":[-117.92073499999999,34.001699],"type":"Point"}
}