{
  "type": "Feature",
  "properties": {
    "iso:country":"US",
    "sg:address":"200 Oracle Parkway",
    "sg:city":"Redwood Shores",
    "sg:classifiers":[
        {
            "category":"Restaurant",
            "type":"Food & Drink"
        }
    ],
    "sg:postcode":"94061",
    "sg:province":"CA",
    "wof:name":"Oracle Cafe 200",
    "wof:placetype":"venue"
},
  "geometry": {"coordinates":[-122.265429,37.529927],"type":"Point"}
}