{
  "type": "Feature",
  "properties": {
    "addr:full":"22785 Main St Hayward CA 94541",
    "addr:housenumber":"22785",
    "addr:postcode":"94541",
    "addr:street":"Main St",
    "iso:country":"US",
    "sg:address":"22785 Main St",
    "sg:city":"Hayward",
    "sg:classifiers":[
        {
            "category":"Personal",
            "subcategory":"Beauty Salon",
            "type":"Services"
        }
    ],
    "sg:phone":"+1 510 889 5893",
    "sg:postcode":"94541",
    "sg:province":"CA",
    "sg:tags":[
        "manicuring"
    ],
    "wof:name":"Beautiful Nails",
    "wof:placetype":"venue"
},
  "geometry": {"coordinates":[-122.08038999999999,37.670285],"type":"Point"}
}