{
  "type": "Feature",
  "properties": {
    "addr:full":"9025 Wilshire Blvd Beverly Hills CA 90211",
    "addr:housenumber":"9025",
    "addr:postcode":"90211",
    "addr:street":"Wilshire Blvd",
    "iso:country":"US",
    "sg:address":"9025 Wilshire Blvd",
    "sg:city":"Beverly Hills",
    "sg:classifiers":[
        {
            "category":"Professional",
            "subcategory":"Lawyer & Legal Services",
            "type":"Services"
        }
    ],
    "sg:phone":"+1 310 550 9999",
    "sg:postcode":"90211",
    "sg:province":"CA",
    "sg:tags":[
        "attorney"
    ],
    "wof:name":"Kharrazi & Assoc",
    "wof:placetype":"venue"
},
  "geometry": {"coordinates":[-118.387811,34.067121],"type":"Point"}
}