{
  "type": "Feature",
  "properties": {
    "addr:full":"244 N Glenoaks Blvd Burbank CA 91502",
    "addr:housenumber":"244",
    "addr:postcode":"91502",
    "addr:street":"N Glenoaks Blvd",
    "iso:country":"US",
    "sg:address":"244 N Glenoaks Blvd",
    "sg:city":"Burbank",
    "sg:classifiers":[
        {
            "category":"Personal",
            "subcategory":"Beauty Salon",
            "type":"Services"
        }
    ],
    "sg:phone":"+1 818 848 3787",
    "sg:postcode":"91502",
    "sg:province":"CA",
    "wof:name":"Classic Hair & Nail Studio",
    "wof:placetype":"venue"
},
  "geometry": {"coordinates":[-118.307357,34.184041],"type":"Point"}
}