{
  "type": "Feature",
  "properties": {
    "addr:full":"9430 Topanga Canyon Blvd Chatsworth CA 91311",
    "addr:housenumber":"9430",
    "addr:postcode":"91311",
    "addr:street":"Topanga Canyon Blvd",
    "iso:country":"US",
    "sg:address":"9430 Topanga Canyon Blvd",
    "sg:city":"Chatsworth",
    "sg:classifiers":[
        {
            "category":"Insurance",
            "subcategory":"Insurance Agent",
            "type":"Services"
        }
    ],
    "sg:phone":"+1 818 576 0162",
    "sg:postcode":"91311",
    "sg:province":"CA",
    "wof:name":"Dunfield Inc",
    "wof:placetype":"venue"
},
  "geometry": {"coordinates":[-118.60593,34.23969],"type":"Point"}
}