{
  "type": "Feature",
  "properties": {
    "addr:full":"597 N Tustin St Orange CA 92867",
    "addr:housenumber":"597",
    "addr:postcode":"92867",
    "addr:street":"N Tustin St",
    "iso:country":"US",
    "sg:address":"597 N Tustin St",
    "sg:city":"Orange",
    "sg:classifiers":[
        {
            "category":"Shopping",
            "subcategory":"Clothing, Apparel, & Fashions",
            "type":"Retail Goods"
        }
    ],
    "sg:phone":"+1 714 516 9965",
    "sg:postcode":"92867",
    "sg:province":"CA",
    "sg:tags":[
        "baby",
        "accessory"
    ],
    "wof:name":"Rita's Children & Baby Store",
    "wof:placetype":"venue"
},
  "geometry": {"coordinates":[-117.835589,33.796574],"type":"Point"}
}