{
  "type": "Feature",
  "properties": {
    "iso:country":"US",
    "sg:address":"312 Main St",
    "sg:city":"Red Bluff",
    "sg:classifiers":[
        {
            "category":"Retail",
            "subcategory":"Car Wash",
            "type":"Services"
        }
    ],
    "sg:phone":"+1 530 527 9274",
    "sg:postcode":"96080",
    "sg:province":"CA",
    "sg:tags":[
        "polishing",
        "washing"
    ],
    "wof:name":"Red Bluff Car Wash & Detail",
    "wof:placetype":"venue"
},
  "geometry": {"coordinates":[-122.23252100000001,40.174805],"type":"Point"}
}