{
  "type": "Feature",
  "properties": {
    "addr:full":"3035 Prospect Park Dr Rancho Cordova CA 95670",
    "addr:housenumber":"3035",
    "addr:postcode":"95670",
    "addr:street":"Prospect Park Dr",
    "iso:country":"US",
    "sg:address":"3035 Prospect Park Dr",
    "sg:city":"Rancho Cordova",
    "sg:classifiers":[
        {
            "category":"Banks & Credit Unions",
            "subcategory":"Bank",
            "type":"Services"
        }
    ],
    "sg:phone":"+1 916 851 6800",
    "sg:postcode":"95670",
    "sg:province":"CA",
    "sg:tags":[
        "commercial"
    ],
    "wof:name":"Bridge Bank Of Silicon Valley",
    "wof:placetype":"venue"
},
  "geometry": {"coordinates":[-121.276293,38.591809],"type":"Point"}
}