{
  "type": "Feature",
  "properties": {
    "addr:full":"275 Shoreline Drive Suite 400 Redwood City CA",
    "addr:housenumber":"275",
    "addr:street":"Shoreline Drive Suite 400",
    "iso:country":"US",
    "sg:address":"275 Shoreline Drive Suite 400",
    "sg:city":"Redwood City",
    "sg:classifiers":[
        {
            "category":"Professional",
            "subcategory":"Computer Services",
            "type":"Services"
        }
    ],
    "sg:phone":"+1 650 264 2000",
    "sg:province":"CA",
    "sg:tags":[
        "mobilepayment"
    ],
    "sg:website":"http://obopay.com",
    "wof:name":"obopay",
    "wof:placetype":"venue"
},
  "geometry": {"coordinates":[-122.26067500000001,37.522442],"type":"Point"}
}