{
  "type": "Feature",
  "properties": {
    "addr:full":"41958 Juniper St Murrieta CA 92562",
    "addr:housenumber":"41958",
    "addr:postcode":"92562",
    "addr:street":"Juniper St",
    "iso:country":"US",
    "sg:address":"41958 Juniper St",
    "sg:city":"Murrieta",
    "sg:classifiers":[
        {
            "category":"Shopping",
            "type":"Retail Goods"
        }
    ],
    "sg:phone":"+1 951 894 6262",
    "sg:postcode":"92562",
    "sg:province":"CA",
    "sg:tags":[
        "merchandise"
    ],
    "wof:name":"A Little Shoppe Downtown",
    "wof:placetype":"venue"
},
  "geometry": {"coordinates":[-117.213369,33.554157],"type":"Point"}
}