{
  "type": "Feature",
  "properties": {
    "iso:country":"US",
    "sg:address":"5455 Wilshire Blvd",
    "sg:city":"Los Angeles",
    "sg:classifiers":[
        {
            "category":"Social Services",
            "type":"Services"
        }
    ],
    "sg:phone":"+1 323 931 6577",
    "sg:postcode":"90036",
    "sg:province":"CA",
    "sg:tags":[
        "counseling",
        "genetic"
    ],
    "sg:website":"www.cureautismnow.org",
    "wof:name":"AGRE",
    "wof:placetype":"venue"
},
  "geometry": {"coordinates":[-118.348189,34.062328],"type":"Point"}
}