{
  "type": "Feature",
  "properties": {
    "iso:country":"US",
    "sg:address":"1809 1/2 Lomita Blvd",
    "sg:city":"Lomita",
    "sg:classifiers":[
        {
            "category":"Health Services",
            "subcategory":"Dentist",
            "type":"Services"
        }
    ],
    "sg:phone":"+1 310 539 1224",
    "sg:postcode":"90717",
    "sg:province":"CA",
    "wof:name":"Abelita Leo C DDS",
    "wof:placetype":"venue"
},
  "geometry": {"coordinates":[-118.309271,33.798575],"type":"Point"}
}