{
  "type": "Feature",
  "properties": {
    "iso:country":"US",
    "sg:address":"5163 W Plain Field Dr",
    "sg:city":"Banning",
    "sg:classifiers":[
        {
            "category":"Building & Trades",
            "subcategory":"Construction",
            "type":"Services"
        }
    ],
    "sg:phone":"+1 951 845 2625",
    "sg:postcode":"92220",
    "sg:province":"CA",
    "sg:tags":[
        "insulation",
        "roofing",
        "contractor"
    ],
    "wof:name":"Affordable Roofing",
    "wof:placetype":"venue"
},
  "geometry": {"coordinates":[-116.93605100000001,33.920082],"type":"Point"}
}