{
  "type": "Feature",
  "properties": {
    "addr:full":"973 Jade Dr Ventura CA 93004",
    "addr:housenumber":"973",
    "addr:postcode":"93004",
    "addr:street":"Jade Dr",
    "iso:country":"US",
    "sg:address":"973 Jade Dr",
    "sg:city":"Ventura",
    "sg:classifiers":[
        {
            "category":"Building & Trades",
            "subcategory":"Plumbing",
            "type":"Services"
        }
    ],
    "sg:phone":"+1 805 659 2611",
    "sg:postcode":"93004",
    "sg:province":"CA",
    "sg:tags":[
        "plumbing",
        "contractor"
    ],
    "wof:name":"Traditional Plumbing & Rooter",
    "wof:placetype":"venue"
},
  "geometry": {"coordinates":[-119.181225,34.270999],"type":"Point"}
}