{
  "type": "Feature",
  "properties": {
    "addr:full":"995 Market St Ste 1450 San Francisco CA 94103",
    "addr:housenumber":"995",
    "addr:postcode":"94103",
    "addr:street":"Market St Ste 1450",
    "iso:country":"US",
    "sg:address":"995 Market St Ste 1450",
    "sg:city":"San Francisco",
    "sg:classifiers":[
        {
            "category":"Government",
            "subcategory":"City Hall",
            "type":"Public Place"
        },
        {
            "category":"Recreation",
            "type":"Entertainment"
        }
    ],
    "sg:phone":"+1 415 431 9255",
    "sg:postcode":"94103",
    "sg:province":"CA",
    "sg:tags":[
        "active",
        "life"
    ],
    "sg:website":"www.walksf.org",
    "wof:name":"Walk San Francisco",
    "wof:placetype":"venue"
},
  "geometry": {"coordinates":[-122.410076,37.782248],"type":"Point"}
}