{
  "type": "Feature",
  "properties": {
    "iso:country":"US",
    "sg:address":"1815 Hawthorne Boulevard",
    "sg:city":"Redondo Beach",
    "sg:classifiers":[
        {
            "category":"Health Services",
            "subcategory":"Doctor",
            "type":"Services"
        }
    ],
    "sg:phone":"+1 310 542 4204",
    "sg:postcode":"90278",
    "sg:province":"CA",
    "sg:tags":[
        "dermatologist"
    ],
    "wof:name":"Lumity Medspa",
    "wof:placetype":"venue"
},
  "geometry": {"coordinates":[-118.35269099999999,33.870689],"type":"Point"}
}