{
  "type": "Feature",
  "properties": {
    "addr:full":"1521 W Collins Ave Orange CA 92867",
    "addr:housenumber":"1521",
    "addr:postcode":"92867",
    "addr:street":"W Collins Ave",
    "iso:country":"US",
    "sg:address":"1521 W Collins Ave",
    "sg:city":"Orange",
    "sg:classifiers":[
        {
            "category":"Wholesale",
            "subcategory":"Durable Goods & Equipment",
            "type":"Manufacturing & Wholesale Goods"
        }
    ],
    "sg:phone":"+1 714 288 9563",
    "sg:postcode":"92867",
    "sg:province":"CA",
    "wof:name":"Praxis Instruments",
    "wof:placetype":"venue"
},
  "geometry": {"coordinates":[-117.86981400000001,33.802492],"type":"Point"}
}