{
  "type": "Feature",
  "properties": {
    "iso:country":"US",
    "sg:address":"2900 Airport Ave",
    "sg:city":"Santa Monica",
    "sg:classifiers":[
        {
            "category":"Professional",
            "type":"Services"
        }
    ],
    "sg:phone":"+1 310 390 7470",
    "sg:postcode":"90405",
    "sg:province":"CA",
    "sg:tags":[
        "establishment"
    ],
    "wof:name":"Lantic USA",
    "wof:placetype":"venue"
},
  "geometry": {"coordinates":[-118.450011,34.01373],"type":"Point"}
}