{
  "type": "Feature",
  "properties": {
    "addr:full":"1184 Koch Ln San Jose CA 95125",
    "addr:housenumber":"1184",
    "addr:postcode":"95125",
    "addr:street":"Koch Ln",
    "iso:country":"US",
    "sg:address":"1184 Koch Ln",
    "sg:city":"San Jose",
    "sg:classifiers":[
        {
            "category":"Banks & Credit Unions",
            "subcategory":"Bank",
            "type":"Services"
        }
    ],
    "sg:phone":"+1 408 723 0379",
    "sg:postcode":"95125",
    "sg:province":"CA",
    "sg:tags":[
        "loan",
        "real estate"
    ],
    "wof:name":"Pekiti-Tirsig KALI West Coast",
    "wof:placetype":"venue"
},
  "geometry": {"coordinates":[-121.883922,37.282197],"type":"Point"}
}