{
  "type": "Feature",
  "properties": {
    "addr:full":"255 Guthrie Ln Brentwood CA 94513",
    "addr:housenumber":"255",
    "addr:postcode":"94513",
    "addr:street":"Guthrie Ln",
    "iso:country":"US",
    "sg:address":"255 Guthrie Ln",
    "sg:city":"Brentwood",
    "sg:classifiers":[
        {
            "category":"Education",
            "subcategory":"School",
            "type":"Public Place"
        }
    ],
    "sg:phone":"+1 925 513 6300",
    "sg:postcode":"94513",
    "sg:province":"CA",
    "wof:name":"Brentwood Union School District",
    "wof:placetype":"venue"
},
  "geometry": {"coordinates":[-121.68285299999999,37.922471],"type":"Point"}
}