{
  "type": "Feature",
  "properties": {
    "addr:full":"1578 Naglee Ave San Jose CA 95126",
    "addr:housenumber":"1578",
    "addr:postcode":"95126",
    "addr:street":"Naglee Ave",
    "iso:country":"US",
    "sg:address":"1578 Naglee Ave",
    "sg:city":"San Jose",
    "sg:classifiers":[
        {
            "category":"Recreation",
            "subcategory":"Playground",
            "type":"Entertainment"
        }
    ],
    "sg:postcode":"95126",
    "sg:province":"CA",
    "sg:website":"www.sjparks.org/Parks/hester.asp",
    "wof:name":"Hester Park",
    "wof:placetype":"venue"
},
  "geometry": {"coordinates":[-121.926534,37.332041],"type":"Point"}
}