{
  "type": "Feature",
  "properties": {
    "iso:country":"US",
    "sg:address":"2896 Canterbury Cir",
    "sg:city":"El Dorado Hills",
    "sg:classifiers":[
        {
            "category":"Social Services",
            "subcategory":"Adult Care",
            "type":"Services"
        }
    ],
    "sg:phone":"+1 916 933 0107",
    "sg:postcode":"95762",
    "sg:province":"CA",
    "sg:tags":[
        "home",
        "residential"
    ],
    "wof:name":"Oakridge Senior Care",
    "wof:placetype":"venue"
},
  "geometry": {"coordinates":[-121.079289,38.68949],"type":"Point"}
}