{
  "type": "Feature",
  "properties": {
    "addr:full":"168 Solana Hills Dr Solana Beach CA 92075",
    "addr:housenumber":"168",
    "addr:postcode":"92075",
    "addr:street":"Solana Hills Dr",
    "iso:country":"US",
    "sg:address":"168 Solana Hills Dr",
    "sg:city":"Solana Beach",
    "sg:classifiers":[
        {
            "category":"Professional",
            "subcategory":"Business Services",
            "type":"Services"
        }
    ],
    "sg:phone":"+1 858 755 4755",
    "sg:postcode":"92075",
    "sg:province":"CA",
    "sg:tags":[
        "interior",
        "consultant",
        "design",
        "decorator"
    ],
    "wof:name":"Designs Of The Interior",
    "wof:placetype":"venue"
},
  "geometry": {"coordinates":[-117.258661,32.995282],"type":"Point"}
}