{
  "type": "Feature",
  "properties": {
    "addr:full":"1231 Manchester Dr El Dorado Hills CA 95762",
    "addr:housenumber":"1231",
    "addr:postcode":"95762",
    "addr:street":"Manchester Dr",
    "iso:country":"US",
    "sg:address":"1231 Manchester Dr",
    "sg:city":"El Dorado Hills",
    "sg:classifiers":[
        {
            "category":"Shopping",
            "subcategory":"Catalog Store",
            "type":"Retail Goods"
        }
    ],
    "sg:phone":"+1 916 933 9838",
    "sg:postcode":"95762",
    "sg:province":"CA",
    "sg:tags":[
        "mail",
        "house"
    ],
    "wof:name":"Home Learners Catalog",
    "wof:placetype":"venue"
},
  "geometry": {"coordinates":[-121.074844,38.642081],"type":"Point"}
}