{
  "type": "Feature",
  "properties": {
    "iso:country":"US",
    "sg:address":"Acupuncture & Integrative Medicine College, Berkeley 2550 Shattuck Ave",
    "sg:city":"Berkeley",
    "sg:classifiers":[
        {
            "category":"Health Services",
            "subcategory":"Health Practitioner",
            "type":"Services"
        }
    ],
    "sg:phone":"+1 510 381 4023",
    "sg:postcode":"94704",
    "sg:province":"CA",
    "sg:tags":[
        "acupuncture"
    ],
    "sg:website":"www.mellyacupuncture.com",
    "wof:name":"David Melly, LAc -- Licensed Acupuncturist",
    "wof:placetype":"venue"
},
  "geometry": {"coordinates":[-122.267354,37.862916],"type":"Point"}
}