{
  "type": "Feature",
  "properties": {
    "addr:full":"655 Lucille Ave Coalinga CA 93210",
    "addr:housenumber":"655",
    "addr:postcode":"93210",
    "addr:street":"Lucille Ave",
    "iso:country":"US",
    "sg:address":"655 Lucille Ave",
    "sg:city":"Coalinga",
    "sg:classifiers":[
        {
            "category":"Real Estate",
            "subcategory":"Real Estate Operator",
            "type":"Services"
        }
    ],
    "sg:phone":"+1 559 934 0190",
    "sg:postcode":"93210",
    "sg:province":"CA",
    "sg:tags":[
        "apartment"
    ],
    "wof:name":"Casa Monterey Apartments",
    "wof:placetype":"venue"
},
  "geometry": {"coordinates":[-120.372195,36.129313],"type":"Point"}
}