{
  "type": "Feature",
  "properties": {
    "addr:full":"1605 N Akers St Visalia CA 93291",
    "addr:housenumber":"1605",
    "addr:postcode":"93291",
    "addr:street":"N Akers St",
    "iso:country":"US",
    "sg:address":"1605 N Akers St",
    "sg:city":"Visalia",
    "sg:classifiers":[
        {
            "category":"Organizations",
            "subcategory":"Professional Association",
            "type":"Services"
        }
    ],
    "sg:phone":"+1 559 625 1900",
    "sg:postcode":"93291",
    "sg:province":"CA",
    "wof:name":"Lakes Homeowners Assn-Visalia",
    "wof:placetype":"venue"
},
  "geometry": {"coordinates":[-119.35006,36.346537],"type":"Point"}
}