{
  "type": "Feature",
  "properties": {
    "addr:full":"2189 E Taylor St Stockton CA 95205",
    "addr:housenumber":"2189",
    "addr:postcode":"95205",
    "addr:street":"E Taylor St",
    "iso:country":"US",
    "sg:address":"2189 E Taylor St",
    "sg:city":"Stockton",
    "sg:classifiers":[
        {
            "category":"Real Estate",
            "subcategory":"Real Estate Operator",
            "type":"Services"
        }
    ],
    "sg:phone":"+1 209 464 3911",
    "sg:postcode":"95205",
    "sg:province":"CA",
    "sg:tags":[
        "mobile",
        "home",
        "site"
    ],
    "wof:name":"Bentley Trailer Park",
    "wof:placetype":"venue"
},
  "geometry": {"coordinates":[-121.25852999999999,37.951255],"type":"Point"}
}