{
  "type": "Feature",
  "properties": {
    "iso:country":"US",
    "sg:address":"1718 Redwood Hwy",
    "sg:city":"Corte Madera",
    "sg:classifiers":[
        {
            "category":"Shopping",
            "subcategory":"Gifts & Souvenirs",
            "type":"Retail Goods"
        }
    ],
    "sg:phone":"+1 415 924 9170",
    "sg:postcode":"94925",
    "sg:province":"CA",
    "sg:tags":[
        "shop"
    ],
    "sg:website":"www.brookstone.com",
    "wof:name":"Brookstone Inc",
    "wof:placetype":"venue"
},
  "geometry": {"coordinates":[-122.51599,37.93412],"type":"Point"}
}