{
  "type": "Feature",
  "properties": {
    "addr:full":"901 Franklin St Oakland CA 94607",
    "addr:housenumber":"901",
    "addr:postcode":"94607",
    "addr:street":"Franklin St",
    "iso:country":"US",
    "sg:address":"901 Franklin St",
    "sg:city":"Oakland",
    "sg:classifiers":[
        {
            "category":"Banks & Credit Unions",
            "subcategory":"Financial Services",
            "type":"Services"
        }
    ],
    "sg:phone":"+1 510 272 1153",
    "sg:postcode":"94607",
    "sg:province":"CA",
    "sg:tags":[
        "broker",
        "mortgage"
    ],
    "wof:name":"Wells Fargo Home Mortgage",
    "wof:placetype":"venue"
},
  "geometry": {"coordinates":[-122.272237,37.800491],"type":"Point"}
}