{
  "type": "Feature",
  "properties": {
    "iso:country":"US",
    "sg:address":"12505 Lambert Rd",
    "sg:city":"Whittier",
    "sg:classifiers":[
        {
            "category":"Wholesale",
            "subcategory":"Medical Equipment & Supplies",
            "type":"Manufacturing & Wholesale Goods"
        }
    ],
    "sg:phone":"+1 562 698 0266",
    "sg:postcode":"90606",
    "sg:province":"CA",
    "sg:tags":[
        "physician",
        "surgeon"
    ],
    "wof:name":"AME-American Medical Ents Inc",
    "wof:placetype":"venue"
},
  "geometry": {"coordinates":[-118.0467,33.96514],"type":"Point"}
}