{
  "type": "Feature",
  "properties": {
    "addr:full":"990 Industrial Way San Luis Obispo CA 93401",
    "addr:housenumber":"990",
    "addr:postcode":"93401",
    "addr:street":"Industrial Way",
    "iso:country":"US",
    "sg:address":"990 Industrial Way",
    "sg:city":"San Luis Obispo",
    "sg:classifiers":[
        {
            "category":"Bars & Pubs",
            "type":"Food & Drink"
        }
    ],
    "sg:phone":"+1 805 541 0700",
    "sg:postcode":"93401",
    "sg:province":"CA",
    "sg:tags":[
        "club",
        "grill",
        "fast",
        "night"
    ],
    "wof:name":"Wildcat House",
    "wof:placetype":"venue"
},
  "geometry": {"coordinates":[-120.643686,35.251185],"type":"Point"}
}