{
  "type": "Feature",
  "properties": {
    "addr:full":"861 Parkside Dr El Sobrante CA 94803",
    "addr:housenumber":"861",
    "addr:postcode":"94803",
    "addr:street":"Parkside Dr El Sobrante",
    "iso:country":"US",
    "sg:address":"861 Parkside Dr",
    "sg:city":"El Sobrante",
    "sg:classifiers":[
        {
            "category":"Travel",
            "subcategory":"Travel Agent",
            "type":"Entertainment"
        }
    ],
    "sg:phone":"+1 510 223 2315",
    "sg:postcode":"94803",
    "sg:province":"CA",
    "sg:tags":[
        "cruise"
    ],
    "wof:name":"Dotto Enterprises",
    "wof:placetype":"venue"
},
  "geometry": {"coordinates":[-122.313766,37.977687],"type":"Point"}
}