{
  "type": "Feature",
  "properties": {
    "iso:country":"US",
    "sg:address":"1375 W Northgrand Ave",
    "sg:city":"Porterville",
    "sg:classifiers":[
        {
            "category":"Education",
            "subcategory":"Dance Studio",
            "type":"Public Place"
        }
    ],
    "sg:phone":"+1 559 781 2158",
    "sg:postcode":"93257",
    "sg:province":"CA",
    "sg:tags":[
        "instruction",
        "dancing"
    ],
    "wof:name":"Deenie's Dance Workshop",
    "wof:placetype":"venue"
},
  "geometry": {"coordinates":[-119.048734,36.098243],"type":"Point"}
}