{
  "type": "Feature",
  "properties": {
    "addr:full":"8807 Ave 384 Dinuba CA 93618",
    "addr:housenumber":"8807",
    "addr:postcode":"93618",
    "addr:street":"Ave 384",
    "iso:country":"US",
    "sg:address":"8807 Ave 384",
    "sg:city":"Dinuba",
    "sg:phone":"+1 559 591 2706",
    "sg:postcode":"93618",
    "sg:province":"CA",
    "sg:tags":[
        "wheat",
        "farm",
        "cash",
        "crop",
        "field",
        "grain",
        "cotton"
    ],
    "wof:name":"David M & Mark A Terry Ranch",
    "wof:placetype":"venue"
},
  "geometry": {"coordinates":[-119.376548,36.487581],"type":"Point"}
}