{
  "type": "Feature",
  "properties": {
    "addr:full":"3760 Rafferty Cir Corona CA 92882",
    "addr:housenumber":"3760",
    "addr:postcode":"92882",
    "addr:street":"Rafferty Cir",
    "iso:country":"US",
    "sg:address":"3760 Rafferty Cir",
    "sg:city":"Corona",
    "sg:classifiers":[
        {
            "category":"Health Services",
            "subcategory":"Doctor",
            "type":"Services"
        }
    ],
    "sg:phone":"+1 951 279 2344",
    "sg:postcode":"92882",
    "sg:province":"CA",
    "sg:tags":[
        "medical",
        "imaging"
    ],
    "wof:name":"C & M Medical Imaging",
    "wof:placetype":"venue"
},
  "geometry": {"coordinates":[-117.582601,33.834383],"type":"Point"}
}