{
  "type": "Feature",
  "properties": {
    "iso:country":"US",
    "sg:address":"920 Eaton Ave",
    "sg:city":"Hemet",
    "sg:classifiers":[
        {
            "category":"Shopping",
            "subcategory":"Computers & Home Electronics",
            "type":"Retail Goods"
        }
    ],
    "sg:phone":"+1 818 435 1368",
    "sg:postcode":"92543",
    "sg:province":"CA",
    "sg:tags":[
        "software"
    ],
    "wof:name":"Dolphin Imaging",
    "wof:placetype":"venue"
},
  "geometry": {"coordinates":[-117.014053,33.765471],"type":"Point"}
}