{
  "type": "Feature",
  "properties": {
    "iso:country":"US",
    "sg:address":"12021 W Pico Blvd",
    "sg:city":"Los Angeles",
    "sg:classifiers":[
        {
            "category":"Cafe",
            "type":"Food & Drink"
        },
        {
            "category":"Restaurant",
            "type":"Food & Drink"
        }
    ],
    "sg:menulink":"http://www.allmenus.com/ca/los-angeles/20799-bombay-cafe/menu/",
    "sg:phone":"+1 310 473 3388",
    "sg:postcode":"90064",
    "sg:province":"CA",
    "sg:tags":[
        "indian",
        "asian"
    ],
    "wof:name":"Bombay Cafe",
    "wof:placetype":"venue"
},
  "geometry": {"coordinates":[-118.449437,34.029785],"type":"Point"}
}