{
  "type": "Feature",
  "properties": {
    "iso:country":"US",
    "sg:address":"815 4th St",
    "sg:city":"Jackson",
    "sg:classifiers":[
        {
            "category":"Health Services",
            "subcategory":"Doctor",
            "type":"Services"
        }
    ],
    "sg:phone":"+1 209 223 2795",
    "sg:postcode":"95616",
    "sg:province":"CA",
    "sg:tags":[
        "physician",
        "surgeon"
    ],
    "wof:name":"Nicholas P Kovacevich MD",
    "wof:placetype":"venue"
},
  "geometry": {"coordinates":[-121.739185,38.546348],"type":"Point"}
}