{
  "type": "Feature",
  "properties": {
    "addr:full":"36 Quail Run Cir Salinas CA 93907",
    "addr:housenumber":"36",
    "addr:postcode":"93907",
    "addr:street":"Quail Run Cir",
    "iso:country":"US",
    "sg:address":"36 Quail Run Cir",
    "sg:city":"Salinas",
    "sg:classifiers":[
        {
            "category":"Manufacturing",
            "subcategory":"Tools & Machinery",
            "type":"Manufacturing & Wholesale Goods"
        }
    ],
    "sg:phone":"+1 831 757 7272",
    "sg:postcode":"93907",
    "sg:province":"CA",
    "sg:tags":[
        "mfg",
        "printing",
        "trade"
    ],
    "wof:name":"American Performage Cartridge",
    "wof:placetype":"venue"
},
  "geometry": {"coordinates":[-121.669916,36.686038],"type":"Point"}
}