{
  "type": "Feature",
  "properties": {
    "iso:country":"US",
    "sg:address":"610 Newport Center Dr",
    "sg:city":"Newport Beach",
    "sg:classifiers":[
        {
            "category":"Banks & Credit Unions",
            "subcategory":"Investment Brokerage",
            "type":"Services"
        }
    ],
    "sg:phone":"+1 949 000 1111",
    "sg:postcode":"92660",
    "sg:province":"CA",
    "sg:tags":[
        "stock",
        "bond"
    ],
    "wof:name":"Charles Schwab & Co",
    "wof:placetype":"venue"
},
  "geometry": {"coordinates":[-117.873126,33.61841],"type":"Point"}
}