{
  "type": "Feature",
  "properties": {
    "iso:country":"US",
    "sg:address":"8316 Clairemont Mesa Blvd",
    "sg:city":"San Diego",
    "sg:classifiers":[
        {
            "category":"Shopping",
            "subcategory":"Gifts & Souvenirs",
            "type":"Retail Goods"
        }
    ],
    "sg:phone":"+1 858 505 0249",
    "sg:postcode":"92117",
    "sg:province":"CA",
    "sg:tags":[
        "balloon",
        "artist"
    ],
    "wof:name":"Balloons By Tony",
    "wof:placetype":"venue"
},
  "geometry": {"coordinates":[-117.14862100000001,32.832843],"type":"Point"}
}