{
  "type": "Feature",
  "properties": {
    "iso:country":"US",
    "sg:address":"1020 Elm St",
    "sg:city":"San Jose",
    "sg:classifiers":[
        {
            "category":"Real Estate",
            "subcategory":"Real Estate Operator",
            "type":"Services"
        }
    ],
    "sg:postcode":"95109",
    "sg:province":"CA",
    "sg:tags":[
        "apartment"
    ],
    "wof:name":"Elm St Apartments",
    "wof:placetype":"venue"
},
  "geometry": {"coordinates":[-121.92229500000001,37.345248],"type":"Point"}
}