{
  "type": "Feature",
  "properties": {
    "iso:country":"US",
    "sg:address":"1400 W Florida Ave",
    "sg:city":"Hemet",
    "sg:classifiers":[
        {
            "category":"Social Services",
            "type":"Services"
        }
    ],
    "sg:phone":"+1 951 652 7375",
    "sg:postcode":"92543",
    "sg:province":"CA",
    "sg:tags":[
        "organization",
        "welfare"
    ],
    "wof:name":"Salvation Army",
    "wof:placetype":"venue"
},
  "geometry": {"coordinates":[-116.985805,33.747555],"type":"Point"}
}