{
  "type": "Feature",
  "properties": {
    "addr:full":"5423 Skyway Rd Paradise CA 95969",
    "addr:housenumber":"5423",
    "addr:postcode":"95969",
    "addr:street":"Skyway Rd",
    "iso:country":"US",
    "sg:address":"5423 Skyway Rd",
    "sg:city":"Paradise",
    "sg:classifiers":[
        {
            "category":"Travel",
            "subcategory":"Hotels & Motels",
            "type":"Entertainment"
        }
    ],
    "sg:phone":"+1 530 877 2127",
    "sg:postcode":"95969",
    "sg:province":"CA",
    "wof:name":"Paradise Inn",
    "wof:placetype":"venue"
},
  "geometry": {"coordinates":[-121.633768,39.748869],"type":"Point"}
}