{
  "type": "Feature",
  "properties": {
    "iso:country":"US",
    "sg:address":"2803 Carmel Way",
    "sg:city":"Fairfield",
    "sg:classifiers":[
        {
            "category":"Building & Trades",
            "subcategory":"Landscaping Services",
            "type":"Services"
        }
    ],
    "sg:phone":"+1 707 428 1280",
    "sg:postcode":"94534",
    "sg:province":"CA",
    "wof:name":"Cypress Landscape Inc",
    "wof:placetype":"venue"
},
  "geometry": {"coordinates":[-122.063627,38.2706],"type":"Point"}
}