{
  "type": "Feature",
  "properties": {
    "iso:country":"US",
    "sg:address":"201 W Las Tunas Dr",
    "sg:city":"San Gabriel",
    "sg:classifiers":[
        {
            "category":"Sports & Exercise",
            "subcategory":"Tennis Court",
            "type":"Entertainment"
        }
    ],
    "sg:phone":"+1 626 576 8370",
    "sg:postcode":"91776",
    "sg:province":"CA",
    "wof:name":"Tennis Unlimited",
    "wof:placetype":"venue"
},
  "geometry": {"coordinates":[-118.101997,34.1026],"type":"Point"}
}