{
  "type": "Feature",
  "properties": {
    "iso:country":"US",
    "sg:address":"302 N Griffith Park Dr",
    "sg:city":"Burbank",
    "sg:classifiers":[
        {
            "category":"Food & Beverages",
            "subcategory":"Specialty",
            "type":"Retail Goods"
        }
    ],
    "sg:phone":"+1 818 845 2952",
    "sg:postcode":"91506",
    "sg:province":"CA",
    "sg:tags":[
        "herb"
    ],
    "wof:name":"Herbalab Products Inc",
    "wof:placetype":"venue"
},
  "geometry": {"coordinates":[-118.32195900000001,34.172663],"type":"Point"}
}