{
  "type": "Feature",
  "properties": {
    "iso:country":"US",
    "sg:address":"410 N Scovell Ave",
    "sg:city":"San Jacinto",
    "sg:classifiers":[
        {
            "category":"Shopping",
            "subcategory":"Computers & Home Electronics",
            "type":"Retail Goods"
        }
    ],
    "sg:phone":"+1 951 654 0034",
    "sg:postcode":"92582",
    "sg:province":"CA",
    "sg:tags":[
        "television",
        "radio"
    ],
    "wof:name":"Gary's TV & Stereo",
    "wof:placetype":"venue"
},
  "geometry": {"coordinates":[-116.972123,33.783877],"type":"Point"}
}