{
  "type": "Feature",
  "properties": {
    "iso:country":"US",
    "sg:address":"208 Robertson Blvd",
    "sg:city":"Chowchilla",
    "sg:classifiers":[
        {
            "category":"Restaurant",
            "type":"Food & Drink"
        }
    ],
    "sg:phone":"+1 559 665 5510",
    "sg:postcode":"93610",
    "sg:province":"CA",
    "wof:name":"Antenucci's Great Eats And Drinks Co.",
    "wof:placetype":"venue"
},
  "geometry": {"coordinates":[-120.260121,37.122776],"type":"Point"}
}