{
  "type": "Feature",
  "properties": {
    "addr:full":"2207 Pennington Rd Live Oak CA 95953",
    "addr:housenumber":"2207",
    "addr:postcode":"95953",
    "addr:street":"Pennington Rd",
    "iso:country":"US",
    "sg:address":"2207 Pennington Rd",
    "sg:city":"Live Oak",
    "sg:classifiers":[
        {
            "category":"Education",
            "subcategory":"School",
            "type":"Public Place"
        }
    ],
    "sg:phone":"+1 530 695 5430",
    "sg:postcode":"95953",
    "sg:province":"CA",
    "wof:name":"Valley Oak High School",
    "wof:placetype":"venue"
},
  "geometry": {"coordinates":[-121.65595,39.276143],"type":"Point"}
}