{
  "type": "Feature",
  "properties": {
    "addr:full":"1291 Simpson Way Escondido CA 92029",
    "addr:housenumber":"1291",
    "addr:postcode":"92029",
    "addr:street":"Simpson Way",
    "iso:country":"US",
    "sg:address":"1291 Simpson Way",
    "sg:city":"Escondido",
    "sg:classifiers":[
        {
            "category":"Home & Garden",
            "subcategory":"Furniture",
            "type":"Retail Goods"
        }
    ],
    "sg:phone":"+1 760 489 5958",
    "sg:postcode":"92029",
    "sg:province":"CA",
    "sg:tags":[
        "top",
        "counter"
    ],
    "wof:name":"Solid Surfaces",
    "wof:placetype":"venue"
},
  "geometry": {"coordinates":[-117.102318,33.119668],"type":"Point"}
}