{
  "type": "Feature",
  "properties": {
    "addr:full":"10357 Magnolia Ave Riverside CA 92505",
    "addr:housenumber":"10357",
    "addr:postcode":"92505",
    "addr:street":"Magnolia Ave",
    "iso:country":"US",
    "sg:address":"10357 Magnolia Ave",
    "sg:city":"Riverside",
    "sg:classifiers":[
        {
            "category":"Personal",
            "subcategory":"Beauty Salon",
            "type":"Services"
        }
    ],
    "sg:phone":"+1 951 785 8353",
    "sg:postcode":"92505",
    "sg:province":"CA",
    "wof:name":"Top City Nails & Hair",
    "wof:placetype":"venue"
},
  "geometry": {"coordinates":[-117.463919,33.910576],"type":"Point"}
}