{
  "type": "Feature",
  "properties": {
    "addr:full":"414 N Yale Ave Claremont CA 91711",
    "addr:housenumber":"414",
    "addr:postcode":"91711",
    "addr:street":"N Yale Ave",
    "iso:country":"US",
    "sg:address":"414 N Yale Ave",
    "sg:city":"Claremont",
    "sg:classifiers":[
        {
            "category":"Professional",
            "subcategory":"Lawyer & Legal Services",
            "type":"Services"
        }
    ],
    "sg:phone":"+1 909 626 1224",
    "sg:postcode":"91711",
    "sg:province":"CA",
    "sg:tags":[
        "attorney"
    ],
    "wof:name":"Stafford Shea & Held",
    "wof:placetype":"venue"
},
  "geometry": {"coordinates":[-117.717789,34.098479],"type":"Point"}
}