{
  "type": "Feature",
  "properties": {
    "addr:full":"1330 S Bascom Ave Ste F San Jose CA 95128",
    "addr:housenumber":"1330",
    "addr:postcode":"95128",
    "addr:street":"S Bascom Ave Ste F",
    "iso:country":"US",
    "sg:address":"1330 S Bascom Ave Ste F",
    "sg:city":"San Jose",
    "sg:classifiers":[
        {
            "category":"Banks & Credit Unions",
            "subcategory":"Financial Services",
            "type":"Services"
        }
    ],
    "sg:phone":"+1 408 293 8700",
    "sg:postcode":"95128",
    "sg:province":"CA",
    "sg:tags":[
        "broker",
        "mortgage"
    ],
    "wof:name":"American Dream Financial",
    "wof:placetype":"venue"
},
  "geometry": {"coordinates":[-121.931054,37.300783],"type":"Point"}
}