{
  "type": "Feature",
  "properties": {
    "addr:full":"3105 1st Ave Sacramento CA 95817",
    "addr:housenumber":"3105",
    "addr:postcode":"95817",
    "addr:street":"1St Ave",
    "iso:country":"US",
    "sg:address":"3105 1st Ave",
    "sg:city":"Sacramento",
    "sg:classifiers":[
        {
            "category":"Professional",
            "subcategory":"Lawyer & Legal Services",
            "type":"Services"
        }
    ],
    "sg:phone":"+1 916 457 5771",
    "sg:postcode":"95817",
    "sg:province":"CA",
    "wof:name":"Hellen Loretta Attorney At Law",
    "wof:placetype":"venue"
},
  "geometry": {"coordinates":[-121.47281599999999,38.555137],"type":"Point"}
}