{
  "type": "Feature",
  "properties": {
    "iso:country":"US",
    "sg:address":"2657 Pasadena Ave",
    "sg:city":"Los Angeles",
    "sg:classifiers":[
        {
            "category":"Restaurant",
            "type":"Food & Drink"
        }
    ],
    "sg:phone":"+1 323 221 3972",
    "sg:postcode":"90031",
    "sg:province":"CA",
    "wof:name":"Gloria's Restaurant",
    "wof:placetype":"venue"
},
  "geometry": {"coordinates":[-118.214996,34.0783],"type":"Point"}
}