{
  "type": "Feature",
  "properties": {
    "addr:full":"23871 Sunnymead Blvd Moreno Valley CA 92553",
    "addr:housenumber":"23871",
    "addr:postcode":"92553",
    "addr:street":"Sunnymead Blvd",
    "iso:country":"US",
    "sg:address":"23871 Sunnymead Blvd",
    "sg:city":"Moreno Valley",
    "sg:classifiers":[
        {
            "category":"Personal",
            "subcategory":"Beauty Salon",
            "type":"Services"
        }
    ],
    "sg:phone":"+1 951 924 0803",
    "sg:postcode":"92553",
    "sg:province":"CA",
    "wof:name":"Vogue Hair",
    "wof:placetype":"venue"
},
  "geometry": {"coordinates":[-117.248243,33.938937],"type":"Point"}
}