{
  "type": "Feature",
  "properties": {
    "addr:full":"1733 Fulton Ave Sacramento CA 95825",
    "addr:housenumber":"1733",
    "addr:postcode":"95825",
    "addr:street":"Fulton Ave",
    "iso:country":"US",
    "sg:address":"1733 Fulton Ave",
    "sg:city":"Sacramento",
    "sg:classifiers":[
        {
            "category":"Autos & Motor Vehicles",
            "subcategory":"Automobile Sales",
            "type":"Retail Goods"
        }
    ],
    "sg:phone":"+1 916 977 3900",
    "sg:postcode":"95825",
    "sg:province":"CA",
    "sg:tags":[
        "car",
        "used"
    ],
    "wof:name":"Amin's Auto Ctr",
    "wof:placetype":"venue"
},
  "geometry": {"coordinates":[-121.401487,38.596328],"type":"Point"}
}