{
  "type": "Feature",
  "properties": {
    "addr:full":"336 Chestnut St San Francisco CA 94133",
    "addr:housenumber":"336",
    "addr:postcode":"94133",
    "addr:street":"Chestnut St",
    "iso:country":"US",
    "sg:address":"336 Chestnut St",
    "sg:city":"San Francisco",
    "sg:classifiers":[
        {
            "category":"Professional",
            "type":"Services"
        }
    ],
    "sg:phone":"+1 415 781 0515",
    "sg:postcode":"94133",
    "sg:province":"CA",
    "wof:name":"Rangewise Company",
    "wof:placetype":"venue"
},
  "geometry": {"coordinates":[-122.40885,37.804394],"type":"Point"}
}