{
  "type": "Feature",
  "properties": {
    "iso:country":"US",
    "sg:address":"1919 Santa Monica Blvd",
    "sg:city":"Santa Monica",
    "sg:classifiers":[
        {
            "category":"Professional",
            "type":"Services"
        }
    ],
    "sg:phone":"+1 310 828 1450",
    "sg:postcode":"90404",
    "sg:province":"CA",
    "sg:tags":[
        "establishment"
    ],
    "wof:name":"Scan US",
    "wof:placetype":"venue"
},
  "geometry": {"coordinates":[-118.48067,34.028214],"type":"Point"}
}