{
  "type": "Feature",
  "properties": {
    "addr:full":"1945 Avenida del Oro Oceanside CA 92056",
    "addr:housenumber":"1945",
    "addr:postcode":"92056",
    "addr:street":"Avenida Del Oro",
    "iso:country":"US",
    "sg:address":"1945 Avenida del Oro",
    "sg:city":"Oceanside",
    "sg:classifiers":[
        {
            "category":"Wholesale",
            "subcategory":"Construction Materials",
            "type":"Manufacturing & Wholesale Goods"
        },
        {
            "category":"Manufacturing",
            "subcategory":"Electronics",
            "type":"Manufacturing & Wholesale Goods"
        }
    ],
    "sg:phone":"+1 760 945 5821",
    "sg:postcode":"92056",
    "sg:province":"CA",
    "sg:tags":[
        "control",
        "system",
        "controls",
        "regulators-wholesale",
        "solenoid",
        "manufacturer"
    ],
    "wof:name":"Tallyrand Industrial Systems",
    "wof:placetype":"venue"
},
  "geometry": {"coordinates":[-117.291034,33.207859],"type":"Point"}
}