{
  "type": "Feature",
  "properties": {
    "addr:full":"1887 E Revere Rd Fresno CA 93720",
    "addr:housenumber":"1887",
    "addr:postcode":"93720",
    "addr:street":"E Revere Rd",
    "iso:country":"US",
    "sg:address":"1887 E Revere Rd",
    "sg:city":"Fresno",
    "sg:classifiers":[
        {
            "category":"Home & Garden",
            "subcategory":"Home Furnishings",
            "type":"Retail Goods"
        }
    ],
    "sg:phone":"+1 559 299 8516",
    "sg:postcode":"93720",
    "sg:province":"CA",
    "wof:name":"Shelli N Shades",
    "wof:placetype":"venue"
},
  "geometry": {"coordinates":[-119.751125,36.879926],"type":"Point"}
}