{
  "type": "Feature",
  "properties": {
    "iso:country":"US",
    "sg:address":"315 Hume Ln",
    "sg:city":"Bakersfield",
    "sg:classifiers":[
        {
            "category":"Shopping",
            "subcategory":"Jewelry",
            "type":"Retail Goods"
        }
    ],
    "sg:phone":"+1 661 831 1459",
    "sg:postcode":"93309",
    "sg:province":"CA",
    "sg:tags":[
        "designer"
    ],
    "wof:name":"Judy's Golden Touch",
    "wof:placetype":"venue"
},
  "geometry": {"coordinates":[-119.074516,35.351459],"type":"Point"}
}