{
  "type": "Feature",
  "properties": {
    "addr:full":"4330 Turcon Ave Bakersfield CA 93308",
    "addr:housenumber":"4330",
    "addr:postcode":"93308",
    "addr:street":"Turcon Ave",
    "iso:country":"US",
    "sg:address":"4330 Turcon Ave",
    "sg:city":"Bakersfield",
    "sg:classifiers":[
        {
            "category":"Retail",
            "subcategory":"Storage",
            "type":"Services"
        },
        {
            "category":"Retail",
            "subcategory":"Auto Repair",
            "type":"Services"
        }
    ],
    "sg:phone":"+1 661 325 5974",
    "sg:postcode":"93308",
    "sg:province":"CA",
    "sg:tags":[
        "body",
        "automobile",
        "recreational",
        "campers-storage",
        "vehicle",
        "painting",
        "repairing",
        "boat",
        "campers-repair"
    ],
    "sg:website":"http://www.automotiveexpresscustoms.com",
    "wof:name":"Automotive Express & Customs",
    "wof:placetype":"venue"
},
  "geometry": {"coordinates":[-119.04994499999999,35.39179],"type":"Point"}
}