{
  "type": "Feature",
  "properties": {
    "iso:country":"US",
    "sg:address":"3650 Traffic Way",
    "sg:city":"Atascadero",
    "sg:classifiers":[
        {
            "category":"Social Services",
            "subcategory":"Retirement Home",
            "type":"Services"
        }
    ],
    "sg:phone":"+1 805 466 9254",
    "sg:postcode":"93422",
    "sg:province":"CA",
    "sg:tags":[
        "convalescent",
        "nursing"
    ],
    "wof:name":"Danish Care Center",
    "wof:placetype":"venue"
},
  "geometry": {"coordinates":[-120.67460699999999,35.512283],"type":"Point"}
}