{
  "type": "Feature",
  "properties": {
    "iso:country":"US",
    "sg:address":"14410 Washington Ave",
    "sg:city":"San Leandro",
    "sg:classifiers":[
        {
            "category":"Shopping",
            "subcategory":"Computers & Home Electronics",
            "type":"Retail Goods"
        }
    ],
    "sg:phone":"+1 510 351 8057",
    "sg:postcode":"94578",
    "sg:province":"CA",
    "sg:tags":[
        "equipment",
        "dealer"
    ],
    "wof:name":"Acrotek Computers",
    "wof:placetype":"venue"
},
  "geometry": {"coordinates":[-122.139937,37.700047],"type":"Point"}
}