{
  "type": "Feature",
  "properties": {
    "addr:full":"1664 Montgomery St Oroville CA 95965",
    "addr:housenumber":"1664",
    "addr:postcode":"95965",
    "addr:street":"Montgomery St",
    "iso:country":"US",
    "sg:address":"1664 Montgomery St",
    "sg:city":"Oroville",
    "sg:classifiers":[
        {
            "category":"Personal",
            "type":"Services"
        }
    ],
    "sg:phone":"+1 530 533 3433",
    "sg:postcode":"95965",
    "sg:province":"CA",
    "sg:tags":[
        "electrolysis"
    ],
    "wof:name":"Electrolysis Studio P Grimm",
    "wof:placetype":"venue"
},
  "geometry": {"coordinates":[-121.559443,39.512784],"type":"Point"}
}