{
  "type": "Feature",
  "properties": {
    "addr:full":"3333 Ridge Rd Lafayette CA 94549",
    "addr:housenumber":"3333",
    "addr:postcode":"94549",
    "addr:street":"Ridge Rd",
    "iso:country":"US",
    "sg:address":"3333 Ridge Rd",
    "sg:city":"Lafayette",
    "sg:classifiers":[
        {
            "category":"Professional",
            "subcategory":"Management & Consulting",
            "type":"Services"
        }
    ],
    "sg:phone":"+1 925 284 7635",
    "sg:postcode":"94549",
    "sg:province":"CA",
    "wof:name":"Manzi Financial Services",
    "wof:placetype":"venue"
},
  "geometry": {"coordinates":[-122.105918,37.889524],"type":"Point"}
}