{
  "type": "Feature",
  "properties": {
    "addr:full":"30650 Rancho California Rd Temecula CA 92591",
    "addr:housenumber":"30650",
    "addr:postcode":"92591",
    "addr:street":"Rancho California Rd",
    "iso:country":"US",
    "sg:address":"30650 Rancho California Rd",
    "sg:city":"Temecula",
    "sg:classifiers":[
        {
            "category":"Banks & Credit Unions",
            "subcategory":"Investment Brokerage",
            "type":"Services"
        }
    ],
    "sg:phone":"+1 951 699 4549",
    "sg:postcode":"92591",
    "sg:province":"CA",
    "sg:tags":[
        "stock",
        "bond"
    ],
    "wof:name":"Edward Jones Co",
    "wof:placetype":"venue"
},
  "geometry": {"coordinates":[-117.125873,33.508258],"type":"Point"}
}