{
  "type": "Feature",
  "properties": {
    "iso:country":"US",
    "sg:address":"1443 Howard Avenue",
    "sg:city":"Burlingame",
    "sg:classifiers":[
        {
            "category":"Arts & Performance",
            "subcategory":"Arts Center",
            "type":"Entertainment"
        }
    ],
    "sg:phone":"+1 650 347 6351",
    "sg:postcode":"94010",
    "sg:province":"CA",
    "sg:tags":[
        "performing"
    ],
    "wof:name":"Peninsula Girls Chorus",
    "wof:placetype":"venue"
},
  "geometry": {"coordinates":[-122.346752,37.576341],"type":"Point"}
}