{
  "type": "Feature",
  "properties": {
    "iso:country":"US",
    "sg:address":"1007 W Grove Ave Ste G",
    "sg:city":"Orange",
    "sg:classifiers":[
        {
            "category":"Shopping",
            "subcategory":"Party Supplies",
            "type":"Retail Goods"
        },
        {
            "category":"Personal",
            "type":"Services"
        }
    ],
    "sg:phone":"+1 714 921 4874",
    "sg:postcode":"92865",
    "sg:province":"CA",
    "sg:tags":[
        "planning",
        "event"
    ],
    "wof:name":"Hush Parties",
    "wof:placetype":"venue"
},
  "geometry": {"coordinates":[-117.86295800000001,33.819216],"type":"Point"}
}