{
  "type": "Feature",
  "properties": {
    "iso:country":"US",
    "sg:address":"8870 Creek Oaks Ln",
    "sg:city":"Orangevale",
    "sg:classifiers":[
        {
            "category":"Building & Trades",
            "subcategory":"Construction",
            "type":"Services"
        }
    ],
    "sg:phone":"+1 916 988 5677",
    "sg:postcode":"95662",
    "sg:province":"CA",
    "sg:tags":[
        "project"
    ],
    "wof:name":"Able Construction",
    "wof:placetype":"venue"
},
  "geometry": {"coordinates":[-121.228533,38.70757],"type":"Point"}
}