{
  "type": "Feature",
  "properties": {
    "iso:country":"US",
    "sg:address":"Hanuman Center 4450 18th St",
    "sg:city":"San Francisco",
    "sg:classifiers":[
        {
            "category":"Sports & Exercise",
            "subcategory":"Gym",
            "type":"Entertainment"
        },
        {
            "category":"Education",
            "subcategory":"Dance Studio",
            "type":"Public Place"
        }
    ],
    "sg:phone":"+1 415 283 6383",
    "sg:postcode":"94114",
    "sg:province":"CA",
    "sg:tags":[
        "yoga"
    ],
    "wof:name":"Triveni Sangam",
    "wof:placetype":"venue"
},
  "geometry": {"coordinates":[-122.43934299999999,37.760645],"type":"Point"}
}