{
  "type": "Feature",
  "properties": {
    "addr:full":"3061 Sawtelle Blvd Los Angeles CA 90066",
    "addr:housenumber":"3061",
    "addr:postcode":"90066",
    "addr:street":"Sawtelle Blvd",
    "iso:country":"US",
    "sg:address":"3061 Sawtelle Blvd",
    "sg:city":"Los Angeles",
    "sg:classifiers":[
        {
            "category":"Fast Food",
            "type":"Food & Drink"
        }
    ],
    "sg:phone":"+1 310 398 6580",
    "sg:postcode":"90066",
    "sg:province":"CA",
    "wof:name":"Kentucky Fried Chicken",
    "wof:placetype":"venue"
},
  "geometry": {"coordinates":[-118.431218,34.025514],"type":"Point"}
}