{
  "type": "Feature",
  "properties": {
    "addr:full":"1662 Long Beach Avenue Los Angeles CA 90021",
    "addr:housenumber":"1662",
    "addr:postcode":"90021",
    "addr:street":"Long Beach Avenue",
    "iso:country":"US",
    "sg:address":"1662 Long Beach Avenue",
    "sg:city":"Los Angeles",
    "sg:classifiers":[
        {
            "category":"Shopping",
            "subcategory":"Clothing, Apparel, & Fashions",
            "type":"Retail Goods"
        }
    ],
    "sg:phone":"+1 213 746 4140",
    "sg:postcode":"90021",
    "sg:province":"CA",
    "sg:tags":[
        "clothing",
        "women's"
    ],
    "wof:name":"La Glo",
    "wof:placetype":"venue"
},
  "geometry": {"coordinates":[-118.242868,34.021589],"type":"Point"}
}