{
  "type": "Feature",
  "properties": {
    "addr:full":"44374 S Grimmer Blvd Fremont CA 94538",
    "addr:housenumber":"44374",
    "addr:postcode":"94538",
    "addr:street":"S Grimmer Blvd",
    "iso:country":"US",
    "sg:address":"44374 S Grimmer Blvd",
    "sg:city":"Fremont",
    "sg:classifiers":[
        {
            "category":"Manufacturing",
            "subcategory":"Tools & Machinery",
            "type":"Manufacturing & Wholesale Goods"
        }
    ],
    "sg:phone":"+1 510 656 6292",
    "sg:postcode":"94538",
    "sg:province":"CA",
    "wof:name":"BCM Svc & Engineering",
    "wof:placetype":"venue"
},
  "geometry": {"coordinates":[-121.95510899999999,37.502752],"type":"Point"}
}