{
  "type": "Feature",
  "properties": {
    "addr:full":"518 E Sanderling St Ontario CA 91761",
    "addr:housenumber":"518",
    "addr:postcode":"91761",
    "addr:street":"E Sanderling St",
    "iso:country":"US",
    "sg:address":"518 E Sanderling St",
    "sg:city":"Ontario",
    "sg:classifiers":[
        {
            "category":"Personal",
            "subcategory":"Nail Salon",
            "type":"Services"
        }
    ],
    "sg:phone":"+1 909 984 8459",
    "sg:postcode":"91761",
    "sg:province":"CA",
    "wof:name":"Long Nails",
    "wof:placetype":"venue"
},
  "geometry": {"coordinates":[-117.645242,34.033175],"type":"Point"}
}