{
  "type": "Feature",
  "properties": {
    "addr:full":"939 S Sinclair Ave Stockton CA 95215",
    "addr:housenumber":"939",
    "addr:postcode":"95215",
    "addr:street":"S Sinclair Ave",
    "iso:country":"US",
    "sg:address":"939 S Sinclair Ave",
    "sg:city":"Stockton",
    "sg:classifiers":[
        {
            "category":"Real Estate",
            "subcategory":"Real Estate Agent",
            "type":"Services"
        }
    ],
    "sg:phone":"+1 209 462 4633",
    "sg:postcode":"95215",
    "sg:province":"CA",
    "sg:tags":[
        "manager"
    ],
    "wof:name":"Scottorosano Realestate",
    "wof:placetype":"venue"
},
  "geometry": {"coordinates":[-121.23218799999999,37.956947],"type":"Point"}
}