{
  "type": "Feature",
  "properties": {
    "addr:full":"1801 Chart Trl Topanga CA 90290",
    "addr:housenumber":"1801",
    "addr:postcode":"90290",
    "addr:street":"Chart Trl",
    "iso:country":"US",
    "sg:address":"1801 Chart Trl",
    "sg:city":"Topanga",
    "sg:classifiers":[
        {
            "category":"Manufacturing",
            "subcategory":"Printing",
            "type":"Manufacturing & Wholesale Goods"
        }
    ],
    "sg:phone":"+1 310 455 2995",
    "sg:postcode":"90290",
    "sg:province":"CA",
    "sg:tags":[
        "miscellaneous",
        "publishing"
    ],
    "wof:name":"Freedom Press Inc",
    "wof:placetype":"venue"
},
  "geometry": {"coordinates":[-118.590974,34.117208],"type":"Point"}
}