{
  "type": "Feature",
  "properties": {
    "addr:full":"88 Townsend Street 120 San Francisco CA 94107",
    "addr:housenumber":"88;120",
    "addr:postcode":"94107",
    "addr:street":"Townsend Street",
    "iso:country":"US",
    "sg:address":"88 Townsend Street 120",
    "sg:city":"San Francisco",
    "sg:classifiers":[
        {
            "category":"Professional",
            "subcategory":"Management & Consulting",
            "type":"Services"
        }
    ],
    "sg:phone":"+1 415 861 2230",
    "sg:postcode":"94107",
    "sg:province":"CA",
    "sg:tags":[
        "life",
        "coach"
    ],
    "wof:name":"Confidential Gay Matchmaking",
    "wof:placetype":"venue"
},
  "geometry": {"coordinates":[-122.390697,37.781167],"type":"Point"}
}