{
  "type": "Feature",
  "properties": {
    "addr:full":"2001 N Marshall Ave El Cajon CA 92020",
    "addr:housenumber":"2001",
    "addr:postcode":"92020",
    "addr:street":"N Marshall Ave",
    "iso:country":"US",
    "sg:address":"2001 N Marshall Ave",
    "sg:city":"El Cajon",
    "sg:classifiers":[
        {
            "category":"Government",
            "subcategory":"Office",
            "type":"Public Place"
        }
    ],
    "sg:phone":"+1 619 448 1449",
    "sg:postcode":"92020",
    "sg:province":"CA",
    "sg:tags":[
        "aviation"
    ],
    "wof:name":"Airport Traffic Control Tower",
    "wof:placetype":"venue"
},
  "geometry": {"coordinates":[-116.975527,32.817022],"type":"Point"}
}