{
  "type": "Feature",
  "properties": {
    "iso:country":"US",
    "sg:address":"4301 Franklin Blvd",
    "sg:city":"Sacramento",
    "sg:classifiers":[
        {
            "category":"Retail",
            "subcategory":"Repair Shop",
            "type":"Services"
        },
        {
            "category":"Retail",
            "subcategory":"Auto Repair",
            "type":"Services"
        }
    ],
    "sg:phone":"+1 916 451 7170",
    "sg:postcode":"95820",
    "sg:province":"CA",
    "sg:tags":[
        "automobile",
        "machine"
    ],
    "sg:website":"http://www.pearl-performance.com",
    "wof:name":"Pearl Performance Engines",
    "wof:placetype":"venue"
},
  "geometry": {"coordinates":[-121.474513,38.535846],"type":"Point"}
}