{
  "type": "Feature",
  "properties": {
    "addr:full":"17813 Countryside Ct Salinas CA 93907",
    "addr:housenumber":"17813",
    "addr:postcode":"93907",
    "addr:street":"Countryside Ct",
    "iso:country":"US",
    "sg:address":"17813 Countryside Ct",
    "sg:city":"Salinas",
    "sg:classifiers":[
        {
            "category":"Wholesale",
            "subcategory":"Fruits & Vegetables",
            "type":"Manufacturing & Wholesale Goods"
        }
    ],
    "sg:phone":"+1 831 663 3311",
    "sg:postcode":"93907",
    "sg:province":"CA",
    "sg:tags":[
        "veggie"
    ],
    "sg:website":"www.thesaladfarm.com",
    "wof:name":"The Salad Farm",
    "wof:placetype":"venue"
},
  "geometry": {"coordinates":[-121.668122,36.795838],"type":"Point"}
}