{
  "type": "Feature",
  "properties": {
    "addr:full":"55 Springstowne Center Vallejo CA 94591",
    "addr:housenumber":"55",
    "addr:postcode":"94591",
    "addr:street":"Springstowne Center",
    "iso:country":"US",
    "sg:address":"55 Springstowne Center",
    "sg:city":"Vallejo",
    "sg:classifiers":[
        {
            "category":"Building & Trades",
            "subcategory":"Landscaping Services",
            "type":"Services"
        }
    ],
    "sg:phone":"+1 707 315 4122",
    "sg:postcode":"94591",
    "sg:province":"CA",
    "sg:tags":[
        "lawn",
        "maintenance",
        "grounds"
    ],
    "wof:name":"Abyl Lawn & Svc",
    "wof:placetype":"venue"
},
  "geometry": {"coordinates":[-122.217223,38.10419],"type":"Point"}
}