{
  "type": "Feature",
  "properties": {
    "iso:country":"US",
    "sg:address":"5856 Corporate Ave",
    "sg:city":"Cypress",
    "sg:classifiers":[
        {
            "category":"Professional",
            "subcategory":"Accounting & Tax Preparation",
            "type":"Services"
        }
    ],
    "sg:phone":"+1 714 236 4000",
    "sg:postcode":"90630",
    "sg:province":"CA",
    "sg:tags":[
        "billing"
    ],
    "sg:website":"www.perse.com",
    "wof:name":"Perse Technology",
    "wof:placetype":"venue"
},
  "geometry": {"coordinates":[-118.030439,33.807915],"type":"Point"}
}