{
  "type": "Feature",
  "properties": {
    "addr:full":"2800 W March Ln Stockton CA 95219",
    "addr:housenumber":"2800",
    "addr:postcode":"95219",
    "addr:street":"W March Ln",
    "iso:country":"US",
    "sg:address":"2800 W March Ln",
    "sg:city":"Stockton",
    "sg:classifiers":[
        {
            "category":"Organizations",
            "subcategory":"Non-profit Organization",
            "type":"Services"
        }
    ],
    "sg:phone":"+1 209 956 3380",
    "sg:postcode":"95219",
    "sg:province":"CA",
    "sg:website":"www.sjpnet.org",
    "wof:name":"San Joaquin Partnership",
    "wof:placetype":"venue"
},
  "geometry": {"coordinates":[-121.34616800000001,37.984345],"type":"Point"}
}