{
  "type": "Feature",
  "properties": {
    "iso:country":"US",
    "sg:address":"3744 W Warner Ave",
    "sg:city":"Santa Ana",
    "sg:classifiers":[
        {
            "category":"Shopping",
            "subcategory":"Computers & Home Electronics",
            "type":"Retail Goods"
        }
    ],
    "sg:phone":"+1 714 546 3886",
    "sg:postcode":"92704",
    "sg:province":"CA",
    "sg:tags":[
        "television",
        "radio"
    ],
    "wof:name":"Advance TV Svc",
    "wof:placetype":"venue"
},
  "geometry": {"coordinates":[-117.918487,33.713888],"type":"Point"}
}