{
  "type": "Feature",
  "properties": {
    "addr:full":"420 S Fairview Ave Goleta CA 93117",
    "addr:housenumber":"420",
    "addr:postcode":"93117",
    "addr:street":"S Fairview Ave",
    "iso:country":"US",
    "sg:address":"420 S Fairview Ave",
    "sg:city":"Goleta",
    "sg:classifiers":[
        {
            "category":"Restaurant",
            "type":"Food & Drink"
        }
    ],
    "sg:phone":"+1 805 683 8864",
    "sg:postcode":"93117",
    "sg:province":"CA",
    "sg:tags":[
        "eating"
    ],
    "wof:name":"Cajun Kitchen",
    "wof:placetype":"venue"
},
  "geometry": {"coordinates":[-119.83029500000001,34.4263],"type":"Point"}
}