{
  "type": "Feature",
  "properties": {
    "iso:country":"US",
    "sg:address":"2777 Alvarado St",
    "sg:city":"San Leandro",
    "sg:classifiers":[
        {
            "category":"Social Services",
            "type":"Services"
        }
    ],
    "sg:phone":"+1 510 347 4620",
    "sg:postcode":"94577",
    "sg:province":"CA",
    "sg:tags":[
        "youth",
        "organization",
        "center"
    ],
    "wof:name":"Peacemakers",
    "wof:placetype":"venue"
},
  "geometry": {"coordinates":[-122.152769,37.706389],"type":"Point"}
}