{
  "type": "Feature",
  "properties": {
    "iso:country":"US",
    "sg:address":"1738 W Arbor Dr",
    "sg:city":"San Diego",
    "sg:classifiers":[
        {
            "category":"Communications",
            "subcategory":"Film & Video Production",
            "type":"Services"
        }
    ],
    "sg:phone":"+1 619 291 3544",
    "sg:postcode":"92103",
    "sg:province":"CA",
    "sg:tags":[
        "taping"
    ],
    "wof:name":"Edit FX Video Svc",
    "wof:placetype":"venue"
},
  "geometry": {"coordinates":[-117.179237,32.753255],"type":"Point"}
}