{
  "type": "Feature",
  "properties": {
    "addr:full":"180 Racquet Club Drive Compton CA 90220",
    "addr:housenumber":"180",
    "addr:postcode":"90220",
    "addr:street":"Racquet Club Drive",
    "iso:country":"US",
    "sg:address":"180 Racquet Club Drive",
    "sg:city":"Compton",
    "sg:classifiers":[
        {
            "category":"Professional",
            "subcategory":"Accounting & Tax Preparation",
            "type":"Services"
        }
    ],
    "sg:phone":"+1 310 632 9600",
    "sg:postcode":"90220",
    "sg:province":"CA",
    "sg:tags":[
        "accountant"
    ],
    "wof:name":"Mollow Barbara CPA",
    "wof:placetype":"venue"
},
  "geometry": {"coordinates":[-118.222117,33.893854],"type":"Point"}
}