{
  "type": "Feature",
  "properties": {
    "addr:full":"37434 Glenmoor Dr Fremont CA 94536",
    "addr:housenumber":"37434",
    "addr:postcode":"94536",
    "addr:street":"Glenmoor Dr",
    "iso:country":"US",
    "sg:address":"37434 Glenmoor Dr",
    "sg:city":"Fremont",
    "sg:classifiers":[
        {
            "category":"Professional",
            "type":"Services"
        }
    ],
    "sg:phone":"+1 510 790 3652",
    "sg:postcode":"94536",
    "sg:province":"CA",
    "wof:name":"Amnel",
    "wof:placetype":"venue"
},
  "geometry": {"coordinates":[-122.01213,37.550491],"type":"Point"}
}