{
  "type": "Feature",
  "properties": {
    "iso:country":"US",
    "sg:address":"2031 Anderson Rd",
    "sg:city":"Davis",
    "sg:classifiers":[
        {
            "category":"Health Services",
            "subcategory":"Doctor",
            "type":"Services"
        }
    ],
    "sg:phone":"+1 530 747 5300",
    "sg:postcode":"95616",
    "sg:province":"CA",
    "sg:tags":[
        "physician",
        "surgeon"
    ],
    "wof:name":"Western Orthopedic Management",
    "wof:placetype":"venue"
},
  "geometry": {"coordinates":[-121.758542,38.561201],"type":"Point"}
}