{
  "type": "Feature",
  "properties": {
    "addr:full":"4320 E Donald Douglas Dr Long Beach CA 90808",
    "addr:housenumber":"4320",
    "addr:postcode":"90808",
    "addr:street":"E Donald Douglas Dr",
    "iso:country":"US",
    "sg:address":"4320 E Donald Douglas Dr",
    "sg:city":"Long Beach",
    "sg:classifiers":[
        {
            "category":"Wholesale",
            "subcategory":"Machinery & Supplies",
            "type":"Manufacturing & Wholesale Goods"
        }
    ],
    "sg:phone":"+1 562 421 1771",
    "sg:postcode":"90808",
    "sg:province":"CA",
    "sg:tags":[
        "engine",
        "aircraft"
    ],
    "wof:name":"Hagelin Aircraft Motors",
    "wof:placetype":"venue"
},
  "geometry": {"coordinates":[-118.140614,33.818737],"type":"Point"}
}