{
  "type": "Feature",
  "properties": {
    "iso:country":"US",
    "sg:address":"9724 Carmel Mountain Rd",
    "sg:city":"San Diego",
    "sg:classifiers":[
        {
            "category":"Retail",
            "subcategory":"Laundry & Dry Cleaning",
            "type":"Services"
        }
    ],
    "sg:phone":"+1 858 484 7335",
    "sg:postcode":"92129",
    "sg:province":"CA",
    "sg:tags":[
        "cleaners"
    ],
    "wof:name":"Farah's Cleaners & Tailoring",
    "wof:placetype":"venue"
},
  "geometry": {"coordinates":[-117.117575,32.961599],"type":"Point"}
}