{
  "type": "Feature",
  "properties": {
    "iso:country":"US",
    "sg:address":"6600 Topanga Canyon Blvd Topanga Canyon Mall",
    "sg:city":"Canoga Park",
    "sg:classifiers":[
        {
            "category":"Shopping",
            "subcategory":"Beauty & Cosmetics",
            "type":"Retail Goods"
        },
        {
            "category":"Personal",
            "subcategory":"Hair Removal",
            "type":"Services"
        },
        {
            "category":"Personal",
            "subcategory":"Day Spa",
            "type":"Services"
        },
        {
            "category":"Personal",
            "subcategory":"Skin Care",
            "type":"Services"
        },
        {
            "category":"Shopping",
            "subcategory":"Bridal",
            "type":"Retail Goods"
        },
        {
            "category":"Personal",
            "subcategory":"Massage",
            "type":"Services"
        }
    ],
    "sg:phone":"+1 818 444 3958",
    "sg:postcode":"91303",
    "sg:province":"CA",
    "sg:tags":[
        "supply"
    ],
    "sg:website":"www.zibabeauty.com",
    "wof:name":"Ziba Beauty",
    "wof:placetype":"venue"
},
  "geometry": {"coordinates":[-118.604766,34.190408],"type":"Point"}
}