{
  "type": "Feature",
  "properties": {
    "iso:country":"US",
    "sg:address":"33981 Polk Ranch Rd",
    "sg:city":"Coarsegold",
    "sg:classifiers":[
        {
            "category":"Real Estate",
            "subcategory":"Real Estate Agent",
            "type":"Services"
        }
    ],
    "sg:phone":"+1 559 658 2828",
    "sg:postcode":"93614",
    "sg:province":"CA",
    "wof:name":"Dan Blogh Assoc",
    "wof:placetype":"venue"
},
  "geometry": {"coordinates":[-119.76156,37.237786],"type":"Point"}
}