{
  "type": "Feature",
  "properties": {
    "iso:country":"US",
    "sg:address":"326 1st St",
    "sg:city":"San Francisco",
    "sg:classifiers":[
        {
            "category":"Restaurant",
            "type":"Food & Drink"
        }
    ],
    "sg:phone":"+1 415 543 8184",
    "sg:postcode":"94105",
    "sg:province":"CA",
    "wof:name":"Baby's Place",
    "wof:placetype":"venue"
},
  "geometry": {"coordinates":[-122.394294,37.787121],"type":"Point"}
}