{
  "type": "Feature",
  "properties": {
    "iso:country":"US",
    "sg:address":"130 Baroni Ave",
    "sg:city":"San Jose",
    "sg:classifiers":[
        {
            "category":"Professional",
            "subcategory":"Accounting & Tax Preparation",
            "type":"Services"
        }
    ],
    "sg:phone":"+1 408 227 8833",
    "sg:postcode":"95136",
    "sg:province":"CA",
    "sg:tags":[
        "return",
        "filing"
    ],
    "wof:name":"Cristina Sheridan",
    "wof:placetype":"venue"
},
  "geometry": {"coordinates":[-121.84101800000001,37.275544],"type":"Point"}
}