{
  "type": "Feature",
  "properties": {
    "addr:full":"201 University Ave Palo Alto CA 94301",
    "addr:housenumber":"201",
    "addr:postcode":"94301",
    "addr:street":"University Ave",
    "iso:country":"US",
    "sg:address":"201 University Ave",
    "sg:city":"Palo Alto",
    "sg:classifiers":[
        {
            "category":"Restaurant",
            "type":"Food & Drink"
        }
    ],
    "sg:menulink":"http://www.allmenus.com/ca/san-jose/46900-sushi-tomo/menu/",
    "sg:phone":"+1 650 856 1100",
    "sg:postcode":"94301",
    "sg:province":"CA",
    "sg:tags":[
        "sushi",
        "asian"
    ],
    "wof:name":"Sushi Tomo",
    "wof:placetype":"venue"
},
  "geometry": {"coordinates":[-122.16277100000001,37.444763],"type":"Point"}
}