{
  "type": "Feature",
  "properties": {
    "iso:country":"US",
    "sg:address":"3212 E Ave H",
    "sg:city":"Lancaster",
    "sg:classifiers":[
        {
            "category":"Professional",
            "type":"Services"
        }
    ],
    "sg:phone":"+1 661 946 1459",
    "sg:postcode":"93535",
    "sg:province":"CA",
    "wof:name":"Miller Victor H Msgt Usaf R Et",
    "wof:placetype":"venue"
},
  "geometry": {"coordinates":[-118.073576,34.718978],"type":"Point"}
}