{
  "type": "Feature",
  "properties": {
    "addr:full":"1721 W Valley Blvd Alhambra CA 91803",
    "addr:housenumber":"1721",
    "addr:postcode":"91803",
    "addr:street":"W Valley Blvd",
    "iso:country":"US",
    "sg:address":"1721 W Valley Blvd",
    "sg:city":"Alhambra",
    "sg:classifiers":[
        {
            "category":"Restaurant",
            "type":"Food & Drink"
        }
    ],
    "sg:phone":"+1 626 282 8634",
    "sg:postcode":"91803",
    "sg:province":"CA",
    "sg:tags":[
        "chinese"
    ],
    "wof:name":"Shanghai Yau Fat",
    "wof:placetype":"venue"
},
  "geometry": {"coordinates":[-118.14299800000001,34.0774],"type":"Point"}
}