{
  "type": "Feature",
  "properties": {
    "addr:full":"212 Owen St Santa Cruz CA 95062",
    "addr:housenumber":"212",
    "addr:postcode":"95062",
    "addr:street":"Owen St",
    "iso:country":"US",
    "sg:address":"212 Owen St",
    "sg:city":"Santa Cruz",
    "sg:classifiers":[
        {
            "category":"Building & Trades",
            "subcategory":"Cleaning & Sanitation",
            "type":"Services"
        }
    ],
    "sg:phone":"+1 831 818 8394",
    "sg:postcode":"95062",
    "sg:province":"CA",
    "sg:tags":[
        "house"
    ],
    "wof:name":"K & D Housecleaning",
    "wof:placetype":"venue"
},
  "geometry": {"coordinates":[-122.004918,36.968182],"type":"Point"}
}