{
  "type": "Feature",
  "properties": {
    "iso:country":"US",
    "sg:address":"3155 Iris Ave",
    "sg:city":"San Ysidro",
    "sg:classifiers":[
        {
            "category":"Wholesale",
            "subcategory":"Scrap",
            "type":"Manufacturing & Wholesale Goods"
        }
    ],
    "sg:phone":"+1 619 423 2348",
    "sg:postcode":"92173",
    "sg:province":"CA",
    "sg:tags":[
        "recycling",
        "center"
    ],
    "wof:name":"Saved The Planet Recycling Ctr",
    "wof:placetype":"venue"
},
  "geometry": {"coordinates":[-117.063794,32.569067],"type":"Point"}
}