{
  "type": "Feature",
  "properties": {
    "iso:country":"US",
    "sg:address":"7033 Canoga Ave",
    "sg:city":"Canoga Park",
    "sg:classifiers":[
        {
            "category":"Shopping",
            "subcategory":"Hobbies, Toys, & Games",
            "type":"Retail Goods"
        }
    ],
    "sg:phone":"+1 818 703 7791",
    "sg:postcode":"91303",
    "sg:province":"CA",
    "sg:tags":[
        "miniature",
        "collector",
        "for",
        "item"
    ],
    "wof:name":"Small Wonders Handcrafts",
    "wof:placetype":"venue"
},
  "geometry": {"coordinates":[-118.597799,34.198612],"type":"Point"}
}