{
  "type": "Feature",
  "properties": {
    "addr:full":"747 N Azusa Ave West Covina CA 91791",
    "addr:housenumber":"747",
    "addr:postcode":"91791",
    "addr:street":"N Azusa Ave",
    "iso:country":"US",
    "sg:address":"747 N Azusa Ave",
    "sg:city":"West Covina",
    "sg:classifiers":[
        {
            "category":"Real Estate",
            "subcategory":"Real Estate Operator",
            "type":"Services"
        }
    ],
    "sg:phone":"+1 626 732 6357",
    "sg:postcode":"91791",
    "sg:province":"CA",
    "sg:tags":[
        "apartment"
    ],
    "wof:name":"Stone Gate Apartments",
    "wof:placetype":"venue"
},
  "geometry": {"coordinates":[-117.907777,34.08515],"type":"Point"}
}