{
  "type": "Feature",
  "properties": {
    "addr:full":"601 Cedar Street Berkeley CA 94710",
    "addr:housenumber":"601",
    "addr:postcode":"94710",
    "addr:street":"Cedar Street",
    "iso:country":"US",
    "sg:address":"601 Cedar Street",
    "sg:city":"Berkeley",
    "sg:classifiers":[
        {
            "category":"Retail",
            "subcategory":"Storage",
            "type":"Services"
        }
    ],
    "sg:phone":"+1 510 525 8565",
    "sg:postcode":"94710",
    "sg:province":"CA",
    "sg:tags":[
        "self"
    ],
    "sg:website":"www.extraspace.com",
    "wof:name":"Extra Space Storage",
    "wof:placetype":"venue"
},
  "geometry": {"coordinates":[-122.304796,37.873527],"type":"Point"}
}