{
  "type": "Feature",
  "properties": {
    "iso:country":"US",
    "sg:address":"15 S Quarantina St",
    "sg:city":"Santa Barbara",
    "sg:classifiers":[
        {
            "category":"Building & Trades",
            "subcategory":"Construction",
            "type":"Services"
        }
    ],
    "sg:phone":"+1 805 966 5880",
    "sg:postcode":"93103",
    "sg:province":"CA",
    "sg:tags":[
        "dry wall",
        "contractor"
    ],
    "wof:name":"Frank Thomas Enterprises Inc",
    "wof:placetype":"venue"
},
  "geometry": {"coordinates":[-119.68060800000001,34.419206],"type":"Point"}
}