{
  "type": "Feature",
  "properties": {
    "iso:country":"US",
    "sg:address":"550 E Ferguson Ct",
    "sg:city":"Visalia",
    "sg:classifiers":[
        {
            "category":"Retail",
            "subcategory":"Repair Shop",
            "type":"Services"
        }
    ],
    "sg:phone":"+1 559 625 8727",
    "sg:postcode":"93292",
    "sg:province":"CA",
    "sg:tags":[
        "clocks",
        "parts"
    ],
    "wof:name":"California Clockworks",
    "wof:placetype":"venue"
},
  "geometry": {"coordinates":[-119.28634099999999,36.349606],"type":"Point"}
}