{
  "type": "Feature",
  "properties": {
    "addr:full":"9113 Foothill Blvd Rancho Cucamonga CA 91730",
    "addr:housenumber":"9113",
    "addr:postcode":"91730",
    "addr:street":"Foothill Blvd",
    "iso:country":"US",
    "sg:address":"9113 Foothill Blvd",
    "sg:city":"Rancho Cucamonga",
    "sg:classifiers":[
        {
            "category":"Banks & Credit Unions",
            "subcategory":"Bank",
            "type":"Services"
        }
    ],
    "sg:phone":"+1 909 484 5882",
    "sg:postcode":"91730",
    "sg:province":"CA",
    "sg:tags":[
        "loan",
        "real estate"
    ],
    "wof:name":"Sea Breeze Mortgage Svc",
    "wof:placetype":"venue"
},
  "geometry": {"coordinates":[-117.60526900000001,34.106551],"type":"Point"}
}