{
  "type": "Feature",
  "properties": {
    "addr:full":"32692 Ortega Hwy Lake Elsinore CA 92530",
    "addr:housenumber":"32692",
    "addr:postcode":"92530",
    "addr:street":"Ortega Hwy",
    "iso:country":"US",
    "sg:address":"32692 Ortega Hwy",
    "sg:city":"Lake Elsinore",
    "sg:classifiers":[
        {
            "category":"Food & Beverages",
            "subcategory":"Groceries & Convenience Stores",
            "type":"Retail Goods"
        }
    ],
    "sg:phone":"+1 951 609 3106",
    "sg:postcode":"92530",
    "sg:province":"CA",
    "sg:tags":[
        "market"
    ],
    "wof:name":"Patty's Place Country Store",
    "wof:placetype":"venue"
},
  "geometry": {"coordinates":[-117.421352,33.641399],"type":"Point"}
}