{
  "type": "Feature",
  "properties": {
    "addr:full":"1825 N Oxnard Blvd Oxnard CA 93030",
    "addr:housenumber":"1825",
    "addr:postcode":"93030",
    "addr:street":"N Oxnard Blvd",
    "iso:country":"US",
    "sg:address":"1825 N Oxnard Blvd",
    "sg:city":"Oxnard",
    "sg:classifiers":[
        {
            "category":"Health Services",
            "subcategory":"Health Practitioner",
            "type":"Services"
        }
    ],
    "sg:phone":"+1 805 983 6787",
    "sg:postcode":"93030",
    "sg:province":"CA",
    "sg:tags":[
        "psychologist"
    ],
    "wof:name":"Isabel Bernal-Ward PHD",
    "wof:placetype":"venue"
},
  "geometry": {"coordinates":[-119.177269,34.214921],"type":"Point"}
}