{
  "type": "Feature",
  "properties": {
    "iso:country":"US",
    "sg:address":"1231 State St",
    "sg:city":"Santa Barbara",
    "sg:classifiers":[
        {
            "category":"Communications",
            "subcategory":"Film & Video Production",
            "type":"Services"
        }
    ],
    "sg:phone":"+1 805 965 4488",
    "sg:postcode":"93101",
    "sg:province":"CA",
    "sg:tags":[
        "television",
        "producer"
    ],
    "wof:name":"Foothill Entertainment",
    "wof:placetype":"venue"
},
  "geometry": {"coordinates":[-119.705452,34.423951],"type":"Point"}
}