{
  "type": "Feature",
  "properties": {
    "addr:full":"4814 W Adams Blvd Los Angeles CA 90016",
    "addr:housenumber":"4814",
    "addr:postcode":"90016",
    "addr:street":"W Adams Blvd",
    "iso:country":"US",
    "sg:address":"4814 W Adams Blvd",
    "sg:city":"Los Angeles",
    "sg:classifiers":[
        {
            "category":"Recreation",
            "subcategory":"Dance Hall",
            "type":"Entertainment"
        }
    ],
    "sg:postcode":"90016",
    "sg:province":"CA",
    "sg:tags":[
        "club"
    ],
    "wof:name":"Jah-Life",
    "wof:placetype":"venue"
},
  "geometry": {"coordinates":[-118.345463,34.032508],"type":"Point"}
}