{
  "type": "Feature",
  "properties": {
    "iso:country":"US",
    "sg:address":"2368 W Winton Ave",
    "sg:city":"Hayward",
    "sg:classifiers":[
        {
            "category":"Wholesale",
            "subcategory":"Electrical",
            "type":"Manufacturing & Wholesale Goods"
        }
    ],
    "sg:phone":"+1 510 264 2121",
    "sg:postcode":"94545",
    "sg:province":"CA",
    "sg:tags":[
        "datum",
        "product",
        "wire",
        "comm",
        "cable"
    ],
    "wof:name":"Arrow Wire & Cable Inc",
    "wof:placetype":"venue"
},
  "geometry": {"coordinates":[-122.144971,37.647306],"type":"Point"}
}