{
  "type": "Feature",
  "properties": {
    "addr:full":"606 S Victory Blvd Burbank CA 91502",
    "addr:housenumber":"606",
    "addr:postcode":"91502",
    "addr:street":"S Victory Blvd",
    "iso:country":"US",
    "sg:address":"606 S Victory Blvd",
    "sg:city":"Burbank",
    "sg:classifiers":[
        {
            "category":"Retail",
            "subcategory":"Auto Repair",
            "type":"Services"
        }
    ],
    "sg:phone":"+1 818 848 9404",
    "sg:postcode":"91502",
    "sg:province":"CA",
    "wof:name":"Le's Foreign Car Repair",
    "wof:placetype":"venue"
},
  "geometry": {"coordinates":[-118.31199599999999,34.169498],"type":"Point"}
}