{
  "type": "Feature",
  "properties": {
    "iso:country":"US",
    "sg:address":"4837 McGrath St",
    "sg:city":"Ventura",
    "sg:classifiers":[
        {
            "category":"Manufacturing",
            "subcategory":"Tools & Machinery",
            "type":"Manufacturing & Wholesale Goods"
        }
    ],
    "sg:phone":"+1 805 289 1090",
    "sg:postcode":"93003",
    "sg:province":"CA",
    "sg:tags":[
        "instrument",
        "surgical"
    ],
    "wof:name":"Pyra Med",
    "wof:placetype":"venue"
},
  "geometry": {"coordinates":[-119.226306,34.254584],"type":"Point"}
}