{
  "type": "Feature",
  "properties": {
    "iso:country":"US",
    "sg:address":"4768 J Street",
    "sg:city":"Sacramento",
    "sg:classifiers":[
        {
            "category":"Banks & Credit Unions",
            "subcategory":"Bank",
            "type":"Services"
        }
    ],
    "sg:phone":"+1 916 454 4800",
    "sg:postcode":"95819",
    "sg:province":"CA",
    "wof:name":"El Dorado Savings Bank",
    "wof:placetype":"venue"
},
  "geometry": {"coordinates":[-121.443901,38.566986],"type":"Point"}
}