{
  "type": "Feature",
  "properties": {
    "addr:full":"8814 Main St Lake Isabella CA 93240",
    "addr:housenumber":"8814",
    "addr:postcode":"93240",
    "addr:street":"Main St",
    "iso:country":"US",
    "sg:address":"8814 Main St",
    "sg:city":"Lake Isabella",
    "sg:classifiers":[
        {
            "category":"Freight",
            "type":"Transportation"
        }
    ],
    "sg:phone":"+1 760 378 3904",
    "sg:postcode":"93240",
    "sg:province":"CA",
    "sg:tags":[
        "operator",
        "local",
        "trucking"
    ],
    "wof:name":"Carl Witten Trucking",
    "wof:placetype":"venue"
},
  "geometry": {"coordinates":[-118.36559,35.641502],"type":"Point"}
}