{
  "type": "Feature",
  "properties": {
    "addr:full":"15220 Vanowen St Van Nuys CA 91405",
    "addr:postcode":"15220;91405",
    "addr:street":"Vanowen St",
    "iso:country":"US",
    "sg:address":"15220 Vanowen St",
    "sg:city":"Van Nuys",
    "sg:classifiers":[
        {
            "category":"Health Services",
            "subcategory":"Nursing And Care Facility",
            "type":"Services"
        }
    ],
    "sg:phone":"+1 818 838 6777",
    "sg:postcode":"91405",
    "sg:province":"CA",
    "sg:tags":[
        "home",
        "convalescent"
    ],
    "wof:name":"Center For Healthy Living",
    "wof:placetype":"venue"
},
  "geometry": {"coordinates":[-118.465981,34.193842],"type":"Point"}
}