{
  "type": "Feature",
  "properties": {
    "addr:full":"4371 E 49th St Los Angeles CA 90058",
    "addr:housenumber":"4371",
    "addr:postcode":"90058",
    "addr:street":"E 49Th St",
    "iso:country":"US",
    "sg:address":"4371 E 49th St",
    "sg:city":"Los Angeles",
    "sg:classifiers":[
        {
            "category":"Professional",
            "subcategory":"Management & Consulting",
            "type":"Services"
        }
    ],
    "sg:phone":"+1 323 277 9747",
    "sg:postcode":"90058",
    "sg:province":"CA",
    "sg:tags":[
        "international",
        "business"
    ],
    "wof:name":"Amber Distributors Inc",
    "wof:placetype":"venue"
},
  "geometry": {"coordinates":[-118.199868,33.998119],"type":"Point"}
}