{
  "type": "Feature",
  "properties": {
    "addr:full":"200 N Hayes Ave Oxnard CA 93030",
    "addr:housenumber":"200",
    "addr:postcode":"93030",
    "addr:street":"N Hayes Ave",
    "iso:country":"US",
    "sg:address":"200 N Hayes Ave",
    "sg:city":"Oxnard",
    "sg:classifiers":[
        {
            "category":"Health Services",
            "subcategory":"Chiropractor",
            "type":"Services"
        }
    ],
    "sg:phone":"+1 805 486 7300",
    "sg:postcode":"93030",
    "sg:province":"CA",
    "wof:name":"Los Quiropractocos",
    "wof:placetype":"venue"
},
  "geometry": {"coordinates":[-119.175349,34.205003],"type":"Point"}
}