{
  "type": "Feature",
  "properties": {
    "addr:full":"2228 W Ramsey St Banning CA 92220",
    "addr:housenumber":"2228",
    "addr:postcode":"92220",
    "addr:street":"W Ramsey St",
    "iso:country":"US",
    "sg:address":"2228 W Ramsey St",
    "sg:city":"Banning",
    "sg:classifiers":[
        {
            "category":"Food & Beverages",
            "subcategory":"Groceries & Convenience Stores",
            "type":"Retail Goods"
        }
    ],
    "sg:phone":"+1 951 849 2515",
    "sg:postcode":"92220",
    "sg:province":"CA",
    "wof:name":"Kofdarali Ampm 2",
    "wof:placetype":"venue"
},
  "geometry": {"coordinates":[-116.90270700000001,33.925656],"type":"Point"}
}