{
  "type": "Feature",
  "properties": {
    "iso:country":"US",
    "sg:address":"1242 Garfield Avenue",
    "sg:city":"Albany",
    "sg:classifiers":[
        {
            "category":"Building & Trades",
            "subcategory":"Construction",
            "type":"Services"
        }
    ],
    "sg:phone":"+1 510 525 5752",
    "sg:postcode":"94706",
    "sg:province":"CA",
    "sg:tags":[
        "contractor",
        "conditioning/hvac",
        "heating",
        "air"
    ],
    "sg:website":"www.phpboilers.com",
    "wof:name":"Pacific Heating & Piping",
    "wof:placetype":"venue"
},
  "geometry": {"coordinates":[-122.295998,37.895901],"type":"Point"}
}