{
  "type": "Feature",
  "properties": {
    "iso:country":"US",
    "sg:address":"2420 Martin Rd",
    "sg:city":"Fairfield",
    "sg:classifiers":[
        {
            "category":"Banks & Credit Unions",
            "subcategory":"Bank",
            "type":"Services"
        }
    ],
    "sg:phone":"+1 707 432 1000",
    "sg:postcode":"94534",
    "sg:province":"CA",
    "sg:tags":[
        "loan",
        "real estate"
    ],
    "wof:name":"First Priority Financial",
    "wof:placetype":"venue"
},
  "geometry": {"coordinates":[-122.04869600000001,38.283621],"type":"Point"}
}