{
  "type": "Feature",
  "properties": {
    "iso:country":"US",
    "sg:address":"9000 Carmel Valley Rd",
    "sg:city":"Carmel",
    "sg:classifiers":[
        {
            "category":"Farming",
            "subcategory":"Nursery",
            "type":"Manufacturing & Wholesale Goods"
        }
    ],
    "sg:phone":"+1 831 626 9141",
    "sg:postcode":"93923",
    "sg:province":"CA",
    "sg:tags":[
        "ornamental"
    ],
    "wof:name":"Flower Farm",
    "wof:placetype":"venue"
},
  "geometry": {"coordinates":[-121.819474,36.528622],"type":"Point"}
}