{
  "type": "Feature",
  "properties": {
    "iso:country":"US",
    "sg:address":"1550 Frontera Way",
    "sg:city":"Millbrae",
    "sg:classifiers":[
        {
            "category":"Real Estate",
            "subcategory":"Real Estate Operator",
            "type":"Services"
        }
    ],
    "sg:phone":"+1 650 697 4398",
    "sg:postcode":"94030",
    "sg:province":"CA",
    "sg:tags":[
        "condominium"
    ],
    "wof:name":"Bayview Condominium Assn",
    "wof:placetype":"venue"
},
  "geometry": {"coordinates":[-122.402365,37.582514],"type":"Point"}
}