{
  "type": "Feature",
  "properties": {
    "iso:country":"US",
    "sg:address":"45590 Jackson St",
    "sg:city":"Indio",
    "sg:classifiers":[
        {
            "category":"Insurance",
            "subcategory":"Insurance Agent",
            "type":"Services"
        }
    ],
    "sg:phone":"+1 760 342 5393",
    "sg:postcode":"92201",
    "sg:province":"CA",
    "wof:name":"Wold & Assoc",
    "wof:placetype":"venue"
},
  "geometry": {"coordinates":[-116.216117,33.718587],"type":"Point"}
}