{
  "type": "Feature",
  "properties": {
    "addr:full":"333 Santana Row San Jose CA 95128",
    "addr:housenumber":"333",
    "addr:postcode":"95128",
    "addr:street":"Santana Row",
    "iso:country":"US",
    "sg:address":"333 Santana Row",
    "sg:city":"San Jose",
    "sg:classifiers":[
        {
            "category":"Shopping",
            "subcategory":"Jewelry",
            "type":"Retail Goods"
        }
    ],
    "sg:phone":"+1 408 850 4200",
    "sg:postcode":"95128",
    "sg:province":"CA",
    "sg:website":"www.dercodiamonds.com",
    "wof:name":"Derco",
    "wof:placetype":"venue"
},
  "geometry": {"coordinates":[-121.94798400000001,37.321382],"type":"Point"}
}