{
  "type": "Feature",
  "properties": {
    "addr:full":"7861 Raytheon Rd San Diego CA 92111",
    "addr:housenumber":"7861",
    "addr:postcode":"92111",
    "addr:street":"Raytheon Rd",
    "iso:country":"US",
    "sg:address":"7861 Raytheon Rd",
    "sg:city":"San Diego",
    "sg:classifiers":[
        {
            "category":"Autos & Motor Vehicles",
            "subcategory":"Auto Supplies",
            "type":"Retail Goods"
        }
    ],
    "sg:phone":"+1 858 560 5455",
    "sg:postcode":"92111",
    "sg:province":"CA",
    "sg:tags":[
        "automobile",
        "alarm"
    ],
    "wof:name":"Sound Check Mobile Electronics",
    "wof:placetype":"venue"
},
  "geometry": {"coordinates":[-117.149737,32.830819],"type":"Point"}
}