{
  "type": "Feature",
  "properties": {
    "iso:country":"US",
    "sg:address":"2801 Zinfandel Dr",
    "sg:city":"Rancho Cordova",
    "sg:classifiers":[
        {
            "category":"Autos & Motor Vehicles",
            "subcategory":"Auto Supplies",
            "type":"Retail Goods"
        }
    ],
    "sg:phone":"+1 916 859 7070",
    "sg:postcode":"95670",
    "sg:province":"CA",
    "sg:tags":[
        "automobile",
        "parts"
    ],
    "wof:name":"NAPA Auto Parts",
    "wof:placetype":"venue"
},
  "geometry": {"coordinates":[-121.28796,38.593663],"type":"Point"}
}