{
  "type": "Feature",
  "properties": {
    "addr:full":"3080 Sacramento St Placerville CA 95667",
    "addr:housenumber":"3080",
    "addr:postcode":"95667",
    "addr:street":"Sacramento St",
    "iso:country":"US",
    "sg:address":"3080 Sacramento St",
    "sg:city":"Placerville",
    "sg:classifiers":[
        {
            "category":"Social Services",
            "type":"Services"
        }
    ],
    "sg:phone":"+1 530 626 5491",
    "sg:postcode":"95667",
    "sg:province":"CA",
    "sg:tags":[
        "organization",
        "welfare"
    ],
    "wof:name":"American Red Cross",
    "wof:placetype":"venue"
},
  "geometry": {"coordinates":[-120.80310900000001,38.725722],"type":"Point"}
}