{
  "type": "Feature",
  "properties": {
    "iso:country":"US",
    "sg:address":"700 S Flower St",
    "sg:city":"Los Angeles",
    "sg:classifiers":[
        {
            "category":"Professional",
            "subcategory":"Lawyer & Legal Services",
            "type":"Services"
        }
    ],
    "sg:phone":"+1 323 663 3525",
    "sg:postcode":"90017",
    "sg:province":"CA",
    "sg:tags":[
        "attorney"
    ],
    "wof:name":"Sharma Madhu Attorney At Law",
    "wof:placetype":"venue"
},
  "geometry": {"coordinates":[-118.26009999999999,34.047256],"type":"Point"}
}