{
  "type": "Feature",
  "properties": {
    "addr:full":"4701 Von Karman Ave Newport Beach CA 92660",
    "addr:housenumber":"4701",
    "addr:postcode":"92660",
    "addr:street":"Von Karman Ave",
    "iso:country":"US",
    "sg:address":"4701 Von Karman Ave",
    "sg:city":"Newport Beach",
    "sg:classifiers":[
        {
            "category":"Professional",
            "subcategory":"Engineering",
            "type":"Services"
        }
    ],
    "sg:phone":"+1 949 263 9366",
    "sg:postcode":"92660",
    "sg:province":"CA",
    "sg:tags":[
        "engineer"
    ],
    "wof:name":"Parsons Engineering Science",
    "wof:placetype":"venue"
},
  "geometry": {"coordinates":[-117.860164,33.668744],"type":"Point"}
}