{
  "type": "Feature",
  "properties": {
    "addr:full":"3305 Fathom Ct Atwater CA 95301",
    "addr:housenumber":"3305",
    "addr:postcode":"95301",
    "addr:street":"Fathom Ct",
    "iso:country":"US",
    "sg:address":"3305 Fathom Ct",
    "sg:city":"Atwater",
    "sg:classifiers":[
        {
            "category":"Shopping",
            "type":"Retail Goods"
        }
    ],
    "sg:phone":"+1 209 358 2794",
    "sg:postcode":"95301",
    "sg:province":"CA",
    "sg:tags":[
        "miscellaneous",
        "store"
    ],
    "wof:name":"Autry's Kettle Popcorn",
    "wof:placetype":"venue"
},
  "geometry": {"coordinates":[-120.594126,37.368849],"type":"Point"}
}