{
  "type": "Feature",
  "properties": {
    "iso:country":"US",
    "sg:address":"3512 16th St",
    "sg:city":"San Francisco",
    "sg:classifiers":[
        {
            "category":"Autos & Motor Vehicles",
            "subcategory":"Automobile Sales",
            "type":"Retail Goods"
        },
        {
            "category":"Retail",
            "subcategory":"Auto Repair",
            "type":"Services"
        }
    ],
    "sg:phone":"+1 415 863 7790",
    "sg:postcode":"94114",
    "sg:province":"CA",
    "sg:tags":[
        "automotive"
    ],
    "sg:website":"www.volvocentrum.net",
    "wof:name":"Volvo Centrum Inc.",
    "wof:placetype":"venue"
},
  "geometry": {"coordinates":[-122.431513,37.764619],"type":"Point"}
}