{
  "type": "Feature",
  "properties": {
    "iso:country":"US",
    "sg:address":"5702 Dexter Cir",
    "sg:city":"Rohnert Park",
    "sg:classifiers":[
        {
            "category":"Building & Trades",
            "subcategory":"Construction",
            "type":"Services"
        }
    ],
    "sg:phone":"+1 707 584 4209",
    "sg:postcode":"94928",
    "sg:province":"CA",
    "sg:tags":[
        "contractor"
    ],
    "wof:name":"Furgason Construction",
    "wof:placetype":"venue"
},
  "geometry": {"coordinates":[-122.701896,38.359054],"type":"Point"}
}