{
  "type": "Feature",
  "properties": {
    "iso:country":"US",
    "sg:address":"8837 Revelstoke Way",
    "sg:city":"San Diego",
    "sg:classifiers":[
        {
            "category":"Building & Trades",
            "subcategory":"Electrical",
            "type":"Services"
        }
    ],
    "sg:phone":"+1 619 850 7385",
    "sg:postcode":"92126",
    "sg:province":"CA",
    "sg:tags":[
        "electrical",
        "contractor"
    ],
    "wof:name":"Anthonys Electrical Services",
    "wof:placetype":"venue"
},
  "geometry": {"coordinates":[-117.133334,32.931334],"type":"Point"}
}