{
  "type": "Feature",
  "properties": {
    "addr:full":"4132 Mount Pinos Way Frazier Park CA 93225",
    "addr:housenumber":"4132",
    "addr:postcode":"93225",
    "addr:street":"Mount Pinos Way",
    "iso:country":"US",
    "sg:address":"4132 Mount Pinos Way",
    "sg:city":"Frazier Park",
    "sg:classifiers":[
        {
            "category":"Retail",
            "subcategory":"Portrait Studio",
            "type":"Services"
        }
    ],
    "sg:phone":"+1 661 245 3238",
    "sg:postcode":"93225",
    "sg:province":"CA",
    "sg:tags":[
        "photographer"
    ],
    "wof:name":"PCD Photo",
    "wof:placetype":"venue"
},
  "geometry": {"coordinates":[-118.954571,34.823213],"type":"Point"}
}