{
  "type": "Feature",
  "properties": {
    "iso:country":"US",
    "sg:address":"1307 W Pico Blvd",
    "sg:city":"Los Angeles",
    "sg:classifiers":[
        {
            "category":"Professional",
            "type":"Services"
        }
    ],
    "sg:phone":"+1 213 250 3330",
    "sg:postcode":"90015",
    "sg:province":"CA",
    "sg:tags":[
        "caterer"
    ],
    "wof:name":"Vinaigrettes",
    "wof:placetype":"venue"
},
  "geometry": {"coordinates":[-118.273282,34.043324],"type":"Point"}
}