{
  "type": "Feature",
  "properties": {
    "iso:country":"US",
    "sg:address":"9561 San Bernardino Rd",
    "sg:city":"Rancho Cucamonga",
    "sg:classifiers":[
        {
            "category":"Professional",
            "subcategory":"Management & Consulting",
            "type":"Services"
        }
    ],
    "sg:phone":"+1 951 966 9776",
    "sg:postcode":"91730",
    "sg:province":"CA",
    "sg:tags":[
        "marketing",
        "program"
    ],
    "wof:name":"Assist Marketing",
    "wof:placetype":"venue"
},
  "geometry": {"coordinates":[-117.59681500000001,34.108544],"type":"Point"}
}