{
  "type": "Feature",
  "properties": {
    "iso:country":"US",
    "sg:address":"22761 Hawthorne Blvd",
    "sg:city":"Torrance",
    "sg:classifiers":[
        {
            "category":"Professional",
            "subcategory":"Employment Agencies",
            "type":"Services"
        }
    ],
    "sg:phone":"+1 310 378 8628",
    "sg:postcode":"90505",
    "sg:province":"CA",
    "sg:tags":[
        "opportunity"
    ],
    "sg:website":"www.hrstaffing.com",
    "wof:name":"H R Staffing",
    "wof:placetype":"venue"
},
  "geometry": {"coordinates":[-118.35104,33.819201],"type":"Point"}
}