{
  "type": "Feature",
  "properties": {
    "addr:full":"4656 Kenmore Ave Baldwin Park CA 91706",
    "addr:housenumber":"4656",
    "addr:postcode":"91706",
    "addr:street":"Kenmore Ave",
    "iso:country":"US",
    "sg:address":"4656 Kenmore Ave",
    "sg:city":"Baldwin Park",
    "sg:classifiers":[
        {
            "category":"Food & Beverages",
            "subcategory":"Fruits & Vegetables",
            "type":"Retail Goods"
        }
    ],
    "sg:phone":"+1 626 960 7862",
    "sg:postcode":"91706",
    "sg:province":"CA",
    "sg:tags":[
        "produce"
    ],
    "wof:name":"Super Produce",
    "wof:placetype":"venue"
},
  "geometry": {"coordinates":[-117.97461300000001,34.097086],"type":"Point"}
}