{
  "type": "Feature",
  "properties": {
    "iso:country":"US",
    "sg:address":"2041 E Gladstone St",
    "sg:city":"Glendora",
    "sg:classifiers":[
        {
            "category":"Real Estate",
            "subcategory":"Real Estate Agent",
            "type":"Services"
        }
    ],
    "sg:phone":"+1 909 592 4784",
    "sg:postcode":"91740",
    "sg:province":"CA",
    "sg:tags":[
        "inspection"
    ],
    "wof:name":"Evans Inspection Svc",
    "wof:placetype":"venue"
},
  "geometry": {"coordinates":[-117.83964,34.113986],"type":"Point"}
}