{
  "type": "Feature",
  "properties": {
    "addr:full":"8116 W 3rd St Los Angeles CA 90048",
    "addr:housenumber":"8116",
    "addr:postcode":"90048",
    "addr:street":"W 3Rd St",
    "iso:country":"US",
    "sg:address":"8116 W 3rd St",
    "sg:city":"Los Angeles",
    "sg:classifiers":[
        {
            "category":"Shopping",
            "subcategory":"Clothing, Apparel, & Fashions",
            "type":"Retail Goods"
        }
    ],
    "sg:phone":"+1 323 653 2957",
    "sg:postcode":"90048",
    "sg:province":"CA",
    "sg:tags":[
        "tailor",
        "alteration",
        "sewing"
    ],
    "wof:name":"Hans the Tailor",
    "wof:placetype":"venue"
},
  "geometry": {"coordinates":[-118.366997,34.0723],"type":"Point"}
}