{
  "type": "Feature",
  "properties": {
    "addr:full":"835 5th Ave San Diego CA 92101",
    "addr:housenumber":"835",
    "addr:postcode":"92101",
    "addr:street":"5Th Ave",
    "iso:country":"US",
    "sg:address":"835 5th Ave",
    "sg:city":"San Diego",
    "sg:classifiers":[
        {
            "category":"Restaurant",
            "type":"Food & Drink"
        }
    ],
    "sg:menulink":"http://www.allmenus.com/ca/san-diego/43612-georges-on-fifth/menu/",
    "sg:phone":"+1 619 702 0444",
    "sg:postcode":"92101",
    "sg:province":"CA",
    "sg:tags":[
        "seafood",
        "american"
    ],
    "wof:name":"George's On Fifth",
    "wof:placetype":"venue"
},
  "geometry": {"coordinates":[-117.15998500000001,32.714014],"type":"Point"}
}