{
  "type": "Feature",
  "properties": {
    "iso:country":"US",
    "sg:address":"3656 Delta Fair Blvd",
    "sg:city":"Antioch",
    "sg:classifiers":[
        {
            "category":"Government",
            "subcategory":"Office",
            "type":"Public Place"
        }
    ],
    "sg:phone":"+1 925 754 7700",
    "sg:postcode":"94509",
    "sg:province":"CA",
    "sg:tags":[
        "state",
        "program",
        "health"
    ],
    "wof:name":"Rehabilitation California Dept",
    "wof:placetype":"venue"
},
  "geometry": {"coordinates":[-121.842295,38.003991],"type":"Point"}
}