{
  "type": "Feature",
  "properties": {
    "iso:country":"US",
    "sg:address":"57 Regina Dr",
    "sg:city":"Tracy",
    "sg:classifiers":[
        {
            "category":"Shopping",
            "subcategory":"Gifts & Souvenirs",
            "type":"Retail Goods"
        }
    ],
    "sg:phone":"+1 209 833 9773",
    "sg:postcode":"95376",
    "sg:province":"CA",
    "sg:tags":[
        "party",
        "supply"
    ],
    "wof:name":"Joe's Jumpers",
    "wof:placetype":"venue"
},
  "geometry": {"coordinates":[-121.426698,37.71833],"type":"Point"}
}