{
  "type": "Feature",
  "properties": {
    "iso:country":"US",
    "sg:address":"310 Hillside Ter Apt B",
    "sg:city":"Vista",
    "sg:classifiers":[
        {
            "category":"Community Center",
            "subcategory":"Youth",
            "type":"Public Place"
        }
    ],
    "sg:phone":"+1 760 207 0172",
    "sg:postcode":"92084",
    "sg:province":"CA",
    "wof:name":"After School Achievement Program Inc.",
    "wof:placetype":"venue"
},
  "geometry": {"coordinates":[-117.238674,33.205761],"type":"Point"}
}