{
  "type": "Feature",
  "properties": {
    "addr:full":"1115 Truxtun Ave Bakersfield CA 93301",
    "addr:housenumber":"1115",
    "addr:postcode":"93301",
    "addr:street":"Truxtun Ave",
    "iso:country":"US",
    "sg:address":"1115 Truxtun Ave",
    "sg:city":"Bakersfield",
    "sg:classifiers":[
        {
            "category":"Government",
            "subcategory":"Office",
            "type":"Public Place"
        }
    ],
    "sg:phone":"+1 661 868 3801",
    "sg:postcode":"93301",
    "sg:province":"CA",
    "wof:name":"KERN County Risk Management",
    "wof:placetype":"venue"
},
  "geometry": {"coordinates":[-119.015131,35.373248],"type":"Point"}
}