{
  "type": "Feature",
  "properties": {
    "addr:full":"150 Knowles Dr Los Gatos CA 95032",
    "addr:housenumber":"150",
    "addr:postcode":"95032",
    "addr:street":"Knowles Dr",
    "iso:country":"US",
    "sg:address":"150 Knowles Dr",
    "sg:city":"Los Gatos",
    "sg:classifiers":[
        {
            "category":"Manufacturing",
            "subcategory":"Electronics",
            "type":"Manufacturing & Wholesale Goods"
        }
    ],
    "sg:phone":"+1 408 379 7482",
    "sg:postcode":"95032",
    "sg:province":"CA",
    "sg:tags":[
        "semiconductor",
        "equipment",
        "mfg",
        "communication"
    ],
    "wof:name":"Anacom Inc",
    "wof:placetype":"venue"
},
  "geometry": {"coordinates":[-121.958484,37.261032],"type":"Point"}
}