{
  "type": "Feature",
  "properties": {
    "iso:country":"US",
    "sg:address":"4116 W Magnolia Blvd # 101",
    "sg:city":"Burbank",
    "sg:classifiers":[
        {
            "category":"Arts & Performance",
            "subcategory":"Art Gallery",
            "type":"Entertainment"
        }
    ],
    "sg:phone":"+1 818 848 9800",
    "sg:postcode":"91505",
    "sg:province":"CA",
    "sg:tags":[
        "fine",
        "artist"
    ],
    "wof:name":"Landmark Artists",
    "wof:placetype":"venue"
},
  "geometry": {"coordinates":[-118.351499,34.166371],"type":"Point"}
}