{
  "type": "Feature",
  "properties": {
    "iso:country":"US",
    "sg:address":"24007 Ventura Blvd",
    "sg:city":"Calabasas",
    "sg:classifiers":[
        {
            "category":"Professional",
            "subcategory":"Engineering",
            "type":"Services"
        }
    ],
    "sg:phone":"+1 818 222 0301",
    "sg:postcode":"91302",
    "sg:province":"CA",
    "sg:tags":[
        "engineer"
    ],
    "wof:name":"HMK Engineering Inc",
    "wof:placetype":"venue"
},
  "geometry": {"coordinates":[-118.650147,34.154914],"type":"Point"}
}