{
  "type": "Feature",
  "properties": {
    "addr:full":"3554 E Enterprise Dr Anaheim CA 92807",
    "addr:housenumber":"3554",
    "addr:postcode":"92807",
    "addr:street":"E Enterprise Dr",
    "iso:country":"US",
    "sg:address":"3554 E Enterprise Dr",
    "sg:city":"Anaheim",
    "sg:classifiers":[
        {
            "category":"Shopping",
            "subcategory":"Bicycles & Sporting Goods",
            "type":"Retail Goods"
        }
    ],
    "sg:phone":"+1 714 238 9247",
    "sg:postcode":"92807",
    "sg:province":"CA",
    "wof:name":"Titan Inc",
    "wof:placetype":"venue"
},
  "geometry": {"coordinates":[-117.841328,33.859192],"type":"Point"}
}