{
  "type": "Feature",
  "properties": {
    "addr:full":"3641 Edison Ave Sacramento CA 95821",
    "addr:housenumber":"3641",
    "addr:postcode":"95821",
    "addr:street":"Edison Ave",
    "iso:country":"US",
    "sg:address":"3641 Edison Ave",
    "sg:city":"Sacramento",
    "sg:classifiers":[
        {
            "category":"Real Estate",
            "subcategory":"Real Estate Operator",
            "type":"Services"
        }
    ],
    "sg:phone":"+1 916 486 0404",
    "sg:postcode":"95821",
    "sg:province":"CA",
    "sg:tags":[
        "building",
        "apartment"
    ],
    "sg:website":"www.quailvista.com",
    "wof:name":"Quail Vista Apartments",
    "wof:placetype":"venue"
},
  "geometry": {"coordinates":[-121.378998,38.634102],"type":"Point"}
}