{
  "type": "Feature",
  "properties": {
    "addr:full":"5779 Treosti Pl Valley Springs CA 95252",
    "addr:housenumber":"5779",
    "addr:postcode":"95252",
    "addr:street":"Treosti Pl",
    "iso:country":"US",
    "sg:address":"5779 Treosti Pl",
    "sg:city":"Valley Springs",
    "sg:classifiers":[
        {
            "category":"Insurance",
            "subcategory":"Insurance Agent",
            "type":"Services"
        }
    ],
    "sg:phone":"+1 209 772 8876",
    "sg:postcode":"95252",
    "sg:province":"CA",
    "wof:name":"Amador Valley Ins Svcs",
    "wof:placetype":"venue"
},
  "geometry": {"coordinates":[-120.84907800000001,38.129693],"type":"Point"}
}