{
  "type": "Feature",
  "properties": {
    "iso:country":"US",
    "sg:address":"1387 Linda Mar Blvd",
    "sg:city":"Pacifica",
    "sg:classifiers":[
        {
            "category":"Shopping",
            "subcategory":"Pets & Pet Supplies",
            "type":"Retail Goods"
        },
        {
            "category":"Retail",
            "subcategory":"Animal Services",
            "type":"Services"
        }
    ],
    "sg:phone":"+1 650 359 3946",
    "sg:postcode":"94044",
    "sg:province":"CA",
    "sg:tags":[
        "grooming",
        "dog",
        "cat"
    ],
    "wof:name":"Pawtastic Grooming",
    "wof:placetype":"venue"
},
  "geometry": {"coordinates":[-122.483467,37.582619],"type":"Point"}
}