{
  "type": "Feature",
  "properties": {
    "addr:full":"12043 Cll Sombra Moreno Valley CA 92557",
    "addr:postcode":"12043;92557",
    "addr:street":"Cll Sombra",
    "iso:country":"US",
    "sg:address":"12043 Cll Sombra",
    "sg:city":"Moreno Valley",
    "sg:classifiers":[
        {
            "category":"Building & Trades",
            "subcategory":"Plumbing",
            "type":"Services"
        }
    ],
    "sg:phone":"+1 951 485 9101",
    "sg:postcode":"92557",
    "sg:province":"CA",
    "sg:tags":[
        "conditioning",
        "air",
        "system",
        "contractor"
    ],
    "wof:name":"Mingin's Heating & AC",
    "wof:placetype":"venue"
},
  "geometry": {"coordinates":[-117.25578299999999,33.945768],"type":"Point"}
}