{
  "type": "Feature",
  "properties": {
    "iso:country":"US",
    "sg:address":"333 City Blvd W",
    "sg:city":"Orange",
    "sg:classifiers":[
        {
            "category":"Banks & Credit Unions",
            "subcategory":"Bank",
            "type":"Services"
        }
    ],
    "sg:phone":"+1 714 221 7270",
    "sg:postcode":"92868",
    "sg:province":"CA",
    "sg:tags":[
        "banking",
        "mortgage"
    ],
    "wof:name":"Hcg Financial Services LLC",
    "wof:placetype":"venue"
},
  "geometry": {"coordinates":[-117.89444399999999,33.786835],"type":"Point"}
}