{
  "type": "Feature",
  "properties": {
    "addr:full":"1011 Broadway St San Pablo CA 94806",
    "addr:housenumber":"1011",
    "addr:postcode":"94806",
    "addr:street":"Broadway St",
    "iso:country":"US",
    "sg:address":"1011 Broadway St",
    "sg:city":"San Pablo",
    "sg:classifiers":[
        {
            "category":"Wholesale",
            "subcategory":"Non-durable Goods",
            "type":"Manufacturing & Wholesale Goods"
        }
    ],
    "sg:phone":"+1 510 235 9309",
    "sg:postcode":"94806",
    "sg:province":"CA",
    "sg:tags":[
        "candle"
    ],
    "wof:name":"Inbal Inc",
    "wof:placetype":"venue"
},
  "geometry": {"coordinates":[-122.351766,37.975227],"type":"Point"}
}