{
  "type": "Feature",
  "properties": {
    "addr:full":"1911 W Glenoaks Blvd Ste B Glendale CA 91201",
    "addr:housenumber":"1911",
    "addr:postcode":"91201",
    "addr:street":"W Glenoaks Blvd Ste B",
    "iso:country":"US",
    "sg:address":"1911 W Glenoaks Blvd Ste B",
    "sg:city":"Glendale",
    "sg:classifiers":[
        {
            "category":"Health Services",
            "subcategory":"Doctor",
            "type":"Services"
        },
        {
            "category":"Health Services",
            "subcategory":"Health Practitioner",
            "type":"Services"
        }
    ],
    "sg:phone":"+1 818 843 6640",
    "sg:postcode":"91201",
    "sg:province":"CA",
    "sg:tags":[
        "physician",
        "surgeons",
        "internal",
        "medicine",
        "alternative",
        "surgeon"
    ],
    "wof:name":"Hanna Laila MD",
    "wof:placetype":"venue"
},
  "geometry": {"coordinates":[-118.293999,34.174099],"type":"Point"}
}