{
  "type": "Feature",
  "properties": {
    "iso:country":"US",
    "sg:address":"4344 Convoy St Ste J",
    "sg:city":"San Diego",
    "sg:classifiers":[
        {
            "category":"Personal",
            "subcategory":"Beauty Salon",
            "type":"Services"
        }
    ],
    "sg:phone":"+1 858 880 8898",
    "sg:postcode":"92111",
    "sg:province":"CA",
    "sg:tags":[
        "hair"
    ],
    "sg:website":"www.beautydotcom.co.cc",
    "wof:name":"Beauty.com",
    "wof:placetype":"venue"
},
  "geometry": {"coordinates":[-117.155722,32.819437],"type":"Point"}
}