{
  "type": "Feature",
  "properties": {
    "addr:full":"2 N 1st St San Jose CA 95112",
    "addr:housenumber":"2",
    "addr:postcode":"95112",
    "addr:street":"N 1St St",
    "iso:country":"US",
    "sg:address":"2 N 1st St",
    "sg:city":"San Jose",
    "sg:classifiers":[
        {
            "category":"Professional",
            "subcategory":"Research",
            "type":"Services"
        }
    ],
    "sg:phone":"+1 408 279 9010",
    "sg:postcode":"95112",
    "sg:province":"CA",
    "sg:tags":[
        "biotechnology",
        "product"
    ],
    "wof:name":"Pathwork Informatics",
    "wof:placetype":"venue"
},
  "geometry": {"coordinates":[-121.89167500000001,37.337655],"type":"Point"}
}