{
  "type": "Feature",
  "properties": {
    "addr:full":"400 W Ohio Ave Richmond CA 94804",
    "addr:housenumber":"400",
    "addr:postcode":"94804",
    "addr:street":"W Ohio Ave",
    "iso:country":"US",
    "sg:address":"400 W Ohio Ave",
    "sg:city":"Richmond",
    "sg:classifiers":[
        {
            "category":"Manufacturing",
            "subcategory":"Rubber & Plastics",
            "type":"Manufacturing & Wholesale Goods"
        }
    ],
    "sg:phone":"+1 510 235 9759",
    "sg:postcode":"94804",
    "sg:province":"CA",
    "wof:name":"Grant Engineering",
    "wof:placetype":"venue"
},
  "geometry": {"coordinates":[-122.371999,37.930777],"type":"Point"}
}