{
  "type": "Feature",
  "properties": {
    "addr:full":"3801 Katella Ave Los Alamitos CA 90720",
    "addr:housenumber":"3801",
    "addr:postcode":"90720",
    "addr:street":"Katella Ave",
    "iso:country":"US",
    "sg:address":"3801 Katella Ave",
    "sg:city":"Los Alamitos",
    "sg:classifiers":[
        {
            "category":"Health Services",
            "subcategory":"Medical Lab",
            "type":"Services"
        }
    ],
    "sg:phone":"+1 562 594 6417",
    "sg:postcode":"90720",
    "sg:province":"CA",
    "sg:tags":[
        "laboratory"
    ],
    "wof:name":"Quest Diagnostics",
    "wof:placetype":"venue"
},
  "geometry": {"coordinates":[-118.06765,33.803255],"type":"Point"}
}