{
  "type": "Feature",
  "properties": {
    "addr:full":"931 Whitley Ave Corcoran CA 93212",
    "addr:housenumber":"931",
    "addr:postcode":"93212",
    "addr:street":"Whitley Ave",
    "iso:country":"US",
    "sg:address":"931 Whitley Ave",
    "sg:city":"Corcoran",
    "sg:classifiers":[
        {
            "category":"Personal",
            "type":"Services"
        }
    ],
    "sg:phone":"+1 559 992 9221",
    "sg:postcode":"93212",
    "sg:province":"CA",
    "sg:tags":[
        "clothing"
    ],
    "wof:name":"Maricela Bride & Formal Wear",
    "wof:placetype":"venue"
},
  "geometry": {"coordinates":[-119.559376,36.097963],"type":"Point"}
}