{
  "type": "Feature",
  "properties": {
    "addr:full":"2017 N Lewis St Santa Ana CA 92706",
    "addr:housenumber":"2017",
    "addr:postcode":"92706",
    "addr:street":"N Lewis St",
    "iso:country":"US",
    "sg:address":"2017 N Lewis St",
    "sg:city":"Santa Ana",
    "sg:classifiers":[
        {
            "category":"Building & Trades",
            "subcategory":"Construction",
            "type":"Services"
        }
    ],
    "sg:phone":"+1 714 742 8497",
    "sg:postcode":"92706",
    "sg:province":"CA",
    "sg:tags":[
        "contractor"
    ],
    "sg:website":"www.duarteusa.com/",
    "wof:name":"Duarte Construction",
    "wof:placetype":"venue"
},
  "geometry": {"coordinates":[-117.897994,33.764249],"type":"Point"}
}