{
  "type": "Feature",
  "properties": {
    "iso:country":"US",
    "sg:address":"20 Rollingwood Dr Spc 165",
    "sg:city":"Jackson",
    "sg:classifiers":[
        {
            "category":"Manufacturing",
            "subcategory":"Glass & Minerals",
            "type":"Manufacturing & Wholesale Goods"
        }
    ],
    "sg:phone":"+1 209 223 3887",
    "sg:postcode":"95642",
    "sg:province":"CA",
    "sg:tags":[
        "glass-wholesale",
        "shape",
        "circle",
        "special",
        "manufacturer"
    ],
    "wof:name":"Pamco Glass Co",
    "wof:placetype":"venue"
},
  "geometry": {"coordinates":[-120.763903,38.362902],"type":"Point"}
}