{
  "type": "Feature",
  "properties": {
    "addr:full":"740 S Atlantic Blvd Monterey Park CA 91754",
    "addr:housenumber":"740",
    "addr:postcode":"91754",
    "addr:street":"S Atlantic Blvd",
    "iso:country":"US",
    "sg:address":"740 S Atlantic Blvd",
    "sg:city":"Monterey Park",
    "sg:classifiers":[
        {
            "category":"Wholesale",
            "subcategory":"Electrical",
            "type":"Manufacturing & Wholesale Goods"
        }
    ],
    "sg:phone":"+1 626 350 6993",
    "sg:postcode":"91754",
    "sg:province":"CA",
    "sg:tags":[
        "radio"
    ],
    "wof:name":"International Communications",
    "wof:placetype":"venue"
},
  "geometry": {"coordinates":[-118.135091,34.055806],"type":"Point"}
}