{
  "type": "Feature",
  "properties": {
    "iso:country":"US",
    "sg:address":"1315 Ridley Ave",
    "sg:city":"Santa Rosa",
    "sg:classifiers":[
        {
            "category":"Building & Trades",
            "subcategory":"Construction",
            "type":"Services"
        }
    ],
    "sg:phone":"+1 707 571 7991",
    "sg:postcode":"95401",
    "sg:province":"CA",
    "sg:tags":[
        "dry wall",
        "contractor"
    ],
    "wof:name":"D W Drywall",
    "wof:placetype":"venue"
},
  "geometry": {"coordinates":[-122.746274,38.449022],"type":"Point"}
}