{
  "type": "Feature",
  "properties": {
    "addr:full":"41570 Big Bear Blvd Big Bear Lake CA 92314",
    "addr:housenumber":"41570",
    "addr:postcode":"92314",
    "addr:street":"Big Bear Blvd",
    "iso:country":"US",
    "sg:address":"41570 Big Bear Blvd",
    "sg:city":"Big Bear Lake",
    "sg:classifiers":[
        {
            "category":"Banks & Credit Unions",
            "subcategory":"Investment Brokerage",
            "type":"Services"
        }
    ],
    "sg:phone":"+1 909 866 8422",
    "sg:postcode":"92314",
    "sg:province":"CA",
    "wof:name":"Edward Jones Investments",
    "wof:placetype":"venue"
},
  "geometry": {"coordinates":[-116.895161,34.243532],"type":"Point"}
}