{
  "type": "Feature",
  "properties": {
    "iso:country":"US",
    "sg:address":"2118 University Ave",
    "sg:city":"Palo Alto",
    "sg:classifiers":[
        {
            "category":"Restaurant",
            "type":"Food & Drink"
        }
    ],
    "sg:phone":"+1 650 324 2983",
    "sg:postcode":"94303",
    "sg:province":"CA",
    "wof:name":"Family House Fast Food",
    "wof:placetype":"venue"
},
  "geometry": {"coordinates":[-122.141623,37.463674],"type":"Point"}
}