{
  "type": "Feature",
  "properties": {
    "addr:full":"555 W Benjamin Holt Dr Stockton CA 95207",
    "addr:housenumber":"555",
    "addr:postcode":"95207",
    "addr:street":"W Benjamin Holt Dr",
    "iso:country":"US",
    "sg:address":"555 W Benjamin Holt Dr",
    "sg:city":"Stockton",
    "sg:classifiers":[
        {
            "category":"Professional",
            "subcategory":"Lawyer & Legal Services",
            "type":"Services"
        }
    ],
    "sg:phone":"+1 209 955 5700",
    "sg:postcode":"95207",
    "sg:province":"CA",
    "wof:name":"Legal Defense Fund",
    "wof:placetype":"venue"
},
  "geometry": {"coordinates":[-121.31980799999999,38.011355],"type":"Point"}
}