{
  "type": "Feature",
  "properties": {
    "addr:full":"405 Ofarrell Street San Francisco CA 94102",
    "addr:housenumber":"405",
    "addr:postcode":"94102",
    "addr:street":"Ofarrell Street",
    "iso:country":"US",
    "sg:address":"405 Ofarrell Street",
    "sg:city":"San Francisco",
    "sg:classifiers":[
        {
            "category":"Food & Beverages",
            "subcategory":"Liquor & Beverages",
            "type":"Retail Goods"
        }
    ],
    "sg:phone":"+1 415 921 2256",
    "sg:postcode":"94102",
    "sg:province":"CA",
    "sg:tags":[
        "beer",
        "spirit",
        "wine"
    ],
    "wof:name":"O'farrell Liquors",
    "wof:placetype":"venue"
},
  "geometry": {"coordinates":[-122.41100299999999,37.7859],"type":"Point"}
}