{
  "type": "Feature",
  "properties": {
    "addr:full":"18218 E McDurmott Irvine CA 92614",
    "addr:housenumber":"18218",
    "addr:postcode":"92614",
    "addr:street":"E Mcdurmott",
    "iso:country":"US",
    "sg:address":"18218 E McDurmott",
    "sg:city":"Irvine",
    "sg:classifiers":[
        {
            "category":"Professional",
            "subcategory":"Business Services",
            "type":"Services"
        }
    ],
    "sg:phone":"+1 949 474 2949",
    "sg:postcode":"92614",
    "sg:province":"CA",
    "sg:tags":[
        "packaging",
        "mover"
    ],
    "wof:name":"Box Brothers of Orange County",
    "wof:placetype":"venue"
},
  "geometry": {"coordinates":[-117.866552,33.688671],"type":"Point"}
}