{
  "type": "Feature",
  "properties": {
    "addr:full":"11642 Victory Blvd North Hollywood CA 91606",
    "addr:housenumber":"11642",
    "addr:postcode":"91606",
    "addr:street":"Victory Blvd",
    "iso:country":"US",
    "sg:address":"11642 Victory Blvd",
    "sg:city":"North Hollywood",
    "sg:classifiers":[
        {
            "category":"Shopping",
            "subcategory":"Party Supplies",
            "type":"Retail Goods"
        }
    ],
    "sg:phone":"+1 818 761 4508",
    "sg:postcode":"91606",
    "sg:province":"CA",
    "wof:name":"La Pinata",
    "wof:placetype":"venue"
},
  "geometry": {"coordinates":[-118.386002,34.186798],"type":"Point"}
}