{
  "type": "Feature",
  "properties": {
    "iso:country":"US",
    "sg:address":"45 Via Granada",
    "sg:city":"Palos Verdes Peninsula",
    "sg:classifiers":[
        {
            "category":"Shopping",
            "subcategory":"Clothing, Apparel, & Fashions",
            "type":"Retail Goods"
        }
    ],
    "sg:phone":"+1 310 377 7263",
    "sg:postcode":"90274",
    "sg:province":"CA",
    "wof:name":"Sending 2u",
    "wof:placetype":"venue"
},
  "geometry": {"coordinates":[-118.38172,33.77341],"type":"Point"}
}