{
  "type": "Feature",
  "properties": {
    "iso:country":"US",
    "sg:address":"9818 Paramount Blvd Ste A",
    "sg:city":"Downey",
    "sg:classifiers":[
        {
            "category":"Health Services",
            "subcategory":"Dentist",
            "type":"Services"
        }
    ],
    "sg:phone":"+1 562 927 6453",
    "sg:postcode":"90240",
    "sg:province":"CA",
    "sg:tags":[
        "orthodontist",
        "pediatric"
    ],
    "sg:website":"www.drscottfishman.com",
    "wof:name":"Scott Fishman, DDS",
    "wof:placetype":"venue"
},
  "geometry": {"coordinates":[-118.127601,33.956038],"type":"Point"}
}