{
  "type": "Feature",
  "properties": {
    "addr:full":"4900 W Washington Boulevard Los Angeles CA 90016",
    "addr:housenumber":"4900",
    "addr:postcode":"90016",
    "addr:street":"W Washington Boulevard",
    "iso:country":"US",
    "sg:address":"4900 W Washington Boulevard",
    "sg:city":"Los Angeles",
    "sg:classifiers":[
        {
            "category":"Home & Garden",
            "subcategory":"Carpets & Floor Coverings",
            "type":"Retail Goods"
        }
    ],
    "sg:phone":"+1 323 937 6700",
    "sg:postcode":"90016",
    "sg:province":"CA",
    "sg:tags":[
        "flooring"
    ],
    "wof:name":"Tristone & Tile",
    "wof:placetype":"venue"
},
  "geometry": {"coordinates":[-118.346057,34.040148],"type":"Point"}
}