{
  "type": "Feature",
  "properties": {
    "iso:country":"US",
    "sg:address":"4531 Market St",
    "sg:city":"Ventura",
    "sg:classifiers":[
        {
            "category":"Shopping",
            "subcategory":"Florist",
            "type":"Retail Goods"
        }
    ],
    "sg:phone":"+1 805 654 8815",
    "sg:postcode":"93003",
    "sg:province":"CA",
    "wof:name":"Bloomin Flowers",
    "wof:placetype":"venue"
},
  "geometry": {"coordinates":[-119.232224,34.257174],"type":"Point"}
}