{
  "type": "Feature",
  "properties": {
    "addr:full":"1716 Brea Canyon Cut Off Rd Walnut CA 91789",
    "addr:housenumber":"1716",
    "addr:postcode":"91789",
    "addr:street":"Brea Canyon Cut Off Rd",
    "iso:country":"US",
    "sg:address":"1716 Brea Canyon Cut Off Rd",
    "sg:city":"Walnut",
    "sg:classifiers":[
        {
            "category":"Education",
            "subcategory":"Special Training",
            "type":"Public Place"
        }
    ],
    "sg:phone":"+1 909 595 8014",
    "sg:postcode":"91789",
    "sg:province":"CA",
    "sg:tags":[
        "instruction",
        "music"
    ],
    "wof:name":"Colima Yamaha Music School",
    "wof:placetype":"venue"
},
  "geometry": {"coordinates":[-117.867237,33.983187],"type":"Point"}
}