{
  "type": "Feature",
  "properties": {
    "iso:country":"US",
    "sg:address":"8211 Orangethorpe Ave",
    "sg:city":"Buena Park",
    "sg:classifiers":[
        {
            "category":"Personal",
            "type":"Services"
        }
    ],
    "sg:phone":"+1 714 523 7094",
    "sg:postcode":"90621",
    "sg:province":"CA",
    "sg:tags":[
        "mover"
    ],
    "wof:name":"Precision Relocation",
    "wof:placetype":"venue"
},
  "geometry": {"coordinates":[-117.989836,33.859175],"type":"Point"}
}