{
  "type": "Feature",
  "properties": {
    "iso:country":"US",
    "sg:address":"809 S Atlantic Blvd",
    "sg:city":"Monterey Park",
    "sg:classifiers":[
        {
            "category":"Real Estate",
            "subcategory":"Real Estate Operator",
            "type":"Services"
        }
    ],
    "sg:phone":"+1 626 570 4488",
    "sg:postcode":"91754",
    "sg:province":"CA",
    "sg:tags":[
        "property",
        "lessor"
    ],
    "wof:name":"California Best Realty Co",
    "wof:placetype":"venue"
},
  "geometry": {"coordinates":[-118.136622,34.053494],"type":"Point"}
}