{
  "type": "Feature",
  "properties": {
    "iso:country":"US",
    "sg:address":"2055 Sebastopol Rd",
    "sg:city":"Santa Rosa",
    "sg:classifiers":[
        {
            "category":"Food & Beverages",
            "subcategory":"Groceries & Convenience Stores",
            "type":"Retail Goods"
        }
    ],
    "sg:phone":"+1 707 578 8900",
    "sg:postcode":"95407",
    "sg:province":"CA",
    "sg:tags":[
        "grocer"
    ],
    "wof:name":"Food Max",
    "wof:placetype":"venue"
},
  "geometry": {"coordinates":[-122.742431,38.426858],"type":"Point"}
}