{
  "type": "Feature",
  "properties": {
    "addr:full":"164 Bliss Canyon Rd Bradbury CA 91008",
    "addr:housenumber":"164",
    "addr:postcode":"91008",
    "addr:street":"Bliss Canyon Rd",
    "iso:country":"US",
    "sg:address":"164 Bliss Canyon Rd",
    "sg:city":"Bradbury",
    "sg:classifiers":[
        {
            "category":"Farming",
            "subcategory":"Livestock Farm",
            "type":"Manufacturing & Wholesale Goods"
        },
        {
            "category":"Arena",
            "subcategory":"Horse Racetrack",
            "type":"Entertainment"
        }
    ],
    "sg:phone":"+1 626 303 4746",
    "sg:postcode":"91008",
    "sg:province":"CA",
    "sg:tags":[
        "breeder"
    ],
    "wof:name":"Green Loft Ranch",
    "wof:placetype":"venue"
},
  "geometry": {"coordinates":[-117.968058,34.15267],"type":"Point"}
}