{
  "type": "Feature",
  "properties": {
    "iso:country":"US",
    "sg:address":"5230 Rosecrans Ave",
    "sg:city":"Lawndale",
    "sg:classifiers":[
        {
            "category":"Autos & Motor Vehicles",
            "subcategory":"Fuel & Gas Station",
            "type":"Retail Goods"
        }
    ],
    "sg:phone":"+1 310 536 0102",
    "sg:postcode":"90260",
    "sg:province":"CA",
    "wof:name":"Thrifty Gas Station",
    "wof:placetype":"venue"
},
  "geometry": {"coordinates":[-118.370712,33.90174],"type":"Point"}
}