{
  "type": "Feature",
  "properties": {
    "iso:country":"US",
    "sg:address":"17611 S C and D Blvd",
    "sg:city":"Blythe",
    "sg:classifiers":[
        {
            "category":"Professional",
            "type":"Services"
        }
    ],
    "sg:phone":"+1 760 922 3551",
    "sg:postcode":"92225",
    "sg:province":"CA",
    "sg:tags":[
        "establishment"
    ],
    "wof:name":"Blythe Mobile Hm Est & Stora",
    "wof:placetype":"venue"
},
  "geometry": {"coordinates":[-114.58739,33.574974],"type":"Point"}
}