{
  "type": "Feature",
  "properties": {
    "addr:full":"40 Cleveland Ave San Jose CA 95128",
    "addr:housenumber":"40",
    "addr:postcode":"95128",
    "addr:street":"Cleveland Ave",
    "iso:country":"US",
    "sg:address":"40 Cleveland Ave",
    "sg:city":"San Jose",
    "sg:classifiers":[
        {
            "category":"Retail",
            "subcategory":"Auto Repair",
            "type":"Services"
        }
    ],
    "sg:phone":"+1 408 293 0601",
    "sg:postcode":"95128",
    "sg:province":"CA",
    "sg:tags":[
        "repairing",
        "automobile"
    ],
    "wof:name":"Ministry of Transport",
    "wof:placetype":"venue"
},
  "geometry": {"coordinates":[-121.93000000000001,37.324001],"type":"Point"}
}