{
  "type": "Feature",
  "properties": {
    "iso:country":"US",
    "sg:address":"23986 Pine St",
    "sg:city":"Newhall",
    "sg:classifiers":[
        {
            "category":"Building & Trades",
            "subcategory":"Construction",
            "type":"Services"
        }
    ],
    "sg:phone":"+1 661 288 0333",
    "sg:postcode":"91321",
    "sg:province":"CA",
    "sg:tags":[
        "contractor"
    ],
    "wof:name":"Max Hy Building Corp",
    "wof:placetype":"venue"
},
  "geometry": {"coordinates":[-118.522028,34.374161],"type":"Point"}
}