{
  "type": "Feature",
  "properties": {
    "iso:country":"US",
    "sg:address":"7800 Wymark Dr",
    "sg:city":"Elk Grove",
    "sg:classifiers":[
        {
            "category":"Wholesale",
            "subcategory":"Machinery & Supplies",
            "type":"Manufacturing & Wholesale Goods"
        }
    ],
    "sg:phone":"+1 916 684 5538",
    "sg:postcode":"95758",
    "sg:province":"CA",
    "wof:name":"Essential Equipment Solutions",
    "wof:placetype":"venue"
},
  "geometry": {"coordinates":[-121.410781,38.412045],"type":"Point"}
}