{
  "type": "Feature",
  "properties": {
    "addr:full":"The Ritz-Carlton Los Angeles 900 W Olympic Blvd Los Angeles CA 90015",
    "addr:housenumber":"900",
    "addr:postcode":"90015",
    "addr:street":"W Olympic Blvd",
    "iso:country":"US",
    "sg:address":"The Ritz-Carlton Los Angeles 900 W Olympic Blvd",
    "sg:city":"Los Angeles",
    "sg:classifiers":[
        {
            "category":"Bars & Pubs",
            "subcategory":"Lounge",
            "type":"Food & Drink"
        }
    ],
    "sg:phone":"+1 213 765 8600",
    "sg:postcode":"90015",
    "sg:province":"CA",
    "sg:website":"www.ritzcarlton.com/en/Propertie...",
    "wof:name":"The Mixing Room",
    "wof:placetype":"venue"
},
  "geometry": {"coordinates":[-118.266565,34.045176],"type":"Point"}
}