{
  "type": "Feature",
  "properties": {
    "addr:full":"2829 Claremont Ave Berkeley CA 94705",
    "addr:housenumber":"2829",
    "addr:postcode":"94705",
    "addr:street":"Claremont Ave",
    "iso:country":"US",
    "sg:address":"2829 Claremont Ave",
    "sg:city":"Berkeley",
    "sg:classifiers":[
        {
            "category":"Health Services",
            "subcategory":"Health Practitioner",
            "type":"Services"
        }
    ],
    "sg:phone":"+1 510 665 1021",
    "sg:postcode":"94705",
    "sg:province":"CA",
    "sg:tags":[
        "nutritionist"
    ],
    "sg:website":"http://www.lindaprout.com",
    "wof:name":"Linda Prout",
    "wof:placetype":"venue"
},
  "geometry": {"coordinates":[-122.24443100000001,37.859798],"type":"Point"}
}