{
  "type": "Feature",
  "properties": {
    "iso:country":"US",
    "sg:address":"12007 Paramount Blvd",
    "sg:city":"Downey",
    "sg:classifiers":[
        {
            "category":"Real Estate",
            "subcategory":"Real Estate Operator",
            "type":"Services"
        }
    ],
    "sg:phone":"+1 562 923 4342",
    "sg:postcode":"90242",
    "sg:province":"CA",
    "sg:tags":[
        "apartment"
    ],
    "wof:name":"Parkdale Apartment Company",
    "wof:placetype":"venue"
},
  "geometry": {"coordinates":[-118.14502,33.933424],"type":"Point"}
}