{
  "type": "Feature",
  "properties": {
    "addr:full":"431 W 13th Ave Escondido CA 92025",
    "addr:housenumber":"431",
    "addr:postcode":"92025",
    "addr:street":"W 13Th Ave",
    "iso:country":"US",
    "sg:address":"431 W 13th Ave",
    "sg:city":"Escondido",
    "sg:classifiers":[
        {
            "category":"Manufacturing",
            "subcategory":"Food",
            "type":"Manufacturing & Wholesale Goods"
        }
    ],
    "sg:phone":"+1 760 745 2144",
    "sg:postcode":"92025",
    "sg:province":"CA",
    "sg:tags":[
        "product"
    ],
    "wof:name":"Mom & Baby Nutrition",
    "wof:placetype":"venue"
},
  "geometry": {"coordinates":[-117.078231,33.108656],"type":"Point"}
}