{
  "type": "Feature",
  "properties": {
    "addr:full":"551 W Anaheim St Long Beach CA 90813",
    "addr:housenumber":"551",
    "addr:postcode":"90813",
    "addr:street":"W Anaheim St",
    "iso:country":"US",
    "sg:address":"551 W Anaheim St",
    "sg:city":"Long Beach",
    "sg:classifiers":[
        {
            "category":"Retail",
            "subcategory":"Auto Repair",
            "type":"Services"
        }
    ],
    "sg:phone":"+1 562 599 6261",
    "sg:postcode":"90813",
    "sg:province":"CA",
    "sg:tags":[
        "repairing",
        "automobile"
    ],
    "wof:name":"Body Frame & Wheel Services",
    "wof:placetype":"venue"
},
  "geometry": {"coordinates":[-118.19899700000001,33.782501],"type":"Point"}
}