{
  "type": "Feature",
  "properties": {
    "iso:country":"US",
    "sg:address":"428 4th St",
    "sg:city":"Manhattan Beach",
    "sg:classifiers":[
        {
            "category":"Building & Trades",
            "subcategory":"Electrical",
            "type":"Services"
        }
    ],
    "sg:phone":"+1 310 379 6231",
    "sg:postcode":"90266",
    "sg:province":"CA",
    "sg:tags":[
        "electric",
        "contractor"
    ],
    "wof:name":"Mc Carty Electric",
    "wof:placetype":"venue"
},
  "geometry": {"coordinates":[-118.405221,33.880561],"type":"Point"}
}