{
  "type": "Feature",
  "properties": {
    "addr:full":"7946 Southwind Cir Huntington Beach CA 92648",
    "addr:housenumber":"7946",
    "addr:postcode":"92648",
    "addr:street":"Southwind Cir",
    "iso:country":"US",
    "sg:address":"7946 Southwind Cir",
    "sg:city":"Huntington Beach",
    "sg:classifiers":[
        {
            "category":"Wholesale",
            "subcategory":"Furniture",
            "type":"Manufacturing & Wholesale Goods"
        }
    ],
    "sg:phone":"+1 714 374 8689",
    "sg:postcode":"92648",
    "sg:province":"CA",
    "wof:name":"International Shop Jun",
    "wof:placetype":"venue"
},
  "geometry": {"coordinates":[-117.990236,33.655665],"type":"Point"}
}