{
  "type": "Feature",
  "properties": {
    "addr:full":"2524 Industrial Rowe Turlock CA 95380",
    "addr:housenumber":"2524",
    "addr:postcode":"95380",
    "addr:street":"Industrial Rowe",
    "iso:country":"US",
    "sg:address":"2524 Industrial Rowe",
    "sg:city":"Turlock",
    "sg:classifiers":[
        {
            "category":"Retail",
            "subcategory":"Laundry & Dry Cleaning",
            "type":"Services"
        }
    ],
    "sg:phone":"+1 209 333 8433",
    "sg:postcode":"95380",
    "sg:province":"CA",
    "sg:tags":[
        "cleaner",
        "rug",
        "carpet"
    ],
    "wof:name":"Steamrite Express Services",
    "wof:placetype":"venue"
},
  "geometry": {"coordinates":[-120.875409,37.486301],"type":"Point"}
}