{
  "type": "Feature",
  "properties": {
    "addr:full":"8312 Lake Murray Blvd San Diego CA 92119",
    "addr:housenumber":"8312",
    "addr:postcode":"92119",
    "addr:street":"Lake Murray Blvd",
    "iso:country":"US",
    "sg:address":"8312 Lake Murray Blvd",
    "sg:city":"San Diego",
    "sg:classifiers":[
        {
            "category":"Health Services",
            "subcategory":"Doctor",
            "type":"Services"
        }
    ],
    "sg:phone":"+1 619 461 5422",
    "sg:postcode":"92119",
    "sg:province":"CA",
    "sg:tags":[
        "dentist"
    ],
    "wof:name":"Guy L Fox DDS",
    "wof:placetype":"venue"
},
  "geometry": {"coordinates":[-117.01984899999999,32.791759],"type":"Point"}
}