{
  "type": "Feature",
  "properties": {
    "iso:country":"US",
    "sg:address":"2555 Greenwood Ave",
    "sg:city":"Calistoga",
    "sg:classifiers":[
        {
            "category":"Shopping",
            "subcategory":"Books",
            "type":"Retail Goods"
        }
    ],
    "sg:phone":"+1 707 942 9557",
    "sg:postcode":"94515",
    "sg:province":"CA",
    "sg:tags":[
        "comic"
    ],
    "wof:name":"Mr Precode",
    "wof:placetype":"venue"
},
  "geometry": {"coordinates":[-122.588489,38.594039],"type":"Point"}
}