{
  "type": "Feature",
  "properties": {
    "addr:full":"4037 Mayette Ave Santa Rosa CA 95405",
    "addr:housenumber":"4037",
    "addr:postcode":"95405",
    "addr:street":"Mayette Ave",
    "iso:country":"US",
    "sg:address":"4037 Mayette Ave",
    "sg:city":"Santa Rosa",
    "sg:classifiers":[
        {
            "category":"Building & Trades",
            "subcategory":"Landscaping Services",
            "type":"Services"
        }
    ],
    "sg:phone":"+1 707 579 4815",
    "sg:postcode":"95405",
    "sg:province":"CA",
    "sg:tags":[
        "landscape"
    ],
    "wof:name":"Joels Landscaping Service",
    "wof:placetype":"venue"
},
  "geometry": {"coordinates":[-122.671711,38.442427],"type":"Point"}
}