{
  "type": "Feature",
  "properties": {
    "iso:country":"US",
    "sg:address":"15075 Cll la Paloma",
    "sg:city":"Chino Hills",
    "sg:classifiers":[
        {
            "category":"Professional",
            "subcategory":"Business Services",
            "type":"Services"
        }
    ],
    "sg:phone":"+1 909 393 7911",
    "sg:postcode":"91709",
    "sg:province":"CA",
    "sg:tags":[
        "notary"
    ],
    "wof:name":"E Z Tempo Document Signers",
    "wof:placetype":"venue"
},
  "geometry": {"coordinates":[-117.746706,33.980253],"type":"Point"}
}