{
  "type": "Feature",
  "properties": {
    "addr:full":"2005 San Jose Dr Antioch CA 94509",
    "addr:housenumber":"2005",
    "addr:postcode":"ca 94509",
    "addr:street":"San Jose Dr",
    "iso:country":"US",
    "sg:address":"2005 San Jose Dr",
    "sg:city":"Antioch",
    "sg:classifiers":[
        {
            "category":"Real Estate",
            "subcategory":"Real Estate Operator",
            "type":"Services"
        }
    ],
    "sg:phone":"+1 925 757 5565",
    "sg:postcode":"94509",
    "sg:province":"CA",
    "sg:tags":[
        "apartment"
    ],
    "wof:name":"Baywoods Apartments",
    "wof:placetype":"venue"
},
  "geometry": {"coordinates":[-121.830825,38.00152],"type":"Point"}
}