{
  "type": "Feature",
  "properties": {
    "iso:country":"US",
    "sg:address":"650 California St",
    "sg:city":"San Francisco",
    "sg:classifiers":[
        {
            "category":"Insurance",
            "subcategory":"Insurance Agent",
            "type":"Services"
        }
    ],
    "sg:phone":"+1 415 981 3510",
    "sg:postcode":"94108",
    "sg:province":"CA",
    "sg:tags":[
        "adjuster"
    ],
    "wof:name":"Nelson & Bernstein LLC",
    "wof:placetype":"venue"
},
  "geometry": {"coordinates":[-122.40506999999999,37.792654],"type":"Point"}
}