{
  "type": "Feature",
  "properties": {
    "addr:full":"1682 E 41st St Los Angeles CA 90011",
    "addr:housenumber":"1682",
    "addr:postcode":"90011",
    "addr:street":"E 41St St",
    "iso:country":"US",
    "sg:address":"1682 E 41st St",
    "sg:city":"Los Angeles",
    "sg:classifiers":[
        {
            "category":"Personal",
            "type":"Services"
        }
    ],
    "sg:phone":"+1 323 264 7074",
    "sg:postcode":"90011",
    "sg:province":"CA",
    "sg:tags":[
        "towing"
    ],
    "sg:website":"www.olympicjunkyard.com",
    "wof:name":"Olympic Junk Yard",
    "wof:placetype":"venue"
},
  "geometry": {"coordinates":[-118.243568,34.007867],"type":"Point"}
}