{
  "type": "Feature",
  "properties": {
    "addr:full":"1630 S Sunkist St Anaheim CA 92806",
    "addr:housenumber":"1630",
    "addr:postcode":"92806",
    "addr:street":"S Sunkist St",
    "iso:country":"US",
    "sg:address":"1630 S Sunkist St",
    "sg:city":"Anaheim",
    "sg:classifiers":[
        {
            "category":"Retail",
            "subcategory":"Repair Shop",
            "type":"Services"
        }
    ],
    "sg:phone":"+1 714 919 2525",
    "sg:postcode":"92806",
    "sg:province":"CA",
    "sg:tags":[
        "equipment",
        "telephone",
        "system"
    ],
    "sg:website":"www.associatedtelecom.com",
    "wof:name":"Associated Telecom Svc",
    "wof:placetype":"venue"
},
  "geometry": {"coordinates":[-117.882975,33.810584],"type":"Point"}
}