{
  "type": "Feature",
  "properties": {
    "iso:country":"US",
    "sg:address":"652 N Sunset Ave",
    "sg:city":"West Covina",
    "sg:classifiers":[
        {
            "category":"Health Services",
            "subcategory":"Nursing And Care Facility",
            "type":"Services"
        }
    ],
    "sg:phone":"+1 626 337 7277",
    "sg:postcode":"91790",
    "sg:province":"CA",
    "sg:tags":[
        "skilled"
    ],
    "wof:name":"Unicare Laboratories",
    "wof:placetype":"venue"
},
  "geometry": {"coordinates":[-117.934468,34.08264],"type":"Point"}
}