{
  "type": "Feature",
  "properties": {
    "addr:full":"8523 Santa Monica Dr Beverly Hills CA 90210",
    "addr:housenumber":"8523",
    "addr:postcode":"90210",
    "addr:street":"Santa Monica Dr",
    "iso:country":"US",
    "sg:address":"8523 Santa Monica Dr",
    "sg:city":"Beverly Hills",
    "sg:classifiers":[
        {
            "category":"Building & Trades",
            "subcategory":"Cleaning & Sanitation",
            "type":"Services"
        }
    ],
    "sg:phone":"+1 310 456 3677",
    "sg:postcode":"90210",
    "sg:province":"CA",
    "sg:tags":[
        "carpet"
    ],
    "wof:name":"ChemDry Clean Masters",
    "wof:placetype":"venue"
},
  "geometry": {"coordinates":[-118.376892,34.089264],"type":"Point"}
}