{
  "type": "Feature",
  "properties": {
    "addr:full":"1307 B Lincoln Ave Calistoga CA 94515",
    "addr:housenumber":"1307 b",
    "addr:postcode":"94515",
    "addr:street":"Lincoln Ave",
    "iso:country":"US",
    "sg:address":"1307 B Lincoln Ave",
    "sg:city":"Calistoga",
    "sg:classifiers":[
        {
            "category":"Winery",
            "type":"Food & Drink"
        }
    ],
    "sg:phone":"+1 707 942 1194",
    "sg:postcode":"94515",
    "sg:province":"CA",
    "sg:website":"winesensoryexperience.com",
    "wof:name":"Wine Sensory Experience",
    "wof:placetype":"venue"
},
  "geometry": {"coordinates":[-122.579886,38.577548],"type":"Point"}
}