{
  "type": "Feature",
  "properties": {
    "iso:country":"US",
    "sg:address":"1524 Golden State Ave",
    "sg:city":"Bakersfield",
    "sg:classifiers":[
        {
            "category":"Bars & Pubs",
            "type":"Food & Drink"
        }
    ],
    "sg:phone":"+1 661 322 7300",
    "sg:postcode":"93301",
    "sg:province":"CA",
    "sg:tags":[
        "club",
        "night"
    ],
    "sg:website":"www.dejavu.com",
    "wof:name":"Deja Vu Show Bar",
    "wof:placetype":"venue"
},
  "geometry": {"coordinates":[-119.019643,35.387495],"type":"Point"}
}