{
  "type": "Feature",
  "properties": {
    "addr:full":"114 Lyon st San Francisco CA 94117",
    "addr:housenumber":"114",
    "addr:postcode":"94117",
    "addr:street":"Lyon St",
    "iso:country":"US",
    "sg:address":"114 Lyon st",
    "sg:city":"San Francisco",
    "sg:classifiers":[
        {
            "category":"Arts & Performance",
            "subcategory":"Arts Center",
            "type":"Entertainment"
        }
    ],
    "sg:phone":"+1 415 819 1620",
    "sg:postcode":"94117",
    "sg:province":"CA",
    "sg:website":"www.1photo3words365days.com",
    "wof:name":"1 photo 3 words 365 days",
    "wof:placetype":"venue"
},
  "geometry": {"coordinates":[-122.44202300000001,37.772138],"type":"Point"}
}