{
  "type": "Feature",
  "properties": {
    "iso:country":"US",
    "sg:address":"23733 Malibu Rd",
    "sg:city":"Malibu",
    "sg:phone":"+1 310 456 1500",
    "sg:postcode":"90265",
    "sg:province":"CA",
    "wof:name":"Bui Sushi",
    "wof:placetype":"venue"
},
  "geometry": {"coordinates":[-118.69145899999999,34.033731],"type":"Point"}
}