{
  "type": "Feature",
  "properties": {
    "iso:country":"US",
    "sg:address":"17250 Lemon St",
    "sg:city":"Hesperia",
    "sg:classifiers":[
        {
            "category":"Manufacturing",
            "subcategory":"Metals",
            "type":"Manufacturing & Wholesale Goods"
        }
    ],
    "sg:phone":"+1 760 244 8279",
    "sg:postcode":"92345",
    "sg:province":"CA",
    "sg:tags":[
        "tube",
        "fabricating"
    ],
    "wof:name":"Athena Industries Tube Bending",
    "wof:placetype":"venue"
},
  "geometry": {"coordinates":[-117.286445,34.442913],"type":"Point"}
}