{
  "type": "Feature",
  "properties": {
    "iso:country":"US",
    "sg:address":"20932 Normandie Ave",
    "sg:city":"Torrance",
    "sg:classifiers":[
        {
            "category":"Manufacturing",
            "subcategory":"Retail Goods",
            "type":"Manufacturing & Wholesale Goods"
        }
    ],
    "sg:phone":"+1 310 539 7727",
    "sg:postcode":"90502",
    "sg:province":"CA",
    "sg:tags":[
        "manufacturer"
    ],
    "wof:name":"Encon Industries",
    "wof:placetype":"venue"
},
  "geometry": {"coordinates":[-118.299125,33.83945],"type":"Point"}
}