{
  "type": "Feature",
  "properties": {
    "iso:country":"US",
    "sg:address":"952 N Elm St",
    "sg:city":"Orange",
    "sg:classifiers":[
        {
            "category":"Manufacturing",
            "subcategory":"Tools & Machinery",
            "type":"Manufacturing & Wholesale Goods"
        }
    ],
    "sg:phone":"+1 714 639 9640",
    "sg:postcode":"92867",
    "sg:province":"CA",
    "sg:tags":[
        "machine",
        "shop"
    ],
    "wof:name":"Allard Engineering Co",
    "wof:placetype":"venue"
},
  "geometry": {"coordinates":[-117.869435,33.803113],"type":"Point"}
}