{
  "type": "Feature",
  "properties": {
    "iso:country":"US",
    "sg:address":"123 Castro Street",
    "sg:city":"Mountain View",
    "sg:classifiers":[
        {
            "category":"Health Services",
            "subcategory":"Clinic",
            "type":"Services"
        },
        {
            "category":"Personal",
            "subcategory":"Psychics & Astrologers",
            "type":"Services"
        }
    ],
    "sg:phone":"+1 831 297 0567",
    "sg:postcode":"94041",
    "sg:province":"CA",
    "sg:tags":[
        "counseling",
        "mental"
    ],
    "sg:website":"www.illuminatingastrology.com",
    "wof:name":"Elena Lumen",
    "wof:placetype":"venue"
},
  "geometry": {"coordinates":[-122.078412,37.394608],"type":"Point"}
}