{
  "type": "Feature",
  "properties": {
    "iso:country":"US",
    "sg:address":"18992 Soledad Canyon Rd",
    "sg:city":"Santa Clarita",
    "sg:classifiers":[
        {
            "category":"Banks & Credit Unions",
            "subcategory":"Financial Services",
            "type":"Services"
        }
    ],
    "sg:phone":"+1 661 298 3700",
    "sg:postcode":"91351",
    "sg:province":"CA",
    "sg:tags":[
        "broker",
        "mortgage"
    ],
    "wof:name":"T M G Financial Services",
    "wof:placetype":"venue"
},
  "geometry": {"coordinates":[-118.467556,34.415572],"type":"Point"}
}