{
  "type": "Feature",
  "properties": {
    "addr:full":"1761 W Romneya Dr Anaheim CA 92801",
    "addr:housenumber":"1761",
    "addr:postcode":"92801",
    "addr:street":"W Romneya Dr",
    "iso:country":"US",
    "sg:address":"1761 W Romneya Dr",
    "sg:city":"Anaheim",
    "sg:classifiers":[
        {
            "category":"Health Services",
            "subcategory":"Doctor",
            "type":"Services"
        }
    ],
    "sg:phone":"+1 714 490 1200",
    "sg:postcode":"92801",
    "sg:province":"CA",
    "sg:tags":[
        "physician",
        "surgeon"
    ],
    "wof:name":"Advanced Medical Group",
    "wof:placetype":"venue"
},
  "geometry": {"coordinates":[-117.945735,33.850789],"type":"Point"}
}