{
  "type": "Feature",
  "properties": {
    "iso:country":"US",
    "sg:address":"5761 Uplander Way",
    "sg:city":"Culver City",
    "sg:classifiers":[
        {
            "category":"Wholesale",
            "subcategory":"Electrical",
            "type":"Manufacturing & Wholesale Goods"
        }
    ],
    "sg:phone":"+1 310 642 6663",
    "sg:postcode":"90230",
    "sg:province":"CA",
    "sg:tags":[
        "control"
    ],
    "wof:name":"AGX Corp",
    "wof:placetype":"venue"
},
  "geometry": {"coordinates":[-118.38494,33.985948],"type":"Point"}
}