{
  "type": "Feature",
  "properties": {
    "iso:country":"US",
    "sg:address":"13658 Hawthorne Blvd",
    "sg:city":"Hawthorne",
    "sg:classifiers":[
        {
            "category":"Banks & Credit Unions",
            "subcategory":"Financial Services",
            "type":"Services"
        }
    ],
    "sg:phone":"+1 310 355 1788",
    "sg:postcode":"90250",
    "sg:province":"CA",
    "sg:tags":[
        "broker",
        "mortgage"
    ],
    "wof:name":"Novastar Home Mortgage",
    "wof:placetype":"venue"
},
  "geometry": {"coordinates":[-118.351997,33.907799],"type":"Point"}
}