{
  "type": "Feature",
  "properties": {
    "iso:country":"US",
    "sg:address":"1140 E Country Club Blvd",
    "sg:city":"Big Bear City",
    "sg:classifiers":[
        {
            "category":"Professional",
            "type":"Services"
        }
    ],
    "sg:phone":"+1 909 584 8119",
    "sg:postcode":"92314",
    "sg:province":"CA",
    "wof:name":"Medieval Masters",
    "wof:placetype":"venue"
},
  "geometry": {"coordinates":[-116.824547,34.262133],"type":"Point"}
}