{
  "type": "Feature",
  "properties": {
    "addr:full":"2145 Foothill Blvd La Verne CA 91750",
    "addr:housenumber":"2145",
    "addr:postcode":"91750",
    "addr:street":"Foothill Blvd",
    "iso:country":"US",
    "sg:address":"2145 Foothill Blvd",
    "sg:city":"La Verne",
    "sg:classifiers":[
        {
            "category":"Coffee & Tea",
            "type":"Food & Drink"
        }
    ],
    "sg:menulink":"http://www.allmenus.com/ca/east-san-gabriel-valley/119537-starbucks-coffee/menu/",
    "sg:phone":"+1 909 593 1271",
    "sg:postcode":"91750",
    "sg:province":"CA",
    "sg:tags":[
        "american"
    ],
    "wof:name":"Starbucks Coffee",
    "wof:placetype":"venue"
},
  "geometry": {"coordinates":[-117.764106,34.113059],"type":"Point"}
}