{
  "type": "Feature",
  "properties": {
    "addr:full":"13808 Imperial Hwy Santa Fe Springs CA 90670",
    "addr:housenumber":"13808",
    "addr:postcode":"90670",
    "addr:street":"Imperial Hwy",
    "iso:country":"US",
    "sg:address":"13808 Imperial Hwy",
    "sg:city":"Santa Fe Springs",
    "sg:classifiers":[
        {
            "category":"Organizations",
            "subcategory":"Religious Organization",
            "type":"Services"
        }
    ],
    "sg:phone":"+1 562 483 4343",
    "sg:postcode":"90670",
    "sg:province":"CA",
    "sg:tags":[
        "church"
    ],
    "wof:name":"Victory Outreach Church",
    "wof:placetype":"venue"
},
  "geometry": {"coordinates":[-118.040397,33.916892],"type":"Point"}
}