{
  "type": "Feature",
  "properties": {
    "addr:full":"4010 Moorpark Ave San Jose CA 95117",
    "addr:housenumber":"4010",
    "addr:postcode":"95117",
    "addr:street":"Moorpark Ave",
    "iso:country":"US",
    "sg:address":"4010 Moorpark Ave",
    "sg:city":"San Jose",
    "sg:classifiers":[
        {
            "category":"Professional",
            "subcategory":"Employment Agencies",
            "type":"Services"
        }
    ],
    "sg:phone":"+1 408 551 5252",
    "sg:postcode":"95117",
    "sg:province":"CA",
    "sg:tags":[
        "opportunity"
    ],
    "wof:name":"Accountants Plus",
    "wof:placetype":"venue"
},
  "geometry": {"coordinates":[-121.973866,37.315792],"type":"Point"}
}