{
  "type": "Feature",
  "properties": {
    "addr:full":"1520 W 139th St Gardena CA 90249",
    "addr:housenumber":"1520",
    "addr:postcode":"90249",
    "addr:street":"W 139Th St",
    "iso:country":"US",
    "sg:address":"1520 W 139th St",
    "sg:city":"Gardena",
    "sg:classifiers":[
        {
            "category":"Building & Trades",
            "subcategory":"Construction",
            "type":"Services"
        }
    ],
    "sg:phone":"+1 310 324 7622",
    "sg:postcode":"90249",
    "sg:province":"CA",
    "sg:tags":[
        "lift",
        "aerial",
        "scaffolding"
    ],
    "wof:name":"Commercial Scaffolding Sales Inc",
    "wof:placetype":"venue"
},
  "geometry": {"coordinates":[-118.303106,33.905548],"type":"Point"}
}