{
  "type": "Feature",
  "properties": {
    "addr:full":"10390 Commerce Center Dr Rancho Cucamonga CA 91730",
    "addr:housenumber":"10390",
    "addr:postcode":"91730",
    "addr:street":"Commerce Center Dr",
    "iso:country":"US",
    "sg:address":"10390 Commerce Center Dr",
    "sg:city":"Rancho Cucamonga",
    "sg:classifiers":[
        {
            "category":"Professional",
            "type":"Services"
        }
    ],
    "sg:phone":"+1 909 581 1514",
    "sg:postcode":"91730",
    "sg:province":"CA",
    "sg:tags":[
        "establishment"
    ],
    "wof:name":"Lauras Permits",
    "wof:placetype":"venue"
},
  "geometry": {"coordinates":[-117.578227,34.078458],"type":"Point"}
}