{
  "type": "Feature",
  "properties": {
    "addr:full":"11664 National Blvd Los Angeles CA 90064",
    "addr:housenumber":"11664",
    "addr:postcode":"90064",
    "addr:street":"National Blvd",
    "iso:country":"US",
    "sg:address":"11664 National Blvd",
    "sg:city":"Los Angeles",
    "sg:classifiers":[
        {
            "category":"Shopping",
            "type":"Retail Goods"
        }
    ],
    "sg:phone":"+1 310 657 4738",
    "sg:postcode":"90064",
    "sg:province":"CA",
    "sg:tags":[
        "pet",
        "food",
        "supply"
    ],
    "wof:name":"Pet Express",
    "wof:placetype":"venue"
},
  "geometry": {"coordinates":[-118.437512,34.023276],"type":"Point"}
}