{
  "type": "Feature",
  "properties": {
    "addr:full":"1777 Vine St Los Angeles CA 90028",
    "addr:housenumber":"1777",
    "addr:postcode":"90028",
    "addr:street":"Vine St",
    "iso:country":"US",
    "sg:address":"1777 Vine St",
    "sg:city":"Los Angeles",
    "sg:classifiers":[
        {
            "category":"Manufacturing",
            "subcategory":"Apparel",
            "type":"Manufacturing & Wholesale Goods"
        }
    ],
    "sg:phone":"+1 323 460 6398",
    "sg:postcode":"90028",
    "sg:province":"CA",
    "sg:tags":[
        "clothing",
        "manufacturer"
    ],
    "wof:name":"Tree",
    "wof:placetype":"venue"
},
  "geometry": {"coordinates":[-118.326761,34.102099],"type":"Point"}
}