{
  "type": "Feature",
  "properties": {
    "iso:country":"US",
    "sg:address":"3557 Mt Diablo Blvd",
    "sg:city":"Lafayette",
    "sg:classifiers":[
        {
            "category":"Shopping",
            "subcategory":"Bicycles & Sporting Goods",
            "type":"Retail Goods"
        }
    ],
    "sg:phone":"+1 925 962 9884",
    "sg:postcode":"94549",
    "sg:province":"CA",
    "wof:name":"AEG Cycling",
    "wof:placetype":"venue"
},
  "geometry": {"coordinates":[-122.121339,37.89161],"type":"Point"}
}