{
  "type": "Feature",
  "properties": {
    "iso:country":"US",
    "sg:address":"500 Front St",
    "sg:city":"Soledad",
    "sg:classifiers":[
        {
            "category":"Wholesale",
            "subcategory":"Fruits & Vegetables",
            "type":"Manufacturing & Wholesale Goods"
        }
    ],
    "sg:phone":"+1 831 678 3470",
    "sg:postcode":"93960",
    "sg:province":"CA",
    "sg:tags":[
        "shipper"
    ],
    "wof:name":"California Fresh Cuts",
    "wof:placetype":"venue"
},
  "geometry": {"coordinates":[-121.329216,36.426928],"type":"Point"}
}