{
  "type": "Feature",
  "properties": {
    "addr:full":"125 Waverly San Francisco CA 94108",
    "addr:housenumber":"125",
    "addr:postcode":"94108",
    "addr:street":"Waverly",
    "iso:country":"US",
    "sg:address":"125 Waverly",
    "sg:city":"San Francisco",
    "sg:classifiers":[
        {
            "category":"Restaurant",
            "type":"Food & Drink"
        }
    ],
    "sg:postcode":"94108",
    "sg:province":"CA",
    "sg:tags":[
        "flavor",
        "local"
    ],
    "wof:name":"Tin How Temple",
    "wof:placetype":"venue"
},
  "geometry": {"coordinates":[-122.40707,37.794544],"type":"Point"}
}