{
  "type": "Feature",
  "properties": {
    "addr:full":"12650 Sherman Way North Hollywood CA 91605",
    "addr:housenumber":"12650",
    "addr:postcode":"91605",
    "addr:street":"Sherman Way",
    "iso:country":"US",
    "sg:address":"12650 Sherman Way",
    "sg:city":"North Hollywood",
    "sg:classifiers":[
        {
            "category":"Shopping",
            "subcategory":"Tobacco",
            "type":"Retail Goods"
        }
    ],
    "sg:phone":"+1 818 503 0033",
    "sg:postcode":"91605",
    "sg:province":"CA",
    "sg:tags":[
        "shop"
    ],
    "wof:name":"Mvs Smoke Shope & Water",
    "wof:placetype":"venue"
},
  "geometry": {"coordinates":[-118.408733,34.201072],"type":"Point"}
}