{
  "type": "Feature",
  "properties": {
    "iso:country":"US",
    "sg:address":"7920 Airway Rd",
    "sg:city":"San Diego",
    "sg:classifiers":[
        {
            "category":"Freight",
            "type":"Transportation"
        }
    ],
    "sg:phone":"+1 619 661 0121",
    "sg:postcode":"92154",
    "sg:province":"CA",
    "sg:tags":[
        "operator",
        "trucking"
    ],
    "wof:name":"Add Express Inc",
    "wof:placetype":"venue"
},
  "geometry": {"coordinates":[-116.975453,32.560629],"type":"Point"}
}