{
  "type": "Feature",
  "properties": {
    "iso:country":"US",
    "sg:address":"1501 Tollhouse Rd",
    "sg:city":"Clovis",
    "sg:classifiers":[
        {
            "category":"Shopping",
            "subcategory":"Bicycles & Sporting Goods",
            "type":"Retail Goods"
        }
    ],
    "sg:phone":"+1 559 323 1127",
    "sg:postcode":"93611",
    "sg:province":"CA",
    "sg:tags":[
        "saddlery",
        "harness"
    ],
    "wof:name":"Morisoli Custom Saddles & Repr",
    "wof:placetype":"venue"
},
  "geometry": {"coordinates":[-119.687166,36.829066],"type":"Point"}
}