{
  "type": "Feature",
  "properties": {
    "addr:full":"8027 70th St Paramount CA 90723",
    "addr:housenumber":"8027",
    "addr:postcode":"90723",
    "addr:street":"70Th St",
    "iso:country":"US",
    "sg:address":"8027 70th St",
    "sg:city":"Paramount",
    "sg:classifiers":[
        {
            "category":"Professional",
            "subcategory":"Detective & Security Services",
            "type":"Services"
        }
    ],
    "sg:phone":"+1 909 786 9421",
    "sg:postcode":"90723",
    "sg:province":"CA",
    "sg:tags":[
        "information",
        "bureau"
    ],
    "wof:name":"A&G Interpreting Services",
    "wof:placetype":"venue"
},
  "geometry": {"coordinates":[-118.159291,33.881955],"type":"Point"}
}