{
  "type": "Feature",
  "properties": {
    "addr:full":"449 E Pine St Exeter CA 93221",
    "addr:housenumber":"449",
    "addr:postcode":"93221",
    "addr:street":"E Pine St",
    "iso:country":"US",
    "sg:address":"449 E Pine St",
    "sg:city":"Exeter",
    "sg:classifiers":[
        {
            "category":"Restaurant",
            "type":"Food & Drink"
        }
    ],
    "sg:phone":"+1 559 592 7179",
    "sg:postcode":"93221",
    "sg:province":"CA",
    "wof:name":"Alejandras Mexican Restaurant",
    "wof:placetype":"venue"
},
  "geometry": {"coordinates":[-119.137749,36.297515],"type":"Point"}
}