{
  "type": "Feature",
  "properties": {
    "addr:full":"10523 Burbank Blvd North Hollywood CA 91601",
    "addr:housenumber":"10523",
    "addr:postcode":"91601",
    "addr:street":"Burbank Blvd",
    "iso:country":"US",
    "sg:address":"10523 Burbank Blvd",
    "sg:city":"North Hollywood",
    "sg:classifiers":[
        {
            "category":"Wholesale",
            "subcategory":"Electrical",
            "type":"Manufacturing & Wholesale Goods"
        }
    ],
    "sg:phone":"+1 818 985 1467",
    "sg:postcode":"91601",
    "sg:province":"CA",
    "sg:tags":[
        "equipment",
        "television",
        "studio"
    ],
    "wof:name":"VTR Interchange Inc",
    "wof:placetype":"venue"
},
  "geometry": {"coordinates":[-118.359844,34.172235],"type":"Point"}
}