{
  "type": "Feature",
  "properties": {
    "addr:full":"7860 el Cajon Blvd La Mesa CA 91941",
    "addr:housenumber":"7860",
    "addr:postcode":"91941",
    "addr:street":"El Cajon Blvd",
    "iso:country":"US",
    "sg:address":"7860 el Cajon Blvd",
    "sg:city":"La Mesa",
    "sg:classifiers":[
        {
            "category":"Retail",
            "subcategory":"Auto Repair",
            "type":"Services"
        }
    ],
    "sg:phone":"+1 619 698 6121",
    "sg:postcode":"91941",
    "sg:province":"CA",
    "sg:tags":[
        "recreational",
        "vehicle"
    ],
    "wof:name":"Budget Rv",
    "wof:placetype":"venue"
},
  "geometry": {"coordinates":[-117.029422,32.768541],"type":"Point"}
}