{
  "type": "Feature",
  "properties": {
    "iso:country":"US",
    "sg:address":"2746 Park Blvd",
    "sg:city":"Oakland",
    "sg:classifiers":[
        {
            "category":"Manufacturing",
            "subcategory":"Tools & Machinery",
            "type":"Manufacturing & Wholesale Goods"
        }
    ],
    "sg:phone":"+1 510 451 1541",
    "sg:postcode":"94606",
    "sg:province":"CA",
    "sg:tags":[
        "cutting",
        "gear"
    ],
    "wof:name":"Awesome Gears",
    "wof:placetype":"venue"
},
  "geometry": {"coordinates":[-122.240495,37.802467],"type":"Point"}
}