{
  "type": "Feature",
  "properties": {
    "addr:full":"2014 Shattuck Ave Berkeley CA 94704",
    "addr:housenumber":"2014",
    "addr:postcode":"94704",
    "addr:street":"Shattuck Ave",
    "iso:country":"US",
    "sg:address":"2014 Shattuck Ave",
    "sg:city":"Berkeley",
    "sg:classifiers":[
        {
            "category":"Professional",
            "type":"Services"
        }
    ],
    "sg:phone":"+1 510 540 0200",
    "sg:postcode":"94704",
    "sg:province":"CA",
    "sg:website":"www.rubypr.com",
    "wof:name":"Ruby Press",
    "wof:placetype":"venue"
},
  "geometry": {"coordinates":[-122.268672,37.871638],"type":"Point"}
}