{
  "type": "Feature",
  "properties": {
    "iso:country":"US",
    "sg:address":"1426 Aurora Dr",
    "sg:city":"El Centro",
    "sg:classifiers":[
        {
            "category":"Building & Trades",
            "subcategory":"Electrical",
            "type":"Services"
        }
    ],
    "sg:phone":"+1 760 352 3799",
    "sg:postcode":"92243",
    "sg:province":"CA",
    "sg:tags":[
        "electrical",
        "contractor"
    ],
    "wof:name":"Superior Electric Services",
    "wof:placetype":"venue"
},
  "geometry": {"coordinates":[-115.569343,32.778474],"type":"Point"}
}