{
  "type": "Feature",
  "properties": {
    "addr:full":"24135 Magic Mountain Parkway Santa Clarita CA 91355",
    "addr:housenumber":"24135",
    "addr:postcode":"91355",
    "addr:street":"Magic Mountain Parkway",
    "iso:country":"US",
    "sg:address":"24135 Magic Mountain Parkway",
    "sg:city":"Santa Clarita",
    "sg:classifiers":[
        {
            "category":"Building & Trades",
            "subcategory":"Construction",
            "type":"Services"
        }
    ],
    "sg:phone":"+1 661 673 1792",
    "sg:postcode":"91355",
    "sg:province":"CA",
    "sg:tags":[
        "contractor"
    ],
    "sg:website":"california-garage-door-services.com",
    "wof:name":"California Repair Services",
    "wof:placetype":"venue"
},
  "geometry": {"coordinates":[-118.560975,34.419337],"type":"Point"}
}