{
  "type": "Feature",
  "properties": {
    "addr:full":"18582 Beach Blvd Ste 223 Huntington Beach CA 92648",
    "addr:housenumber":"18582",
    "addr:postcode":"92648",
    "addr:street":"Beach Blvd Ste 223",
    "iso:country":"US",
    "sg:address":"18582 Beach Blvd Ste 223",
    "sg:city":"Huntington Beach",
    "sg:classifiers":[
        {
            "category":"Building & Trades",
            "subcategory":"Plumbing",
            "type":"Services"
        }
    ],
    "sg:phone":"+1 714 465 4847",
    "sg:postcode":"92648",
    "sg:province":"CA",
    "wof:name":"J & M Plumbing",
    "wof:placetype":"venue"
},
  "geometry": {"coordinates":[-117.98853699999999,33.692601],"type":"Point"}
}