{
  "type": "Feature",
  "properties": {
    "addr:full":"17975 Sky Park Cir Irvine CA 92614",
    "addr:housenumber":"17975",
    "addr:postcode":"92614",
    "addr:street":"Sky Park Cir",
    "iso:country":"US",
    "sg:address":"17975 Sky Park Cir",
    "sg:city":"Irvine",
    "sg:classifiers":[
        {
            "category":"Building & Trades",
            "subcategory":"Electrical",
            "type":"Services"
        }
    ],
    "sg:phone":"+1 949 261 9400",
    "sg:postcode":"92614",
    "sg:province":"CA",
    "sg:tags":[
        "electrical",
        "contractor"
    ],
    "wof:name":"Pacificom Intelligent Cabling",
    "wof:placetype":"venue"
},
  "geometry": {"coordinates":[-117.859858,33.689343],"type":"Point"}
}