{
  "type": "Feature",
  "properties": {
    "addr:full":"3513 Whittier Boulevard Los Angeles CA 90023",
    "addr:housenumber":"3513",
    "addr:postcode":"90023",
    "addr:street":"Whittier Boulevard",
    "iso:country":"US",
    "sg:address":"3513 Whittier Boulevard",
    "sg:city":"Los Angeles",
    "sg:classifiers":[
        {
            "category":"Health Services",
            "subcategory":"Doctor",
            "type":"Services"
        }
    ],
    "sg:phone":"+1 323 262 1814",
    "sg:postcode":"90023",
    "sg:province":"CA",
    "wof:name":"Alpha Omega Radiology",
    "wof:placetype":"venue"
},
  "geometry": {"coordinates":[-118.198002,34.026588],"type":"Point"}
}