{
  "type": "Feature",
  "properties": {
    "iso:country":"US",
    "sg:address":"440 Illinois St",
    "sg:city":"Vallejo",
    "sg:classifiers":[
        {
            "category":"Building & Trades",
            "subcategory":"Construction",
            "type":"Services"
        }
    ],
    "sg:phone":"+1 707 554 9950",
    "sg:postcode":"94590",
    "sg:province":"CA",
    "sg:tags":[
        "residential"
    ],
    "wof:name":"Pearson Construction",
    "wof:placetype":"venue"
},
  "geometry": {"coordinates":[-122.25188199999999,38.112028],"type":"Point"}
}