{
  "type": "Feature",
  "properties": {
    "iso:country":"US",
    "sg:address":"8728 Imperial Hwy",
    "sg:city":"Downey",
    "sg:classifiers":[
        {
            "category":"Health Services",
            "subcategory":"Dentist",
            "type":"Services"
        }
    ],
    "sg:phone":"+1 562 862 9199",
    "sg:postcode":"90242",
    "sg:province":"CA",
    "wof:name":"Dr Niranjan J Shah",
    "wof:placetype":"venue"
},
  "geometry": {"coordinates":[-118.139999,33.917801],"type":"Point"}
}