{
  "type": "Feature",
  "properties": {
    "addr:full":"18835 Nandina Ave Riverside CA 92508",
    "addr:housenumber":"18835",
    "addr:postcode":"92508",
    "addr:street":"Nandina Ave",
    "iso:country":"US",
    "sg:address":"18835 Nandina Ave",
    "sg:city":"Riverside",
    "sg:classifiers":[
        {
            "category":"Shopping",
            "subcategory":"Florist",
            "type":"Retail Goods"
        }
    ],
    "sg:phone":"+1 951 780 1414",
    "sg:postcode":"92508",
    "sg:province":"CA",
    "sg:tags":[
        "supply"
    ],
    "wof:name":"Torres Nursery",
    "wof:placetype":"venue"
},
  "geometry": {"coordinates":[-117.335267,33.865375],"type":"Point"}
}