{
  "type": "Feature",
  "properties": {
    "iso:country":"US",
    "sg:address":"1172 N Western Ave",
    "sg:city":"Los Angeles",
    "sg:classifiers":[
        {
            "category":"Retail",
            "subcategory":"Auto Repair",
            "type":"Services"
        }
    ],
    "sg:phone":"+1 323 465 2166",
    "sg:postcode":"90029",
    "sg:province":"CA",
    "sg:tags":[
        "repairing",
        "automobile"
    ],
    "wof:name":"AAA Discount Muffler",
    "wof:placetype":"venue"
},
  "geometry": {"coordinates":[-118.308998,34.092701],"type":"Point"}
}