{
  "type": "Feature",
  "properties": {
    "iso:country":"US",
    "sg:address":"1432 Mandeville Pl",
    "sg:city":"Escondido",
    "sg:classifiers":[
        {
            "category":"Professional",
            "subcategory":"Computer Services",
            "type":"Services"
        },
        {
            "category":"Internet Cafe",
            "subcategory":"None",
            "type":"Food & Drink"
        }
    ],
    "sg:phone":"+1 760 747 6922",
    "sg:postcode":"92029",
    "sg:province":"CA",
    "sg:tags":[
        "product",
        "software"
    ],
    "wof:name":"Wavecon",
    "wof:placetype":"venue"
},
  "geometry": {"coordinates":[-117.09886899999999,33.087124],"type":"Point"}
}