{
  "type": "Feature",
  "properties": {
    "iso:country":"US",
    "sg:address":"459 Marvin Way",
    "sg:city":"Dixon",
    "sg:classifiers":[
        {
            "category":"Building & Trades",
            "subcategory":"Electrical",
            "type":"Services"
        }
    ],
    "sg:phone":"+1 707 678 1198",
    "sg:postcode":"95620",
    "sg:province":"CA",
    "sg:tags":[
        "electric",
        "contractor"
    ],
    "wof:name":"R D Melton Co",
    "wof:placetype":"venue"
},
  "geometry": {"coordinates":[-121.829454,38.444729],"type":"Point"}
}