{
  "type": "Feature",
  "properties": {
    "iso:country":"US",
    "sg:address":"9322 Madison Ave",
    "sg:city":"Orangevale",
    "sg:classifiers":[
        {
            "category":"Professional",
            "type":"Services"
        }
    ],
    "sg:phone":"+1 916 989 6975",
    "sg:postcode":"95662",
    "sg:province":"CA",
    "sg:tags":[
        "establishment"
    ],
    "wof:name":"Bnng Mc Phrn Intr Inc",
    "wof:placetype":"venue"
},
  "geometry": {"coordinates":[-121.203462,38.6715],"type":"Point"}
}