{
  "type": "Feature",
  "properties": {
    "addr:full":"1331 T St Sacramento CA 95811",
    "addr:housenumber":"1331",
    "addr:postcode":"95811",
    "addr:street":"T St",
    "iso:country":"US",
    "sg:address":"1331 T St",
    "sg:city":"Sacramento",
    "sg:classifiers":[
        {
            "category":"Professional",
            "subcategory":"Engineering",
            "type":"Services"
        }
    ],
    "sg:phone":"+1 916 446 8182",
    "sg:postcode":"95811",
    "sg:province":"CA",
    "sg:tags":[
        "consulting",
        "engineer",
        "contractor"
    ],
    "wof:name":"Neema Engineering Construction Inc",
    "wof:placetype":"venue"
},
  "geometry": {"coordinates":[-121.493589,38.56805],"type":"Point"}
}