{
  "type": "Feature",
  "properties": {
    "iso:country":"US",
    "sg:address":"1187 Coast Village Rd",
    "sg:city":"Santa Barbara",
    "sg:classifiers":[
        {
            "category":"Communications",
            "subcategory":"Radio Station",
            "type":"Services"
        }
    ],
    "sg:phone":"+1 805 566 9988",
    "sg:postcode":"93108",
    "sg:province":"CA",
    "sg:tags":[
        "broadcast"
    ],
    "wof:name":"Garden Gossip",
    "wof:placetype":"venue"
},
  "geometry": {"coordinates":[-119.64746,34.421356],"type":"Point"}
}