{
  "type": "Feature",
  "properties": {
    "addr:full":"7582 Hardy Ln Granite Bay CA 95746",
    "addr:housenumber":"7582",
    "addr:postcode":"95746",
    "addr:street":"Hardy Ln",
    "iso:country":"US",
    "sg:address":"7582 Hardy Ln",
    "sg:city":"Granite Bay",
    "sg:classifiers":[
        {
            "category":"Wholesale",
            "subcategory":"Construction Materials",
            "type":"Manufacturing & Wholesale Goods"
        }
    ],
    "sg:phone":"+1 916 791 4568",
    "sg:postcode":"95746",
    "sg:province":"CA",
    "wof:name":"Golden State Millwork",
    "wof:placetype":"venue"
},
  "geometry": {"coordinates":[-121.193736,38.758323],"type":"Point"}
}