{
  "type": "Feature",
  "properties": {
    "iso:country":"US",
    "sg:address":"6905 Stockton Blvd Ste 20",
    "sg:city":"Sacramento",
    "sg:classifiers":[
        {
            "category":"Professional",
            "subcategory":"Accounting & Tax Preparation",
            "type":"Services"
        }
    ],
    "sg:phone":"+1 916 392 8200",
    "sg:postcode":"95823",
    "sg:province":"CA",
    "sg:tags":[
        "bookkeeping",
        "return",
        "preparation-business",
        "billing"
    ],
    "wof:name":"Valley Bookkeeping & Tax Service",
    "wof:placetype":"venue"
},
  "geometry": {"coordinates":[-121.43130499999999,38.500753],"type":"Point"}
}