{
  "type": "Feature",
  "properties": {
    "iso:country":"US",
    "sg:address":"1064 N Petaluma St",
    "sg:city":"Tulare",
    "sg:classifiers":[
        {
            "category":"Wholesale",
            "subcategory":"Machinery & Supplies",
            "type":"Manufacturing & Wholesale Goods"
        }
    ],
    "sg:phone":"+1 559 688 1360",
    "sg:postcode":"93274",
    "sg:province":"CA",
    "sg:tags":[
        "equipment",
        "establishment"
    ],
    "wof:name":"Express Popcorn",
    "wof:placetype":"venue"
},
  "geometry": {"coordinates":[-119.36520899999999,36.22293],"type":"Point"}
}