{
  "type": "Feature",
  "properties": {
    "addr:full":"2107 James Ave South Lake Tahoe CA 96150",
    "addr:housenumber":"2107",
    "addr:postcode":"96150",
    "addr:street":"James Ave",
    "iso:country":"US",
    "sg:address":"2107 James Ave",
    "sg:city":"South Lake Tahoe",
    "sg:classifiers":[
        {
            "category":"Education",
            "subcategory":"Dance Studio",
            "type":"Public Place"
        }
    ],
    "sg:phone":"+1 530 541 7211",
    "sg:postcode":"96150",
    "sg:province":"CA",
    "sg:tags":[
        "instruction",
        "dancing"
    ],
    "wof:name":"Marcia Sarosik Dance Studio",
    "wof:placetype":"venue"
},
  "geometry": {"coordinates":[-120.00107,38.916762],"type":"Point"}
}