{
  "type": "Feature",
  "properties": {
    "addr:full":"171 Branham Ln Ste 9 San Jose CA 95136",
    "addr:housenumber":"171",
    "addr:postcode":"95136",
    "addr:street":"Branham Ln Ste 9",
    "iso:country":"US",
    "sg:address":"171 Branham Ln Ste 9",
    "sg:city":"San Jose",
    "sg:classifiers":[
        {
            "category":"Health Services",
            "subcategory":"Dentist",
            "type":"Services"
        }
    ],
    "sg:phone":"+1 408 229 6199",
    "sg:postcode":"95136",
    "sg:province":"CA",
    "wof:name":"Branham Dental Care",
    "wof:placetype":"venue"
},
  "geometry": {"coordinates":[-121.834,37.266102],"type":"Point"}
}