{
  "type": "Feature",
  "properties": {
    "iso:country":"US",
    "sg:address":"726 Brentwood Dr",
    "sg:city":"San Jose",
    "sg:classifiers":[
        {
            "category":"Health Services",
            "subcategory":"Nursing And Care Facility",
            "type":"Services"
        }
    ],
    "sg:phone":"+1 408 865 1267",
    "sg:postcode":"95129",
    "sg:province":"CA",
    "sg:tags":[
        "home",
        "retirement",
        "community"
    ],
    "wof:name":"Rose Meadows Elder Care",
    "wof:placetype":"venue"
},
  "geometry": {"coordinates":[-121.987104,37.313987],"type":"Point"}
}