{
  "type": "Feature",
  "properties": {
    "iso:country":"US",
    "sg:address":"1611 Solano Way",
    "sg:city":"Concord",
    "sg:classifiers":[
        {
            "category":"Professional",
            "type":"Services"
        }
    ],
    "sg:phone":"+1 925 687 6445",
    "sg:postcode":"94520",
    "sg:province":"CA",
    "wof:name":"Syufy",
    "wof:placetype":"venue"
},
  "geometry": {"coordinates":[-122.053,37.997933],"type":"Point"}
}