{
  "type": "Feature",
  "properties": {
    "addr:full":"1119 W Alvarez Ave Orange CA 92868",
    "addr:housenumber":"1119",
    "addr:postcode":"92868",
    "addr:street":"W Alvarez Ave",
    "iso:country":"US",
    "sg:address":"1119 W Alvarez Ave",
    "sg:city":"Orange",
    "sg:classifiers":[
        {
            "category":"Autos & Motor Vehicles",
            "subcategory":"Auto Supplies",
            "type":"Retail Goods"
        },
        {
            "category":"Retail",
            "subcategory":"Auto Repair",
            "type":"Services"
        }
    ],
    "sg:phone":"+1 714 633 4208",
    "sg:postcode":"92868",
    "sg:province":"CA",
    "sg:tags":[
        "automobile",
        "part",
        "accessory"
    ],
    "sg:website":"http://www.reyesalt.qpg.com/",
    "wof:name":"Reyes Alternators",
    "wof:placetype":"venue"
},
  "geometry": {"coordinates":[-117.865008,33.79812],"type":"Point"}
}