{
  "type": "Feature",
  "properties": {
    "addr:full":"101 Orange Ave Coronado CA 92118",
    "addr:housenumber":"101",
    "addr:postcode":"92118",
    "addr:street":"Orange Ave",
    "iso:country":"US",
    "sg:address":"101 Orange Ave",
    "sg:city":"Coronado",
    "sg:classifiers":[
        {
            "category":"Real Estate",
            "subcategory":"Real Estate Services",
            "type":"Services"
        }
    ],
    "sg:phone":"+1 619 435 8722",
    "sg:postcode":"92118",
    "sg:province":"CA",
    "sg:website":"www.kathykoop.com/",
    "wof:name":"The Kathy Koop Group Real Estate",
    "wof:placetype":"venue"
},
  "geometry": {"coordinates":[-117.171993,32.698456],"type":"Point"}
}