{
  "type": "Feature",
  "properties": {
    "addr:full":"633 W Katella Ave Orange CA 92867",
    "addr:housenumber":"633",
    "addr:postcode":"92867",
    "addr:street":"W Katella Ave",
    "iso:country":"US",
    "sg:address":"633 W Katella Ave",
    "sg:city":"Orange",
    "sg:classifiers":[
        {
            "category":"Retail",
            "subcategory":"Repair Shop",
            "type":"Services"
        }
    ],
    "sg:phone":"+1 714 639 5579",
    "sg:postcode":"92867",
    "sg:province":"CA",
    "sg:tags":[
        "plumbing",
        "drain",
        "cleaning",
        "sewer"
    ],
    "wof:name":"Sunset Rooter & Plumbing",
    "wof:placetype":"venue"
},
  "geometry": {"coordinates":[-117.85756600000001,33.809108],"type":"Point"}
}