{
  "type": "Feature",
  "properties": {
    "addr:full":"1433 Superior Ave Newport Beach CA 92663",
    "addr:housenumber":"1433",
    "addr:postcode":"92663",
    "addr:street":"Superior Ave",
    "iso:country":"US",
    "sg:address":"1433 Superior Ave",
    "sg:city":"Newport Beach",
    "sg:classifiers":[
        {
            "category":"Autos & Motor Vehicles",
            "subcategory":"Automobile Sales",
            "type":"Retail Goods"
        }
    ],
    "sg:phone":"+1 949 233 2364",
    "sg:postcode":"92663",
    "sg:province":"CA",
    "wof:name":"Biyaku Co",
    "wof:placetype":"venue"
},
  "geometry": {"coordinates":[-117.933291,33.626351],"type":"Point"}
}