{
  "type": "Feature",
  "properties": {
    "addr:full":"16315 Piuma Ave Cerritos CA 90703",
    "addr:housenumber":"16315",
    "addr:postcode":"ca 90703",
    "addr:street":"Piuma Ave",
    "iso:country":"US",
    "sg:address":"16315 Piuma Ave",
    "sg:city":"Cerritos",
    "sg:classifiers":[
        {
            "category":"Building & Trades",
            "subcategory":"Construction",
            "type":"Services"
        }
    ],
    "sg:phone":"+1 714 963 5456",
    "sg:postcode":"90703",
    "sg:province":"CA",
    "sg:tags":[
        "fire",
        "restoration",
        "damage"
    ],
    "wof:name":"Qwikresponse Disaster Control",
    "wof:placetype":"venue"
},
  "geometry": {"coordinates":[-118.105921,33.886819],"type":"Point"}
}