{
  "type": "Feature",
  "properties": {
    "iso:country":"US",
    "sg:address":"675 Texas St",
    "sg:city":"Fairfield",
    "sg:classifiers":[
        {
            "category":"Recreation",
            "type":"Entertainment"
        }
    ],
    "sg:phone":"+1 707 784 1847",
    "sg:postcode":"94533",
    "sg:province":"CA",
    "sg:tags":[
        "parks"
    ],
    "wof:name":"Solano County Regional Parks",
    "wof:placetype":"venue"
},
  "geometry": {"coordinates":[-122.04107399999999,38.249143],"type":"Point"}
}