{
  "type": "Feature",
  "properties": {
    "addr:full":"4790 47th Avenue Sacramento CA 95824",
    "addr:housenumber":"4790",
    "addr:postcode":"95824",
    "addr:street":"47Th Avenue",
    "iso:country":"US",
    "sg:address":"4790 47th Avenue",
    "sg:city":"Sacramento",
    "sg:classifiers":[
        {
            "category":"Autos & Motor Vehicles",
            "subcategory":"Fuel & Gas Station",
            "type":"Retail Goods"
        }
    ],
    "sg:phone":"+1 916 391 9611",
    "sg:postcode":"95824",
    "sg:province":"CA",
    "wof:name":"Petro Star Gas Auto Repair & Smog",
    "wof:placetype":"venue"
},
  "geometry": {"coordinates":[-121.45063500000001,38.510558],"type":"Point"}
}