{
  "type": "Feature",
  "properties": {
    "iso:country":"US",
    "sg:address":"351 Cedar St",
    "sg:city":"Ventura",
    "sg:classifiers":[
        {
            "category":"Food & Beverages",
            "subcategory":"Specialty",
            "type":"Retail Goods"
        }
    ],
    "sg:phone":"+1 805 643 4064",
    "sg:postcode":"93001",
    "sg:province":"CA",
    "sg:tags":[
        "gourmet",
        "shop"
    ],
    "wof:name":"Chile Head Salsa",
    "wof:placetype":"venue"
},
  "geometry": {"coordinates":[-119.298727,34.283531],"type":"Point"}
}