{
  "type": "Feature",
  "properties": {
    "iso:country":"US",
    "sg:address":"205 Main St",
    "sg:city":"Pleasanton",
    "sg:classifiers":[
        {
            "category":"Shopping",
            "type":"Retail Goods"
        }
    ],
    "sg:phone":"+1 925 417 3440",
    "sg:postcode":"94566",
    "sg:province":"CA",
    "sg:tags":[
        "pet",
        "shop"
    ],
    "wof:name":"Dog WYLD",
    "wof:placetype":"venue"
},
  "geometry": {"coordinates":[-121.878753,37.65671],"type":"Point"}
}