{
  "type": "Feature",
  "properties": {
    "addr:full":"4538 Cass St San Diego CA 92109",
    "addr:housenumber":"4538",
    "addr:postcode":"92109",
    "addr:street":"Cass St",
    "iso:country":"US",
    "sg:address":"4538 Cass St",
    "sg:city":"San Diego",
    "sg:classifiers":[
        {
            "category":"Real Estate",
            "subcategory":"Real Estate Services",
            "type":"Services"
        },
        {
            "category":"Real Estate",
            "subcategory":"Real Estate Agent",
            "type":"Services"
        }
    ],
    "sg:phone":"+1 619 952 5934",
    "sg:postcode":"92109",
    "sg:province":"CA",
    "wof:name":"Glenn Dewyea Prudential Dunn Realtors",
    "wof:placetype":"venue"
},
  "geometry": {"coordinates":[-117.251991,32.797796],"type":"Point"}
}