{
  "type": "Feature",
  "properties": {
    "iso:country":"US",
    "sg:address":"1625 E Shaw Ave",
    "sg:city":"Fresno",
    "sg:classifiers":[
        {
            "category":"Wholesale",
            "subcategory":"Fruits & Vegetables",
            "type":"Manufacturing & Wholesale Goods"
        }
    ],
    "sg:phone":"+1 559 230 0262",
    "sg:postcode":"93710",
    "sg:province":"CA",
    "sg:tags":[
        "shipper"
    ],
    "sg:website":"www.tomato.org",
    "wof:name":"Ca Fresh Growers Exchange",
    "wof:placetype":"venue"
},
  "geometry": {"coordinates":[-119.75460699999999,36.808514],"type":"Point"}
}