{
  "type": "Feature",
  "properties": {
    "iso:country":"US",
    "sg:address":"8215 Sunland Blvd",
    "sg:city":"Sun Valley",
    "sg:classifiers":[
        {
            "category":"Health Services",
            "subcategory":"Dentist",
            "type":"Services"
        }
    ],
    "sg:phone":"+1 818 381 5743",
    "sg:postcode":"91352",
    "sg:province":"CA",
    "wof:name":"Fresh Smile Dental Center",
    "wof:placetype":"venue"
},
  "geometry": {"coordinates":[-118.368495,34.219949],"type":"Point"}
}