{
  "type": "Feature",
  "properties": {
    "iso:country":"US",
    "sg:address":"1430 W 135th Street",
    "sg:city":"Gardena",
    "sg:classifiers":[
        {
            "category":"Retail",
            "subcategory":"Laundry & Dry Cleaning",
            "type":"Services"
        }
    ],
    "sg:phone":"+1 310 323 7246",
    "sg:postcode":"90249",
    "sg:province":"CA",
    "wof:name":"Ace Air Mfg",
    "wof:placetype":"venue"
},
  "geometry": {"coordinates":[-118.30119500000001,33.90929],"type":"Point"}
}