{
  "type": "Feature",
  "properties": {
    "iso:country":"US",
    "sg:address":"5701 State Farm Dr",
    "sg:city":"Rohnert Park",
    "sg:classifiers":[
        {
            "category":"Retail",
            "subcategory":"Portrait Studio",
            "type":"Services"
        }
    ],
    "sg:phone":"+1 707 527 6004",
    "sg:postcode":"94928",
    "sg:province":"CA",
    "sg:tags":[
        "photographer"
    ],
    "wof:name":"Creative Light Productions",
    "wof:placetype":"venue"
},
  "geometry": {"coordinates":[-122.708175,38.354783],"type":"Point"}
}