{
  "type": "Feature",
  "properties": {
    "addr:full":"546 Jay St Colusa CA 95932",
    "addr:housenumber":"546",
    "addr:postcode":"95932",
    "addr:street":"Jay St",
    "iso:country":"US",
    "sg:address":"546 Jay St",
    "sg:city":"Colusa",
    "sg:classifiers":[
        {
            "category":"Government",
            "subcategory":"Office",
            "type":"Public Place"
        }
    ],
    "sg:phone":"+1 530 458 0494",
    "sg:postcode":"95932",
    "sg:province":"CA",
    "sg:tags":[
        "federal",
        "affairs",
        "govt",
        "admin"
    ],
    "wof:name":"Us Veterans Affairs Dept",
    "wof:placetype":"venue"
},
  "geometry": {"coordinates":[-122.009152,39.213387],"type":"Point"}
}