{
  "type": "Feature",
  "properties": {
    "iso:country":"US",
    "sg:address":"5180 Mercedes Ave",
    "sg:city":"Atascadero",
    "sg:classifiers":[
        {
            "category":"Building & Trades",
            "subcategory":"Construction",
            "type":"Services"
        }
    ],
    "sg:phone":"+1 805 460 0129",
    "sg:postcode":"93422",
    "sg:province":"CA",
    "sg:tags":[
        "painter"
    ],
    "wof:name":"J C Coverings Painting",
    "wof:placetype":"venue"
},
  "geometry": {"coordinates":[-120.66120600000001,35.499587],"type":"Point"}
}