{
  "type": "Feature",
  "properties": {
    "iso:country":"US",
    "sg:address":"586 San Mateo Ave",
    "sg:city":"San Bruno",
    "sg:classifiers":[
        {
            "category":"Personal",
            "type":"Services"
        },
        {
            "category":"Restaurant",
            "type":"Food & Drink"
        }
    ],
    "sg:phone":"+1 650 873 1388",
    "sg:postcode":"94066",
    "sg:province":"CA",
    "sg:tags":[
        "burmese",
        "chinese"
    ],
    "sg:website":"www.innyalake.com/",
    "wof:name":"Innya Lake Restaurant",
    "wof:placetype":"venue"
},
  "geometry": {"coordinates":[-122.41100299999999,37.626202],"type":"Point"}
}