{
  "type": "Feature",
  "properties": {
    "iso:country":"US",
    "sg:address":"9250 Mason Ave",
    "sg:city":"Chatsworth",
    "sg:classifiers":[
        {
            "category":"Manufacturing",
            "subcategory":"Chemicals & Compounds",
            "type":"Manufacturing & Wholesale Goods"
        }
    ],
    "sg:phone":"+1 818 206 6700",
    "sg:postcode":"91311",
    "sg:province":"CA",
    "sg:tags":[
        "cosmetic"
    ],
    "wof:name":"Aware Products Inc",
    "wof:placetype":"venue"
},
  "geometry": {"coordinates":[-118.57979899999999,34.24273],"type":"Point"}
}