{
  "type": "Feature",
  "properties": {
    "addr:full":"44900 60th St W Lancaster CA 93536",
    "addr:housenumber":"44900",
    "addr:postcode":"93536",
    "addr:street":"60Th St W",
    "iso:country":"US",
    "sg:address":"44900 60th St W",
    "sg:city":"Lancaster",
    "sg:classifiers":[
        {
            "category":"Health Services",
            "subcategory":"Doctor",
            "type":"Services"
        }
    ],
    "sg:phone":"+1 661 945 8461",
    "sg:postcode":"93536",
    "sg:province":"CA",
    "sg:tags":[
        "medical",
        "general",
        "hospital",
        "specialty"
    ],
    "wof:name":"La County High Desert Hlth Sys",
    "wof:placetype":"venue"
},
  "geometry": {"coordinates":[-118.23662899999999,34.697167],"type":"Point"}
}