{
  "type": "Feature",
  "properties": {
    "addr:full":"3320 Cameron Park Dr Cameron Park CA 95682",
    "addr:housenumber":"3320",
    "addr:postcode":"95682",
    "addr:street":"Cameron Park Dr",
    "iso:country":"US",
    "sg:address":"3320 Cameron Park Dr",
    "sg:city":"Cameron Park",
    "sg:classifiers":[
        {
            "category":"Retail",
            "subcategory":"Auto Rental",
            "type":"Services"
        }
    ],
    "sg:phone":"+1 530 676 9658",
    "sg:postcode":"95682",
    "sg:province":"CA",
    "sg:tags":[
        "renting",
        "automobile"
    ],
    "sg:website":"www.davesrentacar.com",
    "wof:name":"Dave's Rent-A-Car",
    "wof:placetype":"venue"
},
  "geometry": {"coordinates":[-120.982253,38.680371],"type":"Point"}
}