{
  "type": "Feature",
  "properties": {
    "iso:country":"US",
    "sg:address":"632 Montana Ave",
    "sg:city":"Santa Monica",
    "sg:classifiers":[
        {
            "category":"Health Services",
            "subcategory":"Medical Lab",
            "type":"Services"
        }
    ],
    "sg:phone":"+1 310 587 3224",
    "sg:postcode":"90403",
    "sg:province":"CA",
    "sg:tags":[
        "laboratory"
    ],
    "wof:name":"Tri-Tech Dental Lab",
    "wof:placetype":"venue"
},
  "geometry": {"coordinates":[-118.502495,34.026138],"type":"Point"}
}