{
  "type": "Feature",
  "properties": {
    "addr:full":"3679 Main St Chula Vista CA 91911",
    "addr:housenumber":"3679",
    "addr:postcode":"91911",
    "addr:street":"Main St",
    "iso:country":"US",
    "sg:address":"3679 Main St",
    "sg:city":"Chula Vista",
    "sg:classifiers":[
        {
            "category":"Retail",
            "subcategory":"Repair Shop",
            "type":"Services"
        }
    ],
    "sg:phone":"+1 619 420 2008",
    "sg:postcode":"91911",
    "sg:province":"CA",
    "sg:tags":[
        "reupholstery",
        "furniture"
    ],
    "sg:website":"www.economy-upholstery.com",
    "wof:name":"Economy Upholstery",
    "wof:placetype":"venue"
},
  "geometry": {"coordinates":[-117.054001,32.594799],"type":"Point"}
}