{
  "type": "Feature",
  "properties": {
    "addr:full":"1619 E Denni St Wilmington CA 90744",
    "addr:housenumber":"1619",
    "addr:postcode":"90744",
    "addr:street":"E Denni St",
    "iso:country":"US",
    "sg:address":"1619 E Denni St",
    "sg:city":"Wilmington",
    "sg:classifiers":[
        {
            "category":"Wholesale",
            "subcategory":"Auto Parts",
            "type":"Manufacturing & Wholesale Goods"
        },
        {
            "category":"Wholesale",
            "subcategory":"Scrap",
            "type":"Manufacturing & Wholesale Goods"
        }
    ],
    "sg:phone":"+1 562 436 6116",
    "sg:postcode":"90744",
    "sg:province":"CA",
    "sg:tags":[
        "automobile",
        "material",
        "used",
        "wrecking"
    ],
    "wof:name":"A-Glen's Auto Wrecking",
    "wof:placetype":"venue"
},
  "geometry": {"coordinates":[-118.240346,33.785916],"type":"Point"}
}