{
  "type": "Feature",
  "properties": {
    "addr:full":"3347 Daisy Ct Hayward CA 94542",
    "addr:housenumber":"3347",
    "addr:postcode":"94542",
    "addr:street":"Daisy Ct",
    "iso:country":"US",
    "sg:address":"3347 Daisy Ct",
    "sg:city":"Hayward",
    "sg:classifiers":[
        {
            "category":"Autos & Motor Vehicles",
            "subcategory":"Auto Supplies",
            "type":"Retail Goods"
        }
    ],
    "sg:phone":"+1 510 783 4544",
    "sg:postcode":"94542",
    "sg:province":"CA",
    "sg:tags":[
        "automobile",
        "parts"
    ],
    "wof:name":"Crown Auto Parts",
    "wof:placetype":"venue"
},
  "geometry": {"coordinates":[-122.03568300000001,37.650002],"type":"Point"}
}