{
  "type": "Feature",
  "properties": {
    "iso:country":"US",
    "sg:address":"960 E Bonita Ave",
    "sg:city":"Pomona",
    "sg:classifiers":[
        {
            "category":"Professional",
            "subcategory":"Management & Consulting",
            "type":"Services"
        }
    ],
    "sg:phone":"+1 909 624 4227",
    "sg:postcode":"91767",
    "sg:province":"CA",
    "sg:tags":[
        "consultant",
        "relation",
        "labor"
    ],
    "wof:name":"Employer's Labor",
    "wof:placetype":"venue"
},
  "geometry": {"coordinates":[-117.73235099999999,34.096219],"type":"Point"}
}