{
  "type": "Feature",
  "properties": {
    "addr:full":"2400 Chanticleer Ave Santa Cruz CA 95062",
    "addr:housenumber":"2400",
    "addr:postcode":"95062",
    "addr:street":"Chanticleer Ave",
    "iso:country":"US",
    "sg:address":"2400 Chanticleer Ave",
    "sg:city":"Santa Cruz",
    "sg:classifiers":[
        {
            "category":"Home & Garden",
            "subcategory":"Home Furnishings",
            "type":"Retail Goods"
        }
    ],
    "sg:phone":"+1 831 475 6283",
    "sg:postcode":"95062",
    "sg:province":"CA",
    "sg:tags":[
        "glassware",
        "chinaware"
    ],
    "sg:website":"www.striniartglass.com",
    "wof:name":"Strini Art Glass",
    "wof:placetype":"venue"
},
  "geometry": {"coordinates":[-121.97895,36.983892],"type":"Point"}
}