{
  "type": "Feature",
  "properties": {
    "iso:country":"US",
    "sg:address":"4781 E Gettysburg Ave",
    "sg:city":"Fresno",
    "sg:classifiers":[
        {
            "category":"Social Services",
            "type":"Services"
        }
    ],
    "sg:phone":"+1 559 348 1856",
    "sg:postcode":"93726",
    "sg:province":"CA",
    "sg:tags":[
        "counselor",
        "marriage",
        "family"
    ],
    "wof:name":"Marriage Family Therapist",
    "wof:placetype":"venue"
},
  "geometry": {"coordinates":[-119.737212,36.801385],"type":"Point"}
}