{
  "type": "Feature",
  "properties": {
    "iso:country":"US",
    "sg:address":"372 Wilson Ave",
    "sg:city":"Sacramento",
    "sg:classifiers":[
        {
            "category":"Banks & Credit Unions",
            "subcategory":"Financial Services",
            "type":"Services"
        }
    ],
    "sg:phone":"+1 707 980 7901",
    "sg:postcode":"95833",
    "sg:province":"CA",
    "sg:tags":[
        "management",
        "investment"
    ],
    "wof:name":"The Beracah Investment",
    "wof:placetype":"venue"
},
  "geometry": {"coordinates":[-121.47132000000001,38.613937],"type":"Point"}
}