{
  "type": "Feature",
  "properties": {
    "iso:country":"US",
    "sg:address":"334 Via Vera Cruz",
    "sg:city":"San Marcos",
    "sg:classifiers":[
        {
            "category":"Professional",
            "subcategory":"Accounting & Tax Preparation",
            "type":"Services"
        }
    ],
    "sg:phone":"+1 760 471 9229",
    "sg:postcode":"92078",
    "sg:province":"CA",
    "sg:tags":[
        "bookkeeping",
        "return",
        "filing",
        "general"
    ],
    "wof:name":"A2Z Bookkeeping & Tax Svc",
    "wof:placetype":"venue"
},
  "geometry": {"coordinates":[-117.188523,33.136085],"type":"Point"}
}