{
  "type": "Feature",
  "properties": {
    "addr:full":"4156 Somerset Dr Los Angeles CA 90008",
    "addr:housenumber":"4156",
    "addr:postcode":"90008",
    "addr:street":"Somerset Dr",
    "iso:country":"US",
    "sg:address":"4156 Somerset Dr",
    "sg:city":"Los Angeles",
    "sg:classifiers":[
        {
            "category":"Personal",
            "subcategory":"Beauty Salon",
            "type":"Services"
        }
    ],
    "sg:phone":"+1 323 294 1116",
    "sg:postcode":"90008",
    "sg:province":"CA",
    "wof:name":"42 GC Beauty Salon",
    "wof:placetype":"venue"
},
  "geometry": {"coordinates":[-118.342198,34.010532],"type":"Point"}
}