{
  "type": "Feature",
  "properties": {
    "iso:country":"US",
    "sg:address":"25 N Pilgrim St",
    "sg:city":"Stockton",
    "sg:classifiers":[
        {
            "category":"Wholesale",
            "subcategory":"Machinery & Supplies",
            "type":"Manufacturing & Wholesale Goods"
        }
    ],
    "sg:phone":"+1 209 466 3041",
    "sg:postcode":"95205",
    "sg:province":"CA",
    "sg:tags":[
        "truck"
    ],
    "wof:name":"GMS Western Lift Truck",
    "wof:placetype":"venue"
},
  "geometry": {"coordinates":[-121.275746,37.955899],"type":"Point"}
}