{
  "type": "Feature",
  "properties": {
    "iso:country":"US",
    "sg:address":"15306 Valley Blvd",
    "sg:city":"City Of Industry",
    "sg:classifiers":[
        {
            "category":"Wholesale",
            "subcategory":"Durable Goods & Equipment",
            "type":"Manufacturing & Wholesale Goods"
        }
    ],
    "sg:phone":"+1 626 369 5440",
    "sg:postcode":"91746",
    "sg:province":"CA",
    "sg:tags":[
        "importer"
    ],
    "wof:name":"Universalink Trading Inc",
    "wof:placetype":"venue"
},
  "geometry": {"coordinates":[-117.961095,34.024492],"type":"Point"}
}