{
  "type": "Feature",
  "properties": {
    "iso:country":"US",
    "sg:address":"12002 Harbor Blvd",
    "sg:city":"Garden Grove",
    "sg:classifiers":[
        {
            "category":"Shopping",
            "subcategory":"Pharmacy",
            "type":"Retail Goods"
        },
        {
            "category":"Food & Beverages",
            "subcategory":"Groceries & Convenience Stores",
            "type":"Retail Goods"
        }
    ],
    "sg:phone":"+1 714 663 2850",
    "sg:postcode":"92840",
    "sg:province":"CA",
    "sg:tags":[
        "drugstore"
    ],
    "sg:website":"www.walgreens.com",
    "wof:name":"Walgreens Drug Store",
    "wof:placetype":"venue"
},
  "geometry": {"coordinates":[-117.915001,33.7882],"type":"Point"}
}