{
  "type": "Feature",
  "properties": {
    "addr:full":"507 Merchant St Vacaville CA 95688",
    "addr:housenumber":"507",
    "addr:postcode":"95688",
    "addr:street":"Merchant St",
    "iso:country":"US",
    "sg:address":"507 Merchant St",
    "sg:city":"Vacaville",
    "sg:classifiers":[
        {
            "category":"Health Services",
            "subcategory":"Chiropractor",
            "type":"Services"
        }
    ],
    "sg:phone":"+1 707 449 9217",
    "sg:postcode":"95688",
    "sg:province":"CA",
    "sg:tags":[
        "chiropractic"
    ],
    "sg:website":"http://www.richardsonchiropractic.com",
    "wof:name":"Richardson & Taylor Chiropractic Care",
    "wof:placetype":"venue"
},
  "geometry": {"coordinates":[-121.991108,38.353765],"type":"Point"}
}