{
  "type": "Feature",
  "properties": {
    "addr:full":"12747 Saticoy St North Hollywood CA 91605",
    "addr:housenumber":"12747",
    "addr:postcode":"91605",
    "addr:street":"Saticoy St",
    "iso:country":"US",
    "sg:address":"12747 Saticoy St",
    "sg:city":"North Hollywood",
    "sg:classifiers":[
        {
            "category":"Wholesale",
            "subcategory":"Drugs",
            "type":"Manufacturing & Wholesale Goods"
        }
    ],
    "sg:phone":"+1 818 759 1050",
    "sg:postcode":"91605",
    "sg:province":"CA",
    "sg:tags":[
        "shop",
        "beauty"
    ],
    "wof:name":"Jessicas Cosmetics",
    "wof:placetype":"venue"
},
  "geometry": {"coordinates":[-118.41103200000001,34.206342],"type":"Point"}
}