{
  "type": "Feature",
  "properties": {
    "iso:country":"US",
    "sg:address":"230 Alberta Ave",
    "sg:city":"San Carlos",
    "sg:classifiers":[
        {
            "category":"Retail",
            "subcategory":"Animal Services",
            "type":"Services"
        }
    ],
    "sg:phone":"+1 650 592 4920",
    "sg:postcode":"94070",
    "sg:province":"CA",
    "sg:tags":[
        "pet",
        "boarding",
        "sitting"
    ],
    "wof:name":"1 Guys Pet Care Svc",
    "wof:placetype":"venue"
},
  "geometry": {"coordinates":[-122.25535499999999,37.488189],"type":"Point"}
}