{
  "type": "Feature",
  "properties": {
    "iso:country":"US",
    "sg:address":"2818 Valley Knolls Rd",
    "sg:city":"Jamul",
    "sg:classifiers":[
        {
            "category":"Building & Trades",
            "subcategory":"Construction",
            "type":"Services"
        }
    ],
    "sg:phone":"+1 619 669 4894",
    "sg:postcode":"91935",
    "sg:province":"CA",
    "sg:tags":[
        "repairing",
        "remodeling",
        "contractor"
    ],
    "wof:name":"Robert Traverson Building",
    "wof:placetype":"venue"
},
  "geometry": {"coordinates":[-116.882732,32.70514],"type":"Point"}
}