{
  "type": "Feature",
  "properties": {
    "addr:full":"115 N Fairfax Ave Los Angeles CA 90036",
    "addr:housenumber":"115",
    "addr:postcode":"90036",
    "addr:street":"N Fairfax Ave",
    "iso:country":"US",
    "sg:address":"115 N Fairfax Ave",
    "sg:city":"Los Angeles",
    "sg:classifiers":[
        {
            "category":"Retail",
            "subcategory":"Laundry & Dry Cleaning",
            "type":"Services"
        }
    ],
    "sg:phone":"+1 323 935 4150",
    "sg:postcode":"90036",
    "sg:province":"CA",
    "wof:name":"Mr Clean Cleaners",
    "wof:placetype":"venue"
},
  "geometry": {"coordinates":[-118.36141600000001,34.074689],"type":"Point"}
}