{
  "type": "Feature",
  "properties": {
    "iso:country":"US",
    "sg:address":"9730 Follett Dr",
    "sg:city":"Santee",
    "sg:classifiers":[
        {
            "category":"Wholesale",
            "subcategory":"Vending Machines",
            "type":"Manufacturing & Wholesale Goods"
        }
    ],
    "sg:phone":"+1 619 562 7022",
    "sg:postcode":"92071",
    "sg:province":"CA",
    "sg:tags":[
        "operator"
    ],
    "wof:name":"Executive Vending Service",
    "wof:placetype":"venue"
},
  "geometry": {"coordinates":[-116.964111,32.852497],"type":"Point"}
}