{
  "type": "Feature",
  "properties": {
    "iso:country":"US",
    "sg:address":"1715 Minnewawa Ave",
    "sg:city":"Clovis",
    "sg:classifiers":[
        {
            "category":"Real Estate",
            "subcategory":"Real Estate Agent",
            "type":"Services"
        }
    ],
    "sg:phone":"+1 559 325 2956",
    "sg:postcode":"93612",
    "sg:province":"CA",
    "wof:name":"Fresno Arrow Realty",
    "wof:placetype":"venue"
},
  "geometry": {"coordinates":[-119.70898,36.810351],"type":"Point"}
}