{
  "type": "Feature",
  "properties": {
    "addr:full":"25461 Alicia Parkway Laguna Hills CA 92653",
    "addr:housenumber":"25461",
    "addr:postcode":"92653",
    "addr:street":"Alicia Parkway",
    "iso:country":"US",
    "sg:address":"25461 Alicia Parkway",
    "sg:city":"Laguna Hills",
    "sg:classifiers":[
        {
            "category":"Professional",
            "subcategory":"Employment Agencies",
            "type":"Services"
        }
    ],
    "sg:phone":"+1 949 609 0291",
    "sg:postcode":"92653",
    "sg:province":"CA",
    "sg:website":"www.laborready.com",
    "wof:name":"Labor Ready",
    "wof:placetype":"venue"
},
  "geometry": {"coordinates":[-117.698604,33.592783],"type":"Point"}
}