{
  "type": "Feature",
  "properties": {
    "iso:country":"US",
    "sg:address":"786 Solana Dr",
    "sg:city":"Lafayette",
    "sg:classifiers":[
        {
            "category":"Real Estate",
            "subcategory":"Architect",
            "type":"Services"
        }
    ],
    "sg:phone":"+1 925 284 7333",
    "sg:postcode":"94549",
    "sg:province":"CA",
    "wof:name":"AAU-Architectural Arts Unltd",
    "wof:placetype":"venue"
},
  "geometry": {"coordinates":[-122.117021,37.880741],"type":"Point"}
}