{
  "type": "Feature",
  "properties": {
    "addr:full":"271 Via Barranca Greenbrae CA 94904",
    "addr:housenumber":"271",
    "addr:postcode":"94904",
    "addr:street":"Via Barranca",
    "iso:country":"US",
    "sg:address":"271 Via Barranca",
    "sg:city":"Greenbrae",
    "sg:classifiers":[
        {
            "category":"Organizations",
            "subcategory":"Non-profit Organization",
            "type":"Services"
        }
    ],
    "sg:phone":"+1 415 461 9561",
    "sg:postcode":"94904",
    "sg:province":"CA",
    "sg:tags":[
        "charity",
        "foundations-educational",
        "philanthropic",
        "research"
    ],
    "wof:name":"Clipped Wings United Airlines Alumnae & Current Flight Attendance",
    "wof:placetype":"venue"
},
  "geometry": {"coordinates":[-122.520499,37.949825],"type":"Point"}
}