{
  "type": "Feature",
  "properties": {
    "addr:full":"1432 W Barstow Ave Fresno CA 93711",
    "addr:housenumber":"1432",
    "addr:postcode":"93711",
    "addr:street":"W Barstow Ave",
    "iso:country":"US",
    "sg:address":"1432 W Barstow Ave",
    "sg:city":"Fresno",
    "sg:classifiers":[
        {
            "category":"Building & Trades",
            "subcategory":"Construction",
            "type":"Services"
        }
    ],
    "sg:phone":"+1 559 437 9409",
    "sg:postcode":"93711",
    "sg:province":"CA",
    "sg:tags":[
        "plastering",
        "contractor"
    ],
    "wof:name":"Ronald Potter Plastering",
    "wof:placetype":"venue"
},
  "geometry": {"coordinates":[-119.821286,36.815616],"type":"Point"}
}