{
  "type": "Feature",
  "properties": {
    "iso:country":"US",
    "sg:address":"5201 E Anaheim Rd",
    "sg:city":"Long Beach",
    "sg:classifiers":[
        {
            "category":"Building & Trades",
            "subcategory":"Cleaning & Sanitation",
            "type":"Services"
        }
    ],
    "sg:phone":"+1 562 437 1272",
    "sg:postcode":"90815",
    "sg:province":"CA",
    "sg:tags":[
        "house"
    ],
    "wof:name":"E Z Way House Cleaning",
    "wof:placetype":"venue"
},
  "geometry": {"coordinates":[-118.133031,33.784516],"type":"Point"}
}