{
  "type": "Feature",
  "properties": {
    "iso:country":"US",
    "sg:address":"5180 E Jensen Ave",
    "sg:city":"Fresno",
    "sg:classifiers":[
        {
            "category":"Freight",
            "type":"Transportation"
        }
    ],
    "sg:phone":"+1 559 237 6074",
    "sg:postcode":"93725",
    "sg:province":"CA",
    "sg:tags":[
        "organ",
        "trucking",
        "moving",
        "operator",
        "piano",
        "local"
    ],
    "wof:name":"Rachael's Furniture Moving",
    "wof:placetype":"venue"
},
  "geometry": {"coordinates":[-119.719618,36.707606],"type":"Point"}
}