{
  "type": "Feature",
  "properties": {
    "iso:country":"US",
    "sg:address":"44352 S Grimmer Blvd",
    "sg:city":"Fremont",
    "sg:classifiers":[
        {
            "category":"Professional",
            "subcategory":"Advertising",
            "type":"Services"
        }
    ],
    "sg:phone":"+1 510 490 5297",
    "sg:postcode":"94538",
    "sg:province":"CA",
    "sg:tags":[
        "mailing",
        "shipping"
    ],
    "sg:website":"www.roadrunnermailing.com",
    "wof:name":"Roadrunner Mailing Svc Inc",
    "wof:placetype":"venue"
},
  "geometry": {"coordinates":[-121.954998,37.502685],"type":"Point"}
}