{
  "type": "Feature",
  "properties": {
    "iso:country":"US",
    "sg:address":"1060 N Batavia St",
    "sg:city":"Orange",
    "sg:classifiers":[
        {
            "category":"Banks & Credit Unions",
            "subcategory":"Financial Services",
            "type":"Services"
        }
    ],
    "sg:phone":"+1 714 744 4402",
    "sg:postcode":"92867",
    "sg:province":"CA",
    "sg:tags":[
        "broker",
        "mortgage"
    ],
    "wof:name":"Home Funding Solutions Inc.",
    "wof:placetype":"venue"
},
  "geometry": {"coordinates":[-117.861887,33.805323],"type":"Point"}
}