{
  "type": "Feature",
  "properties": {
    "addr:full":"5861 Avalon Blvd Los Angeles CA 90003",
    "addr:housenumber":"5861",
    "addr:postcode":"90003",
    "addr:street":"Avalon Blvd",
    "iso:country":"US",
    "sg:address":"5861 Avalon Blvd",
    "sg:city":"Los Angeles",
    "sg:classifiers":[
        {
            "category":"Wholesale",
            "subcategory":"Machinery & Supplies",
            "type":"Manufacturing & Wholesale Goods"
        }
    ],
    "sg:phone":"+1 323 846 7006",
    "sg:postcode":"90003",
    "sg:province":"CA",
    "sg:tags":[
        "equipment",
        "industrial"
    ],
    "wof:name":"Victor Welding Supply",
    "wof:placetype":"venue"
},
  "geometry": {"coordinates":[-118.26526,33.989034],"type":"Point"}
}