{
  "type": "Feature",
  "properties": {
    "iso:country":"US",
    "sg:address":"1025 Black Diamond St",
    "sg:city":"Pittsburg",
    "sg:classifiers":[
        {
            "category":"Education",
            "subcategory":"School",
            "type":"Public Place"
        }
    ],
    "sg:phone":"+1 925 473 4488",
    "sg:postcode":"94565",
    "sg:province":"CA",
    "sg:website":"http://www.pittsburg.k12.ca.us",
    "wof:name":"Riverside High School",
    "wof:placetype":"venue"
},
  "geometry": {"coordinates":[-121.886532,38.028042],"type":"Point"}
}