{
  "type": "Feature",
  "properties": {
    "iso:country":"US",
    "sg:address":"16360 Roscoe Blvd",
    "sg:city":"Van Nuys",
    "sg:classifiers":[
        {
            "category":"Personal",
            "subcategory":"Beauty Salon",
            "type":"Services"
        }
    ],
    "sg:phone":"+1 818 920 9971",
    "sg:postcode":"91402",
    "sg:province":"CA",
    "wof:name":"Great Clips",
    "wof:placetype":"venue"
},
  "geometry": {"coordinates":[-118.488956,34.221224],"type":"Point"}
}