{
  "type": "Feature",
  "properties": {
    "addr:full":"12818 Loma Rica Dr Grass Valley CA 95945",
    "addr:housenumber":"12818",
    "addr:postcode":"95945",
    "addr:street":"Loma Rica Dr",
    "iso:country":"US",
    "sg:address":"12818 Loma Rica Dr",
    "sg:city":"Grass Valley",
    "sg:classifiers":[
        {
            "category":"Government",
            "subcategory":"Office",
            "type":"Public Place"
        }
    ],
    "sg:phone":"+1 530 477 0103",
    "sg:postcode":"95945",
    "sg:province":"CA",
    "sg:tags":[
        "county",
        "govt",
        "program"
    ],
    "wof:name":"TRANSIT Services",
    "wof:placetype":"venue"
},
  "geometry": {"coordinates":[-121.008426,39.221436],"type":"Point"}
}