{
  "type": "Feature",
  "properties": {
    "iso:country":"US",
    "sg:address":"17865 Sky Park Cir Ste F",
    "sg:city":"Irvine",
    "sg:classifiers":[
        {
            "category":"Manufacturing",
            "subcategory":"Apparel",
            "type":"Manufacturing & Wholesale Goods"
        }
    ],
    "sg:phone":"+1 714 799 0077",
    "sg:postcode":"92614",
    "sg:province":"CA",
    "sg:tags":[
        "work",
        "clothing-wholesale",
        "manufacturer"
    ],
    "wof:name":"Sullen",
    "wof:placetype":"venue"
},
  "geometry": {"coordinates":[-117.856137,33.69114],"type":"Point"}
}