{
  "type": "Feature",
  "properties": {
    "addr:full":"3513 Cam Arroyo Santa Ynez CA 93460",
    "addr:housenumber":"3513",
    "addr:postcode":"93460",
    "addr:street":"Cam Arroyo",
    "iso:country":"US",
    "sg:address":"3513 Cam Arroyo",
    "sg:city":"Santa Ynez",
    "sg:classifiers":[
        {
            "category":"Real Estate",
            "subcategory":"Real Estate Agent",
            "type":"Services"
        }
    ],
    "sg:phone":"+1 805 693 1985",
    "sg:postcode":"93460",
    "sg:province":"CA",
    "wof:name":"Otobai Inc",
    "wof:placetype":"venue"
},
  "geometry": {"coordinates":[-120.081917,34.615132],"type":"Point"}
}