{
  "type": "Feature",
  "properties": {
    "iso:country":"US",
    "sg:address":"6101 27th St",
    "sg:city":"Sacramento",
    "sg:classifiers":[
        {
            "category":"Social Services",
            "type":"Services"
        }
    ],
    "sg:phone":"+1 916 391 7467",
    "sg:postcode":"95822",
    "sg:province":"CA",
    "sg:tags":[
        "organization",
        "welfare"
    ],
    "wof:name":"Independent Benefit Supporters",
    "wof:placetype":"venue"
},
  "geometry": {"coordinates":[-121.477198,38.510315],"type":"Point"}
}