{
  "type": "Feature",
  "properties": {
    "iso:country":"US",
    "sg:address":"21070 Golden Springs Dr",
    "sg:city":"Walnut",
    "sg:classifiers":[
        {
            "category":"Shopping",
            "subcategory":"Crafts & Fabrics",
            "type":"Retail Goods"
        }
    ],
    "sg:phone":"+1 909 598 6642",
    "sg:postcode":"91789",
    "sg:province":"CA",
    "sg:tags":[
        "shop"
    ],
    "wof:name":"Jo-Ann Fabrics & Crafts",
    "wof:placetype":"venue"
},
  "geometry": {"coordinates":[-117.84423099999999,33.999905],"type":"Point"}
}