{
  "type": "Feature",
  "properties": {
    "iso:country":"US",
    "sg:address":"2405 Saddleback Ln",
    "sg:city":"Modesto",
    "sg:classifiers":[
        {
            "category":"Social Services",
            "subcategory":"Child Care",
            "type":"Services"
        }
    ],
    "sg:phone":"+1 209 551 5764",
    "sg:postcode":"95355",
    "sg:province":"CA",
    "wof:name":"A Childs World Daycare",
    "wof:placetype":"venue"
},
  "geometry": {"coordinates":[-120.952788,37.676166],"type":"Point"}
}