{
  "type": "Feature",
  "properties": {
    "iso:country":"US",
    "sg:address":"1024 Mission St Ste A",
    "sg:city":"South Pasadena",
    "sg:classifiers":[
        {
            "category":"Health Services",
            "subcategory":"Clinic",
            "type":"Services"
        },
        {
            "category":"Personal",
            "subcategory":"Skin Care",
            "type":"Services"
        }
    ],
    "sg:phone":"+1 626 441 8968",
    "sg:postcode":"91030",
    "sg:province":"CA",
    "sg:tags":[
        "spa",
        "medical"
    ],
    "sg:website":"www.RejuvaYou.com",
    "wof:name":"RejuvaYou Medical Spa",
    "wof:placetype":"venue"
},
  "geometry": {"coordinates":[-118.155853,34.115769],"type":"Point"}
}