{
  "type": "Feature",
  "properties": {
    "addr:full":"555 Lewelling Blvd San Leandro CA 94579",
    "addr:housenumber":"555",
    "addr:postcode":"94579",
    "addr:street":"Lewelling Blvd",
    "iso:country":"US",
    "sg:address":"555 Lewelling Blvd",
    "sg:city":"San Leandro",
    "sg:classifiers":[
        {
            "category":"Restaurant",
            "type":"Food & Drink"
        }
    ],
    "sg:phone":"+1 510 614 2938",
    "sg:postcode":"94579",
    "sg:province":"CA",
    "sg:tags":[
        "chinese"
    ],
    "wof:name":"Super 5 Kitchen",
    "wof:placetype":"venue"
},
  "geometry": {"coordinates":[-122.13444699999999,37.687145],"type":"Point"}
}