{
  "type": "Feature",
  "properties": {
    "iso:country":"US",
    "sg:address":"3210 E Anaheim St",
    "sg:city":"Long Beach",
    "sg:classifiers":[
        {
            "category":"Banks & Credit Unions",
            "subcategory":"Bank",
            "type":"Services"
        }
    ],
    "sg:phone":"+1 562 621 6520",
    "sg:postcode":"90804",
    "sg:province":"CA",
    "wof:name":"Downey Savings & Loan",
    "wof:placetype":"venue"
},
  "geometry": {"coordinates":[-118.153999,33.782501],"type":"Point"}
}