{
  "type": "Feature",
  "properties": {
    "iso:country":"US",
    "sg:address":"601 Montgomery St",
    "sg:city":"San Francisco",
    "sg:classifiers":[
        {
            "category":"Professional",
            "subcategory":"Lawyer & Legal Services",
            "type":"Services"
        }
    ],
    "sg:phone":"+1 415 986 2479",
    "sg:postcode":"94111",
    "sg:province":"CA",
    "sg:tags":[
        "attorney"
    ],
    "wof:name":"Scopelitis Garvin Light",
    "wof:placetype":"venue"
},
  "geometry": {"coordinates":[-122.403221,37.795066],"type":"Point"}
}