{
  "type": "Feature",
  "properties": {
    "iso:country":"US",
    "sg:address":"1232 Montgomery Ave",
    "sg:city":"South San Francisco",
    "sg:classifiers":[
        {
            "category":"Shopping",
            "subcategory":"Pets & Pet Supplies",
            "type":"Retail Goods"
        }
    ],
    "sg:phone":"+1 415 409 3900",
    "sg:postcode":"94066",
    "sg:province":"CA",
    "sg:tags":[
        "store"
    ],
    "sg:website":"www.vavadog.com",
    "wof:name":"Vavadog",
    "wof:placetype":"venue"
},
  "geometry": {"coordinates":[-122.412435,37.639799],"type":"Point"}
}