{
  "type": "Feature",
  "properties": {
    "addr:full":"8816 Artesia Blvd Bellflower CA 90706",
    "addr:housenumber":"8816",
    "addr:postcode":"90706",
    "addr:street":"Artesia Blvd",
    "iso:country":"US",
    "sg:address":"8816 Artesia Blvd",
    "sg:city":"Bellflower",
    "sg:classifiers":[
        {
            "category":"Place Of Worship",
            "type":"Public Place"
        }
    ],
    "sg:phone":"+1 562 630 3764",
    "sg:postcode":"90706",
    "sg:province":"CA",
    "sg:tags":[
        "church"
    ],
    "wof:name":"Chu William",
    "wof:placetype":"venue"
},
  "geometry": {"coordinates":[-118.14400999999999,33.874697],"type":"Point"}
}