{
  "type": "Feature",
  "properties": {
    "addr:full":"4807 Las Virgenes Rd Calabasas CA 91302",
    "addr:housenumber":"4807",
    "addr:postcode":"91302",
    "addr:street":"Las Virgenes Rd",
    "iso:country":"US",
    "sg:address":"4807 Las Virgenes Rd",
    "sg:city":"Calabasas",
    "sg:classifiers":[
        {
            "category":"Manufacturing",
            "subcategory":"Buildings",
            "type":"Manufacturing & Wholesale Goods"
        },
        {
            "category":"Personal",
            "type":"Services"
        }
    ],
    "sg:phone":"+1 800 275 7767",
    "sg:postcode":"91302",
    "sg:province":"CA",
    "sg:tags":[
        "house",
        "mover",
        "full",
        "storage",
        "raising"
    ],
    "wof:name":"NorthStar Moving Corporation",
    "wof:placetype":"venue"
},
  "geometry": {"coordinates":[-118.69809600000001,34.144432],"type":"Point"}
}