{
  "type": "Feature",
  "properties": {
    "iso:country":"US",
    "sg:address":"1050 Park Place",
    "sg:city":"San Mateo",
    "sg:classifiers":[
        {
            "category":"Restaurant",
            "type":"Food & Drink"
        }
    ],
    "sg:phone":"+1 650 286 9174",
    "sg:postcode":"94497",
    "sg:province":"CA",
    "sg:tags":[
        "greek",
        "mediterranean"
    ],
    "sg:website":"www.daphnesgreekcafe.com",
    "wof:name":"Daphne's Greek Cafe",
    "wof:placetype":"venue"
},
  "geometry": {"coordinates":[-122.292,37.544498],"type":"Point"}
}