{
  "type": "Feature",
  "properties": {
    "iso:country":"US",
    "sg:address":"3675 Main St",
    "sg:city":"Riverside",
    "sg:classifiers":[
        {
            "category":"Shopping",
            "subcategory":"Gifts & Souvenirs",
            "type":"Retail Goods"
        }
    ],
    "sg:phone":"+1 951 683 0221",
    "sg:postcode":"92501",
    "sg:province":"CA",
    "sg:tags":[
        "shop"
    ],
    "wof:name":"Tiggy-Winkles Gift Shoppe",
    "wof:placetype":"venue"
},
  "geometry": {"coordinates":[-117.373413,33.983755],"type":"Point"}
}