{
  "type": "Feature",
  "properties": {
    "addr:full":"705 Main St Fortuna CA 95540",
    "addr:housenumber":"705",
    "addr:postcode":"95540",
    "addr:street":"Main St",
    "iso:country":"US",
    "sg:address":"705 Main St",
    "sg:city":"Fortuna",
    "sg:classifiers":[
        {
            "category":"Health Services",
            "subcategory":"Chiropractor",
            "type":"Services"
        }
    ],
    "sg:phone":"+1 707 725 0875",
    "sg:postcode":"95540",
    "sg:province":"CA",
    "sg:tags":[
        "food"
    ],
    "wof:name":"Bonnie Travis DC",
    "wof:placetype":"venue"
},
  "geometry": {"coordinates":[-124.16019,40.598242],"type":"Point"}
}