{
  "type": "Feature",
  "properties": {
    "iso:country":"US",
    "sg:address":"745 Distel Dr",
    "sg:city":"Los Altos",
    "sg:classifiers":[
        {
            "category":"Professional",
            "subcategory":"Management & Consulting",
            "type":"Services"
        }
    ],
    "sg:phone":"+1 650 968 7727",
    "sg:postcode":"94022",
    "sg:province":"CA",
    "sg:tags":[
        "consultant",
        "business"
    ],
    "wof:name":"D R Kennedy & Assoc Inc",
    "wof:placetype":"venue"
},
  "geometry": {"coordinates":[-122.103385,37.395941],"type":"Point"}
}