{
  "type": "Feature",
  "properties": {
    "addr:full":"183 Paulsen Rd Watsonville CA 95076",
    "addr:housenumber":"183",
    "addr:postcode":"95076",
    "addr:street":"Paulsen Rd",
    "iso:country":"US",
    "sg:address":"183 Paulsen Rd",
    "sg:city":"Watsonville",
    "sg:classifiers":[
        {
            "category":"Wholesale",
            "subcategory":"Plants",
            "type":"Manufacturing & Wholesale Goods"
        }
    ],
    "sg:phone":"+1 831 786 9690",
    "sg:postcode":"95076",
    "sg:province":"CA",
    "sg:tags":[
        "nursery",
        "tree"
    ],
    "wof:name":"Green Land Nurseries",
    "wof:placetype":"venue"
},
  "geometry": {"coordinates":[-121.747463,36.955259],"type":"Point"}
}