{
  "type": "Feature",
  "properties": {
    "iso:country":"US",
    "sg:address":"9140 Brookshire Ave",
    "sg:city":"Downey",
    "sg:classifiers":[
        {
            "category":"Real Estate",
            "subcategory":"Real Estate Agent",
            "type":"Services"
        }
    ],
    "sg:phone":"+1 562 923 4033",
    "sg:postcode":"90240",
    "sg:province":"CA",
    "wof:name":"JD Management & Inv Svcs",
    "wof:placetype":"venue"
},
  "geometry": {"coordinates":[-118.113614,33.957521],"type":"Point"}
}