{
  "type": "Feature",
  "properties": {
    "iso:country":"US",
    "sg:address":"6672 Hollywood Boulevard",
    "sg:city":"Los Angeles",
    "sg:classifiers":[
        {
            "category":"Shopping",
            "subcategory":"Shoes",
            "type":"Retail Goods"
        }
    ],
    "sg:phone":"+1 323 461 8090",
    "sg:postcode":"90028",
    "sg:province":"CA",
    "sg:tags":[
        "store"
    ],
    "wof:name":"Azura",
    "wof:placetype":"venue"
},
  "geometry": {"coordinates":[-118.335914,34.101668],"type":"Point"}
}