{
  "type": "Feature",
  "properties": {
    "addr:full":"15000 Los Gatos Blvd Los Gatos CA 95032",
    "addr:housenumber":"15000",
    "addr:postcode":"95032",
    "addr:street":"Los Gatos Blvd",
    "iso:country":"US",
    "sg:address":"15000 Los Gatos Blvd",
    "sg:city":"Los Gatos",
    "sg:classifiers":[
        {
            "category":"Professional",
            "subcategory":"Accounting & Tax Preparation",
            "type":"Services"
        }
    ],
    "sg:phone":"+1 408 358 3320",
    "sg:postcode":"95032",
    "sg:province":"CA",
    "sg:tags":[
        "accountant"
    ],
    "wof:name":"Hane & Co",
    "wof:placetype":"venue"
},
  "geometry": {"coordinates":[-121.952994,37.252415],"type":"Point"}
}