{
  "type": "Feature",
  "properties": {
    "iso:country":"US",
    "sg:address":"1661 Triangle Dr",
    "sg:city":"Ridgecrest",
    "sg:classifiers":[
        {
            "category":"Bars & Pubs",
            "type":"Food & Drink"
        }
    ],
    "sg:phone":"+1 760 446 0805",
    "sg:postcode":"93555",
    "sg:province":"CA",
    "sg:tags":[
        "club",
        "night"
    ],
    "wof:name":"Mickey's Pub",
    "wof:placetype":"venue"
},
  "geometry": {"coordinates":[-117.670967,35.650788],"type":"Point"}
}