{
  "type": "Feature",
  "properties": {
    "addr:full":"8220 Katella Ave Stanton CA 90680",
    "addr:housenumber":"8220",
    "addr:postcode":"ca 90680",
    "addr:street":"Katella Ave",
    "iso:country":"US",
    "sg:address":"8220 Katella Ave",
    "sg:city":"Stanton",
    "sg:classifiers":[
        {
            "category":"Shopping",
            "subcategory":"Gifts & Souvenirs",
            "type":"Retail Goods"
        },
        {
            "category":"Banks & Credit Unions",
            "subcategory":"Bank",
            "type":"Services"
        }
    ],
    "sg:phone":"+1 714 657 7502",
    "sg:postcode":"90680",
    "sg:province":"CA",
    "sg:tags":[
        "other",
        "plan",
        "card"
    ],
    "wof:name":"Credit Card Debt Specialists",
    "wof:placetype":"venue"
},
  "geometry": {"coordinates":[-117.989422,33.80288],"type":"Point"}
}