{
  "type": "Feature",
  "properties": {
    "iso:country":"US",
    "sg:address":"1408 S Grove Ave",
    "sg:city":"Ontario",
    "sg:classifiers":[
        {
            "category":"Professional",
            "type":"Services"
        },
        {
            "category":"Manufacturing",
            "subcategory":"Motor Vehicles & Parts",
            "type":"Manufacturing & Wholesale Goods"
        }
    ],
    "sg:phone":"+1 909 673 0157",
    "sg:postcode":"91761",
    "sg:province":"CA",
    "sg:tags":[
        "scooter",
        "motorcycle"
    ],
    "wof:name":"Black Label Choppers",
    "wof:placetype":"venue"
},
  "geometry": {"coordinates":[-117.628686,34.049447],"type":"Point"}
}