{
  "type": "Feature",
  "properties": {
    "iso:country":"US",
    "sg:address":"3523 5th Ave",
    "sg:city":"San Diego",
    "sg:classifiers":[
        {
            "category":"Shopping",
            "subcategory":"Books",
            "type":"Retail Goods"
        }
    ],
    "sg:phone":"+1 619 291 8088",
    "sg:postcode":"92103",
    "sg:province":"CA",
    "sg:tags":[
        "used",
        "merchandise"
    ],
    "wof:name":"Cape Cod Clutter",
    "wof:placetype":"venue"
},
  "geometry": {"coordinates":[-117.1603,32.741559],"type":"Point"}
}