{
  "type": "Feature",
  "properties": {
    "addr:full":"519 N Harbor Blvd Fullerton CA 92832",
    "addr:housenumber":"519",
    "addr:postcode":"92832",
    "addr:street":"N Harbor Blvd",
    "iso:country":"US",
    "sg:address":"519 N Harbor Blvd",
    "sg:city":"Fullerton",
    "sg:classifiers":[
        {
            "category":"Personal",
            "subcategory":"Tattoo Parlor",
            "type":"Services"
        },
        {
            "category":"Personal",
            "subcategory":"Piercing",
            "type":"Services"
        }
    ],
    "sg:phone":"+1 714 773 5110",
    "sg:postcode":"92832",
    "sg:province":"CA",
    "wof:name":"Nothing Shocking",
    "wof:placetype":"venue"
},
  "geometry": {"coordinates":[-117.924329,33.874779],"type":"Point"}
}