{
  "type": "Feature",
  "properties": {
    "addr:full":"42353 47th St W Quartz Hill CA 93536",
    "addr:housenumber":"42353",
    "addr:postcode":"93536",
    "addr:street":"47Th St W Quartz Hill",
    "iso:country":"US",
    "sg:address":"42353 47th St W",
    "sg:city":"Quartz Hill",
    "sg:classifiers":[
        {
            "category":"Organizations",
            "subcategory":"Religious Organization",
            "type":"Services"
        }
    ],
    "sg:phone":"+1 661 943 1180",
    "sg:postcode":"93536",
    "sg:province":"CA",
    "sg:tags":[
        "church"
    ],
    "wof:name":"Christ Missionary Bible",
    "wof:placetype":"venue"
},
  "geometry": {"coordinates":[-118.21329,34.652109],"type":"Point"}
}