{
  "type": "Feature",
  "properties": {
    "addr:full":"2875 Glascock St Ste 103 Oakland CA 94601",
    "addr:housenumber":"2875",
    "addr:postcode":"94601",
    "addr:street":"Glascock St Ste 103",
    "iso:country":"US",
    "sg:address":"2875 Glascock St Ste 103",
    "sg:city":"Oakland",
    "sg:classifiers":[
        {
            "category":"Professional",
            "type":"Services"
        },
        {
            "category":"Building & Trades",
            "subcategory":"Construction",
            "type":"Services"
        }
    ],
    "sg:phone":"+1 510 865 8850",
    "sg:postcode":"94601",
    "sg:province":"CA",
    "sg:tags":[
        "contractor"
    ],
    "wof:name":"derek pavlik DESIGN",
    "wof:placetype":"venue"
},
  "geometry": {"coordinates":[-122.235078,37.772246],"type":"Point"}
}