{
  "type": "Feature",
  "properties": {
    "iso:country":"US",
    "sg:address":"15820 Applegate Rd",
    "sg:city":"Auburn",
    "sg:classifiers":[
        {
            "category":"Social Services",
            "subcategory":"Child Care",
            "type":"Services"
        }
    ],
    "sg:phone":"+1 530 878 1600",
    "sg:postcode":"95603",
    "sg:province":"CA",
    "sg:tags":[
        "kindergarten",
        "academic",
        "school"
    ],
    "wof:name":"Clipper Gap Head Start",
    "wof:placetype":"venue"
},
  "geometry": {"coordinates":[-121.016414,38.969201],"type":"Point"}
}