{
  "type": "Feature",
  "properties": {
    "addr:full":"8259 Corona Ave Hesperia CA 92345",
    "addr:housenumber":"8259",
    "addr:postcode":"92345",
    "addr:street":"Corona Ave",
    "iso:country":"US",
    "sg:address":"8259 Corona Ave",
    "sg:city":"Hesperia",
    "sg:classifiers":[
        {
            "category":"Professional",
            "subcategory":"Art Services",
            "type":"Services"
        }
    ],
    "sg:phone":"+1 760 948 8365",
    "sg:postcode":"92345",
    "sg:province":"CA",
    "sg:tags":[
        "artist"
    ],
    "wof:name":"Artistic Enterprises",
    "wof:placetype":"venue"
},
  "geometry": {"coordinates":[-117.26836299999999,34.402579],"type":"Point"}
}