{
  "type": "Feature",
  "properties": {
    "iso:country":"US",
    "sg:address":"2293 W 190th St",
    "sg:city":"Torrance",
    "sg:classifiers":[
        {
            "category":"Professional",
            "type":"Services"
        }
    ],
    "sg:phone":"+1 310 539 8300",
    "sg:postcode":"90504",
    "sg:province":"CA",
    "sg:website":"www.business-team.com/N_corp/off...",
    "wof:name":"Business Team Los Angeles",
    "wof:placetype":"venue"
},
  "geometry": {"coordinates":[-118.319024,33.858335],"type":"Point"}
}