{
  "type": "Feature",
  "properties": {
    "addr:full":"1007 Dana Dr Redding CA 96003",
    "addr:housenumber":"1007",
    "addr:postcode":"96003",
    "addr:street":"Dana Dr",
    "iso:country":"US",
    "sg:address":"1007 Dana Dr",
    "sg:city":"Redding",
    "sg:classifiers":[
        {
            "category":"Health Services",
            "subcategory":"Doctor",
            "type":"Services"
        }
    ],
    "sg:phone":"+1 530 222 1221",
    "sg:postcode":"96003",
    "sg:province":"CA",
    "sg:tags":[
        "dentist"
    ],
    "wof:name":"Kevin E Platner DDS",
    "wof:placetype":"venue"
},
  "geometry": {"coordinates":[-122.35408200000001,40.585718],"type":"Point"}
}