{
  "type": "Feature",
  "properties": {
    "iso:country":"US",
    "sg:address":"300 W Grand Ave",
    "sg:city":"Escondido",
    "sg:classifiers":[
        {
            "category":"Professional",
            "subcategory":"Advertising",
            "type":"Services"
        }
    ],
    "sg:phone":"+1 760 294 5563",
    "sg:postcode":"92025",
    "sg:province":"CA",
    "sg:tags":[
        "medium",
        "broker"
    ],
    "wof:name":"Commonwealth Business Media",
    "wof:placetype":"venue"
},
  "geometry": {"coordinates":[-117.085531,33.119624],"type":"Point"}
}