{
  "type": "Feature",
  "properties": {
    "addr:full":"9541 Bus Center Dr Rancho Cucamonga CA 91730",
    "addr:postcode":"9541;91730",
    "addr:street":"Center Dr",
    "iso:country":"US",
    "sg:address":"9541 Bus Center Dr",
    "sg:city":"Rancho Cucamonga",
    "sg:classifiers":[
        {
            "category":"Home & Garden",
            "subcategory":"Carpets & Floor Coverings",
            "type":"Retail Goods"
        }
    ],
    "sg:phone":"+1 909 945 2155",
    "sg:postcode":"91730",
    "sg:province":"CA",
    "sg:tags":[
        "dealer",
        "rug"
    ],
    "wof:name":"Life Time Floors",
    "wof:placetype":"venue"
},
  "geometry": {"coordinates":[-117.59445599999999,34.098033],"type":"Point"}
}