{
  "type": "Feature",
  "properties": {
    "iso:country":"US",
    "sg:address":"2001 Refugio Valley Rd",
    "sg:city":"Hercules",
    "sg:classifiers":[
        {
            "category":"Personal",
            "type":"Services"
        },
        {
            "category":"Sports & Exercise",
            "subcategory":"Gym",
            "type":"Entertainment"
        }
    ],
    "sg:phone":"+1 510 417 4435",
    "sg:postcode":"94547",
    "sg:province":"CA",
    "sg:tags":[
        "trainer",
        "consultant",
        "program",
        "physical",
        "fitness"
    ],
    "sg:website":"http://eastbay.citysearch.com/profile/external/603964062/hercules_ca/jazzercise_hercules_community_swim_center.html?publisher=yellowpages&reference_id=1&placement=ypwebsitemip",
    "wof:name":"Jazzercise Hercules Community Swim Center",
    "wof:placetype":"venue"
},
  "geometry": {"coordinates":[-122.249421,37.998619],"type":"Point"}
}