{
  "type": "Feature",
  "properties": {
    "iso:country":"US",
    "sg:address":"2557 W Winton Ave Ste 7C",
    "sg:city":"Hayward",
    "sg:classifiers":[
        {
            "category":"Autos & Motor Vehicles",
            "subcategory":"Auto Supplies",
            "type":"Retail Goods"
        }
    ],
    "sg:phone":"+1 510 786 0300",
    "sg:postcode":"94545",
    "sg:province":"CA",
    "sg:tags":[
        "glass"
    ],
    "wof:name":"US Auto Glass Center",
    "wof:placetype":"venue"
},
  "geometry": {"coordinates":[-122.139999,37.652199],"type":"Point"}
}