{
  "type": "Feature",
  "properties": {
    "iso:country":"US",
    "sg:address":"12607 Sherman Way",
    "sg:city":"North Hollywood",
    "sg:classifiers":[
        {
            "category":"Home & Garden",
            "subcategory":"Furniture",
            "type":"Retail Goods"
        },
        {
            "category":"Home & Garden",
            "subcategory":"Carpets & Floor Coverings",
            "type":"Retail Goods"
        }
    ],
    "sg:phone":"+1 818 503 0704",
    "sg:postcode":"91605",
    "sg:province":"CA",
    "sg:tags":[
        "store",
        "mattress"
    ],
    "sg:website":"www.maximsfurniture.net/",
    "wof:name":"Maxim Furniture",
    "wof:placetype":"venue"
},
  "geometry": {"coordinates":[-118.408997,34.201099],"type":"Point"}
}