{
  "type": "Feature",
  "properties": {
    "iso:country":"US",
    "sg:address":"849 Dickson St",
    "sg:city":"Marina Del Rey",
    "sg:classifiers":[
        {
            "category":"Professional",
            "type":"Services"
        }
    ],
    "sg:phone":"+1 310 821 9413",
    "sg:postcode":"90292",
    "sg:province":"CA",
    "wof:name":"National Psychomedia Center",
    "wof:placetype":"venue"
},
  "geometry": {"coordinates":[-118.449728,33.98747],"type":"Point"}
}