{
  "type": "Feature",
  "properties": {
    "iso:country":"US",
    "sg:address":"406 S California Ave",
    "sg:city":"Palo Alto",
    "sg:classifiers":[
        {
            "category":"Restaurant",
            "type":"Food & Drink"
        }
    ],
    "sg:phone":"+1 650 327 1688",
    "sg:postcode":"94306",
    "sg:province":"CA",
    "wof:name":"Szechwan Cafe",
    "wof:placetype":"venue"
},
  "geometry": {"coordinates":[-122.145943,37.425164],"type":"Point"}
}