{
  "type": "Feature",
  "properties": {
    "iso:country":"US",
    "sg:address":"14822 Bodger Ave",
    "sg:city":"Hawthorne",
    "sg:classifiers":[
        {
            "category":"Professional",
            "type":"Services"
        }
    ],
    "sg:phone":"+1 310 675 8560",
    "sg:postcode":"90250",
    "sg:province":"CA",
    "wof:name":"Drains Only Corp",
    "wof:placetype":"venue"
},
  "geometry": {"coordinates":[-118.338611,33.895637],"type":"Point"}
}