{
  "type": "Feature",
  "properties": {
    "addr:full":"1941 Mitchell Rd Ceres CA 95307",
    "addr:housenumber":"1941",
    "addr:postcode":"95307",
    "addr:street":"Mitchell Rd",
    "iso:country":"US",
    "sg:address":"1941 Mitchell Rd",
    "sg:city":"Ceres",
    "sg:classifiers":[
        {
            "category":"Personal",
            "subcategory":"Beauty Salon",
            "type":"Services"
        }
    ],
    "sg:phone":"+1 209 538 2452",
    "sg:postcode":"95307",
    "sg:province":"CA",
    "wof:name":"Tiffanys",
    "wof:placetype":"venue"
},
  "geometry": {"coordinates":[-120.93878100000001,37.599014],"type":"Point"}
}