{
  "type": "Feature",
  "properties": {
    "addr:full":"132 4th St Encinitas CA 92024",
    "addr:housenumber":"132",
    "addr:postcode":"92024",
    "addr:street":"4Th St",
    "iso:country":"US",
    "sg:address":"132 4th St",
    "sg:city":"Encinitas",
    "sg:classifiers":[
        {
            "category":"Professional",
            "type":"Services"
        }
    ],
    "sg:phone":"+1 760 753 4217",
    "sg:postcode":"92024",
    "sg:province":"CA",
    "wof:name":"Carol Patton",
    "wof:placetype":"venue"
},
  "geometry": {"coordinates":[-117.297397,33.050033],"type":"Point"}
}