{
  "type": "Feature",
  "properties": {
    "iso:country":"US",
    "sg:address":"1337 Ocean Ave",
    "sg:city":"Santa Monica",
    "sg:classifiers":[
        {
            "category":"Professional",
            "subcategory":"Business Services",
            "type":"Services"
        }
    ],
    "sg:phone":"+1 310 395 5657",
    "sg:postcode":"90401",
    "sg:province":"CA",
    "sg:tags":[
        "trade",
        "contractor"
    ],
    "wof:name":"Architrave Interiors",
    "wof:placetype":"venue"
},
  "geometry": {"coordinates":[-118.498452,34.014615],"type":"Point"}
}