{
  "type": "Feature",
  "properties": {
    "addr:full":"4122 Parten Dr Malibu CA 90265",
    "addr:housenumber":"4122",
    "addr:postcode":"90265",
    "addr:street":"Parten Dr",
    "iso:country":"US",
    "sg:address":"4122 Parten Dr",
    "sg:city":"Malibu",
    "sg:classifiers":[
        {
            "category":"Professional",
            "type":"Services"
        }
    ],
    "sg:phone":"+1 310 457 3242",
    "sg:postcode":"90265",
    "sg:province":"CA",
    "wof:name":"Calamity Co",
    "wof:placetype":"venue"
},
  "geometry": {"coordinates":[-118.778158,34.049572],"type":"Point"}
}