{
  "type": "Feature",
  "properties": {
    "addr:full":"9516 Gidley St Temple City CA 91780",
    "addr:postcode":"9516;91780",
    "addr:street":"Gidley St",
    "iso:country":"US",
    "sg:address":"9516 Gidley St",
    "sg:city":"Temple City",
    "sg:classifiers":[
        {
            "category":"Building & Trades",
            "subcategory":"Construction",
            "type":"Services"
        }
    ],
    "sg:phone":"+1 626 575 3516",
    "sg:postcode":"91780",
    "sg:province":"CA",
    "sg:tags":[
        "contractor"
    ],
    "wof:name":"Classical Building Arts",
    "wof:placetype":"venue"
},
  "geometry": {"coordinates":[-118.05898500000001,34.087291],"type":"Point"}
}