{
  "type": "Feature",
  "properties": {
    "iso:country":"US",
    "sg:address":"7940 Hollywood Boulevard",
    "sg:city":"Los Angeles",
    "sg:classifiers":[
        {
            "category":"Building & Trades",
            "subcategory":"Locksmith",
            "type":"Services"
        }
    ],
    "sg:phone":"+1 323 928 4330",
    "sg:postcode":"90046",
    "sg:province":"CA",
    "sg:tags":[
        "key"
    ],
    "wof:name":"Emergency 24 7 Locks & Locksmith",
    "wof:placetype":"venue"
},
  "geometry": {"coordinates":[-118.362676,34.101268],"type":"Point"}
}