{
  "type": "Feature",
  "properties": {
    "addr:full":"3705 El Camino Real Santa Clara CA 95051",
    "addr:housenumber":"3705",
    "addr:postcode":"95051",
    "addr:street":"El Camino Real",
    "iso:country":"US",
    "sg:address":"3705 El Camino Real",
    "sg:city":"Santa Clara",
    "sg:classifiers":[
        {
            "category":"Food & Beverages",
            "subcategory":"Groceries & Convenience Stores",
            "type":"Retail Goods"
        }
    ],
    "sg:phone":"+1 408 247 5200",
    "sg:postcode":"95051",
    "sg:province":"CA",
    "wof:name":"Albertsons-Sav-On",
    "wof:placetype":"venue"
},
  "geometry": {"coordinates":[-121.998396,37.352302],"type":"Point"}
}