{
  "type": "Feature",
  "properties": {
    "addr:full":"7898 Dublin Blvd Dublin CA 94568",
    "addr:housenumber":"7898",
    "addr:postcode":"94568",
    "addr:street":"Dublin Blvd",
    "iso:country":"US",
    "sg:address":"7898 Dublin Blvd",
    "sg:city":"Dublin",
    "sg:classifiers":[
        {
            "category":"Shopping",
            "subcategory":"Jewelry",
            "type":"Retail Goods"
        }
    ],
    "sg:phone":"+1 925 875 1942",
    "sg:postcode":"94568",
    "sg:province":"CA",
    "sg:tags":[
        "jeweler"
    ],
    "wof:name":"Books Half Price",
    "wof:placetype":"venue"
},
  "geometry": {"coordinates":[-121.933632,37.70282],"type":"Point"}
}