{
  "type": "Feature",
  "properties": {
    "addr:full":"31153 Palm Dr Exeter CA 93221",
    "addr:housenumber":"31153",
    "addr:postcode":"93221",
    "addr:street":"Palm Dr",
    "iso:country":"US",
    "sg:address":"31153 Palm Dr",
    "sg:city":"Exeter",
    "sg:classifiers":[
        {
            "category":"Manufacturing",
            "subcategory":"Petroleum Products",
            "type":"Manufacturing & Wholesale Goods"
        }
    ],
    "sg:phone":"+1 559 592 6987",
    "sg:postcode":"93221",
    "sg:province":"CA",
    "sg:tags":[
        "refiner"
    ],
    "wof:name":"Galloping H Ranch",
    "wof:placetype":"venue"
},
  "geometry": {"coordinates":[-119.04195,36.336098],"type":"Point"}
}