{
  "type": "Feature",
  "properties": {
    "addr:full":"54391 Village Center Dr Idyllwild CA 92549",
    "addr:housenumber":"54391",
    "addr:postcode":"92549",
    "addr:street":"Village Center Dr",
    "iso:country":"US",
    "sg:address":"54391 Village Center Dr",
    "sg:city":"Idyllwild",
    "sg:classifiers":[
        {
            "category":"Restaurant",
            "type":"Food & Drink"
        }
    ],
    "sg:phone":"+1 951 659 5900",
    "sg:postcode":"92549",
    "sg:province":"CA",
    "wof:name":"Idyllwild Pizza Sports-Family",
    "wof:placetype":"venue"
},
  "geometry": {"coordinates":[-116.71132900000001,33.743512],"type":"Point"}
}