{
  "type": "Feature",
  "properties": {
    "addr:full":"870 E Bedford Ave Fresno CA 93720",
    "addr:housenumber":"870",
    "addr:postcode":"93720",
    "addr:street":"E Bedford Ave",
    "iso:country":"US",
    "sg:address":"870 E Bedford Ave",
    "sg:city":"Fresno",
    "sg:classifiers":[
        {
            "category":"Real Estate",
            "subcategory":"Real Estate Agent",
            "type":"Services"
        }
    ],
    "sg:phone":"+1 559 446 0701",
    "sg:postcode":"93720",
    "sg:province":"CA",
    "wof:name":"Kellogg Bonnie Hawley",
    "wof:placetype":"venue"
},
  "geometry": {"coordinates":[-119.769324,36.846226],"type":"Point"}
}