{
  "type": "Feature",
  "properties": {
    "addr:full":"81 Lindan Ave Quincy CA 95971",
    "addr:housenumber":"81",
    "addr:postcode":"95971",
    "addr:street":"Lindan Ave",
    "iso:country":"US",
    "sg:address":"81 Lindan Ave",
    "sg:city":"Quincy",
    "sg:classifiers":[
        {
            "category":"Building & Trades",
            "subcategory":"Construction",
            "type":"Services"
        }
    ],
    "sg:phone":"+1 530 283 4613",
    "sg:postcode":"95971",
    "sg:province":"CA",
    "wof:name":"JMJ Construction",
    "wof:placetype":"venue"
},
  "geometry": {"coordinates":[-120.938425,39.937806],"type":"Point"}
}