{
  "type": "Feature",
  "properties": {
    "iso:country":"US",
    "sg:address":"688 Bridgeway",
    "sg:city":"Sausalito",
    "sg:classifiers":[
        {
            "category":"Shopping",
            "subcategory":"Hobbies, Toys, & Games",
            "type":"Retail Goods"
        }
    ],
    "sg:phone":"+1 415 332 9590",
    "sg:postcode":"94965",
    "sg:province":"CA",
    "wof:name":"Sausalito Ferry Co Gift Store",
    "wof:placetype":"venue"
},
  "geometry": {"coordinates":[-122.47903700000001,37.85519],"type":"Point"}
}