{
  "type": "Feature",
  "properties": {
    "addr:full":"737 Daniels St Woodland CA 95695",
    "addr:housenumber":"737",
    "addr:postcode":"95695",
    "addr:street":"Daniels St",
    "iso:country":"US",
    "sg:address":"737 Daniels St",
    "sg:city":"Woodland",
    "sg:classifiers":[
        {
            "category":"Shopping",
            "subcategory":"Discount & Variety Stores",
            "type":"Retail Goods"
        }
    ],
    "sg:phone":"+1 530 666 7019",
    "sg:postcode":"95695",
    "sg:province":"CA",
    "sg:tags":[
        "merchandise",
        "general"
    ],
    "wof:name":"Steve Szepesi Products",
    "wof:placetype":"venue"
},
  "geometry": {"coordinates":[-121.796763,38.671414],"type":"Point"}
}