{
  "type": "Feature",
  "properties": {
    "addr:full":"2 Palmieri Aisle Irvine CA 92606",
    "addr:housenumber":"2",
    "addr:postcode":"92606",
    "addr:street":"Palmieri Aisle",
    "iso:country":"US",
    "sg:address":"2 Palmieri Aisle",
    "sg:city":"Irvine",
    "sg:classifiers":[
        {
            "category":"Professional",
            "subcategory":"Business Services",
            "type":"Services"
        }
    ],
    "sg:phone":"+1 949 222 2250",
    "sg:postcode":"92606",
    "sg:province":"CA",
    "sg:tags":[
        "appraiser"
    ],
    "wof:name":"American Appraisal Assoc",
    "wof:placetype":"venue"
},
  "geometry": {"coordinates":[-117.819643,33.687014],"type":"Point"}
}