{
  "type": "Feature",
  "properties": {
    "addr:full":"908 Ocean St Santa Cruz CA 95060",
    "addr:housenumber":"908",
    "addr:postcode":"95060",
    "addr:street":"Ocean St",
    "iso:country":"US",
    "sg:address":"908 Ocean St",
    "sg:city":"Santa Cruz",
    "sg:classifiers":[
        {
            "category":"Retail",
            "subcategory":"Auto Rental",
            "type":"Services"
        }
    ],
    "sg:phone":"+1 831 423 8816",
    "sg:postcode":"95060",
    "sg:province":"CA",
    "sg:tags":[
        "renting",
        "truck",
        "leasing"
    ],
    "wof:name":"U-Haul Co",
    "wof:placetype":"venue"
},
  "geometry": {"coordinates":[-122.021809,36.981211],"type":"Point"}
}