{
  "type": "Feature",
  "properties": {
    "iso:country":"US",
    "sg:address":"928 S San Pedro St",
    "sg:city":"Los Angeles",
    "sg:classifiers":[
        {
            "category":"Shopping",
            "subcategory":"Clothing, Apparel, & Fashions",
            "type":"Retail Goods"
        }
    ],
    "sg:phone":"+1 213 745 6630",
    "sg:postcode":"90015",
    "sg:province":"CA",
    "wof:name":"Y P Central Corp",
    "wof:placetype":"venue"
},
  "geometry": {"coordinates":[-118.250522,34.037106],"type":"Point"}
}