{
  "type": "Feature",
  "properties": {
    "iso:country":"US",
    "sg:address":"2344 E 12th St",
    "sg:city":"Oakland",
    "sg:classifiers":[
        {
            "category":"Wholesale",
            "subcategory":"Auto Parts",
            "type":"Manufacturing & Wholesale Goods"
        }
    ],
    "sg:phone":"+1 510 533 7476",
    "sg:postcode":"94601",
    "sg:province":"CA",
    "sg:tags":[
        "body",
        "automobile",
        "shop"
    ],
    "wof:name":"Peninsula Color Svc",
    "wof:placetype":"venue"
},
  "geometry": {"coordinates":[-122.236428,37.782552],"type":"Point"}
}