{
  "type": "Feature",
  "properties": {
    "iso:country":"US",
    "sg:address":"7265 Murdy Cir",
    "sg:city":"Huntington Beach",
    "sg:classifiers":[
        {
            "category":"Professional",
            "subcategory":"Accounting & Tax Preparation",
            "type":"Services"
        }
    ],
    "sg:phone":"+1 714 841 5542",
    "sg:postcode":"92647",
    "sg:province":"CA",
    "sg:tags":[
        "bookkeeping",
        "general"
    ],
    "wof:name":"A-Action Tax",
    "wof:placetype":"venue"
},
  "geometry": {"coordinates":[-118.00102,33.725915],"type":"Point"}
}