{
  "type": "Feature",
  "properties": {
    "iso:country":"US",
    "sg:address":"17742 Beach Blvd Ste 305",
    "sg:city":"Huntington Beach",
    "sg:classifiers":[
        {
            "category":"Health Services",
            "subcategory":"Optometrist",
            "type":"Services"
        }
    ],
    "sg:phone":"+1 714 848 1215",
    "sg:postcode":"92647",
    "sg:province":"CA",
    "wof:name":"Clairity Eye Group",
    "wof:placetype":"venue"
},
  "geometry": {"coordinates":[-117.98890299999999,33.704712],"type":"Point"}
}