{
  "type": "Feature",
  "properties": {
    "iso:country":"US",
    "sg:address":"642 Quarry Rd",
    "sg:city":"San Carlos",
    "sg:classifiers":[
        {
            "category":"Professional",
            "subcategory":"Business Services",
            "type":"Services"
        }
    ],
    "sg:phone":"+1 650 654 3441",
    "sg:postcode":"94070",
    "sg:province":"CA",
    "sg:tags":[
        "fund",
        "promotion",
        "raising"
    ],
    "wof:name":"Spirit Wear",
    "wof:placetype":"venue"
},
  "geometry": {"coordinates":[-122.26860600000001,37.516227],"type":"Point"}
}