{
  "type": "Feature",
  "properties": {
    "addr:full":"701 Kings Row Ste 85F San Jose CA 95112",
    "addr:housenumber":"701",
    "addr:postcode":"95112",
    "addr:street":"Kings Row Ste 85F",
    "iso:country":"US",
    "sg:address":"701 Kings Row Ste 85F",
    "sg:city":"San Jose",
    "sg:classifiers":[
        {
            "category":"Taxi",
            "type":"Transportation"
        },
        {
            "category":"Airline",
            "type":"Transportation"
        }
    ],
    "sg:phone":"+1 408 998 3333",
    "sg:postcode":"95112",
    "sg:province":"CA",
    "sg:tags":[
        "shuttle",
        "airport"
    ],
    "wof:name":"City Cab",
    "wof:placetype":"venue"
},
  "geometry": {"coordinates":[-121.898883,37.373222],"type":"Point"}
}