{
  "type": "Feature",
  "properties": {
    "addr:full":"4501 Pleasanton Ave Pleasanton CA 94566",
    "addr:housenumber":"4501",
    "addr:postcode":"94566",
    "addr:street":"Pleasanton Ave",
    "iso:country":"US",
    "sg:address":"4501 Pleasanton Ave",
    "sg:city":"Pleasanton",
    "sg:classifiers":[
        {
            "category":"Government",
            "subcategory":"Office",
            "type":"Public Place"
        }
    ],
    "sg:phone":"+1 925 426 7600",
    "sg:postcode":"94566",
    "sg:province":"CA",
    "sg:website":"www.alcofairgrounds.com",
    "wof:name":"Alameda County Fairgrounds",
    "wof:placetype":"venue"
},
  "geometry": {"coordinates":[-121.880717,37.660925],"type":"Point"}
}