{
  "type": "Feature",
  "properties": {
    "iso:country":"US",
    "sg:address":"1310 Yosemite Boulevard",
    "sg:city":"Modesto",
    "sg:classifiers":[
        {
            "category":"Shopping",
            "subcategory":"Florist",
            "type":"Retail Goods"
        }
    ],
    "sg:phone":"+1 209 527 1136",
    "sg:postcode":"95354",
    "sg:province":"CA",
    "wof:name":"Papadopoulos Flowers",
    "wof:placetype":"venue"
},
  "geometry": {"coordinates":[-120.97416200000001,37.638187],"type":"Point"}
}