{
  "type": "Feature",
  "properties": {
    "addr:full":"10936 Ave 272 Visalia CA 93277",
    "addr:housenumber":"10936",
    "addr:postcode":"93277",
    "addr:street":"Ave 272",
    "iso:country":"US",
    "sg:address":"10936 Ave 272",
    "sg:city":"Visalia",
    "sg:classifiers":[
        {
            "category":"Building & Trades",
            "subcategory":"Plumbing",
            "type":"Services"
        }
    ],
    "sg:phone":"+1 559 686 6926",
    "sg:postcode":"93277",
    "sg:province":"CA",
    "sg:tags":[
        "conditioning",
        "air",
        "system",
        "contractor"
    ],
    "wof:name":"Saldana's Heating & Air Cond",
    "wof:placetype":"venue"
},
  "geometry": {"coordinates":[-119.328574,36.28385],"type":"Point"}
}