{
  "type": "Feature",
  "properties": {
    "addr:full":"12028 Vose St North Hollywood CA 91605",
    "addr:postcode":"12028;91605",
    "addr:street":"Vose St",
    "iso:country":"US",
    "sg:address":"12028 Vose St",
    "sg:city":"North Hollywood",
    "sg:classifiers":[
        {
            "category":"Communications",
            "subcategory":"Film & Video Production",
            "type":"Services"
        }
    ],
    "sg:phone":"+1 818 982 0180",
    "sg:postcode":"91605",
    "sg:province":"CA",
    "sg:tags":[
        "studio",
        "rental"
    ],
    "wof:name":"Bill's Place",
    "wof:placetype":"venue"
},
  "geometry": {"coordinates":[-118.39417899999999,34.198365],"type":"Point"}
}