{
  "type": "Feature",
  "properties": {
    "addr:full":"465 W Julian St San Jose CA 95110",
    "addr:housenumber":"465",
    "addr:postcode":"95110",
    "addr:street":"W Julian St",
    "iso:country":"US",
    "sg:address":"465 W Julian St",
    "sg:city":"San Jose",
    "sg:classifiers":[
        {
            "category":"Building & Trades",
            "subcategory":"Construction",
            "type":"Services"
        }
    ],
    "sg:phone":"+1 408 279 8396",
    "sg:postcode":"95110",
    "sg:province":"CA",
    "sg:tags":[
        "interior",
        "design"
    ],
    "wof:name":"Quintero Custom Cabinet",
    "wof:placetype":"venue"
},
  "geometry": {"coordinates":[-121.902,37.335701],"type":"Point"}
}