{
  "type": "Feature",
  "properties": {
    "addr:full":"4561 Mission Gorge Pl San Diego CA 92120",
    "addr:housenumber":"4561",
    "addr:postcode":"92120",
    "addr:street":"Mission Gorge Pl",
    "iso:country":"US",
    "sg:address":"4561 Mission Gorge Pl",
    "sg:city":"San Diego",
    "sg:classifiers":[
        {
            "category":"Professional",
            "subcategory":"Advertising",
            "type":"Services"
        }
    ],
    "sg:phone":"+1 619 284 4721",
    "sg:postcode":"92120",
    "sg:province":"CA",
    "sg:tags":[
        "counselor"
    ],
    "wof:name":"Mountain's Secret",
    "wof:placetype":"venue"
},
  "geometry": {"coordinates":[-117.092032,32.782462],"type":"Point"}
}