{
  "type": "Feature",
  "properties": {
    "iso:country":"US",
    "sg:address":"2337 Harrison St",
    "sg:city":"Santa Clara",
    "sg:classifiers":[
        {
            "category":"Education",
            "subcategory":"Special Training",
            "type":"Public Place"
        }
    ],
    "sg:phone":"+1 408 248 5992",
    "sg:postcode":"95050",
    "sg:province":"CA",
    "sg:tags":[
        "instruction",
        "music"
    ],
    "wof:name":"Patricia Cachopo Piano",
    "wof:placetype":"venue"
},
  "geometry": {"coordinates":[-121.966786,37.349305],"type":"Point"}
}