{
  "type": "Feature",
  "properties": {
    "iso:country":"US",
    "sg:address":"909 Hyde Street Ste #303",
    "sg:city":"San Francisco",
    "sg:classifiers":[
        {
            "category":"Health Services",
            "subcategory":"Doctor",
            "type":"Services"
        }
    ],
    "sg:phone":"+1 415 673 6522",
    "sg:postcode":"94118",
    "sg:province":"CA",
    "sg:tags":[
        "obstetrician",
        "gynecologist"
    ],
    "wof:name":"Mary Ulrich, M.D.",
    "wof:placetype":"venue"
},
  "geometry": {"coordinates":[-122.417604,37.789509],"type":"Point"}
}