{
  "type": "Feature",
  "properties": {
    "addr:full":"3649 Yale Way Fremont CA 94538",
    "addr:housenumber":"3649",
    "addr:postcode":"94538",
    "addr:street":"Yale Way",
    "iso:country":"US",
    "sg:address":"3649 Yale Way",
    "sg:city":"Fremont",
    "sg:classifiers":[
        {
            "category":"Manufacturing",
            "subcategory":"Tools & Machinery",
            "type":"Manufacturing & Wholesale Goods"
        }
    ],
    "sg:phone":"+1 510 651 2012",
    "sg:postcode":"94538",
    "sg:province":"CA",
    "sg:tags":[
        "mold"
    ],
    "wof:name":"Mold 2 Specs Inc",
    "wof:placetype":"venue"
},
  "geometry": {"coordinates":[-121.94612600000001,37.509948],"type":"Point"}
}