{
  "type": "Feature",
  "properties": {
    "iso:country":"US",
    "sg:address":"2020 Matthew Ave",
    "sg:city":"Rosamond",
    "sg:classifiers":[
        {
            "category":"Professional",
            "subcategory":"Computer Services",
            "type":"Services"
        }
    ],
    "sg:phone":"+1 661 256 1188",
    "sg:postcode":"93560",
    "sg:province":"CA",
    "wof:name":"James Bros Systems",
    "wof:placetype":"venue"
},
  "geometry": {"coordinates":[-118.168702,34.856187],"type":"Point"}
}