{
  "type": "Feature",
  "properties": {
    "addr:full":"3134 W Olympic Blvd Los Angeles CA 90006",
    "addr:housenumber":"3134",
    "addr:postcode":"90006",
    "addr:street":"W Olympic Blvd",
    "iso:country":"US",
    "sg:address":"3134 W Olympic Blvd",
    "sg:city":"Los Angeles",
    "sg:classifiers":[
        {
            "category":"Shopping",
            "subcategory":"Hobbies, Toys, & Games",
            "type":"Retail Goods"
        }
    ],
    "sg:phone":"+1 323 732 8399",
    "sg:postcode":"90006",
    "sg:province":"CA",
    "wof:name":"Mickey Video",
    "wof:placetype":"venue"
},
  "geometry": {"coordinates":[-118.305173,34.052522],"type":"Point"}
}