{
  "type": "Feature",
  "properties": {
    "iso:country":"US",
    "sg:address":"940 Rescue Rd",
    "sg:city":"Rescue",
    "sg:classifiers":[
        {
            "category":"Building & Trades",
            "subcategory":"Construction",
            "type":"Services"
        }
    ],
    "sg:phone":"+1 530 677 2750",
    "sg:postcode":"95672",
    "sg:province":"CA",
    "sg:tags":[
        "water",
        "well",
        "drilling"
    ],
    "sg:website":"www.trianglewell.com",
    "wof:name":"Triangle Well Drilling",
    "wof:placetype":"venue"
},
  "geometry": {"coordinates":[-120.97950899999999,38.748984],"type":"Point"}
}