{
  "type": "Feature",
  "properties": {
    "addr:full":"2612 Alcatraz Ave Berkeley CA 94705",
    "addr:housenumber":"2612",
    "addr:postcode":"94705",
    "addr:street":"Alcatraz Ave",
    "iso:country":"US",
    "sg:address":"2612 Alcatraz Ave",
    "sg:city":"Berkeley",
    "sg:classifiers":[
        {
            "category":"Shopping",
            "subcategory":"Clothing, Apparel, & Fashions",
            "type":"Retail Goods"
        }
    ],
    "sg:phone":"+1 510 420 1338",
    "sg:postcode":"94705",
    "sg:province":"CA",
    "sg:tags":[
        "shop",
        "bridal"
    ],
    "sg:website":"theweddingpartyonline.com/",
    "wof:name":"The Wedding Party",
    "wof:placetype":"venue"
},
  "geometry": {"coordinates":[-122.253058,37.851175],"type":"Point"}
}