{
  "type": "Feature",
  "properties": {
    "addr:full":"47411 Cottonwood Rd Newberry Springs CA 92365",
    "addr:housenumber":"47411",
    "addr:postcode":"92365",
    "addr:street":"Cottonwood Rd",
    "iso:country":"US",
    "sg:address":"47411 Cottonwood Rd",
    "sg:city":"Newberry Springs",
    "sg:classifiers":[
        {
            "category":"Professional",
            "subcategory":"Lawyer & Legal Services",
            "type":"Services"
        }
    ],
    "sg:phone":"+1 760 257 4636",
    "sg:postcode":"92365",
    "sg:province":"CA",
    "sg:tags":[
        "grove",
        "nut",
        "tree"
    ],
    "wof:name":"Roger Luna",
    "wof:placetype":"venue"
},
  "geometry": {"coordinates":[-116.626993,34.850719],"type":"Point"}
}