{
  "type": "Feature",
  "properties": {
    "addr:full":"3013 S. Beverly Dr. Los Angeles CA 90034",
    "addr:housenumber":"3013",
    "addr:postcode":"90034",
    "addr:street":"S. Beverly Dr.",
    "iso:country":"US",
    "sg:address":"3013 S. Beverly Dr.",
    "sg:city":"Los Angeles",
    "sg:classifiers":[
        {
            "category":"Professional",
            "subcategory":"Accounting & Tax Preparation",
            "type":"Services"
        }
    ],
    "sg:phone":"+1 310 280 0374",
    "sg:postcode":"90034",
    "sg:province":"CA",
    "sg:tags":[
        "accountant"
    ],
    "sg:website":"www.taxmark.com",
    "wof:name":"Mark Lowen",
    "wof:placetype":"venue"
},
  "geometry": {"coordinates":[-118.39747199999999,34.035142],"type":"Point"}
}