{
  "type": "Feature",
  "properties": {
    "addr:full":"34151 Monterey Ave. Rancho Mirage CA 92270",
    "addr:housenumber":"34151",
    "addr:postcode":"92270",
    "addr:street":"Monterey Ave.",
    "iso:country":"US",
    "sg:address":"34151 Monterey Ave.",
    "sg:city":"Rancho Mirage",
    "sg:classifiers":[
        {
            "category":"Coffee & Tea",
            "type":"Food & Drink"
        }
    ],
    "sg:phone":"+1 760 776 7913",
    "sg:postcode":"92270",
    "sg:province":"CA",
    "sg:website":"www.badasscoffee.com/index.php",
    "wof:name":"Bad Ass Coffee",
    "wof:placetype":"venue"
},
  "geometry": {"coordinates":[-116.388853,33.801057],"type":"Point"}
}