{
  "type": "Feature",
  "properties": {
    "addr:full":"4083 24th St San Francisco CA 94114",
    "addr:housenumber":"4083",
    "addr:postcode":"94114",
    "addr:street":"24Th St",
    "iso:country":"US",
    "sg:address":"4083 24th St",
    "sg:city":"San Francisco",
    "sg:classifiers":[
        {
            "category":"Government",
            "subcategory":"Post Office",
            "type":"Public Place"
        }
    ],
    "sg:phone":"+1 415 821 3914",
    "sg:postcode":"94114",
    "sg:province":"CA",
    "sg:website":"www.usps.gov",
    "wof:name":"US Post Office - Noe Valley",
    "wof:placetype":"venue"
},
  "geometry": {"coordinates":[-122.433746,37.751344],"type":"Point"}
}