{
  "type": "Feature",
  "properties": {
    "iso:country":"US",
    "sg:address":"2801 W Ave H",
    "sg:city":"Lancaster",
    "sg:classifiers":[
        {
            "category":"Wholesale",
            "subcategory":"Drugs",
            "type":"Manufacturing & Wholesale Goods"
        }
    ],
    "sg:phone":"+1 661 951 7500",
    "sg:postcode":"93536",
    "sg:province":"CA",
    "sg:website":"www.riteaid.com",
    "wof:name":"Rite Aid Pharmacy",
    "wof:placetype":"venue"
},
  "geometry": {"coordinates":[-118.179794,34.718826],"type":"Point"}
}