{
  "type": "Feature",
  "properties": {
    "iso:country":"US",
    "sg:address":"859 N Hollywood Way",
    "sg:city":"Burbank",
    "sg:classifiers":[
        {
            "category":"Professional",
            "subcategory":"Engineering",
            "type":"Services"
        }
    ],
    "sg:phone":"+1 818 549 9981",
    "sg:postcode":"91505",
    "sg:province":"CA",
    "sg:tags":[
        "engineer"
    ],
    "wof:name":"Bnet Technologies",
    "wof:placetype":"venue"
},
  "geometry": {"coordinates":[-118.346598,34.166861],"type":"Point"}
}