{
  "type": "Feature",
  "properties": {
    "addr:full":"6837 La Jolla Blvd La Jolla CA 92037",
    "addr:housenumber":"6837",
    "addr:postcode":"92037",
    "addr:street":"La Jolla Blvd",
    "iso:country":"US",
    "sg:address":"6837 La Jolla Blvd",
    "sg:city":"La Jolla",
    "sg:classifiers":[
        {
            "category":"Shopping",
            "subcategory":"Computers & Home Electronics",
            "type":"Retail Goods"
        },
        {
            "category":"Professional",
            "subcategory":"Computer Services",
            "type":"Services"
        }
    ],
    "sg:phone":"+1 858 750 3177",
    "sg:postcode":"92037",
    "sg:province":"CA",
    "sg:tags":[
        "repair",
        "installation",
        "theatre"
    ],
    "sg:website":"www.lajollahomeaudio.com",
    "wof:name":"La Jolla Home Theater & Automation",
    "wof:placetype":"venue"
},
  "geometry": {"coordinates":[-117.276117,32.831327],"type":"Point"}
}