{
  "type": "Feature",
  "properties": {
    "addr:full":"16970 Hidden Valley Rd Perris CA 92570",
    "addr:housenumber":"16970",
    "addr:postcode":"92570",
    "addr:street":"Hidden Valley Rd",
    "iso:country":"US",
    "sg:address":"16970 Hidden Valley Rd",
    "sg:city":"Perris",
    "sg:classifiers":[
        {
            "category":"Retail",
            "subcategory":"Repair Shop",
            "type":"Services"
        },
        {
            "category":"Wholesale",
            "subcategory":"Durable Goods & Equipment",
            "type":"Manufacturing & Wholesale Goods"
        }
    ],
    "sg:phone":"+1 951 780 8393",
    "sg:postcode":"92570",
    "sg:province":"CA",
    "sg:tags":[
        "closer",
        "door",
        "check"
    ],
    "wof:name":"Western Product Co",
    "wof:placetype":"venue"
},
  "geometry": {"coordinates":[-117.36398199999999,33.775313],"type":"Point"}
}