{
  "type": "Feature",
  "properties": {
    "iso:country":"US",
    "sg:address":"3933 James Dr",
    "sg:city":"Carlsbad",
    "sg:classifiers":[
        {
            "category":"Banks & Credit Unions",
            "subcategory":"Financial Services",
            "type":"Services"
        }
    ],
    "sg:phone":"+1 760 434 6889",
    "sg:postcode":"92008",
    "sg:province":"CA",
    "sg:tags":[
        "trust",
        "management"
    ],
    "wof:name":"Malone Family Living Trus",
    "wof:placetype":"venue"
},
  "geometry": {"coordinates":[-117.329434,33.155067],"type":"Point"}
}