{
  "type": "Feature",
  "properties": {
    "iso:country":"US",
    "sg:address":"600 Peach Ct",
    "sg:city":"Fairfield",
    "sg:classifiers":[
        {
            "category":"Real Estate",
            "subcategory":"Real Estate Agent",
            "type":"Services"
        }
    ],
    "sg:phone":"+1 707 435 8841",
    "sg:postcode":"94534",
    "sg:province":"CA",
    "sg:tags":[
        "inspection"
    ],
    "sg:website":"www.accuratehomeinspection.com",
    "wof:name":"Accurate Home Inspections",
    "wof:placetype":"venue"
},
  "geometry": {"coordinates":[-122.165933,38.246383],"type":"Point"}
}