{
  "type": "Feature",
  "properties": {
    "iso:country":"US",
    "sg:address":"1370 N Brea Blvd",
    "sg:city":"Fullerton",
    "sg:classifiers":[
        {
            "category":"Insurance",
            "subcategory":"Insurance Agent",
            "type":"Services"
        }
    ],
    "sg:phone":"+1 714 870 7740",
    "sg:postcode":"92835",
    "sg:province":"CA",
    "wof:name":"Farmers Insurance",
    "wof:placetype":"venue"
},
  "geometry": {"coordinates":[-117.924226,33.884085],"type":"Point"}
}