{
  "type": "Feature",
  "properties": {
    "addr:full":"13011 Garvey Ave Baldwin Park CA 91706",
    "addr:housenumber":"13011",
    "addr:postcode":"91706",
    "addr:street":"Garvey Ave",
    "iso:country":"US",
    "sg:address":"13011 Garvey Ave",
    "sg:city":"Baldwin Park",
    "sg:classifiers":[
        {
            "category":"Retail",
            "subcategory":"Auto Repair",
            "type":"Services"
        }
    ],
    "sg:phone":"+1 626 338 0724",
    "sg:postcode":"91706",
    "sg:province":"CA",
    "sg:tags":[
        "repairing",
        "automobile"
    ],
    "wof:name":"Gold Star Auto Svc",
    "wof:placetype":"venue"
},
  "geometry": {"coordinates":[-117.987786,34.067089],"type":"Point"}
}