{
  "type": "Feature",
  "properties": {
    "addr:full":"7815 Somerset Blvd Paramount CA 90723",
    "addr:housenumber":"7815",
    "addr:postcode":"90723",
    "addr:street":"Somerset Blvd",
    "iso:country":"US",
    "sg:address":"7815 Somerset Blvd",
    "sg:city":"Paramount",
    "sg:classifiers":[
        {
            "category":"Manufacturing",
            "subcategory":"Metals",
            "type":"Manufacturing & Wholesale Goods"
        }
    ],
    "sg:phone":"+1 562 630 6804",
    "sg:postcode":"90723",
    "sg:province":"CA",
    "sg:tags":[
        "steel"
    ],
    "sg:website":"www.enertechmetals.com",
    "wof:name":"Ener-Tech Metals Inc",
    "wof:placetype":"venue"
},
  "geometry": {"coordinates":[-118.162246,33.896427],"type":"Point"}
}