{
  "type": "Feature",
  "properties": {
    "addr:full":"2475 Colorado Ave Santa Monica CA 90404",
    "addr:housenumber":"2475",
    "addr:postcode":"90404",
    "addr:street":"Colorado Ave",
    "iso:country":"US",
    "sg:address":"2475 Colorado Ave",
    "sg:city":"Santa Monica",
    "sg:classifiers":[
        {
            "category":"Communications",
            "subcategory":"Film & Video Production",
            "type":"Services"
        }
    ],
    "sg:phone":"+1 310 712 1676",
    "sg:postcode":"90404",
    "sg:province":"CA",
    "sg:tags":[
        "co"
    ],
    "wof:name":"Desert Oasis Productions Inc",
    "wof:placetype":"venue"
},
  "geometry": {"coordinates":[-118.47272700000001,34.029452],"type":"Point"}
}