{
  "type": "Feature",
  "properties": {
    "addr:full":"140 S 6th St Chowchilla CA 93610",
    "addr:housenumber":"140",
    "addr:postcode":"93610",
    "addr:street":"S 6Th St",
    "iso:country":"US",
    "sg:address":"140 S 6th St",
    "sg:city":"Chowchilla",
    "sg:classifiers":[
        {
            "category":"Cemetery",
            "type":"Public Place"
        },
        {
            "category":"Retail",
            "subcategory":"Funeral Services",
            "type":"Services"
        }
    ],
    "sg:phone":"+1 559 665 3012",
    "sg:postcode":"93610",
    "sg:province":"CA",
    "sg:tags":[
        "director",
        "embalmer",
        "crematory"
    ],
    "wof:name":"Palm Memorial Worden Chapel",
    "wof:placetype":"venue"
},
  "geometry": {"coordinates":[-120.263222,37.119768],"type":"Point"}
}