{
  "type": "Feature",
  "properties": {
    "addr:full":"401 Bel Marin Keys Blvd Novato CA 94949",
    "addr:housenumber":"401",
    "addr:postcode":"94949",
    "addr:street":"Bel Marin Keys Blvd",
    "iso:country":"US",
    "sg:address":"401 Bel Marin Keys Blvd",
    "sg:city":"Novato",
    "sg:classifiers":[
        {
            "category":"Shopping",
            "subcategory":"Gifts & Souvenirs",
            "type":"Retail Goods"
        }
    ],
    "sg:phone":"+1 415 883 4180",
    "sg:postcode":"94949",
    "sg:province":"CA",
    "sg:tags":[
        "party",
        "supply"
    ],
    "wof:name":"Pinball Revival Co",
    "wof:placetype":"venue"
},
  "geometry": {"coordinates":[-122.537533,38.073923],"type":"Point"}
}