{
  "type": "Feature",
  "properties": {
    "iso:country":"US",
    "sg:address":"59 Cam del Oro",
    "sg:city":"Rancho Santa Margarita",
    "sg:classifiers":[
        {
            "category":"Retail",
            "subcategory":"Photofinishing",
            "type":"Services"
        }
    ],
    "sg:phone":"+1 949 459 9165",
    "sg:postcode":"92688",
    "sg:province":"CA",
    "sg:tags":[
        "laboratory"
    ],
    "wof:name":"Fleming Photo & Design",
    "wof:placetype":"venue"
},
  "geometry": {"coordinates":[-117.61962699999999,33.654649],"type":"Point"}
}