{
  "type": "Feature",
  "properties": {
    "iso:country":"US",
    "sg:address":"1417 Georgia St",
    "sg:city":"Vallejo",
    "sg:classifiers":[
        {
            "category":"Shopping",
            "subcategory":"Clothing, Apparel, & Fashions",
            "type":"Retail Goods"
        }
    ],
    "sg:phone":"+1 707 643 6674",
    "sg:postcode":"94590",
    "sg:province":"CA",
    "sg:tags":[
        "wig",
        "toupee",
        "hairpiece"
    ],
    "wof:name":"Myrran Inc",
    "wof:placetype":"venue"
},
  "geometry": {"coordinates":[-122.238775,38.100829],"type":"Point"}
}