{
  "type": "Feature",
  "properties": {
    "iso:country":"US",
    "sg:address":"73413 Terraza Dr",
    "sg:city":"Palm Desert",
    "sg:classifiers":[
        {
            "category":"Insurance",
            "subcategory":"Insurance Agent",
            "type":"Services"
        }
    ],
    "sg:phone":"+1 760 776 8849",
    "sg:postcode":"92260",
    "sg:province":"CA",
    "wof:name":"Randy L Rosten Insurance",
    "wof:placetype":"venue"
},
  "geometry": {"coordinates":[-116.38463400000001,33.75294],"type":"Point"}
}