{
  "type": "Feature",
  "properties": {
    "iso:country":"US",
    "sg:address":"428 J St",
    "sg:city":"Sacramento",
    "sg:classifiers":[
        {
            "category":"Professional",
            "subcategory":"Management & Consulting",
            "type":"Services"
        }
    ],
    "sg:phone":"+1 916 447 7315",
    "sg:postcode":"95814",
    "sg:province":"CA",
    "sg:tags":[
        "lobbyist"
    ],
    "wof:name":"Alliance Of Automobile Mfr Inc",
    "wof:placetype":"venue"
},
  "geometry": {"coordinates":[-121.500417,38.582113],"type":"Point"}
}