{
  "type": "Feature",
  "properties": {
    "addr:full":"1400 N La Brea Ave Inglewood CA 90302",
    "addr:housenumber":"1400",
    "addr:postcode":"90302",
    "addr:street":"N La Brea Ave",
    "iso:country":"US",
    "sg:address":"1400 N La Brea Ave",
    "sg:city":"Inglewood",
    "sg:classifiers":[
        {
            "category":"Restaurant",
            "type":"Food & Drink"
        }
    ],
    "sg:phone":"+1 310 673 0824",
    "sg:postcode":"90302",
    "sg:province":"CA",
    "sg:tags":[
        "cajun/creole"
    ],
    "sg:website":"www.bayougrille.net",
    "wof:name":"Bayou Grille",
    "wof:placetype":"venue"
},
  "geometry": {"coordinates":[-118.35785199999999,33.980363],"type":"Point"}
}