{
  "type": "Feature",
  "properties": {
    "addr:full":"25171 de Salle St Laguna Hills CA 92653",
    "addr:postcode":"25171;92653",
    "addr:street":"Salle St",
    "iso:country":"US",
    "sg:address":"25171 de Salle St",
    "sg:city":"Laguna Hills",
    "sg:classifiers":[
        {
            "category":"Professional",
            "subcategory":"Business Services",
            "type":"Services"
        }
    ],
    "sg:phone":"+1 949 495 5570",
    "sg:postcode":"92653",
    "sg:province":"CA",
    "sg:tags":[
        "pool",
        "swimming"
    ],
    "wof:name":"Pool Cleaner",
    "wof:placetype":"venue"
},
  "geometry": {"coordinates":[-117.68606800000001,33.59721],"type":"Point"}
}