{
  "type": "Feature",
  "properties": {
    "iso:country":"US",
    "sg:address":"21521 Brookhurst St",
    "sg:city":"Huntington Beach",
    "sg:classifiers":[
        {
            "category":"Organizations",
            "subcategory":"Religious Organization",
            "type":"Services"
        }
    ],
    "sg:phone":"+1 714 964 7315",
    "sg:postcode":"92646",
    "sg:province":"CA",
    "wof:name":"Beach Cities Community",
    "wof:placetype":"venue"
},
  "geometry": {"coordinates":[-117.95382499999999,33.650294],"type":"Point"}
}