{
  "type": "Feature",
  "properties": {
    "addr:full":"52454 Cll Techa Coachella CA 92236",
    "addr:housenumber":"52454",
    "addr:postcode":"92236",
    "addr:street":"Cll Techa",
    "iso:country":"US",
    "sg:address":"52454 Cll Techa",
    "sg:city":"Coachella",
    "sg:classifiers":[
        {
            "category":"Professional",
            "subcategory":"Accounting & Tax Preparation",
            "type":"Services"
        }
    ],
    "sg:phone":"+1 760 398 0679",
    "sg:postcode":"92236",
    "sg:province":"CA",
    "sg:tags":[
        "return",
        "filing"
    ],
    "wof:name":"Aurora's Income Tax & Notary",
    "wof:placetype":"venue"
},
  "geometry": {"coordinates":[-116.185006,33.668853],"type":"Point"}
}