{
  "type": "Feature",
  "properties": {
    "iso:country":"US",
    "sg:address":"9025 Atlanta Ave",
    "sg:city":"Huntington Beach",
    "sg:classifiers":[
        {
            "category":"Personal",
            "subcategory":"Beauty Salon",
            "type":"Services"
        },
        {
            "category":"Health Services",
            "subcategory":"Chiropractor",
            "type":"Services"
        }
    ],
    "sg:phone":"+1 714 963 3232",
    "sg:postcode":"92646",
    "sg:province":"CA",
    "sg:tags":[
        "spa"
    ],
    "sg:website":"hudsonwellnesscenterhb.com",
    "wof:name":"Beach Reflexology and Hudson Wellness Center",
    "wof:placetype":"venue"
},
  "geometry": {"coordinates":[-117.97095299999999,33.657767],"type":"Point"}
}