{
  "type": "Feature",
  "properties": {
    "iso:country":"US",
    "sg:address":"30401 Agoura Rd",
    "sg:city":"Agoura Hills",
    "sg:classifiers":[
        {
            "category":"Government",
            "subcategory":"Office",
            "type":"Public Place"
        }
    ],
    "sg:phone":"+1 818 597 1036",
    "sg:postcode":"91301",
    "sg:province":"CA",
    "sg:tags":[
        "management",
        "agency",
        "protection",
        "land"
    ],
    "wof:name":"Santa Monica Mountains Nra",
    "wof:placetype":"venue"
},
  "geometry": {"coordinates":[-118.784868,34.145146],"type":"Point"}
}