{
  "type": "Feature",
  "properties": {
    "iso:country":"US",
    "sg:address":"7250 Painter Ave",
    "sg:city":"Whittier",
    "sg:classifiers":[
        {
            "category":"Banks & Credit Unions",
            "subcategory":"Financial Services",
            "type":"Services"
        }
    ],
    "sg:phone":"+1 562 698 5600",
    "sg:postcode":"90602",
    "sg:province":"CA",
    "sg:tags":[
        "broker",
        "mortgage"
    ],
    "wof:name":"Elite Team Mortgage",
    "wof:placetype":"venue"
},
  "geometry": {"coordinates":[-118.24946300000001,33.976023],"type":"Point"}
}