{
  "type": "Feature",
  "properties": {
    "iso:country":"US",
    "sg:address":"4644 Lincoln Blvd",
    "sg:city":"Marina Del Rey",
    "sg:classifiers":[
        {
            "category":"Health Services",
            "subcategory":"Doctor",
            "type":"Services"
        }
    ],
    "sg:phone":"+1 310 482 6906",
    "sg:postcode":"90292",
    "sg:province":"CA",
    "wof:name":"Seymore Castoria Jr MD",
    "wof:placetype":"venue"
},
  "geometry": {"coordinates":[-118.440684,33.982541],"type":"Point"}
}