{
  "type": "Feature",
  "properties": {
    "addr:full":"800 Coffee Rd Modesto CA 95355",
    "addr:housenumber":"800",
    "addr:postcode":"ca 95355",
    "addr:street":"Coffee Rd",
    "iso:country":"US",
    "sg:address":"800 Coffee Rd",
    "sg:city":"Modesto",
    "sg:classifiers":[
        {
            "category":"Personal",
            "subcategory":"Beauty Salon",
            "type":"Services"
        }
    ],
    "sg:phone":"+1 209 525 3600",
    "sg:postcode":"95355",
    "sg:province":"CA",
    "wof:name":"Illumina Laser & Skin Care",
    "wof:placetype":"venue"
},
  "geometry": {"coordinates":[-120.97549600000001,37.654905],"type":"Point"}
}