{
  "type": "Feature",
  "properties": {
    "addr:full":"14620 Dickens St Sherman Oaks CA 91403",
    "addr:housenumber":"14620",
    "addr:postcode":"91403",
    "addr:street":"Dickens St",
    "iso:country":"US",
    "sg:address":"14620 Dickens St",
    "sg:city":"Sherman Oaks",
    "sg:classifiers":[
        {
            "category":"Professional",
            "subcategory":"Art Services",
            "type":"Services"
        }
    ],
    "sg:phone":"+1 818 907 0023",
    "sg:postcode":"91403",
    "sg:province":"CA",
    "sg:tags":[
        "graphic",
        "designer"
    ],
    "wof:name":"Levram Design",
    "wof:placetype":"venue"
},
  "geometry": {"coordinates":[-118.456519,34.150877],"type":"Point"}
}