{
  "type": "Feature",
  "properties": {
    "iso:country":"US",
    "sg:address":"2400 Geng Rd",
    "sg:city":"Palo Alto",
    "sg:classifiers":[
        {
            "category":"Manufacturing",
            "subcategory":"Electronics",
            "type":"Manufacturing & Wholesale Goods"
        }
    ],
    "sg:phone":"+1 650 424 1937",
    "sg:postcode":"94303",
    "sg:province":"CA",
    "sg:tags":[
        "semiconductor",
        "devices"
    ],
    "sg:website":"www.iterracommunications.com",
    "wof:name":"Iterra Communications",
    "wof:placetype":"venue"
},
  "geometry": {"coordinates":[-122.118866,37.450304],"type":"Point"}
}