{
  "type": "Feature",
  "properties": {
    "iso:country":"US",
    "sg:address":"100 Throckmorton Ave",
    "sg:city":"Mill Valley",
    "sg:classifiers":[
        {
            "category":"Home & Garden",
            "subcategory":"Home Furnishings",
            "type":"Retail Goods"
        }
    ],
    "sg:phone":"+1 415 388 1720",
    "sg:postcode":"94941",
    "sg:province":"CA",
    "sg:tags":[
        "utensil",
        "cooking"
    ],
    "wof:name":"Capricorn Gourmet Cookware",
    "wof:placetype":"venue"
},
  "geometry": {"coordinates":[-122.547903,37.906456],"type":"Point"}
}