{
  "type": "Feature",
  "properties": {
    "iso:country":"US",
    "sg:address":"2350 Mission College Blvd",
    "sg:city":"Santa Clara",
    "sg:classifiers":[
        {
            "category":"Professional",
            "type":"Services"
        }
    ],
    "sg:phone":"+1 408 346 0145",
    "sg:postcode":"95054",
    "sg:province":"CA",
    "sg:tags":[
        "establishment"
    ],
    "sg:website":"www.solution-soft.com",
    "wof:name":"Solution Soft Inc",
    "wof:placetype":"venue"
},
  "geometry": {"coordinates":[-121.96659,37.38879],"type":"Point"}
}