{
  "type": "Feature",
  "properties": {
    "addr:full":"3914 Murphy Canyon Rd San Diego CA 92123",
    "addr:housenumber":"3914",
    "addr:postcode":"92123",
    "addr:street":"Murphy Canyon Rd",
    "iso:country":"US",
    "sg:address":"3914 Murphy Canyon Rd",
    "sg:city":"San Diego",
    "sg:classifiers":[
        {
            "category":"Banks & Credit Unions",
            "subcategory":"Bank",
            "type":"Services"
        }
    ],
    "sg:phone":"+1 858 492 4413",
    "sg:postcode":"92123",
    "sg:province":"CA",
    "sg:tags":[
        "loan",
        "real estate"
    ],
    "wof:name":"Bay Mortgage",
    "wof:placetype":"venue"
},
  "geometry": {"coordinates":[-117.11739,32.821312],"type":"Point"}
}