{
  "type": "Feature",
  "properties": {
    "addr:full":"500 Park St Lodi CA 95240",
    "addr:housenumber":"500",
    "addr:postcode":"95240",
    "addr:street":"Park St",
    "iso:country":"US",
    "sg:address":"500 Park St",
    "sg:city":"Lodi",
    "sg:classifiers":[
        {
            "category":"Organizations",
            "subcategory":"Religious Organization",
            "type":"Services"
        }
    ],
    "sg:phone":"+1 209 369 3004",
    "sg:postcode":"95240",
    "sg:province":"CA",
    "sg:tags":[
        "church"
    ],
    "wof:name":"Faith Fellowship Foursquare",
    "wof:placetype":"venue"
},
  "geometry": {"coordinates":[-121.282906,38.1203],"type":"Point"}
}