{
  "type": "Feature",
  "properties": {
    "iso:country":"US",
    "sg:address":"16018 Adelante St",
    "sg:city":"Irwindale",
    "sg:classifiers":[
        {
            "category":"Manufacturing",
            "subcategory":"Tools & Machinery",
            "type":"Manufacturing & Wholesale Goods"
        }
    ],
    "sg:phone":"+1 626 914 3287",
    "sg:postcode":"91702",
    "sg:province":"CA",
    "sg:tags":[
        "physician",
        "surgeon"
    ],
    "wof:name":"KVP Inc",
    "wof:placetype":"venue"
},
  "geometry": {"coordinates":[-117.931274,34.126866],"type":"Point"}
}