{
  "type": "Feature",
  "properties": {
    "iso:country":"US",
    "sg:address":"6000 Atlantic Ave",
    "sg:city":"Long Beach",
    "sg:classifiers":[
        {
            "category":"Food & Beverages",
            "subcategory":"Groceries & Convenience Stores",
            "type":"Retail Goods"
        }
    ],
    "sg:phone":"+1 562 423 2500",
    "sg:postcode":"90805",
    "sg:province":"CA",
    "sg:website":"www.albertsons.com",
    "wof:name":"Albertsons",
    "wof:placetype":"venue"
},
  "geometry": {"coordinates":[-118.184774,33.8637],"type":"Point"}
}