{
  "type": "Feature",
  "properties": {
    "iso:country":"US",
    "sg:address":"2488 Main St",
    "sg:city":"Chula Vista",
    "sg:classifiers":[
        {
            "category":"Food & Beverages",
            "subcategory":"Specialty",
            "type":"Retail Goods"
        },
        {
            "category":"Wholesale",
            "subcategory":"Drugs",
            "type":"Manufacturing & Wholesale Goods"
        }
    ],
    "sg:phone":"+1 619 575 6802",
    "sg:postcode":"91911",
    "sg:province":"CA",
    "sg:tags":[
        "vitamin"
    ],
    "wof:name":"Mex Natura",
    "wof:placetype":"venue"
},
  "geometry": {"coordinates":[-117.077759,32.594863],"type":"Point"}
}