{
  "type": "Feature",
  "properties": {
    "addr:full":"933 Main St Ramona CA 92065",
    "addr:housenumber":"933",
    "addr:postcode":"92065",
    "addr:street":"Main St",
    "iso:country":"US",
    "sg:address":"933 Main St",
    "sg:city":"Ramona",
    "sg:classifiers":[
        {
            "category":"Personal",
            "subcategory":"Tattoo Parlor",
            "type":"Services"
        }
    ],
    "sg:phone":"+1 760 787 0894",
    "sg:postcode":"92065",
    "sg:province":"CA",
    "sg:tags":[
        "tattooing"
    ],
    "wof:name":"Inkwell Tattooing & Body Prcng",
    "wof:placetype":"venue"
},
  "geometry": {"coordinates":[-116.868149,33.042382],"type":"Point"}
}