{
  "type": "Feature",
  "properties": {
    "addr:full":"31724 Casino Dr Lake Elsinore CA 92530",
    "addr:postcode":"31724;92530",
    "addr:street":"Casino Dr",
    "iso:country":"US",
    "sg:address":"31724 Casino Dr",
    "sg:city":"Lake Elsinore",
    "sg:classifiers":[
        {
            "category":"Restaurant",
            "type":"Food & Drink"
        }
    ],
    "sg:phone":"+1 951 674 8989",
    "sg:postcode":"92530",
    "sg:province":"CA",
    "sg:tags":[
        "steakhouse"
    ],
    "sg:website":"www.sizzler.com/",
    "wof:name":"Sizzler",
    "wof:placetype":"venue"
},
  "geometry": {"coordinates":[-117.30150999999999,33.662147],"type":"Point"}
}