{
  "type": "Feature",
  "properties": {
    "addr:full":"3800 Del Paso Rd Sacramento CA 95834",
    "addr:housenumber":"3800",
    "addr:postcode":"95834",
    "addr:street":"Del Paso Rd",
    "iso:country":"US",
    "sg:address":"3800 Del Paso Rd",
    "sg:city":"Sacramento",
    "sg:classifiers":[
        {
            "category":"Education",
            "subcategory":"Preschool",
            "type":"Public Place"
        }
    ],
    "sg:phone":"+1 916 567 5760",
    "sg:postcode":"95834",
    "sg:province":"CA",
    "sg:website":"www.westlakecharter.com/preschoo...",
    "wof:name":"Westlake Little Explorers Preschool",
    "wof:placetype":"venue"
},
  "geometry": {"coordinates":[-121.55392500000001,38.655584],"type":"Point"}
}