{
  "type": "Feature",
  "properties": {
    "iso:country":"US",
    "sg:address":"1035 Rosewood Dr",
    "sg:city":"Santa Maria",
    "sg:classifiers":[
        {
            "category":"Farming",
            "subcategory":"Farm",
            "type":"Manufacturing & Wholesale Goods"
        }
    ],
    "sg:phone":"+1 805 922 8923",
    "sg:postcode":"93458",
    "sg:province":"CA",
    "sg:tags":[
        "crop",
        "general"
    ],
    "wof:name":"Body Cooling",
    "wof:placetype":"venue"
},
  "geometry": {"coordinates":[-120.450124,34.957992],"type":"Point"}
}