{
  "type": "Feature",
  "properties": {
    "iso:country":"US",
    "sg:address":"1218 Sam Ave",
    "sg:city":"Modesto",
    "sg:classifiers":[
        {
            "category":"Building & Trades",
            "subcategory":"Construction",
            "type":"Services"
        }
    ],
    "sg:phone":"+1 209 576 0735",
    "sg:postcode":"95351",
    "sg:province":"CA",
    "sg:tags":[
        "house"
    ],
    "wof:name":"Home Improvers",
    "wof:placetype":"venue"
},
  "geometry": {"coordinates":[-120.97696,37.614112],"type":"Point"}
}