{
  "type": "Feature",
  "properties": {
    "addr:full":"678 Poinsettia Park S Encinitas CA 92024",
    "addr:housenumber":"678",
    "addr:postcode":"92024",
    "addr:street":"Poinsettia Park S",
    "iso:country":"US",
    "sg:address":"678 Poinsettia Park S",
    "sg:city":"Encinitas",
    "sg:classifiers":[
        {
            "category":"Banks & Credit Unions",
            "subcategory":"Investment Brokerage",
            "type":"Services"
        }
    ],
    "sg:phone":"+1 760 634 3993",
    "sg:postcode":"92024",
    "sg:province":"CA",
    "sg:tags":[
        "consultant",
        "planning",
        "financial"
    ],
    "wof:name":"Educators Financial Planning",
    "wof:placetype":"venue"
},
  "geometry": {"coordinates":[-117.28814199999999,33.059818],"type":"Point"}
}