{
  "type": "Feature",
  "properties": {
    "addr:full":"315 Morro Bay Blvd Morro Bay CA 93442",
    "addr:housenumber":"315",
    "addr:postcode":"93442",
    "addr:street":"Morro Bay Blvd",
    "iso:country":"US",
    "sg:address":"315 Morro Bay Blvd",
    "sg:city":"Morro Bay",
    "sg:classifiers":[
        {
            "category":"Shopping",
            "subcategory":"Clothing, Apparel, & Fashions",
            "type":"Retail Goods"
        }
    ],
    "sg:phone":"+1 805 772 4288",
    "sg:postcode":"93442",
    "sg:province":"CA",
    "sg:tags":[
        "accessory"
    ],
    "wof:name":"Queen's Closet the",
    "wof:placetype":"venue"
},
  "geometry": {"coordinates":[-120.849998,35.3661],"type":"Point"}
}