{
  "type": "Feature",
  "properties": {
    "addr:full":"575 W Mathews Rd French Camp CA 95231",
    "addr:housenumber":"575",
    "addr:postcode":"95231",
    "addr:street":"W Mathews Rd",
    "iso:country":"US",
    "sg:address":"575 W Mathews Rd",
    "sg:city":"French Camp",
    "sg:classifiers":[
        {
            "category":"Social Services",
            "type":"Services"
        }
    ],
    "sg:phone":"+1 209 468 4068",
    "sg:postcode":"95231",
    "sg:province":"CA",
    "sg:tags":[
        "executive"
    ],
    "wof:name":"County Probation",
    "wof:placetype":"venue"
},
  "geometry": {"coordinates":[-121.28961200000001,37.882475],"type":"Point"}
}