{
  "type": "Feature",
  "properties": {
    "addr:full":"28067 Burrough Valley Rd Tollhouse CA 93667",
    "addr:postcode":"28067;93667",
    "addr:street":"Burrough Valley Rd",
    "iso:country":"US",
    "sg:address":"28067 Burrough Valley Rd",
    "sg:city":"Tollhouse",
    "sg:classifiers":[
        {
            "category":"Organizations",
            "subcategory":"Religious Organization",
            "type":"Services"
        }
    ],
    "sg:phone":"+1 559 855 2372",
    "sg:postcode":"93667",
    "sg:province":"CA",
    "sg:tags":[
        "church"
    ],
    "wof:name":"Burrough Valley Church",
    "wof:placetype":"venue"
},
  "geometry": {"coordinates":[-119.394525,36.979798],"type":"Point"}
}