{
  "type": "Feature",
  "properties": {
    "iso:country":"US",
    "sg:address":"4033 Judah St",
    "sg:city":"San Francisco",
    "sg:classifiers":[
        {
            "category":"Coffee & Tea",
            "type":"Food & Drink"
        }
    ],
    "sg:phone":"+1 415 682 4732",
    "sg:postcode":"94122",
    "sg:province":"CA",
    "sg:website":"www.troublecoffee.com",
    "wof:name":"Trouble Coffee Company",
    "wof:placetype":"venue"
},
  "geometry": {"coordinates":[-122.505458,37.76043],"type":"Point"}
}