{
  "type": "Feature",
  "properties": {
    "iso:country":"US",
    "sg:address":"8662 Lowmead Dr",
    "sg:city":"Huntington Beach",
    "sg:classifiers":[
        {
            "category":"Wholesale",
            "subcategory":"Machinery & Supplies",
            "type":"Manufacturing & Wholesale Goods"
        }
    ],
    "sg:phone":"+1 714 962 9996",
    "sg:postcode":"92646",
    "sg:province":"CA",
    "sg:tags":[
        "equipment"
    ],
    "wof:name":"O C Exchange Sales",
    "wof:placetype":"venue"
},
  "geometry": {"coordinates":[-117.97908700000001,33.672657],"type":"Point"}
}