{
  "type": "Feature",
  "properties": {
    "iso:country":"US",
    "sg:address":"6758 Los Verdes Dr",
    "sg:city":"Rancho Pls Vrds",
    "sg:classifiers":[
        {
            "category":"Real Estate",
            "subcategory":"Real Estate Operator",
            "type":"Services"
        }
    ],
    "sg:phone":"+1 310 377 5900",
    "sg:postcode":"90275",
    "sg:province":"CA",
    "sg:tags":[
        "apartment"
    ],
    "wof:name":"P V Victoria Apartments",
    "wof:placetype":"venue"
},
  "geometry": {"coordinates":[-118.39716799999999,33.75671],"type":"Point"}
}