{
  "type": "Feature",
  "properties": {
    "iso:country":"US",
    "sg:address":"11801 W Olympic Blvd",
    "sg:city":"Los Angeles",
    "sg:classifiers":[
        {
            "category":"Home & Garden",
            "subcategory":"Furniture",
            "type":"Retail Goods"
        }
    ],
    "sg:phone":"+1 310 473 4278",
    "sg:postcode":"90064",
    "sg:province":"CA",
    "sg:tags":[
        "mattress"
    ],
    "wof:name":"Select Comfort Corp",
    "wof:placetype":"venue"
},
  "geometry": {"coordinates":[-118.45372,34.032376],"type":"Point"}
}