{
  "type": "Feature",
  "properties": {
    "iso:country":"US",
    "sg:address":"420 S Grand Ave",
    "sg:city":"Los Angeles",
    "sg:classifiers":[
        {
            "category":"Professional",
            "subcategory":"Lawyer & Legal Services",
            "type":"Services"
        }
    ],
    "sg:phone":"+1 323 296 6771",
    "sg:postcode":"90071",
    "sg:province":"CA",
    "sg:tags":[
        "attorney"
    ],
    "wof:name":"Kimberly Lee",
    "wof:placetype":"venue"
},
  "geometry": {"coordinates":[-118.253076,34.050991],"type":"Point"}
}