{
  "type": "Feature",
  "properties": {
    "addr:full":"5108 Broadway Oakland CA 94611",
    "addr:housenumber":"5108",
    "addr:postcode":"94611",
    "addr:street":"Broadway",
    "iso:country":"US",
    "sg:address":"5108 Broadway",
    "sg:city":"Oakland",
    "sg:classifiers":[
        {
            "category":"Shopping",
            "subcategory":"Mobile Phones",
            "type":"Retail Goods"
        }
    ],
    "sg:phone":"+1 510 450 1940",
    "sg:postcode":"94611",
    "sg:province":"CA",
    "wof:name":"Sprint Pcs Personal Communication Services",
    "wof:placetype":"venue"
},
  "geometry": {"coordinates":[-122.251999,37.834801],"type":"Point"}
}