{
  "type": "Feature",
  "properties": {
    "iso:country":"US",
    "sg:address":"10623 International Blvd",
    "sg:city":"Oakland",
    "sg:classifiers":[
        {
            "category":"Manufacturing",
            "subcategory":"Jewelry",
            "type":"Manufacturing & Wholesale Goods"
        }
    ],
    "sg:phone":"+1 510 636 4008",
    "sg:postcode":"94603",
    "sg:province":"CA",
    "sg:tags":[
        "jewelers-wholesale",
        "manufacturer"
    ],
    "wof:name":"Gold Tooth Master",
    "wof:placetype":"venue"
},
  "geometry": {"coordinates":[-122.166,37.7383],"type":"Point"}
}