{
  "type": "Feature",
  "properties": {
    "iso:country":"US",
    "sg:address":"620 Buena Vista Dr",
    "sg:city":"Santa Rosa",
    "sg:classifiers":[
        {
            "category":"Professional",
            "subcategory":"Management & Consulting",
            "type":"Services"
        }
    ],
    "sg:phone":"+1 707 578 9371",
    "sg:postcode":"95404",
    "sg:province":"CA",
    "wof:name":"Soccer Elite",
    "wof:placetype":"venue"
},
  "geometry": {"coordinates":[-122.71577,38.469465],"type":"Point"}
}