{
  "type": "Feature",
  "properties": {
    "addr:full":"521 E Elder St Ste 206 Fallbrook CA 92028",
    "addr:housenumber":"521",
    "addr:postcode":"92028",
    "addr:street":"E Elder St Ste 206",
    "iso:country":"US",
    "sg:address":"521 E Elder St Ste 206",
    "sg:city":"Fallbrook",
    "sg:classifiers":[
        {
            "category":"Health Services",
            "subcategory":"Doctor",
            "type":"Services"
        }
    ],
    "sg:phone":"+1 760 728 5753",
    "sg:postcode":"92028",
    "sg:province":"CA",
    "sg:tags":[
        "medicine",
        "internal"
    ],
    "wof:name":"Fallbrook Medical Associates",
    "wof:placetype":"venue"
},
  "geometry": {"coordinates":[-117.246419,33.380042],"type":"Point"}
}