{
  "type": "Feature",
  "properties": {
    "iso:country":"US",
    "sg:address":"713 Eugene Rd",
    "sg:city":"Palm Springs",
    "sg:classifiers":[
        {
            "category":"Building & Trades",
            "subcategory":"Construction",
            "type":"Services"
        }
    ],
    "sg:phone":"+1 760 343 2783",
    "sg:postcode":"92264",
    "sg:province":"CA",
    "sg:tags":[
        "contractor"
    ],
    "wof:name":"Jerris Construction",
    "wof:placetype":"venue"
},
  "geometry": {"coordinates":[-116.494151,33.810737],"type":"Point"}
}