{
  "type": "Feature",
  "properties": {
    "iso:country":"US",
    "sg:address":"2182 E. Lincoln Ave.",
    "sg:city":"Anaheim",
    "sg:classifiers":[
        {
            "category":"Personal",
            "subcategory":"Hair Removal",
            "type":"Services"
        },
        {
            "category":"Personal",
            "subcategory":"Skin Care",
            "type":"Services"
        }
    ],
    "sg:phone":"+1 714 817 0443",
    "sg:postcode":"92806",
    "sg:province":"CA",
    "sg:tags":[
        "laser"
    ],
    "sg:website":"www.precisionlaserskin.com",
    "wof:name":"Precision Laser Skin Care",
    "wof:placetype":"venue"
},
  "geometry": {"coordinates":[-117.886067,33.839396],"type":"Point"}
}