{
  "type": "Feature",
  "properties": {
    "addr:full":"515 N Michillinda Ave Pasadena CA 91107",
    "addr:housenumber":"515",
    "addr:postcode":"91107",
    "addr:street":"N Michillinda Ave",
    "iso:country":"US",
    "sg:address":"515 N Michillinda Ave",
    "sg:city":"Pasadena",
    "sg:classifiers":[
        {
            "category":"Professional",
            "type":"Services"
        }
    ],
    "sg:phone":"+1 626 351 6810",
    "sg:postcode":"91107",
    "sg:province":"CA",
    "wof:name":"Albino C Valenzuela",
    "wof:placetype":"venue"
},
  "geometry": {"coordinates":[-118.067981,34.153733],"type":"Point"}
}