{
  "type": "Feature",
  "properties": {
    "addr:full":"13126 S Broadway Los Angeles CA 90061",
    "addr:housenumber":"13126",
    "addr:postcode":"90061",
    "addr:street":"S Broadway",
    "iso:country":"US",
    "sg:address":"13126 S Broadway",
    "sg:city":"Los Angeles",
    "sg:classifiers":[
        {
            "category":"Freight",
            "type":"Transportation"
        }
    ],
    "sg:phone":"+1 310 516 6099",
    "sg:postcode":"90061",
    "sg:province":"CA",
    "sg:tags":[
        "brokerage",
        "customs"
    ],
    "wof:name":"Preferred LSI Inc",
    "wof:placetype":"venue"
},
  "geometry": {"coordinates":[-118.278262,33.912579],"type":"Point"}
}