{
  "type": "Feature",
  "properties": {
    "addr:full":"280 S Abel St Milpitas CA 95035",
    "addr:housenumber":"280",
    "addr:postcode":"95035",
    "addr:street":"S Abel St",
    "iso:country":"US",
    "sg:address":"280 S Abel St",
    "sg:city":"Milpitas",
    "sg:classifiers":[
        {
            "category":"Personal",
            "subcategory":"Skin Care",
            "type":"Services"
        }
    ],
    "sg:phone":"+1 408 781 5288",
    "sg:postcode":"95035",
    "sg:province":"CA",
    "wof:name":"Kathy's Skincare",
    "wof:placetype":"venue"
},
  "geometry": {"coordinates":[-121.90818299999999,37.427382],"type":"Point"}
}