{
  "type": "Feature",
  "properties": {
    "addr:full":"420 Aviation Blvd Santa Rosa CA 95403",
    "addr:housenumber":"420",
    "addr:postcode":"95403",
    "addr:street":"Aviation Blvd",
    "iso:country":"US",
    "sg:address":"420 Aviation Blvd",
    "sg:city":"Santa Rosa",
    "sg:classifiers":[
        {
            "category":"Professional",
            "subcategory":"Lawyer & Legal Services",
            "type":"Services"
        }
    ],
    "sg:phone":"+1 707 543 4900",
    "sg:postcode":"95403",
    "sg:province":"CA",
    "sg:tags":[
        "attorney"
    ],
    "sg:website":"www.fogzlaw.com",
    "wof:name":"Friedemann O'Brien Goldberg",
    "wof:placetype":"venue"
},
  "geometry": {"coordinates":[-122.78706699999999,38.515045],"type":"Point"}
}