{
  "type": "Feature",
  "properties": {
    "iso:country":"US",
    "sg:address":"7770 Firenze Ave",
    "sg:city":"Los Angeles",
    "sg:classifiers":[
        {
            "category":"Building & Trades",
            "subcategory":"Landscaping Services",
            "type":"Services"
        }
    ],
    "sg:phone":"+1 323 851 1198",
    "sg:postcode":"90046",
    "sg:province":"CA",
    "wof:name":"Humphrey Tree Co",
    "wof:placetype":"venue"
},
  "geometry": {"coordinates":[-118.36524300000001,34.122587],"type":"Point"}
}