{
  "type": "Feature",
  "properties": {
    "addr:full":"1237 S Euclid St Anaheim CA 92802",
    "addr:housenumber":"1237",
    "addr:postcode":"92802",
    "addr:street":"S Euclid St",
    "iso:country":"US",
    "sg:address":"1237 S Euclid St",
    "sg:city":"Anaheim",
    "sg:classifiers":[
        {
            "category":"Travel",
            "subcategory":"Travel Agent",
            "type":"Entertainment"
        }
    ],
    "sg:phone":"+1 714 758 3783",
    "sg:postcode":"92802",
    "sg:province":"CA",
    "sg:tags":[
        "agency"
    ],
    "wof:name":"Rainbow Travel",
    "wof:placetype":"venue"
},
  "geometry": {"coordinates":[-117.94149,33.817128],"type":"Point"}
}