{
  "type": "Feature",
  "properties": {
    "iso:country":"US",
    "sg:address":"410 Main St",
    "sg:city":"Trinidad",
    "sg:phone":"+1 707 677 3223",
    "sg:postcode":"95570",
    "sg:province":"CA",
    "wof:name":"The Sea Around Us",
    "wof:placetype":"venue"
},
  "geometry": {"coordinates":[-124.140935,41.061353],"type":"Point"}
}