{
  "type": "Feature",
  "properties": {
    "addr:full":"410 Main St Trinidad CA 95570",
    "addr:housenumber":"410",
    "addr:postcode":"95570",
    "addr:street":"Main St",
    "iso:country":"US",
    "sg:address":"410 Main St",
    "sg:city":"Trinidad",
    "sg:phone":"+1 707 677 3223",
    "sg:postcode":"95570",
    "sg:province":"CA",
    "wof:name":"The Sea Around Us",
    "wof:placetype":"venue"
},
  "geometry": {"coordinates":[-124.140935,41.061353],"type":"Point"}
}