{
  "type": "Feature",
  "properties": {
    "addr:full":"310 Rose Ave Danville CA 94526",
    "addr:housenumber":"310",
    "addr:postcode":"94526",
    "addr:street":"Rose Ave",
    "iso:country":"US",
    "sg:address":"310 Rose Ave",
    "sg:city":"Danville",
    "sg:classifiers":[
        {
            "category":"Personal",
            "subcategory":"Beauty Salon",
            "type":"Services"
        }
    ],
    "sg:phone":"+1 925 820 2441",
    "sg:postcode":"94526",
    "sg:province":"CA",
    "wof:name":"Abby Rose Salon",
    "wof:placetype":"venue"
},
  "geometry": {"coordinates":[-122.00122399999999,37.824165],"type":"Point"}
}