{
  "type": "Feature",
  "properties": {
    "addr:full":"14260 E Nelson Ave City Of Industry CA 91744",
    "addr:housenumber":"14260",
    "addr:postcode":"91744",
    "addr:street":"E Nelson Ave",
    "iso:country":"US",
    "sg:address":"14260 E Nelson Ave",
    "sg:city":"City Of Industry",
    "sg:classifiers":[
        {
            "category":"Food & Beverages",
            "subcategory":"Bakery",
            "type":"Retail Goods"
        }
    ],
    "sg:phone":"+1 626 330 9895",
    "sg:postcode":"91744",
    "sg:province":"CA",
    "sg:tags":[
        "baker"
    ],
    "wof:name":"LA Flor De Michuacan",
    "wof:placetype":"venue"
},
  "geometry": {"coordinates":[-117.977412,34.04082],"type":"Point"}
}