{
  "type": "Feature",
  "properties": {
    "addr:full":"2288 Westwood Blvd Los Angeles CA 90064",
    "addr:housenumber":"2288",
    "addr:postcode":"90064",
    "addr:street":"Westwood Blvd",
    "iso:country":"US",
    "sg:address":"2288 Westwood Blvd",
    "sg:city":"Los Angeles",
    "sg:classifiers":[
        {
            "category":"Building & Trades",
            "subcategory":"Construction",
            "type":"Services"
        }
    ],
    "sg:phone":"+1 310 475 2920",
    "sg:postcode":"90064",
    "sg:province":"CA",
    "sg:tags":[
        "general",
        "contractor"
    ],
    "wof:name":"Bima Construction",
    "wof:placetype":"venue"
},
  "geometry": {"coordinates":[-118.43134499999999,34.043772],"type":"Point"}
}