{
  "type": "Feature",
  "properties": {
    "iso:country":"US",
    "sg:address":"8800 East Rd",
    "sg:city":"Redwood Valley",
    "sg:classifiers":[
        {
            "category":"Freight",
            "type":"Transportation"
        }
    ],
    "sg:phone":"+1 707 485 8766",
    "sg:postcode":"95470",
    "sg:province":"CA",
    "sg:tags":[
        "warehouse",
        "self",
        "storage"
    ],
    "wof:name":"Redwood Valley Ind Park",
    "wof:placetype":"venue"
},
  "geometry": {"coordinates":[-123.205325,39.269861],"type":"Point"}
}