{
  "type": "Feature",
  "properties": {
    "addr:full":"2502 Telegraph Ave Berkeley CA 94704",
    "addr:housenumber":"2502",
    "addr:postcode":"94704",
    "addr:street":"Telegraph Ave",
    "iso:country":"US",
    "sg:address":"2502 Telegraph Ave",
    "sg:city":"Berkeley",
    "sg:classifiers":[
        {
            "category":"Restaurant",
            "type":"Food & Drink"
        }
    ],
    "sg:phone":"+1 510 665 1900",
    "sg:postcode":"94704",
    "sg:province":"CA",
    "sg:tags":[
        "breakfast",
        "pizza",
        "brunch",
        "italian"
    ],
    "sg:website":"www.milanesecafe.com",
    "wof:name":"Milanese Caffe",
    "wof:placetype":"venue"
},
  "geometry": {"coordinates":[-122.258865,37.865035],"type":"Point"}
}