{
  "type": "Feature",
  "properties": {
    "addr:full":"2513 185th Street Redondo Beach CA 90278",
    "addr:housenumber":"2513",
    "addr:postcode":"90278",
    "addr:street":"185Th Street",
    "iso:country":"US",
    "sg:address":"2513 185th Street",
    "sg:city":"Redondo Beach",
    "sg:classifiers":[
        {
            "category":"Building & Trades",
            "subcategory":"Construction",
            "type":"Services"
        }
    ],
    "sg:phone":"+1 310 376 8790",
    "sg:postcode":"90278",
    "sg:province":"CA",
    "sg:tags":[
        "contractor"
    ],
    "wof:name":"Wachtfogel Construction Company",
    "wof:placetype":"venue"
},
  "geometry": {"coordinates":[-118.364575,33.862785],"type":"Point"}
}