{
  "type": "Feature",
  "properties": {
    "iso:country":"US",
    "sg:address":"26068 Twain Pl",
    "sg:city":"Stevenson Ranch",
    "sg:classifiers":[
        {
            "category":"Shopping",
            "subcategory":"Computers & Home Electronics",
            "type":"Retail Goods"
        }
    ],
    "sg:phone":"+1 661 373 8369",
    "sg:postcode":"91381",
    "sg:province":"CA",
    "wof:name":"Mkautoelite Co",
    "wof:placetype":"venue"
},
  "geometry": {"coordinates":[-118.59056200000001,34.393121],"type":"Point"}
}