{
  "type": "Feature",
  "properties": {
    "iso:country":"US",
    "sg:address":"922 S Lyon St",
    "sg:city":"Santa Ana",
    "sg:classifiers":[
        {
            "category":"Personal",
            "type":"Services"
        }
    ],
    "sg:phone":"+1 714 542 7775",
    "sg:postcode":"92705",
    "sg:province":"CA",
    "sg:tags":[
        "party",
        "planning",
        "event"
    ],
    "sg:website":"www.confettipartyrentals.net",
    "wof:name":"Confetti Party Rentals",
    "wof:placetype":"venue"
},
  "geometry": {"coordinates":[-117.84507499999999,33.736796],"type":"Point"}
}