{
  "type": "Feature",
  "properties": {
    "addr:full":"1520 Rose Garden Ct Modesto CA 95356",
    "addr:housenumber":"1520",
    "addr:postcode":"ca 95356",
    "addr:street":"Rose Garden Ct",
    "iso:country":"US",
    "sg:address":"1520 Rose Garden Ct",
    "sg:city":"Modesto",
    "sg:classifiers":[
        {
            "category":"Building & Trades",
            "subcategory":"Landscaping Services",
            "type":"Services"
        }
    ],
    "sg:phone":"+1 209 525 8893",
    "sg:postcode":"95356",
    "sg:province":"CA",
    "wof:name":"Huynh Gardening",
    "wof:placetype":"venue"
},
  "geometry": {"coordinates":[-121.019784,37.699715],"type":"Point"}
}