{
  "type": "Feature",
  "properties": {
    "addr:full":"1462 Glendale Blvd Los Angeles CA 90026",
    "addr:housenumber":"1462",
    "addr:postcode":"90026",
    "addr:street":"Glendale Blvd",
    "iso:country":"US",
    "sg:address":"1462 Glendale Blvd",
    "sg:city":"Los Angeles",
    "sg:classifiers":[
        {
            "category":"Autos & Motor Vehicles",
            "subcategory":"Auto Supplies",
            "type":"Retail Goods"
        }
    ],
    "sg:phone":"+1 213 413 5449",
    "sg:postcode":"90026",
    "sg:province":"CA",
    "sg:tags":[
        "part"
    ],
    "wof:name":"Caye's Auto Parts Distribution",
    "wof:placetype":"venue"
},
  "geometry": {"coordinates":[-118.259953,34.081484],"type":"Point"}
}