{
  "type": "Feature",
  "properties": {
    "iso:country":"US",
    "sg:address":"8712 Smith Rd",
    "sg:city":"Bakersfield",
    "sg:classifiers":[
        {
            "category":"Farming",
            "subcategory":"Farm & Veterinary Services",
            "type":"Manufacturing & Wholesale Goods"
        }
    ],
    "sg:phone":"+1 661 366 7618",
    "sg:postcode":"93307",
    "sg:province":"CA",
    "sg:tags":[
        "crop",
        "harvesting"
    ],
    "wof:name":"Farming & Harvesting",
    "wof:placetype":"venue"
},
  "geometry": {"coordinates":[-118.909269,35.342532],"type":"Point"}
}