{
  "type": "Feature",
  "properties": {
    "addr:full":"8712 Smith Rd Bakersfield CA 93307",
    "addr:housenumber":"8712",
    "addr:postcode":"93307",
    "addr:street":"Smith Rd",
    "iso:country":"US",
    "sg:address":"8712 Smith Rd",
    "sg:city":"Bakersfield",
    "sg:classifiers":[
        {
            "category":"Farming",
            "subcategory":"Farm & Veterinary Services",
            "type":"Manufacturing & Wholesale Goods"
        }
    ],
    "sg:phone":"+1 661 366 7618",
    "sg:postcode":"93307",
    "sg:province":"CA",
    "sg:tags":[
        "crop",
        "harvesting"
    ],
    "wof:name":"Farming & Harvesting",
    "wof:placetype":"venue"
},
  "geometry": {"coordinates":[-118.90926899999999,35.342532],"type":"Point"}
}