{
  "type": "Feature",
  "properties": {
    "addr:full":"9301 La Rosa Dr Temple City CA 91780",
    "addr:housenumber":"9301",
    "addr:postcode":"91780",
    "addr:street":"La Rosa Dr",
    "iso:country":"US",
    "sg:address":"9301 La Rosa Dr",
    "sg:city":"Temple City",
    "sg:classifiers":[
        {
            "category":"Education",
            "subcategory":"School",
            "type":"Public Place"
        }
    ],
    "sg:phone":"+1 626 309 2805",
    "sg:postcode":"91780",
    "sg:province":"CA",
    "sg:tags":[
        "high",
        "middle",
        "elementary"
    ],
    "wof:name":"Temple City Chinese School Arcadia Chinese School",
    "wof:placetype":"venue"
},
  "geometry": {"coordinates":[-118.06500200000001,34.092999],"type":"Point"}
}