{
  "type": "Feature",
  "properties": {
    "iso:country":"US",
    "sg:address":"7510 W Sunset Blvd Ste 505",
    "sg:city":"Los Angeles",
    "sg:classifiers":[
        {
            "category":"Professional",
            "subcategory":"Printing & Photocopies",
            "type":"Services"
        }
    ],
    "sg:phone":"+1 888 649 1995",
    "sg:postcode":"90046",
    "sg:province":"CA",
    "sg:website":"unifiedmanufacturing.com/",
    "wof:name":"Unified Manufacturing",
    "wof:placetype":"venue"
},
  "geometry": {"coordinates":[-118.353283,34.097887],"type":"Point"}
}