{
  "type": "Feature",
  "properties": {
    "iso:country":"US",
    "sg:address":"1129 San Julian Street",
    "sg:city":"Los Angeles",
    "sg:classifiers":[
        {
            "category":"Shopping",
            "subcategory":"Clothing, Apparel, & Fashions",
            "type":"Retail Goods"
        }
    ],
    "sg:phone":"+1 213 745 6005",
    "sg:postcode":"90015",
    "sg:province":"CA",
    "sg:tags":[
        "clothing",
        "women's"
    ],
    "wof:name":"Beleza Fashion",
    "wof:placetype":"venue"
},
  "geometry": {"coordinates":[-118.253503,34.035438],"type":"Point"}
}