{
  "type": "Feature",
  "properties": {
    "addr:full":"220 W Ivy Ave Inglewood CA 90302",
    "addr:housenumber":"220",
    "addr:postcode":"90302",
    "addr:street":"W Ivy Ave",
    "iso:country":"US",
    "sg:address":"220 W Ivy Ave",
    "sg:city":"Inglewood",
    "sg:classifiers":[
        {
            "category":"Freight",
            "type":"Transportation"
        }
    ],
    "sg:phone":"+1 310 680 2013",
    "sg:postcode":"90302",
    "sg:province":"CA",
    "wof:name":"Planet Cargo Inc",
    "wof:placetype":"venue"
},
  "geometry": {"coordinates":[-118.356098,33.966562],"type":"Point"}
}