{
  "type": "Feature",
  "properties": {
    "iso:country":"US",
    "sg:address":"8520 Santa Rita Grade",
    "sg:city":"Dos Palos",
    "sg:classifiers":[
        {
            "category":"Retail",
            "subcategory":"Repair Shop",
            "type":"Services"
        }
    ],
    "sg:phone":"+1 209 387 4676",
    "sg:postcode":"93620",
    "sg:province":"CA",
    "sg:tags":[
        "upholsterer"
    ],
    "wof:name":"Pinto Upholstery",
    "wof:placetype":"venue"
},
  "geometry": {"coordinates":[-120.640434,37.054437],"type":"Point"}
}