{
  "type": "Feature",
  "properties": {
    "iso:country":"US",
    "sg:address":"412 Red Hill Ave",
    "sg:city":"San Anselmo",
    "sg:classifiers":[
        {
            "category":"Social Services",
            "type":"Services"
        }
    ],
    "sg:phone":"+1 415 459 3342",
    "sg:postcode":"94960",
    "sg:province":"CA",
    "sg:tags":[
        "worker"
    ],
    "wof:name":"Lois Lane",
    "wof:placetype":"venue"
},
  "geometry": {"coordinates":[-122.558874,37.976638],"type":"Point"}
}