{
  "type": "Feature",
  "properties": {
    "addr:full":"1625 Pacific Ave Oxnard CA 93033",
    "addr:housenumber":"1625",
    "addr:postcode":"93033",
    "addr:street":"Pacific Ave",
    "iso:country":"US",
    "sg:address":"1625 Pacific Ave",
    "sg:city":"Oxnard",
    "sg:classifiers":[
        {
            "category":"Wholesale",
            "subcategory":"Non-durable Goods",
            "type":"Manufacturing & Wholesale Goods"
        }
    ],
    "sg:phone":"+1 805 483 5754",
    "sg:postcode":"93033",
    "sg:province":"CA",
    "wof:name":"Way Stoked Enterprises",
    "wof:placetype":"venue"
},
  "geometry": {"coordinates":[-119.165222,34.18387],"type":"Point"}
}