{
  "type": "Feature",
  "properties": {
    "iso:country":"US",
    "sg:address":"576 E Santa Clara St",
    "sg:city":"San Jose",
    "sg:classifiers":[
        {
            "category":"Restaurant",
            "type":"Food & Drink"
        }
    ],
    "sg:postcode":"95112",
    "sg:province":"CA",
    "sg:tags":[
        "pizza"
    ],
    "sg:website":"www.dominos.com/",
    "wof:name":"Domino's Pizza",
    "wof:placetype":"venue"
},
  "geometry": {"coordinates":[-121.878451,37.341778],"type":"Point"}
}