{
  "type": "Feature",
  "properties": {
    "iso:country":"US",
    "sg:address":"146 Flynn Ave",
    "sg:city":"Mountain View",
    "sg:classifiers":[
        {
            "category":"Professional",
            "type":"Services"
        }
    ],
    "sg:phone":"+1 650 960 3729",
    "sg:postcode":"94043",
    "sg:province":"CA",
    "sg:tags":[
        "establishment"
    ],
    "wof:name":"Techxpertise",
    "wof:placetype":"venue"
},
  "geometry": {"coordinates":[-122.06176000000001,37.399117],"type":"Point"}
}