{
  "type": "Feature",
  "properties": {
    "iso:country":"US",
    "sg:address":"3524 Burritt Way",
    "sg:city":"La Crescenta",
    "sg:classifiers":[
        {
            "category":"Professional",
            "type":"Services"
        }
    ],
    "sg:phone":"+1 818 248 5478",
    "sg:postcode":"91214",
    "sg:province":"CA",
    "wof:name":"Pierot of California Inc",
    "wof:placetype":"venue"
},
  "geometry": {"coordinates":[-118.256817,34.243555],"type":"Point"}
}