{
  "type": "Feature",
  "properties": {
    "iso:country":"US",
    "sg:address":"1846 Story Rd",
    "sg:city":"San Jose",
    "sg:classifiers":[
        {
            "category":"Food & Beverages",
            "subcategory":"Groceries & Convenience Stores",
            "type":"Retail Goods"
        }
    ],
    "sg:phone":"+1 408 649 6339",
    "sg:postcode":"95122",
    "sg:province":"CA",
    "wof:name":"Twenty Four Market",
    "wof:placetype":"venue"
},
  "geometry": {"coordinates":[-121.840613,37.341349],"type":"Point"}
}