{
  "type": "Feature",
  "properties": {
    "addr:full":"8555 W Sunset Boulevard West Hollywood CA 90069",
    "addr:housenumber":"8555",
    "addr:postcode":"90069",
    "addr:street":"W Sunset Boulevard",
    "iso:country":"US",
    "sg:address":"8555 W Sunset Boulevard",
    "sg:city":"West Hollywood",
    "sg:classifiers":[
        {
            "category":"Shopping",
            "subcategory":"Clothing, Apparel, & Fashions",
            "type":"Retail Goods"
        }
    ],
    "sg:phone":"+1 310 659 9880",
    "sg:postcode":"90069",
    "sg:province":"CA",
    "sg:tags":[
        "accessory",
        "clothing",
        "women's"
    ],
    "wof:name":"McNair Linda Fine Fashions",
    "wof:placetype":"venue"
},
  "geometry": {"coordinates":[-118.37804300000001,34.093289],"type":"Point"}
}