{
  "type": "Feature",
  "properties": {
    "iso:country":"US",
    "sg:address":"14522 Vanowen St Ste 8",
    "sg:city":"Van Nuys",
    "sg:classifiers":[
        {
            "category":"Retail",
            "subcategory":"Laundry & Dry Cleaning",
            "type":"Services"
        }
    ],
    "sg:phone":"+1 818 901 7314",
    "sg:postcode":"91405",
    "sg:province":"CA",
    "wof:name":"Budget Cleaners",
    "wof:placetype":"venue"
},
  "geometry": {"coordinates":[-118.44899700000001,34.193901],"type":"Point"}
}