{
  "type": "Feature",
  "properties": {
    "addr:full":"72 el Toyonal Orinda CA 94563",
    "addr:housenumber":"72",
    "addr:postcode":"94563",
    "addr:street":"El Toyonal",
    "iso:country":"US",
    "sg:address":"72 el Toyonal",
    "sg:city":"Orinda",
    "sg:classifiers":[
        {
            "category":"Recreation",
            "type":"Entertainment"
        }
    ],
    "sg:phone":"+1 925 254 5988",
    "sg:postcode":"94563",
    "sg:province":"CA",
    "sg:tags":[
        "pool",
        "swimming"
    ],
    "wof:name":"Orinda Park Pool",
    "wof:placetype":"venue"
},
  "geometry": {"coordinates":[-122.19667099999999,37.886098],"type":"Point"}
}