{
  "type": "Feature",
  "properties": {
    "addr:full":"13900 Palm Dr Desert Hot Springs CA 92240",
    "addr:housenumber":"13900",
    "addr:postcode":"92240",
    "addr:street":"Palm Dr",
    "iso:country":"US",
    "sg:address":"13900 Palm Dr",
    "sg:city":"Desert Hot Springs",
    "sg:classifiers":[
        {
            "category":"Restaurant",
            "type":"Food & Drink"
        }
    ],
    "sg:menulink":"http://www.allmenus.com/ca/desert-hot-springs/74048-dominos-pizza/menu/",
    "sg:phone":"+1 760 251 1444",
    "sg:postcode":"92240",
    "sg:province":"CA",
    "sg:tags":[
        "american",
        "wing",
        "pizza"
    ],
    "wof:name":"Domino's Pizza",
    "wof:placetype":"venue"
},
  "geometry": {"coordinates":[-116.500872,33.947525],"type":"Point"}
}