{
  "type": "Feature",
  "properties": {
    "addr:full":"1221 Nevin Ave Fl 4 Richmond CA 94801",
    "addr:housenumber":"1221;4",
    "addr:postcode":"94801",
    "addr:street":"Nevin Ave Fl",
    "iso:country":"US",
    "sg:address":"1221 Nevin Ave Fl 4",
    "sg:city":"Richmond",
    "sg:classifiers":[
        {
            "category":"Social Services",
            "type":"Services"
        }
    ],
    "sg:phone":"+1 510 970 1581",
    "sg:postcode":"94801",
    "sg:province":"CA",
    "sg:tags":[
        "consultant",
        "security",
        "representative"
    ],
    "sg:website":"http://www.ssa.gov",
    "wof:name":"Disability Processing Branch",
    "wof:placetype":"venue"
},
  "geometry": {"coordinates":[-122.35788599999999,37.936812],"type":"Point"}
}