{
  "type": "Feature",
  "properties": {
    "iso:country":"US",
    "sg:address":"7028 Greenleaf Ave # E",
    "sg:city":"Whittier",
    "sg:classifiers":[
        {
            "category":"Personal",
            "subcategory":"Beauty Salon",
            "type":"Services"
        }
    ],
    "sg:phone":"+1 562 693 4994",
    "sg:postcode":"90602",
    "sg:province":"CA",
    "sg:tags":[
        "hair",
        "stylist"
    ],
    "wof:name":"Hair By Jamie",
    "wof:placetype":"venue"
},
  "geometry": {"coordinates":[-118.037376,33.978568],"type":"Point"}
}