{
  "type": "Feature",
  "properties": {
    "iso:country":"US",
    "sg:address":"1112 C St",
    "sg:city":"Sacramento",
    "sg:classifiers":[
        {
            "category":"Sports & Exercise",
            "subcategory":"Swimming Pool",
            "type":"Entertainment"
        }
    ],
    "sg:phone":"+1 916 442 1826",
    "sg:postcode":"95814",
    "sg:province":"CA",
    "sg:tags":[
        "diving",
        "instruction"
    ],
    "wof:name":"Dive Guys Scuba School",
    "wof:placetype":"venue"
},
  "geometry": {"coordinates":[-121.48864399999999,38.587564],"type":"Point"}
}