{
  "type": "Feature",
  "properties": {
    "iso:country":"US",
    "sg:address":"8448 S Gate Ave",
    "sg:city":"South Gate",
    "sg:classifiers":[
        {
            "category":"Home & Garden",
            "subcategory":"Building Materials",
            "type":"Retail Goods"
        }
    ],
    "sg:phone":"+1 323 249 6237",
    "sg:postcode":"90280",
    "sg:province":"CA",
    "sg:tags":[
        "glass",
        "window",
        "plate"
    ],
    "wof:name":"Princess Windows",
    "wof:placetype":"venue"
},
  "geometry": {"coordinates":[-118.21368,33.959924],"type":"Point"}
}