{
  "type": "Feature",
  "properties": {
    "addr:full":"467 N Moorpark Rd Thousand Oaks CA 91360",
    "addr:housenumber":"467",
    "addr:postcode":"91360",
    "addr:street":"N Moorpark Rd",
    "iso:country":"US",
    "sg:address":"467 N Moorpark Rd",
    "sg:city":"Thousand Oaks",
    "sg:classifiers":[
        {
            "category":"Retail",
            "subcategory":"Car Wash",
            "type":"Services"
        }
    ],
    "sg:phone":"+1 805 379 4900",
    "sg:postcode":"91360",
    "sg:province":"CA",
    "sg:tags":[
        "carwash"
    ],
    "sg:website":"www.washdepot.com",
    "wof:name":"Simoniz Janss Mall Car Wash",
    "wof:placetype":"venue"
},
  "geometry": {"coordinates":[-118.875085,34.185678],"type":"Point"}
}