{
  "type": "Feature",
  "properties": {
    "addr:full":"3079 Kilgore Rd Rancho Cordova CA 95670",
    "addr:housenumber":"3079",
    "addr:postcode":"95670",
    "addr:street":"Kilgore Rd",
    "iso:country":"US",
    "sg:address":"3079 Kilgore Rd",
    "sg:city":"Rancho Cordova",
    "sg:classifiers":[
        {
            "category":"Professional",
            "subcategory":"Accounting & Tax Preparation",
            "type":"Services"
        }
    ],
    "sg:phone":"+1 916 266 4454",
    "sg:postcode":"95670",
    "sg:province":"CA",
    "sg:tags":[
        "accountant"
    ],
    "wof:name":"Professional Solutions Group",
    "wof:placetype":"venue"
},
  "geometry": {"coordinates":[-121.27059300000001,38.594167],"type":"Point"}
}