{
  "type": "Feature",
  "properties": {
    "iso:country":"US",
    "sg:address":"44814, South Grimmer Blvd",
    "sg:city":"Fremont",
    "sg:classifiers":[
        {
            "category":"Professional",
            "subcategory":"Computer Services",
            "type":"Services"
        }
    ],
    "sg:phone":"+1 510 894 6651",
    "sg:postcode":"94538",
    "sg:province":"CA",
    "sg:tags":[
        "social-media",
        "facebook-applications",
        "development",
        "consulting",
        "iphone-applications",
        "facebook-pages",
        "fan-pages",
        "twitter-applications",
        "custom-development"
    ],
    "sg:website":"http://www.cygnismedia.com",
    "wof:name":"Cygnis Media",
    "wof:placetype":"venue"
},
  "geometry": {"coordinates":[-121.947063,37.503046],"type":"Point"}
}