{
  "type": "Feature",
  "properties": {
    "addr:full":"8927 Salmon Falls Dr Sacramento CA 95826",
    "addr:housenumber":"8927",
    "addr:postcode":"95826",
    "addr:street":"Salmon Falls Dr",
    "iso:country":"US",
    "sg:address":"8927 Salmon Falls Dr",
    "sg:city":"Sacramento",
    "sg:classifiers":[
        {
            "category":"Shopping",
            "subcategory":"Gifts & Souvenirs",
            "type":"Retail Goods"
        }
    ],
    "sg:phone":"+1 916 825 9309",
    "sg:postcode":"95826",
    "sg:province":"CA",
    "sg:tags":[
        "shop"
    ],
    "wof:name":"Jeannies Second Hand Treasures",
    "wof:placetype":"venue"
},
  "geometry": {"coordinates":[-121.37308299999999,38.561218],"type":"Point"}
}