{
  "type": "Feature",
  "properties": {
    "iso:country":"US",
    "sg:address":"972 Mission St",
    "sg:city":"San Francisco",
    "sg:classifiers":[
        {
            "category":"Government",
            "subcategory":"Office",
            "type":"Public Place"
        }
    ],
    "sg:phone":"+1 415 546 1155",
    "sg:postcode":"94103",
    "sg:province":"CA",
    "sg:tags":[
        "federal",
        "affairs"
    ],
    "wof:name":"Jordan Consulate",
    "wof:placetype":"venue"
},
  "geometry": {"coordinates":[-122.408052,37.781733],"type":"Point"}
}