{
  "type": "Feature",
  "properties": {
    "addr:full":"5621 Highland Rd Pleasanton CA 94588",
    "addr:housenumber":"5621",
    "addr:postcode":"94588",
    "addr:street":"Highland Rd",
    "iso:country":"US",
    "sg:address":"5621 Highland Rd",
    "sg:city":"Pleasanton",
    "sg:classifiers":[
        {
            "category":"Retail",
            "subcategory":"Animal Services",
            "type":"Services"
        }
    ],
    "sg:phone":"+1 925 248 6009",
    "sg:postcode":"94588",
    "sg:province":"CA",
    "wof:name":"Lomoli Farms",
    "wof:placetype":"venue"
},
  "geometry": {"coordinates":[-121.85861300000001,37.776198],"type":"Point"}
}