{
  "type": "Feature",
  "properties": {
    "addr:full":"15262 Pipeline Ln Huntington Beach CA 92649",
    "addr:housenumber":"15262",
    "addr:postcode":"92649",
    "addr:street":"Pipeline Ln",
    "iso:country":"US",
    "sg:address":"15262 Pipeline Ln",
    "sg:city":"Huntington Beach",
    "sg:classifiers":[
        {
            "category":"Wholesale",
            "subcategory":"Non-durable Goods",
            "type":"Manufacturing & Wholesale Goods"
        }
    ],
    "sg:phone":"+1 714 898 2400",
    "sg:postcode":"92649",
    "sg:province":"CA",
    "sg:tags":[
        "calendar"
    ],
    "sg:website":"www.avalanchepub.com",
    "wof:name":"Avalanche Publishing Inc",
    "wof:placetype":"venue"
},
  "geometry": {"coordinates":[-118.028402,33.741212],"type":"Point"}
}