{
  "type": "Feature",
  "properties": {
    "addr:full":"18555 Butterfield Blvd Morgan Hill CA 95037",
    "addr:housenumber":"18555",
    "addr:postcode":"95037",
    "addr:street":"Butterfield Blvd",
    "iso:country":"US",
    "sg:address":"18555 Butterfield Blvd",
    "sg:city":"Morgan Hill",
    "sg:classifiers":[
        {
            "category":"Social Services",
            "type":"Services"
        }
    ],
    "sg:phone":"+1 408 778 2930",
    "sg:postcode":"95037",
    "sg:province":"CA",
    "sg:tags":[
        "counseling"
    ],
    "wof:name":"4 C Counsel",
    "wof:placetype":"venue"
},
  "geometry": {"coordinates":[-121.657098,37.142308],"type":"Point"}
}