{
  "type": "Feature",
  "properties": {
    "addr:full":"5560 Van Nuys Blvd Sherman Oaks CA 91401",
    "addr:housenumber":"5560",
    "addr:postcode":"91401",
    "addr:street":"Van Nuys Blvd",
    "iso:country":"US",
    "sg:address":"5560 Van Nuys Blvd",
    "sg:city":"Sherman Oaks",
    "sg:classifiers":[
        {
            "category":"Autos & Motor Vehicles",
            "subcategory":"Fuel & Gas Station",
            "type":"Retail Goods"
        }
    ],
    "sg:phone":"+1 818 781 7157",
    "sg:postcode":"91401",
    "sg:province":"CA",
    "sg:tags":[
        "repair",
        "oil"
    ],
    "sg:website":"www.mobil.com",
    "wof:name":"Chris's Mobil",
    "wof:placetype":"venue"
},
  "geometry": {"coordinates":[-118.44899700000001,34.171799],"type":"Point"}
}