{
  "type": "Feature",
  "properties": {
    "iso:country":"US",
    "sg:address":"5405 Morehouse Dr",
    "sg:city":"San Diego",
    "sg:classifiers":[
        {
            "category":"Professional",
            "subcategory":"Engineering",
            "type":"Services"
        }
    ],
    "sg:phone":"+1 858 453 9866",
    "sg:postcode":"92121",
    "sg:province":"CA",
    "sg:tags":[
        "general",
        "contractor"
    ],
    "wof:name":"Summit Design Technologies",
    "wof:placetype":"venue"
},
  "geometry": {"coordinates":[-117.195274,32.897445],"type":"Point"}
}