{
  "type": "Feature",
  "properties": {
    "iso:country":"US",
    "sg:address":"1800 Ximeno Ave",
    "sg:city":"Long Beach",
    "sg:classifiers":[
        {
            "category":"Restaurant",
            "type":"Food & Drink"
        }
    ],
    "sg:menulink":"http://www.allmenus.com/ca/long-beach-lakewood/221674-chipotle/menu/",
    "sg:phone":"+1 562 597 0469",
    "sg:postcode":"90815",
    "sg:province":"CA",
    "sg:tags":[
        "mexican"
    ],
    "wof:name":"Chipotle",
    "wof:placetype":"venue"
},
  "geometry": {"coordinates":[-118.13783100000001,33.791149],"type":"Point"}
}