{
  "type": "Feature",
  "properties": {
    "iso:country":"US",
    "sg:address":"1011 el Camino Real",
    "sg:city":"Menlo Park",
    "sg:classifiers":[
        {
            "category":"Recreation",
            "type":"Entertainment"
        }
    ],
    "sg:phone":"+1 650 324 2510",
    "sg:postcode":"94025",
    "sg:province":"CA",
    "sg:tags":[
        "instruction",
        "yoga"
    ],
    "wof:name":"Hot Yoga 101",
    "wof:placetype":"venue"
},
  "geometry": {"coordinates":[-122.18293199999999,37.453438],"type":"Point"}
}