{
  "type": "Feature",
  "properties": {
    "iso:country":"US",
    "sg:address":"10 Mulberry Ct",
    "sg:city":"Belmont",
    "sg:classifiers":[
        {
            "category":"Professional",
            "type":"Services"
        }
    ],
    "sg:phone":"+1 650 596 2859",
    "sg:postcode":"94002",
    "sg:province":"CA",
    "wof:name":"Stanley Friedman",
    "wof:placetype":"venue"
},
  "geometry": {"coordinates":[-122.297902,37.51014],"type":"Point"}
}