{
  "type": "Feature",
  "properties": {
    "iso:country":"US",
    "sg:address":"626 Frederick St",
    "sg:city":"Santa Cruz",
    "sg:classifiers":[
        {
            "category":"Personal",
            "subcategory":"Massage",
            "type":"Services"
        }
    ],
    "sg:phone":"+1 831 458 2226",
    "sg:postcode":"95062",
    "sg:province":"CA",
    "wof:name":"Riexinger Vina",
    "wof:placetype":"venue"
},
  "geometry": {"coordinates":[-122.003998,36.98],"type":"Point"}
}