{
  "type": "Feature",
  "properties": {
    "addr:full":"950 Florin Rd Sacramento CA 95831",
    "addr:housenumber":"950",
    "addr:postcode":"95831",
    "addr:street":"Florin Rd",
    "iso:country":"US",
    "sg:address":"950 Florin Rd",
    "sg:city":"Sacramento",
    "sg:classifiers":[
        {
            "category":"Banks & Credit Unions",
            "subcategory":"Bank",
            "type":"Services"
        }
    ],
    "sg:phone":"+1 916 391 4080",
    "sg:postcode":"95831",
    "sg:province":"CA",
    "sg:website":"www.usbank.com",
    "wof:name":"US Bank",
    "wof:placetype":"venue"
},
  "geometry": {"coordinates":[-121.523752,38.495881],"type":"Point"}
}