{
  "type": "Feature",
  "properties": {
    "addr:full":"3775 Bodega Ave Petaluma CA 94952",
    "addr:housenumber":"3775",
    "addr:postcode":"94952",
    "addr:street":"Bodega Ave",
    "iso:country":"US",
    "sg:address":"3775 Bodega Ave",
    "sg:city":"Petaluma",
    "sg:classifiers":[
        {
            "category":"Education",
            "subcategory":"School",
            "type":"Public Place"
        }
    ],
    "sg:phone":"+1 707 765 4340",
    "sg:postcode":"94952",
    "sg:province":"CA",
    "wof:name":"Wilson School",
    "wof:placetype":"venue"
},
  "geometry": {"coordinates":[-122.684308,38.244633],"type":"Point"}
}