{
  "type": "Feature",
  "properties": {
    "iso:country":"US",
    "sg:address":"612 E Boronda Rd",
    "sg:city":"Salinas",
    "sg:classifiers":[
        {
            "category":"Shopping",
            "subcategory":"Computers & Home Electronics",
            "type":"Retail Goods"
        }
    ],
    "sg:phone":"+1 831 443 4706",
    "sg:postcode":"93906",
    "sg:province":"CA",
    "sg:tags":[
        "equipment",
        "electronic",
        "supply"
    ],
    "wof:name":"Radio Shack",
    "wof:placetype":"venue"
},
  "geometry": {"coordinates":[-121.611868,36.713237],"type":"Point"}
}