{
  "type": "Feature",
  "properties": {
    "iso:country":"US",
    "sg:address":"4350 Galbrath Dr Apt 72",
    "sg:city":"Sacramento",
    "sg:classifiers":[
        {
            "category":"Manufacturing",
            "subcategory":"Glass & Minerals",
            "type":"Manufacturing & Wholesale Goods"
        }
    ],
    "sg:phone":"+1 916 331 3984",
    "sg:postcode":"95842",
    "sg:province":"CA",
    "sg:tags":[
        "glass-wholesale",
        "shape",
        "circle",
        "special",
        "manufacturer"
    ],
    "wof:name":"Alex Beliakou Auto Glass",
    "wof:placetype":"venue"
},
  "geometry": {"coordinates":[-121.36322699999999,38.697604],"type":"Point"}
}