{
  "type": "Feature",
  "properties": {
    "iso:country":"US",
    "sg:address":"56621 Cahuilla Rd",
    "sg:city":"Anza",
    "sg:classifiers":[
        {
            "category":"Food & Beverages",
            "subcategory":"Groceries & Convenience Stores",
            "type":"Retail Goods"
        }
    ],
    "sg:phone":"+1 951 763 2212",
    "sg:postcode":"92539",
    "sg:province":"CA",
    "wof:name":"Circle K",
    "wof:placetype":"venue"
},
  "geometry": {"coordinates":[-116.672695,33.555052],"type":"Point"}
}