{
  "type": "Feature",
  "properties": {
    "addr:full":"23528 Calabasas Rd Calabasas CA 91302",
    "addr:housenumber":"23528",
    "addr:postcode":"91302",
    "addr:street":"Calabasas Rd",
    "iso:country":"US",
    "sg:address":"23528 Calabasas Rd",
    "sg:city":"Calabasas",
    "sg:classifiers":[
        {
            "category":"Real Estate",
            "subcategory":"Real Estate Agent",
            "type":"Services"
        }
    ],
    "sg:phone":"+1 818 222 7707",
    "sg:postcode":"91302",
    "sg:province":"CA",
    "sg:website":"www.paramountproperties.com",
    "wof:name":"Paramount Properties",
    "wof:placetype":"venue"
},
  "geometry": {"coordinates":[-118.640868,34.156712],"type":"Point"}
}