{
  "type": "Feature",
  "properties": {
    "iso:country":"US",
    "sg:address":"15790 Monterey Rd",
    "sg:city":"Morgan Hill",
    "sg:classifiers":[
        {
            "category":"Sports & Exercise",
            "subcategory":"Gym",
            "type":"Entertainment"
        }
    ],
    "sg:phone":"+1 408 778 8411",
    "sg:postcode":"95037",
    "sg:province":"CA",
    "sg:tags":[
        "club",
        "health",
        "studio",
        "gymnasium"
    ],
    "wof:name":"Contours Express",
    "wof:placetype":"venue"
},
  "geometry": {"coordinates":[-121.641824,37.111833],"type":"Point"}
}