{
  "type": "Feature",
  "properties": {
    "addr:full":"1242 S Bascom Ave San Jose CA 95128",
    "addr:housenumber":"1242",
    "addr:postcode":"95128",
    "addr:street":"S Bascom Ave",
    "iso:country":"US",
    "sg:address":"1242 S Bascom Ave",
    "sg:city":"San Jose",
    "sg:classifiers":[
        {
            "category":"Retail",
            "subcategory":"Laundry & Dry Cleaning",
            "type":"Services"
        }
    ],
    "sg:phone":"+1 408 287 1802",
    "sg:postcode":"95128",
    "sg:province":"CA",
    "sg:tags":[
        "cleaner"
    ],
    "wof:name":"Bonded Cleaners",
    "wof:placetype":"venue"
},
  "geometry": {"coordinates":[-121.931999,37.3032],"type":"Point"}
}