{
  "type": "Feature",
  "properties": {
    "iso:country":"US",
    "sg:address":"3195 Park Rd Ste C",
    "sg:city":"Benicia",
    "sg:phone":"+1 707 747 6251",
    "sg:postcode":"94510",
    "sg:province":"CA",
    "wof:name":"Frontline Electrical Services",
    "wof:placetype":"venue"
},
  "geometry": {"coordinates":[-122.132721,38.064819],"type":"Point"}
}