{
  "type": "Feature",
  "properties": {
    "addr:full":"20921 Longeway Rd Sonora CA 95370",
    "addr:postcode":"20921;95370",
    "addr:street":"Longeway Rd",
    "iso:country":"US",
    "sg:address":"20921 Longeway Rd",
    "sg:city":"Sonora",
    "sg:phone":"+1 209 533 4653",
    "sg:postcode":"95370",
    "sg:province":"CA",
    "sg:website":"http://www.mooseintl.org",
    "wof:name":"Sonora Lodge",
    "wof:placetype":"venue"
},
  "geometry": {"coordinates":[-120.265694,38.001895],"type":"Point"}
}