{
  "type": "Feature",
  "properties": {
    "addr:full":"2436 6th St Eureka CA 95501",
    "addr:housenumber":"2436",
    "addr:postcode":"95501",
    "addr:street":"6Th St",
    "iso:country":"US",
    "sg:address":"2436 6th St",
    "sg:city":"Eureka",
    "sg:classifiers":[
        {
            "category":"Museum",
            "subcategory":"Botanical Garden",
            "type":"Entertainment"
        }
    ],
    "sg:phone":"+1 707 442 5139",
    "sg:postcode":"95501",
    "sg:province":"CA",
    "wof:name":"Humboldt Botanical Gardens Foundation",
    "wof:placetype":"venue"
},
  "geometry": {"coordinates":[-124.14722999999999,40.80335],"type":"Point"}
}