{
  "type": "Feature",
  "properties": {
    "iso:country":"US",
    "sg:address":"1149 Macdonald Ave",
    "sg:city":"Richmond",
    "sg:classifiers":[
        {
            "category":"Social Services",
            "type":"Services"
        }
    ],
    "sg:phone":"+1 510 412 2039",
    "sg:postcode":"94801",
    "sg:province":"CA",
    "sg:tags":[
        "youth",
        "organization",
        "center"
    ],
    "wof:name":"Richmond Summer Youth Works",
    "wof:placetype":"venue"
},
  "geometry": {"coordinates":[-122.35846100000001,37.935775],"type":"Point"}
}