{
  "type": "Feature",
  "properties": {
    "iso:country":"US",
    "sg:address":"462 Santa Clara Ave",
    "sg:city":"Oakland",
    "sg:classifiers":[
        {
            "category":"Restaurant",
            "type":"Food & Drink"
        }
    ],
    "sg:phone":"+1 510 464 2948",
    "sg:postcode":"94610",
    "sg:province":"CA",
    "sg:tags":[
        "ethiopian"
    ],
    "wof:name":"Mimosa Ethiopian Restaurant & Cafe",
    "wof:placetype":"venue"
},
  "geometry": {"coordinates":[-122.248386,37.811823],"type":"Point"}
}