{
  "type": "Feature",
  "properties": {
    "iso:country":"US",
    "sg:address":"6855 Irving Rd",
    "sg:city":"Redding",
    "sg:classifiers":[
        {
            "category":"Professional",
            "subcategory":"Employment Agencies",
            "type":"Services"
        }
    ],
    "sg:phone":"+1 530 241 8570",
    "sg:postcode":"96001",
    "sg:province":"CA",
    "sg:tags":[
        "opportunity"
    ],
    "wof:name":"Career Designs",
    "wof:placetype":"venue"
},
  "geometry": {"coordinates":[-122.36757799999999,40.516644],"type":"Point"}
}