{
  "type": "Feature",
  "properties": {
    "iso:country":"US",
    "sg:address":"13 W 5th St",
    "sg:city":"Crows Landing",
    "sg:classifiers":[
        {
            "category":"Government",
            "subcategory":"Post Office",
            "type":"Public Place"
        }
    ],
    "sg:phone":"+1 209 837 4210",
    "sg:postcode":"95313",
    "sg:province":"CA",
    "wof:name":"US Post Office",
    "wof:placetype":"venue"
},
  "geometry": {"coordinates":[-121.072259,37.393677],"type":"Point"}
}