{
  "type": "Feature",
  "properties": {
    "addr:full":"4785 Beacon Hill Dr Castro Valley CA 94552",
    "addr:housenumber":"4785",
    "addr:postcode":"94552",
    "addr:street":"Beacon Hill Dr",
    "iso:country":"US",
    "sg:address":"4785 Beacon Hill Dr",
    "sg:city":"Castro Valley",
    "sg:classifiers":[
        {
            "category":"Professional",
            "type":"Services"
        }
    ],
    "sg:phone":"+1 510 886 9567",
    "sg:postcode":"94552",
    "sg:province":"CA",
    "wof:name":"Livingwater Co",
    "wof:placetype":"venue"
},
  "geometry": {"coordinates":[-122.05352600000001,37.699375],"type":"Point"}
}