{
  "type": "Feature",
  "properties": {
    "iso:country":"US",
    "sg:address":"12230 Shale Ridge Rd",
    "sg:city":"Auburn",
    "sg:classifiers":[
        {
            "category":"Wholesale",
            "subcategory":"Machinery & Supplies",
            "type":"Manufacturing & Wholesale Goods"
        }
    ],
    "sg:phone":"+1 530 888 7004",
    "sg:postcode":"95602",
    "sg:province":"CA",
    "sg:tags":[
        "sprinkler"
    ],
    "wof:name":"California Fire Systems",
    "wof:placetype":"venue"
},
  "geometry": {"coordinates":[-121.10028200000001,38.952968],"type":"Point"}
}