{
  "type": "Feature",
  "properties": {
    "iso:country":"US",
    "sg:address":"5759 Watt Ave",
    "sg:city":"North Highlands",
    "sg:classifiers":[
        {
            "category":"Personal",
            "subcategory":"Beauty Salon",
            "type":"Services"
        }
    ],
    "sg:phone":"+1 916 332 1264",
    "sg:postcode":"95660",
    "sg:province":"CA",
    "sg:tags":[
        "hair"
    ],
    "wof:name":"Jan's Hair Studio",
    "wof:placetype":"venue"
},
  "geometry": {"coordinates":[-121.38300599999999,38.671644],"type":"Point"}
}