{
  "type": "Feature",
  "properties": {
    "addr:full":"1558 Montague Expy San Jose CA 95131",
    "addr:housenumber":"1558",
    "addr:postcode":"95131",
    "addr:street":"Montague Expy",
    "iso:country":"US",
    "sg:address":"1558 Montague Expy",
    "sg:city":"San Jose",
    "sg:classifiers":[
        {
            "category":"Personal",
            "type":"Services"
        }
    ],
    "sg:phone":"+1 408 433 0880",
    "sg:postcode":"95131",
    "sg:province":"CA",
    "sg:tags":[
        "mover"
    ],
    "wof:name":"United Van Lines Agent",
    "wof:placetype":"venue"
},
  "geometry": {"coordinates":[-121.90100099999999,37.403999],"type":"Point"}
}