{
  "type": "Feature",
  "properties": {
    "iso:country":"US",
    "sg:address":"4752 E Carmen Ave",
    "sg:city":"Fresno",
    "sg:classifiers":[
        {
            "category":"Manufacturing",
            "subcategory":"Metals",
            "type":"Manufacturing & Wholesale Goods"
        }
    ],
    "sg:phone":"+1 559 252 1977",
    "sg:postcode":"93703",
    "sg:province":"CA",
    "sg:tags":[
        "fabricated",
        "structural"
    ],
    "wof:name":"Fresno Fab-Tech Inc",
    "wof:placetype":"venue"
},
  "geometry": {"coordinates":[-119.739304,36.76456],"type":"Point"}
}