{
  "type": "Feature",
  "properties": {
    "addr:full":"21058 Kingscrest Dr Santa Clarita CA 91350",
    "addr:postcode":"21058;91350",
    "addr:street":"Kingscrest Dr",
    "iso:country":"US",
    "sg:address":"21058 Kingscrest Dr",
    "sg:city":"Santa Clarita",
    "sg:classifiers":[
        {
            "category":"Building & Trades",
            "subcategory":"Plumbing",
            "type":"Services"
        }
    ],
    "sg:phone":"+1 661 296 6612",
    "sg:postcode":"91350",
    "sg:province":"CA",
    "wof:name":"Day E A Plumbing",
    "wof:placetype":"venue"
},
  "geometry": {"coordinates":[-118.504997,34.449299],"type":"Point"}
}