{
  "type": "Feature",
  "properties": {
    "addr:full":"1005 Emma Ct San Jose CA 95120",
    "addr:housenumber":"1005",
    "addr:postcode":"95120",
    "addr:street":"Emma Ct",
    "iso:country":"US",
    "sg:address":"1005 Emma Ct",
    "sg:city":"San Jose",
    "sg:classifiers":[
        {
            "category":"Professional",
            "type":"Services"
        }
    ],
    "sg:phone":"+1 408 927 6462",
    "sg:postcode":"95120",
    "sg:province":"CA",
    "wof:name":"Pean Uts",
    "wof:placetype":"venue"
},
  "geometry": {"coordinates":[-121.83892400000001,37.201169],"type":"Point"}
}