{
  "type": "Feature",
  "properties": {
    "iso:country":"US",
    "sg:address":"423 Tehama St",
    "sg:city":"San Francisco",
    "sg:classifiers":[
        {
            "category":"Professional",
            "subcategory":"Computer Services",
            "type":"Services"
        }
    ],
    "sg:phone":"+1 415 495 7344",
    "sg:postcode":"94103",
    "sg:province":"CA",
    "sg:tags":[
        "electronics"
    ],
    "wof:name":"Tehama Wireless Design",
    "wof:placetype":"venue"
},
  "geometry": {"coordinates":[-122.40618000000001,37.779657],"type":"Point"}
}