{
  "type": "Feature",
  "properties": {
    "addr:full":"2265 Westwood Blvd #886 San Francisco CA 94114",
    "addr:housenumber":"2265",
    "addr:postcode":"94114",
    "addr:street":"Westwood Blvd # 886",
    "iso:country":"US",
    "sg:address":"2265 Westwood Blvd #886",
    "sg:city":"San Francisco",
    "sg:classifiers":[
        {
            "category":"Personal",
            "type":"Services"
        }
    ],
    "sg:phone":"+1 866 808 5444",
    "sg:postcode":"94114",
    "sg:province":"CA",
    "sg:tags":[
        "mover"
    ],
    "sg:website":"www.amexmovers.com",
    "wof:name":"AMEXMOVERS, Inc.",
    "wof:placetype":"venue"
},
  "geometry": {"coordinates":[-122.459059,37.727612],"type":"Point"}
}