{
  "type": "Feature",
  "properties": {
    "iso:country":"US",
    "sg:address":"1815 Hawthorne Blvd",
    "sg:city":"Redondo Beach",
    "sg:classifiers":[
        {
            "category":"Shopping",
            "subcategory":"Hobbies, Toys, & Games",
            "type":"Retail Goods"
        }
    ],
    "sg:phone":"+1 310 542 9687",
    "sg:postcode":"90278",
    "sg:province":"CA",
    "sg:tags":[
        "toy",
        "store"
    ],
    "sg:website":"www.disneystore.com",
    "wof:name":"The Disney Store",
    "wof:placetype":"venue"
},
  "geometry": {"coordinates":[-118.352709,33.866718],"type":"Point"}
}