{
  "type": "Feature",
  "properties": {
    "iso:country":"US",
    "sg:address":"100 Corson St",
    "sg:city":"Pasadena",
    "sg:classifiers":[
        {
            "category":"Professional",
            "subcategory":"Detective & Security Services",
            "type":"Services"
        }
    ],
    "sg:phone":"+1 626 584 1921",
    "sg:postcode":"91103",
    "sg:province":"CA",
    "sg:tags":[
        "guard",
        "patrol"
    ],
    "wof:name":"ASRC Airfield & Range Svc",
    "wof:placetype":"venue"
},
  "geometry": {"coordinates":[-118.148111,34.151168],"type":"Point"}
}