{
  "type": "Feature",
  "properties": {
    "addr:full":"52 37th Ave San Mateo CA 94403",
    "addr:housenumber":"52",
    "addr:postcode":"94403",
    "addr:street":"37Th Ave",
    "iso:country":"US",
    "sg:address":"52 37th Ave",
    "sg:city":"San Mateo",
    "sg:classifiers":[
        {
            "category":"Personal",
            "subcategory":"Nail Salon",
            "type":"Services"
        }
    ],
    "sg:phone":"+1 650 356 0809",
    "sg:postcode":"94403",
    "sg:province":"CA",
    "wof:name":"Hanna's Hair and Nail Salon",
    "wof:placetype":"venue"
},
  "geometry": {"coordinates":[-122.295998,37.534],"type":"Point"}
}