{
  "type": "Feature",
  "properties": {
    "addr:full":"1150 El Camino Real San Bruno CA 94066",
    "addr:housenumber":"1150",
    "addr:postcode":"94066",
    "addr:street":"El Camino Real",
    "iso:country":"US",
    "sg:address":"1150 El Camino Real",
    "sg:city":"San Bruno",
    "sg:classifiers":[
        {
            "category":"Shopping",
            "subcategory":"Jewelry",
            "type":"Retail Goods"
        }
    ],
    "sg:phone":"+1 650 583 0431",
    "sg:postcode":"94066",
    "sg:province":"CA",
    "wof:name":"Crescent Jewelers",
    "wof:placetype":"venue"
},
  "geometry": {"coordinates":[-122.420663,37.635962],"type":"Point"}
}