{
  "type": "Feature",
  "properties": {
    "addr:full":"696 W el Camino Real Sunnyvale CA 94087",
    "addr:housenumber":"696",
    "addr:postcode":"94087",
    "addr:street":"W El Camino Real",
    "iso:country":"US",
    "sg:address":"696 W el Camino Real",
    "sg:city":"Sunnyvale",
    "sg:classifiers":[
        {
            "category":"Autos & Motor Vehicles",
            "subcategory":"Fuel & Gas Station",
            "type":"Retail Goods"
        }
    ],
    "sg:phone":"+1 408 736 0927",
    "sg:postcode":"94087",
    "sg:province":"CA",
    "sg:tags":[
        "oil"
    ],
    "wof:name":"Valero Service Station",
    "wof:placetype":"venue"
},
  "geometry": {"coordinates":[-122.03718000000001,37.368965],"type":"Point"}
}