{
  "type": "Feature",
  "properties": {
    "addr:full":"9646 E Garvey Ave # 104 El Monte CA 91733",
    "addr:housenumber":"9646",
    "addr:postcode":"91733",
    "addr:street":"E Garvey Ave # 104",
    "iso:country":"US",
    "sg:address":"9646 E Garvey Ave # 104",
    "sg:city":"El Monte",
    "sg:classifiers":[
        {
            "category":"Restaurant",
            "type":"Food & Drink"
        }
    ],
    "sg:phone":"+1 626 448 4617",
    "sg:postcode":"91733",
    "sg:province":"CA",
    "sg:tags":[
        "vietnamese"
    ],
    "wof:name":"Thanh Loi Tofu",
    "wof:placetype":"venue"
},
  "geometry": {"coordinates":[-118.059505,34.050036],"type":"Point"}
}