{
  "type": "Feature",
  "properties": {
    "iso:country":"US",
    "sg:address":"325 Encinitas Blvd Exxon Station Parking Lot",
    "sg:city":"Encinitas",
    "sg:classifiers":[
        {
            "category":"Coffee & Tea",
            "type":"Food & Drink"
        }
    ],
    "sg:phone":"+1 760 632 5256",
    "sg:postcode":"92024",
    "sg:province":"CA",
    "wof:name":"Java Express",
    "wof:placetype":"venue"
},
  "geometry": {"coordinates":[-117.28534500000001,33.048243],"type":"Point"}
}