{
  "type": "Feature",
  "properties": {
    "iso:country":"US",
    "sg:address":"2483 Sunrise Blvd",
    "sg:city":"Rancho Cordova",
    "sg:classifiers":[
        {
            "category":"Insurance",
            "subcategory":"Insurance Agent",
            "type":"Services"
        }
    ],
    "sg:phone":"+1 916 852 2060",
    "sg:postcode":"95670",
    "sg:province":"CA",
    "wof:name":"Allstate",
    "wof:placetype":"venue"
},
  "geometry": {"coordinates":[-121.269279,38.615055],"type":"Point"}
}