{
  "type": "Feature",
  "properties": {
    "addr:full":"5376 Moonshadow St Simi Valley CA 93063",
    "addr:housenumber":"5376",
    "addr:postcode":"93063",
    "addr:street":"Moonshadow St",
    "iso:country":"US",
    "sg:address":"5376 Moonshadow St",
    "sg:city":"Simi Valley",
    "sg:classifiers":[
        {
            "category":"Shopping",
            "subcategory":"Discount & Variety Stores",
            "type":"Retail Goods"
        }
    ],
    "sg:phone":"+1 805 578 9370",
    "sg:postcode":"93063",
    "sg:province":"CA",
    "sg:tags":[
        "merchandise",
        "general"
    ],
    "wof:name":"Silverthorne Sales Office",
    "wof:placetype":"venue"
},
  "geometry": {"coordinates":[-118.686753,34.294641],"type":"Point"}
}