{
  "type": "Feature",
  "properties": {
    "addr:full":"11021 Sunnyside Dr Yucaipa CA 92399",
    "addr:housenumber":"11021",
    "addr:postcode":"92399",
    "addr:street":"Sunnyside Dr",
    "iso:country":"US",
    "sg:address":"11021 Sunnyside Dr",
    "sg:city":"Yucaipa",
    "sg:classifiers":[
        {
            "category":"Education",
            "subcategory":"School",
            "type":"Public Place"
        }
    ],
    "sg:phone":"+1 909 790 3270",
    "sg:postcode":"92399",
    "sg:province":"CA",
    "sg:tags":[
        "high",
        "middle",
        "elementary"
    ],
    "wof:name":"Yucaipa-Calimesa Joint Unified School District",
    "wof:placetype":"venue"
},
  "geometry": {"coordinates":[-117.041,34.051201],"type":"Point"}
}