{
  "type": "Feature",
  "properties": {
    "addr:full":"6789 Warner Ave Huntington Beach CA 92647",
    "addr:housenumber":"6789",
    "addr:postcode":"92647",
    "addr:street":"Warner Ave",
    "iso:country":"US",
    "sg:address":"6789 Warner Ave",
    "sg:city":"Huntington Beach",
    "sg:classifiers":[
        {
            "category":"Insurance",
            "subcategory":"Health Insurance",
            "type":"Services"
        }
    ],
    "sg:phone":"+1 714 847 5325",
    "sg:postcode":"92647",
    "sg:province":"CA",
    "sg:tags":[
        "market"
    ],
    "wof:name":"Natural Tonic Center",
    "wof:placetype":"venue"
},
  "geometry": {"coordinates":[-118.011002,33.715698],"type":"Point"}
}