{
  "type": "Feature",
  "properties": {
    "iso:country":"US",
    "sg:address":"3144 E Maria St",
    "sg:city":"Compton",
    "sg:classifiers":[
        {
            "category":"Manufacturing",
            "subcategory":"Metals",
            "type":"Manufacturing & Wholesale Goods"
        }
    ],
    "sg:phone":"+1 310 608 0693",
    "sg:postcode":"90221",
    "sg:province":"CA",
    "sg:tags":[
        "hinge"
    ],
    "sg:website":"www.spep.com",
    "wof:name":"Sierra Pacific Engineering",
    "wof:placetype":"venue"
},
  "geometry": {"coordinates":[-118.20502500000001,33.859236],"type":"Point"}
}