{
  "type": "Feature",
  "properties": {
    "iso:country":"US",
    "sg:address":"2509 McHenry Ave",
    "sg:city":"Modesto",
    "sg:classifiers":[
        {
            "category":"Banks & Credit Unions",
            "subcategory":"Bank",
            "type":"Services"
        }
    ],
    "sg:phone":"+1 209 526 5990",
    "sg:postcode":"95350",
    "sg:province":"CA",
    "sg:tags":[
        "savings",
        "loan",
        "association"
    ],
    "sg:website":"www.worldsavings.com",
    "wof:name":"World Savings Bank",
    "wof:placetype":"venue"
},
  "geometry": {"coordinates":[-120.994188,37.676942],"type":"Point"}
}