{
  "type": "Feature",
  "properties": {
    "addr:full":"619 Pine Ave Long Beach CA 90802",
    "addr:housenumber":"619",
    "addr:postcode":"90802",
    "addr:street":"Pine Ave",
    "iso:country":"US",
    "sg:address":"619 Pine Ave",
    "sg:city":"Long Beach",
    "sg:classifiers":[
        {
            "category":"Health Services",
            "subcategory":"Optometrist",
            "type":"Services"
        }
    ],
    "sg:phone":"+1 562 366 0777",
    "sg:postcode":"90802",
    "sg:province":"CA",
    "wof:name":"Quality Eye Care Optometry",
    "wof:placetype":"venue"
},
  "geometry": {"coordinates":[-118.19267499999999,33.774582],"type":"Point"}
}