{
  "type": "Feature",
  "properties": {
    "iso:country":"US",
    "sg:address":"10111 Imperial Ave",
    "sg:city":"Garden Grove",
    "sg:classifiers":[
        {
            "category":"Professional",
            "type":"Services"
        }
    ],
    "sg:phone":"+1 714 636 8962",
    "sg:postcode":"92843",
    "sg:province":"CA",
    "wof:name":"Comback Treatment",
    "wof:placetype":"venue"
},
  "geometry": {"coordinates":[-117.95228400000001,33.769659],"type":"Point"}
}