{
  "type": "Feature",
  "properties": {
    "addr:full":"2537 Via Pisa Del Mar CA 92014",
    "addr:housenumber":"2537",
    "addr:postcode":"92014",
    "addr:street":"Via Pisa",
    "iso:country":"US",
    "sg:address":"2537 Via Pisa",
    "sg:city":"Del Mar",
    "sg:classifiers":[
        {
            "category":"Professional",
            "subcategory":"Lawyer & Legal Services",
            "type":"Services"
        }
    ],
    "sg:phone":"+1 858 558 4600",
    "sg:postcode":"92014",
    "sg:province":"CA",
    "sg:tags":[
        "attorney"
    ],
    "wof:name":"Charles D Richmond",
    "wof:placetype":"venue"
},
  "geometry": {"coordinates":[-117.24811699999999,32.931913],"type":"Point"}
}