{
  "type": "Feature",
  "properties": {
    "iso:country":"US",
    "sg:address":"1604 S Coast Hwy 101",
    "sg:city":"Encinitas",
    "sg:classifiers":[
        {
            "category":"Food & Beverages",
            "subcategory":"Bakery",
            "type":"Retail Goods"
        }
    ],
    "sg:phone":"+1 760 942 8981",
    "sg:postcode":"92007",
    "sg:province":"CA",
    "sg:tags":[
        "product",
        "mfg"
    ],
    "wof:name":"Leucadia Donut Shoppe",
    "wof:placetype":"venue"
},
  "geometry": {"coordinates":[-117.290213,33.03273],"type":"Point"}
}