{
  "type": "Feature",
  "properties": {
    "addr:full":"72 Mill Stone Ln San Jose CA 95136",
    "addr:housenumber":"72",
    "addr:postcode":"95136",
    "addr:street":"Mill Stone Ln",
    "iso:country":"US",
    "sg:address":"72 Mill Stone Ln",
    "sg:city":"San Jose",
    "sg:classifiers":[
        {
            "category":"Wholesale",
            "subcategory":"Electrical",
            "type":"Manufacturing & Wholesale Goods"
        }
    ],
    "sg:phone":"+1 408 360 0740",
    "sg:postcode":"95136",
    "sg:province":"CA",
    "sg:tags":[
        "electronic"
    ],
    "wof:name":"Excel Components",
    "wof:placetype":"venue"
},
  "geometry": {"coordinates":[-121.816346,37.26036],"type":"Point"}
}