{
  "type": "Feature",
  "properties": {
    "addr:full":"2860 Eden Valley Ln Escondido CA 92029",
    "addr:housenumber":"2860",
    "addr:postcode":"92029",
    "addr:street":"Eden Valley Ln",
    "iso:country":"US",
    "sg:address":"2860 Eden Valley Ln",
    "sg:city":"Escondido",
    "sg:classifiers":[
        {
            "category":"Banks & Credit Unions",
            "subcategory":"Bank",
            "type":"Services"
        }
    ],
    "sg:phone":"+1 760 480 8600",
    "sg:postcode":"92029",
    "sg:province":"CA",
    "sg:tags":[
        "loan",
        "real estate"
    ],
    "wof:name":"Met & Assoc Inc",
    "wof:placetype":"venue"
},
  "geometry": {"coordinates":[-117.131376,33.117779],"type":"Point"}
}