{
  "type": "Feature",
  "properties": {
    "addr:full":"1439 W Paul Ave Fresno CA 93711",
    "addr:housenumber":"1439",
    "addr:postcode":"93711",
    "addr:street":"W Paul Ave",
    "iso:country":"US",
    "sg:address":"1439 W Paul Ave",
    "sg:city":"Fresno",
    "sg:classifiers":[
        {
            "category":"Organizations",
            "subcategory":"Non-profit Organization",
            "type":"Services"
        }
    ],
    "sg:phone":"+1 559 432 5014",
    "sg:postcode":"93711",
    "sg:province":"CA",
    "sg:tags":[
        "fund",
        "counselor",
        "raising"
    ],
    "wof:name":"Harlan Fundraising Svc",
    "wof:placetype":"venue"
},
  "geometry": {"coordinates":[-119.820639,36.832409],"type":"Point"}
}