{
  "type": "Feature",
  "properties": {
    "addr:full":"10911 Canyon Hill Ln San Diego CA 92126",
    "addr:housenumber":"10911",
    "addr:postcode":"92126",
    "addr:street":"Canyon Hill Ln",
    "iso:country":"US",
    "sg:address":"10911 Canyon Hill Ln",
    "sg:city":"San Diego",
    "sg:classifiers":[
        {
            "category":"Taxi",
            "type":"Transportation"
        }
    ],
    "sg:phone":"+1 858 578 9638",
    "sg:postcode":"92126",
    "sg:province":"CA",
    "sg:tags":[
        "driver"
    ],
    "wof:name":"Antony N Velasquez",
    "wof:placetype":"venue"
},
  "geometry": {"coordinates":[-117.16528,32.916576],"type":"Point"}
}