{
  "type": "Feature",
  "properties": {
    "iso:country":"US",
    "sg:address":"115 E 9th Street",
    "sg:city":"Los Angeles",
    "sg:classifiers":[
        {
            "category":"Shopping",
            "subcategory":"Clothing, Apparel, & Fashions",
            "type":"Retail Goods"
        }
    ],
    "sg:phone":"+1 213 542 1860",
    "sg:postcode":"90015",
    "sg:province":"CA",
    "sg:tags":[
        "clothing",
        "women's"
    ],
    "wof:name":"Nataya",
    "wof:placetype":"venue"
},
  "geometry": {"coordinates":[-118.256036,34.039442],"type":"Point"}
}