{
  "type": "Feature",
  "properties": {
    "addr:full":"46166 Paloma Rd Coarsegold CA 93614",
    "addr:housenumber":"46166",
    "addr:postcode":"93614",
    "addr:street":"Paloma Rd",
    "iso:country":"US",
    "sg:address":"46166 Paloma Rd",
    "sg:city":"Coarsegold",
    "sg:classifiers":[
        {
            "category":"Professional",
            "type":"Services"
        }
    ],
    "sg:phone":"+1 559 642 3948",
    "sg:postcode":"93614",
    "sg:province":"CA",
    "wof:name":"Trimble Inc",
    "wof:placetype":"venue"
},
  "geometry": {"coordinates":[-119.70650999999999,37.230228],"type":"Point"}
}