{
  "type": "Feature",
  "properties": {
    "iso:country":"US",
    "sg:address":"43842 Windsor Pl",
    "sg:city":"Lancaster",
    "sg:classifiers":[
        {
            "category":"Shopping",
            "subcategory":"Computers & Home Electronics",
            "type":"Retail Goods"
        }
    ],
    "sg:phone":"+1 661 942 1420",
    "sg:postcode":"93536",
    "sg:province":"CA",
    "sg:tags":[
        "equipment",
        "audio-visual"
    ],
    "wof:name":"Audio Vandal Music",
    "wof:placetype":"venue"
},
  "geometry": {"coordinates":[-118.181892,34.680112],"type":"Point"}
}