{
  "type": "Feature",
  "properties": {
    "iso:country":"US",
    "sg:address":"28073 Diaz Rd",
    "sg:city":"Temecula",
    "sg:classifiers":[
        {
            "category":"Professional",
            "type":"Services"
        }
    ],
    "sg:phone":"+1 951 677 8539",
    "sg:postcode":"92590",
    "sg:province":"CA",
    "wof:name":"House Hse Ministrys",
    "wof:placetype":"venue"
},
  "geometry": {"coordinates":[-117.156362,33.500178],"type":"Point"}
}