{
  "type": "Feature",
  "properties": {
    "acgov:api":"933.0",
    "acgov:type":"ES",
    "addr:full":"400 Packet Landing Rd Alameda CA",
    "wof:categories":[
        "education_and_religion:education=school"
    ],
    "wof:name":"Amelia Earhart Elementary",
    "wof:placetype":"venue"
},
  "geometry": {"coordinates":[-122.23876149479162,37.74476393804745],"type":"Point"}
}