{
  "type": "Feature",
  "properties": {
    "addr:full":"35 Argonaut Laguna Beach CA 92656",
    "addr:housenumber":"35",
    "addr:postcode":"92656",
    "addr:street":"Argonaut",
    "iso:country":"US",
    "sg:address":"35 Argonaut",
    "sg:city":"Laguna Beach",
    "sg:classifiers":[
        {
            "category":"Health Services",
            "subcategory":"Medical Lab",
            "type":"Services"
        }
    ],
    "sg:phone":"+1 949 830 9724",
    "sg:postcode":"92656",
    "sg:province":"CA",
    "sg:tags":[
        "laboratory"
    ],
    "wof:name":"Nuth & Nicolai",
    "wof:placetype":"venue"
},
  "geometry": {"coordinates":[-117.724875,33.592084],"type":"Point"}
}