{
  "type": "Feature",
  "properties": {
    "iso:country":"US",
    "sg:address":"12631 Coldbrook Ave",
    "sg:city":"Downey",
    "sg:classifiers":[
        {
            "category":"Freight",
            "type":"Transportation"
        }
    ],
    "sg:phone":"+1 562 803 5395",
    "sg:postcode":"90242",
    "sg:province":"CA",
    "sg:tags":[
        "delivery",
        "produce"
    ],
    "wof:name":"Zacks Produce",
    "wof:placetype":"venue"
},
  "geometry": {"coordinates":[-118.122808,33.914099],"type":"Point"}
}