{
  "type": "Feature",
  "properties": {
    "addr:full":"8969 Kenamar Dr San Diego CA 92121",
    "addr:housenumber":"8969",
    "addr:postcode":"92121",
    "addr:street":"Kenamar Dr",
    "iso:country":"US",
    "sg:address":"8969 Kenamar Dr",
    "sg:city":"San Diego",
    "sg:classifiers":[
        {
            "category":"Professional",
            "subcategory":"Computer Services",
            "type":"Services"
        }
    ],
    "sg:phone":"+1 858 527 1675",
    "sg:postcode":"92121",
    "sg:province":"CA",
    "sg:tags":[
        "scanning"
    ],
    "wof:name":"Broad Display",
    "wof:placetype":"venue"
},
  "geometry": {"coordinates":[-117.15540300000001,32.886137],"type":"Point"}
}