{
  "type": "Feature",
  "properties": {
    "iso:country":"US",
    "sg:address":"1130 E Clark Ave",
    "sg:city":"Santa Maria",
    "sg:classifiers":[
        {
            "category":"Education",
            "subcategory":"Special Training",
            "type":"Public Place"
        }
    ],
    "sg:phone":"+1 805 938 5160",
    "sg:postcode":"93455",
    "sg:province":"CA",
    "sg:tags":[
        "tutoring"
    ],
    "wof:name":"Tutoring Club",
    "wof:placetype":"venue"
},
  "geometry": {"coordinates":[-120.415517,34.864904],"type":"Point"}
}