{
  "type": "Feature",
  "properties": {
    "addr:full":"5700 Occidental Rd Santa Rosa CA 95401",
    "addr:housenumber":"5700",
    "addr:postcode":"95401",
    "addr:street":"Occidental Rd",
    "iso:country":"US",
    "sg:address":"5700 Occidental Rd",
    "sg:city":"Santa Rosa",
    "sg:classifiers":[
        {
            "category":"Manufacturing",
            "subcategory":"Food",
            "type":"Manufacturing & Wholesale Goods"
        }
    ],
    "sg:phone":"+1 707 544 7876",
    "sg:postcode":"95401",
    "sg:province":"CA",
    "sg:tags":[
        "winery"
    ],
    "wof:name":"Abundance Vineyards",
    "wof:placetype":"venue"
},
  "geometry": {"coordinates":[-122.82074900000001,38.423832],"type":"Point"}
}