{
  "type": "Feature",
  "properties": {
    "iso:country":"US",
    "sg:address":"368 Riviera Dr",
    "sg:city":"Lemoore",
    "sg:classifiers":[
        {
            "category":"Manufacturing",
            "subcategory":"Apparel",
            "type":"Manufacturing & Wholesale Goods"
        }
    ],
    "sg:phone":"+1 559 924 8634",
    "sg:postcode":"93245",
    "sg:province":"CA",
    "sg:tags":[
        "mfg"
    ],
    "wof:name":"Anne Hoover Enterprises",
    "wof:placetype":"venue"
},
  "geometry": {"coordinates":[-119.770136,36.29296],"type":"Point"}
}