{
  "type": "Feature",
  "properties": {
    "addr:full":"4250 Williams Rd San Jose CA 95129",
    "addr:housenumber":"4250",
    "addr:postcode":"95129",
    "addr:street":"Williams Rd",
    "iso:country":"US",
    "sg:address":"4250 Williams Rd",
    "sg:city":"San Jose",
    "sg:classifiers":[
        {
            "category":"Autos & Motor Vehicles",
            "subcategory":"Fuel & Gas Station",
            "type":"Retail Goods"
        }
    ],
    "sg:phone":"+1 408 257 2222",
    "sg:postcode":"95129",
    "sg:province":"CA",
    "wof:name":"Rotten Robbie Main Office",
    "wof:placetype":"venue"
},
  "geometry": {"coordinates":[-121.977997,37.3083],"type":"Point"}
}