{
  "type": "Feature",
  "properties": {
    "iso:country":"US",
    "sg:address":"941 West 35th Street USC University Park Campus",
    "sg:city":"Los Angeles",
    "sg:classifiers":[
        {
            "category":"Food Court",
            "type":"Food & Drink"
        }
    ],
    "sg:phone":"+1 562 650 2951",
    "sg:postcode":"90089",
    "sg:province":"CA",
    "sg:tags":[
        "stand"
    ],
    "wof:name":"Armando's Lunch Truck",
    "wof:placetype":"venue"
},
  "geometry": {"coordinates":[-118.287798,34.023463],"type":"Point"}
}