{
  "type": "Feature",
  "properties": {
    "iso:country":"US",
    "sg:address":"11635 Valley Blvd",
    "sg:city":"El Monte",
    "sg:classifiers":[
        {
            "category":"Restaurant",
            "type":"Food & Drink"
        }
    ],
    "sg:phone":"+1 626 453 3897",
    "sg:postcode":"91732",
    "sg:province":"CA",
    "wof:name":"French Bakery House",
    "wof:placetype":"venue"
},
  "geometry": {"coordinates":[-118.024154,34.066183],"type":"Point"}
}