{
  "type": "Feature",
  "properties": {
    "iso:country":"US",
    "sg:address":"1629 Pollasky Ave",
    "sg:city":"Clovis",
    "sg:classifiers":[
        {
            "category":"Shopping",
            "type":"Retail Goods"
        }
    ],
    "sg:phone":"+1 559 323 6972",
    "sg:postcode":"93612",
    "sg:province":"CA",
    "sg:tags":[
        "product",
        "wood"
    ],
    "wof:name":"Trus Joist Inc",
    "wof:placetype":"venue"
},
  "geometry": {"coordinates":[-119.701952,36.811793],"type":"Point"}
}