{
  "type": "Feature",
  "properties": {
    "addr:full":"2851 Bedford Ln Chino Hills CA 91709",
    "addr:housenumber":"2851",
    "addr:postcode":"91709",
    "addr:street":"Bedford Ln",
    "iso:country":"US",
    "sg:address":"2851 Bedford Ln",
    "sg:city":"Chino Hills",
    "sg:classifiers":[
        {
            "category":"Building & Trades",
            "subcategory":"Cleaning & Sanitation",
            "type":"Services"
        }
    ],
    "sg:phone":"+1 909 591 1197",
    "sg:postcode":"91709",
    "sg:province":"CA",
    "sg:tags":[
        "house"
    ],
    "wof:name":"Mighty Tidy House Cleaning",
    "wof:placetype":"venue"
},
  "geometry": {"coordinates":[-117.740657,34.008264],"type":"Point"}
}