{
  "type": "Feature",
  "properties": {
    "addr:full":"580 Lorraine Ave San Jose CA 95110",
    "addr:housenumber":"580",
    "addr:postcode":"95110",
    "addr:street":"Lorraine Ave",
    "iso:country":"US",
    "sg:address":"580 Lorraine Ave",
    "sg:city":"San Jose",
    "sg:classifiers":[
        {
            "category":"Recreation",
            "type":"Entertainment"
        }
    ],
    "sg:phone":"+1 408 292 1525",
    "sg:postcode":"95110",
    "sg:province":"CA",
    "sg:tags":[
        "hall",
        "auditorium"
    ],
    "wof:name":"Democracy Hall",
    "wof:placetype":"venue"
},
  "geometry": {"coordinates":[-121.899396,37.326233],"type":"Point"}
}