{
  "type": "Feature",
  "properties": {
    "iso:country":"US",
    "sg:address":"2433 E Cesar E Chavez Avenue # A",
    "sg:city":"Los Angeles",
    "sg:classifiers":[
        {
            "category":"Personal",
            "subcategory":"Barber",
            "type":"Services"
        }
    ],
    "sg:phone":"+1 323 526 0854",
    "sg:postcode":"90033",
    "sg:province":"CA",
    "wof:name":"J & J Barber Shop",
    "wof:placetype":"venue"
},
  "geometry": {"coordinates":[-118.206757,34.046473],"type":"Point"}
}