{
  "type": "Feature",
  "properties": {
    "addr:full":"2231 Commerce Ave Concord CA 94520",
    "addr:housenumber":"2231",
    "addr:postcode":"94520",
    "addr:street":"Commerce Ave",
    "iso:country":"US",
    "sg:address":"2231 Commerce Ave",
    "sg:city":"Concord",
    "sg:classifiers":[
        {
            "category":"Retail",
            "subcategory":"Repair Shop",
            "type":"Services"
        }
    ],
    "sg:phone":"+1 925 825 4993",
    "sg:postcode":"94520",
    "sg:province":"CA",
    "sg:tags":[
        "upholsterer"
    ],
    "sg:website":"http://www.smartpages.com/home/bdupholstery",
    "wof:name":"B & D Upholstery Inc",
    "wof:placetype":"venue"
},
  "geometry": {"coordinates":[-122.045807,37.977425],"type":"Point"}
}