{
  "type": "Feature",
  "properties": {
    "addr:full":"136 W 40 St San Bernardino CA 92407",
    "addr:housenumber":"136",
    "addr:postcode":"92407",
    "addr:street":"W 40 St",
    "iso:country":"US",
    "sg:address":"136 W 40 St",
    "sg:city":"San Bernardino",
    "sg:classifiers":[
        {
            "category":"Shopping",
            "subcategory":"Tobacco",
            "type":"Retail Goods"
        }
    ],
    "sg:phone":"+1 909 881 1505",
    "sg:postcode":"92407",
    "sg:province":"CA",
    "sg:tags":[
        "cigarette",
        "cigar",
        "dealer"
    ],
    "wof:name":"Cig Zone",
    "wof:placetype":"venue"
},
  "geometry": {"coordinates":[-117.285077,34.164977],"type":"Point"}
}