{
  "type": "Feature",
  "properties": {
    "addr:full":"20601 3rd St Saratoga CA 95070",
    "addr:housenumber":"20601",
    "addr:postcode":"95070",
    "addr:street":"3Rd St",
    "iso:country":"US",
    "sg:address":"20601 3rd St",
    "sg:city":"Saratoga",
    "sg:classifiers":[
        {
            "category":"Personal",
            "subcategory":"Beauty Salon",
            "type":"Services"
        }
    ],
    "sg:phone":"+1 408 867 7784",
    "sg:postcode":"95070",
    "sg:province":"CA",
    "wof:name":"Mary Duffy",
    "wof:placetype":"venue"
},
  "geometry": {"coordinates":[-122.03388,37.257419],"type":"Point"}
}