{
  "type": "Feature",
  "properties": {
    "addr:full":"1691 E Noble Ave Visalia CA 93292",
    "addr:housenumber":"1691",
    "addr:postcode":"93292",
    "addr:street":"E Noble Ave",
    "iso:country":"US",
    "sg:address":"1691 E Noble Ave",
    "sg:city":"Visalia",
    "sg:classifiers":[
        {
            "category":"Restaurant",
            "type":"Food & Drink"
        }
    ],
    "sg:menulink":"http://www.allmenus.com/ca/visalia/75511-round-table-pizza/menu/",
    "sg:phone":"+1 559 625 8753",
    "sg:postcode":"93292",
    "sg:province":"CA",
    "sg:tags":[
        "american",
        "pizza"
    ],
    "wof:name":"Round Table Pizza",
    "wof:placetype":"venue"
},
  "geometry": {"coordinates":[-119.277005,36.325651],"type":"Point"}
}