{
  "type": "Feature",
  "properties": {
    "iso:country":"US",
    "sg:address":"39873 Crocus Dr",
    "sg:city":"Big Bear Lake",
    "sg:classifiers":[
        {
            "category":"Organizations",
            "subcategory":"Community Association",
            "type":"Services"
        }
    ],
    "sg:phone":"+1 909 866 4155",
    "sg:postcode":"92315",
    "sg:province":"CA",
    "sg:tags":[
        "fraternal"
    ],
    "wof:name":"Sahale Lodge",
    "wof:placetype":"venue"
},
  "geometry": {"coordinates":[-116.931674,34.238365],"type":"Point"}
}