{
  "type": "Feature",
  "properties": {
    "addr:full":"681 Lincoln Ave Napa CA 94558",
    "addr:housenumber":"681",
    "addr:postcode":"94558",
    "addr:street":"Lincoln Ave",
    "iso:country":"US",
    "sg:address":"681 Lincoln Ave",
    "sg:city":"Napa",
    "sg:classifiers":[
        {
            "category":"Restaurant",
            "type":"Food & Drink"
        }
    ],
    "sg:menulink":"http://www.allmenus.com/ca/napa/150386-subway/menu/",
    "sg:phone":"+1 707 257 2565",
    "sg:postcode":"94558",
    "sg:province":"CA",
    "sg:tags":[
        "american",
        "sandwich"
    ],
    "wof:name":"Subway",
    "wof:placetype":"venue"
},
  "geometry": {"coordinates":[-122.283568,38.309293],"type":"Point"}
}