{
  "type": "Feature",
  "properties": {
    "iso:country":"US",
    "sg:address":"2690 Pacific Ave",
    "sg:city":"Long Beach",
    "sg:classifiers":[
        {
            "category":"Health Services",
            "subcategory":"Doctor",
            "type":"Services"
        }
    ],
    "sg:phone":"+1 562 997 4070",
    "sg:postcode":"90806",
    "sg:province":"CA",
    "wof:name":"Saeed Sohail MD",
    "wof:placetype":"venue"
},
  "geometry": {"coordinates":[-118.194,33.806099],"type":"Point"}
}