{
  "type": "Feature",
  "properties": {
    "addr:full":"7377 Brentwood Blvd Brentwood CA 94513",
    "addr:housenumber":"7377",
    "addr:postcode":"ca 94513",
    "addr:street":"Brentwood Blvd",
    "iso:country":"US",
    "sg:address":"7377 Brentwood Blvd",
    "sg:city":"Brentwood",
    "sg:classifiers":[
        {
            "category":"Retail",
            "subcategory":"Auto Repair",
            "type":"Services"
        }
    ],
    "sg:phone":"+1 925 516 0623",
    "sg:postcode":"94513",
    "sg:province":"CA",
    "sg:tags":[
        "repairing",
        "automobile"
    ],
    "wof:name":"Speedee Oil Change & Tune Up",
    "wof:placetype":"venue"
},
  "geometry": {"coordinates":[-121.696231,37.947229],"type":"Point"}
}