{
  "type": "Feature",
  "properties": {
    "iso:country":"US",
    "sg:address":"1119 Queens Hwy",
    "sg:city":"Long Beach",
    "sg:classifiers":[
        {
            "category":"Organizations",
            "subcategory":"Non-profit Organization",
            "type":"Services"
        }
    ],
    "sg:phone":"+1 562 495 8445",
    "sg:postcode":"90802",
    "sg:province":"CA",
    "sg:tags":[
        "service/non-profit",
        "community"
    ],
    "wof:name":"Catholic Maritime Ministry",
    "wof:placetype":"venue"
},
  "geometry": {"coordinates":[-118.191814,33.75015],"type":"Point"}
}