{
  "type": "Feature",
  "properties": {
    "iso:country":"US",
    "sg:address":"888 E Walnut St",
    "sg:city":"Pasadena",
    "sg:classifiers":[
        {
            "category":"Professional",
            "subcategory":"Detective & Security Services",
            "type":"Services"
        }
    ],
    "sg:phone":"+1 626 535 5901",
    "sg:postcode":"91101",
    "sg:province":"CA",
    "sg:tags":[
        "information",
        "bureau"
    ],
    "wof:name":"One West Investment Services",
    "wof:placetype":"venue"
},
  "geometry": {"coordinates":[-118.132564,34.149571],"type":"Point"}
}