{
  "type": "Feature",
  "properties": {
    "addr:full":"808 Camaritas Ave South San Francisco CA 94080",
    "addr:housenumber":"808",
    "addr:postcode":"94080",
    "addr:street":"Camaritas Ave",
    "iso:country":"US",
    "sg:address":"808 Camaritas Ave",
    "sg:city":"South San Francisco",
    "sg:classifiers":[
        {
            "category":"Wholesale",
            "subcategory":"Non-durable Goods",
            "type":"Manufacturing & Wholesale Goods"
        }
    ],
    "sg:phone":"+1 650 757 3991",
    "sg:postcode":"94080",
    "sg:province":"CA",
    "wof:name":"Interline Imports Inc",
    "wof:placetype":"venue"
},
  "geometry": {"coordinates":[-122.45234600000001,37.664113],"type":"Point"}
}