{
  "type": "Feature",
  "properties": {
    "addr:full":"1700 Ygnacio Valley Rd Walnut Creek CA 94598",
    "addr:housenumber":"1700",
    "addr:postcode":"94598",
    "addr:street":"Ygnacio Valley Rd",
    "iso:country":"US",
    "sg:address":"1700 Ygnacio Valley Rd",
    "sg:city":"Walnut Creek",
    "sg:classifiers":[
        {
            "category":"Health Services",
            "subcategory":"Health Practitioner",
            "type":"Services"
        }
    ],
    "sg:phone":"+1 925 935 7667",
    "sg:postcode":"94598",
    "sg:province":"CA",
    "sg:tags":[
        "psychologist"
    ],
    "wof:name":"Contra Costa Sleep Ctr",
    "wof:placetype":"venue"
},
  "geometry": {"coordinates":[-122.03939,37.917524],"type":"Point"}
}