{
  "type": "Feature",
  "properties": {
    "iso:country":"US",
    "sg:address":"13572 Newport Ave",
    "sg:city":"Tustin",
    "sg:classifiers":[
        {
            "category":"Restaurant",
            "type":"Food & Drink"
        }
    ],
    "sg:phone":"+1 714 731 1711",
    "sg:postcode":"92780",
    "sg:province":"CA",
    "sg:tags":[
        "thai"
    ],
    "sg:website":"www.thaispecialty2.com",
    "wof:name":"Thai Specialty 2",
    "wof:placetype":"venue"
},
  "geometry": {"coordinates":[-117.817001,33.742901],"type":"Point"}
}