{
  "type": "Feature",
  "properties": {
    "addr:full":"215 N Marina Dr Long Beach CA 90803",
    "addr:housenumber":"215",
    "addr:postcode":"90803",
    "addr:street":"N Marina Dr",
    "iso:country":"US",
    "sg:address":"215 N Marina Dr",
    "sg:city":"Long Beach",
    "sg:classifiers":[
        {
            "category":"Personal",
            "type":"Services"
        },
        {
            "category":"Restaurant",
            "type":"Food & Drink"
        }
    ],
    "sg:phone":"+1 562 430 0272",
    "sg:postcode":"90803",
    "sg:province":"CA",
    "sg:tags":[
        "drinking",
        "eating"
    ],
    "sg:website":"www.thecrabpot.com",
    "wof:name":"Crab Pot Restaurants",
    "wof:placetype":"venue"
},
  "geometry": {"coordinates":[-118.110371,33.750316],"type":"Point"}
}