{
  "type": "Feature",
  "properties": {
    "iso:country":"US",
    "sg:address":"1500 S Central Ave",
    "sg:city":"Glendale",
    "sg:classifiers":[
        {
            "category":"Health Services",
            "subcategory":"Medical Lab",
            "type":"Services"
        }
    ],
    "sg:phone":"+1 818 242 0662",
    "sg:postcode":"91204",
    "sg:province":"CA",
    "sg:tags":[
        "laboratory"
    ],
    "wof:name":"Med Science Ctr",
    "wof:placetype":"venue"
},
  "geometry": {"coordinates":[-118.25789,34.126793],"type":"Point"}
}