{
  "type": "Feature",
  "properties": {
    "iso:country":"US",
    "sg:address":"4524 Sherman Oaks Ave",
    "sg:city":"Sherman Oaks",
    "sg:classifiers":[
        {
            "category":"Social Services",
            "subcategory":"Job Training",
            "type":"Services"
        }
    ],
    "sg:phone":"+1 818 788 9811",
    "sg:postcode":"91403",
    "sg:province":"CA",
    "sg:tags":[
        "rehabilitation"
    ],
    "wof:name":"Family Health & Sports Rehab",
    "wof:placetype":"venue"
},
  "geometry": {"coordinates":[-118.468924,34.154006],"type":"Point"}
}