{
  "type": "Feature",
  "properties": {
    "addr:full":"2202 4th Ave San Diego CA 92101",
    "addr:housenumber":"2202",
    "addr:postcode":"92101",
    "addr:street":"4Th Ave",
    "iso:country":"US",
    "sg:address":"2202 4th Ave",
    "sg:city":"San Diego",
    "sg:classifiers":[
        {
            "category":"Restaurant",
            "type":"Food & Drink"
        }
    ],
    "sg:phone":"+1 619 234 5540",
    "sg:postcode":"92101",
    "sg:province":"CA",
    "wof:name":"Liaison",
    "wof:placetype":"venue"
},
  "geometry": {"coordinates":[-117.16100299999999,32.7285],"type":"Point"}
}