{
  "type": "Feature",
  "properties": {
    "iso:country":"US",
    "sg:address":"2 Solano St",
    "sg:city":"Brisbane",
    "sg:classifiers":[
        {
            "category":"Recreation",
            "type":"Entertainment"
        }
    ],
    "sg:phone":"+1 415 657 4321",
    "sg:postcode":"94005",
    "sg:province":"CA",
    "sg:tags":[
        "pool",
        "swimming"
    ],
    "wof:name":"Brisbane Community Pool",
    "wof:placetype":"venue"
},
  "geometry": {"coordinates":[-122.40472,37.68474],"type":"Point"}
}