{
  "type": "Feature",
  "properties": {
    "iso:country":"US",
    "sg:address":"645 Ellsworth St",
    "sg:city":"San Francisco",
    "sg:classifiers":[
        {
            "category":"Wholesale",
            "subcategory":"Motor Vehicles",
            "type":"Manufacturing & Wholesale Goods"
        }
    ],
    "sg:phone":"+1 415 282 0233",
    "sg:postcode":"94110",
    "sg:province":"CA",
    "wof:name":"Neo France",
    "wof:placetype":"venue"
},
  "geometry": {"coordinates":[-122.414823,37.735314],"type":"Point"}
}