{
  "type": "Feature",
  "properties": {
    "iso:country":"US",
    "sg:address":"2960 N Sunnyside Ave Ste 109",
    "sg:city":"Fresno",
    "sg:classifiers":[
        {
            "category":"Wholesale",
            "subcategory":"Painting Supplies",
            "type":"Manufacturing & Wholesale Goods"
        },
        {
            "category":"Wholesale",
            "subcategory":"Construction Materials",
            "type":"Manufacturing & Wholesale Goods"
        },
        {
            "category":"Home & Garden",
            "subcategory":"Building Materials",
            "type":"Retail Goods"
        }
    ],
    "sg:phone":"+1 559 291 1106",
    "sg:postcode":"93727",
    "sg:province":"CA",
    "sg:tags":[
        "coatings-protective",
        "wallpaper",
        "paint-wholesale",
        "paint",
        "wallcoverings",
        "manufacturer"
    ],
    "wof:name":"Moore Jim Enterprises",
    "wof:placetype":"venue"
},
  "geometry": {"coordinates":[-119.691709,36.776396],"type":"Point"}
}