{
  "type": "Feature",
  "properties": {
    "iso:country":"US",
    "sg:address":"8929 Wilshire Boulevard",
    "sg:city":"Beverly Hills",
    "sg:classifiers":[
        {
            "category":"Building & Trades",
            "subcategory":"Construction",
            "type":"Services"
        }
    ],
    "sg:phone":"+1 310 289 7826",
    "sg:postcode":"90211",
    "sg:province":"CA",
    "sg:tags":[
        "interior",
        "design"
    ],
    "sg:website":"www.piccadillydesigns.com",
    "wof:name":"Piccadilly Designs",
    "wof:placetype":"venue"
},
  "geometry": {"coordinates":[-118.386689,34.067127],"type":"Point"}
}