{
  "type": "Feature",
  "properties": {
    "iso:country":"US",
    "sg:address":"3471 W 5th St",
    "sg:city":"Los Angeles",
    "sg:classifiers":[
        {
            "category":"Real Estate",
            "subcategory":"Real Estate Operator",
            "type":"Services"
        }
    ],
    "sg:phone":"+1 213 380 9464",
    "sg:postcode":"90020",
    "sg:province":"CA",
    "sg:tags":[
        "apartment"
    ],
    "wof:name":"Du Berry Apartments the",
    "wof:placetype":"venue"
},
  "geometry": {"coordinates":[-118.29499800000001,34.065399],"type":"Point"}
}