{
  "type": "Feature",
  "properties": {
    "addr:full":"3441 Mt Diablo Blvd Lafayette CA 94549",
    "addr:housenumber":"3441",
    "addr:postcode":"94549",
    "addr:street":"Mt Diablo Blvd",
    "iso:country":"US",
    "sg:address":"3441 Mt Diablo Blvd",
    "sg:city":"Lafayette",
    "sg:classifiers":[
        {
            "category":"Personal",
            "subcategory":"Beauty Salon",
            "type":"Services"
        },
        {
            "category":"Personal",
            "subcategory":"Skin Care",
            "type":"Services"
        }
    ],
    "sg:phone":"+1 925 299 1035",
    "sg:postcode":"94549",
    "sg:province":"CA",
    "wof:name":"Skin Solutions",
    "wof:placetype":"venue"
},
  "geometry": {"coordinates":[-122.112397,37.892891],"type":"Point"}
}