{
  "type": "Feature",
  "properties": {
    "addr:full":"350 State St Los Altos CA 94022",
    "addr:housenumber":"350",
    "addr:postcode":"94022",
    "addr:street":"State St",
    "iso:country":"US",
    "sg:address":"350 State St",
    "sg:city":"Los Altos",
    "sg:classifiers":[
        {
            "category":"Personal",
            "subcategory":"Beauty Salon",
            "type":"Services"
        }
    ],
    "sg:phone":"+1 650 948 2429",
    "sg:postcode":"94022",
    "sg:province":"CA",
    "sg:tags":[
        "manicuring"
    ],
    "wof:name":"Fabulous Nails & Skin Care",
    "wof:placetype":"venue"
},
  "geometry": {"coordinates":[-122.117947,37.37895],"type":"Point"}
}