{
  "type": "Feature",
  "properties": {
    "iso:country":"US",
    "sg:address":"7124 Radford Ave",
    "sg:city":"North Hollywood",
    "sg:classifiers":[
        {
            "category":"Mining & Drilling",
            "type":"Manufacturing & Wholesale Goods"
        }
    ],
    "sg:phone":"+1 818 764 4777",
    "sg:postcode":"91605",
    "sg:province":"CA",
    "sg:tags":[
        "stone",
        "cut",
        "dimension",
        "quarry",
        "mfg"
    ],
    "wof:name":"Marble Yard",
    "wof:placetype":"venue"
},
  "geometry": {"coordinates":[-118.392072,34.199168],"type":"Point"}
}