{
  "type": "Feature",
  "properties": {
    "addr:full":"5610 San Jacinto Rd Atascadero CA 93422",
    "addr:housenumber":"5610",
    "addr:postcode":"93422",
    "addr:street":"San Jacinto Rd",
    "iso:country":"US",
    "sg:address":"5610 San Jacinto Rd",
    "sg:city":"Atascadero",
    "sg:classifiers":[
        {
            "category":"Social Services",
            "subcategory":"Child Care",
            "type":"Services"
        }
    ],
    "sg:phone":"+1 805 466 2809",
    "sg:postcode":"93422",
    "sg:province":"CA",
    "wof:name":"Faye's Playhouse",
    "wof:placetype":"venue"
},
  "geometry": {"coordinates":[-120.67492300000001,35.497393],"type":"Point"}
}