{
  "type": "Feature",
  "properties": {
    "addr:full":"1526 Elm St El Cerrito CA 94530",
    "addr:housenumber":"1526",
    "addr:postcode":"94530",
    "addr:street":"Elm St",
    "iso:country":"US",
    "sg:address":"1526 Elm St",
    "sg:city":"El Cerrito",
    "sg:classifiers":[
        {
            "category":"Building & Trades",
            "subcategory":"Plumbing",
            "type":"Services"
        }
    ],
    "sg:phone":"+1 510 233 2529",
    "sg:postcode":"94530",
    "sg:province":"CA",
    "sg:website":"www.mount-everest-plumbing.com/",
    "wof:name":"Everest Plumbing",
    "wof:placetype":"venue"
},
  "geometry": {"coordinates":[-122.31098799999999,37.921298],"type":"Point"}
}