{
  "type": "Feature",
  "properties": {
    "iso:country":"US",
    "sg:address":"36211 Worthing Dr",
    "sg:city":"Newark",
    "sg:classifiers":[
        {
            "category":"Wholesale",
            "subcategory":"Sporting Goods",
            "type":"Manufacturing & Wholesale Goods"
        }
    ],
    "sg:phone":"+1 510 797 5882",
    "sg:postcode":"94560",
    "sg:province":"CA",
    "sg:tags":[
        "equipment",
        "pool",
        "swimming"
    ],
    "wof:name":"Able Pool",
    "wof:placetype":"venue"
},
  "geometry": {"coordinates":[-122.028728,37.552198],"type":"Point"}
}