{
  "type": "Feature",
  "properties": {
    "iso:country":"US",
    "sg:address":"3501 E South St",
    "sg:city":"Long Beach",
    "sg:classifiers":[
        {
            "category":"Fast Food",
            "type":"Food & Drink"
        },
        {
            "category":"Restaurant",
            "type":"Food & Drink"
        }
    ],
    "sg:phone":"+1 562 634 6152",
    "sg:postcode":"90805",
    "sg:province":"CA",
    "sg:tags":[
        "mexican"
    ],
    "sg:website":"www.deltaco.com",
    "wof:name":"Del Taco",
    "wof:placetype":"venue"
},
  "geometry": {"coordinates":[-118.151152,33.860213],"type":"Point"}
}