{
  "type": "Feature",
  "properties": {
    "iso:country":"US",
    "sg:address":"16500 Sherman Way",
    "sg:city":"Van Nuys",
    "sg:classifiers":[
        {
            "category":"Autos & Motor Vehicles",
            "subcategory":"Auto Supplies",
            "type":"Retail Goods"
        }
    ],
    "sg:phone":"+1 818 779 7865",
    "sg:postcode":"91406",
    "sg:province":"CA",
    "sg:tags":[
        "automobile",
        "parts"
    ],
    "wof:name":"Autozone",
    "wof:placetype":"venue"
},
  "geometry": {"coordinates":[-118.493482,34.201043],"type":"Point"}
}