{
  "type": "Feature",
  "properties": {
    "addr:full":"17080 Bear Valley Rd Victorville CA 92395",
    "addr:housenumber":"17080",
    "addr:postcode":"92395",
    "addr:street":"Bear Valley Rd",
    "iso:country":"US",
    "sg:address":"17080 Bear Valley Rd",
    "sg:city":"Victorville",
    "sg:classifiers":[
        {
            "category":"Restaurant",
            "type":"Food & Drink"
        }
    ],
    "sg:phone":"+1 760 843 3747",
    "sg:postcode":"92395",
    "sg:province":"CA",
    "wof:name":"Subway Sandwiches & Salads",
    "wof:placetype":"venue"
},
  "geometry": {"coordinates":[-117.29058999999999,34.47104],"type":"Point"}
}