{
  "type": "Feature",
  "properties": {
    "addr:full":"2842 Springdale Ln San Ramon CA 94583",
    "addr:housenumber":"2842",
    "addr:postcode":"94583",
    "addr:street":"Springdale Ln",
    "iso:country":"US",
    "sg:address":"2842 Springdale Ln",
    "sg:city":"San Ramon",
    "sg:classifiers":[
        {
            "category":"Utilities",
            "subcategory":"Telephone",
            "type":"Services"
        }
    ],
    "sg:phone":"+1 925 556 3400",
    "sg:postcode":"94583",
    "sg:province":"CA",
    "sg:tags":[
        "telecommunication"
    ],
    "sg:website":"www.choice-com.com",
    "wof:name":"Choice Communications",
    "wof:placetype":"venue"
},
  "geometry": {"coordinates":[-121.94941799999999,37.739343],"type":"Point"}
}