{
  "type": "Feature",
  "properties": {
    "addr:full":"23505 Crenshaw Blvd Torrance CA 90505",
    "addr:housenumber":"23505",
    "addr:postcode":"90505",
    "addr:street":"Crenshaw Blvd",
    "iso:country":"US",
    "sg:address":"23505 Crenshaw Blvd",
    "sg:city":"Torrance",
    "sg:classifiers":[
        {
            "category":"Professional",
            "subcategory":"Detective & Security Services",
            "type":"Services"
        }
    ],
    "sg:phone":"+1 310 539 3737",
    "sg:postcode":"90505",
    "sg:province":"CA",
    "sg:tags":[
        "guard",
        "patrol"
    ],
    "wof:name":"PRO-Tex Security Svc",
    "wof:placetype":"venue"
},
  "geometry": {"coordinates":[-118.328115,33.811333],"type":"Point"}
}