{
  "type": "Feature",
  "properties": {
    "iso:country":"US",
    "sg:address":"121 Emerson St",
    "sg:city":"Palo Alto",
    "sg:classifiers":[
        {
            "category":"Wholesale",
            "subcategory":"Medical Equipment & Supplies",
            "type":"Manufacturing & Wholesale Goods"
        }
    ],
    "sg:phone":"+1 650 321 4258",
    "sg:postcode":"94301",
    "sg:province":"CA",
    "sg:tags":[
        "laser",
        "diagnostic"
    ],
    "wof:name":"Gentec Inc",
    "wof:placetype":"venue"
},
  "geometry": {"coordinates":[-122.166752,37.447297],"type":"Point"}
}