{
  "type": "Feature",
  "properties": {
    "iso:country":"US",
    "sg:address":"1005 Jefferson St",
    "sg:city":"Napa",
    "sg:classifiers":[
        {
            "category":"Professional",
            "subcategory":"Accounting & Tax Preparation",
            "type":"Services"
        }
    ],
    "sg:phone":"+1 707 255 8704",
    "sg:postcode":"94559",
    "sg:province":"CA",
    "sg:tags":[
        "accountant"
    ],
    "wof:name":"Judy Parsons CPA",
    "wof:placetype":"venue"
},
  "geometry": {"coordinates":[-122.293272,38.298222],"type":"Point"}
}