{
  "type": "Feature",
  "properties": {
    "iso:country":"US",
    "sg:address":"315 Sutter Ave",
    "sg:city":"Modesto",
    "sg:classifiers":[
        {
            "category":"Personal",
            "subcategory":"Massage",
            "type":"Services"
        }
    ],
    "sg:phone":"+1 209 614 0299",
    "sg:postcode":"95351",
    "sg:province":"CA",
    "sg:website":"www.CaringTouchTherapy.com",
    "wof:name":"Caring Touch Therapy",
    "wof:placetype":"venue"
},
  "geometry": {"coordinates":[-121.011466,37.627233],"type":"Point"}
}