{
  "type": "Feature",
  "properties": {
    "addr:full":"1999 Harrison St Ste 1600 Oakland CA 94612",
    "addr:housenumber":"1999",
    "addr:postcode":"94612",
    "addr:street":"Harrison St Ste 1600",
    "iso:country":"US",
    "sg:address":"1999 Harrison St Ste 1600",
    "sg:city":"Oakland",
    "sg:classifiers":[
        {
            "category":"Professional",
            "subcategory":"Lawyer & Legal Services",
            "type":"Services"
        }
    ],
    "sg:phone":"+1 510 832 5411",
    "sg:postcode":"94612",
    "sg:province":"CA",
    "sg:tags":[
        "personal",
        "injury"
    ],
    "wof:name":"Gwilliam Ivary Chiosso Cavlli & Brwr-A Prfssnl Crp",
    "wof:placetype":"venue"
},
  "geometry": {"coordinates":[-122.264999,37.807899],"type":"Point"}
}