{
  "type": "Feature",
  "properties": {
    "addr:full":"4960 Olivehurst Ave Olivehurst CA 95961",
    "addr:postcode":"4960;ca 95961",
    "addr:street":"Olivehurst Ave",
    "iso:country":"US",
    "sg:address":"4960 Olivehurst Ave",
    "sg:city":"Olivehurst",
    "sg:classifiers":[
        {
            "category":"Autos & Motor Vehicles",
            "subcategory":"Fuel & Gas Station",
            "type":"Retail Goods"
        }
    ],
    "sg:phone":"+1 530 743 6447",
    "sg:postcode":"95961",
    "sg:province":"CA",
    "sg:tags":[
        "oil"
    ],
    "wof:name":"Lally's Gas & Food",
    "wof:placetype":"venue"
},
  "geometry": {"coordinates":[-121.551626,39.097368],"type":"Point"}
}