{
  "type": "Feature",
  "properties": {
    "addr:full":"720 S Sylvan St Anaheim CA 92804",
    "addr:housenumber":"720",
    "addr:postcode":"92804",
    "addr:street":"S Sylvan St",
    "iso:country":"US",
    "sg:address":"720 S Sylvan St",
    "sg:city":"Anaheim",
    "sg:classifiers":[
        {
            "category":"Real Estate",
            "subcategory":"Real Estate Operator",
            "type":"Services"
        }
    ],
    "sg:phone":"+1 714 828 6648",
    "sg:postcode":"92804",
    "sg:province":"CA",
    "sg:tags":[
        "property",
        "lessor"
    ],
    "wof:name":"William J McFadden",
    "wof:placetype":"venue"
},
  "geometry": {"coordinates":[-117.978894,33.821859],"type":"Point"}
}