{
  "type": "Feature",
  "properties": {
    "addr:full":"1900 Lincoln Blvd Santa Monica CA 90405",
    "addr:housenumber":"1900",
    "addr:postcode":"90405",
    "addr:street":"Lincoln Blvd",
    "iso:country":"US",
    "sg:address":"1900 Lincoln Blvd",
    "sg:city":"Santa Monica",
    "sg:classifiers":[
        {
            "category":"Retail",
            "subcategory":"Auto Repair",
            "type":"Services"
        }
    ],
    "sg:phone":"+1 310 829 1515",
    "sg:postcode":"90405",
    "sg:province":"CA",
    "sg:tags":[
        "repairing",
        "automobile"
    ],
    "wof:name":"A Motors",
    "wof:placetype":"venue"
},
  "geometry": {"coordinates":[-118.482158,34.011642],"type":"Point"}
}