{
  "type": "Feature",
  "properties": {
    "iso:country":"US",
    "sg:address":"8380 Melrose Ave",
    "sg:city":"Los Angeles",
    "sg:classifiers":[
        {
            "category":"Professional",
            "subcategory":"Business Services",
            "type":"Services"
        }
    ],
    "sg:phone":"+1 323 852 0646",
    "sg:postcode":"90069",
    "sg:province":"CA",
    "sg:tags":[
        "interior",
        "consultant",
        "design",
        "decorator"
    ],
    "wof:name":"Toni Sherman Interiors",
    "wof:placetype":"venue"
},
  "geometry": {"coordinates":[-118.372703,34.08357],"type":"Point"}
}