{
  "type": "Feature",
  "properties": {
    "iso:country":"US",
    "sg:address":"5021 San Vicente Blvd",
    "sg:city":"Los Angeles",
    "sg:classifiers":[
        {
            "category":"Organizations",
            "subcategory":"Religious Organization",
            "type":"Services"
        }
    ],
    "sg:phone":"+1 323 634 9585",
    "sg:postcode":"90019",
    "sg:province":"CA",
    "sg:tags":[
        "church"
    ],
    "wof:name":"Absolute Home Health Agency",
    "wof:placetype":"venue"
},
  "geometry": {"coordinates":[-118.345153,34.050721],"type":"Point"}
}