{
  "type": "Feature",
  "properties": {
    "iso:country":"US",
    "sg:address":"830 Cortland Ave",
    "sg:city":"San Francisco",
    "sg:classifiers":[
        {
            "category":"Restaurant",
            "type":"Food & Drink"
        }
    ],
    "sg:menulink":"http://www.allmenus.com/ca/san-francisco/81832-piqueos/menu/",
    "sg:phone":"+1 415 282 8812",
    "sg:postcode":"94110",
    "sg:province":"CA",
    "sg:tags":[
        "peruvian"
    ],
    "wof:name":"Piqueo's",
    "wof:placetype":"venue"
},
  "geometry": {"coordinates":[-122.41441,37.738942],"type":"Point"}
}