{
  "type": "Feature",
  "properties": {
    "iso:country":"US",
    "sg:address":"8539 Pratt Ave",
    "sg:city":"Durham",
    "sg:classifiers":[
        {
            "category":"Freight",
            "type":"Transportation"
        }
    ],
    "sg:phone":"+1 530 896 0625",
    "sg:postcode":"95938",
    "sg:province":"CA",
    "sg:tags":[
        "operator",
        "local",
        "trucking"
    ],
    "wof:name":"One More Delivery",
    "wof:placetype":"venue"
},
  "geometry": {"coordinates":[-121.815776,39.619628],"type":"Point"}
}