{
  "type": "Feature",
  "properties": {
    "iso:country":"US",
    "sg:address":"10911 Kinross Ave",
    "sg:city":"Los Angeles",
    "sg:classifiers":[
        {
            "category":"Personal",
            "subcategory":"Beauty Salon",
            "type":"Services"
        }
    ],
    "sg:phone":"+1 559 308 6780",
    "sg:postcode":"90024",
    "sg:province":"CA",
    "sg:tags":[
        "spa"
    ],
    "sg:website":"rmcosmetics.vpweb.com/About-Us.html",
    "wof:name":"Rm Cosmetics & Hair",
    "wof:placetype":"venue"
},
  "geometry": {"coordinates":[-118.446107,34.060504],"type":"Point"}
}