{
  "type": "Feature",
  "properties": {
    "iso:country":"US",
    "sg:address":"225 S Chevy Chase Dr",
    "sg:city":"Glendale",
    "sg:classifiers":[
        {
            "category":"Organizations",
            "subcategory":"Religious Organization",
            "type":"Services"
        }
    ],
    "sg:phone":"+1 818 242 5915",
    "sg:postcode":"91205",
    "sg:province":"CA",
    "sg:tags":[
        "church"
    ],
    "wof:name":"Chinese Faith Church",
    "wof:placetype":"venue"
},
  "geometry": {"coordinates":[-118.23967,34.144321],"type":"Point"}
}