{
  "type": "Feature",
  "properties": {
    "addr:full":"2851 Palo Alto Ave Clovis CA 93611",
    "addr:housenumber":"2851",
    "addr:postcode":"93611",
    "addr:street":"Palo Alto Ave",
    "iso:country":"US",
    "sg:address":"2851 Palo Alto Ave",
    "sg:city":"Clovis",
    "sg:classifiers":[
        {
            "category":"Education",
            "subcategory":"School",
            "type":"Public Place"
        }
    ],
    "sg:phone":"+1 559 323 4295",
    "sg:postcode":"93611",
    "sg:province":"CA",
    "wof:name":"Cedarwood Elementary School",
    "wof:placetype":"venue"
},
  "geometry": {"coordinates":[-119.66045,36.834105],"type":"Point"}
}