{
  "type": "Feature",
  "properties": {
    "iso:country":"US",
    "sg:address":"4131 Ball Rd",
    "sg:city":"Cypress",
    "sg:classifiers":[
        {
            "category":"Shopping",
            "subcategory":"Gifts & Souvenirs",
            "type":"Retail Goods"
        }
    ],
    "sg:phone":"+1 714 220 1113",
    "sg:postcode":"90630",
    "sg:province":"CA",
    "sg:tags":[
        "stationery",
        "shop",
        "card"
    ],
    "wof:name":"Kay's Korner Hallmark",
    "wof:placetype":"venue"
},
  "geometry": {"coordinates":[-118.05999799999999,33.817799],"type":"Point"}
}