{
  "type": "Feature",
  "properties": {
    "addr:full":"4070 W 3rd St Los Angeles CA 90020",
    "addr:housenumber":"4070",
    "addr:postcode":"90020",
    "addr:street":"W 3Rd St",
    "iso:country":"US",
    "sg:address":"4070 W 3rd St",
    "sg:city":"Los Angeles",
    "sg:classifiers":[
        {
            "category":"Recreation",
            "type":"Entertainment"
        },
        {
            "category":"Wholesale",
            "subcategory":"Electrical",
            "type":"Manufacturing & Wholesale Goods"
        }
    ],
    "sg:phone":"+1 213 384 4657",
    "sg:postcode":"90020",
    "sg:province":"CA",
    "sg:tags":[
        "amusement"
    ],
    "wof:name":"L A Laser Plus",
    "wof:placetype":"venue"
},
  "geometry": {"coordinates":[-118.30239400000001,34.06893],"type":"Point"}
}