{
  "type": "Feature",
  "properties": {
    "iso:country":"US",
    "sg:address":"1501 Huntington Dr",
    "sg:city":"Duarte",
    "sg:classifiers":[
        {
            "category":"Restaurant",
            "type":"Food & Drink"
        },
        {
            "category":"Retail",
            "subcategory":"Event Space",
            "type":"Services"
        }
    ],
    "sg:phone":"+1 626 358 6398",
    "sg:postcode":"91010",
    "sg:province":"CA",
    "sg:tags":[
        "banquet",
        "mexican",
        "hall",
        "reception",
        "facility"
    ],
    "wof:name":"Ranchero Mexican Food",
    "wof:placetype":"venue"
},
  "geometry": {"coordinates":[-117.97328899999999,34.139709],"type":"Point"}
}