{
  "type": "Feature",
  "properties": {
    "iso:country":"US",
    "sg:address":"1113 Adella Avenue",
    "sg:city":"Coronado",
    "sg:classifiers":[
        {
            "category":"Shopping",
            "subcategory":"Clothing, Apparel, & Fashions",
            "type":"Retail Goods"
        }
    ],
    "sg:phone":"+1 619 319 5858",
    "sg:postcode":"92118",
    "sg:province":"CA",
    "sg:tags":[
        "clothing",
        "women's"
    ],
    "sg:website":"www.BlueJeansandBikinis.com",
    "wof:name":"Blue Jeans and Bikinis",
    "wof:placetype":"venue"
},
  "geometry": {"coordinates":[-117.177164,32.682139],"type":"Point"}
}