{
  "type": "Feature",
  "properties": {
    "iso:country":"US",
    "sg:address":"819 Anita Ave",
    "sg:city":"Belmont",
    "sg:classifiers":[
        {
            "category":"Manufacturing",
            "subcategory":"Retail Goods",
            "type":"Manufacturing & Wholesale Goods"
        }
    ],
    "sg:phone":"+1 650 508 0138",
    "sg:postcode":"94002",
    "sg:province":"CA",
    "sg:tags":[
        "mfg",
        "identification",
        "seal"
    ],
    "wof:name":"Silver Rocket Inc",
    "wof:placetype":"venue"
},
  "geometry": {"coordinates":[-122.288337,37.527147],"type":"Point"}
}