{
  "type": "Feature",
  "properties": {
    "addr:full":"245 N Euclid Ave Ontario CA 91762",
    "addr:housenumber":"245",
    "addr:postcode":"91762",
    "addr:street":"N Euclid Ave",
    "iso:country":"US",
    "sg:address":"245 N Euclid Ave",
    "sg:city":"Ontario",
    "sg:classifiers":[
        {
            "category":"Shopping",
            "subcategory":"Clothing, Apparel, & Fashions",
            "type":"Retail Goods"
        }
    ],
    "sg:phone":"+1 909 984 8646",
    "sg:postcode":"91762",
    "sg:province":"CA",
    "sg:tags":[
        "men's",
        "clothing"
    ],
    "wof:name":"Big & Tall",
    "wof:placetype":"venue"
},
  "geometry": {"coordinates":[-117.651207,34.065103],"type":"Point"}
}