{
  "type": "Feature",
  "properties": {
    "addr:full":"2382 Faraday Ave Carlsbad CA 92008",
    "addr:housenumber":"2382",
    "addr:postcode":"92008",
    "addr:street":"Faraday Ave",
    "iso:country":"US",
    "sg:address":"2382 Faraday Ave",
    "sg:city":"Carlsbad",
    "sg:classifiers":[
        {
            "category":"Sports & Exercise",
            "subcategory":"Sports Center",
            "type":"Entertainment"
        }
    ],
    "sg:phone":"+1 760 804 1517",
    "sg:postcode":"92008",
    "sg:province":"CA",
    "sg:tags":[
        "manager",
        "promoter"
    ],
    "wof:name":"Connexions Sports",
    "wof:placetype":"venue"
},
  "geometry": {"coordinates":[-117.274058,33.136166],"type":"Point"}
}