{
  "type": "Feature",
  "properties": {
    "iso:country":"US",
    "sg:address":"6386 Cmt Marcial",
    "sg:city":"San Diego",
    "sg:classifiers":[
        {
            "category":"Wholesale",
            "subcategory":"Electrical",
            "type":"Manufacturing & Wholesale Goods"
        }
    ],
    "sg:phone":"+1 858 279 2245",
    "sg:postcode":"92111",
    "sg:province":"CA",
    "sg:tags":[
        "burglar",
        "alarm",
        "electronic",
        "system"
    ],
    "wof:name":"Dingers Aletrting Systems",
    "wof:placetype":"venue"
},
  "geometry": {"coordinates":[-117.182236,32.771384],"type":"Point"}
}