{
  "type": "Feature",
  "properties": {
    "addr:full":"508 N Kaweah Ave Exeter CA 93221",
    "addr:housenumber":"508",
    "addr:postcode":"93221",
    "addr:street":"N Kaweah Ave",
    "iso:country":"US",
    "sg:address":"508 N Kaweah Ave",
    "sg:city":"Exeter",
    "sg:classifiers":[
        {
            "category":"Banks & Credit Unions",
            "subcategory":"Bank",
            "type":"Services"
        }
    ],
    "sg:phone":"+1 559 592 3114",
    "sg:postcode":"93221",
    "sg:province":"CA",
    "sg:tags":[
        "loan",
        "real estate"
    ],
    "wof:name":"National City Mortgage",
    "wof:placetype":"venue"
},
  "geometry": {"coordinates":[-119.135842,36.302706],"type":"Point"}
}