{
  "type": "Feature",
  "properties": {
    "iso:country":"US",
    "sg:address":"14449 Titus St",
    "sg:city":"Panorama City",
    "sg:classifiers":[
        {
            "category":"Personal",
            "subcategory":"Beauty Salon",
            "type":"Services"
        }
    ],
    "sg:phone":"+1 818 994 2425",
    "sg:postcode":"91402",
    "sg:province":"CA",
    "wof:name":"D'Right Cut Hair & Nail Studio",
    "wof:placetype":"venue"
},
  "geometry": {"coordinates":[-118.448459,34.219838],"type":"Point"}
}