{
  "type": "Feature",
  "properties": {
    "iso:country":"US",
    "sg:address":"518 S Long Beach Blvd",
    "sg:city":"Compton",
    "sg:classifiers":[
        {
            "category":"Banks & Credit Unions",
            "subcategory":"Bank",
            "type":"Services"
        }
    ],
    "sg:phone":"+1 310 886 5807",
    "sg:postcode":"90221",
    "sg:province":"CA",
    "sg:website":"www.bankofamerica.com",
    "wof:name":"Bank of America",
    "wof:placetype":"venue"
},
  "geometry": {"coordinates":[-118.208,33.892101],"type":"Point"}
}