{
  "type": "Feature",
  "properties": {
    "addr:full":"42450 Blacow Rd Fremont CA 94539",
    "addr:postcode":"42450;94539",
    "addr:street":"Blacow Rd",
    "iso:country":"US",
    "sg:address":"42450 Blacow Rd",
    "sg:city":"Fremont",
    "sg:classifiers":[
        {
            "category":"Retail",
            "subcategory":"Auto Repair",
            "type":"Services"
        }
    ],
    "sg:phone":"+1 510 656 0490",
    "sg:postcode":"94539",
    "sg:province":"CA",
    "sg:tags":[
        "repairing",
        "automobile"
    ],
    "wof:name":"Fremont Automotive",
    "wof:placetype":"venue"
},
  "geometry": {"coordinates":[-121.950334,37.525397],"type":"Point"}
}