{
  "type": "Feature",
  "properties": {
    "iso:country":"US",
    "sg:address":"2950 E Nutwood Ave",
    "sg:city":"Fullerton",
    "sg:classifiers":[
        {
            "category":"Retail",
            "subcategory":"Car Wash",
            "type":"Services"
        }
    ],
    "sg:phone":"+1 714 528 0306",
    "sg:postcode":"92831",
    "sg:province":"CA",
    "wof:name":"University Car Wash",
    "wof:placetype":"venue"
},
  "geometry": {"coordinates":[-117.87841,33.877488],"type":"Point"}
}