{
  "type": "Feature",
  "properties": {
    "iso:country":"US",
    "sg:address":"11 El Camino Real",
    "sg:city":"Millbrae",
    "sg:classifiers":[
        {
            "category":"Personal",
            "subcategory":"Tattoo Parlor",
            "type":"Services"
        },
        {
            "category":"Personal",
            "subcategory":"Piercing",
            "type":"Services"
        }
    ],
    "sg:phone":"+1 650 259 7555",
    "sg:postcode":"94030",
    "sg:province":"CA",
    "wof:name":"Rubin's",
    "wof:placetype":"venue"
},
  "geometry": {"coordinates":[-122.38811800000001,37.599014],"type":"Point"}
}