{
  "type": "Feature",
  "properties": {
    "iso:country":"US",
    "sg:address":"3360 Grand Ave",
    "sg:city":"Oakland",
    "sg:classifiers":[
        {
            "category":"Restaurant",
            "type":"Food & Drink"
        }
    ],
    "sg:menulink":"http://www.allmenus.com/ca/oakland/74259-dominos-pizza/menu/",
    "sg:phone":"+1 510 839 1952",
    "sg:postcode":"94610",
    "sg:province":"CA",
    "sg:tags":[
        "american",
        "wing",
        "pizza"
    ],
    "wof:name":"Domino's Pizza",
    "wof:placetype":"venue"
},
  "geometry": {"coordinates":[-122.246624,37.813601],"type":"Point"}
}