{
  "type": "Feature",
  "properties": {
    "addr:full":"1309 S Harbor Blvd Fullerton CA 92832",
    "addr:housenumber":"1309",
    "addr:postcode":"92832",
    "addr:street":"S Harbor Blvd",
    "iso:country":"US",
    "sg:address":"1309 S Harbor Blvd",
    "sg:city":"Fullerton",
    "sg:classifiers":[
        {
            "category":"Shopping",
            "subcategory":"Florist",
            "type":"Retail Goods"
        }
    ],
    "sg:phone":"+1 714 449 9455",
    "sg:postcode":"92832",
    "sg:province":"CA",
    "wof:name":"Lilac Flowers & Gifts",
    "wof:placetype":"venue"
},
  "geometry": {"coordinates":[-117.924004,33.856201],"type":"Point"}
}