{
  "type": "Feature",
  "properties": {
    "addr:full":"1154 Granada Ave Salinas CA 93906",
    "addr:housenumber":"1154",
    "addr:postcode":"93906",
    "addr:street":"Granada Ave",
    "iso:country":"US",
    "sg:address":"1154 Granada Ave",
    "sg:city":"Salinas",
    "sg:classifiers":[
        {
            "category":"Building & Trades",
            "subcategory":"Landscaping Services",
            "type":"Services"
        }
    ],
    "sg:phone":"+1 831 424 1507",
    "sg:postcode":"93906",
    "sg:province":"CA",
    "sg:tags":[
        "lawn",
        "architect",
        "landscape"
    ],
    "wof:name":"Johns Ldscpg & Lawn Maint",
    "wof:placetype":"venue"
},
  "geometry": {"coordinates":[-121.64414600000001,36.694221],"type":"Point"}
}