{
  "type": "Feature",
  "properties": {
    "addr:full":"12510 Oak Knoll Rd Poway CA 92064",
    "addr:housenumber":"12510",
    "addr:postcode":"ca 92064",
    "addr:street":"Oak Knoll Rd",
    "iso:country":"US",
    "sg:address":"12510 Oak Knoll Rd",
    "sg:city":"Poway",
    "sg:classifiers":[
        {
            "category":"Shopping",
            "subcategory":"Gifts & Souvenirs",
            "type":"Retail Goods"
        }
    ],
    "sg:phone":"+1 858 679 5777",
    "sg:postcode":"92064",
    "sg:province":"CA",
    "wof:name":"Gifts From Heart",
    "wof:placetype":"venue"
},
  "geometry": {"coordinates":[-117.055727,32.950699],"type":"Point"}
}