{
  "type": "Feature",
  "properties": {
    "addr:full":"26353 Oak Plain Dr Santa Clarita CA 91321",
    "addr:housenumber":"26353",
    "addr:postcode":"91321",
    "addr:street":"Oak Plain Dr",
    "iso:country":"US",
    "sg:address":"26353 Oak Plain Dr",
    "sg:city":"Santa Clarita",
    "sg:classifiers":[
        {
            "category":"Professional",
            "subcategory":"Business Services",
            "type":"Services"
        }
    ],
    "sg:phone":"+1 661 251 8582",
    "sg:postcode":"91321",
    "sg:province":"CA",
    "sg:tags":[
        "interior",
        "consultant",
        "design",
        "decorator"
    ],
    "wof:name":"Design Renaissance",
    "wof:placetype":"venue"
},
  "geometry": {"coordinates":[-118.479444,34.401573],"type":"Point"}
}