{
  "type": "Feature",
  "properties": {
    "iso:country":"US",
    "sg:address":"2490 Mariner Sq Lp",
    "sg:city":"Alameda",
    "sg:classifiers":[
        {
            "category":"Professional",
            "subcategory":"Business Services",
            "type":"Services"
        }
    ],
    "sg:phone":"+1 510 769 9648",
    "sg:postcode":"94501",
    "sg:province":"CA",
    "sg:tags":[
        "information",
        "referral"
    ],
    "wof:name":"Allied Information & Svc Corp",
    "wof:placetype":"venue"
},
  "geometry": {"coordinates":[-122.279889,37.789219],"type":"Point"}
}