{
  "type": "Feature",
  "properties": {
    "iso:country":"US",
    "sg:address":"5011 Santa Monica Blvd",
    "sg:city":"Los Angeles",
    "sg:classifiers":[
        {
            "category":"Building & Trades",
            "subcategory":"Plumbing",
            "type":"Services"
        }
    ],
    "sg:phone":"+1 323 662 8325",
    "sg:postcode":"90029",
    "sg:province":"CA",
    "sg:tags":[
        "conditioning",
        "air",
        "system",
        "contractor"
    ],
    "wof:name":"C & T Svc Air Cond & Heating",
    "wof:placetype":"venue"
},
  "geometry": {"coordinates":[-118.298857,34.090907],"type":"Point"}
}