{
  "type": "Feature",
  "properties": {
    "iso:country":"US",
    "sg:address":"837 Industrial Dr",
    "sg:city":"Hollister",
    "sg:classifiers":[
        {
            "category":"Wholesale",
            "subcategory":"Office Equipment",
            "type":"Manufacturing & Wholesale Goods"
        },
        {
            "category":"Professional",
            "subcategory":"Printing & Photocopies",
            "type":"Services"
        },
        {
            "category":"Shopping",
            "subcategory":"Computers & Home Electronics",
            "type":"Retail Goods"
        }
    ],
    "sg:phone":"+1 831 637 1919",
    "sg:postcode":"95023",
    "sg:province":"CA",
    "sg:tags":[
        "scanning",
        "printer",
        "supply",
        "services-commercial",
        "lithographer",
        "plotting"
    ],
    "sg:website":"http://www.bencaputoprinting.com",
    "wof:name":"Ben Caputo Printing Co",
    "wof:placetype":"venue"
},
  "geometry": {"coordinates":[-121.391752,36.846571],"type":"Point"}
}