{
  "type": "Feature",
  "properties": {
    "addr:full":"9665 Wilshire Boulevard Beverly Hills CA 90212",
    "addr:housenumber":"9665",
    "addr:postcode":"90212",
    "addr:street":"Wilshire Boulevard",
    "iso:country":"US",
    "sg:address":"9665 Wilshire Boulevard",
    "sg:city":"Beverly Hills",
    "sg:classifiers":[
        {
            "category":"Professional",
            "subcategory":"Lawyer & Legal Services",
            "type":"Services"
        }
    ],
    "sg:phone":"+1 310 858 7888",
    "sg:postcode":"90212",
    "sg:province":"CA",
    "wof:name":"Holmes Henry --Atty--",
    "wof:placetype":"venue"
},
  "geometry": {"coordinates":[-118.404608,34.067144],"type":"Point"}
}