{
  "type": "Feature",
  "properties": {
    "iso:country":"US",
    "sg:address":"4880 San Juan Ave",
    "sg:city":"Fair Oaks",
    "sg:classifiers":[
        {
            "category":"Professional",
            "subcategory":"Advertising",
            "type":"Services"
        }
    ],
    "sg:phone":"+1 916 863 6245",
    "sg:postcode":"95628",
    "sg:province":"CA",
    "sg:tags":[
        "mailing",
        "shipping"
    ],
    "wof:name":"Mail Boxes Etc",
    "wof:placetype":"venue"
},
  "geometry": {"coordinates":[-121.29198,38.651938],"type":"Point"}
}