{
  "type": "Feature",
  "properties": {
    "iso:country":"US",
    "sg:address":"5400 Balboa Blvd",
    "sg:city":"Encino",
    "sg:classifiers":[
        {
            "category":"Shopping",
            "subcategory":"Optical Goods",
            "type":"Retail Goods"
        }
    ],
    "sg:phone":"+1 818 981 4754",
    "sg:postcode":"91316",
    "sg:province":"CA",
    "sg:tags":[
        "optician"
    ],
    "wof:name":"Rubio Optical Co",
    "wof:placetype":"venue"
},
  "geometry": {"coordinates":[-118.501092,34.170001],"type":"Point"}
}