{
  "type": "Feature",
  "properties": {
    "iso:country":"US",
    "sg:address":"516 E Tokay St",
    "sg:city":"Lodi",
    "sg:classifiers":[
        {
            "category":"Banks & Credit Unions",
            "subcategory":"Investment Brokerage",
            "type":"Services"
        }
    ],
    "sg:phone":"+1 209 333 1430",
    "sg:postcode":"95240",
    "sg:province":"CA",
    "sg:tags":[
        "trust"
    ],
    "wof:name":"Raymond R Blasingame Trust",
    "wof:placetype":"venue"
},
  "geometry": {"coordinates":[-121.262457,38.12694],"type":"Point"}
}