{
  "type": "Feature",
  "properties": {
    "addr:full":"754 Corvey Cir Galt CA 95632",
    "addr:housenumber":"754",
    "addr:postcode":"95632",
    "addr:street":"Corvey Cir",
    "iso:country":"US",
    "sg:address":"754 Corvey Cir",
    "sg:city":"Galt",
    "sg:classifiers":[
        {
            "category":"Shopping",
            "subcategory":"Bicycles & Sporting Goods",
            "type":"Retail Goods"
        }
    ],
    "sg:phone":"+1 209 745 3350",
    "sg:postcode":"95632",
    "sg:province":"CA",
    "wof:name":"Hunter Technical Support",
    "wof:placetype":"venue"
},
  "geometry": {"coordinates":[-121.30439,38.285696],"type":"Point"}
}