{
  "type": "Feature",
  "properties": {
    "addr:full":"112 Delano St Elverta CA 95626",
    "addr:housenumber":"112",
    "addr:postcode":"ca 95626",
    "addr:street":"Delano St",
    "iso:country":"US",
    "sg:address":"112 Delano St",
    "sg:city":"Elverta",
    "sg:classifiers":[
        {
            "category":"Place Of Worship",
            "subcategory":"Church",
            "type":"Public Place"
        },
        {
            "category":"Place Of Worship",
            "type":"Public Place"
        }
    ],
    "sg:phone":"+1 916 991 5545",
    "sg:postcode":"95626",
    "sg:province":"CA",
    "sg:tags":[
        "churches-baptist-general",
        "churches-baptist-southern",
        "churches-baptist"
    ],
    "wof:name":"First Baptist Church",
    "wof:placetype":"venue"
},
  "geometry": {"coordinates":[-121.466224,38.710018],"type":"Point"}
}