{
  "type": "Feature",
  "properties": {
    "addr:full":"1800 Merced st San Leandro CA 94577",
    "addr:housenumber":"1800",
    "addr:postcode":"94577",
    "addr:street":"Merced St",
    "iso:country":"US",
    "sg:address":"1800 Merced st",
    "sg:city":"San Leandro",
    "sg:classifiers":[
        {
            "category":"Personal",
            "type":"Services"
        },
        {
            "category":"Shopping",
            "type":"Retail Goods"
        }
    ],
    "sg:phone":"+1 510 895 8182",
    "sg:postcode":"94577",
    "sg:province":"CA",
    "sg:tags":[
        "home"
    ],
    "wof:name":"U S Superior Stone & Tile Inc",
    "wof:placetype":"venue"
},
  "geometry": {"coordinates":[-122.17295799999999,37.711952],"type":"Point"}
}