{
  "type": "Feature",
  "properties": {
    "addr:full":"5604 La Jolla Blvd. San Diego CA 92037",
    "addr:housenumber":"5604",
    "addr:postcode":"92037",
    "addr:street":"La Jolla Blvd.",
    "iso:country":"US",
    "sg:address":"5604 La Jolla Blvd.",
    "sg:city":"San Diego",
    "sg:classifiers":[
        {
            "category":"Personal",
            "subcategory":"Massage",
            "type":"Services"
        }
    ],
    "sg:phone":"+1 858 551 0425",
    "sg:postcode":"92037",
    "sg:province":"CA",
    "sg:website":"www.birdrockmassagetherapy.com",
    "wof:name":"Bird Rock Massage Therapy",
    "wof:placetype":"venue"
},
  "geometry": {"coordinates":[-117.26996699999999,32.813919],"type":"Point"}
}