{
  "type": "Feature",
  "properties": {
    "addr:full":"520 Main St Huntington Beach CA 92648",
    "addr:housenumber":"520",
    "addr:postcode":"92648",
    "addr:street":"Main St",
    "iso:country":"US",
    "sg:address":"520 Main St",
    "sg:city":"Huntington Beach",
    "sg:classifiers":[
        {
            "category":"Restaurant",
            "type":"Food & Drink"
        }
    ],
    "sg:phone":"+1 714 969 2148",
    "sg:postcode":"92648",
    "sg:province":"CA",
    "sg:tags":[
        "italian"
    ],
    "sg:website":"www.cucinaalessa.com/",
    "wof:name":"Cucina Alessa",
    "wof:placetype":"venue"
},
  "geometry": {"coordinates":[-117.998571,33.661742],"type":"Point"}
}