{
  "type": "Feature",
  "properties": {
    "addr:full":"2490 Blackpool Ln San Leandro CA 94577",
    "addr:housenumber":"2490",
    "addr:postcode":"94577",
    "addr:street":"Blackpool Ln",
    "iso:country":"US",
    "sg:address":"2490 Blackpool Ln",
    "sg:city":"San Leandro",
    "sg:classifiers":[
        {
            "category":"Wholesale",
            "subcategory":"Toys & Hobbies",
            "type":"Manufacturing & Wholesale Goods"
        }
    ],
    "sg:phone":"+1 510 614 2044",
    "sg:postcode":"94577",
    "sg:province":"CA",
    "wof:name":"Doll Room",
    "wof:placetype":"venue"
},
  "geometry": {"coordinates":[-122.14806900000001,37.716375],"type":"Point"}
}