{
  "type": "Feature",
  "properties": {
    "iso:country":"US",
    "sg:address":"Costco 2700 Park Ave",
    "sg:city":"Tustin",
    "sg:classifiers":[
        {
            "category":"Health Services",
            "subcategory":"Optometrist",
            "type":"Services"
        }
    ],
    "sg:phone":"+1 714 259 1530",
    "sg:postcode":"92782",
    "sg:province":"CA",
    "wof:name":"Barbara Villa, OD",
    "wof:placetype":"venue"
},
  "geometry": {"coordinates":[-117.823314,33.698304],"type":"Point"}
}