{
  "type": "Feature",
  "properties": {
    "addr:full":"1726 S Amphlett Blvd San Mateo CA 94402",
    "addr:housenumber":"1726",
    "addr:postcode":"94402",
    "addr:street":"S Amphlett Blvd",
    "iso:country":"US",
    "sg:address":"1726 S Amphlett Blvd",
    "sg:city":"San Mateo",
    "sg:classifiers":[
        {
            "category":"Retail",
            "subcategory":"Laundry & Dry Cleaning",
            "type":"Services"
        }
    ],
    "sg:phone":"+1 650 574 1384",
    "sg:postcode":"94402",
    "sg:province":"CA",
    "wof:name":"Primo Cobbler & Cleaners",
    "wof:placetype":"venue"
},
  "geometry": {"coordinates":[-122.30100299999999,37.557098],"type":"Point"}
}