{
  "type": "Feature",
  "properties": {
    "addr:full":"10438 Ojai Santa Paula Rd Ojai CA 93023",
    "addr:housenumber":"10438",
    "addr:postcode":"93023",
    "addr:street":"Ojai Santa Paula Rd",
    "iso:country":"US",
    "sg:address":"10438 Ojai Santa Paula Rd",
    "sg:city":"Ojai",
    "sg:classifiers":[
        {
            "category":"Retail",
            "subcategory":"Animal Services",
            "type":"Services"
        }
    ],
    "sg:phone":"+1 805 646 2204",
    "sg:postcode":"93023",
    "sg:province":"CA",
    "wof:name":"Scott Weis Cutting Horses",
    "wof:placetype":"venue"
},
  "geometry": {"coordinates":[-119.16345200000001,34.436731],"type":"Point"}
}