{
  "type": "Feature",
  "properties": {
    "addr:full":"34946 Rd 192 Woodlake CA 93286",
    "addr:postcode":"34946;93286",
    "addr:street":"Rd 192",
    "iso:country":"US",
    "sg:address":"34946 Rd 192",
    "sg:city":"Woodlake",
    "sg:classifiers":[
        {
            "category":"Farming",
            "subcategory":"Farm",
            "type":"Manufacturing & Wholesale Goods"
        }
    ],
    "sg:phone":"+1 559 564 5004",
    "sg:postcode":"93286",
    "sg:province":"CA",
    "wof:name":"Griffith Farms",
    "wof:placetype":"venue"
},
  "geometry": {"coordinates":[-119.14353300000001,36.416732],"type":"Point"}
}