{
  "type": "Feature",
  "properties": {
    "iso:country":"US",
    "sg:address":"25225 Pacific St",
    "sg:city":"San Bernardino",
    "sg:classifiers":[
        {
            "category":"Shopping",
            "subcategory":"Beauty & Cosmetics",
            "type":"Retail Goods"
        }
    ],
    "sg:phone":"+1 909 855 6711",
    "sg:postcode":"92404",
    "sg:province":"CA",
    "sg:tags":[
        "surgical",
        "appliance"
    ],
    "wof:name":"Eyes Of The Heart Self Help",
    "wof:placetype":"venue"
},
  "geometry": {"coordinates":[-117.25291300000001,34.128542],"type":"Point"}
}