{
  "type": "Feature",
  "properties": {
    "iso:country":"US",
    "sg:address":"1660 Hudson Ave",
    "sg:city":"San Francisco",
    "sg:classifiers":[
        {
            "category":"Home & Garden",
            "subcategory":"Home Furnishings",
            "type":"Retail Goods"
        }
    ],
    "sg:phone":"+1 415 285 9888",
    "sg:postcode":"94124",
    "sg:province":"CA",
    "sg:tags":[
        "bedspread"
    ],
    "wof:name":"Frank's Trading Co",
    "wof:placetype":"venue"
},
  "geometry": {"coordinates":[-122.38951,37.740743],"type":"Point"}
}