{
  "type": "Feature",
  "properties": {
    "addr:full":"20832 Dearborn St Chatsworth CA 91311",
    "addr:housenumber":"20832",
    "addr:postcode":"91311",
    "addr:street":"Dearborn St",
    "iso:country":"US",
    "sg:address":"20832 Dearborn St",
    "sg:city":"Chatsworth",
    "sg:classifiers":[
        {
            "category":"Professional",
            "subcategory":"Testing Lab",
            "type":"Services"
        }
    ],
    "sg:phone":"+1 818 882 5622",
    "sg:postcode":"91311",
    "sg:province":"CA",
    "sg:tags":[
        "laboratory"
    ],
    "wof:name":"Northridge Laboratories",
    "wof:placetype":"venue"
},
  "geometry": {"coordinates":[-118.58725099999999,34.23725],"type":"Point"}
}