{
  "type": "Feature",
  "properties": {
    "iso:country":"US",
    "sg:address":"322 W el Norte Pkwy",
    "sg:city":"Escondido",
    "sg:classifiers":[
        {
            "category":"Professional",
            "type":"Services"
        }
    ],
    "sg:phone":"+1 760 432 0557",
    "sg:postcode":"92026",
    "sg:province":"CA",
    "wof:name":"Park Hyunsoo",
    "wof:placetype":"venue"
},
  "geometry": {"coordinates":[-117.094334,33.140553],"type":"Point"}
}