{
  "type": "Feature",
  "properties": {
    "addr:full":"1021 N Hacienda Blvd La Puente CA 91744",
    "addr:housenumber":"1021",
    "addr:postcode":"91744",
    "addr:street":"N Hacienda Blvd",
    "iso:country":"US",
    "sg:address":"1021 N Hacienda Blvd",
    "sg:city":"La Puente",
    "sg:classifiers":[
        {
            "category":"Autos & Motor Vehicles",
            "subcategory":"Auto Supplies",
            "type":"Retail Goods"
        }
    ],
    "sg:phone":"+1 626 330 3367",
    "sg:postcode":"91744",
    "sg:province":"CA",
    "sg:tags":[
        "tire"
    ],
    "wof:name":"Firestone Tire & Svc Ctr",
    "wof:placetype":"venue"
},
  "geometry": {"coordinates":[-117.949912,34.038007],"type":"Point"}
}