{
  "type": "Feature",
  "properties": {
    "iso:country":"US",
    "sg:address":"1441 W Palo Alto Ave",
    "sg:city":"Fresno",
    "sg:classifiers":[
        {
            "category":"Building & Trades",
            "subcategory":"Landscaping Services",
            "type":"Services"
        }
    ],
    "sg:phone":"+1 559 435 0894",
    "sg:postcode":"93711",
    "sg:province":"CA",
    "sg:tags":[
        "lawn",
        "garden",
        "provides"
    ],
    "wof:name":"San Joaquin Valley Ldscp Maint",
    "wof:placetype":"venue"
},
  "geometry": {"coordinates":[-119.81874500000001,36.833196],"type":"Point"}
}