{
  "type": "Feature",
  "properties": {
    "addr:full":"3208 Honolulu Ave La Crescenta CA 91214",
    "addr:housenumber":"3208",
    "addr:postcode":"91214",
    "addr:street":"Honolulu Ave",
    "iso:country":"US",
    "sg:address":"3208 Honolulu Ave",
    "sg:city":"La Crescenta",
    "sg:classifiers":[
        {
            "category":"Retail",
            "subcategory":"Laundry & Dry Cleaning",
            "type":"Services"
        }
    ],
    "sg:phone":"+1 818 957 5419",
    "sg:postcode":"91214",
    "sg:province":"CA",
    "wof:name":"Blossom Hills",
    "wof:placetype":"venue"
},
  "geometry": {"coordinates":[-118.24900100000001,34.2211],"type":"Point"}
}