{
  "type": "Feature",
  "properties": {
    "addr:full":"4910 Van Nuys Blvd Ste 303 Sherman Oaks CA 91403",
    "addr:housenumber":"4910",
    "addr:postcode":"91403",
    "addr:street":"Van Nuys Blvd Ste 303",
    "iso:country":"US",
    "sg:address":"4910 Van Nuys Blvd Ste 303",
    "sg:city":"Sherman Oaks",
    "sg:classifiers":[
        {
            "category":"Health Services",
            "subcategory":"Doctor",
            "type":"Services"
        }
    ],
    "sg:phone":"+1 818 789 8848",
    "sg:postcode":"91403",
    "sg:province":"CA",
    "wof:name":"Levy Joshua MD",
    "wof:placetype":"venue"
},
  "geometry": {"coordinates":[-118.44899700000001,34.159599],"type":"Point"}
}