{
  "type": "Feature",
  "properties": {
    "addr:full":"10807 Jersey Blvd Rancho Cucamonga CA 91730",
    "addr:housenumber":"10807",
    "addr:postcode":"91730",
    "addr:street":"Jersey Blvd",
    "iso:country":"US",
    "sg:address":"10807 Jersey Blvd",
    "sg:city":"Rancho Cucamonga",
    "sg:classifiers":[
        {
            "category":"Freight",
            "type":"Transportation"
        }
    ],
    "sg:phone":"+1 909 758 5151",
    "sg:postcode":"91730",
    "sg:province":"CA",
    "wof:name":"Estenson Logistics LLC",
    "wof:placetype":"venue"
},
  "geometry": {"coordinates":[-117.566862,34.094551],"type":"Point"}
}