{
  "type": "Feature",
  "properties": {
    "addr:full":"50 San Miguel Ave Salinas CA 93901",
    "addr:housenumber":"50",
    "addr:postcode":"93901",
    "addr:street":"San Miguel Ave",
    "iso:country":"US",
    "sg:address":"50 San Miguel Ave",
    "sg:city":"Salinas",
    "sg:classifiers":[
        {
            "category":"Personal",
            "subcategory":"Beauty Salon",
            "type":"Services"
        }
    ],
    "sg:phone":"+1 831 757 8841",
    "sg:postcode":"93901",
    "sg:province":"CA",
    "wof:name":"Cutting Co",
    "wof:placetype":"venue"
},
  "geometry": {"coordinates":[-121.657292,36.6593],"type":"Point"}
}