{
  "type": "Feature",
  "properties": {
    "addr:full":"750 E Main St Santa Paula CA 93060",
    "addr:housenumber":"750",
    "addr:postcode":"93060",
    "addr:street":"E Main St",
    "iso:country":"US",
    "sg:address":"750 E Main St",
    "sg:city":"Santa Paula",
    "sg:classifiers":[
        {
            "category":"Real Estate",
            "subcategory":"Real Estate Services",
            "type":"Services"
        }
    ],
    "sg:phone":"+1 805 654 8274",
    "sg:postcode":"93060",
    "sg:province":"CA",
    "sg:tags":[
        "management",
        "property"
    ],
    "sg:website":"www.century21.com",
    "wof:name":"Century 21 Buena Vista",
    "wof:placetype":"venue"
},
  "geometry": {"coordinates":[-119.472973,34.352321],"type":"Point"}
}