{
  "type": "Feature",
  "properties": {
    "iso:country":"US",
    "sg:address":"3524 San Fernando Trl",
    "sg:city":"Frazier Park",
    "sg:classifiers":[
        {
            "category":"Professional",
            "subcategory":"Computer Services",
            "type":"Services"
        }
    ],
    "sg:phone":"+1 661 245 3173",
    "sg:postcode":"93225",
    "sg:province":"CA",
    "sg:tags":[
        "consultant"
    ],
    "wof:name":"Graphic Tech",
    "wof:placetype":"venue"
},
  "geometry": {"coordinates":[-118.945424,34.825349],"type":"Point"}
}