{
  "type": "Feature",
  "properties": {
    "addr:full":"33 Bartlett St San Francisco CA 94110",
    "addr:housenumber":"33",
    "addr:postcode":"94110",
    "addr:street":"Bartlett St",
    "iso:country":"US",
    "sg:address":"33 Bartlett St",
    "sg:city":"San Francisco",
    "sg:classifiers":[
        {
            "category":"Wholesale",
            "subcategory":"Machinery & Supplies",
            "type":"Manufacturing & Wholesale Goods"
        }
    ],
    "sg:phone":"+1 415 282 3131",
    "sg:postcode":"94110",
    "sg:province":"CA",
    "sg:tags":[
        "janitor"
    ],
    "wof:name":"Santora Sales Janitorial",
    "wof:placetype":"venue"
},
  "geometry": {"coordinates":[-122.41982299999999,37.755894],"type":"Point"}
}