{
  "type": "Feature",
  "properties": {
    "iso:country":"US",
    "sg:address":"275 E 9th St",
    "sg:city":"San Bernardino",
    "sg:classifiers":[
        {
            "category":"Shopping",
            "subcategory":"Tobacco",
            "type":"Retail Goods"
        }
    ],
    "sg:phone":"+1 909 885 4580",
    "sg:postcode":"92410",
    "sg:province":"CA",
    "sg:tags":[
        "cigarette",
        "cigar",
        "dealer"
    ],
    "wof:name":"Smoke Shop Plus Two",
    "wof:placetype":"venue"
},
  "geometry": {"coordinates":[-117.280432,34.115733],"type":"Point"}
}