{
  "type": "Feature",
  "properties": {
    "iso:country":"US",
    "sg:address":"1330 N Kraemer Blvd",
    "sg:city":"Anaheim",
    "sg:classifiers":[
        {
            "category":"Manufacturing",
            "subcategory":"Metals",
            "type":"Manufacturing & Wholesale Goods"
        }
    ],
    "sg:phone":"+1 714 630 3111",
    "sg:postcode":"92806",
    "sg:province":"CA",
    "sg:tags":[
        "fabricator",
        "aluminum"
    ],
    "sg:website":"www.anaheimextrude.com",
    "wof:name":"Anaheim Extrusion Co Inc",
    "wof:placetype":"venue"
},
  "geometry": {"coordinates":[-117.860272,33.859474],"type":"Point"}
}