{
  "type": "Feature",
  "properties": {
    "addr:full":"8902 Gowdy Ave San Diego CA 92123",
    "addr:housenumber":"8902",
    "addr:postcode":"92123",
    "addr:street":"Gowdy Ave",
    "iso:country":"US",
    "sg:address":"8902 Gowdy Ave",
    "sg:city":"San Diego",
    "sg:classifiers":[
        {
            "category":"Professional",
            "subcategory":"Management & Consulting",
            "type":"Services"
        },
        {
            "category":"Wholesale",
            "subcategory":"Chemicals & Plastics",
            "type":"Manufacturing & Wholesale Goods"
        }
    ],
    "sg:phone":"+1 858 571 1676",
    "sg:postcode":"92123",
    "sg:province":"CA",
    "sg:tags":[
        "home",
        "demonstration"
    ],
    "wof:name":"Amway Distributors",
    "wof:placetype":"venue"
},
  "geometry": {"coordinates":[-117.14182599999999,32.794663],"type":"Point"}
}