{
  "type": "Feature",
  "properties": {
    "addr:full":"1432 E 25th St Los Angeles CA 90011",
    "addr:housenumber":"1432",
    "addr:postcode":"90011",
    "addr:street":"E 25Th St",
    "iso:country":"US",
    "sg:address":"1432 E 25th St",
    "sg:city":"Los Angeles",
    "sg:classifiers":[
        {
            "category":"Organizations",
            "subcategory":"Religious Organization",
            "type":"Services"
        }
    ],
    "sg:phone":"+1 323 231 1813",
    "sg:postcode":"90011",
    "sg:province":"CA",
    "sg:tags":[
        "church"
    ],
    "wof:name":"House Of Prayer UHC Of A",
    "wof:placetype":"venue"
},
  "geometry": {"coordinates":[-118.249117,34.017262],"type":"Point"}
}