{
  "type": "Feature",
  "properties": {
    "addr:full":"10448 McVine Ave Sunland CA 91040",
    "addr:housenumber":"10448",
    "addr:postcode":"91040",
    "addr:street":"Mcvine Ave",
    "iso:country":"US",
    "sg:address":"10448 McVine Ave",
    "sg:city":"Sunland",
    "sg:classifiers":[
        {
            "category":"Manufacturing",
            "subcategory":"Tools & Machinery",
            "type":"Manufacturing & Wholesale Goods"
        }
    ],
    "sg:phone":"+1 818 951 9517",
    "sg:postcode":"91040",
    "sg:province":"CA",
    "sg:tags":[
        "equipment",
        "assembly",
        "electronic",
        "mfg"
    ],
    "wof:name":"West Valley Sales & Service",
    "wof:placetype":"venue"
},
  "geometry": {"coordinates":[-118.311379,34.257842],"type":"Point"}
}