{
  "type": "Feature",
  "properties": {
    "iso:country":"US",
    "sg:address":"3558 Agate Dr",
    "sg:city":"Santa Clara",
    "sg:classifiers":[
        {
            "category":"Insurance",
            "subcategory":"Insurance Agent",
            "type":"Services"
        }
    ],
    "sg:phone":"+1 408 984 6792",
    "sg:postcode":"95051",
    "sg:province":"CA",
    "wof:name":"Delbert Benson Insurance",
    "wof:placetype":"venue"
},
  "geometry": {"coordinates":[-121.993501,37.369605],"type":"Point"}
}