{
  "type": "Feature",
  "properties": {
    "addr:full":"3 Hamilton Dr Novato CA 94949",
    "addr:housenumber":"3",
    "addr:postcode":"94949",
    "addr:street":"Hamilton Dr",
    "iso:country":"US",
    "sg:address":"3 Hamilton Dr",
    "sg:city":"Novato",
    "sg:classifiers":[
        {
            "category":"Insurance",
            "subcategory":"Insurance Agent",
            "type":"Services"
        }
    ],
    "sg:phone":"+1 415 884 7400",
    "sg:postcode":"94949",
    "sg:province":"CA",
    "wof:name":"Brown & Brown Insurance",
    "wof:placetype":"venue"
},
  "geometry": {"coordinates":[-122.536125,38.070015],"type":"Point"}
}