{
  "type": "Feature",
  "properties": {
    "addr:full":"1275 Churn Creek Rd Redding CA 96003",
    "addr:housenumber":"1275",
    "addr:postcode":"96003",
    "addr:street":"Churn Creek Rd",
    "iso:country":"US",
    "sg:address":"1275 Churn Creek Rd",
    "sg:city":"Redding",
    "sg:classifiers":[
        {
            "category":"Autos & Motor Vehicles",
            "subcategory":"Fuel & Gas Station",
            "type":"Retail Goods"
        }
    ],
    "sg:phone":"+1 530 223 1271",
    "sg:postcode":"96003",
    "sg:province":"CA",
    "sg:tags":[
        "oil"
    ],
    "wof:name":"Ballpark 76",
    "wof:placetype":"venue"
},
  "geometry": {"coordinates":[-122.35099599999999,40.589033],"type":"Point"}
}