{
  "type": "Feature",
  "properties": {
    "addr:full":"230 Gellert Dr San Francisco CA 94132",
    "addr:housenumber":"230",
    "addr:postcode":"94132",
    "addr:street":"Gellert Dr",
    "iso:country":"US",
    "sg:address":"230 Gellert Dr",
    "sg:city":"San Francisco",
    "sg:classifiers":[
        {
            "category":"Wholesale",
            "subcategory":"Hardware",
            "type":"Manufacturing & Wholesale Goods"
        }
    ],
    "sg:phone":"+1 415 731 5843",
    "sg:postcode":"94132",
    "sg:province":"CA",
    "sg:tags":[
        "plumbing",
        "industrial",
        "exporter",
        "supply"
    ],
    "wof:name":"Henry J Frankel",
    "wof:placetype":"venue"
},
  "geometry": {"coordinates":[-122.493126,37.731936],"type":"Point"}
}