{
  "type": "Feature",
  "properties": {
    "addr:full":"8317 Main St Mokelumne Hill CA 95245",
    "addr:housenumber":"8317",
    "addr:postcode":"95245",
    "addr:street":"Main St",
    "iso:country":"US",
    "sg:address":"8317 Main St",
    "sg:city":"Mokelumne Hill",
    "sg:classifiers":[
        {
            "category":"Shopping",
            "subcategory":"Gifts & Souvenirs",
            "type":"Retail Goods"
        }
    ],
    "sg:phone":"+1 209 286 1488",
    "sg:postcode":"95245",
    "sg:province":"CA",
    "sg:tags":[
        "shop"
    ],
    "wof:name":"Keskydee Collections",
    "wof:placetype":"venue"
},
  "geometry": {"coordinates":[-120.705809,38.302014],"type":"Point"}
}