{
  "type": "Feature",
  "properties": {
    "addr:full":"9428 Eton Ave Chatsworth CA 91311",
    "addr:housenumber":"9428",
    "addr:postcode":"91311",
    "addr:street":"Eton Ave",
    "iso:country":"US",
    "sg:address":"9428 Eton Ave",
    "sg:city":"Chatsworth",
    "sg:classifiers":[
        {
            "category":"Wholesale",
            "subcategory":"Apparel",
            "type":"Manufacturing & Wholesale Goods"
        },
        {
            "category":"Shopping",
            "subcategory":"Clothing, Apparel, & Fashions",
            "type":"Retail Goods"
        }
    ],
    "sg:phone":"+1 818 998 4387",
    "sg:postcode":"91311",
    "sg:province":"CA",
    "sg:tags":[
        "fur",
        "business"
    ],
    "wof:name":"Dicker & Dicker-Beverly Hills",
    "wof:placetype":"venue"
},
  "geometry": {"coordinates":[-118.59594300000001,34.241184],"type":"Point"}
}