{
  "type": "Feature",
  "properties": {
    "addr:full":"18966 Jayhawk Dr Penn Valley CA 95946",
    "addr:postcode":"18966;95946",
    "addr:street":"Jayhawk Dr",
    "iso:country":"US",
    "sg:address":"18966 Jayhawk Dr",
    "sg:city":"Penn Valley",
    "sg:classifiers":[
        {
            "category":"Professional",
            "type":"Services"
        }
    ],
    "sg:phone":"+1 530 432 8139",
    "sg:postcode":"95946",
    "sg:province":"CA",
    "wof:name":"Netlink",
    "wof:placetype":"venue"
},
  "geometry": {"coordinates":[-121.199111,39.230367],"type":"Point"}
}