{
  "type": "Feature",
  "properties": {
    "addr:full":"116 E 25th Ave San Mateo CA 94403",
    "addr:housenumber":"116",
    "addr:postcode":"94403",
    "addr:street":"E 25Th Ave",
    "iso:country":"US",
    "sg:address":"116 E 25th Ave",
    "sg:city":"San Mateo",
    "sg:classifiers":[
        {
            "category":"Manufacturing",
            "subcategory":"Printing",
            "type":"Manufacturing & Wholesale Goods"
        }
    ],
    "sg:phone":"+1 650 358 0229",
    "sg:postcode":"94403",
    "sg:province":"CA",
    "sg:tags":[
        "commercial"
    ],
    "wof:name":"Visual Impressions Printing",
    "wof:placetype":"venue"
},
  "geometry": {"coordinates":[-122.304222,37.545449],"type":"Point"}
}