{
  "type": "Feature",
  "properties": {
    "addr:full":"16129 Cohasset St Van Nuys CA 91406",
    "addr:postcode":"16129;91406",
    "addr:street":"St",
    "iso:country":"US",
    "sg:address":"16129 Cohasset St",
    "sg:city":"Van Nuys",
    "sg:classifiers":[
        {
            "category":"Shopping",
            "subcategory":"Pharmacy",
            "type":"Retail Goods"
        }
    ],
    "sg:phone":"+1 818 782 8100",
    "sg:postcode":"91406",
    "sg:province":"CA",
    "wof:name":"North American Pharmacy",
    "wof:placetype":"venue"
},
  "geometry": {"coordinates":[-118.485359,34.206694],"type":"Point"}
}