{
  "type": "Feature",
  "properties": {
    "addr:full":"287 Water St Santa Cruz CA 95060",
    "addr:housenumber":"287",
    "addr:postcode":"95060",
    "addr:street":"Water St",
    "iso:country":"US",
    "sg:address":"287 Water St",
    "sg:city":"Santa Cruz",
    "sg:classifiers":[
        {
            "category":"Insurance",
            "subcategory":"Hazard Insurance",
            "type":"Services"
        }
    ],
    "sg:phone":"+1 831 425 1180",
    "sg:postcode":"95060",
    "sg:province":"CA",
    "sg:tags":[
        "notary",
        "bond"
    ],
    "sg:website":"www.santacruzbailbonds.com",
    "wof:name":"Santa Cruz Bail Bonds",
    "wof:placetype":"venue"
},
  "geometry": {"coordinates":[-122.023003,36.979198],"type":"Point"}
}