{
  "type": "Feature",
  "properties": {
    "addr:full":"226 Airport Pkwy San Jose CA 95110",
    "addr:housenumber":"226",
    "addr:postcode":"95110",
    "addr:street":"Airport Pkwy",
    "iso:country":"US",
    "sg:address":"226 Airport Pkwy",
    "sg:city":"San Jose",
    "sg:classifiers":[
        {
            "category":"Insurance",
            "subcategory":"Title Insurance",
            "type":"Services"
        }
    ],
    "sg:phone":"+1 408 501 0350",
    "sg:postcode":"95110",
    "sg:province":"CA",
    "wof:name":"Fidelity National Financial",
    "wof:placetype":"venue"
},
  "geometry": {"coordinates":[-121.92207000000001,37.369652],"type":"Point"}
}