{
  "type": "Feature",
  "properties": {
    "addr:full":"45911 Monroe St Indio CA 92201",
    "addr:housenumber":"45911",
    "addr:postcode":"92201",
    "addr:street":"Monroe St",
    "iso:country":"US",
    "sg:address":"45911 Monroe St",
    "sg:city":"Indio",
    "sg:classifiers":[
        {
            "category":"Personal",
            "subcategory":"Beauty Salon",
            "type":"Services"
        }
    ],
    "sg:phone":"+1 760 775 5070",
    "sg:postcode":"92201",
    "sg:province":"CA",
    "wof:name":"Lucy's Beauty Salon",
    "wof:placetype":"venue"
},
  "geometry": {"coordinates":[-116.233823,33.715095],"type":"Point"}
}