{
  "type": "Feature",
  "properties": {
    "addr:full":"960 N San Antonio Rd Los Altos CA 94022",
    "addr:housenumber":"960",
    "addr:postcode":"94022",
    "addr:street":"N San Antonio Rd",
    "iso:country":"US",
    "sg:address":"960 N San Antonio Rd",
    "sg:city":"Los Altos",
    "sg:classifiers":[
        {
            "category":"Arts & Performance",
            "subcategory":"Theater",
            "type":"Entertainment"
        }
    ],
    "sg:phone":"+1 650 917 0430",
    "sg:postcode":"94022",
    "sg:province":"CA",
    "sg:tags":[
        "talent",
        "agency",
        "casting"
    ],
    "wof:name":"APC Talent",
    "wof:placetype":"venue"
},
  "geometry": {"coordinates":[-122.114266,37.399165],"type":"Point"}
}