{
  "type": "Feature",
  "properties": {
    "addr:full":"3223 Pentland Ct San Jose CA 95148",
    "addr:housenumber":"3223",
    "addr:postcode":"95148",
    "addr:street":"Pentland Ct",
    "iso:country":"US",
    "sg:address":"3223 Pentland Ct",
    "sg:city":"San Jose",
    "sg:classifiers":[
        {
            "category":"Building & Trades",
            "subcategory":"Construction",
            "type":"Services"
        }
    ],
    "sg:phone":"+1 408 594 0976",
    "sg:postcode":"95148",
    "sg:province":"CA",
    "sg:tags":[
        "contractor"
    ],
    "wof:name":"Tom Flores Drywall",
    "wof:placetype":"venue"
},
  "geometry": {"coordinates":[-121.800665,37.313884],"type":"Point"}
}