{
  "type": "Feature",
  "properties": {
    "addr:full":"3941 Austin Rd Brawley CA 92227",
    "addr:housenumber":"3941",
    "addr:postcode":"92227",
    "addr:street":"Austin Rd",
    "iso:country":"US",
    "sg:address":"3941 Austin Rd",
    "sg:city":"Brawley",
    "sg:phone":"+1 760 351 1982",
    "sg:postcode":"92227",
    "sg:province":"CA",
    "sg:tags":[
        "vegetable",
        "wholesale",
        "grows"
    ],
    "wof:name":"Jack Blue Nursery",
    "wof:placetype":"venue"
},
  "geometry": {"coordinates":[-115.57444599999999,32.945301],"type":"Point"}
}