{
  "type": "Feature",
  "properties": {
    "addr:full":"31140 Danelaw Ave Redlands CA 92373",
    "addr:postcode":"31140;92373",
    "addr:street":"Danelaw Ave",
    "iso:country":"US",
    "sg:address":"31140 Danelaw Ave",
    "sg:city":"Redlands",
    "sg:classifiers":[
        {
            "category":"Autos & Motor Vehicles",
            "subcategory":"Automobile Sales",
            "type":"Retail Goods"
        }
    ],
    "sg:phone":"+1 909 239 0040",
    "sg:postcode":"92373",
    "sg:province":"CA",
    "sg:tags":[
        "car",
        "dealer"
    ],
    "wof:name":"All Auto Sales",
    "wof:placetype":"venue"
},
  "geometry": {"coordinates":[-117.123808,34.017523],"type":"Point"}
}