{
  "type": "Feature",
  "properties": {
    "iso:country":"US",
    "sg:address":"1112 Truxtun Ave",
    "sg:city":"Bakersfield",
    "sg:classifiers":[
        {
            "category":"Professional",
            "subcategory":"Lawyer & Legal Services",
            "type":"Services"
        }
    ],
    "sg:phone":"+1 661 327 0676",
    "sg:postcode":"93301",
    "sg:province":"CA",
    "sg:tags":[
        "attorney"
    ],
    "wof:name":"Edwin W Wilson Law Office",
    "wof:placetype":"venue"
},
  "geometry": {"coordinates":[-119.01515000000001,35.373399],"type":"Point"}
}