{
  "type": "Feature",
  "properties": {
    "addr:full":"1828A S Coast Hwy Oceanside CA 92054",
    "addr:housenumber":"1828a",
    "addr:postcode":"92054",
    "addr:street":"S Coast Hwy",
    "iso:country":"US",
    "sg:address":"1828A S Coast Hwy",
    "sg:city":"Oceanside",
    "sg:classifiers":[
        {
            "category":"Autos & Motor Vehicles",
            "subcategory":"Motorcycle Sales",
            "type":"Retail Goods"
        }
    ],
    "sg:phone":"+1 760 453 2400",
    "sg:postcode":"92054",
    "sg:province":"CA",
    "sg:website":"www.southcoastscooter.com",
    "wof:name":"SOUTH COAST SCOOTER",
    "wof:placetype":"venue"
},
  "geometry": {"coordinates":[-117.36166900000001,33.174895],"type":"Point"}
}