{
  "type": "Feature",
  "properties": {
    "iso:country":"US",
    "sg:address":"11639 Gale Ave",
    "sg:city":"Hawthorne",
    "sg:classifiers":[
        {
            "category":"Social Services",
            "type":"Services"
        }
    ],
    "sg:phone":"+1 310 355 1938",
    "sg:postcode":"90250",
    "sg:province":"CA",
    "sg:tags":[
        "care",
        "center",
        "day"
    ],
    "wof:name":"Prostegise Adult Day Care",
    "wof:placetype":"venue"
},
  "geometry": {"coordinates":[-118.360245,33.929482],"type":"Point"}
}