{
  "type": "Feature",
  "properties": {
    "addr:full":"35901 Perkins St Fremont CA 94536",
    "addr:housenumber":"35901",
    "addr:postcode":"94536",
    "addr:street":"Perkins St",
    "iso:country":"US",
    "sg:address":"35901 Perkins St",
    "sg:city":"Fremont",
    "sg:classifiers":[
        {
            "category":"Building & Trades",
            "subcategory":"Landscaping Services",
            "type":"Services"
        }
    ],
    "sg:phone":"+1 510 793 9694",
    "sg:postcode":"94536",
    "sg:province":"CA",
    "wof:name":"Anytime Tree Specialist",
    "wof:placetype":"venue"
},
  "geometry": {"coordinates":[-122.02404799999999,37.564446],"type":"Point"}
}