{
  "type": "Feature",
  "properties": {
    "addr:full":"4446 Monterey Ave Baldwin Park CA 91706",
    "addr:housenumber":"4446",
    "addr:postcode":"91706",
    "addr:street":"Monterey Ave",
    "iso:country":"US",
    "sg:address":"4446 Monterey Ave",
    "sg:city":"Baldwin Park",
    "sg:classifiers":[
        {
            "category":"Professional",
            "type":"Services"
        }
    ],
    "sg:phone":"+1 626 960 9802",
    "sg:postcode":"91706",
    "sg:province":"CA",
    "wof:name":"Lily Golden Internatioanal Co",
    "wof:placetype":"venue"
},
  "geometry": {"coordinates":[-117.976788,34.093728],"type":"Point"}
}