{
  "type": "Feature",
  "properties": {
    "iso:country":"US",
    "sg:address":"7938 Carmel Valley Rd",
    "sg:city":"Carmel",
    "sg:classifiers":[
        {
            "category":"Professional",
            "subcategory":"Computer Services",
            "type":"Services"
        }
    ],
    "sg:phone":"+1 831 626 1500",
    "sg:postcode":"93923",
    "sg:province":"CA",
    "wof:name":"Intellegy",
    "wof:placetype":"venue"
},
  "geometry": {"coordinates":[-121.83283,36.530422],"type":"Point"}
}