{
  "type": "Feature",
  "properties": {
    "addr:full":"2450 Mohawk St Bakersfield CA 93308",
    "addr:housenumber":"2450",
    "addr:postcode":"93308",
    "addr:street":"Mohawk St",
    "iso:country":"US",
    "sg:address":"2450 Mohawk St",
    "sg:city":"Bakersfield",
    "sg:classifiers":[
        {
            "category":"Wholesale",
            "subcategory":"Machinery & Supplies",
            "type":"Manufacturing & Wholesale Goods"
        }
    ],
    "sg:phone":"+1 661 323 5754",
    "sg:postcode":"93308",
    "sg:province":"CA",
    "sg:tags":[
        "equipment",
        "oil",
        "well"
    ],
    "sg:website":"www.janesco.com",
    "wof:name":"David Janes Co",
    "wof:placetype":"venue"
},
  "geometry": {"coordinates":[-119.06537899999999,35.38249],"type":"Point"}
}