{
  "type": "Feature",
  "properties": {
    "addr:full":"744 8th Ave Ste 106 A San Diego CA 92101",
    "addr:housenumber":"744",
    "addr:postcode":"92101",
    "addr:street":"8Th Ave Ste 106 A",
    "iso:country":"US",
    "sg:address":"744 8th Ave Ste 106 A",
    "sg:city":"San Diego",
    "sg:classifiers":[
        {
            "category":"Shopping",
            "subcategory":"Clothing, Apparel, & Fashions",
            "type":"Retail Goods"
        }
    ],
    "sg:phone":"+1 619 446 6828",
    "sg:postcode":"92101",
    "sg:province":"CA",
    "sg:tags":[
        "men's",
        "clothing",
        "accessory"
    ],
    "sg:website":"www.unsteadyboutique.com",
    "wof:name":"Unsteady",
    "wof:placetype":"venue"
},
  "geometry": {"coordinates":[-117.157563,32.713052],"type":"Point"}
}