{
  "type": "Feature",
  "properties": {
    "iso:country":"US",
    "sg:address":"2354 Lincoln St",
    "sg:city":"Oroville",
    "sg:classifiers":[
        {
            "category":"Personal",
            "subcategory":"Beauty Salon",
            "type":"Services"
        },
        {
            "category":"Personal",
            "subcategory":"Nail Salon",
            "type":"Services"
        }
    ],
    "sg:phone":"+1 530 538 8220",
    "sg:postcode":"95966",
    "sg:province":"CA",
    "wof:name":"Studio 3 Hair & Nail Salon",
    "wof:placetype":"venue"
},
  "geometry": {"coordinates":[-121.552786,39.50479],"type":"Point"}
}