{
  "type": "Feature",
  "properties": {
    "addr:full":"2801 Prospect Park Drive Rancho Cordova CA 95670",
    "addr:housenumber":"2801",
    "addr:postcode":"95670",
    "addr:street":"Prospect Park Drive",
    "iso:country":"US",
    "sg:address":"2801 Prospect Park Drive",
    "sg:city":"Rancho Cordova",
    "sg:classifiers":[
        {
            "category":"Restaurant",
            "type":"Food & Drink"
        }
    ],
    "sg:phone":"+1 916 293 7480",
    "sg:postcode":"95670",
    "sg:province":"CA",
    "sg:tags":[
        "traditional",
        "american"
    ],
    "sg:website":"www.cordovacasino.com",
    "wof:name":"Cordova Restaurant Casino",
    "wof:placetype":"venue"
},
  "geometry": {"coordinates":[-121.28439299999999,38.591959],"type":"Point"}
}