{
  "type": "Feature",
  "properties": {
    "iso:country":"US",
    "sg:address":"1725 Finecroft Dr",
    "sg:city":"Claremont",
    "sg:classifiers":[
        {
            "category":"Professional",
            "subcategory":"Management & Consulting",
            "type":"Services"
        }
    ],
    "sg:phone":"+1 909 625 7571",
    "sg:postcode":"91711",
    "sg:province":"CA",
    "sg:tags":[
        "party",
        "planning"
    ],
    "wof:name":"Giggles & Grins Unlimited",
    "wof:placetype":"venue"
},
  "geometry": {"coordinates":[-117.73904899999999,34.115144],"type":"Point"}
}