{
  "type": "Feature",
  "properties": {
    "addr:full":"333 W Florence Ave Inglewood CA 90301",
    "addr:housenumber":"333",
    "addr:postcode":"90301",
    "addr:street":"W Florence Ave",
    "iso:country":"US",
    "sg:address":"333 W Florence Ave",
    "sg:city":"Inglewood",
    "sg:classifiers":[
        {
            "category":"Education",
            "subcategory":"College",
            "type":"Public Place"
        }
    ],
    "sg:phone":"+1 310 419 5870",
    "sg:postcode":"90301",
    "sg:province":"CA",
    "sg:tags":[
        "academic",
        "university",
        "school"
    ],
    "wof:name":"Biola Bold Extension Program",
    "wof:placetype":"venue"
},
  "geometry": {"coordinates":[-118.360001,33.965401],"type":"Point"}
}