{
  "type": "Feature",
  "properties": {
    "addr:full":"1020 Tierra Del Rey Chula Vista CA 91910",
    "addr:housenumber":"1020",
    "addr:postcode":"91910",
    "addr:street":"Tierra Del Rey",
    "iso:country":"US",
    "sg:address":"1020 Tierra Del Rey",
    "sg:city":"Chula Vista",
    "sg:classifiers":[
        {
            "category":"Shopping",
            "subcategory":"Party Supplies",
            "type":"Retail Goods"
        }
    ],
    "sg:phone":"+1 619 656 0600",
    "sg:postcode":"91910",
    "sg:province":"CA",
    "wof:name":"Party Land",
    "wof:placetype":"venue"
},
  "geometry": {"coordinates":[-117.012154,32.637502],"type":"Point"}
}