{
  "type": "Feature",
  "properties": {
    "addr:full":"5225 Hillsdale Boulevard Sacramento CA 95842",
    "addr:housenumber":"5225",
    "addr:postcode":"95842",
    "addr:street":"Hillsdale Boulevard",
    "iso:country":"US",
    "sg:address":"5225 Hillsdale Boulevard",
    "sg:city":"Sacramento",
    "sg:classifiers":[
        {
            "category":"Education",
            "subcategory":"School",
            "type":"Public Place"
        }
    ],
    "sg:phone":"+1 916 331 7377",
    "sg:postcode":"95842",
    "sg:province":"CA",
    "sg:tags":[
        "high",
        "middle",
        "elementary"
    ],
    "sg:website":"www.tcssac.org",
    "wof:name":"Trinity Christian School",
    "wof:placetype":"venue"
},
  "geometry": {"coordinates":[-121.364546,38.661963],"type":"Point"}
}