{
  "type": "Feature",
  "properties": {
    "addr:full":"83281 60th Ave Thermal CA 92274",
    "addr:housenumber":"83281",
    "addr:postcode":"92274",
    "addr:street":"60Th Ave",
    "iso:country":"US",
    "sg:address":"83281 60th Ave",
    "sg:city":"Thermal",
    "sg:classifiers":[
        {
            "category":"Farming",
            "subcategory":"Farm",
            "type":"Manufacturing & Wholesale Goods"
        }
    ],
    "sg:phone":"+1 760 399 8116",
    "sg:postcode":"92274",
    "sg:province":"CA",
    "sg:tags":[
        "crop",
        "general"
    ],
    "wof:name":"Sun Valley Farms",
    "wof:placetype":"venue"
},
  "geometry": {"coordinates":[-116.207581,33.612812],"type":"Point"}
}