{
  "type": "Feature",
  "properties": {
    "addr:full":"11018 W Ocean Air Dr San Diego CA 92130",
    "addr:housenumber":"11018",
    "addr:postcode":"92130",
    "addr:street":"W Ocean Air Dr",
    "iso:country":"US",
    "sg:address":"11018 W Ocean Air Dr",
    "sg:city":"San Diego",
    "sg:classifiers":[
        {
            "category":"Professional",
            "subcategory":"Management & Consulting",
            "type":"Services"
        }
    ],
    "sg:phone":"+1 858 523 0765",
    "sg:postcode":"92130",
    "sg:province":"CA",
    "sg:tags":[
        "marketing",
        "consultant"
    ],
    "wof:name":"Marketingweb",
    "wof:placetype":"venue"
},
  "geometry": {"coordinates":[-117.216621,32.922741],"type":"Point"}
}