{
  "type": "Feature",
  "properties": {
    "iso:country":"US",
    "sg:address":"100 Smith Ranch Rd",
    "sg:city":"San Rafael",
    "sg:classifiers":[
        {
            "category":"Insurance",
            "subcategory":"Insurance Agent",
            "type":"Services"
        }
    ],
    "sg:phone":"+1 707 538 8726",
    "sg:postcode":"94903",
    "sg:province":"CA",
    "wof:name":"Financial Flagship Ins Svc",
    "wof:placetype":"venue"
},
  "geometry": {"coordinates":[-122.531108,38.019448],"type":"Point"}
}