{
  "type": "Feature",
  "properties": {
    "addr:full":"6554 Cowles Mountain Boulevard San Diego CA 92119",
    "addr:housenumber":"6554",
    "addr:postcode":"92119",
    "addr:street":"Cowles Mountain Boulevard",
    "iso:country":"US",
    "sg:address":"6554 Cowles Mountain Boulevard",
    "sg:city":"San Diego",
    "sg:classifiers":[
        {
            "category":"Education",
            "subcategory":"Preschool",
            "type":"Public Place"
        },
        {
            "category":"Education",
            "subcategory":"School",
            "type":"Public Place"
        }
    ],
    "sg:phone":"+1 619 464 4335",
    "sg:postcode":"92119",
    "sg:province":"CA",
    "sg:tags":[
        "elementary"
    ],
    "wof:name":"San Carlos United Methodist Preschool",
    "wof:placetype":"venue"
},
  "geometry": {"coordinates":[-117.025265,32.80254],"type":"Point"}
}