{
  "type": "Feature",
  "properties": {
    "addr:full":"7515 Creekridge Cir Citrus Heights CA 95610",
    "addr:housenumber":"7515",
    "addr:postcode":"95610",
    "addr:street":"Creekridge Cir",
    "iso:country":"US",
    "sg:address":"7515 Creekridge Cir",
    "sg:city":"Citrus Heights",
    "sg:classifiers":[
        {
            "category":"Professional",
            "type":"Services"
        }
    ],
    "sg:phone":"+1 916 768 6325",
    "sg:postcode":"95610",
    "sg:province":"CA",
    "wof:name":"Grand Old Girls Network",
    "wof:placetype":"venue"
},
  "geometry": {"coordinates":[-121.247578,38.702264],"type":"Point"}
}