{
  "type": "Feature",
  "properties": {
    "addr:full":"950 N Broadway Los Angeles CA 90012",
    "addr:housenumber":"950",
    "addr:postcode":"90012",
    "addr:street":"N Broadway",
    "iso:country":"US",
    "sg:address":"950 N Broadway",
    "sg:city":"Los Angeles",
    "sg:classifiers":[
        {
            "category":"Shopping",
            "subcategory":"Beauty & Cosmetics",
            "type":"Retail Goods"
        }
    ],
    "sg:phone":"+1 213 620 1937",
    "sg:postcode":"90012",
    "sg:province":"CA",
    "sg:tags":[
        "supply"
    ],
    "wof:name":"Bella Ana",
    "wof:placetype":"venue"
},
  "geometry": {"coordinates":[-118.236453,34.06585],"type":"Point"}
}