{
  "type": "Feature",
  "properties": {
    "addr:full":"26366 Carmel Rancho Ln Ste B Carmel-by-the-Sea CA 93923",
    "addr:housenumber":"26366",
    "addr:postcode":"93923",
    "addr:street":"Carmel Rancho Ln Ste B Carmel-By-The-Sea",
    "iso:country":"US",
    "sg:address":"26366 Carmel Rancho Ln Ste B",
    "sg:city":"Carmel-by-the-Sea",
    "sg:classifiers":[
        {
            "category":"Home & Garden",
            "subcategory":"Carpets & Floor Coverings",
            "type":"Retail Goods"
        }
    ],
    "sg:phone":"+1 831 624 4045",
    "sg:postcode":"93923",
    "sg:province":"CA",
    "sg:tags":[
        "flooring"
    ],
    "wof:name":"Casa Dolores Gallery",
    "wof:placetype":"venue"
},
  "geometry": {"coordinates":[-121.906432,36.540517],"type":"Point"}
}