{
  "type": "Feature",
  "properties": {
    "iso:country":"US",
    "sg:address":"1808 Verdugo Blvd Ste 102",
    "sg:city":"Glendale",
    "sg:classifiers":[
        {
            "category":"Health Services",
            "subcategory":"Optometrist",
            "type":"Services"
        }
    ],
    "sg:phone":"+1 818 952 1136",
    "sg:postcode":"91208",
    "sg:province":"CA",
    "sg:tags":[
        "ophthalmologist"
    ],
    "wof:name":"Nilles Jeffrey J MD",
    "wof:placetype":"venue"
},
  "geometry": {"coordinates":[-118.230003,34.187599],"type":"Point"}
}