{
  "type": "Feature",
  "properties": {
    "addr:full":"930 Boardwalk San Marcos CA 92078",
    "addr:housenumber":"930",
    "addr:postcode":"92078",
    "addr:street":"Boardwalk",
    "iso:country":"US",
    "sg:address":"930 Boardwalk",
    "sg:city":"San Marcos",
    "sg:classifiers":[
        {
            "category":"Social Services",
            "type":"Services"
        }
    ],
    "sg:phone":"+1 760 752 9373",
    "sg:postcode":"92078",
    "sg:province":"CA",
    "sg:tags":[
        "organization",
        "welfare"
    ],
    "wof:name":"Life Skills Learning Ctr",
    "wof:placetype":"venue"
},
  "geometry": {"coordinates":[-117.188418,33.136001],"type":"Point"}
}