{
  "type": "Feature",
  "properties": {
    "iso:country":"US",
    "sg:address":"12304 Santa Monica Blvd",
    "sg:city":"Los Angeles",
    "sg:classifiers":[
        {
            "category":"Professional",
            "subcategory":"Accounting & Tax Preparation",
            "type":"Services"
        }
    ],
    "sg:phone":"+1 310 841 2642",
    "sg:postcode":"90025",
    "sg:province":"CA",
    "sg:tags":[
        "bookkeeping",
        "general"
    ],
    "wof:name":"Keystone Accounting Assoc",
    "wof:placetype":"venue"
},
  "geometry": {"coordinates":[-118.466526,34.03906],"type":"Point"}
}