{
  "type": "Feature",
  "properties": {
    "iso:country":"US",
    "sg:address":"1182 Warner Way",
    "sg:city":"Chester",
    "sg:classifiers":[
        {
            "category":"Organizations",
            "subcategory":"Religious Organization",
            "type":"Services"
        }
    ],
    "sg:phone":"+1 530 258 2057",
    "sg:postcode":"96088",
    "sg:province":"CA",
    "sg:tags":[
        "church"
    ],
    "wof:name":"Church Of Christ",
    "wof:placetype":"venue"
},
  "geometry": {"coordinates":[-121.744435,40.537737],"type":"Point"}
}