{
  "type": "Feature",
  "properties": {
    "iso:country":"US",
    "sg:address":"1951 Willow Glen Dr",
    "sg:city":"El Cajon",
    "sg:classifiers":[
        {
            "category":"Retail",
            "subcategory":"Veterinary Services",
            "type":"Services"
        }
    ],
    "sg:phone":"+1 619 441 5850",
    "sg:postcode":"92019",
    "sg:province":"CA",
    "wof:name":"Cornell Lanny H Dvm",
    "wof:placetype":"venue"
},
  "geometry": {"coordinates":[-116.902978,32.757399],"type":"Point"}
}