{
  "type": "Feature",
  "properties": {
    "addr:full":"6247 Graham Hill Rd Felton CA 95018",
    "addr:housenumber":"6247",
    "addr:postcode":"95018",
    "addr:street":"Graham Hill Rd",
    "iso:country":"US",
    "sg:address":"6247 Graham Hill Rd",
    "sg:city":"Felton",
    "sg:classifiers":[
        {
            "category":"Restaurant",
            "type":"Food & Drink"
        }
    ],
    "sg:phone":"+1 831 335 6400",
    "sg:postcode":"95018",
    "sg:province":"CA",
    "sg:tags":[
        "american"
    ],
    "wof:name":"Ngs Drug Store 9853",
    "wof:placetype":"venue"
},
  "geometry": {"coordinates":[-122.068686,37.051484],"type":"Point"}
}