{
  "type": "Feature",
  "properties": {
    "iso:country":"US",
    "sg:address":"150 E Leland Rd",
    "sg:city":"Pittsburg",
    "sg:classifiers":[
        {
            "category":"Social Services",
            "subcategory":"Child Care",
            "type":"Services"
        }
    ],
    "sg:phone":"+1 925 432 8800",
    "sg:postcode":"94565",
    "sg:province":"CA",
    "sg:website":"www.kindercare.com",
    "wof:name":"Kinder Care Learning Ctr",
    "wof:placetype":"venue"
},
  "geometry": {"coordinates":[-121.890471,38.012071],"type":"Point"}
}