{
  "type": "Feature",
  "properties": {
    "iso:country":"US",
    "sg:address":"729 W 16th Street",
    "sg:city":"Costa Mesa",
    "sg:classifiers":[
        {
            "category":"Coffee & Tea",
            "type":"Food & Drink"
        }
    ],
    "sg:phone":"+1 949 574 0202",
    "sg:postcode":"92627",
    "sg:province":"CA",
    "sg:website":"www.galeoscafe.com",
    "wof:name":"Galeos Cafe",
    "wof:placetype":"venue"
},
  "geometry": {"coordinates":[-117.92881199999999,33.632523],"type":"Point"}
}