{
  "type": "Feature",
  "properties": {
    "iso:country":"US",
    "sg:address":"32432 Alipaz St",
    "sg:city":"San Juan Capistrano",
    "sg:classifiers":[
        {
            "category":"Building & Trades",
            "subcategory":"Construction",
            "type":"Services"
        }
    ],
    "sg:phone":"+1 949 493 0404",
    "sg:postcode":"92675",
    "sg:province":"CA",
    "sg:tags":[
        "carpentry",
        "contractor"
    ],
    "wof:name":"Laminated Specialties",
    "wof:placetype":"venue"
},
  "geometry": {"coordinates":[-117.67211,33.49078],"type":"Point"}
}