{
  "type": "Feature",
  "properties": {
    "addr:full":"12940 Telegraph Rd Santa Fe Springs CA 90670",
    "addr:housenumber":"12940",
    "addr:postcode":"90670",
    "addr:street":"Telegraph Rd",
    "iso:country":"US",
    "sg:address":"12940 Telegraph Rd",
    "sg:city":"Santa Fe Springs",
    "sg:classifiers":[
        {
            "category":"Government",
            "subcategory":"Jail",
            "type":"Public Place"
        }
    ],
    "sg:phone":"+1 562 941 1947",
    "sg:postcode":"90670",
    "sg:province":"CA",
    "sg:tags":[
        "govt",
        "state",
        "institution"
    ],
    "wof:name":"Corrections Dept",
    "wof:placetype":"venue"
},
  "geometry": {"coordinates":[-118.057592,33.941804],"type":"Point"}
}