{
  "type": "Feature",
  "properties": {
    "addr:full":"640 Tuolumne St Vallejo CA 94590",
    "addr:housenumber":"640",
    "addr:postcode":"94590",
    "addr:street":"Tuolumne St",
    "iso:country":"US",
    "sg:address":"640 Tuolumne St",
    "sg:city":"Vallejo",
    "sg:classifiers":[
        {
            "category":"Real Estate",
            "subcategory":"Real Estate Agent",
            "type":"Services"
        }
    ],
    "sg:phone":"+1 707 644 7253",
    "sg:postcode":"94590",
    "sg:province":"CA",
    "wof:name":"Realty Executives",
    "wof:placetype":"venue"
},
  "geometry": {"coordinates":[-122.238133,38.105335],"type":"Point"}
}