{
  "type": "Feature",
  "properties": {
    "iso:country":"US",
    "sg:address":"4401 Capitola Rd",
    "sg:city":"Capitola",
    "sg:classifiers":[
        {
            "category":"Professional",
            "subcategory":"Accounting & Tax Preparation",
            "type":"Services"
        }
    ],
    "sg:phone":"+1 831 464 0188",
    "sg:postcode":"95010",
    "sg:province":"CA",
    "sg:tags":[
        "return",
        "public",
        "accountants-certified"
    ],
    "sg:website":"http://www.mauramateracpa.com",
    "wof:name":"Matera Maura CPA",
    "wof:placetype":"venue"
},
  "geometry": {"coordinates":[-121.960831,36.973721],"type":"Point"}
}