{
  "type": "Feature",
  "properties": {
    "iso:country":"US",
    "sg:address":"411 Dayloma Ave",
    "sg:city":"Ventura",
    "sg:classifiers":[
        {
            "category":"Health Services",
            "subcategory":"Health Practitioner",
            "type":"Services"
        }
    ],
    "sg:phone":"+1 805 642 1873",
    "sg:postcode":"93003",
    "sg:province":"CA",
    "sg:tags":[
        "acupuncture"
    ],
    "wof:name":"Comprehensive Acupuncture",
    "wof:placetype":"venue"
},
  "geometry": {"coordinates":[-119.228576,34.283274],"type":"Point"}
}