{
  "type": "Feature",
  "properties": {
    "addr:full":"744 W 20th St Merced CA 95340",
    "addr:housenumber":"744",
    "addr:postcode":"95340",
    "addr:street":"W 20Th St",
    "iso:country":"US",
    "sg:address":"744 W 20th St",
    "sg:city":"Merced",
    "sg:classifiers":[
        {
            "category":"Utilities",
            "subcategory":"Water",
            "type":"Services"
        },
        {
            "category":"Wholesale",
            "subcategory":"Machinery & Supplies",
            "type":"Manufacturing & Wholesale Goods"
        }
    ],
    "sg:phone":"+1 209 726 6141",
    "sg:postcode":"95340",
    "sg:province":"CA",
    "sg:tags":[
        "company-utility",
        "irrigation",
        "system",
        "equipment"
    ],
    "wof:name":"Merced Irrigation District",
    "wof:placetype":"venue"
},
  "geometry": {"coordinates":[-120.485342,37.305787],"type":"Point"}
}