{
  "type": "Feature",
  "properties": {
    "iso:country":"US",
    "sg:address":"885 E H St Ste B",
    "sg:city":"Chula Vista",
    "sg:classifiers":[
        {
            "category":"Personal",
            "subcategory":"Nail Salon",
            "type":"Services"
        }
    ],
    "sg:phone":"+1 619 656 8903",
    "sg:postcode":"91910",
    "sg:province":"CA",
    "wof:name":"Cutie Nails",
    "wof:placetype":"venue"
},
  "geometry": {"coordinates":[-117.054001,32.635101],"type":"Point"}
}