{
  "type": "Feature",
  "properties": {
    "addr:full":"42 Hidden Valley Rd Palos Verdes Peninsula CA 90274",
    "addr:housenumber":"42",
    "addr:postcode":"90274",
    "addr:street":"Hidden Valley Rd",
    "iso:country":"US",
    "sg:address":"42 Hidden Valley Rd",
    "sg:city":"Palos Verdes Peninsula",
    "sg:classifiers":[
        {
            "category":"Freight",
            "type":"Transportation"
        }
    ],
    "sg:phone":"+1 310 378 2662",
    "sg:postcode":"90274",
    "sg:province":"CA",
    "sg:tags":[
        "horse"
    ],
    "wof:name":"Porter Horse Transportation",
    "wof:placetype":"venue"
},
  "geometry": {"coordinates":[-118.355131,33.792877],"type":"Point"}
}