{
  "type": "Feature",
  "properties": {
    "addr:full":"21765 Sutherland Dr Yorba Linda CA 92887",
    "addr:housenumber":"21765",
    "addr:postcode":"92887",
    "addr:street":"Sutherland Dr",
    "iso:country":"US",
    "sg:address":"21765 Sutherland Dr",
    "sg:city":"Yorba Linda",
    "sg:classifiers":[
        {
            "category":"Manufacturing",
            "subcategory":"Motor Vehicles & Parts",
            "type":"Manufacturing & Wholesale Goods"
        }
    ],
    "sg:phone":"+1 714 777 8870",
    "sg:postcode":"92887",
    "sg:province":"CA",
    "sg:tags":[
        "body",
        "mfg"
    ],
    "wof:name":"Ford",
    "wof:placetype":"venue"
},
  "geometry": {"coordinates":[-117.754563,33.890428],"type":"Point"}
}