{
  "type": "Feature",
  "properties": {
    "addr:full":"1728 E Cypress Ave Redding CA 96002",
    "addr:housenumber":"1728",
    "addr:postcode":"96002",
    "addr:street":"E Cypress Ave",
    "iso:country":"US",
    "sg:address":"1728 E Cypress Ave",
    "sg:city":"Redding",
    "sg:classifiers":[
        {
            "category":"Shopping",
            "subcategory":"Florist",
            "type":"Retail Goods"
        }
    ],
    "sg:phone":"+1 530 222 5663",
    "sg:postcode":"96002",
    "sg:province":"CA",
    "wof:name":"Flower Express",
    "wof:placetype":"venue"
},
  "geometry": {"coordinates":[-122.340934,40.571121],"type":"Point"}
}