{
  "type": "Feature",
  "properties": {
    "addr:full":"92 Natoma St San Francisco CA 94105",
    "addr:housenumber":"92",
    "addr:postcode":"94105",
    "addr:street":"Natoma St",
    "iso:country":"US",
    "sg:address":"92 Natoma St",
    "sg:city":"San Francisco",
    "sg:classifiers":[
        {
            "category":"Mining & Drilling",
            "type":"Manufacturing & Wholesale Goods"
        }
    ],
    "sg:phone":"+1 415 901 4400",
    "sg:postcode":"94105",
    "sg:province":"CA",
    "sg:tags":[
        "company"
    ],
    "sg:website":"www.malcolmdrilling.com",
    "wof:name":"Malcolm Drilling Co Inc",
    "wof:placetype":"venue"
},
  "geometry": {"coordinates":[-122.397986,37.788101],"type":"Point"}
}