{
  "type": "Feature",
  "properties": {
    "iso:country":"US",
    "sg:address":"9375 Customhouse Plz",
    "sg:city":"San Diego",
    "sg:classifiers":[
        {
            "category":"Food & Beverages",
            "subcategory":"Groceries & Convenience Stores",
            "type":"Retail Goods"
        }
    ],
    "sg:phone":"+1 619 710 4960",
    "sg:postcode":"92154",
    "sg:province":"CA",
    "sg:tags":[
        "product"
    ],
    "wof:name":"California Food & Beverage Inc",
    "wof:placetype":"venue"
},
  "geometry": {"coordinates":[-116.944016,32.551692],"type":"Point"}
}