{
  "type": "Feature",
  "properties": {
    "iso:country":"US",
    "sg:address":"242 Hartnell Ave",
    "sg:city":"Redding",
    "sg:classifiers":[
        {
            "category":"Banks & Credit Unions",
            "subcategory":"Bank",
            "type":"Services"
        }
    ],
    "sg:phone":"+1 530 224 2791",
    "sg:postcode":"96002",
    "sg:province":"CA",
    "sg:tags":[
        "loan",
        "real estate"
    ],
    "wof:name":"Windsor Club Mortgage",
    "wof:placetype":"venue"
},
  "geometry": {"coordinates":[-122.368216,40.565612],"type":"Point"}
}