{
  "type": "Feature",
  "properties": {
    "addr:full":"PO Box 28885 San Jose CA 95159",
    "addr:housenumber":"po box 28885",
    "addr:postcode":"95159",
    "iso:country":"US",
    "sg:address":"PO Box 28885",
    "sg:city":"San Jose",
    "sg:classifiers":[
        {
            "category":"Banks & Credit Unions",
            "subcategory":"Investment Brokerage",
            "type":"Services"
        }
    ],
    "sg:phone":"+1 408 297 8870",
    "sg:postcode":"95159",
    "sg:province":"CA",
    "sg:tags":[
        "investing"
    ],
    "wof:name":"Visionplus Associates",
    "wof:placetype":"venue"
},
  "geometry": {"coordinates":[-121.921997,37.316898],"type":"Point"}
}