{
  "type": "Feature",
  "properties": {
    "iso:country":"US",
    "sg:address":"24331 Muirlands Blvd",
    "sg:city":"Lake Forest",
    "sg:classifiers":[
        {
            "category":"Shopping",
            "subcategory":"Computers & Home Electronics",
            "type":"Retail Goods"
        }
    ],
    "sg:phone":"+1 949 707 0777",
    "sg:postcode":"92630",
    "sg:province":"CA",
    "sg:tags":[
        "software"
    ],
    "sg:website":"www.spinnsoft.com",
    "wof:name":"Spinnsoft",
    "wof:placetype":"venue"
},
  "geometry": {"coordinates":[-117.702681,33.627618],"type":"Point"}
}