{
  "type": "Feature",
  "properties": {
    "addr:full":"11841 Stuart Dr Garden Grove CA 92843",
    "addr:housenumber":"11841",
    "addr:postcode":"92843",
    "addr:street":"Stuart Dr",
    "iso:country":"US",
    "sg:address":"11841 Stuart Dr",
    "sg:city":"Garden Grove",
    "sg:classifiers":[
        {
            "category":"Building & Trades",
            "subcategory":"Construction",
            "type":"Services"
        }
    ],
    "sg:phone":"+1 714 337 7803",
    "sg:postcode":"92843",
    "sg:province":"CA",
    "sg:tags":[
        "handyman"
    ],
    "wof:name":"Ed Baird Handyman",
    "wof:placetype":"venue"
},
  "geometry": {"coordinates":[-117.923013,33.773309],"type":"Point"}
}