{
  "type": "Feature",
  "properties": {
    "addr:full":"1310 E Swain Rd Stockton CA 95210",
    "addr:housenumber":"1310",
    "addr:postcode":"95210",
    "addr:street":"E Swain Rd",
    "iso:country":"US",
    "sg:address":"1310 E Swain Rd",
    "sg:city":"Stockton",
    "sg:classifiers":[
        {
            "category":"Health Services",
            "subcategory":"Doctor",
            "type":"Services"
        }
    ],
    "sg:phone":"+1 209 951 4251",
    "sg:postcode":"95210",
    "sg:province":"CA",
    "sg:tags":[
        "dentist"
    ],
    "sg:website":"www.martinimplants.com",
    "wof:name":"Martin Implant Dentistry",
    "wof:placetype":"venue"
},
  "geometry": {"coordinates":[-121.29421600000001,38.010773],"type":"Point"}
}