{
  "type": "Feature",
  "properties": {
    "iso:country":"US",
    "sg:address":"165 Satinwood Ave",
    "sg:city":"Oak Park",
    "sg:classifiers":[
        {
            "category":"Education",
            "subcategory":"School",
            "type":"Public Place"
        }
    ],
    "sg:phone":"+1 818 597 4200",
    "sg:postcode":"91377",
    "sg:province":"CA",
    "sg:tags":[
        "high",
        "middle",
        "elementary"
    ],
    "wof:name":"Oak Park Unified School District",
    "wof:placetype":"venue"
},
  "geometry": {"coordinates":[-118.75700399999999,34.173],"type":"Point"}
}