{
  "type": "Feature",
  "properties": {
    "iso:country":"US",
    "sg:address":"23457 S Central Ave",
    "sg:city":"Sonoma",
    "sg:classifiers":[
        {
            "category":"Manufacturing",
            "subcategory":"Glass & Minerals",
            "type":"Manufacturing & Wholesale Goods"
        }
    ],
    "sg:phone":"+1 707 938 1939",
    "sg:postcode":"95476",
    "sg:province":"CA",
    "sg:tags":[
        "product",
        "mfg"
    ],
    "wof:name":"JW Mirrors",
    "wof:placetype":"venue"
},
  "geometry": {"coordinates":[-122.416982,38.243206],"type":"Point"}
}