{
  "type": "Feature",
  "properties": {
    "iso:country":"US",
    "sg:address":"103 Fletcher Pkwy",
    "sg:city":"El Cajon",
    "sg:classifiers":[
        {
            "category":"Restaurant",
            "type":"Food & Drink"
        }
    ],
    "sg:phone":"+1 619 441 0200",
    "sg:postcode":"92020",
    "sg:province":"CA",
    "sg:tags":[
        "mexican"
    ],
    "wof:name":"On the Border Mexican Grill & Cantina",
    "wof:placetype":"venue"
},
  "geometry": {"coordinates":[-116.962997,32.8074],"type":"Point"}
}