{
  "type": "Feature",
  "properties": {
    "addr:full":"8407 S Vermont Ave Los Angeles CA 90044",
    "addr:housenumber":"8407",
    "addr:postcode":"90044",
    "addr:street":"S Vermont Ave",
    "iso:country":"US",
    "sg:address":"8407 S Vermont Ave",
    "sg:city":"Los Angeles",
    "sg:classifiers":[
        {
            "category":"Real Estate",
            "subcategory":"Real Estate Agent",
            "type":"Services"
        }
    ],
    "sg:phone":"+1 323 750 3399",
    "sg:postcode":"90044",
    "sg:province":"CA",
    "wof:name":"Central Real Estate",
    "wof:placetype":"venue"
},
  "geometry": {"coordinates":[-118.291639,33.962589],"type":"Point"}
}