{
  "type": "Feature",
  "properties": {
    "iso:country":"US",
    "sg:address":"26941 Cabot Rd",
    "sg:city":"Laguna Hills",
    "sg:classifiers":[
        {
            "category":"Wholesale",
            "subcategory":"Sporting Goods",
            "type":"Manufacturing & Wholesale Goods"
        }
    ],
    "sg:phone":"+1 949 348 7330",
    "sg:postcode":"92653",
    "sg:province":"CA",
    "sg:tags":[
        "steel",
        "head",
        "golf",
        "mfg",
        "cover",
        "go",
        "import"
    ],
    "wof:name":"International Sports",
    "wof:placetype":"venue"
},
  "geometry": {"coordinates":[-117.674422,33.571167],"type":"Point"}
}