{
  "type": "Feature",
  "properties": {
    "iso:country":"US",
    "sg:address":"26856 Adams Ave",
    "sg:city":"Murrieta",
    "sg:classifiers":[
        {
            "category":"Retail",
            "subcategory":"Auto Repair",
            "type":"Services"
        }
    ],
    "sg:phone":"+1 951 600 1997",
    "sg:postcode":"92562",
    "sg:province":"CA",
    "sg:tags":[
        "windshield"
    ],
    "wof:name":"Pacific Windshield Repair",
    "wof:placetype":"venue"
},
  "geometry": {"coordinates":[-117.177725,33.525566],"type":"Point"}
}