{
  "type": "Feature",
  "properties": {
    "iso:country":"US",
    "sg:address":"212 Francis St",
    "sg:city":"Ferndale",
    "sg:classifiers":[
        {
            "category":"Organizations",
            "subcategory":"Community Association",
            "type":"Services"
        }
    ],
    "sg:phone":"+1 707 786 4532",
    "sg:postcode":"95536",
    "sg:province":"CA",
    "sg:tags":[
        "fraternal"
    ],
    "wof:name":"Masonic Lodge",
    "wof:placetype":"venue"
},
  "geometry": {"coordinates":[-124.264981,40.575436],"type":"Point"}
}