{
  "type": "Feature",
  "properties": {
    "iso:country":"US",
    "sg:address":"2442 Iowa Ave",
    "sg:city":"Riverside",
    "sg:classifiers":[
        {
            "category":"Real Estate",
            "subcategory":"Real Estate Operator",
            "type":"Services"
        }
    ],
    "sg:phone":"+1 951 682 4104",
    "sg:postcode":"92507",
    "sg:province":"CA",
    "sg:tags":[
        "apartment"
    ],
    "wof:name":"Boulder Creek Apartments",
    "wof:placetype":"venue"
},
  "geometry": {"coordinates":[-117.33974000000001,33.990183],"type":"Point"}
}