{
  "type": "Feature",
  "properties": {
    "addr:full":"1306 Chewpon Ave Milpitas CA 95035",
    "addr:housenumber":"1306",
    "addr:postcode":"95035",
    "addr:street":"Chewpon Ave",
    "iso:country":"US",
    "sg:address":"1306 Chewpon Ave",
    "sg:city":"Milpitas",
    "sg:classifiers":[
        {
            "category":"Shopping",
            "subcategory":"Clothing, Apparel, & Fashions",
            "type":"Retail Goods"
        }
    ],
    "sg:phone":"+1 408 957 0493",
    "sg:postcode":"95035",
    "sg:province":"CA",
    "sg:tags":[
        "accessory",
        "clothing",
        "women's"
    ],
    "wof:name":"Adaa Boutique",
    "wof:placetype":"venue"
},
  "geometry": {"coordinates":[-121.87929800000001,37.419349],"type":"Point"}
}