{
  "type": "Feature",
  "properties": {
    "addr:full":"3902 J Street Sacramento CA 95819",
    "addr:housenumber":"3902",
    "addr:postcode":"95819",
    "addr:street":"J Street",
    "iso:country":"US",
    "sg:address":"3902 J Street",
    "sg:city":"Sacramento",
    "sg:classifiers":[
        {
            "category":"Health Services",
            "subcategory":"Dentist",
            "type":"Services"
        }
    ],
    "sg:phone":"+1 916 452 0513",
    "sg:postcode":"95819",
    "sg:province":"CA",
    "wof:name":"Taketa David J DDS",
    "wof:placetype":"venue"
},
  "geometry": {"coordinates":[-121.453571,38.569575],"type":"Point"}
}