{
  "type": "Feature",
  "properties": {
    "iso:country":"US",
    "sg:address":"150 W Florence Ave",
    "sg:city":"Los Angeles",
    "sg:classifiers":[
        {
            "category":"Wholesale",
            "subcategory":"Electrical",
            "type":"Manufacturing & Wholesale Goods"
        }
    ],
    "sg:phone":"+1 323 758 9615",
    "sg:postcode":"90003",
    "sg:province":"CA",
    "sg:tags":[
        "electronic"
    ],
    "wof:name":"A & B Number 2",
    "wof:placetype":"venue"
},
  "geometry": {"coordinates":[-118.277384,33.974604],"type":"Point"}
}