{
  "type": "Feature",
  "properties": {
    "addr:full":"21420 Bundy Canyon Rd Wildomar CA 92595",
    "addr:postcode":"92595",
    "addr:street":"Bundy Canyon Rd",
    "iso:country":"US",
    "sg:address":"21420 Bundy Canyon Rd",
    "sg:city":"Wildomar",
    "sg:classifiers":[
        {
            "category":"Home & Garden",
            "subcategory":"Garden Supply",
            "type":"Retail Goods"
        }
    ],
    "sg:phone":"+1 951 674 0428",
    "sg:postcode":"92595",
    "sg:province":"CA",
    "sg:tags":[
        "landscaping",
        "nursery",
        "gardening",
        "equipment"
    ],
    "sg:website":"www.bundycanyonturf.com",
    "wof:name":"Bundy Canyon Turf Supply",
    "wof:placetype":"venue"
},
  "geometry": {"coordinates":[-117.285004,33.626999],"type":"Point"}
}