{
  "type": "Feature",
  "properties": {
    "iso:country":"US",
    "sg:address":"1629 Kiowa Crest Dr",
    "sg:city":"Diamond Bar",
    "sg:classifiers":[
        {
            "category":"Manufacturing",
            "subcategory":"Tools & Machinery",
            "type":"Manufacturing & Wholesale Goods"
        }
    ],
    "sg:phone":"+1 909 860 3194",
    "sg:postcode":"91765",
    "sg:province":"CA",
    "sg:tags":[
        "devices"
    ],
    "wof:name":"Switches & Controls",
    "wof:placetype":"venue"
},
  "geometry": {"coordinates":[-117.828429,33.991038],"type":"Point"}
}