{
  "type": "Feature",
  "properties": {
    "addr:full":"440 Aldo Ave Santa Clara CA 95054",
    "addr:housenumber":"440",
    "addr:postcode":"95054",
    "addr:street":"Aldo Ave",
    "iso:country":"US",
    "sg:address":"440 Aldo Ave",
    "sg:city":"Santa Clara",
    "sg:classifiers":[
        {
            "category":"Professional",
            "type":"Services"
        }
    ],
    "sg:phone":"+1 408 988 0151",
    "sg:postcode":"95054",
    "sg:province":"CA",
    "wof:name":"Jim & Linda Stout",
    "wof:placetype":"venue"
},
  "geometry": {"coordinates":[-121.939322,37.38752],"type":"Point"}
}