{
  "type": "Feature",
  "properties": {
    "iso:country":"US",
    "sg:address":"2594 Rio Linda Blvd",
    "sg:city":"Sacramento",
    "sg:classifiers":[
        {
            "category":"Retail",
            "subcategory":"Auto Repair",
            "type":"Services"
        }
    ],
    "sg:phone":"+1 916 349 0600",
    "sg:postcode":"95815",
    "sg:province":"CA",
    "sg:tags":[
        "wrecker"
    ],
    "wof:name":"Tow U4 Less",
    "wof:placetype":"venue"
},
  "geometry": {"coordinates":[-121.447861,38.612963],"type":"Point"}
}