{
  "type": "Feature",
  "properties": {
    "iso:country":"US",
    "sg:address":"24940 Redlands Blvd",
    "sg:city":"Loma Linda",
    "sg:classifiers":[
        {
            "category":"Restaurant",
            "type":"Food & Drink"
        }
    ],
    "sg:menulink":"http://www.allmenus.com/ca/san-bernardino/164352-wienerschnitzel/menu/",
    "sg:phone":"+1 909 796 3822",
    "sg:postcode":"92354",
    "sg:province":"CA",
    "sg:tags":[
        "sandwich",
        "dog",
        "burger",
        "hot",
        "wrap",
        "american"
    ],
    "wof:name":"Wienerschnitzel",
    "wof:placetype":"venue"
},
  "geometry": {"coordinates":[-117.260498,34.063046],"type":"Point"}
}