{
  "type": "Feature",
  "properties": {
    "addr:full":"613 Beta Ct Campbell CA 95008",
    "addr:housenumber":"613",
    "addr:postcode":"95008",
    "addr:street":"Beta Ct",
    "iso:country":"US",
    "sg:address":"613 Beta Ct",
    "sg:city":"Campbell",
    "sg:classifiers":[
        {
            "category":"Real Estate",
            "subcategory":"Real Estate Operator",
            "type":"Services"
        }
    ],
    "sg:phone":"+1 408 374 3370",
    "sg:postcode":"95008",
    "sg:province":"CA",
    "sg:tags":[
        "apartment"
    ],
    "wof:name":"Goo, David/Shirley",
    "wof:placetype":"venue"
},
  "geometry": {"coordinates":[-121.96029299999999,37.273839],"type":"Point"}
}