{
  "type": "Feature",
  "properties": {
    "addr:full":"1521 Pier C St Long Beach CA 90813",
    "addr:housenumber":"1521",
    "addr:postcode":"90813",
    "addr:street":"Pier C St",
    "iso:country":"US",
    "sg:address":"1521 Pier C St",
    "sg:city":"Long Beach",
    "sg:classifiers":[
        {
            "category":"Insurance",
            "subcategory":"Insurance Agent",
            "type":"Services"
        }
    ],
    "sg:phone":"+1 562 495 8670",
    "sg:postcode":"90813",
    "sg:province":"CA",
    "wof:name":"Homeport Insurance",
    "wof:placetype":"venue"
},
  "geometry": {"coordinates":[-118.210345,33.77434],"type":"Point"}
}