{
  "type": "Feature",
  "properties": {
    "addr:full":"5129 Wedgewood Way Rocklin CA 95765",
    "addr:housenumber":"5129",
    "addr:postcode":"95765",
    "addr:street":"Wedgewood Way",
    "iso:country":"US",
    "sg:address":"5129 Wedgewood Way",
    "sg:city":"Rocklin",
    "sg:classifiers":[
        {
            "category":"Building & Trades",
            "subcategory":"Construction",
            "type":"Services"
        }
    ],
    "sg:phone":"+1 916 315 1811",
    "sg:postcode":"95765",
    "sg:province":"CA",
    "sg:tags":[
        "refinishing",
        "flooring",
        "floor",
        "laying",
        "contractor",
        "resurfacing"
    ],
    "sg:website":"http://www.floorinstallations.com",
    "wof:name":"Liston Floor Installation",
    "wof:placetype":"venue"
},
  "geometry": {"coordinates":[-121.247803,38.811644],"type":"Point"}
}