{
  "type": "Feature",
  "properties": {
    "addr:full":"201 Mission Street Suite 1380 San Francisco CA 94105",
    "addr:housenumber":"201",
    "addr:postcode":"94105",
    "addr:street":"Mission Street Suite 1380",
    "iso:country":"US",
    "sg:address":"201 Mission Street Suite 1380",
    "sg:city":"San Francisco",
    "sg:classifiers":[
        {
            "category":"Professional",
            "subcategory":"Research",
            "type":"Services"
        }
    ],
    "sg:phone":"+1 415 281 8886",
    "sg:postcode":"94105",
    "sg:province":"CA",
    "sg:website":"http://www.jennerex.com",
    "wof:name":"Jennerex Biotherapeutics",
    "wof:placetype":"venue"
},
  "geometry": {"coordinates":[-122.395813,37.791153],"type":"Point"}
}