{
  "type": "Feature",
  "properties": {
    "iso:country":"US",
    "sg:address":"250 E Colorado Blvd",
    "sg:city":"Arcadia",
    "sg:classifiers":[
        {
            "category":"Banks & Credit Unions",
            "subcategory":"Financial Services",
            "type":"Services"
        }
    ],
    "sg:phone":"+1 626 461 0190",
    "sg:postcode":"91006",
    "sg:province":"CA",
    "sg:tags":[
        "broker",
        "mortgage"
    ],
    "wof:name":"CDS Capital",
    "wof:placetype":"venue"
},
  "geometry": {"coordinates":[-118.394705,34.145471],"type":"Point"}
}