{
  "type": "Feature",
  "properties": {
    "iso:country":"US",
    "sg:address":"650 Walnut St",
    "sg:city":"Yuba City",
    "sg:classifiers":[
        {
            "category":"Building & Trades",
            "subcategory":"Construction",
            "type":"Services"
        }
    ],
    "sg:phone":"+1 530 755 2038",
    "sg:postcode":"95991",
    "sg:province":"CA",
    "sg:tags":[
        "general",
        "contractor"
    ],
    "wof:name":"Bolduc & Son Construction",
    "wof:placetype":"venue"
},
  "geometry": {"coordinates":[-121.617863,39.136613],"type":"Point"}
}