{
  "type": "Feature",
  "properties": {
    "addr:full":"2439 Meridian Ave San Jose CA 95124",
    "addr:housenumber":"2439",
    "addr:postcode":"95124",
    "addr:street":"Meridian Ave",
    "iso:country":"US",
    "sg:address":"2439 Meridian Ave",
    "sg:city":"San Jose",
    "sg:classifiers":[
        {
            "category":"Retail",
            "subcategory":"Portrait Studio",
            "type":"Services"
        }
    ],
    "sg:phone":"+1 408 448 4466",
    "sg:postcode":"95124",
    "sg:province":"CA",
    "sg:tags":[
        "photographer"
    ],
    "wof:name":"Abracadabra Art Portraits",
    "wof:placetype":"venue"
},
  "geometry": {"coordinates":[-121.912319,37.280338],"type":"Point"}
}