{
  "type": "Feature",
  "properties": {
    "iso:country":"US",
    "sg:address":"2400 Balfour Rd Ste 237",
    "sg:city":"Brentwood",
    "sg:classifiers":[
        {
            "category":"Health Services",
            "subcategory":"Doctor",
            "type":"Services"
        }
    ],
    "sg:phone":"+1 925 516 3020",
    "sg:postcode":"94513",
    "sg:province":"CA",
    "wof:name":"DIABLO NEUROSURGICAL MEDICAL GROUP INC",
    "wof:placetype":"venue"
},
  "geometry": {"coordinates":[-121.734666,37.925079],"type":"Point"}
}