{
  "type": "Feature",
  "properties": {
    "addr:full":"245 Rey Street San Francisco CA 94134",
    "addr:housenumber":"245",
    "addr:postcode":"94134",
    "addr:street":"Rey Street",
    "iso:country":"US",
    "sg:address":"245 Rey Street",
    "sg:city":"San Francisco",
    "sg:classifiers":[
        {
            "category":"Social Services",
            "subcategory":"Child Care",
            "type":"Services"
        }
    ],
    "sg:phone":"+1 415 586 8700",
    "sg:postcode":"94134",
    "sg:province":"CA",
    "sg:tags":[
        "day"
    ],
    "wof:name":"Heritage Homes Child & Family Development Center",
    "wof:placetype":"venue"
},
  "geometry": {"coordinates":[-122.412003,37.710201],"type":"Point"}
}