{
  "type": "Feature",
  "properties": {
    "iso:country":"US",
    "sg:address":"235 Montgomery Street Suite 830",
    "sg:city":"San Francisco",
    "sg:classifiers":[
        {
            "category":"Health Services",
            "subcategory":"Doctor",
            "type":"Services"
        }
    ],
    "sg:phone":"+1 415 550 7535",
    "sg:postcode":"94104",
    "sg:province":"CA",
    "sg:tags":[
        "psychiatrist"
    ],
    "wof:name":"Perl Mark MD",
    "wof:placetype":"venue"
},
  "geometry": {"coordinates":[-122.402,37.791302],"type":"Point"}
}