{
  "type": "Feature",
  "properties": {
    "addr:full":"5020 Douglas Ln Santa Barbara CA 93111",
    "addr:housenumber":"5020",
    "addr:postcode":"93111",
    "addr:street":"Douglas Ln",
    "iso:country":"US",
    "sg:address":"5020 Douglas Ln",
    "sg:city":"Santa Barbara",
    "sg:classifiers":[
        {
            "category":"Home & Garden",
            "subcategory":"Carpets & Floor Coverings",
            "type":"Retail Goods"
        }
    ],
    "sg:phone":"+1 805 967 3112",
    "sg:postcode":"93111",
    "sg:province":"CA",
    "sg:tags":[
        "material"
    ],
    "wof:name":"Douglas Hardwood Floors Inc",
    "wof:placetype":"venue"
},
  "geometry": {"coordinates":[-119.798242,34.430194],"type":"Point"}
}