{
  "type": "Feature",
  "properties": {
    "iso:country":"US",
    "sg:address":"1320 E Main St",
    "sg:city":"Woodland",
    "sg:classifiers":[
        {
            "category":"Food & Beverages",
            "subcategory":"Groceries & Convenience Stores",
            "type":"Retail Goods"
        }
    ],
    "sg:phone":"+1 530 662 3213",
    "sg:postcode":"95776",
    "sg:province":"CA",
    "sg:tags":[
        "grocer"
    ],
    "wof:name":"Cracchiolo's Market Deli",
    "wof:placetype":"venue"
},
  "geometry": {"coordinates":[-121.761943,38.677389],"type":"Point"}
}