{
  "type": "Feature",
  "properties": {
    "addr:full":"1476 Mustang Ct Salinas CA 93905",
    "addr:housenumber":"1476",
    "addr:postcode":"93905",
    "addr:street":"Mustang Ct",
    "iso:country":"US",
    "sg:address":"1476 Mustang Ct",
    "sg:city":"Salinas",
    "sg:classifiers":[
        {
            "category":"Building & Trades",
            "subcategory":"Construction",
            "type":"Services"
        }
    ],
    "sg:phone":"+1 831 753 0317",
    "sg:postcode":"93905",
    "sg:province":"CA",
    "sg:tags":[
        "contractor"
    ],
    "wof:name":"Baker Custom Tile",
    "wof:placetype":"venue"
},
  "geometry": {"coordinates":[-121.594549,36.687402],"type":"Point"}
}