{
  "type": "Feature",
  "properties": {
    "iso:country":"US",
    "sg:address":"1350 Dell Ave Ste 202",
    "sg:city":"Campbell",
    "sg:classifiers":[
        {
            "category":"Building & Trades",
            "subcategory":"Construction",
            "type":"Services"
        }
    ],
    "sg:phone":"+1 408 369 7447",
    "sg:postcode":"95008",
    "sg:province":"CA",
    "sg:tags":[
        "contractor"
    ],
    "sg:website":"www.nulightsolutions.com/",
    "wof:name":"NuLight Solutions, Inc",
    "wof:placetype":"venue"
},
  "geometry": {"coordinates":[-121.953526,37.266667],"type":"Point"}
}