{
  "type": "Feature",
  "properties": {
    "iso:country":"US",
    "sg:address":"16168 Beach Blvd Ste 100",
    "sg:city":"Huntington Beach",
    "sg:classifiers":[
        {
            "category":"Health Services",
            "subcategory":"Dentist",
            "type":"Services"
        }
    ],
    "sg:phone":"+1 714 842 7729",
    "sg:postcode":"92647",
    "sg:province":"CA",
    "wof:name":"Forte John T DDS Inc",
    "wof:placetype":"venue"
},
  "geometry": {"coordinates":[-117.988998,33.728001],"type":"Point"}
}