{
  "type": "Feature",
  "properties": {
    "iso:country":"US",
    "sg:address":"200 N Midland St",
    "sg:city":"Visalia",
    "sg:classifiers":[
        {
            "category":"Farming",
            "subcategory":"Orchard",
            "type":"Manufacturing & Wholesale Goods"
        }
    ],
    "sg:phone":"+1 559 627 4201",
    "sg:postcode":"93291",
    "sg:province":"CA",
    "sg:tags":[
        "citrus",
        "grove",
        "fruit"
    ],
    "wof:name":"Robert Wagner Jr",
    "wof:placetype":"venue"
},
  "geometry": {"coordinates":[-119.313656,36.331434],"type":"Point"}
}