{
  "type": "Feature",
  "properties": {
    "addr:full":"4575 Artesia Blvd Lawndale CA 90260",
    "addr:housenumber":"4575",
    "addr:postcode":"ca 90260",
    "addr:street":"Artesia Blvd",
    "iso:country":"US",
    "sg:address":"4575 Artesia Blvd",
    "sg:city":"Lawndale",
    "sg:classifiers":[
        {
            "category":"Retail",
            "subcategory":"Car Wash",
            "type":"Services"
        }
    ],
    "sg:phone":"+1 310 371 3945",
    "sg:postcode":"90260",
    "sg:province":"CA",
    "sg:tags":[
        "polishing",
        "washing"
    ],
    "wof:name":"H & M Carwash",
    "wof:placetype":"venue"
},
  "geometry": {"coordinates":[-118.35651300000001,33.872937],"type":"Point"}
}