{
  "type": "Feature",
  "properties": {
    "addr:full":"11828 Rancho Bernardo Rd San Diego CA 92128",
    "addr:housenumber":"11828",
    "addr:postcode":"92128",
    "addr:street":"Rancho Bernardo Rd",
    "iso:country":"US",
    "sg:address":"11828 Rancho Bernardo Rd",
    "sg:city":"San Diego",
    "sg:classifiers":[
        {
            "category":"Building & Trades",
            "subcategory":"Landscaping Services",
            "type":"Services"
        }
    ],
    "sg:phone":"+1 858 451 3815",
    "sg:postcode":"92128",
    "sg:province":"CA",
    "sg:tags":[
        "landscape"
    ],
    "wof:name":"My Secret Garden",
    "wof:placetype":"venue"
},
  "geometry": {"coordinates":[-117.078669,33.023075],"type":"Point"}
}