{
  "type": "Feature",
  "properties": {
    "iso:country":"US",
    "sg:address":"339 Bonair Siding Rd",
    "sg:city":"Stanford",
    "sg:classifiers":[
        {
            "category":"Utilities",
            "subcategory":"Refuse",
            "type":"Services"
        }
    ],
    "sg:phone":"+1 650 321 4236",
    "sg:postcode":"94305",
    "sg:province":"CA",
    "sg:tags":[
        "garbage",
        "collection"
    ],
    "wof:name":"Peninsula Sanitary Svc",
    "wof:placetype":"venue"
},
  "geometry": {"coordinates":[-122.15906200000001,37.428064],"type":"Point"}
}