{
  "type": "Feature",
  "properties": {
    "addr:full":"9018 Lindblade Street Culver City CA 90232",
    "addr:housenumber":"9018",
    "addr:postcode":"90232",
    "addr:street":"Lindblade Street",
    "iso:country":"US",
    "sg:address":"9018 Lindblade Street",
    "sg:city":"Culver City",
    "sg:classifiers":[
        {
            "category":"Real Estate",
            "subcategory":"Architect",
            "type":"Services"
        }
    ],
    "sg:phone":"+1 310 815 2000",
    "sg:postcode":"90232",
    "sg:province":"CA",
    "wof:name":"Robert Ginsberg & Associates",
    "wof:placetype":"venue"
},
  "geometry": {"coordinates":[-118.390365,34.025049],"type":"Point"}
}