{
  "type": "Feature",
  "properties": {
    "addr:full":"1414 W Carson St Torrance CA 90501",
    "addr:housenumber":"1414",
    "addr:postcode":"90501",
    "addr:street":"W Carson St",
    "iso:country":"US",
    "sg:address":"1414 W Carson St",
    "sg:city":"Torrance",
    "sg:classifiers":[
        {
            "category":"Shopping",
            "subcategory":"Stationery & Office Supplies",
            "type":"Retail Goods"
        },
        {
            "category":"Autos & Motor Vehicles",
            "subcategory":"Automobile Sales",
            "type":"Retail Goods"
        }
    ],
    "sg:phone":"+1 310 618 8030",
    "sg:postcode":"90501",
    "sg:province":"CA",
    "sg:tags":[
        "repair",
        "tool",
        "machine",
        "part",
        "tools-repairing",
        "rebuild"
    ],
    "wof:name":"Williams Rooter",
    "wof:placetype":"venue"
},
  "geometry": {"coordinates":[-118.301962,33.831532],"type":"Point"}
}