{
  "type": "Feature",
  "properties": {
    "iso:country":"US",
    "sg:address":"3800 Lankershim Blvd",
    "sg:city":"Studio City",
    "sg:classifiers":[
        {
            "category":"Retail",
            "subcategory":"Car Wash",
            "type":"Services"
        }
    ],
    "sg:phone":"+1 818 754 1004",
    "sg:postcode":"90068",
    "sg:province":"CA",
    "sg:tags":[
        "polishing",
        "washing"
    ],
    "wof:name":"Steve's Detailing & Hand Car",
    "wof:placetype":"venue"
},
  "geometry": {"coordinates":[-118.362925,34.137682],"type":"Point"}
}