{
  "type": "Feature",
  "properties": {
    "addr:full":"7805W Sunset Blvd Los Angeles CA 90046",
    "addr:housenumber":"7805w",
    "addr:postcode":"90046",
    "addr:street":"Sunset Blvd",
    "iso:country":"US",
    "sg:address":"7805W Sunset Blvd",
    "sg:city":"Los Angeles",
    "sg:classifiers":[
        {
            "category":"Shopping",
            "subcategory":"Shoes",
            "type":"Retail Goods"
        }
    ],
    "sg:phone":"+1 323 876 7308",
    "sg:postcode":"90046",
    "sg:province":"CA",
    "sg:tags":[
        "store"
    ],
    "sg:website":"www.ballardfootwear.com",
    "wof:name":"Ballard Custom Footwear",
    "wof:placetype":"venue"
},
  "geometry": {"coordinates":[-118.359283,34.098081],"type":"Point"}
}