{
  "type": "Feature",
  "properties": {
    "iso:country":"US",
    "sg:address":"207 Woodland Pkwy",
    "sg:city":"San Marcos",
    "sg:classifiers":[
        {
            "category":"Shopping",
            "subcategory":"Hobbies, Toys, & Games",
            "type":"Retail Goods"
        }
    ],
    "sg:phone":"+1 760 744 2078",
    "sg:postcode":"92069",
    "sg:province":"CA",
    "wof:name":"Boys Toys",
    "wof:placetype":"venue"
},
  "geometry": {"coordinates":[-117.137271,33.142739],"type":"Point"}
}