{
  "type": "Feature",
  "properties": {
    "addr:full":"1157 N Long Beach Blvd Long Beach CA 90813",
    "addr:housenumber":"1157",
    "addr:postcode":"90813",
    "addr:street":"N Long Beach Blvd",
    "iso:country":"US",
    "sg:address":"1157 N Long Beach Blvd",
    "sg:city":"Long Beach",
    "sg:classifiers":[
        {
            "category":"Building & Trades",
            "subcategory":"Construction",
            "type":"Services"
        }
    ],
    "sg:phone":"+1 562 628 9582",
    "sg:postcode":"90813",
    "sg:province":"CA",
    "sg:tags":[
        "tile",
        "dealer"
    ],
    "wof:name":"All Tile",
    "wof:placetype":"venue"
},
  "geometry": {"coordinates":[-118.18944500000001,33.78114],"type":"Point"}
}