{
  "type": "Feature",
  "properties": {
    "iso:country":"US",
    "sg:address":"8065 Brentwood Blvd Ste 3",
    "sg:city":"Brentwood",
    "sg:classifiers":[
        {
            "category":"Personal",
            "subcategory":"Nail Salon",
            "type":"Services"
        }
    ],
    "sg:phone":"+1 925 634 4563",
    "sg:postcode":"94513",
    "sg:province":"CA",
    "wof:name":"Le Nails",
    "wof:placetype":"venue"
},
  "geometry": {"coordinates":[-121.695999,37.939301],"type":"Point"}
}