{
  "type": "Feature",
  "properties": {
    "addr:full":"2930 Wisteria Ln Castro Valley CA 94546",
    "addr:housenumber":"2930",
    "addr:postcode":"94546",
    "addr:street":"Wisteria Ln",
    "iso:country":"US",
    "sg:address":"2930 Wisteria Ln",
    "sg:city":"Castro Valley",
    "sg:classifiers":[
        {
            "category":"Shopping",
            "subcategory":"Gifts & Souvenirs",
            "type":"Retail Goods"
        }
    ],
    "sg:phone":"+1 510 538 4909",
    "sg:postcode":"94546",
    "sg:province":"CA",
    "wof:name":"Bannies Balloons",
    "wof:placetype":"venue"
},
  "geometry": {"coordinates":[-122.08736500000001,37.701045],"type":"Point"}
}