{
  "type": "Feature",
  "properties": {
    "iso:country":"US",
    "sg:address":"3811 Artesia Ave",
    "sg:city":"Fullerton",
    "sg:classifiers":[
        {
            "category":"Retail",
            "subcategory":"Auto Repair",
            "type":"Services"
        }
    ],
    "sg:phone":"+1 714 523 4741",
    "sg:postcode":"92833",
    "sg:province":"CA",
    "sg:tags":[
        "body",
        "shop"
    ],
    "wof:name":"U S A-1 Auto Body Shop",
    "wof:placetype":"venue"
},
  "geometry": {"coordinates":[-117.98200199999999,33.873501],"type":"Point"}
}