{
  "type": "Feature",
  "properties": {
    "iso:country":"US",
    "sg:address":"3649 Mission Inn Ave",
    "sg:city":"Riverside",
    "sg:classifiers":[
        {
            "category":"Restaurant",
            "type":"Food & Drink"
        }
    ],
    "sg:phone":"+1 800 843 7755",
    "sg:postcode":"92501",
    "sg:province":"CA",
    "sg:tags":[
        "house",
        "style",
        "steak",
        "family"
    ],
    "wof:name":"Duane's Prime Steak & Seafood",
    "wof:placetype":"venue"
},
  "geometry": {"coordinates":[-117.37318,33.982655],"type":"Point"}
}