{
  "type": "Feature",
  "properties": {
    "addr:full":"1560 Linda Rosa Ave Los Angeles CA 90041",
    "addr:housenumber":"1560",
    "addr:postcode":"90041",
    "addr:street":"Linda Rosa Ave",
    "iso:country":"US",
    "sg:address":"1560 Linda Rosa Ave",
    "sg:city":"Los Angeles",
    "sg:classifiers":[
        {
            "category":"Travel",
            "subcategory":"Travel Agent",
            "type":"Entertainment"
        }
    ],
    "sg:phone":"+1 323 255 7443",
    "sg:postcode":"90041",
    "sg:province":"CA",
    "sg:tags":[
        "agency",
        "bureau"
    ],
    "wof:name":"Taj Travel Express",
    "wof:placetype":"venue"
},
  "geometry": {"coordinates":[-118.20098299999999,34.134683],"type":"Point"}
}