{
  "type": "Feature",
  "properties": {
    "iso:country":"US",
    "sg:address":"1668 Scarlet Pl",
    "sg:city":"Santa Rosa",
    "sg:classifiers":[
        {
            "category":"Professional",
            "subcategory":"Business Services",
            "type":"Services"
        },
        {
            "category":"Building & Trades",
            "subcategory":"Construction",
            "type":"Services"
        }
    ],
    "sg:phone":"+1 707 576 8145",
    "sg:postcode":"95403",
    "sg:province":"CA",
    "sg:tags":[
        "drafting",
        "nonresidential"
    ],
    "sg:website":"www.christophersdesigns.com",
    "wof:name":"Christopher's Designs",
    "wof:placetype":"venue"
},
  "geometry": {"coordinates":[-122.751807,38.479134],"type":"Point"}
}