{
  "type": "Feature",
  "properties": {
    "addr:full":"6300 Canoga Ave Woodland Hills CA 91367",
    "addr:housenumber":"6300",
    "addr:postcode":"91367",
    "addr:street":"Canoga Ave",
    "iso:country":"US",
    "sg:address":"6300 Canoga Ave",
    "sg:city":"Woodland Hills",
    "sg:classifiers":[
        {
            "category":"Professional",
            "subcategory":"Computer Services",
            "type":"Services"
        }
    ],
    "sg:phone":"+1 818 598 6608",
    "sg:postcode":"91367",
    "sg:province":"CA",
    "sg:tags":[
        "programing",
        "custom"
    ],
    "wof:name":"Oao Healthcare Solutions Inc",
    "wof:placetype":"venue"
},
  "geometry": {"coordinates":[-118.597341,34.188276],"type":"Point"}
}