{
  "type": "Feature",
  "properties": {
    "addr:full":"4140 Beverly Blvd Los Angeles CA 90004",
    "addr:housenumber":"4140",
    "addr:postcode":"90004",
    "addr:street":"Beverly Blvd",
    "iso:country":"US",
    "sg:address":"4140 Beverly Blvd",
    "sg:city":"Los Angeles",
    "sg:classifiers":[
        {
            "category":"Food & Beverages",
            "subcategory":"Groceries & Convenience Stores",
            "type":"Retail Goods"
        }
    ],
    "sg:phone":"+1 213 380 4543",
    "sg:postcode":"90004",
    "sg:province":"CA",
    "wof:name":"El Latino Market",
    "wof:placetype":"venue"
},
  "geometry": {"coordinates":[-118.300003,34.076401],"type":"Point"}
}