{
  "type": "Feature",
  "properties": {
    "addr:full":"5100 Lakewood Blvd Lakewood CA 90716",
    "addr:housenumber":"5100",
    "addr:postcode":"90716",
    "addr:street":"Lakewood Blvd",
    "iso:country":"US",
    "sg:address":"5100 Lakewood Blvd",
    "sg:city":"Lakewood",
    "sg:classifiers":[
        {
            "category":"Shopping",
            "subcategory":"Beauty & Cosmetics",
            "type":"Retail Goods"
        }
    ],
    "sg:postcode":"90716",
    "sg:province":"CA",
    "sg:tags":[
        "supply"
    ],
    "sg:website":"www.maccosmetics.com",
    "wof:name":"MAC Cosmetics - Macy's",
    "wof:placetype":"venue"
},
  "geometry": {"coordinates":[-118.142444,33.85052],"type":"Point"}
}