{
  "type": "Feature",
  "properties": {
    "addr:full":"2569 Hallmark Dr Belmont CA 94002",
    "addr:housenumber":"2569",
    "addr:postcode":"94002",
    "addr:street":"Hallmark Dr",
    "iso:country":"US",
    "sg:address":"2569 Hallmark Dr",
    "sg:city":"Belmont",
    "sg:classifiers":[
        {
            "category":"Education",
            "subcategory":"University",
            "type":"Public Place"
        }
    ],
    "sg:phone":"+1 510 642 8226",
    "sg:postcode":"94002",
    "sg:province":"CA",
    "sg:tags":[
        "college"
    ],
    "wof:name":"University Of California, Berkeley",
    "wof:placetype":"venue"
},
  "geometry": {"coordinates":[-122.307461,37.502518],"type":"Point"}
}