{
  "type": "Feature",
  "properties": {
    "iso:country":"US",
    "sg:address":"2100 N Rancho Ave",
    "sg:city":"Colton",
    "sg:classifiers":[
        {
            "category":"Professional",
            "type":"Services"
        }
    ],
    "sg:phone":"+1 909 384 9505",
    "sg:postcode":"92324",
    "sg:province":"CA",
    "wof:name":"Mystique Cell",
    "wof:placetype":"venue"
},
  "geometry": {"coordinates":[-117.333584,34.093264],"type":"Point"}
}