{
  "type": "Feature",
  "properties": {
    "iso:country":"US",
    "sg:address":"14362 High Valley Rd",
    "sg:city":"Poway",
    "sg:classifiers":[
        {
            "category":"Farming",
            "subcategory":"Farm",
            "type":"Manufacturing & Wholesale Goods"
        }
    ],
    "sg:phone":"+1 858 675 8691",
    "sg:postcode":"92064",
    "sg:province":"CA",
    "sg:tags":[
        "crop",
        "general"
    ],
    "wof:name":"GPA Farms",
    "wof:placetype":"venue"
},
  "geometry": {"coordinates":[-117.020661,32.990665],"type":"Point"}
}