{
  "type": "Feature",
  "properties": {
    "addr:full":"820 H St Modesto CA 95354",
    "addr:housenumber":"820",
    "addr:postcode":"ca 95354",
    "addr:street":"H St",
    "iso:country":"US",
    "sg:address":"820 H St",
    "sg:city":"Modesto",
    "sg:classifiers":[
        {
            "category":"Organizations",
            "subcategory":"Religious Organization",
            "type":"Services"
        }
    ],
    "sg:phone":"+1 209 579 0338",
    "sg:postcode":"95354",
    "sg:province":"CA",
    "sg:tags":[
        "church"
    ],
    "sg:website":"www.takingdominion.org",
    "wof:name":"Dominion Christian Ctr",
    "wof:placetype":"venue"
},
  "geometry": {"coordinates":[-120.99897900000001,37.637755],"type":"Point"}
}