{
  "type": "Feature",
  "properties": {
    "iso:country":"US",
    "sg:address":"1329 Powell St",
    "sg:city":"San Francisco",
    "sg:classifiers":[
        {
            "category":"Personal",
            "subcategory":"Beauty Salon",
            "type":"Services"
        }
    ],
    "sg:postcode":"94101",
    "sg:province":"CA",
    "sg:tags":[
        "spa"
    ],
    "wof:name":"Hong Kong Green Palace Beauty Salon",
    "wof:placetype":"venue"
},
  "geometry": {"coordinates":[-122.410155,37.796876],"type":"Point"}
}