{
  "type": "Feature",
  "properties": {
    "addr:full":"285 W Bullard Ave Fresno CA 93704",
    "addr:housenumber":"285",
    "addr:postcode":"93704",
    "addr:street":"W Bullard Ave",
    "iso:country":"US",
    "sg:address":"285 W Bullard Ave",
    "sg:city":"Fresno",
    "sg:classifiers":[
        {
            "category":"Wholesale",
            "subcategory":"Computers",
            "type":"Manufacturing & Wholesale Goods"
        }
    ],
    "sg:phone":"+1 559 447 3520",
    "sg:postcode":"93704",
    "sg:province":"CA",
    "sg:tags":[
        "equipment",
        "processing",
        "datum"
    ],
    "wof:name":"IBM Corp",
    "wof:placetype":"venue"
},
  "geometry": {"coordinates":[-119.795057,36.822829],"type":"Point"}
}