{
  "type": "Feature",
  "properties": {
    "addr:full":"406 W Ocean Ave Lompoc CA 93436",
    "addr:housenumber":"406",
    "addr:postcode":"93436",
    "addr:street":"W Ocean Ave",
    "iso:country":"US",
    "sg:address":"406 W Ocean Ave",
    "sg:city":"Lompoc",
    "sg:classifiers":[
        {
            "category":"Shopping",
            "subcategory":"Musical Instruments",
            "type":"Retail Goods"
        }
    ],
    "sg:phone":"+1 805 735 9097",
    "sg:postcode":"93436",
    "sg:province":"CA",
    "sg:tags":[
        "music",
        "dealer"
    ],
    "wof:name":"Discolandia",
    "wof:placetype":"venue"
},
  "geometry": {"coordinates":[-120.461798,34.638892],"type":"Point"}
}