{
  "type": "Feature",
  "properties": {
    "addr:full":"10621 Bloomfield St Los Alamitos CA 90720",
    "addr:housenumber":"10621",
    "addr:postcode":"90720",
    "addr:street":"Bloomfield St",
    "iso:country":"US",
    "sg:address":"10621 Bloomfield St",
    "sg:city":"Los Alamitos",
    "sg:classifiers":[
        {
            "category":"Retail",
            "subcategory":"Repair Shop",
            "type":"Services"
        }
    ],
    "sg:phone":"+1 562 594 5579",
    "sg:postcode":"90720",
    "sg:province":"CA",
    "sg:tags":[
        "picture",
        "framing"
    ],
    "wof:name":"Art Images Frame Shop",
    "wof:placetype":"venue"
},
  "geometry": {"coordinates":[-118.06314,33.818901],"type":"Point"}
}