{
  "type": "Feature",
  "properties": {
    "iso:country":"US",
    "sg:address":"2920 Inland Empire Blvd",
    "sg:city":"Ontario",
    "sg:classifiers":[
        {
            "category":"Professional",
            "subcategory":"Engineering",
            "type":"Services"
        }
    ],
    "sg:phone":"+1 909 945 3000",
    "sg:postcode":"91764",
    "sg:province":"CA",
    "sg:tags":[
        "engineer"
    ],
    "sg:website":"www.cdm.com",
    "wof:name":"Camp Dresser & Mc Kee Inc",
    "wof:placetype":"venue"
},
  "geometry": {"coordinates":[-117.589431,34.07029],"type":"Point"}
}