{
  "type": "Feature",
  "properties": {
    "iso:country":"US",
    "sg:address":"8013 Canterbury Way",
    "sg:city":"Buena Park",
    "sg:classifiers":[
        {
            "category":"Professional",
            "type":"Services"
        }
    ],
    "sg:phone":"+1 714 522 6956",
    "sg:postcode":"90620",
    "sg:province":"CA",
    "wof:name":"Laser Image 2000",
    "wof:placetype":"venue"
},
  "geometry": {"coordinates":[-117.992126,33.854783],"type":"Point"}
}