{
  "type": "Feature",
  "properties": {
    "iso:country":"US",
    "sg:address":"850 North Lake Boulevard",
    "sg:city":"Sunnyside-Tahoe City",
    "sg:classifiers":[
        {
            "category":"Health Services",
            "subcategory":"Clinic",
            "type":"Services"
        }
    ],
    "sg:phone":"+1 530 584 0244",
    "sg:postcode":"96146",
    "sg:province":"CA",
    "sg:tags":[
        "medical"
    ],
    "wof:name":"CVS",
    "wof:placetype":"venue"
},
  "geometry": {"coordinates":[-120.137882,39.174001],"type":"Point"}
}