{
  "type": "Feature",
  "properties": {
    "iso:country":"US",
    "sg:address":"2409 E 19th St",
    "sg:city":"Signal Hill",
    "sg:classifiers":[
        {
            "category":"Building & Trades",
            "subcategory":"Construction",
            "type":"Services"
        }
    ],
    "sg:phone":"+1 562 592 1136",
    "sg:postcode":"90755",
    "sg:province":"CA",
    "sg:tags":[
        "wallpaper"
    ],
    "wof:name":"South Bay Paperhangers",
    "wof:placetype":"venue"
},
  "geometry": {"coordinates":[-118.162817,33.791728],"type":"Point"}
}