{
  "type": "Feature",
  "properties": {
    "addr:full":"11039 Downey Avenue Downey CA 90241",
    "addr:housenumber":"11039",
    "addr:postcode":"90241",
    "addr:street":"Downey Avenue",
    "iso:country":"US",
    "sg:address":"11039 Downey Avenue",
    "sg:city":"Downey",
    "sg:classifiers":[
        {
            "category":"Restaurant",
            "type":"Food & Drink"
        }
    ],
    "sg:phone":"+1 562 869 2607",
    "sg:postcode":"90241",
    "sg:province":"CA",
    "sg:tags":[
        "chinese"
    ],
    "wof:name":"Peking Restaurant",
    "wof:placetype":"venue"
},
  "geometry": {"coordinates":[-118.13236000000001,33.941095],"type":"Point"}
}