{
  "type": "Feature",
  "properties": {
    "addr:full":"2318 Mission St San Francisco CA 94110",
    "addr:housenumber":"2318",
    "addr:postcode":"94110",
    "addr:street":"Mission St",
    "iso:country":"US",
    "sg:address":"2318 Mission St",
    "sg:city":"San Francisco",
    "sg:classifiers":[
        {
            "category":"Shopping",
            "subcategory":"Used Merchandise",
            "type":"Retail Goods"
        }
    ],
    "sg:phone":"+1 415 647 5000",
    "sg:postcode":"94110",
    "sg:province":"CA",
    "sg:tags":[
        "pawnbroker"
    ],
    "wof:name":"Mission Jewelry & Loan",
    "wof:placetype":"venue"
},
  "geometry": {"coordinates":[-122.419149,37.758921],"type":"Point"}
}