{
  "type": "Feature",
  "properties": {
    "iso:country":"US",
    "sg:address":"1735 Villa Ave",
    "sg:city":"Clovis",
    "sg:classifiers":[
        {
            "category":"Retail",
            "subcategory":"Veterinary Services",
            "type":"Services"
        }
    ],
    "sg:phone":"+1 559 325 0200",
    "sg:postcode":"93612",
    "sg:province":"CA",
    "sg:tags":[
        "veterinarian",
        "emergency"
    ],
    "wof:name":"Country Veterinary Clinic",
    "wof:placetype":"venue"
},
  "geometry": {"coordinates":[-119.713551,36.810313],"type":"Point"}
}