{
  "type": "Feature",
  "properties": {
    "addr:full":"4552 N Towne Ave Claremont CA 91711",
    "addr:housenumber":"4552",
    "addr:postcode":"91711",
    "addr:street":"N Towne Ave",
    "iso:country":"US",
    "sg:address":"4552 N Towne Ave",
    "sg:city":"Claremont",
    "sg:classifiers":[
        {
            "category":"Place Of Worship",
            "subcategory":"Church",
            "type":"Public Place"
        },
        {
            "category":"Place Of Worship",
            "type":"Public Place"
        }
    ],
    "sg:phone":"+1 909 624 6626",
    "sg:postcode":"91711",
    "sg:province":"CA",
    "sg:tags":[
        "churches-baptist-general",
        "churches-baptist",
        "christ",
        "churches-community"
    ],
    "sg:website":"http://www.glbc.net",
    "wof:name":"Baseline Community Church",
    "wof:placetype":"venue"
},
  "geometry": {"coordinates":[-117.736462,34.123249],"type":"Point"}
}