{
  "type": "Feature",
  "properties": {
    "addr:full":"2520 E Palmdale Blvd Palmdale CA 93550",
    "addr:housenumber":"2520",
    "addr:postcode":"ca 93550",
    "addr:street":"E Palmdale Blvd",
    "iso:country":"US",
    "sg:address":"2520 E Palmdale Blvd",
    "sg:city":"Palmdale",
    "sg:classifiers":[
        {
            "category":"Professional",
            "type":"Services"
        },
        {
            "category":"Shopping",
            "type":"Retail Goods"
        }
    ],
    "sg:phone":"+1 323 972 3601",
    "sg:postcode":"93550",
    "sg:province":"CA",
    "sg:tags":[
        "candle"
    ],
    "wof:name":"Celeste's Botanic",
    "wof:placetype":"venue"
},
  "geometry": {"coordinates":[-118.08511,34.580139],"type":"Point"}
}