{
  "type": "Feature",
  "properties": {
    "iso:country":"US",
    "sg:address":"3132 E Pleasant Valley Rd",
    "sg:city":"Oxnard",
    "sg:classifiers":[
        {
            "category":"Shopping",
            "subcategory":"Florist",
            "type":"Retail Goods"
        }
    ],
    "sg:phone":"+1 805 986 2776",
    "sg:postcode":"93033",
    "sg:province":"CA",
    "wof:name":"Pleasant Valley Flowers",
    "wof:placetype":"venue"
},
  "geometry": {"coordinates":[-119.13200399999999,34.171299],"type":"Point"}
}