{
  "type": "Feature",
  "properties": {
    "iso:country":"US",
    "sg:address":"617 S Olive St Ste 206 Suite 1010",
    "sg:city":"Los Angeles",
    "sg:classifiers":[
        {
            "category":"Shopping",
            "subcategory":"Jewelry",
            "type":"Retail Goods"
        }
    ],
    "sg:phone":"+1 213 892 1033",
    "sg:postcode":"90014",
    "sg:province":"CA",
    "wof:name":"Cedrick Jewelry",
    "wof:placetype":"venue"
},
  "geometry": {"coordinates":[-118.25447,34.047695],"type":"Point"}
}