{
  "type": "Feature",
  "properties": {
    "iso:country":"US",
    "sg:address":"8675 Baseline Rd",
    "sg:city":"Rancho Cucamonga",
    "sg:classifiers":[
        {
            "category":"Wholesale",
            "subcategory":"Groceries",
            "type":"Manufacturing & Wholesale Goods"
        }
    ],
    "sg:phone":"+1 909 948 5366",
    "sg:postcode":"91730",
    "sg:province":"CA",
    "sg:tags":[
        "grocer"
    ],
    "sg:website":"www.smartandfinal.com",
    "wof:name":"Smart & Final",
    "wof:placetype":"venue"
},
  "geometry": {"coordinates":[-117.618416,34.121565],"type":"Point"}
}