{
  "type": "Feature",
  "properties": {
    "addr:full":"96 Murica Aisle Irvine CA 92614",
    "addr:housenumber":"96",
    "addr:postcode":"92614",
    "addr:street":"Murica Aisle",
    "iso:country":"US",
    "sg:address":"96 Murica Aisle",
    "sg:city":"Irvine",
    "sg:classifiers":[
        {
            "category":"Shopping",
            "type":"Retail Goods"
        }
    ],
    "sg:phone":"+1 949 260 9640",
    "sg:postcode":"92614",
    "sg:province":"CA",
    "sg:tags":[
        "religious"
    ],
    "wof:name":"Jesus First Intl",
    "wof:placetype":"venue"
},
  "geometry": {"coordinates":[-117.825689,33.683232],"type":"Point"}
}