{
  "type": "Feature",
  "properties": {
    "addr:full":"3901 Cincinnati Ave Rocklin CA 95765",
    "addr:housenumber":"3901",
    "addr:postcode":"95765",
    "addr:street":"Cincinnati Ave",
    "iso:country":"US",
    "sg:address":"3901 Cincinnati Ave",
    "sg:city":"Rocklin",
    "sg:classifiers":[
        {
            "category":"Manufacturing",
            "subcategory":"Building Materials",
            "type":"Manufacturing & Wholesale Goods"
        }
    ],
    "sg:phone":"+1 916 782 4900",
    "sg:postcode":"95765",
    "sg:province":"CA",
    "sg:tags":[
        "mfg"
    ],
    "wof:name":"Doorcraft-Rocklin",
    "wof:placetype":"venue"
},
  "geometry": {"coordinates":[-121.31197,38.819321],"type":"Point"}
}