{
  "type": "Feature",
  "properties": {
    "addr:full":"16055 Sherman Way Van Nuys CA 91406",
    "addr:housenumber":"16055",
    "addr:postcode":"91406",
    "addr:street":"Sherman Way",
    "iso:country":"US",
    "sg:address":"16055 Sherman Way",
    "sg:city":"Van Nuys",
    "sg:classifiers":[
        {
            "category":"Health Services",
            "subcategory":"Doctor",
            "type":"Services"
        }
    ],
    "sg:phone":"+1 818 909 0500",
    "sg:postcode":"91406",
    "sg:province":"CA",
    "sg:tags":[
        "dentist"
    ],
    "wof:name":"St Anthony Dental Office",
    "wof:placetype":"venue"
},
  "geometry": {"coordinates":[-118.480852,34.201129],"type":"Point"}
}