{
  "type": "Feature",
  "properties": {
    "addr:full":"14504 Carmenita Rd Norwalk CA 90650",
    "addr:housenumber":"14504",
    "addr:postcode":"90650",
    "addr:street":"Carmenita Rd",
    "iso:country":"US",
    "sg:address":"14504 Carmenita Rd",
    "sg:city":"Norwalk",
    "sg:classifiers":[
        {
            "category":"Wholesale",
            "subcategory":"Construction Materials",
            "type":"Manufacturing & Wholesale Goods"
        },
        {
            "category":"Manufacturing",
            "subcategory":"Building Materials",
            "type":"Manufacturing & Wholesale Goods"
        }
    ],
    "sg:phone":"+1 562 404 1868",
    "sg:postcode":"90650",
    "sg:province":"CA",
    "sg:tags":[
        "cabinet",
        "wood",
        "kitchen",
        "mfg"
    ],
    "wof:name":"Del Valle Cabinets",
    "wof:placetype":"venue"
},
  "geometry": {"coordinates":[-118.04652,33.899964],"type":"Point"}
}