{
  "type": "Feature",
  "properties": {
    "addr:full":"7912 Seville Ave Huntington Park CA 90255",
    "addr:housenumber":"7912",
    "addr:postcode":"90255",
    "addr:street":"Seville Ave;Park",
    "iso:country":"US",
    "sg:address":"7912 Seville Ave",
    "sg:city":"Huntington Park",
    "sg:classifiers":[
        {
            "category":"Manufacturing",
            "subcategory":"Printing",
            "type":"Manufacturing & Wholesale Goods"
        }
    ],
    "sg:phone":"+1 323 588 5855",
    "sg:postcode":"90255",
    "sg:province":"CA",
    "sg:tags":[
        "printer"
    ],
    "wof:name":"Todd Printing",
    "wof:placetype":"venue"
},
  "geometry": {"coordinates":[-118.22230399999999,33.965648],"type":"Point"}
}