{
  "type": "Feature",
  "properties": {
    "iso:country":"US",
    "sg:address":"7912 Seville Ave",
    "sg:city":"Huntington Park",
    "sg:classifiers":[
        {
            "category":"Manufacturing",
            "subcategory":"Printing",
            "type":"Manufacturing & Wholesale Goods"
        }
    ],
    "sg:phone":"+1 323 588 5855",
    "sg:postcode":"90255",
    "sg:province":"CA",
    "sg:tags":[
        "printer"
    ],
    "wof:name":"Todd Printing",
    "wof:placetype":"venue"
},
  "geometry": {"coordinates":[-118.222304,33.965648],"type":"Point"}
}