{
  "type": "Feature",
  "properties": {
    "iso:country":"US",
    "sg:address":"1 Park Pl",
    "sg:city":"Newport Beach",
    "sg:classifiers":[
        {
            "category":"Health Services",
            "subcategory":"Clinic",
            "type":"Services"
        }
    ],
    "sg:phone":"+1 949 852 7393",
    "sg:postcode":"92663",
    "sg:province":"CA",
    "sg:tags":[
        "specialty",
        "outpatient"
    ],
    "wof:name":"Consortium Rhblttion Prfession",
    "wof:placetype":"venue"
},
  "geometry": {"coordinates":[-117.921284,33.621094],"type":"Point"}
}