{
  "type": "Feature",
  "properties": {
    "iso:country":"US",
    "sg:address":"2449 Valine Ln",
    "sg:city":"Chico",
    "sg:classifiers":[
        {
            "category":"Retail",
            "subcategory":"Auto Repair",
            "type":"Services"
        }
    ],
    "sg:phone":"+1 530 345 1557",
    "sg:postcode":"95928",
    "sg:province":"CA",
    "sg:tags":[
        "carburetor"
    ],
    "wof:name":"Cliff Rose Carburetion",
    "wof:placetype":"venue"
},
  "geometry": {"coordinates":[-121.817249,39.713422],"type":"Point"}
}