{
  "type": "Feature",
  "properties": {
    "addr:full":"1775 Kinsley St Santa Cruz CA 95062",
    "addr:housenumber":"1775",
    "addr:postcode":"95062",
    "addr:street":"Kinsley St",
    "iso:country":"US",
    "sg:address":"1775 Kinsley St",
    "sg:city":"Santa Cruz",
    "sg:classifiers":[
        {
            "category":"Building & Trades",
            "subcategory":"Construction",
            "type":"Services"
        }
    ],
    "sg:phone":"+1 831 239 8024",
    "sg:postcode":"95062",
    "sg:province":"CA",
    "sg:tags":[
        "handyman"
    ],
    "wof:name":"J M Handyman",
    "wof:placetype":"venue"
},
  "geometry": {"coordinates":[-121.983322,36.969695],"type":"Point"}
}