{
  "type": "Feature",
  "properties": {
    "addr:full":"20 City Blvd E Orange CA 92868",
    "addr:housenumber":"20",
    "addr:postcode":"92868",
    "addr:street":"City Blvd E",
    "iso:country":"US",
    "sg:address":"20 City Blvd E",
    "sg:city":"Orange",
    "sg:classifiers":[
        {
            "category":"Manufacturing",
            "subcategory":"Apparel",
            "type":"Manufacturing & Wholesale Goods"
        }
    ],
    "sg:phone":"+1 714 769 3330",
    "sg:postcode":"92868",
    "sg:province":"CA",
    "sg:tags":[
        "clothing",
        "mfg"
    ],
    "wof:name":"Honolua Surf",
    "wof:placetype":"venue"
},
  "geometry": {"coordinates":[-117.894009,33.780114],"type":"Point"}
}