{
  "type": "Feature",
  "properties": {
    "addr:full":"1235 S Mission Rd Fallbrook CA 92028",
    "addr:housenumber":"1235",
    "addr:postcode":"92028",
    "addr:street":"S Mission Rd",
    "iso:country":"US",
    "sg:address":"1235 S Mission Rd",
    "sg:city":"Fallbrook",
    "sg:classifiers":[
        {
            "category":"Restaurant",
            "type":"Food & Drink"
        }
    ],
    "sg:menulink":"http://www.allmenus.com/ca/fallbrook/78554-pizza-hut/menu/",
    "sg:phone":"+1 760 728 5864",
    "sg:postcode":"92028",
    "sg:province":"CA",
    "sg:tags":[
        "american",
        "pizza"
    ],
    "wof:name":"Pizza Hut",
    "wof:placetype":"venue"
},
  "geometry": {"coordinates":[-117.252078,33.370341],"type":"Point"}
}