{
  "type": "Feature",
  "properties": {
    "addr:full":"17161 Goldenwest Street Huntington Beach CA 92647",
    "addr:housenumber":"17161",
    "addr:postcode":"92647",
    "addr:street":"Goldenwest Street",
    "iso:country":"US",
    "sg:address":"17161 Goldenwest Street",
    "sg:city":"Huntington Beach",
    "sg:classifiers":[
        {
            "category":"Education",
            "subcategory":"School",
            "type":"Public Place"
        }
    ],
    "sg:phone":"+1 714 841 7587",
    "sg:postcode":"92647",
    "sg:province":"CA",
    "sg:tags":[
        "high",
        "middle",
        "elementary"
    ],
    "wof:name":"United Chinese Learning Center",
    "wof:placetype":"venue"
},
  "geometry": {"coordinates":[-118.00660499999999,33.713312],"type":"Point"}
}