{
  "type": "Feature",
  "properties": {
    "addr:full":"315 Winnipeg Green Fremont CA 94538",
    "addr:housenumber":"315",
    "addr:postcode":"94538",
    "addr:street":"Winnipeg Green",
    "iso:country":"US",
    "sg:address":"315 Winnipeg Green",
    "sg:city":"Fremont",
    "sg:classifiers":[
        {
            "category":"Recreation",
            "type":"Entertainment"
        }
    ],
    "sg:phone":"+1 510 657 6944",
    "sg:postcode":"94538",
    "sg:province":"CA",
    "sg:tags":[
        "center"
    ],
    "wof:name":"Fremont American Little League",
    "wof:placetype":"venue"
},
  "geometry": {"coordinates":[-121.953395,37.512732],"type":"Point"}
}