{
  "type": "Feature",
  "properties": {
    "addr:full":"32735 Sea Gate Dr Rancho Pls Vrds CA 90275",
    "addr:housenumber":"32735",
    "addr:postcode":"90275",
    "addr:street":"Sea Gate Dr",
    "iso:country":"US",
    "sg:address":"32735 Sea Gate Dr",
    "sg:city":"Rancho Pls Vrds",
    "sg:classifiers":[
        {
            "category":"Real Estate",
            "subcategory":"Real Estate Agent",
            "type":"Services"
        }
    ],
    "sg:phone":"+1 310 377 7960",
    "sg:postcode":"90275",
    "sg:province":"CA",
    "sg:website":"www.pvbayclub.com",
    "wof:name":"Burrell Realty",
    "wof:placetype":"venue"
},
  "geometry": {"coordinates":[-118.388465,33.744009],"type":"Point"}
}