{
  "type": "Feature",
  "properties": {
    "addr:full":"13373 Perris Blvd Moreno Valley CA 92553",
    "addr:housenumber":"13373",
    "addr:postcode":"92553",
    "addr:street":"Perris Blvd",
    "iso:country":"US",
    "sg:address":"13373 Perris Blvd",
    "sg:city":"Moreno Valley",
    "sg:classifiers":[
        {
            "category":"Food & Beverages",
            "subcategory":"Meat & Fish",
            "type":"Retail Goods"
        }
    ],
    "sg:phone":"+1 951 242 8161",
    "sg:postcode":"92553",
    "sg:province":"CA",
    "wof:name":"LA Perla Meat Market",
    "wof:placetype":"venue"
},
  "geometry": {"coordinates":[-117.226353,33.926353],"type":"Point"}
}