{
  "type": "Feature",
  "properties": {
    "iso:country":"US",
    "sg:address":"45 Shield",
    "sg:city":"Irvine",
    "sg:classifiers":[
        {
            "category":"Building & Trades",
            "subcategory":"Construction",
            "type":"Services"
        }
    ],
    "sg:phone":"+1 949 679 7318",
    "sg:postcode":"92618",
    "sg:province":"CA",
    "sg:tags":[
        "interior",
        "design"
    ],
    "wof:name":"Auston Johnson Interiors",
    "wof:placetype":"venue"
},
  "geometry": {"coordinates":[-117.766391,33.679375],"type":"Point"}
}