{
  "type": "Feature",
  "properties": {
    "addr:full":"7735 Soquel Dr Aptos CA 95003",
    "addr:housenumber":"7735",
    "addr:postcode":"ca 95003",
    "addr:street":"Soquel Dr",
    "iso:country":"US",
    "sg:address":"7735 Soquel Dr",
    "sg:city":"Aptos",
    "sg:classifiers":[
        {
            "category":"Shopping",
            "subcategory":"Gifts & Souvenirs",
            "type":"Retail Goods"
        }
    ],
    "sg:phone":"+1 831 662 2954",
    "sg:postcode":"95003",
    "sg:province":"CA",
    "sg:tags":[
        "shop"
    ],
    "wof:name":"Sweet Pea Home & Gift Boutique",
    "wof:placetype":"venue"
},
  "geometry": {"coordinates":[-121.907084,36.97851],"type":"Point"}
}