{
  "type": "Feature",
  "properties": {
    "addr:full":"27800 Oak View Drive Aliso Viejo CA 92656",
    "addr:housenumber":"27800",
    "addr:postcode":"92656",
    "addr:street":"Oak View Drive",
    "iso:country":"US",
    "sg:address":"27800 Oak View Drive",
    "sg:city":"Aliso Viejo",
    "sg:classifiers":[
        {
            "category":"Education",
            "subcategory":"School",
            "type":"Public Place"
        }
    ],
    "sg:phone":"+1 949 234 5941",
    "sg:postcode":"92656",
    "sg:province":"CA",
    "sg:tags":[
        "high",
        "middle",
        "elementary"
    ],
    "wof:name":"Capistrano Unified School District",
    "wof:placetype":"venue"
},
  "geometry": {"coordinates":[-117.731246,33.561948],"type":"Point"}
}