{
  "type": "Feature",
  "properties": {
    "iso:country":"US",
    "sg:address":"33509 Valley Center Rd",
    "sg:city":"Valley Center",
    "sg:classifiers":[
        {
            "category":"Social Services",
            "type":"Services"
        }
    ],
    "sg:phone":"+1 760 749 5608",
    "sg:postcode":"92082",
    "sg:province":"CA",
    "sg:tags":[
        "organization",
        "welfare"
    ],
    "wof:name":"So Ca Tribal Chairman's Assn",
    "wof:placetype":"venue"
},
  "geometry": {"coordinates":[-116.959522,33.255615],"type":"Point"}
}