{
  "type": "Feature",
  "properties": {
    "addr:full":"490 San Benito Cir Salinas CA 93905",
    "addr:housenumber":"490",
    "addr:postcode":"93905",
    "addr:street":"San Benito Cir",
    "iso:country":"US",
    "sg:address":"490 San Benito Cir",
    "sg:city":"Salinas",
    "sg:classifiers":[
        {
            "category":"Recreation",
            "type":"Entertainment"
        }
    ],
    "sg:phone":"+1 831 422 8319",
    "sg:postcode":"93905",
    "sg:province":"CA",
    "sg:tags":[
        "hall",
        "auditorium"
    ],
    "wof:name":"Portuguese Social Hall",
    "wof:placetype":"venue"
},
  "geometry": {"coordinates":[-121.63963099999999,36.673228],"type":"Point"}
}