{
  "type": "Feature",
  "properties": {
    "iso:country":"US",
    "sg:address":"91 Broadway Ln",
    "sg:city":"Walnut Creek",
    "sg:classifiers":[
        {
            "category":"Travel",
            "subcategory":"Travel Agent",
            "type":"Entertainment"
        }
    ],
    "sg:phone":"+1 925 938 0800",
    "sg:postcode":"94596",
    "sg:province":"CA",
    "sg:tags":[
        "agency",
        "bureau"
    ],
    "wof:name":"American Express Travel Rltd",
    "wof:placetype":"venue"
},
  "geometry": {"coordinates":[-122.058087,37.895276],"type":"Point"}
}