{
  "type": "Feature",
  "properties": {
    "addr:full":"1527 Old Oak Park Rd Arroyo Grande CA 93420",
    "addr:housenumber":"1527",
    "addr:postcode":"93420",
    "addr:street":"Old Oak Park Rd",
    "iso:country":"US",
    "sg:address":"1527 Old Oak Park Rd",
    "sg:city":"Arroyo Grande",
    "sg:classifiers":[
        {
            "category":"Building & Trades",
            "subcategory":"Construction",
            "type":"Services"
        }
    ],
    "sg:phone":"+1 805 481 8530",
    "sg:postcode":"93420",
    "sg:province":"CA",
    "sg:tags":[
        "roofing",
        "contractor"
    ],
    "sg:website":"www.amwsc.com",
    "wof:name":"American Roofing",
    "wof:placetype":"venue"
},
  "geometry": {"coordinates":[-120.59983099999999,35.149496],"type":"Point"}
}