{
  "type": "Feature",
  "properties": {
    "addr:full":"1355 E Hillcrest Dr Thousand Oaks CA 91362",
    "addr:housenumber":"1355",
    "addr:postcode":"91362",
    "addr:street":"E Hillcrest Dr",
    "iso:country":"US",
    "sg:address":"1355 E Hillcrest Dr",
    "sg:city":"Thousand Oaks",
    "sg:classifiers":[
        {
            "category":"Professional",
            "subcategory":"Computer Services",
            "type":"Services"
        }
    ],
    "sg:phone":"+1 805 778 9221",
    "sg:postcode":"91362",
    "sg:province":"CA",
    "sg:tags":[
        "developer"
    ],
    "wof:name":"ASM Solutions",
    "wof:placetype":"venue"
},
  "geometry": {"coordinates":[-118.856611,34.181831],"type":"Point"}
}