{
  "type": "Feature",
  "properties": {
    "addr:full":"575 E Pico Blvd Los Angeles CA 90015",
    "addr:housenumber":"575",
    "addr:postcode":"90015",
    "addr:street":"E Pico Blvd",
    "iso:country":"US",
    "sg:address":"575 E Pico Blvd",
    "sg:city":"Los Angeles",
    "sg:classifiers":[
        {
            "category":"Restaurant",
            "type":"Food & Drink"
        }
    ],
    "sg:phone":"+1 213 741 2370",
    "sg:postcode":"90015",
    "sg:province":"CA",
    "wof:name":"El Salvador Cafe",
    "wof:placetype":"venue"
},
  "geometry": {"coordinates":[-118.25512500000001,34.033575],"type":"Point"}
}