{
  "type": "Feature",
  "properties": {
    "addr:full":"1145 S de Anza Blvd San Jose CA 95129",
    "addr:housenumber":"1145",
    "addr:postcode":"95129",
    "addr:street":"S De Anza Blvd",
    "iso:country":"US",
    "sg:address":"1145 S de Anza Blvd",
    "sg:city":"San Jose",
    "sg:classifiers":[
        {
            "category":"Personal",
            "type":"Services"
        }
    ],
    "sg:phone":"+1 408 973 1088",
    "sg:postcode":"95129",
    "sg:province":"CA",
    "sg:tags":[
        "program",
        "physical",
        "exercise",
        "fitness"
    ],
    "wof:name":"Right Stuff Health Club-Women",
    "wof:placetype":"venue"
},
  "geometry": {"coordinates":[-122.032324,37.303985],"type":"Point"}
}