{
  "type": "Feature",
  "properties": {
    "iso:country":"US",
    "sg:address":"6151 W Pico Ave",
    "sg:city":"Los Angeles",
    "sg:classifiers":[
        {
            "category":"Shopping",
            "subcategory":"Crafts & Fabrics",
            "type":"Retail Goods"
        }
    ],
    "sg:phone":"+1 323 653 6663",
    "sg:postcode":"90035",
    "sg:province":"CA",
    "sg:tags":[
        "store"
    ],
    "sg:website":"www.moodfabrics.com",
    "wof:name":"Mood Designer Fabrics",
    "wof:placetype":"venue"
},
  "geometry": {"coordinates":[-118.375626,34.053226],"type":"Point"}
}