{
  "type": "Feature",
  "properties": {
    "iso:country":"US",
    "sg:address":"2440 N Glassell St",
    "sg:city":"Orange",
    "sg:classifiers":[
        {
            "category":"Building & Trades",
            "subcategory":"Construction",
            "type":"Services"
        }
    ],
    "sg:phone":"+1 714 637 3330",
    "sg:postcode":"92865",
    "sg:province":"CA",
    "sg:tags":[
        "interior",
        "design"
    ],
    "wof:name":"Clairmont Design",
    "wof:placetype":"venue"
},
  "geometry": {"coordinates":[-117.853155,33.828358],"type":"Point"}
}