{
  "type": "Feature",
  "properties": {
    "iso:country":"US",
    "sg:address":"1060 Reno Ave",
    "sg:city":"Modesto",
    "sg:classifiers":[
        {
            "category":"Manufacturing",
            "subcategory":"Metals",
            "type":"Manufacturing & Wholesale Goods"
        }
    ],
    "sg:phone":"+1 209 529 8504",
    "sg:postcode":"95351",
    "sg:province":"CA",
    "sg:tags":[
        "steel"
    ],
    "sg:website":"www.fabpi.com",
    "wof:name":"Fabritec Precision Inc",
    "wof:placetype":"venue"
},
  "geometry": {"coordinates":[-121.02787600000001,37.650295],"type":"Point"}
}