{
  "type": "Feature",
  "properties": {
    "iso:country":"US",
    "sg:address":"4722 N Maroa Ave",
    "sg:city":"Fresno",
    "sg:classifiers":[
        {
            "category":"Recreation",
            "type":"Entertainment"
        }
    ],
    "sg:phone":"+1 559 222 4816",
    "sg:postcode":"93704",
    "sg:province":"CA",
    "sg:tags":[
        "tennis",
        "court"
    ],
    "wof:name":"Fig Garden Swim & Racket Club",
    "wof:placetype":"venue"
},
  "geometry": {"coordinates":[-119.799408,36.803558],"type":"Point"}
}