{
  "type": "Feature",
  "properties": {
    "iso:country":"US",
    "sg:address":"2240 S Macarthur Dr",
    "sg:city":"Tracy",
    "sg:classifiers":[
        {
            "category":"Arts & Performance",
            "subcategory":"Theater",
            "type":"Entertainment"
        }
    ],
    "sg:phone":"+1 209 834 2300",
    "sg:postcode":"95376",
    "sg:province":"CA",
    "sg:tags":[
        "bureau"
    ],
    "wof:name":"Full Blast Music Group",
    "wof:placetype":"venue"
},
  "geometry": {"coordinates":[-121.416377,37.725022],"type":"Point"}
}