{
  "type": "Feature",
  "properties": {
    "iso:country":"US",
    "sg:address":"2323 Monte Vista Dr",
    "sg:city":"Pinole",
    "sg:classifiers":[
        {
            "category":"Professional",
            "subcategory":"Detective & Security Services",
            "type":"Services"
        }
    ],
    "sg:phone":"+1 510 409 9373",
    "sg:postcode":"94564",
    "sg:province":"CA",
    "sg:tags":[
        "guard",
        "patrol"
    ],
    "wof:name":"Eagle I Surveillance Systems",
    "wof:placetype":"venue"
},
  "geometry": {"coordinates":[-122.270871,37.984778],"type":"Point"}
}