{
  "type": "Feature",
  "properties": {
    "iso:country":"US",
    "sg:address":"10880 Wilshire Blvd",
    "sg:city":"Los Angeles",
    "sg:classifiers":[
        {
            "category":"Retail",
            "subcategory":"Laundry & Dry Cleaning",
            "type":"Services"
        }
    ],
    "sg:postcode":"90024",
    "sg:province":"CA",
    "wof:name":"R & B Dry Cleaners",
    "wof:placetype":"venue"
},
  "geometry": {"coordinates":[-118.442684,34.059136],"type":"Point"}
}