{
  "type": "Feature",
  "properties": {
    "iso:country":"US",
    "sg:address":"253 Croydon Ln",
    "sg:city":"El Cajon",
    "sg:classifiers":[
        {
            "category":"Professional",
            "type":"Services"
        }
    ],
    "sg:phone":"+1 619 825 5088",
    "sg:postcode":"92020",
    "sg:province":"CA",
    "sg:tags":[
        "establishment"
    ],
    "wof:name":"Helpful Elf",
    "wof:placetype":"venue"
},
  "geometry": {"coordinates":[-116.99032,32.795945],"type":"Point"}
}