{
  "type": "Feature",
  "properties": {
    "iso:country":"US",
    "sg:address":"1190 Saratoga Ave",
    "sg:city":"San Jose",
    "sg:classifiers":[
        {
            "category":"Insurance",
            "subcategory":"Insurance Agent",
            "type":"Services"
        }
    ],
    "sg:phone":"+1 408 246 7887",
    "sg:postcode":"95129",
    "sg:province":"CA",
    "wof:name":"Suhr Risk Services",
    "wof:placetype":"venue"
},
  "geometry": {"coordinates":[-121.979641,37.303334],"type":"Point"}
}