{
  "type": "Feature",
  "properties": {
    "iso:country":"US",
    "sg:address":"16787 Bernardo Center Dr",
    "sg:city":"San Diego",
    "sg:classifiers":[
        {
            "category":"Professional",
            "subcategory":"Lawyer & Legal Services",
            "type":"Services"
        }
    ],
    "sg:phone":"+1 858 613 6699",
    "sg:postcode":"92128",
    "sg:province":"CA",
    "sg:tags":[
        "attorney"
    ],
    "wof:name":"Greer & Assoc",
    "wof:placetype":"venue"
},
  "geometry": {"coordinates":[-117.07484100000001,33.020146],"type":"Point"}
}