{
  "type": "Feature",
  "properties": {
    "addr:full":"25252 McIntyre St Laguna Hills CA 92653",
    "addr:housenumber":"25252",
    "addr:postcode":"92653",
    "addr:street":"Mcintyre St",
    "iso:country":"US",
    "sg:address":"25252 McIntyre St",
    "sg:city":"Laguna Hills",
    "sg:classifiers":[
        {
            "category":"Shopping",
            "subcategory":"Crafts & Fabrics",
            "type":"Retail Goods"
        }
    ],
    "sg:phone":"+1 949 586 3496",
    "sg:postcode":"92653",
    "sg:province":"CA",
    "sg:tags":[
        "shop",
        "store"
    ],
    "wof:name":"Jo-Ann Fabrics and Crafts",
    "wof:placetype":"venue"
},
  "geometry": {"coordinates":[-117.679867,33.596288],"type":"Point"}
}