{
  "type": "Feature",
  "properties": {
    "iso:country":"US",
    "sg:address":"500 S Virgil Ave",
    "sg:city":"Los Angeles",
    "sg:classifiers":[
        {
            "category":"Government",
            "subcategory":"Office",
            "type":"Public Place"
        }
    ],
    "sg:phone":"+1 213 639 2220",
    "sg:postcode":"90020",
    "sg:province":"CA",
    "sg:tags":[
        "program",
        "health"
    ],
    "wof:name":"Health Services Dept of",
    "wof:placetype":"venue"
},
  "geometry": {"coordinates":[-118.287042,34.063705],"type":"Point"}
}