{
  "type": "Feature",
  "properties": {
    "iso:country":"US",
    "sg:address":"362 W Foothill Blvd",
    "sg:city":"Glendora",
    "sg:classifiers":[
        {
            "category":"Home & Garden",
            "subcategory":"Home Furnishings",
            "type":"Retail Goods"
        }
    ],
    "sg:phone":"+1 626 914 5353",
    "sg:postcode":"91741",
    "sg:province":"CA",
    "sg:tags":[
        "installation",
        "drapery"
    ],
    "wof:name":"Hang Rite Window Coverings",
    "wof:placetype":"venue"
},
  "geometry": {"coordinates":[-117.869905,34.135961],"type":"Point"}
}