{
  "type": "Feature",
  "properties": {
    "addr:full":"2210 County Center Dr Santa Rosa CA 95403",
    "addr:housenumber":"2210",
    "addr:postcode":"95403",
    "addr:street":"County Center Dr",
    "iso:country":"US",
    "sg:address":"2210 County Center Dr",
    "sg:city":"Santa Rosa",
    "sg:classifiers":[
        {
            "category":"Retail",
            "subcategory":"Veterinary Services",
            "type":"Services"
        }
    ],
    "sg:phone":"+1 707 546 4646",
    "sg:postcode":"95403",
    "sg:province":"CA",
    "wof:name":"Jordan Jona Dvm",
    "wof:placetype":"venue"
},
  "geometry": {"coordinates":[-122.726004,38.463003],"type":"Point"}
}