{
  "type": "Feature",
  "properties": {
    "addr:full":"725 Lenzen Ave San Jose CA 95126",
    "addr:housenumber":"725",
    "addr:postcode":"95126",
    "addr:street":"Lenzen Ave",
    "iso:country":"US",
    "sg:address":"725 Lenzen Ave",
    "sg:city":"San Jose",
    "sg:classifiers":[
        {
            "category":"Utilities",
            "type":"Services"
        }
    ],
    "sg:phone":"+1 408 298 1224",
    "sg:postcode":"95126",
    "sg:province":"CA",
    "sg:tags":[
        "sweeping"
    ],
    "wof:name":"Sweepco",
    "wof:placetype":"venue"
},
  "geometry": {"coordinates":[-121.91003499999999,37.336166],"type":"Point"}
}