{
  "type": "Feature",
  "properties": {
    "iso:country":"US",
    "sg:address":"1942 Rock Ln",
    "sg:city":"La Verne",
    "sg:classifiers":[
        {
            "category":"Banks & Credit Unions",
            "subcategory":"Investment Brokerage",
            "type":"Services"
        }
    ],
    "sg:phone":"+1 909 392 0596",
    "sg:postcode":"91750",
    "sg:province":"CA",
    "wof:name":"Pierpont Investment Corp",
    "wof:placetype":"venue"
},
  "geometry": {"coordinates":[-117.768351,34.116432],"type":"Point"}
}