{
  "type": "Feature",
  "properties": {
    "iso:country":"US",
    "sg:address":"717 K St Ste 224",
    "sg:city":"Sacramento",
    "sg:classifiers":[
        {
            "category":"Professional",
            "subcategory":"Lawyer & Legal Services",
            "type":"Services"
        }
    ],
    "sg:phone":"+1 916 441 4540",
    "sg:postcode":"95814",
    "sg:province":"CA",
    "wof:name":"Tedmon Law Offices",
    "wof:placetype":"venue"
},
  "geometry": {"coordinates":[-121.498001,38.5802],"type":"Point"}
}