{
  "type": "Feature",
  "properties": {
    "iso:country":"US",
    "sg:address":"1149 Fair Weather Cir",
    "sg:city":"Concord",
    "sg:classifiers":[
        {
            "category":"Social Services",
            "subcategory":"Job Training",
            "type":"Services"
        }
    ],
    "sg:phone":"+1 925 827 2040",
    "sg:postcode":"94518",
    "sg:province":"CA",
    "sg:tags":[
        "nursing",
        "homes-skilled",
        "facility"
    ],
    "wof:name":"Aglcs Home",
    "wof:placetype":"venue"
},
  "geometry": {"coordinates":[-122.001518,37.947532],"type":"Point"}
}