{
  "type": "Feature",
  "properties": {
    "addr:full":"5125 Foothill Blvd San Diego CA 92109",
    "addr:housenumber":"5125",
    "addr:postcode":"92109",
    "addr:street":"Foothill Blvd",
    "iso:country":"US",
    "sg:address":"5125 Foothill Blvd",
    "sg:city":"San Diego",
    "sg:classifiers":[
        {
            "category":"Wholesale",
            "subcategory":"Vending Machines",
            "type":"Manufacturing & Wholesale Goods"
        }
    ],
    "sg:phone":"+1 858 488 9504",
    "sg:postcode":"92109",
    "sg:province":"CA",
    "sg:tags":[
        "operator"
    ],
    "wof:name":"Personal Vending Service",
    "wof:placetype":"venue"
},
  "geometry": {"coordinates":[-117.24761700000001,32.809867],"type":"Point"}
}