{
  "type": "Feature",
  "properties": {
    "addr:full":"2540 Saviers Rd Oxnard CA 93033",
    "addr:housenumber":"2540",
    "addr:postcode":"93033",
    "addr:street":"Saviers Rd",
    "iso:country":"US",
    "sg:address":"2540 Saviers Rd",
    "sg:city":"Oxnard",
    "sg:classifiers":[
        {
            "category":"Professional",
            "type":"Services"
        }
    ],
    "sg:phone":"+1 805 247 0828",
    "sg:postcode":"93033",
    "sg:province":"CA",
    "wof:name":"Oxnard Craft",
    "wof:placetype":"venue"
},
  "geometry": {"coordinates":[-119.177474,34.174087],"type":"Point"}
}