{
  "type": "Feature",
  "properties": {
    "addr:full":"477 Bret Harte Dr Murphys CA 95247",
    "addr:housenumber":"477",
    "addr:postcode":"95247",
    "addr:street":"Bret Harte Dr",
    "iso:country":"US",
    "sg:address":"477 Bret Harte Dr",
    "sg:city":"Murphys",
    "sg:classifiers":[
        {
            "category":"Utilities",
            "subcategory":"Electric",
            "type":"Services"
        }
    ],
    "sg:phone":"+1 209 728 2051",
    "sg:postcode":"95247",
    "sg:province":"CA",
    "sg:tags":[
        "company"
    ],
    "wof:name":"Norther California Power Agncy",
    "wof:placetype":"venue"
},
  "geometry": {"coordinates":[-120.45876699999999,38.142956],"type":"Point"}
}