{
  "type": "Feature",
  "properties": {
    "iso:country":"US",
    "sg:address":"2151 Michelson Dr",
    "sg:city":"Irvine",
    "sg:classifiers":[
        {
            "category":"Real Estate",
            "subcategory":"Architect",
            "type":"Services"
        }
    ],
    "sg:phone":"+1 949 852 5900",
    "sg:postcode":"92612",
    "sg:province":"CA",
    "wof:name":"Volk Michael W Aia",
    "wof:placetype":"venue"
},
  "geometry": {"coordinates":[-117.85700199999999,33.676899],"type":"Point"}
}