{
  "type": "Feature",
  "properties": {
    "iso:country":"US",
    "sg:address":"626 S Lake Ave",
    "sg:city":"Pasadena",
    "sg:classifiers":[
        {
            "category":"Professional",
            "subcategory":"Accounting & Tax Preparation",
            "type":"Services"
        }
    ],
    "sg:phone":"+1 626 792 2179",
    "sg:postcode":"91106",
    "sg:province":"CA",
    "sg:tags":[
        "accountant"
    ],
    "sg:website":"www.abjbcpa.com",
    "wof:name":"Archer Bulmahn Jenkins & Bowler",
    "wof:placetype":"venue"
},
  "geometry": {"coordinates":[-118.13200399999999,34.134701],"type":"Point"}
}