{
  "type": "Feature",
  "properties": {
    "iso:country":"US",
    "sg:address":"1040 Leavesley Rd",
    "sg:city":"Gilroy",
    "sg:classifiers":[
        {
            "category":"Farming",
            "subcategory":"Farm",
            "type":"Manufacturing & Wholesale Goods"
        }
    ],
    "sg:phone":"+1 408 842 4980",
    "sg:postcode":"95020",
    "sg:province":"CA",
    "wof:name":"B & T Farms",
    "wof:placetype":"venue"
},
  "geometry": {"coordinates":[-121.559692,37.024995],"type":"Point"}
}