{
  "type": "Feature",
  "properties": {
    "iso:country":"US",
    "sg:address":"10231 Santa Monica Blvd",
    "sg:city":"Los Angeles",
    "sg:classifiers":[
        {
            "category":"Health Services",
            "subcategory":"Doctor",
            "type":"Services"
        }
    ],
    "sg:phone":"+1 310 551 1902",
    "sg:postcode":"90067",
    "sg:province":"CA",
    "sg:tags":[
        "dentist"
    ],
    "wof:name":"Grant Nakagawa, DDS",
    "wof:placetype":"venue"
},
  "geometry": {"coordinates":[-118.420581,34.060386],"type":"Point"}
}