{
  "type": "Feature",
  "properties": {
    "addr:full":"1023 W Briardale Ave Orange CA 92865",
    "addr:housenumber":"1023",
    "addr:postcode":"92865",
    "addr:street":"W Briardale Ave",
    "iso:country":"US",
    "sg:address":"1023 W Briardale Ave",
    "sg:city":"Orange",
    "sg:classifiers":[
        {
            "category":"Building & Trades",
            "subcategory":"Plumbing",
            "type":"Services"
        }
    ],
    "sg:phone":"+1 714 974 4861",
    "sg:postcode":"92865",
    "sg:province":"CA",
    "wof:name":"D & E Plumbing Inc",
    "wof:placetype":"venue"
},
  "geometry": {"coordinates":[-117.863998,33.816601],"type":"Point"}
}