{
  "type": "Feature",
  "properties": {
    "addr:full":"474 N Robertson Blvd Los Angeles CA 90048",
    "addr:housenumber":"474",
    "addr:postcode":"90048",
    "addr:street":"N Robertson Blvd",
    "iso:country":"US",
    "sg:address":"474 N Robertson Blvd",
    "sg:city":"Los Angeles",
    "sg:classifiers":[
        {
            "category":"Shopping",
            "subcategory":"Clothing, Apparel, & Fashions",
            "type":"Retail Goods"
        }
    ],
    "sg:phone":"+1 310 652 0064",
    "sg:postcode":"90048",
    "sg:province":"CA",
    "sg:tags":[
        "men's",
        "clothing",
        "women's"
    ],
    "wof:name":"HLNR",
    "wof:placetype":"venue"
},
  "geometry": {"coordinates":[-118.384686,34.079982],"type":"Point"}
}