{
  "type": "Feature",
  "properties": {
    "iso:country":"US",
    "sg:address":"18558 Roscoe Blvd",
    "sg:city":"Northridge",
    "sg:classifiers":[
        {
            "category":"Freight",
            "type":"Transportation"
        }
    ],
    "sg:phone":"+1 818 885 6922",
    "sg:postcode":"91324",
    "sg:province":"CA",
    "sg:tags":[
        "courier"
    ],
    "wof:name":"Sas Courier Service",
    "wof:placetype":"venue"
},
  "geometry": {"coordinates":[-118.53755,34.220633],"type":"Point"}
}