{
  "type": "Feature",
  "properties": {
    "iso:country":"US",
    "sg:address":"375 Central Ave",
    "sg:city":"Riverside",
    "sg:classifiers":[
        {
            "category":"Real Estate",
            "subcategory":"Real Estate Operator",
            "type":"Services"
        }
    ],
    "sg:phone":"+1 951 778 9000",
    "sg:postcode":"92507",
    "sg:province":"CA",
    "sg:tags":[
        "apartment"
    ],
    "wof:name":"Quail View Apartments",
    "wof:placetype":"venue"
},
  "geometry": {"coordinates":[-117.31304299999999,33.9579],"type":"Point"}
}