{
  "type": "Feature",
  "properties": {
    "addr:full":"13531 Wyandotte St Van Nuys CA 91405",
    "addr:housenumber":"13531",
    "addr:postcode":"91405",
    "addr:street":"Wyandotte St",
    "iso:country":"US",
    "sg:address":"13531 Wyandotte St",
    "sg:city":"Van Nuys",
    "sg:classifiers":[
        {
            "category":"Manufacturing",
            "subcategory":"Tools & Machinery",
            "type":"Manufacturing & Wholesale Goods"
        }
    ],
    "sg:phone":"+1 818 785 6865",
    "sg:postcode":"91405",
    "sg:province":"CA",
    "sg:tags":[
        "equipment",
        "mfg"
    ],
    "wof:name":"Hollandia Designs",
    "wof:placetype":"venue"
},
  "geometry": {"coordinates":[-118.428819,34.203113],"type":"Point"}
}