{
  "type": "Feature",
  "properties": {
    "iso:country":"US",
    "sg:address":"2640 Yosemite Blvd",
    "sg:city":"Modesto",
    "sg:classifiers":[
        {
            "category":"Freight",
            "type":"Transportation"
        }
    ],
    "sg:phone":"+1 209 544 1492",
    "sg:postcode":"95354",
    "sg:province":"CA",
    "sg:tags":[
        "trucking"
    ],
    "sg:website":"www.wksh.com",
    "wof:name":"Watkins & Shepard Trucking",
    "wof:placetype":"venue"
},
  "geometry": {"coordinates":[-120.944304,37.638068],"type":"Point"}
}