{
  "type": "Feature",
  "properties": {
    "iso:country":"US",
    "sg:address":"5441 N Paramount Blvd",
    "sg:city":"Long Beach",
    "sg:classifiers":[
        {
            "category":"Real Estate",
            "subcategory":"Real Estate Operator",
            "type":"Services"
        }
    ],
    "sg:phone":"+1 562 634 3548",
    "sg:postcode":"90805",
    "sg:province":"CA",
    "sg:tags":[
        "apartment"
    ],
    "wof:name":"North Pointe Apartment Homes",
    "wof:placetype":"venue"
},
  "geometry": {"coordinates":[-118.160004,33.855999],"type":"Point"}
}