{
  "type": "Feature",
  "properties": {
    "addr:full":"427 W Seaview Dr Benicia CA 94510",
    "addr:housenumber":"427",
    "addr:postcode":"94510",
    "addr:street":"W Seaview Dr",
    "iso:country":"US",
    "sg:address":"427 W Seaview Dr",
    "sg:city":"Benicia",
    "sg:classifiers":[
        {
            "category":"Building & Trades",
            "subcategory":"Landscaping Services",
            "type":"Services"
        }
    ],
    "sg:phone":"+1 707 747 6295",
    "sg:postcode":"94510",
    "sg:province":"CA",
    "sg:tags":[
        "landscape",
        "contractor"
    ],
    "wof:name":"Landcon Inc",
    "wof:placetype":"venue"
},
  "geometry": {"coordinates":[-122.153113,38.06423],"type":"Point"}
}