{
  "type": "Feature",
  "properties": {
    "addr:full":"250 el Camino Real Tustin CA 92780",
    "addr:housenumber":"250",
    "addr:postcode":"92780",
    "addr:street":"El Camino Real",
    "iso:country":"US",
    "sg:address":"250 el Camino Real",
    "sg:city":"Tustin",
    "sg:classifiers":[
        {
            "category":"Wholesale",
            "subcategory":"Durable Goods & Equipment",
            "type":"Manufacturing & Wholesale Goods"
        }
    ],
    "sg:phone":"+1 714 832 1939",
    "sg:postcode":"92780",
    "sg:province":"CA",
    "wof:name":"Prosales",
    "wof:placetype":"venue"
},
  "geometry": {"coordinates":[-117.823734,33.743644],"type":"Point"}
}