{
  "type": "Feature",
  "properties": {
    "iso:country":"US",
    "sg:address":"1405 S el Camino Real",
    "sg:city":"Oceanside",
    "sg:classifiers":[
        {
            "category":"Organizations",
            "subcategory":"Religious Organization",
            "type":"Services"
        }
    ],
    "sg:phone":"+1 760 757 7334",
    "sg:postcode":"92054",
    "sg:province":"CA",
    "sg:tags":[
        "church"
    ],
    "wof:name":"Harvest Time Apostolic Church",
    "wof:placetype":"venue"
},
  "geometry": {"coordinates":[-117.329173,33.196519],"type":"Point"}
}