{
  "type": "Feature",
  "properties": {
    "iso:country":"US",
    "sg:address":"5234 Foothill Blvd",
    "sg:city":"Oakland",
    "sg:classifiers":[
        {
            "category":"Organizations",
            "subcategory":"Religious Organization",
            "type":"Services"
        }
    ],
    "sg:phone":"+1 510 532 2551",
    "sg:postcode":"94601",
    "sg:province":"CA",
    "sg:tags":[
        "church"
    ],
    "wof:name":"True Love Christian Ctr",
    "wof:placetype":"venue"
},
  "geometry": {"coordinates":[-122.202843,37.772748],"type":"Point"}
}