{
  "type": "Feature",
  "properties": {
    "addr:full":"1416 35th Ave Oakland CA 94601",
    "addr:housenumber":"1416",
    "addr:postcode":"94601",
    "addr:street":"35Th Ave",
    "iso:country":"US",
    "sg:address":"1416 35th Ave",
    "sg:city":"Oakland",
    "sg:classifiers":[
        {
            "category":"Personal",
            "subcategory":"Beauty Salon",
            "type":"Services"
        }
    ],
    "sg:phone":"+1 510 534 4782",
    "sg:postcode":"94601",
    "sg:province":"CA",
    "sg:tags":[
        "hair"
    ],
    "wof:name":"Elli's Beauty Salon",
    "wof:placetype":"venue"
},
  "geometry": {"coordinates":[-122.22227599999999,37.776796],"type":"Point"}
}