{
  "type": "Feature",
  "properties": {
    "addr:full":"16210 Foothill Blvd San Leandro CA 94578",
    "addr:housenumber":"16210",
    "addr:postcode":"94578",
    "addr:street":"Foothill Blvd",
    "iso:country":"US",
    "sg:address":"16210 Foothill Blvd",
    "sg:city":"San Leandro",
    "sg:classifiers":[
        {
            "category":"Government",
            "subcategory":"Office",
            "type":"Public Place"
        }
    ],
    "sg:phone":"+1 510 449 6110",
    "sg:postcode":"94578",
    "sg:province":"CA",
    "sg:tags":[
        "smog",
        "check"
    ],
    "wof:name":"Clean Air Test Only",
    "wof:placetype":"venue"
},
  "geometry": {"coordinates":[-122.109949,37.702374],"type":"Point"}
}