{
  "type": "Feature",
  "properties": {
    "iso:country":"US",
    "sg:address":"232 N Lake Ave",
    "sg:city":"Pasadena",
    "sg:classifiers":[
        {
            "category":"Professional",
            "subcategory":"Engineering",
            "type":"Services"
        }
    ],
    "sg:phone":"+1 626 577 0449",
    "sg:postcode":"91101",
    "sg:province":"CA",
    "sg:tags":[
        "engineer"
    ],
    "wof:name":"Consulting Electric",
    "wof:placetype":"venue"
},
  "geometry": {"coordinates":[-118.132322,34.150029],"type":"Point"}
}