{
  "type": "Feature",
  "properties": {
    "addr:full":"9433 Mountain Shadow Pl Rancho Cucamonga CA 91730",
    "addr:housenumber":"9433",
    "addr:postcode":"91730",
    "addr:street":"Mountain Shadow Pl",
    "iso:country":"US",
    "sg:address":"9433 Mountain Shadow Pl",
    "sg:city":"Rancho Cucamonga",
    "sg:classifiers":[
        {
            "category":"Professional",
            "subcategory":"Business Services",
            "type":"Services"
        }
    ],
    "sg:phone":"+1 909 210 8309",
    "sg:postcode":"91730",
    "sg:province":"CA",
    "sg:tags":[
        "packaging"
    ],
    "wof:name":"Cutting Edge Package Design",
    "wof:placetype":"venue"
},
  "geometry": {"coordinates":[-117.598296,34.082178],"type":"Point"}
}