{
  "type": "Feature",
  "properties": {
    "addr:full":"2021 The Alameda San Jose CA 95126",
    "addr:housenumber":"2021",
    "addr:postcode":"95126",
    "addr:street":"The Alameda",
    "iso:country":"US",
    "sg:address":"2021 The Alameda",
    "sg:city":"San Jose",
    "sg:classifiers":[
        {
            "category":"Insurance",
            "subcategory":"Insurance Agent",
            "type":"Services"
        }
    ],
    "sg:phone":"+1 408 248 0909",
    "sg:postcode":"95126",
    "sg:province":"CA",
    "sg:website":"www.michaelguarino.com",
    "wof:name":"Mike Guarino Insurance",
    "wof:placetype":"venue"
},
  "geometry": {"coordinates":[-121.926802,37.342809],"type":"Point"}
}