{
  "type": "Feature",
  "properties": {
    "addr:full":"27 E Napa St Sonoma CA 95476",
    "addr:housenumber":"27",
    "addr:postcode":"95476",
    "addr:street":"E Napa St",
    "iso:country":"US",
    "sg:address":"27 E Napa St",
    "sg:city":"Sonoma",
    "sg:classifiers":[
        {
            "category":"Manufacturing",
            "subcategory":"Food",
            "type":"Manufacturing & Wholesale Goods"
        }
    ],
    "sg:phone":"+1 707 935 2100",
    "sg:postcode":"95476",
    "sg:province":"CA",
    "sg:tags":[
        "winery"
    ],
    "wof:name":"Woodward Graff Wine Foundation",
    "wof:placetype":"venue"
},
  "geometry": {"coordinates":[-122.45701,38.291797],"type":"Point"}
}