{
  "type": "Feature",
  "properties": {
    "addr:full":"3215 Fleur St Bakersfield CA 93306",
    "addr:housenumber":"3215",
    "addr:postcode":"93306",
    "addr:street":"Fleur St",
    "iso:country":"US",
    "sg:address":"3215 Fleur St",
    "sg:city":"Bakersfield",
    "sg:classifiers":[
        {
            "category":"Professional",
            "type":"Services"
        }
    ],
    "sg:phone":"+1 661 871 4944",
    "sg:postcode":"93306",
    "sg:province":"CA",
    "sg:tags":[
        "establishment"
    ],
    "wof:name":"Quinn & Assoc",
    "wof:placetype":"venue"
},
  "geometry": {"coordinates":[-118.94398099999999,35.402496],"type":"Point"}
}