{
  "type": "Feature",
  "properties": {
    "iso:country":"US",
    "sg:address":"10800 W Pico Blvd",
    "sg:city":"Los Angeles",
    "sg:classifiers":[
        {
            "category":"Manufacturing",
            "subcategory":"Printing",
            "type":"Manufacturing & Wholesale Goods"
        }
    ],
    "sg:phone":"+1 310 470 0648",
    "sg:postcode":"90064",
    "sg:province":"CA",
    "sg:tags":[
        "lithographic",
        "commercial"
    ],
    "wof:name":"Wik-Wik Food Corp Inc",
    "wof:placetype":"venue"
},
  "geometry": {"coordinates":[-118.428488,34.040116],"type":"Point"}
}