{
  "type": "Feature",
  "properties": {
    "iso:country":"US",
    "sg:address":"San Jose & Santa Clara",
    "sg:city":"Richmond",
    "sg:classifiers":[
        {
            "category":"Professional",
            "subcategory":"Art Services",
            "type":"Services"
        }
    ],
    "sg:phone":"+1 510 499 0098",
    "sg:postcode":"94804",
    "sg:province":"CA",
    "sg:tags":[
        "photographer"
    ],
    "wof:name":"Stealing Beauty Photography",
    "wof:placetype":"venue"
},
  "geometry": {"coordinates":[-122.30786000000001,37.9033],"type":"Point"}
}