{
  "type": "Feature",
  "properties": {
    "addr:full":"2485 Natomas Park Dr Suite 250 Sacramento CA 95833",
    "addr:postcode":"2485;95833",
    "addr:street":"Natomas Park Dr Suite 250",
    "iso:country":"US",
    "sg:address":"2485 Natomas Park Dr Suite 250",
    "sg:city":"Sacramento",
    "sg:classifiers":[
        {
            "category":"Shopping",
            "subcategory":"Stationery & Office Supplies",
            "type":"Retail Goods"
        },
        {
            "category":"Retail",
            "subcategory":"Repair Shop",
            "type":"Services"
        },
        {
            "category":"Shopping",
            "subcategory":"Computers & Home Electronics",
            "type":"Retail Goods"
        }
    ],
    "sg:phone":"+1 804 289 5400",
    "sg:postcode":"95833",
    "sg:province":"CA",
    "sg:tags":[
        "machine",
        "copy",
        "printer"
    ],
    "sg:website":"http://findxeroxagents.com/copiers-in-sacramento-california_1073",
    "wof:name":"Xerox Sales Demo Room",
    "wof:placetype":"venue"
},
  "geometry": {"coordinates":[-121.506817,38.610322],"type":"Point"}
}