{
  "type": "Feature",
  "properties": {
    "iso:country":"US",
    "sg:address":"5350 Overpass Rd",
    "sg:city":"Santa Barbara",
    "sg:classifiers":[
        {
            "category":"Shopping",
            "type":"Retail Goods"
        }
    ],
    "sg:phone":"+1 805 964 5583",
    "sg:postcode":"93111",
    "sg:province":"CA",
    "sg:tags":[
        "picture",
        "frame"
    ],
    "wof:name":"Parameters Custom Framing",
    "wof:placetype":"venue"
},
  "geometry": {"coordinates":[-119.808727,34.439094],"type":"Point"}
}