{
  "type": "Feature",
  "properties": {
    "addr:full":"831 N Rosemead Blvd South El Monte CA 91733",
    "addr:housenumber":"831",
    "addr:postcode":"91733",
    "addr:street":"N Rosemead Blvd",
    "iso:country":"US",
    "sg:address":"831 N Rosemead Blvd",
    "sg:city":"South El Monte",
    "sg:classifiers":[
        {
            "category":"Recreation",
            "subcategory":"Gun Range",
            "type":"Entertainment"
        }
    ],
    "sg:phone":"+1 626 579 5201",
    "sg:postcode":"91733",
    "sg:province":"CA",
    "sg:tags":[
        "gun/rifle"
    ],
    "sg:website":"www.triplebclays.com",
    "wof:name":"Triple B Clays",
    "wof:placetype":"venue"
},
  "geometry": {"coordinates":[-118.06500200000001,34.034199],"type":"Point"}
}