{
  "type": "Feature",
  "properties": {
    "iso:country":"US",
    "sg:address":"5363 Venice Blvd",
    "sg:city":"Los Angeles",
    "sg:classifiers":[
        {
            "category":"Retail",
            "subcategory":"Auto Repair",
            "type":"Services"
        }
    ],
    "sg:phone":"+1 323 732 8839",
    "sg:postcode":"90019",
    "sg:province":"CA",
    "sg:tags":[
        "general"
    ],
    "wof:name":"C&R Auto Repair & Electric Ser",
    "wof:placetype":"venue"
},
  "geometry": {"coordinates":[-118.35714900000001,34.044496],"type":"Point"}
}