{
  "type": "Feature",
  "properties": {
    "iso:country":"US",
    "sg:address":"6677 Foothill Blvd",
    "sg:city":"Oakland",
    "sg:classifiers":[
        {
            "category":"Place Of Worship",
            "subcategory":"Church",
            "type":"Public Place"
        },
        {
            "category":"Place Of Worship",
            "type":"Public Place"
        },
        {
            "category":"Organizations",
            "subcategory":"Religious Organization",
            "type":"Services"
        }
    ],
    "sg:phone":"+1 510 638 3985",
    "sg:postcode":"94605",
    "sg:province":"CA",
    "sg:tags":[
        "churches-interdenominational",
        "churches-various",
        "denomination"
    ],
    "wof:name":"New Covenant Tabernacle Church",
    "wof:placetype":"venue"
},
  "geometry": {"coordinates":[-122.180127,37.770033],"type":"Point"}
}