{
  "type": "Feature",
  "properties": {
    "iso:country":"US",
    "sg:address":"6335 Homewood Ave",
    "sg:city":"Los Angeles",
    "sg:classifiers":[
        {
            "category":"Communications",
            "subcategory":"Film & Video Production",
            "type":"Services"
        }
    ],
    "sg:phone":"+1 323 462 2300",
    "sg:postcode":"90028",
    "sg:province":"CA",
    "sg:tags":[
        "audio"
    ],
    "sg:website":"www.postgroup.com",
    "wof:name":"Post Group",
    "wof:placetype":"venue"
},
  "geometry": {"coordinates":[-118.327047,34.095346],"type":"Point"}
}