{
  "type": "Feature",
  "properties": {
    "iso:country":"US",
    "sg:address":"935 Sierra Vista Ave",
    "sg:city":"Mountain View",
    "sg:classifiers":[
        {
            "category":"Professional",
            "subcategory":"Advertising",
            "type":"Services"
        }
    ],
    "sg:phone":"+1 650 940 6000",
    "sg:postcode":"94043",
    "sg:province":"CA",
    "sg:tags":[
        "counselor"
    ],
    "sg:website":"www.asci4d.com",
    "wof:name":"ASCI",
    "wof:placetype":"venue"
},
  "geometry": {"coordinates":[-122.089761,37.418299],"type":"Point"}
}