{
  "type": "Feature",
  "properties": {
    "iso:country":"US",
    "sg:address":"150 Valpreda Rd",
    "sg:city":"San Marcos",
    "sg:classifiers":[
        {
            "category":"Health Services",
            "subcategory":"Doctor",
            "type":"Services"
        }
    ],
    "sg:phone":"+1 760 736 6767",
    "sg:postcode":"92069",
    "sg:province":"CA",
    "sg:tags":[
        "physician",
        "surgeon",
        "care"
    ],
    "sg:website":"www.nchs-health.org",
    "wof:name":"North County Health Services",
    "wof:placetype":"venue"
},
  "geometry": {"coordinates":[-117.15646599999999,33.141667],"type":"Point"}
}