{
  "type": "Feature",
  "properties": {
    "iso:country":"US",
    "sg:address":"58 Danton St",
    "sg:city":"San Francisco",
    "sg:classifiers":[
        {
            "category":"Social Services",
            "subcategory":"Child Care",
            "type":"Services"
        }
    ],
    "sg:phone":"+1 415 585 1158",
    "sg:postcode":"94112",
    "sg:province":"CA",
    "wof:name":"Munchkinland-Child Care",
    "wof:placetype":"venue"
},
  "geometry": {"coordinates":[-122.432333,37.731129],"type":"Point"}
}