{
  "type": "Feature",
  "properties": {
    "iso:country":"US",
    "sg:address":"6081 Center Dr Ste 218",
    "sg:city":"Los Angeles",
    "sg:classifiers":[
        {
            "category":"Restaurant",
            "type":"Food & Drink"
        }
    ],
    "sg:phone":"+1 310 410 9999",
    "sg:postcode":"90045",
    "sg:province":"CA",
    "sg:tags":[
        "mediterranean"
    ],
    "sg:website":"www.thehummusfactory.com/",
    "wof:name":"The Hummus Factory",
    "wof:placetype":"venue"
},
  "geometry": {"coordinates":[-118.391949,33.978057],"type":"Point"}
}