{
  "type": "Feature",
  "properties": {
    "addr:full":"2428 E 55th St Los Angeles CA 90058",
    "addr:housenumber":"2428",
    "addr:postcode":"90058",
    "addr:street":"E 55Th St",
    "iso:country":"US",
    "sg:address":"2428 E 55th St",
    "sg:city":"Los Angeles",
    "sg:classifiers":[
        {
            "category":"Shopping",
            "subcategory":"Clothing, Apparel, & Fashions",
            "type":"Retail Goods"
        }
    ],
    "sg:phone":"+1 323 583 3993",
    "sg:postcode":"90058",
    "sg:province":"CA",
    "sg:tags":[
        "designer"
    ],
    "wof:name":"Azteca Fashion Inc",
    "wof:placetype":"venue"
},
  "geometry": {"coordinates":[-118.228407,33.992855],"type":"Point"}
}