{
  "type": "Feature",
  "properties": {
    "addr:full":"2952 Lethbridge Ct Pleasanton CA 94588",
    "addr:housenumber":"2952",
    "addr:postcode":"94588",
    "addr:street":"Lethbridge Ct",
    "iso:country":"US",
    "sg:address":"2952 Lethbridge Ct",
    "sg:city":"Pleasanton",
    "sg:classifiers":[
        {
            "category":"Airline",
            "type":"Transportation"
        },
        {
            "category":"Travel",
            "subcategory":"Travel Agent",
            "type":"Entertainment"
        },
        {
            "category":"Marine",
            "type":"Transportation"
        }
    ],
    "sg:phone":"+1 925 417 1733",
    "sg:postcode":"94588",
    "sg:province":"CA",
    "sg:tags":[
        "ticket",
        "agency",
        "services-commercial",
        "cruise"
    ],
    "wof:name":"Cruise & Travel Company",
    "wof:placetype":"venue"
},
  "geometry": {"coordinates":[-121.861062,37.694723],"type":"Point"}
}