{
  "type": "Feature",
  "properties": {
    "addr:full":"6496 Whitworth Rd Gustine CA 95322",
    "addr:housenumber":"6496",
    "addr:postcode":"95322",
    "addr:street":"Whitworth Rd",
    "iso:country":"US",
    "sg:address":"6496 Whitworth Rd",
    "sg:city":"Gustine",
    "sg:classifiers":[
        {
            "category":"Wholesale",
            "subcategory":"Groceries",
            "type":"Manufacturing & Wholesale Goods"
        }
    ],
    "sg:phone":"+1 209 854 6533",
    "sg:postcode":"95322",
    "sg:province":"CA",
    "sg:tags":[
        "grocer",
        "general"
    ],
    "wof:name":"Rebeto Farms",
    "wof:placetype":"venue"
},
  "geometry": {"coordinates":[-121.030753,37.2023],"type":"Point"}
}