{
  "type": "Feature",
  "properties": {
    "addr:full":"130 W Union St Pasadena CA 91103",
    "addr:housenumber":"130",
    "addr:postcode":"91103",
    "addr:street":"W Union St",
    "iso:country":"US",
    "sg:address":"130 W Union St",
    "sg:city":"Pasadena",
    "sg:classifiers":[
        {
            "category":"Professional",
            "subcategory":"Computer Services",
            "type":"Services"
        }
    ],
    "sg:postcode":"91103",
    "sg:province":"CA",
    "sg:tags":[
        "food",
        "deals",
        "real-time-deals",
        "local",
        "mobile",
        "discount"
    ],
    "sg:website":"http://foodme.com",
    "wof:name":"Foodme",
    "wof:placetype":"venue"
},
  "geometry": {"coordinates":[-118.15364700000001,34.146641],"type":"Point"}
}