{
  "type": "Feature",
  "properties": {
    "addr:full":"1026 Truxtun Ave Bakersfield CA 93301",
    "addr:housenumber":"1026",
    "addr:postcode":"93301",
    "addr:street":"Truxtun Ave",
    "iso:country":"US",
    "sg:address":"1026 Truxtun Ave",
    "sg:city":"Bakersfield",
    "sg:classifiers":[
        {
            "category":"Personal",
            "subcategory":"Beauty Salon",
            "type":"Services"
        }
    ],
    "sg:phone":"+1 661 633 0321",
    "sg:postcode":"93301",
    "sg:province":"CA",
    "wof:name":"Martha's Cottage Salon",
    "wof:placetype":"venue"
},
  "geometry": {"coordinates":[-119.013851,35.373394],"type":"Point"}
}