{
  "type": "Feature",
  "properties": {
    "addr:full":"3450 Kurtz St Ste D San Diego CA 92110",
    "addr:housenumber":"3450",
    "addr:postcode":"92110",
    "addr:street":"Kurtz St Ste D",
    "iso:country":"US",
    "sg:address":"3450 Kurtz St Ste D",
    "sg:city":"San Diego",
    "sg:classifiers":[
        {
            "category":"Shopping",
            "subcategory":"Optician",
            "type":"Retail Goods"
        }
    ],
    "sg:phone":"+1 619 291 4810",
    "sg:postcode":"92110",
    "sg:province":"CA",
    "sg:tags":[
        "eyewear"
    ],
    "sg:website":"www.sunglassoptical.com",
    "wof:name":"Sunglass & Optical Warehouse",
    "wof:placetype":"venue"
},
  "geometry": {"coordinates":[-117.208861,32.755676],"type":"Point"}
}