{
  "type": "Feature",
  "properties": {
    "addr:full":"2519 W Winton Ave Hayward CA 94545",
    "addr:housenumber":"2519",
    "addr:postcode":"94545",
    "addr:street":"W Winton Ave",
    "iso:country":"US",
    "sg:address":"2519 W Winton Ave",
    "sg:city":"Hayward",
    "sg:classifiers":[
        {
            "category":"Wholesale",
            "subcategory":"Machinery & Supplies",
            "type":"Manufacturing & Wholesale Goods"
        }
    ],
    "sg:phone":"+1 510 785 3825",
    "sg:postcode":"94545",
    "sg:province":"CA",
    "sg:tags":[
        "equipment",
        "chiropractor"
    ],
    "sg:website":"www.choatetables.com",
    "wof:name":"Choate Tables",
    "wof:placetype":"venue"
},
  "geometry": {"coordinates":[-122.145167,37.647979],"type":"Point"}
}