{
  "type": "Feature",
  "properties": {
    "iso:country":"US",
    "sg:address":"PO Box 3157",
    "sg:city":"La Jolla",
    "sg:classifiers":[
        {
            "category":"Professional",
            "subcategory":"Employment Agencies",
            "type":"Services"
        }
    ],
    "sg:phone":"+1 858 566 6113",
    "sg:postcode":"92038",
    "sg:province":"CA",
    "sg:website":"www.thehouseservice.com",
    "wof:name":"Vera Troy's Agency",
    "wof:placetype":"venue"
},
  "geometry": {"coordinates":[-117.273003,32.847301],"type":"Point"}
}