{
  "type": "Feature",
  "properties": {
    "addr:full":"97 E Brokaw Rd San Jose CA 95112",
    "addr:housenumber":"97",
    "addr:postcode":"95112",
    "addr:street":"E Brokaw Rd",
    "iso:country":"US",
    "sg:address":"97 E Brokaw Rd",
    "sg:city":"San Jose",
    "sg:classifiers":[
        {
            "category":"Banks & Credit Unions",
            "subcategory":"Bank",
            "type":"Services"
        }
    ],
    "sg:phone":"+1 408 436 8111",
    "sg:postcode":"95112",
    "sg:province":"CA",
    "sg:tags":[
        "loan",
        "real estate"
    ],
    "wof:name":"Brokaw Capital",
    "wof:placetype":"venue"
},
  "geometry": {"coordinates":[-121.91617599999999,37.375158],"type":"Point"}
}