{
  "type": "Feature",
  "properties": {
    "iso:country":"US",
    "sg:address":"255 N Lone Hill Ave",
    "sg:city":"San Dimas",
    "sg:classifiers":[
        {
            "category":"Banks & Credit Unions",
            "subcategory":"Bank",
            "type":"Services"
        }
    ],
    "sg:phone":"+1 909 971 9643",
    "sg:postcode":"91773",
    "sg:province":"CA",
    "wof:name":"Christian Community CU",
    "wof:placetype":"venue"
},
  "geometry": {"coordinates":[-117.828479,34.108368],"type":"Point"}
}