{
  "type": "Feature",
  "properties": {
    "addr:full":"3019 Travis Blvd Fairfield CA 94534",
    "addr:housenumber":"3019",
    "addr:postcode":"94534",
    "addr:street":"Travis Blvd",
    "iso:country":"US",
    "sg:address":"3019 Travis Blvd",
    "sg:city":"Fairfield",
    "sg:classifiers":[
        {
            "category":"Shopping",
            "subcategory":"Jewelry",
            "type":"Retail Goods"
        }
    ],
    "sg:phone":"+1 707 435 1900",
    "sg:postcode":"94534",
    "sg:province":"CA",
    "sg:tags":[
        "precious",
        "metal",
        "mfg"
    ],
    "sg:website":"www.nandengems.com",
    "wof:name":"Nan-Den Gems",
    "wof:placetype":"venue"
},
  "geometry": {"coordinates":[-122.06525999999999,38.258147],"type":"Point"}
}