{
  "type": "Feature",
  "properties": {
    "addr:full":"20 City Blvd W Orange CA 92856",
    "addr:housenumber":"20",
    "addr:postcode":"92856",
    "addr:street":"City Blvd W",
    "iso:country":"US",
    "sg:address":"20 City Blvd W",
    "sg:city":"Orange",
    "sg:classifiers":[
        {
            "category":"Fast Food",
            "type":"Food & Drink"
        },
        {
            "category":"Restaurant",
            "type":"Food & Drink"
        }
    ],
    "sg:phone":"+1 714 769 3177",
    "sg:postcode":"92856",
    "sg:province":"CA",
    "sg:tags":[
        "mexican"
    ],
    "sg:website":"www.rubios.com",
    "wof:name":"Rubio's Fresh Mexican Grill",
    "wof:placetype":"venue"
},
  "geometry": {"coordinates":[-117.895278,33.781306],"type":"Point"}
}