{
  "type": "Feature",
  "properties": {
    "addr:full":"4188 Product Dr Cameron Park CA 95682",
    "addr:housenumber":"4188",
    "addr:postcode":"95682",
    "addr:street":"Product Dr",
    "iso:country":"US",
    "sg:address":"4188 Product Dr",
    "sg:city":"Cameron Park",
    "sg:classifiers":[
        {
            "category":"Retail",
            "subcategory":"Auto Repair",
            "type":"Services"
        }
    ],
    "sg:phone":"+1 530 677 3227",
    "sg:postcode":"95682",
    "sg:province":"CA",
    "sg:tags":[
        "body",
        "automobile",
        "painting"
    ],
    "wof:name":"Cameron Park Auto Body",
    "wof:placetype":"venue"
},
  "geometry": {"coordinates":[-120.95054,38.654824],"type":"Point"}
}