{
  "type": "Feature",
  "properties": {
    "addr:full":"5280 N Bond Ave Fresno CA 93710",
    "addr:housenumber":"5280",
    "addr:postcode":"93710",
    "addr:street":"N Bond Ave",
    "iso:country":"US",
    "sg:address":"5280 N Bond Ave",
    "sg:city":"Fresno",
    "sg:classifiers":[
        {
            "category":"Social Services",
            "subcategory":"Adult Care",
            "type":"Services"
        }
    ],
    "sg:phone":"+1 559 221 9777",
    "sg:postcode":"93710",
    "sg:province":"CA",
    "sg:tags":[
        "home",
        "residential"
    ],
    "wof:name":"Integrity Group Homes",
    "wof:placetype":"venue"
},
  "geometry": {"coordinates":[-119.76629200000001,36.814154],"type":"Point"}
}