{
  "type": "Feature",
  "properties": {
    "iso:country":"US",
    "sg:address":"4346 South St",
    "sg:city":"Lakewood",
    "sg:classifiers":[
        {
            "category":"Health Services",
            "subcategory":"Doctor",
            "type":"Services"
        }
    ],
    "sg:phone":"+1 562 408 3500",
    "sg:postcode":"90712",
    "sg:province":"CA",
    "sg:tags":[
        "dentist"
    ],
    "sg:website":"www.lakewoodplazadentalgroup.com",
    "wof:name":"Lakewood Plaza Dental Group",
    "wof:placetype":"venue"
},
  "geometry": {"coordinates":[-118.1412,33.860237],"type":"Point"}
}