{
  "type": "Feature",
  "properties": {
    "iso:country":"US",
    "sg:address":"602 Mission St",
    "sg:city":"Santa Cruz",
    "sg:classifiers":[
        {
            "category":"Wholesale",
            "subcategory":"Electrical",
            "type":"Manufacturing & Wholesale Goods"
        }
    ],
    "sg:phone":"+1 831 425 5771",
    "sg:postcode":"95060",
    "sg:province":"CA",
    "sg:tags":[
        "alarm",
        "burglar",
        "system"
    ],
    "sg:website":"www.superioralarm.com",
    "wof:name":"Superior Alarm Co",
    "wof:placetype":"venue"
},
  "geometry": {"coordinates":[-122.034435,36.974142],"type":"Point"}
}