{
  "type": "Feature",
  "properties": {
    "addr:full":"560 Sanford Ave Richmond CA 94801",
    "addr:housenumber":"560",
    "addr:postcode":"94801",
    "addr:street":"Sanford Ave",
    "iso:country":"US",
    "sg:address":"560 Sanford Ave",
    "sg:city":"Richmond",
    "sg:classifiers":[
        {
            "category":"Home & Garden",
            "subcategory":"Carpets & Floor Coverings",
            "type":"Retail Goods"
        }
    ],
    "sg:phone":"+1 510 965 0285",
    "sg:postcode":"94801",
    "sg:province":"CA",
    "wof:name":"Aldanas Flooring Carpet",
    "wof:placetype":"venue"
},
  "geometry": {"coordinates":[-122.363855,37.951903],"type":"Point"}
}