{
  "type": "Feature",
  "properties": {
    "addr:full":"21174 Keith Ct Redding CA 96003",
    "addr:housenumber":"21174",
    "addr:postcode":"96003",
    "addr:street":"Keith Ct",
    "iso:country":"US",
    "sg:address":"21174 Keith Ct",
    "sg:city":"Redding",
    "sg:classifiers":[
        {
            "category":"Building & Trades",
            "subcategory":"Construction",
            "type":"Services"
        }
    ],
    "sg:phone":"+1 530 515 9779",
    "sg:postcode":"96003",
    "sg:province":"CA",
    "sg:tags":[
        "house"
    ],
    "wof:name":"Burrows Construction",
    "wof:placetype":"venue"
},
  "geometry": {"coordinates":[-122.270658,40.652002],"type":"Point"}
}