{
  "type": "Feature",
  "properties": {
    "addr:full":"1200 Dodson Way Riverside CA 92507",
    "addr:housenumber":"1200",
    "addr:postcode":"92507",
    "addr:street":"Dodson Way",
    "iso:country":"US",
    "sg:address":"1200 Dodson Way",
    "sg:city":"Riverside",
    "sg:classifiers":[
        {
            "category":"Manufacturing",
            "subcategory":"Tools & Machinery",
            "type":"Manufacturing & Wholesale Goods"
        }
    ],
    "sg:phone":"+1 951 779 8020",
    "sg:postcode":"92507",
    "sg:province":"CA",
    "sg:tags":[
        "machine",
        "shop"
    ],
    "wof:name":"BAMM Engineering",
    "wof:placetype":"venue"
},
  "geometry": {"coordinates":[-117.345454,33.999447],"type":"Point"}
}