{
  "type": "Feature",
  "properties": {
    "addr:full":"43246 Christy St Fremont CA 94538",
    "addr:housenumber":"43246",
    "addr:postcode":"94538",
    "addr:street":"Christy St",
    "iso:country":"US",
    "sg:address":"43246 Christy St",
    "sg:city":"Fremont",
    "sg:classifiers":[
        {
            "category":"Wholesale",
            "subcategory":"Machinery & Supplies",
            "type":"Manufacturing & Wholesale Goods"
        },
        {
            "category":"Wholesale",
            "subcategory":"Electrical",
            "type":"Manufacturing & Wholesale Goods"
        }
    ],
    "sg:phone":"+1 510 226 8210",
    "sg:postcode":"94538",
    "sg:province":"CA",
    "sg:tags":[
        "equipment",
        "industrial",
        "ultrasonic"
    ],
    "wof:name":"Branson Ultrasonics Corp",
    "wof:placetype":"venue"
},
  "geometry": {"coordinates":[-121.973767,37.506882],"type":"Point"}
}