{
  "type": "Feature",
  "properties": {
    "iso:country":"US",
    "sg:address":"1050 California Ave",
    "sg:city":"San Jose",
    "sg:classifiers":[
        {
            "category":"Building & Trades",
            "subcategory":"Electrical",
            "type":"Services"
        }
    ],
    "sg:phone":"+1 408 971 2311",
    "sg:postcode":"95125",
    "sg:province":"CA",
    "sg:tags":[
        "electric",
        "contractor"
    ],
    "wof:name":"Temple Electric",
    "wof:placetype":"venue"
},
  "geometry": {"coordinates":[-121.894727,37.302633],"type":"Point"}
}