{
  "type": "Feature",
  "properties": {
    "addr:full":"1580 N Batavia St Ste 4 Orange CA 92867",
    "addr:housenumber":"1580",
    "addr:postcode":"92867",
    "addr:street":"N Batavia St Ste 4",
    "iso:country":"US",
    "sg:address":"1580 N Batavia St Ste 4",
    "sg:city":"Orange",
    "sg:classifiers":[
        {
            "category":"Shopping",
            "subcategory":"Clothing, Apparel, & Fashions",
            "type":"Retail Goods"
        }
    ],
    "sg:phone":"+1 714 998 6768",
    "sg:postcode":"92867",
    "sg:province":"CA",
    "sg:tags":[
        "men's",
        "clothing",
        "accessory"
    ],
    "wof:name":"Orisue",
    "wof:placetype":"venue"
},
  "geometry": {"coordinates":[-117.862533,33.813775],"type":"Point"}
}