{
  "type": "Feature",
  "properties": {
    "addr:full":"1655 Cedar Crest Ave Tahoe City CA 96145",
    "addr:housenumber":"1655",
    "addr:postcode":"96145",
    "addr:street":"Cedar Crest Ave",
    "iso:country":"US",
    "sg:address":"1655 Cedar Crest Ave",
    "sg:city":"Tahoe City",
    "sg:classifiers":[
        {
            "category":"Personal",
            "type":"Services"
        }
    ],
    "sg:phone":"+1 530 583 3355",
    "sg:postcode":"96145",
    "sg:province":"CA",
    "sg:tags":[
        "therapist",
        "massage"
    ],
    "wof:name":"Soul Kneads Massage Therapy",
    "wof:placetype":"venue"
},
  "geometry": {"coordinates":[-120.155681,39.142392],"type":"Point"}
}