{
  "type": "Feature",
  "properties": {
    "addr:full":"1100 Maple Ave Los Angeles CA 90015",
    "addr:housenumber":"1100",
    "addr:postcode":"90015",
    "addr:street":"Maple Ave",
    "iso:country":"US",
    "sg:address":"1100 Maple Ave",
    "sg:city":"Los Angeles",
    "sg:classifiers":[
        {
            "category":"Manufacturing",
            "subcategory":"Apparel",
            "type":"Manufacturing & Wholesale Goods"
        }
    ],
    "sg:phone":"+1 213 741 0202",
    "sg:postcode":"90015",
    "sg:province":"CA",
    "wof:name":"Sally",
    "wof:placetype":"venue"
},
  "geometry": {"coordinates":[-118.256336,34.035644],"type":"Point"}
}