{
  "type": "Feature",
  "properties": {
    "iso:country":"US",
    "sg:address":"515 W 6th St",
    "sg:city":"Corona",
    "sg:classifiers":[
        {
            "category":"Restaurant",
            "type":"Food & Drink"
        }
    ],
    "sg:phone":"+1 951 272 2235",
    "sg:postcode":"92882",
    "sg:province":"CA",
    "wof:name":"El Acapulco",
    "wof:placetype":"venue"
},
  "geometry": {"coordinates":[-117.57235300000001,33.876142],"type":"Point"}
}