{
  "type": "Feature",
  "properties": {
    "iso:country":"US",
    "sg:address":"2205 E Carson St",
    "sg:city":"Carson",
    "sg:classifiers":[
        {
            "category":"Wholesale",
            "subcategory":"Machinery & Supplies",
            "type":"Manufacturing & Wholesale Goods"
        }
    ],
    "sg:phone":"+1 310 513 1021",
    "sg:postcode":"90810",
    "sg:province":"CA",
    "sg:tags":[
        "cargo",
        "container",
        "freight"
    ],
    "wof:name":"Schumacher Cargo Lines",
    "wof:placetype":"venue"
},
  "geometry": {"coordinates":[-118.237381,33.831806],"type":"Point"}
}