{
  "type": "Feature",
  "properties": {
    "iso:country":"US",
    "sg:address":"3710 W 54th St",
    "sg:city":"Los Angeles",
    "sg:classifiers":[
        {
            "category":"Education",
            "subcategory":"Special Training",
            "type":"Public Place"
        }
    ],
    "sg:phone":"+1 323 294 8515",
    "sg:postcode":"90043",
    "sg:province":"CA",
    "sg:tags":[
        "center"
    ],
    "wof:name":"Inner City Education Foundatn",
    "wof:placetype":"venue"
},
  "geometry": {"coordinates":[-118.338641,33.992991],"type":"Point"}
}