{
  "type": "Feature",
  "properties": {
    "addr:full":"435 Roosevelt St Coalinga CA 93210",
    "addr:housenumber":"435",
    "addr:postcode":"93210",
    "addr:street":"Roosevelt St",
    "iso:country":"US",
    "sg:address":"435 Roosevelt St",
    "sg:city":"Coalinga",
    "sg:classifiers":[
        {
            "category":"Professional",
            "type":"Services"
        }
    ],
    "sg:phone":"+1 559 935 0023",
    "sg:postcode":"93210",
    "sg:province":"CA",
    "wof:name":"Ebert Bissett",
    "wof:placetype":"venue"
},
  "geometry": {"coordinates":[-120.348913,36.140424],"type":"Point"}
}