{
  "type": "Feature",
  "properties": {
    "iso:country":"US",
    "sg:address":"1851 McCarthy Blvd Ste 220",
    "sg:city":"Milpitas",
    "sg:classifiers":[
        {
            "category":"Building & Trades",
            "subcategory":"Construction",
            "type":"Services"
        }
    ],
    "sg:phone":"+1 510 227 8300",
    "sg:postcode":"95035",
    "sg:province":"CA",
    "sg:tags":[
        "contractor"
    ],
    "sg:website":"www.sherconstruction.com",
    "wof:name":"Sher Construction, Inc",
    "wof:placetype":"venue"
},
  "geometry": {"coordinates":[-121.91495500000001,37.400236],"type":"Point"}
}