{
  "type": "Feature",
  "properties": {
    "addr:full":"1524 W Mineral King Ave Visalia CA 93291",
    "addr:housenumber":"1524",
    "addr:postcode":"93291",
    "addr:street":"W Mineral King Ave",
    "iso:country":"US",
    "sg:address":"1524 W Mineral King Ave",
    "sg:city":"Visalia",
    "sg:classifiers":[
        {
            "category":"Real Estate",
            "subcategory":"Real Estate Agent",
            "type":"Services"
        }
    ],
    "sg:phone":"+1 559 733 4371",
    "sg:postcode":"93291",
    "sg:province":"CA",
    "sg:tags":[
        "appraiser"
    ],
    "wof:name":"Central Valley Appraisal Co-Op",
    "wof:placetype":"venue"
},
  "geometry": {"coordinates":[-119.30943000000001,36.327499],"type":"Point"}
}