{
  "type": "Feature",
  "properties": {
    "addr:full":"2118 29th St San Diego CA 92104",
    "addr:housenumber":"2118",
    "addr:postcode":"92104",
    "addr:street":"29Th St",
    "iso:country":"US",
    "sg:address":"2118 29th St",
    "sg:city":"San Diego",
    "sg:classifiers":[
        {
            "category":"Manufacturing",
            "subcategory":"Building Materials",
            "type":"Manufacturing & Wholesale Goods"
        }
    ],
    "sg:phone":"+1 619 233 4632",
    "sg:postcode":"92104",
    "sg:province":"CA",
    "sg:tags":[
        "mfg",
        "wood",
        "kitchen",
        "cabinet"
    ],
    "wof:name":"PH Cabinetry",
    "wof:placetype":"venue"
},
  "geometry": {"coordinates":[-117.132057,32.728423],"type":"Point"}
}