{
  "type": "Feature",
  "properties": {
    "iso:country":"US",
    "sg:address":"2029 Newpark Mall",
    "sg:city":"Newark",
    "sg:classifiers":[
        {
            "category":"Shopping",
            "subcategory":"Clothing, Apparel, & Fashions",
            "type":"Retail Goods"
        }
    ],
    "sg:phone":"+1 510 494 0244",
    "sg:postcode":"94560",
    "sg:province":"CA",
    "sg:tags":[
        "furnishing"
    ],
    "wof:name":"Express Mens",
    "wof:placetype":"venue"
},
  "geometry": {"coordinates":[-122.00528199999999,37.526946],"type":"Point"}
}