{
  "type": "Feature",
  "properties": {
    "addr:full":"19485 Sonoma Hwy Ste B Sonoma CA 95476",
    "addr:housenumber":"19485",
    "addr:postcode":"95476",
    "addr:street":"Sonoma Hwy Ste B",
    "iso:country":"US",
    "sg:address":"19485 Sonoma Hwy Ste B",
    "sg:city":"Sonoma",
    "sg:classifiers":[
        {
            "category":"Banks & Credit Unions",
            "subcategory":"Investment Brokerage",
            "type":"Services"
        }
    ],
    "sg:phone":"+1 707 935 0865",
    "sg:postcode":"95476",
    "sg:province":"CA",
    "sg:tags":[
        "security"
    ],
    "wof:name":"James Wandzilak",
    "wof:placetype":"venue"
},
  "geometry": {"coordinates":[-122.47582800000001,38.294298],"type":"Point"}
}