{
  "type": "Feature",
  "properties": {
    "addr:full":"21 Hamilton Ct Hollister CA 95023",
    "addr:housenumber":"21",
    "addr:postcode":"hollister ca 95023",
    "addr:street":"Hamilton Ct",
    "iso:country":"US",
    "sg:address":"21 Hamilton Ct",
    "sg:city":"Hollister",
    "sg:classifiers":[
        {
            "category":"Manufacturing",
            "subcategory":"Electronics",
            "type":"Manufacturing & Wholesale Goods"
        }
    ],
    "sg:phone":"+1 831 636 7728",
    "sg:postcode":"95023",
    "sg:province":"CA",
    "sg:tags":[
        "printed",
        "circuit",
        "etched"
    ],
    "sg:website":"www.royalcircuits.com",
    "wof:name":"Royal Circuit Solutions Inc",
    "wof:placetype":"venue"
},
  "geometry": {"coordinates":[-121.390457,36.882428],"type":"Point"}
}