{
  "type": "Feature",
  "properties": {
    "addr:full":"1012 Manhattan Ave Manhattan Beach CA 90266",
    "addr:housenumber":"1012",
    "addr:postcode":"90266",
    "addr:street":"Manhattan Ave",
    "iso:country":"US",
    "sg:address":"1012 Manhattan Ave",
    "sg:city":"Manhattan Beach",
    "sg:classifiers":[
        {
            "category":"Arts & Performance",
            "subcategory":"Arts Center",
            "type":"Entertainment"
        }
    ],
    "sg:phone":"+1 310 374 4500",
    "sg:postcode":"90266",
    "sg:province":"CA",
    "sg:website":"ceramicstogo.net",
    "wof:name":"Ceramics To Go",
    "wof:placetype":"venue"
},
  "geometry": {"coordinates":[-118.409977,33.883834],"type":"Point"}
}