{
  "type": "Feature",
  "properties": {
    "addr:full":"490 S Leggett St Porterville CA 93257",
    "addr:housenumber":"490",
    "addr:postcode":"93257",
    "addr:street":"S Leggett St",
    "iso:country":"US",
    "sg:address":"490 S Leggett St",
    "sg:city":"Porterville",
    "sg:classifiers":[
        {
            "category":"Restaurant",
            "type":"Food & Drink"
        }
    ],
    "sg:phone":"+1 559 784 2589",
    "sg:postcode":"93257",
    "sg:province":"CA",
    "sg:tags":[
        "sandwich"
    ],
    "wof:name":"Los Arcos",
    "wof:placetype":"venue"
},
  "geometry": {"coordinates":[-118.99942799999999,36.058319],"type":"Point"}
}