{
  "type": "Feature",
  "properties": {
    "addr:full":"2512 Horton Ave San Diego CA 92101",
    "addr:housenumber":"2512",
    "addr:postcode":"92101",
    "addr:street":"Horton Ave",
    "iso:country":"US",
    "sg:address":"2512 Horton Ave",
    "sg:city":"San Diego",
    "sg:classifiers":[
        {
            "category":"Social Services",
            "type":"Services"
        }
    ],
    "sg:phone":"+1 619 232 8811",
    "sg:postcode":"92101",
    "sg:province":"CA",
    "sg:tags":[
        "organization",
        "welfare"
    ],
    "sg:website":"www.icfe.info",
    "wof:name":"National Center-Financial Ed",
    "wof:placetype":"venue"
},
  "geometry": {"coordinates":[-117.168042,32.731747],"type":"Point"}
}