{
  "type": "Feature",
  "properties": {
    "iso:country":"US",
    "sg:address":"6150 Stoneridge Mall Rd",
    "sg:city":"Pleasanton",
    "sg:classifiers":[
        {
            "category":"Real Estate",
            "subcategory":"Real Estate Operator",
            "type":"Services"
        }
    ],
    "sg:phone":"+1 925 469 0477",
    "sg:postcode":"94588",
    "sg:province":"CA",
    "sg:tags":[
        "property",
        "lessor"
    ],
    "wof:name":"Town & Cntry Credit",
    "wof:placetype":"venue"
},
  "geometry": {"coordinates":[-121.925678,37.696518],"type":"Point"}
}