{
  "type": "Feature",
  "properties": {
    "addr:full":"205 S Harbor Blvd Santa Ana CA 92704",
    "addr:housenumber":"205",
    "addr:postcode":"92704",
    "addr:street":"S Harbor Blvd",
    "iso:country":"US",
    "sg:address":"205 S Harbor Blvd",
    "sg:city":"Santa Ana",
    "sg:classifiers":[
        {
            "category":"Wholesale",
            "subcategory":"Durable Goods & Equipment",
            "type":"Manufacturing & Wholesale Goods"
        }
    ],
    "sg:phone":"+1 714 812 6605",
    "sg:postcode":"92704",
    "sg:province":"CA",
    "wof:name":"Only Wholesale",
    "wof:placetype":"venue"
},
  "geometry": {"coordinates":[-117.920098,33.743237],"type":"Point"}
}