{
  "type": "Feature",
  "properties": {
    "addr:full":"6102 Ave Encinas Carlsbad CA 92011",
    "addr:postcode":"92011",
    "addr:street":"6102 Ave Encinas",
    "iso:country":"US",
    "sg:address":"6102 Ave Encinas",
    "sg:city":"Carlsbad",
    "sg:classifiers":[
        {
            "category":"Professional",
            "type":"Services"
        }
    ],
    "sg:phone":"+1 760 603 8321",
    "sg:postcode":"92011",
    "sg:province":"CA",
    "wof:name":"Motion Products West",
    "wof:placetype":"venue"
},
  "geometry": {"coordinates":[-117.32496399999999,33.122296],"type":"Point"}
}