{
  "type": "Feature",
  "properties": {
    "iso:country":"US",
    "sg:address":"1301 W 21st St",
    "sg:city":"Long Beach",
    "sg:classifiers":[
        {
            "category":"Social Services",
            "subcategory":"Child Care",
            "type":"Services"
        }
    ],
    "sg:phone":"+1 562 951 1992",
    "sg:postcode":"90810",
    "sg:province":"CA",
    "sg:tags":[
        "day"
    ],
    "wof:name":"Children Today Inc",
    "wof:placetype":"venue"
},
  "geometry": {"coordinates":[-118.20892,33.795437],"type":"Point"}
}