{
  "type": "Feature",
  "properties": {
    "addr:full":"1180 S Mount Vernon Ave Colton CA 92324",
    "addr:housenumber":"1180",
    "addr:postcode":"92324",
    "addr:street":"S Mount Vernon Ave",
    "iso:country":"US",
    "sg:address":"1180 S Mount Vernon Ave",
    "sg:city":"Colton",
    "sg:classifiers":[
        {
            "category":"Restaurant",
            "type":"Food & Drink"
        }
    ],
    "sg:menulink":"http://www.allmenus.com/ca/san-bernardino/170897-carls-jr/menu/",
    "sg:phone":"+1 909 824 8003",
    "sg:postcode":"92324",
    "sg:province":"CA",
    "sg:tags":[
        "burger",
        "american"
    ],
    "wof:name":"Carl's Jr.",
    "wof:placetype":"venue"
},
  "geometry": {"coordinates":[-117.30848,34.04919],"type":"Point"}
}