{
  "type": "Feature",
  "properties": {
    "addr:full":"13576 Harbor Boulevard Garden Grove CA 92843",
    "addr:housenumber":"13576",
    "addr:postcode":"92843",
    "addr:street":"Harbor Boulevard",
    "iso:country":"US",
    "sg:address":"13576 Harbor Boulevard",
    "sg:city":"Garden Grove",
    "sg:classifiers":[
        {
            "category":"Food & Beverages",
            "subcategory":"Bakery",
            "type":"Retail Goods"
        }
    ],
    "sg:phone":"+1 714 530 9799",
    "sg:postcode":"92843",
    "sg:province":"CA",
    "sg:tags":[
        "sandwich"
    ],
    "wof:name":"9 Sandwiches",
    "wof:placetype":"venue"
},
  "geometry": {"coordinates":[-117.92022299999999,33.765784],"type":"Point"}
}