{
  "type": "Feature",
  "properties": {
    "iso:country":"US",
    "sg:address":"2186 Eastman Ave",
    "sg:city":"Ventura",
    "sg:classifiers":[
        {
            "category":"Professional",
            "subcategory":"Accounting & Tax Preparation",
            "type":"Services"
        }
    ],
    "sg:phone":"+1 805 644 7629",
    "sg:postcode":"93003",
    "sg:province":"CA",
    "sg:tags":[
        "return",
        "filing"
    ],
    "wof:name":"Butson & Barrett Financial Svc",
    "wof:placetype":"venue"
},
  "geometry": {"coordinates":[-119.229803,34.252577],"type":"Point"}
}