{
  "type": "Feature",
  "properties": {
    "iso:country":"US",
    "sg:address":"5658 Sepulveda Blvd",
    "sg:city":"Van Nuys",
    "sg:classifiers":[
        {
            "category":"Restaurant",
            "type":"Food & Drink"
        }
    ],
    "sg:phone":"+1 818 997 7118",
    "sg:postcode":"91411",
    "sg:province":"CA",
    "wof:name":"Hong Kong 88 Chinese Cuisine",
    "wof:placetype":"venue"
},
  "geometry": {"coordinates":[-118.466094,34.174672],"type":"Point"}
}