{
  "type": "Feature",
  "properties": {
    "addr:full":"2327 Blanding Ave Alameda CA 94501",
    "addr:housenumber":"2327",
    "addr:postcode":"94501",
    "addr:street":"Blanding Ave",
    "iso:country":"US",
    "sg:address":"2327 Blanding Ave",
    "sg:city":"Alameda",
    "sg:classifiers":[
        {
            "category":"Building & Trades",
            "subcategory":"Cleaning & Sanitation",
            "type":"Services"
        }
    ],
    "sg:phone":"+1 510 521 5878",
    "sg:postcode":"94501",
    "sg:province":"CA",
    "sg:tags":[
        "house"
    ],
    "wof:name":"Merry Maids Inc",
    "wof:placetype":"venue"
},
  "geometry": {"coordinates":[-122.238542,37.771146],"type":"Point"}
}