{
  "type": "Feature",
  "properties": {
    "addr:full":"12371 Incline Dr Auburn CA 95603",
    "addr:housenumber":"12371",
    "addr:postcode":"ca 95603",
    "addr:street":"Incline Dr",
    "iso:country":"US",
    "sg:address":"12371 Incline Dr",
    "sg:city":"Auburn",
    "sg:classifiers":[
        {
            "category":"Professional",
            "subcategory":"Business Services",
            "type":"Services"
        }
    ],
    "sg:phone":"+1 530 823 0913",
    "sg:postcode":"95603",
    "sg:province":"CA",
    "sg:tags":[
        "consultant",
        "coach"
    ],
    "wof:name":"Ck Consulting",
    "wof:placetype":"venue"
},
  "geometry": {"coordinates":[-121.077454,38.923672],"type":"Point"}
}