{
  "type": "Feature",
  "properties": {
    "addr:full":"12030 Sherman Way North Hollywood CA 91605",
    "addr:housenumber":"12030",
    "addr:postcode":"91605",
    "addr:street":"Sherman Way",
    "iso:country":"US",
    "sg:address":"12030 Sherman Way",
    "sg:city":"North Hollywood",
    "sg:classifiers":[
        {
            "category":"Home & Garden",
            "subcategory":"Carpets & Floor Coverings",
            "type":"Retail Goods"
        },
        {
            "category":"Wholesale",
            "subcategory":"Home Furnishings",
            "type":"Manufacturing & Wholesale Goods"
        }
    ],
    "sg:phone":"+1 818 503 9454",
    "sg:postcode":"91605",
    "sg:province":"CA",
    "sg:tags":[
        "recycled",
        "rug",
        "lining",
        "accessory"
    ],
    "wof:name":"Carpet Pad Recycling Center",
    "wof:placetype":"venue"
},
  "geometry": {"coordinates":[-118.39400999999999,34.200888],"type":"Point"}
}