{
  "type": "Feature",
  "properties": {
    "iso:country":"US",
    "sg:address":"2254 Pacific Ave",
    "sg:city":"Long Beach",
    "sg:classifiers":[
        {
            "category":"Wholesale",
            "subcategory":"Computers",
            "type":"Manufacturing & Wholesale Goods"
        },
        {
            "category":"Professional",
            "subcategory":"Computer Services",
            "type":"Services"
        }
    ],
    "sg:phone":"+1 562 595 0899",
    "sg:postcode":"90806",
    "sg:province":"CA",
    "sg:tags":[
        "repair"
    ],
    "wof:name":"Computer Station",
    "wof:placetype":"venue"
},
  "geometry": {"coordinates":[-118.194,33.797901],"type":"Point"}
}