{
  "type": "Feature",
  "properties": {
    "addr:full":"1080 University Ave San Diego CA 92103",
    "addr:housenumber":"1080",
    "addr:postcode":"92103",
    "addr:street":"University Ave",
    "iso:country":"US",
    "sg:address":"1080 University Ave",
    "sg:city":"San Diego",
    "sg:classifiers":[
        {
            "category":"Shopping",
            "subcategory":"Tobacco",
            "type":"Retail Goods"
        }
    ],
    "sg:phone":"+1 619 294 3529",
    "sg:postcode":"92103",
    "sg:province":"CA",
    "sg:tags":[
        "shop",
        "cigarette",
        "cigar"
    ],
    "wof:name":"Holy Smoke",
    "wof:placetype":"venue"
},
  "geometry": {"coordinates":[-117.153999,32.7486],"type":"Point"}
}