{
  "type": "Feature",
  "properties": {
    "addr:full":"1485 Enea Cir Concord CA 94520",
    "addr:housenumber":"1485",
    "addr:postcode":"94520",
    "addr:street":"Enea Cir",
    "iso:country":"US",
    "sg:address":"1485 Enea Cir",
    "sg:city":"Concord",
    "sg:classifiers":[
        {
            "category":"Health Services",
            "subcategory":"Doctor",
            "type":"Services"
        }
    ],
    "sg:phone":"+1 925 363 4945",
    "sg:postcode":"94520",
    "sg:province":"CA",
    "sg:tags":[
        "physician",
        "surgeon"
    ],
    "wof:name":"Tom Franklin MD",
    "wof:placetype":"venue"
},
  "geometry": {"coordinates":[-122.051802,37.971239],"type":"Point"}
}