{
  "type": "Feature",
  "properties": {
    "iso:country":"US",
    "sg:address":"40485 Murrieta Hot Springs Rd",
    "sg:city":"Murrieta",
    "sg:classifiers":[
        {
            "category":"Personal",
            "subcategory":"Beauty Salon",
            "type":"Services"
        }
    ],
    "sg:phone":"+1 951 696 1114",
    "sg:postcode":"92563",
    "sg:province":"CA",
    "sg:tags":[
        "treatment",
        "skin"
    ],
    "wof:name":"Smith Family Handmade Soap Co",
    "wof:placetype":"venue"
},
  "geometry": {"coordinates":[-117.179017,33.556442],"type":"Point"}
}