{
  "type": "Feature",
  "properties": {
    "addr:full":"108 E Walnut Ave Monrovia CA 91016",
    "addr:housenumber":"108",
    "addr:postcode":"91016",
    "addr:street":"E Walnut Ave",
    "iso:country":"US",
    "sg:address":"108 E Walnut Ave",
    "sg:city":"Monrovia",
    "sg:classifiers":[
        {
            "category":"Manufacturing",
            "subcategory":"Printing",
            "type":"Manufacturing & Wholesale Goods"
        }
    ],
    "sg:phone":"+1 626 599 8502",
    "sg:postcode":"91016",
    "sg:province":"CA",
    "sg:tags":[
        "commercial"
    ],
    "wof:name":"S J L Printery",
    "wof:placetype":"venue"
},
  "geometry": {"coordinates":[-117.998734,34.143658],"type":"Point"}
}