{
  "type": "Feature",
  "properties": {
    "addr:full":"23576 Ave 96 Terra Bella CA 93270",
    "addr:housenumber":"23576;96",
    "addr:postcode":"93270",
    "addr:street":"Ave",
    "iso:country":"US",
    "sg:address":"23576 Ave 96",
    "sg:city":"Terra Bella",
    "sg:classifiers":[
        {
            "category":"Wholesale",
            "subcategory":"Farm Supplies",
            "type":"Manufacturing & Wholesale Goods"
        }
    ],
    "sg:phone":"+1 559 535 4461",
    "sg:postcode":"93270",
    "sg:province":"CA",
    "sg:tags":[
        "chemical",
        "agricultural"
    ],
    "wof:name":"Leffingwell Ag Sales Co",
    "wof:placetype":"venue"
},
  "geometry": {"coordinates":[-119.044687,35.964311],"type":"Point"}
}