{
  "type": "Feature",
  "properties": {
    "addr:full":"7300 Laguna Blvd Elk Grove CA 95758",
    "addr:housenumber":"7300",
    "addr:postcode":"95758",
    "addr:street":"Laguna Blvd",
    "iso:country":"US",
    "sg:address":"7300 Laguna Blvd",
    "sg:city":"Elk Grove",
    "sg:classifiers":[
        {
            "category":"Restaurant",
            "type":"Food & Drink"
        }
    ],
    "sg:phone":"+1 916 683 9898",
    "sg:postcode":"95758",
    "sg:province":"CA",
    "wof:name":"Bamboo Inn",
    "wof:placetype":"venue"
},
  "geometry": {"coordinates":[-121.40674199999999,38.421693],"type":"Point"}
}