{
  "type": "Feature",
  "properties": {
    "iso:country":"US",
    "sg:address":"3315 183rd St",
    "sg:city":"Torrance",
    "sg:classifiers":[
        {
            "category":"Building & Trades",
            "subcategory":"Electrical",
            "type":"Services"
        }
    ],
    "sg:phone":"+1 310 719 8640",
    "sg:postcode":"90504",
    "sg:province":"CA",
    "sg:tags":[
        "electrical",
        "contractor"
    ],
    "wof:name":"Avanti Electric Inc",
    "wof:placetype":"venue"
},
  "geometry": {"coordinates":[-118.330118,33.864886],"type":"Point"}
}