{
  "type": "Feature",
  "properties": {
    "iso:country":"US",
    "sg:address":"2891 Zinfandel Drive",
    "sg:city":"Rancho Cordova",
    "sg:classifiers":[
        {
            "category":"Restaurant",
            "type":"Food & Drink"
        }
    ],
    "sg:phone":"+1 916 631 8619",
    "sg:postcode":"95670",
    "sg:province":"CA",
    "wof:name":"Taco Bell",
    "wof:placetype":"venue"
},
  "geometry": {"coordinates":[-121.28776499999999,38.594016],"type":"Point"}
}