{
  "type": "Feature",
  "properties": {
    "iso:country":"US",
    "sg:address":"8821 San Fernando Rd",
    "sg:city":"Sun Valley",
    "sg:classifiers":[
        {
            "category":"Wholesale",
            "subcategory":"Metals & Minerals",
            "type":"Manufacturing & Wholesale Goods"
        },
        {
            "category":"Wholesale",
            "subcategory":"Scrap",
            "type":"Manufacturing & Wholesale Goods"
        }
    ],
    "sg:phone":"+1 562 862 0833",
    "sg:postcode":"91352",
    "sg:province":"CA",
    "sg:tags":[
        "broker",
        "iron"
    ],
    "wof:name":"Kal Industrial Metals Co",
    "wof:placetype":"venue"
},
  "geometry": {"coordinates":[-118.382453,34.228518],"type":"Point"}
}