{
  "type": "Feature",
  "properties": {
    "addr:full":"28159 Avenue Stanford Valencia CA 91355",
    "addr:housenumber":"28159",
    "addr:postcode":"91355",
    "addr:street":"Avenue",
    "iso:country":"US",
    "sg:address":"28159 Avenue Stanford",
    "sg:city":"Valencia",
    "sg:classifiers":[
        {
            "category":"Building & Trades",
            "subcategory":"Cleaning & Sanitation",
            "type":"Services"
        }
    ],
    "sg:phone":"+1 661 451 1505",
    "sg:postcode":"91355",
    "sg:province":"CA",
    "sg:tags":[
        "carpet"
    ],
    "sg:website":"www.supercleancarpetcleaning.com",
    "wof:name":"Super Clean Carpet Cleaning In Valencia",
    "wof:placetype":"venue"
},
  "geometry": {"coordinates":[-118.590181,34.434486],"type":"Point"}
}