{
  "type": "Feature",
  "properties": {
    "iso:country":"US",
    "sg:address":"2700 Marconi Ave",
    "sg:city":"Sacramento",
    "sg:classifiers":[
        {
            "category":"Shopping",
            "type":"Retail Goods"
        }
    ],
    "sg:phone":"+1 916 485 1915",
    "sg:postcode":"95821",
    "sg:province":"CA",
    "sg:tags":[
        "infant",
        "gear",
        "retailer",
        "accessory",
        "youth",
        "baby",
        "furniture"
    ],
    "sg:website":"www.goores.com",
    "wof:name":"Goore's For Babies To Teens",
    "wof:placetype":"venue"
},
  "geometry": {"coordinates":[-121.398003,38.617901],"type":"Point"}
}