{
  "type": "Feature",
  "properties": {
    "iso:country":"US",
    "sg:address":"217 Bettyhill Ave",
    "sg:city":"Duarte",
    "sg:classifiers":[
        {
            "category":"Building & Trades",
            "subcategory":"Construction",
            "type":"Services"
        }
    ],
    "sg:phone":"+1 626 358 3626",
    "sg:postcode":"91010",
    "sg:province":"CA",
    "sg:tags":[
        "nonresidential"
    ],
    "wof:name":"Daniel Weir Construction",
    "wof:placetype":"venue"
},
  "geometry": {"coordinates":[-117.941919,34.149114],"type":"Point"}
}