{
  "type": "Feature",
  "properties": {
    "addr:full":"1000 Doran Ct Crescent City CA 95531",
    "addr:housenumber":"1000",
    "addr:postcode":"95531",
    "addr:street":"Doran Ct Crescent",
    "iso:country":"US",
    "sg:address":"1000 Doran Ct",
    "sg:city":"Crescent City",
    "sg:classifiers":[
        {
            "category":"Real Estate",
            "subcategory":"Real Estate Agent",
            "type":"Services"
        }
    ],
    "sg:phone":"+1 707 464 9741",
    "sg:postcode":"95531",
    "sg:province":"CA",
    "sg:website":"www.mingtreerealestate.com",
    "wof:name":"Ming Tree Real Estate",
    "wof:placetype":"venue"
},
  "geometry": {"coordinates":[-124.212384,41.752296],"type":"Point"}
}