{
  "type": "Feature",
  "properties": {
    "iso:country":"US",
    "sg:address":"2130 Redwood Hwy",
    "sg:city":"Greenbrae",
    "sg:classifiers":[
        {
            "category":"Professional",
            "type":"Services"
        },
        {
            "category":"Shopping",
            "subcategory":"Computers & Home Electronics",
            "type":"Retail Goods"
        }
    ],
    "sg:phone":"+1 415 461 9447",
    "sg:postcode":"94904",
    "sg:province":"CA",
    "sg:tags":[
        "equipment",
        "electronic",
        "supply"
    ],
    "wof:name":"Mr Sound Man",
    "wof:placetype":"venue"
},
  "geometry": {"coordinates":[-122.514833,37.941592],"type":"Point"}
}