{
  "type": "Feature",
  "properties": {
    "addr:full":"1212 W Main St Visalia CA 93291",
    "addr:housenumber":"1212",
    "addr:postcode":"93291",
    "addr:street":"W Main St",
    "iso:country":"US",
    "sg:address":"1212 W Main St",
    "sg:city":"Visalia",
    "sg:classifiers":[
        {
            "category":"Health Services",
            "subcategory":"Health Practitioner",
            "type":"Services"
        }
    ],
    "sg:phone":"+1 559 635 2124",
    "sg:postcode":"93291",
    "sg:province":"CA",
    "sg:tags":[
        "psychotherapist"
    ],
    "wof:name":"Stress Reduction Ctr",
    "wof:placetype":"venue"
},
  "geometry": {"coordinates":[-119.305356,36.330167],"type":"Point"}
}