{
  "type": "Feature",
  "properties": {
    "addr:full":"11257 Essex Ave Pomona CA 91766",
    "addr:housenumber":"11257",
    "addr:postcode":"91766",
    "addr:street":"Essex Ave",
    "iso:country":"US",
    "sg:address":"11257 Essex Ave",
    "sg:city":"Pomona",
    "sg:classifiers":[
        {
            "category":"Social Services",
            "subcategory":"Child Care",
            "type":"Services"
        }
    ],
    "sg:phone":"+1 909 628 3219",
    "sg:postcode":"91766",
    "sg:province":"CA",
    "wof:name":"Shelley's Family Day Care",
    "wof:placetype":"venue"
},
  "geometry": {"coordinates":[-117.71149699999999,34.049625],"type":"Point"}
}