{
  "type": "Feature",
  "properties": {
    "iso:country":"US",
    "sg:address":"7401 Fulton Ave",
    "sg:city":"North Hollywood",
    "sg:classifiers":[
        {
            "category":"Mining & Drilling",
            "type":"Manufacturing & Wholesale Goods"
        }
    ],
    "sg:phone":"+1 818 764 8464",
    "sg:postcode":"91605",
    "sg:province":"CA",
    "sg:tags":[
        "stone"
    ],
    "wof:name":"Stone Age Marble",
    "wof:placetype":"venue"
},
  "geometry": {"coordinates":[-118.4226,34.202871],"type":"Point"}
}