{
  "type": "Feature",
  "properties": {
    "iso:country":"US",
    "sg:address":"61 Curtner Avenue",
    "sg:city":"San Jose",
    "sg:classifiers":[
        {
            "category":"Restaurant",
            "type":"Food & Drink"
        }
    ],
    "sg:postcode":"95112",
    "sg:province":"CA",
    "sg:tags":[
        "barbeque"
    ],
    "sg:website":"www.famousdaves.com/",
    "wof:name":"Famous Dave's BBQ",
    "wof:placetype":"venue"
},
  "geometry": {"coordinates":[-121.86287299999999,37.302597],"type":"Point"}
}