{
  "type": "Feature",
  "properties": {
    "iso:country":"US",
    "sg:address":"9567 Arrow Rte",
    "sg:city":"Rancho Cucamonga",
    "sg:classifiers":[
        {
            "category":"Health Services",
            "subcategory":"Clinic",
            "type":"Services"
        }
    ],
    "sg:phone":"+1 909 476 9030",
    "sg:postcode":"91730",
    "sg:province":"CA",
    "sg:tags":[
        "home"
    ],
    "sg:website":"www.homeinstead.com",
    "wof:name":"Home Instead Senior Care",
    "wof:placetype":"venue"
},
  "geometry": {"coordinates":[-117.59434,34.099248],"type":"Point"}
}