{
  "type": "Feature",
  "properties": {
    "iso:country":"US",
    "sg:address":"4342 E La Palma Ave",
    "sg:city":"Anaheim",
    "sg:classifiers":[
        {
            "category":"Building & Trades",
            "subcategory":"Pest Control",
            "type":"Services"
        }
    ],
    "sg:phone":"+1 714 572 1384",
    "sg:postcode":"92807",
    "sg:province":"CA",
    "sg:website":"www.preventivepestcontrol.com",
    "wof:name":"Preventive Pest Control",
    "wof:placetype":"venue"
},
  "geometry": {"coordinates":[-117.822301,33.859198],"type":"Point"}
}