{
  "type": "Feature",
  "properties": {
    "addr:full":"5630 Bay St Emeryville CA 94608",
    "addr:housenumber":"5630",
    "addr:postcode":"94608",
    "addr:street":"Bay St",
    "iso:country":"US",
    "sg:address":"5630 Bay St",
    "sg:city":"Emeryville",
    "sg:classifiers":[
        {
            "category":"Home & Garden",
            "subcategory":"Home Furnishings",
            "type":"Retail Goods"
        }
    ],
    "sg:phone":"+1 510 547 0998",
    "sg:postcode":"94608",
    "sg:province":"CA",
    "sg:tags":[
        "housewares"
    ],
    "wof:name":"Hold Everything",
    "wof:placetype":"venue"
},
  "geometry": {"coordinates":[-122.292295,37.834585],"type":"Point"}
}