{
  "type": "Feature",
  "properties": {
    "iso:country":"US",
    "sg:address":"866 Embarcadero Dr",
    "sg:city":"Broderick",
    "sg:classifiers":[
        {
            "category":"Shopping",
            "type":"Retail Goods"
        }
    ],
    "sg:phone":"+1 916 373 1400",
    "sg:postcode":"95605",
    "sg:province":"CA",
    "sg:tags":[
        "equipment",
        "supply"
    ],
    "wof:name":"Mexifoods Inc",
    "wof:placetype":"venue"
},
  "geometry": {"coordinates":[-121.562591,38.587564],"type":"Point"}
}