{
  "type": "Feature",
  "properties": {
    "addr:full":"1348 Trinity St Redding CA 96001",
    "addr:housenumber":"1348",
    "addr:postcode":"96001",
    "addr:street":"Trinity St",
    "iso:country":"US",
    "sg:address":"1348 Trinity St",
    "sg:city":"Redding",
    "sg:classifiers":[
        {
            "category":"Social Services",
            "type":"Services"
        }
    ],
    "sg:phone":"+1 530 241 8472",
    "sg:postcode":"96001",
    "sg:province":"CA",
    "sg:tags":[
        "counselor",
        "marriage",
        "family"
    ],
    "wof:name":"Bernadette Butz",
    "wof:placetype":"venue"
},
  "geometry": {"coordinates":[-122.392629,40.588696],"type":"Point"}
}