{
  "type": "Feature",
  "properties": {
    "iso:country":"US",
    "sg:address":"6319 de Soto Ave",
    "sg:city":"Woodland Hills",
    "sg:classifiers":[
        {
            "category":"Building & Trades",
            "subcategory":"Construction",
            "type":"Services"
        }
    ],
    "sg:phone":"+1 818 884 3018",
    "sg:postcode":"91303",
    "sg:province":"CA",
    "sg:tags":[
        "general",
        "contractor"
    ],
    "wof:name":"A2Z Construction Inc",
    "wof:placetype":"venue"
},
  "geometry": {"coordinates":[-118.588525,34.188036],"type":"Point"}
}