{
  "type": "Feature",
  "properties": {
    "addr:full":"5504 Balboa Avenue San Diego CA 92111",
    "addr:housenumber":"5504",
    "addr:postcode":"92111",
    "addr:street":"Balboa Avenue",
    "iso:country":"US",
    "sg:address":"5504 Balboa Avenue",
    "sg:city":"San Diego",
    "sg:classifiers":[
        {
            "category":"Shopping",
            "subcategory":"Mobile Phones",
            "type":"Retail Goods"
        }
    ],
    "sg:phone":"+1 858 569 6757",
    "sg:postcode":"92111",
    "sg:province":"CA",
    "wof:name":"T-Mobile",
    "wof:placetype":"venue"
},
  "geometry": {"coordinates":[-117.178011,32.81785],"type":"Point"}
}