{
  "type": "Feature",
  "properties": {
    "iso:country":"US",
    "sg:address":"731 E Angeleno Ave",
    "sg:city":"Burbank",
    "sg:classifiers":[
        {
            "category":"Banks & Credit Unions",
            "subcategory":"Financial Services",
            "type":"Services"
        }
    ],
    "sg:phone":"+1 818 841 0255",
    "sg:postcode":"91501",
    "sg:province":"CA",
    "wof:name":"El Cid Bookkeeping Services",
    "wof:placetype":"venue"
},
  "geometry": {"coordinates":[-118.300635,34.186795],"type":"Point"}
}