{
  "type": "Feature",
  "properties": {
    "addr:full":"816 W Whittier Blvd La Habra CA 90631",
    "addr:housenumber":"816",
    "addr:postcode":"90631",
    "addr:street":"W Whittier Blvd",
    "iso:country":"US",
    "sg:address":"816 W Whittier Blvd",
    "sg:city":"La Habra",
    "sg:classifiers":[
        {
            "category":"Restaurant",
            "type":"Food & Drink"
        }
    ],
    "sg:phone":"+1 562 690 2011",
    "sg:postcode":"90631",
    "sg:province":"CA",
    "sg:website":"www.restaurantbusinessinc.com",
    "wof:name":"Restaurant Business Inc",
    "wof:placetype":"venue"
},
  "geometry": {"coordinates":[-117.956879,33.939035],"type":"Point"}
}