{
  "type": "Feature",
  "properties": {
    "iso:country":"US",
    "sg:address":"833 Torrance Blvd Ste 102",
    "sg:city":"Torrance",
    "sg:classifiers":[
        {
            "category":"Education",
            "subcategory":"Kindergarten",
            "type":"Public Place"
        }
    ],
    "sg:phone":"+1 310 538 8668",
    "sg:postcode":"90502",
    "sg:province":"CA",
    "sg:tags":[
        "school",
        "driving"
    ],
    "wof:name":"Avus Driving & Traffic School",
    "wof:placetype":"venue"
},
  "geometry": {"coordinates":[-118.289001,33.842098],"type":"Point"}
}