{
  "type": "Feature",
  "properties": {
    "addr:full":"120 Gray Ave Santa Barbara CA 93101",
    "addr:housenumber":"120",
    "addr:postcode":"93101",
    "addr:street":"Gray Ave",
    "iso:country":"US",
    "sg:address":"120 Gray Ave",
    "sg:city":"Santa Barbara",
    "sg:classifiers":[
        {
            "category":"Building & Trades",
            "subcategory":"Construction",
            "type":"Services"
        }
    ],
    "sg:phone":"+1 805 682 0005",
    "sg:postcode":"93101",
    "sg:province":"CA",
    "sg:tags":[
        "maker",
        "cabinet"
    ],
    "wof:name":"Charles Saenger Woodworking",
    "wof:placetype":"venue"
},
  "geometry": {"coordinates":[-119.68969199999999,34.41546],"type":"Point"}
}