{
  "type": "Feature",
  "properties": {
    "addr:full":"2840 Kenmore Pl Santa Barbara CA 93105",
    "addr:housenumber":"2840",
    "addr:postcode":"93105",
    "addr:street":"Kenmore Pl",
    "iso:country":"US",
    "sg:address":"2840 Kenmore Pl",
    "sg:city":"Santa Barbara",
    "sg:classifiers":[
        {
            "category":"Real Estate",
            "subcategory":"Real Estate Operator",
            "type":"Services"
        }
    ],
    "sg:phone":"+1 805 682 9588",
    "sg:postcode":"93105",
    "sg:province":"CA",
    "sg:tags":[
        "building",
        "nonresidential"
    ],
    "wof:name":"Renee Templeraud Commercial RE",
    "wof:placetype":"venue"
},
  "geometry": {"coordinates":[-119.718101,34.449498],"type":"Point"}
}