{
  "type": "Feature",
  "properties": {
    "addr:full":"555 S E St Santa Rosa CA 95404",
    "addr:housenumber":"555",
    "addr:postcode":"ca 95404",
    "addr:street":"S E St",
    "iso:country":"US",
    "sg:address":"555 S E St",
    "sg:city":"Santa Rosa",
    "sg:classifiers":[
        {
            "category":"Professional",
            "subcategory":"Credit Reporting & Collection",
            "type":"Services"
        }
    ],
    "sg:phone":"+1 707 528 6363",
    "sg:postcode":"95404",
    "sg:province":"CA",
    "sg:tags":[
        "agency"
    ],
    "wof:name":"Palmer Systems Inc",
    "wof:placetype":"venue"
},
  "geometry": {"coordinates":[-122.70458499999999,38.43362],"type":"Point"}
}