{
  "type": "Feature",
  "properties": {
    "iso:country":"US",
    "sg:address":"7 Barcelona",
    "sg:city":"Irvine",
    "sg:classifiers":[
        {
            "category":"Shopping",
            "subcategory":"Computers & Home Electronics",
            "type":"Retail Goods"
        }
    ],
    "sg:phone":"+1 949 261 7110",
    "sg:postcode":"92614",
    "sg:province":"CA",
    "sg:tags":[
        "equipment"
    ],
    "wof:name":"Information Exchange",
    "wof:placetype":"venue"
},
  "geometry": {"coordinates":[-117.819851,33.674364],"type":"Point"}
}