{
  "type": "Feature",
  "properties": {
    "addr:full":"12942 Harbor Blvd Garden Grove CA 92840",
    "addr:housenumber":"12942",
    "addr:postcode":"92840",
    "addr:street":"Harbor Blvd",
    "iso:country":"US",
    "sg:address":"12942 Harbor Blvd",
    "sg:city":"Garden Grove",
    "sg:classifiers":[
        {
            "category":"Shopping",
            "subcategory":"Computers & Home Electronics",
            "type":"Retail Goods"
        }
    ],
    "sg:phone":"+1 714 530 1678",
    "sg:postcode":"92840",
    "sg:province":"CA",
    "sg:website":"www.directv.com",
    "wof:name":"DIRECTV",
    "wof:placetype":"venue"
},
  "geometry": {"coordinates":[-117.918998,33.774912],"type":"Point"}
}