{
  "type": "Feature",
  "properties": {
    "addr:full":"10101 Systems Pkwy Sacramento CA 95827",
    "addr:housenumber":"10101",
    "addr:postcode":"95827",
    "addr:street":"Systems Pkwy",
    "iso:country":"US",
    "sg:address":"10101 Systems Pkwy",
    "sg:city":"Sacramento",
    "sg:classifiers":[
        {
            "category":"Education",
            "subcategory":"School",
            "type":"Public Place"
        }
    ],
    "sg:phone":"+1 916 228 5751",
    "sg:postcode":"95827",
    "sg:province":"CA",
    "wof:name":"Sacramento City Unified School District",
    "wof:placetype":"venue"
},
  "geometry": {"coordinates":[-121.31791699999999,38.564167],"type":"Point"}
}