{
  "type": "Feature",
  "properties": {
    "iso:country":"US",
    "sg:address":"906 Kensington Dr",
    "sg:city":"Redlands",
    "sg:classifiers":[
        {
            "category":"Professional",
            "type":"Services"
        }
    ],
    "sg:phone":"+1 909 794 5909",
    "sg:postcode":"92374",
    "sg:province":"CA",
    "sg:tags":[
        "religious"
    ],
    "wof:name":"Esa Indah Non Profit Organation",
    "wof:placetype":"venue"
},
  "geometry": {"coordinates":[-117.144812,34.063634],"type":"Point"}
}