{
  "type": "Feature",
  "properties": {
    "iso:country":"US",
    "sg:address":"4728 E 2nd St",
    "sg:city":"Benicia",
    "sg:classifiers":[
        {
            "category":"Personal",
            "subcategory":"Beauty Salon",
            "type":"Services"
        }
    ],
    "sg:phone":"+1 707 746 5002",
    "sg:postcode":"94510",
    "sg:province":"CA",
    "wof:name":"Hair Design By Rebecca",
    "wof:placetype":"venue"
},
  "geometry": {"coordinates":[-122.126889,38.080905],"type":"Point"}
}