{
  "type": "Feature",
  "properties": {
    "addr:full":"10350 Venice Boulevard Culver City CA 90232",
    "addr:housenumber":"10350",
    "addr:postcode":"90232",
    "addr:street":"Venice Boulevard",
    "iso:country":"US",
    "sg:address":"10350 Venice Boulevard",
    "sg:city":"Culver City",
    "sg:classifiers":[
        {
            "category":"Building & Trades",
            "subcategory":"Locksmith",
            "type":"Services"
        }
    ],
    "sg:phone":"+1 310 838 4860",
    "sg:postcode":"90232",
    "sg:province":"CA",
    "sg:tags":[
        "key"
    ],
    "wof:name":"A Locksmith Locks Etc",
    "wof:placetype":"venue"
},
  "geometry": {"coordinates":[-118.40349500000001,34.020712],"type":"Point"}
}