{
  "type": "Feature",
  "properties": {
    "addr:full":"13211 Vinter Way Poway CA 92064",
    "addr:housenumber":"13211",
    "addr:postcode":"ca 92064",
    "addr:street":"Vinter Way",
    "iso:country":"US",
    "sg:address":"13211 Vinter Way",
    "sg:city":"Poway",
    "sg:classifiers":[
        {
            "category":"Shopping",
            "type":"Retail Goods"
        }
    ],
    "sg:phone":"+1 858 451 3823",
    "sg:postcode":"92064",
    "sg:province":"CA",
    "sg:tags":[
        "merchandise"
    ],
    "wof:name":"Holy Land Products",
    "wof:placetype":"venue"
},
  "geometry": {"coordinates":[-117.042591,33.022615],"type":"Point"}
}