{
  "type": "Feature",
  "properties": {
    "addr:full":"1410 Ramona St Ramona CA 92065",
    "addr:housenumber":"1410",
    "addr:postcode":"92065",
    "addr:street":"Ramona St",
    "iso:country":"US",
    "sg:address":"1410 Ramona St",
    "sg:city":"Ramona",
    "sg:classifiers":[
        {
            "category":"Retail",
            "subcategory":"Animal Services",
            "type":"Services"
        }
    ],
    "sg:phone":"+1 760 789 0592",
    "sg:postcode":"92065",
    "sg:province":"CA",
    "sg:tags":[
        "cat",
        "dog",
        "kennel"
    ],
    "wof:name":"Buckwood Kennels",
    "wof:placetype":"venue"
},
  "geometry": {"coordinates":[-116.879436,33.015002],"type":"Point"}
}