{
  "type": "Feature",
  "properties": {
    "addr:full":"1462 S Canfield Ave Los Angeles CA 90035",
    "addr:housenumber":"1462",
    "addr:postcode":"90035",
    "addr:street":"S Canfield Ave",
    "iso:country":"US",
    "sg:address":"1462 S Canfield Ave",
    "sg:city":"Los Angeles",
    "sg:classifiers":[
        {
            "category":"Wholesale",
            "subcategory":"Durable Goods & Equipment",
            "type":"Manufacturing & Wholesale Goods"
        }
    ],
    "sg:phone":"+1 310 558 1667",
    "sg:postcode":"90035",
    "sg:province":"CA",
    "sg:tags":[
        "importer"
    ],
    "wof:name":"MCM Import",
    "wof:placetype":"venue"
},
  "geometry": {"coordinates":[-118.38938400000001,34.053299],"type":"Point"}
}