{
  "type": "Feature",
  "properties": {
    "iso:country":"US",
    "sg:address":"7099 Skyway",
    "sg:city":"Paradise",
    "sg:classifiers":[
        {
            "category":"Restaurant",
            "type":"Food & Drink"
        }
    ],
    "sg:phone":"+1 530 877 1255",
    "sg:postcode":"95969",
    "sg:province":"CA",
    "wof:name":"Kalico Kitchen Of Paradise",
    "wof:placetype":"venue"
},
  "geometry": {"coordinates":[-121.61715700000001,39.765598],"type":"Point"}
}