{
  "type": "Feature",
  "properties": {
    "iso:country":"US",
    "sg:address":"311 4th Ave",
    "sg:city":"San Francisco",
    "sg:classifiers":[
        {
            "category":"Personal",
            "subcategory":"Massage",
            "type":"Services"
        },
        {
            "category":"Personal",
            "subcategory":"Skin Care",
            "type":"Services"
        }
    ],
    "sg:phone":"+1 415 876 6372",
    "sg:postcode":"94118",
    "sg:province":"CA",
    "sg:website":"www.enchantingskincare.com",
    "wof:name":"The Enchanting Place",
    "wof:placetype":"venue"
},
  "geometry": {"coordinates":[-122.46257799999999,37.782613],"type":"Point"}
}