{
  "type": "Feature",
  "properties": {
    "iso:country":"US",
    "sg:address":"430 Evans Rd",
    "sg:city":"Milpitas",
    "sg:classifiers":[
        {
            "category":"Home & Garden",
            "subcategory":"Garden Supply",
            "type":"Retail Goods"
        },
        {
            "category":"Professional",
            "subcategory":"Credit Reporting & Collection",
            "type":"Services"
        }
    ],
    "sg:phone":"+1 408 262 8989",
    "sg:postcode":"95035",
    "sg:province":"CA",
    "sg:tags":[
        "plants",
        "leasing",
        "plants-interior",
        "living-renting",
        "design",
        "maintenance"
    ],
    "sg:website":"http://www.kimparkerplants.com",
    "wof:name":"Kim Parker Plants Inc.",
    "wof:placetype":"venue"
},
  "geometry": {"coordinates":[-121.87569999999999,37.443331],"type":"Point"}
}