{
  "type": "Feature",
  "properties": {
    "addr:full":"19918 Nancy Cir Cerritos CA 90703",
    "addr:housenumber":"19918",
    "addr:postcode":"ca 90703",
    "addr:street":"Nancy Cir",
    "iso:country":"US",
    "sg:address":"19918 Nancy Cir",
    "sg:city":"Cerritos",
    "sg:classifiers":[
        {
            "category":"Building & Trades",
            "subcategory":"Construction",
            "type":"Services"
        }
    ],
    "sg:phone":"+1 562 865 2796",
    "sg:postcode":"90703",
    "sg:province":"CA",
    "sg:tags":[
        "roofing",
        "contractor"
    ],
    "wof:name":"Walton Roofing",
    "wof:placetype":"venue"
},
  "geometry": {"coordinates":[-118.080994,33.849163],"type":"Point"}
}