{
  "type": "Feature",
  "properties": {
    "iso:country":"US",
    "sg:address":"4200 International Blvd",
    "sg:city":"Oakland",
    "sg:classifiers":[
        {
            "category":"Restaurant",
            "type":"Food & Drink"
        }
    ],
    "sg:phone":"+1 510 436 0280",
    "sg:postcode":"94601",
    "sg:province":"CA",
    "wof:name":"Burger King",
    "wof:placetype":"venue"
},
  "geometry": {"coordinates":[-122.216003,37.772999],"type":"Point"}
}