{
  "type": "Feature",
  "properties": {
    "iso:country":"US",
    "sg:address":"9343 Fostoria St",
    "sg:city":"Downey",
    "sg:classifiers":[
        {
            "category":"Building & Trades",
            "subcategory":"Construction",
            "type":"Services"
        }
    ],
    "sg:phone":"+1 562 861 9655",
    "sg:postcode":"90241",
    "sg:province":"CA",
    "sg:tags":[
        "designer",
        "dealer",
        "pool",
        "swimming"
    ],
    "wof:name":"Morales Pool Plastering Inc",
    "wof:placetype":"venue"
},
  "geometry": {"coordinates":[-118.114795,33.934398],"type":"Point"}
}