{
  "type": "Feature",
  "properties": {
    "iso:country":"US",
    "sg:address":"35201 Newark Blvd",
    "sg:city":"Newark",
    "sg:classifiers":[
        {
            "category":"Restaurant",
            "type":"Food & Drink"
        }
    ],
    "sg:phone":"+1 510 793 1616",
    "sg:postcode":"94560",
    "sg:province":"CA",
    "sg:tags":[
        "delicatessen"
    ],
    "wof:name":"Lido Hot Deli",
    "wof:placetype":"venue"
},
  "geometry": {"coordinates":[-122.046941,37.54931],"type":"Point"}
}