{
  "type": "Feature",
  "properties": {
    "addr:full":"600 Corporate Pointe Culver City CA 90230",
    "addr:housenumber":"600",
    "addr:postcode":"90230",
    "addr:street":"Corporate Pointe",
    "iso:country":"US",
    "sg:address":"600 Corporate Pointe",
    "sg:city":"Culver City",
    "sg:classifiers":[
        {
            "category":"Professional",
            "subcategory":"Accounting & Tax Preparation",
            "type":"Services"
        }
    ],
    "sg:phone":"+1 310 216 0066",
    "sg:postcode":"90230",
    "sg:province":"CA",
    "sg:tags":[
        "accountant"
    ],
    "sg:website":"www.pandacpas.com",
    "wof:name":"Pollack & Andreassen",
    "wof:placetype":"venue"
},
  "geometry": {"coordinates":[-118.384683,33.987749],"type":"Point"}
}