{
  "type": "Feature",
  "properties": {
    "addr:full":"449 Leavesley Rd Gilroy CA 95020",
    "addr:housenumber":"449",
    "addr:postcode":"95020",
    "addr:street":"Leavesley Rd",
    "iso:country":"US",
    "sg:address":"449 Leavesley Rd",
    "sg:city":"Gilroy",
    "sg:classifiers":[
        {
            "category":"Insurance",
            "subcategory":"Insurance Agent",
            "type":"Services"
        },
        {
            "category":"Insurance",
            "subcategory":"Hazard Insurance",
            "type":"Services"
        },
        {
            "category":"Insurance",
            "subcategory":"Title Insurance",
            "type":"Services"
        },
        {
            "category":"Insurance",
            "subcategory":"Life Insurance",
            "type":"Services"
        }
    ],
    "sg:phone":"+1 408 848 3800",
    "sg:postcode":"95020",
    "sg:province":"CA",
    "sg:tags":[
        "business",
        "auto",
        "commercial",
        "homeowner",
        "motorcycle",
        "renter"
    ],
    "wof:name":"Allstate Insurance Company - Mike Blake",
    "wof:placetype":"venue"
},
  "geometry": {"coordinates":[-121.569008,37.021572],"type":"Point"}
}