{
  "type": "Feature",
  "properties": {
    "addr:full":"22640 Garzota Dr Santa Clarita CA 91350",
    "addr:postcode":"22640;91350",
    "addr:street":"Garzota Dr",
    "iso:country":"US",
    "sg:address":"22640 Garzota Dr",
    "sg:city":"Santa Clarita",
    "sg:classifiers":[
        {
            "category":"Building & Trades",
            "subcategory":"Construction",
            "type":"Services"
        }
    ],
    "sg:phone":"+1 661 296 9008",
    "sg:postcode":"91350",
    "sg:province":"CA",
    "sg:tags":[
        "hanging",
        "contractor"
    ],
    "wof:name":"Ghc Painting",
    "wof:placetype":"venue"
},
  "geometry": {"coordinates":[-118.532551,34.43752],"type":"Point"}
}