{
  "type": "Feature",
  "properties": {
    "addr:full":"3627 Hayvenhurst Ave Encino CA 91436",
    "addr:housenumber":"3627",
    "addr:postcode":"91436",
    "addr:street":"Hayvenhurst Ave",
    "iso:country":"US",
    "sg:address":"3627 Hayvenhurst Ave",
    "sg:city":"Encino",
    "sg:classifiers":[
        {
            "category":"Professional",
            "type":"Services"
        }
    ],
    "sg:phone":"+1 818 907 0241",
    "sg:postcode":"91436",
    "sg:province":"CA",
    "wof:name":"Blinkyblinkybodylights Co",
    "wof:placetype":"venue"
},
  "geometry": {"coordinates":[-118.497028,34.137671],"type":"Point"}
}