{
  "type": "Feature",
  "properties": {
    "addr:full":"2335 American River Dr Sacramento CA 95825",
    "addr:housenumber":"2335",
    "addr:postcode":"95825",
    "addr:street":"American River Dr",
    "iso:country":"US",
    "sg:address":"2335 American River Dr",
    "sg:city":"Sacramento",
    "sg:classifiers":[
        {
            "category":"Banks & Credit Unions",
            "subcategory":"Financial Services",
            "type":"Services"
        }
    ],
    "sg:phone":"+1 916 920 1547",
    "sg:postcode":"95825",
    "sg:province":"CA",
    "sg:tags":[
        "broker",
        "mortgage"
    ],
    "wof:name":"Eagle Mortgage",
    "wof:placetype":"venue"
},
  "geometry": {"coordinates":[-121.408997,38.569599],"type":"Point"}
}