{
  "type": "Feature",
  "properties": {
    "iso:country":"US",
    "sg:address":"511 L St",
    "sg:city":"Davis",
    "sg:classifiers":[
        {
            "category":"Food & Beverages",
            "subcategory":"Liquor & Beverages",
            "type":"Retail Goods"
        }
    ],
    "sg:phone":"+1 530 753 4441",
    "sg:postcode":"95616",
    "sg:province":"CA",
    "wof:name":"Aggie Liquor & Deli",
    "wof:placetype":"venue"
},
  "geometry": {"coordinates":[-121.734775,38.550081],"type":"Point"}
}