{
  "type": "Feature",
  "properties": {
    "addr:full":"2485 Clay Street San Francisco CA 94115",
    "addr:housenumber":"2485",
    "addr:postcode":"94115",
    "addr:street":"Clay Street",
    "iso:country":"US",
    "sg:address":"2485 Clay Street",
    "sg:city":"San Francisco",
    "sg:classifiers":[
        {
            "category":"Health Services",
            "subcategory":"Doctor",
            "type":"Services"
        }
    ],
    "sg:phone":"+1 415 673 3505",
    "sg:postcode":"94115",
    "sg:province":"CA",
    "sg:tags":[
        "psychiatrist"
    ],
    "wof:name":"Karp Margaret M D",
    "wof:placetype":"venue"
},
  "geometry": {"coordinates":[-122.433998,37.790798],"type":"Point"}
}