{
  "type": "Feature",
  "properties": {
    "iso:country":"US",
    "sg:address":"15333 Wicks Blvd",
    "sg:city":"San Leandro",
    "sg:classifiers":[
        {
            "category":"Real Estate",
            "subcategory":"Real Estate Services",
            "type":"Services"
        }
    ],
    "sg:postcode":"94579",
    "sg:province":"CA",
    "wof:name":"Mission Bay Mobile Home Park",
    "wof:placetype":"venue"
},
  "geometry": {"coordinates":[-122.159677,37.682571],"type":"Point"}
}