{
  "type": "Feature",
  "properties": {
    "addr:full":"5900 Brockton Ave Riverside CA 92506",
    "addr:housenumber":"5900",
    "addr:postcode":"92506",
    "addr:street":"Brockton Ave",
    "iso:country":"US",
    "sg:address":"5900 Brockton Ave",
    "sg:city":"Riverside",
    "sg:classifiers":[
        {
            "category":"Health Services",
            "subcategory":"Hospital",
            "type":"Services"
        }
    ],
    "sg:phone":"+1 951 788 3500",
    "sg:postcode":"92506",
    "sg:province":"CA",
    "wof:name":"Riverside Community Hospital",
    "wof:placetype":"venue"
},
  "geometry": {"coordinates":[-117.395348,33.963139],"type":"Point"}
}