{
  "type": "Feature",
  "properties": {
    "iso:country":"US",
    "sg:address":"5430 Alvern Cir",
    "sg:city":"Los Angeles",
    "sg:classifiers":[
        {
            "category":"Real Estate",
            "subcategory":"Real Estate Operator",
            "type":"Services"
        }
    ],
    "sg:phone":"+1 310 337 7335",
    "sg:postcode":"90045",
    "sg:province":"CA",
    "sg:tags":[
        "apartment"
    ],
    "wof:name":"Alvern Circle Apartments",
    "wof:placetype":"venue"
},
  "geometry": {"coordinates":[-118.37508800000001,33.975791],"type":"Point"}
}