{
  "type": "Feature",
  "properties": {
    "iso:country":"US",
    "sg:address":"2290 Pacific Ave",
    "sg:city":"Long Beach",
    "sg:classifiers":[
        {
            "category":"Education",
            "subcategory":"School",
            "type":"Public Place"
        }
    ],
    "sg:phone":"+1 562 595 9100",
    "sg:postcode":"90806",
    "sg:province":"CA",
    "sg:tags":[
        "high",
        "middle",
        "elementary"
    ],
    "wof:name":"Soledad Enrichment Action",
    "wof:placetype":"venue"
},
  "geometry": {"coordinates":[-118.194,33.798801],"type":"Point"}
}