{
  "type": "Feature",
  "properties": {
    "iso:country":"US",
    "sg:address":"2746 Reservoir Canyon Rd",
    "sg:city":"San Luis Obispo",
    "sg:classifiers":[
        {
            "category":"Professional",
            "type":"Services"
        }
    ],
    "sg:phone":"+1 805 544 2746",
    "sg:postcode":"93401",
    "sg:province":"CA",
    "sg:tags":[
        "establishment"
    ],
    "wof:name":"Obispo Mansion",
    "wof:placetype":"venue"
},
  "geometry": {"coordinates":[-120.629953,35.294961],"type":"Point"}
}