{
  "type": "Feature",
  "properties": {
    "iso:country":"US",
    "sg:address":"4 The Crossroads",
    "sg:city":"Carmel",
    "sg:classifiers":[
        {
            "category":"Building & Trades",
            "subcategory":"Construction",
            "type":"Services"
        }
    ],
    "sg:phone":"+1 831 626 8665",
    "sg:postcode":"93923",
    "sg:province":"CA",
    "sg:tags":[
        "contractor"
    ],
    "wof:name":"McFall Wm Associates Inc",
    "wof:placetype":"venue"
},
  "geometry": {"coordinates":[-121.908997,36.538502],"type":"Point"}
}