{
  "type": "Feature",
  "properties": {
    "addr:full":"334 S D St Perris CA 92570",
    "addr:housenumber":"334",
    "addr:postcode":"92570",
    "addr:street":"S D St",
    "iso:country":"US",
    "sg:address":"334 S D St",
    "sg:city":"Perris",
    "sg:classifiers":[
        {
            "category":"Banks & Credit Unions",
            "subcategory":"Bank",
            "type":"Services"
        }
    ],
    "sg:phone":"+1 951 943 9538",
    "sg:postcode":"92570",
    "sg:province":"CA",
    "sg:tags":[
        "money",
        "transfer"
    ],
    "wof:name":"Salon Envios",
    "wof:placetype":"venue"
},
  "geometry": {"coordinates":[-117.22847899999999,33.784101],"type":"Point"}
}