{
  "type": "Feature",
  "properties": {
    "addr:full":"793 Gravenstein Ave Sebastopol CA 95472",
    "addr:housenumber":"793",
    "addr:postcode":"95472",
    "addr:street":"Gravenstein Ave",
    "iso:country":"US",
    "sg:address":"793 Gravenstein Ave",
    "sg:city":"Sebastopol",
    "sg:classifiers":[
        {
            "category":"Personal",
            "subcategory":"Beauty Salon",
            "type":"Services"
        }
    ],
    "sg:phone":"+1 707 823 6277",
    "sg:postcode":"95472",
    "sg:province":"CA",
    "wof:name":"California Cuts",
    "wof:placetype":"venue"
},
  "geometry": {"coordinates":[-122.818787,38.394431],"type":"Point"}
}