{
  "type": "Feature",
  "properties": {
    "iso:country":"US",
    "sg:address":"4000 Fruitvale Ave",
    "sg:city":"Bakersfield",
    "sg:classifiers":[
        {
            "category":"Retail",
            "subcategory":"Auto Rental",
            "type":"Services"
        }
    ],
    "sg:phone":"+1 661 325 5516",
    "sg:postcode":"93308",
    "sg:province":"CA",
    "sg:tags":[
        "renting",
        "automobile"
    ],
    "wof:name":"Rent-A-Wreck",
    "wof:placetype":"venue"
},
  "geometry": {"coordinates":[-119.074257,35.396981],"type":"Point"}
}