{
  "type": "Feature",
  "properties": {
    "iso:country":"US",
    "sg:address":"2500 W Lincoln Ave Ste 3",
    "sg:city":"Anaheim",
    "sg:classifiers":[
        {
            "category":"Health Services",
            "subcategory":"Chiropractor",
            "type":"Services"
        }
    ],
    "sg:phone":"+1 714 828 9235",
    "sg:postcode":"92801",
    "sg:province":"CA",
    "wof:name":"Anaheim Medical Corp",
    "wof:placetype":"venue"
},
  "geometry": {"coordinates":[-117.97230500000001,33.832083],"type":"Point"}
}