{
  "type": "Feature",
  "properties": {
    "iso:country":"US",
    "sg:address":"1830 E M St",
    "sg:city":"Wilmington",
    "sg:classifiers":[
        {
            "category":"Manufacturing",
            "subcategory":"Metals",
            "type":"Manufacturing & Wholesale Goods"
        }
    ],
    "sg:phone":"+1 310 834 7159",
    "sg:postcode":"90744",
    "sg:province":"CA",
    "sg:tags":[
        "ornamental",
        "work"
    ],
    "wof:name":"Huerta's Shop",
    "wof:placetype":"venue"
},
  "geometry": {"coordinates":[-118.240272,33.789516],"type":"Point"}
}