{
  "type": "Feature",
  "properties": {
    "iso:country":"US",
    "sg:address":"171 El Toyonal",
    "sg:city":"Orinda",
    "sg:classifiers":[
        {
            "category":"Professional",
            "subcategory":"Testing Lab",
            "type":"Services"
        }
    ],
    "sg:phone":"+1 925 254 7717",
    "sg:postcode":"94563",
    "sg:province":"CA",
    "sg:tags":[
        "biological",
        "laboratory"
    ],
    "wof:name":"Camatex/Basic Chemistry",
    "wof:placetype":"venue"
},
  "geometry": {"coordinates":[-122.20134,37.883942],"type":"Point"}
}