{
  "type": "Feature",
  "properties": {
    "addr:full":"277 S Euclid Ave Pasadena CA 91101",
    "addr:housenumber":"277",
    "addr:postcode":"91101",
    "addr:street":"S Euclid Ave",
    "iso:country":"US",
    "sg:address":"277 S Euclid Ave",
    "sg:city":"Pasadena",
    "sg:classifiers":[
        {
            "category":"Health Services",
            "subcategory":"Dentist",
            "type":"Services"
        }
    ],
    "sg:phone":"+1 626 793 4185",
    "sg:postcode":"91101",
    "sg:province":"CA",
    "sg:website":"www.pasadenacosmeticdentist.com",
    "wof:name":"Robert Shimasaki, DDS",
    "wof:placetype":"venue"
},
  "geometry": {"coordinates":[-118.142872,34.140935],"type":"Point"}
}