{
  "type": "Feature",
  "properties": {
    "iso:country":"US",
    "sg:address":"10150 Coloma Rd",
    "sg:city":"Rancho Cordova",
    "sg:classifiers":[
        {
            "category":"Building & Trades",
            "subcategory":"Construction",
            "type":"Services"
        }
    ],
    "sg:phone":"+1 916 363 6315",
    "sg:postcode":"95670",
    "sg:province":"CA",
    "sg:tags":[
        "contractor"
    ],
    "wof:name":"3-D Svc Inc",
    "wof:placetype":"venue"
},
  "geometry": {"coordinates":[-121.303337,38.590125],"type":"Point"}
}