{
  "type": "Feature",
  "properties": {
    "addr:full":"3822 Keefer Rd Chico CA 95973",
    "addr:housenumber":"3822",
    "addr:postcode":"95973",
    "addr:street":"Keefer Rd",
    "iso:country":"US",
    "sg:address":"3822 Keefer Rd",
    "sg:city":"Chico",
    "sg:classifiers":[
        {
            "category":"Utilities",
            "type":"Services"
        }
    ],
    "sg:phone":"+1 530 899 1195",
    "sg:postcode":"95973",
    "sg:province":"CA",
    "sg:tags":[
        "sweeping"
    ],
    "wof:name":"Chico Power Sweeping Svc",
    "wof:placetype":"venue"
},
  "geometry": {"coordinates":[-121.879519,39.818528],"type":"Point"}
}