{
  "type": "Feature",
  "properties": {
    "addr:full":"743 N Olive St Anaheim CA 92805",
    "addr:housenumber":"743",
    "addr:postcode":"92805",
    "addr:street":"N Olive St",
    "iso:country":"US",
    "sg:address":"743 N Olive St",
    "sg:city":"Anaheim",
    "sg:classifiers":[
        {
            "category":"Food & Beverages",
            "subcategory":"Groceries & Convenience Stores",
            "type":"Retail Goods"
        }
    ],
    "sg:phone":"+1 714 772 6317",
    "sg:postcode":"92805",
    "sg:province":"CA",
    "sg:tags":[
        "grocer"
    ],
    "wof:name":"Barajas Grocery",
    "wof:placetype":"venue"
},
  "geometry": {"coordinates":[-117.91300200000001,33.844398],"type":"Point"}
}