{
  "type": "Feature",
  "properties": {
    "iso:country":"US",
    "sg:address":"541 Main St",
    "sg:city":"Pleasanton",
    "sg:classifiers":[
        {
            "category":"Personal",
            "subcategory":"Beauty Salon",
            "type":"Services"
        }
    ],
    "sg:phone":"+1 925 846 5642",
    "sg:postcode":"94566",
    "sg:province":"CA",
    "wof:name":"Beauty Nook",
    "wof:placetype":"venue"
},
  "geometry": {"coordinates":[-121.87565,37.661033],"type":"Point"}
}