{
  "type": "Feature",
  "properties": {
    "addr:full":"3506 E Mariposa Rd Stockton CA 95205",
    "addr:housenumber":"3506",
    "addr:postcode":"95205",
    "addr:street":"E Mariposa Rd",
    "iso:country":"US",
    "sg:address":"3506 E Mariposa Rd",
    "sg:city":"Stockton",
    "sg:classifiers":[
        {
            "category":"Manufacturing",
            "subcategory":"Metals",
            "type":"Manufacturing & Wholesale Goods"
        }
    ],
    "sg:phone":"+1 209 941 2276",
    "sg:postcode":"95205",
    "sg:province":"CA",
    "sg:tags":[
        "building"
    ],
    "wof:name":"M D Barns",
    "wof:placetype":"venue"
},
  "geometry": {"coordinates":[-121.231436,37.932931],"type":"Point"}
}