{
  "type": "Feature",
  "properties": {
    "iso:country":"US",
    "sg:address":"2100 E Howell Ave #206",
    "sg:city":"Anaheim",
    "sg:classifiers":[
        {
            "category":"Professional",
            "subcategory":"Computer Services",
            "type":"Services"
        },
        {
            "category":"Manufacturing",
            "subcategory":"Electronics",
            "type":"Manufacturing & Wholesale Goods"
        },
        {
            "category":"Wholesale",
            "subcategory":"Computers",
            "type":"Manufacturing & Wholesale Goods"
        }
    ],
    "sg:phone":"+1 800 487 1486",
    "sg:postcode":"92806",
    "sg:province":"CA",
    "sg:tags":[
        "equipment",
        "cd-rom",
        "printers-equipment",
        "supply"
    ],
    "sg:website":"http://www.MesaLaser.com",
    "wof:name":"Mesa Laser",
    "wof:placetype":"venue"
},
  "geometry": {"coordinates":[-117.88723,33.806979],"type":"Point"}
}