{
  "type": "Feature",
  "properties": {
    "iso:country":"US",
    "sg:address":"2206 Gateway Oaks Dr",
    "sg:city":"Sacramento",
    "sg:classifiers":[
        {
            "category":"Utilities",
            "subcategory":"Fuel Oil & Lpg",
            "type":"Services"
        }
    ],
    "sg:phone":"+1 209 261 4490",
    "sg:postcode":"95833",
    "sg:province":"CA",
    "sg:tags":[
        "bulk",
        "petroleum-bottled",
        "gas-liquefied"
    ],
    "wof:name":"Kieran S Cullen Petroleum",
    "wof:placetype":"venue"
},
  "geometry": {"coordinates":[-121.513384,38.605369],"type":"Point"}
}