{
  "type": "Feature",
  "properties": {
    "addr:full":"1323 Mokelumne Dr Antioch CA 94531",
    "addr:housenumber":"1323",
    "addr:postcode":"ca 94531",
    "addr:street":"Mokelumne Dr",
    "iso:country":"US",
    "sg:address":"1323 Mokelumne Dr",
    "sg:city":"Antioch",
    "sg:classifiers":[
        {
            "category":"Professional",
            "subcategory":"Engineering",
            "type":"Services"
        }
    ],
    "sg:phone":"+1 510 914 1805",
    "sg:postcode":"94531",
    "sg:province":"CA",
    "sg:tags":[
        "engineer"
    ],
    "wof:name":"Markham & Co",
    "wof:placetype":"venue"
},
  "geometry": {"coordinates":[-121.79982099999999,37.956992],"type":"Point"}
}