{
  "type": "Feature",
  "properties": {
    "addr:full":"3554 Bus Park Dr Costa Mesa CA 92626",
    "addr:housenumber":"3554",
    "addr:postcode":"92626",
    "addr:street":"Bus Park Dr",
    "iso:country":"US",
    "sg:address":"3554 Bus Park Dr",
    "sg:city":"Costa Mesa",
    "sg:classifiers":[
        {
            "category":"Shopping",
            "subcategory":"Gifts & Souvenirs",
            "type":"Retail Goods"
        }
    ],
    "sg:phone":"+1 714 444 3871",
    "sg:postcode":"92626",
    "sg:province":"CA",
    "wof:name":"Creative Baskets",
    "wof:placetype":"venue"
},
  "geometry": {"coordinates":[-117.923835,33.698691],"type":"Point"}
}