{
  "type": "Feature",
  "properties": {
    "addr:full":"1504 W El Camino Ave Sacramento CA 95833",
    "addr:housenumber":"1504",
    "addr:postcode":"95833",
    "addr:street":"W El Camino Ave",
    "iso:country":"US",
    "sg:address":"1504 W El Camino Ave",
    "sg:city":"Sacramento",
    "sg:classifiers":[
        {
            "category":"Personal",
            "subcategory":"Beauty Salon",
            "type":"Services"
        },
        {
            "category":"Personal",
            "subcategory":"Hair Removal",
            "type":"Services"
        },
        {
            "category":"Personal",
            "subcategory":"Nail Salon",
            "type":"Services"
        }
    ],
    "sg:phone":"+1 916 924 3916",
    "sg:postcode":"95833",
    "sg:province":"CA",
    "wof:name":"Kimberly's Hair & Nails",
    "wof:placetype":"venue"
},
  "geometry": {"coordinates":[-121.49415999999999,38.612893],"type":"Point"}
}