{
  "type": "Feature",
  "properties": {
    "addr:full":"1199 Fairway Dr Walnut CA 91789",
    "addr:housenumber":"1199",
    "addr:postcode":"91789",
    "addr:street":"Fairway Dr",
    "iso:country":"US",
    "sg:address":"1199 Fairway Dr",
    "sg:city":"Walnut",
    "sg:classifiers":[
        {
            "category":"Food & Beverages",
            "subcategory":"Specialty",
            "type":"Retail Goods"
        }
    ],
    "sg:phone":"+1 626 333 9998",
    "sg:postcode":"91789",
    "sg:province":"CA",
    "sg:tags":[
        "herb"
    ],
    "sg:website":"www.hsusa.net",
    "wof:name":"Herbal Science Intl Inc",
    "wof:placetype":"venue"
},
  "geometry": {"coordinates":[-117.86973399999999,33.994425],"type":"Point"}
}