{
  "type": "Feature",
  "properties": {
    "iso:country":"US",
    "sg:address":"967 S Coast Highway 101",
    "sg:city":"Encinitas",
    "sg:classifiers":[
        {
            "category":"Restaurant",
            "type":"Food & Drink"
        }
    ],
    "sg:phone":"+1 760 632 1901",
    "sg:postcode":"92024",
    "sg:province":"CA",
    "wof:name":"Pino's Cucina Italiana",
    "wof:placetype":"venue"
},
  "geometry": {"coordinates":[-117.29299899999999,33.040001],"type":"Point"}
}