{
  "type": "Feature",
  "properties": {
    "iso:country":"US",
    "sg:address":"1919 S Pacific Ave",
    "sg:city":"San Pedro",
    "sg:classifiers":[
        {
            "category":"Health Services",
            "subcategory":"Doctor",
            "type":"Services"
        }
    ],
    "sg:phone":"+1 310 514 1000",
    "sg:postcode":"90731",
    "sg:province":"CA",
    "sg:tags":[
        "dentist"
    ],
    "wof:name":"Marina Dental Svc",
    "wof:placetype":"venue"
},
  "geometry": {"coordinates":[-118.288033,33.727813],"type":"Point"}
}