{
  "type": "Feature",
  "properties": {
    "iso:country":"US",
    "sg:address":"10933 Cotter St",
    "sg:city":"Oakland",
    "sg:classifiers":[
        {
            "category":"Professional",
            "subcategory":"Management & Consulting",
            "type":"Services"
        }
    ],
    "sg:phone":"+1 510 632 9175",
    "sg:postcode":"94605",
    "sg:province":"CA",
    "sg:tags":[
        "town",
        "city",
        "regional",
        "planner"
    ],
    "wof:name":"Gabriel-Roche",
    "wof:placetype":"venue"
},
  "geometry": {"coordinates":[-122.122113,37.753458],"type":"Point"}
}