{
  "type": "Feature",
  "properties": {
    "iso:country":"US",
    "sg:address":"14799 Washington Ave Ste C",
    "sg:city":"San Leandro",
    "sg:classifiers":[
        {
            "category":"Donuts",
            "subcategory":"None",
            "type":"Food & Drink"
        }
    ],
    "sg:phone":"+1 510 352 1959",
    "sg:postcode":"94578",
    "sg:province":"CA",
    "wof:name":"Donut Design",
    "wof:placetype":"venue"
},
  "geometry": {"coordinates":[-122.139,37.6959],"type":"Point"}
}