{
  "type": "Feature",
  "properties": {
    "addr:full":"9306 Summertime Ln Culver City CA 90230",
    "addr:housenumber":"9306",
    "addr:postcode":"90230",
    "addr:street":"Summertime Ln",
    "iso:country":"US",
    "sg:address":"9306 Summertime Ln",
    "sg:city":"Culver City",
    "sg:classifiers":[
        {
            "category":"Real Estate",
            "subcategory":"Real Estate Agent",
            "type":"Services"
        }
    ],
    "sg:phone":"+1 310 202 6411",
    "sg:postcode":"90230",
    "sg:province":"CA",
    "wof:name":"Milan Management",
    "wof:placetype":"venue"
},
  "geometry": {"coordinates":[-118.389989,34.003953],"type":"Point"}
}