{
  "type": "Feature",
  "properties": {
    "addr:full":"2957 Harbor Blvd Costa Mesa CA 92626",
    "addr:housenumber":"2957",
    "addr:postcode":"92626",
    "addr:street":"Harbor Blvd Costa",
    "iso:country":"US",
    "sg:address":"2957 Harbor Blvd",
    "sg:city":"Costa Mesa",
    "sg:classifiers":[
        {
            "category":"Travel",
            "subcategory":"Travel Agent",
            "type":"Entertainment"
        }
    ],
    "sg:phone":"+1 866 884 4223",
    "sg:postcode":"92626",
    "sg:province":"CA",
    "sg:website":"www.iace-usa.com/us/index.php",
    "wof:name":"Iace Travel",
    "wof:placetype":"venue"
},
  "geometry": {"coordinates":[-117.919438,33.679133],"type":"Point"}
}