{
  "type": "Feature",
  "properties": {
    "addr:full":"45 S 1st Street Campbell CA 95008",
    "addr:housenumber":"45",
    "addr:postcode":"95008",
    "addr:street":"S 1St Street",
    "iso:country":"US",
    "sg:address":"45 S 1st Street",
    "sg:city":"Campbell",
    "sg:classifiers":[
        {
            "category":"Building & Trades",
            "subcategory":"Construction",
            "type":"Services"
        }
    ],
    "sg:phone":"+1 408 866 4898",
    "sg:postcode":"95008",
    "sg:province":"CA",
    "sg:tags":[
        "contractor"
    ],
    "wof:name":"Miracle Method Surface Restoration",
    "wof:placetype":"venue"
},
  "geometry": {"coordinates":[-121.945052,37.286486],"type":"Point"}
}