{
  "type": "Feature",
  "properties": {
    "addr:full":"5233 Champlain St Oceanside CA 92056",
    "addr:housenumber":"5233",
    "addr:postcode":"92056",
    "addr:street":"Champlain St",
    "iso:country":"US",
    "sg:address":"5233 Champlain St",
    "sg:city":"Oceanside",
    "sg:classifiers":[
        {
            "category":"Wholesale",
            "subcategory":"Computers",
            "type":"Manufacturing & Wholesale Goods"
        }
    ],
    "sg:phone":"+1 310 862 4486",
    "sg:postcode":"92056",
    "sg:province":"CA",
    "sg:tags":[
        "equipment"
    ],
    "wof:name":"Rose Pc",
    "wof:placetype":"venue"
},
  "geometry": {"coordinates":[-117.269183,33.236129],"type":"Point"}
}