{
  "type": "Feature",
  "properties": {
    "addr:full":"30 Robak Drive Watsonville CA 95076",
    "addr:housenumber":"30",
    "addr:postcode":"95076",
    "addr:street":"Robak Drive",
    "iso:country":"US",
    "sg:address":"30 Robak Drive",
    "sg:city":"Watsonville",
    "sg:classifiers":[
        {
            "category":"Professional",
            "subcategory":"Accounting & Tax Preparation",
            "type":"Services"
        }
    ],
    "sg:phone":"+1 831 684 1044",
    "sg:postcode":"95076",
    "sg:province":"CA",
    "sg:tags":[
        "accountant"
    ],
    "wof:name":"Cooper Nancy G CPA",
    "wof:placetype":"venue"
},
  "geometry": {"coordinates":[-121.852653,36.948487],"type":"Point"}
}