{
  "type": "Feature",
  "properties": {
    "addr:full":"2085 E 3rd St Long Beach CA 90814",
    "addr:housenumber":"2085",
    "addr:postcode":"90814",
    "addr:street":"E 3Rd St",
    "iso:country":"US",
    "sg:address":"2085 E 3rd St",
    "sg:city":"Long Beach",
    "sg:classifiers":[
        {
            "category":"Social Services",
            "subcategory":"Job Training",
            "type":"Services"
        }
    ],
    "sg:phone":"+1 562 438 9781",
    "sg:postcode":"90814",
    "sg:province":"CA",
    "sg:tags":[
        "rehabilitation"
    ],
    "wof:name":"Transitional Rehab Svc",
    "wof:placetype":"venue"
},
  "geometry": {"coordinates":[-118.165796,33.768769],"type":"Point"}
}