{
  "type": "Feature",
  "properties": {
    "addr:full":"9570 Kruse Rd Pico Rivera CA 90660",
    "addr:housenumber":"9570",
    "addr:postcode":"90660",
    "addr:street":"Kruse Rd",
    "iso:country":"US",
    "sg:address":"9570 Kruse Rd",
    "sg:city":"Pico Rivera",
    "sg:classifiers":[
        {
            "category":"Shopping",
            "subcategory":"Pets & Pet Supplies",
            "type":"Retail Goods"
        }
    ],
    "sg:phone":"+1 562 695 1020",
    "sg:postcode":"90660",
    "sg:province":"CA",
    "sg:tags":[
        "store"
    ],
    "wof:name":"International Pet",
    "wof:placetype":"venue"
},
  "geometry": {"coordinates":[-118.06300400000001,34.0196],"type":"Point"}
}