{
  "type": "Feature",
  "properties": {
    "iso:country":"US",
    "sg:address":"1524 Hill Rd",
    "sg:city":"Novato",
    "sg:classifiers":[
        {
            "category":"Retail",
            "subcategory":"Animal Services",
            "type":"Services"
        }
    ],
    "sg:phone":"+1 415 246 4717",
    "sg:postcode":"94947",
    "sg:province":"CA",
    "sg:tags":[
        "pet",
        "boarding",
        "sitting"
    ],
    "wof:name":"Pro Care Pet Sitting",
    "wof:placetype":"venue"
},
  "geometry": {"coordinates":[-122.573324,38.095486],"type":"Point"}
}