{
  "type": "Feature",
  "properties": {
    "addr:full":"136 9th Ave City Of Industry CA 91746",
    "addr:housenumber":"136",
    "addr:postcode":"91746",
    "addr:street":"9Th Ave",
    "iso:country":"US",
    "sg:address":"136 9th Ave",
    "sg:city":"City Of Industry",
    "sg:classifiers":[
        {
            "category":"Local Transit",
            "type":"Transportation"
        }
    ],
    "sg:phone":"+1 626 330 4966",
    "sg:postcode":"91746",
    "sg:province":"CA",
    "sg:tags":[
        "limousine"
    ],
    "wof:name":"Limo World Transportation",
    "wof:placetype":"venue"
},
  "geometry": {"coordinates":[-117.96792000000001,34.029804],"type":"Point"}
}