{
  "type": "Feature",
  "properties": {
    "addr:full":"4888 Ronson Ct Ste N San Diego CA 92111",
    "addr:housenumber":"4888",
    "addr:postcode":"92111",
    "addr:street":"Ronson Ct Ste N",
    "iso:country":"US",
    "sg:address":"4888 Ronson Ct Ste N",
    "sg:city":"San Diego",
    "sg:classifiers":[
        {
            "category":"Shopping",
            "subcategory":"Crafts & Fabrics",
            "type":"Retail Goods"
        }
    ],
    "sg:phone":"+1 858 569 9663",
    "sg:postcode":"92111",
    "sg:province":"CA",
    "sg:tags":[
        "art"
    ],
    "wof:name":"Infinity Limited",
    "wof:placetype":"venue"
},
  "geometry": {"coordinates":[-117.145895,32.831222],"type":"Point"}
}