{
  "type": "Feature",
  "properties": {
    "iso:country":"US",
    "sg:address":"420 W Pine St",
    "sg:city":"Lodi",
    "sg:classifiers":[
        {
            "category":"Organizations",
            "subcategory":"Professional Association",
            "type":"Services"
        }
    ],
    "sg:phone":"+1 209 334 6956",
    "sg:postcode":"95240",
    "sg:province":"CA",
    "sg:tags":[
        "lumber"
    ],
    "wof:name":"Calif Lumber Inspection Svc",
    "wof:placetype":"venue"
},
  "geometry": {"coordinates":[-121.278845,38.13434],"type":"Point"}
}