{
  "type": "Feature",
  "properties": {
    "addr:full":"2886 Bay Rd Redwood City CA 94063",
    "addr:housenumber":"2886",
    "addr:postcode":"94063",
    "addr:street":"Bay Rd",
    "iso:country":"US",
    "sg:address":"2886 Bay Rd",
    "sg:city":"Redwood City",
    "sg:classifiers":[
        {
            "category":"Manufacturing",
            "subcategory":"Metals",
            "type":"Manufacturing & Wholesale Goods"
        }
    ],
    "sg:phone":"+1 650 368 1551",
    "sg:postcode":"94063",
    "sg:province":"CA",
    "sg:tags":[
        "metalwork",
        "foundry",
        "iron",
        "architectural",
        "mfg"
    ],
    "wof:name":"Custom Iron & Casting Works",
    "wof:placetype":"venue"
},
  "geometry": {"coordinates":[-122.204622,37.483424],"type":"Point"}
}