{
  "type": "Feature",
  "properties": {
    "iso:country":"US",
    "sg:address":"2610 Telephone Rd",
    "sg:city":"Santa Maria",
    "sg:classifiers":[
        {
            "category":"Food & Beverages",
            "subcategory":"Fruits & Vegetables",
            "type":"Retail Goods"
        }
    ],
    "sg:phone":"+1 805 349 9408",
    "sg:postcode":"93454",
    "sg:province":"CA",
    "sg:tags":[
        "produce"
    ],
    "wof:name":"LVL Produce Co Inc",
    "wof:placetype":"venue"
},
  "geometry": {"coordinates":[-120.383118,34.878847],"type":"Point"}
}