{
  "type": "Feature",
  "properties": {
    "iso:country":"US",
    "sg:address":"136 S Linden Ave",
    "sg:city":"S San Francisco",
    "sg:classifiers":[
        {
            "category":"Retail",
            "subcategory":"Auto Repair",
            "type":"Services"
        }
    ],
    "sg:phone":"+1 650 583 8093",
    "sg:postcode":"94080",
    "sg:province":"CA",
    "sg:tags":[
        "body",
        "automobile",
        "painting"
    ],
    "wof:name":"Kemet Auto Works",
    "wof:placetype":"venue"
},
  "geometry": {"coordinates":[-122.414187,37.643879],"type":"Point"}
}