{
  "type": "Feature",
  "properties": {
    "iso:country":"US",
    "sg:address":"458 W Arrow Hwy",
    "sg:city":"San Dimas",
    "sg:classifiers":[
        {
            "category":"Real Estate",
            "subcategory":"Real Estate Agent",
            "type":"Services"
        }
    ],
    "sg:phone":"+1 909 394 0111",
    "sg:postcode":"91773",
    "sg:province":"CA",
    "wof:name":"San Dimas Commerce Center",
    "wof:placetype":"venue"
},
  "geometry": {"coordinates":[-117.814269,34.102848],"type":"Point"}
}