{
  "type": "Feature",
  "properties": {
    "iso:country":"US",
    "sg:address":"14365 Rough and Ready Hwy",
    "sg:city":"Rough And Ready",
    "sg:classifiers":[
        {
            "category":"Shopping",
            "subcategory":"Used Merchandise",
            "type":"Retail Goods"
        }
    ],
    "sg:phone":"+1 530 273 8742",
    "sg:postcode":"95975",
    "sg:province":"CA",
    "sg:tags":[
        "antique"
    ],
    "wof:name":"Toll House Antiques",
    "wof:placetype":"venue"
},
  "geometry": {"coordinates":[-121.13133999999999,39.231111],"type":"Point"}
}