{
  "type": "Feature",
  "properties": {
    "iso:country":"US",
    "sg:address":"65 E Daily Dr",
    "sg:city":"Camarillo",
    "sg:classifiers":[
        {
            "category":"Restaurant",
            "type":"Food & Drink"
        }
    ],
    "sg:phone":"+1 805 388 1138",
    "sg:postcode":"93010",
    "sg:province":"CA",
    "sg:tags":[
        "thai"
    ],
    "sg:website":"www.charn-thai.com/",
    "wof:name":"Charn Thai Restaurant",
    "wof:placetype":"venue"
},
  "geometry": {"coordinates":[-119.069,34.222],"type":"Point"}
}