{
  "type": "Feature",
  "properties": {
    "addr:full":"8201 E Santa Ana Canyon Rd Anaheim CA 92808",
    "addr:housenumber":"8201",
    "addr:postcode":"92808",
    "addr:street":"E Santa Ana Canyon Rd",
    "iso:country":"US",
    "sg:address":"8201 E Santa Ana Canyon Rd",
    "sg:city":"Anaheim",
    "sg:classifiers":[
        {
            "category":"Place Of Worship",
            "subcategory":"Church",
            "type":"Public Place"
        }
    ],
    "sg:phone":"+1 714 797 0454",
    "sg:postcode":"92808",
    "sg:province":"CA",
    "sg:tags":[
        "churches-calvary",
        "chapel"
    ],
    "wof:name":"Calvary Chapel Of Anaheim Hills",
    "wof:placetype":"venue"
},
  "geometry": {"coordinates":[-117.746143,33.867436],"type":"Point"}
}