{
  "type": "Feature",
  "properties": {
    "addr:full":"520 Mendocino Ave Santa Rosa CA 95401",
    "addr:housenumber":"520",
    "addr:postcode":"95401",
    "addr:street":"Mendocino Ave",
    "iso:country":"US",
    "sg:address":"520 Mendocino Ave",
    "sg:city":"Santa Rosa",
    "sg:classifiers":[
        {
            "category":"Building & Trades",
            "subcategory":"Construction",
            "type":"Services"
        }
    ],
    "sg:phone":"+1 707 568 1226",
    "sg:postcode":"95401",
    "sg:province":"CA",
    "sg:tags":[
        "elevator"
    ],
    "wof:name":"Otis Elevator Co",
    "wof:placetype":"venue"
},
  "geometry": {"coordinates":[-122.715932,38.443206],"type":"Point"}
}