{
  "type": "Feature",
  "properties": {
    "addr:full":"135 E Santa Clara St Arcadia CA 91006",
    "addr:housenumber":"135",
    "addr:postcode":"91006",
    "addr:street":"E Santa Clara St",
    "iso:country":"US",
    "sg:address":"135 E Santa Clara St",
    "sg:city":"Arcadia",
    "sg:classifiers":[
        {
            "category":"Building & Trades",
            "subcategory":"Construction",
            "type":"Services"
        }
    ],
    "sg:phone":"+1 626 446 3095",
    "sg:postcode":"91006",
    "sg:province":"CA",
    "sg:tags":[
        "school",
        "general",
        "commercial",
        "contractor"
    ],
    "wof:name":"B K Wheeler Construction Co",
    "wof:placetype":"venue"
},
  "geometry": {"coordinates":[-118.026101,34.14239],"type":"Point"}
}