{
  "type": "Feature",
  "properties": {
    "iso:country":"US",
    "sg:address":"1637 Plaza Del AMO",
    "sg:city":"Torrance",
    "sg:classifiers":[
        {
            "category":"Building & Trades",
            "subcategory":"Construction",
            "type":"Services"
        }
    ],
    "sg:phone":"+1 323 567 0900",
    "sg:postcode":"90501",
    "sg:province":"CA",
    "sg:tags":[
        "wallcoverings-installation",
        "wallpaper",
        "painting",
        "painter",
        "contractor"
    ],
    "wof:name":"Sun Power Painting & Maintenance",
    "wof:placetype":"venue"
},
  "geometry": {"coordinates":[-118.307999,33.822399],"type":"Point"}
}