{
  "type": "Feature",
  "properties": {
    "addr:full":"3598 Kings Way Sacramento CA 95821",
    "addr:housenumber":"3598",
    "addr:postcode":"95821",
    "addr:street":"Kings Way",
    "iso:country":"US",
    "sg:address":"3598 Kings Way",
    "sg:city":"Sacramento",
    "sg:classifiers":[
        {
            "category":"Social Services",
            "subcategory":"Child Care",
            "type":"Services"
        }
    ],
    "sg:phone":"+1 916 971 0425",
    "sg:postcode":"95821",
    "sg:province":"CA",
    "sg:tags":[
        "center"
    ],
    "wof:name":"Child Care Mothers Referral",
    "wof:placetype":"venue"
},
  "geometry": {"coordinates":[-121.38072699999999,38.613931],"type":"Point"}
}