{
  "type": "Feature",
  "properties": {
    "addr:full":"1805 University Ave Riverside CA 92507",
    "addr:housenumber":"1805",
    "addr:postcode":"92507",
    "addr:street":"University Ave",
    "iso:country":"US",
    "sg:address":"1805 University Ave",
    "sg:city":"Riverside",
    "sg:classifiers":[
        {
            "category":"Bars & Pubs",
            "type":"Food & Drink"
        }
    ],
    "sg:phone":"+1 951 788 0310",
    "sg:postcode":"92507",
    "sg:province":"CA",
    "sg:tags":[
        "brew"
    ],
    "wof:name":"The Vibe",
    "wof:placetype":"venue"
},
  "geometry": {"coordinates":[-117.350765,33.97565],"type":"Point"}
}