{
  "type": "Feature",
  "properties": {
    "iso:country":"US",
    "sg:address":"1400 J St",
    "sg:city":"Sacramento",
    "sg:classifiers":[
        {
            "category":"Real Estate",
            "subcategory":"Real Estate Services",
            "type":"Services"
        },
        {
            "category":"Professional",
            "subcategory":"Business Services",
            "type":"Services"
        },
        {
            "category":"Real Estate",
            "subcategory":"Surveying",
            "type":"Services"
        }
    ],
    "sg:phone":"+1 916 447 4937",
    "sg:postcode":"95814",
    "sg:province":"CA",
    "sg:tags":[
        "appraisers-business",
        "industrial",
        "appraisers-commercial",
        "commercial",
        "appraiser"
    ],
    "wof:name":"Accurate Auto Appraisers",
    "wof:placetype":"venue"
},
  "geometry": {"coordinates":[-121.48786200000001,38.57885],"type":"Point"}
}