{
  "type": "Feature",
  "properties": {
    "addr:full":"967 Golf Course Dr Rohnert Park CA 94928",
    "addr:housenumber":"967",
    "addr:postcode":"94928",
    "addr:street":"Golf Course Dr",
    "iso:country":"US",
    "sg:address":"967 Golf Course Dr",
    "sg:city":"Rohnert Park",
    "sg:classifiers":[
        {
            "category":"Real Estate",
            "subcategory":"Real Estate Agent",
            "type":"Services"
        }
    ],
    "sg:phone":"+1 707 588 8900",
    "sg:postcode":"94928",
    "sg:province":"CA",
    "sg:website":"www.sonomaehomes.com",
    "wof:name":"Prudential California Realty",
    "wof:placetype":"venue"
},
  "geometry": {"coordinates":[-122.69235399999999,38.363211],"type":"Point"}
}