{
  "type": "Feature",
  "properties": {
    "iso:country":"US",
    "sg:address":"25876 The Old Rd Ste 233",
    "sg:city":"Stevenson Ranch",
    "sg:classifiers":[
        {
            "category":"Building & Trades",
            "subcategory":"Cleaning & Sanitation",
            "type":"Services"
        }
    ],
    "sg:phone":"+1 661 288 0077",
    "sg:postcode":"91381",
    "sg:province":"CA",
    "sg:tags":[
        "carpet"
    ],
    "sg:website":"www.carpetcleaningvalencia.com",
    "wof:name":"American Carpet Cleaning",
    "wof:placetype":"venue"
},
  "geometry": {"coordinates":[-118.57371500000001,34.391525],"type":"Point"}
}