{
  "type": "Feature",
  "properties": {
    "addr:full":"40835 38th St W Palmdale CA 93551",
    "addr:housenumber":"40835",
    "addr:postcode":"ca 93551",
    "addr:street":"38Th St W",
    "iso:country":"US",
    "sg:address":"40835 38th St W",
    "sg:city":"Palmdale",
    "sg:classifiers":[
        {
            "category":"Wholesale",
            "subcategory":"Durable Goods & Equipment",
            "type":"Manufacturing & Wholesale Goods"
        }
    ],
    "sg:phone":"+1 661 265 9577",
    "sg:postcode":"93551",
    "sg:province":"CA",
    "wof:name":"Kelley Tree Service",
    "wof:placetype":"venue"
},
  "geometry": {"coordinates":[-118.19768500000001,34.626106],"type":"Point"}
}