{
  "type": "Feature",
  "properties": {
    "addr:full":"974 Ruby Dr Vista CA 92083",
    "addr:housenumber":"974",
    "addr:postcode":"92083",
    "addr:street":"Ruby Dr",
    "iso:country":"US",
    "sg:address":"974 Ruby Dr",
    "sg:city":"Vista",
    "sg:classifiers":[
        {
            "category":"Building & Trades",
            "subcategory":"Plumbing",
            "type":"Services"
        }
    ],
    "sg:phone":"+1 760 726 6769",
    "sg:postcode":"92083",
    "sg:province":"CA",
    "sg:tags":[
        "contractor"
    ],
    "wof:name":"Schmid Tom Plumbing",
    "wof:placetype":"venue"
},
  "geometry": {"coordinates":[-117.276876,33.204185],"type":"Point"}
}