{
  "type": "Feature",
  "properties": {
    "iso:country":"US",
    "sg:address":"7669 Woodland Ln",
    "sg:city":"Fair Oaks",
    "sg:classifiers":[
        {
            "category":"Professional",
            "subcategory":"Management & Consulting",
            "type":"Services"
        }
    ],
    "sg:phone":"+1 916 727 1792",
    "sg:postcode":"95628",
    "sg:province":"CA",
    "sg:tags":[
        "consultant",
        "energy",
        "conservation"
    ],
    "wof:name":"Jean Arthur Baker Building Dsr",
    "wof:placetype":"venue"
},
  "geometry": {"coordinates":[-121.285714,38.638379],"type":"Point"}
}