{
  "type": "Feature",
  "properties": {
    "addr:full":"8825 Shirley Ave Northridge CA 91324",
    "addr:housenumber":"8825",
    "addr:postcode":"91324",
    "addr:street":"Shirley Ave",
    "iso:country":"US",
    "sg:address":"8825 Shirley Ave",
    "sg:city":"Northridge",
    "sg:classifiers":[
        {
            "category":"Wholesale",
            "subcategory":"Machinery & Supplies",
            "type":"Manufacturing & Wholesale Goods"
        }
    ],
    "sg:phone":"+1 818 886 8140",
    "sg:postcode":"91324",
    "sg:province":"CA",
    "sg:tags":[
        "packaging"
    ],
    "wof:name":"Superior Container Corp",
    "wof:placetype":"venue"
},
  "geometry": {"coordinates":[-118.558007,34.230998],"type":"Point"}
}