{
  "type": "Feature",
  "properties": {
    "addr:full":"735 E Ohio Ave Escondido CA 92025",
    "addr:housenumber":"735",
    "addr:postcode":"92025",
    "addr:street":"E Ohio Ave",
    "iso:country":"US",
    "sg:address":"735 E Ohio Ave",
    "sg:city":"Escondido",
    "sg:classifiers":[
        {
            "category":"Health Services",
            "subcategory":"Doctor",
            "type":"Services"
        }
    ],
    "sg:phone":"+1 760 745 5354",
    "sg:postcode":"92025",
    "sg:province":"CA",
    "sg:tags":[
        "dentist"
    ],
    "wof:name":"High Tech Family Dentistry",
    "wof:placetype":"venue"
},
  "geometry": {"coordinates":[-117.07229599999999,33.126131],"type":"Point"}
}