{
  "type": "Feature",
  "properties": {
    "iso:country":"US",
    "sg:address":"44000 Old Warm Springs Blvd",
    "sg:city":"Fremont",
    "sg:classifiers":[
        {
            "category":"Wholesale",
            "subcategory":"Electrical",
            "type":"Manufacturing & Wholesale Goods"
        }
    ],
    "sg:phone":"+1 510 770 1568",
    "sg:postcode":"94538",
    "sg:province":"CA",
    "sg:tags":[
        "semiconductor"
    ],
    "wof:name":"Semi Quip Technology Sales",
    "wof:placetype":"venue"
},
  "geometry": {"coordinates":[-121.948651,37.508786],"type":"Point"}
}