{
  "type": "Feature",
  "properties": {
    "iso:country":"US",
    "sg:address":"2301 N Fairview St",
    "sg:city":"Burbank",
    "sg:classifiers":[
        {
            "category":"Freight",
            "type":"Transportation"
        }
    ],
    "sg:phone":"+1 818 847 0312",
    "sg:postcode":"91504",
    "sg:province":"CA",
    "sg:tags":[
        "operator",
        "trucking"
    ],
    "wof:name":"M-Run Inc",
    "wof:placetype":"venue"
},
  "geometry": {"coordinates":[-118.34349400000001,34.194214],"type":"Point"}
}