{
  "type": "Feature",
  "properties": {
    "addr:full":"2144 Foothill Ln Santa Barbara CA 93105",
    "addr:housenumber":"2144",
    "addr:postcode":"93105",
    "addr:street":"Foothill Ln",
    "iso:country":"US",
    "sg:address":"2144 Foothill Ln",
    "sg:city":"Santa Barbara",
    "sg:classifiers":[
        {
            "category":"Building & Trades",
            "subcategory":"Construction",
            "type":"Services"
        }
    ],
    "sg:phone":"+1 805 965 5544",
    "sg:postcode":"93105",
    "sg:province":"CA",
    "sg:tags":[
        "marble",
        "contractor"
    ],
    "wof:name":"Giovanni's Tile & Marble",
    "wof:placetype":"venue"
},
  "geometry": {"coordinates":[-119.700411,34.445381],"type":"Point"}
}