{
  "type": "Feature",
  "properties": {
    "iso:country":"US",
    "sg:address":"8968 Fullbright Ave",
    "sg:city":"Chatsworth",
    "sg:classifiers":[
        {
            "category":"Shopping",
            "type":"Retail Goods"
        }
    ],
    "sg:phone":"+1 818 886 9200",
    "sg:postcode":"91311",
    "sg:province":"CA",
    "sg:tags":[
        "equipment",
        "supply"
    ],
    "wof:name":"Utility Refrigerator",
    "wof:placetype":"venue"
},
  "geometry": {"coordinates":[-118.577471,34.234218],"type":"Point"}
}