{
  "type": "Feature",
  "properties": {
    "iso:country":"US",
    "sg:address":"857 Horcajo St",
    "sg:city":"Milpitas",
    "sg:classifiers":[
        {
            "category":"Manufacturing",
            "subcategory":"Printing",
            "type":"Manufacturing & Wholesale Goods"
        }
    ],
    "sg:phone":"+1 408 946 7497",
    "sg:postcode":"95035",
    "sg:province":"CA",
    "sg:tags":[
        "screen"
    ],
    "wof:name":"Sonny Skyze Custom Screen",
    "wof:placetype":"venue"
},
  "geometry": {"coordinates":[-121.89548000000001,37.448457],"type":"Point"}
}