{
  "type": "Feature",
  "properties": {
    "iso:country":"US",
    "sg:address":"14909 Donnington Ln",
    "sg:city":"Truckee",
    "sg:classifiers":[
        {
            "category":"Building & Trades",
            "subcategory":"Construction",
            "type":"Services"
        }
    ],
    "sg:phone":"+1 530 550 0799",
    "sg:postcode":"96161",
    "sg:province":"CA",
    "sg:tags":[
        "roofing",
        "contractor"
    ],
    "wof:name":"Avante Roofing",
    "wof:placetype":"venue"
},
  "geometry": {"coordinates":[-120.111126,39.351618],"type":"Point"}
}