{
  "type": "Feature",
  "properties": {
    "iso:country":"US",
    "sg:address":"944 High View Dr",
    "sg:city":"Riverside",
    "sg:classifiers":[
        {
            "category":"Shopping",
            "subcategory":"Catalog Store",
            "type":"Retail Goods"
        }
    ],
    "sg:phone":"+1 951 789 9709",
    "sg:postcode":"92506",
    "sg:province":"CA",
    "sg:tags":[
        "mail",
        "order",
        "online"
    ],
    "wof:name":"Milbourne Enterprises",
    "wof:placetype":"venue"
},
  "geometry": {"coordinates":[-117.331588,33.919464],"type":"Point"}
}