{
  "type": "Feature",
  "properties": {
    "iso:country":"US",
    "sg:address":"1163 E Alosta Ave",
    "sg:city":"Azusa",
    "sg:classifiers":[
        {
            "category":"Wholesale",
            "subcategory":"Machinery & Supplies",
            "type":"Manufacturing & Wholesale Goods"
        },
        {
            "category":"Personal",
            "subcategory":"Beauty Salon",
            "type":"Services"
        }
    ],
    "sg:phone":"+1 626 963 5558",
    "sg:postcode":"91702",
    "sg:province":"CA",
    "sg:tags":[
        "shop",
        "equipment",
        "establishment"
    ],
    "wof:name":"Young's Beauty Supply",
    "wof:placetype":"venue"
},
  "geometry": {"coordinates":[-117.88135200000001,34.128651],"type":"Point"}
}