{
  "type": "Feature",
  "properties": {
    "iso:country":"US",
    "sg:address":"536 Meadowrun St",
    "sg:city":"Thousand Oaks",
    "sg:classifiers":[
        {
            "category":"Shopping",
            "subcategory":"Used Merchandise",
            "type":"Retail Goods"
        }
    ],
    "sg:phone":"+1 805 373 6701",
    "sg:postcode":"91360",
    "sg:province":"CA",
    "sg:tags":[
        "antique"
    ],
    "wof:name":"Moore Antiques",
    "wof:placetype":"venue"
},
  "geometry": {"coordinates":[-118.867812,34.234255],"type":"Point"}
}