{
  "type": "Feature",
  "properties": {
    "addr:full":"15760 Thomas Paine Dr Ramona CA 92065",
    "addr:housenumber":"15760",
    "addr:postcode":"92065",
    "addr:street":"Thomas Paine Dr",
    "iso:country":"US",
    "sg:address":"15760 Thomas Paine Dr",
    "sg:city":"Ramona",
    "sg:classifiers":[
        {
            "category":"Professional",
            "subcategory":"Advertising",
            "type":"Services"
        },
        {
            "category":"Professional",
            "subcategory":"Business Services",
            "type":"Services"
        },
        {
            "category":"Professional",
            "subcategory":"Printing & Photocopies",
            "type":"Services"
        }
    ],
    "sg:phone":"+1 760 788 9364",
    "sg:postcode":"92065",
    "sg:province":"CA",
    "sg:tags":[
        "printers-business",
        "system",
        "form",
        "specialty"
    ],
    "wof:name":"Coast Grphics Lbels Nameplates",
    "wof:placetype":"venue"
},
  "geometry": {"coordinates":[-116.927435,33.001282],"type":"Point"}
}