{
  "type": "Feature",
  "properties": {
    "addr:full":"2225 East Bayshore Rd Suite 200 Palo Alto CA 94303",
    "addr:housenumber":"2225",
    "addr:postcode":"94303",
    "addr:street":"East Bayshore Rd Suite 200",
    "iso:country":"US",
    "sg:address":"2225 East Bayshore Rd Suite 200",
    "sg:city":"Palo Alto",
    "sg:classifiers":[
        {
            "category":"Professional",
            "subcategory":"Computer Services",
            "type":"Services"
        }
    ],
    "sg:phone":"+44 117 911 8408",
    "sg:postcode":"94303",
    "sg:province":"CA",
    "sg:tags":[
        "design",
        "infrastructure",
        "systems"
    ],
    "sg:website":"http://www.gnodal.com",
    "wof:name":"Gnodal",
    "wof:placetype":"venue"
},
  "geometry": {"coordinates":[-122.12766000000001,37.45303],"type":"Point"}
}