{
  "type": "Feature",
  "properties": {
    "addr:full":"1744 Canal St Merced CA 95340",
    "addr:housenumber":"1744",
    "addr:postcode":"95340",
    "addr:street":"Canal St",
    "iso:country":"US",
    "sg:address":"1744 Canal St",
    "sg:city":"Merced",
    "sg:classifiers":[
        {
            "category":"Personal",
            "subcategory":"Beauty Salon",
            "type":"Services"
        }
    ],
    "sg:phone":"+1 209 723 9737",
    "sg:postcode":"95340",
    "sg:province":"CA",
    "wof:name":"Faye's Beauty Salon",
    "wof:placetype":"venue"
},
  "geometry": {"coordinates":[-120.483189,37.301433],"type":"Point"}
}