{
  "type": "Feature",
  "properties": {
    "addr:full":"3231 Waring Ct Oceanside CA 92056",
    "addr:housenumber":"3231",
    "addr:postcode":"92056",
    "addr:street":"Waring Ct",
    "iso:country":"US",
    "sg:address":"3231 Waring Ct",
    "sg:city":"Oceanside",
    "sg:classifiers":[
        {
            "category":"Health Services",
            "subcategory":"Doctor",
            "type":"Services"
        }
    ],
    "sg:phone":"+1 760 630 5613",
    "sg:postcode":"92056",
    "sg:province":"CA",
    "sg:tags":[
        "physician",
        "surgeon"
    ],
    "wof:name":"Asclepius Wellness Ctr",
    "wof:placetype":"venue"
},
  "geometry": {"coordinates":[-117.290795,33.18743],"type":"Point"}
}