{
  "type": "Feature",
  "properties": {
    "iso:country":"US",
    "sg:address":"1817 Maryal Dr",
    "sg:city":"Sacramento",
    "sg:classifiers":[
        {
            "category":"Health Services",
            "subcategory":"Clinic",
            "type":"Services"
        }
    ],
    "sg:phone":"+1 916 488 0242",
    "sg:postcode":"95864",
    "sg:province":"CA",
    "sg:tags":[
        "info",
        "chiropractic",
        "bureau",
        "doctor"
    ],
    "wof:name":"Choropractic Info & Referral",
    "wof:placetype":"venue"
},
  "geometry": {"coordinates":[-121.37730000000001,38.604592],"type":"Point"}
}