{
  "type": "Feature",
  "properties": {
    "addr:full":"19463 Diablo Rd Madera CA 93638",
    "addr:housenumber":"19463",
    "addr:postcode":"93638",
    "addr:street":"Diablo Rd",
    "iso:country":"US",
    "sg:address":"19463 Diablo Rd",
    "sg:city":"Madera",
    "sg:classifiers":[
        {
            "category":"Professional",
            "type":"Services"
        }
    ],
    "sg:phone":"+1 559 674 1507",
    "sg:postcode":"93638",
    "sg:province":"CA",
    "wof:name":"Sharp Image Svc",
    "wof:placetype":"venue"
},
  "geometry": {"coordinates":[-120.061538,37.031219],"type":"Point"}
}