{
  "type": "Feature",
  "properties": {
    "iso:country":"US",
    "sg:address":"4020 W Washington Boulevard",
    "sg:city":"Los Angeles",
    "sg:classifiers":[
        {
            "category":"Cinema",
            "subcategory":"Movie Rental",
            "type":"Entertainment"
        }
    ],
    "sg:phone":"+1 323 730 8927",
    "sg:postcode":"90018",
    "sg:province":"CA",
    "sg:tags":[
        "game",
        "video"
    ],
    "wof:name":"Video 21",
    "wof:placetype":"venue"
},
  "geometry": {"coordinates":[-118.328027,34.039852],"type":"Point"}
}