{
  "type": "Feature",
  "properties": {
    "addr:full":"4020 W Washington Boulevard Los Angeles CA 90018",
    "addr:housenumber":"4020",
    "addr:postcode":"90018",
    "addr:street":"W Washington Boulevard",
    "iso:country":"US",
    "sg:address":"4020 W Washington Boulevard",
    "sg:city":"Los Angeles",
    "sg:classifiers":[
        {
            "category":"Cinema",
            "subcategory":"Movie Rental",
            "type":"Entertainment"
        }
    ],
    "sg:phone":"+1 323 730 8927",
    "sg:postcode":"90018",
    "sg:province":"CA",
    "sg:tags":[
        "game",
        "video"
    ],
    "wof:name":"Video 21",
    "wof:placetype":"venue"
},
  "geometry": {"coordinates":[-118.32802700000001,34.039852],"type":"Point"}
}