{
  "type": "Feature",
  "properties": {
    "addr:full":"1736 Corporate Cir Petaluma CA 94954",
    "addr:housenumber":"1736",
    "addr:postcode":"94954",
    "addr:street":"Corporate Cir",
    "iso:country":"US",
    "sg:address":"1736 Corporate Cir",
    "sg:city":"Petaluma",
    "sg:classifiers":[
        {
            "category":"Wholesale",
            "subcategory":"Machinery & Supplies",
            "type":"Manufacturing & Wholesale Goods"
        }
    ],
    "sg:phone":"+1 707 769 9696",
    "sg:postcode":"94954",
    "sg:province":"CA",
    "sg:tags":[
        "equipment",
        "irrigation",
        "system"
    ],
    "wof:name":"Hydropoint Data Systems Inc",
    "wof:placetype":"venue"
},
  "geometry": {"coordinates":[-122.59916,38.229734],"type":"Point"}
}