{
  "type": "Feature",
  "properties": {
    "addr:full":"349 Violet Pl Tracy CA 95377",
    "addr:housenumber":"349",
    "addr:postcode":"95377",
    "addr:street":"Violet Pl",
    "iso:country":"US",
    "sg:address":"349 Violet Pl",
    "sg:city":"Tracy",
    "sg:classifiers":[
        {
            "category":"Social Services",
            "subcategory":"Child Care",
            "type":"Services"
        }
    ],
    "sg:phone":"+1 209 525 8673",
    "sg:postcode":"95377",
    "sg:province":"CA",
    "sg:tags":[
        "nursery",
        "day"
    ],
    "wof:name":"Tender Heart Family Childcare",
    "wof:placetype":"venue"
},
  "geometry": {"coordinates":[-121.43099599999999,37.69877],"type":"Point"}
}