{
  "type": "Feature",
  "properties": {
    "iso:country":"US",
    "sg:address":"1810 W Slauson Avenue",
    "sg:city":"Los Angeles",
    "sg:classifiers":[
        {
            "category":"Restaurant",
            "type":"Food & Drink"
        }
    ],
    "sg:phone":"+1 323 299 3288",
    "sg:postcode":"90047",
    "sg:province":"CA",
    "sg:tags":[
        "chinese"
    ],
    "wof:name":"China Bowl",
    "wof:placetype":"venue"
},
  "geometry": {"coordinates":[-118.31151300000001,33.98901],"type":"Point"}
}