{
  "type": "Feature",
  "properties": {
    "addr:full":"2015 Broad St San Luis Obispo CA 93401",
    "addr:housenumber":"2015",
    "addr:postcode":"93401",
    "addr:street":"Broad St",
    "iso:country":"US",
    "sg:address":"2015 Broad St",
    "sg:city":"San Luis Obispo",
    "sg:classifiers":[
        {
            "category":"Food & Beverages",
            "subcategory":"Groceries & Convenience Stores",
            "type":"Retail Goods"
        }
    ],
    "sg:phone":"+1 805 541 2658",
    "sg:postcode":"93401",
    "sg:province":"CA",
    "wof:name":"Circle K",
    "wof:placetype":"venue"
},
  "geometry": {"coordinates":[-120.658405,35.271999],"type":"Point"}
}