{
  "type": "Feature",
  "properties": {
    "addr:full":"736 Elm Street El Cerrito CA 94530",
    "addr:housenumber":"736",
    "addr:postcode":"94530",
    "addr:street":"Elm Street",
    "iso:country":"US",
    "sg:address":"736 Elm Street",
    "sg:city":"El Cerrito",
    "sg:classifiers":[
        {
            "category":"Building & Trades",
            "subcategory":"Cleaning & Sanitation",
            "type":"Services"
        }
    ],
    "sg:phone":"+1 510 559 8222",
    "sg:postcode":"94530",
    "sg:province":"CA",
    "sg:tags":[
        "window",
        "washing"
    ],
    "wof:name":"Lightstream Home Services",
    "wof:placetype":"venue"
},
  "geometry": {"coordinates":[-122.302002,37.908798],"type":"Point"}
}