{
  "type": "Feature",
  "properties": {
    "addr:full":"630 James Ave South Lake Tahoe CA 96150",
    "addr:housenumber":"630",
    "addr:postcode":"96150",
    "addr:street":"James Ave",
    "iso:country":"US",
    "sg:address":"630 James Ave",
    "sg:city":"South Lake Tahoe",
    "sg:classifiers":[
        {
            "category":"Professional",
            "subcategory":"Advertising",
            "type":"Services"
        }
    ],
    "sg:phone":"+1 530 544 2200",
    "sg:postcode":"96150",
    "sg:province":"CA",
    "sg:tags":[
        "distribution"
    ],
    "wof:name":"Herbalife",
    "wof:placetype":"venue"
},
  "geometry": {"coordinates":[-120.01702,38.92148],"type":"Point"}
}