{
  "type": "Feature",
  "properties": {
    "iso:country":"US",
    "sg:address":"2222 2nd St",
    "sg:city":"Livermore",
    "sg:classifiers":[
        {
            "category":"Museum",
            "type":"Entertainment"
        }
    ],
    "sg:phone":"+1 925 245 0010",
    "sg:postcode":"94550",
    "sg:province":"CA",
    "sg:tags":[
        "art"
    ],
    "wof:name":"Chel'Style",
    "wof:placetype":"venue"
},
  "geometry": {"coordinates":[-121.767527,37.681265],"type":"Point"}
}