{
  "type": "Feature",
  "properties": {
    "iso:country":"US",
    "sg:address":"1824 San Vicente Rd",
    "sg:city":"Ramona",
    "sg:classifiers":[
        {
            "category":"Building & Trades",
            "subcategory":"Construction",
            "type":"Services"
        }
    ],
    "sg:phone":"+1 760 788 6979",
    "sg:postcode":"92065",
    "sg:province":"CA",
    "sg:tags":[
        "maker",
        "cabinet"
    ],
    "wof:name":"Benevides Woodwork Mfg",
    "wof:placetype":"venue"
},
  "geometry": {"coordinates":[-116.866448,33.016862],"type":"Point"}
}