{
  "type": "Feature",
  "properties": {
    "iso:country":"US",
    "sg:address":"180 S A St",
    "sg:city":"Perris",
    "sg:classifiers":[
        {
            "category":"Health Services",
            "subcategory":"Doctor",
            "type":"Services"
        }
    ],
    "sg:phone":"+1 951 657 3102",
    "sg:postcode":"92570",
    "sg:province":"CA",
    "sg:tags":[
        "dentist"
    ],
    "wof:name":"Perris Dental Care",
    "wof:placetype":"venue"
},
  "geometry": {"coordinates":[-117.234858,33.78559],"type":"Point"}
}