{
  "type": "Feature",
  "properties": {
    "addr:full":"383 Valencia St San Francisco CA 94103",
    "addr:housenumber":"383",
    "addr:postcode":"94103",
    "addr:street":"Valencia St",
    "iso:country":"US",
    "sg:address":"383 Valencia St",
    "sg:city":"San Francisco",
    "sg:classifiers":[
        {
            "category":"Organizations",
            "subcategory":"Non-profit Organization",
            "type":"Services"
        }
    ],
    "sg:phone":"+1 415 554 8811",
    "sg:postcode":"94103",
    "sg:province":"CA",
    "sg:tags":[
        "information",
        "alcoholism",
        "treatment"
    ],
    "wof:name":"Alcoholics Anonimos En Espanol",
    "wof:placetype":"venue"
},
  "geometry": {"coordinates":[-122.42200800000001,37.767057],"type":"Point"}
}