{
  "type": "Feature",
  "properties": {
    "addr:full":"531 Hartnell St Monterey CA 93940",
    "addr:housenumber":"531",
    "addr:postcode":"93940",
    "addr:street":"Hartnell St",
    "iso:country":"US",
    "sg:address":"531 Hartnell St",
    "sg:city":"Monterey",
    "sg:classifiers":[
        {
            "category":"Shopping",
            "type":"Retail Goods"
        }
    ],
    "sg:phone":"+1 831 372 1447",
    "sg:postcode":"93940",
    "sg:province":"CA",
    "sg:tags":[
        "hearing",
        "equipment",
        "supply",
        "merchandise",
        "impaired"
    ],
    "wof:name":"Hartnell Hearing Aid Center",
    "wof:placetype":"venue"
},
  "geometry": {"coordinates":[-121.896006,36.596899],"type":"Point"}
}