{
  "type": "Feature",
  "properties": {
    "addr:full":"991 Lomas Santa Fe Dr Solana Beach CA 92075",
    "addr:housenumber":"991",
    "addr:postcode":"92075",
    "addr:street":"Lomas Santa Fe Dr",
    "iso:country":"US",
    "sg:address":"991 Lomas Santa Fe Dr",
    "sg:city":"Solana Beach",
    "sg:classifiers":[
        {
            "category":"Professional",
            "subcategory":"Management & Consulting",
            "type":"Services"
        }
    ],
    "sg:phone":"+1 858 350 1555",
    "sg:postcode":"92075",
    "sg:province":"CA",
    "sg:tags":[
        "counselor",
        "public",
        "relations"
    ],
    "wof:name":"Margolin & Assoc",
    "wof:placetype":"venue"
},
  "geometry": {"coordinates":[-117.25440999999999,32.995652],"type":"Point"}
}