{
  "type": "Feature",
  "properties": {
    "iso:country":"US",
    "sg:address":"5537 Claremont Ave",
    "sg:city":"Oakland",
    "sg:classifiers":[
        {
            "category":"Taxi",
            "type":"Transportation"
        }
    ],
    "sg:phone":"+1 510 420 0123",
    "sg:postcode":"94618",
    "sg:province":"CA",
    "wof:name":"Friendly Aa Cab",
    "wof:placetype":"venue"
},
  "geometry": {"coordinates":[-122.25694,37.843623],"type":"Point"}
}