{
  "type": "Feature",
  "properties": {
    "addr:full":"4632 Shasta Ct Pleasanton CA 94566",
    "addr:housenumber":"4632",
    "addr:postcode":"94566",
    "addr:street":"Shasta Ct",
    "iso:country":"US",
    "sg:address":"4632 Shasta Ct",
    "sg:city":"Pleasanton",
    "sg:classifiers":[
        {
            "category":"Health Services",
            "subcategory":"Nursing And Care Facility",
            "type":"Services"
        }
    ],
    "sg:phone":"+1 925 931 0213",
    "sg:postcode":"94566",
    "sg:province":"CA",
    "sg:tags":[
        "home",
        "convalescent"
    ],
    "wof:name":"Crow Canyon Residential Care",
    "wof:placetype":"venue"
},
  "geometry": {"coordinates":[-121.879007,37.683764],"type":"Point"}
}