{
  "type": "Feature",
  "properties": {
    "iso:country":"US",
    "sg:address":"4322 Orange Grove Ave",
    "sg:city":"Sacramento",
    "sg:classifiers":[
        {
            "category":"Building & Trades",
            "subcategory":"Construction",
            "type":"Services"
        }
    ],
    "sg:phone":"+1 916 484 6594",
    "sg:postcode":"95841",
    "sg:province":"CA",
    "sg:tags":[
        "dry wall",
        "contractor"
    ],
    "wof:name":"Custom Building Systems",
    "wof:placetype":"venue"
},
  "geometry": {"coordinates":[-121.363665,38.648067],"type":"Point"}
}