{
  "type": "Feature",
  "properties": {
    "addr:full":"10369 Gridley Rd Santa Fe Springs CA 90670",
    "addr:postcode":"10369;90670",
    "addr:street":"Gridley Rd",
    "iso:country":"US",
    "sg:address":"10369 Gridley Rd",
    "sg:city":"Santa Fe Springs",
    "sg:classifiers":[
        {
            "category":"Freight",
            "type":"Transportation"
        }
    ],
    "sg:phone":"+1 562 864 3734",
    "sg:postcode":"90670",
    "sg:province":"CA",
    "sg:tags":[
        "local",
        "storage",
        "trucking"
    ],
    "wof:name":"Javier J Trejo",
    "wof:placetype":"venue"
},
  "geometry": {"coordinates":[-118.09168099999999,33.940551],"type":"Point"}
}