{
  "type": "Feature",
  "properties": {
    "iso:country":"US",
    "sg:address":"7345 Medical Center Dr",
    "sg:city":"West Hills",
    "sg:classifiers":[
        {
            "category":"Health Services",
            "subcategory":"Doctor",
            "type":"Services"
        }
    ],
    "sg:phone":"+1 818 348 5098",
    "sg:postcode":"91307",
    "sg:province":"CA",
    "sg:tags":[
        "physician",
        "surgeon"
    ],
    "wof:name":"Jerome Adler MD",
    "wof:placetype":"venue"
},
  "geometry": {"coordinates":[-118.631371,34.203638],"type":"Point"}
}