{
  "type": "Feature",
  "properties": {
    "addr:full":"13550 Whittier Blvd Whittier CA 90605",
    "addr:housenumber":"13550",
    "addr:postcode":"90605",
    "addr:street":"Whittier Blvd",
    "iso:country":"US",
    "sg:address":"13550 Whittier Blvd",
    "sg:city":"Whittier",
    "sg:classifiers":[
        {
            "category":"Shopping",
            "subcategory":"Stationery & Office Supplies",
            "type":"Retail Goods"
        }
    ],
    "sg:phone":"+1 562 698 2034",
    "sg:postcode":"90605",
    "sg:province":"CA",
    "wof:name":"Staples The Office Superstore",
    "wof:placetype":"venue"
},
  "geometry": {"coordinates":[-118.029601,33.961196],"type":"Point"}
}