{
  "type": "Feature",
  "properties": {
    "addr:full":"1785 La Costa Meadows Dr San Marcos CA 92078",
    "addr:housenumber":"1785",
    "addr:postcode":"92078",
    "addr:street":"La Costa Meadows Dr",
    "iso:country":"US",
    "sg:address":"1785 La Costa Meadows Dr",
    "sg:city":"San Marcos",
    "sg:classifiers":[
        {
            "category":"Building & Trades",
            "subcategory":"Construction",
            "type":"Services"
        }
    ],
    "sg:phone":"+1 760 510 0079",
    "sg:postcode":"92078",
    "sg:province":"CA",
    "sg:tags":[
        "contractor"
    ],
    "wof:name":"Lusardi Construction",
    "wof:placetype":"venue"
},
  "geometry": {"coordinates":[-117.2184,33.103333],"type":"Point"}
}