{
  "type": "Feature",
  "properties": {
    "addr:full":"2588 N Temperance Ave Fresno CA 93727",
    "addr:housenumber":"2588",
    "addr:postcode":"93727",
    "addr:street":"N Temperance Ave",
    "iso:country":"US",
    "sg:address":"2588 N Temperance Ave",
    "sg:city":"Fresno",
    "sg:classifiers":[
        {
            "category":"Retail",
            "subcategory":"Veterinary Services",
            "type":"Services"
        }
    ],
    "sg:phone":"+1 559 292 7393",
    "sg:postcode":"93727",
    "sg:province":"CA",
    "sg:tags":[
        "veterinarian"
    ],
    "wof:name":"Charlene Hagus DVM",
    "wof:placetype":"venue"
},
  "geometry": {"coordinates":[-119.663968,36.772591],"type":"Point"}
}