{
  "type": "Feature",
  "properties": {
    "addr:full":"180 Selandia Ln Carson CA 90746",
    "addr:housenumber":"180",
    "addr:postcode":"90746",
    "addr:street":"Selandia Ln",
    "iso:country":"US",
    "sg:address":"180 Selandia Ln",
    "sg:city":"Carson",
    "sg:classifiers":[
        {
            "category":"Freight",
            "type":"Transportation"
        }
    ],
    "sg:phone":"+1 310 375 2783",
    "sg:postcode":"90746",
    "sg:province":"CA",
    "wof:name":"Quality Express Intl Inc",
    "wof:placetype":"venue"
},
  "geometry": {"coordinates":[-118.27055,33.870441],"type":"Point"}
}