{
  "type": "Feature",
  "properties": {
    "addr:full":"12319 Manor Dr Hawthorne CA 90250",
    "addr:housenumber":"12319",
    "addr:postcode":"90250",
    "addr:street":"Manor Dr",
    "iso:country":"US",
    "sg:address":"12319 Manor Dr",
    "sg:city":"Hawthorne",
    "sg:classifiers":[
        {
            "category":"Real Estate",
            "subcategory":"Real Estate Operator",
            "type":"Services"
        }
    ],
    "sg:phone":"+1 626 823 1956",
    "sg:postcode":"90250",
    "sg:province":"CA",
    "sg:tags":[
        "apartment"
    ],
    "wof:name":"Duquesne Apartments",
    "wof:placetype":"venue"
},
  "geometry": {"coordinates":[-118.355817,33.920071],"type":"Point"}
}