{
  "type": "Feature",
  "properties": {
    "iso:country":"US",
    "sg:address":"13489 Arrow Blvd",
    "sg:city":"Fontana",
    "sg:classifiers":[
        {
            "category":"Organizations",
            "subcategory":"Religious Organization",
            "type":"Services"
        }
    ],
    "sg:phone":"+1 909 355 3168",
    "sg:postcode":"92335",
    "sg:province":"CA",
    "sg:tags":[
        "church"
    ],
    "sg:website":"www.thecarpentershouse.com",
    "wof:name":"Carpenters House",
    "wof:placetype":"venue"
},
  "geometry": {"coordinates":[-117.513862,34.099017],"type":"Point"}
}