{
  "type": "Feature",
  "properties": {
    "iso:country":"US",
    "sg:address":"756 Bromley Ave",
    "sg:city":"Yuba City",
    "sg:classifiers":[
        {
            "category":"Shopping",
            "subcategory":"Gifts & Souvenirs",
            "type":"Retail Goods"
        }
    ],
    "sg:phone":"+1 530 822 9269",
    "sg:postcode":"95993",
    "sg:province":"CA",
    "wof:name":"Europa Gifts",
    "wof:placetype":"venue"
},
  "geometry": {"coordinates":[-121.645445,39.114224],"type":"Point"}
}