{
  "type": "Feature",
  "properties": {
    "iso:country":"US",
    "sg:address":"3625 del Amo Blvd",
    "sg:city":"Torrance",
    "sg:classifiers":[
        {
            "category":"Restaurant",
            "type":"Food & Drink"
        }
    ],
    "sg:phone":"+1 310 542 2679",
    "sg:postcode":"90501",
    "sg:province":"CA",
    "wof:name":"Sammies Cafe",
    "wof:placetype":"venue"
},
  "geometry": {"coordinates":[-118.350125,33.848644],"type":"Point"}
}