{
  "type": "Feature",
  "properties": {
    "iso:country":"US",
    "sg:address":"1066 Charles St",
    "sg:city":"Pasadena",
    "sg:classifiers":[
        {
            "category":"Real Estate",
            "subcategory":"Real Estate Agent",
            "type":"Services"
        }
    ],
    "sg:phone":"+1 310 275 2222",
    "sg:postcode":"91103",
    "sg:province":"CA",
    "wof:name":"Mossler Deaey & Doe",
    "wof:placetype":"venue"
},
  "geometry": {"coordinates":[-118.174119,34.163885],"type":"Point"}
}