{
  "type": "Feature",
  "properties": {
    "iso:country":"US",
    "sg:address":"942 S New Hampshire Ave",
    "sg:city":"Los Angeles",
    "sg:classifiers":[
        {
            "category":"Health Services",
            "subcategory":"Doctor",
            "type":"Services"
        }
    ],
    "sg:phone":"+1 213 386 5418",
    "sg:postcode":"90006",
    "sg:province":"CA",
    "sg:tags":[
        "physician",
        "surgeon"
    ],
    "wof:name":"Dong Hoon Kim MD",
    "wof:placetype":"venue"
},
  "geometry": {"coordinates":[-118.292584,34.052723],"type":"Point"}
}