{
  "type": "Feature",
  "properties": {
    "addr:full":"1350 7th Ave San Francisco CA 94122",
    "addr:housenumber":"1350",
    "addr:postcode":"94122",
    "addr:street":"7Th Ave",
    "iso:country":"US",
    "sg:address":"1350 7th Ave",
    "sg:city":"San Francisco",
    "sg:classifiers":[
        {
            "category":"Education",
            "subcategory":"School",
            "type":"Public Place"
        }
    ],
    "sg:phone":"+1 415 242 2654",
    "sg:postcode":"94122",
    "sg:province":"CA",
    "sg:website":"www.gatewayhigh.org",
    "wof:name":"Gateway High School",
    "wof:placetype":"venue"
},
  "geometry": {"coordinates":[-122.46401899999999,37.763223],"type":"Point"}
}