{
  "type": "Feature",
  "properties": {
    "iso:country":"US",
    "sg:address":"5322 D Avilla Way",
    "sg:city":"El Sobrante",
    "sg:classifiers":[
        {
            "category":"Real Estate",
            "subcategory":"Real Estate Operator",
            "type":"Services"
        }
    ],
    "sg:phone":"+1 510 223 7630",
    "sg:postcode":"94803",
    "sg:province":"CA",
    "sg:tags":[
        "apartment"
    ],
    "wof:name":"D'Avila Woods Apartments",
    "wof:placetype":"venue"
},
  "geometry": {"coordinates":[-122.281744,37.962829],"type":"Point"}
}