{
  "type": "Feature",
  "properties": {
    "iso:country":"US",
    "sg:address":"8803 Hobbs Rd",
    "sg:city":"Yuba City",
    "sg:classifiers":[
        {
            "category":"Farming",
            "subcategory":"Farm & Veterinary Services",
            "type":"Manufacturing & Wholesale Goods"
        }
    ],
    "sg:phone":"+1 530 908 3160",
    "sg:postcode":"95993",
    "sg:province":"CA",
    "sg:tags":[
        "consultant",
        "irrigation"
    ],
    "wof:name":"Tudor Mutual Water Co",
    "wof:placetype":"venue"
},
  "geometry": {"coordinates":[-121.644251,38.998698],"type":"Point"}
}