{
  "type": "Feature",
  "properties": {
    "iso:country":"US",
    "sg:address":"24082 Via Madrugada",
    "sg:city":"Mission Viejo",
    "sg:classifiers":[
        {
            "category":"Autos & Motor Vehicles",
            "subcategory":"Automobile Sales",
            "type":"Retail Goods"
        },
        {
            "category":"Airline",
            "type":"Transportation"
        }
    ],
    "sg:phone":"+1 949 770 2318",
    "sg:postcode":"92692",
    "sg:province":"CA",
    "sg:tags":[
        "shuttle",
        "airport",
        "limo"
    ],
    "wof:name":"Pacific Limousine",
    "wof:placetype":"venue"
},
  "geometry": {"coordinates":[-117.65235800000001,33.612924],"type":"Point"}
}