{
  "type": "Feature",
  "properties": {
    "addr:full":"509 N Isabel St Glendale CA 91206",
    "addr:housenumber":"509",
    "addr:postcode":"91206",
    "addr:street":"N Isabel St",
    "iso:country":"US",
    "sg:address":"509 N Isabel St",
    "sg:city":"Glendale",
    "sg:classifiers":[
        {
            "category":"Building & Trades",
            "subcategory":"Plumbing",
            "type":"Services"
        }
    ],
    "sg:phone":"+1 818 500 1974",
    "sg:postcode":"91206",
    "sg:province":"CA",
    "sg:tags":[
        "conditioning",
        "air",
        "system",
        "contractor"
    ],
    "wof:name":"Airway Air Conditioning & Htg",
    "wof:placetype":"venue"
},
  "geometry": {"coordinates":[-118.24896099999999,34.153109],"type":"Point"}
}