{
  "type": "Feature",
  "properties": {
    "iso:country":"US",
    "sg:address":"4721 E Hunter Ave",
    "sg:city":"Anaheim",
    "sg:classifiers":[
        {
            "category":"Building & Trades",
            "subcategory":"Plumbing",
            "type":"Services"
        }
    ],
    "sg:phone":"+1 714 693 3700",
    "sg:postcode":"92807",
    "sg:province":"CA",
    "sg:tags":[
        "balancing",
        "air"
    ],
    "sg:website":"www.americanairbalance.com",
    "wof:name":"American Air Balance",
    "wof:placetype":"venue"
},
  "geometry": {"coordinates":[-117.815316,33.864445],"type":"Point"}
}