{
  "type": "Feature",
  "properties": {
    "iso:country":"US",
    "sg:address":"1035 Grouse St",
    "sg:city":"El Cajon",
    "sg:classifiers":[
        {
            "category":"Professional",
            "type":"Services"
        }
    ],
    "sg:phone":"+1 619 562 8351",
    "sg:postcode":"92020",
    "sg:province":"CA",
    "wof:name":"Mike Dice",
    "wof:placetype":"venue"
},
  "geometry": {"coordinates":[-116.981527,32.810526],"type":"Point"}
}