{
  "type": "Feature",
  "properties": {
    "iso:country":"US",
    "sg:address":"2650 Hogan Dr",
    "sg:city":"Turlock",
    "sg:classifiers":[
        {
            "category":"Professional",
            "type":"Services"
        }
    ],
    "sg:phone":"+1 209 667 2596",
    "sg:postcode":"95382",
    "sg:province":"CA",
    "wof:name":"Don Wells Inc",
    "wof:placetype":"venue"
},
  "geometry": {"coordinates":[-120.82961,37.517196],"type":"Point"}
}