{
  "type": "Feature",
  "properties": {
    "iso:country":"US",
    "sg:address":"617 Abbott St",
    "sg:city":"Salinas",
    "sg:classifiers":[
        {
            "category":"Retail",
            "subcategory":"Auto Repair",
            "type":"Services"
        }
    ],
    "sg:phone":"+1 831 759 9923",
    "sg:postcode":"93901",
    "sg:province":"CA",
    "sg:tags":[
        "wrecker"
    ],
    "wof:name":"Classic Towing",
    "wof:placetype":"venue"
},
  "geometry": {"coordinates":[-121.640179,36.66043],"type":"Point"}
}