{
  "type": "Feature",
  "properties": {
    "addr:full":"99 Smith Ranch Rd San Rafael CA 94903",
    "addr:housenumber":"99",
    "addr:postcode":"94903",
    "addr:street":"Smith Ranch Rd",
    "iso:country":"US",
    "sg:address":"99 Smith Ranch Rd",
    "sg:city":"San Rafael",
    "sg:classifiers":[
        {
            "category":"Insurance",
            "subcategory":"Insurance Agent",
            "type":"Services"
        }
    ],
    "sg:phone":"+1 415 472 6700",
    "sg:postcode":"94903",
    "sg:province":"CA",
    "wof:name":"California State Automobile",
    "wof:placetype":"venue"
},
  "geometry": {"coordinates":[-122.535094,38.01983],"type":"Point"}
}