{
  "type": "Feature",
  "properties": {
    "addr:full":"1256 Brooks St Ste B Ontario CA 91762",
    "addr:housenumber":"1256",
    "addr:postcode":"91762",
    "addr:street":"Brooks St Ste B",
    "iso:country":"US",
    "sg:address":"1256 Brooks St Ste B",
    "sg:city":"Ontario",
    "sg:classifiers":[
        {
            "category":"Professional",
            "subcategory":"Engineering",
            "type":"Services"
        },
        {
            "category":"Building & Trades",
            "subcategory":"Electrical",
            "type":"Services"
        },
        {
            "category":"Professional",
            "subcategory":"Management & Consulting",
            "type":"Services"
        }
    ],
    "sg:phone":"+1 909 983 3848",
    "sg:postcode":"91762",
    "sg:province":"CA",
    "sg:tags":[
        "control",
        "consultant",
        "system",
        "controls",
        "regulator",
        "environmental",
        "ecological",
        "engineer"
    ],
    "wof:name":"Metro Environmental Services, Inc.",
    "wof:placetype":"venue"
},
  "geometry": {"coordinates":[-117.67430899999999,34.061911],"type":"Point"}
}