{
  "type": "Feature",
  "properties": {
    "addr:full":"120 Colton Ave San Carlos CA 94070",
    "addr:housenumber":"120",
    "addr:postcode":"94070",
    "addr:street":"Colton Ave",
    "iso:country":"US",
    "sg:address":"120 Colton Ave",
    "sg:city":"San Carlos",
    "sg:classifiers":[
        {
            "category":"Professional",
            "subcategory":"Management & Consulting",
            "type":"Services"
        }
    ],
    "sg:phone":"+1 650 508 0680",
    "sg:postcode":"94070",
    "sg:province":"CA",
    "sg:tags":[
        "consultant",
        "business"
    ],
    "wof:name":"Parallel Consulting Group",
    "wof:placetype":"venue"
},
  "geometry": {"coordinates":[-122.250654,37.487259],"type":"Point"}
}