{
  "type": "Feature",
  "properties": {
    "addr:full":"2375 E Tulare Ave Tulare CA 93274",
    "addr:housenumber":"2375",
    "addr:postcode":"93274",
    "addr:street":"E Tulare Ave",
    "iso:country":"US",
    "sg:address":"2375 E Tulare Ave",
    "sg:city":"Tulare",
    "sg:classifiers":[
        {
            "category":"Home & Garden",
            "subcategory":"Home Furnishings",
            "type":"Retail Goods"
        }
    ],
    "sg:phone":"+1 559 688 0696",
    "sg:postcode":"93274",
    "sg:province":"CA",
    "sg:tags":[
        "lighting",
        "fixture"
    ],
    "wof:name":"Anchor Lighting",
    "wof:placetype":"venue"
},
  "geometry": {"coordinates":[-119.313016,36.211288],"type":"Point"}
}