{
  "type": "Feature",
  "properties": {
    "addr:full":"1520 N Grand Ave Santa Ana CA 92701",
    "addr:housenumber":"1520",
    "addr:postcode":"92701",
    "addr:street":"N Grand Ave",
    "iso:country":"US",
    "sg:address":"1520 N Grand Ave",
    "sg:city":"Santa Ana",
    "sg:classifiers":[
        {
            "category":"Health Services",
            "subcategory":"Optometrist",
            "type":"Services"
        }
    ],
    "sg:phone":"+1 714 835 5500",
    "sg:postcode":"92701",
    "sg:province":"CA",
    "wof:name":"De La Pena Eye Clinic A Medical Group",
    "wof:placetype":"venue"
},
  "geometry": {"coordinates":[-117.85257300000001,33.758547],"type":"Point"}
}