{
  "type": "Feature",
  "properties": {
    "addr:full":"5700 Skyway Rd Paradise CA 95969",
    "addr:housenumber":"5700",
    "addr:postcode":"95969",
    "addr:street":"Skyway Rd",
    "iso:country":"US",
    "sg:address":"5700 Skyway Rd",
    "sg:city":"Paradise",
    "sg:classifiers":[
        {
            "category":"Shopping",
            "subcategory":"Jewelry",
            "type":"Retail Goods"
        }
    ],
    "sg:phone":"+1 530 895 8501",
    "sg:postcode":"95969",
    "sg:province":"CA",
    "sg:tags":[
        "jeweler"
    ],
    "wof:name":"In My Dreams",
    "wof:placetype":"venue"
},
  "geometry": {"coordinates":[-121.63072699999999,39.751602],"type":"Point"}
}