{
  "type": "Feature",
  "properties": {
    "addr:full":"2001 W Magnolia Blvd Burbank CA 91506",
    "addr:housenumber":"2001",
    "addr:postcode":"91506",
    "addr:street":"W Magnolia Blvd",
    "iso:country":"US",
    "sg:address":"2001 W Magnolia Blvd",
    "sg:city":"Burbank",
    "sg:classifiers":[
        {
            "category":"Health Services",
            "subcategory":"Health Practitioner",
            "type":"Services"
        }
    ],
    "sg:phone":"+1 818 566 1900",
    "sg:postcode":"91506",
    "sg:province":"CA",
    "sg:tags":[
        "therapist",
        "physical"
    ],
    "wof:name":"New Vision Rehabilitaion",
    "wof:placetype":"venue"
},
  "geometry": {"coordinates":[-118.330602,34.173327],"type":"Point"}
}