{
  "type": "Feature",
  "properties": {
    "addr:full":"514 W 7th St Los Angeles CA 90013",
    "addr:housenumber":"514",
    "addr:postcode":"90013",
    "addr:street":"W 7Th St",
    "iso:country":"US",
    "sg:address":"514 W 7th St",
    "sg:city":"Los Angeles",
    "sg:classifiers":[
        {
            "category":"Restaurant",
            "type":"Food & Drink"
        }
    ],
    "sg:phone":"+1 213 612 0107",
    "sg:postcode":"90013",
    "sg:province":"CA",
    "sg:website":"www.sandellas.com/",
    "wof:name":"Sandella's Flatbread Cafe",
    "wof:placetype":"venue"
},
  "geometry": {"coordinates":[-118.256182,34.047002],"type":"Point"}
}