{
  "type": "Feature",
  "properties": {
    "addr:full":"1120 Industrial Ave Petaluma CA 94952",
    "addr:housenumber":"1120",
    "addr:postcode":"94952",
    "addr:street":"Industrial Ave",
    "iso:country":"US",
    "sg:address":"1120 Industrial Ave",
    "sg:city":"Petaluma",
    "sg:classifiers":[
        {
            "category":"Retail",
            "subcategory":"Veterinary Services",
            "type":"Services"
        }
    ],
    "sg:phone":"+1 415 892 5893",
    "sg:postcode":"94952",
    "sg:province":"CA",
    "wof:name":"Jeff Pelton Dvm",
    "wof:placetype":"venue"
},
  "geometry": {"coordinates":[-122.664452,38.264682],"type":"Point"}
}