{
  "type": "Feature",
  "properties": {
    "iso:country":"US",
    "sg:address":"4990 Stockton Boulevard",
    "sg:city":"Sacramento",
    "sg:classifiers":[
        {
            "category":"Professional",
            "subcategory":"Employment Agencies",
            "type":"Services"
        },
        {
            "category":"Building & Trades",
            "subcategory":"Construction",
            "type":"Services"
        }
    ],
    "sg:phone":"+1 916 875 3330",
    "sg:postcode":"95820",
    "sg:province":"CA",
    "sg:tags":[
        "contractor"
    ],
    "wof:name":"Sacramento County of",
    "wof:placetype":"venue"
},
  "geometry": {"coordinates":[-121.445172,38.530258],"type":"Point"}
}