{
  "type": "Feature",
  "properties": {
    "addr:full":"1400 Hyde Street San Francisco CA 94109",
    "addr:housenumber":"1400",
    "addr:postcode":"94109",
    "addr:street":"Hyde Street",
    "iso:country":"US",
    "sg:address":"1400 Hyde Street",
    "sg:city":"San Francisco",
    "sg:classifiers":[
        {
            "category":"Retail",
            "subcategory":"Laundry & Dry Cleaning",
            "type":"Services"
        }
    ],
    "sg:phone":"+1 415 885 3360",
    "sg:postcode":"94109",
    "sg:province":"CA",
    "wof:name":"American Cleaners",
    "wof:placetype":"venue"
},
  "geometry": {"coordinates":[-122.41799899999999,37.793701],"type":"Point"}
}