{
  "type": "Feature",
  "properties": {
    "addr:full":"10269 McBroom St Sunland CA 91040",
    "addr:housenumber":"10269",
    "addr:postcode":"91040",
    "addr:street":"Mcbroom St",
    "iso:country":"US",
    "sg:address":"10269 McBroom St",
    "sg:city":"Sunland",
    "sg:classifiers":[
        {
            "category":"Education",
            "subcategory":"School",
            "type":"Public Place"
        }
    ],
    "sg:phone":"+1 818 352 0164",
    "sg:postcode":"91040",
    "sg:province":"CA",
    "wof:name":"Ace Academy",
    "wof:placetype":"venue"
},
  "geometry": {"coordinates":[-118.352261,34.263613],"type":"Point"}
}