{
  "type": "Feature",
  "properties": {
    "iso:country":"US",
    "sg:address":"3801 Las Posas Rd Ste 208",
    "sg:city":"Camarillo",
    "sg:classifiers":[
        {
            "category":"Community Center",
            "type":"Public Place"
        }
    ],
    "sg:phone":"+1 877 493 5991",
    "sg:postcode":"93010",
    "sg:province":"CA",
    "sg:tags":[
        "medical"
    ],
    "sg:website":"www.localstdtesting.com",
    "wof:name":"Camarillo Local HIV/STD Testing",
    "wof:placetype":"venue"
},
  "geometry": {"coordinates":[-119.067232,34.22972],"type":"Point"}
}