{
  "type": "Feature",
  "properties": {
    "iso:country":"US",
    "sg:address":"1026 Garnet Ave",
    "sg:city":"San Diego",
    "sg:classifiers":[
        {
            "category":"Personal",
            "subcategory":"Tattoo Parlor",
            "type":"Services"
        }
    ],
    "sg:phone":"+1 858 270 8287",
    "sg:postcode":"92109",
    "sg:province":"CA",
    "sg:website":"www.abovealltattoo.com",
    "wof:name":"Above All Tattoo",
    "wof:placetype":"venue"
},
  "geometry": {"coordinates":[-117.251242,32.797797],"type":"Point"}
}