{
  "type": "Feature",
  "properties": {
    "iso:country":"US",
    "sg:address":"900 12th St",
    "sg:city":"Sacramento",
    "sg:classifiers":[
        {
            "category":"Restaurant",
            "type":"Food & Drink"
        }
    ],
    "sg:phone":"+1 916 443 5588",
    "sg:postcode":"95814",
    "sg:province":"CA",
    "sg:tags":[
        "thai",
        "asian",
        "pan"
    ],
    "sg:website":"www.bangkok12restaurant.com",
    "wof:name":"Bangkok @12 Thai Restaurant",
    "wof:placetype":"venue"
},
  "geometry": {"coordinates":[-121.490353,38.58069],"type":"Point"}
}