{
  "type": "Feature",
  "properties": {
    "addr:full":"2051 Palomar Airport Rd Ste 250 Carlsbad CA 92011",
    "addr:housenumber":"2051",
    "addr:postcode":"92011",
    "addr:street":"Palomar Airport Rd Ste 250",
    "iso:country":"US",
    "sg:address":"2051 Palomar Airport Rd Ste 250",
    "sg:city":"Carlsbad",
    "sg:classifiers":[
        {
            "category":"Cinema",
            "subcategory":"Movie Rental",
            "type":"Entertainment"
        }
    ],
    "sg:phone":"+1 760 804 1533",
    "sg:postcode":"92011",
    "sg:province":"CA",
    "sg:tags":[
        "game",
        "video"
    ],
    "wof:name":"Concrete Games",
    "wof:placetype":"venue"
},
  "geometry": {"coordinates":[-117.27986799999999,33.12126],"type":"Point"}
}