{
  "type": "Feature",
  "properties": {
    "addr:full":"1295 S Main St Walnut Creek CA 94595",
    "addr:housenumber":"1295",
    "addr:postcode":"94595",
    "addr:street":"S Main St",
    "iso:country":"US",
    "sg:address":"1295 S Main St",
    "sg:city":"Walnut Creek",
    "sg:classifiers":[
        {
            "category":"Shopping",
            "subcategory":"Department Store",
            "type":"Retail Goods"
        }
    ],
    "sg:phone":"+1 925 934 1900",
    "sg:postcode":"94595",
    "sg:province":"CA",
    "sg:website":"www.ross.com",
    "wof:name":"Ross Dress For Less",
    "wof:placetype":"venue"
},
  "geometry": {"coordinates":[-122.059589,37.895101],"type":"Point"}
}