{
  "type": "Feature",
  "properties": {
    "addr:full":"32387 Yucaipa Blvd Yucaipa CA 92399",
    "addr:housenumber":"32387",
    "addr:postcode":"92399",
    "addr:street":"Yucaipa Blvd",
    "iso:country":"US",
    "sg:address":"32387 Yucaipa Blvd",
    "sg:city":"Yucaipa",
    "sg:classifiers":[
        {
            "category":"Insurance",
            "subcategory":"Hazard Insurance",
            "type":"Services"
        },
        {
            "category":"Insurance",
            "subcategory":"Life Insurance",
            "type":"Services"
        },
        {
            "category":"Banks & Credit Unions",
            "subcategory":"Financial Services",
            "type":"Services"
        }
    ],
    "sg:phone":"+1 909 790 1500",
    "sg:postcode":"92399",
    "sg:province":"CA",
    "sg:tags":[
        "annuity",
        "retirement",
        "plan"
    ],
    "wof:name":"Rhokar, Inc.",
    "wof:placetype":"venue"
},
  "geometry": {"coordinates":[-117.09725299999999,34.033859],"type":"Point"}
}