{
  "type": "Feature",
  "properties": {
    "iso:country":"US",
    "sg:address":"29395 Agoura Rd",
    "sg:city":"Agoura Hills",
    "sg:classifiers":[
        {
            "category":"Professional",
            "subcategory":"Business Services",
            "type":"Services"
        }
    ],
    "sg:phone":"+1 818 889 4546",
    "sg:postcode":"91301",
    "sg:province":"CA",
    "sg:tags":[
        "messenger"
    ],
    "sg:website":"www.stateexpress.net",
    "wof:name":"State Express",
    "wof:placetype":"venue"
},
  "geometry": {"coordinates":[-118.771503,34.145235],"type":"Point"}
}