{
  "type": "Feature",
  "properties": {
    "iso:country":"US",
    "sg:address":"10160 Swanton Dr",
    "sg:city":"Santee",
    "sg:classifiers":[
        {
            "category":"Professional",
            "subcategory":"Management & Consulting",
            "type":"Services"
        }
    ],
    "sg:phone":"+1 619 562 2270",
    "sg:postcode":"92071",
    "sg:province":"CA",
    "sg:tags":[
        "retail",
        "direct",
        "sales"
    ],
    "wof:name":"Madsen Computer Services",
    "wof:placetype":"venue"
},
  "geometry": {"coordinates":[-117.000919,32.862206],"type":"Point"}
}