{
  "type": "Feature",
  "properties": {
    "iso:country":"US",
    "sg:address":"1502 171st Ave",
    "sg:city":"Hayward",
    "sg:classifiers":[
        {
            "category":"Building & Trades",
            "subcategory":"Landscaping Services",
            "type":"Services"
        }
    ],
    "sg:phone":"+1 510 481 9708",
    "sg:postcode":"94541",
    "sg:province":"CA",
    "sg:tags":[
        "aged",
        "homes-institutional"
    ],
    "wof:name":"Morning Sun Care Home",
    "wof:placetype":"venue"
},
  "geometry": {"coordinates":[-122.10543699999999,37.690916],"type":"Point"}
}