{
  "type": "Feature",
  "properties": {
    "addr:full":"6407 Jadeite Ave Rancho Cucamonga CA 91737",
    "addr:housenumber":"6407",
    "addr:postcode":"91737",
    "addr:street":"Jadeite Ave",
    "iso:country":"US",
    "sg:address":"6407 Jadeite Ave",
    "sg:city":"Rancho Cucamonga",
    "sg:classifiers":[
        {
            "category":"Building & Trades",
            "subcategory":"Landscaping Services",
            "type":"Services"
        }
    ],
    "sg:phone":"+1 909 987 3247",
    "sg:postcode":"91737",
    "sg:province":"CA",
    "wof:name":"Gonzalez Robert",
    "wof:placetype":"venue"
},
  "geometry": {"coordinates":[-117.59402799999999,34.138103],"type":"Point"}
}