{
  "type": "Feature",
  "properties": {
    "iso:country":"US",
    "sg:address":"124 E 17 T St",
    "sg:city":"Costa Mesa",
    "sg:classifiers":[
        {
            "category":"Home & Garden",
            "subcategory":"Carpets & Floor Coverings",
            "type":"Retail Goods"
        }
    ],
    "sg:phone":"+1 949 650 7676",
    "sg:postcode":"92626",
    "sg:province":"CA",
    "sg:tags":[
        "flooring"
    ],
    "wof:name":"Floor Guys the",
    "wof:placetype":"venue"
},
  "geometry": {"coordinates":[-117.91100299999999,33.678699],"type":"Point"}
}