{
  "type": "Feature",
  "properties": {
    "iso:country":"US",
    "sg:address":"647 Cornish Dr",
    "sg:city":"Encinitas",
    "sg:classifiers":[
        {
            "category":"Utilities",
            "subcategory":"Fuel Oil & Lpg",
            "type":"Services"
        }
    ],
    "sg:phone":"+1 760 753 4344",
    "sg:postcode":"92024",
    "sg:province":"CA",
    "sg:tags":[
        "firewood"
    ],
    "wof:name":"Lymans's Firewood Sale",
    "wof:placetype":"venue"
},
  "geometry": {"coordinates":[-117.290201,33.043844],"type":"Point"}
}