{
  "type": "Feature",
  "properties": {
    "iso:country":"US",
    "sg:address":"501 The City Dr S",
    "sg:city":"Orange",
    "sg:classifiers":[
        {
            "category":"Professional",
            "subcategory":"Engineering",
            "type":"Services"
        }
    ],
    "sg:phone":"+1 714 935 6007",
    "sg:postcode":"92868",
    "sg:province":"CA",
    "sg:tags":[
        "consulting"
    ],
    "wof:name":"HDR Engineering Inc",
    "wof:placetype":"venue"
},
  "geometry": {"coordinates":[-117.88870900000001,33.780195],"type":"Point"}
}