{
  "type": "Feature",
  "properties": {
    "iso:country":"US",
    "sg:address":"2917 del Paso Blvd",
    "sg:city":"Sacramento",
    "sg:classifiers":[
        {
            "category":"Building & Trades",
            "subcategory":"Construction",
            "type":"Services"
        }
    ],
    "sg:phone":"+1 916 564 0577",
    "sg:postcode":"95815",
    "sg:province":"CA",
    "sg:tags":[
        "altering",
        "remodeling",
        "contractor"
    ],
    "wof:name":"Marland Properties, Inc.",
    "wof:placetype":"venue"
},
  "geometry": {"coordinates":[-121.43650700000001,38.61929],"type":"Point"}
}