{
  "type": "Feature",
  "properties": {
    "iso:country":"US",
    "sg:address":"24175 Mission Blvd",
    "sg:city":"Hayward",
    "sg:classifiers":[
        {
            "category":"Fast Food",
            "type":"Food & Drink"
        }
    ],
    "sg:postcode":"94544",
    "sg:province":"CA",
    "wof:name":"Jack In The Box",
    "wof:placetype":"venue"
},
  "geometry": {"coordinates":[-122.078306,37.665114],"type":"Point"}
}