{
  "type": "Feature",
  "properties": {
    "iso:country":"US",
    "sg:address":"1020 S Fairfax Ave",
    "sg:city":"Los Angeles",
    "sg:classifiers":[
        {
            "category":"Health Services",
            "subcategory":"Nursing And Care Facility",
            "type":"Services"
        }
    ],
    "sg:phone":"+1 323 938 2451",
    "sg:postcode":"90019",
    "sg:province":"CA",
    "sg:tags":[
        "home",
        "convalescent"
    ],
    "wof:name":"Westside Health Care",
    "wof:placetype":"venue"
},
  "geometry": {"coordinates":[-118.364806,34.055884],"type":"Point"}
}