{
  "type": "Feature",
  "properties": {
    "iso:country":"US",
    "sg:address":"434 E Elmwood Ave Apt 101",
    "sg:city":"Burbank",
    "sg:classifiers":[
        {
            "category":"Building & Trades",
            "subcategory":"Construction",
            "type":"Services"
        }
    ],
    "sg:phone":"+1 818 260 0596",
    "sg:postcode":"91501",
    "sg:province":"CA",
    "sg:tags":[
        "contractor"
    ],
    "sg:website":"www.centuryconstructionwest.com/...",
    "wof:name":"Century Construction",
    "wof:placetype":"venue"
},
  "geometry": {"coordinates":[-118.299004,34.1786],"type":"Point"}
}