{
  "type": "Feature",
  "properties": {
    "iso:country":"US",
    "sg:address":"400 S Baldwin Ave",
    "sg:city":"Arcadia",
    "sg:classifiers":[
        {
            "category":"Food & Beverages",
            "subcategory":"Groceries & Convenience Stores",
            "type":"Retail Goods"
        }
    ],
    "sg:phone":"+1 626 445 7226",
    "sg:postcode":"91007",
    "sg:province":"CA",
    "sg:website":"www.famima-usa.com",
    "wof:name":"Famima!!",
    "wof:placetype":"venue"
},
  "geometry": {"coordinates":[-118.052301,34.132837],"type":"Point"}
}