{
  "type": "Feature",
  "properties": {
    "iso:country":"US",
    "sg:address":"1701 Santa Rosa Ave",
    "sg:city":"Santa Rosa",
    "sg:classifiers":[
        {
            "category":"Autos & Motor Vehicles",
            "subcategory":"Auto Supplies",
            "type":"Retail Goods"
        }
    ],
    "sg:phone":"+1 707 527 5000",
    "sg:postcode":"95404",
    "sg:province":"CA",
    "sg:tags":[
        "automobile",
        "stereo",
        "radio"
    ],
    "wof:name":"Kustom Kar Audio",
    "wof:placetype":"venue"
},
  "geometry": {"coordinates":[-122.713424,38.422485],"type":"Point"}
}