{
  "type": "Feature",
  "properties": {
    "addr:full":"3265 Old Adobe Rd Petaluma CA 94954",
    "addr:housenumber":"3265",
    "addr:postcode":"94954",
    "addr:street":"Old Adobe Rd",
    "iso:country":"US",
    "sg:address":"3265 Old Adobe Rd",
    "sg:city":"Petaluma",
    "sg:classifiers":[
        {
            "category":"Building & Trades",
            "subcategory":"Construction",
            "type":"Services"
        }
    ],
    "sg:phone":"+1 707 765 9157",
    "sg:postcode":"94954",
    "sg:province":"CA",
    "sg:tags":[
        "excavating",
        "contractor"
    ],
    "wof:name":"C Hardy General Engineering",
    "wof:placetype":"venue"
},
  "geometry": {"coordinates":[-122.583457,38.254456],"type":"Point"}
}