{
  "type": "Feature",
  "properties": {
    "iso:country":"US",
    "sg:address":"1417 University Ave",
    "sg:city":"San Diego",
    "sg:classifiers":[
        {
            "category":"Restaurant",
            "type":"Food & Drink"
        }
    ],
    "sg:phone":"+1 619 295 7911",
    "sg:postcode":"92103",
    "sg:province":"CA",
    "sg:tags":[
        "shop",
        "coffee"
    ],
    "wof:name":"Living Room Coffeehouse",
    "wof:placetype":"venue"
},
  "geometry": {"coordinates":[-117.15021900000001,32.748413],"type":"Point"}
}