{
  "type": "Feature",
  "properties": {
    "addr:full":"1350 E Chapman Ave Fullerton CA 92866",
    "addr:housenumber":"1350",
    "addr:postcode":"92866",
    "addr:street":"E Chapman Ave",
    "iso:country":"US",
    "sg:address":"1350 E Chapman Ave",
    "sg:city":"Fullerton",
    "sg:classifiers":[
        {
            "category":"Government",
            "subcategory":"Post Office",
            "type":"Public Place"
        }
    ],
    "sg:phone":"+1 714 525 1024",
    "sg:postcode":"92866",
    "sg:province":"CA",
    "wof:name":"Fullerton Post Office",
    "wof:placetype":"venue"
},
  "geometry": {"coordinates":[-117.83860199999999,33.787746],"type":"Point"}
}