{
  "type": "Feature",
  "properties": {
    "iso:country":"US",
    "sg:address":"994 Country Glen Ln",
    "sg:city":"Brentwood",
    "sg:classifiers":[
        {
            "category":"Retail",
            "subcategory":"Repair Shop",
            "type":"Services"
        }
    ],
    "sg:phone":"+1 925 240 9428",
    "sg:postcode":"94513",
    "sg:province":"CA",
    "sg:tags":[
        "repairing",
        "piano",
        "refinishing"
    ],
    "wof:name":"Franks Music Svc",
    "wof:placetype":"venue"
},
  "geometry": {"coordinates":[-121.71064699999999,37.947187],"type":"Point"}
}