{
  "type": "Feature",
  "properties": {
    "addr:full":"5070 Etiwanda Ave Mira Loma CA 91752",
    "addr:housenumber":"5070",
    "addr:postcode":"91752",
    "addr:street":"Etiwanda Ave",
    "iso:country":"US",
    "sg:address":"5070 Etiwanda Ave",
    "sg:city":"Mira Loma",
    "sg:classifiers":[
        {
            "category":"Autos & Motor Vehicles",
            "subcategory":"Auto Supplies",
            "type":"Retail Goods"
        }
    ],
    "sg:phone":"+1 951 681 9525",
    "sg:postcode":"91752",
    "sg:province":"CA",
    "sg:tags":[
        "tire"
    ],
    "wof:name":"Vanny's Auto Svc",
    "wof:placetype":"venue"
},
  "geometry": {"coordinates":[-117.523278,33.994003],"type":"Point"}
}