{
  "type": "Feature",
  "properties": {
    "addr:full":"1660 Hobart Blvd B Los Angeles CA 90027",
    "addr:housenumber":"1660",
    "addr:postcode":"90027",
    "addr:street":"Hobart Blvd B",
    "iso:country":"US",
    "sg:address":"1660 Hobart Blvd B",
    "sg:city":"Los Angeles",
    "sg:classifiers":[
        {
            "category":"Professional",
            "type":"Services"
        }
    ],
    "sg:phone":"+1 323 468 9176",
    "sg:postcode":"90027",
    "sg:province":"CA",
    "sg:website":"amigossegurosinsurance.com/index...",
    "wof:name":"Amigos Seguros Insurance",
    "wof:placetype":"venue"
},
  "geometry": {"coordinates":[-118.305645,34.10137],"type":"Point"}
}