{
  "type": "Feature",
  "properties": {
    "iso:country":"US",
    "sg:address":"18900 Stevens Creek Blvd",
    "sg:city":"Cupertino",
    "sg:classifiers":[
        {
            "category":"Insurance",
            "subcategory":"Insurance Agent",
            "type":"Services"
        }
    ],
    "sg:phone":"+1 408 973 9500",
    "sg:postcode":"95014",
    "sg:province":"CA",
    "wof:name":"R G Speno Inc",
    "wof:placetype":"venue"
},
  "geometry": {"coordinates":[-122.00437,37.32295],"type":"Point"}
}