{
  "type": "Feature",
  "properties": {
    "addr:full":"21522 Osborne St Canoga Park CA 91304",
    "addr:housenumber":"21522",
    "addr:postcode":"91304",
    "addr:street":"Osborne St",
    "iso:country":"US",
    "sg:address":"21522 Osborne St",
    "sg:city":"Canoga Park",
    "sg:classifiers":[
        {
            "category":"Autos & Motor Vehicles",
            "subcategory":"Motorcycle Sales",
            "type":"Retail Goods"
        }
    ],
    "sg:phone":"+1 818 701 5435",
    "sg:postcode":"91304",
    "sg:province":"CA",
    "sg:tags":[
        "scooter"
    ],
    "wof:name":"Sandrails Unlimited",
    "wof:placetype":"venue"
},
  "geometry": {"coordinates":[-118.60024900000001,34.23356],"type":"Point"}
}