{
  "type": "Feature",
  "properties": {
    "addr:full":"3037 Lakeshore Blvd Lakeport CA 95453",
    "addr:housenumber":"3037",
    "addr:postcode":"95453",
    "addr:street":"Lakeshore Blvd",
    "iso:country":"US",
    "sg:address":"3037 Lakeshore Blvd",
    "sg:city":"Lakeport",
    "sg:classifiers":[
        {
            "category":"Organizations",
            "subcategory":"Religious Organization",
            "type":"Services"
        }
    ],
    "sg:phone":"+1 707 263 3208",
    "sg:postcode":"95453",
    "sg:province":"CA",
    "sg:tags":[
        "church"
    ],
    "wof:name":"Lakeport Church Of Christ",
    "wof:placetype":"venue"
},
  "geometry": {"coordinates":[-122.913837,39.073041],"type":"Point"}
}