{
  "type": "Feature",
  "properties": {
    "addr:full":"5266 Iris Way Livermore CA 94551",
    "addr:housenumber":"5266",
    "addr:postcode":"94551",
    "addr:street":"Iris Way",
    "iso:country":"US",
    "sg:address":"5266 Iris Way",
    "sg:city":"Livermore",
    "sg:classifiers":[
        {
            "category":"Utilities",
            "subcategory":"Telephone",
            "type":"Services"
        }
    ],
    "sg:phone":"+1 925 449 2404",
    "sg:postcode":"94551",
    "sg:province":"CA",
    "sg:tags":[
        "installation",
        "system"
    ],
    "wof:name":"James J Communications",
    "wof:placetype":"venue"
},
  "geometry": {"coordinates":[-121.735918,37.713483],"type":"Point"}
}