{
  "type": "Feature",
  "properties": {
    "iso:country":"US",
    "sg:address":"27112 Sunnyridge Road",
    "sg:city":"Palos Verdes Peninsu",
    "sg:classifiers":[
        {
            "category":"Real Estate",
            "subcategory":"Real Estate Services",
            "type":"Services"
        }
    ],
    "sg:phone":"+1 310 377 3833",
    "sg:postcode":"90274",
    "sg:province":"CA",
    "wof:name":"Seals Earl K Realtor",
    "wof:placetype":"venue"
},
  "geometry": {"coordinates":[-118.354918,33.773289],"type":"Point"}
}