{
  "type": "Feature",
  "properties": {
    "iso:country":"US",
    "sg:address":"5650 District Blvd",
    "sg:city":"Bakersfield",
    "sg:classifiers":[
        {
            "category":"Professional",
            "type":"Services"
        }
    ],
    "sg:phone":"+1 661 831 1376",
    "sg:postcode":"93313",
    "sg:province":"CA",
    "wof:name":"MRB Bit Svc",
    "wof:placetype":"venue"
},
  "geometry": {"coordinates":[-119.065167,35.313133],"type":"Point"}
}