{
  "type": "Feature",
  "properties": {
    "iso:country":"US",
    "sg:address":"14642 Rancho Vista Dr",
    "sg:city":"Fontana",
    "sg:classifiers":[
        {
            "category":"Building & Trades",
            "subcategory":"Equipment Rental",
            "type":"Services"
        }
    ],
    "sg:phone":"+1 909 355 3600",
    "sg:postcode":"92335",
    "sg:province":"CA",
    "sg:tags":[
        "supply",
        "contractor"
    ],
    "wof:name":"Rd. Machinery",
    "wof:placetype":"venue"
},
  "geometry": {"coordinates":[-117.485783,34.089241],"type":"Point"}
}