{
  "type": "Feature",
  "properties": {
    "addr:full":"624 E Holt Blvd Ontario CA 91761",
    "addr:housenumber":"624",
    "addr:postcode":"91761",
    "addr:street":"E Holt Blvd",
    "iso:country":"US",
    "sg:address":"624 E Holt Blvd",
    "sg:city":"Ontario",
    "sg:classifiers":[
        {
            "category":"Shopping",
            "subcategory":"Used Merchandise",
            "type":"Retail Goods"
        }
    ],
    "sg:phone":"+1 909 460 1402",
    "sg:postcode":"91761",
    "sg:province":"CA",
    "wof:name":"Thrift Store",
    "wof:placetype":"venue"
},
  "geometry": {"coordinates":[-117.64214800000001,34.063308],"type":"Point"}
}