{
  "type": "Feature",
  "properties": {
    "addr:full":"8260 Mulholland Drive Los Angeles CA 90046",
    "addr:housenumber":"8260",
    "addr:postcode":"90046",
    "addr:street":"Mulholland Drive",
    "iso:country":"US",
    "sg:address":"8260 Mulholland Drive",
    "sg:city":"Los Angeles",
    "sg:classifiers":[
        {
            "category":"Park",
            "type":"Public Place"
        }
    ],
    "sg:phone":"+1 818 769 4415",
    "sg:postcode":"90046",
    "sg:province":"CA",
    "sg:website":"www.laparks.org/dos/parks/facili...",
    "wof:name":"Laurel Canyon Dog Park",
    "wof:placetype":"venue"
},
  "geometry": {"coordinates":[-118.37799800000001,34.122101],"type":"Point"}
}