{
  "type": "Feature",
  "properties": {
    "iso:country":"US",
    "sg:address":"17502 Gothard Street",
    "sg:city":"Huntington Beach",
    "sg:classifiers":[
        {
            "category":"Retail",
            "subcategory":"Auto Repair",
            "type":"Services"
        }
    ],
    "sg:phone":"+1 714 847 4448",
    "sg:postcode":"92647",
    "sg:province":"CA",
    "sg:website":"www.oconnellshb.com",
    "wof:name":"O'Connell's Automotive Service",
    "wof:placetype":"venue"
},
  "geometry": {"coordinates":[-118.000128,33.708321],"type":"Point"}
}