{
  "type": "Feature",
  "properties": {
    "iso:country":"US",
    "sg:address":"729 Colusa Ave",
    "sg:city":"Yuba City",
    "sg:classifiers":[
        {
            "category":"Shopping",
            "subcategory":"Crafts & Fabrics",
            "type":"Retail Goods"
        }
    ],
    "sg:phone":"+1 530 674 2221",
    "sg:postcode":"95991",
    "sg:province":"CA",
    "sg:tags":[
        "shop"
    ],
    "sg:website":"www.joann.com",
    "wof:name":"Jo-Ann Fabrics & Crafts",
    "wof:placetype":"venue"
},
  "geometry": {"coordinates":[-121.627852,39.141619],"type":"Point"}
}