{
  "type": "Feature",
  "properties": {
    "addr:full":"1018 Carolina Ave Clovis CA 93611",
    "addr:housenumber":"1018",
    "addr:postcode":"93611",
    "addr:street":"Carolina Ave",
    "iso:country":"US",
    "sg:address":"1018 Carolina Ave",
    "sg:city":"Clovis",
    "sg:classifiers":[
        {
            "category":"Professional",
            "subcategory":"Business Services",
            "type":"Services"
        }
    ],
    "sg:phone":"+1 559 271 2000",
    "sg:postcode":"93611",
    "sg:province":"CA",
    "sg:tags":[
        "eviction"
    ],
    "wof:name":"Speedy Eviction Svc",
    "wof:placetype":"venue"
},
  "geometry": {"coordinates":[-119.66534,36.818259],"type":"Point"}
}