{
  "type": "Feature",
  "properties": {
    "addr:full":"7300 Fulton Ave Unit B North Hollywood CA 91605",
    "addr:housenumber":"7300",
    "addr:postcode":"91605",
    "addr:street":"Fulton Ave Unit B",
    "iso:country":"US",
    "sg:address":"7300 Fulton Ave Unit B",
    "sg:city":"North Hollywood",
    "sg:classifiers":[
        {
            "category":"Building & Trades",
            "subcategory":"Construction",
            "type":"Services"
        }
    ],
    "sg:phone":"+1 818 764 8007",
    "sg:postcode":"91605",
    "sg:province":"CA",
    "sg:tags":[
        "contractor"
    ],
    "wof:name":"J C Construction",
    "wof:placetype":"venue"
},
  "geometry": {"coordinates":[-118.422997,34.202801],"type":"Point"}
}