{
  "type": "Feature",
  "properties": {
    "addr:full":"10327 E Alder Creek Rd Truckee CA 96161",
    "addr:housenumber":"10327",
    "addr:postcode":"96161",
    "addr:street":"E Alder Creek Rd",
    "iso:country":"US",
    "sg:address":"10327 E Alder Creek Rd",
    "sg:city":"Truckee",
    "sg:classifiers":[
        {
            "category":"Building & Trades",
            "subcategory":"Cleaning & Sanitation",
            "type":"Services"
        }
    ],
    "sg:phone":"+1 530 550 9558",
    "sg:postcode":"96161",
    "sg:province":"CA",
    "sg:tags":[
        "snow",
        "removal"
    ],
    "wof:name":"A & A Snow Blowing Svc",
    "wof:placetype":"venue"
},
  "geometry": {"coordinates":[-120.177105,39.369741],"type":"Point"}
}