{
  "type": "Feature",
  "properties": {
    "iso:country":"US",
    "sg:address":"31661 Via Cervantes",
    "sg:city":"San Juan Capistrano",
    "sg:classifiers":[
        {
            "category":"Professional",
            "type":"Services"
        }
    ],
    "sg:phone":"+1 949 240 1984",
    "sg:postcode":"92675",
    "sg:province":"CA",
    "wof:name":"Geosoft Inc",
    "wof:placetype":"venue"
},
  "geometry": {"coordinates":[-117.637201,33.503091],"type":"Point"}
}