{
  "type": "Feature",
  "properties": {
    "iso:country":"US",
    "sg:address":"3380 Somis Rd",
    "sg:city":"Somis",
    "sg:classifiers":[
        {
            "category":"Government",
            "subcategory":"Office",
            "type":"Public Place"
        }
    ],
    "sg:phone":"+1 805 386 4685",
    "sg:postcode":"93066",
    "sg:province":"CA",
    "wof:name":"Ventura County Resource",
    "wof:placetype":"venue"
},
  "geometry": {"coordinates":[-118.99611899999999,34.256521],"type":"Point"}
}