{
  "type": "Feature",
  "properties": {
    "iso:country":"US",
    "sg:address":"709 S Madera Ave",
    "sg:city":"Kerman",
    "sg:classifiers":[
        {
            "category":"Personal",
            "subcategory":"Beauty Salon",
            "type":"Services"
        }
    ],
    "sg:phone":"+1 559 846 9600",
    "sg:postcode":"93630",
    "sg:province":"CA",
    "wof:name":"Patricia's",
    "wof:placetype":"venue"
},
  "geometry": {"coordinates":[-120.060314,36.724474],"type":"Point"}
}