{
  "type": "Feature",
  "properties": {
    "addr:full":"709 S Madera Ave Kerman CA 93630",
    "addr:housenumber":"709",
    "addr:postcode":"93630",
    "addr:street":"S Madera Ave",
    "iso:country":"US",
    "sg:address":"709 S Madera Ave",
    "sg:city":"Kerman",
    "sg:classifiers":[
        {
            "category":"Personal",
            "subcategory":"Beauty Salon",
            "type":"Services"
        }
    ],
    "sg:phone":"+1 559 846 9600",
    "sg:postcode":"93630",
    "sg:province":"CA",
    "wof:name":"Patricia's",
    "wof:placetype":"venue"
},
  "geometry": {"coordinates":[-120.06031400000001,36.724474],"type":"Point"}
}