{
  "type": "Feature",
  "properties": {
    "iso:country":"US",
    "sg:address":"4999 Bradshaw Ct",
    "sg:city":"San Diego",
    "sg:classifiers":[
        {
            "category":"Building & Trades",
            "subcategory":"Construction",
            "type":"Services"
        }
    ],
    "sg:phone":"+1 858 794 7965",
    "sg:postcode":"92130",
    "sg:province":"CA",
    "sg:tags":[
        "handyman"
    ],
    "wof:name":"Handy 2 Have",
    "wof:placetype":"venue"
},
  "geometry": {"coordinates":[-117.207886,32.949078],"type":"Point"}
}