{
  "type": "Feature",
  "properties": {
    "iso:country":"US",
    "sg:address":"847 N Vail Ave",
    "sg:city":"Montebello",
    "sg:classifiers":[
        {
            "category":"Building & Trades",
            "subcategory":"Construction",
            "type":"Services"
        }
    ],
    "sg:phone":"+1 323 838 6463",
    "sg:postcode":"90640",
    "sg:province":"CA",
    "sg:tags":[
        "system",
        "specialty",
        "heating",
        "contractor",
        "air conditioning"
    ],
    "wof:name":"Cal Coast Air",
    "wof:placetype":"venue"
},
  "geometry": {"coordinates":[-118.116127,34.02697],"type":"Point"}
}