{
  "type": "Feature",
  "properties": {
    "iso:country":"US",
    "sg:address":"24875 Alessandro Blvd",
    "sg:city":"Moreno Valley",
    "sg:classifiers":[
        {
            "category":"Restaurant",
            "type":"Food & Drink"
        }
    ],
    "sg:phone":"+1 951 485 8687",
    "sg:postcode":"92553",
    "sg:province":"CA",
    "wof:name":"Little Beijing",
    "wof:placetype":"venue"
},
  "geometry": {"coordinates":[-117.22746600000001,33.917229],"type":"Point"}
}