{
  "type": "Feature",
  "properties": {
    "iso:country":"US",
    "sg:address":"7073 Tatler Rd",
    "sg:city":"Carlsbad",
    "sg:classifiers":[
        {
            "category":"Manufacturing",
            "subcategory":"Jewelry",
            "type":"Manufacturing & Wholesale Goods"
        }
    ],
    "sg:phone":"+1 760 929 9876",
    "sg:postcode":"92009",
    "sg:province":"CA",
    "sg:tags":[
        "costume",
        "mfg"
    ],
    "wof:name":"Watch Over ME",
    "wof:placetype":"venue"
},
  "geometry": {"coordinates":[-117.290403,33.104532],"type":"Point"}
}