{
  "type": "Feature",
  "properties": {
    "iso:country":"US",
    "sg:address":"455 E Cadena Dr",
    "sg:city":"Riverside",
    "sg:classifiers":[
        {
            "category":"Building & Trades",
            "subcategory":"Cleaning & Sanitation",
            "type":"Services"
        }
    ],
    "sg:phone":"+1 909 824 3141",
    "sg:postcode":"92501",
    "sg:province":"CA",
    "sg:tags":[
        "janitor"
    ],
    "wof:name":"Service Master Professional",
    "wof:placetype":"venue"
},
  "geometry": {"coordinates":[-117.34416899999999,34.012714],"type":"Point"}
}