{
  "type": "Feature",
  "properties": {
    "iso:country":"US",
    "sg:address":"1281 N Santa Fe Ave",
    "sg:city":"Vista",
    "sg:classifiers":[
        {
            "category":"Shopping",
            "subcategory":"Florist",
            "type":"Retail Goods"
        },
        {
            "category":"Shopping",
            "subcategory":"Gifts & Souvenirs",
            "type":"Retail Goods"
        }
    ],
    "sg:phone":"+1 760 945 7709",
    "sg:postcode":"92084",
    "sg:province":"CA",
    "sg:tags":[
        "shop"
    ],
    "wof:name":"Keb Gifts & Flowers",
    "wof:placetype":"venue"
},
  "geometry": {"coordinates":[-117.244792,33.217171],"type":"Point"}
}