{
  "type": "Feature",
  "properties": {
    "addr:full":"289 Stillman Ave Upland CA 91786",
    "addr:housenumber":"289",
    "addr:postcode":"91786",
    "addr:street":"Stillman Ave",
    "iso:country":"US",
    "sg:address":"289 Stillman Ave",
    "sg:city":"Upland",
    "sg:classifiers":[
        {
            "category":"Building & Trades",
            "subcategory":"Landscaping Services",
            "type":"Services"
        }
    ],
    "sg:phone":"+1 951 505 8270",
    "sg:postcode":"91786",
    "sg:province":"CA",
    "wof:name":"F G Landscape Services",
    "wof:placetype":"venue"
},
  "geometry": {"coordinates":[-117.67385400000001,34.08984],"type":"Point"}
}