{
  "type": "Feature",
  "properties": {
    "iso:country":"US",
    "sg:address":"17509 Ventura Blvd",
    "sg:city":"Encino",
    "sg:classifiers":[
        {
            "category":"Banks & Credit Unions",
            "subcategory":"Bank",
            "type":"Services"
        }
    ],
    "sg:phone":"+1 818 528 3933",
    "sg:postcode":"91316",
    "sg:province":"CA",
    "sg:tags":[
        "escrow"
    ],
    "wof:name":"Encore Escrow",
    "wof:placetype":"venue"
},
  "geometry": {"coordinates":[-118.516952,34.162078],"type":"Point"}
}