{
  "type": "Feature",
  "properties": {
    "iso:country":"US",
    "sg:address":"21 Grant St",
    "sg:city":"Redlands",
    "sg:classifiers":[
        {
            "category":"Government",
            "subcategory":"Office",
            "type":"Public Place"
        }
    ],
    "sg:phone":"+1 909 798 7550",
    "sg:postcode":"92373",
    "sg:province":"CA",
    "sg:tags":[
        "village"
    ],
    "wof:name":"Joslyn Senior Ctr",
    "wof:placetype":"venue"
},
  "geometry": {"coordinates":[-117.185492,34.053631],"type":"Point"}
}