{
  "type": "Feature",
  "properties": {
    "addr:full":"9710 Woodman Ave Pacoima CA 91331",
    "addr:housenumber":"9710",
    "addr:postcode":"91331",
    "addr:street":"Woodman Ave",
    "iso:country":"US",
    "sg:address":"9710 Woodman Ave",
    "sg:city":"Pacoima",
    "sg:classifiers":[
        {
            "category":"Wholesale",
            "subcategory":"Groceries",
            "type":"Manufacturing & Wholesale Goods"
        }
    ],
    "sg:phone":"+1 818 897 6797",
    "sg:postcode":"91331",
    "sg:province":"CA",
    "wof:name":"Jugomix",
    "wof:placetype":"venue"
},
  "geometry": {"coordinates":[-118.447204,34.245426],"type":"Point"}
}