{
  "type": "Feature",
  "properties": {
    "addr:full":"3133 Ad Art Rd Stockton CA 95215",
    "addr:postcode":"3133;95215",
    "addr:street":"Art Rd",
    "iso:country":"US",
    "sg:address":"3133 Ad Art Rd",
    "sg:city":"Stockton",
    "sg:classifiers":[
        {
            "category":"Manufacturing",
            "subcategory":"Tools & Machinery",
            "type":"Manufacturing & Wholesale Goods"
        }
    ],
    "sg:phone":"+1 209 931 4282",
    "sg:postcode":"95215",
    "sg:province":"CA",
    "sg:tags":[
        "construction"
    ],
    "wof:name":"Mc Neilus Truck & Mfg Inc",
    "wof:placetype":"venue"
},
  "geometry": {"coordinates":[-121.25140500000001,37.993216],"type":"Point"}
}