{
  "type": "Feature",
  "properties": {
    "iso:country":"US",
    "sg:address":"1441 Detroit Ave",
    "sg:city":"Concord",
    "sg:classifiers":[
        {
            "category":"Building & Trades",
            "subcategory":"Construction",
            "type":"Services"
        }
    ],
    "sg:phone":"+1 925 349 6632",
    "sg:postcode":"94520",
    "sg:province":"CA",
    "sg:tags":[
        "concrete",
        "contractor"
    ],
    "wof:name":"Hansen's Concrete",
    "wof:placetype":"venue"
},
  "geometry": {"coordinates":[-122.041094,37.967885],"type":"Point"}
}