{
  "type": "Feature",
  "properties": {
    "addr:full":"2615 L St Eureka CA 95501",
    "addr:housenumber":"2615",
    "addr:postcode":"95501",
    "addr:street":"L St",
    "iso:country":"US",
    "sg:address":"2615 L St",
    "sg:city":"Eureka",
    "sg:classifiers":[
        {
            "category":"Professional",
            "subcategory":"Business Services",
            "type":"Services"
        }
    ],
    "sg:phone":"+1 707 445 2887",
    "sg:postcode":"95501",
    "sg:province":"CA",
    "sg:tags":[
        "interior",
        "consultant",
        "design",
        "decorator"
    ],
    "wof:name":"Sandra Greenleaf Interior",
    "wof:placetype":"venue"
},
  "geometry": {"coordinates":[-124.156638,40.784343],"type":"Point"}
}