{
  "type": "Feature",
  "properties": {
    "iso:country":"US",
    "sg:address":"42319 Winchester Rd",
    "sg:city":"Temecula",
    "sg:classifiers":[
        {
            "category":"Wholesale",
            "subcategory":"Electrical",
            "type":"Manufacturing & Wholesale Goods"
        }
    ],
    "sg:phone":"+1 951 491 0546",
    "sg:postcode":"92590",
    "sg:province":"CA",
    "sg:tags":[
        "equipment",
        "electronic",
        "supply"
    ],
    "wof:name":"Royal Distributors Inc",
    "wof:placetype":"venue"
},
  "geometry": {"coordinates":[-117.171001,33.514071],"type":"Point"}
}