{
  "type": "Feature",
  "properties": {
    "addr:full":"27083 Strawberry Ln Helendale CA 92342",
    "addr:housenumber":"27083",
    "addr:postcode":"92342",
    "addr:street":"Strawberry Ln",
    "iso:country":"US",
    "sg:address":"27083 Strawberry Ln",
    "sg:city":"Helendale",
    "sg:classifiers":[
        {
            "category":"Organizations",
            "subcategory":"Religious Organization",
            "type":"Services"
        }
    ],
    "sg:phone":"+1 760 243 4396",
    "sg:postcode":"92342",
    "sg:province":"CA",
    "sg:tags":[
        "church"
    ],
    "sg:website":"www.gbcsl.com",
    "wof:name":"Grace Bible Church",
    "wof:placetype":"venue"
},
  "geometry": {"coordinates":[-117.33745399999999,34.743596],"type":"Point"}
}