{
  "type": "Feature",
  "properties": {
    "iso:country":"US",
    "sg:address":"2459 Fruitvale Ave",
    "sg:city":"Bakersfield",
    "sg:classifiers":[
        {
            "category":"Manufacturing",
            "subcategory":"Metals",
            "type":"Manufacturing & Wholesale Goods"
        }
    ],
    "sg:phone":"+1 661 321 9200",
    "sg:postcode":"93308",
    "sg:province":"CA",
    "sg:tags":[
        "steel"
    ],
    "sg:website":"www.spacetronlaser.com",
    "wof:name":"Spacetron Inc",
    "wof:placetype":"venue"
},
  "geometry": {"coordinates":[-119.07451399999999,35.380398],"type":"Point"}
}