{
  "type": "Feature",
  "properties": {
    "addr:full":"2661 Gravenstein Hwy S Sebastopol CA 95472",
    "addr:housenumber":"2661",
    "addr:postcode":"95472",
    "addr:street":"Gravenstein Hwy S",
    "iso:country":"US",
    "sg:address":"2661 Gravenstein Hwy S",
    "sg:city":"Sebastopol",
    "sg:classifiers":[
        {
            "category":"Building & Trades",
            "subcategory":"Construction",
            "type":"Services"
        }
    ],
    "sg:phone":"+1 707 829 2636",
    "sg:postcode":"95472",
    "sg:province":"CA",
    "sg:tags":[
        "maker",
        "cabinet"
    ],
    "wof:name":"Woodencraft",
    "wof:placetype":"venue"
},
  "geometry": {"coordinates":[-122.791466,38.374534],"type":"Point"}
}