{
  "type": "Feature",
  "properties": {
    "iso:country":"US",
    "sg:address":"157 Southwest Blvd",
    "sg:city":"Rohnert Park",
    "sg:classifiers":[
        {
            "category":"Restaurant",
            "type":"Food & Drink"
        }
    ],
    "sg:phone":"+1 707 793 7849",
    "sg:postcode":"94928",
    "sg:province":"CA",
    "wof:name":"Cerrano's",
    "wof:placetype":"venue"
},
  "geometry": {"coordinates":[-122.708259,38.335947],"type":"Point"}
}