{
  "type": "Feature",
  "properties": {
    "addr:full":"940 Terminal Way San Carlos CA 94070",
    "addr:housenumber":"940",
    "addr:postcode":"94070",
    "addr:street":"Terminal Way",
    "iso:country":"US",
    "sg:address":"940 Terminal Way",
    "sg:city":"San Carlos",
    "sg:classifiers":[
        {
            "category":"Professional",
            "subcategory":"Management & Consulting",
            "type":"Services"
        }
    ],
    "sg:phone":"+1 650 610 0993",
    "sg:postcode":"94070",
    "sg:province":"CA",
    "sg:tags":[
        "food",
        "facility"
    ],
    "wof:name":"Restaurant Environmental Svc",
    "wof:placetype":"venue"
},
  "geometry": {"coordinates":[-122.254807,37.507706],"type":"Point"}
}