{
  "type": "Feature",
  "properties": {
    "addr:full":"1346 Muscat Cir Roseville CA 95747",
    "addr:housenumber":"1346",
    "addr:postcode":"95747",
    "addr:street":"Muscat Cir",
    "iso:country":"US",
    "sg:address":"1346 Muscat Cir",
    "sg:city":"Roseville",
    "sg:classifiers":[
        {
            "category":"Communications",
            "subcategory":"Film & Video Production",
            "type":"Services"
        }
    ],
    "sg:phone":"+1 916 788 1690",
    "sg:postcode":"95747",
    "sg:province":"CA",
    "sg:tags":[
        "taping"
    ],
    "wof:name":"Acti-Video Svc",
    "wof:placetype":"venue"
},
  "geometry": {"coordinates":[-121.313176,38.745683],"type":"Point"}
}