{
  "type": "Feature",
  "properties": {
    "iso:country":"US",
    "sg:address":"8976 Rosetta Cir",
    "sg:city":"Sacramento",
    "sg:classifiers":[
        {
            "category":"Manufacturing",
            "subcategory":"Musical Instruments",
            "type":"Manufacturing & Wholesale Goods"
        }
    ],
    "sg:phone":"+1 916 366 3919",
    "sg:postcode":"95826",
    "sg:province":"CA",
    "wof:name":"Gardner Guitars",
    "wof:placetype":"venue"
},
  "geometry": {"coordinates":[-121.371154,38.544468],"type":"Point"}
}