{
  "type": "Feature",
  "properties": {
    "iso:country":"US",
    "sg:address":"3824 E Roberta Dr",
    "sg:city":"Orange",
    "sg:classifiers":[
        {
            "category":"Personal",
            "subcategory":"Beauty Salon",
            "type":"Services"
        }
    ],
    "sg:phone":"+1 714 504 8113",
    "sg:postcode":"92869",
    "sg:province":"CA",
    "wof:name":"Aaahh Some Hair",
    "wof:placetype":"venue"
},
  "geometry": {"coordinates":[-117.812745,33.78333],"type":"Point"}
}