{
  "type": "Feature",
  "properties": {
    "iso:country":"US",
    "sg:address":"24 Robert Pl",
    "sg:city":"Millbrae",
    "sg:classifiers":[
        {
            "category":"Manufacturing",
            "subcategory":"Food",
            "type":"Manufacturing & Wholesale Goods"
        }
    ],
    "sg:phone":"+1 650 697 0584",
    "sg:postcode":"94030",
    "sg:province":"CA",
    "sg:tags":[
        "mfg",
        "salad",
        "dressing"
    ],
    "wof:name":"Sierras Food Products",
    "wof:placetype":"venue"
},
  "geometry": {"coordinates":[-122.39977500000001,37.603736],"type":"Point"}
}