{
  "type": "Feature",
  "properties": {
    "addr:full":"1068 Center St San Carlos CA 94070",
    "addr:housenumber":"1068",
    "addr:postcode":"94070",
    "addr:street":"Center St",
    "iso:country":"US",
    "sg:address":"1068 Center St",
    "sg:city":"San Carlos",
    "sg:classifiers":[
        {
            "category":"Home & Garden",
            "subcategory":"Building Materials",
            "type":"Retail Goods"
        }
    ],
    "sg:phone":"+1 650 592 4917",
    "sg:postcode":"94070",
    "sg:province":"CA",
    "sg:tags":[
        "door"
    ],
    "sg:website":"www.pioneermillwork.com",
    "wof:name":"Pioneer Millwork Inc",
    "wof:placetype":"venue"
},
  "geometry": {"coordinates":[-122.24695699999999,37.498216],"type":"Point"}
}