{
  "type": "Feature",
  "properties": {
    "addr:full":"13345 Artesia Blvd Cerritos CA 90703",
    "addr:postcode":"13345;ca 90703",
    "addr:street":"Artesia Blvd",
    "iso:country":"US",
    "sg:address":"13345 Artesia Blvd",
    "sg:city":"Cerritos",
    "sg:classifiers":[
        {
            "category":"Health Services",
            "subcategory":"Doctor",
            "type":"Services"
        }
    ],
    "sg:phone":"+1 562 926 3354",
    "sg:postcode":"90703",
    "sg:province":"CA",
    "sg:tags":[
        "surgeon",
        "oral"
    ],
    "wof:name":"Nguyen Toan DDS",
    "wof:placetype":"venue"
},
  "geometry": {"coordinates":[-118.046997,33.873501],"type":"Point"}
}