{
  "type": "Feature",
  "properties": {
    "iso:country":"US",
    "sg:address":"2299 Union St",
    "sg:city":"San Francisco",
    "sg:classifiers":[
        {
            "category":"Restaurant",
            "type":"Food & Drink"
        }
    ],
    "sg:phone":"+1 415 921 3990",
    "sg:postcode":"94123",
    "sg:province":"CA",
    "sg:tags":[
        "sandwich"
    ],
    "wof:name":"Marina Submarine",
    "wof:placetype":"venue"
},
  "geometry": {"coordinates":[-122.43549,37.797089],"type":"Point"}
}