{
  "type": "Feature",
  "properties": {
    "addr:full":"1124 Main St Irvine CA 92614",
    "addr:housenumber":"1124",
    "addr:postcode":"92614",
    "addr:street":"Main St",
    "iso:country":"US",
    "sg:address":"1124 Main St",
    "sg:city":"Irvine",
    "sg:classifiers":[
        {
            "category":"Communications",
            "subcategory":"Film & Video Production",
            "type":"Services"
        }
    ],
    "sg:phone":"+1 949 752 7761",
    "sg:postcode":"92614",
    "sg:province":"CA",
    "sg:tags":[
        "taping"
    ],
    "sg:website":"www.roycemultimedia.com",
    "wof:name":"Royce Multimedia",
    "wof:placetype":"venue"
},
  "geometry": {"coordinates":[-117.86723000000001,33.691211],"type":"Point"}
}