{
  "type": "Feature",
  "properties": {
    "iso:country":"US",
    "sg:address":"340 F St",
    "sg:city":"Davis",
    "sg:classifiers":[
        {
            "category":"Banks & Credit Unions",
            "subcategory":"Bank",
            "type":"Services"
        }
    ],
    "sg:phone":"+1 530 756 7660",
    "sg:postcode":"95616",
    "sg:province":"CA",
    "wof:name":"Wells Fargo Bank",
    "wof:placetype":"venue"
},
  "geometry": {"coordinates":[-121.740519,38.545507],"type":"Point"}
}