{
  "type": "Feature",
  "properties": {
    "iso:country":"US",
    "sg:address":"11150 International Dr Suite 100",
    "sg:city":"Rancho Cordova",
    "sg:classifiers":[
        {
            "category":"Insurance",
            "subcategory":"Hazard Insurance",
            "type":"Services"
        }
    ],
    "sg:phone":"+1 916 636 1534",
    "sg:postcode":"95670",
    "sg:province":"CA",
    "wof:name":"Mercury Insurance Group",
    "wof:placetype":"venue"
},
  "geometry": {"coordinates":[-121.272639,38.583217],"type":"Point"}
}