{
  "type": "Feature",
  "properties": {
    "iso:country":"US",
    "sg:address":"8338 N Lake Blvd",
    "sg:city":"Kings Beach",
    "sg:classifiers":[
        {
            "category":"Home & Garden",
            "subcategory":"Furniture",
            "type":"Retail Goods"
        }
    ],
    "sg:phone":"+1 530 546 0358",
    "sg:postcode":"96143",
    "sg:province":"CA",
    "sg:tags":[
        "store"
    ],
    "wof:name":"Inside Outfitters",
    "wof:placetype":"venue"
},
  "geometry": {"coordinates":[-120.03600299999999,39.276199],"type":"Point"}
}