{
  "type": "Feature",
  "properties": {
    "iso:country":"US",
    "sg:address":"6001 S Vermont Ave",
    "sg:city":"Los Angeles",
    "sg:classifiers":[
        {
            "category":"Health Services",
            "subcategory":"Health Practitioner",
            "type":"Services"
        }
    ],
    "sg:phone":"+1 323 778 8994",
    "sg:postcode":"90044",
    "sg:province":"CA",
    "sg:tags":[
        "nutritionist"
    ],
    "wof:name":"Aly's Nutricion",
    "wof:placetype":"venue"
},
  "geometry": {"coordinates":[-118.29148000000001,33.9855],"type":"Point"}
}