{
  "type": "Feature",
  "properties": {
    "addr:full":"5600 Nicasio Valley Rd Nicasio CA 94946",
    "addr:postcode":"5600;94946",
    "addr:street":"Nicasio Valley Rd",
    "iso:country":"US",
    "sg:address":"5600 Nicasio Valley Rd",
    "sg:city":"Nicasio",
    "sg:classifiers":[
        {
            "category":"Government",
            "subcategory":"Office",
            "type":"Public Place"
        }
    ],
    "sg:phone":"+1 415 446 4421",
    "sg:postcode":"94946",
    "sg:province":"CA",
    "sg:tags":[
        "management"
    ],
    "wof:name":"West Marin Public Works",
    "wof:placetype":"venue"
},
  "geometry": {"coordinates":[-122.70341000000001,38.068685],"type":"Point"}
}