{
  "type": "Feature",
  "properties": {
    "addr:full":"25761 Obrero Dr Ste G Mission Viejo CA 92691",
    "addr:postcode":"25761;92691",
    "addr:street":"Obrero Dr Ste G",
    "iso:country":"US",
    "sg:address":"25761 Obrero Dr Ste G",
    "sg:city":"Mission Viejo",
    "sg:classifiers":[
        {
            "category":"Retail",
            "subcategory":"Auto Repair",
            "type":"Services"
        }
    ],
    "sg:phone":"+1 949 455 9388",
    "sg:postcode":"92691",
    "sg:province":"CA",
    "wof:name":"Ag Automotive",
    "wof:placetype":"venue"
},
  "geometry": {"coordinates":[-117.681999,33.6185],"type":"Point"}
}