{
  "type": "Feature",
  "properties": {
    "iso:country":"US",
    "sg:address":"121 Paul Dr",
    "sg:city":"San Rafael",
    "sg:classifiers":[
        {
            "category":"Banks & Credit Unions",
            "subcategory":"Bank",
            "type":"Services"
        }
    ],
    "sg:phone":"+1 415 491 2300",
    "sg:postcode":"94903",
    "sg:province":"CA",
    "sg:tags":[
        "loan",
        "real estate"
    ],
    "wof:name":"Sonoma Marin Realty & Finance",
    "wof:placetype":"venue"
},
  "geometry": {"coordinates":[-122.536871,38.019302],"type":"Point"}
}