{
  "type": "Feature",
  "properties": {
    "addr:full":"625 S San Pedro St Los Angeles CA 90014",
    "addr:housenumber":"625",
    "addr:postcode":"90014",
    "addr:street":"S San Pedro St",
    "iso:country":"US",
    "sg:address":"625 S San Pedro St",
    "sg:city":"Los Angeles",
    "sg:classifiers":[
        {
            "category":"Wholesale",
            "subcategory":"Electrical",
            "type":"Manufacturing & Wholesale Goods"
        }
    ],
    "sg:phone":"+1 213 622 0025",
    "sg:postcode":"90014",
    "sg:province":"CA",
    "sg:tags":[
        "machine",
        "sewing"
    ],
    "wof:name":"Zeal Inc",
    "wof:placetype":"venue"
},
  "geometry": {"coordinates":[-118.246499,34.041125],"type":"Point"}
}