{
  "type": "Feature",
  "properties": {
    "addr:full":"81812 Doctor Carreon Blvd Indio CA 92201",
    "addr:postcode":"81812;92201",
    "addr:street":"Doctor Carreon Blvd",
    "iso:country":"US",
    "sg:address":"81812 Doctor Carreon Blvd",
    "sg:city":"Indio",
    "sg:classifiers":[
        {
            "category":"Health Services",
            "subcategory":"Doctor",
            "type":"Services"
        }
    ],
    "sg:phone":"+1 760 775 0560",
    "sg:postcode":"92201",
    "sg:province":"CA",
    "sg:tags":[
        "physician",
        "surgeon"
    ],
    "wof:name":"Lander Comprehensive Urology",
    "wof:placetype":"venue"
},
  "geometry": {"coordinates":[-116.242414,33.707455],"type":"Point"}
}