{
  "type": "Feature",
  "properties": {
    "addr:full":"2337 S el Camino Real San Mateo CA 94403",
    "addr:housenumber":"2337",
    "addr:postcode":"94403",
    "addr:street":"S El Camino Real",
    "iso:country":"US",
    "sg:address":"2337 S el Camino Real",
    "sg:city":"San Mateo",
    "sg:classifiers":[
        {
            "category":"Retail",
            "subcategory":"Portrait Studio",
            "type":"Services"
        }
    ],
    "sg:phone":"+1 650 345 8377",
    "sg:postcode":"94403",
    "sg:province":"CA",
    "sg:tags":[
        "photographer"
    ],
    "wof:name":"Studio 1 & 2",
    "wof:placetype":"venue"
},
  "geometry": {"coordinates":[-122.30652499999999,37.545422],"type":"Point"}
}