{
  "type": "Feature",
  "properties": {
    "iso:country":"US",
    "sg:address":"3551 Monte Real",
    "sg:city":"Escondido",
    "sg:classifiers":[
        {
            "category":"Professional",
            "subcategory":"Management & Consulting",
            "type":"Services"
        }
    ],
    "sg:phone":"+1 760 233 8006",
    "sg:postcode":"92029",
    "sg:province":"CA",
    "sg:tags":[
        "consultant",
        "business"
    ],
    "wof:name":"Krishon Consulting Group",
    "wof:placetype":"venue"
},
  "geometry": {"coordinates":[-117.075867,33.064049],"type":"Point"}
}