{
  "type": "Feature",
  "properties": {
    "addr:full":"17100 Pioneer Blvd Ste 195 Artesia CA 90701",
    "addr:housenumber":"17100",
    "addr:postcode":"90701",
    "addr:street":"Pioneer Blvd Ste 195",
    "iso:country":"US",
    "sg:address":"17100 Pioneer Blvd Ste 195",
    "sg:city":"Artesia",
    "sg:classifiers":[
        {
            "category":"Real Estate",
            "subcategory":"Real Estate Services",
            "type":"Services"
        },
        {
            "category":"Banks & Credit Unions",
            "subcategory":"Investment Brokerage",
            "type":"Services"
        }
    ],
    "sg:phone":"+1 562 402 2686",
    "sg:postcode":"90701",
    "sg:province":"CA",
    "sg:tags":[
        "investing"
    ],
    "sg:website":"www.BizBizBiz.com",
    "wof:name":"VR Business Brokers",
    "wof:placetype":"venue"
},
  "geometry": {"coordinates":[-118.082217,33.875225],"type":"Point"}
}