{
  "type": "Feature",
  "properties": {
    "addr:full":"1917 1st St Bakersfield CA 93304",
    "addr:housenumber":"1917",
    "addr:postcode":"93304",
    "addr:street":"1St St",
    "iso:country":"US",
    "sg:address":"1917 1st St",
    "sg:city":"Bakersfield",
    "sg:classifiers":[
        {
            "category":"Professional",
            "subcategory":"Business Services",
            "type":"Services"
        }
    ],
    "sg:phone":"+1 661 342 2402",
    "sg:postcode":"93304",
    "sg:province":"CA",
    "sg:tags":[
        "glass"
    ],
    "wof:name":"Board Em-Up",
    "wof:placetype":"venue"
},
  "geometry": {"coordinates":[-119.025358,35.354908],"type":"Point"}
}