{
  "type": "Feature",
  "properties": {
    "addr:full":"1649 El Prado San Diego CA 92101",
    "addr:housenumber":"1649",
    "addr:postcode":"92101",
    "addr:street":"El",
    "iso:country":"US",
    "sg:address":"1649 El Prado",
    "sg:city":"San Diego",
    "sg:classifiers":[
        {
            "category":"Museum",
            "type":"Entertainment"
        }
    ],
    "sg:phone":"+1 619 238 7559",
    "sg:postcode":"92101",
    "sg:province":"CA",
    "sg:website":"www.mopa.org",
    "wof:name":"Museum Of Photographic Arts",
    "wof:placetype":"venue"
},
  "geometry": {"coordinates":[-117.149002,32.7313],"type":"Point"}
}