{
  "type": "Feature",
  "properties": {
    "iso:country":"US",
    "sg:address":"36464 Fremont Blvd",
    "sg:city":"Fremont",
    "sg:classifiers":[
        {
            "category":"Wholesale",
            "subcategory":"Non-durable Goods",
            "type":"Manufacturing & Wholesale Goods"
        }
    ],
    "sg:phone":"+1 510 792 8500",
    "sg:postcode":"94536",
    "sg:province":"CA",
    "wof:name":"Siddhartha International",
    "wof:placetype":"venue"
},
  "geometry": {"coordinates":[-122.018345,37.563978],"type":"Point"}
}