{
  "type": "Feature",
  "properties": {
    "addr:full":"6309 Watt Ave North Highlands CA 95660",
    "addr:housenumber":"6309",
    "addr:postcode":"95660",
    "addr:street":"Watt Ave",
    "iso:country":"US",
    "sg:address":"6309 Watt Ave",
    "sg:city":"North Highlands",
    "sg:classifiers":[
        {
            "category":"Retail",
            "subcategory":"Auto Repair",
            "type":"Services"
        }
    ],
    "sg:phone":"+1 916 331 6534",
    "sg:postcode":"95660",
    "sg:province":"CA",
    "sg:tags":[
        "repairing",
        "automobile"
    ],
    "wof:name":"Auto Repairs For Less",
    "wof:placetype":"venue"
},
  "geometry": {"coordinates":[-121.382949,38.6808],"type":"Point"}
}