{
  "type": "Feature",
  "properties": {
    "iso:country":"US",
    "sg:address":"4435 Crestwood Cir",
    "sg:city":"Concord",
    "sg:classifiers":[
        {
            "category":"Shopping",
            "type":"Retail Goods"
        }
    ],
    "sg:phone":"+1 925 686 4036",
    "sg:postcode":"94521",
    "sg:province":"CA",
    "sg:tags":[
        "pet",
        "food",
        "supply"
    ],
    "wof:name":"Bj's Dog Stuff",
    "wof:placetype":"venue"
},
  "geometry": {"coordinates":[-121.979939,37.975081],"type":"Point"}
}