{
  "type": "Feature",
  "properties": {
    "iso:country":"US",
    "sg:address":"2661 Strozier Ave",
    "sg:city":"El Monte",
    "sg:classifiers":[
        {
            "category":"Animal Shelter",
            "type":"Public Place"
        },
        {
            "category":"Retail",
            "subcategory":"Pet Boarding",
            "type":"Services"
        }
    ],
    "sg:phone":"+1 626 444 9664",
    "sg:postcode":"91733",
    "sg:province":"CA",
    "sg:tags":[
        "boarding/pet",
        "sitting"
    ],
    "sg:website":"www.beaglesandbuddies.com",
    "wof:name":"Beagles & Buddies Dog Rescue",
    "wof:placetype":"venue"
},
  "geometry": {"coordinates":[-118.050003,34.060699],"type":"Point"}
}