{
  "type": "Feature",
  "properties": {
    "addr:full":"950 King Plz Ste 103 Daly City CA 94015",
    "addr:housenumber":"950",
    "addr:postcode":"94015",
    "addr:street":"King Plz Ste 103",
    "iso:country":"US",
    "sg:address":"950 King Plz Ste 103",
    "sg:city":"Daly City",
    "sg:classifiers":[
        {
            "category":"Shopping",
            "subcategory":"Florist",
            "type":"Retail Goods"
        }
    ],
    "sg:phone":"+1 650 754 9814",
    "sg:postcode":"94015",
    "sg:province":"CA",
    "wof:name":"Veronica's Salon & Flowers",
    "wof:placetype":"venue"
},
  "geometry": {"coordinates":[-122.468495,37.650509],"type":"Point"}
}