{
  "type": "Feature",
  "properties": {
    "addr:full":"698 Mowry Ave Fremont CA 94536",
    "addr:housenumber":"698",
    "addr:postcode":"94536",
    "addr:street":"Mowry Ave",
    "iso:country":"US",
    "sg:address":"698 Mowry Ave",
    "sg:city":"Fremont",
    "sg:classifiers":[
        {
            "category":"Health Services",
            "subcategory":"Doctor",
            "type":"Services"
        }
    ],
    "sg:phone":"+1 510 608 6097",
    "sg:postcode":"94536",
    "sg:province":"CA",
    "sg:tags":[
        "dentist"
    ],
    "wof:name":"Angelita Yumena DDS",
    "wof:placetype":"venue"
},
  "geometry": {"coordinates":[-121.973896,37.567022],"type":"Point"}
}