{
  "type": "Feature",
  "properties": {
    "addr:full":"10600 Dawson Canyon Rd Corona CA 92883",
    "addr:housenumber":"10600",
    "addr:postcode":"92883",
    "addr:street":"Dawson Canyon Rd",
    "iso:country":"US",
    "sg:address":"10600 Dawson Canyon Rd",
    "sg:city":"Corona",
    "sg:classifiers":[
        {
            "category":"Wholesale",
            "subcategory":"Machinery & Supplies",
            "type":"Manufacturing & Wholesale Goods"
        }
    ],
    "sg:phone":"+1 951 277 7820",
    "sg:postcode":"92883",
    "sg:province":"CA",
    "sg:tags":[
        "pulverizing",
        "crushing"
    ],
    "wof:name":"Cooley Equipment Corp",
    "wof:placetype":"venue"
},
  "geometry": {"coordinates":[-117.466295,33.783244],"type":"Point"}
}