{
  "type": "Feature",
  "properties": {
    "addr:full":"782 San Carlos Ave Mountain View CA 94043",
    "addr:housenumber":"782",
    "addr:postcode":"94043",
    "addr:street":"San Carlos Ave",
    "iso:country":"US",
    "sg:address":"782 San Carlos Ave",
    "sg:city":"Mountain View",
    "sg:classifiers":[
        {
            "category":"Organizations",
            "subcategory":"Religious Organization",
            "type":"Services"
        }
    ],
    "sg:phone":"+1 650 967 6200",
    "sg:postcode":"94043",
    "sg:province":"CA",
    "sg:tags":[
        "church"
    ],
    "wof:name":"Jehovah's Witnesses Hall",
    "wof:placetype":"venue"
},
  "geometry": {"coordinates":[-122.071062,37.404901],"type":"Point"}
}