{
  "type": "Feature",
  "properties": {
    "addr:full":"1170 Spokane Dr San Jose CA 95122",
    "addr:housenumber":"1170",
    "addr:postcode":"95122",
    "addr:street":"Spokane Dr",
    "iso:country":"US",
    "sg:address":"1170 Spokane Dr",
    "sg:city":"San Jose",
    "sg:classifiers":[
        {
            "category":"Building & Trades",
            "subcategory":"Construction",
            "type":"Services"
        }
    ],
    "sg:phone":"+1 408 225 8838",
    "sg:postcode":"95122",
    "sg:province":"CA",
    "sg:tags":[
        "resurfacing",
        "laying",
        "refinishing",
        "floor"
    ],
    "wof:name":"D & N Hardwood Floors",
    "wof:placetype":"venue"
},
  "geometry": {"coordinates":[-121.837755,37.318888],"type":"Point"}
}