{
  "type": "Feature",
  "properties": {
    "addr:full":"6690 Foothill Blvd Oakland CA 94605",
    "addr:housenumber":"6690",
    "addr:postcode":"94605",
    "addr:street":"Foothill Blvd",
    "iso:country":"US",
    "sg:address":"6690 Foothill Blvd",
    "sg:city":"Oakland",
    "sg:classifiers":[
        {
            "category":"Retail",
            "subcategory":"Funeral Services",
            "type":"Services"
        }
    ],
    "sg:phone":"+1 510 632 5232",
    "sg:postcode":"94605",
    "sg:province":"CA",
    "sg:tags":[
        "cemetery"
    ],
    "wof:name":"Caporgno & Co Evergreen Chapel Mortuary",
    "wof:placetype":"venue"
},
  "geometry": {"coordinates":[-122.18000000000001,37.7701],"type":"Point"}
}