{
  "type": "Feature",
  "properties": {
    "iso:country":"US",
    "sg:address":"9593 Shimizu River Cir",
    "sg:city":"Fountain Valley",
    "sg:classifiers":[
        {
            "category":"Professional",
            "type":"Services"
        }
    ],
    "sg:phone":"+1 714 963 7436",
    "sg:postcode":"92708",
    "sg:province":"CA",
    "wof:name":"Cap Anchor Systems",
    "wof:placetype":"venue"
},
  "geometry": {"coordinates":[-117.959635,33.687449],"type":"Point"}
}