{
  "type": "Feature",
  "properties": {
    "iso:country":"US",
    "sg:address":"27487 Diane Marie Cir",
    "sg:city":"Santa Clarita",
    "sg:classifiers":[
        {
            "category":"Building & Trades",
            "subcategory":"Construction",
            "type":"Services"
        }
    ],
    "sg:phone":"+1 661 296 9890",
    "sg:postcode":"91350",
    "sg:province":"CA",
    "sg:tags":[
        "contractor"
    ],
    "wof:name":"Santa Clarita Builders Corp",
    "wof:placetype":"venue"
},
  "geometry": {"coordinates":[-118.512343,34.439785],"type":"Point"}
}