{
  "type": "Feature",
  "properties": {
    "addr:full":"20700 Denker Ave Torrance CA 90501",
    "addr:postcode":"20700;90501",
    "addr:street":"Denker Ave",
    "iso:country":"US",
    "sg:address":"20700 Denker Ave",
    "sg:city":"Torrance",
    "sg:classifiers":[
        {
            "category":"Professional",
            "subcategory":"Advertising",
            "type":"Services"
        }
    ],
    "sg:phone":"+1 310 328 1212",
    "sg:postcode":"90501",
    "sg:province":"CA",
    "sg:tags":[
        "designer",
        "display",
        "producer"
    ],
    "sg:website":"www.boothsale.com",
    "wof:name":"Exhibitcorp",
    "wof:placetype":"venue"
},
  "geometry": {"coordinates":[-118.303946,33.84191],"type":"Point"}
}