{
  "type": "Feature",
  "properties": {
    "addr:full":"16610 Crenshaw Blvd Torrance CA 90504",
    "addr:housenumber":"16610",
    "addr:postcode":"90504",
    "addr:street":"Crenshaw Blvd",
    "iso:country":"US",
    "sg:address":"16610 Crenshaw Blvd",
    "sg:city":"Torrance",
    "sg:classifiers":[
        {
            "category":"Health Services",
            "subcategory":"Clinic",
            "type":"Services"
        }
    ],
    "sg:phone":"+1 310 856 0406",
    "sg:postcode":"90504",
    "sg:province":"CA",
    "wof:name":"Noble Heart Svc",
    "wof:placetype":"venue"
},
  "geometry": {"coordinates":[-118.32639399999999,33.879982],"type":"Point"}
}