{
  "type": "Feature",
  "properties": {
    "addr:full":"918 Postal Way Vista CA 92083",
    "addr:housenumber":"918",
    "addr:postcode":"92083",
    "addr:street":"Postal Way",
    "iso:country":"US",
    "sg:address":"918 Postal Way",
    "sg:city":"Vista",
    "sg:classifiers":[
        {
            "category":"Retail",
            "subcategory":"Auto Repair",
            "type":"Services"
        }
    ],
    "sg:phone":"+1 760 726 2972",
    "sg:postcode":"92083",
    "sg:province":"CA",
    "sg:tags":[
        "repairing",
        "automobile"
    ],
    "wof:name":"B & C Auto Repair",
    "wof:placetype":"venue"
},
  "geometry": {"coordinates":[-117.23499200000001,33.192625],"type":"Point"}
}