{
  "type": "Feature",
  "properties": {
    "iso:country":"US",
    "sg:address":"193 S Main St",
    "sg:city":"Porterville",
    "sg:classifiers":[
        {
            "category":"Personal",
            "subcategory":"Beauty Salon",
            "type":"Services"
        }
    ],
    "sg:phone":"+1 559 782 1602",
    "sg:postcode":"93257",
    "sg:province":"CA",
    "wof:name":"Cuts & Curls",
    "wof:placetype":"venue"
},
  "geometry": {"coordinates":[-119.016622,36.061711],"type":"Point"}
}