{
  "type": "Feature",
  "properties": {
    "addr:full":"15260 Swallow Ln Westminster CA 92683",
    "addr:housenumber":"15260",
    "addr:postcode":"92683",
    "addr:street":"Swallow Ln",
    "iso:country":"US",
    "sg:address":"15260 Swallow Ln",
    "sg:city":"Westminster",
    "sg:classifiers":[
        {
            "category":"Manufacturing",
            "subcategory":"Signs",
            "type":"Manufacturing & Wholesale Goods"
        }
    ],
    "sg:phone":"+1 714 531 4888",
    "sg:postcode":"92683",
    "sg:province":"CA",
    "sg:tags":[
        "specialty",
        "mfg"
    ],
    "wof:name":"David Lestar Signs",
    "wof:placetype":"venue"
},
  "geometry": {"coordinates":[-117.960598,33.739471],"type":"Point"}
}