{
  "type": "Feature",
  "properties": {
    "addr:full":"1942 University Ave Berkeley CA 94704",
    "addr:housenumber":"1942",
    "addr:postcode":"94704",
    "addr:street":"University Ave",
    "iso:country":"US",
    "sg:address":"1942 University Ave",
    "sg:city":"Berkeley",
    "sg:classifiers":[
        {
            "category":"Arts & Performance",
            "subcategory":"Theater",
            "type":"Entertainment"
        }
    ],
    "sg:phone":"+1 510 204 9440",
    "sg:postcode":"94704",
    "sg:province":"CA",
    "sg:tags":[
        "theatrical",
        "manager",
        "producer"
    ],
    "wof:name":"Jonathan Reinis Productions",
    "wof:placetype":"venue"
},
  "geometry": {"coordinates":[-122.272745,37.871462],"type":"Point"}
}