{
  "type": "Feature",
  "properties": {
    "addr:full":"9960 Baldwin Pl El Monte CA 91731",
    "addr:housenumber":"9960",
    "addr:postcode":"91731",
    "addr:street":"Baldwin Pl",
    "iso:country":"US",
    "sg:address":"9960 Baldwin Pl",
    "sg:city":"El Monte",
    "sg:classifiers":[
        {
            "category":"Organizations",
            "subcategory":"Religious Organization",
            "type":"Services"
        }
    ],
    "sg:phone":"+1 626 401 2448",
    "sg:postcode":"91731",
    "sg:province":"CA",
    "sg:tags":[
        "church"
    ],
    "sg:website":"www.destinytraining.net",
    "wof:name":"Destiny Training Intl",
    "wof:placetype":"venue"
},
  "geometry": {"coordinates":[-118.054906,34.071294],"type":"Point"}
}