{
  "type": "Feature",
  "properties": {
    "iso:country":"US",
    "sg:address":"5873 Blackwelder St",
    "sg:city":"Culver City",
    "sg:classifiers":[
        {
            "category":"Home & Garden",
            "subcategory":"Building Materials",
            "type":"Retail Goods"
        }
    ],
    "sg:phone":"+1 310 836 7525",
    "sg:postcode":"90232",
    "sg:province":"CA",
    "sg:tags":[
        "wallpaper"
    ],
    "wof:name":"Kneedler' Fauchere",
    "wof:placetype":"venue"
},
  "geometry": {"coordinates":[-118.372933,34.030608],"type":"Point"}
}