{
  "type": "Feature",
  "properties": {
    "addr:full":"442 Kirkham St San Francisco CA 94122",
    "addr:housenumber":"442",
    "addr:postcode":"94122",
    "addr:street":"Kirkham St",
    "iso:country":"US",
    "sg:address":"442 Kirkham St",
    "sg:city":"San Francisco",
    "sg:classifiers":[
        {
            "category":"Professional",
            "subcategory":"Computer Services",
            "type":"Services"
        }
    ],
    "sg:phone":"+1 415 759 9032",
    "sg:postcode":"94122",
    "sg:province":"CA",
    "wof:name":"Cyclops",
    "wof:placetype":"venue"
},
  "geometry": {"coordinates":[-122.465692,37.760407],"type":"Point"}
}