{
  "type": "Feature",
  "properties": {
    "addr:full":"2003 E Main St Quincy CA 95971",
    "addr:housenumber":"2003",
    "addr:postcode":"95971",
    "addr:street":"E Main St",
    "iso:country":"US",
    "sg:address":"2003 E Main St",
    "sg:city":"Quincy",
    "sg:classifiers":[
        {
            "category":"Building & Trades",
            "subcategory":"Construction",
            "type":"Services"
        }
    ],
    "sg:phone":"+1 530 283 3214",
    "sg:postcode":"95971",
    "sg:province":"CA",
    "sg:tags":[
        "concrete",
        "contractor"
    ],
    "wof:name":"Sierra Concrete",
    "wof:placetype":"venue"
},
  "geometry": {"coordinates":[-120.901843,39.934138],"type":"Point"}
}