{
  "type": "Feature",
  "properties": {
    "iso:country":"US",
    "sg:address":"538 Valley Way",
    "sg:city":"Milpitas",
    "sg:classifiers":[
        {
            "category":"Health Services",
            "subcategory":"Clinic",
            "type":"Services"
        }
    ],
    "sg:phone":"+1 408 956 8034",
    "sg:postcode":"95035",
    "sg:province":"CA",
    "wof:name":"Social Advocates For Youth",
    "wof:placetype":"venue"
},
  "geometry": {"coordinates":[-121.913934,37.42727],"type":"Point"}
}