{
  "type": "Feature",
  "properties": {
    "addr:full":"920 Ocean Street Santa Cruz CA 95060",
    "addr:housenumber":"920",
    "addr:postcode":"95060",
    "addr:street":"Ocean Street",
    "iso:country":"US",
    "sg:address":"920 Ocean Street",
    "sg:city":"Santa Cruz",
    "sg:classifiers":[
        {
            "category":"Building & Trades",
            "subcategory":"Construction",
            "type":"Services"
        }
    ],
    "sg:phone":"+1 831 420 0590",
    "sg:postcode":"95060",
    "sg:province":"CA",
    "sg:tags":[
        "contractor"
    ],
    "wof:name":"Bogaard Brian Construction",
    "wof:placetype":"venue"
},
  "geometry": {"coordinates":[-122.02157699999999,36.981082],"type":"Point"}
}