{
  "type": "Feature",
  "properties": {
    "addr:full":"1424 4th St Santa Monica CA 90401",
    "addr:housenumber":"1424",
    "addr:postcode":"90401",
    "addr:street":"4Th St",
    "iso:country":"US",
    "sg:address":"1424 4th St",
    "sg:city":"Santa Monica",
    "sg:classifiers":[
        {
            "category":"Professional",
            "type":"Services"
        }
    ],
    "sg:phone":"+1 310 587 0034",
    "sg:postcode":"90401",
    "sg:province":"CA",
    "sg:tags":[
        "establishment"
    ],
    "wof:name":"David Twicken Lac I Ching",
    "wof:placetype":"venue"
},
  "geometry": {"coordinates":[-118.493965,34.015352],"type":"Point"}
}