{
  "type": "Feature",
  "properties": {
    "addr:full":"4222 E Butler Ave Fresno CA 93702",
    "addr:housenumber":"4222",
    "addr:postcode":"93702",
    "addr:street":"E Butler Ave",
    "iso:country":"US",
    "sg:address":"4222 E Butler Ave",
    "sg:city":"Fresno",
    "sg:classifiers":[
        {
            "category":"Shopping",
            "subcategory":"Pharmacy",
            "type":"Retail Goods"
        }
    ],
    "sg:phone":"+1 559 233 7183",
    "sg:postcode":"93702",
    "sg:province":"CA",
    "wof:name":"Family Pharmacy",
    "wof:placetype":"venue"
},
  "geometry": {"coordinates":[-119.751454,36.728547],"type":"Point"}
}