{
  "type": "Feature",
  "properties": {
    "addr:full":"804 E Main St Ventura CA 93001",
    "addr:housenumber":"804",
    "addr:postcode":"93001",
    "addr:street":"E Main St",
    "iso:country":"US",
    "sg:address":"804 E Main St",
    "sg:city":"Ventura",
    "sg:classifiers":[
        {
            "category":"Autos & Motor Vehicles",
            "subcategory":"Auto Supplies",
            "type":"Retail Goods"
        }
    ],
    "sg:phone":"+1 805 648 2712",
    "sg:postcode":"93001",
    "sg:province":"CA",
    "sg:tags":[
        "tire"
    ],
    "wof:name":"5 Day Tire Store",
    "wof:placetype":"venue"
},
  "geometry": {"coordinates":[-119.28703,34.280761],"type":"Point"}
}