{
  "type": "Feature",
  "properties": {
    "iso:country":"US",
    "sg:address":"319 E 157th St",
    "sg:city":"Gardena",
    "sg:classifiers":[
        {
            "category":"Autos & Motor Vehicles",
            "subcategory":"Recreational Vehicle Sales",
            "type":"Retail Goods"
        }
    ],
    "sg:phone":"+1 310 516 1538",
    "sg:postcode":"90248",
    "sg:province":"CA",
    "sg:tags":[
        "camper",
        "pick"
    ],
    "wof:name":"California Container Svc",
    "wof:placetype":"venue"
},
  "geometry": {"coordinates":[-118.270555,33.889532],"type":"Point"}
}