{
  "type": "Feature",
  "properties": {
    "iso:country":"US",
    "sg:address":"2527 Ridge Rd",
    "sg:city":"Berkeley",
    "sg:classifiers":[
        {
            "category":"Real Estate",
            "subcategory":"Real Estate Operator",
            "type":"Services"
        }
    ],
    "sg:phone":"+1 510 848 1936",
    "sg:postcode":"94709",
    "sg:province":"CA",
    "sg:tags":[
        "apartment"
    ],
    "sg:website":"www.usca.org/coops/ste.php",
    "wof:name":"Stebbins Hall",
    "wof:placetype":"venue"
},
  "geometry": {"coordinates":[-122.259832,37.876077],"type":"Point"}
}