{
  "type": "Feature",
  "properties": {
    "addr:full":"30 E San Joaquin St # 101 Salinas CA 93901",
    "addr:housenumber":"30",
    "addr:postcode":"93901",
    "addr:street":"E San Joaquin St # 101",
    "iso:country":"US",
    "sg:address":"30 E San Joaquin St # 101",
    "sg:city":"Salinas",
    "sg:classifiers":[
        {
            "category":"Banks & Credit Unions",
            "subcategory":"Investment Brokerage",
            "type":"Services"
        },
        {
            "category":"Insurance",
            "subcategory":"Hazard Insurance",
            "type":"Services"
        }
    ],
    "sg:phone":"+1 831 422 9623",
    "sg:postcode":"93901",
    "sg:province":"CA",
    "sg:tags":[
        "agent",
        "resume"
    ],
    "sg:website":"http://www.homeworkhelppage.com",
    "wof:name":"Mony Life",
    "wof:placetype":"venue"
},
  "geometry": {"coordinates":[-121.658171,36.658669],"type":"Point"}
}