{
  "type": "Feature",
  "properties": {
    "addr:full":"2779 Fieldbrook Rd Mckinleyville CA 95519",
    "addr:housenumber":"2779",
    "addr:postcode":"95519",
    "addr:street":"Fieldbrook Rd",
    "iso:country":"US",
    "sg:address":"2779 Fieldbrook Rd",
    "sg:city":"Mckinleyville",
    "sg:classifiers":[
        {
            "category":"Building & Trades",
            "subcategory":"Construction",
            "type":"Services"
        }
    ],
    "sg:phone":"+1 707 839 8303",
    "sg:postcode":"95519",
    "sg:province":"CA",
    "sg:tags":[
        "home",
        "improvement"
    ],
    "wof:name":"Frank Pinckney's Fix-It-Frank",
    "wof:placetype":"venue"
},
  "geometry": {"coordinates":[-124.023453,40.939943],"type":"Point"}
}