{
  "type": "Feature",
  "properties": {
    "iso:country":"US",
    "sg:address":"52 S Linden Ave",
    "sg:city":"S San Francisco",
    "sg:classifiers":[
        {
            "category":"Manufacturing",
            "subcategory":"Motor Vehicles & Parts",
            "type":"Manufacturing & Wholesale Goods"
        }
    ],
    "sg:phone":"+1 650 876 9988",
    "sg:postcode":"94080",
    "sg:province":"CA",
    "sg:tags":[
        "automobile",
        "supply"
    ],
    "wof:name":"GTM",
    "wof:placetype":"venue"
},
  "geometry": {"coordinates":[-122.412809,37.647779],"type":"Point"}
}