{
  "type": "Feature",
  "properties": {
    "addr:full":"14 Fredson Ct Novato CA 94947",
    "addr:housenumber":"14",
    "addr:postcode":"94947",
    "addr:street":"Fredson Ct",
    "iso:country":"US",
    "sg:address":"14 Fredson Ct",
    "sg:city":"Novato",
    "sg:classifiers":[
        {
            "category":"Building & Trades",
            "subcategory":"Plumbing",
            "type":"Services"
        }
    ],
    "sg:phone":"+1 415 892 3502",
    "sg:postcode":"94947",
    "sg:province":"CA",
    "sg:tags":[
        "contractor"
    ],
    "wof:name":"J W Kegg Plumbing",
    "wof:placetype":"venue"
},
  "geometry": {"coordinates":[-122.590845,38.107092],"type":"Point"}
}