{
  "type": "Feature",
  "properties": {
    "addr:full":"5291 Colodny Dr Unit 1 Agoura Hills CA 91301",
    "addr:housenumber":"5291;1",
    "addr:postcode":"91301",
    "addr:street":"Colodny Dr Unit",
    "iso:country":"US",
    "sg:address":"5291 Colodny Dr Unit 1",
    "sg:city":"Agoura Hills",
    "sg:classifiers":[
        {
            "category":"Building & Trades",
            "subcategory":"Plumbing",
            "type":"Services"
        }
    ],
    "sg:phone":"+1 818 889 8268",
    "sg:postcode":"91301",
    "sg:province":"CA",
    "wof:name":"Old Agoura Plumbing & Heating",
    "wof:placetype":"venue"
},
  "geometry": {"coordinates":[-118.741997,34.144798],"type":"Point"}
}