{
  "type": "Feature",
  "properties": {
    "addr:full":"1956 Redondela Dr Rancho Palos Verdes CA 90275",
    "addr:housenumber":"1956",
    "addr:postcode":"90275",
    "addr:street":"Redondela Dr",
    "iso:country":"US",
    "sg:address":"1956 Redondela Dr",
    "sg:city":"Rancho Palos Verdes",
    "sg:classifiers":[
        {
            "category":"Wholesale",
            "subcategory":"Machinery & Supplies",
            "type":"Manufacturing & Wholesale Goods"
        }
    ],
    "sg:phone":"+1 310 833 8777",
    "sg:postcode":"90275",
    "sg:province":"CA",
    "sg:tags":[
        "industrial"
    ],
    "wof:name":"David R & Judith E Scott",
    "wof:placetype":"venue"
},
  "geometry": {"coordinates":[-118.31303800000001,33.76887],"type":"Point"}
}