{
  "type": "Feature",
  "properties": {
    "addr:full":"2302 Inyo St Mojave CA 93501",
    "addr:housenumber":"2302",
    "addr:postcode":"93501",
    "addr:street":"Inyo St",
    "iso:country":"US",
    "sg:address":"2302 Inyo St",
    "sg:city":"Mojave",
    "sg:classifiers":[
        {
            "category":"Shopping",
            "subcategory":"Gifts & Souvenirs",
            "type":"Retail Goods"
        }
    ],
    "sg:phone":"+1 661 824 8645",
    "sg:postcode":"93501",
    "sg:province":"CA",
    "wof:name":"Regalos Y Mas",
    "wof:placetype":"venue"
},
  "geometry": {"coordinates":[-118.172355,35.052563],"type":"Point"}
}