{
  "type": "Feature",
  "properties": {
    "iso:country":"US",
    "sg:address":"5651 E Kings Canyon Rd",
    "sg:city":"Fresno",
    "sg:classifiers":[
        {
            "category":"Restaurant",
            "type":"Food & Drink"
        }
    ],
    "sg:menulink":"http://www.allmenus.com/ca/fresno/200782-long-john-silvers/menu/",
    "sg:phone":"+1 559 251 0541",
    "sg:postcode":"93727",
    "sg:province":"CA",
    "sg:tags":[
        "seafood",
        "american"
    ],
    "wof:name":"Long John Silver's",
    "wof:placetype":"venue"
},
  "geometry": {"coordinates":[-119.69872700000001,36.736971],"type":"Point"}
}