{
  "type": "Feature",
  "properties": {
    "iso:country":"US",
    "sg:address":"3154 Campus Dr",
    "sg:city":"San Mateo",
    "sg:classifiers":[
        {
            "category":"Professional",
            "subcategory":"Computer Services",
            "type":"Services"
        }
    ],
    "sg:phone":"+1 510 324 6100",
    "sg:postcode":"94497",
    "sg:province":"CA",
    "wof:name":"I X Computer Network",
    "wof:placetype":"venue"
},
  "geometry": {"coordinates":[-122.327808,37.533614],"type":"Point"}
}