{
  "type": "Feature",
  "properties": {
    "addr:full":"9101 W Olympic Boulevard Beverly Hills CA 90212",
    "addr:housenumber":"9101",
    "addr:postcode":"90212",
    "addr:street":"W Olympic Boulevard",
    "iso:country":"US",
    "sg:address":"9101 W Olympic Boulevard",
    "sg:city":"Beverly Hills",
    "sg:classifiers":[
        {
            "category":"Shopping",
            "subcategory":"Florist",
            "type":"Retail Goods"
        }
    ],
    "sg:phone":"+1 310 271 3332",
    "sg:postcode":"90212",
    "sg:province":"CA",
    "wof:name":"Apropos Floral & Event Design",
    "wof:placetype":"venue"
},
  "geometry": {"coordinates":[-118.389895,34.059264],"type":"Point"}
}