{
  "type": "Feature",
  "properties": {
    "addr:full":"1724 Ximeno Ave Apt 7 Long Beach CA 90815",
    "addr:housenumber":"1724;7",
    "addr:postcode":"90815",
    "addr:street":"Ximeno Ave Apt",
    "iso:country":"US",
    "sg:address":"1724 Ximeno Ave Apt 7",
    "sg:city":"Long Beach",
    "sg:classifiers":[
        {
            "category":"Building & Trades",
            "subcategory":"Construction",
            "type":"Services"
        }
    ],
    "sg:phone":"+1 562 494 3566",
    "sg:postcode":"90815",
    "sg:province":"CA",
    "sg:tags":[
        "contractor"
    ],
    "wof:name":"RMG Construction",
    "wof:placetype":"venue"
},
  "geometry": {"coordinates":[-118.13891,33.788161],"type":"Point"}
}