{
  "type": "Feature",
  "properties": {
    "iso:country":"US",
    "sg:address":"665 Sedgeworth Ct",
    "sg:city":"Simi Valley",
    "sg:classifiers":[
        {
            "category":"Wholesale",
            "subcategory":"Electrical",
            "type":"Manufacturing & Wholesale Goods"
        }
    ],
    "sg:phone":"+1 805 520 3809",
    "sg:postcode":"93065",
    "sg:province":"CA",
    "sg:tags":[
        "electronic"
    ],
    "wof:name":"Hefty Electronic Sales",
    "wof:placetype":"venue"
},
  "geometry": {"coordinates":[-118.814229,34.23462],"type":"Point"}
}