{
  "type": "Feature",
  "properties": {
    "addr:full":"409 Natoma St Folsom CA 95630",
    "addr:housenumber":"409",
    "addr:postcode":"95630",
    "addr:street":"Natoma St",
    "iso:country":"US",
    "sg:address":"409 Natoma St",
    "sg:city":"Folsom",
    "sg:classifiers":[
        {
            "category":"Restaurant",
            "type":"Food & Drink"
        }
    ],
    "sg:phone":"+1 916 351 9083",
    "sg:postcode":"95630",
    "sg:province":"CA",
    "sg:website":"www.solazteca.com",
    "wof:name":"Sol Azteca Mexican Cuisine",
    "wof:placetype":"venue"
},
  "geometry": {"coordinates":[-121.171367,38.676859],"type":"Point"}
}