{
  "type": "Feature",
  "properties": {
    "iso:country":"US",
    "sg:address":"10531 Venita St",
    "sg:city":"El Monte",
    "sg:classifiers":[
        {
            "category":"Shopping",
            "subcategory":"Florist",
            "type":"Retail Goods"
        }
    ],
    "sg:phone":"+1 626 442 4619",
    "sg:postcode":"91731",
    "sg:province":"CA",
    "wof:name":"Nunez Creations",
    "wof:placetype":"venue"
},
  "geometry": {"coordinates":[-118.043538,34.083004],"type":"Point"}
}