{
  "type": "Feature",
  "properties": {
    "addr:full":"2 Regina Dana Point CA 92629",
    "addr:housenumber":"2",
    "addr:postcode":"92629",
    "addr:street":"Regina",
    "iso:country":"US",
    "sg:address":"2 Regina",
    "sg:city":"Dana Point",
    "sg:classifiers":[
        {
            "category":"Building & Trades",
            "subcategory":"Construction",
            "type":"Services"
        }
    ],
    "sg:phone":"+1 949 493 6594",
    "sg:postcode":"92629",
    "sg:province":"CA",
    "sg:tags":[
        "residence",
        "general",
        "contractor"
    ],
    "wof:name":"South Shore Construction",
    "wof:placetype":"venue"
},
  "geometry": {"coordinates":[-117.70842,33.486939],"type":"Point"}
}