{
  "type": "Feature",
  "properties": {
    "iso:country":"US",
    "sg:address":"6365 Southfront Rd",
    "sg:city":"Livermore",
    "sg:classifiers":[
        {
            "category":"Sports & Exercise",
            "subcategory":"Swimming Pool",
            "type":"Entertainment"
        }
    ],
    "sg:phone":"+1 925 449 3446",
    "sg:postcode":"94551",
    "sg:province":"CA",
    "sg:tags":[
        "repair",
        "consulting",
        "designing"
    ],
    "wof:name":"American Built Pools, Inc",
    "wof:placetype":"venue"
},
  "geometry": {"coordinates":[-121.71913600000001,37.710486],"type":"Point"}
}