{
  "type": "Feature",
  "properties": {
    "addr:full":"6901 Bali Ct Orangevale CA 95662",
    "addr:housenumber":"6901",
    "addr:postcode":"95662",
    "addr:street":"Bali Ct",
    "iso:country":"US",
    "sg:address":"6901 Bali Ct",
    "sg:city":"Orangevale",
    "sg:classifiers":[
        {
            "category":"Retail",
            "subcategory":"Repair Shop",
            "type":"Services"
        }
    ],
    "sg:phone":"+1 916 486 0349",
    "sg:postcode":"95662",
    "sg:province":"CA",
    "sg:tags":[
        "lock",
        "locksmith"
    ],
    "wof:name":"Carmichael Lock & Safe",
    "wof:placetype":"venue"
},
  "geometry": {"coordinates":[-121.228511,38.692083],"type":"Point"}
}