{
  "type": "Feature",
  "properties": {
    "addr:full":"1027 Swarthmore Ave Pacific Plsds CA 90272",
    "addr:housenumber":"1027",
    "addr:postcode":"90272",
    "addr:street":"Swarthmore Ave",
    "iso:country":"US",
    "sg:address":"1027 Swarthmore Ave",
    "sg:city":"Pacific Plsds",
    "sg:classifiers":[
        {
            "category":"Health Services",
            "subcategory":"Chiropractor",
            "type":"Services"
        }
    ],
    "sg:phone":"+1 310 459 4600",
    "sg:postcode":"90272",
    "sg:province":"CA",
    "wof:name":"Billauer-Sato Chiropractic Ofc",
    "wof:placetype":"venue"
},
  "geometry": {"coordinates":[-118.52495399999999,34.048211],"type":"Point"}
}