{
  "type": "Feature",
  "properties": {
    "addr:full":"911 W Pacheco Blvd Los Banos CA 93635",
    "addr:housenumber":"911",
    "addr:postcode":"93635",
    "addr:street":"W Pacheco Blvd",
    "iso:country":"US",
    "sg:address":"911 W Pacheco Blvd",
    "sg:city":"Los Banos",
    "sg:classifiers":[
        {
            "category":"Restaurant",
            "type":"Food & Drink"
        }
    ],
    "sg:menulink":"http://www.allmenus.com/ca/los-banos/216765-mcdonalds/menu/",
    "sg:postcode":"93635",
    "sg:province":"CA",
    "sg:tags":[
        "burger",
        "american"
    ],
    "wof:name":"McDonald's",
    "wof:placetype":"venue"
},
  "geometry": {"coordinates":[-120.866023,37.056849],"type":"Point"}
}