{
  "type": "Feature",
  "properties": {
    "iso:country":"US",
    "sg:address":"1851 Shell Beach Rd",
    "sg:city":"Pismo Beach",
    "sg:classifiers":[
        {
            "category":"Banks & Credit Unions",
            "subcategory":"Investment Brokerage",
            "type":"Services"
        }
    ],
    "sg:phone":"+1 805 773 8700",
    "sg:postcode":"93449",
    "sg:province":"CA",
    "sg:tags":[
        "advisory"
    ],
    "wof:name":"Johannssen Kurt Inv Exec",
    "wof:placetype":"venue"
},
  "geometry": {"coordinates":[-120.67517100000001,35.158755],"type":"Point"}
}