{
  "type": "Feature",
  "properties": {
    "addr:full":"2501 E 28th St Ste 111 Signal Hill CA 90755",
    "addr:housenumber":"2501",
    "addr:postcode":"90755",
    "addr:street":"E 28Th St Ste 111;Hill",
    "iso:country":"US",
    "sg:address":"2501 E 28th St Ste 111",
    "sg:city":"Signal Hill",
    "sg:classifiers":[
        {
            "category":"Shopping",
            "subcategory":"Stationery & Office Supplies",
            "type":"Retail Goods"
        }
    ],
    "sg:phone":"+1 562 595 0900",
    "sg:postcode":"90755",
    "sg:province":"CA",
    "sg:tags":[
        "equipment"
    ],
    "wof:name":"Macro-Pro",
    "wof:placetype":"venue"
},
  "geometry": {"coordinates":[-118.162003,33.808102],"type":"Point"}
}