{
  "type": "Feature",
  "properties": {
    "iso:country":"US",
    "sg:address":"108 W Big Bear Blvd",
    "sg:city":"Big Bear City",
    "sg:classifiers":[
        {
            "category":"Food & Beverages",
            "subcategory":"Bakery",
            "type":"Retail Goods"
        }
    ],
    "sg:phone":"+1 909 584 4399",
    "sg:postcode":"92314",
    "sg:province":"CA",
    "sg:tags":[
        "doughnut"
    ],
    "wof:name":"Big Bear Donuts",
    "wof:placetype":"venue"
},
  "geometry": {"coordinates":[-116.84724,34.261063],"type":"Point"}
}