{
  "type": "Feature",
  "properties": {
    "addr:full":"5524 Del AMO Blvd Lakewood CA 90713",
    "addr:housenumber":"5524",
    "addr:postcode":"90713",
    "addr:street":"Del Amo Blvd",
    "iso:country":"US",
    "sg:address":"5524 Del AMO Blvd",
    "sg:city":"Lakewood",
    "sg:classifiers":[
        {
            "category":"Retail",
            "subcategory":"Laundry & Dry Cleaning",
            "type":"Services"
        }
    ],
    "sg:phone":"+1 562 421 8297",
    "sg:postcode":"90713",
    "sg:province":"CA",
    "wof:name":"Del AMO Cleaners",
    "wof:placetype":"venue"
},
  "geometry": {"coordinates":[-118.125,33.846901],"type":"Point"}
}