{
  "type": "Feature",
  "properties": {
    "iso:country":"US",
    "sg:address":"960 Main Street",
    "sg:city":"El Segundo",
    "sg:classifiers":[
        {
            "category":"Restaurant",
            "type":"Food & Drink"
        }
    ],
    "sg:phone":"+1 310 322 0567",
    "sg:postcode":"90245",
    "sg:province":"CA",
    "sg:website":"www.subway.com",
    "wof:name":"Subway",
    "wof:placetype":"venue"
},
  "geometry": {"coordinates":[-118.416,33.93],"type":"Point"}
}