{
  "type": "Feature",
  "properties": {
    "addr:full":"32700 Alvarado Blvd Fremont CA 94555",
    "addr:housenumber":"32700",
    "addr:postcode":"94555",
    "addr:street":"Alvarado Blvd",
    "iso:country":"US",
    "sg:address":"32700 Alvarado Blvd",
    "sg:city":"Fremont",
    "sg:classifiers":[
        {
            "category":"Health Services",
            "subcategory":"Doctor",
            "type":"Services"
        }
    ],
    "sg:phone":"+1 510 477 0811",
    "sg:postcode":"94555",
    "sg:province":"CA",
    "sg:tags":[
        "dentist"
    ],
    "wof:name":"Creative Smile Dental",
    "wof:placetype":"venue"
},
  "geometry": {"coordinates":[-122.06169300000001,37.585274],"type":"Point"}
}