{
  "type": "Feature",
  "properties": {
    "iso:country":"US",
    "sg:address":"4716 Stine Rd",
    "sg:city":"Bakersfield",
    "sg:classifiers":[
        {
            "category":"Autos & Motor Vehicles",
            "subcategory":"Auto Supplies",
            "type":"Retail Goods"
        },
        {
            "category":"Retail",
            "subcategory":"Auto Repair",
            "type":"Services"
        }
    ],
    "sg:phone":"+1 661 837 2572",
    "sg:postcode":"93313",
    "sg:province":"CA",
    "sg:tags":[
        "brake",
        "tire"
    ],
    "wof:name":"Gutierrez New & Used Tires",
    "wof:placetype":"venue"
},
  "geometry": {"coordinates":[-119.05668300000001,35.311986],"type":"Point"}
}