{
  "type": "Feature",
  "properties": {
    "addr:full":"3525 W Carson St Torrance CA 90503",
    "addr:housenumber":"3525",
    "addr:postcode":"90503",
    "addr:street":"W Carson St",
    "iso:country":"US",
    "sg:address":"3525 W Carson St",
    "sg:city":"Torrance",
    "sg:classifiers":[
        {
            "category":"Shopping",
            "subcategory":"Tobacco",
            "type":"Retail Goods"
        }
    ],
    "sg:phone":"+1 310 793 1013",
    "sg:postcode":"90503",
    "sg:province":"CA",
    "sg:tags":[
        "shop"
    ],
    "wof:name":"Cohiba Cigar Lounge",
    "wof:placetype":"venue"
},
  "geometry": {"coordinates":[-118.34784000000001,33.831221],"type":"Point"}
}