{
  "type": "Feature",
  "properties": {
    "iso:country":"US",
    "sg:address":"2585 Jensen Ave",
    "sg:city":"Sanger",
    "sg:classifiers":[
        {
            "category":"Food & Beverages",
            "subcategory":"Groceries & Convenience Stores",
            "type":"Retail Goods"
        }
    ],
    "sg:phone":"+1 559 875 1422",
    "sg:postcode":"93657",
    "sg:province":"CA",
    "sg:tags":[
        "market"
    ],
    "wof:name":"Sierra View Market",
    "wof:placetype":"venue"
},
  "geometry": {"coordinates":[-119.569668,36.706712],"type":"Point"}
}