{
  "type": "Feature",
  "properties": {
    "addr:full":"777 Mariners Island Blvd San Mateo CA 94404",
    "addr:housenumber":"777",
    "addr:postcode":"94404",
    "addr:street":"Mariners Island Blvd",
    "iso:country":"US",
    "sg:address":"777 Mariners Island Blvd",
    "sg:city":"San Mateo",
    "sg:classifiers":[
        {
            "category":"Health Services",
            "subcategory":"Doctor",
            "type":"Services"
        }
    ],
    "sg:phone":"+1 650 312 1662",
    "sg:postcode":"94404",
    "sg:province":"CA",
    "wof:name":"Physician Referral Service",
    "wof:placetype":"venue"
},
  "geometry": {"coordinates":[-122.286387,37.562535],"type":"Point"}
}