{
  "type": "Feature",
  "properties": {
    "iso:country":"US",
    "sg:address":"4880 Virginiatown Rd",
    "sg:city":"Newcastle",
    "sg:classifiers":[
        {
            "category":"Home & Garden",
            "subcategory":"Garden Supply",
            "type":"Retail Goods"
        },
        {
            "category":"Building & Trades",
            "subcategory":"Landscaping Services",
            "type":"Services"
        }
    ],
    "sg:phone":"+1 916 645 1820",
    "sg:postcode":"95658",
    "sg:province":"CA",
    "sg:tags":[
        "nurseryman"
    ],
    "wof:name":"Matsuda Landscape & Nursery",
    "wof:placetype":"venue"
},
  "geometry": {"coordinates":[-121.219089,38.898723],"type":"Point"}
}