{
  "type": "Feature",
  "properties": {
    "iso:country":"US",
    "sg:address":"11509 S Vermont Ave",
    "sg:city":"Los Angeles",
    "sg:classifiers":[
        {
            "category":"Travel",
            "subcategory":"Hotels & Motels",
            "type":"Entertainment"
        }
    ],
    "sg:phone":"+1 323 756 3333",
    "sg:postcode":"90044",
    "sg:province":"CA",
    "wof:name":"Magic Carpet Motor Inn",
    "wof:placetype":"venue"
},
  "geometry": {"coordinates":[-118.292,33.930099],"type":"Point"}
}