{
  "type": "Feature",
  "properties": {
    "addr:full":"322 Sun West Pl Manteca CA 95337",
    "addr:housenumber":"322",
    "addr:postcode":"95337",
    "addr:street":"Sun West Pl",
    "iso:country":"US",
    "sg:address":"322 Sun West Pl",
    "sg:city":"Manteca",
    "sg:classifiers":[
        {
            "category":"Professional",
            "subcategory":"Engineering",
            "type":"Services"
        }
    ],
    "sg:phone":"+1 209 239 6229",
    "sg:postcode":"95337",
    "sg:province":"CA",
    "sg:tags":[
        "engineer"
    ],
    "sg:website":"www.mcreng.com",
    "wof:name":"MCR Engineering",
    "wof:placetype":"venue"
},
  "geometry": {"coordinates":[-121.23225100000001,37.801981],"type":"Point"}
}