{
  "type": "Feature",
  "properties": {
    "addr:full":"250 Stockton Ave San Jose CA 95126",
    "addr:housenumber":"250",
    "addr:postcode":"95126",
    "addr:street":"Stockton Ave",
    "iso:country":"US",
    "sg:address":"250 Stockton Ave",
    "sg:city":"San Jose",
    "sg:classifiers":[
        {
            "category":"Communications",
            "type":"Services"
        }
    ],
    "sg:phone":"+1 408 297 2550",
    "sg:postcode":"95126",
    "sg:province":"CA",
    "sg:tags":[
        "communication"
    ],
    "wof:name":"Arvada Communications",
    "wof:placetype":"venue"
},
  "geometry": {"coordinates":[-121.90589900000001,37.333769],"type":"Point"}
}