{
  "type": "Feature",
  "properties": {
    "addr:full":"33 New Montgomery St San Francisco CA 94105",
    "addr:housenumber":"33",
    "addr:postcode":"94105",
    "addr:street":"New Montgomery St",
    "iso:country":"US",
    "sg:address":"33 New Montgomery St",
    "sg:city":"San Francisco",
    "sg:classifiers":[
        {
            "category":"Professional",
            "subcategory":"Lawyer & Legal Services",
            "type":"Services"
        }
    ],
    "sg:phone":"+1 415 882 7840",
    "sg:postcode":"94105",
    "sg:province":"CA",
    "wof:name":"Ogden M Blaire Law Office of",
    "wof:placetype":"venue"
},
  "geometry": {"coordinates":[-122.40184600000001,37.788722],"type":"Point"}
}