{
  "type": "Feature",
  "properties": {
    "addr:full":"1350 Hayes St Ste A30 Benicia CA 94510",
    "addr:housenumber":"1350",
    "addr:postcode":"94510",
    "addr:street":"Hayes St Ste A30",
    "iso:country":"US",
    "sg:address":"1350 Hayes St Ste A30",
    "sg:city":"Benicia",
    "sg:classifiers":[
        {
            "category":"Education",
            "subcategory":"School",
            "type":"Public Place"
        }
    ],
    "sg:phone":"+1 707 748 7818",
    "sg:postcode":"94510",
    "sg:province":"CA",
    "sg:tags":[
        "k-",
        "private"
    ],
    "wof:name":"Pathways Charter School",
    "wof:placetype":"venue"
},
  "geometry": {"coordinates":[-122.139066,38.047636],"type":"Point"}
}