{
  "type": "Feature",
  "properties": {
    "iso:country":"US",
    "sg:address":"2901 Macdonald Ave",
    "sg:city":"Richmond",
    "sg:classifiers":[
        {
            "category":"Social Services",
            "subcategory":"Adult Care",
            "type":"Services"
        }
    ],
    "sg:phone":"+1 510 233 2728",
    "sg:postcode":"94801",
    "sg:province":"CA",
    "sg:tags":[
        "foster"
    ],
    "wof:name":"Westwind Foster Family Agency",
    "wof:placetype":"venue"
},
  "geometry": {"coordinates":[-122.340374,37.934708],"type":"Point"}
}