{
  "type": "Feature",
  "properties": {
    "iso:country":"US",
    "sg:address":"1528 Eureka Rd",
    "sg:city":"Roseville",
    "sg:classifiers":[
        {
            "category":"Utilities",
            "type":"Services"
        }
    ],
    "sg:phone":"+1 916 960 1408",
    "sg:postcode":"95661",
    "sg:province":"CA",
    "sg:tags":[
        "sanitary"
    ],
    "wof:name":"O4 Inc",
    "wof:placetype":"venue"
},
  "geometry": {"coordinates":[-121.25182,38.752279],"type":"Point"}
}