{
  "type": "Feature",
  "properties": {
    "addr:full":"8383 Wilshire Blvd Beverly Hills CA 90211",
    "addr:housenumber":"8383",
    "addr:postcode":"90211",
    "addr:street":"Wilshire Blvd",
    "iso:country":"US",
    "sg:address":"8383 Wilshire Blvd",
    "sg:city":"Beverly Hills",
    "sg:classifiers":[
        {
            "category":"Real Estate",
            "subcategory":"Developer",
            "type":"Services"
        }
    ],
    "sg:phone":"+1 323 653 6677",
    "sg:postcode":"90211",
    "sg:province":"CA",
    "wof:name":"Jan Development",
    "wof:placetype":"venue"
},
  "geometry": {"coordinates":[-118.37331399999999,34.064543],"type":"Point"}
}