{
  "type": "Feature",
  "properties": {
    "iso:country":"US",
    "sg:address":"20071 State Hwy 33",
    "sg:city":"Dos Palos",
    "sg:classifiers":[
        {
            "category":"Farming",
            "subcategory":"Farm & Veterinary Services",
            "type":"Manufacturing & Wholesale Goods"
        }
    ],
    "sg:phone":"+1 209 392 3204",
    "sg:postcode":"93620",
    "sg:province":"CA",
    "sg:tags":[
        "crop",
        "harvesting"
    ],
    "wof:name":"Samuel Buie",
    "wof:placetype":"venue"
},
  "geometry": {"coordinates":[-120.635711,36.995935],"type":"Point"}
}