{
  "type": "Feature",
  "properties": {
    "addr:full":"10639 Wixom St Sun Valley CA 91352",
    "addr:housenumber":"10639",
    "addr:postcode":"91352",
    "addr:street":"Wixom St",
    "iso:country":"US",
    "sg:address":"10639 Wixom St",
    "sg:city":"Sun Valley",
    "sg:classifiers":[
        {
            "category":"Retail",
            "subcategory":"Repair Shop",
            "type":"Services"
        }
    ],
    "sg:phone":"+1 818 542 2242",
    "sg:postcode":"91352",
    "sg:province":"CA",
    "sg:tags":[
        "plumbing",
        "drain",
        "cleaning",
        "sewer"
    ],
    "wof:name":"LA Hydrojet",
    "wof:placetype":"venue"
},
  "geometry": {"coordinates":[-118.363401,34.211352],"type":"Point"}
}