{
  "type": "Feature",
  "properties": {
    "addr:full":"731 Enterprise St Escondido CA 92029",
    "addr:housenumber":"731",
    "addr:postcode":"92029",
    "addr:street":"Enterprise St",
    "iso:country":"US",
    "sg:address":"731 Enterprise St",
    "sg:city":"Escondido",
    "sg:classifiers":[
        {
            "category":"Wholesale",
            "subcategory":"Machinery & Supplies",
            "type":"Manufacturing & Wholesale Goods"
        }
    ],
    "sg:phone":"+1 760 746 8000",
    "sg:postcode":"92029",
    "sg:province":"CA",
    "sg:tags":[
        "equipment",
        "irrigation",
        "system"
    ],
    "sg:website":"www.hydroscape.com",
    "wof:name":"Hydro-Scape Products",
    "wof:placetype":"venue"
},
  "geometry": {"coordinates":[-117.11435299999999,33.123635],"type":"Point"}
}