{
  "type": "Feature",
  "properties": {
    "iso:country":"US",
    "sg:address":"1931 W Middlefield Rd",
    "sg:city":"Mountain View",
    "sg:classifiers":[
        {
            "category":"Professional",
            "subcategory":"Management & Consulting",
            "type":"Services"
        }
    ],
    "sg:phone":"+1 650 968 3600",
    "sg:postcode":"94043",
    "sg:province":"CA",
    "sg:tags":[
        "party",
        "planning"
    ],
    "wof:name":"Amazing Events",
    "wof:placetype":"venue"
},
  "geometry": {"coordinates":[-122.090194,37.410617],"type":"Point"}
}