{
  "type": "Feature",
  "properties": {
    "iso:country":"US",
    "sg:address":"5060 Laguna Blvd",
    "sg:city":"Elk Grove",
    "sg:classifiers":[
        {
            "category":"Travel",
            "subcategory":"Travel Agent",
            "type":"Entertainment"
        }
    ],
    "sg:phone":"+1 916 684 8025",
    "sg:postcode":"95758",
    "sg:province":"CA",
    "sg:tags":[
        "bureau",
        "passenger",
        "agency",
        "transportation",
        "arrangement"
    ],
    "wof:name":"Patterson Travel",
    "wof:placetype":"venue"
},
  "geometry": {"coordinates":[-121.447302,38.423147],"type":"Point"}
}