{
  "type": "Feature",
  "properties": {
    "addr:full":"1798 Angela St San Jose CA 95125",
    "addr:housenumber":"1798",
    "addr:postcode":"95125",
    "addr:street":"Angela St",
    "iso:country":"US",
    "sg:address":"1798 Angela St",
    "sg:city":"San Jose",
    "sg:classifiers":[
        {
            "category":"Autos & Motor Vehicles",
            "subcategory":"Auto Supplies",
            "type":"Retail Goods"
        }
    ],
    "sg:phone":"+1 408 271 9800",
    "sg:postcode":"95125",
    "sg:province":"CA",
    "sg:tags":[
        "equipment",
        "repair",
        "racing",
        "car",
        "automobile"
    ],
    "wof:name":"Dynospot Racing",
    "wof:placetype":"venue"
},
  "geometry": {"coordinates":[-121.876999,37.3046],"type":"Point"}
}