{
  "type": "Feature",
  "properties": {
    "iso:country":"US",
    "sg:address":"329 W Armsley Sq",
    "sg:city":"Ontario",
    "sg:classifiers":[
        {
            "category":"Professional",
            "type":"Services"
        }
    ],
    "sg:phone":"+1 909 268 0011",
    "sg:postcode":"91762",
    "sg:province":"CA",
    "sg:tags":[
        "establishment"
    ],
    "wof:name":"Culture Beat Music",
    "wof:placetype":"venue"
},
  "geometry": {"coordinates":[-117.655976,34.083893],"type":"Point"}
}