{
  "type": "Feature",
  "properties": {
    "addr:full":"1033 N Sycamore Ave Los Angeles CA 90038",
    "addr:housenumber":"1033",
    "addr:postcode":"90038",
    "addr:street":"N Sycamore Ave",
    "iso:country":"US",
    "sg:address":"1033 N Sycamore Ave",
    "sg:city":"Los Angeles",
    "sg:classifiers":[
        {
            "category":"Shopping",
            "subcategory":"Computers & Home Electronics",
            "type":"Retail Goods"
        }
    ],
    "sg:phone":"+1 323 934 3566",
    "sg:postcode":"90038",
    "sg:province":"CA",
    "sg:website":"www.opamplabs.com/",
    "wof:name":"Opamp Labs",
    "wof:placetype":"venue"
},
  "geometry": {"coordinates":[-118.342783,34.089842],"type":"Point"}
}