{
  "type": "Feature",
  "properties": {
    "iso:country":"US",
    "sg:address":"130 Allison Ct",
    "sg:city":"Vacaville",
    "sg:classifiers":[
        {
            "category":"Banks & Credit Unions",
            "subcategory":"Bank",
            "type":"Services"
        }
    ],
    "sg:phone":"+1 707 447 9962",
    "sg:postcode":"95688",
    "sg:province":"CA",
    "sg:tags":[
        "loan",
        "real estate"
    ],
    "wof:name":"Superior Home Loans",
    "wof:placetype":"venue"
},
  "geometry": {"coordinates":[-121.971636,38.363261],"type":"Point"}
}