{
  "type": "Feature",
  "properties": {
    "addr:full":"14299 Wicks Blvd San Leandro CA 94579",
    "addr:housenumber":"14299",
    "addr:postcode":"94579",
    "addr:street":"Wicks Blvd",
    "iso:country":"US",
    "sg:address":"14299 Wicks Blvd",
    "sg:city":"San Leandro",
    "sg:classifiers":[
        {
            "category":"Professional",
            "subcategory":"Business Services",
            "type":"Services"
        }
    ],
    "sg:phone":"+1 510 895 6663",
    "sg:postcode":"94579",
    "sg:province":"CA",
    "sg:tags":[
        "water",
        "treatment"
    ],
    "wof:name":"Us Filter Elcat Prod Siemans G",
    "wof:placetype":"venue"
},
  "geometry": {"coordinates":[-122.16571399999999,37.700102],"type":"Point"}
}