{
  "type": "Feature",
  "properties": {
    "addr:full":"3754 Williams Rd San Jose CA 95117",
    "addr:housenumber":"3754",
    "addr:postcode":"95117",
    "addr:street":"Williams Rd",
    "iso:country":"US",
    "sg:address":"3754 Williams Rd",
    "sg:city":"San Jose",
    "sg:classifiers":[
        {
            "category":"Wholesale",
            "subcategory":"Non-durable Goods",
            "type":"Manufacturing & Wholesale Goods"
        }
    ],
    "sg:phone":"+1 408 243 0465",
    "sg:postcode":"95117",
    "sg:province":"CA",
    "wof:name":"Balistreri Distribution",
    "wof:placetype":"venue"
},
  "geometry": {"coordinates":[-121.96684500000001,37.308393],"type":"Point"}
}