{
  "type": "Feature",
  "properties": {
    "iso:country":"US",
    "sg:address":"1834 Windy Ct",
    "sg:city":"Cool",
    "sg:classifiers":[
        {
            "category":"Building & Trades",
            "subcategory":"Construction",
            "type":"Services"
        }
    ],
    "sg:phone":"+1 530 889 1511",
    "sg:postcode":"95614",
    "sg:province":"CA",
    "sg:tags":[
        "wallcoverings-installation",
        "wallpaper",
        "painting",
        "contractor"
    ],
    "wof:name":"Cool Mountain Painting",
    "wof:placetype":"venue"
},
  "geometry": {"coordinates":[-120.950239,38.923595],"type":"Point"}
}