{
  "type": "Feature",
  "properties": {
    "iso:country":"US",
    "sg:address":"3 Serramonte Blvd",
    "sg:city":"Daly City",
    "sg:classifiers":[
        {
            "category":"Wholesale",
            "subcategory":"Non-durable Goods",
            "type":"Manufacturing & Wholesale Goods"
        }
    ],
    "sg:phone":"+1 650 992 7298",
    "sg:postcode":"94015",
    "sg:province":"CA",
    "wof:name":"Escentual Elements",
    "wof:placetype":"venue"
},
  "geometry": {"coordinates":[-122.46664699999999,37.669491],"type":"Point"}
}