{
  "type": "Feature",
  "properties": {
    "iso:country":"US",
    "sg:address":"1836 N Broadway",
    "sg:city":"Santa Maria",
    "sg:classifiers":[
        {
            "category":"Restaurant",
            "type":"Food & Drink"
        }
    ],
    "sg:phone":"+1 805 614 0289",
    "sg:postcode":"93454",
    "sg:province":"CA",
    "wof:name":"Taco Loco",
    "wof:placetype":"venue"
},
  "geometry": {"coordinates":[-120.435499,34.974954],"type":"Point"}
}