{
  "type": "Feature",
  "properties": {
    "addr:full":"1836 N Broadway Santa Maria CA 93454",
    "addr:housenumber":"1836",
    "addr:postcode":"93454",
    "addr:street":"N Broadway",
    "iso:country":"US",
    "sg:address":"1836 N Broadway",
    "sg:city":"Santa Maria",
    "sg:classifiers":[
        {
            "category":"Restaurant",
            "type":"Food & Drink"
        }
    ],
    "sg:phone":"+1 805 614 0289",
    "sg:postcode":"93454",
    "sg:province":"CA",
    "wof:name":"Taco Loco",
    "wof:placetype":"venue"
},
  "geometry": {"coordinates":[-120.43549899999999,34.974954],"type":"Point"}
}