{
  "type": "Feature",
  "properties": {
    "iso:country":"US",
    "sg:address":"5355 Mira Sorrento Pl",
    "sg:city":"San Diego",
    "sg:classifiers":[
        {
            "category":"Professional",
            "subcategory":"Lawyer & Legal Services",
            "type":"Services"
        }
    ],
    "sg:phone":"+1 858 558 6745",
    "sg:postcode":"92121",
    "sg:province":"CA",
    "sg:tags":[
        "attorney"
    ],
    "wof:name":"Shackleford Zelkind LLP",
    "wof:placetype":"venue"
},
  "geometry": {"coordinates":[-117.202555,32.894746],"type":"Point"}
}