{
  "type": "Feature",
  "properties": {
    "iso:country":"US",
    "sg:address":"1230 E Washington St",
    "sg:city":"Colton",
    "sg:classifiers":[
        {
            "category":"Shopping",
            "subcategory":"Computers & Home Electronics",
            "type":"Retail Goods"
        }
    ],
    "sg:phone":"+1 909 370 1035",
    "sg:postcode":"92324",
    "sg:province":"CA",
    "sg:tags":[
        "equipment",
        "dealer"
    ],
    "wof:name":"Advanced Tech Computers",
    "wof:placetype":"venue"
},
  "geometry": {"coordinates":[-117.306814,34.047297],"type":"Point"}
}