{
  "type": "Feature",
  "properties": {
    "iso:country":"US",
    "sg:address":"60 Upland Rd",
    "sg:city":"Kentfield",
    "sg:classifiers":[
        {
            "category":"Building & Trades",
            "subcategory":"Construction",
            "type":"Services"
        }
    ],
    "sg:phone":"+1 415 924 9400",
    "sg:postcode":"94904",
    "sg:province":"CA",
    "sg:tags":[
        "contractor"
    ],
    "wof:name":"Bimco",
    "wof:placetype":"venue"
},
  "geometry": {"coordinates":[-122.563473,37.947813],"type":"Point"}
}