{
  "type": "Feature",
  "properties": {
    "iso:country":"US",
    "sg:address":"2122 S Hacienda Blvd",
    "sg:city":"Hacienda Heights",
    "sg:classifiers":[
        {
            "category":"Coffee & Tea",
            "type":"Food & Drink"
        }
    ],
    "sg:menulink":"http://www.allmenus.com/ca/east-san-gabriel-valley/119536-starbucks-coffee/menu/",
    "sg:phone":"+1 626 330 4216",
    "sg:postcode":"91745",
    "sg:province":"CA",
    "sg:tags":[
        "american"
    ],
    "wof:name":"Starbucks Coffee",
    "wof:placetype":"venue"
},
  "geometry": {"coordinates":[-117.96655699999999,33.995017],"type":"Point"}
}