{
  "type": "Feature",
  "properties": {
    "iso:country":"US",
    "sg:address":"440 W Foothill Blvd",
    "sg:city":"Glendora",
    "sg:classifiers":[
        {
            "category":"Health Services",
            "subcategory":"Nursing And Care Facility",
            "type":"Services"
        }
    ],
    "sg:phone":"+1 626 963 9402",
    "sg:postcode":"91741",
    "sg:province":"CA",
    "sg:tags":[
        "nurse",
        "practice-arnp",
        "nurses-advanced"
    ],
    "wof:name":"Robben-Folsom Dana K",
    "wof:placetype":"venue"
},
  "geometry": {"coordinates":[-117.87141200000001,34.136023],"type":"Point"}
}