{
  "type": "Feature",
  "properties": {
    "iso:country":"US",
    "sg:address":"3430 W Ashlan Ave",
    "sg:city":"Fresno",
    "sg:classifiers":[
        {
            "category":"Wholesale",
            "subcategory":"Auto Parts",
            "type":"Manufacturing & Wholesale Goods"
        }
    ],
    "sg:phone":"+1 559 227 7403",
    "sg:postcode":"93722",
    "sg:province":"CA",
    "sg:tags":[
        "automobile",
        "educational",
        "retail"
    ],
    "wof:name":"Auto Service Systems",
    "wof:placetype":"venue"
},
  "geometry": {"coordinates":[-119.856095,36.793599],"type":"Point"}
}