{
  "type": "Feature",
  "properties": {
    "iso:country":"US",
    "sg:address":"931 E Pico Boulevard",
    "sg:city":"Los Angeles",
    "sg:classifiers":[
        {
            "category":"Shopping",
            "subcategory":"Clothing, Apparel, & Fashions",
            "type":"Retail Goods"
        }
    ],
    "sg:phone":"+1 213 741 1007",
    "sg:postcode":"90021",
    "sg:province":"CA",
    "sg:tags":[
        "clothing",
        "women's"
    ],
    "wof:name":"Fumblin Foe",
    "wof:placetype":"venue"
},
  "geometry": {"coordinates":[-118.24942900000001,34.03082],"type":"Point"}
}