{
  "type": "Feature",
  "properties": {
    "iso:country":"US",
    "sg:address":"7459 Kenyon Ave",
    "sg:city":"Hesperia",
    "sg:classifiers":[
        {
            "category":"Building & Trades",
            "subcategory":"Pest Control",
            "type":"Services"
        }
    ],
    "sg:phone":"+1 909 823 8323",
    "sg:postcode":"92345",
    "sg:province":"CA",
    "wof:name":"Reinas Termite Control",
    "wof:placetype":"venue"
},
  "geometry": {"coordinates":[-117.283034,34.3843],"type":"Point"}
}