{
  "type": "Feature",
  "properties": {
    "addr:full":"42132 Big Bear Blvd Big Bear Lake CA 92315",
    "addr:housenumber":"42132",
    "addr:postcode":"92315",
    "addr:street":"Big Bear Blvd",
    "iso:country":"US",
    "sg:address":"42132 Big Bear Blvd",
    "sg:city":"Big Bear Lake",
    "sg:classifiers":[
        {
            "category":"Building & Trades",
            "subcategory":"Construction",
            "type":"Services"
        }
    ],
    "sg:phone":"+1 909 866 3400",
    "sg:postcode":"92315",
    "sg:province":"CA",
    "sg:tags":[
        "contractor"
    ],
    "wof:name":"Del Morris Construction",
    "wof:placetype":"venue"
},
  "geometry": {"coordinates":[-116.885817,34.243501],"type":"Point"}
}