{
  "type": "Feature",
  "properties": {
    "iso:country":"US",
    "sg:address":"1590 Oakland Road",
    "sg:city":"San Jose",
    "sg:classifiers":[
        {
            "category":"Professional",
            "subcategory":"Accounting & Tax Preparation",
            "type":"Services"
        }
    ],
    "sg:phone":"+1 408 451 9750",
    "sg:postcode":"95131",
    "sg:province":"CA",
    "sg:tags":[
        "accountant"
    ],
    "wof:name":"Bains Accountancy Corporation",
    "wof:placetype":"venue"
},
  "geometry": {"coordinates":[-121.89532199999999,37.380217],"type":"Point"}
}