{
  "type": "Feature",
  "properties": {
    "iso:country":"US",
    "sg:address":"231 E Dyer Rd Ste A",
    "sg:city":"Santa Ana",
    "sg:classifiers":[
        {
            "category":"Food & Beverages",
            "subcategory":"Bakery",
            "type":"Retail Goods"
        }
    ],
    "sg:phone":"+1 714 641 0978",
    "sg:postcode":"92707",
    "sg:province":"CA",
    "sg:tags":[
        "sandwich"
    ],
    "wof:name":"Pumper Pickle the",
    "wof:placetype":"venue"
},
  "geometry": {"coordinates":[-117.86599699999999,33.708801],"type":"Point"}
}