{
  "type": "Feature",
  "properties": {
    "addr:full":"4250 Brockton Ave Riverside CA 92501",
    "addr:housenumber":"4250",
    "addr:postcode":"92501",
    "addr:street":"Brockton Ave",
    "iso:country":"US",
    "sg:address":"4250 Brockton Ave",
    "sg:city":"Riverside",
    "sg:classifiers":[
        {
            "category":"Real Estate",
            "subcategory":"Developer",
            "type":"Services"
        }
    ],
    "sg:phone":"+1 951 341 6511",
    "sg:postcode":"92501",
    "sg:province":"CA",
    "wof:name":"Riverside Housing Development",
    "wof:placetype":"venue"
},
  "geometry": {"coordinates":[-117.38200999999999,33.97977],"type":"Point"}
}