{
  "type": "Feature",
  "properties": {
    "iso:country":"US",
    "sg:address":"398 W Washington Blvd",
    "sg:city":"Pasadena",
    "sg:classifiers":[
        {
            "category":"Restaurant",
            "type":"Food & Drink"
        }
    ],
    "sg:phone":"+1 626 798 8489",
    "sg:postcode":"91103",
    "sg:province":"CA",
    "sg:tags":[
        "caterer"
    ],
    "sg:website":"www.dillycatering.com",
    "wof:name":"Dilly Catering",
    "wof:placetype":"venue"
},
  "geometry": {"coordinates":[-118.158423,34.169629],"type":"Point"}
}