{
  "type": "Feature",
  "properties": {
    "iso:country":"US",
    "sg:address":"5650 Marconi Ave",
    "sg:city":"Carmichael",
    "sg:classifiers":[
        {
            "category":"Social Services",
            "type":"Services"
        }
    ],
    "sg:phone":"+1 916 481 1419",
    "sg:postcode":"95608",
    "sg:province":"CA",
    "sg:tags":[
        "counselor",
        "marriage",
        "family"
    ],
    "wof:name":"Meredith Lattin",
    "wof:placetype":"venue"
},
  "geometry": {"coordinates":[-121.332482,38.61713],"type":"Point"}
}