{
  "type": "Feature",
  "properties": {
    "addr:full":"7032 Orangethorpe Ave Buena Park CA 90621",
    "addr:housenumber":"7032",
    "addr:postcode":"90621",
    "addr:street":"Orangethorpe Ave",
    "iso:country":"US",
    "sg:address":"7032 Orangethorpe Ave",
    "sg:city":"Buena Park",
    "sg:classifiers":[
        {
            "category":"Travel",
            "subcategory":"Hotels & Motels",
            "type":"Entertainment"
        }
    ],
    "sg:phone":"+1 712 523 1488",
    "sg:postcode":"90621",
    "sg:province":"CA",
    "sg:website":"www.goodnite.com",
    "wof:name":"Good Nite Inn",
    "wof:placetype":"venue"
},
  "geometry": {"coordinates":[-118.00999400000001,33.858905],"type":"Point"}
}