{
  "type": "Feature",
  "properties": {
    "addr:full":"4074 East Ave Livermore CA 94550",
    "addr:housenumber":"4074",
    "addr:postcode":"94550",
    "addr:street":"East Ave",
    "iso:country":"US",
    "sg:address":"4074 East Ave",
    "sg:city":"Livermore",
    "sg:classifiers":[
        {
            "category":"Retail",
            "subcategory":"Laundry & Dry Cleaning",
            "type":"Services"
        }
    ],
    "sg:phone":"+1 925 371 6496",
    "sg:postcode":"94550",
    "sg:province":"CA",
    "sg:tags":[
        "cleaners"
    ],
    "wof:name":"East Avenue Cleaners",
    "wof:placetype":"venue"
},
  "geometry": {"coordinates":[-121.748355,37.679961],"type":"Point"}
}