{
  "type": "Feature",
  "properties": {
    "addr:full":"350 Bay St San Francisco CA 94133",
    "addr:housenumber":"350",
    "addr:postcode":"94133",
    "addr:street":"Bay St",
    "iso:country":"US",
    "sg:address":"350 Bay St",
    "sg:city":"San Francisco",
    "sg:classifiers":[
        {
            "category":"Shopping",
            "subcategory":"Computers & Home Electronics",
            "type":"Retail Goods"
        }
    ],
    "sg:phone":"+1 415 362 8915",
    "sg:postcode":"94133",
    "sg:province":"CA",
    "sg:tags":[
        "equipment",
        "electronic",
        "supply"
    ],
    "wof:name":"Radio Shack",
    "wof:placetype":"venue"
},
  "geometry": {"coordinates":[-122.412948,37.805797],"type":"Point"}
}