{
  "type": "Feature",
  "properties": {
    "iso:country":"US",
    "sg:address":"1658 Griffith Park Blvd",
    "sg:city":"Los Angeles",
    "sg:classifiers":[
        {
            "category":"Shopping",
            "subcategory":"Used Merchandise",
            "type":"Retail Goods"
        }
    ],
    "sg:phone":"+1 323 661 5052",
    "sg:postcode":"90026",
    "sg:province":"CA",
    "sg:tags":[
        "book",
        "rare",
        "dealer"
    ],
    "wof:name":"Black Ace Books",
    "wof:placetype":"venue"
},
  "geometry": {"coordinates":[-118.278118,34.093652],"type":"Point"}
}