{
  "type": "Feature",
  "properties": {
    "iso:country":"US",
    "sg:address":"1790 University Dr",
    "sg:city":"Vista",
    "sg:classifiers":[
        {
            "category":"Restaurant",
            "type":"Food & Drink"
        }
    ],
    "sg:phone":"+1 760 414 9596",
    "sg:postcode":"92083",
    "sg:province":"CA",
    "wof:name":"Carl's Jr",
    "wof:placetype":"venue"
},
  "geometry": {"coordinates":[-117.221846,33.170969],"type":"Point"}
}