{
  "type": "Feature",
  "properties": {
    "addr:full":"1017 Stonecrest Dr Antioch CA 94531",
    "addr:housenumber":"1017",
    "addr:postcode":"ca 94531",
    "addr:street":"Stonecrest Dr",
    "iso:country":"US",
    "sg:address":"1017 Stonecrest Dr",
    "sg:city":"Antioch",
    "sg:classifiers":[
        {
            "category":"Freight",
            "type":"Transportation"
        }
    ],
    "sg:phone":"+1 925 766 5826",
    "sg:postcode":"94531",
    "sg:province":"CA",
    "sg:tags":[
        "operator",
        "trucking"
    ],
    "wof:name":"Grewall Amandeep Singh",
    "wof:placetype":"venue"
},
  "geometry": {"coordinates":[-121.80388000000001,37.962122],"type":"Point"}
}