{
  "type": "Feature",
  "properties": {
    "iso:country":"US",
    "sg:address":"1938 Kellogg Ave",
    "sg:city":"Carlsbad",
    "sg:classifiers":[
        {
            "category":"Real Estate",
            "subcategory":"Architect",
            "type":"Services"
        }
    ],
    "sg:phone":"+1 760 603 0219",
    "sg:postcode":"92008",
    "sg:province":"CA",
    "wof:name":"Gowdy J Daniel Architect",
    "wof:placetype":"venue"
},
  "geometry": {"coordinates":[-117.286423,33.124839],"type":"Point"}
}