{
  "type": "Feature",
  "properties": {
    "iso:country":"US",
    "sg:address":"8657 Hayden Pl",
    "sg:city":"Culver City",
    "sg:classifiers":[
        {
            "category":"Food & Beverages",
            "subcategory":"Specialty",
            "type":"Retail Goods"
        }
    ],
    "sg:phone":"+1 310 842 8850",
    "sg:postcode":"90232",
    "sg:province":"CA",
    "sg:tags":[
        "gourmet",
        "shop"
    ],
    "wof:name":"Da Rosario",
    "wof:placetype":"venue"
},
  "geometry": {"coordinates":[-118.383759,34.021709],"type":"Point"}
}