{
  "type": "Feature",
  "properties": {
    "iso:country":"US",
    "sg:address":"501 Avalon Dr",
    "sg:city":"Vista",
    "sg:classifiers":[
        {
            "category":"Recreation",
            "type":"Entertainment"
        }
    ],
    "sg:phone":"+1 760 716 3902",
    "sg:postcode":"92084",
    "sg:province":"CA",
    "sg:tags":[
        "aquarium"
    ],
    "wof:name":"Dale's Aquarium",
    "wof:placetype":"venue"
},
  "geometry": {"coordinates":[-117.232048,33.199339],"type":"Point"}
}