{
  "type": "Feature",
  "properties": {
    "addr:full":"501 Avalon Dr Vista CA 92084",
    "addr:housenumber":"501",
    "addr:postcode":"92084",
    "addr:street":"Avalon Dr",
    "iso:country":"US",
    "sg:address":"501 Avalon Dr",
    "sg:city":"Vista",
    "sg:classifiers":[
        {
            "category":"Recreation",
            "type":"Entertainment"
        }
    ],
    "sg:phone":"+1 760 716 3902",
    "sg:postcode":"92084",
    "sg:province":"CA",
    "sg:tags":[
        "aquarium"
    ],
    "wof:name":"Dale's Aquarium",
    "wof:placetype":"venue"
},
  "geometry": {"coordinates":[-117.23204800000001,33.199339],"type":"Point"}
}