{
  "type": "Feature",
  "properties": {
    "iso:country":"US",
    "sg:address":"1038 Freedom Blvd",
    "sg:city":"Watsonville",
    "sg:classifiers":[
        {
            "category":"Professional",
            "type":"Services"
        }
    ],
    "sg:phone":"+1 831 588 4930",
    "sg:postcode":"95076",
    "sg:province":"CA",
    "sg:tags":[
        "establishment"
    ],
    "wof:name":"Sistema Ovniel Inimaginable",
    "wof:placetype":"venue"
},
  "geometry": {"coordinates":[-121.761134,36.921699],"type":"Point"}
}