{
  "type": "Feature",
  "properties": {
    "addr:full":"919 S Central Ave Ste C Glendale CA 91204",
    "addr:housenumber":"919",
    "addr:postcode":"91204",
    "addr:street":"S Central Ave Ste C",
    "iso:country":"US",
    "sg:address":"919 S Central Ave Ste C",
    "sg:city":"Glendale",
    "sg:classifiers":[
        {
            "category":"Restaurant",
            "type":"Food & Drink"
        }
    ],
    "sg:phone":"+1 818 244 3334",
    "sg:postcode":"91204",
    "sg:province":"CA",
    "sg:tags":[
        "middle",
        "eastern"
    ],
    "wof:name":"Shwarma Factory",
    "wof:placetype":"venue"
},
  "geometry": {"coordinates":[-118.25823,34.135128],"type":"Point"}
}