{
  "type": "Feature",
  "properties": {
    "addr:full":"101 University Ave Palo Alto CA 94301",
    "addr:housenumber":"101",
    "addr:postcode":"94301",
    "addr:street":"University Ave",
    "iso:country":"US",
    "sg:address":"101 University Ave",
    "sg:city":"Palo Alto",
    "sg:classifiers":[
        {
            "category":"Banks & Credit Unions",
            "subcategory":"Investment Brokerage",
            "type":"Services"
        }
    ],
    "sg:phone":"+1 650 327 9100",
    "sg:postcode":"94301",
    "sg:province":"CA",
    "sg:tags":[
        "advisory",
        "financial"
    ],
    "wof:name":"Goodwin Financial",
    "wof:placetype":"venue"
},
  "geometry": {"coordinates":[-122.16383,37.443609],"type":"Point"}
}