{
  "type": "Feature",
  "properties": {
    "iso:country":"US",
    "sg:address":"627 W Arbor Vitae St",
    "sg:city":"Inglewood",
    "sg:classifiers":[
        {
            "category":"Cinema",
            "subcategory":"Movie Rental",
            "type":"Entertainment"
        }
    ],
    "sg:phone":"+1 310 730 5510",
    "sg:postcode":"90301",
    "sg:province":"CA",
    "sg:tags":[
        "motion",
        "picture",
        "distributor",
        "film",
        "exchange"
    ],
    "wof:name":"Alexander Productions",
    "wof:placetype":"venue"
},
  "geometry": {"coordinates":[-118.36644800000001,33.952702],"type":"Point"}
}