{
  "type": "Feature",
  "properties": {
    "iso:country":"US",
    "sg:address":"11838 Bernardo Plaza Ct",
    "sg:city":"San Diego",
    "sg:classifiers":[
        {
            "category":"Real Estate",
            "subcategory":"Real Estate Agent",
            "type":"Services"
        }
    ],
    "sg:phone":"+1 858 487 7054",
    "sg:postcode":"92128",
    "sg:province":"CA",
    "wof:name":"Labianca Realty",
    "wof:placetype":"venue"
},
  "geometry": {"coordinates":[-117.076117,33.020338],"type":"Point"}
}