{
  "type": "Feature",
  "properties": {
    "iso:country":"US",
    "sg:address":"645 Clay St",
    "sg:city":"Fillmore",
    "sg:classifiers":[
        {
            "category":"Shopping",
            "subcategory":"Bicycles & Sporting Goods",
            "type":"Retail Goods"
        }
    ],
    "sg:phone":"+1 805 524 5977",
    "sg:postcode":"93015",
    "sg:province":"CA",
    "sg:tags":[
        "repair"
    ],
    "wof:name":"Mikes Gun Bluing",
    "wof:placetype":"venue"
},
  "geometry": {"coordinates":[-118.91126800000001,34.405967],"type":"Point"}
}