{
  "type": "Feature",
  "properties": {
    "iso:country":"US",
    "sg:address":"455 N D St",
    "sg:city":"San Bernardino",
    "sg:classifiers":[
        {
            "category":"Retail",
            "subcategory":"Repair Shop",
            "type":"Services"
        }
    ],
    "sg:phone":"+1 909 388 4654",
    "sg:postcode":"92401",
    "sg:province":"CA",
    "sg:tags":[
        "clocks",
        "parts"
    ],
    "wof:name":"Senior Employment Program",
    "wof:placetype":"venue"
},
  "geometry": {"coordinates":[-117.291854,34.107287],"type":"Point"}
}