{
  "type": "Feature",
  "properties": {
    "iso:country":"US",
    "sg:address":"7303 Pearblossom Hwy",
    "sg:city":"Littlerock",
    "sg:classifiers":[
        {
            "category":"Place Of Worship",
            "subcategory":"Church",
            "type":"Public Place"
        },
        {
            "category":"Place Of Worship",
            "type":"Public Place"
        }
    ],
    "sg:phone":"+1 661 944 9082",
    "sg:postcode":"93543",
    "sg:province":"CA",
    "sg:tags":[
        "churches-interdenominational",
        "churches-various",
        "denomination"
    ],
    "wof:name":"Viva Rios De Agua",
    "wof:placetype":"venue"
},
  "geometry": {"coordinates":[-117.99687900000001,34.521042],"type":"Point"}
}