{
  "type": "Feature",
  "properties": {
    "addr:full":"6350 Laurel Canyon Blvd Ste 300 North Hollywood CA 91606",
    "addr:housenumber":"6350",
    "addr:postcode":"91606",
    "addr:street":"Laurel Canyon Blvd Ste 300",
    "iso:country":"US",
    "sg:address":"6350 Laurel Canyon Blvd Ste 300",
    "sg:city":"North Hollywood",
    "sg:classifiers":[
        {
            "category":"Building & Trades",
            "subcategory":"Construction",
            "type":"Services"
        }
    ],
    "sg:phone":"+1 818 760 7100",
    "sg:postcode":"91606",
    "sg:province":"CA",
    "sg:tags":[
        "contractor"
    ],
    "wof:name":"ABC Builder Inc",
    "wof:placetype":"venue"
},
  "geometry": {"coordinates":[-118.395956,34.186365],"type":"Point"}
}