{
  "type": "Feature",
  "properties": {
    "iso:country":"US",
    "sg:address":"2584 N Locust Ave",
    "sg:city":"Rialto",
    "sg:classifiers":[
        {
            "category":"Manufacturing",
            "subcategory":"Glass & Minerals",
            "type":"Manufacturing & Wholesale Goods"
        }
    ],
    "sg:phone":"+1 909 350 8283",
    "sg:postcode":"92377",
    "sg:province":"CA",
    "sg:tags":[
        "concrete"
    ],
    "wof:name":"Conrad Constructors",
    "wof:placetype":"venue"
},
  "geometry": {"coordinates":[-117.40985499999999,34.145545],"type":"Point"}
}