{
  "type": "Feature",
  "properties": {
    "iso:country":"US",
    "sg:address":"830 Lawn Ct",
    "sg:city":"Tracy",
    "sg:classifiers":[
        {
            "category":"Professional",
            "type":"Services"
        }
    ],
    "sg:phone":"+1 209 836 4910",
    "sg:postcode":"95376",
    "sg:province":"CA",
    "wof:name":"Xpert Judgment Recovery",
    "wof:placetype":"venue"
},
  "geometry": {"coordinates":[-121.43691200000001,37.732889],"type":"Point"}
}