{
  "type": "Feature",
  "properties": {
    "iso:country":"US",
    "sg:address":"3822 Ray St",
    "sg:city":"San Diego",
    "sg:classifiers":[
        {
            "category":"Personal",
            "subcategory":"Beauty Salon",
            "type":"Services"
        }
    ],
    "sg:phone":"+1 619 997 3293",
    "sg:postcode":"92104",
    "sg:province":"CA",
    "sg:tags":[
        "hair"
    ],
    "wof:name":"Luxe Hair Studio",
    "wof:placetype":"venue"
},
  "geometry": {"coordinates":[-117.12925,32.747847],"type":"Point"}
}