{
  "type": "Feature",
  "properties": {
    "iso:country":"US",
    "sg:address":"8061 Vineland Ave",
    "sg:city":"Sun Valley",
    "sg:classifiers":[
        {
            "category":"Retail",
            "subcategory":"Laundry & Dry Cleaning",
            "type":"Services"
        }
    ],
    "sg:phone":"+1 818 767 2237",
    "sg:postcode":"91352",
    "sg:province":"CA",
    "wof:name":"Sun Valley Ctr Cleaners",
    "wof:placetype":"venue"
},
  "geometry": {"coordinates":[-118.370411,34.217177],"type":"Point"}
}