{
  "type": "Feature",
  "properties": {
    "iso:country":"US",
    "sg:address":"8427 Stewart And Gray Rd",
    "sg:city":"Downey",
    "sg:classifiers":[
        {
            "category":"Banks & Credit Unions",
            "subcategory":"Bank",
            "type":"Services"
        },
        {
            "category":"Banks & Credit Unions",
            "subcategory":"Financial Services",
            "type":"Services"
        }
    ],
    "sg:phone":"+1 562 622 0303",
    "sg:postcode":"90241",
    "sg:province":"CA",
    "sg:tags":[
        "saving",
        "loan",
        "commercial",
        "banking",
        "internet"
    ],
    "sg:website":"https://www.bankofamerica.com/",
    "wof:name":"Bank of America",
    "wof:placetype":"venue"
},
  "geometry": {"coordinates":[-118.136383,33.931129],"type":"Point"}
}