{
  "type": "Feature",
  "properties": {
    "iso:country":"US",
    "sg:address":"190 Depot Dr",
    "sg:city":"Corona",
    "sg:classifiers":[
        {
            "category":"Retail",
            "subcategory":"Auto Repair",
            "type":"Services"
        }
    ],
    "sg:phone":"+1 951 371 6400",
    "sg:postcode":"92882",
    "sg:province":"CA",
    "sg:tags":[
        "automotive",
        "information"
    ],
    "wof:name":"Xpress Auto Svc",
    "wof:placetype":"venue"
},
  "geometry": {"coordinates":[-117.567398,33.882173],"type":"Point"}
}