{
  "type": "Feature",
  "properties": {
    "iso:country":"US",
    "sg:address":"211 Driftwood Dr",
    "sg:city":"Suisun City",
    "sg:classifiers":[
        {
            "category":"Retail",
            "subcategory":"Auto Repair",
            "type":"Services"
        },
        {
            "category":"Autos & Motor Vehicles",
            "subcategory":"Auto Supplies",
            "type":"Retail Goods"
        }
    ],
    "sg:phone":"+1 707 425 2996",
    "sg:postcode":"94585",
    "sg:province":"CA",
    "sg:tags":[
        "engine",
        "e",
        "automotive",
        "high",
        "parts",
        "build",
        "exchanging",
        "performance"
    ],
    "wof:name":"T O E Performance Products",
    "wof:placetype":"venue"
},
  "geometry": {"coordinates":[-122.041878,38.241361],"type":"Point"}
}