{
  "type": "Feature",
  "properties": {
    "addr:full":"321 6th St Turlock CA 95380",
    "addr:housenumber":"321",
    "addr:postcode":"95380",
    "addr:street":"6Th St",
    "iso:country":"US",
    "sg:address":"321 6th St",
    "sg:city":"Turlock",
    "sg:classifiers":[
        {
            "category":"Wholesale",
            "subcategory":"Farm Supplies",
            "type":"Manufacturing & Wholesale Goods"
        }
    ],
    "sg:phone":"+1 209 664 0944",
    "sg:postcode":"95380",
    "sg:province":"CA",
    "wof:name":"Hilmar Country Plaza",
    "wof:placetype":"venue"
},
  "geometry": {"coordinates":[-120.84814799999999,37.487716],"type":"Point"}
}