{
  "type": "Feature",
  "properties": {
    "addr:full":"2414 Shelbourne Way Antioch CA 94531",
    "addr:housenumber":"2414",
    "addr:postcode":"ca 94531",
    "addr:street":"Shelbourne Way",
    "iso:country":"US",
    "sg:address":"2414 Shelbourne Way",
    "sg:city":"Antioch",
    "sg:classifiers":[
        {
            "category":"Health Services",
            "subcategory":"Medical Lab",
            "type":"Services"
        }
    ],
    "sg:phone":"+1 925 754 6896",
    "sg:postcode":"94531",
    "sg:province":"CA",
    "sg:tags":[
        "laboratory"
    ],
    "wof:name":"Comarell Delta Dental Svc",
    "wof:placetype":"venue"
},
  "geometry": {"coordinates":[-121.779297,37.984092],"type":"Point"}
}