{
  "type": "Feature",
  "properties": {
    "addr:full":"714 W Olympic Blvd Los Angeles CA 90015",
    "addr:housenumber":"714",
    "addr:postcode":"90015",
    "addr:street":"W Olympic Blvd",
    "iso:country":"US",
    "sg:address":"714 W Olympic Blvd",
    "sg:city":"Los Angeles",
    "sg:classifiers":[
        {
            "category":"Professional",
            "subcategory":"Management & Consulting",
            "type":"Services"
        }
    ],
    "sg:phone":"+1 213 747 8612",
    "sg:postcode":"90015",
    "sg:province":"CA",
    "sg:tags":[
        "marketing",
        "travel"
    ],
    "wof:name":"Student World Traveler",
    "wof:placetype":"venue"
},
  "geometry": {"coordinates":[-118.26382599999999,34.044855],"type":"Point"}
}