{
  "type": "Feature",
  "properties": {
    "addr:full":"3008 Hyde Park Blvd Los Angeles CA 90043",
    "addr:housenumber":"3008",
    "addr:postcode":"90043",
    "addr:street":"Hyde Park Blvd",
    "iso:country":"US",
    "sg:address":"3008 Hyde Park Blvd",
    "sg:city":"Los Angeles",
    "sg:classifiers":[
        {
            "category":"Shopping",
            "subcategory":"Used Merchandise",
            "type":"Retail Goods"
        }
    ],
    "sg:phone":"+1 323 759 4629",
    "sg:postcode":"90043",
    "sg:province":"CA",
    "sg:tags":[
        "furniture"
    ],
    "wof:name":"Fine Antique Furniture",
    "wof:placetype":"venue"
},
  "geometry": {"coordinates":[-118.326415,33.980572],"type":"Point"}
}