{
  "type": "Feature",
  "properties": {
    "iso:country":"US",
    "sg:address":"5560 Skylane Blvd",
    "sg:city":"Santa Rosa",
    "sg:classifiers":[
        {
            "category":"Shopping",
            "subcategory":"Computers & Home Electronics",
            "type":"Retail Goods"
        }
    ],
    "sg:phone":"+1 707 527 4060",
    "sg:postcode":"95403",
    "sg:province":"CA",
    "sg:tags":[
        "software"
    ],
    "wof:name":"Software Solutions",
    "wof:placetype":"venue"
},
  "geometry": {"coordinates":[-122.798692,38.514485],"type":"Point"}
}