{
  "type": "Feature",
  "properties": {
    "addr:full":"875 El Camino Real San Bruno CA 94066",
    "addr:housenumber":"875",
    "addr:postcode":"94066",
    "addr:street":"El Camino Real",
    "iso:country":"US",
    "sg:address":"875 El Camino Real",
    "sg:city":"San Bruno",
    "sg:classifiers":[
        {
            "category":"Banks & Credit Unions",
            "subcategory":"Bank",
            "type":"Services"
        }
    ],
    "sg:phone":"+1 650 875 7064",
    "sg:postcode":"94066",
    "sg:province":"CA",
    "sg:website":"www.wellsfargo.com",
    "wof:name":"Wells Fargo",
    "wof:placetype":"venue"
},
  "geometry": {"coordinates":[-122.417457,37.63],"type":"Point"}
}