{
  "type": "Feature",
  "properties": {
    "addr:full":"706 6th Ave Venice CA 90291",
    "addr:housenumber":"706",
    "addr:postcode":"90291",
    "addr:street":"6Th Ave",
    "iso:country":"US",
    "sg:address":"706 6th Ave",
    "sg:city":"Venice",
    "sg:classifiers":[
        {
            "category":"Building & Trades",
            "subcategory":"Construction",
            "type":"Services"
        }
    ],
    "sg:phone":"+1 310 399 0771",
    "sg:postcode":"90291",
    "sg:province":"CA",
    "sg:tags":[
        "designer"
    ],
    "wof:name":"Stratton Design",
    "wof:placetype":"venue"
},
  "geometry": {"coordinates":[-118.469357,33.996234],"type":"Point"}
}