{
  "type": "Feature",
  "properties": {
    "iso:country":"US",
    "sg:address":"1214 Maple St",
    "sg:city":"Marysville",
    "sg:classifiers":[
        {
            "category":"Manufacturing",
            "subcategory":"Printing",
            "type":"Manufacturing & Wholesale Goods"
        }
    ],
    "sg:phone":"+1 530 743 6523",
    "sg:postcode":"95901",
    "sg:province":"CA",
    "sg:tags":[
        "commercial"
    ],
    "wof:name":"Agles Forms & More",
    "wof:placetype":"venue"
},
  "geometry": {"coordinates":[-121.595661,39.148692],"type":"Point"}
}