{
  "type": "Feature",
  "properties": {
    "iso:country":"US",
    "sg:address":"4705 Clairmont Drive",
    "sg:city":"San Diego",
    "sg:classifiers":[
        {
            "category":"Restaurant",
            "type":"Food & Drink"
        }
    ],
    "sg:phone":"+1 858 270 2020",
    "sg:postcode":"92117",
    "sg:province":"CA",
    "sg:tags":[
        "pizza"
    ],
    "sg:website":"extremepizza.com",
    "wof:name":"Extreme Pizza",
    "wof:placetype":"venue"
},
  "geometry": {"coordinates":[-117.205817,32.830856],"type":"Point"}
}