{
  "type": "Feature",
  "properties": {
    "addr:full":"900 Lenzen Ave San Jose CA 95126",
    "addr:housenumber":"900",
    "addr:postcode":"95126",
    "addr:street":"Lenzen Ave",
    "iso:country":"US",
    "sg:address":"900 Lenzen Ave",
    "sg:city":"San Jose",
    "sg:classifiers":[
        {
            "category":"Wholesale",
            "subcategory":"Fruits & Vegetables",
            "type":"Manufacturing & Wholesale Goods"
        }
    ],
    "sg:phone":"+1 408 288 8810",
    "sg:postcode":"95126",
    "sg:province":"CA",
    "sg:tags":[
        "veggie"
    ],
    "sg:website":"www.asiana-produce.com",
    "wof:name":"Asiana Produce Inc",
    "wof:placetype":"venue"
},
  "geometry": {"coordinates":[-121.912003,37.334801],"type":"Point"}
}