{
  "type": "Feature",
  "properties": {
    "iso:country":"US",
    "sg:address":"655 W Tennyson Rd",
    "sg:city":"Hayward",
    "sg:classifiers":[
        {
            "category":"Real Estate",
            "subcategory":"Real Estate Operator",
            "type":"Services"
        }
    ],
    "sg:phone":"+1 510 538 7400",
    "sg:postcode":"94544",
    "sg:province":"CA",
    "sg:tags":[
        "apartment"
    ],
    "wof:name":"Archstone Barrington Hills",
    "wof:placetype":"venue"
},
  "geometry": {"coordinates":[-122.06827699999999,37.632234],"type":"Point"}
}