{
  "type": "Feature",
  "properties": {
    "iso:country":"US",
    "sg:address":"13205 McCarter Way",
    "sg:city":"Grass Valley",
    "sg:classifiers":[
        {
            "category":"Retail",
            "subcategory":"Animal Services",
            "type":"Services"
        }
    ],
    "sg:phone":"+1 530 274 2236",
    "sg:postcode":"95949",
    "sg:province":"CA",
    "wof:name":"Newdawn Dog Rescue",
    "wof:placetype":"venue"
},
  "geometry": {"coordinates":[-121.114485,39.17513],"type":"Point"}
}