{
  "type": "Feature",
  "properties": {
    "iso:country":"US",
    "sg:address":"581 Churchill Downs Ct",
    "sg:city":"Walnut Creek",
    "sg:classifiers":[
        {
            "category":"Professional",
            "type":"Services"
        }
    ],
    "sg:phone":"+1 925 930 8598",
    "sg:postcode":"94597",
    "sg:province":"CA",
    "wof:name":"Audrey Hunt Vocal Co",
    "wof:placetype":"venue"
},
  "geometry": {"coordinates":[-122.062952,37.913552],"type":"Point"}
}