{
  "type": "Feature",
  "properties": {
    "addr:full":"15221 Beach Boulevard Westminster CA 92683",
    "addr:housenumber":"15221",
    "addr:postcode":"92683",
    "addr:street":"Beach Boulevard",
    "iso:country":"US",
    "sg:address":"15221 Beach Boulevard",
    "sg:city":"Westminster",
    "sg:classifiers":[
        {
            "category":"Government",
            "subcategory":"Office",
            "type":"Public Place"
        }
    ],
    "sg:phone":"+1 714 893 8544",
    "sg:postcode":"92683",
    "sg:province":"CA",
    "sg:tags":[
        "smog",
        "check"
    ],
    "wof:name":"Pep Boys Automotive",
    "wof:placetype":"venue"
},
  "geometry": {"coordinates":[-117.98944299999999,33.741291],"type":"Point"}
}