{
  "type": "Feature",
  "properties": {
    "addr:full":"41825 State Hwy 74 Hemet CA 92544",
    "addr:housenumber":"41825",
    "addr:postcode":"92544",
    "addr:street":"State Hwy 74",
    "iso:country":"US",
    "sg:address":"41825 State Hwy 74",
    "sg:city":"Hemet",
    "sg:classifiers":[
        {
            "category":"Shopping",
            "subcategory":"Tobacco",
            "type":"Retail Goods"
        }
    ],
    "sg:phone":"+1 951 765 2001",
    "sg:postcode":"92544",
    "sg:province":"CA",
    "sg:tags":[
        "cigarette",
        "cigar",
        "dealer"
    ],
    "wof:name":"Cigar House",
    "wof:placetype":"venue"
},
  "geometry": {"coordinates":[-116.932576,33.747737],"type":"Point"}
}