{
  "type": "Feature",
  "properties": {
    "iso:country":"US",
    "sg:address":"8745 Shirley Ave",
    "sg:city":"Northridge",
    "sg:classifiers":[
        {
            "category":"Shopping",
            "subcategory":"Clothing, Apparel, & Fashions",
            "type":"Retail Goods"
        }
    ],
    "sg:phone":"+1 818 727 7039",
    "sg:postcode":"91324",
    "sg:province":"CA",
    "sg:tags":[
        "baby",
        "accessory"
    ],
    "wof:name":"Bananafish",
    "wof:placetype":"venue"
},
  "geometry": {"coordinates":[-118.558008,34.229129],"type":"Point"}
}