{
  "type": "Feature",
  "properties": {
    "iso:country":"US",
    "sg:address":"18744 Main St",
    "sg:city":"Groveland",
    "sg:classifiers":[
        {
            "category":"Shopping",
            "subcategory":"Used Merchandise",
            "type":"Retail Goods"
        }
    ],
    "sg:phone":"+1 209 962 7112",
    "sg:postcode":"95321",
    "sg:province":"CA",
    "sg:tags":[
        "antique"
    ],
    "sg:website":"www.jenniferandcompany.com",
    "wof:name":"Jennifer & Co",
    "wof:placetype":"venue"
},
  "geometry": {"coordinates":[-120.230733,37.838607],"type":"Point"}
}