{
  "type": "Feature",
  "properties": {
    "iso:country":"US",
    "sg:address":"1511 San Andres St",
    "sg:city":"Santa Barbara",
    "sg:classifiers":[
        {
            "category":"Retail",
            "subcategory":"Self-service Laundry",
            "type":"Services"
        }
    ],
    "sg:phone":"+1 805 899 7701",
    "sg:postcode":"93101",
    "sg:province":"CA",
    "wof:name":"Super Laundry",
    "wof:placetype":"venue"
},
  "geometry": {"coordinates":[-119.71641,34.418784],"type":"Point"}
}