{
  "type": "Feature",
  "properties": {
    "iso:country":"US",
    "sg:address":"1235 N Harbor Blvd",
    "sg:city":"Fullerton",
    "sg:classifiers":[
        {
            "category":"Education",
            "subcategory":"Special Training",
            "type":"Public Place"
        }
    ],
    "sg:phone":"+1 714 870 2795",
    "sg:postcode":"92835",
    "sg:province":"CA",
    "sg:tags":[
        "tutoring"
    ],
    "sg:website":"www.kingmathusa.com",
    "wof:name":"King Learning Center",
    "wof:placetype":"venue"
},
  "geometry": {"coordinates":[-117.924955,33.881191],"type":"Point"}
}