{
  "type": "Feature",
  "properties": {
    "iso:country":"US",
    "sg:address":"5728 Garfield Ave",
    "sg:city":"Sacramento",
    "sg:classifiers":[
        {
            "category":"Home & Garden",
            "subcategory":"Furniture",
            "type":"Retail Goods"
        }
    ],
    "sg:phone":"+1 916 331 3896",
    "sg:postcode":"95841",
    "sg:province":"CA",
    "wof:name":"Ala Mode Furnishings",
    "wof:placetype":"venue"
},
  "geometry": {"coordinates":[-121.336766,38.672159],"type":"Point"}
}