{
  "type": "Feature",
  "properties": {
    "iso:country":"US",
    "sg:address":"313 S Mirage Ave",
    "sg:city":"Lindsay",
    "sg:classifiers":[
        {
            "category":"Retail",
            "subcategory":"Self-service Laundry",
            "type":"Services"
        }
    ],
    "sg:phone":"+1 559 784 2797",
    "sg:postcode":"93247",
    "sg:province":"CA",
    "wof:name":"Lindsay Laundromat",
    "wof:placetype":"venue"
},
  "geometry": {"coordinates":[-119.087548,36.200482],"type":"Point"}
}