{
  "type": "Feature",
  "properties": {
    "iso:country":"US",
    "sg:address":"30 S el Camino Real",
    "sg:city":"San Mateo",
    "sg:classifiers":[
        {
            "category":"Professional",
            "subcategory":"Management & Consulting",
            "type":"Services"
        }
    ],
    "sg:phone":"+1 650 570 0505",
    "sg:postcode":"94401",
    "sg:province":"CA",
    "sg:tags":[
        "communications",
        "consultant"
    ],
    "sg:website":"www.csd-inc.com",
    "wof:name":"Communications Sales Dynamics",
    "wof:placetype":"venue"
},
  "geometry": {"coordinates":[-122.327614,37.564668],"type":"Point"}
}