{
  "type": "Feature",
  "properties": {
    "iso:country":"US",
    "sg:address":"1955 The Alameda Floor 1",
    "sg:city":"San Jose",
    "sg:classifiers":[
        {
            "category":"Professional",
            "subcategory":"Computer Services",
            "type":"Services"
        }
    ],
    "sg:phone":"+1 408 320 0318",
    "sg:postcode":"95126",
    "sg:province":"CA",
    "sg:tags":[
        "repair"
    ],
    "sg:website":"www.cogentsol.com",
    "wof:name":"Cogent Solutions Inc.",
    "wof:placetype":"venue"
},
  "geometry": {"coordinates":[-121.92481100000001,37.34152],"type":"Point"}
}