{
  "type": "Feature",
  "properties": {
    "addr:full":"9450 Gilman Dr UCSD Campus San Diego CA 92101",
    "addr:housenumber":"9450",
    "addr:postcode":"92101",
    "addr:street":"Gilman Dr",
    "iso:country":"US",
    "sg:address":"9450 Gilman Dr UCSD Campus",
    "sg:city":"San Diego",
    "sg:classifiers":[
        {
            "category":"Shopping",
            "subcategory":"Used Merchandise",
            "type":"Retail Goods"
        }
    ],
    "sg:phone":"+1 858 534 1124",
    "sg:postcode":"92101",
    "sg:province":"CA",
    "sg:tags":[
        "vintage",
        "consignment"
    ],
    "sg:website":"www.facebook.com/pages/La-Jolla-...",
    "wof:name":"Friends' Resale/Thrift Shop",
    "wof:placetype":"venue"
},
  "geometry": {"coordinates":[-117.23866200000001,32.876822],"type":"Point"}
}