{
  "type": "Feature",
  "properties": {
    "addr:full":"3424 Fruitridge Rd Sacramento CA 95820",
    "addr:housenumber":"3424",
    "addr:postcode":"95820",
    "addr:street":"Fruitridge Rd",
    "iso:country":"US",
    "sg:address":"3424 Fruitridge Rd",
    "sg:city":"Sacramento",
    "sg:classifiers":[
        {
            "category":"Organizations",
            "subcategory":"Religious Organization",
            "type":"Services"
        }
    ],
    "sg:phone":"+1 916 421 8207",
    "sg:postcode":"95820",
    "sg:province":"CA",
    "sg:tags":[
        "church"
    ],
    "wof:name":"Maranatha Christian Church",
    "wof:placetype":"venue"
},
  "geometry": {"coordinates":[-121.47014799999999,38.524902],"type":"Point"}
}