{
  "type": "Feature",
  "properties": {
    "addr:full":"25016 Narbonne Ave Lomita CA 90717",
    "addr:postcode":"25016;90717",
    "addr:street":"Narbonne Ave",
    "iso:country":"US",
    "sg:address":"25016 Narbonne Ave",
    "sg:city":"Lomita",
    "sg:classifiers":[
        {
            "category":"Building & Trades",
            "subcategory":"Construction",
            "type":"Services"
        }
    ],
    "sg:phone":"+1 310 872 8916",
    "sg:postcode":"90717",
    "sg:province":"CA",
    "sg:tags":[
        "repair",
        "handyman",
        "maintenance",
        "home"
    ],
    "wof:name":"Jet Speed Plumbing",
    "wof:placetype":"venue"
},
  "geometry": {"coordinates":[-118.31997,33.798035],"type":"Point"}
}