{
  "type": "Feature",
  "properties": {
    "addr:full":"3042 Ocean View Blvd San Diego CA 92113",
    "addr:housenumber":"3042",
    "addr:postcode":"92113",
    "addr:street":"Ocean View Blvd",
    "iso:country":"US",
    "sg:address":"3042 Ocean View Blvd",
    "sg:city":"San Diego",
    "sg:classifiers":[
        {
            "category":"Personal",
            "subcategory":"Beauty Salon",
            "type":"Services"
        }
    ],
    "sg:phone":"+1 619 702 6261",
    "sg:postcode":"92113",
    "sg:province":"CA",
    "sg:tags":[
        "hair"
    ],
    "wof:name":"Fantastik Beauty Salon And Permanent Makeup",
    "wof:placetype":"venue"
},
  "geometry": {"coordinates":[-117.12855999999999,32.701319],"type":"Point"}
}