{
  "type": "Feature",
  "properties": {
    "addr:full":"1000 Town Center Dr Oxnard CA 93036",
    "addr:housenumber":"1000",
    "addr:postcode":"93036",
    "addr:street":"Town Center Dr",
    "iso:country":"US",
    "sg:address":"1000 Town Center Dr",
    "sg:city":"Oxnard",
    "sg:classifiers":[
        {
            "category":"Wholesale",
            "subcategory":"Non-durable Goods",
            "type":"Manufacturing & Wholesale Goods"
        }
    ],
    "sg:phone":"+1 805 278 9332",
    "sg:postcode":"93036",
    "sg:province":"CA",
    "wof:name":"Kysela Imports Inc",
    "wof:placetype":"venue"
},
  "geometry": {"coordinates":[-119.182973,34.242698],"type":"Point"}
}