{
  "type": "Feature",
  "properties": {
    "iso:country":"US",
    "sg:address":"120 N Campus Ave",
    "sg:city":"Ontario",
    "sg:classifiers":[
        {
            "category":"Autos & Motor Vehicles",
            "subcategory":"Auto Supplies",
            "type":"Retail Goods"
        }
    ],
    "sg:phone":"+1 909 988 6974",
    "sg:postcode":"91764",
    "sg:province":"CA",
    "sg:tags":[
        "tire"
    ],
    "wof:name":"Chanos Tire Shop",
    "wof:placetype":"venue"
},
  "geometry": {"coordinates":[-117.641414,34.063651],"type":"Point"}
}