{
  "type": "Feature",
  "properties": {
    "iso:country":"US",
    "sg:address":"2845 Clemson Dr",
    "sg:city":"Shingle Springs",
    "sg:classifiers":[
        {
            "category":"Professional",
            "type":"Services"
        }
    ],
    "sg:phone":"+1 530 677 5853",
    "sg:postcode":"95682",
    "sg:province":"CA",
    "wof:name":"Wendy Galli",
    "wof:placetype":"venue"
},
  "geometry": {"coordinates":[-121.005143,38.688955],"type":"Point"}
}