{
  "type": "Feature",
  "properties": {
    "addr:full":"4020 Paloma St Los Angeles CA 90011",
    "addr:housenumber":"4020",
    "addr:postcode":"90011",
    "addr:street":"Paloma St",
    "iso:country":"US",
    "sg:address":"4020 Paloma St",
    "sg:city":"Los Angeles",
    "sg:classifiers":[
        {
            "category":"Organizations",
            "subcategory":"Religious Organization",
            "type":"Services"
        }
    ],
    "sg:phone":"+1 323 232 4734",
    "sg:postcode":"90011",
    "sg:province":"CA",
    "sg:tags":[
        "church"
    ],
    "wof:name":"New Life Baptist Church",
    "wof:placetype":"venue"
},
  "geometry": {"coordinates":[-118.261905,34.010324],"type":"Point"}
}