{
  "type": "Feature",
  "properties": {
    "addr:full":"416 W Visalia Rd Exeter CA 93221",
    "addr:housenumber":"416",
    "addr:postcode":"93221",
    "addr:street":"W Visalia Rd",
    "iso:country":"US",
    "sg:address":"416 W Visalia Rd",
    "sg:city":"Exeter",
    "sg:classifiers":[
        {
            "category":"Shopping",
            "subcategory":"Used Merchandise",
            "type":"Retail Goods"
        }
    ],
    "sg:phone":"+1 559 592 1590",
    "sg:postcode":"93221",
    "sg:province":"CA",
    "sg:tags":[
        "shop",
        "consignment"
    ],
    "wof:name":"Winn Communications",
    "wof:placetype":"venue"
},
  "geometry": {"coordinates":[-119.14700000000001,36.297177],"type":"Point"}
}