{
  "type": "Feature",
  "properties": {
    "iso:country":"US",
    "sg:address":"947 D St",
    "sg:city":"Ramona",
    "sg:classifiers":[
        {
            "category":"Insurance",
            "subcategory":"Insurance Agent",
            "type":"Services"
        },
        {
            "category":"Insurance",
            "subcategory":"Hazard Insurance",
            "type":"Services"
        },
        {
            "category":"Insurance",
            "subcategory":"Title Insurance",
            "type":"Services"
        },
        {
            "category":"Insurance",
            "subcategory":"Life Insurance",
            "type":"Services"
        }
    ],
    "sg:phone":"+1 760 789 5200",
    "sg:postcode":"92065",
    "sg:province":"CA",
    "sg:tags":[
        "business",
        "auto",
        "commercial",
        "homeowner",
        "motorcycle",
        "renter"
    ],
    "wof:name":"Allstate Insurance Company - Brook Daly",
    "wof:placetype":"venue"
},
  "geometry": {"coordinates":[-116.867025,33.041551],"type":"Point"}
}