{
  "type": "Feature",
  "properties": {
    "iso:country":"US",
    "sg:address":"1045 5th St",
    "sg:city":"Colusa",
    "sg:classifiers":[
        {
            "category":"Professional",
            "type":"Services"
        }
    ],
    "sg:phone":"+1 530 458 4414",
    "sg:postcode":"95932",
    "sg:province":"CA",
    "sg:tags":[
        "establishment"
    ],
    "wof:name":"Stagedoor",
    "wof:placetype":"venue"
},
  "geometry": {"coordinates":[-122.010837,39.20632],"type":"Point"}
}