{
  "type": "Feature",
  "properties": {
    "iso:country":"US",
    "sg:address":"7648 Painter Ave",
    "sg:city":"Whittier",
    "sg:classifiers":[
        {
            "category":"Health Services",
            "subcategory":"Chiropractor",
            "type":"Services"
        }
    ],
    "sg:phone":"+1 562 696 2016",
    "sg:postcode":"90602",
    "sg:province":"CA",
    "wof:name":"Dietz Chiropractic",
    "wof:placetype":"venue"
},
  "geometry": {"coordinates":[-118.032598,33.972013],"type":"Point"}
}