{
  "type": "Feature",
  "properties": {
    "addr:full":"1715 Carlson Ln Redondo Beach CA 90278",
    "addr:housenumber":"1715",
    "addr:postcode":"90278",
    "addr:street":"Carlson Ln",
    "iso:country":"US",
    "sg:address":"1715 Carlson Ln",
    "sg:city":"Redondo Beach",
    "sg:classifiers":[
        {
            "category":"Professional",
            "subcategory":"Accounting & Tax Preparation",
            "type":"Services"
        }
    ],
    "sg:phone":"+1 310 318 7844",
    "sg:postcode":"90278",
    "sg:province":"CA",
    "sg:tags":[
        "accountant"
    ],
    "wof:name":"Absolute Tax & Accounting",
    "wof:placetype":"venue"
},
  "geometry": {"coordinates":[-118.38137,33.86012],"type":"Point"}
}