{
  "type": "Feature",
  "properties": {
    "iso:country":"US",
    "sg:address":"155 Moffett Park Dr",
    "sg:city":"Sunnyvale",
    "sg:classifiers":[
        {
            "category":"Shopping",
            "subcategory":"Computers & Home Electronics",
            "type":"Retail Goods"
        }
    ],
    "sg:phone":"+1 408 744 0102",
    "sg:postcode":"94089",
    "sg:province":"CA",
    "sg:tags":[
        "equipment",
        "dealer"
    ],
    "sg:website":"www.jeskel.com",
    "wof:name":"Jeskell",
    "wof:placetype":"venue"
},
  "geometry": {"coordinates":[-122.013537,37.406262],"type":"Point"}
}