{
  "type": "Feature",
  "properties": {
    "iso:country":"US",
    "sg:address":"1115 E Houston Ave",
    "sg:city":"Visalia",
    "sg:classifiers":[
        {
            "category":"Home & Garden",
            "subcategory":"Building Materials",
            "type":"Retail Goods"
        }
    ],
    "sg:phone":"+1 559 627 4100",
    "sg:postcode":"93292",
    "sg:province":"CA",
    "sg:tags":[
        "paint"
    ],
    "wof:name":"Spectra Tone",
    "wof:placetype":"venue"
},
  "geometry": {"coordinates":[-119.27882700000001,36.34177],"type":"Point"}
}