{
  "type": "Feature",
  "properties": {
    "iso:country":"US",
    "sg:address":"4032 Wilshire Blvd",
    "sg:city":"Los Angeles",
    "sg:classifiers":[
        {
            "category":"Real Estate",
            "subcategory":"Real Estate Agent",
            "type":"Services"
        }
    ],
    "sg:phone":"+1 213 380 3024",
    "sg:postcode":"90010",
    "sg:province":"CA",
    "sg:tags":[
        "appraiser"
    ],
    "wof:name":"Kristy Yun",
    "wof:placetype":"venue"
},
  "geometry": {"coordinates":[-118.316488,34.061621],"type":"Point"}
}