{
  "type": "Feature",
  "properties": {
    "iso:country":"US",
    "sg:address":"1065 E Anaheim St",
    "sg:city":"Long Beach",
    "sg:classifiers":[
        {
            "category":"Travel",
            "subcategory":"Travel Agent",
            "type":"Entertainment"
        }
    ],
    "sg:phone":"+1 562 599 5464",
    "sg:postcode":"90813",
    "sg:province":"CA",
    "sg:tags":[
        "agency"
    ],
    "wof:name":"Asian Pacific",
    "wof:placetype":"venue"
},
  "geometry": {"coordinates":[-118.180063,33.782604],"type":"Point"}
}