{
  "type": "Feature",
  "properties": {
    "addr:full":"19234 Lake Chabot Rd Castro Valley CA 94546",
    "addr:housenumber":"19234",
    "addr:postcode":"94546",
    "addr:street":"Lake Chabot Rd",
    "iso:country":"US",
    "sg:address":"19234 Lake Chabot Rd",
    "sg:city":"Castro Valley",
    "sg:classifiers":[
        {
            "category":"Social Services",
            "subcategory":"Child Care",
            "type":"Services"
        }
    ],
    "sg:phone":"+1 510 278 1115",
    "sg:postcode":"94546",
    "sg:province":"CA",
    "sg:tags":[
        "elementary",
        "kindergarten",
        "school",
        "academic"
    ],
    "wof:name":"Montessori Schools",
    "wof:placetype":"venue"
},
  "geometry": {"coordinates":[-122.089996,37.705502],"type":"Point"}
}