{
  "type": "Feature",
  "properties": {
    "iso:country":"US",
    "sg:address":"4300 Broadway St",
    "sg:city":"Eureka",
    "sg:classifiers":[
        {
            "category":"Manufacturing",
            "subcategory":"Buildings",
            "type":"Manufacturing & Wholesale Goods"
        }
    ],
    "sg:phone":"+1 707 442 5781",
    "sg:postcode":"95503",
    "sg:province":"CA",
    "sg:tags":[
        "prefab"
    ],
    "wof:name":"W & W Mobile Home Sales Inc",
    "wof:placetype":"venue"
},
  "geometry": {"coordinates":[-124.19176899999999,40.766985],"type":"Point"}
}