{
  "type": "Feature",
  "properties": {
    "addr:full":"2119 Andover Pl Cambria CA 93428",
    "addr:housenumber":"2119",
    "addr:postcode":"93428",
    "addr:street":"Andover Pl",
    "iso:country":"US",
    "sg:address":"2119 Andover Pl",
    "sg:city":"Cambria",
    "sg:classifiers":[
        {
            "category":"Building & Trades",
            "subcategory":"Electrical",
            "type":"Services"
        }
    ],
    "sg:phone":"+1 805 927 0314",
    "sg:postcode":"93428",
    "sg:province":"CA",
    "sg:tags":[
        "electrical",
        "contractor"
    ],
    "wof:name":"Mm Electric",
    "wof:placetype":"venue"
},
  "geometry": {"coordinates":[-121.08865,35.557415],"type":"Point"}
}