{
  "type": "Feature",
  "properties": {
    "iso:country":"US",
    "sg:address":"1501 Alamo Dr",
    "sg:city":"Vacaville",
    "sg:classifiers":[
        {
            "category":"Building & Trades",
            "subcategory":"Construction",
            "type":"Services"
        }
    ],
    "sg:phone":"+1 707 249 3671",
    "sg:postcode":"95687",
    "sg:province":"CA",
    "sg:tags":[
        "cabling",
        "wiring",
        "telecommunication"
    ],
    "wof:name":"With AK Svc",
    "wof:placetype":"venue"
},
  "geometry": {"coordinates":[-121.982719,38.335491],"type":"Point"}
}