{
  "type": "Feature",
  "properties": {
    "iso:country":"US",
    "sg:address":"333 9th St",
    "sg:city":"San Francisco",
    "sg:classifiers":[
        {
            "category":"Home & Garden",
            "subcategory":"Furniture",
            "type":"Retail Goods"
        }
    ],
    "sg:phone":"+1 415 626 0655",
    "sg:postcode":"94103",
    "sg:province":"CA",
    "wof:name":"Mc Carney Furniture",
    "wof:placetype":"venue"
},
  "geometry": {"coordinates":[-122.411376,37.773753],"type":"Point"}
}