{
  "type": "Feature",
  "properties": {
    "addr:full":"2020 Market St San Diego CA 92102",
    "addr:housenumber":"2020",
    "addr:postcode":"92102",
    "addr:street":"Market St",
    "iso:country":"US",
    "sg:address":"2020 Market St",
    "sg:city":"San Diego",
    "sg:classifiers":[
        {
            "category":"Shopping",
            "subcategory":"Gifts & Souvenirs",
            "type":"Retail Goods"
        }
    ],
    "sg:phone":"+1 619 232 1674",
    "sg:postcode":"92102",
    "sg:province":"CA",
    "wof:name":"San Diego Trading Co",
    "wof:placetype":"venue"
},
  "geometry": {"coordinates":[-117.145084,32.711618],"type":"Point"}
}