{
  "type": "Feature",
  "properties": {
    "addr:full":"355 12th St Oakland CA 94607",
    "addr:housenumber":"355",
    "addr:postcode":"94607",
    "addr:street":"12Th St",
    "iso:country":"US",
    "sg:address":"355 12th St",
    "sg:city":"Oakland",
    "sg:classifiers":[
        {
            "category":"Wholesale",
            "subcategory":"Machinery & Supplies",
            "type":"Manufacturing & Wholesale Goods"
        }
    ],
    "sg:phone":"+1 510 452 2570",
    "sg:postcode":"94607",
    "sg:province":"CA",
    "sg:tags":[
        "equipment",
        "establishment"
    ],
    "wof:name":"Kruse Brothers Barber Supply",
    "wof:placetype":"venue"
},
  "geometry": {"coordinates":[-122.27082799999999,37.802365],"type":"Point"}
}