{
  "type": "Feature",
  "properties": {
    "addr:full":"112 Hoffman Ave San Francisco CA 94114",
    "addr:housenumber":"112",
    "addr:postcode":"94114",
    "addr:street":"Hoffman Ave",
    "iso:country":"US",
    "sg:address":"112 Hoffman Ave",
    "sg:city":"San Francisco",
    "sg:classifiers":[
        {
            "category":"Retail",
            "subcategory":"Funeral Services",
            "type":"Services"
        }
    ],
    "sg:phone":"+1 415 826 5330",
    "sg:postcode":"94114",
    "sg:province":"CA",
    "sg:tags":[
        "director"
    ],
    "wof:name":"Collage Chapel Mortuary",
    "wof:placetype":"venue"
},
  "geometry": {"coordinates":[-122.440856,37.75259],"type":"Point"}
}