{
  "type": "Feature",
  "properties": {
    "iso:country":"US",
    "sg:address":"1757 Union St",
    "sg:city":"San Francisco",
    "sg:classifiers":[
        {
            "category":"Professional",
            "type":"Services"
        }
    ],
    "sg:phone":"+1 415 409 1108",
    "sg:postcode":"94123",
    "sg:province":"CA",
    "wof:name":"Welldone Resources Inc",
    "wof:placetype":"venue"
},
  "geometry": {"coordinates":[-122.42815899999999,37.79797],"type":"Point"}
}