{
  "type": "Feature",
  "properties": {
    "addr:full":"9130 Norwalk Blvd Santa Fe Springs CA 90670",
    "addr:housenumber":"9130",
    "addr:postcode":"90670",
    "addr:street":"Norwalk Blvd",
    "iso:country":"US",
    "sg:address":"9130 Norwalk Blvd",
    "sg:city":"Santa Fe Springs",
    "sg:classifiers":[
        {
            "category":"Professional",
            "subcategory":"Computer Services",
            "type":"Services"
        }
    ],
    "sg:phone":"+1 562 463 6832",
    "sg:postcode":"90670",
    "sg:province":"CA",
    "sg:tags":[
        "repair"
    ],
    "wof:name":"Enterprise Network Solutions",
    "wof:placetype":"venue"
},
  "geometry": {"coordinates":[-118.11375,33.957843],"type":"Point"}
}