{
  "type": "Feature",
  "properties": {
    "iso:country":"US",
    "sg:address":"16160 Hwy 76",
    "sg:city":"Pauma Valley",
    "sg:classifiers":[
        {
            "category":"Farming",
            "subcategory":"Farm & Veterinary Services",
            "type":"Manufacturing & Wholesale Goods"
        }
    ],
    "sg:phone":"+1 760 742 3553",
    "sg:postcode":"92061",
    "sg:province":"CA",
    "sg:tags":[
        "management"
    ],
    "wof:name":"C F Farming Inc",
    "wof:placetype":"venue"
},
  "geometry": {"coordinates":[-116.979477,33.304553],"type":"Point"}
}