{
  "type": "Feature",
  "properties": {
    "addr:full":"9360 Activity Rd San Diego CA 92126",
    "addr:housenumber":"9360",
    "addr:postcode":"92126",
    "addr:street":"Activity Rd",
    "iso:country":"US",
    "sg:address":"9360 Activity Rd",
    "sg:city":"San Diego",
    "sg:classifiers":[
        {
            "category":"Wholesale",
            "subcategory":"Office Equipment",
            "type":"Manufacturing & Wholesale Goods"
        },
        {
            "category":"Professional",
            "subcategory":"Business Services",
            "type":"Services"
        }
    ],
    "sg:phone":"+1 858 536 1844",
    "sg:postcode":"92126",
    "sg:province":"CA",
    "sg:tags":[
        "microfilming",
        "special"
    ],
    "wof:name":"New Image Conversion Service",
    "wof:placetype":"venue"
},
  "geometry": {"coordinates":[-117.124365,32.897113],"type":"Point"}
}