{
  "type": "Feature",
  "properties": {
    "iso:country":"US",
    "sg:address":"1041 Los Arabis Ln",
    "sg:city":"Lafayette",
    "sg:classifiers":[
        {
            "category":"Professional",
            "subcategory":"Research",
            "type":"Services"
        }
    ],
    "sg:phone":"+1 925 283 8454",
    "sg:postcode":"94549",
    "sg:province":"CA",
    "sg:tags":[
        "development"
    ],
    "wof:name":"Microwave Sciences",
    "wof:placetype":"venue"
},
  "geometry": {"coordinates":[-122.145519,37.894734],"type":"Point"}
}