{
  "type": "Feature",
  "properties": {
    "addr:full":"218 N Conyer St Visalia CA 93291",
    "addr:housenumber":"218",
    "addr:postcode":"93291",
    "addr:street":"N Conyer St",
    "iso:country":"US",
    "sg:address":"218 N Conyer St",
    "sg:city":"Visalia",
    "sg:classifiers":[
        {
            "category":"Professional",
            "subcategory":"Detective & Security Services",
            "type":"Services"
        }
    ],
    "sg:phone":"+1 559 490 0840",
    "sg:postcode":"93291",
    "sg:province":"CA",
    "sg:tags":[
        "car",
        "investigator"
    ],
    "wof:name":"Llorente Investigations Inc",
    "wof:placetype":"venue"
},
  "geometry": {"coordinates":[-119.30098599999999,36.331301],"type":"Point"}
}