{
  "type": "Feature",
  "properties": {
    "addr:full":"1738 E Valley Pkwy Escondido CA 92027",
    "addr:housenumber":"1738",
    "addr:postcode":"92027",
    "addr:street":"E Valley Pkwy",
    "iso:country":"US",
    "sg:address":"1738 E Valley Pkwy",
    "sg:city":"Escondido",
    "sg:classifiers":[
        {
            "category":"Shopping",
            "subcategory":"Clothing, Apparel, & Fashions",
            "type":"Retail Goods"
        }
    ],
    "sg:phone":"+1 760 739 0056",
    "sg:postcode":"92027",
    "sg:province":"CA",
    "sg:tags":[
        "alteration"
    ],
    "wof:name":"Pins & Needles",
    "wof:placetype":"venue"
},
  "geometry": {"coordinates":[-117.054586,33.136301],"type":"Point"}
}