{
  "type": "Feature",
  "properties": {
    "addr:full":"9336 Washington Blvd Culver City CA 90232",
    "addr:housenumber":"9336",
    "addr:postcode":"90232",
    "addr:street":"Washington Blvd",
    "iso:country":"US",
    "sg:address":"9336 Washington Blvd",
    "sg:city":"Culver City",
    "sg:classifiers":[
        {
            "category":"Arts & Performance",
            "subcategory":"Arts Center",
            "type":"Entertainment"
        },
        {
            "category":"Retail",
            "subcategory":"Event Space",
            "type":"Services"
        },
        {
            "category":"Communications",
            "subcategory":"Television Station",
            "type":"Services"
        }
    ],
    "sg:phone":"+1 310 202 1234",
    "sg:postcode":"90232",
    "sg:province":"CA",
    "sg:tags":[
        "venue"
    ],
    "sg:website":"www.theculverstudios.com/",
    "wof:name":"The Culver Studios",
    "wof:placetype":"venue"
},
  "geometry": {"coordinates":[-118.39299800000001,34.0243],"type":"Point"}
}