{
  "type": "Feature",
  "properties": {
    "iso:country":"US",
    "sg:address":"8563 San Fernando Rd",
    "sg:city":"Sun Valley",
    "sg:classifiers":[
        {
            "category":"Home & Garden",
            "subcategory":"Building Materials",
            "type":"Retail Goods"
        }
    ],
    "sg:phone":"+1 818 768 3176",
    "sg:postcode":"91352",
    "sg:province":"CA",
    "wof:name":"Masonry Club",
    "wof:placetype":"venue"
},
  "geometry": {"coordinates":[-118.378227,34.225208],"type":"Point"}
}