{
  "type": "Feature",
  "properties": {
    "addr:full":"1755 Brown Ave Riverside CA 92509",
    "addr:housenumber":"1755",
    "addr:postcode":"92509",
    "addr:street":"Brown Ave",
    "iso:country":"US",
    "sg:address":"1755 Brown Ave",
    "sg:city":"Riverside",
    "sg:classifiers":[
        {
            "category":"Building & Trades",
            "subcategory":"Construction",
            "type":"Services"
        }
    ],
    "sg:phone":"+1 951 328 2667",
    "sg:postcode":"92509",
    "sg:province":"CA",
    "sg:tags":[
        "site",
        "clean"
    ],
    "wof:name":"Spartan Cleanup Corp",
    "wof:placetype":"venue"
},
  "geometry": {"coordinates":[-117.375491,34.019433],"type":"Point"}
}