{
  "type": "Feature",
  "properties": {
    "addr:full":"6261 Southworth Rd Valley Springs CA 95252",
    "addr:postcode":"6261;95252",
    "addr:street":"Southworth Rd",
    "iso:country":"US",
    "sg:address":"6261 Southworth Rd",
    "sg:city":"Valley Springs",
    "sg:classifiers":[
        {
            "category":"Real Estate",
            "subcategory":"Real Estate Operator",
            "type":"Services"
        }
    ],
    "sg:phone":"+1 209 772 1311",
    "sg:postcode":"95252",
    "sg:province":"CA",
    "sg:tags":[
        "property",
        "lessor"
    ],
    "wof:name":"June Cree",
    "wof:placetype":"venue"
},
  "geometry": {"coordinates":[-120.91229300000001,38.148555],"type":"Point"}
}