{
  "type": "Feature",
  "properties": {
    "iso:country":"US",
    "sg:address":"344 Lily St",
    "sg:city":"Fairfield",
    "sg:classifiers":[
        {
            "category":"Shopping",
            "type":"Retail Goods"
        }
    ],
    "sg:phone":"+1 707 290 6293",
    "sg:postcode":"94533",
    "sg:province":"CA",
    "sg:tags":[
        "pet",
        "food",
        "supply"
    ],
    "wof:name":"Sit & Stay Doggie Bakery",
    "wof:placetype":"venue"
},
  "geometry": {"coordinates":[-122.043622,38.275747],"type":"Point"}
}