{
  "type": "Feature",
  "properties": {
    "iso:country":"US",
    "sg:address":"6374 del Cerro Blvd",
    "sg:city":"San Diego",
    "sg:classifiers":[
        {
            "category":"Personal",
            "subcategory":"Beauty Salon",
            "type":"Services"
        }
    ],
    "sg:phone":"+1 619 298 9990",
    "sg:postcode":"92120",
    "sg:province":"CA",
    "wof:name":"Lira Juan Ayala",
    "wof:placetype":"venue"
},
  "geometry": {"coordinates":[-117.06002599999999,32.783193],"type":"Point"}
}