{
  "type": "Feature",
  "properties": {
    "iso:country":"US",
    "sg:address":"2000 E 4th St",
    "sg:city":"Santa Ana",
    "sg:classifiers":[
        {
            "category":"Real Estate",
            "subcategory":"Real Estate Agent",
            "type":"Services"
        }
    ],
    "sg:phone":"+1 714 836 5570",
    "sg:postcode":"92705",
    "sg:province":"CA",
    "wof:name":"Goltech Realty",
    "wof:placetype":"venue"
},
  "geometry": {"coordinates":[-117.83628,33.748239],"type":"Point"}
}