{
  "type": "Feature",
  "properties": {
    "iso:country":"US",
    "sg:address":"13564 Imperial Hwy Ste A",
    "sg:city":"Santa Fe Springs",
    "sg:classifiers":[
        {
            "category":"Shopping",
            "subcategory":"Stationery & Office Supplies",
            "type":"Retail Goods"
        }
    ],
    "sg:phone":"+1 562 623 0927",
    "sg:postcode":"90670",
    "sg:province":"CA",
    "sg:tags":[
        "equipment"
    ],
    "wof:name":"Pacific Office System",
    "wof:placetype":"venue"
},
  "geometry": {"coordinates":[-118.04299899999999,33.916901],"type":"Point"}
}