{
  "type": "Feature",
  "properties": {
    "iso:country":"US",
    "sg:address":"18302 Marygold Ave",
    "sg:city":"Bloomington",
    "sg:classifiers":[
        {
            "category":"Social Services",
            "subcategory":"Child Care",
            "type":"Services"
        }
    ],
    "sg:phone":"+1 909 877 3900",
    "sg:postcode":"92316",
    "sg:province":"CA",
    "sg:tags":[
        "nursery",
        "day"
    ],
    "wof:name":"Bell Daycare",
    "wof:placetype":"venue"
},
  "geometry": {"coordinates":[-117.404971,34.074053],"type":"Point"}
}