{
  "type": "Feature",
  "properties": {
    "addr:full":"7524 S Main St Los Angeles CA 90003",
    "addr:housenumber":"7524",
    "addr:postcode":"90003",
    "addr:street":"S Main St",
    "iso:country":"US",
    "sg:address":"7524 S Main St",
    "sg:city":"Los Angeles",
    "sg:classifiers":[
        {
            "category":"Retail",
            "subcategory":"Auto Repair",
            "type":"Services"
        }
    ],
    "sg:phone":"+1 323 750 0987",
    "sg:postcode":"90003",
    "sg:province":"CA",
    "sg:tags":[
        "repairing",
        "automobile"
    ],
    "wof:name":"Espino Auto Repair",
    "wof:placetype":"venue"
},
  "geometry": {"coordinates":[-118.274002,33.971401],"type":"Point"}
}