{
  "type": "Feature",
  "properties": {
    "addr:full":"17648 Lemay Pl Van Nuys CA 91406",
    "addr:housenumber":"17648",
    "addr:postcode":"91406",
    "addr:street":"Lemay Pl",
    "iso:country":"US",
    "sg:address":"17648 Lemay Pl",
    "sg:city":"Van Nuys",
    "sg:classifiers":[
        {
            "category":"Professional",
            "subcategory":"Business Services",
            "type":"Services"
        }
    ],
    "sg:phone":"+1 818 996 7068",
    "sg:postcode":"91406",
    "sg:province":"CA",
    "sg:tags":[
        "packaging"
    ],
    "wof:name":"J T Works",
    "wof:placetype":"venue"
},
  "geometry": {"coordinates":[-118.51576900000001,34.191044],"type":"Point"}
}