{
  "type": "Feature",
  "properties": {
    "iso:country":"US",
    "sg:address":"1986 2nd St",
    "sg:city":"Livermore",
    "sg:classifiers":[
        {
            "category":"Banks & Credit Unions",
            "subcategory":"Bank",
            "type":"Services"
        }
    ],
    "sg:phone":"+1 925 243 9600",
    "sg:postcode":"94550",
    "sg:province":"CA",
    "sg:website":"www.vcb-ca.com",
    "wof:name":"Valley Community Bank",
    "wof:placetype":"venue"
},
  "geometry": {"coordinates":[-121.772052,37.679881],"type":"Point"}
}