{
  "type": "Feature",
  "properties": {
    "addr:full":"199 Fremont St San Francisco CA 94105",
    "addr:housenumber":"199",
    "addr:postcode":"94105",
    "addr:street":"Fremont St",
    "iso:country":"US",
    "sg:address":"199 Fremont St",
    "sg:city":"San Francisco",
    "sg:classifiers":[
        {
            "category":"Real Estate",
            "subcategory":"Developer",
            "type":"Services"
        }
    ],
    "sg:phone":"+1 415 284 8500",
    "sg:postcode":"94105",
    "sg:province":"CA",
    "sg:tags":[
        "company",
        "investment",
        "holding"
    ],
    "wof:name":"Fremont Investors Inc",
    "wof:placetype":"venue"
},
  "geometry": {"coordinates":[-122.395685,37.78966],"type":"Point"}
}