{
  "type": "Feature",
  "properties": {
    "addr:full":"7223 55th St Sacramento CA 95823",
    "addr:housenumber":"7223",
    "addr:postcode":"95823",
    "addr:street":"55Th St",
    "iso:country":"US",
    "sg:address":"7223 55th St",
    "sg:city":"Sacramento",
    "sg:classifiers":[
        {
            "category":"Professional",
            "type":"Services"
        },
        {
            "category":"Restaurant",
            "type":"Food & Drink"
        }
    ],
    "sg:phone":"+1 916 429 1949",
    "sg:postcode":"95823",
    "sg:province":"CA",
    "sg:tags":[
        "style",
        "family",
        "caterer"
    ],
    "wof:name":"South Villa Restaurant Inc",
    "wof:placetype":"venue"
},
  "geometry": {"coordinates":[-121.441317,38.495132],"type":"Point"}
}