{
  "type": "Feature",
  "properties": {
    "addr:full":"3119 Hutchison Ave Los Angeles CA 90034",
    "addr:housenumber":"3119",
    "addr:postcode":"90034",
    "addr:street":"Hutchison Ave",
    "iso:country":"US",
    "sg:address":"3119 Hutchison Ave",
    "sg:city":"Los Angeles",
    "sg:classifiers":[
        {
            "category":"Shopping",
            "subcategory":"Hobbies, Toys, & Games",
            "type":"Retail Goods"
        }
    ],
    "sg:phone":"+1 310 403 5329",
    "sg:postcode":"90034",
    "sg:province":"CA",
    "sg:tags":[
        "equipment",
        "arts",
        "craft",
        "supply"
    ],
    "wof:name":"AAA Leaf",
    "wof:placetype":"venue"
},
  "geometry": {"coordinates":[-118.384686,34.031981],"type":"Point"}
}