{
  "type": "Feature",
  "properties": {
    "iso:country":"US",
    "sg:address":"1615 Alum Rock Ave",
    "sg:city":"San Jose",
    "sg:classifiers":[
        {
            "category":"Utilities",
            "subcategory":"Mobile Phone",
            "type":"Services"
        }
    ],
    "sg:phone":"+1 408 254 3400",
    "sg:postcode":"95116",
    "sg:province":"CA",
    "sg:tags":[
        "communication",
        "radiotelephone"
    ],
    "wof:name":"West Coast Wireless",
    "wof:placetype":"venue"
},
  "geometry": {"coordinates":[-121.858884,37.351272],"type":"Point"}
}