{
  "type": "Feature",
  "properties": {
    "addr:full":"6158 E Floradora Ave Fresno CA 93727",
    "addr:housenumber":"6158",
    "addr:postcode":"93727",
    "addr:street":"E Floradora Ave",
    "iso:country":"US",
    "sg:address":"6158 E Floradora Ave",
    "sg:city":"Fresno",
    "sg:classifiers":[
        {
            "category":"Home & Garden",
            "subcategory":"Building Materials",
            "type":"Retail Goods"
        }
    ],
    "sg:phone":"+1 559 253 1141",
    "sg:postcode":"93727",
    "sg:province":"CA",
    "sg:tags":[
        "door"
    ],
    "wof:name":"Sierra Garage Door Repair Svc",
    "wof:placetype":"venue"
},
  "geometry": {"coordinates":[-119.67922799999999,36.761215],"type":"Point"}
}