{
  "type": "Feature",
  "properties": {
    "addr:full":"749 39th Ave San Francisco CA 94121",
    "addr:housenumber":"749",
    "addr:postcode":"94121",
    "addr:street":"39Th Ave",
    "iso:country":"US",
    "sg:address":"749 39th Ave",
    "sg:city":"San Francisco",
    "sg:classifiers":[
        {
            "category":"Education",
            "subcategory":"Preschool",
            "type":"Public Place"
        }
    ],
    "sg:phone":"+1 415 751 7977",
    "sg:postcode":"94121",
    "sg:province":"CA",
    "sg:website":"www.hummingbirdsf.com",
    "wof:name":"Hummingbird Preschool",
    "wof:placetype":"venue"
},
  "geometry": {"coordinates":[-122.499711,37.77462],"type":"Point"}
}