{
  "type": "Feature",
  "properties": {
    "addr:full":"21211 Hawthorne Blvd Torrance CA 90503",
    "addr:housenumber":"21211",
    "addr:postcode":"90503",
    "addr:street":"Hawthorne Blvd",
    "iso:country":"US",
    "sg:address":"21211 Hawthorne Blvd",
    "sg:city":"Torrance",
    "sg:classifiers":[
        {
            "category":"Wholesale",
            "subcategory":"Non-durable Goods",
            "type":"Manufacturing & Wholesale Goods"
        }
    ],
    "sg:phone":"+1 310 540 8328",
    "sg:postcode":"90503",
    "sg:province":"CA",
    "wof:name":"Sun Systems",
    "wof:placetype":"venue"
},
  "geometry": {"coordinates":[-118.35316400000001,33.835406],"type":"Point"}
}