{
  "type": "Feature",
  "properties": {
    "addr:full":"6548 Telegraph Road Los Angeles CA 90040",
    "addr:housenumber":"6548",
    "addr:postcode":"90040",
    "addr:street":"Telegraph Road",
    "iso:country":"US",
    "sg:address":"6548 Telegraph Road",
    "sg:city":"Los Angeles",
    "sg:classifiers":[
        {
            "category":"Home & Garden",
            "subcategory":"Building Materials",
            "type":"Retail Goods"
        }
    ],
    "sg:phone":"+1 323 721 0800",
    "sg:postcode":"90040",
    "sg:province":"CA",
    "sg:tags":[
        "supply"
    ],
    "wof:name":"Lumber Liquidators",
    "wof:placetype":"venue"
},
  "geometry": {"coordinates":[-118.13994,33.990832],"type":"Point"}
}