{
  "type": "Feature",
  "properties": {
    "addr:full":"2915 Chanticleer Ave Santa Cruz CA 95065",
    "addr:housenumber":"2915",
    "addr:postcode":"95065",
    "addr:street":"Chanticleer Ave",
    "iso:country":"US",
    "sg:address":"2915 Chanticleer Ave",
    "sg:city":"Santa Cruz",
    "sg:classifiers":[
        {
            "category":"Health Services",
            "subcategory":"Doctor",
            "type":"Services"
        },
        {
            "category":"Personal",
            "subcategory":"Adult",
            "type":"Services"
        }
    ],
    "sg:phone":"+1 831 477 2375",
    "sg:postcode":"95065",
    "sg:province":"CA",
    "sg:tags":[
        "obstetrician",
        "midwife",
        "gynecologist"
    ],
    "wof:name":"Salvay Howard B MD Facog Facs Santa Crz Mdcl Fndtn",
    "wof:placetype":"venue"
},
  "geometry": {"coordinates":[-121.977997,36.988499],"type":"Point"}
}