{
  "type": "Feature",
  "properties": {
    "addr:full":"2115 S Victoria Ave Ventura CA 93003",
    "addr:housenumber":"2115",
    "addr:postcode":"93003",
    "addr:street":"S Victoria Ave",
    "iso:country":"US",
    "sg:address":"2115 S Victoria Ave",
    "sg:city":"Ventura",
    "sg:classifiers":[
        {
            "category":"Restaurant",
            "type":"Food & Drink"
        }
    ],
    "sg:menulink":"http://www.allmenus.com/ca/ventura/178744-jack-in-the-box/menu/",
    "sg:phone":"+1 805 658 1723",
    "sg:postcode":"93003",
    "sg:province":"CA",
    "sg:tags":[
        "burger",
        "american"
    ],
    "wof:name":"Jack in the Box",
    "wof:placetype":"venue"
},
  "geometry": {"coordinates":[-119.210739,34.25438],"type":"Point"}
}