{
  "type": "Feature",
  "properties": {
    "iso:country":"US",
    "sg:address":"1200 Del Paso Rd",
    "sg:city":"Sacramento",
    "sg:classifiers":[
        {
            "category":"Personal",
            "type":"Services"
        }
    ],
    "sg:phone":"+1 916 830 3400",
    "sg:postcode":"95834",
    "sg:province":"CA",
    "sg:tags":[
        "home"
    ],
    "wof:name":"Sears Home Improvement",
    "wof:placetype":"venue"
},
  "geometry": {"coordinates":[-121.488906,38.655451],"type":"Point"}
}