{
  "type": "Feature",
  "properties": {
    "addr:full":"23600 Old Wagon Rd Willits CA 95490",
    "addr:housenumber":"23600",
    "addr:postcode":"95490",
    "addr:street":"Old Wagon Rd",
    "iso:country":"US",
    "sg:address":"23600 Old Wagon Rd",
    "sg:city":"Willits",
    "sg:classifiers":[
        {
            "category":"Shopping",
            "subcategory":"Crafts & Fabrics",
            "type":"Retail Goods"
        }
    ],
    "sg:phone":"+1 707 459 6611",
    "sg:postcode":"95490",
    "sg:province":"CA",
    "sg:tags":[
        "sewing"
    ],
    "wof:name":"Silk Wave",
    "wof:placetype":"venue"
},
  "geometry": {"coordinates":[-123.202127,39.452011],"type":"Point"}
}