{
  "type": "Feature",
  "properties": {
    "iso:country":"US",
    "sg:address":"13127 San Antonio Dr",
    "sg:city":"Norwalk",
    "sg:classifiers":[
        {
            "category":"Building & Trades",
            "subcategory":"Plumbing",
            "type":"Services"
        }
    ],
    "sg:phone":"+1 562 868 9855",
    "sg:postcode":"90650",
    "sg:province":"CA",
    "wof:name":"Yellen's Plumbing & Heating",
    "wof:placetype":"venue"
},
  "geometry": {"coordinates":[-118.07399700000001,33.911098],"type":"Point"}
}