{
  "type": "Feature",
  "properties": {
    "addr:full":"181 Bolla Ave Alamo CA 94507",
    "addr:housenumber":"181",
    "addr:postcode":"94507",
    "addr:street":"Bolla Ave",
    "iso:country":"US",
    "sg:address":"181 Bolla Ave",
    "sg:city":"Alamo",
    "sg:classifiers":[
        {
            "category":"Professional",
            "type":"Services"
        }
    ],
    "sg:phone":"+1 925 838 3846",
    "sg:postcode":"94507",
    "sg:province":"CA",
    "wof:name":"Debbie Bloomberg",
    "wof:placetype":"venue"
},
  "geometry": {"coordinates":[-122.017867,37.855096],"type":"Point"}
}