{
  "type": "Feature",
  "properties": {
    "iso:country":"US",
    "sg:address":"11144 Portage River Ct",
    "sg:city":"Rancho Cordova",
    "sg:classifiers":[
        {
            "category":"Home & Garden",
            "subcategory":"Home Furnishings",
            "type":"Retail Goods"
        }
    ],
    "sg:phone":"+1 916 635 6742",
    "sg:postcode":"95670",
    "sg:province":"CA",
    "wof:name":"Wicker Boutique",
    "wof:placetype":"venue"
},
  "geometry": {"coordinates":[-121.272896,38.62279],"type":"Point"}
}