{
  "type": "Feature",
  "properties": {
    "addr:full":"2458 Rosemead Blvd South El Monte CA 91733",
    "addr:housenumber":"2458",
    "addr:postcode":"91733",
    "addr:street":"Rosemead Blvd",
    "iso:country":"US",
    "sg:address":"2458 Rosemead Blvd",
    "sg:city":"South El Monte",
    "sg:classifiers":[
        {
            "category":"Retail",
            "subcategory":"Auto Repair",
            "type":"Services"
        }
    ],
    "sg:phone":"+1 626 228 8640",
    "sg:postcode":"91733",
    "sg:province":"CA",
    "sg:tags":[
        "motorcycle"
    ],
    "sg:website":"www.standardfunctions.com",
    "wof:name":"Standard Functions",
    "wof:placetype":"venue"
},
  "geometry": {"coordinates":[-118.062484,34.057169],"type":"Point"}
}