{
  "type": "Feature",
  "properties": {
    "addr:full":"274 Cohasset Rd Chico CA 95973",
    "addr:housenumber":"274",
    "addr:postcode":"95973",
    "addr:street":"Cohasset Rd",
    "iso:country":"US",
    "sg:address":"274 Cohasset Rd",
    "sg:city":"Chico",
    "sg:classifiers":[
        {
            "category":"Professional",
            "subcategory":"Management & Consulting",
            "type":"Services"
        }
    ],
    "sg:phone":"+1 530 895 3287",
    "sg:postcode":"95973",
    "sg:province":"CA",
    "sg:tags":[
        "consultant",
        "business"
    ],
    "wof:name":"Insight Unlimited Inc",
    "wof:placetype":"venue"
},
  "geometry": {"coordinates":[-121.849904,39.75125],"type":"Point"}
}