{
  "type": "Feature",
  "properties": {
    "addr:full":"1105 Hobson Ave Broderick CA 95605",
    "addr:housenumber":"1105",
    "addr:postcode":"95605",
    "addr:street":"Hobson Ave",
    "iso:country":"US",
    "sg:address":"1105 Hobson Ave",
    "sg:city":"Broderick",
    "sg:classifiers":[
        {
            "category":"Professional",
            "subcategory":"Accounting & Tax Preparation",
            "type":"Services"
        }
    ],
    "sg:phone":"+1 916 372 8022",
    "sg:postcode":"95605",
    "sg:province":"CA",
    "sg:tags":[
        "bookkeeping",
        "general"
    ],
    "wof:name":"Mandala Business Svc",
    "wof:placetype":"venue"
},
  "geometry": {"coordinates":[-121.52972800000001,38.592547],"type":"Point"}
}