{
  "type": "Feature",
  "properties": {
    "addr:full":"220 S California Ave Palo Alto CA 94306",
    "addr:housenumber":"220",
    "addr:postcode":"94306",
    "addr:street":"S California Ave",
    "iso:country":"US",
    "sg:address":"220 S California Ave",
    "sg:city":"Palo Alto",
    "sg:classifiers":[
        {
            "category":"Social Services",
            "type":"Services"
        }
    ],
    "sg:phone":"+1 650 327 2129",
    "sg:postcode":"94306",
    "sg:province":"CA",
    "sg:tags":[
        "counselor",
        "marriage",
        "family"
    ],
    "wof:name":"Susan Owicki",
    "wof:placetype":"venue"
},
  "geometry": {"coordinates":[-122.143843,37.427639],"type":"Point"}
}