{
  "type": "Feature",
  "properties": {
    "iso:country":"US",
    "sg:address":"1529 Grace Pl",
    "sg:city":"Santa Ana",
    "sg:classifiers":[
        {
            "category":"Social Services",
            "subcategory":"Child Care",
            "type":"Services"
        }
    ],
    "sg:phone":"+1 714 542 7530",
    "sg:postcode":"92701",
    "sg:province":"CA",
    "wof:name":"Magical Start Day Care",
    "wof:placetype":"venue"
},
  "geometry": {"coordinates":[-117.847751,33.755154],"type":"Point"}
}