{
  "type": "Feature",
  "properties": {
    "addr:full":"1534 Duran Cir Salinas CA 93906",
    "addr:housenumber":"1534",
    "addr:postcode":"93906",
    "addr:street":"Duran Cir",
    "iso:country":"US",
    "sg:address":"1534 Duran Cir",
    "sg:city":"Salinas",
    "sg:classifiers":[
        {
            "category":"Professional",
            "type":"Services"
        }
    ],
    "sg:phone":"+1 831 442 1054",
    "sg:postcode":"93906",
    "sg:province":"CA",
    "wof:name":"El Rodeo Western Wear",
    "wof:placetype":"venue"
},
  "geometry": {"coordinates":[-121.66264099999999,36.709287],"type":"Point"}
}