{
  "type": "Feature",
  "properties": {
    "addr:full":"1103 N 4th St San Jose CA 95112",
    "addr:housenumber":"1103",
    "addr:postcode":"95112",
    "addr:street":"N 4Th St",
    "iso:country":"US",
    "sg:address":"1103 N 4th St",
    "sg:city":"San Jose",
    "sg:classifiers":[
        {
            "category":"Professional",
            "subcategory":"Art Services",
            "type":"Services"
        }
    ],
    "sg:phone":"+1 408 278 1552",
    "sg:postcode":"95112",
    "sg:province":"CA",
    "sg:tags":[
        "graphic",
        "designer"
    ],
    "sg:website":"www.trandesign.com",
    "wof:name":"Tran Design & Assoc",
    "wof:placetype":"venue"
},
  "geometry": {"coordinates":[-121.90343300000001,37.359039],"type":"Point"}
}