{
  "type": "Feature",
  "properties": {
    "addr:full":"5723 Sycamore Ave Rialto CA 92377",
    "addr:housenumber":"5723",
    "addr:postcode":"92377",
    "addr:street":"Sycamore Ave",
    "iso:country":"US",
    "sg:address":"5723 Sycamore Ave",
    "sg:city":"Rialto",
    "sg:classifiers":[
        {
            "category":"Personal",
            "type":"Services"
        }
    ],
    "sg:phone":"+1 909 820 0481",
    "sg:postcode":"92377",
    "sg:province":"CA",
    "sg:tags":[
        "baby",
        "sitter"
    ],
    "wof:name":"It Takes A Village",
    "wof:placetype":"venue"
},
  "geometry": {"coordinates":[-117.381411,34.149622],"type":"Point"}
}