{
  "type": "Feature",
  "properties": {
    "addr:full":"14501 Pearl Ave Clearlake CA 95422",
    "addr:housenumber":"14501",
    "addr:postcode":"95422",
    "addr:street":"Pearl Ave",
    "iso:country":"US",
    "sg:address":"14501 Pearl Ave",
    "sg:city":"Clearlake",
    "sg:classifiers":[
        {
            "category":"Social Services",
            "subcategory":"Child Care",
            "type":"Services"
        }
    ],
    "sg:phone":"+1 707 994 6045",
    "sg:postcode":"95422",
    "sg:province":"CA",
    "sg:tags":[
        "kindergarten",
        "academic",
        "school"
    ],
    "wof:name":"Head Start",
    "wof:placetype":"venue"
},
  "geometry": {"coordinates":[-122.641592,38.953552],"type":"Point"}
}