{
  "type": "Feature",
  "properties": {
    "addr:full":"2909 Fairview Road Costa Mesa CA 92626",
    "addr:housenumber":"2909",
    "addr:postcode":"92626",
    "addr:street":"Fairview Road",
    "iso:country":"US",
    "sg:address":"2909 Fairview Road",
    "sg:city":"Costa Mesa",
    "sg:classifiers":[
        {
            "category":"Professional",
            "subcategory":"Lawyer & Legal Services",
            "type":"Services"
        }
    ],
    "sg:phone":"+1 949 722 4555",
    "sg:postcode":"92626",
    "sg:province":"CA",
    "wof:name":"Mi Abogado",
    "wof:placetype":"venue"
},
  "geometry": {"coordinates":[-117.907894,33.678049],"type":"Point"}
}