{
  "type": "Feature",
  "properties": {
    "addr:full":"2808 Glendale Blvd Los Angeles CA 90039",
    "addr:housenumber":"2808",
    "addr:postcode":"90039",
    "addr:street":"Glendale Blvd",
    "iso:country":"US",
    "sg:address":"2808 Glendale Blvd",
    "sg:city":"Los Angeles",
    "sg:classifiers":[
        {
            "category":"Health Services",
            "subcategory":"Health Practitioner",
            "type":"Services"
        }
    ],
    "sg:phone":"+1 323 662 3907",
    "sg:postcode":"90039",
    "sg:province":"CA",
    "sg:tags":[
        "acupuncture"
    ],
    "wof:name":"Levinson Allison Acupuncture",
    "wof:placetype":"venue"
},
  "geometry": {"coordinates":[-118.26300000000001,34.1073],"type":"Point"}
}