{
  "type": "Feature",
  "properties": {
    "iso:country":"US",
    "sg:address":"2207 S Bascom Ave",
    "sg:city":"Campbell",
    "sg:classifiers":[
        {
            "category":"Banks & Credit Unions",
            "subcategory":"Investment Brokerage",
            "type":"Services"
        }
    ],
    "sg:phone":"+1 408 583 0550",
    "sg:postcode":"95008",
    "sg:province":"CA",
    "sg:tags":[
        "advisory",
        "financial"
    ],
    "wof:name":"Bernard D Vilona Corp",
    "wof:placetype":"venue"
},
  "geometry": {"coordinates":[-121.931771,37.28272],"type":"Point"}
}