{
  "type": "Feature",
  "properties": {
    "iso:country":"US",
    "sg:address":"2080 E Pacific Coast Hwy",
    "sg:city":"Long Beach",
    "sg:classifiers":[
        {
            "category":"Cinema",
            "subcategory":"Movie Rental",
            "type":"Entertainment"
        }
    ],
    "sg:phone":"+1 562 433 2203",
    "sg:postcode":"90804",
    "sg:province":"CA",
    "sg:tags":[
        "game",
        "video"
    ],
    "wof:name":"Khmer Star Video & Gift",
    "wof:placetype":"venue"
},
  "geometry": {"coordinates":[-118.166,33.7897],"type":"Point"}
}