{
  "type": "Feature",
  "properties": {
    "iso:country":"US",
    "sg:address":"11632 Atlantic Ave",
    "sg:city":"Lynwood",
    "sg:classifiers":[
        {
            "category":"Building & Trades",
            "subcategory":"Electrical",
            "type":"Services"
        }
    ],
    "sg:phone":"+1 323 567 8316",
    "sg:postcode":"90262",
    "sg:province":"CA",
    "sg:tags":[
        "electric",
        "contractor"
    ],
    "wof:name":"A & L Electric",
    "wof:placetype":"venue"
},
  "geometry": {"coordinates":[-118.18855600000001,33.918648],"type":"Point"}
}