{
  "type": "Feature",
  "properties": {
    "iso:country":"US",
    "sg:address":"1200 K St",
    "sg:city":"Sacramento",
    "sg:classifiers":[
        {
            "category":"Shopping Center",
            "type":"Public Place"
        }
    ],
    "sg:postcode":"95816",
    "sg:province":"CA",
    "wof:name":"K Street Mall",
    "wof:placetype":"venue"
},
  "geometry": {"coordinates":[-121.490207,38.578182],"type":"Point"}
}