{
  "type": "Feature",
  "properties": {
    "addr:full":"21762 Lake Forest Dr Lake Forest CA 92630",
    "addr:housenumber":"21762",
    "addr:postcode":"92630",
    "addr:street":"Lake Forest Dr",
    "iso:country":"US",
    "sg:address":"21762 Lake Forest Dr",
    "sg:city":"Lake Forest",
    "sg:classifiers":[
        {
            "category":"Shopping",
            "subcategory":"Computers & Home Electronics",
            "type":"Retail Goods"
        }
    ],
    "sg:phone":"+1 949 544 1158",
    "sg:postcode":"92630",
    "sg:province":"CA",
    "wof:name":"DISH Network",
    "wof:placetype":"venue"
},
  "geometry": {"coordinates":[-117.685907,33.646676],"type":"Point"}
}