{
  "type": "Feature",
  "properties": {
    "iso:country":"US",
    "sg:address":"5330 Office Center Ct",
    "sg:city":"Bakersfield",
    "sg:classifiers":[
        {
            "category":"Health Services",
            "subcategory":"Health Practitioner",
            "type":"Services"
        }
    ],
    "sg:phone":"+1 661 328 9913",
    "sg:postcode":"93309",
    "sg:province":"CA",
    "sg:tags":[
        "therapist",
        "physical"
    ],
    "wof:name":"Jessica Hein Physical Therapy",
    "wof:placetype":"venue"
},
  "geometry": {"coordinates":[-119.061605,35.36049],"type":"Point"}
}