{
  "type": "Feature",
  "properties": {
    "iso:country":"US",
    "sg:address":"28104 Bobwhite Cir",
    "sg:city":"Santa Clarita",
    "sg:classifiers":[
        {
            "category":"Building & Trades",
            "subcategory":"Construction",
            "type":"Services"
        }
    ],
    "sg:phone":"+1 661 296 5465",
    "sg:postcode":"91350",
    "sg:province":"CA",
    "sg:tags":[
        "contractor"
    ],
    "wof:name":"Errington Construction Co",
    "wof:placetype":"venue"
},
  "geometry": {"coordinates":[-118.511631,34.455651],"type":"Point"}
}