{
  "type": "Feature",
  "properties": {
    "addr:full":"28104 Bobwhite Cir Santa Clarita CA 91350",
    "addr:housenumber":"28104",
    "addr:postcode":"91350",
    "addr:street":"Bobwhite Cir",
    "iso:country":"US",
    "sg:address":"28104 Bobwhite Cir",
    "sg:city":"Santa Clarita",
    "sg:classifiers":[
        {
            "category":"Building & Trades",
            "subcategory":"Construction",
            "type":"Services"
        }
    ],
    "sg:phone":"+1 661 296 5465",
    "sg:postcode":"91350",
    "sg:province":"CA",
    "sg:tags":[
        "contractor"
    ],
    "wof:name":"Errington Construction Co",
    "wof:placetype":"venue"
},
  "geometry": {"coordinates":[-118.51163099999999,34.455651],"type":"Point"}
}