{
  "type": "Feature",
  "properties": {
    "iso:country":"US",
    "sg:address":"1521 Terminal Avenue",
    "sg:city":"San Jose",
    "sg:classifiers":[
        {
            "category":"Professional",
            "subcategory":"Employment Agencies",
            "type":"Services"
        }
    ],
    "sg:phone":"+1 408 441 8367",
    "sg:postcode":"95112",
    "sg:province":"CA",
    "wof:name":"Pro Trades Connection",
    "wof:placetype":"venue"
},
  "geometry": {"coordinates":[-121.905226,37.367081],"type":"Point"}
}