{
  "type": "Feature",
  "properties": {
    "addr:full":"2865 Foss Ave Arcadia CA 91006",
    "addr:housenumber":"2865",
    "addr:postcode":"91006",
    "addr:street":"Foss Ave",
    "iso:country":"US",
    "sg:address":"2865 Foss Ave",
    "sg:city":"Arcadia",
    "sg:classifiers":[
        {
            "category":"Freight",
            "type":"Transportation"
        }
    ],
    "sg:phone":"+1 626 278 1263",
    "sg:postcode":"91006",
    "sg:province":"CA",
    "sg:tags":[
        "operator",
        "local",
        "trucking"
    ],
    "wof:name":"Em Trucking",
    "wof:placetype":"venue"
},
  "geometry": {"coordinates":[-118.01499,34.113579],"type":"Point"}
}