{
  "type": "Feature",
  "properties": {
    "addr:full":"215 Denny Way El Cajon CA 92020",
    "addr:housenumber":"215",
    "addr:postcode":"92020",
    "addr:street":"Denny Way",
    "iso:country":"US",
    "sg:address":"215 Denny Way",
    "sg:city":"El Cajon",
    "sg:classifiers":[
        {
            "category":"Home & Garden",
            "subcategory":"Building Materials",
            "type":"Retail Goods"
        }
    ],
    "sg:phone":"+1 619 258 7412",
    "sg:postcode":"92020",
    "sg:province":"CA",
    "sg:tags":[
        "equipment",
        "electric",
        "supply"
    ],
    "sg:website":"www.probemaster.com",
    "wof:name":"Probe Master",
    "wof:placetype":"venue"
},
  "geometry": {"coordinates":[-116.96320799999999,32.820469],"type":"Point"}
}