{
  "type": "Feature",
  "properties": {
    "iso:country":"US",
    "sg:address":"37660 Bautista Canyon Rd",
    "sg:city":"Anza",
    "sg:classifiers":[
        {
            "category":"Retail",
            "subcategory":"Repair Shop",
            "type":"Services"
        }
    ],
    "sg:phone":"+1 951 763 4037",
    "sg:postcode":"92539",
    "sg:province":"CA",
    "sg:tags":[
        "welding"
    ],
    "wof:name":"Elmore's Welding",
    "wof:placetype":"venue"
},
  "geometry": {"coordinates":[-116.700718,33.577566],"type":"Point"}
}