{
  "type": "Feature",
  "properties": {
    "addr:full":"1404 Old County Rd Belmont CA 94002",
    "addr:housenumber":"1404",
    "addr:postcode":"94002",
    "addr:street":"Old County Rd",
    "iso:country":"US",
    "sg:address":"1404 Old County Rd",
    "sg:city":"Belmont",
    "sg:classifiers":[
        {
            "category":"Manufacturing",
            "subcategory":"Printing",
            "type":"Manufacturing & Wholesale Goods"
        }
    ],
    "sg:phone":"+1 650 517 0200",
    "sg:postcode":"94002",
    "sg:province":"CA",
    "sg:tags":[
        "commercial"
    ],
    "wof:name":"Mega Color Corp",
    "wof:placetype":"venue"
},
  "geometry": {"coordinates":[-122.24628800000001,37.496805],"type":"Point"}
}