{
  "type": "Feature",
  "properties": {
    "iso:country":"US",
    "sg:address":"801 W Hawthorne St",
    "sg:city":"Bloomington",
    "sg:classifiers":[
        {
            "category":"Restaurant",
            "type":"Food & Drink"
        }
    ],
    "sg:phone":"+1 619 235 4376",
    "sg:postcode":"92316",
    "sg:province":"CA",
    "sg:tags":[
        "shop",
        "coffee"
    ],
    "wof:name":"Starbucks",
    "wof:placetype":"venue"
},
  "geometry": {"coordinates":[-117.385336,34.08168],"type":"Point"}
}