{
  "type": "Feature",
  "properties": {
    "iso:country":"US",
    "sg:address":"1934 S El Camino Real",
    "sg:city":"San Mateo",
    "sg:classifiers":[
        {
            "category":"Shopping",
            "subcategory":"Mobile Phones",
            "type":"Retail Goods"
        }
    ],
    "sg:phone":"+1 650 378 6350",
    "sg:postcode":"94403",
    "sg:province":"CA",
    "sg:website":"www.sprint.com",
    "wof:name":"Sprint",
    "wof:placetype":"venue"
},
  "geometry": {"coordinates":[-122.310997,37.549198],"type":"Point"}
}