{
  "type": "Feature",
  "properties": {
    "addr:full":"1490 W Artesia Blvd Gardena CA 90248",
    "addr:housenumber":"1490",
    "addr:postcode":"90248",
    "addr:street":"W Artesia Blvd",
    "iso:country":"US",
    "sg:address":"1490 W Artesia Blvd",
    "sg:city":"Gardena",
    "sg:classifiers":[
        {
            "category":"Professional",
            "type":"Services"
        }
    ],
    "sg:phone":"+1 310 539 5500",
    "sg:postcode":"90248",
    "sg:province":"CA",
    "sg:tags":[
        "establishment"
    ],
    "wof:name":"Classic Components",
    "wof:placetype":"venue"
},
  "geometry": {"coordinates":[-118.300736,33.872742],"type":"Point"}
}