{
  "type": "Feature",
  "properties": {
    "iso:country":"US",
    "sg:address":"111 Rathburn Way",
    "sg:city":"Santa Cruz",
    "sg:classifiers":[
        {
            "category":"Restaurant",
            "type":"Food & Drink"
        }
    ],
    "sg:postcode":"95062",
    "sg:province":"CA",
    "sg:website":"dirtygirlproduce.com/",
    "wof:name":"Dirty Girl Produce",
    "wof:placetype":"venue"
},
  "geometry": {"coordinates":[-122.015897,36.978508],"type":"Point"}
}