{
  "type": "Feature",
  "properties": {
    "addr:full":"19 Park Rd Burlingame CA 94010",
    "addr:housenumber":"19",
    "addr:postcode":"94010",
    "addr:street":"Park Rd",
    "iso:country":"US",
    "sg:address":"19 Park Rd",
    "sg:city":"Burlingame",
    "sg:classifiers":[
        {
            "category":"Communications",
            "subcategory":"Film & Video Production",
            "type":"Services"
        }
    ],
    "sg:phone":"+1 650 342 6333",
    "sg:postcode":"94010",
    "sg:province":"CA",
    "sg:tags":[
        "taping"
    ],
    "wof:name":"Robert Cahen Photography",
    "wof:placetype":"venue"
},
  "geometry": {"coordinates":[-122.344105,37.575648],"type":"Point"}
}