{
  "type": "Feature",
  "properties": {
    "addr:full":"707 Broadway Lbby San Diego CA 92101",
    "addr:housenumber":"707",
    "addr:postcode":"92101",
    "addr:street":"Broadway",
    "iso:country":"US",
    "sg:address":"707 Broadway Lbby",
    "sg:city":"San Diego",
    "sg:classifiers":[
        {
            "category":"Professional",
            "subcategory":"Lawyer & Legal Services",
            "type":"Services"
        }
    ],
    "sg:phone":"+1 619 236 1142",
    "sg:postcode":"92101",
    "sg:province":"CA",
    "wof:name":"Iolta Thomas J Atty",
    "wof:placetype":"venue"
},
  "geometry": {"coordinates":[-117.15799699999999,32.715698],"type":"Point"}
}