{
  "type": "Feature",
  "properties": {
    "addr:full":"2131 Broadway Oakland CA 94620",
    "addr:housenumber":"2131",
    "addr:postcode":"94620",
    "addr:street":"Broadway",
    "iso:country":"US",
    "sg:address":"2131 Broadway",
    "sg:city":"Oakland",
    "sg:classifiers":[
        {
            "category":"Shopping",
            "subcategory":"Stationery & Office Supplies",
            "type":"Retail Goods"
        }
    ],
    "sg:phone":"+1 510 452 4465",
    "sg:postcode":"94620",
    "sg:province":"CA",
    "sg:tags":[
        "equipment"
    ],
    "sg:website":"www.cartridgealternative.com/",
    "wof:name":"Cartridge Alternative",
    "wof:placetype":"venue"
},
  "geometry": {"coordinates":[-122.26745099999999,37.810325],"type":"Point"}
}