{
  "type": "Feature",
  "properties": {
    "addr:full":"415 3rd Ave Chula Vista CA 91910",
    "addr:housenumber":"415",
    "addr:postcode":"91910",
    "addr:street":"3Rd Ave",
    "iso:country":"US",
    "sg:address":"415 3rd Ave",
    "sg:city":"Chula Vista",
    "sg:classifiers":[
        {
            "category":"Retail",
            "subcategory":"Laundry & Dry Cleaning",
            "type":"Services"
        }
    ],
    "sg:phone":"+1 619 422 2371",
    "sg:postcode":"91910",
    "sg:province":"CA",
    "sg:tags":[
        "cleaner"
    ],
    "wof:name":"Braley Cleaners of Chula Vista",
    "wof:placetype":"venue"
},
  "geometry": {"coordinates":[-117.078003,32.637001],"type":"Point"}
}