{
  "type": "Feature",
  "properties": {
    "iso:country":"US",
    "sg:address":"3807 Wilshire Blvd",
    "sg:city":"Los Angeles",
    "sg:classifiers":[
        {
            "category":"Professional",
            "subcategory":"Management & Consulting",
            "type":"Services"
        }
    ],
    "sg:phone":"+1 213 389 0000",
    "sg:postcode":"90010",
    "sg:province":"CA",
    "sg:tags":[
        "consultant",
        "business"
    ],
    "wof:name":"Choice Network Consultants",
    "wof:placetype":"venue"
},
  "geometry": {"coordinates":[-118.310203,34.061768],"type":"Point"}
}