{
  "type": "Feature",
  "properties": {
    "addr:full":"2608 9th St Berkeley CA 94710",
    "addr:housenumber":"2608",
    "addr:postcode":"94710",
    "addr:street":"9Th St",
    "iso:country":"US",
    "sg:address":"2608 9th St",
    "sg:city":"Berkeley",
    "sg:classifiers":[
        {
            "category":"Arts & Performance",
            "subcategory":"Theater",
            "type":"Entertainment"
        }
    ],
    "sg:phone":"+1 510 843 4902",
    "sg:postcode":"94710",
    "sg:province":"CA",
    "sg:tags":[
        "bureau"
    ],
    "sg:website":"www.berkeleyagency.com",
    "wof:name":"Berkeley Agency",
    "wof:placetype":"venue"
},
  "geometry": {"coordinates":[-122.29116399999999,37.858217],"type":"Point"}
}