{
  "type": "Feature",
  "properties": {
    "addr:full":"15830 Cromdale St Hesperia CA 92345",
    "addr:postcode":"15830;92345",
    "addr:street":"Cromdale St",
    "iso:country":"US",
    "sg:address":"15830 Cromdale St",
    "sg:city":"Hesperia",
    "sg:classifiers":[
        {
            "category":"Professional",
            "type":"Services"
        }
    ],
    "sg:phone":"+1 760 947 7027",
    "sg:postcode":"92345",
    "sg:province":"CA",
    "wof:name":"Woodguys",
    "wof:placetype":"venue"
},
  "geometry": {"coordinates":[-117.31790700000001,34.380184],"type":"Point"}
}