{
  "type": "Feature",
  "properties": {
    "addr:full":"10927 Downey Ave Downey CA 90241",
    "addr:housenumber":"10927",
    "addr:postcode":"90241",
    "addr:street":"Downey Ave",
    "iso:country":"US",
    "sg:address":"10927 Downey Ave",
    "sg:city":"Downey",
    "sg:classifiers":[
        {
            "category":"Real Estate",
            "subcategory":"Real Estate Agent",
            "type":"Services"
        }
    ],
    "sg:phone":"+1 562 904 1968",
    "sg:postcode":"90241",
    "sg:province":"CA",
    "wof:name":"Paula B Montoya",
    "wof:placetype":"venue"
},
  "geometry": {"coordinates":[-118.13168899999999,33.942076],"type":"Point"}
}