{
  "type": "Feature",
  "properties": {
    "addr:full":"23043 Sea Brook Ln Moreno Valley CA 92557",
    "addr:housenumber":"23043",
    "addr:postcode":"92557",
    "addr:street":"Sea Brook Ln",
    "iso:country":"US",
    "sg:address":"23043 Sea Brook Ln",
    "sg:city":"Moreno Valley",
    "sg:classifiers":[
        {
            "category":"Building & Trades",
            "subcategory":"Landscaping Services",
            "type":"Services"
        }
    ],
    "sg:phone":"+1 951 242 7671",
    "sg:postcode":"92557",
    "sg:province":"CA",
    "wof:name":"Osorios Complete Lawn Care Svc",
    "wof:placetype":"venue"
},
  "geometry": {"coordinates":[-117.260778,33.94801],"type":"Point"}
}