{
  "type": "Feature",
  "properties": {
    "iso:country":"US",
    "sg:address":"1943 Tully Rd",
    "sg:city":"San Jose",
    "sg:classifiers":[
        {
            "category":"Health Services",
            "subcategory":"Dentist",
            "type":"Services"
        }
    ],
    "sg:phone":"+1 408 258 5298",
    "sg:postcode":"95122",
    "sg:province":"CA",
    "wof:name":"King Dentistry",
    "wof:placetype":"venue"
},
  "geometry": {"coordinates":[-121.822095,37.325079],"type":"Point"}
}