{
  "type": "Feature",
  "properties": {
    "iso:country":"US",
    "sg:address":"8827 Eula Way",
    "sg:city":"Orangevale",
    "sg:classifiers":[
        {
            "category":"Social Services",
            "subcategory":"Child Care",
            "type":"Services"
        }
    ],
    "sg:phone":"+1 916 989 1019",
    "sg:postcode":"95662",
    "sg:province":"CA",
    "wof:name":"Bev's Country Daycare",
    "wof:placetype":"venue"
},
  "geometry": {"coordinates":[-121.228493,38.688084],"type":"Point"}
}