{
  "type": "Feature",
  "properties": {
    "addr:full":"3039 Monterey Hwy San Jose CA 95111",
    "addr:housenumber":"3039",
    "addr:postcode":"95111",
    "addr:street":"Monterey Hwy",
    "iso:country":"US",
    "sg:address":"3039 Monterey Hwy",
    "sg:city":"San Jose",
    "sg:classifiers":[
        {
            "category":"Retail",
            "subcategory":"Auto Rental",
            "type":"Services"
        }
    ],
    "sg:phone":"+1 408 226 3505",
    "sg:postcode":"95111",
    "sg:province":"CA",
    "sg:tags":[
        "renting",
        "truck",
        "leasing"
    ],
    "wof:name":"U-Haul Co",
    "wof:placetype":"venue"
},
  "geometry": {"coordinates":[-121.845517,37.287796],"type":"Point"}
}