{
  "type": "Feature",
  "properties": {
    "iso:country":"US",
    "sg:address":"831 E 30th St Ste B",
    "sg:city":"National City",
    "sg:classifiers":[
        {
            "category":"Personal",
            "subcategory":"Nail Salon",
            "type":"Services"
        }
    ],
    "sg:phone":"+1 619 474 2777",
    "sg:postcode":"91950",
    "sg:province":"CA",
    "wof:name":"Nail Smart",
    "wof:placetype":"venue"
},
  "geometry": {"coordinates":[-117.09063999999999,32.659594],"type":"Point"}
}