{
  "type": "Feature",
  "properties": {
    "addr:full":"180 Sea Brg Alameda CA 94502",
    "addr:housenumber":"180",
    "addr:postcode":"94502",
    "addr:street":"Sea",
    "iso:country":"US",
    "sg:address":"180 Sea Brg",
    "sg:city":"Alameda",
    "sg:classifiers":[
        {
            "category":"Building & Trades",
            "subcategory":"Landscaping Services",
            "type":"Services"
        }
    ],
    "sg:phone":"+1 510 337 1878",
    "sg:postcode":"94502",
    "sg:province":"CA",
    "sg:tags":[
        "lawn"
    ],
    "wof:name":"Garden Of Eva",
    "wof:placetype":"venue"
},
  "geometry": {"coordinates":[-122.238463,37.742884],"type":"Point"}
}