{
  "type": "Feature",
  "properties": {
    "iso:country":"US",
    "sg:address":"742 Crompton Rd",
    "sg:city":"Redwood City",
    "sg:classifiers":[
        {
            "category":"Shopping",
            "subcategory":"Used Merchandise",
            "type":"Retail Goods"
        }
    ],
    "sg:phone":"+1 650 366 0771",
    "sg:postcode":"94061",
    "sg:province":"CA",
    "wof:name":"Learned Electronics",
    "wof:placetype":"venue"
},
  "geometry": {"coordinates":[-122.247329,37.465969],"type":"Point"}
}