{
  "type": "Feature",
  "properties": {
    "addr:full":"742 Crompton Rd Redwood City CA 94061",
    "addr:housenumber":"742",
    "addr:postcode":"94061",
    "addr:street":"Crompton Rd",
    "iso:country":"US",
    "sg:address":"742 Crompton Rd",
    "sg:city":"Redwood City",
    "sg:classifiers":[
        {
            "category":"Shopping",
            "subcategory":"Used Merchandise",
            "type":"Retail Goods"
        }
    ],
    "sg:phone":"+1 650 366 0771",
    "sg:postcode":"94061",
    "sg:province":"CA",
    "wof:name":"Learned Electronics",
    "wof:placetype":"venue"
},
  "geometry": {"coordinates":[-122.24732899999999,37.465969],"type":"Point"}
}