{
  "type": "Feature",
  "properties": {
    "iso:country":"US",
    "sg:address":"15727 Elmbrook Dr",
    "sg:city":"La Mirada",
    "sg:classifiers":[
        {
            "category":"Cinema",
            "subcategory":"Movie Rental",
            "type":"Entertainment"
        }
    ],
    "sg:phone":"+1 714 994 0223",
    "sg:postcode":"90638",
    "sg:province":"CA",
    "sg:tags":[
        "game",
        "video"
    ],
    "wof:name":"Trojan Amusement Company",
    "wof:placetype":"venue"
},
  "geometry": {"coordinates":[-118.000999,33.8885],"type":"Point"}
}