{
  "type": "Feature",
  "properties": {
    "addr:full":"590 S Park Ave Pomona CA 91766",
    "addr:housenumber":"590",
    "addr:postcode":"91766",
    "addr:street":"S Park Ave",
    "iso:country":"US",
    "sg:address":"590 S Park Ave",
    "sg:city":"Pomona",
    "sg:classifiers":[
        {
            "category":"Government",
            "subcategory":"Fire Station",
            "type":"Public Place"
        }
    ],
    "sg:phone":"+1 909 620 2218",
    "sg:postcode":"91766",
    "sg:province":"CA",
    "sg:tags":[
        "department"
    ],
    "wof:name":"Pomona Fire Prevention",
    "wof:placetype":"venue"
},
  "geometry": {"coordinates":[-117.75432600000001,34.054928],"type":"Point"}
}