{
  "type": "Feature",
  "properties": {
    "iso:country":"US",
    "sg:address":"26483 Baseline St",
    "sg:city":"Highland",
    "sg:classifiers":[
        {
            "category":"Food & Beverages",
            "subcategory":"Meat & Fish",
            "type":"Retail Goods"
        }
    ],
    "sg:phone":"+1 909 864 0270",
    "sg:postcode":"92346",
    "sg:province":"CA",
    "sg:tags":[
        "seafood"
    ],
    "wof:name":"Seafood For Less",
    "wof:placetype":"venue"
},
  "geometry": {"coordinates":[-117.226548,34.121202],"type":"Point"}
}