{
  "type": "Feature",
  "properties": {
    "iso:country":"US",
    "sg:address":"515 Cedar St",
    "sg:city":"Santa Cruz",
    "sg:classifiers":[
        {
            "category":"Food & Beverages",
            "subcategory":"Specialty",
            "type":"Retail Goods"
        }
    ],
    "sg:phone":"+1 831 426 5595",
    "sg:postcode":"95060",
    "sg:province":"CA",
    "sg:tags":[
        "spice"
    ],
    "wof:name":"Tony's Italian Gourmet",
    "wof:placetype":"venue"
},
  "geometry": {"coordinates":[-122.026896,36.971312],"type":"Point"}
}