{
  "type": "Feature",
  "properties": {
    "iso:country":"US",
    "sg:address":"227 N Main Ave",
    "sg:city":"Fallbrook",
    "sg:classifiers":[
        {
            "category":"Personal",
            "subcategory":"Barber",
            "type":"Services"
        }
    ],
    "sg:phone":"+1 760 731 7356",
    "sg:postcode":"92028",
    "sg:province":"CA",
    "wof:name":"Mr Hair",
    "wof:placetype":"venue"
},
  "geometry": {"coordinates":[-117.251288,33.383483],"type":"Point"}
}