{
  "type": "Feature",
  "properties": {
    "iso:country":"US",
    "sg:address":"8187 California City Blvd",
    "sg:city":"California City",
    "sg:classifiers":[
        {
            "category":"Professional",
            "type":"Services"
        }
    ],
    "sg:phone":"+1 760 373 8282",
    "sg:postcode":"93505",
    "sg:province":"CA",
    "sg:tags":[
        "establishment"
    ],
    "wof:name":"Miester & Miester",
    "wof:placetype":"venue"
},
  "geometry": {"coordinates":[-117.982739,35.125899],"type":"Point"}
}