{
  "type": "Feature",
  "properties": {
    "iso:country":"US",
    "sg:address":"2517 Corinth Ave",
    "sg:city":"Los Angeles",
    "sg:classifiers":[
        {
            "category":"Education",
            "subcategory":"Special Training",
            "type":"Public Place"
        }
    ],
    "sg:phone":"+1 310 479 7156",
    "sg:postcode":"90064",
    "sg:province":"CA",
    "sg:tags":[
        "instruction",
        "music"
    ],
    "wof:name":"Devine Music Studios",
    "wof:placetype":"venue"
},
  "geometry": {"coordinates":[-118.43725499999999,34.031684],"type":"Point"}
}