{
  "type": "Feature",
  "properties": {
    "iso:country":"US",
    "sg:address":"2234 San Pablo Ave",
    "sg:city":"Berkeley",
    "sg:classifiers":[
        {
            "category":"Taxi",
            "type":"Transportation"
        }
    ],
    "sg:phone":"+1 510 666 1224",
    "sg:postcode":"94702",
    "sg:province":"CA",
    "sg:tags":[
        "taxicab"
    ],
    "wof:name":"Berkeley A Yellow Cab",
    "wof:placetype":"venue"
},
  "geometry": {"coordinates":[-122.291033,37.865223],"type":"Point"}
}