{
  "type": "Feature",
  "properties": {
    "iso:country":"US",
    "sg:address":"205 W Grand Ave",
    "sg:city":"El Segundo",
    "sg:classifiers":[
        {
            "category":"Shopping",
            "subcategory":"Used Merchandise",
            "type":"Retail Goods"
        }
    ],
    "sg:phone":"+1 310 322 5255",
    "sg:postcode":"90245",
    "sg:province":"CA",
    "wof:name":"St Michaels Church",
    "wof:placetype":"venue"
},
  "geometry": {"coordinates":[-118.417698,33.919046],"type":"Point"}
}