{
  "type": "Feature",
  "properties": {
    "addr:full":"736 Del AMO Blvd Torrance CA 90502",
    "addr:housenumber":"736",
    "addr:postcode":"90502",
    "addr:street":"Del Amo Blvd",
    "iso:country":"US",
    "sg:address":"736 Del AMO Blvd",
    "sg:city":"Torrance",
    "sg:classifiers":[
        {
            "category":"Retail",
            "subcategory":"Storage",
            "type":"Services"
        }
    ],
    "sg:phone":"+1 310 327 1107",
    "sg:postcode":"90502",
    "sg:province":"CA",
    "sg:tags":[
        "self"
    ],
    "wof:name":"U-Haul Co",
    "wof:placetype":"venue"
},
  "geometry": {"coordinates":[-118.285004,33.846298],"type":"Point"}
}