{
  "type": "Feature",
  "properties": {
    "addr:full":"9170 Mission Blvd Riverside CA 92509",
    "addr:housenumber":"9170",
    "addr:postcode":"92509",
    "addr:street":"Mission Blvd",
    "iso:country":"US",
    "sg:address":"9170 Mission Blvd",
    "sg:city":"Riverside",
    "sg:classifiers":[
        {
            "category":"Food & Beverages",
            "subcategory":"Groceries & Convenience Stores",
            "type":"Retail Goods"
        }
    ],
    "sg:phone":"+1 951 685 2535",
    "sg:postcode":"92509",
    "sg:province":"CA",
    "wof:name":"Lucky 1 Food Store 2",
    "wof:placetype":"venue"
},
  "geometry": {"coordinates":[-117.48267,34.011719],"type":"Point"}
}