{
  "type": "Feature",
  "properties": {
    "iso:country":"US",
    "sg:address":"1499 Wagstaff Rd",
    "sg:city":"Paradise",
    "sg:classifiers":[
        {
            "category":"Real Estate",
            "subcategory":"Real Estate Agent",
            "type":"Services"
        }
    ],
    "sg:phone":"+1 530 872 7827",
    "sg:postcode":"95969",
    "sg:province":"CA",
    "wof:name":"North Star Real Estate",
    "wof:placetype":"venue"
},
  "geometry": {"coordinates":[-121.590627,39.777705],"type":"Point"}
}