{
  "type": "Feature",
  "properties": {
    "iso:country":"US",
    "sg:address":"2441 Levante St",
    "sg:city":"Carlsbad",
    "sg:classifiers":[
        {
            "category":"Manufacturing",
            "subcategory":"Buildings",
            "type":"Manufacturing & Wholesale Goods"
        },
        {
            "category":"Building & Trades",
            "subcategory":"Construction",
            "type":"Services"
        },
        {
            "category":"Professional",
            "subcategory":"Computer Services",
            "type":"Services"
        }
    ],
    "sg:phone":"+1 760 944 0884",
    "sg:postcode":"92009",
    "sg:province":"CA",
    "sg:tags":[
        "information",
        "recovery",
        "builder",
        "processing",
        "system",
        "contractor",
        "equipment",
        "home",
        "data",
        "retrieval"
    ],
    "wof:name":"Chris Barca Construction",
    "wof:placetype":"venue"
},
  "geometry": {"coordinates":[-117.25627900000001,33.084587],"type":"Point"}
}