{
  "type": "Feature",
  "properties": {
    "addr:full":"1233 W Rancho Vista Blvd Ste 243 Palmdale CA 93551",
    "addr:housenumber":"1233",
    "addr:postcode":"ca 93551",
    "addr:street":"W Rancho Vista Blvd Ste 243",
    "iso:country":"US",
    "sg:address":"1233 W Rancho Vista Blvd Ste 243",
    "sg:city":"Palmdale",
    "sg:classifiers":[
        {
            "category":"Personal",
            "subcategory":"Beauty Salon",
            "type":"Services"
        }
    ],
    "sg:phone":"+1 661 947 5174",
    "sg:postcode":"93551",
    "sg:province":"CA",
    "wof:name":"Vans",
    "wof:placetype":"venue"
},
  "geometry": {"coordinates":[-118.15302699999999,34.601841],"type":"Point"}
}