{
  "type": "Feature",
  "properties": {
    "addr:full":"8 Roquedo Rancho Santa Margarita CA 92688",
    "addr:housenumber":"8",
    "addr:postcode":"92688",
    "addr:street":"Roquedo",
    "iso:country":"US",
    "sg:address":"8 Roquedo",
    "sg:city":"Rancho Santa Margarita",
    "sg:classifiers":[
        {
            "category":"Utilities",
            "subcategory":"Telephone",
            "type":"Services"
        }
    ],
    "sg:phone":"+1 949 858 3915",
    "sg:postcode":"92688",
    "sg:province":"CA",
    "sg:tags":[
        "communications"
    ],
    "wof:name":"Broadcom Corporation",
    "wof:placetype":"venue"
},
  "geometry": {"coordinates":[-117.62030900000001,33.621428],"type":"Point"}
}