{
  "type": "Feature",
  "properties": {
    "iso:country":"US",
    "sg:address":"706 S Hill St",
    "sg:city":"Los Angeles",
    "sg:classifiers":[
        {
            "category":"Manufacturing",
            "subcategory":"Jewelry",
            "type":"Manufacturing & Wholesale Goods"
        },
        {
            "category":"Shopping",
            "subcategory":"Jewelry",
            "type":"Retail Goods"
        }
    ],
    "sg:phone":"+1 213 623 5575",
    "sg:postcode":"90014",
    "sg:province":"CA",
    "sg:tags":[
        "mfg",
        "material",
        "diamond",
        "setter"
    ],
    "wof:name":"Creative Designs By J & V",
    "wof:placetype":"venue"
},
  "geometry": {"coordinates":[-118.255658,34.044511],"type":"Point"}
}