{
  "type": "Feature",
  "properties": {
    "iso:country":"US",
    "sg:address":"534 Elm St",
    "sg:city":"Tahoma",
    "sg:classifiers":[
        {
            "category":"Recreation",
            "type":"Entertainment"
        }
    ],
    "sg:phone":"+1 530 525 9928",
    "sg:postcode":"96145",
    "sg:province":"CA",
    "sg:tags":[
        "club",
        "membership"
    ],
    "wof:name":"Saratoga Ski Club",
    "wof:placetype":"venue"
},
  "geometry": {"coordinates":[-120.13543900000001,39.064372],"type":"Point"}
}