{
  "type": "Feature",
  "properties": {
    "addr:full":"10765 Noel St Los Alamitos CA 90720",
    "addr:housenumber":"10765",
    "addr:postcode":"90720",
    "addr:street":"Noel St",
    "iso:country":"US",
    "sg:address":"10765 Noel St",
    "sg:city":"Los Alamitos",
    "sg:classifiers":[
        {
            "category":"Shopping",
            "subcategory":"Pharmacy",
            "type":"Retail Goods"
        }
    ],
    "sg:phone":"+1 714 821 6166",
    "sg:postcode":"90720",
    "sg:province":"CA",
    "sg:tags":[
        "drugstore"
    ],
    "sg:website":"eventmedical.com/",
    "wof:name":"Event Medical Services Inc",
    "wof:placetype":"venue"
},
  "geometry": {"coordinates":[-118.058998,33.804501],"type":"Point"}
}