{
  "type": "Feature",
  "properties": {
    "addr:full":"1605 N Cahuenga Blvd Los Angeles CA 90028",
    "addr:housenumber":"1605",
    "addr:postcode":"90028",
    "addr:street":"N Cahuenga Blvd",
    "iso:country":"US",
    "sg:address":"1605 N Cahuenga Blvd",
    "sg:city":"Los Angeles",
    "sg:classifiers":[
        {
            "category":"Education",
            "subcategory":"Vocational School",
            "type":"Public Place"
        }
    ],
    "sg:phone":"+1 323 461 8333",
    "sg:postcode":"90028",
    "sg:province":"CA",
    "sg:website":"www.moviewriting.com",
    "wof:name":"Hollywood Scriptwriting Inst",
    "wof:placetype":"venue"
},
  "geometry": {"coordinates":[-118.329609,34.101529],"type":"Point"}
}