{
  "type": "Feature",
  "properties": {
    "iso:country":"US",
    "sg:address":"1630 Basswood Ave",
    "sg:city":"Carlsbad",
    "sg:classifiers":[
        {
            "category":"Manufacturing",
            "subcategory":"Jewelry",
            "type":"Manufacturing & Wholesale Goods"
        }
    ],
    "sg:phone":"+1 760 729 3312",
    "sg:postcode":"92008",
    "sg:province":"CA",
    "sg:tags":[
        "costume",
        "mfg"
    ],
    "wof:name":"Silver & Gold",
    "wof:placetype":"venue"
},
  "geometry": {"coordinates":[-117.332556,33.163032],"type":"Point"}
}