{
  "type": "Feature",
  "properties": {
    "addr:full":"10109 Toluca Lake Ave Toluca Lake CA 91602",
    "addr:housenumber":"10109",
    "addr:postcode":"91602",
    "addr:street":"Toluca Lake Ave",
    "iso:country":"US",
    "sg:address":"10109 Toluca Lake Ave",
    "sg:city":"Toluca Lake",
    "sg:classifiers":[
        {
            "category":"Professional",
            "subcategory":"Lawyer & Legal Services",
            "type":"Services"
        }
    ],
    "sg:phone":"+1 818 769 3411",
    "sg:postcode":"91602",
    "sg:province":"CA",
    "sg:tags":[
        "attorney"
    ],
    "wof:name":"Frank L Zugelter",
    "wof:placetype":"venue"
},
  "geometry": {"coordinates":[-118.350827,34.148516],"type":"Point"}
}