{
  "type": "Feature",
  "properties": {
    "addr:full":"2556 Somersville Rd Antioch CA 94509",
    "addr:housenumber":"2556",
    "addr:postcode":"ca 94509",
    "addr:street":"Somersville Rd",
    "iso:country":"US",
    "sg:address":"2556 Somersville Rd",
    "sg:city":"Antioch",
    "sg:classifiers":[
        {
            "category":"Government",
            "subcategory":"Office",
            "type":"Public Place"
        }
    ],
    "sg:phone":"+1 925 754 4860",
    "sg:postcode":"94509",
    "sg:province":"CA",
    "wof:name":"United States Airforce Recrutr",
    "wof:placetype":"venue"
},
  "geometry": {"coordinates":[-121.842119,37.999864],"type":"Point"}
}