{
  "type": "Feature",
  "properties": {
    "iso:country":"US",
    "sg:address":"1279 E Florida Ave",
    "sg:city":"Hemet",
    "sg:classifiers":[
        {
            "category":"Personal",
            "subcategory":"Beauty Salon",
            "type":"Services"
        }
    ],
    "sg:phone":"+1 951 652 1716",
    "sg:postcode":"92543",
    "sg:province":"CA",
    "wof:name":"Scarlet O'Haira's Salon",
    "wof:placetype":"venue"
},
  "geometry": {"coordinates":[-116.960553,33.747526],"type":"Point"}
}