{
  "type": "Feature",
  "properties": {
    "iso:country":"US",
    "sg:address":"21300 Victory Blvd",
    "sg:city":"Woodland Hills",
    "sg:classifiers":[
        {
            "category":"Professional",
            "subcategory":"Lawyer & Legal Services",
            "type":"Services"
        }
    ],
    "sg:phone":"+1 818 340 0597",
    "sg:postcode":"91367",
    "sg:province":"CA",
    "wof:name":"Brauer Marc Atty",
    "wof:placetype":"venue"
},
  "geometry": {"coordinates":[-118.596001,34.188301],"type":"Point"}
}