{
  "type": "Feature",
  "properties": {
    "addr:full":"1835 Columbia St Ste 206 San Diego CA 92101",
    "addr:housenumber":"1835",
    "addr:postcode":"92101",
    "addr:street":"Columbia St Ste 206",
    "iso:country":"US",
    "sg:address":"1835 Columbia St Ste 206",
    "sg:city":"San Diego",
    "sg:classifiers":[
        {
            "category":"Personal",
            "subcategory":"Beauty Salon",
            "type":"Services"
        },
        {
            "category":"Personal",
            "subcategory":"Day Spa",
            "type":"Services"
        }
    ],
    "sg:phone":"+1 619 564 3757",
    "sg:postcode":"92101",
    "sg:province":"CA",
    "sg:tags":[
        "hair"
    ],
    "sg:website":"www.evolvesd.com",
    "wof:name":"Evolve Salon and Spa",
    "wof:placetype":"venue"
},
  "geometry": {"coordinates":[-117.16721699999999,32.724373],"type":"Point"}
}