{
  "type": "Feature",
  "properties": {
    "addr:full":"1431 Oakland Blvd Walnut Creek CA 94596",
    "addr:housenumber":"1431",
    "addr:postcode":"94596",
    "addr:street":"Oakland Blvd",
    "iso:country":"US",
    "sg:address":"1431 Oakland Blvd",
    "sg:city":"Walnut Creek",
    "sg:classifiers":[
        {
            "category":"Banks & Credit Unions",
            "subcategory":"Investment Brokerage",
            "type":"Services"
        }
    ],
    "sg:phone":"+1 925 906 1350",
    "sg:postcode":"94596",
    "sg:province":"CA",
    "sg:tags":[
        "stock",
        "bond"
    ],
    "wof:name":"Bayside Financial",
    "wof:placetype":"venue"
},
  "geometry": {"coordinates":[-122.069745,37.89865],"type":"Point"}
}