{
  "type": "Feature",
  "properties": {
    "iso:country":"US",
    "sg:address":"4134 Judah St",
    "sg:city":"San Francisco",
    "sg:classifiers":[
        {
            "category":"Communications",
            "subcategory":"Radio Station",
            "type":"Services"
        },
        {
            "category":"Organizations",
            "subcategory":"Non-profit Organization",
            "type":"Services"
        }
    ],
    "sg:phone":"+1 415 564 4230",
    "sg:postcode":"94122",
    "sg:province":"CA",
    "sg:tags":[
        "broadcast",
        "school",
        "art"
    ],
    "sg:website":"www.sfgms.org",
    "wof:name":"S F Gem & Mineral Society",
    "wof:placetype":"venue"
},
  "geometry": {"coordinates":[-122.50632299999999,37.760411],"type":"Point"}
}