{
  "type": "Feature",
  "properties": {
    "iso:country":"US",
    "sg:address":"2909 F St",
    "sg:city":"Eureka",
    "sg:classifiers":[
        {
            "category":"Shopping",
            "subcategory":"Used Merchandise",
            "type":"Retail Goods"
        }
    ],
    "sg:phone":"+1 707 441 9575",
    "sg:postcode":"95501",
    "sg:province":"CA",
    "wof:name":"A Plus For You",
    "wof:placetype":"venue"
},
  "geometry": {"coordinates":[-124.163433,40.781595],"type":"Point"}
}