{
  "type": "Feature",
  "properties": {
    "addr:full":"9904 Westminster Ave Garden Grove CA 92844",
    "addr:housenumber":"9904",
    "addr:postcode":"92844",
    "addr:street":"Westminster Ave",
    "iso:country":"US",
    "sg:address":"9904 Westminster Ave",
    "sg:city":"Garden Grove",
    "sg:classifiers":[
        {
            "category":"Restaurant",
            "type":"Food & Drink"
        }
    ],
    "sg:phone":"+1 714 530 7077",
    "sg:postcode":"92844",
    "sg:province":"CA",
    "sg:tags":[
        "vietnamese"
    ],
    "wof:name":"Tay Thuong Restaurant",
    "wof:placetype":"venue"
},
  "geometry": {"coordinates":[-117.956352,33.759488],"type":"Point"}
}