{
  "type": "Feature",
  "properties": {
    "iso:country":"US",
    "sg:address":"1293 W Stowell Rd",
    "sg:city":"Santa Maria",
    "sg:classifiers":[
        {
            "category":"Farming",
            "subcategory":"Farm",
            "type":"Manufacturing & Wholesale Goods"
        }
    ],
    "sg:phone":"+1 805 349 9640",
    "sg:postcode":"93458",
    "sg:province":"CA",
    "wof:name":"Babe' Farms Inc",
    "wof:placetype":"venue"
},
  "geometry": {"coordinates":[-120.457538,34.938902],"type":"Point"}
}