{
  "type": "Feature",
  "properties": {
    "addr:full":"3485 University Ave Riverside CA 92501",
    "addr:housenumber":"3485",
    "addr:postcode":"92501",
    "addr:street":"University Ave",
    "iso:country":"US",
    "sg:address":"3485 University Ave",
    "sg:city":"Riverside",
    "sg:classifiers":[
        {
            "category":"Sports & Exercise",
            "subcategory":"Gym",
            "type":"Entertainment"
        }
    ],
    "sg:phone":"+1 951 788 6115",
    "sg:postcode":"92501",
    "sg:province":"CA",
    "sg:tags":[
        "club",
        "health",
        "studio",
        "gymnasium"
    ],
    "wof:name":"City Gym",
    "wof:placetype":"venue"
},
  "geometry": {"coordinates":[-117.372146,33.980862],"type":"Point"}
}