{
  "type": "Feature",
  "properties": {
    "iso:country":"US",
    "sg:address":"7516 Paddon Rd",
    "sg:city":"Vacaville",
    "sg:classifiers":[
        {
            "category":"Organizations",
            "subcategory":"Non-profit Organization",
            "type":"Services"
        }
    ],
    "sg:phone":"+1 707 449 4733",
    "sg:postcode":"95688",
    "sg:province":"CA",
    "sg:tags":[
        "information",
        "alcoholism",
        "treatment"
    ],
    "wof:name":"Principles Alcohol & Drug",
    "wof:placetype":"venue"
},
  "geometry": {"coordinates":[-121.953335,38.427347],"type":"Point"}
}