{
  "type": "Feature",
  "properties": {
    "addr:full":"14352 Beach Blvd Westminster CA 92683",
    "addr:housenumber":"14352",
    "addr:postcode":"92683",
    "addr:street":"Beach Blvd",
    "iso:country":"US",
    "sg:address":"14352 Beach Blvd",
    "sg:city":"Westminster",
    "sg:classifiers":[
        {
            "category":"Home & Garden",
            "subcategory":"Building Materials",
            "type":"Retail Goods"
        }
    ],
    "sg:phone":"+1 714 897 7696",
    "sg:postcode":"92683",
    "sg:province":"CA",
    "sg:tags":[
        "door"
    ],
    "wof:name":"AAA American Custom Gar Door",
    "wof:placetype":"venue"
},
  "geometry": {"coordinates":[-117.98941600000001,33.754455],"type":"Point"}
}