{
  "type": "Feature",
  "properties": {
    "iso:country":"US",
    "sg:address":"725 California Ave",
    "sg:city":"Santa Monica",
    "sg:classifiers":[
        {
            "category":"Education",
            "subcategory":"School",
            "type":"Public Place"
        }
    ],
    "sg:phone":"+1 310 393 9287",
    "sg:postcode":"90403",
    "sg:province":"CA",
    "sg:tags":[
        "elementary",
        "secondary"
    ],
    "wof:name":"Saint Monica High School",
    "wof:placetype":"venue"
},
  "geometry": {"coordinates":[-118.496356,34.023423],"type":"Point"}
}