{
  "type": "Feature",
  "properties": {
    "iso:country":"US",
    "sg:address":"2735 Olive Ct",
    "sg:city":"West Sacramento",
    "sg:classifiers":[
        {
            "category":"Manufacturing",
            "subcategory":"Lumber",
            "type":"Manufacturing & Wholesale Goods"
        }
    ],
    "sg:phone":"+1 916 374 8520",
    "sg:postcode":"95691",
    "sg:province":"CA",
    "sg:tags":[
        "mill"
    ],
    "wof:name":"Saw Mill Services",
    "wof:placetype":"venue"
},
  "geometry": {"coordinates":[-121.553338,38.551184],"type":"Point"}
}