{
  "type": "Feature",
  "properties": {
    "iso:country":"US",
    "sg:address":"27240 Turnberry Ln",
    "sg:city":"Valencia",
    "sg:classifiers":[
        {
            "category":"Health Services",
            "subcategory":"Health Practitioner",
            "type":"Services"
        }
    ],
    "sg:phone":"+1 661 362 0787",
    "sg:postcode":"91355",
    "sg:province":"CA",
    "sg:tags":[
        "hypnotist"
    ],
    "wof:name":"Motivational Hypnosis",
    "wof:placetype":"venue"
},
  "geometry": {"coordinates":[-118.577048,34.421055],"type":"Point"}
}