{
  "type": "Feature",
  "properties": {
    "addr:full":"222 Kearny St San Francisco CA 94108",
    "addr:housenumber":"222",
    "addr:postcode":"94108",
    "addr:street":"Kearny St",
    "iso:country":"US",
    "sg:address":"222 Kearny St",
    "sg:city":"San Francisco",
    "sg:classifiers":[
        {
            "category":"Professional",
            "subcategory":"Lawyer & Legal Services",
            "type":"Services"
        }
    ],
    "sg:phone":"+1 415 391 4800",
    "sg:postcode":"94108",
    "sg:province":"CA",
    "wof:name":"O'brien Harry C",
    "wof:placetype":"venue"
},
  "geometry": {"coordinates":[-122.40366400000001,37.790196],"type":"Point"}
}