{
  "type": "Feature",
  "properties": {
    "iso:country":"US",
    "sg:address":"922 N Wilson Way",
    "sg:city":"Stockton",
    "sg:classifiers":[
        {
            "category":"Shopping",
            "subcategory":"Bicycles & Sporting Goods",
            "type":"Retail Goods"
        }
    ],
    "sg:phone":"+1 209 466 8133",
    "sg:postcode":"95205",
    "sg:province":"CA",
    "sg:tags":[
        "repair",
        "book"
    ],
    "wof:name":"Savio Bicycle Supplies",
    "wof:placetype":"venue"
},
  "geometry": {"coordinates":[-121.273968,37.96468],"type":"Point"}
}