{
  "type": "Feature",
  "properties": {
    "addr:full":"1 E Live Oak Ave Arcadia CA 91006",
    "addr:housenumber":"1",
    "addr:postcode":"91006",
    "addr:street":"E Live Oak Ave",
    "iso:country":"US",
    "sg:address":"1 E Live Oak Ave",
    "sg:city":"Arcadia",
    "sg:classifiers":[
        {
            "category":"Food & Beverages",
            "subcategory":"Liquor & Beverages",
            "type":"Retail Goods"
        }
    ],
    "sg:phone":"+1 626 445 2795",
    "sg:postcode":"91006",
    "sg:province":"CA",
    "sg:tags":[
        "alcoholic"
    ],
    "wof:name":"Home Liquor",
    "wof:placetype":"venue"
},
  "geometry": {"coordinates":[-118.02923699999999,34.107538],"type":"Point"}
}