{
  "type": "Feature",
  "properties": {
    "iso:country":"US",
    "sg:address":"27990 Eucalyptus Ave",
    "sg:city":"Moreno Valley",
    "sg:classifiers":[
        {
            "category":"Autos & Motor Vehicles",
            "subcategory":"Automobile Sales",
            "type":"Retail Goods"
        }
    ],
    "sg:phone":"+1 951 247 8000",
    "sg:postcode":"92555",
    "sg:province":"CA",
    "sg:tags":[
        "car",
        "dealer"
    ],
    "sg:website":"www.morenovalleymegastore.com",
    "wof:name":"Moreno Valley Toyota",
    "wof:placetype":"venue"
},
  "geometry": {"coordinates":[-117.175145,33.937392],"type":"Point"}
}