{
  "type": "Feature",
  "properties": {
    "addr:full":"4180 Treat Blvd Concord CA 94518",
    "addr:housenumber":"4180",
    "addr:postcode":"94518",
    "addr:street":"Treat Blvd",
    "iso:country":"US",
    "sg:address":"4180 Treat Blvd",
    "sg:city":"Concord",
    "sg:classifiers":[
        {
            "category":"Shopping",
            "type":"Retail Goods"
        }
    ],
    "sg:phone":"+1 925 691 8330",
    "sg:postcode":"94518",
    "sg:province":"CA",
    "sg:tags":[
        "church",
        "supply"
    ],
    "wof:name":"New Systems Alliance",
    "wof:placetype":"venue"
},
  "geometry": {"coordinates":[-122.00243,37.954734],"type":"Point"}
}