{
  "type": "Feature",
  "properties": {
    "addr:full":"1050 W 163rd St Gardena CA 90247",
    "addr:housenumber":"1050",
    "addr:postcode":"90247",
    "addr:street":"W 163Rd St",
    "iso:country":"US",
    "sg:address":"1050 W 163rd St",
    "sg:city":"Gardena",
    "sg:classifiers":[
        {
            "category":"Organizations",
            "subcategory":"Religious Organization",
            "type":"Services"
        }
    ],
    "sg:phone":"+1 310 327 5830",
    "sg:postcode":"90247",
    "sg:province":"CA",
    "sg:tags":[
        "church"
    ],
    "wof:name":"St Anthony Of Padua Catholic",
    "wof:placetype":"venue"
},
  "geometry": {"coordinates":[-118.293165,33.883287],"type":"Point"}
}