{
  "type": "Feature",
  "properties": {
    "addr:full":"18420 S Broadway St Gardena CA 90248",
    "addr:housenumber":"18420",
    "addr:postcode":"90248",
    "addr:street":"S Broadway St",
    "iso:country":"US",
    "sg:address":"18420 S Broadway St",
    "sg:city":"Gardena",
    "sg:classifiers":[
        {
            "category":"Building & Trades",
            "subcategory":"Construction",
            "type":"Services"
        }
    ],
    "sg:phone":"+1 310 516 1800",
    "sg:postcode":"90248",
    "sg:province":"CA",
    "sg:tags":[
        "painter"
    ],
    "wof:name":"Cornerstone Painting Co",
    "wof:placetype":"venue"
},
  "geometry": {"coordinates":[-118.27839299999999,33.862268],"type":"Point"}
}