{
  "type": "Feature",
  "properties": {
    "iso:country":"US",
    "sg:address":"30175 Ave Tranquila",
    "sg:city":"Rancho Pls Vrds",
    "sg:classifiers":[
        {
            "category":"Health Services",
            "subcategory":"Health Practitioner",
            "type":"Services"
        }
    ],
    "sg:phone":"+1 310 377 3200",
    "sg:postcode":"90275",
    "sg:province":"CA",
    "sg:tags":[
        "info",
        "eating",
        "disorder",
        "treatment"
    ],
    "sg:website":"www.oceanaireinc.com",
    "wof:name":"Oceanaire Residential Program",
    "wof:placetype":"venue"
},
  "geometry": {"coordinates":[-118.401436,33.76321],"type":"Point"}
}