{
  "type": "Feature",
  "properties": {
    "addr:full":"440 Hitchcock Way Santa Barbara CA 93105",
    "addr:housenumber":"440",
    "addr:postcode":"93105",
    "addr:street":"Hitchcock Way",
    "iso:country":"US",
    "sg:address":"440 Hitchcock Way",
    "sg:city":"Santa Barbara",
    "sg:classifiers":[
        {
            "category":"Autos & Motor Vehicles",
            "subcategory":"Automobile Sales",
            "type":"Retail Goods"
        }
    ],
    "sg:phone":"+1 805 682 2411",
    "sg:postcode":"93105",
    "sg:province":"CA",
    "sg:tags":[
        "car",
        "dealer"
    ],
    "sg:website":"www.perryauto.com",
    "wof:name":"Perry Lincoln Mercury Mazda",
    "wof:placetype":"venue"
},
  "geometry": {"coordinates":[-119.745603,34.434767],"type":"Point"}
}