{
  "type": "Feature",
  "properties": {
    "addr:full":"3085 Stone Rd Bethel Island CA 94511",
    "addr:housenumber":"3085",
    "addr:postcode":"94511",
    "addr:street":"Stone Rd",
    "iso:country":"US",
    "sg:address":"3085 Stone Rd",
    "sg:city":"Bethel Island",
    "sg:classifiers":[
        {
            "category":"Organizations",
            "subcategory":"Religious Organization",
            "type":"Services"
        }
    ],
    "sg:phone":"+1 925 684 2210",
    "sg:postcode":"94511",
    "sg:province":"CA",
    "sg:tags":[
        "church"
    ],
    "wof:name":"Bethel Island Municipal Dist",
    "wof:placetype":"venue"
},
  "geometry": {"coordinates":[-121.63871,38.014461],"type":"Point"}
}