{
  "type": "Feature",
  "properties": {
    "addr:full":"3767 Birch Street Newport Beach CA 92660",
    "addr:housenumber":"3767",
    "addr:postcode":"92660",
    "addr:street":"Birch Street",
    "iso:country":"US",
    "sg:address":"3767 Birch Street",
    "sg:city":"Newport Beach",
    "sg:classifiers":[
        {
            "category":"Retail",
            "subcategory":"Auto Repair",
            "type":"Services"
        }
    ],
    "sg:phone":"+1 949 493 6906",
    "sg:postcode":"92660",
    "sg:province":"CA",
    "sg:website":"europeancarspecialist.net",
    "wof:name":"European Car Specialist",
    "wof:placetype":"venue"
},
  "geometry": {"coordinates":[-117.872338,33.662911],"type":"Point"}
}