{
  "type": "Feature",
  "properties": {
    "addr:full":"1361 Noe St San Francisco CA 94131",
    "addr:housenumber":"1361",
    "addr:postcode":"94131",
    "addr:street":"Noe St",
    "iso:country":"US",
    "sg:address":"1361 Noe St",
    "sg:city":"San Francisco",
    "sg:classifiers":[
        {
            "category":"Manufacturing",
            "subcategory":"Printing",
            "type":"Manufacturing & Wholesale Goods"
        }
    ],
    "sg:phone":"+1 415 821 4385",
    "sg:postcode":"94131",
    "sg:province":"CA",
    "sg:tags":[
        "broker"
    ],
    "sg:website":"www.printpartners.com",
    "wof:name":"Print Partners Inc",
    "wof:placetype":"venue"
},
  "geometry": {"coordinates":[-122.431348,37.746801],"type":"Point"}
}