{
  "type": "Feature",
  "properties": {
    "iso:country":"US",
    "sg:address":"7379 Milliken Ave",
    "sg:city":"Rancho Cucamonga",
    "sg:classifiers":[
        {
            "category":"Shopping",
            "subcategory":"Books",
            "type":"Retail Goods"
        }
    ],
    "sg:phone":"+1 909 987 7900",
    "sg:postcode":"91730",
    "sg:province":"CA",
    "sg:tags":[
        "dealer"
    ],
    "wof:name":"Full-Grace Christian Books",
    "wof:placetype":"venue"
},
  "geometry": {"coordinates":[-117.558591,34.119782],"type":"Point"}
}