{
  "type": "Feature",
  "properties": {
    "iso:country":"US",
    "sg:address":"3208 Scott St",
    "sg:city":"San Francisco",
    "sg:classifiers":[
        {
            "category":"Personal",
            "type":"Services"
        }
    ],
    "sg:phone":"+1 415 737 2167",
    "sg:postcode":"94123",
    "sg:province":"CA",
    "sg:tags":[
        "towing"
    ],
    "wof:name":"24 7 Towing",
    "wof:placetype":"venue"
},
  "geometry": {"coordinates":[-122.44083500000001,37.799363],"type":"Point"}
}