{
  "type": "Feature",
  "properties": {
    "iso:country":"US",
    "sg:address":"983 E Harvard Blvd",
    "sg:city":"Santa Paula",
    "sg:classifiers":[
        {
            "category":"Autos & Motor Vehicles",
            "subcategory":"Fuel & Gas Station",
            "type":"Retail Goods"
        }
    ],
    "sg:phone":"+1 805 933 0311",
    "sg:postcode":"93060",
    "sg:province":"CA",
    "sg:tags":[
        "oil"
    ],
    "wof:name":"Santa Paula Chevron",
    "wof:placetype":"venue"
},
  "geometry": {"coordinates":[-119.059045,34.350347],"type":"Point"}
}