{
  "type": "Feature",
  "properties": {
    "iso:country":"US",
    "sg:address":"49 N D St",
    "sg:city":"Porterville",
    "sg:classifiers":[
        {
            "category":"Restaurant",
            "type":"Food & Drink"
        }
    ],
    "sg:phone":"+1 559 781 0530",
    "sg:postcode":"93257",
    "sg:province":"CA",
    "sg:tags":[
        "pizza"
    ],
    "wof:name":"Mom's U-Bake Pizza",
    "wof:placetype":"venue"
},
  "geometry": {"coordinates":[-119.861289,36.606108],"type":"Point"}
}