{
  "type": "Feature",
  "properties": {
    "addr:full":"261 Hartz Ave Danville CA 94526",
    "addr:housenumber":"261",
    "addr:postcode":"94526",
    "addr:street":"Hartz Ave",
    "iso:country":"US",
    "sg:address":"261 Hartz Ave",
    "sg:city":"Danville",
    "sg:classifiers":[
        {
            "category":"Wholesale",
            "subcategory":"Durable Goods & Equipment",
            "type":"Manufacturing & Wholesale Goods"
        }
    ],
    "sg:phone":"+1 925 837 5903",
    "sg:postcode":"94526",
    "sg:province":"CA",
    "sg:tags":[
        "exporter"
    ],
    "wof:name":"Grand Monde Trading Co",
    "wof:placetype":"venue"
},
  "geometry": {"coordinates":[-122.001176,37.822791],"type":"Point"}
}