{
  "type": "Feature",
  "properties": {
    "iso:country":"US",
    "sg:address":"509 Marin St",
    "sg:city":"Thousand Oaks",
    "sg:classifiers":[
        {
            "category":"Health Services",
            "subcategory":"Health Practitioner",
            "type":"Services"
        }
    ],
    "sg:phone":"+1 805 379 1979",
    "sg:postcode":"91360",
    "sg:province":"CA",
    "sg:tags":[
        "pathologist",
        "speech"
    ],
    "wof:name":"Wendy B Weisberg",
    "wof:placetype":"venue"
},
  "geometry": {"coordinates":[-118.879711,34.183737],"type":"Point"}
}