{
  "type": "Feature",
  "properties": {
    "iso:country":"US",
    "sg:address":"12155 Tributary Pt Dr",
    "sg:city":"Rancho Cordova",
    "sg:classifiers":[
        {
            "category":"Shopping",
            "subcategory":"Computers & Home Electronics",
            "type":"Retail Goods"
        }
    ],
    "sg:phone":"+1 916 355 8790",
    "sg:postcode":"95670",
    "sg:province":"CA",
    "sg:tags":[
        "equipment",
        "electronic",
        "supply"
    ],
    "wof:name":"AKM Electronics Ind Co LTD",
    "wof:placetype":"venue"
},
  "geometry": {"coordinates":[-121.22184300000001,38.629889],"type":"Point"}
}