{
  "type": "Feature",
  "properties": {
    "addr:full":"1366 E Harvard St Glendale CA 91205",
    "addr:housenumber":"1366",
    "addr:postcode":"91205",
    "addr:street":"E Harvard St",
    "iso:country":"US",
    "sg:address":"1366 E Harvard St",
    "sg:city":"Glendale",
    "sg:classifiers":[
        {
            "category":"Home & Garden",
            "subcategory":"Household Appliances",
            "type":"Retail Goods"
        }
    ],
    "sg:phone":"+1 818 545 8581",
    "sg:postcode":"91205",
    "sg:province":"CA",
    "sg:tags":[
        "repair"
    ],
    "wof:name":"Glendale Appliances",
    "wof:placetype":"venue"
},
  "geometry": {"coordinates":[-118.235001,34.144299],"type":"Point"}
}