{
  "type": "Feature",
  "properties": {
    "addr:full":"8301 Imperial Hwy Downey CA 90242",
    "addr:housenumber":"8301",
    "addr:postcode":"90242",
    "addr:street":"Imperial Hwy",
    "iso:country":"US",
    "sg:address":"8301 Imperial Hwy",
    "sg:city":"Downey",
    "sg:classifiers":[
        {
            "category":"Health Services",
            "subcategory":"Dentist",
            "type":"Services"
        }
    ],
    "sg:phone":"+1 562 869 7006",
    "sg:postcode":"90242",
    "sg:province":"CA",
    "wof:name":"Downey Dental Health Center",
    "wof:placetype":"venue"
},
  "geometry": {"coordinates":[-118.146275,33.92139],"type":"Point"}
}