{
  "type": "Feature",
  "properties": {
    "addr:full":"12891 Austin Rd Manteca CA 95336",
    "addr:housenumber":"12891",
    "addr:postcode":"95336",
    "addr:street":"Austin Rd",
    "iso:country":"US",
    "sg:address":"12891 Austin Rd",
    "sg:city":"Manteca",
    "sg:classifiers":[
        {
            "category":"Building & Trades",
            "subcategory":"Construction",
            "type":"Services"
        }
    ],
    "sg:phone":"+1 209 983 1805",
    "sg:postcode":"95336",
    "sg:province":"CA",
    "sg:tags":[
        "demolition",
        "contractor"
    ],
    "wof:name":"Action Concrete Cutting & Dem",
    "wof:placetype":"venue"
},
  "geometry": {"coordinates":[-121.18642,37.847583],"type":"Point"}
}