{
  "type": "Feature",
  "properties": {
    "iso:country":"US",
    "sg:address":"36 W Gutierrez St",
    "sg:city":"Santa Barbara",
    "sg:classifiers":[
        {
            "category":"Autos & Motor Vehicles",
            "subcategory":"Auto Supplies",
            "type":"Retail Goods"
        }
    ],
    "sg:phone":"+1 805 966 4926",
    "sg:postcode":"93101",
    "sg:province":"CA",
    "sg:tags":[
        "automobile",
        "stereo",
        "radio"
    ],
    "wof:name":"Ladd's Auto Stereo Instltn",
    "wof:placetype":"venue"
},
  "geometry": {"coordinates":[-119.69448,34.415722],"type":"Point"}
}