{
  "type": "Feature",
  "properties": {
    "iso:country":"US",
    "sg:address":"111 Rhode Island St",
    "sg:city":"San Francisco",
    "sg:classifiers":[
        {
            "category":"Home & Garden",
            "subcategory":"Carpets & Floor Coverings",
            "type":"Retail Goods"
        }
    ],
    "sg:phone":"+1 415 621 2055",
    "sg:postcode":"94103",
    "sg:province":"CA",
    "sg:tags":[
        "dealer",
        "rug"
    ],
    "wof:name":"ABC Decorative Rugs",
    "wof:placetype":"venue"
},
  "geometry": {"coordinates":[-122.402742,37.767509],"type":"Point"}
}