{
  "type": "Feature",
  "properties": {
    "iso:country":"US",
    "sg:address":"1235 W Memory Ln",
    "sg:city":"Santa Ana",
    "sg:classifiers":[
        {
            "category":"Banks & Credit Unions",
            "subcategory":"Bank",
            "type":"Services"
        }
    ],
    "sg:phone":"+1 714 543 0422",
    "sg:postcode":"92706",
    "sg:province":"CA",
    "wof:name":"State Farm Insurance Companies",
    "wof:placetype":"venue"
},
  "geometry": {"coordinates":[-117.88400300000001,33.772999],"type":"Point"}
}