{
  "type": "Feature",
  "properties": {
    "addr:full":"654 Pacific Ct Upland CA 91786",
    "addr:housenumber":"654",
    "addr:postcode":"91786",
    "addr:street":"Pacific Ct",
    "iso:country":"US",
    "sg:address":"654 Pacific Ct",
    "sg:city":"Upland",
    "sg:classifiers":[
        {
            "category":"Communications",
            "type":"Services"
        }
    ],
    "sg:phone":"+1 909 981 3997",
    "sg:postcode":"91786",
    "sg:province":"CA",
    "wof:name":"Downie Communication",
    "wof:placetype":"venue"
},
  "geometry": {"coordinates":[-117.659311,34.113303],"type":"Point"}
}