{
  "type": "Feature",
  "properties": {
    "iso:country":"US",
    "sg:address":"109 Via Ravenna",
    "sg:city":"Newport Beach",
    "sg:classifiers":[
        {
            "category":"Insurance",
            "subcategory":"Insurance Agent",
            "type":"Services"
        }
    ],
    "sg:phone":"+1 949 675 3105",
    "sg:postcode":"92663",
    "sg:province":"CA",
    "wof:name":"Harris Dan E Insurance",
    "wof:placetype":"venue"
},
  "geometry": {"coordinates":[-117.914948,33.611174],"type":"Point"}
}