{
  "type": "Feature",
  "properties": {
    "addr:full":"819 S Orange Grove Ave Los Angeles CA 90036",
    "addr:housenumber":"819",
    "addr:postcode":"90036",
    "addr:street":"S Orange Grove Ave",
    "iso:country":"US",
    "sg:address":"819 S Orange Grove Ave",
    "sg:city":"Los Angeles",
    "sg:classifiers":[
        {
            "category":"Communications",
            "subcategory":"Film & Video Production",
            "type":"Services"
        }
    ],
    "sg:phone":"+1 323 571 2420",
    "sg:postcode":"90036",
    "sg:province":"CA",
    "sg:tags":[
        "taping"
    ],
    "wof:name":"Set Apart Pictures",
    "wof:placetype":"venue"
},
  "geometry": {"coordinates":[-118.36188300000001,34.060036],"type":"Point"}
}