{
  "type": "Feature",
  "properties": {
    "addr:full":"3507 del Sol Way Sacramento CA 95834",
    "addr:housenumber":"3507",
    "addr:postcode":"95834",
    "addr:street":"Del Sol Way",
    "iso:country":"US",
    "sg:address":"3507 del Sol Way",
    "sg:city":"Sacramento",
    "sg:classifiers":[
        {
            "category":"Real Estate",
            "subcategory":"Real Estate Services",
            "type":"Services"
        },
        {
            "category":"Building & Trades",
            "subcategory":"Cleaning & Sanitation",
            "type":"Services"
        }
    ],
    "sg:phone":"+1 916 920 4022",
    "sg:postcode":"95834",
    "sg:province":"CA",
    "sg:tags":[
        "maintenance",
        "cleaners-interior"
    ],
    "wof:name":"M & K Landscape Maintenance",
    "wof:placetype":"venue"
},
  "geometry": {"coordinates":[-121.48814900000001,38.632333],"type":"Point"}
}