{
  "type": "Feature",
  "properties": {
    "addr:full":"7101 Jurupa Ave Riverside CA 92504",
    "addr:housenumber":"7101",
    "addr:postcode":"92504",
    "addr:street":"Jurupa Ave",
    "iso:country":"US",
    "sg:address":"7101 Jurupa Ave",
    "sg:city":"Riverside",
    "sg:classifiers":[
        {
            "category":"Building & Trades",
            "subcategory":"Construction",
            "type":"Services"
        }
    ],
    "sg:phone":"+1 909 519 7825",
    "sg:postcode":"92504",
    "sg:province":"CA",
    "sg:tags":[
        "carpentry",
        "contractor"
    ],
    "wof:name":"E & J Wood Working",
    "wof:placetype":"venue"
},
  "geometry": {"coordinates":[-117.450277,33.960238],"type":"Point"}
}