{
  "type": "Feature",
  "properties": {
    "iso:country":"US",
    "sg:address":"2211 American Ave",
    "sg:city":"Hayward",
    "sg:classifiers":[
        {
            "category":"Retail",
            "subcategory":"Laundry & Dry Cleaning",
            "type":"Services"
        }
    ],
    "sg:phone":"+1 510 784 0700",
    "sg:postcode":"94545",
    "sg:province":"CA",
    "sg:tags":[
        "cleaners",
        "rug",
        "carpet"
    ],
    "wof:name":"ACS Cleaning Systems",
    "wof:placetype":"venue"
},
  "geometry": {"coordinates":[-122.12516100000001,37.646411],"type":"Point"}
}