{
  "type": "Feature",
  "properties": {
    "addr:full":"3651 W 3rd St Los Angeles CA 90020",
    "addr:housenumber":"3651",
    "addr:postcode":"90020",
    "addr:street":"W 3Rd St",
    "iso:country":"US",
    "sg:address":"3651 W 3rd St",
    "sg:city":"Los Angeles",
    "sg:classifiers":[
        {
            "category":"Professional",
            "subcategory":"Management & Consulting",
            "type":"Services"
        }
    ],
    "sg:phone":"+1 213 487 5090",
    "sg:postcode":"90020",
    "sg:province":"CA",
    "sg:tags":[
        "consultant",
        "business"
    ],
    "wof:name":"L A Discount Market",
    "wof:placetype":"venue"
},
  "geometry": {"coordinates":[-118.296654,34.069032],"type":"Point"}
}