{
  "type": "Feature",
  "properties": {
    "iso:country":"US",
    "sg:address":"2251 Camino Diablo",
    "sg:city":"Brentwood",
    "sg:classifiers":[
        {
            "category":"Food & Beverages",
            "subcategory":"Farmers Market",
            "type":"Retail Goods"
        }
    ],
    "sg:postcode":"94513",
    "sg:province":"CA",
    "wof:name":"Brentwood Cherry Orchard",
    "wof:placetype":"venue"
},
  "geometry": {"coordinates":[-121.654188,37.867442],"type":"Point"}
}