{
  "type": "Feature",
  "properties": {
    "addr:full":"2614 Garfield Ave Ontario CA 91761",
    "addr:housenumber":"2614",
    "addr:postcode":"91761",
    "addr:street":"Garfield Ave",
    "iso:country":"US",
    "sg:address":"2614 Garfield Ave",
    "sg:city":"Ontario",
    "sg:classifiers":[
        {
            "category":"Building & Trades",
            "subcategory":"Construction",
            "type":"Services"
        }
    ],
    "sg:phone":"+1 909 947 4776",
    "sg:postcode":"91761",
    "sg:province":"CA",
    "sg:tags":[
        "house"
    ],
    "wof:name":"Rollman Construction",
    "wof:placetype":"venue"
},
  "geometry": {"coordinates":[-117.635057,34.023723],"type":"Point"}
}