{
  "type": "Feature",
  "properties": {
    "addr:full":"11327 Trade Center Dr Rancho Cordova CA 95742",
    "addr:housenumber":"11327",
    "addr:postcode":"95742",
    "addr:street":"Trade Center Dr",
    "iso:country":"US",
    "sg:address":"11327 Trade Center Dr",
    "sg:city":"Rancho Cordova",
    "sg:classifiers":[
        {
            "category":"Local Transit",
            "type":"Transportation"
        }
    ],
    "sg:phone":"+1 916 485 7268",
    "sg:postcode":"95742",
    "sg:province":"CA",
    "sg:tags":[
        "limousine"
    ],
    "wof:name":"Carey Limousines Unlimited",
    "wof:placetype":"venue"
},
  "geometry": {"coordinates":[-121.261854,38.607308],"type":"Point"}
}