{
  "type": "Feature",
  "properties": {
    "addr:full":"815 E Ave Q Palmdale CA 93550",
    "addr:housenumber":"815",
    "addr:postcode":"ca 93550",
    "addr:street":"E Ave Q",
    "iso:country":"US",
    "sg:address":"815 E Ave Q",
    "sg:city":"Palmdale",
    "sg:classifiers":[
        {
            "category":"Social Services",
            "type":"Services"
        }
    ],
    "sg:phone":"+1 661 267 2582",
    "sg:postcode":"93550",
    "sg:province":"CA",
    "sg:tags":[
        "youth",
        "organization",
        "center"
    ],
    "sg:website":"www.avbgc.org",
    "wof:name":"Antelope Valley Boys & Girls",
    "wof:placetype":"venue"
},
  "geometry": {"coordinates":[-118.11604,34.587368],"type":"Point"}
}