{
  "type": "Feature",
  "properties": {
    "iso:country":"US",
    "sg:address":"1615 N Maple Ave",
    "sg:city":"Fresno",
    "sg:classifiers":[
        {
            "category":"Professional",
            "type":"Services"
        }
    ],
    "sg:phone":"+1 559 448 9225",
    "sg:postcode":"93703",
    "sg:province":"CA",
    "wof:name":"Joga Harbhajan",
    "wof:placetype":"venue"
},
  "geometry": {"coordinates":[-119.745476,36.766582],"type":"Point"}
}