{
  "type": "Feature",
  "properties": {
    "addr:full":"7600 Dublin Blvd Dublin CA 94568",
    "addr:housenumber":"7600",
    "addr:postcode":"94568",
    "addr:street":"Dublin Blvd",
    "iso:country":"US",
    "sg:address":"7600 Dublin Blvd",
    "sg:city":"Dublin",
    "sg:classifiers":[
        {
            "category":"Professional",
            "subcategory":"Management & Consulting",
            "type":"Services"
        }
    ],
    "sg:phone":"+1 925 551 6117",
    "sg:postcode":"94568",
    "sg:province":"CA",
    "sg:tags":[
        "consultant",
        "business"
    ],
    "wof:name":"Royce Asset Management",
    "wof:placetype":"venue"
},
  "geometry": {"coordinates":[-121.933618,37.702735],"type":"Point"}
}