{
  "type": "Feature",
  "properties": {
    "addr:full":"2285 Fordham Dr Costa Mesa CA 92626",
    "addr:housenumber":"2285",
    "addr:postcode":"92626",
    "addr:street":"Fordham Dr",
    "iso:country":"US",
    "sg:address":"2285 Fordham Dr",
    "sg:city":"Costa Mesa",
    "sg:classifiers":[
        {
            "category":"Professional",
            "type":"Services"
        }
    ],
    "sg:phone":"+1 949 278 8345",
    "sg:postcode":"92626",
    "sg:province":"CA",
    "wof:name":"The Nots",
    "wof:placetype":"venue"
},
  "geometry": {"coordinates":[-117.91414899999999,33.656853],"type":"Point"}
}