{
  "type": "Feature",
  "properties": {
    "addr:full":"16229 Bear Valley Rd Hesperia CA 92345",
    "addr:housenumber":"16229",
    "addr:postcode":"92345",
    "addr:street":"Bear Valley Rd",
    "iso:country":"US",
    "sg:address":"16229 Bear Valley Rd",
    "sg:city":"Hesperia",
    "sg:classifiers":[
        {
            "category":"Real Estate",
            "subcategory":"Real Estate Services",
            "type":"Services"
        },
        {
            "category":"Real Estate",
            "subcategory":"Developer",
            "type":"Services"
        },
        {
            "category":"Real Estate",
            "subcategory":"Real Estate Agent",
            "type":"Services"
        }
    ],
    "sg:phone":"+1 760 949 4500",
    "sg:postcode":"92345",
    "sg:province":"CA",
    "sg:tags":[
        "buyer",
        "consultant",
        "management",
        "commercial",
        "broker"
    ],
    "sg:website":"http://www.classicre.com",
    "wof:name":"Classic Real Estate",
    "wof:placetype":"venue"
},
  "geometry": {"coordinates":[-117.309445,34.470794],"type":"Point"}
}