{
  "type": "Feature",
  "properties": {
    "addr:full":"1485 E 3rd St Pomona CA 91766",
    "addr:housenumber":"1485",
    "addr:postcode":"91766",
    "addr:street":"E 3Rd St",
    "iso:country":"US",
    "sg:address":"1485 E 3rd St",
    "sg:city":"Pomona",
    "sg:classifiers":[
        {
            "category":"Manufacturing",
            "subcategory":"Tools & Machinery",
            "type":"Manufacturing & Wholesale Goods"
        }
    ],
    "sg:phone":"+1 909 629 2217",
    "sg:postcode":"91766",
    "sg:province":"CA",
    "sg:tags":[
        "machine",
        "shop"
    ],
    "wof:name":"Hansen Manufacturing Co",
    "wof:placetype":"venue"
},
  "geometry": {"coordinates":[-117.727935,34.057542],"type":"Point"}
}