{
  "type": "Feature",
  "properties": {
    "iso:country":"US",
    "sg:address":"2310 E Colorado Blvd",
    "sg:city":"Pasadena",
    "sg:classifiers":[
        {
            "category":"Shopping",
            "subcategory":"Jewelry",
            "type":"Retail Goods"
        },
        {
            "category":"Shopping",
            "subcategory":"Antiques",
            "type":"Retail Goods"
        }
    ],
    "sg:phone":"+1 626 795 1414",
    "sg:postcode":"91107",
    "sg:province":"CA",
    "sg:website":"www.desperatechics.com",
    "wof:name":"Desperate Chic's",
    "wof:placetype":"venue"
},
  "geometry": {"coordinates":[-118.10307400000001,34.146086],"type":"Point"}
}