{
  "type": "Feature",
  "properties": {
    "iso:country":"US",
    "sg:address":"5148 Stevens Creek Blvd",
    "sg:city":"San Jose",
    "sg:classifiers":[
        {
            "category":"Shopping",
            "subcategory":"Pets & Pet Supplies",
            "type":"Retail Goods"
        }
    ],
    "sg:phone":"+1 408 247 0077",
    "sg:postcode":"95129",
    "sg:province":"CA",
    "sg:website":"www.petfoodexpress.com",
    "wof:name":"Pet Food Express",
    "wof:placetype":"venue"
},
  "geometry": {"coordinates":[-121.991997,37.3232],"type":"Point"}
}