{
  "type": "Feature",
  "properties": {
    "addr:full":"27250 Los Arboles Dr Carmel CA 93923",
    "addr:housenumber":"27250",
    "addr:postcode":"93923",
    "addr:street":"Los Arboles Dr",
    "iso:country":"US",
    "sg:address":"27250 Los Arboles Dr",
    "sg:city":"Carmel",
    "sg:classifiers":[
        {
            "category":"Real Estate",
            "subcategory":"Real Estate Services",
            "type":"Services"
        },
        {
            "category":"Real Estate",
            "subcategory":"Developer",
            "type":"Services"
        },
        {
            "category":"Real Estate",
            "subcategory":"Real Estate Agent",
            "type":"Services"
        }
    ],
    "sg:phone":"+1 831 625 1414",
    "sg:postcode":"93923",
    "sg:province":"CA",
    "sg:tags":[
        "investing",
        "commercial"
    ],
    "sg:website":"http://www.jnmcommercial.com",
    "wof:name":"JNM Company",
    "wof:placetype":"venue"
},
  "geometry": {"coordinates":[-121.82959700000001,36.530561],"type":"Point"}
}