{
  "type": "Feature",
  "properties": {
    "addr:full":"7790 Serpa Ln Dixon CA 95620",
    "addr:postcode":"7790;95620",
    "addr:street":"Serpa Ln",
    "iso:country":"US",
    "sg:address":"7790 Serpa Ln",
    "sg:city":"Dixon",
    "sg:classifiers":[
        {
            "category":"Retail",
            "subcategory":"Repair Shop",
            "type":"Services"
        }
    ],
    "sg:phone":"+1 707 678 6077",
    "sg:postcode":"95620",
    "sg:province":"CA",
    "sg:tags":[
        "tractor"
    ],
    "wof:name":"C & C Mobile Tractor Repair",
    "wof:placetype":"venue"
},
  "geometry": {"coordinates":[-121.882521,38.438645],"type":"Point"}
}