{
  "type": "Feature",
  "properties": {
    "addr:full":"1188 Franklin St Oakland CA 94607",
    "addr:housenumber":"1188",
    "addr:postcode":"94607",
    "addr:street":"Franklin St",
    "iso:country":"US",
    "sg:address":"1188 Franklin St",
    "sg:city":"Oakland",
    "sg:classifiers":[
        {
            "category":"Food & Beverages",
            "subcategory":"Meat & Fish",
            "type":"Retail Goods"
        }
    ],
    "sg:phone":"+1 510 452 1320",
    "sg:postcode":"94607",
    "sg:province":"CA",
    "sg:tags":[
        "seafood-wholesale"
    ],
    "wof:name":"Motea Seafood Incorporated",
    "wof:placetype":"venue"
},
  "geometry": {"coordinates":[-122.27086300000001,37.802401],"type":"Point"}
}