{
  "type": "Feature",
  "properties": {
    "iso:country":"US",
    "sg:address":"6500 Winnetka Ave",
    "sg:city":"Woodland Hills",
    "sg:classifiers":[
        {
            "category":"Building & Trades",
            "subcategory":"Landscaping Services",
            "type":"Services"
        }
    ],
    "sg:phone":"+1 818 345 1130",
    "sg:postcode":"91367",
    "sg:province":"CA",
    "sg:tags":[
        "tree"
    ],
    "wof:name":"United Tree Svc",
    "wof:placetype":"venue"
},
  "geometry": {"coordinates":[-118.570888,34.188628],"type":"Point"}
}