{
  "type": "Feature",
  "properties": {
    "addr:full":"1483 Donner Ave San Francisco CA 94124",
    "addr:housenumber":"1483",
    "addr:postcode":"94124",
    "addr:street":"Donner Ave",
    "iso:country":"US",
    "sg:address":"1483 Donner Ave",
    "sg:city":"San Francisco",
    "sg:classifiers":[
        {
            "category":"Manufacturing",
            "subcategory":"Metals",
            "type":"Manufacturing & Wholesale Goods"
        }
    ],
    "sg:phone":"+1 415 822 7128",
    "sg:postcode":"94124",
    "sg:province":"CA",
    "sg:tags":[
        "steel"
    ],
    "wof:name":"Owa Steel",
    "wof:placetype":"venue"
},
  "geometry": {"coordinates":[-122.39086399999999,37.722338],"type":"Point"}
}