{
  "type": "Feature",
  "properties": {
    "iso:country":"US",
    "sg:address":"1483 Donner Ave",
    "sg:city":"San Francisco",
    "sg:classifiers":[
        {
            "category":"Manufacturing",
            "subcategory":"Metals",
            "type":"Manufacturing & Wholesale Goods"
        }
    ],
    "sg:phone":"+1 415 822 7128",
    "sg:postcode":"94124",
    "sg:province":"CA",
    "sg:tags":[
        "steel"
    ],
    "wof:name":"Owa Steel",
    "wof:placetype":"venue"
},
  "geometry": {"coordinates":[-122.390864,37.722338],"type":"Point"}
}