{
  "type": "Feature",
  "properties": {
    "addr:full":"1000 Charleston Cir Roseville CA 95661",
    "addr:housenumber":"1000",
    "addr:postcode":"95661",
    "addr:street":"Charleston Cir",
    "iso:country":"US",
    "sg:address":"1000 Charleston Cir",
    "sg:city":"Roseville",
    "sg:classifiers":[
        {
            "category":"Shopping",
            "subcategory":"Bicycles & Sporting Goods",
            "type":"Retail Goods"
        }
    ],
    "sg:phone":"+1 916 786 3921",
    "sg:postcode":"95661",
    "sg:province":"CA",
    "wof:name":"GK Slim & Associates",
    "wof:placetype":"venue"
},
  "geometry": {"coordinates":[-121.26553699999999,38.733301],"type":"Point"}
}