{
  "type": "Feature",
  "properties": {
    "addr:full":"66863 Flora Ave Desert Hot Spgs CA 92240",
    "addr:housenumber":"66863",
    "addr:postcode":"92240",
    "addr:street":"Flora Ave;Hot Spgs",
    "iso:country":"US",
    "sg:address":"66863 Flora Ave",
    "sg:city":"Desert Hot Spgs",
    "sg:classifiers":[
        {
            "category":"Social Services",
            "subcategory":"Job Training",
            "type":"Services"
        }
    ],
    "sg:phone":"+1 760 251 2068",
    "sg:postcode":"92240",
    "sg:province":"CA",
    "sg:tags":[
        "rehabilitation"
    ],
    "sg:website":"www.angelview.org",
    "wof:name":"Angel View Crippled Children's",
    "wof:placetype":"venue"
},
  "geometry": {"coordinates":[-116.494457,33.955914],"type":"Point"}
}