{
  "type": "Feature",
  "properties": {
    "addr:full":"1800 N Pepper St Burbank CA 91505",
    "addr:housenumber":"1800",
    "addr:postcode":"91505",
    "addr:street":"N Pepper St",
    "iso:country":"US",
    "sg:address":"1800 N Pepper St",
    "sg:city":"Burbank",
    "sg:classifiers":[
        {
            "category":"Wholesale",
            "subcategory":"Construction Materials",
            "type":"Manufacturing & Wholesale Goods"
        }
    ],
    "sg:phone":"+1 818 526 0006",
    "sg:postcode":"91505",
    "sg:province":"CA",
    "sg:tags":[
        "pipe",
        "sewer",
        "drain"
    ],
    "wof:name":"J & C Underground",
    "wof:placetype":"venue"
},
  "geometry": {"coordinates":[-118.350268,34.18429],"type":"Point"}
}