{
  "type": "Feature",
  "properties": {
    "iso:country":"US",
    "sg:address":"2917 Salvio St Ste D",
    "sg:city":"Concord",
    "sg:classifiers":[
        {
            "category":"Personal",
            "subcategory":"Beauty Salon",
            "type":"Services"
        },
        {
            "category":"Personal",
            "subcategory":"Skin Care",
            "type":"Services"
        }
    ],
    "sg:phone":"+1 925 798 7546",
    "sg:postcode":"94519",
    "sg:province":"CA",
    "sg:website":"http://www.skinclinic.com",
    "wof:name":"Eastbay Acne & Skin Care Clinic Inc",
    "wof:placetype":"venue"
},
  "geometry": {"coordinates":[-122.025746,37.981773],"type":"Point"}
}