{
  "type": "Feature",
  "properties": {
    "iso:country":"US",
    "sg:address":"30933 Curran Ct",
    "sg:city":"Valley Center",
    "sg:classifiers":[
        {
            "category":"Shopping",
            "subcategory":"Gifts & Souvenirs",
            "type":"Retail Goods"
        }
    ],
    "sg:phone":"+1 760 438 0243",
    "sg:postcode":"92082",
    "sg:province":"CA",
    "wof:name":"Designs By Davi",
    "wof:placetype":"venue"
},
  "geometry": {"coordinates":[-116.999111,33.281956],"type":"Point"}
}