{
  "type": "Feature",
  "properties": {
    "iso:country":"US",
    "sg:address":"1111 S 4th St",
    "sg:city":"El Centro",
    "sg:classifiers":[
        {
            "category":"Health Services",
            "subcategory":"Doctor",
            "type":"Services"
        }
    ],
    "sg:phone":"+1 760 336 2600",
    "sg:postcode":"92243",
    "sg:province":"CA",
    "sg:tags":[
        "dentist"
    ],
    "wof:name":"El Centro Dental",
    "wof:placetype":"venue"
},
  "geometry": {"coordinates":[-115.552369,32.782747],"type":"Point"}
}