{
  "type": "Feature",
  "properties": {
    "iso:country":"US",
    "sg:address":"325 Oak Ave",
    "sg:city":"Carlsbad",
    "sg:classifiers":[
        {
            "category":"Recreation",
            "type":"Entertainment"
        }
    ],
    "sg:phone":"+1 760 729 2062",
    "sg:postcode":"92008",
    "sg:province":"CA",
    "sg:tags":[
        "amusement"
    ],
    "wof:name":"Rusty Whitlock Surfboards",
    "wof:placetype":"venue"
},
  "geometry": {"coordinates":[-117.349403,33.157438],"type":"Point"}
}