{
  "type": "Feature",
  "properties": {
    "addr:full":"166 W Portal Avenue San Francisco CA 94127",
    "addr:housenumber":"166",
    "addr:postcode":"94127",
    "addr:street":"W Portal Avenue",
    "iso:country":"US",
    "sg:address":"166 W Portal Avenue",
    "sg:city":"San Francisco",
    "sg:classifiers":[
        {
            "category":"Retail",
            "subcategory":"Laundry & Dry Cleaning",
            "type":"Services"
        }
    ],
    "sg:phone":"+1 415 564 1011",
    "sg:postcode":"94127",
    "sg:province":"CA",
    "wof:name":"West Portal Quick Clean",
    "wof:placetype":"venue"
},
  "geometry": {"coordinates":[-122.468002,37.739201],"type":"Point"}
}