{
  "type": "Feature",
  "properties": {
    "iso:country":"US",
    "sg:address":"3801 S Normandie Ave",
    "sg:city":"Los Angeles",
    "sg:classifiers":[
        {
            "category":"Organizations",
            "subcategory":"Religious Organization",
            "type":"Services"
        }
    ],
    "sg:phone":"+1 323 731 7787",
    "sg:postcode":"90037",
    "sg:province":"CA",
    "sg:tags":[
        "church"
    ],
    "wof:name":"Normandie Community Temple",
    "wof:placetype":"venue"
},
  "geometry": {"coordinates":[-118.300168,34.016424],"type":"Point"}
}