{
  "type": "Feature",
  "properties": {
    "iso:country":"US",
    "sg:address":"4065 E Castro Valley Blvd",
    "sg:city":"Castro Valley",
    "sg:classifiers":[
        {
            "category":"Banks & Credit Unions",
            "subcategory":"Bank",
            "type":"Services"
        },
        {
            "category":"Banks & Credit Unions",
            "subcategory":"Financial Services",
            "type":"Services"
        }
    ],
    "sg:phone":"+1 510 247 8350",
    "sg:postcode":"94552",
    "sg:province":"CA",
    "sg:tags":[
        "broker",
        "mortgage"
    ],
    "wof:name":"Washington Mutual",
    "wof:placetype":"venue"
},
  "geometry": {"coordinates":[-122.049004,37.696701],"type":"Point"}
}