{
  "type": "Feature",
  "properties": {
    "iso:country":"US",
    "sg:address":"5856 Adams Blvd",
    "sg:city":"Culver City",
    "sg:classifiers":[
        {
            "category":"Manufacturing",
            "subcategory":"Tools & Machinery",
            "type":"Manufacturing & Wholesale Goods"
        }
    ],
    "sg:phone":"+1 323 549 9909",
    "sg:postcode":"90232",
    "sg:province":"CA",
    "sg:tags":[
        "equipment",
        "lighting",
        "mfg"
    ],
    "wof:name":"Elite Lighting Corporation",
    "wof:placetype":"venue"
},
  "geometry": {"coordinates":[-118.373028,34.032826],"type":"Point"}
}