{
  "type": "Feature",
  "properties": {
    "iso:country":"US",
    "sg:address":"916 E Imperial Hwy",
    "sg:city":"Brea",
    "sg:classifiers":[
        {
            "category":"Health Services",
            "subcategory":"Health Practitioner",
            "type":"Services"
        }
    ],
    "sg:phone":"+1 714 990 0824",
    "sg:postcode":"92821",
    "sg:province":"CA",
    "sg:tags":[
        "medicine",
        "alternative"
    ],
    "wof:name":"G Douglas Andersen",
    "wof:placetype":"venue"
},
  "geometry": {"coordinates":[-117.89184899999999,33.913213],"type":"Point"}
}