{
  "type": "Feature",
  "properties": {
    "iso:country":"US",
    "sg:address":"1227 de la Vina St",
    "sg:city":"Santa Barbara",
    "sg:classifiers":[
        {
            "category":"Building & Trades",
            "subcategory":"Landscaping Services",
            "type":"Services"
        }
    ],
    "sg:phone":"+1 805 963 2006",
    "sg:postcode":"93101",
    "sg:province":"CA",
    "sg:tags":[
        "designer",
        "landscape"
    ],
    "wof:name":"Earthform Design",
    "wof:placetype":"venue"
},
  "geometry": {"coordinates":[-119.707771,34.421853],"type":"Point"}
}