{
  "type": "Feature",
  "properties": {
    "iso:country":"US",
    "sg:address":"11647 Morrison St",
    "sg:city":"North Hollywood",
    "sg:classifiers":[
        {
            "category":"Local Transit",
            "type":"Transportation"
        }
    ],
    "sg:phone":"+1 323 874 4085",
    "sg:postcode":"91601",
    "sg:province":"CA",
    "sg:tags":[
        "passenger"
    ],
    "wof:name":"Gmd Transportation Inc",
    "wof:placetype":"venue"
},
  "geometry": {"coordinates":[-118.386897,34.160451],"type":"Point"}
}