{
  "type": "Feature",
  "properties": {
    "iso:country":"US",
    "sg:address":"757 Lincoln Ave",
    "sg:city":"San Rafael",
    "sg:classifiers":[
        {
            "category":"Retail",
            "subcategory":"Repair Shop",
            "type":"Services"
        }
    ],
    "sg:phone":"+1 415 456 1525",
    "sg:postcode":"94901",
    "sg:province":"CA",
    "sg:tags":[
        "antique",
        "restoring"
    ],
    "wof:name":"Pilgrim Plating Co",
    "wof:placetype":"venue"
},
  "geometry": {"coordinates":[-122.524457,37.969381],"type":"Point"}
}