{
  "type": "Feature",
  "properties": {
    "addr:full":"901 S Western Ave Los Angeles CA 90006",
    "addr:housenumber":"901",
    "addr:postcode":"90006",
    "addr:street":"S Western Ave",
    "iso:country":"US",
    "sg:address":"901 S Western Ave",
    "sg:city":"Los Angeles",
    "sg:classifiers":[
        {
            "category":"Food & Beverages",
            "subcategory":"Fruits & Vegetables",
            "type":"Retail Goods"
        }
    ],
    "sg:phone":"+1 323 733 0105",
    "sg:postcode":"90006",
    "sg:province":"CA",
    "sg:tags":[
        "produce"
    ],
    "wof:name":"Tomato",
    "wof:placetype":"venue"
},
  "geometry": {"coordinates":[-118.30905799999999,34.054438],"type":"Point"}
}