{
  "type": "Feature",
  "properties": {
    "addr:full":"1050 Rosecrans St San Diego CA 92106",
    "addr:housenumber":"1050",
    "addr:postcode":"92106",
    "addr:street":"Rosecrans St",
    "iso:country":"US",
    "sg:address":"1050 Rosecrans St",
    "sg:city":"San Diego",
    "sg:classifiers":[
        {
            "category":"Real Estate",
            "subcategory":"Real Estate Agent",
            "type":"Services"
        }
    ],
    "sg:phone":"+1 619 221 6688",
    "sg:postcode":"92106",
    "sg:province":"CA",
    "sg:website":"www.pacificviewre.com",
    "wof:name":"Pacific View Real Estate",
    "wof:placetype":"venue"
},
  "geometry": {"coordinates":[-117.23208,32.721242],"type":"Point"}
}