{
  "type": "Feature",
  "properties": {
    "iso:country":"US",
    "sg:address":"1545 Sawtelle Blvd",
    "sg:city":"Los Angeles",
    "sg:classifiers":[
        {
            "category":"Professional",
            "subcategory":"Advertising",
            "type":"Services"
        },
        {
            "category":"Manufacturing",
            "subcategory":"Printing",
            "type":"Manufacturing & Wholesale Goods"
        }
    ],
    "sg:phone":"+1 310 473 9419",
    "sg:postcode":"90025",
    "sg:province":"CA",
    "sg:tags":[
        "communication",
        "multimedia",
        "representative"
    ],
    "wof:name":"Kargl Reinhard Media Services",
    "wof:placetype":"venue"
},
  "geometry": {"coordinates":[-118.450037,34.048365],"type":"Point"}
}