{
  "type": "Feature",
  "properties": {
    "addr:full":"1075 Tully Rd San Jose CA 95111",
    "addr:housenumber":"1075",
    "addr:postcode":"95111",
    "addr:street":"Tully Rd",
    "iso:country":"US",
    "sg:address":"1075 Tully Rd",
    "sg:city":"San Jose",
    "sg:classifiers":[
        {
            "category":"Building & Trades",
            "subcategory":"Construction",
            "type":"Services"
        }
    ],
    "sg:phone":"+1 408 292 7180",
    "sg:postcode":"95111",
    "sg:province":"CA",
    "sg:tags":[
        "tile",
        "dealer"
    ],
    "wof:name":"ABC Tile",
    "wof:placetype":"venue"
},
  "geometry": {"coordinates":[-121.83748799999999,37.31454],"type":"Point"}
}