{
  "type": "Feature",
  "properties": {
    "addr:full":"1925 Arapahoe St Los Angeles CA 90007",
    "addr:housenumber":"1925",
    "addr:postcode":"90007",
    "addr:street":"Arapahoe St",
    "iso:country":"US",
    "sg:address":"1925 Arapahoe St",
    "sg:city":"Los Angeles",
    "sg:classifiers":[
        {
            "category":"Manufacturing",
            "subcategory":"Toys & Sporting Goods",
            "type":"Manufacturing & Wholesale Goods"
        }
    ],
    "sg:phone":"+1 213 749 3226",
    "sg:postcode":"90007",
    "sg:province":"CA",
    "sg:tags":[
        "fund",
        "game",
        "raising",
        "mdse"
    ],
    "sg:website":"www.adams-brooks.com",
    "wof:name":"Adams & Brooks Inc",
    "wof:placetype":"venue"
},
  "geometry": {"coordinates":[-118.284836,34.038633],"type":"Point"}
}