{
  "type": "Feature",
  "properties": {
    "addr:full":"746 5th Ave Chula Vista CA 91910",
    "addr:housenumber":"746",
    "addr:postcode":"91910",
    "addr:street":"5Th Ave",
    "iso:country":"US",
    "sg:address":"746 5th Ave",
    "sg:city":"Chula Vista",
    "sg:classifiers":[
        {
            "category":"Banks & Credit Unions",
            "subcategory":"Financial Services",
            "type":"Services"
        }
    ],
    "sg:phone":"+1 619 427 0489",
    "sg:postcode":"91910",
    "sg:province":"CA",
    "sg:tags":[
        "trust",
        "management"
    ],
    "wof:name":"Wilson Family Trust 09 21",
    "wof:placetype":"venue"
},
  "geometry": {"coordinates":[-117.082251,32.624009],"type":"Point"}
}