{
  "type": "Feature",
  "properties": {
    "addr:full":"500 Columbia South Pasadena CA 91030",
    "addr:housenumber":"500",
    "addr:postcode":"91030",
    "addr:street":"Columbia",
    "iso:country":"US",
    "sg:address":"500 Columbia",
    "sg:city":"South Pasadena",
    "sg:classifiers":[
        {
            "category":"Health Services",
            "subcategory":"Dentist",
            "type":"Services"
        }
    ],
    "sg:phone":"+1 323 682 1131",
    "sg:postcode":"91030",
    "sg:province":"CA",
    "wof:name":"Mary Chess-Abelson, DDS",
    "wof:placetype":"venue"
},
  "geometry": {"coordinates":[-118.16091299999999,34.123589],"type":"Point"}
}