{
  "type": "Feature",
  "properties": {
    "addr:full":"1039 S La Cienega Boulevard Los Angeles CA 90035",
    "addr:housenumber":"1039",
    "addr:postcode":"90035",
    "addr:street":"S La Cienega Boulevard",
    "iso:country":"US",
    "sg:address":"1039 S La Cienega Boulevard",
    "sg:city":"Los Angeles",
    "sg:classifiers":[
        {
            "category":"Place Of Worship",
            "subcategory":"Synagogue",
            "type":"Public Place"
        }
    ],
    "sg:phone":"+1 310 652 7353",
    "sg:postcode":"90035",
    "sg:province":"CA",
    "wof:name":"Pressman Academy",
    "wof:placetype":"venue"
},
  "geometry": {"coordinates":[-118.37606,34.058669],"type":"Point"}
}