{
  "type": "Feature",
  "properties": {
    "iso:country":"US",
    "sg:address":"851 W Midway Ave Ste 10C",
    "sg:city":"Alameda",
    "sg:classifiers":[
        {
            "category":"Utilities",
            "subcategory":"Water",
            "type":"Services"
        },
        {
            "category":"Recreation",
            "subcategory":"Water Park",
            "type":"Entertainment"
        }
    ],
    "sg:phone":"+1 510 748 9993",
    "sg:postcode":"94501",
    "sg:province":"CA",
    "sg:tags":[
        "industrial",
        "supply-wholesale",
        "treatment",
        "supplies-commercial",
        "systems-equipment"
    ],
    "sg:website":"http://www.renovare.com",
    "wof:name":"Renovare International Inc",
    "wof:placetype":"venue"
},
  "geometry": {"coordinates":[-122.29979400000001,37.785676],"type":"Point"}
}