{
  "type": "Feature",
  "properties": {
    "addr:full":"2424 Pico Blvd Santa Monica CA 90405",
    "addr:housenumber":"2424",
    "addr:postcode":"90405",
    "addr:street":"Pico Blvd",
    "iso:country":"US",
    "sg:address":"2424 Pico Blvd",
    "sg:city":"Santa Monica",
    "sg:classifiers":[
        {
            "category":"Restaurant",
            "type":"Food & Drink"
        }
    ],
    "sg:menulink":"http://www.allmenus.com/ca/santa-monica/20863-josie/menu/",
    "sg:phone":"+1 310 581 9888",
    "sg:postcode":"90405",
    "sg:province":"CA",
    "sg:tags":[
        "american"
    ],
    "wof:name":"Josie",
    "wof:placetype":"venue"
},
  "geometry": {"coordinates":[-118.46427300000001,34.022215],"type":"Point"}
}