{
  "type": "Feature",
  "properties": {
    "iso:country":"US",
    "sg:address":"413 Ridgecrest Dr",
    "sg:city":"Mammoth Lakes",
    "sg:classifiers":[
        {
            "category":"Home & Garden",
            "subcategory":"Building Materials",
            "type":"Retail Goods"
        }
    ],
    "sg:phone":"+1 760 924 0945",
    "sg:postcode":"93546",
    "sg:province":"CA",
    "sg:tags":[
        "shutter"
    ],
    "wof:name":"Todays Window Fashions",
    "wof:placetype":"venue"
},
  "geometry": {"coordinates":[-118.988901,37.650354],"type":"Point"}
}