{
  "type": "Feature",
  "properties": {
    "addr:full":"44467 Arapaho Ave Fremont CA 94539",
    "addr:housenumber":"44467",
    "addr:postcode":"94539",
    "addr:street":"Arapaho Ave",
    "iso:country":"US",
    "sg:address":"44467 Arapaho Ave",
    "sg:city":"Fremont",
    "sg:classifiers":[
        {
            "category":"Professional",
            "type":"Services"
        }
    ],
    "sg:phone":"+1 510 668 0791",
    "sg:postcode":"94539",
    "sg:province":"CA",
    "sg:tags":[
        "establishment"
    ],
    "wof:name":"Compeq International",
    "wof:placetype":"venue"
},
  "geometry": {"coordinates":[-121.932501,37.511745],"type":"Point"}
}