{
  "type": "Feature",
  "properties": {
    "addr:full":"4901 Green River Rd Corona CA 92880",
    "addr:housenumber":"4901",
    "addr:postcode":"92880",
    "addr:street":"Green River Rd",
    "iso:country":"US",
    "sg:address":"4901 Green River Rd",
    "sg:city":"Corona",
    "sg:classifiers":[
        {
            "category":"Building & Trades",
            "subcategory":"Construction",
            "type":"Services"
        }
    ],
    "sg:phone":"+1 951 371 6418",
    "sg:postcode":"92880",
    "sg:province":"CA",
    "sg:tags":[
        "floor",
        "laying",
        "contractor"
    ],
    "wof:name":"Deep & Deeper Gomez Carpet",
    "wof:placetype":"venue"
},
  "geometry": {"coordinates":[-117.66710999999999,33.871732],"type":"Point"}
}