{
  "type": "Feature",
  "properties": {
    "iso:country":"US",
    "sg:address":"3236 Auburn Blvd",
    "sg:city":"Sacramento",
    "sg:classifiers":[
        {
            "category":"Shopping",
            "subcategory":"Clothing, Apparel, & Fashions",
            "type":"Retail Goods"
        },
        {
            "category":"Home & Garden",
            "subcategory":"Furniture",
            "type":"Retail Goods"
        }
    ],
    "sg:phone":"+1 916 483 1093",
    "sg:postcode":"95821",
    "sg:province":"CA",
    "sg:tags":[
        "consignment",
        "store"
    ],
    "wof:name":"Upscale Consignment Furniture",
    "wof:placetype":"venue"
},
  "geometry": {"coordinates":[-121.388982,38.634841],"type":"Point"}
}