{
  "type": "Feature",
  "properties": {
    "addr:full":"2180 Westwood Blvd Los Angeles CA 90025",
    "addr:housenumber":"2180",
    "addr:postcode":"90025",
    "addr:street":"Westwood Blvd",
    "iso:country":"US",
    "sg:address":"2180 Westwood Blvd",
    "sg:city":"Los Angeles",
    "sg:classifiers":[
        {
            "category":"Personal",
            "subcategory":"Beauty Salon",
            "type":"Services"
        }
    ],
    "sg:phone":"+1 310 234 8259",
    "sg:postcode":"90025",
    "sg:province":"CA",
    "wof:name":"Boghozion Satik",
    "wof:placetype":"venue"
},
  "geometry": {"coordinates":[-118.432474,34.045044],"type":"Point"}
}