{
  "type": "Feature",
  "properties": {
    "addr:full":"725 Parkway Plz El Cajon CA 92020",
    "addr:housenumber":"725",
    "addr:postcode":"92020",
    "addr:street":"Parkway Plz",
    "iso:country":"US",
    "sg:address":"725 Parkway Plz",
    "sg:city":"El Cajon",
    "sg:classifiers":[
        {
            "category":"Shopping",
            "subcategory":"Jewelry",
            "type":"Retail Goods"
        }
    ],
    "sg:phone":"+1 619 444 2012",
    "sg:postcode":"92020",
    "sg:province":"CA",
    "sg:website":"www.helzberg.com",
    "wof:name":"Helzberg Diamonds",
    "wof:placetype":"venue"
},
  "geometry": {"coordinates":[-116.968431,32.803596],"type":"Point"}
}