{
  "type": "Feature",
  "properties": {
    "addr:full":"1422 Kains Ave Berkeley CA 94702",
    "addr:housenumber":"1422",
    "addr:postcode":"94702",
    "addr:street":"Kains Ave",
    "iso:country":"US",
    "sg:address":"1422 Kains Ave",
    "sg:city":"Berkeley",
    "sg:classifiers":[
        {
            "category":"Banks & Credit Unions",
            "subcategory":"Financial Services",
            "type":"Services"
        }
    ],
    "sg:phone":"+1 415 205 0702",
    "sg:postcode":"94702",
    "sg:province":"CA",
    "sg:tags":[
        "management",
        "investment"
    ],
    "wof:name":"Denari Investors",
    "wof:placetype":"venue"
},
  "geometry": {"coordinates":[-122.294011,37.87799],"type":"Point"}
}