{
  "type": "Feature",
  "properties": {
    "iso:country":"US",
    "sg:address":"2069 Pacific Coast Hwy",
    "sg:city":"Lomita",
    "sg:classifiers":[
        {
            "category":"Health Services",
            "subcategory":"Chiropractor",
            "type":"Services"
        }
    ],
    "sg:phone":"+1 310 539 3999",
    "sg:postcode":"90717",
    "sg:province":"CA",
    "wof:name":"Krynen Chiropractic",
    "wof:placetype":"venue"
},
  "geometry": {"coordinates":[-118.317001,33.789398],"type":"Point"}
}