{
  "type": "Feature",
  "properties": {
    "addr:full":"751 20th St Oakland CA 94612",
    "addr:housenumber":"751",
    "addr:postcode":"94612",
    "addr:street":"20Th St",
    "iso:country":"US",
    "sg:address":"751 20th St",
    "sg:city":"Oakland",
    "sg:classifiers":[
        {
            "category":"Professional",
            "subcategory":"Computer Services",
            "type":"Services"
        }
    ],
    "sg:phone":"+1 510 904 0476",
    "sg:postcode":"94612",
    "sg:province":"CA",
    "sg:tags":[
        "repair"
    ],
    "sg:website":"www.computerrepairoaklandca.com",
    "wof:name":"Computer Repair Oakland - Geeks In Minutes",
    "wof:placetype":"venue"
},
  "geometry": {"coordinates":[-122.276284,37.811215],"type":"Point"}
}