{
  "type": "Feature",
  "properties": {
    "addr:full":"2014 Teodoro St Placentia CA 92870",
    "addr:postcode":"ca 92870",
    "addr:street":"Teodoro St",
    "iso:country":"US",
    "sg:address":"2014 Teodoro St",
    "sg:city":"Placentia",
    "sg:classifiers":[
        {
            "category":"Professional",
            "subcategory":"Testing Lab",
            "type":"Services"
        }
    ],
    "sg:phone":"+1 714 993 2200",
    "sg:postcode":"92870",
    "sg:province":"CA",
    "sg:tags":[
        "laboratory",
        "repair"
    ],
    "wof:name":"Major Services",
    "wof:placetype":"venue"
},
  "geometry": {"coordinates":[-117.856334,33.899672],"type":"Point"}
}