{
  "type": "Feature",
  "properties": {
    "addr:full":"1840 E Buena Vista Ave Visalia CA 93292",
    "addr:housenumber":"1840",
    "addr:postcode":"93292",
    "addr:street":"E Buena Vista Ave",
    "iso:country":"US",
    "sg:address":"1840 E Buena Vista Ave",
    "sg:city":"Visalia",
    "sg:classifiers":[
        {
            "category":"Professional",
            "subcategory":"Computer Services",
            "type":"Services"
        }
    ],
    "sg:phone":"+1 559 732 8745",
    "sg:postcode":"93292",
    "sg:province":"CA",
    "sg:tags":[
        "repair"
    ],
    "wof:name":"Business Machine Svc",
    "wof:placetype":"venue"
},
  "geometry": {"coordinates":[-119.273675,36.345921],"type":"Point"}
}