{
  "type": "Feature",
  "properties": {
    "iso:country":"US",
    "sg:address":"552 S Paseo Dorotea Ste 2",
    "sg:city":"Palm Springs",
    "sg:classifiers":[
        {
            "category":"Health Services",
            "subcategory":"Doctor",
            "type":"Services"
        }
    ],
    "sg:phone":"+1 760 320 6988",
    "sg:postcode":"92264",
    "sg:province":"CA",
    "wof:name":"Anderson Albert Medical Corporation",
    "wof:placetype":"venue"
},
  "geometry": {"coordinates":[-116.50165200000001,33.815195],"type":"Point"}
}