{
  "type": "Feature",
  "properties": {
    "iso:country":"US",
    "sg:address":"340 National City Blvd",
    "sg:city":"San Diego",
    "sg:classifiers":[
        {
            "category":"Shopping",
            "subcategory":"Clothing, Apparel, & Fashions",
            "type":"Retail Goods"
        }
    ],
    "sg:phone":"+1 619 477 2900",
    "sg:postcode":"91950",
    "sg:province":"CA",
    "sg:tags":[
        "leather"
    ],
    "sg:website":"www.leather.com",
    "wof:name":"San Diego Leather Jacket Factory",
    "wof:placetype":"venue"
},
  "geometry": {"coordinates":[-117.108495,32.679389],"type":"Point"}
}