{
  "type": "Feature",
  "properties": {
    "iso:country":"US",
    "sg:address":"1490 Mason St",
    "sg:city":"San Francisco",
    "sg:classifiers":[
        {
            "category":"Government",
            "subcategory":"Office",
            "type":"Public Place"
        }
    ],
    "sg:phone":"+1 415 364 7600",
    "sg:postcode":"94133",
    "sg:province":"CA",
    "sg:tags":[
        "city",
        "program",
        "health"
    ],
    "wof:name":"Chinatown Public Health Ctr",
    "wof:placetype":"venue"
},
  "geometry": {"coordinates":[-122.41168500000001,37.796337],"type":"Point"}
}