{
  "type": "Feature",
  "properties": {
    "iso:country":"US",
    "sg:address":"470 Tres Pinos Rd",
    "sg:city":"Hollister",
    "sg:classifiers":[
        {
            "category":"Personal",
            "subcategory":"Beauty Salon",
            "type":"Services"
        }
    ],
    "sg:phone":"+1 831 635 9999",
    "sg:postcode":"95023",
    "sg:province":"CA",
    "sg:tags":[
        "manicuring"
    ],
    "wof:name":"Perfect Nails",
    "wof:placetype":"venue"
},
  "geometry": {"coordinates":[-121.394625,36.839561],"type":"Point"}
}