{
  "type": "Feature",
  "properties": {
    "iso:country":"US",
    "sg:address":"401 S Hope Ave",
    "sg:city":"Santa Barbara",
    "sg:classifiers":[
        {
            "category":"Autos & Motor Vehicles",
            "subcategory":"Automobile Sales",
            "type":"Retail Goods"
        }
    ],
    "sg:phone":"+1 805 682 2800",
    "sg:postcode":"93105",
    "sg:province":"CA",
    "sg:tags":[
        "truck"
    ],
    "wof:name":"Cutter Dodge Infiniti",
    "wof:placetype":"venue"
},
  "geometry": {"coordinates":[-119.747227,34.43523],"type":"Point"}
}