{
  "type": "Feature",
  "properties": {
    "addr:full":"4340 Moorpark Ave San Jose CA 95129",
    "addr:housenumber":"4340",
    "addr:postcode":"95129",
    "addr:street":"Moorpark Ave",
    "iso:country":"US",
    "sg:address":"4340 Moorpark Ave",
    "sg:city":"San Jose",
    "sg:classifiers":[
        {
            "category":"Bars & Pubs",
            "subcategory":"Nightclub",
            "type":"Food & Drink"
        }
    ],
    "sg:phone":"+1 408 257 7770",
    "sg:postcode":"95129",
    "sg:province":"CA",
    "sg:tags":[
        "nightlife"
    ],
    "wof:name":"Redi Room",
    "wof:placetype":"venue"
},
  "geometry": {"coordinates":[-121.978996,37.316002],"type":"Point"}
}