{
  "type": "Feature",
  "properties": {
    "iso:country":"US",
    "sg:address":"6398 Dougherty Rd",
    "sg:city":"Dublin",
    "sg:classifiers":[
        {
            "category":"Home & Garden",
            "subcategory":"Building Materials",
            "type":"Retail Goods"
        }
    ],
    "sg:phone":"+1 925 828 2900",
    "sg:postcode":"94568",
    "sg:province":"CA",
    "sg:tags":[
        "glazier",
        "supply"
    ],
    "wof:name":"Stan Hodge & Co",
    "wof:placetype":"venue"
},
  "geometry": {"coordinates":[-121.910309,37.710332],"type":"Point"}
}