{
  "type": "Feature",
  "properties": {
    "addr:full":"4347 Twain Ave San Diego CA 92120",
    "addr:housenumber":"4347",
    "addr:postcode":"92120",
    "addr:street":"Twain Ave",
    "iso:country":"US",
    "sg:address":"4347 Twain Ave",
    "sg:city":"San Diego",
    "sg:classifiers":[
        {
            "category":"Building & Trades",
            "subcategory":"Landscaping Services",
            "type":"Services"
        }
    ],
    "sg:phone":"+1 619 229 1316",
    "sg:postcode":"92120",
    "sg:province":"CA",
    "wof:name":"Dave Suda Ldscpg & Irrigation",
    "wof:placetype":"venue"
},
  "geometry": {"coordinates":[-117.10028200000001,32.784944],"type":"Point"}
}