{
  "type": "Feature",
  "properties": {
    "addr:full":"1175 Willow Ave Sunnyvale CA 94086",
    "addr:housenumber":"1175",
    "addr:postcode":"94086",
    "addr:street":"Willow Ave",
    "iso:country":"US",
    "sg:address":"1175 Willow Ave",
    "sg:city":"Sunnyvale",
    "sg:classifiers":[
        {
            "category":"Shopping",
            "subcategory":"Computers & Home Electronics",
            "type":"Retail Goods"
        }
    ],
    "sg:phone":"+1 408 243 0000",
    "sg:postcode":"94086",
    "sg:province":"CA",
    "sg:tags":[
        "software"
    ],
    "wof:name":"Softeq",
    "wof:placetype":"venue"
},
  "geometry": {"coordinates":[-121.99811,37.36796],"type":"Point"}
}