{
  "type": "Feature",
  "properties": {
    "iso:country":"US",
    "sg:address":"4919 Rimwood Dr",
    "sg:city":"Fair Oaks",
    "sg:classifiers":[
        {
            "category":"Professional",
            "type":"Services"
        }
    ],
    "sg:phone":"+1 916 961 3515",
    "sg:postcode":"95628",
    "sg:province":"CA",
    "sg:tags":[
        "establishment"
    ],
    "wof:name":"Ruby's",
    "wof:placetype":"venue"
},
  "geometry": {"coordinates":[-121.267329,38.65628],"type":"Point"}
}