{
  "type": "Feature",
  "properties": {
    "iso:country":"US",
    "sg:address":"42211 Sierra Hwy Ste C",
    "sg:city":"Lancaster",
    "sg:classifiers":[
        {
            "category":"Health Services",
            "subcategory":"Clinic",
            "type":"Services"
        }
    ],
    "sg:phone":"+1 661 942 9700",
    "sg:postcode":"93535",
    "sg:province":"CA",
    "sg:tags":[
        "welfare"
    ],
    "wof:name":"Moto Medic",
    "wof:placetype":"venue"
},
  "geometry": {"coordinates":[-118.12888100000001,34.649702],"type":"Point"}
}