{
  "type": "Feature",
  "properties": {
    "iso:country":"US",
    "sg:address":"8838 Limonite Ave",
    "sg:city":"Riverside",
    "sg:classifiers":[
        {
            "category":"Retail",
            "subcategory":"Laundry & Dry Cleaning",
            "type":"Services"
        }
    ],
    "sg:phone":"+1 951 685 1637",
    "sg:postcode":"92509",
    "sg:province":"CA",
    "sg:tags":[
        "cleaners"
    ],
    "wof:name":"Alpha Cleaners",
    "wof:placetype":"venue"
},
  "geometry": {"coordinates":[-117.476221,33.975646],"type":"Point"}
}