{
  "type": "Feature",
  "properties": {
    "addr:full":"13320 San Pablo Ave San Pablo CA 94806",
    "addr:housenumber":"13320",
    "addr:postcode":"94806",
    "addr:street":"San Pablo Ave",
    "iso:country":"US",
    "sg:address":"13320 San Pablo Ave",
    "sg:city":"San Pablo",
    "sg:classifiers":[
        {
            "category":"Banks & Credit Unions",
            "subcategory":"Bank",
            "type":"Services"
        }
    ],
    "sg:phone":"+1 510 234 5000",
    "sg:postcode":"94806",
    "sg:province":"CA",
    "sg:tags":[
        "depository",
        "banking"
    ],
    "wof:name":"Ace Cash Express",
    "wof:placetype":"venue"
},
  "geometry": {"coordinates":[-122.33364400000001,37.95349],"type":"Point"}
}