{
  "type": "Feature",
  "properties": {
    "iso:country":"US",
    "sg:address":"4039 Lake Tahoe Blvd",
    "sg:city":"South Lake Tahoe",
    "sg:classifiers":[
        {
            "category":"Shopping",
            "subcategory":"Jewelry",
            "type":"Retail Goods"
        }
    ],
    "sg:phone":"+1 530 541 7676",
    "sg:postcode":"96150",
    "sg:province":"CA",
    "sg:tags":[
        "stone"
    ],
    "wof:name":"Buffalo Trading Post",
    "wof:placetype":"venue"
},
  "geometry": {"coordinates":[-119.944247,38.956047],"type":"Point"}
}