{
  "type": "Feature",
  "properties": {
    "addr:full":"16585 Von Karman Ave Irvine CA 92606",
    "addr:housenumber":"16585",
    "addr:postcode":"92606",
    "addr:street":"Von Karman Ave",
    "iso:country":"US",
    "sg:address":"16585 Von Karman Ave",
    "sg:city":"Irvine",
    "sg:classifiers":[
        {
            "category":"Professional",
            "type":"Services"
        }
    ],
    "sg:phone":"+1 949 261 4801",
    "sg:postcode":"92606",
    "sg:province":"CA",
    "wof:name":"Page Enterworx",
    "wof:placetype":"venue"
},
  "geometry": {"coordinates":[-117.838003,33.694086],"type":"Point"}
}