{
  "type": "Feature",
  "properties": {
    "addr:full":"1206 S Chapel Ave Alhambra CA 91801",
    "addr:housenumber":"1206",
    "addr:postcode":"91801",
    "addr:street":"S Chapel Ave",
    "iso:country":"US",
    "sg:address":"1206 S Chapel Ave",
    "sg:city":"Alhambra",
    "sg:classifiers":[
        {
            "category":"Wholesale",
            "subcategory":"Non-durable Goods",
            "type":"Manufacturing & Wholesale Goods"
        }
    ],
    "sg:phone":"+1 626 282 7568",
    "sg:postcode":"91801",
    "sg:province":"CA",
    "wof:name":"Commercial Mely Intl Trading",
    "wof:placetype":"venue"
},
  "geometry": {"coordinates":[-118.119665,34.079356],"type":"Point"}
}