{
  "type": "Feature",
  "properties": {
    "iso:country":"US",
    "sg:address":"1403 Ocean St",
    "sg:city":"Santa Cruz",
    "sg:classifiers":[
        {
            "category":"Donuts",
            "subcategory":"None",
            "type":"Food & Drink"
        }
    ],
    "sg:phone":"+1 831 423 9470",
    "sg:postcode":"95060",
    "sg:province":"CA",
    "wof:name":"Ferrell's Donut House",
    "wof:placetype":"venue"
},
  "geometry": {"coordinates":[-122.023003,36.984001],"type":"Point"}
}