{
  "type": "Feature",
  "properties": {
    "iso:country":"US",
    "sg:address":"801 Main St",
    "sg:city":"Saint Helena",
    "sg:classifiers":[
        {
            "category":"Freight",
            "type":"Transportation"
        },
        {
            "category":"Manufacturing",
            "subcategory":"Food",
            "type":"Manufacturing & Wholesale Goods"
        }
    ],
    "sg:phone":"+1 707 967 6371",
    "sg:postcode":"94574",
    "sg:province":"CA",
    "sg:tags":[
        "farm",
        "product",
        "warehousing",
        "mfg"
    ],
    "wof:name":"Fransiscan Estates",
    "wof:placetype":"venue"
},
  "geometry": {"coordinates":[-122.464392,38.501256],"type":"Point"}
}