{
  "type": "Feature",
  "properties": {
    "iso:country":"US",
    "sg:address":"520 Jessie St",
    "sg:city":"San Francisco",
    "sg:classifiers":[
        {
            "category":"Social Services",
            "type":"Services"
        }
    ],
    "sg:phone":"+1 415 575 4848",
    "sg:postcode":"94103",
    "sg:province":"CA",
    "sg:tags":[
        "organization",
        "welfare"
    ],
    "wof:name":"Salvation Army Svc Ctr",
    "wof:placetype":"venue"
},
  "geometry": {"coordinates":[-122.410092,37.780856],"type":"Point"}
}