{
  "type": "Feature",
  "properties": {
    "addr:full":"5819 Riverside Dr Chino CA 91710",
    "addr:housenumber":"5819",
    "addr:postcode":"91710",
    "addr:street":"Riverside Dr",
    "iso:country":"US",
    "sg:address":"5819 Riverside Dr",
    "sg:city":"Chino",
    "sg:classifiers":[
        {
            "category":"Real Estate",
            "subcategory":"Real Estate Operator",
            "type":"Services"
        }
    ],
    "sg:phone":"+1 909 591 4212",
    "sg:postcode":"91710",
    "sg:province":"CA",
    "sg:tags":[
        "apartment"
    ],
    "wof:name":"Vista Park Chino Apts",
    "wof:placetype":"venue"
},
  "geometry": {"coordinates":[-117.678549,34.019065],"type":"Point"}
}