{
  "type": "Feature",
  "properties": {
    "iso:country":"US",
    "sg:address":"27402 Valley Center Rd",
    "sg:city":"Valley Center",
    "sg:classifiers":[
        {
            "category":"Building & Trades",
            "subcategory":"Landscaping Services",
            "type":"Services"
        }
    ],
    "sg:phone":"+1 760 749 9769",
    "sg:postcode":"92082",
    "sg:province":"CA",
    "wof:name":"Will Frinchaboy Landscaping",
    "wof:placetype":"venue"
},
  "geometry": {"coordinates":[-117.033644,33.207636],"type":"Point"}
}