{
  "type": "Feature",
  "properties": {
    "iso:country":"US",
    "sg:address":"1000 Webster St",
    "sg:city":"Fairfield",
    "sg:classifiers":[
        {
            "category":"Government",
            "subcategory":"Office",
            "type":"Public Place"
        }
    ],
    "sg:phone":"+1 707 428 7451",
    "sg:postcode":"94533",
    "sg:province":"CA",
    "sg:tags":[
        "village"
    ],
    "sg:website":"www.ci.fairfield.ca.us",
    "wof:name":"Fairfield City Building Permit",
    "wof:placetype":"venue"
},
  "geometry": {"coordinates":[-122.045044,38.253672],"type":"Point"}
}