{
  "type": "Feature",
  "properties": {
    "iso:country":"US",
    "sg:address":"45 Serramonte Blvd",
    "sg:city":"Daly City",
    "sg:classifiers":[
        {
            "category":"Shopping",
            "subcategory":"Photographic Equipment",
            "type":"Retail Goods"
        }
    ],
    "sg:phone":"+1 650 994 7007",
    "sg:postcode":"94015",
    "sg:province":"CA",
    "sg:tags":[
        "supply"
    ],
    "wof:name":"Ritz Camera Ctr",
    "wof:placetype":"venue"
},
  "geometry": {"coordinates":[-122.466809,37.669441],"type":"Point"}
}