{
  "type": "Feature",
  "properties": {
    "addr:full":"425 Brearcliffe Dr Red Bluff CA 96080",
    "addr:housenumber":"425",
    "addr:postcode":"96080",
    "addr:street":"Brearcliffe Dr",
    "iso:country":"US",
    "sg:address":"425 Brearcliffe Dr",
    "sg:city":"Red Bluff",
    "sg:classifiers":[
        {
            "category":"Farming",
            "subcategory":"Crops",
            "type":"Manufacturing & Wholesale Goods"
        }
    ],
    "sg:phone":"+1 530 527 4854",
    "sg:postcode":"96080",
    "sg:province":"CA",
    "sg:tags":[
        "grove",
        "nut",
        "fruit",
        "tree",
        "orchard"
    ],
    "wof:name":"Sale Family Orchards",
    "wof:placetype":"venue"
},
  "geometry": {"coordinates":[-122.22504000000001,40.167605],"type":"Point"}
}