{
  "type": "Feature",
  "properties": {
    "iso:country":"US",
    "sg:address":"200 Benbow Ave",
    "sg:city":"San Jose",
    "sg:classifiers":[
        {
            "category":"Professional",
            "type":"Services"
        }
    ],
    "sg:phone":"+1 408 281 9881",
    "sg:postcode":"95123",
    "sg:province":"CA",
    "wof:name":"Fernando J Quinones",
    "wof:placetype":"venue"
},
  "geometry": {"coordinates":[-121.808916,37.246761],"type":"Point"}
}