{
  "type": "Feature",
  "properties": {
    "addr:full":"48 Hartnell Ave Redding CA 96002",
    "addr:housenumber":"48",
    "addr:postcode":"96002",
    "addr:street":"Hartnell Ave",
    "iso:country":"US",
    "sg:address":"48 Hartnell Ave",
    "sg:city":"Redding",
    "sg:classifiers":[
        {
            "category":"Professional",
            "subcategory":"Accounting & Tax Preparation",
            "type":"Services"
        }
    ],
    "sg:phone":"+1 530 722 1000",
    "sg:postcode":"96002",
    "sg:province":"CA",
    "sg:tags":[
        "return",
        "filing"
    ],
    "wof:name":"Jackson Hewitt Tax Svc",
    "wof:placetype":"venue"
},
  "geometry": {"coordinates":[-122.36914400000001,40.568663],"type":"Point"}
}