{
  "type": "Feature",
  "properties": {
    "iso:country":"US",
    "sg:address":"8528 Aleksander Ct",
    "sg:city":"Sacramento",
    "sg:classifiers":[
        {
            "category":"Building & Trades",
            "subcategory":"Cleaning & Sanitation",
            "type":"Services"
        }
    ],
    "sg:phone":"+1 916 688 4185",
    "sg:postcode":"95828",
    "sg:province":"CA",
    "sg:tags":[
        "house"
    ],
    "wof:name":"A Veronika's House Cleaning",
    "wof:placetype":"venue"
},
  "geometry": {"coordinates":[-121.388834,38.483951],"type":"Point"}
}