{
  "type": "Feature",
  "properties": {
    "iso:country":"US",
    "sg:address":"2155 E Colorado Blvd",
    "sg:city":"Pasadena",
    "sg:classifiers":[
        {
            "category":"Autos & Motor Vehicles",
            "subcategory":"Auto Supplies",
            "type":"Retail Goods"
        }
    ],
    "sg:phone":"+1 626 793 1900",
    "sg:postcode":"91107",
    "sg:province":"CA",
    "sg:tags":[
        "tire"
    ],
    "wof:name":"Autobahn Tire & Automotive Centers",
    "wof:placetype":"venue"
},
  "geometry": {"coordinates":[-118.106003,34.146099],"type":"Point"}
}