{
  "type": "Feature",
  "properties": {
    "addr:full":"3130 20th St San Francisco CA 94110",
    "addr:housenumber":"3130",
    "addr:postcode":"94110",
    "addr:street":"20Th St",
    "iso:country":"US",
    "sg:address":"3130 20th St",
    "sg:city":"San Francisco",
    "sg:classifiers":[
        {
            "category":"Arts & Performance",
            "subcategory":"Theater",
            "type":"Entertainment"
        },
        {
            "category":"Travel",
            "subcategory":"Travel Agent",
            "type":"Entertainment"
        }
    ],
    "sg:phone":"+1 415 285 8080",
    "sg:postcode":"94110",
    "sg:province":"CA",
    "sg:tags":[
        "agency",
        "bureau"
    ],
    "wof:name":"TJT Traveling Jewish Theatre",
    "wof:placetype":"venue"
},
  "geometry": {"coordinates":[-122.412283,37.75912],"type":"Point"}
}