{
  "type": "Feature",
  "properties": {
    "addr:full":"4801 Reece Ct Richmond CA 94804",
    "addr:housenumber":"4801",
    "addr:postcode":"94804",
    "addr:street":"Reece Ct",
    "iso:country":"US",
    "sg:address":"4801 Reece Ct",
    "sg:city":"Richmond",
    "sg:classifiers":[
        {
            "category":"Professional",
            "type":"Services"
        }
    ],
    "sg:phone":"+1 510 233 0663",
    "sg:postcode":"94804",
    "sg:province":"CA",
    "wof:name":"Hancock Nannette Dr PHD",
    "wof:placetype":"venue"
},
  "geometry": {"coordinates":[-122.32460399999999,37.927063],"type":"Point"}
}