{
  "type": "Feature",
  "properties": {
    "iso:country":"US",
    "sg:address":"5444 Bellingham Ave",
    "sg:city":"Valley Village",
    "sg:classifiers":[
        {
            "category":"Wholesale",
            "subcategory":"Jewelry",
            "type":"Manufacturing & Wholesale Goods"
        }
    ],
    "sg:phone":"+1 818 416 0520",
    "sg:postcode":"91607",
    "sg:province":"CA",
    "sg:tags":[
        "stone"
    ],
    "wof:name":"Dannys International Jwly Ctr",
    "wof:placetype":"venue"
},
  "geometry": {"coordinates":[-118.399141,34.169584],"type":"Point"}
}