{
  "type": "Feature",
  "properties": {
    "addr:full":"800 S Milliken Ave Ste G Ontario CA 91761",
    "addr:housenumber":"800",
    "addr:postcode":"91761",
    "addr:street":"S Milliken Ave Ste G",
    "iso:country":"US",
    "sg:address":"800 S Milliken Ave Ste G",
    "sg:city":"Ontario",
    "sg:classifiers":[
        {
            "category":"Professional",
            "subcategory":"Printing & Photocopies",
            "type":"Services"
        }
    ],
    "sg:phone":"+1 909 390 6700",
    "sg:postcode":"91761",
    "sg:province":"CA",
    "sg:tags":[
        "lithographer"
    ],
    "wof:name":"Picture That",
    "wof:placetype":"venue"
},
  "geometry": {"coordinates":[-117.558294,34.055884],"type":"Point"}
}