{
  "type": "Feature",
  "properties": {
    "addr:full":"903 S Lake St Burbank CA 91502",
    "addr:housenumber":"903",
    "addr:postcode":"91502",
    "addr:street":"S Lake St",
    "iso:country":"US",
    "sg:address":"903 S Lake St",
    "sg:city":"Burbank",
    "sg:classifiers":[
        {
            "category":"Shopping",
            "subcategory":"Gifts & Souvenirs",
            "type":"Retail Goods"
        }
    ],
    "sg:phone":"+1 818 557 0281",
    "sg:postcode":"91502",
    "sg:province":"CA",
    "sg:tags":[
        "basket",
        "parcel"
    ],
    "wof:name":"Pauly's Gourmet Gift Basket",
    "wof:placetype":"venue"
},
  "geometry": {"coordinates":[-118.306628,34.169873],"type":"Point"}
}