{
  "type": "Feature",
  "properties": {
    "addr:full":"2150 River Plaza Dr Sacramento CA 95833",
    "addr:housenumber":"2150",
    "addr:postcode":"95833",
    "addr:street":"River Plaza Dr",
    "iso:country":"US",
    "sg:address":"2150 River Plaza Dr",
    "sg:city":"Sacramento",
    "sg:classifiers":[
        {
            "category":"Professional",
            "type":"Services"
        }
    ],
    "sg:phone":"+1 916 418 3311",
    "sg:postcode":"95833",
    "sg:province":"CA",
    "sg:tags":[
        "establishment"
    ],
    "wof:name":"R F Mattei & Assoc Inc",
    "wof:placetype":"venue"
},
  "geometry": {"coordinates":[-121.512213,38.605209],"type":"Point"}
}