{
  "type": "Feature",
  "properties": {
    "addr:full":"1641 Princeton Ave Modesto CA 95350",
    "addr:housenumber":"1641",
    "addr:postcode":"ca 95350",
    "addr:street":"Princeton Ave",
    "iso:country":"US",
    "sg:address":"1641 Princeton Ave",
    "sg:city":"Modesto",
    "sg:classifiers":[
        {
            "category":"Manufacturing",
            "subcategory":"Signs",
            "type":"Manufacturing & Wholesale Goods"
        }
    ],
    "sg:phone":"+1 209 526 4599",
    "sg:postcode":"95350",
    "sg:province":"CA",
    "sg:tags":[
        "specialty",
        "mfg"
    ],
    "wof:name":"Sign Source",
    "wof:placetype":"venue"
},
  "geometry": {"coordinates":[-121.02119,37.656937],"type":"Point"}
}