{
  "type": "Feature",
  "properties": {
    "iso:country":"US",
    "sg:address":"6317 Ferguson Dr",
    "sg:city":"Los Angeles",
    "sg:classifiers":[
        {
            "category":"Freight",
            "type":"Transportation"
        }
    ],
    "sg:phone":"+1 323 720 9652",
    "sg:postcode":"90022",
    "sg:province":"CA",
    "sg:tags":[
        "operator",
        "trucking"
    ],
    "wof:name":"E Leon & Son Trucking Co",
    "wof:placetype":"venue"
},
  "geometry": {"coordinates":[-118.131964,34.008502],"type":"Point"}
}