{
  "type": "Feature",
  "properties": {
    "addr:full":"3338 El Encanto Ct Bakersfield CA 93301",
    "addr:housenumber":"3338",
    "addr:postcode":"93301",
    "addr:street":"El Encanto Ct",
    "iso:country":"US",
    "sg:address":"3338 El Encanto Ct",
    "sg:city":"Bakersfield",
    "sg:classifiers":[
        {
            "category":"Landmark",
            "subcategory":"Tourist Information",
            "type":"Public Place"
        }
    ],
    "sg:phone":"+1 661 325 3200",
    "sg:postcode":"93301",
    "sg:province":"CA",
    "sg:tags":[
        "promoter",
        "tours-operators"
    ],
    "wof:name":"Petker Tours",
    "wof:placetype":"venue"
},
  "geometry": {"coordinates":[-119.03000400000001,35.392922],"type":"Point"}
}