{
  "type": "Feature",
  "properties": {
    "iso:country":"US",
    "sg:address":"503 Ethel Ave",
    "sg:city":"Mill Valley",
    "sg:classifiers":[
        {
            "category":"Retail",
            "subcategory":"Repair Shop",
            "type":"Services"
        }
    ],
    "sg:phone":"+1 415 383 7690",
    "sg:postcode":"94941",
    "sg:province":"CA",
    "sg:tags":[
        "repairing",
        "piano",
        "refinishing"
    ],
    "wof:name":"Larry Newhouse Piano Svc",
    "wof:placetype":"venue"
},
  "geometry": {"coordinates":[-122.538344,37.896591],"type":"Point"}
}