{
  "type": "Feature",
  "properties": {
    "iso:country":"US",
    "sg:address":"824 Carolina Street",
    "sg:city":"San Francisco",
    "sg:classifiers":[
        {
            "category":"Education",
            "subcategory":"Preschool",
            "type":"Public Place"
        },
        {
            "category":"Education",
            "subcategory":"School",
            "type":"Public Place"
        }
    ],
    "sg:phone":"+1 415 821 6639",
    "sg:postcode":"94107",
    "sg:province":"CA",
    "sg:tags":[
        "elementary"
    ],
    "wof:name":"Head Start",
    "wof:placetype":"venue"
},
  "geometry": {"coordinates":[-122.400002,37.757702],"type":"Point"}
}