{
  "type": "Feature",
  "properties": {
    "iso:country":"US",
    "sg:address":"6281 Bristol Parkway",
    "sg:city":"Culver City",
    "sg:classifiers":[
        {
            "category":"Building & Trades",
            "subcategory":"Locksmith",
            "type":"Services"
        }
    ],
    "sg:phone":"+1 310 733 3511",
    "sg:postcode":"90230",
    "sg:province":"CA",
    "sg:tags":[
        "key"
    ],
    "wof:name":"Anytime 24 Hour Locks & Locksmith",
    "wof:placetype":"venue"
},
  "geometry": {"coordinates":[-118.39124099999999,33.982603],"type":"Point"}
}