{
  "type": "Feature",
  "properties": {
    "iso:country":"US",
    "sg:address":"6610 Foothill Blvd",
    "sg:city":"Tujunga",
    "sg:classifiers":[
        {
            "category":"Autos & Motor Vehicles",
            "subcategory":"Fuel & Gas Station",
            "type":"Retail Goods"
        },
        {
            "category":"Banks & Credit Unions",
            "subcategory":"Financial Services",
            "type":"Services"
        },
        {
            "category":"Banks & Credit Unions",
            "subcategory":"Atm",
            "type":"Services"
        },
        {
            "category":"Food & Beverages",
            "subcategory":"Groceries & Convenience Stores",
            "type":"Retail Goods"
        }
    ],
    "sg:phone":"+1 818 353 9202",
    "sg:postcode":"91042",
    "sg:province":"CA",
    "sg:tags":[
        "money",
        "location",
        "order"
    ],
    "sg:website":"http://www.7-eleven.com",
    "wof:name":"7-Eleven",
    "wof:placetype":"venue"
},
  "geometry": {"coordinates":[-118.276321,34.246549],"type":"Point"}
}