{
  "type": "Feature",
  "properties": {
    "addr:full":"6600 Koll Center Pkwy Pleasanton CA 94566",
    "addr:postcode":"6600;94566",
    "addr:street":"Center Pkwy",
    "iso:country":"US",
    "sg:address":"6600 Koll Center Pkwy",
    "sg:city":"Pleasanton",
    "sg:classifiers":[
        {
            "category":"Insurance",
            "subcategory":"Insurance Agent",
            "type":"Services"
        }
    ],
    "sg:phone":"+1 925 462 8400",
    "sg:postcode":"94566",
    "sg:province":"CA",
    "sg:website":"www.graniteins.com",
    "wof:name":"Granite Professional Insurance",
    "wof:placetype":"venue"
},
  "geometry": {"coordinates":[-121.897121,37.660047],"type":"Point"}
}