{
  "type": "Feature",
  "properties": {
    "addr:full":"29414 Roadside Dr Agoura Hills CA 91301",
    "addr:postcode":"29414;91301",
    "addr:street":"Roadside Dr",
    "iso:country":"US",
    "sg:address":"29414 Roadside Dr",
    "sg:city":"Agoura Hills",
    "sg:classifiers":[
        {
            "category":"Recreation",
            "subcategory":"Amusement Park",
            "type":"Entertainment"
        },
        {
            "category":"Shopping",
            "subcategory":"Bicycles & Sporting Goods",
            "type":"Retail Goods"
        }
    ],
    "sg:phone":"+1 805 494 3963",
    "sg:postcode":"91301",
    "sg:province":"CA",
    "wof:name":"Fence Factory",
    "wof:placetype":"venue"
},
  "geometry": {"coordinates":[-118.76300000000001,34.145901],"type":"Point"}
}