{
  "type": "Feature",
  "properties": {
    "addr:full":"2655 Camino Del Rio N San Diego CA 92108",
    "addr:housenumber":"2655",
    "addr:postcode":"92108",
    "addr:street":"Camino Del Rio N",
    "iso:country":"US",
    "sg:address":"2655 Camino Del Rio N",
    "sg:city":"San Diego",
    "sg:classifiers":[
        {
            "category":"Real Estate",
            "subcategory":"Real Estate Services",
            "type":"Services"
        }
    ],
    "sg:phone":"+1 619 688 2678",
    "sg:postcode":"92108",
    "sg:province":"CA",
    "wof:name":"Greene Linda",
    "wof:placetype":"venue"
},
  "geometry": {"coordinates":[-117.136186,32.772024],"type":"Point"}
}