{
  "type": "Feature",
  "properties": {
    "iso:country":"US",
    "sg:address":"3694 Hilborn Rd",
    "sg:city":"Fairfield",
    "sg:classifiers":[
        {
            "category":"Health Services",
            "subcategory":"Dentist",
            "type":"Services"
        }
    ],
    "sg:phone":"+1 707 422 2190",
    "sg:postcode":"94534",
    "sg:province":"CA",
    "sg:tags":[
        "dentists-orthodontists"
    ],
    "wof:name":"Anderson, Robert W DDS MSD",
    "wof:placetype":"venue"
},
  "geometry": {"coordinates":[-122.03636299999999,38.294873],"type":"Point"}
}