{
  "type": "Feature",
  "properties": {
    "iso:country":"US",
    "sg:address":"2401 Preisker Ln",
    "sg:city":"Santa Maria",
    "sg:classifiers":[
        {
            "category":"Professional",
            "type":"Services"
        }
    ],
    "sg:phone":"+1 805 928 4824",
    "sg:postcode":"93458",
    "sg:province":"CA",
    "wof:name":"Thayer Services",
    "wof:placetype":"venue"
},
  "geometry": {"coordinates":[-120.435391,34.985949],"type":"Point"}
}