{
  "type": "Feature",
  "properties": {
    "iso:country":"US",
    "sg:address":"486 E Campbell Avenue",
    "sg:city":"Campbell",
    "sg:classifiers":[
        {
            "category":"Health Services",
            "subcategory":"Dentist",
            "type":"Services"
        }
    ],
    "sg:phone":"+1 408 374 9457",
    "sg:postcode":"95008",
    "sg:province":"CA",
    "wof:name":"Young Namching Jennifer",
    "wof:placetype":"venue"
},
  "geometry": {"coordinates":[-121.94130800000001,37.287056],"type":"Point"}
}