{
  "type": "Feature",
  "properties": {
    "addr:full":"9520 Garden Grove Blvd Ste 9 Garden Grove CA 92844",
    "addr:housenumber":"9520",
    "addr:postcode":"92844",
    "addr:street":"Garden Grove Blvd Ste 9",
    "iso:country":"US",
    "sg:address":"9520 Garden Grove Blvd Ste 9",
    "sg:city":"Garden Grove",
    "sg:classifiers":[
        {
            "category":"Restaurant",
            "type":"Food & Drink"
        }
    ],
    "sg:phone":"+1 714 636 5599",
    "sg:postcode":"92844",
    "sg:province":"CA",
    "sg:tags":[
        "korean"
    ],
    "wof:name":"BCD Tofu House Restaurant",
    "wof:placetype":"venue"
},
  "geometry": {"coordinates":[-117.966426,33.773517],"type":"Point"}
}