{
  "type": "Feature",
  "properties": {
    "addr:full":"3680 Wilshire Blvd Los Angeles CA 90010",
    "addr:housenumber":"3680",
    "addr:postcode":"90010",
    "addr:street":"Wilshire Blvd",
    "iso:country":"US",
    "sg:address":"3680 Wilshire Blvd",
    "sg:city":"Los Angeles",
    "sg:classifiers":[
        {
            "category":"Ice Cream",
            "type":"Food & Drink"
        }
    ],
    "sg:phone":"+1 213 382 7153",
    "sg:postcode":"90010",
    "sg:province":"CA",
    "sg:tags":[
        "frozen",
        "yogurt"
    ],
    "wof:name":"Yogurt Factory Cafe",
    "wof:placetype":"venue"
},
  "geometry": {"coordinates":[-118.305931,34.061706],"type":"Point"}
}