{
  "type": "Feature",
  "properties": {
    "addr:full":"38 Front St San Rafael CA 94901",
    "addr:housenumber":"38",
    "addr:postcode":"94901",
    "addr:street":"Front St",
    "iso:country":"US",
    "sg:address":"38 Front St",
    "sg:city":"San Rafael",
    "sg:classifiers":[
        {
            "category":"Professional",
            "subcategory":"Detective & Security Services",
            "type":"Services"
        }
    ],
    "sg:phone":"+1 415 258 0444",
    "sg:postcode":"94901",
    "sg:province":"CA",
    "sg:tags":[
        "investigator"
    ],
    "wof:name":"Infotech Investigation Svc",
    "wof:placetype":"venue"
},
  "geometry": {"coordinates":[-122.510807,37.964395],"type":"Point"}
}