{
  "type": "Feature",
  "properties": {
    "iso:country":"US",
    "sg:address":"540 Silver Avenue",
    "sg:city":"San Francisco",
    "sg:classifiers":[
        {
            "category":"Retail",
            "subcategory":"Laundry & Dry Cleaning",
            "type":"Services"
        }
    ],
    "sg:phone":"+1 415 587 6464",
    "sg:postcode":"94112",
    "sg:province":"CA",
    "wof:name":"Apollo Cleaners",
    "wof:placetype":"venue"
},
  "geometry": {"coordinates":[-122.42600299999999,37.7286],"type":"Point"}
}