{
  "type": "Feature",
  "properties": {
    "addr:full":"460 N Imperial Ave El Centro CA 92243",
    "addr:housenumber":"460",
    "addr:postcode":"92243",
    "addr:street":"N Imperial Ave",
    "iso:country":"US",
    "sg:address":"460 N Imperial Ave",
    "sg:city":"El Centro",
    "sg:classifiers":[
        {
            "category":"Personal",
            "subcategory":"Beauty Salon",
            "type":"Services"
        }
    ],
    "sg:phone":"+1 760 352 4860",
    "sg:postcode":"92243",
    "sg:province":"CA",
    "wof:name":"Carolyn's House Of Styles",
    "wof:placetype":"venue"
},
  "geometry": {"coordinates":[-115.56994,32.79501],"type":"Point"}
}