{
  "type": "Feature",
  "properties": {
    "addr:full":"760 N Euclid St Anaheim CA 92801",
    "addr:housenumber":"760",
    "addr:postcode":"92801",
    "addr:street":"N Euclid St",
    "iso:country":"US",
    "sg:address":"760 N Euclid St",
    "sg:city":"Anaheim",
    "sg:classifiers":[
        {
            "category":"Autos & Motor Vehicles",
            "subcategory":"Automobile Sales",
            "type":"Retail Goods"
        }
    ],
    "sg:phone":"+1 949 235 3417",
    "sg:postcode":"92801",
    "sg:province":"CA",
    "sg:tags":[
        "used"
    ],
    "wof:name":"Orange Coast Autobrokers",
    "wof:placetype":"venue"
},
  "geometry": {"coordinates":[-117.94154,33.84223],"type":"Point"}
}