{
  "type": "Feature",
  "properties": {
    "addr:full":"1221 Palomares Ct Fallbrook CA 92028",
    "addr:housenumber":"1221",
    "addr:postcode":"92028",
    "addr:street":"Palomares Ct",
    "iso:country":"US",
    "sg:address":"1221 Palomares Ct",
    "sg:city":"Fallbrook",
    "sg:classifiers":[
        {
            "category":"Real Estate",
            "subcategory":"Real Estate Agent",
            "type":"Services"
        }
    ],
    "sg:phone":"+1 760 723 9452",
    "sg:postcode":"92028",
    "sg:province":"CA",
    "sg:tags":[
        "management"
    ],
    "wof:name":"S & E Management Svc",
    "wof:placetype":"venue"
},
  "geometry": {"coordinates":[-117.232556,33.357833],"type":"Point"}
}