{
  "type": "Feature",
  "properties": {
    "iso:country":"US",
    "sg:address":"231 S 8th St",
    "sg:city":"Dixon",
    "sg:classifiers":[
        {
            "category":"Education",
            "subcategory":"Special Training",
            "type":"Public Place"
        }
    ],
    "sg:phone":"+1 707 678 1660",
    "sg:postcode":"95620",
    "sg:province":"CA",
    "sg:tags":[
        "instruction",
        "driving"
    ],
    "wof:name":"Quality Driving School",
    "wof:placetype":"venue"
},
  "geometry": {"coordinates":[-121.813666,38.442677],"type":"Point"}
}