{
  "type": "Feature",
  "properties": {
    "iso:country":"US",
    "sg:address":"26810 Ynez Ct",
    "sg:city":"Temecula",
    "sg:classifiers":[
        {
            "category":"Home & Garden",
            "subcategory":"Household Appliances",
            "type":"Retail Goods"
        }
    ],
    "sg:phone":"+1 951 679 5055",
    "sg:postcode":"92591",
    "sg:province":"CA",
    "wof:name":"Maytag Home Appliance Ctr",
    "wof:placetype":"venue"
},
  "geometry": {"coordinates":[-117.14986500000001,33.510937],"type":"Point"}
}