{
  "type": "Feature",
  "properties": {
    "addr:full":"10 Faraday Irvine CA 92618",
    "addr:housenumber":"10",
    "addr:postcode":"92618",
    "addr:street":"Faraday",
    "iso:country":"US",
    "sg:address":"10 Faraday",
    "sg:city":"Irvine",
    "sg:classifiers":[
        {
            "category":"Shopping",
            "subcategory":"Mobile Phones",
            "type":"Retail Goods"
        }
    ],
    "sg:phone":"+1 949 273 5010",
    "sg:postcode":"92618",
    "sg:province":"CA",
    "wof:name":"Power Wireless Systems",
    "wof:placetype":"venue"
},
  "geometry": {"coordinates":[-117.720893,33.639914],"type":"Point"}
}