{
  "type": "Feature",
  "properties": {
    "addr:full":"11767 Rd 27 Madera CA 93637",
    "addr:housenumber":"11767",
    "addr:postcode":"93637",
    "addr:street":"Rd 27",
    "iso:country":"US",
    "sg:address":"11767 Rd 27",
    "sg:city":"Madera",
    "sg:classifiers":[
        {
            "category":"Manufacturing",
            "subcategory":"Food",
            "type":"Manufacturing & Wholesale Goods"
        }
    ],
    "sg:phone":"+1 559 299 7258",
    "sg:postcode":"93637",
    "sg:province":"CA",
    "sg:tags":[
        "dehydrating"
    ],
    "sg:website":"www.reginagrapejuice.com",
    "wof:name":"Lamanuzzi & Pantaleo Cold Stge",
    "wof:placetype":"venue"
},
  "geometry": {"coordinates":[-120.055949,36.919981],"type":"Point"}
}