{
  "type": "Feature",
  "properties": {
    "iso:country":"US",
    "sg:address":"8030 Mango Ave",
    "sg:city":"Fontana",
    "sg:classifiers":[
        {
            "category":"Retail",
            "subcategory":"Funeral Services",
            "type":"Services"
        }
    ],
    "sg:phone":"+1 909 822 2285",
    "sg:postcode":"92336",
    "sg:province":"CA",
    "sg:tags":[
        "establishment"
    ],
    "wof:name":"Dickey Mortuary",
    "wof:placetype":"venue"
},
  "geometry": {"coordinates":[-117.431543,34.10766],"type":"Point"}
}