{
  "type": "Feature",
  "properties": {
    "iso:country":"US",
    "sg:address":"8500 Beverly Boulevard",
    "sg:city":"Los Angeles",
    "sg:classifiers":[
        {
            "category":"Shopping",
            "subcategory":"Beauty & Cosmetics",
            "type":"Retail Goods"
        }
    ],
    "sg:phone":"+1 310 855 9655",
    "sg:postcode":"90048",
    "sg:province":"CA",
    "sg:tags":[
        "supply"
    ],
    "wof:name":"Maru Cosmetics",
    "wof:placetype":"venue"
},
  "geometry": {"coordinates":[-118.3766,34.076041],"type":"Point"}
}