{
  "type": "Feature",
  "properties": {
    "iso:country":"US",
    "sg:address":"2520 Avalon Dr",
    "sg:city":"Sacramento",
    "sg:classifiers":[
        {
            "category":"Arts & Performance",
            "subcategory":"Theater",
            "type":"Entertainment"
        }
    ],
    "sg:phone":"+1 916 482 6787",
    "sg:postcode":"95821",
    "sg:province":"CA",
    "sg:tags":[
        "magician"
    ],
    "wof:name":"Wizardworks Magical",
    "wof:placetype":"venue"
},
  "geometry": {"coordinates":[-121.368857,38.611739],"type":"Point"}
}