{
  "type": "Feature",
  "properties": {
    "iso:country":"US",
    "sg:address":"439 S Highland Ave",
    "sg:city":"Los Angeles",
    "sg:classifiers":[
        {
            "category":"Wholesale",
            "subcategory":"Durable Goods & Equipment",
            "type":"Manufacturing & Wholesale Goods"
        }
    ],
    "sg:phone":"+1 323 939 8863",
    "sg:postcode":"90036",
    "sg:province":"CA",
    "wof:name":"Epicure Music Inc",
    "wof:placetype":"venue"
},
  "geometry": {"coordinates":[-118.338545,34.065304],"type":"Point"}
}