{
  "type": "Feature",
  "properties": {
    "iso:country":"US",
    "sg:address":"3682 Katella Ave # 2",
    "sg:city":"Los Alamitos",
    "sg:classifiers":[
        {
            "category":"Health Services",
            "subcategory":"Doctor",
            "type":"Services"
        }
    ],
    "sg:phone":"+1 562 596 1629",
    "sg:postcode":"90720",
    "sg:province":"CA",
    "wof:name":"Zinkan Richard E MD",
    "wof:placetype":"venue"
},
  "geometry": {"coordinates":[-118.069,33.803001],"type":"Point"}
}