{
  "type": "Feature",
  "properties": {
    "iso:country":"US",
    "sg:address":"2525 Q St",
    "sg:city":"Rio Linda",
    "sg:classifiers":[
        {
            "category":"Wholesale",
            "subcategory":"Electrical",
            "type":"Manufacturing & Wholesale Goods"
        }
    ],
    "sg:phone":"+1 916 921 9174",
    "sg:postcode":"95673",
    "sg:province":"CA",
    "sg:tags":[
        "fire",
        "equipment",
        "protection"
    ],
    "sg:website":"www.aafp-inc.com",
    "wof:name":"American Automatic Fire Protec",
    "wof:placetype":"venue"
},
  "geometry": {"coordinates":[-121.40822,38.69792],"type":"Point"}
}