{
  "type": "Feature",
  "properties": {
    "addr:full":"378 68th St San Diego CA 92114",
    "addr:housenumber":"378",
    "addr:postcode":"92114",
    "addr:street":"68Th St",
    "iso:country":"US",
    "sg:address":"378 68th St",
    "sg:city":"San Diego",
    "sg:classifiers":[
        {
            "category":"Retail",
            "subcategory":"Repair Shop",
            "type":"Services"
        }
    ],
    "sg:phone":"+1 619 262 9966",
    "sg:postcode":"92114",
    "sg:province":"CA",
    "sg:tags":[
        "bathtub",
        "sink",
        "refinishing"
    ],
    "wof:name":"Lazaro's Bathtub Refinishing",
    "wof:placetype":"venue"
},
  "geometry": {"coordinates":[-117.051137,32.707316],"type":"Point"}
}