{
  "type": "Feature",
  "properties": {
    "iso:country":"US",
    "sg:address":"730 Park Center Dr",
    "sg:city":"Santa Ana",
    "sg:classifiers":[
        {
            "category":"Utilities",
            "subcategory":"Telephone",
            "type":"Services"
        }
    ],
    "sg:phone":"+1 714 210 3771",
    "sg:postcode":"92705",
    "sg:province":"CA",
    "sg:tags":[
        "communications"
    ],
    "wof:name":"Kwest 4",
    "wof:placetype":"venue"
},
  "geometry": {"coordinates":[-117.836865,33.752697],"type":"Point"}
}