{
  "type": "Feature",
  "properties": {
    "iso:country":"US",
    "sg:address":"2420 Wilshire Blvd",
    "sg:city":"Santa Monica",
    "sg:classifiers":[
        {
            "category":"Retail",
            "subcategory":"Laundry & Dry Cleaning",
            "type":"Services"
        }
    ],
    "sg:phone":"+1 310 828 1893",
    "sg:postcode":"90403",
    "sg:province":"CA",
    "sg:tags":[
        "cleaners"
    ],
    "wof:name":"Wilshire Cleaners",
    "wof:placetype":"venue"
},
  "geometry": {"coordinates":[-118.479304,34.034348],"type":"Point"}
}