{
  "type": "Feature",
  "properties": {
    "iso:country":"US",
    "sg:address":"4212 N Pershing Ave",
    "sg:city":"Stockton",
    "sg:classifiers":[
        {
            "category":"Organizations",
            "subcategory":"Religious Organization",
            "type":"Services"
        }
    ],
    "sg:phone":"+1 209 474 6320",
    "sg:postcode":"95207",
    "sg:province":"CA",
    "sg:tags":[
        "church"
    ],
    "wof:name":"Love Fellowship Baptist Church",
    "wof:placetype":"venue"
},
  "geometry": {"coordinates":[-121.32066399999999,37.986517],"type":"Point"}
}