{
  "type": "Feature",
  "properties": {
    "addr:full":"940 Bangor St San Diego CA 92106",
    "addr:housenumber":"940",
    "addr:postcode":"92106",
    "addr:street":"Bangor St",
    "iso:country":"US",
    "sg:address":"940 Bangor St",
    "sg:city":"San Diego",
    "sg:classifiers":[
        {
            "category":"Professional",
            "type":"Services"
        }
    ],
    "sg:phone":"+1 619 222 9323",
    "sg:postcode":"92106",
    "sg:province":"CA",
    "wof:name":"Conrad Schaefer",
    "wof:placetype":"venue"
},
  "geometry": {"coordinates":[-117.239006,32.721022],"type":"Point"}
}