{
  "type": "Feature",
  "properties": {
    "iso:country":"US",
    "sg:address":"10866 Wilshire Blvd",
    "sg:city":"Los Angeles",
    "sg:classifiers":[
        {
            "category":"Banks & Credit Unions",
            "subcategory":"Investment Brokerage",
            "type":"Services"
        }
    ],
    "sg:phone":"+1 310 475 7073",
    "sg:postcode":"90024",
    "sg:province":"CA",
    "sg:tags":[
        "advisory",
        "financial"
    ],
    "wof:name":"AMI Asset Management Corp",
    "wof:placetype":"venue"
},
  "geometry": {"coordinates":[-118.44056,34.059692],"type":"Point"}
}