{
  "type": "Feature",
  "properties": {
    "addr:full":"25 Fulton Ave Pasadena CA 91107",
    "addr:housenumber":"25",
    "addr:postcode":"91107",
    "addr:street":"Fulton Ave",
    "iso:country":"US",
    "sg:address":"25 Fulton Ave",
    "sg:city":"Pasadena",
    "sg:classifiers":[
        {
            "category":"Retail",
            "subcategory":"Veterinary Services",
            "type":"Services"
        },
        {
            "category":"Retail",
            "subcategory":"Pet Boarding",
            "type":"Services"
        }
    ],
    "sg:phone":"+1 626 795 4353",
    "sg:postcode":"91107",
    "sg:province":"CA",
    "sg:tags":[
        "veterinarian",
        "boarding/pet",
        "sitting"
    ],
    "wof:name":"Willis Richard A DVM",
    "wof:placetype":"venue"
},
  "geometry": {"coordinates":[-118.075996,34.1465],"type":"Point"}
}