{
  "type": "Feature",
  "properties": {
    "addr:full":"368 Kanan Rd Oak Park CA 91377",
    "addr:housenumber":"368",
    "addr:postcode":"91377",
    "addr:street":"Kanan Rd",
    "iso:country":"US",
    "sg:address":"368 Kanan Rd",
    "sg:city":"Oak Park",
    "sg:classifiers":[
        {
            "category":"Health Services",
            "subcategory":"Dentist",
            "type":"Services"
        }
    ],
    "sg:phone":"+1 818 889 5440",
    "sg:postcode":"91377",
    "sg:province":"CA",
    "sg:tags":[
        "pediatric"
    ],
    "sg:website":"www.oakparkdentistryforchildren....",
    "wof:name":"Oak Park Dentistry For Children",
    "wof:placetype":"venue"
},
  "geometry": {"coordinates":[-118.759542,34.176143],"type":"Point"}
}