{
  "type": "Feature",
  "properties": {
    "addr:full":"707 E Sepulveda Blvd Carson CA 90745",
    "addr:housenumber":"707",
    "addr:postcode":"90745",
    "addr:street":"E Sepulveda Blvd",
    "iso:country":"US",
    "sg:address":"707 E Sepulveda Blvd",
    "sg:city":"Carson",
    "sg:classifiers":[
        {
            "category":"Freight",
            "type":"Transportation"
        }
    ],
    "sg:phone":"+1 310 522 0650",
    "sg:postcode":"90745",
    "sg:province":"CA",
    "wof:name":"Intermodal Bridge Services",
    "wof:placetype":"venue"
},
  "geometry": {"coordinates":[-118.26026,33.808401],"type":"Point"}
}