{
  "type": "Feature",
  "properties": {
    "addr:full":"22704 Ventura Blvd Woodland Hills CA 91364",
    "addr:housenumber":"22704",
    "addr:postcode":"91364",
    "addr:street":"Ventura Blvd",
    "iso:country":"US",
    "sg:address":"22704 Ventura Blvd",
    "sg:city":"Woodland Hills",
    "sg:classifiers":[
        {
            "category":"Building & Trades",
            "subcategory":"Landscaping Services",
            "type":"Services"
        }
    ],
    "sg:phone":"+1 818 704 6232",
    "sg:postcode":"91364",
    "sg:province":"CA",
    "sg:tags":[
        "lawn",
        "maintenance",
        "grounds"
    ],
    "wof:name":"Schmitz Landscape Maintenance",
    "wof:placetype":"venue"
},
  "geometry": {"coordinates":[-118.623188,34.165995],"type":"Point"}
}