{
  "type": "Feature",
  "properties": {
    "iso:country":"US",
    "sg:address":"1600 School St",
    "sg:city":"Moraga",
    "sg:classifiers":[
        {
            "category":"Banks & Credit Unions",
            "subcategory":"Investment Brokerage",
            "type":"Services"
        }
    ],
    "sg:phone":"+1 925 376 1815",
    "sg:postcode":"94556",
    "sg:province":"CA",
    "sg:tags":[
        "management"
    ],
    "wof:name":"Garland Investment Mgmt",
    "wof:placetype":"venue"
},
  "geometry": {"coordinates":[-122.132477,37.833172],"type":"Point"}
}