{
  "type": "Feature",
  "properties": {
    "addr:full":"2132 Pine St Ceres CA 95307",
    "addr:housenumber":"2132",
    "addr:postcode":"95307",
    "addr:street":"Pine St",
    "iso:country":"US",
    "sg:address":"2132 Pine St",
    "sg:city":"Ceres",
    "sg:classifiers":[
        {
            "category":"Personal",
            "type":"Services"
        }
    ],
    "sg:phone":"+1 209 538 3811",
    "sg:postcode":"95307",
    "sg:province":"CA",
    "sg:tags":[
        "towing"
    ],
    "wof:name":"Craig's Towing",
    "wof:placetype":"venue"
},
  "geometry": {"coordinates":[-120.95521599999999,37.586092],"type":"Point"}
}