{
  "type": "Feature",
  "properties": {
    "addr:full":"1098 S 6th St San Jose CA 95112",
    "addr:housenumber":"1098",
    "addr:postcode":"95112",
    "addr:street":"S 6Th St",
    "iso:country":"US",
    "sg:address":"1098 S 6th St",
    "sg:city":"San Jose",
    "sg:classifiers":[
        {
            "category":"Home & Garden",
            "subcategory":"Carpets & Floor Coverings",
            "type":"Retail Goods"
        }
    ],
    "sg:phone":"+1 408 297 0420",
    "sg:postcode":"95112",
    "sg:province":"CA",
    "sg:tags":[
        "material"
    ],
    "sg:website":"www.finerfloors.com",
    "wof:name":"Finer Floor Coverings Inc",
    "wof:placetype":"venue"
},
  "geometry": {"coordinates":[-121.874078,37.323699],"type":"Point"}
}