{
  "type": "Feature",
  "properties": {
    "iso:country":"US",
    "sg:address":"2400 Wyandotte Street Suite A",
    "sg:city":"Mountain View",
    "sg:classifiers":[
        {
            "category":"Education",
            "subcategory":"University",
            "type":"Public Place"
        }
    ],
    "sg:phone":"+1 650 938 2478",
    "sg:postcode":"94043",
    "sg:province":"CA",
    "sg:tags":[
        "college"
    ],
    "wof:name":"Chinese Graduate School of Theology",
    "wof:placetype":"venue"
},
  "geometry": {"coordinates":[-122.07971000000001,37.404629],"type":"Point"}
}