{
  "type": "Feature",
  "properties": {
    "addr:full":"111 Independence Dr Menlo Park CA 94025",
    "addr:housenumber":"111",
    "addr:postcode":"94025",
    "addr:street":"Independence Dr",
    "iso:country":"US",
    "sg:address":"111 Independence Dr",
    "sg:city":"Menlo Park",
    "sg:classifiers":[
        {
            "category":"Professional",
            "subcategory":"Lawyer & Legal Services",
            "type":"Services"
        },
        {
            "category":"Professional",
            "subcategory":"Business Services",
            "type":"Services"
        }
    ],
    "sg:phone":"+1 650 462 8200",
    "sg:postcode":"94025",
    "sg:province":"CA",
    "sg:tags":[
        "attorney",
        "bureau"
    ],
    "sg:website":"www.dtiglobal.com",
    "wof:name":"Document Technologies L L C",
    "wof:placetype":"venue"
},
  "geometry": {"coordinates":[-122.17773200000001,37.48355],"type":"Point"}
}