{
  "type": "Feature",
  "properties": {
    "iso:country":"US",
    "sg:address":"1925 Delaware St",
    "sg:city":"Berkeley",
    "sg:classifiers":[
        {
            "category":"Education",
            "subcategory":"Special Training",
            "type":"Public Place"
        }
    ],
    "sg:phone":"+1 510 841 4159",
    "sg:postcode":"94709",
    "sg:province":"CA",
    "sg:tags":[
        "instruction",
        "music"
    ],
    "wof:name":"Piano Lessons-Harry Likas",
    "wof:placetype":"venue"
},
  "geometry": {"coordinates":[-122.27113799999999,37.874562],"type":"Point"}
}