{
  "type": "Feature",
  "properties": {
    "iso:country":"US",
    "sg:address":"1825 Willowside Rd",
    "sg:city":"Santa Rosa",
    "sg:classifiers":[
        {
            "category":"Social Services",
            "type":"Services"
        }
    ],
    "sg:phone":"+1 707 544 3309",
    "sg:postcode":"95401",
    "sg:province":"CA",
    "sg:tags":[
        "organization",
        "welfare"
    ],
    "wof:name":"YMCA",
    "wof:placetype":"venue"
},
  "geometry": {"coordinates":[-122.806898,38.467032],"type":"Point"}
}