{
  "type": "Feature",
  "properties": {
    "iso:country":"US",
    "sg:address":"7816 Mountain View Rd",
    "sg:city":"Bakersfield",
    "sg:classifiers":[
        {
            "category":"Building & Trades",
            "subcategory":"Landscaping Services",
            "type":"Services"
        }
    ],
    "sg:phone":"+1 661 845 4368",
    "sg:postcode":"93307",
    "sg:province":"CA",
    "wof:name":"Landscape Gardening",
    "wof:placetype":"venue"
},
  "geometry": {"coordinates":[-118.916901,35.281619],"type":"Point"}
}