{
  "type": "Feature",
  "properties": {
    "addr:full":"2400 Historic Decatur Rd San Diego CA 92101",
    "addr:housenumber":"2400",
    "addr:postcode":"92101",
    "addr:street":"Historic Decatur Rd",
    "iso:country":"US",
    "sg:address":"2400 Historic Decatur Rd",
    "sg:city":"San Diego",
    "sg:classifiers":[
        {
            "category":"Restaurant",
            "type":"Food & Drink"
        },
        {
            "category":"Food & Beverages",
            "subcategory":"Bakery",
            "type":"Retail Goods"
        },
        {
            "category":"Food & Beverages",
            "subcategory":"Groceries & Convenience Stores",
            "type":"Retail Goods"
        }
    ],
    "sg:phone":"+1 619 226 6254",
    "sg:postcode":"92101",
    "sg:province":"CA",
    "sg:tags":[
        "soup",
        "american",
        "sandwich",
        "new"
    ],
    "sg:website":"www.tendergreensfood.com",
    "wof:name":"Tender Greens",
    "wof:placetype":"venue"
},
  "geometry": {"coordinates":[-117.219731,32.730034],"type":"Point"}
}