{
  "type": "Feature",
  "properties": {
    "iso:country":"US",
    "sg:address":"15604 Delhi Ct",
    "sg:city":"La Mirada",
    "sg:classifiers":[
        {
            "category":"Real Estate",
            "subcategory":"Real Estate Operator",
            "type":"Services"
        }
    ],
    "sg:phone":"+1 714 670 7010",
    "sg:postcode":"90638",
    "sg:province":"CA",
    "sg:tags":[
        "building",
        "apartment"
    ],
    "wof:name":"Bright Apts",
    "wof:placetype":"venue"
},
  "geometry": {"coordinates":[-117.997529,33.894118],"type":"Point"}
}