{
  "type": "Feature",
  "properties": {
    "addr:full":"18041 Devonshire St Northridge CA 91325",
    "addr:housenumber":"18041",
    "addr:postcode":"91325",
    "addr:street":"Devonshire St",
    "iso:country":"US",
    "sg:address":"18041 Devonshire St",
    "sg:city":"Northridge",
    "sg:classifiers":[
        {
            "category":"Communications",
            "subcategory":"Film & Video Production",
            "type":"Services"
        }
    ],
    "sg:phone":"+1 818 363 0292",
    "sg:postcode":"91325",
    "sg:province":"CA",
    "sg:tags":[
        "motion"
    ],
    "wof:name":"Lunarsea",
    "wof:placetype":"venue"
},
  "geometry": {"coordinates":[-118.52502200000001,34.257341],"type":"Point"}
}