{
  "type": "Feature",
  "properties": {
    "iso:country":"US",
    "sg:address":"1 Thomas Moore Way",
    "sg:city":"San Francisco",
    "sg:classifiers":[
        {
            "category":"Organizations",
            "subcategory":"Membership Organization",
            "type":"Services"
        }
    ],
    "sg:phone":"+1 415 933 6038",
    "sg:postcode":"94132",
    "sg:province":"CA",
    "wof:name":"F Police Officers Stress",
    "wof:placetype":"venue"
},
  "geometry": {"coordinates":[-122.473259,37.711636],"type":"Point"}
}