{
  "type": "Feature",
  "properties": {
    "iso:country":"US",
    "sg:address":"3080 Olcott St",
    "sg:city":"Santa Clara",
    "sg:classifiers":[
        {
            "category":"Professional",
            "subcategory":"Computer Services",
            "type":"Services"
        }
    ],
    "sg:phone":"+1 408 986 1517",
    "sg:postcode":"95054",
    "sg:province":"CA",
    "sg:tags":[
        "consultant",
        "designer"
    ],
    "sg:website":"www.kapsconsulting.com",
    "wof:name":"KAPS Consulting",
    "wof:placetype":"venue"
},
  "geometry": {"coordinates":[-121.967464,37.377682],"type":"Point"}
}