{
  "type": "Feature",
  "properties": {
    "addr:full":"2355 N Chain Dr Simi Valley CA 93065",
    "addr:housenumber":"2355",
    "addr:postcode":"93065",
    "addr:street":"N Chain Dr",
    "iso:country":"US",
    "sg:address":"2355 N Chain Dr",
    "sg:city":"Simi Valley",
    "sg:classifiers":[
        {
            "category":"Home & Garden",
            "subcategory":"Hardware",
            "type":"Retail Goods"
        }
    ],
    "sg:phone":"+1 818 347 6771",
    "sg:postcode":"93065",
    "sg:province":"CA",
    "sg:tags":[
        "manufacture",
        "small",
        "tool"
    ],
    "wof:name":"Gemtec Tool Company",
    "wof:placetype":"venue"
},
  "geometry": {"coordinates":[-118.793226,34.278516],"type":"Point"}
}