{
  "type": "Feature",
  "properties": {
    "iso:country":"US",
    "sg:address":"26730 Towne Centre Dr Suite 204",
    "sg:city":"Foothill Ranch",
    "sg:classifiers":[
        {
            "category":"Health Services",
            "subcategory":"Optometrist",
            "type":"Services"
        }
    ],
    "sg:phone":"+1 949 916 6428",
    "sg:postcode":"92610",
    "sg:province":"CA",
    "sg:tags":[
        "laser",
        "surgery/lasik",
        "eye",
        "ophthalmologist"
    ],
    "sg:website":"www.atlantiseyecare.com",
    "wof:name":"Atlantis Eyecare",
    "wof:placetype":"venue"
},
  "geometry": {"coordinates":[-117.66275899999999,33.673694],"type":"Point"}
}