{
  "type": "Feature",
  "properties": {
    "addr:full":"3401 Dale Rd Modesto CA 95356",
    "addr:housenumber":"3401",
    "addr:postcode":"ca 95356",
    "addr:street":"Dale Rd",
    "iso:country":"US",
    "sg:address":"3401 Dale Rd",
    "sg:city":"Modesto",
    "sg:classifiers":[
        {
            "category":"Shopping",
            "subcategory":"Department Store",
            "type":"Retail Goods"
        },
        {
            "category":"Shopping",
            "subcategory":"Beauty & Cosmetics",
            "type":"Retail Goods"
        },
        {
            "category":"Home & Garden",
            "subcategory":"Home Furnishings",
            "type":"Retail Goods"
        },
        {
            "category":"Shopping",
            "type":"Retail Goods"
        },
        {
            "category":"Shopping",
            "subcategory":"Optical Goods",
            "type":"Retail Goods"
        },
        {
            "category":"Shopping",
            "subcategory":"Catalog Store",
            "type":"Retail Goods"
        },
        {
            "category":"Professional",
            "subcategory":"Art Services",
            "type":"Services"
        },
        {
            "category":"Shopping",
            "subcategory":"Shoes",
            "type":"Retail Goods"
        },
        {
            "category":"Shopping",
            "subcategory":"Jewelry",
            "type":"Retail Goods"
        }
    ],
    "sg:phone":"+1 209 574 0710",
    "sg:postcode":"95356",
    "sg:province":"CA",
    "sg:tags":[
        "repair",
        "designer",
        "draperies",
        "vertical",
        "supply",
        "blinds-venetian",
        "jeweler",
        "equipment",
        "window",
        "interior",
        "treatment",
        "housewares",
        "curtain",
        "showroom",
        "eyeglass",
        "decorator",
        "merchandise"
    ],
    "wof:name":"JCPenney Optical Center",
    "wof:placetype":"venue"
},
  "geometry": {"coordinates":[-121.04995,37.688171],"type":"Point"}
}