{
  "type": "Feature",
  "properties": {
    "addr:full":"350 Cypress St Fort Bragg CA 95437",
    "addr:housenumber":"350",
    "addr:postcode":"95437",
    "addr:street":"Cypress St",
    "iso:country":"US",
    "sg:address":"350 Cypress St",
    "sg:city":"Fort Bragg",
    "sg:classifiers":[
        {
            "category":"Building & Trades",
            "subcategory":"Landscaping Services",
            "type":"Services"
        }
    ],
    "sg:phone":"+1 707 964 8539",
    "sg:postcode":"95437",
    "sg:province":"CA",
    "sg:tags":[
        "lawn",
        "maintenance",
        "grounds"
    ],
    "wof:name":"Cypress Landscape Svc",
    "wof:placetype":"venue"
},
  "geometry": {"coordinates":[-123.802915,39.432575],"type":"Point"}
}