{
  "type": "Feature",
  "properties": {
    "iso:country":"US",
    "sg:address":"2000 Hearst Ave",
    "sg:city":"Berkeley",
    "sg:classifiers":[
        {
            "category":"Health Services",
            "subcategory":"Doctor",
            "type":"Services"
        },
        {
            "category":"Health Services",
            "subcategory":"Clinic",
            "type":"Services"
        }
    ],
    "sg:phone":"+1 510 981 1471",
    "sg:postcode":"94709",
    "sg:province":"CA",
    "sg:tags":[
        "psychological",
        "psychologist"
    ],
    "wof:name":"Endurance - A Sports And Psychology Center, Inc.",
    "wof:placetype":"venue"
},
  "geometry": {"coordinates":[-122.270866,37.873589],"type":"Point"}
}