{
  "type": "Feature",
  "properties": {
    "iso:country":"US",
    "sg:address":"419 N Larchmont Blvd",
    "sg:city":"Los Angeles",
    "sg:classifiers":[
        {
            "category":"Communications",
            "subcategory":"Television Station",
            "type":"Services"
        }
    ],
    "sg:phone":"+1 323 934 5005",
    "sg:postcode":"90004",
    "sg:province":"CA",
    "sg:tags":[
        "broadcasting",
        "co"
    ],
    "wof:name":"Fisher-Merlis Television Inc",
    "wof:placetype":"venue"
},
  "geometry": {"coordinates":[-118.323719,34.077315],"type":"Point"}
}