{
  "type": "Feature",
  "properties": {
    "iso:country":"US",
    "sg:address":"Keller Williams Realty 8560 W Sunset Blvd",
    "sg:city":"West Hollywood",
    "sg:classifiers":[
        {
            "category":"Real Estate",
            "subcategory":"Real Estate Agent",
            "type":"Services"
        }
    ],
    "sg:phone":"+1 310 435 7114",
    "sg:postcode":"90069",
    "sg:province":"CA",
    "sg:website":"www.victoriasilver.com",
    "wof:name":"Victoria Silver - Keller Williams",
    "wof:placetype":"venue"
},
  "geometry": {"coordinates":[-118.37796899999999,34.093003],"type":"Point"}
}