{
  "type": "Feature",
  "properties": {
    "addr:full":"443 S Catalina St Los Angeles CA 90020",
    "addr:housenumber":"443",
    "addr:postcode":"90020",
    "addr:street":"S Catalina St",
    "iso:country":"US",
    "sg:address":"443 S Catalina St",
    "sg:city":"Los Angeles",
    "sg:classifiers":[
        {
            "category":"Sports & Exercise",
            "subcategory":"Gym",
            "type":"Entertainment"
        }
    ],
    "sg:phone":"+1 213 632 2333",
    "sg:postcode":"90020",
    "sg:province":"CA",
    "wof:name":"Symmetry Fitness Professionals",
    "wof:placetype":"venue"
},
  "geometry": {"coordinates":[-118.29499800000001,34.066399],"type":"Point"}
}