{
  "type": "Feature",
  "properties": {
    "addr:full":"12758 Emelita St Valley Village CA 91607",
    "addr:postcode":"12758;91607",
    "addr:street":"Emelita St",
    "iso:country":"US",
    "sg:address":"12758 Emelita St",
    "sg:city":"Valley Village",
    "sg:classifiers":[
        {
            "category":"Personal",
            "type":"Services"
        }
    ],
    "sg:phone":"+1 800 349 5000",
    "sg:postcode":"91607",
    "sg:province":"CA",
    "sg:tags":[
        "mover"
    ],
    "sg:website":"www.AandAmovers.com",
    "wof:name":"A & A Moving Co",
    "wof:placetype":"venue"
},
  "geometry": {"coordinates":[-118.411506,34.176389],"type":"Point"}
}