{
  "type": "Feature",
  "properties": {
    "iso:country":"US",
    "sg:address":"1667 N Mountain Ave",
    "sg:city":"Upland",
    "sg:classifiers":[
        {
            "category":"Shopping",
            "subcategory":"Florist",
            "type":"Retail Goods"
        }
    ],
    "sg:phone":"+1 909 946 2841",
    "sg:postcode":"91784",
    "sg:province":"CA",
    "wof:name":"Cardin's Flowers & Gifts",
    "wof:placetype":"venue"
},
  "geometry": {"coordinates":[-117.670376,34.122006],"type":"Point"}
}