{
  "type": "Feature",
  "properties": {
    "addr:full":"20226 Avalon Blvd Carson CA 90746",
    "addr:housenumber":"20226",
    "addr:postcode":"90746",
    "addr:street":"Avalon Blvd",
    "iso:country":"US",
    "sg:address":"20226 Avalon Blvd",
    "sg:city":"Carson",
    "sg:classifiers":[
        {
            "category":"Food & Beverages",
            "subcategory":"Groceries & Convenience Stores",
            "type":"Retail Goods"
        }
    ],
    "sg:phone":"+1 310 323 5480",
    "sg:postcode":"90746",
    "sg:province":"CA",
    "sg:tags":[
        "grocer"
    ],
    "wof:name":"Best Way Super Markets",
    "wof:placetype":"venue"
},
  "geometry": {"coordinates":[-118.264999,33.848598],"type":"Point"}
}