{
  "type": "Feature",
  "properties": {
    "iso:country":"US",
    "sg:address":"24443 Willimet Way",
    "sg:city":"Hayward",
    "sg:classifiers":[
        {
            "category":"Social Services",
            "subcategory":"Adult Care",
            "type":"Services"
        }
    ],
    "sg:phone":"+1 510 887 4759",
    "sg:postcode":"94544",
    "sg:province":"CA",
    "sg:tags":[
        "home",
        "residential"
    ],
    "wof:name":"A Safe Haven Manor",
    "wof:placetype":"venue"
},
  "geometry": {"coordinates":[-122.099215,37.654161],"type":"Point"}
}