{
  "type": "Feature",
  "properties": {
    "iso:country":"US",
    "sg:address":"1747 N Hudson Ave",
    "sg:city":"Los Angeles",
    "sg:classifiers":[
        {
            "category":"Retail",
            "subcategory":"Auto Repair",
            "type":"Services"
        }
    ],
    "sg:phone":"+1 310 231 5105",
    "sg:postcode":"90028",
    "sg:province":"CA",
    "sg:tags":[
        "repairing",
        "automobile"
    ],
    "wof:name":"Advanced Car Repair",
    "wof:placetype":"venue"
},
  "geometry": {"coordinates":[-118.332277,34.102524],"type":"Point"}
}