{
  "type": "Feature",
  "properties": {
    "iso:country":"US",
    "sg:address":"935 Newhall St",
    "sg:city":"Costa Mesa",
    "sg:classifiers":[
        {
            "category":"Manufacturing",
            "subcategory":"Metals",
            "type":"Manufacturing & Wholesale Goods"
        }
    ],
    "sg:phone":"+1 714 662 1755",
    "sg:postcode":"92627",
    "sg:province":"CA",
    "sg:tags":[
        "ornamental",
        "work"
    ],
    "wof:name":"Pacific Wrought Iron",
    "wof:placetype":"venue"
},
  "geometry": {"coordinates":[-117.936925,33.634181],"type":"Point"}
}