{
  "type": "Feature",
  "properties": {
    "addr:full":"980 9th Street Sacramento CA 95814",
    "addr:housenumber":"980",
    "addr:postcode":"95814",
    "addr:street":"9Th Street",
    "iso:country":"US",
    "sg:address":"980 9th Street",
    "sg:city":"Sacramento",
    "sg:classifiers":[
        {
            "category":"Banks & Credit Unions",
            "subcategory":"Bank",
            "type":"Services"
        }
    ],
    "sg:phone":"+1 916 558 1596",
    "sg:postcode":"95814",
    "sg:province":"CA",
    "sg:tags":[
        "commercial",
        "saving"
    ],
    "wof:name":"Investor Bank & Trust",
    "wof:placetype":"venue"
},
  "geometry": {"coordinates":[-121.49464500000001,38.580976],"type":"Point"}
}