{
  "type": "Feature",
  "properties": {
    "iso:country":"US",
    "sg:address":"12881 Knott St #203",
    "sg:city":"Garden Grove",
    "sg:classifiers":[
        {
            "category":"Health Services",
            "subcategory":"Clinic",
            "type":"Services"
        }
    ],
    "sg:phone":"+1 714 897 2727",
    "sg:postcode":"92841",
    "sg:province":"CA",
    "sg:tags":[
        "medical"
    ],
    "sg:website":"www.advanscpap.com",
    "wof:name":"Advans CPAP",
    "wof:placetype":"venue"
},
  "geometry": {"coordinates":[-118.008538,33.775314],"type":"Point"}
}