{
  "type": "Feature",
  "properties": {
    "iso:country":"US",
    "sg:address":"4516 Kickapoo Ct",
    "sg:city":"San Diego",
    "sg:classifiers":[
        {
            "category":"Real Estate",
            "subcategory":"Real Estate Agent",
            "type":"Services"
        }
    ],
    "sg:phone":"+1 858 274 2345",
    "sg:postcode":"92117",
    "sg:province":"CA",
    "wof:name":"Pacific Investor Realty",
    "wof:placetype":"venue"
},
  "geometry": {"coordinates":[-117.21209899999999,32.825503],"type":"Point"}
}