{
  "type": "Feature",
  "properties": {
    "addr:full":"11809 Artesia Blvd Artesia CA 90701",
    "addr:housenumber":"11809",
    "addr:postcode":"90701",
    "addr:street":"Artesia Blvd",
    "iso:country":"US",
    "sg:address":"11809 Artesia Blvd",
    "sg:city":"Artesia",
    "sg:classifiers":[
        {
            "category":"Coffee & Tea",
            "type":"Food & Drink"
        }
    ],
    "sg:menulink":"http://www.allmenus.com/ca/downey-norwalk/117313-starbucks-coffee/menu/",
    "sg:phone":"+1 562 860 5444",
    "sg:postcode":"90701",
    "sg:province":"CA",
    "sg:tags":[
        "american"
    ],
    "wof:name":"Starbucks Coffee",
    "wof:placetype":"venue"
},
  "geometry": {"coordinates":[-118.081908,33.874032],"type":"Point"}
}