{
  "type": "Feature",
  "properties": {
    "iso:country":"US",
    "sg:address":"1778 N Milpitas Boulevard",
    "sg:city":"Milpitas",
    "sg:classifiers":[
        {
            "category":"Health Services",
            "subcategory":"Dentist",
            "type":"Services"
        }
    ],
    "sg:phone":"+1 408 263 6386",
    "sg:postcode":"95035",
    "sg:province":"CA",
    "wof:name":"Wong Wendy DDS",
    "wof:placetype":"venue"
},
  "geometry": {"coordinates":[-121.910955,37.456017],"type":"Point"}
}