{
  "type": "Feature",
  "properties": {
    "iso:country":"US",
    "sg:address":"7660 Bell Rd",
    "sg:city":"Windsor",
    "sg:classifiers":[
        {
            "category":"Personal",
            "subcategory":"Beauty Salon",
            "type":"Services"
        }
    ],
    "sg:phone":"+1 707 837 9692",
    "sg:postcode":"95492",
    "sg:province":"CA",
    "sg:tags":[
        "treatment",
        "skin"
    ],
    "wof:name":"Drhauschka Skincare Inc",
    "wof:placetype":"venue"
},
  "geometry": {"coordinates":[-122.801365,38.534955],"type":"Point"}
}