{
  "type": "Feature",
  "properties": {
    "addr:full":"17602 Sampson Ln Huntington Beach CA 92647",
    "addr:housenumber":"17602",
    "addr:postcode":"92647",
    "addr:street":"Sampson Ln",
    "iso:country":"US",
    "sg:address":"17602 Sampson Ln",
    "sg:city":"Huntington Beach",
    "sg:phone":"+1 714 848 1314",
    "sg:postcode":"92647",
    "sg:province":"CA",
    "sg:tags":[
        "product",
        "petroleum"
    ],
    "wof:name":"Pacific Fuel Resources",
    "wof:placetype":"venue"
},
  "geometry": {"coordinates":[-117.996965,33.704278],"type":"Point"}
}