{
  "type": "Feature",
  "properties": {
    "addr:full":"9351 Deering Avenue Chatsworth CA 91311",
    "addr:housenumber":"9351",
    "addr:postcode":"91311",
    "addr:street":"Deering Avenue",
    "iso:country":"US",
    "sg:address":"9351 Deering Avenue",
    "sg:city":"Chatsworth",
    "sg:classifiers":[
        {
            "category":"Professional",
            "subcategory":"Computer Services",
            "type":"Services"
        }
    ],
    "sg:phone":"+1 800 837 2298",
    "sg:postcode":"91311",
    "sg:province":"CA",
    "sg:website":"http://www.ddn.com",
    "wof:name":"DataDirect Networks",
    "wof:placetype":"venue"
},
  "geometry": {"coordinates":[-118.59615100000001,34.236357],"type":"Point"}
}