{
  "type": "Feature",
  "properties": {
    "iso:country":"US",
    "sg:address":"11900 South St Ste 105",
    "sg:city":"Cerritos",
    "sg:classifiers":[
        {
            "category":"Restaurant",
            "type":"Food & Drink"
        }
    ],
    "sg:phone":"+1 562 924 9998",
    "sg:postcode":"90703",
    "sg:province":"CA",
    "sg:tags":[
        "vietnamese"
    ],
    "sg:website":"www.pho4u.net",
    "wof:name":"Pho 4 U",
    "wof:placetype":"venue"
},
  "geometry": {"coordinates":[-118.079532,33.85791],"type":"Point"}
}