{
  "type": "Feature",
  "properties": {
    "iso:country":"US",
    "sg:address":"13373 Poway Rd",
    "sg:city":"Poway",
    "sg:classifiers":[
        {
            "category":"Health Services",
            "subcategory":"Optometrist",
            "type":"Services"
        }
    ],
    "sg:phone":"+1 858 748 0171",
    "sg:postcode":"92064",
    "sg:province":"CA",
    "wof:name":"Okamura & Decker",
    "wof:placetype":"venue"
},
  "geometry": {"coordinates":[-117.044634,32.956407],"type":"Point"}
}