{
  "type": "Feature",
  "properties": {
    "iso:country":"US",
    "sg:address":"2800 N Main St Ste 580",
    "sg:city":"Santa Ana",
    "sg:classifiers":[
        {
            "category":"Shopping",
            "subcategory":"Tobacco",
            "type":"Retail Goods"
        },
        {
            "category":"Restaurant",
            "type":"Food & Drink"
        }
    ],
    "sg:phone":"+1 714 541 5500",
    "sg:postcode":"92705",
    "sg:province":"CA",
    "sg:tags":[
        "shop"
    ],
    "wof:name":"Street Corner News",
    "wof:placetype":"venue"
},
  "geometry": {"coordinates":[-117.869246,33.776374],"type":"Point"}
}