{
  "type": "Feature",
  "properties": {
    "addr:full":"3501 W Sunflower Ave Santa Ana CA 92704",
    "addr:housenumber":"3501",
    "addr:postcode":"92704",
    "addr:street":"W Sunflower Ave",
    "iso:country":"US",
    "sg:address":"3501 W Sunflower Ave",
    "sg:city":"Santa Ana",
    "sg:classifiers":[
        {
            "category":"Shopping",
            "subcategory":"Clothing, Apparel, & Fashions",
            "type":"Retail Goods"
        }
    ],
    "sg:phone":"+1 714 546 9500",
    "sg:postcode":"92704",
    "sg:province":"CA",
    "sg:tags":[
        "department",
        "management",
        "family"
    ],
    "wof:name":"Nordstrom",
    "wof:placetype":"venue"
},
  "geometry": {"coordinates":[-117.91482499999999,33.695695],"type":"Point"}
}