{
  "type": "Feature",
  "properties": {
    "addr:full":"9220 S Harvard Blvd Los Angeles CA 90047",
    "addr:housenumber":"9220",
    "addr:postcode":"90047",
    "addr:street":"S Harvard Blvd",
    "iso:country":"US",
    "sg:address":"9220 S Harvard Blvd",
    "sg:city":"Los Angeles",
    "sg:classifiers":[
        {
            "category":"Professional",
            "type":"Services"
        }
    ],
    "sg:phone":"+1 323 755 9635",
    "sg:postcode":"90047",
    "sg:province":"CA",
    "wof:name":"Instrument of Praise Iop",
    "wof:placetype":"venue"
},
  "geometry": {"coordinates":[-118.30672300000001,33.951283],"type":"Point"}
}