{
  "type": "Feature",
  "properties": {
    "iso:country":"US",
    "sg:address":"3836 S Grand Avenue",
    "sg:city":"Los Angeles",
    "sg:classifiers":[
        {
            "category":"Insurance",
            "subcategory":"Health Insurance",
            "type":"Services"
        }
    ],
    "sg:phone":"+1 213 745 7737",
    "sg:postcode":"90037",
    "sg:province":"CA",
    "sg:tags":[
        "market"
    ],
    "wof:name":"G S America",
    "wof:placetype":"venue"
},
  "geometry": {"coordinates":[-118.279889,34.014552],"type":"Point"}
}