{
  "type": "Feature",
  "properties": {
    "iso:country":"US",
    "sg:address":"24341 El Toro Rd",
    "sg:city":"Laguna Hills",
    "sg:classifiers":[
        {
            "category":"Travel",
            "subcategory":"Hotels & Motels",
            "type":"Entertainment"
        }
    ],
    "sg:phone":"+1 949 588 0131",
    "sg:postcode":"92637",
    "sg:province":"CA",
    "wof:name":"Ayres Hotel Laguna Woods",
    "wof:placetype":"venue"
},
  "geometry": {"coordinates":[-117.72936900000001,33.610468],"type":"Point"}
}