{
  "type": "Feature",
  "properties": {
    "addr:full":"30 Tevis Pl Palo Alto CA 94301",
    "addr:housenumber":"30",
    "addr:postcode":"94301",
    "addr:street":"Tevis Pl",
    "iso:country":"US",
    "sg:address":"30 Tevis Pl",
    "sg:city":"Palo Alto",
    "sg:classifiers":[
        {
            "category":"Insurance",
            "subcategory":"Health Insurance",
            "type":"Services"
        }
    ],
    "sg:phone":"+1 650 326 7050",
    "sg:postcode":"94301",
    "sg:province":"CA",
    "sg:tags":[
        "carrier"
    ],
    "wof:name":"Erica Fund For Children",
    "wof:placetype":"venue"
},
  "geometry": {"coordinates":[-122.14359,37.450381],"type":"Point"}
}