{
  "type": "Feature",
  "properties": {
    "addr:full":"745 W Capitol Expy San Jose CA 95136",
    "addr:housenumber":"745",
    "addr:postcode":"95136",
    "addr:street":"W Capitol Expy",
    "iso:country":"US",
    "sg:address":"745 W Capitol Expy",
    "sg:city":"San Jose",
    "sg:classifiers":[
        {
            "category":"Autos & Motor Vehicles",
            "subcategory":"Automobile Sales",
            "type":"Retail Goods"
        }
    ],
    "sg:phone":"+1 408 264 4495",
    "sg:postcode":"95136",
    "sg:province":"CA",
    "sg:tags":[
        "car",
        "dealer"
    ],
    "wof:name":"Ted Stevens Car Co",
    "wof:placetype":"venue"
},
  "geometry": {"coordinates":[-121.870351,37.275348],"type":"Point"}
}