{
  "type": "Feature",
  "properties": {
    "iso:country":"US",
    "sg:address":"1853 Solano Ave",
    "sg:city":"Berkeley",
    "sg:classifiers":[
        {
            "category":"Restaurant",
            "type":"Food & Drink"
        }
    ],
    "sg:menulink":"http://www.allmenus.com/ca/berkeley/54726-zacharys-chicago-pizza/menu/",
    "sg:phone":"+1 510 525 5950",
    "sg:postcode":"94707",
    "sg:province":"CA",
    "sg:tags":[
        "american",
        "pizza"
    ],
    "wof:name":"Zachary's Chicago Pizza",
    "wof:placetype":"venue"
},
  "geometry": {"coordinates":[-122.278431,37.891282],"type":"Point"}
}