{
  "type": "Feature",
  "properties": {
    "iso:country":"US",
    "sg:address":"1 2nd St",
    "sg:city":"Salinas",
    "sg:classifiers":[
        {
            "category":"Freight",
            "type":"Transportation"
        }
    ],
    "sg:phone":"+1 831 784 0331",
    "sg:postcode":"93927",
    "sg:province":"CA",
    "sg:tags":[
        "operator",
        "local",
        "trucking"
    ],
    "wof:name":"Laines Delivery Service",
    "wof:placetype":"venue"
},
  "geometry": {"coordinates":[-121.226753,36.330109],"type":"Point"}
}