{
  "type": "Feature",
  "properties": {
    "iso:country":"US",
    "sg:address":"2128 S Atlantic Blvd",
    "sg:city":"Commerce",
    "sg:classifiers":[
        {
            "category":"Taxi",
            "type":"Transportation"
        }
    ],
    "sg:phone":"+1 323 262 9823",
    "sg:postcode":"90040",
    "sg:province":"CA",
    "wof:name":"Dia Y Noche Yellow Taxi",
    "wof:placetype":"venue"
},
  "geometry": {"coordinates":[-118.161047,34.007551],"type":"Point"}
}