{
  "type": "Feature",
  "properties": {
    "addr:full":"430 N Canal Street South San Francisco CA 94080",
    "addr:housenumber":"430",
    "addr:postcode":"94080",
    "addr:street":"N Canal Street",
    "iso:country":"US",
    "sg:address":"430 N Canal Street",
    "sg:city":"South San Francisco",
    "sg:classifiers":[
        {
            "category":"Home & Garden",
            "subcategory":"Furniture",
            "type":"Retail Goods"
        }
    ],
    "sg:phone":"+1 650 872 0182",
    "sg:postcode":"94080",
    "sg:province":"CA",
    "sg:tags":[
        "store"
    ],
    "wof:name":"Tai Nam Yang Furniture Company",
    "wof:placetype":"venue"
},
  "geometry": {"coordinates":[-122.415446,37.651235],"type":"Point"}
}