{
  "type": "Feature",
  "properties": {
    "iso:country":"US",
    "sg:address":"3760 Sonoma Blvd",
    "sg:city":"Vallejo",
    "sg:classifiers":[
        {
            "category":"Manufacturing",
            "subcategory":"Jewelry",
            "type":"Manufacturing & Wholesale Goods"
        },
        {
            "category":"Retail",
            "subcategory":"Repair Shop",
            "type":"Services"
        }
    ],
    "sg:phone":"+1 707 554 3080",
    "sg:postcode":"94589",
    "sg:province":"CA",
    "sg:tags":[
        "repairing",
        "clock"
    ],
    "wof:name":"Mr Bling Bling Jewelry",
    "wof:placetype":"venue"
},
  "geometry": {"coordinates":[-122.25532800000001,38.125417],"type":"Point"}
}