{
  "type": "Feature",
  "properties": {
    "addr:full":"13205 Philadelphia St Whittier CA 90601",
    "addr:housenumber":"13205",
    "addr:postcode":"90601",
    "addr:street":"Philadelphia St",
    "iso:country":"US",
    "sg:address":"13205 Philadelphia St",
    "sg:city":"Whittier",
    "sg:classifiers":[
        {
            "category":"Organizations",
            "subcategory":"Religious Organization",
            "type":"Services"
        }
    ],
    "sg:phone":"+1 562 698 9805",
    "sg:postcode":"90601",
    "sg:province":"CA",
    "sg:tags":[
        "church"
    ],
    "sg:website":"www.firstfriendswhittier.org",
    "wof:name":"First Friends Church-Whittier",
    "wof:placetype":"venue"
},
  "geometry": {"coordinates":[-118.034446,33.979164],"type":"Point"}
}