{
  "type": "Feature",
  "properties": {
    "iso:country":"US",
    "sg:address":"5077 E Lew Davis St",
    "sg:city":"Long Beach",
    "sg:classifiers":[
        {
            "category":"Banks & Credit Unions",
            "subcategory":"Bank",
            "type":"Services"
        }
    ],
    "sg:phone":"+1 562 627 9800",
    "sg:postcode":"90808",
    "sg:province":"CA",
    "sg:website":"www.paramountchamber.org",
    "wof:name":"Gateway Business Bank",
    "wof:placetype":"venue"
},
  "geometry": {"coordinates":[-118.134232,33.830097],"type":"Point"}
}