{
  "type": "Feature",
  "properties": {
    "iso:country":"US",
    "sg:address":"20021 S Susana Rd",
    "sg:city":"Compton",
    "sg:classifiers":[
        {
            "category":"Travel",
            "subcategory":"Travel Agent",
            "type":"Entertainment"
        }
    ],
    "sg:phone":"+1 310 764 4600",
    "sg:postcode":"90221",
    "sg:province":"CA",
    "sg:tags":[
        "agency",
        "mfg"
    ],
    "wof:name":"American Express",
    "wof:placetype":"venue"
},
  "geometry": {"coordinates":[-118.206872,33.848471],"type":"Point"}
}