{
  "type": "Feature",
  "properties": {
    "addr:full":"1401 San Miguelito Rd Lompoc CA 93436",
    "addr:housenumber":"1401",
    "addr:postcode":"93436",
    "addr:street":"San Miguelito Rd",
    "iso:country":"US",
    "sg:address":"1401 San Miguelito Rd",
    "sg:city":"Lompoc",
    "sg:classifiers":[
        {
            "category":"Professional",
            "subcategory":"Business Services",
            "type":"Services"
        }
    ],
    "sg:phone":"+1 805 735 7139",
    "sg:postcode":"93436",
    "sg:province":"CA",
    "sg:tags":[
        "consultant",
        "coach"
    ],
    "wof:name":"Payne Company",
    "wof:placetype":"venue"
},
  "geometry": {"coordinates":[-120.461257,34.619064],"type":"Point"}
}