{
  "type": "Feature",
  "properties": {
    "iso:country":"US",
    "sg:address":"1430 S Grand Ave",
    "sg:city":"Glendora",
    "sg:classifiers":[
        {
            "category":"Professional",
            "subcategory":"Business Services",
            "type":"Services"
        }
    ],
    "sg:phone":"+1 626 914 1593",
    "sg:postcode":"91740",
    "sg:province":"CA",
    "sg:tags":[
        "communication",
        "receiving",
        "mailbox-rental",
        "telegraph"
    ],
    "wof:name":"Ams Mail",
    "wof:placetype":"venue"
},
  "geometry": {"coordinates":[-117.872522,34.113256],"type":"Point"}
}