{
  "type": "Feature",
  "properties": {
    "addr:full":"649 S Maple Ave Montebello CA 90640",
    "addr:housenumber":"649",
    "addr:postcode":"90640",
    "addr:street":"S Maple Ave",
    "iso:country":"US",
    "sg:address":"649 S Maple Ave",
    "sg:city":"Montebello",
    "sg:classifiers":[
        {
            "category":"Personal",
            "type":"Services"
        }
    ],
    "sg:phone":"+1 800 954 8691",
    "sg:postcode":"90640",
    "sg:province":"CA",
    "sg:tags":[
        "towing"
    ],
    "wof:name":"Helms & Hill Inc",
    "wof:placetype":"venue"
},
  "geometry": {"coordinates":[-118.11900300000001,34.004398],"type":"Point"}
}