{
  "type": "Feature",
  "properties": {
    "addr:full":"71800 Highway 111 Rancho Mirage CA 92270",
    "addr:housenumber":"71800",
    "addr:postcode":"92270",
    "addr:street":"Highway 111",
    "iso:country":"US",
    "sg:address":"71800 Highway 111",
    "sg:city":"Rancho Mirage",
    "sg:classifiers":[
        {
            "category":"Ice Cream",
            "type":"Food & Drink"
        }
    ],
    "sg:phone":"+1 760 779 1823",
    "sg:postcode":"92270",
    "sg:province":"CA",
    "sg:tags":[
        "frozen",
        "yogurt"
    ],
    "wof:name":"Ben & Jerrys of Cal Inc",
    "wof:placetype":"venue"
},
  "geometry": {"coordinates":[-116.410004,33.738701],"type":"Point"}
}