{
  "type": "Feature",
  "properties": {
    "addr:full":"3905 Park Dr El Dorado Hills CA 95762",
    "addr:housenumber":"3905",
    "addr:postcode":"95762",
    "addr:street":"Park Dr",
    "iso:country":"US",
    "sg:address":"3905 Park Dr",
    "sg:city":"El Dorado Hills",
    "sg:classifiers":[
        {
            "category":"Health Services",
            "subcategory":"Doctor",
            "type":"Services"
        }
    ],
    "sg:phone":"+1 916 933 9998",
    "sg:postcode":"95762",
    "sg:province":"CA",
    "sg:tags":[
        "dentist"
    ],
    "wof:name":"James H Hastings DDS",
    "wof:placetype":"venue"
},
  "geometry": {"coordinates":[-121.073909,38.659825],"type":"Point"}
}