{
  "type": "Feature",
  "properties": {
    "iso:country":"US",
    "sg:address":"3433 Pickwick Street",
    "sg:city":"San Diego",
    "sg:classifiers":[
        {
            "category":"Retail",
            "subcategory":"Laundry & Dry Cleaning",
            "type":"Services"
        }
    ],
    "sg:phone":"+1 619 234 8523",
    "sg:postcode":"92102",
    "sg:province":"CA",
    "wof:name":"Zion Laundry No 2",
    "wof:placetype":"venue"
},
  "geometry": {"coordinates":[-117.120661,32.715277],"type":"Point"}
}