{
  "type": "Feature",
  "properties": {
    "iso:country":"US",
    "sg:address":"845 Commerce St",
    "sg:city":"Stockton",
    "sg:classifiers":[
        {
            "category":"Wholesale",
            "subcategory":"Machinery & Supplies",
            "type":"Manufacturing & Wholesale Goods"
        }
    ],
    "sg:phone":"+1 209 948 4410",
    "sg:postcode":"95206",
    "sg:province":"CA",
    "sg:tags":[
        "engine"
    ],
    "wof:name":"Collins Diesel Injection",
    "wof:placetype":"venue"
},
  "geometry": {"coordinates":[-121.290123,37.943742],"type":"Point"}
}