{
  "type": "Feature",
  "properties": {
    "addr:full":"2928 N Main St Los Angeles CA 90031",
    "addr:housenumber":"2928",
    "addr:postcode":"90031",
    "addr:street":"N Main St",
    "iso:country":"US",
    "sg:address":"2928 N Main St",
    "sg:city":"Los Angeles",
    "sg:classifiers":[
        {
            "category":"Restaurant",
            "type":"Food & Drink"
        }
    ],
    "sg:phone":"+1 323 225 0075",
    "sg:postcode":"90031",
    "sg:province":"CA",
    "sg:tags":[
        "mexican"
    ],
    "wof:name":"El Dorado Mexican Food Products",
    "wof:placetype":"venue"
},
  "geometry": {"coordinates":[-118.209999,34.065899],"type":"Point"}
}