{
  "type": "Feature",
  "properties": {
    "iso:country":"US",
    "sg:address":"1478 Guerneville Rd",
    "sg:city":"Santa Rosa",
    "sg:classifiers":[
        {
            "category":"Home & Garden",
            "subcategory":"Building Materials",
            "type":"Retail Goods"
        }
    ],
    "sg:phone":"+1 707 546 0863",
    "sg:postcode":"95403",
    "sg:province":"CA",
    "sg:tags":[
        "paint"
    ],
    "sg:website":"www.kellymoore.com",
    "wof:name":"Kelley-Moore Paint Co",
    "wof:placetype":"venue"
},
  "geometry": {"coordinates":[-122.732595,38.458839],"type":"Point"}
}