{
  "type": "Feature",
  "properties": {
    "addr:full":"5692 Mother Lode Dr Placerville CA 95667",
    "addr:housenumber":"5692",
    "addr:postcode":"95667",
    "addr:street":"Mother Lode Dr",
    "iso:country":"US",
    "sg:address":"5692 Mother Lode Dr",
    "sg:city":"Placerville",
    "sg:classifiers":[
        {
            "category":"Building & Trades",
            "subcategory":"Construction",
            "type":"Services"
        }
    ],
    "sg:phone":"+1 530 642 2606",
    "sg:postcode":"95667",
    "sg:province":"CA",
    "sg:tags":[
        "maker",
        "cabinet"
    ],
    "wof:name":"Bill's Cabinets",
    "wof:placetype":"venue"
},
  "geometry": {"coordinates":[-120.870576,38.679617],"type":"Point"}
}