{
  "type": "Feature",
  "properties": {
    "iso:country":"US",
    "sg:address":"2 Krotona St",
    "sg:city":"Ojai",
    "sg:classifiers":[
        {
            "category":"Organizations",
            "subcategory":"Professional Association",
            "type":"Services"
        }
    ],
    "sg:phone":"+1 805 646 2653",
    "sg:postcode":"93023",
    "sg:province":"CA",
    "wof:name":"Theosophical Society-Ojai Vlly",
    "wof:placetype":"venue"
},
  "geometry": {"coordinates":[-119.27303499999999,34.436591],"type":"Point"}
}