{
  "type": "Feature",
  "properties": {
    "addr:full":"7418 S Denker Ave Los Angeles CA 90047",
    "addr:housenumber":"7418",
    "addr:postcode":"90047",
    "addr:street":"S Denker Ave",
    "iso:country":"US",
    "sg:address":"7418 S Denker Ave",
    "sg:city":"Los Angeles",
    "sg:classifiers":[
        {
            "category":"Building & Trades",
            "subcategory":"Cleaning & Sanitation",
            "type":"Services"
        }
    ],
    "sg:phone":"+1 323 841 3343",
    "sg:postcode":"90047",
    "sg:province":"CA",
    "sg:tags":[
        "investment"
    ],
    "wof:name":"B Ready Detailing",
    "wof:placetype":"venue"
},
  "geometry": {"coordinates":[-118.304554,33.971085],"type":"Point"}
}