{
  "type": "Feature",
  "properties": {
    "addr:full":"547 S Marengo Ave Pasadena CA 91101",
    "addr:housenumber":"547",
    "addr:postcode":"91101",
    "addr:street":"S Marengo Ave",
    "iso:country":"US",
    "sg:address":"547 S Marengo Ave",
    "sg:city":"Pasadena",
    "sg:classifiers":[
        {
            "category":"Professional",
            "subcategory":"Lawyer & Legal Services",
            "type":"Services"
        }
    ],
    "sg:phone":"+1 626 564 8052",
    "sg:postcode":"91101",
    "sg:province":"CA",
    "sg:tags":[
        "attorney"
    ],
    "wof:name":"Wills & Kliger Law Office",
    "wof:placetype":"venue"
},
  "geometry": {"coordinates":[-118.145933,34.136042],"type":"Point"}
}