{
  "type": "Feature",
  "properties": {
    "iso:country":"US",
    "sg:address":"5038 W. El Segundo Blvd",
    "sg:city":"Hawthorne",
    "sg:classifiers":[
        {
            "category":"Autos & Motor Vehicles",
            "subcategory":"Fuel & Gas Station",
            "type":"Retail Goods"
        }
    ],
    "sg:phone":"+1 310 978 0769",
    "sg:postcode":"90250",
    "sg:province":"CA",
    "sg:website":"www.arco.com",
    "wof:name":"Thrifty Oil",
    "wof:placetype":"venue"
},
  "geometry": {"coordinates":[-118.366984,33.916368],"type":"Point"}
}