{
  "type": "Feature",
  "properties": {
    "iso:country":"US",
    "sg:address":"4425 Main St",
    "sg:city":"Shasta Lake",
    "sg:classifiers":[
        {
            "category":"Education",
            "subcategory":"School",
            "type":"Public Place"
        }
    ],
    "sg:phone":"+1 530 275 7020",
    "sg:postcode":"96019",
    "sg:province":"CA",
    "sg:tags":[
        "intermediate"
    ],
    "wof:name":"Central Vly Intermediate Schl",
    "wof:placetype":"venue"
},
  "geometry": {"coordinates":[-122.36560799999999,40.682081],"type":"Point"}
}