{
  "type": "Feature",
  "properties": {
    "addr:full":"2299 Ogden Sannazor Dr Tracy CA 95377",
    "addr:housenumber":"2299",
    "addr:postcode":"95377",
    "addr:street":"Ogden Sannazor Dr",
    "iso:country":"US",
    "sg:address":"2299 Ogden Sannazor Dr",
    "sg:city":"Tracy",
    "sg:classifiers":[
        {
            "category":"Recreation",
            "type":"Entertainment"
        }
    ],
    "sg:phone":"+1 209 832 9510",
    "sg:postcode":"95377",
    "sg:province":"CA",
    "sg:tags":[
        "tennis",
        "court"
    ],
    "wof:name":"USPTA Nor Cal",
    "wof:placetype":"venue"
},
  "geometry": {"coordinates":[-121.458966,37.742971],"type":"Point"}
}