{
  "type": "Feature",
  "properties": {
    "addr:full":"329 Primrose Rd Burlingame CA 94010",
    "addr:housenumber":"329",
    "addr:postcode":"94010",
    "addr:street":"Primrose Rd",
    "iso:country":"US",
    "sg:address":"329 Primrose Rd",
    "sg:city":"Burlingame",
    "sg:classifiers":[
        {
            "category":"Personal",
            "subcategory":"Beauty Salon",
            "type":"Services"
        }
    ],
    "sg:phone":"+1 650 344 2080",
    "sg:postcode":"94010",
    "sg:province":"CA",
    "wof:name":"Puttin On The Ritz Nelson",
    "wof:placetype":"venue"
},
  "geometry": {"coordinates":[-122.34856499999999,37.578031],"type":"Point"}
}