{
  "type": "Feature",
  "properties": {
    "iso:country":"US",
    "sg:address":"1359 N Helen Ave",
    "sg:city":"Ontario",
    "sg:classifiers":[
        {
            "category":"Building & Trades",
            "subcategory":"Construction",
            "type":"Services"
        }
    ],
    "sg:phone":"+1 909 984 2781",
    "sg:postcode":"91762",
    "sg:province":"CA",
    "sg:tags":[
        "contractor"
    ],
    "wof:name":"Emory C Jackson Co",
    "wof:placetype":"venue"
},
  "geometry": {"coordinates":[-117.678106,34.082369],"type":"Point"}
}