{
  "type": "Feature",
  "properties": {
    "addr:full":"604 S Emily St Anaheim CA 92805",
    "addr:housenumber":"604",
    "addr:postcode":"92805",
    "addr:street":"S Emily St",
    "iso:country":"US",
    "sg:address":"604 S Emily St",
    "sg:city":"Anaheim",
    "sg:classifiers":[
        {
            "category":"Arts & Performance",
            "subcategory":"Music",
            "type":"Entertainment"
        }
    ],
    "sg:phone":"+1 714 532 0147",
    "sg:postcode":"92805",
    "sg:province":"CA",
    "sg:tags":[
        "dj"
    ],
    "wof:name":"Anaheim Disc Jockey",
    "wof:placetype":"venue"
},
  "geometry": {"coordinates":[-117.910004,33.828999],"type":"Point"}
}