{
  "type": "Feature",
  "properties": {
    "addr:full":"10243 Russett Ave Sunland CA 91040",
    "addr:housenumber":"10243",
    "addr:postcode":"91040",
    "addr:street":"Russett Ave",
    "iso:country":"US",
    "sg:address":"10243 Russett Ave",
    "sg:city":"Sunland",
    "sg:classifiers":[
        {
            "category":"Health Services",
            "subcategory":"Doctor",
            "type":"Services"
        },
        {
            "category":"Health Services",
            "subcategory":"Chiropractor",
            "type":"Services"
        }
    ],
    "sg:phone":"+1 818 951 2777",
    "sg:postcode":"91040",
    "sg:province":"CA",
    "sg:tags":[
        "physician",
        "surgeon",
        "chiropractic"
    ],
    "wof:name":"Edward Klein Dr",
    "wof:placetype":"venue"
},
  "geometry": {"coordinates":[-118.31929100000001,34.255069],"type":"Point"}
}