{
  "type": "Feature",
  "properties": {
    "addr:full":"3261 Calimyrna Rd Acampo CA 95220",
    "addr:housenumber":"3261",
    "addr:postcode":"95220",
    "addr:street":"Calimyrna Rd",
    "iso:country":"US",
    "sg:address":"3261 Calimyrna Rd",
    "sg:city":"Acampo",
    "sg:classifiers":[
        {
            "category":"Wholesale",
            "subcategory":"Vending Machines",
            "type":"Manufacturing & Wholesale Goods"
        }
    ],
    "sg:phone":"+1 209 339 9211",
    "sg:postcode":"95220",
    "sg:province":"CA",
    "sg:tags":[
        "operator"
    ],
    "wof:name":"Sweet BS Vending",
    "wof:placetype":"venue"
},
  "geometry": {"coordinates":[-121.274879,38.214684],"type":"Point"}
}