{
  "type": "Feature",
  "properties": {
    "iso:country":"US",
    "sg:address":"233 Clark Ave",
    "sg:city":"Yuba City",
    "sg:classifiers":[
        {
            "category":"Real Estate",
            "subcategory":"Real Estate Operator",
            "type":"Services"
        }
    ],
    "sg:phone":"+1 530 671 0679",
    "sg:postcode":"95991",
    "sg:province":"CA",
    "sg:tags":[
        "apartment"
    ],
    "wof:name":"Hillcrest Court Apartments",
    "wof:placetype":"venue"
},
  "geometry": {"coordinates":[-121.624721,39.122341],"type":"Point"}
}