{
  "type": "Feature",
  "properties": {
    "addr:full":"28047 Dorothy Dr Ste 201 Agoura Hills CA 91301",
    "addr:housenumber":"28047",
    "addr:postcode":"91301",
    "addr:street":"Dorothy Dr Ste 201",
    "iso:country":"US",
    "sg:address":"28047 Dorothy Dr Ste 201",
    "sg:city":"Agoura Hills",
    "sg:classifiers":[
        {
            "category":"Health Services",
            "subcategory":"Health Practitioner",
            "type":"Services"
        }
    ],
    "sg:phone":"+1 818 879 7979",
    "sg:postcode":"91301",
    "sg:province":"CA",
    "sg:tags":[
        "nutritionist"
    ],
    "sg:website":"www.mediwellness.net",
    "wof:name":"Mediwellness",
    "wof:placetype":"venue"
},
  "geometry": {"coordinates":[-118.737745,34.142513],"type":"Point"}
}