{
  "type": "Feature",
  "properties": {
    "addr:full":"4225 Park Blvd San Diego CA 92103",
    "addr:housenumber":"4225",
    "addr:postcode":"92103",
    "addr:street":"Park Blvd",
    "iso:country":"US",
    "sg:address":"4225 Park Blvd",
    "sg:city":"San Diego",
    "sg:classifiers":[
        {
            "category":"Personal",
            "subcategory":"Beauty Salon",
            "type":"Services"
        }
    ],
    "sg:phone":"+1 619 220 0565",
    "sg:postcode":"92103",
    "sg:province":"CA",
    "sg:tags":[
        "nail",
        "manicuring"
    ],
    "wof:name":"My Nails Skin Care",
    "wof:placetype":"venue"
},
  "geometry": {"coordinates":[-117.146004,32.754398],"type":"Point"}
}