{
  "type": "Feature",
  "properties": {
    "iso:country":"US",
    "sg:address":"12294 Carmel Mountain Rd",
    "sg:city":"San Diego",
    "sg:classifiers":[
        {
            "category":"Home & Garden",
            "subcategory":"Carpets & Floor Coverings",
            "type":"Retail Goods"
        }
    ],
    "sg:phone":"+1 858 592 9434",
    "sg:postcode":"92129",
    "sg:province":"CA",
    "sg:tags":[
        "material"
    ],
    "wof:name":"Carpeteria Markarian Inc",
    "wof:placetype":"venue"
},
  "geometry": {"coordinates":[-117.075643,32.986915],"type":"Point"}
}