{
  "type": "Feature",
  "properties": {
    "iso:country":"US",
    "sg:address":"4200 Mother Lode Dr",
    "sg:city":"Shingle Springs",
    "sg:classifiers":[
        {
            "category":"Professional",
            "subcategory":"Accounting & Tax Preparation",
            "type":"Services"
        }
    ],
    "sg:phone":"+1 530 677 2040",
    "sg:postcode":"95682",
    "sg:province":"CA",
    "sg:tags":[
        "bookkeeping",
        "general"
    ],
    "wof:name":"Bookkeeping Center",
    "wof:placetype":"venue"
},
  "geometry": {"coordinates":[-120.92655499999999,38.665625],"type":"Point"}
}