{
  "type": "Feature",
  "properties": {
    "addr:full":"4825 Firestone Blvd South Gate CA 90280",
    "addr:housenumber":"4825",
    "addr:postcode":"90280",
    "addr:street":"Firestone Blvd;Gate",
    "iso:country":"US",
    "sg:address":"4825 Firestone Blvd",
    "sg:city":"South Gate",
    "sg:classifiers":[
        {
            "category":"Home & Garden",
            "subcategory":"Furniture",
            "type":"Retail Goods"
        }
    ],
    "sg:phone":"+1 323 249 1777",
    "sg:postcode":"90280",
    "sg:province":"CA",
    "sg:tags":[
        "store"
    ],
    "wof:name":"Lupita's Furniture",
    "wof:placetype":"venue"
},
  "geometry": {"coordinates":[-118.184371,33.95217],"type":"Point"}
}