{
  "type": "Feature",
  "properties": {
    "addr:full":"11618 Artesia Blvd Artesia CA 90701",
    "addr:housenumber":"11618",
    "addr:postcode":"90701",
    "addr:street":"Artesia Blvd",
    "iso:country":"US",
    "sg:address":"11618 Artesia Blvd",
    "sg:city":"Artesia",
    "sg:classifiers":[
        {
            "category":"Retail",
            "subcategory":"Auto Repair",
            "type":"Services"
        }
    ],
    "sg:phone":"+1 562 865 2772",
    "sg:postcode":"90701",
    "sg:province":"CA",
    "wof:name":"Mark's Auto Repair",
    "wof:placetype":"venue"
},
  "geometry": {"coordinates":[-118.08699799999999,33.872898],"type":"Point"}
}