{
  "type": "Feature",
  "properties": {
    "addr:full":"6420 el Camino Real Atascadero CA 93422",
    "addr:housenumber":"6420",
    "addr:postcode":"93422",
    "addr:street":"El Camino Real",
    "iso:country":"US",
    "sg:address":"6420 el Camino Real",
    "sg:city":"Atascadero",
    "sg:classifiers":[
        {
            "category":"Shopping",
            "subcategory":"Used Merchandise",
            "type":"Retail Goods"
        }
    ],
    "sg:phone":"+1 805 466 8281",
    "sg:postcode":"93422",
    "sg:province":"CA",
    "sg:tags":[
        "shop",
        "consignment"
    ],
    "wof:name":"Yours N Mine Consignment Shop",
    "wof:placetype":"venue"
},
  "geometry": {"coordinates":[-120.669258,35.488687],"type":"Point"}
}