{
  "type": "Feature",
  "properties": {
    "iso:country":"US",
    "sg:address":"1637 E Prosperity Ave",
    "sg:city":"Tulare",
    "sg:classifiers":[
        {
            "category":"Health Services",
            "subcategory":"Chiropractor",
            "type":"Services"
        }
    ],
    "sg:phone":"+1 559 687 2225",
    "sg:postcode":"93274",
    "sg:province":"CA",
    "sg:tags":[
        "chiropractic"
    ],
    "wof:name":"Mendonca Kendall Dc",
    "wof:placetype":"venue"
},
  "geometry": {"coordinates":[-119.32283700000001,36.225857],"type":"Point"}
}