{
  "type": "Feature",
  "properties": {
    "addr:full":"11530 W Eight Mile Rd Stockton CA 95219",
    "addr:housenumber":"11530",
    "addr:postcode":"95219",
    "addr:street":"W Eight Mile Rd",
    "iso:country":"US",
    "sg:address":"11530 W Eight Mile Rd",
    "sg:city":"Stockton",
    "sg:classifiers":[
        {
            "category":"Farming",
            "subcategory":"Fish & Marine Products",
            "type":"Manufacturing & Wholesale Goods"
        },
        {
            "category":"Recreation",
            "subcategory":"Fishing",
            "type":"Entertainment"
        }
    ],
    "sg:phone":"+1 209 473 3979",
    "sg:postcode":"95219",
    "sg:province":"CA",
    "sg:tags":[
        "tackle",
        "bait",
        "fishermen's",
        "supply"
    ],
    "wof:name":"Stockton Bass Bait & Tackle",
    "wof:placetype":"venue"
},
  "geometry": {"coordinates":[-121.456763,38.059266],"type":"Point"}
}