{
  "type": "Feature",
  "properties": {
    "iso:country":"US",
    "sg:address":"18847 Oak Tree Rd",
    "sg:city":"Nevada City",
    "sg:classifiers":[
        {
            "category":"Education",
            "subcategory":"Preschool",
            "type":"Public Place"
        },
        {
            "category":"Education",
            "subcategory":"School",
            "type":"Public Place"
        }
    ],
    "sg:phone":"+1 530 292 1323",
    "sg:postcode":"95959",
    "sg:province":"CA",
    "sg:tags":[
        "elementary"
    ],
    "wof:name":"Headstart-North San Juan",
    "wof:placetype":"venue"
},
  "geometry": {"coordinates":[-121.098,39.367901],"type":"Point"}
}