{
  "type": "Feature",
  "properties": {
    "addr:full":"700 el Camino Real Menlo Park CA 94025",
    "addr:housenumber":"700",
    "addr:postcode":"94025",
    "addr:street":"El Camino Real",
    "iso:country":"US",
    "sg:address":"700 el Camino Real",
    "sg:city":"Menlo Park",
    "sg:classifiers":[
        {
            "category":"Shopping",
            "subcategory":"Optical Goods",
            "type":"Retail Goods"
        }
    ],
    "sg:phone":"+1 650 329 9966",
    "sg:postcode":"94025",
    "sg:province":"CA",
    "wof:name":"Eyexam Of California Inc",
    "wof:placetype":"venue"
},
  "geometry": {"coordinates":[-122.17801,37.451025],"type":"Point"}
}