{
  "type": "Feature",
  "properties": {
    "addr:full":"16 E Redlands Blvd Redlands CA 92373",
    "addr:housenumber":"16",
    "addr:postcode":"92373",
    "addr:street":"E Redlands Blvd",
    "iso:country":"US",
    "sg:address":"16 E Redlands Blvd",
    "sg:city":"Redlands",
    "sg:classifiers":[
        {
            "category":"Personal",
            "subcategory":"Beauty Salon",
            "type":"Services"
        }
    ],
    "sg:phone":"+1 909 748 7799",
    "sg:postcode":"92373",
    "sg:province":"CA",
    "wof:name":"Claudia",
    "wof:placetype":"venue"
},
  "geometry": {"coordinates":[-117.181574,34.057231],"type":"Point"}
}