{
  "type": "Feature",
  "properties": {
    "addr:full":"1920 N Thompson Ave Reedley CA 93654",
    "addr:housenumber":"1920",
    "addr:postcode":"93654",
    "addr:street":"N Thompson Ave",
    "iso:country":"US",
    "sg:address":"1920 N Thompson Ave",
    "sg:city":"Reedley",
    "sg:classifiers":[
        {
            "category":"Professional",
            "type":"Services"
        }
    ],
    "sg:phone":"+1 559 638 9978",
    "sg:postcode":"93654",
    "sg:province":"CA",
    "wof:name":"Eric Helgesen",
    "wof:placetype":"venue"
},
  "geometry": {"coordinates":[-119.442554,36.613177],"type":"Point"}
}