{
  "type": "Feature",
  "properties": {
    "iso:country":"US",
    "sg:address":"1114 Olive St",
    "sg:city":"Santa Barbara",
    "sg:classifiers":[
        {
            "category":"Real Estate",
            "subcategory":"Architect",
            "type":"Services"
        }
    ],
    "sg:phone":"+1 805 884 8784",
    "sg:postcode":"93101",
    "sg:province":"CA",
    "wof:name":"Mark Wienke",
    "wof:placetype":"venue"
},
  "geometry": {"coordinates":[-119.69859700000001,34.428584],"type":"Point"}
}