{
  "type": "Feature",
  "properties": {
    "iso:country":"US",
    "sg:address":"1132 Santee St",
    "sg:city":"Los Angeles",
    "sg:classifiers":[
        {
            "category":"Retail",
            "subcategory":"Auto Repair",
            "type":"Services"
        }
    ],
    "sg:phone":"+1 213 745 7392",
    "sg:postcode":"90015",
    "sg:province":"CA",
    "sg:tags":[
        "repairing",
        "automobile"
    ],
    "wof:name":"Jaes International Corp",
    "wof:placetype":"venue"
},
  "geometry": {"coordinates":[-118.256942,34.036734],"type":"Point"}
}