{
  "type": "Feature",
  "properties": {
    "addr:full":"360 Coddingtown Center Santa Rosa CA 95401",
    "addr:housenumber":"360",
    "addr:postcode":"95401",
    "addr:street":"Coddingtown Center",
    "iso:country":"US",
    "sg:address":"360 Coddingtown Center",
    "sg:city":"Santa Rosa",
    "sg:classifiers":[
        {
            "category":"Shopping",
            "subcategory":"Bicycles & Sporting Goods",
            "type":"Retail Goods"
        }
    ],
    "sg:phone":"+1 707 575 8475",
    "sg:postcode":"95401",
    "sg:province":"CA",
    "wof:name":"Big 5 Sporting Goods",
    "wof:placetype":"venue"
},
  "geometry": {"coordinates":[-122.72727999999999,38.458075],"type":"Point"}
}