{
  "type": "Feature",
  "properties": {
    "addr:full":"21 Copperstone Mission Viejo CA 92679",
    "addr:housenumber":"21",
    "addr:postcode":"92679",
    "addr:street":"Copperstone",
    "iso:country":"US",
    "sg:address":"21 Copperstone",
    "sg:city":"Mission Viejo",
    "sg:classifiers":[
        {
            "category":"Communications",
            "type":"Services"
        }
    ],
    "sg:phone":"+1 949 305 4168",
    "sg:postcode":"92679",
    "sg:province":"CA",
    "sg:tags":[
        "communication"
    ],
    "wof:name":"Lici Communications",
    "wof:placetype":"venue"
},
  "geometry": {"coordinates":[-117.62615099999999,33.670431],"type":"Point"}
}