{
  "type": "Feature",
  "properties": {
    "iso:country":"US",
    "sg:address":"17461 Derian Ave",
    "sg:city":"Irvine",
    "sg:classifiers":[
        {
            "category":"Building & Trades",
            "subcategory":"Construction",
            "type":"Services"
        }
    ],
    "sg:phone":"+1 949 474 1450",
    "sg:postcode":"92614",
    "sg:province":"CA",
    "sg:tags":[
        "contractor"
    ],
    "wof:name":"Lighthouse Builders",
    "wof:placetype":"venue"
},
  "geometry": {"coordinates":[-117.83836100000001,33.687629],"type":"Point"}
}