{
  "type": "Feature",
  "properties": {
    "addr:full":"126 Spring Grove Ave San Rafael CA 94901",
    "addr:housenumber":"126",
    "addr:postcode":"94901",
    "addr:street":"Spring Grove Ave",
    "iso:country":"US",
    "sg:address":"126 Spring Grove Ave",
    "sg:city":"San Rafael",
    "sg:classifiers":[
        {
            "category":"Professional",
            "subcategory":"Art Services",
            "type":"Services"
        }
    ],
    "sg:phone":"+1 415 454 8255",
    "sg:postcode":"94901",
    "sg:province":"CA",
    "sg:tags":[
        "graphic",
        "designer"
    ],
    "wof:name":"Keating Identity Group",
    "wof:placetype":"venue"
},
  "geometry": {"coordinates":[-122.54638199999999,37.972614],"type":"Point"}
}