{
  "type": "Feature",
  "properties": {
    "addr:full":"2102 E Montclair Plaza Ln Montclair CA 91763",
    "addr:housenumber":"2102",
    "addr:postcode":"91763",
    "addr:street":"E Montclair Plaza Ln",
    "iso:country":"US",
    "sg:address":"2102 E Montclair Plaza Ln",
    "sg:city":"Montclair",
    "sg:classifiers":[
        {
            "category":"Shopping",
            "subcategory":"Clothing, Apparel, & Fashions",
            "type":"Retail Goods"
        }
    ],
    "sg:phone":"+1 909 626 7850",
    "sg:postcode":"91763",
    "sg:province":"CA",
    "wof:name":"Woman Plus",
    "wof:placetype":"venue"
},
  "geometry": {"coordinates":[-117.69700899999999,34.0874],"type":"Point"}
}