{
  "type": "Feature",
  "properties": {
    "addr:full":"6310 San Vicente Blvd Ste 425 Los Angeles CA 90048",
    "addr:housenumber":"6310",
    "addr:postcode":"90048",
    "addr:street":"San Vicente Blvd Ste 425",
    "iso:country":"US",
    "sg:address":"6310 San Vicente Blvd Ste 425",
    "sg:city":"Los Angeles",
    "sg:classifiers":[
        {
            "category":"Organizations",
            "subcategory":"Non-profit Organization",
            "type":"Services"
        }
    ],
    "sg:phone":"+1 323 939 6790",
    "sg:postcode":"90048",
    "sg:province":"CA",
    "sg:tags":[
        "service/non-profit",
        "community"
    ],
    "wof:name":"California League Of Conservation Voters",
    "wof:placetype":"venue"
},
  "geometry": {"coordinates":[-118.367363,34.064938],"type":"Point"}
}