{
  "type": "Feature",
  "properties": {
    "iso:country":"US",
    "sg:address":"299 N Fairview Ave",
    "sg:city":"Goleta",
    "sg:classifiers":[
        {
            "category":"Banks & Credit Unions",
            "subcategory":"Bank",
            "type":"Services"
        }
    ],
    "sg:phone":"+1 805 683 1403",
    "sg:postcode":"93117",
    "sg:province":"CA",
    "wof:name":"Santa Barbara Bank & Trust",
    "wof:placetype":"venue"
},
  "geometry": {"coordinates":[-119.83066700000001,34.441666],"type":"Point"}
}