{
  "type": "Feature",
  "properties": {
    "iso:country":"US",
    "sg:address":"201 E Magnolia Blvd, Ste 345",
    "sg:city":"Burbank",
    "sg:classifiers":[
        {
            "category":"Cinema",
            "subcategory":"Movie Theater",
            "type":"Entertainment"
        }
    ],
    "sg:phone":"+1 310 289 4262",
    "sg:postcode":"91502",
    "sg:province":"CA",
    "wof:name":"AMC Burbank Town Center 8",
    "wof:placetype":"venue"
},
  "geometry": {"coordinates":[-118.312164,34.183429],"type":"Point"}
}