{
  "type": "Feature",
  "properties": {
    "addr:full":"1539 Centinela Ave Inglewood CA 90302",
    "addr:housenumber":"1539",
    "addr:postcode":"90302",
    "addr:street":"Centinela Ave",
    "iso:country":"US",
    "sg:address":"1539 Centinela Ave",
    "sg:city":"Inglewood",
    "sg:classifiers":[
        {
            "category":"Real Estate",
            "subcategory":"Architect",
            "type":"Services"
        }
    ],
    "sg:phone":"+1 310 338 8717",
    "sg:postcode":"90302",
    "sg:province":"CA",
    "sg:tags":[
        "home",
        "planning",
        "design"
    ],
    "wof:name":"Carlton Designs",
    "wof:placetype":"venue"
},
  "geometry": {"coordinates":[-118.36614299999999,33.97689],"type":"Point"}
}