{
  "type": "Feature",
  "properties": {
    "addr:full":"115 Ave Pico San Clemente CA 92672",
    "addr:housenumber":"115",
    "addr:postcode":"92672",
    "addr:street":"Ave Pico",
    "iso:country":"US",
    "sg:address":"115 Ave Pico",
    "sg:city":"San Clemente",
    "sg:classifiers":[
        {
            "category":"Building & Trades",
            "subcategory":"Landscaping Services",
            "type":"Services"
        }
    ],
    "sg:phone":"+1 949 498 4140",
    "sg:postcode":"92672",
    "sg:province":"CA",
    "wof:name":"Diaz Landscape",
    "wof:placetype":"venue"
},
  "geometry": {"coordinates":[-117.631311,33.432308],"type":"Point"}
}