{
  "type": "Feature",
  "properties": {
    "iso:country":"US",
    "sg:address":"39150 Fremont Blvd",
    "sg:city":"Fremont",
    "sg:classifiers":[
        {
            "category":"Real Estate",
            "subcategory":"Developer",
            "type":"Services"
        }
    ],
    "sg:phone":"+1 510 792 2300",
    "sg:postcode":"94538",
    "sg:province":"CA",
    "wof:name":"Bancorp Properties Investmark",
    "wof:placetype":"venue"
},
  "geometry": {"coordinates":[-121.986026,37.547411],"type":"Point"}
}