{
  "type": "Feature",
  "properties": {
    "iso:country":"US",
    "sg:address":"716 N La Cienega Blvd",
    "sg:city":"West Hollywood",
    "sg:classifiers":[
        {
            "category":"Shopping",
            "subcategory":"Antiques",
            "type":"Retail Goods"
        }
    ],
    "sg:phone":"+1 310 657 4615",
    "sg:postcode":"90069",
    "sg:province":"CA",
    "sg:website":"www.therien.com",
    "wof:name":"Therien & Co Inc",
    "wof:placetype":"venue"
},
  "geometry": {"coordinates":[-118.375999,34.0839],"type":"Point"}
}