{
  "type": "Feature",
  "properties": {
    "iso:country":"US",
    "sg:address":"2670 Middlefield Rd",
    "sg:city":"Redwood City",
    "sg:classifiers":[
        {
            "category":"Retail",
            "subcategory":"Auto Repair",
            "type":"Services"
        }
    ],
    "sg:phone":"+1 650 368 8484",
    "sg:postcode":"94063",
    "sg:province":"CA",
    "sg:tags":[
        "repairing",
        "automobile"
    ],
    "sg:website":"www.okradiator.com",
    "wof:name":"O K Radiator Co",
    "wof:placetype":"venue"
},
  "geometry": {"coordinates":[-122.211555,37.476778],"type":"Point"}
}