{
  "type": "Feature",
  "properties": {
    "addr:full":"155 Monterey Blvd San Francisco CA 94131",
    "addr:housenumber":"155",
    "addr:postcode":"94131",
    "addr:street":"Monterey Blvd",
    "iso:country":"US",
    "sg:address":"155 Monterey Blvd",
    "sg:city":"San Francisco",
    "sg:classifiers":[
        {
            "category":"Professional",
            "subcategory":"Engineering",
            "type":"Services"
        }
    ],
    "sg:phone":"+1 415 374 2744",
    "sg:postcode":"94131",
    "sg:province":"CA",
    "sg:tags":[
        "engineer"
    ],
    "wof:name":"Arcadis",
    "wof:placetype":"venue"
},
  "geometry": {"coordinates":[-122.43871900000001,37.731461],"type":"Point"}
}