{
  "type": "Feature",
  "properties": {
    "iso:country":"US",
    "sg:address":"394 Boynton Ave",
    "sg:city":"San Jose",
    "sg:classifiers":[
        {
            "category":"Real Estate",
            "subcategory":"Real Estate Operator",
            "type":"Services"
        }
    ],
    "sg:phone":"+1 408 247 3354",
    "sg:postcode":"95117",
    "sg:province":"CA",
    "sg:tags":[
        "apartment"
    ],
    "wof:name":"Rosa Crest Studios",
    "wof:placetype":"venue"
},
  "geometry": {"coordinates":[-121.966003,37.320301],"type":"Point"}
}