{
  "type": "Feature",
  "properties": {
    "addr:full":"3024 Railroad Ave Pittsburg CA 94565",
    "addr:housenumber":"3024",
    "addr:postcode":"94565",
    "addr:street":"Railroad Ave",
    "iso:country":"US",
    "sg:address":"3024 Railroad Ave",
    "sg:city":"Pittsburg",
    "sg:classifiers":[
        {
            "category":"Professional",
            "subcategory":"Lawyer & Legal Services",
            "type":"Services"
        },
        {
            "category":"Organizations",
            "subcategory":"Professional Association",
            "type":"Services"
        }
    ],
    "sg:phone":"+1 925 427 1771",
    "sg:postcode":"94565",
    "sg:province":"CA",
    "sg:tags":[
        "litigation",
        "attorney",
        "accident",
        "nursing",
        "worker",
        "damage",
        "elder",
        "compensation",
        "benefit",
        "employee",
        "home",
        "property",
        "law"
    ],
    "sg:website":"http://www.stevenhendersonlawoffice.com",
    "wof:name":"Henderson Steven & Jill Law Office Of",
    "wof:placetype":"venue"
},
  "geometry": {"coordinates":[-121.892636,38.008157],"type":"Point"}
}