{
  "type": "Feature",
  "properties": {
    "addr:full":"203 S H St Bakersfield CA 93304",
    "addr:housenumber":"203",
    "addr:postcode":"93304",
    "addr:street":"S H St",
    "iso:country":"US",
    "sg:address":"203 S H St",
    "sg:city":"Bakersfield",
    "sg:classifiers":[
        {
            "category":"Organizations",
            "subcategory":"Religious Organization",
            "type":"Services"
        }
    ],
    "sg:phone":"+1 661 831 9055",
    "sg:postcode":"93304",
    "sg:province":"CA",
    "sg:tags":[
        "church"
    ],
    "wof:name":"Central Baptist Church",
    "wof:placetype":"venue"
},
  "geometry": {"coordinates":[-119.02131900000001,35.352184],"type":"Point"}
}