{
  "type": "Feature",
  "properties": {
    "iso:country":"US",
    "sg:address":"201 S San Mateo Dr",
    "sg:city":"San Mateo",
    "sg:classifiers":[
        {
            "category":"Shopping",
            "subcategory":"Optician",
            "type":"Retail Goods"
        }
    ],
    "sg:phone":"+1 650 344 4232",
    "sg:postcode":"94401",
    "sg:province":"CA",
    "sg:tags":[
        "eyewear"
    ],
    "sg:website":"www.bundyopticians.com",
    "wof:name":"Bundy Opticians",
    "wof:placetype":"venue"
},
  "geometry": {"coordinates":[-122.3248,37.565059],"type":"Point"}
}