{
  "type": "Feature",
  "properties": {
    "addr:full":"760 N Mission Rd Los Angeles CA 90033",
    "addr:housenumber":"760",
    "addr:postcode":"90033",
    "addr:street":"N Mission Rd",
    "iso:country":"US",
    "sg:address":"760 N Mission Rd",
    "sg:city":"Los Angeles",
    "sg:classifiers":[
        {
            "category":"Wholesale",
            "subcategory":"Scrap",
            "type":"Manufacturing & Wholesale Goods"
        }
    ],
    "sg:phone":"+1 323 221 9813",
    "sg:postcode":"90033",
    "sg:province":"CA",
    "wof:name":"Aztec Auto Wrecking",
    "wof:placetype":"venue"
},
  "geometry": {"coordinates":[-118.22218599999999,34.055821],"type":"Point"}
}