{
  "type": "Feature",
  "properties": {
    "iso:country":"US",
    "sg:address":"6100 Wilshire Blvd",
    "sg:city":"Los Angeles",
    "sg:classifiers":[
        {
            "category":"Banks & Credit Unions",
            "subcategory":"Bank",
            "type":"Services"
        },
        {
            "category":"Professional",
            "subcategory":"Lawyer & Legal Services",
            "type":"Services"
        }
    ],
    "sg:phone":"+1 323 951 9999",
    "sg:postcode":"90048",
    "sg:province":"CA",
    "wof:name":"California Bankers",
    "wof:placetype":"venue"
},
  "geometry": {"coordinates":[-118.36189,34.062788],"type":"Point"}
}