{
  "type": "Feature",
  "properties": {
    "addr:full":"4555 Hilltop Dr El Sobrante CA 94803",
    "addr:housenumber":"4555",
    "addr:postcode":"94803",
    "addr:street":"Hilltop Dr El Sobrante",
    "iso:country":"US",
    "sg:address":"4555 Hilltop Dr",
    "sg:city":"El Sobrante",
    "sg:classifiers":[
        {
            "category":"Social Services",
            "subcategory":"Child Care",
            "type":"Services"
        }
    ],
    "sg:phone":"+1 510 222 6059",
    "sg:postcode":"94803",
    "sg:province":"CA",
    "sg:tags":[
        "kindergarten",
        "academic",
        "school"
    ],
    "wof:name":"Small World Montessori School",
    "wof:placetype":"venue"
},
  "geometry": {"coordinates":[-122.30950900000001,37.976623],"type":"Point"}
}