{
  "type": "Feature",
  "properties": {
    "iso:country":"US",
    "sg:address":"2634 N Tustin St",
    "sg:city":"Orange",
    "sg:classifiers":[
        {
            "category":"Fast Food",
            "type":"Food & Drink"
        },
        {
            "category":"Ice Cream",
            "type":"Food & Drink"
        }
    ],
    "sg:phone":"+1 714 283 2871",
    "sg:postcode":"92865",
    "sg:province":"CA",
    "sg:tags":[
        "frozen",
        "yogurt"
    ],
    "sg:website":"www.dairyqueen.com",
    "wof:name":"Dairy Queen",
    "wof:placetype":"venue"
},
  "geometry": {"coordinates":[-117.835999,33.832001],"type":"Point"}
}