{
  "type": "Feature",
  "properties": {
    "addr:full":"119 S L St Dinuba CA 93618",
    "addr:housenumber":"119",
    "addr:postcode":"93618",
    "addr:street":"S L St",
    "iso:country":"US",
    "sg:address":"119 S L St",
    "sg:city":"Dinuba",
    "sg:classifiers":[
        {
            "category":"Health Services",
            "subcategory":"Optometrist",
            "type":"Services"
        },
        {
            "category":"Health Services",
            "subcategory":"Doctor",
            "type":"Services"
        },
        {
            "category":"Health Services",
            "subcategory":"Health Practitioner",
            "type":"Services"
        },
        {
            "category":"Shopping",
            "subcategory":"Optical Goods",
            "type":"Retail Goods"
        }
    ],
    "sg:phone":"+1 559 591 4656",
    "sg:postcode":"93618",
    "sg:province":"CA",
    "sg:tags":[
        "physician",
        "surgeons",
        "lens",
        "ophthalmology",
        "contact",
        "surgeon"
    ],
    "wof:name":"Dr Allyson Farrell",
    "wof:placetype":"venue"
},
  "geometry": {"coordinates":[-119.389995,36.540685],"type":"Point"}
}