{
  "type": "Feature",
  "properties": {
    "iso:country":"US",
    "sg:address":"15581 Product Ln",
    "sg:city":"Huntington Beach",
    "sg:classifiers":[
        {
            "category":"Wholesale",
            "subcategory":"Construction Materials",
            "type":"Manufacturing & Wholesale Goods"
        }
    ],
    "sg:phone":"+1 714 897 9877",
    "sg:postcode":"92649",
    "sg:province":"CA",
    "sg:tags":[
        "interior",
        "building",
        "exterior"
    ],
    "wof:name":"Crownmark Building Materials",
    "wof:placetype":"venue"
},
  "geometry": {"coordinates":[-118.027689,33.735382],"type":"Point"}
}