{
  "type": "Feature",
  "properties": {
    "iso:country":"US",
    "sg:address":"2054 Humboldt St",
    "sg:city":"Los Angeles",
    "sg:classifiers":[
        {
            "category":"Food & Beverages",
            "subcategory":"Meat & Fish",
            "type":"Retail Goods"
        }
    ],
    "sg:phone":"+1 213 626 7326",
    "sg:postcode":"90031",
    "sg:province":"CA",
    "sg:tags":[
        "hot",
        "dog"
    ],
    "wof:name":"Hot Dogs R Us",
    "wof:placetype":"venue"
},
  "geometry": {"coordinates":[-118.222185,34.077175],"type":"Point"}
}