{
  "type": "Feature",
  "properties": {
    "addr:full":"879 W 190th St Gardena CA 90248",
    "addr:housenumber":"879",
    "addr:postcode":"90248",
    "addr:street":"W 190Th St",
    "iso:country":"US",
    "sg:address":"879 W 190th St",
    "sg:city":"Gardena",
    "sg:classifiers":[
        {
            "category":"Professional",
            "type":"Services"
        }
    ],
    "sg:phone":"+1 310 802 4671",
    "sg:postcode":"90248",
    "sg:province":"CA",
    "sg:tags":[
        "establishment"
    ],
    "wof:name":"Edenburg Technologies",
    "wof:placetype":"venue"
},
  "geometry": {"coordinates":[-118.288329,33.860023],"type":"Point"}
}