{
  "type": "Feature",
  "properties": {
    "iso:country":"US",
    "sg:address":"917 Glenneyre St",
    "sg:city":"Laguna Beach",
    "sg:classifiers":[
        {
            "category":"Banks & Credit Unions",
            "subcategory":"Bank",
            "type":"Services"
        }
    ],
    "sg:phone":"+1 949 494 7531",
    "sg:postcode":"92651",
    "sg:province":"CA",
    "sg:tags":[
        "escrow"
    ],
    "wof:name":"Chicago Title Escrow",
    "wof:placetype":"venue"
},
  "geometry": {"coordinates":[-117.77698100000001,33.535538],"type":"Point"}
}