{
  "type": "Feature",
  "properties": {
    "addr:full":"4150 Mission Blvd San Diego CA 92109",
    "addr:housenumber":"4150",
    "addr:postcode":"92109",
    "addr:street":"Mission Blvd",
    "iso:country":"US",
    "sg:address":"4150 Mission Blvd",
    "sg:city":"San Diego",
    "sg:classifiers":[
        {
            "category":"Shopping",
            "subcategory":"Clothing, Apparel, & Fashions",
            "type":"Retail Goods"
        }
    ],
    "sg:phone":"+1 858 581 3329",
    "sg:postcode":"92109",
    "sg:province":"CA",
    "sg:tags":[
        "item",
        "boutique"
    ],
    "wof:name":"Brava Boutique",
    "wof:placetype":"venue"
},
  "geometry": {"coordinates":[-117.253907,32.791086],"type":"Point"}
}