{
  "type": "Feature",
  "properties": {
    "iso:country":"US",
    "sg:address":"11360 Long Beach Blvd",
    "sg:city":"Lynwood",
    "sg:classifiers":[
        {
            "category":"Retail",
            "subcategory":"Auto Repair",
            "type":"Services"
        }
    ],
    "sg:phone":"+1 310 763 1282",
    "sg:postcode":"90262",
    "sg:province":"CA",
    "sg:tags":[
        "carburetor"
    ],
    "wof:name":"Zamora Carburetors",
    "wof:placetype":"venue"
},
  "geometry": {"coordinates":[-118.210657,33.927782],"type":"Point"}
}