{
  "type": "Feature",
  "properties": {
    "addr:full":"6250 Atlantic Avenue Bell CA 90201",
    "addr:housenumber":"6250",
    "addr:postcode":"90201",
    "addr:street":"Atlantic Avenue",
    "iso:country":"US",
    "sg:address":"6250 Atlantic Avenue",
    "sg:city":"Bell",
    "sg:classifiers":[
        {
            "category":"Shopping",
            "subcategory":"Shoes",
            "type":"Retail Goods"
        }
    ],
    "sg:phone":"+1 323 562 9999",
    "sg:postcode":"90201",
    "sg:province":"CA",
    "sg:tags":[
        "store"
    ],
    "wof:name":"Eurostar",
    "wof:placetype":"venue"
},
  "geometry": {"coordinates":[-118.186671,33.980169],"type":"Point"}
}