{
  "type": "Feature",
  "properties": {
    "iso:country":"US",
    "sg:address":"6474 University Avenue",
    "sg:city":"San Diego",
    "sg:classifiers":[
        {
            "category":"Professional",
            "subcategory":"Accounting & Tax Preparation",
            "type":"Services"
        }
    ],
    "sg:phone":"+1 619 286 9610",
    "sg:postcode":"92115",
    "sg:province":"CA",
    "sg:tags":[
        "accountant"
    ],
    "wof:name":"Ulle Park Lee & Associates",
    "wof:placetype":"venue"
},
  "geometry": {"coordinates":[-117.056498,32.755099],"type":"Point"}
}