{
  "type": "Feature",
  "properties": {
    "addr:full":"6401 Ruby St Los Angeles CA 90042",
    "addr:housenumber":"6401",
    "addr:postcode":"90042",
    "addr:street":"Ruby St",
    "iso:country":"US",
    "sg:address":"6401 Ruby St",
    "sg:city":"Los Angeles",
    "sg:classifiers":[
        {
            "category":"Recreation",
            "type":"Entertainment"
        }
    ],
    "sg:phone":"+1 323 258 4481",
    "sg:postcode":"90042",
    "sg:province":"CA",
    "sg:tags":[
        "club",
        "membership"
    ],
    "wof:name":"Danish Soldiers Society",
    "wof:placetype":"venue"
},
  "geometry": {"coordinates":[-118.179089,34.115845],"type":"Point"}
}