{
  "type": "Feature",
  "properties": {
    "iso:country":"US",
    "sg:address":"305 W Fyffe St",
    "sg:city":"Stockton",
    "sg:classifiers":[
        {
            "category":"Building & Trades",
            "subcategory":"Construction",
            "type":"Services"
        }
    ],
    "sg:phone":"+1 209 810 5518",
    "sg:postcode":"95203",
    "sg:province":"CA",
    "sg:tags":[
        "coping",
        "plastering",
        "tiling",
        "pool",
        "swimming"
    ],
    "wof:name":"Central Valley Pool",
    "wof:placetype":"venue"
},
  "geometry": {"coordinates":[-121.348572,37.948942],"type":"Point"}
}