{
  "type": "Feature",
  "properties": {
    "iso:country":"US",
    "sg:address":"20131 Bahama St",
    "sg:city":"Chatsworth",
    "sg:classifiers":[
        {
            "category":"Professional",
            "subcategory":"Business Services",
            "type":"Services"
        }
    ],
    "sg:phone":"+1 818 709 0508",
    "sg:postcode":"91311",
    "sg:province":"CA",
    "sg:tags":[
        "packaging"
    ],
    "wof:name":"Multi Pak Corp",
    "wof:placetype":"venue"
},
  "geometry": {"coordinates":[-118.574972,34.233014],"type":"Point"}
}