{
  "type": "Feature",
  "properties": {
    "addr:full":"8656 Reseda Blvd Northridge CA 91324",
    "addr:housenumber":"8656",
    "addr:postcode":"91324",
    "addr:street":"Reseda Blvd",
    "iso:country":"US",
    "sg:address":"8656 Reseda Blvd",
    "sg:city":"Northridge",
    "sg:classifiers":[
        {
            "category":"Building & Trades",
            "subcategory":"Construction",
            "type":"Services"
        },
        {
            "category":"Retail",
            "subcategory":"Auto Repair",
            "type":"Services"
        }
    ],
    "sg:phone":"+1 818 885 8468",
    "sg:postcode":"91324",
    "sg:province":"CA",
    "sg:tags":[
        "flat",
        "mfg",
        "automotive",
        "coating",
        "tinting",
        "contractor",
        "glass"
    ],
    "wof:name":"Blackout Glass Tinting",
    "wof:placetype":"venue"
},
  "geometry": {"coordinates":[-118.536007,34.227889],"type":"Point"}
}