{
  "type": "Feature",
  "properties": {
    "addr:full":"3600 McHenry Ave Modesto CA 95356",
    "addr:housenumber":"3600",
    "addr:postcode":"ca 95356",
    "addr:street":"Mchenry Ave",
    "iso:country":"US",
    "sg:address":"3600 McHenry Ave",
    "sg:city":"Modesto",
    "sg:classifiers":[
        {
            "category":"Banks & Credit Unions",
            "subcategory":"Bank",
            "type":"Services"
        }
    ],
    "sg:phone":"+1 209 521 8060",
    "sg:postcode":"95356",
    "sg:province":"CA",
    "sg:website":"www.bankofthewest.com",
    "wof:name":"Bank Of The West",
    "wof:placetype":"venue"
},
  "geometry": {"coordinates":[-120.994361,37.693179],"type":"Point"}
}