{
  "type": "Feature",
  "properties": {
    "addr:full":"3724 Spencer St Torrance CA 90503",
    "addr:housenumber":"3724",
    "addr:postcode":"90503",
    "addr:street":"Spencer St",
    "iso:country":"US",
    "sg:address":"3724 Spencer St",
    "sg:city":"Torrance",
    "sg:classifiers":[
        {
            "category":"Professional",
            "type":"Services"
        }
    ],
    "sg:phone":"+1 310 542 7188",
    "sg:postcode":"90503",
    "sg:province":"CA",
    "wof:name":"Katarzyna Kozak",
    "wof:placetype":"venue"
},
  "geometry": {"coordinates":[-118.351602,33.844911],"type":"Point"}
}