{
  "type": "Feature",
  "properties": {
    "addr:full":"540 University Ave Palo Alto CA 94301",
    "addr:housenumber":"540",
    "addr:postcode":"94301",
    "addr:street":"University Ave",
    "iso:country":"US",
    "sg:address":"540 University Ave",
    "sg:city":"Palo Alto",
    "sg:classifiers":[
        {
            "category":"Professional",
            "subcategory":"Lawyer & Legal Services",
            "type":"Services"
        }
    ],
    "sg:phone":"+1 650 752 0990",
    "sg:postcode":"94301",
    "sg:province":"CA",
    "sg:tags":[
        "attorney"
    ],
    "wof:name":"Stattler Johansen & Adell",
    "wof:placetype":"venue"
},
  "geometry": {"coordinates":[-122.15797600000001,37.449407],"type":"Point"}
}