{
  "type": "Feature",
  "properties": {
    "iso:country":"US",
    "sg:address":"2174 W Foothill Blvd",
    "sg:city":"Upland",
    "sg:classifiers":[
        {
            "category":"Personal",
            "subcategory":"Beauty Salon",
            "type":"Services"
        }
    ],
    "sg:phone":"+1 909 920 9433",
    "sg:postcode":"91786",
    "sg:province":"CA",
    "wof:name":"T's Salon",
    "wof:placetype":"venue"
},
  "geometry": {"coordinates":[-117.691917,34.106708],"type":"Point"}
}