{
  "type": "Feature",
  "properties": {
    "addr:full":"25500 Hawthorne Blvd Ste 2120 Torrance CA 90505",
    "addr:housenumber":"25500",
    "addr:postcode":"90505",
    "addr:street":"Hawthorne Blvd Ste 2120",
    "iso:country":"US",
    "sg:address":"25500 Hawthorne Blvd Ste 2120",
    "sg:city":"Torrance",
    "sg:classifiers":[
        {
            "category":"Professional",
            "subcategory":"Accounting & Tax Preparation",
            "type":"Services"
        }
    ],
    "sg:phone":"+1 310 373 8804",
    "sg:postcode":"90505",
    "sg:province":"CA",
    "sg:tags":[
        "accountant"
    ],
    "wof:name":"Hanasono Theodore Y Accountancy Corporation",
    "wof:placetype":"venue"
},
  "geometry": {"coordinates":[-118.34899900000001,33.7948],"type":"Point"}
}