{
  "type": "Feature",
  "properties": {
    "iso:country":"US",
    "sg:address":"1289 Reamwood Ave",
    "sg:city":"Los Altos",
    "sg:classifiers":[
        {
            "category":"Banks & Credit Unions",
            "subcategory":"Financial Services",
            "type":"Services"
        }
    ],
    "sg:phone":"+1 650 948 7558",
    "sg:postcode":"94089",
    "sg:province":"CA",
    "sg:tags":[
        "trust",
        "management"
    ],
    "wof:name":"Constance Lebaron",
    "wof:placetype":"venue"
},
  "geometry": {"coordinates":[-121.98860500000001,37.409853],"type":"Point"}
}