{
  "type": "Feature",
  "properties": {
    "addr:full":"1674 E Hammer Ln Stockton CA 95210",
    "addr:housenumber":"1674",
    "addr:postcode":"95210",
    "addr:street":"E Hammer Ln",
    "iso:country":"US",
    "sg:address":"1674 E Hammer Ln",
    "sg:city":"Stockton",
    "sg:classifiers":[
        {
            "category":"Restaurant",
            "type":"Food & Drink"
        }
    ],
    "sg:menulink":"http://www.allmenus.com/ca/stockton/50479-ihop/menu/",
    "sg:phone":"+1 209 951 3137",
    "sg:postcode":"95210",
    "sg:province":"CA",
    "sg:tags":[
        "sandwich",
        "salad",
        "burger",
        "soup",
        "american",
        "steakhouse",
        "wrap"
    ],
    "wof:name":"IHOP",
    "wof:placetype":"venue"
},
  "geometry": {"coordinates":[-121.292103,38.020858],"type":"Point"}
}