{
  "type": "Feature",
  "properties": {
    "addr:full":"13709 S Willowbrook Avenue Compton CA 90222",
    "addr:housenumber":"13709",
    "addr:postcode":"90222",
    "addr:street":"S Willowbrook Avenue",
    "iso:country":"US",
    "sg:address":"13709 S Willowbrook Avenue",
    "sg:city":"Compton",
    "sg:classifiers":[
        {
            "category":"Food & Beverages",
            "subcategory":"Liquor & Beverages",
            "type":"Retail Goods"
        }
    ],
    "sg:phone":"+1 310 638 2554",
    "sg:postcode":"90222",
    "sg:province":"CA",
    "sg:tags":[
        "beer",
        "spirit",
        "wine"
    ],
    "wof:name":"Naples Winery",
    "wof:placetype":"venue"
},
  "geometry": {"coordinates":[-118.227553,33.908585],"type":"Point"}
}