{
  "type": "Feature",
  "properties": {
    "addr:full":"1750 York Dr Vista CA 92084",
    "addr:housenumber":"1750",
    "addr:postcode":"92084",
    "addr:street":"York Dr",
    "iso:country":"US",
    "sg:address":"1750 York Dr",
    "sg:city":"Vista",
    "sg:classifiers":[
        {
            "category":"Professional",
            "subcategory":"Detective & Security Services",
            "type":"Services"
        }
    ],
    "sg:phone":"+1 760 758 4110",
    "sg:postcode":"92084",
    "sg:province":"CA",
    "sg:tags":[
        "investigator"
    ],
    "wof:name":"National Consulting & Security",
    "wof:placetype":"venue"
},
  "geometry": {"coordinates":[-117.20967899999999,33.178261],"type":"Point"}
}