{
  "type": "Feature",
  "properties": {
    "addr:full":"5500 W Rosecrans Ave Hawthorne CA 90250",
    "addr:housenumber":"5500",
    "addr:postcode":"90250",
    "addr:street":"W Rosecrans Ave",
    "iso:country":"US",
    "sg:address":"5500 W Rosecrans Ave",
    "sg:city":"Hawthorne",
    "sg:classifiers":[
        {
            "category":"Wholesale",
            "subcategory":"Electrical",
            "type":"Manufacturing & Wholesale Goods"
        }
    ],
    "sg:phone":"+1 310 643 3456",
    "sg:postcode":"90250",
    "sg:province":"CA",
    "sg:tags":[
        "semiconductor",
        "component",
        "sales"
    ],
    "wof:name":"Pantera Technologies",
    "wof:placetype":"venue"
},
  "geometry": {"coordinates":[-118.37646100000001,33.901753],"type":"Point"}
}