{
  "type": "Feature",
  "properties": {
    "iso:country":"US",
    "sg:address":"120 E 12th St",
    "sg:city":"Tracy",
    "sg:classifiers":[
        {
            "category":"Professional",
            "subcategory":"Lawyer & Legal Services",
            "type":"Services"
        }
    ],
    "sg:phone":"+1 209 832 2500",
    "sg:postcode":"95376",
    "sg:province":"CA",
    "sg:tags":[
        "attorney",
        "death",
        "personal",
        "automobile",
        "worker",
        "compensation",
        "wrongful",
        "benefit",
        "accident",
        "employee",
        "injury",
        "law"
    ],
    "sg:website":"http://www.tracylawcenter.com/rhyppa.htm",
    "wof:name":"Tracy Law Center",
    "wof:placetype":"venue"
},
  "geometry": {"coordinates":[-121.423866,37.740391],"type":"Point"}
}