{
  "type": "Feature",
  "properties": {
    "addr:full":"11455 Jefferson Blvd Culver City CA 90230",
    "addr:housenumber":"11455",
    "addr:postcode":"90230",
    "addr:street":"Jefferson Blvd",
    "iso:country":"US",
    "sg:address":"11455 Jefferson Blvd",
    "sg:city":"Culver City",
    "sg:classifiers":[
        {
            "category":"Shopping",
            "subcategory":"Discount & Variety Stores",
            "type":"Retail Goods"
        }
    ],
    "sg:postcode":"90230",
    "sg:province":"CA",
    "sg:website":"www.dollartree.com",
    "wof:name":"Dollar Tree",
    "wof:placetype":"venue"
},
  "geometry": {"coordinates":[-118.396783,33.989319],"type":"Point"}
}