{
  "type": "Feature",
  "properties": {
    "iso:country":"US",
    "sg:address":"11239 Ventura Blvd Studio 38",
    "sg:city":"Studio City",
    "sg:classifiers":[
        {
            "category":"Personal",
            "subcategory":"Day Spa",
            "type":"Services"
        }
    ],
    "sg:phone":"+1 818 406 7791",
    "sg:postcode":"91604",
    "sg:province":"CA",
    "sg:website":"www.skinbeautybar.com",
    "wof:name":"Skin Beauty Bar",
    "wof:placetype":"venue"
},
  "geometry": {"coordinates":[-118.37495699999999,34.14186],"type":"Point"}
}