{
  "type": "Feature",
  "properties": {
    "addr:full":"895 Mountain View Dr Lafayette CA 94549",
    "addr:housenumber":"895",
    "addr:postcode":"94549",
    "addr:street":"Mountain View Dr",
    "iso:country":"US",
    "sg:address":"895 Mountain View Dr",
    "sg:city":"Lafayette",
    "sg:classifiers":[
        {
            "category":"Personal",
            "subcategory":"Tanning Parlor",
            "type":"Services"
        }
    ],
    "sg:phone":"+1 925 283 2921",
    "sg:postcode":"94549",
    "sg:province":"CA",
    "sg:tags":[
        "color",
        "consultant"
    ],
    "wof:name":"Linda Rosenthal Design",
    "wof:placetype":"venue"
},
  "geometry": {"coordinates":[-122.12723200000001,37.886733],"type":"Point"}
}