{
  "type": "Feature",
  "properties": {
    "iso:country":"US",
    "sg:address":"1400 Cam de la Reina",
    "sg:city":"San Diego",
    "sg:classifiers":[
        {
            "category":"Shopping",
            "subcategory":"Gifts & Souvenirs",
            "type":"Retail Goods"
        }
    ],
    "sg:phone":"+1 619 294 9654",
    "sg:postcode":"92108",
    "sg:province":"CA",
    "sg:tags":[
        "announcement",
        "invitation"
    ],
    "wof:name":"Daydreams Invitations",
    "wof:placetype":"venue"
},
  "geometry": {"coordinates":[-117.148022,32.770546],"type":"Point"}
}