{
  "type": "Feature",
  "properties": {
    "addr:full":"5355 Avenida Encinas Carlsbad CA 92008",
    "addr:housenumber":"5355",
    "addr:postcode":"92008",
    "addr:street":"Avenida Encinas",
    "iso:country":"US",
    "sg:address":"5355 Avenida Encinas",
    "sg:city":"Carlsbad",
    "sg:classifiers":[
        {
            "category":"Insurance",
            "subcategory":"Insurance Agent",
            "type":"Services"
        },
        {
            "category":"Insurance",
            "subcategory":"Hazard Insurance",
            "type":"Services"
        },
        {
            "category":"Insurance",
            "subcategory":"Title Insurance",
            "type":"Services"
        },
        {
            "category":"Insurance",
            "subcategory":"Life Insurance",
            "type":"Services"
        }
    ],
    "sg:phone":"+1 760 438 5700",
    "sg:postcode":"92008",
    "sg:province":"CA",
    "sg:tags":[
        "business",
        "consultant",
        "commercial",
        "homeowner",
        "motorcycle",
        "renter",
        "auto",
        "analyst"
    ],
    "sg:website":"http://www.allstate.com/seandoherty",
    "wof:name":"Allstate Insurance Company - Sean Doherty",
    "wof:placetype":"venue"
},
  "geometry": {"coordinates":[-117.32584799999999,33.127556],"type":"Point"}
}