{
  "type": "Feature",
  "properties": {
    "iso:country":"US",
    "sg:address":"20 S L St",
    "sg:city":"Livermore",
    "sg:classifiers":[
        {
            "category":"Real Estate",
            "subcategory":"Real Estate Agent",
            "type":"Services"
        }
    ],
    "sg:phone":"+1 925 294 5959",
    "sg:postcode":"94550",
    "sg:province":"CA",
    "wof:name":"Coldwell Banker",
    "wof:placetype":"venue"
},
  "geometry": {"coordinates":[-121.77122,37.681201],"type":"Point"}
}