{
  "type": "Feature",
  "properties": {
    "addr:full":"141 Boat Yard Dr Fort Bragg CA 95437",
    "addr:housenumber":"141",
    "addr:postcode":"95437",
    "addr:street":"Boat Yard Dr",
    "iso:country":"US",
    "sg:address":"141 Boat Yard Dr",
    "sg:city":"Fort Bragg",
    "sg:classifiers":[
        {
            "category":"Insurance",
            "subcategory":"Insurance Agent",
            "type":"Services"
        }
    ],
    "sg:phone":"+1 707 962 2860",
    "sg:postcode":"95437",
    "sg:province":"CA",
    "wof:name":"State Farm Insurance",
    "wof:placetype":"venue"
},
  "geometry": {"coordinates":[-123.805798,39.422348],"type":"Point"}
}