{
  "type": "Feature",
  "properties": {
    "iso:country":"US",
    "sg:address":"14155 Magnolia Blvd Suite 206",
    "sg:city":"Van Nuys",
    "sg:classifiers":[
        {
            "category":"Arts & Performance",
            "subcategory":"Arts Center",
            "type":"Entertainment"
        }
    ],
    "sg:phone":"+1 877 538 7743",
    "sg:postcode":"91401",
    "sg:province":"CA",
    "sg:website":"www.wemusproductions.com",
    "wof:name":"Wemus Productions",
    "wof:placetype":"venue"
},
  "geometry": {"coordinates":[-118.44215199999999,34.165646],"type":"Point"}
}