{
  "type": "Feature",
  "properties": {
    "iso:country":"US",
    "sg:address":"1340 S Los Angeles St",
    "sg:city":"Los Angeles",
    "sg:classifiers":[
        {
            "category":"Wholesale",
            "subcategory":"Apparel",
            "type":"Manufacturing & Wholesale Goods"
        }
    ],
    "sg:phone":"+1 213 741 0660",
    "sg:postcode":"90015",
    "sg:province":"CA",
    "sg:tags":[
        "clothing"
    ],
    "wof:name":"L A Brand Name Incorporation",
    "wof:placetype":"venue"
},
  "geometry": {"coordinates":[-118.259812,34.035099],"type":"Point"}
}