{
  "type": "Feature",
  "properties": {
    "addr:full":"21 Orinda Way Ste C Orinda CA 94563",
    "addr:housenumber":"21",
    "addr:postcode":"94563",
    "addr:street":"Orinda Way Ste C",
    "iso:country":"US",
    "sg:address":"21 Orinda Way Ste C",
    "sg:city":"Orinda",
    "sg:classifiers":[
        {
            "category":"Health Services",
            "subcategory":"Doctor",
            "type":"Services"
        },
        {
            "category":"Health Services",
            "subcategory":"Clinic",
            "type":"Services"
        }
    ],
    "sg:phone":"+1 925 215 8694",
    "sg:postcode":"94563",
    "sg:province":"CA",
    "sg:tags":[
        "psychological",
        "psychologist"
    ],
    "wof:name":"Grelling Psychology Associates Inc",
    "wof:placetype":"venue"
},
  "geometry": {"coordinates":[-122.187127,37.881754],"type":"Point"}
}