{
  "type": "Feature",
  "properties": {
    "addr:full":"818 San Pablo Ave Albany CA 94706",
    "addr:housenumber":"818",
    "addr:postcode":"94706",
    "addr:street":"San Pablo Ave",
    "iso:country":"US",
    "sg:address":"818 San Pablo Ave",
    "sg:city":"Albany",
    "sg:classifiers":[
        {
            "category":"Shopping",
            "type":"Retail Goods"
        }
    ],
    "sg:phone":"+1 510 525 1166",
    "sg:postcode":"94706",
    "sg:province":"CA",
    "sg:tags":[
        "pet",
        "food",
        "store",
        "supply"
    ],
    "sg:website":"www.albanyaquarium.com/",
    "wof:name":"Albany Aquarium",
    "wof:placetype":"venue"
},
  "geometry": {"coordinates":[-122.299665,37.891637],"type":"Point"}
}