{
  "type": "Feature",
  "properties": {
    "addr:full":"2238 Cotner Ave Los Angeles CA 90064",
    "addr:housenumber":"2238",
    "addr:postcode":"90064",
    "addr:street":"Cotner Ave",
    "iso:country":"US",
    "sg:address":"2238 Cotner Ave",
    "sg:city":"Los Angeles",
    "sg:classifiers":[
        {
            "category":"Arts & Performance",
            "subcategory":"Theater",
            "type":"Entertainment"
        }
    ],
    "sg:phone":"+1 310 575 0660",
    "sg:postcode":"90064",
    "sg:province":"CA",
    "sg:tags":[
        "entertainer",
        "adult"
    ],
    "sg:website":"www.4playclub.com",
    "wof:name":"4Play Gentleman's Club",
    "wof:placetype":"venue"
},
  "geometry": {"coordinates":[-118.43883700000001,34.038682],"type":"Point"}
}