{
  "type": "Feature",
  "properties": {
    "iso:country":"US",
    "sg:address":"2070 Hillhurst Ave",
    "sg:city":"Los Angeles",
    "sg:classifiers":[
        {
            "category":"Place Of Worship",
            "subcategory":"Church",
            "type":"Public Place"
        }
    ],
    "sg:phone":"+1 424 235 3352",
    "sg:postcode":"90027",
    "sg:province":"CA",
    "sg:website":"www.exodus3la.com",
    "wof:name":"Exodus3LA",
    "wof:placetype":"venue"
},
  "geometry": {"coordinates":[-118.287335,34.109625],"type":"Point"}
}