{
  "type": "Feature",
  "properties": {
    "iso:country":"US",
    "sg:address":"14137 Oxnard St",
    "sg:city":"Van Nuys",
    "sg:classifiers":[
        {
            "category":"Retail",
            "subcategory":"Auto Repair",
            "type":"Services"
        }
    ],
    "sg:phone":"+1 323 873 4166",
    "sg:postcode":"91401",
    "sg:province":"CA",
    "sg:tags":[
        "body",
        "shop",
        "painting",
        "automobile"
    ],
    "wof:name":"D M Auto Body",
    "wof:placetype":"venue"
},
  "geometry": {"coordinates":[-118.441002,34.179298],"type":"Point"}
}