{
  "type": "Feature",
  "properties": {
    "addr:full":"271 Virginia Pl Costa Mesa CA 92627",
    "addr:housenumber":"271",
    "addr:postcode":"92627",
    "addr:street":"Virginia Pl",
    "iso:country":"US",
    "sg:address":"271 Virginia Pl",
    "sg:city":"Costa Mesa",
    "sg:classifiers":[
        {
            "category":"Building & Trades",
            "subcategory":"Cleaning & Sanitation",
            "type":"Services"
        }
    ],
    "sg:phone":"+1 949 574 8391",
    "sg:postcode":"92627",
    "sg:province":"CA",
    "sg:tags":[
        "window"
    ],
    "wof:name":"Martin's Mobile",
    "wof:placetype":"venue"
},
  "geometry": {"coordinates":[-117.90294799999999,33.649338],"type":"Point"}
}