{
  "type": "Feature",
  "properties": {
    "addr:full":"San Francisco International Airport San Francisco CA 94128",
    "addr:postcode":"94128",
    "iso:country":"US",
    "sg:address":"San Francisco International Airport",
    "sg:city":"San Francisco",
    "sg:classifiers":[
        {
            "category":"Airline",
            "type":"Transportation"
        }
    ],
    "sg:postcode":"94128",
    "sg:province":"CA",
    "sg:website":"www.usairways.com",
    "wof:name":"US Airways",
    "wof:placetype":"venue"
},
  "geometry": {"coordinates":[-122.389903,37.615463],"type":"Point"}
}