{
  "type": "Feature",
  "properties": {
    "iso:country":"US",
    "sg:address":"160 W 97th St",
    "sg:city":"Los Angeles",
    "sg:classifiers":[
        {
            "category":"Social Services",
            "subcategory":"Child Care",
            "type":"Services"
        }
    ],
    "sg:phone":"+1 323 777 1250",
    "sg:postcode":"90003",
    "sg:province":"CA",
    "wof:name":"Helen Wyatt Day Care",
    "wof:placetype":"venue"
},
  "geometry": {"coordinates":[-118.278157,33.948274],"type":"Point"}
}