{
  "type": "Feature",
  "properties": {
    "addr:full":"1245 Laurelwood Rd Santa Clara CA 95054",
    "addr:housenumber":"1245",
    "addr:postcode":"95054",
    "addr:street":"Laurelwood Rd",
    "iso:country":"US",
    "sg:address":"1245 Laurelwood Rd",
    "sg:city":"Santa Clara",
    "sg:classifiers":[
        {
            "category":"Manufacturing",
            "subcategory":"Chemicals & Compounds",
            "type":"Manufacturing & Wholesale Goods"
        }
    ],
    "sg:phone":"+1 408 496 6181",
    "sg:postcode":"95054",
    "sg:province":"CA",
    "sg:tags":[
        "c",
        "mfg",
        "encl",
        "molding",
        "plastic",
        "p",
        "injection",
        "custom",
        "card"
    ],
    "wof:name":"I T T Canon",
    "wof:placetype":"venue"
},
  "geometry": {"coordinates":[-121.952472,37.379171],"type":"Point"}
}