{
  "type": "Feature",
  "properties": {
    "iso:country":"US",
    "sg:address":"151 Kentucky St",
    "sg:city":"Petaluma",
    "sg:classifiers":[
        {
            "category":"Shopping",
            "subcategory":"Baby Store",
            "type":"Retail Goods"
        }
    ],
    "sg:phone":"+1 707 765 6573",
    "sg:postcode":"94952",
    "sg:province":"CA",
    "sg:tags":[
        "children's",
        "infant",
        "wear"
    ],
    "wof:name":"Binkies Children Clothing",
    "wof:placetype":"venue"
},
  "geometry": {"coordinates":[-122.641599,38.234629],"type":"Point"}
}