{
  "type": "Feature",
  "properties": {
    "iso:country":"US",
    "sg:address":"19720 Colima Rd",
    "sg:city":"Diamond Bar",
    "sg:classifiers":[
        {
            "category":"Travel",
            "subcategory":"Travel Agent",
            "type":"Entertainment"
        }
    ],
    "sg:phone":"+1 909 444 4668",
    "sg:postcode":"91748",
    "sg:province":"CA",
    "sg:tags":[
        "agency"
    ],
    "wof:name":"California Family Travel",
    "wof:placetype":"venue"
},
  "geometry": {"coordinates":[-117.870355,33.986441],"type":"Point"}
}