{
  "type": "Feature",
  "properties": {
    "addr:full":"4908 Conejo Rd Fallbrook CA 92028",
    "addr:housenumber":"4908",
    "addr:postcode":"92028",
    "addr:street":"Conejo Rd",
    "iso:country":"US",
    "sg:address":"4908 Conejo Rd",
    "sg:city":"Fallbrook",
    "sg:classifiers":[
        {
            "category":"Wholesale",
            "subcategory":"Machinery & Supplies",
            "type":"Manufacturing & Wholesale Goods"
        }
    ],
    "sg:phone":"+1 760 723 8062",
    "sg:postcode":"92028",
    "sg:province":"CA",
    "sg:tags":[
        "valve"
    ],
    "wof:name":"Coyle Products",
    "wof:placetype":"venue"
},
  "geometry": {"coordinates":[-117.266673,33.303737],"type":"Point"}
}