{
  "type": "Feature",
  "properties": {
    "addr:full":"444 Alaska Ave Torrance CA 90503",
    "addr:housenumber":"444",
    "addr:postcode":"90503",
    "addr:street":"Alaska Ave",
    "iso:country":"US",
    "sg:address":"444 Alaska Ave",
    "sg:city":"Torrance",
    "sg:classifiers":[
        {
            "category":"Freight",
            "type":"Transportation"
        }
    ],
    "sg:phone":"+1 310 328 6199",
    "sg:postcode":"90503",
    "sg:province":"CA",
    "sg:tags":[
        "warehouse",
        "self",
        "storage"
    ],
    "wof:name":"M B Pacing & Crating",
    "wof:placetype":"venue"
},
  "geometry": {"coordinates":[-118.33265900000001,33.842325],"type":"Point"}
}