{
  "type": "Feature",
  "properties": {
    "iso:country":"US",
    "sg:address":"5911 Colodny Dr",
    "sg:city":"Agoura Hills",
    "sg:classifiers":[
        {
            "category":"Wholesale",
            "subcategory":"Non-durable Goods",
            "type":"Manufacturing & Wholesale Goods"
        }
    ],
    "sg:phone":"+1 818 991 1057",
    "sg:postcode":"91301",
    "sg:province":"CA",
    "sg:tags":[
        "print",
        "edition",
        "limited"
    ],
    "wof:name":"Equinart Inc",
    "wof:placetype":"venue"
},
  "geometry": {"coordinates":[-118.738097,34.15589],"type":"Point"}
}