{
  "type": "Feature",
  "properties": {
    "iso:country":"US",
    "sg:address":"937 N Peach Ave",
    "sg:city":"Fresno",
    "sg:classifiers":[
        {
            "category":"Arts & Performance",
            "subcategory":"Theater",
            "type":"Entertainment"
        }
    ],
    "sg:phone":"+1 559 255 9609",
    "sg:postcode":"93727",
    "sg:province":"CA",
    "sg:tags":[
        "live",
        "music"
    ],
    "wof:name":"Big Boss",
    "wof:placetype":"venue"
},
  "geometry": {"coordinates":[-119.71831899999999,36.75648],"type":"Point"}
}