{
  "type": "Feature",
  "properties": {
    "iso:country":"US",
    "sg:address":"18555 Eddy St",
    "sg:city":"Northridge",
    "sg:classifiers":[
        {
            "category":"Building & Trades",
            "subcategory":"Landscaping Services",
            "type":"Services"
        }
    ],
    "sg:phone":"+1 818 885 5000",
    "sg:postcode":"91324",
    "sg:province":"CA",
    "sg:tags":[
        "landscape",
        "contractor"
    ],
    "sg:website":"www.tropicalcreations.com",
    "wof:name":"Tropical Creations Inc",
    "wof:placetype":"venue"
},
  "geometry": {"coordinates":[-118.53848499999999,34.229948],"type":"Point"}
}