{
  "type": "Feature",
  "properties": {
    "addr:full":"2677 Union Ave San Jose CA 95124",
    "addr:housenumber":"2677",
    "addr:postcode":"95124",
    "addr:street":"Union Ave",
    "iso:country":"US",
    "sg:address":"2677 Union Ave",
    "sg:city":"San Jose",
    "sg:classifiers":[
        {
            "category":"Personal",
            "type":"Services"
        }
    ],
    "sg:phone":"+1 408 377 2925",
    "sg:postcode":"95124",
    "sg:province":"CA",
    "sg:tags":[
        "local"
    ],
    "sg:website":"www.reddogshred.com",
    "wof:name":"Red Dog Shred",
    "wof:placetype":"venue"
},
  "geometry": {"coordinates":[-121.933291,37.27296],"type":"Point"}
}