{
  "type": "Feature",
  "properties": {
    "addr:full":"7167 Beverly Blvd Los Angeles CA 90036",
    "addr:housenumber":"7167",
    "addr:postcode":"90036",
    "addr:street":"Beverly Blvd",
    "iso:country":"US",
    "sg:address":"7167 Beverly Blvd",
    "sg:city":"Los Angeles",
    "sg:classifiers":[
        {
            "category":"Personal",
            "subcategory":"Beauty Salon",
            "type":"Services"
        }
    ],
    "sg:phone":"+1 818 389 4352",
    "sg:postcode":"90036",
    "sg:province":"CA",
    "wof:name":"Thaddues Winton Hair Stylist",
    "wof:placetype":"venue"
},
  "geometry": {"coordinates":[-118.345911,34.076232],"type":"Point"}
}