{
  "type": "Feature",
  "properties": {
    "addr:full":"214 S Locust St Inglewood CA 90301",
    "addr:housenumber":"214",
    "addr:postcode":"90301",
    "addr:street":"S Locust St",
    "iso:country":"US",
    "sg:address":"214 S Locust St",
    "sg:city":"Inglewood",
    "sg:classifiers":[
        {
            "category":"Health Services",
            "subcategory":"Doctor",
            "type":"Services"
        }
    ],
    "sg:phone":"+1 310 673 4188",
    "sg:postcode":"90301",
    "sg:province":"CA",
    "wof:name":"Headache Clinic",
    "wof:placetype":"venue"
},
  "geometry": {"coordinates":[-118.350998,33.961399],"type":"Point"}
}