{
  "type": "Feature",
  "properties": {
    "iso:country":"US",
    "sg:address":"74104 Hwy 111",
    "sg:city":"Palm Desert",
    "sg:classifiers":[
        {
            "category":"Home & Garden",
            "subcategory":"Furniture",
            "type":"Retail Goods"
        }
    ],
    "sg:phone":"+1 760 346 4664",
    "sg:postcode":"92260",
    "sg:province":"CA",
    "sg:website":"www.wackywicker.com",
    "wof:name":"Wacky Wicker",
    "wof:placetype":"venue"
},
  "geometry": {"coordinates":[-116.372525,33.721371],"type":"Point"}
}