{
  "type": "Feature",
  "properties": {
    "addr:full":"11941 Ramona Ave Chino CA 91710",
    "addr:housenumber":"11941",
    "addr:postcode":"91710",
    "addr:street":"Ramona Ave",
    "iso:country":"US",
    "sg:address":"11941 Ramona Ave",
    "sg:city":"Chino",
    "sg:classifiers":[
        {
            "category":"Organizations",
            "subcategory":"Religious Organization",
            "type":"Services"
        }
    ],
    "sg:phone":"+1 909 627 2252",
    "sg:postcode":"91710",
    "sg:province":"CA",
    "wof:name":"Ahmadiyya Move In Islam",
    "wof:placetype":"venue"
},
  "geometry": {"coordinates":[-117.706824,34.034238],"type":"Point"}
}