{
  "type": "Feature",
  "properties": {
    "iso:country":"US",
    "sg:address":"395 Stockton Ave",
    "sg:city":"San Jose",
    "sg:classifiers":[
        {
            "category":"Wholesale",
            "subcategory":"Auto Parts",
            "type":"Manufacturing & Wholesale Goods"
        }
    ],
    "sg:phone":"+1 408 947 1043",
    "sg:postcode":"95126",
    "sg:province":"CA",
    "wof:name":"J & J Radiator Service",
    "wof:placetype":"venue"
},
  "geometry": {"coordinates":[-121.906093,37.33379],"type":"Point"}
}