{
  "type": "Feature",
  "properties": {
    "addr:full":"5235 Ardenel Ave Temple City CA 91780",
    "addr:housenumber":"5235",
    "addr:postcode":"91780",
    "addr:street":"Ardenel Ave",
    "iso:country":"US",
    "sg:address":"5235 Ardenel Ave",
    "sg:city":"Temple City",
    "sg:classifiers":[
        {
            "category":"Real Estate",
            "subcategory":"Real Estate Agent",
            "type":"Services"
        }
    ],
    "sg:phone":"+1 626 285 8274",
    "sg:postcode":"91780",
    "sg:province":"CA",
    "wof:name":"Dan Snell Realty",
    "wof:placetype":"venue"
},
  "geometry": {"coordinates":[-118.053814,34.096406],"type":"Point"}
}