{
  "type": "Feature",
  "properties": {
    "iso:country":"US",
    "sg:address":"459 43rd St",
    "sg:city":"Oakland",
    "sg:classifiers":[
        {
            "category":"Communications",
            "type":"Services"
        }
    ],
    "sg:phone":"+1 510 450 0844",
    "sg:postcode":"94609",
    "sg:province":"CA",
    "wof:name":"Center For Media Justice",
    "wof:placetype":"venue"
},
  "geometry": {"coordinates":[-122.261526,37.831726],"type":"Point"}
}