{
  "type": "Feature",
  "properties": {
    "addr:full":"1695 10th St Arcata CA 95521",
    "addr:housenumber":"1695",
    "addr:postcode":"95521",
    "addr:street":"10Th St",
    "iso:country":"US",
    "sg:address":"1695 10th St",
    "sg:city":"Arcata",
    "sg:classifiers":[
        {
            "category":"Social Services",
            "subcategory":"Child Care",
            "type":"Services"
        },
        {
            "category":"Education",
            "subcategory":"Preschool",
            "type":"Public Place"
        }
    ],
    "sg:phone":"+1 707 822 1423",
    "sg:postcode":"95521",
    "sg:province":"CA",
    "sg:tags":[
        "kindergarten"
    ],
    "sg:website":"http://www.armcc.net",
    "wof:name":"Arcata & Rooney - McKinleyville Children's Center",
    "wof:placetype":"venue"
},
  "geometry": {"coordinates":[-124.095859,40.871852],"type":"Point"}
}