{
  "type": "Feature",
  "properties": {
    "iso:country":"US",
    "sg:address":"3633 Martin Luther King Jr Blvd Ste 3",
    "sg:city":"Lynwood",
    "sg:classifiers":[
        {
            "category":"Health Services",
            "subcategory":"Doctor",
            "type":"Services"
        }
    ],
    "sg:phone":"+1 310 763 3075",
    "sg:postcode":"90262",
    "sg:province":"CA",
    "wof:name":"Jones John K MD",
    "wof:placetype":"venue"
},
  "geometry": {"coordinates":[-118.201684,33.930129],"type":"Point"}
}