{
  "type": "Feature",
  "properties": {
    "addr:full":"10719 Riverside Dr North Hollywood CA 91602",
    "addr:housenumber":"10719",
    "addr:postcode":"91602",
    "addr:street":"Riverside Dr",
    "iso:country":"US",
    "sg:address":"10719 Riverside Dr",
    "sg:city":"North Hollywood",
    "sg:classifiers":[
        {
            "category":"Health Services",
            "subcategory":"Dentist",
            "type":"Services"
        }
    ],
    "sg:phone":"+1 818 508 7272",
    "sg:postcode":"91602",
    "sg:province":"CA",
    "sg:tags":[
        "orthodontist",
        "cosmetic"
    ],
    "sg:website":"www.hollywood-dentist.com",
    "wof:name":"Sally Kashani, DDS",
    "wof:placetype":"venue"
},
  "geometry": {"coordinates":[-118.364479,34.152245],"type":"Point"}
}