{
  "type": "Feature",
  "properties": {
    "iso:country":"US",
    "sg:address":"1151 E Holt Ave",
    "sg:city":"Pomona",
    "sg:classifiers":[
        {
            "category":"Utilities",
            "subcategory":"Water",
            "type":"Services"
        }
    ],
    "sg:phone":"+1 909 629 5244",
    "sg:postcode":"91767",
    "sg:province":"CA",
    "sg:tags":[
        "dealer"
    ],
    "wof:name":"Aquapuro",
    "wof:placetype":"venue"
},
  "geometry": {"coordinates":[-117.72821399999999,34.062994],"type":"Point"}
}