{
  "type": "Feature",
  "properties": {
    "iso:country":"US",
    "sg:address":"1211 Maricopa Hwy",
    "sg:city":"Ojai",
    "sg:classifiers":[
        {
            "category":"Professional",
            "subcategory":"Accounting & Tax Preparation",
            "type":"Services"
        }
    ],
    "sg:phone":"+1 805 557 4500",
    "sg:postcode":"93023",
    "sg:province":"CA",
    "sg:tags":[
        "return",
        "filing"
    ],
    "wof:name":"Fidelity Tax & Estate Planners",
    "wof:placetype":"venue"
},
  "geometry": {"coordinates":[-119.26410799999999,34.442029],"type":"Point"}
}