{
  "type": "Feature",
  "properties": {
    "iso:country":"US",
    "sg:address":"4068 Mother Lode Dr",
    "sg:city":"Shingle Springs",
    "sg:classifiers":[
        {
            "category":"Building & Trades",
            "subcategory":"Construction",
            "type":"Services"
        }
    ],
    "sg:phone":"+1 530 676 5291",
    "sg:postcode":"95682",
    "sg:province":"CA",
    "sg:tags":[
        "site",
        "clean"
    ],
    "wof:name":"Comprehensive Construction",
    "wof:placetype":"venue"
},
  "geometry": {"coordinates":[-120.936061,38.661889],"type":"Point"}
}