{
  "type": "Feature",
  "properties": {
    "addr:full":"1833 W 5th St Los Angeles CA 90057",
    "addr:housenumber":"1833",
    "addr:postcode":"90057",
    "addr:street":"W 5Th St",
    "iso:country":"US",
    "sg:address":"1833 W 5th St",
    "sg:city":"Los Angeles",
    "sg:classifiers":[
        {
            "category":"Real Estate",
            "subcategory":"Real Estate Operator",
            "type":"Services"
        }
    ],
    "sg:phone":"+1 213 483 0777",
    "sg:postcode":"90057",
    "sg:province":"CA",
    "sg:tags":[
        "apartment"
    ],
    "wof:name":"St James Square Apartments",
    "wof:placetype":"venue"
},
  "geometry": {"coordinates":[-118.271004,34.058899],"type":"Point"}
}