{
  "type": "Feature",
  "properties": {
    "iso:country":"US",
    "sg:address":"171 Mace St",
    "sg:city":"Chula Vista",
    "sg:classifiers":[
        {
            "category":"Professional",
            "subcategory":"Management & Consulting",
            "type":"Services"
        }
    ],
    "sg:phone":"+1 619 476 8292",
    "sg:postcode":"91911",
    "sg:province":"CA",
    "sg:tags":[
        "development",
        "industrial"
    ],
    "wof:name":"Ingalls' Enterprises",
    "wof:placetype":"venue"
},
  "geometry": {"coordinates":[-117.053623,32.591454],"type":"Point"}
}