{
  "type": "Feature",
  "properties": {
    "addr:full":"280 Baldwin Ave San Mateo CA 94401",
    "addr:housenumber":"280",
    "addr:postcode":"94401",
    "addr:street":"Baldwin Ave",
    "iso:country":"US",
    "sg:address":"280 Baldwin Ave",
    "sg:city":"San Mateo",
    "sg:classifiers":[
        {
            "category":"Health Services",
            "subcategory":"Doctor",
            "type":"Services"
        },
        {
            "category":"Personal",
            "subcategory":"Hair Removal",
            "type":"Services"
        }
    ],
    "sg:phone":"+1 650 344 1121",
    "sg:postcode":"94401",
    "sg:province":"CA",
    "sg:tags":[
        "laser",
        "dermatologist"
    ],
    "wof:name":"Bruce L Maltz, MD",
    "wof:placetype":"venue"
},
  "geometry": {"coordinates":[-122.32538599999999,37.567034],"type":"Point"}
}