{
  "type": "Feature",
  "properties": {
    "addr:full":"8957 Laguna Place Way Elk Grove CA 95758",
    "addr:housenumber":"8957",
    "addr:postcode":"95758",
    "addr:street":"Laguna Place Way",
    "iso:country":"US",
    "sg:address":"8957 Laguna Place Way",
    "sg:city":"Elk Grove",
    "sg:classifiers":[
        {
            "category":"Building & Trades",
            "subcategory":"Landscaping Services",
            "type":"Services"
        }
    ],
    "sg:phone":"+1 916 682 0877",
    "sg:postcode":"95758",
    "sg:province":"CA",
    "sg:tags":[
        "lawn",
        "maintenance",
        "grounds"
    ],
    "wof:name":"River City Landscape Mntnc",
    "wof:placetype":"venue"
},
  "geometry": {"coordinates":[-121.43353,38.423841],"type":"Point"}
}