{
  "type": "Feature",
  "properties": {
    "iso:country":"US",
    "sg:address":"2405 Gads Hill St",
    "sg:city":"Santa Rosa",
    "sg:classifiers":[
        {
            "category":"Retail",
            "subcategory":"Car Wash",
            "type":"Services"
        }
    ],
    "sg:phone":"+1 707 566 6856",
    "sg:postcode":"95401",
    "sg:province":"CA",
    "sg:tags":[
        "automobile",
        "detail",
        "clean"
    ],
    "wof:name":"Mobile Detail Ctr",
    "wof:placetype":"venue"
},
  "geometry": {"coordinates":[-122.765851,38.442413],"type":"Point"}
}