{
  "type": "Feature",
  "properties": {
    "addr:full":"213 S Hobart Boulevard Los Angeles CA 90004",
    "addr:housenumber":"213",
    "addr:postcode":"90004",
    "addr:street":"S Hobart Boulevard",
    "iso:country":"US",
    "sg:address":"213 S Hobart Boulevard",
    "sg:city":"Los Angeles",
    "sg:classifiers":[
        {
            "category":"Social Services",
            "subcategory":"Child Care",
            "type":"Services"
        }
    ],
    "sg:phone":"+1 213 380 6236",
    "sg:postcode":"90004",
    "sg:province":"CA",
    "sg:tags":[
        "day"
    ],
    "wof:name":"L A First Education Center",
    "wof:placetype":"venue"
},
  "geometry": {"coordinates":[-118.305357,34.070689],"type":"Point"}
}