{
  "type": "Feature",
  "properties": {
    "iso:country":"US",
    "sg:address":"13512 Newhope St",
    "sg:city":"Garden Grove",
    "sg:classifiers":[
        {
            "category":"Professional",
            "subcategory":"Lawyer & Legal Services",
            "type":"Services"
        }
    ],
    "sg:phone":"+1 714 534 0500",
    "sg:postcode":"92843",
    "sg:province":"CA",
    "wof:name":"Lexington Law Firm CA",
    "wof:placetype":"venue"
},
  "geometry": {"coordinates":[-117.929185,33.76681],"type":"Point"}
}