{
  "type": "Feature",
  "properties": {
    "iso:country":"US",
    "sg:address":"1655 E G St",
    "sg:city":"Ontario",
    "sg:classifiers":[
        {
            "category":"Home & Garden",
            "subcategory":"Furniture",
            "type":"Retail Goods"
        }
    ],
    "sg:phone":"+1 909 445 1730",
    "sg:postcode":"91764",
    "sg:province":"CA",
    "sg:tags":[
        "house",
        "furnishing"
    ],
    "wof:name":"B & I Home Decor",
    "wof:placetype":"venue"
},
  "geometry": {"coordinates":[-117.61685300000001,34.070788],"type":"Point"}
}