{
  "type": "Feature",
  "properties": {
    "iso:country":"US",
    "sg:address":"4149 Suisun Valley Rd",
    "sg:city":"Fairfield",
    "sg:classifiers":[
        {
            "category":"Real Estate",
            "subcategory":"Real Estate Agent",
            "type":"Services"
        }
    ],
    "sg:phone":"+1 707 864 4965",
    "sg:postcode":"94534",
    "sg:province":"CA",
    "wof:name":"Catalina Olivo",
    "wof:placetype":"venue"
},
  "geometry": {"coordinates":[-122.123778,38.240336],"type":"Point"}
}