{
  "type": "Feature",
  "properties": {
    "iso:country":"US",
    "sg:address":"25 W Valley St",
    "sg:city":"Pasadena",
    "sg:classifiers":[
        {
            "category":"Manufacturing",
            "subcategory":"Printing",
            "type":"Manufacturing & Wholesale Goods"
        }
    ],
    "sg:phone":"+1 626 449 0393",
    "sg:postcode":"91105",
    "sg:province":"CA",
    "sg:tags":[
        "commercial"
    ],
    "wof:name":"T-Graphics Sign Co",
    "wof:placetype":"venue"
},
  "geometry": {"coordinates":[-118.152295,34.142482],"type":"Point"}
}