{
  "type": "Feature",
  "properties": {
    "addr:full":"56059 Winged Foot La Quinta CA 92253",
    "addr:housenumber":"56059",
    "addr:postcode":"92253",
    "addr:street":"Winged Foot",
    "iso:country":"US",
    "sg:address":"56059 Winged Foot",
    "sg:city":"La Quinta",
    "sg:classifiers":[
        {
            "category":"Wholesale",
            "subcategory":"Medical Equipment & Supplies",
            "type":"Manufacturing & Wholesale Goods"
        }
    ],
    "sg:phone":"+1 760 564 9853",
    "sg:postcode":"92253",
    "sg:province":"CA",
    "sg:tags":[
        "orthopedic"
    ],
    "wof:name":"SWB Elbow Brace Ltd",
    "wof:placetype":"venue"
},
  "geometry": {"coordinates":[-116.251165,33.643495],"type":"Point"}
}