{
  "type": "Feature",
  "properties": {
    "addr:full":"48873 Kato Rd Fremont CA 94539",
    "addr:housenumber":"48873",
    "addr:postcode":"94539",
    "addr:street":"Kato Rd",
    "iso:country":"US",
    "sg:address":"48873 Kato Rd",
    "sg:city":"Fremont",
    "sg:classifiers":[
        {
            "category":"Shopping",
            "subcategory":"Computers & Home Electronics",
            "type":"Retail Goods"
        }
    ],
    "sg:phone":"+1 510 438 0373",
    "sg:postcode":"94539",
    "sg:province":"CA",
    "sg:tags":[
        "software"
    ],
    "sg:website":"www.mediafactoryinc.com",
    "wof:name":"Media Factory Inc",
    "wof:placetype":"venue"
},
  "geometry": {"coordinates":[-121.91858499999999,37.462179],"type":"Point"}
}