{
  "type": "Feature",
  "properties": {
    "iso:country":"US",
    "sg:address":"20592 Laguna Canyon Rd",
    "sg:city":"Laguna Beach",
    "sg:classifiers":[
        {
            "category":"Retail",
            "subcategory":"Pet Boarding",
            "type":"Services"
        }
    ],
    "sg:phone":"+1 949 494 0142",
    "sg:postcode":"92651",
    "sg:province":"CA",
    "sg:tags":[
        "boarding/pet",
        "sitting"
    ],
    "sg:website":"coastalkennels.net",
    "wof:name":"Coastal Kennels",
    "wof:placetype":"venue"
},
  "geometry": {"coordinates":[-117.76301100000001,33.572275],"type":"Point"}
}