{
  "type": "Feature",
  "properties": {
    "iso:country":"US",
    "sg:address":"7111 Talbert",
    "sg:city":"Huntington Beach",
    "sg:classifiers":[
        {
            "category":"Place Of Worship",
            "subcategory":"Church",
            "type":"Public Place"
        }
    ],
    "sg:postcode":"92647",
    "sg:province":"CA",
    "sg:website":"www.churchalivehb.com",
    "wof:name":"Church ALIVE",
    "wof:placetype":"venue"
},
  "geometry": {"coordinates":[-118.004279,33.701546],"type":"Point"}
}