{
  "type": "Feature",
  "properties": {
    "addr:full":"625 Beachcomber Dr Seal Beach CA 90740",
    "addr:housenumber":"625",
    "addr:postcode":"90740",
    "addr:street":"Beachcomber Dr",
    "iso:country":"US",
    "sg:address":"625 Beachcomber Dr",
    "sg:city":"Seal Beach",
    "sg:classifiers":[
        {
            "category":"Wholesale",
            "subcategory":"Durable Goods & Equipment",
            "type":"Manufacturing & Wholesale Goods"
        }
    ],
    "sg:phone":"+1 562 493 2049",
    "sg:postcode":"90740",
    "sg:province":"CA",
    "wof:name":"Prestige Fund Raising",
    "wof:placetype":"venue"
},
  "geometry": {"coordinates":[-118.095248,33.747663],"type":"Point"}
}