{
  "type": "Feature",
  "properties": {
    "iso:country":"US",
    "sg:address":"546 W Holt Blvd",
    "sg:city":"Ontario",
    "sg:classifiers":[
        {
            "category":"Autos & Motor Vehicles",
            "subcategory":"Automobile Sales",
            "type":"Retail Goods"
        }
    ],
    "sg:phone":"+1 909 984 3100",
    "sg:postcode":"91762",
    "sg:province":"CA",
    "sg:tags":[
        "car",
        "dealer"
    ],
    "wof:name":"V & I Auto Sales",
    "wof:placetype":"venue"
},
  "geometry": {"coordinates":[-117.656097,34.06343],"type":"Point"}
}