{
  "type": "Feature",
  "properties": {
    "addr:full":"57 Marlow Dr Oakland CA 94605",
    "addr:housenumber":"57",
    "addr:postcode":"94605",
    "addr:street":"Marlow Dr",
    "iso:country":"US",
    "sg:address":"57 Marlow Dr",
    "sg:city":"Oakland",
    "sg:classifiers":[
        {
            "category":"Shopping",
            "subcategory":"Clothing, Apparel, & Fashions",
            "type":"Retail Goods"
        }
    ],
    "sg:phone":"+1 510 562 6046",
    "sg:postcode":"94605",
    "sg:province":"CA",
    "sg:tags":[
        "theatrical",
        "instruction",
        "art",
        "dancing",
        "performing",
        "costume"
    ],
    "wof:name":"Casa Folklorica",
    "wof:placetype":"venue"
},
  "geometry": {"coordinates":[-122.138851,37.73559],"type":"Point"}
}