{
  "type": "Feature",
  "properties": {
    "addr:full":"569 N Mountain Ave Upland CA 91786",
    "addr:housenumber":"569",
    "addr:postcode":"91786",
    "addr:street":"N Mountain Ave",
    "iso:country":"US",
    "sg:address":"569 N Mountain Ave",
    "sg:city":"Upland",
    "sg:classifiers":[
        {
            "category":"Banks & Credit Unions",
            "subcategory":"Bank",
            "type":"Services"
        }
    ],
    "sg:phone":"+1 909 946 9800",
    "sg:postcode":"91786",
    "sg:province":"CA",
    "sg:tags":[
        "escrow"
    ],
    "wof:name":"Escrow Options",
    "wof:placetype":"venue"
},
  "geometry": {"coordinates":[-117.670261,34.103112],"type":"Point"}
}