{
  "type": "Feature",
  "properties": {
    "addr:full":"709 Randolph Avenue Costa Mesa CA 92626",
    "addr:housenumber":"709",
    "addr:postcode":"92626",
    "addr:street":"Randolph Avenue",
    "iso:country":"US",
    "sg:address":"709 Randolph Avenue",
    "sg:city":"Costa Mesa",
    "sg:classifiers":[
        {
            "category":"Sports & Exercise",
            "subcategory":"Gym",
            "type":"Entertainment"
        }
    ],
    "sg:phone":"+1 714 979 2936",
    "sg:postcode":"92626",
    "sg:province":"CA",
    "sg:tags":[
        "trainer"
    ],
    "wof:name":"Aline Conditioning",
    "wof:placetype":"venue"
},
  "geometry": {"coordinates":[-117.886905,33.676612],"type":"Point"}
}