{
  "type": "Feature",
  "properties": {
    "addr:full":"1 Straw Flower Irvine CA 92620",
    "addr:housenumber":"1",
    "addr:postcode":"92620",
    "addr:street":"Straw Flower",
    "iso:country":"US",
    "sg:address":"1 Straw Flower",
    "sg:city":"Irvine",
    "sg:classifiers":[
        {
            "category":"Professional",
            "type":"Services"
        }
    ],
    "sg:phone":"+1 714 505 1966",
    "sg:postcode":"92620",
    "sg:province":"CA",
    "wof:name":"Toylight Zone",
    "wof:placetype":"venue"
},
  "geometry": {"coordinates":[-117.757948,33.727982],"type":"Point"}
}