{
  "type": "Feature",
  "properties": {
    "iso:country":"US",
    "sg:address":"721 56th St",
    "sg:city":"Sacramento",
    "sg:classifiers":[
        {
            "category":"Retail",
            "subcategory":"Animal Services",
            "type":"Services"
        }
    ],
    "sg:phone":"+1 916 556 1155",
    "sg:postcode":"95819",
    "sg:province":"CA",
    "sg:tags":[
        "shelter"
    ],
    "sg:website":"www.happytails.org",
    "wof:name":"Happy Tails Pet Sanctuary",
    "wof:placetype":"venue"
},
  "geometry": {"coordinates":[-121.434028,38.56762],"type":"Point"}
}