{
  "type": "Feature",
  "properties": {
    "iso:country":"US",
    "sg:address":"31 W Broadway",
    "sg:city":"Long Beach",
    "sg:classifiers":[
        {
            "category":"Restaurant",
            "type":"Food & Drink"
        }
    ],
    "sg:phone":"+1 562 436 2111",
    "sg:postcode":"90802",
    "sg:province":"CA",
    "sg:tags":[
        "mexican"
    ],
    "wof:name":"Carnitas Michoacan",
    "wof:placetype":"venue"
},
  "geometry": {"coordinates":[-118.184352,33.767072],"type":"Point"}
}