{
  "type": "Feature",
  "properties": {
    "addr:full":"2495 Estand Way Pleasant Hill CA 94523",
    "addr:housenumber":"2495",
    "addr:postcode":"94523",
    "addr:street":"Estand Way",
    "iso:country":"US",
    "sg:address":"2495 Estand Way",
    "sg:city":"Pleasant Hill",
    "sg:classifiers":[
        {
            "category":"Wholesale",
            "subcategory":"Electrical",
            "type":"Manufacturing & Wholesale Goods"
        }
    ],
    "sg:phone":"+1 925 887 5600",
    "sg:postcode":"94523",
    "sg:province":"CA",
    "sg:tags":[
        "alarm",
        "burglar",
        "system"
    ],
    "wof:name":"A H M Security Inc",
    "wof:placetype":"venue"
},
  "geometry": {"coordinates":[-122.053493,37.940537],"type":"Point"}
}