{
  "type": "Feature",
  "properties": {
    "addr:full":"5217 Hollywood Blvd Los Angeles CA 90027",
    "addr:housenumber":"5217",
    "addr:postcode":"90027",
    "addr:street":"Hollywood Blvd",
    "iso:country":"US",
    "sg:address":"5217 Hollywood Blvd",
    "sg:city":"Los Angeles",
    "sg:classifiers":[
        {
            "category":"Real Estate",
            "subcategory":"Real Estate Operator",
            "type":"Services"
        }
    ],
    "sg:phone":"+1 323 469 2711",
    "sg:postcode":"90027",
    "sg:province":"CA",
    "sg:tags":[
        "apartment"
    ],
    "wof:name":"New Hollywood Apartments",
    "wof:placetype":"venue"
},
  "geometry": {"coordinates":[-118.303888,34.101825],"type":"Point"}
}