{
  "type": "Feature",
  "properties": {
    "iso:country":"US",
    "sg:address":"3755 6th Ave",
    "sg:city":"San Diego",
    "sg:classifiers":[
        {
            "category":"Shopping",
            "type":"Retail Goods"
        }
    ],
    "sg:phone":"+1 619 291 8047",
    "sg:postcode":"92103",
    "sg:province":"CA",
    "sg:tags":[
        "picture",
        "frame"
    ],
    "wof:name":"Great Frame Up",
    "wof:placetype":"venue"
},
  "geometry": {"coordinates":[-117.159449,32.746894],"type":"Point"}
}