{
  "type": "Feature",
  "properties": {
    "iso:country":"US",
    "sg:address":"90 Pso del Sol",
    "sg:city":"Rcho Sta Marg",
    "sg:classifiers":[
        {
            "category":"Professional",
            "subcategory":"Business Services",
            "type":"Services"
        }
    ],
    "sg:phone":"+1 949 766 3231",
    "sg:postcode":"92688",
    "sg:province":"CA",
    "sg:tags":[
        "interior",
        "consultant",
        "design",
        "decorator"
    ],
    "wof:name":"Beautiful Interiors",
    "wof:placetype":"venue"
},
  "geometry": {"coordinates":[-117.62007199999999,33.652682],"type":"Point"}
}