{
  "type": "Feature",
  "properties": {
    "addr:full":"1133 High St Auburn CA 95603",
    "addr:housenumber":"1133",
    "addr:postcode":"ca 95603",
    "addr:street":"High St",
    "iso:country":"US",
    "sg:address":"1133 High St",
    "sg:city":"Auburn",
    "sg:classifiers":[
        {
            "category":"Professional",
            "type":"Services"
        }
    ],
    "sg:phone":"+1 530 888 7803",
    "sg:postcode":"95603",
    "sg:province":"CA",
    "sg:tags":[
        "establishment"
    ],
    "sg:website":"www.audiopartners.com",
    "wof:name":"Audio Partners Inc",
    "wof:placetype":"venue"
},
  "geometry": {"coordinates":[-121.071472,38.897052],"type":"Point"}
}