{
  "type": "Feature",
  "properties": {
    "iso:country":"US",
    "sg:address":"5626 Van Nuys Blvd",
    "sg:city":"Van Nuys",
    "sg:classifiers":[
        {
            "category":"Insurance",
            "subcategory":"Insurance Agent",
            "type":"Services"
        }
    ],
    "sg:phone":"+1 818 947 1555",
    "sg:postcode":"91401",
    "sg:province":"CA",
    "wof:name":"Eastwood Insurance Svc",
    "wof:placetype":"venue"
},
  "geometry": {"coordinates":[-118.448632,34.175268],"type":"Point"}
}