{
  "type": "Feature",
  "properties": {
    "iso:country":"US",
    "sg:address":"244 S Oxford Avenue Suite 9",
    "sg:city":"Los Angeles",
    "sg:classifiers":[
        {
            "category":"Health Services",
            "subcategory":"Doctor",
            "type":"Services"
        }
    ],
    "sg:phone":"+1 213 382 1770",
    "sg:postcode":"90004",
    "sg:province":"CA",
    "wof:name":"Oxford Medical Clinic",
    "wof:placetype":"venue"
},
  "geometry": {"coordinates":[-118.30788,34.070169],"type":"Point"}
}