{
  "type": "Feature",
  "properties": {
    "addr:full":"411 Connor Cir Sacramento CA 95835",
    "addr:housenumber":"411",
    "addr:postcode":"95835",
    "addr:street":"Connor Cir",
    "iso:country":"US",
    "sg:address":"411 Connor Cir",
    "sg:city":"Sacramento",
    "sg:classifiers":[
        {
            "category":"Communications",
            "type":"Services"
        }
    ],
    "sg:phone":"+1 916 419 0909",
    "sg:postcode":"95835",
    "sg:province":"CA",
    "wof:name":"Real Wire Home Solutions",
    "wof:placetype":"venue"
},
  "geometry": {"coordinates":[-121.502663,38.663343],"type":"Point"}
}