{
  "type": "Feature",
  "properties": {
    "iso:country":"US",
    "sg:address":"2694 Bishop Dr",
    "sg:city":"San Ramon",
    "sg:classifiers":[
        {
            "category":"Banks & Credit Unions",
            "subcategory":"Bank",
            "type":"Services"
        }
    ],
    "sg:phone":"+1 925 244 1693",
    "sg:postcode":"94583",
    "sg:province":"CA",
    "sg:tags":[
        "financing"
    ],
    "wof:name":"Beneficial Management Corp",
    "wof:placetype":"venue"
},
  "geometry": {"coordinates":[-121.960239,37.763691],"type":"Point"}
}