{
  "type": "Feature",
  "properties": {
    "iso:country":"US",
    "sg:address":"344 E Foothill Blvd",
    "sg:city":"Pomona",
    "sg:classifiers":[
        {
            "category":"Retail",
            "subcategory":"Auto Repair",
            "type":"Services"
        }
    ],
    "sg:phone":"+1 909 596 5752",
    "sg:postcode":"91767",
    "sg:province":"CA",
    "sg:tags":[
        "automotive"
    ],
    "wof:name":"Hac & Mac Brake Algnmt Spclist",
    "wof:placetype":"venue"
},
  "geometry": {"coordinates":[-117.742714,34.107102],"type":"Point"}
}