{
  "type": "Feature",
  "properties": {
    "addr:full":"2122 Auto Park Way Escondido CA 92029",
    "addr:housenumber":"2122",
    "addr:postcode":"92029",
    "addr:street":"Auto Park Way",
    "iso:country":"US",
    "sg:address":"2122 Auto Park Way",
    "sg:city":"Escondido",
    "sg:classifiers":[
        {
            "category":"Retail",
            "subcategory":"Repair Shop",
            "type":"Services"
        },
        {
            "category":"Shopping",
            "subcategory":"Computers & Home Electronics",
            "type":"Retail Goods"
        },
        {
            "category":"Manufacturing",
            "subcategory":"Motor Vehicles & Parts",
            "type":"Manufacturing & Wholesale Goods"
        },
        {
            "category":"Wholesale",
            "subcategory":"Office Equipment",
            "type":"Manufacturing & Wholesale Goods"
        },
        {
            "category":"Manufacturing",
            "subcategory":"Electronics",
            "type":"Manufacturing & Wholesale Goods"
        },
        {
            "category":"Professional",
            "subcategory":"Printing & Photocopies",
            "type":"Services"
        },
        {
            "category":"Professional",
            "subcategory":"Computer Services",
            "type":"Services"
        },
        {
            "category":"Shopping",
            "subcategory":"Stationery & Office Supplies",
            "type":"Retail Goods"
        },
        {
            "category":"Manufacturing",
            "subcategory":"Printing",
            "type":"Manufacturing & Wholesale Goods"
        }
    ],
    "sg:phone":"+1 760 738 3836",
    "sg:postcode":"92029",
    "sg:province":"CA",
    "sg:tags":[
        "scanning",
        "fax",
        "printer",
        "copier",
        "duplicating",
        "machine",
        "copying",
        "equipment-service",
        "printers-equipment",
        "copy",
        "supplies-wholesale",
        "plotting",
        "manufacturer"
    ],
    "sg:website":"http://www.copycaresd.com",
    "wof:name":"Copycare Of San Diego Inc",
    "wof:placetype":"venue"
},
  "geometry": {"coordinates":[-117.11192699999999,33.119336],"type":"Point"}
}