{
  "type": "Feature",
  "properties": {
    "addr:full":"2261 Lichen Ln Tustin CA 92780",
    "addr:housenumber":"2261",
    "addr:postcode":"92780",
    "addr:street":"Lichen Ln",
    "iso:country":"US",
    "sg:address":"2261 Lichen Ln",
    "sg:city":"Tustin",
    "sg:classifiers":[
        {
            "category":"Professional",
            "subcategory":"Computer Services",
            "type":"Services"
        }
    ],
    "sg:phone":"+1 714 730 2077",
    "sg:postcode":"92780",
    "sg:province":"CA",
    "sg:tags":[
        "information",
        "technology"
    ],
    "wof:name":"Appareo Inc",
    "wof:placetype":"venue"
},
  "geometry": {"coordinates":[-117.807225,33.724191],"type":"Point"}
}