{
  "type": "Feature",
  "properties": {
    "iso:country":"US",
    "sg:address":"25881 Pinewood Ln",
    "sg:city":"Laguna Hills",
    "sg:classifiers":[
        {
            "category":"Health Services",
            "subcategory":"Nursing And Care Facility",
            "type":"Services"
        }
    ],
    "sg:phone":"+1 949 859 8547",
    "sg:postcode":"92653",
    "sg:province":"CA",
    "sg:tags":[
        "home",
        "rest"
    ],
    "wof:name":"B & B's Country Manor Inc",
    "wof:placetype":"venue"
},
  "geometry": {"coordinates":[-117.676586,33.592677],"type":"Point"}
}