{
  "type": "Feature",
  "properties": {
    "iso:country":"US",
    "sg:address":"20 E Foothill Blvd",
    "sg:city":"Arcadia",
    "sg:classifiers":[
        {
            "category":"Retail",
            "subcategory":"Animal Services",
            "type":"Services"
        }
    ],
    "sg:phone":"+1 626 574 9900",
    "sg:postcode":"91006",
    "sg:province":"CA",
    "wof:name":"Class Racing Stable",
    "wof:placetype":"venue"
},
  "geometry": {"coordinates":[-118.03078499999999,34.150902],"type":"Point"}
}