{
  "type": "Feature",
  "properties": {
    "addr:full":"38350 Fremont Blvd Fremont CA 94536",
    "addr:housenumber":"38350",
    "addr:postcode":"94536",
    "addr:street":"Fremont Blvd",
    "iso:country":"US",
    "sg:address":"38350 Fremont Blvd",
    "sg:city":"Fremont",
    "sg:classifiers":[
        {
            "category":"Health Services",
            "subcategory":"Doctor",
            "type":"Services"
        }
    ],
    "sg:phone":"+1 510 795 7786",
    "sg:postcode":"94536",
    "sg:province":"CA",
    "sg:tags":[
        "dentist"
    ],
    "wof:name":"Star Brite Dental",
    "wof:placetype":"venue"
},
  "geometry": {"coordinates":[-121.997901,37.553564],"type":"Point"}
}