{
  "type": "Feature",
  "properties": {
    "addr:full":"4865 Mancini Dr Castro Valley CA 94546",
    "addr:postcode":"4865;94546",
    "addr:street":"Mancini Dr",
    "iso:country":"US",
    "sg:address":"4865 Mancini Dr",
    "sg:city":"Castro Valley",
    "sg:classifiers":[
        {
            "category":"Manufacturing",
            "subcategory":"Tools & Machinery",
            "type":"Manufacturing & Wholesale Goods"
        }
    ],
    "sg:phone":"+1 510 537 1394",
    "sg:postcode":"94546",
    "sg:province":"CA",
    "sg:tags":[
        "textile",
        "mfg"
    ],
    "wof:name":"Quatum Graphics Studios",
    "wof:placetype":"venue"
},
  "geometry": {"coordinates":[-122.06792,37.709614],"type":"Point"}
}