{
  "type": "Feature",
  "properties": {
    "addr:full":"4752 Mission St San Francisco CA 94112",
    "addr:housenumber":"4752",
    "addr:postcode":"94112",
    "addr:street":"Mission St",
    "iso:country":"US",
    "sg:address":"4752 Mission St",
    "sg:city":"San Francisco",
    "sg:classifiers":[
        {
            "category":"Organizations",
            "subcategory":"Non-profit Organization",
            "type":"Services"
        }
    ],
    "sg:phone":"+1 415 841 8820",
    "sg:postcode":"94112",
    "sg:province":"CA",
    "sg:website":"www.sfphp.org",
    "wof:name":"Parents Helping Parents",
    "wof:placetype":"venue"
},
  "geometry": {"coordinates":[-122.436944,37.722059],"type":"Point"}
}