{
  "type": "Feature",
  "properties": {
    "addr:full":"6477 Almaden Rd San Jose CA 95120",
    "addr:housenumber":"6477",
    "addr:postcode":"95120",
    "addr:street":"Almaden Rd",
    "iso:country":"US",
    "sg:address":"6477 Almaden Rd",
    "sg:city":"San Jose",
    "sg:classifiers":[
        {
            "category":"Food & Beverages",
            "subcategory":"Groceries & Convenience Stores",
            "type":"Retail Goods"
        }
    ],
    "sg:phone":"+1 408 268 3511",
    "sg:postcode":"95120",
    "sg:province":"CA",
    "sg:website":"www.safeway.com",
    "wof:name":"Safeway",
    "wof:placetype":"venue"
},
  "geometry": {"coordinates":[-121.86933500000001,37.226967],"type":"Point"}
}