{
  "type": "Feature",
  "properties": {
    "addr:full":"Grossmont Shopping Mall 5500 Grossmont Center Dr La Mesa CA 91942",
    "addr:housenumber":"5500",
    "addr:postcode":"91942",
    "addr:street":"Grossmont Center Dr",
    "iso:country":"US",
    "sg:address":"Grossmont Shopping Mall 5500 Grossmont Center Dr",
    "sg:city":"La Mesa",
    "sg:classifiers":[
        {
            "category":"Personal",
            "subcategory":"Hair Removal",
            "type":"Services"
        }
    ],
    "sg:phone":"+1 619 589 0732",
    "sg:postcode":"91942",
    "sg:province":"CA",
    "sg:website":"www.superbrows.com",
    "wof:name":"Super Brows",
    "wof:placetype":"venue"
},
  "geometry": {"coordinates":[-117.010081,32.779644],"type":"Point"}
}