{
  "type": "Feature",
  "properties": {
    "addr:full":"2 Palo Alto Sq Palo Alto CA 94306",
    "addr:housenumber":"2",
    "addr:postcode":"94306",
    "addr:street":"Palo Alto Sq",
    "iso:country":"US",
    "sg:address":"2 Palo Alto Sq",
    "sg:city":"Palo Alto",
    "sg:classifiers":[
        {
            "category":"Professional",
            "subcategory":"Lawyer & Legal Services",
            "type":"Services"
        }
    ],
    "sg:phone":"+1 650 988 8500",
    "sg:postcode":"94306",
    "sg:province":"CA",
    "sg:tags":[
        "attorney"
    ],
    "wof:name":"Fenwick & West",
    "wof:placetype":"venue"
},
  "geometry": {"coordinates":[-122.142521,37.423731],"type":"Point"}
}