{
  "type": "Feature",
  "properties": {
    "addr:full":"10312 Oakdale Ave Chatsworth CA 91311",
    "addr:housenumber":"10312",
    "addr:postcode":"91311",
    "addr:street":"Oakdale Ave",
    "iso:country":"US",
    "sg:address":"10312 Oakdale Ave",
    "sg:city":"Chatsworth",
    "sg:classifiers":[
        {
            "category":"Social Services",
            "subcategory":"Child Care",
            "type":"Services"
        }
    ],
    "sg:phone":"+1 818 832 5051",
    "sg:postcode":"91311",
    "sg:province":"CA",
    "wof:name":"Aj's Daycare",
    "wof:placetype":"venue"
},
  "geometry": {"coordinates":[-118.566642,34.259557],"type":"Point"}
}