{
  "type": "Feature",
  "properties": {
    "addr:full":"973 E San Carlos Ave San Carlos CA 94070",
    "addr:housenumber":"973",
    "addr:postcode":"94070",
    "addr:street":"E San Carlos Ave",
    "iso:country":"US",
    "sg:address":"973 E San Carlos Ave",
    "sg:city":"San Carlos",
    "sg:classifiers":[
        {
            "category":"Shopping",
            "subcategory":"Computers & Home Electronics",
            "type":"Retail Goods"
        }
    ],
    "sg:phone":"+1 650 631 8521",
    "sg:postcode":"94070",
    "sg:province":"CA",
    "sg:website":"www.bayimaging.com",
    "wof:name":"Bay Imaging",
    "wof:placetype":"venue"
},
  "geometry": {"coordinates":[-122.25666699999999,37.509995],"type":"Point"}
}