{
  "type": "Feature",
  "properties": {
    "addr:full":"4644 Alice St San Diego CA 92115",
    "addr:housenumber":"4644",
    "addr:postcode":"92115",
    "addr:street":"Alice St",
    "iso:country":"US",
    "sg:address":"4644 Alice St",
    "sg:city":"San Diego",
    "sg:classifiers":[
        {
            "category":"Professional",
            "subcategory":"Art Services",
            "type":"Services"
        }
    ],
    "sg:phone":"+1 619 280 5180",
    "sg:postcode":"92115",
    "sg:province":"CA",
    "sg:tags":[
        "graphic",
        "designer"
    ],
    "wof:name":"Bonkers' Graphic Design",
    "wof:placetype":"venue"
},
  "geometry": {"coordinates":[-117.07183000000001,32.761823],"type":"Point"}
}