{
  "type": "Feature",
  "properties": {
    "addr:full":"6109 Pickford Pl Elk Grove CA 95758",
    "addr:housenumber":"6109",
    "addr:postcode":"95758",
    "addr:street":"Pickford Pl",
    "iso:country":"US",
    "sg:address":"6109 Pickford Pl",
    "sg:city":"Elk Grove",
    "sg:classifiers":[
        {
            "category":"Social Services",
            "subcategory":"Child Care",
            "type":"Services"
        }
    ],
    "sg:phone":"+1 916 691 2415",
    "sg:postcode":"95758",
    "sg:province":"CA",
    "wof:name":"Little Stars Day Care",
    "wof:placetype":"venue"
},
  "geometry": {"coordinates":[-121.43210500000001,38.432811],"type":"Point"}
}