{
  "type": "Feature",
  "properties": {
    "iso:country":"US",
    "sg:address":"344 E 4th St",
    "sg:city":"Long Beach",
    "sg:classifiers":[
        {
            "category":"Shopping",
            "subcategory":"Pets & Pet Supplies",
            "type":"Retail Goods"
        },
        {
            "category":"Retail",
            "subcategory":"Animal Services",
            "type":"Services"
        }
    ],
    "sg:phone":"+1 562 432 6934",
    "sg:postcode":"90802",
    "sg:province":"CA",
    "sg:tags":[
        "groomers"
    ],
    "sg:website":"soggydoglb.com",
    "wof:name":"Soggy Dog",
    "wof:placetype":"venue"
},
  "geometry": {"coordinates":[-118.188568,33.771712],"type":"Point"}
}