{
  "type": "Feature",
  "properties": {
    "addr:full":"44911 Industrial Dr Fremont CA 94538",
    "addr:housenumber":"44911",
    "addr:postcode":"94538",
    "addr:street":"Industrial Dr",
    "iso:country":"US",
    "sg:address":"44911 Industrial Dr",
    "sg:city":"Fremont",
    "sg:classifiers":[
        {
            "category":"Manufacturing",
            "subcategory":"Tools & Machinery",
            "type":"Manufacturing & Wholesale Goods"
        }
    ],
    "sg:phone":"+1 510 252 0786",
    "sg:postcode":"94538",
    "sg:province":"CA",
    "sg:tags":[
        "equipment",
        "electric",
        "cable"
    ],
    "sg:website":"www.bizconn.com",
    "wof:name":"Bizlink Technology Inc",
    "wof:placetype":"venue"
},
  "geometry": {"coordinates":[-121.951593,37.500217],"type":"Point"}
}