{
  "type": "Feature",
  "properties": {
    "iso:country":"US",
    "sg:address":"2785 Claray Dr",
    "sg:city":"Los Angeles",
    "sg:classifiers":[
        {
            "category":"Travel",
            "subcategory":"Travel Agent",
            "type":"Entertainment"
        }
    ],
    "sg:phone":"+1 310 474 3211",
    "sg:postcode":"90077",
    "sg:province":"CA",
    "sg:tags":[
        "agency"
    ],
    "wof:name":"A-V World Travel Center",
    "wof:placetype":"venue"
},
  "geometry": {"coordinates":[-118.447913,34.122757],"type":"Point"}
}