{
  "type": "Feature",
  "properties": {
    "iso:country":"US",
    "sg:address":"429 Santa Monica Blvd",
    "sg:city":"Santa Monica",
    "sg:classifiers":[
        {
            "category":"Cinema",
            "subcategory":"Movie Theater",
            "type":"Entertainment"
        }
    ],
    "sg:phone":"+1 310 451 3664",
    "sg:postcode":"90401",
    "sg:province":"CA",
    "wof:name":"Screenvision Cinema Network",
    "wof:placetype":"venue"
},
  "geometry": {"coordinates":[-118.494939,34.01663],"type":"Point"}
}