{
  "type": "Feature",
  "properties": {
    "addr:full":"40 Windward Ave Venice CA 90291",
    "addr:housenumber":"40",
    "addr:postcode":"90291",
    "addr:street":"Windward Ave",
    "iso:country":"US",
    "sg:address":"40 Windward Ave",
    "sg:city":"Venice",
    "sg:classifiers":[
        {
            "category":"Shopping",
            "subcategory":"Clothing, Apparel, & Fashions",
            "type":"Retail Goods"
        }
    ],
    "sg:phone":"+1 310 399 1623",
    "sg:postcode":"90291",
    "sg:province":"CA",
    "wof:name":"Red Line",
    "wof:placetype":"venue"
},
  "geometry": {"coordinates":[-118.472495,33.987415],"type":"Point"}
}