{
  "type": "Feature",
  "properties": {
    "addr:full":"31 N Sacramento St Lodi CA 95240",
    "addr:housenumber":"31",
    "addr:postcode":"95240",
    "addr:street":"N Sacramento St",
    "iso:country":"US",
    "sg:address":"31 N Sacramento St",
    "sg:city":"Lodi",
    "sg:classifiers":[
        {
            "category":"Bars & Pubs",
            "type":"Food & Drink"
        }
    ],
    "sg:phone":"+1 209 339 8658",
    "sg:postcode":"95240",
    "sg:province":"CA",
    "sg:tags":[
        "lounge",
        "cocktail"
    ],
    "wof:name":"Jack's Back",
    "wof:placetype":"venue"
},
  "geometry": {"coordinates":[-121.27220800000001,38.135027],"type":"Point"}
}