{
  "type": "Feature",
  "properties": {
    "addr:full":"8701 S Broadway Los Angeles CA 90003",
    "addr:housenumber":"8701",
    "addr:postcode":"90003",
    "addr:street":"S Broadway",
    "iso:country":"US",
    "sg:address":"8701 S Broadway",
    "sg:city":"Los Angeles",
    "sg:classifiers":[
        {
            "category":"Retail",
            "subcategory":"Repair Shop",
            "type":"Services"
        }
    ],
    "sg:phone":"+1 323 753 6339",
    "sg:postcode":"90003",
    "sg:province":"CA",
    "sg:tags":[
        "watch",
        "jewelry"
    ],
    "wof:name":"K S Watch",
    "wof:placetype":"venue"
},
  "geometry": {"coordinates":[-118.27800000000001,33.9585],"type":"Point"}
}