{
  "type": "Feature",
  "properties": {
    "addr:full":"1346 Pacific Ave Santa Cruz CA 95060",
    "addr:housenumber":"1346",
    "addr:postcode":"95060",
    "addr:street":"Pacific Ave",
    "iso:country":"US",
    "sg:address":"1346 Pacific Ave",
    "sg:city":"Santa Cruz",
    "sg:classifiers":[
        {
            "category":"Sports & Exercise",
            "subcategory":"Bicycle Rental",
            "type":"Entertainment"
        }
    ],
    "sg:phone":"+1 831 458 9585",
    "sg:postcode":"95060",
    "sg:province":"CA",
    "sg:tags":[
        "wear"
    ],
    "wof:name":"Hat Company of Santa Cruz",
    "wof:placetype":"venue"
},
  "geometry": {"coordinates":[-122.02600099999999,36.9744],"type":"Point"}
}