{
  "type": "Feature",
  "properties": {
    "addr:full":"236 Sutherland Dr Auburn CA 95603",
    "addr:housenumber":"236",
    "addr:postcode":"ca 95603",
    "addr:street":"Sutherland Dr",
    "iso:country":"US",
    "sg:address":"236 Sutherland Dr",
    "sg:city":"Auburn",
    "sg:classifiers":[
        {
            "category":"Retail",
            "subcategory":"Auto Repair",
            "type":"Services"
        }
    ],
    "sg:phone":"+1 530 823 2285",
    "sg:postcode":"95603",
    "sg:province":"CA",
    "sg:tags":[
        "repairing",
        "automobile",
        "radiator"
    ],
    "wof:name":"Auburn Radiator",
    "wof:placetype":"venue"
},
  "geometry": {"coordinates":[-121.061573,38.919193],"type":"Point"}
}