{
  "type": "Feature",
  "properties": {
    "addr:full":"3077 Clairemont Dr San Diego CA 92117",
    "addr:housenumber":"3077",
    "addr:postcode":"92117",
    "addr:street":"Clairemont Dr",
    "iso:country":"US",
    "sg:address":"3077 Clairemont Dr",
    "sg:city":"San Diego",
    "sg:classifiers":[
        {
            "category":"Personal",
            "subcategory":"Beauty Salon",
            "type":"Services"
        }
    ],
    "sg:phone":"+1 619 275 1526",
    "sg:postcode":"92117",
    "sg:province":"CA",
    "wof:name":"Rose Nails",
    "wof:placetype":"venue"
},
  "geometry": {"coordinates":[-117.193106,32.796972],"type":"Point"}
}