{
  "type": "Feature",
  "properties": {
    "addr:full":"1173 N Dixie Dr San Dimas CA 91773",
    "addr:housenumber":"1173",
    "addr:postcode":"91773",
    "addr:street":"N Dixie Dr",
    "iso:country":"US",
    "sg:address":"1173 N Dixie Dr",
    "sg:city":"San Dimas",
    "sg:classifiers":[
        {
            "category":"Professional",
            "subcategory":"Engineering",
            "type":"Services"
        }
    ],
    "sg:phone":"+1 909 599 1788",
    "sg:postcode":"91773",
    "sg:province":"CA",
    "sg:tags":[
        "engineer"
    ],
    "wof:name":"Mechanical Technology Intl",
    "wof:placetype":"venue"
},
  "geometry": {"coordinates":[-117.800558,34.123399],"type":"Point"}
}