{
  "type": "Feature",
  "properties": {
    "addr:full":"2400 Athens Ave Redding CA 96001",
    "addr:housenumber":"2400",
    "addr:postcode":"96001",
    "addr:street":"Athens Ave",
    "iso:country":"US",
    "sg:address":"2400 Athens Ave",
    "sg:city":"Redding",
    "sg:classifiers":[
        {
            "category":"Shopping",
            "subcategory":"Bicycles & Sporting Goods",
            "type":"Retail Goods"
        }
    ],
    "sg:phone":"+1 530 244 1954",
    "sg:postcode":"96001",
    "sg:province":"CA",
    "wof:name":"Bikes Etc",
    "wof:placetype":"venue"
},
  "geometry": {"coordinates":[-122.376707,40.573088],"type":"Point"}
}