{
  "type": "Feature",
  "properties": {
    "iso:country":"US",
    "sg:address":"23861 McBean Pkwy Ste D16",
    "sg:city":"Valencia",
    "sg:classifiers":[
        {
            "category":"Health Services",
            "subcategory":"Doctor",
            "type":"Services"
        }
    ],
    "sg:phone":"+1 661 253 3008",
    "sg:postcode":"91355",
    "sg:province":"CA",
    "wof:name":"Brar Balbir S MD",
    "wof:placetype":"venue"
},
  "geometry": {"coordinates":[-118.55300099999999,34.396301],"type":"Point"}
}