{
  "type": "Feature",
  "properties": {
    "addr:full":"2157 Lincoln Ave Altadena CA 91001",
    "addr:housenumber":"2157",
    "addr:postcode":"91001",
    "addr:street":"Lincoln Ave",
    "iso:country":"US",
    "sg:address":"2157 Lincoln Ave",
    "sg:city":"Altadena",
    "sg:classifiers":[
        {
            "category":"Fast Food",
            "type":"Food & Drink"
        },
        {
            "category":"Restaurant",
            "type":"Food & Drink"
        }
    ],
    "sg:phone":"+1 626 398 9966",
    "sg:postcode":"91001",
    "sg:province":"CA",
    "sg:website":"http://www.mcdonalds.com",
    "wof:name":"McDonald's",
    "wof:placetype":"venue"
},
  "geometry": {"coordinates":[-118.160095,34.182605],"type":"Point"}
}