{
  "type": "Feature",
  "properties": {
    "addr:full":"3131 Middlefield Rd Redwood City CA 94063",
    "addr:housenumber":"3131",
    "addr:postcode":"94063",
    "addr:street":"Middlefield Rd",
    "iso:country":"US",
    "sg:address":"3131 Middlefield Rd",
    "sg:city":"Redwood City",
    "sg:classifiers":[
        {
            "category":"Shopping",
            "subcategory":"Gifts & Souvenirs",
            "type":"Retail Goods"
        }
    ],
    "sg:phone":"+1 650 364 7400",
    "sg:postcode":"94063",
    "sg:province":"CA",
    "sg:tags":[
        "shop"
    ],
    "wof:name":"Villa Latina",
    "wof:placetype":"venue"
},
  "geometry": {"coordinates":[-122.204519,37.472153],"type":"Point"}
}