{
  "type": "Feature",
  "properties": {
    "iso:country":"US",
    "sg:address":"512 Westline Dr",
    "sg:city":"Alameda",
    "sg:classifiers":[
        {
            "category":"Banks & Credit Unions",
            "subcategory":"Investment Brokerage",
            "type":"Services"
        },
        {
            "category":"Banks & Credit Unions",
            "subcategory":"Financial Services",
            "type":"Services"
        }
    ],
    "sg:phone":"+1 510 522 3020",
    "sg:postcode":"94501",
    "sg:province":"CA",
    "sg:tags":[
        "advisory",
        "planning",
        "retirement",
        "planner"
    ],
    "wof:name":"Bluewater Funding",
    "wof:placetype":"venue"
},
  "geometry": {"coordinates":[-122.27153,37.764231],"type":"Point"}
}