{
  "type": "Feature",
  "properties": {
    "iso:country":"US",
    "sg:address":"11837 Molette St",
    "sg:city":"Norwalk",
    "sg:classifiers":[
        {
            "category":"Autos & Motor Vehicles",
            "subcategory":"Auto Supplies",
            "type":"Retail Goods"
        }
    ],
    "sg:phone":"+1 562 863 7476",
    "sg:postcode":"90650",
    "sg:province":"CA",
    "sg:tags":[
        "automobile",
        "part",
        "accessory"
    ],
    "wof:name":"Jose Body Shop",
    "wof:placetype":"venue"
},
  "geometry": {"coordinates":[-118.081607,33.891734],"type":"Point"}
}