{
  "type": "Feature",
  "properties": {
    "iso:country":"US",
    "sg:address":"2373 E Washington Blvd",
    "sg:city":"Pasadena",
    "sg:classifiers":[
        {
            "category":"Building & Trades",
            "subcategory":"Construction",
            "type":"Services"
        }
    ],
    "sg:phone":"+1 626 798 8068",
    "sg:postcode":"91104",
    "sg:province":"CA",
    "sg:tags":[
        "coping",
        "plastering",
        "tiling",
        "pool",
        "swimming"
    ],
    "wof:name":"Swim Con Pool Co",
    "wof:placetype":"venue"
},
  "geometry": {"coordinates":[-118.100779,34.169207],"type":"Point"}
}