{
  "type": "Feature",
  "properties": {
    "iso:country":"US",
    "sg:address":"477 N. El Camino Real Ste 105",
    "sg:city":"Encinitas",
    "sg:classifiers":[
        {
            "category":"Health Services",
            "subcategory":"Clinic",
            "type":"Services"
        }
    ],
    "sg:phone":"+1 760 942 2256",
    "sg:postcode":"92024",
    "sg:province":"CA",
    "sg:tags":[
        "medical"
    ],
    "wof:name":"Imaging Healthcare Specialists",
    "wof:placetype":"venue"
},
  "geometry": {"coordinates":[-117.262518,33.057309],"type":"Point"}
}