{
  "type": "Feature",
  "properties": {
    "addr:full":"1004 W Foothill Blvd Upland CA 91786",
    "addr:housenumber":"1004",
    "addr:postcode":"91786",
    "addr:street":"W Foothill Blvd",
    "iso:country":"US",
    "sg:address":"1004 W Foothill Blvd",
    "sg:city":"Upland",
    "sg:classifiers":[
        {
            "category":"Retail",
            "subcategory":"Auto Repair",
            "type":"Services"
        }
    ],
    "sg:phone":"+1 909 985 1366",
    "sg:postcode":"91786",
    "sg:province":"CA",
    "sg:tags":[
        "wrecker"
    ],
    "wof:name":"American Towing Alliance",
    "wof:placetype":"venue"
},
  "geometry": {"coordinates":[-117.66170200000001,34.106906],"type":"Point"}
}