{
  "type": "Feature",
  "properties": {
    "addr:full":"3081 E Clinton Ave Fresno CA 93703",
    "addr:housenumber":"3081",
    "addr:postcode":"93703",
    "addr:street":"E Clinton Ave",
    "iso:country":"US",
    "sg:address":"3081 E Clinton Ave",
    "sg:city":"Fresno",
    "sg:classifiers":[
        {
            "category":"Government",
            "subcategory":"Post Office",
            "type":"Public Place"
        }
    ],
    "sg:phone":"+1 559 229 1300",
    "sg:postcode":"93703",
    "sg:province":"CA",
    "wof:name":"Clinter Station",
    "wof:placetype":"venue"
},
  "geometry": {"coordinates":[-119.774356,36.77235],"type":"Point"}
}