{
  "type": "Feature",
  "properties": {
    "addr:full":"3071 W Shaw Ave Fresno CA 93711",
    "addr:housenumber":"3071",
    "addr:postcode":"93711",
    "addr:street":"W Shaw Ave",
    "iso:country":"US",
    "sg:address":"3071 W Shaw Ave",
    "sg:city":"Fresno",
    "sg:classifiers":[
        {
            "category":"Restaurant",
            "type":"Food & Drink"
        }
    ],
    "sg:phone":"+1 559 225 6900",
    "sg:postcode":"93711",
    "sg:province":"CA",
    "wof:name":"Subway Sandwiches & Salads",
    "wof:placetype":"venue"
},
  "geometry": {"coordinates":[-119.847724,36.808206],"type":"Point"}
}