{
  "type": "Feature",
  "properties": {
    "iso:country":"US",
    "sg:address":"5100 Figueroa Mountain Rd",
    "sg:city":"Los Olivos",
    "sg:classifiers":[
        {
            "category":"Education",
            "subcategory":"School",
            "type":"Public Place"
        }
    ],
    "sg:phone":"+1 805 688 5440",
    "sg:postcode":"93441",
    "sg:province":"CA",
    "wof:name":"Family School",
    "wof:placetype":"venue"
},
  "geometry": {"coordinates":[-120.088448,34.734268],"type":"Point"}
}