{
  "type": "Feature",
  "properties": {
    "iso:country":"US",
    "sg:address":"5422 W Rosecrans Ave",
    "sg:city":"Hawthorne",
    "sg:classifiers":[
        {
            "category":"Professional",
            "subcategory":"Management & Consulting",
            "type":"Services"
        }
    ],
    "sg:phone":"+1 310 536 0388",
    "sg:postcode":"90250",
    "sg:province":"CA",
    "sg:tags":[
        "logistics"
    ],
    "wof:name":"3pL Logistics Inc.",
    "wof:placetype":"venue"
},
  "geometry": {"coordinates":[-118.374706,33.901751],"type":"Point"}
}