{
  "type": "Feature",
  "properties": {
    "addr:full":"4547 Frontier Way Stockton CA 95215",
    "addr:housenumber":"4547",
    "addr:postcode":"95215",
    "addr:street":"Frontier Way",
    "iso:country":"US",
    "sg:address":"4547 Frontier Way",
    "sg:city":"Stockton",
    "sg:classifiers":[
        {
            "category":"Freight",
            "type":"Transportation"
        }
    ],
    "sg:phone":"+1 209 465 5847",
    "sg:postcode":"95215",
    "sg:province":"CA",
    "sg:tags":[
        "special"
    ],
    "wof:name":"GATX Logistics",
    "wof:placetype":"venue"
},
  "geometry": {"coordinates":[-121.21306800000001,37.910451],"type":"Point"}
}