{
  "type": "Feature",
  "properties": {
    "iso:country":"US",
    "sg:address":"16921 Parthenia St",
    "sg:city":"Northridge",
    "sg:classifiers":[
        {
            "category":"Professional",
            "subcategory":"Computer Services",
            "type":"Services"
        }
    ],
    "sg:phone":"+1 818 891 5886",
    "sg:postcode":"91343",
    "sg:province":"CA",
    "sg:tags":[
        "consultant",
        "designer"
    ],
    "sg:website":"www.coastcoast.com",
    "wof:name":"Coast To Coast Computer Prods",
    "wof:placetype":"venue"
},
  "geometry": {"coordinates":[-118.500493,34.228561],"type":"Point"}
}