{
  "type": "Feature",
  "properties": {
    "addr:full":"4560 Admiralty Way Suite 352 Marina Del Rey CA 90292",
    "addr:housenumber":"4560",
    "addr:postcode":"90292",
    "addr:street":"Admiralty Way Suite 352",
    "iso:country":"US",
    "sg:address":"4560 Admiralty Way Suite 352",
    "sg:city":"Marina Del Rey",
    "sg:classifiers":[
        {
            "category":"Health Services",
            "subcategory":"Doctor",
            "type":"Services"
        }
    ],
    "sg:phone":"+1 310 306 8876",
    "sg:postcode":"90292",
    "sg:province":"CA",
    "wof:name":"Giombetti Robt J MD",
    "wof:placetype":"venue"
},
  "geometry": {"coordinates":[-118.442472,33.983114],"type":"Point"}
}