{
  "type": "Feature",
  "properties": {
    "iso:country":"US",
    "sg:address":"3750 Garnet St",
    "sg:city":"Torrance",
    "sg:classifiers":[
        {
            "category":"Health Services",
            "subcategory":"Nursing And Care Facility",
            "type":"Services"
        }
    ],
    "sg:phone":"+1 310 371 2431",
    "sg:postcode":"90503",
    "sg:province":"CA",
    "sg:tags":[
        "home",
        "convalescent"
    ],
    "wof:name":"Bay Crest Care Ctr",
    "wof:placetype":"venue"
},
  "geometry": {"coordinates":[-118.350359,33.843091],"type":"Point"}
}