{
  "type": "Feature",
  "properties": {
    "addr:full":"2645 Ocean Ave San Francisco CA 94132",
    "addr:housenumber":"2645",
    "addr:postcode":"94132",
    "addr:street":"Ocean Ave",
    "iso:country":"US",
    "sg:address":"2645 Ocean Ave",
    "sg:city":"San Francisco",
    "sg:classifiers":[
        {
            "category":"Health Services",
            "subcategory":"Health Practitioner",
            "type":"Services"
        }
    ],
    "sg:phone":"+1 415 841 1040",
    "sg:postcode":"94132",
    "sg:province":"CA",
    "sg:tags":[
        "homeopath"
    ],
    "wof:name":"Gregory R Manteuffel MD",
    "wof:placetype":"venue"
},
  "geometry": {"coordinates":[-122.474884,37.73233],"type":"Point"}
}