{
  "type": "Feature",
  "properties": {
    "iso:country":"US",
    "sg:address":"1500 Fashion Island Blvd",
    "sg:city":"San Mateo",
    "sg:classifiers":[
        {
            "category":"Shopping",
            "subcategory":"Computers & Home Electronics",
            "type":"Retail Goods"
        }
    ],
    "sg:phone":"+1 650 372 0900",
    "sg:postcode":"94404",
    "sg:province":"CA",
    "sg:tags":[
        "software"
    ],
    "wof:name":"Software Pursuits Inc",
    "wof:placetype":"venue"
},
  "geometry": {"coordinates":[-122.287153,37.557832],"type":"Point"}
}