{
  "type": "Feature",
  "properties": {
    "addr:full":"17440 Crenshaw Blvd Torrance CA 90504",
    "addr:housenumber":"17440",
    "addr:postcode":"90504",
    "addr:street":"Crenshaw Blvd",
    "iso:country":"US",
    "sg:address":"17440 Crenshaw Blvd",
    "sg:city":"Torrance",
    "sg:classifiers":[
        {
            "category":"Shopping",
            "type":"Retail Goods"
        }
    ],
    "sg:phone":"+1 310 719 7088",
    "sg:postcode":"90504",
    "sg:province":"CA",
    "sg:tags":[
        "pet",
        "food",
        "store",
        "supply"
    ],
    "wof:name":"Pets Plus",
    "wof:placetype":"venue"
},
  "geometry": {"coordinates":[-118.327003,33.872601],"type":"Point"}
}