{
  "type": "Feature",
  "properties": {
    "iso:country":"US",
    "sg:address":"2520 Zanker Rd",
    "sg:city":"San Jose",
    "sg:classifiers":[
        {
            "category":"Manufacturing",
            "subcategory":"Electronics",
            "type":"Manufacturing & Wholesale Goods"
        }
    ],
    "sg:phone":"+1 408 435 9445",
    "sg:postcode":"95134",
    "sg:province":"CA",
    "sg:tags":[
        "electronic",
        "component",
        "mfg"
    ],
    "wof:name":"Multi Component 3",
    "wof:placetype":"venue"
},
  "geometry": {"coordinates":[-121.92317799999999,37.387349],"type":"Point"}
}