{
  "type": "Feature",
  "properties": {
    "addr:full":"139 W Hobsonway Blythe CA 92225",
    "addr:housenumber":"139",
    "addr:postcode":"92225",
    "addr:street":"W Hobsonway",
    "iso:country":"US",
    "sg:address":"139 W Hobsonway",
    "sg:city":"Blythe",
    "sg:classifiers":[
        {
            "category":"Banks & Credit Unions",
            "subcategory":"Bank",
            "type":"Services"
        }
    ],
    "sg:phone":"+1 760 921 3662",
    "sg:postcode":"92225",
    "sg:province":"CA",
    "sg:tags":[
        "loan"
    ],
    "wof:name":"Instant Cash",
    "wof:placetype":"venue"
},
  "geometry": {"coordinates":[-114.59706,33.610425],"type":"Point"}
}