{
  "type": "Feature",
  "properties": {
    "addr:full":"372 Florin Rd Sacramento CA 95831",
    "addr:housenumber":"372",
    "addr:postcode":"95831",
    "addr:street":"Florin Rd",
    "iso:country":"US",
    "sg:address":"372 Florin Rd",
    "sg:city":"Sacramento",
    "sg:classifiers":[
        {
            "category":"Professional",
            "subcategory":"Computer Services",
            "type":"Services"
        }
    ],
    "sg:phone":"+1 916 392 5600",
    "sg:postcode":"95831",
    "sg:province":"CA",
    "sg:tags":[
        "consultant",
        "designer"
    ],
    "wof:name":"Fine Line Management",
    "wof:placetype":"venue"
},
  "geometry": {"coordinates":[-121.54114800000001,38.507636],"type":"Point"}
}