{
  "type": "Feature",
  "properties": {
    "addr:full":"4764 Parkwest Dr San Jose CA 95130",
    "addr:housenumber":"4764",
    "addr:postcode":"95130",
    "addr:street":"Parkwest Dr",
    "iso:country":"US",
    "sg:address":"4764 Parkwest Dr",
    "sg:city":"San Jose",
    "sg:classifiers":[
        {
            "category":"Professional",
            "type":"Services"
        }
    ],
    "sg:phone":"+1 408 370 2278",
    "sg:postcode":"95130",
    "sg:province":"CA",
    "wof:name":"Willow Elf Creations",
    "wof:placetype":"venue"
},
  "geometry": {"coordinates":[-121.985558,37.294092],"type":"Point"}
}