{
  "type": "Feature",
  "properties": {
    "iso:country":"US",
    "sg:address":"1747 E Ave Q",
    "sg:city":"Palmdale",
    "sg:classifiers":[
        {
            "category":"Arts & Performance",
            "subcategory":"Theater",
            "type":"Entertainment"
        }
    ],
    "sg:phone":"+1 661 947 6581",
    "sg:postcode":"93550",
    "sg:province":"CA",
    "sg:tags":[
        "magician"
    ],
    "wof:name":"Malloy Modern Magic",
    "wof:placetype":"venue"
},
  "geometry": {"coordinates":[-118.097729,34.58748],"type":"Point"}
}