{
  "type": "Feature",
  "properties": {
    "addr:full":"2449 S Watney Way Fairfield CA 94533",
    "addr:housenumber":"2449",
    "addr:postcode":"94533",
    "addr:street":"S Watney Way",
    "iso:country":"US",
    "sg:address":"2449 S Watney Way",
    "sg:city":"Fairfield",
    "sg:classifiers":[
        {
            "category":"Winery",
            "type":"Food & Drink"
        },
        {
            "category":"Food & Beverages",
            "subcategory":"Liquor & Beverages",
            "type":"Retail Goods"
        },
        {
            "category":"Wholesale",
            "subcategory":"Wine & Distilled Alcoholic Beverages",
            "type":"Manufacturing & Wholesale Goods"
        }
    ],
    "sg:phone":"+1 707 426 1746",
    "sg:postcode":"94533",
    "sg:province":"CA",
    "sg:tags":[
        "broker"
    ],
    "wof:name":"Grateful Palate The",
    "wof:placetype":"venue"
},
  "geometry": {"coordinates":[-122.07512,38.232501],"type":"Point"}
}