{
  "type": "Feature",
  "properties": {
    "addr:full":"120 W Walnut St Santa Ana CA 92701",
    "addr:housenumber":"120",
    "addr:postcode":"92701",
    "addr:street":"W Walnut St",
    "iso:country":"US",
    "sg:address":"120 W Walnut St",
    "sg:city":"Santa Ana",
    "sg:classifiers":[
        {
            "category":"Government",
            "subcategory":"Fire Station",
            "type":"Public Place"
        }
    ],
    "sg:phone":"+1 714 647 5700",
    "sg:postcode":"92701",
    "sg:province":"CA",
    "sg:tags":[
        "protection"
    ],
    "wof:name":"Santa Ana Fire Dept",
    "wof:placetype":"venue"
},
  "geometry": {"coordinates":[-117.868487,33.744342],"type":"Point"}
}