{
  "type": "Feature",
  "properties": {
    "iso:country":"US",
    "sg:address":"5260 Anna Ave",
    "sg:city":"San Diego",
    "sg:classifiers":[
        {
            "category":"Freight",
            "type":"Transportation"
        }
    ],
    "sg:phone":"+1 619 293 1498",
    "sg:postcode":"92110",
    "sg:province":"CA",
    "sg:tags":[
        "general"
    ],
    "wof:name":"San Diego Union Tribune",
    "wof:placetype":"venue"
},
  "geometry": {"coordinates":[-117.201262,32.763167],"type":"Point"}
}