{
  "type": "Feature",
  "properties": {
    "iso:country":"US",
    "sg:address":"1515 E Alluvial Ave",
    "sg:city":"Fresno",
    "sg:classifiers":[
        {
            "category":"Health Services",
            "subcategory":"Doctor",
            "type":"Services"
        }
    ],
    "sg:phone":"+1 559 299 1515",
    "sg:postcode":"93720",
    "sg:province":"CA",
    "sg:tags":[
        "physician",
        "surgeon"
    ],
    "wof:name":"Margolin Brain Institute",
    "wof:placetype":"venue"
},
  "geometry": {"coordinates":[-119.75197799999999,36.844845],"type":"Point"}
}