{
  "type": "Feature",
  "properties": {
    "iso:country":"US",
    "sg:address":"5782 Benecia Dr",
    "sg:city":"Riverside",
    "sg:classifiers":[
        {
            "category":"Building & Trades",
            "subcategory":"Construction",
            "type":"Services"
        }
    ],
    "sg:phone":"+1 951 637 5534",
    "sg:postcode":"92504",
    "sg:province":"CA",
    "sg:tags":[
        "contractor"
    ],
    "wof:name":"Apex Roofing Co",
    "wof:placetype":"venue"
},
  "geometry": {"coordinates":[-117.42776000000001,33.958835],"type":"Point"}
}