{
  "type": "Feature",
  "properties": {
    "addr:full":"6477 Van Nuys Blvd Van Nuys CA 91401",
    "addr:housenumber":"6477",
    "addr:postcode":"91401",
    "addr:street":"Van Nuys Blvd",
    "iso:country":"US",
    "sg:address":"6477 Van Nuys Blvd",
    "sg:city":"Van Nuys",
    "sg:classifiers":[
        {
            "category":"Shopping",
            "subcategory":"Clothing, Apparel, & Fashions",
            "type":"Retail Goods"
        }
    ],
    "sg:phone":"+1 818 786 3484",
    "sg:postcode":"91401",
    "sg:province":"CA",
    "sg:tags":[
        "lingerie"
    ],
    "wof:name":"Daisy Y Lorena Underwear",
    "wof:placetype":"venue"
},
  "geometry": {"coordinates":[-118.44879,34.188116],"type":"Point"}
}