{
  "type": "Feature",
  "properties": {
    "addr:full":"471 Saratoga Ave Santa Clara CA 95050",
    "addr:housenumber":"471",
    "addr:postcode":"95050",
    "addr:street":"Saratoga Ave",
    "iso:country":"US",
    "sg:address":"471 Saratoga Ave",
    "sg:city":"Santa Clara",
    "sg:classifiers":[
        {
            "category":"Food & Beverages",
            "subcategory":"Groceries & Convenience Stores",
            "type":"Retail Goods"
        }
    ],
    "sg:phone":"+1 408 554 9398",
    "sg:postcode":"95050",
    "sg:province":"CA",
    "wof:name":"Lion Food Center",
    "wof:placetype":"venue"
},
  "geometry": {"coordinates":[-121.96007,37.33501],"type":"Point"}
}