{
  "type": "Feature",
  "properties": {
    "iso:country":"US",
    "sg:address":"3955 Dunhill St",
    "sg:city":"Napa",
    "sg:classifiers":[
        {
            "category":"Manufacturing",
            "subcategory":"Apparel",
            "type":"Manufacturing & Wholesale Goods"
        }
    ],
    "sg:phone":"+1 707 254 9485",
    "sg:postcode":"94558",
    "sg:province":"CA",
    "sg:tags":[
        "product",
        "mfg"
    ],
    "wof:name":"Canvas Custom Wines",
    "wof:placetype":"venue"
},
  "geometry": {"coordinates":[-122.317542,38.328393],"type":"Point"}
}