{
  "type": "Feature",
  "properties": {
    "iso:country":"US",
    "sg:address":"18838 State Hwy 18",
    "sg:city":"Apple Valley",
    "sg:classifiers":[
        {
            "category":"Utilities",
            "subcategory":"Mobile Phone",
            "type":"Services"
        }
    ],
    "sg:phone":"+1 760 242 5787",
    "sg:postcode":"92307",
    "sg:province":"CA",
    "sg:tags":[
        "communication",
        "radiotelephone"
    ],
    "wof:name":"Atlantic Communications",
    "wof:placetype":"venue"
},
  "geometry": {"coordinates":[-117.253129,34.537724],"type":"Point"}
}