{
  "type": "Feature",
  "properties": {
    "addr:full":"530 Alameda Del Prado # 311 Novato CA 94949",
    "addr:housenumber":"530;311",
    "addr:postcode":"94949",
    "addr:street":"Alameda Del Prado #",
    "iso:country":"US",
    "sg:address":"530 Alameda Del Prado # 311",
    "sg:city":"Novato",
    "sg:classifiers":[
        {
            "category":"Building & Trades",
            "subcategory":"Pest Control",
            "type":"Services"
        }
    ],
    "sg:phone":"+1 707 538 8877",
    "sg:postcode":"94949",
    "sg:province":"CA",
    "wof:name":"Hodson Termite Control Inc",
    "wof:placetype":"venue"
},
  "geometry": {"coordinates":[-122.539869,38.528093],"type":"Point"}
}