{
  "type": "Feature",
  "properties": {
    "iso:country":"US",
    "sg:address":"6336 Rockhurst Dr",
    "sg:city":"San Diego",
    "sg:classifiers":[
        {
            "category":"Utilities",
            "subcategory":"Telephone",
            "type":"Services"
        }
    ],
    "sg:phone":"+1 619 229 1331",
    "sg:postcode":"92120",
    "sg:province":"CA",
    "sg:tags":[
        "communications"
    ],
    "wof:name":"Extreme Enterprises",
    "wof:placetype":"venue"
},
  "geometry": {"coordinates":[-117.059504,32.785484],"type":"Point"}
}