{
  "type": "Feature",
  "properties": {
    "iso:country":"US",
    "sg:address":"750 N Mountain Ave",
    "sg:city":"Upland",
    "sg:classifiers":[
        {
            "category":"Professional",
            "type":"Services"
        }
    ],
    "sg:phone":"+1 909 985 4752",
    "sg:postcode":"91786",
    "sg:province":"CA",
    "wof:name":"Superior Sales & Svc",
    "wof:placetype":"venue"
},
  "geometry": {"coordinates":[-117.670108,34.102518],"type":"Point"}
}