{
  "type": "Feature",
  "properties": {
    "iso:country":"US",
    "sg:address":"2124 Lincoln Blvd",
    "sg:city":"Venice",
    "sg:classifiers":[
        {
            "category":"Autos & Motor Vehicles",
            "subcategory":"Automobile Sales",
            "type":"Retail Goods"
        },
        {
            "category":"Retail",
            "subcategory":"Auto Rental",
            "type":"Services"
        }
    ],
    "sg:phone":"+1 310 392 2070",
    "sg:postcode":"90291",
    "sg:province":"CA",
    "sg:tags":[
        "dealers-used",
        "car",
        "used",
        "cars-wholesale"
    ],
    "wof:name":"Bayview Motors",
    "wof:placetype":"venue"
},
  "geometry": {"coordinates":[-118.45523,33.995247],"type":"Point"}
}