{
  "type": "Feature",
  "properties": {
    "addr:full":"1318 E Cypress Ave Redding CA 96002",
    "addr:housenumber":"1318",
    "addr:postcode":"96002",
    "addr:street":"E Cypress Ave",
    "iso:country":"US",
    "sg:address":"1318 E Cypress Ave",
    "sg:city":"Redding",
    "sg:classifiers":[
        {
            "category":"Organizations",
            "subcategory":"Religious Organization",
            "type":"Services"
        }
    ],
    "sg:phone":"+1 530 222 6733",
    "sg:postcode":"96002",
    "sg:province":"CA",
    "sg:tags":[
        "church"
    ],
    "wof:name":"Adventist Community Svc",
    "wof:placetype":"venue"
},
  "geometry": {"coordinates":[-122.344032,40.571142],"type":"Point"}
}