{
  "type": "Feature",
  "properties": {
    "iso:country":"US",
    "sg:address":"300 W Glenoaks Blvd Ste 200",
    "sg:city":"Glendale",
    "sg:classifiers":[
        {
            "category":"Professional",
            "subcategory":"Accounting & Tax Preparation",
            "type":"Services"
        }
    ],
    "sg:phone":"+1 818 242 4888",
    "sg:postcode":"91202",
    "sg:province":"CA",
    "sg:tags":[
        "accountant"
    ],
    "sg:website":"www.roberthalltaxes.com",
    "wof:name":"Robert Hall & Associates",
    "wof:placetype":"venue"
},
  "geometry": {"coordinates":[-118.260046,34.15963],"type":"Point"}
}