{
  "type": "Feature",
  "properties": {
    "addr:full":"13710 Mountain House Rd Hopland CA 95449",
    "addr:housenumber":"13710",
    "addr:postcode":"95449",
    "addr:street":"Mountain House Rd",
    "iso:country":"US",
    "sg:address":"13710 Mountain House Rd",
    "sg:city":"Hopland",
    "sg:classifiers":[
        {
            "category":"Education",
            "subcategory":"School",
            "type":"Public Place"
        }
    ],
    "sg:phone":"+1 707 744 1333",
    "sg:postcode":"95449",
    "sg:province":"CA",
    "wof:name":"Hopland Elementary School",
    "wof:placetype":"venue"
},
  "geometry": {"coordinates":[-123.11760200000001,38.967304],"type":"Point"}
}