{
  "type": "Feature",
  "properties": {
    "iso:country":"US",
    "sg:address":"27011 McBean Pkwy Ste109",
    "sg:city":"Valencia",
    "sg:classifiers":[
        {
            "category":"Health Services",
            "subcategory":"Dentist",
            "type":"Services"
        }
    ],
    "sg:phone":"+1 661 877 4565",
    "sg:postcode":"91355",
    "sg:province":"CA",
    "sg:website":"promenadedentistry.aitrk.com",
    "wof:name":"Promenade Dentistry",
    "wof:placetype":"venue"
},
  "geometry": {"coordinates":[-118.564345,34.420656],"type":"Point"}
}