{
  "type": "Feature",
  "properties": {
    "iso:country":"US",
    "sg:address":"1050 Brookside Dr",
    "sg:city":"Richmond",
    "sg:classifiers":[
        {
            "category":"Wholesale",
            "subcategory":"Office Equipment",
            "type":"Manufacturing & Wholesale Goods"
        }
    ],
    "sg:phone":"+1 510 233 1484",
    "sg:postcode":"94801",
    "sg:province":"CA",
    "sg:tags":[
        "machine",
        "duplicating",
        "copying"
    ],
    "wof:name":"American Printers & Copiers",
    "wof:placetype":"venue"
},
  "geometry": {"coordinates":[-122.35839199999999,37.965229],"type":"Point"}
}