{
  "type": "Feature",
  "properties": {
    "iso:country":"US",
    "sg:address":"2500 Wilshire Blvd",
    "sg:city":"Los Angeles",
    "sg:classifiers":[
        {
            "category":"Wholesale",
            "subcategory":"Construction Materials",
            "type":"Manufacturing & Wholesale Goods"
        }
    ],
    "sg:phone":"+1 213 252 4292",
    "sg:postcode":"90057",
    "sg:province":"CA",
    "sg:tags":[
        "gates"
    ],
    "sg:website":"www.hacla.org",
    "wof:name":"Design & Construction Svc",
    "wof:placetype":"venue"
},
  "geometry": {"coordinates":[-118.281417,34.060506],"type":"Point"}
}