{
  "type": "Feature",
  "properties": {
    "addr:full":"5555 Business Park S # 210 Bakersfield CA 93309",
    "addr:housenumber":"5555",
    "addr:postcode":"93309",
    "addr:street":"Business Park S # 210",
    "iso:country":"US",
    "sg:address":"5555 Business Park S # 210",
    "sg:city":"Bakersfield",
    "sg:classifiers":[
        {
            "category":"Insurance",
            "subcategory":"Hazard Insurance",
            "type":"Services"
        },
        {
            "category":"Insurance",
            "subcategory":"Health Insurance",
            "type":"Services"
        }
    ],
    "sg:phone":"+1 661 322 3660",
    "sg:postcode":"93309",
    "sg:province":"CA",
    "sg:tags":[
        "commercial",
        "business"
    ],
    "sg:website":"http://www.choatinsurance.com",
    "wof:name":"Choat Insurance Services",
    "wof:placetype":"venue"
},
  "geometry": {"coordinates":[-119.060182,35.356381],"type":"Point"}
}