{
  "type": "Feature",
  "properties": {
    "iso:country":"US",
    "sg:address":"1348 58th St",
    "sg:city":"Sacramento",
    "sg:classifiers":[
        {
            "category":"Health Services",
            "subcategory":"Clinic",
            "type":"Services"
        }
    ],
    "sg:phone":"+1 916 451 7343",
    "sg:postcode":"95819",
    "sg:province":"CA",
    "sg:tags":[
        "home",
        "care"
    ],
    "wof:name":"Free Spirit Enterprises",
    "wof:placetype":"venue"
},
  "geometry": {"coordinates":[-121.435219,38.559516],"type":"Point"}
}