{
  "type": "Feature",
  "properties": {
    "iso:country":"US",
    "sg:address":"4041 Lone Tree Way",
    "sg:city":"Antioch",
    "sg:classifiers":[
        {
            "category":"Real Estate",
            "subcategory":"Real Estate Services",
            "type":"Services"
        },
        {
            "category":"Real Estate",
            "subcategory":"Real Estate Agent",
            "type":"Services"
        }
    ],
    "sg:phone":"+1 925 757 3612",
    "sg:postcode":"94531",
    "sg:province":"CA",
    "sg:tags":[
        "buyer",
        "broker"
    ],
    "wof:name":"Antioch Realty Group",
    "wof:placetype":"venue"
},
  "geometry": {"coordinates":[-121.773628,37.96419],"type":"Point"}
}