{
  "type": "Feature",
  "properties": {
    "addr:full":"1525 Country Club Dr Bakersfield CA 93306",
    "addr:housenumber":"1525",
    "addr:postcode":"93306",
    "addr:street":"Country Club Dr",
    "iso:country":"US",
    "sg:address":"1525 Country Club Dr",
    "sg:city":"Bakersfield",
    "sg:classifiers":[
        {
            "category":"Building & Trades",
            "subcategory":"Electrical",
            "type":"Services"
        }
    ],
    "sg:phone":"+1 661 978 6267",
    "sg:postcode":"93306",
    "sg:province":"CA",
    "sg:tags":[
        "electrician"
    ],
    "wof:name":"Victor Electric Co",
    "wof:placetype":"venue"
},
  "geometry": {"coordinates":[-118.95522699999999,35.377758],"type":"Point"}
}