{
  "type": "Feature",
  "properties": {
    "addr:full":"144 W Lake Ave Watsonville CA 95076",
    "addr:housenumber":"144",
    "addr:postcode":"95076",
    "addr:street":"W Lake Ave",
    "iso:country":"US",
    "sg:address":"144 W Lake Ave",
    "sg:city":"Watsonville",
    "sg:classifiers":[
        {
            "category":"Freight",
            "type":"Transportation"
        }
    ],
    "sg:phone":"+1 831 728 4535",
    "sg:postcode":"95076",
    "sg:province":"CA",
    "sg:tags":[
        "operator",
        "local",
        "trucking"
    ],
    "wof:name":"Pt Logistics Inc",
    "wof:placetype":"venue"
},
  "geometry": {"coordinates":[-121.762355,36.908812],"type":"Point"}
}