{
  "type": "Feature",
  "properties": {
    "addr:full":"2939 Promenade St West Sacramento CA 95605",
    "addr:housenumber":"2939",
    "addr:postcode":"95605",
    "addr:street":"Promenade St",
    "iso:country":"US",
    "sg:address":"2939 Promenade St",
    "sg:city":"West Sacramento",
    "sg:classifiers":[
        {
            "category":"Recreation",
            "subcategory":"Playground",
            "type":"Entertainment"
        }
    ],
    "sg:phone":"+1 916 371 2386",
    "sg:postcode":"95605",
    "sg:province":"CA",
    "sg:website":"www.thebouncespot.com",
    "wof:name":"The Bounce Spot",
    "wof:placetype":"venue"
},
  "geometry": {"coordinates":[-121.56776499999999,38.54855],"type":"Point"}
}