{
  "type": "Feature",
  "properties": {
    "iso:country":"US",
    "sg:address":"2295 Needham Rd",
    "sg:city":"El Cajon",
    "sg:classifiers":[
        {
            "category":"Arts & Performance",
            "subcategory":"Theater",
            "type":"Entertainment"
        }
    ],
    "sg:phone":"+1 619 562 2636",
    "sg:postcode":"92020",
    "sg:province":"CA",
    "sg:tags":[
        "live",
        "music"
    ],
    "wof:name":"Sound Tracks Music & Lights",
    "wof:placetype":"venue"
},
  "geometry": {"coordinates":[-116.994696,32.804016],"type":"Point"}
}