{
  "type": "Feature",
  "properties": {
    "iso:country":"US",
    "sg:address":"6738 Larkin Rd",
    "sg:city":"Live Oak",
    "sg:classifiers":[
        {
            "category":"Farming",
            "subcategory":"Orchard",
            "type":"Manufacturing & Wholesale Goods"
        }
    ],
    "sg:phone":"+1 530 695 2225",
    "sg:postcode":"95953",
    "sg:province":"CA",
    "sg:tags":[
        "used",
        "grove",
        "automobile",
        "nut",
        "tree",
        "fruit"
    ],
    "wof:name":"Boones Auto Sales",
    "wof:placetype":"venue"
},
  "geometry": {"coordinates":[-121.66016500000001,39.230391],"type":"Point"}
}