{
  "type": "Feature",
  "properties": {
    "iso:country":"US",
    "sg:address":"6868 E Foppiano Ln",
    "sg:city":"Stockton",
    "sg:classifiers":[
        {
            "category":"Wholesale",
            "subcategory":"Farm Supplies",
            "type":"Manufacturing & Wholesale Goods"
        }
    ],
    "sg:phone":"+1 209 931 8663",
    "sg:postcode":"95212",
    "sg:province":"CA",
    "wof:name":"Jim Hicks & Company Inc",
    "wof:placetype":"venue"
},
  "geometry": {"coordinates":[-121.22721,38.028195],"type":"Point"}
}