{
  "type": "Feature",
  "properties": {
    "iso:country":"US",
    "sg:address":"673 Parker Ave",
    "sg:city":"Rodeo",
    "sg:classifiers":[
        {
            "category":"Sports & Exercise",
            "subcategory":"Gym",
            "type":"Entertainment"
        }
    ],
    "sg:phone":"+1 510 799 6310",
    "sg:postcode":"94572",
    "sg:province":"CA",
    "sg:tags":[
        "club",
        "health",
        "studio",
        "gymnasium"
    ],
    "wof:name":"Curves For Women",
    "wof:placetype":"venue"
},
  "geometry": {"coordinates":[-122.266034,38.029222],"type":"Point"}
}