{
  "type": "Feature",
  "properties": {
    "addr:full":"19825 State Hwy 18 Apple Valley CA 92307",
    "addr:housenumber":"19825",
    "addr:postcode":"92307",
    "addr:street":"State Hwy 18",
    "iso:country":"US",
    "sg:address":"19825 State Hwy 18",
    "sg:city":"Apple Valley",
    "sg:classifiers":[
        {
            "category":"Airport",
            "type":"Transportation"
        }
    ],
    "sg:phone":"+1 760 242 9334",
    "sg:postcode":"92307",
    "sg:province":"CA",
    "sg:tags":[
        "cleaning"
    ],
    "wof:name":"Office Cubicle Cleaning Svc",
    "wof:placetype":"venue"
},
  "geometry": {"coordinates":[-117.232283,34.532192],"type":"Point"}
}