{
  "type": "Feature",
  "properties": {
    "iso:country":"US",
    "sg:address":"1260 Broadway Ave",
    "sg:city":"Atwater",
    "sg:classifiers":[
        {
            "category":"Shopping",
            "subcategory":"Used Merchandise",
            "type":"Retail Goods"
        }
    ],
    "sg:phone":"+1 209 356 1055",
    "sg:postcode":"95301",
    "sg:province":"CA",
    "sg:tags":[
        "shop",
        "collectible",
        "consignment"
    ],
    "wof:name":"My Sister's Attic",
    "wof:placetype":"venue"
},
  "geometry": {"coordinates":[-120.609517,37.347074],"type":"Point"}
}