{
  "type": "Feature",
  "properties": {
    "iso:country":"US",
    "sg:address":"13786 Wings of Morning Dr",
    "sg:city":"Nevada City",
    "sg:classifiers":[
        {
            "category":"Building & Trades",
            "subcategory":"Plumbing",
            "type":"Services"
        }
    ],
    "sg:phone":"+1 530 265 9360",
    "sg:postcode":"95959",
    "sg:province":"CA",
    "sg:tags":[
        "contractor"
    ],
    "wof:name":"Tri County Heating & AC",
    "wof:placetype":"venue"
},
  "geometry": {"coordinates":[-120.94864800000001,39.245086],"type":"Point"}
}