{
  "type": "Feature",
  "properties": {
    "iso:country":"US",
    "sg:address":"8055 W Manchester Avenue",
    "sg:city":"Playa Del Rey",
    "sg:classifiers":[
        {
            "category":"Professional",
            "subcategory":"Lawyer & Legal Services",
            "type":"Services"
        }
    ],
    "sg:phone":"+1 310 578 7025",
    "sg:postcode":"90293",
    "sg:province":"CA",
    "wof:name":"Saltsman Jay R A P C Atty",
    "wof:placetype":"venue"
},
  "geometry": {"coordinates":[-118.437128,33.959084],"type":"Point"}
}