{
  "type": "Feature",
  "properties": {
    "iso:country":"US",
    "sg:address":"4327 N Golden State Blvd",
    "sg:city":"Fresno",
    "sg:classifiers":[
        {
            "category":"Wholesale",
            "subcategory":"Groceries",
            "type":"Manufacturing & Wholesale Goods"
        }
    ],
    "sg:phone":"+1 559 271 9220",
    "sg:postcode":"93722",
    "sg:province":"CA",
    "sg:tags":[
        "feed",
        "farm",
        "supply",
        "prepared",
        "mfg"
    ],
    "wof:name":"Westway Terminal Company  Inc",
    "wof:placetype":"venue"
},
  "geometry": {"coordinates":[-119.867378,36.798609],"type":"Point"}
}