{
  "type": "Feature",
  "properties": {
    "addr:full":"1810 S 7th St San Jose CA 95112",
    "addr:housenumber":"1810",
    "addr:postcode":"95112",
    "addr:street":"S 7Th St",
    "iso:country":"US",
    "sg:address":"1810 S 7th St",
    "sg:city":"San Jose",
    "sg:classifiers":[
        {
            "category":"Building & Trades",
            "subcategory":"Construction",
            "type":"Services"
        }
    ],
    "sg:phone":"+1 408 294 5112",
    "sg:postcode":"95112",
    "sg:province":"CA",
    "sg:tags":[
        "contractor"
    ],
    "wof:name":"Rain Tree Landscape Services Inc.",
    "wof:placetype":"venue"
},
  "geometry": {"coordinates":[-121.862762,37.31171],"type":"Point"}
}