{
  "type": "Feature",
  "properties": {
    "iso:country":"US",
    "sg:address":"6409 Peinado Way",
    "sg:city":"San Diego",
    "sg:classifiers":[
        {
            "category":"Banks & Credit Unions",
            "subcategory":"Bank",
            "type":"Services"
        }
    ],
    "sg:phone":"+1 858 453 2001",
    "sg:postcode":"92121",
    "sg:province":"CA",
    "sg:tags":[
        "loan"
    ],
    "wof:name":"Central Park Equity LLC",
    "wof:placetype":"venue"
},
  "geometry": {"coordinates":[-117.181682,32.918895],"type":"Point"}
}