{
  "type": "Feature",
  "properties": {
    "iso:country":"US",
    "sg:address":"1695 E 6th St",
    "sg:city":"Beaumont",
    "sg:classifiers":[
        {
            "category":"Restaurant",
            "type":"Food & Drink"
        }
    ],
    "sg:phone":"+1 951 769 0031",
    "sg:postcode":"92223",
    "sg:province":"CA",
    "wof:name":"Burger King",
    "wof:placetype":"venue"
},
  "geometry": {"coordinates":[-116.947154,33.92934],"type":"Point"}
}