{
  "type": "Feature",
  "properties": {
    "addr:full":"28073 Smyth Dr Valencia CA 91355",
    "addr:postcode":"28073;91355",
    "addr:street":"Smyth Dr",
    "iso:country":"US",
    "sg:address":"28073 Smyth Dr",
    "sg:city":"Valencia",
    "sg:classifiers":[
        {
            "category":"Personal",
            "subcategory":"Skin Care",
            "type":"Services"
        }
    ],
    "sg:phone":"+1 661 295 0027",
    "sg:postcode":"91355",
    "sg:province":"CA",
    "sg:website":"www.dermalsolutions.com",
    "wof:name":"Dermal Solutions Esthetic Center",
    "wof:placetype":"venue"
},
  "geometry": {"coordinates":[-118.57131,34.443042],"type":"Point"}
}