{
  "type": "Feature",
  "properties": {
    "addr:full":"1730 South Amphlett Blvd., Suite 101 San Mateo CA 94402",
    "addr:housenumber":"1730",
    "addr:postcode":"94402",
    "addr:street":"South Amphlett Blvd. Suite 101",
    "iso:country":"US",
    "sg:address":"1730 South Amphlett Blvd., Suite 101",
    "sg:city":"San Mateo",
    "sg:classifiers":[
        {
            "category":"Manufacturing",
            "subcategory":"Electronics",
            "type":"Manufacturing & Wholesale Goods"
        }
    ],
    "sg:phone":"+1 650 235 3510",
    "sg:postcode":"94402",
    "sg:province":"CA",
    "sg:tags":[
        "mobile-tv",
        "tv"
    ],
    "sg:website":"http://monsoonmultimedia.com/",
    "wof:name":"Monsoon Multimedia",
    "wof:placetype":"venue"
},
  "geometry": {"coordinates":[-122.30206099999999,37.558349],"type":"Point"}
}