{
  "type": "Feature",
  "properties": {
    "addr:full":"7875 Valle Vista Ct Rancho Cucamonga CA 91730",
    "addr:housenumber":"7875",
    "addr:postcode":"91730",
    "addr:street":"Valle Vista Ct",
    "iso:country":"US",
    "sg:address":"7875 Valle Vista Ct",
    "sg:city":"Rancho Cucamonga",
    "sg:classifiers":[
        {
            "category":"Insurance",
            "subcategory":"Insurance Agent",
            "type":"Services"
        }
    ],
    "sg:phone":"+1 909 985 7621",
    "sg:postcode":"91730",
    "sg:province":"CA",
    "wof:name":"Hay Insurance",
    "wof:placetype":"venue"
},
  "geometry": {"coordinates":[-117.620135,34.109867],"type":"Point"}
}