{
  "type": "Feature",
  "properties": {
    "iso:country":"US",
    "sg:address":"7755 W Sunset Boulevard",
    "sg:city":"Los Angeles",
    "sg:classifiers":[
        {
            "category":"Organizations",
            "subcategory":"Non-profit Organization",
            "type":"Services"
        }
    ],
    "sg:phone":"+1 323 876 0160",
    "sg:postcode":"90046",
    "sg:province":"CA",
    "sg:tags":[
        "service/non-profit",
        "community"
    ],
    "wof:name":"Local 600 Iatse",
    "wof:placetype":"venue"
},
  "geometry": {"coordinates":[-118.358536,34.097944],"type":"Point"}
}