{
  "type": "Feature",
  "properties": {
    "iso:country":"US",
    "sg:address":"3024 Hampshire Dr",
    "sg:city":"Sacramento",
    "sg:classifiers":[
        {
            "category":"Professional",
            "subcategory":"Accounting & Tax Preparation",
            "type":"Services"
        }
    ],
    "sg:phone":"+1 916 481 0687",
    "sg:postcode":"95821",
    "sg:province":"CA",
    "sg:tags":[
        "bookkeeping",
        "billing"
    ],
    "wof:name":"Julie S Bookeeping Service",
    "wof:placetype":"venue"
},
  "geometry": {"coordinates":[-121.39290800000001,38.611897],"type":"Point"}
}