{
  "type": "Feature",
  "properties": {
    "iso:country":"US",
    "sg:address":"9126 Mission Blvd",
    "sg:city":"Riverside",
    "sg:classifiers":[
        {
            "category":"Retail",
            "subcategory":"Repair Shop",
            "type":"Services"
        }
    ],
    "sg:phone":"+1 951 681 3798",
    "sg:postcode":"92509",
    "sg:province":"CA",
    "sg:tags":[
        "tool",
        "parts"
    ],
    "wof:name":"Mancilla Electric Tool Repair",
    "wof:placetype":"venue"
},
  "geometry": {"coordinates":[-117.48355100000001,34.011718],"type":"Point"}
}