{
  "type": "Feature",
  "properties": {
    "addr:full":"101 W Beverly Blvd Montebello CA 90640",
    "addr:housenumber":"101",
    "addr:postcode":"90640",
    "addr:street":"W Beverly Blvd",
    "iso:country":"US",
    "sg:address":"101 W Beverly Blvd",
    "sg:city":"Montebello",
    "sg:classifiers":[
        {
            "category":"Health Services",
            "subcategory":"Doctor",
            "type":"Services"
        }
    ],
    "sg:phone":"+1 707 772 6701",
    "sg:postcode":"90640",
    "sg:province":"CA",
    "sg:tags":[
        "physician",
        "surgeon"
    ],
    "wof:name":"Nugent-Odou Surgical Group",
    "wof:placetype":"venue"
},
  "geometry": {"coordinates":[-118.099655,34.015848],"type":"Point"}
}