{
  "type": "Feature",
  "properties": {
    "addr:full":"921 N Idaho St San Mateo CA 94401",
    "addr:housenumber":"921",
    "addr:postcode":"94401",
    "addr:street":"N Idaho St",
    "iso:country":"US",
    "sg:address":"921 N Idaho St",
    "sg:city":"San Mateo",
    "sg:classifiers":[
        {
            "category":"Home & Garden",
            "subcategory":"Home Furnishings",
            "type":"Retail Goods"
        }
    ],
    "sg:phone":"+1 650 342 2071",
    "sg:postcode":"94401",
    "sg:province":"CA",
    "sg:tags":[
        "curtain",
        "drapery",
        "related",
        "accessory"
    ],
    "wof:name":"Belliveau Interiors",
    "wof:placetype":"venue"
},
  "geometry": {"coordinates":[-122.331096,37.584649],"type":"Point"}
}