{
  "type": "Feature",
  "properties": {
    "iso:country":"US",
    "sg:address":"5353 Topanga Canyon Blvd Ste 102",
    "sg:city":"Woodland Hills",
    "sg:classifiers":[
        {
            "category":"Shopping",
            "subcategory":"Florist",
            "type":"Retail Goods"
        }
    ],
    "sg:phone":"+1 818 883 7729",
    "sg:postcode":"91364",
    "sg:province":"CA",
    "sg:website":"www.liliansflowers.com",
    "wof:name":"Lilian's Flowers",
    "wof:placetype":"venue"
},
  "geometry": {"coordinates":[-118.606083,34.167418],"type":"Point"}
}