{
  "type": "Feature",
  "properties": {
    "iso:country":"US",
    "sg:address":"4427 Santa Monica Boulevard",
    "sg:city":"Los Angeles",
    "sg:classifiers":[
        {
            "category":"Retail",
            "subcategory":"Portrait Studio",
            "type":"Services"
        }
    ],
    "sg:phone":"+1 323 660 0187",
    "sg:postcode":"90029",
    "sg:province":"CA",
    "sg:tags":[
        "photography",
        "store"
    ],
    "sg:website":"www.budgetfilms.com",
    "wof:name":"Budget Films",
    "wof:placetype":"venue"
},
  "geometry": {"coordinates":[-118.2855,34.090754],"type":"Point"}
}