{
  "type": "Feature",
  "properties": {
    "addr:full":"1004 14th St Oakland CA 94607",
    "addr:housenumber":"1004",
    "addr:postcode":"94607",
    "addr:street":"14Th St",
    "iso:country":"US",
    "sg:address":"1004 14th St",
    "sg:city":"Oakland",
    "sg:classifiers":[
        {
            "category":"Organizations",
            "subcategory":"Religious Organization",
            "type":"Services"
        }
    ],
    "sg:phone":"+1 510 452 3028",
    "sg:postcode":"94607",
    "sg:province":"CA",
    "sg:tags":[
        "church"
    ],
    "wof:name":"Antioch Baptist Church",
    "wof:placetype":"venue"
},
  "geometry": {"coordinates":[-122.283418,37.809041],"type":"Point"}
}