{
  "type": "Feature",
  "properties": {
    "iso:country":"US",
    "sg:address":"19433 Kneebone Ct",
    "sg:city":"Penn Valley",
    "sg:classifiers":[
        {
            "category":"Retail",
            "subcategory":"Animal Services",
            "type":"Services"
        }
    ],
    "sg:phone":"+1 530 432 3108",
    "sg:postcode":"95946",
    "sg:province":"CA",
    "wof:name":"Maple Leaf Stables",
    "wof:placetype":"venue"
},
  "geometry": {"coordinates":[-121.19631800000001,39.25567],"type":"Point"}
}