{
  "type": "Feature",
  "properties": {
    "addr:full":"1050 Marina Village Pkwy Ste 104 Alameda CA 94501",
    "addr:housenumber":"1050",
    "addr:postcode":"94501",
    "addr:street":"Marina Village Pkwy Ste 104",
    "iso:country":"US",
    "sg:address":"1050 Marina Village Pkwy Ste 104",
    "sg:city":"Alameda",
    "sg:classifiers":[
        {
            "category":"Health Services",
            "subcategory":"Chiropractor",
            "type":"Services"
        }
    ],
    "sg:phone":"+1 510 207 5565",
    "sg:postcode":"94501",
    "sg:province":"CA",
    "sg:website":"www.vitalogychiropractic.com",
    "wof:name":"Vitalogy Chiropractic",
    "wof:placetype":"venue"
},
  "geometry": {"coordinates":[-122.269273,37.785003],"type":"Point"}
}