{
  "type": "Feature",
  "properties": {
    "addr:full":"762 W Ventura Blvd Camarillo CA 93010",
    "addr:housenumber":"762",
    "addr:postcode":"93010",
    "addr:street":"W Ventura Blvd",
    "iso:country":"US",
    "sg:address":"762 W Ventura Blvd",
    "sg:city":"Camarillo",
    "sg:classifiers":[
        {
            "category":"Utilities",
            "subcategory":"Telephone",
            "type":"Services"
        }
    ],
    "sg:phone":"+1 805 445 9590",
    "sg:postcode":"93010",
    "sg:province":"CA",
    "sg:tags":[
        "communications"
    ],
    "wof:name":"Dial Long Distance Inc",
    "wof:placetype":"venue"
},
  "geometry": {"coordinates":[-119.09632999999999,34.220891],"type":"Point"}
}