{
  "type": "Feature",
  "properties": {
    "addr:full":"1311 W Washington Blvd Los Angeles CA 90007",
    "addr:housenumber":"1311",
    "addr:postcode":"90007",
    "addr:street":"W Washington Blvd",
    "iso:country":"US",
    "sg:address":"1311 W Washington Blvd",
    "sg:city":"Los Angeles",
    "sg:classifiers":[
        {
            "category":"Restaurant",
            "type":"Food & Drink"
        }
    ],
    "sg:menulink":"http://www.allmenus.com/ca/los-angeles/215975-mcdonalds/menu/",
    "sg:postcode":"90007",
    "sg:province":"CA",
    "sg:tags":[
        "burger",
        "american"
    ],
    "wof:name":"McDonald's",
    "wof:placetype":"venue"
},
  "geometry": {"coordinates":[-118.284643,34.040037],"type":"Point"}
}