{
  "type": "Feature",
  "properties": {
    "addr:full":"400 Main St Los Altos CA 94022",
    "addr:housenumber":"400",
    "addr:postcode":"94022",
    "addr:street":"Main St",
    "iso:country":"US",
    "sg:address":"400 Main St",
    "sg:city":"Los Altos",
    "sg:classifiers":[
        {
            "category":"Shopping",
            "subcategory":"Used Merchandise",
            "type":"Retail Goods"
        }
    ],
    "sg:phone":"+1 650 917 8526",
    "sg:postcode":"94022",
    "sg:province":"CA",
    "sg:tags":[
        "shop",
        "consignment"
    ],
    "wof:name":"Home Consignment Ctr",
    "wof:placetype":"venue"
},
  "geometry": {"coordinates":[-122.11787,37.377729],"type":"Point"}
}