{
  "type": "Feature",
  "properties": {
    "addr:full":"10398 Rockingham Dr Ste 3 Sacramento CA 95827",
    "addr:housenumber":"10398",
    "addr:postcode":"95827",
    "addr:street":"Rockingham Dr Ste 3",
    "iso:country":"US",
    "sg:address":"10398 Rockingham Dr Ste 3",
    "sg:city":"Sacramento",
    "sg:classifiers":[
        {
            "category":"Shopping",
            "subcategory":"Mobile Phones",
            "type":"Retail Goods"
        }
    ],
    "sg:phone":"+1 916 368 5100",
    "sg:postcode":"95827",
    "sg:province":"CA",
    "wof:name":"Xcell Accessories",
    "wof:placetype":"venue"
},
  "geometry": {"coordinates":[-121.304061,38.574497],"type":"Point"}
}