{
  "type": "Feature",
  "properties": {
    "addr:full":"8612 Norwich Ave North Hills CA 91343",
    "addr:housenumber":"8612",
    "addr:postcode":"91343",
    "addr:street":"Norwich Ave",
    "iso:country":"US",
    "sg:address":"8612 Norwich Ave",
    "sg:city":"North Hills",
    "sg:classifiers":[
        {
            "category":"Professional",
            "type":"Services"
        }
    ],
    "sg:phone":"+1 818 894 7855",
    "sg:postcode":"91343",
    "sg:province":"CA",
    "wof:name":"Violets Boarding CA",
    "wof:placetype":"venue"
},
  "geometry": {"coordinates":[-118.460131,34.225705],"type":"Point"}
}