{
  "type": "Feature",
  "properties": {
    "addr:full":"12207 Wilshire Blvd Los Angeles CA 90025",
    "addr:housenumber":"12207",
    "addr:postcode":"90025",
    "addr:street":"Wilshire Blvd",
    "iso:country":"US",
    "sg:address":"12207 Wilshire Blvd",
    "sg:city":"Los Angeles",
    "sg:classifiers":[
        {
            "category":"Retail",
            "subcategory":"Laundry & Dry Cleaning",
            "type":"Services"
        }
    ],
    "sg:phone":"+1 310 442 5211",
    "sg:postcode":"90025",
    "sg:province":"CA",
    "sg:tags":[
        "repairing",
        "rug",
        "carpet"
    ],
    "wof:name":"Carpet Co Of Tabriz",
    "wof:placetype":"venue"
},
  "geometry": {"coordinates":[-118.46916,34.042837],"type":"Point"}
}