{
  "type": "Feature",
  "properties": {
    "addr:full":"15120 Sequoia St Hesperia CA 92345",
    "addr:housenumber":"15120",
    "addr:postcode":"92345",
    "addr:street":"Sequoia St",
    "iso:country":"US",
    "sg:address":"15120 Sequoia St",
    "sg:city":"Hesperia",
    "sg:classifiers":[
        {
            "category":"Real Estate",
            "subcategory":"Real Estate Agent",
            "type":"Services"
        }
    ],
    "sg:phone":"+1 760 949 3326",
    "sg:postcode":"92345",
    "sg:province":"CA",
    "sg:tags":[
        "agency",
        "rental"
    ],
    "wof:name":"Stevenson Rentals",
    "wof:placetype":"venue"
},
  "geometry": {"coordinates":[-117.333839,34.468809],"type":"Point"}
}