{
  "type": "Feature",
  "properties": {
    "iso:country":"US",
    "sg:address":"2180 W Foothill Blvd",
    "sg:city":"Upland",
    "sg:classifiers":[
        {
            "category":"Wholesale",
            "subcategory":"Electrical",
            "type":"Manufacturing & Wholesale Goods"
        }
    ],
    "sg:phone":"+1 714 310 5328",
    "sg:postcode":"91786",
    "sg:province":"CA",
    "sg:tags":[
        "electronic"
    ],
    "wof:name":"Bill Brooks Enterprises",
    "wof:placetype":"venue"
},
  "geometry": {"coordinates":[-117.691264,34.106707],"type":"Point"}
}