{
  "type": "Feature",
  "properties": {
    "iso:country":"US",
    "sg:address":"27364 Jefferson Ave",
    "sg:city":"Temecula",
    "sg:classifiers":[
        {
            "category":"Banks & Credit Unions",
            "subcategory":"Bank",
            "type":"Services"
        }
    ],
    "sg:phone":"+1 951 296 5340",
    "sg:postcode":"92590",
    "sg:province":"CA",
    "sg:tags":[
        "mortgage"
    ],
    "wof:name":"World Savings & Loan",
    "wof:placetype":"venue"
},
  "geometry": {"coordinates":[-117.16644599999999,33.522434],"type":"Point"}
}