{
  "type": "Feature",
  "properties": {
    "addr:full":"1060 Newpark Mall Newark CA 94560",
    "addr:housenumber":"1060",
    "addr:postcode":"94560",
    "addr:street":"Newpark Mall",
    "iso:country":"US",
    "sg:address":"1060 Newpark Mall",
    "sg:city":"Newark",
    "sg:classifiers":[
        {
            "category":"Restaurant",
            "type":"Food & Drink"
        }
    ],
    "sg:phone":"+1 510 713 8998",
    "sg:postcode":"94560",
    "sg:province":"CA",
    "wof:name":"LA Creperie",
    "wof:placetype":"venue"
},
  "geometry": {"coordinates":[-122.005032,37.525733],"type":"Point"}
}