{
  "type": "Feature",
  "properties": {
    "addr:full":"7301 Orangethorpe Ave Buena Park CA 90621",
    "addr:housenumber":"7301",
    "addr:postcode":"90621",
    "addr:street":"Orangethorpe Ave",
    "iso:country":"US",
    "sg:address":"7301 Orangethorpe Ave",
    "sg:city":"Buena Park",
    "sg:classifiers":[
        {
            "category":"Insurance",
            "subcategory":"Hazard Insurance",
            "type":"Services"
        }
    ],
    "sg:phone":"+1 714 523 0922",
    "sg:postcode":"90621",
    "sg:province":"CA",
    "sg:tags":[
        "bond"
    ],
    "wof:name":"Apex Bail Bonds",
    "wof:placetype":"venue"
},
  "geometry": {"coordinates":[-118.006,33.85888],"type":"Point"}
}