{
  "type": "Feature",
  "properties": {
    "iso:country":"US",
    "sg:address":"14734 Holly Dr",
    "sg:city":"Fontana",
    "sg:classifiers":[
        {
            "category":"Health Services",
            "subcategory":"Medical Lab",
            "type":"Services"
        }
    ],
    "sg:phone":"+1 909 421 0893",
    "sg:postcode":"92335",
    "sg:province":"CA",
    "sg:tags":[
        "laboratory"
    ],
    "wof:name":"N B Dental Laboratory",
    "wof:placetype":"venue"
},
  "geometry": {"coordinates":[-117.48315599999999,34.080703],"type":"Point"}
}