{
  "type": "Feature",
  "properties": {
    "addr:full":"2950 S Cherry Ave Fresno CA 93706",
    "addr:housenumber":"2950",
    "addr:postcode":"93706",
    "addr:street":"S Cherry Ave",
    "iso:country":"US",
    "sg:address":"2950 S Cherry Ave",
    "sg:city":"Fresno",
    "sg:classifiers":[
        {
            "category":"Farming",
            "subcategory":"Poultry Farm",
            "type":"Manufacturing & Wholesale Goods"
        }
    ],
    "sg:phone":"+1 559 457 6500",
    "sg:postcode":"93706",
    "sg:province":"CA",
    "wof:name":"Foster Farms Commodities",
    "wof:placetype":"venue"
},
  "geometry": {"coordinates":[-119.78173099999999,36.692244],"type":"Point"}
}