{
  "type": "Feature",
  "properties": {
    "addr:full":"3025 E 2nd St Long Beach CA 90803",
    "addr:housenumber":"3025",
    "addr:postcode":"90803",
    "addr:street":"E 2Nd St",
    "iso:country":"US",
    "sg:address":"3025 E 2nd St",
    "sg:city":"Long Beach",
    "sg:classifiers":[
        {
            "category":"Manufacturing",
            "subcategory":"Toys & Sporting Goods",
            "type":"Manufacturing & Wholesale Goods"
        }
    ],
    "sg:phone":"+1 562 433 5244",
    "sg:postcode":"90803",
    "sg:province":"CA",
    "sg:tags":[
        "equipment",
        "mfg",
        "video",
        "custom"
    ],
    "wof:name":"K Y Enterprises",
    "wof:placetype":"venue"
},
  "geometry": {"coordinates":[-118.155782,33.764285],"type":"Point"}
}