{
  "type": "Feature",
  "properties": {
    "addr:full":"849 Veterans Blvd Redwood City CA 94063",
    "addr:housenumber":"849",
    "addr:postcode":"94063",
    "addr:street":"Veterans Blvd",
    "iso:country":"US",
    "sg:address":"849 Veterans Blvd",
    "sg:city":"Redwood City",
    "sg:classifiers":[
        {
            "category":"Wholesale",
            "subcategory":"Medical Equipment & Supplies",
            "type":"Manufacturing & Wholesale Goods"
        }
    ],
    "sg:phone":"+1 650 556 1070",
    "sg:postcode":"94063",
    "sg:province":"CA",
    "sg:tags":[
        "development",
        "surgical",
        "devices",
        "research"
    ],
    "sg:website":"www.rubicor.com",
    "wof:name":"Rubicor Medical Inc",
    "wof:placetype":"venue"
},
  "geometry": {"coordinates":[-122.228874,37.490639],"type":"Point"}
}