{
  "type": "Feature",
  "properties": {
    "addr:full":"5720 Cabrillo Hwy Pescadero CA 94060",
    "addr:housenumber":"5720",
    "addr:postcode":"94060",
    "addr:street":"Cabrillo Hwy",
    "iso:country":"US",
    "sg:address":"5720 Cabrillo Hwy",
    "sg:city":"Pescadero",
    "sg:classifiers":[
        {
            "category":"Restaurant",
            "type":"Food & Drink"
        }
    ],
    "sg:phone":"+1 650 879 1010",
    "sg:postcode":"94060",
    "sg:province":"CA",
    "sg:tags":[
        "operation",
        "eating"
    ],
    "wof:name":"Beach House Restaurant",
    "wof:placetype":"venue"
},
  "geometry": {"coordinates":[-122.36102,37.166517],"type":"Point"}
}