{
  "type": "Feature",
  "properties": {
    "iso:country":"US",
    "sg:address":"2509 Bryant St",
    "sg:city":"San Francisco",
    "sg:classifiers":[
        {
            "category":"Education",
            "subcategory":"School",
            "type":"Public Place"
        }
    ],
    "sg:phone":"+1 425 770 1052",
    "sg:postcode":"94101",
    "sg:province":"CA",
    "sg:website":"www.soundcave.org/experience.php",
    "wof:name":"Tyson Ayers - Guitar Teacher",
    "wof:placetype":"venue"
},
  "geometry": {"coordinates":[-122.40923600000001,37.754245],"type":"Point"}
}