{
  "type": "Feature",
  "properties": {
    "iso:country":"US",
    "sg:address":"610 W Main St",
    "sg:city":"Visalia",
    "sg:classifiers":[
        {
            "category":"Building & Trades",
            "subcategory":"Construction",
            "type":"Services"
        }
    ],
    "sg:phone":"+1 559 636 1300",
    "sg:postcode":"93291",
    "sg:province":"CA",
    "sg:tags":[
        "contractor"
    ],
    "sg:website":"www.coldwellbankervisalia.com",
    "wof:name":"LRG Construction Co",
    "wof:placetype":"venue"
},
  "geometry": {"coordinates":[-119.298714,36.3302],"type":"Point"}
}