{
  "type": "Feature",
  "properties": {
    "iso:country":"US",
    "sg:address":"2350 Meyers Ave",
    "sg:city":"Escondido",
    "sg:classifiers":[
        {
            "category":"Manufacturing",
            "subcategory":"Retail Goods",
            "type":"Manufacturing & Wholesale Goods"
        }
    ],
    "sg:phone":"+1 760 744 1793",
    "sg:postcode":"92029",
    "sg:province":"CA",
    "sg:tags":[
        "manufacturer"
    ],
    "wof:name":"Anything Goes",
    "wof:placetype":"venue"
},
  "geometry": {"coordinates":[-117.128459,33.130446],"type":"Point"}
}