{
  "type": "Feature",
  "properties": {
    "addr:full":"308 Washington Blvd Roseville CA 95678",
    "addr:housenumber":"308",
    "addr:postcode":"95678",
    "addr:street":"Washington Blvd",
    "iso:country":"US",
    "sg:address":"308 Washington Blvd",
    "sg:city":"Roseville",
    "sg:classifiers":[
        {
            "category":"Restaurant",
            "type":"Food & Drink"
        }
    ],
    "sg:phone":"+1 916 782 2084",
    "sg:postcode":"95678",
    "sg:province":"CA",
    "wof:name":"Nubbin's Drive-In",
    "wof:placetype":"venue"
},
  "geometry": {"coordinates":[-121.28780999999999,38.752842],"type":"Point"}
}