{
  "type": "Feature",
  "properties": {
    "iso:country":"US",
    "sg:address":"308 Washington Blvd",
    "sg:city":"Roseville",
    "sg:classifiers":[
        {
            "category":"Restaurant",
            "type":"Food & Drink"
        }
    ],
    "sg:phone":"+1 916 782 2084",
    "sg:postcode":"95678",
    "sg:province":"CA",
    "wof:name":"Nubbin's Drive-In",
    "wof:placetype":"venue"
},
  "geometry": {"coordinates":[-121.28781,38.752842],"type":"Point"}
}