{
  "type": "Feature",
  "properties": {
    "iso:country":"US",
    "sg:address":"910 W Coast Hwy",
    "sg:city":"Newport Beach",
    "sg:classifiers":[
        {
            "category":"Shopping",
            "type":"Retail Goods"
        }
    ],
    "sg:phone":"+1 949 646 4435",
    "sg:postcode":"92663",
    "sg:province":"CA",
    "sg:tags":[
        "merchandise"
    ],
    "wof:name":"Design Canvas",
    "wof:placetype":"venue"
},
  "geometry": {"coordinates":[-117.922798,33.619737],"type":"Point"}
}