{
  "type": "Feature",
  "properties": {
    "iso:country":"US",
    "sg:address":"4810 Sonata Ln",
    "sg:city":"Los Angeles",
    "sg:classifiers":[
        {
            "category":"Professional",
            "subcategory":"Management & Consulting",
            "type":"Services"
        }
    ],
    "sg:phone":"+1 323 333 7060",
    "sg:postcode":"90042",
    "sg:province":"CA",
    "sg:tags":[
        "consultant"
    ],
    "wof:name":"Lee's Consulting Co",
    "wof:placetype":"venue"
},
  "geometry": {"coordinates":[-118.208572,34.10913],"type":"Point"}
}