{
  "type": "Feature",
  "properties": {
    "iso:country":"US",
    "sg:address":"18594 Ventura Blvd",
    "sg:city":"Tarzana",
    "sg:classifiers":[
        {
            "category":"Restaurant",
            "type":"Food & Drink"
        }
    ],
    "sg:phone":"+1 818 757 1514",
    "sg:postcode":"91356",
    "sg:province":"CA",
    "wof:name":"Takzin Thai Restaurant",
    "wof:placetype":"venue"
},
  "geometry": {"coordinates":[-118.538304,34.169665],"type":"Point"}
}