{
  "type": "Feature",
  "properties": {
    "addr:full":"110 W Ocean Blvd Ste 614 Long Beach CA 90802",
    "addr:housenumber":"110",
    "addr:postcode":"90802",
    "addr:street":"W Ocean Blvd Ste 614",
    "iso:country":"US",
    "sg:address":"110 W Ocean Blvd Ste 614",
    "sg:city":"Long Beach",
    "sg:classifiers":[
        {
            "category":"Health Services",
            "subcategory":"Clinic",
            "type":"Services"
        }
    ],
    "sg:phone":"+1 310 668 1608",
    "sg:postcode":"90802",
    "sg:province":"CA",
    "sg:tags":[
        "counseling",
        "mental"
    ],
    "sg:website":"www.newlifepastoralcounseling.com/",
    "wof:name":"New Life Pastoral Counseling",
    "wof:placetype":"venue"
},
  "geometry": {"coordinates":[-118.192637,33.766415],"type":"Point"}
}