{
  "type": "Feature",
  "properties": {
    "iso:country":"US",
    "sg:address":"251 W Harder Rd",
    "sg:city":"Hayward",
    "sg:classifiers":[
        {
            "category":"Real Estate",
            "subcategory":"Real Estate Operator",
            "type":"Services"
        }
    ],
    "sg:phone":"+1 510 782 0498",
    "sg:postcode":"94544",
    "sg:province":"CA",
    "sg:tags":[
        "apartment"
    ],
    "wof:name":"Triangle Garden Apartments",
    "wof:placetype":"venue"
},
  "geometry": {"coordinates":[-122.085999,37.648102],"type":"Point"}
}