{
  "type": "Feature",
  "properties": {
    "iso:country":"US",
    "sg:address":"1141 6th Avenue",
    "sg:city":"San Diego",
    "sg:classifiers":[
        {
            "category":"Shopping",
            "subcategory":"Pharmacy",
            "type":"Retail Goods"
        }
    ],
    "sg:phone":"+1 619 232 8101",
    "sg:postcode":"92101",
    "sg:province":"CA",
    "sg:tags":[
        "drugstore"
    ],
    "wof:name":"Allen's Pharmacy",
    "wof:placetype":"venue"
},
  "geometry": {"coordinates":[-117.159378,32.717049],"type":"Point"}
}