{
  "type": "Feature",
  "properties": {
    "iso:country":"US",
    "sg:address":"7721 Rudyard Cir",
    "sg:city":"Antelope",
    "sg:classifiers":[
        {
            "category":"Personal",
            "type":"Services"
        }
    ],
    "sg:phone":"+1 916 332 7387",
    "sg:postcode":"95843",
    "sg:province":"CA",
    "sg:tags":[
        "therapist",
        "massage"
    ],
    "wof:name":"Sonja's Hands That Help Heal",
    "wof:placetype":"venue"
},
  "geometry": {"coordinates":[-121.393097,38.707737],"type":"Point"}
}