{
  "type": "Feature",
  "properties": {
    "addr:full":"1741 Pomona Ave Costa Mesa CA 92627",
    "addr:housenumber":"1741",
    "addr:postcode":"92627",
    "addr:street":"Pomona Ave",
    "iso:country":"US",
    "sg:address":"1741 Pomona Ave",
    "sg:city":"Costa Mesa",
    "sg:classifiers":[
        {
            "category":"Real Estate",
            "subcategory":"Real Estate Operator",
            "type":"Services"
        }
    ],
    "sg:phone":"+1 949 650 4669",
    "sg:postcode":"92627",
    "sg:province":"CA",
    "sg:tags":[
        "mobile",
        "home",
        "community"
    ],
    "wof:name":"Vista Verde Mobile Home Park",
    "wof:placetype":"venue"
},
  "geometry": {"coordinates":[-117.927632,33.636345],"type":"Point"}
}