{
  "type": "Feature",
  "properties": {
    "iso:country":"US",
    "sg:address":"7347 Hinds Ave",
    "sg:city":"North Hollywood",
    "sg:classifiers":[
        {
            "category":"Manufacturing",
            "subcategory":"Tools & Machinery",
            "type":"Manufacturing & Wholesale Goods"
        }
    ],
    "sg:phone":"+1 818 982 9886",
    "sg:postcode":"91605",
    "sg:province":"CA",
    "sg:tags":[
        "lamp"
    ],
    "wof:name":"Alken Industries",
    "wof:placetype":"venue"
},
  "geometry": {"coordinates":[-118.391133,34.203974],"type":"Point"}
}