{
  "type": "Feature",
  "properties": {
    "iso:country":"US",
    "sg:address":"27674 Newhall Ranch Rd Unit 30",
    "sg:city":"Valencia",
    "sg:classifiers":[
        {
            "category":"Restaurant",
            "type":"Food & Drink"
        }
    ],
    "sg:phone":"+1 661 295 1989",
    "sg:postcode":"91355",
    "sg:province":"CA",
    "sg:tags":[
        "mexican"
    ],
    "wof:name":"Rosarito Fresh Mexican Grill",
    "wof:placetype":"venue"
},
  "geometry": {"coordinates":[-118.56300400000001,34.435902],"type":"Point"}
}