{
  "type": "Feature",
  "properties": {
    "addr:full":"239 Padua Hills Place San Ysidro CA 92173",
    "addr:housenumber":"239",
    "addr:postcode":"92173",
    "addr:street":"Padua Hills Place",
    "iso:country":"US",
    "sg:address":"239 Padua Hills Place",
    "sg:city":"San Ysidro",
    "sg:classifiers":[
        {
            "category":"Real Estate",
            "subcategory":"Real Estate Operator",
            "type":"Services"
        }
    ],
    "sg:phone":"+1 619 428 6011",
    "sg:postcode":"92173",
    "sg:province":"CA",
    "sg:tags":[
        "apartment"
    ],
    "wof:name":"Cerro Carmel Apartments",
    "wof:placetype":"venue"
},
  "geometry": {"coordinates":[-117.046314,32.560326],"type":"Point"}
}