{
  "type": "Feature",
  "properties": {
    "iso:country":"US",
    "sg:address":"19618 Gault St",
    "sg:city":"Reseda",
    "sg:classifiers":[
        {
            "category":"Building & Trades",
            "subcategory":"Pest Control",
            "type":"Services"
        }
    ],
    "sg:phone":"+1 818 521 6892",
    "sg:postcode":"91335",
    "sg:province":"CA",
    "sg:website":"www.facilitypestcontrol.com",
    "wof:name":"Facility Pest Control",
    "wof:placetype":"venue"
},
  "geometry": {"coordinates":[-118.560698,34.198997],"type":"Point"}
}