{
  "type": "Feature",
  "properties": {
    "iso:country":"US",
    "sg:address":"178 E Main St",
    "sg:city":"El Cajon",
    "sg:classifiers":[
        {
            "category":"Real Estate",
            "subcategory":"Real Estate Agent",
            "type":"Services"
        }
    ],
    "sg:phone":"+1 619 401 7355",
    "sg:postcode":"92020",
    "sg:province":"CA",
    "wof:name":"Help U Sell Turnkey Properties",
    "wof:placetype":"venue"
},
  "geometry": {"coordinates":[-116.96045100000001,32.795005],"type":"Point"}
}