{
  "type": "Feature",
  "properties": {
    "addr:full":"2185 Churn Creek Rd Redding CA 96002",
    "addr:housenumber":"2185",
    "addr:postcode":"96002",
    "addr:street":"Churn Creek Rd",
    "iso:country":"US",
    "sg:address":"2185 Churn Creek Rd",
    "sg:city":"Redding",
    "sg:classifiers":[
        {
            "category":"Shopping",
            "subcategory":"Jewelry",
            "type":"Retail Goods"
        }
    ],
    "sg:phone":"+1 530 223 2373",
    "sg:postcode":"96002",
    "sg:province":"CA",
    "sg:tags":[
        "jeweler"
    ],
    "wof:name":"Schritter's Jewelry",
    "wof:placetype":"venue"
},
  "geometry": {"coordinates":[-122.352901,40.575657],"type":"Point"}
}