{
  "type": "Feature",
  "properties": {
    "addr:full":"22875 Savi Ranch Pkwy Yorba Linda CA 92887",
    "addr:housenumber":"22875",
    "addr:postcode":"92887",
    "addr:street":"Savi Ranch Pkwy",
    "iso:country":"US",
    "sg:address":"22875 Savi Ranch Pkwy",
    "sg:city":"Yorba Linda",
    "sg:classifiers":[
        {
            "category":"Building & Trades",
            "subcategory":"Construction",
            "type":"Services"
        }
    ],
    "sg:phone":"+1 714 282 1798",
    "sg:postcode":"92887",
    "sg:province":"CA",
    "sg:tags":[
        "contractor"
    ],
    "sg:website":"www.retaildevelopmentadvisors.com",
    "wof:name":"Retail Development Advisors",
    "wof:placetype":"venue"
},
  "geometry": {"coordinates":[-117.73693,33.87507],"type":"Point"}
}