{
  "type": "Feature",
  "properties": {
    "addr:full":"32188 Corte Utnehmer Temecula CA 92592",
    "addr:housenumber":"32188",
    "addr:postcode":"92592",
    "addr:street":"Corte Utnehmer",
    "iso:country":"US",
    "sg:address":"32188 Corte Utnehmer",
    "sg:city":"Temecula",
    "sg:classifiers":[
        {
            "category":"Professional",
            "type":"Services"
        },
        {
            "category":"Sports & Exercise",
            "subcategory":"Swimming Pool",
            "type":"Entertainment"
        }
    ],
    "sg:phone":"+1 951 302 2345",
    "sg:postcode":"92592",
    "sg:province":"CA",
    "sg:tags":[
        "spa",
        "repair",
        "hot",
        "tubs-repair"
    ],
    "sg:website":"http://www.getswimmingpoolservice.com",
    "wof:name":"Clean Sweep Pool Service",
    "wof:placetype":"venue"
},
  "geometry": {"coordinates":[-117.098392,33.489792],"type":"Point"}
}