{
  "type": "Feature",
  "properties": {
    "iso:country":"US",
    "sg:address":"182 N Bellah Ave",
    "sg:city":"Lindsay",
    "sg:classifiers":[
        {
            "category":"Restaurant",
            "type":"Food & Drink"
        }
    ],
    "sg:phone":"+1 559 562 3409",
    "sg:postcode":"93247",
    "sg:province":"CA",
    "sg:tags":[
        "eating",
        "religious",
        "organization"
    ],
    "wof:name":"Travel China Roads",
    "wof:placetype":"venue"
},
  "geometry": {"coordinates":[-119.086444,36.208435],"type":"Point"}
}