{
  "type": "Feature",
  "properties": {
    "iso:country":"US",
    "sg:address":"1252 Travis Blvd",
    "sg:city":"Fairfield",
    "sg:classifiers":[
        {
            "category":"Health Services",
            "subcategory":"Chiropractor",
            "type":"Services"
        }
    ],
    "sg:phone":"+1 707 426 1111",
    "sg:postcode":"94533",
    "sg:province":"CA",
    "sg:tags":[
        "medicine",
        "alternative",
        "practitioner"
    ],
    "sg:website":"http://www.kosakchiropractic.com",
    "wof:name":"Kosak Chiropractic Inc",
    "wof:placetype":"venue"
},
  "geometry": {"coordinates":[-122.048666,38.258186],"type":"Point"}
}