{
  "type": "Feature",
  "properties": {
    "iso:country":"US",
    "sg:address":"1589 Drew Rd",
    "sg:city":"El Centro",
    "sg:classifiers":[
        {
            "category":"Sports & Exercise",
            "subcategory":"Golf",
            "type":"Entertainment"
        }
    ],
    "sg:phone":"+1 760 352 7061",
    "sg:postcode":"92243",
    "sg:province":"CA",
    "sg:tags":[
        "course"
    ],
    "wof:name":"Rio Bend RV Resort Ranch",
    "wof:placetype":"venue"
},
  "geometry": {"coordinates":[-115.690387,32.762187],"type":"Point"}
}