{
  "type": "Feature",
  "properties": {
    "addr:full":"29 Alamo Sq Alamo CA 94507",
    "addr:housenumber":"29",
    "addr:postcode":"94507",
    "addr:street":"Alamo Sq",
    "iso:country":"US",
    "sg:address":"29 Alamo Sq",
    "sg:city":"Alamo",
    "sg:classifiers":[
        {
            "category":"Insurance",
            "subcategory":"Hazard Insurance",
            "type":"Services"
        },
        {
            "category":"Insurance",
            "subcategory":"Insurance Agent",
            "type":"Services"
        },
        {
            "category":"Insurance",
            "subcategory":"Life Insurance",
            "type":"Services"
        },
        {
            "category":"Insurance",
            "subcategory":"Title Insurance",
            "type":"Services"
        }
    ],
    "sg:phone":"+1 925 855 0657",
    "sg:postcode":"94507",
    "sg:province":"CA",
    "sg:tags":[
        "auto",
        "commercial",
        "business",
        "homeowner"
    ],
    "sg:website":"http://www.farmersagent.com/jherzog/",
    "wof:name":"James Herzog - Farmers Insurance",
    "wof:placetype":"venue"
},
  "geometry": {"coordinates":[-122.031755,37.849864],"type":"Point"}
}