{
  "type": "Feature",
  "properties": {
    "addr:full":"6906 Miramar Rd San Diego CA 92121",
    "addr:housenumber":"6906",
    "addr:postcode":"92121",
    "addr:street":"Miramar Rd",
    "iso:country":"US",
    "sg:address":"6906 Miramar Rd",
    "sg:city":"San Diego",
    "sg:classifiers":[
        {
            "category":"Professional",
            "subcategory":"Accounting & Tax Preparation",
            "type":"Services"
        }
    ],
    "sg:phone":"+1 858 530 2070",
    "sg:postcode":"92121",
    "sg:province":"CA",
    "sg:tags":[
        "return",
        "filing"
    ],
    "wof:name":"H & R Block Tax Svc",
    "wof:placetype":"venue"
},
  "geometry": {"coordinates":[-117.16703699999999,32.878399],"type":"Point"}
}