{
  "type": "Feature",
  "properties": {
    "iso:country":"US",
    "sg:address":"1264 Higuera St",
    "sg:city":"San Luis Obispo",
    "sg:classifiers":[
        {
            "category":"Health Services",
            "subcategory":"Health Practitioner",
            "type":"Services"
        }
    ],
    "sg:phone":"+1 805 541 0322",
    "sg:postcode":"93401",
    "sg:province":"CA",
    "sg:tags":[
        "psychologist"
    ],
    "wof:name":"San Luis Obispo Ctr",
    "wof:placetype":"venue"
},
  "geometry": {"coordinates":[-120.65730600000001,35.283141],"type":"Point"}
}