{
  "type": "Feature",
  "properties": {
    "addr:full":"1046 S Victoria Ave Los Angeles CA 90019",
    "addr:housenumber":"1046",
    "addr:postcode":"90019",
    "addr:street":"S Victoria Ave",
    "iso:country":"US",
    "sg:address":"1046 S Victoria Ave",
    "sg:city":"Los Angeles",
    "sg:classifiers":[
        {
            "category":"Professional",
            "type":"Services"
        }
    ],
    "sg:phone":"+1 323 935 0088",
    "sg:postcode":"90019",
    "sg:province":"CA",
    "wof:name":"Hanmi Opera Co Inc",
    "wof:placetype":"venue"
},
  "geometry": {"coordinates":[-118.32466599999999,34.054098],"type":"Point"}
}