{
  "type": "Feature",
  "properties": {
    "iso:country":"US",
    "sg:address":"3553 Atlantic Ave",
    "sg:city":"Long Beach",
    "sg:classifiers":[
        {
            "category":"Shopping",
            "type":"Retail Goods"
        }
    ],
    "sg:phone":"+1 562 423 5552",
    "sg:postcode":"90807",
    "sg:province":"CA",
    "sg:tags":[
        "trophy",
        "medal",
        "award"
    ],
    "wof:name":"GIVETHEMINCENTIVES.COM",
    "wof:placetype":"venue"
},
  "geometry": {"coordinates":[-118.185086,33.82105],"type":"Point"}
}