{
  "type": "Feature",
  "properties": {
    "addr:full":"1975 Placer St Redding CA 96001",
    "addr:housenumber":"1975",
    "addr:postcode":"96001",
    "addr:street":"Placer St",
    "iso:country":"US",
    "sg:address":"1975 Placer St",
    "sg:city":"Redding",
    "sg:classifiers":[
        {
            "category":"Insurance",
            "subcategory":"Hazard Insurance",
            "type":"Services"
        }
    ],
    "sg:phone":"+1 530 243 2886",
    "sg:postcode":"96001",
    "sg:province":"CA",
    "sg:tags":[
        "bond"
    ],
    "wof:name":"Godfather Bail Bonds",
    "wof:placetype":"venue"
},
  "geometry": {"coordinates":[-122.396716,40.580609],"type":"Point"}
}