{
  "type": "Feature",
  "properties": {
    "iso:country":"US",
    "sg:address":"1 Miramar St",
    "sg:city":"San Diego",
    "sg:classifiers":[
        {
            "category":"Real Estate",
            "subcategory":"Real Estate Operator",
            "type":"Services"
        }
    ],
    "sg:phone":"+1 858 822 3293",
    "sg:postcode":"92092",
    "sg:province":"CA",
    "sg:tags":[
        "apartment"
    ],
    "sg:website":"hds.ucsd.edu/onemiramar/",
    "wof:name":"One Miramar Street Apartments",
    "wof:placetype":"venue"
},
  "geometry": {"coordinates":[-117.268722,32.841373],"type":"Point"}
}