{
  "type": "Feature",
  "properties": {
    "addr:full":"3200 Kearney St Fremont CA 94538",
    "addr:housenumber":"3200",
    "addr:postcode":"94538",
    "addr:street":"Kearney St",
    "iso:country":"US",
    "sg:address":"3200 Kearney St",
    "sg:city":"Fremont",
    "sg:classifiers":[
        {
            "category":"Health Services",
            "subcategory":"Clinic",
            "type":"Services"
        },
        {
            "category":"Health Services",
            "subcategory":"Podiatrist",
            "type":"Services"
        },
        {
            "category":"Community Center",
            "type":"Public Place"
        },
        {
            "category":"Health Services",
            "subcategory":"Hospital",
            "type":"Services"
        }
    ],
    "sg:phone":"+1 510 490 1222",
    "sg:postcode":"94538",
    "sg:province":"CA",
    "sg:tags":[
        "physician",
        "medical",
        "surgeons"
    ],
    "sg:website":"http://pamf.org/fremont/",
    "wof:name":"Palo Alto Medical Foundation",
    "wof:placetype":"venue"
},
  "geometry": {"coordinates":[-121.974711,37.549179],"type":"Point"}
}