{
  "type": "Feature",
  "properties": {
    "iso:country":"US",
    "sg:address":"310 Locust St",
    "sg:city":"Pacific Grove",
    "sg:classifiers":[
        {
            "category":"Insurance",
            "subcategory":"Insurance Agent",
            "type":"Services"
        }
    ],
    "sg:phone":"+1 831 655 8670",
    "sg:postcode":"93950",
    "sg:province":"CA",
    "sg:website":"www.is4life.com",
    "wof:name":"Income Solutions For Life",
    "wof:placetype":"venue"
},
  "geometry": {"coordinates":[-121.925712,36.620899],"type":"Point"}
}