{
  "type": "Feature",
  "properties": {
    "addr:full":"29023 Rolando Rd Lake Elsinore CA 92530",
    "addr:postcode":"29023;92530",
    "addr:street":"Rolando Rd",
    "iso:country":"US",
    "sg:address":"29023 Rolando Rd",
    "sg:city":"Lake Elsinore",
    "sg:classifiers":[
        {
            "category":"Professional",
            "type":"Services"
        }
    ],
    "sg:phone":"+1 951 245 1150",
    "sg:postcode":"92530",
    "sg:province":"CA",
    "wof:name":"Kelly Akins",
    "wof:placetype":"venue"
},
  "geometry": {"coordinates":[-117.394717,33.700859],"type":"Point"}
}