{
  "type": "Feature",
  "properties": {
    "addr:full":"1532 San Bernardino Ave Pomona CA 91767",
    "addr:housenumber":"1532",
    "addr:postcode":"91767",
    "addr:street":"San Bernardino Ave",
    "iso:country":"US",
    "sg:address":"1532 San Bernardino Ave",
    "sg:city":"Pomona",
    "sg:classifiers":[
        {
            "category":"Health Services",
            "subcategory":"Doctor",
            "type":"Services"
        }
    ],
    "sg:phone":"+1 909 624 0392",
    "sg:postcode":"91767",
    "sg:province":"CA",
    "sg:tags":[
        "clinic"
    ],
    "wof:name":"Clinica Medica Villatoro",
    "wof:placetype":"venue"
},
  "geometry": {"coordinates":[-117.719246,34.075882],"type":"Point"}
}