{
  "type": "Feature",
  "properties": {
    "addr:full":"25840 Oak St Lomita CA 90717",
    "addr:housenumber":"25840",
    "addr:postcode":"90717",
    "addr:street":"Oak St",
    "iso:country":"US",
    "sg:address":"25840 Oak St",
    "sg:city":"Lomita",
    "sg:classifiers":[
        {
            "category":"Real Estate",
            "subcategory":"Real Estate Services",
            "type":"Services"
        }
    ],
    "sg:phone":"+1 310 539 8722",
    "sg:postcode":"90717",
    "sg:province":"CA",
    "sg:tags":[
        "management",
        "property"
    ],
    "wof:name":"J Handy And Services",
    "wof:placetype":"venue"
},
  "geometry": {"coordinates":[-118.317134,33.788461],"type":"Point"}
}