{
  "type": "Feature",
  "properties": {
    "addr:full":"19340 Red Hill Mine Rd Pine Grove CA 95665",
    "addr:housenumber":"19340",
    "addr:postcode":"95665",
    "addr:street":"Red Hill Mine Rd",
    "iso:country":"US",
    "sg:address":"19340 Red Hill Mine Rd",
    "sg:city":"Pine Grove",
    "sg:phone":"+1 925 784 7461",
    "sg:postcode":"95665",
    "sg:province":"CA",
    "sg:tags":[
        "forestry",
        "trucking"
    ],
    "wof:name":"DC Trucking",
    "wof:placetype":"venue"
},
  "geometry": {"coordinates":[-120.67247399999999,38.419013],"type":"Point"}
}