{
  "type": "Feature",
  "properties": {
    "iso:country":"US",
    "sg:address":"338 E Carson St Ste C",
    "sg:city":"Carson",
    "sg:classifiers":[
        {
            "category":"Retail",
            "subcategory":"Auto Repair",
            "type":"Services"
        }
    ],
    "sg:phone":"+1 310 830 9598",
    "sg:postcode":"90745",
    "sg:province":"CA",
    "wof:name":"Aquino's General Auto Repairs",
    "wof:placetype":"venue"
},
  "geometry": {"coordinates":[-118.270785,33.831452],"type":"Point"}
}