{
  "type": "Feature",
  "properties": {
    "iso:country":"US",
    "sg:address":"734 Fairmount Ave",
    "sg:city":"Pasadena",
    "sg:classifiers":[
        {
            "category":"Health Services",
            "subcategory":"Medical Lab",
            "type":"Services"
        }
    ],
    "sg:phone":"+1 626 397 5804",
    "sg:postcode":"91105",
    "sg:province":"CA",
    "sg:tags":[
        "laboratory"
    ],
    "sg:website":"www.hmri.org",
    "wof:name":"Huntington Medical Research",
    "wof:placetype":"venue"
},
  "geometry": {"coordinates":[-118.151706,34.132148],"type":"Point"}
}