{
  "type": "Feature",
  "properties": {
    "addr:full":"549 N Western Avenue Los Angeles CA 90004",
    "addr:housenumber":"549",
    "addr:postcode":"90004",
    "addr:street":"N Western Avenue",
    "iso:country":"US",
    "sg:address":"549 N Western Avenue",
    "sg:city":"Los Angeles",
    "sg:classifiers":[
        {
            "category":"Home & Garden",
            "subcategory":"Furniture",
            "type":"Retail Goods"
        }
    ],
    "sg:phone":"+1 323 957 9915",
    "sg:postcode":"90004",
    "sg:province":"CA",
    "sg:tags":[
        "store"
    ],
    "wof:name":"Home Decor Furniture",
    "wof:placetype":"venue"
},
  "geometry": {"coordinates":[-118.30925499999999,34.081329],"type":"Point"}
}