{
  "type": "Feature",
  "properties": {
    "iso:country":"US",
    "sg:address":"122 S Patterson Ave",
    "sg:city":"Santa Barbara",
    "sg:classifiers":[
        {
            "category":"Health Services",
            "subcategory":"Doctor",
            "type":"Services"
        }
    ],
    "sg:phone":"+1 805 964 4759",
    "sg:postcode":"93111",
    "sg:province":"CA",
    "sg:tags":[
        "dentist"
    ],
    "wof:name":"F Stanton Palmer DDS",
    "wof:placetype":"venue"
},
  "geometry": {"coordinates":[-119.80885499999999,34.43557],"type":"Point"}
}