{
  "type": "Feature",
  "properties": {
    "addr:full":"15831 Imperial Hwy La Mirada CA 90639",
    "addr:housenumber":"15831",
    "addr:postcode":"90639",
    "addr:street":"Imperial Hwy",
    "iso:country":"US",
    "sg:address":"15831 Imperial Hwy",
    "sg:city":"La Mirada",
    "sg:classifiers":[
        {
            "category":"Professional",
            "type":"Services"
        },
        {
            "category":"Restaurant",
            "type":"Food & Drink"
        }
    ],
    "sg:phone":"+1 562 902 8422",
    "sg:postcode":"90639",
    "sg:province":"CA",
    "sg:tags":[
        "filipino",
        "caterer"
    ],
    "sg:website":"www.lakusina.com/",
    "wof:name":"La Kusina - CLOSED EXCEPT FOR CATERING",
    "wof:placetype":"venue"
},
  "geometry": {"coordinates":[-117.993256,33.917332],"type":"Point"}
}