{
  "type": "Feature",
  "properties": {
    "addr:full":"10112 Casa de Oro Blvd Spring Valley CA 91977",
    "addr:housenumber":"10112",
    "addr:postcode":"91977",
    "addr:street":"Casa De Oro Blvd",
    "iso:country":"US",
    "sg:address":"10112 Casa de Oro Blvd",
    "sg:city":"Spring Valley",
    "sg:classifiers":[
        {
            "category":"Personal",
            "type":"Services"
        }
    ],
    "sg:phone":"+1 619 750 8136",
    "sg:postcode":"91977",
    "sg:province":"CA",
    "sg:tags":[
        "therapist",
        "massage"
    ],
    "wof:name":"Choices In Holistic Therapy",
    "wof:placetype":"venue"
},
  "geometry": {"coordinates":[-116.974964,32.75152],"type":"Point"}
}