{
  "type": "Feature",
  "properties": {
    "iso:country":"US",
    "sg:address":"6401 W Imperial Hwy",
    "sg:city":"Los Angeles",
    "sg:classifiers":[
        {
            "category":"Airline",
            "type":"Transportation"
        }
    ],
    "sg:phone":"+1 310 641 6307",
    "sg:postcode":"90045",
    "sg:province":"CA",
    "sg:tags":[
        "courier",
        "air"
    ],
    "wof:name":"Dynair Cfe Services",
    "wof:placetype":"venue"
},
  "geometry": {"coordinates":[-118.421274,33.931444],"type":"Point"}
}