{
  "type": "Feature",
  "properties": {
    "addr:full":"2047 University Ave Berkeley CA 94704",
    "addr:housenumber":"2047",
    "addr:postcode":"94704",
    "addr:street":"University Ave",
    "iso:country":"US",
    "sg:address":"2047 University Ave",
    "sg:city":"Berkeley",
    "sg:classifiers":[
        {
            "category":"Personal",
            "subcategory":"Massage",
            "type":"Services"
        }
    ],
    "sg:phone":"+1 510 649 9848",
    "sg:postcode":"94704",
    "sg:province":"CA",
    "sg:website":"www.magicfingers.com",
    "wof:name":"Magic Fingers",
    "wof:placetype":"venue"
},
  "geometry": {"coordinates":[-122.26958399999999,37.872177],"type":"Point"}
}