{
  "type": "Feature",
  "properties": {
    "addr:full":"899 E H St Chula Vista CA 91910",
    "addr:housenumber":"899",
    "addr:postcode":"91910",
    "addr:street":"E H St",
    "iso:country":"US",
    "sg:address":"899 E H St",
    "sg:city":"Chula Vista",
    "sg:classifiers":[
        {
            "category":"Restaurant",
            "type":"Food & Drink"
        }
    ],
    "sg:menulink":"http://www.allmenus.com/ca/san-diego/172136-burger-king/menu/",
    "sg:phone":"+1 619 482 4431",
    "sg:postcode":"91910",
    "sg:province":"CA",
    "sg:tags":[
        "burger",
        "american"
    ],
    "wof:name":"Burger King",
    "wof:placetype":"venue"
},
  "geometry": {"coordinates":[-117.021159,32.636458],"type":"Point"}
}