{
  "type": "Feature",
  "properties": {
    "addr:full":"2775 Cottage Way Sacramento CA 95825",
    "addr:housenumber":"2775",
    "addr:postcode":"95825",
    "addr:street":"Cottage Way",
    "iso:country":"US",
    "sg:address":"2775 Cottage Way",
    "sg:city":"Sacramento",
    "sg:classifiers":[
        {
            "category":"Professional",
            "subcategory":"Accounting & Tax Preparation",
            "type":"Services"
        }
    ],
    "sg:phone":"+1 916 974 1534",
    "sg:postcode":"95825",
    "sg:province":"CA",
    "sg:tags":[
        "return",
        "filing"
    ],
    "wof:name":"Beverly J Farris",
    "wof:placetype":"venue"
},
  "geometry": {"coordinates":[-121.396433,38.603423],"type":"Point"}
}