{
  "type": "Feature",
  "properties": {
    "iso:country":"US",
    "sg:address":"2307 D St",
    "sg:city":"La Verne",
    "sg:classifiers":[
        {
            "category":"Restaurant",
            "type":"Food & Drink"
        }
    ],
    "sg:phone":"+1 909 593 2239",
    "sg:postcode":"91750",
    "sg:province":"CA",
    "wof:name":"Aoki Japanese Restaurant",
    "wof:placetype":"venue"
},
  "geometry": {"coordinates":[-117.76988,34.10145],"type":"Point"}
}