{
  "type": "Feature",
  "properties": {
    "iso:country":"US",
    "sg:address":"2807 Loma Vista Rd",
    "sg:city":"Ventura",
    "sg:classifiers":[
        {
            "category":"Health Services",
            "subcategory":"Doctor",
            "type":"Services"
        }
    ],
    "sg:phone":"+1 805 643 1266",
    "sg:postcode":"93003",
    "sg:province":"CA",
    "sg:tags":[
        "dentist"
    ],
    "wof:name":"Paul F Hannah DDS",
    "wof:placetype":"venue"
},
  "geometry": {"coordinates":[-119.257739,34.275405],"type":"Point"}
}