{
  "type": "Feature",
  "properties": {
    "addr:full":"10025 Campo Rd Spring Valley CA 91977",
    "addr:housenumber":"10025",
    "addr:postcode":"91977",
    "addr:street":"Campo Rd",
    "iso:country":"US",
    "sg:address":"10025 Campo Rd",
    "sg:city":"Spring Valley",
    "sg:classifiers":[
        {
            "category":"Restaurant",
            "type":"Food & Drink"
        }
    ],
    "sg:phone":"+1 619 670 3555",
    "sg:postcode":"91977",
    "sg:province":"CA",
    "sg:tags":[
        "italian"
    ],
    "wof:name":"Gaetano's Italian Restaurant",
    "wof:placetype":"venue"
},
  "geometry": {"coordinates":[-116.980003,32.748001],"type":"Point"}
}