{
  "type": "Feature",
  "properties": {
    "iso:country":"US",
    "sg:address":"1355 Lawrence Dr",
    "sg:city":"Newbury Park",
    "sg:classifiers":[
        {
            "category":"Wholesale",
            "subcategory":"Hardware",
            "type":"Manufacturing & Wholesale Goods"
        }
    ],
    "sg:phone":"+1 805 375 4311",
    "sg:postcode":"91320",
    "sg:province":"CA",
    "sg:tags":[
        "fastener"
    ],
    "wof:name":"TSIA Total Svc Co",
    "wof:placetype":"venue"
},
  "geometry": {"coordinates":[-118.9299,34.195289],"type":"Point"}
}