{
  "type": "Feature",
  "properties": {
    "iso:country":"US",
    "sg:address":"161 Greentree Ln",
    "sg:city":"La Habra",
    "sg:classifiers":[
        {
            "category":"Real Estate",
            "subcategory":"Real Estate Operator",
            "type":"Services"
        }
    ],
    "sg:phone":"+1 562 690 8176",
    "sg:postcode":"90631",
    "sg:province":"CA",
    "sg:tags":[
        "building",
        "apartment"
    ],
    "wof:name":"William Ervin Apartments",
    "wof:placetype":"venue"
},
  "geometry": {"coordinates":[-117.931181,33.932581],"type":"Point"}
}