{
  "type": "Feature",
  "properties": {
    "iso:country":"US",
    "sg:address":"1711 Lila Ln",
    "sg:city":"La Canada Fltrdg",
    "sg:classifiers":[
        {
            "category":"Professional",
            "subcategory":"Management & Consulting",
            "type":"Services"
        }
    ],
    "sg:phone":"+1 818 790 0775",
    "sg:postcode":"91011",
    "sg:province":"CA",
    "sg:tags":[
        "counselor",
        "public",
        "relations"
    ],
    "sg:website":"www.giftlistmedia.com",
    "wof:name":"Gift List",
    "wof:placetype":"venue"
},
  "geometry": {"coordinates":[-118.21365400000001,34.216507],"type":"Point"}
}