{
  "type": "Feature",
  "properties": {
    "iso:country":"US",
    "sg:address":"15021 Bloomfield Ave",
    "sg:city":"Norwalk",
    "sg:classifiers":[
        {
            "category":"Social Services",
            "subcategory":"Child Care",
            "type":"Services"
        }
    ],
    "sg:phone":"+1 562 404 8806",
    "sg:postcode":"90650",
    "sg:province":"CA",
    "sg:tags":[
        "day"
    ],
    "sg:website":"www.nlmusd.k12.ca.us",
    "wof:name":"Academic Recreational Child Care-Norwlk-La Mirada",
    "wof:placetype":"venue"
},
  "geometry": {"coordinates":[-118.42864,33.894838],"type":"Point"}
}