{
  "type": "Feature",
  "properties": {
    "iso:country":"US",
    "sg:address":"314 Wisconsin Ave",
    "sg:city":"Oceanside",
    "sg:classifiers":[
        {
            "category":"Wholesale",
            "subcategory":"Medical Equipment & Supplies",
            "type":"Manufacturing & Wholesale Goods"
        }
    ],
    "sg:phone":"+1 760 722 3939",
    "sg:postcode":"92054",
    "sg:province":"CA",
    "sg:tags":[
        "physician",
        "surgeon"
    ],
    "wof:name":"Project Health Medical Systems",
    "wof:placetype":"venue"
},
  "geometry": {"coordinates":[-117.374664,33.187827],"type":"Point"}
}