{
  "type": "Feature",
  "properties": {
    "iso:country":"US",
    "sg:address":"8055 W Manchester Ave",
    "sg:city":"Playa Del Rey",
    "sg:classifiers":[
        {
            "category":"Wholesale",
            "subcategory":"Furniture",
            "type":"Manufacturing & Wholesale Goods"
        }
    ],
    "sg:phone":"+1 310 390 8506",
    "sg:postcode":"90293",
    "sg:province":"CA",
    "wof:name":"Ideal Office Interiors",
    "wof:placetype":"venue"
},
  "geometry": {"coordinates":[-118.436442,33.959335],"type":"Point"}
}