{
  "type": "Feature",
  "properties": {
    "addr:full":"1455 Deauville Pl Costa Mesa CA 92626",
    "addr:housenumber":"1455",
    "addr:postcode":"92626",
    "addr:street":"Deauville Pl",
    "iso:country":"US",
    "sg:address":"1455 Deauville Pl",
    "sg:city":"Costa Mesa",
    "sg:classifiers":[
        {
            "category":"Building & Trades",
            "subcategory":"Construction",
            "type":"Services"
        }
    ],
    "sg:phone":"+1 714 546 0070",
    "sg:postcode":"92626",
    "sg:province":"CA",
    "sg:tags":[
        "repairing",
        "remodeling",
        "contractor"
    ],
    "wof:name":"Appraisal Remedies",
    "wof:placetype":"venue"
},
  "geometry": {"coordinates":[-117.91767,33.68547],"type":"Point"}
}