{
  "type": "Feature",
  "properties": {
    "iso:country":"US",
    "sg:address":"42186 Thornton Ave",
    "sg:city":"Hemet",
    "sg:classifiers":[
        {
            "category":"Building & Trades",
            "subcategory":"Landscaping Services",
            "type":"Services"
        }
    ],
    "sg:phone":"+1 951 927 3646",
    "sg:postcode":"92544",
    "sg:province":"CA",
    "sg:tags":[
        "consultant",
        "designer",
        "landscape"
    ],
    "wof:name":"Boyd, L Eugene Designer",
    "wof:placetype":"venue"
},
  "geometry": {"coordinates":[-116.92491200000001,33.725955],"type":"Point"}
}