{
  "type": "Feature",
  "properties": {
    "addr:full":"460 Sierra Madre Villa Ave Pasadena CA 91107",
    "addr:housenumber":"460",
    "addr:postcode":"91107",
    "addr:street":"Sierra Madre Villa Ave",
    "iso:country":"US",
    "sg:address":"460 Sierra Madre Villa Ave",
    "sg:city":"Pasadena",
    "sg:classifiers":[
        {
            "category":"Professional",
            "subcategory":"Computer Services",
            "type":"Services"
        }
    ],
    "sg:phone":"+1 626 351 7114",
    "sg:postcode":"91107",
    "sg:province":"CA",
    "sg:tags":[
        "retrieval"
    ],
    "wof:name":"Earthlink Inc",
    "wof:placetype":"venue"
},
  "geometry": {"coordinates":[-118.08180299999999,34.155245],"type":"Point"}
}