{
  "type": "Feature",
  "properties": {
    "iso:country":"US",
    "sg:address":"30071 Industrial Pkwy",
    "sg:city":"Union City",
    "sg:classifiers":[
        {
            "category":"Travel",
            "subcategory":"Travel Agent",
            "type":"Entertainment"
        }
    ],
    "sg:phone":"+1 510 441 0271",
    "sg:postcode":"94544",
    "sg:province":"CA",
    "sg:tags":[
        "agency",
        "bureau"
    ],
    "wof:name":"CEA Travel",
    "wof:placetype":"venue"
},
  "geometry": {"coordinates":[-122.06679,37.612363],"type":"Point"}
}