{
  "type": "Feature",
  "properties": {
    "addr:full":"100 14th St Oakland CA 94612",
    "addr:housenumber":"100",
    "addr:postcode":"94612",
    "addr:street":"14Th St",
    "iso:country":"US",
    "sg:address":"100 14th St",
    "sg:city":"Oakland",
    "sg:classifiers":[
        {
            "category":"Government",
            "subcategory":"Office",
            "type":"Public Place"
        }
    ],
    "sg:phone":"+1 510 271 5136",
    "sg:postcode":"94612",
    "sg:province":"CA",
    "wof:name":"Alameda Personnel & Labor",
    "wof:placetype":"venue"
},
  "geometry": {"coordinates":[-122.264071,37.801572],"type":"Point"}
}