{
  "type": "Feature",
  "properties": {
    "addr:full":"3200 W Century Blvd Inglewood CA 90303",
    "addr:housenumber":"3200",
    "addr:postcode":"90303",
    "addr:street":"W Century Blvd",
    "iso:country":"US",
    "sg:address":"3200 W Century Blvd",
    "sg:city":"Inglewood",
    "sg:classifiers":[
        {
            "category":"Food & Beverages",
            "subcategory":"Groceries & Convenience Stores",
            "type":"Retail Goods"
        }
    ],
    "sg:phone":"+1 310 672 6890",
    "sg:postcode":"90303",
    "sg:province":"CA",
    "wof:name":"Ralphs",
    "wof:placetype":"venue"
},
  "geometry": {"coordinates":[-118.327918,33.945328],"type":"Point"}
}