{
  "type": "Feature",
  "properties": {
    "addr:full":"25371 Mountainwood Way Lake Forest CA 92630",
    "addr:housenumber":"25371",
    "addr:postcode":"92630",
    "addr:street":"Mountainwood Way",
    "iso:country":"US",
    "sg:address":"25371 Mountainwood Way",
    "sg:city":"Lake Forest",
    "sg:classifiers":[
        {
            "category":"Professional",
            "subcategory":"Business Services",
            "type":"Services"
        }
    ],
    "sg:phone":"+1 949 215 5296",
    "sg:postcode":"92630",
    "sg:province":"CA",
    "sg:tags":[
        "drafting"
    ],
    "wof:name":"Product Design Labs",
    "wof:placetype":"venue"
},
  "geometry": {"coordinates":[-117.687258,33.653355],"type":"Point"}
}