{
  "type": "Feature",
  "properties": {
    "addr:full":"7470 Carmelo Ave Tracy CA 95304",
    "addr:housenumber":"7470",
    "addr:postcode":"95304",
    "addr:street":"Carmelo Ave",
    "iso:country":"US",
    "sg:address":"7470 Carmelo Ave",
    "sg:city":"Tracy",
    "sg:classifiers":[
        {
            "category":"Professional",
            "subcategory":"Engineering",
            "type":"Services"
        },
        {
            "category":"Retail",
            "subcategory":"Auto Repair",
            "type":"Services"
        }
    ],
    "sg:phone":"+1 209 836 3255",
    "sg:postcode":"95304",
    "sg:province":"CA",
    "sg:tags":[
        "shop",
        "automobile",
        "consulting",
        "machine",
        "engineer"
    ],
    "wof:name":"N Q Engineering Inc.",
    "wof:placetype":"venue"
},
  "geometry": {"coordinates":[-121.39896400000001,37.741894],"type":"Point"}
}