{
  "type": "Feature",
  "properties": {
    "addr:full":"27480 Ynez Rd Temecula CA 92591",
    "addr:housenumber":"27480",
    "addr:postcode":"92591",
    "addr:street":"Ynez Rd",
    "iso:country":"US",
    "sg:address":"27480 Ynez Rd",
    "sg:city":"Temecula",
    "sg:classifiers":[
        {
            "category":"Restaurant",
            "type":"Food & Drink"
        }
    ],
    "sg:menulink":"http://www.allmenus.com/ca/murrieta/7477-rubios/menu/",
    "sg:phone":"+1 951 694 9948",
    "sg:postcode":"92591",
    "sg:province":"CA",
    "sg:tags":[
        "seafood",
        "mexican",
        "american"
    ],
    "wof:name":"Rubio's",
    "wof:placetype":"venue"
},
  "geometry": {"coordinates":[-117.15039299999999,33.507789],"type":"Point"}
}