{
  "type": "Feature",
  "properties": {
    "addr:full":"1825 S Main St Lakeport CA 95453",
    "addr:housenumber":"1825",
    "addr:postcode":"95453",
    "addr:street":"S Main St",
    "iso:country":"US",
    "sg:address":"1825 S Main St",
    "sg:city":"Lakeport",
    "sg:classifiers":[
        {
            "category":"Government",
            "subcategory":"Office",
            "type":"Public Place"
        }
    ],
    "sg:phone":"+1 707 263 5316",
    "sg:postcode":"95453",
    "sg:province":"CA",
    "wof:name":"Lake County Heavy Eqpt Shop",
    "wof:placetype":"venue"
},
  "geometry": {"coordinates":[-122.91612499999999,39.029151],"type":"Point"}
}