{
  "type": "Feature",
  "properties": {
    "addr:full":"205 Fernwood Way Dixon CA 95620",
    "addr:housenumber":"205",
    "addr:postcode":"95620",
    "addr:street":"Fernwood Way",
    "iso:country":"US",
    "sg:address":"205 Fernwood Way",
    "sg:city":"Dixon",
    "sg:classifiers":[
        {
            "category":"Building & Trades",
            "subcategory":"Electrical",
            "type":"Services"
        }
    ],
    "sg:phone":"+1 530 681 1472",
    "sg:postcode":"95620",
    "sg:province":"CA",
    "sg:tags":[
        "electrician"
    ],
    "wof:name":"Hensley 5 Electric",
    "wof:placetype":"venue"
},
  "geometry": {"coordinates":[-121.834412,38.4444],"type":"Point"}
}