{
  "type": "Feature",
  "properties": {
    "addr:full":"126 Rochester St Costa Mesa CA 92627",
    "addr:housenumber":"126",
    "addr:postcode":"92627",
    "addr:street":"Rochester St",
    "iso:country":"US",
    "sg:address":"126 Rochester St",
    "sg:city":"Costa Mesa",
    "sg:classifiers":[
        {
            "category":"Building & Trades",
            "subcategory":"Construction",
            "type":"Services"
        }
    ],
    "sg:phone":"+1 714 997 1800",
    "sg:postcode":"92627",
    "sg:province":"CA",
    "sg:tags":[
        "air",
        "heating",
        "conditioning/hvac"
    ],
    "wof:name":"Dependable Graham Air Conditioning Inc",
    "wof:placetype":"venue"
},
  "geometry": {"coordinates":[-117.91999800000001,33.639198],"type":"Point"}
}