{
  "type": "Feature",
  "properties": {
    "addr:full":"145 N N St Tulare CA 93274",
    "addr:housenumber":"145",
    "addr:postcode":"93274",
    "addr:street":"N N St",
    "iso:country":"US",
    "sg:address":"145 N N St",
    "sg:city":"Tulare",
    "sg:classifiers":[
        {
            "category":"Banks & Credit Unions",
            "subcategory":"Investment Brokerage",
            "type":"Services"
        }
    ],
    "sg:phone":"+1 559 688 5618",
    "sg:postcode":"93274",
    "sg:province":"CA",
    "sg:tags":[
        "security"
    ],
    "wof:name":"W A Richmond",
    "wof:placetype":"venue"
},
  "geometry": {"coordinates":[-119.342324,36.209305],"type":"Point"}
}