{
  "type": "Feature",
  "properties": {
    "addr:full":"5143 W Adams Blvd Los Angeles CA 90016",
    "addr:housenumber":"5143",
    "addr:postcode":"90016",
    "addr:street":"W Adams Blvd",
    "iso:country":"US",
    "sg:address":"5143 W Adams Blvd",
    "sg:city":"Los Angeles",
    "sg:classifiers":[
        {
            "category":"Personal",
            "type":"Services"
        }
    ],
    "sg:phone":"+1 323 933 7739",
    "sg:postcode":"90016",
    "sg:province":"CA",
    "sg:tags":[
        "mover"
    ],
    "sg:website":"www.jbmoving.com",
    "wof:name":"JB Moving & Delivery",
    "wof:placetype":"venue"
},
  "geometry": {"coordinates":[-118.353393,34.032728],"type":"Point"}
}