{
  "type": "Feature",
  "properties": {
    "addr:full":"562 Central Ave Shafter CA 93263",
    "addr:housenumber":"562",
    "addr:postcode":"93263",
    "addr:street":"Central Ave",
    "iso:country":"US",
    "sg:address":"562 Central Ave",
    "sg:city":"Shafter",
    "sg:classifiers":[
        {
            "category":"Wholesale",
            "subcategory":"Toys & Hobbies",
            "type":"Manufacturing & Wholesale Goods"
        }
    ],
    "sg:phone":"+1 661 746 2842",
    "sg:postcode":"93263",
    "sg:province":"CA",
    "sg:tags":[
        "firework"
    ],
    "wof:name":"Zambelli Fireworks",
    "wof:placetype":"venue"
},
  "geometry": {"coordinates":[-119.27276999999999,35.504025],"type":"Point"}
}