{
  "type": "Feature",
  "properties": {
    "iso:country":"US",
    "sg:address":"4779 S Broadway",
    "sg:city":"Los Angeles",
    "sg:classifiers":[
        {
            "category":"Building & Trades",
            "subcategory":"Cleaning & Sanitation",
            "type":"Services"
        },
        {
            "category":"Building & Trades",
            "subcategory":"Construction",
            "type":"Services"
        }
    ],
    "sg:phone":"+1 323 232 6787",
    "sg:postcode":"90037",
    "sg:province":"CA",
    "sg:tags":[
        "contractor",
        "carpet"
    ],
    "wof:name":"American Construction Enterprises",
    "wof:placetype":"venue"
},
  "geometry": {"coordinates":[-118.2782,33.999255],"type":"Point"}
}