{
  "type": "Feature",
  "properties": {
    "iso:country":"US",
    "sg:address":"8561 Whitaker St",
    "sg:city":"Buena Park",
    "sg:classifiers":[
        {
            "category":"Building & Trades",
            "subcategory":"Plumbing",
            "type":"Services"
        }
    ],
    "sg:phone":"+1 714 994 1971",
    "sg:postcode":"90621",
    "sg:province":"CA",
    "sg:website":"www.vernesplumbing.com",
    "wof:name":"Verne's Plumbing",
    "wof:placetype":"venue"
},
  "geometry": {"coordinates":[-117.983698,33.866654],"type":"Point"}
}