{
  "type": "Feature",
  "properties": {
    "iso:country":"US",
    "sg:address":"1689 Arden Way Ste 1090",
    "sg:city":"Sacramento",
    "sg:classifiers":[
        {
            "category":"Shopping",
            "subcategory":"Gifts & Souvenirs",
            "type":"Retail Goods"
        },
        {
            "category":"Health Services",
            "subcategory":"Nursing And Care Facility",
            "type":"Services"
        }
    ],
    "sg:phone":"+1 916 922 3136",
    "sg:postcode":"95815",
    "sg:province":"CA",
    "sg:tags":[
        "shop",
        "equipment",
        "massage",
        "supply"
    ],
    "sg:website":"http://www.brookstone.com",
    "wof:name":"Brookstone",
    "wof:placetype":"venue"
},
  "geometry": {"coordinates":[-121.426852,38.599594],"type":"Point"}
}