{
  "type": "Feature",
  "properties": {
    "iso:country":"US",
    "sg:address":"30211 Ave de Las Banderas",
    "sg:city":"Rancho Santa Margarita",
    "sg:classifiers":[
        {
            "category":"Manufacturing",
            "subcategory":"Chemicals & Compounds",
            "type":"Manufacturing & Wholesale Goods"
        }
    ],
    "sg:phone":"+1 949 212 1863",
    "sg:postcode":"92688",
    "sg:province":"CA",
    "sg:tags":[
        "preparation",
        "mfg"
    ],
    "wof:name":"Lubrizol Corporation",
    "wof:placetype":"venue"
},
  "geometry": {"coordinates":[-117.603272,33.634444],"type":"Point"}
}