{
  "type": "Feature",
  "properties": {
    "addr:full":"1915 N Tustin St Orange CA 92865",
    "addr:housenumber":"1915",
    "addr:postcode":"92865",
    "addr:street":"N Tustin St",
    "iso:country":"US",
    "sg:address":"1915 N Tustin St",
    "sg:city":"Orange",
    "sg:classifiers":[
        {
            "category":"Home & Garden",
            "subcategory":"Carpets & Floor Coverings",
            "type":"Retail Goods"
        }
    ],
    "sg:phone":"+1 714 998 3200",
    "sg:postcode":"92865",
    "sg:province":"CA",
    "sg:tags":[
        "mattress"
    ],
    "wof:name":"Simmons Mattress Gallery",
    "wof:placetype":"venue"
},
  "geometry": {"coordinates":[-117.835999,33.820499],"type":"Point"}
}