{
  "type": "Feature",
  "properties": {
    "addr:full":"35436 Panorama Dr Yucaipa CA 92399",
    "addr:housenumber":"35436",
    "addr:postcode":"ca 92399",
    "addr:street":"Panorama Dr",
    "iso:country":"US",
    "sg:address":"35436 Panorama Dr",
    "sg:city":"Yucaipa",
    "sg:classifiers":[
        {
            "category":"Professional",
            "type":"Services"
        }
    ],
    "sg:phone":"+1 909 790 9359",
    "sg:postcode":"92399",
    "sg:province":"CA",
    "wof:name":"Rosemarinos Inc",
    "wof:placetype":"venue"
},
  "geometry": {"coordinates":[-117.031341,34.043065],"type":"Point"}
}