{
  "type": "Feature",
  "properties": {
    "iso:country":"US",
    "sg:address":"671 Via Alondra",
    "sg:city":"Camarillo",
    "sg:classifiers":[
        {
            "category":"Wholesale",
            "subcategory":"Office Equipment",
            "type":"Manufacturing & Wholesale Goods"
        }
    ],
    "sg:phone":"+1 805 484 3957",
    "sg:postcode":"93012",
    "sg:province":"CA",
    "sg:tags":[
        "machine",
        "mailing"
    ],
    "wof:name":"Golden State Systems",
    "wof:placetype":"venue"
},
  "geometry": {"coordinates":[-119.025201,34.223984],"type":"Point"}
}