{
  "type": "Feature",
  "properties": {
    "iso:country":"US",
    "sg:address":"301 Main St",
    "sg:city":"Placerville",
    "sg:classifiers":[
        {
            "category":"Shopping",
            "subcategory":"Gifts & Souvenirs",
            "type":"Retail Goods"
        }
    ],
    "sg:phone":"+1 530 626 1050",
    "sg:postcode":"95667",
    "sg:province":"CA",
    "sg:tags":[
        "shop"
    ],
    "wof:name":"Ambiance",
    "wof:placetype":"venue"
},
  "geometry": {"coordinates":[-120.801306,38.728903],"type":"Point"}
}