{
  "type": "Feature",
  "properties": {
    "addr:full":"3739 Balboa Street San Francisco CA 94121",
    "addr:housenumber":"3739",
    "addr:postcode":"94121",
    "addr:street":"Balboa Street",
    "iso:country":"US",
    "sg:address":"3739 Balboa Street",
    "sg:city":"San Francisco",
    "sg:classifiers":[
        {
            "category":"Communications",
            "type":"Services"
        }
    ],
    "sg:phone":"+1 415 751 8323",
    "sg:postcode":"94121",
    "sg:province":"CA",
    "sg:tags":[
        "web",
        "design"
    ],
    "wof:name":"Media Pro",
    "wof:placetype":"venue"
},
  "geometry": {"coordinates":[-122.49900100000001,37.7756],"type":"Point"}
}