{
  "type": "Feature",
  "properties": {
    "iso:country":"US",
    "sg:address":"785 Grand Ave Ste 200",
    "sg:city":"Carlsbad",
    "sg:classifiers":[
        {
            "category":"Education",
            "subcategory":"Special Training",
            "type":"Public Place"
        }
    ],
    "sg:phone":"+1 760 434 7720",
    "sg:postcode":"92008",
    "sg:province":"CA",
    "sg:tags":[
        "educational",
        "tutoring"
    ],
    "wof:name":"Foundations For Reading & Learning",
    "wof:placetype":"venue"
},
  "geometry": {"coordinates":[-117.346672,33.162345],"type":"Point"}
}