{
  "type": "Feature",
  "properties": {
    "iso:country":"US",
    "sg:address":"537 Georgia St",
    "sg:city":"Vallejo",
    "sg:classifiers":[
        {
            "category":"Personal",
            "subcategory":"Beauty Salon",
            "type":"Services"
        }
    ],
    "sg:phone":"+1 707 648 9737",
    "sg:postcode":"94590",
    "sg:province":"CA",
    "wof:name":"First Impression Beauty",
    "wof:placetype":"venue"
},
  "geometry": {"coordinates":[-122.25376900000001,38.101003],"type":"Point"}
}