{
  "type": "Feature",
  "properties": {
    "addr:full":"1232 Otay Valley Rd San Diego CA 92154",
    "addr:housenumber":"1232",
    "addr:postcode":"92154",
    "addr:street":"Otay Valley Rd",
    "iso:country":"US",
    "sg:address":"1232 Otay Valley Rd",
    "sg:city":"San Diego",
    "sg:classifiers":[
        {
            "category":"Wholesale",
            "subcategory":"Auto Parts",
            "type":"Manufacturing & Wholesale Goods"
        }
    ],
    "sg:phone":"+1 619 661 6262",
    "sg:postcode":"92154",
    "sg:province":"CA",
    "sg:tags":[
        "automobile",
        "wrecking"
    ],
    "wof:name":"Silverado",
    "wof:placetype":"venue"
},
  "geometry": {"coordinates":[-116.99789699999999,32.571984],"type":"Point"}
}