{
  "type": "Feature",
  "properties": {
    "iso:country":"US",
    "sg:address":"13654 Nimes Ct",
    "sg:city":"Chino Hills",
    "sg:classifiers":[
        {
            "category":"Wholesale",
            "subcategory":"Non-durable Goods",
            "type":"Manufacturing & Wholesale Goods"
        },
        {
            "category":"Manufacturing",
            "subcategory":"Motor Vehicles & Parts",
            "type":"Manufacturing & Wholesale Goods"
        }
    ],
    "sg:phone":"+1 909 591 7672",
    "sg:postcode":"91709",
    "sg:province":"CA",
    "sg:tags":[
        "importer"
    ],
    "wof:name":"Rodcas Imports",
    "wof:placetype":"venue"
},
  "geometry": {"coordinates":[-117.750839,34.003375],"type":"Point"}
}