{
  "type": "Feature",
  "properties": {
    "addr:full":"3001 N Sherwood Dr Fresno CA 93722",
    "addr:housenumber":"3001",
    "addr:postcode":"93722",
    "addr:street":"N Sherwood Dr",
    "iso:country":"US",
    "sg:address":"3001 N Sherwood Dr",
    "sg:city":"Fresno",
    "sg:classifiers":[
        {
            "category":"Building & Trades",
            "subcategory":"Landscaping Services",
            "type":"Services"
        }
    ],
    "sg:phone":"+1 559 250 3234",
    "sg:postcode":"93722",
    "sg:province":"CA",
    "sg:tags":[
        "lawn",
        "maintenance",
        "grounds"
    ],
    "wof:name":"Casillas Lawn Svc",
    "wof:placetype":"venue"
},
  "geometry": {"coordinates":[-119.85511200000001,36.779415],"type":"Point"}
}