{
  "type": "Feature",
  "properties": {
    "addr:full":"2739 Taylor St San Francisco CA 94133",
    "addr:housenumber":"2739",
    "addr:postcode":"94133",
    "addr:street":"Taylor St",
    "iso:country":"US",
    "sg:address":"2739 Taylor St",
    "sg:city":"San Francisco",
    "sg:classifiers":[
        {
            "category":"Restaurant",
            "type":"Food & Drink"
        }
    ],
    "sg:menulink":"http://www.allmenus.com/ca/san-francisco/171664-burger-king/menu/",
    "sg:phone":"+1 415 674 8159",
    "sg:postcode":"94133",
    "sg:province":"CA",
    "sg:tags":[
        "burger",
        "american"
    ],
    "wof:name":"Burger King",
    "wof:placetype":"venue"
},
  "geometry": {"coordinates":[-122.416099,37.807886],"type":"Point"}
}