{
  "type": "Feature",
  "properties": {
    "iso:country":"US",
    "sg:address":"14508 S Western Avenue",
    "sg:city":"Gardena",
    "sg:classifiers":[
        {
            "category":"Travel",
            "subcategory":"Hotels & Motels",
            "type":"Entertainment"
        }
    ],
    "sg:phone":"+1 310 719 7119",
    "sg:postcode":"90249",
    "sg:province":"CA",
    "wof:name":"Budget Hotel",
    "wof:placetype":"venue"
},
  "geometry": {"coordinates":[-118.309277,33.899582],"type":"Point"}
}