{
  "type": "Feature",
  "properties": {
    "addr:full":"1316 E 29th St Signal Hill CA 90755",
    "addr:housenumber":"1316",
    "addr:postcode":"90755",
    "addr:street":"E 29Th St",
    "iso:country":"US",
    "sg:address":"1316 E 29th St",
    "sg:city":"Signal Hill",
    "sg:classifiers":[
        {
            "category":"Wholesale",
            "subcategory":"Non-durable Goods",
            "type":"Manufacturing & Wholesale Goods"
        }
    ],
    "sg:phone":"+1 562 490 2160",
    "sg:postcode":"90755",
    "sg:province":"CA",
    "sg:tags":[
        "button"
    ],
    "sg:website":"www.remarkablethings.com",
    "wof:name":"Remarkable Things",
    "wof:placetype":"venue"
},
  "geometry": {"coordinates":[-118.175077,33.809749],"type":"Point"}
}