{
  "type": "Feature",
  "properties": {
    "addr:full":"837 W Arrow Hwy Glendora CA 91740",
    "addr:housenumber":"837",
    "addr:postcode":"91740",
    "addr:street":"W Arrow Hwy",
    "iso:country":"US",
    "sg:address":"837 W Arrow Hwy",
    "sg:city":"Glendora",
    "sg:classifiers":[
        {
            "category":"Education",
            "subcategory":"School",
            "type":"Public Place"
        }
    ],
    "sg:phone":"+1 626 339 1244",
    "sg:postcode":"91740",
    "sg:province":"CA",
    "sg:website":"www.liveoaknps.org",
    "wof:name":"Live Oak Canyon School",
    "wof:placetype":"venue"
},
  "geometry": {"coordinates":[-117.876752,34.105563],"type":"Point"}
}