{
  "type": "Feature",
  "properties": {
    "addr:full":"401 E 17th Street Costa Mesa CA 92627",
    "addr:housenumber":"401",
    "addr:postcode":"92627",
    "addr:street":"E 17Th Street",
    "iso:country":"US",
    "sg:address":"401 E 17th Street",
    "sg:city":"Costa Mesa",
    "sg:classifiers":[
        {
            "category":"Arts & Performance",
            "subcategory":"Arts Center",
            "type":"Entertainment"
        }
    ],
    "sg:phone":"+1 949 574 4905",
    "sg:postcode":"92627",
    "sg:province":"CA",
    "sg:tags":[
        "performing"
    ],
    "sg:website":"www.tiffanydance.com",
    "wof:name":"Tiffany's Dance Academy",
    "wof:placetype":"venue"
},
  "geometry": {"coordinates":[-117.912049,33.630792],"type":"Point"}
}