{
  "type": "Feature",
  "properties": {
    "addr:full":"1900 S La Brea Ave Los Angeles CA 90016",
    "addr:housenumber":"1900",
    "addr:postcode":"90016",
    "addr:street":"S;Brea Ave",
    "iso:country":"US",
    "sg:address":"1900 S La Brea Ave",
    "sg:city":"Los Angeles",
    "sg:classifiers":[
        {
            "category":"Food & Beverages",
            "subcategory":"Groceries & Convenience Stores",
            "type":"Retail Goods"
        }
    ],
    "sg:phone":"+1 323 938 1233",
    "sg:postcode":"90016",
    "sg:province":"CA",
    "wof:name":"777 Market",
    "wof:placetype":"venue"
},
  "geometry": {"coordinates":[-118.348,34.040298],"type":"Point"}
}