{
  "type": "Feature",
  "properties": {
    "addr:full":"880 Apollo St, Ste 245 El Segundo CA 90245",
    "addr:housenumber":"880",
    "addr:postcode":"90245",
    "addr:street":"Apollo St Ste 245",
    "iso:country":"US",
    "sg:address":"880 Apollo St, Ste 245",
    "sg:city":"El Segundo",
    "sg:classifiers":[
        {
            "category":"Professional",
            "type":"Services"
        },
        {
            "category":"Professional",
            "subcategory":"Business Services",
            "type":"Services"
        }
    ],
    "sg:phone":"+1 310 524 1555",
    "sg:postcode":"90245",
    "sg:province":"CA",
    "sg:tags":[
        "delivery",
        "courier"
    ],
    "sg:website":"www.tmllc.com/",
    "wof:name":"Transportation Management Llc",
    "wof:placetype":"venue"
},
  "geometry": {"coordinates":[-118.38652,33.903519],"type":"Point"}
}