{
  "type": "Feature",
  "properties": {
    "addr:full":"5443 College Oak Dr Sacramento CA 95841",
    "addr:housenumber":"5443",
    "addr:postcode":"95841",
    "addr:street":"College Oak Dr",
    "iso:country":"US",
    "sg:address":"5443 College Oak Dr",
    "sg:city":"Sacramento",
    "sg:classifiers":[
        {
            "category":"Shopping",
            "type":"Retail Goods"
        }
    ],
    "sg:phone":"+1 916 256 8427",
    "sg:postcode":"95841",
    "sg:province":"CA",
    "sg:tags":[
        "miscellaneous",
        "store"
    ],
    "wof:name":"Executive VIP",
    "wof:placetype":"venue"
},
  "geometry": {"coordinates":[-121.350589,38.665811],"type":"Point"}
}