{
  "type": "Feature",
  "properties": {
    "addr:full":"1276 N Main St Salinas CA 93906",
    "addr:housenumber":"1276",
    "addr:postcode":"93906",
    "addr:street":"N Main St",
    "iso:country":"US",
    "sg:address":"1276 N Main St",
    "sg:city":"Salinas",
    "sg:classifiers":[
        {
            "category":"Personal",
            "subcategory":"Beauty Salon",
            "type":"Services"
        }
    ],
    "sg:phone":"+1 831 449 0769",
    "sg:postcode":"93906",
    "sg:province":"CA",
    "wof:name":"Designers Styling Salon",
    "wof:placetype":"venue"
},
  "geometry": {"coordinates":[-121.65192500000001,36.699321],"type":"Point"}
}