{
  "type": "Feature",
  "properties": {
    "iso:country":"US",
    "sg:address":"2775 N Angus St",
    "sg:city":"Fresno",
    "sg:classifiers":[
        {
            "category":"Wholesale",
            "subcategory":"Wine & Distilled Alcoholic Beverages",
            "type":"Manufacturing & Wholesale Goods"
        }
    ],
    "sg:phone":"+1 559 493 3400",
    "sg:postcode":"93703",
    "sg:province":"CA",
    "sg:tags":[
        "liquor"
    ],
    "sg:website":"www.southernwine.com",
    "wof:name":"Southern Wine & Spirits-N Ca",
    "wof:placetype":"venue"
},
  "geometry": {"coordinates":[-119.777105,36.775219],"type":"Point"}
}