{
  "type": "Feature",
  "properties": {
    "addr:full":"2775 N Angus St Fresno CA 93703",
    "addr:housenumber":"2775",
    "addr:postcode":"93703",
    "addr:street":"N Angus",
    "iso:country":"US",
    "sg:address":"2775 N Angus St",
    "sg:city":"Fresno",
    "sg:classifiers":[
        {
            "category":"Wholesale",
            "subcategory":"Wine & Distilled Alcoholic Beverages",
            "type":"Manufacturing & Wholesale Goods"
        }
    ],
    "sg:phone":"+1 559 493 3400",
    "sg:postcode":"93703",
    "sg:province":"CA",
    "sg:tags":[
        "liquor"
    ],
    "sg:website":"www.southernwine.com",
    "wof:name":"Southern Wine & Spirits-N Ca",
    "wof:placetype":"venue"
},
  "geometry": {"coordinates":[-119.77710500000001,36.775219],"type":"Point"}
}