{
  "type": "Feature",
  "properties": {
    "addr:full":"528 Capitola Ave Capitola CA 95010",
    "addr:housenumber":"528",
    "addr:postcode":"95010",
    "addr:street":"Capitola Ave",
    "iso:country":"US",
    "sg:address":"528 Capitola Ave",
    "sg:city":"Capitola",
    "sg:classifiers":[
        {
            "category":"Health Services",
            "subcategory":"Doctor",
            "type":"Services"
        }
    ],
    "sg:phone":"+1 831 475 1630",
    "sg:postcode":"95010",
    "sg:province":"CA",
    "sg:tags":[
        "medicine",
        "practice",
        "internal",
        "family"
    ],
    "wof:name":"Greenstreet Nancy MD",
    "wof:placetype":"venue"
},
  "geometry": {"coordinates":[-121.953003,36.976299],"type":"Point"}
}