{
  "type": "Feature",
  "properties": {
    "addr:full":"59 Burbank Ave San Mateo CA 94403",
    "addr:housenumber":"59",
    "addr:postcode":"94403",
    "addr:street":"Burbank Ave",
    "iso:country":"US",
    "sg:address":"59 Burbank Ave",
    "sg:city":"San Mateo",
    "sg:classifiers":[
        {
            "category":"Building & Trades",
            "subcategory":"Electrical",
            "type":"Services"
        }
    ],
    "sg:phone":"+1 650 574 8548",
    "sg:postcode":"94403",
    "sg:province":"CA",
    "sg:tags":[
        "electrician",
        "contractor"
    ],
    "wof:name":"Electrovation",
    "wof:placetype":"venue"
},
  "geometry": {"coordinates":[-122.29299899999999,37.530399],"type":"Point"}
}