{
  "type": "Feature",
  "properties": {
    "addr:full":"1807 Coronado St Needles CA 92363",
    "addr:housenumber":"1807",
    "addr:postcode":"92363",
    "addr:street":"Coronado St",
    "iso:country":"US",
    "sg:address":"1807 Coronado St",
    "sg:city":"Needles",
    "sg:classifiers":[
        {
            "category":"Freight",
            "type":"Transportation"
        }
    ],
    "sg:phone":"+1 760 326 1101",
    "sg:postcode":"92363",
    "sg:province":"CA",
    "sg:tags":[
        "storage",
        "general"
    ],
    "wof:name":"Ace Storage I",
    "wof:placetype":"venue"
},
  "geometry": {"coordinates":[-114.62247499999999,34.829496],"type":"Point"}
}