{
  "type": "Feature",
  "properties": {
    "addr:full":"5740 Main St Oakley CA 94561",
    "addr:housenumber":"5740",
    "addr:postcode":"94561",
    "addr:street":"Main St",
    "iso:country":"US",
    "sg:address":"5740 Main St",
    "sg:city":"Oakley",
    "sg:classifiers":[
        {
            "category":"Autos & Motor Vehicles",
            "subcategory":"Auto Supplies",
            "type":"Retail Goods"
        },
        {
            "category":"Wholesale",
            "subcategory":"Auto Parts",
            "type":"Manufacturing & Wholesale Goods"
        }
    ],
    "sg:phone":"+1 925 679 8998",
    "sg:postcode":"94561",
    "sg:province":"CA",
    "sg:tags":[
        "automobile",
        "used"
    ],
    "wof:name":"Tri County Auto Recyclers",
    "wof:placetype":"venue"
},
  "geometry": {"coordinates":[-121.69591800000001,37.972059],"type":"Point"}
}