{
  "type": "Feature",
  "properties": {
    "iso:country":"US",
    "sg:address":"1802 E Cedar St",
    "sg:city":"Ontario",
    "sg:classifiers":[
        {
            "category":"Home & Garden",
            "subcategory":"Building Materials",
            "type":"Retail Goods"
        }
    ],
    "sg:phone":"+1 909 484 3861",
    "sg:postcode":"91761",
    "sg:province":"CA",
    "sg:tags":[
        "windows",
        "door"
    ],
    "wof:name":"Cucamango Shutters & Doors",
    "wof:placetype":"venue"
},
  "geometry": {"coordinates":[-117.611047,34.037645],"type":"Point"}
}