{
  "type": "Feature",
  "properties": {
    "iso:country":"US",
    "sg:address":"6340 Genesee Ave",
    "sg:city":"San Diego",
    "sg:classifiers":[
        {
            "category":"Real Estate",
            "subcategory":"Real Estate Operator",
            "type":"Services"
        }
    ],
    "sg:phone":"+1 858 587 8789",
    "sg:postcode":"92122",
    "sg:province":"CA",
    "sg:tags":[
        "condominium"
    ],
    "wof:name":"Regency Villas HOA",
    "wof:placetype":"venue"
},
  "geometry": {"coordinates":[-117.204401,32.853639],"type":"Point"}
}