{
  "type": "Feature",
  "properties": {
    "iso:country":"US",
    "sg:address":"4301 Piedmont Ave",
    "sg:city":"Oakland",
    "sg:classifiers":[
        {
            "category":"Deli",
            "type":"Food & Drink"
        },
        {
            "category":"Food & Beverages",
            "subcategory":"Groceries & Convenience Stores",
            "type":"Retail Goods"
        }
    ],
    "sg:phone":"+1 510 595 3649",
    "sg:postcode":"94611",
    "sg:province":"CA",
    "sg:website":"www.euromixdeli.com",
    "wof:name":"Euromix Delicatessen",
    "wof:placetype":"venue"
},
  "geometry": {"coordinates":[-122.249066,37.828963],"type":"Point"}
}