{
  "type": "Feature",
  "properties": {
    "iso:country":"US",
    "sg:address":"1625 E Donovan Rd",
    "sg:city":"Santa Maria",
    "sg:classifiers":[
        {
            "category":"Home & Garden",
            "subcategory":"Building Materials",
            "type":"Retail Goods"
        }
    ],
    "sg:phone":"+1 805 922 3551",
    "sg:postcode":"93454",
    "sg:province":"CA",
    "sg:tags":[
        "mixed",
        "concrete"
    ],
    "sg:website":"www.unionasphalt.com",
    "wof:name":"Union Asphalt",
    "wof:placetype":"venue"
},
  "geometry": {"coordinates":[-120.410343,34.96756],"type":"Point"}
}