{
  "type": "Feature",
  "properties": {
    "addr:full":"2160 Leavenworth St San Francisco CA 94133",
    "addr:housenumber":"2160",
    "addr:postcode":"94133",
    "addr:street":"Leavenworth St",
    "iso:country":"US",
    "sg:address":"2160 Leavenworth St",
    "sg:city":"San Francisco",
    "sg:classifiers":[
        {
            "category":"Farming",
            "subcategory":"Vineyard",
            "type":"Manufacturing & Wholesale Goods"
        }
    ],
    "sg:phone":"+1 415 885 2072",
    "sg:postcode":"94133",
    "sg:province":"CA",
    "sg:tags":[
        "grape"
    ],
    "wof:name":"Piccetti Vineyards Partne",
    "wof:placetype":"venue"
},
  "geometry": {"coordinates":[-122.417601,37.800712],"type":"Point"}
}