{
  "type": "Feature",
  "properties": {
    "addr:full":"3074 W Temple Ave Pomona CA 91766",
    "addr:housenumber":"3074",
    "addr:postcode":"91766",
    "addr:street":"W Temple Ave",
    "iso:country":"US",
    "sg:address":"3074 W Temple Ave",
    "sg:city":"Pomona",
    "sg:classifiers":[
        {
            "category":"Real Estate",
            "subcategory":"Real Estate Agent",
            "type":"Services"
        }
    ],
    "sg:phone":"+1 909 524 4989",
    "sg:postcode":"91766",
    "sg:province":"CA",
    "sg:website":"www.newstarrealty.com",
    "wof:name":"Era New Star Realty",
    "wof:placetype":"venue"
},
  "geometry": {"coordinates":[-117.800991,34.043679],"type":"Point"}
}