{
  "type": "Feature",
  "properties": {
    "iso:country":"US",
    "sg:address":"801 W 9th St",
    "sg:city":"San Pedro",
    "sg:classifiers":[
        {
            "category":"Real Estate",
            "subcategory":"Real Estate Agent",
            "type":"Services"
        }
    ],
    "sg:phone":"+1 310 519 7733",
    "sg:postcode":"90731",
    "sg:province":"CA",
    "wof:name":"Henry Falkenstein & Assoc",
    "wof:placetype":"venue"
},
  "geometry": {"coordinates":[-118.296748,33.736066],"type":"Point"}
}