{
  "type": "Feature",
  "properties": {
    "addr:full":"506 N Gilbert St Fullerton CA 92833",
    "addr:housenumber":"506",
    "addr:postcode":"92833",
    "addr:street":"N Gilbert St",
    "iso:country":"US",
    "sg:address":"506 N Gilbert St",
    "sg:city":"Fullerton",
    "sg:classifiers":[
        {
            "category":"Retail",
            "subcategory":"Auto Repair",
            "type":"Services"
        }
    ],
    "sg:phone":"+1 714 870 4589",
    "sg:postcode":"92833",
    "sg:province":"CA",
    "wof:name":"Fullerton Hills Toyota-Lexus Specialist",
    "wof:placetype":"venue"
},
  "geometry": {"coordinates":[-117.968098,33.876244],"type":"Point"}
}