{
  "type": "Feature",
  "properties": {
    "addr:full":"231 W Main St El Cajon CA 92020",
    "addr:housenumber":"231",
    "addr:postcode":"92020",
    "addr:street":"W Main St",
    "iso:country":"US",
    "sg:address":"231 W Main St",
    "sg:city":"El Cajon",
    "sg:classifiers":[
        {
            "category":"Insurance",
            "subcategory":"Insurance Agent",
            "type":"Services"
        }
    ],
    "sg:phone":"+1 619 401 1800",
    "sg:postcode":"92020",
    "sg:province":"CA",
    "wof:name":"Norven Storrs Agency",
    "wof:placetype":"venue"
},
  "geometry": {"coordinates":[-116.964437,32.794854],"type":"Point"}
}