{
  "type": "Feature",
  "properties": {
    "addr:full":"10226 Lower Azusa Rd El Monte CA 91731",
    "addr:housenumber":"10226",
    "addr:postcode":"91731",
    "addr:street":"Lower Azusa Rd",
    "iso:country":"US",
    "sg:address":"10226 Lower Azusa Rd",
    "sg:city":"El Monte",
    "sg:classifiers":[
        {
            "category":"Education",
            "subcategory":"School",
            "type":"Public Place"
        }
    ],
    "sg:phone":"+1 626 575 2323",
    "sg:postcode":"91731",
    "sg:province":"CA",
    "sg:tags":[
        "high",
        "middle",
        "elementary"
    ],
    "wof:name":"El Monte City Elementary School District",
    "wof:placetype":"venue"
},
  "geometry": {"coordinates":[-118.42601000000001,34.124845],"type":"Point"}
}