{
  "type": "Feature",
  "properties": {
    "iso:country":"US",
    "sg:address":"16919 Cooper Rd",
    "sg:city":"Nevada City",
    "sg:classifiers":[
        {
            "category":"Manufacturing",
            "subcategory":"Toys & Sporting Goods",
            "type":"Manufacturing & Wholesale Goods"
        }
    ],
    "sg:phone":"+1 530 478 9773",
    "sg:postcode":"95959",
    "sg:province":"CA",
    "sg:tags":[
        "hardwood",
        "mi",
        "mfg"
    ],
    "wof:name":"Birds In Wood",
    "wof:placetype":"venue"
},
  "geometry": {"coordinates":[-120.97824900000001,39.296086],"type":"Point"}
}