{
  "type": "Feature",
  "properties": {
    "addr:full":"417 S Tamarind Ave Compton CA 90220",
    "addr:housenumber":"417",
    "addr:postcode":"90220",
    "addr:street":"S Tamarind Ave",
    "iso:country":"US",
    "sg:address":"417 S Tamarind Ave",
    "sg:city":"Compton",
    "sg:classifiers":[
        {
            "category":"Organizations",
            "subcategory":"Religious Organization",
            "type":"Services"
        }
    ],
    "sg:phone":"+1 310 639 2662",
    "sg:postcode":"90220",
    "sg:province":"CA",
    "sg:tags":[
        "church"
    ],
    "wof:name":"Tamarind Church",
    "wof:placetype":"venue"
},
  "geometry": {"coordinates":[-118.22199999999999,33.8927],"type":"Point"}
}