{
  "type": "Feature",
  "properties": {
    "iso:country":"US",
    "sg:address":"600 S Broadway",
    "sg:city":"Los Angeles",
    "sg:classifiers":[
        {
            "category":"Shopping",
            "subcategory":"Jewelry",
            "type":"Retail Goods"
        },
        {
            "category":"Wholesale",
            "subcategory":"Jewelry",
            "type":"Manufacturing & Wholesale Goods"
        }
    ],
    "sg:phone":"+1 213 624 0903",
    "sg:postcode":"90014",
    "sg:province":"CA",
    "sg:tags":[
        "jeweler"
    ],
    "wof:name":"Aquarius Jewelry",
    "wof:placetype":"venue"
},
  "geometry": {"coordinates":[-118.253367,34.045213],"type":"Point"}
}