{
  "type": "Feature",
  "properties": {
    "iso:country":"US",
    "sg:address":"3140 Thorntree Dr",
    "sg:city":"Chico",
    "sg:classifiers":[
        {
            "category":"Home & Garden",
            "subcategory":"Building Materials",
            "type":"Retail Goods"
        }
    ],
    "sg:phone":"+1 530 345 5266",
    "sg:postcode":"95973",
    "sg:province":"CA",
    "sg:tags":[
        "windows"
    ],
    "wof:name":"Hull's Nor Cal Windows",
    "wof:placetype":"venue"
},
  "geometry": {"coordinates":[-121.84002,39.783384],"type":"Point"}
}