{
  "type": "Feature",
  "properties": {
    "iso:country":"US",
    "sg:address":"2714 Griffith Park Boulevard",
    "sg:city":"Los Angeles",
    "sg:classifiers":[
        {
            "category":"Retail",
            "subcategory":"Laundry & Dry Cleaning",
            "type":"Services"
        }
    ],
    "sg:phone":"+1 323 660 0514",
    "sg:postcode":"90027",
    "sg:province":"CA",
    "wof:name":"Classic Cleaners",
    "wof:placetype":"venue"
},
  "geometry": {"coordinates":[-118.27228,34.106873],"type":"Point"}
}