{
  "type": "Feature",
  "properties": {
    "iso:country":"US",
    "sg:address":"7003 Pacific Blvd Ste A",
    "sg:city":"Huntington Park",
    "sg:classifiers":[
        {
            "category":"Organizations",
            "subcategory":"Religious Organization",
            "type":"Services"
        }
    ],
    "sg:phone":"+1 323 587 6397",
    "sg:postcode":"90255",
    "sg:province":"CA",
    "wof:name":"Pacific Wedding Chapel",
    "wof:placetype":"venue"
},
  "geometry": {"coordinates":[-118.225621,33.976133],"type":"Point"}
}