{
  "type": "Feature",
  "properties": {
    "addr:full":"1436 S Wooster St Los Angeles CA 90035",
    "addr:housenumber":"1436",
    "addr:postcode":"90035",
    "addr:street":"S Wooster St",
    "iso:country":"US",
    "sg:address":"1436 S Wooster St",
    "sg:city":"Los Angeles",
    "sg:classifiers":[
        {
            "category":"Professional",
            "subcategory":"Computer Services",
            "type":"Services"
        }
    ],
    "sg:phone":"+1 310 659 5945",
    "sg:postcode":"90035",
    "sg:province":"CA",
    "wof:name":"Sharon Computer Svc",
    "wof:placetype":"venue"
},
  "geometry": {"coordinates":[-118.382778,34.052929],"type":"Point"}
}