{
  "type": "Feature",
  "properties": {
    "addr:full":"749 N Ave 50 Los Angeles CA 90042",
    "addr:housenumber":"749;50",
    "addr:postcode":"90042",
    "addr:street":"N Ave",
    "iso:country":"US",
    "sg:address":"749 N Ave 50",
    "sg:city":"Los Angeles",
    "sg:classifiers":[
        {
            "category":"Food & Beverages",
            "subcategory":"Groceries & Convenience Stores",
            "type":"Retail Goods"
        }
    ],
    "sg:phone":"+1 323 258 2560",
    "sg:postcode":"90042",
    "sg:province":"CA",
    "sg:tags":[
        "grocer"
    ],
    "wof:name":"Avenue 50 Mini Mart",
    "wof:placetype":"venue"
},
  "geometry": {"coordinates":[-118.206677,34.111022],"type":"Point"}
}