{
  "type": "Feature",
  "properties": {
    "addr:full":"678 Toland St San Francisco CA 94124",
    "addr:housenumber":"678",
    "addr:postcode":"94124",
    "addr:street":"Toland St",
    "iso:country":"US",
    "sg:address":"678 Toland St",
    "sg:city":"San Francisco",
    "sg:classifiers":[
        {
            "category":"Manufacturing",
            "subcategory":"Wood Products",
            "type":"Manufacturing & Wholesale Goods"
        }
    ],
    "sg:phone":"+1 415 282 3551",
    "sg:postcode":"94124",
    "sg:province":"CA",
    "sg:tags":[
        "picture",
        "frame"
    ],
    "wof:name":"China Basin Designs",
    "wof:placetype":"venue"
},
  "geometry": {"coordinates":[-122.400327,37.742471],"type":"Point"}
}