{
  "type": "Feature",
  "properties": {
    "iso:country":"US",
    "sg:address":"340 Valley Dr",
    "sg:city":"Brisbane",
    "sg:classifiers":[
        {
            "category":"Wholesale",
            "subcategory":"Durable Goods & Equipment",
            "type":"Manufacturing & Wholesale Goods"
        }
    ],
    "sg:phone":"+1 415 657 4100",
    "sg:postcode":"94005",
    "sg:province":"CA",
    "sg:tags":[
        "importer"
    ],
    "wof:name":"Nishimoto Trading Co LTD",
    "wof:placetype":"venue"
},
  "geometry": {"coordinates":[-122.40958500000001,37.688285],"type":"Point"}
}