{
  "type": "Feature",
  "properties": {
    "addr:full":"160 W Santa Clara St San Jose CA 95113",
    "addr:housenumber":"160",
    "addr:postcode":"95113",
    "addr:street":"W Santa Clara St",
    "iso:country":"US",
    "sg:address":"160 W Santa Clara St",
    "sg:city":"San Jose",
    "sg:classifiers":[
        {
            "category":"Parking",
            "type":"Transportation"
        }
    ],
    "sg:phone":"+1 408 298 6630",
    "sg:postcode":"95113",
    "sg:province":"CA",
    "wof:name":"Century Parking",
    "wof:placetype":"venue"
},
  "geometry": {"coordinates":[-121.89299800000001,37.3349],"type":"Point"}
}