{
  "type": "Feature",
  "properties": {
    "iso:country":"US",
    "sg:address":"5605 Kanan Rd",
    "sg:city":"Agoura Hills",
    "sg:classifiers":[
        {
            "category":"Retail",
            "subcategory":"Veterinary Services",
            "type":"Services"
        }
    ],
    "sg:phone":"+1 818 991 2424",
    "sg:postcode":"91301",
    "sg:province":"CA",
    "sg:tags":[
        "veterinarian"
    ],
    "wof:name":"Agoura Hills Animal Hospital",
    "wof:placetype":"venue"
},
  "geometry": {"coordinates":[-118.758003,34.152802],"type":"Point"}
}