{
  "type": "Feature",
  "properties": {
    "addr:full":"848 W 1st St Chico CA 95928",
    "addr:housenumber":"848",
    "addr:postcode":"95928",
    "addr:street":"W 1St St",
    "iso:country":"US",
    "sg:address":"848 W 1st St",
    "sg:city":"Chico",
    "sg:classifiers":[
        {
            "category":"Professional",
            "type":"Services"
        }
    ],
    "sg:phone":"+1 831 429 5075",
    "sg:postcode":"95928",
    "sg:province":"CA",
    "wof:name":"Stile Designs",
    "wof:placetype":"venue"
},
  "geometry": {"coordinates":[-121.848056,39.726433],"type":"Point"}
}