{
  "type": "Feature",
  "properties": {
    "iso:country":"US",
    "sg:address":"16606 Ogram Ave",
    "sg:city":"Torrance",
    "sg:classifiers":[
        {
            "category":"Retail",
            "subcategory":"Repair Shop",
            "type":"Services"
        }
    ],
    "sg:phone":"+1 310 808 9448",
    "sg:postcode":"90504",
    "sg:province":"CA",
    "sg:tags":[
        "plumbing",
        "drain",
        "cleaning",
        "sewer"
    ],
    "wof:name":"Ausland Plumbing",
    "wof:placetype":"venue"
},
  "geometry": {"coordinates":[-118.32865099999999,33.878391],"type":"Point"}
}