{
  "type": "Feature",
  "properties": {
    "addr:full":"24911 Avenue Stanford Santa Clarita CA 91355",
    "addr:housenumber":"24911",
    "addr:postcode":"91355",
    "addr:street":"Avenue",
    "iso:country":"US",
    "sg:address":"24911 Avenue Stanford",
    "sg:city":"Santa Clarita",
    "sg:classifiers":[
        {
            "category":"Professional",
            "subcategory":"Lawyer & Legal Services",
            "type":"Services"
        }
    ],
    "sg:phone":"+1 661 253 0075",
    "sg:postcode":"91355",
    "sg:province":"CA",
    "wof:name":"Law Offices of Alan L Trock",
    "wof:placetype":"venue"
},
  "geometry": {"coordinates":[-118.57150900000001,34.440079],"type":"Point"}
}