{
  "type": "Feature",
  "properties": {
    "addr:full":"200 Kansas St San Francisco CA 94103",
    "addr:housenumber":"200",
    "addr:postcode":"94103",
    "addr:street":"Kansas St",
    "iso:country":"US",
    "sg:address":"200 Kansas St",
    "sg:city":"San Francisco",
    "sg:classifiers":[
        {
            "category":"Restaurant",
            "type":"Food & Drink"
        }
    ],
    "sg:phone":"+1 415 861 1152",
    "sg:postcode":"94103",
    "sg:province":"CA",
    "wof:name":"Cafe Veloce",
    "wof:placetype":"venue"
},
  "geometry": {"coordinates":[-122.403643,37.766017],"type":"Point"}
}