{
  "type": "Feature",
  "properties": {
    "addr:full":"2209 Laurel Ave Manhattan Beach CA 90266",
    "addr:housenumber":"2209",
    "addr:postcode":"90266",
    "addr:street":"Laurel Ave",
    "iso:country":"US",
    "sg:address":"2209 Laurel Ave",
    "sg:city":"Manhattan Beach",
    "sg:classifiers":[
        {
            "category":"Professional",
            "subcategory":"Art Services",
            "type":"Services"
        }
    ],
    "sg:phone":"+1 310 594 8074",
    "sg:postcode":"90266",
    "sg:province":"CA",
    "sg:tags":[
        "photographer"
    ],
    "sg:website":"www.grahamandgrahamphotography.com",
    "wof:name":"Graham & Graham Photography",
    "wof:placetype":"venue"
},
  "geometry": {"coordinates":[-118.404544,33.893312],"type":"Point"}
}