{
  "type": "Feature",
  "properties": {
    "iso:country":"US",
    "sg:address":"23011 Moulton Pkwy",
    "sg:city":"Laguna Hills",
    "sg:classifiers":[
        {
            "category":"Education",
            "subcategory":"Special Training",
            "type":"Public Place"
        }
    ],
    "sg:phone":"+1 949 422 4296",
    "sg:postcode":"92653",
    "sg:province":"CA",
    "sg:tags":[
        "instruction",
        "music"
    ],
    "sg:website":"www.keithfelch.com",
    "wof:name":"Accent Woodwind Instruction",
    "wof:placetype":"venue"
},
  "geometry": {"coordinates":[-117.730282,33.628236],"type":"Point"}
}