{
  "type": "Feature",
  "properties": {
    "addr:full":"10447 Mountair Ave Tujunga CA 91042",
    "addr:housenumber":"10447",
    "addr:postcode":"91042",
    "addr:street":"Mountair Ave",
    "iso:country":"US",
    "sg:address":"10447 Mountair Ave",
    "sg:city":"Tujunga",
    "sg:classifiers":[
        {
            "category":"Autos & Motor Vehicles",
            "subcategory":"Automobile Sales",
            "type":"Retail Goods"
        }
    ],
    "sg:phone":"+1 818 353 9522",
    "sg:postcode":"91042",
    "sg:province":"CA",
    "sg:tags":[
        "dealers-used",
        "used",
        "cars-wholesale",
        "car"
    ],
    "wof:name":"Donas Used & New Clothing",
    "wof:placetype":"venue"
},
  "geometry": {"coordinates":[-118.29320199999999,34.258603],"type":"Point"}
}