{
  "type": "Feature",
  "properties": {
    "addr:full":"2375 W Grant Line Rd Tracy CA 95377",
    "addr:housenumber":"2375",
    "addr:postcode":"95377",
    "addr:street":"W Grant Line Rd",
    "iso:country":"US",
    "sg:address":"2375 W Grant Line Rd",
    "sg:city":"Tracy",
    "sg:classifiers":[
        {
            "category":"Autos & Motor Vehicles",
            "subcategory":"Fuel & Gas Station",
            "type":"Retail Goods"
        }
    ],
    "sg:phone":"+1 209 836 8908",
    "sg:postcode":"95377",
    "sg:province":"CA",
    "sg:tags":[
        "oil"
    ],
    "wof:name":"Grant Line Shell",
    "wof:placetype":"venue"
},
  "geometry": {"coordinates":[-121.460955,37.75418],"type":"Point"}
}