{
  "type": "Feature",
  "properties": {
    "iso:country":"US",
    "sg:address":"1523 W Ave J",
    "sg:city":"Lancaster",
    "sg:classifiers":[
        {
            "category":"Health Services",
            "subcategory":"Doctor",
            "type":"Services"
        }
    ],
    "sg:phone":"+1 661 729 2662",
    "sg:postcode":"93534",
    "sg:province":"CA",
    "sg:tags":[
        "dentist"
    ],
    "wof:name":"Manuel De Leon DDS",
    "wof:placetype":"venue"
},
  "geometry": {"coordinates":[-118.157241,34.689433],"type":"Point"}
}