{
  "type": "Feature",
  "properties": {
    "addr:full":"1401 Avocado Ave Ste 802 Newport Beach CA 92660",
    "addr:housenumber":"1401",
    "addr:postcode":"92660",
    "addr:street":"Avocado Ave Ste 802",
    "iso:country":"US",
    "sg:address":"1401 Avocado Ave Ste 802",
    "sg:city":"Newport Beach",
    "sg:classifiers":[
        {
            "category":"Health Services",
            "subcategory":"Hospital",
            "type":"Services"
        }
    ],
    "sg:phone":"+1 714 488 6607",
    "sg:postcode":"92660",
    "sg:province":"CA",
    "sg:website":"www.newportchildren.com",
    "wof:name":"William Holm Md Faap",
    "wof:placetype":"venue"
},
  "geometry": {"coordinates":[-117.871066,33.611986],"type":"Point"}
}