{
  "type": "Feature",
  "properties": {
    "addr:full":"3166 Impala Dr San Jose CA 95117",
    "addr:housenumber":"3166",
    "addr:postcode":"95117",
    "addr:street":"Impala Dr",
    "iso:country":"US",
    "sg:address":"3166 Impala Dr",
    "sg:city":"San Jose",
    "sg:classifiers":[
        {
            "category":"Real Estate",
            "subcategory":"Real Estate Operator",
            "type":"Services"
        }
    ],
    "sg:phone":"+1 408 779 6576",
    "sg:postcode":"95117",
    "sg:province":"CA",
    "sg:tags":[
        "building",
        "apartment"
    ],
    "wof:name":"David Neunzig",
    "wof:placetype":"venue"
},
  "geometry": {"coordinates":[-121.95305399999999,37.295917],"type":"Point"}
}