{
  "type": "Feature",
  "properties": {
    "addr:full":"6100 Sunrise Blvd Citrus Heights CA 95610",
    "addr:housenumber":"6100",
    "addr:postcode":"95610",
    "addr:street":"Sunrise Blvd",
    "iso:country":"US",
    "sg:address":"6100 Sunrise Blvd",
    "sg:city":"Citrus Heights",
    "sg:classifiers":[
        {
            "category":"Shopping",
            "subcategory":"Baby Store",
            "type":"Retail Goods"
        },
        {
            "category":"Shopping",
            "subcategory":"Department Store",
            "type":"Retail Goods"
        },
        {
            "category":"Shopping",
            "subcategory":"Clothing, Apparel, & Fashions",
            "type":"Retail Goods"
        },
        {
            "category":"Personal",
            "subcategory":"Day Spa",
            "type":"Services"
        }
    ],
    "sg:phone":"+1 916 726 8811",
    "sg:postcode":"95610",
    "sg:province":"CA",
    "sg:tags":[
        "furniture",
        "clothing",
        "gear",
        "women's"
    ],
    "sg:website":"www.JCPenney.com",
    "wof:name":"JCPenney",
    "wof:placetype":"venue"
},
  "geometry": {"coordinates":[-121.26719799999999,38.67621],"type":"Point"}
}