{
  "type": "Feature",
  "properties": {
    "addr:full":"7377 Hollywood Blvd West Hollywood CA 90046",
    "addr:housenumber":"7377",
    "addr:postcode":"90046",
    "addr:street":"Hollywood Blvd",
    "iso:country":"US",
    "sg:address":"7377 Hollywood Blvd",
    "sg:city":"West Hollywood",
    "sg:classifiers":[
        {
            "category":"Recreation",
            "type":"Entertainment"
        }
    ],
    "sg:phone":"+1 818 523 8868",
    "sg:postcode":"90046",
    "sg:province":"CA",
    "sg:tags":[
        "karate",
        "judo",
        "instr"
    ],
    "wof:name":"Ju-Jitsu Academy Hand To Hand",
    "wof:placetype":"venue"
},
  "geometry": {"coordinates":[-118.351541,34.101712],"type":"Point"}
}