{
  "type": "Feature",
  "properties": {
    "addr:full":"8 Fallbrook Irvine CA 92604",
    "addr:housenumber":"8",
    "addr:postcode":"92604",
    "addr:street":"Fallbrook",
    "iso:country":"US",
    "sg:address":"8 Fallbrook",
    "sg:city":"Irvine",
    "sg:classifiers":[
        {
            "category":"Building & Trades",
            "subcategory":"Plumbing",
            "type":"Services"
        }
    ],
    "sg:phone":"+1 949 552 5612",
    "sg:postcode":"92604",
    "sg:province":"CA",
    "sg:tags":[
        "contractor"
    ],
    "wof:name":"West Coast Heating & Air",
    "wof:placetype":"venue"
},
  "geometry": {"coordinates":[-117.783734,33.680851],"type":"Point"}
}