{
  "type": "Feature",
  "properties": {
    "addr:full":"9713 Baseline Rd Rancho Cucamonga CA 91730",
    "addr:housenumber":"9713",
    "addr:postcode":"91730",
    "addr:street":"Baseline Rd",
    "iso:country":"US",
    "sg:address":"9713 Baseline Rd",
    "sg:city":"Rancho Cucamonga",
    "sg:classifiers":[
        {
            "category":"Shopping",
            "subcategory":"Pharmacy",
            "type":"Retail Goods"
        }
    ],
    "sg:phone":"+1 909 948 2701",
    "sg:postcode":"91730",
    "sg:province":"CA",
    "wof:name":"Econo Drugs",
    "wof:placetype":"venue"
},
  "geometry": {"coordinates":[-117.59111900000001,34.121458],"type":"Point"}
}