{
  "type": "Feature",
  "properties": {
    "iso:country":"US",
    "sg:address":"6351 Owensmouth Ave",
    "sg:city":"Woodland Hills",
    "sg:classifiers":[
        {
            "category":"Professional",
            "subcategory":"Lawyer & Legal Services",
            "type":"Services"
        }
    ],
    "sg:phone":"+1 818 884 0101",
    "sg:postcode":"91303",
    "sg:province":"CA",
    "sg:tags":[
        "attorney"
    ],
    "sg:website":"www.heislerbray.com",
    "wof:name":"Heisler & Bray",
    "wof:placetype":"venue"
},
  "geometry": {"coordinates":[-118.60159400000001,34.183077],"type":"Point"}
}