{
  "type": "Feature",
  "properties": {
    "addr:full":"31400 Lakeview Ave E Nuevo CA 92567",
    "addr:housenumber":"31400",
    "addr:postcode":"92567",
    "addr:street":"Lakeview Ave E Nuevo",
    "iso:country":"US",
    "sg:address":"31400 Lakeview Ave E",
    "sg:city":"Nuevo",
    "sg:classifiers":[
        {
            "category":"Professional",
            "subcategory":"Detective & Security Services",
            "type":"Services"
        }
    ],
    "sg:phone":"+1 951 928 3940",
    "sg:postcode":"92567",
    "sg:province":"CA",
    "sg:tags":[
        "information",
        "bureau"
    ],
    "wof:name":"Hope Caregiving Services",
    "wof:placetype":"venue"
},
  "geometry": {"coordinates":[-117.114288,33.835609],"type":"Point"}
}