{
  "type": "Feature",
  "properties": {
    "iso:country":"US",
    "sg:address":"12636 Pearblossom Hwy",
    "sg:city":"Pearblossom",
    "sg:classifiers":[
        {
            "category":"Real Estate",
            "subcategory":"Real Estate Agent",
            "type":"Services"
        }
    ],
    "sg:phone":"+1 661 944 4734",
    "sg:postcode":"93553",
    "sg:province":"CA",
    "wof:name":"Naffziger Real Estate & Apprsl",
    "wof:placetype":"venue"
},
  "geometry": {"coordinates":[-117.904978,34.506368],"type":"Point"}
}