{
  "type": "Feature",
  "properties": {
    "iso:country":"US",
    "sg:address":"368 Rose Ave",
    "sg:city":"Danville",
    "sg:classifiers":[
        {
            "category":"Personal",
            "subcategory":"Massage",
            "type":"Services"
        }
    ],
    "sg:phone":"+1 925 552 5896",
    "sg:postcode":"94526",
    "sg:province":"CA",
    "wof:name":"Michelle Kemmeter",
    "wof:placetype":"venue"
},
  "geometry": {"coordinates":[-122.00093099999999,37.823847],"type":"Point"}
}