{
  "type": "Feature",
  "properties": {
    "addr:full":"5530 Burgundy Ct Vallejo CA 94591",
    "addr:housenumber":"5530",
    "addr:postcode":"94591",
    "addr:street":"Burgundy Ct",
    "iso:country":"US",
    "sg:address":"5530 Burgundy Ct",
    "sg:city":"Vallejo",
    "sg:classifiers":[
        {
            "category":"Manufacturing",
            "subcategory":"Apparel",
            "type":"Manufacturing & Wholesale Goods"
        }
    ],
    "sg:phone":"+1 707 552 5567",
    "sg:postcode":"94591",
    "sg:province":"CA",
    "sg:tags":[
        "sewing",
        "contractor"
    ],
    "wof:name":"Oh Sew This Is Melinda's",
    "wof:placetype":"venue"
},
  "geometry": {"coordinates":[-122.197017,38.128989],"type":"Point"}
}