{
  "type": "Feature",
  "properties": {
    "addr:full":"4132 Grand View Blvd Los Angeles CA 90066",
    "addr:housenumber":"4132",
    "addr:postcode":"90066",
    "addr:street":"Grand View Blvd",
    "iso:country":"US",
    "sg:address":"4132 Grand View Blvd",
    "sg:city":"Los Angeles",
    "sg:classifiers":[
        {
            "category":"Real Estate",
            "subcategory":"Real Estate Operator",
            "type":"Services"
        }
    ],
    "sg:phone":"+1 310 391 9888",
    "sg:postcode":"90066",
    "sg:province":"CA",
    "sg:tags":[
        "apartment"
    ],
    "wof:name":"Marina East Apartments",
    "wof:placetype":"venue"
},
  "geometry": {"coordinates":[-118.42600299999999,33.998299],"type":"Point"}
}