{
  "type": "Feature",
  "properties": {
    "addr:full":"69 Columbia St Pasadena CA 91105",
    "addr:housenumber":"69",
    "addr:postcode":"91105",
    "addr:street":"Columbia St",
    "iso:country":"US",
    "sg:address":"69 Columbia St",
    "sg:city":"Pasadena",
    "sg:classifiers":[
        {
            "category":"Shopping",
            "subcategory":"Computers & Home Electronics",
            "type":"Retail Goods"
        }
    ],
    "sg:phone":"+1 626 799 7206",
    "sg:postcode":"91105",
    "sg:province":"CA",
    "sg:tags":[
        "music",
        "dvd's",
        "software"
    ],
    "sg:website":"www.imageunlimited.com",
    "wof:name":"Image Unlimited",
    "wof:placetype":"venue"
},
  "geometry": {"coordinates":[-118.151815,34.124177],"type":"Point"}
}