{
  "type": "Feature",
  "properties": {
    "iso:country":"US",
    "sg:address":"10356 Truckee Airport Rd",
    "sg:city":"Truckee",
    "sg:classifiers":[
        {
            "category":"Professional",
            "type":"Services"
        },
        {
            "category":"Deli",
            "type":"Food & Drink"
        },
        {
            "category":"Restaurant",
            "type":"Food & Drink"
        },
        {
            "category":"Coffee & Tea",
            "type":"Food & Drink"
        }
    ],
    "sg:phone":"+1 530 582 9351",
    "sg:postcode":"96161",
    "sg:province":"CA",
    "sg:tags":[
        "delicatessen",
        "cafeteria",
        "espresso",
        "caterer"
    ],
    "wof:name":"Runway Cafe & Catering",
    "wof:placetype":"venue"
},
  "geometry": {"coordinates":[-120.14517499999999,39.319069],"type":"Point"}
}