{
  "type": "Feature",
  "properties": {
    "iso:country":"US",
    "sg:address":"1235 W Ave I",
    "sg:city":"Lancaster",
    "sg:classifiers":[
        {
            "category":"Shopping",
            "subcategory":"Used Merchandise",
            "type":"Retail Goods"
        },
        {
            "category":"Professional",
            "subcategory":"Business Services",
            "type":"Services"
        }
    ],
    "sg:phone":"+1 661 723 9544",
    "sg:postcode":"93534",
    "sg:province":"CA",
    "sg:tags":[
        "shop",
        "meet",
        "swap"
    ],
    "wof:name":"Linda S Mini Mall",
    "wof:placetype":"venue"
},
  "geometry": {"coordinates":[-118.151848,34.704054],"type":"Point"}
}