{
  "type": "Feature",
  "properties": {
    "addr:full":"4320 Earnscliff Ave Fair Oaks CA 95628",
    "addr:housenumber":"4320",
    "addr:postcode":"95628",
    "addr:street":"Earnscliff Ave",
    "iso:country":"US",
    "sg:address":"4320 Earnscliff Ave",
    "sg:city":"Fair Oaks",
    "sg:classifiers":[
        {
            "category":"Real Estate",
            "subcategory":"Real Estate Agent",
            "type":"Services"
        }
    ],
    "sg:phone":"+1 916 962 0828",
    "sg:postcode":"95628",
    "sg:province":"CA",
    "wof:name":"AAA Real Estate Management",
    "wof:placetype":"venue"
},
  "geometry": {"coordinates":[-121.262258,38.643943],"type":"Point"}
}