{
  "type": "Feature",
  "properties": {
    "addr:full":"701 S Abel St Milpitas CA 95035",
    "addr:housenumber":"701",
    "addr:postcode":"95035",
    "addr:street":"S Abel St",
    "iso:country":"US",
    "sg:address":"701 S Abel St",
    "sg:city":"Milpitas",
    "sg:classifiers":[
        {
            "category":"Government",
            "subcategory":"Office",
            "type":"Public Place"
        }
    ],
    "sg:phone":"+1 408 957 5414",
    "sg:postcode":"95035",
    "sg:province":"CA",
    "wof:name":"Santa Clara County",
    "wof:placetype":"venue"
},
  "geometry": {"coordinates":[-121.904836,37.415535],"type":"Point"}
}