{
  "type": "Feature",
  "properties": {
    "addr:full":"1025 MacDonald Ave Richmond CA 94801",
    "addr:housenumber":"1025",
    "addr:postcode":"94801",
    "addr:street":"Macdonald Ave",
    "iso:country":"US",
    "sg:address":"1025 MacDonald Ave",
    "sg:city":"Richmond",
    "sg:classifiers":[
        {
            "category":"Professional",
            "subcategory":"Lawyer & Legal Services",
            "type":"Services"
        }
    ],
    "sg:phone":"+1 510 233 9954",
    "sg:postcode":"94801",
    "sg:province":"CA",
    "wof:name":"Contra Costa Legal Service Foundation",
    "wof:placetype":"venue"
},
  "geometry": {"coordinates":[-122.359318,37.935964],"type":"Point"}
}