{
  "type": "Feature",
  "properties": {
    "iso:country":"US",
    "sg:address":"2245 Montgomery Dr",
    "sg:city":"Santa Rosa",
    "sg:classifiers":[
        {
            "category":"Professional",
            "subcategory":"Lawyer & Legal Services",
            "type":"Services"
        }
    ],
    "sg:phone":"+1 707 579 3567",
    "sg:postcode":"95405",
    "sg:province":"CA",
    "sg:tags":[
        "attorney"
    ],
    "wof:name":"Schrag Michael Schrag & Baum",
    "wof:placetype":"venue"
},
  "geometry": {"coordinates":[-122.68837600000001,38.446509],"type":"Point"}
}