{
  "type": "Feature",
  "properties": {
    "addr:full":"28708 Roadside Dr. Agoura Hills CA 91301",
    "addr:postcode":"28708;91301",
    "addr:street":"Roadside Dr.",
    "iso:country":"US",
    "sg:address":"28708 Roadside Dr.",
    "sg:city":"Agoura Hills",
    "sg:classifiers":[
        {
            "category":"Restaurant",
            "type":"Food & Drink"
        }
    ],
    "sg:phone":"+1 818 889 1168",
    "sg:postcode":"91301",
    "sg:province":"CA",
    "sg:tags":[
        "chinese"
    ],
    "wof:name":"Hot Wok",
    "wof:placetype":"venue"
},
  "geometry": {"coordinates":[-118.752335,34.144314],"type":"Point"}
}