{
  "type": "Feature",
  "properties": {
    "iso:country":"US",
    "sg:address":"13371 Wilson St",
    "sg:city":"Garden Grove",
    "sg:classifiers":[
        {
            "category":"Manufacturing",
            "subcategory":"Food",
            "type":"Manufacturing & Wholesale Goods"
        }
    ],
    "sg:phone":"+1 714 636 2438",
    "sg:postcode":"92844",
    "sg:province":"CA",
    "sg:tags":[
        "preparation"
    ],
    "sg:website":"www.delsalsa.com",
    "wof:name":"De Salsa Co",
    "wof:placetype":"venue"
},
  "geometry": {"coordinates":[-117.98393299999999,33.768687],"type":"Point"}
}