{
  "type": "Feature",
  "properties": {
    "addr:full":"6051 White Ln Bakersfield CA 93309",
    "addr:housenumber":"6051",
    "addr:postcode":"93309",
    "addr:street":"White Ln",
    "iso:country":"US",
    "sg:address":"6051 White Ln",
    "sg:city":"Bakersfield",
    "sg:classifiers":[
        {
            "category":"Shopping",
            "subcategory":"Used Merchandise",
            "type":"Retail Goods"
        }
    ],
    "sg:phone":"+1 661 834 9355",
    "sg:postcode":"93309",
    "sg:province":"CA",
    "sg:tags":[
        "shop",
        "thrift"
    ],
    "wof:name":"Goodwill Industries",
    "wof:placetype":"venue"
},
  "geometry": {"coordinates":[-119.069924,35.318096],"type":"Point"}
}