{
  "type": "Feature",
  "properties": {
    "addr:full":"9544 Enos Ln Bakersfield CA 93314",
    "addr:housenumber":"9544",
    "addr:postcode":"93314",
    "addr:street":"Enos Ln",
    "iso:country":"US",
    "sg:address":"9544 Enos Ln",
    "sg:city":"Bakersfield",
    "sg:classifiers":[
        {
            "category":"Building & Trades",
            "subcategory":"Construction",
            "type":"Services"
        }
    ],
    "sg:phone":"+1 661 835 0708",
    "sg:postcode":"93314",
    "sg:province":"CA",
    "sg:tags":[
        "sandblasting"
    ],
    "sg:website":"www.eaglesandblastingandpainting.com",
    "wof:name":"Eagle Sandblasting & Painting",
    "wof:placetype":"venue"
},
  "geometry": {"coordinates":[-119.256941,35.451771],"type":"Point"}
}