{
  "type": "Feature",
  "properties": {
    "addr:full":"2580 Lake Tahoe Blvd South Lake Tahoe CA 96150",
    "addr:housenumber":"2580",
    "addr:postcode":"96150",
    "addr:street":"Lake Tahoe Blvd",
    "iso:country":"US",
    "sg:address":"2580 Lake Tahoe Blvd",
    "sg:city":"South Lake Tahoe",
    "sg:classifiers":[
        {
            "category":"Manufacturing",
            "subcategory":"Lumber",
            "type":"Manufacturing & Wholesale Goods"
        }
    ],
    "sg:phone":"+1 530 541 6564",
    "sg:postcode":"96150",
    "sg:province":"CA",
    "sg:tags":[
        "government"
    ],
    "wof:name":"Forestry & Fire Protection",
    "wof:placetype":"venue"
},
  "geometry": {"coordinates":[-119.985843,38.925482],"type":"Point"}
}