{
  "type": "Feature",
  "properties": {
    "iso:country":"US",
    "sg:address":"786 Ulloa St",
    "sg:city":"San Francisco",
    "sg:classifiers":[
        {
            "category":"Banks & Credit Unions",
            "subcategory":"Investment Brokerage",
            "type":"Services"
        }
    ],
    "sg:phone":"+1 415 564 8894",
    "sg:postcode":"94127",
    "sg:province":"CA",
    "wof:name":"PAC Investments",
    "wof:placetype":"venue"
},
  "geometry": {"coordinates":[-122.463461,37.740835],"type":"Point"}
}