{
  "type": "Feature",
  "properties": {
    "iso:country":"US",
    "sg:address":"11766 Wilshire Blvd",
    "sg:city":"Los Angeles",
    "sg:classifiers":[
        {
            "category":"Government",
            "subcategory":"Office",
            "type":"Public Place"
        }
    ],
    "sg:phone":"+1 310 473 9344",
    "sg:postcode":"90025",
    "sg:province":"CA",
    "sg:tags":[
        "international",
        "affairs"
    ],
    "wof:name":"Republic of Hungary",
    "wof:placetype":"venue"
},
  "geometry": {"coordinates":[-118.462619,34.048033],"type":"Point"}
}