{
  "type": "Feature",
  "properties": {
    "addr:full":"2150 W Washington Street San Diego CA 92110",
    "addr:housenumber":"2150",
    "addr:postcode":"92110",
    "addr:street":"W Washington Street",
    "iso:country":"US",
    "sg:address":"2150 W Washington Street",
    "sg:city":"San Diego",
    "sg:classifiers":[
        {
            "category":"Real Estate",
            "subcategory":"Architect",
            "type":"Services"
        }
    ],
    "sg:phone":"+1 619 692 9393",
    "sg:postcode":"92110",
    "sg:province":"CA",
    "wof:name":"Dominy & Associates Architects",
    "wof:placetype":"venue"
},
  "geometry": {"coordinates":[-117.183499,32.741779],"type":"Point"}
}