{
  "type": "Feature",
  "properties": {
    "addr:full":"5140 Fredericksburg Way Sacramento CA 95835",
    "addr:housenumber":"5140",
    "addr:postcode":"95835",
    "addr:street":"Fredericksburg Way",
    "iso:country":"US",
    "sg:address":"5140 Fredericksburg Way",
    "sg:city":"Sacramento",
    "sg:classifiers":[
        {
            "category":"Professional",
            "type":"Services"
        }
    ],
    "sg:phone":"+1 916 928 9551",
    "sg:postcode":"95835",
    "sg:province":"CA",
    "wof:name":"Joel M Korotkin A Prof Corp",
    "wof:placetype":"venue"
},
  "geometry": {"coordinates":[-121.51369099999999,38.66864],"type":"Point"}
}