{
  "type": "Feature",
  "properties": {
    "iso:country":"US",
    "sg:address":"6922 Churn Creek Rd",
    "sg:city":"Redding",
    "sg:classifiers":[
        {
            "category":"Professional",
            "type":"Services"
        }
    ],
    "sg:phone":"+1 530 378 1727",
    "sg:postcode":"96002",
    "sg:province":"CA",
    "wof:name":"Wizard Of Spas",
    "wof:placetype":"venue"
},
  "geometry": {"coordinates":[-122.333739,40.521005],"type":"Point"}
}