{
  "type": "Feature",
  "properties": {
    "addr:full":"4813 Enterprise Way Modesto CA 95356",
    "addr:housenumber":"4813",
    "addr:postcode":"ca 95356",
    "addr:street":"Enterprise Way",
    "iso:country":"US",
    "sg:address":"4813 Enterprise Way",
    "sg:city":"Modesto",
    "sg:classifiers":[
        {
            "category":"Wholesale",
            "subcategory":"Toys & Hobbies",
            "type":"Manufacturing & Wholesale Goods"
        }
    ],
    "sg:phone":"+1 209 251 9855",
    "sg:postcode":"95356",
    "sg:province":"CA",
    "sg:tags":[
        "wholesaler"
    ],
    "wof:name":"P & R Wholesale",
    "wof:placetype":"venue"
},
  "geometry": {"coordinates":[-121.072131,37.707793],"type":"Point"}
}