{
  "type": "Feature",
  "properties": {
    "addr:full":"1143 N Pacific Ave Glendale CA 91202",
    "addr:housenumber":"1143",
    "addr:postcode":"91202",
    "addr:street":"N Pacific Ave",
    "iso:country":"US",
    "sg:address":"1143 N Pacific Ave",
    "sg:city":"Glendale",
    "sg:classifiers":[
        {
            "category":"Shopping",
            "subcategory":"Gifts & Souvenirs",
            "type":"Retail Goods"
        }
    ],
    "sg:phone":"+1 818 547 5769",
    "sg:postcode":"91202",
    "sg:province":"CA",
    "wof:name":"Gifts Baccara",
    "wof:placetype":"venue"
},
  "geometry": {"coordinates":[-118.264909,34.163072],"type":"Point"}
}