{
  "type": "Feature",
  "properties": {
    "iso:country":"US",
    "sg:address":"1202 W Edinger Ave",
    "sg:city":"Santa Ana",
    "sg:classifiers":[
        {
            "category":"Education",
            "subcategory":"School",
            "type":"Public Place"
        }
    ],
    "sg:phone":"+1 714 754 7711",
    "sg:postcode":"92707",
    "sg:province":"CA",
    "sg:tags":[
        "high",
        "middle"
    ],
    "sg:website":"www.materdei.org",
    "wof:name":"Mater Dei High School",
    "wof:placetype":"venue"
},
  "geometry": {"coordinates":[-117.88400300000001,33.727299],"type":"Point"}
}