{
  "type": "Feature",
  "properties": {
    "addr:full":"7505 W Linne Rd Tracy CA 95304",
    "addr:housenumber":"7505",
    "addr:postcode":"95304",
    "addr:street":"W Linne Rd",
    "iso:country":"US",
    "sg:address":"7505 W Linne Rd",
    "sg:city":"Tracy",
    "sg:classifiers":[
        {
            "category":"Bars & Pubs",
            "type":"Food & Drink"
        },
        {
            "category":"Restaurant",
            "type":"Food & Drink"
        }
    ],
    "sg:phone":"+1 209 836 4035",
    "sg:postcode":"95304",
    "sg:province":"CA",
    "sg:tags":[
        "brew",
        "style",
        "family"
    ],
    "wof:name":"Four Corners Restaurant",
    "wof:placetype":"venue"
},
  "geometry": {"coordinates":[-121.398124,37.696152],"type":"Point"}
}