{
  "type": "Feature",
  "properties": {
    "addr:full":"4858 San Juan Avenue Fair Oaks CA 95628",
    "addr:housenumber":"4858",
    "addr:postcode":"95628",
    "addr:street":"San Juan Avenue",
    "iso:country":"US",
    "sg:address":"4858 San Juan Avenue",
    "sg:city":"Fair Oaks",
    "sg:classifiers":[
        {
            "category":"Social Services",
            "subcategory":"Child Care",
            "type":"Services"
        },
        {
            "category":"Education",
            "subcategory":"Preschool",
            "type":"Public Place"
        },
        {
            "category":"Education",
            "subcategory":"School",
            "type":"Public Place"
        }
    ],
    "sg:phone":"+1 916 965 3190",
    "sg:postcode":"95628",
    "sg:province":"CA",
    "sg:tags":[
        "elementary",
        "day"
    ],
    "wof:name":"Tutor Time Child Care Learning Centers",
    "wof:placetype":"venue"
},
  "geometry": {"coordinates":[-121.291943,38.654302],"type":"Point"}
}