{
  "type": "Feature",
  "properties": {
    "iso:country":"US",
    "sg:address":"13053 Benton St",
    "sg:city":"Garden Grove",
    "sg:classifiers":[
        {
            "category":"Restaurant",
            "type":"Food & Drink"
        }
    ],
    "sg:phone":"+1 714 534 3407",
    "sg:postcode":"92843",
    "sg:province":"CA",
    "sg:tags":[
        "eating"
    ],
    "wof:name":"Manchite Ice Cream & Food",
    "wof:placetype":"venue"
},
  "geometry": {"coordinates":[-117.94643000000001,33.773675],"type":"Point"}
}