{
  "type": "Feature",
  "properties": {
    "addr:full":"1806 W Ashlan Ave Fresno CA 93705",
    "addr:housenumber":"1806",
    "addr:postcode":"93705",
    "addr:street":"W Ashlan Ave",
    "iso:country":"US",
    "sg:address":"1806 W Ashlan Ave",
    "sg:city":"Fresno",
    "sg:classifiers":[
        {
            "category":"Social Services",
            "subcategory":"Child Care",
            "type":"Services"
        }
    ],
    "sg:phone":"+1 559 222 9401",
    "sg:postcode":"93705",
    "sg:province":"CA",
    "wof:name":"YMCA Of The East Bay",
    "wof:placetype":"venue"
},
  "geometry": {"coordinates":[-119.83176,36.793886],"type":"Point"}
}