{
  "type": "Feature",
  "properties": {
    "addr:full":"4535 Garfield Ave Carmichael CA 95608",
    "addr:housenumber":"4535",
    "addr:postcode":"95608",
    "addr:street":"Garfield Ave",
    "iso:country":"US",
    "sg:address":"4535 Garfield Ave",
    "sg:city":"Carmichael",
    "sg:classifiers":[
        {
            "category":"Professional",
            "subcategory":"Computer Services",
            "type":"Services"
        }
    ],
    "sg:phone":"+1 916 214 9290",
    "sg:postcode":"95608",
    "sg:province":"CA",
    "wof:name":"PC Therapist",
    "wof:placetype":"venue"
},
  "geometry": {"coordinates":[-121.336782,38.647787],"type":"Point"}
}