{
  "type": "Feature",
  "properties": {
    "iso:country":"US",
    "sg:address":"98 Banks St",
    "sg:city":"San Francisco",
    "sg:classifiers":[
        {
            "category":"Manufacturing",
            "subcategory":"Signs",
            "type":"Manufacturing & Wholesale Goods"
        }
    ],
    "sg:phone":"+1 415 860 2001",
    "sg:postcode":"94110",
    "sg:province":"CA",
    "wof:name":"Art Central",
    "wof:placetype":"venue"
},
  "geometry": {"coordinates":[-122.412562,37.741774],"type":"Point"}
}