{
  "type": "Feature",
  "properties": {
    "iso:country":"US",
    "sg:address":"307 Parker St",
    "sg:city":"Vacaville",
    "sg:classifiers":[
        {
            "category":"Health Services",
            "subcategory":"Doctor",
            "type":"Services"
        }
    ],
    "sg:phone":"+1 707 448 2134",
    "sg:postcode":"95688",
    "sg:province":"CA",
    "sg:tags":[
        "dentist"
    ],
    "wof:name":"Garcelon Dental",
    "wof:placetype":"venue"
},
  "geometry": {"coordinates":[-121.989863,38.35511],"type":"Point"}
}