{
  "type": "Feature",
  "properties": {
    "addr:full":"10 High Eagle Rd Alamo CA 94507",
    "addr:housenumber":"10",
    "addr:postcode":"94507",
    "addr:street":"High Eagle Rd",
    "iso:country":"US",
    "sg:address":"10 High Eagle Rd",
    "sg:city":"Alamo",
    "sg:classifiers":[
        {
            "category":"Building & Trades",
            "subcategory":"Construction",
            "type":"Services"
        }
    ],
    "sg:phone":"+1 925 831 0851",
    "sg:postcode":"94507",
    "sg:province":"CA",
    "sg:tags":[
        "contractor",
        "grading"
    ],
    "wof:name":"E & Lc Co Inc",
    "wof:placetype":"venue"
},
  "geometry": {"coordinates":[-122.01446300000001,37.852225],"type":"Point"}
}