{
  "type": "Feature",
  "properties": {
    "addr:full":"7400 Florence Avenue Downey CA 90240",
    "addr:housenumber":"7400",
    "addr:postcode":"90240",
    "addr:street":"Florence Avenue",
    "iso:country":"US",
    "sg:address":"7400 Florence Avenue",
    "sg:city":"Downey",
    "sg:classifiers":[
        {
            "category":"Restaurant",
            "type":"Food & Drink"
        }
    ],
    "sg:phone":"+1 562 927 0114",
    "sg:postcode":"90240",
    "sg:province":"CA",
    "wof:name":"Uncle Henry's Deli & Meat Specialties",
    "wof:placetype":"venue"
},
  "geometry": {"coordinates":[-118.14108299999999,33.959859],"type":"Point"}
}