{
  "type": "Feature",
  "properties": {
    "addr:full":"3030 W Warner Ave Santa Ana CA 92704",
    "addr:housenumber":"3030",
    "addr:postcode":"92704",
    "addr:street":"W Warner Ave",
    "iso:country":"US",
    "sg:address":"3030 W Warner Ave",
    "sg:city":"Santa Ana",
    "sg:classifiers":[
        {
            "category":"Food & Beverages",
            "subcategory":"Groceries & Convenience Stores",
            "type":"Retail Goods"
        }
    ],
    "sg:phone":"+1 714 641 1778",
    "sg:postcode":"92704",
    "sg:province":"CA",
    "wof:name":"Bonert's Slice Of Pie",
    "wof:placetype":"venue"
},
  "geometry": {"coordinates":[-117.909665,33.715282],"type":"Point"}
}