{
  "type": "Feature",
  "properties": {
    "addr:full":"750 Yale St Los Angeles CA 90012",
    "addr:housenumber":"750",
    "addr:postcode":"90012",
    "addr:street":"Yale St",
    "iso:country":"US",
    "sg:address":"750 Yale St",
    "sg:city":"Los Angeles",
    "sg:classifiers":[
        {
            "category":"Organizations",
            "subcategory":"Professional Association",
            "type":"Services"
        }
    ],
    "sg:phone":"+1 213 680 1860",
    "sg:postcode":"90012",
    "sg:province":"CA",
    "wof:name":"Southern California Camau Assn",
    "wof:placetype":"venue"
},
  "geometry": {"coordinates":[-118.24115500000001,34.062151],"type":"Point"}
}