{
  "type": "Feature",
  "properties": {
    "iso:country":"US",
    "sg:address":"2709 E Slauson Ave",
    "sg:city":"Huntington Park",
    "sg:classifiers":[
        {
            "category":"Personal",
            "subcategory":"Beauty Salon",
            "type":"Services"
        }
    ],
    "sg:phone":"+1 323 581 2279",
    "sg:postcode":"90255",
    "sg:province":"CA",
    "sg:tags":[
        "manicuring"
    ],
    "wof:name":"Pretty Nails",
    "wof:placetype":"venue"
},
  "geometry": {"coordinates":[-118.222196,33.989284],"type":"Point"}
}