{
  "type": "Feature",
  "properties": {
    "iso:country":"US",
    "sg:address":"770 N Sepulveda Blvd",
    "sg:city":"El Segundo",
    "sg:classifiers":[
        {
            "category":"Retail",
            "subcategory":"Auto Repair",
            "type":"Services"
        }
    ],
    "sg:phone":"+1 310 640 0970",
    "sg:postcode":"90245",
    "sg:province":"CA",
    "sg:tags":[
        "repairing",
        "automobile"
    ],
    "wof:name":"Bob's Union 76 Svc",
    "wof:placetype":"venue"
},
  "geometry": {"coordinates":[-118.396196,33.925642],"type":"Point"}
}