{
  "type": "Feature",
  "properties": {
    "addr:full":"22644 Sylvan St Woodland Hills CA 91367",
    "addr:housenumber":"22644",
    "addr:postcode":"91367",
    "addr:street":"Sylvan St",
    "iso:country":"US",
    "sg:address":"22644 Sylvan St",
    "sg:city":"Woodland Hills",
    "sg:classifiers":[
        {
            "category":"Shopping",
            "subcategory":"Party Supplies",
            "type":"Retail Goods"
        },
        {
            "category":"Personal",
            "type":"Services"
        }
    ],
    "sg:phone":"+1 818 883 3311",
    "sg:postcode":"91367",
    "sg:province":"CA",
    "sg:tags":[
        "planning",
        "event"
    ],
    "sg:website":"www.absolutelyeverythingentertai...",
    "wof:name":"Absolutely Everything Entertainment Service",
    "wof:placetype":"venue"
},
  "geometry": {"coordinates":[-118.619953,34.184498],"type":"Point"}
}