{
  "type": "Feature",
  "properties": {
    "addr:full":"482 Reynolds Cir San Jose CA 95112",
    "addr:housenumber":"482",
    "addr:postcode":"95112",
    "addr:street":"Reynolds Cir",
    "iso:country":"US",
    "sg:address":"482 Reynolds Cir",
    "sg:city":"San Jose",
    "sg:classifiers":[
        {
            "category":"Manufacturing",
            "subcategory":"Glass & Minerals",
            "type":"Manufacturing & Wholesale Goods"
        }
    ],
    "sg:phone":"+1 408 437 1069",
    "sg:postcode":"95112",
    "sg:province":"CA",
    "sg:tags":[
        "cut",
        "mfg"
    ],
    "wof:name":"Cortez Machine Saw",
    "wof:placetype":"venue"
},
  "geometry": {"coordinates":[-121.909221,37.370409],"type":"Point"}
}