{
  "type": "Feature",
  "properties": {
    "addr:full":"10850 Jamacha Blvd Spring Valley CA 91978",
    "addr:housenumber":"10850",
    "addr:postcode":"91978",
    "addr:street":"Jamacha Blvd",
    "iso:country":"US",
    "sg:address":"10850 Jamacha Blvd",
    "sg:city":"Spring Valley",
    "sg:classifiers":[
        {
            "category":"Real Estate",
            "subcategory":"Real Estate Operator",
            "type":"Services"
        }
    ],
    "sg:phone":"+1 619 670 1858",
    "sg:postcode":"91978",
    "sg:province":"CA",
    "sg:tags":[
        "apartment"
    ],
    "sg:website":"www.calavowoods.com",
    "wof:name":"Calavo Woods",
    "wof:placetype":"venue"
},
  "geometry": {"coordinates":[-116.959999,32.731201],"type":"Point"}
}