{
  "type": "Feature",
  "properties": {
    "addr:full":"12650 Westminster Ave Santa Ana CA 92706",
    "addr:housenumber":"12650",
    "addr:postcode":"92706",
    "addr:street":"Westminster Ave",
    "iso:country":"US",
    "sg:address":"12650 Westminster Ave",
    "sg:city":"Santa Ana",
    "sg:classifiers":[
        {
            "category":"Real Estate",
            "subcategory":"Architect",
            "type":"Services"
        }
    ],
    "sg:phone":"+1 714 554 0106",
    "sg:postcode":"92706",
    "sg:province":"CA",
    "wof:name":"Giano Architectural Design",
    "wof:placetype":"venue"
},
  "geometry": {"coordinates":[-117.90925,33.759642],"type":"Point"}
}