{
  "type": "Feature",
  "properties": {
    "addr:full":"2270 Sunrise Blvd Rancho Cordova CA 95670",
    "addr:housenumber":"2270",
    "addr:postcode":"95670",
    "addr:street":"Sunrise Blvd",
    "iso:country":"US",
    "sg:address":"2270 Sunrise Blvd",
    "sg:city":"Rancho Cordova",
    "sg:classifiers":[
        {
            "category":"Personal",
            "subcategory":"Tanning Parlor",
            "type":"Services"
        }
    ],
    "sg:phone":"+1 916 631 4100",
    "sg:postcode":"95670",
    "sg:province":"CA",
    "sg:website":"www.amazingtans.com",
    "wof:name":"Amazing Tans",
    "wof:placetype":"venue"
},
  "geometry": {"coordinates":[-121.267732,38.620006],"type":"Point"}
}