{
  "type": "Feature",
  "properties": {
    "iso:country":"US",
    "sg:address":"13567 Ventura Blvd",
    "sg:city":"Sherman Oaks",
    "sg:classifiers":[
        {
            "category":"Food & Beverages",
            "subcategory":"Specialty",
            "type":"Retail Goods"
        }
    ],
    "sg:phone":"+1 818 905 9719",
    "sg:postcode":"91423",
    "sg:province":"CA",
    "sg:tags":[
        "tea",
        "coffee",
        "mfg",
        "grocery",
        "roasted"
    ],
    "sg:website":"www.thecoffeeroaster.net",
    "wof:name":"The Coffee Roaster",
    "wof:placetype":"venue"
},
  "geometry": {"coordinates":[-118.429243,34.147712],"type":"Point"}
}