{
  "type": "Feature",
  "properties": {
    "iso:country":"US",
    "sg:address":"4320 Van Nuys Blvd",
    "sg:city":"Sherman Oaks",
    "sg:classifiers":[
        {
            "category":"Manufacturing",
            "subcategory":"Apparel",
            "type":"Manufacturing & Wholesale Goods"
        }
    ],
    "sg:phone":"+1 818 501 7003",
    "sg:postcode":"91403",
    "sg:province":"CA",
    "sg:tags":[
        "mfg"
    ],
    "wof:name":"Kitty Hats",
    "wof:placetype":"venue"
},
  "geometry": {"coordinates":[-118.448955,34.149398],"type":"Point"}
}