{
  "type": "Feature",
  "properties": {
    "iso:country":"US",
    "sg:address":"8306 Wilshire Blvd",
    "sg:city":"Beverly Hills",
    "sg:classifiers":[
        {
            "category":"Communications",
            "subcategory":"Film & Video Production",
            "type":"Services"
        }
    ],
    "sg:phone":"+1 323 852 1009",
    "sg:postcode":"90211",
    "sg:province":"CA",
    "sg:tags":[
        "motion",
        "picture",
        "studio",
        "producer"
    ],
    "wof:name":"Blue Star Pictures",
    "wof:placetype":"venue"
},
  "geometry": {"coordinates":[-118.37244699999999,34.064204],"type":"Point"}
}