{
  "type": "Feature",
  "properties": {
    "addr:full":"20739 Lycoming St Ofc Walnut CA 91789",
    "addr:postcode":"20739;91789",
    "addr:street":"Lycoming St",
    "iso:country":"US",
    "sg:address":"20739 Lycoming St Ofc",
    "sg:city":"Walnut",
    "sg:classifiers":[
        {
            "category":"Wholesale",
            "subcategory":"Office Equipment",
            "type":"Manufacturing & Wholesale Goods"
        }
    ],
    "sg:phone":"+1 909 598 3284",
    "sg:postcode":"91789",
    "sg:province":"CA",
    "sg:tags":[
        "equipment-repair",
        "refinish",
        "furniture"
    ],
    "wof:name":"Copri Tech",
    "wof:placetype":"venue"
},
  "geometry": {"coordinates":[-117.852146,34.002877],"type":"Point"}
}