{
  "type": "Feature",
  "properties": {
    "addr:full":"1773 Carson Ct Fairfield CA 94534",
    "addr:housenumber":"1773",
    "addr:postcode":"94534",
    "addr:street":"Carson Ct",
    "iso:country":"US",
    "sg:address":"1773 Carson Ct",
    "sg:city":"Fairfield",
    "sg:classifiers":[
        {
            "category":"Retail",
            "subcategory":"Auto Repair",
            "type":"Services"
        }
    ],
    "sg:phone":"+1 707 426 3354",
    "sg:postcode":"94534",
    "sg:province":"CA",
    "sg:tags":[
        "machine",
        "automotive",
        "shop"
    ],
    "wof:name":"Bradshaw Balancing & Machine",
    "wof:placetype":"venue"
},
  "geometry": {"coordinates":[-122.07060199999999,38.263907],"type":"Point"}
}