{
  "type": "Feature",
  "properties": {
    "iso:country":"US",
    "sg:address":"5375 Kearny Villa Road",
    "sg:city":"San Diego",
    "sg:classifiers":[
        {
            "category":"Restaurant",
            "type":"Food & Drink"
        }
    ],
    "sg:phone":"+1 858 505 9051",
    "sg:postcode":"92123",
    "sg:province":"CA",
    "wof:name":"Gallegos Taco Shop 2",
    "wof:placetype":"venue"
},
  "geometry": {"coordinates":[-117.13938,32.831054],"type":"Point"}
}