{
  "type": "Feature",
  "properties": {
    "addr:full":"217 Church St San Francisco CA 94114",
    "addr:housenumber":"217",
    "addr:postcode":"94114",
    "addr:street":"Church St",
    "iso:country":"US",
    "sg:address":"217 Church St",
    "sg:city":"San Francisco",
    "sg:classifiers":[
        {
            "category":"Wholesale",
            "subcategory":"Durable Goods & Equipment",
            "type":"Manufacturing & Wholesale Goods"
        }
    ],
    "sg:phone":"+1 415 701 1895",
    "sg:postcode":"94114",
    "sg:province":"CA",
    "sg:tags":[
        "recording",
        "compilation"
    ],
    "wof:name":"Putumayo World Music Inc",
    "wof:placetype":"venue"
},
  "geometry": {"coordinates":[-122.42876099999999,37.76636],"type":"Point"}
}