{
  "type": "Feature",
  "properties": {
    "iso:country":"US",
    "sg:address":"1321 W Burbank Blvd",
    "sg:city":"Burbank",
    "sg:classifiers":[
        {
            "category":"Autos & Motor Vehicles",
            "subcategory":"Automobile Sales",
            "type":"Retail Goods"
        }
    ],
    "sg:phone":"+1 818 842 6960",
    "sg:postcode":"91506",
    "sg:province":"CA",
    "sg:tags":[
        "car",
        "dealer"
    ],
    "wof:name":"Radical Auto Deals",
    "wof:placetype":"venue"
},
  "geometry": {"coordinates":[-118.326683,34.182633],"type":"Point"}
}