{
  "type": "Feature",
  "properties": {
    "addr:full":"2300 Broadway St Redwood City CA 94063",
    "addr:housenumber":"2300",
    "addr:postcode":"94063",
    "addr:street":"Broadway St",
    "iso:country":"US",
    "sg:address":"2300 Broadway St",
    "sg:city":"Redwood City",
    "sg:classifiers":[
        {
            "category":"Banks & Credit Unions",
            "subcategory":"Bank",
            "type":"Services"
        }
    ],
    "sg:phone":"+1 650 364 4340",
    "sg:postcode":"94063",
    "sg:province":"CA",
    "sg:website":"www.wamu.com",
    "wof:name":"Washington Mutual",
    "wof:placetype":"venue"
},
  "geometry": {"coordinates":[-122.23106199999999,37.486387],"type":"Point"}
}