{
  "type": "Feature",
  "properties": {
    "iso:country":"US",
    "sg:address":"2690 S White Rd Ste 240",
    "sg:city":"San Jose",
    "sg:classifiers":[
        {
            "category":"Professional",
            "subcategory":"Lawyer & Legal Services",
            "type":"Services"
        }
    ],
    "sg:phone":"+1 408 270 4221",
    "sg:postcode":"95148",
    "sg:province":"CA",
    "wof:name":"Law Office Of Manuel Reynoso",
    "wof:placetype":"venue"
},
  "geometry": {"coordinates":[-121.79809899999999,37.329189],"type":"Point"}
}