{
  "type": "Feature",
  "properties": {
    "addr:full":"801 Brundage Ln Ste C Bakersfield CA 93304",
    "addr:housenumber":"801",
    "addr:postcode":"93304",
    "addr:street":"Brundage Ln Ste C",
    "iso:country":"US",
    "sg:address":"801 Brundage Ln Ste C",
    "sg:city":"Bakersfield",
    "sg:classifiers":[
        {
            "category":"Place Of Worship",
            "subcategory":"Church",
            "type":"Public Place"
        },
        {
            "category":"Place Of Worship",
            "type":"Public Place"
        }
    ],
    "sg:phone":"+1 661 324 0487",
    "sg:postcode":"93304",
    "sg:province":"CA",
    "sg:tags":[
        "churches-interdenominational",
        "churches-various",
        "denomination"
    ],
    "wof:name":"True Dominion & Power Ministries",
    "wof:placetype":"venue"
},
  "geometry": {"coordinates":[-119.010963,35.353882],"type":"Point"}
}