{
  "type": "Feature",
  "properties": {
    "addr:full":"2111 Research Dr Livermore CA 94550",
    "addr:housenumber":"2111",
    "addr:postcode":"94550",
    "addr:street":"Research Dr",
    "iso:country":"US",
    "sg:address":"2111 Research Dr",
    "sg:city":"Livermore",
    "sg:classifiers":[
        {
            "category":"Professional",
            "subcategory":"Business Services",
            "type":"Services"
        }
    ],
    "sg:phone":"+1 925 449 9820",
    "sg:postcode":"94550",
    "sg:province":"CA",
    "sg:tags":[
        "recording",
        "studio"
    ],
    "sg:website":"www.audiovoyage.com",
    "wof:name":"Audio Voyage Recording Svc",
    "wof:placetype":"venue"
},
  "geometry": {"coordinates":[-121.721279,37.678457],"type":"Point"}
}