{
  "type": "Feature",
  "properties": {
    "addr:full":"2436 Foothill Blvd, Ste C Calistoga CA 94515",
    "addr:housenumber":"2436",
    "addr:postcode":"94515",
    "addr:street":"Foothill Blvd Ste C",
    "iso:country":"US",
    "sg:address":"2436 Foothill Blvd, Ste C",
    "sg:city":"Calistoga",
    "sg:classifiers":[
        {
            "category":"Health Services",
            "subcategory":"Health Practitioner",
            "type":"Services"
        }
    ],
    "sg:phone":"+1 707 942 3927",
    "sg:postcode":"94515",
    "sg:province":"CA",
    "sg:tags":[
        "therapy",
        "physical"
    ],
    "wof:name":"Focus Forward Wellness & Physical Therapy",
    "wof:placetype":"venue"
},
  "geometry": {"coordinates":[-122.59558,38.581794],"type":"Point"}
}