{
  "type": "Feature",
  "properties": {
    "addr:full":"1907 W Badillo St West Covina CA 91790",
    "addr:housenumber":"1907",
    "addr:postcode":"91790",
    "addr:street":"W Badillo St",
    "iso:country":"US",
    "sg:address":"1907 W Badillo St",
    "sg:city":"West Covina",
    "sg:classifiers":[
        {
            "category":"Personal",
            "subcategory":"Beauty Salon",
            "type":"Services"
        }
    ],
    "sg:phone":"+1 626 338 3646",
    "sg:postcode":"91790",
    "sg:province":"CA",
    "wof:name":"Joannas Hair Cuts",
    "wof:placetype":"venue"
},
  "geometry": {"coordinates":[-117.94372,34.087194],"type":"Point"}
}