{
  "type": "Feature",
  "properties": {
    "iso:country":"US",
    "sg:address":"1633 San Pablo Ave",
    "sg:city":"Oakland",
    "sg:classifiers":[
        {
            "category":"Professional",
            "subcategory":"Lawyer & Legal Services",
            "type":"Services"
        }
    ],
    "sg:phone":"+1 415 986 1166",
    "sg:postcode":"94612",
    "sg:province":"CA",
    "wof:name":"Vitellus Legal",
    "wof:placetype":"venue"
},
  "geometry": {"coordinates":[-122.272273,37.806868],"type":"Point"}
}