{
  "type": "Feature",
  "properties": {
    "addr:full":"1420 N Batavia St Orange CA 92867",
    "addr:housenumber":"1420",
    "addr:postcode":"92867",
    "addr:street":"N Batavia St",
    "iso:country":"US",
    "sg:address":"1420 N Batavia St",
    "sg:city":"Orange",
    "sg:classifiers":[
        {
            "category":"Manufacturing",
            "subcategory":"Building Materials",
            "type":"Manufacturing & Wholesale Goods"
        },
        {
            "category":"Building & Trades",
            "subcategory":"Construction",
            "type":"Services"
        }
    ],
    "sg:phone":"+1 714 771 2377",
    "sg:postcode":"92867",
    "sg:province":"CA",
    "sg:tags":[
        "mfg",
        "cabinet",
        "contractor",
        "maker",
        "carpentry"
    ],
    "wof:name":"Simpson Customj Woodworks",
    "wof:placetype":"venue"
},
  "geometry": {"coordinates":[-117.862504,33.811008],"type":"Point"}
}