{
  "type": "Feature",
  "properties": {
    "addr:full":"9000 Ming Ave Bakersfield CA 93311",
    "addr:housenumber":"9000",
    "addr:postcode":"93311",
    "addr:street":"Ming Ave",
    "iso:country":"US",
    "sg:address":"9000 Ming Ave",
    "sg:city":"Bakersfield",
    "sg:classifiers":[
        {
            "category":"Restaurant",
            "type":"Food & Drink"
        }
    ],
    "sg:menulink":"http://www.allmenus.com/ca/bakersfield/238050-tahoe-joes-famous-steakhouse/menu/",
    "sg:phone":"+1 661 664 7750",
    "sg:postcode":"93311",
    "sg:province":"CA",
    "sg:tags":[
        "american",
        "steakhouse"
    ],
    "wof:name":"Tahoe Joe's Famous Steakhouse",
    "wof:placetype":"venue"
},
  "geometry": {"coordinates":[-119.10179599999999,35.340185],"type":"Point"}
}