{
  "type": "Feature",
  "properties": {
    "addr:full":"10511 Laramie Pl Chatsworth CA 91311",
    "addr:housenumber":"10511",
    "addr:postcode":"91311",
    "addr:street":"Laramie Pl",
    "iso:country":"US",
    "sg:address":"10511 Laramie Pl",
    "sg:city":"Chatsworth",
    "sg:classifiers":[
        {
            "category":"Professional",
            "subcategory":"Secretarial Services",
            "type":"Services"
        }
    ],
    "sg:phone":"+1 818 709 0460",
    "sg:postcode":"91311",
    "sg:province":"CA",
    "sg:tags":[
        "reporting",
        "court"
    ],
    "wof:name":"Ambassador Secretarial Group",
    "wof:placetype":"venue"
},
  "geometry": {"coordinates":[-118.57338,34.262041],"type":"Point"}
}