{
  "type": "Feature",
  "properties": {
    "addr:full":"616 Gilroy Dr Capitola CA 95010",
    "addr:housenumber":"616",
    "addr:postcode":"95010",
    "addr:street":"Gilroy Dr",
    "iso:country":"US",
    "sg:address":"616 Gilroy Dr",
    "sg:city":"Capitola",
    "sg:classifiers":[
        {
            "category":"Real Estate",
            "subcategory":"Real Estate Agent",
            "type":"Services"
        }
    ],
    "sg:phone":"+1 831 477 0100",
    "sg:postcode":"95010",
    "sg:province":"CA",
    "sg:tags":[
        "appraiser"
    ],
    "wof:name":"Home Appraisals",
    "wof:placetype":"venue"
},
  "geometry": {"coordinates":[-121.954994,36.97984],"type":"Point"}
}