{
  "type": "Feature",
  "properties": {
    "addr:full":"6055 Magnolia Ave Riverside CA 92506",
    "addr:housenumber":"6055",
    "addr:postcode":"92506",
    "addr:street":"Magnolia Ave",
    "iso:country":"US",
    "sg:address":"6055 Magnolia Ave",
    "sg:city":"Riverside",
    "sg:classifiers":[
        {
            "category":"Restaurant",
            "type":"Food & Drink"
        }
    ],
    "sg:phone":"+1 951 276 4984",
    "sg:postcode":"92506",
    "sg:province":"CA",
    "wof:name":"New Hong Kong Chinese Rstrnt",
    "wof:placetype":"venue"
},
  "geometry": {"coordinates":[-117.391981,33.960761],"type":"Point"}
}