{
  "type": "Feature",
  "properties": {
    "iso:country":"US",
    "sg:address":"115 Crown Rd",
    "sg:city":"Watsonville",
    "sg:classifiers":[
        {
            "category":"Farming",
            "subcategory":"Farm",
            "type":"Manufacturing & Wholesale Goods"
        }
    ],
    "sg:phone":"+1 831 728 4322",
    "sg:postcode":"95076",
    "sg:province":"CA",
    "wof:name":"Richard Uyematsu Farms",
    "wof:placetype":"venue"
},
  "geometry": {"coordinates":[-121.686122,36.912037],"type":"Point"}
}