{
  "type": "Feature",
  "properties": {
    "iso:country":"US",
    "sg:address":"828 E Lewelling Blvd",
    "sg:city":"Hayward",
    "sg:classifiers":[
        {
            "category":"Home & Garden",
            "subcategory":"Household Appliances",
            "type":"Retail Goods"
        }
    ],
    "sg:phone":"+1 510 278 2308",
    "sg:postcode":"94541",
    "sg:province":"CA",
    "wof:name":"Nu-Vac",
    "wof:placetype":"venue"
},
  "geometry": {"coordinates":[-122.10858,37.687801],"type":"Point"}
}