{
  "type": "Feature",
  "properties": {
    "addr:full":"4370 La Jolla Village Drive Suite 1000 San Diego CA 92122",
    "addr:housenumber":"4370",
    "addr:postcode":"92122",
    "addr:street":"La Jolla Village Drive Suite 1000",
    "iso:country":"US",
    "sg:address":"4370 La Jolla Village Drive Suite 1000",
    "sg:city":"San Diego",
    "sg:classifiers":[
        {
            "category":"Banks & Credit Unions",
            "subcategory":"Bank",
            "type":"Services"
        },
        {
            "category":"Banks & Credit Unions",
            "subcategory":"Financial Services",
            "type":"Services"
        }
    ],
    "sg:phone":"+1 858 824 1200",
    "sg:postcode":"92122",
    "sg:province":"CA",
    "sg:tags":[
        "broker",
        "mortgage"
    ],
    "wof:name":"Northern Trust Bank",
    "wof:placetype":"venue"
},
  "geometry": {"coordinates":[-117.212368,32.873099],"type":"Point"}
}