{
  "type": "Feature",
  "properties": {
    "iso:country":"US",
    "sg:address":"218 I St",
    "sg:city":"Antioch",
    "sg:classifiers":[
        {
            "category":"Government",
            "subcategory":"Office",
            "type":"Public Place"
        }
    ],
    "sg:phone":"+1 925 778 8800",
    "sg:postcode":"94509",
    "sg:province":"CA",
    "sg:tags":[
        "program",
        "state",
        "adm"
    ],
    "wof:name":"Employment Development Dept",
    "wof:placetype":"venue"
},
  "geometry": {"coordinates":[-121.81598,38.016326],"type":"Point"}
}