{
  "type": "Feature",
  "properties": {
    "iso:country":"US",
    "sg:address":"15505 Facilidad St",
    "sg:city":"Hacienda Heights",
    "sg:classifiers":[
        {
            "category":"Professional",
            "subcategory":"Management & Consulting",
            "type":"Services"
        }
    ],
    "sg:phone":"+1 626 820 0955",
    "sg:postcode":"91745",
    "sg:province":"CA",
    "sg:tags":[
        "marketing",
        "program"
    ],
    "wof:name":"Healthcare Marketing Svc",
    "wof:placetype":"venue"
},
  "geometry": {"coordinates":[-117.980211,33.990749],"type":"Point"}
}