{
  "type": "Feature",
  "properties": {
    "addr:full":"978 Kaiser Rd Napa CA 94558",
    "addr:housenumber":"978",
    "addr:postcode":"94558",
    "addr:street":"Kaiser Rd",
    "iso:country":"US",
    "sg:address":"978 Kaiser Rd",
    "sg:city":"Napa",
    "sg:classifiers":[
        {
            "category":"Professional",
            "subcategory":"Management & Consulting",
            "type":"Services"
        }
    ],
    "sg:phone":"+1 707 224 7434",
    "sg:postcode":"94558",
    "sg:province":"CA",
    "sg:tags":[
        "break",
        "coffee",
        "supply"
    ],
    "sg:website":"www.paupaiz.com",
    "wof:name":"Paupaiz Fine Coffees",
    "wof:placetype":"venue"
},
  "geometry": {"coordinates":[-122.275571,38.257594],"type":"Point"}
}