{
  "type": "Feature",
  "properties": {
    "addr:full":"543 F St Lincoln CA 95648",
    "addr:housenumber":"543",
    "addr:postcode":"95648",
    "addr:street":"F St",
    "iso:country":"US",
    "sg:address":"543 F St",
    "sg:city":"Lincoln",
    "sg:classifiers":[
        {
            "category":"Personal",
            "subcategory":"Beauty Salon",
            "type":"Services"
        }
    ],
    "sg:phone":"+1 916 645 4220",
    "sg:postcode":"95648",
    "sg:province":"CA",
    "wof:name":"Skin Essentials",
    "wof:placetype":"venue"
},
  "geometry": {"coordinates":[-121.291472,38.892611],"type":"Point"}
}