{
  "type": "Feature",
  "properties": {
    "iso:country":"US",
    "sg:address":"3860 Convoy St",
    "sg:city":"San Diego",
    "sg:classifiers":[
        {
            "category":"Restaurant",
            "type":"Food & Drink"
        }
    ],
    "sg:menulink":"http://www.allmenus.com/ca/san-diego/59421-subway/menu/",
    "sg:phone":"+1 858 292 4141",
    "sg:postcode":"92111",
    "sg:province":"CA",
    "sg:tags":[
        "american",
        "sandwich"
    ],
    "wof:name":"Subway",
    "wof:placetype":"venue"
},
  "geometry": {"coordinates":[-117.16864,32.83454],"type":"Point"}
}