{
  "type": "Feature",
  "properties": {
    "iso:country":"US",
    "sg:address":"1109 Mound Ave",
    "sg:city":"South Pasadena",
    "sg:classifiers":[
        {
            "category":"Professional",
            "type":"Services"
        }
    ],
    "sg:phone":"+1 626 403 0216",
    "sg:postcode":"91030",
    "sg:province":"CA",
    "sg:tags":[
        "establishment"
    ],
    "wof:name":"Evergreen Village Hoa",
    "wof:placetype":"venue"
},
  "geometry": {"coordinates":[-118.151841,34.112231],"type":"Point"}
}