{
  "type": "Feature",
  "properties": {
    "iso:country":"US",
    "sg:address":"8324 Hollywood Blvd",
    "sg:city":"West Hollywood",
    "sg:classifiers":[
        {
            "category":"Communications",
            "subcategory":"Film & Video Production",
            "type":"Services"
        }
    ],
    "sg:phone":"+1 323 468 8340",
    "sg:postcode":"90069",
    "sg:province":"CA",
    "sg:tags":[
        "motion",
        "picture",
        "studio",
        "producer"
    ],
    "wof:name":"Kinetic Pictures",
    "wof:placetype":"venue"
},
  "geometry": {"coordinates":[-118.368363,34.099129],"type":"Point"}
}