{
  "type": "Feature",
  "properties": {
    "addr:full":"543 Athol Ave Oakland CA 94606",
    "addr:housenumber":"543",
    "addr:postcode":"94606",
    "addr:street":"Athol Ave",
    "iso:country":"US",
    "sg:address":"543 Athol Ave",
    "sg:city":"Oakland",
    "sg:classifiers":[
        {
            "category":"Arts & Performance",
            "subcategory":"Theater",
            "type":"Entertainment"
        }
    ],
    "sg:phone":"+1 510 836 6773",
    "sg:postcode":"94606",
    "sg:province":"CA",
    "sg:tags":[
        "opera",
        "company"
    ],
    "sg:website":"www.oaklandlyricopera.com",
    "wof:name":"Oakland Lyric Opera",
    "wof:placetype":"venue"
},
  "geometry": {"coordinates":[-122.245555,37.803822],"type":"Point"}
}