{
  "type": "Feature",
  "properties": {
    "addr:full":"8989 Mission Blvd Riverside CA 92509",
    "addr:housenumber":"8989",
    "addr:postcode":"92509",
    "addr:street":"Mission Blvd",
    "iso:country":"US",
    "sg:address":"8989 Mission Blvd",
    "sg:city":"Riverside",
    "sg:classifiers":[
        {
            "category":"Health Services",
            "subcategory":"Clinic",
            "type":"Services"
        }
    ],
    "sg:phone":"+1 951 361 1366",
    "sg:postcode":"92509",
    "sg:province":"CA",
    "sg:tags":[
        "hospital",
        "specialty",
        "outpatient"
    ],
    "wof:name":"De 24 En 24",
    "wof:placetype":"venue"
},
  "geometry": {"coordinates":[-117.478707,34.011874],"type":"Point"}
}