{
  "type": "Feature",
  "properties": {
    "addr:full":"590 W Hedding St San Jose CA 95110",
    "addr:housenumber":"590",
    "addr:postcode":"95110",
    "addr:street":"W Hedding St",
    "iso:country":"US",
    "sg:address":"590 W Hedding St",
    "sg:city":"San Jose",
    "sg:classifiers":[
        {
            "category":"Retail",
            "subcategory":"Auto Repair",
            "type":"Services"
        }
    ],
    "sg:phone":"+1 408 292 9171",
    "sg:postcode":"95110",
    "sg:province":"CA",
    "sg:tags":[
        "repairing",
        "automobile"
    ],
    "wof:name":"John Colendich Automotive Svc",
    "wof:placetype":"venue"
},
  "geometry": {"coordinates":[-121.915262,37.346132],"type":"Point"}
}