{
  "type": "Feature",
  "properties": {
    "iso:country":"US",
    "sg:address":"6304 Sandpiper Ct",
    "sg:city":"Citrus Heights",
    "sg:classifiers":[
        {
            "category":"Building & Trades",
            "subcategory":"Construction",
            "type":"Services"
        },
        {
            "category":"Home & Garden",
            "subcategory":"Carpets & Floor Coverings",
            "type":"Retail Goods"
        }
    ],
    "sg:phone":"+1 916 712 2627",
    "sg:postcode":"95610",
    "sg:province":"CA",
    "sg:tags":[
        "flooring",
        "contractor"
    ],
    "wof:name":"Universal Flooring",
    "wof:placetype":"venue"
},
  "geometry": {"coordinates":[-121.277012,38.68075],"type":"Point"}
}