{
  "type": "Feature",
  "properties": {
    "iso:country":"US",
    "sg:address":"1482 E Valley Rd",
    "sg:city":"Santa Barbara",
    "sg:classifiers":[
        {
            "category":"Professional",
            "subcategory":"Advertising",
            "type":"Services"
        }
    ],
    "sg:phone":"+1 805 695 8488",
    "sg:postcode":"93108",
    "sg:province":"CA",
    "sg:tags":[
        "distribution"
    ],
    "wof:name":"Weber Distribution",
    "wof:placetype":"venue"
},
  "geometry": {"coordinates":[-119.633506,34.437032],"type":"Point"}
}