{
  "type": "Feature",
  "properties": {
    "iso:country":"US",
    "sg:address":"345 Oak Manor Dr",
    "sg:city":"Fairfax",
    "sg:classifiers":[
        {
            "category":"Manufacturing",
            "subcategory":"Printing",
            "type":"Manufacturing & Wholesale Goods"
        }
    ],
    "sg:phone":"+1 415 785 7517",
    "sg:postcode":"94930",
    "sg:province":"CA",
    "sg:tags":[
        "publishing"
    ],
    "wof:name":"Epiphanycards",
    "wof:placetype":"venue"
},
  "geometry": {"coordinates":[-122.593899,38.000787],"type":"Point"}
}