{
  "type": "Feature",
  "properties": {
    "addr:full":"3000 Eastern Ave Sacramento CA 95821",
    "addr:housenumber":"3000",
    "addr:postcode":"95821",
    "addr:street":"Eastern Ave",
    "iso:country":"US",
    "sg:address":"3000 Eastern Ave",
    "sg:city":"Sacramento",
    "sg:classifiers":[
        {
            "category":"Building & Trades",
            "subcategory":"Construction",
            "type":"Services"
        }
    ],
    "sg:phone":"+1 916 201 7292",
    "sg:postcode":"95821",
    "sg:province":"CA",
    "sg:tags":[
        "woodworker"
    ],
    "wof:name":"Into Wood",
    "wof:placetype":"venue"
},
  "geometry": {"coordinates":[-121.364476,38.62122],"type":"Point"}
}