{
  "type": "Feature",
  "properties": {
    "iso:country":"US",
    "sg:address":"5911 South St",
    "sg:city":"Lakewood",
    "sg:classifiers":[
        {
            "category":"Health Services",
            "subcategory":"Dentist",
            "type":"Services"
        }
    ],
    "sg:phone":"+1 562 461 2991",
    "sg:postcode":"90713",
    "sg:province":"CA",
    "wof:name":"Cabanban Dr M Hernandez",
    "wof:placetype":"venue"
},
  "geometry": {"coordinates":[-118.11799600000001,33.858601],"type":"Point"}
}