{
  "type": "Feature",
  "properties": {
    "iso:country":"US",
    "sg:address":"304 N Kathryn Dr",
    "sg:city":"Anaheim",
    "sg:classifiers":[
        {
            "category":"Building & Trades",
            "subcategory":"Landscaping Services",
            "type":"Services"
        }
    ],
    "sg:phone":"+1 714 746 3004",
    "sg:postcode":"92801",
    "sg:province":"CA",
    "sg:tags":[
        "tree"
    ],
    "wof:name":"B R J Landscape",
    "wof:placetype":"venue"
},
  "geometry": {"coordinates":[-117.960758,33.835544],"type":"Point"}
}