{
  "type": "Feature",
  "properties": {
    "addr:full":"42335 Washington St Palm Desert CA 92211",
    "addr:housenumber":"42335",
    "addr:postcode":"92211",
    "addr:street":"Washington St",
    "iso:country":"US",
    "sg:address":"42335 Washington St",
    "sg:city":"Palm Desert",
    "sg:classifiers":[
        {
            "category":"Retail",
            "subcategory":"Car Wash",
            "type":"Services"
        }
    ],
    "sg:phone":"+1 760 772 5991",
    "sg:postcode":"92211",
    "sg:province":"CA",
    "sg:tags":[
        "automobile",
        "detail",
        "clean"
    ],
    "wof:name":"Got Heat",
    "wof:placetype":"venue"
},
  "geometry": {"coordinates":[-116.30393100000001,33.742839],"type":"Point"}
}