{
  "type": "Feature",
  "properties": {
    "addr:full":"9825 International Blvd Oakland CA 94603",
    "addr:housenumber":"9825",
    "addr:postcode":"94603",
    "addr:street":"International Blvd",
    "iso:country":"US",
    "sg:address":"9825 International Blvd",
    "sg:city":"Oakland",
    "sg:classifiers":[
        {
            "category":"Restaurant",
            "type":"Food & Drink"
        }
    ],
    "sg:phone":"+1 510 638 5988",
    "sg:postcode":"94603",
    "sg:province":"CA",
    "wof:name":"Kentucky Fried Chicken",
    "wof:placetype":"venue"
},
  "geometry": {"coordinates":[-122.16999800000001,37.7439],"type":"Point"}
}