{
  "type": "Feature",
  "properties": {
    "addr:full":"1053 Arkell Rd Walnut Creek CA 94598",
    "addr:housenumber":"1053",
    "addr:postcode":"94598",
    "addr:street":"Arkell Rd",
    "iso:country":"US",
    "sg:address":"1053 Arkell Rd",
    "sg:city":"Walnut Creek",
    "sg:classifiers":[
        {
            "category":"Wholesale",
            "subcategory":"Auto Parts",
            "type":"Manufacturing & Wholesale Goods"
        }
    ],
    "sg:phone":"+1 925 366 6645",
    "sg:postcode":"94598",
    "sg:province":"CA",
    "wof:name":"Matco Tools",
    "wof:placetype":"venue"
},
  "geometry": {"coordinates":[-122.031701,37.932501],"type":"Point"}
}