{
  "type": "Feature",
  "properties": {
    "iso:country":"US",
    "sg:address":"130 Fogg St",
    "sg:city":"Colton",
    "sg:classifiers":[
        {
            "category":"Food & Beverages",
            "subcategory":"Specialty",
            "type":"Retail Goods"
        }
    ],
    "sg:phone":"+1 951 686 2040",
    "sg:postcode":"92324",
    "sg:province":"CA",
    "sg:tags":[
        "water",
        "bulk",
        "company"
    ],
    "wof:name":"Puritas Distilled Drnk Water",
    "wof:placetype":"venue"
},
  "geometry": {"coordinates":[-117.325712,34.052836],"type":"Point"}
}