{
  "type": "Feature",
  "properties": {
    "addr:full":"5223 Gayle Dr Santa Rosa CA 95403",
    "addr:housenumber":"5223",
    "addr:postcode":"95403",
    "addr:street":"Gayle Dr",
    "iso:country":"US",
    "sg:address":"5223 Gayle Dr",
    "sg:city":"Santa Rosa",
    "sg:classifiers":[
        {
            "category":"Professional",
            "type":"Services"
        }
    ],
    "sg:phone":"+1 707 566 8034",
    "sg:postcode":"95403",
    "sg:province":"CA",
    "wof:name":"Marin Cultural Center",
    "wof:placetype":"venue"
},
  "geometry": {"coordinates":[-122.778756,38.509019],"type":"Point"}
}