{
  "type": "Feature",
  "properties": {
    "iso:country":"US",
    "sg:address":"6001 Truxtun Ave",
    "sg:city":"Bakersfield",
    "sg:classifiers":[
        {
            "category":"Health Services",
            "subcategory":"Hospital",
            "type":"Services"
        }
    ],
    "sg:phone":"+1 661 323 8100",
    "sg:postcode":"93309",
    "sg:province":"CA",
    "sg:tags":[
        "sleep",
        "treatment",
        "disorders-information"
    ],
    "wof:name":"Apne Quest Sleep Center",
    "wof:placetype":"venue"
},
  "geometry": {"coordinates":[-119.06967899999999,35.363541],"type":"Point"}
}