{
  "type": "Feature",
  "properties": {
    "addr:full":"21141 Strathmoor Ln Huntington Beach CA 92646",
    "addr:housenumber":"21141",
    "addr:postcode":"92646",
    "addr:street":"Strathmoor Ln",
    "iso:country":"US",
    "sg:address":"21141 Strathmoor Ln",
    "sg:city":"Huntington Beach",
    "sg:classifiers":[
        {
            "category":"Education",
            "subcategory":"Special Training",
            "type":"Public Place"
        },
        {
            "category":"Education",
            "subcategory":"School",
            "type":"Public Place"
        }
    ],
    "sg:phone":"+1 714 235 5559",
    "sg:postcode":"92646",
    "sg:province":"CA",
    "sg:tags":[
        "high",
        "middle",
        "elementary",
        "language"
    ],
    "sg:website":"www.orangecoastgakuen.org",
    "wof:name":"Orange Coast Gakuen Japanese Language School",
    "wof:placetype":"venue"
},
  "geometry": {"coordinates":[-117.957596,33.656062],"type":"Point"}
}