{
  "type": "Feature",
  "properties": {
    "addr:full":"4040 Easton Dr Bakersfield CA 93309",
    "addr:housenumber":"4040",
    "addr:postcode":"93309",
    "addr:street":"Easton Dr",
    "iso:country":"US",
    "sg:address":"4040 Easton Dr",
    "sg:city":"Bakersfield",
    "sg:classifiers":[
        {
            "category":"Shopping",
            "subcategory":"Bicycles & Sporting Goods",
            "type":"Retail Goods"
        }
    ],
    "sg:phone":"+1 661 327 1976",
    "sg:postcode":"93309",
    "sg:province":"CA",
    "sg:tags":[
        "gun",
        "gunsmith"
    ],
    "wof:name":"Ammo Dump",
    "wof:placetype":"venue"
},
  "geometry": {"coordinates":[-119.04447,35.367759],"type":"Point"}
}