{
  "type": "Feature",
  "properties": {
    "addr:full":"4384 Moraga Ave San Diego CA 92117",
    "addr:housenumber":"4384",
    "addr:postcode":"92117",
    "addr:street":"Moraga Ave",
    "iso:country":"US",
    "sg:address":"4384 Moraga Ave",
    "sg:city":"San Diego",
    "sg:classifiers":[
        {
            "category":"Food & Beverages",
            "subcategory":"Liquor & Beverages",
            "type":"Retail Goods"
        }
    ],
    "sg:phone":"+1 858 274 3811",
    "sg:postcode":"92117",
    "sg:province":"CA",
    "sg:tags":[
        "wine"
    ],
    "wof:name":"R J Liquor",
    "wof:placetype":"venue"
},
  "geometry": {"coordinates":[-117.21364199999999,32.822387],"type":"Point"}
}