{
  "type": "Feature",
  "properties": {
    "addr:full":"11108 Whittier Blvd Whittier CA 90606",
    "addr:housenumber":"11108",
    "addr:postcode":"90606",
    "addr:street":"Whittier Blvd",
    "iso:country":"US",
    "sg:address":"11108 Whittier Blvd",
    "sg:city":"Whittier",
    "sg:classifiers":[
        {
            "category":"Retail",
            "subcategory":"Laundry & Dry Cleaning",
            "type":"Services"
        }
    ],
    "sg:phone":"+1 562 699 7190",
    "sg:postcode":"90606",
    "sg:province":"CA",
    "wof:name":"A 1 Laundry Mart",
    "wof:placetype":"venue"
},
  "geometry": {"coordinates":[-118.058431,33.98607],"type":"Point"}
}