{
  "type": "Feature",
  "properties": {
    "addr:full":"2906 Santa Fe St Riverbank CA 95367",
    "addr:housenumber":"2906",
    "addr:postcode":"95367",
    "addr:street":"Santa Fe St",
    "iso:country":"US",
    "sg:address":"2906 Santa Fe St",
    "sg:city":"Riverbank",
    "sg:classifiers":[
        {
            "category":"Manufacturing",
            "subcategory":"Food",
            "type":"Manufacturing & Wholesale Goods"
        }
    ],
    "sg:phone":"+1 209 869 9300",
    "sg:postcode":"95367",
    "sg:province":"CA",
    "sg:tags":[
        "canning"
    ],
    "wof:name":"California Fruit/Tomato Ktchns",
    "wof:placetype":"venue"
},
  "geometry": {"coordinates":[-120.943378,37.735938],"type":"Point"}
}