{
  "type": "Feature",
  "properties": {
    "iso:country":"US",
    "sg:address":"7956 Orchid Dr",
    "sg:city":"Buena Park",
    "sg:classifiers":[
        {
            "category":"Travel",
            "subcategory":"Travel Agent",
            "type":"Entertainment"
        }
    ],
    "sg:phone":"+1 714 522 4947",
    "sg:postcode":"90620",
    "sg:province":"CA",
    "sg:tags":[
        "tours",
        "promoter"
    ],
    "wof:name":"Afrika Travel Tours & Safari",
    "wof:placetype":"venue"
},
  "geometry": {"coordinates":[-117.994789,33.854494],"type":"Point"}
}