{
  "type": "Feature",
  "properties": {
    "addr:full":"14411 Vanowen St Van Nuys CA 91405",
    "addr:housenumber":"14411",
    "addr:postcode":"91405",
    "addr:street":"Vanowen St",
    "iso:country":"US",
    "sg:address":"14411 Vanowen St",
    "sg:city":"Van Nuys",
    "sg:classifiers":[
        {
            "category":"Social Services",
            "type":"Services"
        }
    ],
    "sg:phone":"+1 818 781 1674",
    "sg:postcode":"91405",
    "sg:province":"CA",
    "sg:tags":[
        "organization",
        "welfare"
    ],
    "wof:name":"San Fernando Valley Comm",
    "wof:placetype":"venue"
},
  "geometry": {"coordinates":[-118.448536,34.194001],"type":"Point"}
}