{
  "type": "Feature",
  "properties": {
    "addr:full":"2041 Landings Dr Mountain View CA 94043",
    "addr:housenumber":"2041",
    "addr:postcode":"94043",
    "addr:street":"Landings Dr",
    "iso:country":"US",
    "sg:address":"2041 Landings Dr",
    "sg:city":"Mountain View",
    "sg:classifiers":[
        {
            "category":"Shopping",
            "subcategory":"Computers & Home Electronics",
            "type":"Retail Goods"
        }
    ],
    "sg:phone":"+1 650 426 2000",
    "sg:postcode":"94043",
    "sg:province":"CA",
    "sg:tags":[
        "software"
    ],
    "wof:name":"Wayfarer Communications Inc",
    "wof:placetype":"venue"
},
  "geometry": {"coordinates":[-122.089783,37.42107],"type":"Point"}
}