{
  "type": "Feature",
  "properties": {
    "iso:country":"US",
    "sg:address":"60 Alta St",
    "sg:city":"Arcadia",
    "sg:classifiers":[
        {
            "category":"Real Estate",
            "subcategory":"Architect",
            "type":"Services"
        }
    ],
    "sg:phone":"+1 626 447 3068",
    "sg:postcode":"91006",
    "sg:province":"CA",
    "sg:website":"www.coardesign.com",
    "wof:name":"Co-Ar Design Inc",
    "wof:placetype":"venue"
},
  "geometry": {"coordinates":[-118.95058400000001,34.13883],"type":"Point"}
}