{
  "type": "Feature",
  "properties": {
    "addr:full":"16500 Los Gatos Blvd Los Gatos CA 95032",
    "addr:housenumber":"16500",
    "addr:postcode":"95032",
    "addr:street":"Los Gatos Blvd",
    "iso:country":"US",
    "sg:address":"16500 Los Gatos Blvd",
    "sg:city":"Los Gatos",
    "sg:classifiers":[
        {
            "category":"Retail",
            "subcategory":"Auto Repair",
            "type":"Services"
        }
    ],
    "sg:phone":"+1 408 356 1117",
    "sg:postcode":"95032",
    "sg:province":"CA",
    "sg:tags":[
        "automobile",
        "smog"
    ],
    "wof:name":"Smog People",
    "wof:placetype":"venue"
},
  "geometry": {"coordinates":[-121.96539,37.230582],"type":"Point"}
}