{
  "type": "Feature",
  "properties": {
    "iso:country":"US",
    "sg:address":"17815 Ventura Blvd",
    "sg:city":"Encino",
    "sg:classifiers":[
        {
            "category":"Health Services",
            "subcategory":"Doctor",
            "type":"Services"
        }
    ],
    "sg:phone":"+1 818 708 4909",
    "sg:postcode":"91316",
    "sg:province":"CA",
    "sg:tags":[
        "dentist"
    ],
    "sg:website":"www.braces4yu.com",
    "wof:name":"Stephen Y Yu DDS",
    "wof:placetype":"venue"
},
  "geometry": {"coordinates":[-118.521781,34.163509],"type":"Point"}
}