{
  "type": "Feature",
  "properties": {
    "addr:full":"1628 Culpepper Ave Ste A Modesto CA 95351",
    "addr:housenumber":"1628",
    "addr:postcode":"ca 95351",
    "addr:street":"Culpepper Ave Ste A",
    "iso:country":"US",
    "sg:address":"1628 Culpepper Ave Ste A",
    "sg:city":"Modesto",
    "sg:classifiers":[
        {
            "category":"Building & Trades",
            "subcategory":"Electrical",
            "type":"Services"
        }
    ],
    "sg:phone":"+1 209 522 2244",
    "sg:postcode":"95351",
    "sg:province":"CA",
    "sg:tags":[
        "electrician"
    ],
    "sg:website":"www.laymanelectric.com",
    "wof:name":"Layman Electric Inc",
    "wof:placetype":"venue"
},
  "geometry": {"coordinates":[-121.02800000000001,37.659901],"type":"Point"}
}