{
  "type": "Feature",
  "properties": {
    "iso:country":"US",
    "sg:address":"900 N San Fernando Blvd",
    "sg:city":"Burbank",
    "sg:classifiers":[
        {
            "category":"Banks & Credit Unions",
            "subcategory":"Bank",
            "type":"Services"
        }
    ],
    "sg:phone":"+1 818 841 6550",
    "sg:postcode":"91504",
    "sg:province":"CA",
    "sg:website":"www.wellsfargo.com",
    "wof:name":"Wells Fargo",
    "wof:placetype":"venue"
},
  "geometry": {"coordinates":[-118.31594800000001,34.186378],"type":"Point"}
}