{
  "type": "Feature",
  "properties": {
    "iso:country":"US",
    "sg:address":"4537 Sierra St",
    "sg:city":"Riverside",
    "sg:classifiers":[
        {
            "category":"Restaurant",
            "type":"Food & Drink"
        }
    ],
    "sg:phone":"+1 951 354 7170",
    "sg:postcode":"92504",
    "sg:province":"CA",
    "wof:name":"Subway Sandwiches & Salads",
    "wof:placetype":"venue"
},
  "geometry": {"coordinates":[-117.402202,33.949916],"type":"Point"}
}