{
  "type": "Feature",
  "properties": {
    "iso:country":"US",
    "sg:address":"107 Kendall Rd",
    "sg:city":"Walnut Creek",
    "sg:classifiers":[
        {
            "category":"Manufacturing",
            "subcategory":"Apparel",
            "type":"Manufacturing & Wholesale Goods"
        }
    ],
    "sg:phone":"+1 925 937 1821",
    "sg:postcode":"94595",
    "sg:province":"CA",
    "sg:tags":[
        "textile",
        "product",
        "fabricated",
        "mfg"
    ],
    "wof:name":"Sassy Mommy",
    "wof:placetype":"venue"
},
  "geometry": {"coordinates":[-122.07884300000001,37.894562],"type":"Point"}
}