{
  "type": "Feature",
  "properties": {
    "iso:country":"US",
    "sg:address":"777 S California Ave",
    "sg:city":"Palo Alto",
    "sg:classifiers":[
        {
            "category":"Real Estate",
            "subcategory":"Real Estate Agent",
            "type":"Services"
        }
    ],
    "sg:phone":"+1 650 856 9800",
    "sg:postcode":"94306",
    "sg:province":"CA",
    "sg:tags":[
        "management"
    ],
    "sg:website":"www.pacificpropertycompany.com",
    "wof:name":"Pacific Property Co",
    "wof:placetype":"venue"
},
  "geometry": {"coordinates":[-122.14767999999999,37.42281],"type":"Point"}
}