{
  "type": "Feature",
  "properties": {
    "addr:full":"6417 Ming Ave Bakersfield CA 93309",
    "addr:housenumber":"6417",
    "addr:postcode":"93309",
    "addr:street":"Ming Ave",
    "iso:country":"US",
    "sg:address":"6417 Ming Ave",
    "sg:city":"Bakersfield",
    "sg:classifiers":[
        {
            "category":"Restaurant",
            "type":"Food & Drink"
        }
    ],
    "sg:phone":"+1 661 397 9700",
    "sg:postcode":"93309",
    "sg:province":"CA",
    "wof:name":"Magoo's Pizza",
    "wof:placetype":"venue"
},
  "geometry": {"coordinates":[-119.074195,35.334662],"type":"Point"}
}