{
  "type": "Feature",
  "properties": {
    "addr:full":"11186 Penrose St Sun Valley CA 91352",
    "addr:housenumber":"11186",
    "addr:postcode":"91352",
    "addr:street":"Penrose St",
    "iso:country":"US",
    "sg:address":"11186 Penrose St",
    "sg:city":"Sun Valley",
    "sg:classifiers":[
        {
            "category":"Building & Trades",
            "subcategory":"Construction",
            "type":"Services"
        }
    ],
    "sg:phone":"+1 818 768 3850",
    "sg:postcode":"91352",
    "sg:province":"CA",
    "sg:tags":[
        "maker",
        "cabinet"
    ],
    "wof:name":"GDK Construction",
    "wof:placetype":"venue"
},
  "geometry": {"coordinates":[-118.37527900000001,34.226297],"type":"Point"}
}