{
  "type": "Feature",
  "properties": {
    "iso:country":"US",
    "sg:address":"17393 E Park",
    "sg:city":"Chino Hills",
    "sg:classifiers":[
        {
            "category":"Freight",
            "type":"Transportation"
        }
    ],
    "sg:phone":"+1 909 393 0336",
    "sg:postcode":"91709",
    "sg:province":"CA",
    "sg:tags":[
        "trucking"
    ],
    "wof:name":"J Lee Trucking",
    "wof:placetype":"venue"
},
  "geometry": {"coordinates":[-117.67081899999999,33.937325],"type":"Point"}
}