{
  "type": "Feature",
  "properties": {
    "addr:full":"11289 W Pico Blvd Los Angeles CA 90064",
    "addr:housenumber":"11289",
    "addr:postcode":"90064",
    "addr:street":"W Pico Blvd",
    "iso:country":"US",
    "sg:address":"11289 W Pico Blvd",
    "sg:city":"Los Angeles",
    "sg:classifiers":[
        {
            "category":"Restaurant",
            "type":"Food & Drink"
        }
    ],
    "sg:phone":"+1 310 479 0601",
    "sg:postcode":"90064",
    "sg:province":"CA",
    "sg:tags":[
        "sandwich"
    ],
    "wof:name":"Big Tomy's",
    "wof:placetype":"venue"
},
  "geometry": {"coordinates":[-118.43800400000001,34.035198],"type":"Point"}
}