{
  "type": "Feature",
  "properties": {
    "addr:full":"601 N Coast Hwy Oceanside CA 92054",
    "addr:housenumber":"601",
    "addr:postcode":"92054",
    "addr:street":"N Coast Hwy",
    "iso:country":"US",
    "sg:address":"601 N Coast Hwy",
    "sg:city":"Oceanside",
    "sg:classifiers":[
        {
            "category":"Autos & Motor Vehicles",
            "subcategory":"Fuel & Gas Station",
            "type":"Retail Goods"
        }
    ],
    "sg:phone":"+1 760 967 0797",
    "sg:postcode":"92054",
    "sg:province":"CA",
    "wof:name":"G & M Oil No 53",
    "wof:placetype":"venue"
},
  "geometry": {"coordinates":[-117.383003,33.199501],"type":"Point"}
}