{
  "type": "Feature",
  "properties": {
    "iso:country":"US",
    "sg:address":"39440 Rd 36",
    "sg:city":"Kingsburg",
    "sg:classifiers":[
        {
            "category":"Farming",
            "subcategory":"Orchard",
            "type":"Manufacturing & Wholesale Goods"
        }
    ],
    "sg:phone":"+1 559 897 4212",
    "sg:postcode":"93631",
    "sg:province":"CA",
    "sg:tags":[
        "vineyard",
        "tree",
        "fruit",
        "grape"
    ],
    "wof:name":"Gary Olson",
    "wof:placetype":"venue"
},
  "geometry": {"coordinates":[-119.493736,36.500673],"type":"Point"}
}