{
  "type": "Feature",
  "properties": {
    "iso:country":"US",
    "sg:address":"510 G St",
    "sg:city":"Antioch",
    "sg:classifiers":[
        {
            "category":"Education",
            "subcategory":"School",
            "type":"Public Place"
        }
    ],
    "sg:phone":"+1 925 706 4100",
    "sg:postcode":"94509",
    "sg:province":"CA",
    "sg:website":"http://www.antioch.k12.ca.us",
    "wof:name":"Antioch Unified School District",
    "wof:placetype":"venue"
},
  "geometry": {"coordinates":[-121.813766,38.014687],"type":"Point"}
}