{
  "type": "Feature",
  "properties": {
    "addr:full":"1400 Lewis St Kingsburg CA 93631",
    "addr:housenumber":"1400",
    "addr:postcode":"93631",
    "addr:street":"Lewis St",
    "iso:country":"US",
    "sg:address":"1400 Lewis St",
    "sg:city":"Kingsburg",
    "sg:classifiers":[
        {
            "category":"Building & Trades",
            "subcategory":"Cleaning & Sanitation",
            "type":"Services"
        }
    ],
    "sg:phone":"+1 559 897 5026",
    "sg:postcode":"93631",
    "sg:province":"CA",
    "sg:tags":[
        "ventilating",
        "system"
    ],
    "sg:website":"www.vikingairandsolar.com",
    "wof:name":"Viking Air",
    "wof:placetype":"venue"
},
  "geometry": {"coordinates":[-119.551766,36.51376],"type":"Point"}
}