{
  "type": "Feature",
  "properties": {
    "addr:full":"3190 S. Bascom Avenue #100 San Jose CA 95124",
    "addr:housenumber":"3190",
    "addr:postcode":"95124",
    "addr:street":"S. Bascom Avenue # 100",
    "iso:country":"US",
    "sg:address":"3190 S. Bascom Avenue #100",
    "sg:city":"San Jose",
    "sg:classifiers":[
        {
            "category":"Banks & Credit Unions",
            "subcategory":"Financial Services",
            "type":"Services"
        }
    ],
    "sg:phone":"+1 408 626 0394",
    "sg:postcode":"95124",
    "sg:province":"CA",
    "sg:tags":[
        "broker",
        "mortgage"
    ],
    "wof:name":"The Hill Team - Cedar Mortgage",
    "wof:placetype":"venue"
},
  "geometry": {"coordinates":[-121.941811,37.265162],"type":"Point"}
}