{
  "type": "Feature",
  "properties": {
    "addr:full":"2312 Branch Creek St Bakersfield CA 93312",
    "addr:housenumber":"2312",
    "addr:postcode":"93312",
    "addr:street":"Branch Creek St",
    "iso:country":"US",
    "sg:address":"2312 Branch Creek St",
    "sg:city":"Bakersfield",
    "sg:classifiers":[
        {
            "category":"Building & Trades",
            "subcategory":"Construction",
            "type":"Services"
        }
    ],
    "sg:phone":"+1 661 588 7195",
    "sg:postcode":"93312",
    "sg:province":"CA",
    "sg:tags":[
        "contractor"
    ],
    "wof:name":"Gary Schallock Construction",
    "wof:placetype":"venue"
},
  "geometry": {"coordinates":[-119.139729,35.37985],"type":"Point"}
}