{
  "type": "Feature",
  "properties": {
    "addr:full":"3918 Mason St San Diego CA 92110",
    "addr:housenumber":"3918",
    "addr:postcode":"92110",
    "addr:street":"Mason St",
    "iso:country":"US",
    "sg:address":"3918 Mason St",
    "sg:city":"San Diego",
    "sg:classifiers":[
        {
            "category":"Bus Charters",
            "type":"Transportation"
        }
    ],
    "sg:phone":"+1 619 435 6310",
    "sg:postcode":"92110",
    "sg:province":"CA",
    "sg:tags":[
        "rental"
    ],
    "wof:name":"Coronado Livery",
    "wof:placetype":"venue"
},
  "geometry": {"coordinates":[-117.197626,32.752971],"type":"Point"}
}