{
  "type": "Feature",
  "properties": {
    "iso:country":"US",
    "sg:address":"16823 Bellflower Blvd.",
    "sg:city":"Bellflower",
    "sg:classifiers":[
        {
            "category":"Home & Garden",
            "subcategory":"Household Appliances",
            "type":"Retail Goods"
        }
    ],
    "sg:phone":"+1 800 626 9610",
    "sg:postcode":"90706",
    "sg:province":"CA",
    "sg:tags":[
        "repair"
    ],
    "wof:name":"Folsom Electric",
    "wof:placetype":"venue"
},
  "geometry": {"coordinates":[-118.125553,33.881374],"type":"Point"}
}