{
  "type": "Feature",
  "properties": {
    "addr:full":"559 Cimarron Dr Chico CA 95973",
    "addr:housenumber":"559",
    "addr:postcode":"95973",
    "addr:street":"Cimarron Dr",
    "iso:country":"US",
    "sg:address":"559 Cimarron Dr",
    "sg:city":"Chico",
    "sg:classifiers":[
        {
            "category":"Professional",
            "subcategory":"Computer Services",
            "type":"Services"
        }
    ],
    "sg:phone":"+1 530 519 1044",
    "sg:postcode":"95973",
    "sg:province":"CA",
    "sg:tags":[
        "website",
        "design"
    ],
    "wof:name":"Vaught Enterprises",
    "wof:placetype":"venue"
},
  "geometry": {"coordinates":[-121.864243,39.772421],"type":"Point"}
}