{
  "type": "Feature",
  "properties": {
    "iso:country":"US",
    "sg:address":"1700 W L St",
    "sg:city":"Wilmington",
    "sg:classifiers":[
        {
            "category":"Sports & Exercise",
            "subcategory":"Golf",
            "type":"Entertainment"
        }
    ],
    "sg:phone":"+1 310 835 3000",
    "sg:postcode":"90744",
    "sg:province":"CA",
    "sg:tags":[
        "range",
        "practice"
    ],
    "wof:name":"Harbor Golf Pro Shop",
    "wof:placetype":"venue"
},
  "geometry": {"coordinates":[-118.28697200000001,33.784981],"type":"Point"}
}