{
  "type": "Feature",
  "properties": {
    "iso:country":"US",
    "sg:address":"1212 Broadway",
    "sg:city":"Oakland",
    "sg:classifiers":[
        {
            "category":"Professional",
            "subcategory":"Lawyer & Legal Services",
            "type":"Services"
        }
    ],
    "sg:phone":"+1 510 839 4235",
    "sg:postcode":"94612",
    "sg:province":"CA",
    "sg:tags":[
        "attorney",
        "bureau"
    ],
    "wof:name":"K W Assoc",
    "wof:placetype":"venue"
},
  "geometry": {"coordinates":[-122.271657,37.803558],"type":"Point"}
}