{
  "type": "Feature",
  "properties": {
    "addr:full":"2018 Pico Blvd Santa Monica CA 90405",
    "addr:housenumber":"2018",
    "addr:postcode":"90405",
    "addr:street":"Pico Blvd",
    "iso:country":"US",
    "sg:address":"2018 Pico Blvd",
    "sg:city":"Santa Monica",
    "sg:classifiers":[
        {
            "category":"Professional",
            "subcategory":"Business Services",
            "type":"Services"
        }
    ],
    "sg:phone":"+1 310 314 1157",
    "sg:postcode":"90405",
    "sg:province":"CA",
    "sg:tags":[
        "notary"
    ],
    "wof:name":"AAAA-Action Income",
    "wof:placetype":"venue"
},
  "geometry": {"coordinates":[-118.469032,34.019561],"type":"Point"}
}