{
  "type": "Feature",
  "properties": {
    "iso:country":"US",
    "sg:address":"21121 Cantebury Ln",
    "sg:city":"Lake Forest",
    "sg:classifiers":[
        {
            "category":"Real Estate",
            "subcategory":"Real Estate Agent",
            "type":"Services"
        }
    ],
    "sg:phone":"+1 949 597 8940",
    "sg:postcode":"92630",
    "sg:province":"CA",
    "sg:tags":[
        "appraiser"
    ],
    "wof:name":"Major Appraisals-Orange County",
    "wof:placetype":"venue"
},
  "geometry": {"coordinates":[-117.660844,33.65733],"type":"Point"}
}