{
  "type": "Feature",
  "properties": {
    "addr:full":"8949 Reseda Blvd Northridge CA 91324",
    "addr:housenumber":"8949",
    "addr:postcode":"91324",
    "addr:street":"Reseda Blvd",
    "iso:country":"US",
    "sg:address":"8949 Reseda Blvd",
    "sg:city":"Northridge",
    "sg:classifiers":[
        {
            "category":"Shopping",
            "subcategory":"Tobacco",
            "type":"Retail Goods"
        }
    ],
    "sg:phone":"+1 818 993 1600",
    "sg:postcode":"91324",
    "sg:province":"CA",
    "sg:tags":[
        "cigarette",
        "cigar",
        "dealer"
    ],
    "wof:name":"Reseda Cigarettes",
    "wof:placetype":"venue"
},
  "geometry": {"coordinates":[-118.53616,34.234611],"type":"Point"}
}