{
  "type": "Feature",
  "properties": {
    "iso:country":"US",
    "sg:address":"708 Middlefield Rd",
    "sg:city":"Salinas",
    "sg:classifiers":[
        {
            "category":"Farming",
            "subcategory":"Livestock Farm",
            "type":"Manufacturing & Wholesale Goods"
        }
    ],
    "sg:phone":"+1 831 443 1425",
    "sg:postcode":"93906",
    "sg:province":"CA",
    "sg:tags":[
        "hog"
    ],
    "wof:name":"Lazy Dayz",
    "wof:placetype":"venue"
},
  "geometry": {"coordinates":[-121.61398699999999,36.757927],"type":"Point"}
}