{
  "type": "Feature",
  "properties": {
    "addr:full":"22555 Mission Blvd Hayward CA 94541",
    "addr:housenumber":"22555",
    "addr:postcode":"94541",
    "addr:street":"Mission Blvd",
    "iso:country":"US",
    "sg:address":"22555 Mission Blvd",
    "sg:city":"Hayward",
    "sg:classifiers":[
        {
            "category":"Food & Beverages",
            "subcategory":"Groceries & Convenience Stores",
            "type":"Retail Goods"
        }
    ],
    "sg:phone":"+1 510 538 7120",
    "sg:postcode":"94541",
    "sg:province":"CA",
    "sg:website":"www.luckysupermarkets.com",
    "wof:name":"Lucky Supermarket",
    "wof:placetype":"venue"
},
  "geometry": {"coordinates":[-122.084423,37.672593],"type":"Point"}
}