{
  "type": "Feature",
  "properties": {
    "iso:country":"US",
    "sg:address":"191 S Oak Park Blvd",
    "sg:city":"Grover Beach",
    "sg:classifiers":[
        {
            "category":"Museum",
            "type":"Entertainment"
        }
    ],
    "sg:phone":"+1 805 481 0374",
    "sg:postcode":"93433",
    "sg:province":"CA",
    "sg:tags":[
        "organization",
        "arts",
        "information"
    ],
    "wof:name":"Arroyo Arts",
    "wof:placetype":"venue"
},
  "geometry": {"coordinates":[-120.609101,35.119947],"type":"Point"}
}