{
  "type": "Feature",
  "properties": {
    "iso:country":"US",
    "sg:address":"322 Jackson Ave",
    "sg:city":"Sunnyvale",
    "sg:classifiers":[
        {
            "category":"Professional",
            "subcategory":"Computer Services",
            "type":"Services"
        }
    ],
    "sg:phone":"+1 408 733 4227",
    "sg:postcode":"94085",
    "sg:province":"CA",
    "sg:tags":[
        "development",
        "software"
    ],
    "wof:name":"Manufacturing Solutions Group",
    "wof:placetype":"venue"
},
  "geometry": {"coordinates":[-122.024228,37.384394],"type":"Point"}
}