{
  "type": "Feature",
  "properties": {
    "iso:country":"US",
    "sg:address":"16005 Main St",
    "sg:city":"Hesperia",
    "sg:classifiers":[
        {
            "category":"Professional",
            "subcategory":"Business Services",
            "type":"Services"
        }
    ],
    "sg:phone":"+1 760 244 0230",
    "sg:postcode":"92345",
    "sg:province":"CA",
    "sg:tags":[
        "liquidator"
    ],
    "wof:name":"High Desert Liquidation",
    "wof:placetype":"venue"
},
  "geometry": {"coordinates":[-117.313402,34.423224],"type":"Point"}
}