{
  "type": "Feature",
  "properties": {
    "iso:country":"US",
    "sg:address":"6478 Westside Rd",
    "sg:city":"Redding",
    "sg:classifiers":[
        {
            "category":"Professional",
            "type":"Services"
        }
    ],
    "sg:phone":"+1 530 242 0227",
    "sg:postcode":"96001",
    "sg:province":"CA",
    "wof:name":"Java Jitters",
    "wof:placetype":"venue"
},
  "geometry": {"coordinates":[-122.382542,40.521672],"type":"Point"}
}