{
  "type": "Feature",
  "properties": {
    "iso:country":"US",
    "sg:address":"32132 Ridge Route Rd",
    "sg:city":"Castaic",
    "sg:classifiers":[
        {
            "category":"Recreation",
            "subcategory":"Boat Charter",
            "type":"Entertainment"
        }
    ],
    "sg:phone":"+1 661 775 6232",
    "sg:postcode":"91384",
    "sg:province":"CA",
    "sg:tags":[
        "boat-rental"
    ],
    "wof:name":"Lake Castaic Marina",
    "wof:placetype":"venue"
},
  "geometry": {"coordinates":[-118.61634599999999,34.501271],"type":"Point"}
}