{
  "type": "Feature",
  "properties": {
    "addr:full":"29008 Agoura Rd Agoura Hills CA 91301",
    "addr:housenumber":"29008",
    "addr:postcode":"91301",
    "addr:street":"Agoura Rd",
    "iso:country":"US",
    "sg:address":"29008 Agoura Rd",
    "sg:city":"Agoura Hills",
    "sg:classifiers":[
        {
            "category":"Bars & Pubs",
            "subcategory":"Lounge",
            "type":"Food & Drink"
        },
        {
            "category":"Restaurant",
            "type":"Food & Drink"
        }
    ],
    "sg:phone":"+1 818 865 3700",
    "sg:postcode":"91301",
    "sg:province":"CA",
    "sg:tags":[
        "italian"
    ],
    "sg:website":"padrirestaurant.net",
    "wof:name":"Padri Italian Cuisine & Martini Bar",
    "wof:placetype":"venue"
},
  "geometry": {"coordinates":[-118.758003,34.1436],"type":"Point"}
}