{
  "type": "Feature",
  "properties": {
    "addr:full":"1096 N Western Ave Los Angeles CA 90029",
    "addr:housenumber":"1096",
    "addr:postcode":"90029",
    "addr:street":"N Western Ave",
    "iso:country":"US",
    "sg:address":"1096 N Western Ave",
    "sg:city":"Los Angeles",
    "sg:classifiers":[
        {
            "category":"Building & Trades",
            "subcategory":"Construction",
            "type":"Services"
        }
    ],
    "sg:phone":"+1 323 735 9006",
    "sg:postcode":"90029",
    "sg:province":"CA",
    "sg:tags":[
        "painter"
    ],
    "wof:name":"United Maintenance & Painting",
    "wof:placetype":"venue"
},
  "geometry": {"coordinates":[-118.309096,34.089575],"type":"Point"}
}