{
  "type": "Feature",
  "properties": {
    "iso:country":"US",
    "sg:address":"4455 W 136th St",
    "sg:city":"Hawthorne",
    "sg:classifiers":[
        {
            "category":"Government",
            "subcategory":"Office",
            "type":"Public Place"
        }
    ],
    "sg:phone":"+1 310 970 7203",
    "sg:postcode":"90250",
    "sg:province":"CA",
    "sg:tags":[
        "executive"
    ],
    "wof:name":"Licensing & Code Enforcement",
    "wof:placetype":"venue"
},
  "geometry": {"coordinates":[-118.35413699999999,33.909005],"type":"Point"}
}