{
  "type": "Feature",
  "properties": {
    "iso:country":"US",
    "sg:address":"4480 Chapparal Dr",
    "sg:city":"Placerville",
    "sg:classifiers":[
        {
            "category":"Building & Trades",
            "subcategory":"Electrical",
            "type":"Services"
        }
    ],
    "sg:phone":"+1 530 621 1013",
    "sg:postcode":"95667",
    "sg:province":"CA",
    "sg:tags":[
        "electrical",
        "contractor"
    ],
    "wof:name":"King & Sons Electrical",
    "wof:placetype":"venue"
},
  "geometry": {"coordinates":[-120.721012,38.694735],"type":"Point"}
}