{
  "type": "Feature",
  "properties": {
    "addr:full":"4701 San Leandro St Oakland CA 94601",
    "addr:housenumber":"4701",
    "addr:postcode":"94601",
    "addr:street":"San Leandro St",
    "iso:country":"US",
    "sg:address":"4701 San Leandro St",
    "sg:city":"Oakland",
    "sg:classifiers":[
        {
            "category":"Manufacturing",
            "subcategory":"Textiles",
            "type":"Manufacturing & Wholesale Goods"
        }
    ],
    "sg:phone":"+1 510 532 9089",
    "sg:postcode":"94601",
    "sg:province":"CA",
    "sg:tags":[
        "plant",
        "silk",
        "finishing",
        "fiber"
    ],
    "wof:name":"Hanger Nineteen Silkscree",
    "wof:placetype":"venue"
},
  "geometry": {"coordinates":[-122.21293799999999,37.767053],"type":"Point"}
}