{
  "type": "Feature",
  "properties": {
    "iso:country":"US",
    "sg:address":"6784 El Cajon Blvd Ste J",
    "sg:city":"San Diego",
    "sg:classifiers":[
        {
            "category":"Restaurant",
            "type":"Food & Drink"
        }
    ],
    "sg:phone":"+1 619 463 2222",
    "sg:postcode":"92115",
    "sg:province":"CA",
    "sg:tags":[
        "pizza"
    ],
    "wof:name":"Grandstand Pizza",
    "wof:placetype":"venue"
},
  "geometry": {"coordinates":[-117.052002,32.7687],"type":"Point"}
}