{
  "type": "Feature",
  "properties": {
    "addr:full":"385 W Shaw Ave 322 Fresno CA 93704",
    "addr:housenumber":"385;322",
    "addr:postcode":"93704",
    "addr:street":"W Shaw Ave",
    "iso:country":"US",
    "sg:address":"385 W Shaw Ave 322",
    "sg:city":"Fresno",
    "sg:classifiers":[
        {
            "category":"Professional",
            "subcategory":"Computer Services",
            "type":"Services"
        }
    ],
    "sg:phone":"+1 559 224 2132",
    "sg:postcode":"93704",
    "sg:province":"CA",
    "sg:tags":[
        "publisher",
        "developer",
        "software"
    ],
    "wof:name":"Felix Graphix",
    "wof:placetype":"venue"
},
  "geometry": {"coordinates":[-119.799122,36.808392],"type":"Point"}
}