{
  "type": "Feature",
  "properties": {
    "addr:full":"9670 Aero Dr San Diego CA 92123",
    "addr:housenumber":"9670",
    "addr:postcode":"92123",
    "addr:street":"Aero Dr",
    "iso:country":"US",
    "sg:address":"9670 Aero Dr",
    "sg:city":"San Diego",
    "sg:classifiers":[
        {
            "category":"Professional",
            "subcategory":"Management & Consulting",
            "type":"Services"
        }
    ],
    "sg:phone":"+1 858 569 8451",
    "sg:postcode":"92123",
    "sg:province":"CA",
    "sg:tags":[
        "business"
    ],
    "wof:name":"All Mobile Video Inc",
    "wof:placetype":"venue"
},
  "geometry": {"coordinates":[-117.120864,32.808392],"type":"Point"}
}