{
  "type": "Feature",
  "properties": {
    "addr:full":"328 N Rodeo Dr Beverly Hills CA 90210",
    "addr:housenumber":"328",
    "addr:postcode":"90210",
    "addr:street":"N Rodeo Dr",
    "iso:country":"US",
    "sg:address":"328 N Rodeo Dr",
    "sg:city":"Beverly Hills",
    "sg:classifiers":[
        {
            "category":"Shopping",
            "subcategory":"Clothing, Apparel, & Fashions",
            "type":"Retail Goods"
        }
    ],
    "sg:phone":"+1 310 550 7220",
    "sg:postcode":"90210",
    "sg:province":"CA",
    "sg:tags":[
        "item",
        "boutique"
    ],
    "wof:name":"Chopard Boutique",
    "wof:placetype":"venue"
},
  "geometry": {"coordinates":[-118.402055,34.06833],"type":"Point"}
}