{
  "type": "Feature",
  "properties": {
    "iso:country":"US",
    "sg:address":"1005 H St",
    "sg:city":"Bakersfield",
    "sg:classifiers":[
        {
            "category":"Professional",
            "subcategory":"Lawyer & Legal Services",
            "type":"Services"
        }
    ],
    "sg:phone":"+1 661 322 1600",
    "sg:postcode":"93304",
    "sg:province":"CA",
    "sg:tags":[
        "divorce",
        "attorney",
        "practice",
        "family",
        "law"
    ],
    "wof:name":"Carl Hart Jr Attorney",
    "wof:placetype":"venue"
},
  "geometry": {"coordinates":[-119.02124000000001,35.366723],"type":"Point"}
}