{
  "type": "Feature",
  "properties": {
    "addr:full":"571 Arch Street San Francisco CA 94101",
    "addr:housenumber":"571",
    "addr:postcode":"94101",
    "addr:street":"Arch Street",
    "iso:country":"US",
    "sg:address":"571 Arch Street",
    "sg:city":"San Francisco",
    "sg:classifiers":[
        {
            "category":"Building & Trades",
            "subcategory":"Electrical",
            "type":"Services"
        }
    ],
    "sg:phone":"+1 415 584 0351",
    "sg:postcode":"94101",
    "sg:province":"CA",
    "sg:tags":[
        "electrician"
    ],
    "wof:name":"Terrell Electrical Service",
    "wof:placetype":"venue"
},
  "geometry": {"coordinates":[-122.46700300000001,37.7211],"type":"Point"}
}