{
  "type": "Feature",
  "properties": {
    "addr:full":"2270 W Lincoln Ave # 8 Anaheim CA 92801",
    "addr:housenumber":"2270",
    "addr:postcode":"92801",
    "addr:street":"W Lincoln Ave # 8",
    "iso:country":"US",
    "sg:address":"2270 W Lincoln Ave # 8",
    "sg:city":"Anaheim",
    "sg:classifiers":[
        {
            "category":"Health Services",
            "subcategory":"Dentist",
            "type":"Services"
        }
    ],
    "sg:phone":"+1 714 409 3485",
    "sg:postcode":"92801",
    "sg:province":"CA",
    "wof:name":"KING DENTAL PRACTICE",
    "wof:placetype":"venue"
},
  "geometry": {"coordinates":[-117.96244,33.832262],"type":"Point"}
}