{
  "type": "Feature",
  "properties": {
    "iso:country":"US",
    "sg:address":"5420 N Figueroa St",
    "sg:city":"Los Angeles",
    "sg:classifiers":[
        {
            "category":"Health Services",
            "subcategory":"Hospital",
            "type":"Services"
        },
        {
            "category":"Health Services",
            "subcategory":"Clinic",
            "type":"Services"
        }
    ],
    "sg:phone":"+1 323 999 2404",
    "sg:postcode":"90042",
    "sg:province":"CA",
    "sg:tags":[
        "mental",
        "outpatient",
        "specialty"
    ],
    "wof:name":"Starview Community Services",
    "wof:placetype":"venue"
},
  "geometry": {"coordinates":[-118.19695,34.107445],"type":"Point"}
}