{
  "type": "Feature",
  "properties": {
    "addr:full":"1165 S De Anza Blvd Ste #A San Jose CA 95129",
    "addr:housenumber":"1165",
    "addr:postcode":"95129",
    "addr:street":"S De Anza Blvd Ste # A",
    "iso:country":"US",
    "sg:address":"1165 S De Anza Blvd Ste #A",
    "sg:city":"San Jose",
    "sg:classifiers":[
        {
            "category":"Health Services",
            "subcategory":"Chiropractor",
            "type":"Services"
        }
    ],
    "sg:phone":"+1 408 873 7154",
    "sg:postcode":"95129",
    "sg:province":"CA",
    "sg:website":"www.jenkinschiro.com",
    "wof:name":"Jenkins Family and Sports Chiropractic",
    "wof:placetype":"venue"
},
  "geometry": {"coordinates":[-122.03232800000001,37.304346],"type":"Point"}
}