{
  "type": "Feature",
  "properties": {
    "addr:full":"285 E Mill St San Bernardino CA 92408",
    "addr:housenumber":"285",
    "addr:postcode":"92408",
    "addr:street":"E Mill St",
    "iso:country":"US",
    "sg:address":"285 E Mill St",
    "sg:city":"San Bernardino",
    "sg:classifiers":[
        {
            "category":"Home & Garden",
            "subcategory":"Building Materials",
            "type":"Retail Goods"
        }
    ],
    "sg:phone":"+1 909 890 9250",
    "sg:postcode":"92408",
    "sg:province":"CA",
    "sg:tags":[
        "shutter"
    ],
    "wof:name":"Exclusive Shutters",
    "wof:placetype":"venue"
},
  "geometry": {"coordinates":[-117.28013900000001,34.092081],"type":"Point"}
}