{
  "type": "Feature",
  "properties": {
    "iso:country":"US",
    "sg:address":"8502 E Chapman Ave",
    "sg:city":"Orange",
    "sg:classifiers":[
        {
            "category":"Utilities",
            "subcategory":"Telephone",
            "type":"Services"
        }
    ],
    "sg:phone":"+1 714 744 1929",
    "sg:postcode":"92869",
    "sg:province":"CA",
    "sg:tags":[
        "communications"
    ],
    "wof:name":"Rome International",
    "wof:placetype":"venue"
},
  "geometry": {"coordinates":[-117.786206,33.792155],"type":"Point"}
}