{
  "type": "Feature",
  "properties": {
    "addr:full":"1933 E Bayshore Rd Redwood City CA 94063",
    "addr:housenumber":"1933",
    "addr:postcode":"94063",
    "addr:street":"E Bayshore Rd",
    "iso:country":"US",
    "sg:address":"1933 E Bayshore Rd",
    "sg:city":"Redwood City",
    "sg:classifiers":[
        {
            "category":"Building & Trades",
            "subcategory":"Landscaping Services",
            "type":"Services"
        }
    ],
    "sg:phone":"+1 650 367 0102",
    "sg:postcode":"94063",
    "sg:province":"CA",
    "sg:tags":[
        "tree"
    ],
    "wof:name":"Quality Tree Svc",
    "wof:placetype":"venue"
},
  "geometry": {"coordinates":[-122.207932,37.488297],"type":"Point"}
}