{
  "type": "Feature",
  "properties": {
    "addr:full":"4718 Engle Rd Carmichael CA 95608",
    "addr:housenumber":"4718",
    "addr:postcode":"95608",
    "addr:street":"Engle Rd",
    "iso:country":"US",
    "sg:address":"4718 Engle Rd",
    "sg:city":"Carmichael",
    "sg:classifiers":[
        {
            "category":"Health Services",
            "subcategory":"Doctor",
            "type":"Services"
        }
    ],
    "sg:phone":"+1 916 486 0612",
    "sg:postcode":"95608",
    "sg:province":"CA",
    "wof:name":"Nazeri Bahman Md",
    "wof:placetype":"venue"
},
  "geometry": {"coordinates":[-121.354641,38.631832],"type":"Point"}
}