{
  "type": "Feature",
  "properties": {
    "addr:full":"7344 Magnolia Ave Riverside CA 92504",
    "addr:housenumber":"7344",
    "addr:postcode":"92504",
    "addr:street":"Magnolia Ave",
    "iso:country":"US",
    "sg:address":"7344 Magnolia Ave",
    "sg:city":"Riverside",
    "sg:classifiers":[
        {
            "category":"Insurance",
            "subcategory":"Title Insurance",
            "type":"Services"
        }
    ],
    "sg:phone":"+1 951 353 8189",
    "sg:postcode":"92504",
    "sg:province":"CA",
    "wof:name":"Fidelity National Financial",
    "wof:placetype":"venue"
},
  "geometry": {"coordinates":[-117.40695599999999,33.942795],"type":"Point"}
}