{
  "type": "Feature",
  "properties": {
    "addr:full":"13200 Brooks Dr Baldwin Park CA 91706",
    "addr:housenumber":"13200",
    "addr:postcode":"91706",
    "addr:street":"Brooks Dr",
    "iso:country":"US",
    "sg:address":"13200 Brooks Dr",
    "sg:city":"Baldwin Park",
    "sg:classifiers":[
        {
            "category":"Autos & Motor Vehicles",
            "subcategory":"Automobile Sales",
            "type":"Retail Goods"
        }
    ],
    "sg:phone":"+1 626 856 5790",
    "sg:postcode":"91706",
    "sg:province":"CA",
    "sg:tags":[
        "equipment",
        "aircraft",
        "parts",
        "supply"
    ],
    "wof:name":"Avia Source Inc",
    "wof:placetype":"venue"
},
  "geometry": {"coordinates":[-117.98308299999999,34.098347],"type":"Point"}
}