{
  "type": "Feature",
  "properties": {
    "addr:full":"1415 Oklahoma Ave Escalon CA 95320",
    "addr:housenumber":"1415",
    "addr:postcode":"95320",
    "addr:street":"Oklahoma Ave",
    "iso:country":"US",
    "sg:address":"1415 Oklahoma Ave",
    "sg:city":"Escalon",
    "sg:classifiers":[
        {
            "category":"Health Services",
            "subcategory":"Doctor",
            "type":"Services"
        }
    ],
    "sg:phone":"+1 209 838 3522",
    "sg:postcode":"95320",
    "sg:province":"CA",
    "sg:tags":[
        "dentist"
    ],
    "wof:name":"Gary M Verigan Inc",
    "wof:placetype":"venue"
},
  "geometry": {"coordinates":[-121.001257,37.796697],"type":"Point"}
}