{
  "type": "Feature",
  "properties": {
    "iso:country":"US",
    "sg:address":"7220 Woodman Ave Ste 203",
    "sg:city":"Van Nuys",
    "sg:classifiers":[
        {
            "category":"Education",
            "subcategory":"Special Training",
            "type":"Public Place"
        }
    ],
    "sg:phone":"+1 818 994 5724",
    "sg:postcode":"91405",
    "sg:province":"CA",
    "sg:tags":[
        "tutoring"
    ],
    "wof:name":"Kumon Van Nuys-Panorama City Math and Reading Ctr",
    "wof:placetype":"venue"
},
  "geometry": {"coordinates":[-118.431,34.201599],"type":"Point"}
}