{
  "type": "Feature",
  "properties": {
    "iso:country":"US",
    "sg:address":"1632 Canal St",
    "sg:city":"Merced",
    "sg:classifiers":[
        {
            "category":"Banks & Credit Unions",
            "subcategory":"Bank",
            "type":"Services"
        }
    ],
    "sg:phone":"+1 209 384 1242",
    "sg:postcode":"95340",
    "sg:province":"CA",
    "sg:tags":[
        "loan",
        "real estate"
    ],
    "wof:name":"First Metropolitan Mortgage",
    "wof:placetype":"venue"
},
  "geometry": {"coordinates":[-120.483692,37.300718],"type":"Point"}
}