{
  "type": "Feature",
  "properties": {
    "iso:country":"US",
    "sg:address":"540 E Nees Ave Ofc",
    "sg:city":"Fresno",
    "sg:classifiers":[
        {
            "category":"Real Estate",
            "subcategory":"Real Estate Operator",
            "type":"Services"
        }
    ],
    "sg:phone":"+1 559 431 4146",
    "sg:postcode":"93720",
    "sg:province":"CA",
    "sg:tags":[
        "apartment"
    ],
    "sg:website":"http://www.trailsapts.com",
    "wof:name":"Willow Creek",
    "wof:placetype":"venue"
},
  "geometry": {"coordinates":[-119.77592199999999,36.852009],"type":"Point"}
}