{
  "type": "Feature",
  "properties": {
    "iso:country":"US",
    "sg:address":"1081 The Alameda",
    "sg:city":"San Jose",
    "sg:classifiers":[
        {
            "category":"Bakery",
            "type":"Food & Drink"
        }
    ],
    "sg:phone":"+1 408 287 4191",
    "sg:postcode":"95126",
    "sg:province":"CA",
    "sg:website":"www.greenleesbakerysj.com",
    "wof:name":"Greenlee's Bakery",
    "wof:placetype":"venue"
},
  "geometry": {"coordinates":[-121.910004,37.331501],"type":"Point"}
}