{
  "type": "Feature",
  "properties": {
    "addr:full":"14372 Harrington St Garden Grove CA 92843",
    "addr:housenumber":"14372",
    "addr:postcode":"92843",
    "addr:street":"Harrington St",
    "iso:country":"US",
    "sg:address":"14372 Harrington St",
    "sg:city":"Garden Grove",
    "sg:classifiers":[
        {
            "category":"Shopping",
            "subcategory":"Florist",
            "type":"Retail Goods"
        }
    ],
    "sg:phone":"+1 714 775 1067",
    "sg:postcode":"92843",
    "sg:province":"CA",
    "wof:name":"Sophies Silk Flowers",
    "wof:placetype":"venue"
},
  "geometry": {"coordinates":[-117.951779,33.753669],"type":"Point"}
}