{
  "type": "Feature",
  "properties": {
    "iso:country":"US",
    "sg:address":"32 Sheridan St",
    "sg:city":"San Francisco",
    "sg:classifiers":[
        {
            "category":"Building & Trades",
            "subcategory":"Construction",
            "type":"Services"
        }
    ],
    "sg:phone":"+1 415 552 6333",
    "sg:postcode":"94103",
    "sg:province":"CA",
    "sg:tags":[
        "painting",
        "contractor"
    ],
    "wof:name":"Southside Painting",
    "wof:placetype":"venue"
},
  "geometry": {"coordinates":[-122.411652,37.772424],"type":"Point"}
}