{
  "type": "Feature",
  "properties": {
    "iso:country":"US",
    "sg:address":"13085 Kerry St.",
    "sg:city":"Garden Grove",
    "sg:classifiers":[
        {
            "category":"Bars & Pubs",
            "subcategory":"Lounge",
            "type":"Food & Drink"
        }
    ],
    "sg:phone":"+1 714 530 0109",
    "sg:postcode":"92844",
    "sg:province":"CA",
    "sg:tags":[
        "karaoke"
    ],
    "wof:name":"GG Karaoke Studio",
    "wof:placetype":"venue"
},
  "geometry": {"coordinates":[-117.959247,33.773008],"type":"Point"}
}