{
  "type": "Feature",
  "properties": {
    "addr:full":"930 Bethany Rd Burbank CA 91504",
    "addr:housenumber":"930",
    "addr:postcode":"91504",
    "addr:street":"Bethany Rd",
    "iso:country":"US",
    "sg:address":"930 Bethany Rd",
    "sg:city":"Burbank",
    "sg:classifiers":[
        {
            "category":"Professional",
            "type":"Services"
        }
    ],
    "sg:phone":"+1 818 842 5808",
    "sg:postcode":"91504",
    "sg:province":"CA",
    "wof:name":"Webcartoons LLC",
    "wof:placetype":"venue"
},
  "geometry": {"coordinates":[-118.31172599999999,34.1968],"type":"Point"}
}