{
  "type": "Feature",
  "properties": {
    "iso:country":"US",
    "sg:address":"11730 Creek Bluff Dr",
    "sg:city":"Poway",
    "sg:classifiers":[
        {
            "category":"Professional",
            "subcategory":"Management & Consulting",
            "type":"Services"
        }
    ],
    "sg:phone":"+1 858 689 9744",
    "sg:postcode":"92064",
    "sg:province":"CA",
    "sg:tags":[
        "construction"
    ],
    "wof:name":"CDM Miller Inc",
    "wof:placetype":"venue"
},
  "geometry": {"coordinates":[-117.063187,32.929903],"type":"Point"}
}