{
  "type": "Feature",
  "properties": {
    "addr:full":"732 Woodside Rd Redwood City CA 94061",
    "addr:housenumber":"732",
    "addr:postcode":"94061",
    "addr:street":"Woodside Rd",
    "iso:country":"US",
    "sg:address":"732 Woodside Rd",
    "sg:city":"Redwood City",
    "sg:classifiers":[
        {
            "category":"Retail",
            "subcategory":"Laundry & Dry Cleaning",
            "type":"Services"
        }
    ],
    "sg:phone":"+1 650 364 2119",
    "sg:postcode":"94061",
    "sg:province":"CA",
    "sg:tags":[
        "cleaners"
    ],
    "wof:name":"Woodside Cleaners",
    "wof:placetype":"venue"
},
  "geometry": {"coordinates":[-122.22403799999999,37.467384],"type":"Point"}
}