{
  "type": "Feature",
  "properties": {
    "iso:country":"US",
    "sg:address":"265 W Harrison Ave",
    "sg:city":"Ventura",
    "sg:classifiers":[
        {
            "category":"Shopping",
            "subcategory":"Bicycles & Sporting Goods",
            "type":"Retail Goods"
        }
    ],
    "sg:phone":"+1 805 643 3263",
    "sg:postcode":"93001",
    "sg:province":"CA",
    "sg:tags":[
        "equipment",
        "diver",
        "supply"
    ],
    "wof:name":"Deep Thought Diving Products",
    "wof:placetype":"venue"
},
  "geometry": {"coordinates":[-119.304444,34.287133],"type":"Point"}
}