{
  "type": "Feature",
  "properties": {
    "addr:full":"1825 Marguerite St Dos Palos CA 93620",
    "addr:housenumber":"1825",
    "addr:postcode":"93620",
    "addr:street":"Marguerite St",
    "iso:country":"US",
    "sg:address":"1825 Marguerite St",
    "sg:city":"Dos Palos",
    "sg:classifiers":[
        {
            "category":"Personal",
            "subcategory":"Beauty Salon",
            "type":"Services"
        }
    ],
    "sg:phone":"+1 209 392 6700",
    "sg:postcode":"93620",
    "sg:province":"CA",
    "wof:name":"Shear Delight",
    "wof:placetype":"venue"
},
  "geometry": {"coordinates":[-120.62636500000001,36.986633],"type":"Point"}
}