{
  "type": "Feature",
  "properties": {
    "iso:country":"US",
    "sg:address":"1106 N Chester Ave",
    "sg:city":"Inglewood",
    "sg:classifiers":[
        {
            "category":"Building & Trades",
            "subcategory":"Construction",
            "type":"Services"
        }
    ],
    "sg:phone":"+1 310 592 1063",
    "sg:postcode":"90302",
    "sg:province":"CA",
    "sg:tags":[
        "wallcoverings-installation",
        "wallpaper",
        "painting",
        "contractor"
    ],
    "wof:name":"Painting Golore",
    "wof:placetype":"venue"
},
  "geometry": {"coordinates":[-118.343312,33.977999],"type":"Point"}
}