{
  "type": "Feature",
  "properties": {
    "iso:country":"US",
    "sg:address":"550 W Olive Ave",
    "sg:city":"Merced",
    "sg:classifiers":[
        {
            "category":"Banks & Credit Unions",
            "subcategory":"Bank",
            "type":"Services"
        }
    ],
    "sg:phone":"+1 209 726 8073",
    "sg:postcode":"95348",
    "sg:province":"CA",
    "sg:tags":[
        "cashing",
        "check"
    ],
    "wof:name":"Money Mart",
    "wof:placetype":"venue"
},
  "geometry": {"coordinates":[-120.47736999999999,37.319212],"type":"Point"}
}