{
  "type": "Feature",
  "properties": {
    "iso:country":"US",
    "sg:address":"121 S Crescent Dr",
    "sg:city":"Beverly Hills",
    "sg:classifiers":[
        {
            "category":"Professional",
            "type":"Services"
        }
    ],
    "sg:phone":"+1 310 281 0908",
    "sg:postcode":"90212",
    "sg:province":"CA",
    "wof:name":"Paloma 101 Films Inc",
    "wof:placetype":"venue"
},
  "geometry": {"coordinates":[-118.395998,34.066894],"type":"Point"}
}