{
  "type": "Feature",
  "properties": {
    "iso:country":"US",
    "sg:address":"805 E Broadway",
    "sg:city":"Glendale",
    "sg:classifiers":[
        {
            "category":"Personal",
            "subcategory":"Hair Removal",
            "type":"Services"
        }
    ],
    "sg:phone":"+1 818 500 8090",
    "sg:postcode":"91205",
    "sg:province":"CA",
    "sg:tags":[
        "laser"
    ],
    "wof:name":"Mi Beauty",
    "wof:placetype":"venue"
},
  "geometry": {"coordinates":[-118.245414,34.14645],"type":"Point"}
}