{
  "type": "Feature",
  "properties": {
    "addr:full":"1409 el Dorado Ct Concord CA 94518",
    "addr:housenumber":"1409",
    "addr:postcode":"94518",
    "addr:street":"El Dorado Ct",
    "iso:country":"US",
    "sg:address":"1409 el Dorado Ct",
    "sg:city":"Concord",
    "sg:classifiers":[
        {
            "category":"Organizations",
            "subcategory":"Community Association",
            "type":"Services"
        }
    ],
    "sg:phone":"+1 925 676 9092",
    "sg:postcode":"94518",
    "sg:province":"CA",
    "sg:tags":[
        "fraternal"
    ],
    "wof:name":"Lions Clubs Of Walnut Creek",
    "wof:placetype":"venue"
},
  "geometry": {"coordinates":[-122.009756,37.967277],"type":"Point"}
}