{
  "type": "Feature",
  "properties": {
    "iso:country":"US",
    "sg:address":"6043 Norwood Ave",
    "sg:city":"Riverside",
    "sg:classifiers":[
        {
            "category":"Building & Trades",
            "subcategory":"Landscaping Services",
            "type":"Services"
        }
    ],
    "sg:phone":"+1 951 785 4818",
    "sg:postcode":"92505",
    "sg:province":"CA",
    "sg:tags":[
        "landscape"
    ],
    "wof:name":"Evergreen Land Maintenance",
    "wof:placetype":"venue"
},
  "geometry": {"coordinates":[-117.486458,33.944027],"type":"Point"}
}