{
  "type": "Feature",
  "properties": {
    "addr:full":"5554 W 142nd Pl Hawthorne CA 90250",
    "addr:housenumber":"5554",
    "addr:postcode":"90250",
    "addr:street":"W 142Nd Pl",
    "iso:country":"US",
    "sg:address":"5554 W 142nd Pl",
    "sg:city":"Hawthorne",
    "sg:classifiers":[
        {
            "category":"Professional",
            "type":"Services"
        }
    ],
    "sg:phone":"+1 310 643 6997",
    "sg:postcode":"90250",
    "sg:province":"CA",
    "wof:name":"Eaglevision Housing Dev Inc",
    "wof:placetype":"venue"
},
  "geometry": {"coordinates":[-118.377782,33.902363],"type":"Point"}
}