{
  "type": "Feature",
  "properties": {
    "iso:country":"US",
    "sg:address":"681 US Hwy 101",
    "sg:city":"Crescent City",
    "sg:classifiers":[
        {
            "category":"Travel",
            "subcategory":"Hotels & Motels",
            "type":"Entertainment"
        }
    ],
    "sg:phone":"+1 707 464 3993",
    "sg:postcode":"95531",
    "sg:province":"CA",
    "wof:name":"Lighthouse Inn",
    "wof:placetype":"venue"
},
  "geometry": {"coordinates":[-124.195475,41.756749],"type":"Point"}
}