{
  "type": "Feature",
  "properties": {
    "addr:full":"160 N Glendora Ave Glendora CA 91741",
    "addr:housenumber":"160",
    "addr:postcode":"91741",
    "addr:street":"N Glendora Ave",
    "iso:country":"US",
    "sg:address":"160 N Glendora Ave",
    "sg:city":"Glendora",
    "sg:classifiers":[
        {
            "category":"Education",
            "subcategory":"Special Training",
            "type":"Public Place"
        }
    ],
    "sg:phone":"+1 626 857 0708",
    "sg:postcode":"91741",
    "sg:province":"CA",
    "sg:tags":[
        "school",
        "instruction",
        "art"
    ],
    "wof:name":"Kidsart",
    "wof:placetype":"venue"
},
  "geometry": {"coordinates":[-117.865336,34.137553],"type":"Point"}
}