{
  "type": "Feature",
  "properties": {
    "addr:full":"1840 Mentone Blvd Mentone CA 92359",
    "addr:housenumber":"1840",
    "addr:postcode":"92359",
    "addr:street":"Mentone Blvd",
    "iso:country":"US",
    "sg:address":"1840 Mentone Blvd",
    "sg:city":"Mentone",
    "sg:classifiers":[
        {
            "category":"Food & Beverages",
            "subcategory":"Liquor & Beverages",
            "type":"Retail Goods"
        }
    ],
    "sg:phone":"+1 909 794 6046",
    "sg:postcode":"92359",
    "sg:province":"CA",
    "sg:tags":[
        "beer",
        "spirit",
        "wine"
    ],
    "wof:name":"Mentone Beach Liquor",
    "wof:placetype":"venue"
},
  "geometry": {"coordinates":[-117.133003,34.069901],"type":"Point"}
}