{
  "type": "Feature",
  "properties": {
    "iso:country":"US",
    "sg:address":"10600 Shoemaker Ave",
    "sg:city":"Santa Fe Springs",
    "sg:classifiers":[
        {
            "category":"Wholesale",
            "subcategory":"Machinery & Supplies",
            "type":"Manufacturing & Wholesale Goods"
        }
    ],
    "sg:phone":"+1 562 903 1224",
    "sg:postcode":"90670",
    "sg:province":"CA",
    "sg:tags":[
        "bearing"
    ],
    "wof:name":"Bearings Limited",
    "wof:placetype":"venue"
},
  "geometry": {"coordinates":[-118.055134,33.93708],"type":"Point"}
}