{
  "type": "Feature",
  "properties": {
    "iso:country":"US",
    "sg:address":"1909 Hackett Avenue",
    "sg:city":"Mountain View",
    "sg:classifiers":[
        {
            "category":"Real Estate",
            "subcategory":"Real Estate Operator",
            "type":"Services"
        }
    ],
    "sg:phone":"+1 650 965 9222",
    "sg:postcode":"94043",
    "sg:province":"CA",
    "sg:tags":[
        "apartment"
    ],
    "wof:name":"Sierra Vista",
    "wof:placetype":"venue"
},
  "geometry": {"coordinates":[-122.090267,37.403024],"type":"Point"}
}