{
  "type": "Feature",
  "properties": {
    "addr:full":"1659 Scott Blvd Santa Clara CA 95050",
    "addr:housenumber":"1659",
    "addr:postcode":"95050",
    "addr:street":"Scott Blvd",
    "iso:country":"US",
    "sg:address":"1659 Scott Blvd",
    "sg:city":"Santa Clara",
    "sg:classifiers":[
        {
            "category":"Building & Trades",
            "subcategory":"Construction",
            "type":"Services"
        }
    ],
    "sg:phone":"+1 408 247 6034",
    "sg:postcode":"95050",
    "sg:province":"CA",
    "sg:tags":[
        "general",
        "contractor"
    ],
    "wof:name":"Level One Construction",
    "wof:placetype":"venue"
},
  "geometry": {"coordinates":[-121.959362,37.354113],"type":"Point"}
}