{
  "type": "Feature",
  "properties": {
    "addr:full":"2877 Schnell School Rd Placerville CA 95667",
    "addr:housenumber":"2877",
    "addr:postcode":"95667",
    "addr:street":"School Rd",
    "iso:country":"US",
    "sg:address":"2877 Schnell School Rd",
    "sg:city":"Placerville",
    "sg:classifiers":[
        {
            "category":"Government",
            "subcategory":"Office",
            "type":"Public Place"
        }
    ],
    "sg:phone":"+1 530 626 7636",
    "sg:postcode":"95667",
    "sg:province":"CA",
    "sg:tags":[
        "bus",
        "school",
        "general"
    ],
    "wof:name":"Transportation Dept",
    "wof:placetype":"venue"
},
  "geometry": {"coordinates":[-120.779341,38.735711],"type":"Point"}
}