{
  "type": "Feature",
  "properties": {
    "addr:full":"712 El Cerrito Plaza El Cerrito CA 94530",
    "addr:housenumber":"712",
    "addr:postcode":"94530",
    "addr:street":"El Cerrito Plaza",
    "iso:country":"US",
    "sg:address":"712 El Cerrito Plaza",
    "sg:city":"El Cerrito",
    "sg:classifiers":[
        {
            "category":"Communications",
            "type":"Services"
        }
    ],
    "sg:phone":"+1 510 558 1534",
    "sg:postcode":"94530",
    "sg:province":"CA",
    "sg:tags":[
        "web",
        "design"
    ],
    "sg:website":"www.pagepoint.com",
    "wof:name":"PagePoint Web Solutions",
    "wof:placetype":"venue"
},
  "geometry": {"coordinates":[-122.299756,37.899737],"type":"Point"}
}