{
  "type": "Feature",
  "properties": {
    "addr:full":"329 7th St Marysville CA 95901",
    "addr:housenumber":"329",
    "addr:postcode":"95901",
    "addr:street":"7Th St",
    "iso:country":"US",
    "sg:address":"329 7th St",
    "sg:city":"Marysville",
    "sg:classifiers":[
        {
            "category":"Professional",
            "subcategory":"Accounting & Tax Preparation",
            "type":"Services"
        }
    ],
    "sg:phone":"+1 530 742 3241",
    "sg:postcode":"95901",
    "sg:province":"CA",
    "sg:tags":[
        "accountant",
        "public",
        "accountants-certified"
    ],
    "wof:name":"Nichols Accountancy Corporation",
    "wof:placetype":"venue"
},
  "geometry": {"coordinates":[-121.588635,39.142601],"type":"Point"}
}