{
  "type": "Feature",
  "properties": {
    "iso:country":"US",
    "sg:address":"452 Olive Dr",
    "sg:city":"Vista",
    "sg:classifiers":[
        {
            "category":"Autos & Motor Vehicles",
            "subcategory":"Auto Supplies",
            "type":"Retail Goods"
        }
    ],
    "sg:phone":"+1 760 724 0938",
    "sg:postcode":"92083",
    "sg:province":"CA",
    "sg:tags":[
        "automobile",
        "parts"
    ],
    "wof:name":"Bowes Automotive Products",
    "wof:placetype":"venue"
},
  "geometry": {"coordinates":[-117.254199,33.204619],"type":"Point"}
}