{
  "type": "Feature",
  "properties": {
    "addr:full":"24815 Ponderosa Dr Idyllwild CA 92549",
    "addr:housenumber":"24815",
    "addr:postcode":"92549",
    "addr:street":"Ponderosa Dr",
    "iso:country":"US",
    "sg:address":"24815 Ponderosa Dr",
    "sg:city":"Idyllwild",
    "sg:classifiers":[
        {
            "category":"Shopping",
            "subcategory":"Books",
            "type":"Retail Goods"
        }
    ],
    "sg:phone":"+1 951 659 6367",
    "sg:postcode":"92549",
    "sg:province":"CA",
    "sg:tags":[
        "dealer"
    ],
    "wof:name":"Arroyo Viejo Books",
    "wof:placetype":"venue"
},
  "geometry": {"coordinates":[-116.732702,33.75915],"type":"Point"}
}