{
  "type": "Feature",
  "properties": {
    "addr:full":"5436 Murietta Ave Sherman Oaks CA 91401",
    "addr:housenumber":"5436",
    "addr:postcode":"91401",
    "addr:street":"Murietta Ave",
    "iso:country":"US",
    "sg:address":"5436 Murietta Ave",
    "sg:city":"Sherman Oaks",
    "sg:classifiers":[
        {
            "category":"Manufacturing",
            "subcategory":"Metals",
            "type":"Manufacturing & Wholesale Goods"
        },
        {
            "category":"Manufacturing",
            "subcategory":"Pottery",
            "type":"Manufacturing & Wholesale Goods"
        }
    ],
    "sg:phone":"+1 818 244 8033",
    "sg:postcode":"91401",
    "sg:province":"CA",
    "sg:tags":[
        "plumbing",
        "manufacture",
        "fixture",
        "supply"
    ],
    "wof:name":"Acapela Inc",
    "wof:placetype":"venue"
},
  "geometry": {"coordinates":[-118.438805,34.169671],"type":"Point"}
}