{
  "type": "Feature",
  "properties": {
    "iso:country":"US",
    "sg:address":"1100 Melody Ln",
    "sg:city":"Roseville",
    "sg:classifiers":[
        {
            "category":"Professional",
            "subcategory":"Computer Services",
            "type":"Services"
        }
    ],
    "sg:phone":"+1 916 677 1716",
    "sg:postcode":"95678",
    "sg:province":"CA",
    "sg:tags":[
        "consultant",
        "designer"
    ],
    "wof:name":"Mara Consulting",
    "wof:placetype":"venue"
},
  "geometry": {"coordinates":[-121.29085600000001,38.727637],"type":"Point"}
}