{
  "type": "Feature",
  "properties": {
    "iso:country":"US",
    "sg:address":"2825 S Western Ave",
    "sg:city":"Los Angeles",
    "sg:classifiers":[
        {
            "category":"Personal",
            "subcategory":"Beauty Salon",
            "type":"Services"
        }
    ],
    "sg:phone":"+1 323 737 8963",
    "sg:postcode":"90018",
    "sg:province":"CA",
    "wof:name":"Estes' Hair Affair",
    "wof:placetype":"venue"
},
  "geometry": {"coordinates":[-118.30900200000001,34.029299],"type":"Point"}
}