{
  "type": "Feature",
  "properties": {
    "iso:country":"US",
    "sg:address":"1270 W Capitol Ave",
    "sg:city":"West Sacramento",
    "sg:classifiers":[
        {
            "category":"Food & Beverages",
            "subcategory":"Groceries & Convenience Stores",
            "type":"Retail Goods"
        }
    ],
    "sg:phone":"+1 916 373 0367",
    "sg:postcode":"95691",
    "sg:province":"CA",
    "wof:name":"Big Lot's Inc",
    "wof:placetype":"venue"
},
  "geometry": {"coordinates":[-121.524002,38.581501],"type":"Point"}
}