{
  "type": "Feature",
  "properties": {
    "iso:country":"US",
    "sg:address":"250 Montgomery Street",
    "sg:city":"San Francisco",
    "sg:classifiers":[
        {
            "category":"Professional",
            "subcategory":"Lawyer & Legal Services",
            "type":"Services"
        }
    ],
    "sg:phone":"+1 415 409 5222",
    "sg:postcode":"94104",
    "sg:province":"CA",
    "wof:name":"Miller Michele P",
    "wof:placetype":"venue"
},
  "geometry": {"coordinates":[-122.402,37.7915],"type":"Point"}
}