{
  "type": "Feature",
  "properties": {
    "addr:full":"5353 Topanga Canyon Blvd Woodland Hills CA 91364",
    "addr:housenumber":"5353",
    "addr:postcode":"91364",
    "addr:street":"Topanga Canyon Blvd",
    "iso:country":"US",
    "sg:address":"5353 Topanga Canyon Blvd",
    "sg:city":"Woodland Hills",
    "sg:classifiers":[
        {
            "category":"Health Services",
            "subcategory":"Health Practitioner",
            "type":"Services"
        }
    ],
    "sg:phone":"+1 818 884 2106",
    "sg:postcode":"91364",
    "sg:province":"CA",
    "sg:tags":[
        "acupuncture"
    ],
    "wof:name":"Healing Compass The",
    "wof:placetype":"venue"
},
  "geometry": {"coordinates":[-118.606083,34.167418],"type":"Point"}
}