{
  "type": "Feature",
  "properties": {
    "addr:full":"1301 Las Villas Way Escondido CA 92026",
    "addr:housenumber":"1301",
    "addr:postcode":"92026",
    "addr:street":"Las Villas Way",
    "iso:country":"US",
    "sg:address":"1301 Las Villas Way",
    "sg:city":"Escondido",
    "sg:classifiers":[
        {
            "category":"Professional",
            "type":"Services"
        }
    ],
    "sg:phone":"+1 760 743 6695",
    "sg:postcode":"92026",
    "sg:province":"CA",
    "sg:tags":[
        "establishment"
    ],
    "wof:name":"Project Care",
    "wof:placetype":"venue"
},
  "geometry": {"coordinates":[-117.093498,33.138537],"type":"Point"}
}