{
  "type": "Feature",
  "properties": {
    "addr:full":"21704 Golden Triangle Rd Santa Clarita CA 91350",
    "addr:housenumber":"21704",
    "addr:postcode":"91350",
    "addr:street":"Golden Triangle Rd",
    "iso:country":"US",
    "sg:address":"21704 Golden Triangle Rd",
    "sg:city":"Santa Clarita",
    "sg:classifiers":[
        {
            "category":"Professional",
            "type":"Services"
        }
    ],
    "sg:phone":"+1 661 243 1006",
    "sg:postcode":"91350",
    "sg:province":"CA",
    "wof:name":"Countrywide Bail Bonds",
    "wof:placetype":"venue"
},
  "geometry": {"coordinates":[-118.515871,34.414107],"type":"Point"}
}