{
  "type": "Feature",
  "properties": {
    "addr:full":"1 Zoo Rd San Francisco CA 94132",
    "addr:housenumber":"1",
    "addr:postcode":"94132",
    "addr:street":"Zoo Rd",
    "iso:country":"US",
    "sg:address":"1 Zoo Rd",
    "sg:city":"San Francisco",
    "sg:classifiers":[
        {
            "category":"Arts & Performance",
            "subcategory":"Arts Center",
            "type":"Entertainment"
        },
        {
            "category":"Museum",
            "subcategory":"Zoo",
            "type":"Entertainment"
        }
    ],
    "sg:phone":"+1 415 753 7080",
    "sg:postcode":"94132",
    "sg:province":"CA",
    "sg:website":"www.sfzoo.org",
    "wof:name":"San Francisco Zoo",
    "wof:placetype":"venue"
},
  "geometry": {"coordinates":[-122.499498,37.731514],"type":"Point"}
}