{
  "type": "Feature",
  "properties": {
    "addr:full":"3211 Live Oak St Huntington Park CA 90255",
    "addr:housenumber":"3211",
    "addr:postcode":"90255",
    "addr:street":"Live Oak St;Park",
    "iso:country":"US",
    "sg:address":"3211 Live Oak St",
    "sg:city":"Huntington Park",
    "sg:classifiers":[
        {
            "category":"Real Estate",
            "subcategory":"Real Estate Agent",
            "type":"Services"
        }
    ],
    "sg:phone":"+1 323 560 1983",
    "sg:postcode":"90255",
    "sg:province":"CA",
    "wof:name":"Century 21",
    "wof:placetype":"venue"
},
  "geometry": {"coordinates":[-118.210368,33.970203],"type":"Point"}
}