{
  "type": "Feature",
  "properties": {
    "iso:country":"US",
    "sg:address":"391 Taylor Blvd",
    "sg:city":"Pleasant Hill",
    "sg:classifiers":[
        {
            "category":"Banks & Credit Unions",
            "subcategory":"Bank",
            "type":"Services"
        }
    ],
    "sg:phone":"+1 925 691 5200",
    "sg:postcode":"94523",
    "sg:province":"CA",
    "sg:tags":[
        "loan"
    ],
    "wof:name":"Excel Funding",
    "wof:placetype":"venue"
},
  "geometry": {"coordinates":[-122.07006199999999,37.961213],"type":"Point"}
}