{
  "type": "Feature",
  "properties": {
    "addr:full":"3040 Ocean Park Blvd Santa Monica CA 90405",
    "addr:housenumber":"3040",
    "addr:postcode":"90405",
    "addr:street":"Ocean Park Blvd",
    "iso:country":"US",
    "sg:address":"3040 Ocean Park Blvd",
    "sg:city":"Santa Monica",
    "sg:classifiers":[
        {
            "category":"Restaurant",
            "type":"Food & Drink"
        }
    ],
    "sg:menulink":"http://www.allmenus.com/ca/santa-monica/152885-carrows/menu/",
    "sg:phone":"+1 310 450 1321",
    "sg:postcode":"90405",
    "sg:province":"CA",
    "sg:tags":[
        "sandwich",
        "salad",
        "burger",
        "dog",
        "soup",
        "hot",
        "wrap",
        "american"
    ],
    "wof:name":"Carrows",
    "wof:placetype":"venue"
},
  "geometry": {"coordinates":[-118.453447,34.019861],"type":"Point"}
}