{
  "type": "Feature",
  "properties": {
    "addr:full":"942 Cll Amanecer San Clemente CA 92673",
    "addr:housenumber":"942",
    "addr:postcode":"92673",
    "addr:street":"Cll Amanecer",
    "iso:country":"US",
    "sg:address":"942 Cll Amanecer",
    "sg:city":"San Clemente",
    "sg:classifiers":[
        {
            "category":"Professional",
            "type":"Services"
        },
        {
            "category":"Manufacturing",
            "subcategory":"Tools & Machinery",
            "type":"Manufacturing & Wholesale Goods"
        }
    ],
    "sg:phone":"+1 949 361 2633",
    "sg:postcode":"92673",
    "sg:province":"CA",
    "sg:tags":[
        "equipment",
        "system",
        "automation"
    ],
    "wof:name":"Code In Motion LLC",
    "wof:placetype":"venue"
},
  "geometry": {"coordinates":[-117.60089000000001,33.452779],"type":"Point"}
}