{
  "type": "Feature",
  "properties": {
    "addr:full":"1491 Lincoln Ave Calistoga CA 94515",
    "addr:housenumber":"1491",
    "addr:postcode":"94515",
    "addr:street":"Lincoln Ave",
    "iso:country":"US",
    "sg:address":"1491 Lincoln Ave",
    "sg:city":"Calistoga",
    "sg:classifiers":[
        {
            "category":"Food & Beverages",
            "subcategory":"Groceries & Convenience Stores",
            "type":"Retail Goods"
        }
    ],
    "sg:phone":"+1 707 942 4545",
    "sg:postcode":"94515",
    "sg:province":"CA",
    "wof:name":"Meat Mart",
    "wof:placetype":"venue"
},
  "geometry": {"coordinates":[-122.578003,38.5802],"type":"Point"}
}