{
  "type": "Feature",
  "properties": {
    "iso:country":"US",
    "sg:address":"1626 Centinela Ave",
    "sg:city":"Inglewood",
    "sg:classifiers":[
        {
            "category":"Banks & Credit Unions",
            "subcategory":"Investment Brokerage",
            "type":"Services"
        }
    ],
    "sg:phone":"+1 310 641 7694",
    "sg:postcode":"90302",
    "sg:province":"CA",
    "sg:tags":[
        "management"
    ],
    "wof:name":"Tri Level Investment & Mgmt",
    "wof:placetype":"venue"
},
  "geometry": {"coordinates":[-118.368153,33.977205],"type":"Point"}
}