{
  "type": "Feature",
  "properties": {
    "addr:full":"24639 Shoshone Rd Apple Valley CA 92307",
    "addr:housenumber":"24639",
    "addr:postcode":"92307",
    "addr:street":"Shoshone Rd",
    "iso:country":"US",
    "sg:address":"24639 Shoshone Rd",
    "sg:city":"Apple Valley",
    "sg:classifiers":[
        {
            "category":"Recreation",
            "type":"Entertainment"
        }
    ],
    "sg:phone":"+1 760 240 4222",
    "sg:postcode":"92307",
    "sg:province":"CA",
    "sg:tags":[
        "concessionaire"
    ],
    "wof:name":"Desert Dogs",
    "wof:placetype":"venue"
},
  "geometry": {"coordinates":[-117.11853499999999,34.551653],"type":"Point"}
}