{
  "type": "Feature",
  "properties": {
    "addr:full":"2363 Thompson Way Santa Maria CA 93455",
    "addr:housenumber":"2363",
    "addr:postcode":"93455",
    "addr:street":"Thompson Way",
    "iso:country":"US",
    "sg:address":"2363 Thompson Way",
    "sg:city":"Santa Maria",
    "sg:classifiers":[
        {
            "category":"Manufacturing",
            "subcategory":"Motor Vehicles & Parts",
            "type":"Manufacturing & Wholesale Goods"
        }
    ],
    "sg:phone":"+1 805 925 5461",
    "sg:postcode":"93455",
    "sg:province":"CA",
    "sg:tags":[
        "exhaust",
        "system",
        "mfg"
    ],
    "wof:name":"Rlv",
    "wof:placetype":"venue"
},
  "geometry": {"coordinates":[-120.456329,34.918574],"type":"Point"}
}