{
  "type": "Feature",
  "properties": {
    "addr:full":"4861 Sevilla Way Carlsbad CA 92008",
    "addr:housenumber":"4861",
    "addr:postcode":"92008",
    "addr:street":"Sevilla Way",
    "iso:country":"US",
    "sg:address":"4861 Sevilla Way",
    "sg:city":"Carlsbad",
    "sg:classifiers":[
        {
            "category":"Banks & Credit Unions",
            "subcategory":"Financial Services",
            "type":"Services"
        }
    ],
    "sg:phone":"+1 760 729 1026",
    "sg:postcode":"92008",
    "sg:province":"CA",
    "sg:tags":[
        "trust",
        "management"
    ],
    "wof:name":"Marital Brown Trust",
    "wof:placetype":"venue"
},
  "geometry": {"coordinates":[-117.315876,33.145103],"type":"Point"}
}