{
  "type": "Feature",
  "properties": {
    "iso:country":"US",
    "sg:address":"1231 S Main St",
    "sg:city":"Santa Ana",
    "sg:classifiers":[
        {
            "category":"Autos & Motor Vehicles",
            "subcategory":"Automobile Sales",
            "type":"Retail Goods"
        }
    ],
    "sg:phone":"+1 714 648 0895",
    "sg:postcode":"92707",
    "sg:province":"CA",
    "sg:tags":[
        "car",
        "dealer"
    ],
    "wof:name":"Auto Plus",
    "wof:placetype":"venue"
},
  "geometry": {"coordinates":[-117.86768499999999,33.731971],"type":"Point"}
}