{
  "type": "Feature",
  "properties": {
    "addr:full":"26151 Wilson St Los Molinos CA 96055",
    "addr:housenumber":"26151",
    "addr:postcode":"96055",
    "addr:street":"Wilson St",
    "iso:country":"US",
    "sg:address":"26151 Wilson St",
    "sg:city":"Los Molinos",
    "sg:classifiers":[
        {
            "category":"Building & Trades",
            "subcategory":"Cleaning & Sanitation",
            "type":"Services"
        }
    ],
    "sg:phone":"+1 530 384 2577",
    "sg:postcode":"96055",
    "sg:province":"CA",
    "sg:tags":[
        "fireplace",
        "chimney"
    ],
    "wof:name":"North Valley Cleaning",
    "wof:placetype":"venue"
},
  "geometry": {"coordinates":[-122.060935,40.057501],"type":"Point"}
}