{
  "type": "Feature",
  "properties": {
    "addr:full":"1016 W Vernon Avenue Los Angeles CA 90037",
    "addr:housenumber":"1016",
    "addr:postcode":"90037",
    "addr:street":"W Vernon Avenue",
    "iso:country":"US",
    "sg:address":"1016 W Vernon Avenue",
    "sg:city":"Los Angeles",
    "sg:classifiers":[
        {
            "category":"Organizations",
            "subcategory":"Religious Organization",
            "type":"Services"
        }
    ],
    "sg:phone":"+1 323 233 9268",
    "sg:postcode":"90037",
    "sg:province":"CA",
    "wof:name":"Iglesia Manantiales De Vida Eterna De La",
    "wof:placetype":"venue"
},
  "geometry": {"coordinates":[-118.291681,34.003784],"type":"Point"}
}