{
  "type": "Feature",
  "properties": {
    "addr:full":"17653 Cam de Yatasto Pacific Plsds CA 90272",
    "addr:housenumber":"17653",
    "addr:postcode":"90272",
    "addr:street":"Cam De Yatasto",
    "iso:country":"US",
    "sg:address":"17653 Cam de Yatasto",
    "sg:city":"Pacific Plsds",
    "sg:classifiers":[
        {
            "category":"Wholesale",
            "subcategory":"Durable Goods & Equipment",
            "type":"Manufacturing & Wholesale Goods"
        }
    ],
    "sg:phone":"+1 310 459 6388",
    "sg:postcode":"90272",
    "sg:province":"CA",
    "sg:tags":[
        "exporter"
    ],
    "wof:name":"Jenny Overseas Of Ca Inc",
    "wof:placetype":"venue"
},
  "geometry": {"coordinates":[-118.569959,34.078041],"type":"Point"}
}