{
  "type": "Feature",
  "properties": {
    "iso:country":"US",
    "sg:address":"831 N Market Blvd",
    "sg:city":"Sacramento",
    "sg:classifiers":[
        {
            "category":"Shopping",
            "subcategory":"Florist",
            "type":"Retail Goods"
        }
    ],
    "sg:phone":"+1 916 565 1988",
    "sg:postcode":"95834",
    "sg:province":"CA",
    "wof:name":"Majestic Floral Intl",
    "wof:placetype":"venue"
},
  "geometry": {"coordinates":[-121.479319,38.647381],"type":"Point"}
}