{
  "type": "Feature",
  "properties": {
    "addr:full":"1141 Catalina Dr Livermore CA 94550",
    "addr:housenumber":"1141",
    "addr:postcode":"94550",
    "addr:street":"Catalina Dr",
    "iso:country":"US",
    "sg:address":"1141 Catalina Dr",
    "sg:city":"Livermore",
    "sg:classifiers":[
        {
            "category":"Manufacturing",
            "subcategory":"Tools & Machinery",
            "type":"Manufacturing & Wholesale Goods"
        }
    ],
    "sg:phone":"+1 925 606 0766",
    "sg:postcode":"94550",
    "sg:province":"CA",
    "sg:tags":[
        "repair",
        "television",
        "camera",
        "video",
        "mfg"
    ],
    "wof:name":"C E I Technology",
    "wof:placetype":"venue"
},
  "geometry": {"coordinates":[-121.78101100000001,37.662849],"type":"Point"}
}