{
  "type": "Feature",
  "properties": {
    "addr:full":"1311 Sutter Street San Francisco CA 94109",
    "addr:housenumber":"1311",
    "addr:postcode":"94109",
    "addr:street":"Sutter Street",
    "iso:country":"US",
    "sg:address":"1311 Sutter Street",
    "sg:city":"San Francisco",
    "sg:classifiers":[
        {
            "category":"Building & Trades",
            "subcategory":"Cleaning & Sanitation",
            "type":"Services"
        }
    ],
    "sg:phone":"+1 415 345 8400",
    "sg:postcode":"94109",
    "sg:province":"CA",
    "sg:tags":[
        "home"
    ],
    "wof:name":"Dana's Housekeeping Personnel Service",
    "wof:placetype":"venue"
},
  "geometry": {"coordinates":[-122.421997,37.787498],"type":"Point"}
}