{
  "type": "Feature",
  "properties": {
    "iso:country":"US",
    "sg:address":"423 Miller Ave",
    "sg:city":"Mill Valley",
    "sg:classifiers":[
        {
            "category":"Professional",
            "subcategory":"Accounting & Tax Preparation",
            "type":"Services"
        }
    ],
    "sg:phone":"+1 415 380 4130",
    "sg:postcode":"94941",
    "sg:province":"CA",
    "sg:tags":[
        "bookkeeping",
        "general"
    ],
    "wof:name":"Logan & Assoc",
    "wof:placetype":"venue"
},
  "geometry": {"coordinates":[-122.534415,37.89532],"type":"Point"}
}