{
  "type": "Feature",
  "properties": {
    "addr:full":"301 Main St, Ste 105 Huntington Beach CA 92648",
    "addr:housenumber":"301",
    "addr:postcode":"92648",
    "addr:street":"Main St Ste 105",
    "iso:country":"US",
    "sg:address":"301 Main St, Ste 105",
    "sg:city":"Huntington Beach",
    "sg:classifiers":[
        {
            "category":"Shopping",
            "subcategory":"Gifts & Souvenirs",
            "type":"Retail Goods"
        }
    ],
    "sg:phone":"+1 714 374 9250",
    "sg:postcode":"92648",
    "sg:province":"CA",
    "sg:tags":[
        "flower"
    ],
    "wof:name":"Cottage by the Sea",
    "wof:placetype":"venue"
},
  "geometry": {"coordinates":[-118.00019500000001,33.658908],"type":"Point"}
}