{
  "type": "Feature",
  "properties": {
    "addr:full":"1230 Columbia St Ste 500 San Diego CA 92101",
    "addr:housenumber":"1230",
    "addr:postcode":"92101",
    "addr:street":"Columbia St Ste 500",
    "iso:country":"US",
    "sg:address":"1230 Columbia St Ste 500",
    "sg:city":"San Diego",
    "sg:classifiers":[
        {
            "category":"Professional",
            "type":"Services"
        }
    ],
    "sg:phone":"+1 619 231 9977",
    "sg:postcode":"92101",
    "sg:province":"CA",
    "sg:website":"www.berkmanpr.com",
    "wof:name":"BERKMAN",
    "wof:placetype":"venue"
},
  "geometry": {"coordinates":[-117.167688,32.718253],"type":"Point"}
}