{
  "type": "Feature",
  "properties": {
    "addr:full":"8787 Lemon Ave La Mesa CA 91941",
    "addr:housenumber":"8787",
    "addr:postcode":"91941",
    "addr:street":"Lemon Ave",
    "iso:country":"US",
    "sg:address":"8787 Lemon Ave",
    "sg:city":"La Mesa",
    "sg:classifiers":[
        {
            "category":"Education",
            "subcategory":"School",
            "type":"Public Place"
        }
    ],
    "sg:phone":"+1 619 668 5835",
    "sg:postcode":"91941",
    "sg:province":"CA",
    "sg:tags":[
        "elementary"
    ],
    "sg:website":"www.lmsvsd.k12.ca.us",
    "wof:name":"Lemon Avenue Elementary School",
    "wof:placetype":"venue"
},
  "geometry": {"coordinates":[-117.00900300000001,32.7682],"type":"Point"}
}