{
  "type": "Feature",
  "properties": {
    "iso:country":"US",
    "sg:address":"6112 N Channing Cir",
    "sg:city":"Fresno",
    "sg:classifiers":[
        {
            "category":"Building & Trades",
            "subcategory":"Plumbing",
            "type":"Services"
        }
    ],
    "sg:phone":"+1 559 449 1985",
    "sg:postcode":"93711",
    "sg:province":"CA",
    "sg:tags":[
        "plumbing",
        "contractor"
    ],
    "wof:name":"Kim's Plumbing",
    "wof:placetype":"venue"
},
  "geometry": {"coordinates":[-119.824528,36.825423],"type":"Point"}
}