{
  "type": "Feature",
  "properties": {
    "iso:country":"US",
    "sg:address":"1521 S Stockton St",
    "sg:city":"Stockton",
    "sg:classifiers":[
        {
            "category":"Utilities",
            "subcategory":"Cable",
            "type":"Services"
        }
    ],
    "sg:phone":"+1 209 369 2426",
    "sg:postcode":"95206",
    "sg:province":"CA",
    "sg:tags":[
        "television"
    ],
    "wof:name":"Comcast Cable Holdings LLC",
    "wof:placetype":"venue"
},
  "geometry": {"coordinates":[-121.299953,37.935045],"type":"Point"}
}