{
  "type": "Feature",
  "properties": {
    "iso:country":"US",
    "sg:address":"2951 Bridgeway",
    "sg:city":"Sausalito",
    "sg:classifiers":[
        {
            "category":"Professional",
            "subcategory":"Management & Consulting",
            "type":"Services"
        }
    ],
    "sg:phone":"+1 415 331 3921",
    "sg:postcode":"94965",
    "sg:province":"CA",
    "sg:tags":[
        "consultant",
        "business"
    ],
    "wof:name":"Bayside Management",
    "wof:placetype":"venue"
},
  "geometry": {"coordinates":[-122.503001,37.86891],"type":"Point"}
}