{
  "type": "Feature",
  "properties": {
    "addr:full":"2138 Stormy Creek Ct Stockton CA 95206",
    "addr:housenumber":"2138",
    "addr:postcode":"95206",
    "addr:street":"Stormy Creek Ct",
    "iso:country":"US",
    "sg:address":"2138 Stormy Creek Ct",
    "sg:city":"Stockton",
    "sg:classifiers":[
        {
            "category":"Shopping",
            "subcategory":"Gifts & Souvenirs",
            "type":"Retail Goods"
        }
    ],
    "sg:phone":"+1 209 465 9525",
    "sg:postcode":"95206",
    "sg:province":"CA",
    "sg:tags":[
        "shop"
    ],
    "wof:name":"Jessie's Fashion Boutique",
    "wof:placetype":"venue"
},
  "geometry": {"coordinates":[-121.322594,37.927346],"type":"Point"}
}