{
  "type": "Feature",
  "properties": {
    "addr:full":"2157 Sorrento Dr Oceanside CA 92056",
    "addr:housenumber":"2157",
    "addr:postcode":"92056",
    "addr:street":"Sorrento Dr",
    "iso:country":"US",
    "sg:address":"2157 Sorrento Dr",
    "sg:city":"Oceanside",
    "sg:classifiers":[
        {
            "category":"Personal",
            "type":"Services"
        }
    ],
    "sg:phone":"+1 760 966 1763",
    "sg:postcode":"92056",
    "sg:province":"CA",
    "sg:tags":[
        "image",
        "consultants-personal"
    ],
    "wof:name":"Rapid Eye Alternative Healing",
    "wof:placetype":"venue"
},
  "geometry": {"coordinates":[-117.308826,33.195094],"type":"Point"}
}