{
  "type": "Feature",
  "properties": {
    "addr:full":"2151 Ferry Pt Alameda CA 94501",
    "addr:housenumber":"2151",
    "addr:postcode":"94501",
    "addr:street":"Ferry Pt",
    "iso:country":"US",
    "sg:address":"2151 Ferry Pt",
    "sg:city":"Alameda",
    "sg:classifiers":[
        {
            "category":"Museum",
            "type":"Entertainment"
        }
    ],
    "sg:phone":"+1 510 522 4262",
    "sg:postcode":"94501",
    "sg:province":"CA",
    "sg:website":"www.alamedanavalairmuseum.org/",
    "wof:name":"Alameda Naval Air Museum",
    "wof:placetype":"venue"
},
  "geometry": {"coordinates":[-122.261002,37.768101],"type":"Point"}
}