{
  "type": "Feature",
  "properties": {
    "addr:city":"Alameda",
    "addr:full":"2151 Ferry Pt Alameda, Ca 94501",
    "addr:house_number":"2151",
    "addr:housenumber":"2151",
    "addr:phone":"+1 510-522-4262",
    "addr:postcode":"94501",
    "addr:road":"Ferry Pt",
    "addr:state":"CA",
    "addr:street":"Ferry Pt",
    "iso:country":"US",
    "sg:address":"2151 Ferry Pt",
    "sg:city":"Alameda",
    "sg:classifiers":[
        {
            "category":"Museum",
            "type":"Entertainment"
        }
    ],
    "sg:phone":"+1 510 522 4262",
    "sg:postcode":"94501",
    "sg:province":"CA",
    "sg:website":"www.alamedanavalairmuseum.org/",
    "wof:airports":[
        102527513,
        102531041,
        102532543
    ],
    "wof:name":"Alameda Naval Air Museum",
    "wof:placetype":"venue"
},
  "geometry": {"coordinates":[-122.2743,37.77145],"type":"Point"}
}