{
  "type": "Feature",
  "properties": {
    "iso:country":"US",
    "sg:address":"544 San Benito St",
    "sg:city":"Hollister",
    "sg:classifiers":[
        {
            "category":"Shopping",
            "subcategory":"Music",
            "type":"Retail Goods"
        }
    ],
    "sg:phone":"+1 831 630 1088",
    "sg:postcode":"95023",
    "sg:province":"CA",
    "sg:tags":[
        "video",
        "disc",
        "tape",
        "cassette"
    ],
    "wof:name":"Video Town",
    "wof:placetype":"venue"
},
  "geometry": {"coordinates":[-121.402242,36.850914],"type":"Point"}
}