{
  "type": "Feature",
  "properties": {
    "sfgov:dept":"7",
    "sfgov:deptname":"SF Unified School District (SFUSD)",
    "sfgov:facility_i":"0000003096",
    "sfgov:school_typ":"Elementary",
    "wof:categories":[
        "education_and_religion:education=school"
    ],
    "wof:name":"Garfield Elementary School",
    "wof:placetype":"venue"
},
  "geometry": {"coordinates":[-122.40653202333976,37.80193503658627],"type":"Point"}
}