{
  "type": "Feature",
  "properties": {
    "iso:country":"US",
    "sg:address":"9872 Shirley Gardens Dr",
    "sg:city":"Santee",
    "sg:classifiers":[
        {
            "category":"Professional",
            "type":"Services"
        }
    ],
    "sg:phone":"+1 619 379 2225",
    "sg:postcode":"92071",
    "sg:province":"CA",
    "sg:tags":[
        "caterer"
    ],
    "sg:website":"indulgencesandiego.com/",
    "wof:name":"Indulgence Catering",
    "wof:placetype":"venue"
},
  "geometry": {"coordinates":[-116.973815,32.855923],"type":"Point"}
}