{
  "type": "Feature",
  "properties": {
    "iso:country":"US",
    "sg:address":"2020 Coffee Rd",
    "sg:city":"Modesto",
    "sg:classifiers":[
        {
            "category":"Health Services",
            "subcategory":"Health Practitioner",
            "type":"Services"
        }
    ],
    "sg:phone":"+1 209 567 1432",
    "sg:postcode":"95355",
    "sg:province":"CA",
    "sg:tags":[
        "acupuncture"
    ],
    "wof:name":"Bills Acupressure & Myofascial",
    "wof:placetype":"venue"
},
  "geometry": {"coordinates":[-120.975674,37.673861],"type":"Point"}
}