{
  "type": "Feature",
  "properties": {
    "addr:full":"23704 Hynford Pl Harbor City CA 90710",
    "addr:postcode":"23704;90710",
    "addr:street":"Pl",
    "iso:country":"US",
    "sg:address":"23704 Hynford Pl",
    "sg:city":"Harbor City",
    "sg:classifiers":[
        {
            "category":"Health Services",
            "subcategory":"Nursing And Care Facility",
            "type":"Services"
        },
        {
            "category":"Travel",
            "subcategory":"Hotels & Motels",
            "type":"Entertainment"
        }
    ],
    "sg:phone":"+1 310 539 5502",
    "sg:postcode":"90710",
    "sg:province":"CA",
    "sg:tags":[
        "home",
        "membership",
        "convalescent",
        "lodging"
    ],
    "wof:name":"Michael's Manor",
    "wof:placetype":"venue"
},
  "geometry": {"coordinates":[-118.306084,33.809611],"type":"Point"}
}