{
  "type": "Feature",
  "properties": {
    "addr:full":"1920 Tienda Dr Lodi CA 95242",
    "addr:postcode":"1920;95242",
    "addr:street":"Tienda Dr",
    "iso:country":"US",
    "sg:address":"1920 Tienda Dr",
    "sg:city":"Lodi",
    "sg:classifiers":[
        {
            "category":"Professional",
            "subcategory":"Accounting & Tax Preparation",
            "type":"Services"
        }
    ],
    "sg:phone":"+1 209 333 8488",
    "sg:postcode":"95242",
    "sg:province":"CA",
    "sg:tags":[
        "payroll",
        "bookkeeping",
        "return",
        "preparation-business"
    ],
    "sg:website":"http://www.qbstax.com",
    "wof:name":"Quality Business Service",
    "wof:placetype":"venue"
},
  "geometry": {"coordinates":[-121.295542,38.11681],"type":"Point"}
}