{
  "type": "Feature",
  "properties": {
    "iso:country":"US",
    "sg:address":"13418 Ventura Blvd",
    "sg:city":"Sherman Oaks",
    "sg:classifiers":[
        {
            "category":"Professional",
            "subcategory":"Lawyer & Legal Services",
            "type":"Services"
        }
    ],
    "sg:phone":"+1 818 783 7300",
    "sg:postcode":"91423",
    "sg:province":"CA",
    "sg:tags":[
        "attorney"
    ],
    "wof:name":"Danz & Gerber",
    "wof:placetype":"venue"
},
  "geometry": {"coordinates":[-118.425566,34.146988],"type":"Point"}
}