{
  "type": "Feature",
  "properties": {
    "addr:full":"2727 N Grove Industrial Dr Fresno CA 93727",
    "addr:housenumber":"2727",
    "addr:postcode":"93727",
    "addr:street":"N Grove Industrial Dr",
    "iso:country":"US",
    "sg:address":"2727 N Grove Industrial Dr",
    "sg:city":"Fresno",
    "sg:classifiers":[
        {
            "category":"Manufacturing",
            "subcategory":"Printing",
            "type":"Manufacturing & Wholesale Goods"
        }
    ],
    "sg:phone":"+1 559 252 8180",
    "sg:postcode":"93727",
    "sg:province":"CA",
    "sg:tags":[
        "printer"
    ],
    "sg:website":"www.4printer.com",
    "wof:name":"Business Connections",
    "wof:placetype":"venue"
},
  "geometry": {"coordinates":[-119.730092,36.7742],"type":"Point"}
}