{
  "type": "Feature",
  "properties": {
    "iso:country":"US",
    "sg:address":"2424 el Camino Ave",
    "sg:city":"Sacramento",
    "sg:classifiers":[
        {
            "category":"Professional",
            "type":"Services"
        }
    ],
    "sg:phone":"+1 916 481 4002",
    "sg:postcode":"95821",
    "sg:province":"CA",
    "wof:name":"Shylark Studios",
    "wof:placetype":"venue"
},
  "geometry": {"coordinates":[-121.40424299999999,38.610602],"type":"Point"}
}