{
  "type": "Feature",
  "properties": {
    "iso:country":"US",
    "sg:address":"7915 E Ave",
    "sg:city":"Hesperia",
    "sg:classifiers":[
        {
            "category":"Restaurant",
            "type":"Food & Drink"
        }
    ],
    "sg:phone":"+1 760 662 1744",
    "sg:postcode":"92345",
    "sg:province":"CA",
    "wof:name":"MTY Meals To You",
    "wof:placetype":"venue"
},
  "geometry": {"coordinates":[-117.299267,34.39509],"type":"Point"}
}