{
  "type": "Feature",
  "properties": {
    "addr:full":"28412 Constellation Rd Valencia CA 91355",
    "addr:housenumber":"28412",
    "addr:postcode":"91355",
    "addr:street":"Constellation Rd",
    "iso:country":"US",
    "sg:address":"28412 Constellation Rd",
    "sg:city":"Valencia",
    "sg:classifiers":[
        {
            "category":"Health Services",
            "subcategory":"Clinic",
            "type":"Services"
        }
    ],
    "sg:phone":"+1 661 257 8442",
    "sg:postcode":"91355",
    "sg:province":"CA",
    "sg:tags":[
        "loss",
        "weight"
    ],
    "sg:website":"www.fusionmixedmartialarts.com",
    "wof:name":"Fusion Mixed Martial Arts",
    "wof:placetype":"venue"
},
  "geometry": {"coordinates":[-118.577252,34.453111],"type":"Point"}
}