{
  "type": "Feature",
  "properties": {
    "iso:country":"US",
    "sg:address":"18726 S Western Ave",
    "sg:city":"Gardena",
    "sg:classifiers":[
        {
            "category":"Professional",
            "subcategory":"Detective & Security Services",
            "type":"Services"
        }
    ],
    "sg:phone":"+1 310 523 9068",
    "sg:postcode":"90248",
    "sg:province":"CA",
    "sg:tags":[
        "guard",
        "patrol"
    ],
    "wof:name":"Johnson Professional Security",
    "wof:placetype":"venue"
},
  "geometry": {"coordinates":[-118.309148,33.860997],"type":"Point"}
}