{
  "type": "Feature",
  "properties": {
    "addr:full":"9064 Shell Rd Marysville CA 95901",
    "addr:housenumber":"9064",
    "addr:postcode":"95901",
    "addr:street":"Shell Rd",
    "iso:country":"US",
    "sg:address":"9064 Shell Rd",
    "sg:city":"Marysville",
    "sg:classifiers":[
        {
            "category":"Retail",
            "subcategory":"Auto Repair",
            "type":"Services"
        }
    ],
    "sg:phone":"+1 530 674 9813",
    "sg:postcode":"95901",
    "sg:province":"CA",
    "sg:tags":[
        "repairing",
        "automobile"
    ],
    "wof:name":"Mid State Pump Co & Water Well",
    "wof:placetype":"venue"
},
  "geometry": {"coordinates":[-121.59276,39.224572],"type":"Point"}
}