{
  "type": "Feature",
  "properties": {
    "iso:country":"US",
    "sg:address":"48531 Warm Springs Blvd",
    "sg:city":"Fremont",
    "sg:classifiers":[
        {
            "category":"Utilities",
            "subcategory":"Mobile Phone",
            "type":"Services"
        }
    ],
    "sg:phone":"+1 510 770 8580",
    "sg:postcode":"94539",
    "sg:province":"CA",
    "sg:tags":[
        "telephone",
        "cellular"
    ],
    "wof:name":"Advanced Cellular Inc",
    "wof:placetype":"venue"
},
  "geometry": {"coordinates":[-121.917665,37.469234],"type":"Point"}
}