{
  "type": "Feature",
  "properties": {
    "addr:full":"116 Astronaut E S Onizuka St Los Angeles CA 90012",
    "addr:housenumber":"116",
    "addr:postcode":"90012",
    "addr:street":"Astronaut E S Onizuka St",
    "iso:country":"US",
    "sg:address":"116 Astronaut E S Onizuka St",
    "sg:city":"Los Angeles",
    "sg:classifiers":[
        {
            "category":"Insurance",
            "subcategory":"Hazard Insurance",
            "type":"Services"
        }
    ],
    "sg:phone":"+1 213 626 2385",
    "sg:postcode":"90012",
    "sg:province":"CA",
    "sg:tags":[
        "bond"
    ],
    "wof:name":"Aliso Village Bail Bonds",
    "wof:placetype":"venue"
},
  "geometry": {"coordinates":[-118.24176300000001,34.049683],"type":"Point"}
}