{
  "type": "Feature",
  "properties": {
    "addr:full":"3585 Myers St Oroville CA 95966",
    "addr:housenumber":"3585",
    "addr:postcode":"95966",
    "addr:street":"Myers St",
    "iso:country":"US",
    "sg:address":"3585 Myers St",
    "sg:city":"Oroville",
    "sg:classifiers":[
        {
            "category":"Retail",
            "subcategory":"Auto Repair",
            "type":"Services"
        }
    ],
    "sg:phone":"+1 530 534 7440",
    "sg:postcode":"95966",
    "sg:province":"CA",
    "sg:tags":[
        "repairing",
        "automobile"
    ],
    "wof:name":"Myers Street Auto",
    "wof:placetype":"venue"
},
  "geometry": {"coordinates":[-121.548613,39.49647],"type":"Point"}
}