{
  "type": "Feature",
  "properties": {
    "iso:country":"US",
    "sg:address":"2150 Appian Way",
    "sg:city":"Pinole",
    "sg:classifiers":[
        {
            "category":"Health Services",
            "subcategory":"Medical Lab",
            "type":"Services"
        }
    ],
    "sg:phone":"+1 510 741 1493",
    "sg:postcode":"94564",
    "sg:province":"CA",
    "sg:tags":[
        "laboratory"
    ],
    "wof:name":"Unilab Corp",
    "wof:placetype":"venue"
},
  "geometry": {"coordinates":[-122.300358,37.991373],"type":"Point"}
}