{
  "type": "Feature",
  "properties": {
    "iso:country":"US",
    "sg:address":"3638 American River Dr",
    "sg:city":"Sacramento",
    "sg:classifiers":[
        {
            "category":"Professional",
            "subcategory":"Lawyer & Legal Services",
            "type":"Services"
        }
    ],
    "sg:phone":"+1 916 978 3434",
    "sg:postcode":"95864",
    "sg:province":"CA",
    "wof:name":"Collard William H",
    "wof:placetype":"venue"
},
  "geometry": {"coordinates":[-121.376915,38.570704],"type":"Point"}
}