{
  "type": "Feature",
  "properties": {
    "addr:full":"432 E 9th St Ste 2 Los Angeles CA 90015",
    "addr:housenumber":"432",
    "addr:postcode":"90015",
    "addr:street":"E 9Th St Ste 2",
    "iso:country":"US",
    "sg:address":"432 E 9th St Ste 2",
    "sg:city":"Los Angeles",
    "sg:classifiers":[
        {
            "category":"Shopping",
            "subcategory":"Crafts & Fabrics",
            "type":"Retail Goods"
        }
    ],
    "sg:phone":"+1 213 891 1522",
    "sg:postcode":"90015",
    "sg:province":"CA",
    "sg:tags":[
        "store"
    ],
    "wof:name":"Eco Fabric",
    "wof:placetype":"venue"
},
  "geometry": {"coordinates":[-118.252332,34.038673],"type":"Point"}
}