{
  "type": "Feature",
  "properties": {
    "iso:country":"US",
    "sg:address":"1605 W Olympic Blvd",
    "sg:city":"Los Angeles",
    "sg:classifiers":[
        {
            "category":"Professional",
            "subcategory":"Advertising",
            "type":"Services"
        }
    ],
    "sg:phone":"+1 213 365 6751",
    "sg:postcode":"90015",
    "sg:province":"CA",
    "wof:name":"CTP Svc",
    "wof:placetype":"venue"
},
  "geometry": {"coordinates":[-118.27473500000001,34.049521],"type":"Point"}
}