{
  "type": "Feature",
  "properties": {
    "addr:full":"2608 W Lincoln Ave Anaheim CA 92801",
    "addr:housenumber":"2608",
    "addr:postcode":"92801",
    "addr:street":"W Lincoln Ave",
    "iso:country":"US",
    "sg:address":"2608 W Lincoln Ave",
    "sg:city":"Anaheim",
    "sg:classifiers":[
        {
            "category":"Retail",
            "subcategory":"Auto Repair",
            "type":"Services"
        }
    ],
    "sg:phone":"+1 714 527 1959",
    "sg:postcode":"92801",
    "sg:province":"CA",
    "sg:tags":[
        "repairing",
        "automobile"
    ],
    "wof:name":"Barney's Transmission",
    "wof:placetype":"venue"
},
  "geometry": {"coordinates":[-117.976997,33.832199],"type":"Point"}
}