{
  "type": "Feature",
  "properties": {
    "addr:full":"401 Victor Way Salinas CA 93907",
    "addr:housenumber":"401",
    "addr:postcode":"93907",
    "addr:street":"Victor Way",
    "iso:country":"US",
    "sg:address":"401 Victor Way",
    "sg:city":"Salinas",
    "sg:classifiers":[
        {
            "category":"Government",
            "subcategory":"Office",
            "type":"Public Place"
        }
    ],
    "sg:phone":"+1 831 770 0164",
    "sg:postcode":"93907",
    "sg:province":"CA",
    "sg:tags":[
        "agricultural",
        "regulation",
        "marketing"
    ],
    "wof:name":"Pacific Grading Service",
    "wof:placetype":"venue"
},
  "geometry": {"coordinates":[-121.66768999999999,36.684256],"type":"Point"}
}