{
  "type": "Feature",
  "properties": {
    "iso:country":"US",
    "sg:address":"152 Main St",
    "sg:city":"Brawley",
    "sg:classifiers":[
        {
            "category":"Manufacturing",
            "subcategory":"Food",
            "type":"Manufacturing & Wholesale Goods"
        }
    ],
    "sg:phone":"+1 760 344 4929",
    "sg:postcode":"92227",
    "sg:province":"CA",
    "sg:tags":[
        "desert",
        "ice",
        "mfg"
    ],
    "wof:name":"Raspados Cuchis",
    "wof:placetype":"venue"
},
  "geometry": {"coordinates":[-115.540536,32.978571],"type":"Point"}
}