{
  "type": "Feature",
  "properties": {
    "iso:country":"US",
    "sg:address":"7010 McKinley Ave",
    "sg:city":"Los Angeles",
    "sg:classifiers":[
        {
            "category":"Professional",
            "subcategory":"Art Services",
            "type":"Services"
        }
    ],
    "sg:phone":"+1 323 759 6509",
    "sg:postcode":"90001",
    "sg:province":"CA",
    "sg:tags":[
        "graphic",
        "designer"
    ],
    "wof:name":"J R Grafix",
    "wof:placetype":"venue"
},
  "geometry": {"coordinates":[-118.26132200000001,33.979114],"type":"Point"}
}