{
  "type": "Feature",
  "properties": {
    "iso:country":"US",
    "sg:address":"23126 Drayton St",
    "sg:city":"Santa Clarita",
    "sg:classifiers":[
        {
            "category":"Home & Garden",
            "subcategory":"Hardware",
            "type":"Retail Goods"
        }
    ],
    "sg:phone":"+1 661 254 3113",
    "sg:postcode":"91350",
    "sg:province":"CA",
    "sg:tags":[
        "store"
    ],
    "sg:website":"www.stockbuildingsupply.com",
    "wof:name":"Stock Building Supply",
    "wof:placetype":"venue"
},
  "geometry": {"coordinates":[-118.540001,34.411598],"type":"Point"}
}