{
  "type": "Feature",
  "properties": {
    "addr:full":"42900 Bob Hope Dr Rancho Mirage CA 92270",
    "addr:housenumber":"42900",
    "addr:postcode":"92270",
    "addr:street":"Bob Hope Dr",
    "iso:country":"US",
    "sg:address":"42900 Bob Hope Dr",
    "sg:city":"Rancho Mirage",
    "sg:classifiers":[
        {
            "category":"Professional",
            "subcategory":"Employment Agencies",
            "type":"Services"
        }
    ],
    "sg:phone":"+1 760 568 1777",
    "sg:postcode":"92270",
    "sg:province":"CA",
    "sg:tags":[
        "opportunity"
    ],
    "wof:name":"Claire Fine Consulting",
    "wof:placetype":"venue"
},
  "geometry": {"coordinates":[-116.40810999999999,33.739102],"type":"Point"}
}