{
  "type": "Feature",
  "properties": {
    "iso:country":"US",
    "sg:address":"2555 State St",
    "sg:city":"San Diego",
    "sg:classifiers":[
        {
            "category":"Manufacturing",
            "subcategory":"Apparel",
            "type":"Manufacturing & Wholesale Goods"
        }
    ],
    "sg:phone":"+1 619 232 2555",
    "sg:postcode":"92101",
    "sg:province":"CA",
    "sg:tags":[
        "product",
        "mfg",
        "distribution",
        "specialty"
    ],
    "wof:name":"Omni/Swings N Things",
    "wof:placetype":"venue"
},
  "geometry": {"coordinates":[-117.1696,32.731293],"type":"Point"}
}