{
  "type": "Feature",
  "properties": {
    "addr:full":"2277 W Bellaire Way Fresno CA 93705",
    "addr:housenumber":"2277",
    "addr:postcode":"93705",
    "addr:street":"W Bellaire Way",
    "iso:country":"US",
    "sg:address":"2277 W Bellaire Way",
    "sg:city":"Fresno",
    "sg:classifiers":[
        {
            "category":"Education",
            "subcategory":"School",
            "type":"Public Place"
        }
    ],
    "sg:phone":"+1 559 248 7050",
    "sg:postcode":"93705",
    "sg:province":"CA",
    "wof:name":"Cooper Middle School",
    "wof:placetype":"venue"
},
  "geometry": {"coordinates":[-119.83868,36.791815],"type":"Point"}
}