{
  "type": "Feature",
  "properties": {
    "iso:country":"US",
    "sg:address":"1050 Stanford Ave",
    "sg:city":"Los Angeles",
    "sg:classifiers":[
        {
            "category":"Wholesale",
            "subcategory":"Apparel",
            "type":"Manufacturing & Wholesale Goods"
        }
    ],
    "sg:phone":"+1 213 489 3435",
    "sg:postcode":"90021",
    "sg:province":"CA",
    "sg:tags":[
        "button"
    ],
    "wof:name":"Ace Button & Trim",
    "wof:placetype":"venue"
},
  "geometry": {"coordinates":[-118.248998,34.033287],"type":"Point"}
}