{
  "type": "Feature",
  "properties": {
    "iso:country":"US",
    "sg:address":"9155 Archibald Ave",
    "sg:city":"Rancho Cucamonga",
    "sg:classifiers":[
        {
            "category":"Freight",
            "type":"Transportation"
        }
    ],
    "sg:phone":"+1 909 476 7974",
    "sg:postcode":"91730",
    "sg:province":"CA",
    "sg:tags":[
        "courier"
    ],
    "wof:name":"California Overnight",
    "wof:placetype":"venue"
},
  "geometry": {"coordinates":[-117.59339900000001,34.089811],"type":"Point"}
}