{
  "type": "Feature",
  "properties": {
    "addr:full":"9212 Bridalveil Cir Stockton CA 95212",
    "addr:housenumber":"9212",
    "addr:postcode":"95212",
    "addr:street":"Bridalveil Cir",
    "iso:country":"US",
    "sg:address":"9212 Bridalveil Cir",
    "sg:city":"Stockton",
    "sg:classifiers":[
        {
            "category":"Social Services",
            "subcategory":"Child Care",
            "type":"Services"
        }
    ],
    "sg:phone":"+1 209 472 7131",
    "sg:postcode":"95212",
    "sg:province":"CA",
    "wof:name":"In The Light Child Care",
    "wof:placetype":"venue"
},
  "geometry": {"coordinates":[-121.274407,38.033567],"type":"Point"}
}