{
  "type": "Feature",
  "properties": {
    "iso:country":"US",
    "sg:address":"3250 Dale Rd",
    "sg:city":"Modesto",
    "sg:classifiers":[
        {
            "category":"Travel",
            "subcategory":"Travel Agent",
            "type":"Entertainment"
        }
    ],
    "sg:phone":"+1 209 577 8779",
    "sg:postcode":"95356",
    "sg:province":"CA",
    "sg:tags":[
        "agency",
        "bureau"
    ],
    "sg:website":"www.modtravel.com",
    "wof:name":"Modesto Travel Co",
    "wof:placetype":"venue"
},
  "geometry": {"coordinates":[-121.04977,37.687576],"type":"Point"}
}