{
  "type": "Feature",
  "properties": {
    "iso:country":"US",
    "sg:address":"5042 Wilshire Blvd",
    "sg:city":"Los Angeles",
    "sg:classifiers":[
        {
            "category":"Shopping",
            "subcategory":"News",
            "type":"Retail Goods"
        }
    ],
    "sg:phone":"+1 323 733 6763",
    "sg:postcode":"90036",
    "sg:province":"CA",
    "sg:tags":[
        "magazine"
    ],
    "wof:name":"Vital Choices",
    "wof:placetype":"venue"
},
  "geometry": {"coordinates":[-118.338814,34.062045],"type":"Point"}
}