{
  "type": "Feature",
  "properties": {
    "addr:full":"1709 Sherborn St Corona CA 92879",
    "addr:housenumber":"1709",
    "addr:postcode":"92879",
    "addr:street":"Sherborn St",
    "iso:country":"US",
    "sg:address":"1709 Sherborn St",
    "sg:city":"Corona",
    "sg:classifiers":[
        {
            "category":"Manufacturing",
            "subcategory":"Building Materials",
            "type":"Manufacturing & Wholesale Goods"
        }
    ],
    "sg:phone":"+1 951 278 3077",
    "sg:postcode":"92879",
    "sg:province":"CA",
    "sg:tags":[
        "aggregate",
        "concrete"
    ],
    "wof:name":"Vulcan Materials Company-Western Division",
    "wof:placetype":"venue"
},
  "geometry": {"coordinates":[-117.523152,33.858997],"type":"Point"}
}