{
  "type": "Feature",
  "properties": {
    "addr:full":"15394 Julia Ranch Rd Grass Valley CA 95945",
    "addr:housenumber":"15394",
    "addr:postcode":"95945",
    "addr:street":"Julia Ranch Rd",
    "iso:country":"US",
    "sg:address":"15394 Julia Ranch Rd",
    "sg:city":"Grass Valley",
    "sg:classifiers":[
        {
            "category":"Building & Trades",
            "subcategory":"Landscaping Services",
            "type":"Services"
        }
    ],
    "sg:phone":"+1 530 477 6225",
    "sg:postcode":"95945",
    "sg:province":"CA",
    "sg:tags":[
        "tree"
    ],
    "wof:name":"C & C Hazardous Tree Removal",
    "wof:placetype":"venue"
},
  "geometry": {"coordinates":[-120.950744,39.207689],"type":"Point"}
}