{
  "type": "Feature",
  "properties": {
    "addr:full":"541 W Colorado St Glendale CA 91204",
    "addr:housenumber":"541",
    "addr:postcode":"91204",
    "addr:street":"W Colorado St",
    "iso:country":"US",
    "sg:address":"541 W Colorado St",
    "sg:city":"Glendale",
    "sg:classifiers":[
        {
            "category":"Health Services",
            "subcategory":"Doctor",
            "type":"Services"
        }
    ],
    "sg:phone":"+1 818 291 9827",
    "sg:postcode":"91204",
    "sg:province":"CA",
    "sg:tags":[
        "physician",
        "surgeon"
    ],
    "wof:name":"Conrad J Miranda MD",
    "wof:placetype":"venue"
},
  "geometry": {"coordinates":[-118.26604,34.142583],"type":"Point"}
}