{
  "type": "Feature",
  "properties": {
    "iso:country":"US",
    "sg:address":"1250 Jefferson Ave",
    "sg:city":"Redwood City",
    "sg:classifiers":[
        {
            "category":"Food & Beverages",
            "subcategory":"Groceries & Convenience Stores",
            "type":"Retail Goods"
        }
    ],
    "sg:phone":"+1 650 367 1400",
    "sg:postcode":"94062",
    "sg:province":"CA",
    "sg:tags":[
        "grocer"
    ],
    "wof:name":"Whole Foods Mkt Redwood City",
    "wof:placetype":"venue"
},
  "geometry": {"coordinates":[-122.231154,37.482306],"type":"Point"}
}