{
  "type": "Feature",
  "properties": {
    "iso:country":"US",
    "sg:address":"5530 University Avenue",
    "sg:city":"San Diego",
    "sg:classifiers":[
        {
            "category":"Retail",
            "subcategory":"Veterinary Services",
            "type":"Services"
        }
    ],
    "sg:phone":"+1 619 286 3360",
    "sg:postcode":"92105",
    "sg:province":"CA",
    "sg:tags":[
        "veterinarian"
    ],
    "sg:website":"www.myvetonline.com/colinavh",
    "wof:name":"Guajardo J Alfonso Dr",
    "wof:placetype":"venue"
},
  "geometry": {"coordinates":[-117.07638900000001,32.747689],"type":"Point"}
}