{
  "type": "Feature",
  "properties": {
    "addr:full":"655 Montgomery St Suite 750 San Francisco CA 94111",
    "addr:housenumber":"655",
    "addr:postcode":"94111",
    "addr:street":"Montgomery St Suite 750",
    "iso:country":"US",
    "sg:address":"655 Montgomery St Suite 750",
    "sg:city":"San Francisco",
    "sg:classifiers":[
        {
            "category":"Communications",
            "subcategory":"Newspaper",
            "type":"Services"
        }
    ],
    "sg:phone":"+1 415 788 2005",
    "sg:postcode":"94111",
    "sg:province":"CA",
    "sg:tags":[
        "print",
        "medium"
    ],
    "wof:name":"Stamats Communications",
    "wof:placetype":"venue"
},
  "geometry": {"coordinates":[-122.40339,37.795144],"type":"Point"}
}