{
  "type": "Feature",
  "properties": {
    "addr:full":"16315 Whittier Blvd Whittier CA 90603",
    "addr:housenumber":"16315",
    "addr:postcode":"90603",
    "addr:street":"Whittier Blvd",
    "iso:country":"US",
    "sg:address":"16315 Whittier Blvd",
    "sg:city":"Whittier",
    "sg:classifiers":[
        {
            "category":"Health Services",
            "subcategory":"Doctor",
            "type":"Services"
        },
        {
            "category":"Health Services",
            "subcategory":"Dentist",
            "type":"Services"
        }
    ],
    "sg:phone":"+1 562 943 0186",
    "sg:postcode":"90603",
    "sg:province":"CA",
    "sg:tags":[
        "surgeon",
        "oral",
        "pediatric"
    ],
    "wof:name":"Beyer Norman L DDS",
    "wof:placetype":"venue"
},
  "geometry": {"coordinates":[-117.98200199999999,33.940201],"type":"Point"}
}