{
  "type": "Feature",
  "properties": {
    "iso:country":"US",
    "sg:address":"15942 Los Serranos Country Club Dr",
    "sg:city":"Chino Hills",
    "sg:classifiers":[
        {
            "category":"Health Services",
            "subcategory":"Optometrist",
            "type":"Services"
        }
    ],
    "sg:phone":"+1 909 606 9943",
    "sg:postcode":"91709",
    "sg:province":"CA",
    "wof:name":"Chino Hills Family Optometry",
    "wof:placetype":"venue"
},
  "geometry": {"coordinates":[-117.695258,33.96319],"type":"Point"}
}