{
  "type": "Feature",
  "properties": {
    "addr:full":"14001 Valley Blvd Fontana CA 92335",
    "addr:housenumber":"14001",
    "addr:postcode":"92335",
    "addr:street":"Valley Blvd",
    "iso:country":"US",
    "sg:address":"14001 Valley Blvd",
    "sg:city":"Fontana",
    "sg:classifiers":[
        {
            "category":"Retail",
            "subcategory":"Auto Rental",
            "type":"Services"
        }
    ],
    "sg:phone":"+1 909 822 8200",
    "sg:postcode":"92335",
    "sg:province":"CA",
    "sg:tags":[
        "renting",
        "leasing",
        "trailer"
    ],
    "sg:website":"www.interstatetrlr.com",
    "wof:name":"Interstate Trailer Sales",
    "wof:placetype":"venue"
},
  "geometry": {"coordinates":[-117.497529,34.070172],"type":"Point"}
}