{
  "type": "Feature",
  "properties": {
    "addr:full":"14441 Fruitvale Rd Valley Center CA 92082",
    "addr:housenumber":"14441",
    "addr:postcode":"92082",
    "addr:street":"Fruitvale Rd",
    "iso:country":"US",
    "sg:address":"14441 Fruitvale Rd",
    "sg:city":"Valley Center",
    "sg:classifiers":[
        {
            "category":"Building & Trades",
            "subcategory":"Plumbing",
            "type":"Services"
        }
    ],
    "sg:phone":"+1 760 743 3119",
    "sg:postcode":"92082",
    "sg:province":"CA",
    "sg:tags":[
        "equipment",
        "solar",
        "contractor"
    ],
    "wof:name":"Energy Core",
    "wof:placetype":"venue"
},
  "geometry": {"coordinates":[-117.018839,33.241557],"type":"Point"}
}