{
  "type": "Feature",
  "properties": {
    "iso:country":"US",
    "sg:address":"1516 E Edinger Ave",
    "sg:city":"Santa Ana",
    "sg:classifiers":[
        {
            "category":"Manufacturing",
            "subcategory":"Tools & Machinery",
            "type":"Manufacturing & Wholesale Goods"
        }
    ],
    "sg:phone":"+1 949 651 8366",
    "sg:postcode":"92707",
    "sg:province":"CA",
    "sg:tags":[
        "assembly",
        "cable"
    ],
    "wof:name":"Market Vision",
    "wof:placetype":"venue"
},
  "geometry": {"coordinates":[-117.849642,33.726753],"type":"Point"}
}