{
  "type": "Feature",
  "properties": {
    "addr:full":"995 N Madeira Ave Salinas CA 93905",
    "addr:housenumber":"995",
    "addr:postcode":"93905",
    "addr:street":"N Madeira Ave",
    "iso:country":"US",
    "sg:address":"995 N Madeira Ave",
    "sg:city":"Salinas",
    "sg:classifiers":[
        {
            "category":"Organizations",
            "subcategory":"Religious Organization",
            "type":"Services"
        }
    ],
    "sg:phone":"+1 831 757 6504",
    "sg:postcode":"93905",
    "sg:province":"CA",
    "sg:tags":[
        "church"
    ],
    "wof:name":"East Salinas Family Ctr",
    "wof:placetype":"venue"
},
  "geometry": {"coordinates":[-121.627467,36.683213],"type":"Point"}
}