{
  "type": "Feature",
  "properties": {
    "iso:country":"US",
    "sg:address":"15431 Red Hill Ave",
    "sg:city":"Tustin",
    "sg:classifiers":[
        {
            "category":"Building & Trades",
            "subcategory":"Construction",
            "type":"Services"
        }
    ],
    "sg:phone":"+1 714 259 7660",
    "sg:postcode":"92780",
    "sg:province":"CA",
    "sg:tags":[
        "tile",
        "dealer"
    ],
    "wof:name":"Art Co",
    "wof:placetype":"venue"
},
  "geometry": {"coordinates":[-117.831906,33.717155],"type":"Point"}
}