{
  "type": "Feature",
  "properties": {
    "addr:full":"24724 Spruce St. Newhall CA 91321",
    "addr:housenumber":"24724",
    "addr:postcode":"91321",
    "addr:street":"Spruce St.",
    "iso:country":"US",
    "sg:address":"24724 Spruce St.",
    "sg:city":"Newhall",
    "sg:classifiers":[
        {
            "category":"Building & Trades",
            "subcategory":"Cleaning & Sanitation",
            "type":"Services"
        }
    ],
    "sg:phone":"+1 661 799 9853",
    "sg:postcode":"91321",
    "sg:province":"CA",
    "sg:tags":[
        "home"
    ],
    "wof:name":"Maids in Santa Clarita",
    "wof:placetype":"venue"
},
  "geometry": {"coordinates":[-118.532173,34.38443],"type":"Point"}
}