{
  "type": "Feature",
  "properties": {
    "addr:full":"8115 S Western Ave Los Angeles CA 90047",
    "addr:housenumber":"8115",
    "addr:postcode":"90047",
    "addr:street":"S Western Ave",
    "iso:country":"US",
    "sg:address":"8115 S Western Ave",
    "sg:city":"Los Angeles",
    "sg:classifiers":[
        {
            "category":"Real Estate",
            "subcategory":"Real Estate Agent",
            "type":"Services"
        }
    ],
    "sg:phone":"+1 323 752 8645",
    "sg:postcode":"90047",
    "sg:province":"CA",
    "wof:name":"Wright Properties",
    "wof:placetype":"venue"
},
  "geometry": {"coordinates":[-118.309076,33.964703],"type":"Point"}
}