{
  "type": "Feature",
  "properties": {
    "iso:country":"US",
    "sg:address":"1305 N Bascom Ave",
    "sg:city":"San Jose",
    "sg:classifiers":[
        {
            "category":"Health Services",
            "subcategory":"Health Practitioner",
            "type":"Services"
        }
    ],
    "sg:phone":"+1 408 483 3799",
    "sg:postcode":"95128",
    "sg:province":"CA",
    "sg:website":"www.litkinwellness.com",
    "wof:name":"Litkin Holistic Wellness Ctr",
    "wof:placetype":"venue"
},
  "geometry": {"coordinates":[-121.937914,37.337791],"type":"Point"}
}