{
  "type": "Feature",
  "properties": {
    "addr:full":"7101 Yorktown Avenue, Suite 101 Huntington Beach CA 92648",
    "addr:housenumber":"7101",
    "addr:postcode":"92648",
    "addr:street":"Yorktown Avenue Suite 101",
    "iso:country":"US",
    "sg:address":"7101 Yorktown Avenue, Suite 101",
    "sg:city":"Huntington Beach",
    "sg:classifiers":[
        {
            "category":"Education",
            "subcategory":"Dance Studio",
            "type":"Public Place"
        }
    ],
    "sg:phone":"+1 714 330 9001",
    "sg:postcode":"92648",
    "sg:province":"CA",
    "sg:website":"www.purebarre.com",
    "wof:name":"Pure Barre",
    "wof:placetype":"venue"
},
  "geometry": {"coordinates":[-118.003698,33.680697],"type":"Point"}
}