{
  "type": "Feature",
  "properties": {
    "addr:full":"1630 Geary Blvd San Francisco CA 94115",
    "addr:housenumber":"1630",
    "addr:postcode":"94115",
    "addr:street":"Geary Blvd",
    "iso:country":"US",
    "sg:address":"1630 Geary Blvd",
    "sg:city":"San Francisco",
    "sg:classifiers":[
        {
            "category":"Health Services",
            "subcategory":"Doctor",
            "type":"Services"
        }
    ],
    "sg:phone":"+1 415 563 0300",
    "sg:postcode":"94115",
    "sg:province":"CA",
    "wof:name":"Yang Joo Sock MD",
    "wof:placetype":"venue"
},
  "geometry": {"coordinates":[-122.429461,37.784991],"type":"Point"}
}