{
  "type": "Feature",
  "properties": {
    "addr:full":"1233 J Street Sacramento CA 95814",
    "addr:housenumber":"1233",
    "addr:postcode":"95814",
    "addr:street":"J Street",
    "iso:country":"US",
    "sg:address":"1233 J Street",
    "sg:city":"Sacramento",
    "sg:classifiers":[
        {
            "category":"Shopping",
            "subcategory":"Shoes",
            "type":"Retail Goods"
        }
    ],
    "sg:phone":"+1 916 444 9200",
    "sg:postcode":"95814",
    "sg:province":"CA",
    "sg:tags":[
        "store"
    ],
    "wof:name":"Jerry Sham Footwear",
    "wof:placetype":"venue"
},
  "geometry": {"coordinates":[-121.489396,38.579355],"type":"Point"}
}