{
  "type": "Feature",
  "properties": {
    "iso:country":"US",
    "sg:address":"307 Orchard City Dr Ste 107",
    "sg:city":"Campbell",
    "sg:classifiers":[
        {
            "category":"Professional",
            "subcategory":"Engineering",
            "type":"Services"
        }
    ],
    "sg:phone":"+1 408 374 6149",
    "sg:postcode":"95008",
    "sg:province":"CA",
    "sg:tags":[
        "civil",
        "consulting",
        "structural",
        "engineer"
    ],
    "sg:website":"http://www.jakabyse.com",
    "wof:name":"Jakaby Engineering",
    "wof:placetype":"venue"
},
  "geometry": {"coordinates":[-121.94358099999999,37.28619],"type":"Point"}
}