{
  "type": "Feature",
  "properties": {
    "iso:country":"US",
    "sg:address":"9548 Frankirst Ave",
    "sg:city":"North Hills",
    "sg:classifiers":[
        {
            "category":"Food & Beverages",
            "subcategory":"Specialty",
            "type":"Retail Goods"
        }
    ],
    "sg:phone":"+1 818 993 8111",
    "sg:postcode":"91343",
    "sg:province":"CA",
    "sg:tags":[
        "vitamin"
    ],
    "sg:website":"www.naturalhorizons.net",
    "wof:name":"Natural Horizons",
    "wof:placetype":"venue"
},
  "geometry": {"coordinates":[-118.488789,34.244045],"type":"Point"}
}