{
  "type": "Feature",
  "properties": {
    "addr:full":"8447 Miramar Mall San Diego CA 92121",
    "addr:housenumber":"8447",
    "addr:postcode":"92121",
    "addr:street":"Miramar Mall",
    "iso:country":"US",
    "sg:address":"8447 Miramar Mall",
    "sg:city":"San Diego",
    "sg:classifiers":[
        {
            "category":"Insurance",
            "subcategory":"Insurance Agent",
            "type":"Services"
        }
    ],
    "sg:phone":"+1 858 535 9444",
    "sg:postcode":"92121",
    "sg:province":"CA",
    "sg:website":"www.cpsimis.com",
    "wof:name":"Integrated Marketing",
    "wof:placetype":"venue"
},
  "geometry": {"coordinates":[-117.18274599999999,32.878282],"type":"Point"}
}