{
  "type": "Feature",
  "properties": {
    "iso:country":"US",
    "sg:address":"121 E Orangeburg Ave",
    "sg:city":"Modesto",
    "sg:classifiers":[
        {
            "category":"Insurance",
            "subcategory":"Insurance Agent",
            "type":"Services"
        }
    ],
    "sg:phone":"+1 209 575 4536",
    "sg:postcode":"95350",
    "sg:province":"CA",
    "wof:name":"Crivelli Insurance",
    "wof:placetype":"venue"
},
  "geometry": {"coordinates":[-120.99153800000001,37.663721],"type":"Point"}
}