{
  "type": "Feature",
  "properties": {
    "addr:full":"6440 Bellingham Ave North Hollywood CA 91606",
    "addr:housenumber":"6440",
    "addr:postcode":"91606",
    "addr:street":"Bellingham Ave",
    "iso:country":"US",
    "sg:address":"6440 Bellingham Ave",
    "sg:city":"North Hollywood",
    "sg:classifiers":[
        {
            "category":"Shopping",
            "subcategory":"Stationery & Office Supplies",
            "type":"Retail Goods"
        }
    ],
    "sg:phone":"+1 818 766 7117",
    "sg:postcode":"91606",
    "sg:province":"CA",
    "sg:tags":[
        "equipment"
    ],
    "wof:name":"Bush's Stationers",
    "wof:placetype":"venue"
},
  "geometry": {"coordinates":[-118.39856399999999,34.187418],"type":"Point"}
}