{
  "type": "Feature",
  "properties": {
    "iso:country":"US",
    "sg:address":"1700 Hamner Ave",
    "sg:city":"Norco",
    "sg:classifiers":[
        {
            "category":"Farming",
            "subcategory":"Livestock Farm",
            "type":"Manufacturing & Wholesale Goods"
        }
    ],
    "sg:phone":"+1 951 280 0348",
    "sg:postcode":"92860",
    "sg:province":"CA",
    "sg:tags":[
        "ranch"
    ],
    "wof:name":"Royal Palm Ranch HOA",
    "wof:placetype":"venue"
},
  "geometry": {"coordinates":[-117.562005,33.903791],"type":"Point"}
}