{
  "type": "Feature",
  "properties": {
    "addr:full":"150 S Main St Lakeport CA 95453",
    "addr:housenumber":"150",
    "addr:postcode":"95453",
    "addr:street":"S Main St",
    "iso:country":"US",
    "sg:address":"150 S Main St",
    "sg:city":"Lakeport",
    "sg:classifiers":[
        {
            "category":"Banks & Credit Unions",
            "subcategory":"Bank",
            "type":"Services"
        }
    ],
    "sg:phone":"+1 707 262 5714",
    "sg:postcode":"95453",
    "sg:province":"CA",
    "sg:tags":[
        "commercial",
        "national",
        "saving"
    ],
    "sg:website":"http://www.westamerica.com/",
    "wof:name":"Westamerica Bank",
    "wof:placetype":"venue"
},
  "geometry": {"coordinates":[-122.915199,39.041522],"type":"Point"}
}