{
  "type": "Feature",
  "properties": {
    "addr:full":"303 W Sunview Ave Palm Springs CA 92262",
    "addr:housenumber":"303",
    "addr:postcode":"92262",
    "addr:street":"W Sunview Ave",
    "iso:country":"US",
    "sg:address":"303 W Sunview Ave",
    "sg:city":"Palm Springs",
    "sg:classifiers":[
        {
            "category":"Building & Trades",
            "subcategory":"Cleaning & Sanitation",
            "type":"Services"
        }
    ],
    "sg:phone":"+1 760 322 8880",
    "sg:postcode":"92262",
    "sg:province":"CA",
    "sg:tags":[
        "janitor"
    ],
    "wof:name":"Clean-Up Woman",
    "wof:placetype":"venue"
},
  "geometry": {"coordinates":[-116.54904500000001,33.865953],"type":"Point"}
}