{
  "type": "Feature",
  "properties": {
    "iso:country":"US",
    "sg:address":"16851 Victory Blvd",
    "sg:city":"Van Nuys",
    "sg:classifiers":[
        {
            "category":"Food & Beverages",
            "subcategory":"Bakery",
            "type":"Retail Goods"
        }
    ],
    "sg:phone":"+1 818 781 0961",
    "sg:postcode":"91406",
    "sg:province":"CA",
    "sg:tags":[
        "product",
        "eating",
        "doughnut",
        "mfg"
    ],
    "wof:name":"Stop In Donut",
    "wof:placetype":"venue"
},
  "geometry": {"coordinates":[-118.50028,34.186703],"type":"Point"}
}