{
  "type": "Feature",
  "properties": {
    "iso:country":"US",
    "sg:address":"2088 Wayne Ave",
    "sg:city":"San Leandro",
    "sg:classifiers":[
        {
            "category":"Wholesale",
            "subcategory":"Auto Parts",
            "type":"Manufacturing & Wholesale Goods"
        }
    ],
    "sg:phone":"+1 510 895 9929",
    "sg:postcode":"94577",
    "sg:province":"CA",
    "sg:tags":[
        "body",
        "automobile",
        "shop"
    ],
    "wof:name":"Finish Master",
    "wof:placetype":"venue"
},
  "geometry": {"coordinates":[-122.16296,37.713021],"type":"Point"}
}