{
  "type": "Feature",
  "properties": {
    "addr:full":"215 24th St Richmond CA 94804",
    "addr:housenumber":"215",
    "addr:postcode":"94804",
    "addr:street":"24Th St",
    "iso:country":"US",
    "sg:address":"215 24th St",
    "sg:city":"Richmond",
    "sg:classifiers":[
        {
            "category":"Retail",
            "subcategory":"Auto Repair",
            "type":"Services"
        }
    ],
    "sg:phone":"+1 510 215 5460",
    "sg:postcode":"94804",
    "sg:province":"CA",
    "sg:tags":[
        "muffler",
        "exhaust",
        "system"
    ],
    "wof:name":"Mr Muffler",
    "wof:placetype":"venue"
},
  "geometry": {"coordinates":[-122.34657900000001,37.934414],"type":"Point"}
}