{
  "type": "Feature",
  "properties": {
    "iso:country":"US",
    "sg:address":"2390 W Pico Blvd",
    "sg:city":"Los Angeles",
    "sg:classifiers":[
        {
            "category":"Government",
            "subcategory":"Post Office",
            "type":"Public Place"
        }
    ],
    "sg:postcode":"90006",
    "sg:province":"CA",
    "wof:name":"USPS",
    "wof:placetype":"venue"
},
  "geometry": {"coordinates":[-118.28885,34.046967],"type":"Point"}
}