{
  "type": "Feature",
  "properties": {
    "iso:country":"US",
    "sg:address":"241 Lake Blvd",
    "sg:city":"Redding",
    "sg:classifiers":[
        {
            "category":"Retail",
            "subcategory":"Self-service Laundry",
            "type":"Services"
        }
    ],
    "sg:phone":"+1 530 244 4480",
    "sg:postcode":"96003",
    "sg:province":"CA",
    "wof:name":"H & H Laundromat",
    "wof:placetype":"venue"
},
  "geometry": {"coordinates":[-122.379896,40.610342],"type":"Point"}
}