{
  "type": "Feature",
  "properties": {
    "iso:country":"US",
    "sg:address":"12707 Trent Jones Ln",
    "sg:city":"Tustin",
    "sg:classifiers":[
        {
            "category":"Manufacturing",
            "subcategory":"Chemicals & Compounds",
            "type":"Manufacturing & Wholesale Goods"
        }
    ],
    "sg:phone":"+1 714 838 7521",
    "sg:postcode":"92782",
    "sg:province":"CA",
    "sg:tags":[
        "industrial",
        "organic",
        "mfg"
    ],
    "wof:name":"Alanna Ward",
    "wof:placetype":"venue"
},
  "geometry": {"coordinates":[-117.781237,33.734656],"type":"Point"}
}