{
  "type": "Feature",
  "properties": {
    "addr:full":"777 E Ocean Blvd Long Beach CA 90802",
    "addr:housenumber":"777",
    "addr:postcode":"90802",
    "addr:street":"E Ocean Blvd",
    "iso:country":"US",
    "sg:address":"777 E Ocean Blvd",
    "sg:city":"Long Beach",
    "sg:classifiers":[
        {
            "category":"Cinema",
            "subcategory":"Movie Rental",
            "type":"Entertainment"
        }
    ],
    "sg:phone":"+1 562 435 8557",
    "sg:postcode":"90802",
    "sg:province":"CA",
    "sg:tags":[
        "video",
        "game",
        "disc",
        "leasing",
        "tape"
    ],
    "wof:name":"Video Choice",
    "wof:placetype":"venue"
},
  "geometry": {"coordinates":[-118.182999,33.766399],"type":"Point"}
}