{
  "type": "Feature",
  "properties": {
    "addr:full":"8690 Aero Dr San Diego CA 92123",
    "addr:housenumber":"8690",
    "addr:postcode":"92123",
    "addr:street":"Aero Dr",
    "iso:country":"US",
    "sg:address":"8690 Aero Dr",
    "sg:city":"San Diego",
    "sg:classifiers":[
        {
            "category":"Shopping",
            "subcategory":"Computers & Home Electronics",
            "type":"Retail Goods"
        }
    ],
    "sg:phone":"+1 858 569 5220",
    "sg:postcode":"92123",
    "sg:province":"CA",
    "sg:website":"www.marvgolden.com",
    "wof:name":"Marv Golden Pilot Supplies",
    "wof:placetype":"venue"
},
  "geometry": {"coordinates":[-117.140851,32.809749],"type":"Point"}
}