{
  "type": "Feature",
  "properties": {
    "iso:country":"US",
    "sg:address":"526 Lakeport Blvd",
    "sg:city":"Lakeport",
    "sg:classifiers":[
        {
            "category":"Shopping",
            "subcategory":"Clothing, Apparel, & Fashions",
            "type":"Retail Goods"
        }
    ],
    "sg:phone":"+1 707 263 0868",
    "sg:postcode":"95453",
    "sg:province":"CA",
    "sg:tags":[
        "infant",
        "wear"
    ],
    "wof:name":"Phillips' Rugrat Reruns",
    "wof:placetype":"venue"
},
  "geometry": {"coordinates":[-122.919567,39.03474],"type":"Point"}
}