{
  "type": "Feature",
  "properties": {
    "addr:full":"1818 Tully Rd San Jose CA 95122",
    "addr:housenumber":"1818",
    "addr:postcode":"95122",
    "addr:street":"Tully Rd",
    "iso:country":"US",
    "sg:address":"1818 Tully Rd",
    "sg:city":"San Jose",
    "sg:classifiers":[
        {
            "category":"Bakery",
            "type":"Food & Drink"
        }
    ],
    "sg:phone":"+1 408 274 6669",
    "sg:postcode":"95122",
    "sg:province":"CA",
    "sg:website":"www.eurodelightsbakery.com/",
    "wof:name":"Euro Delight Bakery",
    "wof:placetype":"venue"
},
  "geometry": {"coordinates":[-121.824997,37.323101],"type":"Point"}
}