{
  "type": "Feature",
  "properties": {
    "iso:country":"US",
    "sg:address":"11595 Coleman Ln",
    "sg:city":"Marysville",
    "sg:classifiers":[
        {
            "category":"Building & Trades",
            "subcategory":"Construction",
            "type":"Services"
        }
    ],
    "sg:phone":"+1 530 742 4253",
    "sg:postcode":"95901",
    "sg:province":"CA",
    "sg:tags":[
        "house"
    ],
    "wof:name":"Coleman Construction Co",
    "wof:placetype":"venue"
},
  "geometry": {"coordinates":[-121.411804,39.296504],"type":"Point"}
}