{
  "type": "Feature",
  "properties": {
    "iso:country":"US",
    "sg:address":"7250 Fulton Ave",
    "sg:city":"North Hollywood",
    "sg:classifiers":[
        {
            "category":"Wholesale",
            "subcategory":"Hardware",
            "type":"Manufacturing & Wholesale Goods"
        }
    ],
    "sg:phone":"+1 818 982 9538",
    "sg:postcode":"91605",
    "sg:province":"CA",
    "sg:tags":[
        "nut",
        "bolt"
    ],
    "wof:name":"Totally Nuts & Bolts",
    "wof:placetype":"venue"
},
  "geometry": {"coordinates":[-118.42245200000001,34.20544],"type":"Point"}
}