{
  "type": "Feature",
  "properties": {
    "iso:country":"US",
    "sg:address":"5356 Clayton Rd Ste 101",
    "sg:city":"Concord",
    "sg:classifiers":[
        {
            "category":"Insurance",
            "subcategory":"Title Insurance",
            "type":"Services"
        }
    ],
    "sg:phone":"+1 925 689 3331",
    "sg:postcode":"94521",
    "sg:province":"CA",
    "sg:tags":[
        "mortgage"
    ],
    "wof:name":"Placer Title",
    "wof:placetype":"venue"
},
  "geometry": {"coordinates":[-121.959791,37.952913],"type":"Point"}
}