{
  "type": "Feature",
  "properties": {
    "addr:full":"855 Elm Ave Long Beach CA 90813",
    "addr:housenumber":"855",
    "addr:postcode":"90813",
    "addr:street":"Elm Ave",
    "iso:country":"US",
    "sg:address":"855 Elm Ave",
    "sg:city":"Long Beach",
    "sg:classifiers":[
        {
            "category":"Organizations",
            "subcategory":"Non-profit Organization",
            "type":"Services"
        }
    ],
    "sg:phone":"+1 562 436 3983",
    "sg:postcode":"90813",
    "sg:province":"CA",
    "sg:tags":[
        "venue",
        "event",
        "space"
    ],
    "sg:website":"www.lbscottishrite.org/lbeventce...",
    "wof:name":"Scottish Rite Cathedral",
    "wof:placetype":"venue"
},
  "geometry": {"coordinates":[-118.18800400000001,33.7775],"type":"Point"}
}