{
  "type": "Feature",
  "properties": {
    "addr:full":"250 N Linden Ave Rialto CA 92376",
    "addr:housenumber":"250",
    "addr:postcode":"92376",
    "addr:street":"N Linden Ave",
    "iso:country":"US",
    "sg:address":"250 N Linden Ave",
    "sg:city":"Rialto",
    "sg:classifiers":[
        {
            "category":"Professional",
            "type":"Services"
        }
    ],
    "sg:phone":"+1 909 355 9303",
    "sg:postcode":"92376",
    "sg:province":"CA",
    "sg:tags":[
        "establishment"
    ],
    "wof:name":"U Been Served",
    "wof:placetype":"venue"
},
  "geometry": {"coordinates":[-117.401015,34.102642],"type":"Point"}
}