{
  "type": "Feature",
  "properties": {
    "iso:country":"US",
    "sg:address":"1821 W Lancaster Blvd",
    "sg:city":"Lancaster",
    "sg:classifiers":[
        {
            "category":"Organizations",
            "subcategory":"Religious Organization",
            "type":"Services"
        }
    ],
    "sg:phone":"+1 661 948 4115",
    "sg:postcode":"93534",
    "sg:province":"CA",
    "sg:tags":[
        "church"
    ],
    "sg:website":"www.oslclan.com",
    "wof:name":"Our Savior's Lutheran Church",
    "wof:placetype":"venue"
},
  "geometry": {"coordinates":[-118.16309200000001,34.696795],"type":"Point"}
}