{
  "type": "Feature",
  "properties": {
    "iso:country":"US",
    "sg:address":"290 N Palm Canyon Dr",
    "sg:city":"Palm Springs",
    "sg:classifiers":[
        {
            "category":"Shopping",
            "subcategory":"Shoes",
            "type":"Retail Goods"
        }
    ],
    "sg:phone":"+1 760 322 4141",
    "sg:postcode":"92262",
    "sg:province":"CA",
    "wof:name":"Fore's Fun Footwear",
    "wof:placetype":"venue"
},
  "geometry": {"coordinates":[-116.546752,33.826569],"type":"Point"}
}