{
  "type": "Feature",
  "properties": {
    "addr:full":"2 E Valley Blvd Ste 1D Alhambra CA 91801",
    "addr:housenumber":"2",
    "addr:postcode":"91801",
    "addr:street":"E Valley Blvd Ste 1D",
    "iso:country":"US",
    "sg:address":"2 E Valley Blvd Ste 1D",
    "sg:city":"Alhambra",
    "sg:classifiers":[
        {
            "category":"Personal",
            "subcategory":"Massage",
            "type":"Services"
        }
    ],
    "sg:phone":"+1 626 280 0699",
    "sg:postcode":"91801",
    "sg:province":"CA",
    "sg:website":"www.orientalnaturaltreatment.com/",
    "wof:name":"Oriental Natural Treatment",
    "wof:placetype":"venue"
},
  "geometry": {"coordinates":[-118.12268299999999,34.078185],"type":"Point"}
}