{
  "type": "Feature",
  "properties": {
    "addr:full":"375 Bristol Ste 95 Costa Mesa CA 92626",
    "addr:housenumber":"375",
    "addr:postcode":"92626",
    "addr:street":"Bristol Ste 95",
    "iso:country":"US",
    "sg:address":"375 Bristol Ste 95",
    "sg:city":"Costa Mesa",
    "sg:classifiers":[
        {
            "category":"Retail",
            "subcategory":"Auto Repair",
            "type":"Services"
        }
    ],
    "sg:phone":"+1 714 210 2525",
    "sg:postcode":"92626",
    "sg:province":"CA",
    "sg:website":"www.competitiongt.com",
    "wof:name":"Competition GT",
    "wof:placetype":"venue"
},
  "geometry": {"coordinates":[-117.87963000000001,33.664368],"type":"Point"}
}