{
  "type": "Feature",
  "properties": {
    "addr:full":"40665 Fremont Blvd Fremont CA 94538",
    "addr:housenumber":"40665",
    "addr:postcode":"94538",
    "addr:street":"Fremont Blvd",
    "iso:country":"US",
    "sg:address":"40665 Fremont Blvd",
    "sg:city":"Fremont",
    "sg:classifiers":[
        {
            "category":"Banks & Credit Unions",
            "subcategory":"Bank",
            "type":"Services"
        }
    ],
    "sg:phone":"+1 510 226 2780",
    "sg:postcode":"94538",
    "sg:province":"CA",
    "sg:tags":[
        "savings",
        "loan",
        "association"
    ],
    "wof:name":"Bank Of America",
    "wof:placetype":"venue"
},
  "geometry": {"coordinates":[-121.964867,37.536046],"type":"Point"}
}