{
  "type": "Feature",
  "properties": {
    "addr:full":"6801 Curved Bridge Rd Rio Linda CA 95673",
    "addr:housenumber":"6801",
    "addr:postcode":"95673",
    "addr:street":"Curved Bridge Rd",
    "iso:country":"US",
    "sg:address":"6801 Curved Bridge Rd",
    "sg:city":"Rio Linda",
    "sg:classifiers":[
        {
            "category":"Real Estate",
            "subcategory":"Real Estate Agent",
            "type":"Services"
        }
    ],
    "sg:phone":"+1 916 992 6585",
    "sg:postcode":"95673",
    "sg:province":"CA",
    "wof:name":"Charles Pott's Real Estate",
    "wof:placetype":"venue"
},
  "geometry": {"coordinates":[-121.443434,38.691876],"type":"Point"}
}