{
  "type": "Feature",
  "properties": {
    "addr:full":"10 Miller St Bodfish CA 93205",
    "addr:housenumber":"10",
    "addr:postcode":"93205",
    "addr:street":"Miller St",
    "iso:country":"US",
    "sg:address":"10 Miller St",
    "sg:city":"Bodfish",
    "sg:classifiers":[
        {
            "category":"Food & Beverages",
            "subcategory":"Groceries & Convenience Stores",
            "type":"Retail Goods"
        }
    ],
    "sg:phone":"+1 760 379 5151",
    "sg:postcode":"93205",
    "sg:province":"CA",
    "sg:tags":[
        "grocer"
    ],
    "wof:name":"Country Korner Market",
    "wof:placetype":"venue"
},
  "geometry": {"coordinates":[-118.496368,35.592074],"type":"Point"}
}