{
  "type": "Feature",
  "properties": {
    "iso:country":"US",
    "sg:address":"7372 Prince Drive",
    "sg:city":"Huntington Beach",
    "sg:classifiers":[
        {
            "category":"Building & Trades",
            "subcategory":"Construction",
            "type":"Services"
        }
    ],
    "sg:phone":"+1 714 847 0469",
    "sg:postcode":"92647",
    "sg:province":"CA",
    "sg:tags":[
        "roofing",
        "contractor"
    ],
    "wof:name":"Gonterman Construction Corporation",
    "wof:placetype":"venue"
},
  "geometry": {"coordinates":[-117.99961,33.717935],"type":"Point"}
}