{
  "type": "Feature",
  "properties": {
    "iso:country":"US",
    "sg:address":"3720 W Pico Boulevard",
    "sg:city":"Los Angeles",
    "sg:classifiers":[
        {
            "category":"Food & Beverages",
            "subcategory":"Groceries & Convenience Stores",
            "type":"Retail Goods"
        }
    ],
    "sg:phone":"+1 323 735 0808",
    "sg:postcode":"90019",
    "sg:province":"CA",
    "wof:name":"Pico Market",
    "wof:placetype":"venue"
},
  "geometry": {"coordinates":[-118.321681,34.047473],"type":"Point"}
}