{
  "type": "Feature",
  "properties": {
    "iso:country":"US",
    "sg:address":"12729 Foothill Blvd",
    "sg:city":"Etiwanda",
    "sg:classifiers":[
        {
            "category":"Health Services",
            "subcategory":"Doctor",
            "type":"Services"
        }
    ],
    "sg:phone":"+1 909 899 8757",
    "sg:postcode":"91730",
    "sg:province":"CA",
    "sg:tags":[
        "dentist"
    ],
    "wof:name":"Star Dental Group",
    "wof:placetype":"venue"
},
  "geometry": {"coordinates":[-117.529038,34.106239],"type":"Point"}
}