{
  "type": "Feature",
  "properties": {
    "iso:country":"US",
    "sg:address":"16701 Highline Rd",
    "sg:city":"Tehachapi",
    "sg:classifiers":[
        {
            "category":"Farming",
            "subcategory":"Orchard",
            "type":"Manufacturing & Wholesale Goods"
        }
    ],
    "sg:phone":"+1 661 822 6510",
    "sg:postcode":"93561",
    "sg:province":"CA",
    "sg:tags":[
        "fruit",
        "tree"
    ],
    "wof:name":"Tehachapi Summit Orchard",
    "wof:placetype":"venue"
},
  "geometry": {"coordinates":[-118.429466,35.109804],"type":"Point"}
}