{
  "type": "Feature",
  "properties": {
    "addr:full":"765 Oddstad Blvd Pacifica CA 94044",
    "addr:housenumber":"765",
    "addr:postcode":"94044",
    "addr:street":"Oddstad Blvd",
    "iso:country":"US",
    "sg:address":"765 Oddstad Blvd",
    "sg:city":"Pacifica",
    "sg:phone":"+1 650 557 2608",
    "sg:postcode":"94044",
    "sg:province":"CA",
    "sg:website":"http://clickserve.dartsearch.net/link/click?lid=43000000313867603&ds_s_kwgid=58000000006820725&ds_e_matchtype={MatchType}&ds_e_kwdid={OrderItemId}&ds_e_adid={AdId}&ds_url_v=2",
    "wof:name":"Pacifica 76",
    "wof:placetype":"venue"
},
  "geometry": {"coordinates":[-122.47407699999999,37.583448],"type":"Point"}
}