{
  "type": "Feature",
  "properties": {
    "addr:full":"4537 W Ave L Quartz Hill CA 93536",
    "addr:housenumber":"4537",
    "addr:postcode":"93536",
    "addr:street":"W Ave L Quartz Hill",
    "iso:country":"US",
    "sg:address":"4537 W Ave L",
    "sg:city":"Quartz Hill",
    "sg:classifiers":[
        {
            "category":"Building & Trades",
            "subcategory":"Construction",
            "type":"Services"
        }
    ],
    "sg:phone":"+1 661 722 5781",
    "sg:postcode":"93536",
    "sg:province":"CA",
    "sg:tags":[
        "contractor"
    ],
    "wof:name":"D M Milstead General Contr",
    "wof:placetype":"venue"
},
  "geometry": {"coordinates":[-118.21088399999999,34.660289],"type":"Point"}
}