{
  "type": "Feature",
  "properties": {
    "addr:full":"2925 Niagra St Turlock CA 95382",
    "addr:housenumber":"2925",
    "addr:postcode":"95382",
    "addr:street":"Niagra St",
    "iso:country":"US",
    "sg:address":"2925 Niagra St",
    "sg:city":"Turlock",
    "sg:classifiers":[
        {
            "category":"Health Services",
            "subcategory":"Chiropractor",
            "type":"Services"
        }
    ],
    "sg:phone":"+1 209 634 9381",
    "sg:postcode":"95382",
    "sg:province":"CA",
    "wof:name":"Niagra Chiropractic Clinic",
    "wof:placetype":"venue"
},
  "geometry": {"coordinates":[-120.850927,37.51961],"type":"Point"}
}