{
  "type": "Feature",
  "properties": {
    "addr:full":"1220 S McDonnell Ave Los Angeles CA 90022",
    "addr:housenumber":"1220",
    "addr:postcode":"90022",
    "addr:street":"S Mcdonnell Ave",
    "iso:country":"US",
    "sg:address":"1220 S McDonnell Ave",
    "sg:city":"Los Angeles",
    "sg:classifiers":[
        {
            "category":"Professional",
            "subcategory":"Business Services",
            "type":"Services"
        }
    ],
    "sg:phone":"+1 323 780 6213",
    "sg:postcode":"90022",
    "sg:province":"CA",
    "sg:tags":[
        "consultant",
        "production",
        "music"
    ],
    "wof:name":"One Man Band Production Inc",
    "wof:placetype":"venue"
},
  "geometry": {"coordinates":[-118.169372,34.017781],"type":"Point"}
}