{
  "type": "Feature",
  "properties": {
    "iso:country":"US",
    "sg:address":"344 F St",
    "sg:city":"Chula Vista",
    "sg:classifiers":[
        {
            "category":"Professional",
            "type":"Services"
        }
    ],
    "sg:phone":"+1 619 427 1592",
    "sg:postcode":"91910",
    "sg:province":"CA",
    "wof:name":"Title Co",
    "wof:placetype":"venue"
},
  "geometry": {"coordinates":[-117.081518,32.640748],"type":"Point"}
}