{
  "type": "Feature",
  "properties": {
    "addr:full":"2473 Whittier Boulevard Los Angeles CA 90023",
    "addr:housenumber":"2473",
    "addr:postcode":"90023",
    "addr:street":"Whittier Boulevard",
    "iso:country":"US",
    "sg:address":"2473 Whittier Boulevard",
    "sg:city":"Los Angeles",
    "sg:classifiers":[
        {
            "category":"Shopping",
            "subcategory":"Bicycles & Sporting Goods",
            "type":"Retail Goods"
        }
    ],
    "sg:phone":"+1 323 267 1041",
    "sg:postcode":"90023",
    "sg:province":"CA",
    "wof:name":"Jimmy Sport",
    "wof:placetype":"venue"
},
  "geometry": {"coordinates":[-118.21410400000001,34.033799],"type":"Point"}
}