{
  "type": "Feature",
  "properties": {
    "addr:full":"25651 Taladro Cir Mission Viejo CA 92691",
    "addr:postcode":"25651;92691",
    "addr:street":"Taladro Cir",
    "iso:country":"US",
    "sg:address":"25651 Taladro Cir",
    "sg:city":"Mission Viejo",
    "sg:classifiers":[
        {
            "category":"Autos & Motor Vehicles",
            "subcategory":"Auto Supplies",
            "type":"Retail Goods"
        }
    ],
    "sg:phone":"+1 949 922 1383",
    "sg:postcode":"92691",
    "sg:province":"CA",
    "sg:tags":[
        "glass"
    ],
    "sg:website":"alfaautoglass.com",
    "wof:name":"Alfa Auto Glass",
    "wof:placetype":"venue"
},
  "geometry": {"coordinates":[-117.683193,33.619842],"type":"Point"}
}