{
  "type": "Feature",
  "properties": {
    "iso:country":"US",
    "sg:address":"1081 Post St",
    "sg:city":"San Francisco",
    "sg:classifiers":[
        {
            "category":"Recreation",
            "subcategory":"Dance Hall",
            "type":"Entertainment"
        }
    ],
    "sg:phone":"+1 415 474 3482",
    "sg:postcode":"94109",
    "sg:province":"CA",
    "sg:tags":[
        "club"
    ],
    "sg:website":"www.divassf.com",
    "wof:name":"Divas Nightclub & Bar",
    "wof:placetype":"venue"
},
  "geometry": {"coordinates":[-122.419487,37.78662],"type":"Point"}
}