{
  "type": "Feature",
  "properties": {
    "iso:country":"US",
    "sg:address":"24551 Raymond Way",
    "sg:city":"Lake Forest",
    "sg:classifiers":[
        {
            "category":"Professional",
            "subcategory":"Employment Agencies",
            "type":"Services"
        }
    ],
    "sg:phone":"+1 949 452 0629",
    "sg:postcode":"92630",
    "sg:province":"CA",
    "sg:tags":[
        "opportunity"
    ],
    "wof:name":"TLC Nanny Svc",
    "wof:placetype":"venue"
},
  "geometry": {"coordinates":[-117.701846,33.622279],"type":"Point"}
}