{
  "type": "Feature",
  "properties": {
    "iso:country":"US",
    "sg:address":"4430 Jewell Street",
    "sg:city":"San Diego",
    "sg:classifiers":[
        {
            "category":"Real Estate",
            "subcategory":"Real Estate Operator",
            "type":"Services"
        }
    ],
    "sg:phone":"+1 858 270 6380",
    "sg:postcode":"92109",
    "sg:province":"CA",
    "sg:tags":[
        "apartment"
    ],
    "wof:name":"Bahaia Jewell Apartments",
    "wof:placetype":"venue"
},
  "geometry": {"coordinates":[-117.238589,32.798911],"type":"Point"}
}