{
  "type": "Feature",
  "properties": {
    "iso:country":"US",
    "sg:address":"907 Chateau Dr",
    "sg:city":"Modesto",
    "sg:classifiers":[
        {
            "category":"Shopping",
            "subcategory":"Catalog Store",
            "type":"Retail Goods"
        }
    ],
    "sg:phone":"+1 209 527 1844",
    "sg:postcode":"95355",
    "sg:province":"CA",
    "sg:tags":[
        "mail",
        "house"
    ],
    "wof:name":"S O S Stamps",
    "wof:placetype":"venue"
},
  "geometry": {"coordinates":[-120.955411,37.656427],"type":"Point"}
}