{
  "type": "Feature",
  "properties": {
    "iso:country":"US",
    "sg:address":"11518 York Ave",
    "sg:city":"Hawthorne",
    "sg:classifiers":[
        {
            "category":"Personal",
            "subcategory":"Nail Salon",
            "type":"Services"
        }
    ],
    "sg:phone":"+1 310 675 1416",
    "sg:postcode":"90250",
    "sg:province":"CA",
    "wof:name":"Lovely Are You",
    "wof:placetype":"venue"
},
  "geometry": {"coordinates":[-118.345015,33.9295],"type":"Point"}
}