{
  "type": "Feature",
  "properties": {
    "addr:full":"2020 Forest Ave San Jose CA 95128",
    "addr:housenumber":"2020",
    "addr:postcode":"95128",
    "addr:street":"Forest Ave",
    "iso:country":"US",
    "sg:address":"2020 Forest Ave",
    "sg:city":"San Jose",
    "sg:classifiers":[
        {
            "category":"Professional",
            "subcategory":"Lawyer & Legal Services",
            "type":"Services"
        }
    ],
    "sg:phone":"+1 408 938 3410",
    "sg:postcode":"95128",
    "sg:province":"CA",
    "sg:tags":[
        "attorney"
    ],
    "wof:name":"Senior Advocate Law Offices",
    "wof:placetype":"venue"
},
  "geometry": {"coordinates":[-121.932199,37.326977],"type":"Point"}
}