{
  "type": "Feature",
  "properties": {
    "addr:full":"540 E Foothill Blvd San Dimas CA 91773",
    "addr:housenumber":"540",
    "addr:postcode":"91773",
    "addr:street":"E Foothill Blvd",
    "iso:country":"US",
    "sg:address":"540 E Foothill Blvd",
    "sg:city":"San Dimas",
    "sg:classifiers":[
        {
            "category":"Professional",
            "subcategory":"Accounting & Tax Preparation",
            "type":"Services"
        }
    ],
    "sg:phone":"+1 909 305 0211",
    "sg:postcode":"91773",
    "sg:province":"CA",
    "sg:tags":[
        "accountant"
    ],
    "wof:name":"Earl B Macasaet CPA",
    "wof:placetype":"venue"
},
  "geometry": {"coordinates":[-117.797738,34.12299],"type":"Point"}
}