{
  "type": "Feature",
  "properties": {
    "addr:full":"2359 Myers St Oroville CA 95966",
    "addr:housenumber":"2359",
    "addr:postcode":"95966",
    "addr:street":"Myers St",
    "iso:country":"US",
    "sg:address":"2359 Myers St",
    "sg:city":"Oroville",
    "sg:classifiers":[
        {
            "category":"Personal",
            "subcategory":"Beauty Salon",
            "type":"Services"
        }
    ],
    "sg:phone":"+1 530 532 1500",
    "sg:postcode":"95966",
    "sg:province":"CA",
    "wof:name":"Cut 4U",
    "wof:placetype":"venue"
},
  "geometry": {"coordinates":[-121.550954,39.506408],"type":"Point"}
}