{
  "type": "Feature",
  "properties": {
    "addr:full":"22757 Ventura Blvd Woodland Hills CA 91364",
    "addr:housenumber":"22757",
    "addr:postcode":"91364",
    "addr:street":"Ventura Blvd",
    "iso:country":"US",
    "sg:address":"22757 Ventura Blvd",
    "sg:city":"Woodland Hills",
    "sg:classifiers":[
        {
            "category":"Restaurant",
            "type":"Food & Drink"
        }
    ],
    "sg:phone":"+1 818 225 9114",
    "sg:postcode":"91364",
    "sg:province":"CA",
    "sg:tags":[
        "french"
    ],
    "wof:name":"Brandywine",
    "wof:placetype":"venue"
},
  "geometry": {"coordinates":[-118.623001,34.166],"type":"Point"}
}