{
  "type": "Feature",
  "properties": {
    "addr:full":"100 N 1st St #404 Burbank CA 91502",
    "addr:housenumber":"100",
    "addr:postcode":"91502",
    "addr:street":"N 1St St # 404",
    "iso:country":"US",
    "sg:address":"100 N 1st St #404",
    "sg:city":"Burbank",
    "sg:classifiers":[
        {
            "category":"Real Estate",
            "subcategory":"Real Estate Services",
            "type":"Services"
        }
    ],
    "sg:phone":"+1 818 382 9889",
    "sg:postcode":"91502",
    "sg:province":"CA",
    "wof:name":"California Title Company",
    "wof:placetype":"venue"
},
  "geometry": {"coordinates":[-118.31003,34.180156],"type":"Point"}
}