{
  "type": "Feature",
  "properties": {
    "iso:country":"US",
    "sg:address":"25072 Redlands Blvd",
    "sg:city":"Loma Linda",
    "sg:classifiers":[
        {
            "category":"Autos & Motor Vehicles",
            "subcategory":"Automobile Sales",
            "type":"Retail Goods"
        }
    ],
    "sg:phone":"+1 909 796 1600",
    "sg:postcode":"92354",
    "sg:province":"CA",
    "sg:tags":[
        "car",
        "dealer"
    ],
    "wof:name":"Rusnak Auto Ctr",
    "wof:placetype":"venue"
},
  "geometry": {"coordinates":[-117.257803,34.063141],"type":"Point"}
}