{
  "type": "Feature",
  "properties": {
    "iso:country":"US",
    "sg:address":"949 E Dakota Ave",
    "sg:city":"Fresno",
    "sg:classifiers":[
        {
            "category":"Professional",
            "type":"Services"
        }
    ],
    "sg:phone":"+1 559 347 0110",
    "sg:postcode":"93704",
    "sg:province":"CA",
    "wof:name":"Tb Networing",
    "wof:placetype":"venue"
},
  "geometry": {"coordinates":[-119.797814,36.786837],"type":"Point"}
}