{
  "type": "Feature",
  "properties": {
    "iso:country":"US",
    "sg:address":"3800 W El Segundo Boulevard",
    "sg:city":"Hawthorne",
    "sg:classifiers":[
        {
            "category":"Food & Beverages",
            "subcategory":"Meat & Fish",
            "type":"Retail Goods"
        }
    ],
    "sg:phone":"+1 310 978 1223",
    "sg:postcode":"90250",
    "sg:province":"CA",
    "sg:tags":[
        "seafood",
        "market"
    ],
    "wof:name":"Ooh Fish Mkt",
    "wof:placetype":"venue"
},
  "geometry": {"coordinates":[-118.33945799999999,33.916445],"type":"Point"}
}