{
  "type": "Feature",
  "properties": {
    "iso:country":"US",
    "sg:address":"594 Howard Street Suite 401",
    "sg:city":"San Francisco",
    "sg:classifiers":[
        {
            "category":"Professional",
            "subcategory":"Computer Services",
            "type":"Services"
        }
    ],
    "sg:phone":"+1 215 253 3060",
    "sg:postcode":"94105",
    "sg:province":"CA",
    "sg:tags":[
        "business-intelligence",
        "analytics",
        "contracts-management",
        "software",
        "cloud",
        "on-demand",
        "services"
    ],
    "sg:website":"http://www.pramata.com",
    "wof:name":"Pramata",
    "wof:placetype":"venue"
},
  "geometry": {"coordinates":[-122.398118,37.787024],"type":"Point"}
}