{
  "type": "Feature",
  "properties": {
    "iso:country":"US",
    "sg:address":"1549 Echo Park Avenue",
    "sg:city":"Los Angeles",
    "sg:classifiers":[
        {
            "category":"Shopping",
            "subcategory":"Jewelry",
            "type":"Retail Goods"
        }
    ],
    "sg:phone":"+1 213 482 9180",
    "sg:postcode":"90026",
    "sg:province":"CA",
    "sg:website":"www.hancholo.com",
    "wof:name":"Han Cholo",
    "wof:placetype":"venue"
},
  "geometry": {"coordinates":[-118.254822,34.080828],"type":"Point"}
}