{
  "type": "Feature",
  "properties": {
    "addr:full":"3450 Loma Vista Rd Ventura CA 93003",
    "addr:housenumber":"3450",
    "addr:postcode":"93003",
    "addr:street":"Loma Vista Rd",
    "iso:country":"US",
    "sg:address":"3450 Loma Vista Rd",
    "sg:city":"Ventura",
    "sg:classifiers":[
        {
            "category":"Health Services",
            "subcategory":"Medical Lab",
            "type":"Services"
        }
    ],
    "sg:phone":"+1 805 339 0602",
    "sg:postcode":"93003",
    "sg:province":"CA",
    "sg:tags":[
        "laboratory",
        "sleep",
        "treatment",
        "disorders-information"
    ],
    "wof:name":"Premier Diagnostic Sleep Disorder",
    "wof:placetype":"venue"
},
  "geometry": {"coordinates":[-119.24968,34.276549],"type":"Point"}
}