{
  "type": "Feature",
  "properties": {
    "iso:country":"US",
    "sg:address":"1100 Las Tablas Rd",
    "sg:city":"Templeton",
    "sg:classifiers":[
        {
            "category":"Health Services",
            "subcategory":"Doctor",
            "type":"Services"
        }
    ],
    "sg:phone":"+1 805 434 1333",
    "sg:postcode":"93465",
    "sg:province":"CA",
    "sg:tags":[
        "physician",
        "surgeon"
    ],
    "wof:name":"North County Outpatient Surg",
    "wof:placetype":"venue"
},
  "geometry": {"coordinates":[-120.72081,35.554455],"type":"Point"}
}