{
  "type": "Feature",
  "properties": {
    "addr:full":"5687 N Wheeler Ave Fresno CA 93722",
    "addr:housenumber":"5687",
    "addr:postcode":"93722",
    "addr:street":"N Wheeler Ave",
    "iso:country":"US",
    "sg:address":"5687 N Wheeler Ave",
    "sg:city":"Fresno",
    "sg:classifiers":[
        {
            "category":"Professional",
            "subcategory":"Art Services",
            "type":"Services"
        }
    ],
    "sg:phone":"+1 559 907 7826",
    "sg:postcode":"93722",
    "sg:province":"CA",
    "sg:tags":[
        "graphic",
        "designer"
    ],
    "sg:website":"www.benchmarkdesign.net",
    "wof:name":"Benchmark Design",
    "wof:placetype":"venue"
},
  "geometry": {"coordinates":[-119.88963,36.818553],"type":"Point"}
}