{
  "type": "Feature",
  "properties": {
    "addr:full":"4845 Sunfield Ave Long Beach CA 90808",
    "addr:housenumber":"4845",
    "addr:postcode":"90808",
    "addr:street":"Sunfield Ave",
    "iso:country":"US",
    "sg:address":"4845 Sunfield Ave",
    "sg:city":"Long Beach",
    "sg:classifiers":[
        {
            "category":"Real Estate",
            "subcategory":"Real Estate Services",
            "type":"Services"
        }
    ],
    "sg:phone":"+1 562 426 4028",
    "sg:postcode":"90808",
    "sg:province":"CA",
    "sg:tags":[
        "home",
        "inspector"
    ],
    "wof:name":"South Bay Building Inspections",
    "wof:placetype":"venue"
},
  "geometry": {"coordinates":[-118.135097,33.845705],"type":"Point"}
}