{
  "type": "Feature",
  "properties": {
    "addr:full":"708 Addison St Berkeley CA 94710",
    "addr:housenumber":"708",
    "addr:postcode":"94710",
    "addr:street":"Addison St",
    "iso:country":"US",
    "sg:address":"708 Addison St",
    "sg:city":"Berkeley",
    "sg:classifiers":[
        {
            "category":"Manufacturing",
            "subcategory":"Food",
            "type":"Manufacturing & Wholesale Goods"
        }
    ],
    "sg:phone":"+1 510 540 8250",
    "sg:postcode":"94710",
    "sg:province":"CA",
    "sg:tags":[
        "winery",
        "brewer"
    ],
    "sg:website":"www.takarasake.com",
    "wof:name":"Takara Sake USA",
    "wof:placetype":"venue"
},
  "geometry": {"coordinates":[-122.300088,37.866123],"type":"Point"}
}