{
  "type": "Feature",
  "properties": {
    "iso:country":"US",
    "sg:address":"902 S Myrtle Ave",
    "sg:city":"Monrovia",
    "sg:classifiers":[
        {
            "category":"Health Services",
            "subcategory":"Clinic",
            "type":"Services"
        }
    ],
    "sg:phone":"+1 626 303 1541",
    "sg:postcode":"91016",
    "sg:province":"CA",
    "sg:tags":[
        "information",
        "mental"
    ],
    "wof:name":"Intensive Mlieu Otptent Prgram",
    "wof:placetype":"venue"
},
  "geometry": {"coordinates":[-118.0009,34.142598],"type":"Point"}
}