{
  "type": "Feature",
  "properties": {
    "addr:full":"7072 Pit Rd Redding CA 96001",
    "addr:housenumber":"7072",
    "addr:postcode":"96001",
    "addr:street":"Pit Rd",
    "iso:country":"US",
    "sg:address":"7072 Pit Rd",
    "sg:city":"Redding",
    "sg:classifiers":[
        {
            "category":"Building & Trades",
            "subcategory":"Plumbing",
            "type":"Services"
        }
    ],
    "sg:phone":"+1 530 245 0265",
    "sg:postcode":"96001",
    "sg:province":"CA",
    "sg:tags":[
        "contractor"
    ],
    "wof:name":"St Nicholas Plumbing",
    "wof:placetype":"venue"
},
  "geometry": {"coordinates":[-122.37551499999999,40.513637],"type":"Point"}
}