{
  "type": "Feature",
  "properties": {
    "iso:country":"US",
    "sg:address":"1297 Mercury Ct",
    "sg:city":"Nipomo",
    "sg:classifiers":[
        {
            "category":"Freight",
            "type":"Transportation"
        }
    ],
    "sg:phone":"+1 805 474 1041",
    "sg:postcode":"93444",
    "sg:province":"CA",
    "sg:tags":[
        "mobile",
        "home"
    ],
    "wof:name":"Gary Bailey Trucking",
    "wof:placetype":"venue"
},
  "geometry": {"coordinates":[-120.493428,35.015759],"type":"Point"}
}