{
  "type": "Feature",
  "properties": {
    "iso:country":"US",
    "sg:address":"8721 W. Sunset Blvd. Suite P8",
    "sg:city":"West Hollywood",
    "sg:classifiers":[
        {
            "category":"Professional",
            "subcategory":"Computer Services",
            "type":"Services"
        }
    ],
    "sg:phone":"+1 310 855 0033",
    "sg:postcode":"90069",
    "sg:province":"CA",
    "sg:tags":[
        "digital-media-wire",
        "social-networks",
        "digital-media",
        "news"
    ],
    "sg:website":"http://www.dmwmedia.com",
    "wof:name":"Digital Media Wire",
    "wof:placetype":"venue"
},
  "geometry": {"coordinates":[-118.38010199999999,34.092172],"type":"Point"}
}