{
  "type": "Feature",
  "properties": {
    "addr:full":"1300 S Grand Ave Santa Ana CA 92705",
    "addr:housenumber":"1300",
    "addr:postcode":"92705",
    "addr:street":"S Grand Ave",
    "iso:country":"US",
    "sg:address":"1300 S Grand Ave",
    "sg:city":"Santa Ana",
    "sg:classifiers":[
        {
            "category":"Government",
            "subcategory":"Office",
            "type":"Public Place"
        }
    ],
    "sg:phone":"+1 714 567 7542",
    "sg:postcode":"92705",
    "sg:province":"CA",
    "sg:tags":[
        "executive"
    ],
    "wof:name":"Board of Supervisors",
    "wof:placetype":"venue"
},
  "geometry": {"coordinates":[-117.850337,33.733495],"type":"Point"}
}