{
  "type": "Feature",
  "properties": {
    "addr:full":"6701 Stanford Ave Los Angeles CA 90001",
    "addr:housenumber":"6701",
    "addr:postcode":"90001",
    "addr:street":"Stanford Ave",
    "iso:country":"US",
    "sg:address":"6701 Stanford Ave",
    "sg:city":"Los Angeles",
    "sg:classifiers":[
        {
            "category":"Shopping",
            "subcategory":"Crafts & Fabrics",
            "type":"Retail Goods"
        }
    ],
    "sg:phone":"+1 323 753 2900",
    "sg:postcode":"90001",
    "sg:province":"CA",
    "sg:tags":[
        "sewing"
    ],
    "wof:name":"Guarantee Fashions",
    "wof:placetype":"venue"
},
  "geometry": {"coordinates":[-118.263046,33.975817],"type":"Point"}
}