{
  "type": "Feature",
  "properties": {
    "iso:country":"US",
    "sg:address":"1200 N el Camino Real",
    "sg:city":"San Clemente",
    "sg:classifiers":[
        {
            "category":"Insurance",
            "subcategory":"Insurance Agent",
            "type":"Services"
        }
    ],
    "sg:phone":"+1 949 361 5033",
    "sg:postcode":"92672",
    "sg:province":"CA",
    "wof:name":"Andrew Varos Insurance",
    "wof:placetype":"venue"
},
  "geometry": {"coordinates":[-117.62264999999999,33.4321],"type":"Point"}
}