{
  "type": "Feature",
  "properties": {
    "addr:full":"2660 N Main St Santa Ana CA 92705",
    "addr:housenumber":"2660",
    "addr:postcode":"92705",
    "addr:street":"N Main St",
    "iso:country":"US",
    "sg:address":"2660 N Main St",
    "sg:city":"Santa Ana",
    "sg:classifiers":[
        {
            "category":"Restaurant",
            "type":"Food & Drink"
        }
    ],
    "sg:menulink":"http://www.allmenus.com/ca/anaheim-santa-ana-garden-grove/38165-pollys-pies/menu/",
    "sg:phone":"+1 714 547 9681",
    "sg:postcode":"92705",
    "sg:province":"CA",
    "sg:tags":[
        "american"
    ],
    "wof:name":"Polly's Pies",
    "wof:placetype":"venue"
},
  "geometry": {"coordinates":[-117.86746599999999,33.772366],"type":"Point"}
}