{
  "type": "Feature",
  "properties": {
    "addr:full":"43145 Business Center Pkwy # 107 Lancaster CA 93535",
    "addr:postcode":"43145;93535",
    "addr:street":"Business Center Pkwy # 107",
    "iso:country":"US",
    "sg:address":"43145 Business Center Pkwy # 107",
    "sg:city":"Lancaster",
    "sg:classifiers":[
        {
            "category":"Retail",
            "subcategory":"Auto Repair",
            "type":"Services"
        }
    ],
    "sg:phone":"+1 661 949 9160",
    "sg:postcode":"93535",
    "sg:province":"CA",
    "sg:tags":[
        "body",
        "painting",
        "repairing",
        "automobile"
    ],
    "wof:name":"Tgs",
    "wof:placetype":"venue"
},
  "geometry": {"coordinates":[-118.12885,34.666269],"type":"Point"}
}