{
  "type": "Feature",
  "properties": {
    "addr:full":"1017 W Alondra Blvd Compton CA 90220",
    "addr:housenumber":"1017",
    "addr:postcode":"90220",
    "addr:street":"W Alondra Blvd",
    "iso:country":"US",
    "sg:address":"1017 W Alondra Blvd",
    "sg:city":"Compton",
    "sg:classifiers":[
        {
            "category":"Autos & Motor Vehicles",
            "subcategory":"Automobile Sales",
            "type":"Retail Goods"
        }
    ],
    "sg:phone":"+1 310 637 8466",
    "sg:postcode":"90220",
    "sg:province":"CA",
    "sg:tags":[
        "aircraft"
    ],
    "wof:name":"EAA Chapter 96",
    "wof:placetype":"venue"
},
  "geometry": {"coordinates":[-118.241834,33.888565],"type":"Point"}
}