{
  "type": "Feature",
  "properties": {
    "addr:full":"10460 San Pablo Ave El Cerrito CA 94530",
    "addr:housenumber":"10460",
    "addr:postcode":"94530",
    "addr:street":"San Pablo Ave",
    "iso:country":"US",
    "sg:address":"10460 San Pablo Ave",
    "sg:city":"El Cerrito",
    "sg:classifiers":[
        {
            "category":"Insurance",
            "subcategory":"Hazard Insurance",
            "type":"Services"
        }
    ],
    "sg:phone":"+1 510 559 1311",
    "sg:postcode":"94530",
    "sg:province":"CA",
    "sg:website":"www.consumerfriendlyinsurance.com",
    "wof:name":"Consumer Friendly Insurance Services",
    "wof:placetype":"venue"
},
  "geometry": {"coordinates":[-122.306804,37.908827],"type":"Point"}
}