{
  "type": "Feature",
  "properties": {
    "iso:country":"US",
    "sg:address":"641 W Whittier Blvd",
    "sg:city":"La Habra",
    "sg:classifiers":[
        {
            "category":"Wholesale",
            "subcategory":"Machinery & Supplies",
            "type":"Manufacturing & Wholesale Goods"
        }
    ],
    "sg:phone":"+1 562 697 6812",
    "sg:postcode":"90631",
    "sg:province":"CA",
    "sg:tags":[
        "equipment",
        "establishment"
    ],
    "wof:name":"LA Habra Beauty Supply",
    "wof:placetype":"venue"
},
  "geometry": {"coordinates":[-117.954508,33.939186],"type":"Point"}
}