{
  "type": "Feature",
  "properties": {
    "addr:full":"980 9th St Sacramento CA 95814",
    "addr:housenumber":"980",
    "addr:postcode":"95814",
    "addr:street":"9Th St",
    "iso:country":"US",
    "sg:address":"980 9th St",
    "sg:city":"Sacramento",
    "sg:classifiers":[
        {
            "category":"Government",
            "subcategory":"Office",
            "type":"Public Place"
        }
    ],
    "sg:phone":"+1 916 323 3562",
    "sg:postcode":"95814",
    "sg:province":"CA",
    "sg:website":"www.csm.ca.gov",
    "wof:name":"Commission On State Mandates",
    "wof:placetype":"venue"
},
  "geometry": {"coordinates":[-121.494581,38.581584],"type":"Point"}
}