{
  "type": "Feature",
  "properties": {
    "addr:full":"5242 Katella Ave Ste 202 Los Alamitos CA 90720",
    "addr:housenumber":"5242",
    "addr:postcode":"90720",
    "addr:street":"Katella Ave Ste 202",
    "iso:country":"US",
    "sg:address":"5242 Katella Ave Ste 202",
    "sg:city":"Los Alamitos",
    "sg:classifiers":[
        {
            "category":"Banks & Credit Unions",
            "subcategory":"Financial Services",
            "type":"Services"
        }
    ],
    "sg:phone":"+1 714 593 1707",
    "sg:postcode":"90720",
    "sg:province":"CA",
    "sg:tags":[
        "broker",
        "mortgage"
    ],
    "wof:name":"Shoreline Funding",
    "wof:placetype":"venue"
},
  "geometry": {"coordinates":[-118.04163800000001,33.802907],"type":"Point"}
}