{
  "type": "Feature",
  "properties": {
    "iso:country":"US",
    "sg:address":"2842 Country Club Blvd",
    "sg:city":"Stockton",
    "sg:classifiers":[
        {
            "category":"Social Services",
            "subcategory":"Child Care",
            "type":"Services"
        }
    ],
    "sg:phone":"+1 209 464 5464",
    "sg:postcode":"95204",
    "sg:province":"CA",
    "wof:name":"King's Kids Child Care",
    "wof:placetype":"venue"
},
  "geometry": {"coordinates":[-121.340048,37.963173],"type":"Point"}
}