{
  "type": "Feature",
  "properties": {
    "iso:country":"US",
    "sg:address":"1524 38th St",
    "sg:city":"Sacramento",
    "sg:classifiers":[
        {
            "category":"Professional",
            "type":"Services"
        }
    ],
    "sg:phone":"+1 916 278 6476",
    "sg:postcode":"95816",
    "sg:province":"CA",
    "wof:name":"Wnm Inc",
    "wof:placetype":"venue"
},
  "geometry": {"coordinates":[-121.45824500000001,38.563712],"type":"Point"}
}