{
  "type": "Feature",
  "properties": {
    "addr:full":"98 Parkridge Dr San Francisco CA 94131",
    "addr:housenumber":"98",
    "addr:postcode":"94131",
    "addr:street":"Parkridge Dr",
    "iso:country":"US",
    "sg:address":"98 Parkridge Dr",
    "sg:city":"San Francisco",
    "sg:classifiers":[
        {
            "category":"Social Services",
            "type":"Services"
        }
    ],
    "sg:phone":"+1 415 401 8094",
    "sg:postcode":"94131",
    "sg:province":"CA",
    "sg:tags":[
        "counseling"
    ],
    "wof:name":"Courage To Love Institute",
    "wof:placetype":"venue"
},
  "geometry": {"coordinates":[-122.445688,37.751853],"type":"Point"}
}