{
  "type": "Feature",
  "properties": {
    "iso:country":"US",
    "sg:address":"19 E Citrus Ave",
    "sg:city":"Redlands",
    "sg:classifiers":[
        {
            "category":"Banks & Credit Unions",
            "subcategory":"Investment Brokerage",
            "type":"Services"
        }
    ],
    "sg:phone":"+1 909 792 6098",
    "sg:postcode":"92373",
    "sg:province":"CA",
    "sg:tags":[
        "consultant",
        "financing"
    ],
    "wof:name":"Gemstar Capital Group Inc",
    "wof:placetype":"venue"
},
  "geometry": {"coordinates":[-117.181615,34.055633],"type":"Point"}
}