{
  "type": "Feature",
  "properties": {
    "addr:full":"1912 Lincoln Ave Ste B San Jose CA 95125",
    "addr:housenumber":"1912",
    "addr:postcode":"95125",
    "addr:street":"Lincoln Ave Ste B",
    "iso:country":"US",
    "sg:address":"1912 Lincoln Ave Ste B",
    "sg:city":"San Jose",
    "sg:classifiers":[
        {
            "category":"Banks & Credit Unions",
            "subcategory":"Financial Services",
            "type":"Services"
        }
    ],
    "sg:phone":"+1 408 448 3838",
    "sg:postcode":"95125",
    "sg:province":"CA",
    "sg:tags":[
        "broker",
        "mortgage"
    ],
    "wof:name":"Blue Sky Funding",
    "wof:placetype":"venue"
},
  "geometry": {"coordinates":[-121.89158999999999,37.295687],"type":"Point"}
}