{
  "type": "Feature",
  "properties": {
    "addr:full":"11860 Courtney Ln Moorpark CA 93021",
    "addr:housenumber":"11860",
    "addr:postcode":"ca 93021",
    "addr:street":"Courtney Ln",
    "iso:country":"US",
    "sg:address":"11860 Courtney Ln",
    "sg:city":"Moorpark",
    "sg:classifiers":[
        {
            "category":"Professional",
            "type":"Services"
        }
    ],
    "sg:phone":"+1 805 523 7478",
    "sg:postcode":"93021",
    "sg:province":"CA",
    "wof:name":"Relaxolgy",
    "wof:placetype":"venue"
},
  "geometry": {"coordinates":[-118.899334,34.277106],"type":"Point"}
}