{
  "type": "Feature",
  "properties": {
    "iso:country":"US",
    "sg:address":"14650 San Pablo Ave",
    "sg:city":"San Pablo",
    "sg:classifiers":[
        {
            "category":"Wholesale",
            "subcategory":"Machinery & Supplies",
            "type":"Manufacturing & Wholesale Goods"
        }
    ],
    "sg:phone":"+1 510 234 6289",
    "sg:postcode":"94806",
    "sg:province":"CA",
    "sg:tags":[
        "equipment",
        "establishment"
    ],
    "wof:name":"My Beauty Supply",
    "wof:placetype":"venue"
},
  "geometry": {"coordinates":[-122.34352199999999,37.969841],"type":"Point"}
}