{
  "type": "Feature",
  "properties": {
    "iso:country":"US",
    "sg:address":"820 20th St",
    "sg:city":"Bakersfield",
    "sg:classifiers":[
        {
            "category":"Wholesale",
            "subcategory":"Hardware",
            "type":"Manufacturing & Wholesale Goods"
        }
    ],
    "sg:phone":"+1 661 327 9795",
    "sg:postcode":"93301",
    "sg:province":"CA",
    "sg:tags":[
        "refrigerating"
    ],
    "wof:name":"Motor Man",
    "wof:placetype":"venue"
},
  "geometry": {"coordinates":[-119.011555,35.377211],"type":"Point"}
}