{
  "type": "Feature",
  "properties": {
    "addr:full":"18 Cantata Dr Mission Viejo CA 92692",
    "addr:housenumber":"18",
    "addr:postcode":"92692",
    "addr:street":"Cantata Dr",
    "iso:country":"US",
    "sg:address":"18 Cantata Dr",
    "sg:city":"Mission Viejo",
    "sg:classifiers":[
        {
            "category":"Building & Trades",
            "subcategory":"Construction",
            "type":"Services"
        }
    ],
    "sg:phone":"+1 949 374 6233",
    "sg:postcode":"92692",
    "sg:province":"CA",
    "sg:tags":[
        "residential"
    ],
    "wof:name":"Rt Squared LLC",
    "wof:placetype":"venue"
},
  "geometry": {"coordinates":[-117.64655,33.59784],"type":"Point"}
}