{
  "type": "Feature",
  "properties": {
    "addr:full":"517 Marine View Street Suite E Belmont CA 94002",
    "addr:housenumber":"517",
    "addr:postcode":"94002",
    "addr:street":"Marine View Street Suite E",
    "iso:country":"US",
    "sg:address":"517 Marine View Street Suite E",
    "sg:city":"Belmont",
    "sg:classifiers":[
        {
            "category":"Arts & Performance",
            "subcategory":"Arts Center",
            "type":"Entertainment"
        }
    ],
    "sg:phone":"+1 650 592 7272",
    "sg:postcode":"94002",
    "sg:province":"CA",
    "sg:tags":[
        "performing"
    ],
    "sg:website":"www.ayakoschool.com/",
    "wof:name":"Ayako School of Ballet",
    "wof:placetype":"venue"
},
  "geometry": {"coordinates":[-122.294625,37.515371],"type":"Point"}
}