{
  "type": "Feature",
  "properties": {
    "iso:country":"US",
    "sg:address":"625 E Main St",
    "sg:city":"Turlock",
    "sg:classifiers":[
        {
            "category":"Shopping",
            "subcategory":"Crafts & Fabrics",
            "type":"Retail Goods"
        }
    ],
    "sg:phone":"+1 209 632 3225",
    "sg:postcode":"95380",
    "sg:province":"CA",
    "sg:tags":[
        "shop"
    ],
    "wof:name":"Cloths & Quilts",
    "wof:placetype":"venue"
},
  "geometry": {"coordinates":[-120.841533,37.497869],"type":"Point"}
}