{
  "type": "Feature",
  "properties": {
    "iso:country":"US",
    "sg:address":"2300 E Vernon Ave",
    "sg:city":"Los Angeles",
    "sg:classifiers":[
        {
            "category":"Manufacturing",
            "subcategory":"Tools & Machinery",
            "type":"Manufacturing & Wholesale Goods"
        }
    ],
    "sg:phone":"+1 323 584 1861",
    "sg:postcode":"90058",
    "sg:province":"CA",
    "sg:tags":[
        "equipment",
        "pump",
        "centrifugal",
        "mfg"
    ],
    "wof:name":"Flowferve Corporation",
    "wof:placetype":"venue"
},
  "geometry": {"coordinates":[-118.231708,34.003946],"type":"Point"}
}