{
  "type": "Feature",
  "properties": {
    "iso:country":"US",
    "sg:address":"5807 Winfield Blvd Ste B6",
    "sg:city":"San Jose",
    "sg:classifiers":[
        {
            "category":"Education",
            "subcategory":"Music School",
            "type":"Public Place"
        }
    ],
    "sg:phone":"+1 408 578 3428",
    "sg:postcode":"95123",
    "sg:province":"CA",
    "sg:tags":[
        "instrument",
        "teacher",
        "musical"
    ],
    "sg:website":"www.cbperkins.com/",
    "wof:name":"C.B. Perkins Co.",
    "wof:placetype":"venue"
},
  "geometry": {"coordinates":[-121.868224,37.247416],"type":"Point"}
}