{
  "type": "Feature",
  "properties": {
    "addr:full":"9240 Dowdy Dr San Diego CA 92126",
    "addr:housenumber":"9240",
    "addr:postcode":"92126",
    "addr:street":"Dowdy Dr",
    "iso:country":"US",
    "sg:address":"9240 Dowdy Dr",
    "sg:city":"San Diego",
    "sg:classifiers":[
        {
            "category":"Autos & Motor Vehicles",
            "subcategory":"Auto Supplies",
            "type":"Retail Goods"
        }
    ],
    "sg:phone":"+1 858 566 1770",
    "sg:postcode":"92126",
    "sg:province":"CA",
    "sg:tags":[
        "automobile",
        "sunroof"
    ],
    "wof:name":"American Sunroof San Diego",
    "wof:placetype":"venue"
},
  "geometry": {"coordinates":[-117.145917,32.888681],"type":"Point"}
}