{
  "type": "Feature",
  "properties": {
    "addr:full":"14117 Van Ness Ave Gardena CA 90249",
    "addr:housenumber":"14117",
    "addr:postcode":"90249",
    "addr:street":"Van Ness Ave",
    "iso:country":"US",
    "sg:address":"14117 Van Ness Ave",
    "sg:city":"Gardena",
    "sg:classifiers":[
        {
            "category":"Insurance",
            "subcategory":"Hazard Insurance",
            "type":"Services"
        }
    ],
    "sg:phone":"+1 310 323 9937",
    "sg:postcode":"90249",
    "sg:province":"CA",
    "wof:name":"Caesar Guyot & Associates: The Insurance Market",
    "wof:placetype":"venue"
},
  "geometry": {"coordinates":[-118.317868,33.903584],"type":"Point"}
}