{
  "type": "Feature",
  "properties": {
    "addr:full":"4436 Clayton Rd Concord CA 94521",
    "addr:housenumber":"4436",
    "addr:postcode":"94521",
    "addr:street":"Clayton Rd",
    "iso:country":"US",
    "sg:address":"4436 Clayton Rd",
    "sg:city":"Concord",
    "sg:classifiers":[
        {
            "category":"Retail",
            "subcategory":"Laundry & Dry Cleaning",
            "type":"Services"
        }
    ],
    "sg:phone":"+1 925 680 7991",
    "sg:postcode":"94521",
    "sg:province":"CA",
    "sg:tags":[
        "cleaners"
    ],
    "wof:name":"Oasis Laundries Inc",
    "wof:placetype":"venue"
},
  "geometry": {"coordinates":[-121.988963,37.963435],"type":"Point"}
}