{
  "type": "Feature",
  "properties": {
    "iso:country":"US",
    "sg:address":"5000 Executive Pkwy",
    "sg:city":"San Ramon",
    "sg:classifiers":[
        {
            "category":"Manufacturing",
            "subcategory":"Printing",
            "type":"Manufacturing & Wholesale Goods"
        }
    ],
    "sg:phone":"+1 510 249 4100",
    "sg:postcode":"94583",
    "sg:province":"CA",
    "sg:tags":[
        "publisher",
        "software"
    ],
    "sg:website":"www.nsitesoftware.net",
    "wof:name":"N Site Software",
    "wof:placetype":"venue"
},
  "geometry": {"coordinates":[-121.969081,37.767177],"type":"Point"}
}