{
  "type": "Feature",
  "properties": {
    "addr:full":"595 E Colorado Blvd Pasadena CA 91106",
    "addr:housenumber":"595",
    "addr:postcode":"91106",
    "addr:street":"E Colorado Blvd",
    "iso:country":"US",
    "sg:address":"595 E Colorado Blvd",
    "sg:city":"Pasadena",
    "sg:classifiers":[
        {
            "category":"Social Services",
            "type":"Services"
        }
    ],
    "sg:phone":"+1 626 796 5621",
    "sg:postcode":"91106",
    "sg:province":"CA",
    "sg:tags":[
        "counselor",
        "marriage",
        "family"
    ],
    "wof:name":"James O Laughrun",
    "wof:placetype":"venue"
},
  "geometry": {"coordinates":[-118.137107,34.145942],"type":"Point"}
}