{
  "type": "Feature",
  "properties": {
    "iso:country":"US",
    "sg:address":"495 Los Santos",
    "sg:city":"Bodega Bay",
    "sg:classifiers":[
        {
            "category":"Building & Trades",
            "subcategory":"Landscaping Services",
            "type":"Services"
        }
    ],
    "sg:phone":"+1 707 875 3321",
    "sg:postcode":"94923",
    "sg:province":"CA",
    "sg:tags":[
        "landscape",
        "contractor"
    ],
    "wof:name":"Ben Goyhenetche Landscape Svc",
    "wof:placetype":"venue"
},
  "geometry": {"coordinates":[-123.073808,38.382849],"type":"Point"}
}