{
  "type": "Feature",
  "properties": {
    "iso:country":"US",
    "sg:address":"497 W Willow St",
    "sg:city":"Long Beach",
    "sg:classifiers":[
        {
            "category":"Personal",
            "type":"Services"
        }
    ],
    "sg:phone":"+1 562 424 0245",
    "sg:postcode":"90806",
    "sg:province":"CA",
    "sg:tags":[
        "sewing",
        "alteration"
    ],
    "wof:name":"European Tailoring",
    "wof:placetype":"venue"
},
  "geometry": {"coordinates":[-118.197998,33.804298],"type":"Point"}
}