{
  "type": "Feature",
  "properties": {
    "addr:full":"817 Main St Chico CA 95928",
    "addr:housenumber":"817",
    "addr:postcode":"95928",
    "addr:street":"Main St",
    "iso:country":"US",
    "sg:address":"817 Main St",
    "sg:city":"Chico",
    "sg:classifiers":[
        {
            "category":"Restaurant",
            "type":"Food & Drink"
        }
    ],
    "sg:phone":"+1 530 342 3390",
    "sg:postcode":"95928",
    "sg:province":"CA",
    "wof:name":"J P's Fish Chops & Fine Wine",
    "wof:placetype":"venue"
},
  "geometry": {"coordinates":[-121.835066,39.725623],"type":"Point"}
}