{
  "type": "Feature",
  "properties": {
    "iso:country":"US",
    "sg:address":"1440 North Harbor Blvd 4th Flr",
    "sg:city":"Fullerton",
    "sg:classifiers":[
        {
            "category":"Professional",
            "subcategory":"Lawyer & Legal Services",
            "type":"Services"
        }
    ],
    "sg:phone":"+1 714 626 3700",
    "sg:postcode":"92835",
    "sg:province":"CA",
    "sg:tags":[
        "attorney",
        "plan"
    ],
    "sg:website":"http://www.pubdef.ocgov.com",
    "wof:name":"Public Defender (North)",
    "wof:placetype":"venue"
},
  "geometry": {"coordinates":[-117.925743,33.884426],"type":"Point"}
}