{
  "type": "Feature",
  "properties": {
    "addr:full":"154 Main St Jackson CA 95642",
    "addr:housenumber":"154",
    "addr:postcode":"95642",
    "addr:street":"Main St",
    "iso:country":"US",
    "sg:address":"154 Main St",
    "sg:city":"Jackson",
    "sg:classifiers":[
        {
            "category":"Personal",
            "subcategory":"Beauty Salon",
            "type":"Services"
        }
    ],
    "sg:phone":"+1 209 223 1928",
    "sg:postcode":"95642",
    "sg:province":"CA",
    "wof:name":"Expressions",
    "wof:placetype":"venue"
},
  "geometry": {"coordinates":[-120.77448200000001,38.349558],"type":"Point"}
}