{
  "type": "Feature",
  "properties": {
    "addr:full":"969 Via Colinas Westlake Village CA 91362",
    "addr:housenumber":"969",
    "addr:postcode":"91362",
    "addr:street":"Via Colinas",
    "iso:country":"US",
    "sg:address":"969 Via Colinas",
    "sg:city":"Westlake Village",
    "sg:classifiers":[
        {
            "category":"Shopping",
            "subcategory":"Computers & Home Electronics",
            "type":"Retail Goods"
        }
    ],
    "sg:phone":"+1 805 497 0986",
    "sg:postcode":"91362",
    "sg:province":"CA",
    "sg:tags":[
        "software"
    ],
    "wof:name":"Dane Co",
    "wof:placetype":"venue"
},
  "geometry": {"coordinates":[-118.807166,34.15946],"type":"Point"}
}