{
  "type": "Feature",
  "properties": {
    "addr:full":"1607 Pontius Ave Los Angeles CA 90025",
    "addr:housenumber":"1607",
    "addr:postcode":"90025",
    "addr:street":"Pontius Ave",
    "iso:country":"US",
    "sg:address":"1607 Pontius Ave",
    "sg:city":"Los Angeles",
    "sg:classifiers":[
        {
            "category":"Professional",
            "subcategory":"Computer Services",
            "type":"Services"
        }
    ],
    "sg:phone":"+1 310 477 4441",
    "sg:postcode":"90025",
    "sg:province":"CA",
    "sg:tags":[
        "repair"
    ],
    "sg:website":"www.generationix.com",
    "wof:name":"Generation IX Technologies Inc",
    "wof:placetype":"venue"
},
  "geometry": {"coordinates":[-118.445999,34.048302],"type":"Point"}
}