{
  "type": "Feature",
  "properties": {
    "addr:full":"2381 Boswell Rd Chula Vista CA 91914",
    "addr:housenumber":"2381",
    "addr:postcode":"91914",
    "addr:street":"Boswell Rd",
    "iso:country":"US",
    "sg:address":"2381 Boswell Rd",
    "sg:city":"Chula Vista",
    "sg:classifiers":[
        {
            "category":"Real Estate",
            "subcategory":"Real Estate Services",
            "type":"Services"
        }
    ],
    "sg:phone":"+1 619 656 2900",
    "sg:postcode":"91914",
    "sg:province":"CA",
    "sg:tags":[
        "management",
        "property"
    ],
    "wof:name":"Coldwell Banker Alliance Real Estate",
    "wof:placetype":"venue"
},
  "geometry": {"coordinates":[-116.96399700000001,32.655602],"type":"Point"}
}