{
  "type": "Feature",
  "properties": {
    "addr:full":"12005 Aspen Cir Grand Terrace CA 92313",
    "addr:housenumber":"12005",
    "addr:postcode":"92313",
    "addr:street":"Aspen Cir",
    "iso:country":"US",
    "sg:address":"12005 Aspen Cir",
    "sg:city":"Grand Terrace",
    "sg:classifiers":[
        {
            "category":"Real Estate",
            "subcategory":"Developer",
            "type":"Services"
        }
    ],
    "sg:phone":"+1 909 783 1213",
    "sg:postcode":"92313",
    "sg:province":"CA",
    "wof:name":"Terrace Pines Townhomes",
    "wof:placetype":"venue"
},
  "geometry": {"coordinates":[-117.316377,34.035044],"type":"Point"}
}