{
  "type": "Feature",
  "properties": {
    "addr:full":"20435 Sherman Way Winnetka CA 91306",
    "addr:housenumber":"20435",
    "addr:postcode":"91306",
    "addr:street":"Sherman Way",
    "iso:country":"US",
    "sg:address":"20435 Sherman Way",
    "sg:city":"Winnetka",
    "sg:classifiers":[
        {
            "category":"Personal",
            "subcategory":"Beauty Salon",
            "type":"Services"
        }
    ],
    "sg:phone":"+1 818 346 5531",
    "sg:postcode":"91306",
    "sg:province":"CA",
    "sg:tags":[
        "hair"
    ],
    "wof:name":"La Contessa Hair Salon",
    "wof:placetype":"venue"
},
  "geometry": {"coordinates":[-118.57881,34.200983],"type":"Point"}
}