{
  "type": "Feature",
  "properties": {
    "addr:full":"2852 Gundry Ave Signal Hill CA 90755",
    "addr:housenumber":"2852",
    "addr:postcode":"90755",
    "addr:street":"Gundry Ave",
    "iso:country":"US",
    "sg:address":"2852 Gundry Ave",
    "sg:city":"Signal Hill",
    "sg:classifiers":[
        {
            "category":"Building & Trades",
            "subcategory":"Construction",
            "type":"Services"
        }
    ],
    "sg:phone":"+1 562 426 0848",
    "sg:postcode":"90755",
    "sg:province":"CA",
    "sg:tags":[
        "roofing",
        "contractor"
    ],
    "wof:name":"Skyline Roof Co",
    "wof:placetype":"venue"
},
  "geometry": {"coordinates":[-118.174063,33.808876],"type":"Point"}
}