{
  "type": "Feature",
  "properties": {
    "addr:full":"1338 N Sierra Bonita Avenue West Hollywood CA 90046",
    "addr:housenumber":"1338",
    "addr:postcode":"90046",
    "addr:street":"N Sierra Bonita Avenue",
    "iso:country":"US",
    "sg:address":"1338 N Sierra Bonita Avenue",
    "sg:city":"West Hollywood",
    "sg:classifiers":[
        {
            "category":"Real Estate",
            "subcategory":"Real Estate Services",
            "type":"Services"
        },
        {
            "category":"Real Estate",
            "subcategory":"Real Estate Operator",
            "type":"Services"
        }
    ],
    "sg:phone":"+1 323 851 7625",
    "sg:postcode":"90046",
    "sg:province":"CA",
    "sg:tags":[
        "apartment",
        "property",
        "management"
    ],
    "wof:name":"Sierra Bonita Apartments",
    "wof:placetype":"venue"
},
  "geometry": {"coordinates":[-118.353893,34.095088],"type":"Point"}
}