{
  "type": "Feature",
  "properties": {
    "iso:country":"US",
    "sg:address":"1350 E Lassen Ave Ste 1",
    "sg:city":"Chico",
    "sg:classifiers":[
        {
            "category":"Real Estate",
            "subcategory":"Real Estate Services",
            "type":"Services"
        },
        {
            "category":"Real Estate",
            "subcategory":"Real Estate Agent",
            "type":"Services"
        }
    ],
    "sg:phone":"+1 530 518 3131",
    "sg:postcode":"95973",
    "sg:province":"CA",
    "sg:tags":[
        "buyer",
        "management",
        "broker"
    ],
    "wof:name":"Glenn Fry Real Estate",
    "wof:placetype":"venue"
},
  "geometry": {"coordinates":[-121.841532,39.773404],"type":"Point"}
}