{
  "type": "Feature",
  "properties": {
    "addr:full":"1625 Drew Rd El Centro CA 92243",
    "addr:housenumber":"1625",
    "addr:postcode":"92243",
    "addr:street":"Drew Rd",
    "iso:country":"US",
    "sg:address":"1625 Drew Rd",
    "sg:city":"El Centro",
    "sg:classifiers":[
        {
            "category":"Wholesale",
            "subcategory":"Farm Supplies",
            "type":"Manufacturing & Wholesale Goods"
        }
    ],
    "sg:phone":"+1 760 352 2143",
    "sg:postcode":"92243",
    "sg:province":"CA",
    "sg:tags":[
        "alfalfa",
        "hay"
    ],
    "wof:name":"Kuhn Farms",
    "wof:placetype":"venue"
},
  "geometry": {"coordinates":[-115.690425,32.767923],"type":"Point"}
}