{
  "type": "Feature",
  "properties": {
    "addr:full":"1613 Park St Alameda CA 94501",
    "addr:housenumber":"1613",
    "addr:postcode":"94501",
    "addr:street":"Park St",
    "iso:country":"US",
    "sg:address":"1613 Park St",
    "sg:city":"Alameda",
    "sg:classifiers":[
        {
            "category":"Manufacturing",
            "subcategory":"Printing",
            "type":"Manufacturing & Wholesale Goods"
        }
    ],
    "sg:phone":"+1 510 521 0500",
    "sg:postcode":"94501",
    "sg:province":"CA",
    "sg:tags":[
        "printer"
    ],
    "wof:name":"Alameda Printing Svc",
    "wof:placetype":"venue"
},
  "geometry": {"coordinates":[-122.240466,37.767056],"type":"Point"}
}