{
  "type": "Feature",
  "properties": {
    "addr:full":"2974 Sacramento Street Berkeley CA 94702",
    "addr:housenumber":"2974",
    "addr:postcode":"94702",
    "addr:street":"Sacramento Street",
    "iso:country":"US",
    "sg:address":"2974 Sacramento Street",
    "sg:city":"Berkeley",
    "sg:classifiers":[
        {
            "category":"Food & Beverages",
            "subcategory":"Groceries & Convenience Stores",
            "type":"Retail Goods"
        }
    ],
    "sg:phone":"+1 510 647 5288",
    "sg:postcode":"94702",
    "sg:province":"CA",
    "wof:name":"Sacramento Market",
    "wof:placetype":"venue"
},
  "geometry": {"coordinates":[-122.278999,37.8535],"type":"Point"}
}