{
  "type": "Feature",
  "properties": {
    "addr:full":"3716 Page St Redwood City CA 94063",
    "addr:housenumber":"3716",
    "addr:postcode":"94063",
    "addr:street":"Page St",
    "iso:country":"US",
    "sg:address":"3716 Page St",
    "sg:city":"Redwood City",
    "sg:classifiers":[
        {
            "category":"Home & Garden",
            "subcategory":"Home Furnishings",
            "type":"Retail Goods"
        }
    ],
    "sg:phone":"+1 650 363 8649",
    "sg:postcode":"94063",
    "sg:province":"CA",
    "sg:tags":[
        "utensil",
        "cooking"
    ],
    "wof:name":"Home Chef Supplies",
    "wof:placetype":"venue"
},
  "geometry": {"coordinates":[-122.186251,37.480863],"type":"Point"}
}