{
  "type": "Feature",
  "properties": {
    "addr:full":"4115 Broadway Oakland CA 94611",
    "addr:housenumber":"4115",
    "addr:postcode":"94611",
    "addr:street":"Broadway",
    "iso:country":"US",
    "sg:address":"4115 Broadway",
    "sg:city":"Oakland",
    "sg:classifiers":[
        {
            "category":"Manufacturing",
            "subcategory":"Metals",
            "type":"Manufacturing & Wholesale Goods"
        }
    ],
    "sg:phone":"+1 510 654 1844",
    "sg:postcode":"94611",
    "sg:province":"CA",
    "sg:tags":[
        "production",
        "grinding"
    ],
    "wof:name":"Pacific Reamer & Cutter Svc Co",
    "wof:placetype":"venue"
},
  "geometry": {"coordinates":[-122.255612,37.829525],"type":"Point"}
}