{
  "type": "Feature",
  "properties": {
    "iso:country":"US",
    "sg:address":"2109 Weatherby Ave",
    "sg:city":"Escondido",
    "sg:classifiers":[
        {
            "category":"Shopping",
            "subcategory":"Discount & Variety Stores",
            "type":"Retail Goods"
        }
    ],
    "sg:phone":"+1 760 747 1944",
    "sg:postcode":"92027",
    "sg:province":"CA",
    "wof:name":"Linda Wade",
    "wof:placetype":"venue"
},
  "geometry": {"coordinates":[-117.049617,33.144971],"type":"Point"}
}