{
  "type": "Feature",
  "properties": {
    "iso:country":"US",
    "sg:address":"3541 Gateway Blvd",
    "sg:city":"Fremont",
    "sg:classifiers":[
        {
            "category":"Manufacturing",
            "subcategory":"Tools & Machinery",
            "type":"Manufacturing & Wholesale Goods"
        }
    ],
    "sg:phone":"+1 510 770 9727",
    "sg:postcode":"94538",
    "sg:province":"CA",
    "sg:tags":[
        "computer",
        "parts",
        "supply"
    ],
    "sg:website":"www.cyclades.com",
    "wof:name":"Cyclades Corp",
    "wof:placetype":"venue"
},
  "geometry": {"coordinates":[-121.940684,37.474047],"type":"Point"}
}