{
  "type": "Feature",
  "properties": {
    "iso:country":"US",
    "sg:address":"7055 Vineland Ave",
    "sg:city":"North Hollywood",
    "sg:classifiers":[
        {
            "category":"Food & Beverages",
            "subcategory":"Liquor & Beverages",
            "type":"Retail Goods"
        }
    ],
    "sg:phone":"+1 818 255 1415",
    "sg:postcode":"91605",
    "sg:province":"CA",
    "sg:tags":[
        "beer",
        "spirit",
        "wine"
    ],
    "wof:name":"West Coast Wine And Spirits Inc",
    "wof:placetype":"venue"
},
  "geometry": {"coordinates":[-118.370475,34.198806],"type":"Point"}
}