{
  "type": "Feature",
  "properties": {
    "iso:country":"US",
    "sg:address":"1800 W 6th St",
    "sg:city":"Los Angeles",
    "sg:classifiers":[
        {
            "category":"Health Services",
            "subcategory":"Doctor",
            "type":"Services"
        }
    ],
    "sg:phone":"+1 213 413 0733",
    "sg:postcode":"90057",
    "sg:province":"CA",
    "sg:tags":[
        "clinic"
    ],
    "wof:name":"Montenegro Medical Clinic",
    "wof:placetype":"venue"
},
  "geometry": {"coordinates":[-118.272422,34.058451],"type":"Point"}
}