{
  "type": "Feature",
  "properties": {
    "iso:country":"US",
    "sg:address":"3329 Fosca St",
    "sg:city":"Carlsbad",
    "sg:classifiers":[
        {
            "category":"Building & Trades",
            "subcategory":"Construction",
            "type":"Services"
        }
    ],
    "sg:phone":"+1 760 632 0958",
    "sg:postcode":"92009",
    "sg:province":"CA",
    "sg:tags":[
        "roofing",
        "contractor"
    ],
    "wof:name":"Southern California Foam",
    "wof:placetype":"venue"
},
  "geometry": {"coordinates":[-117.232862,33.088231],"type":"Point"}
}