{
  "type": "Feature",
  "properties": {
    "addr:full":"7842 Calle del Rio St Highland CA 92346",
    "addr:housenumber":"7842",
    "addr:postcode":"92346",
    "addr:street":"Calle Del Rio St",
    "iso:country":"US",
    "sg:address":"7842 Calle del Rio St",
    "sg:city":"Highland",
    "sg:classifiers":[
        {
            "category":"Building & Trades",
            "subcategory":"Construction",
            "type":"Services"
        },
        {
            "category":"Manufacturing",
            "subcategory":"Building Materials",
            "type":"Manufacturing & Wholesale Goods"
        }
    ],
    "sg:phone":"+1 909 748 7911",
    "sg:postcode":"92346",
    "sg:province":"CA",
    "sg:tags":[
        "roofing",
        "sheet",
        "work",
        "metal",
        "contractor",
        "siding"
    ],
    "wof:name":"Alamo Industries",
    "wof:placetype":"venue"
},
  "geometry": {"coordinates":[-117.140851,34.111372],"type":"Point"}
}