{
  "type": "Feature",
  "properties": {
    "iso:country":"US",
    "sg:address":"227 del Amo Fashion Sq",
    "sg:city":"Torrance",
    "sg:classifiers":[
        {
            "category":"Personal",
            "type":"Services"
        }
    ],
    "sg:phone":"+1 310 344 4270",
    "sg:postcode":"90503",
    "sg:province":"CA",
    "sg:tags":[
        "therapist",
        "massage"
    ],
    "wof:name":"Ultimate Tender Massage-Women",
    "wof:placetype":"venue"
},
  "geometry": {"coordinates":[-118.35109,33.828515],"type":"Point"}
}