{
  "type": "Feature",
  "properties": {
    "iso:country":"US",
    "sg:address":"2360 Shasta Way",
    "sg:city":"Simi Valley",
    "sg:classifiers":[
        {
            "category":"Manufacturing",
            "subcategory":"Petroleum Products",
            "type":"Manufacturing & Wholesale Goods"
        },
        {
            "category":"Building & Trades",
            "subcategory":"Construction",
            "type":"Services"
        }
    ],
    "sg:phone":"+1 805 527 9330",
    "sg:postcode":"93065",
    "sg:province":"CA",
    "sg:tags":[
        "engineering",
        "contractor",
        "paving",
        "general"
    ],
    "sg:website":"www.carasmussen.com",
    "wof:name":"C A Rasmussen Inc",
    "wof:placetype":"venue"
},
  "geometry": {"coordinates":[-118.789018,34.275233],"type":"Point"}
}