{
  "type": "Feature",
  "properties": {
    "iso:country":"US",
    "sg:address":"1075 Dixieanne Ave Apt 121",
    "sg:city":"Sacramento",
    "sg:classifiers":[
        {
            "category":"Real Estate",
            "subcategory":"Real Estate Operator",
            "type":"Services"
        }
    ],
    "sg:phone":"+1 916 923 1624",
    "sg:postcode":"95815",
    "sg:province":"CA",
    "sg:tags":[
        "apartment"
    ],
    "wof:name":"Evergreen Estates",
    "wof:placetype":"venue"
},
  "geometry": {"coordinates":[-121.442153,38.609794],"type":"Point"}
}