{
  "type": "Feature",
  "properties": {
    "addr:full":"1020 High St Oakland CA 94601",
    "addr:housenumber":"1020",
    "addr:postcode":"94601",
    "addr:street":"High St",
    "iso:country":"US",
    "sg:address":"1020 High St",
    "sg:city":"Oakland",
    "sg:classifiers":[
        {
            "category":"Autos & Motor Vehicles",
            "subcategory":"Auto Supplies",
            "type":"Retail Goods"
        }
    ],
    "sg:phone":"+1 510 535 9410",
    "sg:postcode":"94601",
    "sg:province":"CA",
    "sg:tags":[
        "tire"
    ],
    "wof:name":"J&F Tires",
    "wof:placetype":"venue"
},
  "geometry": {"coordinates":[-122.217112,37.770636],"type":"Point"}
}