{
  "type": "Feature",
  "properties": {
    "iso:country":"US",
    "sg:address":"16906 Burbank Blvd",
    "sg:city":"Encino",
    "sg:classifiers":[
        {
            "category":"Professional",
            "type":"Services"
        }
    ],
    "sg:phone":"+1 818 906 0160",
    "sg:postcode":"91316",
    "sg:province":"CA",
    "wof:name":"Provincity Inc",
    "wof:placetype":"venue"
},
  "geometry": {"coordinates":[-118.50546,34.172233],"type":"Point"}
}