{
  "type": "Feature",
  "properties": {
    "iso:country":"US",
    "sg:address":"1420 E Ocean Ave",
    "sg:city":"Lompoc",
    "sg:classifiers":[
        {
            "category":"Manufacturing",
            "subcategory":"Toys & Sporting Goods",
            "type":"Manufacturing & Wholesale Goods"
        }
    ],
    "sg:phone":"+1 805 736 8045",
    "sg:postcode":"93436",
    "sg:province":"CA",
    "sg:tags":[
        "mfg"
    ],
    "wof:name":"Pro Zone",
    "wof:placetype":"venue"
},
  "geometry": {"coordinates":[-120.441542,34.638724],"type":"Point"}
}