{
  "type": "Feature",
  "properties": {
    "iso:country":"US",
    "sg:address":"9911 W Pico Blvd",
    "sg:city":"Los Angeles",
    "sg:classifiers":[
        {
            "category":"Professional",
            "type":"Services"
        }
    ],
    "sg:phone":"+1 310 843 9846",
    "sg:postcode":"90035",
    "sg:province":"CA",
    "sg:tags":[
        "establishment"
    ],
    "wof:name":"International Judea Foundation",
    "wof:placetype":"venue"
},
  "geometry": {"coordinates":[-118.404588,34.053257],"type":"Point"}
}