{
  "type": "Feature",
  "properties": {
    "addr:full":"1917 Eye St Bakersfield CA 93301",
    "addr:housenumber":"1917",
    "addr:postcode":"93301",
    "addr:street":"Eye St",
    "iso:country":"US",
    "sg:address":"1917 Eye St",
    "sg:city":"Bakersfield",
    "sg:classifiers":[
        {
            "category":"Shopping",
            "subcategory":"Jewelry",
            "type":"Retail Goods"
        }
    ],
    "sg:phone":"+1 661 323 6241",
    "sg:postcode":"93301",
    "sg:province":"CA",
    "sg:tags":[
        "repair"
    ],
    "wof:name":"Chism Jewelers",
    "wof:placetype":"venue"
},
  "geometry": {"coordinates":[-119.020094,35.376544],"type":"Point"}
}