{
  "type": "Feature",
  "properties": {
    "iso:country":"US",
    "sg:address":"633 W 5th St Ste 2800",
    "sg:city":"Los Angeles",
    "sg:classifiers":[
        {
            "category":"Professional",
            "subcategory":"Lawyer & Legal Services",
            "type":"Services"
        }
    ],
    "sg:phone":"+1 213 223 2040",
    "sg:postcode":"90071",
    "sg:province":"CA",
    "wof:name":"General Counsel Group PC The",
    "wof:placetype":"venue"
},
  "geometry": {"coordinates":[-118.254127,34.056183],"type":"Point"}
}