{
  "type": "Feature",
  "properties": {
    "addr:full":"3646 W el Segundo Blvd Hawthorne CA 90250",
    "addr:housenumber":"3646",
    "addr:postcode":"90250",
    "addr:street":"W El Segundo Blvd",
    "iso:country":"US",
    "sg:address":"3646 W el Segundo Blvd",
    "sg:city":"Hawthorne",
    "sg:classifiers":[
        {
            "category":"Wholesale",
            "subcategory":"Plants",
            "type":"Manufacturing & Wholesale Goods"
        }
    ],
    "sg:phone":"+1 310 678 5944",
    "sg:postcode":"90250",
    "sg:province":"CA",
    "sg:tags":[
        "florist"
    ],
    "wof:name":"Satow Grows Inc",
    "wof:placetype":"venue"
},
  "geometry": {"coordinates":[-118.33732500000001,33.91644],"type":"Point"}
}