{
  "type": "Feature",
  "properties": {
    "iso:country":"US",
    "sg:address":"463 E Foothill Blvd",
    "sg:city":"Rialto",
    "sg:classifiers":[
        {
            "category":"Shopping",
            "type":"Retail Goods"
        }
    ],
    "sg:phone":"+1 909 877 5411",
    "sg:postcode":"92376",
    "sg:province":"CA",
    "sg:tags":[
        "perfume"
    ],
    "wof:name":"Caasta's Perfume",
    "wof:placetype":"venue"
},
  "geometry": {"coordinates":[-117.366013,34.106784],"type":"Point"}
}