{
  "type": "Feature",
  "properties": {
    "iso:country":"US",
    "sg:address":"19206 Bessemer St",
    "sg:city":"Tarzana",
    "sg:classifiers":[
        {
            "category":"Manufacturing",
            "subcategory":"Retail Goods",
            "type":"Manufacturing & Wholesale Goods"
        }
    ],
    "sg:phone":"+1 818 343 2712",
    "sg:postcode":"91335",
    "sg:province":"CA",
    "sg:tags":[
        "product",
        "contract",
        "mfg"
    ],
    "wof:name":"Prescott Industries",
    "wof:placetype":"venue"
},
  "geometry": {"coordinates":[-118.55070600000001,34.181031],"type":"Point"}
}