{
  "type": "Feature",
  "properties": {
    "iso:country":"US",
    "sg:address":"5055 Exposition Blvd",
    "sg:city":"Los Angeles",
    "sg:classifiers":[
        {
            "category":"Wholesale",
            "subcategory":"Scrap",
            "type":"Manufacturing & Wholesale Goods"
        }
    ],
    "sg:phone":"+1 323 734 2430",
    "sg:postcode":"90016",
    "sg:province":"CA",
    "sg:tags":[
        "salvage",
        "surplus",
        "merchandise"
    ],
    "wof:name":"E T Supply",
    "wof:placetype":"venue"
},
  "geometry": {"coordinates":[-118.354322,34.024934],"type":"Point"}
}