{
  "type": "Feature",
  "properties": {
    "iso:country":"US",
    "sg:address":"7368 Locke Rd",
    "sg:city":"Vacaville",
    "sg:classifiers":[
        {
            "category":"Building & Trades",
            "subcategory":"Construction",
            "type":"Services"
        }
    ],
    "sg:phone":"+1 707 455 1784",
    "sg:postcode":"95688",
    "sg:province":"CA",
    "sg:tags":[
        "contractor",
        "paving",
        "asphalt",
        "sealcoating"
    ],
    "wof:name":"Midway Asphalt Paving",
    "wof:placetype":"venue"
},
  "geometry": {"coordinates":[-121.948317,38.419784],"type":"Point"}
}