{
  "type": "Feature",
  "properties": {
    "addr:full":"1333 Vintage Way Auburn CA 95603",
    "addr:housenumber":"1333",
    "addr:postcode":"ca 95603",
    "addr:street":"Vintage Way",
    "iso:country":"US",
    "sg:address":"1333 Vintage Way",
    "sg:city":"Auburn",
    "sg:classifiers":[
        {
            "category":"Professional",
            "subcategory":"Business Services",
            "type":"Services"
        }
    ],
    "sg:phone":"+1 530 889 1855",
    "sg:postcode":"95603",
    "sg:province":"CA",
    "sg:tags":[
        "consultant",
        "coach"
    ],
    "wof:name":"Dba Joyce E Beeman Consulting",
    "wof:placetype":"venue"
},
  "geometry": {"coordinates":[-121.088155,38.865153],"type":"Point"}
}