{
  "type": "Feature",
  "properties": {
    "addr:full":"20362 Beach Blvd Huntington Beach CA 92646",
    "addr:housenumber":"20362",
    "addr:postcode":"92646",
    "addr:street":"Beach Blvd",
    "iso:country":"US",
    "sg:address":"20362 Beach Blvd",
    "sg:city":"Huntington Beach",
    "sg:classifiers":[
        {
            "category":"Fast Food",
            "type":"Food & Drink"
        }
    ],
    "sg:phone":"+1 714 536 7977",
    "sg:postcode":"92646",
    "sg:province":"CA",
    "sg:tags":[
        "burger"
    ],
    "sg:website":"www.mcdonalds.com",
    "wof:name":"McDonald's",
    "wof:placetype":"venue"
},
  "geometry": {"coordinates":[-117.988372,33.666738],"type":"Point"}
}