{
  "type": "Feature",
  "properties": {
    "iso:country":"US",
    "sg:address":"23101 Sherman Pl Ste 304",
    "sg:city":"West Hills",
    "sg:classifiers":[
        {
            "category":"Health Services",
            "subcategory":"Doctor",
            "type":"Services"
        }
    ],
    "sg:phone":"+1 818 703 9500",
    "sg:postcode":"91307",
    "sg:province":"CA",
    "sg:website":"drsafir.com/",
    "wof:name":"Southern California Center for Advanced Urology",
    "wof:placetype":"venue"
},
  "geometry": {"coordinates":[-118.629853,34.201422],"type":"Point"}
}