{
  "type": "Feature",
  "properties": {
    "iso:country":"US",
    "sg:address":"626 Jefferson Ave",
    "sg:city":"Redwood City",
    "sg:classifiers":[
        {
            "category":"Professional",
            "subcategory":"Advertising",
            "type":"Services"
        }
    ],
    "sg:phone":"+1 650 368 6252",
    "sg:postcode":"94063",
    "sg:province":"CA",
    "sg:tags":[
        "shop",
        "letter"
    ],
    "wof:name":"CSALC",
    "wof:placetype":"venue"
},
  "geometry": {"coordinates":[-122.228342,37.487847],"type":"Point"}
}