{
  "type": "Feature",
  "properties": {
    "iso:country":"US",
    "sg:address":"25571 Jeronimo Rd #21",
    "sg:city":"Mission Viejo",
    "sg:classifiers":[
        {
            "category":"Professional",
            "subcategory":"Computer Services",
            "type":"Services"
        }
    ],
    "sg:phone":"+1 949 829 1451",
    "sg:postcode":"92691",
    "sg:province":"CA",
    "sg:tags":[
        "repair"
    ],
    "sg:website":"www.CoronadoComputers.com",
    "wof:name":"Coronado Computers",
    "wof:placetype":"venue"
},
  "geometry": {"coordinates":[-117.673455,33.611027],"type":"Point"}
}