{
  "type": "Feature",
  "properties": {
    "addr:full":"971 B St Hayward CA 94541",
    "addr:housenumber":"971",
    "addr:postcode":"94541",
    "addr:street":"B St",
    "iso:country":"US",
    "sg:address":"971 B St",
    "sg:city":"Hayward",
    "sg:classifiers":[
        {
            "category":"Education",
            "subcategory":"School",
            "type":"Public Place"
        }
    ],
    "sg:phone":"+1 510 537 9190",
    "sg:postcode":"94541",
    "sg:province":"CA",
    "sg:tags":[
        "academic",
        "centers-adult",
        "day",
        "special",
        "care"
    ],
    "sg:website":"http://www.over21inc.org",
    "wof:name":"Over 21 Adult Day Program",
    "wof:placetype":"venue"
},
  "geometry": {"coordinates":[-122.083046,37.672624],"type":"Point"}
}