{
  "type": "Feature",
  "properties": {
    "addr:full":"3150 Panama Ln Bakersfield CA 93313",
    "addr:housenumber":"3150",
    "addr:postcode":"93313",
    "addr:street":"Panama Ln",
    "iso:country":"US",
    "sg:address":"3150 Panama Ln",
    "sg:city":"Bakersfield",
    "sg:classifiers":[
        {
            "category":"Food & Beverages",
            "subcategory":"Bakery",
            "type":"Retail Goods"
        }
    ],
    "sg:phone":"+1 661 836 1080",
    "sg:postcode":"93313",
    "sg:province":"CA",
    "sg:tags":[
        "baker"
    ],
    "wof:name":"LA Ilusion",
    "wof:placetype":"venue"
},
  "geometry": {"coordinates":[-119.038639,35.295966],"type":"Point"}
}