{
  "type": "Feature",
  "properties": {
    "iso:country":"US",
    "sg:address":"145 Thunder Dr",
    "sg:city":"Vista",
    "sg:classifiers":[
        {
            "category":"Health Services",
            "subcategory":"Doctor",
            "type":"Services"
        }
    ],
    "sg:phone":"+1 760 630 5464",
    "sg:postcode":"92083",
    "sg:province":"CA",
    "sg:tags":[
        "medicine",
        "practice",
        "internal",
        "family"
    ],
    "sg:website":"cassidymg.com",
    "wof:name":"Cassidy Medical Group",
    "wof:placetype":"venue"
},
  "geometry": {"coordinates":[-117.288076,33.185864],"type":"Point"}
}