{
  "type": "Feature",
  "properties": {
    "iso:country":"US",
    "sg:address":"1 Alamo Ave",
    "sg:city":"Weed",
    "sg:classifiers":[
        {
            "category":"Home & Garden",
            "subcategory":"Building Materials",
            "type":"Retail Goods"
        }
    ],
    "sg:phone":"+1 530 938 1494",
    "sg:postcode":"96094",
    "sg:province":"CA",
    "sg:tags":[
        "plywood",
        "veneer"
    ],
    "wof:name":"Mt Shasta Veneer",
    "wof:placetype":"venue"
},
  "geometry": {"coordinates":[-122.38500500000001,41.427054],"type":"Point"}
}