{
  "type": "Feature",
  "properties": {
    "iso:country":"US",
    "sg:address":"1880 Pleasant Valley Ave",
    "sg:city":"Oakland",
    "sg:classifiers":[
        {
            "category":"Food & Beverages",
            "subcategory":"Liquor & Beverages",
            "type":"Retail Goods"
        },
        {
            "category":"Wholesale",
            "subcategory":"Wine & Distilled Alcoholic Beverages",
            "type":"Manufacturing & Wholesale Goods"
        }
    ],
    "sg:phone":"+1 510 653 9424",
    "sg:postcode":"94611",
    "sg:province":"CA",
    "sg:tags":[
        "broker"
    ],
    "wof:name":"New Wines Inc",
    "wof:placetype":"venue"
},
  "geometry": {"coordinates":[-122.24782,37.830643],"type":"Point"}
}