{
  "type": "Feature",
  "properties": {
    "addr:full":"1213 Maple Avenue Los Angeles CA 90015",
    "addr:housenumber":"1213",
    "addr:postcode":"90015",
    "addr:street":"Maple Avenue",
    "iso:country":"US",
    "sg:address":"1213 Maple Avenue",
    "sg:city":"Los Angeles",
    "sg:classifiers":[
        {
            "category":"Shopping",
            "subcategory":"Clothing, Apparel, & Fashions",
            "type":"Retail Goods"
        }
    ],
    "sg:phone":"+1 213 744 0787",
    "sg:postcode":"90015",
    "sg:province":"CA",
    "sg:tags":[
        "accessory",
        "clothing",
        "women's"
    ],
    "wof:name":"2 Fabulous",
    "wof:placetype":"venue"
},
  "geometry": {"coordinates":[-118.256445,34.035513],"type":"Point"}
}