{
  "type": "Feature",
  "properties": {
    "addr:full":"1340 Wooden Valley Rd Napa CA 94558",
    "addr:housenumber":"1340",
    "addr:postcode":"94558",
    "addr:street":"Wooden Valley Rd",
    "iso:country":"US",
    "sg:address":"1340 Wooden Valley Rd",
    "sg:city":"Napa",
    "sg:classifiers":[
        {
            "category":"Education",
            "subcategory":"School",
            "type":"Public Place"
        }
    ],
    "sg:phone":"+1 707 253 3703",
    "sg:postcode":"94558",
    "sg:province":"CA",
    "wof:name":"Wooden Valley Elementary Schl",
    "wof:placetype":"venue"
},
  "geometry": {"coordinates":[-122.190579,38.375055],"type":"Point"}
}