{
  "type": "Feature",
  "properties": {
    "iso:country":"US",
    "sg:address":"6370 Altura Blvd",
    "sg:city":"Buena Park",
    "sg:classifiers":[
        {
            "category":"Manufacturing",
            "subcategory":"Chemicals & Compounds",
            "type":"Manufacturing & Wholesale Goods"
        }
    ],
    "sg:phone":"+1 714 562 8873",
    "sg:postcode":"90620",
    "sg:province":"CA",
    "sg:tags":[
        "product",
        "mfg",
        "cleaning",
        "specialty"
    ],
    "wof:name":"Awesome Products Inc",
    "wof:placetype":"venue"
},
  "geometry": {"coordinates":[-118.021419,33.871328],"type":"Point"}
}