{
  "type": "Feature",
  "properties": {
    "iso:country":"US",
    "sg:address":"6103 Tyrone Ave",
    "sg:city":"Van Nuys",
    "sg:classifiers":[
        {
            "category":"Building & Trades",
            "subcategory":"Construction",
            "type":"Services"
        }
    ],
    "sg:phone":"+1 818 787 9216",
    "sg:postcode":"91401",
    "sg:province":"CA",
    "sg:tags":[
        "contractor"
    ],
    "sg:website":"www.ykaindustries.com",
    "wof:name":"Yka Industries",
    "wof:placetype":"venue"
},
  "geometry": {"coordinates":[-118.444,34.180901],"type":"Point"}
}