{
  "type": "Feature",
  "properties": {
    "iso:country":"US",
    "sg:address":"2601 E Tahquitz Canyon Way",
    "sg:city":"Palm Springs",
    "sg:classifiers":[
        {
            "category":"Professional",
            "subcategory":"Business Services",
            "type":"Services"
        }
    ],
    "sg:phone":"+1 760 318 2980",
    "sg:postcode":"92262",
    "sg:province":"CA",
    "wof:name":"Desert Advanced Imaging",
    "wof:placetype":"venue"
},
  "geometry": {"coordinates":[-116.51494099999999,33.823161],"type":"Point"}
}