{
  "type": "Feature",
  "properties": {
    "addr:full":"UU Fellowship Hall 6401 Freedom Blvd Aptos CA 95003",
    "addr:housenumber":"6401",
    "addr:postcode":"ca 95003",
    "addr:street":"Freedom Blvd",
    "iso:country":"US",
    "sg:address":"UU Fellowship Hall 6401 Freedom Blvd",
    "sg:city":"Aptos",
    "sg:classifiers":[
        {
            "category":"Health Services",
            "subcategory":"Clinic",
            "type":"Services"
        }
    ],
    "sg:phone":"+1 831 662 2895",
    "sg:postcode":"95003",
    "sg:province":"CA",
    "sg:tags":[
        "counseling",
        "mental"
    ],
    "wof:name":"Lyme Disease Support Group",
    "wof:placetype":"venue"
},
  "geometry": {"coordinates":[-121.861496,36.985478],"type":"Point"}
}