{
  "type": "Feature",
  "properties": {
    "iso:country":"US",
    "sg:address":"102 N Freeman St",
    "sg:city":"Oceanside",
    "sg:classifiers":[
        {
            "category":"Shopping",
            "subcategory":"Bicycles & Sporting Goods",
            "type":"Retail Goods"
        }
    ],
    "sg:phone":"+1 760 722 6363",
    "sg:postcode":"92054",
    "sg:province":"CA",
    "sg:tags":[
        "surfboard"
    ],
    "wof:name":"Christian Surfers United State",
    "wof:placetype":"venue"
},
  "geometry": {"coordinates":[-117.378291,33.195936],"type":"Point"}
}