{
  "type": "Feature",
  "properties": {
    "addr:full":"3464 El Camino Real Santa Clara CA 95051",
    "addr:housenumber":"3464",
    "addr:postcode":"95051",
    "addr:street":"El Camino Real",
    "iso:country":"US",
    "sg:address":"3464 El Camino Real",
    "sg:city":"Santa Clara",
    "sg:classifiers":[
        {
            "category":"Shopping",
            "subcategory":"Bicycles & Sporting Goods",
            "type":"Retail Goods"
        },
        {
            "category":"Sports & Exercise",
            "subcategory":"Golf",
            "type":"Entertainment"
        }
    ],
    "sg:phone":"+1 408 247 0878",
    "sg:postcode":"95051",
    "sg:province":"CA",
    "wof:name":"U S Pro Golf",
    "wof:placetype":"venue"
},
  "geometry": {"coordinates":[-121.991574,37.352398],"type":"Point"}
}