{
  "type": "Feature",
  "properties": {
    "iso:country":"US",
    "sg:address":"14501 Hindry Ave",
    "sg:city":"Hawthorne",
    "sg:classifiers":[
        {
            "category":"Restaurant",
            "type":"Food & Drink"
        }
    ],
    "sg:phone":"+1 310 727 0403",
    "sg:postcode":"90250",
    "sg:province":"CA",
    "sg:website":"www.costco.com",
    "wof:name":"Costco Snack Bar",
    "wof:placetype":"venue"
},
  "geometry": {"coordinates":[-118.372745,33.898805],"type":"Point"}
}