{
  "type": "Feature",
  "properties": {
    "iso:country":"US",
    "sg:address":"13564 Imperial Hwy",
    "sg:city":"Santa Fe Springs",
    "sg:classifiers":[
        {
            "category":"Wholesale",
            "subcategory":"Groceries",
            "type":"Manufacturing & Wholesale Goods"
        }
    ],
    "sg:phone":"+1 562 407 2643",
    "sg:postcode":"90670",
    "sg:province":"CA",
    "wof:name":"G P Desilva & Sons SPICE USA",
    "wof:placetype":"venue"
},
  "geometry": {"coordinates":[-118.043406,33.916881],"type":"Point"}
}