{
  "type": "Feature",
  "properties": {
    "addr:full":"114 Frederick St San Francisco CA 94117",
    "addr:housenumber":"114",
    "addr:postcode":"94117",
    "addr:street":"Frederick St",
    "iso:country":"US",
    "sg:address":"114 Frederick St",
    "sg:city":"San Francisco",
    "sg:classifiers":[
        {
            "category":"Professional",
            "subcategory":"Business Services",
            "type":"Services"
        }
    ],
    "sg:phone":"+1 415 431 7741",
    "sg:postcode":"94117",
    "sg:province":"CA",
    "sg:tags":[
        "water",
        "treatment"
    ],
    "sg:website":"www.moviepostersltd.com",
    "wof:name":"Fredric Mae Assoc",
    "wof:placetype":"venue"
},
  "geometry": {"coordinates":[-122.445148,37.767463],"type":"Point"}
}