{
  "type": "Feature",
  "properties": {
    "addr:full":"44 Grande Paseo San Rafael CA 94903",
    "addr:housenumber":"44",
    "addr:postcode":"94903",
    "addr:street":"Grande Paseo",
    "iso:country":"US",
    "sg:address":"44 Grande Paseo",
    "sg:city":"San Rafael",
    "sg:classifiers":[
        {
            "category":"Manufacturing",
            "subcategory":"Printing",
            "type":"Manufacturing & Wholesale Goods"
        }
    ],
    "sg:phone":"+1 415 785 2888",
    "sg:postcode":"94903",
    "sg:province":"CA",
    "sg:tags":[
        "publisher",
        "software"
    ],
    "wof:name":"Acoustx",
    "wof:placetype":"venue"
},
  "geometry": {"coordinates":[-122.54134999999999,38.031716],"type":"Point"}
}