{
  "type": "Feature",
  "properties": {
    "iso:country":"US",
    "sg:address":"9022 W Pico Blvd",
    "sg:city":"Los Angeles",
    "sg:classifiers":[
        {
            "category":"Social Services",
            "type":"Services"
        }
    ],
    "sg:phone":"+1 310 777 0358",
    "sg:postcode":"90035",
    "sg:province":"CA",
    "sg:tags":[
        "youth",
        "organization",
        "center"
    ],
    "wof:name":"Chabad Persian Youth",
    "wof:placetype":"venue"
},
  "geometry": {"coordinates":[-118.387499,34.055193],"type":"Point"}
}