{
  "type": "Feature",
  "properties": {
    "iso:country":"US",
    "sg:address":"3895 Princeton Dr",
    "sg:city":"Santa Rosa",
    "sg:classifiers":[
        {
            "category":"Health Services",
            "subcategory":"Optometrist",
            "type":"Services"
        }
    ],
    "sg:phone":"+1 707 526 4050",
    "sg:postcode":"95405",
    "sg:province":"CA",
    "wof:name":"Bennett Valley Optometry Group",
    "wof:placetype":"venue"
},
  "geometry": {"coordinates":[-122.676375,38.443379],"type":"Point"}
}