{
  "type": "Feature",
  "properties": {
    "iso:country":"US",
    "sg:address":"320 13th St Ste 306",
    "sg:city":"Oakland",
    "sg:classifiers":[
        {
            "category":"Real Estate",
            "subcategory":"Real Estate Services",
            "type":"Services"
        },
        {
            "category":"Real Estate",
            "subcategory":"Real Estate Agent",
            "type":"Services"
        }
    ],
    "sg:phone":"+1 510 893 6888",
    "sg:postcode":"94612",
    "sg:province":"CA",
    "sg:tags":[
        "buyer",
        "broker"
    ],
    "wof:name":"Bay Cities Realty & Servi",
    "wof:placetype":"venue"
},
  "geometry": {"coordinates":[-122.26853300000001,37.802426],"type":"Point"}
}