{
  "type": "Feature",
  "properties": {
    "addr:full":"2286 46th Ave San Francisco CA 94116",
    "addr:housenumber":"2286",
    "addr:postcode":"94116",
    "addr:street":"46Th Ave",
    "iso:country":"US",
    "sg:address":"2286 46th Ave",
    "sg:city":"San Francisco",
    "sg:classifiers":[
        {
            "category":"Taxi",
            "type":"Transportation"
        }
    ],
    "sg:phone":"+1 415 242 1191",
    "sg:postcode":"94116",
    "sg:province":"CA",
    "wof:name":"Yellow Cab",
    "wof:placetype":"venue"
},
  "geometry": {"coordinates":[-122.504591,37.743892],"type":"Point"}
}