{
  "type": "Feature",
  "properties": {
    "iso:country":"US",
    "sg:address":"1150 Simpson Way",
    "sg:city":"Escondido",
    "sg:classifiers":[
        {
            "category":"Building & Trades",
            "subcategory":"Construction",
            "type":"Services"
        }
    ],
    "sg:phone":"+1 760 510 4969",
    "sg:postcode":"92029",
    "sg:province":"CA",
    "sg:tags":[
        "product",
        "earthquake"
    ],
    "wof:name":"Trev Co",
    "wof:placetype":"venue"
},
  "geometry": {"coordinates":[-117.105023,33.120959],"type":"Point"}
}