{
  "type": "Feature",
  "properties": {
    "addr:full":"8829 Greenleaf Ave Whittier CA 90602",
    "addr:housenumber":"8829",
    "addr:postcode":"90602",
    "addr:street":"Greenleaf Ave",
    "iso:country":"US",
    "sg:address":"8829 Greenleaf Ave",
    "sg:city":"Whittier",
    "sg:classifiers":[
        {
            "category":"Food & Beverages",
            "subcategory":"Groceries & Convenience Stores",
            "type":"Retail Goods"
        }
    ],
    "sg:phone":"+1 562 693 3250",
    "sg:postcode":"90602",
    "sg:province":"CA",
    "wof:name":"Carlos Market",
    "wof:placetype":"venue"
},
  "geometry": {"coordinates":[-118.321646,33.959837],"type":"Point"}
}