{
  "type": "Feature",
  "properties": {
    "iso:country":"US",
    "sg:address":"1248 Reamwood Avenue",
    "sg:city":"Sunnyvale",
    "sg:classifiers":[
        {
            "category":"Professional",
            "subcategory":"Management & Consulting",
            "type":"Services"
        }
    ],
    "sg:phone":"+1 408 743 4400",
    "sg:postcode":"94089 ",
    "sg:province":"CA",
    "sg:website":"http://www.xoriant.com",
    "wof:name":"Xoriant",
    "wof:placetype":"venue"
},
  "geometry": {"coordinates":[-121.988455,37.409375],"type":"Point"}
}