{
  "type": "Feature",
  "properties": {
    "iso:country":"US",
    "sg:address":"2265 W Lincoln Ave",
    "sg:city":"Anaheim",
    "sg:classifiers":[
        {
            "category":"Health Services",
            "subcategory":"Dentist",
            "type":"Services"
        }
    ],
    "sg:phone":"+1 714 491 8600",
    "sg:postcode":"92801",
    "sg:province":"CA",
    "sg:website":"www.7daydental.com",
    "wof:name":"7 Day Dental",
    "wof:placetype":"venue"
},
  "geometry": {"coordinates":[-117.96204,33.832953],"type":"Point"}
}