{
  "type": "Feature",
  "properties": {
    "addr:full":"1357 Garner Ave Salinas CA 93905",
    "addr:housenumber":"1357",
    "addr:postcode":"93905",
    "addr:street":"Garner Ave",
    "iso:country":"US",
    "sg:address":"1357 Garner Ave",
    "sg:city":"Salinas",
    "sg:classifiers":[
        {
            "category":"Real Estate",
            "subcategory":"Real Estate Operator",
            "type":"Services"
        }
    ],
    "sg:phone":"+1 831 758 4744",
    "sg:postcode":"93905",
    "sg:province":"CA",
    "sg:tags":[
        "apartment"
    ],
    "wof:name":"Thorndike Apartments",
    "wof:placetype":"venue"
},
  "geometry": {"coordinates":[-121.61035200000001,36.680915],"type":"Point"}
}