{
  "type": "Feature",
  "properties": {
    "addr:full":"3148 Willow Ave Clovis CA 93612",
    "addr:housenumber":"3148",
    "addr:postcode":"93612",
    "addr:street":"Willow Ave",
    "iso:country":"US",
    "sg:address":"3148 Willow Ave",
    "sg:city":"Clovis",
    "sg:classifiers":[
        {
            "category":"Professional",
            "subcategory":"Accounting & Tax Preparation",
            "type":"Services"
        }
    ],
    "sg:phone":"+1 559 291 0277",
    "sg:postcode":"93612",
    "sg:province":"CA",
    "sg:tags":[
        "accountant"
    ],
    "wof:name":"Sampson & Sampson",
    "wof:placetype":"venue"
},
  "geometry": {"coordinates":[-119.72726,36.794738],"type":"Point"}
}