{
  "type": "Feature",
  "properties": {
    "addr:full":"14137 Durhullen Dr Poway CA 92064",
    "addr:housenumber":"14137",
    "addr:postcode":"ca 92064",
    "addr:street":"Durhullen Dr",
    "iso:country":"US",
    "sg:address":"14137 Durhullen Dr",
    "sg:city":"Poway",
    "sg:classifiers":[
        {
            "category":"Manufacturing",
            "subcategory":"Chemicals & Compounds",
            "type":"Manufacturing & Wholesale Goods"
        }
    ],
    "sg:phone":"+1 858 748 3995",
    "sg:postcode":"92064",
    "sg:province":"CA",
    "wof:name":"Roche Inc",
    "wof:placetype":"venue"
},
  "geometry": {"coordinates":[-117.025441,32.984688],"type":"Point"}
}