{
  "type": "Feature",
  "properties": {
    "addr:full":"608 12th St Paso Robles CA 93446",
    "addr:housenumber":"608",
    "addr:postcode":"93446",
    "addr:street":"12Th St",
    "iso:country":"US",
    "sg:address":"608 12th St",
    "sg:city":"Paso Robles",
    "sg:classifiers":[
        {
            "category":"Restaurant",
            "type":"Food & Drink"
        }
    ],
    "sg:phone":"+1 805 238 5637",
    "sg:postcode":"93446",
    "sg:province":"CA",
    "sg:website":"www.eatatjoes.net",
    "wof:name":"Joe's Place",
    "wof:placetype":"venue"
},
  "geometry": {"coordinates":[-120.690494,35.626734],"type":"Point"}
}