{
  "type": "Feature",
  "properties": {
    "addr:full":"8680 Greenback Ln Orangevale CA 95662",
    "addr:housenumber":"8680",
    "addr:postcode":"95662",
    "addr:street":"Greenback Ln",
    "iso:country":"US",
    "sg:address":"8680 Greenback Ln",
    "sg:city":"Orangevale",
    "sg:classifiers":[
        {
            "category":"Health Services",
            "subcategory":"Medical Lab",
            "type":"Services"
        }
    ],
    "sg:phone":"+1 916 987 2626",
    "sg:postcode":"95662",
    "sg:province":"CA",
    "sg:tags":[
        "laboratory",
        "clinical"
    ],
    "wof:name":"Unilab Corporation",
    "wof:placetype":"venue"
},
  "geometry": {"coordinates":[-121.23602099999999,38.678496],"type":"Point"}
}