{
  "type": "Feature",
  "properties": {
    "iso:country":"US",
    "sg:address":"13591 Yockey St",
    "sg:city":"Garden Grove",
    "sg:classifiers":[
        {
            "category":"Building & Trades",
            "subcategory":"Landscaping Services",
            "type":"Services"
        }
    ],
    "sg:phone":"+1 714 892 6756",
    "sg:postcode":"92844",
    "sg:province":"CA",
    "sg:tags":[
        "landscape",
        "contractor"
    ],
    "wof:name":"Valley View Landscape Inc",
    "wof:placetype":"venue"
},
  "geometry": {"coordinates":[-117.97676300000001,33.764607],"type":"Point"}
}