{
  "type": "Feature",
  "properties": {
    "addr:full":"4629 Eagle Rock Blvd Los Angeles CA 90041",
    "addr:housenumber":"4629",
    "addr:postcode":"90041",
    "addr:street":"Eagle Rock Blvd",
    "iso:country":"US",
    "sg:address":"4629 Eagle Rock Blvd",
    "sg:city":"Los Angeles",
    "sg:classifiers":[
        {
            "category":"Personal",
            "subcategory":"Beauty Salon",
            "type":"Services"
        },
        {
            "category":"Personal",
            "subcategory":"Hair Removal",
            "type":"Services"
        }
    ],
    "sg:phone":"+1 323 272 5052",
    "sg:postcode":"90041",
    "sg:province":"CA",
    "sg:tags":[
        "spa"
    ],
    "wof:name":"Arch Studio",
    "wof:placetype":"venue"
},
  "geometry": {"coordinates":[-118.217805,34.128444],"type":"Point"}
}