{
  "type": "Feature",
  "properties": {
    "iso:country":"US",
    "sg:address":"9192 Topaz Way",
    "sg:city":"San Diego",
    "sg:classifiers":[
        {
            "category":"Social Services",
            "subcategory":"Child Care",
            "type":"Services"
        },
        {
            "category":"Education",
            "subcategory":"Preschool",
            "type":"Public Place"
        },
        {
            "category":"Education",
            "subcategory":"School",
            "type":"Public Place"
        }
    ],
    "sg:phone":"+1 858 576 4387",
    "sg:postcode":"92123",
    "sg:province":"CA",
    "sg:tags":[
        "elementary",
        "day"
    ],
    "sg:website":"www.kindercare.com",
    "wof:name":"KinderCare",
    "wof:placetype":"venue"
},
  "geometry": {"coordinates":[-117.134225,32.834294],"type":"Point"}
}