{
  "type": "Feature",
  "properties": {
    "addr:full":"494 Park Blvd Orange Cove CA 93646",
    "addr:housenumber":"494",
    "addr:postcode":"93646",
    "addr:street":"Park Blvd",
    "iso:country":"US",
    "sg:address":"494 Park Blvd",
    "sg:city":"Orange Cove",
    "sg:classifiers":[
        {
            "category":"Manufacturing",
            "subcategory":"Tools & Machinery",
            "type":"Manufacturing & Wholesale Goods"
        },
        {
            "category":"Retail",
            "subcategory":"Auto Repair",
            "type":"Services"
        }
    ],
    "sg:phone":"+1 559 626 3626",
    "sg:postcode":"93646",
    "sg:province":"CA",
    "sg:tags":[
        "shop",
        "industrial",
        "mfg",
        "automobile",
        "machine",
        "automotive"
    ],
    "wof:name":"J C's Cylinder Head Repair",
    "wof:placetype":"venue"
},
  "geometry": {"coordinates":[-119.310242,36.624558],"type":"Point"}
}