{
  "type": "Feature",
  "properties": {
    "iso:country":"US",
    "sg:address":"6040 San Rafael Ct",
    "sg:city":"Alta Loma",
    "sg:classifiers":[
        {
            "category":"Building & Trades",
            "subcategory":"Construction",
            "type":"Services"
        }
    ],
    "sg:phone":"+1 909 404 0979",
    "sg:postcode":"91737",
    "sg:province":"CA",
    "sg:tags":[
        "general",
        "contractor"
    ],
    "wof:name":"Falstone Construction Svc Co",
    "wof:placetype":"venue"
},
  "geometry": {"coordinates":[-117.577439,34.146018],"type":"Point"}
}