{
  "type": "Feature",
  "properties": {
    "iso:country":"US",
    "sg:address":"933 S Hoover St",
    "sg:city":"Los Angeles",
    "sg:classifiers":[
        {
            "category":"Social Services",
            "subcategory":"Adult Care",
            "type":"Services"
        }
    ],
    "sg:phone":"+1 213 368 0118",
    "sg:postcode":"90006",
    "sg:province":"CA",
    "sg:tags":[
        "organization",
        "senior",
        "citizen"
    ],
    "wof:name":"Wise Senior Svc",
    "wof:placetype":"venue"
},
  "geometry": {"coordinates":[-118.28430899999999,34.054848],"type":"Point"}
}