{
  "type": "Feature",
  "properties": {
    "addr:full":"15593 Carrie Dr Grass Valley CA 95949",
    "addr:housenumber":"15593",
    "addr:postcode":"95949",
    "addr:street":"Carrie Dr",
    "iso:country":"US",
    "sg:address":"15593 Carrie Dr",
    "sg:city":"Grass Valley",
    "sg:classifiers":[
        {
            "category":"Building & Trades",
            "subcategory":"Construction",
            "type":"Services"
        }
    ],
    "sg:phone":"+1 530 273 7688",
    "sg:postcode":"95949",
    "sg:province":"CA",
    "sg:tags":[
        "handyman"
    ],
    "wof:name":"Mountain Style Handyman Svc",
    "wof:placetype":"venue"
},
  "geometry": {"coordinates":[-121.040076,39.141194],"type":"Point"}
}