{
  "type": "Feature",
  "properties": {
    "addr:full":"4051 Broad Street, Suite #220 San Luis Obispo CA 93401",
    "addr:housenumber":"4051",
    "addr:postcode":"93401",
    "addr:street":"Broad Street Suite # 220",
    "iso:country":"US",
    "sg:address":"4051 Broad Street, Suite #220",
    "sg:city":"San Luis Obispo",
    "sg:classifiers":[
        {
            "category":"Professional",
            "subcategory":"Computer Services",
            "type":"Services"
        }
    ],
    "sg:phone":"+1 877 755 4279",
    "sg:postcode":"93401",
    "sg:province":"CA",
    "sg:website":"http://mindbodyonline.com",
    "wof:name":"MINDBODY",
    "wof:placetype":"venue"
},
  "geometry": {"coordinates":[-120.642197,35.246582],"type":"Point"}
}