{
  "type": "Feature",
  "properties": {
    "iso:country":"US",
    "sg:address":"1762 Technology Dr",
    "sg:city":"San Jose",
    "sg:classifiers":[
        {
            "category":"Professional",
            "subcategory":"Management & Consulting",
            "type":"Services"
        }
    ],
    "sg:phone":"+1 408 986 8989",
    "sg:postcode":"95110",
    "sg:province":"CA",
    "sg:tags":[
        "consultant",
        "business"
    ],
    "sg:website":"www.vantone.com",
    "wof:name":"Vantone International Group",
    "wof:placetype":"venue"
},
  "geometry": {"coordinates":[-121.919268,37.368289],"type":"Point"}
}