{
  "type": "Feature",
  "properties": {
    "iso:country":"US",
    "sg:address":"73386 Hwy 111",
    "sg:city":"Palm Desert",
    "sg:classifiers":[
        {
            "category":"Personal",
            "subcategory":"Barber",
            "type":"Services"
        }
    ],
    "sg:phone":"+1 760 674 4797",
    "sg:postcode":"92260",
    "sg:province":"CA",
    "wof:name":"Di Bella Donna",
    "wof:placetype":"venue"
},
  "geometry": {"coordinates":[-116.384438,33.721465],"type":"Point"}
}