{
  "type": "Feature",
  "properties": {
    "addr:full":"1139 Treat Ave San Francisco CA 94110",
    "addr:housenumber":"1139",
    "addr:postcode":"94110",
    "addr:street":"Treat Ave",
    "iso:country":"US",
    "sg:address":"1139 Treat Ave",
    "sg:city":"San Francisco",
    "sg:classifiers":[
        {
            "category":"Travel",
            "subcategory":"Hotels & Motels",
            "type":"Entertainment"
        },
        {
            "category":"Travel",
            "subcategory":"Bed & Breakfast",
            "type":"Entertainment"
        }
    ],
    "sg:phone":"+1 415 513 0079",
    "sg:postcode":"94110",
    "sg:province":"CA",
    "sg:tags":[
        "house",
        "guest"
    ],
    "sg:website":"www.balmyalley.com/gardenstudio",
    "wof:name":"Garden Studio",
    "wof:placetype":"venue"
},
  "geometry": {"coordinates":[-122.412954,37.751889],"type":"Point"}
}