{
  "type": "Feature",
  "properties": {
    "iso:country":"US",
    "sg:address":"6165 Greenwich Drive Suite 320",
    "sg:city":"San Diego",
    "sg:classifiers":[
        {
            "category":"Professional",
            "subcategory":"Computer Services",
            "type":"Services"
        }
    ],
    "sg:phone":"+1 888 587 6587",
    "sg:postcode":"92122",
    "sg:province":"CA",
    "sg:website":"http://www.brickfish.com/",
    "wof:name":"brickfish",
    "wof:placetype":"venue"
},
  "geometry": {"coordinates":[-117.18662,32.855575],"type":"Point"}
}