{
  "type": "Feature",
  "properties": {
    "addr:full":"180 Otto Circle Sacramento CA 95822",
    "addr:housenumber":"180",
    "addr:postcode":"95822",
    "addr:street":"Otto Circle",
    "iso:country":"US",
    "sg:address":"180 Otto Circle",
    "sg:city":"Sacramento",
    "sg:classifiers":[
        {
            "category":"Professional",
            "type":"Services"
        },
        {
            "category":"Restaurant",
            "type":"Food & Drink"
        },
        {
            "category":"Retail",
            "subcategory":"Event Space",
            "type":"Services"
        }
    ],
    "sg:phone":"+1 916 424 3520",
    "sg:postcode":"95822",
    "sg:province":"CA",
    "sg:tags":[
        "style",
        "family",
        "facility",
        "house",
        "hall",
        "lunch",
        "american",
        "reception",
        "caterer",
        "barbecue",
        "breakfast",
        "steak",
        "brunch",
        "banquet",
        "barbeque"
    ],
    "sg:website":"www.jrtexasbbq.com/index.html",
    "wof:name":"JR's Texas Bar-B-Cue",
    "wof:placetype":"venue"
},
  "geometry": {"coordinates":[-121.476997,38.508099],"type":"Point"}
}