{
  "type": "Feature",
  "properties": {
    "iso:country":"US",
    "sg:address":"14701 Adams St Ste B",
    "sg:city":"Midway City",
    "sg:classifiers":[
        {
            "category":"Building & Trades",
            "subcategory":"Cleaning & Sanitation",
            "type":"Services"
        }
    ],
    "sg:phone":"+1 714 554 6727",
    "sg:postcode":"92655",
    "sg:province":"CA",
    "sg:tags":[
        "carpet"
    ],
    "wof:name":"Overall Carpet Dyeing & Restoration",
    "wof:placetype":"venue"
},
  "geometry": {"coordinates":[-117.988894,33.748874],"type":"Point"}
}