{
  "type": "Feature",
  "properties": {
    "addr:full":"720 Cholla Rd Chula Vista CA 91910",
    "addr:housenumber":"720",
    "addr:postcode":"91910",
    "addr:street":"Cholla Rd",
    "iso:country":"US",
    "sg:address":"720 Cholla Rd",
    "sg:city":"Chula Vista",
    "sg:classifiers":[
        {
            "category":"Food & Beverages",
            "subcategory":"Bakery",
            "type":"Retail Goods"
        }
    ],
    "sg:phone":"+1 619 421 0503",
    "sg:postcode":"91910",
    "sg:province":"CA",
    "sg:tags":[
        "bagel"
    ],
    "wof:name":"Bagel Bar",
    "wof:placetype":"venue"
},
  "geometry": {"coordinates":[-117.03043099999999,32.62774],"type":"Point"}
}