{
  "type": "Feature",
  "properties": {
    "addr:full":"21618 Los Alimos St Chatsworth CA 91311",
    "addr:housenumber":"21618",
    "addr:postcode":"91311",
    "addr:street":"Los Alimos St",
    "iso:country":"US",
    "sg:address":"21618 Los Alimos St",
    "sg:city":"Chatsworth",
    "sg:classifiers":[
        {
            "category":"Shopping",
            "subcategory":"Clothing, Apparel, & Fashions",
            "type":"Retail Goods"
        }
    ],
    "sg:phone":"+1 818 718 8808",
    "sg:postcode":"91311",
    "sg:province":"CA",
    "sg:tags":[
        "dancing",
        "supply"
    ],
    "wof:name":"Dance Kinetices",
    "wof:placetype":"venue"
},
  "geometry": {"coordinates":[-118.601507,34.265123],"type":"Point"}
}