{
  "type": "Feature",
  "properties": {
    "iso:country":"US",
    "sg:address":"414 1st St",
    "sg:city":"Woodland",
    "sg:classifiers":[
        {
            "category":"Personal",
            "subcategory":"Barber",
            "type":"Services"
        }
    ],
    "sg:phone":"+1 530 662 7661",
    "sg:postcode":"95695",
    "sg:province":"CA",
    "wof:name":"Top Hat Barbers",
    "wof:placetype":"venue"
},
  "geometry": {"coordinates":[-121.773247,38.676894],"type":"Point"}
}