{
  "type": "Feature",
  "properties": {
    "iso:country":"US",
    "sg:address":"21 Harbor Rd",
    "sg:city":"San Francisco",
    "sg:classifiers":[
        {
            "category":"Professional",
            "type":"Services"
        }
    ],
    "sg:phone":"+1 415 970 8559",
    "sg:postcode":"94124",
    "sg:province":"CA",
    "wof:name":"Festus Tayo",
    "wof:placetype":"venue"
},
  "geometry": {"coordinates":[-122.377562,37.731537],"type":"Point"}
}