{
  "type": "Feature",
  "properties": {
    "iso:country":"US",
    "sg:address":"576 B St",
    "sg:city":"Santa Rosa",
    "sg:classifiers":[
        {
            "category":"Social Services",
            "type":"Services"
        }
    ],
    "sg:phone":"+1 707 525 8710",
    "sg:postcode":"95401",
    "sg:province":"CA",
    "sg:tags":[
        "counselor",
        "marriage",
        "family"
    ],
    "wof:name":"Jo Lauer",
    "wof:placetype":"venue"
},
  "geometry": {"coordinates":[-122.718267,38.443333],"type":"Point"}
}