{
  "type": "Feature",
  "properties": {
    "iso:country":"US",
    "sg:address":"2805 Twelve Oaks Dr",
    "sg:city":"Penryn",
    "sg:classifiers":[
        {
            "category":"Banks & Credit Unions",
            "subcategory":"Investment Brokerage",
            "type":"Services"
        },
        {
            "category":"Real Estate",
            "subcategory":"Developer",
            "type":"Services"
        }
    ],
    "sg:phone":"+1 916 933 2185",
    "sg:postcode":"95663",
    "sg:province":"CA",
    "sg:tags":[
        "investing"
    ],
    "sg:website":"http://www.dupriest.com",
    "wof:name":"The Trace Corp",
    "wof:placetype":"venue"
},
  "geometry": {"coordinates":[-121.156372,38.843552],"type":"Point"}
}