{
  "type": "Feature",
  "properties": {
    "iso:country":"US",
    "sg:address":"1630 Aviation Blvd",
    "sg:city":"Redondo Beach",
    "sg:classifiers":[
        {
            "category":"Building & Trades",
            "subcategory":"Plumbing",
            "type":"Services"
        }
    ],
    "sg:phone":"+1 310 379 0932",
    "sg:postcode":"90278",
    "sg:province":"CA",
    "sg:tags":[
        "plumbing",
        "heating",
        "contractor"
    ],
    "wof:name":"Bay View Plumbing & Heating",
    "wof:placetype":"venue"
},
  "geometry": {"coordinates":[-118.38237700000001,33.870512],"type":"Point"}
}