{
  "type": "Feature",
  "properties": {
    "iso:country":"US",
    "sg:address":"17851 Sky Park Cir",
    "sg:city":"Irvine",
    "sg:classifiers":[
        {
            "category":"Food & Beverages",
            "subcategory":"Specialty",
            "type":"Retail Goods"
        }
    ],
    "sg:phone":"+1 949 833 2929",
    "sg:postcode":"92614",
    "sg:province":"CA",
    "sg:tags":[
        "health",
        "market",
        "diet"
    ],
    "wof:name":"Healthy Gourmet",
    "wof:placetype":"venue"
},
  "geometry": {"coordinates":[-117.857241,33.691198],"type":"Point"}
}