{
  "type": "Feature",
  "properties": {
    "iso:country":"US",
    "sg:address":"19010 Brookhurst",
    "sg:city":"Huntington Beach",
    "sg:classifiers":[
        {
            "category":"Personal",
            "subcategory":"Beauty Salon",
            "type":"Services"
        }
    ],
    "sg:phone":"+1 714 914 4966",
    "sg:postcode":"92646",
    "sg:province":"CA",
    "sg:tags":[
        "spa"
    ],
    "sg:website":"Www.brazilianblowoutnow.com",
    "wof:name":"Brazilian Blowout",
    "wof:placetype":"venue"
},
  "geometry": {"coordinates":[-117.95396700000001,33.686504],"type":"Point"}
}