{
  "type": "Feature",
  "properties": {
    "addr:full":"3269 Seldon Ct Fremont CA 94539",
    "addr:postcode":"3269;94539",
    "addr:street":"Seldon Ct",
    "iso:country":"US",
    "sg:address":"3269 Seldon Ct",
    "sg:city":"Fremont",
    "sg:classifiers":[
        {
            "category":"Building & Trades",
            "subcategory":"Plumbing",
            "type":"Services"
        }
    ],
    "sg:phone":"+1 510 651 1800",
    "sg:postcode":"94539",
    "sg:province":"CA",
    "sg:tags":[
        "conditioning",
        "air",
        "system",
        "contractor"
    ],
    "sg:website":"www.airtechmechanical.com",
    "wof:name":"Airtech Mechanical Inc",
    "wof:placetype":"venue"
},
  "geometry": {"coordinates":[-121.946461,37.518944],"type":"Point"}
}