{
  "type": "Feature",
  "properties": {
    "iso:country":"US",
    "sg:address":"3295 Azevedo Dr",
    "sg:city":"Sacramento",
    "sg:classifiers":[
        {
            "category":"Professional",
            "type":"Services"
        },
        {
            "category":"Arts & Performance",
            "subcategory":"Music",
            "type":"Entertainment"
        }
    ],
    "sg:phone":"+1 916 925 0558",
    "sg:postcode":"95833",
    "sg:province":"CA",
    "sg:tags":[
        "record",
        "producer",
        "label"
    ],
    "wof:name":"Guaranteed Records Inc",
    "wof:placetype":"venue"
},
  "geometry": {"coordinates":[-121.50848999999999,38.626965],"type":"Point"}
}