{
  "type": "Feature",
  "properties": {
    "addr:full":"806 S Alvarado Street Los Angeles CA 90057",
    "addr:housenumber":"806",
    "addr:postcode":"90057",
    "addr:street":"S Alvarado Street",
    "iso:country":"US",
    "sg:address":"806 S Alvarado Street",
    "sg:city":"Los Angeles",
    "sg:classifiers":[
        {
            "category":"Restaurant",
            "type":"Food & Drink"
        }
    ],
    "sg:phone":"+1 213 380 6400",
    "sg:postcode":"90057",
    "sg:province":"CA",
    "wof:name":"Flor Blanca Restaurant",
    "wof:placetype":"venue"
},
  "geometry": {"coordinates":[-118.278182,34.054552],"type":"Point"}
}