{
  "type": "Feature",
  "properties": {
    "addr:full":"5229 Riverton Ave North Hollywood CA 91601",
    "addr:housenumber":"5229",
    "addr:postcode":"91601",
    "addr:street":"Riverton Ave",
    "iso:country":"US",
    "sg:address":"5229 Riverton Ave",
    "sg:city":"North Hollywood",
    "sg:classifiers":[
        {
            "category":"Utilities",
            "subcategory":"Cable",
            "type":"Services"
        }
    ],
    "sg:phone":"+1 818 487 2772",
    "sg:postcode":"91601",
    "sg:province":"CA",
    "sg:tags":[
        "television"
    ],
    "wof:name":"Express Satellite Service",
    "wof:placetype":"venue"
},
  "geometry": {"coordinates":[-118.365438,34.167603],"type":"Point"}
}