{
  "type": "Feature",
  "properties": {
    "iso:country":"US",
    "sg:address":"545 2nd St",
    "sg:city":"Encinitas",
    "sg:classifiers":[
        {
            "category":"Professional",
            "subcategory":"Research",
            "type":"Services"
        }
    ],
    "sg:phone":"+1 760 635 4300",
    "sg:postcode":"92024",
    "sg:province":"CA",
    "sg:tags":[
        "market",
        "analysis"
    ],
    "sg:website":"www.metafactsusa.com",
    "wof:name":"Metafacts",
    "wof:placetype":"venue"
},
  "geometry": {"coordinates":[-117.294607,33.045181],"type":"Point"}
}