{
  "type": "Feature",
  "properties": {
    "iso:country":"US",
    "sg:address":"1184 Monroe St Ste 6",
    "sg:city":"Salinas",
    "sg:classifiers":[
        {
            "category":"Professional",
            "subcategory":"Lawyer & Legal Services",
            "type":"Services"
        }
    ],
    "sg:phone":"+1 800 638 4878",
    "sg:postcode":"93906",
    "sg:province":"CA",
    "sg:tags":[
        "personal",
        "injury"
    ],
    "wof:name":"PERSONAL INJURY AND DEATH",
    "wof:placetype":"venue"
},
  "geometry": {"coordinates":[-121.66128,36.697759],"type":"Point"}
}