{
  "type": "Feature",
  "properties": {
    "iso:country":"US",
    "sg:address":"301 Lombard St",
    "sg:city":"Oxnard",
    "sg:classifiers":[
        {
            "category":"Home & Garden",
            "subcategory":"Building Materials",
            "type":"Retail Goods"
        }
    ],
    "sg:phone":"+1 805 983 8283",
    "sg:postcode":"93030",
    "sg:province":"CA",
    "sg:website":"www.obmsales.com",
    "wof:name":"Pro Wall Building Products",
    "wof:placetype":"venue"
},
  "geometry": {"coordinates":[-119.14893600000001,34.204242],"type":"Point"}
}