{
  "type": "Feature",
  "properties": {
    "iso:country":"US",
    "sg:address":"38930 Blacow Rd",
    "sg:city":"Fremont",
    "sg:classifiers":[
        {
            "category":"Banks & Credit Unions",
            "subcategory":"Bank",
            "type":"Services"
        }
    ],
    "sg:phone":"+1 510 792 9500",
    "sg:postcode":"94536",
    "sg:province":"CA",
    "sg:tags":[
        "loan",
        "real estate"
    ],
    "wof:name":"Fidelity Brokers",
    "wof:placetype":"venue"
},
  "geometry": {"coordinates":[-121.999382,37.536946],"type":"Point"}
}