{
  "type": "Feature",
  "properties": {
    "addr:full":"16511 S Western Avenue Gardena CA 90247",
    "addr:housenumber":"16511",
    "addr:postcode":"90247",
    "addr:street":"S Western Avenue",
    "iso:country":"US",
    "sg:address":"16511 S Western Avenue",
    "sg:city":"Gardena",
    "sg:classifiers":[
        {
            "category":"Home & Garden",
            "subcategory":"Garden Supply",
            "type":"Retail Goods"
        },
        {
            "category":"Shopping",
            "subcategory":"Florist",
            "type":"Retail Goods"
        }
    ],
    "sg:phone":"+1 310 327 3034",
    "sg:postcode":"90247",
    "sg:province":"CA",
    "sg:tags":[
        "nursery",
        "gardening"
    ],
    "wof:name":"Kiku Florist & Gifts",
    "wof:placetype":"venue"
},
  "geometry": {"coordinates":[-118.308993,33.880586],"type":"Point"}
}