{
  "type": "Feature",
  "properties": {
    "iso:country":"US",
    "sg:address":"42640 Whittier Ave",
    "sg:city":"Hemet",
    "sg:classifiers":[
        {
            "category":"Shopping",
            "subcategory":"Clothing, Apparel, & Fashions",
            "type":"Retail Goods"
        }
    ],
    "sg:phone":"+1 951 766 1934",
    "sg:postcode":"92544",
    "sg:province":"CA",
    "sg:tags":[
        "salvage",
        "surplus",
        "merchandise"
    ],
    "wof:name":"Ifg Assoc",
    "wof:placetype":"venue"
},
  "geometry": {"coordinates":[-116.917856,33.736973],"type":"Point"}
}