{
  "type": "Feature",
  "properties": {
    "addr:full":"655 Mariners Island Blvd Ste 302 San Mateo CA 94404",
    "addr:housenumber":"655",
    "addr:postcode":"94404",
    "addr:street":"Mariners Island Blvd Ste 302",
    "iso:country":"US",
    "sg:address":"655 Mariners Island Blvd Ste 302",
    "sg:city":"San Mateo",
    "sg:classifiers":[
        {
            "category":"Banks & Credit Unions",
            "subcategory":"Financial Services",
            "type":"Services"
        }
    ],
    "sg:phone":"+1 650 341 0322",
    "sg:postcode":"94404",
    "sg:province":"CA",
    "sg:tags":[
        "broker",
        "mortgage"
    ],
    "wof:name":"E & F Financial Services Inc",
    "wof:placetype":"venue"
},
  "geometry": {"coordinates":[-122.28449000000001,37.564041],"type":"Point"}
}