{
  "type": "Feature",
  "properties": {
    "addr:full":"7633 Sunrise Blvd Citrus Heights CA 95610",
    "addr:housenumber":"7633",
    "addr:postcode":"95610",
    "addr:street":"Sunrise Blvd",
    "iso:country":"US",
    "sg:address":"7633 Sunrise Blvd",
    "sg:city":"Citrus Heights",
    "sg:classifiers":[
        {
            "category":"Retail",
            "subcategory":"Auto Repair",
            "type":"Services"
        }
    ],
    "sg:phone":"+1 916 725 1777",
    "sg:postcode":"95610",
    "sg:province":"CA",
    "sg:tags":[
        "body",
        "automobile",
        "painting"
    ],
    "wof:name":"Kniesel's Body Shop Parts Dept",
    "wof:placetype":"venue"
},
  "geometry": {"coordinates":[-121.27188,38.70417],"type":"Point"}
}