{
  "type": "Feature",
  "properties": {
    "addr:full":"7256 Wall St Yucca Valley CA 92284",
    "addr:housenumber":"7256",
    "addr:postcode":"92284",
    "addr:street":"Wall St",
    "iso:country":"US",
    "sg:address":"7256 Wall St",
    "sg:city":"Yucca Valley",
    "sg:classifiers":[
        {
            "category":"Retail",
            "subcategory":"Auto Repair",
            "type":"Services"
        }
    ],
    "sg:phone":"+1 760 365 0001",
    "sg:postcode":"92284",
    "sg:province":"CA",
    "sg:tags":[
        "truck"
    ],
    "wof:name":"Mark & Sons Transmissions",
    "wof:placetype":"venue"
},
  "geometry": {"coordinates":[-116.452028,34.121492],"type":"Point"}
}