{
  "type": "Feature",
  "properties": {
    "iso:country":"US",
    "sg:address":"1525 N Schnoor St Ste 103",
    "sg:city":"Madera",
    "sg:classifiers":[
        {
            "category":"Health Services",
            "subcategory":"Doctor",
            "type":"Services"
        },
        {
            "category":"Health Services",
            "subcategory":"Dentist",
            "type":"Services"
        }
    ],
    "sg:phone":"+1 559 673 3698",
    "sg:postcode":"93637",
    "sg:province":"CA",
    "sg:tags":[
        "dentists-oral",
        "physician",
        "maxillofacial",
        "surgeons",
        "surgery",
        "oral"
    ],
    "wof:name":"David L Rich Dmd",
    "wof:placetype":"venue"
},
  "geometry": {"coordinates":[-120.084418,36.974809],"type":"Point"}
}