{
  "type": "Feature",
  "properties": {
    "iso:country":"US",
    "sg:address":"20960 Sage Ln",
    "sg:city":"Tehachapi",
    "sg:classifiers":[
        {
            "category":"Health Services",
            "subcategory":"Doctor",
            "type":"Services"
        }
    ],
    "sg:phone":"+1 661 822 4640",
    "sg:postcode":"93561",
    "sg:province":"CA",
    "sg:tags":[
        "physician",
        "surgeon"
    ],
    "wof:name":"Kanwaljit S Gill MD",
    "wof:placetype":"venue"
},
  "geometry": {"coordinates":[-118.47873800000001,35.121091],"type":"Point"}
}