{
  "type": "Feature",
  "properties": {
    "addr:full":"5948 Russell Ln Forestville CA 95436",
    "addr:housenumber":"5948",
    "addr:postcode":"95436",
    "addr:street":"Russell Ln",
    "iso:country":"US",
    "sg:address":"5948 Russell Ln",
    "sg:city":"Forestville",
    "sg:classifiers":[
        {
            "category":"Retail",
            "subcategory":"Veterinary Services",
            "type":"Services"
        }
    ],
    "sg:phone":"+1 707 571 8442",
    "sg:postcode":"95436",
    "sg:province":"CA",
    "sg:tags":[
        "veterinarian"
    ],
    "wof:name":"Santa Rosa Animal Eye Center",
    "wof:placetype":"venue"
},
  "geometry": {"coordinates":[-122.876999,38.480999],"type":"Point"}
}