{
  "type": "Feature",
  "properties": {
    "addr:full":"6525 West Blvd Inglewood CA 90302",
    "addr:housenumber":"6525",
    "addr:postcode":"90302",
    "addr:street":"West Blvd",
    "iso:country":"US",
    "sg:address":"6525 West Blvd",
    "sg:city":"Inglewood",
    "sg:classifiers":[
        {
            "category":"Restaurant",
            "type":"Food & Drink"
        }
    ],
    "sg:phone":"+1 310 680 1602",
    "sg:postcode":"90302",
    "sg:province":"CA",
    "wof:name":"Water Show Granados",
    "wof:placetype":"venue"
},
  "geometry": {"coordinates":[-118.33519200000001,33.980582],"type":"Point"}
}