{
  "type": "Feature",
  "properties": {
    "addr:full":"721 Sandpiper Dr Laguna Beach CA 92651",
    "addr:housenumber":"721",
    "addr:postcode":"92651",
    "addr:street":"Sandpiper Dr",
    "iso:country":"US",
    "sg:address":"721 Sandpiper Dr",
    "sg:city":"Laguna Beach",
    "sg:classifiers":[
        {
            "category":"Building & Trades",
            "subcategory":"Construction",
            "type":"Services"
        }
    ],
    "sg:phone":"+1 949 499 5656",
    "sg:postcode":"92651",
    "sg:province":"CA",
    "sg:tags":[
        "boring",
        "drilling",
        "contractor"
    ],
    "wof:name":"Drilco Inc",
    "wof:placetype":"venue"
},
  "geometry": {"coordinates":[-117.75760200000001,33.524174],"type":"Point"}
}