{
  "type": "Feature",
  "properties": {
    "iso:country":"US",
    "sg:address":"1108 Main St",
    "sg:city":"Delano",
    "sg:classifiers":[
        {
            "category":"Professional",
            "subcategory":"Employment Agencies",
            "type":"Services"
        }
    ],
    "sg:phone":"+1 661 721 1165",
    "sg:postcode":"93215",
    "sg:province":"CA",
    "sg:tags":[
        "farm",
        "labor",
        "contractor"
    ],
    "wof:name":"Sweet Valley Harvesting",
    "wof:placetype":"venue"
},
  "geometry": {"coordinates":[-119.24615,35.771603],"type":"Point"}
}