{
  "type": "Feature",
  "properties": {
    "addr:full":"2939 E 11th St Los Angeles CA 90023",
    "addr:housenumber":"2939",
    "addr:postcode":"90023",
    "addr:street":"E 11Th St",
    "iso:country":"US",
    "sg:address":"2939 E 11th St",
    "sg:city":"Los Angeles",
    "sg:classifiers":[
        {
            "category":"Wholesale",
            "subcategory":"Apparel",
            "type":"Manufacturing & Wholesale Goods"
        }
    ],
    "sg:phone":"+1 323 981 1860",
    "sg:postcode":"90023",
    "sg:province":"CA",
    "sg:tags":[
        "dress",
        "trimmings"
    ],
    "wof:name":"Vogue Trimming",
    "wof:placetype":"venue"
},
  "geometry": {"coordinates":[-118.215013,34.021301],"type":"Point"}
}