{
  "type": "Feature",
  "properties": {
    "addr:full":"4163 W Washington Blvd Los Angeles CA 90018",
    "addr:housenumber":"4163",
    "addr:postcode":"90018",
    "addr:street":"W Washington Blvd",
    "iso:country":"US",
    "sg:address":"4163 W Washington Blvd",
    "sg:city":"Los Angeles",
    "sg:classifiers":[
        {
            "category":"Restaurant",
            "type":"Food & Drink"
        }
    ],
    "sg:phone":"+1 323 737 5002",
    "sg:postcode":"90018",
    "sg:province":"CA",
    "sg:tags":[
        "mexican"
    ],
    "wof:name":"El Venado",
    "wof:placetype":"venue"
},
  "geometry": {"coordinates":[-118.33013800000001,34.039884],"type":"Point"}
}