{
  "type": "Feature",
  "properties": {
    "addr:full":"600 E Market St Salinas CA 93905",
    "addr:housenumber":"600",
    "addr:postcode":"93905",
    "addr:street":"E Market St",
    "iso:country":"US",
    "sg:address":"600 E Market St",
    "sg:city":"Salinas",
    "sg:classifiers":[
        {
            "category":"Insurance",
            "subcategory":"Insurance Agent",
            "type":"Services"
        }
    ],
    "sg:phone":"+1 831 755 7828",
    "sg:postcode":"93905",
    "sg:province":"CA",
    "wof:name":"Ramirez Insurance Svc",
    "wof:placetype":"venue"
},
  "geometry": {"coordinates":[-121.634906,36.676856],"type":"Point"}
}