{
  "type": "Feature",
  "properties": {
    "addr:full":"42876 Rd 80 Dinuba CA 93618",
    "addr:postcode":"42876;93618",
    "addr:street":"Rd 80",
    "iso:country":"US",
    "sg:address":"42876 Rd 80",
    "sg:city":"Dinuba",
    "sg:classifiers":[
        {
            "category":"Bars & Pubs",
            "type":"Food & Drink"
        }
    ],
    "sg:phone":"+1 559 595 8443",
    "sg:postcode":"93618",
    "sg:province":"CA",
    "sg:tags":[
        "drinking"
    ],
    "wof:name":"Les & Lou's",
    "wof:placetype":"venue"
},
  "geometry": {"coordinates":[-119.39501,36.568627],"type":"Point"}
}