{
  "type": "Feature",
  "properties": {
    "iso:country":"US",
    "sg:address":"346 Jamacha Rd",
    "sg:city":"El Cajon",
    "sg:classifiers":[
        {
            "category":"Personal",
            "subcategory":"Adult",
            "type":"Services"
        }
    ],
    "sg:phone":"+1 619 593 7071",
    "sg:postcode":"92019",
    "sg:province":"CA",
    "sg:tags":[
        "escort"
    ],
    "wof:name":"Angels Escorts",
    "wof:placetype":"venue"
},
  "geometry": {"coordinates":[-116.933214,32.792113],"type":"Point"}
}