{
  "type": "Feature",
  "properties": {
    "iso:country":"US",
    "sg:address":"6137 Thornton Ave",
    "sg:city":"Newark",
    "sg:classifiers":[
        {
            "category":"Real Estate",
            "subcategory":"Real Estate Operator",
            "type":"Services"
        }
    ],
    "sg:phone":"+1 510 745 9169",
    "sg:postcode":"94560",
    "sg:province":"CA",
    "sg:tags":[
        "apartment"
    ],
    "wof:name":"Foxwood Townhomes HOA",
    "wof:placetype":"venue"
},
  "geometry": {"coordinates":[-122.032284,37.534921],"type":"Point"}
}