{
  "type": "Feature",
  "properties": {
    "addr:full":"8355 Monterey St Gilroy CA 95020",
    "addr:housenumber":"8355",
    "addr:postcode":"95020",
    "addr:street":"Monterey St",
    "iso:country":"US",
    "sg:address":"8355 Monterey St",
    "sg:city":"Gilroy",
    "sg:classifiers":[
        {
            "category":"Shopping",
            "subcategory":"Hobbies, Toys, & Games",
            "type":"Retail Goods"
        },
        {
            "category":"Shopping",
            "subcategory":"Crafts & Fabrics",
            "type":"Retail Goods"
        }
    ],
    "sg:phone":"+1 408 846 8841",
    "sg:postcode":"95020",
    "sg:province":"CA",
    "sg:tags":[
        "shop",
        "hobby",
        "model",
        "art",
        "supply"
    ],
    "wof:name":"All Aboard Junction",
    "wof:placetype":"venue"
},
  "geometry": {"coordinates":[-121.574489,37.018803],"type":"Point"}
}