{
  "type": "Feature",
  "properties": {
    "iso:country":"US",
    "sg:address":"1515 Arroyo Dr",
    "sg:city":"Laguna Beach",
    "sg:classifiers":[
        {
            "category":"Building & Trades",
            "subcategory":"Landscaping Services",
            "type":"Services"
        }
    ],
    "sg:phone":"+1 949 285 9533",
    "sg:postcode":"92651",
    "sg:province":"CA",
    "sg:tags":[
        "landscape"
    ],
    "wof:name":"Laurals Plantscaping",
    "wof:placetype":"venue"
},
  "geometry": {"coordinates":[-117.772818,33.558155],"type":"Point"}
}