{
  "type": "Feature",
  "properties": {
    "addr:full":"8159 Grand Ave Yucca Valley CA 92284",
    "addr:housenumber":"8159",
    "addr:postcode":"92284",
    "addr:street":"Grand Ave",
    "iso:country":"US",
    "sg:address":"8159 Grand Ave",
    "sg:city":"Yucca Valley",
    "sg:classifiers":[
        {
            "category":"Health Services",
            "subcategory":"Clinic",
            "type":"Services"
        }
    ],
    "sg:phone":"+1 760 365 1247",
    "sg:postcode":"92284",
    "sg:province":"CA",
    "sg:tags":[
        "home"
    ],
    "wof:name":"Alina's Home",
    "wof:placetype":"venue"
},
  "geometry": {"coordinates":[-116.426604,34.103821],"type":"Point"}
}