{
  "type": "Feature",
  "properties": {
    "addr:full":"324 Seville Way San Mateo CA 94402",
    "addr:housenumber":"324",
    "addr:postcode":"94402",
    "addr:street":"Seville Way",
    "iso:country":"US",
    "sg:address":"324 Seville Way",
    "sg:city":"San Mateo",
    "sg:classifiers":[
        {
            "category":"Education",
            "subcategory":"School",
            "type":"Public Place"
        }
    ],
    "sg:phone":"+1 650 548 0131",
    "sg:postcode":"94402",
    "sg:province":"CA",
    "wof:name":"Five Winds Charter School",
    "wof:placetype":"venue"
},
  "geometry": {"coordinates":[-122.325503,37.552776],"type":"Point"}
}