{
  "type": "Feature",
  "properties": {
    "iso:country":"US",
    "sg:address":"1065 W el Camino Real",
    "sg:city":"Mountain View",
    "sg:classifiers":[
        {
            "category":"Building & Trades",
            "subcategory":"Plumbing",
            "type":"Services"
        }
    ],
    "sg:phone":"+1 650 691 1111",
    "sg:postcode":"94040",
    "sg:province":"CA",
    "sg:tags":[
        "contractor"
    ],
    "wof:name":"National Mechanical",
    "wof:placetype":"venue"
},
  "geometry": {"coordinates":[-122.084206,37.385676],"type":"Point"}
}