{
  "type": "Feature",
  "properties": {
    "iso:country":"US",
    "sg:address":"10300 N Magnolia Ave",
    "sg:city":"Santee",
    "sg:classifiers":[
        {
            "category":"Education",
            "subcategory":"School",
            "type":"Public Place"
        }
    ],
    "sg:phone":"+1 619 956 2400",
    "sg:postcode":"92071",
    "sg:province":"CA",
    "sg:tags":[
        "high",
        "middle",
        "elementary"
    ],
    "wof:name":"Cajon Park Elementary School",
    "wof:placetype":"venue"
},
  "geometry": {"coordinates":[-116.971203,32.86596],"type":"Point"}
}