{
  "type": "Feature",
  "properties": {
    "iso:country":"US",
    "sg:address":"2800 N State St",
    "sg:city":"Ukiah",
    "sg:classifiers":[
        {
            "category":"Autos & Motor Vehicles",
            "subcategory":"Automobile Sales",
            "type":"Retail Goods"
        }
    ],
    "sg:phone":"+1 707 462 8817",
    "sg:postcode":"95482",
    "sg:province":"CA",
    "sg:tags":[
        "car",
        "dealer"
    ],
    "sg:website":"www.thurstonautoplaza.com",
    "wof:name":"Thurston Chevrolet-Oldsmobile",
    "wof:placetype":"venue"
},
  "geometry": {"coordinates":[-123.209755,39.187356],"type":"Point"}
}