{
  "type": "Feature",
  "properties": {
    "iso:country":"US",
    "sg:address":"1450 Chapin Ave",
    "sg:city":"Burlingame",
    "sg:classifiers":[
        {
            "category":"Health Services",
            "subcategory":"Clinic",
            "type":"Services"
        },
        {
            "category":"Personal",
            "type":"Services"
        },
        {
            "category":"Health Services",
            "subcategory":"Health Practitioner",
            "type":"Services"
        },
        {
            "category":"Organizations",
            "subcategory":"Membership Organization",
            "type":"Services"
        }
    ],
    "sg:phone":"+1 650 348 6603",
    "sg:postcode":"94010",
    "sg:province":"CA",
    "sg:tags":[
        "information",
        "group",
        "support",
        "drug",
        "alcoholism",
        "abuse",
        "treatment",
        "counseling",
        "addiction",
        "rehabilitation"
    ],
    "sg:website":"http://www.womensrecovery.org",
    "wof:name":"Women's Recovery Association",
    "wof:placetype":"venue"
},
  "geometry": {"coordinates":[-122.350927,37.577314],"type":"Point"}
}