{
  "type": "Feature",
  "properties": {
    "iso:country":"US",
    "sg:address":"4351 Faculty Ave",
    "sg:city":"Long Beach",
    "sg:classifiers":[
        {
            "category":"Professional",
            "type":"Services"
        }
    ],
    "sg:phone":"+1 562 420 9485",
    "sg:postcode":"90808",
    "sg:province":"CA",
    "wof:name":"James Bynum Co",
    "wof:placetype":"venue"
},
  "geometry": {"coordinates":[-118.13722,33.838719],"type":"Point"}
}