{
  "type": "Feature",
  "properties": {
    "addr:full":"13205 South St Cerritos CA 90703",
    "addr:housenumber":"13205",
    "addr:postcode":"ca 90703",
    "addr:street":"South St",
    "iso:country":"US",
    "sg:address":"13205 South St",
    "sg:city":"Cerritos",
    "sg:classifiers":[
        {
            "category":"Organizations",
            "subcategory":"Non-profit Organization",
            "type":"Services"
        }
    ],
    "sg:phone":"+1 562 402 2466",
    "sg:postcode":"90703",
    "sg:province":"CA",
    "sg:tags":[
        "information",
        "alcoholism",
        "treatment"
    ],
    "wof:name":"Southern California Alcohol &",
    "wof:placetype":"venue"
},
  "geometry": {"coordinates":[-118.05018800000001,33.858739],"type":"Point"}
}