{
  "type": "Feature",
  "properties": {
    "addr:full":"513 Fairhaven Way Vallejo CA 94591",
    "addr:housenumber":"513",
    "addr:postcode":"94591",
    "addr:street":"Fairhaven Way",
    "iso:country":"US",
    "sg:address":"513 Fairhaven Way",
    "sg:city":"Vallejo",
    "sg:classifiers":[
        {
            "category":"Retail",
            "subcategory":"Portrait Studio",
            "type":"Services"
        }
    ],
    "sg:phone":"+1 707 647 0420",
    "sg:postcode":"94591",
    "sg:province":"CA",
    "sg:tags":[
        "photographer"
    ],
    "wof:name":"Eileen Fahy Photography",
    "wof:placetype":"venue"
},
  "geometry": {"coordinates":[-122.205946,38.079206],"type":"Point"}
}