{
  "type": "Feature",
  "properties": {
    "addr:full":"2141 Petaluma Blvd N Petaluma CA 94952",
    "addr:housenumber":"2141",
    "addr:postcode":"94952",
    "addr:street":"Petaluma Blvd N",
    "iso:country":"US",
    "sg:address":"2141 Petaluma Blvd N",
    "sg:city":"Petaluma",
    "sg:classifiers":[
        {
            "category":"Professional",
            "type":"Services"
        }
    ],
    "sg:phone":"+1 707 762 3310",
    "sg:postcode":"94952",
    "sg:province":"CA",
    "sg:tags":[
        "establishment"
    ],
    "wof:name":"Ray Slaughter & Assoc",
    "wof:placetype":"venue"
},
  "geometry": {"coordinates":[-122.651571,38.255132],"type":"Point"}
}