{
  "type": "Feature",
  "properties": {
    "addr:full":"216 S Citrus Ave Covina CA 91723",
    "addr:housenumber":"216",
    "addr:postcode":"91723",
    "addr:street":"S Citrus Ave",
    "iso:country":"US",
    "sg:address":"216 S Citrus Ave",
    "sg:city":"Covina",
    "sg:phone":"+1 626 332 0364",
    "sg:postcode":"91723",
    "sg:province":"CA",
    "wof:name":"Studio C Hair Salon",
    "wof:placetype":"venue"
},
  "geometry": {"coordinates":[-117.89013,34.084875],"type":"Point"}
}