{
  "type": "Feature",
  "properties": {
    "iso:country":"US",
    "sg:address":"10885 Telegraph Rd",
    "sg:city":"Ventura",
    "sg:classifiers":[
        {
            "category":"Health Services",
            "subcategory":"Clinic",
            "type":"Services"
        }
    ],
    "sg:phone":"+1 805 659 3696",
    "sg:postcode":"93004",
    "sg:province":"CA",
    "wof:name":"Primary Medical Group",
    "wof:placetype":"venue"
},
  "geometry": {"coordinates":[-119.16441500000001,34.293226],"type":"Point"}
}