{
  "type": "Feature",
  "properties": {
    "addr:full":"3000 Lomita Blvd Torrance CA 90505",
    "addr:housenumber":"3000",
    "addr:postcode":"90505",
    "addr:street":"Lomita Blvd",
    "iso:country":"US",
    "sg:address":"3000 Lomita Blvd",
    "sg:city":"Torrance",
    "sg:classifiers":[
        {
            "category":"Wholesale",
            "subcategory":"Machinery & Supplies",
            "type":"Manufacturing & Wholesale Goods"
        },
        {
            "category":"Wholesale",
            "subcategory":"Hardware",
            "type":"Manufacturing & Wholesale Goods"
        }
    ],
    "sg:phone":"+1 310 530 2220",
    "sg:postcode":"90505",
    "sg:province":"CA",
    "sg:tags":[
        "fastener",
        "industrial"
    ],
    "wof:name":"Alcoa Fastening Systems Aerosp",
    "wof:placetype":"venue"
},
  "geometry": {"coordinates":[-118.340019,33.81106],"type":"Point"}
}