{
  "type": "Feature",
  "properties": {
    "iso:country":"US",
    "sg:address":"3313 N Hilliard St",
    "sg:city":"Fresno",
    "sg:classifiers":[
        {
            "category":"Health Services",
            "subcategory":"Doctor",
            "type":"Services"
        }
    ],
    "sg:phone":"+1 559 227 4810",
    "sg:postcode":"93726",
    "sg:province":"CA",
    "sg:tags":[
        "physician",
        "surgeon"
    ],
    "wof:name":"Alzheimers & Memory Ctr",
    "wof:placetype":"venue"
},
  "geometry": {"coordinates":[-119.766259,36.780034],"type":"Point"}
}