{
  "type": "Feature",
  "properties": {
    "iso:country":"US",
    "sg:address":"2912 Chiplay St",
    "sg:city":"Sacramento",
    "sg:classifiers":[
        {
            "category":"Personal",
            "type":"Services"
        }
    ],
    "sg:phone":"+1 916 341 3325",
    "sg:postcode":"95826",
    "sg:province":"CA",
    "sg:tags":[
        "therapist",
        "massage"
    ],
    "wof:name":"Rayma Forrest Somatic",
    "wof:placetype":"venue"
},
  "geometry": {"coordinates":[-121.384303,38.552778],"type":"Point"}
}