{
  "type": "Feature",
  "properties": {
    "iso:country":"US",
    "sg:address":"8323 Firestone Blvd",
    "sg:city":"Downey",
    "sg:classifiers":[
        {
            "category":"Shopping",
            "subcategory":"Books",
            "type":"Retail Goods"
        }
    ],
    "sg:phone":"+1 562 869 1492",
    "sg:postcode":"90241",
    "sg:province":"CA",
    "sg:tags":[
        "comic"
    ],
    "wof:name":"Metropolis Comics",
    "wof:placetype":"venue"
},
  "geometry": {"coordinates":[-118.13165100000001,33.939457],"type":"Point"}
}