{
  "type": "Feature",
  "properties": {
    "addr:full":"22338 Short Ave Hilmar CA 95324",
    "addr:housenumber":"22338",
    "addr:postcode":"95324",
    "addr:street":"Short Ave",
    "iso:country":"US",
    "sg:address":"22338 Short Ave",
    "sg:city":"Hilmar",
    "sg:classifiers":[
        {
            "category":"Farming",
            "subcategory":"Dairy Farm",
            "type":"Manufacturing & Wholesale Goods"
        }
    ],
    "sg:phone":"+1 209 667 2393",
    "sg:postcode":"95324",
    "sg:province":"CA",
    "wof:name":"Ken Van Foeken Dairy",
    "wof:placetype":"venue"
},
  "geometry": {"coordinates":[-120.88941199999999,37.426381],"type":"Point"}
}