{
  "type": "Feature",
  "properties": {
    "addr:full":"10549 W Pico Blvd Los Angeles CA 90064",
    "addr:housenumber":"10549",
    "addr:postcode":"90064",
    "addr:street":"W Pico Blvd",
    "iso:country":"US",
    "sg:address":"10549 W Pico Blvd",
    "sg:city":"Los Angeles",
    "sg:classifiers":[
        {
            "category":"Health Services",
            "subcategory":"Clinic",
            "type":"Services"
        }
    ],
    "sg:postcode":"90064",
    "sg:province":"CA",
    "sg:tags":[
        "medical"
    ],
    "wof:name":"Dr Tali Tehrani",
    "wof:placetype":"venue"
},
  "geometry": {"coordinates":[-118.420542,34.0445],"type":"Point"}
}