{
  "type": "Feature",
  "properties": {
    "addr:full":"3274 E Gage Ave Huntington Park CA 90255",
    "addr:housenumber":"3274",
    "addr:postcode":"90255",
    "addr:street":"E Gage Ave;Park",
    "iso:country":"US",
    "sg:address":"3274 E Gage Ave",
    "sg:city":"Huntington Park",
    "sg:classifiers":[
        {
            "category":"Banks & Credit Unions",
            "subcategory":"Investment Brokerage",
            "type":"Services"
        }
    ],
    "sg:phone":"+1 323 589 3271",
    "sg:postcode":"90255",
    "sg:province":"CA",
    "sg:tags":[
        "consultant",
        "planning",
        "financial"
    ],
    "wof:name":"Proteccion Financiera",
    "wof:placetype":"venue"
},
  "geometry": {"coordinates":[-118.207696,33.980149],"type":"Point"}
}