{
  "type": "Feature",
  "properties": {
    "addr:full":"109 W Barstow Ave Apt 121 Fresno CA 93704",
    "addr:housenumber":"109;121",
    "addr:postcode":"93704",
    "addr:street":"W Barstow Ave Apt",
    "iso:country":"US",
    "sg:address":"109 W Barstow Ave Apt 121",
    "sg:city":"Fresno",
    "sg:classifiers":[
        {
            "category":"Real Estate",
            "subcategory":"Real Estate Services",
            "type":"Services"
        },
        {
            "category":"Real Estate",
            "subcategory":"Real Estate Operator",
            "type":"Services"
        }
    ],
    "sg:phone":"+1 559 431 1746",
    "sg:postcode":"93704",
    "sg:province":"CA",
    "sg:tags":[
        "vacancy",
        "apartment",
        "rental",
        "listing"
    ],
    "sg:website":"http://www.robertljensen.com",
    "wof:name":"Colonia Delsol Apts",
    "wof:placetype":"venue"
},
  "geometry": {"coordinates":[-119.79306099999999,36.815697],"type":"Point"}
}