{
  "type": "Feature",
  "properties": {
    "iso:country":"US",
    "sg:address":"7817 Herschel Ave",
    "sg:city":"La Jolla",
    "sg:classifiers":[
        {
            "category":"Professional",
            "subcategory":"Lawyer & Legal Services",
            "type":"Services"
        }
    ],
    "sg:phone":"+1 858 824 6602",
    "sg:postcode":"92037",
    "sg:province":"CA",
    "wof:name":"Vattuone Richard J attorney",
    "wof:placetype":"venue"
},
  "geometry": {"coordinates":[-117.272684,32.845683],"type":"Point"}
}