{
  "type": "Feature",
  "properties": {
    "addr:full":"5070 N 6th St Fresno CA 93710",
    "addr:housenumber":"5070",
    "addr:postcode":"93710",
    "addr:street":"N 6Th St",
    "iso:country":"US",
    "sg:address":"5070 N 6th St",
    "sg:city":"Fresno",
    "sg:classifiers":[
        {
            "category":"Building & Trades",
            "subcategory":"Construction",
            "type":"Services"
        }
    ],
    "sg:phone":"+1 559 244 0372",
    "sg:postcode":"93710",
    "sg:province":"CA",
    "sg:tags":[
        "demolition",
        "contractor"
    ],
    "wof:name":"Sanchez Grading",
    "wof:placetype":"venue"
},
  "geometry": {"coordinates":[-119.763164,36.810962],"type":"Point"}
}