{
  "type": "Feature",
  "properties": {
    "iso:country":"US",
    "sg:address":"11423 Telegraph Rd",
    "sg:city":"Santa Fe Springs",
    "sg:classifiers":[
        {
            "category":"Retail",
            "subcategory":"Laundry & Dry Cleaning",
            "type":"Services"
        }
    ],
    "sg:phone":"+1 562 942 2446",
    "sg:postcode":"90670",
    "sg:province":"CA",
    "sg:tags":[
        "cleaners"
    ],
    "wof:name":"V & M Cleaners",
    "wof:placetype":"venue"
},
  "geometry": {"coordinates":[-118.08981900000001,33.948933],"type":"Point"}
}