{
  "type": "Feature",
  "properties": {
    "addr:full":"15 N Market St San Jose CA 95113",
    "addr:housenumber":"15",
    "addr:postcode":"95113",
    "addr:street":"N Market St",
    "iso:country":"US",
    "sg:address":"15 N Market St",
    "sg:city":"San Jose",
    "sg:classifiers":[
        {
            "category":"Professional",
            "subcategory":"Lawyer & Legal Services",
            "type":"Services"
        }
    ],
    "sg:phone":"+1 408 998 0973",
    "sg:postcode":"95113",
    "sg:province":"CA",
    "wof:name":"Itchhaporia Nita J Atty",
    "wof:placetype":"venue"
},
  "geometry": {"coordinates":[-121.89299800000001,37.336102],"type":"Point"}
}