{
  "type": "Feature",
  "properties": {
    "addr:full":"28 Argonaut Ste 150 Aliso Viejo CA 92656",
    "addr:housenumber":"28",
    "addr:postcode":"92656",
    "addr:street":"Argonaut Ste 150",
    "iso:country":"US",
    "sg:address":"28 Argonaut Ste 150",
    "sg:city":"Aliso Viejo",
    "sg:classifiers":[
        {
            "category":"Utilities",
            "type":"Services"
        }
    ],
    "sg:phone":"+1 949 951 6900",
    "sg:postcode":"92656",
    "sg:province":"CA",
    "sg:tags":[
        "provider",
        "internet"
    ],
    "sg:website":"www.solesourcetechnology.com",
    "wof:name":"Sole Source Technology Llc",
    "wof:placetype":"venue"
},
  "geometry": {"coordinates":[-117.72595099999999,33.592822],"type":"Point"}
}