{
  "type": "Feature",
  "properties": {
    "iso:country":"US",
    "sg:address":"333 N Lantana St Ste 287",
    "sg:city":"Camarillo",
    "sg:classifiers":[
        {
            "category":"Health Services",
            "subcategory":"Doctor",
            "type":"Services"
        }
    ],
    "sg:phone":"+1 805 987 5886",
    "sg:postcode":"93010",
    "sg:province":"CA",
    "sg:tags":[
        "psychiatrist"
    ],
    "wof:name":"Institute For Applied Behavior Analysis",
    "wof:placetype":"venue"
},
  "geometry": {"coordinates":[-119.05500000000001,34.236198],"type":"Point"}
}