{
  "type": "Feature",
  "properties": {
    "iso:country":"US",
    "sg:address":"14755 S Airport Way",
    "sg:city":"Manteca",
    "sg:classifiers":[
        {
            "category":"Farming",
            "subcategory":"Farm",
            "type":"Manufacturing & Wholesale Goods"
        }
    ],
    "sg:phone":"+1 209 858 2481",
    "sg:postcode":"95336",
    "sg:province":"CA",
    "sg:tags":[
        "crop",
        "general"
    ],
    "wof:name":"Aufdermaur Ranch",
    "wof:placetype":"venue"
},
  "geometry": {"coordinates":[-121.254078,37.830284],"type":"Point"}
}