{
  "type": "Feature",
  "properties": {
    "addr:full":"20118 Sherman Way Winnetka CA 91306",
    "addr:housenumber":"20118",
    "addr:postcode":"91306",
    "addr:street":"Sherman Way",
    "iso:country":"US",
    "sg:address":"20118 Sherman Way",
    "sg:city":"Winnetka",
    "sg:classifiers":[
        {
            "category":"Retail",
            "subcategory":"Auto Repair",
            "type":"Services"
        }
    ],
    "sg:phone":"+1 818 340 3738",
    "sg:postcode":"91306",
    "sg:province":"CA",
    "wof:name":"Le Auto Service Smog & Repair",
    "wof:placetype":"venue"
},
  "geometry": {"coordinates":[-118.57199900000001,34.201099],"type":"Point"}
}