{
  "type": "Feature",
  "properties": {
    "addr:full":"13621 Moorpark St Sherman Oaks CA 91423",
    "addr:housenumber":"13621",
    "addr:postcode":"91423",
    "addr:street":"Moorpark St",
    "iso:country":"US",
    "sg:address":"13621 Moorpark St",
    "sg:city":"Sherman Oaks",
    "sg:classifiers":[
        {
            "category":"Insurance",
            "subcategory":"Insurance Agent",
            "type":"Services"
        }
    ],
    "sg:phone":"+1 818 788 5222",
    "sg:postcode":"91423",
    "sg:province":"CA",
    "wof:name":"State Farm Insurance",
    "wof:placetype":"venue"
},
  "geometry": {"coordinates":[-118.43060699999999,34.150426],"type":"Point"}
}