{
  "type": "Feature",
  "properties": {
    "iso:country":"US",
    "sg:address":"1203 Main St",
    "sg:city":"Morro Bay",
    "sg:classifiers":[
        {
            "category":"Insurance",
            "subcategory":"Insurance Agent",
            "type":"Services"
        }
    ],
    "sg:phone":"+1 805 772 1201",
    "sg:postcode":"93442",
    "sg:province":"CA",
    "sg:website":"www.baywestinsurance.com",
    "wof:name":"Bay-West Insurance",
    "wof:placetype":"venue"
},
  "geometry": {"coordinates":[-120.850348,35.371312],"type":"Point"}
}