{
  "type": "Feature",
  "properties": {
    "addr:full":"6632 N Blackstone Ave Fresno CA 93710",
    "addr:housenumber":"6632",
    "addr:postcode":"93710",
    "addr:street":"N Blackstone Ave",
    "iso:country":"US",
    "sg:address":"6632 N Blackstone Ave",
    "sg:city":"Fresno",
    "sg:classifiers":[
        {
            "category":"Retail",
            "subcategory":"Auto Repair",
            "type":"Services"
        }
    ],
    "sg:phone":"+1 559 436 8060",
    "sg:postcode":"93710",
    "sg:province":"CA",
    "sg:tags":[
        "body",
        "automobile",
        "painting"
    ],
    "wof:name":"Fresno Body Works & Garage",
    "wof:placetype":"venue"
},
  "geometry": {"coordinates":[-119.790187,36.833982],"type":"Point"}
}