{
  "type": "Feature",
  "properties": {
    "addr:full":"612 Sanford Ave Wilmington CA 90744",
    "addr:housenumber":"612",
    "addr:postcode":"90744",
    "addr:street":"Sanford Ave",
    "iso:country":"US",
    "sg:address":"612 Sanford Ave",
    "sg:city":"Wilmington",
    "sg:classifiers":[
        {
            "category":"Wholesale",
            "subcategory":"Non-durable Goods",
            "type":"Manufacturing & Wholesale Goods"
        }
    ],
    "sg:phone":"+1 310 513 6067",
    "sg:postcode":"90744",
    "sg:province":"CA",
    "wof:name":"Vts Trading USA LLC",
    "wof:placetype":"venue"
},
  "geometry": {"coordinates":[-118.25052100000001,33.778981],"type":"Point"}
}