{
  "type": "Feature",
  "properties": {
    "addr:full":"560 W Putnam Ave Porterville CA 93257",
    "addr:housenumber":"560",
    "addr:postcode":"93257",
    "addr:street":"W Putnam Ave",
    "iso:country":"US",
    "sg:address":"560 W Putnam Ave",
    "sg:city":"Porterville",
    "sg:classifiers":[
        {
            "category":"Health Services",
            "subcategory":"Doctor",
            "type":"Services"
        }
    ],
    "sg:phone":"+1 559 781 2000",
    "sg:postcode":"93257",
    "sg:province":"CA",
    "sg:tags":[
        "physician",
        "surgeon"
    ],
    "wof:name":"Ram Seralathan Md",
    "wof:placetype":"venue"
},
  "geometry": {"coordinates":[-119.029775,36.069595],"type":"Point"}
}