{
  "type": "Feature",
  "properties": {
    "addr:full":"121 W B St Ontario CA 91762",
    "addr:housenumber":"121",
    "addr:postcode":"91762",
    "addr:street":"W B St",
    "iso:country":"US",
    "sg:address":"121 W B St",
    "sg:city":"Ontario",
    "sg:classifiers":[
        {
            "category":"Insurance",
            "subcategory":"Insurance Agent",
            "type":"Services"
        }
    ],
    "sg:phone":"+1 909 467 3544",
    "sg:postcode":"91762",
    "sg:province":"CA",
    "wof:name":"Gomez Insurance",
    "wof:placetype":"venue"
},
  "geometry": {"coordinates":[-117.65212200000001,34.064509],"type":"Point"}
}