{
  "type": "Feature",
  "properties": {
    "iso:country":"US",
    "sg:address":"307 N Avalon Blvd",
    "sg:city":"Wilmington",
    "sg:classifiers":[
        {
            "category":"Freight",
            "type":"Transportation"
        }
    ],
    "sg:phone":"+1 310 830 2180",
    "sg:postcode":"90744",
    "sg:province":"CA",
    "sg:tags":[
        "trucking"
    ],
    "wof:name":"Supreme Transport Inc",
    "wof:placetype":"venue"
},
  "geometry": {"coordinates":[-118.262045,33.774079],"type":"Point"}
}