{
  "type": "Feature",
  "properties": {
    "iso:country":"US",
    "sg:address":"608 S Maclay St",
    "sg:city":"San Fernando",
    "sg:classifiers":[
        {
            "category":"Shopping",
            "subcategory":"Gifts & Souvenirs",
            "type":"Retail Goods"
        }
    ],
    "sg:phone":"+1 818 837 6069",
    "sg:postcode":"91340",
    "sg:province":"CA",
    "sg:tags":[
        "shop"
    ],
    "wof:name":"Miscelanea Familiar",
    "wof:placetype":"venue"
},
  "geometry": {"coordinates":[-118.446127,34.279701],"type":"Point"}
}