{
  "type": "Feature",
  "properties": {
    "iso:country":"US",
    "sg:address":"8237 3rd St",
    "sg:city":"Downey",
    "sg:classifiers":[
        {
            "category":"Banks & Credit Unions",
            "subcategory":"Bank",
            "type":"Services"
        }
    ],
    "sg:phone":"+1 562 862 8141",
    "sg:postcode":"90241",
    "sg:province":"CA",
    "sg:website":"http://www.downeyfcu.org",
    "wof:name":"Downey Federal Credit Union",
    "wof:placetype":"venue"
},
  "geometry": {"coordinates":[-118.133003,33.942299],"type":"Point"}
}