{
  "type": "Feature",
  "properties": {
    "iso:country":"US",
    "sg:address":"4251 18th Street",
    "sg:city":"San Francisco",
    "sg:classifiers":[
        {
            "category":"Retail",
            "subcategory":"Laundry & Dry Cleaning",
            "type":"Services"
        }
    ],
    "sg:phone":"+1 415 552 8926",
    "sg:postcode":"94114",
    "sg:province":"CA",
    "wof:name":"Big Cleaners",
    "wof:placetype":"venue"
},
  "geometry": {"coordinates":[-122.43693500000001,37.760682],"type":"Point"}
}