{
  "type": "Feature",
  "properties": {
    "iso:country":"US",
    "sg:address":"24262 Cross St",
    "sg:city":"Santa Clarita",
    "sg:classifiers":[
        {
            "category":"Building & Trades",
            "subcategory":"Construction",
            "type":"Services"
        }
    ],
    "sg:phone":"+1 661 259 7522",
    "sg:postcode":"91321",
    "sg:province":"CA",
    "sg:tags":[
        "contractor"
    ],
    "wof:name":"CKC Contractors",
    "wof:placetype":"venue"
},
  "geometry": {"coordinates":[-118.534853,34.368912],"type":"Point"}
}