{
  "type": "Feature",
  "properties": {
    "iso:country":"US",
    "sg:address":"1442 Westwood Blvd",
    "sg:city":"Los Angeles",
    "sg:classifiers":[
        {
            "category":"Restaurant",
            "type":"Food & Drink"
        }
    ],
    "sg:phone":"+1 310 470 4885",
    "sg:postcode":"90024",
    "sg:province":"CA",
    "wof:name":"Cafe Dahab",
    "wof:placetype":"venue"
},
  "geometry": {"coordinates":[-118.440995,34.05466],"type":"Point"}
}