{
  "type": "Feature",
  "properties": {
    "addr:full":"419 Tara Ct Vacaville CA 95688",
    "addr:housenumber":"419",
    "addr:postcode":"95688",
    "addr:street":"Tara Ct",
    "iso:country":"US",
    "sg:address":"419 Tara Ct",
    "sg:city":"Vacaville",
    "sg:classifiers":[
        {
            "category":"Wholesale",
            "subcategory":"Non-durable Goods",
            "type":"Manufacturing & Wholesale Goods"
        }
    ],
    "sg:phone":"+1 707 718 1940",
    "sg:postcode":"95688",
    "sg:province":"CA",
    "sg:tags":[
        "advertising"
    ],
    "wof:name":"A & M Creative Ink",
    "wof:placetype":"venue"
},
  "geometry": {"coordinates":[-121.973181,38.382128],"type":"Point"}
}