{
  "type": "Feature",
  "properties": {
    "iso:country":"US",
    "sg:address":"14646 Wake Ave",
    "sg:city":"San Leandro",
    "sg:classifiers":[
        {
            "category":"Retail",
            "subcategory":"Auto Repair",
            "type":"Services"
        }
    ],
    "sg:phone":"+1 510 352 2596",
    "sg:postcode":"94578",
    "sg:province":"CA",
    "wof:name":"Birini Vehicle Maintenance",
    "wof:placetype":"venue"
},
  "geometry": {"coordinates":[-122.13103,37.713037],"type":"Point"}
}