{
  "type": "Feature",
  "properties": {
    "addr:full":"1000 Wilshire Blvd Los Angeles CA 90017",
    "addr:housenumber":"1000",
    "addr:postcode":"90017",
    "addr:street":"Wilshire Blvd",
    "iso:country":"US",
    "sg:address":"1000 Wilshire Blvd",
    "sg:city":"Los Angeles",
    "sg:classifiers":[
        {
            "category":"Professional",
            "subcategory":"Accounting & Tax Preparation",
            "type":"Services"
        }
    ],
    "sg:phone":"+1 213 627 1717",
    "sg:postcode":"90017",
    "sg:province":"CA",
    "sg:tags":[
        "accountant"
    ],
    "wof:name":"Grant Thornton Llp",
    "wof:placetype":"venue"
},
  "geometry": {"coordinates":[-118.261002,34.0508],"type":"Point"}
}