{
  "type": "Feature",
  "properties": {
    "addr:full":"1213 W Ashland Ave Visalia CA 93277",
    "addr:housenumber":"1213",
    "addr:postcode":"93277",
    "addr:street":"W Ashland Ave",
    "iso:country":"US",
    "sg:address":"1213 W Ashland Ave",
    "sg:city":"Visalia",
    "sg:classifiers":[
        {
            "category":"Building & Trades",
            "subcategory":"Cleaning & Sanitation",
            "type":"Services"
        }
    ],
    "sg:phone":"+1 559 625 2860",
    "sg:postcode":"93277",
    "sg:province":"CA",
    "sg:tags":[
        "janitor"
    ],
    "wof:name":"Ultimate Healthcare Cleaning",
    "wof:placetype":"venue"
},
  "geometry": {"coordinates":[-119.304395,36.308062],"type":"Point"}
}