{
  "type": "Feature",
  "properties": {
    "addr:full":"2313 N San Fernando Blvd Burbank CA 91504",
    "addr:housenumber":"2313",
    "addr:postcode":"91504",
    "addr:street":"N San Fernando Blvd",
    "iso:country":"US",
    "sg:address":"2313 N San Fernando Blvd",
    "sg:city":"Burbank",
    "sg:classifiers":[
        {
            "category":"Arena",
            "subcategory":"Sports Club",
            "type":"Entertainment"
        }
    ],
    "sg:phone":"+1 818 717 8851",
    "sg:postcode":"91504",
    "sg:province":"CA",
    "sg:tags":[
        "martial art",
        "instruction"
    ],
    "wof:name":"Kung Fu Dvd",
    "wof:placetype":"venue"
},
  "geometry": {"coordinates":[-118.335814,34.196361],"type":"Point"}
}