{
  "type": "Feature",
  "properties": {
    "addr:full":"845 E 8th St National City CA 91950",
    "addr:housenumber":"845",
    "addr:postcode":"91950",
    "addr:street":"E 8Th St",
    "iso:country":"US",
    "sg:address":"845 E 8th St",
    "sg:city":"National City",
    "sg:classifiers":[
        {
            "category":"Wholesale",
            "subcategory":"Construction Materials",
            "type":"Manufacturing & Wholesale Goods"
        }
    ],
    "sg:phone":"+1 619 474 2243",
    "sg:postcode":"91950",
    "sg:province":"CA",
    "sg:tags":[
        "sand",
        "gravel"
    ],
    "wof:name":"Parra Abel Consultant",
    "wof:placetype":"venue"
},
  "geometry": {"coordinates":[-117.098141,32.678356],"type":"Point"}
}