{
  "type": "Feature",
  "properties": {
    "addr:full":"5750 Fieldcrest Dr Camarillo CA 93012",
    "addr:housenumber":"5750",
    "addr:postcode":"93012",
    "addr:street":"Fieldcrest Dr",
    "iso:country":"US",
    "sg:address":"5750 Fieldcrest Dr",
    "sg:city":"Camarillo",
    "sg:classifiers":[
        {
            "category":"Education",
            "subcategory":"School",
            "type":"Public Place"
        }
    ],
    "sg:phone":"+1 805 484 0461",
    "sg:postcode":"93012",
    "sg:province":"CA",
    "sg:tags":[
        "high",
        "middle",
        "elementary"
    ],
    "wof:name":"Las Colinas School",
    "wof:placetype":"venue"
},
  "geometry": {"coordinates":[-118.991997,34.2346],"type":"Point"}
}