{
  "type": "Feature",
  "properties": {
    "addr:full":"315 Boyd St Los Angeles CA 90013",
    "addr:housenumber":"315",
    "addr:postcode":"90013",
    "addr:street":"Boyd St",
    "iso:country":"US",
    "sg:address":"315 Boyd St",
    "sg:city":"Los Angeles",
    "sg:classifiers":[
        {
            "category":"Shopping",
            "subcategory":"Gifts & Souvenirs",
            "type":"Retail Goods"
        }
    ],
    "sg:phone":"+1 213 620 9478",
    "sg:postcode":"90013",
    "sg:province":"CA",
    "sg:tags":[
        "shop"
    ],
    "wof:name":"Fengshui King Inc",
    "wof:placetype":"venue"
},
  "geometry": {"coordinates":[-118.24286499999999,34.046826],"type":"Point"}
}