{
  "type": "Feature",
  "properties": {
    "iso:country":"US",
    "sg:address":"5318 N 6th St",
    "sg:city":"Fresno",
    "sg:classifiers":[
        {
            "category":"Arts & Performance",
            "subcategory":"Theater",
            "type":"Entertainment"
        }
    ],
    "sg:phone":"+1 559 270 9177",
    "sg:postcode":"93710",
    "sg:province":"CA",
    "sg:tags":[
        "bureau"
    ],
    "wof:name":"Tara Elsea Entertainment Svc",
    "wof:placetype":"venue"
},
  "geometry": {"coordinates":[-119.762954,36.813386],"type":"Point"}
}