{
  "type": "Feature",
  "properties": {
    "addr:full":"5318 N 6th St Fresno CA 93710",
    "addr:housenumber":"5318",
    "addr:postcode":"93710",
    "addr:street":"N 6Th St",
    "iso:country":"US",
    "sg:address":"5318 N 6th St",
    "sg:city":"Fresno",
    "sg:classifiers":[
        {
            "category":"Arts & Performance",
            "subcategory":"Theater",
            "type":"Entertainment"
        }
    ],
    "sg:phone":"+1 559 270 9177",
    "sg:postcode":"93710",
    "sg:province":"CA",
    "sg:tags":[
        "bureau"
    ],
    "wof:name":"Tara Elsea Entertainment Svc",
    "wof:placetype":"venue"
},
  "geometry": {"coordinates":[-119.76295399999999,36.813386],"type":"Point"}
}