{
  "type": "Feature",
  "properties": {
    "iso:country":"US",
    "sg:address":"9838 Joe Vargas Way",
    "sg:city":"South El Monte",
    "sg:classifiers":[
        {
            "category":"Building & Trades",
            "subcategory":"Construction",
            "type":"Services"
        }
    ],
    "sg:phone":"+1 626 454 3501",
    "sg:postcode":"91733",
    "sg:province":"CA",
    "sg:tags":[
        "contractor"
    ],
    "wof:name":"Dr D Construction",
    "wof:placetype":"venue"
},
  "geometry": {"coordinates":[-118.055361,34.044539],"type":"Point"}
}