{
  "type": "Feature",
  "properties": {
    "addr:full":"17707 S Santa Fe Ave Compton CA 90221",
    "addr:housenumber":"17707",
    "addr:postcode":"90221",
    "addr:street":"S Santa Fe Ave",
    "iso:country":"US",
    "sg:address":"17707 S Santa Fe Ave",
    "sg:city":"Compton",
    "sg:classifiers":[
        {
            "category":"Freight",
            "type":"Transportation"
        }
    ],
    "sg:phone":"+1 310 898 2090",
    "sg:postcode":"90221",
    "sg:province":"CA",
    "sg:tags":[
        "storage",
        "special",
        "warehousing"
    ],
    "wof:name":"AZ West",
    "wof:placetype":"venue"
},
  "geometry": {"coordinates":[-118.213601,33.870572],"type":"Point"}
}