{
  "type": "Feature",
  "properties": {
    "iso:country":"US",
    "sg:address":"8424 Santa Monica Blvd Suite A-729",
    "sg:city":"West Hollywood",
    "sg:classifiers":[
        {
            "category":"Personal",
            "subcategory":"Massage",
            "type":"Services"
        }
    ],
    "sg:phone":"+1 323 651 3529",
    "sg:postcode":"90069",
    "sg:province":"CA",
    "sg:website":"www.bodywork411.com",
    "wof:name":"Bodywork411 Massage Directory",
    "wof:placetype":"venue"
},
  "geometry": {"coordinates":[-118.374199,34.090477],"type":"Point"}
}