{
  "type": "Feature",
  "properties": {
    "iso:country":"US",
    "sg:address":"1112 14th St",
    "sg:city":"Bakersfield",
    "sg:classifiers":[
        {
            "category":"Professional",
            "type":"Services"
        }
    ],
    "sg:phone":"+1 661 328 0796",
    "sg:postcode":"93301",
    "sg:province":"CA",
    "sg:tags":[
        "establishment"
    ],
    "wof:name":"KERN Forms Inc",
    "wof:placetype":"venue"
},
  "geometry": {"coordinates":[-119.015166,35.370497],"type":"Point"}
}