{
  "type": "Feature",
  "properties": {
    "addr:full":"4888 Olivehurst Ave Olivehurst CA 95961",
    "addr:postcode":"4888;ca 95961",
    "addr:street":"Olivehurst Ave",
    "iso:country":"US",
    "sg:address":"4888 Olivehurst Ave",
    "sg:city":"Olivehurst",
    "sg:classifiers":[
        {
            "category":"Shopping",
            "subcategory":"Clothing, Apparel, & Fashions",
            "type":"Retail Goods"
        }
    ],
    "sg:phone":"+1 530 749 7411",
    "sg:postcode":"95961",
    "sg:province":"CA",
    "sg:tags":[
        "western"
    ],
    "wof:name":"Villa's Market",
    "wof:placetype":"venue"
},
  "geometry": {"coordinates":[-121.551659,39.09638],"type":"Point"}
}