{
  "type": "Feature",
  "properties": {
    "iso:country":"US",
    "sg:address":"630 Mission St Ste B",
    "sg:city":"South Pasadena",
    "sg:classifiers":[
        {
            "category":"Health Services",
            "subcategory":"Health Practitioner",
            "type":"Services"
        }
    ],
    "sg:phone":"+1 626 799 9888",
    "sg:postcode":"91030",
    "sg:province":"CA",
    "sg:tags":[
        "acupuncture"
    ],
    "sg:website":"www.joyeeenterpriseinc.com/",
    "wof:name":"Joyee Acupuncture & Herbs",
    "wof:placetype":"venue"
},
  "geometry": {"coordinates":[-118.162397,34.116015],"type":"Point"}
}