{
  "type": "Feature",
  "properties": {
    "iso:country":"US",
    "sg:address":"2923 Pullman St",
    "sg:city":"Santa Ana",
    "sg:classifiers":[
        {
            "category":"Manufacturing",
            "subcategory":"Electronics",
            "type":"Manufacturing & Wholesale Goods"
        }
    ],
    "sg:phone":"+1 949 660 8014",
    "sg:postcode":"92705",
    "sg:province":"CA",
    "sg:tags":[
        "control",
        "electronic",
        "mfg"
    ],
    "wof:name":"Parko Electronics Company Inc",
    "wof:placetype":"venue"
},
  "geometry": {"coordinates":[-117.852126,33.706589],"type":"Point"}
}