{
  "type": "Feature",
  "properties": {
    "iso:country":"US",
    "sg:address":"2961 San Juan Rd",
    "sg:city":"Aromas",
    "sg:classifiers":[
        {
            "category":"Manufacturing",
            "subcategory":"Petroleum Products",
            "type":"Manufacturing & Wholesale Goods"
        }
    ],
    "sg:phone":"+1 831 757 3544",
    "sg:postcode":"95004",
    "sg:province":"CA",
    "sg:tags":[
        "refiner"
    ],
    "wof:name":"101 Beacon",
    "wof:placetype":"venue"
},
  "geometry": {"coordinates":[-121.637962,36.854716],"type":"Point"}
}