{
  "type": "Feature",
  "properties": {
    "addr:full":"9739 Highway 79 Descanso CA 91916",
    "addr:housenumber":"9739",
    "addr:postcode":"91916",
    "addr:street":"Highway 79",
    "iso:country":"US",
    "sg:address":"9739 Highway 79",
    "sg:city":"Descanso",
    "sg:classifiers":[
        {
            "category":"Manufacturing",
            "subcategory":"Furniture",
            "type":"Manufacturing & Wholesale Goods"
        }
    ],
    "sg:phone":"+1 619 445 1899",
    "sg:postcode":"91916",
    "sg:province":"CA",
    "sg:tags":[
        "equipment",
        "supply",
        "manufacturer"
    ],
    "wof:name":"McClelland Lane",
    "wof:placetype":"venue"
},
  "geometry": {"coordinates":[-116.59217599999999,32.863422],"type":"Point"}
}