{
  "type": "Feature",
  "properties": {
    "addr:full":"17551 Macarthur Blvd Irvine CA 92614",
    "addr:housenumber":"17551",
    "addr:postcode":"92614",
    "addr:street":"Macarthur Blvd",
    "iso:country":"US",
    "sg:address":"17551 Macarthur Blvd",
    "sg:city":"Irvine",
    "sg:classifiers":[
        {
            "category":"Restaurant",
            "type":"Food & Drink"
        }
    ],
    "sg:menulink":"http://www.allmenus.com/ca/anaheim-santa-ana-garden-grove/60093-subway/menu/",
    "sg:phone":"+1 949 477 9038",
    "sg:postcode":"92614",
    "sg:province":"CA",
    "sg:tags":[
        "american",
        "sandwich"
    ],
    "wof:name":"Subway",
    "wof:placetype":"venue"
},
  "geometry": {"coordinates":[-117.855808,33.694564],"type":"Point"}
}