{
  "type": "Feature",
  "properties": {
    "iso:country":"US",
    "sg:address":"2475 del Mar Way",
    "sg:city":"Corona",
    "sg:classifiers":[
        {
            "category":"Real Estate",
            "subcategory":"Real Estate Operator",
            "type":"Services"
        }
    ],
    "sg:phone":"+1 951 272 8100",
    "sg:postcode":"92882",
    "sg:province":"CA",
    "sg:tags":[
        "apartment"
    ],
    "wof:name":"Sage Canyon Apartments",
    "wof:placetype":"venue"
},
  "geometry": {"coordinates":[-117.61771400000001,33.865877],"type":"Point"}
}