{
  "type": "Feature",
  "properties": {
    "iso:country":"US",
    "sg:address":"19 Nelson Ave",
    "sg:city":"Oroville",
    "sg:classifiers":[
        {
            "category":"Professional",
            "subcategory":"Lawyer & Legal Services",
            "type":"Services"
        }
    ],
    "sg:phone":"+1 530 533 4800",
    "sg:postcode":"95965",
    "sg:province":"CA",
    "sg:tags":[
        "attorney"
    ],
    "wof:name":"Harris Sanford & Baggett",
    "wof:placetype":"venue"
},
  "geometry": {"coordinates":[-121.563025,39.523989],"type":"Point"}
}