{
  "type": "Feature",
  "properties": {
    "addr:full":"21580 Stevens Creek Blvd Cupertino CA 95014",
    "addr:housenumber":"21580",
    "addr:postcode":"95014",
    "addr:street":"Stevens Creek Blvd",
    "iso:country":"US",
    "sg:address":"21580 Stevens Creek Blvd",
    "sg:city":"Cupertino",
    "sg:classifiers":[
        {
            "category":"Manufacturing",
            "subcategory":"Electronics",
            "type":"Manufacturing & Wholesale Goods"
        }
    ],
    "sg:phone":"+1 408 973 9845",
    "sg:postcode":"95014",
    "sg:province":"CA",
    "sg:tags":[
        "satellite",
        "mfg"
    ],
    "wof:name":"Alenia Aerospazio",
    "wof:placetype":"venue"
},
  "geometry": {"coordinates":[-122.052198,37.322718],"type":"Point"}
}