{
  "type": "Feature",
  "properties": {
    "iso:country":"US",
    "sg:address":"41 Summit St",
    "sg:city":"Jackson",
    "sg:classifiers":[
        {
            "category":"Freight",
            "type":"Transportation"
        }
    ],
    "sg:phone":"+1 209 223 1848",
    "sg:postcode":"95642",
    "sg:province":"CA",
    "sg:tags":[
        "warehouse",
        "self",
        "storage"
    ],
    "wof:name":"Up Country Mini Storage",
    "wof:placetype":"venue"
},
  "geometry": {"coordinates":[-120.772891,38.348848],"type":"Point"}
}