{
  "type": "Feature",
  "properties": {
    "iso:country":"US",
    "sg:address":"16502 W Jensen Ave",
    "sg:city":"Kerman",
    "sg:phone":"+1 559 846 9500",
    "sg:postcode":"93630",
    "sg:province":"CA",
    "sg:tags":[
        "farm",
        "vineyard",
        "grape",
        "cotton"
    ],
    "wof:name":"S R Bothelho",
    "wof:placetype":"venue"
},
  "geometry": {"coordinates":[-120.089623,36.705689],"type":"Point"}
}