{
  "type": "Feature",
  "properties": {
    "iso:country":"US",
    "sg:address":"230 E Chapman Ave",
    "sg:city":"Orange",
    "sg:classifiers":[
        {
            "category":"Government",
            "subcategory":"Office",
            "type":"Public Place"
        }
    ],
    "sg:phone":"+1 714 771 2315",
    "sg:postcode":"92866",
    "sg:province":"CA",
    "sg:tags":[
        "agency",
        "redevelopment"
    ],
    "wof:name":"Redevelpoment Authority",
    "wof:placetype":"venue"
},
  "geometry": {"coordinates":[-117.851232,33.787799],"type":"Point"}
}