{
  "type": "Feature",
  "properties": {
    "addr:full":"9557 Copus Rd Bakersfield CA 93313",
    "addr:housenumber":"9557",
    "addr:postcode":"93313",
    "addr:street":"Copus Rd",
    "iso:country":"US",
    "sg:address":"9557 Copus Rd",
    "sg:city":"Bakersfield",
    "sg:classifiers":[
        {
            "category":"Farming",
            "subcategory":"Farm",
            "type":"Manufacturing & Wholesale Goods"
        }
    ],
    "sg:phone":"+1 661 858 1100",
    "sg:postcode":"93313",
    "sg:province":"CA",
    "sg:tags":[
        "crop",
        "general"
    ],
    "wof:name":"Murray Family Farms",
    "wof:placetype":"venue"
},
  "geometry": {"coordinates":[-119.03333000000001,35.095],"type":"Point"}
}