{
  "type": "Feature",
  "properties": {
    "iso:country":"US",
    "sg:address":"1422 Oak Ave",
    "sg:city":"Redwood City",
    "sg:classifiers":[
        {
            "category":"Building & Trades",
            "subcategory":"Electrical",
            "type":"Services"
        }
    ],
    "sg:phone":"+1 650 261 1519",
    "sg:postcode":"94061",
    "sg:province":"CA",
    "sg:tags":[
        "electrical",
        "contractor"
    ],
    "wof:name":"Vb Electric",
    "wof:placetype":"venue"
},
  "geometry": {"coordinates":[-122.234858,37.468679],"type":"Point"}
}