{
  "type": "Feature",
  "properties": {
    "addr:full":"9007 Folsom Blvd Sacramento CA 95826",
    "addr:housenumber":"9007",
    "addr:postcode":"95826",
    "addr:street":"Folsom Blvd",
    "iso:country":"US",
    "sg:address":"9007 Folsom Blvd",
    "sg:city":"Sacramento",
    "sg:classifiers":[
        {
            "category":"Restaurant",
            "type":"Food & Drink"
        }
    ],
    "sg:phone":"+1 916 366 8618",
    "sg:postcode":"95826",
    "sg:province":"CA",
    "wof:name":"Jimboy's Tacos",
    "wof:placetype":"venue"
},
  "geometry": {"coordinates":[-121.370688,38.555026],"type":"Point"}
}