{
  "type": "Feature",
  "properties": {
    "iso:country":"US",
    "sg:address":"20400 Lake Chabot Rd",
    "sg:city":"Castro Valley",
    "sg:classifiers":[
        {
            "category":"Restaurant",
            "type":"Food & Drink"
        }
    ],
    "sg:phone":"+1 510 733 0788",
    "sg:postcode":"94546",
    "sg:province":"CA",
    "wof:name":"Sazio Ristorante Italiano",
    "wof:placetype":"venue"
},
  "geometry": {"coordinates":[-122.08767899999999,37.699759],"type":"Point"}
}