{
  "type": "Feature",
  "properties": {
    "addr:full":"2615 Homestead Pl Rancho Dominguez CA 90220",
    "addr:housenumber":"2615",
    "addr:postcode":"90220",
    "addr:street":"Homestead Pl",
    "iso:country":"US",
    "sg:address":"2615 Homestead Pl",
    "sg:city":"Rancho Dominguez",
    "sg:classifiers":[
        {
            "category":"Manufacturing",
            "subcategory":"Tools & Machinery",
            "type":"Manufacturing & Wholesale Goods"
        }
    ],
    "sg:phone":"+1 310 608 4422",
    "sg:postcode":"90220",
    "sg:province":"CA",
    "sg:tags":[
        "machine"
    ],
    "sg:website":"www.southwesternindustries.com",
    "wof:name":"Southwestern Industries Inc",
    "wof:placetype":"venue"
},
  "geometry": {"coordinates":[-118.217084,33.868476],"type":"Point"}
}