{
  "type": "Feature",
  "properties": {
    "addr:full":"920 Saratoga Ave San Jose CA 95129",
    "addr:housenumber":"920",
    "addr:postcode":"95129",
    "addr:street":"Saratoga Ave",
    "iso:country":"US",
    "sg:address":"920 Saratoga Ave",
    "sg:city":"San Jose",
    "sg:classifiers":[
        {
            "category":"Home & Garden",
            "subcategory":"Home Furnishings",
            "type":"Retail Goods"
        }
    ],
    "sg:phone":"+1 408 615 8880",
    "sg:postcode":"95129",
    "sg:province":"CA",
    "sg:tags":[
        "cutlery"
    ],
    "sg:website":"www.vectormarketing.com",
    "wof:name":"Cutco Cutlery",
    "wof:placetype":"venue"
},
  "geometry": {"coordinates":[-121.977666,37.30813],"type":"Point"}
}