{
  "type": "Feature",
  "properties": {
    "addr:full":"2071 23rd Ave San Francisco CA 94116",
    "addr:housenumber":"2071",
    "addr:postcode":"94116",
    "addr:street":"23Rd Ave",
    "iso:country":"US",
    "sg:address":"2071 23rd Ave",
    "sg:city":"San Francisco",
    "sg:classifiers":[
        {
            "category":"Local Transit",
            "type":"Transportation"
        }
    ],
    "sg:phone":"+1 415 681 1001",
    "sg:postcode":"94116",
    "sg:province":"CA",
    "sg:tags":[
        "passenger",
        "transport"
    ],
    "wof:name":"A Deluxe Limousine & Sedan Svc",
    "wof:placetype":"venue"
},
  "geometry": {"coordinates":[-122.480497,37.749441],"type":"Point"}
}