{
  "type": "Feature",
  "properties": {
    "addr:full":"100 W el Camino Real Mountain View CA 94040",
    "addr:housenumber":"100",
    "addr:postcode":"94040",
    "addr:street":"W El Camino Real",
    "iso:country":"US",
    "sg:address":"100 W el Camino Real",
    "sg:city":"Mountain View",
    "sg:classifiers":[
        {
            "category":"Health Services",
            "subcategory":"Doctor",
            "type":"Services"
        }
    ],
    "sg:phone":"+1 650 968 9600",
    "sg:postcode":"94040",
    "sg:province":"CA",
    "sg:tags":[
        "physician",
        "surgeon"
    ],
    "wof:name":"Allstar Medical Group",
    "wof:placetype":"venue"
},
  "geometry": {"coordinates":[-122.073987,37.380819],"type":"Point"}
}