{
  "type": "Feature",
  "properties": {
    "addr:full":"909 S Broadway Los Angeles CA 90015",
    "addr:housenumber":"909",
    "addr:postcode":"90015",
    "addr:street":"S Broadway",
    "iso:country":"US",
    "sg:address":"909 S Broadway",
    "sg:city":"Los Angeles",
    "sg:classifiers":[
        {
            "category":"Shopping",
            "subcategory":"Clothing, Apparel, & Fashions",
            "type":"Retail Goods"
        }
    ],
    "sg:phone":"+1 213 627 8385",
    "sg:postcode":"90015",
    "sg:province":"CA",
    "sg:tags":[
        "clothing",
        "women's"
    ],
    "wof:name":"Collage",
    "wof:placetype":"venue"
},
  "geometry": {"coordinates":[-118.256317,34.041861],"type":"Point"}
}