{
  "type": "Feature",
  "properties": {
    "iso:country":"US",
    "sg:address":"2222 N Pacific Ave",
    "sg:city":"Stockton",
    "sg:classifiers":[
        {
            "category":"Real Estate",
            "subcategory":"Real Estate Agent",
            "type":"Services"
        }
    ],
    "sg:phone":"+1 209 467 1200",
    "sg:postcode":"95204",
    "sg:province":"CA",
    "wof:name":"Lela Nelson Realty",
    "wof:placetype":"venue"
},
  "geometry": {"coordinates":[-121.30085800000001,37.972265],"type":"Point"}
}