{
  "type": "Feature",
  "properties": {
    "addr:full":"4501 Sunnycrest Dr Ukiah CA 95482",
    "addr:housenumber":"4501",
    "addr:postcode":"ca 95482",
    "addr:street":"Sunnycrest Dr",
    "iso:country":"US",
    "sg:address":"4501 Sunnycrest Dr",
    "sg:city":"Ukiah",
    "sg:classifiers":[
        {
            "category":"Building & Trades",
            "subcategory":"Construction",
            "type":"Services"
        }
    ],
    "sg:phone":"+1 707 485 8919",
    "sg:postcode":"95482",
    "sg:province":"CA",
    "sg:tags":[
        "equipment",
        "station"
    ],
    "wof:name":"Ehlert's Petroleum Maintenance",
    "wof:placetype":"venue"
},
  "geometry": {"coordinates":[-123.203895,39.209731],"type":"Point"}
}