{
  "type": "Feature",
  "properties": {
    "iso:country":"US",
    "sg:address":"6377 Ascot Dr",
    "sg:city":"Oakland",
    "sg:classifiers":[
        {
            "category":"Professional",
            "subcategory":"Engineering",
            "type":"Services"
        }
    ],
    "sg:phone":"+1 510 530 3155",
    "sg:postcode":"94611",
    "sg:province":"CA",
    "sg:tags":[
        "industrial",
        "clothing",
        "engineer"
    ],
    "wof:name":"Schinzinger & Co",
    "wof:placetype":"venue"
},
  "geometry": {"coordinates":[-122.192401,37.822508],"type":"Point"}
}