{
  "type": "Feature",
  "properties": {
    "addr:full":"178 Herlong Avenue San Jose CA 95123",
    "addr:housenumber":"178",
    "addr:postcode":"95123",
    "addr:street":"Herlong Avenue",
    "iso:country":"US",
    "sg:address":"178 Herlong Avenue",
    "sg:city":"San Jose",
    "sg:classifiers":[
        {
            "category":"Communications",
            "subcategory":"Newspaper",
            "type":"Services"
        }
    ],
    "sg:phone":"+1 408 225 5777",
    "sg:postcode":"95123",
    "sg:province":"CA",
    "sg:tags":[
        "magazine"
    ],
    "wof:name":"Rj Bender Publishing",
    "wof:placetype":"venue"
},
  "geometry": {"coordinates":[-121.808576,37.243908],"type":"Point"}
}