{
  "type": "Feature",
  "properties": {
    "iso:country":"US",
    "sg:address":"1658 E Edom St",
    "sg:city":"Carson",
    "sg:classifiers":[
        {
            "category":"Social Services",
            "subcategory":"Child Care",
            "type":"Services"
        }
    ],
    "sg:phone":"+1 310 537 0384",
    "sg:postcode":"90746",
    "sg:province":"CA",
    "sg:tags":[
        "day"
    ],
    "wof:name":"Our Future Day Care",
    "wof:placetype":"venue"
},
  "geometry": {"coordinates":[-118.241675,33.849376],"type":"Point"}
}