{
  "type": "Feature",
  "properties": {
    "addr:full":"21011 Pioneer Blvd Corner of Pioneer and Centralia Lakewood CA 90715",
    "addr:housenumber":"21011",
    "addr:postcode":"90715",
    "addr:street":"Pioneer Blvd Corner Of",
    "iso:country":"US",
    "sg:address":"21011 Pioneer Blvd Corner of Pioneer and Centralia",
    "sg:city":"Lakewood",
    "sg:classifiers":[
        {
            "category":"Retail",
            "subcategory":"Car Wash",
            "type":"Services"
        },
        {
            "category":"Retail",
            "subcategory":"Auto Repair",
            "type":"Services"
        }
    ],
    "sg:phone":"+1 562 445 4260",
    "sg:postcode":"90715",
    "sg:province":"CA",
    "sg:tags":[
        "detailing"
    ],
    "sg:website":"detailscarwashandlube.com/",
    "wof:name":"Details Car Wash and Lube",
    "wof:placetype":"venue"
},
  "geometry": {"coordinates":[-118.082279,33.838392],"type":"Point"}
}