{
  "type": "Feature",
  "properties": {
    "iso:country":"US",
    "sg:address":"1011 S Alvarado Street Suite 101",
    "sg:city":"Los Angeles",
    "sg:classifiers":[
        {
            "category":"Retail",
            "subcategory":"Portrait Studio",
            "type":"Services"
        }
    ],
    "sg:phone":"+1 213 388 6055",
    "sg:postcode":"90006",
    "sg:province":"CA",
    "sg:tags":[
        "photography",
        "store"
    ],
    "wof:name":"Fantasy Photo",
    "wof:placetype":"venue"
},
  "geometry": {"coordinates":[-118.280055,34.051161],"type":"Point"}
}