{
  "type": "Feature",
  "properties": {
    "addr:full":"9640 Creemore Dr Tujunga CA 91042",
    "addr:housenumber":"9640",
    "addr:postcode":"91042",
    "addr:street":"Creemore Dr",
    "iso:country":"US",
    "sg:address":"9640 Creemore Dr",
    "sg:city":"Tujunga",
    "sg:classifiers":[
        {
            "category":"Autos & Motor Vehicles",
            "subcategory":"Automobile Sales",
            "type":"Retail Goods"
        }
    ],
    "sg:phone":"+1 818 353 0539",
    "sg:postcode":"91042",
    "sg:province":"CA",
    "sg:tags":[
        "used"
    ],
    "wof:name":"Heno Auto Sales",
    "wof:placetype":"venue"
},
  "geometry": {"coordinates":[-118.27233,34.2424],"type":"Point"}
}