{
  "type": "Feature",
  "properties": {
    "addr:full":"33 Hopper Canyon Rd Fillmore CA 93015",
    "addr:housenumber":"33",
    "addr:postcode":"93015",
    "addr:street":"Hopper Canyon Rd",
    "iso:country":"US",
    "sg:address":"33 Hopper Canyon Rd",
    "sg:city":"Fillmore",
    "sg:classifiers":[
        {
            "category":"Building & Trades",
            "subcategory":"Equipment Rental",
            "type":"Services"
        },
        {
            "category":"Building & Trades",
            "subcategory":"Construction",
            "type":"Services"
        }
    ],
    "sg:phone":"+1 805 521 1570",
    "sg:postcode":"93015",
    "sg:province":"CA",
    "sg:tags":[
        "excavating",
        "bulldozing",
        "general"
    ],
    "wof:name":"Lowe Construction Company Inc",
    "wof:placetype":"venue"
},
  "geometry": {"coordinates":[-118.832145,34.400235],"type":"Point"}
}