{
  "type": "Feature",
  "properties": {
    "addr:full":"10640 Sepulveda Blvd Mission Hills CA 91345",
    "addr:housenumber":"10640",
    "addr:postcode":"91345",
    "addr:street":"Sepulveda Blvd",
    "iso:country":"US",
    "sg:address":"10640 Sepulveda Blvd",
    "sg:city":"Mission Hills",
    "sg:classifiers":[
        {
            "category":"Building & Trades",
            "subcategory":"Electrical",
            "type":"Services"
        }
    ],
    "sg:phone":"+1 818 365 7103",
    "sg:postcode":"91345",
    "sg:province":"CA",
    "sg:tags":[
        "electrical",
        "contractor"
    ],
    "wof:name":"Prescott Network Solution Inc",
    "wof:placetype":"venue"
},
  "geometry": {"coordinates":[-118.46725600000001,34.261982],"type":"Point"}
}