{
  "type": "Feature",
  "properties": {
    "addr:full":"21800 Burbank Blvd Woodland Hills CA 91367",
    "addr:housenumber":"21800",
    "addr:postcode":"91367",
    "addr:street":"Burbank Blvd",
    "iso:country":"US",
    "sg:address":"21800 Burbank Blvd",
    "sg:city":"Woodland Hills",
    "sg:classifiers":[
        {
            "category":"Professional",
            "subcategory":"Computer Services",
            "type":"Services"
        }
    ],
    "sg:phone":"+1 805 493 8050",
    "sg:postcode":"91367",
    "sg:province":"CA",
    "sg:tags":[
        "consultant",
        "designer"
    ],
    "wof:name":"Data Move",
    "wof:placetype":"venue"
},
  "geometry": {"coordinates":[-118.604209,34.17197],"type":"Point"}
}