{
  "type": "Feature",
  "properties": {
    "iso:country":"US",
    "sg:address":"3740 Florence St",
    "sg:city":"Redwood City",
    "sg:classifiers":[
        {
            "category":"Personal",
            "subcategory":"Beauty Salon",
            "type":"Services"
        }
    ],
    "sg:phone":"+1 650 366 5533",
    "sg:postcode":"94063",
    "sg:province":"CA",
    "wof:name":"Hair West",
    "wof:placetype":"venue"
},
  "geometry": {"coordinates":[-122.18678,37.478641],"type":"Point"}
}