{
  "type": "Feature",
  "properties": {
    "addr:full":"806 Jackman St El Cajon CA 92020",
    "addr:housenumber":"806",
    "addr:postcode":"92020",
    "addr:street":"Jackman St",
    "iso:country":"US",
    "sg:address":"806 Jackman St",
    "sg:city":"El Cajon",
    "sg:classifiers":[
        {
            "category":"Home & Garden",
            "subcategory":"Building Materials",
            "type":"Retail Goods"
        }
    ],
    "sg:phone":"+1 619 447 1400",
    "sg:postcode":"92020",
    "sg:province":"CA",
    "sg:tags":[
        "paint"
    ],
    "wof:name":"Advanced Color Coatings Inc",
    "wof:placetype":"venue"
},
  "geometry": {"coordinates":[-116.973466,32.807553],"type":"Point"}
}