{
  "type": "Feature",
  "properties": {
    "iso:country":"US",
    "sg:address":"2637 Shadelands Dr",
    "sg:city":"Walnut Creek",
    "sg:classifiers":[
        {
            "category":"Manufacturing",
            "subcategory":"Chemicals & Compounds",
            "type":"Manufacturing & Wholesale Goods"
        }
    ],
    "sg:phone":"+1 925 295 0200",
    "sg:postcode":"94598",
    "sg:province":"CA",
    "sg:tags":[
        "pharmaceutical",
        "mfg",
        "prep",
        "instr"
    ],
    "wof:name":"Fresenius USA Manufacturing",
    "wof:placetype":"venue"
},
  "geometry": {"coordinates":[-122.020625,37.92829],"type":"Point"}
}