{
  "type": "Feature",
  "properties": {
    "iso:country":"US",
    "sg:address":"1515 Parrott Dr",
    "sg:city":"San Mateo",
    "sg:classifiers":[
        {
            "category":"Professional",
            "type":"Services"
        }
    ],
    "sg:phone":"+1 650 571 8377",
    "sg:postcode":"94402",
    "sg:province":"CA",
    "wof:name":"Eric Larson",
    "wof:placetype":"venue"
},
  "geometry": {"coordinates":[-122.340837,37.531269],"type":"Point"}
}