{
  "type": "Feature",
  "properties": {
    "iso:country":"US",
    "sg:address":"1336 Newport Ave",
    "sg:city":"Long Beach",
    "sg:classifiers":[
        {
            "category":"Retail",
            "subcategory":"Storage",
            "type":"Services"
        }
    ],
    "sg:phone":"+1 562 498 3740",
    "sg:postcode":"90804",
    "sg:province":"CA",
    "sg:tags":[
        "self"
    ],
    "wof:name":"Security Mini Storage",
    "wof:placetype":"venue"
},
  "geometry": {"coordinates":[-118.150994,33.783374],"type":"Point"}
}