{
  "type": "Feature",
  "properties": {
    "addr:full":"11401 Chandler Blvd North Hollywood CA 91601",
    "addr:housenumber":"11401",
    "addr:postcode":"91601",
    "addr:street":"Chandler Blvd",
    "iso:country":"US",
    "sg:address":"11401 Chandler Blvd",
    "sg:city":"North Hollywood",
    "sg:classifiers":[
        {
            "category":"Arts & Performance",
            "subcategory":"Arts Center",
            "type":"Entertainment"
        }
    ],
    "sg:phone":"+1 818 752 2893",
    "sg:postcode":"91601",
    "sg:province":"CA",
    "sg:tags":[
        "performing"
    ],
    "wof:name":"Mkm Cultural Arts Center",
    "wof:placetype":"venue"
},
  "geometry": {"coordinates":[-118.378998,34.168999],"type":"Point"}
}