{
  "type": "Feature",
  "properties": {
    "addr:full":"11944 S La Cienega Blvd Hawthorne CA 90250",
    "addr:housenumber":"11944",
    "addr:postcode":"90250",
    "addr:street":"S La Cienega Blvd",
    "iso:country":"US",
    "sg:address":"11944 S La Cienega Blvd",
    "sg:city":"Hawthorne",
    "sg:classifiers":[
        {
            "category":"Sports & Exercise",
            "subcategory":"Gym",
            "type":"Entertainment"
        }
    ],
    "sg:phone":"+1 424 240 5291",
    "sg:postcode":"90250",
    "sg:province":"CA",
    "wof:name":"LAX CrossFit",
    "wof:placetype":"venue"
},
  "geometry": {"coordinates":[-118.369845,33.924212],"type":"Point"}
}