{
  "type": "Feature",
  "properties": {
    "addr:full":"12626 High Bluff Dr Ste 325 San Diego CA 92130",
    "addr:housenumber":"12626",
    "addr:postcode":"92130",
    "addr:street":"High Bluff Dr Ste 325",
    "iso:country":"US",
    "sg:address":"12626 High Bluff Dr Ste 325",
    "sg:city":"San Diego",
    "sg:classifiers":[
        {
            "category":"Banks & Credit Unions",
            "subcategory":"Financial Services",
            "type":"Services"
        }
    ],
    "sg:phone":"+1 858 793 1759",
    "sg:postcode":"92130",
    "sg:province":"CA",
    "sg:tags":[
        "broker",
        "mortgage"
    ],
    "wof:name":"Pathfinder Mortgage Corporation",
    "wof:placetype":"venue"
},
  "geometry": {"coordinates":[-117.22399900000001,32.945499],"type":"Point"}
}