{
  "type": "Feature",
  "properties": {
    "addr:full":"1555 E Lassen Ave Chico CA 95973",
    "addr:housenumber":"1555",
    "addr:postcode":"95973",
    "addr:street":"E Lassen Ave",
    "iso:country":"US",
    "sg:address":"1555 E Lassen Ave",
    "sg:city":"Chico",
    "sg:classifiers":[
        {
            "category":"Education",
            "subcategory":"School",
            "type":"Public Place"
        }
    ],
    "sg:phone":"+1 530 343 1343",
    "sg:postcode":"95973",
    "sg:province":"CA",
    "sg:tags":[
        "massage"
    ],
    "wof:name":"Chico Therapy Wellness Center",
    "wof:placetype":"venue"
},
  "geometry": {"coordinates":[-121.83437499999999,39.774068],"type":"Point"}
}