{
  "type": "Feature",
  "properties": {
    "iso:country":"US",
    "sg:address":"3700 Santa Fe Ave",
    "sg:city":"Long Beach",
    "sg:classifiers":[
        {
            "category":"Professional",
            "subcategory":"Lawyer & Legal Services",
            "type":"Services"
        }
    ],
    "sg:phone":"+1 530 243 9999",
    "sg:postcode":"90810",
    "sg:province":"CA",
    "wof:name":"PACIFIC ATTORNEY GROUP",
    "wof:placetype":"venue"
},
  "geometry": {"coordinates":[-118.215278,33.824848],"type":"Point"}
}