{
  "type": "Feature",
  "properties": {
    "addr:full":"219 International Blvd Oakland CA 94606",
    "addr:housenumber":"219",
    "addr:postcode":"94606",
    "addr:street":"International Blvd",
    "iso:country":"US",
    "sg:address":"219 International Blvd",
    "sg:city":"Oakland",
    "sg:classifiers":[
        {
            "category":"Personal",
            "subcategory":"Beauty Salon",
            "type":"Services"
        }
    ],
    "sg:phone":"+1 510 763 4140",
    "sg:postcode":"94606",
    "sg:province":"CA",
    "sg:tags":[
        "nail",
        "manicuring"
    ],
    "wof:name":"Vivi Cosmetic & Skincare",
    "wof:placetype":"venue"
},
  "geometry": {"coordinates":[-122.25599699999999,37.797699],"type":"Point"}
}