{
  "type": "Feature",
  "properties": {
    "addr:full":"461 S Western Ave Los Angeles CA 90020",
    "addr:housenumber":"461",
    "addr:postcode":"90020",
    "addr:street":"S Western Ave",
    "iso:country":"US",
    "sg:address":"461 S Western Ave",
    "sg:city":"Los Angeles",
    "sg:classifiers":[
        {
            "category":"Shopping",
            "subcategory":"Pharmacy",
            "type":"Retail Goods"
        }
    ],
    "sg:phone":"+1 213 480 3322",
    "sg:postcode":"90020",
    "sg:province":"CA",
    "sg:tags":[
        "drugstore"
    ],
    "wof:name":"Hyundai Pharmacy",
    "wof:placetype":"venue"
},
  "geometry": {"coordinates":[-118.308998,34.0658],"type":"Point"}
}