{
  "type": "Feature",
  "properties": {
    "addr:full":"2851 State Hwy 32 Chico CA 95973",
    "addr:housenumber":"2851",
    "addr:postcode":"95973",
    "addr:street":"State Hwy 32",
    "iso:country":"US",
    "sg:address":"2851 State Hwy 32",
    "sg:city":"Chico",
    "sg:classifiers":[
        {
            "category":"Wholesale",
            "subcategory":"Furniture",
            "type":"Manufacturing & Wholesale Goods"
        }
    ],
    "sg:phone":"+1 530 891 5335",
    "sg:postcode":"95973",
    "sg:province":"CA",
    "sg:website":"www.budgetministoragechico.com",
    "wof:name":"Budget Mini Storage",
    "wof:placetype":"venue"
},
  "geometry": {"coordinates":[-121.889325,39.744279],"type":"Point"}
}