{
  "type": "Feature",
  "properties": {
    "iso:country":"US",
    "sg:address":"8620 S Gate Ave",
    "sg:city":"South Gate",
    "sg:classifiers":[
        {
            "category":"Government",
            "subcategory":"Police Station",
            "type":"Public Place"
        }
    ],
    "sg:phone":"+1 323 563 5400",
    "sg:postcode":"90280",
    "sg:province":"CA",
    "sg:tags":[
        "protection"
    ],
    "wof:name":"Police Department",
    "wof:placetype":"venue"
},
  "geometry": {"coordinates":[-118.214436,33.955272],"type":"Point"}
}