{
  "type": "Feature",
  "properties": {
    "iso:country":"US",
    "sg:address":"23727 Hawthorne Blvd",
    "sg:city":"Torrance",
    "sg:classifiers":[
        {
            "category":"Organizations",
            "subcategory":"Non-profit Organization",
            "type":"Services"
        }
    ],
    "sg:phone":"+1 310 378 7838",
    "sg:postcode":"90505",
    "sg:province":"CA",
    "sg:tags":[
        "service/non-profit",
        "community"
    ],
    "wof:name":"Concours D'elegance",
    "wof:placetype":"venue"
},
  "geometry": {"coordinates":[-118.350998,33.8097],"type":"Point"}
}