{
  "type": "Feature",
  "properties": {
    "addr:full":"577 University Ave Los Gatos CA 95032",
    "addr:housenumber":"577",
    "addr:postcode":"95032",
    "addr:street":"University Ave",
    "iso:country":"US",
    "sg:address":"577 University Ave",
    "sg:city":"Los Gatos",
    "sg:classifiers":[
        {
            "category":"Autos & Motor Vehicles",
            "subcategory":"Auto Supplies",
            "type":"Retail Goods"
        }
    ],
    "sg:phone":"+1 408 354 4011",
    "sg:postcode":"95032",
    "sg:province":"CA",
    "sg:tags":[
        "tire"
    ],
    "wof:name":"Big O Tire Stores",
    "wof:placetype":"venue"
},
  "geometry": {"coordinates":[-121.975998,37.2369],"type":"Point"}
}