{
  "type": "Feature",
  "properties": {
    "iso:country":"US",
    "sg:address":"9525 Tweedy Ln",
    "sg:city":"Downey",
    "sg:classifiers":[
        {
            "category":"Education",
            "subcategory":"School",
            "type":"Public Place"
        }
    ],
    "sg:phone":"+1 562 904 3575",
    "sg:postcode":"90240",
    "sg:province":"CA",
    "sg:tags":[
        "high",
        "middle",
        "elementary"
    ],
    "sg:website":"www.dusd.net",
    "wof:name":"Price Maude Elementary School",
    "wof:placetype":"venue"
},
  "geometry": {"coordinates":[-118.127379,33.960489],"type":"Point"}
}