{
  "type": "Feature",
  "properties": {
    "iso:country":"US",
    "sg:address":"1125 N Vermont Ave",
    "sg:city":"Los Angeles",
    "sg:classifiers":[
        {
            "category":"Shopping",
            "subcategory":"Clothing, Apparel, & Fashions",
            "type":"Retail Goods"
        },
        {
            "category":"Professional",
            "subcategory":"Printing & Photocopies",
            "type":"Services"
        }
    ],
    "sg:phone":"+1 323 680 4465",
    "sg:postcode":"90029",
    "sg:province":"CA",
    "sg:tags":[
        "men's",
        "clothing",
        "women's"
    ],
    "sg:website":"www.DIYshirts.com",
    "wof:name":"DIY Shirts",
    "wof:placetype":"venue"
},
  "geometry": {"coordinates":[-118.29208199999999,34.091578],"type":"Point"}
}