{
  "type": "Feature",
  "properties": {
    "addr:full":"1082 Stockton Ave San Jose CA 95110",
    "addr:housenumber":"1082",
    "addr:postcode":"95110",
    "addr:street":"Stockton Ave",
    "iso:country":"US",
    "sg:address":"1082 Stockton Ave",
    "sg:city":"San Jose",
    "sg:classifiers":[
        {
            "category":"Retail",
            "subcategory":"Portrait Studio",
            "type":"Services"
        }
    ],
    "sg:phone":"+1 408 295 6585",
    "sg:postcode":"95110",
    "sg:province":"CA",
    "sg:tags":[
        "photographer"
    ],
    "sg:website":"www.eaganpv.com",
    "wof:name":"Eagan Photography & Video",
    "wof:placetype":"venue"
},
  "geometry": {"coordinates":[-121.921209,37.347781],"type":"Point"}
}