{
  "type": "Feature",
  "properties": {
    "addr:full":"943 Lomas Santa Fe Dr Solana Beach CA 92075",
    "addr:housenumber":"943",
    "addr:postcode":"92075",
    "addr:street":"Lomas Santa Fe Dr",
    "iso:country":"US",
    "sg:address":"943 Lomas Santa Fe Dr",
    "sg:city":"Solana Beach",
    "sg:classifiers":[
        {
            "category":"Wholesale",
            "subcategory":"Stationery",
            "type":"Manufacturing & Wholesale Goods"
        }
    ],
    "sg:phone":"+1 858 755 6871",
    "sg:postcode":"92075",
    "sg:province":"CA",
    "sg:tags":[
        "school",
        "supply"
    ],
    "wof:name":"Creative Teaching Supplies",
    "wof:placetype":"venue"
},
  "geometry": {"coordinates":[-117.25540599999999,32.99572],"type":"Point"}
}