{
  "type": "Feature",
  "properties": {
    "iso:country":"US",
    "sg:address":"641 W Sycamore Dr",
    "sg:city":"San Gabriel",
    "sg:classifiers":[
        {
            "category":"Wholesale",
            "subcategory":"Medical Equipment & Supplies",
            "type":"Manufacturing & Wholesale Goods"
        }
    ],
    "sg:phone":"+1 626 457 1801",
    "sg:postcode":"91775",
    "sg:province":"CA",
    "sg:tags":[
        "organization",
        "membership"
    ],
    "wof:name":"Clear River Investment",
    "wof:placetype":"venue"
},
  "geometry": {"coordinates":[-118.109562,34.107163],"type":"Point"}
}