{
  "type": "Feature",
  "properties": {
    "addr:full":"31465 Whispering Palms Trl Cathedral City CA 92234",
    "addr:housenumber":"31465",
    "addr:postcode":"92234",
    "addr:street":"Whispering Palms Trl",
    "iso:country":"US",
    "sg:address":"31465 Whispering Palms Trl",
    "sg:city":"Cathedral City",
    "sg:classifiers":[
        {
            "category":"Building & Trades",
            "subcategory":"Construction",
            "type":"Services"
        }
    ],
    "sg:phone":"+1 760 202 7373",
    "sg:postcode":"92234",
    "sg:province":"CA",
    "sg:tags":[
        "coping",
        "plastering",
        "tiling",
        "pool",
        "swimming"
    ],
    "wof:name":"Segals Pool Svc",
    "wof:placetype":"venue"
},
  "geometry": {"coordinates":[-116.471294,33.822937],"type":"Point"}
}