{
  "type": "Feature",
  "properties": {
    "iso:country":"US",
    "sg:address":"8200 Firestone Blvd Ste B",
    "sg:city":"Downey",
    "sg:classifiers":[
        {
            "category":"Health Services",
            "subcategory":"Health Practitioner",
            "type":"Services"
        }
    ],
    "sg:phone":"+1 562 923 1111",
    "sg:postcode":"90241",
    "sg:province":"CA",
    "sg:tags":[
        "acupuncture"
    ],
    "wof:name":"Dong Kook Acupuncture Clinic & Herbs",
    "wof:placetype":"venue"
},
  "geometry": {"coordinates":[-118.135002,33.9408],"type":"Point"}
}