{
  "type": "Feature",
  "properties": {
    "iso:country":"US",
    "sg:address":"4301 S Figueroa St Ste G",
    "sg:city":"Los Angeles",
    "sg:classifiers":[
        {
            "category":"Food & Beverages",
            "subcategory":"Groceries & Convenience Stores",
            "type":"Retail Goods"
        }
    ],
    "sg:phone":"+1 323 235 4640",
    "sg:postcode":"90037",
    "sg:province":"CA",
    "wof:name":"One Dollar Warehouse",
    "wof:placetype":"venue"
},
  "geometry": {"coordinates":[-118.28299699999999,34.005402],"type":"Point"}
}