{
  "type": "Feature",
  "properties": {
    "addr:full":"6251 W 78th St Los Angeles CA 90045",
    "addr:housenumber":"6251",
    "addr:postcode":"90045",
    "addr:street":"W 78Th St",
    "iso:country":"US",
    "sg:address":"6251 W 78th St",
    "sg:city":"Los Angeles",
    "sg:classifiers":[
        {
            "category":"Manufacturing",
            "subcategory":"Printing",
            "type":"Manufacturing & Wholesale Goods"
        }
    ],
    "sg:phone":"+1 310 649 2573",
    "sg:postcode":"90045",
    "sg:province":"CA",
    "sg:tags":[
        "publisher"
    ],
    "sg:website":"www.multimediayearbook.com",
    "wof:name":"International Video Yearbooks",
    "wof:placetype":"venue"
},
  "geometry": {"coordinates":[-118.39423600000001,33.969785],"type":"Point"}
}