{
  "type": "Feature",
  "properties": {
    "iso:country":"US",
    "sg:address":"37 E Olive Ave",
    "sg:city":"Redlands",
    "sg:classifiers":[
        {
            "category":"Professional",
            "subcategory":"Engineering",
            "type":"Services"
        }
    ],
    "sg:phone":"+1 909 793 2257",
    "sg:postcode":"92373",
    "sg:province":"CA",
    "sg:tags":[
        "engineer"
    ],
    "wof:name":"Hicks & Hartwick Inc",
    "wof:placetype":"venue"
},
  "geometry": {"coordinates":[-117.180938,34.053637],"type":"Point"}
}