{
  "type": "Feature",
  "properties": {
    "addr:full":"209 S 4th St Santa Paula CA 93060",
    "addr:housenumber":"209",
    "addr:postcode":"93060",
    "addr:street":"S 4Th St",
    "iso:country":"US",
    "sg:address":"209 S 4th St",
    "sg:city":"Santa Paula",
    "sg:phone":"+1 805 525 2992",
    "sg:postcode":"93060",
    "sg:province":"CA",
    "sg:tags":[
        "farm",
        "wheat"
    ],
    "wof:name":"Dale Von Trebra",
    "wof:placetype":"venue"
},
  "geometry": {"coordinates":[-119.06786200000001,34.349277],"type":"Point"}
}