{
  "type": "Feature",
  "properties": {
    "iso:country":"US",
    "sg:address":"370 Park St",
    "sg:city":"Moraga",
    "sg:classifiers":[
        {
            "category":"Arts & Performance",
            "subcategory":"Arts Center",
            "type":"Entertainment"
        },
        {
            "category":"Arts & Performance",
            "subcategory":"Dance",
            "type":"Entertainment"
        }
    ],
    "sg:phone":"+1 925 376 2454",
    "sg:postcode":"94556",
    "sg:province":"CA",
    "sg:tags":[
        "information",
        "instruction",
        "dancing"
    ],
    "sg:website":"http://www.capadance.net",
    "wof:name":"California Academy Of Performing Arts Inc",
    "wof:placetype":"venue"
},
  "geometry": {"coordinates":[-122.126312,37.860544],"type":"Point"}
}