{
  "type": "Feature",
  "properties": {
    "iso:country":"US",
    "sg:address":"11100 Valley Blvd",
    "sg:city":"El Monte",
    "sg:classifiers":[
        {
            "category":"Wholesale",
            "subcategory":"Durable Goods & Equipment",
            "type":"Manufacturing & Wholesale Goods"
        }
    ],
    "sg:phone":"+1 626 448 3039",
    "sg:postcode":"91731",
    "sg:province":"CA",
    "sg:tags":[
        "professional",
        "scientific"
    ],
    "wof:name":"Youngin USA Inc",
    "wof:placetype":"venue"
},
  "geometry": {"coordinates":[-118.032456,34.072597],"type":"Point"}
}