{
  "type": "Feature",
  "properties": {
    "iso:country":"US",
    "sg:address":"1170 Arnold Dr",
    "sg:city":"Martinez",
    "sg:classifiers":[
        {
            "category":"Restaurant",
            "type":"Food & Drink"
        }
    ],
    "sg:menulink":"http://www.allmenus.com/ca/central-contra-costa/197794-kfc---kentucky-fried-chicken/menu/",
    "sg:phone":"+1 925 229 2244",
    "sg:postcode":"94553",
    "sg:province":"CA",
    "sg:tags":[
        "american",
        "chicken"
    ],
    "wof:name":"KFC - Kentucky Fried Chicken",
    "wof:placetype":"venue"
},
  "geometry": {"coordinates":[-122.101528,37.993236],"type":"Point"}
}