{
  "type": "Feature",
  "properties": {
    "iso:country":"US",
    "sg:address":"Campland by the Bay 2211 Pacific Beach Dr",
    "sg:city":"San Diego",
    "sg:classifiers":[
        {
            "category":"Restaurant",
            "type":"Food & Drink"
        }
    ],
    "sg:phone":"+1 858 581 4226",
    "sg:postcode":"92109",
    "sg:province":"CA",
    "sg:website":"www.campland.com/cafeteria.php?t...",
    "wof:name":"Hungry Wolf Barbecue and Ice Cream Parlor",
    "wof:placetype":"venue"
},
  "geometry": {"coordinates":[-117.227869,32.796589],"type":"Point"}
}