{
  "type": "Feature",
  "properties": {
    "addr:full":"312 Arroyo Way Sonoma CA 95476",
    "addr:housenumber":"312",
    "addr:postcode":"95476",
    "addr:street":"Arroyo Way",
    "iso:country":"US",
    "sg:address":"312 Arroyo Way",
    "sg:city":"Sonoma",
    "sg:classifiers":[
        {
            "category":"Building & Trades",
            "subcategory":"Construction",
            "type":"Services"
        }
    ],
    "sg:phone":"+1 707 938 8234",
    "sg:postcode":"95476",
    "sg:province":"CA",
    "sg:tags":[
        "contractor"
    ],
    "wof:name":"Hoffman Dean Acoustical E",
    "wof:placetype":"venue"
},
  "geometry": {"coordinates":[-122.464433,38.28704],"type":"Point"}
}