{
  "type": "Feature",
  "properties": {
    "iso:country":"US",
    "sg:address":"166 E Laguna Dr",
    "sg:city":"Tracy",
    "sg:classifiers":[
        {
            "category":"Building & Trades",
            "subcategory":"Construction",
            "type":"Services"
        }
    ],
    "sg:phone":"+1 209 835 4579",
    "sg:postcode":"95376",
    "sg:province":"CA",
    "sg:tags":[
        "heavy"
    ],
    "wof:name":"Martin Cotta Land Leveling",
    "wof:placetype":"venue"
},
  "geometry": {"coordinates":[-121.425206,37.759905],"type":"Point"}
}