{
  "type": "Feature",
  "properties": {
    "addr:full":"777 N State Highway 49-88 Jackson CA 95642",
    "addr:housenumber":"777;49-88",
    "addr:postcode":"95642",
    "addr:street":"N State Highway",
    "iso:country":"US",
    "sg:address":"777 N State Highway 49-88",
    "sg:city":"Jackson",
    "sg:classifiers":[
        {
            "category":"Restaurant",
            "type":"Food & Drink"
        }
    ],
    "sg:menulink":"http://www.allmenus.com/ca/jackson/77864-papa-murphys/menu/",
    "sg:phone":"+1 209 223 5052",
    "sg:postcode":"95642",
    "sg:province":"CA",
    "sg:tags":[
        "american",
        "pizza"
    ],
    "wof:name":"Papa Murphy's",
    "wof:placetype":"venue"
},
  "geometry": {"coordinates":[-120.78080300000001,38.355888],"type":"Point"}
}