{
  "type": "Feature",
  "properties": {
    "iso:country":"US",
    "sg:address":"55 San Fernando Way",
    "sg:city":"Daly City",
    "sg:classifiers":[
        {
            "category":"Organizations",
            "subcategory":"Religious Organization",
            "type":"Services"
        }
    ],
    "sg:phone":"+1 650 991 4673",
    "sg:postcode":"94015",
    "sg:province":"CA",
    "sg:tags":[
        "counseling",
        "pastoral",
        "clergy"
    ],
    "wof:name":"Hope Lutheran Church-Missouri",
    "wof:placetype":"venue"
},
  "geometry": {"coordinates":[-122.473343,37.683497],"type":"Point"}
}