{
  "type": "Feature",
  "properties": {
    "addr:full":"7 Journey Aliso Viejo CA 92656",
    "addr:housenumber":"7",
    "addr:postcode":"92656",
    "addr:street":"Journey",
    "iso:country":"US",
    "sg:address":"7 Journey",
    "sg:city":"Aliso Viejo",
    "sg:classifiers":[
        {
            "category":"Social Services",
            "subcategory":"Child Care",
            "type":"Services"
        }
    ],
    "sg:phone":"+1 949 425 8257",
    "sg:postcode":"92656",
    "sg:province":"CA",
    "wof:name":"Celebration Kid's Co",
    "wof:placetype":"venue"
},
  "geometry": {"coordinates":[-117.72782100000001,33.567329],"type":"Point"}
}