{
  "type": "Feature",
  "properties": {
    "addr:full":"221 E Whittier Blvd La Habra CA 90631",
    "addr:housenumber":"221",
    "addr:postcode":"90631",
    "addr:street":"E Whittier Blvd",
    "iso:country":"US",
    "sg:address":"221 E Whittier Blvd",
    "sg:city":"La Habra",
    "sg:classifiers":[
        {
            "category":"Autos & Motor Vehicles",
            "subcategory":"Auto Supplies",
            "type":"Retail Goods"
        }
    ],
    "sg:phone":"+1 562 694 0087",
    "sg:postcode":"90631",
    "sg:province":"CA",
    "sg:tags":[
        "tire"
    ],
    "wof:name":"Salinas Tire",
    "wof:placetype":"venue"
},
  "geometry": {"coordinates":[-117.94434699999999,33.939191],"type":"Point"}
}