{
  "type": "Feature",
  "properties": {
    "addr:full":"10078 Arrow Rte Rancho Cucamonga CA 91730",
    "addr:housenumber":"10078",
    "addr:postcode":"91730",
    "addr:street":"Arrow Rte",
    "iso:country":"US",
    "sg:address":"10078 Arrow Rte",
    "sg:city":"Rancho Cucamonga",
    "sg:classifiers":[
        {
            "category":"Food & Beverages",
            "subcategory":"Bakery",
            "type":"Retail Goods"
        }
    ],
    "sg:phone":"+1 909 941 9838",
    "sg:postcode":"91730",
    "sg:province":"CA",
    "sg:tags":[
        "doughnut"
    ],
    "wof:name":"Grand Slam Donuts & Ice Cream",
    "wof:placetype":"venue"
},
  "geometry": {"coordinates":[-117.58668400000001,34.099371],"type":"Point"}
}