{
  "type": "Feature",
  "properties": {
    "iso:country":"US",
    "sg:address":"24201 W Valencia Blvd Ste 3552",
    "sg:city":"Valencia",
    "sg:classifiers":[
        {
            "category":"Food & Beverages",
            "subcategory":"Candy",
            "type":"Retail Goods"
        }
    ],
    "sg:phone":"+1 661 260 2253",
    "sg:postcode":"91355",
    "sg:province":"CA",
    "sg:tags":[
        "dessert"
    ],
    "sg:website":"www.velvetcupcakes.com",
    "wof:name":"Velvet Cupcakes",
    "wof:placetype":"venue"
},
  "geometry": {"coordinates":[-118.557666,34.416061],"type":"Point"}
}