{
  "type": "Feature",
  "properties": {
    "iso:country":"US",
    "sg:address":"7231 Balboa Blvd",
    "sg:city":"Van Nuys",
    "sg:classifiers":[
        {
            "category":"Building & Trades",
            "subcategory":"Construction",
            "type":"Services"
        }
    ],
    "sg:phone":"+1 818 994 1500",
    "sg:postcode":"91406",
    "sg:province":"CA",
    "sg:tags":[
        "hanging",
        "contractor"
    ],
    "wof:name":"Pauls Custom Painting",
    "wof:placetype":"venue"
},
  "geometry": {"coordinates":[-118.5012,34.201773],"type":"Point"}
}