{
  "type": "Feature",
  "properties": {
    "addr:full":"8861 N Magnolia Ave Santee CA 92071",
    "addr:housenumber":"8861",
    "addr:postcode":"92071",
    "addr:street":"N Magnolia Ave",
    "iso:country":"US",
    "sg:address":"8861 N Magnolia Ave",
    "sg:city":"Santee",
    "sg:classifiers":[
        {
            "category":"Autos & Motor Vehicles",
            "subcategory":"Automobile Sales",
            "type":"Retail Goods"
        }
    ],
    "sg:phone":"+1 619 449 8500",
    "sg:postcode":"92071",
    "sg:province":"CA",
    "sg:tags":[
        "dealers-used",
        "car",
        "used",
        "cars-wholesale",
        "new"
    ],
    "sg:website":"http://www.auto-webdesign.com",
    "wof:name":"El Cajon Motors",
    "wof:placetype":"venue"
},
  "geometry": {"coordinates":[-116.966644,32.837303],"type":"Point"}
}