{
  "type": "Feature",
  "properties": {
    "iso:country":"US",
    "sg:address":"20942 Osborne St",
    "sg:city":"Canoga Park",
    "sg:classifiers":[
        {
            "category":"Professional",
            "subcategory":"Computer Services",
            "type":"Services"
        }
    ],
    "sg:phone":"+1 818 772 5370",
    "sg:postcode":"91304",
    "sg:province":"CA",
    "sg:tags":[
        "home",
        "consulting",
        "page",
        "dev",
        "internet"
    ],
    "wof:name":"Green Web Properties",
    "wof:placetype":"venue"
},
  "geometry": {"coordinates":[-118.589939,34.232965],"type":"Point"}
}