{
  "type": "Feature",
  "properties": {
    "addr:full":"2170 Arrowhead Dr Oakland CA 94611",
    "addr:housenumber":"2170",
    "addr:postcode":"94611",
    "addr:street":"Arrowhead Dr",
    "iso:country":"US",
    "sg:address":"2170 Arrowhead Dr",
    "sg:city":"Oakland",
    "sg:classifiers":[
        {
            "category":"Organizations",
            "subcategory":"Non-profit Organization",
            "type":"Services"
        }
    ],
    "sg:phone":"+1 510 339 1265",
    "sg:postcode":"94611",
    "sg:province":"CA",
    "sg:tags":[
        "society",
        "humane"
    ],
    "wof:name":"Tidy Year Turf",
    "wof:placetype":"venue"
},
  "geometry": {"coordinates":[-122.190395,37.836431],"type":"Point"}
}