{
  "type": "Feature",
  "properties": {
    "addr:full":"3342 Hollowtree Dr Oceanside CA 92058",
    "addr:housenumber":"3342",
    "addr:postcode":"92058",
    "addr:street":"Hollowtree Dr",
    "iso:country":"US",
    "sg:address":"3342 Hollowtree Dr",
    "sg:city":"Oceanside",
    "sg:classifiers":[
        {
            "category":"Professional",
            "subcategory":"Employment Agencies",
            "type":"Services"
        }
    ],
    "sg:phone":"+1 760 754 8177",
    "sg:postcode":"92058",
    "sg:province":"CA",
    "sg:tags":[
        "opportunity"
    ],
    "wof:name":"Broadcast Employment Services",
    "wof:placetype":"venue"
},
  "geometry": {"coordinates":[-117.350408,33.226934],"type":"Point"}
}