{
  "type": "Feature",
  "properties": {
    "addr:full":"1132 Santee Street Los Angeles CA 90015",
    "addr:housenumber":"1132",
    "addr:postcode":"90015",
    "addr:street":"Santee Street",
    "iso:country":"US",
    "sg:address":"1132 Santee Street",
    "sg:city":"Los Angeles",
    "sg:classifiers":[
        {
            "category":"Shopping",
            "subcategory":"Shoes",
            "type":"Retail Goods"
        }
    ],
    "sg:phone":"+1 213 747 0415",
    "sg:postcode":"90015",
    "sg:province":"CA",
    "sg:tags":[
        "store"
    ],
    "wof:name":"Rachel's Shoes",
    "wof:placetype":"venue"
},
  "geometry": {"coordinates":[-118.27153800000001,34.039118],"type":"Point"}
}