{
  "type": "Feature",
  "properties": {
    "iso:country":"US",
    "sg:address":"12660 Riverside Dr Ste 240",
    "sg:city":"Valley Village",
    "sg:classifiers":[
        {
            "category":"Health Services",
            "subcategory":"Dentist",
            "type":"Services"
        }
    ],
    "sg:phone":"+1 818 760 8966",
    "sg:postcode":"91607",
    "sg:province":"CA",
    "sg:tags":[
        "endodontist"
    ],
    "sg:website":"www.myrootcanalcare.com",
    "wof:name":"Dynamic Endontics",
    "wof:placetype":"venue"
},
  "geometry": {"coordinates":[-118.408997,34.1576],"type":"Point"}
}