{
  "type": "Feature",
  "properties": {
    "iso:country":"US",
    "sg:address":"3333 Midway Dr Ste 100",
    "sg:city":"San Diego",
    "sg:classifiers":[
        {
            "category":"Personal",
            "subcategory":"Skin Care",
            "type":"Services"
        },
        {
            "category":"Personal",
            "subcategory":"Piercing",
            "type":"Services"
        }
    ],
    "sg:phone":"+1 619 222 4210",
    "sg:postcode":"92110",
    "sg:province":"CA",
    "sg:website":"www.bodyartbyrns.com",
    "wof:name":"Body Art Salon",
    "wof:placetype":"venue"
},
  "geometry": {"coordinates":[-117.211315,32.750387],"type":"Point"}
}