{
  "type": "Feature",
  "properties": {
    "addr:full":"11340 W Olympic Blvd Los Angeles CA 90064",
    "addr:housenumber":"11340",
    "addr:postcode":"90064",
    "addr:street":"W Olympic Blvd",
    "iso:country":"US",
    "sg:address":"11340 W Olympic Blvd",
    "sg:city":"Los Angeles",
    "sg:classifiers":[
        {
            "category":"Real Estate",
            "subcategory":"Real Estate Operator",
            "type":"Services"
        }
    ],
    "sg:phone":"+1 310 477 1023",
    "sg:postcode":"90064",
    "sg:province":"CA",
    "sg:tags":[
        "building",
        "parks"
    ],
    "wof:name":"Commerce Plaza",
    "wof:placetype":"venue"
},
  "geometry": {"coordinates":[-118.44150999999999,34.038031],"type":"Point"}
}