{
  "type": "Feature",
  "properties": {
    "iso:country":"US",
    "sg:address":"123 Nevada St",
    "sg:city":"El Segundo",
    "sg:classifiers":[
        {
            "category":"Retail",
            "subcategory":"Auto Repair",
            "type":"Services"
        }
    ],
    "sg:phone":"+1 310 322 2265",
    "sg:postcode":"90245",
    "sg:province":"CA",
    "wof:name":"Craig's Automotive Service",
    "wof:placetype":"venue"
},
  "geometry": {"coordinates":[-118.403999,33.917],"type":"Point"}
}