{
  "type": "Feature",
  "properties": {
    "addr:full":"510 S Vermont Ave Los Angeles CA 90020",
    "addr:housenumber":"510",
    "addr:postcode":"90020",
    "addr:street":"S Vermont Ave",
    "iso:country":"US",
    "sg:address":"510 S Vermont Ave",
    "sg:city":"Los Angeles",
    "sg:classifiers":[
        {
            "category":"Organizations",
            "subcategory":"Non-profit Organization",
            "type":"Services"
        }
    ],
    "sg:phone":"+1 213 738 2243",
    "sg:postcode":"90020",
    "sg:province":"CA",
    "sg:tags":[
        "administrative",
        "program",
        "health",
        "public",
        "social"
    ],
    "wof:name":"Health Services Dept of",
    "wof:placetype":"venue"
},
  "geometry": {"coordinates":[-118.291569,34.063861],"type":"Point"}
}