{
  "type": "Feature",
  "properties": {
    "addr:full":"2805 Garnet Ave San Diego CA 92109",
    "addr:housenumber":"2805",
    "addr:postcode":"92109",
    "addr:street":"Garnet Ave",
    "iso:country":"US",
    "sg:address":"2805 Garnet Ave",
    "sg:city":"San Diego",
    "sg:classifiers":[
        {
            "category":"Food & Beverages",
            "subcategory":"Groceries & Convenience Stores",
            "type":"Retail Goods"
        }
    ],
    "sg:phone":"+1 858 273 5195",
    "sg:postcode":"92109",
    "sg:province":"CA",
    "wof:name":"7-Eleven",
    "wof:placetype":"venue"
},
  "geometry": {"coordinates":[-117.217743,32.806258],"type":"Point"}
}