{
  "type": "Feature",
  "properties": {
    "addr:full":"5217 Hollywood Blvd Suite 508 Los Angeles CA 90027",
    "addr:housenumber":"5217",
    "addr:postcode":"90027",
    "addr:street":"Hollywood Blvd Suite 508",
    "iso:country":"US",
    "sg:address":"5217 Hollywood Blvd Suite 508",
    "sg:city":"Los Angeles",
    "sg:classifiers":[
        {
            "category":"Professional",
            "subcategory":"Art Services",
            "type":"Services"
        },
        {
            "category":"Communications",
            "type":"Services"
        }
    ],
    "sg:phone":"+1 323 309 3396",
    "sg:postcode":"90027",
    "sg:province":"CA",
    "sg:tags":[
        "web",
        "graphic",
        "design"
    ],
    "sg:website":"studiofluid.com",
    "wof:name":"Studiofluid, Inc",
    "wof:placetype":"venue"
},
  "geometry": {"coordinates":[-118.304143,34.102124],"type":"Point"}
}