{
  "type": "Feature",
  "properties": {
    "iso:country":"US",
    "sg:address":"8050 W 3rd St",
    "sg:city":"Los Angeles",
    "sg:classifiers":[
        {
            "category":"Arts & Performance",
            "subcategory":"Theater",
            "type":"Entertainment"
        }
    ],
    "sg:phone":"+1 323 651 3736",
    "sg:postcode":"90048",
    "sg:province":"CA",
    "sg:tags":[
        "karaoke"
    ],
    "wof:name":"Karaoke Depot",
    "wof:placetype":"venue"
},
  "geometry": {"coordinates":[-118.365571,34.072001],"type":"Point"}
}