{
  "type": "Feature",
  "properties": {
    "iso:country":"US",
    "sg:address":"7250 Auburn Blvd",
    "sg:city":"Citrus Heights",
    "sg:classifiers":[
        {
            "category":"Professional",
            "subcategory":"Lawyer & Legal Services",
            "type":"Services"
        }
    ],
    "sg:phone":"+1 916 721 6781",
    "sg:postcode":"95610",
    "sg:province":"CA",
    "sg:tags":[
        "right",
        "way",
        "acquisition",
        "contractor"
    ],
    "wof:name":"Davis Derwin & Assoc",
    "wof:placetype":"venue"
},
  "geometry": {"coordinates":[-121.290249,38.697932],"type":"Point"}
}