{
  "type": "Feature",
  "properties": {
    "addr:full":"26171 La Paz Rd Mission Viejo CA 92691",
    "addr:housenumber":"26171",
    "addr:postcode":"92691",
    "addr:street":"La Paz Rd",
    "iso:country":"US",
    "sg:address":"26171 La Paz Rd",
    "sg:city":"Mission Viejo",
    "sg:classifiers":[
        {
            "category":"Restaurant",
            "type":"Food & Drink"
        }
    ],
    "sg:phone":"+1 949 587 1074",
    "sg:postcode":"92691",
    "sg:province":"CA",
    "wof:name":"Taco Bell",
    "wof:placetype":"venue"
},
  "geometry": {"coordinates":[-117.672529,33.600849],"type":"Point"}
}