{
  "type": "Feature",
  "properties": {
    "iso:country":"US",
    "sg:address":"11075 Santa Monica Blvd",
    "sg:city":"Los Angeles",
    "sg:classifiers":[
        {
            "category":"Organizations",
            "subcategory":"Non-profit Organization",
            "type":"Services"
        }
    ],
    "sg:phone":"+1 310 479 9330",
    "sg:postcode":"90025",
    "sg:province":"CA",
    "sg:tags":[
        "info",
        "addiction",
        "abuse",
        "treatment",
        "drug"
    ],
    "wof:name":"Friends Research Institute",
    "wof:placetype":"venue"
},
  "geometry": {"coordinates":[-118.443579,34.047953],"type":"Point"}
}