{
  "type": "Feature",
  "properties": {
    "iso:country":"US",
    "sg:address":"16603 Calahan St",
    "sg:city":"North Hills",
    "sg:classifiers":[
        {
            "category":"Retail",
            "subcategory":"Repair Shop",
            "type":"Services"
        },
        {
            "category":"Home & Garden",
            "subcategory":"Home Furnishings",
            "type":"Retail Goods"
        }
    ],
    "sg:phone":"+1 818 893 5402",
    "sg:postcode":"91343",
    "sg:province":"CA",
    "sg:tags":[
        "blind",
        "venetian",
        "trade",
        "welding",
        "contractor"
    ],
    "wof:name":"Specialty Window Coverings",
    "wof:placetype":"venue"
},
  "geometry": {"coordinates":[-118.495372,34.236746],"type":"Point"}
}