{
  "type": "Feature",
  "properties": {
    "addr:full":"1503 E Chestnut Ave Lompoc CA 93436",
    "addr:housenumber":"1503",
    "addr:postcode":"93436",
    "addr:street":"E Chestnut Ave",
    "iso:country":"US",
    "sg:address":"1503 E Chestnut Ave",
    "sg:city":"Lompoc",
    "sg:classifiers":[
        {
            "category":"Professional",
            "subcategory":"Engineering",
            "type":"Services"
        }
    ],
    "sg:phone":"+1 805 736 5744",
    "sg:postcode":"93436",
    "sg:province":"CA",
    "sg:tags":[
        "engineer"
    ],
    "wof:name":"Sobhani Engineering & Survey",
    "wof:placetype":"venue"
},
  "geometry": {"coordinates":[-120.44031,34.642169],"type":"Point"}
}