{
  "type": "Feature",
  "properties": {
    "iso:country":"US",
    "sg:address":"601 W Alvin Ave",
    "sg:city":"Santa Maria",
    "sg:classifiers":[
        {
            "category":"Education",
            "subcategory":"School",
            "type":"Public Place"
        }
    ],
    "sg:phone":"+1 805 361 6940",
    "sg:postcode":"93458",
    "sg:province":"CA",
    "sg:tags":[
        "secondary"
    ],
    "wof:name":"Robert Bruce Elementary School",
    "wof:placetype":"venue"
},
  "geometry": {"coordinates":[-120.442595,34.960568],"type":"Point"}
}