{
  "type": "Feature",
  "properties": {
    "iso:country":"US",
    "sg:address":"300 Sycamore Rd",
    "sg:city":"Arvin",
    "sg:classifiers":[
        {
            "category":"Building & Trades",
            "subcategory":"Plumbing",
            "type":"Services"
        }
    ],
    "sg:phone":"+1 661 854 6690",
    "sg:postcode":"93203",
    "sg:province":"CA",
    "sg:tags":[
        "conditioning",
        "air",
        "system",
        "contractor"
    ],
    "wof:name":"Absolute Chiller Svc",
    "wof:placetype":"venue"
},
  "geometry": {"coordinates":[-118.806074,35.194623],"type":"Point"}
}