{
  "type": "Feature",
  "properties": {
    "addr:full":"2645 Dalemead St Torrance CA 90505",
    "addr:housenumber":"2645",
    "addr:postcode":"90505",
    "addr:street":"Dalemead St",
    "iso:country":"US",
    "sg:address":"2645 Dalemead St",
    "sg:city":"Torrance",
    "sg:classifiers":[
        {
            "category":"Freight",
            "type":"Transportation"
        }
    ],
    "sg:phone":"+1 310 534 1222",
    "sg:postcode":"90505",
    "sg:province":"CA",
    "sg:tags":[
        "arrangement"
    ],
    "wof:name":"Seaborne International Inc",
    "wof:placetype":"venue"
},
  "geometry": {"coordinates":[-118.331686,33.788265],"type":"Point"}
}