{
  "type": "Feature",
  "properties": {
    "addr:full":"330 W Felicita Ave Escondido CA 92025",
    "addr:housenumber":"330",
    "addr:postcode":"92025",
    "addr:street":"W Felicita Ave",
    "iso:country":"US",
    "sg:address":"330 W Felicita Ave",
    "sg:city":"Escondido",
    "sg:classifiers":[
        {
            "category":"Professional",
            "subcategory":"Detective & Security Services",
            "type":"Services"
        }
    ],
    "sg:phone":"+1 760 746 7792",
    "sg:postcode":"92025",
    "sg:province":"CA",
    "sg:tags":[
        "guard",
        "patrol"
    ],
    "wof:name":"Securitas",
    "wof:placetype":"venue"
},
  "geometry": {"coordinates":[-117.07469500000001,33.103925],"type":"Point"}
}