{
  "type": "Feature",
  "properties": {
    "addr:full":"42335 50th St W Quartz Hill CA 93536",
    "addr:housenumber":"42335",
    "addr:postcode":"93536",
    "addr:street":"50Th St W Quartz Hill",
    "iso:country":"US",
    "sg:address":"42335 50th St W",
    "sg:city":"Quartz Hill",
    "sg:classifiers":[
        {
            "category":"Building & Trades",
            "subcategory":"Construction",
            "type":"Services"
        }
    ],
    "sg:phone":"+1 661 718 2360",
    "sg:postcode":"93536",
    "sg:province":"CA",
    "sg:tags":[
        "contractor"
    ],
    "wof:name":"Smart Uniques Svc Corp",
    "wof:placetype":"venue"
},
  "geometry": {"coordinates":[-118.218666,34.651725],"type":"Point"}
}