{
  "type": "Feature",
  "properties": {
    "addr:full":"16323 Tulsa St Granada Hills CA 91344",
    "addr:housenumber":"16323",
    "addr:postcode":"91344",
    "addr:street":"Tulsa St",
    "iso:country":"US",
    "sg:address":"16323 Tulsa St",
    "sg:city":"Granada Hills",
    "sg:classifiers":[
        {
            "category":"Shopping",
            "subcategory":"Gifts & Souvenirs",
            "type":"Retail Goods"
        }
    ],
    "sg:phone":"+1 818 363 0661",
    "sg:postcode":"91344",
    "sg:province":"CA",
    "wof:name":"Daves Cards",
    "wof:placetype":"venue"
},
  "geometry": {"coordinates":[-118.488919,34.268037],"type":"Point"}
}