{
  "type": "Feature",
  "properties": {
    "addr:full":"2648 Mohawk St Santa Rosa CA 95403",
    "addr:housenumber":"2648",
    "addr:postcode":"ca 95403",
    "addr:street":"Mohawk St",
    "iso:country":"US",
    "sg:address":"2648 Mohawk St",
    "sg:city":"Santa Rosa",
    "sg:classifiers":[
        {
            "category":"Utilities",
            "subcategory":"Refuse",
            "type":"Services"
        }
    ],
    "sg:phone":"+1 707 527 8788",
    "sg:postcode":"95403",
    "sg:province":"CA",
    "sg:tags":[
        "sanitation"
    ],
    "wof:name":"Bdk Septic Svc",
    "wof:placetype":"venue"
},
  "geometry": {"coordinates":[-122.7457,38.462025],"type":"Point"}
}