{
  "type": "Feature",
  "properties": {
    "iso:country":"US",
    "sg:address":"1681 The Alameda",
    "sg:city":"San Jose",
    "sg:classifiers":[
        {
            "category":"Professional",
            "subcategory":"Lawyer & Legal Services",
            "type":"Services"
        }
    ],
    "sg:phone":"+1 408 279 3300",
    "sg:postcode":"95126",
    "sg:province":"CA",
    "sg:tags":[
        "attorney"
    ],
    "wof:name":"Laura Kyriazis Law Office",
    "wof:placetype":"venue"
},
  "geometry": {"coordinates":[-121.91914800000001,37.337378],"type":"Point"}
}