{
  "type": "Feature",
  "properties": {
    "addr:full":"4325 Moorpark Avenue San Jose CA 95129",
    "addr:housenumber":"4325",
    "addr:postcode":"95129",
    "addr:street":"Moorpark Avenue",
    "iso:country":"US",
    "sg:address":"4325 Moorpark Avenue",
    "sg:city":"San Jose",
    "sg:classifiers":[
        {
            "category":"Health Services",
            "subcategory":"Health Practitioner",
            "type":"Services"
        }
    ],
    "sg:phone":"+1 408 255 9588",
    "sg:postcode":"95129",
    "sg:province":"CA",
    "sg:tags":[
        "acupuncture"
    ],
    "wof:name":"Zhao Patrick Acupuncture Clinic",
    "wof:placetype":"venue"
},
  "geometry": {"coordinates":[-121.97837,37.315903],"type":"Point"}
}