{
  "type": "Feature",
  "properties": {
    "iso:country":"US",
    "sg:address":"3095 Kerner Blvd",
    "sg:city":"San Rafael",
    "sg:classifiers":[
        {
            "category":"Education",
            "subcategory":"Vocational School",
            "type":"Public Place"
        }
    ],
    "sg:phone":"+1 415 456 7388",
    "sg:postcode":"94901",
    "sg:province":"CA",
    "sg:tags":[
        "training",
        "computer"
    ],
    "wof:name":"EAH Software Training",
    "wof:placetype":"venue"
},
  "geometry": {"coordinates":[-122.498322,37.955554],"type":"Point"}
}