{
  "type": "Feature",
  "properties": {
    "addr:full":"4215 Norwood Ave Sacramento CA 95838",
    "addr:housenumber":"4215",
    "addr:postcode":"95838",
    "addr:street":"Norwood Ave",
    "iso:country":"US",
    "sg:address":"4215 Norwood Ave",
    "sg:city":"Sacramento",
    "sg:classifiers":[
        {
            "category":"Banks & Credit Unions",
            "subcategory":"Bank",
            "type":"Services"
        }
    ],
    "sg:phone":"+1 916 646 9794",
    "sg:postcode":"95838",
    "sg:province":"CA",
    "sg:tags":[
        "cashing",
        "personal",
        "check",
        "institution"
    ],
    "wof:name":"Advance America",
    "wof:placetype":"venue"
},
  "geometry": {"coordinates":[-121.456973,38.646315],"type":"Point"}
}