{
  "type": "Feature",
  "properties": {
    "iso:country":"US",
    "sg:address":"4225 Prado Rd",
    "sg:city":"Corona",
    "sg:classifiers":[
        {
            "category":"Professional",
            "subcategory":"Business Services",
            "type":"Services"
        }
    ],
    "sg:phone":"+1 951 808 1992",
    "sg:postcode":"92880",
    "sg:province":"CA",
    "sg:tags":[
        "water",
        "treatment"
    ],
    "sg:website":"www.sun-pure.com",
    "wof:name":"Ultra Sun Technologies Inc",
    "wof:placetype":"venue"
},
  "geometry": {"coordinates":[-117.650634,33.881667],"type":"Point"}
}