{
  "type": "Feature",
  "properties": {
    "addr:full":"17900 Sky Park Cir Irvine CA 92614",
    "addr:housenumber":"17900",
    "addr:postcode":"92614",
    "addr:street":"Sky Park Cir",
    "iso:country":"US",
    "sg:address":"17900 Sky Park Cir",
    "sg:city":"Irvine",
    "sg:classifiers":[
        {
            "category":"Professional",
            "subcategory":"Computer Services",
            "type":"Services"
        }
    ],
    "sg:phone":"+1 949 261 1700",
    "sg:postcode":"92614",
    "sg:province":"CA",
    "sg:tags":[
        "consulting",
        "software"
    ],
    "wof:name":"Softmine Corporation",
    "wof:placetype":"venue"
},
  "geometry": {"coordinates":[-117.86067,33.690843],"type":"Point"}
}