{
  "type": "Feature",
  "properties": {
    "addr:full":"1450 Frazee Rd Suite #101 San Diego CA 92123",
    "addr:housenumber":"1450",
    "addr:postcode":"92123",
    "addr:street":"Frazee Rd Suite # 101",
    "iso:country":"US",
    "sg:address":"1450 Frazee Rd Suite #101",
    "sg:city":"San Diego",
    "sg:classifiers":[
        {
            "category":"Personal",
            "subcategory":"Beauty Salon",
            "type":"Services"
        }
    ],
    "sg:phone":"+1 619 471 4835",
    "sg:postcode":"92123",
    "sg:province":"CA",
    "sg:tags":[
        "hair"
    ],
    "sg:website":"www.HennasHairStudio.com",
    "wof:name":"Henna's Hair Studio",
    "wof:placetype":"venue"
},
  "geometry": {"coordinates":[-117.15926899999999,32.773326],"type":"Point"}
}