{
  "type": "Feature",
  "properties": {
    "addr:full":"Smashbox Studios 1011 North Fuller Ave West Hollywood CA 90046",
    "addr:housenumber":"1011",
    "addr:postcode":"90046",
    "addr:street":"North Fuller Ave",
    "iso:country":"US",
    "sg:address":"Smashbox Studios 1011 North Fuller Ave",
    "sg:city":"West Hollywood",
    "sg:classifiers":[
        {
            "category":"Education",
            "subcategory":"Special Training",
            "type":"Public Place"
        }
    ],
    "sg:phone":"+1 323 938 9703",
    "sg:postcode":"90046",
    "sg:province":"CA",
    "sg:tags":[
        "school",
        "specialty"
    ],
    "sg:website":"www.theschoolofstyle.com",
    "wof:name":"School of Style",
    "wof:placetype":"venue"
},
  "geometry": {"coordinates":[-118.35024300000001,34.089323],"type":"Point"}
}