{
  "type": "Feature",
  "properties": {
    "addr:full":"1757 W Carson St Ste L Torrance CA 90501",
    "addr:housenumber":"1757",
    "addr:postcode":"90501",
    "addr:street":"W Carson St Ste L Torrance",
    "iso:country":"US",
    "sg:address":"1757 W Carson St Ste L",
    "sg:city":"Torrance",
    "sg:classifiers":[
        {
            "category":"Restaurant",
            "type":"Food & Drink"
        }
    ],
    "sg:phone":"+1 310 320 5511",
    "sg:postcode":"90501",
    "sg:province":"CA",
    "sg:tags":[
        "sushi",
        "bar",
        "japanese"
    ],
    "sg:website":"www.sushinozomi.com",
    "wof:name":"Nozomi",
    "wof:placetype":"venue"
},
  "geometry": {"coordinates":[-118.3111,33.831433],"type":"Point"}
}