{
  "type": "Feature",
  "properties": {
    "addr:full":"1000 Town Center Dr Oxnard CA 93036",
    "addr:housenumber":"1000",
    "addr:postcode":"93036",
    "addr:street":"Town Center Dr",
    "iso:country":"US",
    "sg:address":"1000 Town Center Dr",
    "sg:city":"Oxnard",
    "sg:classifiers":[
        {
            "category":"Professional",
            "type":"Services"
        }
    ],
    "sg:phone":"+1 805 981 1380",
    "sg:postcode":"93036",
    "sg:province":"CA",
    "sg:tags":[
        "establishment"
    ],
    "wof:name":"Costello Ed III",
    "wof:placetype":"venue"
},
  "geometry": {"coordinates":[-119.182973,34.242698],"type":"Point"}
}