{
  "type": "Feature",
  "properties": {
    "iso:country":"US",
    "sg:address":"15035 Ventura Blvd",
    "sg:city":"Sherman Oaks",
    "sg:classifiers":[
        {
            "category":"Shopping",
            "type":"Retail Goods"
        }
    ],
    "sg:phone":"+1 818 788 7777",
    "sg:postcode":"91403",
    "sg:province":"CA",
    "sg:tags":[
        "communication",
        "radiotelephone",
        "merchandise"
    ],
    "wof:name":"1 Hotcell",
    "wof:placetype":"venue"
},
  "geometry": {"coordinates":[-118.461033,34.153015],"type":"Point"}
}