{
  "type": "Feature",
  "properties": {
    "iso:country":"US",
    "sg:address":"3321 Foothill Blvd",
    "sg:city":"Oakland",
    "sg:classifiers":[
        {
            "category":"Food & Beverages",
            "subcategory":"Groceries & Convenience Stores",
            "type":"Retail Goods"
        }
    ],
    "sg:phone":"+1 510 533 3888",
    "sg:postcode":"94601",
    "sg:province":"CA",
    "sg:tags":[
        "grocer"
    ],
    "wof:name":"East Bay Market",
    "wof:placetype":"venue"
},
  "geometry": {"coordinates":[-122.22168000000001,37.783344],"type":"Point"}
}