{
  "type": "Feature",
  "properties": {
    "addr:full":"180 W Rincon Ave Campbell CA 95008",
    "addr:housenumber":"180",
    "addr:postcode":"95008",
    "addr:street":"W Rincon Ave",
    "iso:country":"US",
    "sg:address":"180 W Rincon Ave",
    "sg:city":"Campbell",
    "sg:classifiers":[
        {
            "category":"Shopping",
            "type":"Retail Goods"
        }
    ],
    "sg:phone":"+1 408 866 6859",
    "sg:postcode":"95008",
    "sg:province":"CA",
    "sg:tags":[
        "merchandise"
    ],
    "wof:name":"Adept Business Services",
    "wof:placetype":"venue"
},
  "geometry": {"coordinates":[-121.952574,37.284794],"type":"Point"}
}