{
  "type": "Feature",
  "properties": {
    "iso:country":"US",
    "sg:address":"2700 E Slauson Avenue",
    "sg:city":"Huntington Park",
    "sg:classifiers":[
        {
            "category":"Health Services",
            "subcategory":"Doctor",
            "type":"Services"
        },
        {
            "category":"Health Services",
            "subcategory":"Hospital",
            "type":"Services"
        }
    ],
    "sg:phone":"+1 323 588 8558",
    "sg:postcode":"90255",
    "sg:province":"CA",
    "wof:name":"St Francis Medical Clinics",
    "wof:placetype":"venue"
},
  "geometry": {"coordinates":[-118.222679,33.989179],"type":"Point"}
}