{
  "type": "Feature",
  "properties": {
    "addr:full":"5350 Hollister Ave Santa Barbara CA 93111",
    "addr:housenumber":"5350",
    "addr:postcode":"93111",
    "addr:street":"Hollister Ave",
    "iso:country":"US",
    "sg:address":"5350 Hollister Ave",
    "sg:city":"Santa Barbara",
    "sg:classifiers":[
        {
            "category":"Organizations",
            "subcategory":"Labor Organization",
            "type":"Services"
        }
    ],
    "sg:phone":"+1 805 683 0552",
    "sg:postcode":"93111",
    "sg:province":"CA",
    "wof:name":"Construction & General Lbrrs",
    "wof:placetype":"venue"
},
  "geometry": {"coordinates":[-119.809133,34.435057],"type":"Point"}
}