{
  "type": "Feature",
  "properties": {
    "addr:full":"529 Market St San Diego CA 92101",
    "addr:housenumber":"529",
    "addr:postcode":"92101",
    "addr:street":"Market St",
    "iso:country":"US",
    "sg:address":"529 Market St",
    "sg:city":"San Diego",
    "sg:classifiers":[
        {
            "category":"Manufacturing",
            "subcategory":"Printing",
            "type":"Manufacturing & Wholesale Goods"
        }
    ],
    "sg:phone":"+1 619 985 9552",
    "sg:postcode":"92101",
    "sg:province":"CA",
    "sg:tags":[
        "newspaper"
    ],
    "wof:name":"Gaslamp Weekly",
    "wof:placetype":"venue"
},
  "geometry": {"coordinates":[-117.159457,32.711422],"type":"Point"}
}