{
  "type": "Feature",
  "properties": {
    "iso:country":"US",
    "sg:address":"6747 Odessa Ave",
    "sg:city":"Van Nuys",
    "sg:classifiers":[
        {
            "category":"Home & Garden",
            "subcategory":"Household Appliances",
            "type":"Retail Goods"
        },
        {
            "category":"Retail",
            "subcategory":"Repair Shop",
            "type":"Services"
        }
    ],
    "sg:phone":"+1 818 994 1101",
    "sg:postcode":"91406",
    "sg:province":"CA",
    "sg:tags":[
        "refrigeration",
        "electrical"
    ],
    "wof:name":"Airflow Appliance Inc",
    "wof:placetype":"venue"
},
  "geometry": {"coordinates":[-118.490274,34.191223],"type":"Point"}
}