{
  "type": "Feature",
  "properties": {
    "iso:country":"US",
    "sg:address":"540 Jacqueline Dr",
    "sg:city":"Santa Rosa",
    "sg:classifiers":[
        {
            "category":"Shopping",
            "subcategory":"Gifts & Souvenirs",
            "type":"Retail Goods"
        }
    ],
    "sg:phone":"+1 707 526 3777",
    "sg:postcode":"95405",
    "sg:province":"CA",
    "sg:tags":[
        "shop"
    ],
    "wof:name":"Minds Eye",
    "wof:placetype":"venue"
},
  "geometry": {"coordinates":[-122.673299,38.448792],"type":"Point"}
}