{
  "type": "Feature",
  "properties": {
    "addr:full":"1005 12th St Ste 4 Sacramento CA 95814",
    "addr:housenumber":"1005",
    "addr:postcode":"95814",
    "addr:street":"12Th St Ste 4",
    "iso:country":"US",
    "sg:address":"1005 12th St Ste 4",
    "sg:city":"Sacramento",
    "sg:classifiers":[
        {
            "category":"Organizations",
            "subcategory":"Labor Organization",
            "type":"Services"
        }
    ],
    "sg:phone":"+1 916 441 2051",
    "sg:postcode":"95814",
    "sg:province":"CA",
    "sg:website":"http://www.utu.org",
    "wof:name":"United Transportation Union",
    "wof:placetype":"venue"
},
  "geometry": {"coordinates":[-121.490803,38.579575],"type":"Point"}
}