{
  "type": "Feature",
  "properties": {
    "addr:full":"2606 S Railroad Ave Fresno CA 93725",
    "addr:housenumber":"2606",
    "addr:postcode":"93725",
    "addr:street":"S Railroad Ave",
    "iso:country":"US",
    "sg:address":"2606 S Railroad Ave",
    "sg:city":"Fresno",
    "sg:classifiers":[
        {
            "category":"Government",
            "subcategory":"Department Of Motor Vehicles",
            "type":"Public Place"
        },
        {
            "category":"Retail",
            "subcategory":"Auto Repair",
            "type":"Services"
        }
    ],
    "sg:phone":"+1 559 233 8444",
    "sg:postcode":"93725",
    "sg:province":"CA",
    "sg:tags":[
        "truck",
        "trailers-repair",
        "trailer"
    ],
    "sg:website":"http://www.cvtrtrailers.com",
    "wof:name":"Central Valley Trailer Repair",
    "wof:placetype":"venue"
},
  "geometry": {"coordinates":[-119.765821,36.706694],"type":"Point"}
}