{
  "type": "Feature",
  "properties": {
    "addr:full":"128 E Katella Ave Orange CA 92867",
    "addr:housenumber":"128",
    "addr:postcode":"92867",
    "addr:street":"E Katella Ave",
    "iso:country":"US",
    "sg:address":"128 E Katella Ave",
    "sg:city":"Orange",
    "sg:classifiers":[
        {
            "category":"Wholesale",
            "subcategory":"Drugs",
            "type":"Manufacturing & Wholesale Goods"
        }
    ],
    "sg:phone":"+1 714 288 1106",
    "sg:postcode":"92867",
    "sg:province":"CA",
    "sg:tags":[
        "cosmetic"
    ],
    "wof:name":"Ati Professional Svc",
    "wof:placetype":"venue"
},
  "geometry": {"coordinates":[-117.849011,33.809038],"type":"Point"}
}