{
  "type": "Feature",
  "properties": {
    "iso:country":"US",
    "sg:address":"101 S Electric Ave",
    "sg:city":"Alhambra",
    "sg:classifiers":[
        {
            "category":"Shopping",
            "subcategory":"Clothing, Apparel, & Fashions",
            "type":"Retail Goods"
        }
    ],
    "sg:phone":"+1 626 282 6010",
    "sg:postcode":"91801",
    "sg:province":"CA",
    "wof:name":"Most Wanted Bags",
    "wof:placetype":"venue"
},
  "geometry": {"coordinates":[-118.139634,34.091367],"type":"Point"}
}