{
  "type": "Feature",
  "properties": {
    "addr:full":"2128 N Glenoaks Blvd 105 Burbank CA 91504",
    "addr:housenumber":"2128;105",
    "addr:postcode":"91504",
    "addr:street":"N Glenoaks Blvd",
    "iso:country":"US",
    "sg:address":"2128 N Glenoaks Blvd 105",
    "sg:city":"Burbank",
    "sg:classifiers":[
        {
            "category":"Food & Beverages",
            "subcategory":"Bakery",
            "type":"Retail Goods"
        }
    ],
    "sg:phone":"+1 818 848 3386",
    "sg:postcode":"91504",
    "sg:province":"CA",
    "sg:tags":[
        "sandwich"
    ],
    "wof:name":"Subway",
    "wof:placetype":"venue"
},
  "geometry": {"coordinates":[-118.326684,34.198626],"type":"Point"}
}