{
  "type": "Feature",
  "properties": {
    "iso:country":"US",
    "sg:address":"2545 W 237th St",
    "sg:city":"Torrance",
    "sg:classifiers":[
        {
            "category":"Building & Trades",
            "subcategory":"Landscaping Services",
            "type":"Services"
        }
    ],
    "sg:phone":"+1 310 534 4070",
    "sg:postcode":"90505",
    "sg:province":"CA",
    "wof:name":"Pacific N S P",
    "wof:placetype":"venue"
},
  "geometry": {"coordinates":[-118.33000199999999,33.810501],"type":"Point"}
}