{
  "type": "Feature",
  "properties": {
    "addr:full":"500 E McGlincy Lane Campbell CA 95008",
    "addr:housenumber":"500",
    "addr:postcode":"95008",
    "addr:street":"E Mcglincy Lane",
    "iso:country":"US",
    "sg:address":"500 E McGlincy Lane",
    "sg:city":"Campbell",
    "sg:classifiers":[
        {
            "category":"Arts & Performance",
            "subcategory":"Arts Center",
            "type":"Entertainment"
        }
    ],
    "sg:phone":"+1 408 371 7379",
    "sg:postcode":"95008",
    "sg:province":"CA",
    "sg:tags":[
        "performing"
    ],
    "wof:name":"West Valley Light Opera Association",
    "wof:placetype":"venue"
},
  "geometry": {"coordinates":[-121.94175,37.277204],"type":"Point"}
}