{
  "type": "Feature",
  "properties": {
    "addr:full":"5442 Kohler Ave Apt 44 Sacramento CA 95841",
    "addr:housenumber":"5442;44",
    "addr:postcode":"95841",
    "addr:street":"Kohler Ave Apt",
    "iso:country":"US",
    "sg:address":"5442 Kohler Ave Apt 44",
    "sg:city":"Sacramento",
    "sg:classifiers":[
        {
            "category":"Professional",
            "subcategory":"Research",
            "type":"Services"
        }
    ],
    "sg:phone":"+1 916 334 5005",
    "sg:postcode":"95841",
    "sg:province":"CA",
    "sg:tags":[
        "development",
        "electronics",
        "technology-research"
    ],
    "wof:name":"Idea",
    "wof:placetype":"venue"
},
  "geometry": {"coordinates":[-121.344899,38.665209],"type":"Point"}
}