{
  "type": "Feature",
  "properties": {
    "addr:full":"65 Westfield Ave Daly City CA 94015",
    "addr:housenumber":"65",
    "addr:postcode":"94015",
    "addr:street":"Westfield Ave",
    "iso:country":"US",
    "sg:address":"65 Westfield Ave",
    "sg:city":"Daly City",
    "sg:classifiers":[
        {
            "category":"Real Estate",
            "subcategory":"Real Estate Agent",
            "type":"Services"
        }
    ],
    "sg:phone":"+1 650 994 3150",
    "sg:postcode":"94015",
    "sg:province":"CA",
    "wof:name":"Henry Trim Realty",
    "wof:placetype":"venue"
},
  "geometry": {"coordinates":[-122.487189,37.687161],"type":"Point"}
}