{
  "type": "Feature",
  "properties": {
    "iso:country":"US",
    "sg:address":"3612 Highland Ave",
    "sg:city":"Manhattan Beach",
    "sg:classifiers":[
        {
            "category":"Home & Garden",
            "subcategory":"Furniture",
            "type":"Retail Goods"
        }
    ],
    "sg:phone":"+1 310 545 4634",
    "sg:postcode":"90266",
    "sg:province":"CA",
    "sg:tags":[
        "store"
    ],
    "wof:name":"Casa Bella",
    "wof:placetype":"venue"
},
  "geometry": {"coordinates":[-118.417999,33.9006],"type":"Point"}
}