{
  "type": "Feature",
  "properties": {
    "iso:country":"US",
    "sg:address":"3888 Grove Ave",
    "sg:city":"Palo Alto",
    "sg:classifiers":[
        {
            "category":"Shopping",
            "subcategory":"Clothing, Apparel, & Fashions",
            "type":"Retail Goods"
        }
    ],
    "sg:phone":"+1 650 493 4908",
    "sg:postcode":"94303",
    "sg:province":"CA",
    "sg:tags":[
        "baby",
        "accessory"
    ],
    "wof:name":"Larry's Baby Safety Svc",
    "wof:placetype":"venue"
},
  "geometry": {"coordinates":[-122.109359,37.422559],"type":"Point"}
}