{
  "type": "Feature",
  "properties": {
    "iso:country":"US",
    "sg:address":"1631 Maria St",
    "sg:city":"Burbank",
    "sg:classifiers":[
        {
            "category":"Professional",
            "type":"Services"
        }
    ],
    "sg:phone":"+1 818 565 0125",
    "sg:postcode":"91504",
    "sg:province":"CA",
    "wof:name":"Armenian TV of Los Angeles",
    "wof:placetype":"venue"
},
  "geometry": {"coordinates":[-118.33210200000001,34.193178],"type":"Point"}
}