{
  "type": "Feature",
  "properties": {
    "iso:country":"US",
    "sg:address":"7007 Friars Rd",
    "sg:city":"San Diego",
    "sg:classifiers":[
        {
            "category":"Shopping",
            "subcategory":"Clothing, Apparel, & Fashions",
            "type":"Retail Goods"
        }
    ],
    "sg:phone":"+1 619 295 7291",
    "sg:postcode":"92101",
    "sg:province":"CA",
    "sg:tags":[
        "children's",
        "infant",
        "clothing",
        "wear"
    ],
    "sg:website":"www.childrensplace.com",
    "wof:name":"The Children's Place",
    "wof:placetype":"venue"
},
  "geometry": {"coordinates":[-117.16936,32.769451],"type":"Point"}
}