{
  "type": "Feature",
  "properties": {
    "addr:full":"2269 E Colorado Blvd Frnt Pasadena CA 91107",
    "addr:housenumber":"2269",
    "addr:postcode":"91107",
    "addr:street":"E Colorado Blvd",
    "iso:country":"US",
    "sg:address":"2269 E Colorado Blvd Frnt",
    "sg:city":"Pasadena",
    "sg:classifiers":[
        {
            "category":"Professional",
            "type":"Services"
        }
    ],
    "sg:phone":"+1 626 577 2521",
    "sg:postcode":"91107",
    "sg:province":"CA",
    "sg:tags":[
        "caterer"
    ],
    "wof:name":"Simply Perfect Catering",
    "wof:placetype":"venue"
},
  "geometry": {"coordinates":[-118.103996,34.146099],"type":"Point"}
}