{
  "type": "Feature",
  "properties": {
    "iso:country":"US",
    "sg:address":"1710 22nd St",
    "sg:city":"Santa Monica",
    "sg:classifiers":[
        {
            "category":"Social Services",
            "type":"Services"
        }
    ],
    "sg:phone":"+1 310 828 6016",
    "sg:postcode":"90404",
    "sg:province":"CA",
    "sg:tags":[
        "organization",
        "welfare"
    ],
    "wof:name":"West Side Food Bank",
    "wof:placetype":"venue"
},
  "geometry": {"coordinates":[-118.47175799999999,34.024568],"type":"Point"}
}