{
  "type": "Feature",
  "properties": {
    "iso:country":"US",
    "sg:address":"931 Hartz Way Ste 100",
    "sg:city":"Danville",
    "sg:classifiers":[
        {
            "category":"Insurance",
            "subcategory":"Insurance Agent",
            "type":"Services"
        },
        {
            "category":"Insurance",
            "subcategory":"Hazard Insurance",
            "type":"Services"
        },
        {
            "category":"Insurance",
            "subcategory":"Title Insurance",
            "type":"Services"
        },
        {
            "category":"Insurance",
            "subcategory":"Life Insurance",
            "type":"Services"
        }
    ],
    "sg:phone":"+1 925 552 0744",
    "sg:postcode":"94526",
    "sg:province":"CA",
    "sg:tags":[
        "auto",
        "commercial",
        "business",
        "homeowner"
    ],
    "sg:website":"http://www.farmersagent.com/kmoody1/",
    "wof:name":"Karen Moody - Farmers Insurance",
    "wof:placetype":"venue"
},
  "geometry": {"coordinates":[-121.99401899999999,37.819328],"type":"Point"}
}