{
  "type": "Feature",
  "properties": {
    "addr:full":"961 Garcia Ave Pittsburg CA 94565",
    "addr:housenumber":"961",
    "addr:postcode":"94565",
    "addr:street":"Garcia Ave",
    "iso:country":"US",
    "sg:address":"961 Garcia Ave",
    "sg:city":"Pittsburg",
    "sg:classifiers":[
        {
            "category":"Shopping",
            "type":"Retail Goods"
        }
    ],
    "sg:phone":"+1 925 427 3198",
    "sg:postcode":"94565",
    "sg:province":"CA",
    "sg:tags":[
        "monument"
    ],
    "wof:name":"Higgins Headstones & Memorials",
    "wof:placetype":"venue"
},
  "geometry": {"coordinates":[-121.875404,38.010728],"type":"Point"}
}