{
  "type": "Feature",
  "properties": {
    "addr:full":"1204 Taylor Ave Vallejo CA 94591",
    "addr:housenumber":"1204",
    "addr:postcode":"94591",
    "addr:street":"Taylor Ave",
    "iso:country":"US",
    "sg:address":"1204 Taylor Ave",
    "sg:city":"Vallejo",
    "sg:classifiers":[
        {
            "category":"Building & Trades",
            "subcategory":"Plumbing",
            "type":"Services"
        },
        {
            "category":"Building & Trades",
            "subcategory":"Construction",
            "type":"Services"
        }
    ],
    "sg:phone":"+1 707 643 9433",
    "sg:postcode":"94591",
    "sg:province":"CA",
    "sg:tags":[
        "plumber",
        "industrial",
        "radiators-heating",
        "supply",
        "sales",
        "contractors-commercial"
    ],
    "wof:name":"House Doctor's Plumbing Service",
    "wof:placetype":"venue"
},
  "geometry": {"coordinates":[-122.21583200000001,38.088886],"type":"Point"}
}