{
  "type": "Feature",
  "properties": {
    "addr:full":"2282 Orchard Dr Newport Beach CA 92660",
    "addr:housenumber":"2282",
    "addr:postcode":"92660",
    "addr:street":"Orchard Dr",
    "iso:country":"US",
    "sg:address":"2282 Orchard Dr",
    "sg:city":"Newport Beach",
    "sg:classifiers":[
        {
            "category":"Building & Trades",
            "subcategory":"Plumbing",
            "type":"Services"
        }
    ],
    "sg:phone":"+1 949 756 0064",
    "sg:postcode":"92660",
    "sg:province":"CA",
    "sg:tags":[
        "conditioning",
        "air",
        "system",
        "contractor"
    ],
    "wof:name":"ABC Heating & Air Cond Co",
    "wof:placetype":"venue"
},
  "geometry": {"coordinates":[-117.873953,33.656138],"type":"Point"}
}