{
  "type": "Feature",
  "properties": {
    "addr:full":"220 Montgomery St Ste 305 San Francisco CA 94104",
    "addr:housenumber":"220",
    "addr:postcode":"94104",
    "addr:street":"Montgomery St Ste 305",
    "iso:country":"US",
    "sg:address":"220 Montgomery St Ste 305",
    "sg:city":"San Francisco",
    "sg:classifiers":[
        {
            "category":"Health Services",
            "subcategory":"Health Practitioner",
            "type":"Services"
        }
    ],
    "sg:phone":"+1 415 677 9900",
    "sg:postcode":"94104",
    "sg:province":"CA",
    "sg:tags":[
        "acupuncture"
    ],
    "sg:website":"www.consciouschiro.com/",
    "wof:name":"Traci Kanzawa, LAc",
    "wof:placetype":"venue"
},
  "geometry": {"coordinates":[-122.401994,37.791316],"type":"Point"}
}