{
  "type": "Feature",
  "properties": {
    "iso:country":"US",
    "sg:address":"1160 Industrial Rd",
    "sg:city":"San Carlos",
    "sg:classifiers":[
        {
            "category":"Wholesale",
            "subcategory":"Electrical",
            "type":"Manufacturing & Wholesale Goods"
        }
    ],
    "sg:phone":"+1 650 592 4806",
    "sg:postcode":"94070",
    "sg:province":"CA",
    "sg:tags":[
        "equipment",
        "electric",
        "supply"
    ],
    "sg:website":"www.controldesignsupplyinc.com",
    "wof:name":"Control Design Supply Corp",
    "wof:placetype":"venue"
},
  "geometry": {"coordinates":[-122.246919,37.502129],"type":"Point"}
}