{
  "type": "Feature",
  "properties": {
    "iso:country":"US",
    "sg:address":"309 East Hillcrest Blvd",
    "sg:city":"Inglewood",
    "sg:classifiers":[
        {
            "category":"Building & Trades",
            "subcategory":"Pest Control",
            "type":"Services"
        }
    ],
    "sg:phone":"+1 310 658 7871",
    "sg:postcode":"90301",
    "sg:province":"CA",
    "wof:name":"Ultimate Pest Eliminator",
    "wof:placetype":"venue"
},
  "geometry": {"coordinates":[-118.351299,33.959894],"type":"Point"}
}