{
  "type": "Feature",
  "properties": {
    "addr:full":"508 W 39th St San Pedro CA 90731",
    "addr:housenumber":"508",
    "addr:postcode":"90731",
    "addr:street":"W 39Th St",
    "iso:country":"US",
    "sg:address":"508 W 39th St",
    "sg:city":"San Pedro",
    "sg:classifiers":[
        {
            "category":"Restaurant",
            "type":"Food & Drink"
        }
    ],
    "sg:phone":"+1 310 548 3354",
    "sg:postcode":"90731",
    "sg:province":"CA",
    "sg:tags":[
        "delicatessen"
    ],
    "wof:name":"Lighthouse Deli",
    "wof:placetype":"venue"
},
  "geometry": {"coordinates":[-118.28846900000001,33.708823],"type":"Point"}
}