{
  "type": "Feature",
  "properties": {
    "addr:full":"801 K Street Suite 110 Sacramento CA 95814",
    "addr:housenumber":"801",
    "addr:postcode":"95814",
    "addr:street":"K Street Suite 110",
    "iso:country":"US",
    "sg:address":"801 K Street Suite 110",
    "sg:city":"Sacramento",
    "sg:classifiers":[
        {
            "category":"Banks & Credit Unions",
            "subcategory":"Bank",
            "type":"Services"
        },
        {
            "category":"Banks & Credit Unions",
            "subcategory":"Financial Services",
            "type":"Services"
        }
    ],
    "sg:phone":"+1 916 326 4500",
    "sg:postcode":"95814",
    "sg:province":"CA",
    "sg:tags":[
        "broker",
        "mortgage"
    ],
    "wof:name":"Washington Mutual",
    "wof:placetype":"venue"
},
  "geometry": {"coordinates":[-121.496606,38.579925],"type":"Point"}
}