{
  "type": "Feature",
  "properties": {
    "iso:country":"US",
    "sg:address":"169 Cohasset Rd",
    "sg:city":"Chico",
    "sg:classifiers":[
        {
            "category":"Insurance",
            "subcategory":"Insurance Agent",
            "type":"Services"
        }
    ],
    "sg:phone":"+1 530 893 9581",
    "sg:postcode":"95926",
    "sg:province":"CA",
    "wof:name":"Cuesta Insurance Svc",
    "wof:placetype":"venue"
},
  "geometry": {"coordinates":[-121.854416,39.751014],"type":"Point"}
}