{
  "type": "Feature",
  "properties": {
    "iso:country":"US",
    "sg:address":"305 E 9th St",
    "sg:city":"Los Angeles",
    "sg:classifiers":[
        {
            "category":"Wholesale",
            "subcategory":"Apparel",
            "type":"Manufacturing & Wholesale Goods"
        }
    ],
    "sg:phone":"+1 213 623 7675",
    "sg:postcode":"90015",
    "sg:province":"CA",
    "sg:tags":[
        "clothing"
    ],
    "wof:name":"Gallery 2000 Corporation",
    "wof:placetype":"venue"
},
  "geometry": {"coordinates":[-118.25267599999999,34.039548],"type":"Point"}
}