{
  "type": "Feature",
  "properties": {
    "iso:country":"US",
    "sg:address":"4420 Park Blvd",
    "sg:city":"Oakland",
    "sg:classifiers":[
        {
            "category":"Building & Trades",
            "subcategory":"Electrical",
            "type":"Services"
        }
    ],
    "sg:phone":"+1 510 482 4098",
    "sg:postcode":"94602",
    "sg:province":"CA",
    "sg:tags":[
        "electrician"
    ],
    "wof:name":"Wai Lam Electric Co",
    "wof:placetype":"venue"
},
  "geometry": {"coordinates":[-122.220083,37.808344],"type":"Point"}
}