{
  "type": "Feature",
  "properties": {
    "addr:full":"6717 Crow Canyon Rd Castro Valley CA 94552",
    "addr:housenumber":"6717",
    "addr:postcode":"94552",
    "addr:street":"Crow Canyon Rd",
    "iso:country":"US",
    "sg:address":"6717 Crow Canyon Rd",
    "sg:city":"Castro Valley",
    "sg:classifiers":[
        {
            "category":"Building & Trades",
            "subcategory":"Construction",
            "type":"Services"
        }
    ],
    "sg:phone":"+1 510 583 0002",
    "sg:postcode":"94552",
    "sg:province":"CA",
    "sg:tags":[
        "pipe",
        "line",
        "contractor"
    ],
    "wof:name":"Talus Construction",
    "wof:placetype":"venue"
},
  "geometry": {"coordinates":[-122.03807500000001,37.718799],"type":"Point"}
}