{
  "type": "Feature",
  "properties": {
    "addr:full":"2901 La Cienega Culver City CA 90232",
    "addr:housenumber":"2901",
    "addr:postcode":"90232",
    "addr:street":"La Cienega",
    "iso:country":"US",
    "sg:address":"2901 La Cienega",
    "sg:city":"Culver City",
    "sg:classifiers":[
        {
            "category":"Restaurant",
            "type":"Food & Drink"
        }
    ],
    "sg:phone":"+1 310 837 8800",
    "sg:postcode":"90232",
    "sg:province":"CA",
    "sg:tags":[
        "pizza"
    ],
    "sg:website":"www.pizzahut.com",
    "wof:name":"Pizza Hut",
    "wof:placetype":"venue"
},
  "geometry": {"coordinates":[-118.374205,34.032409],"type":"Point"}
}