{
  "type": "Feature",
  "properties": {
    "iso:country":"US",
    "sg:address":"12828 S Broadway",
    "sg:city":"Los Angeles",
    "sg:classifiers":[
        {
            "category":"Shopping",
            "subcategory":"Crafts & Fabrics",
            "type":"Retail Goods"
        }
    ],
    "sg:phone":"+1 310 516 1969",
    "sg:postcode":"90061",
    "sg:province":"CA",
    "sg:tags":[
        "store"
    ],
    "wof:name":"PV Tex Inc",
    "wof:placetype":"venue"
},
  "geometry": {"coordinates":[-118.278152,33.916108],"type":"Point"}
}