{
  "type": "Feature",
  "properties": {
    "iso:country":"US",
    "sg:address":"123 Seaport Blvd",
    "sg:city":"Redwood City",
    "sg:classifiers":[
        {
            "category":"Home & Garden",
            "subcategory":"Building Materials",
            "type":"Retail Goods"
        }
    ],
    "sg:phone":"+1 650 365 4811",
    "sg:postcode":"94063",
    "sg:province":"CA",
    "sg:tags":[
        "mixed",
        "concrete"
    ],
    "wof:name":"Harbor Ready-Mix",
    "wof:placetype":"venue"
},
  "geometry": {"coordinates":[-122.213508,37.493491],"type":"Point"}
}