{
  "type": "Feature",
  "properties": {
    "addr:full":"2101 N Fruit Ave Fresno CA 93705",
    "addr:housenumber":"2101",
    "addr:postcode":"93705",
    "addr:street":"N Fruit Ave",
    "iso:country":"US",
    "sg:address":"2101 N Fruit Ave",
    "sg:city":"Fresno",
    "sg:classifiers":[
        {
            "category":"Place Of Worship",
            "subcategory":"Church",
            "type":"Public Place"
        },
        {
            "category":"Place Of Worship",
            "type":"Public Place"
        }
    ],
    "sg:phone":"+1 559 237 7597",
    "sg:postcode":"93705",
    "sg:province":"CA",
    "sg:tags":[
        "lutheran",
        "america",
        "elca",
        "churches-lutheran",
        "churches-lutheran-evangelical"
    ],
    "sg:website":"http://www.oursavioursfresno.com",
    "wof:name":"Our Saviors Lutheran Church",
    "wof:placetype":"venue"
},
  "geometry": {"coordinates":[-119.817627,36.769341],"type":"Point"}
}