{
  "type": "Feature",
  "properties": {
    "addr:full":"16388 Colima Rd La Puente CA 91745",
    "addr:postcode":"16388;91745",
    "addr:street":"Colima Rd",
    "iso:country":"US",
    "sg:address":"16388 Colima Rd",
    "sg:city":"La Puente",
    "sg:classifiers":[
        {
            "category":"Health Services",
            "subcategory":"Doctor",
            "type":"Services"
        }
    ],
    "sg:phone":"+1 626 333 6001",
    "sg:postcode":"91745",
    "sg:province":"CA",
    "sg:tags":[
        "clinic"
    ],
    "wof:name":"Childrens Clinic",
    "wof:placetype":"venue"
},
  "geometry": {"coordinates":[-117.95899,33.982894],"type":"Point"}
}