{
  "type": "Feature",
  "properties": {
    "addr:full":"1444 N Batavia St Orange CA 92867",
    "addr:housenumber":"1444",
    "addr:postcode":"92867",
    "addr:street":"N Batavia St",
    "iso:country":"US",
    "sg:address":"1444 N Batavia St",
    "sg:city":"Orange",
    "sg:classifiers":[
        {
            "category":"Building & Trades",
            "subcategory":"Construction",
            "type":"Services"
        }
    ],
    "sg:phone":"+1 714 538 7111",
    "sg:postcode":"92867",
    "sg:province":"CA",
    "sg:tags":[
        "contractor"
    ],
    "wof:name":"C R Kitchen Remodeling",
    "wof:placetype":"venue"
},
  "geometry": {"coordinates":[-117.862503,33.810734],"type":"Point"}
}