{
  "type": "Feature",
  "properties": {
    "iso:country":"US",
    "sg:address":"138 S Atlantic Blvd",
    "sg:city":"Monterey Park",
    "sg:classifiers":[
        {
            "category":"Personal",
            "subcategory":"Massage",
            "type":"Services"
        },
        {
            "category":"Personal",
            "subcategory":"Nail Salon",
            "type":"Services"
        }
    ],
    "sg:phone":"+1 626 293 1789",
    "sg:postcode":"91754",
    "sg:province":"CA",
    "wof:name":"Atlantic Beauty & Foot Spa",
    "wof:placetype":"venue"
},
  "geometry": {"coordinates":[-118.134102,34.061445],"type":"Point"}
}