{
  "type": "Feature",
  "properties": {
    "addr:full":"700 Montgomery St San Francisco CA 94111",
    "addr:housenumber":"700",
    "addr:postcode":"94111",
    "addr:street":"Montgomery St",
    "iso:country":"US",
    "sg:address":"700 Montgomery St",
    "sg:city":"San Francisco",
    "sg:classifiers":[
        {
            "category":"Winery",
            "type":"Food & Drink"
        }
    ],
    "sg:phone":"+1 415 563 8370",
    "sg:postcode":"94111",
    "sg:province":"CA",
    "wof:name":"Verotto",
    "wof:placetype":"venue"
},
  "geometry": {"coordinates":[-122.403139,37.795556],"type":"Point"}
}