{
  "type": "Feature",
  "properties": {
    "addr:full":"18827 Studebaker Rd Cerritos CA 90703",
    "addr:housenumber":"18827",
    "addr:postcode":"ca 90703",
    "addr:street":"Studebaker Rd",
    "iso:country":"US",
    "sg:address":"18827 Studebaker Rd",
    "sg:city":"Cerritos",
    "sg:classifiers":[
        {
            "category":"Autos & Motor Vehicles",
            "subcategory":"Automobile Sales",
            "type":"Retail Goods"
        }
    ],
    "sg:phone":"+1 562 402 5281",
    "sg:postcode":"90703",
    "sg:province":"CA",
    "sg:tags":[
        "body",
        "repairing",
        "painting",
        "car"
    ],
    "sg:website":"www.cerritosacura.com",
    "wof:name":"Cerritos Acura",
    "wof:placetype":"venue"
},
  "geometry": {"coordinates":[-118.09972399999999,33.860198],"type":"Point"}
}