{
  "type": "Feature",
  "properties": {
    "addr:full":"16326 S Western Ave Gardena CA 90247",
    "addr:housenumber":"16326",
    "addr:postcode":"90247",
    "addr:street":"S Western Ave",
    "iso:country":"US",
    "sg:address":"16326 S Western Ave",
    "sg:city":"Gardena",
    "sg:classifiers":[
        {
            "category":"Shopping",
            "subcategory":"Clothing, Apparel, & Fashions",
            "type":"Retail Goods"
        }
    ],
    "sg:phone":"+1 310 532 5421",
    "sg:postcode":"90247",
    "sg:province":"CA",
    "wof:name":"Luxury",
    "wof:placetype":"venue"
},
  "geometry": {"coordinates":[-118.309045,33.88311],"type":"Point"}
}