{
  "type": "Feature",
  "properties": {
    "iso:country":"US",
    "sg:address":"16200 Ventura Blvd",
    "sg:city":"Encino",
    "sg:classifiers":[
        {
            "category":"Health Services",
            "subcategory":"Medical Lab",
            "type":"Services"
        }
    ],
    "sg:phone":"+1 818 990 3470",
    "sg:postcode":"91436",
    "sg:province":"CA",
    "sg:tags":[
        "laboratory"
    ],
    "wof:name":"Promed Diagnostics Inc",
    "wof:placetype":"venue"
},
  "geometry": {"coordinates":[-118.48617,34.156591],"type":"Point"}
}