{
  "type": "Feature",
  "properties": {
    "addr:full":"14291 Euclid St Ste D114 Garden Grove CA 92843",
    "addr:housenumber":"14291",
    "addr:postcode":"92843",
    "addr:street":"Euclid St;D114",
    "iso:country":"US",
    "sg:address":"14291 Euclid St Ste D114",
    "sg:city":"Garden Grove",
    "sg:classifiers":[
        {
            "category":"Health Services",
            "subcategory":"Dentist",
            "type":"Services"
        }
    ],
    "sg:phone":"+1 714 554 2054",
    "sg:postcode":"92843",
    "sg:province":"CA",
    "wof:name":"Mylan Luu DDS",
    "wof:placetype":"venue"
},
  "geometry": {"coordinates":[-117.93775599999999,33.759692],"type":"Point"}
}