{
  "type": "Feature",
  "properties": {
    "addr:full":"4471 Stoneridge Dr Pleasanton CA 94588",
    "addr:housenumber":"4471",
    "addr:postcode":"94588",
    "addr:street":"Stoneridge Dr",
    "iso:country":"US",
    "sg:address":"4471 Stoneridge Dr",
    "sg:city":"Pleasanton",
    "sg:classifiers":[
        {
            "category":"Professional",
            "subcategory":"Accounting & Tax Preparation",
            "type":"Services"
        }
    ],
    "sg:phone":"+1 925 426 6600",
    "sg:postcode":"94588",
    "sg:province":"CA",
    "sg:tags":[
        "bookkeeping",
        "general"
    ],
    "wof:name":"Management Systems",
    "wof:placetype":"venue"
},
  "geometry": {"coordinates":[-121.88681800000001,37.690208],"type":"Point"}
}