{
  "type": "Feature",
  "properties": {
    "addr:full":"802 Denise Ln El Cajon CA 92020",
    "addr:housenumber":"802",
    "addr:postcode":"92020",
    "addr:street":"Denise Ln",
    "iso:country":"US",
    "sg:address":"802 Denise Ln",
    "sg:city":"El Cajon",
    "sg:classifiers":[
        {
            "category":"Manufacturing",
            "subcategory":"Glass & Minerals",
            "type":"Manufacturing & Wholesale Goods"
        }
    ],
    "sg:phone":"+1 619 647 4200",
    "sg:postcode":"92020",
    "sg:province":"CA",
    "sg:tags":[
        "concrete",
        "product",
        "mfg"
    ],
    "wof:name":"Dots Dw",
    "wof:placetype":"venue"
},
  "geometry": {"coordinates":[-116.95544700000001,32.784152],"type":"Point"}
}