{
  "type": "Feature",
  "properties": {
    "addr:full":"17151 Main St Hesperia CA 92345",
    "addr:housenumber":"17151",
    "addr:postcode":"92345",
    "addr:street":"Main St",
    "iso:country":"US",
    "sg:address":"17151 Main St",
    "sg:city":"Hesperia",
    "sg:classifiers":[
        {
            "category":"Health Services",
            "subcategory":"Optometrist",
            "type":"Services"
        }
    ],
    "sg:phone":"+1 760 244 4904",
    "sg:postcode":"92345",
    "sg:province":"CA",
    "wof:name":"Charles A Richards OD",
    "wof:placetype":"venue"
},
  "geometry": {"coordinates":[-117.288889,34.419566],"type":"Point"}
}