{
  "type": "Feature",
  "properties": {
    "iso:country":"US",
    "sg:address":"1050 Cindy Ln",
    "sg:city":"Carpinteria",
    "sg:classifiers":[
        {
            "category":"Wholesale",
            "subcategory":"Medical Equipment & Supplies",
            "type":"Manufacturing & Wholesale Goods"
        }
    ],
    "sg:phone":"+1 805 684 8780",
    "sg:postcode":"93013",
    "sg:province":"CA",
    "sg:tags":[
        "instrument",
        "surgical"
    ],
    "wof:name":"Nusil Corporation",
    "wof:placetype":"venue"
},
  "geometry": {"coordinates":[-119.484388,34.386481],"type":"Point"}
}