{
  "type": "Feature",
  "properties": {
    "addr:full":"1436 Howard St San Francisco CA 94103",
    "addr:housenumber":"1436",
    "addr:postcode":"94103",
    "addr:street":"Howard St",
    "iso:country":"US",
    "sg:address":"1436 Howard St",
    "sg:city":"San Francisco",
    "sg:classifiers":[
        {
            "category":"Professional",
            "subcategory":"Computer Services",
            "type":"Services"
        }
    ],
    "sg:postcode":"94103",
    "sg:province":"CA",
    "sg:tags":[
        "online-recruiting",
        "facebook",
        "social-recruiting",
        "pages"
    ],
    "sg:website":"http://www.work4labs.com",
    "wof:name":"Work4 Labs",
    "wof:placetype":"venue"
},
  "geometry": {"coordinates":[-122.415268,37.7735],"type":"Point"}
}