{
  "type": "Feature",
  "properties": {
    "iso:country":"US",
    "sg:address":"1150 7th Ave Studio # 1 & # 3",
    "sg:city":"Sacramento",
    "sg:classifiers":[
        {
            "category":"Personal",
            "type":"Services"
        }
    ],
    "sg:phone":"+1 619 237 6177",
    "sg:postcode":"92101",
    "sg:province":"CA",
    "sg:tags":[
        "sewing",
        "alteration"
    ],
    "wof:name":"Soudi Design & Alteration",
    "wof:placetype":"venue"
},
  "geometry": {"coordinates":[-121.504462,38.550596],"type":"Point"}
}