{
  "type": "Feature",
  "properties": {
    "addr:full":"23903 Malibu Knolls Rd Malibu CA 90265",
    "addr:housenumber":"23903",
    "addr:postcode":"90265",
    "addr:street":"Malibu Knolls Rd",
    "iso:country":"US",
    "sg:address":"23903 Malibu Knolls Rd",
    "sg:city":"Malibu",
    "sg:classifiers":[
        {
            "category":"Manufacturing",
            "subcategory":"Metals",
            "type":"Manufacturing & Wholesale Goods"
        }
    ],
    "sg:phone":"+1 310 456 1291",
    "sg:postcode":"90265",
    "sg:province":"CA",
    "sg:tags":[
        "equipment",
        "energy",
        "solar"
    ],
    "wof:name":"Macrowave Products",
    "wof:placetype":"venue"
},
  "geometry": {"coordinates":[-118.696168,34.04012],"type":"Point"}
}