{
  "type": "Feature",
  "properties": {
    "addr:full":"29822 State Rte 108 Long Barn CA 95335",
    "addr:housenumber":"29822",
    "addr:postcode":"95335",
    "addr:street":"State Rte 108",
    "iso:country":"US",
    "sg:address":"29822 State Rte 108",
    "sg:city":"Long Barn",
    "sg:classifiers":[
        {
            "category":"Food & Beverages",
            "subcategory":"Groceries & Convenience Stores",
            "type":"Retail Goods"
        }
    ],
    "sg:phone":"+1 209 965 4242",
    "sg:postcode":"95335",
    "sg:province":"CA",
    "wof:name":"Fuel & Food",
    "wof:placetype":"venue"
},
  "geometry": {"coordinates":[-120.048535,38.165236],"type":"Point"}
}