{
  "type": "Feature",
  "properties": {
    "iso:country":"US",
    "sg:address":"3000 Taylor Rd",
    "sg:city":"Roseville",
    "sg:classifiers":[
        {
            "category":"Freight",
            "type":"Transportation"
        }
    ],
    "sg:phone":"+1 916 773 3000",
    "sg:postcode":"95678",
    "sg:province":"CA",
    "sg:tags":[
        "commercial",
        "storage",
        "general"
    ],
    "wof:name":"A-A A A Taylor Road Self Stora",
    "wof:placetype":"venue"
},
  "geometry": {"coordinates":[-121.252939,38.770759],"type":"Point"}
}