{
  "type": "Feature",
  "properties": {
    "iso:country":"US",
    "sg:address":"5960 Florence Ave",
    "sg:city":"Bell Gardens",
    "sg:classifiers":[
        {
            "category":"Shopping",
            "subcategory":"Musical Instruments",
            "type":"Retail Goods"
        }
    ],
    "sg:phone":"+1 323 562 3028",
    "sg:postcode":"90201",
    "sg:province":"CA",
    "sg:tags":[
        "music",
        "dealer"
    ],
    "wof:name":"Discotea Y Regalos Culican",
    "wof:placetype":"venue"
},
  "geometry": {"coordinates":[-118.158221,33.96715],"type":"Point"}
}