{
  "type": "Feature",
  "properties": {
    "iso:country":"US",
    "sg:address":"1455 34th St",
    "sg:city":"Sacramento",
    "sg:classifiers":[
        {
            "category":"Health Services",
            "subcategory":"Doctor",
            "type":"Services"
        }
    ],
    "sg:phone":"+1 916 452 1504",
    "sg:postcode":"95816",
    "sg:province":"CA",
    "wof:name":"Schaffer Charles MD",
    "wof:placetype":"venue"
},
  "geometry": {"coordinates":[-121.462997,38.567101],"type":"Point"}
}