{
  "type": "Feature",
  "properties": {
    "addr:full":"10660 Gay Rd Wilton CA 95693",
    "addr:housenumber":"10660",
    "addr:postcode":"95693",
    "addr:street":"Gay Rd",
    "iso:country":"US",
    "sg:address":"10660 Gay Rd",
    "sg:city":"Wilton",
    "sg:classifiers":[
        {
            "category":"Farming",
            "subcategory":"Farm & Veterinary Services",
            "type":"Manufacturing & Wholesale Goods"
        }
    ],
    "sg:phone":"+1 916 687 4669",
    "sg:postcode":"95693",
    "sg:province":"CA",
    "sg:tags":[
        "breeder",
        "livestock"
    ],
    "wof:name":"Pheasant Trek",
    "wof:placetype":"venue"
},
  "geometry": {"coordinates":[-121.28743799999999,38.396659],"type":"Point"}
}