{
  "type": "Feature",
  "properties": {
    "addr:full":"554 42nd Ave San Francisco CA 94121",
    "addr:housenumber":"554",
    "addr:postcode":"94121",
    "addr:street":"42Nd Ave",
    "iso:country":"US",
    "sg:address":"554 42nd Ave",
    "sg:city":"San Francisco",
    "sg:classifiers":[
        {
            "category":"Communications",
            "subcategory":"Film & Video Production",
            "type":"Services"
        }
    ],
    "sg:phone":"+1 415 831 0667",
    "sg:postcode":"94121",
    "sg:province":"CA",
    "sg:tags":[
        "taping"
    ],
    "wof:name":"Teamkiowa Film Media Prdctns",
    "wof:placetype":"venue"
},
  "geometry": {"coordinates":[-122.502793,37.778399],"type":"Point"}
}