{
  "type": "Feature",
  "properties": {
    "iso:country":"US",
    "sg:address":"240 Mountain View Ave",
    "sg:city":"Mountain View",
    "sg:classifiers":[
        {
            "category":"Building & Trades",
            "subcategory":"Cleaning & Sanitation",
            "type":"Services"
        }
    ],
    "sg:phone":"+1 650 969 4657",
    "sg:postcode":"94041",
    "sg:province":"CA",
    "sg:tags":[
        "butler",
        "maid"
    ],
    "wof:name":"Clearviews",
    "wof:placetype":"venue"
},
  "geometry": {"coordinates":[-122.08447,37.39599],"type":"Point"}
}