{
  "type": "Feature",
  "properties": {
    "iso:country":"US",
    "sg:address":"809 S Grand Ave",
    "sg:city":"Santa Ana",
    "sg:classifiers":[
        {
            "category":"Autos & Motor Vehicles",
            "subcategory":"Auto Supplies",
            "type":"Retail Goods"
        },
        {
            "category":"Retail",
            "subcategory":"Auto Repair",
            "type":"Services"
        }
    ],
    "sg:phone":"+1 714 542 9800",
    "sg:postcode":"92705",
    "sg:province":"CA",
    "sg:tags":[
        "tire"
    ],
    "sg:website":"www.4wheelparts.com",
    "wof:name":"4 Wheel Parts",
    "wof:placetype":"venue"
},
  "geometry": {"coordinates":[-117.85023099999999,33.737167],"type":"Point"}
}