{
  "type": "Feature",
  "properties": {
    "addr:full":"301 Leconte Hall Berkeley CA 94720",
    "addr:housenumber":"301",
    "addr:postcode":"94720",
    "addr:street":"Leconte Hall",
    "iso:country":"US",
    "sg:address":"301 Leconte Hall",
    "sg:city":"Berkeley",
    "sg:classifiers":[
        {
            "category":"Education",
            "subcategory":"University",
            "type":"Public Place"
        }
    ],
    "sg:phone":"+1 510 642 4705",
    "sg:postcode":"94720",
    "sg:province":"CA",
    "sg:tags":[
        "college"
    ],
    "wof:name":"University of California Berkeley",
    "wof:placetype":"venue"
},
  "geometry": {"coordinates":[-122.256792,37.872371],"type":"Point"}
}