{
  "type": "Feature",
  "properties": {
    "addr:full":"23801 Calabasas Rd Calabasas CA 91302",
    "addr:housenumber":"23801",
    "addr:postcode":"91302",
    "addr:street":"Calabasas Rd",
    "iso:country":"US",
    "sg:address":"23801 Calabasas Rd",
    "sg:city":"Calabasas",
    "sg:classifiers":[
        {
            "category":"Banks & Credit Unions",
            "subcategory":"Financial Services",
            "type":"Services"
        }
    ],
    "sg:phone":"+1 818 225 6290",
    "sg:postcode":"91302",
    "sg:province":"CA",
    "sg:tags":[
        "broker",
        "mortgage"
    ],
    "wof:name":"Equity Fund Group Inc",
    "wof:placetype":"venue"
},
  "geometry": {"coordinates":[-118.644997,34.155102],"type":"Point"}
}