{
  "type": "Feature",
  "properties": {
    "addr:full":"3524 Oakdale Rd Ste C Modesto CA 95357",
    "addr:housenumber":"3524",
    "addr:postcode":"ca 95357",
    "addr:street":"Oakdale Rd Ste C",
    "iso:country":"US",
    "sg:address":"3524 Oakdale Rd Ste C",
    "sg:city":"Modesto",
    "sg:classifiers":[
        {
            "category":"Health Services",
            "subcategory":"Doctor",
            "type":"Services"
        }
    ],
    "sg:phone":"+1 209 572 0458",
    "sg:postcode":"95357",
    "sg:province":"CA",
    "sg:tags":[
        "medicine",
        "physician",
        "addiction",
        "surgeons"
    ],
    "wof:name":"Gleeson Educational Program",
    "wof:placetype":"venue"
},
  "geometry": {"coordinates":[-120.95798499999999,37.689333],"type":"Point"}
}