{
  "type": "Feature",
  "properties": {
    "addr:full":"427 Capitola Road Ext Santa Cruz CA 95062",
    "addr:housenumber":"427",
    "addr:postcode":"95062",
    "addr:street":"Capitola Road Ext",
    "iso:country":"US",
    "sg:address":"427 Capitola Road Ext",
    "sg:city":"Santa Cruz",
    "sg:classifiers":[
        {
            "category":"Social Services",
            "subcategory":"Child Care",
            "type":"Services"
        },
        {
            "category":"Education",
            "subcategory":"Preschool",
            "type":"Public Place"
        },
        {
            "category":"Education",
            "subcategory":"School",
            "type":"Public Place"
        }
    ],
    "sg:phone":"+1 831 476 9684",
    "sg:postcode":"95062",
    "sg:province":"CA",
    "sg:tags":[
        "elementary",
        "day"
    ],
    "wof:name":"Discoveryland Christian Preschool",
    "wof:placetype":"venue"
},
  "geometry": {"coordinates":[-121.991997,36.980598],"type":"Point"}
}