{
  "type": "Feature",
  "properties": {
    "addr:full":"900 S Westmoreland Ave Los Angeles CA 90006",
    "addr:housenumber":"900",
    "addr:postcode":"90006",
    "addr:street":"S Westmoreland Ave",
    "iso:country":"US",
    "sg:address":"900 S Westmoreland Ave",
    "sg:city":"Los Angeles",
    "sg:classifiers":[
        {
            "category":"Wholesale",
            "subcategory":"Apparel",
            "type":"Manufacturing & Wholesale Goods"
        }
    ],
    "sg:phone":"+1 213 383 0210",
    "sg:postcode":"90006",
    "sg:province":"CA",
    "sg:tags":[
        "clothing"
    ],
    "wof:name":"Moreland Clothing Wholesale",
    "wof:placetype":"venue"
},
  "geometry": {"coordinates":[-118.289072,34.054995],"type":"Point"}
}