{
  "type": "Feature",
  "properties": {
    "addr:full":"11218 Mountain View Dr Madera CA 93636",
    "addr:housenumber":"11218",
    "addr:postcode":"93636",
    "addr:street":"Mountain View Dr",
    "iso:country":"US",
    "sg:address":"11218 Mountain View Dr",
    "sg:city":"Madera",
    "sg:classifiers":[
        {
            "category":"Shopping",
            "type":"Retail Goods"
        }
    ],
    "sg:phone":"+1 559 439 3643",
    "sg:postcode":"93636",
    "sg:province":"CA",
    "sg:tags":[
        "merchandise"
    ],
    "wof:name":"Mark Hansston Enterprise",
    "wof:placetype":"venue"
},
  "geometry": {"coordinates":[-119.79579,36.91117],"type":"Point"}
}