{
  "type": "Feature",
  "properties": {
    "iso:country":"US",
    "sg:address":"1918 W Magnolia Blvd Ste 201",
    "sg:city":"Burbank",
    "sg:classifiers":[
        {
            "category":"Building & Trades",
            "subcategory":"Construction",
            "type":"Services"
        }
    ],
    "sg:phone":"+1 818 848 6395",
    "sg:postcode":"91506",
    "sg:province":"CA",
    "sg:tags":[
        "contractor"
    ],
    "wof:name":"Towne Robt Towne Development C",
    "wof:placetype":"venue"
},
  "geometry": {"coordinates":[-118.329002,34.174],"type":"Point"}
}