{
  "type": "Feature",
  "properties": {
    "addr:full":"203 Sunrise Ave Roseville CA 95661",
    "addr:housenumber":"203",
    "addr:postcode":"95661",
    "addr:street":"Sunrise Ave",
    "iso:country":"US",
    "sg:address":"203 Sunrise Ave",
    "sg:city":"Roseville",
    "sg:classifiers":[
        {
            "category":"Real Estate",
            "subcategory":"Real Estate Agent",
            "type":"Services"
        }
    ],
    "sg:phone":"+1 916 780 8284",
    "sg:postcode":"95661",
    "sg:province":"CA",
    "wof:name":"Realty Estate Corp",
    "wof:placetype":"venue"
},
  "geometry": {"coordinates":[-121.270886,38.742652],"type":"Point"}
}