{
  "type": "Feature",
  "properties": {
    "iso:country":"US",
    "sg:address":"518 W Foothill Blvd",
    "sg:city":"Rialto",
    "sg:classifiers":[
        {
            "category":"Food & Beverages",
            "subcategory":"Groceries & Convenience Stores",
            "type":"Retail Goods"
        }
    ],
    "sg:phone":"+1 909 820 9753",
    "sg:postcode":"92376",
    "sg:province":"CA",
    "wof:name":"Circle K",
    "wof:placetype":"venue"
},
  "geometry": {"coordinates":[-117.383174,34.106832],"type":"Point"}
}