{
  "type": "Feature",
  "properties": {
    "iso:country":"US",
    "sg:address":"710 N Heliotrope Dr",
    "sg:city":"Los Angeles",
    "sg:classifiers":[
        {
            "category":"Restaurant",
            "type":"Food & Drink"
        }
    ],
    "sg:phone":"+1 323 669 2823",
    "sg:postcode":"90029",
    "sg:province":"CA",
    "sg:tags":[
        "shop",
        "tea",
        "coffee"
    ],
    "wof:name":"Night In Tunisia",
    "wof:placetype":"venue"
},
  "geometry": {"coordinates":[-118.29499800000001,34.085098],"type":"Point"}
}