{
  "type": "Feature",
  "properties": {
    "iso:country":"US",
    "sg:address":"6340 Coldwater Canyon Ave",
    "sg:city":"North Hollywood",
    "sg:classifiers":[
        {
            "category":"Professional",
            "type":"Services"
        }
    ],
    "sg:phone":"+1 818 753 5201",
    "sg:postcode":"91606",
    "sg:province":"CA",
    "wof:name":"Hill Center",
    "wof:placetype":"venue"
},
  "geometry": {"coordinates":[-118.41371100000001,34.185946],"type":"Point"}
}