{
  "type": "Feature",
  "properties": {
    "iso:country":"US",
    "sg:address":"370 N Palm Canyon Dr",
    "sg:city":"Palm Springs",
    "sg:classifiers":[
        {
            "category":"Restaurant",
            "type":"Food & Drink"
        }
    ],
    "sg:phone":"+1 760 416 0227",
    "sg:postcode":"92262",
    "sg:province":"CA",
    "wof:name":"Crosswalk Cafe",
    "wof:placetype":"venue"
},
  "geometry": {"coordinates":[-116.546997,33.8279],"type":"Point"}
}