{
  "type": "Feature",
  "properties": {
    "addr:full":"1525 S Coast Hwy Oceanside CA 92054",
    "addr:housenumber":"1525",
    "addr:postcode":"92054",
    "addr:street":"S Coast Hwy",
    "iso:country":"US",
    "sg:address":"1525 S Coast Hwy",
    "sg:city":"Oceanside",
    "sg:classifiers":[
        {
            "category":"Retail",
            "subcategory":"Repair Shop",
            "type":"Services"
        }
    ],
    "sg:phone":"+1 760 722 2588",
    "sg:postcode":"92054",
    "sg:province":"CA",
    "sg:tags":[
        "welding",
        "metal",
        "fabrication",
        "structural"
    ],
    "wof:name":"Ace Welding",
    "wof:placetype":"venue"
},
  "geometry": {"coordinates":[-117.365987,33.179623],"type":"Point"}
}