{
  "type": "Feature",
  "properties": {
    "iso:country":"US",
    "sg:address":"1458 W Monterey Ave",
    "sg:city":"Stockton",
    "sg:classifiers":[
        {
            "category":"Real Estate",
            "subcategory":"Real Estate Agent",
            "type":"Services"
        }
    ],
    "sg:phone":"+1 209 467 7933",
    "sg:postcode":"95204",
    "sg:province":"CA",
    "wof:name":"Schon Realty",
    "wof:placetype":"venue"
},
  "geometry": {"coordinates":[-121.32030899999999,37.972168],"type":"Point"}
}