{
  "type": "Feature",
  "properties": {
    "iso:country":"US",
    "sg:address":"10573 W Pico Blvd",
    "sg:city":"Los Angeles",
    "sg:classifiers":[
        {
            "category":"Health Services",
            "subcategory":"Health Practitioner",
            "type":"Services"
        }
    ],
    "sg:phone":"+1 310 474 4165",
    "sg:postcode":"90064",
    "sg:province":"CA",
    "sg:tags":[
        "psychotherapist"
    ],
    "wof:name":"Joanna Poppink",
    "wof:placetype":"venue"
},
  "geometry": {"coordinates":[-118.421948,34.043579],"type":"Point"}
}