{
  "type": "Feature",
  "properties": {
    "addr:full":"8824 Shirley Ave Northridge CA 91324",
    "addr:housenumber":"8824",
    "addr:postcode":"91324",
    "addr:street":"Shirley Ave",
    "iso:country":"US",
    "sg:address":"8824 Shirley Ave",
    "sg:city":"Northridge",
    "sg:classifiers":[
        {
            "category":"Wholesale",
            "subcategory":"Toys & Hobbies",
            "type":"Manufacturing & Wholesale Goods"
        }
    ],
    "sg:phone":"+1 818 407 0384",
    "sg:postcode":"91324",
    "sg:province":"CA",
    "wof:name":"Extreme Bounce",
    "wof:placetype":"venue"
},
  "geometry": {"coordinates":[-118.557857,34.230998],"type":"Point"}
}