{
  "type": "Feature",
  "properties": {
    "iso:country":"US",
    "sg:address":"2100 Zinfandel Dr",
    "sg:city":"Rancho Cordova",
    "sg:classifiers":[
        {
            "category":"Education",
            "subcategory":"School",
            "type":"Public Place"
        }
    ],
    "sg:phone":"+1 916 635 8460",
    "sg:postcode":"95670",
    "sg:province":"CA",
    "sg:tags":[
        "high",
        "middle",
        "elementary"
    ],
    "sg:website":"www.fcusd.k12.ca.us",
    "wof:name":"Mitchell Middle School",
    "wof:placetype":"venue"
},
  "geometry": {"coordinates":[-121.275002,38.611],"type":"Point"}
}