{
  "type": "Feature",
  "properties": {
    "iso:country":"US",
    "sg:address":"395 S Oakland Ave",
    "sg:city":"Pasadena",
    "sg:classifiers":[
        {
            "category":"Travel",
            "subcategory":"Travel Agent",
            "type":"Entertainment"
        }
    ],
    "sg:phone":"+1 626 577 4477",
    "sg:postcode":"91101",
    "sg:province":"CA",
    "sg:tags":[
        "tours",
        "promoter"
    ],
    "sg:website":"www.nextstagetours.com",
    "wof:name":"Next Stage Tours",
    "wof:placetype":"venue"
},
  "geometry": {"coordinates":[-118.139744,34.137191],"type":"Point"}
}