{
  "type": "Feature",
  "properties": {
    "iso:country":"US",
    "sg:address":"411 U St",
    "sg:city":"Eureka",
    "sg:classifiers":[
        {
            "category":"Health Services",
            "subcategory":"Clinic",
            "type":"Services"
        },
        {
            "category":"Insurance",
            "subcategory":"Life Insurance",
            "type":"Services"
        }
    ],
    "sg:phone":"+1 707 445 8232",
    "sg:postcode":"95501",
    "sg:province":"CA",
    "sg:tags":[
        "carrier",
        "examination"
    ],
    "wof:name":"North Coast Para Medical Svcs",
    "wof:placetype":"venue"
},
  "geometry": {"coordinates":[-124.15028599999999,40.804588],"type":"Point"}
}