{
  "type": "Feature",
  "properties": {
    "addr:full":"14380 Saratoga Ave Saratoga CA 95070",
    "addr:housenumber":"14380",
    "addr:postcode":"95070",
    "addr:street":"Saratoga Ave",
    "iso:country":"US",
    "sg:address":"14380 Saratoga Ave",
    "sg:city":"Saratoga",
    "sg:classifiers":[
        {
            "category":"Government",
            "subcategory":"Fire Station",
            "type":"Public Place"
        }
    ],
    "sg:phone":"+1 408 867 9001",
    "sg:postcode":"95070",
    "sg:province":"CA",
    "sg:tags":[
        "department"
    ],
    "wof:name":"Saratoga Fire Dept",
    "wof:placetype":"venue"
},
  "geometry": {"coordinates":[-122.03148299999999,37.259297],"type":"Point"}
}