{
  "type": "Feature",
  "properties": {
    "iso:country":"US",
    "sg:address":"41232 Rd 70",
    "sg:city":"Dinuba",
    "sg:classifiers":[
        {
            "category":"Farming",
            "subcategory":"Vineyard",
            "type":"Manufacturing & Wholesale Goods"
        }
    ],
    "sg:phone":"+1 559 591 1033",
    "sg:postcode":"93618",
    "sg:province":"CA",
    "sg:tags":[
        "grape"
    ],
    "wof:name":"Hirata Akito",
    "wof:placetype":"venue"
},
  "geometry": {"coordinates":[-119.417243,36.545559],"type":"Point"}
}