{
  "type": "Feature",
  "properties": {
    "iso:country":"US",
    "sg:address":"519 Marine View St",
    "sg:city":"Belmont",
    "sg:classifiers":[
        {
            "category":"Home & Garden",
            "subcategory":"Furniture",
            "type":"Retail Goods"
        }
    ],
    "sg:phone":"+1 650 593 5008",
    "sg:postcode":"94002",
    "sg:province":"CA",
    "wof:name":"Casa Collection",
    "wof:placetype":"venue"
},
  "geometry": {"coordinates":[-122.280795,37.525452],"type":"Point"}
}