{
  "type": "Feature",
  "properties": {
    "iso:country":"US",
    "sg:address":"2121 Park Pl",
    "sg:city":"El Segundo",
    "sg:classifiers":[
        {
            "category":"Professional",
            "subcategory":"Computer Services",
            "type":"Services"
        }
    ],
    "sg:phone":"+1 310 335 8341",
    "sg:postcode":"90245",
    "sg:province":"CA",
    "sg:tags":[
        "datum"
    ],
    "wof:name":"EDS",
    "wof:placetype":"venue"
},
  "geometry": {"coordinates":[-118.38663699999999,33.905234],"type":"Point"}
}