{
  "type": "Feature",
  "properties": {
    "addr:full":"14274 Doolittle Dr San Leandro CA 94577",
    "addr:housenumber":"14274",
    "addr:postcode":"94577",
    "addr:street":"Doolittle Dr",
    "iso:country":"US",
    "sg:address":"14274 Doolittle Dr",
    "sg:city":"San Leandro",
    "sg:classifiers":[
        {
            "category":"Health Services",
            "subcategory":"Medical Lab",
            "type":"Services"
        }
    ],
    "sg:phone":"+1 510 352 6261",
    "sg:postcode":"94577",
    "sg:province":"CA",
    "sg:tags":[
        "laboratory"
    ],
    "wof:name":"Galaxy Dental Ceramics",
    "wof:placetype":"venue"
},
  "geometry": {"coordinates":[-122.173705,37.695344],"type":"Point"}
}