{
  "type": "Feature",
  "properties": {
    "addr:full":"1005 Newpark Mall Newark CA 94560",
    "addr:housenumber":"1005",
    "addr:postcode":"94560",
    "addr:street":"Newpark Mall",
    "iso:country":"US",
    "sg:address":"1005 Newpark Mall",
    "sg:city":"Newark",
    "sg:classifiers":[
        {
            "category":"Manufacturing",
            "subcategory":"Furniture",
            "type":"Manufacturing & Wholesale Goods"
        },
        {
            "category":"Shopping",
            "subcategory":"Gifts & Souvenirs",
            "type":"Retail Goods"
        }
    ],
    "sg:phone":"+1 510 744 0281",
    "sg:postcode":"94560",
    "sg:province":"CA",
    "sg:tags":[
        "shop",
        "household",
        "mfg"
    ],
    "wof:name":"Something Special",
    "wof:placetype":"venue"
},
  "geometry": {"coordinates":[-122.003905,37.525246],"type":"Point"}
}