{
  "type": "Feature",
  "properties": {
    "addr:full":"532 Dawson Dr Camarillo CA 93012",
    "addr:housenumber":"532",
    "addr:postcode":"93012",
    "addr:street":"Dawson Dr",
    "iso:country":"US",
    "sg:address":"532 Dawson Dr",
    "sg:city":"Camarillo",
    "sg:classifiers":[
        {
            "category":"Utilities",
            "subcategory":"Refuse",
            "type":"Services"
        },
        {
            "category":"Wholesale",
            "subcategory":"Scrap",
            "type":"Manufacturing & Wholesale Goods"
        }
    ],
    "sg:phone":"+1 805 987 0226",
    "sg:postcode":"93012",
    "sg:province":"CA",
    "sg:tags":[
        "recycling",
        "material",
        "center",
        "system"
    ],
    "sg:website":"www.camarillorecycling.com",
    "wof:name":"Camarillo Recycling Inc",
    "wof:placetype":"venue"
},
  "geometry": {"coordinates":[-119.03630099999999,34.209198],"type":"Point"}
}