{
  "type": "Feature",
  "properties": {
    "addr:full":"304 Lincoln St Roseville CA 95678",
    "addr:housenumber":"304",
    "addr:postcode":"95678",
    "addr:street":"Lincoln St",
    "iso:country":"US",
    "sg:address":"304 Lincoln St",
    "sg:city":"Roseville",
    "sg:classifiers":[
        {
            "category":"Shopping",
            "subcategory":"Hobbies, Toys, & Games",
            "type":"Retail Goods"
        }
    ],
    "sg:phone":"+1 916 773 9691",
    "sg:postcode":"95678",
    "sg:province":"CA",
    "sg:tags":[
        "model",
        "supply"
    ],
    "wof:name":"Roseville Roundhouse Model",
    "wof:placetype":"venue"
},
  "geometry": {"coordinates":[-121.285158,38.751947],"type":"Point"}
}