{
  "type": "Feature",
  "properties": {
    "addr:full":"11690 Bartlett Ave Adelanto CA 92301",
    "addr:housenumber":"11690",
    "addr:postcode":"92301",
    "addr:street":"Bartlett Ave",
    "iso:country":"US",
    "sg:address":"11690 Bartlett Ave",
    "sg:city":"Adelanto",
    "sg:classifiers":[
        {
            "category":"Retail",
            "subcategory":"Auto Repair",
            "type":"Services"
        }
    ],
    "sg:phone":"+1 760 246 0799",
    "sg:postcode":"92301",
    "sg:province":"CA",
    "sg:tags":[
        "transmission"
    ],
    "wof:name":"Alex Transmissions",
    "wof:placetype":"venue"
},
  "geometry": {"coordinates":[-117.409656,34.5793],"type":"Point"}
}