{
  "type": "Feature",
  "properties": {
    "iso:country":"US",
    "sg:address":"8698 Elk Grove Blvd",
    "sg:city":"Elk Grove",
    "sg:classifiers":[
        {
            "category":"Banks & Credit Unions",
            "subcategory":"Bank",
            "type":"Services"
        }
    ],
    "sg:phone":"+1 916 368 7283",
    "sg:postcode":"95624",
    "sg:province":"CA",
    "sg:tags":[
        "broker",
        "mortgage"
    ],
    "wof:name":"Progressive Mortgage Corp",
    "wof:placetype":"venue"
},
  "geometry": {"coordinates":[-121.380183,38.408914],"type":"Point"}
}