{
  "type": "Feature",
  "properties": {
    "addr:full":"25370 Cypress Ave. Unit A Hayward CA 94544",
    "addr:housenumber":"25370",
    "addr:postcode":"94544",
    "addr:street":"Cypress Ave. Unit A",
    "iso:country":"US",
    "sg:address":"25370 Cypress Ave. Unit A",
    "sg:city":"Hayward",
    "sg:classifiers":[
        {
            "category":"Retail",
            "subcategory":"Auto Repair",
            "type":"Services"
        }
    ],
    "sg:phone":"+1 510 258 8576",
    "sg:postcode":"94544",
    "sg:province":"CA",
    "wof:name":"Nor Cal Custom Automotive",
    "wof:placetype":"venue"
},
  "geometry": {"coordinates":[-122.085441,37.649496],"type":"Point"}
}