{
  "type": "Feature",
  "properties": {
    "iso:country":"US",
    "sg:address":"4 Hutton Center Dr",
    "sg:city":"Irvine",
    "sg:classifiers":[
        {
            "category":"Professional",
            "subcategory":"Employment Agencies",
            "type":"Services"
        }
    ],
    "sg:phone":"+1 714 557 9990",
    "sg:postcode":"92602",
    "sg:province":"CA",
    "wof:name":"Job Finders",
    "wof:placetype":"venue"
},
  "geometry": {"coordinates":[-117.772003,33.729599],"type":"Point"}
}