{
  "type": "Feature",
  "properties": {
    "addr:full":"3625 E 18th St Antioch CA 94509",
    "addr:housenumber":"3625",
    "addr:postcode":"ca 94509",
    "addr:street":"E 18Th St",
    "iso:country":"US",
    "sg:address":"3625 E 18th St",
    "sg:city":"Antioch",
    "sg:classifiers":[
        {
            "category":"Retail",
            "subcategory":"Portrait Studio",
            "type":"Services"
        }
    ],
    "sg:phone":"+1 925 755 3687",
    "sg:postcode":"94509",
    "sg:province":"CA",
    "wof:name":"Olan Mills Portrait Studios",
    "wof:placetype":"venue"
},
  "geometry": {"coordinates":[-121.75524799999999,38.005083],"type":"Point"}
}