{
  "type": "Feature",
  "properties": {
    "addr:full":"245 W 92nd St Los Angeles CA 90003",
    "addr:housenumber":"245",
    "addr:postcode":"90003",
    "addr:street":"W 92Nd St",
    "iso:country":"US",
    "sg:address":"245 W 92nd St",
    "sg:city":"Los Angeles",
    "sg:classifiers":[
        {
            "category":"Social Services",
            "subcategory":"Job Training",
            "type":"Services"
        }
    ],
    "sg:phone":"+1 323 756 8487",
    "sg:postcode":"90003",
    "sg:province":"CA",
    "sg:tags":[
        "rehabilitation"
    ],
    "wof:name":"Gospel Counseling Ctr",
    "wof:placetype":"venue"
},
  "geometry": {"coordinates":[-118.27558399999999,33.952897],"type":"Point"}
}