{
  "type": "Feature",
  "properties": {
    "iso:country":"US",
    "sg:address":"245 W 92nd St",
    "sg:city":"Los Angeles",
    "sg:classifiers":[
        {
            "category":"Social Services",
            "subcategory":"Job Training",
            "type":"Services"
        }
    ],
    "sg:phone":"+1 323 756 8487",
    "sg:postcode":"90003",
    "sg:province":"CA",
    "sg:tags":[
        "rehabilitation"
    ],
    "wof:name":"Gospel Counseling Ctr",
    "wof:placetype":"venue"
},
  "geometry": {"coordinates":[-118.275584,33.952897],"type":"Point"}
}