{
  "type": "Feature",
  "properties": {
    "iso:country":"US",
    "sg:address":"4959 Sepulveda Blvd",
    "sg:city":"Sherman Oaks",
    "sg:classifiers":[
        {
            "category":"Utilities",
            "subcategory":"Telephone",
            "type":"Services"
        }
    ],
    "sg:phone":"+1 818 995 5954",
    "sg:postcode":"91403",
    "sg:province":"CA",
    "sg:tags":[
        "communications"
    ],
    "wof:name":"Pac Bell",
    "wof:placetype":"venue"
},
  "geometry": {"coordinates":[-118.466232,34.161],"type":"Point"}
}