{
  "type": "Feature",
  "properties": {
    "iso:country":"US",
    "sg:address":"550 E Lakeshore Dr",
    "sg:city":"Lake Elsinore",
    "sg:classifiers":[
        {
            "category":"Autos & Motor Vehicles",
            "subcategory":"Auto Supplies",
            "type":"Retail Goods"
        }
    ],
    "sg:phone":"+1 951 674 9888",
    "sg:postcode":"92530",
    "sg:province":"CA",
    "sg:tags":[
        "tire"
    ],
    "wof:name":"Budget Tire & Wheel",
    "wof:placetype":"venue"
},
  "geometry": {"coordinates":[-117.322998,33.6632],"type":"Point"}
}