{
  "type": "Feature",
  "properties": {
    "iso:country":"US",
    "sg:address":"27 S Newport Dr",
    "sg:city":"Napa",
    "sg:classifiers":[
        {
            "category":"Professional",
            "subcategory":"Management & Consulting",
            "type":"Services"
        }
    ],
    "sg:phone":"+1 707 853 0054",
    "sg:postcode":"94559",
    "sg:province":"CA",
    "sg:tags":[
        "consultant"
    ],
    "wof:name":"Landmark Consulting Group",
    "wof:placetype":"venue"
},
  "geometry": {"coordinates":[-122.287118,38.274857],"type":"Point"}
}