{
  "type": "Feature",
  "properties": {
    "iso:country":"US",
    "sg:address":"648 Mitchell Dr",
    "sg:city":"San Luis Obispo",
    "sg:classifiers":[
        {
            "category":"Building & Trades",
            "subcategory":"Plumbing",
            "type":"Services"
        }
    ],
    "sg:phone":"+1 805 544 3060",
    "sg:postcode":"93401",
    "sg:province":"CA",
    "sg:tags":[
        "plumbing",
        "contractor"
    ],
    "wof:name":"Arrow Rooter & Plumbing",
    "wof:placetype":"venue"
},
  "geometry": {"coordinates":[-120.653855,35.265095],"type":"Point"}
}