{
  "type": "Feature",
  "properties": {
    "addr:full":"5511 Westminster Boulevard Westminster CA 92683",
    "addr:housenumber":"5511",
    "addr:postcode":"92683",
    "addr:street":"Westminster Boulevard",
    "iso:country":"US",
    "sg:address":"5511 Westminster Boulevard",
    "sg:city":"Westminster",
    "sg:classifiers":[
        {
            "category":"Food & Beverages",
            "subcategory":"Groceries & Convenience Stores",
            "type":"Retail Goods"
        }
    ],
    "sg:phone":"+1 714 894 5452",
    "sg:postcode":"92683",
    "sg:province":"CA",
    "sg:website":"www.7-eleven.com/",
    "wof:name":"7-Eleven",
    "wof:placetype":"venue"
},
  "geometry": {"coordinates":[-118.034003,33.759492],"type":"Point"}
}