{
  "type": "Feature",
  "properties": {
    "iso:country":"US",
    "sg:address":"511 E Gutierrez St",
    "sg:city":"Santa Barbara",
    "sg:classifiers":[
        {
            "category":"Wholesale",
            "subcategory":"Electrical",
            "type":"Manufacturing & Wholesale Goods"
        }
    ],
    "sg:phone":"+1 805 403 2383",
    "sg:postcode":"93103",
    "sg:province":"CA",
    "sg:tags":[
        "electronic"
    ],
    "wof:name":"Jgd",
    "wof:placetype":"venue"
},
  "geometry": {"coordinates":[-119.687577,34.422144],"type":"Point"}
}