{
  "type": "Feature",
  "properties": {
    "addr:full":"2689 Via De La Valle Del Mar CA 92014",
    "addr:housenumber":"2689",
    "addr:postcode":"92014",
    "addr:street":"Via De La Valle",
    "iso:country":"US",
    "sg:address":"2689 Via De La Valle",
    "sg:city":"Del Mar",
    "sg:classifiers":[
        {
            "category":"Restaurant",
            "type":"Food & Drink"
        }
    ],
    "sg:phone":"+1 858 755 5585",
    "sg:postcode":"92014",
    "sg:province":"CA",
    "sg:tags":[
        "sushi",
        "bar"
    ],
    "sg:website":"www.tabusushibar.com",
    "wof:name":"Tabu Sushi Bar & Grill",
    "wof:placetype":"venue"
},
  "geometry": {"coordinates":[-117.249441,32.979796],"type":"Point"}
}