{
  "type": "Feature",
  "properties": {
    "iso:country":"US",
    "sg:address":"1740 Ofarrell St",
    "sg:city":"San Francisco",
    "sg:classifiers":[
        {
            "category":"Shopping",
            "subcategory":"Clothing, Apparel, & Fashions",
            "type":"Retail Goods"
        }
    ],
    "sg:phone":"+1 415 345 1042",
    "sg:postcode":"94115",
    "sg:province":"CA",
    "wof:name":"Diva-Diva",
    "wof:placetype":"venue"
},
  "geometry": {"coordinates":[-122.433228,37.783319],"type":"Point"}
}