{
  "type": "Feature",
  "properties": {
    "iso:country":"US",
    "sg:address":"4378 Auburn Blvd # 300",
    "sg:city":"Sacramento",
    "sg:classifiers":[
        {
            "category":"Real Estate",
            "subcategory":"Real Estate Services",
            "type":"Services"
        },
        {
            "category":"Building & Trades",
            "subcategory":"Construction",
            "type":"Services"
        }
    ],
    "sg:phone":"+1 916 978 0800",
    "sg:postcode":"95841",
    "sg:province":"CA",
    "sg:tags":[
        "management",
        "property",
        "contractor"
    ],
    "wof:name":"Tower Development Corp",
    "wof:placetype":"venue"
},
  "geometry": {"coordinates":[-121.361,38.646801],"type":"Point"}
}