{
  "type": "Feature",
  "properties": {
    "iso:country":"US",
    "sg:address":"2829 S State St",
    "sg:city":"Hemet",
    "sg:classifiers":[
        {
            "category":"Farming",
            "subcategory":"Farm",
            "type":"Manufacturing & Wholesale Goods"
        }
    ],
    "sg:phone":"+1 951 658 7357",
    "sg:postcode":"92545",
    "sg:province":"CA",
    "sg:tags":[
        "crop",
        "general"
    ],
    "wof:name":"Kirby & Acacia",
    "wof:placetype":"venue"
},
  "geometry": {"coordinates":[-116.971445,33.713124],"type":"Point"}
}