{
  "type": "Feature",
  "properties": {
    "iso:country":"US",
    "sg:address":"101 E Foothill Blvd",
    "sg:city":"Rialto",
    "sg:classifiers":[
        {
            "category":"Banks & Credit Unions",
            "subcategory":"Bank",
            "type":"Services"
        }
    ],
    "sg:phone":"+1 909 875 7010",
    "sg:postcode":"92376",
    "sg:province":"CA",
    "wof:name":"Washington Mutual",
    "wof:placetype":"venue"
},
  "geometry": {"coordinates":[-117.369103,34.106773],"type":"Point"}
}