{
  "type": "Feature",
  "properties": {
    "addr:full":"679 Jackson St San Jose CA 95112",
    "addr:housenumber":"679",
    "addr:postcode":"95112",
    "addr:street":"Jackson St",
    "iso:country":"US",
    "sg:address":"679 Jackson St",
    "sg:city":"San Jose",
    "sg:classifiers":[
        {
            "category":"Shopping",
            "subcategory":"Clothing, Apparel, & Fashions",
            "type":"Retail Goods"
        }
    ],
    "sg:phone":"+1 408 947 7241",
    "sg:postcode":"95112",
    "sg:province":"CA",
    "wof:name":"Nanez Importations",
    "wof:placetype":"venue"
},
  "geometry": {"coordinates":[-121.88479100000001,37.353554],"type":"Point"}
}