{
  "type": "Feature",
  "properties": {
    "iso:country":"US",
    "sg:address":"781 Bolinas Rd",
    "sg:city":"Fairfax",
    "sg:classifiers":[
        {
            "category":"Professional",
            "type":"Services"
        }
    ],
    "sg:phone":"+1 415 459 0455",
    "sg:postcode":"94930",
    "sg:province":"CA",
    "wof:name":"American University For Islami",
    "wof:placetype":"venue"
},
  "geometry": {"coordinates":[-122.60618100000001,37.972842],"type":"Point"}
}