{
  "type": "Feature",
  "properties": {
    "addr:full":"6821 Tujunga Ave North Hollywood CA 91605",
    "addr:housenumber":"6821",
    "addr:postcode":"91605",
    "addr:street":"Tujunga Ave",
    "iso:country":"US",
    "sg:address":"6821 Tujunga Ave",
    "sg:city":"North Hollywood",
    "sg:classifiers":[
        {
            "category":"Professional",
            "subcategory":"Business Services",
            "type":"Services"
        }
    ],
    "sg:phone":"+1 818 761 7793",
    "sg:postcode":"91605",
    "sg:province":"CA",
    "sg:tags":[
        "instrument",
        "teacher",
        "musical"
    ],
    "wof:name":"Music Art Production",
    "wof:placetype":"venue"
},
  "geometry": {"coordinates":[-118.378998,34.194302],"type":"Point"}
}