{
  "type": "Feature",
  "properties": {
    "iso:country":"US",
    "sg:address":"933 S Glendora Ave",
    "sg:city":"West Covina",
    "sg:classifiers":[
        {
            "category":"Government",
            "subcategory":"Office",
            "type":"Public Place"
        }
    ],
    "sg:phone":"+1 626 960 5106",
    "sg:postcode":"91790",
    "sg:province":"CA",
    "sg:tags":[
        "veteran",
        "employment",
        "training"
    ],
    "wof:name":"V E T S Region 6",
    "wof:placetype":"venue"
},
  "geometry": {"coordinates":[-117.935031,34.058625],"type":"Point"}
}