{
  "type": "Feature",
  "properties": {
    "iso:country":"US",
    "sg:address":"19626 Ventura Blvd",
    "sg:city":"Tarzana",
    "sg:classifiers":[
        {
            "category":"Shopping",
            "subcategory":"Mobile Phones",
            "type":"Retail Goods"
        }
    ],
    "sg:phone":"+1 818 343 8106",
    "sg:postcode":"91356",
    "sg:province":"CA",
    "wof:name":"N E P",
    "wof:placetype":"venue"
},
  "geometry": {"coordinates":[-118.560997,34.172699],"type":"Point"}
}