{
  "type": "Feature",
  "properties": {
    "iso:country":"US",
    "sg:address":"329 E Main St",
    "sg:city":"Visalia",
    "sg:classifiers":[
        {
            "category":"Shopping",
            "subcategory":"Party Supplies",
            "type":"Retail Goods"
        }
    ],
    "sg:phone":"+1 559 738 0577",
    "sg:postcode":"93291",
    "sg:province":"CA",
    "sg:tags":[
        "delivery",
        "balloons-retail"
    ],
    "wof:name":"Chavez Balloons",
    "wof:placetype":"venue"
},
  "geometry": {"coordinates":[-119.289759,36.33017],"type":"Point"}
}