{
  "type": "Feature",
  "properties": {
    "iso:country":"US",
    "sg:address":"1428 E Denni St",
    "sg:city":"Wilmington",
    "sg:classifiers":[
        {
            "category":"Professional",
            "subcategory":"Detective & Security Services",
            "type":"Services"
        }
    ],
    "sg:phone":"+1 310 549 2569",
    "sg:postcode":"90744",
    "sg:province":"CA",
    "sg:tags":[
        "information",
        "bureau"
    ],
    "wof:name":"Lky Building Services",
    "wof:placetype":"venue"
},
  "geometry": {"coordinates":[-118.246017,33.785321],"type":"Point"}
}