{
  "type": "Feature",
  "properties": {
    "addr:full":"15723 Foothill Blvd Fontana CA 92335",
    "addr:housenumber":"15723",
    "addr:postcode":"92335",
    "addr:street":"Foothill Blvd",
    "iso:country":"US",
    "sg:address":"15723 Foothill Blvd",
    "sg:city":"Fontana",
    "sg:classifiers":[
        {
            "category":"Freight",
            "type":"Transportation"
        }
    ],
    "sg:phone":"+1 909 822 1677",
    "sg:postcode":"92335",
    "sg:province":"CA",
    "sg:tags":[
        "commercial",
        "storage",
        "general"
    ],
    "wof:name":"Storemore Self Storage",
    "wof:placetype":"venue"
},
  "geometry": {"coordinates":[-117.46225099999999,34.106461],"type":"Point"}
}