{
  "type": "Feature",
  "properties": {
    "iso:country":"US",
    "sg:address":"60 E J St",
    "sg:city":"Chula Vista",
    "sg:classifiers":[
        {
            "category":"Personal",
            "subcategory":"Beauty Salon",
            "type":"Services"
        }
    ],
    "sg:phone":"+1 619 476 8778",
    "sg:postcode":"91910",
    "sg:province":"CA",
    "wof:name":"Marsha & Hilda",
    "wof:placetype":"venue"
},
  "geometry": {"coordinates":[-117.060649,32.63126],"type":"Point"}
}