{
  "type": "Feature",
  "properties": {
    "iso:country":"US",
    "sg:address":"2650 Via De La Valle",
    "sg:city":"Del Mar",
    "sg:classifiers":[
        {
            "category":"Restaurant",
            "type":"Food & Drink"
        }
    ],
    "sg:phone":"+1 858 481 7171",
    "sg:postcode":"92014",
    "sg:province":"CA",
    "sg:tags":[
        "italian",
        "pizza"
    ],
    "sg:website":"www.papachinos.com/",
    "wof:name":"Papachino's Ristorante",
    "wof:placetype":"venue"
},
  "geometry": {"coordinates":[-117.24900100000001,32.980801],"type":"Point"}
}