{
  "type": "Feature",
  "properties": {
    "addr:full":"1519 Brandywine Rd San Mateo CA 94402",
    "addr:housenumber":"1519",
    "addr:postcode":"94402",
    "addr:street":"Brandywine Rd",
    "iso:country":"US",
    "sg:address":"1519 Brandywine Rd",
    "sg:city":"San Mateo",
    "sg:classifiers":[
        {
            "category":"Professional",
            "type":"Services"
        }
    ],
    "sg:phone":"+1 650 571 8545",
    "sg:postcode":"94402",
    "sg:province":"CA",
    "sg:tags":[
        "establishment"
    ],
    "wof:name":"Ozonair",
    "wof:placetype":"venue"
},
  "geometry": {"coordinates":[-122.350576,37.528156],"type":"Point"}
}