{
  "type": "Feature",
  "properties": {
    "addr:full":"2528 E 125th St Compton CA 90222",
    "addr:housenumber":"2528",
    "addr:postcode":"90222",
    "addr:street":"E 125Th St",
    "iso:country":"US",
    "sg:address":"2528 E 125th St",
    "sg:city":"Compton",
    "sg:classifiers":[
        {
            "category":"Building & Trades",
            "subcategory":"Construction",
            "type":"Services"
        },
        {
            "category":"Mining & Drilling",
            "type":"Manufacturing & Wholesale Goods"
        }
    ],
    "sg:phone":"+1 310 635 3277",
    "sg:postcode":"90222",
    "sg:province":"CA",
    "sg:tags":[
        "company",
        "contractor"
    ],
    "wof:name":"Alameda Construction Services",
    "wof:placetype":"venue"
},
  "geometry": {"coordinates":[-118.223958,33.918918],"type":"Point"}
}