{
  "type": "Feature",
  "properties": {
    "addr:full":"23815 Neitzelt St Perris CA 92570",
    "addr:postcode":"23815;92570",
    "addr:street":"Neitzelt St",
    "iso:country":"US",
    "sg:address":"23815 Neitzelt St",
    "sg:city":"Perris",
    "sg:classifiers":[
        {
            "category":"Retail",
            "subcategory":"Animal Services",
            "type":"Services"
        }
    ],
    "sg:phone":"+1 951 488 0215",
    "sg:postcode":"92570",
    "sg:province":"CA",
    "sg:tags":[
        "pet",
        "grooming",
        "washing"
    ],
    "wof:name":"A Mobile Pet Groomer",
    "wof:placetype":"venue"
},
  "geometry": {"coordinates":[-117.25246,33.774276],"type":"Point"}
}