{
  "type": "Feature",
  "properties": {
    "addr:full":"1427 Abbot Kinney Blvd Venice CA 90291",
    "addr:housenumber":"1427",
    "addr:postcode":"90291",
    "addr:street":"Abbot Kinney Blvd",
    "iso:country":"US",
    "sg:address":"1427 Abbot Kinney Blvd",
    "sg:city":"Venice",
    "sg:classifiers":[
        {
            "category":"Shopping",
            "subcategory":"Used Merchandise",
            "type":"Retail Goods"
        }
    ],
    "sg:phone":"+1 310 392 9905",
    "sg:postcode":"90291",
    "sg:province":"CA",
    "sg:tags":[
        "antique"
    ],
    "wof:name":"French 50's & 60's",
    "wof:placetype":"venue"
},
  "geometry": {"coordinates":[-118.46491,33.990449],"type":"Point"}
}