{
  "type": "Feature",
  "properties": {
    "iso:country":"US",
    "sg:address":"200 N Pacific Coast Hwy",
    "sg:city":"Redondo Beach",
    "sg:classifiers":[
        {
            "category":"Government",
            "subcategory":"Police Station",
            "type":"Public Place"
        }
    ],
    "sg:phone":"+1 310 318 0614",
    "sg:postcode":"90277",
    "sg:province":"CA",
    "sg:tags":[
        "department"
    ],
    "wof:name":"Police-Investigations-Adult",
    "wof:placetype":"venue"
},
  "geometry": {"coordinates":[-118.387254,33.844963],"type":"Point"}
}