{
  "type": "Feature",
  "properties": {
    "addr:full":"13401 Buggy Whip Ct Victorville CA 92392",
    "addr:housenumber":"13401",
    "addr:postcode":"92392",
    "addr:street":"Buggy Whip Ct",
    "iso:country":"US",
    "sg:address":"13401 Buggy Whip Ct",
    "sg:city":"Victorville",
    "sg:classifiers":[
        {
            "category":"Organizations",
            "subcategory":"Religious Organization",
            "type":"Services"
        }
    ],
    "sg:phone":"+1 760 951 0374",
    "sg:postcode":"92392",
    "sg:province":"CA",
    "sg:tags":[
        "church"
    ],
    "sg:website":"www.utahgospelmission.org",
    "wof:name":"Trinity Evangelical Bible",
    "wof:placetype":"venue"
},
  "geometry": {"coordinates":[-117.370357,34.483067],"type":"Point"}
}