{
  "type": "Feature",
  "properties": {
    "addr:full":"10631 Los Alamitos Blvd Los Alamitos CA 90720",
    "addr:housenumber":"10631",
    "addr:postcode":"90720",
    "addr:street":"Los Alamitos Blvd",
    "iso:country":"US",
    "sg:address":"10631 Los Alamitos Blvd",
    "sg:city":"Los Alamitos",
    "sg:classifiers":[
        {
            "category":"Restaurant",
            "type":"Food & Drink"
        }
    ],
    "sg:postcode":"90720",
    "sg:province":"CA",
    "sg:tags":[
        "traditional",
        "american"
    ],
    "sg:website":"www.shenandoahatthearbor.com/ind...",
    "wof:name":"Shenandoah At the Arbors",
    "wof:placetype":"venue"
},
  "geometry": {"coordinates":[-118.071797,33.808273],"type":"Point"}
}