{
  "type": "Feature",
  "properties": {
    "addr:full":"2000 5th St Berkeley CA 94710",
    "addr:housenumber":"2000",
    "addr:postcode":"94710",
    "addr:street":"5Th St",
    "iso:country":"US",
    "sg:address":"2000 5th St",
    "sg:city":"Berkeley",
    "sg:classifiers":[
        {
            "category":"Banks & Credit Unions",
            "subcategory":"Investment Brokerage",
            "type":"Services"
        }
    ],
    "sg:phone":"+1 510 704 6560",
    "sg:postcode":"94710",
    "sg:province":"CA",
    "wof:name":"Reed Investments",
    "wof:placetype":"venue"
},
  "geometry": {"coordinates":[-122.298812,37.867655],"type":"Point"}
}