{
  "type": "Feature",
  "properties": {
    "iso:country":"US",
    "sg:address":"2000 5th St",
    "sg:city":"Berkeley",
    "sg:classifiers":[
        {
            "category":"Banks & Credit Unions",
            "subcategory":"Investment Brokerage",
            "type":"Services"
        }
    ],
    "sg:phone":"+1 510 704 6560",
    "sg:postcode":"94710",
    "sg:province":"CA",
    "wof:name":"Reed Investments",
    "wof:placetype":"venue"
},
  "geometry": {"coordinates":[-122.298812,37.867655],"type":"Point"}
}