{
  "type": "Feature",
  "properties": {
    "addr:full":"1750 S Pacific Ave San Pedro CA 90731",
    "addr:housenumber":"1750",
    "addr:postcode":"90731",
    "addr:street":"S Pacific Ave",
    "iso:country":"US",
    "sg:address":"1750 S Pacific Ave",
    "sg:city":"San Pedro",
    "sg:classifiers":[
        {
            "category":"Retail",
            "subcategory":"Auto Repair",
            "type":"Services"
        }
    ],
    "sg:phone":"+1 310 833 4188",
    "sg:postcode":"90731",
    "sg:province":"CA",
    "sg:tags":[
        "general",
        "vehicle"
    ],
    "wof:name":"Harbor Auto Repair",
    "wof:placetype":"venue"
},
  "geometry": {"coordinates":[-118.287953,33.728778],"type":"Point"}
}