{
  "type": "Feature",
  "properties": {
    "iso:country":"US",
    "sg:address":"2300 E Katella Ave",
    "sg:city":"Anaheim",
    "sg:classifiers":[
        {
            "category":"Building & Trades",
            "subcategory":"Landscaping Services",
            "type":"Services"
        }
    ],
    "sg:phone":"+1 714 935 2400",
    "sg:postcode":"92867",
    "sg:province":"CA",
    "wof:name":"Goodlooking Gardening Services",
    "wof:placetype":"venue"
},
  "geometry": {"coordinates":[-117.827991,33.810264],"type":"Point"}
}