{
  "type": "Feature",
  "properties": {
    "iso:country":"US",
    "sg:address":"1634 Channing Way",
    "sg:city":"Berkeley",
    "sg:classifiers":[
        {
            "category":"Communications",
            "subcategory":"Film & Video Production",
            "type":"Services"
        }
    ],
    "sg:phone":"+1 510 549 9424",
    "sg:postcode":"94703",
    "sg:province":"CA",
    "sg:tags":[
        "recording",
        "service-sound"
    ],
    "sg:website":"http://www.startupsounds.com",
    "wof:name":"John Swerdan",
    "wof:placetype":"venue"
},
  "geometry": {"coordinates":[-122.277845,37.864456],"type":"Point"}
}