{
  "type": "Feature",
  "properties": {
    "addr:full":"1363 5th Ave San Francisco CA 94122",
    "addr:housenumber":"1363",
    "addr:postcode":"94122",
    "addr:street":"5Th Ave",
    "iso:country":"US",
    "sg:address":"1363 5th Ave",
    "sg:city":"San Francisco",
    "sg:classifiers":[
        {
            "category":"Social Services",
            "subcategory":"Adult Care",
            "type":"Services"
        }
    ],
    "sg:phone":"+1 415 566 4527",
    "sg:postcode":"94122",
    "sg:province":"CA",
    "sg:tags":[
        "home",
        "residential"
    ],
    "wof:name":"Julie's Rest Home",
    "wof:placetype":"venue"
},
  "geometry": {"coordinates":[-122.462041,37.763536],"type":"Point"}
}