{
  "type": "Feature",
  "properties": {
    "iso:country":"US",
    "sg:address":"107 S Fair Oaks Ave Ste 321",
    "sg:city":"Pasadena",
    "sg:classifiers":[
        {
            "category":"Personal",
            "subcategory":"Beauty Salon",
            "type":"Services"
        }
    ],
    "sg:phone":"+1 626 475 3338",
    "sg:postcode":"91105",
    "sg:province":"CA",
    "sg:tags":[
        "makeup",
        "artist"
    ],
    "sg:website":"www.thmakeupdesign.com",
    "wof:name":"Theresa Huang Make-Up & Hair Design",
    "wof:placetype":"venue"
},
  "geometry": {"coordinates":[-118.15075899999999,34.143828],"type":"Point"}
}