{
  "type": "Feature",
  "properties": {
    "iso:country":"US",
    "sg:address":"3710 Robertson Blvd",
    "sg:city":"Culver City",
    "sg:classifiers":[
        {
            "category":"Real Estate",
            "subcategory":"Architect",
            "type":"Services"
        }
    ],
    "sg:phone":"+1 310 838 0466",
    "sg:postcode":"90232",
    "sg:province":"CA",
    "wof:name":"Kevan Lynd",
    "wof:placetype":"venue"
},
  "geometry": {"coordinates":[-118.389901,34.027756],"type":"Point"}
}