{
  "type": "Feature",
  "properties": {
    "iso:country":"US",
    "sg:address":"9910 6th St",
    "sg:city":"Rancho Cucamonga",
    "sg:classifiers":[
        {
            "category":"Wholesale",
            "subcategory":"Metals & Minerals",
            "type":"Manufacturing & Wholesale Goods"
        }
    ],
    "sg:phone":"+1 909 980 1203",
    "sg:postcode":"91730",
    "sg:province":"CA",
    "sg:tags":[
        "aluminum"
    ],
    "wof:name":"Tomra Pacific Inc",
    "wof:placetype":"venue"
},
  "geometry": {"coordinates":[-117.590094,34.084817],"type":"Point"}
}