{
  "type": "Feature",
  "properties": {
    "addr:full":"342 S Cochran Ave Los Angeles CA 90036",
    "addr:housenumber":"342",
    "addr:postcode":"90036",
    "addr:street":"S Cochran Ave",
    "iso:country":"US",
    "sg:address":"342 S Cochran Ave",
    "sg:city":"Los Angeles",
    "sg:classifiers":[
        {
            "category":"Real Estate",
            "subcategory":"Real Estate Operator",
            "type":"Services"
        }
    ],
    "sg:phone":"+1 323 932 0450",
    "sg:postcode":"90036",
    "sg:province":"CA",
    "sg:tags":[
        "apartment"
    ],
    "wof:name":"Cochran Island Apartments",
    "wof:placetype":"venue"
},
  "geometry": {"coordinates":[-118.34699999999999,34.0681],"type":"Point"}
}