{
  "type": "Feature",
  "properties": {
    "iso:country":"US",
    "sg:address":"27907 Smyth Dr",
    "sg:city":"Valencia",
    "sg:classifiers":[
        {
            "category":"Insurance",
            "subcategory":"Insurance Agent",
            "type":"Services"
        }
    ],
    "sg:phone":"+1 661 775 9125",
    "sg:postcode":"91355",
    "sg:province":"CA",
    "sg:tags":[
        "consultant"
    ],
    "sg:website":"www.honiwell.com",
    "wof:name":"Honiwell & Assoc Farmers Ins",
    "wof:placetype":"venue"
},
  "geometry": {"coordinates":[-118.572624,34.443913],"type":"Point"}
}