{
  "type": "Feature",
  "properties": {
    "iso:country":"US",
    "sg:address":"40 Jessie St",
    "sg:city":"San Francisco",
    "sg:classifiers":[
        {
            "category":"Coffee & Tea",
            "type":"Food & Drink"
        },
        {
            "category":"Food & Beverages",
            "subcategory":"Bakery",
            "type":"Retail Goods"
        }
    ],
    "sg:phone":"+1 415 442 7277",
    "sg:postcode":"94105",
    "sg:province":"CA",
    "sg:tags":[
        "sandwich"
    ],
    "wof:name":"Golden Gate University Cafe",
    "wof:placetype":"venue"
},
  "geometry": {"coordinates":[-122.399181,37.789596],"type":"Point"}
}