{
  "type": "Feature",
  "properties": {
    "addr:full":"2730 Wilshire Blvd Santa Monica CA 90403",
    "addr:housenumber":"2730",
    "addr:postcode":"90403",
    "addr:street":"Wilshire Blvd",
    "iso:country":"US",
    "sg:address":"2730 Wilshire Blvd",
    "sg:city":"Santa Monica",
    "sg:classifiers":[
        {
            "category":"Professional",
            "subcategory":"Management & Consulting",
            "type":"Services"
        }
    ],
    "sg:phone":"+1 310 829 9192",
    "sg:postcode":"90403",
    "sg:province":"CA",
    "sg:tags":[
        "consultant",
        "business"
    ],
    "wof:name":"Coaching Education Affliates",
    "wof:placetype":"venue"
},
  "geometry": {"coordinates":[-118.475931,34.03714],"type":"Point"}
}