{
  "type": "Feature",
  "properties": {
    "addr:full":"7444 Reseda Blvd Reseda CA 91335",
    "addr:housenumber":"7444",
    "addr:postcode":"91335",
    "addr:street":"Reseda Blvd",
    "iso:country":"US",
    "sg:address":"7444 Reseda Blvd",
    "sg:city":"Reseda",
    "sg:classifiers":[
        {
            "category":"Retail",
            "subcategory":"Auto Repair",
            "type":"Services"
        }
    ],
    "sg:phone":"+1 818 343 0945",
    "sg:postcode":"91335",
    "sg:province":"CA",
    "sg:tags":[
        "repairing",
        "automobile"
    ],
    "wof:name":"Nissan Independent Repair",
    "wof:placetype":"venue"
},
  "geometry": {"coordinates":[-118.535979,34.205284],"type":"Point"}
}