{
  "type": "Feature",
  "properties": {
    "addr:full":"53 Commerce Pl Vacaville CA 95687",
    "addr:housenumber":"53",
    "addr:postcode":"95687",
    "addr:street":"Commerce Pl",
    "iso:country":"US",
    "sg:address":"53 Commerce Pl",
    "sg:city":"Vacaville",
    "sg:classifiers":[
        {
            "category":"Organizations",
            "subcategory":"Non-profit Organization",
            "type":"Services"
        }
    ],
    "sg:phone":"+1 707 449 1019",
    "sg:postcode":"95687",
    "sg:province":"CA",
    "sg:tags":[
        "disability"
    ],
    "wof:name":"Pace Solano",
    "wof:placetype":"venue"
},
  "geometry": {"coordinates":[-121.936179,38.353204],"type":"Point"}
}