{
  "type": "Feature",
  "properties": {
    "iso:country":"US",
    "sg:address":"820 Clement St",
    "sg:city":"San Francisco",
    "sg:classifiers":[
        {
            "category":"Shopping",
            "subcategory":"Used Merchandise",
            "type":"Retail Goods"
        }
    ],
    "sg:phone":"+1 415 668 3635",
    "sg:postcode":"94118",
    "sg:province":"CA",
    "sg:tags":[
        "shop",
        "thrift"
    ],
    "wof:name":"Goodwill Industries",
    "wof:placetype":"venue"
},
  "geometry": {"coordinates":[-122.468535,37.782836],"type":"Point"}
}