{
  "type": "Feature",
  "properties": {
    "addr:full":"1151 W Mission Blvd Pomona CA 91766",
    "addr:housenumber":"1151",
    "addr:postcode":"91766",
    "addr:street":"W Mission Blvd",
    "iso:country":"US",
    "sg:address":"1151 W Mission Blvd",
    "sg:city":"Pomona",
    "sg:classifiers":[
        {
            "category":"Shopping",
            "subcategory":"Shoes",
            "type":"Retail Goods"
        }
    ],
    "sg:phone":"+1 909 865 9069",
    "sg:postcode":"91766",
    "sg:province":"CA",
    "wof:name":"Zapateria LA Merced",
    "wof:placetype":"venue"
},
  "geometry": {"coordinates":[-117.76440700000001,34.054836],"type":"Point"}
}