{
  "type": "Feature",
  "properties": {
    "iso:country":"US",
    "sg:address":"1680 Vine Street",
    "sg:city":"Los Angeles",
    "sg:classifiers":[
        {
            "category":"Real Estate",
            "subcategory":"Architect",
            "type":"Services"
        }
    ],
    "sg:phone":"+1 323 461 6140",
    "sg:postcode":"90028",
    "sg:province":"CA",
    "wof:name":"Fluidity",
    "wof:placetype":"venue"
},
  "geometry": {"coordinates":[-118.32664800000001,34.101174],"type":"Point"}
}