{
  "type": "Feature",
  "properties": {
    "addr:full":"3739 1st Ave San Diego CA 92103",
    "addr:housenumber":"3739",
    "addr:postcode":"92103",
    "addr:street":"1St Ave",
    "iso:country":"US",
    "sg:address":"3739 1st Ave",
    "sg:city":"San Diego",
    "sg:classifiers":[
        {
            "category":"Professional",
            "type":"Services"
        }
    ],
    "sg:phone":"+1 619 699 8684",
    "sg:postcode":"92103",
    "sg:province":"CA",
    "sg:tags":[
        "establishment"
    ],
    "wof:name":"D Kent & Assoc",
    "wof:placetype":"venue"
},
  "geometry": {"coordinates":[-117.163805,32.746228],"type":"Point"}
}