{
  "type": "Feature",
  "properties": {
    "addr:full":"537 24th St Oakland CA 94612",
    "addr:housenumber":"537",
    "addr:postcode":"94612",
    "addr:street":"24Th St",
    "iso:country":"US",
    "sg:address":"537 24th St",
    "sg:city":"Oakland",
    "sg:classifiers":[
        {
            "category":"Personal",
            "type":"Services"
        }
    ],
    "sg:phone":"+1 510 444 2020",
    "sg:postcode":"94612",
    "sg:province":"CA",
    "sg:tags":[
        "towing"
    ],
    "wof:name":"Jenkin Bros Acme Towing Service Inc",
    "wof:placetype":"venue"
},
  "geometry": {"coordinates":[-122.268997,37.813499],"type":"Point"}
}