{
  "type": "Feature",
  "properties": {
    "addr:full":"9261 Survey Rd Elk Grove CA 95624",
    "addr:housenumber":"9261",
    "addr:postcode":"95624",
    "addr:street":"Survey Rd",
    "iso:country":"US",
    "sg:address":"9261 Survey Rd",
    "sg:city":"Elk Grove",
    "sg:classifiers":[
        {
            "category":"Building & Trades",
            "subcategory":"Landscaping Services",
            "type":"Services"
        }
    ],
    "sg:phone":"+1 916 423 4620",
    "sg:postcode":"95624",
    "sg:province":"CA",
    "sg:tags":[
        "landscape",
        "contractor"
    ],
    "wof:name":"Salens Landscaping Inc",
    "wof:placetype":"venue"
},
  "geometry": {"coordinates":[-121.357068,38.377365],"type":"Point"}
}