{
  "type": "Feature",
  "properties": {
    "addr:full":"1281 Talmage Rd Ukiah CA 95482",
    "addr:housenumber":"1281",
    "addr:postcode":"ca 95482",
    "addr:street":"Talmage Rd",
    "iso:country":"US",
    "sg:address":"1281 Talmage Rd",
    "sg:city":"Ukiah",
    "sg:classifiers":[
        {
            "category":"Food & Beverages",
            "subcategory":"Specialty",
            "type":"Retail Goods"
        }
    ],
    "sg:phone":"+1 707 463 2310",
    "sg:postcode":"95482",
    "sg:province":"CA",
    "sg:tags":[
        "american",
        "latin",
        "mexican",
        "product"
    ],
    "wof:name":"Tortilleria Barron",
    "wof:placetype":"venue"
},
  "geometry": {"coordinates":[-123.18033800000001,39.13302],"type":"Point"}
}