{
  "type": "Feature",
  "properties": {
    "iso:country":"US",
    "sg:address":"6272 Van Buren Blvd",
    "sg:city":"Riverside",
    "sg:classifiers":[
        {
            "category":"Home & Garden",
            "subcategory":"Household Appliances",
            "type":"Retail Goods"
        }
    ],
    "sg:phone":"+1 951 359 4661",
    "sg:postcode":"92503",
    "sg:province":"CA",
    "wof:name":"Sub-Zero Refrigerators & Frzrs",
    "wof:placetype":"venue"
},
  "geometry": {"coordinates":[-117.453983,33.943758],"type":"Point"}
}