{
  "type": "Feature",
  "properties": {
    "addr:full":"12350 California St Yucaipa CA 92399",
    "addr:housenumber":"12350",
    "addr:postcode":"92399",
    "addr:street":"California St",
    "iso:country":"US",
    "sg:address":"12350 California St",
    "sg:city":"Yucaipa",
    "sg:classifiers":[
        {
            "category":"Wholesale",
            "subcategory":"Stationery",
            "type":"Manufacturing & Wholesale Goods"
        },
        {
            "category":"Shopping",
            "subcategory":"Pharmacy",
            "type":"Retail Goods"
        }
    ],
    "sg:phone":"+1 909 797 9191",
    "sg:postcode":"92399",
    "sg:province":"CA",
    "sg:tags":[
        "drugstore",
        "card"
    ],
    "wof:name":"Sail Discount Drug Centers",
    "wof:placetype":"venue"
},
  "geometry": {"coordinates":[-117.039001,34.029701],"type":"Point"}
}