{
  "type": "Feature",
  "properties": {
    "iso:country":"US",
    "sg:address":"8731 La Tijera Blvd",
    "sg:city":"Los Angeles",
    "sg:classifiers":[
        {
            "category":"Personal",
            "subcategory":"Hair Removal",
            "type":"Services"
        }
    ],
    "sg:phone":"+1 310 704 3857",
    "sg:postcode":"90045",
    "sg:province":"CA",
    "wof:name":"Kristine McDougle Electrolysis",
    "wof:placetype":"venue"
},
  "geometry": {"coordinates":[-118.393891,33.957652],"type":"Point"}
}