{
  "type": "Feature",
  "properties": {
    "addr:full":"455 Reservation Rd Ste H Marina CA 93933",
    "addr:housenumber":"455",
    "addr:postcode":"93933",
    "addr:street":"Reservation Rd Ste H",
    "iso:country":"US",
    "sg:address":"455 Reservation Rd Ste H",
    "sg:city":"Marina",
    "sg:classifiers":[
        {
            "category":"Manufacturing",
            "subcategory":"Food",
            "type":"Manufacturing & Wholesale Goods"
        },
        {
            "category":"Restaurant",
            "type":"Food & Drink"
        },
        {
            "category":"Food & Beverages",
            "subcategory":"Groceries & Convenience Stores",
            "type":"Retail Goods"
        }
    ],
    "sg:phone":"+1 831 883 9631",
    "sg:postcode":"93933",
    "sg:province":"CA",
    "sg:tags":[
        "pasta",
        "product",
        "italian"
    ],
    "wof:name":"Pensi Pasta",
    "wof:placetype":"venue"
},
  "geometry": {"coordinates":[-121.781598,36.679031],"type":"Point"}
}