{
  "type": "Feature",
  "properties": {
    "addr:full":"771 W Foothill Blvd Upland CA 91786",
    "addr:housenumber":"771",
    "addr:postcode":"91786",
    "addr:street":"W Foothill Blvd",
    "iso:country":"US",
    "sg:address":"771 W Foothill Blvd",
    "sg:city":"Upland",
    "sg:classifiers":[
        {
            "category":"Retail",
            "subcategory":"Repair Shop",
            "type":"Services"
        }
    ],
    "sg:phone":"+1 909 949 1777",
    "sg:postcode":"91786",
    "sg:province":"CA",
    "wof:name":"Big Screen Specialists",
    "wof:placetype":"venue"
},
  "geometry": {"coordinates":[-117.660139,34.10706],"type":"Point"}
}