{
  "type": "Feature",
  "properties": {
    "addr:full":"14852 Pipeline Ave Chino Hills CA 91710",
    "addr:housenumber":"14852",
    "addr:postcode":"91710",
    "addr:street":"Pipeline Ave",
    "iso:country":"US",
    "sg:address":"14852 Pipeline Ave",
    "sg:city":"Chino Hills",
    "sg:classifiers":[
        {
            "category":"Professional",
            "subcategory":"Computer Services",
            "type":"Services"
        }
    ],
    "sg:phone":"+1 909 597 9497",
    "sg:postcode":"91710",
    "sg:province":"CA",
    "sg:tags":[
        "repair"
    ],
    "wof:name":"Quality Plus Computer",
    "wof:placetype":"venue"
},
  "geometry": {"coordinates":[-117.715118,33.985241],"type":"Point"}
}