{
  "type": "Feature",
  "properties": {
    "addr:full":"4875 Mowry Ave Fremont CA 94538",
    "addr:housenumber":"4875",
    "addr:postcode":"94538",
    "addr:street":"Mowry Ave",
    "iso:country":"US",
    "sg:address":"4875 Mowry Ave",
    "sg:city":"Fremont",
    "sg:classifiers":[
        {
            "category":"Travel",
            "subcategory":"Travel Agent",
            "type":"Entertainment"
        }
    ],
    "sg:phone":"+1 510 505 0108",
    "sg:postcode":"94538",
    "sg:province":"CA",
    "sg:tags":[
        "agency",
        "bureau"
    ],
    "wof:name":"Worldwide Travel Inc",
    "wof:placetype":"venue"
},
  "geometry": {"coordinates":[-121.998463,37.536556],"type":"Point"}
}