{
  "type": "Feature",
  "properties": {
    "addr:full":"7 S Wood St Salinas CA 93905",
    "addr:housenumber":"7",
    "addr:postcode":"93905",
    "addr:street":"S Wood St",
    "iso:country":"US",
    "sg:address":"7 S Wood St",
    "sg:city":"Salinas",
    "sg:classifiers":[
        {
            "category":"Personal",
            "subcategory":"Beauty Salon",
            "type":"Services"
        }
    ],
    "sg:phone":"+1 831 422 2504",
    "sg:postcode":"93905",
    "sg:province":"CA",
    "wof:name":"Elva's Beauty Salon",
    "wof:placetype":"venue"
},
  "geometry": {"coordinates":[-121.635583,36.672883],"type":"Point"}
}