{
  "type": "Feature",
  "properties": {
    "addr:full":"2659 Portage Bay E Davis CA 95616",
    "addr:housenumber":"2659",
    "addr:postcode":"95616",
    "addr:street":"Portage Bay E",
    "iso:country":"US",
    "sg:address":"2659 Portage Bay E",
    "sg:city":"Davis",
    "sg:classifiers":[
        {
            "category":"Professional",
            "subcategory":"Computer Services",
            "type":"Services"
        }
    ],
    "sg:phone":"+1 530 297 7917",
    "sg:postcode":"95616",
    "sg:province":"CA",
    "wof:name":"Corbett Learning Media",
    "wof:placetype":"venue"
},
  "geometry": {"coordinates":[-121.784993,38.548332],"type":"Point"}
}