{
  "type": "Feature",
  "properties": {
    "iso:country":"US",
    "sg:address":"46365 W Panoche Rd",
    "sg:city":"Firebaugh",
    "sg:classifiers":[
        {
            "category":"Autos & Motor Vehicles",
            "subcategory":"Fuel & Gas Station",
            "type":"Retail Goods"
        }
    ],
    "sg:phone":"+1 559 659 0171",
    "sg:postcode":"93622",
    "sg:province":"CA",
    "sg:tags":[
        "oil"
    ],
    "wof:name":"Panoche Mobil",
    "wof:placetype":"venue"
},
  "geometry": {"coordinates":[-120.626332,36.638041],"type":"Point"}
}