{
  "type": "Feature",
  "properties": {
    "iso:country":"US",
    "sg:address":"15011 E Badillo St",
    "sg:city":"Baldwin Park",
    "sg:classifiers":[
        {
            "category":"Wholesale",
            "subcategory":"Groceries",
            "type":"Manufacturing & Wholesale Goods"
        }
    ],
    "sg:phone":"+1 626 813 1006",
    "sg:postcode":"91706",
    "sg:province":"CA",
    "sg:tags":[
        "tea",
        "coffee"
    ],
    "wof:name":"Tropical Fine Wholesale Coffee",
    "wof:placetype":"venue"
},
  "geometry": {"coordinates":[-117.951577,34.087394],"type":"Point"}
}