{
  "type": "Feature",
  "properties": {
    "addr:full":"3275 Salvatore Ln Stockton CA 95212",
    "addr:housenumber":"3275",
    "addr:postcode":"95212",
    "addr:street":"Salvatore Ln",
    "iso:country":"US",
    "sg:address":"3275 Salvatore Ln",
    "sg:city":"Stockton",
    "sg:classifiers":[
        {
            "category":"Building & Trades",
            "subcategory":"Construction",
            "type":"Services"
        }
    ],
    "sg:phone":"+1 209 952 9864",
    "sg:postcode":"95212",
    "sg:province":"CA",
    "sg:tags":[
        "home",
        "builder"
    ],
    "wof:name":"Meritage Homes Sterling Wllws",
    "wof:placetype":"venue"
},
  "geometry": {"coordinates":[-121.274134,38.040493],"type":"Point"}
}