{
  "type": "Feature",
  "properties": {
    "iso:country":"US",
    "sg:address":"351 Tres Pinos Rd",
    "sg:city":"Hollister",
    "sg:classifiers":[
        {
            "category":"Banks & Credit Unions",
            "subcategory":"Bank",
            "type":"Services"
        }
    ],
    "sg:phone":"+1 831 638 1276",
    "sg:postcode":"95023",
    "sg:province":"CA",
    "sg:tags":[
        "saving",
        "commercial"
    ],
    "wof:name":"Rabobank",
    "wof:placetype":"venue"
},
  "geometry": {"coordinates":[-121.394553,36.839448],"type":"Point"}
}