{
  "type": "Feature",
  "properties": {
    "addr:full":"5059 Fallhaven Ln La Canada Flintridge CA 91011",
    "addr:housenumber":"5059",
    "addr:postcode":"91011",
    "addr:street":"Fallhaven Ln",
    "iso:country":"US",
    "sg:address":"5059 Fallhaven Ln",
    "sg:city":"La Canada Flintridge",
    "sg:classifiers":[
        {
            "category":"Wholesale",
            "subcategory":"Toys & Hobbies",
            "type":"Manufacturing & Wholesale Goods"
        }
    ],
    "sg:phone":"+1 818 790 6420",
    "sg:postcode":"91011",
    "sg:province":"CA",
    "wof:name":"Girl In Lane",
    "wof:placetype":"venue"
},
  "geometry": {"coordinates":[-118.196789,34.213111],"type":"Point"}
}