{
  "type": "Feature",
  "properties": {
    "addr:full":"4912 Harwick Pl San Diego CA 92130",
    "addr:housenumber":"4912",
    "addr:postcode":"92130",
    "addr:street":"Harwick Pl",
    "iso:country":"US",
    "sg:address":"4912 Harwick Pl",
    "sg:city":"San Diego",
    "sg:classifiers":[
        {
            "category":"Real Estate",
            "subcategory":"Real Estate Agent",
            "type":"Services"
        }
    ],
    "sg:phone":"+1 858 847 3286",
    "sg:postcode":"92130",
    "sg:province":"CA",
    "wof:name":"B L T Ventures LLC",
    "wof:placetype":"venue"
},
  "geometry": {"coordinates":[-117.21146,32.955171],"type":"Point"}
}