{
  "type": "Feature",
  "properties": {
    "addr:full":"4060 Douglas Blvd Granite Bay CA 95746",
    "addr:housenumber":"4060",
    "addr:postcode":"95746",
    "addr:street":"Douglas Blvd",
    "iso:country":"US",
    "sg:address":"4060 Douglas Blvd",
    "sg:city":"Granite Bay",
    "sg:classifiers":[
        {
            "category":"Health Services",
            "subcategory":"Doctor",
            "type":"Services"
        }
    ],
    "sg:phone":"+1 916 789 2273",
    "sg:postcode":"95746",
    "sg:province":"CA",
    "sg:tags":[
        "dentist"
    ],
    "wof:name":"Granite Dental Care",
    "wof:placetype":"venue"
},
  "geometry": {"coordinates":[-121.224433,38.743699],"type":"Point"}
}