{
  "type": "Feature",
  "properties": {
    "iso:country":"US",
    "sg:address":"429 E March Ln",
    "sg:city":"Stockton",
    "sg:classifiers":[
        {
            "category":"Autos & Motor Vehicles",
            "subcategory":"Auto Supplies",
            "type":"Retail Goods"
        }
    ],
    "sg:phone":"+1 209 475 9111",
    "sg:postcode":"95207",
    "sg:province":"CA",
    "sg:tags":[
        "equipment",
        "racing",
        "car",
        "automobile"
    ],
    "wof:name":"Autosport Addiction",
    "wof:placetype":"venue"
},
  "geometry": {"coordinates":[-121.3028,37.998161],"type":"Point"}
}