{
  "type": "Feature",
  "properties": {
    "addr:full":"14415 S Main St Gardena CA 90248",
    "addr:housenumber":"14415",
    "addr:postcode":"90248",
    "addr:street":"S Main St",
    "iso:country":"US",
    "sg:address":"14415 S Main St",
    "sg:city":"Gardena",
    "sg:classifiers":[
        {
            "category":"Wholesale",
            "subcategory":"Durable Goods & Equipment",
            "type":"Manufacturing & Wholesale Goods"
        }
    ],
    "sg:phone":"+1 310 516 6799",
    "sg:postcode":"90248",
    "sg:province":"CA",
    "sg:tags":[
        "importer"
    ],
    "wof:name":"Transat Trade Co",
    "wof:placetype":"venue"
},
  "geometry": {"coordinates":[-118.274086,33.899718],"type":"Point"}
}