{
  "type": "Feature",
  "properties": {
    "iso:country":"US",
    "sg:address":"330 Main St",
    "sg:city":"Seal Beach",
    "sg:classifiers":[
        {
            "category":"Shopping",
            "subcategory":"Bicycles & Sporting Goods",
            "type":"Retail Goods"
        }
    ],
    "sg:phone":"+1 562 431 1010",
    "sg:postcode":"90740",
    "sg:province":"CA",
    "wof:name":"A S",
    "wof:placetype":"venue"
},
  "geometry": {"coordinates":[-118.10291599999999,33.743759],"type":"Point"}
}