{
  "type": "Feature",
  "properties": {
    "iso:country":"US",
    "sg:address":"2407 Coldwater Canyon Dr",
    "sg:city":"Beverly Hills",
    "sg:classifiers":[
        {
            "category":"Shopping",
            "type":"Retail Goods"
        }
    ],
    "sg:phone":"+1 310 271 1813",
    "sg:postcode":"90210",
    "sg:province":"CA",
    "sg:tags":[
        "art",
        "gallery",
        "dealer"
    ],
    "wof:name":"Executive Trading Co",
    "wof:placetype":"venue"
},
  "geometry": {"coordinates":[-118.40361799999999,34.118631],"type":"Point"}
}