{
  "type": "Feature",
  "properties": {
    "addr:full":"51 S Ventu Park Rd Newbury Park CA 91320",
    "addr:housenumber":"51",
    "addr:postcode":"91320",
    "addr:street":"S Ventu Park Rd",
    "iso:country":"US",
    "sg:address":"51 S Ventu Park Rd",
    "sg:city":"Newbury Park",
    "sg:classifiers":[
        {
            "category":"Museum",
            "type":"Entertainment"
        }
    ],
    "sg:phone":"+1 805 498 9441",
    "sg:postcode":"91320",
    "sg:province":"CA",
    "wof:name":"Stagecoach Inn Museum",
    "wof:placetype":"venue"
},
  "geometry": {"coordinates":[-118.91097499999999,34.175841],"type":"Point"}
}