{
  "type": "Feature",
  "properties": {
    "addr:full":"6891 Lindale Dr Sacramento CA 95828",
    "addr:housenumber":"6891",
    "addr:postcode":"95828",
    "addr:street":"Lindale Dr",
    "iso:country":"US",
    "sg:address":"6891 Lindale Dr",
    "sg:city":"Sacramento",
    "sg:classifiers":[
        {
            "category":"Banks & Credit Unions",
            "subcategory":"Bank",
            "type":"Services"
        }
    ],
    "sg:phone":"+1 916 393 9580",
    "sg:postcode":"95828",
    "sg:province":"CA",
    "sg:tags":[
        "loan",
        "real estate"
    ],
    "wof:name":"Greater Valley Mortgage",
    "wof:placetype":"venue"
},
  "geometry": {"coordinates":[-121.427007,38.498939],"type":"Point"}
}