{
  "type": "Feature",
  "properties": {
    "addr:full":"62 Hattie St San Francisco CA 94114",
    "addr:housenumber":"62",
    "addr:postcode":"94114",
    "addr:street":"Hattie St",
    "iso:country":"US",
    "sg:address":"62 Hattie St",
    "sg:city":"San Francisco",
    "sg:classifiers":[
        {
            "category":"Personal",
            "subcategory":"Barber",
            "type":"Services"
        }
    ],
    "sg:phone":"+1 415 621 2220",
    "sg:postcode":"94114",
    "sg:province":"CA",
    "wof:name":"Shear Madness",
    "wof:placetype":"venue"
},
  "geometry": {"coordinates":[-122.44099,37.760948],"type":"Point"}
}