{
  "type": "Feature",
  "properties": {
    "addr:full":"779 Newton Way Costa Mesa CA 92627",
    "addr:housenumber":"779",
    "addr:postcode":"92627",
    "addr:street":"Newton Way",
    "iso:country":"US",
    "sg:address":"779 Newton Way",
    "sg:city":"Costa Mesa",
    "sg:classifiers":[
        {
            "category":"Building & Trades",
            "subcategory":"Construction",
            "type":"Services"
        }
    ],
    "sg:phone":"+1 949 631 3022",
    "sg:postcode":"92627",
    "sg:province":"CA",
    "sg:tags":[
        "home",
        "improvement"
    ],
    "wof:name":"Man De Villa",
    "wof:placetype":"venue"
},
  "geometry": {"coordinates":[-117.930645,33.63741],"type":"Point"}
}