{
  "type": "Feature",
  "properties": {
    "iso:country":"US",
    "sg:address":"280 E Palm Ave",
    "sg:city":"Burbank",
    "sg:classifiers":[
        {
            "category":"Shopping",
            "subcategory":"Computers & Home Electronics",
            "type":"Retail Goods"
        }
    ],
    "sg:phone":"+1 323 874 6688",
    "sg:postcode":"91502",
    "sg:province":"CA",
    "wof:name":"Ntv Los Angeles",
    "wof:placetype":"venue"
},
  "geometry": {"coordinates":[-118.308998,34.183399],"type":"Point"}
}