{
  "type": "Feature",
  "properties": {
    "iso:country":"US",
    "sg:address":"1015 1st St",
    "sg:city":"Benicia",
    "sg:classifiers":[
        {
            "category":"Real Estate",
            "subcategory":"Real Estate Services",
            "type":"Services"
        }
    ],
    "sg:phone":"+1 707 745 6300",
    "sg:postcode":"94510",
    "sg:province":"CA",
    "sg:tags":[
        "company",
        "title"
    ],
    "wof:name":"Placer Title Co",
    "wof:placetype":"venue"
},
  "geometry": {"coordinates":[-122.156364,38.052968],"type":"Point"}
}