{
  "type": "Feature",
  "properties": {
    "addr:full":"1485 Armstrong Ave San Francisco CA 94124",
    "addr:housenumber":"1485",
    "addr:postcode":"94124",
    "addr:street":"Armstrong Ave",
    "iso:country":"US",
    "sg:address":"1485 Armstrong Ave",
    "sg:city":"San Francisco",
    "sg:classifiers":[
        {
            "category":"Building & Trades",
            "subcategory":"Construction",
            "type":"Services"
        }
    ],
    "sg:phone":"+1 415 671 1070",
    "sg:postcode":"94124",
    "sg:province":"CA",
    "sg:tags":[
        "roofing",
        "contractor"
    ],
    "wof:name":"Pioneer Roofing",
    "wof:placetype":"venue"
},
  "geometry": {"coordinates":[-122.389141,37.724192],"type":"Point"}
}