{
  "type": "Feature",
  "properties": {
    "iso:country":"US",
    "sg:address":"7222 Pacific Blvd",
    "sg:city":"Huntington Park",
    "sg:classifiers":[
        {
            "category":"Wholesale",
            "subcategory":"Durable Goods & Equipment",
            "type":"Manufacturing & Wholesale Goods"
        }
    ],
    "sg:phone":"+1 323 585 4381",
    "sg:postcode":"90255",
    "sg:province":"CA",
    "wof:name":"Mil Fiestas Party Supply",
    "wof:placetype":"venue"
},
  "geometry": {"coordinates":[-118.22515199999999,33.97354],"type":"Point"}
}