{
  "type": "Feature",
  "properties": {
    "addr:full":"46 Hahnemann Ln Napa CA 94558",
    "addr:housenumber":"46",
    "addr:postcode":"94558",
    "addr:street":"Hahnemann Ln",
    "iso:country":"US",
    "sg:address":"46 Hahnemann Ln",
    "sg:city":"Napa",
    "sg:classifiers":[
        {
            "category":"Manufacturing",
            "subcategory":"Apparel",
            "type":"Manufacturing & Wholesale Goods"
        }
    ],
    "sg:phone":"+1 707 529 7624",
    "sg:postcode":"94558",
    "sg:province":"CA",
    "sg:tags":[
        "sewing",
        "contractor"
    ],
    "wof:name":"Debi Rose Media",
    "wof:placetype":"venue"
},
  "geometry": {"coordinates":[-122.32696799999999,38.336371],"type":"Point"}
}