{
  "type": "Feature",
  "properties": {
    "iso:country":"US",
    "sg:address":"715 2nd St",
    "sg:city":"Fairfield",
    "sg:classifiers":[
        {
            "category":"Shopping",
            "type":"Retail Goods"
        }
    ],
    "sg:phone":"+1 707 425 6309",
    "sg:postcode":"94533",
    "sg:province":"CA",
    "sg:tags":[
        "trophy",
        "medal",
        "award"
    ],
    "wof:name":"A & M Awards",
    "wof:placetype":"venue"
},
  "geometry": {"coordinates":[-122.055263,38.249772],"type":"Point"}
}