{
  "type": "Feature",
  "properties": {
    "iso:country":"US",
    "sg:address":"14944 Camden Ave",
    "sg:city":"San Jose",
    "sg:classifiers":[
        {
            "category":"Food & Beverages",
            "subcategory":"Bakery",
            "type":"Retail Goods"
        }
    ],
    "sg:phone":"+1 408 371 3352",
    "sg:postcode":"95124",
    "sg:province":"CA",
    "sg:tags":[
        "sandwich"
    ],
    "sg:website":"www.togos.com",
    "wof:name":"Togo's",
    "wof:placetype":"venue"
},
  "geometry": {"coordinates":[-121.92800099999999,37.259201],"type":"Point"}
}