{
  "type": "Feature",
  "properties": {
    "iso:country":"US",
    "sg:address":"5921 Windy Ridge Rd",
    "sg:city":"Shingle Springs",
    "sg:classifiers":[
        {
            "category":"Building & Trades",
            "subcategory":"Construction",
            "type":"Services"
        }
    ],
    "sg:phone":"+1 530 677 1495",
    "sg:postcode":"95682",
    "sg:province":"CA",
    "sg:tags":[
        "contractor"
    ],
    "wof:name":"Phil Foster Painting",
    "wof:placetype":"venue"
},
  "geometry": {"coordinates":[-120.894367,38.636297],"type":"Point"}
}