{
  "type": "Feature",
  "properties": {
    "iso:country":"US",
    "sg:address":"2422 Rosemead Blvd",
    "sg:city":"South El Monte",
    "sg:classifiers":[
        {
            "category":"Wholesale",
            "subcategory":"Apparel",
            "type":"Manufacturing & Wholesale Goods"
        }
    ],
    "sg:phone":"+1 626 443 2333",
    "sg:postcode":"91733",
    "sg:province":"CA",
    "sg:tags":[
        "lingerie"
    ],
    "sg:website":"www.ladymateusa.com",
    "wof:name":"Ladymate Inc",
    "wof:placetype":"venue"
},
  "geometry": {"coordinates":[-118.064127,34.055467],"type":"Point"}
}