{
  "type": "Feature",
  "properties": {
    "addr:full":"636 State St Santa Barbara CA 93101",
    "addr:housenumber":"636",
    "addr:postcode":"93101",
    "addr:street":"State St",
    "iso:country":"US",
    "sg:address":"636 State St",
    "sg:city":"Santa Barbara",
    "sg:classifiers":[
        {
            "category":"Food & Beverages",
            "subcategory":"Groceries & Convenience Stores",
            "type":"Retail Goods"
        }
    ],
    "sg:phone":"+1 805 962 6815",
    "sg:postcode":"93101",
    "sg:province":"CA",
    "sg:tags":[
        "grocer"
    ],
    "wof:name":"Italian & Greek Delicatessen",
    "wof:placetype":"venue"
},
  "geometry": {"coordinates":[-119.69760599999999,34.418378],"type":"Point"}
}