{
  "type": "Feature",
  "properties": {
    "addr:full":"3425 25th St San Francisco CA 94110",
    "addr:housenumber":"3425",
    "addr:postcode":"94110",
    "addr:street":"25Th St",
    "iso:country":"US",
    "sg:address":"3425 25th St",
    "sg:city":"San Francisco",
    "sg:classifiers":[
        {
            "category":"Insurance",
            "subcategory":"Hazard Insurance",
            "type":"Services"
        },
        {
            "category":"Banks & Credit Unions",
            "subcategory":"Bank",
            "type":"Services"
        }
    ],
    "sg:phone":"+1 415 647 9900",
    "sg:postcode":"94110",
    "sg:province":"CA",
    "sg:website":"www.davidchacon.com/",
    "wof:name":"David Chacon - State Farm Insurance",
    "wof:placetype":"venue"
},
  "geometry": {"coordinates":[-122.418859,37.750597],"type":"Point"}
}