{
  "type": "Feature",
  "properties": {
    "addr:full":"227 Broadway Ste 302 Santa Monica CA 90401",
    "addr:housenumber":"227",
    "addr:postcode":"90401",
    "addr:street":"Broadway Ste 302",
    "iso:country":"US",
    "sg:address":"227 Broadway Ste 302",
    "sg:city":"Santa Monica",
    "sg:classifiers":[
        {
            "category":"Shopping",
            "subcategory":"Pharmacy",
            "type":"Retail Goods"
        }
    ],
    "sg:phone":"+1 310 395 6374",
    "sg:postcode":"90401",
    "sg:province":"CA",
    "sg:tags":[
        "drugstore"
    ],
    "wof:name":"Natural Health Pharmaceuticals",
    "wof:placetype":"venue"
},
  "geometry": {"coordinates":[-118.49509399999999,34.403663],"type":"Point"}
}