{
  "type": "Feature",
  "properties": {
    "iso:country":"US",
    "sg:address":"7500 Santa Monica Blvd",
    "sg:city":"Los Angeles",
    "sg:classifiers":[
        {
            "category":"Wholesale",
            "subcategory":"Auto Parts",
            "type":"Manufacturing & Wholesale Goods"
        }
    ],
    "sg:phone":"+1 323 581 2096",
    "sg:postcode":"90046",
    "sg:province":"CA",
    "wof:name":"Peters Auto Body & Parts",
    "wof:placetype":"venue"
},
  "geometry": {"coordinates":[-118.354286,34.090773],"type":"Point"}
}