{
  "type": "Feature",
  "properties": {
    "addr:full":"760 Inland Center Dr San Bernardino CA 92408",
    "addr:housenumber":"760",
    "addr:postcode":"92408",
    "addr:street":"Inland Center Dr",
    "iso:country":"US",
    "sg:address":"760 Inland Center Dr",
    "sg:city":"San Bernardino",
    "sg:classifiers":[
        {
            "category":"Home & Garden",
            "subcategory":"Furniture",
            "type":"Retail Goods"
        }
    ],
    "sg:phone":"+1 909 386 7411",
    "sg:postcode":"92408",
    "sg:province":"CA",
    "wof:name":"LA Canasta Furnishings",
    "wof:placetype":"venue"
},
  "geometry": {"coordinates":[-117.300552,34.085685],"type":"Point"}
}