{
  "type": "Feature",
  "properties": {
    "addr:full":"5661 Ashland Ave San Diego CA 92120",
    "addr:housenumber":"5661",
    "addr:postcode":"92120",
    "addr:street":"Ashland Ave",
    "iso:country":"US",
    "sg:address":"5661 Ashland Ave",
    "sg:city":"San Diego",
    "sg:classifiers":[
        {
            "category":"Professional",
            "type":"Services"
        }
    ],
    "sg:phone":"+1 619 286 9499",
    "sg:postcode":"92120",
    "sg:province":"CA",
    "wof:name":"Louise Seedorf Ctr",
    "wof:placetype":"venue"
},
  "geometry": {"coordinates":[-117.05571399999999,32.780713],"type":"Point"}
}