{
  "type": "Feature",
  "properties": {
    "iso:country":"US",
    "sg:address":"519 S School St",
    "sg:city":"Ukiah",
    "sg:classifiers":[
        {
            "category":"Insurance",
            "subcategory":"Insurance Agent",
            "type":"Services"
        }
    ],
    "sg:phone":"+1 707 462 4748",
    "sg:postcode":"95482",
    "sg:province":"CA",
    "wof:name":"Matsen Insurance Brokers Inc",
    "wof:placetype":"venue"
},
  "geometry": {"coordinates":[-123.207853,39.14688],"type":"Point"}
}