{
  "type": "Feature",
  "properties": {
    "addr:full":"2875 Larsen Dr Camino CA 95709",
    "addr:housenumber":"2875",
    "addr:postcode":"95709",
    "addr:street":"Larsen Dr Camino",
    "iso:country":"US",
    "sg:address":"2875 Larsen Dr",
    "sg:city":"Camino",
    "sg:classifiers":[
        {
            "category":"Winery",
            "type":"Food & Drink"
        }
    ],
    "sg:phone":"+1 530 647 9463",
    "sg:postcode":"95709",
    "sg:province":"CA",
    "sg:website":"www.ParaVi.com",
    "wof:name":"ParaVi Vineyards",
    "wof:placetype":"venue"
},
  "geometry": {"coordinates":[-120.674969,38.740234],"type":"Point"}
}