{
  "type": "Feature",
  "properties": {
    "iso:country":"US",
    "sg:address":"20578 Sitting Bull Rd",
    "sg:city":"Apple Valley",
    "sg:classifiers":[
        {
            "category":"Building & Trades",
            "subcategory":"Electrical",
            "type":"Services"
        }
    ],
    "sg:phone":"+1 760 247 8760",
    "sg:postcode":"92308",
    "sg:province":"CA",
    "sg:tags":[
        "electric",
        "contractor"
    ],
    "wof:name":"Vance Electric",
    "wof:placetype":"venue"
},
  "geometry": {"coordinates":[-117.21518,34.485401],"type":"Point"}
}