{
  "type": "Feature",
  "properties": {
    "addr:full":"1535 Folsom St San Francisco CA 94103",
    "addr:housenumber":"1535",
    "addr:postcode":"94103",
    "addr:street":"Folsom St",
    "iso:country":"US",
    "sg:address":"1535 Folsom St",
    "sg:city":"San Francisco",
    "sg:classifiers":[
        {
            "category":"Bars & Pubs",
            "subcategory":"Nightclub",
            "type":"Food & Drink"
        }
    ],
    "sg:phone":"+1 415 621 6087",
    "sg:postcode":"94103",
    "sg:province":"CA",
    "sg:tags":[
        "nightlife"
    ],
    "sg:website":"www.theholycow.com",
    "wof:name":"The Holy Cow",
    "wof:placetype":"venue"
},
  "geometry": {"coordinates":[-122.41448800000001,37.77148],"type":"Point"}
}