{
  "type": "Feature",
  "properties": {
    "addr:full":"34 S B St San Mateo CA 94401",
    "addr:housenumber":"34",
    "addr:postcode":"94401",
    "addr:street":"S B St",
    "iso:country":"US",
    "sg:address":"34 S B St",
    "sg:city":"San Mateo",
    "sg:classifiers":[
        {
            "category":"Bars & Pubs",
            "type":"Food & Drink"
        },
        {
            "category":"Restaurant",
            "type":"Food & Drink"
        },
        {
            "category":"Bars & Pubs",
            "subcategory":"Dive Bar",
            "type":"Food & Drink"
        }
    ],
    "sg:phone":"+1 650 347 1544",
    "sg:postcode":"94401",
    "sg:province":"CA",
    "sg:tags":[
        "irish"
    ],
    "sg:website":"www.tisoneills.com",
    "wof:name":"O'Neill's Irish Pub",
    "wof:placetype":"venue"
},
  "geometry": {"coordinates":[-122.324431,37.567385],"type":"Point"}
}