{
  "type": "Feature",
  "properties": {
    "iso:country":"US",
    "sg:address":"1739 Farnham Ave.",
    "sg:city":"Woodland",
    "sg:classifiers":[
        {
            "category":"Professional",
            "subcategory":"Computer Services",
            "type":"Services"
        }
    ],
    "sg:phone":"+1 530 405 3015",
    "sg:postcode":"95776",
    "sg:province":"CA",
    "sg:tags":[
        "healthcare-supplies",
        "health-care-supplies",
        "home-healthcare-supplies",
        "home-health-care-supplies"
    ],
    "sg:website":"http://healthcaresupplypros.com/",
    "wof:name":"Healthcare Supply Pros",
    "wof:placetype":"venue"
},
  "geometry": {"coordinates":[-121.74226899999999,38.673288],"type":"Point"}
}