{
  "type": "Feature",
  "properties": {
    "iso:country":"US",
    "sg:address":"2317 W 1st St",
    "sg:city":"Santa Ana",
    "sg:classifiers":[
        {
            "category":"Shopping",
            "subcategory":"Clothing, Apparel, & Fashions",
            "type":"Retail Goods"
        }
    ],
    "sg:phone":"+1 714 836 5139",
    "sg:postcode":"92703",
    "sg:province":"CA",
    "sg:tags":[
        "t"
    ],
    "wof:name":"Black Zone",
    "wof:placetype":"venue"
},
  "geometry": {"coordinates":[-117.899346,33.74524],"type":"Point"}
}