{
  "type": "Feature",
  "properties": {
    "addr:full":"11260 Point East Dr Rancho Cordova CA 95742",
    "addr:housenumber":"11260",
    "addr:postcode":"95742",
    "addr:street":"Point East Dr",
    "iso:country":"US",
    "sg:address":"11260 Point East Dr",
    "sg:city":"Rancho Cordova",
    "sg:classifiers":[
        {
            "category":"Travel",
            "subcategory":"Hotels & Motels",
            "type":"Entertainment"
        }
    ],
    "sg:phone":"+1 916 638 4141",
    "sg:postcode":"95742",
    "sg:province":"CA",
    "sg:website":"www.hotel-sierra.com/locations/r...",
    "wof:name":"Hotel Sierra",
    "wof:placetype":"venue"
},
  "geometry": {"coordinates":[-121.26799800000001,38.607201],"type":"Point"}
}