{
  "type": "Feature",
  "properties": {
    "iso:country":"US",
    "sg:address":"501 7th St",
    "sg:city":"Manhattan Beach",
    "sg:classifiers":[
        {
            "category":"Real Estate",
            "subcategory":"Real Estate Agent",
            "type":"Services"
        }
    ],
    "sg:phone":"+1 310 318 9871",
    "sg:postcode":"90266",
    "sg:province":"CA",
    "wof:name":"Manhattan Beach An Est",
    "wof:placetype":"venue"
},
  "geometry": {"coordinates":[-118.405121,33.882931],"type":"Point"}
}