{
  "type": "Feature",
  "properties": {
    "iso:country":"US",
    "sg:address":"1640 E 6th St",
    "sg:city":"Corona",
    "sg:classifiers":[
        {
            "category":"Retail",
            "subcategory":"Repair Shop",
            "type":"Services"
        }
    ],
    "sg:phone":"+1 951 738 8977",
    "sg:postcode":"92879",
    "sg:province":"CA",
    "sg:tags":[
        "upholsterer"
    ],
    "wof:name":"Arellanos Upholstery",
    "wof:placetype":"venue"
},
  "geometry": {"coordinates":[-117.531651,33.873698],"type":"Point"}
}