{
  "type": "Feature",
  "properties": {
    "addr:full":"1361 N Calaveras St Fresno CA 93728",
    "addr:housenumber":"1361",
    "addr:postcode":"93728",
    "addr:street":"N Calaveras",
    "iso:country":"US",
    "sg:address":"1361 N Calaveras St",
    "sg:city":"Fresno",
    "sg:classifiers":[
        {
            "category":"Building & Trades",
            "subcategory":"Landscaping Services",
            "type":"Services"
        }
    ],
    "sg:phone":"+1 559 268 2508",
    "sg:postcode":"93728",
    "sg:province":"CA",
    "sg:tags":[
        "tree"
    ],
    "wof:name":"Alonso Tree Svc",
    "wof:placetype":"venue"
},
  "geometry": {"coordinates":[-119.792314,36.760237],"type":"Point"}
}