{
  "type": "Feature",
  "properties": {
    "iso:country":"US",
    "sg:address":"2758 White Ln",
    "sg:city":"Bakersfield",
    "sg:classifiers":[
        {
            "category":"Restaurant",
            "type":"Food & Drink"
        }
    ],
    "sg:menulink":"http://www.allmenus.com/ca/bakersfield/8413-dennys/menu/",
    "sg:phone":"+1 661 831 6961",
    "sg:postcode":"93304",
    "sg:province":"CA",
    "sg:tags":[
        "american",
        "diner"
    ],
    "wof:name":"Denny's",
    "wof:placetype":"venue"
},
  "geometry": {"coordinates":[-119.034347,35.317761],"type":"Point"}
}