{
  "type": "Feature",
  "properties": {
    "addr:full":"1800 Market St San Francisco CA 94102",
    "addr:housenumber":"1800",
    "addr:postcode":"94102",
    "addr:street":"Market St",
    "iso:country":"US",
    "sg:address":"1800 Market St",
    "sg:city":"San Francisco",
    "sg:classifiers":[
        {
            "category":"Arts & Performance",
            "subcategory":"Festival",
            "type":"Entertainment"
        }
    ],
    "sg:phone":"+1 415 864 3733",
    "sg:postcode":"94102",
    "sg:province":"CA",
    "sg:website":"www.sfpride.org",
    "wof:name":"San Francisco LGBT Pride Parade",
    "wof:placetype":"venue"
},
  "geometry": {"coordinates":[-122.424048,37.771736],"type":"Point"}
}