{
  "type": "Feature",
  "properties": {
    "iso:country":"US",
    "sg:address":"5852 88th St Suite# 800",
    "sg:city":"Sacramento",
    "sg:classifiers":[
        {
            "category":"Building & Trades",
            "subcategory":"Construction",
            "type":"Services"
        }
    ],
    "sg:phone":"+1 916 386 4017",
    "sg:postcode":"95828",
    "sg:province":"CA",
    "sg:tags":[
        "industrial",
        "contractors-commercial",
        "contractor"
    ],
    "sg:website":"http://www.mjbbixbyconstruction.com",
    "wof:name":"MJB / Bixby Construcion Inc.",
    "wof:placetype":"venue"
},
  "geometry": {"coordinates":[-121.375839,38.521267],"type":"Point"}
}