{
  "type": "Feature",
  "properties": {
    "addr:full":"14404 Flomar Dr Whittier CA 90603",
    "addr:housenumber":"14404",
    "addr:postcode":"90603",
    "addr:street":"Flomar Dr",
    "iso:country":"US",
    "sg:address":"14404 Flomar Dr",
    "sg:city":"Whittier",
    "sg:classifiers":[
        {
            "category":"Shopping",
            "subcategory":"Hobbies, Toys, & Games",
            "type":"Retail Goods"
        }
    ],
    "sg:phone":"+1 562 696 6286",
    "sg:postcode":"90603",
    "sg:province":"CA",
    "wof:name":"Underwood Designs",
    "wof:placetype":"venue"
},
  "geometry": {"coordinates":[-118.02117699999999,33.94869],"type":"Point"}
}