{
  "type": "Feature",
  "properties": {
    "addr:full":"275 Co Rd 98 Woodland CA 95695",
    "addr:housenumber":"275;98",
    "addr:postcode":"95695",
    "addr:street":"Co Rd",
    "iso:country":"US",
    "sg:address":"275 Co Rd 98",
    "sg:city":"Woodland",
    "sg:classifiers":[
        {
            "category":"Wholesale",
            "subcategory":"Machinery & Supplies",
            "type":"Manufacturing & Wholesale Goods"
        }
    ],
    "sg:phone":"+1 530 662 2825",
    "sg:postcode":"95695",
    "sg:province":"CA",
    "sg:tags":[
        "pump"
    ],
    "wof:name":"Layne Christensen Co",
    "wof:placetype":"venue"
},
  "geometry": {"coordinates":[-121.802412,38.680006],"type":"Point"}
}