{
  "type": "Feature",
  "properties": {
    "addr:full":"3188 Kimlee Drive Suite 100 San Jose CA 95132-3604",
    "addr:housenumber":"3188",
    "addr:postcode":"95132-3604",
    "addr:street":"Kimlee Drive Suite 100",
    "iso:country":"US",
    "sg:address":"3188 Kimlee Drive Suite 100",
    "sg:city":"San Jose",
    "sg:classifiers":[
        {
            "category":"Professional",
            "subcategory":"Computer Services",
            "type":"Services"
        }
    ],
    "sg:phone":"+1 650 331 0165",
    "sg:postcode":"95132-3604",
    "sg:province":"CA",
    "sg:tags":[
        "video-conferencing",
        "video-collaboration",
        "application-sharing",
        "file-transfer"
    ],
    "sg:website":"http://vsee.com/",
    "wof:name":"VSee Lab",
    "wof:placetype":"venue"
},
  "geometry": {"coordinates":[-121.854147,37.403731],"type":"Point"}
}