{
  "type": "Feature",
  "properties": {
    "addr:full":"120 E 1st St Cloverdale CA 95425",
    "addr:housenumber":"120",
    "addr:postcode":"95425",
    "addr:street":"E 1St St",
    "iso:country":"US",
    "sg:address":"120 E 1st St",
    "sg:city":"Cloverdale",
    "sg:classifiers":[
        {
            "category":"Personal",
            "subcategory":"Beauty Salon",
            "type":"Services"
        }
    ],
    "sg:phone":"+1 707 894 0500",
    "sg:postcode":"95425",
    "sg:province":"CA",
    "wof:name":"T-Styles",
    "wof:placetype":"venue"
},
  "geometry": {"coordinates":[-123.01607199999999,38.805702],"type":"Point"}
}