{
  "type": "Feature",
  "properties": {
    "iso:country":"US",
    "sg:address":"4650 Caterpillar Rd",
    "sg:city":"Redding",
    "sg:classifiers":[
        {
            "category":"Wholesale",
            "subcategory":"Metals & Minerals",
            "type":"Manufacturing & Wholesale Goods"
        }
    ],
    "sg:phone":"+1 530 244 1050",
    "sg:postcode":"96003",
    "sg:province":"CA",
    "sg:tags":[
        "aluminum"
    ],
    "sg:website":"www.mobiledesignsinc.com",
    "wof:name":"Mobile Designs Inc",
    "wof:placetype":"venue"
},
  "geometry": {"coordinates":[-122.383097,40.62709],"type":"Point"}
}