{
  "type": "Feature",
  "properties": {
    "addr:full":"2297 Meadowview Ln Chino Hills CA 91709",
    "addr:housenumber":"2297",
    "addr:postcode":"91709",
    "addr:street":"Meadowview Ln",
    "iso:country":"US",
    "sg:address":"2297 Meadowview Ln",
    "sg:city":"Chino Hills",
    "sg:classifiers":[
        {
            "category":"Travel",
            "subcategory":"Travel Agent",
            "type":"Entertainment"
        }
    ],
    "sg:phone":"+1 909 591 4238",
    "sg:postcode":"91709",
    "sg:province":"CA",
    "sg:tags":[
        "agency"
    ],
    "wof:name":"Sherian Travel",
    "wof:placetype":"venue"
},
  "geometry": {"coordinates":[-117.755685,33.998422],"type":"Point"}
}