{
  "type": "Feature",
  "properties": {
    "addr:full":"2265 South Grand Avenue Santa Ana CA 92705",
    "addr:housenumber":"2265",
    "addr:postcode":"92705",
    "addr:street":"South Grand Avenue",
    "iso:country":"US",
    "sg:address":"2265 South Grand Avenue",
    "sg:city":"Santa Ana",
    "sg:classifiers":[
        {
            "category":"Building & Trades",
            "subcategory":"Construction",
            "type":"Services"
        }
    ],
    "sg:phone":"+1 888 765 2489",
    "sg:postcode":"92705",
    "sg:province":"CA",
    "sg:tags":[
        "installation",
        "solar"
    ],
    "sg:website":"www.solarcity.com",
    "wof:name":"SolarCity",
    "wof:placetype":"venue"
},
  "geometry": {"coordinates":[-117.850555,33.716296],"type":"Point"}
}