{
  "type": "Feature",
  "properties": {
    "iso:country":"US",
    "sg:address":"26910 Sierra Hwy",
    "sg:city":"Newhall",
    "sg:classifiers":[
        {
            "category":"Restaurant",
            "type":"Food & Drink"
        }
    ],
    "sg:phone":"+1 661 251 1963",
    "sg:postcode":"91321",
    "sg:province":"CA",
    "sg:tags":[
        "eating"
    ],
    "wof:name":"Taqueria Dos Mil",
    "wof:placetype":"venue"
},
  "geometry": {"coordinates":[-118.466155,34.404526],"type":"Point"}
}