{
  "type": "Feature",
  "properties": {
    "addr:full":"775 Pine Ave Holtville CA 92250",
    "addr:housenumber":"775",
    "addr:postcode":"92250",
    "addr:street":"Pine Ave",
    "iso:country":"US",
    "sg:address":"775 Pine Ave",
    "sg:city":"Holtville",
    "sg:classifiers":[
        {
            "category":"Place Of Worship",
            "subcategory":"Church",
            "type":"Public Place"
        },
        {
            "category":"Place Of Worship",
            "type":"Public Place"
        }
    ],
    "sg:phone":"+1 760 356 2785",
    "sg:postcode":"92250",
    "sg:province":"CA",
    "sg:tags":[
        "nazarene",
        "churches-church",
        "churches-nazarene"
    ],
    "sg:website":"http://www.nazarene.org",
    "wof:name":"Church Of Nazarene",
    "wof:placetype":"venue"
},
  "geometry": {"coordinates":[-115.381434,32.81612],"type":"Point"}
}