{
  "type": "Feature",
  "properties": {
    "iso:country":"US",
    "sg:address":"5111 S Central Ave",
    "sg:city":"Los Angeles",
    "sg:classifiers":[
        {
            "category":"Food & Beverages",
            "subcategory":"Groceries & Convenience Stores",
            "type":"Retail Goods"
        }
    ],
    "sg:phone":"+1 323 231 2201",
    "sg:postcode":"90011",
    "sg:province":"CA",
    "wof:name":"Odales Mini Mart",
    "wof:placetype":"venue"
},
  "geometry": {"coordinates":[-118.255997,33.996399],"type":"Point"}
}