{
  "type": "Feature",
  "properties": {
    "addr:full":"1417 N 10th St San Jose CA 95112",
    "addr:housenumber":"1417",
    "addr:postcode":"95112",
    "addr:street":"N 10Th St",
    "iso:country":"US",
    "sg:address":"1417 N 10th St",
    "sg:city":"San Jose",
    "sg:classifiers":[
        {
            "category":"Retail",
            "subcategory":"Auto Repair",
            "type":"Services"
        }
    ],
    "sg:phone":"+1 866 511 0672",
    "sg:postcode":"95112",
    "sg:province":"CA",
    "wof:name":"CNA Auto Service",
    "wof:placetype":"venue"
},
  "geometry": {"coordinates":[-121.900413,37.366313],"type":"Point"}
}