{
  "type": "Feature",
  "properties": {
    "iso:country":"US",
    "sg:address":"16665 Van Ness Ave",
    "sg:city":"Torrance",
    "sg:classifiers":[
        {
            "category":"Building & Trades",
            "subcategory":"Construction",
            "type":"Services"
        }
    ],
    "sg:phone":"+1 310 352 6287",
    "sg:postcode":"90504",
    "sg:province":"CA",
    "sg:tags":[
        "steam",
        "cleaning"
    ],
    "wof:name":"Doug's Concrete Steam Cleaning",
    "wof:placetype":"venue"
},
  "geometry": {"coordinates":[-118.317869,33.878199],"type":"Point"}
}