{
  "type": "Feature",
  "properties": {
    "iso:country":"US",
    "sg:address":"1107 N Hayworth",
    "sg:city":"West Hollywood",
    "sg:classifiers":[
        {
            "category":"Deli",
            "type":"Food & Drink"
        },
        {
            "category":"Restaurant",
            "type":"Food & Drink"
        }
    ],
    "sg:phone":"+1 323 654 9500",
    "sg:postcode":"90046",
    "sg:province":"CA",
    "sg:tags":[
        "scandinavian"
    ],
    "wof:name":"Shoop's",
    "wof:placetype":"venue"
},
  "geometry": {"coordinates":[-118.362981,34.091125],"type":"Point"}
}