{
  "type": "Feature",
  "properties": {
    "addr:full":"9253 Glenoaks Blvd Sun Valley CA 91352",
    "addr:housenumber":"9253",
    "addr:postcode":"91352",
    "addr:street":"Glenoaks Blvd",
    "iso:country":"US",
    "sg:address":"9253 Glenoaks Blvd",
    "sg:city":"Sun Valley",
    "sg:classifiers":[
        {
            "category":"Professional",
            "subcategory":"Engineering",
            "type":"Services"
        }
    ],
    "sg:phone":"+1 818 767 3157",
    "sg:postcode":"91352",
    "sg:province":"CA",
    "sg:tags":[
        "engineer"
    ],
    "sg:website":"www.harvest-technology.com",
    "wof:name":"Harvest Energy Technology",
    "wof:placetype":"venue"
},
  "geometry": {"coordinates":[-118.37385399999999,34.236657],"type":"Point"}
}