{
  "type": "Feature",
  "properties": {
    "iso:country":"US",
    "sg:address":"The Beverly Hilton Hotel 9876 Wilshire Blvd Pool Level",
    "sg:city":"Beverly Hills",
    "sg:classifiers":[
        {
            "category":"Personal",
            "subcategory":"Beauty Salon",
            "type":"Services"
        },
        {
            "category":"Personal",
            "subcategory":"Nail Salon",
            "type":"Services"
        }
    ],
    "sg:phone":"+1 310 270 4247",
    "sg:postcode":"90210",
    "sg:province":"CA",
    "sg:tags":[
        "hair"
    ],
    "sg:website":"www.beverlyhilton.com/Hotel_Feat...",
    "wof:name":"Bellezza Salon",
    "wof:placetype":"venue"
},
  "geometry": {"coordinates":[-118.412995,34.066347],"type":"Point"}
}