{
  "type": "Feature",
  "properties": {
    "iso:country":"US",
    "sg:address":"1855 Park Ave",
    "sg:city":"San Jose",
    "sg:classifiers":[
        {
            "category":"Wholesale",
            "subcategory":"Groceries",
            "type":"Manufacturing & Wholesale Goods"
        }
    ],
    "sg:phone":"+1 408 984 6710",
    "sg:postcode":"95126",
    "sg:province":"CA",
    "sg:tags":[
        "food",
        "broker"
    ],
    "wof:name":"Martin Sales Co",
    "wof:placetype":"venue"
},
  "geometry": {"coordinates":[-121.926147,37.335535],"type":"Point"}
}