{
  "type": "Feature",
  "properties": {
    "addr:full":"2824 Dell Ave Venice CA 90291",
    "addr:housenumber":"2824",
    "addr:postcode":"90291",
    "addr:street":"Dell Ave",
    "iso:country":"US",
    "sg:address":"2824 Dell Ave",
    "sg:city":"Venice",
    "sg:classifiers":[
        {
            "category":"Food & Beverages",
            "subcategory":"Groceries & Convenience Stores",
            "type":"Retail Goods"
        }
    ],
    "sg:phone":"+1 310 822 7318",
    "sg:postcode":"90291",
    "sg:province":"CA",
    "sg:tags":[
        "product"
    ],
    "wof:name":"Country Sweet Food Products",
    "wof:placetype":"venue"
},
  "geometry": {"coordinates":[-118.46351900000001,33.981225],"type":"Point"}
}