{
  "type": "Feature",
  "properties": {
    "iso:country":"US",
    "sg:address":"352 S Indian Hill Blvd",
    "sg:city":"Claremont",
    "sg:classifiers":[
        {
            "category":"Restaurant",
            "type":"Food & Drink"
        }
    ],
    "sg:phone":"+1 909 621 1855",
    "sg:postcode":"91711",
    "sg:province":"CA",
    "sg:tags":[
        "asian",
        "chinese",
        "pan"
    ],
    "wof:name":"Royal Panda Chinese Rstrnt",
    "wof:placetype":"venue"
},
  "geometry": {"coordinates":[-117.71923099999999,34.088645],"type":"Point"}
}