{
  "type": "Feature",
  "properties": {
    "addr:full":"North Park Plaza 1708 Oakland Rd, Ste 200 San Jose CA 95131",
    "addr:housenumber":"1708",
    "addr:postcode":"95131",
    "addr:street":"Oakland Rd Ste 200",
    "iso:country":"US",
    "sg:address":"North Park Plaza 1708 Oakland Rd, Ste 200",
    "sg:city":"San Jose",
    "sg:classifiers":[
        {
            "category":"Personal",
            "subcategory":"Beauty Salon",
            "type":"Services"
        },
        {
            "category":"Shopping",
            "subcategory":"Beauty & Cosmetics",
            "type":"Retail Goods"
        }
    ],
    "sg:phone":"+1 408 982 7895",
    "sg:postcode":"95131",
    "sg:province":"CA",
    "sg:tags":[
        "hair",
        "supply"
    ],
    "sg:website":"www.FantasticSamsNorthSJ.com",
    "wof:name":"Fantastic Sams Hair Salon",
    "wof:placetype":"venue"
},
  "geometry": {"coordinates":[-121.892775,37.383826],"type":"Point"}
}