{
  "type": "Feature",
  "properties": {
    "addr:full":"17 Ross Aly San Francisco CA 94108",
    "addr:housenumber":"17",
    "addr:postcode":"94108",
    "addr:street":"Ross Aly",
    "iso:country":"US",
    "sg:address":"17 Ross Aly",
    "sg:city":"San Francisco",
    "sg:classifiers":[
        {
            "category":"Health Services",
            "subcategory":"Health Practitioner",
            "type":"Services"
        }
    ],
    "sg:phone":"+1 415 397 1798",
    "sg:postcode":"94108",
    "sg:province":"CA",
    "sg:tags":[
        "acupuncture"
    ],
    "wof:name":"Herbs Acupuncture",
    "wof:placetype":"venue"
},
  "geometry": {"coordinates":[-122.40745699999999,37.795216],"type":"Point"}
}