{
  "type": "Feature",
  "properties": {
    "iso:country":"US",
    "sg:address":"4550 Balfour Rd Ste C",
    "sg:city":"Brentwood",
    "sg:classifiers":[
        {
            "category":"Shopping",
            "subcategory":"Tobacco",
            "type":"Retail Goods"
        }
    ],
    "sg:phone":"+1 925 516 4715",
    "sg:postcode":"94513",
    "sg:province":"CA",
    "sg:tags":[
        "shop"
    ],
    "sg:website":"Www.Smokeshopbrentwood.com",
    "wof:name":"Smoke Shop",
    "wof:placetype":"venue"
},
  "geometry": {"coordinates":[-121.694935,37.925341],"type":"Point"}
}