{
  "type": "Feature",
  "properties": {
    "iso:country":"US",
    "sg:address":"1777 Argonaut St",
    "sg:city":"Stockton",
    "sg:classifiers":[
        {
            "category":"Manufacturing",
            "subcategory":"Tools & Machinery",
            "type":"Manufacturing & Wholesale Goods"
        }
    ],
    "sg:phone":"+1 209 944 0743",
    "sg:postcode":"95206",
    "sg:province":"CA",
    "sg:tags":[
        "farm",
        "equipment"
    ],
    "wof:name":"Hahn Tractor Co",
    "wof:placetype":"venue"
},
  "geometry": {"coordinates":[-121.303009,37.932018],"type":"Point"}
}