{
  "type": "Feature",
  "properties": {
    "iso:country":"US",
    "sg:address":"4226 W 231st St",
    "sg:city":"Torrance",
    "sg:classifiers":[
        {
            "category":"Social Services",
            "type":"Services"
        }
    ],
    "sg:phone":"+1 310 378 1729",
    "sg:postcode":"90505",
    "sg:province":"CA",
    "sg:tags":[
        "organization",
        "welfare"
    ],
    "wof:name":"Star Caribou",
    "wof:placetype":"venue"
},
  "geometry": {"coordinates":[-118.358738,33.817727],"type":"Point"}
}