{
  "type": "Feature",
  "properties": {
    "addr:full":"1308 E Yanonali St Santa Barbara CA 93103",
    "addr:housenumber":"1308",
    "addr:postcode":"93103",
    "addr:street":"E Yanonali St",
    "iso:country":"US",
    "sg:address":"1308 E Yanonali St",
    "sg:city":"Santa Barbara",
    "sg:classifiers":[
        {
            "category":"Building & Trades",
            "subcategory":"Construction",
            "type":"Services"
        }
    ],
    "sg:phone":"+1 805 963 6441",
    "sg:postcode":"93103",
    "sg:province":"CA",
    "sg:tags":[
        "residential",
        "contractor"
    ],
    "wof:name":"Praja Construction",
    "wof:placetype":"venue"
},
  "geometry": {"coordinates":[-119.67747199999999,34.427256],"type":"Point"}
}