{
  "type": "Feature",
  "properties": {
    "iso:country":"US",
    "sg:address":"420 N McKinley St",
    "sg:city":"Corona",
    "sg:classifiers":[
        {
            "category":"Restaurant",
            "type":"Food & Drink"
        }
    ],
    "sg:phone":"+1 951 372 0582",
    "sg:postcode":"92879",
    "sg:province":"CA",
    "wof:name":"Hughes Texas BBQ",
    "wof:placetype":"venue"
},
  "geometry": {"coordinates":[-117.519879,33.888716],"type":"Point"}
}