{
  "type": "Feature",
  "properties": {
    "iso:country":"US",
    "sg:address":"751 N Vine Ave",
    "sg:city":"Ontario",
    "sg:classifiers":[
        {
            "category":"Professional",
            "type":"Services"
        }
    ],
    "sg:phone":"+1 909 466 3679",
    "sg:postcode":"91762",
    "sg:province":"CA",
    "sg:tags":[
        "establishment"
    ],
    "wof:name":"Mira Mesa",
    "wof:placetype":"venue"
},
  "geometry": {"coordinates":[-117.65603,34.071524],"type":"Point"}
}