{
  "type": "Feature",
  "properties": {
    "iso:country":"US",
    "sg:address":"4800 Martin Luther King Jr Blvd",
    "sg:city":"Sacramento",
    "sg:classifiers":[
        {
            "category":"Organizations",
            "subcategory":"Religious Organization",
            "type":"Services"
        }
    ],
    "sg:phone":"+1 916 451 4030",
    "sg:postcode":"95820",
    "sg:province":"CA",
    "sg:tags":[
        "church"
    ],
    "wof:name":"Mt Pilgrim Baptist Church",
    "wof:placetype":"venue"
},
  "geometry": {"coordinates":[-121.464706,38.530896],"type":"Point"}
}