{
  "type": "Feature",
  "properties": {
    "addr:full":"6633 Mountain Side Dr Igo CA 96047",
    "addr:housenumber":"6633",
    "addr:postcode":"96047",
    "addr:street":"Mountain Side Dr",
    "iso:country":"US",
    "sg:address":"6633 Mountain Side Dr",
    "sg:city":"Igo",
    "sg:classifiers":[
        {
            "category":"Building & Trades",
            "subcategory":"Construction",
            "type":"Services"
        }
    ],
    "sg:phone":"+1 530 396 2450",
    "sg:postcode":"96047",
    "sg:province":"CA",
    "sg:tags":[
        "tile-contractors"
    ],
    "wof:name":"California Tile Contractors",
    "wof:placetype":"venue"
},
  "geometry": {"coordinates":[-122.670779,40.481013],"type":"Point"}
}