{
  "type": "Feature",
  "properties": {
    "iso:country":"US",
    "sg:address":"130 N Maryland Ave",
    "sg:city":"Glendale",
    "sg:classifiers":[
        {
            "category":"Restaurant",
            "type":"Food & Drink"
        }
    ],
    "sg:phone":"+1 818 241 8860",
    "sg:postcode":"91206",
    "sg:province":"CA",
    "sg:tags":[
        "italian"
    ],
    "wof:name":"Louise's Trattoria",
    "wof:placetype":"venue"
},
  "geometry": {"coordinates":[-118.253625,34.147044],"type":"Point"}
}