{
  "type": "Feature",
  "properties": {
    "addr:full":"236 W East Ave Chico CA 95926",
    "addr:housenumber":"236",
    "addr:postcode":"95926",
    "addr:street":"W East Ave",
    "iso:country":"US",
    "sg:address":"236 W East Ave",
    "sg:city":"Chico",
    "sg:classifiers":[
        {
            "category":"Real Estate",
            "subcategory":"Real Estate Agent",
            "type":"Services"
        }
    ],
    "sg:phone":"+1 530 342 9448",
    "sg:postcode":"95926",
    "sg:province":"CA",
    "wof:name":"Woodside Garden Apartments",
    "wof:placetype":"venue"
},
  "geometry": {"coordinates":[-121.863618,39.755291],"type":"Point"}
}