{
  "type": "Feature",
  "properties": {
    "iso:country":"US",
    "sg:address":"7848 Tigerwoods Dr",
    "sg:city":"Sacramento",
    "sg:classifiers":[
        {
            "category":"Building & Trades",
            "subcategory":"Construction",
            "type":"Services"
        }
    ],
    "sg:phone":"+1 916 681 7290",
    "sg:postcode":"95829",
    "sg:province":"CA",
    "sg:tags":[
        "wallcoverings-installation",
        "wallpaper",
        "painting",
        "contractor"
    ],
    "wof:name":"Cook Painting",
    "wof:placetype":"venue"
},
  "geometry": {"coordinates":[-121.31053199999999,38.47324],"type":"Point"}
}