{
  "type": "Feature",
  "properties": {
    "addr:full":"1375 6th St Norco CA 92860",
    "addr:housenumber":"1375",
    "addr:postcode":"92860",
    "addr:street":"6Th St",
    "iso:country":"US",
    "sg:address":"1375 6th St",
    "sg:city":"Norco",
    "sg:classifiers":[
        {
            "category":"Manufacturing",
            "subcategory":"Pet Food",
            "type":"Manufacturing & Wholesale Goods"
        },
        {
            "category":"Shopping",
            "subcategory":"Pets & Pet Supplies",
            "type":"Retail Goods"
        }
    ],
    "sg:phone":"+1 951 737 4440",
    "sg:postcode":"92860",
    "sg:province":"CA",
    "sg:tags":[
        "feed",
        "hay"
    ],
    "wof:name":"Tony's Hay & Grain",
    "wof:placetype":"venue"
},
  "geometry": {"coordinates":[-117.551351,33.938412],"type":"Point"}
}