{
  "type": "Feature",
  "properties": {
    "iso:country":"US",
    "sg:address":"1229 S Mary Ave",
    "sg:city":"Sunnyvale",
    "sg:classifiers":[
        {
            "category":"Banks & Credit Unions",
            "subcategory":"Investment Brokerage",
            "type":"Services"
        }
    ],
    "sg:phone":"+1 408 739 5330",
    "sg:postcode":"94087",
    "sg:province":"CA",
    "sg:tags":[
        "consultant",
        "planning",
        "financial"
    ],
    "wof:name":"Foothill Financial Svc",
    "wof:placetype":"venue"
},
  "geometry": {"coordinates":[-122.050625,37.352725],"type":"Point"}
}