{
  "type": "Feature",
  "properties": {
    "addr:full":"202 Main St Venice CA 90291",
    "addr:housenumber":"202",
    "addr:postcode":"90291",
    "addr:street":"Main St",
    "iso:country":"US",
    "sg:address":"202 Main St",
    "sg:city":"Venice",
    "sg:classifiers":[
        {
            "category":"Professional",
            "subcategory":"Management & Consulting",
            "type":"Services"
        }
    ],
    "sg:phone":"+1 310 396 1165",
    "sg:postcode":"90291",
    "sg:province":"CA",
    "sg:tags":[
        "consultant",
        "broker"
    ],
    "wof:name":"Rules Of The Game",
    "wof:placetype":"venue"
},
  "geometry": {"coordinates":[-118.477655,33.996213],"type":"Point"}
}