{
  "type": "Feature",
  "properties": {
    "addr:full":"501 N Hillford Ave Compton CA 90220",
    "addr:housenumber":"501",
    "addr:postcode":"90220",
    "addr:street":"N Hillford Ave",
    "iso:country":"US",
    "sg:address":"501 N Hillford Ave",
    "sg:city":"Compton",
    "sg:classifiers":[
        {
            "category":"Wholesale",
            "subcategory":"Home Furnishings",
            "type":"Manufacturing & Wholesale Goods"
        }
    ],
    "sg:phone":"+1 310 631 1235",
    "sg:postcode":"90220",
    "sg:province":"CA",
    "sg:tags":[
        "frame",
        "sheet"
    ],
    "wof:name":"Carrying Message",
    "wof:placetype":"venue"
},
  "geometry": {"coordinates":[-118.252039,33.899394],"type":"Point"}
}