{
  "type": "Feature",
  "properties": {
    "addr:full":"544 S San Pedro St Los Angeles CA 90013",
    "addr:housenumber":"544",
    "addr:postcode":"90013",
    "addr:street":"S San Pedro St",
    "iso:country":"US",
    "sg:address":"544 S San Pedro St",
    "sg:city":"Los Angeles",
    "sg:classifiers":[
        {
            "category":"Social Services",
            "type":"Services"
        }
    ],
    "sg:phone":"+1 213 622 3540",
    "sg:postcode":"90013",
    "sg:province":"CA",
    "sg:tags":[
        "organization",
        "welfare"
    ],
    "sg:website":"www.voala.org",
    "wof:name":"Volunteers Of America",
    "wof:placetype":"venue"
},
  "geometry": {"coordinates":[-118.244658,34.043085],"type":"Point"}
}