{
  "type": "Feature",
  "properties": {
    "iso:country":"US",
    "sg:address":"1657 Purdue Ave",
    "sg:city":"East Palo Alto",
    "sg:classifiers":[
        {
            "category":"Professional",
            "subcategory":"Accounting & Tax Preparation",
            "type":"Services"
        }
    ],
    "sg:phone":"+1 650 328 5010",
    "sg:postcode":"94303",
    "sg:province":"CA",
    "sg:tags":[
        "return",
        "filing"
    ],
    "wof:name":"Maria's Tax Svc",
    "wof:placetype":"venue"
},
  "geometry": {"coordinates":[-122.137792,37.479091],"type":"Point"}
}