{
  "type": "Feature",
  "properties": {
    "iso:country":"US",
    "sg:address":"1213 S H St",
    "sg:city":"Bakersfield",
    "sg:classifiers":[
        {
            "category":"Insurance",
            "subcategory":"Insurance Agent",
            "type":"Services"
        }
    ],
    "sg:phone":"+1 661 835 9631",
    "sg:postcode":"93304",
    "sg:province":"CA",
    "wof:name":"Farmers Insurance Group",
    "wof:placetype":"venue"
},
  "geometry": {"coordinates":[-119.02126800000001,35.342274],"type":"Point"}
}