{
  "type": "Feature",
  "properties": {
    "iso:country":"US",
    "sg:address":"40 Auto Center Dr",
    "sg:city":"Tustin",
    "sg:classifiers":[
        {
            "category":"Autos & Motor Vehicles",
            "subcategory":"Automobile Sales",
            "type":"Retail Goods"
        }
    ],
    "sg:phone":"+1 714 730 4600",
    "sg:postcode":"92782",
    "sg:province":"CA",
    "sg:tags":[
        "car"
    ],
    "wof:name":"Tustin Chrysler Jeep Dodge",
    "wof:placetype":"venue"
},
  "geometry": {"coordinates":[-117.799004,33.7239],"type":"Point"}
}