{
  "type": "Feature",
  "properties": {
    "addr:full":"14518 Polk St Sylmar CA 91342",
    "addr:housenumber":"14518",
    "addr:postcode":"91342",
    "addr:street":"Polk St",
    "iso:country":"US",
    "sg:address":"14518 Polk St",
    "sg:city":"Sylmar",
    "sg:classifiers":[
        {
            "category":"Wholesale",
            "subcategory":"Hardware",
            "type":"Manufacturing & Wholesale Goods"
        }
    ],
    "sg:phone":"+1 818 364 5112",
    "sg:postcode":"91342",
    "sg:province":"CA",
    "sg:tags":[
        "refrigerating"
    ],
    "wof:name":"Kg Industries",
    "wof:placetype":"venue"
},
  "geometry": {"coordinates":[-118.448705,34.308564],"type":"Point"}
}