{
  "type": "Feature",
  "properties": {
    "iso:country":"US",
    "sg:address":"16350 Meacham Rd",
    "sg:city":"Bakersfield",
    "sg:classifiers":[
        {
            "category":"Professional",
            "subcategory":"Art Services",
            "type":"Services"
        }
    ],
    "sg:phone":"+1 661 829 1792",
    "sg:postcode":"93314",
    "sg:province":"CA",
    "sg:tags":[
        "photographer"
    ],
    "wof:name":"Photo Thrift Ads",
    "wof:placetype":"venue"
},
  "geometry": {"coordinates":[-119.184325,35.390808],"type":"Point"}
}