{
  "type": "Feature",
  "properties": {
    "addr:full":"11630 Ramona Blvd El Monte CA 91732",
    "addr:housenumber":"11630",
    "addr:postcode":"91732",
    "addr:street":"Ramona Blvd",
    "iso:country":"US",
    "sg:address":"11630 Ramona Blvd",
    "sg:city":"El Monte",
    "sg:classifiers":[
        {
            "category":"Autos & Motor Vehicles",
            "subcategory":"Auto Supplies",
            "type":"Retail Goods"
        }
    ],
    "sg:phone":"+1 626 579 4103",
    "sg:postcode":"91732",
    "sg:province":"CA",
    "sg:tags":[
        "automobile",
        "stereo",
        "radio"
    ],
    "wof:name":"UFO Custom Sounds",
    "wof:placetype":"venue"
},
  "geometry": {"coordinates":[-118.020132,34.074397],"type":"Point"}
}