{
  "type": "Feature",
  "properties": {
    "addr:full":"10256 Westminster Ave Garden Grove CA 92843",
    "addr:housenumber":"10256",
    "addr:postcode":"92843",
    "addr:street":"Westminster Ave",
    "iso:country":"US",
    "sg:address":"10256 Westminster Ave",
    "sg:city":"Garden Grove",
    "sg:classifiers":[
        {
            "category":"Health Services",
            "subcategory":"Doctor",
            "type":"Services"
        }
    ],
    "sg:phone":"+1 714 537 5528",
    "sg:postcode":"92843",
    "sg:province":"CA",
    "sg:tags":[
        "physician",
        "surgeon"
    ],
    "wof:name":"Arcadia Acupuncture Group",
    "wof:placetype":"venue"
},
  "geometry": {"coordinates":[-117.948323,33.759499],"type":"Point"}
}