{
  "type": "Feature",
  "properties": {
    "iso:country":"US",
    "sg:address":"7131 Trask Ave",
    "sg:city":"Playa Del Rey",
    "sg:classifiers":[
        {
            "category":"Professional",
            "type":"Services"
        }
    ],
    "sg:phone":"+1 310 822 9798",
    "sg:postcode":"90293",
    "sg:province":"CA",
    "wof:name":"Costrite Co",
    "wof:placetype":"venue"
},
  "geometry": {"coordinates":[-118.445104,33.9565],"type":"Point"}
}