{
  "type": "Feature",
  "properties": {
    "iso:country":"US",
    "sg:address":"1400 N Imperial Ave",
    "sg:city":"El Centro",
    "sg:classifiers":[
        {
            "category":"Real Estate",
            "subcategory":"Real Estate Operator",
            "type":"Services"
        }
    ],
    "sg:phone":"+1 760 353 2800",
    "sg:postcode":"92243",
    "sg:province":"CA",
    "sg:tags":[
        "building",
        "apartment"
    ],
    "wof:name":"Posada Del Sol III A Cal Ptn",
    "wof:placetype":"venue"
},
  "geometry": {"coordinates":[-115.569886,32.807442],"type":"Point"}
}