{
  "type": "Feature",
  "properties": {
    "iso:country":"US",
    "sg:address":"2100 Lakeshore Ave #A",
    "sg:city":"Oakland",
    "sg:classifiers":[
        {
            "category":"Professional",
            "subcategory":"Accounting & Tax Preparation",
            "type":"Services"
        },
        {
            "category":"Insurance",
            "subcategory":"Hazard Insurance",
            "type":"Services"
        }
    ],
    "sg:phone":"+1 510 444 0500",
    "sg:postcode":"94606",
    "sg:province":"CA",
    "sg:tags":[
        "bookkeeping",
        "return",
        "representative",
        "preparation-business",
        "taxes-consultants"
    ],
    "wof:name":"Freedman Lucille Ea",
    "wof:placetype":"venue"
},
  "geometry": {"coordinates":[-122.25102200000001,37.804369],"type":"Point"}
}