{
  "type": "Feature",
  "properties": {
    "addr:full":"208 Utah Street Suite 350 San Francisco CA 94103",
    "addr:housenumber":"208",
    "addr:postcode":"94103",
    "addr:street":"Utah Street Suite 350",
    "iso:country":"US",
    "sg:address":"208 Utah Street Suite 350",
    "sg:city":"San Francisco",
    "sg:classifiers":[
        {
            "category":"Professional",
            "subcategory":"Computer Services",
            "type":"Services"
        }
    ],
    "sg:phone":"+1 415 975 3855",
    "sg:postcode":"94103",
    "sg:province":"CA",
    "sg:website":"http://www.workshare.com/",
    "wof:name":"Workshare",
    "wof:placetype":"venue"
},
  "geometry": {"coordinates":[-122.406706,37.766876],"type":"Point"}
}