{
  "type": "Feature",
  "properties": {
    "addr:full":"30450 Pudding Creek Rd Fort Bragg CA 95437",
    "addr:postcode":"30450;95437",
    "addr:street":"Pudding Creek Rd",
    "iso:country":"US",
    "sg:address":"30450 Pudding Creek Rd",
    "sg:city":"Fort Bragg",
    "sg:classifiers":[
        {
            "category":"Freight",
            "type":"Transportation"
        }
    ],
    "sg:phone":"+1 707 964 5505",
    "sg:postcode":"95437",
    "sg:province":"CA",
    "sg:tags":[
        "operator",
        "local",
        "trucking"
    ],
    "wof:name":"Kenneth Shipley",
    "wof:placetype":"venue"
},
  "geometry": {"coordinates":[-123.75774199999999,39.452101],"type":"Point"}
}