{
  "type": "Feature",
  "properties": {
    "iso:country":"US",
    "sg:address":"2530 Douglas Blvd",
    "sg:city":"Roseville",
    "sg:classifiers":[
        {
            "category":"Professional",
            "subcategory":"Accounting & Tax Preparation",
            "type":"Services"
        }
    ],
    "sg:phone":"+1 916 677 2289",
    "sg:postcode":"95678",
    "sg:province":"CA",
    "sg:tags":[
        "return",
        "filing"
    ],
    "wof:name":"Lorrie Beeman",
    "wof:placetype":"venue"
},
  "geometry": {"coordinates":[-121.249887,38.744203],"type":"Point"}
}