{
  "type": "Feature",
  "properties": {
    "iso:country":"US",
    "sg:address":"101 Townsend St",
    "sg:city":"San Francisco",
    "sg:classifiers":[
        {
            "category":"Shopping",
            "subcategory":"Gifts & Souvenirs",
            "type":"Retail Goods"
        }
    ],
    "sg:phone":"+1 415 777 1230",
    "sg:postcode":"94107",
    "sg:province":"CA",
    "sg:tags":[
        "party",
        "supply"
    ],
    "wof:name":"Excel Meetings & Events",
    "wof:placetype":"venue"
},
  "geometry": {"coordinates":[-122.391065,37.780182],"type":"Point"}
}