{
  "type": "Feature",
  "properties": {
    "addr:full":"669 W Calaveras St Altadena CA 91001",
    "addr:housenumber":"669",
    "addr:postcode":"91001",
    "addr:street":"W Calaveras St",
    "iso:country":"US",
    "sg:address":"669 W Calaveras St",
    "sg:city":"Altadena",
    "sg:classifiers":[
        {
            "category":"Health Services",
            "subcategory":"Hospital",
            "type":"Services"
        }
    ],
    "sg:phone":"+1 626 794 9917",
    "sg:postcode":"91001",
    "sg:province":"CA",
    "sg:tags":[
        "center",
        "birth"
    ],
    "wof:name":"Children Are Our Future Inc",
    "wof:placetype":"venue"
},
  "geometry": {"coordinates":[-118.163799,34.193869],"type":"Point"}
}