{
  "type": "Feature",
  "properties": {
    "addr:full":"5200 Sharp Rd Calistoga CA 94515",
    "addr:housenumber":"5200",
    "addr:postcode":"94515",
    "addr:street":"Sharp Rd",
    "iso:country":"US",
    "sg:address":"5200 Sharp Rd",
    "sg:city":"Calistoga",
    "sg:classifiers":[
        {
            "category":"Farming",
            "subcategory":"Crops",
            "type":"Manufacturing & Wholesale Goods"
        }
    ],
    "sg:phone":"+1 707 942 5576",
    "sg:postcode":"94515",
    "sg:province":"CA",
    "sg:tags":[
        "grove",
        "nut",
        "tree"
    ],
    "wof:name":"R E Fechter & Sons",
    "wof:placetype":"venue"
},
  "geometry": {"coordinates":[-122.605114,38.552347],"type":"Point"}
}