{
  "type": "Feature",
  "properties": {
    "addr:full":"1816 Industrial Way Sanger CA 93657",
    "addr:housenumber":"1816",
    "addr:postcode":"ca 93657",
    "addr:street":"Industrial Way",
    "iso:country":"US",
    "sg:address":"1816 Industrial Way",
    "sg:city":"Sanger",
    "sg:classifiers":[
        {
            "category":"Building & Trades",
            "subcategory":"Construction",
            "type":"Services"
        }
    ],
    "sg:phone":"+1 559 875 6861",
    "sg:postcode":"93657",
    "sg:province":"CA",
    "sg:tags":[
        "painter"
    ],
    "wof:name":"Ro's Precise Powder Coating",
    "wof:placetype":"venue"
},
  "geometry": {"coordinates":[-119.54845400000001,36.691724],"type":"Point"}
}