{
  "type": "Feature",
  "properties": {
    "iso:country":"US",
    "sg:address":"3214 Riverside Blvd",
    "sg:city":"Sacramento",
    "sg:classifiers":[
        {
            "category":"Restaurant",
            "type":"Food & Drink"
        }
    ],
    "sg:phone":"+1 916 930 9401",
    "sg:postcode":"95818",
    "sg:province":"CA",
    "sg:tags":[
        "products-wholesale",
        "caterer"
    ],
    "sg:website":"treasuredteatime.com",
    "wof:name":"Treasured Tea Time",
    "wof:placetype":"venue"
},
  "geometry": {"coordinates":[-121.50602000000001,38.549961],"type":"Point"}
}