{
  "type": "Feature",
  "properties": {
    "addr:full":"431 N Buchanan Cir Martinez CA 94553",
    "addr:housenumber":"431",
    "addr:postcode":"94553",
    "addr:street":"N Buchanan Cir Martinez",
    "iso:country":"US",
    "sg:address":"431 N Buchanan Cir",
    "sg:city":"Martinez",
    "sg:classifiers":[
        {
            "category":"Manufacturing",
            "subcategory":"Leather Goods",
            "type":"Manufacturing & Wholesale Goods"
        },
        {
            "category":"Wholesale",
            "subcategory":"Non-durable Goods",
            "type":"Manufacturing & Wholesale Goods"
        }
    ],
    "sg:phone":"+1 925 671 2644",
    "sg:postcode":"94553",
    "sg:province":"CA",
    "sg:tags":[
        "mfg"
    ],
    "wof:name":"Awl Leathered Up",
    "wof:placetype":"venue"
},
  "geometry": {"coordinates":[-122.07153700000001,37.99117],"type":"Point"}
}