{
  "type": "Feature",
  "properties": {
    "iso:country":"US",
    "sg:address":"22 N Milpas St",
    "sg:city":"Santa Barbara",
    "sg:classifiers":[
        {
            "category":"Restaurant",
            "type":"Food & Drink"
        }
    ],
    "sg:phone":"+1 805 966 5151",
    "sg:postcode":"93103",
    "sg:province":"CA",
    "wof:name":"Your Place Thai Restaurant",
    "wof:placetype":"venue"
},
  "geometry": {"coordinates":[-119.679902,34.42241],"type":"Point"}
}