{
  "type": "Feature",
  "properties": {
    "iso:country":"US",
    "sg:address":"8632 Greenback Lane",
    "sg:city":"Orangevale",
    "sg:classifiers":[
        {
            "category":"Social Services",
            "subcategory":"Child Care",
            "type":"Services"
        }
    ],
    "sg:phone":"+1 916 987 8632",
    "sg:postcode":"95662",
    "sg:province":"CA",
    "sg:tags":[
        "day"
    ],
    "wof:name":"My Friends Pediatric Day Care Center",
    "wof:placetype":"venue"
},
  "geometry": {"coordinates":[-121.237968,38.678456],"type":"Point"}
}