{
  "type": "Feature",
  "properties": {
    "addr:full":"14105 Pontlavey Ave Santa Fe Springs CA 90670",
    "addr:housenumber":"14105",
    "addr:postcode":"90670",
    "addr:street":"Pontlavey Ave",
    "iso:country":"US",
    "sg:address":"14105 Pontlavey Ave",
    "sg:city":"Santa Fe Springs",
    "sg:classifiers":[
        {
            "category":"Wholesale",
            "subcategory":"Machinery & Supplies",
            "type":"Manufacturing & Wholesale Goods"
        }
    ],
    "sg:phone":"+1 562 946 4111",
    "sg:postcode":"90670",
    "sg:province":"CA",
    "sg:tags":[
        "equipment",
        "layer",
        "carpet"
    ],
    "wof:name":"De Soto Sales",
    "wof:placetype":"venue"
},
  "geometry": {"coordinates":[-118.049381,33.9035],"type":"Point"}
}