{
  "type": "Feature",
  "properties": {
    "iso:country":"US",
    "sg:address":"9037 Arrow Blvd",
    "sg:city":"Rancho Cucamonga",
    "sg:classifiers":[
        {
            "category":"Retail",
            "subcategory":"Repair Shop",
            "type":"Services"
        }
    ],
    "sg:phone":"+1 909 481 6200",
    "sg:postcode":"91730",
    "sg:province":"CA",
    "sg:tags":[
        "lock",
        "locksmith"
    ],
    "wof:name":"Van Gaalen Lock & Key Inc",
    "wof:placetype":"venue"
},
  "geometry": {"coordinates":[-117.60727300000001,34.099266],"type":"Point"}
}