{
  "type": "Feature",
  "properties": {
    "iso:country":"US",
    "sg:address":"9358 E American Ave",
    "sg:city":"Del Rey",
    "sg:classifiers":[
        {
            "category":"Manufacturing",
            "subcategory":"Food",
            "type":"Manufacturing & Wholesale Goods"
        }
    ],
    "sg:phone":"+1 559 897 4637",
    "sg:postcode":"93616",
    "sg:province":"CA",
    "sg:tags":[
        "dehydrated",
        "mfg"
    ],
    "wof:name":"Geraldine E Lenocker",
    "wof:placetype":"venue"
},
  "geometry": {"coordinates":[-119.625463,36.663366],"type":"Point"}
}