{
  "type": "Feature",
  "properties": {
    "addr:full":"3194 Dogwood Dr Corona CA 92882",
    "addr:housenumber":"3194",
    "addr:postcode":"92882",
    "addr:street":"Dogwood Dr",
    "iso:country":"US",
    "sg:address":"3194 Dogwood Dr",
    "sg:city":"Corona",
    "sg:classifiers":[
        {
            "category":"Building & Trades",
            "subcategory":"Construction",
            "type":"Services"
        }
    ],
    "sg:phone":"+1 951 237 9099",
    "sg:postcode":"92882",
    "sg:province":"CA",
    "sg:tags":[
        "nonresidential"
    ],
    "wof:name":"Gleasons Cnstr Productions",
    "wof:placetype":"venue"
},
  "geometry": {"coordinates":[-117.629394,33.879259],"type":"Point"}
}