{
  "type": "Feature",
  "properties": {
    "addr:full":"1433 E 38th St Oakland CA 94602",
    "addr:housenumber":"1433",
    "addr:postcode":"94602",
    "addr:street":"E 38Th St",
    "iso:country":"US",
    "sg:address":"1433 E 38th St",
    "sg:city":"Oakland",
    "sg:classifiers":[
        {
            "category":"Manufacturing",
            "subcategory":"Buildings",
            "type":"Manufacturing & Wholesale Goods"
        },
        {
            "category":"Building & Trades",
            "subcategory":"Construction",
            "type":"Services"
        }
    ],
    "sg:phone":"+1 510 336 1725",
    "sg:postcode":"94602",
    "sg:province":"CA",
    "sg:tags":[
        "home",
        "builder",
        "contractor"
    ],
    "wof:name":"Mw Construction",
    "wof:placetype":"venue"
},
  "geometry": {"coordinates":[-122.226658,37.803809],"type":"Point"}
}