{
  "type": "Feature",
  "properties": {
    "addr:full":"12 W Colorado Blvd Pasadena CA 91105",
    "addr:housenumber":"12",
    "addr:postcode":"91105",
    "addr:street":"W Colorado Blvd",
    "iso:country":"US",
    "sg:address":"12 W Colorado Blvd",
    "sg:city":"Pasadena",
    "sg:phone":"+1 626 356 0712",
    "sg:postcode":"91105",
    "sg:province":"CA",
    "wof:name":"Squeeze & Scoop",
    "wof:placetype":"venue"
},
  "geometry": {"coordinates":[-118.150826,34.145773],"type":"Point"}
}