{
  "type": "Feature",
  "properties": {
    "addr:full":"244 Campodonico Ave Guadalupe CA 93434",
    "addr:housenumber":"244",
    "addr:postcode":"93434",
    "addr:street":"Campodonico Ave",
    "iso:country":"US",
    "sg:address":"244 Campodonico Ave",
    "sg:city":"Guadalupe",
    "sg:classifiers":[
        {
            "category":"Professional",
            "type":"Services"
        }
    ],
    "sg:phone":"+1 805 343 0126",
    "sg:postcode":"93434",
    "sg:province":"CA",
    "wof:name":"Sonido Ritmo Caliente",
    "wof:placetype":"venue"
},
  "geometry": {"coordinates":[-120.575187,34.960834],"type":"Point"}
}