{
  "type": "Feature",
  "properties": {
    "addr:full":"25001 The Old Rd Stevenson Ranch CA 91381",
    "addr:housenumber":"25001",
    "addr:postcode":"91381",
    "addr:street":"The Old Rd",
    "iso:country":"US",
    "sg:address":"25001 The Old Rd",
    "sg:city":"Stevenson Ranch",
    "sg:classifiers":[
        {
            "category":"Professional",
            "subcategory":"Accounting & Tax Preparation",
            "type":"Services"
        }
    ],
    "sg:phone":"+1 661 222 2988",
    "sg:postcode":"91381",
    "sg:province":"CA",
    "sg:tags":[
        "accountant"
    ],
    "wof:name":"Friedman Thompson & Co",
    "wof:placetype":"venue"
},
  "geometry": {"coordinates":[-118.560997,34.3703],"type":"Point"}
}