{
  "type": "Feature",
  "properties": {
    "addr:full":"20211 Valley Blvd Tehachapi CA 93561",
    "addr:housenumber":"20211",
    "addr:postcode":"93561",
    "addr:street":"Valley Blvd",
    "iso:country":"US",
    "sg:address":"20211 Valley Blvd",
    "sg:city":"Tehachapi",
    "sg:classifiers":[
        {
            "category":"Health Services",
            "subcategory":"Doctor",
            "type":"Services"
        }
    ],
    "sg:phone":"+1 661 822 5544",
    "sg:postcode":"93561",
    "sg:province":"CA",
    "sg:tags":[
        "physician",
        "surgeon"
    ],
    "wof:name":"Alpine Medical",
    "wof:placetype":"venue"
},
  "geometry": {"coordinates":[-118.4906,35.124357],"type":"Point"}
}