{
  "type": "Feature",
  "properties": {
    "addr:full":"1601 Cook Pl Goleta CA 93117",
    "addr:housenumber":"1601",
    "addr:postcode":"93117",
    "addr:street":"Cook Pl",
    "iso:country":"US",
    "sg:address":"1601 Cook Pl",
    "sg:city":"Goleta",
    "sg:classifiers":[
        {
            "category":"Education",
            "subcategory":"Special Training",
            "type":"Public Place"
        }
    ],
    "sg:phone":"+1 805 681 9200",
    "sg:postcode":"93117",
    "sg:province":"CA",
    "sg:tags":[
        "aircraft",
        "school"
    ],
    "wof:name":"Red Barron Aviation",
    "wof:placetype":"venue"
},
  "geometry": {"coordinates":[-119.84612,34.429596],"type":"Point"}
}