{
  "type": "Feature",
  "properties": {
    "iso:country":"US",
    "sg:address":"8360 Clairemont Mesa Blvd",
    "sg:city":"San Diego",
    "sg:classifiers":[
        {
            "category":"Retail",
            "subcategory":"Repair Shop",
            "type":"Services"
        }
    ],
    "sg:phone":"+1 858 268 3088",
    "sg:postcode":"92117",
    "sg:province":"CA",
    "sg:tags":[
        "coffee",
        "brewing",
        "devices"
    ],
    "wof:name":"Jim Duke Svc Co",
    "wof:placetype":"venue"
},
  "geometry": {"coordinates":[-117.143887,32.83289],"type":"Point"}
}