{
  "type": "Feature",
  "properties": {
    "iso:country":"US",
    "sg:address":"2700 Dwight Way",
    "sg:city":"Berkeley",
    "sg:classifiers":[
        {
            "category":"Place Of Worship",
            "subcategory":"Church",
            "type":"Public Place"
        }
    ],
    "sg:phone":"+1 510 848 7812",
    "sg:postcode":"94704",
    "sg:province":"CA",
    "sg:website":"www.calnewman.org/",
    "wof:name":"Newman Hall Holy Spirit Parish",
    "wof:placetype":"venue"
},
  "geometry": {"coordinates":[-122.253998,37.865601],"type":"Point"}
}