{
  "type": "Feature",
  "properties": {
    "iso:country":"US",
    "sg:address":"650 Merchant St",
    "sg:city":"Vacaville",
    "sg:classifiers":[
        {
            "category":"Building & Trades",
            "subcategory":"Construction",
            "type":"Services"
        }
    ],
    "sg:phone":"+1 707 449 5170",
    "sg:postcode":"95688",
    "sg:province":"CA",
    "sg:tags":[
        "marking",
        "maintenance",
        "parking"
    ],
    "sg:website":"www.cityofvacaville.com",
    "wof:name":"Vacaville Public Works Dept",
    "wof:placetype":"venue"
},
  "geometry": {"coordinates":[-121.995011,38.349728],"type":"Point"}
}