{
  "type": "Feature",
  "properties": {
    "addr:full":"5930 Elmwood Rd San Bernardino CA 92404",
    "addr:housenumber":"5930",
    "addr:postcode":"92404",
    "addr:street":"Elmwood Rd",
    "iso:country":"US",
    "sg:address":"5930 Elmwood Rd",
    "sg:city":"San Bernardino",
    "sg:classifiers":[
        {
            "category":"Building & Trades",
            "subcategory":"Landscaping Services",
            "type":"Services"
        }
    ],
    "sg:phone":"+1 909 882 1936",
    "sg:postcode":"92404",
    "sg:province":"CA",
    "wof:name":"Orozco Lawn Service",
    "wof:placetype":"venue"
},
  "geometry": {"coordinates":[-117.25154000000001,34.14496],"type":"Point"}
}