{
  "type": "Feature",
  "properties": {
    "addr:full":"3200 Wilshire Blvd Ste 1300 Los Angeles CA 90010",
    "addr:housenumber":"3200",
    "addr:postcode":"90010",
    "addr:street":"Wilshire Blvd Ste 1300",
    "iso:country":"US",
    "sg:address":"3200 Wilshire Blvd Ste 1300",
    "sg:city":"Los Angeles",
    "sg:classifiers":[
        {
            "category":"Professional",
            "subcategory":"Lawyer & Legal Services",
            "type":"Services"
        }
    ],
    "sg:phone":"+1 213 383 1244",
    "sg:postcode":"90010",
    "sg:province":"CA",
    "wof:name":"Law Offices Of Linda E Lee",
    "wof:placetype":"venue"
},
  "geometry": {"coordinates":[-118.291648,34.165287],"type":"Point"}
}