{
  "type": "Feature",
  "properties": {
    "addr:full":"14 Monticello Irvine CA 92620",
    "addr:housenumber":"14",
    "addr:postcode":"92620",
    "addr:street":"Monticello",
    "iso:country":"US",
    "sg:address":"14 Monticello",
    "sg:city":"Irvine",
    "sg:classifiers":[
        {
            "category":"Communications",
            "subcategory":"Television Station",
            "type":"Services"
        }
    ],
    "sg:phone":"+1 949 857 1310",
    "sg:postcode":"92620",
    "sg:province":"CA",
    "sg:tags":[
        "distributor",
        "program",
        "producer"
    ],
    "wof:name":"Randal Schultz Video Prdctns",
    "wof:placetype":"venue"
},
  "geometry": {"coordinates":[-117.758696,33.706728],"type":"Point"}
}