{
  "type": "Feature",
  "properties": {
    "iso:country":"US",
    "sg:address":"1001 N H St",
    "sg:city":"Lompoc",
    "sg:classifiers":[
        {
            "category":"Personal",
            "type":"Services"
        },
        {
            "category":"Retail",
            "subcategory":"Auto Rental",
            "type":"Services"
        },
        {
            "category":"Building & Trades",
            "subcategory":"Equipment Rental",
            "type":"Services"
        },
        {
            "category":"Retail",
            "subcategory":"Storage",
            "type":"Services"
        }
    ],
    "sg:phone":"+1 805 736 5254",
    "sg:postcode":"93436",
    "sg:province":"CA",
    "sg:tags":[
        "renting",
        "moving-self",
        "leasing",
        "truck",
        "mover",
        "trailer",
        "contractors'"
    ],
    "sg:website":"http://www.uhaul.com/Locations/Rentals-near-Lompoc-CA-93436/050202",
    "wof:name":"U-Haul Neighborhood Dealer - Pommervilles Unocal",
    "wof:placetype":"venue"
},
  "geometry": {"coordinates":[-120.457718,34.653389],"type":"Point"}
}