{
  "type": "Feature",
  "properties": {
    "iso:country":"US",
    "sg:address":"30 Stillings Ave",
    "sg:city":"San Francisco",
    "sg:classifiers":[
        {
            "category":"Professional",
            "subcategory":"Business Services",
            "type":"Services"
        }
    ],
    "sg:phone":"+1 415 333 4932",
    "sg:postcode":"94131",
    "sg:province":"CA",
    "sg:tags":[
        "interior",
        "consultant",
        "design",
        "decorator"
    ],
    "wof:name":"Erik Kramvik Design",
    "wof:placetype":"venue"
},
  "geometry": {"coordinates":[-122.440977,37.734474],"type":"Point"}
}