{
  "type": "Feature",
  "properties": {
    "iso:country":"US",
    "sg:address":"575 Maude Ct",
    "sg:city":"Sunnyvale",
    "sg:classifiers":[
        {
            "category":"Manufacturing",
            "subcategory":"Electronics",
            "type":"Manufacturing & Wholesale Goods"
        }
    ],
    "sg:phone":"+1 408 522 9200",
    "sg:postcode":"94085",
    "sg:province":"CA",
    "sg:tags":[
        "semiconductor",
        "devices"
    ],
    "wof:name":"Qualitau Inc",
    "wof:placetype":"venue"
},
  "geometry": {"coordinates":[-122.039168,37.392812],"type":"Point"}
}