{
  "type": "Feature",
  "properties": {
    "iso:country":"US",
    "sg:address":"150 McAllister",
    "sg:city":"San Francisco",
    "sg:classifiers":[
        {
            "category":"Real Estate",
            "subcategory":"Real Estate Operator",
            "type":"Services"
        }
    ],
    "sg:phone":"+1 415 503 0354",
    "sg:postcode":"94101",
    "sg:province":"CA",
    "sg:tags":[
        "apartment"
    ],
    "wof:name":"McAllister Hotel",
    "wof:placetype":"venue"
},
  "geometry": {"coordinates":[-122.414536,37.780933],"type":"Point"}
}