{
  "type": "Feature",
  "properties": {
    "iso:country":"US",
    "sg:address":"1563 W Betteravia Rd",
    "sg:city":"Santa Maria",
    "sg:classifiers":[
        {
            "category":"Retail",
            "subcategory":"Auto Repair",
            "type":"Services"
        }
    ],
    "sg:phone":"+1 805 925 4292",
    "sg:postcode":"93455",
    "sg:province":"CA",
    "sg:tags":[
        "body",
        "shop"
    ],
    "wof:name":"Wuethrich George",
    "wof:placetype":"venue"
},
  "geometry": {"coordinates":[-120.47199999999999,34.920799],"type":"Point"}
}