{
  "type": "Feature",
  "properties": {
    "iso:country":"US",
    "sg:address":"13681 Newport Ave Ste 8",
    "sg:city":"Tustin",
    "sg:classifiers":[
        {
            "category":"Home & Garden",
            "subcategory":"Household Appliances",
            "type":"Retail Goods"
        }
    ],
    "sg:phone":"+1 714 593 4678",
    "sg:postcode":"92780",
    "sg:province":"CA",
    "wof:name":"Smith Bros Appliance",
    "wof:placetype":"venue"
},
  "geometry": {"coordinates":[-117.819574,33.740989],"type":"Point"}
}