{
  "type": "Feature",
  "properties": {
    "iso:country":"US",
    "sg:address":"1458 S San Pedro St #112",
    "sg:city":"Los Angeles",
    "sg:classifiers":[
        {
            "category":"Shopping",
            "subcategory":"Clothing, Apparel, & Fashions",
            "type":"Retail Goods"
        }
    ],
    "sg:phone":"+1 213 747 2570",
    "sg:postcode":"90015",
    "sg:province":"CA",
    "sg:tags":[
        "clothing",
        "women's"
    ],
    "wof:name":"Fashion Maxima",
    "wof:placetype":"venue"
},
  "geometry": {"coordinates":[-118.25539000000001,34.030722],"type":"Point"}
}