{
  "type": "Feature",
  "properties": {
    "iso:country":"US",
    "sg:address":"1120 E Las Tunas Dr",
    "sg:city":"San Gabriel",
    "sg:classifiers":[
        {
            "category":"Travel",
            "subcategory":"Travel Agent",
            "type":"Entertainment"
        }
    ],
    "sg:phone":"+1 626 287 4494",
    "sg:postcode":"91776",
    "sg:province":"CA",
    "sg:tags":[
        "agency"
    ],
    "wof:name":"Travel By Design",
    "wof:placetype":"venue"
},
  "geometry": {"coordinates":[-118.08304,34.103445],"type":"Point"}
}