{
  "type": "Feature",
  "properties": {
    "addr:full":"160 E St Chula Vista CA 91910",
    "addr:housenumber":"160",
    "addr:postcode":"91910",
    "addr:street":"E St",
    "iso:country":"US",
    "sg:address":"160 E St",
    "sg:city":"Chula Vista",
    "sg:classifiers":[
        {
            "category":"Real Estate",
            "subcategory":"Real Estate Services",
            "type":"Services"
        }
    ],
    "sg:phone":"+1 619 585 9471",
    "sg:postcode":"91910",
    "sg:province":"CA",
    "sg:tags":[
        "management",
        "property"
    ],
    "wof:name":"Starks Gracelyn",
    "wof:placetype":"venue"
},
  "geometry": {"coordinates":[-117.075378,32.645846],"type":"Point"}
}