{
  "type": "Feature",
  "properties": {
    "addr:full":"5212 Cahuenga Blvd North Hollywood CA 91601",
    "addr:housenumber":"5212",
    "addr:postcode":"91601",
    "addr:street":"Cahuenga Blvd",
    "iso:country":"US",
    "sg:address":"5212 Cahuenga Blvd",
    "sg:city":"North Hollywood",
    "sg:classifiers":[
        {
            "category":"Retail",
            "subcategory":"Laundry & Dry Cleaning",
            "type":"Services"
        }
    ],
    "sg:phone":"+1 818 761 1588",
    "sg:postcode":"91601",
    "sg:province":"CA",
    "sg:tags":[
        "cleaner"
    ],
    "wof:name":"Bonjour Cleaners",
    "wof:placetype":"venue"
},
  "geometry": {"coordinates":[-118.361,34.165501],"type":"Point"}
}