{
  "type": "Feature",
  "properties": {
    "iso:country":"US",
    "sg:address":"2415 W 5th St",
    "sg:city":"Santa Ana",
    "sg:classifiers":[
        {
            "category":"Manufacturing",
            "subcategory":"Motor Vehicles & Parts",
            "type":"Manufacturing & Wholesale Goods"
        }
    ],
    "sg:phone":"+1 714 647 9010",
    "sg:postcode":"92703",
    "sg:province":"CA",
    "sg:tags":[
        "automobile",
        "supply"
    ],
    "wof:name":"A-1 Automotive Core Supplier",
    "wof:placetype":"venue"
},
  "geometry": {"coordinates":[-117.901395,33.748784],"type":"Point"}
}