{
  "type": "Feature",
  "properties": {
    "iso:country":"US",
    "sg:address":"68225 Ramon Rd",
    "sg:city":"Cathedral City",
    "sg:classifiers":[
        {
            "category":"Recreation",
            "type":"Entertainment"
        }
    ],
    "sg:phone":"+1 760 770 0792",
    "sg:postcode":"92234",
    "sg:province":"CA",
    "sg:tags":[
        "martial",
        "arts",
        "instruction"
    ],
    "wof:name":"Desert Institute Of Kung Fu",
    "wof:placetype":"venue"
},
  "geometry": {"coordinates":[-116.470457,33.815854],"type":"Point"}
}