{
  "type": "Feature",
  "properties": {
    "addr:full":"7615 Glade Ave Canoga Park CA 91304",
    "addr:housenumber":"7615",
    "addr:postcode":"91304",
    "addr:street":"Glade Ave",
    "iso:country":"US",
    "sg:address":"7615 Glade Ave",
    "sg:city":"Canoga Park",
    "sg:classifiers":[
        {
            "category":"Local Transit",
            "type":"Transportation"
        }
    ],
    "sg:phone":"+1 818 593 4285",
    "sg:postcode":"91304",
    "sg:province":"CA",
    "sg:tags":[
        "limousine"
    ],
    "wof:name":"Stark Limo",
    "wof:placetype":"venue"
},
  "geometry": {"coordinates":[-118.60821900000001,34.210796],"type":"Point"}
}