{
  "type": "Feature",
  "properties": {
    "addr:full":"43230 Christy St Fremont CA 94538",
    "addr:housenumber":"43230",
    "addr:postcode":"94538",
    "addr:street":"Christy St",
    "iso:country":"US",
    "sg:address":"43230 Christy St",
    "sg:city":"Fremont",
    "sg:classifiers":[
        {
            "category":"Professional",
            "subcategory":"Computer Services",
            "type":"Services"
        }
    ],
    "sg:phone":"+1 510 979 9961",
    "sg:postcode":"94538",
    "sg:province":"CA",
    "wof:name":"Ituner Networks",
    "wof:placetype":"venue"
},
  "geometry": {"coordinates":[-121.973525,37.506802],"type":"Point"}
}