{
  "type": "Feature",
  "properties": {
    "addr:full":"24455 Via Pansa Laguna Niguel CA 92677",
    "addr:housenumber":"24455",
    "addr:postcode":"92677",
    "addr:street":"Via Pansa",
    "iso:country":"US",
    "sg:address":"24455 Via Pansa",
    "sg:city":"Laguna Niguel",
    "sg:classifiers":[
        {
            "category":"Real Estate",
            "subcategory":"Real Estate Operator",
            "type":"Services"
        }
    ],
    "sg:phone":"+1 949 643 3328",
    "sg:postcode":"92677",
    "sg:province":"CA",
    "sg:tags":[
        "apartment"
    ],
    "wof:name":"Laguna Gardens Apartments",
    "wof:placetype":"venue"
},
  "geometry": {"coordinates":[-117.703613,33.568803],"type":"Point"}
}