{
  "type": "Feature",
  "properties": {
    "addr:full":"555 Oxford St Chula Vista CA 91911",
    "addr:housenumber":"555",
    "addr:postcode":"91911",
    "addr:street":"Oxford St",
    "iso:country":"US",
    "sg:address":"555 Oxford St",
    "sg:city":"Chula Vista",
    "sg:classifiers":[
        {
            "category":"Real Estate",
            "subcategory":"Real Estate Operator",
            "type":"Services"
        }
    ],
    "sg:phone":"+1 619 420 1182",
    "sg:postcode":"91911",
    "sg:province":"CA",
    "sg:tags":[
        "apartment"
    ],
    "wof:name":"Oxford Terrace Apartments",
    "wof:placetype":"venue"
},
  "geometry": {"coordinates":[-117.077003,32.607498],"type":"Point"}
}