{
  "type": "Feature",
  "properties": {
    "addr:full":"16168 Beach Blvd Ste 151 Huntington Beach CA 92647",
    "addr:housenumber":"16168",
    "addr:postcode":"92647",
    "addr:street":"Beach Blvd Ste 151",
    "iso:country":"US",
    "sg:address":"16168 Beach Blvd Ste 151",
    "sg:city":"Huntington Beach",
    "sg:classifiers":[
        {
            "category":"Professional",
            "subcategory":"Accounting & Tax Preparation",
            "type":"Services"
        }
    ],
    "sg:phone":"+1 714 848 1000",
    "sg:postcode":"92647",
    "sg:province":"CA",
    "sg:tags":[
        "accountant"
    ],
    "wof:name":"Automated Floral Machines",
    "wof:placetype":"venue"
},
  "geometry": {"coordinates":[-117.988998,33.728001],"type":"Point"}
}