{
  "type": "Feature",
  "properties": {
    "iso:country":"US",
    "sg:address":"2503 K Street",
    "sg:city":"Sacramento",
    "sg:classifiers":[
        {
            "category":"Health Services",
            "subcategory":"Doctor",
            "type":"Services"
        }
    ],
    "sg:phone":"+1 916 448 4500",
    "sg:postcode":"95816",
    "sg:province":"CA",
    "sg:tags":[
        "surgeon",
        "oral"
    ],
    "sg:website":"www.sacramentooralsurgery.com/",
    "wof:name":"Sacramento Oral Surgery",
    "wof:placetype":"venue"
},
  "geometry": {"coordinates":[-121.473686,38.573854],"type":"Point"}
}