{
  "type": "Feature",
  "properties": {
    "iso:country":"US",
    "sg:address":"11151 Westminster Ave",
    "sg:city":"Garden Grove",
    "sg:classifiers":[
        {
            "category":"Building & Trades",
            "subcategory":"Plumbing",
            "type":"Services"
        }
    ],
    "sg:phone":"+1 714 953 0247",
    "sg:postcode":"92843",
    "sg:province":"CA",
    "sg:tags":[
        "tank",
        "septic"
    ],
    "wof:name":"American Septic Systems",
    "wof:placetype":"venue"
},
  "geometry": {"coordinates":[-117.934845,33.759735],"type":"Point"}
}