{
  "type": "Feature",
  "properties": {
    "iso:country":"US",
    "sg:address":"522 Sutter Street",
    "sg:city":"San Francisco",
    "sg:classifiers":[
        {
            "category":"Arts & Performance",
            "subcategory":"Art Gallery",
            "type":"Entertainment"
        }
    ],
    "sg:phone":"+1 415 732 4300",
    "sg:postcode":"94102",
    "sg:province":"CA",
    "wof:name":"Louis Aronow Gallery",
    "wof:placetype":"venue"
},
  "geometry": {"coordinates":[-122.408997,37.789299],"type":"Point"}
}