{
  "type": "Feature",
  "properties": {
    "iso:country":"US",
    "sg:address":"25 N 14th St",
    "sg:city":"San Jose",
    "sg:classifiers":[
        {
            "category":"Health Services",
            "subcategory":"Doctor",
            "type":"Services"
        }
    ],
    "sg:phone":"+1 408 279 1048",
    "sg:postcode":"95112",
    "sg:province":"CA",
    "sg:tags":[
        "physician",
        "surgeon"
    ],
    "wof:name":"Neena Madireddi MD",
    "wof:placetype":"venue"
},
  "geometry": {"coordinates":[-121.878095,37.34361],"type":"Point"}
}