{
  "type": "Feature",
  "properties": {
    "iso:country":"US",
    "sg:address":"1004 N Puente Ave",
    "sg:city":"La Puente",
    "sg:classifiers":[
        {
            "category":"Manufacturing",
            "subcategory":"Retail Goods",
            "type":"Manufacturing & Wholesale Goods"
        }
    ],
    "sg:phone":"+1 626 338 8384",
    "sg:postcode":"91746",
    "sg:province":"CA",
    "sg:tags":[
        "marking",
        "devices",
        "mfg"
    ],
    "wof:name":"Scha Way Enterprises",
    "wof:placetype":"venue"
},
  "geometry": {"coordinates":[-117.974952,34.057584],"type":"Point"}
}