{
  "type": "Feature",
  "properties": {
    "addr:full":"6581 Barbara Dr Sebastopol CA 95472",
    "addr:housenumber":"6581",
    "addr:postcode":"95472",
    "addr:street":"Barbara Dr",
    "iso:country":"US",
    "sg:address":"6581 Barbara Dr",
    "sg:city":"Sebastopol",
    "sg:classifiers":[
        {
            "category":"Utilities",
            "subcategory":"Water",
            "type":"Services"
        }
    ],
    "sg:phone":"+1 707 829 3824",
    "sg:postcode":"95472",
    "sg:province":"CA",
    "sg:tags":[
        "supply"
    ],
    "wof:name":"Kelly Mutual Water Co",
    "wof:placetype":"venue"
},
  "geometry": {"coordinates":[-122.80809600000001,38.384632],"type":"Point"}
}