{
  "type": "Feature",
  "properties": {
    "iso:country":"US",
    "sg:address":"6581 Barbara Dr",
    "sg:city":"Sebastopol",
    "sg:classifiers":[
        {
            "category":"Utilities",
            "subcategory":"Water",
            "type":"Services"
        }
    ],
    "sg:phone":"+1 707 829 3824",
    "sg:postcode":"95472",
    "sg:province":"CA",
    "sg:tags":[
        "supply"
    ],
    "wof:name":"Kelly Mutual Water Co",
    "wof:placetype":"venue"
},
  "geometry": {"coordinates":[-122.808096,38.384632],"type":"Point"}
}