{
  "type": "Feature",
  "properties": {
    "addr:full":"4305 Gesner St Ste 212 San Diego CA 92117",
    "addr:housenumber":"4305",
    "addr:postcode":"92117",
    "addr:street":"Gesner St Ste 212",
    "iso:country":"US",
    "sg:address":"4305 Gesner St Ste 212",
    "sg:city":"San Diego",
    "sg:classifiers":[
        {
            "category":"Professional",
            "subcategory":"Accounting & Tax Preparation",
            "type":"Services"
        }
    ],
    "sg:phone":"+1 619 275 7526",
    "sg:postcode":"92117",
    "sg:province":"CA",
    "sg:tags":[
        "accountant"
    ],
    "wof:name":"Skane A K An Accountancy Corp",
    "wof:placetype":"venue"
},
  "geometry": {"coordinates":[-117.203003,32.791599],"type":"Point"}
}