{
  "type": "Feature",
  "properties": {
    "addr:full":"7042 Stanford Oak Dr Sacramento CA 95842",
    "addr:housenumber":"7042",
    "addr:postcode":"95842",
    "addr:street":"Stanford Oak Dr",
    "iso:country":"US",
    "sg:address":"7042 Stanford Oak Dr",
    "sg:city":"Sacramento",
    "sg:classifiers":[
        {
            "category":"Real Estate",
            "subcategory":"Real Estate Agent",
            "type":"Services"
        }
    ],
    "sg:phone":"+1 916 606 2429",
    "sg:postcode":"95842",
    "sg:province":"CA",
    "sg:tags":[
        "agency",
        "rental"
    ],
    "wof:name":"R B Rental",
    "wof:placetype":"venue"
},
  "geometry": {"coordinates":[-121.328136,38.693479],"type":"Point"}
}