{
  "type": "Feature",
  "properties": {
    "iso:country":"US",
    "sg:address":"9919 Gould St",
    "sg:city":"Oakland",
    "sg:classifiers":[
        {
            "category":"Shopping",
            "subcategory":"Stationery & Office Supplies",
            "type":"Retail Goods"
        }
    ],
    "sg:phone":"+1 510 638 9086",
    "sg:postcode":"94603",
    "sg:province":"CA",
    "sg:tags":[
        "equipment"
    ],
    "sg:website":"www.networkfurnishings.com",
    "wof:name":"Network Furnishings Inc",
    "wof:placetype":"venue"
},
  "geometry": {"coordinates":[-122.177655,37.740272],"type":"Point"}
}