{
  "type": "Feature",
  "properties": {
    "addr:full":"1501 N China Lake Blvd Ridgecrest CA 93555",
    "addr:housenumber":"1501",
    "addr:postcode":"93555",
    "addr:street":"N China Lake Blvd",
    "iso:country":"US",
    "sg:address":"1501 N China Lake Blvd",
    "sg:city":"Ridgecrest",
    "sg:classifiers":[
        {
            "category":"Building & Trades",
            "subcategory":"Construction",
            "type":"Services"
        }
    ],
    "sg:phone":"+1 760 446 4818",
    "sg:postcode":"93555",
    "sg:province":"CA",
    "sg:tags":[
        "general",
        "commercial",
        "contractor"
    ],
    "wof:name":"South Bay Edc",
    "wof:placetype":"venue"
},
  "geometry": {"coordinates":[-117.66988499999999,35.647991],"type":"Point"}
}