{
  "type": "Feature",
  "properties": {
    "addr:full":"15237 Crenshaw Blvd Gardena CA 90249",
    "addr:housenumber":"15237",
    "addr:postcode":"90249",
    "addr:street":"Crenshaw Blvd",
    "iso:country":"US",
    "sg:address":"15237 Crenshaw Blvd",
    "sg:city":"Gardena",
    "sg:classifiers":[
        {
            "category":"Home & Garden",
            "subcategory":"Building Materials",
            "type":"Retail Goods"
        }
    ],
    "sg:phone":"+1 310 676 6791",
    "sg:postcode":"90249",
    "sg:province":"CA",
    "sg:tags":[
        "glass",
        "window",
        "trade",
        "plate",
        "contractor"
    ],
    "wof:name":"Chang's Glass",
    "wof:placetype":"venue"
},
  "geometry": {"coordinates":[-118.32658499999999,33.892697],"type":"Point"}
}