{
  "type": "Feature",
  "properties": {
    "iso:country":"US",
    "sg:address":"1020 A-2 Tierra Del Rey",
    "sg:city":"Chula Vista",
    "sg:classifiers":[
        {
            "category":"Shopping",
            "subcategory":"Bicycles & Sporting Goods",
            "type":"Retail Goods"
        }
    ],
    "sg:phone":"+1 619 656 5222",
    "sg:postcode":"91910",
    "sg:province":"CA",
    "sg:tags":[
        "bike"
    ],
    "sg:website":"www.pulseendurance.com",
    "wof:name":"Pulse Endurance Sports",
    "wof:placetype":"venue"
},
  "geometry": {"coordinates":[-117.02054800000001,32.63743],"type":"Point"}
}