{
  "type": "Feature",
  "properties": {
    "addr:full":"1011 Swarthmore Ave Pacific Plsds CA 90272",
    "addr:housenumber":"1011",
    "addr:postcode":"90272",
    "addr:street":"Swarthmore Ave",
    "iso:country":"US",
    "sg:address":"1011 Swarthmore Ave",
    "sg:city":"Pacific Plsds",
    "sg:classifiers":[
        {
            "category":"Home & Garden",
            "subcategory":"Garden Supply",
            "type":"Retail Goods"
        }
    ],
    "sg:phone":"+1 310 230 2200",
    "sg:postcode":"90272",
    "sg:province":"CA",
    "sg:tags":[
        "fertilizer"
    ],
    "sg:website":"www.oyi.com",
    "wof:name":"Optimum Yield",
    "wof:placetype":"venue"
},
  "geometry": {"coordinates":[-118.524638,34.048254],"type":"Point"}
}