{
  "type": "Feature",
  "properties": {
    "iso:country":"US",
    "sg:address":"5233 Kauai Way",
    "sg:city":"Fair Oaks",
    "sg:classifiers":[
        {
            "category":"Building & Trades",
            "subcategory":"Construction",
            "type":"Services"
        }
    ],
    "sg:phone":"+1 916 965 7527",
    "sg:postcode":"95628",
    "sg:province":"CA",
    "sg:tags":[
        "floor",
        "laying",
        "contractor"
    ],
    "wof:name":"Specialized Flooring",
    "wof:placetype":"venue"
},
  "geometry": {"coordinates":[-121.25514699999999,38.663188],"type":"Point"}
}