{
  "type": "Feature",
  "properties": {
    "iso:country":"US",
    "sg:address":"11821 Mississippi Ave",
    "sg:city":"Los Angeles",
    "sg:classifiers":[
        {
            "category":"Professional",
            "subcategory":"Engineering",
            "type":"Services"
        }
    ],
    "sg:phone":"+1 310 444 3878",
    "sg:postcode":"90025",
    "sg:province":"CA",
    "sg:tags":[
        "engineer"
    ],
    "wof:name":"Blackdust Design LTD",
    "wof:placetype":"venue"
},
  "geometry": {"coordinates":[-118.45132099999999,34.034409],"type":"Point"}
}