{
  "type": "Feature",
  "properties": {
    "iso:country":"US",
    "sg:address":"17820 Chatsworth St",
    "sg:city":"Granada Hills",
    "sg:classifiers":[
        {
            "category":"Real Estate",
            "subcategory":"Real Estate Agent",
            "type":"Services"
        }
    ],
    "sg:phone":"+1 818 885 5800",
    "sg:postcode":"91344",
    "sg:province":"CA",
    "wof:name":"Powell Prestige Mortgage",
    "wof:placetype":"venue"
},
  "geometry": {"coordinates":[-118.523083,34.264828],"type":"Point"}
}