{
  "type": "Feature",
  "properties": {
    "addr:full":"24900 Anza Dr Valencia CA 91355",
    "addr:housenumber":"24900",
    "addr:postcode":"91355",
    "addr:street":"Anza Dr",
    "iso:country":"US",
    "sg:address":"24900 Anza Dr",
    "sg:city":"Valencia",
    "sg:classifiers":[
        {
            "category":"Recreation",
            "type":"Entertainment"
        }
    ],
    "sg:phone":"+1 661 257 8801",
    "sg:postcode":"91355",
    "sg:province":"CA",
    "sg:tags":[
        "entertainers-family",
        "business"
    ],
    "wof:name":"Manex Entertainment",
    "wof:placetype":"venue"
},
  "geometry": {"coordinates":[-118.569734,34.434702],"type":"Point"}
}