{
  "type": "Feature",
  "properties": {
    "addr:full":"4235 Spring Street La Mesa CA 91941",
    "addr:housenumber":"4235",
    "addr:postcode":"91941",
    "addr:street":"Spring Street",
    "iso:country":"US",
    "sg:address":"4235 Spring Street",
    "sg:city":"La Mesa",
    "sg:classifiers":[
        {
            "category":"Restaurant",
            "type":"Food & Drink"
        }
    ],
    "sg:phone":"+1 619 465 7000",
    "sg:postcode":"91941",
    "sg:province":"CA",
    "sg:tags":[
        "diner"
    ],
    "sg:website":"www.dennys.com",
    "wof:name":"Denny's Restautant",
    "wof:placetype":"venue"
},
  "geometry": {"coordinates":[-117.01512200000001,32.756285],"type":"Point"}
}