{
  "type": "Feature",
  "properties": {
    "addr:full":"6751 Stanton Ave Buena Park CA 90621",
    "addr:housenumber":"6751",
    "addr:postcode":"90621",
    "addr:street":"Stanton Ave",
    "iso:country":"US",
    "sg:address":"6751 Stanton Ave",
    "sg:city":"Buena Park",
    "sg:classifiers":[
        {
            "category":"Building & Trades",
            "subcategory":"Construction",
            "type":"Services"
        }
    ],
    "sg:phone":"+1 714 522 7863",
    "sg:postcode":"90621",
    "sg:province":"CA",
    "wof:name":"E&C Industries",
    "wof:placetype":"venue"
},
  "geometry": {"coordinates":[-117.99378299999999,33.862062],"type":"Point"}
}