{
  "type": "Feature",
  "properties": {
    "iso:country":"US",
    "sg:address":"25688 Baseline St",
    "sg:city":"San Bernardino",
    "sg:classifiers":[
        {
            "category":"Restaurant",
            "type":"Food & Drink"
        }
    ],
    "sg:phone":"+1 909 884 5252",
    "sg:postcode":"92410",
    "sg:province":"CA",
    "wof:name":"Brian's Super Burger",
    "wof:placetype":"venue"
},
  "geometry": {"coordinates":[-117.24466700000001,34.121389],"type":"Point"}
}