{
  "type": "Feature",
  "properties": {
    "iso:country":"US",
    "sg:address":"9349 Melvin Ave",
    "sg:city":"Northridge",
    "sg:classifiers":[
        {
            "category":"Shopping",
            "subcategory":"Bicycles & Sporting Goods",
            "type":"Retail Goods"
        }
    ],
    "sg:phone":"+1 818 341 9222",
    "sg:postcode":"91324",
    "sg:province":"CA",
    "sg:tags":[
        "equipment",
        "skateboard"
    ],
    "wof:name":"Empireskate Board Shop",
    "wof:placetype":"venue"
},
  "geometry": {"coordinates":[-118.5602,34.239819],"type":"Point"}
}