{
  "type": "Feature",
  "properties": {
    "addr:full":"113 E St Davis CA 95616",
    "addr:housenumber":"113",
    "addr:postcode":"95616",
    "addr:street":"E St",
    "iso:country":"US",
    "sg:address":"113 E St",
    "sg:city":"Davis",
    "sg:classifiers":[
        {
            "category":"Shopping",
            "subcategory":"Gifts & Souvenirs",
            "type":"Retail Goods"
        }
    ],
    "sg:phone":"+1 530 750 2701",
    "sg:postcode":"95616",
    "sg:province":"CA",
    "sg:tags":[
        "shop"
    ],
    "wof:name":"Home & Garden Beautiful",
    "wof:placetype":"venue"
},
  "geometry": {"coordinates":[-121.741112,38.543068],"type":"Point"}
}