{
  "type": "Feature",
  "properties": {
    "iso:country":"US",
    "sg:address":"1517 Vernon Ave",
    "sg:city":"Modesto",
    "sg:classifiers":[
        {
            "category":"Personal",
            "type":"Services"
        }
    ],
    "sg:phone":"+1 209 312 2089",
    "sg:postcode":"95351",
    "sg:province":"CA",
    "sg:tags":[
        "therapist",
        "massage"
    ],
    "wof:name":"Massage For The Health Of It",
    "wof:placetype":"venue"
},
  "geometry": {"coordinates":[-121.02811699999999,37.619563],"type":"Point"}
}