{
  "type": "Feature",
  "properties": {
    "addr:full":"1300 S Santa Fe Ave Compton CA 90221",
    "addr:housenumber":"1300",
    "addr:postcode":"90221",
    "addr:street":"S Santa Fe Ave",
    "iso:country":"US",
    "sg:address":"1300 S Santa Fe Ave",
    "sg:city":"Compton",
    "sg:classifiers":[
        {
            "category":"Freight",
            "type":"Transportation"
        }
    ],
    "sg:phone":"+1 310 898 3848",
    "sg:postcode":"90221",
    "sg:province":"CA",
    "sg:tags":[
        "operator",
        "local",
        "trucking"
    ],
    "wof:name":"Demenno Kerdoon",
    "wof:placetype":"venue"
},
  "geometry": {"coordinates":[-118.215653,33.883308],"type":"Point"}
}