{
  "type": "Feature",
  "properties": {
    "iso:country":"US",
    "sg:address":"2336 Midvale Ave",
    "sg:city":"Los Angeles",
    "sg:classifiers":[
        {
            "category":"Real Estate",
            "subcategory":"Architect",
            "type":"Services"
        }
    ],
    "sg:phone":"+1 310 441 9590",
    "sg:postcode":"90064",
    "sg:province":"CA",
    "wof:name":"Wehmueller & Stephens",
    "wof:placetype":"venue"
},
  "geometry": {"coordinates":[-118.429985,34.040502],"type":"Point"}
}