{
  "type": "Feature",
  "properties": {
    "iso:country":"US",
    "sg:address":"3530 Catalina Dr",
    "sg:city":"Carlsbad",
    "sg:classifiers":[
        {
            "category":"Building & Trades",
            "subcategory":"Construction",
            "type":"Services"
        }
    ],
    "sg:phone":"+1 760 434 3607",
    "sg:postcode":"92010",
    "sg:province":"CA",
    "sg:tags":[
        "excavation",
        "contractor"
    ],
    "wof:name":"Last Ditch Excavation",
    "wof:placetype":"venue"
},
  "geometry": {"coordinates":[-117.319776,33.166228],"type":"Point"}
}