{
  "type": "Feature",
  "properties": {
    "addr:full":"515 E Edna Pl Covina CA 91723",
    "addr:housenumber":"515",
    "addr:postcode":"91723",
    "addr:street":"E Edna Pl",
    "iso:country":"US",
    "sg:address":"515 E Edna Pl",
    "sg:city":"Covina",
    "sg:classifiers":[
        {
            "category":"Retail",
            "subcategory":"Repair Shop",
            "type":"Services"
        }
    ],
    "sg:phone":"+1 626 858 4750",
    "sg:postcode":"91723",
    "sg:province":"CA",
    "sg:tags":[
        "equipment",
        "welding"
    ],
    "wof:name":"Vernon Electric",
    "wof:placetype":"venue"
},
  "geometry": {"coordinates":[-117.87916300000001,34.093093],"type":"Point"}
}