{
  "type": "Feature",
  "properties": {
    "addr:full":"2425 S Eastern Ave City Of Commerce CA 90040",
    "addr:housenumber":"2425",
    "addr:postcode":"90040",
    "addr:street":"S Eastern Ave",
    "iso:country":"US",
    "sg:address":"2425 S Eastern Ave",
    "sg:city":"City Of Commerce",
    "sg:classifiers":[
        {
            "category":"Wholesale",
            "subcategory":"Durable Goods & Equipment",
            "type":"Manufacturing & Wholesale Goods"
        }
    ],
    "sg:phone":"+1 323 887 0200",
    "sg:postcode":"90040",
    "sg:province":"CA",
    "sg:tags":[
        "importer"
    ],
    "wof:name":"ZNO Co",
    "wof:placetype":"venue"
},
  "geometry": {"coordinates":[-118.159255,34.003765],"type":"Point"}
}