{
  "type": "Feature",
  "properties": {
    "iso:country":"US",
    "sg:address":"684 Ponderosa St",
    "sg:city":"Seaside",
    "sg:classifiers":[
        {
            "category":"Autos & Motor Vehicles",
            "subcategory":"Automobile Sales",
            "type":"Retail Goods"
        }
    ],
    "sg:phone":"+1 831 899 3696",
    "sg:postcode":"93955",
    "sg:province":"CA",
    "sg:tags":[
        "new",
        "used",
        "car"
    ],
    "wof:name":"Coppa Bella Motors",
    "wof:placetype":"venue"
},
  "geometry": {"coordinates":[-121.849003,36.610498],"type":"Point"}
}