{
  "type": "Feature",
  "properties": {
    "iso:country":"US",
    "sg:address":"3727 N Hughes Ave",
    "sg:city":"Fresno",
    "sg:classifiers":[
        {
            "category":"Government",
            "subcategory":"Post Office",
            "type":"Public Place"
        }
    ],
    "sg:phone":"+1 559 222 2138",
    "sg:postcode":"93705",
    "sg:province":"CA",
    "wof:name":"Hughes Station",
    "wof:placetype":"venue"
},
  "geometry": {"coordinates":[-119.83548399999999,36.786029],"type":"Point"}
}