{
  "type": "Feature",
  "properties": {
    "addr:full":"2300 River Plaza Dr Sacramento CA 95833",
    "addr:housenumber":"2300",
    "addr:postcode":"95833",
    "addr:street":"River Plaza Dr",
    "iso:country":"US",
    "sg:address":"2300 River Plaza Dr",
    "sg:city":"Sacramento",
    "sg:classifiers":[
        {
            "category":"Organizations",
            "subcategory":"Non-profit Organization",
            "type":"Services"
        }
    ],
    "sg:phone":"+1 916 561 5520",
    "sg:postcode":"95833",
    "sg:province":"CA",
    "sg:tags":[
        "charity",
        "foundations-educational",
        "philanthropic",
        "research"
    ],
    "wof:name":"Agricultural Clean Water Initiative Foundation",
    "wof:placetype":"venue"
},
  "geometry": {"coordinates":[-121.51853199999999,38.6073],"type":"Point"}
}