{
  "type": "Feature",
  "properties": {
    "addr:full":"1620 Tiburon Blvd Belvedere Tiburon CA 94920",
    "addr:housenumber":"1620",
    "addr:postcode":"94920",
    "addr:street":"Tiburon Blvd",
    "iso:country":"US",
    "sg:address":"1620 Tiburon Blvd",
    "sg:city":"Belvedere Tiburon",
    "sg:classifiers":[
        {
            "category":"Education",
            "subcategory":"College",
            "type":"Public Place"
        }
    ],
    "sg:phone":"+1 415 435 6191",
    "sg:postcode":"94920",
    "sg:province":"CA",
    "wof:name":"Trustees of Mt Holyoke College",
    "wof:placetype":"venue"
},
  "geometry": {"coordinates":[-122.458119,37.874731],"type":"Point"}
}