{
  "type": "Feature",
  "properties": {
    "addr:full":"9099 Soquel Drive Aptos CA 95003",
    "addr:housenumber":"9099",
    "addr:postcode":"ca 95003",
    "addr:street":"Soquel Drive",
    "iso:country":"US",
    "sg:address":"9099 Soquel Drive",
    "sg:city":"Aptos",
    "sg:classifiers":[
        {
            "category":"Health Services",
            "subcategory":"Doctor",
            "type":"Services"
        }
    ],
    "sg:phone":"+1 831 662 8421",
    "sg:postcode":"95003",
    "sg:province":"CA",
    "wof:name":"Malka Deborah MD PHD",
    "wof:placetype":"venue"
},
  "geometry": {"coordinates":[-121.88600700000001,36.975872],"type":"Point"}
}