{
  "type": "Feature",
  "properties": {
    "addr:full":"900 E Altadena Dr Altadena CA 91001",
    "addr:housenumber":"900",
    "addr:postcode":"91001",
    "addr:street":"E Altadena Dr",
    "iso:country":"US",
    "sg:address":"900 E Altadena Dr",
    "sg:city":"Altadena",
    "sg:classifiers":[
        {
            "category":"Shopping",
            "subcategory":"Florist",
            "type":"Retail Goods"
        }
    ],
    "sg:phone":"+1 626 657 2290",
    "sg:postcode":"91001",
    "sg:province":"CA",
    "wof:name":"Altadena Buds And Bows",
    "wof:placetype":"venue"
},
  "geometry": {"coordinates":[-118.131005,34.189934],"type":"Point"}
}