{
  "type": "Feature",
  "properties": {
    "addr:full":"1067 Broxton Ave Los Angeles CA 90024",
    "addr:housenumber":"1067",
    "addr:postcode":"90024",
    "addr:street":"Broxton Ave",
    "iso:country":"US",
    "sg:address":"1067 Broxton Ave",
    "sg:city":"Los Angeles",
    "sg:classifiers":[
        {
            "category":"Shopping",
            "subcategory":"Beauty & Cosmetics",
            "type":"Retail Goods"
        },
        {
            "category":"Personal",
            "subcategory":"Skin Care",
            "type":"Services"
        }
    ],
    "sg:phone":"+1 310 209 6252",
    "sg:postcode":"90024",
    "sg:province":"CA",
    "sg:tags":[
        "supply"
    ],
    "wof:name":"Emma's European Beauty Signature",
    "wof:placetype":"venue"
},
  "geometry": {"coordinates":[-118.44604,34.061274],"type":"Point"}
}