{
  "type": "Feature",
  "properties": {
    "addr:full":"9901 Paramount Blvd Downey CA 90240",
    "addr:housenumber":"9901",
    "addr:postcode":"90240",
    "addr:street":"Paramount Blvd",
    "iso:country":"US",
    "sg:address":"9901 Paramount Blvd",
    "sg:city":"Downey",
    "sg:classifiers":[
        {
            "category":"Real Estate",
            "subcategory":"Real Estate Agent",
            "type":"Services"
        }
    ],
    "sg:phone":"+1 562 806 1616",
    "sg:postcode":"90240",
    "sg:province":"CA",
    "wof:name":"Casa Bella Properties",
    "wof:placetype":"venue"
},
  "geometry": {"coordinates":[-118.129538,33.954401],"type":"Point"}
}