{
  "type": "Feature",
  "properties": {
    "addr:full":"21600 Hawthorne Blvd Torrance CA 90503",
    "addr:housenumber":"21600",
    "addr:postcode":"90503",
    "addr:street":"Hawthorne Blvd",
    "iso:country":"US",
    "sg:address":"21600 Hawthorne Blvd",
    "sg:city":"Torrance",
    "sg:classifiers":[
        {
            "category":"Shopping",
            "subcategory":"Hobbies, Toys, & Games",
            "type":"Retail Goods"
        }
    ],
    "sg:phone":"+1 310 371 1737",
    "sg:postcode":"90503",
    "sg:province":"CA",
    "sg:tags":[
        "toy",
        "store"
    ],
    "wof:name":"Amazing Creations",
    "wof:placetype":"venue"
},
  "geometry": {"coordinates":[-118.35217,33.830544],"type":"Point"}
}