{
  "type": "Feature",
  "properties": {
    "addr:full":"1111 N California Ave La Puente CA 91744",
    "addr:housenumber":"1111",
    "addr:postcode":"91744",
    "addr:street":"N California Ave",
    "iso:country":"US",
    "sg:address":"1111 N California Ave",
    "sg:city":"La Puente",
    "sg:classifiers":[
        {
            "category":"Education",
            "subcategory":"School",
            "type":"Public Place"
        }
    ],
    "sg:phone":"+1 626 933 5200",
    "sg:postcode":"91744",
    "sg:province":"CA",
    "wof:name":"California Elementary School",
    "wof:placetype":"venue"
},
  "geometry": {"coordinates":[-117.954764,34.045275],"type":"Point"}
}