{
  "type": "Feature",
  "properties": {
    "iso:country":"US",
    "sg:address":"701 E Elizabeth Dr",
    "sg:city":"Orange",
    "sg:classifiers":[
        {
            "category":"Professional",
            "type":"Services"
        }
    ],
    "sg:phone":"+1 714 997 3175",
    "sg:postcode":"92867",
    "sg:province":"CA",
    "wof:name":"Bill McGuire Inc",
    "wof:placetype":"venue"
},
  "geometry": {"coordinates":[-117.846575,33.805572],"type":"Point"}
}