{
  "type": "Feature",
  "properties": {
    "iso:country":"US",
    "sg:address":"2006 Dufour St",
    "sg:city":"Redondo Beach",
    "sg:classifiers":[
        {
            "category":"Manufacturing",
            "subcategory":"Textiles",
            "type":"Manufacturing & Wholesale Goods"
        }
    ],
    "sg:phone":"+1 310 376 7050",
    "sg:postcode":"90278",
    "sg:province":"CA",
    "sg:tags":[
        "mill",
        "fabric",
        "cotton"
    ],
    "wof:name":"Suttle Exposure",
    "wof:placetype":"venue"
},
  "geometry": {"coordinates":[-118.374984,33.885513],"type":"Point"}
}