{
  "type": "Feature",
  "properties": {
    "iso:country":"US",
    "sg:address":"2340 Gold River Rd",
    "sg:city":"Rancho Cordova",
    "sg:classifiers":[
        {
            "category":"Retail",
            "subcategory":"Auto Repair",
            "type":"Services"
        }
    ],
    "sg:phone":"+1 916 638 7868",
    "sg:postcode":"95670",
    "sg:province":"CA",
    "sg:tags":[
        "repairing",
        "automobile"
    ],
    "wof:name":"Tomz Kustoms",
    "wof:placetype":"venue"
},
  "geometry": {"coordinates":[-121.26162100000001,38.618911],"type":"Point"}
}