{
  "type": "Feature",
  "properties": {
    "addr:full":"23937 Clinton Keith Rd Wildomar CA 92595",
    "addr:housenumber":"23937",
    "addr:postcode":"92595",
    "addr:street":"Clinton Keith Rd",
    "iso:country":"US",
    "sg:address":"23937 Clinton Keith Rd",
    "sg:city":"Wildomar",
    "sg:classifiers":[
        {
            "category":"Fast Food",
            "type":"Food & Drink"
        },
        {
            "category":"Restaurant",
            "type":"Food & Drink"
        }
    ],
    "sg:phone":"+1 951 461 2621",
    "sg:postcode":"92595",
    "sg:province":"CA",
    "sg:tags":[
        "american",
        "hot",
        "hamburger",
        "dog"
    ],
    "sg:website":"http://www.wienerschnitzel.com",
    "wof:name":"Wienerschnitzel",
    "wof:placetype":"venue"
},
  "geometry": {"coordinates":[-117.242006,33.59749],"type":"Point"}
}