{
  "type": "Feature",
  "properties": {
    "addr:full":"406 Garces Dr San Francisco CA 94132",
    "addr:housenumber":"406",
    "addr:postcode":"94132",
    "addr:street":"Garces Dr",
    "iso:country":"US",
    "sg:address":"406 Garces Dr",
    "sg:city":"San Francisco",
    "sg:classifiers":[
        {
            "category":"Building & Trades",
            "subcategory":"Construction",
            "type":"Services"
        }
    ],
    "sg:phone":"+1 415 239 2654",
    "sg:postcode":"94132",
    "sg:province":"CA",
    "sg:tags":[
        "painter"
    ],
    "wof:name":"Giampolini & Co",
    "wof:placetype":"venue"
},
  "geometry": {"coordinates":[-122.48445100000001,37.716273],"type":"Point"}
}