{
  "type": "Feature",
  "properties": {
    "iso:country":"US",
    "sg:address":"14091 Newport Ave",
    "sg:city":"Tustin",
    "sg:classifiers":[
        {
            "category":"Banks & Credit Unions",
            "subcategory":"Financial Services",
            "type":"Services"
        }
    ],
    "sg:phone":"+1 714 573 2136",
    "sg:postcode":"92780",
    "sg:province":"CA",
    "sg:tags":[
        "broker",
        "mortgage"
    ],
    "wof:name":"Wells Fargo Financial",
    "wof:placetype":"venue"
},
  "geometry": {"coordinates":[-117.824759,33.735787],"type":"Point"}
}