{
  "type": "Feature",
  "properties": {
    "addr:full":"13295 Black Mountain Rd San Diego CA 92129",
    "addr:housenumber":"13295",
    "addr:postcode":"92129",
    "addr:street":"Black Mountain Rd",
    "iso:country":"US",
    "sg:address":"13295 Black Mountain Rd",
    "sg:city":"San Diego",
    "sg:classifiers":[
        {
            "category":"Banks & Credit Unions",
            "subcategory":"Investment Brokerage",
            "type":"Services"
        }
    ],
    "sg:phone":"+1 858 484 1700",
    "sg:postcode":"92129",
    "sg:province":"CA",
    "sg:tags":[
        "stock",
        "bond"
    ],
    "wof:name":"Edward Jones Co",
    "wof:placetype":"venue"
},
  "geometry": {"coordinates":[-117.12990600000001,32.954574],"type":"Point"}
}