{
  "type": "Feature",
  "properties": {
    "iso:country":"US",
    "sg:address":"10810 San Pablo Ave",
    "sg:city":"El Cerrito",
    "sg:classifiers":[
        {
            "category":"Education",
            "subcategory":"Special Training",
            "type":"Public Place"
        }
    ],
    "sg:phone":"+1 510 559 1400",
    "sg:postcode":"94530",
    "sg:province":"CA",
    "sg:tags":[
        "tutoring"
    ],
    "wof:name":"Sylvan Learning Center",
    "wof:placetype":"venue"
},
  "geometry": {"coordinates":[-122.310519,37.9143],"type":"Point"}
}