{
  "type": "Feature",
  "properties": {
    "iso:country":"US",
    "sg:address":"5707 Chenault Dr",
    "sg:city":"Modesto",
    "sg:classifiers":[
        {
            "category":"Freight",
            "type":"Transportation"
        }
    ],
    "sg:phone":"+1 209 567 0767",
    "sg:postcode":"95356",
    "sg:province":"CA",
    "sg:tags":[
        "trucking"
    ],
    "wof:name":"Online Trucking",
    "wof:placetype":"venue"
},
  "geometry": {"coordinates":[-120.991294,37.723197],"type":"Point"}
}