{
  "type": "Feature",
  "properties": {
    "iso:country":"US",
    "sg:address":"37733 Rd 76",
    "sg:city":"Dinuba",
    "sg:classifiers":[
        {
            "category":"Farming",
            "subcategory":"Farm",
            "type":"Manufacturing & Wholesale Goods"
        }
    ],
    "sg:phone":"+1 559 591 6308",
    "sg:postcode":"93618",
    "sg:province":"CA",
    "wof:name":"River View Farms",
    "wof:placetype":"venue"
},
  "geometry": {"coordinates":[-119.403008,36.473211],"type":"Point"}
}