{
  "type": "Feature",
  "properties": {
    "addr:full":"710 N Van Ness Ave Los Angeles CA 90038",
    "addr:housenumber":"710",
    "addr:postcode":"90038",
    "addr:street":"N Van Ness Ave",
    "iso:country":"US",
    "sg:address":"710 N Van Ness Ave",
    "sg:city":"Los Angeles",
    "sg:classifiers":[
        {
            "category":"Shopping",
            "subcategory":"Gifts & Souvenirs",
            "type":"Retail Goods"
        }
    ],
    "sg:phone":"+1 323 462 5333",
    "sg:postcode":"90038",
    "sg:province":"CA",
    "sg:tags":[
        "shop"
    ],
    "wof:name":"A Little Something",
    "wof:placetype":"venue"
},
  "geometry": {"coordinates":[-118.315639,34.084417],"type":"Point"}
}