{
  "type": "Feature",
  "properties": {
    "addr:full":"14136 Okanogan Dr Saratoga CA 95070",
    "addr:housenumber":"14136",
    "addr:postcode":"95070",
    "addr:street":"Okanogan Dr",
    "iso:country":"US",
    "sg:address":"14136 Okanogan Dr",
    "sg:city":"Saratoga",
    "sg:classifiers":[
        {
            "category":"Retail",
            "subcategory":"Animal Services",
            "type":"Services"
        }
    ],
    "sg:phone":"+1 408 544 8015",
    "sg:postcode":"95070",
    "sg:province":"CA",
    "sg:tags":[
        "pet",
        "exercising",
        "sitting"
    ],
    "wof:name":"Nathan And Shelly Sarkisian Foundation",
    "wof:placetype":"venue"
},
  "geometry": {"coordinates":[-122.015226,37.262224],"type":"Point"}
}