{
  "type": "Feature",
  "properties": {
    "iso:country":"US",
    "sg:address":"8141 2nd St",
    "sg:city":"Downey",
    "sg:classifiers":[
        {
            "category":"Health Services",
            "subcategory":"Clinic",
            "type":"Services"
        }
    ],
    "sg:phone":"+1 562 869 9001",
    "sg:postcode":"90241",
    "sg:province":"CA",
    "sg:tags":[
        "home"
    ],
    "wof:name":"Good Shepherd Home Care Inc",
    "wof:placetype":"venue"
},
  "geometry": {"coordinates":[-118.134724,33.942394],"type":"Point"}
}