{
  "type": "Feature",
  "properties": {
    "iso:country":"US",
    "sg:address":"690 Dolliver St",
    "sg:city":"Pismo Beach",
    "sg:classifiers":[
        {
            "category":"Restaurant",
            "type":"Food & Drink"
        }
    ],
    "sg:phone":"+1 805 773 6170",
    "sg:postcode":"93449",
    "sg:province":"CA",
    "wof:name":"Beach Burgers",
    "wof:placetype":"venue"
},
  "geometry": {"coordinates":[-120.640623,35.140029],"type":"Point"}
}