{
  "type": "Feature",
  "properties": {
    "iso:country":"US",
    "sg:address":"115 S Palm Canyon Dr",
    "sg:city":"Palm Springs",
    "sg:classifiers":[
        {
            "category":"Professional",
            "type":"Services"
        }
    ],
    "sg:phone":"+1 760 327 8891",
    "sg:postcode":"92262",
    "sg:province":"CA",
    "wof:name":"Frank Worth Exhibit",
    "wof:placetype":"venue"
},
  "geometry": {"coordinates":[-116.54685499999999,33.822856],"type":"Point"}
}