{
  "type": "Feature",
  "properties": {
    "iso:country":"US",
    "sg:address":"3878 Hitch Blvd",
    "sg:city":"Moorpark",
    "sg:classifiers":[
        {
            "category":"Retail",
            "subcategory":"Repair Shop",
            "type":"Services"
        }
    ],
    "sg:phone":"+1 805 532 2116",
    "sg:postcode":"93021",
    "sg:province":"CA",
    "sg:tags":[
        "sharpening",
        "grooming",
        "supply"
    ],
    "wof:name":"L & C Sharpening",
    "wof:placetype":"venue"
},
  "geometry": {"coordinates":[-118.914304,34.262695],"type":"Point"}
}