{
  "type": "Feature",
  "properties": {
    "iso:country":"US",
    "sg:address":"7213 1/2 Santa Monica Blvd",
    "sg:city":"West Hollywood",
    "sg:classifiers":[
        {
            "category":"Personal",
            "subcategory":"Tattoo Parlor",
            "type":"Services"
        },
        {
            "category":"Personal",
            "subcategory":"Piercing",
            "type":"Services"
        }
    ],
    "sg:phone":"+1 323 876 5048",
    "sg:postcode":"90046",
    "sg:province":"CA",
    "sg:website":"www.velvetgripfamily.com",
    "wof:name":"Velvet Grip",
    "wof:placetype":"venue"
},
  "geometry": {"coordinates":[-118.34670800000001,34.090832],"type":"Point"}
}