{
  "type": "Feature",
  "properties": {
    "addr:full":"1068 Mission St San Francisco CA 94103",
    "addr:housenumber":"1068",
    "addr:postcode":"94103",
    "addr:street":"Mission St",
    "iso:country":"US",
    "sg:address":"1068 Mission St",
    "sg:city":"San Francisco",
    "sg:classifiers":[
        {
            "category":"Professional",
            "type":"Services"
        }
    ],
    "sg:phone":"+1 415 522 1320",
    "sg:postcode":"94103",
    "sg:province":"CA",
    "wof:name":"Dick Morganti Nibbi",
    "wof:placetype":"venue"
},
  "geometry": {"coordinates":[-122.409768,37.780486],"type":"Point"}
}