{
  "type": "Feature",
  "properties": {
    "addr:full":"1335 Coffee Rd Modesto CA 95355",
    "addr:housenumber":"1335",
    "addr:postcode":"ca 95355",
    "addr:street":"Coffee Rd",
    "iso:country":"US",
    "sg:address":"1335 Coffee Rd",
    "sg:city":"Modesto",
    "sg:classifiers":[
        {
            "category":"Health Services",
            "subcategory":"Health Practitioner",
            "type":"Services"
        }
    ],
    "sg:phone":"+1 209 576 1946",
    "sg:postcode":"95355",
    "sg:province":"CA",
    "sg:tags":[
        "therapist",
        "physical"
    ],
    "wof:name":"Golden Bear Physical Therapy",
    "wof:placetype":"venue"
},
  "geometry": {"coordinates":[-120.975731,37.662746],"type":"Point"}
}