{
  "type": "Feature",
  "properties": {
    "iso:country":"US",
    "sg:address":"436 Clementina St",
    "sg:city":"San Francisco",
    "sg:classifiers":[
        {
            "category":"Retail",
            "subcategory":"Auto Repair",
            "type":"Services"
        }
    ],
    "sg:phone":"+1 415 255 8882",
    "sg:postcode":"94103",
    "sg:province":"CA",
    "sg:tags":[
        "repairing",
        "automobile"
    ],
    "wof:name":"Tom's Auto Svc",
    "wof:placetype":"venue"
},
  "geometry": {"coordinates":[-122.405564,37.779641],"type":"Point"}
}