{
  "type": "Feature",
  "properties": {
    "addr:full":"2500 Shelter Island Dr San Diego CA 92106",
    "addr:housenumber":"2500",
    "addr:postcode":"92106",
    "addr:street":"Shelter Island Dr",
    "iso:country":"US",
    "sg:address":"2500 Shelter Island Dr",
    "sg:city":"San Diego",
    "sg:classifiers":[
        {
            "category":"Recreation",
            "subcategory":"Marina",
            "type":"Entertainment"
        }
    ],
    "sg:phone":"+1 619 221 6930",
    "sg:postcode":"92106",
    "sg:province":"CA",
    "sg:tags":[
        "repairing",
        "boat"
    ],
    "wof:name":"Kenttenburg Marine",
    "wof:placetype":"venue"
},
  "geometry": {"coordinates":[-117.227041,32.72033],"type":"Point"}
}