{
  "type": "Feature",
  "properties": {
    "addr:full":"3024 Pacific Ave Livermore CA 94550",
    "addr:housenumber":"3024",
    "addr:postcode":"94550",
    "addr:street":"Pacific Ave",
    "iso:country":"US",
    "sg:address":"3024 Pacific Ave",
    "sg:city":"Livermore",
    "sg:classifiers":[
        {
            "category":"Shopping",
            "subcategory":"Pharmacy",
            "type":"Retail Goods"
        }
    ],
    "sg:phone":"+1 925 443 8088",
    "sg:postcode":"94550",
    "sg:province":"CA",
    "wof:name":"Medicine Shoppe Pharmacy",
    "wof:placetype":"venue"
},
  "geometry": {"coordinates":[-121.75895,37.676254],"type":"Point"}
}