{
  "type": "Feature",
  "properties": {
    "addr:full":"1335 Via Vida Nueva Escondido CA 92026",
    "addr:housenumber":"1335",
    "addr:postcode":"92026",
    "addr:street":"Via Vida Nueva",
    "iso:country":"US",
    "sg:address":"1335 Via Vida Nueva",
    "sg:city":"Escondido",
    "sg:classifiers":[
        {
            "category":"Retail",
            "subcategory":"Auto Repair",
            "type":"Services"
        }
    ],
    "sg:phone":"+1 760 745 5613",
    "sg:postcode":"92026",
    "sg:province":"CA",
    "sg:tags":[
        "wrecker"
    ],
    "wof:name":"Alpha Heavy Duty Towing",
    "wof:placetype":"venue"
},
  "geometry": {"coordinates":[-117.110707,33.147082],"type":"Point"}
}