{
  "type": "Feature",
  "properties": {
    "addr:full":"821 N Arquilla Rd Palm Springs CA 92262",
    "addr:housenumber":"821",
    "addr:postcode":"92262",
    "addr:street":"N Arquilla Rd",
    "iso:country":"US",
    "sg:address":"821 N Arquilla Rd",
    "sg:city":"Palm Springs",
    "sg:classifiers":[
        {
            "category":"Manufacturing",
            "subcategory":"Tools & Machinery",
            "type":"Manufacturing & Wholesale Goods"
        }
    ],
    "sg:phone":"+1 760 322 3277",
    "sg:postcode":"92262",
    "sg:province":"CA",
    "sg:tags":[
        "measuring",
        "instrument",
        "electrical",
        "mfg"
    ],
    "wof:name":"Hydro-Eye LLC",
    "wof:placetype":"venue"
},
  "geometry": {"coordinates":[-116.53481499999999,33.834093],"type":"Point"}
}