{
  "type": "Feature",
  "properties": {
    "addr:full":"19361 Baywater Ln Huntington Beach CA 92646",
    "addr:postcode":"19361;92646",
    "addr:street":"Baywater Ln",
    "iso:country":"US",
    "sg:address":"19361 Baywater Ln",
    "sg:city":"Huntington Beach",
    "sg:classifiers":[
        {
            "category":"Professional",
            "type":"Services"
        }
    ],
    "sg:phone":"+1 714 963 0168",
    "sg:postcode":"92646",
    "sg:province":"CA",
    "wof:name":"Shada Envmtl Specialists",
    "wof:placetype":"venue"
},
  "geometry": {"coordinates":[-117.976483,33.680758],"type":"Point"}
}