{
  "type": "Feature",
  "properties": {
    "iso:country":"US",
    "sg:address":"340 Moss St Apt A4",
    "sg:city":"Chula Vista",
    "sg:classifiers":[
        {
            "category":"Real Estate",
            "subcategory":"Real Estate Operator",
            "type":"Services"
        }
    ],
    "sg:phone":"+1 619 420 5443",
    "sg:postcode":"91911",
    "sg:province":"CA",
    "sg:tags":[
        "apartment"
    ],
    "wof:name":"Megan Court Apartments",
    "wof:placetype":"venue"
},
  "geometry": {"coordinates":[-117.07199900000001,32.616699],"type":"Point"}
}