{
  "type": "Feature",
  "properties": {
    "addr:full":"3555 Sonoma Blvd Vallejo CA 94590",
    "addr:housenumber":"3555",
    "addr:postcode":"94590",
    "addr:street":"Sonoma Blvd",
    "iso:country":"US",
    "sg:address":"3555 Sonoma Blvd",
    "sg:city":"Vallejo",
    "sg:classifiers":[
        {
            "category":"Shopping",
            "subcategory":"Jewelry",
            "type":"Retail Goods"
        }
    ],
    "sg:phone":"+1 707 552 2000",
    "sg:postcode":"94590",
    "sg:province":"CA",
    "sg:tags":[
        "jeweler"
    ],
    "wof:name":"De Mares Jewelers",
    "wof:placetype":"venue"
},
  "geometry": {"coordinates":[-122.255371,38.12182],"type":"Point"}
}