{
  "type": "Feature",
  "properties": {
    "addr:full":"1638 I St Brawley CA 92227",
    "addr:housenumber":"1638",
    "addr:postcode":"92227",
    "addr:street":"I St",
    "iso:country":"US",
    "sg:address":"1638 I St",
    "sg:city":"Brawley",
    "sg:classifiers":[
        {
            "category":"Farming",
            "subcategory":"Farm & Veterinary Services",
            "type":"Manufacturing & Wholesale Goods"
        }
    ],
    "sg:phone":"+1 760 344 0370",
    "sg:postcode":"92227",
    "sg:province":"CA",
    "sg:tags":[
        "processing",
        "feedlot",
        "cattle"
    ],
    "wof:name":"W W Enterprises",
    "wof:placetype":"venue"
},
  "geometry": {"coordinates":[-115.512766,32.974904],"type":"Point"}
}