{
  "type": "Feature",
  "properties": {
    "iso:country":"US",
    "sg:address":"2752 Walnut Ave",
    "sg:city":"Tustin",
    "sg:classifiers":[
        {
            "category":"Professional",
            "subcategory":"Engineering",
            "type":"Services"
        },
        {
            "category":"Utilities",
            "subcategory":"Electric",
            "type":"Services"
        },
        {
            "category":"Building & Trades",
            "subcategory":"Construction",
            "type":"Services"
        },
        {
            "category":"Building & Trades",
            "subcategory":"Electrical",
            "type":"Services"
        }
    ],
    "sg:phone":"+1 714 505 1501",
    "sg:postcode":"92780",
    "sg:province":"CA",
    "sg:tags":[
        "repair",
        "industrial",
        "electrician",
        "energy",
        "systems-service",
        "equipment",
        "equipment-repair",
        "contractors-commercial",
        "solar",
        "engineer"
    ],
    "sg:website":"http://www.ajk-a.com",
    "wof:name":"Aj Kirkwood & Associates",
    "wof:placetype":"venue"
},
  "geometry": {"coordinates":[-117.806,33.714802],"type":"Point"}
}