{
  "type": "Feature",
  "properties": {
    "iso:country":"US",
    "sg:address":"1813 E Colorado Blvd",
    "sg:city":"Pasadena",
    "sg:classifiers":[
        {
            "category":"Autos & Motor Vehicles",
            "subcategory":"Fuel & Gas Station",
            "type":"Retail Goods"
        }
    ],
    "sg:phone":"+1 626 440 9761",
    "sg:postcode":"91107",
    "sg:province":"CA",
    "sg:website":"www.mobil.com",
    "wof:name":"K & S Mobil Service Station",
    "wof:placetype":"venue"
},
  "geometry": {"coordinates":[-118.112999,34.146099],"type":"Point"}
}