{
  "type": "Feature",
  "properties": {
    "addr:full":"2228 Bacon St San Diego CA 92107",
    "addr:housenumber":"2228",
    "addr:postcode":"92107",
    "addr:street":"Bacon St",
    "iso:country":"US",
    "sg:address":"2228 Bacon St",
    "sg:city":"San Diego",
    "sg:classifiers":[
        {
            "category":"Bars & Pubs",
            "subcategory":"Lounge",
            "type":"Food & Drink"
        },
        {
            "category":"Arts & Performance",
            "subcategory":"Music",
            "type":"Entertainment"
        }
    ],
    "sg:phone":"+1 619 222 8131",
    "sg:postcode":"92107",
    "sg:province":"CA",
    "sg:tags":[
        "venue"
    ],
    "sg:website":"www.dreamstreetlive.com",
    "wof:name":"Dreamstreet Live",
    "wof:placetype":"venue"
},
  "geometry": {"coordinates":[-117.246002,32.752499],"type":"Point"}
}