{
  "type": "Feature",
  "properties": {
    "iso:country":"US",
    "sg:address":"31951 Dove Canyon Dr",
    "sg:city":"Trabuco Canyon",
    "sg:classifiers":[
        {
            "category":"Banks & Credit Unions",
            "subcategory":"Bank",
            "type":"Services"
        }
    ],
    "sg:phone":"+1 949 766 4795",
    "sg:postcode":"92679",
    "sg:province":"CA",
    "sg:tags":[
        "mortgage"
    ],
    "wof:name":"Left Bank Mortgage",
    "wof:placetype":"venue"
},
  "geometry": {"coordinates":[-117.576114,33.642321],"type":"Point"}
}