{
  "type": "Feature",
  "properties": {
    "iso:country":"US",
    "sg:address":"434 S Mollison Ave",
    "sg:city":"El Cajon",
    "sg:classifiers":[
        {
            "category":"Real Estate",
            "subcategory":"Real Estate Operator",
            "type":"Services"
        }
    ],
    "sg:phone":"+1 619 444 6599",
    "sg:postcode":"92020",
    "sg:province":"CA",
    "sg:tags":[
        "building",
        "apartment"
    ],
    "wof:name":"El Tesoro Apartments",
    "wof:placetype":"venue"
},
  "geometry": {"coordinates":[-116.95102799999999,32.792449],"type":"Point"}
}