{
  "type": "Feature",
  "properties": {
    "addr:full":"27101 Aliso Creek Rd Aliso Viejo CA 92656",
    "addr:housenumber":"27101",
    "addr:postcode":"92656",
    "addr:street":"Aliso Creek Rd",
    "iso:country":"US",
    "sg:address":"27101 Aliso Creek Rd",
    "sg:city":"Aliso Viejo",
    "sg:classifiers":[
        {
            "category":"Education",
            "subcategory":"Dance Studio",
            "type":"Public Place"
        }
    ],
    "sg:phone":"+1 949 360 4233",
    "sg:postcode":"92656",
    "sg:province":"CA",
    "sg:tags":[
        "instruction",
        "dancing"
    ],
    "wof:name":"Classical Ballet Academy",
    "wof:placetype":"venue"
},
  "geometry": {"coordinates":[-117.72327300000001,33.569648],"type":"Point"}
}