{
  "type": "Feature",
  "properties": {
    "iso:country":"US",
    "sg:address":"3672 S Western Ave",
    "sg:city":"Los Angeles",
    "sg:classifiers":[
        {
            "category":"Personal",
            "subcategory":"Beauty Salon",
            "type":"Services"
        }
    ],
    "sg:phone":"+1 323 734 9446",
    "sg:postcode":"90018",
    "sg:province":"CA",
    "wof:name":"Joyce's Salon Of Beauty",
    "wof:placetype":"venue"
},
  "geometry": {"coordinates":[-118.308817,34.021517],"type":"Point"}
}