{
  "type": "Feature",
  "properties": {
    "addr:full":"20595 Pegasus St Tehachapi CA 93561",
    "addr:housenumber":"20595",
    "addr:postcode":"93561",
    "addr:street":"Pegasus St",
    "iso:country":"US",
    "sg:address":"20595 Pegasus St",
    "sg:city":"Tehachapi",
    "sg:classifiers":[
        {
            "category":"Retail",
            "subcategory":"Animal Services",
            "type":"Services"
        }
    ],
    "sg:phone":"+1 661 823 0307",
    "sg:postcode":"93561",
    "sg:province":"CA",
    "wof:name":"Tranquility Farm",
    "wof:placetype":"venue"
},
  "geometry": {"coordinates":[-118.619248,35.126818],"type":"Point"}
}