{
  "type": "Feature",
  "properties": {
    "iso:country":"US",
    "sg:address":"6300 Florence Ave",
    "sg:city":"Bell Gardens",
    "sg:classifiers":[
        {
            "category":"Retail",
            "subcategory":"Laundry & Dry Cleaning",
            "type":"Services"
        }
    ],
    "sg:phone":"+1 562 776 9123",
    "sg:postcode":"90201",
    "sg:province":"CA",
    "wof:name":"Tri Laundry",
    "wof:placetype":"venue"
},
  "geometry": {"coordinates":[-118.152432,33.965997],"type":"Point"}
}