{
  "type": "Feature",
  "properties": {
    "iso:country":"US",
    "sg:address":"1120 Mc Kendrie St",
    "sg:city":"San Jose",
    "sg:classifiers":[
        {
            "category":"Social Services",
            "type":"Services"
        }
    ],
    "sg:phone":"+1 408 244 6814",
    "sg:postcode":"95126",
    "sg:province":"CA",
    "sg:tags":[
        "worker"
    ],
    "wof:name":"Joann Kirkpatrick",
    "wof:placetype":"venue"
},
  "geometry": {"coordinates":[-121.925285,37.34075],"type":"Point"}
}