{
  "type": "Feature",
  "properties": {
    "addr:full":"1122 Rose Ave Selma CA 93662",
    "addr:housenumber":"1122",
    "addr:postcode":"93662",
    "addr:street":"Rose Ave",
    "iso:country":"US",
    "sg:address":"1122 Rose Ave",
    "sg:city":"Selma",
    "sg:classifiers":[
        {
            "category":"Health Services",
            "subcategory":"Doctor",
            "type":"Services"
        }
    ],
    "sg:phone":"+1 559 896 0323",
    "sg:postcode":"93662",
    "sg:province":"CA",
    "sg:tags":[
        "dentist"
    ],
    "wof:name":"Engstrom & Engstrom",
    "wof:placetype":"venue"
},
  "geometry": {"coordinates":[-119.59531699999999,36.568904],"type":"Point"}
}