{
  "type": "Feature",
  "properties": {
    "addr:full":"844 Colorado Blvd Los Angeles CA 90041",
    "addr:housenumber":"844",
    "addr:postcode":"90041",
    "addr:street":"Colorado Blvd",
    "iso:country":"US",
    "sg:address":"844 Colorado Blvd",
    "sg:city":"Los Angeles",
    "sg:classifiers":[
        {
            "category":"Professional",
            "subcategory":"Computer Services",
            "type":"Services"
        }
    ],
    "sg:phone":"+1 323 256 1500",
    "sg:postcode":"90041",
    "sg:province":"CA",
    "sg:tags":[
        "repair"
    ],
    "wof:name":"Arcware Consulting",
    "wof:placetype":"venue"
},
  "geometry": {"coordinates":[-118.184077,34.140127],"type":"Point"}
}