{
  "type": "Feature",
  "properties": {
    "addr:full":"4076 Scholes Ave Riverside CA 92509",
    "addr:housenumber":"4076",
    "addr:postcode":"92509",
    "addr:street":"Scholes Ave",
    "iso:country":"US",
    "sg:address":"4076 Scholes Ave",
    "sg:city":"Riverside",
    "sg:classifiers":[
        {
            "category":"Building & Trades",
            "subcategory":"Construction",
            "type":"Services"
        }
    ],
    "sg:phone":"+1 951 681 7611",
    "sg:postcode":"92509",
    "sg:province":"CA",
    "sg:tags":[
        "fence",
        "contractor"
    ],
    "wof:name":"Lopez Welding & Fencing",
    "wof:placetype":"venue"
},
  "geometry": {"coordinates":[-117.464207,34.01357],"type":"Point"}
}