{
  "type": "Feature",
  "properties": {
    "iso:country":"US",
    "sg:address":"609 E Olive Ave",
    "sg:city":"Fresno",
    "sg:classifiers":[
        {
            "category":"Restaurant",
            "type":"Food & Drink"
        }
    ],
    "sg:phone":"+1 559 442 3246",
    "sg:postcode":"93728",
    "sg:province":"CA",
    "sg:website":"www.echomenu.com",
    "wof:name":"Echo Restaurant",
    "wof:placetype":"venue"
},
  "geometry": {"coordinates":[-119.804389,36.757721],"type":"Point"}
}