{
  "type": "Feature",
  "properties": {
    "addr:full":"3201 W Temple Ave Pomona CA 91768",
    "addr:housenumber":"3201",
    "addr:postcode":"91768",
    "addr:street":"W Temple Ave",
    "iso:country":"US",
    "sg:address":"3201 W Temple Ave",
    "sg:city":"Pomona",
    "sg:classifiers":[
        {
            "category":"Professional",
            "subcategory":"Computer Services",
            "type":"Services"
        }
    ],
    "sg:phone":"+1 909 595 8282",
    "sg:postcode":"91768",
    "sg:province":"CA",
    "sg:tags":[
        "internet"
    ],
    "wof:name":"First Choice Leads",
    "wof:placetype":"venue"
},
  "geometry": {"coordinates":[-117.806028,34.046738],"type":"Point"}
}