{
  "type": "Feature",
  "properties": {
    "iso:country":"US",
    "sg:address":"3636 E Coast Hwy",
    "sg:city":"Corona Del Mar",
    "sg:classifiers":[
        {
            "category":"Shopping",
            "subcategory":"Clothing, Apparel, & Fashions",
            "type":"Retail Goods"
        }
    ],
    "sg:phone":"+1 949 673 9466",
    "sg:postcode":"92625",
    "sg:province":"CA",
    "sg:tags":[
        "clothing",
        "women's"
    ],
    "wof:name":"Holly Sharp Signature Boutique",
    "wof:placetype":"venue"
},
  "geometry": {"coordinates":[-117.868337,33.594502],"type":"Point"}
}