{
  "type": "Feature",
  "properties": {
    "addr:full":"330 Shoreline Hwy Mill Valley CA 94941",
    "addr:housenumber":"330",
    "addr:postcode":"94941",
    "addr:street":"Shoreline Hwy",
    "iso:country":"US",
    "sg:address":"330 Shoreline Hwy",
    "sg:city":"Mill Valley",
    "sg:classifiers":[
        {
            "category":"Shopping",
            "subcategory":"Musical Instruments",
            "type":"Retail Goods"
        }
    ],
    "sg:phone":"+1 415 250 1649",
    "sg:postcode":"94941",
    "sg:province":"CA",
    "sg:tags":[
        "music",
        "dealer"
    ],
    "wof:name":"Music Medicine",
    "wof:placetype":"venue"
},
  "geometry": {"coordinates":[-122.528069,37.879788],"type":"Point"}
}