{
  "type": "Feature",
  "properties": {
    "addr:full":"3625 E Thousand Oaks Blvd Westlake Village CA 91362",
    "addr:housenumber":"3625",
    "addr:postcode":"91362",
    "addr:street":"E Thousand Oaks Blvd",
    "iso:country":"US",
    "sg:address":"3625 E Thousand Oaks Blvd",
    "sg:city":"Westlake Village",
    "sg:classifiers":[
        {
            "category":"Social Services",
            "type":"Services"
        }
    ],
    "sg:phone":"+1 805 497 2424",
    "sg:postcode":"91362",
    "sg:province":"CA",
    "sg:tags":[
        "counselor",
        "marriage",
        "family"
    ],
    "wof:name":"Family Phases Counseling",
    "wof:placetype":"venue"
},
  "geometry": {"coordinates":[-118.82936599999999,34.164424],"type":"Point"}
}