{
  "type": "Feature",
  "properties": {
    "addr:full":"1845 5th Ave. San Diego CA 92101",
    "addr:housenumber":"1845",
    "addr:postcode":"92101",
    "addr:street":"5Th Ave.",
    "iso:country":"US",
    "sg:address":"1845 5th Ave.",
    "sg:city":"San Diego",
    "sg:classifiers":[
        {
            "category":"Personal",
            "type":"Services"
        }
    ],
    "sg:phone":"+1 619 238 5169",
    "sg:postcode":"92101",
    "sg:province":"CA",
    "sg:tags":[
        "sewing",
        "alteration"
    ],
    "sg:website":"www.arjsalterations.com",
    "wof:name":"AR-J'S Alterations",
    "wof:placetype":"venue"
},
  "geometry": {"coordinates":[-117.16023800000001,32.724819],"type":"Point"}
}