{
  "type": "Feature",
  "properties": {
    "addr:full":"2461 Santa Monica Blvd Santa Monica CA 90404",
    "addr:housenumber":"2461",
    "addr:postcode":"90404",
    "addr:street":"Santa Monica Blvd",
    "iso:country":"US",
    "sg:address":"2461 Santa Monica Blvd",
    "sg:city":"Santa Monica",
    "sg:classifiers":[
        {
            "category":"Coffee & Tea",
            "type":"Food & Drink"
        }
    ],
    "sg:menulink":"http://www.allmenus.com/ca/santa-monica/116593-starbucks-coffee/menu/",
    "sg:phone":"+1 310 829 6152",
    "sg:postcode":"90404",
    "sg:province":"CA",
    "sg:tags":[
        "american"
    ],
    "wof:name":"Starbucks Coffee",
    "wof:placetype":"venue"
},
  "geometry": {"coordinates":[-118.47525400000001,34.032545],"type":"Point"}
}