{
  "type": "Feature",
  "properties": {
    "addr:full":"1069 E Shaw Ave Fresno CA 93710",
    "addr:housenumber":"1069",
    "addr:postcode":"93710",
    "addr:street":"E Shaw Ave",
    "iso:country":"US",
    "sg:address":"1069 E Shaw Ave",
    "sg:city":"Fresno",
    "sg:classifiers":[
        {
            "category":"Restaurant",
            "type":"Food & Drink"
        }
    ],
    "sg:phone":"+1 559 221 7245",
    "sg:postcode":"93710",
    "sg:province":"CA",
    "sg:tags":[
        "eating"
    ],
    "wof:name":"Thai House",
    "wof:placetype":"venue"
},
  "geometry": {"coordinates":[-119.771466,36.808483],"type":"Point"}
}