{
  "type": "Feature",
  "properties": {
    "addr:full":"1740 Airline Hwy Hollister CA 95023",
    "addr:housenumber":"1740",
    "addr:postcode":"hollister ca 95023",
    "addr:street":"Airline Hwy",
    "iso:country":"US",
    "sg:address":"1740 Airline Hwy",
    "sg:city":"Hollister",
    "sg:classifiers":[
        {
            "category":"Cinema",
            "subcategory":"Movie Rental",
            "type":"Entertainment"
        }
    ],
    "sg:phone":"+1 831 636 0284",
    "sg:postcode":"95023",
    "sg:province":"CA",
    "sg:tags":[
        "leasing",
        "video",
        "disc",
        "tape"
    ],
    "sg:website":"www.blockbuster.com",
    "wof:name":"Blockbuster Video",
    "wof:placetype":"venue"
},
  "geometry": {"coordinates":[-121.389174,36.836723],"type":"Point"}
}