{
  "type": "Feature",
  "properties": {
    "addr:full":"6919 Paradise Valley Rd San Diego CA 92139",
    "addr:housenumber":"6919",
    "addr:postcode":"92139",
    "addr:street":"Paradise Valley Rd",
    "iso:country":"US",
    "sg:address":"6919 Paradise Valley Rd",
    "sg:city":"San Diego",
    "sg:classifiers":[
        {
            "category":"Health Services",
            "subcategory":"Doctor",
            "type":"Services"
        }
    ],
    "sg:phone":"+1 619 479 5700",
    "sg:postcode":"92139",
    "sg:province":"CA",
    "sg:tags":[
        "dentist"
    ],
    "wof:name":"Dorman R Malone Jr DDS",
    "wof:placetype":"venue"
},
  "geometry": {"coordinates":[-117.045428,32.689202],"type":"Point"}
}