{
  "type": "Feature",
  "properties": {
    "addr:full":"1 Ferry Bldg San Francisco CA 94111",
    "addr:housenumber":"1;bldg",
    "addr:postcode":"94111",
    "addr:street":"Ferry",
    "iso:country":"US",
    "sg:address":"1 Ferry Bldg",
    "sg:city":"San Francisco",
    "sg:classifiers":[
        {
            "category":"Bakery",
            "type":"Food & Drink"
        }
    ],
    "sg:phone":"+1 707 763 0161",
    "sg:postcode":"94111",
    "sg:province":"CA",
    "sg:website":"www.dellafattoria.com",
    "wof:name":"Della Fattoria",
    "wof:placetype":"venue"
},
  "geometry": {"coordinates":[-122.39434900000001,37.796754],"type":"Point"}
}