{
  "type": "Feature",
  "properties": {
    "addr:full":"560 Mission Street San Francisco CA 94105",
    "addr:housenumber":"560",
    "addr:postcode":"94105",
    "addr:street":"Mission Street",
    "iso:country":"US",
    "sg:address":"560 Mission Street",
    "sg:city":"San Francisco",
    "sg:classifiers":[
        {
            "category":"Professional",
            "subcategory":"Lawyer & Legal Services",
            "type":"Services"
        }
    ],
    "sg:phone":"+1 415 397 2823",
    "sg:postcode":"94105",
    "sg:province":"CA",
    "wof:name":"McNaught Andrew M",
    "wof:placetype":"venue"
},
  "geometry": {"coordinates":[-122.398404,37.789114],"type":"Point"}
}