{
  "type": "Feature",
  "properties": {
    "iso:country":"US",
    "sg:address":"2037 Whitley Ave",
    "sg:city":"Los Angeles",
    "sg:classifiers":[
        {
            "category":"Wholesale",
            "subcategory":"Drugs",
            "type":"Manufacturing & Wholesale Goods"
        }
    ],
    "sg:phone":"+1 323 850 3404",
    "sg:postcode":"90068",
    "sg:province":"CA",
    "sg:tags":[
        "cosmetic"
    ],
    "wof:name":"Maximum Cosmetics Inc",
    "wof:placetype":"venue"
},
  "geometry": {"coordinates":[-118.332756,34.107977],"type":"Point"}
}