{
  "type": "Feature",
  "properties": {
    "addr:full":"24262 Hawthorne Blvd Torrance CA 90505",
    "addr:housenumber":"24262",
    "addr:postcode":"90505",
    "addr:street":"Hawthorne Blvd",
    "iso:country":"US",
    "sg:address":"24262 Hawthorne Blvd",
    "sg:city":"Torrance",
    "sg:classifiers":[
        {
            "category":"Personal",
            "subcategory":"Beauty Salon",
            "type":"Services"
        }
    ],
    "sg:phone":"+1 310 483 3886",
    "sg:postcode":"90505",
    "sg:province":"CA",
    "sg:tags":[
        "hair"
    ],
    "wof:name":"Gina Zamudio @ Encore",
    "wof:placetype":"venue"
},
  "geometry": {"coordinates":[-118.35072599999999,33.802034],"type":"Point"}
}