{
  "type": "Feature",
  "properties": {
    "iso:country":"US",
    "sg:address":"7252 Stockton Blvd",
    "sg:city":"Sacramento",
    "sg:classifiers":[
        {
            "category":"Retail",
            "subcategory":"Auto Repair",
            "type":"Services"
        }
    ],
    "sg:phone":"+1 916 428 5744",
    "sg:postcode":"95823",
    "sg:province":"CA",
    "sg:tags":[
        "automobile",
        "restoration-antique",
        "brake",
        "classic"
    ],
    "wof:name":"A & L Automotive",
    "wof:placetype":"venue"
},
  "geometry": {"coordinates":[-121.42819900000001,38.494148],"type":"Point"}
}