{
  "type": "Feature",
  "properties": {
    "addr:full":"77780 Country Club Dr Palm Desert CA 92211",
    "addr:housenumber":"77780",
    "addr:postcode":"ca 92211",
    "addr:street":"Country Club Dr",
    "iso:country":"US",
    "sg:address":"77780 Country Club Dr",
    "sg:city":"Palm Desert",
    "sg:classifiers":[
        {
            "category":"Retail",
            "subcategory":"Laundry & Dry Cleaning",
            "type":"Services"
        }
    ],
    "sg:phone":"+1 760 772 0009",
    "sg:postcode":"92211",
    "sg:province":"CA",
    "sg:tags":[
        "cleaners",
        "rug",
        "carpet"
    ],
    "wof:name":"Magsams Rug Pro",
    "wof:placetype":"venue"
},
  "geometry": {"coordinates":[-116.308235,33.758316],"type":"Point"}
}