{
  "type": "Feature",
  "properties": {
    "iso:country":"US",
    "sg:address":"550 E Carson St",
    "sg:city":"Carson",
    "sg:classifiers":[
        {
            "category":"Real Estate",
            "subcategory":"Real Estate Agent",
            "type":"Services"
        }
    ],
    "sg:phone":"+1 310 522 5077",
    "sg:postcode":"90745",
    "sg:province":"CA",
    "wof:name":"Frank Jones Realty",
    "wof:placetype":"venue"
},
  "geometry": {"coordinates":[-118.266873,33.831509],"type":"Point"}
}