{
  "type": "Feature",
  "properties": {
    "iso:country":"US",
    "sg:address":"1320 Gertrude St",
    "sg:city":"San Diego",
    "sg:classifiers":[
        {
            "category":"Wholesale",
            "subcategory":"Electrical",
            "type":"Manufacturing & Wholesale Goods"
        }
    ],
    "sg:phone":"+1 619 275 0070",
    "sg:postcode":"92110",
    "sg:province":"CA",
    "sg:tags":[
        "recording",
        "studio"
    ],
    "wof:name":"Grand Apartments Recording",
    "wof:placetype":"venue"
},
  "geometry": {"coordinates":[-117.201797,32.772857],"type":"Point"}
}