{
  "type": "Feature",
  "properties": {
    "iso:country":"US",
    "sg:address":"26550 Heritage View Ln",
    "sg:city":"Valencia",
    "sg:classifiers":[
        {
            "category":"Shopping",
            "subcategory":"Bicycles & Sporting Goods",
            "type":"Retail Goods"
        },
        {
            "category":"Organizations",
            "subcategory":"Membership Organization",
            "type":"Services"
        },
        {
            "category":"Organizations",
            "subcategory":"Community Association",
            "type":"Services"
        },
        {
            "category":"Sports & Exercise",
            "subcategory":"Golf",
            "type":"Entertainment"
        }
    ],
    "sg:phone":"+1 661 799 0454",
    "sg:postcode":"91381",
    "sg:province":"CA",
    "sg:tags":[
        "course",
        "club",
        "supply",
        "private",
        "equipment",
        "courses-private"
    ],
    "wof:name":"Tournament Players Club",
    "wof:placetype":"venue"
},
  "geometry": {"coordinates":[-118.584987,34.403274],"type":"Point"}
}