{
  "type": "Feature",
  "properties": {
    "iso:country":"US",
    "sg:address":"610 Broadway St",
    "sg:city":"El Centro",
    "sg:classifiers":[
        {
            "category":"Home & Garden",
            "subcategory":"Furniture",
            "type":"Retail Goods"
        }
    ],
    "sg:phone":"+1 760 353 5454",
    "sg:postcode":"92243",
    "sg:province":"CA",
    "sg:tags":[
        "mattress"
    ],
    "wof:name":"El Centro Furniture",
    "wof:placetype":"venue"
},
  "geometry": {"coordinates":[-115.55893500000001,32.793949],"type":"Point"}
}