{
  "type": "Feature",
  "properties": {
    "iso:country":"US",
    "sg:address":"5230 Las Virgenes Rd",
    "sg:city":"Calabasas",
    "sg:classifiers":[
        {
            "category":"Real Estate",
            "subcategory":"Real Estate Services",
            "type":"Services"
        }
    ],
    "sg:phone":"+1 818 871 0972",
    "sg:postcode":"91302",
    "sg:province":"CA",
    "sg:tags":[
        "management",
        "property"
    ],
    "wof:name":"Colorado Capital Dba Realty Bancorp",
    "wof:placetype":"venue"
},
  "geometry": {"coordinates":[-118.69712800000001,34.15125],"type":"Point"}
}