{
  "type": "Feature",
  "properties": {
    "addr:full":"404 N Berry St Brea CA 92821",
    "addr:housenumber":"404",
    "addr:postcode":"92821",
    "addr:street":"N Berry St",
    "iso:country":"US",
    "sg:address":"404 N Berry St",
    "sg:city":"Brea",
    "sg:classifiers":[
        {
            "category":"Professional",
            "subcategory":"Research",
            "type":"Services"
        },
        {
            "category":"Building & Trades",
            "subcategory":"Construction",
            "type":"Services"
        }
    ],
    "sg:phone":"+1 714 672 3500",
    "sg:postcode":"92821",
    "sg:province":"CA",
    "sg:tags":[
        "control",
        "hazardous",
        "material",
        "contractor",
        "environmental",
        "ecological",
        "removal"
    ],
    "sg:website":"www.cstenvironmental.com",
    "wof:name":"CST Environmental Inc.",
    "wof:placetype":"venue"
},
  "geometry": {"coordinates":[-117.90675400000001,33.924905],"type":"Point"}
}