{
  "type": "Feature",
  "properties": {
    "iso:country":"US",
    "sg:address":"1791 Marlow Rd",
    "sg:city":"Santa Rosa",
    "sg:classifiers":[
        {
            "category":"Health Services",
            "subcategory":"Doctor",
            "type":"Services"
        }
    ],
    "sg:phone":"+1 707 576 1240",
    "sg:postcode":"95401",
    "sg:province":"CA",
    "sg:tags":[
        "dentist"
    ],
    "wof:name":"Eric Fraiser DDS",
    "wof:placetype":"venue"
},
  "geometry": {"coordinates":[-122.75138699999999,38.451609],"type":"Point"}
}