{
  "type": "Feature",
  "properties": {
    "addr:full":"2776 Madera Ave Oakland CA 94619",
    "addr:housenumber":"2776",
    "addr:postcode":"94619",
    "addr:street":"Madera Ave",
    "iso:country":"US",
    "sg:address":"2776 Madera Ave",
    "sg:city":"Oakland",
    "sg:classifiers":[
        {
            "category":"Professional",
            "subcategory":"Employment Agencies",
            "type":"Services"
        }
    ],
    "sg:phone":"+1 858 869 7707",
    "sg:postcode":"94619",
    "sg:province":"CA",
    "sg:tags":[
        "contractor"
    ],
    "wof:name":"Clp Molecular Biology",
    "wof:placetype":"venue"
},
  "geometry": {"coordinates":[-122.19492099999999,37.777057],"type":"Point"}
}