{
  "type": "Feature",
  "properties": {
    "addr:full":"2316 Wilbur Avenue San Diego CA 92109",
    "addr:housenumber":"2316",
    "addr:postcode":"92109",
    "addr:street":"Wilbur Avenue",
    "iso:country":"US",
    "sg:address":"2316 Wilbur Avenue",
    "sg:city":"San Diego",
    "sg:classifiers":[
        {
            "category":"Retail",
            "subcategory":"Pet Boarding",
            "type":"Services"
        }
    ],
    "sg:phone":"+1 858 483 7387",
    "sg:postcode":"92109",
    "sg:province":"CA",
    "sg:tags":[
        "boarding/pet",
        "sitting"
    ],
    "wof:name":"Animals R US",
    "wof:placetype":"venue"
},
  "geometry": {"coordinates":[-117.229806,32.81009],"type":"Point"}
}