{
  "type": "Feature",
  "properties": {
    "addr:full":"7897 Walerga Rd Antelope CA 95843",
    "addr:housenumber":"7897",
    "addr:postcode":"95843",
    "addr:street":"Walerga Rd",
    "iso:country":"US",
    "sg:address":"7897 Walerga Rd",
    "sg:city":"Antelope",
    "sg:classifiers":[
        {
            "category":"Personal",
            "subcategory":"Beauty Salon",
            "type":"Services"
        }
    ],
    "sg:phone":"+1 916 726 4926",
    "sg:postcode":"95843",
    "sg:province":"CA",
    "wof:name":"Primpters Of California",
    "wof:placetype":"venue"
},
  "geometry": {"coordinates":[-121.364529,38.712793],"type":"Point"}
}