{
  "type": "Feature",
  "properties": {
    "addr:full":"113 Maciel Ave Roseville CA 95678",
    "addr:housenumber":"113",
    "addr:postcode":"95678",
    "addr:street":"Maciel Ave",
    "iso:country":"US",
    "sg:address":"113 Maciel Ave",
    "sg:city":"Roseville",
    "sg:classifiers":[
        {
            "category":"Wholesale",
            "subcategory":"Electrical",
            "type":"Manufacturing & Wholesale Goods"
        }
    ],
    "sg:phone":"+1 916 783 3817",
    "sg:postcode":"95678",
    "sg:province":"CA",
    "sg:tags":[
        "electronic"
    ],
    "wof:name":"Assoc Mfg Svc",
    "wof:placetype":"venue"
},
  "geometry": {"coordinates":[-121.27836499999999,38.749744],"type":"Point"}
}