{
  "type": "Feature",
  "properties": {
    "iso:country":"US",
    "sg:address":"5822 Holser Canyon Rd",
    "sg:city":"Piru",
    "sg:classifiers":[
        {
            "category":"Travel",
            "subcategory":"Hotels & Motels",
            "type":"Entertainment"
        }
    ],
    "sg:phone":"+1 805 521 0622",
    "sg:postcode":"93040",
    "sg:province":"CA",
    "sg:tags":[
        "breakfast",
        "accommodation",
        "bed"
    ],
    "wof:name":"Bunk House Bed & Breakfast",
    "wof:placetype":"venue"
},
  "geometry": {"coordinates":[-118.74874199999999,34.440051],"type":"Point"}
}