{
  "type": "Feature",
  "properties": {
    "iso:country":"US",
    "sg:address":"1145 Tara Ct",
    "sg:city":"Rocklin",
    "sg:classifiers":[
        {
            "category":"Transit Center",
            "subcategory":"Freight",
            "type":"Transportation"
        }
    ],
    "sg:phone":"+1 916 645 6299",
    "sg:postcode":"95765",
    "sg:province":"CA",
    "sg:tags":[
        "air",
        "cargo",
        "express",
        "package"
    ],
    "wof:name":"Airwolf Express",
    "wof:placetype":"venue"
},
  "geometry": {"coordinates":[-121.30908100000001,38.819547],"type":"Point"}
}