{
  "type": "Feature",
  "properties": {
    "iso:country":"US",
    "sg:address":"1442 S Signal Dr",
    "sg:city":"Pomona",
    "sg:classifiers":[
        {
            "category":"Manufacturing",
            "subcategory":"Printing",
            "type":"Manufacturing & Wholesale Goods"
        }
    ],
    "sg:phone":"+1 909 623 4550",
    "sg:postcode":"91766",
    "sg:province":"CA",
    "sg:tags":[
        "lithographic",
        "commercial"
    ],
    "wof:name":"Precise Screen Printing",
    "wof:placetype":"venue"
},
  "geometry": {"coordinates":[-117.726889,34.047372],"type":"Point"}
}