{
  "type": "Feature",
  "properties": {
    "addr:full":"3156 W Center St Anderson CA 96007",
    "addr:housenumber":"3156",
    "addr:postcode":"96007",
    "addr:street":"W Center St",
    "iso:country":"US",
    "sg:address":"3156 W Center St",
    "sg:city":"Anderson",
    "sg:classifiers":[
        {
            "category":"Retail",
            "subcategory":"Animal Services",
            "type":"Services"
        }
    ],
    "sg:phone":"+1 530 365 0361",
    "sg:postcode":"96007",
    "sg:province":"CA",
    "wof:name":"Happy Hound",
    "wof:placetype":"venue"
},
  "geometry": {"coordinates":[-122.303284,40.451249],"type":"Point"}
}