{
  "type": "Feature",
  "properties": {
    "addr:full":"353 San Jon Rd Ventura CA 93001",
    "addr:housenumber":"353",
    "addr:postcode":"93001",
    "addr:street":"San Jon Rd",
    "iso:country":"US",
    "sg:address":"353 San Jon Rd",
    "sg:city":"Ventura",
    "sg:classifiers":[
        {
            "category":"Professional",
            "subcategory":"Lawyer & Legal Services",
            "type":"Services"
        }
    ],
    "sg:phone":"+1 805 653 7937",
    "sg:postcode":"93001",
    "sg:province":"CA",
    "sg:tags":[
        "information",
        "attorney",
        "law",
        "practice",
        "disability",
        "social",
        "security",
        "referral"
    ],
    "sg:website":"http://www.andrewtkoeniglaw.com",
    "wof:name":"Andrew T Koenig",
    "wof:placetype":"venue"
},
  "geometry": {"coordinates":[-119.281497,34.276007],"type":"Point"}
}