{
  "type": "Feature",
  "properties": {
    "addr:full":"7447 N Figueroa St Los Angeles CA 90041",
    "addr:housenumber":"7447",
    "addr:postcode":"90041",
    "addr:street":"N Figueroa St",
    "iso:country":"US",
    "sg:address":"7447 N Figueroa St",
    "sg:city":"Los Angeles",
    "sg:classifiers":[
        {
            "category":"Health Services",
            "subcategory":"Optometrist",
            "type":"Services"
        }
    ],
    "sg:phone":"+1 323 257 3937",
    "sg:postcode":"90041",
    "sg:province":"CA",
    "wof:name":"Tawansy MD Khaled A",
    "wof:placetype":"venue"
},
  "geometry": {"coordinates":[-118.18719900000001,34.140191],"type":"Point"}
}