{
  "type": "Feature",
  "properties": {
    "addr:full":"717 Valley Dr Hermosa Beach CA 90254",
    "addr:housenumber":"717",
    "addr:postcode":"90254",
    "addr:street":"Valley Dr",
    "iso:country":"US",
    "sg:address":"717 Valley Dr",
    "sg:city":"Hermosa Beach",
    "sg:classifiers":[
        {
            "category":"Manufacturing",
            "subcategory":"Printing",
            "type":"Manufacturing & Wholesale Goods"
        }
    ],
    "sg:phone":"+1 310 372 0194",
    "sg:postcode":"90254",
    "sg:province":"CA",
    "sg:tags":[
        "screen"
    ],
    "wof:name":"Jol Design Inc",
    "wof:placetype":"venue"
},
  "geometry": {"coordinates":[-118.39420699999999,33.858829],"type":"Point"}
}