{
  "type": "Feature",
  "properties": {
    "addr:full":"1071 W 151st St Compton CA 90220",
    "addr:housenumber":"1071",
    "addr:postcode":"90220",
    "addr:street":"W 151St St",
    "iso:country":"US",
    "sg:address":"1071 W 151st St",
    "sg:city":"Compton",
    "sg:classifiers":[
        {
            "category":"Building & Trades",
            "subcategory":"Construction",
            "type":"Services"
        }
    ],
    "sg:phone":"+1 310 547 9111",
    "sg:postcode":"90220",
    "sg:province":"CA",
    "sg:tags":[
        "fire",
        "restoration",
        "damage"
    ],
    "wof:name":"Lucas Brothers Construction",
    "wof:placetype":"venue"
},
  "geometry": {"coordinates":[-118.243641,33.895115],"type":"Point"}
}