{
  "type": "Feature",
  "properties": {
    "iso:country":"US",
    "sg:address":"4611 Hollister Ave",
    "sg:city":"Santa Barbara",
    "sg:classifiers":[
        {
            "category":"Building & Trades",
            "subcategory":"Landscaping Services",
            "type":"Services"
        }
    ],
    "sg:phone":"+1 805 683 4806",
    "sg:postcode":"93110",
    "sg:province":"CA",
    "sg:tags":[
        "tree"
    ],
    "wof:name":"Peterson Tree Care",
    "wof:placetype":"venue"
},
  "geometry": {"coordinates":[-119.781603,34.438092],"type":"Point"}
}