{
  "type": "Feature",
  "properties": {
    "addr:full":"408 8th St Oakland CA 94607",
    "addr:housenumber":"408",
    "addr:postcode":"94607",
    "addr:street":"8Th St",
    "iso:country":"US",
    "sg:address":"408 8th St",
    "sg:city":"Oakland",
    "sg:classifiers":[
        {
            "category":"Personal",
            "subcategory":"Beauty Salon",
            "type":"Services"
        }
    ],
    "sg:phone":"+1 510 763 5607",
    "sg:postcode":"94607",
    "sg:province":"CA",
    "sg:tags":[
        "hair"
    ],
    "wof:name":"Hair Garden",
    "wof:placetype":"venue"
},
  "geometry": {"coordinates":[-122.273003,37.799999],"type":"Point"}
}