{
  "type": "Feature",
  "properties": {
    "iso:country":"US",
    "sg:address":"9036 Thornton Rd",
    "sg:city":"Stockton",
    "sg:classifiers":[
        {
            "category":"Autos & Motor Vehicles",
            "subcategory":"Automobile Sales",
            "type":"Retail Goods"
        }
    ],
    "sg:phone":"+1 775 265 7138",
    "sg:postcode":"95209",
    "sg:province":"CA",
    "sg:tags":[
        "dealers-used",
        "car",
        "used",
        "cars-wholesale"
    ],
    "wof:name":"Advantage Auto Sales",
    "wof:placetype":"venue"
},
  "geometry": {"coordinates":[-121.33598499999999,38.032438],"type":"Point"}
}