{
  "type": "Feature",
  "properties": {
    "iso:country":"US",
    "sg:address":"2286 Cameo Rd",
    "sg:city":"Carlsbad",
    "sg:classifiers":[
        {
            "category":"Shopping",
            "subcategory":"Used Merchandise",
            "type":"Retail Goods"
        }
    ],
    "sg:phone":"+1 760 729 3032",
    "sg:postcode":"92008",
    "sg:province":"CA",
    "sg:tags":[
        "antique"
    ],
    "wof:name":"Backroads Antiques",
    "wof:placetype":"venue"
},
  "geometry": {"coordinates":[-117.322246,33.161995],"type":"Point"}
}