{
  "type": "Feature",
  "properties": {
    "addr:full":"2286 Cameo Rd Carlsbad CA 92008",
    "addr:housenumber":"2286",
    "addr:postcode":"92008",
    "addr:street":"Cameo Rd",
    "iso:country":"US",
    "sg:address":"2286 Cameo Rd",
    "sg:city":"Carlsbad",
    "sg:classifiers":[
        {
            "category":"Shopping",
            "subcategory":"Used Merchandise",
            "type":"Retail Goods"
        }
    ],
    "sg:phone":"+1 760 729 3032",
    "sg:postcode":"92008",
    "sg:province":"CA",
    "sg:tags":[
        "antique"
    ],
    "wof:name":"Backroads Antiques",
    "wof:placetype":"venue"
},
  "geometry": {"coordinates":[-117.32224600000001,33.161995],"type":"Point"}
}