{
  "type": "Feature",
  "properties": {
    "addr:full":"3000 Q St Sacramento CA 95816",
    "addr:housenumber":"3000",
    "addr:postcode":"95816",
    "addr:street":"Q St",
    "iso:country":"US",
    "sg:address":"3000 Q St",
    "sg:city":"Sacramento",
    "sg:classifiers":[
        {
            "category":"Health Services",
            "subcategory":"Doctor",
            "type":"Services"
        }
    ],
    "sg:phone":"+1 916 733 3400",
    "sg:postcode":"95816",
    "sg:province":"CA",
    "sg:tags":[
        "medicine",
        "internal"
    ],
    "sg:website":"www.mymercymedgroup.org",
    "wof:name":"Dr. Shefali Shah",
    "wof:placetype":"venue"
},
  "geometry": {"coordinates":[-121.46964199999999,38.564982],"type":"Point"}
}