{
  "type": "Feature",
  "properties": {
    "iso:country":"US",
    "sg:address":"437 Los Cerritos Mall Space F8E",
    "sg:city":"Cerritos",
    "sg:classifiers":[
        {
            "category":"Food & Beverages",
            "subcategory":"Candy",
            "type":"Retail Goods"
        }
    ],
    "sg:phone":"+1 562 809 2500",
    "sg:postcode":"90703",
    "sg:province":"CA",
    "sg:tags":[
        "dessert"
    ],
    "sg:website":"www.nestlecafe.com",
    "wof:name":"Nestle Toll House Cafe",
    "wof:placetype":"venue"
},
  "geometry": {"coordinates":[-118.09458,33.864245],"type":"Point"}
}