{
  "type": "Feature",
  "properties": {
    "addr:full":"1045 Redwood St Vallejo CA 94590",
    "addr:housenumber":"1045",
    "addr:postcode":"94590",
    "addr:street":"Redwood St",
    "iso:country":"US",
    "sg:address":"1045 Redwood St",
    "sg:city":"Vallejo",
    "sg:classifiers":[
        {
            "category":"Health Services",
            "subcategory":"Chiropractor",
            "type":"Services"
        }
    ],
    "sg:phone":"+1 707 642 2676",
    "sg:postcode":"94590",
    "sg:province":"CA",
    "wof:name":"Amso Healthy Chiropractic",
    "wof:placetype":"venue"
},
  "geometry": {"coordinates":[-122.251407,38.122234],"type":"Point"}
}