{
  "type": "Feature",
  "properties": {
    "addr:full":"27953 Harwood Dr Santa Clarita CA 91350",
    "addr:housenumber":"27953",
    "addr:postcode":"91350",
    "addr:street":"Harwood Dr",
    "iso:country":"US",
    "sg:address":"27953 Harwood Dr",
    "sg:city":"Santa Clarita",
    "sg:classifiers":[
        {
            "category":"Organizations",
            "subcategory":"Religious Organization",
            "type":"Services"
        }
    ],
    "sg:phone":"+1 661 513 9220",
    "sg:postcode":"91350",
    "sg:province":"CA",
    "sg:tags":[
        "church"
    ],
    "wof:name":"Arumdawoon Korean Presbyterian",
    "wof:placetype":"venue"
},
  "geometry": {"coordinates":[-118.52977,34.457916],"type":"Point"}
}