{
  "type": "Feature",
  "properties": {
    "iso:country":"US",
    "sg:address":"510 S Glendora Ave",
    "sg:city":"West Covina",
    "sg:classifiers":[
        {
            "category":"Restaurant",
            "type":"Food & Drink"
        }
    ],
    "sg:phone":"+1 626 337 1994",
    "sg:postcode":"91790",
    "sg:province":"CA",
    "wof:name":"Kosta's Family Restaurant",
    "wof:placetype":"venue"
},
  "geometry": {"coordinates":[-117.926681,34.066204],"type":"Point"}
}