{
  "type": "Feature",
  "properties": {
    "iso:country":"US",
    "sg:address":"1233 W Ave P",
    "sg:city":"Palmdale",
    "sg:classifiers":[
        {
            "category":"Shopping",
            "subcategory":"Computers & Home Electronics",
            "type":"Retail Goods"
        }
    ],
    "sg:phone":"+1 661 267 2060",
    "sg:postcode":"93551",
    "sg:province":"CA",
    "sg:tags":[
        "game",
        "video"
    ],
    "sg:website":"www.gamestop.com",
    "wof:name":"Game Stop Corp",
    "wof:placetype":"venue"
},
  "geometry": {"coordinates":[-118.15138,34.601777],"type":"Point"}
}