{
  "type": "Feature",
  "properties": {
    "addr:full":"7407 Santa Fe Avenue Huntington Park CA 90255",
    "addr:housenumber":"7407",
    "addr:postcode":"90255",
    "addr:street":"Santa Fe Avenue;Park",
    "iso:country":"US",
    "sg:address":"7407 Santa Fe Avenue",
    "sg:city":"Huntington Park",
    "sg:classifiers":[
        {
            "category":"Autos & Motor Vehicles",
            "subcategory":"Auto Supplies",
            "type":"Retail Goods"
        }
    ],
    "sg:phone":"+1 323 583 8800",
    "sg:postcode":"90255",
    "sg:province":"CA",
    "sg:tags":[
        "tire"
    ],
    "wof:name":"C & A Tire & Wheels",
    "wof:placetype":"venue"
},
  "geometry": {"coordinates":[-118.230147,33.972893],"type":"Point"}
}