{
  "type": "Feature",
  "properties": {
    "addr:full":"404 W Polk St Coalinga CA 93210",
    "addr:housenumber":"404",
    "addr:postcode":"93210",
    "addr:street":"W Polk St",
    "iso:country":"US",
    "sg:address":"404 W Polk St",
    "sg:city":"Coalinga",
    "sg:classifiers":[
        {
            "category":"Place Of Worship",
            "subcategory":"Church",
            "type":"Public Place"
        },
        {
            "category":"Place Of Worship",
            "type":"Public Place"
        }
    ],
    "sg:phone":"+1 559 934 1905",
    "sg:postcode":"93210",
    "sg:province":"CA",
    "sg:tags":[
        "christ",
        "latter-day",
        "jesus",
        "churches-church",
        "saint"
    ],
    "wof:name":"Colinga 2nd Spanish Branch",
    "wof:placetype":"venue"
},
  "geometry": {"coordinates":[-120.36869,36.136509],"type":"Point"}
}