{
  "type": "Feature",
  "properties": {
    "iso:country":"US",
    "sg:address":"47 Krotona St",
    "sg:city":"Ojai",
    "sg:classifiers":[
        {
            "category":"Shopping",
            "subcategory":"Used Merchandise",
            "type":"Retail Goods"
        }
    ],
    "sg:phone":"+1 805 646 0873",
    "sg:postcode":"93023",
    "sg:province":"CA",
    "sg:tags":[
        "book",
        "rare",
        "dealer"
    ],
    "wof:name":"Krotona Quest Bookshop",
    "wof:placetype":"venue"
},
  "geometry": {"coordinates":[-119.273313,34.436537],"type":"Point"}
}