{
  "type": "Feature",
  "properties": {
    "iso:country":"US",
    "sg:address":"1540 Montague Expy",
    "sg:city":"San Jose",
    "sg:classifiers":[
        {
            "category":"Building & Trades",
            "subcategory":"Locksmith",
            "type":"Services"
        }
    ],
    "sg:phone":"+1 408 876 6249",
    "sg:postcode":"95131",
    "sg:province":"CA",
    "sg:tags":[
        "key"
    ],
    "wof:name":"24 Hour Montague Expy Available Locksm",
    "wof:placetype":"venue"
},
  "geometry": {"coordinates":[-121.901532,37.404001],"type":"Point"}
}