{
  "type": "Feature",
  "properties": {
    "addr:full":"468 N Camden Drive Beverly Hills CA 90210",
    "addr:housenumber":"468",
    "addr:postcode":"90210",
    "addr:street":"N Camden Drive",
    "iso:country":"US",
    "sg:address":"468 N Camden Drive",
    "sg:city":"Beverly Hills",
    "sg:classifiers":[
        {
            "category":"Real Estate",
            "subcategory":"Real Estate Services",
            "type":"Services"
        }
    ],
    "sg:phone":"+1 310 860 7633",
    "sg:postcode":"90210",
    "sg:province":"CA",
    "wof:name":"Lyndel Funding",
    "wof:placetype":"venue"
},
  "geometry": {"coordinates":[-118.405181,34.06992],"type":"Point"}
}