{
  "type": "Feature",
  "properties": {
    "addr:full":"16690 E 14th St San Leandro CA 94578",
    "addr:housenumber":"16690",
    "addr:postcode":"94578",
    "addr:street":"E 14Th St",
    "iso:country":"US",
    "sg:address":"16690 E 14th St",
    "sg:city":"San Leandro",
    "sg:classifiers":[
        {
            "category":"Autos & Motor Vehicles",
            "subcategory":"Fuel & Gas Station",
            "type":"Retail Goods"
        }
    ],
    "sg:phone":"+1 510 276 1325",
    "sg:postcode":"94578",
    "sg:province":"CA",
    "wof:name":"Shawn Enterprise Inc",
    "wof:placetype":"venue"
},
  "geometry": {"coordinates":[-122.109911,37.692421],"type":"Point"}
}