{
  "type": "Feature",
  "properties": {
    "addr:full":"258 E Redlands Blvd San Bernardino CA 92408",
    "addr:housenumber":"258",
    "addr:postcode":"92408",
    "addr:street":"E Redlands Blvd",
    "iso:country":"US",
    "sg:address":"258 E Redlands Blvd",
    "sg:city":"San Bernardino",
    "sg:classifiers":[
        {
            "category":"Restaurant",
            "type":"Food & Drink"
        }
    ],
    "sg:phone":"+1 909 825 7220",
    "sg:postcode":"92408",
    "sg:province":"CA",
    "wof:name":"Taco Bell",
    "wof:placetype":"venue"
},
  "geometry": {"coordinates":[-117.28079,34.063142],"type":"Point"}
}