{
  "type": "Feature",
  "properties": {
    "addr:full":"9930 Haas Ave Los Angeles CA 90047",
    "addr:housenumber":"9930",
    "addr:postcode":"90047",
    "addr:street":"Haas Ave",
    "iso:country":"US",
    "sg:address":"9930 Haas Ave",
    "sg:city":"Los Angeles",
    "sg:classifiers":[
        {
            "category":"Freight",
            "type":"Transportation"
        }
    ],
    "sg:phone":"+1 323 757 3382",
    "sg:postcode":"90047",
    "sg:province":"CA",
    "wof:name":"Quality Transportation",
    "wof:placetype":"venue"
},
  "geometry": {"coordinates":[-118.31595799999999,33.945864],"type":"Point"}
}