{
  "type": "Feature",
  "properties": {
    "addr:full":"16545 Arminta St Van Nuys CA 91406",
    "addr:housenumber":"16545",
    "addr:postcode":"91406",
    "addr:street":"Arminta St",
    "iso:country":"US",
    "sg:address":"16545 Arminta St",
    "sg:city":"Van Nuys",
    "sg:classifiers":[
        {
            "category":"Wholesale",
            "subcategory":"Medical Equipment & Supplies",
            "type":"Manufacturing & Wholesale Goods"
        }
    ],
    "sg:phone":"+1 818 901 7728",
    "sg:postcode":"91406",
    "sg:province":"CA",
    "sg:tags":[
        "physician",
        "surgeon"
    ],
    "wof:name":"Option One Home Medical Eqpt",
    "wof:placetype":"venue"
},
  "geometry": {"coordinates":[-118.49328,34.21493],"type":"Point"}
}