{
  "type": "Feature",
  "properties": {
    "addr:full":"12625 High Bluff Dr San Diego CA 92130",
    "addr:housenumber":"12625",
    "addr:postcode":"92130",
    "addr:street":"High Bluff Dr",
    "iso:country":"US",
    "sg:address":"12625 High Bluff Dr",
    "sg:city":"San Diego",
    "sg:classifiers":[
        {
            "category":"Health Services",
            "subcategory":"Health Practitioner",
            "type":"Services"
        }
    ],
    "sg:phone":"+1 858 755 3006",
    "sg:postcode":"92130",
    "sg:province":"CA",
    "sg:tags":[
        "psychotherapist"
    ],
    "wof:name":"Morrison Marjorie Mft",
    "wof:placetype":"venue"
},
  "geometry": {"coordinates":[-117.240526,32.945787],"type":"Point"}
}