{
  "type": "Feature",
  "properties": {
    "iso:country":"US",
    "sg:address":"8227 Blacburn Ave",
    "sg:city":"Los Angeles",
    "sg:classifiers":[
        {
            "category":"Professional",
            "subcategory":"Management & Consulting",
            "type":"Services"
        }
    ],
    "sg:phone":"+1 310 926 2722",
    "sg:postcode":"90048",
    "sg:province":"CA",
    "sg:tags":[
        "life",
        "coach"
    ],
    "sg:website":"www.fengshuifromtheheart.com",
    "wof:name":"Feng Shui from the Heart",
    "wof:placetype":"venue"
},
  "geometry": {"coordinates":[-118.36870500000001,34.071844],"type":"Point"}
}