{
  "type": "Feature",
  "properties": {
    "addr:full":"16202 Orange Ave Paramount CA 90723",
    "addr:housenumber":"16202",
    "addr:postcode":"90723",
    "addr:street":"Orange Ave",
    "iso:country":"US",
    "sg:address":"16202 Orange Ave",
    "sg:city":"Paramount",
    "sg:classifiers":[
        {
            "category":"Manufacturing",
            "subcategory":"Metals",
            "type":"Manufacturing & Wholesale Goods"
        }
    ],
    "sg:phone":"+1 562 634 7664",
    "sg:postcode":"90723",
    "sg:province":"CA",
    "sg:tags":[
        "stamping"
    ],
    "wof:name":"Caran Precision Engrg & Mfg",
    "wof:placetype":"venue"
},
  "geometry": {"coordinates":[-118.17734,33.886427],"type":"Point"}
}