{
  "type": "Feature",
  "properties": {
    "addr:full":"1545 Faraday Ave Ste 101 Carlsbad CA 92008",
    "addr:housenumber":"1545",
    "addr:postcode":"92008",
    "addr:street":"Faraday Ave Ste 101",
    "iso:country":"US",
    "sg:address":"1545 Faraday Ave Ste 101",
    "sg:city":"Carlsbad",
    "sg:classifiers":[
        {
            "category":"Sports & Exercise",
            "subcategory":"Sports Center",
            "type":"Entertainment"
        }
    ],
    "sg:phone":"+1 760 602 6200",
    "sg:postcode":"92008",
    "sg:province":"CA",
    "sg:tags":[
        "athletic"
    ],
    "sg:website":"http://www.thefamilie.com",
    "wof:name":"Familie, The",
    "wof:placetype":"venue"
},
  "geometry": {"coordinates":[-117.299021,33.132801],"type":"Point"}
}