{
  "type": "Feature",
  "properties": {
    "iso:country":"US",
    "sg:address":"5077 E Lew Davis St",
    "sg:city":"Long Beach",
    "sg:classifiers":[
        {
            "category":"Building & Trades",
            "subcategory":"Pest Control",
            "type":"Services"
        }
    ],
    "sg:phone":"+1 562 938 9600",
    "sg:postcode":"90808",
    "sg:province":"CA",
    "wof:name":"Bugs Or Us",
    "wof:placetype":"venue"
},
  "geometry": {"coordinates":[-118.134232,33.830097],"type":"Point"}
}