{
  "type": "Feature",
  "properties": {
    "iso:country":"US",
    "sg:address":"895 W Valley Blvd",
    "sg:city":"Colton",
    "sg:classifiers":[
        {
            "category":"Health Services",
            "subcategory":"Health Practitioner",
            "type":"Services"
        }
    ],
    "sg:phone":"+1 909 825 5660",
    "sg:postcode":"92324",
    "sg:province":"CA",
    "sg:tags":[
        "therapist",
        "physical"
    ],
    "wof:name":"Rehab & Conditioning",
    "wof:placetype":"venue"
},
  "geometry": {"coordinates":[-117.338724,34.068804],"type":"Point"}
}