{
  "type": "Feature",
  "properties": {
    "iso:country":"US",
    "sg:address":"2870 Clark Ave",
    "sg:city":"Norco",
    "sg:classifiers":[
        {
            "category":"Recreation",
            "type":"Entertainment"
        }
    ],
    "sg:phone":"+1 951 270 5632",
    "sg:postcode":"92860",
    "sg:province":"CA",
    "sg:tags":[
        "parks"
    ],
    "sg:website":"www.ci.norco.ca.us",
    "wof:name":"Norco Parks & Recreation",
    "wof:placetype":"venue"
},
  "geometry": {"coordinates":[-117.560919,33.922411],"type":"Point"}
}