{
  "type": "Feature",
  "properties": {
    "addr:full":"999 California St San Francisco CA 94108",
    "addr:housenumber":"999",
    "addr:postcode":"94108",
    "addr:street":"California St",
    "iso:country":"US",
    "sg:address":"999 California St",
    "sg:city":"San Francisco",
    "sg:classifiers":[
        {
            "category":"Travel",
            "subcategory":"Hotels & Motels",
            "type":"Entertainment"
        }
    ],
    "sg:phone":"+1 415 392 3434",
    "sg:postcode":"94108",
    "sg:province":"CA",
    "wof:name":"San Francisco Accommodations",
    "wof:placetype":"venue"
},
  "geometry": {"coordinates":[-122.410798,37.791819],"type":"Point"}
}