{
  "type": "Feature",
  "properties": {
    "iso:country":"US",
    "sg:address":"5306 Roosevelt Ave",
    "sg:city":"Santa Ana",
    "sg:classifiers":[
        {
            "category":"Manufacturing",
            "subcategory":"Building Materials",
            "type":"Manufacturing & Wholesale Goods"
        }
    ],
    "sg:phone":"+1 714 785 1386",
    "sg:postcode":"92703",
    "sg:province":"CA",
    "sg:tags":[
        "mfg"
    ],
    "wof:name":"Tuans Woodworks",
    "wof:placetype":"venue"
},
  "geometry": {"coordinates":[-117.940816,33.750174],"type":"Point"}
}