{
  "type": "Feature",
  "properties": {
    "addr:full":"1744 W Bullard Ave Fresno CA 93711",
    "addr:housenumber":"1744",
    "addr:postcode":"93711",
    "addr:street":"W Bullard Ave",
    "iso:country":"US",
    "sg:address":"1744 W Bullard Ave",
    "sg:city":"Fresno",
    "sg:classifiers":[
        {
            "category":"Shopping",
            "type":"Retail Goods"
        }
    ],
    "sg:phone":"+1 559 432 8490",
    "sg:postcode":"93711",
    "sg:province":"CA",
    "sg:tags":[
        "cards",
        "sport",
        "baseball",
        "memorabilia"
    ],
    "wof:name":"Mossette's Baseball Cards",
    "wof:placetype":"venue"
},
  "geometry": {"coordinates":[-119.826302,36.822823],"type":"Point"}
}