{
  "type": "Feature",
  "properties": {
    "addr:full":"9362 River Oaks Ln Orangevale CA 95662",
    "addr:housenumber":"9362",
    "addr:postcode":"95662",
    "addr:street":"River Oaks Ln",
    "iso:country":"US",
    "sg:address":"9362 River Oaks Ln",
    "sg:city":"Orangevale",
    "sg:classifiers":[
        {
            "category":"Retail",
            "subcategory":"Repair Shop",
            "type":"Services"
        }
    ],
    "sg:phone":"+1 916 954 0275",
    "sg:postcode":"95662",
    "sg:province":"CA",
    "sg:tags":[
        "equipment",
        "arts",
        "photographic"
    ],
    "wof:name":"Beck & Beck Enterprises",
    "wof:placetype":"venue"
},
  "geometry": {"coordinates":[-121.204453,38.674936],"type":"Point"}
}