{
  "type": "Feature",
  "properties": {
    "iso:country":"US",
    "sg:address":"2101 Forest Ave Ste 123",
    "sg:city":"San Jose",
    "sg:classifiers":[
        {
            "category":"Personal",
            "subcategory":"Massage",
            "type":"Services"
        },
        {
            "category":"Health Services",
            "subcategory":"Chiropractor",
            "type":"Services"
        }
    ],
    "sg:phone":"+1 408 947 0385",
    "sg:postcode":"95128",
    "sg:province":"CA",
    "wof:name":"Dr. Peter S Block, DC",
    "wof:placetype":"venue"
},
  "geometry": {"coordinates":[-121.937162,37.327146],"type":"Point"}
}