{
  "type": "Feature",
  "properties": {
    "iso:country":"US",
    "sg:address":"3501 Adams St",
    "sg:city":"Riverside",
    "sg:classifiers":[
        {
            "category":"Insurance",
            "subcategory":"Insurance Agent",
            "type":"Services"
        }
    ],
    "sg:phone":"+1 951 343 2949",
    "sg:postcode":"92504",
    "sg:province":"CA",
    "wof:name":"Farmers Insurance Group",
    "wof:placetype":"venue"
},
  "geometry": {"coordinates":[-117.41994,33.927811],"type":"Point"}
}