{
  "type": "Feature",
  "properties": {
    "addr:full":"228 N Harbor Blvd Santa Ana CA 92703",
    "addr:housenumber":"228",
    "addr:postcode":"92703",
    "addr:street":"N Harbor Blvd",
    "iso:country":"US",
    "sg:address":"228 N Harbor Blvd",
    "sg:city":"Santa Ana",
    "sg:classifiers":[
        {
            "category":"Shopping",
            "subcategory":"Pharmacy",
            "type":"Retail Goods"
        }
    ],
    "sg:phone":"+1 714 554 7120",
    "sg:postcode":"92703",
    "sg:province":"CA",
    "sg:tags":[
        "drugstore"
    ],
    "wof:name":"CVS pharmacy",
    "wof:placetype":"venue"
},
  "geometry": {"coordinates":[-117.920331,33.746418],"type":"Point"}
}