{
  "type": "Feature",
  "properties": {
    "iso:country":"US",
    "sg:address":"3273 Martin Ave",
    "sg:city":"San Diego",
    "sg:classifiers":[
        {
            "category":"Building & Trades",
            "subcategory":"Cleaning & Sanitation",
            "type":"Services"
        }
    ],
    "sg:phone":"+1 619 269 7371",
    "sg:postcode":"92113",
    "sg:province":"CA",
    "sg:tags":[
        "janitor"
    ],
    "wof:name":"Perfection Cleaning Svc",
    "wof:placetype":"venue"
},
  "geometry": {"coordinates":[-117.121741,32.699375],"type":"Point"}
}