{
  "type": "Feature",
  "properties": {
    "iso:country":"US",
    "sg:address":"152 Redding Rd",
    "sg:city":"Campbell",
    "sg:classifiers":[
        {
            "category":"Communications",
            "type":"Services"
        }
    ],
    "sg:phone":"+1 408 369 1196",
    "sg:postcode":"95008",
    "sg:province":"CA",
    "sg:tags":[
        "communication"
    ],
    "wof:name":"Mrv Communication",
    "wof:placetype":"venue"
},
  "geometry": {"coordinates":[-121.945611,37.265055],"type":"Point"}
}