{
  "type": "Feature",
  "properties": {
    "addr:full":"15 Jaeger Ln Aliso Viejo CA 92656",
    "addr:housenumber":"15",
    "addr:postcode":"92656",
    "addr:street":"Jaeger Ln",
    "iso:country":"US",
    "sg:address":"15 Jaeger Ln",
    "sg:city":"Aliso Viejo",
    "sg:classifiers":[
        {
            "category":"Building & Trades",
            "subcategory":"Plumbing",
            "type":"Services"
        }
    ],
    "sg:phone":"+1 949 454 2052",
    "sg:postcode":"92656",
    "sg:province":"CA",
    "sg:tags":[
        "contractor"
    ],
    "wof:name":"Plotkowski Plumbing",
    "wof:placetype":"venue"
},
  "geometry": {"coordinates":[-117.743703,33.600703],"type":"Point"}
}