{
  "type": "Feature",
  "properties": {
    "iso:country":"US",
    "sg:address":"7931 Girard Ave",
    "sg:city":"La Jolla",
    "sg:classifiers":[
        {
            "category":"Shopping",
            "subcategory":"Shoes",
            "type":"Retail Goods"
        }
    ],
    "sg:phone":"+1 858 459 7232",
    "sg:postcode":"92037",
    "sg:province":"CA",
    "sg:tags":[
        "store"
    ],
    "wof:name":"Go of La Jolla",
    "wof:placetype":"venue"
},
  "geometry": {"coordinates":[-117.275002,32.847301],"type":"Point"}
}