{
  "type": "Feature",
  "properties": {
    "iso:country":"US",
    "sg:address":"2856 Los Feliz Pl",
    "sg:city":"Los Angeles",
    "sg:classifiers":[
        {
            "category":"Insurance",
            "subcategory":"Insurance Agent",
            "type":"Services"
        }
    ],
    "sg:phone":"+1 323 661 1655",
    "sg:postcode":"90039",
    "sg:province":"CA",
    "wof:name":"Race Insurance Svc",
    "wof:placetype":"venue"
},
  "geometry": {"coordinates":[-118.262356,34.126285],"type":"Point"}
}