{
  "type": "Feature",
  "properties": {
    "addr:full":"3111 Sunset Blvd Ste L Rocklin CA 95677",
    "addr:housenumber":"3111",
    "addr:postcode":"95677",
    "addr:street":"Sunset Blvd Ste L",
    "iso:country":"US",
    "sg:address":"3111 Sunset Blvd Ste L",
    "sg:city":"Rocklin",
    "sg:classifiers":[
        {
            "category":"Professional",
            "subcategory":"Engineering",
            "type":"Services"
        },
        {
            "category":"Real Estate",
            "subcategory":"Surveying",
            "type":"Services"
        }
    ],
    "sg:phone":"+1 916 624 1221",
    "sg:postcode":"95677",
    "sg:province":"CA",
    "sg:tags":[
        "civil",
        "surveyor",
        "consulting",
        "land",
        "engineer"
    ],
    "wof:name":"Ourada Engineering",
    "wof:placetype":"venue"
},
  "geometry": {"coordinates":[-121.251384,38.786502],"type":"Point"}
}