{
  "type": "Feature",
  "properties": {
    "addr:full":"475 S Santa Anita Ave Pasadena CA 91107",
    "addr:housenumber":"475",
    "addr:postcode":"91107",
    "addr:street":"S Santa Anita Ave",
    "iso:country":"US",
    "sg:address":"475 S Santa Anita Ave",
    "sg:city":"Pasadena",
    "sg:classifiers":[
        {
            "category":"Personal",
            "type":"Services"
        }
    ],
    "sg:phone":"+1 626 585 9000",
    "sg:postcode":"91107",
    "sg:province":"CA",
    "sg:tags":[
        "towing"
    ],
    "wof:name":"Farris & Sons Towing",
    "wof:placetype":"venue"
},
  "geometry": {"coordinates":[-118.098735,34.138198],"type":"Point"}
}