{
  "type": "Feature",
  "properties": {
    "addr:full":"1 Maritime Plaza 250 Clay St, Ste 1600 San Francisco CA 94111",
    "addr:housenumber":"1;250",
    "addr:postcode":"94111",
    "addr:street":"Maritime;Clay St Ste 1600",
    "iso:country":"US",
    "sg:address":"1 Maritime Plaza 250 Clay St, Ste 1600",
    "sg:city":"San Francisco",
    "sg:classifiers":[
        {
            "category":"Professional",
            "subcategory":"Lawyer & Legal Services",
            "type":"Services"
        }
    ],
    "sg:phone":"+1 415 956 5111",
    "sg:postcode":"94111",
    "sg:province":"CA",
    "sg:website":"www.zarehassociates.com",
    "wof:name":"Zareh & Associates",
    "wof:placetype":"venue"
},
  "geometry": {"coordinates":[-122.306572,37.799549],"type":"Point"}
}