{
  "type": "Feature",
  "properties": {
    "addr:full":"1150 E 4th St Long Beach CA 90802",
    "addr:housenumber":"1150",
    "addr:postcode":"90802",
    "addr:street":"E 4Th St",
    "iso:country":"US",
    "sg:address":"1150 E 4th St",
    "sg:city":"Long Beach",
    "sg:classifiers":[
        {
            "category":"Government",
            "subcategory":"Office",
            "type":"Public Place"
        },
        {
            "category":"Social Services",
            "type":"Services"
        }
    ],
    "sg:phone":"+1 562 570 3500",
    "sg:postcode":"90802",
    "sg:province":"CA",
    "sg:tags":[
        "executive",
        "village"
    ],
    "wof:name":"Long Beach Senior Citizens Lbr",
    "wof:placetype":"venue"
},
  "geometry": {"coordinates":[-118.17653900000001,33.771635],"type":"Point"}
}