{
  "type": "Feature",
  "properties": {
    "iso:country":"US",
    "sg:address":"2483 W Middlefield Rd",
    "sg:city":"Mountain View",
    "sg:classifiers":[
        {
            "category":"Insurance",
            "subcategory":"Insurance Agent",
            "type":"Services"
        }
    ],
    "sg:phone":"+1 650 934 0700",
    "sg:postcode":"94043",
    "sg:province":"CA",
    "wof:name":"State Farm Insurance",
    "wof:placetype":"venue"
},
  "geometry": {"coordinates":[-122.099123,37.412859],"type":"Point"}
}