{
  "type": "Feature",
  "properties": {
    "iso:country":"US",
    "sg:address":"17360 Colima Rd",
    "sg:city":"Rowland Heights",
    "sg:classifiers":[
        {
            "category":"Professional",
            "subcategory":"Accounting & Tax Preparation",
            "type":"Services"
        }
    ],
    "sg:phone":"+1 626 330 5410",
    "sg:postcode":"91748",
    "sg:province":"CA",
    "sg:tags":[
        "consultant"
    ],
    "wof:name":"Friedman & Assoc",
    "wof:placetype":"venue"
},
  "geometry": {"coordinates":[-117.92447,33.990385],"type":"Point"}
}