{
  "type": "Feature",
  "properties": {
    "addr:full":"1214 E Edna Pl Covina CA 91724",
    "addr:housenumber":"1214",
    "addr:postcode":"91724",
    "addr:street":"E Edna Pl",
    "iso:country":"US",
    "sg:address":"1214 E Edna Pl",
    "sg:city":"Covina",
    "sg:classifiers":[
        {
            "category":"Professional",
            "subcategory":"Business Services",
            "type":"Services"
        }
    ],
    "sg:phone":"+1 626 858 4810",
    "sg:postcode":"91724",
    "sg:province":"CA",
    "wof:name":"NTI Enterprises",
    "wof:placetype":"venue"
},
  "geometry": {"coordinates":[-117.865712,34.094392],"type":"Point"}
}