{
  "type": "Feature",
  "properties": {
    "addr:full":"1706 Glyndon Ave Venice CA 90291",
    "addr:housenumber":"1706",
    "addr:postcode":"90291",
    "addr:street":"Glyndon Ave",
    "iso:country":"US",
    "sg:address":"1706 Glyndon Ave",
    "sg:city":"Venice",
    "sg:classifiers":[
        {
            "category":"Building & Trades",
            "subcategory":"Plumbing",
            "type":"Services"
        }
    ],
    "sg:phone":"+1 310 396 5346",
    "sg:postcode":"90291",
    "sg:province":"CA",
    "sg:tags":[
        "contractor"
    ],
    "wof:name":"Stephen Larson",
    "wof:placetype":"venue"
},
  "geometry": {"coordinates":[-118.454548,34.002965],"type":"Point"}
}