{
  "type": "Feature",
  "properties": {
    "iso:country":"US",
    "sg:address":"1351 E Chapman Ave",
    "sg:city":"Fullerton",
    "sg:phone":"+1 714 680 3222",
    "sg:postcode":"92831",
    "sg:province":"CA",
    "wof:name":"Legal Document Assistance",
    "wof:placetype":"venue"
},
  "geometry": {"coordinates":[-117.903436,33.874121],"type":"Point"}
}