{
  "type": "Feature",
  "properties": {
    "iso:country":"US",
    "sg:address":"1816 W Cherry Ave",
    "sg:city":"Fullerton",
    "sg:classifiers":[
        {
            "category":"Building & Trades",
            "subcategory":"Cleaning & Sanitation",
            "type":"Services"
        }
    ],
    "sg:phone":"+1 714 870 6121",
    "sg:postcode":"92833",
    "sg:province":"CA",
    "sg:tags":[
        "carpet"
    ],
    "wof:name":"Morgan's Carpet & Furniture Cleaners",
    "wof:placetype":"venue"
},
  "geometry": {"coordinates":[-117.960999,33.862],"type":"Point"}
}