{
  "type": "Feature",
  "properties": {
    "iso:country":"US",
    "sg:address":"2933 Segovia Way",
    "sg:city":"Carlsbad",
    "sg:classifiers":[
        {
            "category":"Professional",
            "subcategory":"Business Services",
            "type":"Services"
        }
    ],
    "sg:phone":"+1 760 846 0936",
    "sg:postcode":"92009",
    "sg:province":"CA",
    "sg:tags":[
        "interior",
        "consultant",
        "design",
        "decorator"
    ],
    "wof:name":"At Home Decor",
    "wof:placetype":"venue"
},
  "geometry": {"coordinates":[-117.250225,33.080125],"type":"Point"}
}