{
  "type": "Feature",
  "properties": {
    "iso:country":"US",
    "sg:address":"812 Corral Ct",
    "sg:city":"Bonita",
    "sg:classifiers":[
        {
            "category":"Health Services",
            "subcategory":"Doctor",
            "type":"Services"
        }
    ],
    "sg:phone":"+1 619 479 9732",
    "sg:postcode":"91902",
    "sg:province":"CA",
    "sg:tags":[
        "medicine",
        "physician",
        "practice",
        "surgeons",
        "family"
    ],
    "wof:name":"Charles D Pickett",
    "wof:placetype":"venue"
},
  "geometry": {"coordinates":[-117.03513100000001,32.651946],"type":"Point"}
}