{
  "type": "Feature",
  "properties": {
    "addr:full":"444 Minor Ave San Jose CA 95126",
    "addr:housenumber":"444",
    "addr:postcode":"95126",
    "addr:street":"Minor Ave",
    "iso:country":"US",
    "sg:address":"444 Minor Ave",
    "sg:city":"San Jose",
    "sg:classifiers":[
        {
            "category":"Building & Trades",
            "subcategory":"Construction",
            "type":"Services"
        }
    ],
    "sg:phone":"+1 408 295 5638",
    "sg:postcode":"95126",
    "sg:province":"CA",
    "sg:tags":[
        "residential"
    ],
    "wof:name":"Rkg Construction",
    "wof:placetype":"venue"
},
  "geometry": {"coordinates":[-121.895017,37.325111],"type":"Point"}
}