{
  "type": "Feature",
  "properties": {
    "addr:full":"817 N N Pl Tulare CA 93274",
    "addr:housenumber":"817",
    "addr:postcode":"93274",
    "addr:street":"N N Pl",
    "iso:country":"US",
    "sg:address":"817 N N Pl",
    "sg:city":"Tulare",
    "sg:classifiers":[
        {
            "category":"Wholesale",
            "subcategory":"Drugs",
            "type":"Manufacturing & Wholesale Goods"
        }
    ],
    "sg:phone":"+1 559 688 7802",
    "sg:postcode":"93274",
    "sg:province":"CA",
    "wof:name":"Kathy Fien",
    "wof:placetype":"venue"
},
  "geometry": {"coordinates":[-119.34322299999999,36.219231],"type":"Point"}
}