{
  "type": "Feature",
  "properties": {
    "iso:country":"US",
    "sg:address":"2140 S El Camino Real",
    "sg:city":"San Mateo",
    "sg:classifiers":[
        {
            "category":"Personal",
            "subcategory":"Beauty Salon",
            "type":"Services"
        },
        {
            "category":"Personal",
            "subcategory":"Barber",
            "type":"Services"
        }
    ],
    "sg:phone":"+1 650 577 8100",
    "sg:postcode":"94403",
    "sg:province":"CA",
    "sg:tags":[
        "hair"
    ],
    "sg:website":"www.facebook.com/home.php#!/grou...",
    "wof:name":"Binh's Family Hair Care",
    "wof:placetype":"venue"
},
  "geometry": {"coordinates":[-122.307999,37.547001],"type":"Point"}
}