{
  "type": "Feature",
  "properties": {
    "addr:full":"322 W 3rd St Santa Ana CA 92701",
    "addr:housenumber":"322",
    "addr:postcode":"92701",
    "addr:street":"W 3Rd St",
    "iso:country":"US",
    "sg:address":"322 W 3rd St",
    "sg:city":"Santa Ana",
    "sg:classifiers":[
        {
            "category":"Professional",
            "subcategory":"Lawyer & Legal Services",
            "type":"Services"
        }
    ],
    "sg:phone":"+1 714 953 0400",
    "sg:postcode":"92701",
    "sg:province":"CA",
    "wof:name":"Wong Clement Law Offices of",
    "wof:placetype":"venue"
},
  "geometry": {"coordinates":[-117.871002,33.7472],"type":"Point"}
}