{
  "type": "Feature",
  "properties": {
    "addr:full":"Frederick Michael Salon 1233 Camino Del Rio S San Diego CA 92108",
    "addr:housenumber":"1233",
    "addr:postcode":"92108",
    "addr:street":"Camino Del Rio S",
    "iso:country":"US",
    "sg:address":"Frederick Michael Salon 1233 Camino Del Rio S",
    "sg:city":"San Diego",
    "sg:classifiers":[
        {
            "category":"Personal",
            "subcategory":"Beauty Salon",
            "type":"Services"
        }
    ],
    "sg:phone":"+1 619 865 8822",
    "sg:postcode":"92108",
    "sg:province":"CA",
    "sg:tags":[
        "spa"
    ],
    "wof:name":"Stan B",
    "wof:placetype":"venue"
},
  "geometry": {"coordinates":[-117.15224000000001,32.765472],"type":"Point"}
}