{
  "type": "Feature",
  "properties": {
    "iso:country":"US",
    "sg:address":"1104 Burghley Ln",
    "sg:city":"Brentwood",
    "sg:classifiers":[
        {
            "category":"Real Estate",
            "subcategory":"Real Estate Agent",
            "type":"Services"
        }
    ],
    "sg:phone":"+1 925 516 4563",
    "sg:postcode":"94513",
    "sg:province":"CA",
    "wof:name":"Ted & Barbara Sanderson Inc",
    "wof:placetype":"venue"
},
  "geometry": {"coordinates":[-121.719915,37.908923],"type":"Point"}
}