{
  "type": "Feature",
  "properties": {
    "addr:full":"2813 18th St San Francisco CA 94110",
    "addr:housenumber":"2813",
    "addr:postcode":"94110",
    "addr:street":"18Th St",
    "iso:country":"US",
    "sg:address":"2813 18th St",
    "sg:city":"San Francisco",
    "sg:classifiers":[
        {
            "category":"Building & Trades",
            "subcategory":"Landscaping Services",
            "type":"Services"
        }
    ],
    "sg:phone":"+1 415 920 2800",
    "sg:postcode":"94110",
    "sg:province":"CA",
    "sg:tags":[
        "designer",
        "landscape"
    ],
    "wof:name":"Lutsko Associates",
    "wof:placetype":"venue"
},
  "geometry": {"coordinates":[-122.41099,37.761632],"type":"Point"}
}