{
  "type": "Feature",
  "properties": {
    "addr:full":"2602 E Anaheim St Long Beach CA 90804",
    "addr:housenumber":"2602",
    "addr:postcode":"90804",
    "addr:street":"E Anaheim St",
    "iso:country":"US",
    "sg:address":"2602 E Anaheim St",
    "sg:city":"Long Beach",
    "sg:classifiers":[
        {
            "category":"Health Services",
            "subcategory":"Health Practitioner",
            "type":"Services"
        }
    ],
    "sg:phone":"+1 562 434 4542",
    "sg:postcode":"90804",
    "sg:province":"CA",
    "sg:tags":[
        "acupuncture"
    ],
    "wof:name":"Khmer Acupuncture & Herb",
    "wof:placetype":"venue"
},
  "geometry": {"coordinates":[-118.160059,33.782521],"type":"Point"}
}