{
  "type": "Feature",
  "properties": {
    "addr:full":"38850 Willowood Ln Squaw Valley CA 93675",
    "addr:postcode":"38850;93675",
    "addr:street":"Willowood Ln",
    "iso:country":"US",
    "sg:address":"38850 Willowood Ln",
    "sg:city":"Squaw Valley",
    "sg:classifiers":[
        {
            "category":"Wholesale",
            "subcategory":"Durable Goods & Equipment",
            "type":"Manufacturing & Wholesale Goods"
        }
    ],
    "sg:phone":"+1 559 338 2539",
    "sg:postcode":"93675",
    "sg:province":"CA",
    "wof:name":"Grace C& Stanley Thomas Tom",
    "wof:placetype":"venue"
},
  "geometry": {"coordinates":[-119.176835,36.662544],"type":"Point"}
}