{
  "type": "Feature",
  "properties": {
    "iso:country":"US",
    "sg:address":"4327 41st St",
    "sg:city":"San Diego",
    "sg:classifiers":[
        {
            "category":"Building & Trades",
            "subcategory":"Landscaping Services",
            "type":"Services"
        }
    ],
    "sg:phone":"+1 619 298 9119",
    "sg:postcode":"92105",
    "sg:province":"CA",
    "wof:name":"Fleck Landscaping Mainten",
    "wof:placetype":"venue"
},
  "geometry": {"coordinates":[-117.107091,32.756587],"type":"Point"}
}