{
  "type": "Feature",
  "properties": {
    "iso:country":"US",
    "sg:address":"77 E Daily Dr # A",
    "sg:city":"Camarillo",
    "sg:classifiers":[
        {
            "category":"Shopping",
            "subcategory":"Florist",
            "type":"Retail Goods"
        }
    ],
    "sg:phone":"+1 805 482 2320",
    "sg:postcode":"93010",
    "sg:province":"CA",
    "wof:name":"Camarillo Flower Shop",
    "wof:placetype":"venue"
},
  "geometry": {"coordinates":[-119.069,34.221901],"type":"Point"}
}