{
  "type": "Feature",
  "properties": {
    "iso:country":"US",
    "sg:address":"310 Tennessee St",
    "sg:city":"Vallejo",
    "sg:classifiers":[
        {
            "category":"Home & Garden",
            "subcategory":"Carpets & Floor Coverings",
            "type":"Retail Goods"
        }
    ],
    "sg:phone":"+1 707 644 0998",
    "sg:postcode":"94590",
    "sg:province":"CA",
    "sg:tags":[
        "dealer",
        "rug"
    ],
    "wof:name":"Vallejo Floor Co",
    "wof:placetype":"venue"
},
  "geometry": {"coordinates":[-122.256573,38.110102],"type":"Point"}
}