{
  "type": "Feature",
  "properties": {
    "iso:country":"US",
    "sg:address":"1856 1st St",
    "sg:city":"Wasco",
    "sg:classifiers":[
        {
            "category":"Professional",
            "subcategory":"Detective & Security Services",
            "type":"Services"
        }
    ],
    "sg:phone":"+1 661 342 6302",
    "sg:postcode":"93280",
    "sg:province":"CA",
    "sg:tags":[
        "information",
        "bureau"
    ],
    "wof:name":"Marias Tax Service",
    "wof:placetype":"venue"
},
  "geometry": {"coordinates":[-119.346537,35.600629],"type":"Point"}
}