{
  "type": "Feature",
  "properties": {
    "addr:full":"9849 Joe Vargas Way South El Monte CA 91733",
    "addr:housenumber":"9849",
    "addr:postcode":"91733",
    "addr:street":"Joe Vargas Way",
    "iso:country":"US",
    "sg:address":"9849 Joe Vargas Way",
    "sg:city":"South El Monte",
    "sg:classifiers":[
        {
            "category":"Wholesale",
            "subcategory":"Durable Goods & Equipment",
            "type":"Manufacturing & Wholesale Goods"
        }
    ],
    "sg:phone":"+1 626 442 3629",
    "sg:postcode":"91733",
    "sg:province":"CA",
    "sg:tags":[
        "importer"
    ],
    "wof:name":"U Chang Intl Inc",
    "wof:placetype":"venue"
},
  "geometry": {"coordinates":[-118.05468399999999,34.04461],"type":"Point"}
}