{
  "type": "Feature",
  "properties": {
    "iso:country":"US",
    "sg:address":"15 Canopy Ln",
    "sg:city":"Napa",
    "sg:classifiers":[
        {
            "category":"Professional",
            "subcategory":"Business Services",
            "type":"Services"
        }
    ],
    "sg:phone":"+1 707 337 4766",
    "sg:postcode":"94558",
    "sg:province":"CA",
    "sg:tags":[
        "interior",
        "consultant",
        "design",
        "decorator"
    ],
    "wof:name":"Papillon Interiors",
    "wof:placetype":"venue"
},
  "geometry": {"coordinates":[-122.33167299999999,38.303877],"type":"Point"}
}