{
  "type": "Feature",
  "properties": {
    "iso:country":"US",
    "sg:address":"1103 E. 16th Ave",
    "sg:city":"San Mateo",
    "sg:classifiers":[
        {
            "category":"Building & Trades",
            "subcategory":"Construction",
            "type":"Services"
        }
    ],
    "sg:phone":"+1 650 400 3600",
    "sg:postcode":"94402",
    "sg:province":"CA",
    "sg:tags":[
        "window",
        "installation",
        "contractor"
    ],
    "sg:website":"www.agreenhomeforyou.com",
    "wof:name":"A Green Home",
    "wof:placetype":"venue"
},
  "geometry": {"coordinates":[-122.304366,37.560944],"type":"Point"}
}