{
  "type": "Feature",
  "properties": {
    "iso:country":"US",
    "sg:address":"2103 S Main St",
    "sg:city":"Lakeport",
    "sg:classifiers":[
        {
            "category":"Retail",
            "subcategory":"Auto Repair",
            "type":"Services"
        }
    ],
    "sg:phone":"+1 707 263 4692",
    "sg:postcode":"95453",
    "sg:province":"CA",
    "sg:tags":[
        "repairing",
        "automobile"
    ],
    "wof:name":"Deschamps Automotive",
    "wof:placetype":"venue"
},
  "geometry": {"coordinates":[-122.916011,39.025937],"type":"Point"}
}