{
  "type": "Feature",
  "properties": {
    "iso:country":"US",
    "sg:address":"6985 Via del Oro",
    "sg:city":"San Jose",
    "sg:classifiers":[
        {
            "category":"Manufacturing",
            "subcategory":"Tools & Machinery",
            "type":"Manufacturing & Wholesale Goods"
        }
    ],
    "sg:phone":"+1 408 578 5073",
    "sg:postcode":"95119",
    "sg:province":"CA",
    "sg:tags":[
        "machine",
        "shop",
        "industrial",
        "mfg"
    ],
    "wof:name":"Ijj Engineering",
    "wof:placetype":"venue"
},
  "geometry": {"coordinates":[-121.77668300000001,37.231013],"type":"Point"}
}