{
  "type": "Feature",
  "properties": {
    "addr:full":"32400 Pine Mountain Rd Cloverdale CA 95425",
    "addr:housenumber":"32400",
    "addr:postcode":"95425",
    "addr:street":"Pine Mountain Rd",
    "iso:country":"US",
    "sg:address":"32400 Pine Mountain Rd",
    "sg:city":"Cloverdale",
    "sg:classifiers":[
        {
            "category":"Farming",
            "subcategory":"Vineyard",
            "type":"Manufacturing & Wholesale Goods"
        }
    ],
    "sg:phone":"+1 707 894 2636",
    "sg:postcode":"95425",
    "sg:province":"CA",
    "sg:tags":[
        "grape"
    ],
    "wof:name":"Black Oak Basin Vineyards",
    "wof:placetype":"venue"
},
  "geometry": {"coordinates":[-123.000469,38.829545],"type":"Point"}
}