{
  "type": "Feature",
  "properties": {
    "addr:full":"18770 Conard Ave Lake Elsinore CA 92532",
    "addr:postcode":"18770;92532",
    "addr:street":"Conard Ave",
    "iso:country":"US",
    "sg:address":"18770 Conard Ave",
    "sg:city":"Lake Elsinore",
    "sg:classifiers":[
        {
            "category":"Retail",
            "subcategory":"Auto Repair",
            "type":"Services"
        }
    ],
    "sg:phone":"+1 951 674 7544",
    "sg:postcode":"92532",
    "sg:province":"CA",
    "sg:tags":[
        "repairing",
        "automobile"
    ],
    "wof:name":"Lakeside Automotive",
    "wof:placetype":"venue"
},
  "geometry": {"coordinates":[-117.331001,33.698101],"type":"Point"}
}