{
  "type": "Feature",
  "properties": {
    "iso:country":"US",
    "sg:address":"350 La Strada Drive",
    "sg:city":"San Jose",
    "sg:classifiers":[
        {
            "category":"Real Estate",
            "subcategory":"Real Estate Operator",
            "type":"Services"
        }
    ],
    "sg:phone":"+1 408 365 9290",
    "sg:postcode":"95123",
    "sg:province":"CA",
    "sg:tags":[
        "apartment"
    ],
    "wof:name":"Villa Veneto",
    "wof:placetype":"venue"
},
  "geometry": {"coordinates":[-121.812639,37.240712],"type":"Point"}
}