{
  "type": "Feature",
  "properties": {
    "iso:country":"US",
    "sg:address":"601 W 5th St",
    "sg:city":"Los Angeles",
    "sg:classifiers":[
        {
            "category":"Restaurant",
            "type":"Food & Drink"
        }
    ],
    "sg:phone":"+1 213 489 1828",
    "sg:postcode":"90071",
    "sg:province":"CA",
    "sg:tags":[
        "sandwich"
    ],
    "wof:name":"One Bunker Hill Snack Shop",
    "wof:placetype":"venue"
},
  "geometry": {"coordinates":[-118.254929,34.05082],"type":"Point"}
}