{
  "type": "Feature",
  "properties": {
    "addr:full":"1775 Rogers Ave San Jose CA 95112",
    "addr:housenumber":"1775",
    "addr:postcode":"95112",
    "addr:street":"Rogers Ave",
    "iso:country":"US",
    "sg:address":"1775 Rogers Ave",
    "sg:city":"San Jose",
    "sg:classifiers":[
        {
            "category":"Building & Trades",
            "subcategory":"Construction",
            "type":"Services"
        }
    ],
    "sg:phone":"+1 408 437 1127",
    "sg:postcode":"95112",
    "sg:province":"CA",
    "sg:tags":[
        "tile",
        "dealer"
    ],
    "wof:name":"Tile Depot",
    "wof:placetype":"venue"
},
  "geometry": {"coordinates":[-121.908962,37.37586],"type":"Point"}
}