{
  "type": "Feature",
  "properties": {
    "iso:country":"US",
    "sg:address":"229 S Vasco Rd",
    "sg:city":"Livermore",
    "sg:classifiers":[
        {
            "category":"Restaurant",
            "type":"Food & Drink"
        }
    ],
    "sg:phone":"+1 925 960 9045",
    "sg:postcode":"94551",
    "sg:province":"CA",
    "wof:name":"Taqueria Consuelito",
    "wof:placetype":"venue"
},
  "geometry": {"coordinates":[-121.723546,37.707932],"type":"Point"}
}