{
  "type": "Feature",
  "properties": {
    "iso:country":"US",
    "sg:address":"2409 21st St",
    "sg:city":"Sacramento",
    "sg:classifiers":[
        {
            "category":"Shopping",
            "subcategory":"Clothing, Apparel, & Fashions",
            "type":"Retail Goods"
        },
        {
            "category":"Home & Garden",
            "subcategory":"Home Furnishings",
            "type":"Retail Goods"
        },
        {
            "category":"Shopping",
            "subcategory":"Antiques",
            "type":"Retail Goods"
        }
    ],
    "sg:phone":"+1 916 706 0216",
    "sg:postcode":"95818",
    "sg:province":"CA",
    "sg:tags":[
        "decor",
        "clothing",
        "women's"
    ],
    "wof:name":"Fringe",
    "wof:placetype":"venue"
},
  "geometry": {"coordinates":[-121.485123,38.560489],"type":"Point"}
}