{
  "type": "Feature",
  "properties": {
    "addr:full":"11305 Rancho Bernardo Rd San Diego CA 92127",
    "addr:housenumber":"11305",
    "addr:postcode":"92127",
    "addr:street":"Rancho Bernardo Rd",
    "iso:country":"US",
    "sg:address":"11305 Rancho Bernardo Rd",
    "sg:city":"San Diego",
    "sg:classifiers":[
        {
            "category":"Professional",
            "subcategory":"Business Services",
            "type":"Services"
        }
    ],
    "sg:phone":"+1 858 451 7490",
    "sg:postcode":"92127",
    "sg:province":"CA",
    "sg:tags":[
        "translator",
        "interpreter"
    ],
    "sg:website":"www.interpretersunlimited.com",
    "wof:name":"Interpreters Unlimited",
    "wof:placetype":"venue"
},
  "geometry": {"coordinates":[-117.085334,33.024362],"type":"Point"}
}