{
  "type": "Feature",
  "properties": {
    "addr:full":"16602 S Harris Ave Compton CA 90221",
    "addr:housenumber":"16602",
    "addr:postcode":"90221",
    "addr:street":"S Harris Ave",
    "iso:country":"US",
    "sg:address":"16602 S Harris Ave",
    "sg:city":"Compton",
    "sg:classifiers":[
        {
            "category":"Travel",
            "subcategory":"Travel Agent",
            "type":"Entertainment"
        }
    ],
    "sg:phone":"+1 310 604 4700",
    "sg:postcode":"90221",
    "sg:province":"CA",
    "sg:tags":[
        "operator",
        "tour"
    ],
    "wof:name":"Dukes Sie & Jeannetta",
    "wof:placetype":"venue"
},
  "geometry": {"coordinates":[-118.19725,33.882514],"type":"Point"}
}