{
  "type": "Feature",
  "properties": {
    "addr:full":"607 Pico Ave San Mateo CA 94403",
    "addr:housenumber":"607",
    "addr:postcode":"94403",
    "addr:street":"Pico Ave",
    "iso:country":"US",
    "sg:address":"607 Pico Ave",
    "sg:city":"San Mateo",
    "sg:classifiers":[
        {
            "category":"Professional",
            "type":"Services"
        }
    ],
    "sg:phone":"+1 650 345 8082",
    "sg:postcode":"94403",
    "sg:province":"CA",
    "wof:name":"Coordinamento Italia LLC",
    "wof:placetype":"venue"
},
  "geometry": {"coordinates":[-122.31858,37.54012],"type":"Point"}
}