{
  "type": "Feature",
  "properties": {
    "addr:full":"4277 Schaefer Ave Chino CA 91710",
    "addr:housenumber":"4277",
    "addr:postcode":"91710",
    "addr:street":"Schaefer Ave",
    "iso:country":"US",
    "sg:address":"4277 Schaefer Ave",
    "sg:city":"Chino",
    "sg:classifiers":[
        {
            "category":"Professional",
            "type":"Services"
        },
        {
            "category":"Personal",
            "type":"Services"
        }
    ],
    "sg:phone":"+1 714 850 1251",
    "sg:postcode":"91710",
    "sg:province":"CA",
    "sg:tags":[
        "mover",
        "material",
        "moving",
        "services-labor"
    ],
    "wof:name":"D O T S",
    "wof:placetype":"venue"
},
  "geometry": {"coordinates":[-117.711331,34.004398],"type":"Point"}
}