{
  "type": "Feature",
  "properties": {
    "iso:country":"US",
    "sg:address":"8424 Santa Monica Blvd Suite E",
    "sg:city":"West Hollywood",
    "sg:classifiers":[
        {
            "category":"Shopping",
            "subcategory":"Beauty & Cosmetics",
            "type":"Retail Goods"
        }
    ],
    "sg:phone":"+1 323 656 2237",
    "sg:postcode":"90069",
    "sg:province":"CA",
    "sg:tags":[
        "supply"
    ],
    "wof:name":"West Hollywood Beauty Supply and Salon",
    "wof:placetype":"venue"
},
  "geometry": {"coordinates":[-118.374218,34.090478],"type":"Point"}
}