{
  "type": "Feature",
  "properties": {
    "addr:full":"2837 36th Street Sacramento CA 95817",
    "addr:housenumber":"2837",
    "addr:postcode":"95817",
    "addr:street":"36Th Street",
    "iso:country":"US",
    "sg:address":"2837 36th Street",
    "sg:city":"Sacramento",
    "sg:classifiers":[
        {
            "category":"Arts & Performance",
            "subcategory":"Art Gallery",
            "type":"Entertainment"
        }
    ],
    "sg:phone":"+1 916 457 2502",
    "sg:postcode":"95817",
    "sg:province":"CA",
    "wof:name":"Brickhouse Art Studios",
    "wof:placetype":"venue"
},
  "geometry": {"coordinates":[-121.467336,38.55053],"type":"Point"}
}