{
  "type": "Feature",
  "properties": {
    "iso:country":"US",
    "sg:address":"11429 Garvey Ave",
    "sg:city":"El Monte",
    "sg:classifiers":[
        {
            "category":"Wholesale",
            "subcategory":"Drugs",
            "type":"Manufacturing & Wholesale Goods"
        }
    ],
    "sg:phone":"+1 626 579 7613",
    "sg:postcode":"91732",
    "sg:province":"CA",
    "sg:tags":[
        "cosmetic"
    ],
    "wof:name":"Fuller Brush By Fernando",
    "wof:placetype":"venue"
},
  "geometry": {"coordinates":[-118.030542,34.062841],"type":"Point"}
}