{
  "type": "Feature",
  "properties": {
    "iso:country":"US",
    "sg:address":"123 E Gladstone St",
    "sg:city":"Azusa",
    "sg:classifiers":[
        {
            "category":"Autos & Motor Vehicles",
            "subcategory":"Auto Supplies",
            "type":"Retail Goods"
        }
    ],
    "sg:phone":"+1 626 812 9712",
    "sg:postcode":"91702",
    "sg:province":"CA",
    "sg:tags":[
        "tire"
    ],
    "wof:name":"K & K Firestone",
    "wof:placetype":"venue"
},
  "geometry": {"coordinates":[-117.905688,34.114306],"type":"Point"}
}