{
  "type": "Feature",
  "properties": {
    "iso:country":"US",
    "sg:address":"9th Ave and Lincoln Way",
    "sg:city":"San Francisco",
    "sg:classifiers":[
        {
            "category":"Government",
            "subcategory":"City Hall",
            "type":"Public Place"
        }
    ],
    "sg:phone":"+1 415 831 5500",
    "sg:postcode":"94122",
    "sg:province":"CA",
    "wof:name":"San Francisco County Fair Building",
    "wof:placetype":"venue"
},
  "geometry": {"coordinates":[-122.466442,37.765967],"type":"Point"}
}