{
  "type": "Feature",
  "properties": {
    "addr:full":"4915 Eagle Rock Boulevard Los Angeles CA 90041",
    "addr:housenumber":"4915",
    "addr:postcode":"90041",
    "addr:street":"Eagle Rock Boulevard",
    "iso:country":"US",
    "sg:address":"4915 Eagle Rock Boulevard",
    "sg:city":"Los Angeles",
    "sg:classifiers":[
        {
            "category":"Retail",
            "subcategory":"Portrait Studio",
            "type":"Services"
        }
    ],
    "sg:phone":"+1 323 256 4001",
    "sg:postcode":"90041",
    "sg:province":"CA",
    "sg:tags":[
        "photography",
        "store"
    ],
    "wof:name":"Photo Express Color Lab",
    "wof:placetype":"venue"
},
  "geometry": {"coordinates":[-118.21542700000001,34.135278],"type":"Point"}
}