{
  "type": "Feature",
  "properties": {
    "iso:country":"US",
    "sg:address":"950 N Fair Oaks Ave",
    "sg:city":"Pasadena",
    "sg:classifiers":[
        {
            "category":"Wholesale",
            "subcategory":"Groceries",
            "type":"Manufacturing & Wholesale Goods"
        }
    ],
    "sg:phone":"+1 626 798 0841",
    "sg:postcode":"91103",
    "sg:province":"CA",
    "sg:tags":[
        "food",
        "product"
    ],
    "sg:website":"www.gourmetpasta.com",
    "wof:name":"Gourmet's Fresh Pasta",
    "wof:placetype":"venue"
},
  "geometry": {"coordinates":[-118.15054,34.162106],"type":"Point"}
}