{
  "type": "Feature",
  "properties": {
    "iso:country":"US",
    "sg:address":"801 Magnolia Ave",
    "sg:city":"Corona",
    "sg:classifiers":[
        {
            "category":"Real Estate",
            "subcategory":"Real Estate Operator",
            "type":"Services"
        }
    ],
    "sg:phone":"+1 951 736 3116",
    "sg:postcode":"92879",
    "sg:province":"CA",
    "sg:tags":[
        "apartment"
    ],
    "wof:name":"Casa Grande Senior Apartments",
    "wof:placetype":"venue"
},
  "geometry": {"coordinates":[-117.55397499999999,33.859271],"type":"Point"}
}