{
  "type": "Feature",
  "properties": {
    "iso:country":"US",
    "sg:address":"30826 Santana St",
    "sg:city":"Hayward",
    "sg:classifiers":[
        {
            "category":"Home & Garden",
            "subcategory":"Kitchen Supply",
            "type":"Retail Goods"
        }
    ],
    "sg:phone":"+1 510 429 8200",
    "sg:postcode":"94544",
    "sg:province":"CA",
    "sg:tags":[
        "utensil",
        "cookware"
    ],
    "sg:website":"http://www.thegsc.com",
    "wof:name":"Gsc",
    "wof:placetype":"venue"
},
  "geometry": {"coordinates":[-122.05722900000001,37.614415],"type":"Point"}
}