{
  "type": "Feature",
  "properties": {
    "addr:full":"300 S Beach Blvd La Habra CA 90631",
    "addr:housenumber":"300",
    "addr:postcode":"90631",
    "addr:street":"S Beach Blvd",
    "iso:country":"US",
    "sg:address":"300 S Beach Blvd",
    "sg:city":"La Habra",
    "sg:classifiers":[
        {
            "category":"Education",
            "subcategory":"School",
            "type":"Public Place"
        }
    ],
    "sg:phone":"+1 562 691 8195",
    "sg:postcode":"90631",
    "sg:province":"CA",
    "wof:name":"Children's Enrichment Center",
    "wof:placetype":"venue"
},
  "geometry": {"coordinates":[-117.967564,33.930199],"type":"Point"}
}