{
  "type": "Feature",
  "properties": {
    "iso:country":"US",
    "sg:address":"435 1st St",
    "sg:city":"Solvang",
    "sg:classifiers":[
        {
            "category":"Freight",
            "type":"Transportation"
        }
    ],
    "sg:phone":"+1 805 693 5000",
    "sg:postcode":"93463",
    "sg:province":"CA",
    "sg:tags":[
        "warehouse"
    ],
    "wof:name":"Bill Berman Cailfornia",
    "wof:placetype":"venue"
},
  "geometry": {"coordinates":[-120.140474,34.593492],"type":"Point"}
}