{
  "type": "Feature",
  "properties": {
    "iso:country":"US",
    "sg:address":"7657 Winnetka Ave Ste 182",
    "sg:city":"Winnetka",
    "sg:classifiers":[
        {
            "category":"Shopping",
            "subcategory":"Gifts & Souvenirs",
            "type":"Retail Goods"
        },
        {
            "category":"Retail",
            "subcategory":"Storage",
            "type":"Services"
        },
        {
            "category":"Manufacturing",
            "subcategory":"Paper Products",
            "type":"Manufacturing & Wholesale Goods"
        }
    ],
    "sg:phone":"+1 818 718 9097",
    "sg:postcode":"91306",
    "sg:province":"CA",
    "sg:tags":[
        "development",
        "container",
        "package",
        "material",
        "wrapping",
        "design"
    ],
    "wof:name":"Diamond Packaging",
    "wof:placetype":"venue"
},
  "geometry": {"coordinates":[-118.57100699999999,34.209664],"type":"Point"}
}