{
  "type": "Feature",
  "properties": {
    "addr:full":"8611 Crenshaw Blvd Inglewood CA 90305",
    "addr:housenumber":"8611",
    "addr:postcode":"90305",
    "addr:street":"Crenshaw Blvd",
    "iso:country":"US",
    "sg:address":"8611 Crenshaw Blvd",
    "sg:city":"Inglewood",
    "sg:classifiers":[
        {
            "category":"Wholesale",
            "subcategory":"Medical Equipment & Supplies",
            "type":"Manufacturing & Wholesale Goods"
        }
    ],
    "sg:phone":"+1 310 419 6046",
    "sg:postcode":"90305",
    "sg:province":"CA",
    "wof:name":"Tonoma Medical Supply",
    "wof:placetype":"venue"
},
  "geometry": {"coordinates":[-118.326424,33.960057],"type":"Point"}
}