{
  "type": "Feature",
  "properties": {
    "addr:full":"1230 Broadway Santa Cruz CA 95062",
    "addr:housenumber":"1230",
    "addr:postcode":"95062",
    "addr:street":"Broadway",
    "iso:country":"US",
    "sg:address":"1230 Broadway",
    "sg:city":"Santa Cruz",
    "sg:classifiers":[
        {
            "category":"Wholesale",
            "subcategory":"Hardware",
            "type":"Manufacturing & Wholesale Goods"
        }
    ],
    "sg:phone":"+1 831 421 0234",
    "sg:postcode":"95062",
    "sg:province":"CA",
    "sg:tags":[
        "equipment",
        "energy",
        "solar"
    ],
    "wof:name":"Apollopower",
    "wof:placetype":"venue"
},
  "geometry": {"coordinates":[-122.009091,36.975169],"type":"Point"}
}