{
  "type": "Feature",
  "properties": {
    "iso:country":"US",
    "sg:address":"1755 Ofarrell St",
    "sg:city":"San Francisco",
    "sg:classifiers":[
        {
            "category":"Building & Trades",
            "subcategory":"Construction",
            "type":"Services"
        }
    ],
    "sg:phone":"+1 415 614 2529",
    "sg:postcode":"94115",
    "sg:province":"CA",
    "sg:tags":[
        "residential"
    ],
    "wof:name":"J K Construction Associates",
    "wof:placetype":"venue"
},
  "geometry": {"coordinates":[-122.433377,37.783143],"type":"Point"}
}