{
  "type": "Feature",
  "properties": {
    "addr:full":"2253 W Whittier Blvd La Habra CA 90631",
    "addr:housenumber":"2253",
    "addr:postcode":"90631",
    "addr:street":"W Whittier Blvd",
    "iso:country":"US",
    "sg:address":"2253 W Whittier Blvd",
    "sg:city":"La Habra",
    "sg:classifiers":[
        {
            "category":"Shopping",
            "subcategory":"Bicycles & Sporting Goods",
            "type":"Retail Goods"
        }
    ],
    "sg:phone":"+1 714 529 3932",
    "sg:postcode":"90631",
    "sg:province":"CA",
    "sg:tags":[
        "gun",
        "gunsmith"
    ],
    "wof:name":"Gun Store",
    "wof:placetype":"venue"
},
  "geometry": {"coordinates":[-117.970788,33.939943],"type":"Point"}
}