{
  "type": "Feature",
  "properties": {
    "addr:full":"1570 The Alameda Ste 228 San Jose CA 95126",
    "addr:housenumber":"1570",
    "addr:postcode":"95126",
    "addr:street":"The Alameda Ste 228",
    "iso:country":"US",
    "sg:address":"1570 The Alameda Ste 228",
    "sg:city":"San Jose",
    "sg:classifiers":[
        {
            "category":"Community Center",
            "type":"Public Place"
        }
    ],
    "sg:phone":"+1 408 293 3888",
    "sg:postcode":"95126",
    "sg:province":"CA",
    "sg:tags":[
        "medical"
    ],
    "wof:name":"The Valley Psychiatric Medical Group",
    "wof:placetype":"venue"
},
  "geometry": {"coordinates":[-121.916135,37.335013],"type":"Point"}
}