{
  "type": "Feature",
  "properties": {
    "addr:full":"8620 Production Ave San Diego CA 92121",
    "addr:housenumber":"8620",
    "addr:postcode":"92121",
    "addr:street":"Production Ave",
    "iso:country":"US",
    "sg:address":"8620 Production Ave",
    "sg:city":"San Diego",
    "sg:classifiers":[
        {
            "category":"Shopping",
            "subcategory":"Photographic Equipment",
            "type":"Retail Goods"
        }
    ],
    "sg:phone":"+1 858 549 6687",
    "sg:postcode":"92121",
    "sg:province":"CA",
    "sg:tags":[
        "supply"
    ],
    "wof:name":"Fotima USA Inc",
    "wof:placetype":"venue"
},
  "geometry": {"coordinates":[-117.16585000000001,32.88398],"type":"Point"}
}