{
  "type": "Feature",
  "properties": {
    "iso:country":"US",
    "sg:address":"1230 Cedar St",
    "sg:city":"Berkeley",
    "sg:classifiers":[
        {
            "category":"Health Services",
            "subcategory":"Medical Lab",
            "type":"Services"
        },
        {
            "category":"Professional",
            "subcategory":"Employment Agencies",
            "type":"Services"
        }
    ],
    "sg:phone":"+1 510 524 4160",
    "sg:postcode":"94702",
    "sg:province":"CA",
    "sg:tags":[
        "transcription",
        "processing",
        "word"
    ],
    "wof:name":"Carol Niehus Word Processing",
    "wof:placetype":"venue"
},
  "geometry": {"coordinates":[-122.28958799999999,37.875795],"type":"Point"}
}