{
  "type": "Feature",
  "properties": {
    "iso:country":"US",
    "sg:address":"11602 Knott St",
    "sg:city":"Garden Grove",
    "sg:classifiers":[
        {
            "category":"Professional",
            "subcategory":"Computer Services",
            "type":"Services"
        }
    ],
    "sg:phone":"+1 714 894 5456",
    "sg:postcode":"92841",
    "sg:province":"CA",
    "sg:tags":[
        "repair"
    ],
    "wof:name":"Matrixtek Computer Technology",
    "wof:placetype":"venue"
},
  "geometry": {"coordinates":[-118.011004,33.793049],"type":"Point"}
}