{
  "type": "Feature",
  "properties": {
    "iso:country":"US",
    "sg:address":"349 S Mountain Ave",
    "sg:city":"Upland",
    "sg:classifiers":[
        {
            "category":"Shopping",
            "subcategory":"Clothing, Apparel, & Fashions",
            "type":"Retail Goods"
        }
    ],
    "sg:phone":"+1 909 982 3637",
    "sg:postcode":"91786",
    "sg:province":"CA",
    "wof:name":"Winston's Sporting Goods",
    "wof:placetype":"venue"
},
  "geometry": {"coordinates":[-117.670215,34.091501],"type":"Point"}
}