{
  "type": "Feature",
  "properties": {
    "addr:full":"168 N Front St Earlimart CA 93274",
    "addr:housenumber":"168",
    "addr:postcode":"93274",
    "addr:street":"N Front St",
    "iso:country":"US",
    "sg:address":"168 N Front St",
    "sg:city":"Earlimart",
    "sg:classifiers":[
        {
            "category":"Utilities",
            "subcategory":"Water",
            "type":"Services"
        }
    ],
    "sg:phone":"+1 661 849 2663",
    "sg:postcode":"93274",
    "sg:province":"CA",
    "sg:tags":[
        "company",
        "sewage"
    ],
    "wof:name":"Earlimart Public Utility Dist",
    "wof:placetype":"venue"
},
  "geometry": {"coordinates":[-119.27392399999999,35.885211],"type":"Point"}
}