{
  "type": "Feature",
  "properties": {
    "iso:country":"US",
    "sg:address":"2343 Ashland Ave",
    "sg:city":"Santa Monica",
    "sg:classifiers":[
        {
            "category":"Shopping",
            "subcategory":"Bicycles & Sporting Goods",
            "type":"Retail Goods"
        }
    ],
    "sg:phone":"+1 310 452 4019",
    "sg:postcode":"90405",
    "sg:province":"CA",
    "sg:tags":[
        "auto"
    ],
    "wof:name":"Sheepskin Experience",
    "wof:placetype":"venue"
},
  "geometry": {"coordinates":[-118.457981,34.013972],"type":"Point"}
}