{
  "type": "Feature",
  "properties": {
    "iso:country":"US",
    "sg:address":"3865 Pacific Coast Hwy",
    "sg:city":"Torrance",
    "sg:classifiers":[
        {
            "category":"Shopping",
            "subcategory":"Hobbies, Toys, & Games",
            "type":"Retail Goods"
        }
    ],
    "sg:phone":"+1 310 791 2637",
    "sg:postcode":"90505",
    "sg:province":"CA",
    "sg:tags":[
        "model",
        "supply"
    ],
    "sg:website":"www.all-aboard-rr.com",
    "wof:name":"All Aboard Model Railroad",
    "wof:placetype":"venue"
},
  "geometry": {"coordinates":[-118.352469,33.805667],"type":"Point"}
}