{
  "type": "Feature",
  "properties": {
    "iso:country":"US",
    "sg:address":"192 Hall Dr",
    "sg:city":"Orinda",
    "sg:classifiers":[
        {
            "category":"Retail",
            "subcategory":"Animal Services",
            "type":"Services"
        }
    ],
    "sg:phone":"+1 925 254 8905",
    "sg:postcode":"94563",
    "sg:province":"CA",
    "wof:name":"Pacific Coast Working Dog Club",
    "wof:placetype":"venue"
},
  "geometry": {"coordinates":[-122.153767,37.860534],"type":"Point"}
}