{
  "type": "Feature",
  "properties": {
    "iso:country":"US",
    "sg:address":"45 John Glenn Dr",
    "sg:city":"Concord",
    "sg:classifiers":[
        {
            "category":"Travel",
            "subcategory":"Hotels & Motels",
            "type":"Entertainment"
        }
    ],
    "sg:phone":"+1 925 825 7700",
    "sg:postcode":"94520",
    "sg:province":"CA",
    "sg:tags":[
        "operation",
        "eating",
        "drinking"
    ],
    "sg:website":"www.sheraton.com",
    "wof:name":"Sheraton",
    "wof:placetype":"venue"
},
  "geometry": {"coordinates":[-122.054683,37.984786],"type":"Point"}
}