{
  "type": "Feature",
  "properties": {
    "iso:country":"US",
    "sg:address":"853 S Van Horn Ave",
    "sg:city":"West Covina",
    "sg:classifiers":[
        {
            "category":"Professional",
            "type":"Services"
        }
    ],
    "sg:phone":"+1 626 960 8111",
    "sg:postcode":"91790",
    "sg:province":"CA",
    "wof:name":"Mark W Wabnitz",
    "wof:placetype":"venue"
},
  "geometry": {"coordinates":[-117.938342,34.058188],"type":"Point"}
}