{
  "type": "Feature",
  "properties": {
    "addr:full":"1010 Oro St Laguna Beach CA 92651",
    "addr:housenumber":"1010",
    "addr:postcode":"92651",
    "addr:street":"Oro St",
    "iso:country":"US",
    "sg:address":"1010 Oro St",
    "sg:city":"Laguna Beach",
    "sg:classifiers":[
        {
            "category":"Real Estate",
            "subcategory":"Architect",
            "type":"Services"
        }
    ],
    "sg:phone":"+1 949 715 6710",
    "sg:postcode":"92651",
    "sg:province":"CA",
    "wof:name":"Douglas Franz Architects",
    "wof:placetype":"venue"
},
  "geometry": {"coordinates":[-117.758645,33.530499],"type":"Point"}
}