{
  "type": "Feature",
  "properties": {
    "iso:country":"US",
    "sg:address":"27740 Santa Margarita Pkwy",
    "sg:city":"Mission Viejo",
    "sg:classifiers":[
        {
            "category":"Personal",
            "subcategory":"Skin Care",
            "type":"Services"
        }
    ],
    "sg:phone":"+1 949 454 1994",
    "sg:postcode":"92691",
    "sg:province":"CA",
    "wof:name":"Top Nails",
    "wof:placetype":"venue"
},
  "geometry": {"coordinates":[-117.64458,33.651528],"type":"Point"}
}