{
  "type": "Feature",
  "properties": {
    "addr:full":"753 E Lake Ave Watsonville CA 95076",
    "addr:housenumber":"753",
    "addr:postcode":"95076",
    "addr:street":"E Lake Ave",
    "iso:country":"US",
    "sg:address":"753 E Lake Ave",
    "sg:city":"Watsonville",
    "sg:classifiers":[
        {
            "category":"Retail",
            "subcategory":"Car Wash",
            "type":"Services"
        }
    ],
    "sg:phone":"+1 831 724 4904",
    "sg:postcode":"95076",
    "sg:province":"CA",
    "sg:tags":[
        "automobile",
        "detail",
        "clean"
    ],
    "wof:name":"L & G Detail",
    "wof:placetype":"venue"
},
  "geometry": {"coordinates":[-121.74729499999999,36.921342],"type":"Point"}
}