{
  "type": "Feature",
  "properties": {
    "addr:full":"711 W 17th Street Costa Mesa CA 92627",
    "addr:housenumber":"711",
    "addr:postcode":"92627",
    "addr:street":"W 17Th Street",
    "iso:country":"US",
    "sg:address":"711 W 17th Street",
    "sg:city":"Costa Mesa",
    "sg:classifiers":[
        {
            "category":"Shopping",
            "subcategory":"Pharmacy",
            "type":"Retail Goods"
        }
    ],
    "sg:phone":"+1 949 642 6926",
    "sg:postcode":"92627",
    "sg:province":"CA",
    "sg:tags":[
        "drugstore"
    ],
    "wof:name":"Rx of Cananda",
    "wof:placetype":"venue"
},
  "geometry": {"coordinates":[-117.928028,33.636145],"type":"Point"}
}