{
  "type": "Feature",
  "properties": {
    "addr:full":"502 N Sheridan St Corona CA 92880",
    "addr:housenumber":"502",
    "addr:postcode":"92880",
    "addr:street":"N Sheridan St",
    "iso:country":"US",
    "sg:address":"502 N Sheridan St",
    "sg:city":"Corona",
    "sg:classifiers":[
        {
            "category":"Professional",
            "subcategory":"Management & Consulting",
            "type":"Services"
        }
    ],
    "sg:phone":"+1 951 279 2150",
    "sg:postcode":"92880",
    "sg:province":"CA",
    "sg:tags":[
        "break",
        "coffee",
        "supply"
    ],
    "wof:name":"Aramark Refreshment Svc",
    "wof:placetype":"venue"
},
  "geometry": {"coordinates":[-117.56842399999999,33.885961],"type":"Point"}
}