{
  "type": "Feature",
  "properties": {
    "iso:country":"US",
    "sg:address":"593 Paradise Rd",
    "sg:city":"Salinas",
    "sg:classifiers":[
        {
            "category":"Utilities",
            "subcategory":"Water",
            "type":"Services"
        }
    ],
    "sg:phone":"+1 831 663 0931",
    "sg:postcode":"93907",
    "sg:province":"CA",
    "sg:tags":[
        "company-utility",
        "supply"
    ],
    "wof:name":"Moro Cojo Water Co",
    "wof:placetype":"venue"
},
  "geometry": {"coordinates":[-121.697113,36.815643],"type":"Point"}
}