{
  "type": "Feature",
  "properties": {
    "iso:country":"US",
    "sg:address":"1214 Bell St",
    "sg:city":"Sacramento",
    "sg:classifiers":[
        {
            "category":"Real Estate",
            "subcategory":"Real Estate Operator",
            "type":"Services"
        }
    ],
    "sg:phone":"+1 916 923 1725",
    "sg:postcode":"95825",
    "sg:province":"CA",
    "sg:tags":[
        "apartment"
    ],
    "wof:name":"Loma Vista Apartments",
    "wof:placetype":"venue"
},
  "geometry": {"coordinates":[-121.410647,38.588578],"type":"Point"}
}