{
  "type": "Feature",
  "properties": {
    "iso:country":"US",
    "sg:address":"31125 Lobo Vista Rd",
    "sg:city":"Agoura Hills",
    "sg:classifiers":[
        {
            "category":"Building & Trades",
            "subcategory":"Construction",
            "type":"Services"
        }
    ],
    "sg:phone":"+1 818 706 3574",
    "sg:postcode":"91301",
    "sg:province":"CA",
    "sg:tags":[
        "concrete",
        "restoration",
        "cleaning",
        "repair"
    ],
    "wof:name":"Houseman Co",
    "wof:placetype":"venue"
},
  "geometry": {"coordinates":[-118.799236,34.121804],"type":"Point"}
}