{
  "type": "Feature",
  "properties": {
    "iso:country":"US",
    "sg:address":"1963 Darkwood Ct",
    "sg:city":"Thousand Oaks",
    "sg:classifiers":[
        {
            "category":"Professional",
            "subcategory":"Management & Consulting",
            "type":"Services"
        }
    ],
    "sg:phone":"+1 805 379 9763",
    "sg:postcode":"91360",
    "sg:province":"CA",
    "sg:tags":[
        "mail",
        "house"
    ],
    "wof:name":"DJM Business Services",
    "wof:placetype":"venue"
},
  "geometry": {"coordinates":[-118.889084,34.20517],"type":"Point"}
}