{
  "type": "Feature",
  "properties": {
    "addr:full":"476 Soscol Ave Napa CA 94559",
    "addr:housenumber":"476",
    "addr:postcode":"94559",
    "addr:street":"Soscol Ave",
    "iso:country":"US",
    "sg:address":"476 Soscol Ave",
    "sg:city":"Napa",
    "sg:classifiers":[
        {
            "category":"Autos & Motor Vehicles",
            "subcategory":"Automobile Sales",
            "type":"Retail Goods"
        },
        {
            "category":"Retail",
            "subcategory":"Auto Rental",
            "type":"Services"
        }
    ],
    "sg:phone":"+1 707 224 7846",
    "sg:postcode":"94559",
    "sg:province":"CA",
    "sg:tags":[
        "car",
        "leasing",
        "truck"
    ],
    "sg:website":"http://budget.com/IYP_tl",
    "wof:name":"Budget Rent A Car",
    "wof:placetype":"venue"
},
  "geometry": {"coordinates":[-122.277282,38.291562],"type":"Point"}
}