{
  "type": "Feature",
  "properties": {
    "addr:full":"325 W Mariposa Dr Redlands CA 92373",
    "addr:housenumber":"325",
    "addr:postcode":"92373",
    "addr:street":"W Mariposa Dr",
    "iso:country":"US",
    "sg:address":"325 W Mariposa Dr",
    "sg:city":"Redlands",
    "sg:classifiers":[
        {
            "category":"Home & Garden",
            "subcategory":"Home Furnishings",
            "type":"Retail Goods"
        },
        {
            "category":"Professional",
            "subcategory":"Art Services",
            "type":"Services"
        }
    ],
    "sg:phone":"+1 909 793 8502",
    "sg:postcode":"92373",
    "sg:province":"CA",
    "sg:tags":[
        "planning",
        "interior",
        "designer",
        "design",
        "decorator"
    ],
    "wof:name":"Jerry Fisher Interior Design",
    "wof:placetype":"venue"
},
  "geometry": {"coordinates":[-117.157259,34.025157],"type":"Point"}
}