{
  "type": "Feature",
  "properties": {
    "iso:country":"US",
    "sg:address":"18723 Ventura Blvd",
    "sg:city":"Tarzana",
    "sg:classifiers":[
        {
            "category":"Shopping",
            "subcategory":"Clothing, Apparel, & Fashions",
            "type":"Retail Goods"
        }
    ],
    "sg:phone":"+1 818 343 5332",
    "sg:postcode":"91356",
    "sg:province":"CA",
    "sg:tags":[
        "handbag"
    ],
    "wof:name":"Billy's Fashions",
    "wof:placetype":"venue"
},
  "geometry": {"coordinates":[-118.542379,34.171388],"type":"Point"}
}