{
  "type": "Feature",
  "properties": {
    "iso:country":"US",
    "sg:address":"44 Montgomery St",
    "sg:city":"San Francisco",
    "sg:classifiers":[
        {
            "category":"Professional",
            "subcategory":"Computer Services",
            "type":"Services"
        }
    ],
    "sg:phone":"+1 510 665 1111",
    "sg:postcode":"94104",
    "sg:province":"CA",
    "sg:website":"www.id8media.com",
    "wof:name":"Id 8 Media",
    "wof:placetype":"venue"
},
  "geometry": {"coordinates":[-122.402049,37.789642],"type":"Point"}
}