{
  "type": "Feature",
  "properties": {
    "iso:country":"US",
    "sg:address":"309 E 9th St",
    "sg:city":"Los Angeles",
    "sg:classifiers":[
        {
            "category":"Shopping",
            "subcategory":"Crafts & Fabrics",
            "type":"Retail Goods"
        }
    ],
    "sg:phone":"+1 213 488 4944",
    "sg:postcode":"90015",
    "sg:province":"CA",
    "sg:tags":[
        "store"
    ],
    "wof:name":"Niki's Fabric Gallery",
    "wof:placetype":"venue"
},
  "geometry": {"coordinates":[-118.252998,34.039501],"type":"Point"}
}