{
  "type": "Feature",
  "properties": {
    "addr:full":"1026 Daisy Ave Carlsbad CA 92011",
    "addr:housenumber":"1026",
    "addr:postcode":"92011",
    "addr:street":"Daisy Ave",
    "iso:country":"US",
    "sg:address":"1026 Daisy Ave",
    "sg:city":"Carlsbad",
    "sg:classifiers":[
        {
            "category":"Professional",
            "type":"Services"
        }
    ],
    "sg:phone":"+1 760 431 0132",
    "sg:postcode":"92011",
    "sg:province":"CA",
    "wof:name":"Avaira Home Support Svc",
    "wof:placetype":"venue"
},
  "geometry": {"coordinates":[-117.297561,33.100207],"type":"Point"}
}