{
  "type": "Feature",
  "properties": {
    "iso:country":"US",
    "sg:address":"2617 K St Ste 250",
    "sg:city":"Sacramento",
    "sg:classifiers":[
        {
            "category":"Social Services",
            "type":"Services"
        }
    ],
    "sg:phone":"+1 916 716 3040",
    "sg:postcode":"95816",
    "sg:province":"CA",
    "sg:tags":[
        "therapist",
        "marriage",
        "family"
    ],
    "wof:name":"Ciminelli Sue MFT",
    "wof:placetype":"venue"
},
  "geometry": {"coordinates":[-121.472161,38.573411],"type":"Point"}
}