{
  "type": "Feature",
  "properties": {
    "iso:country":"US",
    "sg:address":"1844 Evergreen St",
    "sg:city":"Duarte",
    "sg:classifiers":[
        {
            "category":"Health Services",
            "subcategory":"Medical Lab",
            "type":"Services"
        }
    ],
    "sg:phone":"+1 626 359 8261",
    "sg:postcode":"91010",
    "sg:province":"CA",
    "sg:tags":[
        "laboratory"
    ],
    "wof:name":"Ortek Orthodontic Laboratories",
    "wof:placetype":"venue"
},
  "geometry": {"coordinates":[-117.965353,34.134997],"type":"Point"}
}