{
  "type": "Feature",
  "properties": {
    "iso:country":"US",
    "sg:address":"1776 All American Way",
    "sg:city":"Corona",
    "sg:classifiers":[
        {
            "category":"Freight",
            "type":"Transportation"
        }
    ],
    "sg:phone":"+1 951 371 6673",
    "sg:postcode":"92879",
    "sg:province":"CA",
    "sg:tags":[
        "trucking"
    ],
    "wof:name":"More Truck Lines",
    "wof:placetype":"venue"
},
  "geometry": {"coordinates":[-117.522768,33.868955],"type":"Point"}
}