{
  "type": "Feature",
  "properties": {
    "iso:country":"US",
    "sg:address":"2771 S Western Ave",
    "sg:city":"Los Angeles",
    "sg:classifiers":[
        {
            "category":"Shopping",
            "type":"Retail Goods"
        }
    ],
    "sg:phone":"+1 323 766 8009",
    "sg:postcode":"90018",
    "sg:province":"CA",
    "sg:tags":[
        "cosmetic",
        "perfume"
    ],
    "wof:name":"Venus Beauty Supply & Nail",
    "wof:placetype":"venue"
},
  "geometry": {"coordinates":[-118.309012,34.030601],"type":"Point"}
}