{
  "type": "Feature",
  "properties": {
    "iso:country":"US",
    "sg:address":"1156 High St",
    "sg:city":"Santa Cruz",
    "sg:classifiers":[
        {
            "category":"Health Services",
            "subcategory":"Clinic",
            "type":"Services"
        }
    ],
    "sg:phone":"+1 831 495 2211",
    "sg:postcode":"95064",
    "sg:province":"CA",
    "sg:tags":[
        "medical"
    ],
    "sg:website":"www2.ucsc.edu/healthcenter/servi...",
    "wof:name":"UCSC Health Center Pharmacy",
    "wof:placetype":"venue"
},
  "geometry": {"coordinates":[-122.053664,36.977285],"type":"Point"}
}