{
  "type": "Feature",
  "properties": {
    "addr:full":"9278 Stillwater Rd Redding CA 96002",
    "addr:housenumber":"9278",
    "addr:postcode":"96002",
    "addr:street":"Stillwater Rd",
    "iso:country":"US",
    "sg:address":"9278 Stillwater Rd",
    "sg:city":"Redding",
    "sg:classifiers":[
        {
            "category":"Building & Trades",
            "subcategory":"Landscaping Services",
            "type":"Services"
        }
    ],
    "sg:phone":"+1 530 223 0874",
    "sg:postcode":"96002",
    "sg:province":"CA",
    "sg:tags":[
        "landscape",
        "contractor"
    ],
    "wof:name":"Godman's Landscaping",
    "wof:placetype":"venue"
},
  "geometry": {"coordinates":[-122.27669899999999,40.552944],"type":"Point"}
}