{
  "type": "Feature",
  "properties": {
    "iso:country":"US",
    "sg:address":"3313 Ocean Park Blvd",
    "sg:city":"Santa Monica",
    "sg:classifiers":[
        {
            "category":"Professional",
            "type":"Services"
        }
    ],
    "sg:phone":"+1 310 399 1928",
    "sg:postcode":"90405",
    "sg:province":"CA",
    "sg:website":"www.posthastesound.com",
    "wof:name":"Post Haste Sound",
    "wof:placetype":"venue"
},
  "geometry": {"coordinates":[-118.450012,34.022221],"type":"Point"}
}