{
  "type": "Feature",
  "properties": {
    "addr:full":"21060 Alexander Ct Hayward CA 94545",
    "addr:housenumber":"21060",
    "addr:postcode":"94545",
    "addr:street":"Alexander Ct",
    "iso:country":"US",
    "sg:address":"21060 Alexander Ct",
    "sg:city":"Hayward",
    "sg:classifiers":[
        {
            "category":"Wholesale",
            "subcategory":"Electrical",
            "type":"Manufacturing & Wholesale Goods"
        }
    ],
    "sg:phone":"+1 510 786 6190",
    "sg:postcode":"94545",
    "sg:province":"CA",
    "sg:tags":[
        "equipment",
        "fixture",
        "lighting"
    ],
    "sg:website":"www.firstlightsystems.com",
    "wof:name":"First Light Lighting Systems",
    "wof:placetype":"venue"
},
  "geometry": {"coordinates":[-122.13099699999999,37.651901],"type":"Point"}
}