{
  "type": "Feature",
  "properties": {
    "addr:full":"12383 10th St Yucaipa CA 92399",
    "addr:housenumber":"12383",
    "addr:postcode":"92399",
    "addr:street":"10Th St",
    "iso:country":"US",
    "sg:address":"12383 10th St",
    "sg:city":"Yucaipa",
    "sg:classifiers":[
        {
            "category":"Shopping",
            "subcategory":"Catalog Store",
            "type":"Retail Goods"
        }
    ],
    "sg:phone":"+1 909 797 7478",
    "sg:postcode":"92399",
    "sg:province":"CA",
    "sg:tags":[
        "mail",
        "order"
    ],
    "wof:name":"Gift Box",
    "wof:placetype":"venue"
},
  "geometry": {"coordinates":[-117.077628,34.030085],"type":"Point"}
}