{
  "type": "Feature",
  "properties": {
    "addr:full":"1231 Academy Ave Sanger CA 93657",
    "addr:housenumber":"1231",
    "addr:postcode":"ca 93657",
    "addr:street":"Academy Ave",
    "iso:country":"US",
    "sg:address":"1231 Academy Ave",
    "sg:city":"Sanger",
    "sg:classifiers":[
        {
            "category":"Wholesale",
            "subcategory":"Machinery & Supplies",
            "type":"Manufacturing & Wholesale Goods"
        }
    ],
    "sg:phone":"+1 559 875 3616",
    "sg:postcode":"93657",
    "sg:province":"CA",
    "sg:tags":[
        "equipment",
        "establishment"
    ],
    "wof:name":"Academy Upholstery",
    "wof:placetype":"venue"
},
  "geometry": {"coordinates":[-119.554226,36.697972],"type":"Point"}
}