{
  "type": "Feature",
  "properties": {
    "iso:country":"US",
    "sg:address":"1910 Cypress Ave",
    "sg:city":"Los Angeles",
    "sg:classifiers":[
        {
            "category":"Restaurant",
            "type":"Food & Drink"
        }
    ],
    "sg:phone":"+1 323 225 4913",
    "sg:postcode":"90065",
    "sg:province":"CA",
    "sg:tags":[
        "mexican"
    ],
    "wof:name":"La Paloma Restaurant",
    "wof:placetype":"venue"
},
  "geometry": {"coordinates":[-118.235096,34.100918],"type":"Point"}
}