{
  "type": "Feature",
  "properties": {
    "iso:country":"US",
    "sg:address":"2231 Fortune Dr",
    "sg:city":"San Jose",
    "sg:classifiers":[
        {
            "category":"Building & Trades",
            "subcategory":"Plumbing",
            "type":"Services"
        }
    ],
    "sg:phone":"+1 408 433 2211",
    "sg:postcode":"95131",
    "sg:province":"CA",
    "sg:tags":[
        "contractor"
    ],
    "wof:name":"Airseco Mechanical Inc",
    "wof:placetype":"venue"
},
  "geometry": {"coordinates":[-121.888026,37.401011],"type":"Point"}
}