{
  "type": "Feature",
  "properties": {
    "addr:full":"1720 E St Napa CA 94559",
    "addr:housenumber":"1720",
    "addr:postcode":"94559",
    "addr:street":"E St",
    "iso:country":"US",
    "sg:address":"1720 E St",
    "sg:city":"Napa",
    "sg:classifiers":[
        {
            "category":"Real Estate",
            "subcategory":"Real Estate Operator",
            "type":"Services"
        }
    ],
    "sg:phone":"+1 707 265 9554",
    "sg:postcode":"94559",
    "sg:province":"CA",
    "sg:tags":[
        "apartment"
    ],
    "wof:name":"1720 E St Apartments",
    "wof:placetype":"venue"
},
  "geometry": {"coordinates":[-122.29983,38.303697],"type":"Point"}
}