{
  "type": "Feature",
  "properties": {
    "addr:full":"9495 Main St Upper Lake CA 95485",
    "addr:housenumber":"9495",
    "addr:postcode":"95485",
    "addr:street":"Main St",
    "iso:country":"US",
    "sg:address":"9495 Main St",
    "sg:city":"Upper Lake",
    "sg:classifiers":[
        {
            "category":"Shopping",
            "subcategory":"Used Merchandise",
            "type":"Retail Goods"
        }
    ],
    "sg:phone":"+1 707 275 2556",
    "sg:postcode":"95485",
    "sg:province":"CA",
    "sg:tags":[
        "antique"
    ],
    "wof:name":"Dakota Crawford Mercantile",
    "wof:placetype":"venue"
},
  "geometry": {"coordinates":[-122.91127899999999,39.163071],"type":"Point"}
}