{
  "type": "Feature",
  "properties": {
    "addr:full":"3511 Renfro Rd Bakersfield CA 93314",
    "addr:housenumber":"3511",
    "addr:postcode":"93314",
    "addr:street":"Renfro Rd",
    "iso:country":"US",
    "sg:address":"3511 Renfro Rd",
    "sg:city":"Bakersfield",
    "sg:classifiers":[
        {
            "category":"Professional",
            "type":"Services"
        }
    ],
    "sg:phone":"+1 661 589 9008",
    "sg:postcode":"93314",
    "sg:province":"CA",
    "wof:name":"Yesterday & Today",
    "wof:placetype":"venue"
},
  "geometry": {"coordinates":[-119.163211,35.390243],"type":"Point"}
}