{
  "type": "Feature",
  "properties": {
    "iso:country":"US",
    "sg:address":"3 Harbor Dr",
    "sg:city":"Sausalito",
    "sg:classifiers":[
        {
            "category":"Education",
            "subcategory":"University",
            "type":"Public Place"
        }
    ],
    "sg:phone":"+1 415 289 1122",
    "sg:postcode":"94965",
    "sg:province":"CA",
    "sg:tags":[
        "meditation",
        "instruction"
    ],
    "wof:name":"Transcendental Meditation",
    "wof:placetype":"venue"
},
  "geometry": {"coordinates":[-122.500512,37.867135],"type":"Point"}
}