{
  "type": "Feature",
  "properties": {
    "iso:country":"US",
    "sg:address":"1830 Palmetto Ave",
    "sg:city":"Pacifica",
    "sg:classifiers":[
        {
            "category":"Professional",
            "subcategory":"Business Services",
            "type":"Services"
        }
    ],
    "sg:phone":"+1 650 359 2412",
    "sg:postcode":"94044",
    "sg:province":"CA",
    "sg:tags":[
        "repossessing"
    ],
    "wof:name":"Bay Area Remarketing",
    "wof:placetype":"venue"
},
  "geometry": {"coordinates":[-122.492091,37.634829],"type":"Point"}
}