{
  "type": "Feature",
  "properties": {
    "addr:full":"1415 N Raymond Ave Anaheim CA 92801",
    "addr:housenumber":"1415",
    "addr:postcode":"92801",
    "addr:street":"N Raymond Ave",
    "iso:country":"US",
    "sg:address":"1415 N Raymond Ave",
    "sg:city":"Anaheim",
    "sg:classifiers":[
        {
            "category":"Wholesale",
            "subcategory":"Dairy",
            "type":"Manufacturing & Wholesale Goods"
        }
    ],
    "sg:phone":"+1 714 871 9508",
    "sg:postcode":"92801",
    "sg:province":"CA",
    "sg:tags":[
        "product"
    ],
    "wof:name":"Saputo Cheese Usa Inc",
    "wof:placetype":"venue"
},
  "geometry": {"coordinates":[-117.90672000000001,33.854569],"type":"Point"}
}