{
  "type": "Feature",
  "properties": {
    "iso:country":"US",
    "sg:address":"3370 N San Fernando Rd Ste 103",
    "sg:city":"Los Angeles",
    "sg:classifiers":[
        {
            "category":"Arts & Performance",
            "subcategory":"Art Gallery",
            "type":"Entertainment"
        },
        {
            "category":"Professional",
            "subcategory":"Art Services",
            "type":"Services"
        }
    ],
    "sg:phone":"+1 323 344 9401",
    "sg:postcode":"90065",
    "sg:province":"CA",
    "sg:tags":[
        "framing"
    ],
    "sg:website":"www.finishingconceptsinc.com",
    "wof:name":"Finishing Concepts",
    "wof:placetype":"venue"
},
  "geometry": {"coordinates":[-118.249881,34.118889],"type":"Point"}
}