{
  "type": "Feature",
  "properties": {
    "addr:full":"181 W Sierra Madre Blvd Sierra Madre CA 91024",
    "addr:housenumber":"181",
    "addr:postcode":"91024",
    "addr:street":"W Sierra Madre Blvd",
    "iso:country":"US",
    "sg:address":"181 W Sierra Madre Blvd",
    "sg:city":"Sierra Madre",
    "sg:classifiers":[
        {
            "category":"Restaurant",
            "type":"Food & Drink"
        }
    ],
    "sg:phone":"+1 626 355 6058",
    "sg:postcode":"91024",
    "sg:province":"CA",
    "sg:tags":[
        "pizza"
    ],
    "wof:name":"Sierra Madre Pizza Company",
    "wof:placetype":"venue"
},
  "geometry": {"coordinates":[-118.05626700000001,34.161843],"type":"Point"}
}