{
  "type": "Feature",
  "properties": {
    "iso:country":"US",
    "sg:address":"181 W Sierra Madre Blvd",
    "sg:city":"Sierra Madre",
    "sg:classifiers":[
        {
            "category":"Restaurant",
            "type":"Food & Drink"
        }
    ],
    "sg:phone":"+1 626 355 6058",
    "sg:postcode":"91024",
    "sg:province":"CA",
    "sg:tags":[
        "pizza"
    ],
    "wof:name":"Sierra Madre Pizza Company",
    "wof:placetype":"venue"
},
  "geometry": {"coordinates":[-118.056267,34.161843],"type":"Point"}
}