{
  "type": "Feature",
  "properties": {
    "addr:full":"27951 Crown Valley Pkwy Laguna Niguel CA 92677",
    "addr:housenumber":"27951",
    "addr:postcode":"92677",
    "addr:street":"Crown Valley Pkwy",
    "iso:country":"US",
    "sg:address":"27951 Crown Valley Pkwy",
    "sg:city":"Laguna Niguel",
    "sg:classifiers":[
        {
            "category":"Education",
            "subcategory":"Special Training",
            "type":"Public Place"
        }
    ],
    "sg:phone":"+1 949 495 2919",
    "sg:postcode":"92677",
    "sg:province":"CA",
    "sg:tags":[
        "center"
    ],
    "wof:name":"Orange Coast Water Shed Ctr",
    "wof:placetype":"venue"
},
  "geometry": {"coordinates":[-117.686538,33.552893],"type":"Point"}
}