{
  "type": "Feature",
  "properties": {
    "iso:country":"US",
    "sg:address":"8715 Boston Pl",
    "sg:city":"Rancho Cucamonga",
    "sg:classifiers":[
        {
            "category":"Professional",
            "subcategory":"Business Services",
            "type":"Services"
        }
    ],
    "sg:phone":"+1 714 956 3050",
    "sg:postcode":"91730",
    "sg:province":"CA",
    "sg:tags":[
        "packaging"
    ],
    "wof:name":"Acr Har-Pak Co",
    "wof:placetype":"venue"
},
  "geometry": {"coordinates":[-117.550004,34.093851],"type":"Point"}
}