{
  "type": "Feature",
  "properties": {
    "addr:full":"14720 S San Pedro Street Gardena CA 90248",
    "addr:housenumber":"14720",
    "addr:postcode":"90248",
    "addr:street":"S San Pedro Street",
    "iso:country":"US",
    "sg:address":"14720 S San Pedro Street",
    "sg:city":"Gardena",
    "sg:classifiers":[
        {
            "category":"Food & Beverages",
            "subcategory":"Cheese",
            "type":"Retail Goods"
        }
    ],
    "sg:phone":"+1 310 366 7903",
    "sg:postcode":"90248",
    "sg:province":"CA",
    "sg:tags":[
        "shop"
    ],
    "wof:name":"Don Francisco Food",
    "wof:placetype":"venue"
},
  "geometry": {"coordinates":[-118.268253,33.89832],"type":"Point"}
}