{
  "type": "Feature",
  "properties": {
    "iso:country":"US",
    "sg:address":"420 Boyd St",
    "sg:city":"Los Angeles",
    "sg:classifiers":[
        {
            "category":"Real Estate",
            "subcategory":"Architect",
            "type":"Services"
        }
    ],
    "sg:phone":"+1 213 613 1922",
    "sg:postcode":"90013",
    "sg:province":"CA",
    "wof:name":"Kritzinger & Rao",
    "wof:placetype":"venue"
},
  "geometry": {"coordinates":[-118.241909,34.046056],"type":"Point"}
}