{
  "type": "Feature",
  "properties": {
    "addr:full":"980 S Western Ave Los Angeles CA 90006",
    "addr:housenumber":"980",
    "addr:postcode":"90006",
    "addr:street":"S Western Ave",
    "iso:country":"US",
    "sg:address":"980 S Western Ave",
    "sg:city":"Los Angeles",
    "sg:classifiers":[
        {
            "category":"Food & Beverages",
            "subcategory":"Groceries & Convenience Stores",
            "type":"Retail Goods"
        }
    ],
    "sg:phone":"+1 323 733 8926",
    "sg:postcode":"90006",
    "sg:province":"CA",
    "sg:tags":[
        "grocer"
    ],
    "wof:name":"J P Market",
    "wof:placetype":"venue"
},
  "geometry": {"coordinates":[-118.30897899999999,34.052861],"type":"Point"}
}