{
  "type": "Feature",
  "properties": {
    "iso:country":"US",
    "sg:address":"980 S Western Ave",
    "sg:city":"Los Angeles",
    "sg:classifiers":[
        {
            "category":"Food & Beverages",
            "subcategory":"Groceries & Convenience Stores",
            "type":"Retail Goods"
        }
    ],
    "sg:phone":"+1 323 733 8926",
    "sg:postcode":"90006",
    "sg:province":"CA",
    "sg:tags":[
        "grocer"
    ],
    "wof:name":"J P Market",
    "wof:placetype":"venue"
},
  "geometry": {"coordinates":[-118.308979,34.052861],"type":"Point"}
}