{
  "type": "Feature",
  "properties": {
    "iso:country":"US",
    "sg:address":"1111 Broadway",
    "sg:city":"Chula Vista",
    "sg:classifiers":[
        {
            "category":"Banks & Credit Unions",
            "subcategory":"Bank",
            "type":"Services"
        }
    ],
    "sg:phone":"+1 619 585 0303",
    "sg:postcode":"91911",
    "sg:province":"CA",
    "sg:tags":[
        "cashing",
        "check"
    ],
    "wof:name":"Check Depot",
    "wof:placetype":"venue"
},
  "geometry": {"coordinates":[-117.080046,32.607197],"type":"Point"}
}