{
  "type": "Feature",
  "properties": {
    "iso:country":"US",
    "sg:address":"1939 Addison St",
    "sg:city":"Berkeley",
    "sg:classifiers":[
        {
            "category":"Organizations",
            "subcategory":"Non-profit Organization",
            "type":"Services"
        }
    ],
    "sg:phone":"+1 510 843 3699",
    "sg:postcode":"94704",
    "sg:province":"CA",
    "sg:tags":[
        "service/non-profit",
        "community"
    ],
    "sg:website":"www.eastbaymediacenter.com/",
    "wof:name":"East Bay Media Center",
    "wof:placetype":"venue"
},
  "geometry": {"coordinates":[-122.271146,37.871062],"type":"Point"}
}