{
  "type": "Feature",
  "properties": {
    "addr:full":"2238 S Sepulveda Blvd Los Angeles CA 90064",
    "addr:housenumber":"2238",
    "addr:postcode":"90064",
    "addr:street":"S Sepulveda Blvd",
    "iso:country":"US",
    "sg:address":"2238 S Sepulveda Blvd",
    "sg:city":"Los Angeles",
    "sg:classifiers":[
        {
            "category":"Shopping",
            "subcategory":"Clothing, Apparel, & Fashions",
            "type":"Retail Goods"
        }
    ],
    "sg:phone":"+1 310 478 1593",
    "sg:postcode":"90064",
    "sg:province":"CA",
    "wof:name":"Azita J",
    "wof:placetype":"venue"
},
  "geometry": {"coordinates":[-118.436966,34.039332],"type":"Point"}
}