{
  "type": "Feature",
  "properties": {
    "addr:full":"10605 Tivoli Ct Bakersfield CA 93311",
    "addr:housenumber":"10605",
    "addr:postcode":"93311",
    "addr:street":"Tivoli Ct",
    "iso:country":"US",
    "sg:address":"10605 Tivoli Ct",
    "sg:city":"Bakersfield",
    "sg:classifiers":[
        {
            "category":"Building & Trades",
            "subcategory":"Plumbing",
            "type":"Services"
        }
    ],
    "sg:phone":"+1 661 665 9849",
    "sg:postcode":"93311",
    "sg:province":"CA",
    "sg:tags":[
        "contractor"
    ],
    "wof:name":"Stumbo AC Heating",
    "wof:placetype":"venue"
},
  "geometry": {"coordinates":[-119.11953699999999,35.324588],"type":"Point"}
}