{
  "type": "Feature",
  "properties": {
    "iso:country":"US",
    "sg:address":"4117 Rosedale Hwy",
    "sg:city":"Bakersfield",
    "sg:classifiers":[
        {
            "category":"Building & Trades",
            "subcategory":"Equipment Rental",
            "type":"Services"
        }
    ],
    "sg:phone":"+1 661 631 8800",
    "sg:postcode":"93308",
    "sg:province":"CA",
    "sg:tags":[
        "contractor"
    ],
    "sg:website":"www.rentalservice.com",
    "wof:name":"Rental Service Corp",
    "wof:placetype":"venue"
},
  "geometry": {"coordinates":[-119.054214,35.38336],"type":"Point"}
}