{
  "type": "Feature",
  "properties": {
    "iso:country":"US",
    "sg:address":"12917 Hawthorne Blvd",
    "sg:city":"Hawthorne",
    "sg:classifiers":[
        {
            "category":"Personal",
            "subcategory":"Beauty Salon",
            "type":"Services"
        }
    ],
    "sg:phone":"+1 310 219 4044",
    "sg:postcode":"90250",
    "sg:province":"CA",
    "sg:tags":[
        "spa",
        "day"
    ],
    "wof:name":"Heavenly Body Skin Care & Day",
    "wof:placetype":"venue"
},
  "geometry": {"coordinates":[-118.352462,33.914615],"type":"Point"}
}