{
  "type": "Feature",
  "properties": {
    "addr:full":"374 Shannon Way Windsor CA 95492",
    "addr:housenumber":"374",
    "addr:postcode":"95492",
    "addr:street":"Shannon Way",
    "iso:country":"US",
    "sg:address":"374 Shannon Way",
    "sg:city":"Windsor",
    "sg:classifiers":[
        {
            "category":"Building & Trades",
            "subcategory":"Construction",
            "type":"Services"
        }
    ],
    "sg:phone":"+1 707 838 9145",
    "sg:postcode":"95492",
    "sg:province":"CA",
    "sg:tags":[
        "house"
    ],
    "wof:name":"R Oroszi & Son",
    "wof:placetype":"venue"
},
  "geometry": {"coordinates":[-122.796716,38.537273],"type":"Point"}
}