{
  "type": "Feature",
  "properties": {
    "addr:full":"2790 Story Rd San Jose CA 95127",
    "addr:housenumber":"2790",
    "addr:postcode":"95127",
    "addr:street":"Story Rd",
    "iso:country":"US",
    "sg:address":"2790 Story Rd",
    "sg:city":"San Jose",
    "sg:classifiers":[
        {
            "category":"Autos & Motor Vehicles",
            "subcategory":"Fuel & Gas Station",
            "type":"Retail Goods"
        }
    ],
    "sg:phone":"+1 408 259 7070",
    "sg:postcode":"95127",
    "sg:province":"CA",
    "wof:name":"USA Petroleum Corp",
    "wof:placetype":"venue"
},
  "geometry": {"coordinates":[-121.82399700000001,37.352299],"type":"Point"}
}