{
  "type": "Feature",
  "properties": {
    "iso:country":"US",
    "sg:address":"1155 S De Anza Blvd",
    "sg:city":"San Jose",
    "sg:classifiers":[
        {
            "category":"Education",
            "subcategory":"Special Training",
            "type":"Public Place"
        }
    ],
    "sg:phone":"+1 408 343 3919",
    "sg:postcode":"95129",
    "sg:province":"CA",
    "sg:tags":[
        "school",
        "art"
    ],
    "sg:website":"www.chineseclayart.com/mall/c110...",
    "wof:name":"The Clayground",
    "wof:placetype":"venue"
},
  "geometry": {"coordinates":[-122.032374,37.303757],"type":"Point"}
}