{
  "type": "Feature",
  "properties": {
    "addr:full":"421 E Valley Blvd San Gabriel CA 91776",
    "addr:housenumber":"421",
    "addr:postcode":"91776",
    "addr:street":"E Valley Blvd",
    "iso:country":"US",
    "sg:address":"421 E Valley Blvd",
    "sg:city":"San Gabriel",
    "sg:classifiers":[
        {
            "category":"Professional",
            "subcategory":"Management & Consulting",
            "type":"Services"
        }
    ],
    "sg:phone":"+1 626 288 4833",
    "sg:postcode":"91776",
    "sg:province":"CA",
    "sg:tags":[
        "water",
        "purification"
    ],
    "wof:name":"MCS Water Purfication Corp",
    "wof:placetype":"venue"
},
  "geometry": {"coordinates":[-118.094892,34.080034],"type":"Point"}
}