{
  "type": "Feature",
  "properties": {
    "iso:country":"US",
    "sg:address":"285 E Main St",
    "sg:city":"Los Gatos",
    "sg:classifiers":[
        {
            "category":"Personal",
            "subcategory":"Massage",
            "type":"Services"
        }
    ],
    "sg:phone":"+1 408 887 7107",
    "sg:postcode":"95030",
    "sg:province":"CA",
    "sg:website":"www.healingthroughtouchmassage.com",
    "wof:name":"Healing Through Touch Massage",
    "wof:placetype":"venue"
},
  "geometry": {"coordinates":[-121.97468000000001,37.226611],"type":"Point"}
}