{
  "type": "Feature",
  "properties": {
    "iso:country":"US",
    "sg:address":"3965 Lindsay Ln",
    "sg:city":"Castro Valley",
    "sg:classifiers":[
        {
            "category":"Home & Garden",
            "subcategory":"Garden Supply",
            "type":"Retail Goods"
        }
    ],
    "sg:phone":"+1 510 537 7822",
    "sg:postcode":"94546",
    "sg:province":"CA",
    "sg:tags":[
        "center"
    ],
    "wof:name":"Kamurascape Techniques",
    "wof:placetype":"venue"
},
  "geometry": {"coordinates":[-122.091,37.71752],"type":"Point"}
}