{
  "type": "Feature",
  "properties": {
    "iso:country":"US",
    "sg:address":"4433 Exchange Ave",
    "sg:city":"Vernon",
    "sg:classifiers":[
        {
            "category":"Railroad",
            "type":"Transportation"
        }
    ],
    "sg:phone":"+1 323 277 2013",
    "sg:postcode":"90058",
    "sg:province":"CA",
    "wof:name":"L A Junction Railway",
    "wof:placetype":"venue"
},
  "geometry": {"coordinates":[-118.198694,34.001962],"type":"Point"}
}