{
  "type": "Feature",
  "properties": {
    "addr:full":"10306 Arlington Ave Riverside CA 92505",
    "addr:housenumber":"10306",
    "addr:postcode":"92505",
    "addr:street":"Arlington Ave",
    "iso:country":"US",
    "sg:address":"10306 Arlington Ave",
    "sg:city":"Riverside",
    "sg:classifiers":[
        {
            "category":"Food & Beverages",
            "subcategory":"Groceries & Convenience Stores",
            "type":"Retail Goods"
        }
    ],
    "sg:phone":"+1 951 352 7441",
    "sg:postcode":"92505",
    "sg:province":"CA",
    "wof:name":"Fastrip Food Store",
    "wof:placetype":"venue"
},
  "geometry": {"coordinates":[-117.480469,33.946563],"type":"Point"}
}