{
  "type": "Feature",
  "properties": {
    "iso:country":"US",
    "sg:address":"5677 Oberlin Dr",
    "sg:city":"San Diego",
    "sg:classifiers":[
        {
            "category":"Professional",
            "subcategory":"Lawyer & Legal Services",
            "type":"Services"
        }
    ],
    "sg:phone":"+1 858 824 9404",
    "sg:postcode":"92121",
    "sg:province":"CA",
    "sg:tags":[
        "attorney"
    ],
    "wof:name":"Kristin Young Law Office",
    "wof:placetype":"venue"
},
  "geometry": {"coordinates":[-117.200728,32.891486],"type":"Point"}
}