{
  "type": "Feature",
  "properties": {
    "addr:full":"4650 Badger Rd Santa Rosa CA 95409",
    "addr:housenumber":"4650",
    "addr:postcode":"95409",
    "addr:street":"Badger Rd",
    "iso:country":"US",
    "sg:address":"4650 Badger Rd",
    "sg:city":"Santa Rosa",
    "sg:classifiers":[
        {
            "category":"Building & Trades",
            "subcategory":"Construction",
            "type":"Services"
        }
    ],
    "sg:phone":"+1 707 537 9318",
    "sg:postcode":"95409",
    "sg:province":"CA",
    "sg:tags":[
        "contractor"
    ],
    "wof:name":"Ridgeview Builders",
    "wof:placetype":"venue"
},
  "geometry": {"coordinates":[-122.670224,38.482196],"type":"Point"}
}