{
  "type": "Feature",
  "properties": {
    "iso:country":"US",
    "sg:address":"7718 Greenleaf Ave",
    "sg:city":"Whittier",
    "sg:classifiers":[
        {
            "category":"Professional",
            "subcategory":"Business Services",
            "type":"Services"
        }
    ],
    "sg:phone":"+1 562 696 7841",
    "sg:postcode":"90602",
    "sg:province":"CA",
    "sg:tags":[
        "inspection"
    ],
    "wof:name":"Uptown Smog Test Only",
    "wof:placetype":"venue"
},
  "geometry": {"coordinates":[-118.037399,33.971591],"type":"Point"}
}