{
  "type": "Feature",
  "properties": {
    "addr:full":"9939 San Fernando Rd Pacoima CA 91331",
    "addr:housenumber":"9939",
    "addr:postcode":"91331",
    "addr:street":"San Fernando Rd",
    "iso:country":"US",
    "sg:address":"9939 San Fernando Rd",
    "sg:city":"Pacoima",
    "sg:classifiers":[
        {
            "category":"Building & Trades",
            "subcategory":"Construction",
            "type":"Services"
        }
    ],
    "sg:phone":"+1 818 890 1709",
    "sg:postcode":"91331",
    "sg:province":"CA",
    "sg:tags":[
        "carpentry",
        "contractor"
    ],
    "wof:name":"Best Valley Cabinetry",
    "wof:placetype":"venue"
},
  "geometry": {"coordinates":[-118.405061,34.249969],"type":"Point"}
}