{
  "type": "Feature",
  "properties": {
    "iso:country":"US",
    "sg:address":"11285 Vallejo Ct",
    "sg:city":"French Camp",
    "sg:classifiers":[
        {
            "category":"Building & Trades",
            "subcategory":"Equipment Rental",
            "type":"Services"
        }
    ],
    "sg:phone":"+1 209 982 9670",
    "sg:postcode":"95231",
    "sg:province":"CA",
    "sg:tags":[
        "yard"
    ],
    "wof:name":"Hertz Equipment Rental",
    "wof:placetype":"venue"
},
  "geometry": {"coordinates":[-121.270902,37.855711],"type":"Point"}
}