{
  "type": "Feature",
  "properties": {
    "addr:full":"2270 Martin Avenue Santa Clara CA 95050",
    "addr:housenumber":"2270",
    "addr:postcode":"95050",
    "addr:street":"Martin Avenue",
    "iso:country":"US",
    "sg:address":"2270 Martin Avenue",
    "sg:city":"Santa Clara",
    "sg:classifiers":[
        {
            "category":"Personal",
            "type":"Services"
        }
    ],
    "sg:phone":"+1 408 727 2121",
    "sg:postcode":"95050",
    "sg:province":"CA",
    "sg:tags":[
        "mover"
    ],
    "wof:name":"Advanced Analog",
    "wof:placetype":"venue"
},
  "geometry": {"coordinates":[-121.96327700000001,37.368193],"type":"Point"}
}