{
  "type": "Feature",
  "properties": {
    "iso:country":"US",
    "sg:address":"1890 7th Ave",
    "sg:city":"Olivehurst",
    "sg:classifiers":[
        {
            "category":"Food & Beverages",
            "subcategory":"Meat & Fish",
            "type":"Retail Goods"
        }
    ],
    "sg:phone":"+1 530 741 8553",
    "sg:postcode":"95961",
    "sg:province":"CA",
    "wof:name":"Art's Family Meats",
    "wof:placetype":"venue"
},
  "geometry": {"coordinates":[-121.543568,39.095009],"type":"Point"}
}