{
  "type": "Feature",
  "properties": {
    "addr:full":"3055 S Archibald Ave Ontario CA 91761",
    "addr:housenumber":"3055",
    "addr:postcode":"91761",
    "addr:street":"S Archibald Ave",
    "iso:country":"US",
    "sg:address":"3055 S Archibald Ave",
    "sg:city":"Ontario",
    "sg:classifiers":[
        {
            "category":"Shopping",
            "subcategory":"Department Store",
            "type":"Retail Goods"
        }
    ],
    "sg:phone":"+1 909 673 9000",
    "sg:postcode":"91761",
    "sg:province":"CA",
    "sg:tags":[
        "shop"
    ],
    "wof:name":"99 Cent Super Store",
    "wof:placetype":"venue"
},
  "geometry": {"coordinates":[-117.593102,34.017486],"type":"Point"}
}