{
  "type": "Feature",
  "properties": {
    "iso:country":"US",
    "sg:address":"12537 Cerise Ave",
    "sg:city":"Hawthorne",
    "sg:classifiers":[
        {
            "category":"Manufacturing",
            "subcategory":"Textiles",
            "type":"Manufacturing & Wholesale Goods"
        }
    ],
    "sg:phone":"+1 310 644 4001",
    "sg:postcode":"90250",
    "sg:province":"CA",
    "sg:tags":[
        "weft",
        "fiber",
        "fabric",
        "mill",
        "silk",
        "knit",
        "finishing",
        "pl"
    ],
    "wof:name":"Eng Textiles",
    "wof:placetype":"venue"
},
  "geometry": {"coordinates":[-118.332381,33.916901],"type":"Point"}
}