{
  "type": "Feature",
  "properties": {
    "addr:full":"509 N Sepulveda Blvd Manhattan Beach CA 90266",
    "addr:housenumber":"509",
    "addr:postcode":"90266",
    "addr:street":"N Sepulveda Blvd",
    "iso:country":"US",
    "sg:address":"509 N Sepulveda Blvd",
    "sg:city":"Manhattan Beach",
    "sg:classifiers":[
        {
            "category":"Health Services",
            "subcategory":"Health Practitioner",
            "type":"Services"
        }
    ],
    "sg:phone":"+1 310 939 9002",
    "sg:postcode":"90266",
    "sg:province":"CA",
    "sg:tags":[
        "psychologist"
    ],
    "wof:name":"Mark Michaels PHD",
    "wof:placetype":"venue"
},
  "geometry": {"coordinates":[-118.396052,33.882598],"type":"Point"}
}