{
  "type": "Feature",
  "properties": {
    "iso:country":"US",
    "sg:address":"2520 Hyperion Ave",
    "sg:city":"Los Angeles",
    "sg:classifiers":[
        {
            "category":"Fast Food",
            "type":"Food & Drink"
        },
        {
            "category":"Restaurant",
            "type":"Food & Drink"
        }
    ],
    "sg:phone":"+1 323 661 8494",
    "sg:postcode":"90027",
    "sg:province":"CA",
    "sg:tags":[
        "burger",
        "american",
        "new"
    ],
    "sg:website":"www.thefixburger.com",
    "wof:name":"The Fix Burger",
    "wof:placetype":"venue"
},
  "geometry": {"coordinates":[-118.27287,34.104759],"type":"Point"}
}