{
  "type": "Feature",
  "properties": {
    "addr:full":"1609 N King St Santa Ana CA 92706",
    "addr:housenumber":"1609",
    "addr:postcode":"92706",
    "addr:street":"N King St",
    "iso:country":"US",
    "sg:address":"1609 N King St",
    "sg:city":"Santa Ana",
    "sg:classifiers":[
        {
            "category":"Government",
            "subcategory":"Post Office",
            "type":"Public Place"
        }
    ],
    "sg:phone":"+1 714 835 3098",
    "sg:postcode":"92706",
    "sg:province":"CA",
    "sg:website":"www.usps.com/",
    "wof:name":"United States Post Office",
    "wof:placetype":"venue"
},
  "geometry": {"coordinates":[-117.898009,33.759515],"type":"Point"}
}