{
  "type": "Feature",
  "properties": {
    "addr:full":"14 Pamaron Way Novato CA 94949",
    "addr:housenumber":"14",
    "addr:postcode":"94949",
    "addr:street":"Pamaron Way",
    "iso:country":"US",
    "sg:address":"14 Pamaron Way",
    "sg:city":"Novato",
    "sg:classifiers":[
        {
            "category":"Manufacturing",
            "subcategory":"Printing",
            "type":"Manufacturing & Wholesale Goods"
        }
    ],
    "sg:phone":"+1 415 884 2100",
    "sg:postcode":"94949",
    "sg:province":"CA",
    "sg:tags":[
        "publisher"
    ],
    "sg:website":"www.nwlib.com",
    "wof:name":"New World Library",
    "wof:placetype":"venue"
},
  "geometry": {"coordinates":[-122.530941,38.065958],"type":"Point"}
}