{
  "type": "Feature",
  "properties": {
    "iso:country":"US",
    "sg:address":"345 W 131st St",
    "sg:city":"Los Angeles",
    "sg:classifiers":[
        {
            "category":"Manufacturing",
            "subcategory":"Metals",
            "type":"Manufacturing & Wholesale Goods"
        }
    ],
    "sg:phone":"+1 310 538 4352",
    "sg:postcode":"90061",
    "sg:province":"CA",
    "sg:tags":[
        "production",
        "grinding"
    ],
    "wof:name":"Specialty Surface Grinding Co",
    "wof:placetype":"venue"
},
  "geometry": {"coordinates":[-118.27987899999999,33.913402],"type":"Point"}
}