{
  "type": "Feature",
  "properties": {
    "iso:country":"US",
    "sg:address":"620 N Gateway Dr",
    "sg:city":"Madera",
    "sg:classifiers":[
        {
            "category":"Restaurant",
            "type":"Food & Drink"
        }
    ],
    "sg:phone":"+1 559 673 5121",
    "sg:postcode":"93637",
    "sg:province":"CA",
    "wof:name":"Tea House Restaurant",
    "wof:placetype":"venue"
},
  "geometry": {"coordinates":[-120.06609899999999,36.966469],"type":"Point"}
}