{
  "type": "Feature",
  "properties": {
    "iso:country":"US",
    "sg:address":"1401 2nd St",
    "sg:city":"San Rafael",
    "sg:classifiers":[
        {
            "category":"Autos & Motor Vehicles",
            "subcategory":"Fuel & Gas Station",
            "type":"Retail Goods"
        }
    ],
    "sg:phone":"+1 415 456 9575",
    "sg:postcode":"94901",
    "sg:province":"CA",
    "sg:tags":[
        "oil"
    ],
    "wof:name":"Arco",
    "wof:placetype":"venue"
},
  "geometry": {"coordinates":[-122.533564,37.971676],"type":"Point"}
}