{
  "type": "Feature",
  "properties": {
    "addr:full":"4434 Pearl Avenue San Jose CA 95136",
    "addr:housenumber":"4434",
    "addr:postcode":"95136",
    "addr:street":"Pearl Avenue",
    "iso:country":"US",
    "sg:address":"4434 Pearl Avenue",
    "sg:city":"San Jose",
    "sg:classifiers":[
        {
            "category":"Banks & Credit Unions",
            "subcategory":"Financial Services",
            "type":"Services"
        }
    ],
    "sg:phone":"+1 408 448 4400",
    "sg:postcode":"95136",
    "sg:province":"CA",
    "sg:tags":[
        "broker",
        "mortgage"
    ],
    "wof:name":"Premier Real Estate & Mortgage Services",
    "wof:placetype":"venue"
},
  "geometry": {"coordinates":[-121.866624,37.266843],"type":"Point"}
}