{
  "type": "Feature",
  "properties": {
    "iso:country":"US",
    "sg:address":"7290 Mohawk St",
    "sg:city":"San Diego",
    "sg:classifiers":[
        {
            "category":"Professional",
            "type":"Services"
        }
    ],
    "sg:phone":"+1 619 461 4120",
    "sg:postcode":"92115",
    "sg:province":"CA",
    "wof:name":"Bumble Bee Pinatas",
    "wof:placetype":"venue"
},
  "geometry": {"coordinates":[-117.04177300000001,32.769938],"type":"Point"}
}