{
  "type": "Feature",
  "properties": {
    "iso:country":"US",
    "sg:address":"6830 Stockton Blvd Ste 140",
    "sg:city":"Sacramento",
    "sg:classifiers":[
        {
            "category":"Health Services",
            "subcategory":"Optometrist",
            "type":"Services"
        }
    ],
    "sg:phone":"+1 916 422 2020",
    "sg:postcode":"95823",
    "sg:province":"CA",
    "sg:website":"www.absolutefamilyeyecare.com/",
    "wof:name":"Absolute Family Eye Care",
    "wof:placetype":"venue"
},
  "geometry": {"coordinates":[-121.432417,38.5028],"type":"Point"}
}