{
  "type": "Feature",
  "properties": {
    "iso:country":"US",
    "sg:address":"2641 Elmdale Pl",
    "sg:city":"Palo Alto",
    "sg:classifiers":[
        {
            "category":"Professional",
            "subcategory":"Engineering",
            "type":"Services"
        }
    ],
    "sg:phone":"+1 650 493 7051",
    "sg:postcode":"94303",
    "sg:province":"CA",
    "sg:tags":[
        "engineer"
    ],
    "wof:name":"Systems Engineering Consultant",
    "wof:placetype":"venue"
},
  "geometry": {"coordinates":[-122.122574,37.44251],"type":"Point"}
}