{
  "type": "Feature",
  "properties": {
    "addr:full":"2186 Woodlawn Dr Rancho Cordova CA 95670",
    "addr:housenumber":"2186",
    "addr:postcode":"95670",
    "addr:street":"Woodlawn Dr",
    "iso:country":"US",
    "sg:address":"2186 Woodlawn Dr",
    "sg:city":"Rancho Cordova",
    "sg:classifiers":[
        {
            "category":"Personal",
            "subcategory":"Barber",
            "type":"Services"
        }
    ],
    "sg:phone":"+1 916 635 1311",
    "sg:postcode":"95670",
    "sg:province":"CA",
    "wof:name":"Cordova Hair Unlimited",
    "wof:placetype":"venue"
},
  "geometry": {"coordinates":[-121.28722,38.614846],"type":"Point"}
}