{
  "type": "Feature",
  "properties": {
    "addr:full":"15507 Parron Ave Gardena CA 90249",
    "addr:postcode":"15507;90249",
    "addr:street":"Parron Ave",
    "iso:country":"US",
    "sg:address":"15507 Parron Ave",
    "sg:city":"Gardena",
    "sg:classifiers":[
        {
            "category":"Shopping",
            "subcategory":"Clothing, Apparel, & Fashions",
            "type":"Retail Goods"
        }
    ],
    "sg:phone":"+1 310 324 6036",
    "sg:postcode":"90249",
    "sg:province":"CA",
    "sg:tags":[
        "family"
    ],
    "wof:name":"110 South Streetwear",
    "wof:placetype":"venue"
},
  "geometry": {"coordinates":[-118.31524,33.889843],"type":"Point"}
}