{
  "type": "Feature",
  "properties": {
    "iso:country":"US",
    "sg:address":"3330 Cameron Park Dr",
    "sg:city":"Cameron Park",
    "sg:classifiers":[
        {
            "category":"Real Estate",
            "subcategory":"Architect",
            "type":"Services"
        }
    ],
    "sg:phone":"+1 530 672 6070",
    "sg:postcode":"95682",
    "sg:province":"CA",
    "wof:name":"Govan Associates",
    "wof:placetype":"venue"
},
  "geometry": {"coordinates":[-120.98214299999999,38.680161],"type":"Point"}
}