{
  "type": "Feature",
  "properties": {
    "addr:full":"6902 Patterson Pass Rd Livermore CA 94550",
    "addr:housenumber":"6902",
    "addr:postcode":"94550",
    "addr:street":"Patterson Pass Rd",
    "iso:country":"US",
    "sg:address":"6902 Patterson Pass Rd",
    "sg:city":"Livermore",
    "sg:classifiers":[
        {
            "category":"Manufacturing",
            "subcategory":"Food",
            "type":"Manufacturing & Wholesale Goods"
        }
    ],
    "sg:phone":"+1 925 606 4370",
    "sg:postcode":"94550",
    "sg:province":"CA",
    "sg:tags":[
        "tea",
        "coffee",
        "product"
    ],
    "wof:name":"Virtues Of Coffee",
    "wof:placetype":"venue"
},
  "geometry": {"coordinates":[-121.704733,37.695863],"type":"Point"}
}