{
  "type": "Feature",
  "properties": {
    "iso:country":"US",
    "sg:address":"140 B St",
    "sg:city":"Davis",
    "sg:classifiers":[
        {
            "category":"Personal",
            "subcategory":"Tattoo Parlor",
            "type":"Services"
        }
    ],
    "sg:phone":"+1 530 792 8282",
    "sg:postcode":"95616",
    "sg:province":"CA",
    "sg:tags":[
        "tattooing"
    ],
    "wof:name":"Icon Tattoo",
    "wof:placetype":"venue"
},
  "geometry": {"coordinates":[-121.74423,38.542532],"type":"Point"}
}