{
  "type": "Feature",
  "properties": {
    "addr:full":"128 N Gateway Dr Madera CA 93637",
    "addr:housenumber":"128",
    "addr:postcode":"93637",
    "addr:street":"N Gateway Dr",
    "iso:country":"US",
    "sg:address":"128 N Gateway Dr",
    "sg:city":"Madera",
    "sg:classifiers":[
        {
            "category":"Real Estate",
            "subcategory":"Real Estate Agent",
            "type":"Services"
        }
    ],
    "sg:phone":"+1 559 674 0067",
    "sg:postcode":"93637",
    "sg:province":"CA",
    "sg:website":"www.donfloydrealty.com",
    "wof:name":"Don Floyd & Assoc",
    "wof:placetype":"venue"
},
  "geometry": {"coordinates":[-120.061297,36.961865],"type":"Point"}
}