{
  "type": "Feature",
  "properties": {
    "iso:country":"US",
    "sg:address":"9313 Christina Ln",
    "sg:city":"Lakeside",
    "sg:classifiers":[
        {
            "category":"Building & Trades",
            "subcategory":"Electrical",
            "type":"Services"
        }
    ],
    "sg:phone":"+1 619 561 9218",
    "sg:postcode":"92040",
    "sg:province":"CA",
    "sg:tags":[
        "electrician"
    ],
    "wof:name":"East County Electric",
    "wof:placetype":"venue"
},
  "geometry": {"coordinates":[-116.94086900000001,32.845242],"type":"Point"}
}