{
  "type": "Feature",
  "properties": {
    "addr:full":"1945 Alpine Blvd Alpine CA 91901",
    "addr:housenumber":"1945",
    "addr:postcode":"91901",
    "addr:street":"Alpine Blvd",
    "iso:country":"US",
    "sg:address":"1945 Alpine Blvd",
    "sg:city":"Alpine",
    "sg:classifiers":[
        {
            "category":"Restaurant",
            "type":"Food & Drink"
        }
    ],
    "sg:phone":"+1 619 445 6064",
    "sg:postcode":"91901",
    "sg:province":"CA",
    "sg:tags":[
        "tea",
        "rooms"
    ],
    "wof:name":"Cobblestone Cottage Tea Shoppe",
    "wof:placetype":"venue"
},
  "geometry": {"coordinates":[-116.767039,32.835417],"type":"Point"}
}