{
  "type": "Feature",
  "properties": {
    "iso:country":"US",
    "sg:address":"500 N St",
    "sg:city":"Sacramento",
    "sg:classifiers":[
        {
            "category":"Personal",
            "subcategory":"Beauty Salon",
            "type":"Services"
        }
    ],
    "sg:phone":"+1 916 446 9383",
    "sg:postcode":"95814",
    "sg:province":"CA",
    "wof:name":"About Scissors Hair & Nails",
    "wof:placetype":"venue"
},
  "geometry": {"coordinates":[-121.499374,38.57693],"type":"Point"}
}