{
  "type": "Feature",
  "properties": {
    "addr:full":"2050 Yulupa Ave Santa Rosa CA 95405",
    "addr:housenumber":"2050",
    "addr:postcode":"95405",
    "addr:street":"Yulupa Ave",
    "iso:country":"US",
    "sg:address":"2050 Yulupa Ave",
    "sg:city":"Santa Rosa",
    "sg:classifiers":[
        {
            "category":"Recreation",
            "type":"Entertainment"
        }
    ],
    "sg:phone":"+1 707 577 7334",
    "sg:postcode":"95405",
    "sg:province":"CA",
    "sg:tags":[
        "hall",
        "auditorium"
    ],
    "wof:name":"Luther Burbank Art & Garden",
    "wof:placetype":"venue"
},
  "geometry": {"coordinates":[-122.67035300000001,38.438124],"type":"Point"}
}