{
  "type": "Feature",
  "properties": {
    "iso:country":"US",
    "sg:address":"18300 Wilmington Ave",
    "sg:city":"Carson",
    "sg:classifiers":[
        {
            "category":"Shopping",
            "subcategory":"Stationery & Office Supplies",
            "type":"Retail Goods"
        }
    ],
    "sg:phone":"+1 310 768 8307",
    "sg:postcode":"90746",
    "sg:province":"CA",
    "sg:tags":[
        "room",
        "shipping"
    ],
    "wof:name":"Cargo Cargo Logistics Inc.",
    "wof:placetype":"venue"
},
  "geometry": {"coordinates":[-118.235486,33.864644],"type":"Point"}
}