{
  "type": "Feature",
  "properties": {
    "iso:country":"US",
    "sg:address":"11463 Quartz Dr Apt 1",
    "sg:city":"Auburn",
    "sg:classifiers":[
        {
            "category":"Structure",
            "subcategory":"Office Building",
            "type":"Public Place"
        }
    ],
    "sg:phone":"+1 530 886 5732",
    "sg:postcode":"95602",
    "sg:province":"CA",
    "sg:tags":[
        "park"
    ],
    "wof:name":"Realty World Auburn Propertie",
    "wof:placetype":"venue"
},
  "geometry": {"coordinates":[-121.104557,38.94724],"type":"Point"}
}