{
  "type": "Feature",
  "properties": {
    "iso:country":"US",
    "sg:address":"1224 Shady Mill Rd",
    "sg:city":"Corona",
    "sg:classifiers":[
        {
            "category":"Manufacturing",
            "subcategory":"Metals",
            "type":"Manufacturing & Wholesale Goods"
        }
    ],
    "sg:phone":"+1 951 735 9118",
    "sg:postcode":"92882",
    "sg:province":"CA",
    "sg:tags":[
        "hardware",
        "tool",
        "mfg"
    ],
    "wof:name":"Matco Tools",
    "wof:placetype":"venue"
},
  "geometry": {"coordinates":[-117.590488,33.852194],"type":"Point"}
}