{
  "type": "Feature",
  "properties": {
    "addr:full":"123 N 10th St Santa Paula CA 93060",
    "addr:housenumber":"123",
    "addr:postcode":"93060",
    "addr:street":"N 10Th St",
    "iso:country":"US",
    "sg:address":"123 N 10th St",
    "sg:city":"Santa Paula",
    "sg:classifiers":[
        {
            "category":"Banks & Credit Unions",
            "subcategory":"Bank",
            "type":"Services"
        }
    ],
    "sg:phone":"+1 805 933 5047",
    "sg:postcode":"93060",
    "sg:province":"CA",
    "sg:tags":[
        "loan"
    ],
    "wof:name":"Trinity Mortgage",
    "wof:placetype":"venue"
},
  "geometry": {"coordinates":[-119.060547,34.355295],"type":"Point"}
}