{
  "type": "Feature",
  "properties": {
    "addr:full":"1853 Main St Ramona CA 92065",
    "addr:housenumber":"1853",
    "addr:postcode":"92065",
    "addr:street":"Main St",
    "iso:country":"US",
    "sg:address":"1853 Main St",
    "sg:city":"Ramona",
    "sg:classifiers":[
        {
            "category":"Shopping",
            "subcategory":"Clothing, Apparel, & Fashions",
            "type":"Retail Goods"
        }
    ],
    "sg:phone":"+1 760 789 5498",
    "sg:postcode":"92065",
    "sg:province":"CA",
    "sg:tags":[
        "sporting",
        "sport"
    ],
    "wof:name":"Sport Shop",
    "wof:placetype":"venue"
},
  "geometry": {"coordinates":[-116.88158300000001,33.034371],"type":"Point"}
}