{
  "type": "Feature",
  "properties": {
    "addr:full":"30117 Vanderbilt St Hayward CA 94544",
    "addr:postcode":"30117;94544",
    "addr:street":"Vanderbilt St",
    "iso:country":"US",
    "sg:address":"30117 Vanderbilt St",
    "sg:city":"Hayward",
    "sg:classifiers":[
        {
            "category":"Social Services",
            "subcategory":"Adult Care",
            "type":"Services"
        }
    ],
    "sg:phone":"+1 510 471 3599",
    "sg:postcode":"94544",
    "sg:province":"CA",
    "sg:tags":[
        "home",
        "residential"
    ],
    "wof:name":"St Sebastian Care Home-Elderly",
    "wof:placetype":"venue"
},
  "geometry": {"coordinates":[-122.041115,37.626201],"type":"Point"}
}