{
  "type": "Feature",
  "properties": {
    "addr:full":"29820 Morning Breeze Dr Menifee CA 92584",
    "addr:housenumber":"29820",
    "addr:postcode":"92584",
    "addr:street":"Morning Breeze Dr",
    "iso:country":"US",
    "sg:address":"29820 Morning Breeze Dr",
    "sg:city":"Menifee",
    "sg:classifiers":[
        {
            "category":"Professional",
            "subcategory":"Management & Consulting",
            "type":"Services"
        }
    ],
    "sg:phone":"+1 951 246 9387",
    "sg:postcode":"92584",
    "sg:province":"CA",
    "sg:tags":[
        "company"
    ],
    "wof:name":"Commbobulator Inc",
    "wof:placetype":"venue"
},
  "geometry": {"coordinates":[-117.219855,33.687821],"type":"Point"}
}