{
  "type": "Feature",
  "properties": {
    "addr:full":"4844 University Ave San Diego CA 92105",
    "addr:housenumber":"4844",
    "addr:postcode":"92105",
    "addr:street":"University Ave",
    "iso:country":"US",
    "sg:address":"4844 University Ave",
    "sg:city":"San Diego",
    "sg:classifiers":[
        {
            "category":"Professional",
            "type":"Services"
        }
    ],
    "sg:phone":"+1 619 281 8489",
    "sg:postcode":"92105",
    "sg:province":"CA",
    "sg:tags":[
        "establishment"
    ],
    "wof:name":"Design Partners",
    "wof:placetype":"venue"
},
  "geometry": {"coordinates":[-117.09052800000001,32.749601],"type":"Point"}
}