{
  "type": "Feature",
  "properties": {
    "addr:full":"9041 S McCall Ave Selma CA 93662",
    "addr:housenumber":"9041",
    "addr:postcode":"93662",
    "addr:street":"S Mccall Ave",
    "iso:country":"US",
    "sg:address":"9041 S McCall Ave",
    "sg:city":"Selma",
    "sg:classifiers":[
        {
            "category":"Marine",
            "type":"Transportation"
        }
    ],
    "sg:phone":"+1 559 896 7756",
    "sg:postcode":"93662",
    "sg:province":"CA",
    "sg:tags":[
        "water",
        "transport"
    ],
    "wof:name":"Tract 1199 Water Systm",
    "wof:placetype":"venue"
},
  "geometry": {"coordinates":[-119.610714,36.604732],"type":"Point"}
}