{
  "type": "Feature",
  "properties": {
    "addr:full":"1015 Broadbeck Dr Newbury Park CA 91320",
    "addr:housenumber":"1015",
    "addr:postcode":"91320",
    "addr:street":"Broadbeck Dr",
    "iso:country":"US",
    "sg:address":"1015 Broadbeck Dr",
    "sg:city":"Newbury Park",
    "sg:classifiers":[
        {
            "category":"Ice Cream",
            "type":"Food & Drink"
        }
    ],
    "sg:phone":"+1 805 375 4331",
    "sg:postcode":"91320",
    "sg:province":"CA",
    "sg:tags":[
        "frozen",
        "yogurt"
    ],
    "wof:name":"Cold Stone Creamery",
    "wof:placetype":"venue"
},
  "geometry": {"coordinates":[-118.943001,34.192699],"type":"Point"}
}