{
  "type": "Feature",
  "properties": {
    "addr:full":"1316 Hollins Rd Oceanside CA 92056",
    "addr:housenumber":"1316",
    "addr:postcode":"92056",
    "addr:street":"Hollins Rd",
    "iso:country":"US",
    "sg:address":"1316 Hollins Rd",
    "sg:city":"Oceanside",
    "sg:classifiers":[
        {
            "category":"Banks & Credit Unions",
            "subcategory":"Financial Services",
            "type":"Services"
        }
    ],
    "sg:phone":"+1 760 758 4576",
    "sg:postcode":"92056",
    "sg:province":"CA",
    "sg:tags":[
        "trust",
        "management"
    ],
    "wof:name":"Garretts Family Trust",
    "wof:placetype":"venue"
},
  "geometry": {"coordinates":[-117.27100299999999,33.237564],"type":"Point"}
}