{
  "type": "Feature",
  "properties": {
    "addr:full":"3807 Wilshire Blvd Los Angeles CA 90010",
    "addr:housenumber":"3807",
    "addr:postcode":"90010",
    "addr:street":"Wilshire Blvd",
    "iso:country":"US",
    "sg:address":"3807 Wilshire Blvd",
    "sg:city":"Los Angeles",
    "sg:classifiers":[
        {
            "category":"Professional",
            "subcategory":"Lawyer & Legal Services",
            "type":"Services"
        }
    ],
    "sg:phone":"+1 213 389 7180",
    "sg:postcode":"90010",
    "sg:province":"CA",
    "wof:name":"Law Offices of Suzanna Chung",
    "wof:placetype":"venue"
},
  "geometry": {"coordinates":[-118.308998,34.061699],"type":"Point"}
}