{
  "type": "Feature",
  "properties": {
    "iso:country":"US",
    "sg:address":"8102 Madison Avenue",
    "sg:city":"Fair Oaks",
    "sg:classifiers":[
        {
            "category":"Food & Beverages",
            "subcategory":"Liquor & Beverages",
            "type":"Retail Goods"
        }
    ],
    "sg:phone":"+1 916 965 6610",
    "sg:postcode":"95628",
    "sg:province":"CA",
    "sg:tags":[
        "beer",
        "spirit",
        "wine"
    ],
    "wof:name":"Payless Food & Liquor",
    "wof:placetype":"venue"
},
  "geometry": {"coordinates":[-121.26200300000001,38.663901],"type":"Point"}
}