{
  "type": "Feature",
  "properties": {
    "iso:country":"US",
    "sg:address":"1941 Wilding Ln",
    "sg:city":"San Luis Obispo",
    "sg:classifiers":[
        {
            "category":"Farming",
            "subcategory":"Vineyard",
            "type":"Manufacturing & Wholesale Goods"
        }
    ],
    "sg:phone":"+1 805 441 1322",
    "sg:postcode":"93401",
    "sg:province":"CA",
    "sg:tags":[
        "grape"
    ],
    "wof:name":"Steven N Beck",
    "wof:placetype":"venue"
},
  "geometry": {"coordinates":[-120.647745,35.278861],"type":"Point"}
}