{
  "type": "Feature",
  "properties": {
    "addr:full":"14565 Valley View Ave Santa Fe Springs CA 90670",
    "addr:housenumber":"14565",
    "addr:postcode":"90670",
    "addr:street":"Valley View Ave",
    "iso:country":"US",
    "sg:address":"14565 Valley View Ave",
    "sg:city":"Santa Fe Springs",
    "sg:classifiers":[
        {
            "category":"Wholesale",
            "subcategory":"Electrical",
            "type":"Manufacturing & Wholesale Goods"
        }
    ],
    "sg:phone":"+1 562 921 8686",
    "sg:postcode":"90670",
    "sg:province":"CA",
    "sg:tags":[
        "fire",
        "equipment",
        "protection"
    ],
    "sg:website":"www.firefightersafety.com",
    "wof:name":"Firefighters Safety Ctr",
    "wof:placetype":"venue"
},
  "geometry": {"coordinates":[-118.02911400000001,33.90105],"type":"Point"}
}