{
  "type": "Feature",
  "properties": {
    "addr:full":"7921 Wish Ave Van Nuys CA 91406",
    "addr:housenumber":"7921",
    "addr:postcode":"91406",
    "addr:street":"Wish Ave",
    "iso:country":"US",
    "sg:address":"7921 Wish Ave",
    "sg:city":"Van Nuys",
    "sg:classifiers":[
        {
            "category":"Manufacturing",
            "subcategory":"Printing",
            "type":"Manufacturing & Wholesale Goods"
        }
    ],
    "sg:phone":"+1 818 774 3763",
    "sg:postcode":"91406",
    "sg:province":"CA",
    "sg:tags":[
        "lithographic",
        "commercial"
    ],
    "wof:name":"Flores Printing",
    "wof:placetype":"venue"
},
  "geometry": {"coordinates":[-118.506423,34.214719],"type":"Point"}
}