{
  "type": "Feature",
  "properties": {
    "addr:full":"9602 Baseline Rd Alta Loma CA 91701",
    "addr:housenumber":"9602",
    "addr:postcode":"91701",
    "addr:street":"Baseline Rd",
    "iso:country":"US",
    "sg:address":"9602 Baseline Rd",
    "sg:city":"Alta Loma",
    "sg:classifiers":[
        {
            "category":"Food & Beverages",
            "subcategory":"Specialty",
            "type":"Retail Goods"
        }
    ],
    "sg:phone":"+1 909 989 7000",
    "sg:postcode":"91701",
    "sg:province":"CA",
    "sg:tags":[
        "vitamin"
    ],
    "wof:name":"Rancho Health Foods",
    "wof:placetype":"venue"
},
  "geometry": {"coordinates":[-117.596155,34.121611],"type":"Point"}
}