{
  "type": "Feature",
  "properties": {
    "addr:full":"5100 Obyrnes Ferry Rd Jamestown CA 95327",
    "addr:housenumber":"5100",
    "addr:postcode":"95327",
    "addr:street":"Obyrnes Ferry Rd",
    "iso:country":"US",
    "sg:address":"5100 Obyrnes Ferry Rd",
    "sg:city":"Jamestown",
    "sg:classifiers":[
        {
            "category":"Travel",
            "subcategory":"Travel Agent",
            "type":"Entertainment"
        }
    ],
    "sg:phone":"+1 209 984 5523",
    "sg:postcode":"95327",
    "sg:province":"CA",
    "sg:tags":[
        "information",
        "tourist"
    ],
    "wof:name":"Friends Outside-Mother Lode",
    "wof:placetype":"venue"
},
  "geometry": {"coordinates":[-120.545768,37.890198],"type":"Point"}
}