{
  "type": "Feature",
  "properties": {
    "addr:full":"42275 Washington St Palm Desert CA 92211",
    "addr:housenumber":"42275",
    "addr:postcode":"92211",
    "addr:street":"Washington St",
    "iso:country":"US",
    "sg:address":"42275 Washington St",
    "sg:city":"Palm Desert",
    "sg:classifiers":[
        {
            "category":"Retail",
            "subcategory":"Auto Repair",
            "type":"Services"
        }
    ],
    "sg:phone":"+1 760 772 4330",
    "sg:postcode":"92211",
    "sg:province":"CA",
    "sg:tags":[
        "automobile",
        "lubrication"
    ],
    "wof:name":"Jiffy Lube",
    "wof:placetype":"venue"
},
  "geometry": {"coordinates":[-116.303933,33.74245],"type":"Point"}
}