{
  "type": "Feature",
  "properties": {
    "iso:country":"US",
    "sg:address":"704 Forest Ave",
    "sg:city":"Pacific Grove",
    "sg:classifiers":[
        {
            "category":"Banks & Credit Unions",
            "subcategory":"Bank",
            "type":"Services"
        }
    ],
    "sg:phone":"+1 831 372 3151",
    "sg:postcode":"93950",
    "sg:province":"CA",
    "sg:tags":[
        "loan",
        "real estate"
    ],
    "wof:name":"Coastal Mortgage Ctr",
    "wof:placetype":"venue"
},
  "geometry": {"coordinates":[-121.920461,36.615138],"type":"Point"}
}