{
  "type": "Feature",
  "properties": {
    "iso:country":"US",
    "sg:address":"493 W Shaw Ave",
    "sg:city":"Clovis",
    "sg:classifiers":[
        {
            "category":"Shopping",
            "subcategory":"Jewelry",
            "type":"Retail Goods"
        },
        {
            "category":"Retail",
            "subcategory":"Repair Shop",
            "type":"Services"
        },
        {
            "category":"Manufacturing",
            "subcategory":"Jewelry",
            "type":"Manufacturing & Wholesale Goods"
        }
    ],
    "sg:phone":"+1 559 297 0201",
    "sg:postcode":"93612",
    "sg:province":"CA",
    "sg:tags":[
        "diamond",
        "watch",
        "designer",
        "jeweler"
    ],
    "sg:website":"http://www.karkazianjewelers.com",
    "wof:name":"Karkazian Jewelers & Watch Makers",
    "wof:placetype":"venue"
},
  "geometry": {"coordinates":[-119.720159,36.808552],"type":"Point"}
}