{
  "type": "Feature",
  "properties": {
    "iso:country":"US",
    "sg:address":"7535 Convoy Ct",
    "sg:city":"San Diego",
    "sg:classifiers":[
        {
            "category":"Manufacturing",
            "subcategory":"Retail Goods",
            "type":"Manufacturing & Wholesale Goods"
        }
    ],
    "sg:phone":"+1 858 560 4127",
    "sg:postcode":"92111",
    "sg:province":"CA",
    "sg:tags":[
        "manufacturer"
    ],
    "sg:website":"www.musichem.com",
    "wof:name":"Musi Chem",
    "wof:placetype":"venue"
},
  "geometry": {"coordinates":[-117.154826,32.834667],"type":"Point"}
}