{
  "type": "Feature",
  "properties": {
    "iso:country":"US",
    "sg:address":"371 Old Newport Boulevard",
    "sg:city":"Newport Beach",
    "sg:classifiers":[
        {
            "category":"Personal",
            "subcategory":"Beauty Salon",
            "type":"Services"
        }
    ],
    "sg:phone":"+1 949 646 9447",
    "sg:postcode":"92663",
    "sg:province":"CA",
    "sg:tags":[
        "spa"
    ],
    "wof:name":"Wiggin Out",
    "wof:placetype":"venue"
},
  "geometry": {"coordinates":[-117.927453,33.625322],"type":"Point"}
}