{
  "type": "Feature",
  "properties": {
    "addr:full":"1088 Huston St Grover Beach CA 93433",
    "addr:housenumber":"1088",
    "addr:postcode":"93433",
    "addr:street":"Huston St",
    "iso:country":"US",
    "sg:address":"1088 Huston St",
    "sg:city":"Grover Beach",
    "sg:classifiers":[
        {
            "category":"Retail",
            "subcategory":"Auto Rental",
            "type":"Services"
        }
    ],
    "sg:phone":"+1 805 489 0384",
    "sg:postcode":"93433",
    "sg:province":"CA",
    "sg:tags":[
        "renting",
        "truck",
        "leasing"
    ],
    "wof:name":"U-Haul Co",
    "wof:placetype":"venue"
},
  "geometry": {"coordinates":[-120.619529,35.109134],"type":"Point"}
}