{
  "type": "Feature",
  "properties": {
    "addr:full":"3252 19th Street San Francisco CA 94110",
    "addr:housenumber":"3252",
    "addr:postcode":"94110",
    "addr:street":"19Th Street",
    "iso:country":"US",
    "sg:address":"3252 19th Street",
    "sg:city":"San Francisco",
    "sg:classifiers":[
        {
            "category":"Retail",
            "subcategory":"Auto Repair",
            "type":"Services"
        }
    ],
    "sg:phone":"+1 415 647 4812",
    "sg:postcode":"94110",
    "sg:province":"CA",
    "sg:tags":[
        "body",
        "shop"
    ],
    "wof:name":"Gigler's Auto Body Shop",
    "wof:placetype":"venue"
},
  "geometry": {"coordinates":[-122.416,37.760502],"type":"Point"}
}