{
  "type": "Feature",
  "properties": {
    "iso:country":"US",
    "sg:address":"1416 18th St",
    "sg:city":"Bakersfield",
    "sg:classifiers":[
        {
            "category":"Shopping",
            "subcategory":"Jewelry",
            "type":"Retail Goods"
        }
    ],
    "sg:phone":"+1 661 322 0405",
    "sg:postcode":"93301",
    "sg:province":"CA",
    "wof:name":"Golden Jewelers",
    "wof:placetype":"venue"
},
  "geometry": {"coordinates":[-119.018654,35.375361],"type":"Point"}
}