{
  "type": "Feature",
  "properties": {
    "addr:full":"201 E Chapman Placentia CA 92870",
    "addr:housenumber":"201",
    "addr:postcode":"ca 92870",
    "addr:street":"E Chapman",
    "iso:country":"US",
    "sg:address":"201 E Chapman",
    "sg:city":"Placentia",
    "sg:classifiers":[
        {
            "category":"Real Estate",
            "subcategory":"Real Estate Operator",
            "type":"Services"
        }
    ],
    "sg:phone":"+1 714 524 9540",
    "sg:postcode":"92870",
    "sg:province":"CA",
    "sg:tags":[
        "apartment"
    ],
    "sg:website":"www.villaangelinaapts.com/",
    "wof:name":"Villa Angelina Apartments",
    "wof:placetype":"venue"
},
  "geometry": {"coordinates":[-117.867268,33.872457],"type":"Point"}
}