{
  "type": "Feature",
  "properties": {
    "iso:country":"US",
    "sg:address":"12107 Santa Monica Blvd",
    "sg:city":"Los Angeles",
    "sg:classifiers":[
        {
            "category":"Wholesale",
            "subcategory":"Machinery & Supplies",
            "type":"Manufacturing & Wholesale Goods"
        }
    ],
    "sg:phone":"+1 310 207 0131",
    "sg:postcode":"90025",
    "sg:province":"CA",
    "sg:tags":[
        "salon",
        "beauty"
    ],
    "wof:name":"Maly's",
    "wof:placetype":"venue"
},
  "geometry": {"coordinates":[-118.464371,34.040173],"type":"Point"}
}