{
  "type": "Feature",
  "properties": {
    "iso:country":"US",
    "sg:address":"1507 Eisenhower St",
    "sg:city":"Fairfield",
    "sg:classifiers":[
        {
            "category":"Building & Trades",
            "subcategory":"Landscaping Services",
            "type":"Services"
        }
    ],
    "sg:phone":"+1 707 344 0568",
    "sg:postcode":"94533",
    "sg:province":"CA",
    "wof:name":"Mendenhall Lawn Service",
    "wof:placetype":"venue"
},
  "geometry": {"coordinates":[-122.029217,38.258142],"type":"Point"}
}