{
  "type": "Feature",
  "properties": {
    "addr:full":"186 Potrero Ave San Francisco CA 94103",
    "addr:housenumber":"186",
    "addr:postcode":"94103",
    "addr:street":"Potrero Ave",
    "iso:country":"US",
    "sg:address":"186 Potrero Ave",
    "sg:city":"San Francisco",
    "sg:classifiers":[
        {
            "category":"Organizations",
            "subcategory":"Labor Organization",
            "type":"Services"
        }
    ],
    "sg:phone":"+1 415 487 8510",
    "sg:postcode":"94103",
    "sg:province":"CA",
    "wof:name":"Bricklayers & Allied Craftwork",
    "wof:placetype":"venue"
},
  "geometry": {"coordinates":[-122.407849,37.768191],"type":"Point"}
}