{
  "type": "Feature",
  "properties": {
    "iso:country":"US",
    "sg:address":"415 Westlake Center",
    "sg:city":"Daly City",
    "sg:classifiers":[
        {
            "category":"Banks & Credit Unions",
            "subcategory":"Bank",
            "type":"Services"
        }
    ],
    "sg:phone":"+1 650 363 1725",
    "sg:postcode":"94015",
    "sg:province":"CA",
    "sg:website":"www.smcu.org",
    "wof:name":"San Mateo Credit Union",
    "wof:placetype":"venue"
},
  "geometry": {"coordinates":[-122.483087,37.700887],"type":"Point"}
}