{
  "type": "Feature",
  "properties": {
    "iso:country":"US",
    "sg:address":"900 Commerce Dr",
    "sg:city":"Chowchilla",
    "sg:classifiers":[
        {
            "category":"Home & Garden",
            "subcategory":"Building Materials",
            "type":"Retail Goods"
        }
    ],
    "sg:phone":"+1 559 665 3558",
    "sg:postcode":"93637",
    "sg:province":"CA",
    "sg:tags":[
        "truss"
    ],
    "wof:name":"E-Wall",
    "wof:placetype":"venue"
},
  "geometry": {"coordinates":[-120.087723,36.946696],"type":"Point"}
}