{
  "type": "Feature",
  "properties": {
    "addr:full":"1841 Fulton Ave Sacramento CA 95825",
    "addr:housenumber":"1841",
    "addr:postcode":"95825",
    "addr:street":"Fulton Ave",
    "iso:country":"US",
    "sg:address":"1841 Fulton Ave",
    "sg:city":"Sacramento",
    "sg:classifiers":[
        {
            "category":"Home & Garden",
            "subcategory":"Furniture",
            "type":"Retail Goods"
        }
    ],
    "sg:phone":"+1 916 922 6833",
    "sg:postcode":"95825",
    "sg:province":"CA",
    "sg:tags":[
        "store"
    ],
    "sg:website":"www.todaysfurniture.us/",
    "wof:name":"Today's Furniture & Accessories",
    "wof:placetype":"venue"
},
  "geometry": {"coordinates":[-121.40206499999999,38.599315],"type":"Point"}
}