{
  "type": "Feature",
  "properties": {
    "iso:country":"US",
    "sg:address":"5842 E Naples Plz",
    "sg:city":"Long Beach",
    "sg:classifiers":[
        {
            "category":"Health Services",
            "subcategory":"Health Practitioner",
            "type":"Services"
        }
    ],
    "sg:phone":"+1 562 439 9539",
    "sg:postcode":"90803",
    "sg:province":"CA",
    "sg:tags":[
        "audiologists"
    ],
    "wof:name":"Riverview Hearing Speech Ctr",
    "wof:placetype":"venue"
},
  "geometry": {"coordinates":[-118.120835,33.756461],"type":"Point"}
}