{
  "type": "Feature",
  "properties": {
    "addr:full":"10410 Rosecrans Ave Bellflower CA 90706",
    "addr:housenumber":"10410",
    "addr:postcode":"90706",
    "addr:street":"Rosecrans Ave",
    "iso:country":"US",
    "sg:address":"10410 Rosecrans Ave",
    "sg:city":"Bellflower",
    "sg:classifiers":[
        {
            "category":"Health Services",
            "subcategory":"Optometrist",
            "type":"Services"
        }
    ],
    "sg:phone":"+1 562 925 7814",
    "sg:postcode":"90706",
    "sg:province":"CA",
    "wof:name":"Stein & Stein",
    "wof:placetype":"venue"
},
  "geometry": {"coordinates":[-118.109061,33.901956],"type":"Point"}
}