{
  "type": "Feature",
  "properties": {
    "iso:country":"US",
    "sg:address":"2443 W Fremont St",
    "sg:city":"Stockton",
    "sg:phone":"+1 209 464 9469",
    "sg:postcode":"95203",
    "sg:province":"CA",
    "sg:tags":[
        "scale"
    ],
    "wof:name":"Scales Inc",
    "wof:placetype":"venue"
},
  "geometry": {"coordinates":[-121.329663,37.955232],"type":"Point"}
}