{
  "type": "Feature",
  "properties": {
    "iso:country":"US",
    "sg:address":"595 Market St",
    "sg:city":"San Francisco",
    "sg:classifiers":[
        {
            "category":"Professional",
            "subcategory":"Accounting & Tax Preparation",
            "type":"Services"
        }
    ],
    "sg:phone":"+1 415 283 4490",
    "sg:postcode":"94105",
    "sg:province":"CA",
    "sg:tags":[
        "return",
        "filing"
    ],
    "wof:name":"HCA & Co",
    "wof:placetype":"venue"
},
  "geometry": {"coordinates":[-122.400146,37.790297],"type":"Point"}
}