{
  "type": "Feature",
  "properties": {
    "iso:country":"US",
    "sg:address":"98 Main St",
    "sg:city":"Belvedere Tiburon",
    "sg:classifiers":[
        {
            "category":"Professional",
            "subcategory":"Art Services",
            "type":"Services"
        }
    ],
    "sg:phone":"+1 415 435 0876",
    "sg:postcode":"94920",
    "sg:province":"CA",
    "sg:tags":[
        "graphic",
        "design",
        "publishing",
        "desktop"
    ],
    "wof:name":"Creative Type The",
    "wof:placetype":"venue"
},
  "geometry": {"coordinates":[-122.458369,37.873713],"type":"Point"}
}