{
  "type": "Feature",
  "properties": {
    "addr:full":"12611 Hiddencreek Way Cerritos CA 90703",
    "addr:housenumber":"12611",
    "addr:postcode":"ca 90703",
    "addr:street":"Hiddencreek Way",
    "iso:country":"US",
    "sg:address":"12611 Hiddencreek Way",
    "sg:city":"Cerritos",
    "sg:classifiers":[
        {
            "category":"Freight",
            "type":"Transportation"
        }
    ],
    "sg:phone":"+1 562 407 0660",
    "sg:postcode":"90703",
    "sg:province":"CA",
    "sg:tags":[
        "warehouse"
    ],
    "wof:name":"Cea-Pack Svc",
    "wof:placetype":"venue"
},
  "geometry": {"coordinates":[-118.06151300000001,33.884961],"type":"Point"}
}