{
  "type": "Feature",
  "properties": {
    "iso:country":"US",
    "sg:address":"3038 Woodside Rd",
    "sg:city":"Woodside",
    "sg:classifiers":[
        {
            "category":"Retail",
            "subcategory":"Laundry & Dry Cleaning",
            "type":"Services"
        }
    ],
    "sg:phone":"+1 650 851 8658",
    "sg:postcode":"94062",
    "sg:province":"CA",
    "sg:tags":[
        "cleaners"
    ],
    "wof:name":"Canada Cleaners",
    "wof:placetype":"venue"
},
  "geometry": {"coordinates":[-122.254122,37.429378],"type":"Point"}
}