{
  "type": "Feature",
  "properties": {
    "addr:full":"2791 N Main St Walnut Creek CA 94597",
    "addr:housenumber":"2791",
    "addr:postcode":"94597",
    "addr:street":"N Main St",
    "iso:country":"US",
    "sg:address":"2791 N Main St",
    "sg:city":"Walnut Creek",
    "sg:classifiers":[
        {
            "category":"Autos & Motor Vehicles",
            "subcategory":"Automobile Sales",
            "type":"Retail Goods"
        }
    ],
    "sg:phone":"+1 925 939 3333",
    "sg:postcode":"94597",
    "sg:province":"CA",
    "sg:tags":[
        "car",
        "dealer"
    ],
    "sg:website":"www.lawrencevolvo.com",
    "wof:name":"Lawrence Volvo",
    "wof:placetype":"venue"
},
  "geometry": {"coordinates":[-122.062653,37.926203],"type":"Point"}
}