{
  "type": "Feature",
  "properties": {
    "addr:full":"10911 Wheatlands Ave Santee CA 92071",
    "addr:housenumber":"10911",
    "addr:postcode":"92071",
    "addr:street":"Wheatlands Ave",
    "iso:country":"US",
    "sg:address":"10911 Wheatlands Ave",
    "sg:city":"Santee",
    "sg:classifiers":[
        {
            "category":"Shopping",
            "subcategory":"Florist",
            "type":"Retail Goods"
        }
    ],
    "sg:phone":"+1 619 596 7519",
    "sg:postcode":"92071",
    "sg:province":"CA",
    "wof:name":"Flowers By Julie",
    "wof:placetype":"venue"
},
  "geometry": {"coordinates":[-116.95950999999999,32.846561],"type":"Point"}
}