{
  "type": "Feature",
  "properties": {
    "iso:country":"US",
    "sg:address":"123 Washington Blvd",
    "sg:city":"Fremont",
    "sg:classifiers":[
        {
            "category":"Museum",
            "type":"Entertainment"
        }
    ],
    "sg:phone":"+1 510 791 4357",
    "sg:postcode":"94539",
    "sg:province":"CA",
    "sg:tags":[
        "executive",
        "gallery"
    ],
    "wof:name":"Olive Hyde Art Gallery",
    "wof:placetype":"venue"
},
  "geometry": {"coordinates":[-121.92131000000001,37.53333],"type":"Point"}
}