{
  "type": "Feature",
  "properties": {
    "addr:full":"22036 Avalon Blvd Carson CA 90745",
    "addr:housenumber":"22036",
    "addr:postcode":"90745",
    "addr:street":"Avalon Blvd",
    "iso:country":"US",
    "sg:address":"22036 Avalon Blvd",
    "sg:city":"Carson",
    "sg:classifiers":[
        {
            "category":"Social Services",
            "subcategory":"Child Care",
            "type":"Services"
        }
    ],
    "sg:phone":"+1 310 834 6021",
    "sg:postcode":"90745",
    "sg:province":"CA",
    "sg:tags":[
        "elementary",
        "kindergarten",
        "school",
        "academic"
    ],
    "wof:name":"Community Development Center",
    "wof:placetype":"venue"
},
  "geometry": {"coordinates":[-118.264,33.826698],"type":"Point"}
}