{
  "type": "Feature",
  "properties": {
    "addr:full":"2436 E Washington Blvd Pasadena CA 91104",
    "addr:housenumber":"2436",
    "addr:postcode":"91104",
    "addr:street":"E Washington Blvd",
    "iso:country":"US",
    "sg:address":"2436 E Washington Blvd",
    "sg:city":"Pasadena",
    "sg:classifiers":[
        {
            "category":"Home & Garden",
            "subcategory":"Carpets & Floor Coverings",
            "type":"Retail Goods"
        }
    ],
    "sg:phone":"+1 626 485 6556",
    "sg:postcode":"91104",
    "sg:province":"CA",
    "sg:tags":[
        "hardwood",
        "material"
    ],
    "wof:name":"Modern Hardwood Floors",
    "wof:placetype":"venue"
},
  "geometry": {"coordinates":[-118.100264,34.169128],"type":"Point"}
}