{
  "type": "Feature",
  "properties": {
    "iso:country":"US",
    "sg:address":"5225 Cochrane Ave",
    "sg:city":"Oakland",
    "sg:classifiers":[
        {
            "category":"Manufacturing",
            "subcategory":"Apparel",
            "type":"Manufacturing & Wholesale Goods"
        }
    ],
    "sg:phone":"+1 510 547 3644",
    "sg:postcode":"94618",
    "sg:province":"CA",
    "sg:tags":[
        "sportswear",
        "mfg"
    ],
    "wof:name":"Boero Inc",
    "wof:placetype":"venue"
},
  "geometry": {"coordinates":[-122.226647,37.840577],"type":"Point"}
}