{
  "type": "Feature",
  "properties": {
    "addr:full":"740 S E St San Bernardino CA 92408",
    "addr:housenumber":"740",
    "addr:postcode":"92408",
    "addr:street":"S E St",
    "iso:country":"US",
    "sg:address":"740 S E St",
    "sg:city":"San Bernardino",
    "sg:classifiers":[
        {
            "category":"Autos & Motor Vehicles",
            "subcategory":"Auto Supplies",
            "type":"Retail Goods"
        }
    ],
    "sg:phone":"+1 909 388 1400",
    "sg:postcode":"92408",
    "sg:province":"CA",
    "sg:tags":[
        "automobile",
        "stereo",
        "radio"
    ],
    "sg:website":"www.californiasound.com",
    "wof:name":"California Sound",
    "wof:placetype":"venue"
},
  "geometry": {"coordinates":[-117.29423300000001,34.090209],"type":"Point"}
}