{
  "type": "Feature",
  "properties": {
    "iso:country":"US",
    "sg:address":"1620 Tully Rd Ste B",
    "sg:city":"Modesto",
    "sg:classifiers":[
        {
            "category":"Personal",
            "subcategory":"Beauty Salon",
            "type":"Services"
        }
    ],
    "sg:phone":"+1 209 524 5452",
    "sg:postcode":"95350",
    "sg:province":"CA",
    "sg:tags":[
        "hair"
    ],
    "wof:name":"Eloquence Salon",
    "wof:placetype":"venue"
},
  "geometry": {"coordinates":[-121.011889,37.668611],"type":"Point"}
}