{
  "type": "Feature",
  "properties": {
    "iso:country":"US",
    "sg:address":"1281 Gould St",
    "sg:city":"San Bernardino",
    "sg:classifiers":[
        {
            "category":"Wholesale",
            "subcategory":"Non-durable Goods",
            "type":"Manufacturing & Wholesale Goods"
        }
    ],
    "sg:phone":"+1 909 799 7334",
    "sg:postcode":"92408",
    "sg:province":"CA",
    "wof:name":"Thompson Quality Import Co",
    "wof:placetype":"venue"
},
  "geometry": {"coordinates":[-117.25920600000001,34.07105],"type":"Point"}
}