{
  "type": "Feature",
  "properties": {
    "iso:country":"US",
    "sg:address":"1020 Aileen St",
    "sg:city":"Lafayette",
    "sg:classifiers":[
        {
            "category":"Professional",
            "subcategory":"Lawyer & Legal Services",
            "type":"Services"
        }
    ],
    "sg:phone":"+1 925 284 9200",
    "sg:postcode":"94549",
    "sg:province":"CA",
    "sg:tags":[
        "attorney",
        "family",
        "divorce",
        "assistance",
        "practice",
        "law"
    ],
    "wof:name":"Joyce Sasse Law Offices of",
    "wof:placetype":"venue"
},
  "geometry": {"coordinates":[-122.10688500000001,37.894807],"type":"Point"}
}