{
  "type": "Feature",
  "properties": {
    "addr:full":"14109 Olde Highway 80 El Cajon CA 92021",
    "addr:housenumber":"14109",
    "addr:postcode":"92021",
    "addr:street":"Olde Highway 80",
    "iso:country":"US",
    "sg:address":"14109 Olde Highway 80",
    "sg:city":"El Cajon",
    "sg:classifiers":[
        {
            "category":"Building & Trades",
            "subcategory":"Landscaping Services",
            "type":"Services"
        }
    ],
    "sg:phone":"+1 619 443 5414",
    "sg:postcode":"92021",
    "sg:province":"CA",
    "wof:name":"Georges Landscaping",
    "wof:placetype":"venue"
},
  "geometry": {"coordinates":[-116.880729,32.843404],"type":"Point"}
}