{
  "type": "Feature",
  "properties": {
    "addr:full":"9320 Church St Gilroy CA 95020",
    "addr:housenumber":"9320",
    "addr:postcode":"95020",
    "addr:street":"Church St",
    "iso:country":"US",
    "sg:address":"9320 Church St",
    "sg:city":"Gilroy",
    "sg:classifiers":[
        {
            "category":"Professional",
            "subcategory":"Business Services",
            "type":"Services"
        }
    ],
    "sg:phone":"+1 831 623 9316",
    "sg:postcode":"95020",
    "sg:province":"CA",
    "sg:tags":[
        "auctioneer"
    ],
    "wof:name":"San Juan Auction",
    "wof:placetype":"venue"
},
  "geometry": {"coordinates":[-121.585238,37.032479],"type":"Point"}
}