{
  "type": "Feature",
  "properties": {
    "iso:country":"US",
    "sg:address":"6440 Sunridge Ct",
    "sg:city":"Alta Loma",
    "sg:classifiers":[
        {
            "category":"Shopping",
            "subcategory":"Clothing, Apparel, & Fashions",
            "type":"Retail Goods"
        }
    ],
    "sg:phone":"+1 909 484 0973",
    "sg:postcode":"91737",
    "sg:province":"CA",
    "wof:name":"Euro Fashion",
    "wof:placetype":"venue"
},
  "geometry": {"coordinates":[-117.548007,34.137366],"type":"Point"}
}