{
  "type": "Feature",
  "properties": {
    "addr:full":"128 Cabrillo St Costa Mesa CA 92627",
    "addr:housenumber":"128",
    "addr:postcode":"92627",
    "addr:street":"Cabrillo St",
    "iso:country":"US",
    "sg:address":"128 Cabrillo St",
    "sg:city":"Costa Mesa",
    "sg:classifiers":[
        {
            "category":"Manufacturing",
            "subcategory":"Printing",
            "type":"Manufacturing & Wholesale Goods"
        }
    ],
    "sg:phone":"+1 949 631 7133",
    "sg:postcode":"92627",
    "sg:province":"CA",
    "sg:tags":[
        "broker"
    ],
    "wof:name":"Golden Printing Solutions Inc",
    "wof:placetype":"venue"
},
  "geometry": {"coordinates":[-117.919763,33.638032],"type":"Point"}
}