{
  "type": "Feature",
  "properties": {
    "iso:country":"US",
    "sg:address":"711 A Ave",
    "sg:city":"National City",
    "sg:classifiers":[
        {
            "category":"Professional",
            "type":"Services"
        }
    ],
    "sg:phone":"+1 619 434 3079",
    "sg:postcode":"91950",
    "sg:province":"CA",
    "wof:name":"Rafaela Jennings",
    "wof:placetype":"venue"
},
  "geometry": {"coordinates":[-117.105822,32.676227],"type":"Point"}
}