{
  "type": "Feature",
  "properties": {
    "addr:full":"668 S Azusa Ave Azusa CA 91702",
    "addr:housenumber":"668",
    "addr:postcode":"91702",
    "addr:street":"S Azusa Ave",
    "iso:country":"US",
    "sg:address":"668 S Azusa Ave",
    "sg:city":"Azusa",
    "sg:classifiers":[
        {
            "category":"Organizations",
            "subcategory":"Religious Organization",
            "type":"Services"
        }
    ],
    "sg:phone":"+1 626 815 9950",
    "sg:postcode":"91702",
    "sg:province":"CA",
    "sg:tags":[
        "churches-christian-reformed",
        "church"
    ],
    "wof:name":"Rosa De Saron Church",
    "wof:placetype":"venue"
},
  "geometry": {"coordinates":[-117.90759300000001,34.111015],"type":"Point"}
}