{
  "type": "Feature",
  "properties": {
    "addr:full":"1000 Apollo Ct Antioch CA 94509",
    "addr:housenumber":"1000",
    "addr:postcode":"ca 94509",
    "addr:street":"Apollo Ct",
    "iso:country":"US",
    "sg:address":"1000 Apollo Ct",
    "sg:city":"Antioch",
    "sg:classifiers":[
        {
            "category":"Building & Trades",
            "subcategory":"Construction",
            "type":"Services"
        }
    ],
    "sg:phone":"+1 925 755 4822",
    "sg:postcode":"94509",
    "sg:province":"CA",
    "sg:tags":[
        "system",
        "specialty",
        "heating",
        "contractor",
        "air conditioning"
    ],
    "wof:name":"Central Heating And Air Conditioning",
    "wof:placetype":"venue"
},
  "geometry": {"coordinates":[-121.78885699999999,38.01123],"type":"Point"}
}