{
  "type": "Feature",
  "properties": {
    "iso:country":"US",
    "sg:address":"106 Esmeralda Ct",
    "sg:city":"Santa Cruz",
    "sg:classifiers":[
        {
            "category":"Professional",
            "subcategory":"Business Services",
            "type":"Services"
        }
    ],
    "sg:phone":"+1 831 457 9349",
    "sg:postcode":"95060",
    "sg:province":"CA",
    "wof:name":"Sdr Communications",
    "wof:placetype":"venue"
},
  "geometry": {"coordinates":[-122.012795,36.999906],"type":"Point"}
}