{
  "type": "Feature",
  "properties": {
    "iso:country":"US",
    "sg:address":"1329 Taylor St",
    "sg:city":"San Francisco",
    "sg:classifiers":[
        {
            "category":"Professional",
            "subcategory":"Employment Agencies",
            "type":"Services"
        }
    ],
    "sg:phone":"+1 415 441 7010",
    "sg:postcode":"94108",
    "sg:province":"CA",
    "sg:tags":[
        "consultant",
        "search",
        "executive"
    ],
    "wof:name":"Todd Madeleine",
    "wof:placetype":"venue"
},
  "geometry": {"coordinates":[-122.413221,37.794936],"type":"Point"}
}