{
  "type": "Feature",
  "properties": {
    "addr:full":"2550 9th St Ste 114 Berkeley CA 94710",
    "addr:housenumber":"2550",
    "addr:postcode":"94710",
    "addr:street":"9Th St Ste 114",
    "iso:country":"US",
    "sg:address":"2550 9th St Ste 114",
    "sg:city":"Berkeley",
    "sg:classifiers":[
        {
            "category":"Wholesale",
            "subcategory":"Computers",
            "type":"Manufacturing & Wholesale Goods"
        },
        {
            "category":"Professional",
            "subcategory":"Computer Services",
            "type":"Services"
        },
        {
            "category":"Professional",
            "subcategory":"Business Services",
            "type":"Services"
        },
        {
            "category":"Internet Cafe",
            "subcategory":"None",
            "type":"Food & Drink"
        }
    ],
    "sg:phone":"+1 510 705 8470",
    "sg:postcode":"94710",
    "sg:province":"CA",
    "sg:tags":[
        "product",
        "coach",
        "consultant",
        "cd-rom",
        "equipment",
        "software"
    ],
    "sg:website":"http://www.io-informatics.com",
    "wof:name":"Io Informatics, Inc.",
    "wof:placetype":"venue"
},
  "geometry": {"coordinates":[-122.29154,37.859746],"type":"Point"}
}