{
  "type": "Feature",
  "properties": {
    "iso:country":"US",
    "sg:address":"5519 Snell Ave",
    "sg:city":"San Jose",
    "sg:classifiers":[
        {
            "category":"Restaurant",
            "type":"Food & Drink"
        }
    ],
    "sg:menulink":"http://www.allmenus.com/ca/san-jose/159949-arbys/menu/",
    "sg:phone":"+1 408 578 8761",
    "sg:postcode":"95123",
    "sg:province":"CA",
    "sg:tags":[
        "burger",
        "american"
    ],
    "wof:name":"Arby's",
    "wof:placetype":"venue"
},
  "geometry": {"coordinates":[-121.831192,37.25262],"type":"Point"}
}