{
  "type": "Feature",
  "properties": {
    "iso:country":"US",
    "sg:address":"2402 Cam Bucanero",
    "sg:city":"San Clemente",
    "sg:classifiers":[
        {
            "category":"Retail",
            "subcategory":"Laundry & Dry Cleaning",
            "type":"Services"
        }
    ],
    "sg:phone":"+1 949 369 1834",
    "sg:postcode":"92673",
    "sg:province":"CA",
    "sg:tags":[
        "cleaners",
        "rug",
        "carpet"
    ],
    "wof:name":"Evergreen Carpet Care",
    "wof:placetype":"venue"
},
  "geometry": {"coordinates":[-117.62969200000001,33.450469],"type":"Point"}
}