{
  "type": "Feature",
  "properties": {
    "iso:country":"US",
    "sg:address":"1940 Diamond St",
    "sg:city":"San Marcos",
    "sg:classifiers":[
        {
            "category":"Manufacturing",
            "subcategory":"Metals",
            "type":"Manufacturing & Wholesale Goods"
        },
        {
            "category":"Manufacturing",
            "subcategory":"Tools & Machinery",
            "type":"Manufacturing & Wholesale Goods"
        }
    ],
    "sg:phone":"+1 760 744 5240",
    "sg:postcode":"92078",
    "sg:province":"CA",
    "sg:tags":[
        "irrigation",
        "mfg",
        "farm",
        "real estate",
        "fixture",
        "system",
        "operates",
        "equipment",
        "fitting",
        "owns",
        "plumbing"
    ],
    "sg:website":"www.hunterindustries.com",
    "wof:name":"Hunter Industries L P",
    "wof:placetype":"venue"
},
  "geometry": {"coordinates":[-117.217552,33.102257],"type":"Point"}
}