{
  "type": "Feature",
  "properties": {
    "iso:country":"US",
    "sg:address":"309 King Ct",
    "sg:city":"Hemet",
    "sg:classifiers":[
        {
            "category":"Manufacturing",
            "subcategory":"Retail Goods",
            "type":"Manufacturing & Wholesale Goods"
        }
    ],
    "sg:phone":"+1 951 766 9081",
    "sg:postcode":"92543",
    "sg:province":"CA",
    "sg:tags":[
        "manufacturer"
    ],
    "wof:name":"Under Cover Extreme",
    "wof:placetype":"venue"
},
  "geometry": {"coordinates":[-116.967164,33.726857],"type":"Point"}
}