{
  "type": "Feature",
  "properties": {
    "iso:country":"US",
    "sg:address":"4810 N Blackstone Ave",
    "sg:city":"Fresno",
    "sg:classifiers":[
        {
            "category":"Autos & Motor Vehicles",
            "subcategory":"Automobile Sales",
            "type":"Retail Goods"
        }
    ],
    "sg:phone":"+1 559 222 4988",
    "sg:postcode":"93726",
    "sg:province":"CA",
    "sg:tags":[
        "classic"
    ],
    "wof:name":"Parisi's Classic Cars",
    "wof:placetype":"venue"
},
  "geometry": {"coordinates":[-119.790365,36.806526],"type":"Point"}
}