{
  "type": "Feature",
  "properties": {
    "iso:country":"US",
    "sg:address":"25715 Redlands Blvd",
    "sg:city":"Redlands",
    "sg:classifiers":[
        {
            "category":"Restaurant",
            "type":"Food & Drink"
        }
    ],
    "sg:menulink":"http://www.allmenus.com/ca/san-bernardino/74083-dominos-pizza/menu/",
    "sg:phone":"+1 909 796 1100",
    "sg:postcode":"92373",
    "sg:province":"CA",
    "sg:tags":[
        "american",
        "wing",
        "pizza"
    ],
    "wof:name":"Domino's Pizza",
    "wof:placetype":"venue"
},
  "geometry": {"coordinates":[-117.24336099999999,34.062744],"type":"Point"}
}