{
  "type": "Feature",
  "properties": {
    "iso:country":"US",
    "sg:address":"1012 E Ave J",
    "sg:city":"Lancaster",
    "sg:classifiers":[
        {
            "category":"Shopping",
            "type":"Retail Goods"
        }
    ],
    "sg:phone":"+1 661 951 6383",
    "sg:postcode":"93535",
    "sg:province":"CA",
    "sg:tags":[
        "telephone",
        "cellular"
    ],
    "sg:website":"www.cingular.com",
    "wof:name":"Pacific West Wireless",
    "wof:placetype":"venue"
},
  "geometry": {"coordinates":[-118.111097,34.689351],"type":"Point"}
}