{
  "type": "Feature",
  "properties": {
    "iso:country":"US",
    "sg:address":"106 Tide Ave",
    "sg:city":"Monterey",
    "sg:classifiers":[
        {
            "category":"Social Services",
            "subcategory":"Job Training",
            "type":"Services"
        }
    ],
    "sg:phone":"+1 831 649 1314",
    "sg:postcode":"93940",
    "sg:province":"CA",
    "sg:tags":[
        "consultant"
    ],
    "wof:name":"William J Tarantino",
    "wof:placetype":"venue"
},
  "geometry": {"coordinates":[-121.86856299999999,36.604581],"type":"Point"}
}