{
  "type": "Feature",
  "properties": {
    "addr:full":"3335 Balmoral Dr Sacramento CA 95821",
    "addr:housenumber":"3335",
    "addr:postcode":"95821",
    "addr:street":"Balmoral Dr",
    "iso:country":"US",
    "sg:address":"3335 Balmoral Dr",
    "sg:city":"Sacramento",
    "sg:classifiers":[
        {
            "category":"Shopping",
            "subcategory":"Photographic Equipment",
            "type":"Retail Goods"
        }
    ],
    "sg:phone":"+1 800 304 3435",
    "sg:postcode":"95821",
    "sg:province":"CA",
    "sg:tags":[
        "supply"
    ],
    "wof:name":"Pardee Cameras Inc.",
    "wof:placetype":"venue"
},
  "geometry": {"coordinates":[-121.385722,38.611678],"type":"Point"}
}