{
  "type": "Feature",
  "properties": {
    "iso:country":"US",
    "sg:address":"3410 S Vickie Ct",
    "sg:city":"Visalia",
    "sg:classifiers":[
        {
            "category":"Farming",
            "subcategory":"Farm & Veterinary Services",
            "type":"Manufacturing & Wholesale Goods"
        }
    ],
    "sg:phone":"+1 559 625 8217",
    "sg:postcode":"93277",
    "sg:province":"CA",
    "sg:tags":[
        "labor",
        "contractor"
    ],
    "wof:name":"Ignacio L Zazueta Jr",
    "wof:placetype":"venue"
},
  "geometry": {"coordinates":[-119.323154,36.300319],"type":"Point"}
}