{
  "type": "Feature",
  "properties": {
    "addr:full":"27120 Cabot Road Laguna Hills CA 92653",
    "addr:housenumber":"27120",
    "addr:postcode":"92653",
    "addr:street":"Cabot Road",
    "iso:country":"US",
    "sg:address":"27120 Cabot Road",
    "sg:city":"Laguna Hills",
    "sg:classifiers":[
        {
            "category":"Autos & Motor Vehicles",
            "subcategory":"Auto Supplies",
            "type":"Retail Goods"
        }
    ],
    "sg:phone":"+1 949 348 8473",
    "sg:postcode":"92653",
    "sg:province":"CA",
    "sg:tags":[
        "tire"
    ],
    "wof:name":"Amato Tire & Service",
    "wof:placetype":"venue"
},
  "geometry": {"coordinates":[-117.6746,33.574042],"type":"Point"}
}