{
  "type": "Feature",
  "properties": {
    "iso:country":"US",
    "sg:address":"14150 Segundo Ct",
    "sg:city":"Poway",
    "sg:classifiers":[
        {
            "category":"Real Estate",
            "subcategory":"Real Estate Agent",
            "type":"Services"
        }
    ],
    "sg:phone":"+1 858 748 1017",
    "sg:postcode":"92064",
    "sg:province":"CA",
    "wof:name":"Sinacore & Assoc Realty",
    "wof:placetype":"venue"
},
  "geometry": {"coordinates":[-117.024688,32.97954],"type":"Point"}
}