{
  "type": "Feature",
  "properties": {
    "iso:country":"US",
    "sg:address":"2086 Newpark Mall",
    "sg:city":"Newark",
    "sg:classifiers":[
        {
            "category":"Restaurant",
            "type":"Food & Drink"
        }
    ],
    "sg:menulink":"http://www.allmenus.com/ca/fremont/193654-manchu-wok/menu/",
    "sg:phone":"+1 510 791 6406",
    "sg:postcode":"94560",
    "sg:province":"CA",
    "sg:tags":[
        "asian",
        "chinese"
    ],
    "wof:name":"Manchu Wok",
    "wof:placetype":"venue"
},
  "geometry": {"coordinates":[-122.001385,37.528308],"type":"Point"}
}