{
  "type": "Feature",
  "properties": {
    "addr:full":"2781 Bechelli Ln Redding CA 96002",
    "addr:housenumber":"2781",
    "addr:postcode":"96002",
    "addr:street":"Bechelli Ln",
    "iso:country":"US",
    "sg:address":"2781 Bechelli Ln",
    "sg:city":"Redding",
    "sg:classifiers":[
        {
            "category":"Shopping",
            "subcategory":"Jewelry",
            "type":"Retail Goods"
        }
    ],
    "sg:phone":"+1 530 222 4561",
    "sg:postcode":"96002",
    "sg:province":"CA",
    "sg:tags":[
        "gold",
        "mfg"
    ],
    "wof:name":"Lady Goldsmith",
    "wof:placetype":"venue"
},
  "geometry": {"coordinates":[-122.362481,40.565247],"type":"Point"}
}