{
  "type": "Feature",
  "properties": {
    "addr:full":"1945 W Commonwealth Ave Ste K Fullerton CA 92833",
    "addr:housenumber":"1945",
    "addr:postcode":"92833",
    "addr:street":"W Commonwealth Ave Ste K",
    "iso:country":"US",
    "sg:address":"1945 W Commonwealth Ave Ste K",
    "sg:city":"Fullerton",
    "sg:classifiers":[
        {
            "category":"Professional",
            "subcategory":"Detective & Security Services",
            "type":"Services"
        }
    ],
    "sg:phone":"+1 877 714 0800",
    "sg:postcode":"92833",
    "sg:province":"CA",
    "sg:tags":[
        "system"
    ],
    "sg:website":"www.aceorangecounty.com",
    "wof:name":"ACE Security Laminates Orange County Inc.",
    "wof:placetype":"venue"
},
  "geometry": {"coordinates":[-117.96540400000001,33.870089],"type":"Point"}
}