{
  "type": "Feature",
  "properties": {
    "iso:country":"US",
    "sg:address":"100 South Murphy Ave",
    "sg:city":"Sunnyvale",
    "sg:classifiers":[
        {
            "category":"Retail",
            "subcategory":"Event Space",
            "type":"Services"
        }
    ],
    "sg:phone":"+1 408 735 7680",
    "sg:postcode":"94086",
    "sg:province":"CA",
    "sg:tags":[
        "venue"
    ],
    "sg:website":"www.thehistoricdelmonte.com/",
    "wof:name":"Historic Del Monte Building",
    "wof:placetype":"venue"
},
  "geometry": {"coordinates":[-122.029651,37.377346],"type":"Point"}
}