{
  "type": "Feature",
  "properties": {
    "iso:country":"US",
    "sg:address":"7579 Melrose Ave",
    "sg:city":"Los Angeles",
    "sg:classifiers":[
        {
            "category":"Shopping",
            "subcategory":"Used Merchandise",
            "type":"Retail Goods"
        }
    ],
    "sg:phone":"+1 323 655 6769",
    "sg:postcode":"90046",
    "sg:province":"CA",
    "sg:tags":[
        "clothing"
    ],
    "wof:name":"Aaardvark's Odd Ark",
    "wof:placetype":"venue"
},
  "geometry": {"coordinates":[-118.354731,34.083738],"type":"Point"}
}