{
  "type": "Feature",
  "properties": {
    "iso:country":"US",
    "sg:address":"1921 Glenhaven Ave",
    "sg:city":"Walnut Creek",
    "sg:classifiers":[
        {
            "category":"Health Services",
            "subcategory":"Health Practitioner",
            "type":"Services"
        }
    ],
    "sg:phone":"+1 925 932 4664",
    "sg:postcode":"94595",
    "sg:province":"CA",
    "sg:tags":[
        "psychologist"
    ],
    "wof:name":"Norman Cavior PHD",
    "wof:placetype":"venue"
},
  "geometry": {"coordinates":[-122.05973899999999,37.882765],"type":"Point"}
}