{
  "type": "Feature",
  "properties": {
    "iso:country":"US",
    "sg:address":"1172 Great Mall Dr",
    "sg:city":"Milpitas",
    "sg:classifiers":[
        {
            "category":"Shopping",
            "subcategory":"Clothing, Apparel, & Fashions",
            "type":"Retail Goods"
        }
    ],
    "sg:phone":"+1 408 956 1498",
    "sg:postcode":"95035",
    "sg:province":"CA",
    "sg:tags":[
        "children's",
        "men's",
        "clothing",
        "women's"
    ],
    "wof:name":"Old Navy Clothing Company",
    "wof:placetype":"venue"
},
  "geometry": {"coordinates":[-121.897003,37.419498],"type":"Point"}
}