{
  "type": "Feature",
  "properties": {
    "addr:full":"224 18th St Pacific Grove CA 93950",
    "addr:housenumber":"224",
    "addr:postcode":"93950",
    "addr:street":"18Th St",
    "iso:country":"US",
    "sg:address":"224 18th St",
    "sg:city":"Pacific Grove",
    "sg:classifiers":[
        {
            "category":"Building & Trades",
            "subcategory":"Landscaping Services",
            "type":"Services"
        }
    ],
    "sg:phone":"+1 831 648 1407",
    "sg:postcode":"93950",
    "sg:province":"CA",
    "sg:tags":[
        "landscape",
        "contractor"
    ],
    "wof:name":"Garden Way",
    "wof:placetype":"venue"
},
  "geometry": {"coordinates":[-121.919872,36.620654],"type":"Point"}
}