{
  "type": "Feature",
  "properties": {
    "iso:country":"US",
    "sg:address":"160 Main St",
    "sg:city":"Los Altos",
    "sg:classifiers":[
        {
            "category":"Travel",
            "subcategory":"Travel Agent",
            "type":"Entertainment"
        }
    ],
    "sg:phone":"+1 650 941 5810",
    "sg:postcode":"94022",
    "sg:province":"CA",
    "sg:tags":[
        "agency",
        "bureau"
    ],
    "sg:website":"www.allhorizonstvl.com",
    "wof:name":"All Horizons Rancho Travel",
    "wof:placetype":"venue"
},
  "geometry": {"coordinates":[-122.114912,37.379712],"type":"Point"}
}