{
  "type": "Feature",
  "properties": {
    "addr:full":"1122 Joellis Way Sacramento CA 95815",
    "addr:housenumber":"1122",
    "addr:postcode":"95815",
    "addr:street":"Joellis Way",
    "iso:country":"US",
    "sg:address":"1122 Joellis Way",
    "sg:city":"Sacramento",
    "sg:classifiers":[
        {
            "category":"Wholesale",
            "subcategory":"Construction Materials",
            "type":"Manufacturing & Wholesale Goods"
        }
    ],
    "sg:phone":"+1 916 927 2727",
    "sg:postcode":"95815",
    "sg:province":"CA",
    "sg:tags":[
        "lumber"
    ],
    "sg:website":"www.higlum.com",
    "wof:name":"J E Higgins Lumber Co",
    "wof:placetype":"venue"
},
  "geometry": {"coordinates":[-121.44360399999999,38.601309],"type":"Point"}
}