{
  "type": "Feature",
  "properties": {
    "iso:country":"US",
    "sg:address":"1834 W 1st St",
    "sg:city":"Santa Ana",
    "sg:classifiers":[
        {
            "category":"Retail",
            "subcategory":"Auto Repair",
            "type":"Services"
        }
    ],
    "sg:phone":"+1 714 547 1628",
    "sg:postcode":"92703",
    "sg:province":"CA",
    "sg:tags":[
        "muffler",
        "exhaust",
        "system"
    ],
    "wof:name":"7-Day Auto",
    "wof:placetype":"venue"
},
  "geometry": {"coordinates":[-117.894687,33.745309],"type":"Point"}
}