{
  "type": "Feature",
  "properties": {
    "iso:country":"US",
    "sg:address":"8687 Melrose Ave",
    "sg:city":"Los Angeles",
    "sg:classifiers":[
        {
            "category":"Home & Garden",
            "subcategory":"Furniture",
            "type":"Retail Goods"
        }
    ],
    "sg:phone":"+1 310 854 7204",
    "sg:postcode":"90069",
    "sg:province":"CA",
    "sg:tags":[
        "builder",
        "custom"
    ],
    "wof:name":"Bernhardt Contract Furniture",
    "wof:placetype":"venue"
},
  "geometry": {"coordinates":[-118.38305800000001,34.081384],"type":"Point"}
}