{
  "type": "Feature",
  "properties": {
    "iso:country":"US",
    "sg:address":"966 Elizabeth Dr",
    "sg:city":"Santa Clara",
    "sg:classifiers":[
        {
            "category":"Arts & Performance",
            "subcategory":"Theater",
            "type":"Entertainment"
        }
    ],
    "sg:phone":"+1 408 243 1038",
    "sg:postcode":"95050",
    "sg:province":"CA",
    "sg:tags":[
        "performing",
        "magician"
    ],
    "wof:name":"Blashek the Magician",
    "wof:placetype":"venue"
},
  "geometry": {"coordinates":[-121.96700300000001,37.344501],"type":"Point"}
}