{
  "type": "Feature",
  "properties": {
    "iso:country":"US",
    "sg:address":"8062 Garvey Ave",
    "sg:city":"Rosemead",
    "sg:classifiers":[
        {
            "category":"Shopping",
            "type":"Retail Goods"
        }
    ],
    "sg:phone":"+1 626 288 0836",
    "sg:postcode":"91770",
    "sg:province":"CA",
    "sg:tags":[
        "pet",
        "tropical",
        "fish",
        "store"
    ],
    "wof:name":"Garvey Fish & Pet",
    "wof:placetype":"venue"
},
  "geometry": {"coordinates":[-118.093002,34.0625],"type":"Point"}
}