{
  "type": "Feature",
  "properties": {
    "iso:country":"US",
    "sg:address":"4395 Middle Two Rock Rd",
    "sg:city":"Petaluma",
    "sg:classifiers":[
        {
            "category":"Retail",
            "subcategory":"Animal Services",
            "type":"Services"
        }
    ],
    "sg:phone":"+1 707 763 3997",
    "sg:postcode":"94952",
    "sg:province":"CA",
    "wof:name":"Cotati Dog Grooming & Boarding",
    "wof:placetype":"venue"
},
  "geometry": {"coordinates":[-122.750699,38.260724],"type":"Point"}
}