{
  "type": "Feature",
  "properties": {
    "iso:country":"US",
    "sg:address":"14513 S Keene Ave",
    "sg:city":"Compton",
    "sg:classifiers":[
        {
            "category":"Shopping",
            "subcategory":"Optical Goods",
            "type":"Retail Goods"
        }
    ],
    "sg:phone":"+1 310 638 7246",
    "sg:postcode":"90220",
    "sg:province":"CA",
    "wof:name":"Long Vision",
    "wof:placetype":"venue"
},
  "geometry": {"coordinates":[-118.25511400000001,33.89963],"type":"Point"}
}