{
  "type": "Feature",
  "properties": {
    "addr:full":"14535 Mountain Quail Rd Salinas CA 93908",
    "addr:housenumber":"14535",
    "addr:postcode":"93908",
    "addr:street":"Mountain Quail Rd",
    "iso:country":"US",
    "sg:address":"14535 Mountain Quail Rd",
    "sg:city":"Salinas",
    "sg:classifiers":[
        {
            "category":"Building & Trades",
            "subcategory":"Construction",
            "type":"Services"
        }
    ],
    "sg:phone":"+1 831 484 2162",
    "sg:postcode":"93908",
    "sg:province":"CA",
    "sg:tags":[
        "contractor"
    ],
    "wof:name":"SMC & Assoc",
    "wof:placetype":"venue"
},
  "geometry": {"coordinates":[-121.72506799999999,36.574116],"type":"Point"}
}