{
  "type": "Feature",
  "properties": {
    "addr:full":"1420 S el Camino Real San Mateo CA 94402",
    "addr:housenumber":"1420",
    "addr:postcode":"94402",
    "addr:street":"S El Camino Real",
    "iso:country":"US",
    "sg:address":"1420 S el Camino Real",
    "sg:city":"San Mateo",
    "sg:classifiers":[
        {
            "category":"Restaurant",
            "type":"Food & Drink"
        }
    ],
    "sg:phone":"+1 650 349 2878",
    "sg:postcode":"94402",
    "sg:province":"CA",
    "sg:website":"www.mcdonalds.com",
    "wof:name":"Mc Donald's",
    "wof:placetype":"venue"
},
  "geometry": {"coordinates":[-122.316188,37.554018],"type":"Point"}
}