{
  "type": "Feature",
  "properties": {
    "addr:full":"9045 Haven Ave Rancho Cucamonga CA 91730",
    "addr:housenumber":"9045",
    "addr:postcode":"91730",
    "addr:street":"Haven Ave",
    "iso:country":"US",
    "sg:address":"9045 Haven Ave",
    "sg:city":"Rancho Cucamonga",
    "sg:classifiers":[
        {
            "category":"Utilities",
            "subcategory":"Telephone",
            "type":"Services"
        }
    ],
    "sg:phone":"+1 909 948 5700",
    "sg:postcode":"91730",
    "sg:province":"CA",
    "sg:tags":[
        "communications"
    ],
    "wof:name":"Atmc Inc",
    "wof:placetype":"venue"
},
  "geometry": {"coordinates":[-117.57569599999999,34.089195],"type":"Point"}
}