{
  "type": "Feature",
  "properties": {
    "iso:country":"US",
    "sg:address":"1311 S Miller St",
    "sg:city":"Santa Maria",
    "sg:classifiers":[
        {
            "category":"Health Services",
            "subcategory":"Doctor",
            "type":"Services"
        }
    ],
    "sg:phone":"+1 805 928 2598",
    "sg:postcode":"93454",
    "sg:province":"CA",
    "sg:tags":[
        "dentist"
    ],
    "wof:name":"Orthodontic Specialist",
    "wof:placetype":"venue"
},
  "geometry": {"coordinates":[-120.431731,34.938302],"type":"Point"}
}