{
  "type": "Feature",
  "properties": {
    "addr:full":"94 Estaban Dr Camarillo CA 93010",
    "addr:housenumber":"94",
    "addr:postcode":"93010",
    "addr:street":"Estaban Dr",
    "iso:country":"US",
    "sg:address":"94 Estaban Dr",
    "sg:city":"Camarillo",
    "sg:classifiers":[
        {
            "category":"Manufacturing",
            "subcategory":"Electronics",
            "type":"Manufacturing & Wholesale Goods"
        }
    ],
    "sg:phone":"+1 805 388 1299",
    "sg:postcode":"93010",
    "sg:province":"CA",
    "sg:tags":[
        "elect",
        "boards",
        "for",
        "mfg",
        "equipment",
        "printed",
        "circuit",
        "test"
    ],
    "wof:name":"Methode of California Inc",
    "wof:placetype":"venue"
},
  "geometry": {"coordinates":[-119.06215,34.242284],"type":"Point"}
}