{
  "type": "Feature",
  "properties": {
    "addr:full":"142 N Milpitas Blvd Milpitas CA 95035",
    "addr:housenumber":"142",
    "addr:postcode":"95035",
    "addr:street":"N Milpitas Blvd",
    "iso:country":"US",
    "sg:address":"142 N Milpitas Blvd",
    "sg:city":"Milpitas",
    "sg:classifiers":[
        {
            "category":"Personal",
            "type":"Services"
        }
    ],
    "sg:phone":"+1 408 701 2452",
    "sg:postcode":"95035",
    "sg:province":"CA",
    "sg:tags":[
        "towing"
    ],
    "sg:website":"www.theautotowing.com/Milpitas/",
    "wof:name":"24 Hour Towing",
    "wof:placetype":"venue"
},
  "geometry": {"coordinates":[-121.900803,37.435452],"type":"Point"}
}