{
  "type": "Feature",
  "properties": {
    "iso:country":"US",
    "sg:address":"1628 Hostetter Rd Ste A",
    "sg:city":"San Jose",
    "sg:classifiers":[
        {
            "category":"Retail",
            "subcategory":"Laundry & Dry Cleaning",
            "type":"Services"
        }
    ],
    "sg:phone":"+1 408 452 0297",
    "sg:postcode":"95131",
    "sg:province":"CA",
    "wof:name":"Lundy Dry Cleaners",
    "wof:placetype":"venue"
},
  "geometry": {"coordinates":[-121.88400300000001,37.387699],"type":"Point"}
}