{
  "type": "Feature",
  "properties": {
    "iso:country":"US",
    "sg:address":"4118 W 183rd St",
    "sg:city":"Torrance",
    "sg:classifiers":[
        {
            "category":"Real Estate",
            "subcategory":"Architect",
            "type":"Services"
        }
    ],
    "sg:phone":"+1 310 370 6121",
    "sg:postcode":"90504",
    "sg:province":"CA",
    "sg:tags":[
        "architects'",
        "specification",
        "construction",
        "builders'",
        "architectural"
    ],
    "wof:name":"Cadmeister",
    "wof:placetype":"venue"
},
  "geometry": {"coordinates":[-118.346198,33.864774],"type":"Point"}
}