{
  "type": "Feature",
  "properties": {
    "addr:full":"1417 Drake Ave Burlingame CA 94010",
    "addr:housenumber":"1417",
    "addr:postcode":"94010",
    "addr:street":"Drake Ave",
    "iso:country":"US",
    "sg:address":"1417 Drake Ave",
    "sg:city":"Burlingame",
    "sg:classifiers":[
        {
            "category":"Professional",
            "type":"Services"
        }
    ],
    "sg:phone":"+1 650 340 8154",
    "sg:postcode":"94010",
    "sg:province":"CA",
    "wof:name":"Patrick Somers Co",
    "wof:placetype":"venue"
},
  "geometry": {"coordinates":[-122.377042,37.58603],"type":"Point"}
}