{
  "type": "Feature",
  "properties": {
    "iso:country":"US",
    "sg:address":"2450 Main St",
    "sg:city":"Cambria",
    "sg:classifiers":[
        {
            "category":"Real Estate",
            "subcategory":"Architect",
            "type":"Services"
        }
    ],
    "sg:phone":"+1 805 783 2712",
    "sg:postcode":"93428",
    "sg:province":"CA",
    "sg:tags":[
        "home",
        "planning",
        "design"
    ],
    "wof:name":"David Einung Residential Dsgn",
    "wof:placetype":"venue"
},
  "geometry": {"coordinates":[-121.078765,35.566209],"type":"Point"}
}