{
  "type": "Feature",
  "properties": {
    "addr:full":"2667 E 28th St Signal Hill CA 90755",
    "addr:housenumber":"2667",
    "addr:postcode":"90755",
    "addr:street":"E 28Th St",
    "iso:country":"US",
    "sg:address":"2667 E 28th St",
    "sg:city":"Signal Hill",
    "sg:classifiers":[
        {
            "category":"Restaurant",
            "type":"Food & Drink"
        }
    ],
    "sg:phone":"+1 562 981 8300",
    "sg:postcode":"90755",
    "sg:province":"CA",
    "sg:tags":[
        "caterer"
    ],
    "sg:website":"www.thebigthrill.net",
    "wof:name":"Blueberry Hill",
    "wof:placetype":"venue"
},
  "geometry": {"coordinates":[-118.160004,33.808102],"type":"Point"}
}