{
  "type": "Feature",
  "properties": {
    "addr:full":"739 A St San Rafael CA 94901",
    "addr:housenumber":"739",
    "addr:postcode":"94901",
    "addr:street":"A St",
    "iso:country":"US",
    "sg:address":"739 A St",
    "sg:city":"San Rafael",
    "sg:classifiers":[
        {
            "category":"Personal",
            "subcategory":"Barber",
            "type":"Services"
        }
    ],
    "sg:phone":"+1 415 453 3900",
    "sg:postcode":"94901",
    "sg:province":"CA",
    "wof:name":"Nigel's",
    "wof:placetype":"venue"
},
  "geometry": {"coordinates":[-122.528628,37.971005],"type":"Point"}
}