{
  "type": "Feature",
  "properties": {
    "iso:country":"US",
    "sg:address":"812 W 22nd St",
    "sg:city":"Merced",
    "sg:classifiers":[
        {
            "category":"Professional",
            "subcategory":"Research",
            "type":"Services"
        }
    ],
    "sg:phone":"+1 209 722 4558",
    "sg:postcode":"95340",
    "sg:province":"CA",
    "sg:tags":[
        "environmental",
        "ecological"
    ],
    "wof:name":"Pitman Marsh Consultant",
    "wof:placetype":"venue"
},
  "geometry": {"coordinates":[-120.486401,37.308502],"type":"Point"}
}