{
  "type": "Feature",
  "properties": {
    "iso:country":"US",
    "sg:address":"5411 Avenida Encinas # 210",
    "sg:city":"Carlsbad",
    "sg:classifiers":[
        {
            "category":"Wholesale",
            "subcategory":"Medical Equipment & Supplies",
            "type":"Manufacturing & Wholesale Goods"
        },
        {
            "category":"Shopping",
            "subcategory":"Pharmacy",
            "type":"Retail Goods"
        }
    ],
    "sg:phone":"+1 760 729 5199",
    "sg:postcode":"92008",
    "sg:province":"CA",
    "sg:tags":[
        "home",
        "health",
        "care"
    ],
    "wof:name":"Care A Van Transport",
    "wof:placetype":"venue"
},
  "geometry": {"coordinates":[-117.32515600000001,33.126429],"type":"Point"}
}