{
  "type": "Feature",
  "properties": {
    "addr:full":"717 Robinhood Ln Redlands CA 92373",
    "addr:housenumber":"717",
    "addr:postcode":"92373",
    "addr:street":"Robinhood Ln",
    "iso:country":"US",
    "sg:address":"717 Robinhood Ln",
    "sg:city":"Redlands",
    "sg:classifiers":[
        {
            "category":"Building & Trades",
            "subcategory":"Construction",
            "type":"Services"
        }
    ],
    "sg:phone":"+1 951 543 2412",
    "sg:postcode":"92373",
    "sg:province":"CA",
    "sg:tags":[
        "builder",
        "patio",
        "deck"
    ],
    "wof:name":"Patios By Design",
    "wof:placetype":"venue"
},
  "geometry": {"coordinates":[-117.18992,34.036783],"type":"Point"}
}