{
  "type": "Feature",
  "properties": {
    "iso:country":"US",
    "sg:address":"6051 Sunburst St",
    "sg:city":"Joshua Tree",
    "sg:classifiers":[
        {
            "category":"Education",
            "subcategory":"School",
            "type":"Public Place"
        }
    ],
    "sg:phone":"+1 760 366 8459",
    "sg:postcode":"92252",
    "sg:province":"CA",
    "wof:name":"Joshua Tree Elementary School",
    "wof:placetype":"venue"
},
  "geometry": {"coordinates":[-116.308546,34.143348],"type":"Point"}
}