{
  "type": "Feature",
  "properties": {
    "addr:full":"6051 Sunburst St Joshua Tree CA 92252",
    "addr:housenumber":"6051",
    "addr:postcode":"92252",
    "addr:street":"Sunburst St",
    "iso:country":"US",
    "sg:address":"6051 Sunburst St",
    "sg:city":"Joshua Tree",
    "sg:classifiers":[
        {
            "category":"Education",
            "subcategory":"School",
            "type":"Public Place"
        }
    ],
    "sg:phone":"+1 760 366 8459",
    "sg:postcode":"92252",
    "sg:province":"CA",
    "wof:name":"Joshua Tree Elementary School",
    "wof:placetype":"venue"
},
  "geometry": {"coordinates":[-116.30854600000001,34.143348],"type":"Point"}
}