{
  "type": "Feature",
  "properties": {
    "addr:full":"38989 Cherry Valley Blvd Cherry Valley CA 92223",
    "addr:housenumber":"38989",
    "addr:postcode":"92223",
    "addr:street":"Cherry Valley Blvd",
    "iso:country":"US",
    "sg:address":"38989 Cherry Valley Blvd",
    "sg:city":"Cherry Valley",
    "sg:classifiers":[
        {
            "category":"Wholesale",
            "subcategory":"Farm Supplies",
            "type":"Manufacturing & Wholesale Goods"
        }
    ],
    "sg:phone":"+1 951 845 6079",
    "sg:postcode":"92223",
    "sg:province":"CA",
    "sg:tags":[
        "feed"
    ],
    "wof:name":"All Season's Hay Co",
    "wof:placetype":"venue"
},
  "geometry": {"coordinates":[-116.985446,33.968666],"type":"Point"}
}