{
  "type": "Feature",
  "properties": {
    "iso:country":"US",
    "sg:address":"22123 Ventura Blvd",
    "sg:city":"Woodland Hills",
    "sg:classifiers":[
        {
            "category":"Autos & Motor Vehicles",
            "subcategory":"Motorcycle Sales",
            "type":"Retail Goods"
        }
    ],
    "sg:phone":"+1 818 348 7865",
    "sg:postcode":"91364",
    "sg:province":"CA",
    "wof:name":"Kolbe Honda Motorcycle Sales",
    "wof:placetype":"venue"
},
  "geometry": {"coordinates":[-118.610001,34.168598],"type":"Point"}
}