{
  "type": "Feature",
  "properties": {
    "addr:full":"3000 E la Palma Ave Anaheim CA 92806",
    "addr:housenumber":"3000",
    "addr:postcode":"92806",
    "addr:street":"E La Palma Ave",
    "iso:country":"US",
    "sg:address":"3000 E la Palma Ave",
    "sg:city":"Anaheim",
    "sg:classifiers":[
        {
            "category":"Airport",
            "type":"Transportation"
        }
    ],
    "sg:phone":"+1 714 237 9227",
    "sg:postcode":"92806",
    "sg:province":"CA",
    "wof:name":"Super Airway Express",
    "wof:placetype":"venue"
},
  "geometry": {"coordinates":[-117.86042,33.850349],"type":"Point"}
}