{
  "type": "Feature",
  "properties": {
    "addr:full":"1 N San Antonio Rd Los Altos CA 94022",
    "addr:housenumber":"1",
    "addr:postcode":"94022",
    "addr:street":"N San Antonio Rd",
    "iso:country":"US",
    "sg:address":"1 N San Antonio Rd",
    "sg:city":"Los Altos",
    "sg:classifiers":[
        {
            "category":"Government",
            "subcategory":"Court House",
            "type":"Public Place"
        }
    ],
    "sg:phone":"+1 650 947 2710",
    "sg:postcode":"94022",
    "sg:province":"CA",
    "sg:tags":[
        "city",
        "counsel"
    ],
    "wof:name":"Los Altos City Attorney",
    "wof:placetype":"venue"
},
  "geometry": {"coordinates":[-122.11405000000001,37.383269],"type":"Point"}
}