{
  "type": "Feature",
  "properties": {
    "addr:full":"505 N Tustin Ave Santa Ana CA 92705",
    "addr:housenumber":"505",
    "addr:postcode":"92705",
    "addr:street":"N Tustin Ave",
    "iso:country":"US",
    "sg:address":"505 N Tustin Ave",
    "sg:city":"Santa Ana",
    "sg:classifiers":[
        {
            "category":"Communications",
            "subcategory":"Film & Video Production",
            "type":"Services"
        }
    ],
    "sg:phone":"+1 714 550 0925",
    "sg:postcode":"92705",
    "sg:province":"CA",
    "sg:tags":[
        "editing"
    ],
    "wof:name":"Dv Post",
    "wof:placetype":"venue"
},
  "geometry": {"coordinates":[-117.83406600000001,33.748402],"type":"Point"}
}