{
  "type": "Feature",
  "properties": {
    "iso:country":"US",
    "sg:address":"19845 Cabot Blvd",
    "sg:city":"Hayward",
    "sg:classifiers":[
        {
            "category":"Retail",
            "subcategory":"Auto Repair",
            "type":"Services"
        }
    ],
    "sg:phone":"+1 510 786 0851",
    "sg:postcode":"94545",
    "sg:province":"CA",
    "sg:website":"www.prmotorsports.com",
    "wof:name":"P R Motorsports",
    "wof:placetype":"venue"
},
  "geometry": {"coordinates":[-122.138706,37.653236],"type":"Point"}
}