{
  "type": "Feature",
  "properties": {
    "addr:full":"Beverly Center USA 8500 Beverly Blvd Los Angeles CA 90048",
    "addr:housenumber":"8500",
    "addr:postcode":"90048",
    "addr:street":"Beverly Blvd",
    "iso:country":"US",
    "sg:address":"Beverly Center USA 8500 Beverly Blvd",
    "sg:city":"Los Angeles",
    "sg:classifiers":[
        {
            "category":"Shopping",
            "subcategory":"Clothing, Apparel, & Fashions",
            "type":"Retail Goods"
        },
        {
            "category":"Shopping",
            "subcategory":"Luggage & Leather Goods",
            "type":"Retail Goods"
        }
    ],
    "sg:phone":"+1 310 360 1506",
    "sg:postcode":"90048",
    "sg:province":"CA",
    "sg:tags":[
        "accessory",
        "clothing",
        "women's"
    ],
    "sg:website":"www.beverlycenter.com/IM/storede...",
    "wof:name":"Louis Vuitton",
    "wof:placetype":"venue"
},
  "geometry": {"coordinates":[-118.376608,34.075945],"type":"Point"}
}