{
  "type": "Feature",
  "properties": {
    "iso:country":"US",
    "sg:address":"1481 Mary Ct",
    "sg:city":"Exeter",
    "sg:classifiers":[
        {
            "category":"Shopping",
            "subcategory":"Florist",
            "type":"Retail Goods"
        }
    ],
    "sg:phone":"+1 559 592 5055",
    "sg:postcode":"93221",
    "sg:province":"CA",
    "sg:tags":[
        "plant"
    ],
    "wof:name":"Plants R Us",
    "wof:placetype":"venue"
},
  "geometry": {"coordinates":[-119.161417,36.30016],"type":"Point"}
}