{
  "type": "Feature",
  "properties": {
    "iso:country":"US",
    "sg:address":"179 Boatyard Dr",
    "sg:city":"Fort Bragg",
    "sg:classifiers":[
        {
            "category":"Restaurant",
            "type":"Food & Drink"
        }
    ],
    "sg:menulink":"http://www.allmenus.com/ca/fort-bragg/77847-papa-murphys/menu/",
    "sg:phone":"+1 707 961 0777",
    "sg:postcode":"95437",
    "sg:province":"CA",
    "sg:tags":[
        "american",
        "pizza"
    ],
    "wof:name":"Papa Murphy's",
    "wof:placetype":"venue"
},
  "geometry": {"coordinates":[-123.80616499999999,39.423413],"type":"Point"}
}