{
  "type": "Feature",
  "properties": {
    "addr:full":"1822 Chestnut Ave Long Beach CA 90806",
    "addr:housenumber":"1822",
    "addr:postcode":"90806",
    "addr:street":"Chestnut Ave",
    "iso:country":"US",
    "sg:address":"1822 Chestnut Ave",
    "sg:city":"Long Beach",
    "sg:classifiers":[
        {
            "category":"Home & Garden",
            "subcategory":"Furniture",
            "type":"Retail Goods"
        }
    ],
    "sg:phone":"+1 562 218 5013",
    "sg:postcode":"90806",
    "sg:province":"CA",
    "wof:name":"C & E Furniture Installation",
    "wof:placetype":"venue"
},
  "geometry": {"coordinates":[-118.19627699999999,33.791263],"type":"Point"}
}