{
  "type": "Feature",
  "properties": {
    "iso:country":"US",
    "sg:address":"28985 Golden Lantern",
    "sg:city":"Laguna Niguel",
    "sg:classifiers":[
        {
            "category":"Restaurant",
            "type":"Food & Drink"
        }
    ],
    "sg:phone":"+1 949 363 7400",
    "sg:postcode":"92677",
    "sg:province":"CA",
    "wof:name":"Bento Box",
    "wof:placetype":"venue"
},
  "geometry": {"coordinates":[-117.691979,33.543092],"type":"Point"}
}