{
  "type": "Feature",
  "properties": {
    "addr:full":"14526 Erwin St Van Nuys CA 91411",
    "addr:housenumber":"14526",
    "addr:postcode":"91411",
    "addr:street":"Erwin St",
    "iso:country":"US",
    "sg:address":"14526 Erwin St",
    "sg:city":"Van Nuys",
    "sg:classifiers":[
        {
            "category":"Retail",
            "subcategory":"Auto Repair",
            "type":"Services"
        }
    ],
    "sg:phone":"+1 818 901 1113",
    "sg:postcode":"91411",
    "sg:province":"CA",
    "sg:tags":[
        "repairing",
        "automobile"
    ],
    "wof:name":"Auto Aid & Rescue",
    "wof:placetype":"venue"
},
  "geometry": {"coordinates":[-118.450417,34.183561],"type":"Point"}
}