{
  "type": "Feature",
  "properties": {
    "addr:full":"14420 Civic Dr Victorville CA 92392",
    "addr:housenumber":"14420",
    "addr:postcode":"92392",
    "addr:street":"Civic Dr",
    "iso:country":"US",
    "sg:address":"14420 Civic Dr",
    "sg:city":"Victorville",
    "sg:classifiers":[
        {
            "category":"Professional",
            "subcategory":"Lawyer & Legal Services",
            "type":"Services"
        }
    ],
    "sg:phone":"+1 760 243 5385",
    "sg:postcode":"92392",
    "sg:province":"CA",
    "sg:tags":[
        "attorney"
    ],
    "wof:name":"David W Brown Law Offices",
    "wof:placetype":"venue"
},
  "geometry": {"coordinates":[-117.323723,34.512827],"type":"Point"}
}