{
  "type": "Feature",
  "properties": {
    "iso:country":"US",
    "sg:address":"1970 Avalon St",
    "sg:city":"Los Angeles",
    "sg:classifiers":[
        {
            "category":"Retail",
            "subcategory":"Repair Shop",
            "type":"Services"
        }
    ],
    "sg:phone":"+1 213 698 8288",
    "sg:postcode":"90039",
    "sg:province":"CA",
    "sg:tags":[
        "related"
    ],
    "wof:name":"Oni's Typewriter Repair",
    "wof:placetype":"venue"
},
  "geometry": {"coordinates":[-118.25631,34.088026],"type":"Point"}
}