{
  "type": "Feature",
  "properties": {
    "addr:full":"116 Miller Way Folsom CA 95630",
    "addr:housenumber":"116",
    "addr:postcode":"95630",
    "addr:street":"Miller Way",
    "iso:country":"US",
    "sg:address":"116 Miller Way",
    "sg:city":"Folsom",
    "sg:classifiers":[
        {
            "category":"Manufacturing",
            "subcategory":"Petroleum Products",
            "type":"Manufacturing & Wholesale Goods"
        }
    ],
    "sg:phone":"+1 916 989 0684",
    "sg:postcode":"95630",
    "sg:province":"CA",
    "sg:tags":[
        "contract"
    ],
    "wof:name":"Harris Manufacturing J. R.",
    "wof:placetype":"venue"
},
  "geometry": {"coordinates":[-121.188779,38.694838],"type":"Point"}
}