{
  "type": "Feature",
  "properties": {
    "addr:full":"444 S Kingsley Dr Los Angeles CA 90020",
    "addr:housenumber":"444",
    "addr:postcode":"90020",
    "addr:street":"S Kingsley Dr",
    "iso:country":"US",
    "sg:address":"444 S Kingsley Dr",
    "sg:city":"Los Angeles",
    "sg:classifiers":[
        {
            "category":"Professional",
            "subcategory":"Art Services",
            "type":"Services"
        }
    ],
    "sg:phone":"+1 213 384 8986",
    "sg:postcode":"90020",
    "sg:province":"CA",
    "sg:tags":[
        "graphic",
        "designer"
    ],
    "wof:name":"Yippeez",
    "wof:placetype":"venue"
},
  "geometry": {"coordinates":[-118.30277700000001,34.066188],"type":"Point"}
}