{
  "type": "Feature",
  "properties": {
    "addr:full":"201 Capitola Avenue Capitola CA 95010",
    "addr:housenumber":"201",
    "addr:postcode":"95010",
    "addr:street":"Capitola Avenue",
    "iso:country":"US",
    "sg:address":"201 Capitola Avenue",
    "sg:city":"Capitola",
    "sg:classifiers":[
        {
            "category":"Shopping",
            "type":"Retail Goods"
        }
    ],
    "sg:phone":"+1 831 476 7566",
    "sg:postcode":"95010",
    "sg:province":"CA",
    "wof:name":"Village Mouse",
    "wof:placetype":"venue"
},
  "geometry": {"coordinates":[-121.952003,36.9729],"type":"Point"}
}