{
  "type": "Feature",
  "properties": {
    "iso:country":"US",
    "sg:address":"4533 W Telephone Rd",
    "sg:city":"Ventura",
    "sg:classifiers":[
        {
            "category":"Retail",
            "subcategory":"Auto Repair",
            "type":"Services"
        }
    ],
    "sg:phone":"+1 805 644 1334",
    "sg:postcode":"93003",
    "sg:province":"CA",
    "sg:tags":[
        "automobile",
        "smog"
    ],
    "wof:name":"Auto Masters Smog Test",
    "wof:placetype":"venue"
},
  "geometry": {"coordinates":[-119.225449,34.263553],"type":"Point"}
}