{
  "type": "Feature",
  "properties": {
    "addr:full":"4415 Trinidad Ct Stockton CA 95210",
    "addr:housenumber":"4415",
    "addr:postcode":"95210",
    "addr:street":"Trinidad Ct",
    "iso:country":"US",
    "sg:address":"4415 Trinidad Ct",
    "sg:city":"Stockton",
    "sg:classifiers":[
        {
            "category":"Building & Trades",
            "subcategory":"Cleaning & Sanitation",
            "type":"Services"
        }
    ],
    "sg:phone":"+1 209 474 7320",
    "sg:postcode":"95210",
    "sg:province":"CA",
    "sg:tags":[
        "janitor"
    ],
    "wof:name":"Chand's Cleaning Svc",
    "wof:placetype":"venue"
},
  "geometry": {"coordinates":[-121.284786,37.995823],"type":"Point"}
}