{
  "type": "Feature",
  "properties": {
    "iso:country":"US",
    "sg:address":"14233 Joanbridge St",
    "sg:city":"Baldwin Park",
    "sg:classifiers":[
        {
            "category":"Utilities",
            "subcategory":"Sewage",
            "type":"Services"
        }
    ],
    "sg:phone":"+1 626 962 1915",
    "sg:postcode":"91706",
    "sg:province":"CA",
    "sg:tags":[
        "water",
        "public",
        "district"
    ],
    "wof:name":"Valley County Water District",
    "wof:placetype":"venue"
},
  "geometry": {"coordinates":[-117.964411,34.105942],"type":"Point"}
}