{
  "type": "Feature",
  "properties": {
    "iso:country":"US",
    "sg:address":"2460 Northbrook Dr",
    "sg:city":"Oxnard",
    "sg:classifiers":[
        {
            "category":"Wholesale",
            "subcategory":"Electrical",
            "type":"Manufacturing & Wholesale Goods"
        }
    ],
    "sg:phone":"+1 805 983 3940",
    "sg:postcode":"93036",
    "sg:province":"CA",
    "sg:tags":[
        "equipment"
    ],
    "wof:name":"Thunder & Lightning",
    "wof:placetype":"venue"
},
  "geometry": {"coordinates":[-119.191511,34.236065],"type":"Point"}
}