{
  "type": "Feature",
  "properties": {
    "iso:country":"US",
    "sg:address":"5720 S 2nd St",
    "sg:city":"Los Angeles",
    "sg:classifiers":[
        {
            "category":"Manufacturing",
            "subcategory":"Tools & Machinery",
            "type":"Manufacturing & Wholesale Goods"
        }
    ],
    "sg:phone":"+1 323 588 1999",
    "sg:postcode":"90058",
    "sg:province":"CA",
    "sg:tags":[
        "physician",
        "product",
        "industrial",
        "mfg",
        "prosthetic",
        "orthopedic",
        "safety",
        "surgeon"
    ],
    "wof:name":"Golden Ross Orthopedic Mfg Co",
    "wof:placetype":"venue"
},
  "geometry": {"coordinates":[-118.23442799999999,33.990071],"type":"Point"}
}