{
  "type": "Feature",
  "properties": {
    "iso:country":"US",
    "sg:address":"28390 S Western Ave",
    "sg:city":"Rancho Pls Vrds",
    "sg:classifiers":[
        {
            "category":"Shopping",
            "subcategory":"Clothing, Apparel, & Fashions",
            "type":"Retail Goods"
        }
    ],
    "sg:phone":"+1 310 831 3585",
    "sg:postcode":"90275",
    "sg:province":"CA",
    "sg:tags":[
        "item",
        "boutique"
    ],
    "wof:name":"My Boutique",
    "wof:placetype":"venue"
},
  "geometry": {"coordinates":[-118.311606,33.763051],"type":"Point"}
}