{
  "type": "Feature",
  "properties": {
    "iso:country":"US",
    "sg:address":"25779 Madrone Dr",
    "sg:city":"Willits",
    "sg:classifiers":[
        {
            "category":"Professional",
            "type":"Services"
        }
    ],
    "sg:phone":"+1 707 456 1095",
    "sg:postcode":"95490",
    "sg:province":"CA",
    "wof:name":"Quick Silver Connections",
    "wof:placetype":"venue"
},
  "geometry": {"coordinates":[-123.37474899999999,39.449959],"type":"Point"}
}