{
  "type": "Feature",
  "properties": {
    "addr:full":"36585 S Lassen Ave Huron CA 93234",
    "addr:housenumber":"36585",
    "addr:postcode":"93234",
    "addr:street":"S Lassen Ave",
    "iso:country":"US",
    "sg:address":"36585 S Lassen Ave",
    "sg:city":"Huron",
    "sg:classifiers":[
        {
            "category":"Personal",
            "subcategory":"Beauty Salon",
            "type":"Services"
        }
    ],
    "sg:phone":"+1 559 945 2393",
    "sg:postcode":"93234",
    "sg:province":"CA",
    "sg:tags":[
        "hair",
        "stylist"
    ],
    "wof:name":"Hair Reflections",
    "wof:placetype":"venue"
},
  "geometry": {"coordinates":[-120.103459,36.201421],"type":"Point"}
}