{
  "type": "Feature",
  "properties": {
    "addr:full":"15353 Barranca Pkwy Irvine CA 92618",
    "addr:housenumber":"15353",
    "addr:postcode":"92618",
    "addr:street":"Barranca Pkwy",
    "iso:country":"US",
    "sg:address":"15353 Barranca Pkwy",
    "sg:city":"Irvine",
    "sg:classifiers":[
        {
            "category":"Manufacturing",
            "subcategory":"Electronics",
            "type":"Manufacturing & Wholesale Goods"
        }
    ],
    "sg:phone":"+1 949 450 7203",
    "sg:postcode":"92618",
    "sg:province":"CA",
    "sg:tags":[
        "electronic",
        "component",
        "mfg"
    ],
    "wof:name":"Electronic Sales",
    "wof:placetype":"venue"
},
  "geometry": {"coordinates":[-117.740454,33.660726],"type":"Point"}
}