{
  "type": "Feature",
  "properties": {
    "addr:full":"600 Polk St San Francisco CA 94102",
    "addr:housenumber":"600",
    "addr:postcode":"94102",
    "addr:street":"Polk St",
    "iso:country":"US",
    "sg:address":"600 Polk St",
    "sg:city":"San Francisco",
    "sg:classifiers":[
        {
            "category":"Bars & Pubs",
            "type":"Food & Drink"
        },
        {
            "category":"Recreation",
            "subcategory":"Dance Hall",
            "type":"Entertainment"
        }
    ],
    "sg:phone":"+1 415 525 3499",
    "sg:postcode":"94102",
    "sg:province":"CA",
    "sg:tags":[
        "club"
    ],
    "sg:website":"www.noblesf.com",
    "wof:name":"Noble",
    "wof:placetype":"venue"
},
  "geometry": {"coordinates":[-122.418983,37.782218],"type":"Point"}
}