{
  "type": "Feature",
  "properties": {
    "iso:country":"US",
    "sg:address":"2015 W Redondo Beach Blvd",
    "sg:city":"Gardena",
    "sg:classifiers":[
        {
            "category":"Restaurant",
            "type":"Food & Drink"
        }
    ],
    "sg:phone":"+1 310 329 1335",
    "sg:postcode":"90247",
    "sg:province":"CA",
    "sg:tags":[
        "japanese"
    ],
    "sg:website":"www.shinsengumiusa.com",
    "wof:name":"Hakata Ramen Shinsengumi",
    "wof:placetype":"venue"
},
  "geometry": {"coordinates":[-118.314003,33.8871],"type":"Point"}
}