{
  "type": "Feature",
  "properties": {
    "addr:full":"42425 5th St E Lancaster CA 93535",
    "addr:housenumber":"42425",
    "addr:postcode":"93535",
    "addr:street":"5Th St E",
    "iso:country":"US",
    "sg:address":"42425 5th St E",
    "sg:city":"Lancaster",
    "sg:classifiers":[
        {
            "category":"Retail",
            "subcategory":"Auto Repair",
            "type":"Services"
        }
    ],
    "sg:phone":"+1 661 948 4430",
    "sg:postcode":"93535",
    "sg:province":"CA",
    "sg:tags":[
        "truck"
    ],
    "wof:name":"A V Truck Repair",
    "wof:placetype":"venue"
},
  "geometry": {"coordinates":[-118.121166,34.653568],"type":"Point"}
}