{
  "type": "Feature",
  "properties": {
    "iso:country":"US",
    "sg:address":"36283 Colbert Pl",
    "sg:city":"Newark",
    "sg:classifiers":[
        {
            "category":"Freight",
            "type":"Transportation"
        }
    ],
    "sg:phone":"+1 510 744 1036",
    "sg:postcode":"94560",
    "sg:province":"CA",
    "sg:tags":[
        "operator",
        "local",
        "trucking"
    ],
    "wof:name":"San Pedro Fish Delivery",
    "wof:placetype":"venue"
},
  "geometry": {"coordinates":[-122.047294,37.53603],"type":"Point"}
}