{
  "type": "Feature",
  "properties": {
    "addr:full":"8251 Village Creek Way Sacramento CA 95823",
    "addr:housenumber":"8251",
    "addr:postcode":"95823",
    "addr:street":"Village Creek Way",
    "iso:country":"US",
    "sg:address":"8251 Village Creek Way",
    "sg:city":"Sacramento",
    "sg:classifiers":[
        {
            "category":"Shopping",
            "subcategory":"Clothing, Apparel, & Fashions",
            "type":"Retail Goods"
        }
    ],
    "sg:phone":"+1 916 422 6774",
    "sg:postcode":"95823",
    "sg:province":"CA",
    "sg:tags":[
        "apparel",
        "women's"
    ],
    "wof:name":"Y Video Fashion",
    "wof:placetype":"venue"
},
  "geometry": {"coordinates":[-121.436791,38.457755],"type":"Point"}
}