{
  "type": "Feature",
  "properties": {
    "iso:country":"US",
    "sg:address":"1121 L St",
    "sg:city":"Sacramento",
    "sg:classifiers":[
        {
            "category":"Professional",
            "subcategory":"Management & Consulting",
            "type":"Services"
        }
    ],
    "sg:phone":"+1 916 440 0829",
    "sg:postcode":"95814",
    "sg:province":"CA",
    "sg:tags":[
        "consultant",
        "business"
    ],
    "wof:name":"Pacific Gateway",
    "wof:placetype":"venue"
},
  "geometry": {"coordinates":[-121.49194199999999,38.577539],"type":"Point"}
}