{
  "type": "Feature",
  "properties": {
    "addr:full":"22400 Town Cir Moreno Valley CA 92553",
    "addr:housenumber":"22400",
    "addr:postcode":"92553",
    "addr:street":"Town Cir",
    "iso:country":"US",
    "sg:address":"22400 Town Cir",
    "sg:city":"Moreno Valley",
    "sg:classifiers":[
        {
            "category":"Shopping",
            "subcategory":"Department Store",
            "type":"Retail Goods"
        }
    ],
    "sg:phone":"+1 951 656 1611",
    "sg:postcode":"92553",
    "sg:province":"CA",
    "wof:name":"Robinsons-May",
    "wof:placetype":"venue"
},
  "geometry": {"coordinates":[-117.27524200000001,33.938523],"type":"Point"}
}