{
  "type": "Feature",
  "properties": {
    "iso:country":"US",
    "sg:address":"4531 1/2 Van Nuys Blvd",
    "sg:city":"Sherman Oaks",
    "sg:classifiers":[
        {
            "category":"Shopping",
            "subcategory":"Pets & Pet Supplies",
            "type":"Retail Goods"
        }
    ],
    "sg:phone":"+1 818 906 7387",
    "sg:postcode":"91403",
    "sg:province":"CA",
    "sg:tags":[
        "groomers"
    ],
    "wof:name":"AJ's Pet Shop & Grooming",
    "wof:placetype":"venue"
},
  "geometry": {"coordinates":[-118.449066,34.153905],"type":"Point"}
}