{
  "type": "Feature",
  "properties": {
    "iso:country":"US",
    "sg:address":"10510 Superfortress Ave",
    "sg:city":"Mather",
    "sg:classifiers":[
        {
            "category":"Airport",
            "type":"Transportation"
        }
    ],
    "sg:phone":"+1 916 645 1701",
    "sg:postcode":"95655",
    "sg:province":"CA",
    "sg:tags":[
        "aircraft",
        "upholsterer"
    ],
    "wof:name":"Lincoln Aviation Interiors",
    "wof:placetype":"venue"
},
  "geometry": {"coordinates":[-121.295697,38.564888],"type":"Point"}
}