{
  "type": "Feature",
  "properties": {
    "addr:full":"7 Progress St San Francisco CA 94124",
    "addr:housenumber":"7",
    "addr:postcode":"94124",
    "addr:street":"Progress St",
    "iso:country":"US",
    "sg:address":"7 Progress St",
    "sg:city":"San Francisco",
    "sg:classifiers":[
        {
            "category":"Building & Trades",
            "subcategory":"Cleaning & Sanitation",
            "type":"Services"
        }
    ],
    "sg:phone":"+1 415 641 6034",
    "sg:postcode":"94124",
    "sg:province":"CA",
    "sg:tags":[
        "home"
    ],
    "wof:name":"DORIS HOUSE CLEANING",
    "wof:placetype":"venue"
},
  "geometry": {"coordinates":[-122.38362600000001,37.733234],"type":"Point"}
}