{
  "type": "Feature",
  "properties": {
    "addr:full":"683 E Port Hueneme Rd Port Hueneme CA 93041",
    "addr:housenumber":"683",
    "addr:postcode":"93041",
    "addr:street":"E Port Hueneme Rd",
    "iso:country":"US",
    "sg:address":"683 E Port Hueneme Rd",
    "sg:city":"Port Hueneme",
    "sg:classifiers":[
        {
            "category":"Building & Trades",
            "subcategory":"Electrical",
            "type":"Services"
        }
    ],
    "sg:phone":"+1 805 488 8658",
    "sg:postcode":"93041",
    "sg:province":"CA",
    "sg:tags":[
        "electrical",
        "contractor"
    ],
    "wof:name":"Nicholas Control Systems",
    "wof:placetype":"venue"
},
  "geometry": {"coordinates":[-119.18800299999999,34.147562],"type":"Point"}
}