{
  "type": "Feature",
  "properties": {
    "iso:country":"US",
    "sg:address":"24925 Pico Canyon Rd",
    "sg:city":"Stevenson Rnh",
    "sg:classifiers":[
        {
            "category":"Retail",
            "subcategory":"Laundry & Dry Cleaning",
            "type":"Services"
        }
    ],
    "sg:phone":"+1 661 260 2280",
    "sg:postcode":"91381",
    "sg:province":"CA",
    "wof:name":"Carriage Cleaners Stevenson Ranch",
    "wof:placetype":"venue"
},
  "geometry": {"coordinates":[-118.57199900000001,34.381199],"type":"Point"}
}