{
  "type": "Feature",
  "properties": {
    "iso:country":"US",
    "sg:address":"100 Bayo Vista Way",
    "sg:city":"San Rafael",
    "sg:classifiers":[
        {
            "category":"Insurance",
            "subcategory":"Insurance Agent",
            "type":"Services"
        }
    ],
    "sg:phone":"+1 415 256 9046",
    "sg:postcode":"94901",
    "sg:province":"CA",
    "sg:tags":[
        "processing"
    ],
    "wof:name":"Ensue Medical Billing Svc",
    "wof:placetype":"venue"
},
  "geometry": {"coordinates":[-122.544297,37.975585],"type":"Point"}
}