{
  "type": "Feature",
  "properties": {
    "addr:full":"7250 Bandini Blvd City Of Commerce CA 90040",
    "addr:housenumber":"7250",
    "addr:postcode":"90040",
    "addr:street":"Bandini Blvd",
    "iso:country":"US",
    "sg:address":"7250 Bandini Blvd",
    "sg:city":"City Of Commerce",
    "sg:classifiers":[
        {
            "category":"Wholesale",
            "subcategory":"Machinery & Supplies",
            "type":"Manufacturing & Wholesale Goods"
        }
    ],
    "sg:phone":"+1 323 888 6569",
    "sg:postcode":"90040",
    "sg:province":"CA",
    "sg:tags":[
        "equipment",
        "safety",
        "clothing"
    ],
    "wof:name":"Lehigh Safety Shoe Co",
    "wof:placetype":"venue"
},
  "geometry": {"coordinates":[-118.13248299999999,33.983054],"type":"Point"}
}