{
  "type": "Feature",
  "properties": {
    "addr:full":"812 E Chapman Ave Fullerton CA 92831",
    "addr:housenumber":"812",
    "addr:postcode":"92831",
    "addr:street":"E Chapman Ave",
    "iso:country":"US",
    "sg:address":"812 E Chapman Ave",
    "sg:city":"Fullerton",
    "sg:classifiers":[
        {
            "category":"Food & Beverages",
            "subcategory":"Groceries & Convenience Stores",
            "type":"Retail Goods"
        }
    ],
    "sg:phone":"+1 714 879 1692",
    "sg:postcode":"92831",
    "sg:province":"CA",
    "wof:name":"Chapman Mini Mart",
    "wof:placetype":"venue"
},
  "geometry": {"coordinates":[-117.91137000000001,33.873902],"type":"Point"}
}