{
  "type": "Feature",
  "properties": {
    "iso:country":"US",
    "sg:address":"6296 Magnolia Ave",
    "sg:city":"Riverside",
    "sg:classifiers":[
        {
            "category":"Wholesale",
            "subcategory":"Stationery",
            "type":"Manufacturing & Wholesale Goods"
        }
    ],
    "sg:phone":"+1 951 782 2140",
    "sg:postcode":"92506",
    "sg:province":"CA",
    "sg:tags":[
        "supply"
    ],
    "wof:name":"Staples",
    "wof:placetype":"venue"
},
  "geometry": {"coordinates":[-117.394056,33.957203],"type":"Point"}
}