{
  "type": "Feature",
  "properties": {
    "iso:country":"US",
    "sg:address":"222 E Hillcrest Dr",
    "sg:city":"Thousand Oaks",
    "sg:classifiers":[
        {
            "category":"Professional",
            "type":"Services"
        }
    ],
    "sg:phone":"+1 805 496 3447",
    "sg:postcode":"91360",
    "sg:province":"CA",
    "wof:name":"Ornaments & Ink",
    "wof:placetype":"venue"
},
  "geometry": {"coordinates":[-118.868782,34.181154],"type":"Point"}
}