{
  "type": "Feature",
  "properties": {
    "iso:country":"US",
    "sg:address":"2559 W Rosamond Blvd",
    "sg:city":"Rosamond",
    "sg:phone":"+1 661 256 1590",
    "sg:postcode":"93560",
    "sg:province":"CA",
    "wof:name":"Video Giant",
    "wof:placetype":"venue"
},
  "geometry": {"coordinates":[-118.177278,34.864183],"type":"Point"}
}