{
  "type": "Feature",
  "properties": {
    "addr:full":"7290 Hedge Ave Sacramento CA 95829",
    "addr:housenumber":"7290",
    "addr:postcode":"95829",
    "addr:street":"Hedge Ave",
    "iso:country":"US",
    "sg:address":"7290 Hedge Ave",
    "sg:city":"Sacramento",
    "sg:classifiers":[
        {
            "category":"Building & Trades",
            "subcategory":"Construction",
            "type":"Services"
        }
    ],
    "sg:phone":"+1 916 386 2401",
    "sg:postcode":"95829",
    "sg:province":"CA",
    "sg:tags":[
        "roofing",
        "contractor"
    ],
    "wof:name":"Southgate Roofing Co",
    "wof:placetype":"venue"
},
  "geometry": {"coordinates":[-121.36280499999999,38.491937],"type":"Point"}
}