{
  "type": "Feature",
  "properties": {
    "addr:full":"20117 Chestnut St Laton CA 93242",
    "addr:housenumber":"20117",
    "addr:postcode":"93242",
    "addr:street":"Chestnut St",
    "iso:country":"US",
    "sg:address":"20117 Chestnut St",
    "sg:city":"Laton",
    "sg:classifiers":[
        {
            "category":"Wholesale",
            "subcategory":"Fruits & Vegetables",
            "type":"Manufacturing & Wholesale Goods"
        }
    ],
    "sg:phone":"+1 559 923 4697",
    "sg:postcode":"93242",
    "sg:province":"CA",
    "sg:tags":[
        "farm",
        "crop",
        "general"
    ],
    "wof:name":"Angels Produce Farms",
    "wof:placetype":"venue"
},
  "geometry": {"coordinates":[-119.74458,36.439926],"type":"Point"}
}