{
  "type": "Feature",
  "properties": {
    "addr:full":"1138 W Redondo Beach Blvd Gardena CA 90247",
    "addr:housenumber":"1138",
    "addr:postcode":"90247",
    "addr:street":"W Redondo Beach Blvd",
    "iso:country":"US",
    "sg:address":"1138 W Redondo Beach Blvd",
    "sg:city":"Gardena",
    "sg:classifiers":[
        {
            "category":"Shopping",
            "type":"Retail Goods"
        }
    ],
    "sg:phone":"+1 310 366 7452",
    "sg:postcode":"90247",
    "sg:province":"CA",
    "sg:tags":[
        "religious"
    ],
    "wof:name":"Liberia Sion",
    "wof:placetype":"venue"
},
  "geometry": {"coordinates":[-118.295815,33.892298],"type":"Point"}
}