{
  "type": "Feature",
  "properties": {
    "iso:country":"US",
    "sg:address":"1901 Harrison St Ste 1575",
    "sg:city":"Oakland",
    "sg:classifiers":[
        {
            "category":"Professional",
            "subcategory":"Engineering",
            "type":"Services"
        }
    ],
    "sg:phone":"+1 510 891 2200",
    "sg:postcode":"94612",
    "sg:province":"CA",
    "sg:tags":[
        "consulting",
        "engineer"
    ],
    "wof:name":"Parsons Brinckerhoff",
    "wof:placetype":"venue"
},
  "geometry": {"coordinates":[-122.26544199999999,37.80637],"type":"Point"}
}