{
  "type": "Feature",
  "properties": {
    "addr:full":"16014 Halldale Ave Gardena CA 90247",
    "addr:postcode":"16014;90247",
    "addr:street":"Halldale Ave",
    "iso:country":"US",
    "sg:address":"16014 Halldale Ave",
    "sg:city":"Gardena",
    "sg:classifiers":[
        {
            "category":"Retail",
            "subcategory":"Auto Repair",
            "type":"Services"
        }
    ],
    "sg:phone":"+1 310 329 8157",
    "sg:postcode":"90247",
    "sg:province":"CA",
    "sg:tags":[
        "body",
        "automobile",
        "painting",
        "repairing"
    ],
    "wof:name":"Americas Masters Paint Brushes",
    "wof:placetype":"venue"
},
  "geometry": {"coordinates":[-118.30201700000001,33.885462],"type":"Point"}
}