{
  "type": "Feature",
  "properties": {
    "iso:country":"US",
    "sg:address":"11641 Morgan Ln",
    "sg:city":"Garden Grove",
    "sg:classifiers":[
        {
            "category":"Building & Trades",
            "subcategory":"Construction",
            "type":"Services"
        }
    ],
    "sg:phone":"+1 714 748 7927",
    "sg:postcode":"92840",
    "sg:province":"CA",
    "sg:tags":[
        "designer"
    ],
    "sg:website":"www.badhombre.com",
    "wof:name":"Bad Hombre Designs",
    "wof:placetype":"venue"
},
  "geometry": {"coordinates":[-117.924923,33.79536],"type":"Point"}
}