{
  "type": "Feature",
  "properties": {
    "iso:country":"US",
    "sg:address":"218 Atlantic Ave",
    "sg:city":"Long Beach",
    "sg:classifiers":[
        {
            "category":"Personal",
            "subcategory":"Beauty Salon",
            "type":"Services"
        }
    ],
    "sg:phone":"+1 562 590 3136",
    "sg:postcode":"90802",
    "sg:province":"CA",
    "sg:tags":[
        "shop",
        "equipment",
        "establishment"
    ],
    "wof:name":"Beautiworx",
    "wof:placetype":"venue"
},
  "geometry": {"coordinates":[-118.185029,33.770495],"type":"Point"}
}