{
  "type": "Feature",
  "properties": {
    "iso:country":"US",
    "sg:address":"105 S Locust St",
    "sg:city":"Inglewood",
    "sg:classifiers":[
        {
            "category":"Real Estate",
            "subcategory":"Real Estate Agent",
            "type":"Services"
        }
    ],
    "sg:phone":"+1 310 590 1286",
    "sg:postcode":"90301",
    "sg:province":"CA",
    "wof:name":"Real Estate Ctr",
    "wof:placetype":"venue"
},
  "geometry": {"coordinates":[-118.35038,33.96235],"type":"Point"}
}