{
  "type": "Feature",
  "properties": {
    "addr:full":"15360 China Rapids Dr Red Bluff CA 96080",
    "addr:housenumber":"15360",
    "addr:postcode":"96080",
    "addr:street":"China Rapids Dr",
    "iso:country":"US",
    "sg:address":"15360 China Rapids Dr",
    "sg:city":"Red Bluff",
    "sg:classifiers":[
        {
            "category":"Professional",
            "subcategory":"Management & Consulting",
            "type":"Services"
        }
    ],
    "sg:phone":"+1 530 527 0300",
    "sg:postcode":"96080",
    "sg:province":"CA",
    "sg:tags":[
        "consultant",
        "business"
    ],
    "wof:name":"Barbara Sherry Financial Svc",
    "wof:placetype":"venue"
},
  "geometry": {"coordinates":[-122.206069,40.243977],"type":"Point"}
}