{
  "type": "Feature",
  "properties": {
    "addr:full":"3316 State Rte 263 Yreka CA 96097",
    "addr:housenumber":"3316",
    "addr:postcode":"96097",
    "addr:street":"State Rte 263",
    "iso:country":"US",
    "sg:address":"3316 State Rte 263",
    "sg:city":"Yreka",
    "sg:classifiers":[
        {
            "category":"Manufacturing",
            "subcategory":"Lumber",
            "type":"Manufacturing & Wholesale Goods"
        }
    ],
    "sg:phone":"+1 530 842 6606",
    "sg:postcode":"96097",
    "sg:province":"CA",
    "sg:tags":[
        "company",
        "logging"
    ],
    "wof:name":"Mark Crawford Logging",
    "wof:placetype":"venue"
},
  "geometry": {"coordinates":[-122.62563400000001,41.757194],"type":"Point"}
}