{
  "type": "Feature",
  "properties": {
    "addr:full":"3507 S Bascom Ave Campbell CA 95008",
    "addr:housenumber":"3507",
    "addr:postcode":"95008",
    "addr:street":"S Bascom Ave",
    "iso:country":"US",
    "sg:address":"3507 S Bascom Ave",
    "sg:city":"Campbell",
    "sg:classifiers":[
        {
            "category":"Real Estate",
            "subcategory":"Real Estate Operator",
            "type":"Services"
        }
    ],
    "sg:phone":"+1 408 371 9208",
    "sg:postcode":"95008",
    "sg:province":"CA",
    "sg:tags":[
        "apartment"
    ],
    "wof:name":"Pines Apartments",
    "wof:placetype":"venue"
},
  "geometry": {"coordinates":[-121.94499999999999,37.262299],"type":"Point"}
}