{
  "type": "Feature",
  "properties": {
    "addr:full":"1100 Burton Dr Redding CA 96003",
    "addr:housenumber":"1100",
    "addr:postcode":"96003",
    "addr:street":"Burton Dr",
    "iso:country":"US",
    "sg:address":"1100 Burton Dr",
    "sg:city":"Redding",
    "sg:classifiers":[
        {
            "category":"Shopping",
            "subcategory":"Clothing, Apparel, & Fashions",
            "type":"Retail Goods"
        }
    ],
    "sg:phone":"+1 530 226 1853",
    "sg:postcode":"96003",
    "sg:province":"CA",
    "wof:name":"Ryda Clothing",
    "wof:placetype":"venue"
},
  "geometry": {"coordinates":[-122.348634,40.592065],"type":"Point"}
}