{
  "type": "Feature",
  "properties": {
    "addr:full":"6464 Sylmar Ave Van Nuys CA 91401",
    "addr:housenumber":"6464",
    "addr:postcode":"91401",
    "addr:street":"Sylmar Ave",
    "iso:country":"US",
    "sg:address":"6464 Sylmar Ave",
    "sg:city":"Van Nuys",
    "sg:classifiers":[
        {
            "category":"Education",
            "subcategory":"School",
            "type":"Public Place"
        }
    ],
    "sg:phone":"+1 818 785 2195",
    "sg:postcode":"91401",
    "sg:province":"CA",
    "sg:tags":[
        "elementary"
    ],
    "sg:website":"www.lausd.k12.ca.us",
    "wof:name":"Van Nuys Elementary School",
    "wof:placetype":"venue"
},
  "geometry": {"coordinates":[-118.445999,34.1884],"type":"Point"}
}