{
  "type": "Feature",
  "properties": {
    "addr:full":"1077 N Harbor Blvd Anaheim CA 92801",
    "addr:housenumber":"1077",
    "addr:postcode":"92801",
    "addr:street":"N Harbor Blvd",
    "iso:country":"US",
    "sg:address":"1077 N Harbor Blvd",
    "sg:city":"Anaheim",
    "sg:classifiers":[
        {
            "category":"Restaurant",
            "type":"Food & Drink"
        }
    ],
    "sg:phone":"+1 714 254 0335",
    "sg:postcode":"92801",
    "sg:province":"CA",
    "wof:name":"La Dame",
    "wof:placetype":"venue"
},
  "geometry": {"coordinates":[-117.92523,33.849903],"type":"Point"}
}