{
  "type": "Feature",
  "properties": {
    "addr:full":"18740 Favre Ridge Rd Los Gatos CA 95033",
    "addr:housenumber":"18740",
    "addr:postcode":"95033",
    "addr:street":"Favre Ridge Rd",
    "iso:country":"US",
    "sg:address":"18740 Favre Ridge Rd",
    "sg:city":"Los Gatos",
    "sg:classifiers":[
        {
            "category":"Professional",
            "subcategory":"Computer Services",
            "type":"Services"
        }
    ],
    "sg:phone":"+1 408 399 9196",
    "sg:postcode":"95033",
    "sg:province":"CA",
    "wof:name":"Information Solutions Inc",
    "wof:placetype":"venue"
},
  "geometry": {"coordinates":[-122.067103,37.196934],"type":"Point"}
}