{
  "type": "Feature",
  "properties": {
    "iso:country":"US",
    "sg:address":"6007 Niles St",
    "sg:city":"Bakersfield",
    "sg:classifiers":[
        {
            "category":"Shopping",
            "subcategory":"Jewelry",
            "type":"Retail Goods"
        }
    ],
    "sg:phone":"+1 661 366 1780",
    "sg:postcode":"93306",
    "sg:province":"CA",
    "sg:tags":[
        "jeweler"
    ],
    "wof:name":"Joyeria Medina",
    "wof:placetype":"venue"
},
  "geometry": {"coordinates":[-118.932001,35.376162],"type":"Point"}
}