{
  "type": "Feature",
  "properties": {
    "iso:country":"US",
    "sg:address":"5950 Colgate Ave",
    "sg:city":"Los Angeles",
    "sg:classifiers":[
        {
            "category":"Building & Trades",
            "subcategory":"Construction",
            "type":"Services"
        }
    ],
    "sg:phone":"+1 323 934 6941",
    "sg:postcode":"90036",
    "sg:province":"CA",
    "sg:tags":[
        "contractor"
    ],
    "wof:name":"Savant Construction",
    "wof:placetype":"venue"
},
  "geometry": {"coordinates":[-118.35217799999999,34.069216],"type":"Point"}
}