{
  "type": "Feature",
  "properties": {
    "iso:country":"US",
    "sg:address":"1880 Century Park E",
    "sg:city":"Los Angeles",
    "sg:classifiers":[
        {
            "category":"Arts & Performance",
            "subcategory":"Theater",
            "type":"Entertainment"
        }
    ],
    "sg:phone":"+1 310 551 9720",
    "sg:postcode":"90067",
    "sg:province":"CA",
    "sg:tags":[
        "television",
        "station",
        "representative"
    ],
    "sg:website":"www.dpashlaw.com",
    "wof:name":"Adam Young Inc",
    "wof:placetype":"venue"
},
  "geometry": {"coordinates":[-118.414302,34.061402],"type":"Point"}
}