{
  "type": "Feature",
  "properties": {
    "iso:country":"US",
    "sg:address":"31452 Highland Ave",
    "sg:city":"Redlands",
    "sg:classifiers":[
        {
            "category":"Farming",
            "subcategory":"Orchard",
            "type":"Manufacturing & Wholesale Goods"
        }
    ],
    "sg:phone":"+1 909 794 4735",
    "sg:postcode":"92374",
    "sg:province":"CA",
    "sg:tags":[
        "citrus",
        "grove",
        "fruit"
    ],
    "wof:name":"Mishak Ranches",
    "wof:placetype":"venue"
},
  "geometry": {"coordinates":[-117.115875,34.051842],"type":"Point"}
}