{
  "type": "Feature",
  "properties": {
    "iso:country":"US",
    "sg:address":"4529 Mattos Dr",
    "sg:city":"Fremont",
    "sg:classifiers":[
        {
            "category":"Health Services",
            "subcategory":"Doctor",
            "type":"Services"
        }
    ],
    "sg:phone":"+1 510 797 2611",
    "sg:postcode":"94536",
    "sg:province":"CA",
    "sg:tags":[
        "dentist"
    ],
    "wof:name":"Bay Area Dental Care",
    "wof:placetype":"venue"
},
  "geometry": {"coordinates":[-122.00438,37.546553],"type":"Point"}
}