{
  "type": "Feature",
  "properties": {
    "addr:full":"912 Olinder Ct San Jose CA 95122",
    "addr:housenumber":"912",
    "addr:postcode":"95122",
    "addr:street":"Olinder Ct",
    "iso:country":"US",
    "sg:address":"912 Olinder Ct",
    "sg:city":"San Jose",
    "sg:classifiers":[
        {
            "category":"Manufacturing",
            "subcategory":"Metals",
            "type":"Manufacturing & Wholesale Goods"
        }
    ],
    "sg:phone":"+1 408 494 3530",
    "sg:postcode":"95122",
    "sg:province":"CA",
    "sg:tags":[
        "fabricator",
        "aluminum"
    ],
    "sg:website":"www.tobar-ind.com",
    "wof:name":"Tobar Industries",
    "wof:placetype":"venue"
},
  "geometry": {"coordinates":[-121.851924,37.334781],"type":"Point"}
}