{
  "type": "Feature",
  "properties": {
    "iso:country":"US",
    "sg:address":"8546 W Knoll Dr",
    "sg:city":"West Hollywood",
    "sg:classifiers":[
        {
            "category":"Wholesale",
            "subcategory":"Farm Supplies",
            "type":"Manufacturing & Wholesale Goods"
        }
    ],
    "sg:phone":"+1 310 657 7666",
    "sg:postcode":"90069",
    "sg:province":"CA",
    "sg:tags":[
        "sell",
        "horse",
        "buy",
        "race"
    ],
    "wof:name":"Pegasus Bloodstock Usa Inc",
    "wof:placetype":"venue"
},
  "geometry": {"coordinates":[-118.378045,34.089522],"type":"Point"}
}