{
  "type": "Feature",
  "properties": {
    "addr:full":"2825 Lenwood Rd Barstow CA 92311",
    "addr:housenumber":"2825",
    "addr:postcode":"92311",
    "addr:street":"Lenwood Rd",
    "iso:country":"US",
    "sg:address":"2825 Lenwood Rd",
    "sg:city":"Barstow",
    "sg:classifiers":[
        {
            "category":"Shopping",
            "subcategory":"Clothing, Apparel, & Fashions",
            "type":"Retail Goods"
        }
    ],
    "sg:phone":"+1 760 253 2020",
    "sg:postcode":"92311",
    "sg:province":"CA",
    "wof:name":"Nautica Factory Barstow Inc",
    "wof:placetype":"venue"
},
  "geometry": {"coordinates":[-117.087937,34.854468],"type":"Point"}
}