{
  "type": "Feature",
  "properties": {
    "addr:full":"16055 Caputo Dr Morgan Hill CA 95037",
    "addr:postcode":"16055;95037",
    "addr:street":"Caputo Dr",
    "iso:country":"US",
    "sg:address":"16055 Caputo Dr",
    "sg:city":"Morgan Hill",
    "sg:classifiers":[
        {
            "category":"Retail",
            "subcategory":"Repair Shop",
            "type":"Services"
        }
    ],
    "sg:phone":"+1 408 778 7555",
    "sg:postcode":"95037",
    "sg:province":"CA",
    "sg:tags":[
        "scooter",
        "motorcycle",
        "motor"
    ],
    "wof:name":"Strictly Wicked Cycles",
    "wof:placetype":"venue"
},
  "geometry": {"coordinates":[-121.63585999999999,37.12065],"type":"Point"}
}