{
  "type": "Feature",
  "properties": {
    "iso:country":"US",
    "sg:address":"428 Arden Ave Ste 201",
    "sg:city":"Glendale",
    "sg:classifiers":[
        {
            "category":"Health Services",
            "subcategory":"Doctor",
            "type":"Services"
        }
    ],
    "sg:phone":"+1 818 243 4287",
    "sg:postcode":"91203",
    "sg:province":"CA",
    "sg:tags":[
        "surgeon",
        "oral"
    ],
    "wof:name":"Sanders Steven C DDS",
    "wof:placetype":"venue"
},
  "geometry": {"coordinates":[-118.262001,34.158401],"type":"Point"}
}