{
  "type": "Feature",
  "properties": {
    "iso:country":"US",
    "sg:address":"16012 Melbourne Ct",
    "sg:city":"Truckee",
    "sg:classifiers":[
        {
            "category":"Building & Trades",
            "subcategory":"Plumbing",
            "type":"Services"
        }
    ],
    "sg:phone":"+1 530 587 4081",
    "sg:postcode":"96161",
    "sg:province":"CA",
    "sg:tags":[
        "plumbing",
        "contractor"
    ],
    "wof:name":"Craig Price",
    "wof:placetype":"venue"
},
  "geometry": {"coordinates":[-120.09201400000001,39.361308],"type":"Point"}
}