{
  "type": "Feature",
  "properties": {
    "addr:full":"16060 Sonoma Hwy Sonoma CA 95476",
    "addr:housenumber":"16060",
    "addr:postcode":"95476",
    "addr:street":"Sonoma Hwy",
    "iso:country":"US",
    "sg:address":"16060 Sonoma Hwy",
    "sg:city":"Sonoma",
    "sg:classifiers":[
        {
            "category":"Professional",
            "subcategory":"Engineering",
            "type":"Services"
        }
    ],
    "sg:phone":"+1 707 933 8483",
    "sg:postcode":"95476",
    "sg:province":"CA",
    "sg:tags":[
        "general",
        "contractor"
    ],
    "wof:name":"Encon General Engineering",
    "wof:placetype":"venue"
},
  "geometry": {"coordinates":[-122.49119399999999,38.334069],"type":"Point"}
}