{
  "type": "Feature",
  "properties": {
    "addr:full":"7513 Santa Monica Boulevard West Hollywood CA 90046",
    "addr:housenumber":"7513",
    "addr:postcode":"90046",
    "addr:street":"Santa Monica Boulevard",
    "iso:country":"US",
    "sg:address":"7513 Santa Monica Boulevard",
    "sg:city":"West Hollywood",
    "sg:classifiers":[
        {
            "category":"Shopping",
            "subcategory":"Books",
            "type":"Retail Goods"
        }
    ],
    "sg:phone":"+1 323 882 6160",
    "sg:postcode":"90046",
    "sg:province":"CA",
    "sg:tags":[
        "bookstore"
    ],
    "wof:name":"Interbook",
    "wof:placetype":"venue"
},
  "geometry": {"coordinates":[-118.353481,34.090667],"type":"Point"}
}