{
  "type": "Feature",
  "properties": {
    "addr:full":"2430 S Escondido Blvd Escondido CA 92025",
    "addr:housenumber":"2430",
    "addr:postcode":"92025",
    "addr:street":"S Escondido Blvd",
    "iso:country":"US",
    "sg:address":"2430 S Escondido Blvd",
    "sg:city":"Escondido",
    "sg:classifiers":[
        {
            "category":"Insurance",
            "subcategory":"Insurance Agent",
            "type":"Services"
        }
    ],
    "sg:phone":"+1 760 738 2100",
    "sg:postcode":"92025",
    "sg:province":"CA",
    "sg:tags":[
        "claim"
    ],
    "wof:name":"State Farm Insurance",
    "wof:placetype":"venue"
},
  "geometry": {"coordinates":[-117.07191,33.092944],"type":"Point"}
}