{
  "type": "Feature",
  "properties": {
    "iso:country":"US",
    "sg:address":"740 S Alameda Street",
    "sg:city":"Los Angeles",
    "sg:classifiers":[
        {
            "category":"Wholesale",
            "subcategory":"Fruits & Vegetables",
            "type":"Manufacturing & Wholesale Goods"
        }
    ],
    "sg:phone":"+1 213 689 0844",
    "sg:postcode":"90021",
    "sg:province":"CA",
    "sg:tags":[
        "veggie"
    ],
    "wof:name":"Continental Sales",
    "wof:placetype":"venue"
},
  "geometry": {"coordinates":[-118.238901,34.032581],"type":"Point"}
}