{
  "type": "Feature",
  "properties": {
    "addr:full":"317 Paul Ave Salinas CA 93906",
    "addr:housenumber":"317",
    "addr:postcode":"93906",
    "addr:street":"Paul Ave",
    "iso:country":"US",
    "sg:address":"317 Paul Ave",
    "sg:city":"Salinas",
    "sg:classifiers":[
        {
            "category":"Professional",
            "type":"Services"
        }
    ],
    "sg:phone":"+1 831 443 4538",
    "sg:postcode":"93906",
    "sg:province":"CA",
    "wof:name":"Designer Creations",
    "wof:placetype":"venue"
},
  "geometry": {"coordinates":[-121.639827,36.73417],"type":"Point"}
}