{
  "type": "Feature",
  "properties": {
    "iso:country":"US",
    "sg:address":"135 Court St",
    "sg:city":"Auburn",
    "sg:classifiers":[
        {
            "category":"Professional",
            "subcategory":"Lawyer & Legal Services",
            "type":"Services"
        }
    ],
    "sg:phone":"+1 530 888 1905",
    "sg:postcode":"95603",
    "sg:province":"CA",
    "sg:tags":[
        "attorney",
        "planning",
        "estate"
    ],
    "sg:website":"http://www.collins4law.com",
    "wof:name":"Collins & Collins",
    "wof:placetype":"venue"
},
  "geometry": {"coordinates":[-121.077282,38.896169],"type":"Point"}
}