{
  "type": "Feature",
  "properties": {
    "addr:full":"500 Solano Ave Vallejo CA 94590",
    "addr:housenumber":"500",
    "addr:postcode":"94590",
    "addr:street":"Solano Ave",
    "iso:country":"US",
    "sg:address":"500 Solano Ave",
    "sg:city":"Vallejo",
    "sg:classifiers":[
        {
            "category":"Autos & Motor Vehicles",
            "subcategory":"Automobile Sales",
            "type":"Retail Goods"
        }
    ],
    "sg:phone":"+1 707 643 8182",
    "sg:postcode":"94590",
    "sg:province":"CA",
    "sg:tags":[
        "car",
        "dealer"
    ],
    "wof:name":"Orange Equipment Co",
    "wof:placetype":"venue"
},
  "geometry": {"coordinates":[-122.251623,38.094232],"type":"Point"}
}