{
  "type": "Feature",
  "properties": {
    "iso:country":"US",
    "sg:address":"41364 Merriwood Dr",
    "sg:city":"Hemet",
    "sg:classifiers":[
        {
            "category":"Building & Trades",
            "subcategory":"Construction",
            "type":"Services"
        }
    ],
    "sg:phone":"+1 951 925 4937",
    "sg:postcode":"92544",
    "sg:province":"CA",
    "sg:tags":[
        "house"
    ],
    "wof:name":"William A Morgan & Sons Bldrs",
    "wof:placetype":"venue"
},
  "geometry": {"coordinates":[-116.938073,33.737652],"type":"Point"}
}