{
  "type": "Feature",
  "properties": {
    "addr:full":"345 E. Stepney St Inglewood CA 90302",
    "addr:housenumber":"345",
    "addr:postcode":"90302",
    "addr:street":"E. Stepney St",
    "iso:country":"US",
    "sg:address":"345 E. Stepney St",
    "sg:city":"Inglewood",
    "sg:classifiers":[
        {
            "category":"Real Estate",
            "subcategory":"Real Estate Operator",
            "type":"Services"
        }
    ],
    "sg:phone":"+1 888 460 0309",
    "sg:postcode":"90302",
    "sg:province":"CA",
    "sg:tags":[
        "apartment"
    ],
    "wof:name":"Stepney Garden Apartments",
    "wof:placetype":"venue"
},
  "geometry": {"coordinates":[-118.35207,33.973101],"type":"Point"}
}