{
  "type": "Feature",
  "properties": {
    "addr:full":"414 Broadway Santa Monica CA 90401",
    "addr:housenumber":"414",
    "addr:postcode":"90401",
    "addr:street":"Broadway",
    "iso:country":"US",
    "sg:address":"414 Broadway",
    "sg:city":"Santa Monica",
    "sg:classifiers":[
        {
            "category":"Wholesale",
            "subcategory":"Medical Equipment & Supplies",
            "type":"Manufacturing & Wholesale Goods"
        }
    ],
    "sg:phone":"+1 310 394 4475",
    "sg:postcode":"90401",
    "sg:province":"CA",
    "sg:tags":[
        "massage"
    ],
    "sg:website":"www.bodywork-emporium.com",
    "wof:name":"Bodywork Emporium",
    "wof:placetype":"venue"
},
  "geometry": {"coordinates":[-118.493179,34.015298],"type":"Point"}
}