{
  "type": "Feature",
  "properties": {
    "iso:country":"US",
    "sg:address":"28810 Lakeview Ave",
    "sg:city":"Nuevo",
    "sg:classifiers":[
        {
            "category":"Building & Trades",
            "subcategory":"Construction",
            "type":"Services"
        }
    ],
    "sg:phone":"+1 951 928 9218",
    "sg:postcode":"92567",
    "sg:province":"CA",
    "sg:tags":[
        "mason",
        "masonry",
        "industrial",
        "contractors-commercial",
        "contractor"
    ],
    "wof:name":"Masonry Builders",
    "wof:placetype":"venue"
},
  "geometry": {"coordinates":[-117.141825,33.810259],"type":"Point"}
}