{
  "type": "Feature",
  "properties": {
    "iso:country":"US",
    "sg:address":"36445 Co Rd 31",
    "sg:city":"Davis",
    "sg:classifiers":[
        {
            "category":"Building & Trades",
            "subcategory":"Construction",
            "type":"Services"
        }
    ],
    "sg:phone":"+1 530 757 2506",
    "sg:postcode":"95616",
    "sg:province":"CA",
    "sg:tags":[
        "excavation",
        "contractor"
    ],
    "wof:name":"A and L Services Inc",
    "wof:placetype":"venue"
},
  "geometry": {"coordinates":[-121.839332,38.561546],"type":"Point"}
}