{
  "type": "Feature",
  "properties": {
    "addr:full":"516 Canfield Ct Lompoc CA 93436",
    "addr:housenumber":"516",
    "addr:postcode":"93436",
    "addr:street":"Canfield Ct",
    "iso:country":"US",
    "sg:address":"516 Canfield Ct",
    "sg:city":"Lompoc",
    "sg:classifiers":[
        {
            "category":"Professional",
            "subcategory":"Secretarial Services",
            "type":"Services"
        }
    ],
    "sg:phone":"+1 805 733 2880",
    "sg:postcode":"93436",
    "sg:province":"CA",
    "sg:tags":[
        "reporting",
        "court"
    ],
    "wof:name":"ASAP Office Support",
    "wof:placetype":"venue"
},
  "geometry": {"coordinates":[-120.452095,34.663967],"type":"Point"}
}