{
  "type": "Feature",
  "properties": {
    "addr:full":"221 Broadway St King City CA 93930",
    "addr:housenumber":"221",
    "addr:postcode":"93930",
    "addr:street":"Broadway St",
    "iso:country":"US",
    "sg:address":"221 Broadway St",
    "sg:city":"King City",
    "sg:classifiers":[
        {
            "category":"Personal",
            "subcategory":"Beauty Salon",
            "type":"Services"
        }
    ],
    "sg:phone":"+1 831 385 6324",
    "sg:postcode":"93930",
    "sg:province":"CA",
    "wof:name":"Emma's Beauty Salon",
    "wof:placetype":"venue"
},
  "geometry": {"coordinates":[-121.125174,36.213408],"type":"Point"}
}