{
  "type": "Feature",
  "properties": {
    "addr:full":"1118 Pinecrest Ave Escondido CA 92025",
    "addr:housenumber":"1118",
    "addr:postcode":"92025",
    "addr:street":"Pinecrest Ave",
    "iso:country":"US",
    "sg:address":"1118 Pinecrest Ave",
    "sg:city":"Escondido",
    "sg:classifiers":[
        {
            "category":"Wholesale",
            "subcategory":"Durable Goods & Equipment",
            "type":"Manufacturing & Wholesale Goods"
        }
    ],
    "sg:phone":"+1 760 745 9834",
    "sg:postcode":"92025",
    "sg:province":"CA",
    "sg:tags":[
        "importer"
    ],
    "wof:name":"Robert P Burrows",
    "wof:placetype":"venue"
},
  "geometry": {"coordinates":[-117.090323,33.104451],"type":"Point"}
}