{
  "type": "Feature",
  "properties": {
    "addr:full":"2481 Bella Vista Ave Martinez CA 94553",
    "addr:housenumber":"2481",
    "addr:postcode":"94553",
    "addr:street":"Bella Vista Ave",
    "iso:country":"US",
    "sg:address":"2481 Bella Vista Ave",
    "sg:city":"Martinez",
    "sg:classifiers":[
        {
            "category":"Freight",
            "type":"Transportation"
        }
    ],
    "sg:phone":"+1 925 228 9858",
    "sg:postcode":"94553",
    "sg:province":"CA",
    "sg:tags":[
        "operator",
        "trucking"
    ],
    "wof:name":"Bella Vista Trucking",
    "wof:placetype":"venue"
},
  "geometry": {"coordinates":[-122.116893,38.007477],"type":"Point"}
}