{
  "type": "Feature",
  "properties": {
    "iso:country":"US",
    "sg:address":"3376 Sheri Dr",
    "sg:city":"Simi Valley",
    "sg:classifiers":[
        {
            "category":"Building & Trades",
            "subcategory":"Cleaning & Sanitation",
            "type":"Services"
        }
    ],
    "sg:phone":"+1 805 581 2700",
    "sg:postcode":"93063",
    "sg:province":"CA",
    "sg:tags":[
        "janitor"
    ],
    "wof:name":"G & M Janitorial Svc",
    "wof:placetype":"venue"
},
  "geometry": {"coordinates":[-118.71866,34.29684],"type":"Point"}
}