{
  "type": "Feature",
  "properties": {
    "iso:country":"US",
    "sg:address":"120 S Eucalyptus Avenue",
    "sg:city":"Inglewood",
    "sg:classifiers":[
        {
            "category":"Food & Beverages",
            "subcategory":"Meat & Fish",
            "type":"Retail Goods"
        }
    ],
    "sg:phone":"+1 310 673 5300",
    "sg:postcode":"90301",
    "sg:province":"CA",
    "sg:tags":[
        "shop",
        "market"
    ],
    "wof:name":"Vennie Mac Meats",
    "wof:placetype":"venue"
},
  "geometry": {"coordinates":[-118.359559,33.962891],"type":"Point"}
}