{
  "type": "Feature",
  "properties": {
    "addr:full":"5 E Citrus Ave Redlands CA 92373",
    "addr:housenumber":"5",
    "addr:postcode":"92373",
    "addr:street":"E Citrus Ave",
    "iso:country":"US",
    "sg:address":"5 E Citrus Ave",
    "sg:city":"Redlands",
    "sg:classifiers":[
        {
            "category":"Professional",
            "type":"Services"
        }
    ],
    "sg:phone":"+1 909 793 2880",
    "sg:postcode":"92373",
    "sg:province":"CA",
    "sg:tags":[
        "establishment"
    ],
    "wof:name":"J D Logistics",
    "wof:placetype":"venue"
},
  "geometry": {"coordinates":[-117.18147999999999,34.055632],"type":"Point"}
}