{
  "type": "Feature",
  "properties": {
    "iso:country":"US",
    "sg:address":"11766 Wilshire Blvd",
    "sg:city":"Los Angeles",
    "sg:classifiers":[
        {
            "category":"Government",
            "subcategory":"Office",
            "type":"Public Place"
        }
    ],
    "sg:phone":"+1 310 477 1009",
    "sg:postcode":"90025",
    "sg:province":"CA",
    "sg:tags":[
        "federal",
        "affairs"
    ],
    "wof:name":"Croatian General Consulate",
    "wof:placetype":"venue"
},
  "geometry": {"coordinates":[-118.462619,34.048033],"type":"Point"}
}