{
  "type": "Feature",
  "properties": {
    "addr:full":"428 S Main St Sebastopol CA 95472",
    "addr:housenumber":"428",
    "addr:postcode":"95472",
    "addr:street":"S Main St",
    "iso:country":"US",
    "sg:address":"428 S Main St",
    "sg:city":"Sebastopol",
    "sg:classifiers":[
        {
            "category":"Shopping",
            "subcategory":"Department Store",
            "type":"Retail Goods"
        },
        {
            "category":"Home & Garden",
            "subcategory":"Building Materials",
            "type":"Retail Goods"
        },
        {
            "category":"Manufacturing",
            "subcategory":"Building Materials",
            "type":"Manufacturing & Wholesale Goods"
        }
    ],
    "sg:phone":"+1 707 824 9400",
    "sg:postcode":"95472",
    "sg:province":"CA",
    "sg:tags":[
        "product",
        "aluminum"
    ],
    "wof:name":"Wizard Industries",
    "wof:placetype":"venue"
},
  "geometry": {"coordinates":[-122.822481,38.398975],"type":"Point"}
}