{
  "type": "Feature",
  "properties": {
    "addr:full":"1659 Short St Berkeley CA 94702",
    "addr:housenumber":"1659",
    "addr:postcode":"94702",
    "addr:street":"Short St",
    "iso:country":"US",
    "sg:address":"1659 Short St",
    "sg:city":"Berkeley",
    "sg:classifiers":[
        {
            "category":"Health Services",
            "subcategory":"Health Practitioner",
            "type":"Services"
        },
        {
            "category":"Communications",
            "type":"Services"
        }
    ],
    "sg:phone":"+1 510 665 3795",
    "sg:postcode":"94702",
    "sg:province":"CA",
    "sg:tags":[
        "pathologist",
        "speech-language",
        "myofunctional",
        "therapy"
    ],
    "wof:name":"Susan M Bluma",
    "wof:placetype":"venue"
},
  "geometry": {"coordinates":[-122.283373,37.875172],"type":"Point"}
}