{
  "type": "Feature",
  "properties": {
    "iso:country":"US",
    "sg:address":"9098 Laguna Main St",
    "sg:city":"Elk Grove",
    "sg:classifiers":[
        {
            "category":"Banks & Credit Unions",
            "subcategory":"Investment Brokerage",
            "type":"Services"
        }
    ],
    "sg:phone":"+1 916 691 4665",
    "sg:postcode":"95758",
    "sg:province":"CA",
    "sg:tags":[
        "security"
    ],
    "wof:name":"Edward Jones Investments",
    "wof:placetype":"venue"
},
  "geometry": {"coordinates":[-121.470117,38.42641],"type":"Point"}
}