{
  "type": "Feature",
  "properties": {
    "addr:full":"6574 San Ignacio Avenue San Jose CA 95119",
    "addr:housenumber":"6574",
    "addr:postcode":"95119",
    "addr:street":"San Ignacio Avenue",
    "iso:country":"US",
    "sg:address":"6574 San Ignacio Avenue",
    "sg:city":"San Jose",
    "sg:classifiers":[
        {
            "category":"Building & Trades",
            "subcategory":"Landscaping Services",
            "type":"Services"
        }
    ],
    "sg:phone":"+1 408 225 8049",
    "sg:postcode":"95119",
    "sg:province":"CA",
    "sg:tags":[
        "gardener"
    ],
    "wof:name":"Forever Green Landscape & Maintenance",
    "wof:placetype":"venue"
},
  "geometry": {"coordinates":[-121.791076,37.228444],"type":"Point"}
}