{
  "type": "Feature",
  "properties": {
    "addr:full":"450 Golden Gate Ave Fl 2 San Francisco CA 94102",
    "addr:housenumber":"450;2",
    "addr:postcode":"94102",
    "addr:street":"Golden Gate Ave Fl",
    "iso:country":"US",
    "sg:address":"450 Golden Gate Ave Fl 2",
    "sg:city":"San Francisco",
    "sg:classifiers":[
        {
            "category":"Coffee & Tea",
            "type":"Food & Drink"
        }
    ],
    "sg:postcode":"94102",
    "sg:province":"CA",
    "wof:name":"Coffee Smith",
    "wof:placetype":"venue"
},
  "geometry": {"coordinates":[-122.417997,37.781358],"type":"Point"}
}