{
  "type": "Feature",
  "properties": {
    "addr:full":"141 E Putnam Ave Porterville CA 93257",
    "addr:housenumber":"141",
    "addr:postcode":"93257",
    "addr:street":"E Putnam Ave",
    "iso:country":"US",
    "sg:address":"141 E Putnam Ave",
    "sg:city":"Porterville",
    "sg:classifiers":[
        {
            "category":"Health Services",
            "subcategory":"Doctor",
            "type":"Services"
        },
        {
            "category":"Health Services",
            "subcategory":"Dentist",
            "type":"Services"
        }
    ],
    "sg:phone":"+1 559 781 2729",
    "sg:postcode":"93257",
    "sg:province":"CA",
    "sg:tags":[
        "dentists-oral",
        "physician",
        "maxillofacial",
        "denture",
        "dentists-prosthodontists",
        "surgeons",
        "surgery",
        "oral"
    ],
    "wof:name":"Rene Herrera Dds",
    "wof:placetype":"venue"
},
  "geometry": {"coordinates":[-119.01340399999999,36.069462],"type":"Point"}
}