{
  "type": "Feature",
  "properties": {
    "addr:full":"28939 Pleasant Knoll Ln Valley Center CA 92082",
    "addr:housenumber":"28939",
    "addr:postcode":"92082",
    "addr:street":"Pleasant Knoll Ln",
    "iso:country":"US",
    "sg:address":"28939 Pleasant Knoll Ln",
    "sg:city":"Valley Center",
    "sg:classifiers":[
        {
            "category":"Manufacturing",
            "subcategory":"Retail Goods",
            "type":"Manufacturing & Wholesale Goods"
        }
    ],
    "sg:phone":"+1 760 751 1523",
    "sg:postcode":"92082",
    "sg:province":"CA",
    "sg:tags":[
        "product",
        "mfg"
    ],
    "wof:name":"Protosaurus Studio",
    "wof:placetype":"venue"
},
  "geometry": {"coordinates":[-117.017295,33.240009],"type":"Point"}
}