{
  "type": "Feature",
  "properties": {
    "addr:full":"1144 Tourmaline Dr Newbury Park CA 91320",
    "addr:housenumber":"1144",
    "addr:postcode":"91320",
    "addr:street":"Tourmaline Dr",
    "iso:country":"US",
    "sg:address":"1144 Tourmaline Dr",
    "sg:city":"Newbury Park",
    "sg:classifiers":[
        {
            "category":"Manufacturing",
            "subcategory":"Rubber & Plastics",
            "type":"Manufacturing & Wholesale Goods"
        }
    ],
    "sg:phone":"+1 805 499 0340",
    "sg:postcode":"91320",
    "sg:province":"CA",
    "sg:tags":[
        "product"
    ],
    "sg:website":"www.westlakeplasticsusa.com",
    "wof:name":"Westlake Plastics",
    "wof:placetype":"venue"
},
  "geometry": {"coordinates":[-118.93139499999999,34.193613],"type":"Point"}
}