{
  "type": "Feature",
  "properties": {
    "addr:full":"1117 E Gutierrez St Santa Barbara CA 93103",
    "addr:housenumber":"1117",
    "addr:postcode":"93103",
    "addr:street":"E Gutierrez St",
    "iso:country":"US",
    "sg:address":"1117 E Gutierrez St",
    "sg:city":"Santa Barbara",
    "sg:classifiers":[
        {
            "category":"Professional",
            "type":"Services"
        }
    ],
    "sg:phone":"+1 805 899 8604",
    "sg:postcode":"93103",
    "sg:province":"CA",
    "wof:name":"Casa La Hoja Nueva",
    "wof:placetype":"venue"
},
  "geometry": {"coordinates":[-119.68177,34.427589],"type":"Point"}
}