{
  "type": "Feature",
  "properties": {
    "iso:country":"US",
    "sg:address":"11355 Nacimiento Lake Dr",
    "sg:city":"Bradley",
    "sg:classifiers":[
        {
            "category":"Home & Garden",
            "subcategory":"Building Materials",
            "type":"Retail Goods"
        }
    ],
    "sg:phone":"+1 805 472 9818",
    "sg:postcode":"93426",
    "sg:province":"CA",
    "sg:tags":[
        "door"
    ],
    "wof:name":"Premier Door & Window Co",
    "wof:placetype":"venue"
},
  "geometry": {"coordinates":[-120.878372,35.789173],"type":"Point"}
}