{
  "type": "Feature",
  "properties": {
    "addr:full":"12030 Hawthorne Blvd Hawthorne CA 90250",
    "addr:housenumber":"12030",
    "addr:postcode":"90250",
    "addr:street":"Hawthorne Blvd",
    "iso:country":"US",
    "sg:address":"12030 Hawthorne Blvd",
    "sg:city":"Hawthorne",
    "sg:classifiers":[
        {
            "category":"Restaurant",
            "type":"Food & Drink"
        }
    ],
    "sg:phone":"+1 310 675 0335",
    "sg:postcode":"90250",
    "sg:province":"CA",
    "wof:name":"Baja Reef A Mexican Restaurant",
    "wof:placetype":"venue"
},
  "geometry": {"coordinates":[-118.35235299999999,33.920427],"type":"Point"}
}