{
  "type": "Feature",
  "properties": {
    "iso:country":"US",
    "sg:address":"1 Civic Plaza Dr Ste 300",
    "sg:city":"Carson",
    "sg:classifiers":[
        {
            "category":"Professional",
            "subcategory":"Lawyer & Legal Services",
            "type":"Services"
        }
    ],
    "sg:phone":"+1 310 834 0973",
    "sg:postcode":"90745",
    "sg:province":"CA",
    "wof:name":"Wuister Michael R Law Offices of",
    "wof:placetype":"venue"
},
  "geometry": {"coordinates":[-118.259003,33.832802],"type":"Point"}
}