{
  "type": "Feature",
  "properties": {
    "iso:country":"US",
    "sg:address":"24642 Narbonne Ave",
    "sg:city":"Lomita",
    "sg:classifiers":[
        {
            "category":"Personal",
            "subcategory":"Barber",
            "type":"Services"
        }
    ],
    "sg:phone":"+1 310 530 5981",
    "sg:postcode":"90717",
    "sg:province":"CA",
    "wof:name":"Franks Barber Shop",
    "wof:placetype":"venue"
},
  "geometry": {"coordinates":[-118.319962,33.801651],"type":"Point"}
}