{
  "type": "Feature",
  "properties": {
    "iso:country":"US",
    "sg:address":"2940 Lytton St",
    "sg:city":"San Diego",
    "sg:classifiers":[
        {
            "category":"Food & Beverages",
            "subcategory":"Groceries & Convenience Stores",
            "type":"Retail Goods"
        }
    ],
    "sg:phone":"+1 619 226 1553",
    "sg:postcode":"92110",
    "sg:province":"CA",
    "wof:name":"AM PM Mini Mart",
    "wof:placetype":"venue"
},
  "geometry": {"coordinates":[-117.212377,32.744234],"type":"Point"}
}