{
  "type": "Feature",
  "properties": {
    "iso:country":"US",
    "sg:address":"209 N Main Ave",
    "sg:city":"Fallbrook",
    "sg:classifiers":[
        {
            "category":"Sports & Exercise",
            "subcategory":"Gym",
            "type":"Entertainment"
        }
    ],
    "sg:phone":"+1 760 451 9447",
    "sg:postcode":"92028",
    "sg:province":"CA",
    "sg:tags":[
        "personal",
        "trainer"
    ],
    "wof:name":"Body Connection",
    "wof:placetype":"venue"
},
  "geometry": {"coordinates":[-117.251287,33.38365],"type":"Point"}
}