{
  "type": "Feature",
  "properties": {
    "addr:full":"319 Miller Ave Mill Valley CA 94941",
    "addr:housenumber":"319",
    "addr:postcode":"94941",
    "addr:street":"Miller Ave",
    "iso:country":"US",
    "sg:address":"319 Miller Ave",
    "sg:city":"Mill Valley",
    "sg:classifiers":[
        {
            "category":"Health Services",
            "subcategory":"Doctor",
            "type":"Services"
        }
    ],
    "sg:phone":"+1 415 380 0700",
    "sg:postcode":"94941",
    "sg:province":"CA",
    "sg:tags":[
        "physician",
        "surgeon"
    ],
    "wof:name":"Michael Saal MD",
    "wof:placetype":"venue"
},
  "geometry": {"coordinates":[-122.539888,37.900082],"type":"Point"}
}