{
  "type": "Feature",
  "properties": {
    "addr:full":"13280 Bavarian Dr San Diego CA 92129",
    "addr:housenumber":"13280",
    "addr:postcode":"92129",
    "addr:street":"Bavarian Dr",
    "iso:country":"US",
    "sg:address":"13280 Bavarian Dr",
    "sg:city":"San Diego",
    "sg:classifiers":[
        {
            "category":"Insurance",
            "subcategory":"Insurance Agent",
            "type":"Services"
        }
    ],
    "sg:phone":"+1 858 538 6811",
    "sg:postcode":"92129",
    "sg:province":"CA",
    "wof:name":"Midland National Life Ins Co",
    "wof:placetype":"venue"
},
  "geometry": {"coordinates":[-117.140649,32.959105],"type":"Point"}
}