{
  "type": "Feature",
  "properties": {
    "iso:country":"US",
    "sg:address":"8898 Madison Ave",
    "sg:city":"Fair Oaks",
    "sg:classifiers":[
        {
            "category":"Restaurant",
            "type":"Food & Drink"
        }
    ],
    "sg:menulink":"http://www.allmenus.com/ca/sacramento/165568-del-taco/menu/",
    "sg:phone":"+1 916 966 4135",
    "sg:postcode":"95628",
    "sg:province":"CA",
    "sg:tags":[
        "american",
        "mexican",
        "tex-mex"
    ],
    "wof:name":"Del Taco",
    "wof:placetype":"venue"
},
  "geometry": {"coordinates":[-121.225899,38.66386],"type":"Point"}
}