{
  "type": "Feature",
  "properties": {
    "iso:country":"US",
    "sg:address":"640 E Dinuba Ave",
    "sg:city":"Fresno",
    "sg:classifiers":[
        {
            "category":"Shopping",
            "subcategory":"Jewelry",
            "type":"Retail Goods"
        }
    ],
    "sg:phone":"+1 559 638 6229",
    "sg:postcode":"93725",
    "sg:province":"CA",
    "sg:tags":[
        "jeweler"
    ],
    "wof:name":"Joyeria Cabrera",
    "wof:placetype":"venue"
},
  "geometry": {"coordinates":[-119.77520699999999,36.590849],"type":"Point"}
}