{
  "type": "Feature",
  "properties": {
    "addr:full":"220 Leo Ave San Jose CA 95112",
    "addr:housenumber":"220",
    "addr:postcode":"95112",
    "addr:street":"Leo Ave",
    "iso:country":"US",
    "sg:address":"220 Leo Ave",
    "sg:city":"San Jose",
    "sg:classifiers":[
        {
            "category":"Retail",
            "subcategory":"Auto Repair",
            "type":"Services"
        }
    ],
    "sg:phone":"+1 408 993 8806",
    "sg:postcode":"95112",
    "sg:province":"CA",
    "wof:name":"Amtek Auto Repair",
    "wof:placetype":"venue"
},
  "geometry": {"coordinates":[-121.86463500000001,37.310338],"type":"Point"}
}