{
  "type": "Feature",
  "properties": {
    "addr:full":"739 E Mission Rd Fallbrook CA 92028",
    "addr:housenumber":"739",
    "addr:postcode":"92028",
    "addr:street":"E Mission Rd",
    "iso:country":"US",
    "sg:address":"739 E Mission Rd",
    "sg:city":"Fallbrook",
    "sg:classifiers":[
        {
            "category":"Coffee & Tea",
            "type":"Food & Drink"
        },
        {
            "category":"Restaurant",
            "type":"Food & Drink"
        }
    ],
    "sg:phone":"+1 760 728 1898",
    "sg:postcode":"92028",
    "sg:province":"CA",
    "wof:name":"Fallbrook Cafe",
    "wof:placetype":"venue"
},
  "geometry": {"coordinates":[-117.24400300000001,33.384701],"type":"Point"}
}