{
  "type": "Feature",
  "properties": {
    "addr:full":"541 N Palm Ave Fresno CA 93728",
    "addr:housenumber":"541",
    "addr:postcode":"93728",
    "addr:street":"N Palm Ave",
    "iso:country":"US",
    "sg:address":"541 N Palm Ave",
    "sg:city":"Fresno",
    "sg:classifiers":[
        {
            "category":"Social Services",
            "subcategory":"Job Training",
            "type":"Services"
        }
    ],
    "sg:phone":"+1 559 264 5993",
    "sg:postcode":"93728",
    "sg:province":"CA",
    "sg:tags":[
        "career",
        "counseling",
        "vocational"
    ],
    "wof:name":"Accelerated Comprehensive Svc",
    "wof:placetype":"venue"
},
  "geometry": {"coordinates":[-119.808651,36.751816],"type":"Point"}
}