{
  "type": "Feature",
  "properties": {
    "iso:country":"US",
    "sg:address":"2000 Baker St",
    "sg:city":"Bakersfield",
    "sg:classifiers":[
        {
            "category":"Social Services",
            "subcategory":"Child Care",
            "type":"Services"
        }
    ],
    "sg:phone":"+1 661 325 3148",
    "sg:postcode":"93305",
    "sg:province":"CA",
    "wof:name":"Wesley Child Development Ctr",
    "wof:placetype":"venue"
},
  "geometry": {"coordinates":[-118.988112,35.39025],"type":"Point"}
}