{
  "type": "Feature",
  "properties": {
    "addr:full":"2243 Arden Way Sacramento CA 95825",
    "addr:housenumber":"2243",
    "addr:postcode":"95825",
    "addr:street":"Arden Way",
    "iso:country":"US",
    "sg:address":"2243 Arden Way",
    "sg:city":"Sacramento",
    "sg:classifiers":[
        {
            "category":"Restaurant",
            "type":"Food & Drink"
        }
    ],
    "sg:phone":"+1 916 927 8399",
    "sg:postcode":"95825",
    "sg:province":"CA",
    "sg:tags":[
        "sushi",
        "bar",
        "barbeque"
    ],
    "sg:website":"www.texwasabis.com/",
    "wof:name":"Tex Wasabi's",
    "wof:placetype":"venue"
},
  "geometry": {"coordinates":[-121.41280399999999,38.59672],"type":"Point"}
}