{
  "type": "Feature",
  "properties": {
    "addr:full":"663 N State College Blvd Fullerton CA 92831",
    "addr:housenumber":"663",
    "addr:postcode":"92831",
    "addr:street":"N State College Blvd",
    "iso:country":"US",
    "sg:address":"663 N State College Blvd",
    "sg:city":"Fullerton",
    "sg:classifiers":[
        {
            "category":"Shopping",
            "subcategory":"Used Merchandise",
            "type":"Retail Goods"
        }
    ],
    "sg:phone":"+1 714 992 6633",
    "sg:postcode":"92831",
    "sg:province":"CA",
    "sg:tags":[
        "instrument",
        "musical"
    ],
    "wof:name":"Anglin's Instruments Repair",
    "wof:placetype":"venue"
},
  "geometry": {"coordinates":[-117.88979399999999,33.877624],"type":"Point"}
}