{
  "type": "Feature",
  "properties": {
    "addr:full":"301 Hegenberger Rd Oakland CA 94621",
    "addr:housenumber":"301",
    "addr:postcode":"94621",
    "addr:street":"Hegenberger Rd",
    "iso:country":"US",
    "sg:address":"301 Hegenberger Rd",
    "sg:city":"Oakland",
    "sg:classifiers":[
        {
            "category":"Parking",
            "type":"Transportation"
        }
    ],
    "sg:phone":"+1 510 777 9000",
    "sg:postcode":"94621",
    "sg:province":"CA",
    "wof:name":"VIP Airport Parking",
    "wof:placetype":"venue"
},
  "geometry": {"coordinates":[-122.197937,37.734354],"type":"Point"}
}