{
  "type": "Feature",
  "properties": {
    "addr:full":"704 N Heliotrope Dr Los Angeles CA 90029",
    "addr:housenumber":"704",
    "addr:postcode":"90029",
    "addr:street":"N Heliotrope Dr",
    "iso:country":"US",
    "sg:address":"704 N Heliotrope Dr",
    "sg:city":"Los Angeles",
    "sg:classifiers":[
        {
            "category":"Shopping",
            "subcategory":"Party Supplies",
            "type":"Retail Goods"
        }
    ],
    "sg:phone":"+1 323 665 5488",
    "sg:postcode":"90029",
    "sg:province":"CA",
    "wof:name":"Catalyst Productions",
    "wof:placetype":"venue"
},
  "geometry": {"coordinates":[-118.29499800000001,34.084301],"type":"Point"}
}