{
  "type": "Feature",
  "properties": {
    "addr:full":"428 N Curry St Tehachapi CA 93561",
    "addr:housenumber":"428",
    "addr:postcode":"93561",
    "addr:street":"N Curry St",
    "iso:country":"US",
    "sg:address":"428 N Curry St",
    "sg:city":"Tehachapi",
    "sg:classifiers":[
        {
            "category":"Building & Trades",
            "subcategory":"Construction",
            "type":"Services"
        }
    ],
    "sg:phone":"+1 661 822 1829",
    "sg:postcode":"93561",
    "sg:province":"CA",
    "sg:tags":[
        "general",
        "contractor"
    ],
    "wof:name":"Triple C Construction",
    "wof:placetype":"venue"
},
  "geometry": {"coordinates":[-118.447906,35.135632],"type":"Point"}
}