{
  "type": "Feature",
  "properties": {
    "addr:full":"1700 McHenry Ave. Modesto CA 95350",
    "addr:housenumber":"1700",
    "addr:postcode":"ca 95350",
    "addr:street":"Mchenry Ave.",
    "iso:country":"US",
    "sg:address":"1700 McHenry Ave.",
    "sg:city":"Modesto",
    "sg:classifiers":[
        {
            "category":"Shopping Center",
            "type":"Public Place"
        }
    ],
    "sg:phone":"+1 209 523 6473",
    "sg:postcode":"95350",
    "sg:province":"CA",
    "sg:website":"www.mchenryvillage.com/",
    "wof:name":"McHenry Village Shopping Center",
    "wof:placetype":"venue"
},
  "geometry": {"coordinates":[-120.993995,37.668834],"type":"Point"}
}