{
  "type": "Feature",
  "properties": {
    "iso:country":"US",
    "sg:address":"8807 Clairemont Mesa Blvd",
    "sg:city":"San Diego",
    "sg:classifiers":[
        {
            "category":"Shopping",
            "type":"Retail Goods"
        }
    ],
    "sg:phone":"+1 858 292 8052",
    "sg:postcode":"92123",
    "sg:province":"CA",
    "sg:tags":[
        "supply",
        "bookstore",
        "church"
    ],
    "wof:name":"Berean Christian Stores",
    "wof:placetype":"venue"
},
  "geometry": {"coordinates":[-117.136002,32.831299],"type":"Point"}
}