{
  "type": "Feature",
  "properties": {
    "addr:full":"2415 Foothill Blvd La Crescenta CA 91214",
    "addr:housenumber":"2415",
    "addr:postcode":"91214",
    "addr:street":"Foothill Blvd",
    "iso:country":"US",
    "sg:address":"2415 Foothill Blvd",
    "sg:city":"La Crescenta",
    "sg:classifiers":[
        {
            "category":"Retail",
            "subcategory":"Animal Services",
            "type":"Services"
        }
    ],
    "sg:phone":"+1 818 957 3647",
    "sg:postcode":"91214",
    "sg:province":"CA",
    "sg:tags":[
        "pet",
        "training"
    ],
    "sg:website":"www.beyondtheleash.com",
    "wof:name":"Beyond The Leash",
    "wof:placetype":"venue"
},
  "geometry": {"coordinates":[-118.231843,34.219412],"type":"Point"}
}