{
  "type": "Feature",
  "properties": {
    "iso:country":"US",
    "sg:address":"213 Triangle St",
    "sg:city":"Thousand Oaks",
    "sg:classifiers":[
        {
            "category":"Professional",
            "type":"Services"
        }
    ],
    "sg:phone":"+1 805 496 8020",
    "sg:postcode":"91360",
    "sg:province":"CA",
    "wof:name":"Sticks Etc",
    "wof:placetype":"venue"
},
  "geometry": {"coordinates":[-118.871278,34.204315],"type":"Point"}
}