{
  "type": "Feature",
  "properties": {
    "addr:full":"1240 Cougar Ridge Rd Buellton CA 93427",
    "addr:housenumber":"1240",
    "addr:postcode":"93427",
    "addr:street":"Cougar Ridge Rd",
    "iso:country":"US",
    "sg:address":"1240 Cougar Ridge Rd",
    "sg:city":"Buellton",
    "sg:classifiers":[
        {
            "category":"Real Estate",
            "subcategory":"Real Estate Agent",
            "type":"Services"
        }
    ],
    "sg:phone":"+1 805 688 4168",
    "sg:postcode":"93427",
    "sg:province":"CA",
    "wof:name":"Hawkeye Investments LLC",
    "wof:placetype":"venue"
},
  "geometry": {"coordinates":[-120.205403,34.639303],"type":"Point"}
}