{
  "type": "Feature",
  "properties": {
    "iso:country":"US",
    "sg:address":"5250 College Ave",
    "sg:city":"Oakland",
    "sg:classifiers":[
        {
            "category":"Professional",
            "subcategory":"Printing & Photocopies",
            "type":"Services"
        }
    ],
    "sg:phone":"+1 510 923 0000",
    "sg:postcode":"94620",
    "sg:province":"CA",
    "sg:website":"www.greengraphics.net",
    "wof:name":"Green Graphics",
    "wof:placetype":"venue"
},
  "geometry": {"coordinates":[-122.251276,37.836951],"type":"Point"}
}