{
  "type": "Feature",
  "properties": {
    "addr:full":"5015 Eagle Rock Blvd Los Angeles CA 90041",
    "addr:housenumber":"5015",
    "addr:postcode":"90041",
    "addr:street":"Eagle Rock Blvd",
    "iso:country":"US",
    "sg:address":"5015 Eagle Rock Blvd",
    "sg:city":"Los Angeles",
    "sg:classifiers":[
        {
            "category":"Real Estate",
            "subcategory":"Surveying",
            "type":"Services"
        }
    ],
    "sg:phone":"+1 323 257 9771",
    "sg:postcode":"90041",
    "sg:province":"CA",
    "sg:tags":[
        "surveyor"
    ],
    "wof:name":"Ray Lombera & Assoc",
    "wof:placetype":"venue"
},
  "geometry": {"coordinates":[-118.21474000000001,34.137229],"type":"Point"}
}