{
  "type": "Feature",
  "properties": {
    "addr:full":"120 Stockton St San Francisco CA 94108",
    "addr:housenumber":"120",
    "addr:postcode":"94108",
    "addr:street":"Stockton St",
    "iso:country":"US",
    "sg:address":"120 Stockton St",
    "sg:city":"San Francisco",
    "sg:classifiers":[
        {
            "category":"Professional",
            "type":"Services"
        }
    ],
    "sg:phone":"+1 415 956 0565",
    "sg:postcode":"94108",
    "sg:province":"CA",
    "wof:name":"Alexandre London Inc",
    "wof:placetype":"venue"
},
  "geometry": {"coordinates":[-122.406485,37.787385],"type":"Point"}
}