{
  "type": "Feature",
  "properties": {
    "iso:country":"US",
    "sg:address":"14703 Oxnard St",
    "sg:city":"Van Nuys",
    "sg:classifiers":[
        {
            "category":"Professional",
            "type":"Services"
        }
    ],
    "sg:phone":"+1 818 994 2274",
    "sg:postcode":"91411",
    "sg:province":"CA",
    "wof:name":"Alfredo Martinez",
    "wof:placetype":"venue"
},
  "geometry": {"coordinates":[-118.457406,34.17946],"type":"Point"}
}