{
  "type": "Feature",
  "properties": {
    "addr:full":"455 E Ave Coronado CA 92118",
    "addr:housenumber":"455",
    "addr:postcode":"92118",
    "addr:street":"E Ave",
    "iso:country":"US",
    "sg:address":"455 E Ave",
    "sg:city":"Coronado",
    "sg:classifiers":[
        {
            "category":"Social Services",
            "subcategory":"Child Care",
            "type":"Services"
        }
    ],
    "sg:phone":"+1 619 435 3371",
    "sg:postcode":"92118",
    "sg:province":"CA",
    "sg:tags":[
        "elementary",
        "kindergarten",
        "school",
        "academic"
    ],
    "wof:name":"Sandpiper School",
    "wof:placetype":"venue"
},
  "geometry": {"coordinates":[-117.17800099999999,32.6945],"type":"Point"}
}