{
  "type": "Feature",
  "properties": {
    "addr:full":"2521 E Florence Ave Ste K11 Huntington Park CA 90255",
    "addr:housenumber":"2521",
    "addr:postcode":"90255",
    "addr:street":"E Florence Ave Ste K11;Park",
    "iso:country":"US",
    "sg:address":"2521 E Florence Ave Ste K11",
    "sg:city":"Huntington Park",
    "sg:classifiers":[
        {
            "category":"Restaurant",
            "type":"Food & Drink"
        }
    ],
    "sg:phone":"+1 323 589 8982",
    "sg:postcode":"90255",
    "sg:province":"CA",
    "sg:tags":[
        "mexican"
    ],
    "wof:name":"Taqueria La Crazy Chiva",
    "wof:placetype":"venue"
},
  "geometry": {"coordinates":[-118.226907,33.974534],"type":"Point"}
}