{
  "type": "Feature",
  "properties": {
    "addr:full":"1519 Texas St Bakersfield CA 93307",
    "addr:housenumber":"1519",
    "addr:postcode":"93307",
    "addr:street":"Texas St",
    "iso:country":"US",
    "sg:address":"1519 Texas St",
    "sg:city":"Bakersfield",
    "sg:classifiers":[
        {
            "category":"Shopping",
            "subcategory":"Discount & Variety Stores",
            "type":"Retail Goods"
        }
    ],
    "sg:phone":"+1 661 324 2026",
    "sg:postcode":"93307",
    "sg:province":"CA",
    "wof:name":"M & I Market",
    "wof:placetype":"venue"
},
  "geometry": {"coordinates":[-118.985427,35.357519],"type":"Point"}
}