{
  "type": "Feature",
  "properties": {
    "addr:full":"1131 Sunset Loop Lafayette CA 94549",
    "addr:housenumber":"1131",
    "addr:postcode":"94549",
    "addr:street":"Sunset Loop",
    "iso:country":"US",
    "sg:address":"1131 Sunset Loop",
    "sg:city":"Lafayette",
    "sg:classifiers":[
        {
            "category":"Food & Beverages",
            "subcategory":"Liquor & Beverages",
            "type":"Retail Goods"
        }
    ],
    "sg:phone":"+1 925 938 2160",
    "sg:postcode":"94549",
    "sg:province":"CA",
    "sg:tags":[
        "alcoholic"
    ],
    "wof:name":"Oak Barrel Winecraft",
    "wof:placetype":"venue"
},
  "geometry": {"coordinates":[-122.085729,37.89087],"type":"Point"}
}