{
  "type": "Feature",
  "properties": {
    "iso:country":"US",
    "sg:address":"445 N Capitol Ave",
    "sg:city":"San Jose",
    "sg:classifiers":[
        {
            "category":"Real Estate",
            "subcategory":"Real Estate Operator",
            "type":"Services"
        }
    ],
    "sg:phone":"+1 408 923 3119",
    "sg:postcode":"95133",
    "sg:province":"CA",
    "sg:tags":[
        "mobile",
        "home",
        "community"
    ],
    "wof:name":"LA Buona Vita-Mobile Park",
    "wof:placetype":"venue"
},
  "geometry": {"coordinates":[-121.844061,37.370998],"type":"Point"}
}