{
  "type": "Feature",
  "properties": {
    "addr:full":"8345 Firestone Blvd Downey CA 90241",
    "addr:housenumber":"8345",
    "addr:postcode":"90241",
    "addr:street":"Firestone Blvd",
    "iso:country":"US",
    "sg:address":"8345 Firestone Blvd",
    "sg:city":"Downey",
    "sg:classifiers":[
        {
            "category":"Real Estate",
            "subcategory":"Real Estate Agent",
            "type":"Services"
        }
    ],
    "sg:phone":"+1 562 862 9246",
    "sg:postcode":"90241",
    "sg:province":"CA",
    "wof:name":"Imperial Properties",
    "wof:placetype":"venue"
},
  "geometry": {"coordinates":[-118.13198199999999,33.939657],"type":"Point"}
}