{
  "type": "Feature",
  "properties": {
    "iso:country":"US",
    "sg:address":"137 Main St",
    "sg:city":"Soledad",
    "sg:classifiers":[
        {
            "category":"Professional",
            "subcategory":"Employment Agencies",
            "type":"Services"
        }
    ],
    "sg:phone":"+1 831 678 8176",
    "sg:postcode":"93960",
    "sg:province":"CA",
    "sg:tags":[
        "labor",
        "contractor"
    ],
    "wof:name":"Roberta's Labor Contracting",
    "wof:placetype":"venue"
},
  "geometry": {"coordinates":[-121.328565,36.427612],"type":"Point"}
}