{
  "type": "Feature",
  "properties": {
    "iso:country":"US",
    "sg:address":"3611 Martin Luther King J",
    "sg:city":"Lynwood",
    "sg:classifiers":[
        {
            "category":"Health Services",
            "subcategory":"Doctor",
            "type":"Services"
        }
    ],
    "sg:phone":"+1 310 639 0445",
    "sg:postcode":"90262",
    "sg:province":"CA",
    "wof:name":"Oparah Sonny MD",
    "wof:placetype":"venue"
},
  "geometry": {"coordinates":[-118.203142,33.931632],"type":"Point"}
}