{
  "type": "Feature",
  "properties": {
    "iso:country":"US",
    "sg:address":"5718 Camellia Ave",
    "sg:city":"North Hollywood",
    "sg:classifiers":[
        {
            "category":"Professional",
            "type":"Services"
        }
    ],
    "sg:phone":"+1 818 761 5317",
    "sg:postcode":"91601",
    "sg:province":"CA",
    "wof:name":"Julies Craft Creations",
    "wof:placetype":"venue"
},
  "geometry": {"coordinates":[-118.382161,34.174359],"type":"Point"}
}