{
  "type": "Feature",
  "properties": {
    "iso:country":"US",
    "sg:address":"11902 Killian St",
    "sg:city":"El Monte",
    "sg:classifiers":[
        {
            "category":"Building & Trades",
            "subcategory":"Plumbing",
            "type":"Services"
        }
    ],
    "sg:phone":"+1 626 443 6490",
    "sg:postcode":"91732",
    "sg:province":"CA",
    "sg:tags":[
        "contractor"
    ],
    "wof:name":"Le Chieu Van",
    "wof:placetype":"venue"
},
  "geometry": {"coordinates":[-118.010194,34.083242],"type":"Point"}
}