{
  "type": "Feature",
  "properties": {
    "iso:country":"US",
    "sg:address":"6882 Serenity Way",
    "sg:city":"San Jose",
    "sg:classifiers":[
        {
            "category":"Health Services",
            "subcategory":"Chiropractor",
            "type":"Services"
        }
    ],
    "sg:phone":"+1 408 289 9394",
    "sg:postcode":"95120",
    "sg:province":"CA",
    "wof:name":"Joseph Gurrieri DC",
    "wof:placetype":"venue"
},
  "geometry": {"coordinates":[-121.849041,37.211607],"type":"Point"}
}