{
  "type": "Feature",
  "properties": {
    "iso:country":"US",
    "sg:address":"10201 Reseda Blvd",
    "sg:city":"Northridge",
    "sg:classifiers":[
        {
            "category":"Retail",
            "subcategory":"Repair Shop",
            "type":"Services"
        }
    ],
    "sg:phone":"+1 818 772 8008",
    "sg:postcode":"91324",
    "sg:province":"CA",
    "sg:tags":[
        "optical",
        "good"
    ],
    "wof:name":"Rome Optics",
    "wof:placetype":"venue"
},
  "geometry": {"coordinates":[-118.536171,34.25674],"type":"Point"}
}