{
  "type": "Feature",
  "properties": {
    "addr:full":"2220 Gold Springs Ct Gold River CA 95670",
    "addr:housenumber":"2220",
    "addr:postcode":"95670",
    "addr:street":"Gold Springs Ct",
    "iso:country":"US",
    "sg:address":"2220 Gold Springs Ct",
    "sg:city":"Gold River",
    "sg:classifiers":[
        {
            "category":"Restaurant",
            "type":"Food & Drink"
        }
    ],
    "sg:phone":"+1 916 852 7533",
    "sg:postcode":"95670",
    "sg:province":"CA",
    "sg:tags":[
        "mexican"
    ],
    "wof:name":"Chevys Fresh Mex",
    "wof:placetype":"venue"
},
  "geometry": {"coordinates":[-121.265227,38.622865],"type":"Point"}
}