{
  "type": "Feature",
  "properties": {
    "addr:full":"109 Stevenson St San Francisco CA 94105",
    "addr:housenumber":"109",
    "addr:postcode":"94105",
    "addr:street":"Stevenson St",
    "iso:country":"US",
    "sg:address":"109 Stevenson St",
    "sg:city":"San Francisco",
    "sg:classifiers":[
        {
            "category":"Organizations",
            "subcategory":"Membership Organization",
            "type":"Services"
        }
    ],
    "sg:phone":"+1 415 593 3250",
    "sg:postcode":"94105",
    "sg:province":"CA",
    "sg:tags":[
        "athletic"
    ],
    "sg:website":"www.sonc.org",
    "wof:name":"Special Olympics Northern Ca",
    "wof:placetype":"venue"
},
  "geometry": {"coordinates":[-122.40136099999999,37.788311],"type":"Point"}
}