{
  "type": "Feature",
  "properties": {
    "addr:full":"2970 Monticello Rd Napa CA 94558",
    "addr:housenumber":"2970",
    "addr:postcode":"94558",
    "addr:street":"Monticello Rd",
    "iso:country":"US",
    "sg:address":"2970 Monticello Rd",
    "sg:city":"Napa",
    "sg:classifiers":[
        {
            "category":"Manufacturing",
            "subcategory":"Food",
            "type":"Manufacturing & Wholesale Goods"
        }
    ],
    "sg:phone":"+1 707 255 5280",
    "sg:postcode":"94558",
    "sg:province":"CA",
    "sg:tags":[
        "winery"
    ],
    "sg:website":"www.jarviswines.com",
    "wof:name":"Jarvis Winery",
    "wof:placetype":"venue"
},
  "geometry": {"coordinates":[-122.21837600000001,38.354015],"type":"Point"}
}