{
  "type": "Feature",
  "properties": {
    "addr:full":"5870 Stoneridge Mall Rd Pleasanton CA 94588",
    "addr:housenumber":"5870",
    "addr:postcode":"94588",
    "addr:street":"Stoneridge Mall Rd",
    "iso:country":"US",
    "sg:address":"5870 Stoneridge Mall Rd",
    "sg:city":"Pleasanton",
    "sg:classifiers":[
        {
            "category":"Banks & Credit Unions",
            "subcategory":"Investment Brokerage",
            "type":"Services"
        }
    ],
    "sg:phone":"+1 925 460 0655",
    "sg:postcode":"94588",
    "sg:province":"CA",
    "sg:tags":[
        "security"
    ],
    "wof:name":"AIG Royal Alliance",
    "wof:placetype":"venue"
},
  "geometry": {"coordinates":[-121.931994,37.696403],"type":"Point"}
}