{
  "type": "Feature",
  "properties": {
    "iso:country":"US",
    "sg:address":"22859 Sheffield Ct",
    "sg:city":"Wildomar",
    "sg:classifiers":[
        {
            "category":"Freight",
            "type":"Transportation"
        }
    ],
    "sg:phone":"+1 951 674 5707",
    "sg:postcode":"92595",
    "sg:province":"CA",
    "wof:name":"Farside Transportation",
    "wof:placetype":"venue"
},
  "geometry": {"coordinates":[-117.261436,33.634526],"type":"Point"}
}