{
  "type": "Feature",
  "properties": {
    "iso:country":"US",
    "sg:address":"803 2nd St",
    "sg:city":"Davis",
    "sg:classifiers":[
        {
            "category":"Health Services",
            "subcategory":"Doctor",
            "type":"Services"
        },
        {
            "category":"Manufacturing",
            "subcategory":"Chemicals & Compounds",
            "type":"Manufacturing & Wholesale Goods"
        },
        {
            "category":"Personal",
            "subcategory":"Hair Removal",
            "type":"Services"
        },
        {
            "category":"Personal",
            "subcategory":"Skin Care",
            "type":"Services"
        }
    ],
    "sg:phone":"+1 530 758 5492",
    "sg:postcode":"95616",
    "sg:province":"CA",
    "sg:tags":[
        "dermatology",
        "physician",
        "electrolysis",
        "cosmetic",
        "surgeons"
    ],
    "sg:website":"http://www.davislaser.com",
    "wof:name":"Davis Laser Center Inc",
    "wof:placetype":"venue"
},
  "geometry": {"coordinates":[-121.73888100000001,38.543642],"type":"Point"}
}