{
  "type": "Feature",
  "properties": {
    "addr:full":"515 W Commonwealth Ave Ste 211 Fullerton CA 92832",
    "addr:housenumber":"515",
    "addr:postcode":"92832",
    "addr:street":"W Commonwealth Ave Ste 211",
    "iso:country":"US",
    "sg:address":"515 W Commonwealth Ave Ste 211",
    "sg:city":"Fullerton",
    "sg:classifiers":[
        {
            "category":"Professional",
            "subcategory":"Business Services",
            "type":"Services"
        },
        {
            "category":"Building & Trades",
            "subcategory":"Construction",
            "type":"Services"
        }
    ],
    "sg:phone":"+1 714 526 1613",
    "sg:postcode":"92832",
    "sg:province":"CA",
    "sg:tags":[
        "consultant",
        "drafting"
    ],
    "wof:name":"Landmarks Design & Drafting",
    "wof:placetype":"venue"
},
  "geometry": {"coordinates":[-117.933797,33.8703],"type":"Point"}
}