{
  "type": "Feature",
  "properties": {
    "iso:country":"US",
    "sg:address":"4601 University Ave",
    "sg:city":"San Diego",
    "sg:classifiers":[
        {
            "category":"Food & Beverages",
            "subcategory":"Fruits & Vegetables",
            "type":"Retail Goods"
        }
    ],
    "sg:phone":"+1 619 516 3420",
    "sg:postcode":"92105",
    "sg:province":"CA",
    "sg:tags":[
        "produce"
    ],
    "wof:name":"LA Especial Produce",
    "wof:placetype":"venue"
},
  "geometry": {"coordinates":[-117.094964,32.749563],"type":"Point"}
}