{
  "type": "Feature",
  "properties": {
    "addr:full":"15229 Cll Juanito San Diego CA 92129",
    "addr:postcode":"15229;92129",
    "addr:street":"Juanito",
    "iso:country":"US",
    "sg:address":"15229 Cll Juanito",
    "sg:city":"San Diego",
    "sg:classifiers":[
        {
            "category":"Home & Garden",
            "subcategory":"Home Furnishings",
            "type":"Retail Goods"
        }
    ],
    "sg:phone":"+1 858 672 8695",
    "sg:postcode":"92129",
    "sg:province":"CA",
    "wof:name":"J & M Window Covering",
    "wof:placetype":"venue"
},
  "geometry": {"coordinates":[-117.094585,32.990223],"type":"Point"}
}