{
  "type": "Feature",
  "properties": {
    "iso:country":"US",
    "sg:address":"6633 Ming Ave",
    "sg:city":"Bakersfield",
    "sg:classifiers":[
        {
            "category":"Bars & Pubs",
            "type":"Food & Drink"
        }
    ],
    "sg:phone":"+1 661 398 7077",
    "sg:postcode":"93309",
    "sg:province":"CA",
    "wof:name":"Sports & Spirits",
    "wof:placetype":"venue"
},
  "geometry": {"coordinates":[-119.07589400000001,35.334664],"type":"Point"}
}