{
  "type": "Feature",
  "properties": {
    "iso:country":"US",
    "sg:address":"1133 B St",
    "sg:city":"Modesto",
    "sg:classifiers":[
        {
            "category":"Organizations",
            "subcategory":"Religious Organization",
            "type":"Services"
        }
    ],
    "sg:phone":"+1 209 578 6719",
    "sg:postcode":"95354",
    "sg:province":"CA",
    "sg:tags":[
        "church"
    ],
    "wof:name":"El Redentor",
    "wof:placetype":"venue"
},
  "geometry": {"coordinates":[-120.989529,37.634065],"type":"Point"}
}