{
  "type": "Feature",
  "properties": {
    "iso:country":"US",
    "sg:address":"1959 Abbott St",
    "sg:city":"San Diego",
    "sg:classifiers":[
        {
            "category":"Food & Beverages",
            "subcategory":"Specialty",
            "type":"Retail Goods"
        }
    ],
    "sg:phone":"+1 619 224 6666",
    "sg:postcode":"92107",
    "sg:province":"CA",
    "sg:tags":[
        "tea",
        "coffee",
        "brunch",
        "breakfast"
    ],
    "sg:website":"www.newbreakcafe.com",
    "wof:name":"Newbreak Coffee & Cafe",
    "wof:placetype":"venue"
},
  "geometry": {"coordinates":[-117.251895,32.748988],"type":"Point"}
}