{
  "type": "Feature",
  "properties": {
    "addr:full":"13721 Newport Ave Tustin CA 92780",
    "addr:housenumber":"13721",
    "addr:postcode":"92780",
    "addr:street":"Newport Ave",
    "iso:country":"US",
    "sg:address":"13721 Newport Ave",
    "sg:city":"Tustin",
    "sg:classifiers":[
        {
            "category":"Arts & Performance",
            "subcategory":"Art Gallery",
            "type":"Entertainment"
        }
    ],
    "sg:phone":"+1 714 544 0818",
    "sg:postcode":"92780",
    "sg:province":"CA",
    "wof:name":"Frame & Gallery",
    "wof:placetype":"venue"
},
  "geometry": {"coordinates":[-117.819,33.741299],"type":"Point"}
}