{
  "type": "Feature",
  "properties": {
    "addr:full":"1409 Foothill Blvd La Canada Fltrdg CA 91011",
    "addr:housenumber":"1409",
    "addr:postcode":"91011",
    "addr:street":"Foothill Blvd La Canada",
    "iso:country":"US",
    "sg:address":"1409 Foothill Blvd",
    "sg:city":"La Canada Fltrdg",
    "sg:classifiers":[
        {
            "category":"Social Services",
            "type":"Services"
        }
    ],
    "sg:phone":"+1 818 790 5608",
    "sg:postcode":"91011",
    "sg:province":"CA",
    "sg:tags":[
        "counselor",
        "marriage",
        "family"
    ],
    "wof:name":"Associated Counseling Svc",
    "wof:placetype":"venue"
},
  "geometry": {"coordinates":[-118.208765,34.208404],"type":"Point"}
}