{
  "type": "Feature",
  "properties": {
    "addr:full":"11801 Cardinal Cir Garden Grove CA 92843",
    "addr:housenumber":"11801",
    "addr:postcode":"92843",
    "addr:street":"Cardinal Cir",
    "iso:country":"US",
    "sg:address":"11801 Cardinal Cir",
    "sg:city":"Garden Grove",
    "sg:classifiers":[
        {
            "category":"Professional",
            "subcategory":"Engineering",
            "type":"Services"
        }
    ],
    "sg:phone":"+1 714 638 3463",
    "sg:postcode":"92843",
    "sg:province":"CA",
    "sg:tags":[
        "general",
        "contractor"
    ],
    "wof:name":"American Technologies Inc",
    "wof:placetype":"venue"
},
  "geometry": {"coordinates":[-117.92238,33.765402],"type":"Point"}
}