{
  "type": "Feature",
  "properties": {
    "addr:full":"18401 Von Karman Ave Irvine CA 92612",
    "addr:housenumber":"18401",
    "addr:postcode":"92612",
    "addr:street":"Von Karman Ave",
    "iso:country":"US",
    "sg:address":"18401 Von Karman Ave",
    "sg:city":"Irvine",
    "sg:classifiers":[
        {
            "category":"Professional",
            "subcategory":"Lawyer & Legal Services",
            "type":"Services"
        }
    ],
    "sg:phone":"+1 949 440 0119",
    "sg:postcode":"92612",
    "sg:province":"CA",
    "sg:tags":[
        "naturalization",
        "immigration"
    ],
    "sg:website":"www.fragomen.com",
    "wof:name":"Global Visa Solutions LLC",
    "wof:placetype":"venue"
},
  "geometry": {"coordinates":[-117.856413,33.672496],"type":"Point"}
}