{
  "type": "Feature",
  "properties": {
    "iso:country":"US",
    "sg:address":"14204 Beyers Ln",
    "sg:city":"Grass Valley",
    "sg:classifiers":[
        {
            "category":"Manufacturing",
            "subcategory":"Rubber & Plastics",
            "type":"Manufacturing & Wholesale Goods"
        }
    ],
    "sg:phone":"+1 530 477 1319",
    "sg:postcode":"95949",
    "sg:province":"CA",
    "sg:tags":[
        "product"
    ],
    "sg:website":"www.samadhitank.com",
    "wof:name":"Samadhi Tank Co",
    "wof:placetype":"venue"
},
  "geometry": {"coordinates":[-121.156908,39.130043],"type":"Point"}
}