{
  "type": "Feature",
  "properties": {
    "addr:full":"4856 E 2nd St Benicia CA 94510",
    "addr:housenumber":"4856",
    "addr:postcode":"94510",
    "addr:street":"E 2Nd St",
    "iso:country":"US",
    "sg:address":"4856 E 2nd St",
    "sg:city":"Benicia",
    "sg:classifiers":[
        {
            "category":"Home & Garden",
            "subcategory":"Building Materials",
            "type":"Retail Goods"
        }
    ],
    "sg:phone":"+1 707 745 4570",
    "sg:postcode":"94510",
    "sg:province":"CA",
    "sg:tags":[
        "glass",
        "window",
        "contractor",
        "plate"
    ],
    "wof:name":"Capitol Glass Co",
    "wof:placetype":"venue"
},
  "geometry": {"coordinates":[-122.128925,38.080802],"type":"Point"}
}