{
  "type": "Feature",
  "properties": {
    "addr:full":"268 Main St Salinas CA 93901",
    "addr:housenumber":"268",
    "addr:postcode":"93901",
    "addr:street":"Main St",
    "iso:country":"US",
    "sg:address":"268 Main St",
    "sg:city":"Salinas",
    "sg:classifiers":[
        {
            "category":"Shopping",
            "subcategory":"Clothing, Apparel, & Fashions",
            "type":"Retail Goods"
        }
    ],
    "sg:phone":"+1 831 422 4720",
    "sg:postcode":"93901",
    "sg:province":"CA",
    "sg:tags":[
        "shop",
        "bridal"
    ],
    "wof:name":"Bridal Fashions",
    "wof:placetype":"venue"
},
  "geometry": {"coordinates":[-121.654945,36.674209],"type":"Point"}
}