{
  "type": "Feature",
  "properties": {
    "addr:full":"526 Hofgaarden St La Puente CA 91744",
    "addr:housenumber":"526",
    "addr:postcode":"91744",
    "addr:street":"Hofgaarden St",
    "iso:country":"US",
    "sg:address":"526 Hofgaarden St",
    "sg:city":"La Puente",
    "sg:classifiers":[
        {
            "category":"Wholesale",
            "subcategory":"Durable Goods & Equipment",
            "type":"Manufacturing & Wholesale Goods"
        }
    ],
    "sg:phone":"+1 626 333 7580",
    "sg:postcode":"91744",
    "sg:province":"CA",
    "wof:name":"Sun Coast Traders",
    "wof:placetype":"venue"
},
  "geometry": {"coordinates":[-117.944478,34.013719],"type":"Point"}
}