{
  "type": "Feature",
  "properties": {
    "addr:full":"9765 Variel Ave Chatsworth CA 91311",
    "addr:housenumber":"9765",
    "addr:postcode":"91311",
    "addr:street":"Variel Ave",
    "iso:country":"US",
    "sg:address":"9765 Variel Ave",
    "sg:city":"Chatsworth",
    "sg:classifiers":[
        {
            "category":"Manufacturing",
            "subcategory":"Metals",
            "type":"Manufacturing & Wholesale Goods"
        },
        {
            "category":"Professional",
            "subcategory":"Art Services",
            "type":"Services"
        },
        {
            "category":"Home & Garden",
            "subcategory":"Building Materials",
            "type":"Retail Goods"
        },
        {
            "category":"Building & Trades",
            "subcategory":"Construction",
            "type":"Services"
        },
        {
            "category":"Manufacturing",
            "subcategory":"Building Materials",
            "type":"Manufacturing & Wholesale Goods"
        }
    ],
    "sg:phone":"+1 818 709 7853",
    "sg:postcode":"91311",
    "sg:province":"CA",
    "sg:tags":[
        "ornamental",
        "fence",
        "work",
        "contractor",
        "iron",
        "gate",
        "accessory",
        "fence-sales"
    ],
    "sg:website":"http://www.canogafence.com",
    "wof:name":"Canoga Fence & Supply Co.",
    "wof:placetype":"venue"
},
  "geometry": {"coordinates":[-118.59294800000001,34.247478],"type":"Point"}
}