{
  "type": "Feature",
  "properties": {
    "iso:country":"US",
    "sg:address":"1120 1st St",
    "sg:city":"Napa",
    "sg:classifiers":[
        {
            "category":"Shopping",
            "subcategory":"Musical Instruments",
            "type":"Retail Goods"
        }
    ],
    "sg:phone":"+1 707 224 1464",
    "sg:postcode":"94559",
    "sg:province":"CA",
    "sg:tags":[
        "piano"
    ],
    "wof:name":"Colton Piano Rentals",
    "wof:placetype":"venue"
},
  "geometry": {"coordinates":[-122.286079,38.298992],"type":"Point"}
}