{
  "type": "Feature",
  "properties": {
    "addr:full":"765 The City Dr S Ste 260 Orange CA 92868",
    "addr:housenumber":"765",
    "addr:postcode":"92868",
    "addr:street":"The City Dr S Ste 260",
    "iso:country":"US",
    "sg:address":"765 The City Dr S Ste 260",
    "sg:city":"Orange",
    "sg:classifiers":[
        {
            "category":"Social Services",
            "type":"Services"
        }
    ],
    "sg:phone":"+1 714 881 0610",
    "sg:postcode":"92868",
    "sg:province":"CA",
    "sg:tags":[
        "human"
    ],
    "sg:website":"http://www.bachelorbidauction.com",
    "wof:name":"Leukemia & Lymphoma Society",
    "wof:placetype":"venue"
},
  "geometry": {"coordinates":[-117.890174,33.775703],"type":"Point"}
}