{
  "type": "Feature",
  "properties": {
    "addr:full":"20430 Town Center Ln Cupertino CA 95014",
    "addr:housenumber":"20430",
    "addr:postcode":"95014",
    "addr:street":"Town Center Ln",
    "iso:country":"US",
    "sg:address":"20430 Town Center Ln",
    "sg:city":"Cupertino",
    "sg:classifiers":[
        {
            "category":"Health Services",
            "subcategory":"Health Practitioner",
            "type":"Services"
        }
    ],
    "sg:phone":"+1 408 268 7090",
    "sg:postcode":"95014",
    "sg:province":"CA",
    "sg:tags":[
        "pathologist",
        "speech"
    ],
    "wof:name":"Blossom Ridge Speech Ctr",
    "wof:placetype":"venue"
},
  "geometry": {"coordinates":[-122.030596,37.318182],"type":"Point"}
}