{
  "type": "Feature",
  "properties": {
    "addr:full":"663 Bristol Ave Simi Valley CA 93065",
    "addr:housenumber":"663",
    "addr:postcode":"93065",
    "addr:street":"Bristol Ave",
    "iso:country":"US",
    "sg:address":"663 Bristol Ave",
    "sg:city":"Simi Valley",
    "sg:classifiers":[
        {
            "category":"Professional",
            "subcategory":"Engineering",
            "type":"Services"
        }
    ],
    "sg:phone":"+1 805 583 8207",
    "sg:postcode":"93065",
    "sg:province":"CA",
    "sg:tags":[
        "acoustical",
        "consultant"
    ],
    "wof:name":"Advanced Engineering Acoustics",
    "wof:placetype":"venue"
},
  "geometry": {"coordinates":[-118.78518,34.251147],"type":"Point"}
}