{
  "type": "Feature",
  "properties": {
    "addr:full":"441 Stockton St San Francisco CA 94108",
    "addr:housenumber":"441",
    "addr:postcode":"94108",
    "addr:street":"Stockton St",
    "iso:country":"US",
    "sg:address":"441 Stockton St",
    "sg:city":"San Francisco",
    "sg:classifiers":[
        {
            "category":"Personal",
            "subcategory":"Shoe Repair & Shine",
            "type":"Services"
        }
    ],
    "sg:phone":"+1 415 309 4491",
    "sg:postcode":"94108",
    "sg:province":"CA",
    "sg:tags":[
        "repairing",
        "boot"
    ],
    "wof:name":"Shoe Craft",
    "wof:placetype":"venue"
},
  "geometry": {"coordinates":[-122.406975,37.789629],"type":"Point"}
}