{
  "type": "Feature",
  "properties": {
    "addr:full":"43845 10th St W Lancaster CA 93534",
    "addr:housenumber":"43845",
    "addr:postcode":"93534",
    "addr:street":"10Th St W",
    "iso:country":"US",
    "sg:address":"43845 10th St W",
    "sg:city":"Lancaster",
    "sg:classifiers":[
        {
            "category":"Health Services",
            "subcategory":"Health Practitioner",
            "type":"Services"
        }
    ],
    "sg:phone":"+1 661 729 4231",
    "sg:postcode":"93534",
    "sg:province":"CA",
    "sg:tags":[
        "therapist",
        "physical"
    ],
    "wof:name":"Healing Touch",
    "wof:placetype":"venue"
},
  "geometry": {"coordinates":[-118.147991,34.68082],"type":"Point"}
}