{
  "type": "Feature",
  "properties": {
    "iso:country":"US",
    "sg:address":"27150 Maine St",
    "sg:city":"Tomales",
    "sg:classifiers":[
        {
            "category":"Recreation",
            "type":"Entertainment"
        }
    ],
    "sg:phone":"+1 707 878 2006",
    "sg:postcode":"94971",
    "sg:province":"CA",
    "sg:tags":[
        "hall",
        "auditorium"
    ],
    "wof:name":"Tomales Town Hall",
    "wof:placetype":"venue"
},
  "geometry": {"coordinates":[-122.904553,38.248287],"type":"Point"}
}