{
  "type": "Feature",
  "properties": {
    "addr:full":"1200 Crossman Ave. 2nd Floor Sunnyvale CA 94089",
    "addr:housenumber":"1200",
    "addr:postcode":"94089",
    "addr:street":"Crossman Ave. 2Nd Floor",
    "iso:country":"US",
    "sg:address":"1200 Crossman Ave. 2nd Floor",
    "sg:city":"Sunnyvale",
    "sg:classifiers":[
        {
            "category":"Professional",
            "subcategory":"Computer Services",
            "type":"Services"
        }
    ],
    "sg:phone":"+1 408 731 9494",
    "sg:postcode":"94089",
    "sg:province":"CA",
    "sg:tags":[
        "real-time",
        "streams",
        "browsing",
        "discovery",
        "sharing",
        "content"
    ],
    "sg:website":"http://SkyGrid.com/",
    "wof:name":"SkyGrid",
    "wof:placetype":"venue"
},
  "geometry": {"coordinates":[-122.01142,37.40694],"type":"Point"}
}