{
  "type": "Feature",
  "properties": {
    "addr:full":"7221 International Blvd Oakland CA 94621",
    "addr:housenumber":"7221",
    "addr:postcode":"94621",
    "addr:street":"International Blvd",
    "iso:country":"US",
    "sg:address":"7221 International Blvd",
    "sg:city":"Oakland",
    "sg:classifiers":[
        {
            "category":"Personal",
            "subcategory":"Beauty Salon",
            "type":"Services"
        }
    ],
    "sg:phone":"+1 510 569 9084",
    "sg:postcode":"94621",
    "sg:province":"CA",
    "sg:tags":[
        "hair"
    ],
    "wof:name":"Rossy's Beauty Salon",
    "wof:placetype":"venue"
},
  "geometry": {"coordinates":[-122.18774000000001,37.759294],"type":"Point"}
}