{
  "type": "Feature",
  "properties": {
    "addr:full":"8938 Santa Monica Blvd. West Hollywood CA 90069",
    "addr:housenumber":"8938",
    "addr:postcode":"90069",
    "addr:street":"Santa Monica Blvd.",
    "iso:country":"US",
    "sg:address":"8938 Santa Monica Blvd.",
    "sg:city":"West Hollywood",
    "sg:classifiers":[
        {
            "category":"Arts & Performance",
            "subcategory":"Arts Center",
            "type":"Entertainment"
        },
        {
            "category":"Education",
            "subcategory":"Dance Studio",
            "type":"Public Place"
        }
    ],
    "sg:phone":"+1 626 476 9069",
    "sg:postcode":"90069",
    "sg:province":"CA",
    "sg:tags":[
        "performing"
    ],
    "sg:website":"beverlyhillsdancestudio.com/",
    "wof:name":"Beverly Hills Dance Studio",
    "wof:placetype":"venue"
},
  "geometry": {"coordinates":[-118.385144,34.084044],"type":"Point"}
}