{
  "type": "Feature",
  "properties": {
    "addr:full":"1717 140th Ave San Leandro CA 94578",
    "addr:housenumber":"1717",
    "addr:postcode":"94578",
    "addr:street":"140Th Ave",
    "iso:country":"US",
    "sg:address":"1717 140th Ave",
    "sg:city":"San Leandro",
    "sg:classifiers":[
        {
            "category":"Shopping",
            "subcategory":"Catalog Store",
            "type":"Retail Goods"
        }
    ],
    "sg:phone":"+1 510 483 7427",
    "sg:postcode":"94578",
    "sg:province":"CA",
    "sg:tags":[
        "mail",
        "house"
    ],
    "wof:name":"Postalgrafix",
    "wof:placetype":"venue"
},
  "geometry": {"coordinates":[-122.13466200000001,37.717899],"type":"Point"}
}