{
  "type": "Feature",
  "properties": {
    "iso:country":"US",
    "sg:address":"3220 Rio Mirada Dr",
    "sg:city":"Bakersfield",
    "sg:classifiers":[
        {
            "category":"Retail",
            "subcategory":"Repair Shop",
            "type":"Services"
        }
    ],
    "sg:phone":"+1 661 631 8979",
    "sg:postcode":"93308",
    "sg:province":"CA",
    "sg:tags":[
        "welding"
    ],
    "wof:name":"Sampson Steel Constructors",
    "wof:placetype":"venue"
},
  "geometry": {"coordinates":[-119.042839,35.398499],"type":"Point"}
}