{
  "type": "Feature",
  "properties": {
    "iso:country":"US",
    "sg:address":"3909 Stevenson Blvd",
    "sg:city":"Fremont",
    "sg:classifiers":[
        {
            "category":"Health Services",
            "subcategory":"Chiropractor",
            "type":"Services"
        }
    ],
    "sg:phone":"+1 805 563 3772",
    "sg:postcode":"94538",
    "sg:province":"CA",
    "wof:name":"Kling Chiropractic",
    "wof:placetype":"venue"
},
  "geometry": {"coordinates":[-121.972676,37.546371],"type":"Point"}
}