{
  "type": "Feature",
  "properties": {
    "addr:full":"4714 Rose Way Union City CA 94587",
    "addr:housenumber":"4714",
    "addr:postcode":"94587",
    "addr:street":"Rose Way",
    "iso:country":"US",
    "sg:address":"4714 Rose Way",
    "sg:city":"Union City",
    "sg:classifiers":[
        {
            "category":"Insurance",
            "subcategory":"Insurance Agent",
            "type":"Services"
        }
    ],
    "sg:phone":"+1 510 489 2481",
    "sg:postcode":"94587",
    "sg:province":"CA",
    "wof:name":"LA Mantia Insurance Svc",
    "wof:placetype":"venue"
},
  "geometry": {"coordinates":[-122.07709800000001,37.577596],"type":"Point"}
}