{
  "type": "Feature",
  "properties": {
    "iso:country":"US",
    "sg:address":"1232 W 134th St",
    "sg:city":"Gardena",
    "sg:classifiers":[
        {
            "category":"Wholesale",
            "subcategory":"Machinery & Supplies",
            "type":"Manufacturing & Wholesale Goods"
        }
    ],
    "sg:phone":"+1 310 538 9305",
    "sg:postcode":"90247",
    "sg:province":"CA",
    "sg:tags":[
        "equipment",
        "industrial"
    ],
    "wof:name":"Pacific Mill & Mine Supply Co",
    "wof:placetype":"venue"
},
  "geometry": {"coordinates":[-118.297456,33.910716],"type":"Point"}
}