{
  "type": "Feature",
  "properties": {
    "addr:full":"408 S Los Angeles St Los Angeles CA 90013",
    "addr:housenumber":"408",
    "addr:postcode":"90013",
    "addr:street":"S Los Angeles St",
    "iso:country":"US",
    "sg:address":"408 S Los Angeles St",
    "sg:city":"Los Angeles",
    "sg:classifiers":[
        {
            "category":"Shopping",
            "subcategory":"Gifts & Souvenirs",
            "type":"Retail Goods"
        }
    ],
    "sg:phone":"+1 213 626 3135",
    "sg:postcode":"90013",
    "sg:province":"CA",
    "sg:tags":[
        "shop"
    ],
    "wof:name":"Passion Enterprises",
    "wof:placetype":"venue"
},
  "geometry": {"coordinates":[-118.246729,34.046784],"type":"Point"}
}