{
  "type": "Feature",
  "properties": {
    "addr:full":"1 Lmu Dr # 8200 Los Angeles CA 90045",
    "addr:housenumber":"1",
    "addr:postcode":"90045",
    "addr:street":"Lmu Dr # 8200",
    "iso:country":"US",
    "sg:address":"1 Lmu Dr # 8200",
    "sg:city":"Los Angeles",
    "sg:classifiers":[
        {
            "category":"Education",
            "subcategory":"Library",
            "type":"Public Place"
        },
        {
            "category":"Education",
            "subcategory":"University",
            "type":"Public Place"
        }
    ],
    "sg:phone":"+1 310 338 2788",
    "sg:postcode":"90045",
    "sg:province":"CA",
    "sg:tags":[
        "college"
    ],
    "sg:website":"library.lmu.edu/",
    "wof:name":"William H. Hannon Library",
    "wof:placetype":"venue"
},
  "geometry": {"coordinates":[-118.419303,33.970698],"type":"Point"}
}