{
  "type": "Feature",
  "properties": {
    "iso:country":"US",
    "sg:address":"224 Ocean Ave",
    "sg:city":"Laguna Beach",
    "sg:classifiers":[
        {
            "category":"Retail",
            "subcategory":"Laundry & Dry Cleaning",
            "type":"Services"
        }
    ],
    "sg:phone":"+1 949 494 1538",
    "sg:postcode":"92651",
    "sg:province":"CA",
    "sg:tags":[
        "cleaners"
    ],
    "wof:name":"City Cleaners",
    "wof:placetype":"venue"
},
  "geometry": {"coordinates":[-117.783609,33.543229],"type":"Point"}
}