{
  "type": "Feature",
  "properties": {
    "addr:full":"705 Gold Lake Dr Folsom CA 95630",
    "addr:housenumber":"705",
    "addr:postcode":"95630",
    "addr:street":"Gold Lake Dr",
    "iso:country":"US",
    "sg:address":"705 Gold Lake Dr",
    "sg:city":"Folsom",
    "sg:classifiers":[
        {
            "category":"Food & Beverages",
            "subcategory":"Bakery",
            "type":"Retail Goods"
        }
    ],
    "sg:phone":"+1 916 985 2665",
    "sg:postcode":"95630",
    "sg:province":"CA",
    "sg:tags":[
        "baker"
    ],
    "wof:name":"Karen's Bakery Cafe & Catering",
    "wof:placetype":"venue"
},
  "geometry": {"coordinates":[-121.17982499999999,38.677078],"type":"Point"}
}