{
  "type": "Feature",
  "properties": {
    "iso:country":"US",
    "sg:address":"1421 S Dunsmuir Ave",
    "sg:city":"Los Angeles",
    "sg:classifiers":[
        {
            "category":"Organizations",
            "subcategory":"Religious Organization",
            "type":"Services"
        }
    ],
    "sg:phone":"+1 323 935 1333",
    "sg:postcode":"90019",
    "sg:province":"CA",
    "sg:tags":[
        "church"
    ],
    "wof:name":"Holy Spirit",
    "wof:placetype":"venue"
},
  "geometry": {"coordinates":[-118.354467,34.046783],"type":"Point"}
}