{
  "type": "Feature",
  "properties": {
    "iso:country":"US",
    "sg:address":"224 E Monterey Ave",
    "sg:city":"Pomona",
    "sg:classifiers":[
        {
            "category":"Home & Garden",
            "subcategory":"Household Appliances",
            "type":"Retail Goods"
        }
    ],
    "sg:phone":"+1 909 620 5088",
    "sg:postcode":"91767",
    "sg:province":"CA",
    "sg:tags":[
        "cleaners",
        "vacuum"
    ],
    "wof:name":"Kirby Of Pomona",
    "wof:placetype":"venue"
},
  "geometry": {"coordinates":[-117.746319,34.060576],"type":"Point"}
}