{
  "type": "Feature",
  "properties": {
    "addr:full":"360 N La Brea Avenue Los Angeles CA 90036",
    "addr:housenumber":"360",
    "addr:postcode":"90036",
    "addr:street":"N La Brea Avenue",
    "iso:country":"US",
    "sg:address":"360 N La Brea Avenue",
    "sg:city":"Los Angeles",
    "sg:classifiers":[
        {
            "category":"Professional",
            "type":"Services"
        }
    ],
    "sg:phone":"+1 323 937 1374",
    "sg:postcode":"90036",
    "sg:province":"CA",
    "sg:tags":[
        "caterer"
    ],
    "wof:name":"Elite Custom Caters",
    "wof:placetype":"venue"
},
  "geometry": {"coordinates":[-118.343907,34.078216],"type":"Point"}
}