{
  "type": "Feature",
  "properties": {
    "addr:full":"577 E Sierra Ave Fresno CA 93710",
    "addr:housenumber":"577",
    "addr:postcode":"93710",
    "addr:street":"E Sierra Ave",
    "iso:country":"US",
    "sg:address":"577 E Sierra Ave",
    "sg:city":"Fresno",
    "sg:classifiers":[
        {
            "category":"Education",
            "subcategory":"School",
            "type":"Public Place"
        }
    ],
    "sg:phone":"+1 559 451 4540",
    "sg:postcode":"93710",
    "sg:province":"CA",
    "wof:name":"Mc Cardle Elementary School",
    "wof:placetype":"venue"
},
  "geometry": {"coordinates":[-119.77833200000001,36.830122],"type":"Point"}
}