{
  "type": "Feature",
  "properties": {
    "iso:country":"US",
    "sg:address":"577 E Sierra Ave",
    "sg:city":"Fresno",
    "sg:classifiers":[
        {
            "category":"Education",
            "subcategory":"School",
            "type":"Public Place"
        }
    ],
    "sg:phone":"+1 559 451 4540",
    "sg:postcode":"93710",
    "sg:province":"CA",
    "wof:name":"Mc Cardle Elementary School",
    "wof:placetype":"venue"
},
  "geometry": {"coordinates":[-119.778332,36.830122],"type":"Point"}
}