{
  "type": "Feature",
  "properties": {
    "iso:country":"US",
    "sg:address":"3920 Coronado St",
    "sg:city":"Anaheim",
    "sg:classifiers":[
        {
            "category":"Manufacturing",
            "subcategory":"Metals",
            "type":"Manufacturing & Wholesale Goods"
        },
        {
            "category":"Building & Trades",
            "subcategory":"Construction",
            "type":"Services"
        }
    ],
    "sg:phone":"+1 714 524 8172",
    "sg:postcode":"92807",
    "sg:province":"CA",
    "sg:tags":[
        "steel",
        "swimming",
        "reinforcing",
        "pool",
        "contractor"
    ],
    "sg:website":"www.longswimmingpoolsteelinc.com",
    "wof:name":"Long Swimming Pool Steel Inc",
    "wof:placetype":"venue"
},
  "geometry": {"coordinates":[-117.832875,33.859145],"type":"Point"}
}