{
  "type": "Feature",
  "properties": {
    "iso:country":"US",
    "sg:address":"7249 Union Ave Ste 2B",
    "sg:city":"Whittier",
    "sg:classifiers":[
        {
            "category":"Building & Trades",
            "subcategory":"Construction",
            "type":"Services"
        }
    ],
    "sg:phone":"+1 562 215 3714",
    "sg:postcode":"90602",
    "sg:province":"CA",
    "sg:tags":[
        "handyman"
    ],
    "sg:website":"www.handymankevin.biz",
    "wof:name":"Kevin Straight's Handyman Service",
    "wof:placetype":"venue"
},
  "geometry": {"coordinates":[-118.04516599999999,33.975812],"type":"Point"}
}