{
  "type": "Feature",
  "properties": {
    "addr:full":"4612 McCray Rd Mountain Mesa CA 93240",
    "addr:postcode":"4612;93240",
    "addr:street":"Mccray Rd",
    "iso:country":"US",
    "sg:address":"4612 McCray Rd",
    "sg:city":"Mountain Mesa",
    "sg:classifiers":[
        {
            "category":"Sports & Exercise",
            "subcategory":"Bowling",
            "type":"Entertainment"
        }
    ],
    "sg:phone":"+1 760 379 3131",
    "sg:postcode":"93240",
    "sg:province":"CA",
    "sg:tags":[
        "center"
    ],
    "wof:name":"Mt Mesa Lanes",
    "wof:placetype":"venue"
},
  "geometry": {"coordinates":[-118.405922,35.638897],"type":"Point"}
}