{
  "type": "Feature",
  "properties": {
    "addr:full":"1126 N Chinowth St Visalia CA 93291",
    "addr:housenumber":"1126",
    "addr:postcode":"93291",
    "addr:street":"N Chinowth St",
    "iso:country":"US",
    "sg:address":"1126 N Chinowth St",
    "sg:city":"Visalia",
    "sg:classifiers":[
        {
            "category":"Professional",
            "subcategory":"Accounting & Tax Preparation",
            "type":"Services"
        }
    ],
    "sg:phone":"+1 559 627 3000",
    "sg:postcode":"93291",
    "sg:province":"CA",
    "sg:tags":[
        "billing"
    ],
    "wof:name":"Resource Billing & Consulting",
    "wof:placetype":"venue"
},
  "geometry": {"coordinates":[-119.336258,36.338753],"type":"Point"}
}