{
  "type": "Feature",
  "properties": {
    "iso:country":"US",
    "sg:address":"124 E Yorba Linda Blvd",
    "sg:city":"Placentia",
    "sg:classifiers":[
        {
            "category":"Personal",
            "subcategory":"Beauty Salon",
            "type":"Services"
        }
    ],
    "sg:phone":"+1 714 981 8889",
    "sg:postcode":"92870",
    "sg:province":"CA",
    "wof:name":"Hair By Suzanne",
    "wof:placetype":"venue"
},
  "geometry": {"coordinates":[-117.86432499999999,33.887699],"type":"Point"}
}