{
  "type": "Feature",
  "properties": {
    "iso:country":"US",
    "sg:address":"14255 Cll Contesa",
    "sg:city":"Victorville",
    "sg:classifiers":[
        {
            "category":"Building & Trades",
            "subcategory":"Construction",
            "type":"Services"
        }
    ],
    "sg:phone":"+1 760 951 5926",
    "sg:postcode":"92392",
    "sg:province":"CA",
    "sg:tags":[
        "maintenance",
        "contractor"
    ],
    "wof:name":"E R & Son Maintenance",
    "wof:placetype":"venue"
},
  "geometry": {"coordinates":[-117.352756,34.476053],"type":"Point"}
}