{
  "type": "Feature",
  "properties": {
    "addr:full":"1384 S Signal Dr Pomona CA 91766",
    "addr:housenumber":"1384",
    "addr:postcode":"91766",
    "addr:street":"S Signal Dr",
    "iso:country":"US",
    "sg:address":"1384 S Signal Dr",
    "sg:city":"Pomona",
    "sg:classifiers":[
        {
            "category":"Wholesale",
            "subcategory":"Construction Materials",
            "type":"Manufacturing & Wholesale Goods"
        },
        {
            "category":"Wholesale",
            "subcategory":"Metals & Minerals",
            "type":"Manufacturing & Wholesale Goods"
        }
    ],
    "sg:phone":"+1 909 623 5888",
    "sg:postcode":"91766",
    "sg:province":"CA",
    "sg:tags":[
        "steel",
        "warehouse",
        "lumber"
    ],
    "wof:name":"Galleher Lumber Co",
    "wof:placetype":"venue"
},
  "geometry": {"coordinates":[-117.726854,34.046301],"type":"Point"}
}