{
  "type": "Feature",
  "properties": {
    "addr:full":"495 Rowland Blvd Novato CA 94947",
    "addr:housenumber":"495",
    "addr:postcode":"94947",
    "addr:street":"Rowland Blvd",
    "iso:country":"US",
    "sg:address":"495 Rowland Blvd",
    "sg:city":"Novato",
    "sg:classifiers":[
        {
            "category":"Taxi",
            "type":"Transportation"
        }
    ],
    "sg:phone":"+1 415 898 8484",
    "sg:postcode":"94947",
    "sg:province":"CA",
    "sg:tags":[
        "taxicab"
    ],
    "wof:name":"Novato Taxi",
    "wof:placetype":"venue"
},
  "geometry": {"coordinates":[-122.565184,38.087863],"type":"Point"}
}