{
  "type": "Feature",
  "properties": {
    "iso:country":"US",
    "sg:address":"1146 Mason Dr",
    "sg:city":"Pacifica",
    "sg:classifiers":[
        {
            "category":"Building & Trades",
            "subcategory":"Construction",
            "type":"Services"
        }
    ],
    "sg:phone":"+1 650 738 1172",
    "sg:postcode":"94044",
    "sg:province":"CA",
    "sg:tags":[
        "general",
        "contractor"
    ],
    "wof:name":"Paul Slattery Gen Contractor",
    "wof:placetype":"venue"
},
  "geometry": {"coordinates":[-122.477771,37.597434],"type":"Point"}
}