{
  "type": "Feature",
  "properties": {
    "iso:country":"US",
    "sg:address":"3008 Sillect Ave",
    "sg:city":"Bakersfield",
    "sg:classifiers":[
        {
            "category":"Professional",
            "subcategory":"Engineering",
            "type":"Services"
        }
    ],
    "sg:phone":"+1 661 321 9414",
    "sg:postcode":"93308",
    "sg:province":"CA",
    "sg:tags":[
        "general",
        "contractor"
    ],
    "wof:name":"Infinity Engineering",
    "wof:placetype":"venue"
},
  "geometry": {"coordinates":[-119.038611,35.386542],"type":"Point"}
}