{
  "type": "Feature",
  "properties": {
    "iso:country":"US",
    "sg:address":"9513 Flintridge Way",
    "sg:city":"Orangevale",
    "sg:classifiers":[
        {
            "category":"Farming",
            "subcategory":"Livestock Farm",
            "type":"Manufacturing & Wholesale Goods"
        }
    ],
    "sg:phone":"+1 916 988 0429",
    "sg:postcode":"95662",
    "sg:province":"CA",
    "sg:tags":[
        "animal",
        "general"
    ],
    "wof:name":"North Star Ranch Inc",
    "wof:placetype":"venue"
},
  "geometry": {"coordinates":[-121.197684,38.660596],"type":"Point"}
}