{
  "type": "Feature",
  "properties": {
    "addr:full":"125 N Prairie Ave Inglewood CA 90301",
    "addr:housenumber":"125",
    "addr:postcode":"90301",
    "addr:street":"N Prairie Ave",
    "iso:country":"US",
    "sg:address":"125 N Prairie Ave",
    "sg:city":"Inglewood",
    "sg:classifiers":[
        {
            "category":"Health Services",
            "subcategory":"Doctor",
            "type":"Services"
        }
    ],
    "sg:phone":"+1 310 671 9754",
    "sg:postcode":"90301",
    "sg:province":"CA",
    "wof:name":"Maynard Walter P MD",
    "wof:placetype":"venue"
},
  "geometry": {"coordinates":[-118.344002,33.963799],"type":"Point"}
}