{
  "type": "Feature",
  "properties": {
    "iso:country":"US",
    "sg:address":"11 Western Ave",
    "sg:city":"Petaluma",
    "sg:classifiers":[
        {
            "category":"Professional",
            "type":"Services"
        }
    ],
    "sg:phone":"+1 707 283 0257",
    "sg:postcode":"94952",
    "sg:province":"CA",
    "sg:tags":[
        "establishment"
    ],
    "wof:name":"Spaulding Mccullough & Tansil",
    "wof:placetype":"venue"
},
  "geometry": {"coordinates":[-122.642076,38.233447],"type":"Point"}
}