{
  "type": "Feature",
  "properties": {
    "addr:full":"3486 E Orangethorpe Ave Placentia CA 92806",
    "addr:housenumber":"3486",
    "addr:postcode":"ca 92806",
    "addr:street":"E Orangethorpe Ave",
    "iso:country":"US",
    "sg:address":"3486 E Orangethorpe Ave",
    "sg:city":"Placentia",
    "sg:classifiers":[
        {
            "category":"Building & Trades",
            "subcategory":"Locksmith",
            "type":"Services"
        }
    ],
    "sg:phone":"+1 714 528 3984",
    "sg:postcode":"92806",
    "sg:province":"CA",
    "sg:tags":[
        "key"
    ],
    "wof:name":"Dick's Lock & Safe",
    "wof:placetype":"venue"
},
  "geometry": {"coordinates":[-117.846627,33.868615],"type":"Point"}
}