{
  "type": "Feature",
  "properties": {
    "addr:full":"6321 38th Ave Sacramento CA 95824",
    "addr:housenumber":"6321",
    "addr:postcode":"95824",
    "addr:street":"38Th Ave",
    "iso:country":"US",
    "sg:address":"6321 38th Ave",
    "sg:city":"Sacramento",
    "sg:classifiers":[
        {
            "category":"Professional",
            "type":"Services"
        }
    ],
    "sg:phone":"+1 916 455 2873",
    "sg:postcode":"95824",
    "sg:province":"CA",
    "wof:name":"Jason Plath",
    "wof:placetype":"venue"
},
  "geometry": {"coordinates":[-121.428579,38.520571],"type":"Point"}
}