{
  "type": "Feature",
  "properties": {
    "iso:country":"US",
    "sg:address":"3010 University Ave",
    "sg:city":"San Diego",
    "sg:classifiers":[
        {
            "category":"Restaurant",
            "type":"Food & Drink"
        }
    ],
    "sg:phone":"+1 619 260 8515",
    "sg:postcode":"92104",
    "sg:province":"CA",
    "sg:tags":[
        "hawaiian"
    ],
    "sg:website":"www.hanaoka-restaurant.com",
    "wof:name":"Junz Teriyaki & BBQ",
    "wof:placetype":"venue"
},
  "geometry": {"coordinates":[-117.12985399999999,32.74872],"type":"Point"}
}