{
  "type": "Feature",
  "properties": {
    "addr:full":"572 Martin Ave Rohnert Park CA 94928",
    "addr:housenumber":"572",
    "addr:postcode":"94928",
    "addr:street":"Martin Ave",
    "iso:country":"US",
    "sg:address":"572 Martin Ave",
    "sg:city":"Rohnert Park",
    "sg:classifiers":[
        {
            "category":"Building & Trades",
            "subcategory":"Construction",
            "type":"Services"
        }
    ],
    "sg:phone":"+1 707 584 7526",
    "sg:postcode":"94928",
    "sg:province":"CA",
    "sg:tags":[
        "concrete",
        "contractor"
    ],
    "sg:website":"www.millerconcrete.com",
    "wof:name":"Miller Concrete Inc",
    "wof:placetype":"venue"
},
  "geometry": {"coordinates":[-122.725483,38.354152],"type":"Point"}
}