{
  "type": "Feature",
  "properties": {
    "addr:full":"6861 Charity Ave Bakersfield CA 93308",
    "addr:housenumber":"6861",
    "addr:postcode":"93308",
    "addr:street":"Charity Ave",
    "iso:country":"US",
    "sg:address":"6861 Charity Ave",
    "sg:city":"Bakersfield",
    "sg:classifiers":[
        {
            "category":"Professional",
            "subcategory":"Engineering",
            "type":"Services"
        }
    ],
    "sg:phone":"+1 661 322 8177",
    "sg:postcode":"93308",
    "sg:province":"CA",
    "sg:tags":[
        "general",
        "contractor"
    ],
    "sg:website":"www.timec.com",
    "wof:name":"Timec Southern California Inc",
    "wof:placetype":"venue"
},
  "geometry": {"coordinates":[-119.075428,35.379723],"type":"Point"}
}