{
  "type": "Feature",
  "properties": {
    "addr:full":"7063 Commerce Cir Pleasanton CA 94588",
    "addr:housenumber":"7063",
    "addr:postcode":"94588",
    "addr:street":"Commerce Cir",
    "iso:country":"US",
    "sg:address":"7063 Commerce Cir",
    "sg:city":"Pleasanton",
    "sg:classifiers":[
        {
            "category":"Manufacturing",
            "subcategory":"Rubber & Plastics",
            "type":"Manufacturing & Wholesale Goods"
        }
    ],
    "sg:phone":"+1 925 463 0688",
    "sg:postcode":"94588",
    "sg:province":"CA",
    "sg:tags":[
        "industrial",
        "mfg"
    ],
    "wof:name":"Hose Venturer of Pleasanton",
    "wof:placetype":"venue"
},
  "geometry": {"coordinates":[-121.915863,37.698262],"type":"Point"}
}