{
  "type": "Feature",
  "properties": {
    "iso:country":"US",
    "sg:address":"3030 W 6th St",
    "sg:city":"Los Angeles",
    "sg:classifiers":[
        {
            "category":"Manufacturing",
            "subcategory":"Apparel",
            "type":"Manufacturing & Wholesale Goods"
        }
    ],
    "sg:phone":"+1 213 388 7400",
    "sg:postcode":"90020",
    "sg:province":"CA",
    "sg:tags":[
        "evening",
        "mfg",
        "better",
        "design",
        "dress",
        "day"
    ],
    "wof:name":"Sue Wong",
    "wof:placetype":"venue"
},
  "geometry": {"coordinates":[-118.288076,34.063624],"type":"Point"}
}