{
  "type": "Feature",
  "properties": {
    "addr:full":"1108 Chaucer St Berkeley CA 94702",
    "addr:housenumber":"1108",
    "addr:postcode":"94702",
    "addr:street":"Chaucer St",
    "iso:country":"US",
    "sg:address":"1108 Chaucer St",
    "sg:city":"Berkeley",
    "sg:classifiers":[
        {
            "category":"Professional",
            "type":"Services"
        }
    ],
    "sg:phone":"+1 510 549 2963",
    "sg:postcode":"94702",
    "sg:province":"CA",
    "sg:tags":[
        "publication",
        "editorial"
    ],
    "wof:name":"Owens Viani, Lisa",
    "wof:placetype":"venue"
},
  "geometry": {"coordinates":[-122.290235,37.863652],"type":"Point"}
}