{
  "type": "Feature",
  "properties": {
    "addr:full":"3998 East Ave Livermore CA 94550",
    "addr:housenumber":"3998",
    "addr:postcode":"94550",
    "addr:street":"East Ave",
    "iso:country":"US",
    "sg:address":"3998 East Ave",
    "sg:city":"Livermore",
    "sg:classifiers":[
        {
            "category":"Real Estate",
            "subcategory":"Real Estate Operator",
            "type":"Services"
        }
    ],
    "sg:phone":"+1 925 606 6246",
    "sg:postcode":"94550",
    "sg:province":"CA",
    "sg:tags":[
        "building",
        "apartment"
    ],
    "wof:name":"Arbol Verde Apts",
    "wof:placetype":"venue"
},
  "geometry": {"coordinates":[-121.751698,37.680039],"type":"Point"}
}