{
  "type": "Feature",
  "properties": {
    "addr:full":"235 Wildrose Ln Bishop CA 93514",
    "addr:housenumber":"235",
    "addr:postcode":"93514",
    "addr:street":"Wildrose Ln",
    "iso:country":"US",
    "sg:address":"235 Wildrose Ln",
    "sg:city":"Bishop",
    "sg:classifiers":[
        {
            "category":"Building & Trades",
            "subcategory":"Construction",
            "type":"Services"
        }
    ],
    "sg:phone":"+1 760 873 7718",
    "sg:postcode":"93514",
    "sg:province":"CA",
    "sg:tags":[
        "concrete",
        "contractor"
    ],
    "wof:name":"Yeager Concrete Inc",
    "wof:placetype":"venue"
},
  "geometry": {"coordinates":[-118.432976,37.359218],"type":"Point"}
}