{
  "type": "Feature",
  "properties": {
    "addr:full":"11257 Coloma Rd Gold River CA 95670",
    "addr:housenumber":"11257",
    "addr:postcode":"95670",
    "addr:street":"Coloma Rd",
    "iso:country":"US",
    "sg:address":"11257 Coloma Rd",
    "sg:city":"Gold River",
    "sg:classifiers":[
        {
            "category":"Retail",
            "subcategory":"Repair Shop",
            "type":"Services"
        }
    ],
    "sg:phone":"+1 916 638 0465",
    "sg:postcode":"95670",
    "sg:province":"CA",
    "sg:tags":[
        "cleaners",
        "parts",
        "vacuum"
    ],
    "wof:name":"Mibach Enterprises",
    "wof:placetype":"venue"
},
  "geometry": {"coordinates":[-121.266228,38.618679],"type":"Point"}
}