{
  "type": "Feature",
  "properties": {
    "iso:country":"US",
    "sg:address":"18 Princeton",
    "sg:city":"Irvine",
    "sg:classifiers":[
        {
            "category":"Professional",
            "subcategory":"Computer Services",
            "type":"Services"
        }
    ],
    "sg:phone":"+1 949 551 2461",
    "sg:postcode":"92620",
    "sg:province":"CA",
    "sg:tags":[
        "consultant"
    ],
    "wof:name":"Altos Inc",
    "wof:placetype":"venue"
},
  "geometry": {"coordinates":[-117.768645,33.714407],"type":"Point"}
}