{
  "type": "Feature",
  "properties": {
    "addr:full":"900 Cherry St Chico CA 95928",
    "addr:housenumber":"900",
    "addr:postcode":"95928",
    "addr:street":"Cherry St",
    "iso:country":"US",
    "sg:address":"900 Cherry St",
    "sg:city":"Chico",
    "sg:classifiers":[
        {
            "category":"Professional",
            "subcategory":"Management & Consulting",
            "type":"Services"
        }
    ],
    "sg:phone":"+1 530 893 0900",
    "sg:postcode":"95928",
    "sg:province":"CA",
    "sg:tags":[
        "consultant"
    ],
    "wof:name":"Rascal's",
    "wof:placetype":"venue"
},
  "geometry": {"coordinates":[-121.841469,39.721149],"type":"Point"}
}