{
  "type": "Feature",
  "properties": {
    "addr:full":"8624 Crocker St Los Angeles CA 90003",
    "addr:housenumber":"8624",
    "addr:postcode":"90003",
    "addr:street":"Crocker St",
    "iso:country":"US",
    "sg:address":"8624 Crocker St",
    "sg:city":"Los Angeles",
    "sg:classifiers":[
        {
            "category":"Professional",
            "type":"Services"
        }
    ],
    "sg:phone":"+1 818 783 3855",
    "sg:postcode":"90003",
    "sg:province":"CA",
    "sg:tags":[
        "establishment"
    ],
    "wof:name":"Cityeide Truck & Equipment",
    "wof:placetype":"venue"
},
  "geometry": {"coordinates":[-118.26796899999999,33.958414],"type":"Point"}
}