{
  "type": "Feature",
  "properties": {
    "addr:full":"2776 Barlow Dr Castro Valley CA 94546",
    "addr:housenumber":"2776",
    "addr:postcode":"94546",
    "addr:street":"Barlow Dr",
    "iso:country":"US",
    "sg:address":"2776 Barlow Dr",
    "sg:city":"Castro Valley",
    "sg:classifiers":[
        {
            "category":"Manufacturing",
            "subcategory":"Tools & Machinery",
            "type":"Manufacturing & Wholesale Goods"
        }
    ],
    "sg:phone":"+1 510 861 0365",
    "sg:postcode":"94546",
    "sg:province":"CA",
    "sg:tags":[
        "measuring",
        "instrument",
        "electrical",
        "mfg"
    ],
    "wof:name":"Martin & Cassie LLC",
    "wof:placetype":"venue"
},
  "geometry": {"coordinates":[-122.089299,37.703806],"type":"Point"}
}