{
  "type": "Feature",
  "properties": {
    "iso:country":"US",
    "sg:address":"433 Airport Blvd",
    "sg:city":"Burlingame",
    "sg:classifiers":[
        {
            "category":"Professional",
            "subcategory":"Accounting & Tax Preparation",
            "type":"Services"
        }
    ],
    "sg:phone":"+1 650 558 0876",
    "sg:postcode":"94010",
    "sg:province":"CA",
    "sg:tags":[
        "accountant"
    ],
    "wof:name":"Arshak Tchobanian CPA",
    "wof:placetype":"venue"
},
  "geometry": {"coordinates":[-122.349542,37.590135],"type":"Point"}
}