{
  "type": "Feature",
  "properties": {
    "addr:full":"16604 Arminta St Van Nuys CA 91406",
    "addr:housenumber":"16604",
    "addr:postcode":"91406",
    "addr:street":"Arminta St",
    "iso:country":"US",
    "sg:address":"16604 Arminta St",
    "sg:city":"Van Nuys",
    "sg:classifiers":[
        {
            "category":"Building & Trades",
            "subcategory":"Plumbing",
            "type":"Services"
        }
    ],
    "sg:phone":"+1 818 997 1977",
    "sg:postcode":"91406",
    "sg:province":"CA",
    "sg:tags":[
        "plumbing",
        "contractor"
    ],
    "sg:website":"www.drainsurgeon.com",
    "wof:name":"Drain Surgeon Inc",
    "wof:placetype":"venue"
},
  "geometry": {"coordinates":[-118.494364,34.214779],"type":"Point"}
}