{
  "type": "Feature",
  "properties": {
    "iso:country":"US",
    "sg:address":"5509 S Centinela Avenue",
    "sg:city":"Los Angeles",
    "sg:classifiers":[
        {
            "category":"Personal",
            "type":"Services"
        }
    ],
    "sg:phone":"+1 310 823 9510",
    "sg:postcode":"90066",
    "sg:province":"CA",
    "sg:tags":[
        "mover"
    ],
    "wof:name":"Popeye Moving Company",
    "wof:placetype":"venue"
},
  "geometry": {"coordinates":[-118.409981,33.982163],"type":"Point"}
}