{
  "type": "Feature",
  "properties": {
    "iso:country":"US",
    "sg:address":"2853 Cherry Ave",
    "sg:city":"Signal Hill",
    "sg:classifiers":[
        {
            "category":"Manufacturing",
            "subcategory":"Tools & Machinery",
            "type":"Manufacturing & Wholesale Goods"
        }
    ],
    "sg:phone":"+1 562 424 8564",
    "sg:postcode":"90755",
    "sg:province":"CA",
    "sg:tags":[
        "oil",
        "gas"
    ],
    "sg:website":"www.cavins.com",
    "wof:name":"Cavins Oil Well Tools",
    "wof:placetype":"venue"
},
  "geometry": {"coordinates":[-118.167672,33.808607],"type":"Point"}
}