{
  "type": "Feature",
  "properties": {
    "iso:country":"US",
    "sg:address":"2765 Baseline Rd",
    "sg:city":"Roseville",
    "sg:classifiers":[
        {
            "category":"Building & Trades",
            "subcategory":"Construction",
            "type":"Services"
        }
    ],
    "sg:phone":"+1 916 771 0735",
    "sg:postcode":"95747",
    "sg:province":"CA",
    "sg:tags":[
        "contractor"
    ],
    "wof:name":"Benton Design & Construction",
    "wof:placetype":"venue"
},
  "geometry": {"coordinates":[-121.329758,38.751782],"type":"Point"}
}