{
  "type": "Feature",
  "properties": {
    "iso:country":"US",
    "sg:address":"2457 Lewis Ave",
    "sg:city":"Signal Hill",
    "sg:classifiers":[
        {
            "category":"Wholesale",
            "subcategory":"Machinery & Supplies",
            "type":"Manufacturing & Wholesale Goods"
        }
    ],
    "sg:phone":"+1 562 492 9710",
    "sg:postcode":"90755",
    "sg:province":"CA",
    "sg:tags":[
        "crane",
        "derrick"
    ],
    "wof:name":"Steve's Oil Field Svc",
    "wof:placetype":"venue"
},
  "geometry": {"coordinates":[-118.17965599999999,33.802084],"type":"Point"}
}