{
  "type": "Feature",
  "properties": {
    "addr:full":"11481 Walnut St Whittier CA 90606",
    "addr:housenumber":"11481",
    "addr:postcode":"90606",
    "addr:street":"Walnut St",
    "iso:country":"US",
    "sg:address":"11481 Walnut St",
    "sg:city":"Whittier",
    "sg:classifiers":[
        {
            "category":"Shopping",
            "type":"Retail Goods"
        }
    ],
    "sg:phone":"+1 562 556 6582",
    "sg:postcode":"90606",
    "sg:province":"CA",
    "sg:tags":[
        "merchandise"
    ],
    "wof:name":"Restore Your Energy",
    "wof:placetype":"venue"
},
  "geometry": {"coordinates":[-118.073446,33.962537],"type":"Point"}
}