{
  "type": "Feature",
  "properties": {
    "addr:full":"921 19th St Bakersfield CA 93301",
    "addr:housenumber":"921",
    "addr:postcode":"93301",
    "addr:street":"19Th St",
    "iso:country":"US",
    "sg:address":"921 19th St",
    "sg:city":"Bakersfield",
    "sg:classifiers":[
        {
            "category":"Retail",
            "subcategory":"Repair Shop",
            "type":"Services"
        }
    ],
    "sg:phone":"+1 661 327 0991",
    "sg:postcode":"93301",
    "sg:province":"CA",
    "sg:tags":[
        "upholsterer"
    ],
    "wof:name":"Webster's Upholstering & Drprs",
    "wof:placetype":"venue"
},
  "geometry": {"coordinates":[-119.01173799999999,35.376274],"type":"Point"}
}