{
  "type": "Feature",
  "properties": {
    "iso:country":"US",
    "sg:address":"921 19th St",
    "sg:city":"Bakersfield",
    "sg:classifiers":[
        {
            "category":"Retail",
            "subcategory":"Repair Shop",
            "type":"Services"
        }
    ],
    "sg:phone":"+1 661 327 0991",
    "sg:postcode":"93301",
    "sg:province":"CA",
    "sg:tags":[
        "upholsterer"
    ],
    "wof:name":"Webster's Upholstering & Drprs",
    "wof:placetype":"venue"
},
  "geometry": {"coordinates":[-119.011738,35.376274],"type":"Point"}
}