{
  "type": "Feature",
  "properties": {
    "iso:country":"US",
    "sg:address":"12730 Hawthorne Boulevard",
    "sg:city":"Hawthorne",
    "sg:classifiers":[
        {
            "category":"Shopping",
            "subcategory":"Clothing, Apparel, & Fashions",
            "type":"Retail Goods"
        }
    ],
    "sg:phone":"+1 310 349 0647",
    "sg:postcode":"90250",
    "sg:province":"CA",
    "sg:tags":[
        "accessory",
        "clothing",
        "women's"
    ],
    "sg:website":"www.ashleystewart.com",
    "wof:name":"Ashley Stewart",
    "wof:placetype":"venue"
},
  "geometry": {"coordinates":[-118.352361,33.91697],"type":"Point"}
}