{
  "type": "Feature",
  "properties": {
    "addr:full":"3500 W Olive Ave Burbank CA 91506",
    "addr:housenumber":"3500",
    "addr:postcode":"91506",
    "addr:street":"W Olive Ave",
    "iso:country":"US",
    "sg:address":"3500 W Olive Ave",
    "sg:city":"Burbank",
    "sg:classifiers":[
        {
            "category":"Insurance",
            "subcategory":"Hazard Insurance",
            "type":"Services"
        }
    ],
    "sg:phone":"+1 818 567 4166",
    "sg:postcode":"91506",
    "sg:province":"CA",
    "sg:tags":[
        "carrier"
    ],
    "wof:name":"Gulf Insurance Company Inc",
    "wof:placetype":"venue"
},
  "geometry": {"coordinates":[-118.338802,34.152471],"type":"Point"}
}