{
  "type": "Feature",
  "properties": {
    "addr:full":"3220 Sports Arena Boulevard San Diego CA 92110",
    "addr:housenumber":"3220",
    "addr:postcode":"92110",
    "addr:street":"Sports Arena Boulevard",
    "iso:country":"US",
    "sg:address":"3220 Sports Arena Boulevard",
    "sg:city":"San Diego",
    "sg:classifiers":[
        {
            "category":"Home & Garden",
            "subcategory":"Garden Supply",
            "type":"Retail Goods"
        }
    ],
    "sg:phone":"+1 619 222 0487",
    "sg:postcode":"92110",
    "sg:province":"CA",
    "wof:name":"Pier 1 Imports",
    "wof:placetype":"venue"
},
  "geometry": {"coordinates":[-117.207016,32.752707],"type":"Point"}
}