{
  "type": "Feature",
  "properties": {
    "addr:full":"221 Washington St Oakland CA 94607",
    "addr:housenumber":"221",
    "addr:postcode":"94607",
    "addr:street":"Washington St",
    "iso:country":"US",
    "sg:address":"221 Washington St",
    "sg:city":"Oakland",
    "sg:classifiers":[
        {
            "category":"Professional",
            "subcategory":"Art Services",
            "type":"Services"
        }
    ],
    "sg:phone":"+1 510 627 0065",
    "sg:postcode":"94607",
    "sg:province":"CA",
    "sg:tags":[
        "photographer"
    ],
    "wof:name":"First Class Photos",
    "wof:placetype":"venue"
},
  "geometry": {"coordinates":[-122.27733499999999,37.797115],"type":"Point"}
}