{
  "type": "Feature",
  "properties": {
    "iso:country":"US",
    "sg:address":"9435 Brighton Way",
    "sg:city":"Beverly Hills",
    "sg:classifiers":[
        {
            "category":"Shopping",
            "subcategory":"Pets & Pet Supplies",
            "type":"Retail Goods"
        }
    ],
    "sg:phone":"+1 310 271 7118",
    "sg:postcode":"90210",
    "sg:province":"CA",
    "sg:tags":[
        "store"
    ],
    "sg:website":"www.ruffruffcouture.com",
    "wof:name":"Ruff Ruff Couture",
    "wof:placetype":"venue"
},
  "geometry": {"coordinates":[-118.40169,34.070213],"type":"Point"}
}