{
  "type": "Feature",
  "properties": {
    "iso:country":"US",
    "sg:address":"1239 9th Ave",
    "sg:city":"San Francisco",
    "sg:classifiers":[
        {
            "category":"Restaurant",
            "type":"Food & Drink"
        }
    ],
    "sg:phone":"+1 415 566 6011",
    "sg:postcode":"94122",
    "sg:province":"CA",
    "wof:name":"Gordo Taqueria",
    "wof:placetype":"venue"
},
  "geometry": {"coordinates":[-122.466425,37.764764],"type":"Point"}
}