{
  "type": "Feature",
  "properties": {
    "iso:country":"US",
    "sg:address":"358 S Main St",
    "sg:city":"Willits",
    "sg:classifiers":[
        {
            "category":"Shopping",
            "subcategory":"Bicycles & Sporting Goods",
            "type":"Retail Goods"
        }
    ],
    "sg:phone":"+1 707 459 3696",
    "sg:postcode":"95490",
    "sg:province":"CA",
    "wof:name":"Bike Shop Earthlab Energy Syst",
    "wof:placetype":"venue"
},
  "geometry": {"coordinates":[-123.35287,39.407938],"type":"Point"}
}