{
  "type": "Feature",
  "properties": {
    "iso:country":"US",
    "sg:address":"2256 Cleveland Ave",
    "sg:city":"Salton City",
    "sg:classifiers":[
        {
            "category":"Government",
            "subcategory":"Office",
            "type":"Public Place"
        }
    ],
    "sg:phone":"+1 760 394 4503",
    "sg:postcode":"92275",
    "sg:province":"CA",
    "sg:tags":[
        "executive"
    ],
    "wof:name":"County of Imperial",
    "wof:placetype":"venue"
},
  "geometry": {"coordinates":[-115.97722400000001,33.293793],"type":"Point"}
}