{
  "type": "Feature",
  "properties": {
    "addr:full":"763 Foothill Blvd San Luis Obispo CA 93405",
    "addr:housenumber":"763",
    "addr:postcode":"93405",
    "addr:street":"Foothill Blvd",
    "iso:country":"US",
    "sg:address":"763 Foothill Blvd",
    "sg:city":"San Luis Obispo",
    "sg:classifiers":[
        {
            "category":"Professional",
            "subcategory":"Lawyer & Legal Services",
            "type":"Services"
        }
    ],
    "sg:phone":"+1 805 927 9700",
    "sg:postcode":"93405",
    "sg:province":"CA",
    "sg:tags":[
        "attorney"
    ],
    "wof:name":"Howard Vallens Law Office",
    "wof:placetype":"venue"
},
  "geometry": {"coordinates":[-120.67222599999999,35.294023],"type":"Point"}
}