{
  "type": "Feature",
  "properties": {
    "addr:full":"38 Perry St San Francisco CA 94107",
    "addr:housenumber":"38",
    "addr:postcode":"94107",
    "addr:street":"Perry St",
    "iso:country":"US",
    "sg:address":"38 Perry St",
    "sg:city":"San Francisco",
    "sg:classifiers":[
        {
            "category":"Shopping",
            "type":"Retail Goods"
        }
    ],
    "sg:phone":"+1 415 546 1467",
    "sg:postcode":"94107",
    "sg:province":"CA",
    "sg:tags":[
        "candle"
    ],
    "wof:name":"Robb Steck Chandlery",
    "wof:placetype":"venue"
},
  "geometry": {"coordinates":[-122.39565899999999,37.783096],"type":"Point"}
}