{
  "type": "Feature",
  "properties": {
    "addr:full":"735 Montgomery San Francisco CA 94111",
    "addr:housenumber":"735",
    "addr:postcode":"94111",
    "addr:street":"Montgomery",
    "iso:country":"US",
    "sg:address":"735 Montgomery",
    "sg:city":"San Francisco",
    "sg:classifiers":[
        {
            "category":"Professional",
            "subcategory":"Lawyer & Legal Services",
            "type":"Services"
        }
    ],
    "sg:phone":"+1 415 956 9200",
    "sg:postcode":"94111",
    "sg:province":"CA",
    "sg:tags":[
        "litigation"
    ],
    "sg:website":"www.walstonlaw.com",
    "wof:name":"Walston Legal Group",
    "wof:placetype":"venue"
},
  "geometry": {"coordinates":[-122.403392,37.796132],"type":"Point"}
}