{
  "type": "Feature",
  "properties": {
    "addr:full":"3700 Vaca Valley Pkwy Vacaville CA 95688",
    "addr:housenumber":"3700",
    "addr:postcode":"95688",
    "addr:street":"Vaca Valley Pkwy",
    "iso:country":"US",
    "sg:address":"3700 Vaca Valley Pkwy",
    "sg:city":"Vacaville",
    "sg:classifiers":[
        {
            "category":"Health Services",
            "subcategory":"Doctor",
            "type":"Services"
        }
    ],
    "sg:phone":"+1 707 453 5055",
    "sg:postcode":"95688",
    "sg:province":"CA",
    "sg:tags":[
        "physician",
        "surgeon"
    ],
    "wof:name":"Vacaville Medical",
    "wof:placetype":"venue"
},
  "geometry": {"coordinates":[-121.935875,38.390094],"type":"Point"}
}