{
  "type": "Feature",
  "properties": {
    "iso:country":"US",
    "sg:address":"637 Paradise Rd",
    "sg:city":"Modesto",
    "sg:classifiers":[
        {
            "category":"Food & Beverages",
            "subcategory":"Groceries & Convenience Stores",
            "type":"Retail Goods"
        }
    ],
    "sg:phone":"+1 209 523 3564",
    "sg:postcode":"95351",
    "sg:province":"CA",
    "wof:name":"Khampong Cham Market",
    "wof:placetype":"venue"
},
  "geometry": {"coordinates":[-121.01599899999999,37.624802],"type":"Point"}
}