{
  "type": "Feature",
  "properties": {
    "iso:country":"US",
    "sg:address":"1427 Kenora St",
    "sg:city":"Escondido",
    "sg:classifiers":[
        {
            "category":"Manufacturing",
            "subcategory":"Tools & Machinery",
            "type":"Manufacturing & Wholesale Goods"
        }
    ],
    "sg:phone":"+1 760 747 2623",
    "sg:postcode":"92027",
    "sg:province":"CA",
    "sg:tags":[
        "machine",
        "mfg",
        "accessory"
    ],
    "wof:name":"Patrick Warner",
    "wof:placetype":"venue"
},
  "geometry": {"coordinates":[-117.05748699999999,33.123963],"type":"Point"}
}