{
  "type": "Feature",
  "properties": {
    "iso:country":"US",
    "sg:address":"4501 Jamboree Road",
    "sg:city":"Newport Beach",
    "sg:classifiers":[
        {
            "category":"Fast Food",
            "type":"Food & Drink"
        }
    ],
    "sg:phone":"+1 949 752 9626",
    "sg:postcode":"92660",
    "sg:province":"CA",
    "wof:name":"Wienerschnitzel",
    "wof:placetype":"venue"
},
  "geometry": {"coordinates":[-117.85696299999999,33.6635],"type":"Point"}
}