{
  "type": "Feature",
  "properties": {
    "iso:country":"US",
    "sg:address":"4050 Market St",
    "sg:city":"Ventura",
    "sg:classifiers":[
        {
            "category":"Place Of Worship",
            "subcategory":"Church",
            "type":"Public Place"
        },
        {
            "category":"Place Of Worship",
            "type":"Public Place"
        }
    ],
    "sg:phone":"+1 805 658 7646",
    "sg:postcode":"93003",
    "sg:province":"CA",
    "sg:tags":[
        "churches-interdenominational",
        "churches-charismatic",
        "churches-various",
        "denomination"
    ],
    "wof:name":"South Coast Fellowship",
    "wof:placetype":"venue"
},
  "geometry": {"coordinates":[-119.239741,34.259247],"type":"Point"}
}