{
  "type": "Feature",
  "properties": {
    "addr:full":"7928 W 3rd St Los Angeles CA 90048",
    "addr:housenumber":"7928",
    "addr:postcode":"90048",
    "addr:street":"W 3Rd St",
    "iso:country":"US",
    "sg:address":"7928 W 3rd St",
    "sg:city":"Los Angeles",
    "sg:classifiers":[
        {
            "category":"Personal",
            "subcategory":"Beauty Salon",
            "type":"Services"
        }
    ],
    "sg:phone":"+1 323 782 1443",
    "sg:postcode":"90048",
    "sg:province":"CA",
    "wof:name":"Millennium Salon",
    "wof:placetype":"venue"
},
  "geometry": {"coordinates":[-118.363439,34.071711],"type":"Point"}
}