{
  "type": "Feature",
  "properties": {
    "addr:full":"2055 D St Hayward CA 94541",
    "addr:housenumber":"2055",
    "addr:postcode":"94541",
    "addr:street":"D St",
    "iso:country":"US",
    "sg:address":"2055 D St",
    "sg:city":"Hayward",
    "sg:classifiers":[
        {
            "category":"Personal",
            "subcategory":"Beauty Salon",
            "type":"Services"
        }
    ],
    "sg:phone":"+1 510 690 3231",
    "sg:postcode":"94541",
    "sg:province":"CA",
    "sg:tags":[
        "hair"
    ],
    "wof:name":"Braids by Ms Attitude",
    "wof:placetype":"venue"
},
  "geometry": {"coordinates":[-122.06120199999999,37.678454],"type":"Point"}
}