{
  "type": "Feature",
  "properties": {
    "addr:full":"6929 Sunrise Blvd Citrus Heights CA 95610",
    "addr:housenumber":"6929",
    "addr:postcode":"95610",
    "addr:street":"Sunrise Blvd",
    "iso:country":"US",
    "sg:address":"6929 Sunrise Blvd",
    "sg:city":"Citrus Heights",
    "sg:classifiers":[
        {
            "category":"Professional",
            "subcategory":"Accounting & Tax Preparation",
            "type":"Services"
        }
    ],
    "sg:phone":"+1 916 722 8991",
    "sg:postcode":"95610",
    "sg:province":"CA",
    "sg:tags":[
        "accountant"
    ],
    "wof:name":"Willis & Walsh",
    "wof:placetype":"venue"
},
  "geometry": {"coordinates":[-121.271787,38.694984],"type":"Point"}
}