{
  "type": "Feature",
  "properties": {
    "iso:country":"US",
    "sg:address":"2624 el Camino Real",
    "sg:city":"Salinas",
    "sg:classifiers":[
        {
            "category":"Building & Trades",
            "subcategory":"Landscaping Services",
            "type":"Services"
        }
    ],
    "sg:phone":"+1 831 663 0214",
    "sg:postcode":"93907",
    "sg:province":"CA",
    "sg:tags":[
        "landscape",
        "contractor"
    ],
    "sg:website":"www.lclc.com",
    "wof:name":"Leon F Conner Landscape Contr",
    "wof:placetype":"venue"
},
  "geometry": {"coordinates":[-121.660877,36.80125],"type":"Point"}
}