{
  "type": "Feature",
  "properties": {
    "addr:full":"5616 Bay St Emeryville CA 94608",
    "addr:housenumber":"5616",
    "addr:postcode":"94608",
    "addr:street":"Bay St",
    "iso:country":"US",
    "sg:address":"5616 Bay St",
    "sg:city":"Emeryville",
    "sg:classifiers":[
        {
            "category":"Shopping",
            "type":"Retail Goods"
        }
    ],
    "sg:phone":"+1 510 652 2833",
    "sg:postcode":"94608",
    "sg:province":"CA",
    "sg:website":"www.calendars.com",
    "wof:name":"Calendar Club",
    "wof:placetype":"venue"
},
  "geometry": {"coordinates":[-122.292281,37.833615],"type":"Point"}
}