{
  "type": "Feature",
  "properties": {
    "addr:full":"5749 Lone Tree Way Antioch CA 94509",
    "addr:housenumber":"5749",
    "addr:postcode":"ca 94509",
    "addr:street":"Lone Tree Way",
    "iso:country":"US",
    "sg:address":"5749 Lone Tree Way",
    "sg:city":"Antioch",
    "sg:classifiers":[
        {
            "category":"Shopping",
            "subcategory":"Shoes",
            "type":"Retail Goods"
        }
    ],
    "sg:phone":"+1 925 757 3583",
    "sg:postcode":"94509",
    "sg:province":"CA",
    "wof:name":"Payless Shoe Source",
    "wof:placetype":"venue"
},
  "geometry": {"coordinates":[-121.75502899999999,37.961794],"type":"Point"}
}