{
  "type": "Feature",
  "properties": {
    "iso:country":"US",
    "sg:address":"345 Sacramento St",
    "sg:city":"Auburn",
    "sg:classifiers":[
        {
            "category":"Building & Trades",
            "subcategory":"Plumbing",
            "type":"Services"
        }
    ],
    "sg:phone":"+1 530 823 0114",
    "sg:postcode":"95603",
    "sg:province":"CA",
    "sg:tags":[
        "conditioning",
        "air",
        "system",
        "contractor"
    ],
    "wof:name":"Sierra Air Conditioning",
    "wof:placetype":"venue"
},
  "geometry": {"coordinates":[-121.076139,38.889727],"type":"Point"}
}