{
  "type": "Feature",
  "properties": {
    "addr:full":"1335 Coleman Avenue Santa Clara CA 95050",
    "addr:housenumber":"1335",
    "addr:postcode":"95050",
    "addr:street":"Coleman Avenue",
    "iso:country":"US",
    "sg:address":"1335 Coleman Avenue",
    "sg:city":"Santa Clara",
    "sg:classifiers":[
        {
            "category":"Retail",
            "subcategory":"Laundry & Dry Cleaning",
            "type":"Services"
        }
    ],
    "sg:phone":"+1 408 986 8055",
    "sg:postcode":"95050",
    "sg:province":"CA",
    "wof:name":"Friendly Cleaners",
    "wof:placetype":"venue"
},
  "geometry": {"coordinates":[-121.93622499999999,37.35694],"type":"Point"}
}