{
  "type": "Feature",
  "properties": {
    "addr:full":"11921 Goldring Rd Arcadia CA 91006",
    "addr:housenumber":"11921",
    "addr:postcode":"91006",
    "addr:street":"Goldring Rd",
    "iso:country":"US",
    "sg:address":"11921 Goldring Rd",
    "sg:city":"Arcadia",
    "sg:classifiers":[
        {
            "category":"Manufacturing",
            "subcategory":"Chemicals & Compounds",
            "type":"Manufacturing & Wholesale Goods"
        }
    ],
    "sg:phone":"+1 626 930 9135",
    "sg:postcode":"91006",
    "sg:province":"CA",
    "sg:tags":[
        "fertilizer"
    ],
    "wof:name":"L T Biosyn Inc",
    "wof:placetype":"venue"
},
  "geometry": {"coordinates":[-118.005197,34.100406],"type":"Point"}
}