{
  "type": "Feature",
  "properties": {
    "addr:full":"1009 W Taft Ave Orange CA 92865",
    "addr:housenumber":"1009",
    "addr:postcode":"92865",
    "addr:street":"W Taft Ave",
    "iso:country":"US",
    "sg:address":"1009 W Taft Ave",
    "sg:city":"Orange",
    "sg:classifiers":[
        {
            "category":"Building & Trades",
            "subcategory":"Construction",
            "type":"Services"
        }
    ],
    "sg:phone":"+1 714 612 9523",
    "sg:postcode":"92865",
    "sg:province":"CA",
    "sg:tags":[
        "restoration",
        "cleaning",
        "patio",
        "deck"
    ],
    "wof:name":"All American High Pressure Wsh",
    "wof:placetype":"venue"
},
  "geometry": {"coordinates":[-117.867302,33.815725],"type":"Point"}
}