{
  "type": "Feature",
  "properties": {
    "addr:full":"16217 Clark Ave Bellflower CA 90706",
    "addr:housenumber":"16217",
    "addr:postcode":"90706",
    "addr:street":"Clark Ave",
    "iso:country":"US",
    "sg:address":"16217 Clark Ave",
    "sg:city":"Bellflower",
    "sg:classifiers":[
        {
            "category":"Real Estate",
            "subcategory":"Real Estate Services",
            "type":"Services"
        }
    ],
    "sg:phone":"+1 562 925 7233",
    "sg:postcode":"90706",
    "sg:province":"CA",
    "sg:tags":[
        "management",
        "property"
    ],
    "wof:name":"Preferred Property Management",
    "wof:placetype":"venue"
},
  "geometry": {"coordinates":[-118.13400300000001,33.8867],"type":"Point"}
}