{
  "type": "Feature",
  "properties": {
    "addr:full":"8001 Irvine Center Dr Ste 1170 Irvine CA 92618",
    "addr:housenumber":"8001",
    "addr:postcode":"92618",
    "addr:street":"Irvine Center Dr Ste 1170",
    "iso:country":"US",
    "sg:address":"8001 Irvine Center Dr Ste 1170",
    "sg:city":"Irvine",
    "sg:classifiers":[
        {
            "category":"Restaurant",
            "type":"Food & Drink"
        }
    ],
    "sg:phone":"+1 562 628 0454",
    "sg:postcode":"92618",
    "sg:province":"CA",
    "wof:name":"Tequila Jack's",
    "wof:placetype":"venue"
},
  "geometry": {"coordinates":[-117.74900100000001,33.655201],"type":"Point"}
}