{
  "type": "Feature",
  "properties": {
    "addr:full":"22591 Rd 132 Tulare CA 93274",
    "addr:housenumber":"22591",
    "addr:postcode":"93274",
    "addr:street":"Rd 132",
    "iso:country":"US",
    "sg:address":"22591 Rd 132",
    "sg:city":"Tulare",
    "sg:classifiers":[
        {
            "category":"Manufacturing",
            "subcategory":"Metals",
            "type":"Manufacturing & Wholesale Goods"
        }
    ],
    "sg:phone":"+1 559 685 8634",
    "sg:postcode":"93274",
    "sg:province":"CA",
    "sg:tags":[
        "fabricator",
        "sheet"
    ],
    "wof:name":"Hilvers Dairy Fabricating",
    "wof:placetype":"venue"
},
  "geometry": {"coordinates":[-119.27813,36.196802],"type":"Point"}
}