{
  "type": "Feature",
  "properties": {
    "addr:full":"11258 Green Arbor Dr Riverside CA 92505",
    "addr:housenumber":"11258",
    "addr:postcode":"92505",
    "addr:street":"Green Arbor Dr",
    "iso:country":"US",
    "sg:address":"11258 Green Arbor Dr",
    "sg:city":"Riverside",
    "sg:classifiers":[
        {
            "category":"Building & Trades",
            "subcategory":"Construction",
            "type":"Services"
        }
    ],
    "sg:phone":"+1 951 352 6475",
    "sg:postcode":"92505",
    "sg:province":"CA",
    "sg:tags":[
        "painter"
    ],
    "wof:name":"Sam's Painting Co",
    "wof:placetype":"venue"
},
  "geometry": {"coordinates":[-117.49677800000001,33.924407],"type":"Point"}
}