{
  "type": "Feature",
  "properties": {
    "addr:full":"1149 S Hill St Los Angeles CA 90015",
    "addr:housenumber":"1149",
    "addr:postcode":"90015",
    "addr:street":"S Hill St",
    "iso:country":"US",
    "sg:address":"1149 S Hill St",
    "sg:city":"Los Angeles",
    "sg:classifiers":[
        {
            "category":"Restaurant",
            "type":"Food & Drink"
        }
    ],
    "sg:phone":"+1 213 741 0034",
    "sg:postcode":"90015",
    "sg:province":"CA",
    "sg:tags":[
        "japanese"
    ],
    "sg:website":"www.mitakirestaurants.net",
    "wof:name":"Mitaki",
    "wof:placetype":"venue"
},
  "geometry": {"coordinates":[-118.260762,34.039153],"type":"Point"}
}