{
  "type": "Feature",
  "properties": {
    "addr:full":"347 E 1st St Los Angeles CA 90012",
    "addr:housenumber":"347",
    "addr:postcode":"90012",
    "addr:street":"E 1St St",
    "iso:country":"US",
    "sg:address":"347 E 1st St",
    "sg:city":"Los Angeles",
    "sg:classifiers":[
        {
            "category":"Restaurant",
            "type":"Food & Drink"
        }
    ],
    "sg:phone":"+1 213 617 9990",
    "sg:postcode":"90012",
    "sg:province":"CA",
    "sg:tags":[
        "chinese"
    ],
    "sg:website":"www.chopsueycafeandlounge.com",
    "wof:name":"Chop Suey Cafe and Lounge",
    "wof:placetype":"venue"
},
  "geometry": {"coordinates":[-118.239676,34.049551],"type":"Point"}
}