{
  "type": "Feature",
  "properties": {
    "addr:full":"4667 Mission St San Francisco CA 94112",
    "addr:housenumber":"4667",
    "addr:postcode":"94112",
    "addr:street":"Mission St",
    "iso:country":"US",
    "sg:address":"4667 Mission St",
    "sg:city":"San Francisco",
    "sg:classifiers":[
        {
            "category":"Building & Trades",
            "subcategory":"Construction",
            "type":"Services"
        }
    ],
    "sg:phone":"+1 415 841 9172",
    "sg:postcode":"94112",
    "sg:province":"CA",
    "sg:tags":[
        "contractor"
    ],
    "wof:name":"Narrowback Construction",
    "wof:placetype":"venue"
},
  "geometry": {"coordinates":[-122.43544199999999,37.723576],"type":"Point"}
}