{
  "type": "Feature",
  "properties": {
    "iso:country":"US",
    "sg:address":"1916 Colony St",
    "sg:city":"Mountain View",
    "sg:classifiers":[
        {
            "category":"Building & Trades",
            "subcategory":"Construction",
            "type":"Services"
        }
    ],
    "sg:phone":"+1 650 964 7021",
    "sg:postcode":"94043",
    "sg:province":"CA",
    "sg:tags":[
        "contractor"
    ],
    "wof:name":"Regis Contractors of Northern California Llp",
    "wof:placetype":"venue"
},
  "geometry": {"coordinates":[-122.087656,37.415694],"type":"Point"}
}