{
  "type": "Feature",
  "properties": {
    "addr:full":"106 N Riverside Ave Rialto CA 92376",
    "addr:housenumber":"106",
    "addr:postcode":"92376",
    "addr:street":"N Riverside Ave",
    "iso:country":"US",
    "sg:address":"106 N Riverside Ave",
    "sg:city":"Rialto",
    "sg:classifiers":[
        {
            "category":"Personal",
            "subcategory":"Beauty Salon",
            "type":"Services"
        }
    ],
    "sg:phone":"+1 909 820 9679",
    "sg:postcode":"92376",
    "sg:province":"CA",
    "wof:name":"Health & Beauty Day Spa",
    "wof:placetype":"venue"
},
  "geometry": {"coordinates":[-117.370256,34.101435],"type":"Point"}
}