{
  "type": "Feature",
  "properties": {
    "iso:country":"US",
    "sg:address":"1945 N Fine Ave",
    "sg:city":"Fresno",
    "sg:classifiers":[
        {
            "category":"Local Transit",
            "type":"Transportation"
        }
    ],
    "sg:phone":"+1 559 454 1321",
    "sg:postcode":"93727",
    "sg:province":"CA",
    "sg:tags":[
        "passenger",
        "limousine"
    ],
    "sg:website":"www.whitediamondlimo.com",
    "wof:name":"White Diamond Touch Limousine",
    "wof:placetype":"venue"
},
  "geometry": {"coordinates":[-119.72867,36.768958],"type":"Point"}
}