{
  "type": "Feature",
  "properties": {
    "iso:country":"US",
    "sg:address":"1101 Airport Rd",
    "sg:city":"Imperial",
    "sg:classifiers":[
        {
            "category":"Education",
            "subcategory":"Special Training",
            "type":"Public Place"
        }
    ],
    "sg:phone":"+1 760 355 1275",
    "sg:postcode":"92251",
    "sg:province":"CA",
    "sg:tags":[
        "instruction",
        "driving"
    ],
    "wof:name":"Benavidez Certified Traffic",
    "wof:placetype":"venue"
},
  "geometry": {"coordinates":[-115.57077700000001,32.838091],"type":"Point"}
}