{
  "type": "Feature",
  "properties": {
    "iso:country":"US",
    "sg:address":"23498 Gold Springs Dr",
    "sg:city":"Columbia",
    "sg:classifiers":[
        {
            "category":"Professional",
            "subcategory":"Art Services",
            "type":"Services"
        }
    ],
    "sg:phone":"+1 209 532 6212",
    "sg:postcode":"95310",
    "sg:province":"CA",
    "sg:tags":[
        "interior",
        "designer",
        "decorator"
    ],
    "wof:name":"Miller Interiors",
    "wof:placetype":"venue"
},
  "geometry": {"coordinates":[-120.41426800000001,38.04804],"type":"Point"}
}