{
  "type": "Feature",
  "properties": {
    "iso:country":"US",
    "sg:address":"3552 Crowell Ave",
    "sg:city":"Riverside",
    "sg:classifiers":[
        {
            "category":"Restaurant",
            "type":"Food & Drink"
        }
    ],
    "sg:phone":"+1 951 785 9545",
    "sg:postcode":"92504",
    "sg:province":"CA",
    "sg:tags":[
        "eating",
        "animal"
    ],
    "wof:name":"Mountain Dogs Rescue",
    "wof:placetype":"venue"
},
  "geometry": {"coordinates":[-117.41904,33.930812],"type":"Point"}
}