{
  "type": "Feature",
  "properties": {
    "addr:full":"33 W Micheltorena St Santa Barbara CA 93101",
    "addr:housenumber":"33",
    "addr:postcode":"93101",
    "addr:street":"W Micheltorena St",
    "iso:country":"US",
    "sg:address":"33 W Micheltorena St",
    "sg:city":"Santa Barbara",
    "sg:classifiers":[
        {
            "category":"Professional",
            "subcategory":"Accounting & Tax Preparation",
            "type":"Services"
        }
    ],
    "sg:phone":"+1 805 569 2500",
    "sg:postcode":"93101",
    "sg:province":"CA",
    "sg:tags":[
        "accountant"
    ],
    "wof:name":"William H Jones CPA",
    "wof:placetype":"venue"
},
  "geometry": {"coordinates":[-119.709064,34.425384],"type":"Point"}
}