{
  "type": "Feature",
  "properties": {
    "addr:full":"6544 Tuscany Ct Rio Linda CA 95673",
    "addr:housenumber":"6544",
    "addr:postcode":"95673",
    "addr:street":"Tuscany Ct",
    "iso:country":"US",
    "sg:address":"6544 Tuscany Ct",
    "sg:city":"Rio Linda",
    "sg:classifiers":[
        {
            "category":"Manufacturing",
            "subcategory":"Apparel",
            "type":"Manufacturing & Wholesale Goods"
        }
    ],
    "sg:phone":"+1 916 991 4841",
    "sg:postcode":"95673",
    "sg:province":"CA",
    "wof:name":"Embroidery By Linda",
    "wof:placetype":"venue"
},
  "geometry": {"coordinates":[-121.45798000000001,38.685986],"type":"Point"}
}