{
  "type": "Feature",
  "properties": {
    "iso:country":"US",
    "sg:address":"1190 Saratoga Ave",
    "sg:city":"San Jose",
    "sg:classifiers":[
        {
            "category":"Banks & Credit Unions",
            "subcategory":"Investment Brokerage",
            "type":"Services"
        }
    ],
    "sg:phone":"+1 408 260 3100",
    "sg:postcode":"95129",
    "sg:province":"CA",
    "sg:tags":[
        "advisory"
    ],
    "wof:name":"Rwb Inc",
    "wof:placetype":"venue"
},
  "geometry": {"coordinates":[-121.979641,37.303334],"type":"Point"}
}