{
  "type": "Feature",
  "properties": {
    "addr:full":"2500 Marin St San Francisco CA 94124",
    "addr:housenumber":"2500",
    "addr:postcode":"94124",
    "addr:street":"Marin St",
    "iso:country":"US",
    "sg:address":"2500 Marin St",
    "sg:city":"San Francisco",
    "sg:classifiers":[
        {
            "category":"Communications",
            "subcategory":"Television Station",
            "type":"Services"
        }
    ],
    "sg:phone":"+1 415 821 2020",
    "sg:postcode":"94124",
    "sg:province":"CA",
    "sg:website":"www.kofytv.com/",
    "wof:name":"KOFY TV20",
    "wof:placetype":"venue"
},
  "geometry": {"coordinates":[-122.402413,37.748476],"type":"Point"}
}