{
  "type": "Feature",
  "properties": {
    "iso:country":"US",
    "sg:address":"1239 Rollins Rd",
    "sg:city":"Burlingame",
    "sg:classifiers":[
        {
            "category":"Manufacturing",
            "subcategory":"Tools & Machinery",
            "type":"Manufacturing & Wholesale Goods"
        }
    ],
    "sg:phone":"+1 650 579 0256",
    "sg:postcode":"94010",
    "sg:province":"CA",
    "sg:tags":[
        "machine",
        "shop"
    ],
    "wof:name":"Copello Security Products",
    "wof:placetype":"venue"
},
  "geometry": {"coordinates":[-122.362497,37.58894],"type":"Point"}
}