{
  "type": "Feature",
  "properties": {
    "addr:full":"1502 W 6th St Santa Ana CA 92703",
    "addr:housenumber":"1502",
    "addr:postcode":"92703",
    "addr:street":"W 6Th St",
    "iso:country":"US",
    "sg:address":"1502 W 6th St",
    "sg:city":"Santa Ana",
    "sg:classifiers":[
        {
            "category":"Building & Trades",
            "subcategory":"Construction",
            "type":"Services"
        }
    ],
    "sg:phone":"+1 714 317 7227",
    "sg:postcode":"92703",
    "sg:province":"CA",
    "sg:tags":[
        "contractor"
    ],
    "wof:name":"Art Stone Design Installation",
    "wof:placetype":"venue"
},
  "geometry": {"coordinates":[-117.891445,33.749565],"type":"Point"}
}