{
  "type": "Feature",
  "properties": {
    "addr:full":"7050 Topanga Canyon Blvd Canoga Park CA 91303",
    "addr:housenumber":"7050",
    "addr:postcode":"91303",
    "addr:street":"Topanga Canyon Blvd",
    "iso:country":"US",
    "sg:address":"7050 Topanga Canyon Blvd",
    "sg:city":"Canoga Park",
    "sg:classifiers":[
        {
            "category":"Autos & Motor Vehicles",
            "subcategory":"Automobile Sales",
            "type":"Retail Goods"
        }
    ],
    "sg:phone":"+1 818 444 1685",
    "sg:postcode":"91303",
    "sg:province":"CA",
    "sg:tags":[
        "car",
        "dealer"
    ],
    "sg:website":"www.bobsmithbmw.com",
    "wof:name":"Succillo Hyundai",
    "wof:placetype":"venue"
},
  "geometry": {"coordinates":[-118.605768,34.198265],"type":"Point"}
}