{
  "type": "Feature",
  "properties": {
    "addr:full":"1424 Fruitvale Ave Oakland CA 94601",
    "addr:housenumber":"1424",
    "addr:postcode":"94601",
    "addr:street":"Fruitvale Ave",
    "iso:country":"US",
    "sg:address":"1424 Fruitvale Ave",
    "sg:city":"Oakland",
    "sg:classifiers":[
        {
            "category":"Professional",
            "subcategory":"Business Services",
            "type":"Services"
        }
    ],
    "sg:phone":"+1 510 436 0675",
    "sg:postcode":"94601",
    "sg:province":"CA",
    "sg:tags":[
        "translator",
        "interpreter"
    ],
    "wof:name":"Hispanic Services",
    "wof:placetype":"venue"
},
  "geometry": {"coordinates":[-122.225595,37.777858],"type":"Point"}
}