{
  "type": "Feature",
  "properties": {
    "addr:full":"856 E Valley Blvd San Gabriel CA 91776",
    "addr:housenumber":"856",
    "addr:postcode":"91776",
    "addr:street":"E Valley Blvd",
    "iso:country":"US",
    "sg:address":"856 E Valley Blvd",
    "sg:city":"San Gabriel",
    "sg:classifiers":[
        {
            "category":"Professional",
            "type":"Services"
        }
    ],
    "sg:phone":"+1 661 274 0365",
    "sg:postcode":"91776",
    "sg:province":"CA",
    "sg:tags":[
        "establishment"
    ],
    "wof:name":"Guerra Baxter Plumbing",
    "wof:placetype":"venue"
},
  "geometry": {"coordinates":[-118.088393,34.080186],"type":"Point"}
}