{
  "type": "Feature",
  "properties": {
    "iso:country":"US",
    "sg:address":"1125 Centre Dr Ste B",
    "sg:city":"Walnut",
    "sg:classifiers":[
        {
            "category":"Fast Food",
            "type":"Food & Drink"
        },
        {
            "category":"Restaurant",
            "type":"Food & Drink"
        }
    ],
    "sg:phone":"+1 909 595 5945",
    "sg:postcode":"91789",
    "sg:province":"CA",
    "sg:tags":[
        "take"
    ],
    "wof:name":"La Chatita Foods",
    "wof:placetype":"venue"
},
  "geometry": {"coordinates":[-117.871938,33.994347],"type":"Point"}
}