{
  "type": "Feature",
  "properties": {
    "addr:full":"938 W Foothill Blvd Claremont CA 91711",
    "addr:housenumber":"938",
    "addr:postcode":"91711",
    "addr:street":"W Foothill Blvd",
    "iso:country":"US",
    "sg:address":"938 W Foothill Blvd",
    "sg:city":"Claremont",
    "sg:classifiers":[
        {
            "category":"Banks & Credit Unions",
            "subcategory":"Bank",
            "type":"Services"
        }
    ],
    "sg:phone":"+1 909 482 1528",
    "sg:postcode":"91711",
    "sg:province":"CA",
    "sg:tags":[
        "loan",
        "real estate"
    ],
    "wof:name":"Community Financial",
    "wof:placetype":"venue"
},
  "geometry": {"coordinates":[-117.73280699999999,34.106914],"type":"Point"}
}