{
  "type": "Feature",
  "properties": {
    "iso:country":"US",
    "sg:address":"2065 S Escondido Blvd",
    "sg:city":"Escondido",
    "sg:classifiers":[
        {
            "category":"Organizations",
            "subcategory":"Religious Organization",
            "type":"Services"
        }
    ],
    "sg:phone":"+1 760 741 0853",
    "sg:postcode":"92025",
    "sg:province":"CA",
    "sg:tags":[
        "church"
    ],
    "wof:name":"Escondido Community Church",
    "wof:placetype":"venue"
},
  "geometry": {"coordinates":[-117.070831,33.098184],"type":"Point"}
}