{
  "type": "Feature",
  "properties": {
    "iso:country":"US",
    "sg:address":"6363 Christie Ave",
    "sg:city":"Emeryville",
    "sg:classifiers":[
        {
            "category":"Professional",
            "type":"Services"
        }
    ],
    "sg:phone":"+1 510 547 2208",
    "sg:postcode":"94608",
    "sg:province":"CA",
    "sg:tags":[
        "establishment"
    ],
    "wof:name":"Berkeley Indoor Gdn Ctr",
    "wof:placetype":"venue"
},
  "geometry": {"coordinates":[-122.294972,37.839625],"type":"Point"}
}