{
  "type": "Feature",
  "properties": {
    "addr:full":"17495 Seidner Rd Escalon CA 95320",
    "addr:postcode":"17495;95320",
    "addr:street":"Seidner Rd",
    "iso:country":"US",
    "sg:address":"17495 Seidner Rd",
    "sg:city":"Escalon",
    "sg:classifiers":[
        {
            "category":"Food & Beverages",
            "subcategory":"Candy",
            "type":"Retail Goods"
        },
        {
            "category":"Food & Beverages",
            "subcategory":"Specialty",
            "type":"Retail Goods"
        }
    ],
    "sg:phone":"+1 209 838 7049",
    "sg:postcode":"95320",
    "sg:province":"CA",
    "sg:tags":[
        "confectionery",
        "nuts-edible"
    ],
    "sg:website":"http://www.qualitynut.com",
    "wof:name":"Export Import Associates",
    "wof:placetype":"venue"
},
  "geometry": {"coordinates":[-120.950965,37.803026],"type":"Point"}
}