{
  "type": "Feature",
  "properties": {
    "addr:full":"12872 Valley View St Garden Grove CA 92845",
    "addr:housenumber":"12872",
    "addr:postcode":"92845",
    "addr:street":"Valley View St",
    "iso:country":"US",
    "sg:address":"12872 Valley View St",
    "sg:city":"Garden Grove",
    "sg:classifiers":[
        {
            "category":"Food & Beverages",
            "subcategory":"Candy",
            "type":"Retail Goods"
        }
    ],
    "sg:phone":"+1 714 895 5055",
    "sg:postcode":"92845",
    "sg:province":"CA",
    "sg:tags":[
        "store"
    ],
    "wof:name":"Classic Treats",
    "wof:placetype":"venue"
},
  "geometry": {"coordinates":[-118.035004,33.776501],"type":"Point"}
}