{
  "type": "Feature",
  "properties": {
    "iso:country":"US",
    "sg:address":"1429 Knox Rd",
    "sg:city":"Oakdale",
    "sg:classifiers":[
        {
            "category":"Manufacturing",
            "subcategory":"Furniture",
            "type":"Manufacturing & Wholesale Goods"
        }
    ],
    "sg:phone":"+1 209 848 0226",
    "sg:postcode":"95361",
    "sg:province":"CA",
    "sg:tags":[
        "household",
        "wood",
        "mfg"
    ],
    "wof:name":"Live Oak Woodworks",
    "wof:placetype":"venue"
},
  "geometry": {"coordinates":[-120.829629,37.761483],"type":"Point"}
}