{
  "type": "Feature",
  "properties": {
    "iso:country":"US",
    "sg:address":"12802 Penn St",
    "sg:city":"Whittier",
    "sg:classifiers":[
        {
            "category":"Food & Beverages",
            "subcategory":"Liquor & Beverages",
            "type":"Retail Goods"
        }
    ],
    "sg:phone":"+1 562 693 7160",
    "sg:postcode":"90602",
    "sg:province":"CA",
    "sg:tags":[
        "beer",
        "spirit",
        "wine"
    ],
    "wof:name":"Super 99 Cents & Up",
    "wof:placetype":"venue"
},
  "geometry": {"coordinates":[-118.040001,33.9753],"type":"Point"}
}