{
  "type": "Feature",
  "properties": {
    "addr:full":"2834 N Verdugo Rd Glendale CA 91208",
    "addr:housenumber":"2834",
    "addr:postcode":"91208",
    "addr:street":"N Verdugo Rd",
    "iso:country":"US",
    "sg:address":"2834 N Verdugo Rd",
    "sg:city":"Glendale",
    "sg:classifiers":[
        {
            "category":"Retail",
            "subcategory":"Animal Services",
            "type":"Services"
        }
    ],
    "sg:phone":"+1 818 243 7387",
    "sg:postcode":"91208",
    "sg:province":"CA",
    "wof:name":"I Stay U-Go",
    "wof:placetype":"venue"
},
  "geometry": {"coordinates":[-118.225809,34.188248],"type":"Point"}
}