{
  "type": "Feature",
  "properties": {
    "addr:full":"780 Main St Pleasanton CA 94566",
    "addr:housenumber":"780",
    "addr:postcode":"94566",
    "addr:street":"Main St",
    "iso:country":"US",
    "sg:address":"780 Main St",
    "sg:city":"Pleasanton",
    "sg:classifiers":[
        {
            "category":"Health Services",
            "subcategory":"Doctor",
            "type":"Services"
        }
    ],
    "sg:phone":"+1 925 426 0474",
    "sg:postcode":"94566",
    "sg:province":"CA",
    "sg:tags":[
        "physician",
        "surgeon"
    ],
    "wof:name":"Abbott Vascular Devices",
    "wof:placetype":"venue"
},
  "geometry": {"coordinates":[-121.87432,37.663833],"type":"Point"}
}