{
  "type": "Feature",
  "properties": {
    "addr:full":"1960 Highland St Seaside CA 93955",
    "addr:housenumber":"1960",
    "addr:postcode":"93955",
    "addr:street":"Highland St",
    "iso:country":"US",
    "sg:address":"1960 Highland St",
    "sg:city":"Seaside",
    "sg:classifiers":[
        {
            "category":"Retail",
            "subcategory":"Repair Shop",
            "type":"Services"
        }
    ],
    "sg:phone":"+1 831 394 1299",
    "sg:postcode":"93955",
    "sg:province":"CA",
    "sg:tags":[
        "repairing",
        "piano",
        "refinishing"
    ],
    "wof:name":"Andy Gonzales Piano Svc",
    "wof:placetype":"venue"
},
  "geometry": {"coordinates":[-121.829812,36.617637],"type":"Point"}
}