{
  "type": "Feature",
  "properties": {
    "iso:country":"US",
    "sg:address":"155 15th St",
    "sg:city":"West Sacramento",
    "sg:classifiers":[
        {
            "category":"Real Estate",
            "subcategory":"Real Estate Agent",
            "type":"Services"
        }
    ],
    "sg:phone":"+1 916 371 2500",
    "sg:postcode":"95691",
    "sg:province":"CA",
    "wof:name":"California Real Estate",
    "wof:placetype":"venue"
},
  "geometry": {"coordinates":[-121.52538199999999,38.571043],"type":"Point"}
}