{
  "type": "Feature",
  "properties": {
    "addr:full":"1640 Superior Ave Costa Mesa CA 92627",
    "addr:housenumber":"1640",
    "addr:postcode":"92627",
    "addr:street":"Superior Ave",
    "iso:country":"US",
    "sg:address":"1640 Superior Ave",
    "sg:city":"Costa Mesa",
    "sg:classifiers":[
        {
            "category":"Professional",
            "subcategory":"Business Services",
            "type":"Services"
        }
    ],
    "sg:phone":"+1 949 722 9622",
    "sg:postcode":"92627",
    "sg:province":"CA",
    "sg:tags":[
        "event"
    ],
    "wof:name":"1 Source Productions",
    "wof:placetype":"venue"
},
  "geometry": {"coordinates":[-117.924812,33.634918],"type":"Point"}
}