{
  "type": "Feature",
  "properties": {
    "iso:country":"US",
    "sg:address":"1605 Potrero Ave",
    "sg:city":"South El Monte",
    "sg:classifiers":[
        {
            "category":"Professional",
            "type":"Services"
        }
    ],
    "sg:phone":"+1 626 350 4110",
    "sg:postcode":"91733",
    "sg:province":"CA",
    "wof:name":"Francisco Polanco",
    "wof:placetype":"venue"
},
  "geometry": {"coordinates":[-118.055702,34.047663],"type":"Point"}
}