{
  "type": "Feature",
  "properties": {
    "iso:country":"US",
    "sg:address":"738 Design Ct",
    "sg:city":"Chula Vista",
    "sg:classifiers":[
        {
            "category":"Wholesale",
            "subcategory":"Office Equipment",
            "type":"Manufacturing & Wholesale Goods"
        }
    ],
    "sg:phone":"+1 619 421 9520",
    "sg:postcode":"91911",
    "sg:province":"CA",
    "sg:tags":[
        "machine",
        "duplicating",
        "copying"
    ],
    "wof:name":"Icopy",
    "wof:placetype":"venue"
},
  "geometry": {"coordinates":[-117.02064,32.595671],"type":"Point"}
}