{
  "type": "Feature",
  "properties": {
    "iso:country":"US",
    "sg:address":"2234 Catherine Pl",
    "sg:city":"Costa Mesa",
    "sg:classifiers":[
        {
            "category":"Travel",
            "subcategory":"Travel Agent",
            "type":"Entertainment"
        }
    ],
    "sg:phone":"+1 949 645 7733",
    "sg:postcode":"92627",
    "sg:province":"CA",
    "sg:tags":[
        "tours",
        "promoter"
    ],
    "sg:website":"www.eco4wd.com",
    "wof:name":"Ecological 4-Wheeling",
    "wof:placetype":"venue"
},
  "geometry": {"coordinates":[-117.90275,33.650149],"type":"Point"}
}