{
  "type": "Feature",
  "properties": {
    "addr:full":"1040 Grant Ave San Francisco CA 94133",
    "addr:housenumber":"1040",
    "addr:postcode":"94133",
    "addr:street":"Grant Ave",
    "iso:country":"US",
    "sg:address":"1040 Grant Ave",
    "sg:city":"San Francisco",
    "sg:classifiers":[
        {
            "category":"Banks & Credit Unions",
            "subcategory":"Bank",
            "type":"Services"
        }
    ],
    "sg:phone":"+1 415 421 5421",
    "sg:postcode":"94133",
    "sg:province":"CA",
    "sg:website":"www.chase.com",
    "wof:name":"Chase",
    "wof:placetype":"venue"
},
  "geometry": {"coordinates":[-122.406581,37.796536],"type":"Point"}
}