{
  "type": "Feature",
  "properties": {
    "iso:country":"US",
    "sg:address":"205 W Hatch Rd",
    "sg:city":"Modesto",
    "sg:classifiers":[
        {
            "category":"Personal",
            "subcategory":"Shoe Repair & Shine",
            "type":"Services"
        }
    ],
    "sg:phone":"+1 209 523 4300",
    "sg:postcode":"95351",
    "sg:province":"CA",
    "wof:name":"EVERGREEN SHOE REPAIR",
    "wof:placetype":"venue"
},
  "geometry": {"coordinates":[-120.99477899999999,37.609587],"type":"Point"}
}