{
  "type": "Feature",
  "properties": {
    "iso:country":"US",
    "sg:address":"926 A Ave",
    "sg:city":"National City",
    "sg:classifiers":[
        {
            "category":"Real Estate",
            "subcategory":"Real Estate Agent",
            "type":"Services"
        }
    ],
    "sg:phone":"+1 619 477 1122",
    "sg:postcode":"91950",
    "sg:province":"CA",
    "wof:name":"Janice Martinelli Real Estate",
    "wof:placetype":"venue"
},
  "geometry": {"coordinates":[-117.105322,32.674598],"type":"Point"}
}