{
  "type": "Feature",
  "properties": {
    "iso:country":"US",
    "sg:address":"928 Fort Stockton Dr",
    "sg:city":"San Diego",
    "sg:classifiers":[
        {
            "category":"Sports & Exercise",
            "subcategory":"Gym",
            "type":"Entertainment"
        }
    ],
    "sg:phone":"+1 619 542 0084",
    "sg:postcode":"92103",
    "sg:province":"CA",
    "sg:tags":[
        "spa",
        "health"
    ],
    "wof:name":"Grace Med Spa",
    "wof:placetype":"venue"
},
  "geometry": {"coordinates":[-117.172057,32.750932],"type":"Point"}
}