{
  "type": "Feature",
  "properties": {
    "iso:country":"US",
    "sg:address":"304 S Central Ave",
    "sg:city":"Compton",
    "sg:classifiers":[
        {
            "category":"Real Estate",
            "subcategory":"Real Estate Agent",
            "type":"Services"
        }
    ],
    "sg:phone":"+1 323 636 5815",
    "sg:postcode":"90220",
    "sg:province":"CA",
    "wof:name":"Nu Star Realty",
    "wof:placetype":"venue"
},
  "geometry": {"coordinates":[-118.25105499999999,33.892899],"type":"Point"}
}