{
  "type": "Feature",
  "properties": {
    "addr:full":"21 Highland Ave Felton CA 95018",
    "addr:housenumber":"21",
    "addr:postcode":"95018",
    "addr:street":"Highland Ave",
    "iso:country":"US",
    "sg:address":"21 Highland Ave",
    "sg:city":"Felton",
    "sg:classifiers":[
        {
            "category":"Insurance",
            "subcategory":"Insurance Agent",
            "type":"Services"
        }
    ],
    "sg:phone":"+1 831 335 2189",
    "sg:postcode":"95018",
    "sg:province":"CA",
    "sg:tags":[
        "administrator"
    ],
    "wof:name":"Carl Warren & Co",
    "wof:placetype":"venue"
},
  "geometry": {"coordinates":[-122.063503,37.052809],"type":"Point"}
}