{
  "type": "Feature",
  "properties": {
    "iso:country":"US",
    "sg:address":"6046 Wenk Ave",
    "sg:city":"Richmond",
    "sg:classifiers":[
        {
            "category":"Shopping",
            "subcategory":"Hobbies, Toys, & Games",
            "type":"Retail Goods"
        }
    ],
    "sg:phone":"+1 510 215 6751",
    "sg:postcode":"94804",
    "sg:province":"CA",
    "sg:tags":[
        "shop",
        "hobby"
    ],
    "wof:name":"FC Creative Corp",
    "wof:placetype":"venue"
},
  "geometry": {"coordinates":[-122.31189999999999,37.915125],"type":"Point"}
}