{
  "type": "Feature",
  "properties": {
    "addr:full":"4597 Park Blvd San Diego CA 92116",
    "addr:housenumber":"4597",
    "addr:postcode":"92116",
    "addr:street":"Park Blvd",
    "iso:country":"US",
    "sg:address":"4597 Park Blvd",
    "sg:city":"San Diego",
    "sg:classifiers":[
        {
            "category":"Professional",
            "type":"Services"
        }
    ],
    "sg:phone":"+1 619 296 6910",
    "sg:postcode":"92116",
    "sg:province":"CA",
    "wof:name":"Mihsin E Jamoo",
    "wof:placetype":"venue"
},
  "geometry": {"coordinates":[-117.146186,32.759131],"type":"Point"}
}