{
  "type": "Feature",
  "properties": {
    "iso:country":"US",
    "sg:address":"2224 S Maple Ave",
    "sg:city":"Fresno",
    "sg:classifiers":[
        {
            "category":"Education",
            "subcategory":"Vocational School",
            "type":"Public Place"
        }
    ],
    "sg:phone":"+1 559 486 0740",
    "sg:postcode":"93725",
    "sg:province":"CA",
    "sg:tags":[
        "instruction",
        "truck",
        "driving"
    ],
    "wof:name":"Five Rivers Truck School",
    "wof:placetype":"venue"
},
  "geometry": {"coordinates":[-119.745646,36.720033],"type":"Point"}
}