{
  "type": "Feature",
  "properties": {
    "addr:full":"3665 S Vermont Ave Los Angeles CA 90007",
    "addr:housenumber":"3665",
    "addr:postcode":"90007",
    "addr:street":"S Vermont Ave",
    "iso:country":"US",
    "sg:address":"3665 S Vermont Ave",
    "sg:city":"Los Angeles",
    "sg:classifiers":[
        {
            "category":"Education",
            "subcategory":"Library",
            "type":"Public Place"
        }
    ],
    "sg:phone":"+1 323 732 0169",
    "sg:postcode":"90007",
    "sg:province":"CA",
    "sg:website":"www.lapl.org/branches/Branch.php...",
    "wof:name":"Dr. Mary McLeod Bethune Regional Branch Library",
    "wof:placetype":"venue"
},
  "geometry": {"coordinates":[-118.291528,34.021458],"type":"Point"}
}