{
  "type": "Feature",
  "properties": {
    "iso:country":"US",
    "sg:address":"5612 Rickey Dr",
    "sg:city":"Sacramento",
    "sg:classifiers":[
        {
            "category":"Building & Trades",
            "subcategory":"Landscaping Services",
            "type":"Services"
        }
    ],
    "sg:phone":"+1 916 832 2010",
    "sg:postcode":"95822",
    "sg:province":"CA",
    "sg:tags":[
        "landscape",
        "contractor"
    ],
    "wof:name":"Sacramento Landscape Co",
    "wof:placetype":"venue"
},
  "geometry": {"coordinates":[-121.499557,38.524334],"type":"Point"}
}