{
  "type": "Feature",
  "properties": {
    "iso:country":"US",
    "sg:address":"Cherry and Willow",
    "sg:city":"Signal Hill",
    "sg:classifiers":[
        {
            "category":"Personal",
            "type":"Services"
        }
    ],
    "sg:postcode":"90806",
    "sg:province":"CA",
    "sg:tags":[
        "local"
    ],
    "wof:name":"Jack the Shoe Shine Man",
    "wof:placetype":"venue"
},
  "geometry": {"coordinates":[-118.167538,33.804344],"type":"Point"}
}