{
  "type": "Feature",
  "properties": {
    "iso:country":"US",
    "sg:address":"965 Mission St Ste 205",
    "sg:city":"San Francisco",
    "sg:classifiers":[
        {
            "category":"Arts & Performance",
            "subcategory":"Arts Center",
            "type":"Entertainment"
        },
        {
            "category":"Education",
            "subcategory":"Special Training",
            "type":"Public Place"
        }
    ],
    "sg:phone":"+1 415 449 1919",
    "sg:postcode":"94103",
    "sg:province":"CA",
    "sg:tags":[
        "school",
        "performing",
        "specialty"
    ],
    "sg:website":"www.bhplayhouse.com/Acting-Class...",
    "wof:name":"Beverly Hills Playhouse Acting School",
    "wof:placetype":"venue"
},
  "geometry": {"coordinates":[-122.407948,37.781549],"type":"Point"}
}