{
  "type": "Feature",
  "properties": {
    "iso:country":"US",
    "sg:address":"550 Waverley St",
    "sg:city":"Palo Alto",
    "sg:classifiers":[
        {
            "category":"Food & Beverages",
            "subcategory":"Bakery",
            "type":"Retail Goods"
        },
        {
            "category":"Bakery",
            "type":"Food & Drink"
        }
    ],
    "sg:menulink":"http://www.allmenus.com/ca/san-jose/20126-the-prolific-oven/menu/",
    "sg:phone":"+1 650 326 8485",
    "sg:postcode":"94301",
    "sg:province":"CA",
    "sg:tags":[
        "american",
        "bakery",
        "pastry"
    ],
    "wof:name":"The Prolific Oven",
    "wof:placetype":"venue"
},
  "geometry": {"coordinates":[-122.159762,37.446693],"type":"Point"}
}