{
  "type": "Feature",
  "properties": {
    "addr:full":"2240 N Angus St Fresno CA 93703",
    "addr:housenumber":"2240",
    "addr:postcode":"93703",
    "addr:street":"N Angus",
    "iso:country":"US",
    "sg:address":"2240 N Angus St",
    "sg:city":"Fresno",
    "sg:classifiers":[
        {
            "category":"Organizations",
            "subcategory":"Religious Organization",
            "type":"Services"
        }
    ],
    "sg:phone":"+1 559 237 4862",
    "sg:postcode":"93703",
    "sg:province":"CA",
    "sg:tags":[
        "church"
    ],
    "wof:name":"Baha'i Faith",
    "wof:placetype":"venue"
},
  "geometry": {"coordinates":[-119.77694099999999,36.768703],"type":"Point"}
}