{
  "type": "Feature",
  "properties": {
    "iso:country":"US",
    "sg:address":"541 N Main St",
    "sg:city":"Corona",
    "sg:classifiers":[
        {
            "category":"Retail",
            "subcategory":"Repair Shop",
            "type":"Services"
        }
    ],
    "sg:phone":"+1 951 340 3340",
    "sg:postcode":"92880",
    "sg:province":"CA",
    "sg:tags":[
        "equipment",
        "medical"
    ],
    "wof:name":"Sterilizer Technical Spec",
    "wof:placetype":"venue"
},
  "geometry": {"coordinates":[-117.564875,33.884386],"type":"Point"}
}