{
  "type": "Feature",
  "properties": {
    "addr:full":"3325 Wilshire Blvd Los Angeles CA 90010",
    "addr:housenumber":"3325",
    "addr:postcode":"90010",
    "addr:street":"Wilshire Blvd",
    "iso:country":"US",
    "sg:address":"3325 Wilshire Blvd",
    "sg:city":"Los Angeles",
    "sg:classifiers":[
        {
            "category":"Travel",
            "subcategory":"Travel Agent",
            "type":"Entertainment"
        }
    ],
    "sg:phone":"+1 213 251 9556",
    "sg:postcode":"90010",
    "sg:province":"CA",
    "sg:tags":[
        "agency",
        "bureau"
    ],
    "wof:name":"Seasons All Travel",
    "wof:placetype":"venue"
},
  "geometry": {"coordinates":[-118.29469899999999,34.061852],"type":"Point"}
}