{
  "type": "Feature",
  "properties": {
    "iso:country":"US",
    "sg:address":"465 34th St",
    "sg:city":"Oakland",
    "sg:classifiers":[
        {
            "category":"Health Services",
            "subcategory":"Clinic",
            "type":"Services"
        }
    ],
    "sg:phone":"+1 510 217 9157",
    "sg:postcode":"94609",
    "sg:province":"CA",
    "sg:tags":[
        "counseling",
        "mental"
    ],
    "sg:website":"www.jovan-yglecias.com",
    "wof:name":"Jovan Yglecias, MA, MFT-Intern",
    "wof:placetype":"venue"
},
  "geometry": {"coordinates":[-122.26481800000001,37.821778],"type":"Point"}
}