{
  "type": "Feature",
  "properties": {
    "iso:country":"US",
    "sg:address":"10439 Felson St",
    "sg:city":"Bellflower",
    "sg:classifiers":[
        {
            "category":"Education",
            "subcategory":"University",
            "type":"Public Place"
        }
    ],
    "sg:phone":"+1 626 914 8807",
    "sg:postcode":"90706",
    "sg:province":"CA",
    "sg:tags":[
        "college"
    ],
    "wof:name":"Citrus Community College District",
    "wof:placetype":"venue"
},
  "geometry": {"coordinates":[-118.11214,33.869409],"type":"Point"}
}