{
  "type": "Feature",
  "properties": {
    "iso:country":"US",
    "sg:address":"8715 El Chapul Way",
    "sg:city":"Fair Oaks",
    "sg:classifiers":[
        {
            "category":"Arts & Performance",
            "subcategory":"Music",
            "type":"Entertainment"
        }
    ],
    "sg:phone":"+1 916 965 8301",
    "sg:postcode":"95628",
    "sg:province":"CA",
    "sg:tags":[
        "dj"
    ],
    "sg:website":"www.casinoanddj.com",
    "wof:name":"CJ Entertainment",
    "wof:placetype":"venue"
},
  "geometry": {"coordinates":[-121.23363999999999,38.65835],"type":"Point"}
}