{
  "type": "Feature",
  "properties": {
    "addr:full":"19037 Highway 94 Dulzura CA 91917",
    "addr:housenumber":"19037",
    "addr:postcode":"91917",
    "addr:street":"Highway 94",
    "iso:country":"US",
    "sg:address":"19037 Highway 94",
    "sg:city":"Dulzura",
    "sg:classifiers":[
        {
            "category":"Real Estate",
            "subcategory":"Real Estate Agent",
            "type":"Services"
        }
    ],
    "sg:phone":"+1 619 739 1397",
    "sg:postcode":"91917",
    "sg:province":"CA",
    "wof:name":"Max Organics",
    "wof:placetype":"venue"
},
  "geometry": {"coordinates":[-116.74568600000001,32.612534],"type":"Point"}
}