{
  "type": "Feature",
  "properties": {
    "addr:full":"6922 Hollywood Blvd. Hollywood CA 90028",
    "addr:housenumber":"6922",
    "addr:postcode":"90028",
    "addr:street":"Hollywood Blvd.",
    "iso:country":"US",
    "sg:address":"6922 Hollywood Blvd.",
    "sg:city":"Hollywood",
    "sg:classifiers":[
        {
            "category":"Professional",
            "subcategory":"Computer Services",
            "type":"Services"
        }
    ],
    "sg:postcode":"90028",
    "sg:province":"CA",
    "sg:tags":[
        "800-numbers",
        "toll-free",
        "vanity-numbers",
        "virtual-pbx",
        "service",
        "virtual-office",
        "resporg"
    ],
    "wof:name":"PhonePeople",
    "wof:placetype":"venue"
},
  "geometry": {"coordinates":[-118.341179,34.101464],"type":"Point"}
}