{
  "type": "Feature",
  "properties": {
    "iso:country":"US",
    "sg:address":"6212 Jarvis Ave",
    "sg:city":"Newark",
    "sg:classifiers":[
        {
            "category":"Building & Trades",
            "subcategory":"Construction",
            "type":"Services"
        }
    ],
    "sg:phone":"+1 510 796 1738",
    "sg:postcode":"94560",
    "sg:province":"CA",
    "sg:tags":[
        "house"
    ],
    "wof:name":"Pera Construction",
    "wof:placetype":"venue"
},
  "geometry": {"coordinates":[-122.05001799999999,37.549668],"type":"Point"}
}