{
  "type": "Feature",
  "properties": {
    "iso:country":"US",
    "sg:address":"9835 Kitty Ln",
    "sg:city":"Oakland",
    "sg:classifiers":[
        {
            "category":"Building & Trades",
            "subcategory":"Electrical",
            "type":"Services"
        },
        {
            "category":"Professional",
            "type":"Services"
        }
    ],
    "sg:phone":"+1 510 430 0399",
    "sg:postcode":"94603",
    "sg:province":"CA",
    "sg:tags":[
        "electrical",
        "bureau",
        "contractor"
    ],
    "sg:website":"www.electricalservices.org",
    "wof:name":"Electrical Services Company",
    "wof:placetype":"venue"
},
  "geometry": {"coordinates":[-122.195229,37.727325],"type":"Point"}
}