{
  "type": "Feature",
  "properties": {
    "addr:full":"8863 Greenback Ln #330 Orangevale CA 95662",
    "addr:housenumber":"8863",
    "addr:postcode":"95662",
    "addr:street":"Greenback Ln # 330",
    "iso:country":"US",
    "sg:address":"8863 Greenback Ln #330",
    "sg:city":"Orangevale",
    "sg:classifiers":[
        {
            "category":"Home & Garden",
            "subcategory":"Building Materials",
            "type":"Retail Goods"
        },
        {
            "category":"Building & Trades",
            "subcategory":"Construction",
            "type":"Services"
        }
    ],
    "sg:phone":"+1 916 988 8681",
    "sg:postcode":"95662",
    "sg:province":"CA",
    "sg:tags":[
        "repair",
        "heater",
        "water",
        "air conditioning"
    ],
    "sg:website":"http://www.evcocentral.com",
    "wof:name":"Evco Heating & Air Conditioning",
    "wof:placetype":"venue"
},
  "geometry": {"coordinates":[-121.227555,38.67854],"type":"Point"}
}