{
  "type": "Feature",
  "properties": {
    "addr:full":"4725 Quail Lakes Dr Stockton CA 95207",
    "addr:housenumber":"4725",
    "addr:postcode":"95207",
    "addr:street":"Quail Lakes Dr",
    "iso:country":"US",
    "sg:address":"4725 Quail Lakes Dr",
    "sg:city":"Stockton",
    "sg:classifiers":[
        {
            "category":"Deli",
            "type":"Food & Drink"
        },
        {
            "category":"Bakery",
            "type":"Food & Drink"
        },
        {
            "category":"Food & Beverages",
            "subcategory":"Supermarket",
            "type":"Retail Goods"
        }
    ],
    "sg:phone":"+1 209 952 0525",
    "sg:postcode":"95207",
    "sg:province":"CA",
    "sg:tags":[
        "delicatessen",
        "super",
        "store"
    ],
    "wof:name":"S - Mart 39",
    "wof:placetype":"venue"
},
  "geometry": {"coordinates":[-121.33998200000001,37.985735],"type":"Point"}
}