{
  "type": "Feature",
  "properties": {
    "addr:full":"3130 Skyway Dr Ste 405 Santa Maria CA 93455",
    "addr:housenumber":"3130",
    "addr:postcode":"93455",
    "addr:street":"Skyway Dr Ste 405",
    "iso:country":"US",
    "sg:address":"3130 Skyway Dr Ste 405",
    "sg:city":"Santa Maria",
    "sg:classifiers":[
        {
            "category":"Building & Trades",
            "subcategory":"Construction",
            "type":"Services"
        }
    ],
    "sg:phone":"+1 805 614 0840",
    "sg:postcode":"93455",
    "sg:province":"CA",
    "sg:tags":[
        "contractor"
    ],
    "wof:name":"PROFESSIONAL CONSTRUCTION CO",
    "wof:placetype":"venue"
},
  "geometry": {"coordinates":[-120.449163,34.902886],"type":"Point"}
}