{
  "type": "Feature",
  "properties": {
    "addr:full":"700 23rd Ave San Francisco CA 94121",
    "addr:housenumber":"700",
    "addr:postcode":"94121",
    "addr:street":"23Rd Ave",
    "iso:country":"US",
    "sg:address":"700 23rd Ave",
    "sg:city":"San Francisco",
    "sg:classifiers":[
        {
            "category":"Professional",
            "subcategory":"Employment Agencies",
            "type":"Services"
        }
    ],
    "sg:phone":"+1 415 831 3337",
    "sg:postcode":"94121",
    "sg:province":"CA",
    "sg:tags":[
        "opportunity"
    ],
    "wof:name":"Timmons Personnel Svc",
    "wof:placetype":"venue"
},
  "geometry": {"coordinates":[-122.482049,37.772667],"type":"Point"}
}