{
  "type": "Feature",
  "properties": {
    "addr:full":"203 Grove St Roseville CA 95678",
    "addr:housenumber":"203",
    "addr:postcode":"95678",
    "addr:street":"Grove St",
    "iso:country":"US",
    "sg:address":"203 Grove St",
    "sg:city":"Roseville",
    "sg:classifiers":[
        {
            "category":"Wholesale",
            "subcategory":"Medical Equipment & Supplies",
            "type":"Manufacturing & Wholesale Goods"
        }
    ],
    "sg:phone":"+1 916 786 6557",
    "sg:postcode":"95678",
    "sg:province":"CA",
    "wof:name":"Ra/Ted Medical Technologies",
    "wof:placetype":"venue"
},
  "geometry": {"coordinates":[-121.287869,38.75285],"type":"Point"}
}