{
  "type": "Feature",
  "properties": {
    "addr:full":"2301 E 8th St Los Angeles CA 90021",
    "addr:housenumber":"2301",
    "addr:postcode":"90021",
    "addr:street":"E 8Th St",
    "iso:country":"US",
    "sg:address":"2301 E 8th St",
    "sg:city":"Los Angeles",
    "sg:classifiers":[
        {
            "category":"Wholesale",
            "subcategory":"Groceries",
            "type":"Manufacturing & Wholesale Goods"
        }
    ],
    "sg:phone":"+1 213 612 4983",
    "sg:postcode":"90021",
    "sg:province":"CA",
    "sg:tags":[
        "confectionery",
        "candy"
    ],
    "wof:name":"G & B Enterprises",
    "wof:placetype":"venue"
},
  "geometry": {"coordinates":[-118.231487,34.029592],"type":"Point"}
}