{
  "type": "Feature",
  "properties": {
    "iso:country":"US",
    "sg:address":"5137 Sunrise Hills Dr",
    "sg:city":"Fair Oaks",
    "sg:classifiers":[
        {
            "category":"Education",
            "subcategory":"Special Training",
            "type":"Public Place"
        }
    ],
    "sg:phone":"+1 916 965 5634",
    "sg:postcode":"95628",
    "sg:province":"CA",
    "sg:tags":[
        "center"
    ],
    "wof:name":"Laureate Learning Ctr",
    "wof:placetype":"venue"
},
  "geometry": {"coordinates":[-121.273779,38.660739],"type":"Point"}
}