{
  "type": "Feature",
  "properties": {
    "addr:full":"12781 Monarch St Garden Grove CA 92841",
    "addr:housenumber":"12781",
    "addr:postcode":"92841",
    "addr:street":"Monarch St",
    "iso:country":"US",
    "sg:address":"12781 Monarch St",
    "sg:city":"Garden Grove",
    "sg:classifiers":[
        {
            "category":"Sports & Exercise",
            "subcategory":"Bicycle Rental",
            "type":"Entertainment"
        }
    ],
    "sg:phone":"+1 714 891 8716",
    "sg:postcode":"92841",
    "sg:province":"CA",
    "sg:tags":[
        "wear"
    ],
    "wof:name":"Pace Sportswear",
    "wof:placetype":"venue"
},
  "geometry": {"coordinates":[-118.006259,33.776601],"type":"Point"}
}