{
  "type": "Feature",
  "properties": {
    "iso:country":"US",
    "sg:address":"23801 Calabasas Rd Ste 1000",
    "sg:city":"Calabasas",
    "sg:classifiers":[
        {
            "category":"Building & Trades",
            "subcategory":"Cleaning & Sanitation",
            "type":"Services"
        }
    ],
    "sg:phone":"+1 818 591 7717",
    "sg:postcode":"91302",
    "sg:province":"CA",
    "sg:tags":[
        "carpet"
    ],
    "sg:website":"www.chemdry.com",
    "wof:name":"A-Aalpha Chem-Dry Superior Carpet & Upholstery Cleaning",
    "wof:placetype":"venue"
},
  "geometry": {"coordinates":[-118.645366,34.155155],"type":"Point"}
}