{
  "type": "Feature",
  "properties": {
    "iso:country":"US",
    "sg:address":"3117 el Camino Ave",
    "sg:city":"Sacramento",
    "sg:classifiers":[
        {
            "category":"Personal",
            "type":"Services"
        }
    ],
    "sg:phone":"+1 916 484 0523",
    "sg:postcode":"95821",
    "sg:province":"CA",
    "sg:tags":[
        "credit",
        "debt",
        "counseling"
    ],
    "wof:name":"Personal Financial Assistance",
    "wof:placetype":"venue"
},
  "geometry": {"coordinates":[-121.3938,38.610643],"type":"Point"}
}