{
  "type": "Feature",
  "properties": {
    "iso:country":"US",
    "sg:address":"13250 Civic Center Dr",
    "sg:city":"Poway",
    "sg:classifiers":[
        {
            "category":"Real Estate",
            "subcategory":"Real Estate Operator",
            "type":"Services"
        }
    ],
    "sg:phone":"+1 858 748 3523",
    "sg:postcode":"92064",
    "sg:province":"CA",
    "sg:tags":[
        "apartment"
    ],
    "wof:name":"Park View Terrace",
    "wof:placetype":"venue"
},
  "geometry": {"coordinates":[-117.044135,32.954785],"type":"Point"}
}