{
  "type": "Feature",
  "properties": {
    "addr:full":"3837 Park Blvd San Diego CA 92103",
    "addr:housenumber":"3837",
    "addr:postcode":"92103",
    "addr:street":"Park Blvd",
    "iso:country":"US",
    "sg:address":"3837 Park Blvd",
    "sg:city":"San Diego",
    "sg:classifiers":[
        {
            "category":"Shopping",
            "subcategory":"Tobacco",
            "type":"Retail Goods"
        }
    ],
    "sg:phone":"+1 619 574 0455",
    "sg:postcode":"92103",
    "sg:province":"CA",
    "sg:tags":[
        "cigarette",
        "cigar",
        "dealer"
    ],
    "wof:name":"Puff N Stuff Smoke Shop",
    "wof:placetype":"venue"
},
  "geometry": {"coordinates":[-117.146246,32.748116],"type":"Point"}
}