{
  "type": "Feature",
  "properties": {
    "iso:country":"US",
    "sg:address":"7134 Owensmouth Ave",
    "sg:city":"Canoga Park",
    "sg:classifiers":[
        {
            "category":"Manufacturing",
            "subcategory":"Glass & Minerals",
            "type":"Manufacturing & Wholesale Goods"
        }
    ],
    "sg:phone":"+1 818 340 0245",
    "sg:postcode":"91303",
    "sg:province":"CA",
    "sg:tags":[
        "product",
        "mfg"
    ],
    "wof:name":"Dragonfly Stained Glass Studio",
    "wof:placetype":"venue"
},
  "geometry": {"coordinates":[-118.601489,34.200388],"type":"Point"}
}