{
  "type": "Feature",
  "properties": {
    "addr:full":"925 E Pennsylvania Ave Ste 1 Escondido CA 92025",
    "addr:housenumber":"925",
    "addr:postcode":"92025",
    "addr:street":"E Pennsylvania Ave Ste 1",
    "iso:country":"US",
    "sg:address":"925 E Pennsylvania Ave Ste 1",
    "sg:city":"Escondido",
    "sg:classifiers":[
        {
            "category":"Health Services",
            "subcategory":"Dentist",
            "type":"Services"
        }
    ],
    "sg:phone":"+1 760 743 7176",
    "sg:postcode":"92025",
    "sg:province":"CA",
    "sg:tags":[
        "dentists-orthodontists",
        "dental",
        "clinic",
        "dentists-pediatric",
        "dentistry"
    ],
    "sg:website":"http://drpeterbond.com",
    "wof:name":"Bond Peter R DDS MS",
    "wof:placetype":"venue"
},
  "geometry": {"coordinates":[-117.07043299999999,33.127893],"type":"Point"}
}