{
  "type": "Feature",
  "properties": {
    "addr:full":"1328 S Mary Ave Sunnyvale CA 94087",
    "addr:housenumber":"1328",
    "addr:postcode":"94087",
    "addr:street":"S Mary Ave",
    "iso:country":"US",
    "sg:address":"1328 S Mary Ave",
    "sg:city":"Sunnyvale",
    "sg:classifiers":[
        {
            "category":"Personal",
            "type":"Services"
        },
        {
            "category":"Freight",
            "type":"Transportation"
        },
        {
            "category":"Retail",
            "subcategory":"Storage",
            "type":"Services"
        }
    ],
    "sg:phone":"+1 408 739 2500",
    "sg:postcode":"94087",
    "sg:province":"CA",
    "sg:tags":[
        "mover",
        "self",
        "shipping"
    ],
    "sg:website":"www.jdmpackingsupplies.com",
    "wof:name":"JDM Packing Supplies",
    "wof:placetype":"venue"
},
  "geometry": {"coordinates":[-122.050511,37.350652],"type":"Point"}
}