{
  "type": "Feature",
  "properties": {
    "addr:full":"9253 Rancho Park Cir N Rancho Cucamonga CA 91730",
    "addr:housenumber":"9253",
    "addr:postcode":"91730",
    "addr:street":"Rancho Park Cir N",
    "iso:country":"US",
    "sg:address":"9253 Rancho Park Cir N",
    "sg:city":"Rancho Cucamonga",
    "sg:classifiers":[
        {
            "category":"Building & Trades",
            "subcategory":"Landscaping Services",
            "type":"Services"
        }
    ],
    "sg:phone":"+1 909 581 1221",
    "sg:postcode":"91730",
    "sg:province":"CA",
    "sg:tags":[
        "landscape"
    ],
    "wof:name":"Dick Oosterheert / Landscape P",
    "wof:placetype":"venue"
},
  "geometry": {"coordinates":[-117.60329400000001,34.088013],"type":"Point"}
}