{
  "type": "Feature",
  "properties": {
    "addr:full":"45274 Industrial Dr Fremont CA 94538",
    "addr:housenumber":"45274",
    "addr:postcode":"94538",
    "addr:street":"Industrial Dr",
    "iso:country":"US",
    "sg:address":"45274 Industrial Dr",
    "sg:city":"Fremont",
    "sg:classifiers":[
        {
            "category":"Shopping",
            "subcategory":"Mobile Phones",
            "type":"Retail Goods"
        }
    ],
    "sg:phone":"+1 510 656 3535",
    "sg:postcode":"94538",
    "sg:province":"CA",
    "wof:name":"Digicom Wireless Inc",
    "wof:placetype":"venue"
},
  "geometry": {"coordinates":[-121.94901,37.497175],"type":"Point"}
}