{
  "type": "Feature",
  "properties": {
    "iso:country":"US",
    "sg:address":"1225 Broadway",
    "sg:city":"Chula Vista",
    "sg:classifiers":[
        {
            "category":"Real Estate",
            "subcategory":"Real Estate Operator",
            "type":"Services"
        }
    ],
    "sg:phone":"+1 619 426 0421",
    "sg:postcode":"91911",
    "sg:province":"CA",
    "sg:tags":[
        "apartment"
    ],
    "wof:name":"Sunset Villa Apartments",
    "wof:placetype":"venue"
},
  "geometry": {"coordinates":[-117.08000199999999,32.6059],"type":"Point"}
}