{
  "type": "Feature",
  "properties": {
    "addr:full":"2860 Olive Hwy Oroville CA 95966",
    "addr:housenumber":"2860",
    "addr:postcode":"95966",
    "addr:street":"Olive Hwy",
    "iso:country":"US",
    "sg:address":"2860 Olive Hwy",
    "sg:city":"Oroville",
    "sg:classifiers":[
        {
            "category":"Health Services",
            "subcategory":"Optometrist",
            "type":"Services"
        }
    ],
    "sg:phone":"+1 530 534 9555",
    "sg:postcode":"95966",
    "sg:province":"CA",
    "wof:name":"Jeffrey W Klink OD",
    "wof:placetype":"venue"
},
  "geometry": {"coordinates":[-121.540893,39.503549],"type":"Point"}
}