{
  "type": "Feature",
  "properties": {
    "addr:full":"2017 E Westport Dr Anaheim CA 92806",
    "addr:housenumber":"2017",
    "addr:postcode":"92806",
    "addr:street":"E Westport Dr",
    "iso:country":"US",
    "sg:address":"2017 E Westport Dr",
    "sg:city":"Anaheim",
    "sg:classifiers":[
        {
            "category":"Real Estate",
            "subcategory":"Real Estate Operator",
            "type":"Services"
        }
    ],
    "sg:phone":"+1 714 778 4428",
    "sg:postcode":"92806",
    "sg:province":"CA",
    "sg:tags":[
        "apartment"
    ],
    "wof:name":"Westport Apartments",
    "wof:placetype":"venue"
},
  "geometry": {"coordinates":[-117.889,33.836899],"type":"Point"}
}