{
  "type": "Feature",
  "properties": {
    "addr:full":"11975 El Camino Real Ste 104 San Diego CA 92130",
    "addr:housenumber":"11975",
    "addr:postcode":"92130",
    "addr:street":"El Camino Real Ste 104",
    "iso:country":"US",
    "sg:address":"11975 El Camino Real Ste 104",
    "sg:city":"San Diego",
    "sg:classifiers":[
        {
            "category":"Health Services",
            "subcategory":"Doctor",
            "type":"Services"
        }
    ],
    "sg:phone":"+1 858 755 3424",
    "sg:postcode":"92130",
    "sg:province":"CA",
    "wof:name":"Carmel Valley Center LLC",
    "wof:placetype":"venue"
},
  "geometry": {"coordinates":[-117.238276,32.936528],"type":"Point"}
}