{
  "type": "Feature",
  "properties": {
    "iso:country":"US",
    "sg:address":"819 Bonita Dr",
    "sg:city":"Vista",
    "sg:classifiers":[
        {
            "category":"Professional",
            "subcategory":"Art Services",
            "type":"Services"
        }
    ],
    "sg:phone":"+1 760 224 3216",
    "sg:postcode":"92083",
    "sg:province":"CA",
    "sg:tags":[
        "graphic",
        "design"
    ],
    "sg:website":"ferdesi.com/index.html",
    "wof:name":"Ferdesi Creative Studio",
    "wof:placetype":"venue"
},
  "geometry": {"coordinates":[-117.26439499999999,33.202868],"type":"Point"}
}