{
  "type": "Feature",
  "properties": {
    "addr:full":"6618 Norwalk Blvd Whittier CA 90606",
    "addr:housenumber":"6618",
    "addr:postcode":"90606",
    "addr:street":"Norwalk Blvd",
    "iso:country":"US",
    "sg:address":"6618 Norwalk Blvd",
    "sg:city":"Whittier",
    "sg:classifiers":[
        {
            "category":"Organizations",
            "subcategory":"Religious Organization",
            "type":"Services"
        }
    ],
    "sg:phone":"+1 562 908 7995",
    "sg:postcode":"90606",
    "sg:province":"CA",
    "sg:tags":[
        "church"
    ],
    "wof:name":"Universal Church",
    "wof:placetype":"venue"
},
  "geometry": {"coordinates":[-118.068898,33.984884],"type":"Point"}
}