{
  "type": "Feature",
  "properties": {
    "addr:full":"5400 Kiernan Ave Salida CA 95368",
    "addr:postcode":"5400;95368",
    "addr:street":"Kiernan Ave",
    "iso:country":"US",
    "sg:address":"5400 Kiernan Ave",
    "sg:city":"Salida",
    "sg:classifiers":[
        {
            "category":"Social Services",
            "subcategory":"Adult Care",
            "type":"Services"
        }
    ],
    "sg:phone":"+1 209 543 9275",
    "sg:postcode":"95368",
    "sg:province":"CA",
    "sg:tags":[
        "home",
        "residential"
    ],
    "wof:name":"Hospitality House",
    "wof:placetype":"venue"
},
  "geometry": {"coordinates":[-121.09505299999999,37.710711],"type":"Point"}
}