{
  "type": "Feature",
  "properties": {
    "iso:country":"US",
    "sg:address":"984 W Foothill Blvd",
    "sg:city":"Upland",
    "sg:classifiers":[
        {
            "category":"Professional",
            "subcategory":"Management & Consulting",
            "type":"Services"
        }
    ],
    "sg:phone":"+1 909 981 1879",
    "sg:postcode":"91786",
    "sg:province":"CA",
    "sg:tags":[
        "marketing",
        "consultant"
    ],
    "wof:name":"T G Marketing",
    "wof:placetype":"venue"
},
  "geometry": {"coordinates":[-117.662459,34.106905],"type":"Point"}
}