{
  "type": "Feature",
  "properties": {
    "addr:full":"4312 S Grand Ave Los Angeles CA 90037",
    "addr:housenumber":"4312",
    "addr:postcode":"90037",
    "addr:street":"S Grand Ave",
    "iso:country":"US",
    "sg:address":"4312 S Grand Ave",
    "sg:city":"Los Angeles",
    "sg:classifiers":[
        {
            "category":"Building & Trades",
            "subcategory":"Construction",
            "type":"Services"
        }
    ],
    "sg:phone":"+1 323 231 7297",
    "sg:postcode":"90037",
    "sg:province":"CA",
    "sg:tags":[
        "cabling",
        "wiring",
        "telecommunication"
    ],
    "wof:name":"Matrix Industries Inc",
    "wof:placetype":"venue"
},
  "geometry": {"coordinates":[-118.280433,34.004233],"type":"Point"}
}