{
  "type": "Feature",
  "properties": {
    "iso:country":"US",
    "sg:address":"39206 Fremont Blvd",
    "sg:city":"Fremont",
    "sg:classifiers":[
        {
            "category":"Restaurant",
            "type":"Food & Drink"
        }
    ],
    "sg:menulink":"http://www.allmenus.com/ca/fremont/111095-cherry-garden/menu/",
    "sg:phone":"+1 510 792 8882",
    "sg:postcode":"94538",
    "sg:province":"CA",
    "sg:tags":[
        "asian",
        "filipino"
    ],
    "wof:name":"Cherry Garden",
    "wof:placetype":"venue"
},
  "geometry": {"coordinates":[-121.985653,37.5473],"type":"Point"}
}