{
  "type": "Feature",
  "properties": {
    "addr:full":"8242 Pinefield Dr Antelope CA 95843",
    "addr:housenumber":"8242",
    "addr:postcode":"95843",
    "addr:street":"Pinefield Dr",
    "iso:country":"US",
    "sg:address":"8242 Pinefield Dr",
    "sg:city":"Antelope",
    "sg:classifiers":[
        {
            "category":"Arts & Performance",
            "subcategory":"Music",
            "type":"Entertainment"
        }
    ],
    "sg:phone":"+1 916 204 2390",
    "sg:postcode":"95843",
    "sg:province":"CA",
    "sg:tags":[
        "jockey",
        "disc"
    ],
    "wof:name":"Marbob Karaoke",
    "wof:placetype":"venue"
},
  "geometry": {"coordinates":[-121.386978,38.718397],"type":"Point"}
}