{
  "type": "Feature",
  "properties": {
    "iso:country":"US",
    "sg:address":"127 N Madison Ave Ste 24",
    "sg:city":"Pasadena",
    "sg:classifiers":[
        {
            "category":"Health Services",
            "subcategory":"Chiropractor",
            "type":"Services"
        }
    ],
    "sg:phone":"+1 626 683 3091",
    "sg:postcode":"91101",
    "sg:province":"CA",
    "wof:name":"Madison Industrial Clinic",
    "wof:placetype":"venue"
},
  "geometry": {"coordinates":[-118.13800000000001,34.148201],"type":"Point"}
}