{
  "type": "Feature",
  "properties": {
    "addr:full":"1952 Sabre St Hayward CA 94545",
    "addr:housenumber":"1952",
    "addr:postcode":"94545",
    "addr:street":"Sabre St",
    "iso:country":"US",
    "sg:address":"1952 Sabre St",
    "sg:city":"Hayward",
    "sg:classifiers":[
        {
            "category":"Shopping",
            "subcategory":"Hobbies, Toys, & Games",
            "type":"Retail Goods"
        }
    ],
    "sg:phone":"+1 510 732 8112",
    "sg:postcode":"94545",
    "sg:province":"CA",
    "sg:tags":[
        "product",
        "ceramic"
    ],
    "wof:name":"Pan American Ceramics",
    "wof:placetype":"venue"
},
  "geometry": {"coordinates":[-122.134559,37.657165],"type":"Point"}
}