{
  "type": "Feature",
  "properties": {
    "iso:country":"US",
    "sg:address":"730 N Orange Ave",
    "sg:city":"West Covina",
    "sg:classifiers":[
        {
            "category":"Retail",
            "subcategory":"Portrait Studio",
            "type":"Services"
        }
    ],
    "sg:phone":"+1 626 480 0344",
    "sg:postcode":"91790",
    "sg:province":"CA",
    "wof:name":"Olan Mills Studios",
    "wof:placetype":"venue"
},
  "geometry": {"coordinates":[-117.942044,34.084282],"type":"Point"}
}