{
  "type": "Feature",
  "properties": {
    "addr:full":"10938 Cochran Ave Riverside CA 92505",
    "addr:housenumber":"10938",
    "addr:postcode":"92505",
    "addr:street":"Cochran Ave",
    "iso:country":"US",
    "sg:address":"10938 Cochran Ave",
    "sg:city":"Riverside",
    "sg:classifiers":[
        {
            "category":"Professional",
            "subcategory":"Accounting & Tax Preparation",
            "type":"Services"
        }
    ],
    "sg:phone":"+1 951 354 7220",
    "sg:postcode":"92505",
    "sg:province":"CA",
    "sg:tags":[
        "return",
        "filing"
    ],
    "wof:name":"Inland Empire Tax & Financial",
    "wof:placetype":"venue"
},
  "geometry": {"coordinates":[-117.47534899999999,33.90897],"type":"Point"}
}