{
  "type": "Feature",
  "properties": {
    "iso:country":"US",
    "sg:address":"25782 Obrero Dr",
    "sg:city":"Mission Viejo",
    "sg:classifiers":[
        {
            "category":"Shopping",
            "subcategory":"Crafts & Fabrics",
            "type":"Retail Goods"
        }
    ],
    "sg:phone":"+1 949 770 4662",
    "sg:postcode":"92691",
    "sg:province":"CA",
    "sg:tags":[
        "store"
    ],
    "wof:name":"Foam'n Fabrics Inc",
    "wof:placetype":"venue"
},
  "geometry": {"coordinates":[-117.66799899999999,33.611198],"type":"Point"}
}