{
  "type": "Feature",
  "properties": {
    "iso:country":"US",
    "sg:address":"26375 Apache Trl",
    "sg:city":"Rimforest",
    "sg:classifiers":[
        {
            "category":"Shopping",
            "type":"Retail Goods"
        }
    ],
    "sg:phone":"+1 909 337 4991",
    "sg:postcode":"92378",
    "sg:province":"CA",
    "sg:tags":[
        "art",
        "gallery",
        "dealer"
    ],
    "wof:name":"Jolley",
    "wof:placetype":"venue"
},
  "geometry": {"coordinates":[-117.226086,34.227863],"type":"Point"}
}