{
  "type": "Feature",
  "properties": {
    "addr:full":"2311 W Burbank Blvd Burbank CA 91506",
    "addr:housenumber":"2311",
    "addr:postcode":"91506",
    "addr:street":"W Burbank Blvd",
    "iso:country":"US",
    "sg:address":"2311 W Burbank Blvd",
    "sg:city":"Burbank",
    "sg:classifiers":[
        {
            "category":"Health Services",
            "subcategory":"Medical Lab",
            "type":"Services"
        }
    ],
    "sg:phone":"+1 818 567 1800",
    "sg:postcode":"91506",
    "sg:province":"CA",
    "sg:tags":[
        "laboratory"
    ],
    "wof:name":"Solo Dental Lab",
    "wof:placetype":"venue"
},
  "geometry": {"coordinates":[-118.336827,34.179261],"type":"Point"}
}