{
  "type": "Feature",
  "properties": {
    "iso:country":"US",
    "sg:address":"53 E Union St",
    "sg:city":"Pasadena",
    "sg:classifiers":[
        {
            "category":"Restaurant",
            "type":"Food & Drink"
        }
    ],
    "sg:phone":"+1 626 795 5546",
    "sg:postcode":"91103",
    "sg:province":"CA",
    "sg:tags":[
        "new",
        "american"
    ],
    "wof:name":"DISH Bistro & Bar",
    "wof:placetype":"venue"
},
  "geometry": {"coordinates":[-118.149322,34.146773],"type":"Point"}
}