{
  "type": "Feature",
  "properties": {
    "addr:full":"1206 Maple Avenue Los Angeles CA 90015",
    "addr:housenumber":"1206",
    "addr:postcode":"90015",
    "addr:street":"Maple Avenue",
    "iso:country":"US",
    "sg:address":"1206 Maple Avenue",
    "sg:city":"Los Angeles",
    "sg:classifiers":[
        {
            "category":"Shopping",
            "subcategory":"Clothing, Apparel, & Fashions",
            "type":"Retail Goods"
        }
    ],
    "sg:phone":"+1 213 749 2551",
    "sg:postcode":"90015",
    "sg:province":"CA",
    "sg:tags":[
        "children's",
        "clothing"
    ],
    "wof:name":"Rico Kids Factory",
    "wof:placetype":"venue"
},
  "geometry": {"coordinates":[-118.25635800000001,34.035553],"type":"Point"}
}