{
  "type": "Feature",
  "properties": {
    "addr:full":"1817 Soquel Ave Santa Cruz CA 95062",
    "addr:housenumber":"1817",
    "addr:postcode":"95062",
    "addr:street":"Soquel Ave",
    "iso:country":"US",
    "sg:address":"1817 Soquel Ave",
    "sg:city":"Santa Cruz",
    "sg:classifiers":[
        {
            "category":"Social Services",
            "type":"Services"
        }
    ],
    "sg:phone":"+1 831 457 8208",
    "sg:postcode":"95062",
    "sg:province":"CA",
    "sg:tags":[
        "organization",
        "welfare"
    ],
    "sg:website":"www.barriosunidos.net",
    "wof:name":"Santa Cruz Barrios Unidos Inc",
    "wof:placetype":"venue"
},
  "geometry": {"coordinates":[-122.00115700000001,36.98154],"type":"Point"}
}