{
  "type": "Feature",
  "properties": {
    "addr:full":"569 Saddleback Dr Marysville CA 95901",
    "addr:housenumber":"569",
    "addr:postcode":"95901",
    "addr:street":"Saddleback Dr",
    "iso:country":"US",
    "sg:address":"569 Saddleback Dr",
    "sg:city":"Marysville",
    "sg:classifiers":[
        {
            "category":"Social Services",
            "subcategory":"Adult Care",
            "type":"Services"
        }
    ],
    "sg:phone":"+1 530 755 2018",
    "sg:postcode":"95901",
    "sg:province":"CA",
    "sg:tags":[
        "organization",
        "senior",
        "citizen"
    ],
    "wof:name":"Ombudsman Services-Northern Ca",
    "wof:placetype":"venue"
},
  "geometry": {"coordinates":[-121.589747,39.186832],"type":"Point"}
}