{
  "type": "Feature",
  "properties": {
    "addr:full":"844 N Van Ness Ave Fresno CA 93728",
    "addr:housenumber":"844",
    "addr:postcode":"93728",
    "addr:street":"N Van Ness Ave",
    "iso:country":"US",
    "sg:address":"844 N Van Ness Ave",
    "sg:city":"Fresno",
    "sg:classifiers":[
        {
            "category":"Professional",
            "subcategory":"Lawyer & Legal Services",
            "type":"Services"
        }
    ],
    "sg:phone":"+1 559 441 0201",
    "sg:postcode":"93728",
    "sg:province":"CA",
    "sg:tags":[
        "attorney"
    ],
    "wof:name":"Jacob M Weisberg Law Offices",
    "wof:placetype":"venue"
},
  "geometry": {"coordinates":[-119.798788,36.754036],"type":"Point"}
}