{
  "type": "Feature",
  "properties": {
    "iso:country":"US",
    "sg:address":"1133 N Tustin Ave",
    "sg:city":"Anaheim",
    "sg:classifiers":[
        {
            "category":"Autos & Motor Vehicles",
            "subcategory":"Auto Supplies",
            "type":"Retail Goods"
        },
        {
            "category":"Retail",
            "subcategory":"Auto Repair",
            "type":"Services"
        }
    ],
    "sg:phone":"+1 714 630 0700",
    "sg:postcode":"92807",
    "sg:province":"CA",
    "sg:tags":[
        "part",
        "tire"
    ],
    "sg:website":"www.CorvetteMike.com",
    "wof:name":"Corvette Mike Sales & Service",
    "wof:placetype":"venue"
},
  "geometry": {"coordinates":[-117.83699799999999,33.856701],"type":"Point"}
}