{
  "type": "Feature",
  "properties": {
    "iso:country":"US",
    "sg:address":"11960 Silvergate Dr",
    "sg:city":"Dublin",
    "sg:classifiers":[
        {
            "category":"Banks & Credit Unions",
            "subcategory":"Bank",
            "type":"Services"
        }
    ],
    "sg:phone":"+1 925 560 0230",
    "sg:postcode":"94568",
    "sg:province":"CA",
    "sg:tags":[
        "national",
        "commercial"
    ],
    "wof:name":"Pacific National Bank",
    "wof:placetype":"venue"
},
  "geometry": {"coordinates":[-121.938683,37.709123],"type":"Point"}
}