{
  "type": "Feature",
  "properties": {
    "addr:full":"1388 Haight St San Francisco CA 94117",
    "addr:housenumber":"1388",
    "addr:postcode":"94117",
    "addr:street":"Haight St",
    "iso:country":"US",
    "sg:address":"1388 Haight St",
    "sg:city":"San Francisco",
    "sg:classifiers":[
        {
            "category":"Manufacturing",
            "subcategory":"Printing",
            "type":"Manufacturing & Wholesale Goods"
        }
    ],
    "sg:phone":"+1 415 861 7583",
    "sg:postcode":"94117",
    "sg:province":"CA",
    "sg:tags":[
        "periodical"
    ],
    "wof:name":"Xlr8r Magazine",
    "wof:placetype":"venue"
},
  "geometry": {"coordinates":[-122.444153,37.770478],"type":"Point"}
}