{
  "type": "Feature",
  "properties": {
    "iso:country":"US",
    "sg:address":"2525 Lupine Hills Dr",
    "sg:city":"Vista",
    "sg:classifiers":[
        {
            "category":"Utilities",
            "subcategory":"Electric",
            "type":"Services"
        },
        {
            "category":"Utilities",
            "type":"Services"
        }
    ],
    "sg:phone":"+1 760 727 0801",
    "sg:postcode":"92081",
    "sg:province":"CA",
    "wof:name":"Shadowridge Water Reclamation Plant",
    "wof:placetype":"venue"
},
  "geometry": {"coordinates":[-117.235028,33.160471],"type":"Point"}
}