{
  "type": "Feature",
  "properties": {
    "addr:full":"20659 Shelly Dr Cupertino CA 95014",
    "addr:housenumber":"20659",
    "addr:postcode":"95014",
    "addr:street":"Shelly Dr",
    "iso:country":"US",
    "sg:address":"20659 Shelly Dr",
    "sg:city":"Cupertino",
    "sg:classifiers":[
        {
            "category":"Building & Trades",
            "subcategory":"Construction",
            "type":"Services"
        }
    ],
    "sg:phone":"+1 408 446 5588",
    "sg:postcode":"95014",
    "sg:province":"CA",
    "sg:tags":[
        "contractor"
    ],
    "wof:name":"L Squarcia Roofing Company",
    "wof:placetype":"venue"
},
  "geometry": {"coordinates":[-122.034893,37.318655],"type":"Point"}
}