{
  "type": "Feature",
  "properties": {
    "iso:country":"US",
    "sg:address":"9200 Sunset Blvd Ste 170",
    "sg:city":"Los Angeles",
    "sg:classifiers":[
        {
            "category":"Professional",
            "type":"Services"
        }
    ],
    "sg:phone":"+1 310 274 0340",
    "sg:postcode":"90069",
    "sg:province":"CA",
    "sg:website":"www.sothebys.com",
    "wof:name":"Sotheby's Auction",
    "wof:placetype":"venue"
},
  "geometry": {"coordinates":[-118.392883,34.089928],"type":"Point"}
}