{
  "type": "Feature",
  "properties": {
    "addr:full":"136 S Oak Knoll Ave Pasadena CA 91101",
    "addr:housenumber":"136",
    "addr:postcode":"91101",
    "addr:street":"S Oak Knoll Ave",
    "iso:country":"US",
    "sg:address":"136 S Oak Knoll Ave",
    "sg:city":"Pasadena",
    "sg:classifiers":[
        {
            "category":"Professional",
            "subcategory":"Accounting & Tax Preparation",
            "type":"Services"
        }
    ],
    "sg:phone":"+1 626 449 7091",
    "sg:postcode":"91101",
    "sg:province":"CA",
    "sg:tags":[
        "accountant"
    ],
    "wof:name":"Goehner Accountancy",
    "wof:placetype":"venue"
},
  "geometry": {"coordinates":[-118.135125,34.144174],"type":"Point"}
}