{
  "type": "Feature",
  "properties": {
    "addr:full":"6000 E Palm Canyon Dr Palm Springs CA 92264",
    "addr:housenumber":"6000",
    "addr:postcode":"92264",
    "addr:street":"E Palm Canyon Dr",
    "iso:country":"US",
    "sg:address":"6000 E Palm Canyon Dr",
    "sg:city":"Palm Springs",
    "sg:classifiers":[
        {
            "category":"Real Estate",
            "subcategory":"Developer",
            "type":"Services"
        }
    ],
    "sg:phone":"+1 760 328 2815",
    "sg:postcode":"92264",
    "sg:province":"CA",
    "sg:tags":[
        "mobile",
        "home"
    ],
    "wof:name":"El Dorado Mobile Country Club",
    "wof:placetype":"venue"
},
  "geometry": {"coordinates":[-116.484407,33.789812],"type":"Point"}
}