{
  "type": "Feature",
  "properties": {
    "addr:full":"1339 W Brooks St Ontario CA 91762",
    "addr:housenumber":"1339",
    "addr:postcode":"91762",
    "addr:street":"W Brooks St",
    "iso:country":"US",
    "sg:address":"1339 W Brooks St",
    "sg:city":"Ontario",
    "sg:classifiers":[
        {
            "category":"Professional",
            "type":"Services"
        },
        {
            "category":"Building & Trades",
            "subcategory":"Construction",
            "type":"Services"
        }
    ],
    "sg:phone":"+1 909 460 1865",
    "sg:postcode":"91762",
    "sg:province":"CA",
    "sg:tags":[
        "house",
        "wood",
        "specialty"
    ],
    "wof:name":"M & R Wood Products Inc",
    "wof:placetype":"venue"
},
  "geometry": {"coordinates":[-117.671008,34.061947],"type":"Point"}
}