{
  "type": "Feature",
  "properties": {
    "iso:country":"US",
    "sg:address":"2742 Loker Ave W",
    "sg:city":"Carlsbad",
    "sg:classifiers":[
        {
            "category":"Professional",
            "type":"Services"
        }
    ],
    "sg:phone":"+1 760 931 2910",
    "sg:postcode":"92008",
    "sg:province":"CA",
    "sg:tags":[
        "establishment"
    ],
    "wof:name":"Auroralight",
    "wof:placetype":"venue"
},
  "geometry": {"coordinates":[-117.254086,33.131462],"type":"Point"}
}