{
  "type": "Feature",
  "properties": {
    "addr:full":"626 Kearney Ave Modesto CA 95350",
    "addr:housenumber":"626",
    "addr:postcode":"ca 95350",
    "addr:street":"Kearney Ave",
    "iso:country":"US",
    "sg:address":"626 Kearney Ave",
    "sg:city":"Modesto",
    "sg:classifiers":[
        {
            "category":"Manufacturing",
            "subcategory":"Furniture",
            "type":"Manufacturing & Wholesale Goods"
        }
    ],
    "sg:phone":"+1 209 529 1716",
    "sg:postcode":"95350",
    "sg:province":"CA",
    "sg:tags":[
        "public"
    ],
    "sg:website":"www.imperialww.com",
    "wof:name":"Overholtzer Church Furniture",
    "wof:placetype":"venue"
},
  "geometry": {"coordinates":[-121.016606,37.654281],"type":"Point"}
}