{
  "type": "Feature",
  "properties": {
    "iso:country":"US",
    "sg:address":"3100 E Florence Avenue",
    "sg:city":"Huntington Park",
    "sg:classifiers":[
        {
            "category":"Health Services",
            "subcategory":"Doctor",
            "type":"Services"
        }
    ],
    "sg:phone":"+1 323 583 6516",
    "sg:postcode":"90255",
    "sg:province":"CA",
    "wof:name":"Nguyen Tao",
    "wof:placetype":"venue"
},
  "geometry": {"coordinates":[-118.21238099999999,33.972871],"type":"Point"}
}