{
  "type": "Feature",
  "properties": {
    "addr:full":"4593 Rd 24 Madera CA 93637",
    "addr:postcode":"4593;93637",
    "addr:street":"Rd 24",
    "iso:country":"US",
    "sg:address":"4593 Rd 24",
    "sg:city":"Madera",
    "sg:phone":"+1 559 674 5945",
    "sg:postcode":"93637",
    "sg:province":"CA",
    "sg:tags":[
        "farm",
        "vineyard",
        "grape"
    ],
    "wof:name":"Foster & Vera Rein",
    "wof:placetype":"venue"
},
  "geometry": {"coordinates":[-120.114814,36.820775],"type":"Point"}
}