{
  "type": "Feature",
  "properties": {
    "iso:country":"US",
    "sg:address":"8415 S Vermont Ave",
    "sg:city":"Los Angeles",
    "sg:classifiers":[
        {
            "category":"Shopping",
            "subcategory":"Clothing, Apparel, & Fashions",
            "type":"Retail Goods"
        }
    ],
    "sg:phone":"+1 323 752 1612",
    "sg:postcode":"90044",
    "sg:province":"CA",
    "sg:tags":[
        "tailor",
        "alteration",
        "sewing"
    ],
    "wof:name":"M-T Tailors Shop",
    "wof:placetype":"venue"
},
  "geometry": {"coordinates":[-118.292,33.9622],"type":"Point"}
}