{
  "type": "Feature",
  "properties": {
    "iso:country":"US",
    "sg:address":"1308 65th St",
    "sg:city":"Sacramento",
    "sg:classifiers":[
        {
            "category":"Retail",
            "subcategory":"Laundry & Dry Cleaning",
            "type":"Services"
        }
    ],
    "sg:phone":"+1 916 455 3081",
    "sg:postcode":"95819",
    "sg:province":"CA",
    "sg:tags":[
        "cleaner",
        "rug",
        "carpeting",
        "carpet"
    ],
    "wof:name":"Sacramento Rug Works",
    "wof:placetype":"venue"
},
  "geometry": {"coordinates":[-121.42800099999999,38.555099],"type":"Point"}
}