{
  "type": "Feature",
  "properties": {
    "iso:country":"US",
    "sg:address":"1925 E Lincoln Ave",
    "sg:city":"Anaheim",
    "sg:classifiers":[
        {
            "category":"Professional",
            "type":"Services"
        }
    ],
    "sg:phone":"+1 714 778 3019",
    "sg:postcode":"92805",
    "sg:province":"CA",
    "wof:name":"MI Fondita",
    "wof:placetype":"venue"
},
  "geometry": {"coordinates":[-117.890574,33.840257],"type":"Point"}
}