{
  "type": "Feature",
  "properties": {
    "iso:country":"US",
    "sg:address":"3107 W Rosecrans Ave",
    "sg:city":"Hawthorne",
    "sg:classifiers":[
        {
            "category":"Retail",
            "subcategory":"Laundry & Dry Cleaning",
            "type":"Services"
        }
    ],
    "sg:phone":"+1 310 675 2378",
    "sg:postcode":"90250",
    "sg:province":"CA",
    "wof:name":"Best Cleaners",
    "wof:placetype":"venue"
},
  "geometry": {"coordinates":[-118.327003,33.901798],"type":"Point"}
}