{
  "type": "Feature",
  "properties": {
    "iso:country":"US",
    "sg:address":"2227 Winchester Blvd",
    "sg:city":"Campbell",
    "sg:classifiers":[
        {
            "category":"Retail",
            "subcategory":"Laundry & Dry Cleaning",
            "type":"Services"
        }
    ],
    "sg:phone":"+1 408 378 3181",
    "sg:postcode":"95008",
    "sg:province":"CA",
    "wof:name":"Michael Cleaners",
    "wof:placetype":"venue"
},
  "geometry": {"coordinates":[-121.950013,37.282976],"type":"Point"}
}