{
  "type": "Feature",
  "properties": {
    "addr:full":"3790 Via De La Valle Del Mar CA 92014",
    "addr:housenumber":"3790",
    "addr:postcode":"92014",
    "addr:street":"Via De La Valle",
    "iso:country":"US",
    "sg:address":"3790 Via De La Valle",
    "sg:city":"Del Mar",
    "sg:classifiers":[
        {
            "category":"Shopping",
            "subcategory":"Beauty & Cosmetics",
            "type":"Retail Goods"
        },
        {
            "category":"Personal",
            "subcategory":"Nail Salon",
            "type":"Services"
        }
    ],
    "sg:phone":"+1 858 792 1985",
    "sg:postcode":"92014",
    "sg:province":"CA",
    "sg:tags":[
        "supply"
    ],
    "wof:name":"Vivace",
    "wof:placetype":"venue"
},
  "geometry": {"coordinates":[-117.228996,32.982899],"type":"Point"}
}