{
  "type": "Feature",
  "properties": {
    "addr:full":"411 Main St Suisun City CA 94585",
    "addr:housenumber":"411",
    "addr:postcode":"94585",
    "addr:street":"Main St",
    "iso:country":"US",
    "sg:address":"411 Main St",
    "sg:city":"Suisun City",
    "sg:classifiers":[
        {
            "category":"Manufacturing",
            "subcategory":"Jewelry",
            "type":"Manufacturing & Wholesale Goods"
        }
    ],
    "sg:phone":"+1 707 425 3891",
    "sg:postcode":"94585",
    "sg:province":"CA",
    "sg:tags":[
        "repair",
        "precious",
        "metal",
        "mfg"
    ],
    "wof:name":"Barbozas Golden Bear",
    "wof:placetype":"venue"
},
  "geometry": {"coordinates":[-122.04062399999999,38.240293],"type":"Point"}
}