{
  "type": "Feature",
  "properties": {
    "iso:country":"US",
    "sg:address":"906 N Court St",
    "sg:city":"Visalia",
    "sg:classifiers":[
        {
            "category":"Food & Beverages",
            "subcategory":"Specialty",
            "type":"Retail Goods"
        },
        {
            "category":"Food & Beverages",
            "subcategory":"Groceries & Convenience Stores",
            "type":"Retail Goods"
        }
    ],
    "sg:phone":"+1 559 734 0304",
    "sg:postcode":"93291",
    "sg:province":"CA",
    "sg:tags":[
        "grocers-specialty"
    ],
    "wof:name":"Visalia Foodland",
    "wof:placetype":"venue"
},
  "geometry": {"coordinates":[-119.292985,36.337481],"type":"Point"}
}