{
  "type": "Feature",
  "properties": {
    "addr:full":"1314 Southgate Ave Daly City CA 94015",
    "addr:housenumber":"1314",
    "addr:postcode":"94015",
    "addr:street":"Southgate Ave",
    "iso:country":"US",
    "sg:address":"1314 Southgate Ave",
    "sg:city":"Daly City",
    "sg:classifiers":[
        {
            "category":"Wholesale",
            "subcategory":"Jewelry",
            "type":"Manufacturing & Wholesale Goods"
        }
    ],
    "sg:phone":"+1 650 755 3000",
    "sg:postcode":"94015",
    "sg:province":"CA",
    "sg:tags":[
        "jeweler"
    ],
    "wof:name":"JJJ Natural Pearls",
    "wof:placetype":"venue"
},
  "geometry": {"coordinates":[-122.483253,37.676022],"type":"Point"}
}