{
  "type": "Feature",
  "properties": {
    "addr:full":"113 W Los Feliz Rd Glendale CA 91204",
    "addr:housenumber":"113",
    "addr:postcode":"91204",
    "addr:street":"W Los Feliz Rd",
    "iso:country":"US",
    "sg:address":"113 W Los Feliz Rd",
    "sg:city":"Glendale",
    "sg:classifiers":[
        {
            "category":"Home & Garden",
            "subcategory":"Home Furnishings",
            "type":"Retail Goods"
        }
    ],
    "sg:phone":"+1 818 242 2988",
    "sg:postcode":"91204",
    "sg:province":"CA",
    "sg:tags":[
        "bath",
        "kitchen"
    ],
    "sg:website":"www.glendalett.com",
    "wof:name":"Glendale Tiles and Tops",
    "wof:placetype":"venue"
},
  "geometry": {"coordinates":[-118.255516,34.128672],"type":"Point"}
}