{
  "type": "Feature",
  "properties": {
    "iso:country":"US",
    "sg:address":"11709 Glenoaks Blvd",
    "sg:city":"San Fernando",
    "sg:classifiers":[
        {
            "category":"Building & Trades",
            "subcategory":"Landscaping Services",
            "type":"Services"
        }
    ],
    "sg:phone":"+1 818 365 8782",
    "sg:postcode":"91340",
    "sg:province":"CA",
    "wof:name":"Interiano Landscaping",
    "wof:placetype":"venue"
},
  "geometry": {"coordinates":[-118.421803,34.283103],"type":"Point"}
}