{
  "type": "Feature",
  "properties": {
    "addr:full":"1010 S Santa Fe Ave Vista CA 92084",
    "addr:housenumber":"1010",
    "addr:postcode":"92084",
    "addr:street":"S Santa Fe Ave",
    "iso:country":"US",
    "sg:address":"1010 S Santa Fe Ave",
    "sg:city":"Vista",
    "sg:classifiers":[
        {
            "category":"Sports & Exercise",
            "subcategory":"Gym",
            "type":"Entertainment"
        }
    ],
    "sg:phone":"+1 760 724 6941",
    "sg:postcode":"92084",
    "sg:province":"CA",
    "sg:tags":[
        "club",
        "health",
        "studio",
        "gymnasium"
    ],
    "wof:name":"San Diego Workout",
    "wof:placetype":"venue"
},
  "geometry": {"coordinates":[-117.23065200000001,33.192563],"type":"Point"}
}