{
  "type": "Feature",
  "properties": {
    "iso:country":"US",
    "sg:address":"10450 Friars Rd #L",
    "sg:city":"San Diego",
    "sg:classifiers":[
        {
            "category":"Personal",
            "subcategory":"Massage",
            "type":"Services"
        },
        {
            "category":"Health Services",
            "subcategory":"Clinic",
            "type":"Services"
        }
    ],
    "sg:phone":"+1 619 280 3333",
    "sg:postcode":"92120",
    "sg:province":"CA",
    "sg:tags":[
        "medical"
    ],
    "wof:name":"Friars Massage",
    "wof:placetype":"venue"
},
  "geometry": {"coordinates":[-117.09876800000001,32.792159],"type":"Point"}
}