{
  "type": "Feature",
  "properties": {
    "iso:country":"US",
    "sg:address":"1487 Virginia Ave",
    "sg:city":"Baldwin Park",
    "sg:classifiers":[
        {
            "category":"Professional",
            "subcategory":"Business Services",
            "type":"Services"
        },
        {
            "category":"Manufacturing",
            "subcategory":"Tools & Machinery",
            "type":"Manufacturing & Wholesale Goods"
        }
    ],
    "sg:phone":"+1 626 338 0090",
    "sg:postcode":"91706",
    "sg:province":"CA",
    "sg:tags":[
        "shop",
        "machine",
        "industrial",
        "mfg"
    ],
    "wof:name":"Hugo's Specialties Inc",
    "wof:placetype":"venue"
},
  "geometry": {"coordinates":[-117.974907,34.067906],"type":"Point"}
}