{
  "type": "Feature",
  "properties": {
    "addr:full":"4854 E Princeton Ave Fresno CA 93703",
    "addr:housenumber":"4854",
    "addr:postcode":"93703",
    "addr:street":"E Princeton Ave",
    "iso:country":"US",
    "sg:address":"4854 E Princeton Ave",
    "sg:city":"Fresno",
    "sg:classifiers":[
        {
            "category":"Building & Trades",
            "subcategory":"Landscaping Services",
            "type":"Services"
        }
    ],
    "sg:phone":"+1 559 453 9554",
    "sg:postcode":"93703",
    "sg:province":"CA",
    "wof:name":"A To Z Landscaping Maintenance",
    "wof:placetype":"venue"
},
  "geometry": {"coordinates":[-119.733926,36.775786],"type":"Point"}
}