{
  "type": "Feature",
  "properties": {
    "addr:full":"911 E 11th St Los Angeles CA 90021",
    "addr:housenumber":"911",
    "addr:postcode":"90021",
    "addr:street":"E 11Th St",
    "iso:country":"US",
    "sg:address":"911 E 11th St",
    "sg:city":"Los Angeles",
    "sg:classifiers":[
        {
            "category":"Shopping",
            "subcategory":"Hobbies, Toys, & Games",
            "type":"Retail Goods"
        }
    ],
    "sg:phone":"+1 213 688 1157",
    "sg:postcode":"90021",
    "sg:province":"CA",
    "sg:tags":[
        "equipment",
        "video",
        "rental"
    ],
    "wof:name":"Awesome Choice Inc",
    "wof:placetype":"venue"
},
  "geometry": {"coordinates":[-118.24485300000001,34.031074],"type":"Point"}
}