{
  "type": "Feature",
  "properties": {
    "addr:full":"574 E Cotati Ave Cotati CA 94931",
    "addr:housenumber":"574",
    "addr:postcode":"94931",
    "addr:street":"E Cotati Ave",
    "iso:country":"US",
    "sg:address":"574 E Cotati Ave",
    "sg:city":"Cotati",
    "sg:classifiers":[
        {
            "category":"Personal",
            "subcategory":"Beauty Salon",
            "type":"Services"
        }
    ],
    "sg:phone":"+1 707 794 9196",
    "sg:postcode":"94931",
    "sg:province":"CA",
    "sg:tags":[
        "manicuring"
    ],
    "wof:name":"Star Nails",
    "wof:placetype":"venue"
},
  "geometry": {"coordinates":[-122.698431,38.328943],"type":"Point"}
}