{
  "type": "Feature",
  "properties": {
    "addr:full":"10007 Topanga Canyon Blvd Chatsworth CA 91311",
    "addr:housenumber":"10007",
    "addr:postcode":"91311",
    "addr:street":"Topanga Canyon Blvd",
    "iso:country":"US",
    "sg:address":"10007 Topanga Canyon Blvd",
    "sg:city":"Chatsworth",
    "sg:classifiers":[
        {
            "category":"Professional",
            "subcategory":"Management & Consulting",
            "type":"Services"
        }
    ],
    "sg:phone":"+1 818 773 8380",
    "sg:postcode":"91311",
    "sg:province":"CA",
    "sg:tags":[
        "marketing",
        "consultant"
    ],
    "wof:name":"Just Ask Dar",
    "wof:placetype":"venue"
},
  "geometry": {"coordinates":[-118.606038,34.251654],"type":"Point"}
}