{
  "type": "Feature",
  "properties": {
    "addr:full":"937 Cole St San Francisco CA 94117",
    "addr:housenumber":"937",
    "addr:postcode":"94117",
    "addr:street":"Cole St",
    "iso:country":"US",
    "sg:address":"937 Cole St",
    "sg:city":"San Francisco",
    "sg:classifiers":[
        {
            "category":"Bars & Pubs",
            "type":"Food & Drink"
        }
    ],
    "sg:phone":"+1 415 731 6119",
    "sg:postcode":"94117",
    "sg:province":"CA",
    "sg:tags":[
        "lounge",
        "cocktail"
    ],
    "wof:name":"Finnegan's Wake",
    "wof:placetype":"venue"
},
  "geometry": {"coordinates":[-122.449896,37.765463],"type":"Point"}
}