{
  "type": "Feature",
  "properties": {
    "addr:full":"4100 Creekside Dr Shingle Springs CA 95682",
    "addr:housenumber":"4100",
    "addr:postcode":"95682",
    "addr:street":"Creekside Dr",
    "iso:country":"US",
    "sg:address":"4100 Creekside Dr",
    "sg:city":"Shingle Springs",
    "sg:classifiers":[
        {
            "category":"Building & Trades",
            "subcategory":"Construction",
            "type":"Services"
        }
    ],
    "sg:phone":"+1 530 677 5361",
    "sg:postcode":"95682",
    "sg:province":"CA",
    "sg:tags":[
        "water",
        "well",
        "drilling"
    ],
    "sg:website":"www.welldrilling.org",
    "wof:name":"Robert Dawson Drilling Inc",
    "wof:placetype":"venue"
},
  "geometry": {"coordinates":[-120.929096,38.663571],"type":"Point"}
}