{
  "type": "Feature",
  "properties": {
    "addr:full":"2561 E Tiffany Ln Sacramento CA 95827",
    "addr:housenumber":"2561",
    "addr:postcode":"95827",
    "addr:street":"E Tiffany Ln",
    "iso:country":"US",
    "sg:address":"2561 E Tiffany Ln",
    "sg:city":"Sacramento",
    "sg:classifiers":[
        {
            "category":"Professional",
            "subcategory":"Computer Services",
            "type":"Services"
        }
    ],
    "sg:phone":"+1 916 366 9663",
    "sg:postcode":"95827",
    "sg:province":"CA",
    "sg:tags":[
        "website",
        "design"
    ],
    "sg:website":"www.transport-media.com",
    "wof:name":"Sanders & Assoc",
    "wof:placetype":"venue"
},
  "geometry": {"coordinates":[-121.32507200000001,38.585615],"type":"Point"}
}