{
  "type": "Feature",
  "properties": {
    "iso:country":"US",
    "sg:address":"6434 Foothill Blvd",
    "sg:city":"Tujunga",
    "sg:classifiers":[
        {
            "category":"Building & Trades",
            "subcategory":"Electrical",
            "type":"Services"
        }
    ],
    "sg:phone":"+1 818 951 8090",
    "sg:postcode":"91042",
    "sg:province":"CA",
    "sg:tags":[
        "electrician"
    ],
    "wof:name":"Cornerstone Electrical",
    "wof:placetype":"venue"
},
  "geometry": {"coordinates":[-118.271825,34.243948],"type":"Point"}
}