{
  "type": "Feature",
  "properties": {
    "addr:full":"25605 Wickerd Rd Menifee CA 92584",
    "addr:housenumber":"25605",
    "addr:postcode":"92584",
    "addr:street":"Wickerd Rd",
    "iso:country":"US",
    "sg:address":"25605 Wickerd Rd",
    "sg:city":"Menifee",
    "sg:classifiers":[
        {
            "category":"Manufacturing",
            "subcategory":"Tools & Machinery",
            "type":"Manufacturing & Wholesale Goods"
        }
    ],
    "sg:phone":"+1 951 679 3110",
    "sg:postcode":"92584",
    "sg:province":"CA",
    "sg:tags":[
        "industrial",
        "mfg"
    ],
    "wof:name":"Micron Erosion Inc",
    "wof:placetype":"venue"
},
  "geometry": {"coordinates":[-117.20667,33.648681],"type":"Point"}
}