{
  "type": "Feature",
  "properties": {
    "iso:country":"US",
    "sg:address":"1110 Bates St",
    "sg:city":"Los Angeles",
    "sg:classifiers":[
        {
            "category":"Sports & Exercise",
            "subcategory":"Gym",
            "type":"Entertainment"
        }
    ],
    "sg:phone":"+1 818 599 9037",
    "sg:postcode":"90029",
    "sg:province":"CA",
    "sg:tags":[
        "trainer"
    ],
    "wof:name":"BASIC Weight Loss Boot Camp",
    "wof:placetype":"venue"
},
  "geometry": {"coordinates":[-118.281671,34.095085],"type":"Point"}
}