{
  "type": "Feature",
  "properties": {
    "addr:full":"15466 Los Gatos Blvd. Ste 210 Los Gatos CA 95032",
    "addr:housenumber":"15466",
    "addr:postcode":"95032",
    "addr:street":"Los Gatos Blvd. Ste 210",
    "iso:country":"US",
    "sg:address":"15466 Los Gatos Blvd. Ste 210",
    "sg:city":"Los Gatos",
    "sg:classifiers":[
        {
            "category":"Shopping",
            "subcategory":"Jewelry",
            "type":"Retail Goods"
        },
        {
            "category":"Shopping",
            "subcategory":"Pawn Shop",
            "type":"Retail Goods"
        }
    ],
    "sg:phone":"+1 408 358 5336",
    "sg:postcode":"95032",
    "sg:province":"CA",
    "sg:website":"www.gemgate.com",
    "wof:name":"Lovelady Diamond Gold & Jewelry Buyers",
    "wof:placetype":"venue"
},
  "geometry": {"coordinates":[-121.957855,37.244291],"type":"Point"}
}