{
  "type": "Feature",
  "properties": {
    "addr:full":"500 US Hwy 395 Alturas CA 96101",
    "addr:housenumber":"500",
    "addr:postcode":"96101",
    "addr:street":"Us Hwy 395",
    "iso:country":"US",
    "sg:address":"500 US Hwy 395",
    "sg:city":"Alturas",
    "sg:classifiers":[
        {
            "category":"Home & Garden",
            "subcategory":"Mobile Homes",
            "type":"Retail Goods"
        }
    ],
    "sg:phone":"+1 530 233 5556",
    "sg:postcode":"96101",
    "sg:province":"CA",
    "wof:name":"North State Homes",
    "wof:placetype":"venue"
},
  "geometry": {"coordinates":[-120.542417,41.480944],"type":"Point"}
}