{
  "type": "Feature",
  "properties": {
    "addr:full":"25421 Cole St Loma Linda CA 92354",
    "addr:housenumber":"25421",
    "addr:postcode":"92354",
    "addr:street":"Cole St",
    "iso:country":"US",
    "sg:address":"25421 Cole St",
    "sg:city":"Loma Linda",
    "sg:classifiers":[
        {
            "category":"Real Estate",
            "subcategory":"Real Estate Operator",
            "type":"Services"
        }
    ],
    "sg:phone":"+1 909 796 1310",
    "sg:postcode":"92354",
    "sg:province":"CA",
    "sg:tags":[
        "apartment"
    ],
    "wof:name":"Loma Sierra Apartments",
    "wof:placetype":"venue"
},
  "geometry": {"coordinates":[-117.249534,34.299286],"type":"Point"}
}