{
  "type": "Feature",
  "properties": {
    "addr:full":"271 Kinney Dr San Jose CA 95112",
    "addr:housenumber":"271",
    "addr:postcode":"95112",
    "addr:street":"Kinney Dr",
    "iso:country":"US",
    "sg:address":"271 Kinney Dr",
    "sg:city":"San Jose",
    "sg:classifiers":[
        {
            "category":"Wholesale",
            "subcategory":"Fruits & Vegetables",
            "type":"Manufacturing & Wholesale Goods"
        }
    ],
    "sg:phone":"+1 408 297 3638",
    "sg:postcode":"95112",
    "sg:province":"CA",
    "wof:name":"L K Produce",
    "wof:placetype":"venue"
},
  "geometry": {"coordinates":[-121.900373,37.359284],"type":"Point"}
}