{
  "type": "Feature",
  "properties": {
    "iso:country":"US",
    "sg:address":"11019 Jacinto Way",
    "sg:city":"Ventura",
    "sg:classifiers":[
        {
            "category":"Manufacturing",
            "subcategory":"Retail Goods",
            "type":"Manufacturing & Wholesale Goods"
        }
    ],
    "sg:phone":"+1 805 672 0210",
    "sg:postcode":"93004",
    "sg:province":"CA",
    "sg:tags":[
        "marking",
        "devices"
    ],
    "wof:name":"Doyle & Co",
    "wof:placetype":"venue"
},
  "geometry": {"coordinates":[-119.145818,34.278533],"type":"Point"}
}