{
  "type": "Feature",
  "properties": {
    "addr:full":"45981 Classic Way Temecula CA 92592",
    "addr:housenumber":"45981",
    "addr:postcode":"92592",
    "addr:street":"Classic Way",
    "iso:country":"US",
    "sg:address":"45981 Classic Way",
    "sg:city":"Temecula",
    "sg:classifiers":[
        {
            "category":"Professional",
            "type":"Services"
        }
    ],
    "sg:phone":"+1 951 506 3969",
    "sg:postcode":"92592",
    "sg:province":"CA",
    "wof:name":"Scentsabilities",
    "wof:placetype":"venue"
},
  "geometry": {"coordinates":[-117.12147299999999,33.46357],"type":"Point"}
}