{
  "type": "Feature",
  "properties": {
    "addr:full":"8110 Manitoba St Playa Del Rey CA 90293",
    "addr:housenumber":"8110",
    "addr:postcode":"90293",
    "addr:street":"Manitoba St",
    "iso:country":"US",
    "sg:address":"8110 Manitoba St",
    "sg:city":"Playa Del Rey",
    "sg:classifiers":[
        {
            "category":"Wholesale",
            "subcategory":"Electrical",
            "type":"Manufacturing & Wholesale Goods"
        }
    ],
    "sg:phone":"+1 310 301 0673",
    "sg:postcode":"90293",
    "sg:province":"CA",
    "sg:tags":[
        "electronic"
    ],
    "wof:name":"Loftworks Co",
    "wof:placetype":"venue"
},
  "geometry": {"coordinates":[-118.436436,33.955768],"type":"Point"}
}