{
  "type": "Feature",
  "properties": {
    "addr:full":"14090 Red Hill Ave Tustin CA 92780",
    "addr:housenumber":"14090",
    "addr:postcode":"92780",
    "addr:street":"Red Hill Ave",
    "iso:country":"US",
    "sg:address":"14090 Red Hill Ave",
    "sg:city":"Tustin",
    "sg:classifiers":[
        {
            "category":"Food & Beverages",
            "subcategory":"Groceries & Convenience Stores",
            "type":"Retail Goods"
        }
    ],
    "sg:phone":"+1 714 832 7584",
    "sg:postcode":"92780",
    "sg:province":"CA",
    "sg:website":"www.7-eleven.com",
    "wof:name":"7-Eleven",
    "wof:placetype":"venue"
},
  "geometry": {"coordinates":[-117.816582,33.732302],"type":"Point"}
}