{
  "type": "Feature",
  "properties": {
    "addr:full":"8738 Chester St Paramount CA 90723",
    "addr:housenumber":"8738",
    "addr:postcode":"90723",
    "addr:street":"Chester St",
    "iso:country":"US",
    "sg:address":"8738 Chester St",
    "sg:city":"Paramount",
    "sg:classifiers":[
        {
            "category":"Restaurant",
            "type":"Food & Drink"
        }
    ],
    "sg:phone":"+1 562 531 0719",
    "sg:postcode":"90723",
    "sg:province":"CA",
    "sg:tags":[
        "mexican"
    ],
    "wof:name":"Garcias Lavado",
    "wof:placetype":"venue"
},
  "geometry": {"coordinates":[-118.145696,33.89016],"type":"Point"}
}