{
  "type": "Feature",
  "properties": {
    "iso:country":"US",
    "sg:address":"11390 Ventura Blvd Ste 7",
    "sg:city":"Studio City",
    "sg:classifiers":[
        {
            "category":"Personal",
            "subcategory":"Tattoo Parlor",
            "type":"Services"
        }
    ],
    "sg:phone":"+1 661 373 3094",
    "sg:postcode":"91344",
    "sg:province":"CA",
    "sg:website":"www.atkinsontattoo.com",
    "wof:name":"Atkinson Tattoo",
    "wof:placetype":"venue"
},
  "geometry": {"coordinates":[-118.378867,34.139901],"type":"Point"}
}