{
  "type": "Feature",
  "properties": {
    "iso:country":"US",
    "sg:address":"10880 Cedar Ave",
    "sg:city":"Bloomington",
    "sg:classifiers":[
        {
            "category":"Shopping",
            "subcategory":"Used Merchandise",
            "type":"Retail Goods"
        }
    ],
    "sg:phone":"+1 909 877 9338",
    "sg:postcode":"92316",
    "sg:province":"CA",
    "sg:tags":[
        "shop",
        "thrift"
    ],
    "wof:name":"Samantha's Second Hand",
    "wof:placetype":"venue"
},
  "geometry": {"coordinates":[-117.396497,34.060124],"type":"Point"}
}