{
  "type": "Feature",
  "properties": {
    "addr:full":"7300 Scout Ave Bell Gardens CA 90201",
    "addr:housenumber":"7300",
    "addr:postcode":"90201",
    "addr:street":"Scout Ave",
    "iso:country":"US",
    "sg:address":"7300 Scout Ave",
    "sg:city":"Bell Gardens",
    "sg:classifiers":[
        {
            "category":"Food & Beverages",
            "subcategory":"Specialty",
            "type":"Retail Goods"
        }
    ],
    "sg:phone":"+1 562 806 8988",
    "sg:postcode":"90201",
    "sg:province":"CA",
    "sg:tags":[
        "spice"
    ],
    "sg:website":"www.lamexicanaspice.com",
    "wof:name":"LA Mexicana Spice & Candy",
    "wof:placetype":"venue"
},
  "geometry": {"coordinates":[-118.141704,33.963707],"type":"Point"}
}