{
  "type": "Feature",
  "properties": {
    "iso:country":"US",
    "sg:address":"1211 14th St",
    "sg:city":"Modesto",
    "sg:classifiers":[
        {
            "category":"Health Services",
            "subcategory":"Doctor",
            "type":"Services"
        },
        {
            "category":"Health Services",
            "subcategory":"Dentist",
            "type":"Services"
        }
    ],
    "sg:phone":"+1 209 577 6649",
    "sg:postcode":"95354",
    "sg:province":"CA",
    "sg:tags":[
        "surgeon",
        "oral",
        "pediatric"
    ],
    "wof:name":"Kinser Corbin DDS",
    "wof:placetype":"venue"
},
  "geometry": {"coordinates":[-120.99900100000001,37.645302],"type":"Point"}
}