{
  "type": "Feature",
  "properties": {
    "iso:country":"US",
    "sg:address":"744 S Broadway",
    "sg:city":"Los Angeles",
    "sg:classifiers":[
        {
            "category":"Shopping",
            "subcategory":"Jewelry",
            "type":"Retail Goods"
        }
    ],
    "sg:phone":"+1 213 627 5733",
    "sg:postcode":"90014",
    "sg:province":"CA",
    "sg:tags":[
        "jeweler"
    ],
    "wof:name":"LA Especial Jewelry",
    "wof:placetype":"venue"
},
  "geometry": {"coordinates":[-118.254148,34.044374],"type":"Point"}
}