{
  "type": "Feature",
  "properties": {
    "iso:country":"US",
    "sg:address":"25862 Commercenter Dr",
    "sg:city":"Lake Forest",
    "sg:classifiers":[
        {
            "category":"Wholesale",
            "subcategory":"Machinery & Supplies",
            "type":"Manufacturing & Wholesale Goods"
        },
        {
            "category":"Manufacturing",
            "subcategory":"Tools & Machinery",
            "type":"Manufacturing & Wholesale Goods"
        }
    ],
    "sg:phone":"+1 949 598 8822",
    "sg:postcode":"92630",
    "sg:province":"CA",
    "sg:tags":[
        "machine",
        "cutting",
        "industrial",
        "miscellaneous",
        "mfg"
    ],
    "sg:website":"www.shape-mate.com",
    "wof:name":"Ellison Educational Equip Inc",
    "wof:placetype":"venue"
},
  "geometry": {"coordinates":[-117.675639,33.664657],"type":"Point"}
}