{
  "type": "Feature",
  "properties": {
    "addr:full":"106 Coleridge St San Francisco CA 94110",
    "addr:housenumber":"106",
    "addr:postcode":"94110",
    "addr:street":"Coleridge St",
    "iso:country":"US",
    "sg:address":"106 Coleridge St",
    "sg:city":"San Francisco",
    "sg:classifiers":[
        {
            "category":"Building & Trades",
            "subcategory":"Construction",
            "type":"Services"
        }
    ],
    "sg:phone":"+1 415 647 1388",
    "sg:postcode":"94110",
    "sg:province":"CA",
    "sg:tags":[
        "contractor"
    ],
    "wof:name":"Clearheart",
    "wof:placetype":"venue"
},
  "geometry": {"coordinates":[-122.420384,37.742848],"type":"Point"}
}