{
  "type": "Feature",
  "properties": {
    "iso:country":"US",
    "sg:address":"16935 W Bernardo Dr",
    "sg:city":"San Diego",
    "sg:classifiers":[
        {
            "category":"Real Estate",
            "subcategory":"Real Estate Operator",
            "type":"Services"
        }
    ],
    "sg:phone":"+1 858 673 5602",
    "sg:postcode":"92127",
    "sg:province":"CA",
    "sg:tags":[
        "building",
        "parks"
    ],
    "wof:name":"Rancho Bernardo Courtyard",
    "wof:placetype":"venue"
},
  "geometry": {"coordinates":[-117.089285,33.012866],"type":"Point"}
}