{
  "type": "Feature",
  "properties": {
    "addr:full":"15129 Foothill Blvd Fontana CA 92335",
    "addr:housenumber":"15129",
    "addr:postcode":"92335",
    "addr:street":"Foothill Blvd",
    "iso:country":"US",
    "sg:address":"15129 Foothill Blvd",
    "sg:city":"Fontana",
    "sg:classifiers":[
        {
            "category":"Professional",
            "subcategory":"Lawyer & Legal Services",
            "type":"Services"
        }
    ],
    "sg:phone":"+1 909 355 3234",
    "sg:postcode":"92335",
    "sg:province":"CA",
    "sg:tags":[
        "attorney"
    ],
    "wof:name":"2nd Chance Credit",
    "wof:placetype":"venue"
},
  "geometry": {"coordinates":[-117.47170699999999,34.106422],"type":"Point"}
}