{
  "type": "Feature",
  "properties": {
    "iso:country":"US",
    "sg:address":"16250 E 14th St Ste A",
    "sg:city":"San Leandro",
    "sg:classifiers":[
        {
            "category":"Restaurant",
            "type":"Food & Drink"
        }
    ],
    "sg:phone":"+1 510 481 0951",
    "sg:postcode":"94578",
    "sg:province":"CA",
    "wof:name":"East Garden Restaurant",
    "wof:placetype":"venue"
},
  "geometry": {"coordinates":[-122.11599699999999,37.6964],"type":"Point"}
}