{
  "type": "Feature",
  "properties": {
    "addr:full":"180 Steuart St San Francisco CA 94105",
    "addr:housenumber":"180",
    "addr:postcode":"94105",
    "addr:street":"Steuart St",
    "iso:country":"US",
    "sg:address":"180 Steuart St",
    "sg:city":"San Francisco",
    "sg:classifiers":[
        {
            "category":"Government",
            "subcategory":"Post Office",
            "type":"Public Place"
        }
    ],
    "sg:phone":"+1 415 896 0762",
    "sg:postcode":"94105",
    "sg:province":"CA",
    "sg:website":"www.usps.com",
    "wof:name":"US Post Office - Rincon Finance Center",
    "wof:placetype":"venue"
},
  "geometry": {"coordinates":[-122.39196200000001,37.792254],"type":"Point"}
}