{
  "type": "Feature",
  "properties": {
    "addr:full":"7546 Lankershim Blvd North Hollywood CA 91605",
    "addr:housenumber":"7546",
    "addr:postcode":"91605",
    "addr:street":"Lankershim Blvd",
    "iso:country":"US",
    "sg:address":"7546 Lankershim Blvd",
    "sg:city":"North Hollywood",
    "sg:classifiers":[
        {
            "category":"Personal",
            "subcategory":"Beauty Salon",
            "type":"Services"
        }
    ],
    "sg:phone":"+1 818 982 6522",
    "sg:postcode":"91605",
    "sg:province":"CA",
    "wof:name":"Anna's Beauty Salon",
    "wof:placetype":"venue"
},
  "geometry": {"coordinates":[-118.387704,34.207607],"type":"Point"}
}