{
  "type": "Feature",
  "properties": {
    "addr:full":"354 S Spring St Ste 213 Los Angeles CA 90013",
    "addr:housenumber":"354",
    "addr:postcode":"90013",
    "addr:street":"S Spring St Ste 213",
    "iso:country":"US",
    "sg:address":"354 S Spring St Ste 213",
    "sg:city":"Los Angeles",
    "sg:classifiers":[
        {
            "category":"Professional",
            "subcategory":"Lawyer & Legal Services",
            "type":"Services"
        }
    ],
    "sg:phone":"+1 213 626 3640",
    "sg:postcode":"90013",
    "sg:province":"CA",
    "wof:name":"Ortega Edward R Law Offices of",
    "wof:placetype":"venue"
},
  "geometry": {"coordinates":[-118.248001,34.0494],"type":"Point"}
}