{
  "type": "Feature",
  "properties": {
    "addr:full":"16227 Avenue 17 1/2 Madera CA 93637",
    "addr:housenumber":"16227;1 / 2",
    "addr:postcode":"93637",
    "addr:street":"Avenue 17",
    "iso:country":"US",
    "sg:address":"16227 Avenue 17 1/2",
    "sg:city":"Madera",
    "sg:classifiers":[
        {
            "category":"Building & Trades",
            "subcategory":"Landscaping Services",
            "type":"Services"
        }
    ],
    "sg:phone":"+1 559 674 3801",
    "sg:postcode":"93637",
    "sg:province":"CA",
    "sg:tags":[
        "arborist",
        "tree"
    ],
    "wof:name":"Dixieland Orchards",
    "wof:placetype":"venue"
},
  "geometry": {"coordinates":[-120.25205,37.003713],"type":"Point"}
}