{
  "type": "Feature",
  "properties": {
    "addr:full":"1470 E Highland Ave San Bernardino CA 92404",
    "addr:housenumber":"1470",
    "addr:postcode":"92404",
    "addr:street":"E Highland Ave",
    "iso:country":"US",
    "sg:address":"1470 E Highland Ave",
    "sg:city":"San Bernardino",
    "sg:classifiers":[
        {
            "category":"Shopping",
            "subcategory":"Tobacco",
            "type":"Retail Goods"
        }
    ],
    "sg:phone":"+1 909 883 7740",
    "sg:postcode":"92404",
    "sg:province":"CA",
    "sg:tags":[
        "cigarette",
        "cigar",
        "dealer"
    ],
    "wof:name":"Cigarettes & More 2",
    "wof:placetype":"venue"
},
  "geometry": {"coordinates":[-117.253857,34.135937],"type":"Point"}
}