{
  "type": "Feature",
  "properties": {
    "addr:full":"9012 Venice Boulevard Culver City CA 90232",
    "addr:housenumber":"9012",
    "addr:postcode":"90232",
    "addr:street":"Venice Boulevard",
    "iso:country":"US",
    "sg:address":"9012 Venice Boulevard",
    "sg:city":"Culver City",
    "sg:classifiers":[
        {
            "category":"Professional",
            "subcategory":"Computer Services",
            "type":"Services"
        }
    ],
    "sg:phone":"+1 310 287 1579",
    "sg:postcode":"90232",
    "sg:province":"CA",
    "sg:tags":[
        "repair"
    ],
    "wof:name":"Tech Quest",
    "wof:placetype":"venue"
},
  "geometry": {"coordinates":[-118.39039200000001,34.028237],"type":"Point"}
}