{
  "type": "Feature",
  "properties": {
    "addr:full":"1715 E Belmont Ave Fresno CA 93701",
    "addr:housenumber":"1715",
    "addr:postcode":"93701",
    "addr:street":"E Belmont Ave",
    "iso:country":"US",
    "sg:address":"1715 E Belmont Ave",
    "sg:city":"Fresno",
    "sg:classifiers":[
        {
            "category":"Shopping",
            "subcategory":"Discount & Variety Stores",
            "type":"Retail Goods"
        }
    ],
    "sg:phone":"+1 559 233 8309",
    "sg:postcode":"93701",
    "sg:province":"CA",
    "sg:tags":[
        "salvage",
        "surplus",
        "merchandise",
        "government"
    ],
    "wof:name":"Army Surplus Sales",
    "wof:placetype":"venue"
},
  "geometry": {"coordinates":[-119.79052799999999,36.750437],"type":"Point"}
}