{
  "type": "Feature",
  "properties": {
    "iso:country":"US",
    "sg:address":"4383 Tujunga Ave Ste C",
    "sg:city":"Studio City",
    "sg:classifiers":[
        {
            "category":"Personal",
            "subcategory":"Beauty Salon",
            "type":"Services"
        }
    ],
    "sg:phone":"+1 818 505 8939",
    "sg:postcode":"91604",
    "sg:province":"CA",
    "sg:tags":[
        "hair"
    ],
    "wof:name":"Luna Hair Studio",
    "wof:placetype":"venue"
},
  "geometry": {"coordinates":[-118.37931500000001,34.149781],"type":"Point"}
}