{
  "type": "Feature",
  "properties": {
    "addr:full":"145 Harvest St Salinas CA 93901",
    "addr:housenumber":"145",
    "addr:postcode":"93901",
    "addr:street":"Harvest St",
    "iso:country":"US",
    "sg:address":"145 Harvest St",
    "sg:city":"Salinas",
    "sg:classifiers":[
        {
            "category":"Building & Trades",
            "subcategory":"Landscaping Services",
            "type":"Services"
        }
    ],
    "sg:phone":"+1 831 758 1798",
    "sg:postcode":"93901",
    "sg:province":"CA",
    "sg:tags":[
        "gardener"
    ],
    "wof:name":"Gone Native Gardening Service",
    "wof:placetype":"venue"
},
  "geometry": {"coordinates":[-121.65181800000001,36.66853],"type":"Point"}
}