{
  "type": "Feature",
  "properties": {
    "iso:country":"US",
    "sg:address":"8721 S Main St",
    "sg:city":"San Joaquin",
    "sg:classifiers":[
        {
            "category":"Shopping",
            "subcategory":"Gifts & Souvenirs",
            "type":"Retail Goods"
        }
    ],
    "sg:phone":"+1 559 693 4030",
    "sg:postcode":"93660",
    "sg:province":"CA",
    "sg:tags":[
        "shop"
    ],
    "wof:name":"Karylulu's Gift Shop",
    "wof:placetype":"venue"
},
  "geometry": {"coordinates":[-120.18630400000001,36.607795],"type":"Point"}
}