{
  "type": "Feature",
  "properties": {
    "addr:full":"11100 Collett Ave Riverside CA 92505",
    "addr:housenumber":"11100",
    "addr:postcode":"92505",
    "addr:street":"Collett Ave",
    "iso:country":"US",
    "sg:address":"11100 Collett Ave",
    "sg:city":"Riverside",
    "sg:classifiers":[
        {
            "category":"Social Services",
            "subcategory":"Child Care",
            "type":"Services"
        }
    ],
    "sg:phone":"+1 951 688 1313",
    "sg:postcode":"92505",
    "sg:province":"CA",
    "wof:name":"LA Petite Academy",
    "wof:placetype":"venue"
},
  "geometry": {"coordinates":[-117.48581299999999,33.91035],"type":"Point"}
}