{
  "type": "Feature",
  "properties": {
    "iso:country":"US",
    "sg:address":"4600 Alum Rock Avenue Suite 7",
    "sg:city":"San Jose",
    "sg:classifiers":[
        {
            "category":"Personal",
            "subcategory":"Massage",
            "type":"Services"
        }
    ],
    "sg:phone":"+1 408 937 0850",
    "sg:postcode":"95127",
    "sg:province":"CA",
    "wof:name":"Elegant Body Care",
    "wof:placetype":"venue"
},
  "geometry": {"coordinates":[-121.824399,37.37064],"type":"Point"}
}