{
  "type": "Feature",
  "properties": {
    "addr:full":"12600 S Western Ave Los Angeles CA 90047",
    "addr:housenumber":"12600",
    "addr:postcode":"90047",
    "addr:street":"S Western Ave",
    "iso:country":"US",
    "sg:address":"12600 S Western Ave",
    "sg:city":"Los Angeles",
    "sg:phone":"+1 213 892 7466",
    "sg:postcode":"90047",
    "sg:province":"CA",
    "sg:tags":[
        "gas"
    ],
    "wof:name":"No Main List",
    "wof:placetype":"venue"
},
  "geometry": {"coordinates":[-118.309006,33.91741],"type":"Point"}
}