{
  "type": "Feature",
  "properties": {
    "iso:country":"US",
    "sg:address":"5967 W 3rd St",
    "sg:city":"Los Angeles",
    "sg:classifiers":[
        {
            "category":"Government",
            "subcategory":"Office",
            "type":"Public Place"
        }
    ],
    "sg:phone":"+1 323 525 0166",
    "sg:postcode":"90036",
    "sg:province":"CA",
    "sg:tags":[
        "village"
    ],
    "wof:name":"Barbara Yaroslavsky-City Cncl",
    "wof:placetype":"venue"
},
  "geometry": {"coordinates":[-118.350703,34.069913],"type":"Point"}
}