{
  "type": "Feature",
  "properties": {
    "addr:full":"912 Cassou Rd San Marcos CA 92069",
    "addr:housenumber":"912",
    "addr:postcode":"92069",
    "addr:street":"Cassou Rd",
    "iso:country":"US",
    "sg:address":"912 Cassou Rd",
    "sg:city":"San Marcos",
    "sg:classifiers":[
        {
            "category":"Professional",
            "type":"Services"
        },
        {
            "category":"Building & Trades",
            "subcategory":"Pest Control",
            "type":"Services"
        }
    ],
    "sg:phone":"+1 760 744 9233",
    "sg:postcode":"92069",
    "sg:province":"CA",
    "wof:name":"Mary's Goodsnails",
    "wof:placetype":"venue"
},
  "geometry": {"coordinates":[-117.17047100000001,33.179424],"type":"Point"}
}