{
  "type": "Feature",
  "properties": {
    "addr:full":"103 W Inyokern Rd Ridgecrest CA 93555",
    "addr:housenumber":"103",
    "addr:postcode":"93555",
    "addr:street":"W Inyokern Rd",
    "iso:country":"US",
    "sg:address":"103 W Inyokern Rd",
    "sg:city":"Ridgecrest",
    "sg:classifiers":[
        {
            "category":"Autos & Motor Vehicles",
            "subcategory":"Automobile Sales",
            "type":"Retail Goods"
        }
    ],
    "sg:phone":"+1 760 446 4558",
    "sg:postcode":"93555",
    "sg:province":"CA",
    "sg:tags":[
        "used",
        "truck",
        "transport",
        "trailer"
    ],
    "wof:name":"American Loan Masters Inc",
    "wof:placetype":"venue"
},
  "geometry": {"coordinates":[-117.669871,35.651631],"type":"Point"}
}