{
  "type": "Feature",
  "properties": {
    "addr:full":"2301 Lawrence St Ceres CA 95307",
    "addr:housenumber":"2301",
    "addr:postcode":"95307",
    "addr:street":"Lawrence St",
    "iso:country":"US",
    "sg:address":"2301 Lawrence St",
    "sg:city":"Ceres",
    "sg:classifiers":[
        {
            "category":"Autos & Motor Vehicles",
            "subcategory":"Fuel & Gas Station",
            "type":"Retail Goods"
        }
    ],
    "sg:phone":"+1 209 537 2079",
    "sg:postcode":"95307",
    "sg:province":"CA",
    "wof:name":"Jack's Texaco Auto Service",
    "wof:placetype":"venue"
},
  "geometry": {"coordinates":[-120.954002,37.590199],"type":"Point"}
}