{
  "type": "Feature",
  "properties": {
    "iso:country":"US",
    "sg:address":"2005 N Blackstone Ave",
    "sg:city":"Fresno",
    "sg:classifiers":[
        {
            "category":"Restaurant",
            "type":"Food & Drink"
        }
    ],
    "sg:menulink":"http://www.allmenus.com/ca/fresno/174392-wendys/menu/",
    "sg:phone":"+1 559 222 1414",
    "sg:postcode":"93703",
    "sg:province":"CA",
    "sg:tags":[
        "burger",
        "american",
        "soup"
    ],
    "wof:name":"Wendy's",
    "wof:placetype":"venue"
},
  "geometry": {"coordinates":[-119.790809,36.769204],"type":"Point"}
}