{
  "type": "Feature",
  "properties": {
    "addr:full":"3941 San Dimas St Bakersfield CA 93301",
    "addr:housenumber":"3941",
    "addr:postcode":"93301",
    "addr:street":"San Dimas St",
    "iso:country":"US",
    "sg:address":"3941 San Dimas St",
    "sg:city":"Bakersfield",
    "sg:classifiers":[
        {
            "category":"Health Services",
            "subcategory":"Doctor",
            "type":"Services"
        }
    ],
    "sg:phone":"+1 661 322 8466",
    "sg:postcode":"93301",
    "sg:province":"CA",
    "sg:tags":[
        "physician",
        "surgeon"
    ],
    "wof:name":"Anil Mehta Inc",
    "wof:placetype":"venue"
},
  "geometry": {"coordinates":[-119.008262,35.394855],"type":"Point"}
}