{
  "type": "Feature",
  "properties": {
    "iso:country":"US",
    "sg:address":"2110 de la Vina St",
    "sg:city":"Santa Barbara",
    "sg:classifiers":[
        {
            "category":"Building & Trades",
            "subcategory":"Construction",
            "type":"Services"
        }
    ],
    "sg:phone":"+1 805 898 2010",
    "sg:postcode":"93105",
    "sg:province":"CA",
    "sg:tags":[
        "repairing",
        "remodeling",
        "contractor"
    ],
    "wof:name":"Deck Creations",
    "wof:placetype":"venue"
},
  "geometry": {"coordinates":[-119.71925,34.430593],"type":"Point"}
}