{
  "type": "Feature",
  "properties": {
    "addr:full":"20580 8th St E Sonoma CA 95487",
    "addr:housenumber":"20580",
    "addr:postcode":"95487",
    "addr:street":"8Th St E",
    "iso:country":"US",
    "sg:address":"20580 8th St E",
    "sg:city":"Sonoma",
    "sg:classifiers":[
        {
            "category":"Real Estate",
            "subcategory":"Real Estate Agent",
            "type":"Services"
        }
    ],
    "sg:phone":"+1 707 939 3106",
    "sg:postcode":"95487",
    "sg:province":"CA",
    "wof:name":"Groskops Logistics",
    "wof:placetype":"venue"
},
  "geometry": {"coordinates":[-122.438785,38.270196],"type":"Point"}
}