{
  "type": "Feature",
  "properties": {
    "iso:country":"US",
    "sg:address":"3170 El Camino Real",
    "sg:city":"Santa Clara",
    "sg:classifiers":[
        {
            "category":"Retail",
            "subcategory":"Auto Repair",
            "type":"Services"
        }
    ],
    "sg:phone":"+1 408 984 5025",
    "sg:postcode":"95051",
    "sg:province":"CA",
    "sg:tags":[
        "body",
        "shop"
    ],
    "sg:website":"www.jozosforeigncar.com",
    "wof:name":"Jozo's Foreign Auto Specialty BMW & M. Benz",
    "wof:placetype":"venue"
},
  "geometry": {"coordinates":[-121.98359000000001,37.351728],"type":"Point"}
}