{
  "type": "Feature",
  "properties": {
    "addr:full":"915 Howard Avenue Burlingame CA 94010",
    "addr:housenumber":"915",
    "addr:postcode":"94010",
    "addr:street":"Howard Avenue",
    "iso:country":"US",
    "sg:address":"915 Howard Avenue",
    "sg:city":"Burlingame",
    "sg:classifiers":[
        {
            "category":"Shopping",
            "subcategory":"Antiques",
            "type":"Retail Goods"
        }
    ],
    "sg:phone":"+1 650 348 0088",
    "sg:postcode":"94010",
    "sg:province":"CA",
    "wof:name":"Harvey Antiques",
    "wof:placetype":"venue"
},
  "geometry": {"coordinates":[-122.341498,37.580026],"type":"Point"}
}