{
  "type": "Feature",
  "properties": {
    "addr:full":"1164 Obispo St Guadalupe CA 93434",
    "addr:housenumber":"1164",
    "addr:postcode":"93434",
    "addr:street":"Obispo St",
    "iso:country":"US",
    "sg:address":"1164 Obispo St",
    "sg:city":"Guadalupe",
    "sg:classifiers":[
        {
            "category":"Organizations",
            "subcategory":"Religious Organization",
            "type":"Services"
        }
    ],
    "sg:phone":"+1 805 343 2181",
    "sg:postcode":"93434",
    "sg:province":"CA",
    "sg:tags":[
        "church"
    ],
    "wof:name":"Our Lady Of Guadalupe Church",
    "wof:placetype":"venue"
},
  "geometry": {"coordinates":[-120.56799700000001,34.971641],"type":"Point"}
}