{
  "type": "Feature",
  "properties": {
    "addr:full":"12100 Wilshire Blvd Los Angeles CA 90025",
    "addr:housenumber":"12100",
    "addr:postcode":"90025",
    "addr:street":"Wilshire Blvd",
    "iso:country":"US",
    "sg:address":"12100 Wilshire Blvd",
    "sg:city":"Los Angeles",
    "sg:classifiers":[
        {
            "category":"Professional",
            "subcategory":"Lawyer & Legal Services",
            "type":"Services"
        }
    ],
    "sg:phone":"+1 310 859 9009",
    "sg:postcode":"90025",
    "sg:province":"CA",
    "sg:tags":[
        "attorney"
    ],
    "wof:name":"Homa Molayem Law Corp",
    "wof:placetype":"venue"
},
  "geometry": {"coordinates":[-118.46831,34.043422],"type":"Point"}
}