{
  "type": "Feature",
  "properties": {
    "iso:country":"US",
    "sg:address":"The Culver Studios 9336 Washington Blvd",
    "sg:city":"Culver City",
    "sg:classifiers":[
        {
            "category":"Organizations",
            "subcategory":"Non-profit Organization",
            "type":"Services"
        }
    ],
    "sg:postcode":"90232",
    "sg:province":"CA",
    "sg:tags":[
        "service/non-profit",
        "community"
    ],
    "sg:website":"www.alexslemonade.org/campaign/l...",
    "wof:name":"LA Loves Alex's Lemonade",
    "wof:placetype":"venue"
},
  "geometry": {"coordinates":[-118.39052700000001,34.022716],"type":"Point"}
}