{
  "type": "Feature",
  "properties": {
    "addr:full":"601 N E St San Bernardino CA 92410",
    "addr:housenumber":"601",
    "addr:postcode":"92410",
    "addr:street":"N E St",
    "iso:country":"US",
    "sg:address":"601 N E St",
    "sg:city":"San Bernardino",
    "sg:classifiers":[
        {
            "category":"Government",
            "subcategory":"Office",
            "type":"Public Place"
        }
    ],
    "sg:phone":"+1 909 386 2784",
    "sg:postcode":"92410",
    "sg:province":"CA",
    "sg:tags":[
        "county",
        "education",
        "supervisor"
    ],
    "wof:name":"San Bernadino County Superinte",
    "wof:placetype":"venue"
},
  "geometry": {"coordinates":[-117.29416399999999,34.111128],"type":"Point"}
}