{
  "type": "Feature",
  "properties": {
    "addr:full":"2420 K Street Sacramento CA 95816",
    "addr:housenumber":"2420",
    "addr:postcode":"95816",
    "addr:street":"K Street",
    "iso:country":"US",
    "sg:address":"2420 K Street",
    "sg:city":"Sacramento",
    "sg:classifiers":[
        {
            "category":"Real Estate",
            "subcategory":"Architect",
            "type":"Services"
        }
    ],
    "sg:phone":"+1 916 444 1480",
    "sg:postcode":"95816",
    "sg:province":"CA",
    "wof:name":"Reyes Rizalito",
    "wof:placetype":"venue"
},
  "geometry": {"coordinates":[-121.474729,38.574101],"type":"Point"}
}