{
  "type": "Feature",
  "properties": {
    "addr:full":"6070 Johnson Dr Ste A Pleasanton CA 94588",
    "addr:housenumber":"6070",
    "addr:postcode":"94588",
    "addr:street":"Johnson Dr Ste A",
    "iso:country":"US",
    "sg:address":"6070 Johnson Dr Ste A",
    "sg:city":"Pleasanton",
    "sg:classifiers":[
        {
            "category":"Communications",
            "subcategory":"News Services",
            "type":"Services"
        },
        {
            "category":"Transit Center",
            "subcategory":"Freight",
            "type":"Transportation"
        },
        {
            "category":"Professional",
            "subcategory":"Business Services",
            "type":"Services"
        },
        {
            "category":"Professional",
            "subcategory":"Printing & Photocopies",
            "type":"Services"
        }
    ],
    "sg:phone":"+1 925 416 0494",
    "sg:postcode":"94588",
    "sg:province":"CA",
    "sg:tags":[
        "cargo",
        "fax",
        "transparency",
        "package",
        "color",
        "express",
        "duplicating",
        "shipping",
        "air",
        "copying",
        "print",
        "mail",
        "photographic"
    ],
    "sg:website":"http://www.kinkos.com",
    "wof:name":"Fedex Kinko's",
    "wof:placetype":"venue"
},
  "geometry": {"coordinates":[-121.90814,37.700608],"type":"Point"}
}