{
  "type": "Feature",
  "properties": {
    "addr:full":"555 Tully Rd San Jose CA 95111",
    "addr:housenumber":"555",
    "addr:postcode":"95111",
    "addr:street":"Tully Rd",
    "iso:country":"US",
    "sg:address":"555 Tully Rd",
    "sg:city":"San Jose",
    "sg:classifiers":[
        {
            "category":"Taxi",
            "type":"Transportation"
        }
    ],
    "sg:phone":"+1 408 971 1111",
    "sg:postcode":"95111",
    "sg:province":"CA",
    "sg:tags":[
        "operator",
        "taxicab"
    ],
    "wof:name":"United Taxicab Corporation",
    "wof:placetype":"venue"
},
  "geometry": {"coordinates":[-121.849603,37.306587],"type":"Point"}
}