{
  "type": "Feature",
  "properties": {
    "iso:country":"US",
    "sg:address":"22958 el Toro Rd",
    "sg:city":"Lake Forest",
    "sg:classifiers":[
        {
            "category":"Personal",
            "subcategory":"Beauty Salon",
            "type":"Services"
        }
    ],
    "sg:phone":"+1 949 380 4885",
    "sg:postcode":"92630",
    "sg:province":"CA",
    "wof:name":"Mark & Mike Estrada Hair Dsgn",
    "wof:placetype":"venue"
},
  "geometry": {"coordinates":[-117.628603,33.669593],"type":"Point"}
}