{
  "type": "Feature",
  "properties": {
    "iso:country":"US",
    "sg:address":"1166 Broadway",
    "sg:city":"Placerville",
    "sg:classifiers":[
        {
            "category":"Professional",
            "subcategory":"Lawyer & Legal Services",
            "type":"Services"
        }
    ],
    "sg:phone":"+1 530 622 1048",
    "sg:postcode":"95667",
    "sg:province":"CA",
    "sg:tags":[
        "attorney",
        "accident",
        "personal",
        "automobile",
        "damage",
        "liability",
        "injury",
        "property",
        "product",
        "law"
    ],
    "sg:website":"http://www.DanielJWhite-Attorney.com",
    "wof:name":"Law Offices of Daniel J. White",
    "wof:placetype":"venue"
},
  "geometry": {"coordinates":[-120.78886900000001,38.731005],"type":"Point"}
}