{
  "type": "Feature",
  "properties": {
    "addr:full":"304 N Pepper Ave Rialto CA 92376",
    "addr:housenumber":"304",
    "addr:postcode":"92376",
    "addr:street":"N Pepper Ave",
    "iso:country":"US",
    "sg:address":"304 N Pepper Ave",
    "sg:city":"Rialto",
    "sg:classifiers":[
        {
            "category":"Social Services",
            "subcategory":"Child Care",
            "type":"Services"
        }
    ],
    "sg:phone":"+1 909 874 0471",
    "sg:postcode":"92376",
    "sg:province":"CA",
    "sg:tags":[
        "kindergarten",
        "academic",
        "school"
    ],
    "wof:name":"Peppercreek School",
    "wof:placetype":"venue"
},
  "geometry": {"coordinates":[-117.353002,34.104913],"type":"Point"}
}