{
  "type": "Feature",
  "properties": {
    "iso:country":"US",
    "sg:address":"6534 Ben Ave",
    "sg:city":"North Hollywood",
    "sg:classifiers":[
        {
            "category":"Professional",
            "type":"Services"
        }
    ],
    "sg:phone":"+1 818 760 7899",
    "sg:postcode":"91606",
    "sg:province":"CA",
    "wof:name":"Angeles Antiquers Inc",
    "wof:placetype":"venue"
},
  "geometry": {"coordinates":[-118.394232,34.189675],"type":"Point"}
}