{
  "type": "Feature",
  "properties": {
    "addr:full":"2339 3rd Street 3R - Suite 51 San Francisco CA 94107",
    "addr:housenumber":"2339;3r suite 51",
    "addr:postcode":"94107",
    "addr:street":"3Rd Street",
    "iso:country":"US",
    "sg:address":"2339 3rd Street 3R - Suite 51",
    "sg:city":"San Francisco",
    "sg:classifiers":[
        {
            "category":"Arts & Performance",
            "subcategory":"Arts Center",
            "type":"Entertainment"
        }
    ],
    "sg:phone":"+1 415 824 4000",
    "sg:postcode":"94107",
    "sg:province":"CA",
    "sg:website":"www.apostrophe.net",
    "wof:name":"Apostrophe",
    "wof:placetype":"venue"
},
  "geometry": {"coordinates":[-122.388352,37.759531],"type":"Point"}
}