{
  "type": "Feature",
  "properties": {
    "addr:full":"504 Broadway St San Francisco CA 94133",
    "addr:housenumber":"504",
    "addr:postcode":"94133",
    "addr:street":"Broadway St",
    "iso:country":"US",
    "sg:address":"504 Broadway St",
    "sg:city":"San Francisco",
    "sg:classifiers":[
        {
            "category":"Restaurant",
            "type":"Food & Drink"
        }
    ],
    "sg:phone":"+1 415 982 6223",
    "sg:postcode":"94133",
    "sg:province":"CA",
    "sg:website":"www.enricossidewalkcafe.com",
    "wof:name":"Paradox Cafe",
    "wof:placetype":"venue"
},
  "geometry": {"coordinates":[-122.406188,37.798003],"type":"Point"}
}