{
  "type": "Feature",
  "properties": {
    "iso:country":"US",
    "sg:address":"1201 Normandy Dr",
    "sg:city":"Modesto",
    "sg:classifiers":[
        {
            "category":"Restaurant",
            "type":"Food & Drink"
        }
    ],
    "sg:phone":"+1 209 525 9992",
    "sg:postcode":"95351",
    "sg:province":"CA",
    "sg:tags":[
        "eating"
    ],
    "wof:name":"Dynamite Dogs",
    "wof:placetype":"venue"
},
  "geometry": {"coordinates":[-121.025153,37.624573],"type":"Point"}
}