{
  "type": "Feature",
  "properties": {
    "addr:full":"912 Harbour Way S Richmond CA 94804",
    "addr:housenumber":"912",
    "addr:postcode":"94804",
    "addr:street":"Harbour Way",
    "iso:country":"US",
    "sg:address":"912 Harbour Way S",
    "sg:city":"Richmond",
    "sg:classifiers":[
        {
            "category":"Building & Trades",
            "subcategory":"Construction",
            "type":"Services"
        }
    ],
    "sg:phone":"+1 510 233 6552",
    "sg:postcode":"94804",
    "sg:province":"CA",
    "sg:tags":[
        "demolition",
        "contractor"
    ],
    "sg:website":"www.plantreclamation.com",
    "wof:name":"Plant Reclamation",
    "wof:placetype":"venue"
},
  "geometry": {"coordinates":[-122.360085,37.919443],"type":"Point"}
}