{
  "type": "Feature",
  "properties": {
    "addr:full":"6915 32nd St North Highlands CA 95660",
    "addr:housenumber":"6915",
    "addr:postcode":"95660",
    "addr:street":"32Nd St",
    "iso:country":"US",
    "sg:address":"6915 32nd St",
    "sg:city":"North Highlands",
    "sg:classifiers":[
        {
            "category":"Retail",
            "subcategory":"Storage",
            "type":"Services"
        }
    ],
    "sg:phone":"+1 916 331 9900",
    "sg:postcode":"95660",
    "sg:province":"CA",
    "sg:tags":[
        "self"
    ],
    "sg:website":"www.a-allministorage.com",
    "wof:name":"A-All Mini Storage",
    "wof:placetype":"venue"
},
  "geometry": {"coordinates":[-121.391998,38.694199],"type":"Point"}
}