{
  "type": "Feature",
  "properties": {
    "addr:full":"4741 Florence Avenue Bell CA 90201",
    "addr:housenumber":"4741",
    "addr:postcode":"90201",
    "addr:street":"Florence Avenue",
    "iso:country":"US",
    "sg:address":"4741 Florence Avenue",
    "sg:city":"Bell",
    "sg:classifiers":[
        {
            "category":"Food & Beverages",
            "subcategory":"Liquor & Beverages",
            "type":"Retail Goods"
        }
    ],
    "sg:phone":"+1 323 562 1770",
    "sg:postcode":"90201",
    "sg:province":"CA",
    "sg:tags":[
        "beer",
        "spirit",
        "wine"
    ],
    "wof:name":"Youngs Liquor & Market",
    "wof:placetype":"venue"
},
  "geometry": {"coordinates":[-118.18234699999999,33.969844],"type":"Point"}
}