{
  "type": "Feature",
  "properties": {
    "iso:country":"US",
    "sg:address":"22935 Ventura Blvd",
    "sg:city":"Woodland Hills",
    "sg:classifiers":[
        {
            "category":"Professional",
            "subcategory":"Accounting & Tax Preparation",
            "type":"Services"
        }
    ],
    "sg:phone":"+1 818 225 9700",
    "sg:postcode":"91364",
    "sg:province":"CA",
    "sg:tags":[
        "bookkeeping",
        "general"
    ],
    "wof:name":"ABS Accounting & Business",
    "wof:placetype":"venue"
},
  "geometry": {"coordinates":[-118.626879,34.164986],"type":"Point"}
}