{
  "type": "Feature",
  "properties": {
    "iso:country":"US",
    "sg:address":"11822 Jonny Ln",
    "sg:city":"San Diego",
    "sg:classifiers":[
        {
            "category":"Food & Beverages",
            "subcategory":"Specialty",
            "type":"Retail Goods"
        }
    ],
    "sg:phone":"+1 858 271 5329",
    "sg:postcode":"92126",
    "sg:province":"CA",
    "sg:website":"www.ecochef.com",
    "wof:name":"Natural Gourmet Earth Friendly",
    "wof:placetype":"venue"
},
  "geometry": {"coordinates":[-117.143702,32.932465],"type":"Point"}
}