{
  "type": "Feature",
  "properties": {
    "addr:full":"550 S Hope St Los Angeles CA 90071",
    "addr:housenumber":"550",
    "addr:postcode":"90071",
    "addr:street":"S Hope St",
    "iso:country":"US",
    "sg:address":"550 S Hope St",
    "sg:city":"Los Angeles",
    "sg:classifiers":[
        {
            "category":"Organizations",
            "subcategory":"Membership Organization",
            "type":"Services"
        }
    ],
    "sg:phone":"+1 213 680 3833",
    "sg:postcode":"90071",
    "sg:province":"CA",
    "sg:website":"www.wmkeck.org",
    "wof:name":"W M Keck Foundation",
    "wof:placetype":"venue"
},
  "geometry": {"coordinates":[-118.256001,34.049759],"type":"Point"}
}