{
  "type": "Feature",
  "properties": {
    "addr:full":"808 N Spring St Los Angeles CA 90012",
    "addr:housenumber":"808",
    "addr:postcode":"90012",
    "addr:street":"N Spring St",
    "iso:country":"US",
    "sg:address":"808 N Spring St",
    "sg:city":"Los Angeles",
    "sg:classifiers":[
        {
            "category":"Arts & Performance",
            "subcategory":"Theater",
            "type":"Entertainment"
        }
    ],
    "sg:phone":"+1 213 625 0228",
    "sg:postcode":"90012",
    "sg:province":"CA",
    "sg:tags":[
        "karaoke"
    ],
    "wof:name":"DTS Karaoke",
    "wof:placetype":"venue"
},
  "geometry": {"coordinates":[-118.23634,34.062881],"type":"Point"}
}