{
  "type": "Feature",
  "properties": {
    "addr:full":"7451 Foothills Blvd Roseville CA 95747",
    "addr:housenumber":"7451",
    "addr:postcode":"95747",
    "addr:street":"Foothills Blvd",
    "iso:country":"US",
    "sg:address":"7451 Foothills Blvd",
    "sg:city":"Roseville",
    "sg:classifiers":[
        {
            "category":"Coffee & Tea",
            "type":"Food & Drink"
        }
    ],
    "sg:menulink":"http://www.allmenus.com/ca/roseville/230717-its-a-grind-coffee-house/menu/",
    "sg:phone":"+1 916 782 4746",
    "sg:postcode":"95747",
    "sg:province":"CA",
    "sg:tags":[
        "american"
    ],
    "wof:name":"It's A Grind Coffee House",
    "wof:placetype":"venue"
},
  "geometry": {"coordinates":[-121.31277900000001,38.77134],"type":"Point"}
}