{
  "type": "Feature",
  "properties": {
    "addr:full":"401 Westacre Rd Ofc West Sacramento CA 95691",
    "addr:housenumber":"401",
    "addr:postcode":"95691",
    "addr:street":"Westacre Rd",
    "iso:country":"US",
    "sg:address":"401 Westacre Rd Ofc",
    "sg:city":"West Sacramento",
    "sg:classifiers":[
        {
            "category":"Real Estate",
            "subcategory":"Real Estate Operator",
            "type":"Services"
        }
    ],
    "sg:phone":"+1 916 371 3939",
    "sg:postcode":"95691",
    "sg:province":"CA",
    "sg:tags":[
        "apartment"
    ],
    "wof:name":"Meadowbrook Apartments",
    "wof:placetype":"venue"
},
  "geometry": {"coordinates":[-121.531998,38.586102],"type":"Point"}
}