{
  "type": "Feature",
  "properties": {
    "addr:full":"8340 Beverly Boulevard Los Angeles CA 90048",
    "addr:housenumber":"8340",
    "addr:postcode":"90048",
    "addr:street":"Beverly Boulevard",
    "iso:country":"US",
    "sg:address":"8340 Beverly Boulevard",
    "sg:city":"Los Angeles",
    "sg:classifiers":[
        {
            "category":"Personal",
            "type":"Services"
        }
    ],
    "sg:phone":"+1 323 653 8006",
    "sg:postcode":"90048",
    "sg:province":"CA",
    "sg:tags":[
        "sewing",
        "alteration"
    ],
    "wof:name":"Balian M F B Tlr",
    "wof:placetype":"venue"
},
  "geometry": {"coordinates":[-118.37146,34.07616],"type":"Point"}
}