{
  "type": "Feature",
  "properties": {
    "iso:country":"US",
    "sg:address":"1390 Laurel Ave",
    "sg:city":"Ukiah",
    "sg:classifiers":[
        {
            "category":"Organizations",
            "subcategory":"Religious Organization",
            "type":"Services"
        }
    ],
    "sg:phone":"+1 707 462 5455",
    "sg:postcode":"95482",
    "sg:province":"CA",
    "sg:tags":[
        "church"
    ],
    "wof:name":"Seventh-Day Adventist Church",
    "wof:placetype":"venue"
},
  "geometry": {"coordinates":[-123.211555,39.129164],"type":"Point"}
}