{
  "type": "Feature",
  "properties": {
    "iso:country":"US",
    "sg:address":"16320 Tish-A-Tang Rd",
    "sg:city":"Lower Lake",
    "sg:classifiers":[
        {
            "category":"Health Services",
            "subcategory":"Chiropractor",
            "type":"Services"
        }
    ],
    "sg:phone":"+1 707 994 5204",
    "sg:postcode":"95457",
    "sg:province":"CA",
    "wof:name":"Southshore Chiropractic Group",
    "wof:placetype":"venue"
},
  "geometry": {"coordinates":[-122.60760500000001,38.922622],"type":"Point"}
}