{
  "type": "Feature",
  "properties": {
    "addr:full":"120 Independence Cir Chico CA 95973",
    "addr:housenumber":"120",
    "addr:postcode":"95973",
    "addr:street":"Independence Cir",
    "iso:country":"US",
    "sg:address":"120 Independence Cir",
    "sg:city":"Chico",
    "sg:classifiers":[
        {
            "category":"Banks & Credit Unions",
            "subcategory":"Investment Brokerage",
            "type":"Services"
        }
    ],
    "sg:phone":"+1 530 345 1186",
    "sg:postcode":"95973",
    "sg:province":"CA",
    "sg:tags":[
        "consultant",
        "planning",
        "financial"
    ],
    "sg:website":"www.cwade.com",
    "wof:name":"Catherine Wade Certified Fncl",
    "wof:placetype":"venue"
},
  "geometry": {"coordinates":[-121.874056,39.772224],"type":"Point"}
}