{
  "type": "Feature",
  "properties": {
    "iso:country":"US",
    "sg:address":"640 3rd St",
    "sg:city":"Santa Rosa",
    "sg:classifiers":[
        {
            "category":"Banks & Credit Unions",
            "subcategory":"Bank",
            "type":"Services"
        }
    ],
    "sg:phone":"+1 707 527 4000",
    "sg:postcode":"95404",
    "sg:province":"CA",
    "sg:tags":[
        "loan",
        "real estate"
    ],
    "wof:name":"First California Mortgage Co",
    "wof:placetype":"venue"
},
  "geometry": {"coordinates":[-122.711873,38.440258],"type":"Point"}
}