{
  "type": "Feature",
  "properties": {
    "iso:country":"US",
    "sg:address":"18 Peninsula Ctr",
    "sg:city":"Rllng Hls Est",
    "sg:classifiers":[
        {
            "category":"Retail",
            "subcategory":"Laundry & Dry Cleaning",
            "type":"Services"
        }
    ],
    "sg:phone":"+1 310 541 8811",
    "sg:postcode":"90274",
    "sg:province":"CA",
    "wof:name":"Spruce Cleaners",
    "wof:placetype":"venue"
},
  "geometry": {"coordinates":[-118.375,33.775398],"type":"Point"}
}