{
  "type": "Feature",
  "properties": {
    "addr:full":"3196 Oakridge Dr Chino Hills CA 91709",
    "addr:housenumber":"3196",
    "addr:postcode":"91709",
    "addr:street":"Oakridge Dr",
    "iso:country":"US",
    "sg:address":"3196 Oakridge Dr",
    "sg:city":"Chino Hills",
    "sg:classifiers":[
        {
            "category":"Retail",
            "subcategory":"Repair Shop",
            "type":"Services"
        }
    ],
    "sg:phone":"+1 909 393 8484",
    "sg:postcode":"91709",
    "sg:province":"CA",
    "wof:name":"Califrn Ultrsnc Crpt & Mini Bl",
    "wof:placetype":"venue"
},
  "geometry": {"coordinates":[-117.734262,33.972244],"type":"Point"}
}