{
  "type": "Feature",
  "properties": {
    "addr:full":"7377 Greenbush Ave North Hollywood CA 91605",
    "addr:housenumber":"7377",
    "addr:postcode":"91605",
    "addr:street":"Greenbush Ave",
    "iso:country":"US",
    "sg:address":"7377 Greenbush Ave",
    "sg:city":"North Hollywood",
    "sg:classifiers":[
        {
            "category":"Wholesale",
            "subcategory":"Durable Goods & Equipment",
            "type":"Manufacturing & Wholesale Goods"
        }
    ],
    "sg:phone":"+1 818 982 2432",
    "sg:postcode":"91605",
    "sg:province":"CA",
    "sg:tags":[
        "importer"
    ],
    "wof:name":"MJM Ent Import & Export",
    "wof:placetype":"venue"
},
  "geometry": {"coordinates":[-118.426355,34.205339],"type":"Point"}
}