{
  "type": "Feature",
  "properties": {
    "addr:full":"2034 Rangeview Dr Glendale CA 91201",
    "addr:housenumber":"2034",
    "addr:postcode":"91201",
    "addr:street":"Rangeview Dr",
    "iso:country":"US",
    "sg:address":"2034 Rangeview Dr",
    "sg:city":"Glendale",
    "sg:classifiers":[
        {
            "category":"Manufacturing",
            "subcategory":"Tools & Machinery",
            "type":"Manufacturing & Wholesale Goods"
        },
        {
            "category":"Wholesale",
            "subcategory":"Electrical",
            "type":"Manufacturing & Wholesale Goods"
        },
        {
            "category":"Wholesale",
            "subcategory":"Home Furnishings",
            "type":"Manufacturing & Wholesale Goods"
        }
    ],
    "sg:phone":"+1 818 840 9051",
    "sg:postcode":"91201",
    "sg:province":"CA",
    "sg:tags":[
        "electric",
        "supply",
        "equipment",
        "fixtures-wholesale",
        "lighting",
        "supplies-wholesale",
        "manufacturer"
    ],
    "sg:website":"http://www.electricalsupplyco.com",
    "wof:name":"Electrical Supply Co",
    "wof:placetype":"venue"
},
  "geometry": {"coordinates":[-118.28666,34.185311],"type":"Point"}
}