{
  "type": "Feature",
  "properties": {
    "iso:country":"US",
    "sg:address":"118 Dufour St",
    "sg:city":"Santa Cruz",
    "sg:classifiers":[
        {
            "category":"Shopping",
            "subcategory":"Hobbies, Toys, & Games",
            "type":"Retail Goods"
        }
    ],
    "sg:phone":"+1 831 427 1295",
    "sg:postcode":"95060",
    "sg:province":"CA",
    "wof:name":"Woodcraft Chessboards",
    "wof:placetype":"venue"
},
  "geometry": {"coordinates":[-122.035602,36.958447],"type":"Point"}
}