{
  "type": "Feature",
  "properties": {
    "iso:country":"US",
    "sg:address":"817 de Garmo St",
    "sg:city":"San Fernando",
    "sg:classifiers":[
        {
            "category":"Organizations",
            "subcategory":"Religious Organization",
            "type":"Services"
        }
    ],
    "sg:phone":"+1 818 837 1162",
    "sg:postcode":"91340",
    "sg:province":"CA",
    "sg:tags":[
        "church"
    ],
    "wof:name":"De Garmo Kingdom Hall Bldg",
    "wof:placetype":"venue"
},
  "geometry": {"coordinates":[-118.430486,34.288602],"type":"Point"}
}