{
  "type": "Feature",
  "properties": {
    "addr:full":"4344 Jensen St Oakland CA 94601",
    "addr:housenumber":"4344",
    "addr:postcode":"94601",
    "addr:street":"Jensen St",
    "iso:country":"US",
    "sg:address":"4344 Jensen St",
    "sg:city":"Oakland",
    "sg:classifiers":[
        {
            "category":"Wholesale",
            "subcategory":"Hardware",
            "type":"Manufacturing & Wholesale Goods"
        }
    ],
    "sg:phone":"+1 510 532 1561",
    "sg:postcode":"94601",
    "sg:province":"CA",
    "wof:name":"Halco Fasteners",
    "wof:placetype":"venue"
},
  "geometry": {"coordinates":[-122.220219,37.766449],"type":"Point"}
}