{
  "type": "Feature",
  "properties": {
    "addr:full":"1701 State Hwy 4 Byron CA 94505",
    "addr:housenumber":"1701",
    "addr:postcode":"94505",
    "addr:street":"State Hwy 4",
    "iso:country":"US",
    "sg:address":"1701 State Hwy 4",
    "sg:city":"Byron",
    "sg:classifiers":[
        {
            "category":"Recreation",
            "subcategory":"Marina",
            "type":"Entertainment"
        }
    ],
    "sg:phone":"+1 925 516 7678",
    "sg:postcode":"94505",
    "sg:province":"CA",
    "sg:tags":[
        "repairing",
        "boat"
    ],
    "wof:name":"Seaton's Marine Svc",
    "wof:placetype":"venue"
},
  "geometry": {"coordinates":[-118.002155,36.266933],"type":"Point"}
}