{
  "type": "Feature",
  "properties": {
    "addr:full":"16466 Perris Blvd Moreno Valley CA 92551",
    "addr:housenumber":"16466",
    "addr:postcode":"92551",
    "addr:street":"Perris Blvd",
    "iso:country":"US",
    "sg:address":"16466 Perris Blvd",
    "sg:city":"Moreno Valley",
    "sg:classifiers":[
        {
            "category":"Autos & Motor Vehicles",
            "subcategory":"Fuel & Gas Station",
            "type":"Retail Goods"
        }
    ],
    "sg:phone":"+1 951 247 2668",
    "sg:postcode":"92551",
    "sg:province":"CA",
    "sg:tags":[
        "oil"
    ],
    "wof:name":"Salib Enterprise Inc",
    "wof:placetype":"venue"
},
  "geometry": {"coordinates":[-117.226107,33.88337],"type":"Point"}
}