{
  "type": "Feature",
  "properties": {
    "iso:country":"US",
    "sg:address":"320 W 11th St",
    "sg:city":"Tracy",
    "sg:classifiers":[
        {
            "category":"Recreation",
            "type":"Entertainment"
        }
    ],
    "sg:phone":"+1 209 834 2888",
    "sg:postcode":"95376",
    "sg:province":"CA",
    "sg:tags":[
        "psychic",
        "medium"
    ],
    "wof:name":"Psychic Visions By Shirley",
    "wof:placetype":"venue"
},
  "geometry": {"coordinates":[-121.431255,37.739641],"type":"Point"}
}