{
  "type": "Feature",
  "properties": {
    "addr:full":"2924 W Vernon Ave Los Angeles CA 90008",
    "addr:housenumber":"2924",
    "addr:postcode":"90008",
    "addr:street":"W Vernon Ave",
    "iso:country":"US",
    "sg:address":"2924 W Vernon Ave",
    "sg:city":"Los Angeles",
    "sg:classifiers":[
        {
            "category":"Organizations",
            "subcategory":"Religious Organization",
            "type":"Services"
        }
    ],
    "sg:phone":"+1 323 291 1714",
    "sg:postcode":"90008",
    "sg:province":"CA",
    "sg:tags":[
        "church"
    ],
    "wof:name":"Arc-Grace Christian Fllwshp",
    "wof:placetype":"venue"
},
  "geometry": {"coordinates":[-118.32552,34.003585],"type":"Point"}
}