{
  "type": "Feature",
  "properties": {
    "iso:country":"US",
    "sg:address":"1901 Jubilee Dr",
    "sg:city":"Wasco",
    "sg:classifiers":[
        {
            "category":"Building & Trades",
            "subcategory":"Landscaping Services",
            "type":"Services"
        }
    ],
    "sg:phone":"+1 661 758 8893",
    "sg:postcode":"93280",
    "sg:province":"CA",
    "wof:name":"Green Forest Gardening",
    "wof:placetype":"venue"
},
  "geometry": {"coordinates":[-119.348179,35.587958],"type":"Point"}
}