{
  "type": "Feature",
  "properties": {
    "addr:full":"4425 U St Sacramento CA 95817",
    "addr:housenumber":"4425",
    "addr:postcode":"95817",
    "addr:street":"U St",
    "iso:country":"US",
    "sg:address":"4425 U St",
    "sg:city":"Sacramento",
    "sg:classifiers":[
        {
            "category":"Health Services",
            "subcategory":"Health Practitioner",
            "type":"Services"
        }
    ],
    "sg:phone":"+1 916 455 7801",
    "sg:postcode":"95817",
    "sg:province":"CA",
    "sg:tags":[
        "psychotherapist"
    ],
    "wof:name":"Jill Kelly",
    "wof:placetype":"venue"
},
  "geometry": {"coordinates":[-121.45466399999999,38.556748],"type":"Point"}
}