{
  "type": "Feature",
  "properties": {
    "iso:country":"US",
    "sg:address":"21543 Broadway",
    "sg:city":"Sonoma",
    "sg:classifiers":[
        {
            "category":"Farming",
            "subcategory":"Livestock Farm",
            "type":"Manufacturing & Wholesale Goods"
        }
    ],
    "sg:phone":"+1 707 938 5503",
    "sg:postcode":"95476",
    "sg:province":"CA",
    "sg:tags":[
        "ranch"
    ],
    "wof:name":"Sangiacomo Vineyards",
    "wof:placetype":"venue"
},
  "geometry": {"coordinates":[-122.457258,38.261699],"type":"Point"}
}