{
  "type": "Feature",
  "properties": {
    "addr:full":"265 W Highland Ave San Bernardino CA 92405",
    "addr:housenumber":"265",
    "addr:postcode":"92405",
    "addr:street":"W Highland Ave",
    "iso:country":"US",
    "sg:address":"265 W Highland Ave",
    "sg:city":"San Bernardino",
    "sg:classifiers":[
        {
            "category":"Restaurant",
            "type":"Food & Drink"
        }
    ],
    "sg:phone":"+1 909 881 1448",
    "sg:postcode":"92405",
    "sg:province":"CA",
    "wof:name":"Casa Sanchez",
    "wof:placetype":"venue"
},
  "geometry": {"coordinates":[-117.289497,34.135893],"type":"Point"}
}