{
  "type": "Feature",
  "properties": {
    "iso:country":"US",
    "sg:address":"2226 E Colorado Blvd",
    "sg:city":"Pasadena",
    "sg:classifiers":[
        {
            "category":"Restaurant",
            "type":"Food & Drink"
        }
    ],
    "sg:phone":"+1 626 795 6900",
    "sg:postcode":"91107",
    "sg:province":"CA",
    "sg:tags":[
        "middle",
        "eastern"
    ],
    "sg:website":"www.saharapasadena.com",
    "wof:name":"Sahara Middle Eastern Cuisine",
    "wof:placetype":"venue"
},
  "geometry": {"coordinates":[-118.103996,34.146],"type":"Point"}
}