{
  "type": "Feature",
  "properties": {
    "iso:country":"US",
    "sg:address":"4281 Technology Dr",
    "sg:city":"Fremont",
    "sg:classifiers":[
        {
            "category":"Real Estate",
            "subcategory":"Real Estate Operator",
            "type":"Services"
        }
    ],
    "sg:phone":"+1 510 268 8500",
    "sg:postcode":"94538",
    "sg:province":"CA",
    "sg:tags":[
        "property",
        "lessor"
    ],
    "wof:name":"T Drive Partners LP",
    "wof:placetype":"venue"
},
  "geometry": {"coordinates":[-121.954509,37.509471],"type":"Point"}
}