{
  "type": "Feature",
  "properties": {
    "addr:full":"3102 State St Santa Barbara CA 93105",
    "addr:housenumber":"3102",
    "addr:postcode":"93105",
    "addr:street":"State St",
    "iso:country":"US",
    "sg:address":"3102 State St",
    "sg:city":"Santa Barbara",
    "sg:classifiers":[
        {
            "category":"Autos & Motor Vehicles",
            "subcategory":"Motorcycle Sales",
            "type":"Retail Goods"
        }
    ],
    "sg:phone":"+1 805 682 9853",
    "sg:postcode":"93105",
    "sg:province":"CA",
    "sg:tags":[
        "scooter"
    ],
    "wof:name":"Full Throttle Custom Cycles",
    "wof:placetype":"venue"
},
  "geometry": {"coordinates":[-119.734191,34.440442],"type":"Point"}
}