{
  "type": "Feature",
  "properties": {
    "addr:full":"27281 La Paz Rd Laguna Niguel CA 92677",
    "addr:housenumber":"27281",
    "addr:postcode":"92677",
    "addr:street":"La Paz Rd",
    "iso:country":"US",
    "sg:address":"27281 La Paz Rd",
    "sg:city":"Laguna Niguel",
    "sg:classifiers":[
        {
            "category":"Personal",
            "subcategory":"Day Spa",
            "type":"Services"
        }
    ],
    "sg:phone":"+1 949 360 1210",
    "sg:postcode":"92677",
    "sg:province":"CA",
    "wof:name":"Rejuvene Salon & Day Spa",
    "wof:placetype":"venue"
},
  "geometry": {"coordinates":[-117.708,33.569801],"type":"Point"}
}