{
  "type": "Feature",
  "properties": {
    "iso:country":"US",
    "sg:address":"9801 Johannah Ave",
    "sg:city":"Garden Grove",
    "sg:classifiers":[
        {
            "category":"Home & Garden",
            "subcategory":"Household Appliances",
            "type":"Retail Goods"
        }
    ],
    "sg:phone":"+1 714 531 2260",
    "sg:postcode":"92844",
    "sg:province":"CA",
    "sg:tags":[
        "repair"
    ],
    "wof:name":"Aaapco Major Home & Commercial Appliance Services",
    "wof:placetype":"venue"
},
  "geometry": {"coordinates":[-117.958,33.7528],"type":"Point"}
}