{
  "type": "Feature",
  "properties": {
    "addr:full":"8218 Santa Fe Springs Rd Whittier CA 90606",
    "addr:housenumber":"8218",
    "addr:postcode":"90606",
    "addr:street":"Santa Fe Springs Rd",
    "iso:country":"US",
    "sg:address":"8218 Santa Fe Springs Rd",
    "sg:city":"Whittier",
    "sg:classifiers":[
        {
            "category":"Health Services",
            "subcategory":"Nursing And Care Facility",
            "type":"Services"
        }
    ],
    "sg:phone":"+1 562 698 4914",
    "sg:postcode":"90606",
    "sg:province":"CA",
    "sg:tags":[
        "home",
        "convalescent"
    ],
    "wof:name":"Exceptional Children's Fndtn",
    "wof:placetype":"venue"
},
  "geometry": {"coordinates":[-118.043269,33.966127],"type":"Point"}
}