{
  "type": "Feature",
  "properties": {
    "iso:country":"US",
    "sg:address":"1189 Pike Ln",
    "sg:city":"Oceano",
    "sg:classifiers":[
        {
            "category":"Manufacturing",
            "subcategory":"Metals",
            "type":"Manufacturing & Wholesale Goods"
        }
    ],
    "sg:phone":"+1 805 489 1682",
    "sg:postcode":"93445",
    "sg:province":"CA",
    "sg:tags":[
        "stamping",
        "drawing"
    ],
    "sg:website":"www.pacificcoaststamping.com",
    "wof:name":"Pacific Coast Stamping",
    "wof:placetype":"venue"
},
  "geometry": {"coordinates":[-120.617594,35.105701],"type":"Point"}
}