{
  "type": "Feature",
  "properties": {
    "addr:full":"1629 Orchard Dr Ojai CA 93023",
    "addr:housenumber":"1629",
    "addr:postcode":"93023",
    "addr:street":"Orchard Dr",
    "iso:country":"US",
    "sg:address":"1629 Orchard Dr",
    "sg:city":"Ojai",
    "sg:classifiers":[
        {
            "category":"Organizations",
            "subcategory":"Community Association",
            "type":"Services"
        }
    ],
    "sg:phone":"+1 805 646 2952",
    "sg:postcode":"93023",
    "sg:province":"CA",
    "wof:name":"General Grand Chptr Order Eas",
    "wof:placetype":"venue"
},
  "geometry": {"coordinates":[-119.28693,34.42859],"type":"Point"}
}