{
  "type": "Feature",
  "properties": {
    "addr:full":"10133 Wolf Rd Grass Valley CA 95949",
    "addr:housenumber":"10133",
    "addr:postcode":"95949",
    "addr:street":"Wolf Rd",
    "iso:country":"US",
    "sg:address":"10133 Wolf Rd",
    "sg:city":"Grass Valley",
    "sg:classifiers":[
        {
            "category":"Wholesale",
            "subcategory":"Farm Supplies",
            "type":"Manufacturing & Wholesale Goods"
        }
    ],
    "sg:phone":"+1 530 268 0471",
    "sg:postcode":"95949",
    "sg:province":"CA",
    "sg:tags":[
        "machinery"
    ],
    "wof:name":"Our 49er",
    "wof:placetype":"venue"
},
  "geometry": {"coordinates":[-121.096343,39.041952],"type":"Point"}
}