{
  "type": "Feature",
  "properties": {
    "iso:country":"US",
    "sg:address":"2303 Cam Ramon",
    "sg:city":"San Ramon",
    "sg:classifiers":[
        {
            "category":"Manufacturing",
            "subcategory":"Paper Products",
            "type":"Manufacturing & Wholesale Goods"
        }
    ],
    "sg:phone":"+1 925 867 3848",
    "sg:postcode":"94583",
    "sg:province":"CA",
    "sg:tags":[
        "packaging",
        "mfg"
    ],
    "wof:name":"Acrapak Inc",
    "wof:placetype":"venue"
},
  "geometry": {"coordinates":[-121.967302,37.776957],"type":"Point"}
}