{
  "type": "Feature",
  "properties": {
    "iso:country":"US",
    "sg:address":"502 W 1st St",
    "sg:city":"Imperial",
    "sg:classifiers":[
        {
            "category":"Airline",
            "type":"Transportation"
        }
    ],
    "sg:phone":"+1 800 238 5355",
    "sg:postcode":"92251",
    "sg:province":"CA",
    "sg:tags":[
        "scheduled",
        "courier",
        "air"
    ],
    "wof:name":"Federal Express Corporation",
    "wof:placetype":"venue"
},
  "geometry": {"coordinates":[-115.57607,32.840171],"type":"Point"}
}