{
  "type": "Feature",
  "properties": {
    "iso:country":"US",
    "sg:address":"822 Lake Tahoe Blvd",
    "sg:city":"South Lake Tahoe",
    "sg:classifiers":[
        {
            "category":"Food & Beverages",
            "subcategory":"Specialty",
            "type":"Retail Goods"
        }
    ],
    "sg:phone":"+1 530 541 7449",
    "sg:postcode":"96150",
    "sg:province":"CA",
    "sg:tags":[
        "tea",
        "coffee"
    ],
    "wof:name":"Alpina Cafe",
    "wof:placetype":"venue"
},
  "geometry": {"coordinates":[-120.037454,38.885456],"type":"Point"}
}