{
  "type": "Feature",
  "properties": {
    "addr:full":"1575 Annie St Daly City CA 94015",
    "addr:housenumber":"1575",
    "addr:postcode":"94015",
    "addr:street":"Annie St",
    "iso:country":"US",
    "sg:address":"1575 Annie St",
    "sg:city":"Daly City",
    "sg:classifiers":[
        {
            "category":"Organizations",
            "subcategory":"Religious Organization",
            "type":"Services"
        }
    ],
    "sg:phone":"+1 650 994 9757",
    "sg:postcode":"94015",
    "sg:province":"CA",
    "sg:tags":[
        "synagogue"
    ],
    "sg:website":"www.karaites.org",
    "wof:name":"KJA Temple",
    "wof:placetype":"venue"
},
  "geometry": {"coordinates":[-122.475273,37.68816],"type":"Point"}
}