{
  "type": "Feature",
  "properties": {
    "addr:full":"2882 Metropolitan Pl Pomona CA 91767",
    "addr:housenumber":"2882",
    "addr:postcode":"91767",
    "addr:street":"Metropolitan Pl",
    "iso:country":"US",
    "sg:address":"2882 Metropolitan Pl",
    "sg:city":"Pomona",
    "sg:classifiers":[
        {
            "category":"Manufacturing",
            "subcategory":"Tools & Machinery",
            "type":"Manufacturing & Wholesale Goods"
        }
    ],
    "sg:phone":"+1 909 593 2535",
    "sg:postcode":"91767",
    "sg:province":"CA",
    "sg:tags":[
        "industry",
        "special"
    ],
    "sg:website":"www.schwien.com",
    "wof:name":"Schwien Engineering",
    "wof:placetype":"venue"
},
  "geometry": {"coordinates":[-117.75266999999999,34.0977],"type":"Point"}
}