{
  "type": "Feature",
  "properties": {
    "addr:full":"1376 Longfellow Ave Chico CA 95926",
    "addr:housenumber":"1376",
    "addr:postcode":"95926",
    "addr:street":"Longfellow Ave",
    "iso:country":"US",
    "sg:address":"1376 Longfellow Ave",
    "sg:city":"Chico",
    "sg:classifiers":[
        {
            "category":"Retail",
            "subcategory":"Portrait Studio",
            "type":"Services"
        }
    ],
    "sg:phone":"+1 530 343 4140",
    "sg:postcode":"95926",
    "sg:province":"CA",
    "sg:tags":[
        "photographer"
    ],
    "wof:name":"Whittle Photography",
    "wof:placetype":"venue"
},
  "geometry": {"coordinates":[-121.824915,39.750811],"type":"Point"}
}