{
  "type": "Feature",
  "properties": {
    "addr:full":"7770 el Camino Real Carlsbad CA 92009",
    "addr:housenumber":"7770",
    "addr:postcode":"92009",
    "addr:street":"El Camino Real",
    "iso:country":"US",
    "sg:address":"7770 el Camino Real",
    "sg:city":"Carlsbad",
    "sg:classifiers":[
        {
            "category":"Banks & Credit Unions",
            "subcategory":"Investment Brokerage",
            "type":"Services"
        }
    ],
    "sg:phone":"+1 760 943 3939",
    "sg:postcode":"92009",
    "sg:province":"CA",
    "sg:tags":[
        "advisory",
        "security"
    ],
    "sg:website":"www.gril.net",
    "wof:name":"Global Resource Investments",
    "wof:placetype":"venue"
},
  "geometry": {"coordinates":[-117.266994,33.105201],"type":"Point"}
}