{
  "type": "Feature",
  "properties": {
    "addr:full":"595 E Colorado Blvd Ste 509 Pasadena CA 91101",
    "addr:housenumber":"595",
    "addr:postcode":"91101",
    "addr:street":"E Colorado Blvd Ste 509",
    "iso:country":"US",
    "sg:address":"595 E Colorado Blvd Ste 509",
    "sg:city":"Pasadena",
    "sg:classifiers":[
        {
            "category":"Health Services",
            "subcategory":"Chiropractor",
            "type":"Services"
        }
    ],
    "sg:phone":"+1 323 888 8866",
    "sg:postcode":"91101",
    "sg:province":"CA",
    "sg:tags":[
        "chiropractic"
    ],
    "wof:name":"Euclid Family Chiropractic",
    "wof:placetype":"venue"
},
  "geometry": {"coordinates":[-118.138215,34.145856],"type":"Point"}
}