{
  "type": "Feature",
  "properties": {
    "addr:full":"4790 Irvine Bvld. ste.105-273 Irvine CA 92620",
    "addr:housenumber":"4790;ste.105-273",
    "addr:postcode":"92620",
    "addr:street":"Irvine Bvld.",
    "iso:country":"US",
    "sg:address":"4790 Irvine Bvld. ste.105-273",
    "sg:city":"Irvine",
    "sg:classifiers":[
        {
            "category":"Building & Trades",
            "subcategory":"Construction",
            "type":"Services"
        }
    ],
    "sg:phone":"+1 714 417 9679",
    "sg:postcode":"92620",
    "sg:province":"CA",
    "sg:tags":[
        "contractor"
    ],
    "sg:website":"zwartconstruction.com",
    "wof:name":"Zwart Construction",
    "wof:placetype":"venue"
},
  "geometry": {"coordinates":[-117.760606,33.714166],"type":"Point"}
}