{
  "type": "Feature",
  "properties": {
    "iso:country":"US",
    "sg:address":"2825 Kovr Dr",
    "sg:city":"West Sacramento",
    "sg:classifiers":[
        {
            "category":"Health Services",
            "subcategory":"Medical Lab",
            "type":"Services"
        }
    ],
    "sg:phone":"+1 916 372 4200",
    "sg:postcode":"95605",
    "sg:province":"CA",
    "sg:tags":[
        "laboratory",
        "testing"
    ],
    "wof:name":"Idexx Veterinary Services Inc",
    "wof:placetype":"venue"
},
  "geometry": {"coordinates":[-121.54784600000001,38.593377],"type":"Point"}
}