{
  "type": "Feature",
  "properties": {
    "addr:full":"3148 5th Ave San Diego CA 92103",
    "addr:housenumber":"3148",
    "addr:postcode":"92103",
    "addr:street":"5Th Ave",
    "iso:country":"US",
    "sg:address":"3148 5th Ave",
    "sg:city":"San Diego",
    "sg:classifiers":[
        {
            "category":"Retail",
            "subcategory":"Auto Repair",
            "type":"Services"
        }
    ],
    "sg:phone":"+1 619 683 2236",
    "sg:postcode":"92103",
    "sg:province":"CA",
    "sg:tags":[
        "body",
        "automobile",
        "painting"
    ],
    "wof:name":"Collision Care Inc",
    "wof:placetype":"venue"
},
  "geometry": {"coordinates":[-117.16042299999999,32.7382],"type":"Point"}
}