{
  "type": "Feature",
  "properties": {
    "addr:full":"1433 Huntington Dr South Pasadena CA 91030",
    "addr:housenumber":"1433",
    "addr:postcode":"91030",
    "addr:street":"Huntington Dr",
    "iso:country":"US",
    "sg:address":"1433 Huntington Dr",
    "sg:city":"South Pasadena",
    "sg:classifiers":[
        {
            "category":"Retail",
            "subcategory":"Laundry & Dry Cleaning",
            "type":"Services"
        }
    ],
    "sg:phone":"+1 626 799 4680",
    "sg:postcode":"91030",
    "sg:province":"CA",
    "wof:name":"Fashion Cleaners",
    "wof:placetype":"venue"
},
  "geometry": {"coordinates":[-118.15154800000001,34.103932],"type":"Point"}
}