{
  "type": "Feature",
  "properties": {
    "iso:country":"US",
    "sg:address":"180 Harbor Dr",
    "sg:city":"Sausalito",
    "sg:classifiers":[
        {
            "category":"Professional",
            "subcategory":"Business Services",
            "type":"Services"
        },
        {
            "category":"Manufacturing",
            "subcategory":"Printing",
            "type":"Manufacturing & Wholesale Goods"
        }
    ],
    "sg:phone":"+1 415 331 3858",
    "sg:postcode":"94965",
    "sg:province":"CA",
    "sg:tags":[
        "broker"
    ],
    "wof:name":"Schultz Peter Printing Svcs",
    "wof:placetype":"venue"
},
  "geometry": {"coordinates":[-122.499508,37.867782],"type":"Point"}
}