{
  "type": "Feature",
  "properties": {
    "iso:country":"US",
    "sg:address":"6484 Washington St",
    "sg:city":"Yountville",
    "sg:classifiers":[
        {
            "category":"Food & Beverages",
            "subcategory":"Liquor & Beverages",
            "type":"Retail Goods"
        }
    ],
    "sg:phone":"+1 707 944 2331",
    "sg:postcode":"94599",
    "sg:province":"CA",
    "sg:tags":[
        "wine"
    ],
    "wof:name":"Groezinger Wine Co",
    "wof:placetype":"venue"
},
  "geometry": {"coordinates":[-122.359824,38.400684],"type":"Point"}
}