{
  "type": "Feature",
  "properties": {
    "addr:full":"1421 W MacArthur Blvd Santa Ana CA 92704",
    "addr:housenumber":"1421",
    "addr:postcode":"92704",
    "addr:street":"W Macarthur Blvd",
    "iso:country":"US",
    "sg:address":"1421 W MacArthur Blvd",
    "sg:city":"Santa Ana",
    "sg:classifiers":[
        {
            "category":"Wholesale",
            "subcategory":"Computers",
            "type":"Manufacturing & Wholesale Goods"
        }
    ],
    "sg:phone":"+1 714 979 2582",
    "sg:postcode":"92704",
    "sg:province":"CA",
    "wof:name":"PC Club South Coast",
    "wof:placetype":"venue"
},
  "geometry": {"coordinates":[-117.887001,33.7001],"type":"Point"}
}