{
  "type": "Feature",
  "properties": {
    "iso:country":"US",
    "sg:address":"856 Beckville St",
    "sg:city":"Duarte",
    "sg:classifiers":[
        {
            "category":"Transit Center",
            "subcategory":"Freight",
            "type":"Transportation"
        },
        {
            "category":"Freight",
            "type":"Transportation"
        }
    ],
    "sg:phone":"+1 626 358 8863",
    "sg:postcode":"91010",
    "sg:province":"CA",
    "sg:tags":[
        "local",
        "trucking-motor",
        "trucking"
    ],
    "wof:name":"Mgg Trucking",
    "wof:placetype":"venue"
},
  "geometry": {"coordinates":[-117.987228,34.125191],"type":"Point"}
}