{
  "type": "Feature",
  "properties": {
    "addr:full":"1531 Argonne Dr Stockton CA 95203",
    "addr:housenumber":"1531",
    "addr:postcode":"95203",
    "addr:street":"Argonne Dr",
    "iso:country":"US",
    "sg:address":"1531 Argonne Dr",
    "sg:city":"Stockton",
    "sg:classifiers":[
        {
            "category":"Professional",
            "subcategory":"Advertising",
            "type":"Services"
        }
    ],
    "sg:phone":"+1 209 948 9333",
    "sg:postcode":"95203",
    "sg:province":"CA",
    "sg:tags":[
        "counselor"
    ],
    "wof:name":"Western Metal In Architecture",
    "wof:placetype":"venue"
},
  "geometry": {"coordinates":[-121.315366,37.961329],"type":"Point"}
}