{
  "type": "Feature",
  "properties": {
    "iso:country":"US",
    "sg:address":"1429 14th Ave",
    "sg:city":"Oakland",
    "sg:classifiers":[
        {
            "category":"Retail",
            "subcategory":"Repair Shop",
            "type":"Services"
        }
    ],
    "sg:phone":"+1 510 316 1161",
    "sg:postcode":"94606",
    "sg:province":"CA",
    "sg:tags":[
        "appliance"
    ],
    "wof:name":"Sam Sung Appliance",
    "wof:placetype":"venue"
},
  "geometry": {"coordinates":[-122.246005,37.789861],"type":"Point"}
}