{
  "type": "Feature",
  "properties": {
    "addr:full":"160 N San Pedro Rd San Rafael CA 94903",
    "addr:housenumber":"160",
    "addr:postcode":"94903",
    "addr:street":"N San Pedro Rd",
    "iso:country":"US",
    "sg:address":"160 N San Pedro Rd",
    "sg:city":"San Rafael",
    "sg:classifiers":[
        {
            "category":"Education",
            "subcategory":"School",
            "type":"Public Place"
        }
    ],
    "sg:phone":"+1 415 491 0581",
    "sg:postcode":"94903",
    "sg:province":"CA",
    "wof:name":"County Community School",
    "wof:placetype":"venue"
},
  "geometry": {"coordinates":[-122.52557,37.998848],"type":"Point"}
}