{
  "type": "Feature",
  "properties": {
    "iso:country":"US",
    "sg:address":"502 W Mission Ave",
    "sg:city":"Escondido",
    "sg:classifiers":[
        {
            "category":"Autos & Motor Vehicles",
            "subcategory":"Automobile Sales",
            "type":"Retail Goods"
        }
    ],
    "sg:phone":"+1 760 871 0400",
    "sg:postcode":"92025",
    "sg:province":"CA",
    "sg:tags":[
        "car",
        "dealer"
    ],
    "wof:name":"North County Cars & Trucks",
    "wof:placetype":"venue"
},
  "geometry": {"coordinates":[-117.092367,33.128254],"type":"Point"}
}