{
  "type": "Feature",
  "properties": {
    "addr:full":"401 Torrance Blvd Redondo Beach CA 90277",
    "addr:housenumber":"401",
    "addr:postcode":"90277",
    "addr:street":"Torrance Blvd",
    "iso:country":"US",
    "sg:address":"401 Torrance Blvd",
    "sg:city":"Redondo Beach",
    "sg:classifiers":[
        {
            "category":"Wholesale",
            "subcategory":"Medical Equipment & Supplies",
            "type":"Manufacturing & Wholesale Goods"
        }
    ],
    "sg:phone":"+1 310 937 3650",
    "sg:postcode":"90277",
    "sg:province":"CA",
    "sg:tags":[
        "physician",
        "surgeon"
    ],
    "wof:name":"Beach Cities Home Help",
    "wof:placetype":"venue"
},
  "geometry": {"coordinates":[-118.38327099999999,33.83795],"type":"Point"}
}