{
  "type": "Feature",
  "properties": {
    "addr:full":"341 Lafayette Street Suite 102 Santa Clara CA 95050",
    "addr:housenumber":"341",
    "addr:postcode":"95050",
    "addr:street":"Lafayette Street Suite 102",
    "iso:country":"US",
    "sg:address":"341 Lafayette Street Suite 102",
    "sg:city":"Santa Clara",
    "sg:classifiers":[
        {
            "category":"Personal",
            "subcategory":"Beauty Salon",
            "type":"Services"
        }
    ],
    "sg:phone":"+1 408 244 7023",
    "sg:postcode":"95050",
    "sg:province":"CA",
    "sg:tags":[
        "hair"
    ],
    "wof:name":"Miracles A Salon",
    "wof:placetype":"venue"
},
  "geometry": {"coordinates":[-121.940882,37.344439],"type":"Point"}
}