{
  "type": "Feature",
  "properties": {
    "addr:full":"841 San Bruno Ave W San Bruno CA 94066",
    "addr:housenumber":"841",
    "addr:postcode":"94066",
    "addr:street":"San Bruno Ave W",
    "iso:country":"US",
    "sg:address":"841 San Bruno Ave W",
    "sg:city":"San Bruno",
    "sg:classifiers":[
        {
            "category":"Banks & Credit Unions",
            "subcategory":"Investment Brokerage",
            "type":"Services"
        }
    ],
    "sg:phone":"+1 650 615 4840",
    "sg:postcode":"94066",
    "sg:province":"CA",
    "sg:tags":[
        "commodity"
    ],
    "sg:website":"www.lorisresources.com",
    "wof:name":"Loris Resources",
    "wof:placetype":"venue"
},
  "geometry": {"coordinates":[-122.417073,37.628565],"type":"Point"}
}