{
  "type": "Feature",
  "properties": {
    "iso:country":"US",
    "sg:address":"4064 Crest Rd",
    "sg:city":"Pebble Beach",
    "sg:classifiers":[
        {
            "category":"Banks & Credit Unions",
            "subcategory":"Bank",
            "type":"Services"
        }
    ],
    "sg:phone":"+1 831 625 9168",
    "sg:postcode":"93953",
    "sg:province":"CA",
    "sg:tags":[
        "loan",
        "real estate"
    ],
    "wof:name":"A Plus Realty & Mortgage",
    "wof:placetype":"venue"
},
  "geometry": {"coordinates":[-121.919866,36.583725],"type":"Point"}
}