{
  "type": "Feature",
  "properties": {
    "addr:full":"6149 Brockton Ave Riverside CA 92506",
    "addr:housenumber":"6149",
    "addr:postcode":"92506",
    "addr:street":"Brockton Ave",
    "iso:country":"US",
    "sg:address":"6149 Brockton Ave",
    "sg:city":"Riverside",
    "sg:classifiers":[
        {
            "category":"Building & Trades",
            "subcategory":"Construction",
            "type":"Services"
        }
    ],
    "sg:phone":"+1 951 787 8281",
    "sg:postcode":"92506",
    "sg:province":"CA",
    "sg:tags":[
        "contractor"
    ],
    "wof:name":"E A Florio Construction",
    "wof:placetype":"venue"
},
  "geometry": {"coordinates":[-117.396832,33.959667],"type":"Point"}
}