{
  "type": "Feature",
  "properties": {
    "iso:country":"US",
    "sg:address":"1022 Gibson Rd",
    "sg:city":"Woodland",
    "sg:classifiers":[
        {
            "category":"Freight",
            "type":"Transportation"
        }
    ],
    "sg:phone":"+1 530 661 0110",
    "sg:postcode":"95695",
    "sg:province":"CA",
    "sg:tags":[
        "commercial",
        "storage",
        "general"
    ],
    "wof:name":"Superior Self Storage",
    "wof:placetype":"venue"
},
  "geometry": {"coordinates":[-121.765975,38.662801],"type":"Point"}
}