{
  "type": "Feature",
  "properties": {
    "addr:full":"8534 Hubbles Ln Santee CA 92071",
    "addr:housenumber":"8534",
    "addr:postcode":"92071",
    "addr:street":"Hubbles Ln",
    "iso:country":"US",
    "sg:address":"8534 Hubbles Ln",
    "sg:city":"Santee",
    "sg:classifiers":[
        {
            "category":"Building & Trades",
            "subcategory":"Construction",
            "type":"Services"
        }
    ],
    "sg:phone":"+1 619 596 5400",
    "sg:postcode":"92071",
    "sg:province":"CA",
    "sg:tags":[
        "concrete",
        "contractor"
    ],
    "wof:name":"Morello Concrete Constr Inc",
    "wof:placetype":"venue"
},
  "geometry": {"coordinates":[-116.975903,32.830741],"type":"Point"}
}