{
  "type": "Feature",
  "properties": {
    "iso:country":"US",
    "sg:address":"1667 E Golden Way",
    "sg:city":"Dinuba",
    "sg:classifiers":[
        {
            "category":"Organizations",
            "subcategory":"Religious Organization",
            "type":"Services"
        }
    ],
    "sg:phone":"+1 559 591 0704",
    "sg:postcode":"93618",
    "sg:province":"CA",
    "sg:tags":[
        "church"
    ],
    "wof:name":"First Southern Baptist Church",
    "wof:placetype":"venue"
},
  "geometry": {"coordinates":[-119.379259,36.535195],"type":"Point"}
}