{
  "type": "Feature",
  "properties": {
    "addr:full":"3450 C St San Diego CA 92102",
    "addr:housenumber":"3450",
    "addr:postcode":"92102",
    "addr:street":"C St",
    "iso:country":"US",
    "sg:address":"3450 C St",
    "sg:city":"San Diego",
    "sg:classifiers":[
        {
            "category":"Building & Trades",
            "subcategory":"Cleaning & Sanitation",
            "type":"Services"
        }
    ],
    "sg:phone":"+1 619 232 6040",
    "sg:postcode":"92102",
    "sg:province":"CA",
    "sg:tags":[
        "janitor"
    ],
    "wof:name":"Mc Pherson's Maintenance Co",
    "wof:placetype":"venue"
},
  "geometry": {"coordinates":[-117.12036000000001,32.717038],"type":"Point"}
}