{
  "type": "Feature",
  "properties": {
    "addr:full":"11400 West Olympic Boulevard Suite 200 Los Angeles CA 90064",
    "addr:housenumber":"11400",
    "addr:postcode":"90064",
    "addr:street":"West Olympic Boulevard Suite 200",
    "iso:country":"US",
    "sg:address":"11400 West Olympic Boulevard Suite 200",
    "sg:city":"Los Angeles",
    "sg:classifiers":[
        {
            "category":"Professional",
            "subcategory":"Management & Consulting",
            "type":"Services"
        }
    ],
    "sg:phone":"+1 917 720 1080",
    "sg:postcode":"90064",
    "sg:province":"CA",
    "sg:tags":[
        "consulting",
        "staffing",
        "recruiting",
        "php-jobs",
        "java-jobs",
        "drupal-jobs",
        "c-jobs",
        "-net-jobs",
        "technology-jobs",
        "project-managers",
        "web-producers"
    ],
    "sg:website":"http://www.talener.com",
    "wof:name":"Talener Group",
    "wof:placetype":"venue"
},
  "geometry": {"coordinates":[-118.444074,34.036502],"type":"Point"}
}