{
  "type": "Feature",
  "properties": {
    "addr:full":"4325 Orange Grove Ave Sacramento CA 95841",
    "addr:housenumber":"4325",
    "addr:postcode":"95841",
    "addr:street":"Orange Grove Ave",
    "iso:country":"US",
    "sg:address":"4325 Orange Grove Ave",
    "sg:city":"Sacramento",
    "sg:classifiers":[
        {
            "category":"Building & Trades",
            "subcategory":"Electrical",
            "type":"Services"
        }
    ],
    "sg:phone":"+1 916 973 8632",
    "sg:postcode":"95841",
    "sg:province":"CA",
    "sg:tags":[
        "electric",
        "contractor"
    ],
    "wof:name":"Zlukta Electric",
    "wof:placetype":"venue"
},
  "geometry": {"coordinates":[-121.362893,38.648062],"type":"Point"}
}