{
  "type": "Feature",
  "properties": {
    "addr:full":"1350 Dell Aveune Suite 107 Campbell CA 95008",
    "addr:housenumber":"1350",
    "addr:postcode":"95008",
    "addr:street":"Dell Aveune Suite 107",
    "iso:country":"US",
    "sg:address":"1350 Dell Aveune Suite 107",
    "sg:city":"Campbell",
    "sg:classifiers":[
        {
            "category":"Professional",
            "type":"Services"
        },
        {
            "category":"Professional",
            "subcategory":"Art Services",
            "type":"Services"
        }
    ],
    "sg:phone":"+1 408 871 0445",
    "sg:postcode":"95008",
    "sg:province":"CA",
    "sg:tags":[
        "planning",
        "graphic",
        "design",
        "event"
    ],
    "sg:website":"www.trendcom.com",
    "wof:name":"Trend Communications",
    "wof:placetype":"venue"
},
  "geometry": {"coordinates":[-121.953526,37.266667],"type":"Point"}
}