{
  "type": "Feature",
  "properties": {
    "addr:full":"4274 el Cajon Blvd San Diego CA 92105",
    "addr:housenumber":"4274",
    "addr:postcode":"92105",
    "addr:street":"El Cajon Blvd",
    "iso:country":"US",
    "sg:address":"4274 el Cajon Blvd",
    "sg:city":"San Diego",
    "sg:classifiers":[
        {
            "category":"Building & Trades",
            "subcategory":"Equipment Rental",
            "type":"Services"
        }
    ],
    "sg:phone":"+1 619 280 2075",
    "sg:postcode":"92105",
    "sg:province":"CA",
    "sg:tags":[
        "instrument",
        "musical"
    ],
    "wof:name":"Music Rental Co & Pawn",
    "wof:placetype":"venue"
},
  "geometry": {"coordinates":[-117.102529,32.755203],"type":"Point"}
}