{
  "type": "Feature",
  "properties": {
    "addr:full":"2035 Granville Ave Los Angeles CA 90025",
    "addr:housenumber":"2035",
    "addr:postcode":"90025",
    "addr:street":"Granville Ave",
    "iso:country":"US",
    "sg:address":"2035 Granville Ave",
    "sg:city":"Los Angeles",
    "sg:classifiers":[
        {
            "category":"Retail",
            "subcategory":"Repair Shop",
            "type":"Services"
        }
    ],
    "sg:phone":"+1 310 473 8684",
    "sg:postcode":"90025",
    "sg:province":"CA",
    "sg:tags":[
        "welding"
    ],
    "wof:name":"Aerospace Welding Inc",
    "wof:placetype":"venue"
},
  "geometry": {"coordinates":[-118.451348,34.034932],"type":"Point"}
}