{
  "type": "Feature",
  "properties": {
    "iso:country":"US",
    "sg:address":"2389 Shoreside Ct",
    "sg:city":"Santa Clara",
    "sg:classifiers":[
        {
            "category":"Professional",
            "type":"Services"
        }
    ],
    "sg:phone":"+1 408 832 9309",
    "sg:postcode":"95054",
    "sg:province":"CA",
    "wof:name":"Randy Zimmerman",
    "wof:placetype":"venue"
},
  "geometry": {"coordinates":[-121.96717099999999,37.393577],"type":"Point"}
}