{
  "type": "Feature",
  "properties": {
    "addr:full":"82753 Miles Ave Indio CA 92201",
    "addr:housenumber":"82753",
    "addr:postcode":"92201",
    "addr:street":"Miles Ave",
    "iso:country":"US",
    "sg:address":"82753 Miles Ave",
    "sg:city":"Indio",
    "sg:classifiers":[
        {
            "category":"Retail",
            "subcategory":"Repair Shop",
            "type":"Services"
        }
    ],
    "sg:phone":"+1 760 342 4116",
    "sg:postcode":"92201",
    "sg:province":"CA",
    "sg:tags":[
        "jewelry"
    ],
    "wof:name":"Wagner Jewelry",
    "wof:placetype":"venue"
},
  "geometry": {"coordinates":[-116.220094,33.721181],"type":"Point"}
}