{
  "type": "Feature",
  "properties": {
    "iso:country":"US",
    "sg:address":"513 14th St",
    "sg:city":"Santa Monica",
    "sg:classifiers":[
        {
            "category":"Professional",
            "type":"Services"
        }
    ],
    "sg:phone":"+1 310 395 4507",
    "sg:postcode":"90402",
    "sg:province":"CA",
    "wof:name":"Far Plus Three Inc",
    "wof:placetype":"venue"
},
  "geometry": {"coordinates":[-118.497303,34.034141],"type":"Point"}
}