{
  "type": "Feature",
  "properties": {
    "addr:full":"801 Fox Lane San Jose 95131 CA",
    "addr:housenumber":"801",
    "addr:postcode":"95131",
    "addr:street":"Fox Lane",
    "iso:country":"US",
    "sg:address":"801 Fox Lane San Jose 95131",
    "sg:classifiers":[
        {
            "category":"Manufacturing",
            "subcategory":"Electronics",
            "type":"Manufacturing & Wholesale Goods"
        }
    ],
    "sg:phone":"+1 408 467 1900",
    "sg:province":"CA",
    "sg:tags":[
        "haptics",
        "haptic",
        "tactile",
        "force-feedback",
        "vibration",
        "touch",
        "touchsense"
    ],
    "sg:website":"http://www.immersion.com/",
    "wof:name":"Immersion Corporation",
    "wof:placetype":"venue"
},
  "geometry": {"coordinates":[-121.87798600000001,37.307287],"type":"Point"}
}