{
  "type": "Feature",
  "properties": {
    "iso:country":"US",
    "sg:address":"2305 Van Ness Avenue Suite E",
    "sg:city":"San Francisco",
    "sg:classifiers":[
        {
            "category":"Health Services",
            "subcategory":"Doctor",
            "type":"Services"
        }
    ],
    "sg:phone":"+1 415 776 5855",
    "sg:postcode":"94109",
    "sg:province":"CA",
    "sg:tags":[
        "surgeon",
        "oral"
    ],
    "wof:name":"Hiura Bruce T Dr",
    "wof:placetype":"venue"
},
  "geometry": {"coordinates":[-122.423725,37.796756],"type":"Point"}
}