{
  "type": "Feature",
  "properties": {
    "addr:full":"17039 Ventura Blvd Encino CA 91316",
    "addr:housenumber":"17039",
    "addr:postcode":"91316",
    "addr:street":"Ventura Blvd",
    "iso:country":"US",
    "sg:address":"17039 Ventura Blvd",
    "sg:city":"Encino",
    "sg:classifiers":[
        {
            "category":"Personal",
            "subcategory":"Beauty Salon",
            "type":"Services"
        }
    ],
    "sg:phone":"+1 818 379 9877",
    "sg:postcode":"91316",
    "sg:province":"CA",
    "sg:tags":[
        "manicuring"
    ],
    "wof:name":"Maria's Nails",
    "wof:placetype":"venue"
},
  "geometry": {"coordinates":[-118.505376,34.160293],"type":"Point"}
}