{
  "type": "Feature",
  "properties": {
    "iso:country":"US",
    "sg:address":"4778 Commons Way",
    "sg:city":"Calabasas",
    "sg:classifiers":[
        {
            "category":"Building & Trades",
            "subcategory":"Plumbing",
            "type":"Services"
        }
    ],
    "sg:phone":"+1 818 532 9270",
    "sg:postcode":"91302",
    "sg:province":"CA",
    "sg:website":"bit.ly/bERI5D",
    "wof:name":"Kathey",
    "wof:placetype":"venue"
},
  "geometry": {"coordinates":[-118.64342499999999,34.154681],"type":"Point"}
}