{
  "type": "Feature",
  "properties": {
    "addr:full":"1126 Broadway Plz Walnut Creek CA 94596",
    "addr:housenumber":"1126",
    "addr:postcode":"94596",
    "addr:street":"Broadway Plz",
    "iso:country":"US",
    "sg:address":"1126 Broadway Plz",
    "sg:city":"Walnut Creek",
    "sg:classifiers":[
        {
            "category":"Shopping",
            "subcategory":"Gifts & Souvenirs",
            "type":"Retail Goods"
        }
    ],
    "sg:phone":"+1 925 947 1991",
    "sg:postcode":"94596",
    "sg:province":"CA",
    "sg:tags":[
        "shop"
    ],
    "wof:name":"David M Brian",
    "wof:placetype":"venue"
},
  "geometry": {"coordinates":[-122.058589,37.896894],"type":"Point"}
}