{
  "type": "Feature",
  "properties": {
    "addr:full":"2660 E South St Long Beach CA 90805",
    "addr:housenumber":"2660 e",
    "addr:postcode":"90805",
    "addr:street":"South St",
    "iso:country":"US",
    "sg:address":"2660 E South St",
    "sg:city":"Long Beach",
    "sg:classifiers":[
        {
            "category":"Building & Trades",
            "subcategory":"Construction",
            "type":"Services"
        }
    ],
    "sg:phone":"+1 562 630 7284",
    "sg:postcode":"90805",
    "sg:province":"CA",
    "sg:tags":[
        "contractor"
    ],
    "wof:name":"C T Gibson Construction",
    "wof:placetype":"venue"
},
  "geometry": {"coordinates":[-118.162237,33.860081],"type":"Point"}
}