{
  "type": "Feature",
  "properties": {
    "iso:country":"US",
    "sg:address":"3721 Marmion Way",
    "sg:city":"Los Angeles",
    "sg:classifiers":[
        {
            "category":"Organizations",
            "subcategory":"Religious Organization",
            "type":"Services"
        }
    ],
    "sg:phone":"+1 323 225 7660",
    "sg:postcode":"90065",
    "sg:province":"CA",
    "sg:tags":[
        "church"
    ],
    "wof:name":"Highland View Pentecostal",
    "wof:placetype":"venue"
},
  "geometry": {"coordinates":[-118.211524,34.090575],"type":"Point"}
}