{
  "type": "Feature",
  "properties": {
    "iso:country":"US",
    "sg:address":"629 E Carnation St",
    "sg:city":"Palm Springs",
    "sg:classifiers":[
        {
            "category":"Personal",
            "type":"Services"
        }
    ],
    "sg:phone":"+1 760 320 9238",
    "sg:postcode":"92262",
    "sg:province":"CA",
    "sg:tags":[
        "mover"
    ],
    "wof:name":"ACTION MOVERS & STORAGE",
    "wof:placetype":"venue"
},
  "geometry": {"coordinates":[-116.540105,33.858102],"type":"Point"}
}