{
  "type": "Feature",
  "properties": {
    "addr:full":"10809 Martis Dr Truckee CA 96161",
    "addr:housenumber":"10809",
    "addr:postcode":"96161",
    "addr:street":"Martis Dr",
    "iso:country":"US",
    "sg:address":"10809 Martis Dr",
    "sg:city":"Truckee",
    "sg:classifiers":[
        {
            "category":"Retail",
            "subcategory":"Laundry & Dry Cleaning",
            "type":"Services"
        }
    ],
    "sg:phone":"+1 530 587 4839",
    "sg:postcode":"96161",
    "sg:province":"CA",
    "sg:tags":[
        "house",
        "cleaner",
        "rug",
        "carpet"
    ],
    "wof:name":"All Seasons Carpet Cleaning",
    "wof:placetype":"venue"
},
  "geometry": {"coordinates":[-120.163574,39.328212],"type":"Point"}
}