{
  "type": "Feature",
  "properties": {
    "iso:country":"US",
    "sg:address":"30343 Canwood St",
    "sg:city":"Agoura Hills",
    "sg:classifiers":[
        {
            "category":"Professional",
            "subcategory":"Lawyer & Legal Services",
            "type":"Services"
        }
    ],
    "sg:phone":"+1 818 991 9019",
    "sg:postcode":"91301",
    "sg:province":"CA",
    "sg:tags":[
        "attorney"
    ],
    "sg:website":"www.mtclaw.com",
    "wof:name":"Chulak & Shiffman",
    "wof:placetype":"venue"
},
  "geometry": {"coordinates":[-118.781632,34.147975],"type":"Point"}
}