{
  "type": "Feature",
  "properties": {
    "addr:full":"3330 E Thousand Oaks Blvd Thousand Oaks CA 91362",
    "addr:housenumber":"3330",
    "addr:postcode":"91362",
    "addr:street":"E Thousand Oaks Blvd",
    "iso:country":"US",
    "sg:address":"3330 E Thousand Oaks Blvd",
    "sg:city":"Thousand Oaks",
    "sg:classifiers":[
        {
            "category":"Shopping",
            "subcategory":"Bicycles & Sporting Goods",
            "type":"Retail Goods"
        }
    ],
    "sg:phone":"+1 805 494 9939",
    "sg:postcode":"91362",
    "sg:province":"CA",
    "sg:tags":[
        "equipment",
        "exercise"
    ],
    "wof:name":"LA Gym Equipment",
    "wof:placetype":"venue"
},
  "geometry": {"coordinates":[-118.833215,34.166785],"type":"Point"}
}