{
  "type": "Feature",
  "properties": {
    "iso:country":"US",
    "sg:address":"717 Merced Mall",
    "sg:city":"Merced",
    "sg:classifiers":[
        {
            "category":"Recreation",
            "subcategory":"Amusement Park",
            "type":"Entertainment"
        },
        {
            "category":"Recreation",
            "subcategory":"Picnic Area",
            "type":"Entertainment"
        }
    ],
    "sg:phone":"+1 209 725 2904",
    "sg:postcode":"95348",
    "sg:province":"CA",
    "sg:tags":[
        "arcade",
        "ride",
        "equipment",
        "place",
        "device"
    ],
    "sg:website":"http://www.namcoarcade.com",
    "wof:name":"Cyberstation",
    "wof:placetype":"venue"
},
  "geometry": {"coordinates":[-120.481803,37.320165],"type":"Point"}
}