{
  "type": "Feature",
  "properties": {
    "addr:full":"1414 Yreka Ager Rd Yreka CA 96097",
    "addr:housenumber":"1414",
    "addr:postcode":"96097",
    "addr:street":"Ager Rd",
    "iso:country":"US",
    "sg:address":"1414 Yreka Ager Rd",
    "sg:city":"Yreka",
    "sg:classifiers":[
        {
            "category":"Organizations",
            "subcategory":"Religious Organization",
            "type":"Services"
        }
    ],
    "sg:phone":"+1 530 842 2825",
    "sg:postcode":"96097",
    "sg:province":"CA",
    "sg:tags":[
        "church"
    ],
    "wof:name":"Jehovah's Witnesses",
    "wof:placetype":"venue"
},
  "geometry": {"coordinates":[-122.586139,41.744052],"type":"Point"}
}