{
  "type": "Feature",
  "properties": {
    "iso:country":"US",
    "sg:address":"4052 Marron St",
    "sg:city":"San Diego",
    "sg:classifiers":[
        {
            "category":"Retail",
            "subcategory":"Repair Shop",
            "type":"Services"
        }
    ],
    "sg:phone":"+1 619 286 7932",
    "sg:postcode":"92115",
    "sg:province":"CA",
    "sg:tags":[
        "related"
    ],
    "wof:name":"Rosehill Dental Svc",
    "wof:placetype":"venue"
},
  "geometry": {"coordinates":[-117.06589700000001,32.748714],"type":"Point"}
}