{
  "type": "Feature",
  "properties": {
    "addr:full":"41111 Rd 128 Orosi CA 93647",
    "addr:postcode":"41111;93647",
    "addr:street":"Rd 128",
    "iso:country":"US",
    "sg:address":"41111 Rd 128",
    "sg:city":"Orosi",
    "sg:classifiers":[
        {
            "category":"Autos & Motor Vehicles",
            "subcategory":"Fuel & Gas Station",
            "type":"Retail Goods"
        }
    ],
    "sg:phone":"+1 559 528 6424",
    "sg:postcode":"93647",
    "sg:province":"CA",
    "sg:tags":[
        "oil"
    ],
    "wof:name":"Leon Service Station",
    "wof:placetype":"venue"
},
  "geometry": {"coordinates":[-119.28691000000001,36.537422],"type":"Point"}
}