{
  "type": "Feature",
  "properties": {
    "addr:full":"2650 Ione St Sacramento CA 95821",
    "addr:housenumber":"2650",
    "addr:postcode":"95821",
    "addr:street":"Ione St",
    "iso:country":"US",
    "sg:address":"2650 Ione St",
    "sg:city":"Sacramento",
    "sg:classifiers":[
        {
            "category":"Banks & Credit Unions",
            "subcategory":"Investment Brokerage",
            "type":"Services"
        }
    ],
    "sg:phone":"+1 916 486 9717",
    "sg:postcode":"95821",
    "sg:province":"CA",
    "sg:tags":[
        "trust"
    ],
    "wof:name":"Trust Of Gibsox",
    "wof:placetype":"venue"
},
  "geometry": {"coordinates":[-121.371201,38.613022],"type":"Point"}
}