{
  "type": "Feature",
  "properties": {
    "iso:country":"US",
    "sg:address":"8852 Washington Blvd",
    "sg:city":"Pico Rivera",
    "sg:classifiers":[
        {
            "category":"Coffee & Tea",
            "type":"Food & Drink"
        },
        {
            "category":"Shopping",
            "subcategory":"Books",
            "type":"Retail Goods"
        }
    ],
    "sg:phone":"+1 562 942 9919",
    "sg:postcode":"90660",
    "sg:province":"CA",
    "sg:tags":[
        "mags",
        "video",
        "books",
        "music"
    ],
    "sg:website":"www.borders.com",
    "wof:name":"Borders",
    "wof:placetype":"venue"
},
  "geometry": {"coordinates":[-118.098876,33.984114],"type":"Point"}
}