{
  "type": "Feature",
  "properties": {
    "iso:country":"US",
    "sg:address":"3174 Noreen Way",
    "sg:city":"Oceanside",
    "sg:classifiers":[
        {
            "category":"Professional",
            "subcategory":"Business Services",
            "type":"Services"
        }
    ],
    "sg:phone":"+1 760 721 7658",
    "sg:postcode":"92054",
    "sg:province":"CA",
    "sg:tags":[
        "interior",
        "consultant",
        "design",
        "decorator"
    ],
    "wof:name":"J Y Designs",
    "wof:placetype":"venue"
},
  "geometry": {"coordinates":[-117.342477,33.212913],"type":"Point"}
}