{
  "type": "Feature",
  "properties": {
    "addr:full":"1014 Pine St Ste A San Francisco CA 94109",
    "addr:housenumber":"1014",
    "addr:postcode":"94109",
    "addr:street":"Pine St Ste A",
    "iso:country":"US",
    "sg:address":"1014 Pine St Ste A",
    "sg:city":"San Francisco",
    "sg:classifiers":[
        {
            "category":"Personal",
            "type":"Services"
        },
        {
            "category":"Retail",
            "subcategory":"Laundry & Dry Cleaning",
            "type":"Services"
        }
    ],
    "sg:phone":"+1 415 346 0500",
    "sg:postcode":"94109",
    "sg:province":"CA",
    "sg:tags":[
        "sewing",
        "alteration"
    ],
    "wof:name":"HLP Dry Cleaner",
    "wof:placetype":"venue"
},
  "geometry": {"coordinates":[-122.41261799999999,37.790763],"type":"Point"}
}