{
  "type": "Feature",
  "properties": {
    "addr:full":"9122 Glenoaks Blvd Sun Valley CA 91352",
    "addr:housenumber":"9122",
    "addr:postcode":"91352",
    "addr:street":"Glenoaks Blvd",
    "iso:country":"US",
    "sg:address":"9122 Glenoaks Blvd",
    "sg:city":"Sun Valley",
    "sg:classifiers":[
        {
            "category":"Freight",
            "type":"Transportation"
        }
    ],
    "sg:phone":"+1 818 252 6400",
    "sg:postcode":"91352",
    "sg:province":"CA",
    "sg:tags":[
        "operator",
        "trucking"
    ],
    "wof:name":"Relibale Carries",
    "wof:placetype":"venue"
},
  "geometry": {"coordinates":[-118.372564,34.235722],"type":"Point"}
}