{
  "type": "Feature",
  "properties": {
    "iso:country":"US",
    "sg:address":"26 Via Candelaria",
    "sg:city":"Trabuco Canyon",
    "sg:classifiers":[
        {
            "category":"Manufacturing",
            "subcategory":"Toys & Sporting Goods",
            "type":"Manufacturing & Wholesale Goods"
        }
    ],
    "sg:phone":"+1 949 589 4681",
    "sg:postcode":"92679",
    "sg:province":"CA",
    "sg:tags":[
        "mfg"
    ],
    "wof:name":"N Rock Sports",
    "wof:placetype":"venue"
},
  "geometry": {"coordinates":[-117.587851,33.620818],"type":"Point"}
}