{
  "type": "Feature",
  "properties": {
    "iso:country":"US",
    "sg:address":"12105 Garden Grove Blvd",
    "sg:city":"Garden Grove",
    "sg:classifiers":[
        {
            "category":"Wholesale",
            "subcategory":"Auto Parts",
            "type":"Manufacturing & Wholesale Goods"
        }
    ],
    "sg:phone":"+1 714 636 8189",
    "sg:postcode":"92843",
    "sg:province":"CA",
    "sg:tags":[
        "automobile"
    ],
    "wof:name":"Auto Mechanic Tools",
    "wof:placetype":"venue"
},
  "geometry": {"coordinates":[-117.922746,33.774439],"type":"Point"}
}