{
  "type": "Feature",
  "properties": {
    "addr:full":"30 Corporate Park Irvine CA 92606",
    "addr:housenumber":"30",
    "addr:postcode":"92606",
    "addr:street":"Corporate Park",
    "iso:country":"US",
    "sg:address":"30 Corporate Park",
    "sg:city":"Irvine",
    "sg:classifiers":[
        {
            "category":"Professional",
            "subcategory":"Research",
            "type":"Services"
        }
    ],
    "sg:phone":"+1 949 724 1474",
    "sg:postcode":"92606",
    "sg:province":"CA",
    "sg:tags":[
        "environmental",
        "ecological"
    ],
    "wof:name":"AAA Guaranteed Property Insp",
    "wof:placetype":"venue"
},
  "geometry": {"coordinates":[-117.82552800000001,33.691767],"type":"Point"}
}