{
  "type": "Feature",
  "properties": {
    "addr:full":"919 Cam Ramon Danville CA 94526",
    "addr:housenumber":"919",
    "addr:postcode":"94526",
    "addr:street":"Cam Ramon",
    "iso:country":"US",
    "sg:address":"919 Cam Ramon",
    "sg:city":"Danville",
    "sg:classifiers":[
        {
            "category":"Social Services",
            "subcategory":"Child Care",
            "type":"Services"
        }
    ],
    "sg:phone":"+1 925 838 7434",
    "sg:postcode":"94526",
    "sg:province":"CA",
    "sg:website":"www.danmont.com",
    "wof:name":"Danville Montessori School",
    "wof:placetype":"venue"
},
  "geometry": {"coordinates":[-121.987562,37.800478],"type":"Point"}
}