{
  "type": "Feature",
  "properties": {
    "iso:country":"US",
    "sg:address":"12424 Old Home Ct",
    "sg:city":"Columbia",
    "sg:classifiers":[
        {
            "category":"Building & Trades",
            "subcategory":"Construction",
            "type":"Services"
        }
    ],
    "sg:phone":"+1 209 588 0209",
    "sg:postcode":"95310",
    "sg:province":"CA",
    "sg:tags":[
        "excavating",
        "contractor"
    ],
    "wof:name":"Columbia Mechanical & General",
    "wof:placetype":"venue"
},
  "geometry": {"coordinates":[-120.37219899999999,38.04109],"type":"Point"}
}