{
  "type": "Feature",
  "properties": {
    "addr:full":"511 Irving St San Francisco CA 94122",
    "addr:housenumber":"511",
    "addr:postcode":"94122",
    "addr:street":"Irving St",
    "iso:country":"US",
    "sg:address":"511 Irving St",
    "sg:city":"San Francisco",
    "sg:classifiers":[
        {
            "category":"Restaurant",
            "type":"Food & Drink"
        }
    ],
    "sg:menulink":"http://www.allmenus.com/ca/san-francisco/275856-lavash/menu/",
    "sg:phone":"+1 415 664 5555",
    "sg:postcode":"94122",
    "sg:province":"CA",
    "sg:tags":[
        "middle",
        "eastern"
    ],
    "wof:name":"Lavash",
    "wof:placetype":"venue"
},
  "geometry": {"coordinates":[-122.46328699999999,37.764053],"type":"Point"}
}