{
  "type": "Feature",
  "properties": {
    "iso:country":"US",
    "sg:address":"607 19th St",
    "sg:city":"Bakersfield",
    "sg:classifiers":[
        {
            "category":"Organizations",
            "subcategory":"Labor Organization",
            "type":"Services"
        }
    ],
    "sg:phone":"+1 661 322 4023",
    "sg:postcode":"93301",
    "sg:province":"CA",
    "wof:name":"Paper Allied-Ind Chemical",
    "wof:placetype":"venue"
},
  "geometry": {"coordinates":[-119.009161,35.376266],"type":"Point"}
}