{
  "type": "Feature",
  "properties": {
    "iso:country":"US",
    "sg:address":"3366 Mira Vista Cir",
    "sg:city":"San Jose",
    "sg:classifiers":[
        {
            "category":"Professional",
            "type":"Services"
        }
    ],
    "sg:phone":"+1 408 923 3500",
    "sg:postcode":"95132",
    "sg:province":"CA",
    "sg:tags":[
        "establishment"
    ],
    "wof:name":"General American Assoc",
    "wof:placetype":"venue"
},
  "geometry": {"coordinates":[-121.840552,37.391728],"type":"Point"}
}