{
  "type": "Feature",
  "properties": {
    "iso:country":"US",
    "sg:address":"28126 Sunwood Pl",
    "sg:city":"Menifee",
    "sg:classifiers":[
        {
            "category":"Professional",
            "subcategory":"Management & Consulting",
            "type":"Services"
        }
    ],
    "sg:phone":"+1 951 672 3912",
    "sg:postcode":"92584",
    "sg:province":"CA",
    "sg:tags":[
        "consultant"
    ],
    "wof:name":"B L J Industries",
    "wof:placetype":"venue"
},
  "geometry": {"coordinates":[-117.169347,33.667574],"type":"Point"}
}