{
  "type": "Feature",
  "properties": {
    "addr:full":"874 Gaspar Vis San Jose CA 95126",
    "addr:housenumber":"874",
    "addr:postcode":"95126",
    "addr:street":"Gaspar Vis",
    "iso:country":"US",
    "sg:address":"874 Gaspar Vis",
    "sg:city":"San Jose",
    "sg:classifiers":[
        {
            "category":"Professional",
            "subcategory":"Lawyer & Legal Services",
            "type":"Services"
        }
    ],
    "sg:phone":"+1 408 286 2071",
    "sg:postcode":"95126",
    "sg:province":"CA",
    "sg:website":"www.kbhome.com",
    "wof:name":"KB Home South Bay Division",
    "wof:placetype":"venue"
},
  "geometry": {"coordinates":[-121.903462,37.3216],"type":"Point"}
}