{
  "type": "Feature",
  "properties": {
    "iso:country":"US",
    "sg:address":"502 Pollasky Ave",
    "sg:city":"Clovis",
    "sg:classifiers":[
        {
            "category":"Shopping",
            "subcategory":"Jewelry",
            "type":"Retail Goods"
        }
    ],
    "sg:phone":"+1 559 298 6992",
    "sg:postcode":"93612",
    "sg:province":"CA",
    "sg:tags":[
        "jeweler"
    ],
    "wof:name":"Jackson Jewelry",
    "wof:placetype":"venue"
},
  "geometry": {"coordinates":[-119.702076,36.823053],"type":"Point"}
}