{
  "type": "Feature",
  "properties": {
    "iso:country":"US",
    "sg:address":"17911 Bushard St",
    "sg:city":"Fountain Valley",
    "sg:classifiers":[
        {
            "category":"Real Estate",
            "subcategory":"Real Estate Operator",
            "type":"Services"
        }
    ],
    "sg:phone":"+1 714 963 9660",
    "sg:postcode":"92708",
    "sg:province":"CA",
    "sg:tags":[
        "apartment"
    ],
    "wof:name":"Jasmine Senior Apartments At Founders Village The",
    "wof:placetype":"venue"
},
  "geometry": {"coordinates":[-117.963123,33.700676],"type":"Point"}
}