{
  "type": "Feature",
  "properties": {
    "addr:full":"5601 Oberlin Dr San Diego CA 92121",
    "addr:housenumber":"5601",
    "addr:postcode":"92121",
    "addr:street":"Oberlin Dr",
    "iso:country":"US",
    "sg:address":"5601 Oberlin Dr",
    "sg:city":"San Diego",
    "sg:classifiers":[
        {
            "category":"Health Services",
            "subcategory":"Medical Lab",
            "type":"Services"
        }
    ],
    "sg:phone":"+1 858 455 1221",
    "sg:postcode":"92121",
    "sg:province":"CA",
    "sg:tags":[
        "laboratory",
        "clinical",
        "testing"
    ],
    "wof:name":"Laboratory Corporation America",
    "wof:placetype":"venue"
},
  "geometry": {"coordinates":[-117.199113,32.891527],"type":"Point"}
}