{
  "type": "Feature",
  "properties": {
    "iso:country":"US",
    "sg:address":"5521 Maine Dr",
    "sg:city":"Concord",
    "sg:classifiers":[
        {
            "category":"Professional",
            "subcategory":"Research",
            "type":"Services"
        },
        {
            "category":"Utilities",
            "subcategory":"Refuse",
            "type":"Services"
        }
    ],
    "sg:phone":"+1 925 672 5380",
    "sg:postcode":"94521",
    "sg:province":"CA",
    "sg:tags":[
        "ecological",
        "environmental",
        "consulting",
        "system",
        "business"
    ],
    "wof:name":"George Recycling Service Co",
    "wof:placetype":"venue"
},
  "geometry": {"coordinates":[-121.955798,37.943736],"type":"Point"}
}