{
  "type": "Feature",
  "properties": {
    "addr:full":"363 Laurelwood Rd Santa Clara CA 95054",
    "addr:housenumber":"363",
    "addr:postcode":"95054",
    "addr:street":"Laurelwood Rd",
    "iso:country":"US",
    "sg:address":"363 Laurelwood Rd",
    "sg:city":"Santa Clara",
    "sg:classifiers":[
        {
            "category":"Wholesale",
            "subcategory":"Painting Supplies",
            "type":"Manufacturing & Wholesale Goods"
        }
    ],
    "sg:phone":"+1 408 969 0310",
    "sg:postcode":"95054",
    "sg:province":"CA",
    "sg:tags":[
        "equipment",
        "painter"
    ],
    "wof:name":"Accurate Metal Finishing",
    "wof:placetype":"venue"
},
  "geometry": {"coordinates":[-121.941143,37.382175],"type":"Point"}
}