{
  "type": "Feature",
  "properties": {
    "addr:full":"19384 Elena Ln Jamul CA 91935",
    "addr:housenumber":"19384",
    "addr:postcode":"91935",
    "addr:street":"Elena Ln",
    "iso:country":"US",
    "sg:address":"19384 Elena Ln",
    "sg:city":"Jamul",
    "sg:classifiers":[
        {
            "category":"Home & Garden",
            "subcategory":"Carpets & Floor Coverings",
            "type":"Retail Goods"
        }
    ],
    "sg:phone":"+1 619 468 9074",
    "sg:postcode":"91935",
    "sg:province":"CA",
    "wof:name":"Arias Floor Covering",
    "wof:placetype":"venue"
},
  "geometry": {"coordinates":[-116.732681,32.678057],"type":"Point"}
}