{
  "type": "Feature",
  "properties": {
    "addr:full":"2524 Fender Ave Fullerton CA 92831",
    "addr:housenumber":"2524",
    "addr:postcode":"92831",
    "addr:street":"Fender Ave",
    "iso:country":"US",
    "sg:address":"2524 Fender Ave",
    "sg:city":"Fullerton",
    "sg:classifiers":[
        {
            "category":"Manufacturing",
            "subcategory":"Wood Products",
            "type":"Manufacturing & Wholesale Goods"
        }
    ],
    "sg:phone":"+1 714 526 4260",
    "sg:postcode":"92831",
    "sg:province":"CA",
    "sg:tags":[
        "mfg"
    ],
    "wof:name":"Mueller Stake House",
    "wof:placetype":"venue"
},
  "geometry": {"coordinates":[-117.88106399999999,33.868092],"type":"Point"}
}