{
  "type": "Feature",
  "properties": {
    "addr:full":"300 Laurellen Rd Marysville CA 95901",
    "addr:housenumber":"300",
    "addr:postcode":"95901",
    "addr:street":"Laurellen Rd",
    "iso:country":"US",
    "sg:address":"300 Laurellen Rd",
    "sg:city":"Marysville",
    "sg:classifiers":[
        {
            "category":"Building & Trades",
            "subcategory":"Construction",
            "type":"Services"
        }
    ],
    "sg:phone":"+1 530 742 0095",
    "sg:postcode":"95901",
    "sg:province":"CA",
    "sg:tags":[
        "excavating",
        "contractor"
    ],
    "wof:name":"Bob Kluender Backhoe Svc",
    "wof:placetype":"venue"
},
  "geometry": {"coordinates":[-121.60725600000001,39.169564],"type":"Point"}
}