{
  "type": "Feature",
  "properties": {
    "addr:full":"3008 N E St San Bernardino CA 92405",
    "addr:housenumber":"3008",
    "addr:postcode":"92405",
    "addr:street":"N E St",
    "iso:country":"US",
    "sg:address":"3008 N E St",
    "sg:city":"San Bernardino",
    "sg:classifiers":[
        {
            "category":"Food & Beverages",
            "subcategory":"Groceries & Convenience Stores",
            "type":"Retail Goods"
        }
    ],
    "sg:phone":"+1 909 883 0937",
    "sg:postcode":"92405",
    "sg:province":"CA",
    "wof:name":"KAYO Oil Co",
    "wof:placetype":"venue"
},
  "geometry": {"coordinates":[-117.294178,34.147679],"type":"Point"}
}