{
  "type": "Feature",
  "properties": {
    "addr:full":"2801 Guirado St Los Angeles CA 90023",
    "addr:housenumber":"2801",
    "addr:postcode":"90023",
    "addr:street":"Guirado St",
    "iso:country":"US",
    "sg:address":"2801 Guirado St",
    "sg:city":"Los Angeles",
    "sg:classifiers":[
        {
            "category":"Freight",
            "type":"Transportation"
        }
    ],
    "sg:phone":"+1 323 269 5535",
    "sg:postcode":"90023",
    "sg:province":"CA",
    "sg:tags":[
        "operator",
        "local",
        "trucking"
    ],
    "wof:name":"Luis Espinoza Trucking",
    "wof:placetype":"venue"
},
  "geometry": {"coordinates":[-118.207435,34.032827],"type":"Point"}
}