{
  "type": "Feature",
  "properties": {
    "addr:full":"3855 State St Santa Barbara CA 93105",
    "addr:housenumber":"3855",
    "addr:postcode":"93105",
    "addr:street":"State St",
    "iso:country":"US",
    "sg:address":"3855 State St",
    "sg:city":"Santa Barbara",
    "sg:classifiers":[
        {
            "category":"Food & Beverages",
            "subcategory":"Groceries & Convenience Stores",
            "type":"Retail Goods"
        }
    ],
    "sg:phone":"+1 805 687 5611",
    "sg:postcode":"93105",
    "sg:province":"CA",
    "sg:tags":[
        "grocer"
    ],
    "wof:name":"Vons Co",
    "wof:placetype":"venue"
},
  "geometry": {"coordinates":[-119.746718,34.44043],"type":"Point"}
}