{
  "type": "Feature",
  "properties": {
    "addr:full":"1300 W Maple Ave Lompoc CA 93436",
    "addr:housenumber":"1300",
    "addr:postcode":"93436",
    "addr:street":"W Maple Ave",
    "iso:country":"US",
    "sg:address":"1300 W Maple Ave",
    "sg:city":"Lompoc",
    "sg:classifiers":[
        {
            "category":"Organizations",
            "subcategory":"Religious Organization",
            "type":"Services"
        }
    ],
    "sg:phone":"+1 805 736 0615",
    "sg:postcode":"93436",
    "sg:province":"CA",
    "sg:tags":[
        "church"
    ],
    "wof:name":"New Beginning Missionary",
    "wof:placetype":"venue"
},
  "geometry": {"coordinates":[-120.47302999999999,34.645554],"type":"Point"}
}