{
  "type": "Feature",
  "properties": {
    "iso:country":"US",
    "sg:address":"1010 Overlook Ridge Rd",
    "sg:city":"Diamond Bar",
    "sg:classifiers":[
        {
            "category":"Organizations",
            "subcategory":"Community Association",
            "type":"Services"
        }
    ],
    "sg:phone":"+1 909 860 3418",
    "sg:postcode":"91765",
    "sg:province":"CA",
    "sg:tags":[
        "club"
    ],
    "wof:name":"Deane Homes Swim Club",
    "wof:placetype":"venue"
},
  "geometry": {"coordinates":[-117.80251,34.036394],"type":"Point"}
}