{
  "type": "Feature",
  "properties": {
    "addr:full":"700 Ballantyne St El Cajon CA 92021",
    "addr:housenumber":"700",
    "addr:postcode":"92021",
    "addr:street":"Ballantyne St",
    "iso:country":"US",
    "sg:address":"700 Ballantyne St",
    "sg:city":"El Cajon",
    "sg:classifiers":[
        {
            "category":"Shopping",
            "subcategory":"Discount & Variety Stores",
            "type":"Retail Goods"
        }
    ],
    "sg:phone":"+1 619 334 6431",
    "sg:postcode":"92021",
    "sg:province":"CA",
    "sg:tags":[
        "merchandise",
        "general"
    ],
    "wof:name":"Family Friendly Shop",
    "wof:placetype":"venue"
},
  "geometry": {"coordinates":[-116.958226,32.804291],"type":"Point"}
}