{
  "type": "Feature",
  "properties": {
    "iso:country":"US",
    "sg:address":"9612 Dale Ave",
    "sg:city":"Spring Valley",
    "sg:classifiers":[
        {
            "category":"Personal",
            "subcategory":"Beauty Salon",
            "type":"Services"
        }
    ],
    "sg:phone":"+1 619 462 5488",
    "sg:postcode":"91977",
    "sg:province":"CA",
    "wof:name":"Gwen's Untouchable Hair Design",
    "wof:placetype":"venue"
},
  "geometry": {"coordinates":[-116.988659,32.745641],"type":"Point"}
}