{
  "type": "Feature",
  "properties": {
    "iso:country":"US",
    "sg:address":"8133 Vineland Ave",
    "sg:city":"Sun Valley",
    "sg:classifiers":[
        {
            "category":"Recreation",
            "type":"Entertainment"
        }
    ],
    "sg:phone":"+1 818 767 7134",
    "sg:postcode":"91352",
    "sg:province":"CA",
    "sg:tags":[
        "parks"
    ],
    "wof:name":"Sun Valley Park Office",
    "wof:placetype":"venue"
},
  "geometry": {"coordinates":[-118.370412,34.218729],"type":"Point"}
}