{
  "type": "Feature",
  "properties": {
    "addr:full":"2530 Berryessa Rd #21 San Jose CA 95132",
    "addr:housenumber":"2530",
    "addr:postcode":"95132",
    "addr:street":"Berryessa Rd # 21 San Jose",
    "iso:country":"US",
    "sg:address":"2530 Berryessa Rd #21",
    "sg:city":"San Jose",
    "sg:classifiers":[
        {
            "category":"Real Estate",
            "subcategory":"Real Estate Services",
            "type":"Services"
        },
        {
            "category":"Real Estate",
            "subcategory":"Real Estate Agent",
            "type":"Services"
        }
    ],
    "sg:phone":"+1 408 691 4204",
    "sg:postcode":"95132",
    "sg:province":"CA",
    "sg:tags":[
        "management",
        "property"
    ],
    "sg:website":"www.realestaterain.com",
    "wof:name":"Edmund Yue - Rainmaker Properties",
    "wof:placetype":"venue"
},
  "geometry": {"coordinates":[-121.859199,37.387799],"type":"Point"}
}