{
  "type": "Feature",
  "properties": {
    "iso:country":"US",
    "sg:address":"980 9th St",
    "sg:city":"Sacramento",
    "sg:classifiers":[
        {
            "category":"Professional",
            "type":"Services"
        }
    ],
    "sg:phone":"+1 916 414 9531",
    "sg:postcode":"95814",
    "sg:province":"CA",
    "sg:tags":[
        "establishment"
    ],
    "wof:name":"Bid Com",
    "wof:placetype":"venue"
},
  "geometry": {"coordinates":[-121.494581,38.581584],"type":"Point"}
}