{
  "type": "Feature",
  "properties": {
    "addr:full":"5402 Q St Sacramento CA 95819",
    "addr:housenumber":"5402",
    "addr:postcode":"95819",
    "addr:street":"Q St",
    "iso:country":"US",
    "sg:address":"5402 Q St",
    "sg:city":"Sacramento",
    "sg:classifiers":[
        {
            "category":"Retail",
            "subcategory":"Veterinary Services",
            "type":"Services"
        }
    ],
    "sg:phone":"+1 916 457 8011",
    "sg:postcode":"95819",
    "sg:province":"CA",
    "sg:tags":[
        "specialty"
    ],
    "wof:name":"Helens Animal Rescue Team",
    "wof:placetype":"venue"
},
  "geometry": {"coordinates":[-121.44152200000001,38.556873],"type":"Point"}
}