{
  "type": "Feature",
  "properties": {
    "iso:country":"US",
    "sg:address":"1440 Rodriguez St",
    "sg:city":"Santa Cruz",
    "sg:classifiers":[
        {
            "category":"Wholesale",
            "subcategory":"Toys & Hobbies",
            "type":"Manufacturing & Wholesale Goods"
        }
    ],
    "sg:phone":"+1 831 476 4093",
    "sg:postcode":"95062",
    "sg:province":"CA",
    "wof:name":"JM Company",
    "wof:placetype":"venue"
},
  "geometry": {"coordinates":[-121.982941,36.982265],"type":"Point"}
}