{
  "type": "Feature",
  "properties": {
    "addr:full":"3278 Wilshire Blvd Los Angeles CA 90010",
    "addr:housenumber":"3278",
    "addr:postcode":"90010",
    "addr:street":"Wilshire Blvd",
    "iso:country":"US",
    "sg:address":"3278 Wilshire Blvd",
    "sg:city":"Los Angeles",
    "sg:classifiers":[
        {
            "category":"Real Estate",
            "subcategory":"Real Estate Agent",
            "type":"Services"
        }
    ],
    "sg:phone":"+1 213 252 9222",
    "sg:postcode":"90010",
    "sg:province":"CA",
    "wof:name":"Mc Fane & Forrest",
    "wof:placetype":"venue"
},
  "geometry": {"coordinates":[-118.293538,34.061708],"type":"Point"}
}