{
  "type": "Feature",
  "properties": {
    "addr:full":"2366 Stanwell Cir Concord CA 94520",
    "addr:housenumber":"2366",
    "addr:postcode":"94520",
    "addr:street":"Stanwell Cir",
    "iso:country":"US",
    "sg:address":"2366 Stanwell Cir",
    "sg:city":"Concord",
    "sg:classifiers":[
        {
            "category":"Government",
            "subcategory":"Office",
            "type":"Public Place"
        }
    ],
    "sg:phone":"+1 925 646 5521",
    "sg:postcode":"94520",
    "sg:province":"CA",
    "sg:tags":[
        "mail",
        "printing"
    ],
    "wof:name":"General Services",
    "wof:placetype":"venue"
},
  "geometry": {"coordinates":[-122.048648,37.981783],"type":"Point"}
}