{
  "type": "Feature",
  "properties": {
    "addr:full":"610 Glasgow Cir Danville CA 94526",
    "addr:housenumber":"610",
    "addr:postcode":"94526",
    "addr:street":"Glasgow Cir",
    "iso:country":"US",
    "sg:address":"610 Glasgow Cir",
    "sg:city":"Danville",
    "sg:classifiers":[
        {
            "category":"Shopping",
            "subcategory":"Gifts & Souvenirs",
            "type":"Retail Goods"
        }
    ],
    "sg:phone":"+1 925 820 5488",
    "sg:postcode":"94526",
    "sg:province":"CA",
    "sg:tags":[
        "greeting",
        "card"
    ],
    "wof:name":"Yard Cards By Erica",
    "wof:placetype":"venue"
},
  "geometry": {"coordinates":[-121.96462099999999,37.817525],"type":"Point"}
}