{
  "type": "Feature",
  "properties": {
    "addr:full":"425 S. Fair Oaks Ave Pasadena CA 91105",
    "addr:housenumber":"425",
    "addr:postcode":"91105",
    "addr:street":"S. Fair Oaks Ave",
    "iso:country":"US",
    "sg:address":"425 S. Fair Oaks Ave",
    "sg:city":"Pasadena",
    "sg:classifiers":[
        {
            "category":"Health Services",
            "subcategory":"Clinic",
            "type":"Services"
        },
        {
            "category":"Personal",
            "subcategory":"Skin Care",
            "type":"Services"
        }
    ],
    "sg:phone":"+1 626 449 8873",
    "sg:postcode":"91105",
    "sg:province":"CA",
    "sg:tags":[
        "spa",
        "medical"
    ],
    "sg:website":"www.skindeeplaser.com/",
    "wof:name":"Skin Deep Laser Medspa",
    "wof:placetype":"venue"
},
  "geometry": {"coordinates":[-118.15038800000001,34.138058],"type":"Point"}
}