{
  "type": "Feature",
  "properties": {
    "iso:country":"US",
    "sg:address":"10763 Bell Ct",
    "sg:city":"Rancho Cucamonga",
    "sg:classifiers":[
        {
            "category":"Home & Garden",
            "subcategory":"Carpets & Floor Coverings",
            "type":"Retail Goods"
        }
    ],
    "sg:phone":"+1 909 941 8305",
    "sg:postcode":"91730",
    "sg:province":"CA",
    "sg:tags":[
        "dealer",
        "rug"
    ],
    "wof:name":"Continental Flooring Inc",
    "wof:placetype":"venue"
},
  "geometry": {"coordinates":[-117.569806,34.096503],"type":"Point"}
}