{
  "type": "Feature",
  "properties": {
    "iso:country":"US",
    "sg:address":"2376 Glendale Ave",
    "sg:city":"Los Angeles",
    "sg:classifiers":[
        {
            "category":"Personal",
            "type":"Services"
        }
    ],
    "sg:phone":"+1 951 505 5424",
    "sg:postcode":"90039",
    "sg:province":"CA",
    "sg:tags":[
        "party",
        "planning",
        "event",
        "wedding"
    ],
    "sg:website":"www.sharlenegriffith.com",
    "wof:name":"Sharlene Griffith",
    "wof:placetype":"venue"
},
  "geometry": {"coordinates":[-118.25898,34.099477],"type":"Point"}
}