{
  "type": "Feature",
  "properties": {
    "addr:full":"624 Opal Ave Ventura CA 93004",
    "addr:housenumber":"624",
    "addr:postcode":"93004",
    "addr:street":"Opal Ave",
    "iso:country":"US",
    "sg:address":"624 Opal Ave",
    "sg:city":"Ventura",
    "sg:classifiers":[
        {
            "category":"Professional",
            "type":"Services"
        }
    ],
    "sg:phone":"+1 805 647 1224",
    "sg:postcode":"93004",
    "sg:province":"CA",
    "wof:name":"Ronald W Derrico",
    "wof:placetype":"venue"
},
  "geometry": {"coordinates":[-119.18623100000001,34.274268],"type":"Point"}
}