{
  "type": "Feature",
  "properties": {
    "iso:country":"US",
    "sg:address":"6909 Ridge Manor Ave",
    "sg:city":"San Diego",
    "sg:classifiers":[
        {
            "category":"Wholesale",
            "subcategory":"Groceries",
            "type":"Manufacturing & Wholesale Goods"
        }
    ],
    "sg:phone":"+1 619 582 2849",
    "sg:postcode":"92120",
    "sg:province":"CA",
    "wof:name":"T A Distributing",
    "wof:placetype":"venue"
},
  "geometry": {"coordinates":[-117.059791,32.797246],"type":"Point"}
}