{
  "type": "Feature",
  "properties": {
    "addr:full":"23832 Rockfield Boulevard Lake Forest CA 92630",
    "addr:housenumber":"23832",
    "addr:postcode":"92630",
    "addr:street":"Rockfield Boulevard",
    "iso:country":"US",
    "sg:address":"23832 Rockfield Boulevard",
    "sg:city":"Lake Forest",
    "sg:classifiers":[
        {
            "category":"Banks & Credit Unions",
            "subcategory":"Financial Services",
            "type":"Services"
        }
    ],
    "sg:phone":"+1 949 458 7342",
    "sg:postcode":"92630",
    "sg:province":"CA",
    "sg:tags":[
        "broker",
        "mortgage"
    ],
    "wof:name":"Stonefield Mortgage",
    "wof:placetype":"venue"
},
  "geometry": {"coordinates":[-117.714586,33.626617],"type":"Point"}
}