{
  "type": "Feature",
  "properties": {
    "iso:country":"US",
    "sg:address":"5005 Florence Avenue",
    "sg:city":"Bell",
    "sg:classifiers":[
        {
            "category":"Building & Trades",
            "subcategory":"Locksmith",
            "type":"Services"
        }
    ],
    "sg:phone":"+1 323 773 4921",
    "sg:postcode":"90201",
    "sg:province":"CA",
    "sg:tags":[
        "key"
    ],
    "wof:name":"Wells Lock & Key",
    "wof:placetype":"venue"
},
  "geometry": {"coordinates":[-118.177558,33.969325],"type":"Point"}
}