{
  "type": "Feature",
  "properties": {
    "addr:full":"5124 Douglas Fir Rd Calabasas CA 91302",
    "addr:housenumber":"5124",
    "addr:postcode":"91302",
    "addr:street":"Douglas Fir Rd",
    "iso:country":"US",
    "sg:address":"5124 Douglas Fir Rd",
    "sg:city":"Calabasas",
    "sg:classifiers":[
        {
            "category":"Retail",
            "subcategory":"Auto Repair",
            "type":"Services"
        }
    ],
    "sg:phone":"+1 818 222 7781",
    "sg:postcode":"91302",
    "sg:province":"CA",
    "wof:name":"Barnes Vince Automotive",
    "wof:placetype":"venue"
},
  "geometry": {"coordinates":[-118.648003,34.156601],"type":"Point"}
}