{
  "type": "Feature",
  "properties": {
    "iso:country":"US",
    "sg:address":"235 S Berendo St",
    "sg:city":"Los Angeles",
    "sg:classifiers":[
        {
            "category":"Real Estate",
            "subcategory":"Real Estate Operator",
            "type":"Services"
        }
    ],
    "sg:phone":"+1 213 381 1782",
    "sg:postcode":"90004",
    "sg:province":"CA",
    "sg:tags":[
        "apartment"
    ],
    "wof:name":"Berendo Portals 2",
    "wof:placetype":"venue"
},
  "geometry": {"coordinates":[-118.293999,34.070202],"type":"Point"}
}