{
  "type": "Feature",
  "properties": {
    "addr:full":"15437 Proctor Ave City Of Industry CA 91746",
    "addr:housenumber":"15437",
    "addr:postcode":"91746",
    "addr:street":"Proctor Ave",
    "iso:country":"US",
    "sg:address":"15437 Proctor Ave",
    "sg:city":"City Of Industry",
    "sg:classifiers":[
        {
            "category":"Shopping",
            "subcategory":"Hobbies, Toys, & Games",
            "type":"Retail Goods"
        }
    ],
    "sg:phone":"+1 626 618 0300",
    "sg:postcode":"91746",
    "sg:province":"CA",
    "sg:tags":[
        "model",
        "supply"
    ],
    "sg:website":"www.pacaeromodel.com",
    "wof:name":"Pacific Aeromodel Mfg",
    "wof:placetype":"venue"
},
  "geometry": {"coordinates":[-117.960025,34.022463],"type":"Point"}
}