{
  "type": "Feature",
  "properties": {
    "addr:full":"3590 Jefferson Blvd West Sacramento CA 95691",
    "addr:housenumber":"3590",
    "addr:postcode":"95691",
    "addr:street":"Jefferson Blvd",
    "iso:country":"US",
    "sg:address":"3590 Jefferson Blvd",
    "sg:city":"West Sacramento",
    "sg:classifiers":[
        {
            "category":"Building & Trades",
            "subcategory":"Landscaping Services",
            "type":"Services"
        }
    ],
    "sg:phone":"+1 916 372 7112",
    "sg:postcode":"95691",
    "sg:province":"CA",
    "sg:tags":[
        "lawn",
        "garden"
    ],
    "wof:name":"Capitol City Landscaping",
    "wof:placetype":"venue"
},
  "geometry": {"coordinates":[-121.556241,38.532502],"type":"Point"}
}