{
  "type": "Feature",
  "properties": {
    "iso:country":"US",
    "sg:address":"1355 S Acacia Ave",
    "sg:city":"Fullerton",
    "sg:classifiers":[
        {
            "category":"Wholesale",
            "subcategory":"Home Furnishings",
            "type":"Manufacturing & Wholesale Goods"
        }
    ],
    "sg:phone":"+1 714 635 7414",
    "sg:postcode":"92831",
    "sg:province":"CA",
    "wof:name":"Lees Carpets",
    "wof:placetype":"venue"
},
  "geometry": {"coordinates":[-117.89804100000001,33.856305],"type":"Point"}
}