{
  "type": "Feature",
  "properties": {
    "addr:full":"19651 Hesperian Blvd Hayward CA 94541",
    "addr:housenumber":"19651",
    "addr:postcode":"94541",
    "addr:street":"Hesperian Blvd",
    "iso:country":"US",
    "sg:address":"19651 Hesperian Blvd",
    "sg:city":"Hayward",
    "sg:classifiers":[
        {
            "category":"Juice Bar",
            "subcategory":"None",
            "type":"Food & Drink"
        }
    ],
    "sg:phone":"+1 510 265 1485",
    "sg:postcode":"94541",
    "sg:province":"CA",
    "sg:tags":[
        "smoothy"
    ],
    "sg:website":"www.jambajuice.com",
    "wof:name":"Jamba Juice",
    "wof:placetype":"venue"
},
  "geometry": {"coordinates":[-122.11991500000001,37.668476],"type":"Point"}
}