{
  "type": "Feature",
  "properties": {
    "iso:country":"US",
    "sg:address":"5419 Hollywood Blvd",
    "sg:city":"Los Angeles",
    "sg:classifiers":[
        {
            "category":"Arts & Performance",
            "subcategory":"Music",
            "type":"Entertainment"
        }
    ],
    "sg:phone":"+1 323 378 5852",
    "sg:postcode":"90027",
    "sg:province":"CA",
    "sg:tags":[
        "dj"
    ],
    "sg:website":"www.gavinwoodinc.com",
    "wof:name":"Gavin Wood Inc",
    "wof:placetype":"venue"
},
  "geometry": {"coordinates":[-118.30797,34.10176],"type":"Point"}
}