{
  "type": "Feature",
  "properties": {
    "iso:country":"US",
    "sg:address":"1610 Oak Park Blvd Ste 202",
    "sg:city":"Pleasant Hill",
    "sg:classifiers":[
        {
            "category":"Health Services",
            "subcategory":"Chiropractor",
            "type":"Services"
        }
    ],
    "sg:phone":"+1 925 943 2222",
    "sg:postcode":"94523",
    "sg:province":"CA",
    "wof:name":"Worrall Chiropratic",
    "wof:placetype":"venue"
},
  "geometry": {"coordinates":[-122.27721699999999,37.933466],"type":"Point"}
}