{
  "type": "Feature",
  "properties": {
    "addr:full":"5242 Laurel Canyon Blvd Valley Village CA 91607",
    "addr:housenumber":"5242",
    "addr:postcode":"91607",
    "addr:street":"Laurel Canyon Blvd",
    "iso:country":"US",
    "sg:address":"5242 Laurel Canyon Blvd",
    "sg:city":"Valley Village",
    "sg:classifiers":[
        {
            "category":"Professional",
            "subcategory":"Art Services",
            "type":"Services"
        }
    ],
    "sg:phone":"+1 818 766 1811",
    "sg:postcode":"91607",
    "sg:province":"CA",
    "sg:tags":[
        "graphic",
        "design"
    ],
    "sg:website":"www.intaglio.com",
    "wof:name":"Intaglio",
    "wof:placetype":"venue"
},
  "geometry": {"coordinates":[-118.396152,34.166089],"type":"Point"}
}