{
  "type": "Feature",
  "properties": {
    "addr:full":"45332 Co Rd 25 Woodland CA 95776",
    "addr:housenumber":"45332;25",
    "addr:postcode":"95776",
    "addr:street":"Co Rd",
    "iso:country":"US",
    "sg:address":"45332 Co Rd 25",
    "sg:city":"Woodland",
    "sg:classifiers":[
        {
            "category":"Real Estate",
            "subcategory":"Real Estate Agent",
            "type":"Services"
        }
    ],
    "sg:phone":"+1 530 662 6200",
    "sg:postcode":"95776",
    "sg:province":"CA",
    "wof:name":"Conaway Conservancy Group",
    "wof:placetype":"venue"
},
  "geometry": {"coordinates":[-121.683584,38.64773],"type":"Point"}
}