{
  "type": "Feature",
  "properties": {
    "iso:country":"US",
    "sg:address":"116 E Redwood Ave",
    "sg:city":"Fort Bragg",
    "sg:classifiers":[
        {
            "category":"Personal",
            "subcategory":"Beauty Salon",
            "type":"Services"
        }
    ],
    "sg:phone":"+1 707 964 3001",
    "sg:postcode":"95437",
    "sg:province":"CA",
    "sg:tags":[
        "manicuring"
    ],
    "wof:name":"My Beautiful Nails",
    "wof:placetype":"venue"
},
  "geometry": {"coordinates":[-123.805927,39.44422],"type":"Point"}
}