{
  "type": "Feature",
  "properties": {
    "addr:full":"445 N Escondido Blvd Escondido CA 92025",
    "addr:housenumber":"445",
    "addr:postcode":"92025",
    "addr:street":"N Escondido Blvd",
    "iso:country":"US",
    "sg:address":"445 N Escondido Blvd",
    "sg:city":"Escondido",
    "sg:classifiers":[
        {
            "category":"Restaurant",
            "type":"Food & Drink"
        }
    ],
    "sg:menulink":"http://www.allmenus.com/ca/oceanside-escondido/30639-chins-szechwan-cuisine/menu/",
    "sg:phone":"+1 760 480 4115",
    "sg:postcode":"92025",
    "sg:province":"CA",
    "sg:tags":[
        "asian",
        "chinese"
    ],
    "wof:name":"Chin's Szechwan Cuisine",
    "wof:placetype":"venue"
},
  "geometry": {"coordinates":[-117.086854,33.124058],"type":"Point"}
}