{
  "type": "Feature",
  "properties": {
    "iso:country":"US",
    "sg:address":"875 Island Dr",
    "sg:city":"Alameda",
    "sg:classifiers":[
        {
            "category":"Restaurant",
            "type":"Food & Drink"
        }
    ],
    "sg:phone":"+1 510 536 3200",
    "sg:postcode":"94502",
    "sg:province":"CA",
    "sg:tags":[
        "pizza"
    ],
    "wof:name":"Domino's Pizza",
    "wof:placetype":"venue"
},
  "geometry": {"coordinates":[-122.238998,37.738899],"type":"Point"}
}