{
  "type": "Feature",
  "properties": {
    "iso:country":"US",
    "sg:address":"350 Crazy Horse Canyon Rd",
    "sg:city":"Salinas",
    "sg:classifiers":[
        {
            "category":"Utilities",
            "subcategory":"Electric",
            "type":"Services"
        }
    ],
    "sg:phone":"+1 831 663 6145",
    "sg:postcode":"93907",
    "sg:province":"CA",
    "sg:tags":[
        "company"
    ],
    "wof:name":"Ogden Power Pacific Inc",
    "wof:placetype":"venue"
},
  "geometry": {"coordinates":[-121.623915,36.809365],"type":"Point"}
}