{
  "type": "Feature",
  "properties": {
    "addr:full":"11151 Trade Center Dr Rancho Cordova CA 95670",
    "addr:housenumber":"11151",
    "addr:postcode":"95670",
    "addr:street":"Trade Center Dr",
    "iso:country":"US",
    "sg:address":"11151 Trade Center Dr",
    "sg:city":"Rancho Cordova",
    "sg:classifiers":[
        {
            "category":"Wholesale",
            "subcategory":"Sporting Goods",
            "type":"Manufacturing & Wholesale Goods"
        }
    ],
    "sg:phone":"+1 916 638 6886",
    "sg:postcode":"95670",
    "sg:province":"CA",
    "sg:tags":[
        "salon",
        "tanning",
        "supply"
    ],
    "sg:website":"www.tanamerica.com",
    "wof:name":"Tan America",
    "wof:placetype":"venue"
},
  "geometry": {"coordinates":[-121.268671,38.603017],"type":"Point"}
}