{
  "type": "Feature",
  "properties": {
    "addr:full":"3825 Bell Avenue Bell CA 90201",
    "addr:housenumber":"3825",
    "addr:postcode":"90201",
    "addr:street":"Bell Avenue",
    "iso:country":"US",
    "sg:address":"3825 Bell Avenue",
    "sg:city":"Bell",
    "sg:classifiers":[
        {
            "category":"Education",
            "subcategory":"School",
            "type":"Public Place"
        }
    ],
    "sg:phone":"+1 323 560 1323",
    "sg:postcode":"90201",
    "sg:province":"CA",
    "sg:tags":[
        "high",
        "middle",
        "elementary"
    ],
    "wof:name":"Corona Avenue Elementary School",
    "wof:placetype":"venue"
},
  "geometry": {"coordinates":[-118.197968,33.975667],"type":"Point"}
}