{
  "type": "Feature",
  "properties": {
    "iso:country":"US",
    "sg:address":"422 W Capitol Expy",
    "sg:city":"San Jose",
    "sg:classifiers":[
        {
            "category":"Shopping",
            "subcategory":"Clothing, Apparel, & Fashions",
            "type":"Retail Goods"
        }
    ],
    "sg:phone":"+1 408 362 9612",
    "sg:postcode":"95136",
    "sg:province":"CA",
    "wof:name":"Mr. I Got It",
    "wof:placetype":"venue"
},
  "geometry": {"coordinates":[-121.84832,37.27451],"type":"Point"}
}