{
  "type": "Feature",
  "properties": {
    "iso:country":"US",
    "sg:address":"1125 Lincoln Ave",
    "sg:city":"Calistoga",
    "sg:classifiers":[
        {
            "category":"Shopping",
            "subcategory":"Used Merchandise",
            "type":"Retail Goods"
        }
    ],
    "sg:phone":"+1 707 942 2240",
    "sg:postcode":"94515",
    "sg:province":"CA",
    "sg:tags":[
        "vintage",
        "consignment"
    ],
    "wof:name":"Vintage Vogue",
    "wof:placetype":"venue"
},
  "geometry": {"coordinates":[-122.58062200000001,38.575836],"type":"Point"}
}