{
  "type": "Feature",
  "properties": {
    "iso:country":"US",
    "sg:address":"3620 Edison Way",
    "sg:city":"Fremont",
    "sg:classifiers":[
        {
            "category":"Manufacturing",
            "subcategory":"Electronics",
            "type":"Manufacturing & Wholesale Goods"
        }
    ],
    "sg:phone":"+1 510 252 9900",
    "sg:postcode":"94538",
    "sg:province":"CA",
    "sg:tags":[
        "semiconductor",
        "related",
        "devices"
    ],
    "sg:website":"www.cpa-sputtering.com",
    "wof:name":"CPA",
    "wof:placetype":"venue"
},
  "geometry": {"coordinates":[-121.945288,37.508926],"type":"Point"}
}