{
  "type": "Feature",
  "properties": {
    "iso:country":"US",
    "sg:address":"27413 Scott River Rd",
    "sg:city":"Scott Bar",
    "sg:classifiers":[
        {
            "category":"Manufacturing",
            "subcategory":"Retail Goods",
            "type":"Manufacturing & Wholesale Goods"
        }
    ],
    "sg:phone":"+1 530 496 3376",
    "sg:postcode":"96085",
    "sg:province":"CA",
    "sg:tags":[
        "manufacturer"
    ],
    "wof:name":"Scott River Industries",
    "wof:placetype":"venue"
},
  "geometry": {"coordinates":[-123.009753,41.747848],"type":"Point"}
}