{
  "type": "Feature",
  "properties": {
    "addr:full":"455 Sycamore Rd San Ysidro CA 92173",
    "addr:housenumber":"455",
    "addr:postcode":"92173",
    "addr:street":"Sycamore Rd",
    "iso:country":"US",
    "sg:address":"455 Sycamore Rd",
    "sg:city":"San Ysidro",
    "sg:classifiers":[
        {
            "category":"Government",
            "subcategory":"Office",
            "type":"Public Place"
        }
    ],
    "sg:phone":"+1 619 661 1722",
    "sg:postcode":"92173",
    "sg:province":"CA",
    "sg:tags":[
        "conservation"
    ],
    "wof:name":"Parks & Recreation",
    "wof:placetype":"venue"
},
  "geometry": {"coordinates":[-117.045253,32.548864],"type":"Point"}
}