{
  "type": "Feature",
  "properties": {
    "iso:country":"US",
    "sg:address":"20255 Prairie St",
    "sg:city":"Chatsworth",
    "sg:classifiers":[
        {
            "category":"Shopping",
            "subcategory":"Computers & Home Electronics",
            "type":"Retail Goods"
        }
    ],
    "sg:phone":"+1 818 998 6777",
    "sg:postcode":"91311",
    "sg:province":"CA",
    "sg:tags":[
        "publishing"
    ],
    "sg:website":"www.imagingctr.com",
    "wof:name":"Continental Imaging Ctr",
    "wof:placetype":"venue"
},
  "geometry": {"coordinates":[-118.572636,34.239278],"type":"Point"}
}