{
  "type": "Feature",
  "properties": {
    "addr:full":"1675 Superior Avenue Costa Mesa CA 92627",
    "addr:housenumber":"1675",
    "addr:postcode":"92627",
    "addr:street":"Superior Avenue",
    "iso:country":"US",
    "sg:address":"1675 Superior Avenue",
    "sg:city":"Costa Mesa",
    "sg:classifiers":[
        {
            "category":"Building & Trades",
            "subcategory":"Plumbing",
            "type":"Services"
        },
        {
            "category":"Building & Trades",
            "subcategory":"Construction",
            "type":"Services"
        }
    ],
    "sg:phone":"+1 714 434 7400",
    "sg:postcode":"92627",
    "sg:province":"CA",
    "sg:tags":[
        "air",
        "heating",
        "conditioning/hvac"
    ],
    "wof:name":"Brothers Plumbing Heating & Air Conditioning",
    "wof:placetype":"venue"
},
  "geometry": {"coordinates":[-117.924143,33.635761],"type":"Point"}
}