{
  "type": "Feature",
  "properties": {
    "addr:full":"200 S Los Robles Ave Pasadena CA 91101",
    "addr:housenumber":"200",
    "addr:postcode":"91101",
    "addr:street":"S Los Robles Ave",
    "iso:country":"US",
    "sg:address":"200 S Los Robles Ave",
    "sg:city":"Pasadena",
    "sg:classifiers":[
        {
            "category":"Banks & Credit Unions",
            "subcategory":"Investment Brokerage",
            "type":"Services"
        }
    ],
    "sg:phone":"+1 626 449 1501",
    "sg:postcode":"91101",
    "sg:province":"CA",
    "sg:tags":[
        "stock",
        "bond"
    ],
    "wof:name":"UBS Financial Svc",
    "wof:placetype":"venue"
},
  "geometry": {"coordinates":[-118.141296,34.143275],"type":"Point"}
}