{
  "type": "Feature",
  "properties": {
    "addr:full":"1625 Cam de Nog Fallbrook CA 92028",
    "addr:housenumber":"1625",
    "addr:postcode":"92028",
    "addr:street":"Cam De Nog",
    "iso:country":"US",
    "sg:address":"1625 Cam de Nog",
    "sg:city":"Fallbrook",
    "sg:classifiers":[
        {
            "category":"Insurance",
            "subcategory":"Hazard Insurance",
            "type":"Services"
        }
    ],
    "sg:phone":"+1 760 731 7441",
    "sg:postcode":"92028",
    "sg:province":"CA",
    "sg:tags":[
        "bond"
    ],
    "wof:name":"Ablaze Bail Bonds",
    "wof:placetype":"venue"
},
  "geometry": {"coordinates":[-117.225948,33.356473],"type":"Point"}
}