{
  "type": "Feature",
  "properties": {
    "iso:country":"US",
    "sg:address":"362 Carroll Park E",
    "sg:city":"Long Beach",
    "sg:classifiers":[
        {
            "category":"Manufacturing",
            "subcategory":"Metals",
            "type":"Manufacturing & Wholesale Goods"
        }
    ],
    "sg:phone":"+1 562 439 4433",
    "sg:postcode":"90814",
    "sg:province":"CA",
    "sg:tags":[
        "steel",
        "foundry",
        "investment"
    ],
    "wof:name":"Aerospace Svcs Svc Konsultants",
    "wof:placetype":"venue"
},
  "geometry": {"coordinates":[-118.162786,33.769517],"type":"Point"}
}