{
  "type": "Feature",
  "properties": {
    "addr:full":"4937 Sweetgrass Ln Bonsall CA 92003",
    "addr:housenumber":"4937",
    "addr:postcode":"92003",
    "addr:street":"Sweetgrass Ln",
    "iso:country":"US",
    "sg:address":"4937 Sweetgrass Ln",
    "sg:city":"Bonsall",
    "sg:classifiers":[
        {
            "category":"Freight",
            "type":"Transportation"
        }
    ],
    "sg:phone":"+1 760 630 5527",
    "sg:postcode":"92003",
    "sg:province":"CA",
    "sg:tags":[
        "storage",
        "container"
    ],
    "wof:name":"Southern California Storage",
    "wof:placetype":"venue"
},
  "geometry": {"coordinates":[-117.21900100000001,33.300302],"type":"Point"}
}