{
  "type": "Feature",
  "properties": {
    "iso:country":"US",
    "sg:address":"829 Pioneer Ave",
    "sg:city":"Wilmington",
    "sg:classifiers":[
        {
            "category":"Wholesale",
            "subcategory":"Durable Goods & Equipment",
            "type":"Manufacturing & Wholesale Goods"
        }
    ],
    "sg:phone":"+1 310 834 2671",
    "sg:postcode":"90744",
    "sg:province":"CA",
    "sg:tags":[
        "importer"
    ],
    "wof:name":"Probelt Corp",
    "wof:placetype":"venue"
},
  "geometry": {"coordinates":[-118.248539,33.78179],"type":"Point"}
}