{
  "type": "Feature",
  "properties": {
    "addr:full":"5415 W Hillsdale Ave Visalia CA 93291",
    "addr:housenumber":"5415",
    "addr:postcode":"93291",
    "addr:street":"W Hillsdale Ave",
    "iso:country":"US",
    "sg:address":"5415 W Hillsdale Ave",
    "sg:city":"Visalia",
    "sg:classifiers":[
        {
            "category":"Health Services",
            "subcategory":"Doctor",
            "type":"Services"
        }
    ],
    "sg:phone":"+1 559 733 1097",
    "sg:postcode":"93291",
    "sg:province":"CA",
    "sg:tags":[
        "dentist"
    ],
    "wof:name":"Karl J Pendegraft DDS",
    "wof:placetype":"venue"
},
  "geometry": {"coordinates":[-119.352835,36.329465],"type":"Point"}
}