{
  "type": "Feature",
  "properties": {
    "addr:full":"3232 W Florida Ave Hemet CA 92545",
    "addr:housenumber":"3232",
    "addr:postcode":"92545",
    "addr:street":"W Florida Ave",
    "iso:country":"US",
    "sg:address":"3232 W Florida Ave",
    "sg:city":"Hemet",
    "sg:classifiers":[
        {
            "category":"Health Services",
            "subcategory":"Doctor",
            "type":"Services"
        }
    ],
    "sg:phone":"+1 951 652 4464",
    "sg:postcode":"92545",
    "sg:province":"CA",
    "sg:tags":[
        "physician",
        "surgery",
        "oral",
        "dentist",
        "surgeons"
    ],
    "wof:name":"Hemet West Dental Office",
    "wof:placetype":"venue"
},
  "geometry": {"coordinates":[-117.006306,33.747369],"type":"Point"}
}