{
  "type": "Feature",
  "properties": {
    "iso:country":"US",
    "sg:address":"2522 Jamacha Rd",
    "sg:city":"El Cajon",
    "sg:classifiers":[
        {
            "category":"Shopping",
            "subcategory":"Jewelry",
            "type":"Retail Goods"
        }
    ],
    "sg:phone":"+1 619 670 0700",
    "sg:postcode":"92019",
    "sg:province":"CA",
    "sg:tags":[
        "jeweler"
    ],
    "wof:name":"Princess Jewelry",
    "wof:placetype":"venue"
},
  "geometry": {"coordinates":[-116.933787,32.7434],"type":"Point"}
}