{
  "type": "Feature",
  "properties": {
    "iso:country":"US",
    "sg:address":"1503 E 66th Street",
    "sg:city":"Los Angeles",
    "sg:classifiers":[
        {
            "category":"Food & Beverages",
            "subcategory":"Groceries & Convenience Stores",
            "type":"Retail Goods"
        }
    ],
    "sg:phone":"+1 323 589 0778",
    "sg:postcode":"90001",
    "sg:province":"CA",
    "wof:name":"Latina Market",
    "wof:placetype":"venue"
},
  "geometry": {"coordinates":[-118.247574,33.98017],"type":"Point"}
}