{
  "type": "Feature",
  "properties": {
    "addr:full":"5237 Aero Dr Santa Rosa CA 95403",
    "addr:housenumber":"5237",
    "addr:postcode":"95403",
    "addr:street":"Aero Dr",
    "iso:country":"US",
    "sg:address":"5237 Aero Dr",
    "sg:city":"Santa Rosa",
    "sg:classifiers":[
        {
            "category":"Personal",
            "subcategory":"Beauty Salon",
            "type":"Services"
        }
    ],
    "sg:phone":"+1 707 576 1229",
    "sg:postcode":"95403",
    "sg:province":"CA",
    "wof:name":"No Worries",
    "wof:placetype":"venue"
},
  "geometry": {"coordinates":[-122.765028,38.51016],"type":"Point"}
}