{
  "type": "Feature",
  "properties": {
    "addr:full":"1784 W Shaw Ave Fresno CA 93711",
    "addr:housenumber":"1784",
    "addr:postcode":"93711",
    "addr:street":"W Shaw Ave",
    "iso:country":"US",
    "sg:address":"1784 W Shaw Ave",
    "sg:city":"Fresno",
    "sg:classifiers":[
        {
            "category":"Food & Beverages",
            "subcategory":"Groceries & Convenience Stores",
            "type":"Retail Goods"
        }
    ],
    "sg:phone":"+1 559 435 4130",
    "sg:postcode":"93711",
    "sg:province":"CA",
    "wof:name":"7-Eleven",
    "wof:placetype":"venue"
},
  "geometry": {"coordinates":[-119.824496,36.808368],"type":"Point"}
}