{
  "type": "Feature",
  "properties": {
    "addr:full":"867 Guadalupe St Guadalupe CA 93434",
    "addr:housenumber":"867",
    "addr:postcode":"93434",
    "addr:street":"Guadalupe St",
    "iso:country":"US",
    "sg:address":"867 Guadalupe St",
    "sg:city":"Guadalupe",
    "sg:classifiers":[
        {
            "category":"Cinema",
            "subcategory":"Movie Rental",
            "type":"Entertainment"
        }
    ],
    "sg:phone":"+1 805 343 6646",
    "sg:postcode":"93434",
    "sg:province":"CA",
    "sg:tags":[
        "leasing",
        "video",
        "disc",
        "tape"
    ],
    "wof:name":"Esmeralda's Jewelry & Video",
    "wof:placetype":"venue"
},
  "geometry": {"coordinates":[-120.57377099999999,34.969425],"type":"Point"}
}