{
  "type": "Feature",
  "properties": {
    "addr:full":"57 Cambon Dr San Francisco CA 94132",
    "addr:housenumber":"57",
    "addr:postcode":"94132",
    "addr:street":"Cambon Dr",
    "iso:country":"US",
    "sg:address":"57 Cambon Dr",
    "sg:city":"San Francisco",
    "sg:classifiers":[
        {
            "category":"Retail",
            "subcategory":"Laundry & Dry Cleaning",
            "type":"Services"
        }
    ],
    "sg:postcode":"94132",
    "sg:province":"CA",
    "wof:name":"Wash 'N Dry Laundry",
    "wof:placetype":"venue"
},
  "geometry": {"coordinates":[-122.474445,37.717988],"type":"Point"}
}