{
  "type": "Feature",
  "properties": {
    "addr:full":"Meridian Square 4674 Meridian Avenue San Jose CA 95118",
    "addr:housenumber":"4674",
    "addr:postcode":"95118",
    "addr:street":"Meridian;Meridian Avenue",
    "iso:country":"US",
    "sg:address":"Meridian Square 4674 Meridian Avenue",
    "sg:city":"San Jose",
    "sg:classifiers":[
        {
            "category":"Personal",
            "subcategory":"Beauty Salon",
            "type":"Services"
        },
        {
            "category":"Personal",
            "subcategory":"Nail Salon",
            "type":"Services"
        }
    ],
    "sg:phone":"+1 408 267 4611",
    "sg:postcode":"95118",
    "sg:province":"CA",
    "sg:tags":[
        "hair"
    ],
    "wof:name":"Beauty Corners",
    "wof:placetype":"venue"
},
  "geometry": {"coordinates":[-121.89832,37.255448],"type":"Point"}
}