{
  "type": "Feature",
  "properties": {
    "addr:full":"257 N Palm St Turlock CA 95380",
    "addr:housenumber":"257",
    "addr:postcode":"95380",
    "addr:street":"N Palm St",
    "iso:country":"US",
    "sg:address":"257 N Palm St",
    "sg:city":"Turlock",
    "sg:classifiers":[
        {
            "category":"Professional",
            "type":"Services"
        }
    ],
    "sg:phone":"+1 209 634 8400",
    "sg:postcode":"95380",
    "sg:province":"CA",
    "wof:name":"Sylvia Colon Vasquez",
    "wof:placetype":"venue"
},
  "geometry": {"coordinates":[-120.84426999999999,37.497981],"type":"Point"}
}