{
  "type": "Feature",
  "properties": {
    "addr:full":"50 Declaration Dr Chico CA 95973",
    "addr:housenumber":"50",
    "addr:postcode":"95973",
    "addr:street":"Declaration Dr",
    "iso:country":"US",
    "sg:address":"50 Declaration Dr",
    "sg:city":"Chico",
    "sg:classifiers":[
        {
            "category":"Professional",
            "subcategory":"Accounting & Tax Preparation",
            "type":"Services"
        }
    ],
    "sg:phone":"+1 530 898 1201",
    "sg:postcode":"95973",
    "sg:province":"CA",
    "sg:tags":[
        "billing"
    ],
    "wof:name":"Accucode Medical Billing Svc",
    "wof:placetype":"venue"
},
  "geometry": {"coordinates":[-121.87340399999999,39.7711],"type":"Point"}
}