{
  "type": "Feature",
  "properties": {
    "addr:full":"5776 Broadway Oakland CA 94618",
    "addr:housenumber":"5776",
    "addr:postcode":"94618",
    "addr:street":"Broadway",
    "iso:country":"US",
    "sg:address":"5776 Broadway",
    "sg:city":"Oakland",
    "sg:classifiers":[
        {
            "category":"Education",
            "subcategory":"Music School",
            "type":"Public Place"
        }
    ],
    "sg:phone":"+1 510 601 5700",
    "sg:postcode":"94618",
    "sg:province":"CA",
    "sg:tags":[
        "instruction-instrumental"
    ],
    "wof:name":"Musically Minded Inc.",
    "wof:placetype":"venue"
},
  "geometry": {"coordinates":[-122.246493,37.843885],"type":"Point"}
}