{
  "type": "Feature",
  "properties": {
    "iso:country":"US",
    "sg:address":"1392 Sarah Pl",
    "sg:city":"Ontario",
    "sg:classifiers":[
        {
            "category":"Freight",
            "type":"Transportation"
        },
        {
            "category":"Manufacturing",
            "subcategory":"Tools & Machinery",
            "type":"Manufacturing & Wholesale Goods"
        }
    ],
    "sg:phone":"+1 909 390 8002",
    "sg:postcode":"91761",
    "sg:province":"CA",
    "sg:tags":[
        "warehouse",
        "lighting",
        "fixture"
    ],
    "wof:name":"Progress Lighting Inc",
    "wof:placetype":"venue"
},
  "geometry": {"coordinates":[-117.53939099999999,34.04821],"type":"Point"}
}