{
  "type": "Feature",
  "properties": {
    "addr:full":"923 Folsom St San Francisco CA 94107",
    "addr:housenumber":"923",
    "addr:postcode":"94107",
    "addr:street":"Folsom St",
    "iso:country":"US",
    "sg:address":"923 Folsom St",
    "sg:city":"San Francisco",
    "sg:classifiers":[
        {
            "category":"Manufacturing",
            "subcategory":"Printing",
            "type":"Manufacturing & Wholesale Goods"
        }
    ],
    "sg:phone":"+1 415 593 2506",
    "sg:postcode":"94107",
    "sg:province":"CA",
    "sg:tags":[
        "broker"
    ],
    "wof:name":"Smashing Graphics",
    "wof:placetype":"venue"
},
  "geometry": {"coordinates":[-122.403965,37.779799],"type":"Point"}
}