{
  "type": "Feature",
  "properties": {
    "iso:country":"US",
    "sg:address":"5729 Terminal Ave",
    "sg:city":"Riverbank",
    "sg:classifiers":[
        {
            "category":"Home & Garden",
            "subcategory":"Household Appliances",
            "type":"Retail Goods"
        },
        {
            "category":"Building & Trades",
            "subcategory":"Construction",
            "type":"Services"
        }
    ],
    "sg:phone":"+1 209 863 1163",
    "sg:postcode":"95367",
    "sg:province":"CA",
    "sg:tags":[
        "major",
        "system",
        "appliances-small",
        "specialty",
        "heating",
        "contractor",
        "air conditioning"
    ],
    "wof:name":"Barnett Plumbing, Inc",
    "wof:placetype":"venue"
},
  "geometry": {"coordinates":[-120.93112600000001,37.721881],"type":"Point"}
}