{
  "type": "Feature",
  "properties": {
    "iso:country":"US",
    "sg:address":"2001 Main St",
    "sg:city":"Chula Vista",
    "sg:classifiers":[
        {
            "category":"Retail",
            "subcategory":"Event Space",
            "type":"Services"
        }
    ],
    "sg:phone":"+1 619 423 1036",
    "sg:postcode":"91911",
    "sg:province":"CA",
    "sg:tags":[
        "venue"
    ],
    "wof:name":"San Diego County Swiss Club",
    "wof:placetype":"venue"
},
  "geometry": {"coordinates":[-117.091003,32.5951],"type":"Point"}
}