{
  "type": "Feature",
  "properties": {
    "addr:full":"1265 el Nido Dr Fallbrook CA 92028",
    "addr:housenumber":"1265",
    "addr:postcode":"92028",
    "addr:street":"El Nido Dr",
    "iso:country":"US",
    "sg:address":"1265 el Nido Dr",
    "sg:city":"Fallbrook",
    "sg:classifiers":[
        {
            "category":"Professional",
            "subcategory":"Management & Consulting",
            "type":"Services"
        }
    ],
    "sg:phone":"+1 760 723 2800",
    "sg:postcode":"92028",
    "sg:province":"CA",
    "sg:tags":[
        "retail",
        "direct",
        "sales"
    ],
    "wof:name":"Select Business Services",
    "wof:placetype":"venue"
},
  "geometry": {"coordinates":[-117.233407,33.321996],"type":"Point"}
}