{
  "type": "Feature",
  "properties": {
    "addr:full":"1030 Bay St Santa Monica CA 90405",
    "addr:housenumber":"1030",
    "addr:postcode":"90405",
    "addr:street":"Bay St",
    "iso:country":"US",
    "sg:address":"1030 Bay St",
    "sg:city":"Santa Monica",
    "sg:classifiers":[
        {
            "category":"Building & Trades",
            "subcategory":"Construction",
            "type":"Services"
        }
    ],
    "sg:phone":"+1 310 664 9823",
    "sg:postcode":"90405",
    "sg:province":"CA",
    "sg:tags":[
        "house"
    ],
    "wof:name":"Alexander Services Inc",
    "wof:placetype":"venue"
},
  "geometry": {"coordinates":[-118.479249,34.013077],"type":"Point"}
}