{
  "type": "Feature",
  "properties": {
    "addr:full":"115 N Rowan Ave Los Angeles CA 90063",
    "addr:housenumber":"115",
    "addr:postcode":"90063",
    "addr:street":"N Rowan Ave",
    "iso:country":"US",
    "sg:address":"115 N Rowan Ave",
    "sg:city":"Los Angeles",
    "sg:classifiers":[
        {
            "category":"Food & Beverages",
            "subcategory":"Specialty",
            "type":"Retail Goods"
        }
    ],
    "sg:phone":"+1 323 268 4211",
    "sg:postcode":"90063",
    "sg:province":"CA",
    "sg:tags":[
        "plumbing"
    ],
    "wof:name":"Aqua Pure Water",
    "wof:placetype":"venue"
},
  "geometry": {"coordinates":[-118.187055,34.036191],"type":"Point"}
}