{
  "type": "Feature",
  "properties": {
    "addr:full":"11110 Artesia Blvd Cerritos CA 90703",
    "addr:housenumber":"11110",
    "addr:postcode":"ca 90703",
    "addr:street":"Artesia Blvd",
    "iso:country":"US",
    "sg:address":"11110 Artesia Blvd",
    "sg:city":"Cerritos",
    "sg:classifiers":[
        {
            "category":"Organizations",
            "subcategory":"Non-profit Organization",
            "type":"Services"
        }
    ],
    "sg:phone":"+1 562 860 7270",
    "sg:postcode":"90703",
    "sg:province":"CA",
    "wof:name":"Easter Seal Society",
    "wof:placetype":"venue"
},
  "geometry": {"coordinates":[-118.095433,33.872925],"type":"Point"}
}