{
  "type": "Feature",
  "properties": {
    "iso:country":"US",
    "sg:address":"1 W Morton Ave",
    "sg:city":"Porterville",
    "sg:classifiers":[
        {
            "category":"Real Estate",
            "subcategory":"Real Estate Agent",
            "type":"Services"
        }
    ],
    "sg:phone":"+1 559 784 3000",
    "sg:postcode":"93257",
    "sg:province":"CA",
    "wof:name":"Letsinger Realty",
    "wof:placetype":"venue"
},
  "geometry": {"coordinates":[-119.016763,36.073087],"type":"Point"}
}