{
  "type": "Feature",
  "properties": {
    "iso:country":"US",
    "sg:address":"23460 Cinema Dr",
    "sg:city":"Valencia",
    "sg:classifiers":[
        {
            "category":"Manufacturing",
            "subcategory":"Food",
            "type":"Manufacturing & Wholesale Goods"
        },
        {
            "category":"Wholesale",
            "subcategory":"Groceries",
            "type":"Manufacturing & Wholesale Goods"
        }
    ],
    "sg:phone":"+1 661 259 3672",
    "sg:postcode":"91355",
    "sg:province":"CA",
    "sg:tags":[
        "baker",
        "product",
        "mfg"
    ],
    "wof:name":"Oroweat",
    "wof:placetype":"venue"
},
  "geometry": {"coordinates":[-118.547332,34.420856],"type":"Point"}
}