{
  "type": "Feature",
  "properties": {
    "addr:full":"401 Watt Ave Sacramento CA 95864",
    "addr:housenumber":"401",
    "addr:postcode":"95864",
    "addr:street":"Watt Ave",
    "iso:country":"US",
    "sg:address":"401 Watt Ave",
    "sg:city":"Sacramento",
    "sg:classifiers":[
        {
            "category":"Professional",
            "subcategory":"Lawyer & Legal Services",
            "type":"Services"
        }
    ],
    "sg:phone":"+1 916 448 9800",
    "sg:postcode":"95864",
    "sg:province":"CA",
    "wof:name":"Talley Stuart",
    "wof:placetype":"venue"
},
  "geometry": {"coordinates":[-121.383555,38.572097],"type":"Point"}
}