{
  "type": "Feature",
  "properties": {
    "addr:full":"18430 Jamestown Rd Jamestown CA 95327",
    "addr:housenumber":"18430",
    "addr:postcode":"95327",
    "addr:street":"Jamestown Rd",
    "iso:country":"US",
    "sg:address":"18430 Jamestown Rd",
    "sg:city":"Jamestown",
    "sg:classifiers":[
        {
            "category":"Home & Garden",
            "subcategory":"Hardware",
            "type":"Retail Goods"
        }
    ],
    "sg:phone":"+1 209 984 3863",
    "sg:postcode":"95327",
    "sg:province":"CA",
    "sg:tags":[
        "saw"
    ],
    "wof:name":"Pine Alley Rentals & Sales",
    "wof:placetype":"venue"
},
  "geometry": {"coordinates":[-120.418498,37.960111],"type":"Point"}
}