{
  "type": "Feature",
  "properties": {
    "iso:country":"US",
    "sg:address":"46115 Grace Ct",
    "sg:city":"Temecula",
    "sg:classifiers":[
        {
            "category":"Insurance",
            "subcategory":"Life Insurance",
            "type":"Services"
        },
        {
            "category":"Banks & Credit Unions",
            "subcategory":"Financial Services",
            "type":"Services"
        }
    ],
    "sg:phone":"+1 951 506 9605",
    "sg:postcode":"92592",
    "sg:province":"CA",
    "sg:tags":[
        "consultant",
        "planning"
    ],
    "sg:website":"http://www.thestromgroupllc.com",
    "wof:name":"The Strom Group Llc",
    "wof:placetype":"venue"
},
  "geometry": {"coordinates":[-117.084907,33.457804],"type":"Point"}
}