{
  "type": "Feature",
  "properties": {
    "addr:full":"210 N Avenue 64 Los Angeles CA 90042",
    "addr:housenumber":"210;64",
    "addr:postcode":"90042",
    "addr:street":"N Avenue",
    "iso:country":"US",
    "sg:address":"210 N Avenue 64",
    "sg:city":"Los Angeles",
    "sg:classifiers":[
        {
            "category":"Health Services",
            "subcategory":"Chiropractor",
            "type":"Services"
        }
    ],
    "sg:phone":"+1 323 254 2882",
    "sg:postcode":"90042",
    "sg:province":"CA",
    "wof:name":"Coffey Family Chiropractic",
    "wof:placetype":"venue"
},
  "geometry": {"coordinates":[-118.181,34.115601],"type":"Point"}
}