{
  "type": "Feature",
  "properties": {
    "iso:country":"US",
    "sg:address":"4643 Norwalk St",
    "sg:city":"Union City",
    "sg:classifiers":[
        {
            "category":"Professional",
            "subcategory":"Management & Consulting",
            "type":"Services"
        }
    ],
    "sg:phone":"+1 510 489 4952",
    "sg:postcode":"94587",
    "sg:province":"CA",
    "sg:tags":[
        "consultant",
        "business"
    ],
    "wof:name":"Michaels & Assoc",
    "wof:placetype":"venue"
},
  "geometry": {"coordinates":[-122.067127,37.572829],"type":"Point"}
}