{
  "type": "Feature",
  "properties": {
    "iso:country":"US",
    "sg:address":"919 N Herrin Ave",
    "sg:city":"Manhattan Beach",
    "sg:classifiers":[
        {
            "category":"Real Estate",
            "subcategory":"Real Estate Agent",
            "type":"Services"
        }
    ],
    "sg:phone":"+1 310 374 7425",
    "sg:postcode":"90266",
    "sg:province":"CA",
    "wof:name":"Excalibur Realty",
    "wof:placetype":"venue"
},
  "geometry": {"coordinates":[-118.38522399999999,33.885427],"type":"Point"}
}