{
  "type": "Feature",
  "properties": {
    "addr:full":"15424 Cabrito Rd Van Nuys CA 91406",
    "addr:postcode":"15424;91406",
    "addr:street":"Cabrito Rd",
    "iso:country":"US",
    "sg:address":"15424 Cabrito Rd",
    "sg:city":"Van Nuys",
    "sg:classifiers":[
        {
            "category":"Wholesale",
            "subcategory":"Durable Goods & Equipment",
            "type":"Manufacturing & Wholesale Goods"
        }
    ],
    "sg:phone":"+1 323 873 6999",
    "sg:postcode":"91406",
    "sg:province":"CA",
    "sg:tags":[
        "professional"
    ],
    "wof:name":"Pegasus Optical Corp",
    "wof:placetype":"venue"
},
  "geometry": {"coordinates":[-118.468542,34.216563],"type":"Point"}
}