{
  "type": "Feature",
  "properties": {
    "iso:country":"US",
    "sg:address":"2624 Fayette Dr",
    "sg:city":"Mountain View",
    "sg:classifiers":[
        {
            "category":"Sports & Exercise",
            "subcategory":"Gym",
            "type":"Entertainment"
        }
    ],
    "sg:phone":"+1 650 941 9148",
    "sg:postcode":"94040",
    "sg:province":"CA",
    "sg:tags":[
        "club",
        "health",
        "studio",
        "gymnasium"
    ],
    "wof:name":"Optimum Results",
    "wof:placetype":"venue"
},
  "geometry": {"coordinates":[-122.112666,37.40341],"type":"Point"}
}