{
  "type": "Feature",
  "properties": {
    "iso:country":"US",
    "sg:address":"3112 Seaborg Ave",
    "sg:city":"Ventura",
    "sg:classifiers":[
        {
            "category":"Professional",
            "subcategory":"Research",
            "type":"Services"
        }
    ],
    "sg:phone":"+1 805 289 0144",
    "sg:postcode":"93003",
    "sg:province":"CA",
    "sg:tags":[
        "development",
        "marketing",
        "product"
    ],
    "sg:website":"www.1-mark.com",
    "wof:name":"1-Mark Consumer Products",
    "wof:placetype":"venue"
},
  "geometry": {"coordinates":[-119.211837,34.24734],"type":"Point"}
}