{
  "type": "Feature",
  "properties": {
    "iso:country":"US",
    "sg:address":"5560 N Blackstone Ave",
    "sg:city":"Fresno",
    "sg:classifiers":[
        {
            "category":"Retail",
            "subcategory":"Auto Repair",
            "type":"Services"
        }
    ],
    "sg:phone":"+1 559 432 9051",
    "sg:postcode":"93710",
    "sg:province":"CA",
    "sg:tags":[
        "body",
        "automobile",
        "painting"
    ],
    "wof:name":"Foxwood Enterprises",
    "wof:placetype":"venue"
},
  "geometry": {"coordinates":[-119.790307,36.816359],"type":"Point"}
}