{
  "type": "Feature",
  "properties": {
    "addr:full":"2715 Porter St Soquel CA 95073",
    "addr:housenumber":"2715",
    "addr:postcode":"95073",
    "addr:street":"Porter St",
    "iso:country":"US",
    "sg:address":"2715 Porter St",
    "sg:city":"Soquel",
    "sg:classifiers":[
        {
            "category":"Social Services",
            "type":"Services"
        }
    ],
    "sg:phone":"+1 831 476 6500",
    "sg:postcode":"95073",
    "sg:province":"CA",
    "sg:tags":[
        "counselor",
        "marriage",
        "family"
    ],
    "wof:name":"Marty Potkin",
    "wof:placetype":"venue"
},
  "geometry": {"coordinates":[-121.95735000000001,36.986309],"type":"Point"}
}