{
  "type": "Feature",
  "properties": {
    "iso:country":"US",
    "sg:address":"244 E 47th St",
    "sg:city":"Long Beach",
    "sg:classifiers":[
        {
            "category":"Wholesale",
            "subcategory":"Office Equipment",
            "type":"Manufacturing & Wholesale Goods"
        }
    ],
    "sg:phone":"+1 562 428 2494",
    "sg:postcode":"90805",
    "sg:province":"CA",
    "wof:name":"Western Imaging",
    "wof:placetype":"venue"
},
  "geometry": {"coordinates":[-118.190836,33.843261],"type":"Point"}
}