{
  "type": "Feature",
  "properties": {
    "iso:country":"US",
    "sg:address":"5000 Overland Ave Ste 5",
    "sg:city":"Culver City",
    "sg:classifiers":[
        {
            "category":"Health Services",
            "subcategory":"Clinic",
            "type":"Services"
        }
    ],
    "sg:phone":"+1 310 280 2700",
    "sg:postcode":"90232",
    "sg:province":"CA",
    "sg:tags":[
        "medical"
    ],
    "sg:website":"www.lavidamed.com/?p=2888",
    "wof:name":"La Vida Medical Group",
    "wof:placetype":"venue"
},
  "geometry": {"coordinates":[-118.395188,34.006519],"type":"Point"}
}