{
  "type": "Feature",
  "properties": {
    "iso:country":"US",
    "sg:address":"1702 Nisson Rd",
    "sg:city":"Tustin",
    "sg:classifiers":[
        {
            "category":"Recreation",
            "type":"Entertainment"
        }
    ],
    "sg:phone":"+1 714 832 8910",
    "sg:postcode":"92780",
    "sg:province":"CA",
    "sg:tags":[
        "instruction",
        "swimming"
    ],
    "sg:website":"www.bluebuoy.com",
    "wof:name":"Blue Buoy Swim School",
    "wof:placetype":"venue"
},
  "geometry": {"coordinates":[-117.809156,33.728625],"type":"Point"}
}