{
  "type": "Feature",
  "properties": {
    "addr:full":"8700 Kittyhawk Ave Los Angeles CA 90045",
    "addr:housenumber":"8700",
    "addr:postcode":"90045",
    "addr:street":"Kittyhawk Ave",
    "iso:country":"US",
    "sg:address":"8700 Kittyhawk Ave",
    "sg:city":"Los Angeles",
    "sg:classifiers":[
        {
            "category":"Building & Trades",
            "subcategory":"Electrical",
            "type":"Services"
        }
    ],
    "sg:phone":"+1 310 649 6345",
    "sg:postcode":"90045",
    "sg:province":"CA",
    "sg:tags":[
        "work",
        "electrical",
        "electric",
        "contractor"
    ],
    "wof:name":"Coast Electric Co",
    "wof:placetype":"venue"
},
  "geometry": {"coordinates":[-118.39232199999999,33.958242],"type":"Point"}
}