{
  "type": "Feature",
  "properties": {
    "iso:country":"US",
    "sg:address":"8399 Garvey Ave",
    "sg:city":"Rosemead",
    "sg:classifiers":[
        {
            "category":"Autos & Motor Vehicles",
            "subcategory":"Automobile Sales",
            "type":"Retail Goods"
        }
    ],
    "sg:phone":"+1 626 571 2288",
    "sg:postcode":"91770",
    "sg:province":"CA",
    "sg:tags":[
        "car",
        "dealer"
    ],
    "sg:website":"www.chauto.com",
    "wof:name":"C H Auto",
    "wof:placetype":"venue"
},
  "geometry": {"coordinates":[-118.086963,34.062659],"type":"Point"}
}