{
  "type": "Feature",
  "properties": {
    "addr:full":"275 Redwood Ave Milpitas CA 95035",
    "addr:housenumber":"275",
    "addr:postcode":"95035",
    "addr:street":"Redwood Ave",
    "iso:country":"US",
    "sg:address":"275 Redwood Ave",
    "sg:city":"Milpitas",
    "sg:classifiers":[
        {
            "category":"Education",
            "subcategory":"School",
            "type":"Public Place"
        }
    ],
    "sg:phone":"+1 408 635 2852",
    "sg:postcode":"95035",
    "sg:province":"CA",
    "sg:website":"www.milpitas.k12.ca.us",
    "wof:name":"Milpitas Unified School District",
    "wof:placetype":"venue"
},
  "geometry": {"coordinates":[-121.912626,37.440156],"type":"Point"}
}