{
  "type": "Feature",
  "properties": {
    "addr:full":"1743 Park Ave San Jose CA 95126",
    "addr:housenumber":"1743",
    "addr:postcode":"95126",
    "addr:street":"Park Ave",
    "iso:country":"US",
    "sg:address":"1743 Park Ave",
    "sg:city":"San Jose",
    "sg:classifiers":[
        {
            "category":"Retail",
            "subcategory":"Portrait Studio",
            "type":"Services"
        }
    ],
    "sg:phone":"+1 408 280 6390",
    "sg:postcode":"95126",
    "sg:province":"CA",
    "sg:tags":[
        "photographer"
    ],
    "wof:name":"Postal Connections",
    "wof:placetype":"venue"
},
  "geometry": {"coordinates":[-121.92424099999999,37.334001],"type":"Point"}
}