{
  "type": "Feature",
  "properties": {
    "addr:full":"806 Corcoran Ave Santa Cruz CA 95062",
    "addr:housenumber":"806",
    "addr:postcode":"95062",
    "addr:street":"Corcoran Ave",
    "iso:country":"US",
    "sg:address":"806 Corcoran Ave",
    "sg:city":"Santa Cruz",
    "sg:classifiers":[
        {
            "category":"Building & Trades",
            "subcategory":"Construction",
            "type":"Services"
        }
    ],
    "sg:phone":"+1 831 465 8345",
    "sg:postcode":"95062",
    "sg:province":"CA",
    "sg:tags":[
        "house"
    ],
    "wof:name":"Copus Construction",
    "wof:placetype":"venue"
},
  "geometry": {"coordinates":[-121.980565,36.966071],"type":"Point"}
}