{
  "type": "Feature",
  "properties": {
    "iso:country":"US",
    "sg:address":"414 N Harbor Blvd",
    "sg:city":"Santa Ana",
    "sg:classifiers":[
        {
            "category":"Personal",
            "subcategory":"Barber",
            "type":"Services"
        }
    ],
    "sg:phone":"+1 714 554 4436",
    "sg:postcode":"92703",
    "sg:province":"CA",
    "wof:name":"Duc's Barbers",
    "wof:placetype":"venue"
},
  "geometry": {"coordinates":[-117.91999800000001,33.748501],"type":"Point"}
}