{
  "type": "Feature",
  "properties": {
    "iso:country":"US",
    "sg:address":"49271 Golden Oak Loop",
    "sg:city":"Oakhurst",
    "sg:classifiers":[
        {
            "category":"Restaurant",
            "type":"Food & Drink"
        }
    ],
    "sg:phone":"+1 559 683 8000",
    "sg:postcode":"93644",
    "sg:province":"CA",
    "wof:name":"Castillo's Mexican Food",
    "wof:placetype":"venue"
},
  "geometry": {"coordinates":[-119.649362,37.33222],"type":"Point"}
}