{
  "type": "Feature",
  "properties": {
    "addr:full":"2755 Herndon Ave Clovis CA 93611",
    "addr:housenumber":"2755",
    "addr:postcode":"93611",
    "addr:street":"Herndon Ave",
    "iso:country":"US",
    "sg:address":"2755 Herndon Ave",
    "sg:city":"Clovis",
    "sg:classifiers":[
        {
            "category":"Health Services",
            "subcategory":"Hospital",
            "type":"Services"
        }
    ],
    "sg:phone":"+1 559 324 4000",
    "sg:postcode":"93611",
    "sg:province":"CA",
    "wof:name":"Clovis Cmnty Hosp & Med Ctr",
    "wof:placetype":"venue"
},
  "geometry": {"coordinates":[-119.665148,36.837328],"type":"Point"}
}