{
  "type": "Feature",
  "properties": {
    "addr:full":"717 E el Segundo Blvd El Segundo CA 90245",
    "addr:housenumber":"717",
    "addr:postcode":"90245",
    "addr:street":"E El Segundo Blvd",
    "iso:country":"US",
    "sg:address":"717 E el Segundo Blvd",
    "sg:city":"El Segundo",
    "sg:classifiers":[
        {
            "category":"Retail",
            "subcategory":"Auto Repair",
            "type":"Services"
        }
    ],
    "sg:phone":"+1 310 322 8411",
    "sg:postcode":"90245",
    "sg:province":"CA",
    "sg:tags":[
        "body",
        "automobile",
        "painting"
    ],
    "wof:name":"El Segundo Auto Body",
    "wof:placetype":"venue"
},
  "geometry": {"coordinates":[-118.408458,33.916446],"type":"Point"}
}