{
  "type": "Feature",
  "properties": {
    "iso:country":"US",
    "sg:address":"5256 S Mission Rd",
    "sg:city":"Bonsall",
    "sg:classifiers":[
        {
            "category":"Professional",
            "subcategory":"Accounting & Tax Preparation",
            "type":"Services"
        }
    ],
    "sg:phone":"+1 760 945 0777",
    "sg:postcode":"92003",
    "sg:province":"CA",
    "sg:tags":[
        "accountant"
    ],
    "sg:website":"www.kearnsco.com",
    "wof:name":"John Kearns & Co Inc",
    "wof:placetype":"venue"
},
  "geometry": {"coordinates":[-117.223554,33.296068],"type":"Point"}
}