{
  "type": "Feature",
  "properties": {
    "iso:country":"US",
    "sg:address":"575 Dawson Dr Ste 9",
    "sg:city":"Camarillo",
    "sg:classifiers":[
        {
            "category":"Retail",
            "subcategory":"Auto Repair",
            "type":"Services"
        }
    ],
    "sg:phone":"+1 805 482 9950",
    "sg:postcode":"93012",
    "sg:province":"CA",
    "wof:name":"Muffler Time Exhaust Specialties",
    "wof:placetype":"venue"
},
  "geometry": {"coordinates":[-119.03600299999999,34.205898],"type":"Point"}
}