{
  "type": "Feature",
  "properties": {
    "addr:full":"1875 Century Park E Los Angeles CA 90067",
    "addr:housenumber":"1875",
    "addr:postcode":"90067",
    "addr:street":"Century Park E",
    "iso:country":"US",
    "sg:address":"1875 Century Park E",
    "sg:city":"Los Angeles",
    "sg:classifiers":[
        {
            "category":"Manufacturing",
            "subcategory":"Electronics",
            "type":"Manufacturing & Wholesale Goods"
        }
    ],
    "sg:phone":"+1 310 286 0243",
    "sg:postcode":"90067",
    "sg:province":"CA",
    "sg:tags":[
        "equipment",
        "electronic",
        "supply"
    ],
    "wof:name":"Hitachi America",
    "wof:placetype":"venue"
},
  "geometry": {"coordinates":[-118.41436899999999,34.061239],"type":"Point"}
}