{
  "type": "Feature",
  "properties": {
    "addr:full":"217 Soscol Ave Napa CA 94559",
    "addr:housenumber":"217",
    "addr:postcode":"94559",
    "addr:street":"Soscol Ave",
    "iso:country":"US",
    "sg:address":"217 Soscol Ave",
    "sg:city":"Napa",
    "sg:classifiers":[
        {
            "category":"Banks & Credit Unions",
            "subcategory":"Bank",
            "type":"Services"
        }
    ],
    "sg:phone":"+1 707 254 8690",
    "sg:postcode":"94559",
    "sg:province":"CA",
    "wof:name":"Wells Fargo Bank",
    "wof:placetype":"venue"
},
  "geometry": {"coordinates":[-122.27462,38.284823],"type":"Point"}
}