{
  "type": "Feature",
  "properties": {
    "addr:full":"949 View Dr El Sobrante CA 94803",
    "addr:housenumber":"949",
    "addr:postcode":"94803",
    "addr:street":"View Dr El Sobrante",
    "iso:country":"US",
    "sg:address":"949 View Dr",
    "sg:city":"El Sobrante",
    "sg:classifiers":[
        {
            "category":"Real Estate",
            "subcategory":"Real Estate Agent",
            "type":"Services"
        }
    ],
    "sg:phone":"+1 510 799 1058",
    "sg:postcode":"94803",
    "sg:province":"CA",
    "sg:tags":[
        "appraiser"
    ],
    "sg:website":"www.cpvaluations.com",
    "wof:name":"A California Prprty Vltn Co",
    "wof:placetype":"venue"
},
  "geometry": {"coordinates":[-122.31259300000001,37.978618],"type":"Point"}
}