{
  "type": "Feature",
  "properties": {
    "iso:country":"US",
    "sg:address":"615 Cahuilla Rd",
    "sg:city":"Borrego Springs",
    "sg:classifiers":[
        {
            "category":"Organizations",
            "subcategory":"Religious Organization",
            "type":"Services"
        }
    ],
    "sg:phone":"+1 760 767 5453",
    "sg:postcode":"92004",
    "sg:province":"CA",
    "sg:tags":[
        "church"
    ],
    "wof:name":"First Baptist Church",
    "wof:placetype":"venue"
},
  "geometry": {"coordinates":[-116.37928100000001,33.263474],"type":"Point"}
}