{
  "type": "Feature",
  "properties": {
    "addr:full":"255 Race Street San Jose CA 95126",
    "addr:housenumber":"255",
    "addr:postcode":"95126",
    "addr:street":"Race Street",
    "iso:country":"US",
    "sg:address":"255 Race Street",
    "sg:city":"San Jose",
    "sg:classifiers":[
        {
            "category":"Restaurant",
            "type":"Food & Drink"
        }
    ],
    "sg:phone":"+1 408 295 7343",
    "sg:postcode":"95126",
    "sg:province":"CA",
    "sg:tags":[
        "mexican"
    ],
    "wof:name":"Taqueria Eduardo",
    "wof:placetype":"venue"
},
  "geometry": {"coordinates":[-121.911659,37.324619],"type":"Point"}
}