{
  "type": "Feature",
  "properties": {
    "iso:country":"US",
    "sg:address":"55 Reiner St",
    "sg:city":"Colma",
    "sg:classifiers":[
        {
            "category":"Autos & Motor Vehicles",
            "subcategory":"Auto Supplies",
            "type":"Retail Goods"
        }
    ],
    "sg:phone":"+1 650 755 1355",
    "sg:postcode":"94014",
    "sg:province":"CA",
    "sg:tags":[
        "automobile",
        "parts"
    ],
    "wof:name":"Tassi Inc",
    "wof:placetype":"venue"
},
  "geometry": {"coordinates":[-122.466525,37.686252],"type":"Point"}
}