{
  "type": "Feature",
  "properties": {
    "addr:full":"811 W Napa St Sonoma CA 95476",
    "addr:housenumber":"811",
    "addr:postcode":"95476",
    "addr:street":"W Napa St",
    "iso:country":"US",
    "sg:address":"811 W Napa St",
    "sg:city":"Sonoma",
    "sg:classifiers":[
        {
            "category":"Shopping",
            "subcategory":"Computers & Home Electronics",
            "type":"Retail Goods"
        }
    ],
    "sg:phone":"+1 707 996 1141",
    "sg:postcode":"95476",
    "sg:province":"CA",
    "sg:tags":[
        "software"
    ],
    "sg:website":"www.checks-balances.com",
    "wof:name":"Checks & Balances",
    "wof:placetype":"venue"
},
  "geometry": {"coordinates":[-122.47403300000001,38.293423],"type":"Point"}
}