{
  "type": "Feature",
  "properties": {
    "addr:full":"939 W State St Ontario CA 91762",
    "addr:housenumber":"939",
    "addr:postcode":"91762",
    "addr:street":"W State St",
    "iso:country":"US",
    "sg:address":"939 W State St",
    "sg:city":"Ontario",
    "sg:classifiers":[
        {
            "category":"Building & Trades",
            "subcategory":"Construction",
            "type":"Services"
        }
    ],
    "sg:phone":"+1 909 988 5317",
    "sg:postcode":"91762",
    "sg:province":"CA",
    "sg:tags":[
        "contractor"
    ],
    "wof:name":"Gabriel Ironworks",
    "wof:placetype":"venue"
},
  "geometry": {"coordinates":[-117.665509,34.059867],"type":"Point"}
}