{
  "type": "Feature",
  "properties": {
    "iso:country":"US",
    "sg:address":"400 W 3rd St",
    "sg:city":"Santa Rosa",
    "sg:classifiers":[
        {
            "category":"Manufacturing",
            "subcategory":"Printing",
            "type":"Manufacturing & Wholesale Goods"
        }
    ],
    "sg:phone":"+1 707 527 6400",
    "sg:postcode":"95401",
    "sg:province":"CA",
    "sg:tags":[
        "printer"
    ],
    "wof:name":"AAA Discount Printing",
    "wof:placetype":"venue"
},
  "geometry": {"coordinates":[-122.72675,38.434012],"type":"Point"}
}