{
  "type": "Feature",
  "properties": {
    "addr:full":"444 W C St San Diego CA 92101",
    "addr:housenumber":"444",
    "addr:postcode":"92101",
    "addr:street":"W C St",
    "iso:country":"US",
    "sg:address":"444 W C St",
    "sg:city":"San Diego",
    "sg:classifiers":[
        {
            "category":"Professional",
            "subcategory":"Lawyer & Legal Services",
            "type":"Services"
        }
    ],
    "sg:phone":"+1 619 233 8044",
    "sg:postcode":"92101",
    "sg:province":"CA",
    "wof:name":"Cameau Elizabeth E Atty A T Law",
    "wof:placetype":"venue"
},
  "geometry": {"coordinates":[-117.167,32.716801],"type":"Point"}
}