{
  "type": "Feature",
  "properties": {
    "iso:country":"US",
    "sg:address":"5328 W 142nd Pl",
    "sg:city":"Hawthorne",
    "sg:classifiers":[
        {
            "category":"Banks & Credit Unions",
            "subcategory":"Investment Brokerage",
            "type":"Services"
        }
    ],
    "sg:phone":"+1 310 643 9882",
    "sg:postcode":"90250",
    "sg:province":"CA",
    "sg:tags":[
        "security"
    ],
    "wof:name":"Hanson Investments",
    "wof:placetype":"venue"
},
  "geometry": {"coordinates":[-118.37397199999999,33.902314],"type":"Point"}
}