{
  "type": "Feature",
  "properties": {
    "addr:full":"4489 el Cajon Blvd San Diego CA 92115",
    "addr:housenumber":"4489",
    "addr:postcode":"92115",
    "addr:street":"El Cajon Blvd",
    "iso:country":"US",
    "sg:address":"4489 el Cajon Blvd",
    "sg:city":"San Diego",
    "sg:classifiers":[
        {
            "category":"Food & Beverages",
            "subcategory":"Groceries & Convenience Stores",
            "type":"Retail Goods"
        }
    ],
    "sg:phone":"+1 619 283 1145",
    "sg:postcode":"92115",
    "sg:province":"CA",
    "sg:tags":[
        "market"
    ],
    "wof:name":"Markato Market",
    "wof:placetype":"venue"
},
  "geometry": {"coordinates":[-117.097824,32.755214],"type":"Point"}
}