{
  "type": "Feature",
  "properties": {
    "addr:full":"160 N San Antonio Ave Pomona CA 91767",
    "addr:housenumber":"160",
    "addr:postcode":"91767",
    "addr:street":"N San Antonio Ave",
    "iso:country":"US",
    "sg:address":"160 N San Antonio Ave",
    "sg:city":"Pomona",
    "sg:phone":"+1 909 629 4021",
    "sg:postcode":"91767",
    "sg:province":"CA",
    "sg:tags":[
        "oil"
    ],
    "wof:name":"HASCO Oil Co",
    "wof:placetype":"venue"
},
  "geometry": {"coordinates":[-117.737042,34.060373],"type":"Point"}
}