{
  "type": "Feature",
  "properties": {
    "iso:country":"US",
    "sg:address":"30 Nopalitos Way",
    "sg:city":"Santa Barbara",
    "sg:classifiers":[
        {
            "category":"Retail",
            "subcategory":"Auto Repair",
            "type":"Services"
        }
    ],
    "sg:phone":"+1 805 962 8804",
    "sg:postcode":"93103",
    "sg:province":"CA",
    "sg:tags":[
        "repairing",
        "automobile"
    ],
    "wof:name":"Anvil Motor Sports",
    "wof:placetype":"venue"
},
  "geometry": {"coordinates":[-119.679742,34.419734],"type":"Point"}
}