{
  "type": "Feature",
  "properties": {
    "addr:full":"758 Carmel Ave Sunnyvale CA 94085",
    "addr:housenumber":"758",
    "addr:postcode":"94085",
    "addr:street":"Carmel Ave",
    "iso:country":"US",
    "sg:address":"758 Carmel Ave",
    "sg:city":"Sunnyvale",
    "sg:classifiers":[
        {
            "category":"Professional",
            "type":"Services"
        }
    ],
    "sg:phone":"+1 408 732 3440",
    "sg:postcode":"94085",
    "sg:province":"CA",
    "wof:name":"Cecilio Lopez",
    "wof:placetype":"venue"
},
  "geometry": {"coordinates":[-122.01028599999999,37.389999],"type":"Point"}
}