{
  "type": "Feature",
  "properties": {
    "iso:country":"US",
    "sg:address":"7904 Tampa Ave",
    "sg:city":"Reseda",
    "sg:classifiers":[
        {
            "category":"Building & Trades",
            "subcategory":"Construction",
            "type":"Services"
        }
    ],
    "sg:phone":"+1 818 727 0400",
    "sg:postcode":"91335",
    "sg:province":"CA",
    "sg:tags":[
        "concrete",
        "contractor"
    ],
    "wof:name":"On Time Concrete",
    "wof:placetype":"venue"
},
  "geometry": {"coordinates":[-118.553467,34.215547],"type":"Point"}
}