{
  "type": "Feature",
  "properties": {
    "addr:full":"919 San Benito Rd Berkeley CA 94707",
    "addr:housenumber":"919",
    "addr:postcode":"94707",
    "addr:street":"San Benito Rd",
    "iso:country":"US",
    "sg:address":"919 San Benito Rd",
    "sg:city":"Berkeley",
    "sg:classifiers":[
        {
            "category":"Building & Trades",
            "subcategory":"Construction",
            "type":"Services"
        }
    ],
    "sg:phone":"+1 510 527 1580",
    "sg:postcode":"94707",
    "sg:province":"CA",
    "sg:tags":[
        "residential"
    ],
    "wof:name":"Nomura Construction",
    "wof:placetype":"venue"
},
  "geometry": {"coordinates":[-122.267533,37.89104],"type":"Point"}
}