{
  "type": "Feature",
  "properties": {
    "iso:country":"US",
    "sg:address":"1102 Milky Way",
    "sg:city":"Cupertino",
    "sg:classifiers":[
        {
            "category":"Manufacturing",
            "subcategory":"Tools & Machinery",
            "type":"Manufacturing & Wholesale Goods"
        }
    ],
    "sg:phone":"+1 408 253 6849",
    "sg:postcode":"95014",
    "sg:province":"CA",
    "sg:tags":[
        "filter"
    ],
    "wof:name":"Yakima Filters  Inc",
    "wof:placetype":"venue"
},
  "geometry": {"coordinates":[-122.044512,37.305485],"type":"Point"}
}