{
  "type": "Feature",
  "properties": {
    "iso:country":"US",
    "sg:address":"718 University Ave",
    "sg:city":"Los Gatos",
    "sg:classifiers":[
        {
            "category":"Banks & Credit Unions",
            "subcategory":"Investment Brokerage",
            "type":"Services"
        }
    ],
    "sg:phone":"+1 408 395 4808",
    "sg:postcode":"95032",
    "sg:province":"CA",
    "sg:tags":[
        "consultant",
        "planning",
        "financial"
    ],
    "wof:name":"Financial Vision LLC",
    "wof:placetype":"venue"
},
  "geometry": {"coordinates":[-121.972638,37.241478],"type":"Point"}
}