{
  "type": "Feature",
  "properties": {
    "iso:country":"US",
    "sg:address":"3920 N Granada Ave",
    "sg:city":"Spring Valley",
    "sg:classifiers":[
        {
            "category":"Education",
            "subcategory":"Preschool",
            "type":"Public Place"
        },
        {
            "category":"Education",
            "subcategory":"School",
            "type":"Public Place"
        }
    ],
    "sg:phone":"+1 619 670 6101",
    "sg:postcode":"91977",
    "sg:province":"CA",
    "sg:tags":[
        "elementary"
    ],
    "wof:name":"Aka Head Start",
    "wof:placetype":"venue"
},
  "geometry": {"coordinates":[-116.979113,32.748333],"type":"Point"}
}