{
  "type": "Feature",
  "properties": {
    "iso:country":"US",
    "sg:address":"6226 Shelter Creek Ln",
    "sg:city":"San Bruno",
    "sg:classifiers":[
        {
            "category":"Professional",
            "subcategory":"Management & Consulting",
            "type":"Services"
        }
    ],
    "sg:phone":"+1 650 589 2322",
    "sg:postcode":"94066",
    "sg:province":"CA",
    "sg:tags":[
        "international",
        "business"
    ],
    "wof:name":"Market Access",
    "wof:placetype":"venue"
},
  "geometry": {"coordinates":[-122.427763,37.622051],"type":"Point"}
}