{
  "type": "Feature",
  "properties": {
    "iso:country":"US",
    "sg:address":"251 Opportunity St",
    "sg:city":"Sacramento",
    "sg:classifiers":[
        {
            "category":"Wholesale",
            "subcategory":"Machinery & Supplies",
            "type":"Manufacturing & Wholesale Goods"
        }
    ],
    "sg:phone":"+1 916 923 2962",
    "sg:postcode":"95838",
    "sg:province":"CA",
    "sg:tags":[
        "equipment",
        "establishment"
    ],
    "wof:name":"I C S West",
    "wof:placetype":"venue"
},
  "geometry": {"coordinates":[-121.458752,38.640029],"type":"Point"}
}