{
  "type": "Feature",
  "properties": {
    "addr:full":"26 S Garden St Ventura CA 93001",
    "addr:housenumber":"26",
    "addr:postcode":"93001",
    "addr:street":"S Garden St",
    "iso:country":"US",
    "sg:address":"26 S Garden St",
    "sg:city":"Ventura",
    "sg:classifiers":[
        {
            "category":"Restaurant",
            "type":"Food & Drink"
        }
    ],
    "sg:phone":"+1 805 652 0338",
    "sg:postcode":"93001",
    "sg:province":"CA",
    "sg:website":"www.yoliesmexgrill.com",
    "wof:name":"Yolie's Fresh Mex Grill",
    "wof:placetype":"venue"
},
  "geometry": {"coordinates":[-119.30219700000001,34.279929],"type":"Point"}
}