{
  "type": "Feature",
  "properties": {
    "addr:full":"154 W Bryant St Bloomington CA 92316",
    "addr:housenumber":"154",
    "addr:postcode":"92316",
    "addr:street":"W Bryant St",
    "iso:country":"US",
    "sg:address":"154 W Bryant St",
    "sg:city":"Bloomington",
    "sg:classifiers":[
        {
            "category":"Professional",
            "type":"Services"
        }
    ],
    "sg:phone":"+1 909 875 0104",
    "sg:postcode":"92316",
    "sg:province":"CA",
    "wof:name":"Mark Anthony Companies",
    "wof:placetype":"venue"
},
  "geometry": {"coordinates":[-117.371094,34.053766],"type":"Point"}
}