{
  "type": "Feature",
  "properties": {
    "addr:full":"980 W Cienega Ave San Dimas CA 91773",
    "addr:housenumber":"980",
    "addr:postcode":"91773",
    "addr:street":"W Cienega Ave",
    "iso:country":"US",
    "sg:address":"980 W Cienega Ave",
    "sg:city":"San Dimas",
    "sg:classifiers":[
        {
            "category":"Manufacturing",
            "subcategory":"Apparel",
            "type":"Manufacturing & Wholesale Goods"
        }
    ],
    "sg:phone":"+1 909 599 8200",
    "sg:postcode":"91773",
    "sg:province":"CA",
    "sg:tags":[
        "home",
        "furnishing",
        "mfg"
    ],
    "wof:name":"Pacific American Manufacturing",
    "wof:placetype":"venue"
},
  "geometry": {"coordinates":[-117.828287,34.102947],"type":"Point"}
}