{
  "type": "Feature",
  "properties": {
    "iso:country":"US",
    "sg:address":"1015 N Lake Ave Ste 204",
    "sg:city":"Pasadena",
    "sg:classifiers":[
        {
            "category":"Professional",
            "type":"Services"
        }
    ],
    "sg:phone":"+1 626 345 1413",
    "sg:postcode":"91104",
    "sg:province":"CA",
    "sg:website":"www.thecarteragency.com",
    "wof:name":"The Carter Agency",
    "wof:placetype":"venue"
},
  "geometry": {"coordinates":[-118.133098,34.163419],"type":"Point"}
}