{
  "type": "Feature",
  "properties": {
    "addr:full":"892 W Rialto Ave Rialto CA 92376",
    "addr:housenumber":"892",
    "addr:postcode":"92376",
    "addr:street":"W Rialto Ave",
    "iso:country":"US",
    "sg:address":"892 W Rialto Ave",
    "sg:city":"Rialto",
    "sg:classifiers":[
        {
            "category":"Manufacturing",
            "subcategory":"Metals",
            "type":"Manufacturing & Wholesale Goods"
        }
    ],
    "sg:phone":"+1 909 875 9181",
    "sg:postcode":"92376",
    "sg:province":"CA",
    "sg:tags":[
        "metalwork",
        "architectural",
        "mfg"
    ],
    "wof:name":"Genesis Iron Work",
    "wof:placetype":"venue"
},
  "geometry": {"coordinates":[-117.38366499999999,34.099598],"type":"Point"}
}