{
  "type": "Feature",
  "properties": {
    "iso:country":"US",
    "sg:address":"828 Date Ave",
    "sg:city":"Chula Vista",
    "sg:classifiers":[
        {
            "category":"Shopping",
            "subcategory":"Pets & Pet Supplies",
            "type":"Retail Goods"
        }
    ],
    "sg:phone":"+1 888 358 3353",
    "sg:postcode":"91911",
    "sg:province":"CA",
    "sg:website":"www.kuddlekots.com/",
    "wof:name":"KuddleKots",
    "wof:placetype":"venue"
},
  "geometry": {"coordinates":[-117.081947,32.620286],"type":"Point"}
}