{
  "type": "Feature",
  "properties": {
    "addr:full":"11765 E Mountain View Ave Kingsburg CA 93631",
    "addr:housenumber":"11765",
    "addr:postcode":"93631",
    "addr:street":"E Mountain View Ave",
    "iso:country":"US",
    "sg:address":"11765 E Mountain View Ave",
    "sg:city":"Kingsburg",
    "sg:classifiers":[
        {
            "category":"Professional",
            "subcategory":"Management & Consulting",
            "type":"Services"
        }
    ],
    "sg:phone":"+1 559 891 9040",
    "sg:postcode":"93631",
    "sg:province":"CA",
    "sg:tags":[
        "consultant",
        "energy",
        "conservation"
    ],
    "wof:name":"Kingsburg Cogeneration Faclty",
    "wof:placetype":"venue"
},
  "geometry": {"coordinates":[-119.57935000000001,36.546774],"type":"Point"}
}