{
  "type": "Feature",
  "properties": {
    "iso:country":"US",
    "sg:address":"446 Robert Ave",
    "sg:city":"Santa Clara",
    "sg:classifiers":[
        {
            "category":"Manufacturing",
            "subcategory":"Tools & Machinery",
            "type":"Manufacturing & Wholesale Goods"
        }
    ],
    "sg:phone":"+1 408 980 9242",
    "sg:postcode":"95050",
    "sg:province":"CA",
    "sg:tags":[
        "machine",
        "parts",
        "mfg"
    ],
    "wof:name":"Polex Precision Machining",
    "wof:placetype":"venue"
},
  "geometry": {"coordinates":[-121.94514100000001,37.363916],"type":"Point"}
}