{
  "type": "Feature",
  "properties": {
    "addr:full":"209 3rd St Yreka CA 96097",
    "addr:housenumber":"209",
    "addr:postcode":"96097",
    "addr:street":"3Rd St",
    "iso:country":"US",
    "sg:address":"209 3rd St",
    "sg:city":"Yreka",
    "sg:classifiers":[
        {
            "category":"Social Services",
            "type":"Services"
        }
    ],
    "sg:phone":"+1 530 842 6629",
    "sg:postcode":"96097",
    "sg:province":"CA",
    "sg:tags":[
        "crisis",
        "intervention"
    ],
    "wof:name":"Siskiyou Domestic Violence",
    "wof:placetype":"venue"
},
  "geometry": {"coordinates":[-122.636348,41.733571],"type":"Point"}
}