{
  "type": "Feature",
  "properties": {
    "addr:full":"3942 Wilda Ave Oakland CA 94611",
    "addr:housenumber":"3942",
    "addr:postcode":"94611",
    "addr:street":"Wilda Ave",
    "iso:country":"US",
    "sg:address":"3942 Wilda Ave",
    "sg:city":"Oakland",
    "sg:classifiers":[
        {
            "category":"Shopping",
            "subcategory":"Pharmacy",
            "type":"Retail Goods"
        }
    ],
    "sg:phone":"+1 510 594 1947",
    "sg:postcode":"94611",
    "sg:province":"CA",
    "sg:tags":[
        "consultants-referral",
        "pharmaceutical",
        "consultant"
    ],
    "wof:name":"Kathleen Senneca",
    "wof:placetype":"venue"
},
  "geometry": {"coordinates":[-122.25224799999999,37.823913],"type":"Point"}
}