{
  "type": "Feature",
  "properties": {
    "addr:full":"2206 Beverly Blvd Los Angeles CA 90057",
    "addr:housenumber":"2206",
    "addr:postcode":"90057",
    "addr:street":"Beverly Blvd",
    "iso:country":"US",
    "sg:address":"2206 Beverly Blvd",
    "sg:city":"Los Angeles",
    "sg:classifiers":[
        {
            "category":"Arts & Performance",
            "subcategory":"Art Gallery",
            "type":"Entertainment"
        },
        {
            "category":"Arts & Performance",
            "subcategory":"Music",
            "type":"Entertainment"
        }
    ],
    "sg:phone":"+1 213 382 3171",
    "sg:postcode":"90057",
    "sg:province":"CA",
    "sg:tags":[
        "venue"
    ],
    "sg:website":"www.myspace.com/theheargallery",
    "wof:name":"The Hear Gallery",
    "wof:placetype":"venue"
},
  "geometry": {"coordinates":[-118.272003,34.067101],"type":"Point"}
}