{
  "type": "Feature",
  "properties": {
    "iso:country":"US",
    "sg:address":"1875 S Grant St",
    "sg:city":"San Mateo",
    "sg:classifiers":[
        {
            "category":"Wholesale",
            "subcategory":"Durable Goods & Equipment",
            "type":"Manufacturing & Wholesale Goods"
        }
    ],
    "sg:phone":"+1 650 571 8483",
    "sg:postcode":"94402",
    "sg:province":"CA",
    "sg:tags":[
        "importer"
    ],
    "wof:name":"Korea Trade Ctr",
    "wof:placetype":"venue"
},
  "geometry": {"coordinates":[-122.302091,37.554463],"type":"Point"}
}