{
  "type": "Feature",
  "properties": {
    "iso:country":"US",
    "sg:address":"24436 Park St",
    "sg:city":"Torrance",
    "sg:classifiers":[
        {
            "category":"Wholesale",
            "subcategory":"Durable Goods & Equipment",
            "type":"Manufacturing & Wholesale Goods"
        }
    ],
    "sg:phone":"+1 310 465 0160",
    "sg:postcode":"90505",
    "sg:province":"CA",
    "sg:tags":[
        "exporter"
    ],
    "wof:name":"Wescom International",
    "wof:placetype":"venue"
},
  "geometry": {"coordinates":[-118.34985399999999,33.801481],"type":"Point"}
}