{
  "type": "Feature",
  "properties": {
    "addr:full":"925 Blossom Hill Road San Jose CA 95123",
    "addr:housenumber":"925",
    "addr:postcode":"95123",
    "addr:street":"Blossom Hill Road",
    "iso:country":"US",
    "sg:address":"925 Blossom Hill Road",
    "sg:city":"San Jose",
    "sg:classifiers":[
        {
            "category":"Shopping",
            "subcategory":"Jewelry",
            "type":"Retail Goods"
        }
    ],
    "sg:phone":"+1 408 365 1717",
    "sg:postcode":"95123",
    "sg:province":"CA",
    "wof:name":"The Whitehall Company. Jewellers",
    "wof:placetype":"venue"
},
  "geometry": {"coordinates":[-121.833088,37.245625],"type":"Point"}
}