{
  "type": "Feature",
  "properties": {
    "iso:country":"US",
    "sg:address":"10020 Shellabarger Rd",
    "sg:city":"Bakersfield",
    "sg:classifiers":[
        {
            "category":"Real Estate",
            "subcategory":"Real Estate Agent",
            "type":"Services"
        }
    ],
    "sg:phone":"+1 661 588 5749",
    "sg:postcode":"93312",
    "sg:province":"CA",
    "sg:tags":[
        "agency",
        "rental"
    ],
    "wof:name":"Watertruck Rental Gremillion",
    "wof:placetype":"venue"
},
  "geometry": {"coordinates":[-119.113696,35.372585],"type":"Point"}
}