{
  "type": "Feature",
  "properties": {
    "iso:country":"US",
    "sg:address":"4791 Arrow Hwy Ste A",
    "sg:city":"Montclair",
    "sg:classifiers":[
        {
            "category":"Wholesale",
            "subcategory":"Scrap",
            "type":"Manufacturing & Wholesale Goods"
        },
        {
            "category":"Utilities",
            "subcategory":"Recycling",
            "type":"Services"
        }
    ],
    "sg:phone":"+1 909 625 6098",
    "sg:postcode":"91763",
    "sg:province":"CA",
    "sg:tags":[
        "metals-wholesale",
        "metal"
    ],
    "wof:name":"Premises Metals Recycling",
    "wof:placetype":"venue"
},
  "geometry": {"coordinates":[-117.701092,34.092507],"type":"Point"}
}