{
  "type": "Feature",
  "properties": {
    "addr:full":"959 Aviation Blvd Hermosa Beach CA 90254",
    "addr:housenumber":"959",
    "addr:postcode":"90254",
    "addr:street":"Aviation Blvd",
    "iso:country":"US",
    "sg:address":"959 Aviation Blvd",
    "sg:city":"Hermosa Beach",
    "sg:classifiers":[
        {
            "category":"Restaurant",
            "type":"Food & Drink"
        }
    ],
    "sg:phone":"+1 310 372 3739",
    "sg:postcode":"90254",
    "sg:province":"CA",
    "wof:name":"Ocean Diner",
    "wof:placetype":"venue"
},
  "geometry": {"coordinates":[-118.39093,33.863302],"type":"Point"}
}