{
  "type": "Feature",
  "properties": {
    "addr:full":"6101 Geary Blvd San Francisco CA 94121",
    "addr:housenumber":"6101",
    "addr:postcode":"94121",
    "addr:street":"Geary Blvd",
    "iso:country":"US",
    "sg:address":"6101 Geary Blvd",
    "sg:city":"San Francisco",
    "sg:classifiers":[
        {
            "category":"Autos & Motor Vehicles",
            "subcategory":"Auto Supplies",
            "type":"Retail Goods"
        }
    ],
    "sg:phone":"+1 415 387 1783",
    "sg:postcode":"94121",
    "sg:province":"CA",
    "sg:tags":[
        "automobile",
        "parts"
    ],
    "wof:name":"Kragen Auto Parts",
    "wof:placetype":"venue"
},
  "geometry": {"coordinates":[-122.48580699999999,37.780038],"type":"Point"}
}