{
  "type": "Feature",
  "properties": {
    "addr:full":"560 N Moorpark Rd Thousand Oaks CA 91360",
    "addr:housenumber":"560",
    "addr:postcode":"91360",
    "addr:street":"N Moorpark Rd",
    "iso:country":"US",
    "sg:address":"560 N Moorpark Rd",
    "sg:city":"Thousand Oaks",
    "sg:classifiers":[
        {
            "category":"Manufacturing",
            "subcategory":"Printing",
            "type":"Manufacturing & Wholesale Goods"
        }
    ],
    "sg:phone":"+1 805 379 9200",
    "sg:postcode":"91360",
    "sg:province":"CA",
    "sg:tags":[
        "publisher"
    ],
    "wof:name":"RPC Marketing",
    "wof:placetype":"venue"
},
  "geometry": {"coordinates":[-118.875151,34.18445],"type":"Point"}
}