{
  "type": "Feature",
  "properties": {
    "addr:full":"814 Gabriel Ct Stockton CA 95206",
    "addr:housenumber":"814",
    "addr:postcode":"95206",
    "addr:street":"Gabriel Ct",
    "iso:country":"US",
    "sg:address":"814 Gabriel Ct",
    "sg:city":"Stockton",
    "sg:classifiers":[
        {
            "category":"Building & Trades",
            "subcategory":"Construction",
            "type":"Services"
        }
    ],
    "sg:phone":"+1 209 466 7273",
    "sg:postcode":"95206",
    "sg:province":"CA",
    "sg:tags":[
        "wallcoverings-installation",
        "wallpaper",
        "painting",
        "contractor"
    ],
    "wof:name":"Spectrum Painting",
    "wof:placetype":"venue"
},
  "geometry": {"coordinates":[-121.29938300000001,37.928225],"type":"Point"}
}