{
  "type": "Feature",
  "properties": {
    "iso:country":"US",
    "sg:address":"54 Willow Ave",
    "sg:city":"Fairfax",
    "sg:classifiers":[
        {
            "category":"Shopping",
            "subcategory":"Gifts & Souvenirs",
            "type":"Retail Goods"
        }
    ],
    "sg:phone":"+1 415 455 9432",
    "sg:postcode":"94930",
    "sg:province":"CA",
    "wof:name":"Delightfully Cherished",
    "wof:placetype":"venue"
},
  "geometry": {"coordinates":[-122.582376,37.987077],"type":"Point"}
}