{
  "type": "Feature",
  "properties": {
    "iso:country":"US",
    "sg:address":"5312 Derry Ave",
    "sg:city":"Agoura Hills",
    "sg:classifiers":[
        {
            "category":"Manufacturing",
            "subcategory":"Furniture",
            "type":"Manufacturing & Wholesale Goods"
        },
        {
            "category":"Home & Garden",
            "subcategory":"Furniture",
            "type":"Retail Goods"
        }
    ],
    "sg:phone":"+1 818 707 3878",
    "sg:postcode":"91301",
    "sg:province":"CA",
    "sg:tags":[
        "builder",
        "custom",
        "mfg"
    ],
    "wof:name":"Gluzzer",
    "wof:placetype":"venue"
},
  "geometry": {"coordinates":[-118.74790900000001,34.147439],"type":"Point"}
}