{
  "type": "Feature",
  "properties": {
    "iso:country":"US",
    "sg:address":"6412 Rushmore Dr",
    "sg:city":"Sacramento",
    "sg:classifiers":[
        {
            "category":"Professional",
            "type":"Services"
        }
    ],
    "sg:phone":"+1 916 332 8955",
    "sg:postcode":"95842",
    "sg:province":"CA",
    "wof:name":"E Headington",
    "wof:placetype":"venue"
},
  "geometry": {"coordinates":[-121.340356,38.681758],"type":"Point"}
}