{
  "type": "Feature",
  "properties": {
    "iso:country":"US",
    "sg:address":"6942 Ed Perkic St",
    "sg:city":"Riverside",
    "sg:classifiers":[
        {
            "category":"Retail",
            "subcategory":"Auto Repair",
            "type":"Services"
        }
    ],
    "sg:phone":"+1 951 637 0889",
    "sg:postcode":"92504",
    "sg:province":"CA",
    "sg:tags":[
        "recreational",
        "vehicle"
    ],
    "wof:name":"CVN Motorsports",
    "wof:placetype":"venue"
},
  "geometry": {"coordinates":[-117.444892,33.962606],"type":"Point"}
}