{
  "type": "Feature",
  "properties": {
    "iso:country":"US",
    "sg:address":"325 E Hillcrest Dr",
    "sg:city":"Thousand Oaks",
    "sg:classifiers":[
        {
            "category":"Insurance",
            "subcategory":"Insurance Agent",
            "type":"Services"
        }
    ],
    "sg:phone":"+1 805 374 2882",
    "sg:postcode":"91360",
    "sg:province":"CA",
    "wof:name":"Stanton-Gamboa Insurance",
    "wof:placetype":"venue"
},
  "geometry": {"coordinates":[-118.871323,34.181324],"type":"Point"}
}