{
  "type": "Feature",
  "properties": {
    "addr:full":"4424 San Jose St Apt 33 Montclair CA 91763",
    "addr:housenumber":"4424;33",
    "addr:postcode":"91763",
    "addr:street":"San Jose St Apt",
    "iso:country":"US",
    "sg:address":"4424 San Jose St Apt 33",
    "sg:city":"Montclair",
    "sg:classifiers":[
        {
            "category":"Structure",
            "subcategory":"Office Building",
            "type":"Public Place"
        }
    ],
    "sg:phone":"+1 909 625 3101",
    "sg:postcode":"91763",
    "sg:province":"CA",
    "sg:tags":[
        "park"
    ],
    "wof:name":"Woodard Properties",
    "wof:placetype":"venue"
},
  "geometry": {"coordinates":[-117.708119,34.085269],"type":"Point"}
}