{
  "type": "Feature",
  "properties": {
    "iso:country":"US",
    "sg:address":"110 N Williams St",
    "sg:city":"Hanford",
    "sg:classifiers":[
        {
            "category":"Retail",
            "subcategory":"Auto Repair",
            "type":"Services"
        }
    ],
    "sg:phone":"+1 559 582 0433",
    "sg:postcode":"93230",
    "sg:province":"CA",
    "sg:tags":[
        "machine",
        "automobile",
        "shop"
    ],
    "wof:name":"Olson's Auto Machine & Marine",
    "wof:placetype":"venue"
},
  "geometry": {"coordinates":[-119.653882,36.325783],"type":"Point"}
}