{
  "type": "Feature",
  "properties": {
    "iso:country":"US",
    "sg:address":"27052 Mallorca Ln",
    "sg:city":"Mission Viejo",
    "sg:classifiers":[
        {
            "category":"Building & Trades",
            "subcategory":"Construction",
            "type":"Services"
        }
    ],
    "sg:phone":"+1 949 582 6999",
    "sg:postcode":"92691",
    "sg:province":"CA",
    "sg:tags":[
        "contractor"
    ],
    "wof:name":"Ziemer Todd",
    "wof:placetype":"venue"
},
  "geometry": {"coordinates":[-117.66994699999999,33.569715],"type":"Point"}
}