{
  "type": "Feature",
  "properties": {
    "addr:full":"12556 Bellder Dr Downey CA 90242",
    "addr:housenumber":"12556",
    "addr:postcode":"90242",
    "addr:street":"Bellder Dr",
    "iso:country":"US",
    "sg:address":"12556 Bellder Dr",
    "sg:city":"Downey",
    "sg:classifiers":[
        {
            "category":"Wholesale",
            "subcategory":"Durable Goods & Equipment",
            "type":"Manufacturing & Wholesale Goods"
        }
    ],
    "sg:phone":"+1 562 862 6213",
    "sg:postcode":"90242",
    "sg:province":"CA",
    "wof:name":"Fire Max Fire Protection",
    "wof:placetype":"venue"
},
  "geometry": {"coordinates":[-118.14272099999999,33.919506],"type":"Point"}
}