{
  "type": "Feature",
  "properties": {
    "iso:country":"US",
    "sg:address":"9511 Artesia Blvd",
    "sg:city":"Bellflower",
    "sg:classifiers":[
        {
            "category":"Retail",
            "subcategory":"Auto Repair",
            "type":"Services"
        }
    ],
    "sg:phone":"+1 562 867 6266",
    "sg:postcode":"90706",
    "sg:province":"CA",
    "wof:name":"Amy's Auto",
    "wof:placetype":"venue"
},
  "geometry": {"coordinates":[-118.130997,33.875],"type":"Point"}
}