{
  "type": "Feature",
  "properties": {
    "iso:country":"US",
    "sg:address":"47609 Avalon Heights Ter",
    "sg:city":"Fremont",
    "sg:classifiers":[
        {
            "category":"Social Services",
            "type":"Services"
        },
        {
            "category":"Professional",
            "subcategory":"Employment Agencies",
            "type":"Services"
        }
    ],
    "sg:phone":"+1 510 651 2547",
    "sg:postcode":"94539",
    "sg:province":"CA",
    "sg:tags":[
        "workers'",
        "placement",
        "volunteer"
    ],
    "wof:name":"Aswani Foundation",
    "wof:placetype":"venue"
},
  "geometry": {"coordinates":[-121.90574599999999,37.488008],"type":"Point"}
}