{
  "type": "Feature",
  "properties": {
    "addr:full":"25202 Crenshaw Blvd Torrance CA 90505",
    "addr:housenumber":"25202",
    "addr:postcode":"90505",
    "addr:street":"Crenshaw Blvd",
    "iso:country":"US",
    "sg:address":"25202 Crenshaw Blvd",
    "sg:city":"Torrance",
    "sg:classifiers":[
        {
            "category":"Health Services",
            "subcategory":"Health Practitioner",
            "type":"Services"
        }
    ],
    "sg:phone":"+1 310 325 6692",
    "sg:postcode":"90505",
    "sg:province":"CA",
    "sg:tags":[
        "psychotherapist"
    ],
    "wof:name":"Lisa Richards",
    "wof:placetype":"venue"
},
  "geometry": {"coordinates":[-118.329033,33.794677],"type":"Point"}
}