{
  "type": "Feature",
  "properties": {
    "iso:country":"US",
    "sg:address":"452 Blossom Hill Rd.",
    "sg:city":"San Jose",
    "sg:classifiers":[
        {
            "category":"Autos & Motor Vehicles",
            "subcategory":"Fuel & Gas Station",
            "type":"Retail Goods"
        },
        {
            "category":"Retail",
            "subcategory":"Car Wash",
            "type":"Services"
        }
    ],
    "sg:postcode":"95123",
    "sg:province":"CA",
    "wof:name":"Chevron",
    "wof:placetype":"venue"
},
  "geometry": {"coordinates":[-121.831284,37.250889],"type":"Point"}
}