{
  "type": "Feature",
  "properties": {
    "addr:full":"600 W Main St Ste 204 Alhambra CA 91801",
    "addr:housenumber":"600",
    "addr:postcode":"91801",
    "addr:street":"W Main St Ste 204",
    "iso:country":"US",
    "sg:address":"600 W Main St Ste 204",
    "sg:city":"Alhambra",
    "sg:classifiers":[
        {
            "category":"Professional",
            "subcategory":"Computer Services",
            "type":"Services"
        }
    ],
    "sg:phone":"+1 626 299 5900",
    "sg:postcode":"91801",
    "sg:province":"CA",
    "sg:tags":[
        "repair"
    ],
    "wof:name":"Cms Network Inc",
    "wof:placetype":"venue"
},
  "geometry": {"coordinates":[-118.133003,34.092098],"type":"Point"}
}