{
  "type": "Feature",
  "properties": {
    "iso:country":"US",
    "sg:address":"4120 Birch St",
    "sg:city":"Newport Beach",
    "sg:classifiers":[
        {
            "category":"Real Estate",
            "subcategory":"Real Estate Agent",
            "type":"Services"
        }
    ],
    "sg:phone":"+1 949 574 2707",
    "sg:postcode":"92660",
    "sg:province":"CA",
    "sg:tags":[
        "management"
    ],
    "wof:name":"Konwiser Corp",
    "wof:placetype":"venue"
},
  "geometry": {"coordinates":[-117.870363,33.664043],"type":"Point"}
}