{
  "type": "Feature",
  "properties": {
    "iso:country":"US",
    "sg:address":"4079 54th St",
    "sg:city":"San Diego",
    "sg:classifiers":[
        {
            "category":"Organizations",
            "subcategory":"Religious Organization",
            "type":"Services"
        }
    ],
    "sg:phone":"+1 619 229 2800",
    "sg:postcode":"92105",
    "sg:province":"CA",
    "sg:tags":[
        "church"
    ],
    "sg:website":"www.apostolicpower.org",
    "wof:name":"North Park Apostolic Church",
    "wof:placetype":"venue"
},
  "geometry": {"coordinates":[-117.079351,32.749354],"type":"Point"}
}