{
  "type": "Feature",
  "properties": {
    "iso:country":"US",
    "sg:address":"211 Sandpiper Dr",
    "sg:city":"Galt",
    "sg:classifiers":[
        {
            "category":"Professional",
            "subcategory":"Engineering",
            "type":"Services"
        }
    ],
    "sg:phone":"+1 209 745 7908",
    "sg:postcode":"95632",
    "sg:province":"CA",
    "sg:tags":[
        "engineer"
    ],
    "wof:name":"MNL Enterprises",
    "wof:placetype":"venue"
},
  "geometry": {"coordinates":[-121.319958,38.261297],"type":"Point"}
}