{
  "type": "Feature",
  "properties": {
    "addr:full":"3929 New Zealand Ave Santa Rosa CA 95407",
    "addr:housenumber":"3929",
    "addr:postcode":"95407",
    "addr:street":"New;Ave",
    "iso:country":"US",
    "sg:address":"3929 New Zealand Ave",
    "sg:city":"Santa Rosa",
    "sg:classifiers":[
        {
            "category":"Professional",
            "subcategory":"Management & Consulting",
            "type":"Services"
        }
    ],
    "sg:phone":"+1 707 591 0880",
    "sg:postcode":"95407",
    "sg:province":"CA",
    "sg:tags":[
        "project"
    ],
    "wof:name":"Alan Strachan",
    "wof:placetype":"venue"
},
  "geometry": {"coordinates":[-122.763335,38.423943],"type":"Point"}
}