{
  "type": "Feature",
  "properties": {
    "iso:country":"US",
    "sg:address":"512 Elm Ave",
    "sg:city":"Chowchilla",
    "sg:classifiers":[
        {
            "category":"Real Estate",
            "subcategory":"Real Estate Agent",
            "type":"Services"
        }
    ],
    "sg:phone":"+1 209 658 9292",
    "sg:postcode":"93610",
    "sg:province":"CA",
    "wof:name":"Floyd De La Cruz",
    "wof:placetype":"venue"
},
  "geometry": {"coordinates":[-120.28049,37.114023],"type":"Point"}
}