{
  "type": "Feature",
  "properties": {
    "iso:country":"US",
    "sg:address":"3538 Golden Gate Way",
    "sg:city":"Lafayette",
    "sg:classifiers":[
        {
            "category":"Health Services",
            "subcategory":"Health Practitioner",
            "type":"Services"
        }
    ],
    "sg:phone":"+1 925 962 0995",
    "sg:postcode":"94549",
    "sg:province":"CA",
    "sg:tags":[
        "therapist",
        "physical"
    ],
    "wof:name":"Focus On Function",
    "wof:placetype":"venue"
},
  "geometry": {"coordinates":[-122.118407,37.892093],"type":"Point"}
}