{
  "type": "Feature",
  "properties": {
    "addr:full":"1339 E Katella Ave Orange CA 92867",
    "addr:housenumber":"1339",
    "addr:postcode":"92867",
    "addr:street":"E Katella Ave",
    "iso:country":"US",
    "sg:address":"1339 E Katella Ave",
    "sg:city":"Orange",
    "sg:classifiers":[
        {
            "category":"Recreation",
            "type":"Entertainment"
        }
    ],
    "sg:phone":"+1 714 637 5009",
    "sg:postcode":"92867",
    "sg:province":"CA",
    "sg:tags":[
        "tour",
        "guide"
    ],
    "wof:name":"Sunland Tours LLC",
    "wof:placetype":"venue"
},
  "geometry": {"coordinates":[-117.836106,33.809255],"type":"Point"}
}