{
  "type": "Feature",
  "properties": {
    "addr:full":"5985 Florence Ave Bell Gardens CA 90201",
    "addr:housenumber":"5985",
    "addr:postcode":"90201",
    "addr:street":"Florence Ave",
    "iso:country":"US",
    "sg:address":"5985 Florence Ave",
    "sg:city":"Bell Gardens",
    "sg:classifiers":[
        {
            "category":"Food & Beverages",
            "subcategory":"Liquor & Beverages",
            "type":"Retail Goods"
        }
    ],
    "sg:phone":"+1 323 773 7977",
    "sg:postcode":"90201",
    "sg:province":"CA",
    "sg:tags":[
        "beer",
        "spirit",
        "wine"
    ],
    "wof:name":"Hi-Bon Liquor",
    "wof:placetype":"venue"
},
  "geometry": {"coordinates":[-118.15799699999999,33.967201],"type":"Point"}
}