{
  "type": "Feature",
  "properties": {
    "iso:country":"US",
    "sg:address":"4971 E Iowa Ave",
    "sg:city":"Fresno",
    "sg:classifiers":[
        {
            "category":"Freight",
            "type":"Transportation"
        }
    ],
    "sg:phone":"+1 559 253 1630",
    "sg:postcode":"93727",
    "sg:province":"CA",
    "sg:tags":[
        "trucking"
    ],
    "wof:name":"J & N Trucking",
    "wof:placetype":"venue"
},
  "geometry": {"coordinates":[-119.72819200000001,36.744151],"type":"Point"}
}