{
  "type": "Feature",
  "properties": {
    "iso:country":"US",
    "sg:address":"215 Church Rd",
    "sg:city":"Ojai",
    "sg:classifiers":[
        {
            "category":"Professional",
            "subcategory":"Business Services",
            "type":"Services"
        }
    ],
    "sg:phone":"+1 805 646 6673",
    "sg:postcode":"93023",
    "sg:province":"CA",
    "sg:tags":[
        "interior",
        "consultant",
        "design",
        "decorator"
    ],
    "sg:website":"www.maraya.com",
    "wof:name":"Droney Maraya Design",
    "wof:placetype":"venue"
},
  "geometry": {"coordinates":[-119.26718,34.443583],"type":"Point"}
}