{
  "type": "Feature",
  "properties": {
    "iso:country":"US",
    "sg:address":"4009 Cherokee Rd",
    "sg:city":"Stockton",
    "sg:classifiers":[
        {
            "category":"Building & Trades",
            "subcategory":"Pest Control",
            "type":"Services"
        }
    ],
    "sg:phone":"+1 209 333 0793",
    "sg:postcode":"95215",
    "sg:province":"CA",
    "sg:tags":[
        "industrial",
        "services-commercial",
        "mothproofing"
    ],
    "sg:website":"http://www.terminix.com",
    "wof:name":"Terminix International Co",
    "wof:placetype":"venue"
},
  "geometry": {"coordinates":[-121.250801,37.9945],"type":"Point"}
}