{
  "type": "Feature",
  "properties": {
    "addr:full":"1901 1st Avenue Suite 335 San Diego CA 92101",
    "addr:housenumber":"1901",
    "addr:postcode":"92101",
    "addr:street":"1St Avenue Suite 335",
    "iso:country":"US",
    "sg:address":"1901 1st Avenue Suite 335",
    "sg:city":"San Diego",
    "sg:classifiers":[
        {
            "category":"Professional",
            "subcategory":"Lawyer & Legal Services",
            "type":"Services"
        }
    ],
    "sg:phone":"+1 619 234 3446",
    "sg:postcode":"92101",
    "sg:province":"CA",
    "wof:name":"The Law Offices of Kathleen E Holden",
    "wof:placetype":"venue"
},
  "geometry": {"coordinates":[-117.163878,32.725216],"type":"Point"}
}