{
  "type": "Feature",
  "properties": {
    "addr:full":"8606 Melrose Ave West Hollywood CA 90069",
    "addr:housenumber":"8606",
    "addr:postcode":"90069",
    "addr:street":"Melrose Ave",
    "iso:country":"US",
    "sg:address":"8606 Melrose Ave",
    "sg:city":"West Hollywood",
    "sg:classifiers":[
        {
            "category":"Shopping",
            "subcategory":"Hobbies, Toys, & Games",
            "type":"Retail Goods"
        }
    ],
    "sg:phone":"+1 310 659 9838",
    "sg:postcode":"90069",
    "sg:province":"CA",
    "sg:tags":[
        "product",
        "ceramic"
    ],
    "wof:name":"Sabi",
    "wof:placetype":"venue"
},
  "geometry": {"coordinates":[-118.380465,34.0819],"type":"Point"}
}