{
  "type": "Feature",
  "properties": {
    "iso:country":"US",
    "sg:address":"3448 Foothill Blvd",
    "sg:city":"Glendale",
    "sg:classifiers":[
        {
            "category":"Retail",
            "subcategory":"Laundry & Dry Cleaning",
            "type":"Services"
        }
    ],
    "sg:phone":"+1 818 541 0230",
    "sg:postcode":"91214",
    "sg:province":"CA",
    "sg:tags":[
        "cleaners"
    ],
    "wof:name":"Superior Dry Cleaners",
    "wof:placetype":"venue"
},
  "geometry": {"coordinates":[-118.253014,34.232292],"type":"Point"}
}