{
  "type": "Feature",
  "properties": {
    "iso:country":"US",
    "sg:address":"8130 Berry Ave",
    "sg:city":"Sacramento",
    "sg:classifiers":[
        {
            "category":"Autos & Motor Vehicles",
            "subcategory":"Auto Supplies",
            "type":"Retail Goods"
        }
    ],
    "sg:phone":"+1 916 838 1880",
    "sg:postcode":"95828",
    "sg:province":"CA",
    "wof:name":"Voodoo Motorsports Wear",
    "wof:placetype":"venue"
},
  "geometry": {"coordinates":[-121.40201399999999,38.505678],"type":"Point"}
}