{
  "type": "Feature",
  "properties": {
    "addr:full":"2600 Auburn Blvd Sacramento CA 95821",
    "addr:housenumber":"2600",
    "addr:postcode":"95821",
    "addr:street":"Auburn Blvd",
    "iso:country":"US",
    "sg:address":"2600 Auburn Blvd",
    "sg:city":"Sacramento",
    "sg:classifiers":[
        {
            "category":"Organizations",
            "subcategory":"Membership Organization",
            "type":"Services"
        }
    ],
    "sg:phone":"+1 916 481 6020",
    "sg:postcode":"95821",
    "sg:province":"CA",
    "sg:tags":[
        "military",
        "veteran"
    ],
    "wof:name":"Vietnam Veterans Of America Inc",
    "wof:placetype":"venue"
},
  "geometry": {"coordinates":[-121.40145099999999,38.630051],"type":"Point"}
}