{
  "type": "Feature",
  "properties": {
    "addr:full":"5330 College Ave Oakland CA 94618",
    "addr:housenumber":"5330",
    "addr:postcode":"94618",
    "addr:street":"College Ave",
    "iso:country":"US",
    "sg:address":"5330 College Ave",
    "sg:city":"Oakland",
    "sg:classifiers":[
        {
            "category":"Shopping",
            "subcategory":"Antiques",
            "type":"Retail Goods"
        }
    ],
    "sg:phone":"+1 510 420 1950",
    "sg:postcode":"94618",
    "sg:province":"CA",
    "wof:name":"Form Vintage Modern",
    "wof:placetype":"venue"
},
  "geometry": {"coordinates":[-122.251311,37.838616],"type":"Point"}
}