{
  "type": "Feature",
  "properties": {
    "iso:country":"US",
    "sg:address":"9342 Oak St",
    "sg:city":"Bellflower",
    "sg:classifiers":[
        {
            "category":"Building & Trades",
            "subcategory":"Landscaping Services",
            "type":"Services"
        }
    ],
    "sg:phone":"+1 562 925 7608",
    "sg:postcode":"90706",
    "sg:province":"CA",
    "sg:tags":[
        "lawn",
        "maintenance",
        "grounds"
    ],
    "wof:name":"AAA Edwards Lawn Svc",
    "wof:placetype":"venue"
},
  "geometry": {"coordinates":[-118.134716,33.884701],"type":"Point"}
}