{
  "type": "Feature",
  "properties": {
    "addr:full":"991 W El Camino Real Sunnyvale CA 94087",
    "addr:housenumber":"991",
    "addr:postcode":"94087",
    "addr:street":"W El Camino Real",
    "iso:country":"US",
    "sg:address":"991 W El Camino Real",
    "sg:city":"Sunnyvale",
    "sg:classifiers":[
        {
            "category":"Restaurant",
            "type":"Food & Drink"
        }
    ],
    "sg:menulink":"http://www.allmenus.com/ca/san-jose/214210-taco-bell/menu/",
    "sg:phone":"+1 408 739 4645",
    "sg:postcode":"94087",
    "sg:province":"CA",
    "sg:tags":[
        "mexican"
    ],
    "wof:name":"Taco Bell",
    "wof:placetype":"venue"
},
  "geometry": {"coordinates":[-122.047663,37.372189],"type":"Point"}
}