{
  "type": "Feature",
  "properties": {
    "addr:full":"24422 Hawthorne Blvd Torrance CA 90505",
    "addr:housenumber":"24422",
    "addr:postcode":"90505",
    "addr:street":"Hawthorne Blvd",
    "iso:country":"US",
    "sg:address":"24422 Hawthorne Blvd",
    "sg:city":"Torrance",
    "sg:classifiers":[
        {
            "category":"Personal",
            "subcategory":"Beauty Salon",
            "type":"Services"
        }
    ],
    "sg:phone":"+1 310 791 0903",
    "sg:postcode":"90505",
    "sg:province":"CA",
    "wof:name":"J T Hair Salon",
    "wof:placetype":"venue"
},
  "geometry": {"coordinates":[-118.350945,33.80145],"type":"Point"}
}