{
  "type": "Feature",
  "properties": {
    "iso:country":"US",
    "sg:address":"2712 Drew Ln",
    "sg:city":"Lemon Grove",
    "sg:classifiers":[
        {
            "category":"Building & Trades",
            "subcategory":"Construction",
            "type":"Services"
        }
    ],
    "sg:phone":"+1 619 589 8487",
    "sg:postcode":"91945",
    "sg:province":"CA",
    "sg:tags":[
        "erectors",
        "machinery"
    ],
    "wof:name":"Cleve Forklift Svc",
    "wof:placetype":"venue"
},
  "geometry": {"coordinates":[-117.041535,32.737694],"type":"Point"}
}