{
  "type": "Feature",
  "properties": {
    "addr:full":"2235 Park Towne Cir Sacramento CA 95825",
    "addr:housenumber":"2235",
    "addr:postcode":"95825",
    "addr:street":"Park Towne Cir",
    "iso:country":"US",
    "sg:address":"2235 Park Towne Cir",
    "sg:city":"Sacramento",
    "sg:classifiers":[
        {
            "category":"Professional",
            "subcategory":"Lawyer & Legal Services",
            "type":"Services"
        }
    ],
    "sg:phone":"+1 916 453 0333",
    "sg:postcode":"95825",
    "sg:province":"CA",
    "sg:tags":[
        "attorney"
    ],
    "wof:name":"Wilson & Wong",
    "wof:placetype":"venue"
},
  "geometry": {"coordinates":[-121.384744,38.60569],"type":"Point"}
}