{
  "type": "Feature",
  "properties": {
    "iso:country":"US",
    "sg:address":"27665 Commerce Center Dr",
    "sg:city":"Temecula",
    "sg:classifiers":[
        {
            "category":"Building & Trades",
            "subcategory":"Construction",
            "type":"Services"
        }
    ],
    "sg:phone":"+1 951 506 1966",
    "sg:postcode":"92590",
    "sg:province":"CA",
    "sg:tags":[
        "tile",
        "dealer"
    ],
    "wof:name":"Southwest Tile & Granite",
    "wof:placetype":"venue"
},
  "geometry": {"coordinates":[-117.162414,33.513642],"type":"Point"}
}