{
  "type": "Feature",
  "properties": {
    "addr:full":"624 Ruisseau Francais Ave Half Moon Bay CA 94019",
    "addr:housenumber":"624",
    "addr:postcode":"94019",
    "addr:street":"Ruisseau Francais Ave",
    "iso:country":"US",
    "sg:address":"624 Ruisseau Francais Ave",
    "sg:city":"Half Moon Bay",
    "sg:classifiers":[
        {
            "category":"Education",
            "subcategory":"Special Training",
            "type":"Public Place"
        }
    ],
    "sg:phone":"+1 650 726 1906",
    "sg:postcode":"94019",
    "sg:province":"CA",
    "sg:tags":[
        "self",
        "motivational",
        "improvement"
    ],
    "wof:name":"Linda J Dvorak",
    "wof:placetype":"venue"
},
  "geometry": {"coordinates":[-122.44208399999999,37.484525],"type":"Point"}
}