{
  "type": "Feature",
  "properties": {
    "iso:country":"US",
    "sg:address":"225 S Civic Dr",
    "sg:city":"Palm Springs",
    "sg:classifiers":[
        {
            "category":"Professional",
            "subcategory":"Lawyer & Legal Services",
            "type":"Services"
        }
    ],
    "sg:phone":"+1 760 327 1285",
    "sg:postcode":"92262",
    "sg:province":"CA",
    "sg:tags":[
        "attorney"
    ],
    "wof:name":"Gilbert Gilbert & Bourke",
    "wof:placetype":"venue"
},
  "geometry": {"coordinates":[-116.51267199999999,33.822682],"type":"Point"}
}