{
  "type": "Feature",
  "properties": {
    "iso:country":"US",
    "sg:address":"1226 N Hacienda Blvd",
    "sg:city":"La Puente",
    "sg:classifiers":[
        {
            "category":"Retail",
            "subcategory":"Auto Rental",
            "type":"Services"
        }
    ],
    "sg:phone":"+1 626 333 1760",
    "sg:postcode":"91744",
    "sg:province":"CA",
    "sg:tags":[
        "passenger",
        "car"
    ],
    "wof:name":"Enterprise Rent-A-Car",
    "wof:placetype":"venue"
},
  "geometry": {"coordinates":[-117.948818,34.04563],"type":"Point"}
}