{
  "type": "Feature",
  "properties": {
    "addr:full":"1186 Chestnut St Menlo Park CA 94025",
    "addr:housenumber":"1186",
    "addr:postcode":"94025",
    "addr:street":"Chestnut St",
    "iso:country":"US",
    "sg:address":"1186 Chestnut St",
    "sg:city":"Menlo Park",
    "sg:classifiers":[
        {
            "category":"Health Services",
            "subcategory":"Doctor",
            "type":"Services"
        }
    ],
    "sg:phone":"+1 650 473 1107",
    "sg:postcode":"94025",
    "sg:province":"CA",
    "sg:tags":[
        "clinic"
    ],
    "sg:website":"www.reikiclinic.com",
    "wof:name":"Reiki Clinic",
    "wof:placetype":"venue"
},
  "geometry": {"coordinates":[-122.18566800000001,37.452392],"type":"Point"}
}