{
  "type": "Feature",
  "properties": {
    "addr:full":"4654 W Ave B Palmdale CA 93536",
    "addr:housenumber":"4654",
    "addr:postcode":"ca 93536",
    "addr:street":"W Ave B",
    "iso:country":"US",
    "sg:address":"4654 W Ave B",
    "sg:city":"Palmdale",
    "sg:classifiers":[
        {
            "category":"Professional",
            "subcategory":"Advertising",
            "type":"Services"
        }
    ],
    "sg:phone":"+1 661 285 4318",
    "sg:postcode":"93536",
    "sg:province":"CA",
    "sg:tags":[
        "mailing",
        "shipping"
    ],
    "wof:name":"Avenue S Mail N More",
    "wof:placetype":"venue"
},
  "geometry": {"coordinates":[-118.21339,34.805559],"type":"Point"}
}