{
  "type": "Feature",
  "properties": {
    "addr:full":"701 Front St Santa Cruz CA 95060",
    "addr:housenumber":"701",
    "addr:postcode":"95060",
    "addr:street":"Front St",
    "iso:country":"US",
    "sg:address":"701 Front St",
    "sg:city":"Santa Cruz",
    "sg:classifiers":[
        {
            "category":"Shopping",
            "subcategory":"Shoes",
            "type":"Retail Goods"
        }
    ],
    "sg:phone":"+1 831 426 1654",
    "sg:postcode":"95060",
    "sg:province":"CA",
    "wof:name":"Bunny's Too",
    "wof:placetype":"venue"
},
  "geometry": {"coordinates":[-122.02545000000001,36.975193],"type":"Point"}
}