{
  "type": "Feature",
  "properties": {
    "iso:country":"US",
    "sg:address":"18737 Napa St",
    "sg:city":"Northridge",
    "sg:classifiers":[
        {
            "category":"Wholesale",
            "subcategory":"Apparel",
            "type":"Manufacturing & Wholesale Goods"
        }
    ],
    "sg:phone":"+1 818 998 5021",
    "sg:postcode":"91324",
    "sg:province":"CA",
    "sg:tags":[
        "clothing",
        "mfg"
    ],
    "wof:name":"Clothing Manufacturers",
    "wof:placetype":"venue"
},
  "geometry": {"coordinates":[-118.542453,34.226493],"type":"Point"}
}