{
  "type": "Feature",
  "properties": {
    "addr:full":"4249 18th St San Francisco CA 94114",
    "addr:housenumber":"4249",
    "addr:postcode":"94114",
    "addr:street":"18Th St",
    "iso:country":"US",
    "sg:address":"4249 18th St",
    "sg:city":"San Francisco",
    "sg:classifiers":[
        {
            "category":"Shopping",
            "subcategory":"Clothing, Apparel, & Fashions",
            "type":"Retail Goods"
        }
    ],
    "sg:phone":"+1 415 626 0311",
    "sg:postcode":"94114",
    "sg:province":"CA",
    "wof:name":"Cottage Industries",
    "wof:placetype":"venue"
},
  "geometry": {"coordinates":[-122.436768,37.760715],"type":"Point"}
}