{
  "type": "Feature",
  "properties": {
    "addr:full":"1636 Francisco St Berkeley CA 94703",
    "addr:housenumber":"1636",
    "addr:postcode":"94703",
    "addr:street":"Francisco St",
    "iso:country":"US",
    "sg:address":"1636 Francisco St",
    "sg:city":"Berkeley",
    "sg:classifiers":[
        {
            "category":"Professional",
            "subcategory":"Computer Services",
            "type":"Services"
        },
        {
            "category":"Wholesale",
            "subcategory":"Computers",
            "type":"Manufacturing & Wholesale Goods"
        }
    ],
    "sg:phone":"+1 510 647 9206",
    "sg:postcode":"94703",
    "sg:province":"CA",
    "sg:tags":[
        "equipment",
        "software"
    ],
    "wof:name":"Factle",
    "wof:placetype":"venue"
},
  "geometry": {"coordinates":[-122.279338,37.874348],"type":"Point"}
}