{
  "type": "Feature",
  "properties": {
    "addr:full":"727 Agnew Pl Santa Rosa CA 95401",
    "addr:housenumber":"727",
    "addr:postcode":"95401",
    "addr:street":"Agnew Pl",
    "iso:country":"US",
    "sg:address":"727 Agnew Pl",
    "sg:city":"Santa Rosa",
    "sg:classifiers":[
        {
            "category":"Building & Trades",
            "subcategory":"Construction",
            "type":"Services"
        }
    ],
    "sg:phone":"+1 707 528 0388",
    "sg:postcode":"95401",
    "sg:province":"CA",
    "sg:tags":[
        "paving",
        "contractor"
    ],
    "wof:name":"A & L Asphalt Maintenance",
    "wof:placetype":"venue"
},
  "geometry": {"coordinates":[-122.742,38.441862],"type":"Point"}
}