{
  "type": "Feature",
  "properties": {
    "iso:country":"US",
    "sg:address":"8806 E Ave T",
    "sg:city":"Littlerock",
    "sg:classifiers":[
        {
            "category":"Building & Trades",
            "subcategory":"Construction",
            "type":"Services"
        }
    ],
    "sg:phone":"+1 661 944 1859",
    "sg:postcode":"93543",
    "sg:province":"CA",
    "sg:tags":[
        "contractor"
    ],
    "wof:name":"Wendell N Harrell",
    "wof:placetype":"venue"
},
  "geometry": {"coordinates":[-117.97345199999999,34.542854],"type":"Point"}
}