{
  "type": "Feature",
  "properties": {
    "iso:country":"US",
    "sg:address":"7354 Ethel Ave",
    "sg:city":"North Hollywood",
    "sg:classifiers":[
        {
            "category":"Wholesale",
            "subcategory":"Apparel",
            "type":"Manufacturing & Wholesale Goods"
        },
        {
            "category":"Manufacturing",
            "subcategory":"Motor Vehicles & Parts",
            "type":"Manufacturing & Wholesale Goods"
        }
    ],
    "sg:phone":"+1 818 759 0083",
    "sg:postcode":"91605",
    "sg:province":"CA",
    "sg:tags":[
        "cloth",
        "cap",
        "sportswear",
        "mfg"
    ],
    "wof:name":"Jimi Cap Inc",
    "wof:placetype":"venue"
},
  "geometry": {"coordinates":[-118.41808399999999,34.203712],"type":"Point"}
}