{
  "type": "Feature",
  "properties": {
    "iso:country":"US",
    "sg:address":"3138 E Dakota Ave",
    "sg:city":"Fresno",
    "sg:classifiers":[
        {
            "category":"Shopping",
            "subcategory":"Bicycles & Sporting Goods",
            "type":"Retail Goods"
        }
    ],
    "sg:phone":"+1 559 288 4560",
    "sg:postcode":"93726",
    "sg:province":"CA",
    "sg:tags":[
        "gun",
        "gunsmith"
    ],
    "wof:name":"Sunrise Mercantile Co",
    "wof:placetype":"venue"
},
  "geometry": {"coordinates":[-119.76942200000001,36.786737],"type":"Point"}
}