{
  "type": "Feature",
  "properties": {
    "iso:country":"US",
    "sg:address":"963 Menlo Ave",
    "sg:city":"Los Angeles",
    "sg:classifiers":[
        {
            "category":"Building & Trades",
            "subcategory":"Cleaning & Sanitation",
            "type":"Services"
        }
    ],
    "sg:phone":"+1 213 386 8605",
    "sg:postcode":"90006",
    "sg:province":"CA",
    "sg:tags":[
        "janitor"
    ],
    "wof:name":"American Real Maid Svc",
    "wof:placetype":"venue"
},
  "geometry": {"coordinates":[-118.290431,34.054037],"type":"Point"}
}