{
  "type": "Feature",
  "properties": {
    "addr:full":"1988 Hartog Dr San Jose CA 95131",
    "addr:housenumber":"1988",
    "addr:postcode":"95131",
    "addr:street":"Hartog Dr",
    "iso:country":"US",
    "sg:address":"1988 Hartog Dr",
    "sg:city":"San Jose",
    "sg:classifiers":[
        {
            "category":"Freight",
            "type":"Transportation"
        }
    ],
    "sg:phone":"+1 408 392 8920",
    "sg:postcode":"95131",
    "sg:province":"CA",
    "sg:tags":[
        "mover"
    ],
    "wof:name":"Survivors Moving & Storage",
    "wof:placetype":"venue"
},
  "geometry": {"coordinates":[-121.909145,37.381665],"type":"Point"}
}