{
  "type": "Feature",
  "properties": {
    "iso:country":"US",
    "sg:address":"705 S Miller St",
    "sg:city":"Santa Maria",
    "sg:classifiers":[
        {
            "category":"Retail",
            "subcategory":"Auto Repair",
            "type":"Services"
        }
    ],
    "sg:phone":"+1 805 928 6522",
    "sg:postcode":"93454",
    "sg:province":"CA",
    "sg:tags":[
        "repairing",
        "automobile"
    ],
    "wof:name":"Dave's Automotive Repair II",
    "wof:placetype":"venue"
},
  "geometry": {"coordinates":[-120.431619,34.945777],"type":"Point"}
}