{
  "type": "Feature",
  "properties": {
    "iso:country":"US",
    "sg:address":"600 E Weddell Dr",
    "sg:city":"Sunnyvale",
    "sg:classifiers":[
        {
            "category":"Professional",
            "subcategory":"Engineering",
            "type":"Services"
        }
    ],
    "sg:phone":"+1 408 734 4110",
    "sg:postcode":"94089",
    "sg:province":"CA",
    "sg:tags":[
        "engineer"
    ],
    "wof:name":"Everitt Engineering",
    "wof:placetype":"venue"
},
  "geometry": {"coordinates":[-122.01137,37.39827],"type":"Point"}
}