{
  "type": "Feature",
  "properties": {
    "iso:country":"US",
    "sg:address":"1611 San Pablo Ave Ste E15",
    "sg:city":"Berkeley",
    "sg:classifiers":[
        {
            "category":"Professional",
            "subcategory":"Lawyer & Legal Services",
            "type":"Services"
        }
    ],
    "sg:phone":"+1 510 526 3774",
    "sg:postcode":"94702",
    "sg:province":"CA",
    "sg:tags":[
        "consultant",
        "ergonomic"
    ],
    "wof:name":"Ergonomic Seating And Products Inc",
    "wof:placetype":"venue"
},
  "geometry": {"coordinates":[-122.294027,37.875039],"type":"Point"}
}