{
  "type": "Feature",
  "properties": {
    "iso:country":"US",
    "sg:address":"8200 Allport Ave",
    "sg:city":"Santa Fe Springs",
    "sg:classifiers":[
        {
            "category":"Retail",
            "subcategory":"Auto Repair",
            "type":"Services"
        }
    ],
    "sg:phone":"+1 562 696 6736",
    "sg:postcode":"90670",
    "sg:province":"CA",
    "wof:name":"Carreon's",
    "wof:placetype":"venue"
},
  "geometry": {"coordinates":[-118.06500200000001,33.967701],"type":"Point"}
}