{
  "type": "Feature",
  "properties": {
    "addr:full":"1590 Dry Creek Rd San Jose CA 95125",
    "addr:housenumber":"1590",
    "addr:postcode":"95125",
    "addr:street":"Dry Creek Rd",
    "iso:country":"US",
    "sg:address":"1590 Dry Creek Rd",
    "sg:city":"San Jose",
    "sg:classifiers":[
        {
            "category":"Social Services",
            "subcategory":"Child Care",
            "type":"Services"
        }
    ],
    "sg:phone":"+1 408 265 3588",
    "sg:postcode":"95125",
    "sg:province":"CA",
    "wof:name":"Ymca At Booksin",
    "wof:placetype":"venue"
},
  "geometry": {"coordinates":[-121.905675,37.28934],"type":"Point"}
}