{
  "type": "Feature",
  "properties": {
    "iso:country":"US",
    "sg:address":"1828 El Camino Real",
    "sg:city":"Burlingame",
    "sg:classifiers":[
        {
            "category":"Health Services",
            "subcategory":"Doctor",
            "type":"Services"
        }
    ],
    "sg:phone":"+1 650 692 1892",
    "sg:postcode":"94010",
    "sg:province":"CA",
    "wof:name":"Kardassakis Dean MD",
    "wof:placetype":"venue"
},
  "geometry": {"coordinates":[-122.383578,37.59543],"type":"Point"}
}