{
  "type": "Feature",
  "properties": {
    "iso:country":"US",
    "sg:address":"908 Tulare Ave",
    "sg:city":"Albany",
    "sg:classifiers":[
        {
            "category":"Social Services",
            "type":"Services"
        }
    ],
    "sg:phone":"+1 510 526 5515",
    "sg:postcode":"94707",
    "sg:province":"CA",
    "sg:tags":[
        "worker"
    ],
    "wof:name":"Phyllis Greene Lcsw",
    "wof:placetype":"venue"
},
  "geometry": {"coordinates":[-122.28230000000001,37.890824],"type":"Point"}
}