{
  "type": "Feature",
  "properties": {
    "addr:full":"653 S Melrose St Placentia CA 92870",
    "addr:housenumber":"653",
    "addr:postcode":"ca 92870",
    "addr:street":"S Melrose St",
    "iso:country":"US",
    "sg:address":"653 S Melrose St",
    "sg:city":"Placentia",
    "sg:classifiers":[
        {
            "category":"Government",
            "subcategory":"Office",
            "type":"Public Place"
        }
    ],
    "sg:phone":"+1 714 993 8204",
    "sg:postcode":"92870",
    "sg:province":"CA",
    "sg:tags":[
        "conservation"
    ],
    "wof:name":"Placentia City Community",
    "wof:placetype":"venue"
},
  "geometry": {"coordinates":[-117.875034,33.862282],"type":"Point"}
}