{
  "type": "Feature",
  "properties": {
    "addr:full":"2465 E Orangethorpe Ave Fullerton CA 92831",
    "addr:housenumber":"2465",
    "addr:postcode":"92831",
    "addr:street":"E Orangethorpe Ave",
    "iso:country":"US",
    "sg:address":"2465 E Orangethorpe Ave",
    "sg:city":"Fullerton",
    "sg:classifiers":[
        {
            "category":"Banks & Credit Unions",
            "subcategory":"Financial Services",
            "type":"Services"
        }
    ],
    "sg:phone":"+1 714 992 6635",
    "sg:postcode":"92831",
    "sg:province":"CA",
    "sg:tags":[
        "broker",
        "mortgage"
    ],
    "sg:website":"www.rosemontmortgage.com",
    "wof:name":"Rosemont Mortgage",
    "wof:placetype":"venue"
},
  "geometry": {"coordinates":[-117.887001,33.859798],"type":"Point"}
}