{
  "type": "Feature",
  "properties": {
    "addr:full":"11333 Greenstone Ave Santa Fe Springs CA 90670",
    "addr:housenumber":"11333",
    "addr:postcode":"90670",
    "addr:street":"Greenstone Ave",
    "iso:country":"US",
    "sg:address":"11333 Greenstone Ave",
    "sg:city":"Santa Fe Springs",
    "sg:classifiers":[
        {
            "category":"Health Services",
            "subcategory":"Clinic",
            "type":"Services"
        },
        {
            "category":"Shopping",
            "subcategory":"Pharmacy",
            "type":"Retail Goods"
        }
    ],
    "sg:phone":"+1 323 582 9900",
    "sg:postcode":"90670",
    "sg:province":"CA",
    "sg:tags":[
        "medical",
        "drugstore"
    ],
    "sg:website":"www.TwinMedDirect.com",
    "wof:name":"Twin Med Direct",
    "wof:placetype":"venue"
},
  "geometry": {"coordinates":[-118.059628,33.92874],"type":"Point"}
}