{
  "type": "Feature",
  "properties": {
    "addr:full":"100 W Hamilton Avenue Campbell CA 95008",
    "addr:housenumber":"100",
    "addr:postcode":"95008",
    "addr:street":"W Hamilton Avenue",
    "iso:country":"US",
    "sg:address":"100 W Hamilton Avenue",
    "sg:city":"Campbell",
    "sg:classifiers":[
        {
            "category":"Food & Beverages",
            "subcategory":"Groceries & Convenience Stores",
            "type":"Retail Goods"
        }
    ],
    "sg:phone":"+1 408 378 7680",
    "sg:postcode":"95008",
    "sg:province":"CA",
    "wof:name":"California Food Mart",
    "wof:placetype":"venue"
},
  "geometry": {"coordinates":[-121.951714,37.294186],"type":"Point"}
}