{
  "type": "Feature",
  "properties": {
    "iso:country":"US",
    "sg:address":"2121 Depot Rd",
    "sg:city":"Hayward",
    "sg:classifiers":[
        {
            "category":"Recreation",
            "type":"Entertainment"
        }
    ],
    "sg:phone":"+1 510 670 5590",
    "sg:postcode":"94545",
    "sg:province":"CA",
    "sg:tags":[
        "club",
        "membership"
    ],
    "wof:name":"Mount Eden Amercn Little Leag",
    "wof:placetype":"venue"
},
  "geometry": {"coordinates":[-122.106689,37.638925],"type":"Point"}
}