{
  "type": "Feature",
  "properties": {
    "iso:country":"US",
    "sg:address":"1925 McKinley Ave",
    "sg:city":"La Verne",
    "sg:classifiers":[
        {
            "category":"Professional",
            "subcategory":"Research",
            "type":"Services"
        }
    ],
    "sg:phone":"+1 909 596 7888",
    "sg:postcode":"91750",
    "sg:province":"CA",
    "sg:tags":[
        "development",
        "electronic"
    ],
    "sg:website":"www.changind.com",
    "wof:name":"Chang Industry",
    "wof:placetype":"venue"
},
  "geometry": {"coordinates":[-117.784128,34.089905],"type":"Point"}
}