{
  "type": "Feature",
  "properties": {
    "addr:full":"286 Winchester Canyon Rd Goleta CA 93117",
    "addr:housenumber":"286",
    "addr:postcode":"93117",
    "addr:street":"Winchester Canyon Rd",
    "iso:country":"US",
    "sg:address":"286 Winchester Canyon Rd",
    "sg:city":"Goleta",
    "sg:classifiers":[
        {
            "category":"Wholesale",
            "subcategory":"Fruits & Vegetables",
            "type":"Manufacturing & Wholesale Goods"
        }
    ],
    "sg:phone":"+1 805 968 4461",
    "sg:postcode":"93117",
    "sg:province":"CA",
    "sg:tags":[
        "shipper"
    ],
    "wof:name":"Growing Concern",
    "wof:placetype":"venue"
},
  "geometry": {"coordinates":[-119.905233,34.440199],"type":"Point"}
}