{
  "type": "Feature",
  "properties": {
    "addr:full":"1344 Cynthia Ln Carlsbad CA 92008",
    "addr:housenumber":"1344",
    "addr:postcode":"92008",
    "addr:street":"Cynthia Ln",
    "iso:country":"US",
    "sg:address":"1344 Cynthia Ln",
    "sg:city":"Carlsbad",
    "sg:classifiers":[
        {
            "category":"Professional",
            "type":"Services"
        },
        {
            "category":"Shopping",
            "subcategory":"Gifts & Souvenirs",
            "type":"Retail Goods"
        }
    ],
    "sg:phone":"+1 760 720 0440",
    "sg:postcode":"92008",
    "sg:province":"CA",
    "sg:tags":[
        "party",
        "supply"
    ],
    "wof:name":"Margaritas Senoritas",
    "wof:placetype":"venue"
},
  "geometry": {"coordinates":[-117.341655,33.168022],"type":"Point"}
}