{
  "type": "Feature",
  "properties": {
    "iso:country":"US",
    "sg:address":"3785 14th St",
    "sg:city":"Riverside",
    "sg:classifiers":[
        {
            "category":"Personal",
            "subcategory":"Barber",
            "type":"Services"
        }
    ],
    "sg:phone":"+1 951 686 8320",
    "sg:postcode":"92501",
    "sg:province":"CA",
    "wof:name":"Artistically Yours Barber Shop",
    "wof:placetype":"venue"
},
  "geometry": {"coordinates":[-117.3785,33.976316],"type":"Point"}
}