{
  "type": "Feature",
  "properties": {
    "addr:full":"9855 Flower St Bellflower CA 90706",
    "addr:housenumber":"9855",
    "addr:postcode":"90706",
    "addr:street":"Flower St",
    "iso:country":"US",
    "sg:address":"9855 Flower St",
    "sg:city":"Bellflower",
    "sg:classifiers":[
        {
            "category":"Shopping",
            "subcategory":"Florist",
            "type":"Retail Goods"
        }
    ],
    "sg:phone":"+1 562 925 1238",
    "sg:postcode":"90706",
    "sg:province":"CA",
    "wof:name":"White House Florist",
    "wof:placetype":"venue"
},
  "geometry": {"coordinates":[-118.12400100000001,33.882198],"type":"Point"}
}