{
  "type": "Feature",
  "properties": {
    "iso:country":"US",
    "sg:address":"15400 Belgrade St Ofc",
    "sg:city":"Westminster",
    "sg:classifiers":[
        {
            "category":"Real Estate",
            "subcategory":"Real Estate Operator",
            "type":"Services"
        }
    ],
    "sg:phone":"+1 714 531 4722",
    "sg:postcode":"92683",
    "sg:province":"CA",
    "sg:tags":[
        "apartment"
    ],
    "sg:website":"www.windmillapartments.com",
    "wof:name":"Windmill Apartments",
    "wof:placetype":"venue"
},
  "geometry": {"coordinates":[-117.958,33.739101],"type":"Point"}
}