{
  "type": "Feature",
  "properties": {
    "addr:full":"3995 Spring Mountain Rd St Helena CA 94574",
    "addr:housenumber":"3995",
    "addr:postcode":"94574",
    "addr:street":"Spring Mountain Rd",
    "iso:country":"US",
    "sg:address":"3995 Spring Mountain Rd",
    "sg:city":"St Helena",
    "sg:classifiers":[
        {
            "category":"Travel",
            "subcategory":"Hotels & Motels",
            "type":"Entertainment"
        }
    ],
    "sg:phone":"+1 707 963 3794",
    "sg:postcode":"94574",
    "sg:province":"CA",
    "sg:tags":[
        "breakfast",
        "accommodation",
        "bed"
    ],
    "wof:name":"Deer Run Inn",
    "wof:placetype":"venue"
},
  "geometry": {"coordinates":[-122.547934,38.523345],"type":"Point"}
}