{
  "type": "Feature",
  "properties": {
    "addr:full":"1595 Chestnut Ave Long Beach CA 90813",
    "addr:housenumber":"1595",
    "addr:postcode":"90813",
    "addr:street":"Chestnut Ave",
    "iso:country":"US",
    "sg:address":"1595 Chestnut Ave",
    "sg:city":"Long Beach",
    "sg:classifiers":[
        {
            "category":"Real Estate",
            "subcategory":"Real Estate Operator",
            "type":"Services"
        }
    ],
    "sg:phone":"+1 562 218 6181",
    "sg:postcode":"90813",
    "sg:province":"CA",
    "sg:tags":[
        "apartment"
    ],
    "wof:name":"Williams Raquel",
    "wof:placetype":"venue"
},
  "geometry": {"coordinates":[-118.19651500000001,33.787095],"type":"Point"}
}