{
  "type": "Feature",
  "properties": {
    "iso:country":"US",
    "sg:address":"2439 Salamanca",
    "sg:city":"La Verne",
    "sg:classifiers":[
        {
            "category":"Building & Trades",
            "subcategory":"Construction",
            "type":"Services"
        }
    ],
    "sg:phone":"+1 626 890 0050",
    "sg:postcode":"91750",
    "sg:province":"CA",
    "sg:tags":[
        "home",
        "builder"
    ],
    "wof:name":"Capitano Construction",
    "wof:placetype":"venue"
},
  "geometry": {"coordinates":[-117.758039,34.146953],"type":"Point"}
}