{
  "type": "Feature",
  "properties": {
    "iso:country":"US",
    "sg:address":"7837 Garvey Ave",
    "sg:city":"Rosemead",
    "sg:classifiers":[
        {
            "category":"Health Services",
            "subcategory":"Doctor",
            "type":"Services"
        }
    ],
    "sg:phone":"+1 626 288 2045",
    "sg:postcode":"91770",
    "sg:province":"CA",
    "sg:tags":[
        "dentist"
    ],
    "wof:name":"Phuong Tu Pruong DDS",
    "wof:placetype":"venue"
},
  "geometry": {"coordinates":[-118.098777,34.0627],"type":"Point"}
}