{
  "type": "Feature",
  "properties": {
    "addr:full":"1401 W Capitol Ave West Sacramento CA 95691",
    "addr:housenumber":"1401",
    "addr:postcode":"95691",
    "addr:street":"W Capitol Ave",
    "iso:country":"US",
    "sg:address":"1401 W Capitol Ave",
    "sg:city":"West Sacramento",
    "sg:classifiers":[
        {
            "category":"Autos & Motor Vehicles",
            "subcategory":"Fuel & Gas Station",
            "type":"Retail Goods"
        }
    ],
    "sg:phone":"+1 916 372 0675",
    "sg:postcode":"95691",
    "sg:province":"CA",
    "sg:tags":[
        "oil"
    ],
    "wof:name":"Flyers Exxon",
    "wof:placetype":"venue"
},
  "geometry": {"coordinates":[-121.53064000000001,38.580261],"type":"Point"}
}