{
  "type": "Feature",
  "properties": {
    "addr:full":"4161 N Greenbrier Rd Long Beach CA 90808",
    "addr:housenumber":"4161",
    "addr:postcode":"90808",
    "addr:street":"N Greenbrier Rd",
    "iso:country":"US",
    "sg:address":"4161 N Greenbrier Rd",
    "sg:city":"Long Beach",
    "sg:classifiers":[
        {
            "category":"Professional",
            "type":"Services"
        }
    ],
    "sg:phone":"+1 562 421 9116",
    "sg:postcode":"90808",
    "sg:province":"CA",
    "wof:name":"Sea Sea Rider",
    "wof:placetype":"venue"
},
  "geometry": {"coordinates":[-118.132825,33.834964],"type":"Point"}
}