{
  "type": "Feature",
  "properties": {
    "iso:country":"US",
    "sg:address":"850 S Atlantic Blvd Ste 303",
    "sg:city":"Monterey Park",
    "sg:classifiers":[
        {
            "category":"Health Services",
            "subcategory":"Dentist",
            "type":"Services"
        }
    ],
    "sg:phone":"+1 626 308 9832",
    "sg:postcode":"91754",
    "sg:province":"CA",
    "wof:name":"JT Chen DDS",
    "wof:placetype":"venue"
},
  "geometry": {"coordinates":[-118.137806,34.102129],"type":"Point"}
}