{
  "type": "Feature",
  "properties": {
    "iso:country":"US",
    "sg:address":"1599 S San Jacinto Ave",
    "sg:city":"San Jacinto",
    "sg:classifiers":[
        {
            "category":"Cinema",
            "subcategory":"Movie Theater",
            "type":"Entertainment"
        }
    ],
    "sg:phone":"+1 951 487 0879",
    "sg:postcode":"92583",
    "sg:province":"CA",
    "wof:name":"Regal Entertainment Grp",
    "wof:placetype":"venue"
},
  "geometry": {"coordinates":[-116.958754,33.771163],"type":"Point"}
}