{
  "type": "Feature",
  "properties": {
    "addr:full":"1630 Loma Crest St Glendale CA 91205",
    "addr:housenumber":"1630",
    "addr:postcode":"91205",
    "addr:street":"Loma Crest St",
    "iso:country":"US",
    "sg:address":"1630 Loma Crest St",
    "sg:city":"Glendale",
    "sg:classifiers":[
        {
            "category":"Real Estate",
            "subcategory":"Real Estate Agent",
            "type":"Services"
        }
    ],
    "sg:phone":"+1 818 553 1994",
    "sg:postcode":"91205",
    "sg:province":"CA",
    "wof:name":"American Teen Properties",
    "wof:placetype":"venue"
},
  "geometry": {"coordinates":[-118.23726000000001,34.127084],"type":"Point"}
}