{
  "type": "Feature",
  "properties": {
    "iso:country":"US",
    "sg:address":"416 Maine St",
    "sg:city":"Vallejo",
    "sg:classifiers":[
        {
            "category":"Taxi",
            "type":"Transportation"
        }
    ],
    "sg:phone":"+1 707 745 3211",
    "sg:postcode":"94590",
    "sg:province":"CA",
    "sg:tags":[
        "taxicab"
    ],
    "wof:name":"Benicia Yellow Cab",
    "wof:placetype":"venue"
},
  "geometry": {"coordinates":[-122.25355,38.099172],"type":"Point"}
}