{
  "type": "Feature",
  "properties": {
    "iso:country":"US",
    "sg:address":"10401 Beach Blvd",
    "sg:city":"Stanton",
    "sg:classifiers":[
        {
            "category":"Travel",
            "subcategory":"Travel Agent",
            "type":"Entertainment"
        }
    ],
    "sg:phone":"+1 714 484 6704",
    "sg:postcode":"90680",
    "sg:province":"CA",
    "sg:tags":[
        "agency",
        "bureau"
    ],
    "wof:name":"Acapulco Travel",
    "wof:placetype":"venue"
},
  "geometry": {"coordinates":[-117.993286,33.811735],"type":"Point"}
}