{
  "type": "Feature",
  "properties": {
    "addr:full":"3601 Oakwood Rd Lake Isabella CA 93240",
    "addr:housenumber":"3601",
    "addr:postcode":"93240",
    "addr:street":"Oakwood Rd",
    "iso:country":"US",
    "sg:address":"3601 Oakwood Rd",
    "sg:city":"Lake Isabella",
    "sg:classifiers":[
        {
            "category":"Building & Trades",
            "subcategory":"Construction",
            "type":"Services"
        }
    ],
    "sg:phone":"+1 760 379 4158",
    "sg:postcode":"93240",
    "sg:province":"CA",
    "sg:tags":[
        "fence",
        "contractor"
    ],
    "wof:name":"KERN Valley Fencing",
    "wof:placetype":"venue"
},
  "geometry": {"coordinates":[-118.41149900000001,35.625191],"type":"Point"}
}