{
  "type": "Feature",
  "properties": {
    "iso:country":"US",
    "sg:address":"341 Haven Dr",
    "sg:city":"Arvin",
    "sg:classifiers":[
        {
            "category":"Education",
            "subcategory":"School",
            "type":"Public Place"
        }
    ],
    "sg:phone":"+1 661 854 6540",
    "sg:postcode":"93203",
    "sg:province":"CA",
    "wof:name":"Arvin Middle School",
    "wof:placetype":"venue"
},
  "geometry": {"coordinates":[-118.827406,35.20544],"type":"Point"}
}