{
  "type": "Feature",
  "properties": {
    "iso:country":"US",
    "sg:address":"3 Huckleberry Island",
    "sg:city":"Brookdale",
    "sg:classifiers":[
        {
            "category":"Wholesale",
            "subcategory":"Durable Goods & Equipment",
            "type":"Manufacturing & Wholesale Goods"
        }
    ],
    "sg:phone":"+1 831 338 9309",
    "sg:postcode":"95007",
    "sg:province":"CA",
    "sg:tags":[
        "importer"
    ],
    "wof:name":"Dog & Dragon Imports",
    "wof:placetype":"venue"
},
  "geometry": {"coordinates":[-122.11167,37.110011],"type":"Point"}
}