{
  "type": "Feature",
  "properties": {
    "iso:country":"US",
    "sg:address":"624 E Grand Blvd",
    "sg:city":"Corona",
    "sg:classifiers":[
        {
            "category":"Shopping",
            "subcategory":"Gifts & Souvenirs",
            "type":"Retail Goods"
        }
    ],
    "sg:phone":"+1 951 280 0386",
    "sg:postcode":"92879",
    "sg:province":"CA",
    "wof:name":"El Rey Party Rentals",
    "wof:placetype":"venue"
},
  "geometry": {"coordinates":[-117.559024,33.873842],"type":"Point"}
}