{
  "type": "Feature",
  "properties": {
    "addr:full":"9 Parrott St Vallejo CA 94590",
    "addr:housenumber":"9",
    "addr:postcode":"94590",
    "addr:street":"Parrott St",
    "iso:country":"US",
    "sg:address":"9 Parrott St",
    "sg:city":"Vallejo",
    "sg:classifiers":[
        {
            "category":"Freight",
            "type":"Transportation"
        }
    ],
    "sg:phone":"+1 707 553 2020",
    "sg:postcode":"94590",
    "sg:province":"CA",
    "sg:tags":[
        "hauling",
        "trucking"
    ],
    "wof:name":"Willie & Katie's Dump Truck",
    "wof:placetype":"venue"
},
  "geometry": {"coordinates":[-122.26195300000001,38.121202],"type":"Point"}
}