{
  "type": "Feature",
  "properties": {
    "iso:country":"US",
    "sg:address":"2125 S Helen Ave",
    "sg:city":"Ontario",
    "sg:classifiers":[
        {
            "category":"Professional",
            "type":"Services"
        }
    ],
    "sg:phone":"+1 909 984 9768",
    "sg:postcode":"91762",
    "sg:province":"CA",
    "wof:name":"Charles A Ritzman",
    "wof:placetype":"venue"
},
  "geometry": {"coordinates":[-117.679215,34.034099],"type":"Point"}
}