{
  "type": "Feature",
  "properties": {
    "addr:full":"146 Egloff Cir Folsom CA 95630",
    "addr:housenumber":"146",
    "addr:postcode":"95630",
    "addr:street":"Egloff Cir",
    "iso:country":"US",
    "sg:address":"146 Egloff Cir",
    "sg:city":"Folsom",
    "sg:classifiers":[
        {
            "category":"Building & Trades",
            "subcategory":"Landscaping Services",
            "type":"Services"
        }
    ],
    "sg:phone":"+1 916 987 5555",
    "sg:postcode":"95630",
    "sg:province":"CA",
    "sg:tags":[
        "designer",
        "landscape"
    ],
    "wof:name":"Dennis Tromburg Assoc",
    "wof:placetype":"venue"
},
  "geometry": {"coordinates":[-121.17579499999999,38.704462],"type":"Point"}
}