{
  "type": "Feature",
  "properties": {
    "iso:country":"US",
    "sg:address":"5155 Myrtle Ave",
    "sg:city":"Eureka",
    "sg:classifiers":[
        {
            "category":"Wholesale",
            "subcategory":"Plants",
            "type":"Manufacturing & Wholesale Goods"
        }
    ],
    "sg:phone":"+1 707 444 8817",
    "sg:postcode":"95503",
    "sg:province":"CA",
    "sg:tags":[
        "florist"
    ],
    "wof:name":"Ophelia's Garden",
    "wof:placetype":"venue"
},
  "geometry": {"coordinates":[-124.103294,40.785446],"type":"Point"}
}