{
  "type": "Feature",
  "properties": {
    "addr:full":"6530 Federal Blvd Lemon Grove CA 91945",
    "addr:housenumber":"6530",
    "addr:postcode":"91945",
    "addr:street":"Federal Blvd",
    "iso:country":"US",
    "sg:address":"6530 Federal Blvd",
    "sg:city":"Lemon Grove",
    "sg:classifiers":[
        {
            "category":"Manufacturing",
            "subcategory":"Furniture",
            "type":"Manufacturing & Wholesale Goods"
        }
    ],
    "sg:phone":"+1 619 582 4040",
    "sg:postcode":"91945",
    "sg:province":"CA",
    "sg:tags":[
        "mill",
        "wood",
        "mfg"
    ],
    "wof:name":"American Mill",
    "wof:placetype":"venue"
},
  "geometry": {"coordinates":[-117.0594,32.731562],"type":"Point"}
}