{
  "type": "Feature",
  "properties": {
    "addr:full":"1230 Burlingame Ave Burlingame CA 94010",
    "addr:housenumber":"1230",
    "addr:postcode":"94010",
    "addr:street":"Burlingame Ave",
    "iso:country":"US",
    "sg:address":"1230 Burlingame Ave",
    "sg:city":"Burlingame",
    "sg:classifiers":[
        {
            "category":"Home & Garden",
            "subcategory":"Home Furnishings",
            "type":"Retail Goods"
        }
    ],
    "sg:phone":"+1 650 348 0668",
    "sg:postcode":"94010",
    "sg:province":"CA",
    "sg:tags":[
        "housewares",
        "store",
        "furniture"
    ],
    "sg:website":"www.potterybarn.com",
    "wof:name":"Pottery Barn",
    "wof:placetype":"venue"
},
  "geometry": {"coordinates":[-122.346504,37.578987],"type":"Point"}
}