{
  "type": "Feature",
  "properties": {
    "addr:full":"1948 W 15th St San Bernardino CA 92411",
    "addr:housenumber":"1948",
    "addr:postcode":"92411",
    "addr:street":"W 15Th St",
    "iso:country":"US",
    "sg:address":"1948 W 15th St",
    "sg:city":"San Bernardino",
    "sg:classifiers":[
        {
            "category":"Communications",
            "subcategory":"Film & Video Production",
            "type":"Services"
        }
    ],
    "sg:phone":"+1 909 381 5969",
    "sg:postcode":"92411",
    "sg:province":"CA",
    "sg:tags":[
        "taping"
    ],
    "wof:name":"Advanced Productions",
    "wof:placetype":"venue"
},
  "geometry": {"coordinates":[-117.334159,34.126669],"type":"Point"}
}