{
  "type": "Feature",
  "properties": {
    "addr:full":"726 Sutter St Folsom CA 95630",
    "addr:housenumber":"726",
    "addr:postcode":"95630",
    "addr:street":"Sutter St",
    "iso:country":"US",
    "sg:address":"726 Sutter St",
    "sg:city":"Folsom",
    "sg:classifiers":[
        {
            "category":"Shopping",
            "subcategory":"Used Merchandise",
            "type":"Retail Goods"
        }
    ],
    "sg:phone":"+1 916 985 2169",
    "sg:postcode":"95630",
    "sg:province":"CA",
    "sg:tags":[
        "antique"
    ],
    "wof:name":"Folsum Mercantile Exchange",
    "wof:placetype":"venue"
},
  "geometry": {"coordinates":[-121.17749999999999,38.677268],"type":"Point"}
}