{
  "type": "Feature",
  "properties": {
    "iso:country":"US",
    "sg:address":"726 Sutter St",
    "sg:city":"Folsom",
    "sg:classifiers":[
        {
            "category":"Shopping",
            "subcategory":"Used Merchandise",
            "type":"Retail Goods"
        }
    ],
    "sg:phone":"+1 916 985 2169",
    "sg:postcode":"95630",
    "sg:province":"CA",
    "sg:tags":[
        "antique"
    ],
    "wof:name":"Folsum Mercantile Exchange",
    "wof:placetype":"venue"
},
  "geometry": {"coordinates":[-121.1775,38.677268],"type":"Point"}
}