{
  "type": "Feature",
  "properties": {
    "iso:country":"US",
    "sg:address":"920 El Camino Real",
    "sg:city":"South San Francisco",
    "sg:classifiers":[
        {
            "category":"Travel",
            "subcategory":"Hotels & Motels",
            "type":"Entertainment"
        }
    ],
    "sg:phone":"+1 650 583 2408",
    "sg:postcode":"94080",
    "sg:province":"CA",
    "wof:name":"Deluxe Inn",
    "wof:placetype":"venue"
},
  "geometry": {"coordinates":[-122.432999,37.654301],"type":"Point"}
}