{
  "type": "Feature",
  "properties": {
    "iso:country":"US",
    "sg:address":"1010 E Arlee Pl",
    "sg:city":"Anaheim",
    "sg:classifiers":[
        {
            "category":"Wholesale",
            "subcategory":"Construction Materials",
            "type":"Manufacturing & Wholesale Goods"
        }
    ],
    "sg:phone":"+1 714 956 1170",
    "sg:postcode":"92805",
    "sg:province":"CA",
    "wof:name":"Cutting Edge of Diamond Blade",
    "wof:placetype":"venue"
},
  "geometry": {"coordinates":[-117.898848,33.823679],"type":"Point"}
}