{
  "type": "Feature",
  "properties": {
    "addr:full":"3129 Clement St San Francisco CA 94121",
    "addr:housenumber":"3129",
    "addr:postcode":"94121",
    "addr:street":"Clement St",
    "iso:country":"US",
    "sg:address":"3129 Clement St",
    "sg:city":"San Francisco",
    "sg:classifiers":[
        {
            "category":"Restaurant",
            "type":"Food & Drink"
        },
        {
            "category":"Bars & Pubs",
            "subcategory":"Dive Bar",
            "type":"Food & Drink"
        }
    ],
    "sg:phone":"+1 415 752 5439",
    "sg:postcode":"94121",
    "sg:province":"CA",
    "sg:tags":[
        "traditional",
        "american"
    ],
    "sg:website":"www.teeoffbarandgrill.com",
    "wof:name":"Tee Off Bar",
    "wof:placetype":"venue"
},
  "geometry": {"coordinates":[-122.492744,37.781528],"type":"Point"}
}