{
  "type": "Feature",
  "properties": {
    "addr:full":"4010 Soto St Riverside CA 92509",
    "addr:housenumber":"4010",
    "addr:postcode":"92509",
    "addr:street":"Soto St",
    "iso:country":"US",
    "sg:address":"4010 Soto St",
    "sg:city":"Riverside",
    "sg:classifiers":[
        {
            "category":"Retail",
            "subcategory":"Auto Repair",
            "type":"Services"
        }
    ],
    "sg:phone":"+1 951 732 4802",
    "sg:postcode":"92509",
    "sg:province":"CA",
    "sg:tags":[
        "body",
        "painting",
        "repairing",
        "automobile"
    ],
    "wof:name":"A&D Dent",
    "wof:placetype":"venue"
},
  "geometry": {"coordinates":[-117.441868,34.015399],"type":"Point"}
}