{
  "type": "Feature",
  "properties": {
    "addr:full":"345 W Portal Avenue 4th Floor San Francisco CA 94127",
    "addr:housenumber":"345;4th",
    "addr:postcode":"94127",
    "addr:street":"W Portal Avenue;Floor",
    "iso:country":"US",
    "sg:address":"345 W Portal Avenue 4th Floor",
    "sg:city":"San Francisco",
    "sg:classifiers":[
        {
            "category":"Health Services",
            "subcategory":"Health Practitioner",
            "type":"Services"
        }
    ],
    "sg:phone":"+1 415 664 6492",
    "sg:postcode":"94127",
    "sg:province":"CA",
    "sg:tags":[
        "therapy",
        "physical"
    ],
    "wof:name":"West Portal Physical Therapy",
    "wof:placetype":"venue"
},
  "geometry": {"coordinates":[-122.469886,37.737239],"type":"Point"}
}