{
  "type": "Feature",
  "properties": {
    "addr:full":"13119 Ave 272 Visalia CA 93292",
    "addr:housenumber":"13119",
    "addr:postcode":"93292",
    "addr:street":"Ave 272",
    "iso:country":"US",
    "sg:address":"13119 Ave 272",
    "sg:city":"Visalia",
    "sg:classifiers":[
        {
            "category":"Manufacturing",
            "subcategory":"Electronics",
            "type":"Manufacturing & Wholesale Goods"
        }
    ],
    "sg:phone":"+1 559 733 4232",
    "sg:postcode":"93292",
    "sg:province":"CA",
    "sg:tags":[
        "equipment",
        "mfg",
        "home"
    ],
    "wof:name":"Revival Audio",
    "wof:placetype":"venue"
},
  "geometry": {"coordinates":[-119.279974,36.285442],"type":"Point"}
}