{
  "type": "Feature",
  "properties": {
    "addr:full":"11781 Easy Way Garden Grove CA 92840",
    "addr:housenumber":"11781",
    "addr:postcode":"92840",
    "addr:street":"Easy Way",
    "iso:country":"US",
    "sg:address":"11781 Easy Way",
    "sg:city":"Garden Grove",
    "sg:classifiers":[
        {
            "category":"Insurance",
            "subcategory":"Insurance Agent",
            "type":"Services"
        }
    ],
    "sg:phone":"+1 714 636 4848",
    "sg:postcode":"92840",
    "sg:province":"CA",
    "sg:website":"www.alsnook.com",
    "wof:name":"Al Snook & Assoc Insurance",
    "wof:placetype":"venue"
},
  "geometry": {"coordinates":[-117.947782,33.789314],"type":"Point"}
}