{
  "type": "Feature",
  "properties": {
    "addr:full":"626 E Alisal St Salinas CA 93905",
    "addr:housenumber":"626",
    "addr:postcode":"93905",
    "addr:street":"E Alisal St",
    "iso:country":"US",
    "sg:address":"626 E Alisal St",
    "sg:city":"Salinas",
    "sg:classifiers":[
        {
            "category":"Recreation",
            "type":"Entertainment"
        },
        {
            "category":"Shopping",
            "subcategory":"Clothing, Apparel, & Fashions",
            "type":"Retail Goods"
        }
    ],
    "sg:phone":"+1 831 770 1811",
    "sg:postcode":"93905",
    "sg:province":"CA",
    "sg:tags":[
        "shop",
        "bridal",
        "piece"
    ],
    "wof:name":"Casa De Telas",
    "wof:placetype":"venue"
},
  "geometry": {"coordinates":[-121.634775,36.673614],"type":"Point"}
}