{
  "type": "Feature",
  "properties": {
    "addr:full":"7200 Bancroft Ave Ste 210 Eastmont Mall Oakland CA 94605",
    "addr:housenumber":"7200",
    "addr:postcode":"94605",
    "addr:street":"Bancroft Ave Ste 210 Eastmont Mall",
    "iso:country":"US",
    "sg:address":"7200 Bancroft Ave Ste 210 Eastmont Mall",
    "sg:city":"Oakland",
    "sg:classifiers":[
        {
            "category":"Health Services",
            "subcategory":"Clinic",
            "type":"Services"
        },
        {
            "category":"Community Center",
            "type":"Public Place"
        }
    ],
    "sg:phone":"+1 800 967 7526",
    "sg:postcode":"94605",
    "sg:province":"CA",
    "sg:tags":[
        "counseling",
        "medical",
        "mental"
    ],
    "wof:name":"Golden Gate Community Health",
    "wof:placetype":"venue"
},
  "geometry": {"coordinates":[-122.177699,37.766472],"type":"Point"}
}