{
  "type": "Feature",
  "properties": {
    "iso:country":"US",
    "sg:address":"23591 el Toro Rd",
    "sg:city":"Lake Forest",
    "sg:classifiers":[
        {
            "category":"Insurance",
            "subcategory":"Insurance Agent",
            "type":"Services"
        }
    ],
    "sg:phone":"+1 949 859 9958",
    "sg:postcode":"92630",
    "sg:province":"CA",
    "wof:name":"Thomas M Boroian Insur Agcy",
    "wof:placetype":"venue"
},
  "geometry": {"coordinates":[-117.701244,33.620009],"type":"Point"}
}