{
  "type": "Feature",
  "properties": {
    "iso:country":"US",
    "sg:address":"764 Mono Way",
    "sg:city":"Sonora",
    "sg:classifiers":[
        {
            "category":"Shopping",
            "subcategory":"Department Store",
            "type":"Retail Goods"
        }
    ],
    "sg:phone":"+1 209 532 8130",
    "sg:postcode":"95370",
    "sg:province":"CA",
    "sg:website":"http://www.jcpenney.com",
    "wof:name":"Ctlg Sales Merchant",
    "wof:placetype":"venue"
},
  "geometry": {"coordinates":[-120.36947600000001,37.974731],"type":"Point"}
}