{
  "type": "Feature",
  "properties": {
    "iso:country":"US",
    "sg:address":"9770 Candida St",
    "sg:city":"San Diego",
    "sg:classifiers":[
        {
            "category":"Professional",
            "subcategory":"Employment Agencies",
            "type":"Services"
        }
    ],
    "sg:phone":"+1 858 653 4520",
    "sg:postcode":"92126",
    "sg:province":"CA",
    "sg:tags":[
        "help",
        "supply"
    ],
    "wof:name":"Care Ambulance",
    "wof:placetype":"venue"
},
  "geometry": {"coordinates":[-117.119272,32.897488],"type":"Point"}
}