{
  "type": "Feature",
  "properties": {
    "addr:full":"465 Los Cerritos Mall Cerritos CA 90703",
    "addr:housenumber":"465;cerritos",
    "addr:postcode":"ca 90703",
    "addr:street":"Los;Mall",
    "iso:country":"US",
    "sg:address":"465 Los Cerritos Mall",
    "sg:city":"Cerritos",
    "sg:classifiers":[
        {
            "category":"Shopping",
            "subcategory":"Clothing, Apparel, & Fashions",
            "type":"Retail Goods"
        }
    ],
    "sg:phone":"+1 562 924 7852",
    "sg:postcode":"90703",
    "sg:province":"CA",
    "sg:website":"www.anchorblue.com",
    "wof:name":"Anchor Blue",
    "wof:placetype":"venue"
},
  "geometry": {"coordinates":[-118.09310000000001,33.86023],"type":"Point"}
}