{
  "type": "Feature",
  "properties": {
    "iso:country":"US",
    "sg:address":"3701 Cahuenga Blvd Ste 3",
    "sg:city":"Studio City",
    "sg:classifiers":[
        {
            "category":"Retail",
            "subcategory":"Laundry & Dry Cleaning",
            "type":"Services"
        }
    ],
    "sg:phone":"+1 818 769 0892",
    "sg:postcode":"91604",
    "sg:province":"CA",
    "wof:name":"Valet Cleaners",
    "wof:placetype":"venue"
},
  "geometry": {"coordinates":[-118.361,34.134899],"type":"Point"}
}