{
  "type": "Feature",
  "properties": {
    "iso:country":"US",
    "sg:address":"203 Lawrence Ave",
    "sg:city":"S San Francisco",
    "sg:classifiers":[
        {
            "category":"Professional",
            "subcategory":"Advertising",
            "type":"Services"
        }
    ],
    "sg:phone":"+1 650 589 3117",
    "sg:postcode":"94080",
    "sg:province":"CA",
    "sg:tags":[
        "distributing",
        "sample"
    ],
    "sg:website":"www.certifiedfolder.com",
    "wof:name":"Certified Folder Display Svc",
    "wof:placetype":"venue"
},
  "geometry": {"coordinates":[-122.394514,37.649157],"type":"Point"}
}