{
  "type": "Feature",
  "properties": {
    "addr:full":"3346 San Gabriel Blvd Rosemead CA 91770",
    "addr:housenumber":"3346",
    "addr:postcode":"91770",
    "addr:street":"San Gabriel Blvd",
    "iso:country":"US",
    "sg:address":"3346 San Gabriel Blvd",
    "sg:city":"Rosemead",
    "sg:classifiers":[
        {
            "category":"Autos & Motor Vehicles",
            "subcategory":"Automobile Sales",
            "type":"Retail Goods"
        }
    ],
    "sg:phone":"+1 626 288 1132",
    "sg:postcode":"91770",
    "sg:province":"CA",
    "sg:tags":[
        "car",
        "dealer"
    ],
    "wof:name":"Ho Ho Motor Inc",
    "wof:placetype":"venue"
},
  "geometry": {"coordinates":[-118.090616,34.066391],"type":"Point"}
}