{
  "type": "Feature",
  "properties": {
    "addr:full":"22706 Ventura Blvd Woodland Hills CA 91364",
    "addr:housenumber":"22706",
    "addr:postcode":"91364",
    "addr:street":"Ventura Blvd",
    "iso:country":"US",
    "sg:address":"22706 Ventura Blvd",
    "sg:city":"Woodland Hills",
    "sg:classifiers":[
        {
            "category":"Retail",
            "subcategory":"Repair Shop",
            "type":"Services"
        }
    ],
    "sg:phone":"+1 818 222 9907",
    "sg:postcode":"91364",
    "sg:province":"CA",
    "sg:tags":[
        "upholsterer"
    ],
    "sg:website":"www.fabricsatcost.com",
    "wof:name":"P Sardo Interiors Inc",
    "wof:placetype":"venue"
},
  "geometry": {"coordinates":[-118.62314600000001,34.166011],"type":"Point"}
}