{
  "type": "Feature",
  "properties": {
    "iso:country":"US",
    "sg:address":"4831 N Old Stage Rd",
    "sg:city":"Mount Shasta",
    "sg:classifiers":[
        {
            "category":"Retail",
            "subcategory":"Repair Shop",
            "type":"Services"
        }
    ],
    "sg:phone":"+1 530 926 2793",
    "sg:postcode":"96067",
    "sg:province":"CA",
    "sg:tags":[
        "sporting"
    ],
    "wof:name":"Gun Shop",
    "wof:placetype":"venue"
},
  "geometry": {"coordinates":[-122.377165,41.361403],"type":"Point"}
}