{
  "type": "Feature",
  "properties": {
    "addr:full":"1542 Park St Alameda CA 94501",
    "addr:housenumber":"1542",
    "addr:postcode":"94501",
    "addr:street":"Park St",
    "iso:country":"US",
    "sg:address":"1542 Park St",
    "sg:city":"Alameda",
    "sg:classifiers":[
        {
            "category":"Utilities",
            "subcategory":"Mobile Phone",
            "type":"Services"
        }
    ],
    "sg:phone":"+1 510 522 2882",
    "sg:postcode":"94501",
    "sg:province":"CA",
    "sg:tags":[
        "communication",
        "radiotelephone"
    ],
    "wof:name":"West Coast Cellular",
    "wof:placetype":"venue"
},
  "geometry": {"coordinates":[-122.24089600000001,37.76631],"type":"Point"}
}