{
  "type": "Feature",
  "properties": {
    "addr:full":"1540 W San Bernardino Rd Covina CA 91791",
    "addr:housenumber":"1540",
    "addr:postcode":"91791",
    "addr:street":"W San Bernardino Rd",
    "iso:country":"US",
    "sg:address":"1540 W San Bernardino Rd",
    "sg:city":"Covina",
    "sg:classifiers":[
        {
            "category":"Manufacturing",
            "subcategory":"Signs",
            "type":"Manufacturing & Wholesale Goods"
        }
    ],
    "sg:phone":"+1 626 915 5694",
    "sg:postcode":"91791",
    "sg:province":"CA",
    "sg:tags":[
        "specialty",
        "mfg"
    ],
    "wof:name":"Academy Signs",
    "wof:placetype":"venue"
},
  "geometry": {"coordinates":[-117.921308,34.088831],"type":"Point"}
}