{
  "type": "Feature",
  "properties": {
    "iso:country":"US",
    "sg:address":"820 Beckman Rd",
    "sg:city":"Lodi",
    "sg:classifiers":[
        {
            "category":"Retail",
            "subcategory":"Auto Repair",
            "type":"Services"
        }
    ],
    "sg:phone":"+1 209 368 1470",
    "sg:postcode":"95240",
    "sg:province":"CA",
    "sg:tags":[
        "muffler",
        "exhaust",
        "system"
    ],
    "wof:name":"Exhaust Pros & Automotive",
    "wof:placetype":"venue"
},
  "geometry": {"coordinates":[-121.259103,38.145549],"type":"Point"}
}