{
  "type": "Feature",
  "properties": {
    "addr:full":"17250 Foothill Blvd Fontana CA 92335",
    "addr:housenumber":"17250",
    "addr:postcode":"92335",
    "addr:street":"Foothill Blvd",
    "iso:country":"US",
    "sg:address":"17250 Foothill Blvd",
    "sg:city":"Fontana",
    "sg:classifiers":[
        {
            "category":"Professional",
            "type":"Services"
        }
    ],
    "sg:phone":"+1 909 350 3885",
    "sg:postcode":"92335",
    "sg:province":"CA",
    "wof:name":"Lonnie Freeman",
    "wof:placetype":"venue"
},
  "geometry": {"coordinates":[-117.429993,34.106719],"type":"Point"}
}