{
  "type": "Feature",
  "properties": {
    "addr:full":"538 Rainsville Rd Petaluma CA 94952",
    "addr:housenumber":"538",
    "addr:postcode":"94952",
    "addr:street":"Rainsville Rd",
    "iso:country":"US",
    "sg:address":"538 Rainsville Rd",
    "sg:city":"Petaluma",
    "sg:classifiers":[
        {
            "category":"Professional",
            "type":"Services"
        }
    ],
    "sg:phone":"+1 707 992 0100",
    "sg:postcode":"94952",
    "sg:province":"CA",
    "wof:name":"Susan Harvey",
    "wof:placetype":"venue"
},
  "geometry": {"coordinates":[-122.69446499999999,38.27084],"type":"Point"}
}