{
  "type": "Feature",
  "properties": {
    "addr:full":"931 San Bruno Ave W San Bruno CA 94066",
    "addr:housenumber":"931",
    "addr:postcode":"94066",
    "addr:street":"San Bruno Ave W",
    "iso:country":"US",
    "sg:address":"931 San Bruno Ave W",
    "sg:city":"San Bruno",
    "sg:classifiers":[
        {
            "category":"Health Services",
            "subcategory":"Doctor",
            "type":"Services"
        }
    ],
    "sg:phone":"+1 650 588 6740",
    "sg:postcode":"94066",
    "sg:province":"CA",
    "sg:tags":[
        "dentist"
    ],
    "wof:name":"Mervyn K Otsuka DDS",
    "wof:placetype":"venue"
},
  "geometry": {"coordinates":[-122.419524,37.627632],"type":"Point"}
}