{
  "type": "Feature",
  "properties": {
    "addr:full":"2601 W Ball Rd Anaheim CA 92804",
    "addr:housenumber":"2601",
    "addr:postcode":"92804",
    "addr:street":"W Ball Rd",
    "iso:country":"US",
    "sg:address":"2601 W Ball Rd",
    "sg:city":"Anaheim",
    "sg:classifiers":[
        {
            "category":"Health Services",
            "subcategory":"Dentist",
            "type":"Services"
        }
    ],
    "sg:phone":"+1 714 282 8282",
    "sg:postcode":"92804",
    "sg:province":"CA",
    "wof:name":"Yaroo.Com",
    "wof:placetype":"venue"
},
  "geometry": {"coordinates":[-117.976153,33.817974],"type":"Point"}
}