{
  "type": "Feature",
  "properties": {
    "addr:full":"439 Grand Ave South San Francisco CA 94080",
    "addr:housenumber":"439",
    "addr:postcode":"94080",
    "addr:street":"Grand Ave",
    "iso:country":"US",
    "sg:address":"439 Grand Ave",
    "sg:city":"South San Francisco",
    "sg:classifiers":[
        {
            "category":"Restaurant",
            "type":"Food & Drink"
        }
    ],
    "sg:menulink":"http://www.allmenus.com/ca/south-san-francisco/55956-la-torta-loca/menu/",
    "sg:phone":"+1 650 952 2790",
    "sg:postcode":"94080",
    "sg:province":"CA",
    "sg:tags":[
        "wrap",
        "american",
        "sandwich"
    ],
    "wof:name":"La Torta Loca",
    "wof:placetype":"venue"
},
  "geometry": {"coordinates":[-122.413871,37.655941],"type":"Point"}
}