{
  "type": "Feature",
  "properties": {
    "iso:country":"US",
    "sg:address":"4505 Slauson Ave",
    "sg:city":"Maywood",
    "sg:classifiers":[
        {
            "category":"Restaurant",
            "type":"Food & Drink"
        }
    ],
    "sg:phone":"+1 323 562 4633",
    "sg:postcode":"90270",
    "sg:province":"CA",
    "wof:name":"Taco Boy",
    "wof:placetype":"venue"
},
  "geometry": {"coordinates":[-118.18499799999999,33.987202],"type":"Point"}
}