{
  "type": "Feature",
  "properties": {
    "addr:full":"4905 Mission St San Francisco CA 94112",
    "addr:housenumber":"4905",
    "addr:postcode":"94112",
    "addr:street":"Mission St",
    "iso:country":"US",
    "sg:address":"4905 Mission St",
    "sg:city":"San Francisco",
    "sg:classifiers":[
        {
            "category":"Building & Trades",
            "subcategory":"Plumbing",
            "type":"Services"
        }
    ],
    "sg:phone":"+1 415 333 2198",
    "sg:postcode":"94112",
    "sg:province":"CA",
    "sg:tags":[
        "plumbing",
        "contractor"
    ],
    "wof:name":"Able Plumbing & Rooter",
    "wof:placetype":"venue"
},
  "geometry": {"coordinates":[-122.438693,37.719372],"type":"Point"}
}