{
  "type": "Feature",
  "properties": {
    "iso:country":"US",
    "sg:address":"14595 Clearview Dr",
    "sg:city":"Los Gatos",
    "sg:classifiers":[
        {
            "category":"Building & Trades",
            "subcategory":"Construction",
            "type":"Services"
        }
    ],
    "sg:phone":"+1 408 395 4486",
    "sg:postcode":"95032",
    "sg:province":"CA",
    "sg:tags":[
        "general",
        "contractor"
    ],
    "wof:name":"San Jose Construction",
    "wof:placetype":"venue"
},
  "geometry": {"coordinates":[-121.97414999999999,37.256199],"type":"Point"}
}