{
  "type": "Feature",
  "properties": {
    "iso:country":"US",
    "sg:address":"1306 Walden Rd",
    "sg:city":"Walnut Creek",
    "sg:classifiers":[
        {
            "category":"Wholesale",
            "subcategory":"Vending Machines",
            "type":"Manufacturing & Wholesale Goods"
        }
    ],
    "sg:phone":"+1 925 756 1868",
    "sg:postcode":"94597",
    "sg:province":"CA",
    "wof:name":"SNACKS.COM",
    "wof:placetype":"venue"
},
  "geometry": {"coordinates":[-122.057265,37.917293],"type":"Point"}
}