{
  "type": "Feature",
  "properties": {
    "iso:country":"US",
    "sg:address":"27401 Albion Ridge Rd",
    "sg:city":"Albion",
    "sg:classifiers":[
        {
            "category":"Banks & Credit Unions",
            "subcategory":"Investment Brokerage",
            "type":"Services"
        }
    ],
    "sg:phone":"+1 707 937 0572",
    "sg:postcode":"95410",
    "sg:province":"CA",
    "sg:tags":[
        "trust"
    ],
    "wof:name":"Coastal Land Trust",
    "wof:placetype":"venue"
},
  "geometry": {"coordinates":[-123.68270099999999,39.211338],"type":"Point"}
}