{
  "type": "Feature",
  "properties": {
    "addr:full":"4444 Geary St San Francisco CA 94118",
    "addr:housenumber":"4444",
    "addr:postcode":"94118",
    "addr:street":"Geary St",
    "iso:country":"US",
    "sg:address":"4444 Geary St",
    "sg:city":"San Francisco",
    "sg:classifiers":[
        {
            "category":"Home & Garden",
            "subcategory":"Household Appliances",
            "type":"Retail Goods"
        },
        {
            "category":"Personal",
            "type":"Services"
        }
    ],
    "sg:phone":"+1 415 424 0269",
    "sg:postcode":"94118",
    "sg:province":"CA",
    "sg:tags":[
        "repair"
    ],
    "wof:name":"Dryer Vent Cleaning",
    "wof:placetype":"venue"
},
  "geometry": {"coordinates":[-122.467192,37.781198],"type":"Point"}
}