{
  "type": "Feature",
  "properties": {
    "addr:full":"3845 Loustalot Way Redding CA 96002",
    "addr:housenumber":"3845",
    "addr:postcode":"96002",
    "addr:street":"Loustalot Way",
    "iso:country":"US",
    "sg:address":"3845 Loustalot Way",
    "sg:city":"Redding",
    "sg:classifiers":[
        {
            "category":"Professional",
            "subcategory":"Art Services",
            "type":"Services"
        }
    ],
    "sg:phone":"+1 530 223 4788",
    "sg:postcode":"96002",
    "sg:province":"CA",
    "sg:tags":[
        "photographer"
    ],
    "wof:name":"Aerial Photography By Don",
    "wof:placetype":"venue"
},
  "geometry": {"coordinates":[-122.361993,40.550055],"type":"Point"}
}