{
  "type": "Feature",
  "properties": {
    "iso:country":"US",
    "sg:address":"106 S Juniper St",
    "sg:city":"Escondido",
    "sg:classifiers":[
        {
            "category":"Professional",
            "subcategory":"Accounting & Tax Preparation",
            "type":"Services"
        }
    ],
    "sg:phone":"+1 760 741 0702",
    "sg:postcode":"92025",
    "sg:province":"CA",
    "sg:tags":[
        "return",
        "filing"
    ],
    "wof:name":"AJE & Assoc",
    "wof:placetype":"venue"
},
  "geometry": {"coordinates":[-117.07838599999999,33.12265],"type":"Point"}
}