{
  "type": "Feature",
  "properties": {
    "addr:full":"46 Natoma St Folsom CA 95630",
    "addr:housenumber":"46",
    "addr:postcode":"95630",
    "addr:street":"Natoma St",
    "iso:country":"US",
    "sg:address":"46 Natoma St",
    "sg:city":"Folsom",
    "sg:classifiers":[
        {
            "category":"Government",
            "subcategory":"Jail",
            "type":"Public Place"
        }
    ],
    "sg:phone":"+1 916 985 5415",
    "sg:postcode":"95630",
    "sg:province":"CA",
    "sg:tags":[
        "correctional",
        "institution"
    ],
    "wof:name":"Community Correctional Fcilty",
    "wof:placetype":"venue"
},
  "geometry": {"coordinates":[-121.163293,38.681665],"type":"Point"}
}