{
  "type": "Feature",
  "properties": {
    "iso:country":"US",
    "sg:address":"150 N San Dimas Ave",
    "sg:city":"San Dimas",
    "sg:classifiers":[
        {
            "category":"Banks & Credit Unions",
            "subcategory":"Bank",
            "type":"Services"
        }
    ],
    "sg:phone":"+1 909 599 7843",
    "sg:postcode":"91773",
    "sg:province":"CA",
    "sg:tags":[
        "loan",
        "real estate"
    ],
    "wof:name":"Fidelity Mortgage Lending",
    "wof:placetype":"venue"
},
  "geometry": {"coordinates":[-117.80704,34.108319],"type":"Point"}
}