{
  "type": "Feature",
  "properties": {
    "iso:country":"US",
    "sg:address":"21241 Ventura Blvd",
    "sg:city":"Woodland Hills",
    "sg:classifiers":[
        {
            "category":"Professional",
            "subcategory":"Lawyer & Legal Services",
            "type":"Services"
        }
    ],
    "sg:phone":"+1 818 888 1703",
    "sg:postcode":"91364",
    "sg:province":"CA",
    "wof:name":"Harjinder Sidhu",
    "wof:placetype":"venue"
},
  "geometry": {"coordinates":[-118.594954,34.167486],"type":"Point"}
}