{
  "type": "Feature",
  "properties": {
    "addr:full":"6300 White Ln Bakersfield CA 93309",
    "addr:housenumber":"6300",
    "addr:postcode":"93309",
    "addr:street":"White Ln",
    "iso:country":"US",
    "sg:address":"6300 White Ln",
    "sg:city":"Bakersfield",
    "sg:classifiers":[
        {
            "category":"Shopping",
            "subcategory":"Used Merchandise",
            "type":"Retail Goods"
        }
    ],
    "sg:phone":"+1 661 835 8483",
    "sg:postcode":"93309",
    "sg:province":"CA",
    "sg:tags":[
        "book",
        "rare",
        "dealer"
    ],
    "sg:website":"www.russosbooks.com",
    "wof:name":"Book Mark",
    "wof:placetype":"venue"
},
  "geometry": {"coordinates":[-119.073154,35.318265],"type":"Point"}
}