{
  "type": "Feature",
  "properties": {
    "addr:full":"18 Latimer Rd Santa Monica CA 90402",
    "addr:housenumber":"18",
    "addr:postcode":"90402",
    "addr:street":"Latimer Rd",
    "iso:country":"US",
    "sg:address":"18 Latimer Rd",
    "sg:city":"Santa Monica",
    "sg:classifiers":[
        {
            "category":"Professional",
            "subcategory":"Lawyer & Legal Services",
            "type":"Services"
        }
    ],
    "sg:phone":"+1 310 459 0075",
    "sg:postcode":"90402",
    "sg:province":"CA",
    "wof:name":"Law Offices of Anne Roberts",
    "wof:placetype":"venue"
},
  "geometry": {"coordinates":[-118.515715,34.036008],"type":"Point"}
}