{
  "type": "Feature",
  "properties": {
    "iso:country":"US",
    "sg:address":"3778 Hackett Ave",
    "sg:city":"Long Beach",
    "sg:classifiers":[
        {
            "category":"Building & Trades",
            "subcategory":"Electrical",
            "type":"Services"
        }
    ],
    "sg:phone":"+1 562 429 9095",
    "sg:postcode":"90808",
    "sg:province":"CA",
    "sg:tags":[
        "electrician"
    ],
    "wof:name":"Augsburger Electric Co",
    "wof:placetype":"venue"
},
  "geometry": {"coordinates":[-118.10700199999999,33.827202],"type":"Point"}
}