{
  "type": "Feature",
  "properties": {
    "addr:full":"1137 W Struck Ave Orange CA 92867",
    "addr:housenumber":"1137",
    "addr:postcode":"92867",
    "addr:street":"W Struck Ave",
    "iso:country":"US",
    "sg:address":"1137 W Struck Ave",
    "sg:city":"Orange",
    "sg:classifiers":[
        {
            "category":"Building & Trades",
            "subcategory":"Plumbing",
            "type":"Services"
        }
    ],
    "sg:phone":"+1 714 639 3003",
    "sg:postcode":"92867",
    "sg:province":"CA",
    "wof:name":"Heaton And Son Plumbing",
    "wof:placetype":"venue"
},
  "geometry": {"coordinates":[-117.864206,33.806163],"type":"Point"}
}