{
  "type": "Feature",
  "properties": {
    "addr:full":"334 N Pacific Ave Glendale CA 91203",
    "addr:housenumber":"334",
    "addr:postcode":"91203",
    "addr:street":"N Pacific Ave",
    "iso:country":"US",
    "sg:address":"334 N Pacific Ave",
    "sg:city":"Glendale",
    "sg:classifiers":[
        {
            "category":"Organizations",
            "subcategory":"Religious Organization",
            "type":"Services"
        }
    ],
    "sg:phone":"+1 818 956 3827",
    "sg:postcode":"91203",
    "sg:province":"CA",
    "wof:name":"Sheep Gate Evangelical Church",
    "wof:placetype":"venue"
},
  "geometry": {"coordinates":[-118.264,34.1511],"type":"Point"}
}