{
  "type": "Feature",
  "properties": {
    "addr:full":"21172 Mission Blvd Hayward CA 94541",
    "addr:housenumber":"21172",
    "addr:postcode":"94541",
    "addr:street":"Mission Blvd",
    "iso:country":"US",
    "sg:address":"21172 Mission Blvd",
    "sg:city":"Hayward",
    "sg:classifiers":[
        {
            "category":"Travel",
            "subcategory":"Hotels & Motels",
            "type":"Entertainment"
        }
    ],
    "sg:phone":"+1 510 537 1200",
    "sg:postcode":"94541",
    "sg:province":"CA",
    "wof:name":"Deluxe Inn",
    "wof:placetype":"venue"
},
  "geometry": {"coordinates":[-122.095001,37.681],"type":"Point"}
}