{
  "type": "Feature",
  "properties": {
    "iso:country":"US",
    "sg:address":"610 California Ave",
    "sg:city":"Venice",
    "sg:classifiers":[
        {
            "category":"Organizations",
            "subcategory":"Non-profit Organization",
            "type":"Services"
        }
    ],
    "sg:phone":"+1 310 578 6069",
    "sg:postcode":"90291",
    "sg:province":"CA",
    "sg:tags":[
        "human"
    ],
    "wof:name":"Latino Resource Organization",
    "wof:placetype":"venue"
},
  "geometry": {"coordinates":[-118.465434,33.991351],"type":"Point"}
}