{
  "type": "Feature",
  "properties": {
    "addr:full":"1957 W Artesia Blvd #A Gardena CA 90247",
    "addr:housenumber":"1957",
    "addr:postcode":"90247",
    "addr:street":"W Artesia Blvd # A",
    "iso:country":"US",
    "sg:address":"1957 W Artesia Blvd #A",
    "sg:city":"Gardena",
    "sg:classifiers":[
        {
            "category":"Government",
            "subcategory":"Office",
            "type":"Public Place"
        }
    ],
    "sg:phone":"+1 310 515 6821",
    "sg:postcode":"90247",
    "sg:province":"CA",
    "sg:tags":[
        "smog",
        "check"
    ],
    "wof:name":"Sun Smog",
    "wof:placetype":"venue"
},
  "geometry": {"coordinates":[-118.313107,33.873229],"type":"Point"}
}