{
  "type": "Feature",
  "properties": {
    "iso:country":"US",
    "sg:address":"182 Westview Dr",
    "sg:city":"Jackson",
    "sg:classifiers":[
        {
            "category":"Wholesale",
            "subcategory":"Non-durable Goods",
            "type":"Manufacturing & Wholesale Goods"
        }
    ],
    "sg:phone":"+1 209 295 2532",
    "sg:postcode":"95642",
    "sg:province":"CA",
    "sg:tags":[
        "advertising"
    ],
    "wof:name":"Galaxy Group",
    "wof:placetype":"venue"
},
  "geometry": {"coordinates":[-120.79125999999999,38.35731],"type":"Point"}
}