{
  "type": "Feature",
  "properties": {
    "addr:full":"3225 Oselot Way Rancho Cordova CA 95655",
    "addr:housenumber":"3225",
    "addr:postcode":"95655",
    "addr:street":"Oselot Way",
    "iso:country":"US",
    "sg:address":"3225 Oselot Way",
    "sg:city":"Rancho Cordova",
    "sg:classifiers":[
        {
            "category":"Shopping",
            "subcategory":"Used Merchandise",
            "type":"Retail Goods"
        }
    ],
    "sg:phone":"+1 916 332 6787",
    "sg:postcode":"95655",
    "sg:province":"CA",
    "sg:tags":[
        "shop",
        "thrift"
    ],
    "wof:name":"Best Discount Store",
    "wof:placetype":"venue"
},
  "geometry": {"coordinates":[-121.26968599999999,38.583192],"type":"Point"}
}