{
  "type": "Feature",
  "properties": {
    "addr:full":"282 Bonta St Blairsden CA 96103",
    "addr:housenumber":"282",
    "addr:postcode":"96103",
    "addr:street":"Bonta St",
    "iso:country":"US",
    "sg:address":"282 Bonta St",
    "sg:city":"Blairsden",
    "sg:classifiers":[
        {
            "category":"Home & Garden",
            "subcategory":"Hardware",
            "type":"Retail Goods"
        }
    ],
    "sg:phone":"+1 530 836 2589",
    "sg:postcode":"96103",
    "sg:province":"CA",
    "wof:name":"Mountain Hardware & Sports",
    "wof:placetype":"venue"
},
  "geometry": {"coordinates":[-120.617752,39.7814],"type":"Point"}
}