{
  "type": "Feature",
  "properties": {
    "addr:full":"1352 W San Ysidro Blvd San Ysidro CA 92173",
    "addr:housenumber":"1352",
    "addr:postcode":"92173",
    "addr:street":"W San Ysidro Blvd",
    "iso:country":"US",
    "sg:address":"1352 W San Ysidro Blvd",
    "sg:city":"San Ysidro",
    "sg:classifiers":[
        {
            "category":"Freight",
            "type":"Transportation"
        }
    ],
    "sg:phone":"+1 619 428 6875",
    "sg:postcode":"92173",
    "sg:province":"CA",
    "sg:tags":[
        "operator",
        "local",
        "trucking"
    ],
    "wof:name":"Carlos Trucking",
    "wof:placetype":"venue"
},
  "geometry": {"coordinates":[-117.06950999999999,32.564583],"type":"Point"}
}