{
  "type": "Feature",
  "properties": {
    "addr:full":"6716 Greenleaf Ave Whittier CA 90601",
    "addr:housenumber":"6716",
    "addr:postcode":"90601",
    "addr:street":"Greenleaf Ave",
    "iso:country":"US",
    "sg:address":"6716 Greenleaf Ave",
    "sg:city":"Whittier",
    "sg:classifiers":[
        {
            "category":"Health Services",
            "subcategory":"Doctor",
            "type":"Services"
        }
    ],
    "sg:phone":"+1 562 696 5544",
    "sg:postcode":"90601",
    "sg:province":"CA",
    "sg:tags":[
        "dentist"
    ],
    "wof:name":"Uptown Smiles Dental Group",
    "wof:placetype":"venue"
},
  "geometry": {"coordinates":[-118.037256,33.979196],"type":"Point"}
}