{
  "type": "Feature",
  "properties": {
    "iso:country":"US",
    "sg:address":"2905 Red Hill Ave",
    "sg:city":"Costa Mesa",
    "sg:classifiers":[
        {
            "category":"Personal",
            "subcategory":"Massage",
            "type":"Services"
        }
    ],
    "sg:phone":"+1 714 668 1278",
    "sg:postcode":"92626",
    "sg:province":"CA",
    "wof:name":"Ashley Body Center Inc",
    "wof:placetype":"venue"
},
  "geometry": {"coordinates":[-117.88142999999999,33.667433],"type":"Point"}
}