{
  "type": "Feature",
  "properties": {
    "iso:country":"US",
    "sg:address":"648 Chenery St",
    "sg:city":"San Francisco",
    "sg:classifiers":[
        {
            "category":"Sports & Exercise",
            "subcategory":"Gym",
            "type":"Entertainment"
        }
    ],
    "sg:phone":"+1 415 333 9133",
    "sg:postcode":"94199",
    "sg:province":"CA",
    "sg:tags":[
        "trainer",
        "pilate"
    ],
    "sg:website":"www.centeredbody.com/glen.html",
    "wof:name":"Centered Body Pilates - Glen Park",
    "wof:placetype":"venue"
},
  "geometry": {"coordinates":[-122.433215,37.734538],"type":"Point"}
}