{
  "type": "Feature",
  "properties": {
    "iso:country":"US",
    "sg:address":"6258 N Muscatel Ave",
    "sg:city":"San Gabriel",
    "sg:classifiers":[
        {
            "category":"Professional",
            "type":"Services"
        }
    ],
    "sg:phone":"+1 626 285 3531",
    "sg:postcode":"91775",
    "sg:province":"CA",
    "wof:name":"Temple Cty Chinese Amer Assoct",
    "wof:placetype":"venue"
},
  "geometry": {"coordinates":[-118.077207,34.110163],"type":"Point"}
}