{
  "type": "Feature",
  "properties": {
    "iso:country":"US",
    "sg:address":"700 S Hill St",
    "sg:city":"Los Angeles",
    "sg:classifiers":[
        {
            "category":"Wholesale",
            "subcategory":"Jewelry",
            "type":"Manufacturing & Wholesale Goods"
        }
    ],
    "sg:phone":"+1 213 627 7933",
    "sg:postcode":"90014",
    "sg:province":"CA",
    "sg:tags":[
        "jeweler"
    ],
    "wof:name":"Golden Swan Jewelry",
    "wof:placetype":"venue"
},
  "geometry": {"coordinates":[-118.255785,34.044468],"type":"Point"}
}