{
  "type": "Feature",
  "properties": {
    "addr:full":"1246 1/2 N Cahuenga Blvd Los Angeles CA 90038",
    "addr:housenumber":"1246 1 / 2",
    "addr:postcode":"90038",
    "addr:street":"N Cahuenga Blvd",
    "iso:country":"US",
    "sg:address":"1246 1/2 N Cahuenga Blvd",
    "sg:city":"Los Angeles",
    "sg:classifiers":[
        {
            "category":"Real Estate",
            "subcategory":"Real Estate Services",
            "type":"Services"
        }
    ],
    "sg:phone":"+1 323 465 8353",
    "sg:postcode":"90038",
    "sg:province":"CA",
    "sg:tags":[
        "management",
        "property"
    ],
    "wof:name":"Lpl Villas",
    "wof:placetype":"venue"
},
  "geometry": {"coordinates":[-118.328855,34.093837],"type":"Point"}
}