{
  "type": "Feature",
  "properties": {
    "addr:full":"2418 Torrance Blvd Torrance CA 90501",
    "addr:housenumber":"2418",
    "addr:postcode":"90501",
    "addr:street":"Torrance Blvd",
    "iso:country":"US",
    "sg:address":"2418 Torrance Blvd",
    "sg:city":"Torrance",
    "sg:classifiers":[
        {
            "category":"Health Services",
            "subcategory":"Doctor",
            "type":"Services"
        }
    ],
    "sg:phone":"+1 310 212 0985",
    "sg:postcode":"90501",
    "sg:province":"CA",
    "sg:tags":[
        "physician",
        "surgeon"
    ],
    "wof:name":"Renee Petty MD",
    "wof:placetype":"venue"
},
  "geometry": {"coordinates":[-118.32701299999999,33.836288],"type":"Point"}
}