{
  "type": "Feature",
  "properties": {
    "iso:country":"US",
    "sg:address":"465 California St",
    "sg:city":"San Francisco",
    "sg:classifiers":[
        {
            "category":"Shopping",
            "subcategory":"Computers & Home Electronics",
            "type":"Retail Goods"
        }
    ],
    "sg:phone":"+1 415 283 1800",
    "sg:postcode":"94104",
    "sg:province":"CA",
    "sg:tags":[
        "software"
    ],
    "sg:website":"www.koyosha.com",
    "wof:name":"Koyosha Graphics Of America",
    "wof:placetype":"venue"
},
  "geometry": {"coordinates":[-122.40255,37.79281],"type":"Point"}
}