{
  "type": "Feature",
  "properties": {
    "addr:full":"400 Mount Vernon Ave Bakersfield CA 93307",
    "addr:housenumber":"400",
    "addr:postcode":"93307",
    "addr:street":"Mount Vernon Ave",
    "iso:country":"US",
    "sg:address":"400 Mount Vernon Ave",
    "sg:city":"Bakersfield",
    "sg:classifiers":[
        {
            "category":"Retail",
            "subcategory":"Auto Repair",
            "type":"Services"
        }
    ],
    "sg:phone":"+1 661 326 1196",
    "sg:postcode":"93307",
    "sg:province":"CA",
    "sg:tags":[
        "body",
        "automobile",
        "painting"
    ],
    "wof:name":"West Coast Specialties",
    "wof:placetype":"venue"
},
  "geometry": {"coordinates":[-118.96751399999999,35.361342],"type":"Point"}
}