{
  "type": "Feature",
  "properties": {
    "addr:full":"855 W 41st Dr Los Angeles CA 90037",
    "addr:housenumber":"855",
    "addr:postcode":"90037",
    "addr:street":"W 41St Dr",
    "iso:country":"US",
    "sg:address":"855 W 41st Dr",
    "sg:city":"Los Angeles",
    "sg:classifiers":[
        {
            "category":"Professional",
            "type":"Services"
        }
    ],
    "sg:phone":"+1 213 232 6427",
    "sg:postcode":"90037",
    "sg:province":"CA",
    "wof:name":"New Millennium Circus Jimenez",
    "wof:placetype":"venue"
},
  "geometry": {"coordinates":[-118.288725,34.008351],"type":"Point"}
}