{
  "type": "Feature",
  "properties": {
    "addr:full":"15541 Beach Blvd Westminster CA 92683",
    "addr:housenumber":"15541",
    "addr:postcode":"92683",
    "addr:street":"Beach Blvd",
    "iso:country":"US",
    "sg:address":"15541 Beach Blvd",
    "sg:city":"Westminster",
    "sg:classifiers":[
        {
            "category":"Wholesale",
            "subcategory":"Electrical",
            "type":"Manufacturing & Wholesale Goods"
        }
    ],
    "sg:phone":"+1 714 891 6710",
    "sg:postcode":"92683",
    "sg:province":"CA",
    "sg:tags":[
        "alarm"
    ],
    "wof:name":"A To Z Alarms Corp",
    "wof:placetype":"venue"
},
  "geometry": {"coordinates":[-117.98935400000001,33.7363],"type":"Point"}
}