{
  "type": "Feature",
  "properties": {
    "addr:full":"10810 Vanowen St Los Angeles CA 90027",
    "addr:housenumber":"10810",
    "addr:postcode":"90027",
    "addr:street":"Vanowen St",
    "iso:country":"US",
    "sg:address":"10810 Vanowen St",
    "sg:city":"Los Angeles",
    "sg:classifiers":[
        {
            "category":"Retail",
            "subcategory":"Storage",
            "type":"Services"
        }
    ],
    "sg:phone":"+1 818 760 2567",
    "sg:postcode":"90027",
    "sg:province":"CA",
    "sg:tags":[
        "self"
    ],
    "wof:name":"Public Storage",
    "wof:placetype":"venue"
},
  "geometry": {"coordinates":[-118.291,34.106098],"type":"Point"}
}