{
  "type": "Feature",
  "properties": {
    "addr:full":"740 S Western Ave Los Angeles CA 90005",
    "addr:housenumber":"740",
    "addr:postcode":"90005",
    "addr:street":"S Western Ave",
    "iso:country":"US",
    "sg:address":"740 S Western Ave",
    "sg:city":"Los Angeles",
    "sg:classifiers":[
        {
            "category":"Professional",
            "subcategory":"Art Services",
            "type":"Services"
        }
    ],
    "sg:phone":"+1 213 389 0134",
    "sg:postcode":"90005",
    "sg:province":"CA",
    "sg:tags":[
        "photographer"
    ],
    "wof:name":"Ucv",
    "wof:placetype":"venue"
},
  "geometry": {"coordinates":[-118.309,34.059164],"type":"Point"}
}