{
  "type": "Feature",
  "properties": {
    "addr:full":"375 S la Cienega Blvd Los Angeles CA 90048",
    "addr:housenumber":"375",
    "addr:postcode":"90048",
    "addr:street":"S La Cienega Blvd",
    "iso:country":"US",
    "sg:address":"375 S la Cienega Blvd",
    "sg:city":"Los Angeles",
    "sg:classifiers":[
        {
            "category":"Wholesale",
            "subcategory":"Plants",
            "type":"Manufacturing & Wholesale Goods"
        }
    ],
    "sg:phone":"+1 714 780 1700",
    "sg:postcode":"90048",
    "sg:province":"CA",
    "sg:tags":[
        "florist"
    ],
    "wof:name":"Florist",
    "wof:placetype":"venue"
},
  "geometry": {"coordinates":[-118.258426,34.121131],"type":"Point"}
}