{
  "type": "Feature",
  "properties": {
    "addr:full":"367 Van Ness Way Torrance CA 90501",
    "addr:housenumber":"367",
    "addr:postcode":"90501",
    "addr:street":"Van Ness Way",
    "iso:country":"US",
    "sg:address":"367 Van Ness Way",
    "sg:city":"Torrance",
    "sg:classifiers":[
        {
            "category":"Professional",
            "subcategory":"Accounting & Tax Preparation",
            "type":"Services"
        }
    ],
    "sg:phone":"+1 310 783 0951",
    "sg:postcode":"90501",
    "sg:province":"CA",
    "sg:tags":[
        "payroll"
    ],
    "wof:name":"Netpay Payroll",
    "wof:placetype":"venue"
},
  "geometry": {"coordinates":[-118.318912,33.846215],"type":"Point"}
}