{
  "type": "Feature",
  "properties": {
    "addr:full":"2682 Middlefield Rd Redwood City CA 94063",
    "addr:housenumber":"2682",
    "addr:postcode":"94063",
    "addr:street":"Middlefield Rd",
    "iso:country":"US",
    "sg:address":"2682 Middlefield Rd",
    "sg:city":"Redwood City",
    "sg:classifiers":[
        {
            "category":"Building & Trades",
            "subcategory":"Construction",
            "type":"Services"
        }
    ],
    "sg:phone":"+1 650 365 3441",
    "sg:postcode":"94063",
    "sg:province":"CA",
    "sg:tags":[
        "contractor"
    ],
    "wof:name":"Profsnl Gutter Service",
    "wof:placetype":"venue"
},
  "geometry": {"coordinates":[-122.211868,37.476933],"type":"Point"}
}