{
  "type": "Feature",
  "properties": {
    "addr:full":"8851 Longden Ave Temple City CA 91780",
    "addr:postcode":"8851;91780",
    "addr:street":"Longden Ave",
    "iso:country":"US",
    "sg:address":"8851 Longden Ave",
    "sg:city":"Temple City",
    "sg:classifiers":[
        {
            "category":"Wholesale",
            "subcategory":"Chemicals & Plastics",
            "type":"Manufacturing & Wholesale Goods"
        }
    ],
    "sg:phone":"+1 626 285 8534",
    "sg:postcode":"91780",
    "sg:province":"CA",
    "wof:name":"Solartex Corporation",
    "wof:placetype":"venue"
},
  "geometry": {"coordinates":[-118.075109,34.113615],"type":"Point"}
}