{
  "type": "Feature",
  "properties": {
    "iso:country":"US",
    "sg:address":"3142 Vista Way Ste 101",
    "sg:city":"Oceanside",
    "sg:classifiers":[
        {
            "category":"Banks & Credit Unions",
            "subcategory":"Bank",
            "type":"Services"
        }
    ],
    "sg:phone":"+1 760 439 9055",
    "sg:postcode":"92056",
    "sg:province":"CA",
    "wof:name":"Community Commerce Bank",
    "wof:placetype":"venue"
},
  "geometry": {"coordinates":[-117.324997,33.182598],"type":"Point"}
}