{
  "type": "Feature",
  "properties": {
    "iso:country":"US",
    "sg:address":"1927 Combs Way",
    "sg:city":"El Centro",
    "sg:classifiers":[
        {
            "category":"Shopping",
            "type":"Retail Goods"
        }
    ],
    "sg:phone":"+1 760 352 5927",
    "sg:postcode":"92243",
    "sg:province":"CA",
    "sg:tags":[
        "cosmetic",
        "perfume"
    ],
    "wof:name":"Mary Kay Cosmetics",
    "wof:placetype":"venue"
},
  "geometry": {"coordinates":[-115.54741300000001,32.776959],"type":"Point"}
}