{
  "type": "Feature",
  "properties": {
    "iso:country":"US",
    "sg:address":"267 Arlington Avenue Suite 2",
    "sg:city":"Berkeley",
    "sg:classifiers":[
        {
            "category":"Health Services",
            "subcategory":"Health Practitioner",
            "type":"Services"
        }
    ],
    "sg:phone":"+1 510 528 0134",
    "sg:postcode":"94707",
    "sg:province":"CA",
    "sg:tags":[
        "acupuncture"
    ],
    "wof:name":"Mink Jeff Ca Omd",
    "wof:placetype":"venue"
},
  "geometry": {"coordinates":[-122.27800000000001,37.904598],"type":"Point"}
}