{
  "type": "Feature",
  "properties": {
    "iso:country":"US",
    "sg:address":"2097 Los Altos Ave",
    "sg:city":"Clovis",
    "sg:classifiers":[
        {
            "category":"Building & Trades",
            "subcategory":"Construction",
            "type":"Services"
        }
    ],
    "sg:phone":"+1 559 323 8819",
    "sg:postcode":"93611",
    "sg:province":"CA",
    "sg:tags":[
        "fire",
        "restoration",
        "damage"
    ],
    "wof:name":"Steve Overstreet Construction",
    "wof:placetype":"venue"
},
  "geometry": {"coordinates":[-119.675299,36.832834],"type":"Point"}
}