{
  "type": "Feature",
  "properties": {
    "iso:country":"US",
    "sg:address":"33122 Grape St",
    "sg:city":"Wildomar",
    "sg:classifiers":[
        {
            "category":"Social Services",
            "subcategory":"Child Care",
            "type":"Services"
        }
    ],
    "sg:phone":"+1 951 674 7241",
    "sg:postcode":"92595",
    "sg:province":"CA",
    "sg:tags":[
        "elementary",
        "kindergarten",
        "school",
        "academic"
    ],
    "wof:name":"A Shepherd's Flock Preschool",
    "wof:placetype":"venue"
},
  "geometry": {"coordinates":[-117.280998,33.639301],"type":"Point"}
}