{
  "type": "Feature",
  "properties": {
    "addr:full":"801 K St Sacramento CA 95814",
    "addr:housenumber":"801",
    "addr:postcode":"95814",
    "addr:street":"K St",
    "iso:country":"US",
    "sg:address":"801 K St",
    "sg:city":"Sacramento",
    "sg:classifiers":[
        {
            "category":"Real Estate",
            "subcategory":"Real Estate Services",
            "type":"Services"
        },
        {
            "category":"Real Estate",
            "subcategory":"Real Estate Agent",
            "type":"Services"
        }
    ],
    "sg:phone":"+1 916 551 1331",
    "sg:postcode":"95814",
    "sg:province":"CA",
    "sg:tags":[
        "management"
    ],
    "wof:name":"Jones Lang Lasalle",
    "wof:placetype":"venue"
},
  "geometry": {"coordinates":[-121.496613,38.579929],"type":"Point"}
}