{
  "type": "Feature",
  "properties": {
    "iso:country":"US",
    "sg:address":"1736 E 14th St",
    "sg:city":"Oakland",
    "sg:classifiers":[
        {
            "category":"Food & Beverages",
            "subcategory":"Groceries & Convenience Stores",
            "type":"Retail Goods"
        }
    ],
    "sg:phone":"+1 510 893 6340",
    "sg:postcode":"94606",
    "sg:province":"CA",
    "sg:tags":[
        "grocer"
    ],
    "wof:name":"Grand Food",
    "wof:placetype":"venue"
},
  "geometry": {"coordinates":[-122.242399,37.787396],"type":"Point"}
}