{
  "type": "Feature",
  "properties": {
    "iso:country":"US",
    "sg:address":"490 W Willow St",
    "sg:city":"Long Beach",
    "sg:classifiers":[
        {
            "category":"Shopping",
            "subcategory":"Jewelry",
            "type":"Retail Goods"
        },
        {
            "category":"Shopping",
            "subcategory":"Antiques",
            "type":"Retail Goods"
        }
    ],
    "sg:phone":"+1 562 988 8844",
    "sg:postcode":"90806",
    "sg:province":"CA",
    "sg:website":"www.magnoliaandwillow.com",
    "wof:name":"Magnolia and Willow",
    "wof:placetype":"venue"
},
  "geometry": {"coordinates":[-118.197736,33.804133],"type":"Point"}
}