{
  "type": "Feature",
  "properties": {
    "iso:country":"US",
    "sg:address":"1623 Aviation Blvd",
    "sg:city":"Redondo Beach",
    "sg:classifiers":[
        {
            "category":"Sports & Exercise",
            "subcategory":"Gym",
            "type":"Entertainment"
        }
    ],
    "sg:phone":"+1 310 704 3634",
    "sg:postcode":"90278",
    "sg:province":"CA",
    "sg:tags":[
        "trainer"
    ],
    "sg:website":"www.thenevman.com",
    "wof:name":"Chris Neville Fitness",
    "wof:placetype":"venue"
},
  "geometry": {"coordinates":[-118.382841,33.870057],"type":"Point"}
}