{
  "type": "Feature",
  "properties": {
    "iso:country":"US",
    "sg:address":"5455 Sepulveda Blvd",
    "sg:city":"Culver City",
    "sg:classifiers":[
        {
            "category":"Personal",
            "subcategory":"Nail Salon",
            "type":"Services"
        }
    ],
    "sg:phone":"+1 310 915 9655",
    "sg:postcode":"90230",
    "sg:province":"CA",
    "wof:name":"American Nails Inc",
    "wof:placetype":"venue"
},
  "geometry": {"coordinates":[-118.394997,33.993401],"type":"Point"}
}