{
  "type": "Feature",
  "properties": {
    "iso:country":"US",
    "sg:address":"18373 Colima Rd",
    "sg:city":"Rowland Heights",
    "sg:classifiers":[
        {
            "category":"Professional",
            "subcategory":"Business Services",
            "type":"Services"
        }
    ],
    "sg:phone":"+1 626 810 4567",
    "sg:postcode":"91748",
    "sg:province":"CA",
    "sg:tags":[
        "box",
        "mail"
    ],
    "wof:name":"Mailend Co",
    "wof:placetype":"venue"
},
  "geometry": {"coordinates":[-117.905102,33.98847],"type":"Point"}
}