{
  "type": "Feature",
  "properties": {
    "addr:full":"9912 Campo Rd Spring Valley CA 91977",
    "addr:housenumber":"9912",
    "addr:postcode":"91977",
    "addr:street":"Campo Rd",
    "iso:country":"US",
    "sg:address":"9912 Campo Rd",
    "sg:city":"Spring Valley",
    "sg:classifiers":[
        {
            "category":"Shopping",
            "subcategory":"Pawn Shop",
            "type":"Retail Goods"
        }
    ],
    "sg:phone":"+1 619 464 3458",
    "sg:postcode":"91977",
    "sg:province":"CA",
    "wof:name":"Benjamin's Bargains Pawn Shop",
    "wof:placetype":"venue"
},
  "geometry": {"coordinates":[-116.983002,32.747799],"type":"Point"}
}