{
  "type": "Feature",
  "properties": {
    "addr:full":"3810 Ocean View Blvd Montrose CA 91020",
    "addr:housenumber":"3810",
    "addr:postcode":"91020",
    "addr:street":"Ocean View Blvd",
    "iso:country":"US",
    "sg:address":"3810 Ocean View Blvd",
    "sg:city":"Montrose",
    "sg:classifiers":[
        {
            "category":"Personal",
            "subcategory":"Barber",
            "type":"Services"
        }
    ],
    "sg:phone":"+1 818 957 9868",
    "sg:postcode":"91020",
    "sg:province":"CA",
    "wof:name":"Montrose Barber Shop",
    "wof:placetype":"venue"
},
  "geometry": {"coordinates":[-118.227997,34.2057],"type":"Point"}
}