{
  "type": "Feature",
  "properties": {
    "iso:country":"US",
    "sg:address":"2060 Wilkins Ave",
    "sg:city":"Napa",
    "sg:classifiers":[
        {
            "category":"Shopping",
            "subcategory":"Clothing, Apparel, & Fashions",
            "type":"Retail Goods"
        }
    ],
    "sg:phone":"+1 707 227 5804",
    "sg:postcode":"94559",
    "sg:province":"CA",
    "sg:tags":[
        "t"
    ],
    "wof:name":"5 Star Vintage",
    "wof:placetype":"venue"
},
  "geometry": {"coordinates":[-122.270581,38.284465],"type":"Point"}
}