{
  "type": "Feature",
  "properties": {
    "iso:country":"US",
    "sg:address":"1001 Dove Street Suite 100",
    "sg:city":"Newport Beach",
    "sg:classifiers":[
        {
            "category":"Banks & Credit Unions",
            "subcategory":"Financial Services",
            "type":"Services"
        }
    ],
    "sg:phone":"+1 949 252 8898",
    "sg:postcode":"92660",
    "sg:province":"CA",
    "sg:tags":[
        "broker",
        "mortgage"
    ],
    "sg:website":"www.primepacific.com",
    "wof:name":"Prime Pacific Financial",
    "wof:placetype":"venue"
},
  "geometry": {"coordinates":[-117.86432499999999,33.65897],"type":"Point"}
}