{
  "type": "Feature",
  "properties": {
    "iso:country":"US",
    "sg:address":"870 Gretna Green Way",
    "sg:city":"Escondido",
    "sg:classifiers":[
        {
            "category":"Freight",
            "type":"Transportation"
        }
    ],
    "sg:phone":"+1 760 740 9114",
    "sg:postcode":"92025",
    "sg:province":"CA",
    "sg:tags":[
        "operator",
        "mover",
        "local",
        "trucking"
    ],
    "wof:name":"AAA Two Men Will Move You In",
    "wof:placetype":"venue"
},
  "geometry": {"coordinates":[-117.05276499999999,33.08575],"type":"Point"}
}