{
  "type": "Feature",
  "properties": {
    "addr:full":"13560 Firestone Blvd Santa Fe Springs CA 90670",
    "addr:housenumber":"13560",
    "addr:postcode":"90670",
    "addr:street":"Firestone Blvd",
    "iso:country":"US",
    "sg:address":"13560 Firestone Blvd",
    "sg:city":"Santa Fe Springs",
    "sg:classifiers":[
        {
            "category":"Wholesale",
            "subcategory":"Groceries",
            "type":"Manufacturing & Wholesale Goods"
        }
    ],
    "sg:phone":"+1 562 483 7337",
    "sg:postcode":"90670",
    "sg:province":"CA",
    "sg:tags":[
        "beverage"
    ],
    "wof:name":"Vend Catering Supply",
    "wof:placetype":"venue"
},
  "geometry": {"coordinates":[-118.041957,33.890903],"type":"Point"}
}