{
  "type": "Feature",
  "properties": {
    "addr:full":"402 W 4th St Santa Ana CA 92701",
    "addr:housenumber":"402",
    "addr:postcode":"92701",
    "addr:street":"W 4Th St",
    "iso:country":"US",
    "sg:address":"402 W 4th St",
    "sg:city":"Santa Ana",
    "sg:classifiers":[
        {
            "category":"Health Services",
            "subcategory":"Optometrist",
            "type":"Services"
        }
    ],
    "sg:phone":"+1 714 558 7200",
    "sg:postcode":"92701",
    "sg:province":"CA",
    "wof:name":"Uptown Optometry",
    "wof:placetype":"venue"
},
  "geometry": {"coordinates":[-117.872426,33.747885],"type":"Point"}
}