{
  "type": "Feature",
  "properties": {
    "iso:country":"US",
    "sg:address":"1144 W Avenue I",
    "sg:city":"Lancaster",
    "sg:classifiers":[
        {
            "category":"Wholesale",
            "subcategory":"Construction Materials",
            "type":"Manufacturing & Wholesale Goods"
        },
        {
            "category":"Building & Trades",
            "subcategory":"Construction",
            "type":"Services"
        },
        {
            "category":"Wholesale",
            "subcategory":"Machinery & Supplies",
            "type":"Manufacturing & Wholesale Goods"
        },
        {
            "category":"Home & Garden",
            "subcategory":"Building Materials",
            "type":"Retail Goods"
        },
        {
            "category":"Professional",
            "subcategory":"Engineering",
            "type":"Services"
        },
        {
            "category":"Wholesale",
            "subcategory":"Electrical",
            "type":"Manufacturing & Wholesale Goods"
        }
    ],
    "sg:phone":"+1 661 945 6902",
    "sg:postcode":"93534",
    "sg:province":"CA",
    "sg:tags":[
        "major",
        "appliance",
        "system",
        "systems-wholesale",
        "equipment",
        "heating",
        "part",
        "contractor",
        "air conditioning",
        "manufacturer"
    ],
    "sg:website":"http://www.aircold.com",
    "wof:name":"Air Cold Supply, a Ferguson Enterprise",
    "wof:placetype":"venue"
},
  "geometry": {"coordinates":[-118.15026899999999,34.703966],"type":"Point"}
}