{
  "type": "Feature",
  "properties": {
    "addr:full":"5793 Acorn Ridge Dr Paradise CA 95969",
    "addr:housenumber":"5793",
    "addr:postcode":"95969",
    "addr:street":"Acorn Ridge Dr",
    "iso:country":"US",
    "sg:address":"5793 Acorn Ridge Dr",
    "sg:city":"Paradise",
    "sg:classifiers":[
        {
            "category":"Wholesale",
            "subcategory":"Medical Equipment & Supplies",
            "type":"Manufacturing & Wholesale Goods"
        },
        {
            "category":"Manufacturing",
            "subcategory":"Tools & Machinery",
            "type":"Manufacturing & Wholesale Goods"
        }
    ],
    "sg:phone":"+1 530 872 7063",
    "sg:postcode":"95969",
    "sg:province":"CA",
    "sg:tags":[
        "physician",
        "surgeon",
        "professional"
    ],
    "sg:website":"www.micrapro.com",
    "wof:name":"Micra Pro Inc",
    "wof:placetype":"venue"
},
  "geometry": {"coordinates":[-121.643612,39.75526],"type":"Point"}
}