{
  "type": "Feature",
  "properties": {
    "addr:full":"1061 W 8th St San Pedro CA 90731",
    "addr:housenumber":"1061",
    "addr:postcode":"90731",
    "addr:street":"W 8Th St",
    "iso:country":"US",
    "sg:address":"1061 W 8th St",
    "sg:city":"San Pedro",
    "sg:classifiers":[
        {
            "category":"Building & Trades",
            "subcategory":"Electrical",
            "type":"Services"
        }
    ],
    "sg:phone":"+1 310 832 3327",
    "sg:postcode":"90731",
    "sg:province":"CA",
    "sg:tags":[
        "installation"
    ],
    "wof:name":"Pauls Installations Svc",
    "wof:placetype":"venue"
},
  "geometry": {"coordinates":[-118.300031,33.736907],"type":"Point"}
}