{
  "type": "Feature",
  "properties": {
    "addr:full":"22055 Clarendon St Ste 101 Woodland Hills CA 91367",
    "addr:housenumber":"22055",
    "addr:postcode":"91367",
    "addr:street":"Clarendon St Ste 101",
    "iso:country":"US",
    "sg:address":"22055 Clarendon St Ste 101",
    "sg:city":"Woodland Hills",
    "sg:classifiers":[
        {
            "category":"Health Services",
            "subcategory":"Chiropractor",
            "type":"Services"
        }
    ],
    "sg:phone":"+1 818 347 4700",
    "sg:postcode":"91367",
    "sg:province":"CA",
    "wof:name":"Purple Aura",
    "wof:placetype":"venue"
},
  "geometry": {"coordinates":[-118.607068,34.169777],"type":"Point"}
}