{
  "type": "Feature",
  "properties": {
    "iso:country":"US",
    "sg:address":"305 Main St",
    "sg:city":"Downieville",
    "sg:classifiers":[
        {
            "category":"Home & Garden",
            "subcategory":"Garden Supply",
            "type":"Retail Goods"
        }
    ],
    "sg:phone":"+1 530 289 3386",
    "sg:postcode":"95936",
    "sg:province":"CA",
    "sg:tags":[
        "nurseryman"
    ],
    "wof:name":"Feathers Flowers & Nursery",
    "wof:placetype":"venue"
},
  "geometry": {"coordinates":[-120.825534,39.566697],"type":"Point"}
}