{
  "type": "Feature",
  "properties": {
    "iso:country":"US",
    "sg:address":"2230 Quimby Rd",
    "sg:city":"San Jose",
    "sg:classifiers":[
        {
            "category":"Wholesale",
            "subcategory":"Construction Materials",
            "type":"Manufacturing & Wholesale Goods"
        }
    ],
    "sg:phone":"+1 408 274 7988",
    "sg:postcode":"95122",
    "sg:province":"CA",
    "wof:name":"Windows 4 Less",
    "wof:placetype":"venue"
},
  "geometry": {"coordinates":[-121.809497,37.323533],"type":"Point"}
}