{
  "type": "Feature",
  "properties": {
    "iso:country":"US",
    "sg:address":"3741 E Iowa Ave",
    "sg:city":"Fresno",
    "sg:classifiers":[
        {
            "category":"Building & Trades",
            "subcategory":"Construction",
            "type":"Services"
        }
    ],
    "sg:phone":"+1 559 237 8278",
    "sg:postcode":"93702",
    "sg:province":"CA",
    "sg:tags":[
        "handyman"
    ],
    "wof:name":"Rick's Handyman Svc",
    "wof:placetype":"venue"
},
  "geometry": {"coordinates":[-119.761481,36.744187],"type":"Point"}
}