{
  "type": "Feature",
  "properties": {
    "addr:full":"9177 Las Tunas Dr Ste A Temple City CA 91780",
    "addr:housenumber":"9177",
    "addr:postcode":"91780",
    "addr:street":"Las Tunas Dr Ste A",
    "iso:country":"US",
    "sg:address":"9177 Las Tunas Dr Ste A",
    "sg:city":"Temple City",
    "sg:classifiers":[
        {
            "category":"Shopping",
            "subcategory":"Florist",
            "type":"Retail Goods"
        }
    ],
    "sg:phone":"+1 626 286 8858",
    "sg:postcode":"91780",
    "sg:province":"CA",
    "sg:website":"www.flowermarttc.com/index.html",
    "wof:name":"Flower Mart",
    "wof:placetype":"venue"
},
  "geometry": {"coordinates":[-118.068297,34.105875],"type":"Point"}
}