{
  "type": "Feature",
  "properties": {
    "addr:full":"4542 E Pacific Coast Hwy Long Beach CA 90804",
    "addr:housenumber":"4542",
    "addr:postcode":"90804",
    "addr:street":"E Pacific Coast Hwy",
    "iso:country":"US",
    "sg:address":"4542 E Pacific Coast Hwy",
    "sg:city":"Long Beach",
    "sg:classifiers":[
        {
            "category":"Restaurant",
            "type":"Food & Drink"
        }
    ],
    "sg:menulink":"http://www.allmenus.com/ca/long-beach-lakewood/171840-burger-king/menu/",
    "sg:phone":"+1 310 498 6331",
    "sg:postcode":"90804",
    "sg:province":"CA",
    "sg:tags":[
        "burger",
        "american"
    ],
    "wof:name":"Burger King",
    "wof:placetype":"venue"
},
  "geometry": {"coordinates":[-118.139574,33.787775],"type":"Point"}
}