{
  "type": "Feature",
  "properties": {
    "addr:full":"1200 N Main St Santa Ana CA 92706",
    "addr:housenumber":"1200",
    "addr:postcode":"92706",
    "addr:street":"N Main St",
    "iso:country":"US",
    "sg:address":"1200 N Main St",
    "sg:city":"Santa Ana",
    "sg:classifiers":[
        {
            "category":"Government",
            "subcategory":"Office",
            "type":"Public Place"
        }
    ],
    "sg:phone":"+1 714 480 6767",
    "sg:postcode":"92706",
    "sg:province":"CA",
    "sg:tags":[
        "county",
        "program",
        "health"
    ],
    "wof:name":"Mental Health Svc Adult",
    "wof:placetype":"venue"
},
  "geometry": {"coordinates":[-117.867603,33.755628],"type":"Point"}
}