{
  "type": "Feature",
  "properties": {
    "addr:full":"3457 E 4th St Los Angeles CA 90063",
    "addr:housenumber":"3457",
    "addr:postcode":"90063",
    "addr:street":"E 4Th St",
    "iso:country":"US",
    "sg:address":"3457 E 4th St",
    "sg:city":"Los Angeles",
    "sg:classifiers":[
        {
            "category":"Retail",
            "subcategory":"Repair Shop",
            "type":"Services"
        }
    ],
    "sg:phone":"+1 323 268 7024",
    "sg:postcode":"90063",
    "sg:province":"CA",
    "sg:tags":[
        "reupholstery",
        "furniture"
    ],
    "wof:name":"Mariana's Custom Upholstery Shop",
    "wof:placetype":"venue"
},
  "geometry": {"coordinates":[-118.19499999999999,34.033298],"type":"Point"}
}