{
  "type": "Feature",
  "properties": {
    "addr:full":"22112 Queen St Castro Valley CA 94546",
    "addr:housenumber":"22112",
    "addr:postcode":"94546",
    "addr:street":"Queen St",
    "iso:country":"US",
    "sg:address":"22112 Queen St",
    "sg:city":"Castro Valley",
    "sg:classifiers":[
        {
            "category":"Building & Trades",
            "subcategory":"Construction",
            "type":"Services"
        }
    ],
    "sg:phone":"+1 510 581 0461",
    "sg:postcode":"94546",
    "sg:province":"CA",
    "sg:tags":[
        "carpentry",
        "contractor"
    ],
    "wof:name":"Bathgate & Bathgate",
    "wof:placetype":"venue"
},
  "geometry": {"coordinates":[-122.067168,37.687504],"type":"Point"}
}