{
  "type": "Feature",
  "properties": {
    "addr:full":"5923 Rosemead Blvd Pico Rivera CA 90660",
    "addr:housenumber":"5923",
    "addr:postcode":"90660",
    "addr:street":"Rosemead Blvd",
    "iso:country":"US",
    "sg:address":"5923 Rosemead Blvd",
    "sg:city":"Pico Rivera",
    "sg:classifiers":[
        {
            "category":"Autos & Motor Vehicles",
            "subcategory":"Fuel & Gas Station",
            "type":"Retail Goods"
        }
    ],
    "sg:phone":"+1 562 942 2687",
    "sg:postcode":"90660",
    "sg:province":"CA",
    "wof:name":"Hovig's Arco",
    "wof:placetype":"venue"
},
  "geometry": {"coordinates":[-118.08899700000001,33.992401],"type":"Point"}
}