{
  "type": "Feature",
  "properties": {
    "iso:country":"US",
    "sg:address":"1030 Nacimiento Lake Dr",
    "sg:city":"Paso Robles",
    "sg:classifiers":[
        {
            "category":"Home & Garden",
            "subcategory":"Garden Supply",
            "type":"Retail Goods"
        }
    ],
    "sg:phone":"+1 805 238 2122",
    "sg:postcode":"93446",
    "sg:province":"CA",
    "sg:tags":[
        "nurseryman"
    ],
    "wof:name":"Scott's Nursery Plus",
    "wof:placetype":"venue"
},
  "geometry": {"coordinates":[-120.72451599999999,35.652734],"type":"Point"}
}