{
  "type": "Feature",
  "properties": {
    "addr:full":"2399 Market Street San Francisco CA 94114",
    "addr:housenumber":"2399",
    "addr:postcode":"94114",
    "addr:street":"Market Street",
    "iso:country":"US",
    "sg:address":"2399 Market Street",
    "sg:city":"San Francisco",
    "sg:classifiers":[
        {
            "category":"Government",
            "subcategory":"Office",
            "type":"Public Place"
        }
    ],
    "sg:phone":"+1 415 431 7664",
    "sg:postcode":"94114",
    "sg:province":"CA",
    "sg:tags":[
        "smog",
        "check"
    ],
    "wof:name":"Smog Queen Test Only Station",
    "wof:placetype":"venue"
},
  "geometry": {"coordinates":[-122.43499799999999,37.762699],"type":"Point"}
}