{
  "type": "Feature",
  "properties": {
    "iso:country":"US",
    "sg:address":"832 Seward St",
    "sg:city":"Los Angeles",
    "sg:classifiers":[
        {
            "category":"Cinema",
            "subcategory":"Movie Theater",
            "type":"Entertainment"
        }
    ],
    "sg:phone":"+1 323 467 7545",
    "sg:postcode":"90038",
    "sg:province":"CA",
    "wof:name":"Kilpatric-Cambridge Theater",
    "wof:placetype":"venue"
},
  "geometry": {"coordinates":[-118.333074,34.086513],"type":"Point"}
}