{
  "type": "Feature",
  "properties": {
    "iso:country":"US",
    "sg:address":"2300 S Reservoir St",
    "sg:city":"Pomona",
    "sg:classifiers":[
        {
            "category":"Manufacturing",
            "subcategory":"Tools & Machinery",
            "type":"Manufacturing & Wholesale Goods"
        }
    ],
    "sg:phone":"+1 909 590 5054",
    "sg:postcode":"91766",
    "sg:province":"CA",
    "sg:tags":[
        "thermocouple",
        "mfg"
    ],
    "wof:name":"Southland Sensors Inc",
    "wof:placetype":"venue"
},
  "geometry": {"coordinates":[-117.731506,34.026478],"type":"Point"}
}