{
  "type": "Feature",
  "properties": {
    "iso:country":"US",
    "sg:address":"2441 N 1st St",
    "sg:city":"Fresno",
    "sg:classifiers":[
        {
            "category":"Restaurant",
            "type":"Food & Drink"
        }
    ],
    "sg:phone":"+1 559 225 8060",
    "sg:postcode":"93703",
    "sg:province":"CA",
    "sg:tags":[
        "eating"
    ],
    "wof:name":"May MEI Chinese Restaurants",
    "wof:placetype":"venue"
},
  "geometry": {"coordinates":[-119.772599,36.772397],"type":"Point"}
}