{
  "type": "Feature",
  "properties": {
    "iso:country":"US",
    "sg:address":"8727 Lake Murray Blvd",
    "sg:city":"San Diego",
    "sg:classifiers":[
        {
            "category":"Professional",
            "type":"Services"
        }
    ],
    "sg:phone":"+1 619 461 1348",
    "sg:postcode":"92119",
    "sg:province":"CA",
    "wof:name":"Boris Abramovich",
    "wof:placetype":"venue"
},
  "geometry": {"coordinates":[-117.01058500000001,32.802435],"type":"Point"}
}