{
  "type": "Feature",
  "properties": {
    "addr:full":"840 N Hillview Dr Milpitas CA 95035",
    "addr:housenumber":"840",
    "addr:postcode":"95035",
    "addr:street":"N Hillview Dr",
    "iso:country":"US",
    "sg:address":"840 N Hillview Dr",
    "sg:city":"Milpitas",
    "sg:classifiers":[
        {
            "category":"Banks & Credit Unions",
            "subcategory":"Bank",
            "type":"Services"
        }
    ],
    "sg:phone":"+1 408 586 9777",
    "sg:postcode":"95035",
    "sg:province":"CA",
    "sg:tags":[
        "financing"
    ],
    "wof:name":"Priority One Funding",
    "wof:placetype":"venue"
},
  "geometry": {"coordinates":[-121.893179,37.445627],"type":"Point"}
}