{
  "type": "Feature",
  "properties": {
    "addr:full":"3343 Santa Fe St Riverbank CA 95367",
    "addr:housenumber":"3343",
    "addr:postcode":"95367",
    "addr:street":"Santa Fe St",
    "iso:country":"US",
    "sg:address":"3343 Santa Fe St",
    "sg:city":"Riverbank",
    "sg:classifiers":[
        {
            "category":"Building & Trades",
            "subcategory":"Construction",
            "type":"Services"
        }
    ],
    "sg:phone":"+1 209 869 5140",
    "sg:postcode":"95367",
    "sg:province":"CA",
    "sg:tags":[
        "residential",
        "contractor",
        "nonresidential"
    ],
    "wof:name":"JHK Construction",
    "wof:placetype":"venue"
},
  "geometry": {"coordinates":[-120.934617,37.736091],"type":"Point"}
}