{
  "type": "Feature",
  "properties": {
    "addr:full":"151 W 73rd St Los Angeles CA 90003",
    "addr:housenumber":"151",
    "addr:postcode":"90003",
    "addr:street":"W 73Rd St",
    "iso:country":"US",
    "sg:address":"151 W 73rd St",
    "sg:city":"Los Angeles",
    "sg:classifiers":[
        {
            "category":"Organizations",
            "subcategory":"Religious Organization",
            "type":"Services"
        }
    ],
    "sg:phone":"+1 323 758 5888",
    "sg:postcode":"90003",
    "sg:province":"CA",
    "sg:tags":[
        "church"
    ],
    "wof:name":"Los Angeles Church Of God",
    "wof:placetype":"venue"
},
  "geometry": {"coordinates":[-118.277382,33.973787],"type":"Point"}
}