{
  "type": "Feature",
  "properties": {
    "addr:full":"1410 62nd Ave Oakland CA 94621",
    "addr:housenumber":"1410",
    "addr:postcode":"94621",
    "addr:street":"62Nd Ave",
    "iso:country":"US",
    "sg:address":"1410 62nd Ave",
    "sg:city":"Oakland",
    "sg:classifiers":[
        {
            "category":"Manufacturing",
            "subcategory":"Printing",
            "type":"Manufacturing & Wholesale Goods"
        }
    ],
    "sg:phone":"+1 510 550 8280",
    "sg:postcode":"94621",
    "sg:province":"CA",
    "sg:tags":[
        "publishers-directory",
        "guide"
    ],
    "wof:name":"Chinook Book",
    "wof:placetype":"venue"
},
  "geometry": {"coordinates":[-122.197141,37.764017],"type":"Point"}
}