{
  "type": "Feature",
  "properties": {
    "iso:country":"US",
    "sg:address":"5443 E Washington Blvd",
    "sg:city":"Los Angeles",
    "sg:classifiers":[
        {
            "category":"Manufacturing",
            "subcategory":"Apparel",
            "type":"Manufacturing & Wholesale Goods"
        }
    ],
    "sg:phone":"+1 323 726 9040",
    "sg:postcode":"90040",
    "sg:province":"CA",
    "sg:tags":[
        "uniform"
    ],
    "wof:name":"JCM & Assoc",
    "wof:placetype":"venue"
},
  "geometry": {"coordinates":[-118.161872,34.001141],"type":"Point"}
}