{
  "type": "Feature",
  "properties": {
    "iso:country":"US",
    "sg:address":"191A University Ave",
    "sg:city":"Berkeley",
    "sg:classifiers":[
        {
            "category":"Education",
            "subcategory":"University",
            "type":"Public Place"
        }
    ],
    "sg:phone":"+1 510 643 4235",
    "sg:postcode":"94710",
    "sg:province":"CA",
    "sg:tags":[
        "college"
    ],
    "wof:name":"Berkeley Budget Finance",
    "wof:placetype":"venue"
},
  "geometry": {"coordinates":[-122.314171,37.863682],"type":"Point"}
}