{
  "type": "Feature",
  "properties": {
    "iso:country":"US",
    "sg:address":"120 S 11th Ave",
    "sg:city":"Hanford",
    "sg:classifiers":[
        {
            "category":"Building & Trades",
            "subcategory":"Equipment Rental",
            "type":"Services"
        }
    ],
    "sg:phone":"+1 559 583 6003",
    "sg:postcode":"93230",
    "sg:province":"CA",
    "sg:tags":[
        "television"
    ],
    "wof:name":"Family Rental Ctr",
    "wof:placetype":"venue"
},
  "geometry": {"coordinates":[-119.65527400000001,36.323125],"type":"Point"}
}