{
  "type": "Feature",
  "properties": {
    "addr:full":"7403 W Sunset Boulevard Los Angeles CA 90046",
    "addr:housenumber":"7403",
    "addr:postcode":"90046",
    "addr:street":"W Sunset Boulevard",
    "iso:country":"US",
    "sg:address":"7403 W Sunset Boulevard",
    "sg:city":"Los Angeles",
    "sg:classifiers":[
        {
            "category":"Arts & Performance",
            "subcategory":"Art Gallery",
            "type":"Entertainment"
        }
    ],
    "sg:phone":"+1 323 882 8340",
    "sg:postcode":"90046",
    "sg:province":"CA",
    "wof:name":"The Shooting Gallery",
    "wof:placetype":"venue"
},
  "geometry": {"coordinates":[-118.35111999999999,34.097911],"type":"Point"}
}