{
  "type": "Feature",
  "properties": {
    "addr:full":"7250 Calabria Ct San Diego CA 92122",
    "addr:housenumber":"7250",
    "addr:postcode":"92122",
    "addr:street":"Calabria Ct",
    "iso:country":"US",
    "sg:address":"7250 Calabria Ct",
    "sg:city":"San Diego",
    "sg:classifiers":[
        {
            "category":"Building & Trades",
            "subcategory":"Construction",
            "type":"Services"
        }
    ],
    "sg:phone":"+1 619 593 8238",
    "sg:postcode":"92122",
    "sg:province":"CA",
    "sg:tags":[
        "tile",
        "contractor"
    ],
    "wof:name":"Dale A Mollenhauer",
    "wof:placetype":"venue"
},
  "geometry": {"coordinates":[-117.204632,32.86608],"type":"Point"}
}