{
  "type": "Feature",
  "properties": {
    "iso:country":"US",
    "sg:address":"5841 S San Pedro St",
    "sg:city":"Los Angeles",
    "sg:classifiers":[
        {
            "category":"Building & Trades",
            "subcategory":"Construction",
            "type":"Services"
        }
    ],
    "sg:phone":"+1 323 231 5407",
    "sg:postcode":"90003",
    "sg:province":"CA",
    "sg:tags":[
        "graffito",
        "protection",
        "removal"
    ],
    "wof:name":"Central Recovery & Development",
    "wof:placetype":"venue"
},
  "geometry": {"coordinates":[-118.26958999999999,33.988736],"type":"Point"}
}