{
  "type": "Feature",
  "properties": {
    "addr:full":"16462 Norwalk Blvd Cerritos CA 90703",
    "addr:housenumber":"16462",
    "addr:postcode":"ca 90703",
    "addr:street":"Norwalk Blvd",
    "iso:country":"US",
    "sg:address":"16462 Norwalk Blvd",
    "sg:city":"Cerritos",
    "sg:classifiers":[
        {
            "category":"Juice Bar",
            "subcategory":"None",
            "type":"Food & Drink"
        }
    ],
    "sg:phone":"+1 562 229 1028",
    "sg:postcode":"90703",
    "sg:province":"CA",
    "sg:tags":[
        "smoothy"
    ],
    "wof:name":"Hcp Drinking & Juice Stop",
    "wof:placetype":"venue"
},
  "geometry": {"coordinates":[-118.072998,33.881199],"type":"Point"}
}