{
  "type": "Feature",
  "properties": {
    "addr:full":"3991 MacArthur Boulevard Suite 175 Newport Beach CA 92660",
    "addr:housenumber":"3991",
    "addr:postcode":"92660",
    "addr:street":"Macarthur Boulevard Suite 175",
    "iso:country":"US",
    "sg:address":"3991 MacArthur Boulevard Suite 175",
    "sg:city":"Newport Beach",
    "sg:classifiers":[
        {
            "category":"Professional",
            "subcategory":"Lawyer & Legal Services",
            "type":"Services"
        }
    ],
    "sg:phone":"+1 949 833 8898",
    "sg:postcode":"92660",
    "sg:province":"CA",
    "wof:name":"Wright Loyd E III Law Offices of",
    "wof:placetype":"venue"
},
  "geometry": {"coordinates":[-117.863134,33.659356],"type":"Point"}
}