{
  "type": "Feature",
  "properties": {
    "iso:country":"US",
    "sg:address":"2326 Cabrillo Ave",
    "sg:city":"Torrance",
    "sg:classifiers":[
        {
            "category":"Organizations",
            "subcategory":"Community Association",
            "type":"Services"
        }
    ],
    "sg:phone":"+1 310 320 4060",
    "sg:postcode":"90501",
    "sg:province":"CA",
    "sg:tags":[
        "fraternal"
    ],
    "wof:name":"Masonic Lodge",
    "wof:placetype":"venue"
},
  "geometry": {"coordinates":[-118.314139,33.825419],"type":"Point"}
}