{
  "type": "Feature",
  "properties": {
    "addr:full":"8307 W 3rd St Los Angeles CA 90048",
    "addr:housenumber":"8307",
    "addr:postcode":"90048",
    "addr:street":"W 3Rd St",
    "iso:country":"US",
    "sg:address":"8307 W 3rd St",
    "sg:city":"Los Angeles",
    "sg:classifiers":[
        {
            "category":"Shopping",
            "subcategory":"Shoes",
            "type":"Retail Goods"
        }
    ],
    "sg:phone":"+1 323 655 6133",
    "sg:postcode":"90048",
    "sg:province":"CA",
    "sg:tags":[
        "store"
    ],
    "wof:name":"Sigerson Morrison",
    "wof:placetype":"venue"
},
  "geometry": {"coordinates":[-118.370003,34.072601],"type":"Point"}
}