{
  "type": "Feature",
  "properties": {
    "iso:country":"US",
    "sg:address":"4345 E Tulare Ave",
    "sg:city":"Fresno",
    "sg:classifiers":[
        {
            "category":"Shopping",
            "subcategory":"Music",
            "type":"Retail Goods"
        }
    ],
    "sg:phone":"+1 559 456 4326",
    "sg:postcode":"93702",
    "sg:province":"CA",
    "sg:tags":[
        "video",
        "disc",
        "tape",
        "cassette"
    ],
    "wof:name":"Heng Heng Video Rental & Toys",
    "wof:placetype":"venue"
},
  "geometry": {"coordinates":[-119.753568,36.743228],"type":"Point"}
}