{
  "type": "Feature",
  "properties": {
    "iso:country":"US",
    "sg:address":"17502 Garrison Rd",
    "sg:city":"Cottonwood",
    "sg:classifiers":[
        {
            "category":"Retail",
            "subcategory":"Animal Services",
            "type":"Services"
        }
    ],
    "sg:phone":"+1 530 347 9958",
    "sg:postcode":"96022",
    "sg:province":"CA",
    "wof:name":"Bound For Home Boarding Kennel",
    "wof:placetype":"venue"
},
  "geometry": {"coordinates":[-122.395639,40.303747],"type":"Point"}
}