{
  "type": "Feature",
  "properties": {
    "iso:country":"US",
    "sg:address":"5015 Pacific St",
    "sg:city":"Rocklin",
    "sg:classifiers":[
        {
            "category":"Restaurant",
            "type":"Food & Drink"
        }
    ],
    "sg:phone":"+1 916 624 4678",
    "sg:postcode":"95677",
    "sg:province":"CA",
    "wof:name":"Happy Pacific Chinese",
    "wof:placetype":"venue"
},
  "geometry": {"coordinates":[-121.23480000000001,38.792089],"type":"Point"}
}