{
  "type": "Feature",
  "properties": {
    "iso:country":"US",
    "sg:address":"14787 Pomerado Rd",
    "sg:city":"Poway",
    "sg:classifiers":[
        {
            "category":"Personal",
            "subcategory":"Beauty Salon",
            "type":"Services"
        }
    ],
    "sg:phone":"+1 858 486 0405",
    "sg:postcode":"92064",
    "sg:province":"CA",
    "wof:name":"Great Clips",
    "wof:placetype":"venue"
},
  "geometry": {"coordinates":[-117.062181,32.982364],"type":"Point"}
}