{
  "type": "Feature",
  "properties": {
    "iso:country":"US",
    "sg:address":"2130 51st St",
    "sg:city":"Sacramento",
    "sg:classifiers":[
        {
            "category":"Food & Beverages",
            "subcategory":"Groceries & Convenience Stores",
            "type":"Retail Goods"
        }
    ],
    "sg:phone":"+1 916 739 6310",
    "sg:postcode":"95817",
    "sg:province":"CA",
    "wof:name":"Cottage Mart",
    "wof:placetype":"venue"
},
  "geometry": {"coordinates":[-121.445999,38.553902],"type":"Point"}
}