{
  "type": "Feature",
  "properties": {
    "addr:full":"11430 I Ave Hesperia CA 92345",
    "addr:housenumber":"11430",
    "addr:postcode":"92345",
    "addr:street":"I Ave",
    "iso:country":"US",
    "sg:address":"11430 I Ave",
    "sg:city":"Hesperia",
    "sg:phone":"+1 760 953 4219",
    "sg:postcode":"92345",
    "sg:province":"CA",
    "wof:name":"Auction City",
    "wof:placetype":"venue"
},
  "geometry": {"coordinates":[-117.277186,34.458744],"type":"Point"}
}