{
  "type": "Feature",
  "properties": {
    "addr:full":"740 S 41st St Richmond CA 94804",
    "addr:housenumber":"740",
    "addr:postcode":"94804",
    "addr:street":"S 41St St",
    "iso:country":"US",
    "sg:address":"740 S 41st St",
    "sg:city":"Richmond",
    "sg:classifiers":[
        {
            "category":"Communications",
            "subcategory":"Film & Video Production",
            "type":"Services"
        },
        {
            "category":"Professional",
            "subcategory":"Art Services",
            "type":"Services"
        }
    ],
    "sg:phone":"+1 510 412 2148",
    "sg:postcode":"94804",
    "sg:province":"CA",
    "sg:tags":[
        "creative",
        "audio-visual"
    ],
    "wof:name":"Terra Post Productions",
    "wof:placetype":"venue"
},
  "geometry": {"coordinates":[-122.330673,37.922089],"type":"Point"}
}