{
  "type": "Feature",
  "properties": {
    "addr:full":"25931 Gardner St Loma Linda CA 92354",
    "addr:housenumber":"25931",
    "addr:postcode":"92354",
    "addr:street":"Gardner St",
    "iso:country":"US",
    "sg:address":"25931 Gardner St",
    "sg:city":"Loma Linda",
    "sg:classifiers":[
        {
            "category":"Travel",
            "subcategory":"Travel Agent",
            "type":"Entertainment"
        }
    ],
    "sg:phone":"+1 909 796 6941",
    "sg:postcode":"92354",
    "sg:province":"CA",
    "sg:tags":[
        "agency",
        "bureau"
    ],
    "wof:name":"Adnar Travel Svc",
    "wof:placetype":"venue"
},
  "geometry": {"coordinates":[-117.23759699999999,34.043777],"type":"Point"}
}