{
  "type": "Feature",
  "properties": {
    "iso:country":"US",
    "sg:address":"541 Frederick Street",
    "sg:city":"Santa Cruz",
    "sg:classifiers":[
        {
            "category":"Health Services",
            "subcategory":"Doctor",
            "type":"Services"
        }
    ],
    "sg:phone":"+1 831 457 2361",
    "sg:postcode":"95062",
    "sg:province":"CA",
    "sg:tags":[
        "cardiologist"
    ],
    "wof:name":"Owens John P Pediatric Cardiologist",
    "wof:placetype":"venue"
},
  "geometry": {"coordinates":[-121.98527,36.973367],"type":"Point"}
}