{
  "type": "Feature",
  "properties": {
    "iso:country":"US",
    "sg:address":"4016 Dale Rd",
    "sg:city":"Modesto",
    "sg:classifiers":[
        {
            "category":"Health Services",
            "subcategory":"Doctor",
            "type":"Services"
        }
    ],
    "sg:phone":"+1 209 238 3589",
    "sg:postcode":"95356",
    "sg:province":"CA",
    "sg:tags":[
        "physician",
        "surgeon",
        "surgeons",
        "surgery-general"
    ],
    "wof:name":"American Dental Surgery Centers, Inc.",
    "wof:placetype":"venue"
},
  "geometry": {"coordinates":[-121.049986,37.696953],"type":"Point"}
}