{
  "type": "Feature",
  "properties": {
    "iso:country":"US",
    "sg:address":"509 Grand Caribe Cswy",
    "sg:city":"Coronado",
    "sg:classifiers":[
        {
            "category":"Real Estate",
            "subcategory":"Real Estate Services",
            "type":"Services"
        }
    ],
    "sg:phone":"+1 619 424 7000",
    "sg:postcode":"92118",
    "sg:province":"CA",
    "wof:name":"Coronado Cays Realty",
    "wof:placetype":"venue"
},
  "geometry": {"coordinates":[-117.130787,32.624048],"type":"Point"}
}