{
  "type": "Feature",
  "properties": {
    "addr:full":"2780 State St Carlsbad CA 92008",
    "addr:housenumber":"2780",
    "addr:postcode":"92008",
    "addr:street":"State St",
    "iso:country":"US",
    "sg:address":"2780 State St",
    "sg:city":"Carlsbad",
    "sg:classifiers":[
        {
            "category":"Restaurant",
            "type":"Food & Drink"
        }
    ],
    "sg:phone":"+1 760 434 3497",
    "sg:postcode":"92008",
    "sg:province":"CA",
    "sg:website":"www.masfinacantina.com",
    "wof:name":"Mas Fina Cantina",
    "wof:placetype":"venue"
},
  "geometry": {"coordinates":[-117.350998,33.161598],"type":"Point"}
}