{
  "type": "Feature",
  "properties": {
    "addr:full":"2597 N Fordham Ave Fresno CA 93727",
    "addr:housenumber":"2597",
    "addr:postcode":"93727",
    "addr:street":"N Fordham Ave",
    "iso:country":"US",
    "sg:address":"2597 N Fordham Ave",
    "sg:city":"Fresno",
    "sg:classifiers":[
        {
            "category":"Manufacturing",
            "subcategory":"Retail Goods",
            "type":"Manufacturing & Wholesale Goods"
        }
    ],
    "sg:phone":"+1 559 294 7414",
    "sg:postcode":"93727",
    "sg:province":"CA",
    "sg:tags":[
        "product",
        "mfg"
    ],
    "wof:name":"Mhf Mfg",
    "wof:placetype":"venue"
},
  "geometry": {"coordinates":[-119.687612,36.773928],"type":"Point"}
}