{
  "type": "Feature",
  "properties": {
    "addr:full":"942 South Los Angeles Street Los Angeles CA 90015",
    "addr:housenumber":"942",
    "addr:postcode":"90015",
    "addr:street":"South Los Angeles Street",
    "iso:country":"US",
    "sg:address":"942 South Los Angeles Street",
    "sg:city":"Los Angeles",
    "sg:classifiers":[
        {
            "category":"Shopping",
            "subcategory":"Clothing, Apparel, & Fashions",
            "type":"Retail Goods"
        }
    ],
    "sg:phone":"+1 213 624 7335",
    "sg:postcode":"90015",
    "sg:province":"CA",
    "wof:name":"Kala International",
    "wof:placetype":"venue"
},
  "geometry": {"coordinates":[-118.254997,34.0401],"type":"Point"}
}