{
  "type": "Feature",
  "properties": {
    "addr:full":"1241 Adams St Saint Helena CA 94574",
    "addr:housenumber":"1241",
    "addr:postcode":"94574",
    "addr:street":"Adams St",
    "iso:country":"US",
    "sg:address":"1241 Adams St",
    "sg:city":"Saint Helena",
    "sg:classifiers":[
        {
            "category":"Manufacturing",
            "subcategory":"Food",
            "type":"Manufacturing & Wholesale Goods"
        }
    ],
    "sg:phone":"+1 707 968 9297",
    "sg:postcode":"94574",
    "sg:province":"CA",
    "sg:tags":[
        "operations",
        "grape",
        "mfg",
        "varietal",
        "vineyard",
        "wine"
    ],
    "wof:name":"Girard Winery LLC",
    "wof:placetype":"venue"
},
  "geometry": {"coordinates":[-122.47037400000001,38.505152],"type":"Point"}
}