{
  "type": "Feature",
  "properties": {
    "iso:country":"US",
    "sg:address":"18600 Ventura Blvd",
    "sg:city":"Tarzana",
    "sg:classifiers":[
        {
            "category":"Shopping",
            "subcategory":"Florist",
            "type":"Retail Goods"
        }
    ],
    "sg:phone":"+1 818 996 0109",
    "sg:postcode":"91356",
    "sg:province":"CA",
    "wof:name":"Floral Creations By Wayne",
    "wof:placetype":"venue"
},
  "geometry": {"coordinates":[-118.540155,34.170443],"type":"Point"}
}