{
  "type": "Feature",
  "properties": {
    "addr:full":"100 Louis Ln Roseville CA 95661",
    "addr:housenumber":"100",
    "addr:postcode":"95661",
    "addr:street":"Louis Ln",
    "iso:country":"US",
    "sg:address":"100 Louis Ln",
    "sg:city":"Roseville",
    "sg:classifiers":[
        {
            "category":"Retail",
            "subcategory":"Repair Shop",
            "type":"Services"
        }
    ],
    "sg:phone":"+1 702 641 4002",
    "sg:postcode":"95661",
    "sg:province":"CA",
    "sg:tags":[
        "scooter",
        "motorcycle",
        "motor"
    ],
    "wof:name":"Dick's Racing",
    "wof:placetype":"venue"
},
  "geometry": {"coordinates":[-121.289655,38.722114],"type":"Point"}
}