{
  "type": "Feature",
  "properties": {
    "iso:country":"US",
    "sg:address":"2125 Lacey Blvd",
    "sg:city":"Hanford",
    "sg:classifiers":[
        {
            "category":"Manufacturing",
            "subcategory":"Chemicals & Compounds",
            "type":"Manufacturing & Wholesale Goods"
        },
        {
            "category":"Home & Garden",
            "subcategory":"Garden Supply",
            "type":"Retail Goods"
        }
    ],
    "sg:phone":"+1 559 582 8825",
    "sg:postcode":"93230",
    "sg:province":"CA",
    "sg:tags":[
        "equipment",
        "landscaping"
    ],
    "wof:name":"Transition Farming Co.",
    "wof:placetype":"venue"
},
  "geometry": {"coordinates":[-119.682705,36.328081],"type":"Point"}
}