{
  "type": "Feature",
  "properties": {
    "iso:country":"US",
    "sg:address":"22517 Crenshaw Blvd",
    "sg:city":"Torrance",
    "sg:classifiers":[
        {
            "category":"Health Services",
            "subcategory":"Dentist",
            "type":"Services"
        }
    ],
    "sg:phone":"+1 310 370 5508",
    "sg:postcode":"90505",
    "sg:province":"CA",
    "wof:name":"Dr Gendy DDS",
    "wof:placetype":"venue"
},
  "geometry": {"coordinates":[-118.328678,33.821382],"type":"Point"}
}