{
  "type": "Feature",
  "properties": {
    "iso:country":"US",
    "sg:address":"2754 Teepee Dr",
    "sg:city":"Stockton",
    "sg:classifiers":[
        {
            "category":"Manufacturing",
            "subcategory":"Motor Vehicles & Parts",
            "type":"Manufacturing & Wholesale Goods"
        }
    ],
    "sg:phone":"+1 209 463 9171",
    "sg:postcode":"95205",
    "sg:province":"CA",
    "sg:tags":[
        "equipment",
        "truck"
    ],
    "wof:name":"Duraliner",
    "wof:placetype":"venue"
},
  "geometry": {"coordinates":[-121.253148,37.987899],"type":"Point"}
}