{
  "type": "Feature",
  "properties": {
    "iso:country":"US",
    "sg:address":"350 N Van Ness Ave",
    "sg:city":"Fresno",
    "sg:classifiers":[
        {
            "category":"Professional",
            "subcategory":"Business Services",
            "type":"Services"
        }
    ],
    "sg:phone":"+1 559 268 4227",
    "sg:postcode":"93701",
    "sg:province":"CA",
    "wof:name":"Child Custody Program",
    "wof:placetype":"venue"
},
  "geometry": {"coordinates":[-119.798784,36.748408],"type":"Point"}
}