{
  "type": "Feature",
  "properties": {
    "iso:country":"US",
    "sg:address":"1431 S Garfield Ave",
    "sg:city":"Alhambra",
    "sg:classifiers":[
        {
            "category":"Professional",
            "subcategory":"Lawyer & Legal Services",
            "type":"Services"
        }
    ],
    "sg:phone":"+1 626 281 4345",
    "sg:postcode":"91801",
    "sg:province":"CA",
    "wof:name":"Tony Hai Professional Services",
    "wof:placetype":"venue"
},
  "geometry": {"coordinates":[-118.12338,34.077263],"type":"Point"}
}