{
  "type": "Feature",
  "properties": {
    "addr:full":"25124 Narbonne Ave Ste 106 Lomita CA 90717",
    "addr:postcode":"25124;90717",
    "addr:street":"Narbonne Ave Ste 106",
    "iso:country":"US",
    "sg:address":"25124 Narbonne Ave Ste 106",
    "sg:city":"Lomita",
    "sg:classifiers":[
        {
            "category":"Professional",
            "subcategory":"Lawyer & Legal Services",
            "type":"Services"
        }
    ],
    "sg:phone":"+1 310 539 6334",
    "sg:postcode":"90717",
    "sg:province":"CA",
    "wof:name":"Splinter Robt G Atty",
    "wof:placetype":"venue"
},
  "geometry": {"coordinates":[-118.31999999999999,33.796799],"type":"Point"}
}