{
  "type": "Feature",
  "properties": {
    "addr:full":"4542 Ruffner St San Diego CA 92111",
    "addr:housenumber":"4542",
    "addr:postcode":"92111",
    "addr:street":"Ruffner St",
    "iso:country":"US",
    "sg:address":"4542 Ruffner St",
    "sg:city":"San Diego",
    "sg:classifiers":[
        {
            "category":"Real Estate",
            "subcategory":"Real Estate Agent",
            "type":"Services"
        }
    ],
    "sg:phone":"+1 858 300 3140",
    "sg:postcode":"92111",
    "sg:province":"CA",
    "wof:name":"Desco Real Estate",
    "wof:placetype":"venue"
},
  "geometry": {"coordinates":[-117.157179,32.822788],"type":"Point"}
}