{
  "type": "Feature",
  "properties": {
    "addr:full":"10861 Cherry St Ste 300 Los Alamitos CA 90720",
    "addr:housenumber":"10861",
    "addr:postcode":"90720",
    "addr:street":"Cherry St Ste 300",
    "iso:country":"US",
    "sg:address":"10861 Cherry St Ste 300",
    "sg:city":"Los Alamitos",
    "sg:classifiers":[
        {
            "category":"Health Services",
            "subcategory":"Doctor",
            "type":"Services"
        }
    ],
    "sg:phone":"+1 562 594 8320",
    "sg:postcode":"90720",
    "sg:province":"CA",
    "sg:tags":[
        "obstetrician",
        "gynecologist"
    ],
    "wof:name":"Hetzler Gretchen MD",
    "wof:placetype":"venue"
},
  "geometry": {"coordinates":[-118.068001,33.804798],"type":"Point"}
}