{
  "type": "Feature",
  "properties": {
    "addr:full":"3095 Fair Oaks Blvd Sacramento CA 95864",
    "addr:housenumber":"3095",
    "addr:postcode":"95864",
    "addr:street":"Fair Oaks Blvd",
    "iso:country":"US",
    "sg:address":"3095 Fair Oaks Blvd",
    "sg:city":"Sacramento",
    "sg:classifiers":[
        {
            "category":"Banks & Credit Unions",
            "subcategory":"Financial Services",
            "type":"Services"
        }
    ],
    "sg:phone":"+1 916 489 5400",
    "sg:postcode":"95864",
    "sg:province":"CA",
    "sg:tags":[
        "broker",
        "mortgage"
    ],
    "wof:name":"First Priority Financial",
    "wof:placetype":"venue"
},
  "geometry": {"coordinates":[-121.392298,38.574307],"type":"Point"}
}