{
  "type": "Feature",
  "properties": {
    "addr:full":"5140 N State St Fresno CA 93722",
    "addr:housenumber":"5140",
    "addr:postcode":"93722",
    "addr:street":"N State St",
    "iso:country":"US",
    "sg:address":"5140 N State St",
    "sg:city":"Fresno",
    "sg:classifiers":[
        {
            "category":"Government",
            "subcategory":"Office",
            "type":"Public Place"
        }
    ],
    "sg:phone":"+1 559 276 0683",
    "sg:postcode":"93722",
    "sg:province":"CA",
    "sg:tags":[
        "village"
    ],
    "wof:name":"Highway City Community Ctr",
    "wof:placetype":"venue"
},
  "geometry": {"coordinates":[-119.88654,36.809214],"type":"Point"}
}