{
  "type": "Feature",
  "properties": {
    "addr:full":"77824 Wolf Rd Palm Desert CA 92211",
    "addr:housenumber":"77824",
    "addr:postcode":"92211",
    "addr:street":"Wolf Rd",
    "iso:country":"US",
    "sg:address":"77824 Wolf Rd",
    "sg:city":"Palm Desert",
    "sg:classifiers":[
        {
            "category":"Building & Trades",
            "subcategory":"Plumbing",
            "type":"Services"
        }
    ],
    "sg:phone":"+1 760 200 0446",
    "sg:postcode":"92211",
    "sg:province":"CA",
    "sg:tags":[
        "plumbing",
        "contractor"
    ],
    "wof:name":"Charles Scicli Plumbing",
    "wof:placetype":"venue"
},
  "geometry": {"coordinates":[-116.305234,33.764262],"type":"Point"}
}