{
  "type": "Feature",
  "properties": {
    "addr:full":"1193 Willow Rd Menlo Park CA 94025",
    "addr:housenumber":"1193",
    "addr:postcode":"94025",
    "addr:street":"Willow Rd",
    "iso:country":"US",
    "sg:address":"1193 Willow Rd",
    "sg:city":"Menlo Park",
    "sg:classifiers":[
        {
            "category":"Retail",
            "subcategory":"Laundry & Dry Cleaning",
            "type":"Services"
        }
    ],
    "sg:phone":"+1 650 325 9030",
    "sg:postcode":"94025",
    "sg:province":"CA",
    "wof:name":"Quality Laundry",
    "wof:placetype":"venue"
},
  "geometry": {"coordinates":[-122.154689,37.472697],"type":"Point"}
}