{
  "type": "Feature",
  "properties": {
    "iso:country":"US",
    "sg:address":"26267 Via California",
    "sg:city":"Capistrano Beach",
    "sg:classifiers":[
        {
            "category":"Professional",
            "type":"Services"
        }
    ],
    "sg:phone":"+1 949 496 1761",
    "sg:postcode":"92624",
    "sg:province":"CA",
    "wof:name":"Piano Tech",
    "wof:placetype":"venue"
},
  "geometry": {"coordinates":[-117.671586,33.462658],"type":"Point"}
}