{
  "type": "Feature",
  "properties": {
    "addr:full":"16830 Ventura Blvd Encino CA 91436",
    "addr:housenumber":"16830",
    "addr:postcode":"91436",
    "addr:street":"Ventura Blvd",
    "iso:country":"US",
    "sg:address":"16830 Ventura Blvd",
    "sg:city":"Encino",
    "sg:classifiers":[
        {
            "category":"Professional",
            "type":"Services"
        }
    ],
    "sg:phone":"+1 323 850 0709",
    "sg:postcode":"91436",
    "sg:province":"CA",
    "sg:tags":[
        "establishment"
    ],
    "wof:name":"Multi Globe Intl",
    "wof:placetype":"venue"
},
  "geometry": {"coordinates":[-118.499932,34.158903],"type":"Point"}
}