{
  "type": "Feature",
  "properties": {
    "iso:country":"US",
    "sg:address":"26720 Towne Centre Drive",
    "sg:city":"Foothill Ranch",
    "sg:classifiers":[
        {
            "category":"Health Services",
            "subcategory":"Dentist",
            "type":"Services"
        }
    ],
    "sg:phone":"+1 949 830 2003",
    "sg:postcode":"92610",
    "sg:province":"CA",
    "sg:tags":[
        "pediatric"
    ],
    "wof:name":"Mauricio Cardenas DDS",
    "wof:placetype":"venue"
},
  "geometry": {"coordinates":[-117.664163,33.674806],"type":"Point"}
}