{
  "type": "Feature",
  "properties": {
    "addr:full":"15354 Stafford St La Puente CA 91744",
    "addr:housenumber":"15354",
    "addr:postcode":"91744",
    "addr:street":"Stafford St",
    "iso:country":"US",
    "sg:address":"15354 Stafford St",
    "sg:city":"La Puente",
    "sg:classifiers":[
        {
            "category":"Professional",
            "subcategory":"Advertising",
            "type":"Services"
        }
    ],
    "sg:phone":"+1 626 968 8541",
    "sg:postcode":"91744",
    "sg:province":"CA",
    "sg:tags":[
        "counselor"
    ],
    "sg:website":"www.vertisinc.com",
    "wof:name":"Vertis",
    "wof:placetype":"venue"
},
  "geometry": {"coordinates":[-117.961721,34.026873],"type":"Point"}
}