{
  "type": "Feature",
  "properties": {
    "addr:full":"620 Drake Ave Sausalito CA 94965",
    "addr:housenumber":"620",
    "addr:postcode":"94965",
    "addr:street":"Drake Ave",
    "iso:country":"US",
    "sg:address":"620 Drake Ave",
    "sg:city":"Sausalito",
    "sg:classifiers":[
        {
            "category":"Social Services",
            "subcategory":"Child Care",
            "type":"Services"
        }
    ],
    "sg:phone":"+1 415 332 3460",
    "sg:postcode":"94965",
    "sg:province":"CA",
    "wof:name":"Manzanita Children's Ctr",
    "wof:placetype":"venue"
},
  "geometry": {"coordinates":[-122.514241,37.874023],"type":"Point"}
}