{
  "type": "Feature",
  "properties": {
    "acgov:api":"866.0",
    "addr:full":"543 Sonoma Avenue Livermore CA",
    "wof:categories":[
        "education_and_religion:education=school"
    ],
    "wof:name":"Livermore Valley Charter",
    "wof:placetype":"venue"
},
  "geometry": {"coordinates":[-121.79393883265926,37.6727372367208],"type":"Point"}
}