{
  "type": "Feature",
  "properties": {
    "addr:full":"800 N Yosemite Ave Oakdale CA 95361",
    "addr:housenumber":"800",
    "addr:postcode":"95361",
    "addr:street":"N Yosemite Ave",
    "iso:country":"US",
    "sg:address":"800 N Yosemite Ave",
    "sg:city":"Oakdale",
    "sg:classifiers":[
        {
            "category":"Restaurant",
            "type":"Food & Drink"
        }
    ],
    "sg:phone":"+1 209 847 7897",
    "sg:postcode":"95361",
    "sg:province":"CA",
    "wof:name":"Cindy's Restaurant",
    "wof:placetype":"venue"
},
  "geometry": {"coordinates":[-120.852611,37.775573],"type":"Point"}
}