{
  "type": "Feature",
  "properties": {
    "addr:full":"2115 Willow Rd Arroyo Grande CA 93420",
    "addr:housenumber":"2115",
    "addr:postcode":"93420",
    "addr:street":"Willow Rd",
    "iso:country":"US",
    "sg:address":"2115 Willow Rd",
    "sg:city":"Arroyo Grande",
    "sg:classifiers":[
        {
            "category":"Travel",
            "subcategory":"Travel Agent",
            "type":"Entertainment"
        }
    ],
    "sg:phone":"+1 805 481 4646",
    "sg:postcode":"93420",
    "sg:province":"CA",
    "sg:tags":[
        "operator",
        "tour"
    ],
    "wof:name":"American Star Transportation",
    "wof:placetype":"venue"
},
  "geometry": {"coordinates":[-120.573123,35.04722],"type":"Point"}
}