{
  "type": "Feature",
  "properties": {
    "addr:full":"15233 Stagg St Van Nuys CA 91405",
    "addr:postcode":"15233;91405",
    "addr:street":"Stagg St",
    "iso:country":"US",
    "sg:address":"15233 Stagg St",
    "sg:city":"Van Nuys",
    "sg:classifiers":[
        {
            "category":"Building & Trades",
            "subcategory":"Construction",
            "type":"Services"
        }
    ],
    "sg:phone":"+1 818 761 5267",
    "sg:postcode":"91405",
    "sg:province":"CA",
    "sg:tags":[
        "tile",
        "dealer"
    ],
    "wof:name":"S S Tile Co",
    "wof:placetype":"venue"
},
  "geometry": {"coordinates":[-118.46439599999999,34.212149],"type":"Point"}
}