{
  "type": "Feature",
  "properties": {
    "iso:country":"US",
    "sg:address":"15233 Stagg St",
    "sg:city":"Van Nuys",
    "sg:classifiers":[
        {
            "category":"Building & Trades",
            "subcategory":"Construction",
            "type":"Services"
        }
    ],
    "sg:phone":"+1 818 761 5267",
    "sg:postcode":"91405",
    "sg:province":"CA",
    "sg:tags":[
        "tile",
        "dealer"
    ],
    "wof:name":"S S Tile Co",
    "wof:placetype":"venue"
},
  "geometry": {"coordinates":[-118.464396,34.212149],"type":"Point"}
}