{
  "type": "Feature",
  "properties": {
    "addr:full":"20354 Thermal Rd Sanger CA 93657",
    "addr:postcode":"20354;ca 93657",
    "addr:street":"Thermal Rd",
    "iso:country":"US",
    "sg:address":"20354 Thermal Rd",
    "sg:city":"Sanger",
    "sg:classifiers":[
        {
            "category":"Farming",
            "subcategory":"Livestock Farm",
            "type":"Manufacturing & Wholesale Goods"
        }
    ],
    "sg:phone":"+1 559 787 2110",
    "sg:postcode":"93657",
    "sg:province":"CA",
    "sg:tags":[
        "specialty",
        "animal"
    ],
    "wof:name":"Herndons Apiary",
    "wof:placetype":"venue"
},
  "geometry": {"coordinates":[-119.42435999999999,36.75921],"type":"Point"}
}