{
  "type": "Feature",
  "properties": {
    "addr:full":"3385 Mount Vernon Ave Riverside CA 92507",
    "addr:housenumber":"3385",
    "addr:postcode":"92507",
    "addr:street":"Mount Vernon Ave",
    "iso:country":"US",
    "sg:address":"3385 Mount Vernon Ave",
    "sg:city":"Riverside",
    "sg:classifiers":[
        {
            "category":"Building & Trades",
            "subcategory":"Landscaping Services",
            "type":"Services"
        }
    ],
    "sg:phone":"+1 951 684 8564",
    "sg:postcode":"92507",
    "sg:province":"CA",
    "wof:name":"Brians Special Lawn Care",
    "wof:placetype":"venue"
},
  "geometry": {"coordinates":[-117.313729,33.981877],"type":"Point"}
}