{
  "type": "Feature",
  "properties": {
    "iso:country":"US",
    "sg:address":"609 1st St",
    "sg:city":"Arbuckle",
    "sg:classifiers":[
        {
            "category":"Manufacturing",
            "subcategory":"Printing",
            "type":"Manufacturing & Wholesale Goods"
        }
    ],
    "sg:phone":"+1 530 476 2423",
    "sg:postcode":"95912",
    "sg:province":"CA",
    "sg:tags":[
        "screen"
    ],
    "wof:name":"Shirley Free Supplies",
    "wof:placetype":"venue"
},
  "geometry": {"coordinates":[-122.052498,39.015376],"type":"Point"}
}