{
  "type": "Feature",
  "properties": {
    "iso:country":"US",
    "sg:address":"5809 E Beverly Blvd",
    "sg:city":"Los Angeles",
    "sg:classifiers":[
        {
            "category":"Personal",
            "subcategory":"Beauty Salon",
            "type":"Services"
        }
    ],
    "sg:phone":"+1 323 721 7335",
    "sg:postcode":"90022",
    "sg:province":"CA",
    "wof:name":"Heavenly Hands Clinical Skin",
    "wof:placetype":"venue"
},
  "geometry": {"coordinates":[-118.143539,34.026128],"type":"Point"}
}