{
  "type": "Feature",
  "properties": {
    "addr:full":"332 Orange Grove Ave San Fernando CA 91340",
    "addr:housenumber":"332",
    "addr:postcode":"91340",
    "addr:street":"Orange Grove Ave",
    "iso:country":"US",
    "sg:address":"332 Orange Grove Ave",
    "sg:city":"San Fernando",
    "sg:classifiers":[
        {
            "category":"Restaurant",
            "type":"Food & Drink"
        }
    ],
    "sg:phone":"+1 818 361 9493",
    "sg:postcode":"91340",
    "sg:province":"CA",
    "sg:tags":[
        "eating"
    ],
    "wof:name":"Pop Rage US",
    "wof:placetype":"venue"
},
  "geometry": {"coordinates":[-118.443753,34.291007],"type":"Point"}
}