{
  "type": "Feature",
  "properties": {
    "addr:full":"1013 W El Segundo Boulevard Gardena CA 90247",
    "addr:housenumber":"1013",
    "addr:postcode":"90247",
    "addr:street":"W El Segundo Boulevard",
    "iso:country":"US",
    "sg:address":"1013 W El Segundo Boulevard",
    "sg:city":"Gardena",
    "sg:classifiers":[
        {
            "category":"Food & Beverages",
            "subcategory":"Liquor & Beverages",
            "type":"Retail Goods"
        }
    ],
    "sg:phone":"+1 323 757 1377",
    "sg:postcode":"90247",
    "sg:province":"CA",
    "sg:tags":[
        "beer",
        "spirit",
        "wine"
    ],
    "wof:name":"J & S Liquor Station",
    "wof:placetype":"venue"
},
  "geometry": {"coordinates":[-118.293041,33.916314],"type":"Point"}
}