{
  "type": "Feature",
  "properties": {
    "addr:full":"1605 Highland Ave National City CA 91950",
    "addr:housenumber":"1605",
    "addr:postcode":"91950",
    "addr:street":"Highland Ave",
    "iso:country":"US",
    "sg:address":"1605 Highland Ave",
    "sg:city":"National City",
    "sg:classifiers":[
        {
            "category":"Retail",
            "subcategory":"Laundry & Dry Cleaning",
            "type":"Services"
        }
    ],
    "sg:phone":"+1 619 474 2480",
    "sg:postcode":"91950",
    "sg:province":"CA",
    "wof:name":"J C Laundry Group Inc",
    "wof:placetype":"venue"
},
  "geometry": {"coordinates":[-117.095293,32.66956],"type":"Point"}
}