{
  "type": "Feature",
  "properties": {
    "addr:full":"1715 E Wilshire Ave Santa Ana CA 92705",
    "addr:housenumber":"1715",
    "addr:postcode":"92705",
    "addr:street":"E Wilshire Ave",
    "iso:country":"US",
    "sg:address":"1715 E Wilshire Ave",
    "sg:city":"Santa Ana",
    "sg:classifiers":[
        {
            "category":"Personal",
            "subcategory":"Hair Removal",
            "type":"Services"
        }
    ],
    "sg:phone":"+1 714 550 9980",
    "sg:postcode":"92705",
    "sg:province":"CA",
    "wof:name":"Aesthetics Systems Usa Inc",
    "wof:placetype":"venue"
},
  "geometry": {"coordinates":[-117.84479899999999,33.73198],"type":"Point"}
}