{
  "type": "Feature",
  "properties": {
    "addr:full":"41876 Los Gatos Rd Coalinga CA 93210",
    "addr:housenumber":"41876",
    "addr:postcode":"93210",
    "addr:street":"Los Gatos Rd",
    "iso:country":"US",
    "sg:address":"41876 Los Gatos Rd",
    "sg:city":"Coalinga",
    "sg:classifiers":[
        {
            "category":"Farming",
            "subcategory":"Livestock Farm",
            "type":"Manufacturing & Wholesale Goods"
        }
    ],
    "sg:phone":"+1 559 935 1414",
    "sg:postcode":"93210",
    "sg:province":"CA",
    "sg:tags":[
        "beef",
        "feedlot",
        "cattle"
    ],
    "wof:name":"Birdwell Ranch",
    "wof:placetype":"venue"
},
  "geometry": {"coordinates":[-120.528807,36.2232],"type":"Point"}
}