{
  "type": "Feature",
  "properties": {
    "addr:full":"555 S Shaffer St Orange CA 92866",
    "addr:housenumber":"555",
    "addr:postcode":"92866",
    "addr:street":"S Shaffer St",
    "iso:country":"US",
    "sg:address":"555 S Shaffer St",
    "sg:city":"Orange",
    "sg:classifiers":[
        {
            "category":"Manufacturing",
            "subcategory":"Tools & Machinery",
            "type":"Manufacturing & Wholesale Goods"
        }
    ],
    "sg:phone":"+1 714 532 3394",
    "sg:postcode":"92866",
    "sg:province":"CA",
    "sg:tags":[
        "equipment",
        "mfg"
    ],
    "wof:name":"Global Space Aeronautical Mari",
    "wof:placetype":"venue"
},
  "geometry": {"coordinates":[-117.848682,33.77989],"type":"Point"}
}