{
  "type": "Feature",
  "properties": {
    "iso:country":"US",
    "sg:address":"3934 Coronado Ave",
    "sg:city":"Stockton",
    "sg:classifiers":[
        {
            "category":"Building & Trades",
            "subcategory":"Electrical",
            "type":"Services"
        }
    ],
    "sg:phone":"+1 209 474 0533",
    "sg:postcode":"95204",
    "sg:province":"CA",
    "sg:tags":[
        "electric",
        "contractor"
    ],
    "sg:website":"www.staggelectric.com",
    "wof:name":"Stagg Electrical Svc",
    "wof:placetype":"venue"
},
  "geometry": {"coordinates":[-121.288093,37.98762],"type":"Point"}
}