{
  "type": "Feature",
  "properties": {
    "iso:country":"US",
    "sg:address":"16930 Charles Way",
    "sg:city":"Grass Valley",
    "sg:classifiers":[
        {
            "category":"Shopping",
            "subcategory":"Hobbies, Toys, & Games",
            "type":"Retail Goods"
        }
    ],
    "sg:phone":"+1 530 274 8811",
    "sg:postcode":"95949",
    "sg:province":"CA",
    "wof:name":"Tally Ho Tallies",
    "wof:placetype":"venue"
},
  "geometry": {"coordinates":[-121.06039699999999,39.12856],"type":"Point"}
}