{
  "type": "Feature",
  "properties": {
    "addr:full":"2 Embarcadero Center San Francisco CA 94111",
    "addr:housenumber":"2",
    "addr:postcode":"94111",
    "addr:street":"Embarcadero Center",
    "iso:country":"US",
    "sg:address":"2 Embarcadero Center",
    "sg:city":"San Francisco",
    "sg:classifiers":[
        {
            "category":"Juice Bar",
            "subcategory":"None",
            "type":"Food & Drink"
        }
    ],
    "sg:postcode":"94111",
    "sg:province":"CA",
    "sg:tags":[
        "smoothy"
    ],
    "sg:website":"www.bluehawaiilifestyle.com",
    "wof:name":"Blue Hawaii LifeStyle",
    "wof:placetype":"venue"
},
  "geometry": {"coordinates":[-122.398625,37.79495],"type":"Point"}
}