{
  "type": "Feature",
  "properties": {
    "iso:country":"US",
    "sg:address":"19553 E Trimmer Springs Rd",
    "sg:city":"Sanger",
    "sg:classifiers":[
        {
            "category":"Government",
            "subcategory":"Office",
            "type":"Public Place"
        }
    ],
    "sg:phone":"+1 559 787 2168",
    "sg:postcode":"93657",
    "sg:province":"CA",
    "sg:tags":[
        "government-united",
        "state"
    ],
    "wof:name":"Us Interior Dept",
    "wof:placetype":"venue"
},
  "geometry": {"coordinates":[-119.44518100000001,36.765722],"type":"Point"}
}