{
  "type": "Feature",
  "properties": {
    "iso:country":"US",
    "sg:address":"10920 Venice Blvd",
    "sg:city":"Culver City",
    "sg:classifiers":[
        {
            "category":"Health Services",
            "subcategory":"Doctor",
            "type":"Services"
        }
    ],
    "sg:phone":"+1 310 204 6661",
    "sg:postcode":"90232",
    "sg:province":"CA",
    "sg:tags":[
        "dentist"
    ],
    "wof:name":"Smile Dental",
    "wof:placetype":"venue"
},
  "geometry": {"coordinates":[-118.41264099999999,34.015455],"type":"Point"}
}