{
  "type": "Feature",
  "properties": {
    "addr:full":"312 Oak St Brentwood CA 94513",
    "addr:housenumber":"312",
    "addr:postcode":"ca 94513",
    "addr:street":"Oak St",
    "iso:country":"US",
    "sg:address":"312 Oak St",
    "sg:city":"Brentwood",
    "sg:classifiers":[
        {
            "category":"Shopping",
            "subcategory":"Party Supplies",
            "type":"Retail Goods"
        }
    ],
    "sg:phone":"+1 925 513 4700",
    "sg:postcode":"94513",
    "sg:province":"CA",
    "sg:website":"www.littlemisseverything.com",
    "wof:name":"Little Miss Everything",
    "wof:placetype":"venue"
},
  "geometry": {"coordinates":[-121.695049,37.932298],"type":"Point"}
}