{
  "type": "Feature",
  "properties": {
    "iso:country":"US",
    "sg:address":"210 Wells Ave",
    "sg:city":"El Cajon",
    "sg:classifiers":[
        {
            "category":"Real Estate",
            "subcategory":"Real Estate Operator",
            "type":"Services"
        }
    ],
    "sg:phone":"+1 619 593 0211",
    "sg:postcode":"92020",
    "sg:province":"CA",
    "sg:tags":[
        "apartment"
    ],
    "wof:name":"The Wells Apartments",
    "wof:placetype":"venue"
},
  "geometry": {"coordinates":[-116.960211,32.799249],"type":"Point"}
}