{
  "type": "Feature",
  "properties": {
    "iso:country":"US",
    "sg:address":"615 Brookside Ave",
    "sg:city":"Redlands",
    "sg:classifiers":[
        {
            "category":"Professional",
            "subcategory":"Lawyer & Legal Services",
            "type":"Services"
        }
    ],
    "sg:phone":"+1 909 888 4159",
    "sg:postcode":"92373",
    "sg:province":"CA",
    "sg:tags":[
        "attorney"
    ],
    "wof:name":"E Toby Bowler",
    "wof:placetype":"venue"
},
  "geometry": {"coordinates":[-117.190682,34.052549],"type":"Point"}
}