{
  "type": "Feature",
  "properties": {
    "addr:full":"315 Grand Ave Pacific Grove CA 93950",
    "addr:housenumber":"315",
    "addr:postcode":"93950",
    "addr:street":"Grand Ave",
    "iso:country":"US",
    "sg:address":"315 Grand Ave",
    "sg:city":"Pacific Grove",
    "sg:classifiers":[
        {
            "category":"Real Estate",
            "subcategory":"Architect",
            "type":"Services"
        }
    ],
    "sg:phone":"+1 831 372 5150",
    "sg:postcode":"93950",
    "sg:province":"CA",
    "wof:name":"William E Bredthauer",
    "wof:placetype":"venue"
},
  "geometry": {"coordinates":[-121.918059,36.61877],"type":"Point"}
}