{
  "type": "Feature",
  "properties": {
    "iso:country":"US",
    "sg:address":"5037 Collina Pl",
    "sg:city":"Sacramento",
    "sg:classifiers":[
        {
            "category":"Building & Trades",
            "subcategory":"Cleaning & Sanitation",
            "type":"Services"
        }
    ],
    "sg:phone":"+1 916 541 6372",
    "sg:postcode":"95841",
    "sg:province":"CA",
    "sg:tags":[
        "janitor"
    ],
    "wof:name":"Lilys Cleaning",
    "wof:placetype":"venue"
},
  "geometry": {"coordinates":[-121.346759,38.656682],"type":"Point"}
}