{
  "type": "Feature",
  "properties": {
    "iso:country":"US",
    "sg:address":"12056 Valley Blvd",
    "sg:city":"El Monte",
    "sg:classifiers":[
        {
            "category":"Food & Beverages",
            "subcategory":"Specialty",
            "type":"Retail Goods"
        }
    ],
    "sg:phone":"+1 626 443 1940",
    "sg:postcode":"91732",
    "sg:province":"CA",
    "sg:tags":[
        "american",
        "latin",
        "mexican",
        "product"
    ],
    "wof:name":"Birrieria Y Taqueria Gdljr",
    "wof:placetype":"venue"
},
  "geometry": {"coordinates":[-118.016785,34.061446],"type":"Point"}
}