{
  "type": "Feature",
  "properties": {
    "addr:full":"243 Glen Park Ave San Rafael CA 94901",
    "addr:housenumber":"243",
    "addr:postcode":"94901",
    "addr:street":"Glen Park Ave",
    "iso:country":"US",
    "sg:address":"243 Glen Park Ave",
    "sg:city":"San Rafael",
    "sg:classifiers":[
        {
            "category":"Manufacturing",
            "subcategory":"Metals",
            "type":"Manufacturing & Wholesale Goods"
        }
    ],
    "sg:phone":"+1 415 459 3490",
    "sg:postcode":"94901",
    "sg:province":"CA",
    "wof:name":"Cactus Metal Design",
    "wof:placetype":"venue"
},
  "geometry": {"coordinates":[-122.524156,37.987131],"type":"Point"}
}