{
  "type": "Feature",
  "properties": {
    "iso:country":"US",
    "sg:address":"7675 Winnetka Ave",
    "sg:city":"Canoga Park",
    "sg:classifiers":[
        {
            "category":"Professional",
            "subcategory":"Business Services",
            "type":"Services"
        }
    ],
    "sg:phone":"+1 818 700 0842",
    "sg:postcode":"91306",
    "sg:province":"CA",
    "sg:tags":[
        "consultant",
        "production",
        "music"
    ],
    "wof:name":"Bankbeat Productions",
    "wof:placetype":"venue"
},
  "geometry": {"coordinates":[-118.571085,34.208633],"type":"Point"}
}