{
  "type": "Feature",
  "properties": {
    "iso:country":"US",
    "sg:address":"5125 Crenshaw Blvd",
    "sg:city":"Los Angeles",
    "sg:classifiers":[
        {
            "category":"Organizations",
            "subcategory":"Religious Organization",
            "type":"Services"
        }
    ],
    "sg:phone":"+1 323 293 6127",
    "sg:postcode":"90043",
    "sg:province":"CA",
    "sg:tags":[
        "church"
    ],
    "wof:name":"United World Church Of God",
    "wof:placetype":"venue"
},
  "geometry": {"coordinates":[-118.33076,33.99612],"type":"Point"}
}