{
  "type": "Feature",
  "properties": {
    "iso:country":"US",
    "sg:address":"715 E Brier Dr",
    "sg:city":"San Bernardino",
    "sg:classifiers":[
        {
            "category":"Government",
            "subcategory":"Office",
            "type":"Public Place"
        }
    ],
    "sg:phone":"+1 909 890 0644",
    "sg:postcode":"92408",
    "sg:province":"CA",
    "sg:tags":[
        "housing",
        "authority"
    ],
    "wof:name":"Housing Auth Cnty/Sn Brnardno",
    "wof:placetype":"venue"
},
  "geometry": {"coordinates":[-117.26977599999999,34.071287],"type":"Point"}
}