{
  "type": "Feature",
  "properties": {
    "addr:full":"21154 Altena Dr Santa Clarita CA 91350",
    "addr:postcode":"21154;91350",
    "addr:street":"Altena Dr",
    "iso:country":"US",
    "sg:address":"21154 Altena Dr",
    "sg:city":"Santa Clarita",
    "sg:classifiers":[
        {
            "category":"Personal",
            "type":"Services"
        }
    ],
    "sg:phone":"+1 800 766 2275",
    "sg:postcode":"91350",
    "sg:province":"CA",
    "sg:tags":[
        "local"
    ],
    "sg:website":"www.romacengineering.com",
    "wof:name":"Romac Engineering",
    "wof:placetype":"venue"
},
  "geometry": {"coordinates":[-118.505869,34.451479],"type":"Point"}
}