{
  "type": "Feature",
  "properties": {
    "addr:full":"1390 10th Street Berkeley CA 94710",
    "addr:housenumber":"1390",
    "addr:postcode":"94710",
    "addr:street":"10Th Street",
    "iso:country":"US",
    "sg:address":"1390 10th Street",
    "sg:city":"Berkeley",
    "sg:classifiers":[
        {
            "category":"Sports & Exercise",
            "subcategory":"Gym",
            "type":"Entertainment"
        }
    ],
    "sg:phone":"+1 415 260 1112",
    "sg:postcode":"94710",
    "sg:province":"CA",
    "sg:tags":[
        "trainer"
    ],
    "sg:website":"www.phoenixfitnessgym.com",
    "wof:name":"Phoenix Gym",
    "wof:placetype":"venue"
},
  "geometry": {"coordinates":[-122.29647,37.878661],"type":"Point"}
}