{
  "type": "Feature",
  "properties": {
    "addr:full":"18921 Canyon Hill Dr Trabuco Canyon CA 92679",
    "addr:housenumber":"18921",
    "addr:postcode":"92679",
    "addr:street":"Canyon Hill Dr",
    "iso:country":"US",
    "sg:address":"18921 Canyon Hill Dr",
    "sg:city":"Trabuco Canyon",
    "sg:classifiers":[
        {
            "category":"Professional",
            "type":"Services"
        }
    ],
    "sg:phone":"+1 949 589 1576",
    "sg:postcode":"92679",
    "sg:province":"CA",
    "wof:name":"Starfire Training",
    "wof:placetype":"venue"
},
  "geometry": {"coordinates":[-117.625333,33.686919],"type":"Point"}
}