{
  "type": "Feature",
  "properties": {
    "iso:country":"US",
    "sg:address":"2127 Harbor Blvd",
    "sg:city":"Costa Mesa",
    "sg:classifiers":[
        {
            "category":"Travel",
            "subcategory":"Travel Agent",
            "type":"Entertainment"
        }
    ],
    "sg:phone":"+1 949 722 2332",
    "sg:postcode":"92627",
    "sg:province":"CA",
    "sg:tags":[
        "agency"
    ],
    "wof:name":"Del Mar Travel",
    "wof:placetype":"venue"
},
  "geometry": {"coordinates":[-117.91914,33.651522],"type":"Point"}
}