{
  "type": "Feature",
  "properties": {
    "iso:country":"US",
    "sg:address":"1712 Carver Rd",
    "sg:city":"Modesto",
    "sg:classifiers":[
        {
            "category":"Manufacturing",
            "subcategory":"Toys & Sporting Goods",
            "type":"Manufacturing & Wholesale Goods"
        }
    ],
    "sg:phone":"+1 209 521 6074",
    "sg:postcode":"95350",
    "sg:province":"CA",
    "sg:tags":[
        "mfg"
    ],
    "wof:name":"Topsy Turvy Train Town",
    "wof:placetype":"venue"
},
  "geometry": {"coordinates":[-121.022041,37.671005],"type":"Point"}
}