{
  "type": "Feature",
  "properties": {
    "iso:country":"US",
    "sg:address":"1353 Colorado Blvd",
    "sg:city":"Eagle Rock",
    "sg:classifiers":[
        {
            "category":"Autos & Motor Vehicles",
            "subcategory":"Auto Supplies",
            "type":"Retail Goods"
        },
        {
            "category":"Professional",
            "subcategory":"Computer Services",
            "type":"Services"
        }
    ],
    "sg:phone":"+1 323 258 7282",
    "sg:postcode":"90041",
    "sg:province":"CA",
    "sg:tags":[
        "glass",
        "stereo",
        "installation"
    ],
    "sg:website":"www.sightwaves.com",
    "wof:name":"Sightwaves",
    "wof:placetype":"venue"
},
  "geometry": {"coordinates":[-118.194461,34.13951],"type":"Point"}
}