{
  "type": "Feature",
  "properties": {
    "iso:country":"US",
    "sg:address":"14855 Chispa Rd",
    "sg:city":"Atascadero",
    "sg:classifiers":[
        {
            "category":"Building & Trades",
            "subcategory":"Construction",
            "type":"Services"
        }
    ],
    "sg:phone":"+1 805 461 3478",
    "sg:postcode":"93422",
    "sg:province":"CA",
    "wof:name":"Voss Construction",
    "wof:placetype":"venue"
},
  "geometry": {"coordinates":[-120.602182,35.432486],"type":"Point"}
}