{
  "type": "Feature",
  "properties": {
    "iso:country":"US",
    "sg:address":"2522 Artesia Boulevard",
    "sg:city":"Redondo Beach",
    "sg:classifiers":[
        {
            "category":"Professional",
            "subcategory":"Lawyer & Legal Services",
            "type":"Services"
        }
    ],
    "sg:phone":"+1 310 372 1988",
    "sg:postcode":"90278",
    "sg:province":"CA",
    "sg:tags":[
        "personal",
        "injury"
    ],
    "wof:name":"Regan & Braun",
    "wof:placetype":"venue"
},
  "geometry": {"coordinates":[-118.365988,33.872797],"type":"Point"}
}