{
  "type": "Feature",
  "properties": {
    "addr:full":"3603 Jamison Way Castro Valley CA 94546",
    "addr:housenumber":"3603",
    "addr:postcode":"94546",
    "addr:street":"Jamison Way",
    "iso:country":"US",
    "sg:address":"3603 Jamison Way",
    "sg:city":"Castro Valley",
    "sg:classifiers":[
        {
            "category":"Health Services",
            "subcategory":"Dentist",
            "type":"Services"
        }
    ],
    "sg:phone":"+1 510 881 1924",
    "sg:postcode":"94546",
    "sg:province":"CA",
    "sg:website":"www.createasmile.com",
    "wof:name":"Joseph Whitehouse, MS, DDS",
    "wof:placetype":"venue"
},
  "geometry": {"coordinates":[-122.075095,37.697745],"type":"Point"}
}