{
  "type": "Feature",
  "properties": {
    "addr:full":"606 S Hill Street Suite 1007 Los Angeles CA 90014",
    "addr:housenumber":"606",
    "addr:postcode":"90014",
    "addr:street":"S Hill Street Suite 1007",
    "iso:country":"US",
    "sg:address":"606 S Hill Street Suite 1007",
    "sg:city":"Los Angeles",
    "sg:classifiers":[
        {
            "category":"Shopping",
            "subcategory":"Jewelry",
            "type":"Retail Goods"
        }
    ],
    "sg:phone":"+1 213 623 3987",
    "sg:postcode":"90014",
    "sg:province":"CA",
    "wof:name":"Orna Gems",
    "wof:placetype":"venue"
},
  "geometry": {"coordinates":[-118.252048,34.044805],"type":"Point"}
}