{
  "type": "Feature",
  "properties": {
    "iso:country":"US",
    "sg:address":"39 N Arroyo Pkwy",
    "sg:city":"Pasadena",
    "sg:classifiers":[
        {
            "category":"Wholesale",
            "subcategory":"Groceries",
            "type":"Manufacturing & Wholesale Goods"
        }
    ],
    "sg:phone":"+1 626 577 4480",
    "sg:postcode":"91103",
    "sg:province":"CA",
    "sg:tags":[
        "smoothie",
        "juice",
        "bar"
    ],
    "wof:name":"Mj Organic World",
    "wof:placetype":"venue"
},
  "geometry": {"coordinates":[-118.148003,34.145901],"type":"Point"}
}