{
  "type": "Feature",
  "properties": {
    "iso:country":"US",
    "sg:address":"31 W Market St",
    "sg:city":"Salinas",
    "sg:classifiers":[
        {
            "category":"Shopping",
            "subcategory":"Computers & Home Electronics",
            "type":"Retail Goods"
        }
    ],
    "sg:phone":"+1 831 753 1309",
    "sg:postcode":"93901",
    "sg:province":"CA",
    "sg:tags":[
        "equipment",
        "electronic",
        "supply"
    ],
    "wof:name":"Cimino Electronics",
    "wof:placetype":"venue"
},
  "geometry": {"coordinates":[-121.65637,36.677575],"type":"Point"}
}