{
  "type": "Feature",
  "properties": {
    "addr:full":"1122 7th St Sacramento CA 95814",
    "addr:housenumber":"1122",
    "addr:postcode":"95814",
    "addr:street":"7Th St",
    "iso:country":"US",
    "sg:address":"1122 7th St",
    "sg:city":"Sacramento",
    "sg:classifiers":[
        {
            "category":"Education",
            "subcategory":"School",
            "type":"Public Place"
        }
    ],
    "sg:phone":"+1 916 929 8306",
    "sg:postcode":"95814",
    "sg:province":"CA",
    "wof:name":"Breckinridge Military Academy",
    "wof:placetype":"venue"
},
  "geometry": {"coordinates":[-121.498153,38.579998],"type":"Point"}
}