{
  "type": "Feature",
  "properties": {
    "iso:country":"US",
    "sg:address":"718 W Compton Blvd",
    "sg:city":"Compton",
    "sg:classifiers":[
        {
            "category":"Education",
            "subcategory":"Vocational School",
            "type":"Public Place"
        }
    ],
    "sg:phone":"+1 310 635 6969",
    "sg:postcode":"90220",
    "sg:province":"CA",
    "sg:tags":[
        "cosmetology"
    ],
    "sg:website":"www.universal-collegeofbeauty.com",
    "wof:name":"Universal College of Beauty Inc",
    "wof:placetype":"venue"
},
  "geometry": {"coordinates":[-118.236,33.896],"type":"Point"}
}