{
  "type": "Feature",
  "properties": {
    "addr:full":"140 Stony Point Rd Santa Rosa CA 95407",
    "addr:housenumber":"140",
    "addr:postcode":"95407",
    "addr:street":"Stony Point Rd",
    "iso:country":"US",
    "sg:address":"140 Stony Point Rd",
    "sg:city":"Santa Rosa",
    "sg:classifiers":[
        {
            "category":"Health Services",
            "subcategory":"Doctor",
            "type":"Services"
        }
    ],
    "sg:phone":"+1 707 578 5521",
    "sg:postcode":"95407",
    "sg:province":"CA",
    "sg:tags":[
        "dentist"
    ],
    "wof:name":"Eric Fraser Ddsd",
    "wof:placetype":"venue"
},
  "geometry": {"coordinates":[-122.742977,38.438423],"type":"Point"}
}