{
  "type": "Feature",
  "properties": {
    "iso:country":"US",
    "sg:address":"3734 Overland Avenue",
    "sg:city":"Los Angeles",
    "sg:classifiers":[
        {
            "category":"Social Services",
            "subcategory":"Child Care",
            "type":"Services"
        },
        {
            "category":"Education",
            "subcategory":"Preschool",
            "type":"Public Place"
        },
        {
            "category":"Education",
            "subcategory":"School",
            "type":"Public Place"
        }
    ],
    "sg:phone":"+1 310 202 1566",
    "sg:postcode":"90034",
    "sg:province":"CA",
    "sg:tags":[
        "elementary",
        "day"
    ],
    "wof:name":"California Wiz Kids",
    "wof:placetype":"venue"
},
  "geometry": {"coordinates":[-118.408171,34.020037],"type":"Point"}
}