{
  "type": "Feature",
  "properties": {
    "iso:country":"US",
    "sg:address":"17400 Irvine Blvd",
    "sg:city":"Tustin",
    "sg:classifiers":[
        {
            "category":"Health Services",
            "subcategory":"Doctor",
            "type":"Services"
        },
        {
            "category":"Health Services",
            "subcategory":"Clinic",
            "type":"Services"
        },
        {
            "category":"Health Services",
            "subcategory":"Chiropractor",
            "type":"Services"
        }
    ],
    "sg:phone":"+1 714 508 1112",
    "sg:postcode":"92780",
    "sg:province":"CA",
    "sg:tags":[
        "medical",
        "chiropractic"
    ],
    "wof:name":"Klemer Chiropratic",
    "wof:placetype":"venue"
},
  "geometry": {"coordinates":[-117.829228,33.748012],"type":"Point"}
}