{
  "type": "Feature",
  "properties": {
    "iso:country":"US",
    "sg:address":"150 London Ct",
    "sg:city":"San Bruno",
    "sg:classifiers":[
        {
            "category":"Building & Trades",
            "subcategory":"Construction",
            "type":"Services"
        }
    ],
    "sg:phone":"+1 650 873 7272",
    "sg:postcode":"94066",
    "sg:province":"CA",
    "sg:tags":[
        "house",
        "contractor"
    ],
    "wof:name":"A-1 Fence",
    "wof:placetype":"venue"
},
  "geometry": {"coordinates":[-122.43017999999999,37.60839],"type":"Point"}
}