{
  "type": "Feature",
  "properties": {
    "iso:country":"US",
    "sg:address":"6841 Marysville Rd",
    "sg:city":"Browns Valley",
    "sg:classifiers":[
        {
            "category":"Freight",
            "type":"Transportation"
        }
    ],
    "sg:phone":"+1 530 743 8724",
    "sg:postcode":"95918",
    "sg:province":"CA",
    "sg:tags":[
        "general"
    ],
    "wof:name":"Country Storage",
    "wof:placetype":"venue"
},
  "geometry": {"coordinates":[-121.368145,39.314564],"type":"Point"}
}