{
  "type": "Feature",
  "properties": {
    "addr:full":"6625 Variel Ave Canoga Park CA 91303",
    "addr:postcode":"6625;91303",
    "addr:street":"Variel Ave",
    "iso:country":"US",
    "sg:address":"6625 Variel Ave",
    "sg:city":"Canoga Park",
    "sg:classifiers":[
        {
            "category":"Professional",
            "type":"Services"
        }
    ],
    "sg:phone":"+1 818 673 1243",
    "sg:postcode":"91303",
    "sg:province":"CA",
    "sg:tags":[
        "establishment"
    ],
    "wof:name":"Artistic Stock Footage",
    "wof:placetype":"venue"
},
  "geometry": {"coordinates":[-118.59287500000001,34.189287],"type":"Point"}
}