{
  "type": "Feature",
  "properties": {
    "iso:country":"US",
    "sg:address":"9537 Cozycroft Ave",
    "sg:city":"Chatsworth",
    "sg:classifiers":[
        {
            "category":"Shopping",
            "subcategory":"Computers & Home Electronics",
            "type":"Retail Goods"
        }
    ],
    "sg:phone":"+1 818 886 5874",
    "sg:postcode":"91311",
    "sg:province":"CA",
    "sg:tags":[
        "equipment",
        "video"
    ],
    "wof:name":"Angel Home Video",
    "wof:placetype":"venue"
},
  "geometry": {"coordinates":[-118.58205599999999,34.245696],"type":"Point"}
}