{
  "type": "Feature",
  "properties": {
    "iso:country":"US",
    "sg:address":"1310 Santa Rita E Ste 12",
    "sg:city":"Chula Vista",
    "sg:classifiers":[
        {
            "category":"Communications",
            "type":"Services"
        },
        {
            "category":"Professional",
            "subcategory":"Computer Services",
            "type":"Services"
        }
    ],
    "sg:phone":"+1 619 851 8999",
    "sg:postcode":"91913",
    "sg:province":"CA",
    "sg:tags":[
        "repair",
        "design",
        "web"
    ],
    "wof:name":"Cortney's Web Development & Computer Repair",
    "wof:placetype":"venue"
},
  "geometry": {"coordinates":[-116.999402,32.622115],"type":"Point"}
}