{
  "type": "Feature",
  "properties": {
    "iso:country":"US",
    "sg:address":"6216 Hwy 9",
    "sg:city":"Felton",
    "sg:classifiers":[
        {
            "category":"Health Services",
            "subcategory":"Health Practitioner",
            "type":"Services"
        }
    ],
    "sg:phone":"+1 831 335 8206",
    "sg:postcode":"95018",
    "sg:province":"CA",
    "sg:tags":[
        "psychologist"
    ],
    "wof:name":"Michelle Franklin PHD",
    "wof:placetype":"venue"
},
  "geometry": {"coordinates":[-122.073167,37.051432],"type":"Point"}
}