{
  "type": "Feature",
  "properties": {
    "iso:country":"US",
    "sg:address":"11988 CA-88",
    "sg:city":"Jackson",
    "sg:classifiers":[
        {
            "category":"Restaurant",
            "type":"Food & Drink"
        }
    ],
    "sg:menulink":"http://www.allmenus.com/ca/ione/29550-perkos/menu/",
    "sg:phone":"+1 209 223 4420",
    "sg:postcode":"95642",
    "sg:province":"CA",
    "sg:tags":[
        "american"
    ],
    "wof:name":"Perko's",
    "wof:placetype":"venue"
},
  "geometry": {"coordinates":[-120.800162,38.364434],"type":"Point"}
}