{
  "type": "Feature",
  "properties": {
    "addr:full":"1210 Oakland Ave Oakland CA 94611",
    "addr:housenumber":"1210",
    "addr:postcode":"94611",
    "addr:street":"Oakland Ave",
    "iso:country":"US",
    "sg:address":"1210 Oakland Ave",
    "sg:city":"Oakland",
    "sg:classifiers":[
        {
            "category":"Manufacturing",
            "subcategory":"Signs",
            "type":"Manufacturing & Wholesale Goods"
        }
    ],
    "sg:phone":"+1 201 854 8888",
    "sg:postcode":"94611",
    "sg:province":"CA",
    "wof:name":"Ed Smith's Original Quicky Sgn",
    "wof:placetype":"venue"
},
  "geometry": {"coordinates":[-122.240256,37.823664],"type":"Point"}
}