{
  "type": "Feature",
  "properties": {
    "addr:full":"6966 Airport Blvd 2 Sacramento CA 95837",
    "addr:housenumber":"6966;2",
    "addr:postcode":"95837",
    "addr:street":"Airport Blvd",
    "iso:country":"US",
    "sg:address":"6966 Airport Blvd 2",
    "sg:city":"Sacramento",
    "sg:classifiers":[
        {
            "category":"Airline",
            "type":"Transportation"
        }
    ],
    "sg:phone":"+1 916 925 4026",
    "sg:postcode":"95837",
    "sg:province":"CA",
    "wof:name":"Horizon Air Industries, Inc.",
    "wof:placetype":"venue"
},
  "geometry": {"coordinates":[-121.59326,38.692573],"type":"Point"}
}