{
  "type": "Feature",
  "properties": {
    "iso:country":"US",
    "sg:address":"2001 Vine St",
    "sg:city":"Berkeley",
    "sg:classifiers":[
        {
            "category":"Professional",
            "subcategory":"Detective & Security Services",
            "type":"Services"
        }
    ],
    "sg:phone":"+1 415 632 9184",
    "sg:postcode":"94709",
    "sg:province":"CA",
    "sg:tags":[
        "information",
        "bureau"
    ],
    "wof:name":"Maat Regulatory Compliance Consulting",
    "wof:placetype":"venue"
},
  "geometry": {"coordinates":[-122.271591,37.879929],"type":"Point"}
}