{
  "type": "Feature",
  "properties": {
    "iso:country":"US",
    "sg:address":"123 Madden St",
    "sg:city":"Willits",
    "sg:classifiers":[
        {
            "category":"Building & Trades",
            "subcategory":"Construction",
            "type":"Services"
        },
        {
            "category":"Home & Garden",
            "subcategory":"Building Materials",
            "type":"Retail Goods"
        },
        {
            "category":"Recreation",
            "type":"Entertainment"
        },
        {
            "category":"Personal",
            "type":"Services"
        },
        {
            "category":"Building & Trades",
            "subcategory":"Cleaning & Sanitation",
            "type":"Services"
        },
        {
            "category":"Bars & Pubs",
            "subcategory":"Champagne Bar",
            "type":"Food & Drink"
        }
    ],
    "sg:phone":"+1 866 909 4915",
    "sg:postcode":"95490",
    "sg:province":"CA",
    "sg:tags":[
        "repair",
        "gutter",
        "burglar",
        "power",
        "deck",
        "assistant",
        "handyman",
        "contractor",
        "decoration",
        "shutter",
        "treatment",
        "maintenance",
        "light",
        "downspouts",
        "washing",
        "fence-sales",
        "drywall",
        "christmas",
        "plastering"
    ],
    "wof:name":"Fix it Dads",
    "wof:placetype":"venue"
},
  "geometry": {"coordinates":[-123.35134499999999,39.411171],"type":"Point"}
}