{
  "type": "Feature",
  "properties": {
    "addr:full":"1644 20th St Santa Monica CA 90404",
    "addr:housenumber":"1644",
    "addr:postcode":"90404",
    "addr:street":"20Th St",
    "iso:country":"US",
    "sg:address":"1644 20th St",
    "sg:city":"Santa Monica",
    "sg:classifiers":[
        {
            "category":"Wholesale",
            "subcategory":"Jewelry",
            "type":"Manufacturing & Wholesale Goods"
        }
    ],
    "sg:phone":"+1 310 828 4465",
    "sg:postcode":"90404",
    "sg:province":"CA",
    "sg:tags":[
        "jeweler",
        "supply"
    ],
    "wof:name":"Bhalla & Assoc",
    "wof:placetype":"venue"
},
  "geometry": {"coordinates":[-118.47524300000001,34.02457],"type":"Point"}
}