{
  "type": "Feature",
  "properties": {
    "addr:full":"1209 S Montebello Blvd Montebello CA 90640",
    "addr:housenumber":"1209",
    "addr:postcode":"90640",
    "addr:street":"S Montebello Blvd",
    "iso:country":"US",
    "sg:address":"1209 S Montebello Blvd",
    "sg:city":"Montebello",
    "sg:classifiers":[
        {
            "category":"Building & Trades",
            "subcategory":"Electrical",
            "type":"Services"
        }
    ],
    "sg:phone":"+1 323 888 8812",
    "sg:postcode":"90640",
    "sg:province":"CA",
    "sg:tags":[
        "telecommunication",
        "contractor"
    ],
    "wof:name":"Network Cabling Solutions",
    "wof:placetype":"venue"
},
  "geometry": {"coordinates":[-118.119849,33.987898],"type":"Point"}
}