{
  "type": "Feature",
  "properties": {
    "iso:country":"US",
    "sg:address":"553 Sandy Way",
    "sg:city":"Benicia",
    "sg:classifiers":[
        {
            "category":"Professional",
            "subcategory":"Business Services",
            "type":"Services"
        }
    ],
    "sg:phone":"+1 707 315 6267",
    "sg:postcode":"94510",
    "sg:province":"CA",
    "sg:tags":[
        "environmental",
        "ecological",
        "product"
    ],
    "wof:name":"Arens Environmental Services, Inc.",
    "wof:placetype":"venue"
},
  "geometry": {"coordinates":[-122.1628,38.062017],"type":"Point"}
}