{
  "type": "Feature",
  "properties": {
    "iso:country":"US",
    "sg:address":"2106 Pontius Ave",
    "sg:city":"Los Angeles",
    "sg:classifiers":[
        {
            "category":"Shopping",
            "subcategory":"Computers & Home Electronics",
            "type":"Retail Goods"
        }
    ],
    "sg:phone":"+1 310 479 1879",
    "sg:postcode":"90025",
    "sg:province":"CA",
    "sg:tags":[
        "equipment",
        "electronic",
        "supply"
    ],
    "wof:name":"Circuit City",
    "wof:placetype":"venue"
},
  "geometry": {"coordinates":[-118.438492,34.039968],"type":"Point"}
}