{
  "type": "Feature",
  "properties": {
    "addr:full":"871 Jessie St Monterey CA 93940",
    "addr:housenumber":"871",
    "addr:postcode":"93940",
    "addr:street":"Jessie St",
    "iso:country":"US",
    "sg:address":"871 Jessie St",
    "sg:city":"Monterey",
    "sg:classifiers":[
        {
            "category":"Social Services",
            "type":"Services"
        }
    ],
    "sg:phone":"+1 831 643 0278",
    "sg:postcode":"93940",
    "sg:province":"CA",
    "sg:tags":[
        "care",
        "center",
        "day"
    ],
    "wof:name":"VNA Adult Day Program Ctr",
    "wof:placetype":"venue"
},
  "geometry": {"coordinates":[-121.919871,36.6089],"type":"Point"}
}