{
  "type": "Feature",
  "properties": {
    "iso:country":"US",
    "sg:address":"745 Christine Ave",
    "sg:city":"Redding",
    "sg:classifiers":[
        {
            "category":"Professional",
            "subcategory":"Computer Services",
            "type":"Services"
        }
    ],
    "sg:phone":"+1 530 241 5704",
    "sg:postcode":"96003",
    "sg:province":"CA",
    "sg:tags":[
        "consultant",
        "designer"
    ],
    "wof:name":"Computer Smith",
    "wof:placetype":"venue"
},
  "geometry": {"coordinates":[-122.39148900000001,40.598449],"type":"Point"}
}