{
  "type": "Feature",
  "properties": {
    "addr:full":"11338 S Harlan Rd Lathrop CA 95330",
    "addr:housenumber":"11338",
    "addr:postcode":"95330",
    "addr:street":"S Harlan Rd",
    "iso:country":"US",
    "sg:address":"11338 S Harlan Rd",
    "sg:city":"Lathrop",
    "sg:classifiers":[
        {
            "category":"Manufacturing",
            "subcategory":"Buildings",
            "type":"Manufacturing & Wholesale Goods"
        },
        {
            "category":"Building & Trades",
            "subcategory":"Construction",
            "type":"Services"
        }
    ],
    "sg:phone":"+1 209 234 2450",
    "sg:postcode":"95330",
    "sg:province":"CA",
    "sg:tags":[
        "home",
        "builder",
        "contractor"
    ],
    "wof:name":"K E Curtis Construction Company Inc",
    "wof:placetype":"venue"
},
  "geometry": {"coordinates":[-121.280548,37.854941],"type":"Point"}
}