{
  "type": "Feature",
  "properties": {
    "addr:full":"747 E Monte Vista Ave Vacaville CA 95688",
    "addr:housenumber":"747",
    "addr:postcode":"95688",
    "addr:street":"E Monte Vista Ave",
    "iso:country":"US",
    "sg:address":"747 E Monte Vista Ave",
    "sg:city":"Vacaville",
    "sg:classifiers":[
        {
            "category":"Banks & Credit Unions",
            "subcategory":"Bank",
            "type":"Services"
        }
    ],
    "sg:phone":"+1 707 451 9360",
    "sg:postcode":"95688",
    "sg:province":"CA",
    "sg:tags":[
        "cashing",
        "check"
    ],
    "wof:name":"Cash & Go",
    "wof:placetype":"venue"
},
  "geometry": {"coordinates":[-121.984264,38.359008],"type":"Point"}
}