{
  "type": "Feature",
  "properties": {
    "iso:country":"US",
    "sg:address":"200 Newport Center Drive",
    "sg:city":"Newport Beach",
    "sg:classifiers":[
        {
            "category":"Health Services",
            "subcategory":"Doctor",
            "type":"Services"
        }
    ],
    "sg:phone":"+1 949 720 0167",
    "sg:postcode":"92660",
    "sg:province":"CA",
    "sg:website":"www.drrecor.com",
    "wof:name":"Richard D Recor PHD",
    "wof:placetype":"venue"
},
  "geometry": {"coordinates":[-117.87508200000001,33.612562],"type":"Point"}
}