{
  "type": "Feature",
  "properties": {
    "iso:country":"US",
    "sg:address":"936 Broadway",
    "sg:city":"El Cajon",
    "sg:classifiers":[
        {
            "category":"Restaurant",
            "type":"Food & Drink"
        }
    ],
    "sg:menulink":"http://www.allmenus.com/ca/san-diego/73985-dominos-pizza/menu/",
    "sg:phone":"+1 619 442 9245",
    "sg:postcode":"92021",
    "sg:province":"CA",
    "sg:tags":[
        "american",
        "wing",
        "pizza"
    ],
    "wof:name":"Domino's Pizza",
    "wof:placetype":"venue"
},
  "geometry": {"coordinates":[-116.94918199999999,32.80773],"type":"Point"}
}