{
  "type": "Feature",
  "properties": {
    "iso:country":"US",
    "sg:address":"5200 Sunrise Blvd",
    "sg:city":"Fair Oaks",
    "sg:classifiers":[
        {
            "category":"Building & Trades",
            "subcategory":"Pest Control",
            "type":"Services"
        }
    ],
    "sg:phone":"+1 916 944 1860",
    "sg:postcode":"95628",
    "sg:province":"CA",
    "wof:name":"Roach Be Gone",
    "wof:placetype":"venue"
},
  "geometry": {"coordinates":[-121.272142,38.663906],"type":"Point"}
}