{
  "type": "Feature",
  "properties": {
    "iso:country":"US",
    "sg:address":"16357 Walnut St",
    "sg:city":"Hesperia",
    "sg:classifiers":[
        {
            "category":"Professional",
            "subcategory":"Lawyer & Legal Services",
            "type":"Services"
        }
    ],
    "sg:phone":"+1 760 244 6287",
    "sg:postcode":"92345",
    "sg:province":"CA",
    "sg:tags":[
        "attorney"
    ],
    "wof:name":"Neil A Harris",
    "wof:placetype":"venue"
},
  "geometry": {"coordinates":[-117.306046,34.42105],"type":"Point"}
}