{
  "type": "Feature",
  "properties": {
    "addr:full":"7000 Hollywood Blvd Los Angeles CA 90028",
    "addr:housenumber":"7000",
    "addr:postcode":"90028",
    "addr:street":"Hollywood Blvd",
    "iso:country":"US",
    "sg:address":"7000 Hollywood Blvd",
    "sg:city":"Los Angeles",
    "sg:classifiers":[
        {
            "category":"Autos & Motor Vehicles",
            "subcategory":"Automobile Sales",
            "type":"Retail Goods"
        }
    ],
    "sg:phone":"+1 818 997 8756",
    "sg:postcode":"90028",
    "sg:province":"CA",
    "sg:tags":[
        "limo"
    ],
    "wof:name":"Apple Limousine Car & Service",
    "wof:placetype":"venue"
},
  "geometry": {"coordinates":[-118.34200300000001,34.1017],"type":"Point"}
}