{
  "type": "Feature",
  "properties": {
    "iso:country":"US",
    "sg:address":"3866 Cardinal Ter",
    "sg:city":"Fremont",
    "sg:classifiers":[
        {
            "category":"Professional",
            "subcategory":"Management & Consulting",
            "type":"Services"
        }
    ],
    "sg:phone":"+1 510 790 1055",
    "sg:postcode":"94555",
    "sg:province":"CA",
    "sg:tags":[
        "consultant"
    ],
    "wof:name":"3 R & M Consulting Svc",
    "wof:placetype":"venue"
},
  "geometry": {"coordinates":[-122.04674300000001,37.5806],"type":"Point"}
}