{
  "type": "Feature",
  "properties": {
    "iso:country":"US",
    "sg:address":"12415 Woodgreen St",
    "sg:city":"Los Angeles",
    "sg:classifiers":[
        {
            "category":"Personal",
            "subcategory":"Beauty Salon",
            "type":"Services"
        }
    ],
    "sg:phone":"+1 310 398 7764",
    "sg:postcode":"90066",
    "sg:province":"CA",
    "sg:tags":[
        "hair"
    ],
    "sg:website":"www.carolquinnsalon.com/",
    "wof:name":"Carol Quinn Salon",
    "wof:placetype":"venue"
},
  "geometry": {"coordinates":[-118.438525,34.009814],"type":"Point"}
}