{
  "type": "Feature",
  "properties": {
    "iso:country":"US",
    "sg:address":"1250 Kifer Rd",
    "sg:city":"Sunnyvale",
    "sg:classifiers":[
        {
            "category":"Wholesale",
            "subcategory":"Metals & Minerals",
            "type":"Manufacturing & Wholesale Goods"
        }
    ],
    "sg:phone":"+1 408 523 7000",
    "sg:postcode":"94086",
    "sg:province":"CA",
    "sg:tags":[
        "die",
        "casting"
    ],
    "wof:name":"Hyatt Die Cast & Engineering",
    "wof:placetype":"venue"
},
  "geometry": {"coordinates":[-121.996503,37.373755],"type":"Point"}
}