{
  "type": "Feature",
  "properties": {
    "addr:full":"701 Pauling Dr Newbury Park CA 91320",
    "addr:housenumber":"701",
    "addr:postcode":"91320",
    "addr:street":"Pauling Dr",
    "iso:country":"US",
    "sg:address":"701 Pauling Dr",
    "sg:city":"Newbury Park",
    "sg:classifiers":[
        {
            "category":"Shopping",
            "subcategory":"Gifts & Souvenirs",
            "type":"Retail Goods"
        }
    ],
    "sg:phone":"+1 805 447 6540",
    "sg:postcode":"91320",
    "sg:province":"CA",
    "sg:tags":[
        "shop"
    ],
    "wof:name":"Amgen Bistro Gift Shop",
    "wof:placetype":"venue"
},
  "geometry": {"coordinates":[-118.921791,34.188221],"type":"Point"}
}