{
  "type": "Feature",
  "properties": {
    "iso:country":"US",
    "sg:address":"2496 E St",
    "sg:city":"San Diego",
    "sg:classifiers":[
        {
            "category":"Professional",
            "type":"Services"
        }
    ],
    "sg:phone":"+1 619 507 5416",
    "sg:postcode":"92102",
    "sg:province":"CA",
    "sg:tags":[
        "establishment"
    ],
    "wof:name":"Jim Ferrara & Co",
    "wof:placetype":"venue"
},
  "geometry": {"coordinates":[-117.14237300000001,32.714823],"type":"Point"}
}