{
  "type": "Feature",
  "properties": {
    "addr:full":"1011 Descanso Dr La Canada Flt CA 91011",
    "addr:housenumber":"1011",
    "addr:postcode":"91011",
    "addr:street":"Descanso Dr La",
    "iso:country":"US",
    "sg:address":"1011 Descanso Dr",
    "sg:city":"La Canada Flt",
    "sg:classifiers":[
        {
            "category":"Building & Trades",
            "subcategory":"Construction",
            "type":"Services"
        }
    ],
    "sg:phone":"+1 213 385 3030",
    "sg:postcode":"91011",
    "sg:province":"CA",
    "sg:tags":[
        "contractor"
    ],
    "wof:name":"V V Construction Co",
    "wof:placetype":"venue"
},
  "geometry": {"coordinates":[-118.20147900000001,34.198407],"type":"Point"}
}