{
  "type": "Feature",
  "properties": {
    "addr:full":"28042 Avenue Stanford Valencia CA 91355",
    "addr:housenumber":"28042",
    "addr:postcode":"91355",
    "addr:street":"Avenue",
    "iso:country":"US",
    "sg:address":"28042 Avenue Stanford",
    "sg:city":"Valencia",
    "sg:classifiers":[
        {
            "category":"Autos & Motor Vehicles",
            "subcategory":"Motorcycle Sales",
            "type":"Retail Goods"
        }
    ],
    "sg:phone":"+1 661 295 1956",
    "sg:postcode":"91355",
    "sg:province":"CA",
    "sg:website":"www.tracdynamics.com",
    "wof:name":"Trac Dynamics",
    "wof:placetype":"venue"
},
  "geometry": {"coordinates":[-118.59899900000001,34.440601],"type":"Point"}
}