{
  "type": "Feature",
  "properties": {
    "iso:country":"US",
    "sg:address":"256 N San Mateo Drive",
    "sg:city":"San Mateo",
    "sg:classifiers":[
        {
            "category":"Health Services",
            "subcategory":"Dentist",
            "type":"Services"
        }
    ],
    "sg:phone":"+1 650 344 7121",
    "sg:postcode":"94401",
    "sg:province":"CA",
    "wof:name":"Fernandez Robert M DDS",
    "wof:placetype":"venue"
},
  "geometry": {"coordinates":[-122.33041799999999,37.570367],"type":"Point"}
}