{
  "type": "Feature",
  "properties": {
    "addr:full":"5704 E Beck Ave Fresno CA 93727",
    "addr:housenumber":"5704",
    "addr:postcode":"93727",
    "addr:street":"E Beck Ave",
    "iso:country":"US",
    "sg:address":"5704 E Beck Ave",
    "sg:city":"Fresno",
    "sg:classifiers":[
        {
            "category":"Real Estate",
            "subcategory":"Real Estate Agent",
            "type":"Services"
        }
    ],
    "sg:phone":"+1 559 252 3333",
    "sg:postcode":"93727",
    "sg:province":"CA",
    "sg:tags":[
        "management"
    ],
    "wof:name":"Kings Garden",
    "wof:placetype":"venue"
},
  "geometry": {"coordinates":[-119.69394800000001,36.739324],"type":"Point"}
}