{
  "type": "Feature",
  "properties": {
    "iso:country":"US",
    "sg:address":"7933 Teesdale Ave",
    "sg:city":"North Hollywood",
    "sg:classifiers":[
        {
            "category":"Freight",
            "type":"Transportation"
        }
    ],
    "sg:phone":"+1 818 503 4622",
    "sg:postcode":"91605",
    "sg:province":"CA",
    "sg:tags":[
        "operator",
        "local",
        "trucking"
    ],
    "wof:name":"J Acosta Trucking",
    "wof:placetype":"venue"
},
  "geometry": {"coordinates":[-118.411601,34.214832],"type":"Point"}
}