{
  "type": "Feature",
  "properties": {
    "addr:full":"1000 Marina Village Pkwy Ste 100 Alameda CA 94501",
    "addr:housenumber":"1000",
    "addr:postcode":"94501",
    "addr:street":"Marina Village Pkwy Ste 100",
    "iso:country":"US",
    "sg:address":"1000 Marina Village Pkwy Ste 100",
    "sg:city":"Alameda",
    "sg:classifiers":[
        {
            "category":"Professional",
            "subcategory":"Management & Consulting",
            "type":"Services"
        },
        {
            "category":"Travel",
            "subcategory":"Hotels & Motels",
            "type":"Entertainment"
        }
    ],
    "sg:phone":"+1 510 832 6868",
    "sg:postcode":"94501",
    "sg:province":"CA",
    "sg:tags":[
        "consultant",
        "lodging"
    ],
    "wof:name":"Pacific Plaza Hotels Inc",
    "wof:placetype":"venue"
},
  "geometry": {"coordinates":[-122.270943,37.783754],"type":"Point"}
}