{
  "type": "Feature",
  "properties": {
    "addr:full":"17692 Cowan Irvine CA 92614",
    "addr:housenumber":"17692",
    "addr:postcode":"92614",
    "addr:street":"Cowan",
    "iso:country":"US",
    "sg:address":"17692 Cowan",
    "sg:city":"Irvine",
    "sg:classifiers":[
        {
            "category":"Social Services",
            "subcategory":"Child Care",
            "type":"Services"
        },
        {
            "category":"Education",
            "subcategory":"Preschool",
            "type":"Public Place"
        },
        {
            "category":"Education",
            "subcategory":"School",
            "type":"Public Place"
        }
    ],
    "sg:phone":"+1 949 476 2445",
    "sg:postcode":"92614",
    "sg:province":"CA",
    "sg:tags":[
        "elementary",
        "day"
    ],
    "wof:name":"Child Development Inc",
    "wof:placetype":"venue"
},
  "geometry": {"coordinates":[-117.85900100000001,33.695301],"type":"Point"}
}