{
  "type": "Feature",
  "properties": {
    "addr:full":"84511 Corte Alturian Coachella CA 92236",
    "addr:housenumber":"84511",
    "addr:postcode":"92236",
    "addr:street":"Corte Alturian",
    "iso:country":"US",
    "sg:address":"84511 Corte Alturian",
    "sg:city":"Coachella",
    "sg:classifiers":[
        {
            "category":"Transit Center",
            "subcategory":"Freight",
            "type":"Transportation"
        },
        {
            "category":"Freight",
            "type":"Transportation"
        }
    ],
    "sg:phone":"+1 760 702 1767",
    "sg:postcode":"92236",
    "sg:province":"CA",
    "sg:tags":[
        "local",
        "trucking-motor",
        "trucking"
    ],
    "wof:name":"Roa Trucking",
    "wof:placetype":"venue"
},
  "geometry": {"coordinates":[-116.18732,33.681485],"type":"Point"}
}