{
  "type": "Feature",
  "properties": {
    "iso:country":"US",
    "sg:address":"1943 Friendship Dr",
    "sg:city":"El Cajon",
    "sg:classifiers":[
        {
            "category":"Wholesale",
            "subcategory":"Office Equipment",
            "type":"Manufacturing & Wholesale Goods"
        }
    ],
    "sg:phone":"+1 619 562 1344",
    "sg:postcode":"92020",
    "sg:province":"CA",
    "sg:tags":[
        "bank",
        "supply"
    ],
    "sg:website":"www.balboacheckpro.com",
    "wof:name":"Balboa Check Protector Co",
    "wof:placetype":"venue"
},
  "geometry": {"coordinates":[-116.978198,32.82287],"type":"Point"}
}