{
  "type": "Feature",
  "properties": {
    "iso:country":"US",
    "sg:address":"2556 Granville Ave",
    "sg:city":"Los Angeles",
    "sg:classifiers":[
        {
            "category":"Professional",
            "subcategory":"Art Services",
            "type":"Services"
        }
    ],
    "sg:phone":"+1 310 445 6550",
    "sg:postcode":"90064",
    "sg:province":"CA",
    "sg:tags":[
        "graphic",
        "designer"
    ],
    "sg:website":"www.blochcoulter.com",
    "wof:name":"Bloch & Coulter Design",
    "wof:placetype":"venue"
},
  "geometry": {"coordinates":[-118.444659,34.027359],"type":"Point"}
}