{
  "type": "Feature",
  "properties": {
    "iso:country":"US",
    "sg:address":"4524 Marine Avenue",
    "sg:city":"Lawndale",
    "sg:classifiers":[
        {
            "category":"Food & Beverages",
            "subcategory":"Groceries & Convenience Stores",
            "type":"Retail Goods"
        }
    ],
    "sg:phone":"+1 310 644 5371",
    "sg:postcode":"90260",
    "sg:province":"CA",
    "wof:name":"Dayro Market",
    "wof:placetype":"venue"
},
  "geometry": {"coordinates":[-118.355587,33.894758],"type":"Point"}
}