{
  "type": "Feature",
  "properties": {
    "addr:full":"1635 Centinela Ave Inglewood CA 90302",
    "addr:housenumber":"1635",
    "addr:postcode":"90302",
    "addr:street":"Centinela Ave",
    "iso:country":"US",
    "sg:address":"1635 Centinela Ave",
    "sg:city":"Inglewood",
    "sg:classifiers":[
        {
            "category":"Taxi",
            "type":"Transportation"
        }
    ],
    "sg:phone":"+1 310 338 5578",
    "sg:postcode":"90302",
    "sg:province":"CA",
    "sg:tags":[
        "taxicab"
    ],
    "wof:name":"Inglewood Shuttle",
    "wof:placetype":"venue"
},
  "geometry": {"coordinates":[-118.36805200000001,33.977044],"type":"Point"}
}