{
  "type": "Feature",
  "properties": {
    "iso:country":"US",
    "sg:address":"1841 National Ave",
    "sg:city":"Hayward",
    "sg:classifiers":[
        {
            "category":"Building & Trades",
            "subcategory":"Plumbing",
            "type":"Services"
        }
    ],
    "sg:phone":"+1 510 784 3094",
    "sg:postcode":"94545",
    "sg:province":"CA",
    "sg:tags":[
        "sheet",
        "work",
        "metal",
        "contractor"
    ],
    "sg:website":"www.usfab.com",
    "wof:name":"U S Fabrications",
    "wof:placetype":"venue"
},
  "geometry": {"coordinates":[-122.127273,37.649622],"type":"Point"}
}