{
  "type": "Feature",
  "properties": {
    "iso:country":"US",
    "sg:address":"6600 Sunset Blvd",
    "sg:city":"Los Angeles",
    "sg:classifiers":[
        {
            "category":"Restaurant",
            "type":"Food & Drink"
        }
    ],
    "sg:phone":"+1 323 962 8200",
    "sg:postcode":"90028",
    "sg:province":"CA",
    "sg:tags":[
        "new",
        "american"
    ],
    "sg:website":"districtonsunset.com",
    "wof:name":"District",
    "wof:placetype":"venue"
},
  "geometry": {"coordinates":[-118.333249,34.097966],"type":"Point"}
}