{
  "type": "Feature",
  "properties": {
    "iso:country":"US",
    "sg:address":"1945 N St",
    "sg:city":"Newman",
    "sg:classifiers":[
        {
            "category":"Freight",
            "type":"Transportation"
        }
    ],
    "sg:phone":"+1 209 652 8883",
    "sg:postcode":"95360",
    "sg:province":"CA",
    "sg:tags":[
        "trucking"
    ],
    "wof:name":"M R Truckline",
    "wof:placetype":"venue"
},
  "geometry": {"coordinates":[-121.019189,37.30991],"type":"Point"}
}