{
  "type": "Feature",
  "properties": {
    "iso:country":"US",
    "sg:address":"17870 Castleton St",
    "sg:city":"City Of Industry",
    "sg:classifiers":[
        {
            "category":"Recreation",
            "type":"Entertainment"
        }
    ],
    "sg:phone":"+1 626 839 3830",
    "sg:postcode":"91748",
    "sg:province":"CA",
    "sg:tags":[
        "club",
        "travel"
    ],
    "wof:name":"C & H Travel & Tours",
    "wof:placetype":"venue"
},
  "geometry": {"coordinates":[-117.91935,33.993613],"type":"Point"}
}