{
  "type": "Feature",
  "properties": {
    "addr:full":"6433 Whittier Blvd Los Angeles CA 90022",
    "addr:housenumber":"6433",
    "addr:postcode":"90022",
    "addr:street":"Whittier Blvd",
    "iso:country":"US",
    "sg:address":"6433 Whittier Blvd",
    "sg:city":"Los Angeles",
    "sg:classifiers":[
        {
            "category":"Health Services",
            "subcategory":"Chiropractor",
            "type":"Services"
        }
    ],
    "sg:phone":"+1 323 724 9691",
    "sg:postcode":"90022",
    "sg:province":"CA",
    "wof:name":"Montebello Family Chiropractic",
    "wof:placetype":"venue"
},
  "geometry": {"coordinates":[-118.132578,34.015268],"type":"Point"}
}