{
  "type": "Feature",
  "properties": {
    "addr:full":"1805 E Capitol Expy San Jose CA 95121",
    "addr:housenumber":"1805",
    "addr:postcode":"95121",
    "addr:street":"E Capitol Expy",
    "iso:country":"US",
    "sg:address":"1805 E Capitol Expy",
    "sg:city":"San Jose",
    "sg:classifiers":[
        {
            "category":"Fast Food",
            "type":"Food & Drink"
        },
        {
            "category":"Restaurant",
            "type":"Food & Drink"
        }
    ],
    "sg:phone":"+1 408 274 1388",
    "sg:postcode":"95121",
    "sg:province":"CA",
    "sg:tags":[
        "hawaiian"
    ],
    "sg:website":"www.hawaiianbarbecue.com",
    "wof:name":"L&L Hawaiian Barbecue",
    "wof:placetype":"venue"
},
  "geometry": {"coordinates":[-121.808787,37.31011],"type":"Point"}
}