{
  "type": "Feature",
  "properties": {
    "iso:country":"US",
    "sg:address":"1067 C St",
    "sg:city":"Galt",
    "sg:classifiers":[
        {
            "category":"Food & Beverages",
            "subcategory":"Liquor & Beverages",
            "type":"Retail Goods"
        }
    ],
    "sg:phone":"+1 209 745 2804",
    "sg:postcode":"95632",
    "sg:province":"CA",
    "sg:tags":[
        "grocery",
        "alcoholic"
    ],
    "wof:name":"Victory Liquor Mart",
    "wof:placetype":"venue"
},
  "geometry": {"coordinates":[-121.29718200000001,38.253205],"type":"Point"}
}