{
  "type": "Feature",
  "properties": {
    "iso:country":"US",
    "sg:address":"2201 Bluebell Dr",
    "sg:city":"Santa Rosa",
    "sg:classifiers":[
        {
            "category":"Building & Trades",
            "subcategory":"Plumbing",
            "type":"Services"
        }
    ],
    "sg:phone":"+1 707 523 4615",
    "sg:postcode":"95403",
    "sg:province":"CA",
    "sg:tags":[
        "d",
        "system",
        "heating",
        "ventilation",
        "warm",
        "conditioning",
        "contractor",
        "air"
    ],
    "wof:name":"Furnace Works Inc",
    "wof:placetype":"venue"
},
  "geometry": {"coordinates":[-122.744241,38.46649],"type":"Point"}
}