{
  "type": "Feature",
  "properties": {
    "addr:full":"3811 Martin Luther King Jr Blvd Lynwood CA 90262",
    "addr:housenumber":"3811",
    "addr:postcode":"90262",
    "addr:street":"Martin Luther King Jr Blvd",
    "iso:country":"US",
    "sg:address":"3811 Martin Luther King Jr Blvd",
    "sg:city":"Lynwood",
    "sg:classifiers":[
        {
            "category":"Professional",
            "subcategory":"Research",
            "type":"Services"
        }
    ],
    "sg:phone":"+1 310 661 3080",
    "sg:postcode":"90262",
    "sg:province":"CA",
    "sg:tags":[
        "development",
        "laboratory"
    ],
    "wof:name":"Harbor UCLA Research",
    "wof:placetype":"venue"
},
  "geometry": {"coordinates":[-118.197681,33.927736],"type":"Point"}
}