{
  "type": "Feature",
  "properties": {
    "iso:country":"US",
    "sg:address":"4201 Torrance Blvd",
    "sg:city":"Torrance",
    "sg:classifiers":[
        {
            "category":"Health Services",
            "subcategory":"Doctor",
            "type":"Services"
        }
    ],
    "sg:phone":"+1 310 944 9094",
    "sg:postcode":"90503",
    "sg:province":"CA",
    "wof:name":"Naylor C Scott MD",
    "wof:placetype":"venue"
},
  "geometry": {"coordinates":[-118.358029,33.837717],"type":"Point"}
}