{
  "type": "Feature",
  "properties": {
    "addr:full":"3227 7th St Hughson CA 95326",
    "addr:housenumber":"3227",
    "addr:postcode":"95326",
    "addr:street":"7Th St",
    "iso:country":"US",
    "sg:address":"3227 7th St",
    "sg:city":"Hughson",
    "sg:classifiers":[
        {
            "category":"Professional",
            "subcategory":"Computer Services",
            "type":"Services"
        }
    ],
    "sg:phone":"+1 209 883 4640",
    "sg:postcode":"95326",
    "sg:province":"CA",
    "sg:tags":[
        "consultant",
        "designer",
        "system"
    ],
    "sg:website":"http://www.almondhulls.com",
    "wof:name":"Data Solutions",
    "wof:placetype":"venue"
},
  "geometry": {"coordinates":[-120.860657,37.588117],"type":"Point"}
}