{
  "type": "Feature",
  "properties": {
    "iso:country":"US",
    "sg:address":"7000 Village Pkwy",
    "sg:city":"Dublin",
    "sg:classifiers":[
        {
            "category":"Social Services",
            "type":"Services"
        }
    ],
    "sg:phone":"+1 925 833 9997",
    "sg:postcode":"94568",
    "sg:province":"CA",
    "sg:tags":[
        "worker"
    ],
    "wof:name":"Julie Dacosta Lcsw",
    "wof:placetype":"venue"
},
  "geometry": {"coordinates":[-121.925505,37.708146],"type":"Point"}
}