{
  "type": "Feature",
  "properties": {
    "addr:full":"421 N Tustin St Orange CA 92867",
    "addr:housenumber":"421",
    "addr:postcode":"92867",
    "addr:street":"N Tustin St",
    "iso:country":"US",
    "sg:address":"421 N Tustin St",
    "sg:city":"Orange",
    "sg:classifiers":[
        {
            "category":"Restaurant",
            "type":"Food & Drink"
        }
    ],
    "sg:phone":"+1 714 744 9446",
    "sg:postcode":"92867",
    "sg:province":"CA",
    "wof:name":"Maharaja Palace",
    "wof:placetype":"venue"
},
  "geometry": {"coordinates":[-117.835706,33.791442],"type":"Point"}
}