{
  "type": "Feature",
  "properties": {
    "iso:country":"US",
    "sg:address":"17604 Chateau Ct",
    "sg:city":"Castro Valley",
    "sg:classifiers":[
        {
            "category":"Professional",
            "type":"Services"
        }
    ],
    "sg:phone":"+1 510 537 4599",
    "sg:postcode":"94552",
    "sg:province":"CA",
    "wof:name":"Farshid Salamati",
    "wof:placetype":"venue"
},
  "geometry": {"coordinates":[-122.062178,37.718223],"type":"Point"}
}