{
  "type": "Feature",
  "properties": {
    "iso:country":"US",
    "sg:address":"771 Freedom Blvd",
    "sg:city":"Watsonville",
    "sg:classifiers":[
        {
            "category":"Professional",
            "subcategory":"Advertising",
            "type":"Services"
        }
    ],
    "sg:phone":"+1 831 728 3261",
    "sg:postcode":"95076",
    "sg:province":"CA",
    "sg:tags":[
        "mailing",
        "shipping"
    ],
    "wof:name":"24 Hr Mailbox",
    "wof:placetype":"venue"
},
  "geometry": {"coordinates":[-121.760487,36.916651],"type":"Point"}
}