{
  "type": "Feature",
  "properties": {
    "addr:full":"7766 San Fernando Rd Sun Valley CA 91352",
    "addr:housenumber":"7766",
    "addr:postcode":"91352",
    "addr:street":"San Fernando Rd",
    "iso:country":"US",
    "sg:address":"7766 San Fernando Rd",
    "sg:city":"Sun Valley",
    "sg:classifiers":[
        {
            "category":"Wholesale",
            "subcategory":"Home Furnishings",
            "type":"Manufacturing & Wholesale Goods"
        }
    ],
    "sg:phone":"+1 818 981 8887",
    "sg:postcode":"91352",
    "sg:province":"CA",
    "wof:name":"Merritt International",
    "wof:placetype":"venue"
},
  "geometry": {"coordinates":[-118.360214,34.213649],"type":"Point"}
}