{
  "type": "Feature",
  "properties": {
    "addr:full":"3549 Sagunto St Santa Ynez CA 93460",
    "addr:housenumber":"3549",
    "addr:postcode":"93460",
    "addr:street":"Sagunto St",
    "iso:country":"US",
    "sg:address":"3549 Sagunto St",
    "sg:city":"Santa Ynez",
    "sg:classifiers":[
        {
            "category":"Professional",
            "subcategory":"Art Services",
            "type":"Services"
        }
    ],
    "sg:phone":"+1 805 693 0031",
    "sg:postcode":"93460",
    "sg:province":"CA",
    "sg:tags":[
        "consultant",
        "photographic"
    ],
    "wof:name":"Gerlach Nature Photography",
    "wof:placetype":"venue"
},
  "geometry": {"coordinates":[-120.081051,34.612942],"type":"Point"}
}