{
  "type": "Feature",
  "properties": {
    "iso:country":"US",
    "sg:address":"1100 S 27th St",
    "sg:city":"Richmond",
    "sg:classifiers":[
        {
            "category":"Utilities",
            "type":"Services"
        }
    ],
    "sg:phone":"+1 510 232 7363",
    "sg:postcode":"94804",
    "sg:province":"CA",
    "sg:tags":[
        "s",
        "management"
    ],
    "wof:name":"Pacific Gas and Electric Co",
    "wof:placetype":"venue"
},
  "geometry": {"coordinates":[-122.344072,37.915706],"type":"Point"}
}