{
  "type": "Feature",
  "properties": {
    "iso:country":"US",
    "sg:address":"351 W Cypress St",
    "sg:city":"Glendale",
    "sg:classifiers":[
        {
            "category":"Retail",
            "subcategory":"Auto Repair",
            "type":"Services"
        }
    ],
    "sg:phone":"+1 818 242 0755",
    "sg:postcode":"91204",
    "sg:province":"CA",
    "sg:tags":[
        "repairing",
        "automobile"
    ],
    "wof:name":"Gabi's Auto Electric",
    "wof:placetype":"venue"
},
  "geometry": {"coordinates":[-118.258956,34.129864],"type":"Point"}
}