{
  "type": "Feature",
  "properties": {
    "iso:country":"US",
    "sg:address":"2909 W Olive Ave",
    "sg:city":"Burbank",
    "sg:classifiers":[
        {
            "category":"Retail",
            "subcategory":"Auto Repair",
            "type":"Services"
        }
    ],
    "sg:phone":"+1 818 846 5861",
    "sg:postcode":"91505",
    "sg:province":"CA",
    "sg:tags":[
        "repairing",
        "automobile"
    ],
    "wof:name":"Bethlehem Motors",
    "wof:placetype":"venue"
},
  "geometry": {"coordinates":[-118.333293,34.157984],"type":"Point"}
}