{
  "type": "Feature",
  "properties": {
    "addr:full":"17810 Miller Ave Fontana CA 92336",
    "addr:housenumber":"17810",
    "addr:postcode":"92336",
    "addr:street":"Miller Ave",
    "iso:country":"US",
    "sg:address":"17810 Miller Ave",
    "sg:city":"Fontana",
    "sg:classifiers":[
        {
            "category":"Shopping",
            "subcategory":"Jewelry",
            "type":"Retail Goods"
        }
    ],
    "sg:phone":"+1 909 355 2619",
    "sg:postcode":"92336",
    "sg:province":"CA",
    "sg:tags":[
        "precious",
        "semi-precious",
        "stone"
    ],
    "wof:name":"Evelias Jewelry",
    "wof:placetype":"venue"
},
  "geometry": {"coordinates":[-117.415893,34.113979],"type":"Point"}
}