{
  "type": "Feature",
  "properties": {
    "addr:full":"901 N Bradford Ave Placentia CA 92870",
    "addr:housenumber":"901",
    "addr:postcode":"ca 92870",
    "addr:street":"N Bradford Ave",
    "iso:country":"US",
    "sg:address":"901 N Bradford Ave",
    "sg:city":"Placentia",
    "sg:classifiers":[
        {
            "category":"Retail",
            "subcategory":"Event Space",
            "type":"Services"
        }
    ],
    "sg:phone":"+1 714 993 4560",
    "sg:postcode":"92870",
    "sg:province":"CA",
    "sg:tags":[
        "venue"
    ],
    "sg:website":"www.placentiartwomensclub.org",
    "wof:name":"Placentia Roundtable Women's Club",
    "wof:placetype":"venue"
},
  "geometry": {"coordinates":[-117.86799600000001,33.880199],"type":"Point"}
}