{
  "type": "Feature",
  "properties": {
    "iso:country":"US",
    "sg:address":"3150 Porter Dr",
    "sg:city":"Palo Alto",
    "sg:classifiers":[
        {
            "category":"Professional",
            "type":"Services"
        }
    ],
    "sg:phone":"+1 650 813 5023",
    "sg:postcode":"94304",
    "sg:province":"CA",
    "wof:name":"Mitchell Blakely",
    "wof:placetype":"venue"
},
  "geometry": {"coordinates":[-122.151318,37.408455],"type":"Point"}
}