{
  "type": "Feature",
  "properties": {
    "addr:full":"2801 Salinas Hwy Monterey CA 93940",
    "addr:housenumber":"2801",
    "addr:postcode":"93940",
    "addr:street":"Salinas Hwy",
    "iso:country":"US",
    "sg:address":"2801 Salinas Hwy",
    "sg:city":"Monterey",
    "sg:classifiers":[
        {
            "category":"Professional",
            "subcategory":"Lawyer & Legal Services",
            "type":"Services"
        }
    ],
    "sg:phone":"+1 831 424 9400",
    "sg:postcode":"93940",
    "sg:province":"CA",
    "sg:tags":[
        "attorney"
    ],
    "wof:name":"Biegel Lawrence E Law Ofc",
    "wof:placetype":"venue"
},
  "geometry": {"coordinates":[-121.84979199999999,36.583982],"type":"Point"}
}