{
  "type": "Feature",
  "properties": {
    "iso:country":"US",
    "sg:address":"1009 Stine Rd",
    "sg:city":"Bakersfield",
    "sg:classifiers":[
        {
            "category":"Real Estate",
            "subcategory":"Real Estate Agent",
            "type":"Services"
        }
    ],
    "sg:phone":"+1 661 397 8095",
    "sg:postcode":"93309",
    "sg:province":"CA",
    "sg:tags":[
        "management"
    ],
    "wof:name":"Royal T Management",
    "wof:placetype":"venue"
},
  "geometry": {"coordinates":[-119.050503,35.339626],"type":"Point"}
}