{
  "type": "Feature",
  "properties": {
    "iso:country":"US",
    "sg:address":"2234 S Sepulveda Blvd",
    "sg:city":"Los Angeles",
    "sg:classifiers":[
        {
            "category":"Home & Garden",
            "subcategory":"Furniture",
            "type":"Retail Goods"
        },
        {
            "category":"Home & Garden",
            "subcategory":"Carpets & Floor Coverings",
            "type":"Retail Goods"
        }
    ],
    "sg:phone":"+1 310 444 1470",
    "sg:postcode":"90064",
    "sg:province":"CA",
    "sg:tags":[
        "store",
        "mattress"
    ],
    "sg:website":"www.alsdiscountfurniture.com",
    "wof:name":"Al's Discount Furniture & Mattress Center",
    "wof:placetype":"venue"
},
  "geometry": {"coordinates":[-118.437459,34.039687],"type":"Point"}
}