{
  "type": "Feature",
  "properties": {
    "iso:country":"US",
    "sg:address":"835 N Vulcan Ave",
    "sg:city":"Encinitas",
    "sg:classifiers":[
        {
            "category":"Manufacturing",
            "subcategory":"Wood Products",
            "type":"Manufacturing & Wholesale Goods"
        }
    ],
    "sg:phone":"+1 760 633 1351",
    "sg:postcode":"92024",
    "sg:province":"CA",
    "sg:tags":[
        "picture",
        "frame"
    ],
    "wof:name":"Award Custom Framing",
    "wof:placetype":"venue"
},
  "geometry": {"coordinates":[-117.299516,33.059666],"type":"Point"}
}