{
  "type": "Feature",
  "properties": {
    "iso:country":"US",
    "sg:address":"3068 Potter Ave",
    "sg:city":"Thousand Oaks",
    "sg:classifiers":[
        {
            "category":"Building & Trades",
            "subcategory":"Landscaping Services",
            "type":"Services"
        }
    ],
    "sg:phone":"+1 805 499 2017",
    "sg:postcode":"91360",
    "sg:province":"CA",
    "sg:tags":[
        "landscape",
        "contractor"
    ],
    "wof:name":"Green Horizon Landscaping",
    "wof:placetype":"venue"
},
  "geometry": {"coordinates":[-118.859033,34.221308],"type":"Point"}
}