{
  "type": "Feature",
  "properties": {
    "iso:country":"US",
    "sg:address":"3596 Skyway Dr",
    "sg:city":"Santa Maria",
    "sg:classifiers":[
        {
            "category":"Shopping",
            "subcategory":"Jewelry",
            "type":"Retail Goods"
        }
    ],
    "sg:phone":"+1 805 937 5266",
    "sg:postcode":"93455",
    "sg:province":"CA",
    "sg:tags":[
        "designer"
    ],
    "wof:name":"Stinn Jewelry & Art Gallery",
    "wof:placetype":"venue"
},
  "geometry": {"coordinates":[-120.439584,34.894749],"type":"Point"}
}