{
  "type": "Feature",
  "properties": {
    "iso:country":"US",
    "sg:address":"510 W Wood St",
    "sg:city":"Willows",
    "sg:classifiers":[
        {
            "category":"Freight",
            "type":"Transportation"
        }
    ],
    "sg:phone":"+1 530 934 3103",
    "sg:postcode":"95988",
    "sg:province":"CA",
    "sg:tags":[
        "commercial",
        "storage"
    ],
    "wof:name":"Cci Investments LP-Mini",
    "wof:placetype":"venue"
},
  "geometry": {"coordinates":[-122.200802,39.5241],"type":"Point"}
}