{
  "type": "Feature",
  "properties": {
    "addr:full":"2041 Bancroft Way Berkeley CA 94704",
    "addr:housenumber":"2041",
    "addr:postcode":"94704",
    "addr:street":"Bancroft Way",
    "iso:country":"US",
    "sg:address":"2041 Bancroft Way",
    "sg:city":"Berkeley",
    "sg:classifiers":[
        {
            "category":"Health Services",
            "subcategory":"Doctor",
            "type":"Services"
        }
    ],
    "sg:phone":"+1 510 981 9141",
    "sg:postcode":"94704",
    "sg:province":"CA",
    "sg:tags":[
        "physician",
        "family",
        "practice",
        "surgeons",
        "medicine",
        "surgeon"
    ],
    "wof:name":"Lawrence S Cohen Md",
    "wof:placetype":"venue"
},
  "geometry": {"coordinates":[-122.26925300000001,37.867392],"type":"Point"}
}