{
  "type": "Feature",
  "properties": {
    "iso:country":"US",
    "sg:address":"701 Southampton Rd",
    "sg:city":"Benicia",
    "sg:classifiers":[
        {
            "category":"Insurance",
            "subcategory":"Insurance Agent",
            "type":"Services"
        }
    ],
    "sg:phone":"+1 707 748 1404",
    "sg:postcode":"94510",
    "sg:province":"CA",
    "sg:tags":[
        "consultant",
        "compensation"
    ],
    "wof:name":"O M Disability Management",
    "wof:placetype":"venue"
},
  "geometry": {"coordinates":[-122.164558,38.064811],"type":"Point"}
}