{
  "type": "Feature",
  "properties": {
    "addr:full":"835 Foothill Blvd La Canada Fltrdg CA 91011",
    "addr:housenumber":"835",
    "addr:postcode":"91011",
    "addr:street":"Foothill Blvd La Canada",
    "iso:country":"US",
    "sg:address":"835 Foothill Blvd",
    "sg:city":"La Canada Fltrdg",
    "sg:classifiers":[
        {
            "category":"Restaurant",
            "type":"Food & Drink"
        }
    ],
    "sg:phone":"+1 818 790 8116",
    "sg:postcode":"91011",
    "sg:province":"CA",
    "sg:tags":[
        "shop",
        "coffee"
    ],
    "wof:name":"Daily Grind",
    "wof:placetype":"venue"
},
  "geometry": {"coordinates":[-118.197121,34.202998],"type":"Point"}
}