{
  "type": "Feature",
  "properties": {
    "iso:country":"US",
    "sg:address":"1838 S Robertson Blvd",
    "sg:city":"Los Angeles",
    "sg:classifiers":[
        {
            "category":"Building & Trades",
            "subcategory":"Construction",
            "type":"Services"
        }
    ],
    "sg:phone":"+1 310 287 1141",
    "sg:postcode":"90035",
    "sg:province":"CA",
    "sg:tags":[
        "repairing",
        "general",
        "remodeling",
        "contractor"
    ],
    "wof:name":"AVI Construction Co",
    "wof:placetype":"venue"
},
  "geometry": {"coordinates":[-118.386478,34.04503],"type":"Point"}
}