{
  "type": "Feature",
  "properties": {
    "iso:country":"US",
    "sg:address":"831 Latour Ct",
    "sg:city":"Napa",
    "sg:classifiers":[
        {
            "category":"Professional",
            "type":"Services"
        }
    ],
    "sg:phone":"+1 707 938 8879",
    "sg:postcode":"94558",
    "sg:province":"CA",
    "sg:tags":[
        "establishment"
    ],
    "wof:name":"B Pad",
    "wof:placetype":"venue"
},
  "geometry": {"coordinates":[-122.273097,38.256414],"type":"Point"}
}