{
  "type": "Feature",
  "properties": {
    "addr:full":"6816 Leone Way Paradise CA 95969",
    "addr:housenumber":"6816",
    "addr:postcode":"95969",
    "addr:street":"Leone Way",
    "iso:country":"US",
    "sg:address":"6816 Leone Way",
    "sg:city":"Paradise",
    "sg:classifiers":[
        {
            "category":"Building & Trades",
            "subcategory":"Construction",
            "type":"Services"
        }
    ],
    "sg:phone":"+1 530 872 5328",
    "sg:postcode":"95969",
    "sg:province":"CA",
    "sg:tags":[
        "maintenance",
        "contractor"
    ],
    "wof:name":"GRS Maintenance",
    "wof:placetype":"venue"
},
  "geometry": {"coordinates":[-121.575879,39.782471],"type":"Point"}
}