{
  "type": "Feature",
  "properties": {
    "iso:country":"US",
    "sg:address":"6816 Leone Way",
    "sg:city":"Paradise",
    "sg:classifiers":[
        {
            "category":"Building & Trades",
            "subcategory":"Construction",
            "type":"Services"
        }
    ],
    "sg:phone":"+1 530 872 5328",
    "sg:postcode":"95969",
    "sg:province":"CA",
    "sg:tags":[
        "maintenance",
        "contractor"
    ],
    "wof:name":"GRS Maintenance",
    "wof:placetype":"venue"
},
  "geometry": {"coordinates":[-121.575879,39.782471],"type":"Point"}
}