{
  "type": "Feature",
  "properties": {
    "iso:country":"US",
    "sg:address":"13075 Garvey Ave",
    "sg:city":"Baldwin Park",
    "sg:classifiers":[
        {
            "category":"Manufacturing",
            "subcategory":"Printing",
            "type":"Manufacturing & Wholesale Goods"
        }
    ],
    "sg:phone":"+1 626 814 1515",
    "sg:postcode":"91706",
    "sg:province":"CA",
    "sg:tags":[
        "commercial"
    ],
    "wof:name":"Corporate Colour Printing Inc",
    "wof:placetype":"venue"
},
  "geometry": {"coordinates":[-117.989007,34.066925],"type":"Point"}
}