{
  "type": "Feature",
  "properties": {
    "iso:country":"US",
    "sg:address":"27260 Los Altos",
    "sg:city":"Mission Viejo",
    "sg:classifiers":[
        {
            "category":"Real Estate",
            "subcategory":"Real Estate Services",
            "type":"Services"
        },
        {
            "category":"Real Estate",
            "subcategory":"Real Estate Operator",
            "type":"Services"
        }
    ],
    "sg:phone":"+1 866 508 7387",
    "sg:postcode":"92691",
    "sg:province":"CA",
    "sg:tags":[
        "apartment",
        "property",
        "management"
    ],
    "sg:website":"www.ArchstoneMissionViejo.com",
    "wof:name":"Archstone Mission Viejo",
    "wof:placetype":"venue"
},
  "geometry": {"coordinates":[-117.667264,33.567735],"type":"Point"}
}