{
  "type": "Feature",
  "properties": {
    "iso:country":"US",
    "sg:address":"39 Iron Springs Rd",
    "sg:city":"Fairfax",
    "sg:classifiers":[
        {
            "category":"Professional",
            "subcategory":"Detective & Security Services",
            "type":"Services"
        }
    ],
    "sg:phone":"+1 415 453 3295",
    "sg:postcode":"94930",
    "sg:province":"CA",
    "sg:tags":[
        "information",
        "bureau"
    ],
    "wof:name":"John's, Ed Pool Service",
    "wof:placetype":"venue"
},
  "geometry": {"coordinates":[-122.599892,37.99297],"type":"Point"}
}