{
  "type": "Feature",
  "properties": {
    "iso:country":"US",
    "sg:address":"1511 Crows Landing Rd",
    "sg:city":"Modesto",
    "sg:classifiers":[
        {
            "category":"Professional",
            "subcategory":"Lawyer & Legal Services",
            "type":"Services"
        },
        {
            "category":"Travel",
            "subcategory":"Travel Agent",
            "type":"Entertainment"
        },
        {
            "category":"Marine",
            "type":"Transportation"
        }
    ],
    "sg:phone":"+1 209 531 1155",
    "sg:postcode":"95358",
    "sg:province":"CA",
    "sg:tags":[
        "notary",
        "agency",
        "services-commercial",
        "steamship",
        "cruise"
    ],
    "wof:name":"Inter Planet Travel",
    "wof:placetype":"venue"
},
  "geometry": {"coordinates":[-120.99299600000001,37.6092],"type":"Point"}
}