{
  "type": "Feature",
  "properties": {
    "addr:full":"1570 Huckleberry Ln San Luis Obispo CA 93401",
    "addr:housenumber":"1570",
    "addr:postcode":"93401",
    "addr:street":"Huckleberry Ln",
    "iso:country":"US",
    "sg:address":"1570 Huckleberry Ln",
    "sg:city":"San Luis Obispo",
    "sg:classifiers":[
        {
            "category":"Real Estate",
            "subcategory":"Real Estate Agent",
            "type":"Services"
        }
    ],
    "sg:phone":"+1 805 235 1736",
    "sg:postcode":"93401",
    "sg:province":"CA",
    "wof:name":"Craig Lose Real Estate",
    "wof:placetype":"venue"
},
  "geometry": {"coordinates":[-120.62272900000001,35.24893],"type":"Point"}
}