{
  "type": "Feature",
  "properties": {
    "iso:country":"US",
    "sg:address":"1921 Main St",
    "sg:city":"Julian",
    "sg:classifiers":[
        {
            "category":"Wholesale",
            "subcategory":"Fruits & Vegetables",
            "type":"Manufacturing & Wholesale Goods"
        }
    ],
    "sg:phone":"+1 760 765 1906",
    "sg:postcode":"92036",
    "sg:province":"CA",
    "sg:tags":[
        "shipper"
    ],
    "wof:name":"Julian Coffee House",
    "wof:placetype":"venue"
},
  "geometry": {"coordinates":[-116.600435,33.077098],"type":"Point"}
}