{
  "type": "Feature",
  "properties": {
    "addr:full":"2436 Loma Ave South El Monte CA 91733",
    "addr:housenumber":"2436",
    "addr:postcode":"91733",
    "addr:street":"Loma Ave",
    "iso:country":"US",
    "sg:address":"2436 Loma Ave",
    "sg:city":"South El Monte",
    "sg:classifiers":[
        {
            "category":"Utilities",
            "subcategory":"Telephone",
            "type":"Services"
        }
    ],
    "sg:phone":"+1 626 618 9988",
    "sg:postcode":"91733",
    "sg:province":"CA",
    "sg:tags":[
        "telecommunication"
    ],
    "wof:name":"M3 Telecom",
    "wof:placetype":"venue"
},
  "geometry": {"coordinates":[-118.068663,34.05601],"type":"Point"}
}