{
  "type": "Feature",
  "properties": {
    "addr:full":"695 W Herndon Ave Clovis CA 93612",
    "addr:housenumber":"695",
    "addr:postcode":"93612",
    "addr:street":"W Herndon Ave",
    "iso:country":"US",
    "sg:address":"695 W Herndon Ave",
    "sg:city":"Clovis",
    "sg:phone":"+1 559 321 0010",
    "sg:postcode":"93612",
    "sg:province":"CA",
    "sg:website":"http://www.target.com",
    "wof:name":"Target",
    "wof:placetype":"venue"
},
  "geometry": {"coordinates":[-119.72563100000001,36.837665],"type":"Point"}
}