{
  "type": "Feature",
  "properties": {
    "addr:full":"2300 Danville Blvd Alamo CA 94507",
    "addr:housenumber":"2300",
    "addr:postcode":"94507",
    "addr:street":"Danville Blvd",
    "iso:country":"US",
    "sg:address":"2300 Danville Blvd",
    "sg:city":"Alamo",
    "sg:classifiers":[
        {
            "category":"Building & Trades",
            "subcategory":"Construction",
            "type":"Services"
        }
    ],
    "sg:phone":"+1 925 938 9563",
    "sg:postcode":"94507",
    "sg:province":"CA",
    "sg:tags":[
        "home",
        "builder"
    ],
    "sg:website":"www.suncresthomes.com",
    "wof:name":"Suncrest Homes",
    "wof:placetype":"venue"
},
  "geometry": {"coordinates":[-122.037837,37.858576],"type":"Point"}
}