{
  "type": "Feature",
  "properties": {
    "iso:country":"US",
    "sg:address":"700 E Blithedale Ave",
    "sg:city":"Mill Valley",
    "sg:classifiers":[
        {
            "category":"Social Services",
            "type":"Services"
        }
    ],
    "sg:phone":"+1 415 389 7934",
    "sg:postcode":"94941",
    "sg:province":"CA",
    "sg:tags":[
        "counselor",
        "marriage",
        "family"
    ],
    "wof:name":"Jacqueline De Lon",
    "wof:placetype":"venue"
},
  "geometry": {"coordinates":[-122.52264599999999,37.903807],"type":"Point"}
}