{
  "type": "Feature",
  "properties": {
    "iso:country":"US",
    "sg:address":"2721 S Elm Ave",
    "sg:city":"Fresno",
    "sg:classifiers":[
        {
            "category":"Utilities",
            "subcategory":"Refuse",
            "type":"Services"
        }
    ],
    "sg:phone":"+1 559 499 1595",
    "sg:postcode":"93706",
    "sg:province":"CA",
    "sg:tags":[
        "disposal",
        "waste"
    ],
    "wof:name":"Sunset Waste Paper Inc",
    "wof:placetype":"venue"
},
  "geometry": {"coordinates":[-119.790791,36.7003],"type":"Point"}
}