{
  "type": "Feature",
  "properties": {
    "iso:country":"US",
    "sg:address":"1001 S Arrowhead Ave",
    "sg:city":"San Bernardino",
    "sg:classifiers":[
        {
            "category":"Wholesale",
            "subcategory":"Electrical",
            "type":"Manufacturing & Wholesale Goods"
        }
    ],
    "sg:phone":"+1 909 885 7771",
    "sg:postcode":"92408",
    "sg:province":"CA",
    "sg:tags":[
        "fire",
        "alarm",
        "system"
    ],
    "sg:website":"www.enkosystems.com",
    "wof:name":"Enko Systems Inc",
    "wof:placetype":"venue"
},
  "geometry": {"coordinates":[-117.289672,34.081095],"type":"Point"}
}