{
  "type": "Feature",
  "properties": {
    "addr:full":"Lynnel's Hair Design 2145 Poinsettia Dr San Diego CA 92106",
    "addr:housenumber":"2145",
    "addr:postcode":"92106",
    "addr:street":"Poinsettia Dr",
    "iso:country":"US",
    "sg:address":"Lynnel's Hair Design 2145 Poinsettia Dr",
    "sg:city":"San Diego",
    "sg:classifiers":[
        {
            "category":"Personal",
            "subcategory":"Beauty Salon",
            "type":"Services"
        }
    ],
    "sg:phone":"+1 619 315 6005",
    "sg:postcode":"92106",
    "sg:province":"CA",
    "sg:tags":[
        "hair"
    ],
    "wof:name":"Tracee Lorenzana Hair Design",
    "wof:placetype":"venue"
},
  "geometry": {"coordinates":[-117.229117,32.739534],"type":"Point"}
}