{
  "type": "Feature",
  "properties": {
    "addr:full":"8777 Haven Ave Rancho Cucamonga CA 91730",
    "addr:housenumber":"8777",
    "addr:postcode":"91730",
    "addr:street":"Haven Ave",
    "iso:country":"US",
    "sg:address":"8777 Haven Ave",
    "sg:city":"Rancho Cucamonga",
    "sg:classifiers":[
        {
            "category":"Retail",
            "subcategory":"Car Wash",
            "type":"Services"
        }
    ],
    "sg:phone":"+1 909 980 3717",
    "sg:postcode":"91730",
    "sg:province":"CA",
    "sg:tags":[
        "automobile",
        "detail",
        "clean"
    ],
    "wof:name":"Haven Car Wash",
    "wof:placetype":"venue"
},
  "geometry": {"coordinates":[-117.57570800000001,34.094112],"type":"Point"}
}