{
  "type": "Feature",
  "properties": {
    "addr:full":"20922 Heston Ln Redding CA 96003",
    "addr:housenumber":"20922",
    "addr:postcode":"96003",
    "addr:street":"Heston Ln",
    "iso:country":"US",
    "sg:address":"20922 Heston Ln",
    "sg:city":"Redding",
    "sg:classifiers":[
        {
            "category":"Building & Trades",
            "subcategory":"Construction",
            "type":"Services"
        }
    ],
    "sg:phone":"+1 530 241 0994",
    "sg:postcode":"96003",
    "sg:province":"CA",
    "sg:tags":[
        "contractor"
    ],
    "wof:name":"Reed Construction Co",
    "wof:placetype":"venue"
},
  "geometry": {"coordinates":[-122.27929,40.610047],"type":"Point"}
}