{
  "type": "Feature",
  "properties": {
    "addr:full":"15555 San Pablo Ave San Pablo CA 94806",
    "addr:housenumber":"15555",
    "addr:postcode":"94806",
    "addr:street":"San Pablo Ave",
    "iso:country":"US",
    "sg:address":"15555 San Pablo Ave",
    "sg:city":"San Pablo",
    "sg:classifiers":[
        {
            "category":"Restaurant",
            "type":"Food & Drink"
        }
    ],
    "sg:menulink":"http://www.allmenus.com/ca/west-contra-costa/197820-kfc---kentucky-fried-chicken/menu/",
    "sg:phone":"+1 510 222 2814",
    "sg:postcode":"94806",
    "sg:province":"CA",
    "sg:tags":[
        "american",
        "chicken"
    ],
    "wof:name":"KFC - Kentucky Fried Chicken",
    "wof:placetype":"venue"
},
  "geometry": {"coordinates":[-122.33370600000001,37.989676],"type":"Point"}
}