{
  "type": "Feature",
  "properties": {
    "addr:full":"3655 Homeway Dr Los Angeles CA 90008",
    "addr:housenumber":"3655",
    "addr:postcode":"90008",
    "addr:street":"Homeway Dr",
    "iso:country":"US",
    "sg:address":"3655 Homeway Dr",
    "sg:city":"Los Angeles",
    "sg:classifiers":[
        {
            "category":"Professional",
            "type":"Services"
        }
    ],
    "sg:phone":"+1 323 293 7481",
    "sg:postcode":"90008",
    "sg:province":"CA",
    "wof:name":"Leon O & Rose Marie Banks",
    "wof:placetype":"venue"
},
  "geometry": {"coordinates":[-118.33816299999999,34.004297],"type":"Point"}
}