{
  "type": "Feature",
  "properties": {
    "addr:full":"6618 Westminster Blvd Westminster CA 92683",
    "addr:housenumber":"6618",
    "addr:postcode":"92683",
    "addr:street":"Westminster Blvd",
    "iso:country":"US",
    "sg:address":"6618 Westminster Blvd",
    "sg:city":"Westminster",
    "sg:classifiers":[
        {
            "category":"Restaurant",
            "type":"Food & Drink"
        }
    ],
    "sg:phone":"+1 714 891 7513",
    "sg:postcode":"92683",
    "sg:province":"CA",
    "sg:tags":[
        "mexican"
    ],
    "sg:website":"chefmoz.org",
    "wof:name":"Casa Brito",
    "wof:placetype":"venue"
},
  "geometry": {"coordinates":[-118.014,33.758999],"type":"Point"}
}