{
  "type": "Feature",
  "properties": {
    "iso:country":"US",
    "sg:address":"10533 Garvey Ave",
    "sg:city":"South El Monte",
    "sg:classifiers":[
        {
            "category":"Restaurant",
            "type":"Food & Drink"
        }
    ],
    "sg:menulink":"http://www.allmenus.com/ca/upper-san-gabriel-valley/149370-subway/menu/",
    "sg:phone":"+1 626 454 4890",
    "sg:postcode":"91733",
    "sg:province":"CA",
    "sg:tags":[
        "american",
        "sandwich"
    ],
    "wof:name":"Subway",
    "wof:placetype":"venue"
},
  "geometry": {"coordinates":[-118.042888,34.063053],"type":"Point"}
}