{
  "type": "Feature",
  "properties": {
    "addr:full":"1955 N Texas St Fairfield CA 94533",
    "addr:housenumber":"1955",
    "addr:postcode":"94533",
    "addr:street":"N Texas St",
    "iso:country":"US",
    "sg:address":"1955 N Texas St",
    "sg:city":"Fairfield",
    "sg:classifiers":[
        {
            "category":"Food & Beverages",
            "subcategory":"Bakery",
            "type":"Retail Goods"
        }
    ],
    "sg:phone":"+1 707 425 1800",
    "sg:postcode":"94533",
    "sg:province":"CA",
    "sg:tags":[
        "pie"
    ],
    "wof:name":"Nation's Foodservice Inc",
    "wof:placetype":"venue"
},
  "geometry": {"coordinates":[-122.034265,38.264843],"type":"Point"}
}