{
  "type": "Feature",
  "properties": {
    "iso:country":"US",
    "sg:address":"4245 United Ct",
    "sg:city":"North Highlands",
    "sg:classifiers":[
        {
            "category":"Manufacturing",
            "subcategory":"Glass & Minerals",
            "type":"Manufacturing & Wholesale Goods"
        }
    ],
    "sg:phone":"+1 916 348 7545",
    "sg:postcode":"95660",
    "sg:province":"CA",
    "sg:tags":[
        "cut",
        "mfg"
    ],
    "wof:name":"Unique Vases That Rock",
    "wof:placetype":"venue"
},
  "geometry": {"coordinates":[-121.36503,38.696804],"type":"Point"}
}