{
  "type": "Feature",
  "properties": {
    "addr:full":"1495 Holiday Ln Fairfield CA 94534",
    "addr:housenumber":"1495",
    "addr:postcode":"94534",
    "addr:street":"Holiday Ln",
    "iso:country":"US",
    "sg:address":"1495 Holiday Ln",
    "sg:city":"Fairfield",
    "sg:classifiers":[
        {
            "category":"Building & Trades",
            "subcategory":"Construction",
            "type":"Services"
        }
    ],
    "sg:phone":"+1 707 427 3673",
    "sg:postcode":"94534",
    "sg:province":"CA",
    "sg:tags":[
        "resurfacing",
        "laying",
        "refinishing",
        "floor"
    ],
    "wof:name":"J L Floors",
    "wof:placetype":"venue"
},
  "geometry": {"coordinates":[-122.05864699999999,38.264319],"type":"Point"}
}