{
  "type": "Feature",
  "properties": {
    "addr:full":"10804 Open Trail Rd Bakersfield CA 93311",
    "addr:housenumber":"10804",
    "addr:postcode":"93311",
    "addr:street":"Open Trail Rd",
    "iso:country":"US",
    "sg:address":"10804 Open Trail Rd",
    "sg:city":"Bakersfield",
    "sg:classifiers":[
        {
            "category":"Building & Trades",
            "subcategory":"Plumbing",
            "type":"Services"
        }
    ],
    "sg:phone":"+1 661 665 9030",
    "sg:postcode":"93311",
    "sg:province":"CA",
    "sg:tags":[
        "contractor"
    ],
    "wof:name":"Rd Holder AC Service",
    "wof:placetype":"venue"
},
  "geometry": {"coordinates":[-119.12345999999999,35.315531],"type":"Point"}
}