{
  "type": "Feature",
  "properties": {
    "addr:full":"16909 Sebastian Way Esparto CA 95627",
    "addr:housenumber":"16909",
    "addr:postcode":"95627",
    "addr:street":"Sebastian Way",
    "iso:country":"US",
    "sg:address":"16909 Sebastian Way",
    "sg:city":"Esparto",
    "sg:classifiers":[
        {
            "category":"Building & Trades",
            "subcategory":"Construction",
            "type":"Services"
        }
    ],
    "sg:phone":"+1 530 787 1900",
    "sg:postcode":"95627",
    "sg:province":"CA",
    "sg:tags":[
        "residential"
    ],
    "wof:name":"Zamminer Construction",
    "wof:placetype":"venue"
},
  "geometry": {"coordinates":[-122.024475,38.696473],"type":"Point"}
}