{
  "type": "Feature",
  "properties": {
    "iso:country":"US",
    "sg:address":"9676 W Chapman Ave",
    "sg:city":"Garden Grove",
    "sg:classifiers":[
        {
            "category":"Food & Beverages",
            "subcategory":"Groceries & Convenience Stores",
            "type":"Retail Goods"
        }
    ],
    "sg:phone":"+1 714 537 4261",
    "sg:postcode":"92841",
    "sg:province":"CA",
    "sg:tags":[
        "grocer"
    ],
    "wof:name":"A & G Nutrition",
    "wof:placetype":"venue"
},
  "geometry": {"coordinates":[-117.959107,33.78851],"type":"Point"}
}