{
  "type": "Feature",
  "properties": {
    "addr:full":"854 N Ventura Rd Oxnard CA 93030",
    "addr:housenumber":"854",
    "addr:postcode":"93030",
    "addr:street":"N Ventura Rd",
    "iso:country":"US",
    "sg:address":"854 N Ventura Rd",
    "sg:city":"Oxnard",
    "sg:classifiers":[
        {
            "category":"Food & Beverages",
            "subcategory":"Bakery",
            "type":"Retail Goods"
        }
    ],
    "sg:phone":"+1 805 486 2775",
    "sg:postcode":"93030",
    "sg:province":"CA",
    "sg:tags":[
        "baker"
    ],
    "wof:name":"Ann's Bakery",
    "wof:placetype":"venue"
},
  "geometry": {"coordinates":[-119.19462,34.211493],"type":"Point"}
}