{
  "type": "Feature",
  "properties": {
    "addr:full":"7602 Talbert Ave Huntington Beach CA 92648",
    "addr:housenumber":"7602",
    "addr:postcode":"92648",
    "addr:street":"Talbert Ave",
    "iso:country":"US",
    "sg:address":"7602 Talbert Ave",
    "sg:city":"Huntington Beach",
    "sg:classifiers":[
        {
            "category":"Shopping",
            "subcategory":"Mobile Phones",
            "type":"Retail Goods"
        }
    ],
    "sg:phone":"+1 714 842 2333",
    "sg:postcode":"92648",
    "sg:province":"CA",
    "wof:name":"Davis Communication Services",
    "wof:placetype":"venue"
},
  "geometry": {"coordinates":[-117.99602400000001,33.700796],"type":"Point"}
}