{
  "type": "Feature",
  "properties": {
    "iso:country":"US",
    "sg:address":"11251 Coloma Rd",
    "sg:city":"Gold River",
    "sg:classifiers":[
        {
            "category":"Personal",
            "type":"Services"
        }
    ],
    "sg:phone":"+1 916 635 2726",
    "sg:postcode":"95670",
    "sg:province":"CA",
    "sg:tags":[
        "control",
        "weight"
    ],
    "wof:name":"Avon Products",
    "wof:placetype":"venue"
},
  "geometry": {"coordinates":[-121.266194,38.618685],"type":"Point"}
}