{
  "type": "Feature",
  "properties": {
    "iso:country":"US",
    "sg:address":"756 San Miguel Ave",
    "sg:city":"Sunnyvale",
    "sg:classifiers":[
        {
            "category":"Professional",
            "type":"Services"
        }
    ],
    "sg:phone":"+1 408 991 9661",
    "sg:postcode":"94085",
    "sg:province":"CA",
    "wof:name":"Coderant",
    "wof:placetype":"venue"
},
  "geometry": {"coordinates":[-122.007876,37.392296],"type":"Point"}
}