{
  "type": "Feature",
  "properties": {
    "iso:country":"US",
    "sg:address":"4256 Cliff Dr",
    "sg:city":"Stockton",
    "sg:classifiers":[
        {
            "category":"Professional",
            "subcategory":"Accounting & Tax Preparation",
            "type":"Services"
        }
    ],
    "sg:phone":"+1 209 943 2954",
    "sg:postcode":"95204",
    "sg:province":"CA",
    "sg:tags":[
        "accountant"
    ],
    "wof:name":"Dennis E Giuffre CPA",
    "wof:placetype":"venue"
},
  "geometry": {"coordinates":[-121.36197,37.964967],"type":"Point"}
}