{
  "type": "Feature",
  "properties": {
    "iso:country":"US",
    "sg:address":"2012 Mozart St",
    "sg:city":"Los Angeles",
    "sg:classifiers":[
        {
            "category":"Organizations",
            "subcategory":"Religious Organization",
            "type":"Services"
        }
    ],
    "sg:phone":"+1 323 221 5995",
    "sg:postcode":"90031",
    "sg:province":"CA",
    "sg:tags":[
        "church"
    ],
    "wof:name":"Iglesia Bautista Hispana",
    "wof:placetype":"venue"
},
  "geometry": {"coordinates":[-118.217795,34.069216],"type":"Point"}
}