{
  "type": "Feature",
  "properties": {
    "iso:country":"US",
    "sg:address":"21250 Hawthorne Blvd",
    "sg:city":"Torrance",
    "sg:classifiers":[
        {
            "category":"Banks & Credit Unions",
            "subcategory":"Bank",
            "type":"Services"
        }
    ],
    "sg:phone":"+1 310 792 8674",
    "sg:postcode":"90503",
    "sg:province":"CA",
    "sg:tags":[
        "loan"
    ],
    "wof:name":"E Loans Funding",
    "wof:placetype":"venue"
},
  "geometry": {"coordinates":[-118.35312,33.836133],"type":"Point"}
}