{
  "type": "Feature",
  "properties": {
    "iso:country":"US",
    "sg:address":"222 Sutter Street Suite 450",
    "sg:city":"San Francisco",
    "sg:classifiers":[
        {
            "category":"Professional",
            "subcategory":"Computer Services",
            "type":"Services"
        }
    ],
    "sg:phone":"+1 415 645 8001",
    "sg:postcode":"94108",
    "sg:province":"CA",
    "sg:tags":[
        "video",
        "adobe",
        "air",
        "innovation",
        "presentation-layer",
        "sharing",
        "visual-search",
        "flash",
        "youtube"
    ],
    "sg:website":"http://www.uvlayer.com",
    "wof:name":"Unknown Vector",
    "wof:placetype":"venue"
},
  "geometry": {"coordinates":[-122.404556,37.789816],"type":"Point"}
}