{
  "type": "Feature",
  "properties": {
    "iso:country":"US",
    "sg:address":"1734 Jefferson St",
    "sg:city":"Napa",
    "sg:classifiers":[
        {
            "category":"Organizations",
            "subcategory":"Professional Association",
            "type":"Services"
        }
    ],
    "sg:phone":"+1 707 252 4522",
    "sg:postcode":"94559",
    "sg:province":"CA",
    "wof:name":"Napa Valley Educators Assn",
    "wof:placetype":"venue"
},
  "geometry": {"coordinates":[-122.294449,38.304302],"type":"Point"}
}