{
  "type": "Feature",
  "properties": {
    "iso:country":"US",
    "sg:address":"541 Fifteen Mile Dr",
    "sg:city":"Roseville",
    "sg:classifiers":[
        {
            "category":"Professional",
            "type":"Services"
        }
    ],
    "sg:phone":"+1 916 721 4236",
    "sg:postcode":"95678",
    "sg:province":"CA",
    "wof:name":"Bounzeez",
    "wof:placetype":"venue"
},
  "geometry": {"coordinates":[-121.30037299999999,38.776411],"type":"Point"}
}