{
  "type": "Feature",
  "properties": {
    "addr:full":"2908 Channing Way Berkeley CA 94704",
    "addr:housenumber":"2908",
    "addr:postcode":"94704",
    "addr:street":"Channing Way",
    "iso:country":"US",
    "sg:address":"2908 Channing Way",
    "sg:city":"Berkeley",
    "sg:classifiers":[
        {
            "category":"Organizations",
            "subcategory":"Non-profit Organization",
            "type":"Services"
        }
    ],
    "sg:phone":"+1 510 486 8380",
    "sg:postcode":"94704",
    "sg:province":"CA",
    "sg:tags":[
        "housing",
        "student"
    ],
    "wof:name":"Pi Kappa Phi",
    "wof:placetype":"venue"
},
  "geometry": {"coordinates":[-122.25059,37.867946],"type":"Point"}
}