{
  "type": "Feature",
  "properties": {
    "iso:country":"US",
    "sg:address":"14120 Valley Blvd",
    "sg:city":"City Of Industry",
    "sg:classifiers":[
        {
            "category":"Wholesale",
            "subcategory":"Groceries",
            "type":"Manufacturing & Wholesale Goods"
        }
    ],
    "sg:phone":"+1 626 330 3479",
    "sg:postcode":"91746",
    "sg:province":"CA",
    "sg:tags":[
        "food",
        "product"
    ],
    "wof:name":"American Commissary",
    "wof:placetype":"venue"
},
  "geometry": {"coordinates":[-117.982199,34.039978],"type":"Point"}
}