{
  "type": "Feature",
  "properties": {
    "iso:country":"US",
    "sg:address":"3449 Longview Dr",
    "sg:city":"Sacramento",
    "sg:classifiers":[
        {
            "category":"Home & Garden",
            "subcategory":"Garden Supply",
            "type":"Retail Goods"
        }
    ],
    "sg:phone":"+1 916 482 2924",
    "sg:postcode":"95821",
    "sg:province":"CA",
    "sg:tags":[
        "sprinkler"
    ],
    "sg:website":"www.normac1.com",
    "wof:name":"Normac Inc",
    "wof:placetype":"venue"
},
  "geometry": {"coordinates":[-121.383718,38.642351],"type":"Point"}
}