{
  "type": "Feature",
  "properties": {
    "addr:full":"3905 Bohannon Dr Menlo Park CA 94025",
    "addr:housenumber":"3905",
    "addr:postcode":"94025",
    "addr:street":"Bohannon Dr",
    "iso:country":"US",
    "sg:address":"3905 Bohannon Dr",
    "sg:city":"Menlo Park",
    "sg:classifiers":[
        {
            "category":"Insurance",
            "subcategory":"Health Insurance",
            "type":"Services"
        }
    ],
    "sg:phone":"+1 650 326 1900",
    "sg:postcode":"94025",
    "sg:province":"CA",
    "sg:tags":[
        "plan"
    ],
    "wof:name":"International Pro Insurance",
    "wof:placetype":"venue"
},
  "geometry": {"coordinates":[-122.17785499999999,37.48149],"type":"Point"}
}