{
  "type": "Feature",
  "properties": {
    "addr:full":"1222 S 5th St Montebello CA 90640",
    "addr:housenumber":"1222",
    "addr:postcode":"90640",
    "addr:street":"S 5Th St",
    "iso:country":"US",
    "sg:address":"1222 S 5th St",
    "sg:city":"Montebello",
    "sg:classifiers":[
        {
            "category":"Professional",
            "subcategory":"Art Services",
            "type":"Services"
        }
    ],
    "sg:phone":"+1 323 726 2786",
    "sg:postcode":"90640",
    "sg:province":"CA",
    "sg:tags":[
        "graphic",
        "designer"
    ],
    "wof:name":"Bilco Design Concepts",
    "wof:placetype":"venue"
},
  "geometry": {"coordinates":[-118.116574,33.987631],"type":"Point"}
}