{
  "type": "Feature",
  "properties": {
    "iso:country":"US",
    "sg:address":"4121 Westerly Pl Ste 101",
    "sg:city":"Newport Beach",
    "sg:classifiers":[
        {
            "category":"Banks & Credit Unions",
            "subcategory":"Investment Brokerage",
            "type":"Services"
        }
    ],
    "sg:phone":"+1 949 752 0101",
    "sg:postcode":"92660",
    "sg:province":"CA",
    "sg:tags":[
        "investing"
    ],
    "sg:website":"www.rjtenterprises.com",
    "wof:name":"Rjt Enterprises Llc",
    "wof:placetype":"venue"
},
  "geometry": {"coordinates":[-117.86739799999999,33.664591],"type":"Point"}
}