{
  "type": "Feature",
  "properties": {
    "addr:full":"12960 Saratoga Sunnyvale R Saratoga CA 95070",
    "addr:housenumber":"12960",
    "addr:postcode":"95070",
    "addr:street":"Saratoga;R",
    "iso:country":"US",
    "sg:address":"12960 Saratoga Sunnyvale R",
    "sg:city":"Saratoga",
    "sg:classifiers":[
        {
            "category":"Coffee & Tea",
            "type":"Food & Drink"
        }
    ],
    "sg:phone":"+1 408 867 1732",
    "sg:postcode":"95070",
    "sg:province":"CA",
    "wof:name":"Starbuck Coffee",
    "wof:placetype":"venue"
},
  "geometry": {"coordinates":[-122.032372,37.279988],"type":"Point"}
}