{
  "type": "Feature",
  "properties": {
    "addr:full":"2400 Pole Line Rd Davis CA 95618",
    "addr:housenumber":"2400",
    "addr:postcode":"95618",
    "addr:street":"Pole Line Rd",
    "iso:country":"US",
    "sg:address":"2400 Pole Line Rd",
    "sg:city":"Davis",
    "sg:classifiers":[
        {
            "category":"Autos & Motor Vehicles",
            "subcategory":"Auto Supplies",
            "type":"Retail Goods"
        }
    ],
    "sg:phone":"+1 408 835 0660",
    "sg:postcode":"95618",
    "sg:province":"CA",
    "wof:name":"Highline Tuning",
    "wof:placetype":"venue"
},
  "geometry": {"coordinates":[-121.73086600000001,38.566033],"type":"Point"}
}