{
  "type": "Feature",
  "properties": {
    "addr:full":"12896 Bradley Ave Ste A Sylmar CA 91342",
    "addr:housenumber":"12896",
    "addr:postcode":"91342",
    "addr:street":"Bradley Ave Ste A",
    "iso:country":"US",
    "sg:address":"12896 Bradley Ave Ste A",
    "sg:city":"Sylmar",
    "sg:classifiers":[
        {
            "category":"Utilities",
            "subcategory":"Telephone",
            "type":"Services"
        },
        {
            "category":"Manufacturing",
            "subcategory":"Electronics",
            "type":"Manufacturing & Wholesale Goods"
        }
    ],
    "sg:phone":"+1 818 362 5935",
    "sg:postcode":"91342",
    "sg:province":"CA",
    "sg:tags":[
        "equipment",
        "telecommunications-equipment",
        "system",
        "supply"
    ],
    "sg:website":"http://www.bcommunications.com",
    "wof:name":"B Communications",
    "wof:placetype":"venue"
},
  "geometry": {"coordinates":[-118.457204,34.303457],"type":"Point"}
}