{
  "type": "Feature",
  "properties": {
    "iso:country":"US",
    "sg:address":"1355 Westwood Blvd",
    "sg:city":"Los Angeles",
    "sg:classifiers":[
        {
            "category":"Travel",
            "subcategory":"Travel Agent",
            "type":"Entertainment"
        }
    ],
    "sg:phone":"+1 310 479 6040",
    "sg:postcode":"90024",
    "sg:province":"CA",
    "sg:tags":[
        "passenger",
        "transportation",
        "arrangement"
    ],
    "wof:name":"JB Travel Company",
    "wof:placetype":"venue"
},
  "geometry": {"coordinates":[-118.441845,34.055363],"type":"Point"}
}