{
  "type": "Feature",
  "properties": {
    "addr:full":"520 Superior Ave Ste 270 Newport Beach CA 92663",
    "addr:housenumber":"520",
    "addr:postcode":"92663",
    "addr:street":"Superior Ave Ste 270",
    "iso:country":"US",
    "sg:address":"520 Superior Ave Ste 270",
    "sg:city":"Newport Beach",
    "sg:classifiers":[
        {
            "category":"Health Services",
            "subcategory":"Doctor",
            "type":"Services"
        }
    ],
    "sg:phone":"+1 949 574 9300",
    "sg:postcode":"92663",
    "sg:province":"CA",
    "wof:name":"Jenkins Scott E MD Inc.",
    "wof:placetype":"venue"
},
  "geometry": {"coordinates":[-117.929211,33.6305],"type":"Point"}
}