{
  "type": "Feature",
  "properties": {
    "addr:full":"3377 Solano Ave Napa CA 94558",
    "addr:housenumber":"3377",
    "addr:postcode":"94558",
    "addr:street":"Solano Ave",
    "iso:country":"US",
    "sg:address":"3377 Solano Ave",
    "sg:city":"Napa",
    "sg:classifiers":[
        {
            "category":"Wholesale",
            "subcategory":"Chemicals & Plastics",
            "type":"Manufacturing & Wholesale Goods"
        }
    ],
    "sg:phone":"+1 707 963 5509",
    "sg:postcode":"94558",
    "sg:province":"CA",
    "sg:tags":[
        "oil"
    ],
    "wof:name":"Deva",
    "wof:placetype":"venue"
},
  "geometry": {"coordinates":[-122.308243,38.317986],"type":"Point"}
}