{
  "type": "Feature",
  "properties": {
    "iso:country":"US",
    "sg:address":"300 S Spring St",
    "sg:city":"Los Angeles",
    "sg:classifiers":[
        {
            "category":"Government",
            "subcategory":"Office",
            "type":"Public Place"
        }
    ],
    "sg:phone":"+1 213 897 7086",
    "sg:postcode":"90013",
    "sg:province":"CA",
    "sg:tags":[
        "agency",
        "tax",
        "governor",
        "lieutenant",
        "state",
        "collection"
    ],
    "wof:name":"Los Angeles Field Office",
    "wof:placetype":"venue"
},
  "geometry": {"coordinates":[-118.248293,34.04882],"type":"Point"}
}