{
  "type": "Feature",
  "properties": {
    "addr:full":"2408 19th Ave San Francisco CA 94116",
    "addr:housenumber":"2408",
    "addr:postcode":"94116",
    "addr:street":"19Th Ave",
    "iso:country":"US",
    "sg:address":"2408 19th Ave",
    "sg:city":"San Francisco",
    "sg:classifiers":[
        {
            "category":"Education",
            "subcategory":"Special Training",
            "type":"Public Place"
        }
    ],
    "sg:phone":"+1 415 509 8689",
    "sg:postcode":"94116",
    "sg:province":"CA",
    "sg:tags":[
        "instruction",
        "driving"
    ],
    "wof:name":"A Plus Driving School",
    "wof:placetype":"venue"
},
  "geometry": {"coordinates":[-122.47541,37.741334],"type":"Point"}
}