{
  "type": "Feature",
  "properties": {
    "iso:country":"US",
    "sg:address":"220 S Maclay St",
    "sg:city":"San Fernando",
    "sg:classifiers":[
        {
            "category":"Health Services",
            "subcategory":"Clinic",
            "type":"Services"
        }
    ],
    "sg:phone":"+1 818 837 1355",
    "sg:postcode":"91340",
    "sg:province":"CA",
    "sg:tags":[
        "medical",
        "group"
    ],
    "wof:name":"Valley Mission Medical Group",
    "wof:placetype":"venue"
},
  "geometry": {"coordinates":[-118.442218,34.282533],"type":"Point"}
}