{
  "type": "Feature",
  "properties": {
    "addr:full":"2500 Milvia Street Berkeley CA 94704",
    "addr:housenumber":"2500",
    "addr:postcode":"94704",
    "addr:street":"Milvia Street",
    "iso:country":"US",
    "sg:address":"2500 Milvia Street",
    "sg:city":"Berkeley",
    "sg:classifiers":[
        {
            "category":"Health Services",
            "subcategory":"Doctor",
            "type":"Services"
        }
    ],
    "sg:phone":"+1 510 849 3800",
    "sg:postcode":"94704",
    "sg:province":"CA",
    "sg:tags":[
        "podiatrist"
    ],
    "wof:name":"Berkeley Foot & Ankle Specialists",
    "wof:placetype":"venue"
},
  "geometry": {"coordinates":[-122.261002,37.864799],"type":"Point"}
}