{
  "type": "Feature",
  "properties": {
    "iso:country":"US",
    "sg:address":"1813 4th St",
    "sg:city":"Berkeley",
    "sg:classifiers":[
        {
            "category":"Professional",
            "type":"Services"
        }
    ],
    "sg:phone":"+1 510 883 1300",
    "sg:postcode":"94710",
    "sg:province":"CA",
    "wof:name":"Claremont Rug Coarmen GA",
    "wof:placetype":"venue"
},
  "geometry": {"coordinates":[-122.300878,37.87106],"type":"Point"}
}