{
  "type": "Feature",
  "properties": {
    "iso:country":"US",
    "sg:address":"1435 Koll Cir",
    "sg:city":"San Jose",
    "sg:classifiers":[
        {
            "category":"Manufacturing",
            "subcategory":"Electronics",
            "type":"Manufacturing & Wholesale Goods"
        }
    ],
    "sg:phone":"+1 408 441 8183",
    "sg:postcode":"95112",
    "sg:province":"CA",
    "sg:tags":[
        "semiconductor",
        "related",
        "devices"
    ],
    "wof:name":"Sigma Probe",
    "wof:placetype":"venue"
},
  "geometry": {"coordinates":[-121.906514,37.365914],"type":"Point"}
}