{
  "type": "Feature",
  "properties": {
    "iso:country":"US",
    "sg:address":"5930 S Land Park Dr",
    "sg:city":"Sacramento",
    "sg:classifiers":[
        {
            "category":"Government",
            "subcategory":"Post Office",
            "type":"Public Place"
        }
    ],
    "sg:phone":"+1 916 421 2373",
    "sg:postcode":"95822",
    "sg:province":"CA",
    "wof:name":"Land Park Station",
    "wof:placetype":"venue"
},
  "geometry": {"coordinates":[-121.512254,38.520639],"type":"Point"}
}