{
  "type": "Feature",
  "properties": {
    "addr:full":"425 Wall St Los Angeles CA 90013",
    "addr:housenumber":"425",
    "addr:postcode":"90013",
    "addr:street":"Wall St",
    "iso:country":"US",
    "sg:address":"425 Wall St",
    "sg:city":"Los Angeles",
    "sg:classifiers":[
        {
            "category":"Wholesale",
            "subcategory":"Non-durable Goods",
            "type":"Manufacturing & Wholesale Goods"
        }
    ],
    "sg:phone":"+1 213 626 7879",
    "sg:postcode":"90013",
    "sg:province":"CA",
    "wof:name":"One Stop 2",
    "wof:placetype":"venue"
},
  "geometry": {"coordinates":[-118.245075,34.045973],"type":"Point"}
}