{
  "type": "Feature",
  "properties": {
    "iso:country":"US",
    "sg:address":"501 N E St",
    "sg:city":"Madera",
    "sg:classifiers":[
        {
            "category":"Retail",
            "subcategory":"Auto Repair",
            "type":"Services"
        }
    ],
    "sg:phone":"+1 559 662 0599",
    "sg:postcode":"93638",
    "sg:province":"CA",
    "sg:tags":[
        "automobile",
        "top",
        "upholstery"
    ],
    "wof:name":"Oveson's Upholstery",
    "wof:placetype":"venue"
},
  "geometry": {"coordinates":[-120.06428699999999,36.966491],"type":"Point"}
}