{
  "type": "Feature",
  "properties": {
    "iso:country":"US",
    "sg:address":"2605 Faivre St",
    "sg:city":"Chula Vista",
    "sg:classifiers":[
        {
            "category":"Manufacturing",
            "subcategory":"Tools & Machinery",
            "type":"Manufacturing & Wholesale Goods"
        }
    ],
    "sg:phone":"+1 619 423 0316",
    "sg:postcode":"91911",
    "sg:province":"CA",
    "sg:tags":[
        "machine",
        "shop"
    ],
    "wof:name":"Pacific Manufacturing Inc",
    "wof:placetype":"venue"
},
  "geometry": {"coordinates":[-117.077599,32.592887],"type":"Point"}
}