{
  "type": "Feature",
  "properties": {
    "iso:country":"US",
    "sg:address":"608 N el Camino Real",
    "sg:city":"San Mateo",
    "sg:classifiers":[
        {
            "category":"Real Estate",
            "subcategory":"Real Estate Agent",
            "type":"Services"
        }
    ],
    "sg:phone":"+1 650 685 7680",
    "sg:postcode":"94401",
    "sg:province":"CA",
    "sg:website":"www.janicepetty.com",
    "wof:name":"Janice K Petty",
    "wof:placetype":"venue"
},
  "geometry": {"coordinates":[-122.337994,37.571407],"type":"Point"}
}