{
  "type": "Feature",
  "properties": {
    "iso:country":"US",
    "sg:address":"13800 Heacock St",
    "sg:city":"Moreno Valley",
    "sg:classifiers":[
        {
            "category":"Health Services",
            "subcategory":"Health Practitioner",
            "type":"Services"
        }
    ],
    "sg:phone":"+1 951 656 6009",
    "sg:postcode":"92553",
    "sg:province":"CA",
    "sg:tags":[
        "occupational",
        "therapist"
    ],
    "wof:name":"Comp",
    "wof:placetype":"venue"
},
  "geometry": {"coordinates":[-117.243654,33.918106],"type":"Point"}
}