{
  "type": "Feature",
  "properties": {
    "addr:full":"39675 Cedar Blvd Newark CA 94560",
    "addr:housenumber":"39675",
    "addr:postcode":"94560",
    "addr:street":"Cedar Blvd",
    "iso:country":"US",
    "sg:address":"39675 Cedar Blvd",
    "sg:city":"Newark",
    "sg:classifiers":[
        {
            "category":"Professional",
            "subcategory":"Computer Services",
            "type":"Services"
        }
    ],
    "sg:phone":"+1 510 656 0500",
    "sg:postcode":"94560",
    "sg:province":"CA",
    "sg:tags":[
        "communications",
        "datum",
        "system"
    ],
    "wof:name":"Dataglance Inc",
    "wof:placetype":"venue"
},
  "geometry": {"coordinates":[-121.99584,37.520478],"type":"Point"}
}