{
  "type": "Feature",
  "properties": {
    "addr:full":"7770 Macaw Ln San Diego CA 92123",
    "addr:housenumber":"7770",
    "addr:postcode":"92123",
    "addr:street":"Macaw Ln",
    "iso:country":"US",
    "sg:address":"7770 Macaw Ln",
    "sg:city":"San Diego",
    "sg:classifiers":[
        {
            "category":"Retail",
            "subcategory":"Animal Services",
            "type":"Services"
        }
    ],
    "sg:phone":"+1 858 505 8636",
    "sg:postcode":"92123",
    "sg:province":"CA",
    "sg:tags":[
        "pet"
    ],
    "wof:name":"Paradise Pet Sitting",
    "wof:placetype":"venue"
},
  "geometry": {"coordinates":[-117.15603,32.780684],"type":"Point"}
}