{
  "type": "Feature",
  "properties": {
    "addr:full":"18300 Wood Edge Ln Riverside CA 92504",
    "addr:housenumber":"18300",
    "addr:postcode":"92504",
    "addr:street":"Wood Edge Ln",
    "iso:country":"US",
    "sg:address":"18300 Wood Edge Ln",
    "sg:city":"Riverside",
    "sg:classifiers":[
        {
            "category":"Professional",
            "type":"Services"
        }
    ],
    "sg:phone":"+1 951 776 1829",
    "sg:postcode":"92504",
    "sg:province":"CA",
    "wof:name":"Carl Pagel",
    "wof:placetype":"venue"
},
  "geometry": {"coordinates":[-117.374449,33.857346],"type":"Point"}
}