{
  "type": "Feature",
  "properties": {
    "addr:full":"2589 S Sepulveda Blvd Los Angeles CA 90064",
    "addr:housenumber":"2589",
    "addr:postcode":"90064",
    "addr:street":"S Sepulveda Blvd",
    "iso:country":"US",
    "sg:address":"2589 S Sepulveda Blvd",
    "sg:city":"Los Angeles",
    "sg:classifiers":[
        {
            "category":"Real Estate",
            "subcategory":"Real Estate Operator",
            "type":"Services"
        }
    ],
    "sg:phone":"+1 310 479 8745",
    "sg:postcode":"90064",
    "sg:province":"CA",
    "sg:tags":[
        "apartment"
    ],
    "wof:name":"Warren Sepulveda",
    "wof:placetype":"venue"
},
  "geometry": {"coordinates":[-118.43331000000001,34.034156],"type":"Point"}
}