{
  "type": "Feature",
  "properties": {
    "addr:full":"12340 Santa Monica Blvd Los Angeles CA 90025",
    "addr:housenumber":"12340",
    "addr:postcode":"90025",
    "addr:street":"Santa Monica Blvd",
    "iso:country":"US",
    "sg:address":"12340 Santa Monica Blvd",
    "sg:city":"Los Angeles",
    "sg:classifiers":[
        {
            "category":"Professional",
            "subcategory":"Management & Consulting",
            "type":"Services"
        }
    ],
    "sg:phone":"+1 310 442 1126",
    "sg:postcode":"90025",
    "sg:province":"CA",
    "sg:tags":[
        "construction"
    ],
    "wof:name":"Gabai Construction Inc",
    "wof:placetype":"venue"
},
  "geometry": {"coordinates":[-118.466183,34.039242],"type":"Point"}
}