{
  "type": "Feature",
  "properties": {
    "iso:country":"US",
    "sg:address":"90 Mission Dr",
    "sg:city":"Pleasanton",
    "sg:classifiers":[
        {
            "category":"Professional",
            "subcategory":"Engineering",
            "type":"Services"
        }
    ],
    "sg:phone":"+1 925 846 7170",
    "sg:postcode":"94566",
    "sg:province":"CA",
    "sg:tags":[
        "engineer"
    ],
    "wof:name":"Betlachin & Assoc",
    "wof:placetype":"venue"
},
  "geometry": {"coordinates":[-121.87872400000001,37.652606],"type":"Point"}
}