{
  "type": "Feature",
  "properties": {
    "addr:full":"139 E 3rd Ave Escondido CA 92025",
    "addr:housenumber":"139",
    "addr:postcode":"92025",
    "addr:street":"E 3Rd Ave",
    "iso:country":"US",
    "sg:address":"139 E 3rd Ave",
    "sg:city":"Escondido",
    "sg:classifiers":[
        {
            "category":"Banks & Credit Unions",
            "subcategory":"Investment Brokerage",
            "type":"Services"
        }
    ],
    "sg:phone":"+1 760 735 5868",
    "sg:postcode":"92025",
    "sg:province":"CA",
    "sg:tags":[
        "retirement",
        "planning"
    ],
    "wof:name":"Price Raffel & Assoc",
    "wof:placetype":"venue"
},
  "geometry": {"coordinates":[-117.079267,33.120194],"type":"Point"}
}