{
  "type": "Feature",
  "properties": {
    "iso:country":"US",
    "sg:address":"20475 Sherman Way",
    "sg:city":"Winnetka",
    "sg:classifiers":[
        {
            "category":"Shopping",
            "subcategory":"Tobacco",
            "type":"Retail Goods"
        }
    ],
    "sg:phone":"+1 818 348 4622",
    "sg:postcode":"91306",
    "sg:province":"CA",
    "sg:tags":[
        "shop"
    ],
    "wof:name":"Tj-Min Cigarettes",
    "wof:placetype":"venue"
},
  "geometry": {"coordinates":[-118.58000199999999,34.201],"type":"Point"}
}