{
  "type": "Feature",
  "properties": {
    "addr:full":"427 Center St Taft CA 93268",
    "addr:housenumber":"427",
    "addr:postcode":"93268",
    "addr:street":"Center St",
    "iso:country":"US",
    "sg:address":"427 Center St",
    "sg:city":"Taft",
    "sg:classifiers":[
        {
            "category":"Professional",
            "subcategory":"Art Services",
            "type":"Services"
        }
    ],
    "sg:phone":"+1 661 763 5429",
    "sg:postcode":"93268",
    "sg:province":"CA",
    "sg:tags":[
        "photographer"
    ],
    "wof:name":"K C Photography & Framing",
    "wof:placetype":"venue"
},
  "geometry": {"coordinates":[-119.458682,35.140751],"type":"Point"}
}