{
  "type": "Feature",
  "properties": {
    "iso:country":"US",
    "sg:address":"1138 Maple Avenue",
    "sg:city":"Los Angeles",
    "sg:classifiers":[
        {
            "category":"Shopping",
            "subcategory":"Clothing, Apparel, & Fashions",
            "type":"Retail Goods"
        }
    ],
    "sg:phone":"+1 213 742 0556",
    "sg:postcode":"90015",
    "sg:province":"CA",
    "sg:tags":[
        "accessory",
        "clothing",
        "women's"
    ],
    "wof:name":"Aspeed Design Corporation",
    "wof:placetype":"venue"
},
  "geometry": {"coordinates":[-118.255912,34.036357],"type":"Point"}
}