{
  "type": "Feature",
  "properties": {
    "addr:full":"35646 Dormer Rd Santa Clarita CA 91390",
    "addr:postcode":"35646;91390",
    "addr:street":"Dormer Rd",
    "iso:country":"US",
    "sg:address":"35646 Dormer Rd",
    "sg:city":"Santa Clarita",
    "sg:classifiers":[
        {
            "category":"Professional",
            "type":"Services"
        }
    ],
    "sg:phone":"+1 661 268 0146",
    "sg:postcode":"91390",
    "sg:province":"CA",
    "wof:name":"Kelly Condon Co",
    "wof:placetype":"venue"
},
  "geometry": {"coordinates":[-118.29703499999999,34.52654],"type":"Point"}
}