{
  "type": "Feature",
  "properties": {
    "iso:country":"US",
    "sg:address":"30020 Ahern Ave",
    "sg:city":"Union City",
    "sg:classifiers":[
        {
            "category":"Professional",
            "subcategory":"Management & Consulting",
            "type":"Services"
        }
    ],
    "sg:phone":"+1 510 429 6659",
    "sg:postcode":"94587",
    "sg:province":"CA",
    "sg:tags":[
        "water",
        "delivery",
        "bottle"
    ],
    "wof:name":"Sparkletts Waters N Amer LP",
    "wof:placetype":"venue"
},
  "geometry": {"coordinates":[-122.07648399999999,37.609001],"type":"Point"}
}