{
  "type": "Feature",
  "properties": {
    "addr:full":"3855 242nd St Torrance CA 90510",
    "addr:housenumber":"3855",
    "addr:postcode":"90510",
    "addr:street":"242Nd St",
    "iso:country":"US",
    "sg:address":"3855 242nd St",
    "sg:city":"Torrance",
    "sg:classifiers":[
        {
            "category":"Park",
            "type":"Public Place"
        }
    ],
    "sg:postcode":"90510",
    "sg:province":"CA",
    "wof:name":"Walteria Park",
    "wof:placetype":"venue"
},
  "geometry": {"coordinates":[-118.353804,33.804391],"type":"Point"}
}