{
  "type": "Feature",
  "properties": {
    "iso:country":"US",
    "sg:address":"23021 Sunnymead Blvd",
    "sg:city":"Moreno Valley",
    "sg:classifiers":[
        {
            "category":"Food & Beverages",
            "subcategory":"Groceries & Convenience Stores",
            "type":"Retail Goods"
        }
    ],
    "sg:phone":"+1 951 242 7474",
    "sg:postcode":"92553",
    "sg:province":"CA",
    "wof:name":"7-Eleven",
    "wof:placetype":"venue"
},
  "geometry": {"coordinates":[-117.25631799999999,33.938962],"type":"Point"}
}