{
  "type": "Feature",
  "properties": {
    "addr:full":"130 S Spruce Avenue South San Francisco CA 94080",
    "addr:housenumber":"130",
    "addr:postcode":"94080",
    "addr:street":"S Spruce Avenue",
    "iso:country":"US",
    "sg:address":"130 S Spruce Avenue",
    "sg:city":"South San Francisco",
    "sg:classifiers":[
        {
            "category":"Food & Beverages",
            "subcategory":"Groceries & Convenience Stores",
            "type":"Retail Goods"
        }
    ],
    "sg:phone":"+1 650 583 9350",
    "sg:postcode":"94080",
    "sg:province":"CA",
    "wof:name":"Good & Rich Dairy",
    "wof:placetype":"venue"
},
  "geometry": {"coordinates":[-122.41819099999999,37.65063],"type":"Point"}
}