{
  "type": "Feature",
  "properties": {
    "addr:full":"30401 Jack Springs Rd Tehachapi CA 93561",
    "addr:housenumber":"30401",
    "addr:postcode":"93561",
    "addr:street":"Jack Springs Rd",
    "iso:country":"US",
    "sg:address":"30401 Jack Springs Rd",
    "sg:city":"Tehachapi",
    "sg:classifiers":[
        {
            "category":"Building & Trades",
            "subcategory":"Construction",
            "type":"Services"
        }
    ],
    "sg:phone":"+1 661 823 0921",
    "sg:postcode":"93561",
    "sg:province":"CA",
    "sg:tags":[
        "contractor"
    ],
    "wof:name":"Dressel Enterprises",
    "wof:placetype":"venue"
},
  "geometry": {"coordinates":[-118.672353,35.109476],"type":"Point"}
}