{
  "type": "Feature",
  "properties": {
    "iso:country":"US",
    "sg:address":"2410 5th Street",
    "sg:city":"Berkeley",
    "sg:classifiers":[
        {
            "category":"Building & Trades",
            "subcategory":"Electrical",
            "type":"Services"
        }
    ],
    "sg:phone":"+1 510 540 1915",
    "sg:postcode":"94710",
    "sg:province":"CA",
    "sg:tags":[
        "industrial",
        "electrician",
        "contractors-commercial",
        "electric"
    ],
    "wof:name":"Anson Electric Company",
    "wof:placetype":"venue"
},
  "geometry": {"coordinates":[-122.296997,37.861301],"type":"Point"}
}