{
  "type": "Feature",
  "properties": {
    "iso:country":"US",
    "sg:address":"3361 Penryn Rd",
    "sg:city":"Loomis",
    "sg:classifiers":[
        {
            "category":"Building & Trades",
            "subcategory":"Construction",
            "type":"Services"
        }
    ],
    "sg:phone":"+1 916 652 5337",
    "sg:postcode":"95650",
    "sg:province":"CA",
    "sg:tags":[
        "altering",
        "remodeling",
        "contractor"
    ],
    "wof:name":"Home Repair Service",
    "wof:placetype":"venue"
},
  "geometry": {"coordinates":[-121.168605,38.829222],"type":"Point"}
}