{
  "type": "Feature",
  "properties": {
    "addr:full":"545 J St Los Banos CA 93635",
    "addr:housenumber":"545",
    "addr:postcode":"93635",
    "addr:street":"J St",
    "iso:country":"US",
    "sg:address":"545 J St",
    "sg:city":"Los Banos",
    "sg:classifiers":[
        {
            "category":"Personal",
            "type":"Services"
        }
    ],
    "sg:phone":"+1 209 827 9288",
    "sg:postcode":"93635",
    "sg:province":"CA",
    "sg:tags":[
        "therapist",
        "massage"
    ],
    "wof:name":"Maria Borba",
    "wof:placetype":"venue"
},
  "geometry": {"coordinates":[-120.84953,37.060256],"type":"Point"}
}