{
  "type": "Feature",
  "properties": {
    "addr:full":"2501 White Ln Bakersfield CA 93304",
    "addr:housenumber":"2501",
    "addr:postcode":"93304",
    "addr:street":"White Ln",
    "iso:country":"US",
    "sg:address":"2501 White Ln",
    "sg:city":"Bakersfield",
    "sg:classifiers":[
        {
            "category":"Food & Beverages",
            "subcategory":"Groceries & Convenience Stores",
            "type":"Retail Goods"
        }
    ],
    "sg:phone":"+1 661 397 3722",
    "sg:postcode":"93304",
    "sg:province":"CA",
    "wof:name":"Lucky 7 Food Store",
    "wof:placetype":"venue"
},
  "geometry": {"coordinates":[-119.03160099999999,35.317675],"type":"Point"}
}