{
  "type": "Feature",
  "properties": {
    "iso:country":"US",
    "sg:address":"1090 Continental",
    "sg:city":"Redding",
    "sg:classifiers":[
        {
            "category":"Professional",
            "subcategory":"Art Services",
            "type":"Services"
        },
        {
            "category":"Professional",
            "subcategory":"Printing & Photocopies",
            "type":"Services"
        }
    ],
    "sg:phone":"+1 608 445 7881",
    "sg:postcode":"96001",
    "sg:province":"CA",
    "sg:tags":[
        "photographers-portrait",
        "graphic",
        "photographers-commercial",
        "designer"
    ],
    "wof:name":"Invisible Attributes Photography",
    "wof:placetype":"venue"
},
  "geometry": {"coordinates":[-122.387574,40.589999],"type":"Point"}
}