{
  "type": "Feature",
  "properties": {
    "addr:full":"400 Spruce St Gridley CA 95948",
    "addr:housenumber":"400",
    "addr:postcode":"95948",
    "addr:street":"Spruce St",
    "iso:country":"US",
    "sg:address":"400 Spruce St",
    "sg:city":"Gridley",
    "sg:classifiers":[
        {
            "category":"Organizations",
            "subcategory":"Religious Organization",
            "type":"Services"
        }
    ],
    "sg:phone":"+1 530 846 3921",
    "sg:postcode":"95948",
    "sg:province":"CA",
    "sg:tags":[
        "church"
    ],
    "wof:name":"Family History Ctr",
    "wof:placetype":"venue"
},
  "geometry": {"coordinates":[-121.692976,39.366709],"type":"Point"}
}