{
  "type": "Feature",
  "properties": {
    "addr:full":"3333 S Peach Ave Fresno CA 93725",
    "addr:housenumber":"3333",
    "addr:postcode":"93725",
    "addr:street":"S Peach Ave",
    "iso:country":"US",
    "sg:address":"3333 S Peach Ave",
    "sg:city":"Fresno",
    "sg:classifiers":[
        {
            "category":"Organizations",
            "subcategory":"Labor Organization",
            "type":"Services"
        }
    ],
    "sg:phone":"+1 559 264 5342",
    "sg:postcode":"93725",
    "sg:province":"CA",
    "wof:name":"United Steelworker America",
    "wof:placetype":"venue"
},
  "geometry": {"coordinates":[-119.71797100000001,36.68588],"type":"Point"}
}