{
  "type": "Feature",
  "properties": {
    "addr:full":"8787 Complex Dr San Diego CA 92123",
    "addr:housenumber":"8787",
    "addr:postcode":"92123",
    "addr:street":"Complex Dr",
    "iso:country":"US",
    "sg:address":"8787 Complex Dr",
    "sg:city":"San Diego",
    "sg:classifiers":[
        {
            "category":"Professional",
            "subcategory":"Research",
            "type":"Services"
        }
    ],
    "sg:phone":"+1 858 244 7328",
    "sg:postcode":"92123",
    "sg:province":"CA",
    "sg:tags":[
        "foundation",
        "philanthropic"
    ],
    "sg:website":"www.juniorseau.org",
    "wof:name":"Junior Seau Foundation",
    "wof:placetype":"venue"
},
  "geometry": {"coordinates":[-117.13515700000001,32.830078],"type":"Point"}
}