{
  "type": "Feature",
  "properties": {
    "addr:full":"2041 Mission College Blvd Santa Clara CA 95054",
    "addr:housenumber":"2041",
    "addr:postcode":"95054",
    "addr:street":"Mission College Blvd",
    "iso:country":"US",
    "sg:address":"2041 Mission College Blvd",
    "sg:city":"Santa Clara",
    "sg:classifiers":[
        {
            "category":"Professional",
            "subcategory":"Employment Agencies",
            "type":"Services"
        }
    ],
    "sg:phone":"+1 408 982 0262",
    "sg:postcode":"95054",
    "sg:province":"CA",
    "sg:website":"www.officepartners.com",
    "wof:name":"Office Partners",
    "wof:placetype":"venue"
},
  "geometry": {"coordinates":[-121.960999,37.3876],"type":"Point"}
}