{
  "type": "Feature",
  "properties": {
    "addr:full":"506 S Magnolia Ave El Cajon CA 92020",
    "addr:housenumber":"506",
    "addr:postcode":"92020",
    "addr:street":"S Magnolia Ave",
    "iso:country":"US",
    "sg:address":"506 S Magnolia Ave",
    "sg:city":"El Cajon",
    "sg:classifiers":[
        {
            "category":"Health Services",
            "subcategory":"Doctor",
            "type":"Services"
        }
    ],
    "sg:phone":"+1 619 588 2420",
    "sg:postcode":"92020",
    "sg:province":"CA",
    "sg:tags":[
        "dentist"
    ],
    "wof:name":"Renae L Wilson Inc",
    "wof:placetype":"venue"
},
  "geometry": {"coordinates":[-116.962394,32.789418],"type":"Point"}
}