{
  "type": "Feature",
  "properties": {
    "addr:full":"134 S Gaffey St San Pedro CA 90731",
    "addr:housenumber":"134",
    "addr:postcode":"90731",
    "addr:street":"S Gaffey St",
    "iso:country":"US",
    "sg:address":"134 S Gaffey St",
    "sg:city":"San Pedro",
    "sg:classifiers":[
        {
            "category":"Food & Beverages",
            "subcategory":"Bakery",
            "type":"Retail Goods"
        }
    ],
    "sg:phone":"+1 310 832 0113",
    "sg:postcode":"90731",
    "sg:province":"CA",
    "sg:tags":[
        "product",
        "mfg"
    ],
    "wof:name":"Fresh Donuts",
    "wof:placetype":"venue"
},
  "geometry": {"coordinates":[-118.292231,33.742678],"type":"Point"}
}