{
  "type": "Feature",
  "properties": {
    "iso:country":"US",
    "sg:address":"831 Riverside Ave",
    "sg:city":"Santa Cruz",
    "sg:classifiers":[
        {
            "category":"Health Services",
            "subcategory":"Doctor",
            "type":"Services"
        }
    ],
    "sg:phone":"+1 831 423 7858",
    "sg:postcode":"95060",
    "sg:province":"CA",
    "sg:tags":[
        "psychiatrist"
    ],
    "wof:name":"Hoban Evelyn RN Lcsw",
    "wof:placetype":"venue"
},
  "geometry": {"coordinates":[-122.022059,36.972861],"type":"Point"}
}