{
  "type": "Feature",
  "properties": {
    "addr:full":"4011 E Elizabeth St Compton CA 90221",
    "addr:housenumber":"4011",
    "addr:postcode":"90221",
    "addr:street":"E Elizabeth St",
    "iso:country":"US",
    "sg:address":"4011 E Elizabeth St",
    "sg:city":"Compton",
    "sg:classifiers":[
        {
            "category":"Real Estate",
            "subcategory":"Real Estate Agent",
            "type":"Services"
        }
    ],
    "sg:phone":"+1 310 632 9697",
    "sg:postcode":"90221",
    "sg:province":"CA",
    "wof:name":"Paramount RE & Property MGT",
    "wof:placetype":"venue"
},
  "geometry": {"coordinates":[-118.19911500000001,33.887919],"type":"Point"}
}