{
  "type": "Feature",
  "properties": {
    "addr:full":"510 Kelly St Half Moon Bay CA 94019",
    "addr:housenumber":"510",
    "addr:postcode":"94019",
    "addr:street":"Kelly St",
    "iso:country":"US",
    "sg:address":"510 Kelly St",
    "sg:city":"Half Moon Bay",
    "sg:classifiers":[
        {
            "category":"Building & Trades",
            "subcategory":"Construction",
            "type":"Services"
        }
    ],
    "sg:phone":"+1 650 726 8141",
    "sg:postcode":"94019",
    "sg:province":"CA",
    "sg:tags":[
        "resurfacing",
        "laying",
        "refinishing",
        "floor"
    ],
    "sg:website":"www.absolutefloors.com",
    "wof:name":"Absolute Flooring",
    "wof:placetype":"venue"
},
  "geometry": {"coordinates":[-122.431366,37.463766],"type":"Point"}
}