{
  "type": "Feature",
  "properties": {
    "addr:full":"15555 Huntington Village Ln Huntington Beach CA 92647",
    "addr:housenumber":"15555",
    "addr:postcode":"92647",
    "addr:street":"Huntington Village Ln",
    "iso:country":"US",
    "sg:address":"15555 Huntington Village Ln",
    "sg:city":"Huntington Beach",
    "sg:classifiers":[
        {
            "category":"Manufacturing",
            "subcategory":"Glass & Minerals",
            "type":"Manufacturing & Wholesale Goods"
        }
    ],
    "sg:phone":"+1 714 892 8517",
    "sg:postcode":"92647",
    "sg:province":"CA",
    "sg:tags":[
        "tile",
        "ceramic",
        "mfg"
    ],
    "wof:name":"R T Images",
    "wof:placetype":"venue"
},
  "geometry": {"coordinates":[-117.99603399999999,33.736159],"type":"Point"}
}