{
  "type": "Feature",
  "properties": {
    "addr:full":"2700 Merced St San Leandro CA 94579",
    "addr:housenumber":"2700",
    "addr:postcode":"94579",
    "addr:street":"Merced St",
    "iso:country":"US",
    "sg:address":"2700 Merced St",
    "sg:city":"San Leandro",
    "sg:classifiers":[
        {
            "category":"Social Services",
            "type":"Services"
        }
    ],
    "sg:phone":"+1 510 614 4477",
    "sg:postcode":"94579",
    "sg:province":"CA",
    "sg:tags":[
        "organization",
        "welfare"
    ],
    "wof:name":"Independent Way-Alameda Co",
    "wof:placetype":"venue"
},
  "geometry": {"coordinates":[-122.165879,37.701212],"type":"Point"}
}