{
  "type": "Feature",
  "properties": {
    "addr:full":"23360 Valencia Blvd Santa Clarita CA 91355",
    "addr:housenumber":"23360",
    "addr:postcode":"91355",
    "addr:street":"Valencia Blvd",
    "iso:country":"US",
    "sg:address":"23360 Valencia Blvd",
    "sg:city":"Santa Clarita",
    "sg:classifiers":[
        {
            "category":"Personal",
            "type":"Services"
        }
    ],
    "sg:phone":"+1 661 255 3131",
    "sg:postcode":"91355",
    "sg:province":"CA",
    "sg:tags":[
        "program",
        "physical",
        "exercise",
        "fitness"
    ],
    "sg:website":"www.fitcommitment.com",
    "wof:name":"Fit Commitment",
    "wof:placetype":"venue"
},
  "geometry": {"coordinates":[-118.546156,34.422263],"type":"Point"}
}