{
  "type": "Feature",
  "properties": {
    "iso:country":"US",
    "sg:address":"453 W Colorado St",
    "sg:city":"Glendale",
    "sg:classifiers":[
        {
            "category":"Retail",
            "subcategory":"Car Wash",
            "type":"Services"
        },
        {
            "category":"Retail",
            "subcategory":"Auto Repair",
            "type":"Services"
        }
    ],
    "sg:phone":"+1 818 500 0445",
    "sg:postcode":"91204",
    "sg:province":"CA",
    "sg:tags":[
        "automobile",
        "detailing"
    ],
    "sg:website":"www.california-detail.com/",
    "wof:name":"California Detail Shop",
    "wof:placetype":"venue"
},
  "geometry": {"coordinates":[-118.264,34.142399],"type":"Point"}
}