{
  "type": "Feature",
  "properties": {
    "addr:full":"300 28Th Avenue San Mateo, Ca 94403",
    "wof:categories":[
        "education_and_religion:education=school"
    ],
    "wof:name":"Beresford Elementary School",
    "wof:placetype":"venue"
},
  "geometry": {"coordinates":[-122.3091892944834,37.53914084445959],"type":"Point"}
}