{
  "type": "Feature",
  "properties": {
    "iso:country":"US",
    "sg:address":"5055 Wilshire Boulevard",
    "sg:city":"Los Angeles",
    "sg:classifiers":[
        {
            "category":"Communications",
            "subcategory":"Newspaper",
            "type":"Services"
        }
    ],
    "sg:phone":"+1 323 525 1752",
    "sg:postcode":"90036",
    "sg:province":"CA",
    "sg:tags":[
        "magazine"
    ],
    "wof:name":"Vnu",
    "wof:placetype":"venue"
},
  "geometry": {"coordinates":[-118.339833,34.062188],"type":"Point"}
}