{
  "type": "Feature",
  "properties": {
    "addr:full":"5636 Van Buren Blvd Riverside CA 92503",
    "addr:housenumber":"5636",
    "addr:postcode":"92503",
    "addr:street":"Van Buren Blvd",
    "iso:country":"US",
    "sg:address":"5636 Van Buren Blvd",
    "sg:city":"Riverside",
    "sg:classifiers":[
        {
            "category":"Shopping",
            "subcategory":"Gifts & Souvenirs",
            "type":"Retail Goods"
        }
    ],
    "sg:phone":"+1 951 637 0507",
    "sg:postcode":"92503",
    "sg:province":"CA",
    "sg:tags":[
        "party",
        "supply"
    ],
    "wof:name":"J R Party Supply",
    "wof:placetype":"venue"
},
  "geometry": {"coordinates":[-117.454005,33.941084],"type":"Point"}
}