{
  "type": "Feature",
  "properties": {
    "iso:country":"US",
    "sg:address":"495 E Perkins St",
    "sg:city":"Ukiah",
    "sg:classifiers":[
        {
            "category":"Real Estate",
            "subcategory":"Real Estate Agent",
            "type":"Services"
        }
    ],
    "sg:phone":"+1 707 468 0423",
    "sg:postcode":"95482",
    "sg:province":"CA",
    "sg:website":"www.d21.com",
    "wof:name":"Les Ryan Realty Property",
    "wof:placetype":"venue"
},
  "geometry": {"coordinates":[-123.202089,39.15079],"type":"Point"}
}