{
  "type": "Feature",
  "properties": {
    "iso:country":"US",
    "sg:address":"1768 W Roberts Ave",
    "sg:city":"Fresno",
    "sg:classifiers":[
        {
            "category":"Real Estate",
            "subcategory":"Real Estate Agent",
            "type":"Services"
        }
    ],
    "sg:phone":"+1 559 432 0132",
    "sg:postcode":"93711",
    "sg:province":"CA",
    "wof:name":"Pace Real Estate Brokerage",
    "wof:placetype":"venue"
},
  "geometry": {"coordinates":[-119.825102,36.820093],"type":"Point"}
}