{
  "type": "Feature",
  "properties": {
    "addr:full":"1050 Meadowbrook Ave Los Angeles CA 90019",
    "addr:housenumber":"1050",
    "addr:postcode":"90019",
    "addr:street":"Meadowbrook Ave",
    "iso:country":"US",
    "sg:address":"1050 Meadowbrook Ave",
    "sg:city":"Los Angeles",
    "sg:classifiers":[
        {
            "category":"Professional",
            "subcategory":"Management & Consulting",
            "type":"Services"
        }
    ],
    "sg:phone":"+1 323 930 0698",
    "sg:postcode":"90019",
    "sg:province":"CA",
    "sg:tags":[
        "retail",
        "direct",
        "sales"
    ],
    "wof:name":"White Telecommunications",
    "wof:placetype":"venue"
},
  "geometry": {"coordinates":[-118.34717499999999,34.05601],"type":"Point"}
}