{
  "type": "Feature",
  "properties": {
    "addr:full":"3739 W Chapman Ave Orange CA 92868",
    "addr:housenumber":"3739",
    "addr:postcode":"92868",
    "addr:street":"W Chapman Ave",
    "iso:country":"US",
    "sg:address":"3739 W Chapman Ave",
    "sg:city":"Orange",
    "sg:classifiers":[
        {
            "category":"Restaurant",
            "type":"Food & Drink"
        }
    ],
    "sg:menulink":"http://www.allmenus.com/ca/anaheim-santa-ana-garden-grove/174475-wendys/menu/",
    "sg:phone":"+1 714 385 1665",
    "sg:postcode":"92868",
    "sg:province":"CA",
    "sg:tags":[
        "burger",
        "american",
        "soup"
    ],
    "wof:name":"Wendy's",
    "wof:placetype":"venue"
},
  "geometry": {"coordinates":[-117.891976,33.789047],"type":"Point"}
}