{
  "type": "Feature",
  "properties": {
    "addr:full":"11451 N West Ln Lodi CA 95242",
    "addr:housenumber":"11451",
    "addr:postcode":"95242",
    "addr:street":"N West Ln",
    "iso:country":"US",
    "sg:address":"11451 N West Ln",
    "sg:city":"Lodi",
    "sg:classifiers":[
        {
            "category":"Organizations",
            "subcategory":"Religious Organization",
            "type":"Services"
        }
    ],
    "sg:phone":"+1 209 339 7333",
    "sg:postcode":"95242",
    "sg:province":"CA",
    "sg:tags":[
        "church"
    ],
    "sg:website":"www.thehomechurch.net",
    "wof:name":"Bible Baptist Church-Home Chr",
    "wof:placetype":"venue"
},
  "geometry": {"coordinates":[-121.287373,38.07523],"type":"Point"}
}