{
  "type": "Feature",
  "properties": {
    "addr:full":"24881 Alicia Pkwy Ste E254 Laguna Hills CA 92653",
    "addr:housenumber":"24881",
    "addr:postcode":"92653",
    "addr:street":"Alicia Pkwy Ste E254",
    "iso:country":"US",
    "sg:address":"24881 Alicia Pkwy Ste E254",
    "sg:city":"Laguna Hills",
    "sg:classifiers":[
        {
            "category":"Education",
            "subcategory":"Special Training",
            "type":"Public Place"
        }
    ],
    "sg:phone":"+1 949 698 6634",
    "sg:postcode":"92653",
    "sg:province":"CA",
    "sg:tags":[
        "tutor",
        "private"
    ],
    "sg:website":"experttutoring.posterous.com/",
    "wof:name":"Expert Tutoring",
    "wof:placetype":"venue"
},
  "geometry": {"coordinates":[-117.691373,33.601989],"type":"Point"}
}