{
  "type": "Feature",
  "properties": {
    "iso:country":"US",
    "sg:address":"5234 E Beverly Blvd",
    "sg:city":"Los Angeles",
    "sg:classifiers":[
        {
            "category":"Social Services",
            "type":"Services"
        }
    ],
    "sg:phone":"+1 323 728 9097",
    "sg:postcode":"90022",
    "sg:province":"CA",
    "sg:tags":[
        "organization",
        "welfare"
    ],
    "wof:name":"Calmecac Youth Ctr",
    "wof:placetype":"venue"
},
  "geometry": {"coordinates":[-118.153562,34.032061],"type":"Point"}
}