{
  "type": "Feature",
  "properties": {
    "iso:country":"US",
    "sg:address":"6863 Western Ave",
    "sg:city":"Buena Park",
    "sg:classifiers":[
        {
            "category":"Shopping",
            "subcategory":"Jewelry",
            "type":"Retail Goods"
        }
    ],
    "sg:phone":"+1 714 670 1034",
    "sg:postcode":"90621",
    "sg:province":"CA",
    "wof:name":"Michelle's Fine Jewelry & Coins",
    "wof:placetype":"venue"
},
  "geometry": {"coordinates":[-118.001999,33.861099],"type":"Point"}
}