{
  "type": "Feature",
  "properties": {
    "addr:full":"3438 El Camino Real Santa Clara CA 95051",
    "addr:housenumber":"3438",
    "addr:postcode":"95051",
    "addr:street":"El Camino Real",
    "iso:country":"US",
    "sg:address":"3438 El Camino Real",
    "sg:city":"Santa Clara",
    "sg:classifiers":[
        {
            "category":"Restaurant",
            "type":"Food & Drink"
        }
    ],
    "sg:phone":"+1 408 984 7718",
    "sg:postcode":"95051",
    "sg:province":"CA",
    "wof:name":"Song DO Restaurant",
    "wof:placetype":"venue"
},
  "geometry": {"coordinates":[-121.99099699999999,37.352402],"type":"Point"}
}