{
  "type": "Feature",
  "properties": {
    "addr:full":"1020 9th St Sacramento CA 95814",
    "addr:housenumber":"1020",
    "addr:postcode":"95814",
    "addr:street":"9Th St",
    "iso:country":"US",
    "sg:address":"1020 9th St",
    "sg:city":"Sacramento",
    "sg:classifiers":[
        {
            "category":"Government",
            "subcategory":"Office",
            "type":"Public Place"
        }
    ],
    "sg:phone":"+1 916 327 1551",
    "sg:postcode":"95814",
    "sg:province":"CA",
    "sg:tags":[
        "water",
        "control",
        "agency",
        "quality"
    ],
    "wof:name":"Flood Control Project Board",
    "wof:placetype":"venue"
},
  "geometry": {"coordinates":[-121.495045,38.58037],"type":"Point"}
}