{
  "type": "Feature",
  "properties": {
    "addr:full":"325 N 2nd Ave Upland CA 91786",
    "addr:housenumber":"325",
    "addr:postcode":"91786",
    "addr:street":"N 2Nd Ave",
    "iso:country":"US",
    "sg:address":"325 N 2nd Ave",
    "sg:city":"Upland",
    "sg:classifiers":[
        {
            "category":"Real Estate",
            "subcategory":"Real Estate Agent",
            "type":"Services"
        }
    ],
    "sg:phone":"+1 909 981 9003",
    "sg:postcode":"91786",
    "sg:province":"CA",
    "wof:name":"American Home Loan",
    "wof:placetype":"venue"
},
  "geometry": {"coordinates":[-117.648509,34.097611],"type":"Point"}
}