{
  "type": "Feature",
  "properties": {
    "iso:country":"US",
    "sg:address":"444 S Flower Street",
    "sg:city":"Los Angeles",
    "sg:classifiers":[
        {
            "category":"Professional",
            "subcategory":"Lawyer & Legal Services",
            "type":"Services"
        }
    ],
    "sg:phone":"+1 213 623 8645",
    "sg:postcode":"90071",
    "sg:province":"CA",
    "wof:name":"Wheeler & Sheehan",
    "wof:placetype":"venue"
},
  "geometry": {"coordinates":[-118.255431,34.05222],"type":"Point"}
}