{
  "type": "Feature",
  "properties": {
    "iso:country":"US",
    "sg:address":"1214 Lincoln Ave",
    "sg:city":"Alameda",
    "sg:classifiers":[
        {
            "category":"Personal",
            "subcategory":"Beauty Salon",
            "type":"Services"
        }
    ],
    "sg:phone":"+1 510 523 6245",
    "sg:postcode":"94501",
    "sg:province":"CA",
    "wof:name":"Lana's European Beauty Studio",
    "wof:placetype":"venue"
},
  "geometry": {"coordinates":[-122.263452,37.774647],"type":"Point"}
}