{
  "type": "Feature",
  "properties": {
    "iso:country":"US",
    "sg:address":"30029 Cll Belcanto",
    "sg:city":"Menifee",
    "sg:classifiers":[
        {
            "category":"Manufacturing",
            "subcategory":"Tools & Machinery",
            "type":"Manufacturing & Wholesale Goods"
        }
    ],
    "sg:phone":"+1 951 672 7447",
    "sg:postcode":"92584",
    "sg:province":"CA",
    "sg:tags":[
        "industry",
        "mfg"
    ],
    "wof:name":"K&B Enterprises",
    "wof:placetype":"venue"
},
  "geometry": {"coordinates":[-117.16330600000001,33.683558],"type":"Point"}
}