{
  "type": "Feature",
  "properties": {
    "iso:country":"US",
    "sg:address":"30 Rio Rancho Rd",
    "sg:city":"Pomona",
    "sg:classifiers":[
        {
            "category":"Restaurant",
            "type":"Food & Drink"
        }
    ],
    "sg:phone":"+1 909 620 1515",
    "sg:postcode":"91766",
    "sg:province":"CA",
    "wof:name":"Mc Donald's",
    "wof:placetype":"venue"
},
  "geometry": {"coordinates":[-117.75342000000001,34.033312],"type":"Point"}
}