{
  "type": "Feature",
  "properties": {
    "iso:country":"US",
    "sg:address":"1612 Grenoble Dr",
    "sg:city":"Woodland",
    "sg:classifiers":[
        {
            "category":"Manufacturing",
            "subcategory":"Petroleum Products",
            "type":"Manufacturing & Wholesale Goods"
        }
    ],
    "sg:phone":"+1 530 668 0988",
    "sg:postcode":"95695",
    "sg:province":"CA",
    "sg:tags":[
        "lubricating",
        "mfg"
    ],
    "wof:name":"Ultra Lemo Service",
    "wof:placetype":"venue"
},
  "geometry": {"coordinates":[-121.797334,38.660289],"type":"Point"}
}