{
  "type": "Feature",
  "properties": {
    "iso:country":"US",
    "sg:address":"777 N Palm Canyon Dr",
    "sg:city":"Palm Springs",
    "sg:classifiers":[
        {
            "category":"Insurance",
            "subcategory":"Insurance Agent",
            "type":"Services"
        }
    ],
    "sg:phone":"+1 760 416 8811",
    "sg:postcode":"92262",
    "sg:province":"CA",
    "wof:name":"R V Blanco & Assoc",
    "wof:placetype":"venue"
},
  "geometry": {"coordinates":[-116.54683799999999,33.833782],"type":"Point"}
}