{
  "type": "Feature",
  "properties": {
    "iso:country":"US",
    "sg:address":"2340 Irving St",
    "sg:city":"San Francisco",
    "sg:classifiers":[
        {
            "category":"Health Services",
            "subcategory":"Health Practitioner",
            "type":"Services"
        }
    ],
    "sg:phone":"+1 415 665 2230",
    "sg:postcode":"94122",
    "sg:province":"CA",
    "sg:tags":[
        "psychotherapist"
    ],
    "wof:name":"Lisa Frankfort",
    "wof:placetype":"venue"
},
  "geometry": {"coordinates":[-122.48321300000001,37.763373],"type":"Point"}
}