{
  "type": "Feature",
  "properties": {
    "iso:country":"US",
    "sg:address":"210 Industrial Rd",
    "sg:city":"San Carlos",
    "sg:classifiers":[
        {
            "category":"Taxi",
            "type":"Transportation"
        }
    ],
    "sg:phone":"+1 650 591 5400",
    "sg:postcode":"94070",
    "sg:province":"CA",
    "sg:website":"www.baycitiestaxi.com",
    "wof:name":"Bay Cities Taxi Cab",
    "wof:placetype":"venue"
},
  "geometry": {"coordinates":[-122.26518299999999,37.517977],"type":"Point"}
}