{
  "type": "Feature",
  "properties": {
    "addr:full":"117 W 9th Street Suite 111 Los Angeles CA 90015",
    "addr:housenumber":"117",
    "addr:postcode":"90015",
    "addr:street":"W 9Th Street Suite 111",
    "iso:country":"US",
    "sg:address":"117 W 9th Street Suite 111",
    "sg:city":"Los Angeles",
    "sg:classifiers":[
        {
            "category":"Shopping",
            "subcategory":"Clothing, Apparel, & Fashions",
            "type":"Retail Goods"
        }
    ],
    "sg:phone":"+1 213 614 0199",
    "sg:postcode":"90015",
    "sg:province":"CA",
    "sg:tags":[
        "accessory",
        "clothing",
        "women's"
    ],
    "wof:name":"World Lob Clothing",
    "wof:placetype":"venue"
},
  "geometry": {"coordinates":[-118.25761300000001,34.043325],"type":"Point"}
}