{
  "type": "Feature",
  "properties": {
    "addr:full":"18022 Cowan Irvine CA 92614",
    "addr:housenumber":"18022",
    "addr:postcode":"92614",
    "addr:street":"Cowan",
    "iso:country":"US",
    "sg:address":"18022 Cowan",
    "sg:city":"Irvine",
    "sg:classifiers":[
        {
            "category":"Insurance",
            "subcategory":"Insurance Agent",
            "type":"Services"
        }
    ],
    "sg:phone":"+1 949 863 1777",
    "sg:postcode":"92614",
    "sg:province":"CA",
    "wof:name":"JTI Insurance Assoc Inc",
    "wof:placetype":"venue"
},
  "geometry": {"coordinates":[-117.86549100000001,33.690322],"type":"Point"}
}