{
  "type": "Feature",
  "properties": {
    "addr:full":"5333 Cochran St Simi Valley CA 93063",
    "addr:housenumber":"5333",
    "addr:postcode":"93063",
    "addr:street":"Cochran St",
    "iso:country":"US",
    "sg:address":"5333 Cochran St",
    "sg:city":"Simi Valley",
    "sg:classifiers":[
        {
            "category":"Real Estate",
            "subcategory":"Real Estate Operator",
            "type":"Services"
        }
    ],
    "sg:phone":"+1 805 522 6803",
    "sg:postcode":"93063",
    "sg:province":"CA",
    "sg:tags":[
        "apartment"
    ],
    "wof:name":"Americana Simi Valley",
    "wof:placetype":"venue"
},
  "geometry": {"coordinates":[-118.69018800000001,34.279069],"type":"Point"}
}