{
  "type": "Feature",
  "properties": {
    "addr:full":"5838 Alcazar Dr San Jose CA 95123",
    "addr:housenumber":"5838",
    "addr:postcode":"95123",
    "addr:street":"Alcazar Dr",
    "iso:country":"US",
    "sg:address":"5838 Alcazar Dr",
    "sg:city":"San Jose",
    "sg:classifiers":[
        {
            "category":"Building & Trades",
            "subcategory":"Construction",
            "type":"Services"
        }
    ],
    "sg:phone":"+1 408 316 9977",
    "sg:postcode":"95123",
    "sg:province":"CA",
    "sg:tags":[
        "hanging",
        "contractor"
    ],
    "wof:name":"Color Your Home",
    "wof:placetype":"venue"
},
  "geometry": {"coordinates":[-121.84389,37.244898],"type":"Point"}
}