{
  "type": "Feature",
  "properties": {
    "addr:full":"44 Lotus Ct Novato CA 94945",
    "addr:housenumber":"44",
    "addr:postcode":"94945",
    "addr:street":"Lotus Ct",
    "iso:country":"US",
    "sg:address":"44 Lotus Ct",
    "sg:city":"Novato",
    "sg:classifiers":[
        {
            "category":"Professional",
            "subcategory":"Employment Agencies",
            "type":"Services"
        }
    ],
    "sg:phone":"+1 415 893 9580",
    "sg:postcode":"94945",
    "sg:province":"CA",
    "sg:tags":[
        "opportunity"
    ],
    "wof:name":"Ottolia Connection",
    "wof:placetype":"venue"
},
  "geometry": {"coordinates":[-122.569036,38.11634],"type":"Point"}
}