{
  "type": "Feature",
  "properties": {
    "addr:full":"11672 Tuxford St Sun Valley CA 91352",
    "addr:housenumber":"11672",
    "addr:postcode":"91352",
    "addr:street":"Tuxford St",
    "iso:country":"US",
    "sg:address":"11672 Tuxford St",
    "sg:city":"Sun Valley",
    "sg:classifiers":[
        {
            "category":"Utilities",
            "subcategory":"Cable",
            "type":"Services"
        }
    ],
    "sg:phone":"+1 818 768 5161",
    "sg:postcode":"91352",
    "sg:province":"CA",
    "sg:tags":[
        "electronics",
        "television"
    ],
    "sg:website":"www.pansatusa.com",
    "wof:name":"Panarex Electronic",
    "wof:placetype":"venue"
},
  "geometry": {"coordinates":[-118.387001,34.223],"type":"Point"}
}