{
  "type": "Feature",
  "properties": {
    "addr:full":"919 Cerritos Ave Long Beach CA 90813",
    "addr:housenumber":"919",
    "addr:postcode":"90813",
    "addr:street":"Cerritos Ave",
    "iso:country":"US",
    "sg:address":"919 Cerritos Ave",
    "sg:city":"Long Beach",
    "sg:classifiers":[
        {
            "category":"Professional",
            "type":"Services"
        }
    ],
    "sg:phone":"+1 562 218 7931",
    "sg:postcode":"90813",
    "sg:province":"CA",
    "wof:name":"Brenda Velasquez",
    "wof:placetype":"venue"
},
  "geometry": {"coordinates":[-118.178116,33.777757],"type":"Point"}
}