{
  "type": "Feature",
  "properties": {
    "iso:country":"US",
    "sg:address":"1208 E Arques Ave Ste 108",
    "sg:city":"Sunnyvale",
    "sg:classifiers":[
        {
            "category":"Insurance",
            "subcategory":"Hazard Insurance",
            "type":"Services"
        },
        {
            "category":"Professional",
            "subcategory":"Lawyer & Legal Services",
            "type":"Services"
        }
    ],
    "sg:phone":"+1 408 739 8300",
    "sg:postcode":"94085",
    "sg:province":"CA",
    "sg:tags":[
        "notary"
    ],
    "sg:website":"asibrokers.com/",
    "wof:name":"All Spectrum Insurance Brokers",
    "wof:placetype":"venue"
},
  "geometry": {"coordinates":[-121.99467,37.380442],"type":"Point"}
}