{
  "type": "Feature",
  "properties": {
    "iso:country":"US",
    "sg:address":"2143 Verdugo Blvd",
    "sg:city":"Montrose",
    "sg:classifiers":[
        {
            "category":"Food & Beverages",
            "subcategory":"Liquor & Beverages",
            "type":"Retail Goods"
        }
    ],
    "sg:phone":"+1 818 249 6119",
    "sg:postcode":"91020",
    "sg:province":"CA",
    "sg:tags":[
        "beer",
        "spirit",
        "store",
        "wine"
    ],
    "wof:name":"Verdugo Liquor",
    "wof:placetype":"venue"
},
  "geometry": {"coordinates":[-118.22399900000001,34.2048],"type":"Point"}
}