{
  "type": "Feature",
  "properties": {
    "iso:country":"US",
    "sg:address":"736 Mariposa Rd",
    "sg:city":"Modesto",
    "sg:classifiers":[
        {
            "category":"Freight",
            "type":"Transportation"
        }
    ],
    "sg:phone":"+1 209 575 1810",
    "sg:postcode":"95354",
    "sg:province":"CA",
    "sg:tags":[
        "general"
    ],
    "wof:name":"Priority 1 Warehousing",
    "wof:placetype":"venue"
},
  "geometry": {"coordinates":[-120.934253,37.62594],"type":"Point"}
}