{
  "type": "Feature",
  "properties": {
    "addr:full":"1017 N La Cienega Boulevard Los Angeles CA 90069",
    "addr:housenumber":"1017",
    "addr:postcode":"90069",
    "addr:street":"N La Cienega Boulevard",
    "iso:country":"US",
    "sg:address":"1017 N La Cienega Boulevard",
    "sg:city":"Los Angeles",
    "sg:classifiers":[
        {
            "category":"Real Estate",
            "subcategory":"Real Estate Services",
            "type":"Services"
        }
    ],
    "sg:phone":"+1 310 659 4500",
    "sg:postcode":"90069",
    "sg:province":"CA",
    "sg:tags":[
        "management",
        "property"
    ],
    "wof:name":"Atlas Management Company.",
    "wof:placetype":"venue"
},
  "geometry": {"coordinates":[-118.376311,34.089744],"type":"Point"}
}