{
  "type": "Feature",
  "properties": {
    "addr:full":"8905 Davis Rd Stockton CA 95209",
    "addr:housenumber":"8905",
    "addr:postcode":"95209",
    "addr:street":"Davis Rd",
    "iso:country":"US",
    "sg:address":"8905 Davis Rd",
    "sg:city":"Stockton",
    "sg:classifiers":[
        {
            "category":"Professional",
            "type":"Services"
        },
        {
            "category":"Social Services",
            "type":"Services"
        }
    ],
    "sg:phone":"+1 209 473 3243",
    "sg:postcode":"95209",
    "sg:province":"CA",
    "sg:tags":[
        "housing",
        "assistance"
    ],
    "wof:name":"Uplift Foundation",
    "wof:placetype":"venue"
},
  "geometry": {"coordinates":[-121.331839,38.030359],"type":"Point"}
}