{
  "type": "Feature",
  "properties": {
    "iso:country":"US",
    "sg:address":"622 W Duarte Rd",
    "sg:city":"Arcadia",
    "sg:classifiers":[
        {
            "category":"Health Services",
            "subcategory":"Doctor",
            "type":"Services"
        }
    ],
    "sg:phone":"+1 626 447 3223",
    "sg:postcode":"91007",
    "sg:province":"CA",
    "wof:name":"Chow Center For Facial Plastic Surgery",
    "wof:placetype":"venue"
},
  "geometry": {"coordinates":[-118.208107,34.126319],"type":"Point"}
}