{
  "type": "Feature",
  "properties": {
    "iso:country":"US",
    "sg:address":"9388 W Telephone Rd",
    "sg:city":"Ventura",
    "sg:classifiers":[
        {
            "category":"Sports & Exercise",
            "subcategory":"Gym",
            "type":"Entertainment"
        }
    ],
    "sg:phone":"+1 805 647 5657",
    "sg:postcode":"93004",
    "sg:province":"CA",
    "sg:tags":[
        "club",
        "health",
        "studio",
        "gymnasium"
    ],
    "wof:name":"Club Energy",
    "wof:placetype":"venue"
},
  "geometry": {"coordinates":[-119.17213599999999,34.271294],"type":"Point"}
}