{
  "type": "Feature",
  "properties": {
    "iso:country":"US",
    "sg:address":"210 E Olympic Boulevard",
    "sg:city":"Los Angeles",
    "sg:classifiers":[
        {
            "category":"Shopping",
            "subcategory":"Clothing, Apparel, & Fashions",
            "type":"Retail Goods"
        },
        {
            "category":"Banks & Credit Unions",
            "subcategory":"Financial Services",
            "type":"Services"
        }
    ],
    "sg:phone":"+1 213 746 4144",
    "sg:postcode":"90015",
    "sg:province":"CA",
    "sg:tags":[
        "clothing",
        "broker",
        "mortgage",
        "women's"
    ],
    "wof:name":"Studio Zonkers",
    "wof:placetype":"venue"
},
  "geometry": {"coordinates":[-118.271538,34.039118],"type":"Point"}
}