{
  "type": "Feature",
  "properties": {
    "addr:full":"2772 Hostetter Rd San Jose CA 95132",
    "addr:housenumber":"2772",
    "addr:postcode":"95132",
    "addr:street":"Hostetter Rd",
    "iso:country":"US",
    "sg:address":"2772 Hostetter Rd",
    "sg:city":"San Jose",
    "sg:classifiers":[
        {
            "category":"Professional",
            "subcategory":"Management & Consulting",
            "type":"Services"
        }
    ],
    "sg:phone":"+1 408 272 8388",
    "sg:postcode":"95132",
    "sg:province":"CA",
    "sg:tags":[
        "consultant",
        "business"
    ],
    "wof:name":"United Vision Intl",
    "wof:placetype":"venue"
},
  "geometry": {"coordinates":[-121.866607,37.399725],"type":"Point"}
}