{
  "type": "Feature",
  "properties": {
    "iso:country":"US",
    "sg:address":"240 E Robertson Blvd",
    "sg:city":"Chowchilla",
    "sg:classifiers":[
        {
            "category":"Autos & Motor Vehicles",
            "subcategory":"Fuel & Gas Station",
            "type":"Retail Goods"
        }
    ],
    "sg:phone":"+1 559 665 3339",
    "sg:postcode":"93610",
    "sg:province":"CA",
    "sg:tags":[
        "oil"
    ],
    "sg:website":"http://www.chevron.com",
    "wof:name":"Chevron Chowchilla",
    "wof:placetype":"venue"
},
  "geometry": {"coordinates":[-120.26041499999999,37.122548],"type":"Point"}
}