{
  "type": "Feature",
  "properties": {
    "addr:full":"8727 Cranford Ave Sun Valley CA 91352",
    "addr:housenumber":"8727",
    "addr:postcode":"91352",
    "addr:street":"Cranford Ave",
    "iso:country":"US",
    "sg:address":"8727 Cranford Ave",
    "sg:city":"Sun Valley",
    "sg:classifiers":[
        {
            "category":"Local Transit",
            "type":"Transportation"
        }
    ],
    "sg:phone":"+1 818 768 3303",
    "sg:postcode":"91352",
    "sg:province":"CA",
    "sg:tags":[
        "passenger",
        "limousine"
    ],
    "wof:name":"One Dream Limousine Service",
    "wof:placetype":"venue"
},
  "geometry": {"coordinates":[-118.40358000000001,34.227646],"type":"Point"}
}