{
  "type": "Feature",
  "properties": {
    "iso:country":"US",
    "sg:address":"8 Hearst",
    "sg:city":"Aliso Viejo",
    "sg:classifiers":[
        {
            "category":"Shopping",
            "subcategory":"Clothing, Apparel, & Fashions",
            "type":"Retail Goods"
        }
    ],
    "sg:phone":"+1 949 643 0549",
    "sg:postcode":"92656",
    "sg:province":"CA",
    "wof:name":"Venerdis By Berdy",
    "wof:placetype":"venue"
},
  "geometry": {"coordinates":[-117.733242,33.579936],"type":"Point"}
}