{
  "type": "Feature",
  "properties": {
    "iso:country":"US",
    "sg:address":"10650 Scripps Ranch Blvd",
    "sg:city":"San Diego",
    "sg:classifiers":[
        {
            "category":"Professional",
            "subcategory":"Management & Consulting",
            "type":"Services"
        }
    ],
    "sg:phone":"+1 858 578 0252",
    "sg:postcode":"92131",
    "sg:province":"CA",
    "sg:tags":[
        "counselor",
        "public",
        "relations"
    ],
    "wof:name":"Allan Rosse & Assoc",
    "wof:placetype":"venue"
},
  "geometry": {"coordinates":[-117.110101,32.913082],"type":"Point"}
}