{
  "type": "Feature",
  "properties": {
    "iso:country":"US",
    "sg:address":"2124 Center St",
    "sg:city":"Berkeley",
    "sg:classifiers":[
        {
            "category":"Food & Beverages",
            "subcategory":"Bakery",
            "type":"Retail Goods"
        }
    ],
    "sg:phone":"+1 510 540 7431",
    "sg:postcode":"94704",
    "sg:province":"CA",
    "sg:tags":[
        "baker"
    ],
    "wof:name":"Cafe Neutron Bakery",
    "wof:placetype":"venue"
},
  "geometry": {"coordinates":[-122.267126,37.870359],"type":"Point"}
}