{
  "type": "Feature",
  "properties": {
    "iso:country":"US",
    "sg:address":"1258 W Betteravia Rd",
    "sg:city":"Santa Maria",
    "sg:classifiers":[
        {
            "category":"Wholesale",
            "subcategory":"Machinery & Supplies",
            "type":"Manufacturing & Wholesale Goods"
        }
    ],
    "sg:phone":"+1 805 347 7878",
    "sg:postcode":"93455",
    "sg:province":"CA",
    "sg:tags":[
        "truck"
    ],
    "wof:name":"Madland Toyota Lift-Inc",
    "wof:placetype":"venue"
},
  "geometry": {"coordinates":[-120.45626799999999,34.920533],"type":"Point"}
}