{
  "type": "Feature",
  "properties": {
    "iso:country":"US",
    "sg:address":"893 E El Camino Real",
    "sg:city":"Sunnyvale",
    "sg:classifiers":[
        {
            "category":"Restaurant",
            "type":"Food & Drink"
        }
    ],
    "sg:postcode":"94086",
    "sg:province":"CA",
    "sg:website":"www.tikkamasala.us",
    "wof:name":"Tikka Masala",
    "wof:placetype":"venue"
},
  "geometry": {"coordinates":[-122.016604,37.354969],"type":"Point"}
}