{
  "type": "Feature",
  "properties": {
    "addr:full":"2226 Fern St San Diego CA 92104",
    "addr:housenumber":"2226",
    "addr:postcode":"92104",
    "addr:street":"Fern St",
    "iso:country":"US",
    "sg:address":"2226 Fern St",
    "sg:city":"San Diego",
    "sg:classifiers":[
        {
            "category":"Education",
            "subcategory":"Special Training",
            "type":"Public Place"
        }
    ],
    "sg:phone":"+1 619 987 4834",
    "sg:postcode":"92104",
    "sg:province":"CA",
    "sg:tags":[
        "school",
        "specialty"
    ],
    "sg:website":"www.babygartenstudio.com",
    "wof:name":"Baby Garten Studio",
    "wof:placetype":"venue"
},
  "geometry": {"coordinates":[-117.129639,32.729164],"type":"Point"}
}