{
  "type": "Feature",
  "properties": {
    "iso:country":"US",
    "sg:address":"31 Fortune Dr Ste 204",
    "sg:city":"Irvine",
    "sg:classifiers":[
        {
            "category":"Juice Bar",
            "subcategory":"None",
            "type":"Food & Drink"
        },
        {
            "category":"Restaurant",
            "type":"Food & Drink"
        }
    ],
    "sg:phone":"+1 949 453 0403",
    "sg:postcode":"92618",
    "sg:province":"CA",
    "sg:tags":[
        "smoothy"
    ],
    "wof:name":"Rollerz",
    "wof:placetype":"venue"
},
  "geometry": {"coordinates":[-117.746002,33.653198],"type":"Point"}
}