{
  "type": "Feature",
  "properties": {
    "iso:country":"US",
    "sg:address":"2440 Toyon Way",
    "sg:city":"San Bruno",
    "sg:classifiers":[
        {
            "category":"Building & Trades",
            "subcategory":"Construction",
            "type":"Services"
        }
    ],
    "sg:phone":"+1 650 872 1995",
    "sg:postcode":"94066",
    "sg:province":"CA",
    "sg:tags":[
        "contractor"
    ],
    "wof:name":"Fernando's Construction",
    "wof:placetype":"venue"
},
  "geometry": {"coordinates":[-122.44119999999999,37.6285],"type":"Point"}
}