{
  "type": "Feature",
  "properties": {
    "addr:full":"10921 Wilshire Boulevard Suite 505 Los Angeles CA 90024",
    "addr:housenumber":"10921",
    "addr:postcode":"90024",
    "addr:street":"Wilshire Boulevard Suite 505",
    "iso:country":"US",
    "sg:address":"10921 Wilshire Boulevard Suite 505",
    "sg:city":"Los Angeles",
    "sg:classifiers":[
        {
            "category":"Health Services",
            "subcategory":"Dentist",
            "type":"Services"
        }
    ],
    "sg:phone":"+1 310 824 0055",
    "sg:postcode":"90024",
    "sg:province":"CA",
    "sg:website":"www.westladentist.com",
    "wof:name":"Woodside Dental",
    "wof:placetype":"venue"
},
  "geometry": {"coordinates":[-118.44547,34.058562],"type":"Point"}
}