{
  "type": "Feature",
  "properties": {
    "addr:full":"1940 W Pacific Coast Hwy Long Beach CA 90810",
    "addr:housenumber":"1940",
    "addr:postcode":"90810",
    "addr:street":"W Pacific Coast Hwy",
    "iso:country":"US",
    "sg:address":"1940 W Pacific Coast Hwy",
    "sg:city":"Long Beach",
    "sg:classifiers":[
        {
            "category":"Travel",
            "subcategory":"Hotels & Motels",
            "type":"Entertainment"
        }
    ],
    "sg:phone":"+1 562 436 1116",
    "sg:postcode":"90810",
    "sg:province":"CA",
    "wof:name":"Sea Breeze Motel",
    "wof:placetype":"venue"
},
  "geometry": {"coordinates":[-118.218002,33.790001],"type":"Point"}
}