{
  "type": "Feature",
  "properties": {
    "iso:country":"US",
    "sg:address":"117 N Broadway",
    "sg:city":"Santa Ana",
    "sg:classifiers":[
        {
            "category":"Home & Garden",
            "subcategory":"Furniture",
            "type":"Retail Goods"
        }
    ],
    "sg:phone":"+1 714 560 1199",
    "sg:postcode":"92701",
    "sg:province":"CA",
    "sg:tags":[
        "store"
    ],
    "wof:name":"Dearden's",
    "wof:placetype":"venue"
},
  "geometry": {"coordinates":[-117.870003,33.7458],"type":"Point"}
}