{
  "type": "Feature",
  "properties": {
    "addr:full":"2131 Riesling Ct Pittsburg CA 94565",
    "addr:housenumber":"2131",
    "addr:postcode":"94565",
    "addr:street":"Riesling Ct",
    "iso:country":"US",
    "sg:address":"2131 Riesling Ct",
    "sg:city":"Pittsburg",
    "sg:classifiers":[
        {
            "category":"Building & Trades",
            "subcategory":"Construction",
            "type":"Services"
        }
    ],
    "sg:phone":"+1 925 439 3515",
    "sg:postcode":"94565",
    "sg:province":"CA",
    "sg:tags":[
        "repair",
        "handyman",
        "maintenance",
        "home"
    ],
    "wof:name":"Bay Area Handyman",
    "wof:placetype":"venue"
},
  "geometry": {"coordinates":[-121.92318,38.016851],"type":"Point"}
}