{
  "type": "Feature",
  "properties": {
    "iso:country":"US",
    "sg:address":"3667 N 7th St",
    "sg:city":"Fresno",
    "sg:classifiers":[
        {
            "category":"Professional",
            "subcategory":"Art Services",
            "type":"Services"
        }
    ],
    "sg:phone":"+1 559 222 7975",
    "sg:postcode":"93726",
    "sg:province":"CA",
    "sg:tags":[
        "graphic",
        "designer"
    ],
    "wof:name":"I Visual Designs",
    "wof:placetype":"venue"
},
  "geometry": {"coordinates":[-119.76178299999999,36.784796],"type":"Point"}
}