{
  "type": "Feature",
  "properties": {
    "addr:full":"1157 3rd St Manhattan Beach CA 90266",
    "addr:housenumber":"1157",
    "addr:postcode":"90266",
    "addr:street":"3Rd St",
    "iso:country":"US",
    "sg:address":"1157 3rd St",
    "sg:city":"Manhattan Beach",
    "sg:classifiers":[
        {
            "category":"Manufacturing",
            "subcategory":"Printing",
            "type":"Manufacturing & Wholesale Goods"
        }
    ],
    "sg:phone":"+1 310 374 0894",
    "sg:postcode":"90266",
    "sg:province":"CA",
    "sg:tags":[
        "commercial"
    ],
    "wof:name":"Celebrations & Tributes",
    "wof:placetype":"venue"
},
  "geometry": {"coordinates":[-118.394408,33.881006],"type":"Point"}
}