{
  "type": "Feature",
  "properties": {
    "addr:full":"2105 Landings Drive Mountain View CA 94043",
    "addr:housenumber":"2105",
    "addr:postcode":"94043",
    "addr:street":"Landings Drive",
    "iso:country":"US",
    "sg:address":"2105 Landings Drive",
    "sg:city":"Mountain View",
    "sg:classifiers":[
        {
            "category":"Professional",
            "subcategory":"Computer Services",
            "type":"Services"
        }
    ],
    "sg:phone":"+1 650 930 9710",
    "sg:postcode":"94043",
    "sg:province":"CA",
    "sg:website":"http://www.ivalua.com",
    "wof:name":"Ivalua",
    "wof:placetype":"venue"
},
  "geometry": {"coordinates":[-122.09031400000001,37.421089],"type":"Point"}
}