{
  "type": "Feature",
  "properties": {
    "addr:full":"1110 N Dutton Ave Santa Rosa CA 95401",
    "addr:housenumber":"1110",
    "addr:postcode":"95401",
    "addr:street":"N Dutton Ave",
    "iso:country":"US",
    "sg:address":"1110 N Dutton Ave",
    "sg:city":"Santa Rosa",
    "sg:classifiers":[
        {
            "category":"Health Services",
            "subcategory":"Clinic",
            "type":"Services"
        }
    ],
    "sg:phone":"+1 707 542 5045",
    "sg:postcode":"95401",
    "sg:province":"CA",
    "sg:tags":[
        "home"
    ],
    "wof:name":"Sutter VNA & Hospice",
    "wof:placetype":"venue"
},
  "geometry": {"coordinates":[-122.731629,38.448042],"type":"Point"}
}