{
  "type": "Feature",
  "properties": {
    "iso:country":"US",
    "sg:address":"6236 Main Ave",
    "sg:city":"Orangevale",
    "sg:classifiers":[
        {
            "category":"Communications",
            "subcategory":"Film & Video Production",
            "type":"Services"
        },
        {
            "category":"Shopping",
            "subcategory":"Bicycles & Sporting Goods",
            "type":"Retail Goods"
        }
    ],
    "sg:phone":"+1 916 989 5438",
    "sg:postcode":"95662",
    "sg:province":"CA",
    "sg:tags":[
        "motion",
        "equipment",
        "diver",
        "supply"
    ],
    "sg:website":"www.underseavideo.com",
    "wof:name":"Under Sea Video",
    "wof:placetype":"venue"
},
  "geometry": {"coordinates":[-121.202212,38.678949],"type":"Point"}
}