{
  "type": "Feature",
  "properties": {
    "iso:country":"US",
    "sg:address":"411 S Yorba St",
    "sg:city":"Orange",
    "sg:classifiers":[
        {
            "category":"Wholesale",
            "subcategory":"Durable Goods & Equipment",
            "type":"Manufacturing & Wholesale Goods"
        }
    ],
    "sg:phone":"+1 714 633 8683",
    "sg:postcode":"92869",
    "sg:province":"CA",
    "wof:name":"Trb Tool Supply",
    "wof:placetype":"venue"
},
  "geometry": {"coordinates":[-117.827127,33.78213],"type":"Point"}
}