{
  "type": "Feature",
  "properties": {
    "iso:country":"US",
    "sg:address":"2618 Montana Ave",
    "sg:city":"Santa Monica",
    "sg:classifiers":[
        {
            "category":"Manufacturing",
            "subcategory":"Printing",
            "type":"Manufacturing & Wholesale Goods"
        }
    ],
    "sg:phone":"+1 310 829 9790",
    "sg:postcode":"90403",
    "sg:province":"CA",
    "sg:tags":[
        "consulting",
        "publishing",
        "business"
    ],
    "wof:name":"K & A Press",
    "wof:placetype":"venue"
},
  "geometry": {"coordinates":[-118.48283499999999,34.042187],"type":"Point"}
}