{
  "type": "Feature",
  "properties": {
    "iso:country":"US",
    "sg:address":"9690 Stackhouse Ln",
    "sg:city":"Oregon House",
    "sg:classifiers":[
        {
            "category":"Manufacturing",
            "subcategory":"Printing",
            "type":"Manufacturing & Wholesale Goods"
        }
    ],
    "sg:phone":"+1 530 692 9531",
    "sg:postcode":"95962",
    "sg:province":"CA",
    "sg:tags":[
        "periodical"
    ],
    "wof:name":"Petrarch Press",
    "wof:placetype":"venue"
},
  "geometry": {"coordinates":[-121.251438,39.318553],"type":"Point"}
}