{
  "type": "Feature",
  "properties": {
    "iso:country":"US",
    "sg:address":"1455 Northhill St",
    "sg:city":"Selma",
    "sg:classifiers":[
        {
            "category":"Professional",
            "subcategory":"Detective & Security Services",
            "type":"Services"
        }
    ],
    "sg:phone":"+1 559 898 0432",
    "sg:postcode":"93662",
    "sg:province":"CA",
    "sg:tags":[
        "guard",
        "patrol"
    ],
    "wof:name":"Thomas Security Agency",
    "wof:placetype":"venue"
},
  "geometry": {"coordinates":[-119.604901,36.586627],"type":"Point"}
}