{
  "type": "Feature",
  "properties": {
    "iso:country":"US",
    "sg:address":"5420 Mission St",
    "sg:city":"San Francisco",
    "sg:classifiers":[
        {
            "category":"Food & Beverages",
            "subcategory":"Groceries & Convenience Stores",
            "type":"Retail Goods"
        }
    ],
    "sg:phone":"+1 415 334 7752",
    "sg:postcode":"94112",
    "sg:province":"CA",
    "sg:tags":[
        "grocer"
    ],
    "wof:name":"Handaan Food Ctr",
    "wof:placetype":"venue"
},
  "geometry": {"coordinates":[-122.443879,37.713564],"type":"Point"}
}