{
  "type": "Feature",
  "properties": {
    "iso:country":"US",
    "sg:address":"2235 Beverly Blvd",
    "sg:city":"Los Angeles",
    "sg:classifiers":[
        {
            "category":"Organizations",
            "subcategory":"Religious Organization",
            "type":"Services"
        }
    ],
    "sg:phone":"+1 213 484 1722",
    "sg:postcode":"90057",
    "sg:province":"CA",
    "wof:name":"Praise Christian Fellowship of Los Angeles",
    "wof:placetype":"venue"
},
  "geometry": {"coordinates":[-118.272003,34.067501],"type":"Point"}
}