{
  "type": "Feature",
  "properties": {
    "addr:full":"16110 S Figueroa St Gardena CA 90248",
    "addr:housenumber":"16110",
    "addr:postcode":"90248",
    "addr:street":"S Figueroa St",
    "iso:country":"US",
    "sg:address":"16110 S Figueroa St",
    "sg:city":"Gardena",
    "sg:classifiers":[
        {
            "category":"Manufacturing",
            "subcategory":"Tools & Machinery",
            "type":"Manufacturing & Wholesale Goods"
        }
    ],
    "sg:phone":"+1 310 366 5999",
    "sg:postcode":"90248",
    "sg:province":"CA",
    "sg:tags":[
        "filtering",
        "material",
        "supply"
    ],
    "wof:name":"Permaflow Inc",
    "wof:placetype":"venue"
},
  "geometry": {"coordinates":[-118.282652,33.885447],"type":"Point"}
}