{
  "type": "Feature",
  "properties": {
    "iso:country":"US",
    "sg:address":"330 Ignacio Blvd",
    "sg:city":"Novato",
    "sg:classifiers":[
        {
            "category":"Manufacturing",
            "subcategory":"Food",
            "type":"Manufacturing & Wholesale Goods"
        }
    ],
    "sg:phone":"+1 415 883 8668",
    "sg:postcode":"94949",
    "sg:province":"CA",
    "sg:tags":[
        "beverage",
        "mfg"
    ],
    "wof:name":"Delicato Estates",
    "wof:placetype":"venue"
},
  "geometry": {"coordinates":[-122.540254,38.066076],"type":"Point"}
}