{
  "type": "Feature",
  "properties": {
    "addr:full":"1260 B St Hayward CA 94541",
    "addr:housenumber":"1260",
    "addr:postcode":"94541",
    "addr:street":"B St",
    "iso:country":"US",
    "sg:address":"1260 B St",
    "sg:city":"Hayward",
    "sg:classifiers":[
        {
            "category":"Professional",
            "subcategory":"Lawyer & Legal Services",
            "type":"Services"
        }
    ],
    "sg:phone":"+1 510 537 7800",
    "sg:postcode":"94541",
    "sg:province":"CA",
    "sg:tags":[
        "attorney"
    ],
    "wof:name":"Margaret E O'Neill Law Offices",
    "wof:placetype":"venue"
},
  "geometry": {"coordinates":[-122.07852800000001,37.675801],"type":"Point"}
}