{
  "type": "Feature",
  "properties": {
    "iso:country":"US",
    "sg:address":"19835 Ventura Blvd",
    "sg:city":"Woodland Hills",
    "sg:classifiers":[
        {
            "category":"Shopping",
            "subcategory":"Clothing, Apparel, & Fashions",
            "type":"Retail Goods"
        }
    ],
    "sg:phone":"+1 818 704 4800",
    "sg:postcode":"91364",
    "sg:province":"CA",
    "sg:tags":[
        "children's",
        "infant",
        "clothing",
        "wear"
    ],
    "wof:name":"L A Babes",
    "wof:placetype":"venue"
},
  "geometry": {"coordinates":[-118.56500200000001,34.172199],"type":"Point"}
}