{
  "type": "Feature",
  "properties": {
    "addr:full":"2820 Fulton Ave Ste A Sacramento CA 95821",
    "addr:housenumber":"2820",
    "addr:postcode":"95821",
    "addr:street":"Fulton Ave Ste A",
    "iso:country":"US",
    "sg:address":"2820 Fulton Ave Ste A",
    "sg:city":"Sacramento",
    "sg:classifiers":[
        {
            "category":"Retail",
            "subcategory":"Auto Repair",
            "type":"Services"
        },
        {
            "category":"Government",
            "subcategory":"Office",
            "type":"Public Place"
        }
    ],
    "sg:phone":"+1 916 924 8219",
    "sg:postcode":"95821",
    "sg:province":"CA",
    "sg:tags":[
        "smog",
        "check"
    ],
    "sg:website":"mkautorepair.com/",
    "wof:name":"MK Auto Repair",
    "wof:placetype":"venue"
},
  "geometry": {"coordinates":[-121.400437,38.616152],"type":"Point"}
}