{
  "type": "Feature",
  "properties": {
    "addr:full":"15112 Jackson Street Midway City CA 92655",
    "addr:housenumber":"15112",
    "addr:postcode":"92655",
    "addr:street":"Jackson Street",
    "iso:country":"US",
    "sg:address":"15112 Jackson Street",
    "sg:city":"Midway City",
    "sg:classifiers":[
        {
            "category":"Building & Trades",
            "subcategory":"Construction",
            "type":"Services"
        }
    ],
    "sg:phone":"+1 714 373 2366",
    "sg:postcode":"92655",
    "sg:province":"CA",
    "sg:tags":[
        "contractor"
    ],
    "wof:name":"H I L Builders",
    "wof:placetype":"venue"
},
  "geometry": {"coordinates":[-117.98755,33.742449],"type":"Point"}
}