{
  "type": "Feature",
  "properties": {
    "iso:country":"US",
    "sg:address":"801 Harrison St",
    "sg:city":"Oakland",
    "sg:classifiers":[
        {
            "category":"Building & Trades",
            "subcategory":"Construction",
            "type":"Services"
        }
    ],
    "sg:phone":"+1 510 432 2385",
    "sg:postcode":"94607",
    "sg:province":"CA",
    "sg:tags":[
        "contractor"
    ],
    "wof:name":"Karda Co.",
    "wof:placetype":"venue"
},
  "geometry": {"coordinates":[-122.270172,37.798779],"type":"Point"}
}