{
  "type": "Feature",
  "properties": {
    "iso:country":"US",
    "sg:address":"1645 Telegraph Ave",
    "sg:city":"Oakland",
    "sg:classifiers":[
        {
            "category":"Professional",
            "type":"Services"
        }
    ],
    "sg:phone":"+1 510 832 2295",
    "sg:postcode":"94612",
    "sg:province":"CA",
    "sg:tags":[
        "establishment"
    ],
    "wof:name":"P 3 Productions",
    "wof:placetype":"venue"
},
  "geometry": {"coordinates":[-122.270483,37.806498],"type":"Point"}
}