{
  "type": "Feature",
  "properties": {
    "addr:full":"11858 Bernardo Plaza Ct San Diego CA 92128",
    "addr:housenumber":"11858",
    "addr:postcode":"92128",
    "addr:street":"Bernardo Plaza Ct",
    "iso:country":"US",
    "sg:address":"11858 Bernardo Plaza Ct",
    "sg:city":"San Diego",
    "sg:classifiers":[
        {
            "category":"Professional",
            "subcategory":"Engineering",
            "type":"Services"
        }
    ],
    "sg:phone":"+1 858 451 8290",
    "sg:postcode":"92128",
    "sg:province":"CA",
    "sg:tags":[
        "engineer"
    ],
    "wof:name":"Southwest Consulting Group Inc",
    "wof:placetype":"venue"
},
  "geometry": {"coordinates":[-117.076382,33.020226],"type":"Point"}
}