{
  "type": "Feature",
  "properties": {
    "addr:full":"4335 Prospect Ave Los Angeles CA 90027",
    "addr:housenumber":"4335",
    "addr:postcode":"90027",
    "addr:street":"Prospect Ave",
    "iso:country":"US",
    "sg:address":"4335 Prospect Ave",
    "sg:city":"Los Angeles",
    "sg:classifiers":[
        {
            "category":"Building & Trades",
            "subcategory":"Construction",
            "type":"Services"
        }
    ],
    "sg:phone":"+1 323 664 7784",
    "sg:postcode":"90027",
    "sg:province":"CA",
    "sg:tags":[
        "house"
    ],
    "wof:name":"Lee Kaye Wan",
    "wof:placetype":"venue"
},
  "geometry": {"coordinates":[-118.28513,34.101872],"type":"Point"}
}