{
  "type": "Feature",
  "properties": {
    "addr:full":"631 S Olive St Los Angeles CA 90014",
    "addr:housenumber":"631",
    "addr:postcode":"90014",
    "addr:street":"S Olive St",
    "iso:country":"US",
    "sg:address":"631 S Olive St",
    "sg:city":"Los Angeles",
    "sg:classifiers":[
        {
            "category":"Freight",
            "type":"Transportation"
        }
    ],
    "sg:phone":"+1 213 614 1010",
    "sg:postcode":"90014",
    "sg:province":"CA",
    "sg:tags":[
        "shipping",
        "agent"
    ],
    "wof:name":"One Service Co",
    "wof:placetype":"venue"
},
  "geometry": {"coordinates":[-118.255241,34.047086],"type":"Point"}
}