{
  "type": "Feature",
  "properties": {
    "addr:full":"67800 E Palm Canyon Dr Cathedral City CA 92234",
    "addr:housenumber":"67800",
    "addr:postcode":"92234",
    "addr:street":"E Palm Canyon Dr",
    "iso:country":"US",
    "sg:address":"67800 E Palm Canyon Dr",
    "sg:city":"Cathedral City",
    "sg:classifiers":[
        {
            "category":"Home & Garden",
            "subcategory":"Carpets & Floor Coverings",
            "type":"Retail Goods"
        }
    ],
    "sg:phone":"+1 760 770 7122",
    "sg:postcode":"92234",
    "sg:province":"CA",
    "sg:tags":[
        "dealer",
        "rug"
    ],
    "wof:name":"Sav-On Carpets & Mattresses",
    "wof:placetype":"venue"
},
  "geometry": {"coordinates":[-116.480771,33.787617],"type":"Point"}
}