{
  "type": "Feature",
  "properties": {
    "iso:country":"US",
    "sg:address":"2906 23rd St",
    "sg:city":"Sacramento",
    "sg:classifiers":[
        {
            "category":"Real Estate",
            "subcategory":"Real Estate Agent",
            "type":"Services"
        }
    ],
    "sg:phone":"+1 916 489 6695",
    "sg:postcode":"95818",
    "sg:province":"CA",
    "wof:name":"Ufirst Realty",
    "wof:placetype":"venue"
},
  "geometry": {"coordinates":[-121.484741,38.551177],"type":"Point"}
}