{
  "type": "Feature",
  "properties": {
    "addr:full":"3465 Torrance Blvd Ste G Torrance CA 90503",
    "addr:housenumber":"3465",
    "addr:postcode":"90503",
    "addr:street":"Torrance Blvd Ste G",
    "iso:country":"US",
    "sg:address":"3465 Torrance Blvd Ste G",
    "sg:city":"Torrance",
    "sg:classifiers":[
        {
            "category":"Professional",
            "subcategory":"Lawyer & Legal Services",
            "type":"Services"
        }
    ],
    "sg:phone":"+1 310 540 1412",
    "sg:postcode":"90503",
    "sg:province":"CA",
    "wof:name":"Yamamoto David K Atty",
    "wof:placetype":"venue"
},
  "geometry": {"coordinates":[-118.34699999999999,33.837601],"type":"Point"}
}