{
  "type": "Feature",
  "properties": {
    "addr:full":"22323 Sherman Way Canoga Park CA 91303",
    "addr:housenumber":"22323",
    "addr:postcode":"91303",
    "addr:street":"Sherman Way",
    "iso:country":"US",
    "sg:address":"22323 Sherman Way",
    "sg:city":"Canoga Park",
    "sg:classifiers":[
        {
            "category":"Shopping",
            "subcategory":"Pets & Pet Supplies",
            "type":"Retail Goods"
        }
    ],
    "sg:phone":"+1 818 992 8860",
    "sg:postcode":"91303",
    "sg:province":"CA",
    "wof:name":"Canoga Park Vet Center",
    "wof:placetype":"venue"
},
  "geometry": {"coordinates":[-118.61272599999999,34.201803],"type":"Point"}
}