{
  "type": "Feature",
  "properties": {
    "addr:full":"139 Woodland Way Milpitas CA 95035",
    "addr:housenumber":"139",
    "addr:postcode":"95035",
    "addr:street":"Woodland Way",
    "iso:country":"US",
    "sg:address":"139 Woodland Way",
    "sg:city":"Milpitas",
    "sg:classifiers":[
        {
            "category":"Real Estate",
            "subcategory":"Real Estate Agent",
            "type":"Services"
        }
    ],
    "sg:phone":"+1 408 934 1197",
    "sg:postcode":"95035",
    "sg:province":"CA",
    "wof:name":"Ceo Realty",
    "wof:placetype":"venue"
},
  "geometry": {"coordinates":[-121.905759,37.410991],"type":"Point"}
}