{
  "type": "Feature",
  "properties": {
    "iso:country":"US",
    "sg:address":"912 New York St",
    "sg:city":"Redlands",
    "sg:classifiers":[
        {
            "category":"Professional",
            "subcategory":"Management & Consulting",
            "type":"Services"
        }
    ],
    "sg:phone":"+1 909 307 2130",
    "sg:postcode":"92374",
    "sg:province":"CA",
    "sg:tags":[
        "marketing",
        "program"
    ],
    "wof:name":"High Touch Solutions",
    "wof:placetype":"venue"
},
  "geometry": {"coordinates":[-117.195482,34.064606],"type":"Point"}
}