{
  "type": "Feature",
  "properties": {
    "addr:full":"3185 Cleveland Ave Santa Rosa CA 95403",
    "addr:housenumber":"3185",
    "addr:postcode":"95403",
    "addr:street":"Cleveland Ave",
    "iso:country":"US",
    "sg:address":"3185 Cleveland Ave",
    "sg:city":"Santa Rosa",
    "sg:classifiers":[
        {
            "category":"Manufacturing",
            "subcategory":"Printing",
            "type":"Manufacturing & Wholesale Goods"
        }
    ],
    "sg:phone":"+1 707 545 1153",
    "sg:postcode":"95403",
    "sg:province":"CA",
    "sg:tags":[
        "commercial"
    ],
    "wof:name":"Printing Express",
    "wof:placetype":"venue"
},
  "geometry": {"coordinates":[-122.73023000000001,38.47117],"type":"Point"}
}