{
  "type": "Feature",
  "properties": {
    "addr:full":"640 Escondido Ave Vista CA 92084",
    "addr:housenumber":"640",
    "addr:postcode":"92084",
    "addr:street":"Escondido Ave",
    "iso:country":"US",
    "sg:address":"640 Escondido Ave",
    "sg:city":"Vista",
    "sg:classifiers":[
        {
            "category":"Home & Garden",
            "subcategory":"Building Materials",
            "type":"Retail Goods"
        },
        {
            "category":"Manufacturing",
            "subcategory":"Lumber",
            "type":"Manufacturing & Wholesale Goods"
        }
    ],
    "sg:phone":"+1 760 724 2153",
    "sg:postcode":"92084",
    "sg:province":"CA",
    "sg:tags":[
        "hardwood",
        "concrete",
        "product",
        "mill",
        "mfg"
    ],
    "wof:name":"Pine Tree Lumber Co",
    "wof:placetype":"venue"
},
  "geometry": {"coordinates":[-117.234112,33.197725],"type":"Point"}
}