{
  "type": "Feature",
  "properties": {
    "iso:country":"US",
    "sg:address":"2806 Story Rd Parking Lot",
    "sg:city":"San Jose",
    "sg:classifiers":[
        {
            "category":"Food Court",
            "type":"Food & Drink"
        },
        {
            "category":"Restaurant",
            "type":"Food & Drink"
        }
    ],
    "sg:postcode":"95127",
    "sg:province":"CA",
    "sg:tags":[
        "mexican",
        "stand"
    ],
    "wof:name":"El Paisa Taqueria",
    "wof:placetype":"venue"
},
  "geometry": {"coordinates":[-121.82378799999999,37.352475],"type":"Point"}
}