{
  "type": "Feature",
  "properties": {
    "iso:country":"US",
    "sg:address":"55 W 5th Ave",
    "sg:city":"San Mateo",
    "sg:classifiers":[
        {
            "category":"Wholesale",
            "subcategory":"Sporting Goods",
            "type":"Manufacturing & Wholesale Goods"
        },
        {
            "category":"Manufacturing",
            "subcategory":"Toys & Sporting Goods",
            "type":"Manufacturing & Wholesale Goods"
        }
    ],
    "sg:phone":"+1 650 344 3873",
    "sg:postcode":"94402",
    "sg:province":"CA",
    "sg:tags":[
        "equipment",
        "golf",
        "supply"
    ],
    "wof:name":"Sunoak International Inc",
    "wof:placetype":"venue"
},
  "geometry": {"coordinates":[-122.326627,37.560091],"type":"Point"}
}