{
  "type": "Feature",
  "properties": {
    "iso:country":"US",
    "sg:address":"3304 Mills Ave",
    "sg:city":"Glendale",
    "sg:classifiers":[
        {
            "category":"Building & Trades",
            "subcategory":"Plumbing",
            "type":"Services"
        }
    ],
    "sg:phone":"+1 818 249 2993",
    "sg:postcode":"91214",
    "sg:province":"CA",
    "sg:tags":[
        "plumbing",
        "contractor"
    ],
    "sg:website":"www.ableatlanta.com",
    "wof:name":"Able Plumbing",
    "wof:placetype":"venue"
},
  "geometry": {"coordinates":[-118.251505,34.220938],"type":"Point"}
}