{
  "type": "Feature",
  "properties": {
    "iso:country":"US",
    "sg:address":"870 S Western Ave",
    "sg:city":"Los Angeles",
    "sg:classifiers":[
        {
            "category":"Shopping",
            "subcategory":"Clothing, Apparel, & Fashions",
            "type":"Retail Goods"
        }
    ],
    "sg:phone":"+1 213 487 2990",
    "sg:postcode":"90005",
    "sg:province":"CA",
    "wof:name":"Ceci",
    "wof:placetype":"venue"
},
  "geometry": {"coordinates":[-118.309071,34.057658],"type":"Point"}
}