{
  "type": "Feature",
  "properties": {
    "iso:country":"US",
    "sg:address":"15950 State Hwy 49",
    "sg:city":"Drytown",
    "sg:classifiers":[
        {
            "category":"Organizations",
            "subcategory":"Community Association",
            "type":"Services"
        }
    ],
    "sg:phone":"+1 209 245 6722",
    "sg:postcode":"95699",
    "sg:province":"CA",
    "sg:tags":[
        "club"
    ],
    "wof:name":"Drytown Club",
    "wof:placetype":"venue"
},
  "geometry": {"coordinates":[-120.855328,38.44163],"type":"Point"}
}