{
  "type": "Feature",
  "properties": {
    "iso:country":"US",
    "sg:address":"707 Cortland Avenue",
    "sg:city":"San Francisco",
    "sg:classifiers":[
        {
            "category":"Professional",
            "subcategory":"Lawyer & Legal Services",
            "type":"Services"
        }
    ],
    "sg:phone":"+1 415 826 6900",
    "sg:postcode":"94110",
    "sg:province":"CA",
    "wof:name":"Bernal Heights Law Office",
    "wof:placetype":"venue"
},
  "geometry": {"coordinates":[-122.415001,37.739101],"type":"Point"}
}