{
  "type": "Feature",
  "properties": {
    "addr:full":"123 Walter Way Santa Maria CA 93455",
    "addr:housenumber":"123",
    "addr:postcode":"93455",
    "addr:street":"Walter Way",
    "iso:country":"US",
    "sg:address":"123 Walter Way",
    "sg:city":"Santa Maria",
    "sg:classifiers":[
        {
            "category":"Shopping",
            "type":"Retail Goods"
        }
    ],
    "sg:phone":"+1 805 934 9229",
    "sg:postcode":"93455",
    "sg:province":"CA",
    "sg:tags":[
        "cards",
        "sport",
        "baseball",
        "memorabilia"
    ],
    "wof:name":"Classic Steam Creations",
    "wof:placetype":"venue"
},
  "geometry": {"coordinates":[-120.436786,34.861034],"type":"Point"}
}