{
  "type": "Feature",
  "properties": {
    "addr:full":"6070 Heights Rd Santa Rosa CA 95404",
    "addr:housenumber":"6070",
    "addr:postcode":"95404",
    "addr:street":"Heights Rd",
    "iso:country":"US",
    "sg:address":"6070 Heights Rd",
    "sg:city":"Santa Rosa",
    "sg:classifiers":[
        {
            "category":"Shopping",
            "type":"Retail Goods"
        }
    ],
    "sg:phone":"+1 707 545 3239",
    "sg:postcode":"95404",
    "sg:province":"CA",
    "sg:tags":[
        "merchandise"
    ],
    "wof:name":"John Pascoe Design",
    "wof:placetype":"venue"
},
  "geometry": {"coordinates":[-122.70275599999999,38.525158],"type":"Point"}
}