{
  "type": "Feature",
  "properties": {
    "addr:full":"7388 Carnelian St Rancho Cucamonga CA 91730",
    "addr:housenumber":"7388",
    "addr:postcode":"91730",
    "addr:street":"Carnelian St",
    "iso:country":"US",
    "sg:address":"7388 Carnelian St",
    "sg:city":"Rancho Cucamonga",
    "sg:classifiers":[
        {
            "category":"Health Services",
            "subcategory":"Chiropractor",
            "type":"Services"
        }
    ],
    "sg:phone":"+1 909 980 1771",
    "sg:postcode":"91730",
    "sg:province":"CA",
    "wof:name":"Jones Chiropractic Ctr",
    "wof:placetype":"venue"
},
  "geometry": {"coordinates":[-117.61615,34.120717],"type":"Point"}
}