{
  "type": "Feature",
  "properties": {
    "iso:country":"US",
    "sg:address":"1373 E Citrus Ave",
    "sg:city":"Redlands",
    "sg:classifiers":[
        {
            "category":"Retail",
            "subcategory":"Laundry & Dry Cleaning",
            "type":"Services"
        }
    ],
    "sg:phone":"+1 909 792 8239",
    "sg:postcode":"92374",
    "sg:province":"CA",
    "wof:name":"Citrus Cleaners",
    "wof:placetype":"venue"
},
  "geometry": {"coordinates":[-117.156998,34.055698],"type":"Point"}
}