{
  "type": "Feature",
  "properties": {
    "iso:country":"US",
    "sg:address":"1451 N California St",
    "sg:city":"San Bernardino",
    "sg:classifiers":[
        {
            "category":"Education",
            "subcategory":"School",
            "type":"Public Place"
        }
    ],
    "sg:phone":"+1 909 388 6450",
    "sg:postcode":"92411",
    "sg:province":"CA",
    "sg:website":"www.sbcusd.com",
    "wof:name":"Rio Vista Elementary School",
    "wof:placetype":"venue"
},
  "geometry": {"coordinates":[-117.331112,34.126452],"type":"Point"}
}