{
  "type": "Feature",
  "properties": {
    "addr:full":"148 Lloyd Ave Ste E Fullerton CA 92833",
    "addr:housenumber":"148",
    "addr:postcode":"92833",
    "addr:street":"Lloyd Ave Ste E",
    "iso:country":"US",
    "sg:address":"148 Lloyd Ave Ste E",
    "sg:city":"Fullerton",
    "sg:classifiers":[
        {
            "category":"Retail",
            "subcategory":"Auto Repair",
            "type":"Services"
        }
    ],
    "sg:phone":"+1 714 446 0892",
    "sg:postcode":"92833",
    "sg:province":"CA",
    "sg:tags":[
        "body",
        "shop"
    ],
    "wof:name":"New Life Auto Collision",
    "wof:placetype":"venue"
},
  "geometry": {"coordinates":[-117.963003,33.86931],"type":"Point"}
}