{
  "type": "Feature",
  "properties": {
    "addr:full":"1643 Atherton Way Salinas CA 93906",
    "addr:housenumber":"1643",
    "addr:postcode":"93906",
    "addr:street":"Atherton Way",
    "iso:country":"US",
    "sg:address":"1643 Atherton Way",
    "sg:city":"Salinas",
    "sg:classifiers":[
        {
            "category":"Building & Trades",
            "subcategory":"Electrical",
            "type":"Services"
        }
    ],
    "sg:phone":"+1 831 444 6268",
    "sg:postcode":"93906",
    "sg:province":"CA",
    "sg:tags":[
        "electrical",
        "contractor"
    ],
    "wof:name":"M&S Electrical",
    "wof:placetype":"venue"
},
  "geometry": {"coordinates":[-121.626369,36.700918],"type":"Point"}
}