{
  "type": "Feature",
  "properties": {
    "addr:full":"701 Truxtun Ave Bakersfield CA 93301",
    "addr:housenumber":"701",
    "addr:postcode":"93301",
    "addr:street":"Truxtun Ave",
    "iso:country":"US",
    "sg:address":"701 Truxtun Ave",
    "sg:city":"Bakersfield",
    "sg:classifiers":[
        {
            "category":"Education",
            "subcategory":"Library",
            "type":"Public Place"
        }
    ],
    "sg:phone":"+1 661 868 0701",
    "sg:postcode":"93301",
    "sg:province":"CA",
    "sg:tags":[
        "educational",
        "program",
        "administrative"
    ],
    "wof:name":"Public Library",
    "wof:placetype":"venue"
},
  "geometry": {"coordinates":[-119.009721,35.373304],"type":"Point"}
}