{
  "type": "Feature",
  "properties": {
    "addr:full":"4373 Central Pl Fairfield CA 94534",
    "addr:housenumber":"4373",
    "addr:postcode":"94534",
    "addr:street":"Central Pl",
    "iso:country":"US",
    "sg:address":"4373 Central Pl",
    "sg:city":"Fairfield",
    "sg:classifiers":[
        {
            "category":"Travel",
            "subcategory":"Hotels & Motels",
            "type":"Entertainment"
        }
    ],
    "sg:phone":"+1 707 864 2029",
    "sg:postcode":"94534",
    "sg:province":"CA",
    "wof:name":"Best Western Inn",
    "wof:placetype":"venue"
},
  "geometry": {"coordinates":[-122.125676,38.222178],"type":"Point"}
}