{
  "type": "Feature",
  "properties": {
    "iso:country":"US",
    "sg:address":"6343 Atlantic Ave Ste D",
    "sg:city":"Bell",
    "sg:classifiers":[
        {
            "category":"Restaurant",
            "type":"Food & Drink"
        }
    ],
    "sg:phone":"+1 323 771 3686",
    "sg:postcode":"90201",
    "sg:province":"CA",
    "wof:name":"Taqueria Jalisco",
    "wof:placetype":"venue"
},
  "geometry": {"coordinates":[-118.187151,33.978976],"type":"Point"}
}