{
  "type": "Feature",
  "properties": {
    "iso:country":"US",
    "sg:address":"947 Wilsey Way",
    "sg:city":"Beaumont",
    "sg:classifiers":[
        {
            "category":"Building & Trades",
            "subcategory":"Plumbing",
            "type":"Services"
        }
    ],
    "sg:phone":"+1 909 809 4939",
    "sg:postcode":"92223",
    "sg:province":"CA",
    "wof:name":"JOSH MAILHOT PLUMBING",
    "wof:placetype":"venue"
},
  "geometry": {"coordinates":[-116.988871,33.934623],"type":"Point"}
}