{
  "type": "Feature",
  "properties": {
    "addr:full":"15811 Fairgrove Ave La Puente CA 91744",
    "addr:housenumber":"15811",
    "addr:postcode":"91744",
    "addr:street":"Fairgrove Ave",
    "iso:country":"US",
    "sg:address":"15811 Fairgrove Ave",
    "sg:city":"La Puente",
    "sg:classifiers":[
        {
            "category":"Retail",
            "subcategory":"Repair Shop",
            "type":"Services"
        }
    ],
    "sg:phone":"+1 626 917 0799",
    "sg:postcode":"91744",
    "sg:province":"CA",
    "sg:tags":[
        "lock",
        "locksmith"
    ],
    "wof:name":"Mario's Towing & Lockout Svc",
    "wof:placetype":"venue"
},
  "geometry": {"coordinates":[-117.939758,34.041568],"type":"Point"}
}