{
  "type": "Feature",
  "properties": {
    "iso:country":"US",
    "sg:address":"8000 Jarvis Ave Suite 100",
    "sg:city":"Newark",
    "sg:classifiers":[
        {
            "category":"Professional",
            "subcategory":"Computer Services",
            "type":"Services"
        }
    ],
    "sg:phone":"+1 510 456 1860",
    "sg:postcode":"94560",
    "sg:province":"CA",
    "sg:tags":[
        "file-sharing",
        "data-aggregation",
        "enterprise-content-management",
        "document-management-system",
        "secure-file-transfer",
        "data-privacy-compliance",
        "cloud-storage"
    ],
    "sg:website":"http://www.leapfile.com",
    "wof:name":"LeapFILE",
    "wof:placetype":"venue"
},
  "geometry": {"coordinates":[-122.05712,37.540909],"type":"Point"}
}