{
  "type": "Feature",
  "properties": {
    "addr:full":"463 Pacific Ave San Francisco CA 94133",
    "addr:housenumber":"463",
    "addr:postcode":"94133",
    "addr:street":"Pacific Ave",
    "iso:country":"US",
    "sg:address":"463 Pacific Ave",
    "sg:city":"San Francisco",
    "sg:classifiers":[
        {
            "category":"Wholesale",
            "subcategory":"Non-durable Goods",
            "type":"Manufacturing & Wholesale Goods"
        }
    ],
    "sg:phone":"+1 415 392 1941",
    "sg:postcode":"94133",
    "sg:province":"CA",
    "wof:name":"Marukita 3d Car Pk & Trdg Inc",
    "wof:placetype":"venue"
},
  "geometry": {"coordinates":[-122.403508,37.797248],"type":"Point"}
}