{
  "type": "Feature",
  "properties": {
    "iso:country":"US",
    "sg:address":"2020 Hurley Way",
    "sg:city":"Sacramento",
    "sg:classifiers":[
        {
            "category":"Professional",
            "subcategory":"Lawyer & Legal Services",
            "type":"Services"
        }
    ],
    "sg:phone":"+1 916 925 3169",
    "sg:postcode":"95825",
    "sg:province":"CA",
    "sg:tags":[
        "attorney"
    ],
    "wof:name":"Kenneth R Reynolds Inc",
    "wof:placetype":"venue"
},
  "geometry": {"coordinates":[-121.418003,38.588845],"type":"Point"}
}