{
  "type": "Feature",
  "properties": {
    "addr:full":"656 E 20th St Chico CA 95928",
    "addr:housenumber":"656",
    "addr:postcode":"95928",
    "addr:street":"E 20Th St",
    "iso:country":"US",
    "sg:address":"656 E 20th St",
    "sg:city":"Chico",
    "sg:classifiers":[
        {
            "category":"Restaurant",
            "type":"Food & Drink"
        }
    ],
    "sg:phone":"+1 530 345 3934",
    "sg:postcode":"95928",
    "sg:province":"CA",
    "sg:tags":[
        "mexican"
    ],
    "wof:name":"Gringo's Burritos",
    "wof:placetype":"venue"
},
  "geometry": {"coordinates":[-121.819526,39.723179],"type":"Point"}
}