{
  "type": "Feature",
  "properties": {
    "addr:full":"101 Hacienda Dr Calexico CA 92231",
    "addr:housenumber":"101",
    "addr:postcode":"92231",
    "addr:street":"Hacienda Dr",
    "iso:country":"US",
    "sg:address":"101 Hacienda Dr",
    "sg:city":"Calexico",
    "sg:classifiers":[
        {
            "category":"Sports & Exercise",
            "subcategory":"Gym",
            "type":"Entertainment"
        }
    ],
    "sg:phone":"+1 760 768 6160",
    "sg:postcode":"92231",
    "sg:province":"CA",
    "sg:tags":[
        "club",
        "health",
        "studio",
        "gymnasium"
    ],
    "wof:name":"Curves For Women",
    "wof:placetype":"venue"
},
  "geometry": {"coordinates":[-115.499292,32.682496],"type":"Point"}
}