{
  "type": "Feature",
  "properties": {
    "iso:country":"US",
    "sg:address":"5867 Fagan Dr",
    "sg:city":"Redding",
    "sg:classifiers":[
        {
            "category":"Real Estate",
            "subcategory":"Real Estate Agent",
            "type":"Services"
        }
    ],
    "sg:phone":"+1 530 244 1836",
    "sg:postcode":"96001",
    "sg:province":"CA",
    "sg:tags":[
        "rental",
        "vacation"
    ],
    "wof:name":"Cove Doney Vacation Home",
    "wof:placetype":"venue"
},
  "geometry": {"coordinates":[-122.370189,40.536572],"type":"Point"}
}