{
  "type": "Feature",
  "properties": {
    "addr:full":"1338 E Washington Blvd Los Angeles CA 90021",
    "addr:housenumber":"1338",
    "addr:postcode":"90021",
    "addr:street":"E Washington Blvd",
    "iso:country":"US",
    "sg:address":"1338 E Washington Blvd",
    "sg:city":"Los Angeles",
    "sg:classifiers":[
        {
            "category":"Wholesale",
            "subcategory":"Drugs",
            "type":"Manufacturing & Wholesale Goods"
        }
    ],
    "sg:phone":"+1 213 623 9288",
    "sg:postcode":"90021",
    "sg:province":"CA",
    "sg:tags":[
        "cosmetic"
    ],
    "wof:name":"Vintage Group Inc",
    "wof:placetype":"venue"
},
  "geometry": {"coordinates":[-118.24888799999999,34.023511],"type":"Point"}
}