{
  "type": "Feature",
  "properties": {
    "iso:country":"US",
    "sg:address":"326 S Center St",
    "sg:city":"Turlock",
    "sg:classifiers":[
        {
            "category":"Home & Garden",
            "subcategory":"Building Materials",
            "type":"Retail Goods"
        }
    ],
    "sg:phone":"+1 209 667 1222",
    "sg:postcode":"95380",
    "sg:province":"CA",
    "sg:tags":[
        "glass",
        "window",
        "plate"
    ],
    "wof:name":"Don's Mobile Glass",
    "wof:placetype":"venue"
},
  "geometry": {"coordinates":[-120.843197,37.493466],"type":"Point"}
}