{
  "type": "Feature",
  "properties": {
    "iso:country":"US",
    "sg:address":"9343 Tech Center Dr",
    "sg:city":"Sacramento",
    "sg:classifiers":[
        {
            "category":"Professional",
            "subcategory":"Research",
            "type":"Services"
        }
    ],
    "sg:phone":"+1 916 361 4400",
    "sg:postcode":"95826",
    "sg:province":"CA",
    "sg:tags":[
        "pharmaceutical",
        "manufacturer",
        "commercial",
        "products-wholesale",
        "nonphysical"
    ],
    "sg:website":"www.medintelligence.com",
    "wof:name":"Pharmaceutical Care Network",
    "wof:placetype":"venue"
},
  "geometry": {"coordinates":[-121.35193200000001,38.563448],"type":"Point"}
}