{
  "type": "Feature",
  "properties": {
    "addr:full":"1408 Hobson Ave West Sacramento CA 95605",
    "addr:housenumber":"1408",
    "addr:postcode":"95605",
    "addr:street":"Hobson Ave",
    "iso:country":"US",
    "sg:address":"1408 Hobson Ave",
    "sg:city":"West Sacramento",
    "sg:classifiers":[
        {
            "category":"Wholesale",
            "subcategory":"Machinery & Supplies",
            "type":"Manufacturing & Wholesale Goods"
        }
    ],
    "sg:phone":"+1 916 371 5858",
    "sg:postcode":"95605",
    "sg:province":"CA",
    "sg:tags":[
        "industrial"
    ],
    "wof:name":"Foremost Filters",
    "wof:placetype":"venue"
},
  "geometry": {"coordinates":[-121.533513,38.592349],"type":"Point"}
}