{
  "type": "Feature",
  "properties": {
    "iso:country":"US",
    "sg:address":"2238 Fillmore St",
    "sg:city":"San Francisco",
    "sg:classifiers":[
        {
            "category":"Professional",
            "subcategory":"Management & Consulting",
            "type":"Services"
        }
    ],
    "sg:phone":"+1 415 202 7550",
    "sg:postcode":"94115",
    "sg:province":"CA",
    "sg:tags":[
        "consultant",
        "public",
        "utility"
    ],
    "wof:name":"PCR Consulting",
    "wof:placetype":"venue"
},
  "geometry": {"coordinates":[-122.43407500000001,37.790384],"type":"Point"}
}