{
  "type": "Feature",
  "properties": {
    "addr:full":"375 Pine Ave Goleta CA 93117",
    "addr:housenumber":"375",
    "addr:postcode":"93117",
    "addr:street":"Pine Ave",
    "iso:country":"US",
    "sg:address":"375 Pine Ave",
    "sg:city":"Goleta",
    "sg:classifiers":[
        {
            "category":"Home & Garden",
            "subcategory":"Furniture",
            "type":"Retail Goods"
        }
    ],
    "sg:phone":"+1 805 681 0330",
    "sg:postcode":"93117",
    "sg:province":"CA",
    "sg:tags":[
        "cabinet"
    ],
    "wof:name":"Ed Ogden",
    "wof:placetype":"venue"
},
  "geometry": {"coordinates":[-119.82671000000001,34.434127],"type":"Point"}
}