{
  "type": "Feature",
  "properties": {
    "addr:full":"20219 Bahama St Chatsworth CA 91311",
    "addr:housenumber":"20219",
    "addr:postcode":"91311",
    "addr:street":"Bahama St",
    "iso:country":"US",
    "sg:address":"20219 Bahama St",
    "sg:city":"Chatsworth",
    "sg:classifiers":[
        {
            "category":"Manufacturing",
            "subcategory":"Glass & Minerals",
            "type":"Manufacturing & Wholesale Goods"
        },
        {
            "category":"Recreation",
            "type":"Entertainment"
        }
    ],
    "sg:phone":"+1 818 882 0300",
    "sg:postcode":"91311",
    "sg:province":"CA",
    "sg:tags":[
        "club",
        "coal",
        "membership",
        "mining",
        "pumice"
    ],
    "sg:website":"www.uspumice.com",
    "wof:name":"United States Pumice Company",
    "wof:placetype":"venue"
},
  "geometry": {"coordinates":[-118.573841,34.233015],"type":"Point"}
}