{
  "type": "Feature",
  "properties": {
    "addr:full":"301 S Main St Alturas CA 96101",
    "addr:housenumber":"301",
    "addr:postcode":"96101",
    "addr:street":"S Main St",
    "iso:country":"US",
    "sg:address":"301 S Main St",
    "sg:city":"Alturas",
    "sg:classifiers":[
        {
            "category":"Shopping",
            "subcategory":"Clothing, Apparel, & Fashions",
            "type":"Retail Goods"
        }
    ],
    "sg:phone":"+1 530 233 5599",
    "sg:postcode":"96101",
    "sg:province":"CA",
    "wof:name":"Ardie's Classie Lassie/Calico",
    "wof:placetype":"venue"
},
  "geometry": {"coordinates":[-120.542422,41.482675],"type":"Point"}
}