{
  "type": "Feature",
  "properties": {
    "iso:country":"US",
    "sg:address":"2500 S Fowler Ave",
    "sg:city":"Fresno",
    "sg:classifiers":[
        {
            "category":"Wholesale",
            "subcategory":"Fruits & Vegetables",
            "type":"Manufacturing & Wholesale Goods"
        }
    ],
    "sg:phone":"+1 559 486 4141",
    "sg:postcode":"93725",
    "sg:province":"CA",
    "sg:tags":[
        "shipper"
    ],
    "wof:name":"Tri-Boro Fruit Co",
    "wof:placetype":"venue"
},
  "geometry": {"coordinates":[-119.681945,36.692793],"type":"Point"}
}