{
  "type": "Feature",
  "properties": {
    "addr:full":"307 N Avenue 50 Los Angeles CA 90042",
    "addr:housenumber":"307;50",
    "addr:postcode":"90042",
    "addr:street":"N Avenue",
    "iso:country":"US",
    "sg:address":"307 N Avenue 50",
    "sg:city":"Los Angeles",
    "sg:classifiers":[
        {
            "category":"Restaurant",
            "type":"Food & Drink"
        }
    ],
    "sg:phone":"+1 323 256 1996",
    "sg:postcode":"90042",
    "sg:province":"CA",
    "sg:tags":[
        "pizza"
    ],
    "wof:name":"Fidel's Pizza",
    "wof:placetype":"venue"
},
  "geometry": {"coordinates":[-118.204063,34.107413],"type":"Point"}
}