{
  "type": "Feature",
  "properties": {
    "addr:full":"6920 Koll Center Pkwy Pleasanton CA 94566",
    "addr:postcode":"6920;94566",
    "addr:street":"Center Pkwy",
    "iso:country":"US",
    "sg:address":"6920 Koll Center Pkwy",
    "sg:city":"Pleasanton",
    "sg:classifiers":[
        {
            "category":"Wholesale",
            "subcategory":"Durable Goods & Equipment",
            "type":"Manufacturing & Wholesale Goods"
        }
    ],
    "sg:phone":"+1 925 461 7100",
    "sg:postcode":"94566",
    "sg:province":"CA",
    "sg:tags":[
        "representative",
        "manufacturer"
    ],
    "sg:website":"www.moulthrop.com",
    "wof:name":"Moulthrop Sales",
    "wof:placetype":"venue"
},
  "geometry": {"coordinates":[-121.90266200000001,37.661103],"type":"Point"}
}