{
  "type": "Feature",
  "properties": {
    "iso:country":"US",
    "sg:address":"17450 Arrow Blvd",
    "sg:city":"Fontana",
    "sg:classifiers":[
        {
            "category":"Real Estate",
            "subcategory":"Real Estate Operator",
            "type":"Services"
        }
    ],
    "sg:phone":"+1 909 428 7931",
    "sg:postcode":"92335",
    "sg:province":"CA",
    "sg:tags":[
        "building",
        "apartment"
    ],
    "wof:name":"Arrow Park Apts Inc",
    "wof:placetype":"venue"
},
  "geometry": {"coordinates":[-117.425879,34.099472],"type":"Point"}
}