{
  "type": "Feature",
  "properties": {
    "iso:country":"US",
    "sg:address":"833 Auto Center Dr",
    "sg:city":"Palmdale",
    "sg:classifiers":[
        {
            "category":"Health Services",
            "subcategory":"Doctor",
            "type":"Services"
        }
    ],
    "sg:phone":"+1 661 274 8828",
    "sg:postcode":"93551",
    "sg:province":"CA",
    "sg:tags":[
        "physician",
        "surgeon"
    ],
    "wof:name":"Glaser Leonard MD Inc",
    "wof:placetype":"venue"
},
  "geometry": {"coordinates":[-118.145123,34.590854],"type":"Point"}
}