{
  "type": "Feature",
  "properties": {
    "addr:full":"9200 W Sunset Blvd Los Angeles CA 90069",
    "addr:housenumber":"9200",
    "addr:postcode":"90069",
    "addr:street":"W Sunset Blvd",
    "iso:country":"US",
    "sg:address":"9200 W Sunset Blvd",
    "sg:city":"Los Angeles",
    "sg:classifiers":[
        {
            "category":"Professional",
            "subcategory":"Management & Consulting",
            "type":"Services"
        }
    ],
    "sg:phone":"+1 310 278 8528",
    "sg:postcode":"90069",
    "sg:province":"CA",
    "sg:tags":[
        "marketing",
        "program"
    ],
    "wof:name":"Procter & Gamble Productions",
    "wof:placetype":"venue"
},
  "geometry": {"coordinates":[-118.39236099999999,34.09052],"type":"Point"}
}