{
  "type": "Feature",
  "properties": {
    "addr:full":"3775 Massachusetts Ave La Mesa CA 91941",
    "addr:housenumber":"3775",
    "addr:postcode":"91941",
    "addr:street":"Massachusetts Ave",
    "iso:country":"US",
    "sg:address":"3775 Massachusetts Ave",
    "sg:city":"La Mesa",
    "sg:classifiers":[
        {
            "category":"Shopping",
            "subcategory":"Computers & Home Electronics",
            "type":"Retail Goods"
        }
    ],
    "sg:phone":"+1 619 567 3265",
    "sg:postcode":"91941",
    "sg:province":"CA",
    "wof:name":"DISH Network",
    "wof:placetype":"venue"
},
  "geometry": {"coordinates":[-117.26382099999999,32.746152],"type":"Point"}
}