{
  "type": "Feature",
  "properties": {
    "iso:country":"US",
    "sg:address":"8757 Woodman Way",
    "sg:city":"Sacramento",
    "sg:classifiers":[
        {
            "category":"Shopping",
            "subcategory":"Gifts & Souvenirs",
            "type":"Retail Goods"
        }
    ],
    "sg:phone":"+1 916 363 3853",
    "sg:postcode":"95826",
    "sg:province":"CA",
    "wof:name":"Gifts N Things By Melinda",
    "wof:placetype":"venue"
},
  "geometry": {"coordinates":[-121.375424,38.565967],"type":"Point"}
}