{
  "type": "Feature",
  "properties": {
    "addr:full":"1480 Canal Ave Long Beach CA 90810",
    "addr:housenumber":"1480",
    "addr:postcode":"90810",
    "addr:street":"Canal Ave",
    "iso:country":"US",
    "sg:address":"1480 Canal Ave",
    "sg:city":"Long Beach",
    "sg:classifiers":[
        {
            "category":"Manufacturing",
            "subcategory":"Metals",
            "type":"Manufacturing & Wholesale Goods"
        }
    ],
    "sg:phone":"+1 562 437 2825",
    "sg:postcode":"90810",
    "sg:province":"CA",
    "sg:tags":[
        "plating"
    ],
    "sg:website":"www.uschromeofca.com",
    "wof:name":"U S Chrome Corp Of California",
    "wof:placetype":"venue"
},
  "geometry": {"coordinates":[-118.213722,33.78499],"type":"Point"}
}