{
  "type": "Feature",
  "properties": {
    "addr:full":"4574 Whittier Blvd Los Angeles CA 90022",
    "addr:housenumber":"4574",
    "addr:postcode":"90022",
    "addr:street":"Whittier Blvd",
    "iso:country":"US",
    "sg:address":"4574 Whittier Blvd",
    "sg:city":"Los Angeles",
    "sg:classifiers":[
        {
            "category":"Utilities",
            "subcategory":"Mobile Phone",
            "type":"Services"
        }
    ],
    "sg:phone":"+1 323 264 1020",
    "sg:postcode":"90022",
    "sg:province":"CA",
    "sg:tags":[
        "communication",
        "electronic",
        "radiotelephone"
    ],
    "wof:name":"Comtel",
    "wof:placetype":"venue"
},
  "geometry": {"coordinates":[-118.168296,34.022653],"type":"Point"}
}