{
  "type": "Feature",
  "properties": {
    "addr:full":"11420 Deerfield Dr Truckee CA 96161",
    "addr:housenumber":"11420",
    "addr:postcode":"96161",
    "addr:street":"Deerfield Dr",
    "iso:country":"US",
    "sg:address":"11420 Deerfield Dr",
    "sg:city":"Truckee",
    "sg:classifiers":[
        {
            "category":"Restaurant",
            "type":"Food & Drink"
        }
    ],
    "sg:menulink":"http://www.allmenus.com/ca/donner/215907-mcdonalds/menu/",
    "sg:postcode":"96161",
    "sg:province":"CA",
    "sg:tags":[
        "burger",
        "american"
    ],
    "wof:name":"McDonald's",
    "wof:placetype":"venue"
},
  "geometry": {"coordinates":[-120.209857,39.320909],"type":"Point"}
}