{
  "type": "Feature",
  "properties": {
    "addr:full":"1032 Bay St Eureka CA 95501",
    "addr:housenumber":"1032",
    "addr:postcode":"95501",
    "addr:street":"Bay St",
    "iso:country":"US",
    "sg:address":"1032 Bay St",
    "sg:city":"Eureka",
    "sg:classifiers":[
        {
            "category":"Organizations",
            "subcategory":"Religious Organization",
            "type":"Services"
        }
    ],
    "sg:phone":"+1 707 442 1784",
    "sg:postcode":"95501",
    "sg:province":"CA",
    "sg:tags":[
        "church"
    ],
    "sg:website":"www.faithcenter.info",
    "wof:name":"Faith Center Foursquare Church",
    "wof:placetype":"venue"
},
  "geometry": {"coordinates":[-124.14084699999999,40.80133],"type":"Point"}
}