{
  "type": "Feature",
  "properties": {
    "addr:full":"8939 Etiwanda Ave Rancho Cucamonga CA 91739",
    "addr:housenumber":"8939",
    "addr:postcode":"91739",
    "addr:street":"Etiwanda Ave",
    "iso:country":"US",
    "sg:address":"8939 Etiwanda Ave",
    "sg:city":"Rancho Cucamonga",
    "sg:classifiers":[
        {
            "category":"Freight",
            "type":"Transportation"
        }
    ],
    "sg:phone":"+1 909 899 5222",
    "sg:postcode":"91739",
    "sg:province":"CA",
    "sg:tags":[
        "local",
        "storage",
        "trucking"
    ],
    "wof:name":"Aguilar Warehousing & Dist",
    "wof:placetype":"venue"
},
  "geometry": {"coordinates":[-117.523898,34.091943],"type":"Point"}
}