{
  "type": "Feature",
  "properties": {
    "addr:full":"2200 Ave del Diablo Escondido CA 92029",
    "addr:postcode":"92029",
    "addr:street":"2200 Ave Del Diablo",
    "iso:country":"US",
    "sg:address":"2200 Ave del Diablo",
    "sg:city":"Escondido",
    "sg:classifiers":[
        {
            "category":"Building & Trades",
            "subcategory":"Construction",
            "type":"Services"
        }
    ],
    "sg:phone":"+1 760 737 7134",
    "sg:postcode":"92029",
    "sg:province":"CA",
    "sg:tags":[
        "demolition",
        "contractor"
    ],
    "wof:name":"Lumberjack Tree Svc",
    "wof:placetype":"venue"
},
  "geometry": {"coordinates":[-117.110557,33.103142],"type":"Point"}
}