{
  "type": "Feature",
  "properties": {
    "iso:country":"US",
    "sg:address":"935 Taylor St",
    "sg:city":"Albany",
    "sg:classifiers":[
        {
            "category":"Organizations",
            "subcategory":"Religious Organization",
            "type":"Services"
        }
    ],
    "sg:phone":"+1 510 528 8739",
    "sg:postcode":"94706",
    "sg:province":"CA",
    "sg:tags":[
        "place",
        "worship",
        "church"
    ],
    "wof:name":"Open Door Marketing Solutions",
    "wof:placetype":"venue"
},
  "geometry": {"coordinates":[-122.303853,37.888683],"type":"Point"}
}