{
  "type": "Feature",
  "properties": {
    "addr:full":"239 S Beverly Dr Beverly Hills CA 90212",
    "addr:housenumber":"239",
    "addr:postcode":"90212",
    "addr:street":"S Beverly Dr",
    "iso:country":"US",
    "sg:address":"239 S Beverly Dr",
    "sg:city":"Beverly Hills",
    "sg:classifiers":[
        {
            "category":"Organizations",
            "subcategory":"Professional Association",
            "type":"Services"
        }
    ],
    "sg:phone":"+1 310 248 1000",
    "sg:postcode":"90212",
    "sg:province":"CA",
    "sg:tags":[
        "chambers",
        "commerce"
    ],
    "wof:name":"Beverly Hills Chamber-Commerce",
    "wof:placetype":"venue"
},
  "geometry": {"coordinates":[-118.399147,34.063288],"type":"Point"}
}