{
  "type": "Feature",
  "properties": {
    "iso:country":"US",
    "sg:address":"16149 Roscoe Blvd",
    "sg:city":"North Hills",
    "sg:classifiers":[
        {
            "category":"Home & Garden",
            "subcategory":"Building Materials",
            "type":"Retail Goods"
        }
    ],
    "sg:phone":"+1 818 347 2302",
    "sg:postcode":"91343",
    "sg:province":"CA",
    "sg:tags":[
        "glass",
        "window",
        "plate"
    ],
    "sg:website":"www.solarco.com",
    "wof:name":"Artistic Auto Glass Tinting",
    "wof:placetype":"venue"
},
  "geometry": {"coordinates":[-118.484583,34.221399],"type":"Point"}
}