{
  "type": "Feature",
  "properties": {
    "iso:country":"US",
    "sg:address":"1 Mills Cir",
    "sg:city":"Ontario",
    "sg:classifiers":[
        {
            "category":"Professional",
            "type":"Services"
        }
    ],
    "sg:phone":"+1 909 481 2778",
    "sg:postcode":"91764",
    "sg:province":"CA",
    "sg:tags":[
        "establishment"
    ],
    "wof:name":"Treasure Box",
    "wof:placetype":"venue"
},
  "geometry": {"coordinates":[-117.550647,34.076077],"type":"Point"}
}