{
  "type": "Feature",
  "properties": {
    "addr:full":"6809 Jade Ln Carlsbad CA 92009",
    "addr:housenumber":"6809",
    "addr:postcode":"92009",
    "addr:street":"Jade Ln",
    "iso:country":"US",
    "sg:address":"6809 Jade Ln",
    "sg:city":"Carlsbad",
    "sg:classifiers":[
        {
            "category":"Health Services",
            "subcategory":"Nursing And Care Facility",
            "type":"Services"
        },
        {
            "category":"Social Services",
            "subcategory":"Adult Care",
            "type":"Services"
        }
    ],
    "sg:phone":"+1 760 295 2634",
    "sg:postcode":"92009",
    "sg:province":"CA",
    "sg:tags":[
        "living",
        "assisted",
        "homes-elderly",
        "elder",
        "people"
    ],
    "wof:name":"Edens Home Care",
    "wof:placetype":"venue"
},
  "geometry": {"coordinates":[-117.256756,33.110448],"type":"Point"}
}