{
  "type": "Feature",
  "properties": {
    "iso:country":"US",
    "sg:address":"700 S Winchester Blvd",
    "sg:city":"San Jose",
    "sg:classifiers":[
        {
            "category":"Shopping",
            "subcategory":"Computers & Home Electronics",
            "type":"Retail Goods"
        }
    ],
    "sg:phone":"+1 408 296 9000",
    "sg:postcode":"95128",
    "sg:province":"CA",
    "sg:tags":[
        "equipment",
        "satellite",
        "system"
    ],
    "wof:name":"Satellite Solutions LLC",
    "wof:placetype":"venue"
},
  "geometry": {"coordinates":[-121.950014,37.31382],"type":"Point"}
}