{
  "type": "Feature",
  "properties": {
    "addr:full":"41021 Sunset Ln Hemet CA 92544",
    "addr:housenumber":"41021",
    "addr:postcode":"92544",
    "addr:street":"Sunset Ln",
    "iso:country":"US",
    "sg:address":"41021 Sunset Ln",
    "sg:city":"Hemet",
    "sg:classifiers":[
        {
            "category":"Building & Trades",
            "subcategory":"Landscaping Services",
            "type":"Services"
        }
    ],
    "sg:phone":"+1 951 929 0111",
    "sg:postcode":"92544",
    "sg:province":"CA",
    "sg:tags":[
        "aged",
        "homes-institutional"
    ],
    "sg:website":"http://www.cflckids.org",
    "wof:name":"California Family Life Center",
    "wof:placetype":"venue"
},
  "geometry": {"coordinates":[-116.94526500000001,33.7323],"type":"Point"}
}