{
  "type": "Feature",
  "properties": {
    "addr:full":"160 W. Santa Clara St Ste 1180 San Jose CA 95113",
    "addr:housenumber":"160",
    "addr:postcode":"95113",
    "addr:street":"W. Santa Clara St Ste 1180",
    "iso:country":"US",
    "sg:address":"160 W. Santa Clara St Ste 1180",
    "sg:city":"San Jose",
    "sg:classifiers":[
        {
            "category":"Professional",
            "subcategory":"Lawyer & Legal Services",
            "type":"Services"
        }
    ],
    "sg:phone":"+1 408 286 1200",
    "sg:postcode":"95113",
    "sg:province":"CA",
    "sg:website":"www.sjlawyers.com/",
    "wof:name":"Mesirow & Fink",
    "wof:placetype":"venue"
},
  "geometry": {"coordinates":[-121.892872,37.33456],"type":"Point"}
}