{
  "type": "Feature",
  "properties": {
    "iso:country":"US",
    "sg:address":"5842 Oakdale Ave",
    "sg:city":"Woodland Hills",
    "sg:classifiers":[
        {
            "category":"Building & Trades",
            "subcategory":"Construction",
            "type":"Services"
        }
    ],
    "sg:phone":"+1 818 344 7976",
    "sg:postcode":"91367",
    "sg:province":"CA",
    "sg:tags":[
        "contractor"
    ],
    "wof:name":"Alexander Construction",
    "wof:placetype":"venue"
},
  "geometry": {"coordinates":[-118.565505,34.176574],"type":"Point"}
}