{
  "type": "Feature",
  "properties": {
    "addr:full":"1262 W 2nd St Los Angeles CA 90026",
    "addr:housenumber":"1262",
    "addr:postcode":"90026",
    "addr:street":"W 2Nd St",
    "iso:country":"US",
    "sg:address":"1262 W 2nd St",
    "sg:city":"Los Angeles",
    "sg:classifiers":[
        {
            "category":"Professional",
            "type":"Services"
        }
    ],
    "sg:phone":"+1 213 977 0550",
    "sg:postcode":"90026",
    "sg:province":"CA",
    "wof:name":"Pantom",
    "wof:placetype":"venue"
},
  "geometry": {"coordinates":[-118.257884,34.059951],"type":"Point"}
}