{
  "type": "Feature",
  "properties": {
    "iso:country":"US",
    "sg:address":"6512 Peggy Way",
    "sg:city":"Bakersfield",
    "sg:classifiers":[
        {
            "category":"Building & Trades",
            "subcategory":"Construction",
            "type":"Services"
        }
    ],
    "sg:phone":"+1 661 836 8894",
    "sg:postcode":"93307",
    "sg:province":"CA",
    "sg:tags":[
        "contractor"
    ],
    "wof:name":"Best Fence Co",
    "wof:placetype":"venue"
},
  "geometry": {"coordinates":[-119.016718,35.295243],"type":"Point"}
}