{
  "type": "Feature",
  "properties": {
    "iso:country":"US",
    "sg:address":"3185 State Rte 12",
    "sg:city":"Burson",
    "sg:classifiers":[
        {
            "category":"Food & Beverages",
            "subcategory":"Groceries & Convenience Stores",
            "type":"Retail Goods"
        }
    ],
    "sg:phone":"+1 209 772 2371",
    "sg:postcode":"95249",
    "sg:province":"CA",
    "sg:tags":[
        "grocer"
    ],
    "wof:name":"Burson Market",
    "wof:placetype":"venue"
},
  "geometry": {"coordinates":[-120.71149200000001,38.206153],"type":"Point"}
}