{
  "type": "Feature",
  "properties": {
    "iso:country":"US",
    "sg:address":"22018 Meekland Ave",
    "sg:city":"Hayward",
    "sg:classifiers":[
        {
            "category":"Retail",
            "subcategory":"Auto Rental",
            "type":"Services"
        }
    ],
    "sg:phone":"+1 510 727 9949",
    "sg:postcode":"94541",
    "sg:province":"CA",
    "sg:tags":[
        "renting",
        "truck",
        "leasing"
    ],
    "wof:name":"U-Haul Co",
    "wof:placetype":"venue"
},
  "geometry": {"coordinates":[-122.103351,37.670985],"type":"Point"}
}