{
  "type": "Feature",
  "properties": {
    "addr:full":"2798 Yulupa Ave Santa Rosa CA 95405",
    "addr:housenumber":"2798",
    "addr:postcode":"95405",
    "addr:street":"Yulupa Ave",
    "iso:country":"US",
    "sg:address":"2798 Yulupa Ave",
    "sg:city":"Santa Rosa",
    "sg:classifiers":[
        {
            "category":"Health Services",
            "subcategory":"Health Practitioner",
            "type":"Services"
        }
    ],
    "sg:phone":"+1 707 527 4001",
    "sg:postcode":"95405",
    "sg:province":"CA",
    "sg:tags":[
        "therapist",
        "physical"
    ],
    "wof:name":"Santa Rosa Back Fitness",
    "wof:placetype":"venue"
},
  "geometry": {"coordinates":[-122.668256,38.427991],"type":"Point"}
}