{
  "type": "Feature",
  "properties": {
    "addr:full":"628 S Hill St Los Angeles CA 90014",
    "addr:housenumber":"628",
    "addr:postcode":"90014",
    "addr:street":"S Hill St",
    "iso:country":"US",
    "sg:address":"628 S Hill St",
    "sg:city":"Los Angeles",
    "sg:classifiers":[
        {
            "category":"Shopping",
            "subcategory":"Jewelry",
            "type":"Retail Goods"
        }
    ],
    "sg:phone":"+1 213 623 3323",
    "sg:postcode":"90014",
    "sg:province":"CA",
    "sg:tags":[
        "jeweler"
    ],
    "wof:name":"Giantto",
    "wof:placetype":"venue"
},
  "geometry": {"coordinates":[-118.25407199999999,34.046273],"type":"Point"}
}