{
  "type": "Feature",
  "properties": {
    "iso:country":"US",
    "sg:address":"1820 State Rte 66",
    "sg:city":"Glendora",
    "sg:classifiers":[
        {
            "category":"Restaurant",
            "type":"Food & Drink"
        }
    ],
    "sg:phone":"+1 626 963 1270",
    "sg:postcode":"91740",
    "sg:province":"CA",
    "wof:name":"Shake A Delic Juice Co",
    "wof:placetype":"venue"
},
  "geometry": {"coordinates":[-117.830859,34.128726],"type":"Point"}
}