{
  "type": "Feature",
  "properties": {
    "iso:country":"US",
    "sg:address":"45973 Warm Springs Blvd",
    "sg:city":"Fremont",
    "sg:classifiers":[
        {
            "category":"Building & Trades",
            "subcategory":"Construction",
            "type":"Services"
        }
    ],
    "sg:phone":"+1 510 770 0183",
    "sg:postcode":"94539",
    "sg:province":"CA",
    "sg:tags":[
        "floor",
        "laying",
        "contractor"
    ],
    "wof:name":"Means Floor Covering",
    "wof:placetype":"venue"
},
  "geometry": {"coordinates":[-121.933515,37.49548],"type":"Point"}
}