{
  "type": "Feature",
  "properties": {
    "iso:country":"US",
    "sg:address":"441 N Newport Blvd",
    "sg:city":"Newport Beach",
    "sg:classifiers":[
        {
            "category":"Banks & Credit Unions",
            "subcategory":"Investment Brokerage",
            "type":"Services"
        }
    ],
    "sg:phone":"+1 949 631 0418",
    "sg:postcode":"92663",
    "sg:province":"CA",
    "sg:tags":[
        "advice"
    ],
    "wof:name":"Harry Grace Steele Foundation",
    "wof:placetype":"venue"
},
  "geometry": {"coordinates":[-117.926264,33.627132],"type":"Point"}
}