{
  "type": "Feature",
  "properties": {
    "addr:full":"13900 Shoemaker Ave Norwalk CA 90650",
    "addr:postcode":"13900;90650",
    "addr:street":"Shoemaker Ave",
    "iso:country":"US",
    "sg:address":"13900 Shoemaker Ave",
    "sg:city":"Norwalk",
    "sg:classifiers":[
        {
            "category":"Wholesale",
            "subcategory":"Construction Materials",
            "type":"Manufacturing & Wholesale Goods"
        },
        {
            "category":"Manufacturing",
            "subcategory":"Rubber & Plastics",
            "type":"Manufacturing & Wholesale Goods"
        }
    ],
    "sg:phone":"+1 714 349 9160",
    "sg:postcode":"90650",
    "sg:province":"CA",
    "sg:tags":[
        "injection",
        "mfg",
        "molding"
    ],
    "wof:name":"ARC Plastics",
    "wof:placetype":"venue"
},
  "geometry": {"coordinates":[-118.0553,33.904641],"type":"Point"}
}