{
  "type": "Feature",
  "properties": {
    "iso:country":"US",
    "sg:address":"10130 Sorrento Valley Rd",
    "sg:city":"San Diego",
    "sg:classifiers":[
        {
            "category":"Professional",
            "subcategory":"Research",
            "type":"Services"
        }
    ],
    "sg:phone":"+1 858 622 0510",
    "sg:postcode":"92121",
    "sg:province":"CA",
    "sg:tags":[
        "biotechnology",
        "product"
    ],
    "wof:name":"Attenuon LLC",
    "wof:placetype":"venue"
},
  "geometry": {"coordinates":[-117.209345,32.890118],"type":"Point"}
}