{
  "type": "Feature",
  "properties": {
    "iso:country":"US",
    "sg:address":"2795 Yard St",
    "sg:city":"Oroville",
    "sg:classifiers":[
        {
            "category":"Education",
            "subcategory":"School",
            "type":"Public Place"
        }
    ],
    "sg:phone":"+1 530 532 3000",
    "sg:postcode":"95966",
    "sg:province":"CA",
    "sg:website":"www.oeta.org",
    "wof:name":"Oroville Elementary School",
    "wof:placetype":"venue"
},
  "geometry": {"coordinates":[-121.546251,39.513147],"type":"Point"}
}