{
  "type": "Feature",
  "properties": {
    "iso:country":"US",
    "sg:address":"2955 Senter Rd",
    "sg:city":"San Jose",
    "sg:classifiers":[
        {
            "category":"Food & Beverages",
            "subcategory":"Ethnic Foods",
            "type":"Retail Goods"
        }
    ],
    "sg:phone":"+1 408 226 2398",
    "sg:postcode":"95111",
    "sg:province":"CA",
    "wof:name":"Vinh Khang 4",
    "wof:placetype":"venue"
},
  "geometry": {"coordinates":[-121.837082,37.296544],"type":"Point"}
}