{
  "type": "Feature",
  "properties": {
    "iso:country":"US",
    "sg:address":"881 Hawthorne Dr",
    "sg:city":"Walnut Creek",
    "sg:classifiers":[
        {
            "category":"Banks & Credit Unions",
            "subcategory":"Investment Brokerage",
            "type":"Services"
        }
    ],
    "sg:phone":"+1 925 937 3839",
    "sg:postcode":"94596",
    "sg:province":"CA",
    "sg:tags":[
        "consultant",
        "planning",
        "financial"
    ],
    "wof:name":"Plan Tomorrow Assoc",
    "wof:placetype":"venue"
},
  "geometry": {"coordinates":[-122.026712,37.885639],"type":"Point"}
}