{
  "type": "Feature",
  "properties": {
    "addr:full":"1924 W Willow St Long Beach CA 90810",
    "addr:housenumber":"1924",
    "addr:postcode":"90810",
    "addr:street":"W Willow St",
    "iso:country":"US",
    "sg:address":"1924 W Willow St",
    "sg:city":"Long Beach",
    "sg:classifiers":[
        {
            "category":"Banks & Credit Unions",
            "subcategory":"Financial Services",
            "type":"Services"
        }
    ],
    "sg:phone":"+1 562 427 5297",
    "sg:postcode":"90810",
    "sg:province":"CA",
    "sg:tags":[
        "broker",
        "mortgage"
    ],
    "wof:name":"Home-Bizz Realty Inc",
    "wof:placetype":"venue"
},
  "geometry": {"coordinates":[-118.218002,33.804401],"type":"Point"}
}