{
  "type": "Feature",
  "properties": {
    "addr:full":"1805 N Fine Ave Fresno CA 93727",
    "addr:housenumber":"1805",
    "addr:postcode":"93727",
    "addr:street":"N Fine Ave",
    "iso:country":"US",
    "sg:address":"1805 N Fine Ave",
    "sg:city":"Fresno",
    "sg:classifiers":[
        {
            "category":"Professional",
            "subcategory":"Business Services",
            "type":"Services"
        }
    ],
    "sg:phone":"+1 559 251 9800",
    "sg:postcode":"93727",
    "sg:province":"CA",
    "sg:tags":[
        "translator",
        "interpreter"
    ],
    "wof:name":"ABC Interpreting Inc",
    "wof:placetype":"venue"
},
  "geometry": {"coordinates":[-119.729249,36.765459],"type":"Point"}
}