{
  "type": "Feature",
  "properties": {
    "iso:country":"US",
    "sg:address":"18700 Sherman Way",
    "sg:city":"Reseda",
    "sg:classifiers":[
        {
            "category":"Professional",
            "subcategory":"Accounting & Tax Preparation",
            "type":"Services"
        }
    ],
    "sg:phone":"+1 818 344 5063",
    "sg:postcode":"91335",
    "sg:province":"CA",
    "sg:tags":[
        "return",
        "filing"
    ],
    "wof:name":"J D Taxes",
    "wof:placetype":"venue"
},
  "geometry": {"coordinates":[-118.541505,34.201057],"type":"Point"}
}