{
  "type": "Feature",
  "properties": {
    "iso:country":"US",
    "sg:address":"5780 Autoport Mall",
    "sg:city":"San Diego",
    "sg:classifiers":[
        {
            "category":"Retail",
            "subcategory":"Auto Repair",
            "type":"Services"
        }
    ],
    "sg:phone":"+1 858 558 8808",
    "sg:postcode":"92121",
    "sg:province":"CA",
    "sg:tags":[
        "transmission"
    ],
    "wof:name":"Transmission Pros",
    "wof:placetype":"venue"
},
  "geometry": {"coordinates":[-117.18447500000001,32.878032],"type":"Point"}
}