{
  "type": "Feature",
  "properties": {
    "addr:full":"1200 E Wardlow Rd Long Beach CA 90807",
    "addr:housenumber":"1200",
    "addr:postcode":"90807",
    "addr:street":"E Wardlow Rd",
    "iso:country":"US",
    "sg:address":"1200 E Wardlow Rd",
    "sg:city":"Long Beach",
    "sg:classifiers":[
        {
            "category":"Restaurant",
            "type":"Food & Drink"
        }
    ],
    "sg:phone":"+1 562 427 3124",
    "sg:postcode":"90807",
    "sg:province":"CA",
    "wof:name":"Eccos Pizza",
    "wof:placetype":"venue"
},
  "geometry": {"coordinates":[-118.175273,33.818909],"type":"Point"}
}