{
  "type": "Feature",
  "properties": {
    "iso:country":"US",
    "sg:address":"817 Mitchell Rd",
    "sg:city":"Newbury Park",
    "sg:classifiers":[
        {
            "category":"Manufacturing",
            "subcategory":"Tools & Machinery",
            "type":"Manufacturing & Wholesale Goods"
        }
    ],
    "sg:phone":"+1 805 375 4525",
    "sg:postcode":"91320",
    "sg:province":"CA",
    "sg:tags":[
        "industrial",
        "mfg"
    ],
    "wof:name":"Dearman Tool Metal Sawing Svc",
    "wof:placetype":"venue"
},
  "geometry": {"coordinates":[-118.926888,34.188027],"type":"Point"}
}