{
  "type": "Feature",
  "properties": {
    "addr:full":"3460 Atwater Blvd Atwater CA 95301",
    "addr:housenumber":"3460",
    "addr:postcode":"95301",
    "addr:street":"Atwater Blvd",
    "iso:country":"US",
    "sg:address":"3460 Atwater Blvd",
    "sg:city":"Atwater",
    "sg:classifiers":[
        {
            "category":"Building & Trades",
            "subcategory":"Construction",
            "type":"Services"
        }
    ],
    "sg:phone":"+1 209 358 2201",
    "sg:postcode":"95301",
    "sg:province":"CA",
    "sg:tags":[
        "roofing",
        "contractor"
    ],
    "wof:name":"Unger Roofing",
    "wof:placetype":"venue"
},
  "geometry": {"coordinates":[-120.583738,37.336479],"type":"Point"}
}