{
  "type": "Feature",
  "properties": {
    "iso:country":"US",
    "sg:address":"1832 19th St",
    "sg:city":"Bakersfield",
    "sg:classifiers":[
        {
            "category":"Food & Beverages",
            "subcategory":"Liquor & Beverages",
            "type":"Retail Goods"
        }
    ],
    "sg:phone":"+1 661 322 5454",
    "sg:postcode":"93301",
    "sg:province":"CA",
    "wof:name":"West Side Liquor Store",
    "wof:placetype":"venue"
},
  "geometry": {"coordinates":[-119.023208,35.37633],"type":"Point"}
}