{
  "type": "Feature",
  "properties": {
    "addr:full":"4725 Mission St San Francisco CA 94112",
    "addr:housenumber":"4725",
    "addr:postcode":"94112",
    "addr:street":"Mission St",
    "iso:country":"US",
    "sg:address":"4725 Mission St",
    "sg:city":"San Francisco",
    "sg:classifiers":[
        {
            "category":"Building & Trades",
            "subcategory":"Cleaning & Sanitation",
            "type":"Services"
        }
    ],
    "sg:phone":"+1 415 337 0135",
    "sg:postcode":"94112",
    "sg:province":"CA",
    "sg:tags":[
        "janitor"
    ],
    "wof:name":"Milen's Janitorial Svc",
    "wof:placetype":"venue"
},
  "geometry": {"coordinates":[-122.436284,37.72263],"type":"Point"}
}