{
  "type": "Feature",
  "properties": {
    "iso:country":"US",
    "sg:address":"6527 Ira Ave",
    "sg:city":"Bell Gardens",
    "sg:classifiers":[
        {
            "category":"Building & Trades",
            "subcategory":"Construction",
            "type":"Services"
        }
    ],
    "sg:phone":"+1 323 771 0750",
    "sg:postcode":"90201",
    "sg:province":"CA",
    "sg:tags":[
        "general",
        "contractor"
    ],
    "wof:name":"J J Construction",
    "wof:placetype":"venue"
},
  "geometry": {"coordinates":[-118.154311,33.969888],"type":"Point"}
}