{
  "type": "Feature",
  "properties": {
    "addr:full":"10875 Elder Ave Hanford CA 93230",
    "addr:housenumber":"10875",
    "addr:postcode":"ca 93230",
    "addr:street":"Elder Ave",
    "iso:country":"US",
    "sg:address":"10875 Elder Ave",
    "sg:city":"Hanford",
    "sg:classifiers":[
        {
            "category":"Building & Trades",
            "subcategory":"Landscaping Services",
            "type":"Services"
        }
    ],
    "sg:phone":"+1 559 583 8733",
    "sg:postcode":"93230",
    "sg:province":"CA",
    "sg:tags":[
        "tree"
    ],
    "wof:name":"Richard's Tree Svc",
    "wof:placetype":"venue"
},
  "geometry": {"coordinates":[-119.651989,36.386333],"type":"Point"}
}