{
  "type": "Feature",
  "properties": {
    "addr:full":"1044 Deer Park Rd Deer Park CA 94576",
    "addr:housenumber":"1044",
    "addr:postcode":"94576",
    "addr:street":"Deer Park Rd",
    "iso:country":"US",
    "sg:address":"1044 Deer Park Rd",
    "sg:city":"Deer Park",
    "sg:classifiers":[
        {
            "category":"Building & Trades",
            "subcategory":"Construction",
            "type":"Services"
        }
    ],
    "sg:phone":"+1 707 963 4620",
    "sg:postcode":"94576",
    "sg:province":"CA",
    "sg:tags":[
        "woodworker"
    ],
    "wof:name":"Futtzn",
    "wof:placetype":"venue"
},
  "geometry": {"coordinates":[-122.472159,38.551415],"type":"Point"}
}