{
  "type": "Feature",
  "properties": {
    "iso:country":"US",
    "sg:address":"5090 Holt Blvd",
    "sg:city":"Montclair",
    "sg:classifiers":[
        {
            "category":"Home & Garden",
            "subcategory":"Furniture",
            "type":"Retail Goods"
        }
    ],
    "sg:phone":"+1 909 625 1557",
    "sg:postcode":"91763",
    "sg:province":"CA",
    "wof:name":"Princess Furniture",
    "wof:placetype":"venue"
},
  "geometry": {"coordinates":[-117.693348,34.063284],"type":"Point"}
}