{
  "type": "Feature",
  "properties": {
    "addr:full":"321 Nut Tree Rd Vacaville CA 95687",
    "addr:housenumber":"321",
    "addr:postcode":"95687",
    "addr:street":"Nut Tree Rd",
    "iso:country":"US",
    "sg:address":"321 Nut Tree Rd",
    "sg:city":"Vacaville",
    "sg:classifiers":[
        {
            "category":"Utilities",
            "subcategory":"Mobile Phone",
            "type":"Services"
        }
    ],
    "sg:phone":"+1 707 452 1730",
    "sg:postcode":"95687",
    "sg:province":"CA",
    "sg:tags":[
        "telephone",
        "cellular"
    ],
    "wof:name":"Verizon Wireless",
    "wof:placetype":"venue"
},
  "geometry": {"coordinates":[-121.953514,38.365157],"type":"Point"}
}