{
  "type": "Feature",
  "properties": {
    "addr:full":"9202 W Pico Boulevard Los Angeles CA 90035",
    "addr:housenumber":"9202",
    "addr:postcode":"90035",
    "addr:street":"W Pico Boulevard",
    "iso:country":"US",
    "sg:address":"9202 W Pico Boulevard",
    "sg:city":"Los Angeles",
    "sg:classifiers":[
        {
            "category":"Health Services",
            "subcategory":"Optometrist",
            "type":"Services"
        },
        {
            "category":"Shopping",
            "subcategory":"Optician",
            "type":"Retail Goods"
        }
    ],
    "sg:phone":"+1 310 274 4626",
    "sg:postcode":"90035",
    "sg:province":"CA",
    "sg:tags":[
        "eyewear"
    ],
    "wof:name":"Garwood J L MD",
    "wof:placetype":"venue"
},
  "geometry": {"coordinates":[-118.39229400000001,34.055363],"type":"Point"}
}