{
  "type": "Feature",
  "properties": {
    "iso:country":"US",
    "sg:address":"7823 Melrose Ave",
    "sg:city":"Los Angeles",
    "sg:classifiers":[
        {
            "category":"Personal",
            "subcategory":"Beauty Salon",
            "type":"Services"
        }
    ],
    "sg:phone":"+1 323 658 8760",
    "sg:postcode":"90046",
    "sg:province":"CA",
    "sg:tags":[
        "hair"
    ],
    "wof:name":"Susan's Hair Salon",
    "wof:placetype":"venue"
},
  "geometry": {"coordinates":[-118.360001,34.083698],"type":"Point"}
}