{
  "type": "Feature",
  "properties": {
    "addr:full":"1562 S Riverside Ave Rialto CA 92376",
    "addr:housenumber":"1562",
    "addr:postcode":"92376",
    "addr:street":"S Riverside Ave",
    "iso:country":"US",
    "sg:address":"1562 S Riverside Ave",
    "sg:city":"Rialto",
    "sg:classifiers":[
        {
            "category":"Restaurant",
            "type":"Food & Drink"
        }
    ],
    "sg:menulink":"http://www.allmenus.com/ca/san-bernardino/178616-jack-in-the-box/menu/",
    "sg:phone":"+1 909 877 1266",
    "sg:postcode":"92376",
    "sg:province":"CA",
    "sg:tags":[
        "burger",
        "american"
    ],
    "wof:name":"Jack in the Box",
    "wof:placetype":"venue"
},
  "geometry": {"coordinates":[-117.370345,34.071899],"type":"Point"}
}