{
  "type": "Feature",
  "properties": {
    "addr:full":"646 Canyon Rd Novato CA 94947",
    "addr:housenumber":"646",
    "addr:postcode":"94947",
    "addr:street":"Canyon Rd",
    "iso:country":"US",
    "sg:address":"646 Canyon Rd",
    "sg:city":"Novato",
    "sg:classifiers":[
        {
            "category":"Real Estate",
            "subcategory":"Real Estate Operator",
            "type":"Services"
        }
    ],
    "sg:phone":"+1 415 897 7565",
    "sg:postcode":"94947",
    "sg:province":"CA",
    "sg:tags":[
        "apartment"
    ],
    "sg:website":"www.seniorlivinginstyle.com",
    "wof:name":"Deer Park Retirement Residence",
    "wof:placetype":"venue"
},
  "geometry": {"coordinates":[-122.582155,38.631039],"type":"Point"}
}