{
  "type": "Feature",
  "properties": {
    "iso:country":"US",
    "sg:address":"22932 Lyons Ave",
    "sg:city":"Newhall",
    "sg:classifiers":[
        {
            "category":"Shopping",
            "subcategory":"Musical Instruments",
            "type":"Retail Goods"
        }
    ],
    "sg:phone":"+1 661 259 5502",
    "sg:postcode":"91321",
    "sg:province":"CA",
    "sg:tags":[
        "music",
        "teacher"
    ],
    "wof:name":"Lowe's Music",
    "wof:placetype":"venue"
},
  "geometry": {"coordinates":[-118.533997,34.380299],"type":"Point"}
}