{
  "type": "Feature",
  "properties": {
    "addr:full":"1030 Calimesa Blvd Calimesa CA 92320",
    "addr:postcode":"1030;92320",
    "addr:street":"Calimesa Blvd",
    "iso:country":"US",
    "sg:address":"1030 Calimesa Blvd",
    "sg:city":"Calimesa",
    "sg:classifiers":[
        {
            "category":"Health Services",
            "subcategory":"Doctor",
            "type":"Services"
        },
        {
            "category":"Health Services",
            "subcategory":"Dentist",
            "type":"Services"
        }
    ],
    "sg:phone":"+1 909 795 6019",
    "sg:postcode":"92320",
    "sg:province":"CA",
    "sg:tags":[
        "surgeon",
        "oral",
        "pediatric"
    ],
    "wof:name":"Parker Richard L Ms DDS",
    "wof:placetype":"venue"
},
  "geometry": {"coordinates":[-117.060997,34.000999],"type":"Point"}
}