{
  "type": "Feature",
  "properties": {
    "addr:full":"649 S Chaparro Rd Covina CA 91724",
    "addr:housenumber":"649",
    "addr:postcode":"91724",
    "addr:street":"S Chaparro Rd",
    "iso:country":"US",
    "sg:address":"649 S Chaparro Rd",
    "sg:city":"Covina",
    "sg:classifiers":[
        {
            "category":"Professional",
            "type":"Services"
        }
    ],
    "sg:phone":"+1 626 339 4118",
    "sg:postcode":"91724",
    "sg:province":"CA",
    "wof:name":"Cat Rocks",
    "wof:placetype":"venue"
},
  "geometry": {"coordinates":[-117.86230399999999,34.077914],"type":"Point"}
}