{
  "type": "Feature",
  "properties": {
    "iso:country":"US",
    "sg:address":"23520 Telo Ave",
    "sg:city":"Torrance",
    "sg:classifiers":[
        {
            "category":"Shopping",
            "subcategory":"Optical Goods",
            "type":"Retail Goods"
        }
    ],
    "sg:phone":"+1 310 326 7938",
    "sg:postcode":"90505",
    "sg:province":"CA",
    "sg:tags":[
        "professional",
        "equipment"
    ],
    "wof:name":"L E S C O Lab",
    "wof:placetype":"venue"
},
  "geometry": {"coordinates":[-118.33773600000001,33.813095],"type":"Point"}
}