{
  "type": "Feature",
  "properties": {
    "addr:full":"1000 W Valley Pkwy Escondido CA 92025",
    "addr:housenumber":"1000",
    "addr:postcode":"92025",
    "addr:street":"W Valley Pkwy",
    "iso:country":"US",
    "sg:address":"1000 W Valley Pkwy",
    "sg:city":"Escondido",
    "sg:classifiers":[
        {
            "category":"Shopping",
            "type":"Retail Goods"
        }
    ],
    "sg:phone":"+1 760 781 1600",
    "sg:postcode":"92025",
    "sg:province":"CA",
    "sg:tags":[
        "merchandise",
        "animal"
    ],
    "wof:name":"Petco 596",
    "wof:placetype":"venue"
},
  "geometry": {"coordinates":[-117.095933,33.117275],"type":"Point"}
}