{
  "type": "Feature",
  "properties": {
    "iso:country":"US",
    "sg:address":"21625 Prairie St",
    "sg:city":"Chatsworth",
    "sg:classifiers":[
        {
            "category":"Travel",
            "subcategory":"Travel Agent",
            "type":"Entertainment"
        }
    ],
    "sg:phone":"+1 818 428 6000",
    "sg:postcode":"91311",
    "sg:province":"CA",
    "sg:tags":[
        "agency",
        "bureau"
    ],
    "sg:website":"www.brendantours.com",
    "wof:name":"Brendan Tours & Worldwide",
    "wof:placetype":"venue"
},
  "geometry": {"coordinates":[-118.600751,34.239097],"type":"Point"}
}