{
  "type": "Feature",
  "properties": {
    "iso:country":"US",
    "sg:address":"241 Main",
    "sg:city":"Bridgeport",
    "sg:classifiers":[
        {
            "category":"Restaurant",
            "type":"Food & Drink"
        }
    ],
    "sg:phone":"+1 760 932 1172",
    "sg:postcode":"93517",
    "sg:province":"CA",
    "wof:name":"Pop's Galley",
    "wof:placetype":"venue"
},
  "geometry": {"coordinates":[-119.22756200000001,38.25592],"type":"Point"}
}