{
  "type": "Feature",
  "properties": {
    "addr:full":"7300 Van Nuys Blvd Ste 7 San Fernando Valley CA 91405",
    "addr:housenumber":"7300",
    "addr:postcode":"91405",
    "addr:street":"Van Nuys Blvd Ste 7;Fernando Valley",
    "iso:country":"US",
    "sg:address":"7300 Van Nuys Blvd Ste 7",
    "sg:city":"San Fernando Valley",
    "sg:classifiers":[
        {
            "category":"Retail",
            "subcategory":"Auto Repair",
            "type":"Services"
        }
    ],
    "sg:phone":"+1 818 454 5625",
    "sg:postcode":"91405",
    "sg:province":"CA",
    "wof:name":"Firetune Complete Auto Care",
    "wof:placetype":"venue"
},
  "geometry": {"coordinates":[-118.448413,34.203069],"type":"Point"}
}