{
  "type": "Feature",
  "properties": {
    "addr:full":"14650 Miller Ave Fontana CA 92336",
    "addr:housenumber":"14650",
    "addr:postcode":"92336",
    "addr:street":"Miller Ave",
    "iso:country":"US",
    "sg:address":"14650 Miller Ave",
    "sg:city":"Fontana",
    "sg:classifiers":[
        {
            "category":"Organizations",
            "subcategory":"Professional Association",
            "type":"Services"
        }
    ],
    "sg:phone":"+1 909 427 1525",
    "sg:postcode":"92336",
    "sg:province":"CA",
    "wof:name":"A & E Svc",
    "wof:placetype":"venue"
},
  "geometry": {"coordinates":[-117.485733,34.114189],"type":"Point"}
}