{
  "type": "Feature",
  "properties": {
    "addr:full":"3140 W Shaw Ave Fresno CA 93711",
    "addr:housenumber":"3140",
    "addr:postcode":"93711",
    "addr:street":"W Shaw Ave",
    "iso:country":"US",
    "sg:address":"3140 W Shaw Ave",
    "sg:city":"Fresno",
    "sg:classifiers":[
        {
            "category":"Shopping",
            "type":"Retail Goods"
        }
    ],
    "sg:phone":"+1 559 277 2500",
    "sg:postcode":"93711",
    "sg:province":"CA",
    "sg:tags":[
        "communication",
        "beeper",
        "telephone",
        "cellular",
        "provides"
    ],
    "sg:website":"www.gizmowireless.com",
    "wof:name":"Cellular Warehouse Inc",
    "wof:placetype":"venue"
},
  "geometry": {"coordinates":[-119.84634800000001,36.808358],"type":"Point"}
}