{
  "type": "Feature",
  "properties": {
    "iso:country":"US",
    "sg:address":"1920 Durfee Ave",
    "sg:city":"South El Monte",
    "sg:classifiers":[
        {
            "category":"Shopping",
            "subcategory":"Music",
            "type":"Retail Goods"
        }
    ],
    "sg:phone":"+1 626 443 3912",
    "sg:postcode":"91733",
    "sg:province":"CA",
    "sg:tags":[
        "video",
        "disc",
        "tape",
        "cassette"
    ],
    "wof:name":"Popcorn Video",
    "wof:placetype":"venue"
},
  "geometry": {"coordinates":[-118.031178,34.044543],"type":"Point"}
}