{
  "type": "Feature",
  "properties": {
    "addr:full":"1384 S Bascom Ave San Jose CA 95128",
    "addr:housenumber":"1384",
    "addr:postcode":"95128",
    "addr:street":"S Bascom Ave",
    "iso:country":"US",
    "sg:address":"1384 S Bascom Ave",
    "sg:city":"San Jose",
    "sg:classifiers":[
        {
            "category":"Building & Trades",
            "subcategory":"Construction",
            "type":"Services"
        }
    ],
    "sg:phone":"+1 408 374 6543",
    "sg:postcode":"95128",
    "sg:province":"CA",
    "sg:tags":[
        "painter"
    ],
    "wof:name":"Choice Painting Co",
    "wof:placetype":"venue"
},
  "geometry": {"coordinates":[-121.93162,37.300289],"type":"Point"}
}