{
  "type": "Feature",
  "properties": {
    "iso:country":"US",
    "sg:address":"635 S Hill St",
    "sg:city":"Los Angeles",
    "sg:classifiers":[
        {
            "category":"Manufacturing",
            "subcategory":"Jewelry",
            "type":"Manufacturing & Wholesale Goods"
        }
    ],
    "sg:phone":"+1 213 622 2660",
    "sg:postcode":"90014",
    "sg:province":"CA",
    "sg:website":"www.simongjewelry.com",
    "wof:name":"Simon G Jewelry",
    "wof:placetype":"venue"
},
  "geometry": {"coordinates":[-118.254122,34.046453],"type":"Point"}
}