{
  "type": "Feature",
  "properties": {
    "addr:full":"27 Cedar Ln Blairsden CA 96103",
    "addr:housenumber":"27",
    "addr:postcode":"96103",
    "addr:street":"Cedar Ln",
    "iso:country":"US",
    "sg:address":"27 Cedar Ln",
    "sg:city":"Blairsden",
    "sg:classifiers":[
        {
            "category":"Building & Trades",
            "subcategory":"Electrical",
            "type":"Services"
        }
    ],
    "sg:phone":"+1 530 836 2126",
    "sg:postcode":"96103",
    "sg:province":"CA",
    "sg:tags":[
        "electric",
        "contractor"
    ],
    "wof:name":"Graeagle Electric",
    "wof:placetype":"venue"
},
  "geometry": {"coordinates":[-120.648571,39.791934],"type":"Point"}
}