{
  "type": "Feature",
  "properties": {
    "iso:country":"US",
    "sg:address":"2620 Buena Vista St",
    "sg:city":"Duarte",
    "sg:classifiers":[
        {
            "category":"Home & Garden",
            "subcategory":"Building Materials",
            "type":"Retail Goods"
        }
    ],
    "sg:phone":"+1 626 303 7755",
    "sg:postcode":"91010",
    "sg:province":"CA",
    "sg:tags":[
        "mixed",
        "concrete"
    ],
    "wof:name":"National Ready Mixed Concrete",
    "wof:placetype":"venue"
},
  "geometry": {"coordinates":[-117.986113,34.11442],"type":"Point"}
}