{
  "type": "Feature",
  "properties": {
    "addr:full":"266 E 7th Ave Chico CA 95926",
    "addr:housenumber":"266",
    "addr:postcode":"95926",
    "addr:street":"E 7Th Ave",
    "iso:country":"US",
    "sg:address":"266 E 7th Ave",
    "sg:city":"Chico",
    "sg:classifiers":[
        {
            "category":"Professional",
            "type":"Services"
        }
    ],
    "sg:phone":"+1 530 894 4082",
    "sg:postcode":"95926",
    "sg:province":"CA",
    "wof:name":"Amber D Kinzler",
    "wof:placetype":"venue"
},
  "geometry": {"coordinates":[-121.84846400000001,39.744898],"type":"Point"}
}