{
  "type": "Feature",
  "properties": {
    "iso:country":"US",
    "sg:address":"Adeline and Hillside",
    "sg:city":"Burlingame",
    "sg:classifiers":[
        {
            "category":"Park",
            "type":"Public Place"
        }
    ],
    "sg:phone":"+1 650 558 7325",
    "sg:postcode":"94010",
    "sg:province":"CA",
    "sg:website":"www.friendsofmillscanyon.org/",
    "wof:name":"Mills Creek Canyon Park",
    "wof:placetype":"venue"
},
  "geometry": {"coordinates":[-122.389944,37.57783],"type":"Point"}
}