{
  "type": "Feature",
  "properties": {
    "addr:full":"798 Cass St Monterey CA 93940",
    "addr:housenumber":"798",
    "addr:postcode":"93940",
    "addr:street":"Cass St",
    "iso:country":"US",
    "sg:address":"798 Cass St",
    "sg:city":"Monterey",
    "sg:classifiers":[
        {
            "category":"Professional",
            "subcategory":"Accounting & Tax Preparation",
            "type":"Services"
        }
    ],
    "sg:phone":"+1 831 372 0121",
    "sg:postcode":"93940",
    "sg:province":"CA",
    "sg:tags":[
        "billing"
    ],
    "wof:name":"Doctors Billing Svc",
    "wof:placetype":"venue"
},
  "geometry": {"coordinates":[-121.895487,36.594091],"type":"Point"}
}