{
  "type": "Feature",
  "properties": {
    "iso:country":"US",
    "sg:address":"1901 W Middlfield Rd",
    "sg:city":"Mountain View",
    "sg:classifiers":[
        {
            "category":"Autos & Motor Vehicles",
            "subcategory":"Automobile Sales",
            "type":"Retail Goods"
        }
    ],
    "sg:phone":"+1 650 869 6227",
    "sg:postcode":"94040",
    "sg:province":"CA",
    "sg:tags":[
        "limo"
    ],
    "sg:website":"www.paloalto-towncar.com",
    "wof:name":"Taxi Meter Town Car",
    "wof:placetype":"venue"
},
  "geometry": {"coordinates":[-122.08717,37.409385],"type":"Point"}
}