{
  "type": "Feature",
  "properties": {
    "addr:full":"424 E Main St Ventura CA 93001",
    "addr:housenumber":"424",
    "addr:postcode":"93001",
    "addr:street":"E Main St",
    "iso:country":"US",
    "sg:address":"424 E Main St",
    "sg:city":"Ventura",
    "sg:classifiers":[
        {
            "category":"Personal",
            "subcategory":"Beauty Salon",
            "type":"Services"
        }
    ],
    "sg:phone":"+1 805 641 2556",
    "sg:postcode":"93001",
    "sg:province":"CA",
    "wof:name":"Cara Mia",
    "wof:placetype":"venue"
},
  "geometry": {"coordinates":[-119.29342,34.280741],"type":"Point"}
}