{
  "type": "Feature",
  "properties": {
    "iso:country":"US",
    "sg:address":"20251 Prairie St",
    "sg:city":"Chatsworth",
    "sg:classifiers":[
        {
            "category":"Shopping",
            "subcategory":"Used Merchandise",
            "type":"Retail Goods"
        }
    ],
    "sg:phone":"+1 818 341 7616",
    "sg:postcode":"91311",
    "sg:province":"CA",
    "sg:tags":[
        "antique"
    ],
    "wof:name":"Vagabond House",
    "wof:placetype":"venue"
},
  "geometry": {"coordinates":[-118.572709,34.239278],"type":"Point"}
}