{
  "type": "Feature",
  "properties": {
    "iso:country":"US",
    "sg:address":"3017 Douglas Blvd",
    "sg:city":"Roseville",
    "sg:classifiers":[
        {
            "category":"Shopping",
            "subcategory":"Computers & Home Electronics",
            "type":"Retail Goods"
        }
    ],
    "sg:phone":"+1 916 774 7597",
    "sg:postcode":"95661",
    "sg:province":"CA",
    "sg:tags":[
        "software"
    ],
    "wof:name":"Parametric Technology Corp",
    "wof:placetype":"venue"
},
  "geometry": {"coordinates":[-121.240742,38.744307],"type":"Point"}
}