{
  "type": "Feature",
  "properties": {
    "iso:country":"US",
    "sg:address":"2375 N Long Beach Blvd",
    "sg:city":"Long Beach",
    "sg:classifiers":[
        {
            "category":"Banks & Credit Unions",
            "subcategory":"Bank",
            "type":"Services"
        }
    ],
    "sg:phone":"+1 562 427 0253",
    "sg:postcode":"90806",
    "sg:province":"CA",
    "sg:tags":[
        "cashing",
        "check"
    ],
    "wof:name":"Money Mart",
    "wof:placetype":"venue"
},
  "geometry": {"coordinates":[-118.189436,33.800282],"type":"Point"}
}