{
  "type": "Feature",
  "properties": {
    "iso:country":"US",
    "sg:address":"2425 Porter Street Suite 10",
    "sg:city":"Soquel",
    "sg:classifiers":[
        {
            "category":"Professional",
            "subcategory":"Lawyer & Legal Services",
            "type":"Services"
        }
    ],
    "sg:phone":"+1 831 464 6884",
    "sg:postcode":"95073",
    "sg:province":"CA",
    "sg:tags":[
        "banking",
        "attorney",
        "law",
        "tax",
        "mortgage"
    ],
    "sg:website":"http://www.pamelaw.com",
    "wof:name":"Law Office of Simmons & Purdy",
    "wof:placetype":"venue"
},
  "geometry": {"coordinates":[-121.95728099999999,36.984255],"type":"Point"}
}