{
  "type": "Feature",
  "properties": {
    "iso:country":"US",
    "sg:address":"2781 S Round Valley Rd",
    "sg:city":"Bishop",
    "sg:classifiers":[
        {
            "category":"Organizations",
            "subcategory":"Membership Organization",
            "type":"Services"
        },
        {
            "category":"Government",
            "subcategory":"Office",
            "type":"Public Place"
        }
    ],
    "sg:phone":"+1 760 387 2686",
    "sg:postcode":"93514",
    "sg:province":"CA",
    "sg:tags":[
        "environmental",
        "ecological",
        "conservation"
    ],
    "sg:website":"http://www.cafiremech.com",
    "wof:name":"Owens Valley Conservation Camp",
    "wof:placetype":"venue"
},
  "geometry": {"coordinates":[-118.55949099999999,37.395233],"type":"Point"}
}