{
  "type": "Feature",
  "properties": {
    "addr:full":"4033 Foothill Blvd Oakland CA 94601",
    "addr:housenumber":"4033",
    "addr:postcode":"94601",
    "addr:street":"Foothill Blvd",
    "iso:country":"US",
    "sg:address":"4033 Foothill Blvd",
    "sg:city":"Oakland",
    "sg:classifiers":[
        {
            "category":"Retail",
            "subcategory":"Auto Repair",
            "type":"Services"
        }
    ],
    "sg:phone":"+1 510 532 8974",
    "sg:postcode":"94601",
    "sg:province":"CA",
    "sg:tags":[
        "automobile",
        "smog",
        "check"
    ],
    "wof:name":"Foothill Smog Test Only",
    "wof:placetype":"venue"
},
  "geometry": {"coordinates":[-122.214996,37.777401],"type":"Point"}
}