{
  "type": "Feature",
  "properties": {
    "addr:full":"123 E Valley Blvd San Gabriel CA 91776",
    "addr:housenumber":"123",
    "addr:postcode":"91776",
    "addr:street":"E Valley Blvd",
    "iso:country":"US",
    "sg:address":"123 E Valley Blvd",
    "sg:city":"San Gabriel",
    "sg:classifiers":[
        {
            "category":"Personal",
            "subcategory":"Beauty Salon",
            "type":"Services"
        }
    ],
    "sg:phone":"+1 626 288 8756",
    "sg:postcode":"91776",
    "sg:province":"CA",
    "sg:tags":[
        "hair"
    ],
    "wof:name":"Unique Hair Saloon",
    "wof:placetype":"venue"
},
  "geometry": {"coordinates":[-118.099146,34.079802],"type":"Point"}
}