{
  "type": "Feature",
  "properties": {
    "addr:full":"3561 El Camino Real Santa Clara CA 95051",
    "addr:housenumber":"3561",
    "addr:postcode":"95051",
    "addr:street":"El Camino Real",
    "iso:country":"US",
    "sg:address":"3561 El Camino Real",
    "sg:city":"Santa Clara",
    "sg:classifiers":[
        {
            "category":"Restaurant",
            "type":"Food & Drink"
        }
    ],
    "sg:phone":"+1 408 899 4655",
    "sg:postcode":"95051",
    "sg:province":"CA",
    "sg:tags":[
        "japanese"
    ],
    "wof:name":"OEC Sushi",
    "wof:placetype":"venue"
},
  "geometry": {"coordinates":[-121.993891,37.352434],"type":"Point"}
}