{
  "type": "Feature",
  "properties": {
    "addr:full":"14911 Beach Boulevard Westminster CA 92683",
    "addr:housenumber":"14911",
    "addr:postcode":"92683",
    "addr:street":"Beach Boulevard",
    "iso:country":"US",
    "sg:address":"14911 Beach Boulevard",
    "sg:city":"Westminster",
    "sg:classifiers":[
        {
            "category":"Autos & Motor Vehicles",
            "subcategory":"Auto Supplies",
            "type":"Retail Goods"
        }
    ],
    "sg:phone":"+1 714 536 7571",
    "sg:postcode":"92683",
    "sg:province":"CA",
    "sg:tags":[
        "tire"
    ],
    "wof:name":"Big O Tires Stores",
    "wof:placetype":"venue"
},
  "geometry": {"coordinates":[-117.989458,33.745832],"type":"Point"}
}