{
  "type": "Feature",
  "properties": {
    "iso:country":"US",
    "sg:address":"1807 E Olympic Blvd",
    "sg:city":"Los Angeles",
    "sg:classifiers":[
        {
            "category":"Manufacturing",
            "subcategory":"Apparel",
            "type":"Manufacturing & Wholesale Goods"
        }
    ],
    "sg:phone":"+1 213 689 0256",
    "sg:postcode":"90021",
    "sg:province":"CA",
    "sg:tags":[
        "sewing",
        "contractor"
    ],
    "wof:name":"Solomons Inc",
    "wof:placetype":"venue"
},
  "geometry": {"coordinates":[-118.23800799999999,34.027391],"type":"Point"}
}