{
  "type": "Feature",
  "properties": {
    "addr:full":"390 N Sepulveda Boulevard El Segundo CA 90245",
    "addr:housenumber":"390",
    "addr:postcode":"90245",
    "addr:street":"N Sepulveda Boulevard",
    "iso:country":"US",
    "sg:address":"390 N Sepulveda Boulevard",
    "sg:city":"El Segundo",
    "sg:classifiers":[
        {
            "category":"Parking",
            "type":"Transportation"
        }
    ],
    "sg:phone":"+1 310 615 1019",
    "sg:postcode":"90245",
    "sg:province":"CA",
    "sg:website":"www.abm.com",
    "wof:name":"Ampco Parking",
    "wof:placetype":"venue"
},
  "geometry": {"coordinates":[-118.39610500000001,33.920691],"type":"Point"}
}