{
  "type": "Feature",
  "properties": {
    "addr:full":"623 Trancas St Napa CA 94558",
    "addr:housenumber":"623",
    "addr:postcode":"94558",
    "addr:street":"Trancas St",
    "iso:country":"US",
    "sg:address":"623 Trancas St",
    "sg:city":"Napa",
    "sg:classifiers":[
        {
            "category":"Restaurant",
            "type":"Food & Drink"
        }
    ],
    "sg:menulink":"http://www.allmenus.com/ca/napa/135568-jamba-juice/menu/",
    "sg:phone":"+1 707 256 3803",
    "sg:postcode":"94558",
    "sg:province":"CA",
    "sg:tags":[
        "smoothy",
        "juice",
        "american"
    ],
    "wof:name":"Jamba Juice",
    "wof:placetype":"venue"
},
  "geometry": {"coordinates":[-122.286924,38.324861],"type":"Point"}
}