{
  "type": "Feature",
  "properties": {
    "iso:country":"US",
    "sg:address":"16240 Arrow Hwy",
    "sg:city":"Irwindale",
    "sg:classifiers":[
        {
            "category":"Manufacturing",
            "subcategory":"Metals",
            "type":"Manufacturing & Wholesale Goods"
        }
    ],
    "sg:phone":"+1 626 338 7227",
    "sg:postcode":"91706",
    "sg:province":"CA",
    "sg:tags":[
        "machine",
        "screw",
        "product"
    ],
    "wof:name":"Rite-On Screw Products",
    "wof:placetype":"venue"
},
  "geometry": {"coordinates":[-117.92943099999999,34.106901],"type":"Point"}
}