{
  "type": "Feature",
  "properties": {
    "iso:country":"US",
    "sg:address":"26051 Merit Cir",
    "sg:city":"Laguna Hills",
    "sg:classifiers":[
        {
            "category":"Organizations",
            "subcategory":"Religious Organization",
            "type":"Services"
        }
    ],
    "sg:phone":"+1 949 582 2567",
    "sg:postcode":"92653",
    "sg:province":"CA",
    "sg:tags":[
        "church"
    ],
    "wof:name":"Sa'Kred Inc",
    "wof:placetype":"venue"
},
  "geometry": {"coordinates":[-117.674702,33.574161],"type":"Point"}
}