{
  "type": "Feature",
  "properties": {
    "addr:full":"2720 S Union Ave Bakersfield CA 93307",
    "addr:housenumber":"2720",
    "addr:postcode":"93307",
    "addr:street":"S Union Ave",
    "iso:country":"US",
    "sg:address":"2720 S Union Ave",
    "sg:city":"Bakersfield",
    "sg:classifiers":[
        {
            "category":"Manufacturing",
            "subcategory":"Tools & Machinery",
            "type":"Manufacturing & Wholesale Goods"
        }
    ],
    "sg:phone":"+1 661 831 8129",
    "sg:postcode":"93307",
    "sg:province":"CA",
    "sg:tags":[
        "shop",
        "repair",
        "machine",
        "industrial",
        "mfg"
    ],
    "wof:name":"Ray Kopf Machine Co",
    "wof:placetype":"venue"
},
  "geometry": {"coordinates":[-119.00305,35.308001],"type":"Point"}
}