{
  "type": "Feature",
  "properties": {
    "addr:full":"3495 Foothill Rd Carpinteria CA 93013",
    "addr:housenumber":"3495",
    "addr:postcode":"93013",
    "addr:street":"Foothill Rd",
    "iso:country":"US",
    "sg:address":"3495 Foothill Rd",
    "sg:city":"Carpinteria",
    "sg:classifiers":[
        {
            "category":"Retail",
            "subcategory":"Pet Boarding",
            "type":"Services"
        }
    ],
    "sg:phone":"+1 805 684 3223",
    "sg:postcode":"93013",
    "sg:province":"CA",
    "sg:tags":[
        "boarding/pet",
        "sitting"
    ],
    "wof:name":"Siegerhaus German Shepherds",
    "wof:placetype":"venue"
},
  "geometry": {"coordinates":[-119.554001,34.418701],"type":"Point"}
}