{
  "type": "Feature",
  "properties": {
    "addr:full":"40015 Sierra Hwy Palmdale CA 93550",
    "addr:housenumber":"40015",
    "addr:postcode":"ca 93550",
    "addr:street":"Sierra Hwy",
    "iso:country":"US",
    "sg:address":"40015 Sierra Hwy",
    "sg:city":"Palmdale",
    "sg:classifiers":[
        {
            "category":"Education",
            "subcategory":"Special Training",
            "type":"Public Place"
        }
    ],
    "sg:phone":"+1 661 947 4025",
    "sg:postcode":"93550",
    "sg:province":"CA",
    "sg:tags":[
        "aircraft",
        "school"
    ],
    "wof:name":"Embry-Riddle Aeronautical Univ",
    "wof:placetype":"venue"
},
  "geometry": {"coordinates":[-118.122671,34.610349],"type":"Point"}
}