{
  "type": "Feature",
  "properties": {
    "iso:country":"US",
    "sg:address":"3117 Pierce St",
    "sg:city":"San Francisco",
    "sg:classifiers":[
        {
            "category":"Building & Trades",
            "subcategory":"Construction",
            "type":"Services"
        }
    ],
    "sg:phone":"+1 415 921 8528",
    "sg:postcode":"94123",
    "sg:province":"CA",
    "sg:tags":[
        "house"
    ],
    "wof:name":"Custom Intl Builders",
    "wof:placetype":"venue"
},
  "geometry": {"coordinates":[-122.43938799999999,37.799267],"type":"Point"}
}