{
  "type": "Feature",
  "properties": {
    "iso:country":"US",
    "sg:address":"1963 S Myrtle Ave",
    "sg:city":"Monrovia",
    "sg:classifiers":[
        {
            "category":"Home & Garden",
            "subcategory":"Garden Supply",
            "type":"Retail Goods"
        }
    ],
    "sg:phone":"+1 626 359 7154",
    "sg:postcode":"91016",
    "sg:province":"CA",
    "sg:tags":[
        "sprinkler"
    ],
    "wof:name":"E E Jensen Sprinklers",
    "wof:placetype":"venue"
},
  "geometry": {"coordinates":[-118.00169200000001,34.129041],"type":"Point"}
}