{
  "type": "Feature",
  "properties": {
    "addr:full":"6401 Pony Express Trl Pollock Pines CA 95726",
    "addr:housenumber":"6401",
    "addr:postcode":"95726",
    "addr:street":"Pony Express Trl",
    "iso:country":"US",
    "sg:address":"6401 Pony Express Trl",
    "sg:city":"Pollock Pines",
    "sg:classifiers":[
        {
            "category":"Food & Beverages",
            "subcategory":"Specialty",
            "type":"Retail Goods"
        }
    ],
    "sg:phone":"+1 530 647 8890",
    "sg:postcode":"95726",
    "sg:province":"CA",
    "sg:tags":[
        "tea",
        "coffee"
    ],
    "wof:name":"Pony Expresso",
    "wof:placetype":"venue"
},
  "geometry": {"coordinates":[-120.58059900000001,38.762823],"type":"Point"}
}