{
  "type": "Feature",
  "properties": {
    "addr:full":"401 W Oak Ln San Gabriel CA 91775",
    "addr:housenumber":"401",
    "addr:postcode":"91775",
    "addr:street":"W Oak Ln",
    "iso:country":"US",
    "sg:address":"401 W Oak Ln",
    "sg:city":"San Gabriel",
    "sg:classifiers":[
        {
            "category":"Professional",
            "type":"Services"
        }
    ],
    "sg:phone":"+1 626 458 8810",
    "sg:postcode":"91775",
    "sg:province":"CA",
    "wof:name":"Baoke Industry USA Inc",
    "wof:placetype":"venue"
},
  "geometry": {"coordinates":[-118.10512199999999,34.112026],"type":"Point"}
}