{
  "type": "Feature",
  "properties": {
    "iso:country":"US",
    "sg:address":"151 Kalmus Dr",
    "sg:city":"Costa Mesa",
    "sg:classifiers":[
        {
            "category":"Wholesale",
            "subcategory":"Stationery",
            "type":"Manufacturing & Wholesale Goods"
        }
    ],
    "sg:phone":"+1 714 754 0117",
    "sg:postcode":"92626",
    "sg:province":"CA",
    "sg:tags":[
        "package"
    ],
    "wof:name":"Techni-Pak Packaging Products",
    "wof:placetype":"venue"
},
  "geometry": {"coordinates":[-117.879858,33.672083],"type":"Point"}
}