{
  "type": "Feature",
  "properties": {
    "addr:full":"7628 Tampa Ave Reseda CA 91335",
    "addr:housenumber":"7628",
    "addr:postcode":"91335",
    "addr:street":"Tampa Ave",
    "iso:country":"US",
    "sg:address":"7628 Tampa Ave",
    "sg:city":"Reseda",
    "sg:classifiers":[
        {
            "category":"Home & Garden",
            "subcategory":"Home Furnishings",
            "type":"Retail Goods"
        },
        {
            "category":"Building & Trades",
            "subcategory":"Construction",
            "type":"Services"
        },
        {
            "category":"Home & Garden",
            "subcategory":"Building Materials",
            "type":"Retail Goods"
        },
        {
            "category":"Commercial Area",
            "type":"Public Place"
        },
        {
            "category":"Manufacturing",
            "subcategory":"Glass & Minerals",
            "type":"Manufacturing & Wholesale Goods"
        },
        {
            "category":"Manufacturing",
            "subcategory":"Building Materials",
            "type":"Manufacturing & Wholesale Goods"
        }
    ],
    "sg:phone":"+1 818 345 1020",
    "sg:postcode":"91335",
    "sg:province":"CA",
    "sg:tags":[
        "plate",
        "installation",
        "windows-repair",
        "top",
        "window",
        "shower",
        "glass-auto",
        "mirror",
        "front",
        "door",
        "table",
        "enclosure",
        "store",
        "replacement"
    ],
    "sg:website":"http://www.tampaglass.com",
    "wof:name":"Tampa Glass Inc.",
    "wof:placetype":"venue"
},
  "geometry": {"coordinates":[-118.55349699999999,34.209019],"type":"Point"}
}