{
  "type": "Feature",
  "properties": {
    "addr:full":"2815 Cam del Rio S San Diego CA 92108",
    "addr:housenumber":"2815",
    "addr:postcode":"92108",
    "addr:street":"Cam Del Rio S",
    "iso:country":"US",
    "sg:address":"2815 Cam del Rio S",
    "sg:city":"San Diego",
    "sg:classifiers":[
        {
            "category":"Building & Trades",
            "subcategory":"Construction",
            "type":"Services"
        }
    ],
    "sg:phone":"+1 619 692 1554",
    "sg:postcode":"92108",
    "sg:province":"CA",
    "sg:tags":[
        "painter"
    ],
    "wof:name":"Pacific Painting Svc",
    "wof:placetype":"venue"
},
  "geometry": {"coordinates":[-117.13484800000001,32.770518],"type":"Point"}
}