{
  "type": "Feature",
  "properties": {
    "addr:full":"4600 Broadway St Sacramento CA 95820",
    "addr:housenumber":"4600",
    "addr:postcode":"95820",
    "addr:street":"Broadway St",
    "iso:country":"US",
    "sg:address":"4600 Broadway St",
    "sg:city":"Sacramento",
    "sg:classifiers":[
        {
            "category":"Professional",
            "subcategory":"Engineering",
            "type":"Services"
        }
    ],
    "sg:phone":"+1 916 731 8153",
    "sg:postcode":"95820",
    "sg:province":"CA",
    "sg:tags":[
        "engineer"
    ],
    "wof:name":"Frank M Booth Inc",
    "wof:placetype":"venue"
},
  "geometry": {"coordinates":[-121.45090999999999,38.54667],"type":"Point"}
}