{
  "type": "Feature",
  "properties": {
    "iso:country":"US",
    "sg:address":"126 N Madrid Ave",
    "sg:city":"Newbury Park",
    "sg:classifiers":[
        {
            "category":"Manufacturing",
            "subcategory":"Printing",
            "type":"Manufacturing & Wholesale Goods"
        }
    ],
    "sg:phone":"+1 805 499 4854",
    "sg:postcode":"91320",
    "sg:province":"CA",
    "sg:tags":[
        "consulting",
        "periodical",
        "business"
    ],
    "wof:name":"Keith Wade",
    "wof:placetype":"venue"
},
  "geometry": {"coordinates":[-118.923704,34.179899],"type":"Point"}
}