{
  "type": "Feature",
  "properties": {
    "addr:full":"50 Bellefontaine St Pasadena CA 91105",
    "addr:housenumber":"50",
    "addr:postcode":"91105",
    "addr:street":"Bellefontaine St",
    "iso:country":"US",
    "sg:address":"50 Bellefontaine St",
    "sg:city":"Pasadena",
    "sg:classifiers":[
        {
            "category":"Health Services",
            "subcategory":"Doctor",
            "type":"Services"
        },
        {
            "category":"Health Services",
            "subcategory":"Health Practitioner",
            "type":"Services"
        }
    ],
    "sg:phone":"+1 626 395 0150",
    "sg:postcode":"91105",
    "sg:province":"CA",
    "sg:tags":[
        "control",
        "physician",
        "management",
        "weight",
        "loss",
        "surgeons"
    ],
    "wof:name":"Healthy For Life",
    "wof:placetype":"venue"
},
  "geometry": {"coordinates":[-118.151802,34.131592],"type":"Point"}
}