{
  "type": "Feature",
  "properties": {
    "iso:country":"US",
    "sg:address":"3801 3rd St Ste 616",
    "sg:city":"San Francisco",
    "sg:classifiers":[
        {
            "category":"Organizations",
            "subcategory":"Non-profit Organization",
            "type":"Services"
        }
    ],
    "sg:phone":"+1 415 647 3728",
    "sg:postcode":"94124",
    "sg:province":"CA",
    "sg:tags":[
        "service/non-profit",
        "community"
    ],
    "sg:website":"www.rencenter.org/bay.htm",
    "wof:name":"Bayview Business Resource Center",
    "wof:placetype":"venue"
},
  "geometry": {"coordinates":[-122.38738600000001,37.741948],"type":"Point"}
}