{
  "type": "Feature",
  "properties": {
    "addr:full":"5030 Bonita Rd Bonita CA 91902",
    "addr:housenumber":"5030",
    "addr:postcode":"91902",
    "addr:street":"Bonita Rd",
    "iso:country":"US",
    "sg:address":"5030 Bonita Rd",
    "sg:city":"Bonita",
    "sg:classifiers":[
        {
            "category":"Health Services",
            "subcategory":"Chiropractor",
            "type":"Services"
        }
    ],
    "sg:phone":"+1 619 479 7473",
    "sg:postcode":"91902",
    "sg:province":"CA",
    "wof:name":"RISE Chiropractic",
    "wof:placetype":"venue"
},
  "geometry": {"coordinates":[-117.020173,32.671886],"type":"Point"}
}