{
  "type": "Feature",
  "properties": {
    "addr:full":"1528 Pacific Ave Santa Cruz CA 95060",
    "addr:housenumber":"1528",
    "addr:postcode":"95060",
    "addr:street":"Pacific Ave",
    "iso:country":"US",
    "sg:address":"1528 Pacific Ave",
    "sg:city":"Santa Cruz",
    "sg:classifiers":[
        {
            "category":"Shopping",
            "subcategory":"Hobbies, Toys, & Games",
            "type":"Retail Goods"
        }
    ],
    "sg:phone":"+1 831 425 1217",
    "sg:postcode":"95060",
    "sg:province":"CA",
    "sg:tags":[
        "shop",
        "rock"
    ],
    "wof:name":"Crystal Kaleidoscope",
    "wof:placetype":"venue"
},
  "geometry": {"coordinates":[-122.026865,36.976662],"type":"Point"}
}