{
  "type": "Feature",
  "properties": {
    "iso:country":"US",
    "sg:address":"46484 Oonay Nation Rd",
    "sg:city":"Oakhurst",
    "sg:classifiers":[
        {
            "category":"Building & Trades",
            "subcategory":"Plumbing",
            "type":"Services"
        }
    ],
    "sg:phone":"+1 559 683 5627",
    "sg:postcode":"93614",
    "sg:province":"CA",
    "sg:tags":[
        "conditioning",
        "air",
        "system",
        "contractor"
    ],
    "wof:name":"Ponderosa Air",
    "wof:placetype":"venue"
},
  "geometry": {"coordinates":[-119.70361,37.234206],"type":"Point"}
}