{
  "type": "Feature",
  "properties": {
    "iso:country":"US",
    "sg:address":"973 E Front St",
    "sg:city":"Ventura",
    "sg:classifiers":[
        {
            "category":"Shopping",
            "type":"Retail Goods"
        }
    ],
    "sg:phone":"+1 805 652 0104",
    "sg:postcode":"93001",
    "sg:province":"CA",
    "sg:tags":[
        "merchandise"
    ],
    "wof:name":"Larson Art",
    "wof:placetype":"venue"
},
  "geometry": {"coordinates":[-119.28648800000001,34.277097],"type":"Point"}
}