{
  "type": "Feature",
  "properties": {
    "addr:full":"2055 N Broadway Walnut Creek CA 94596",
    "addr:housenumber":"2055",
    "addr:postcode":"94596",
    "addr:street":"N Broadway",
    "iso:country":"US",
    "sg:address":"2055 N Broadway",
    "sg:city":"Walnut Creek",
    "sg:classifiers":[
        {
            "category":"Professional",
            "subcategory":"Lawyer & Legal Services",
            "type":"Services"
        }
    ],
    "sg:phone":"+1 925 974 0800",
    "sg:postcode":"94596",
    "sg:province":"CA",
    "sg:tags":[
        "attorney"
    ],
    "wof:name":"Madsen & Wolch LLP",
    "wof:placetype":"venue"
},
  "geometry": {"coordinates":[-122.06164,37.907068],"type":"Point"}
}