{
  "type": "Feature",
  "properties": {
    "iso:country":"US",
    "sg:address":"16134 Nordhoff St",
    "sg:city":"North Hills",
    "sg:classifiers":[
        {
            "category":"Shopping",
            "subcategory":"Discount & Variety Stores",
            "type":"Retail Goods"
        }
    ],
    "sg:phone":"+1 818 830 1801",
    "sg:postcode":"91343",
    "sg:province":"CA",
    "wof:name":"Dollar Store Of North Hills",
    "wof:placetype":"venue"
},
  "geometry": {"coordinates":[-118.48317,34.235554],"type":"Point"}
}