{
  "type": "Feature",
  "properties": {
    "iso:country":"US",
    "sg:address":"10920 Cll Real",
    "sg:city":"Goleta",
    "sg:classifiers":[
        {
            "category":"Retail",
            "subcategory":"Animal Services",
            "type":"Services"
        }
    ],
    "sg:phone":"+1 805 685 4440",
    "sg:postcode":"93117",
    "sg:province":"CA",
    "sg:tags":[
        "horse",
        "training"
    ],
    "wof:name":"Horseman's Hangout M Nelson",
    "wof:placetype":"venue"
},
  "geometry": {"coordinates":[-119.994454,34.460717],"type":"Point"}
}