{
  "type": "Feature",
  "properties": {
    "addr:full":"1001 Texas St Fairfield CA 94533",
    "addr:housenumber":"1001",
    "addr:postcode":"94533",
    "addr:street":"Texas St",
    "iso:country":"US",
    "sg:address":"1001 Texas St",
    "sg:city":"Fairfield",
    "sg:classifiers":[
        {
            "category":"Restaurant",
            "type":"Food & Drink"
        }
    ],
    "sg:phone":"+1 707 426 2056",
    "sg:postcode":"94533",
    "sg:province":"CA",
    "sg:tags":[
        "shop",
        "coffee"
    ],
    "wof:name":"Heavenly Grounds",
    "wof:placetype":"venue"
},
  "geometry": {"coordinates":[-122.047213,38.249233],"type":"Point"}
}