{
  "type": "Feature",
  "properties": {
    "iso:country":"US",
    "sg:address":"23785 Reynolds Hwy",
    "sg:city":"Willits",
    "sg:classifiers":[
        {
            "category":"Farming",
            "subcategory":"Livestock Farm",
            "type":"Manufacturing & Wholesale Goods"
        }
    ],
    "sg:phone":"+1 707 459 5790",
    "sg:postcode":"95490",
    "sg:province":"CA",
    "sg:tags":[
        "feeding",
        "ranch"
    ],
    "wof:name":"P/6 Ranch",
    "wof:placetype":"venue"
},
  "geometry": {"coordinates":[-123.312563,39.434485],"type":"Point"}
}