{
  "type": "Feature",
  "properties": {
    "addr:full":"1693 Market St San Francisco CA 94103",
    "addr:housenumber":"1693",
    "addr:postcode":"94103",
    "addr:street":"Market St",
    "iso:country":"US",
    "sg:address":"1693 Market St",
    "sg:city":"San Francisco",
    "sg:classifiers":[
        {
            "category":"Travel",
            "subcategory":"Hotels & Motels",
            "type":"Entertainment"
        }
    ],
    "sg:phone":"+1 415 558 1700",
    "sg:postcode":"94103",
    "sg:province":"CA",
    "wof:name":"CSV Hospitality LLC",
    "wof:placetype":"venue"
},
  "geometry": {"coordinates":[-122.422112,37.772579],"type":"Point"}
}