{
  "type": "Feature",
  "properties": {
    "iso:country":"US",
    "sg:address":"12825 Ventura Blvd",
    "sg:city":"Studio City",
    "sg:classifiers":[
        {
            "category":"Personal",
            "subcategory":"Beauty Salon",
            "type":"Services"
        }
    ],
    "sg:phone":"+1 818 769 4102",
    "sg:postcode":"91604",
    "sg:province":"CA",
    "sg:tags":[
        "manicuring"
    ],
    "wof:name":"Nails By Tina",
    "wof:placetype":"venue"
},
  "geometry": {"coordinates":[-118.411793,34.144851],"type":"Point"}
}