{
  "type": "Feature",
  "properties": {
    "iso:country":"US",
    "sg:address":"30041 Red Setter Pl",
    "sg:city":"Sun City",
    "sg:classifiers":[
        {
            "category":"Freight",
            "type":"Transportation"
        }
    ],
    "sg:phone":"+1 951 244 8921",
    "sg:postcode":"92587",
    "sg:province":"CA",
    "sg:tags":[
        "operator",
        "trucking"
    ],
    "wof:name":"Wrome Express",
    "wof:placetype":"venue"
},
  "geometry": {"coordinates":[-117.254593,33.684242],"type":"Point"}
}