{
  "type": "Feature",
  "properties": {
    "iso:country":"US",
    "sg:address":"1423 J St",
    "sg:city":"Sacramento",
    "sg:classifiers":[
        {
            "category":"Retail",
            "subcategory":"Auto Repair",
            "type":"Services"
        }
    ],
    "sg:phone":"+1 916 443 1209",
    "sg:postcode":"95814",
    "sg:province":"CA",
    "sg:tags":[
        "transmission"
    ],
    "wof:name":"Eternal Transmissions",
    "wof:placetype":"venue"
},
  "geometry": {"coordinates":[-121.486755,38.578619],"type":"Point"}
}