{
  "type": "Feature",
  "properties": {
    "acgov:api":"0.0",
    "acgov:type":"Small Schools",
    "addr:full":"5263 Broadway Terrace Oakland CA",
    "wof:categories":[
        "education_and_religion:education=school"
    ],
    "wof:name":"Far West",
    "wof:placetype":"venue"
},
  "geometry": {"coordinates":[-122.24909470490832,37.83709733079568],"type":"Point"}
}