{
  "type": "Feature",
  "properties": {
    "addr:full":"323 Cll Neblina San Clemente CA 92672",
    "addr:housenumber":"323",
    "addr:postcode":"92672",
    "addr:street":"Cll Neblina",
    "iso:country":"US",
    "sg:address":"323 Cll Neblina",
    "sg:city":"San Clemente",
    "sg:classifiers":[
        {
            "category":"Building & Trades",
            "subcategory":"Electrical",
            "type":"Services"
        }
    ],
    "sg:phone":"+1 949 361 5734",
    "sg:postcode":"92672",
    "sg:province":"CA",
    "sg:tags":[
        "television",
        "installation",
        "closed",
        "tv",
        "circuit",
        "plasma"
    ],
    "wof:name":"Nucctv Industries",
    "wof:placetype":"venue"
},
  "geometry": {"coordinates":[-117.612015,33.438136],"type":"Point"}
}