{
  "type": "Feature",
  "properties": {
    "addr:full":"7770 Pardee Ln Oakland CA 94621",
    "addr:housenumber":"7770",
    "addr:postcode":"94621",
    "addr:street":"Pardee Ln",
    "iso:country":"US",
    "sg:address":"7770 Pardee Ln",
    "sg:city":"Oakland",
    "sg:classifiers":[
        {
            "category":"Professional",
            "subcategory":"Research",
            "type":"Services"
        }
    ],
    "sg:phone":"+1 510 746 7334",
    "sg:postcode":"94621",
    "sg:province":"CA",
    "sg:tags":[
        "educational"
    ],
    "sg:website":"http://www.sfei.org",
    "wof:name":"San Francisco Estuary Institute",
    "wof:placetype":"venue"
},
  "geometry": {"coordinates":[-122.20653299999999,37.742049],"type":"Point"}
}