{
  "type": "Feature",
  "properties": {
    "iso:country":"US",
    "sg:address":"689 H St",
    "sg:city":"Chula Vista",
    "sg:classifiers":[
        {
            "category":"Restaurant",
            "type":"Food & Drink"
        }
    ],
    "sg:phone":"+1 619 691 8848",
    "sg:postcode":"91910",
    "sg:province":"CA",
    "sg:tags":[
        "mexican"
    ],
    "wof:name":"Tacos El Gordo",
    "wof:placetype":"venue"
},
  "geometry": {"coordinates":[-117.093307,32.630244],"type":"Point"}
}