{
  "type": "Feature",
  "properties": {
    "iso:country":"US",
    "sg:address":"2930 Shattuck Ave Ste 200",
    "sg:city":"Oakland",
    "sg:classifiers":[
        {
            "category":"Personal",
            "subcategory":"Skin Care",
            "type":"Services"
        }
    ],
    "sg:phone":"+1 510 465 7635",
    "sg:postcode":"94705",
    "sg:province":"CA",
    "wof:name":"Heads Together Phase III",
    "wof:placetype":"venue"
},
  "geometry": {"coordinates":[-122.266868,37.855859],"type":"Point"}
}