{
  "type": "Feature",
  "properties": {
    "iso:country":"US",
    "sg:address":"4100 Throwita Way",
    "sg:city":"Placerville",
    "sg:classifiers":[
        {
            "category":"Utilities",
            "subcategory":"Recycling",
            "type":"Services"
        }
    ],
    "sg:phone":"+1 530 642 1176",
    "sg:postcode":"95667",
    "sg:province":"CA",
    "wof:name":"Westrn El Dorado Recycling Ctr",
    "wof:placetype":"venue"
},
  "geometry": {"coordinates":[-120.81461299999999,38.701839],"type":"Point"}
}