{
  "type": "Feature",
  "properties": {
    "addr:full":"6166 Enterprise Dr Diamond Springs CA 95619",
    "addr:housenumber":"6166",
    "addr:postcode":"ca 95619",
    "addr:street":"Enterprise Dr Diamond Springs",
    "iso:country":"US",
    "sg:address":"6166 Enterprise Dr",
    "sg:city":"Diamond Springs",
    "sg:classifiers":[
        {
            "category":"Wholesale",
            "subcategory":"Hardware",
            "type":"Manufacturing & Wholesale Goods"
        }
    ],
    "sg:phone":"+1 530 621 3070",
    "sg:postcode":"95619",
    "sg:province":"CA",
    "sg:tags":[
        "fastener"
    ],
    "wof:name":"Fastener Depot",
    "wof:placetype":"venue"
},
  "geometry": {"coordinates":[-120.829255,38.694844],"type":"Point"}
}