{
  "type": "Feature",
  "properties": {
    "addr:full":"333 E St Eureka CA 95501",
    "addr:housenumber":"333",
    "addr:postcode":"95501",
    "addr:street":"E St",
    "iso:country":"US",
    "sg:address":"333 E St",
    "sg:city":"Eureka",
    "sg:classifiers":[
        {
            "category":"Real Estate",
            "subcategory":"Real Estate Operator",
            "type":"Services"
        }
    ],
    "sg:phone":"+1 707 445 2990",
    "sg:postcode":"95501",
    "sg:province":"CA",
    "sg:tags":[
        "apartment"
    ],
    "wof:name":"Eureka Central Residence",
    "wof:placetype":"venue"
},
  "geometry": {"coordinates":[-124.16729599999999,40.803173],"type":"Point"}
}