{
  "type": "Feature",
  "properties": {
    "iso:country":"US",
    "sg:address":"4500 Campus Dr",
    "sg:city":"Newport Beach",
    "sg:classifiers":[
        {
            "category":"Professional",
            "subcategory":"Business Services",
            "type":"Services"
        }
    ],
    "sg:phone":"+1 949 833 9790",
    "sg:postcode":"92660",
    "sg:province":"CA",
    "sg:tags":[
        "paging",
        "answering"
    ],
    "wof:name":"A-Action Telephone Answering",
    "wof:placetype":"venue"
},
  "geometry": {"coordinates":[-117.865795,33.671281],"type":"Point"}
}