{
  "type": "Feature",
  "properties": {
    "iso:country":"US",
    "sg:address":"3338 Arden Way",
    "sg:city":"Sacramento",
    "sg:classifiers":[
        {
            "category":"Food & Beverages",
            "subcategory":"Groceries & Convenience Stores",
            "type":"Retail Goods"
        }
    ],
    "sg:phone":"+1 916 480 0321",
    "sg:postcode":"95825",
    "sg:province":"CA",
    "sg:tags":[
        "grocer"
    ],
    "wof:name":"Longs Drug",
    "wof:placetype":"venue"
},
  "geometry": {"coordinates":[-121.386639,38.595709],"type":"Point"}
}