{
  "type": "Feature",
  "properties": {
    "addr:full":"230 Campbell Ave Redlands CA 92373",
    "addr:housenumber":"230",
    "addr:postcode":"92373",
    "addr:street":"Campbell Ave",
    "iso:country":"US",
    "sg:address":"230 Campbell Ave",
    "sg:city":"Redlands",
    "sg:classifiers":[
        {
            "category":"Building & Trades",
            "subcategory":"Construction",
            "type":"Services"
        }
    ],
    "sg:phone":"+1 909 792 7849",
    "sg:postcode":"92373",
    "sg:province":"CA",
    "sg:tags":[
        "contractor"
    ],
    "wof:name":"Donna Co the",
    "wof:placetype":"venue"
},
  "geometry": {"coordinates":[-117.162003,34.040501],"type":"Point"}
}