{
  "type": "Feature",
  "properties": {
    "addr:full":"17594 Colima Rd Rowland Heights CA 91748",
    "addr:housenumber":"17594",
    "addr:postcode":"91748",
    "addr:street":"Colima Rd",
    "iso:country":"US",
    "sg:address":"17594 Colima Rd",
    "sg:city":"Rowland Heights",
    "sg:classifiers":[
        {
            "category":"Personal",
            "subcategory":"Beauty Salon",
            "type":"Services"
        }
    ],
    "sg:phone":"+1 626 964 0919",
    "sg:postcode":"91748",
    "sg:province":"CA",
    "wof:name":"Elysee Salon",
    "wof:placetype":"venue"
},
  "geometry": {"coordinates":[-117.923636,33.99033],"type":"Point"}
}