{
  "type": "Feature",
  "properties": {
    "iso:country":"US",
    "sg:address":"15951 Caras Ct",
    "sg:city":"Ramona",
    "sg:classifiers":[
        {
            "category":"Communications",
            "subcategory":"Film & Video Production",
            "type":"Services"
        }
    ],
    "sg:phone":"+1 760 788 4474",
    "sg:postcode":"92065",
    "sg:province":"CA",
    "sg:tags":[
        "audio"
    ],
    "wof:name":"Audio Video Technologies",
    "wof:placetype":"venue"
},
  "geometry": {"coordinates":[-116.76025,33.00285],"type":"Point"}
}