{
  "type": "Feature",
  "properties": {
    "addr:full":"737 Pearl Street Ste 201 La Jolla CA 92037",
    "addr:housenumber":"737",
    "addr:postcode":"92037",
    "addr:street":"Pearl Street Ste 201",
    "iso:country":"US",
    "sg:address":"737 Pearl Street Ste 201",
    "sg:city":"La Jolla",
    "sg:classifiers":[
        {
            "category":"Personal",
            "subcategory":"Massage",
            "type":"Services"
        },
        {
            "category":"Personal",
            "subcategory":"Hair Removal",
            "type":"Services"
        }
    ],
    "sg:phone":"+1 858 456 0008",
    "sg:postcode":"92037",
    "sg:province":"CA",
    "sg:website":"www.rejuve-lajolla.com/",
    "wof:name":"Rejuve Med Spa Laser Hair Removal",
    "wof:placetype":"venue"
},
  "geometry": {"coordinates":[-117.275206,32.839707],"type":"Point"}
}