{
  "type": "Feature",
  "properties": {
    "iso:country":"US",
    "sg:address":"22549 Sawmill Flat Rd",
    "sg:city":"Sonora",
    "sg:classifiers":[
        {
            "category":"Manufacturing",
            "subcategory":"Wood Products",
            "type":"Manufacturing & Wholesale Goods"
        }
    ],
    "sg:phone":"+1 209 536 9147",
    "sg:postcode":"95370",
    "sg:province":"CA",
    "sg:tags":[
        "mfg"
    ],
    "wof:name":"Rattlesnake Gulch Forge",
    "wof:placetype":"venue"
},
  "geometry": {"coordinates":[-120.379132,38.033327],"type":"Point"}
}