{
  "type": "Feature",
  "properties": {
    "addr:full":"1 Bush St San Francisco CA 94104",
    "addr:housenumber":"1",
    "addr:postcode":"94104",
    "addr:street":"Bush St",
    "iso:country":"US",
    "sg:address":"1 Bush St",
    "sg:city":"San Francisco",
    "sg:classifiers":[
        {
            "category":"Real Estate",
            "subcategory":"Real Estate Agent",
            "type":"Services"
        }
    ],
    "sg:phone":"+1 415 273 7900",
    "sg:postcode":"94104",
    "sg:province":"CA",
    "sg:tags":[
        "management"
    ],
    "wof:name":"One Bush I Delaware Inc",
    "wof:placetype":"venue"
},
  "geometry": {"coordinates":[-122.39957200000001,37.791326],"type":"Point"}
}