{
  "type": "Feature",
  "properties": {
    "iso:country":"US",
    "sg:address":"8246 Valley View St",
    "sg:city":"Buena Park",
    "sg:classifiers":[
        {
            "category":"Organizations",
            "subcategory":"Religious Organization",
            "type":"Services"
        }
    ],
    "sg:phone":"+1 714 226 9191",
    "sg:postcode":"90620",
    "sg:province":"CA",
    "sg:tags":[
        "church"
    ],
    "wof:name":"Ban Sulk Methodist Church",
    "wof:placetype":"venue"
},
  "geometry": {"coordinates":[-118.028313,33.843395],"type":"Point"}
}