{
  "type": "Feature",
  "properties": {
    "addr:full":"727 E Pico Boulevard Los Angeles CA 90021",
    "addr:housenumber":"727",
    "addr:postcode":"90021",
    "addr:street":"E Pico Boulevard",
    "iso:country":"US",
    "sg:address":"727 E Pico Boulevard",
    "sg:city":"Los Angeles",
    "sg:classifiers":[
        {
            "category":"Personal",
            "subcategory":"Nail Salon",
            "type":"Services"
        }
    ],
    "sg:phone":"+1 213 748 4651",
    "sg:postcode":"90021",
    "sg:province":"CA",
    "wof:name":"Top Ten",
    "wof:placetype":"venue"
},
  "geometry": {"coordinates":[-118.25334700000001,34.032489],"type":"Point"}
}