{
  "type": "Feature",
  "properties": {
    "iso:country":"US",
    "sg:address":"7813 Auburn Woods Dr",
    "sg:city":"Citrus Heights",
    "sg:classifiers":[
        {
            "category":"Building & Trades",
            "subcategory":"Plumbing",
            "type":"Services"
        }
    ],
    "sg:phone":"+1 916 722 9521",
    "sg:postcode":"95610",
    "sg:province":"CA",
    "sg:tags":[
        "contractor"
    ],
    "wof:name":"GM Fire / Mechanical",
    "wof:placetype":"venue"
},
  "geometry": {"coordinates":[-121.25990299999999,38.707798],"type":"Point"}
}