{
  "type": "Feature",
  "properties": {
    "addr:full":"8460 Reseda Blvd Northridge CA 91324",
    "addr:housenumber":"8460",
    "addr:postcode":"91324",
    "addr:street":"Reseda Blvd",
    "iso:country":"US",
    "sg:address":"8460 Reseda Blvd",
    "sg:city":"Northridge",
    "sg:classifiers":[
        {
            "category":"Autos & Motor Vehicles",
            "subcategory":"Auto Supplies",
            "type":"Retail Goods"
        }
    ],
    "sg:phone":"+1 818 886 8995",
    "sg:postcode":"91324",
    "sg:province":"CA",
    "sg:tags":[
        "tire"
    ],
    "wof:name":"Express Tire & Auto Repair",
    "wof:placetype":"venue"
},
  "geometry": {"coordinates":[-118.53600400000001,34.221472],"type":"Point"}
}