{
  "type": "Feature",
  "properties": {
    "addr:full":"239 Harbor Way South San Francisco CA 94080",
    "addr:housenumber":"239",
    "addr:postcode":"94080",
    "addr:street":"Harbor Way",
    "iso:country":"US",
    "sg:address":"239 Harbor Way",
    "sg:city":"South San Francisco",
    "sg:classifiers":[
        {
            "category":"Airline",
            "type":"Transportation"
        }
    ],
    "sg:phone":"+1 650 742 7934",
    "sg:postcode":"94080",
    "sg:province":"CA",
    "sg:tags":[
        "scheduled",
        "air"
    ],
    "wof:name":"Korean Air Cargo Corp",
    "wof:placetype":"venue"
},
  "geometry": {"coordinates":[-122.40008,37.649726],"type":"Point"}
}