{
  "type": "Feature",
  "properties": {
    "iso:country":"US",
    "sg:address":"13586 Marengo Rd",
    "sg:city":"Galt",
    "sg:classifiers":[
        {
            "category":"Building & Trades",
            "subcategory":"Landscaping Services",
            "type":"Services"
        }
    ],
    "sg:phone":"+1 209 329 2986",
    "sg:postcode":"95632",
    "sg:province":"CA",
    "sg:tags":[
        "tree"
    ],
    "wof:name":"Cliff's Tree Svc",
    "wof:placetype":"venue"
},
  "geometry": {"coordinates":[-121.282674,38.266163],"type":"Point"}
}