{
  "type": "Feature",
  "properties": {
    "addr:full":"2247 18th Ave Kingsburg CA 93631",
    "addr:housenumber":"2247",
    "addr:postcode":"93631",
    "addr:street":"18Th Ave",
    "iso:country":"US",
    "sg:address":"2247 18th Ave",
    "sg:city":"Kingsburg",
    "sg:classifiers":[
        {
            "category":"Freight",
            "type":"Transportation"
        }
    ],
    "sg:phone":"+1 559 897 1414",
    "sg:postcode":"93631",
    "sg:province":"CA",
    "wof:name":"Brooks Produce",
    "wof:placetype":"venue"
},
  "geometry": {"coordinates":[-119.54794699999999,36.521526],"type":"Point"}
}