{
  "type": "Feature",
  "properties": {
    "iso:country":"US",
    "sg:address":"2247 18th Ave",
    "sg:city":"Kingsburg",
    "sg:classifiers":[
        {
            "category":"Freight",
            "type":"Transportation"
        }
    ],
    "sg:phone":"+1 559 897 1414",
    "sg:postcode":"93631",
    "sg:province":"CA",
    "wof:name":"Brooks Produce",
    "wof:placetype":"venue"
},
  "geometry": {"coordinates":[-119.547947,36.521526],"type":"Point"}
}