{
  "type": "Feature",
  "properties": {
    "iso:country":"US",
    "sg:address":"500 Porter Way",
    "sg:city":"Placentia",
    "sg:classifiers":[
        {
            "category":"Manufacturing",
            "subcategory":"Signs",
            "type":"Manufacturing & Wholesale Goods"
        }
    ],
    "sg:phone":"+1 714 996 4343",
    "sg:postcode":"92870",
    "sg:province":"CA",
    "sg:tags":[
        "mfg"
    ],
    "wof:name":"One Stop & Graphic",
    "wof:placetype":"venue"
},
  "geometry": {"coordinates":[-117.869088,33.866813],"type":"Point"}
}