{
  "type": "Feature",
  "properties": {
    "addr:full":"3955 Bonita Rd Bldg A Bonita CA 91902",
    "addr:housenumber":"3955",
    "addr:postcode":"91902",
    "addr:street":"Bonita Rd Bldg A",
    "iso:country":"US",
    "sg:address":"3955 Bonita Rd Bldg A",
    "sg:city":"Bonita",
    "sg:classifiers":[
        {
            "category":"Education",
            "subcategory":"Special Training",
            "type":"Public Place"
        }
    ],
    "sg:phone":"+1 619 409 6418",
    "sg:postcode":"91902",
    "sg:province":"CA",
    "sg:tags":[
        "career",
        "counseling",
        "vocational"
    ],
    "wof:name":"Welcome Back Center",
    "wof:placetype":"venue"
},
  "geometry": {"coordinates":[-117.04179999999999,32.657413],"type":"Point"}
}