{
  "type": "Feature",
  "properties": {
    "addr:full":"3801 Pegasus Dr Bakersfield CA 93308",
    "addr:housenumber":"3801",
    "addr:postcode":"93308",
    "addr:street":"Pegasus Dr",
    "iso:country":"US",
    "sg:address":"3801 Pegasus Dr",
    "sg:city":"Bakersfield",
    "sg:classifiers":[
        {
            "category":"Government",
            "subcategory":"Office",
            "type":"Public Place"
        }
    ],
    "sg:phone":"+1 661 391 6162",
    "sg:postcode":"93308",
    "sg:province":"CA",
    "sg:tags":[
        "federal"
    ],
    "wof:name":"Natural Resources Conservation",
    "wof:placetype":"venue"
},
  "geometry": {"coordinates":[-119.07205500000001,35.439083],"type":"Point"}
}