{
  "type": "Feature",
  "properties": {
    "addr:full":"9172 Greenback Ln Orangevale CA 95662",
    "addr:housenumber":"9172",
    "addr:postcode":"95662",
    "addr:street":"Greenback Ln",
    "iso:country":"US",
    "sg:address":"9172 Greenback Ln",
    "sg:city":"Orangevale",
    "sg:classifiers":[
        {
            "category":"Wholesale",
            "subcategory":"Jewelry",
            "type":"Manufacturing & Wholesale Goods"
        }
    ],
    "sg:phone":"+1 916 987 1787",
    "sg:postcode":"95662",
    "sg:province":"CA",
    "sg:tags":[
        "stone",
        "book",
        "beads"
    ],
    "wof:name":"Beauty & The Beads",
    "wof:placetype":"venue"
},
  "geometry": {"coordinates":[-121.211775,38.678178],"type":"Point"}
}