{
  "type": "Feature",
  "properties": {
    "iso:country":"US",
    "sg:address":"2701 S Vermont Ave",
    "sg:city":"Los Angeles",
    "sg:classifiers":[
        {
            "category":"Restaurant",
            "type":"Food & Drink"
        }
    ],
    "sg:phone":"+1 323 735 0599",
    "sg:postcode":"90007",
    "sg:province":"CA",
    "sg:tags":[
        "burger"
    ],
    "wof:name":"Olympian Burgers",
    "wof:placetype":"venue"
},
  "geometry": {"coordinates":[-118.291935,34.030198],"type":"Point"}
}