{
  "type": "Feature",
  "properties": {
    "addr:full":"7910 Frost St San Diego CA 92123",
    "addr:housenumber":"7910",
    "addr:postcode":"92123",
    "addr:street":"Frost St",
    "iso:country":"US",
    "sg:address":"7910 Frost St",
    "sg:city":"San Diego",
    "sg:classifiers":[
        {
            "category":"Health Services",
            "subcategory":"Doctor",
            "type":"Services"
        }
    ],
    "sg:phone":"+1 858 560 1161",
    "sg:postcode":"92123",
    "sg:province":"CA",
    "sg:tags":[
        "clinic"
    ],
    "wof:name":"Plastic Surgery-Face",
    "wof:placetype":"venue"
},
  "geometry": {"coordinates":[-117.154732,32.800329],"type":"Point"}
}