{
  "type": "Feature",
  "properties": {
    "addr:full":"2285 Whitney Ave Summerland CA 93067",
    "addr:housenumber":"2285",
    "addr:postcode":"93067",
    "addr:street":"Whitney Ave",
    "iso:country":"US",
    "sg:address":"2285 Whitney Ave",
    "sg:city":"Summerland",
    "sg:classifiers":[
        {
            "category":"Wholesale",
            "subcategory":"Groceries",
            "type":"Manufacturing & Wholesale Goods"
        }
    ],
    "sg:phone":"+1 805 565 5445",
    "sg:postcode":"93067",
    "sg:province":"CA",
    "wof:name":"Kindred Cookies LLC",
    "wof:placetype":"venue"
},
  "geometry": {"coordinates":[-119.60024199999999,34.424561],"type":"Point"}
}