{
  "type": "Feature",
  "properties": {
    "iso:country":"US",
    "sg:address":"620 Lanyard Ct E",
    "sg:city":"Rohnert Park",
    "sg:classifiers":[
        {
            "category":"Recreation",
            "subcategory":"Marina",
            "type":"Entertainment"
        }
    ],
    "sg:phone":"+1 707 793 7547",
    "sg:postcode":"94928",
    "sg:province":"CA",
    "sg:tags":[
        "repairing",
        "boat"
    ],
    "wof:name":"TNT Watersports",
    "wof:placetype":"venue"
},
  "geometry": {"coordinates":[-122.689059,38.321198],"type":"Point"}
}