{
  "type": "Feature",
  "properties": {
    "iso:country":"US",
    "sg:address":"2143 Hurley Way",
    "sg:city":"Sacramento",
    "sg:classifiers":[
        {
            "category":"Health Services",
            "subcategory":"Health Practitioner",
            "type":"Services"
        }
    ],
    "sg:phone":"+1 916 563 3846",
    "sg:postcode":"95825",
    "sg:province":"CA",
    "sg:tags":[
        "nurse",
        "registry"
    ],
    "wof:name":"Accentcare Skilled Nursing",
    "wof:placetype":"venue"
},
  "geometry": {"coordinates":[-121.416164,38.588976],"type":"Point"}
}