{
  "type": "Feature",
  "properties": {
    "addr:full":"4239 Tujunga Ave Studio City CA 91604",
    "addr:housenumber":"4239",
    "addr:postcode":"91604",
    "addr:street":"Tujunga Ave",
    "iso:country":"US",
    "sg:address":"4239 Tujunga Ave",
    "sg:city":"Studio City",
    "sg:classifiers":[
        {
            "category":"Professional",
            "type":"Services"
        }
    ],
    "sg:phone":"+1 818 505 0610",
    "sg:postcode":"91604",
    "sg:province":"CA",
    "sg:tags":[
        "establishment"
    ],
    "wof:name":"Advance Group",
    "wof:placetype":"venue"
},
  "geometry": {"coordinates":[-118.379047,34.145498],"type":"Point"}
}