{
  "type": "Feature",
  "properties": {
    "iso:country":"US",
    "sg:address":"181 Pierce St",
    "sg:city":"Gilroy",
    "sg:classifiers":[
        {
            "category":"Real Estate",
            "subcategory":"Real Estate Operator",
            "type":"Services"
        }
    ],
    "sg:phone":"+1 408 842 6341",
    "sg:postcode":"95020",
    "sg:province":"CA",
    "sg:tags":[
        "apartment"
    ],
    "wof:name":"Park View Apartments",
    "wof:placetype":"venue"
},
  "geometry": {"coordinates":[-121.57674799999999,37.022118],"type":"Point"}
}