{
  "type": "Feature",
  "properties": {
    "addr:full":"1844 Cam Estrada Concord CA 94521",
    "addr:housenumber":"1844",
    "addr:postcode":"94521",
    "addr:street":"Cam Estrada",
    "iso:country":"US",
    "sg:address":"1844 Cam Estrada",
    "sg:city":"Concord",
    "sg:classifiers":[
        {
            "category":"Building & Trades",
            "subcategory":"Construction",
            "type":"Services"
        }
    ],
    "sg:phone":"+1 925 672 9238",
    "sg:postcode":"94521",
    "sg:province":"CA",
    "sg:tags":[
        "home",
        "improvement"
    ],
    "wof:name":"W M Wright Construction Svc",
    "wof:placetype":"venue"
},
  "geometry": {"coordinates":[-121.946259,37.953041],"type":"Point"}
}