{
  "type": "Feature",
  "properties": {
    "addr:full":"1545 W 5th St Oxnard CA 93030",
    "addr:housenumber":"1545",
    "addr:postcode":"93030",
    "addr:street":"W 5Th St",
    "iso:country":"US",
    "sg:address":"1545 W 5th St",
    "sg:city":"Oxnard",
    "sg:classifiers":[
        {
            "category":"Real Estate",
            "subcategory":"Real Estate Agent",
            "type":"Services"
        }
    ],
    "sg:phone":"+1 805 815 4072",
    "sg:postcode":"93030",
    "sg:province":"CA",
    "wof:name":"Riviera Realty & Financial",
    "wof:placetype":"venue"
},
  "geometry": {"coordinates":[-119.19663300000001,34.197532],"type":"Point"}
}