{
  "type": "Feature",
  "properties": {
    "addr:full":"115 E Arbor Vitae St Inglewood CA 90301",
    "addr:housenumber":"115",
    "addr:postcode":"90301",
    "addr:street":"E Arbor Vitae St",
    "iso:country":"US",
    "sg:address":"115 E Arbor Vitae St",
    "sg:city":"Inglewood",
    "sg:classifiers":[
        {
            "category":"Wholesale",
            "subcategory":"Medical Equipment & Supplies",
            "type":"Manufacturing & Wholesale Goods"
        }
    ],
    "sg:phone":"+1 310 677 9922",
    "sg:postcode":"90301",
    "sg:province":"CA",
    "wof:name":"One Stop Medical Supply Inc",
    "wof:placetype":"venue"
},
  "geometry": {"coordinates":[-118.354223,33.95271],"type":"Point"}
}