{
  "type": "Feature",
  "properties": {
    "iso:country":"US",
    "sg:address":"1115 Navarro St",
    "sg:city":"Santa Rosa",
    "sg:classifiers":[
        {
            "category":"Shopping",
            "subcategory":"Computers & Home Electronics",
            "type":"Retail Goods"
        }
    ],
    "sg:phone":"+1 707 579 1263",
    "sg:postcode":"95401",
    "sg:province":"CA",
    "sg:tags":[
        "equipment",
        "dealer"
    ],
    "wof:name":"Quality Computer Systems",
    "wof:placetype":"venue"
},
  "geometry": {"coordinates":[-122.754446,38.446475],"type":"Point"}
}