{
  "type": "Feature",
  "properties": {
    "iso:country":"US",
    "sg:address":"825 International Blvd",
    "sg:city":"Oakland",
    "sg:classifiers":[
        {
            "category":"Travel",
            "subcategory":"Travel Agent",
            "type":"Entertainment"
        }
    ],
    "sg:phone":"+1 510 268 8639",
    "sg:postcode":"94606",
    "sg:province":"CA",
    "sg:website":"www.ustoursinc.com",
    "wof:name":"US Tours Inc",
    "wof:placetype":"venue"
},
  "geometry": {"coordinates":[-122.25099899999999,37.793301],"type":"Point"}
}