{
  "type": "Feature",
  "properties": {
    "addr:full":"2687 Castro Valley Blvd Castro Valley CA 94546",
    "addr:housenumber":"2687",
    "addr:postcode":"94546",
    "addr:street":"Castro Valley Blvd",
    "iso:country":"US",
    "sg:address":"2687 Castro Valley Blvd",
    "sg:city":"Castro Valley",
    "sg:classifiers":[
        {
            "category":"Insurance",
            "subcategory":"Title Insurance",
            "type":"Services"
        }
    ],
    "sg:phone":"+1 510 881 8474",
    "sg:postcode":"94546",
    "sg:province":"CA",
    "wof:name":"First American Title Guaranty",
    "wof:placetype":"venue"
},
  "geometry": {"coordinates":[-122.08664899999999,37.694213],"type":"Point"}
}