{
  "type": "Feature",
  "properties": {
    "iso:country":"US",
    "sg:address":"3450 Claremore Ave",
    "sg:city":"Long Beach",
    "sg:classifiers":[
        {
            "category":"Professional",
            "type":"Services"
        }
    ],
    "sg:phone":"+1 562 856 2473",
    "sg:postcode":"90808",
    "sg:province":"CA",
    "wof:name":"Colvin Company",
    "wof:placetype":"venue"
},
  "geometry": {"coordinates":[-118.078025,33.819427],"type":"Point"}
}