{
  "type": "Feature",
  "properties": {
    "iso:country":"US",
    "sg:address":"5551 Fremont St",
    "sg:city":"Oakland",
    "sg:classifiers":[
        {
            "category":"Professional",
            "subcategory":"Business Services",
            "type":"Services"
        }
    ],
    "sg:phone":"+1 510 985 0335",
    "sg:postcode":"94608",
    "sg:province":"CA",
    "sg:tags":[
        "recording",
        "studio"
    ],
    "wof:name":"On-Site Audio Recording Prdctn",
    "wof:placetype":"venue"
},
  "geometry": {"coordinates":[-122.284679,37.839626],"type":"Point"}
}