{
  "type": "Feature",
  "properties": {
    "iso:country":"US",
    "sg:address":"3308 Alanreed Ave",
    "sg:city":"Rosemead",
    "sg:classifiers":[
        {
            "category":"Professional",
            "type":"Services"
        }
    ],
    "sg:phone":"+1 626 571 0245",
    "sg:postcode":"91770",
    "sg:province":"CA",
    "sg:tags":[
        "establishment"
    ],
    "wof:name":"Mac Bay",
    "wof:placetype":"venue"
},
  "geometry": {"coordinates":[-118.091686,34.068308],"type":"Point"}
}