{
  "type": "Feature",
  "properties": {
    "addr:full":"401 S Euclid Ave Ontario CA 91762",
    "addr:housenumber":"401",
    "addr:postcode":"91762",
    "addr:street":"S Euclid Ave",
    "iso:country":"US",
    "sg:address":"401 S Euclid Ave",
    "sg:city":"Ontario",
    "sg:phone":"+1 909 391 3889",
    "sg:postcode":"91762",
    "sg:province":"CA",
    "sg:tags":[
        "equipment",
        "station"
    ],
    "wof:name":"J P Sales",
    "wof:placetype":"venue"
},
  "geometry": {"coordinates":[-117.650975,34.058977],"type":"Point"}
}