{
  "type": "Feature",
  "properties": {
    "iso:country":"US",
    "sg:address":"700 W Hamilton St",
    "sg:city":"Campbell",
    "sg:classifiers":[
        {
            "category":"Health Services",
            "subcategory":"Clinic",
            "type":"Services"
        },
        {
            "category":"Sports & Exercise",
            "subcategory":"Gym",
            "type":"Entertainment"
        }
    ],
    "sg:phone":"+1 408 506 2209",
    "sg:postcode":"95008",
    "sg:province":"CA",
    "sg:tags":[
        "trainer",
        "loss",
        "weight"
    ],
    "sg:website":"www.isotonex.com",
    "wof:name":"ISOTONEX High Intensity Training",
    "wof:placetype":"venue"
},
  "geometry": {"coordinates":[-121.961674,37.293168],"type":"Point"}
}