{
  "type": "Feature",
  "properties": {
    "addr:full":"13662 Oxnard St Van Nuys CA 91401",
    "addr:housenumber":"13662",
    "addr:postcode":"91401",
    "addr:street":"Oxnard St",
    "iso:country":"US",
    "sg:address":"13662 Oxnard St",
    "sg:city":"Van Nuys",
    "sg:classifiers":[
        {
            "category":"Restaurant",
            "type":"Food & Drink"
        }
    ],
    "sg:phone":"+1 818 787 2899",
    "sg:postcode":"91401",
    "sg:province":"CA",
    "sg:tags":[
        "mexican"
    ],
    "wof:name":"Rigos Taco 2",
    "wof:placetype":"venue"
},
  "geometry": {"coordinates":[-118.431,34.179501],"type":"Point"}
}