{
  "type": "Feature",
  "properties": {
    "addr:full":"3420 San Pablo Ave Emeryville CA 94608",
    "addr:housenumber":"3420",
    "addr:postcode":"94608",
    "addr:street":"San Pablo Ave",
    "iso:country":"US",
    "sg:address":"3420 San Pablo Ave",
    "sg:city":"Emeryville",
    "sg:classifiers":[
        {
            "category":"Autos & Motor Vehicles",
            "subcategory":"Fuel & Gas Station",
            "type":"Retail Goods"
        }
    ],
    "sg:phone":"+1 510 595 9395",
    "sg:postcode":"94608",
    "sg:province":"CA",
    "wof:name":"Coast Gasoline/San Pablo Station",
    "wof:placetype":"venue"
},
  "geometry": {"coordinates":[-122.27788200000001,37.825936],"type":"Point"}
}