{
  "type": "Feature",
  "properties": {
    "iso:country":"US",
    "sg:address":"907 Newport Center Dr",
    "sg:city":"Newport Beach",
    "sg:classifiers":[
        {
            "category":"Food & Beverages",
            "subcategory":"Specialty",
            "type":"Retail Goods"
        }
    ],
    "sg:phone":"+1 949 219 0495",
    "sg:postcode":"92660",
    "sg:province":"CA",
    "wof:name":"Oliviers & Company",
    "wof:placetype":"venue"
},
  "geometry": {"coordinates":[-117.87850299999999,33.617015],"type":"Point"}
}