{
  "type": "Feature",
  "properties": {
    "iso:country":"US",
    "sg:address":"2021 Business Center Dr #115",
    "sg:city":"Irvine",
    "sg:classifiers":[
        {
            "category":"Place Of Worship",
            "subcategory":"Church",
            "type":"Public Place"
        }
    ],
    "sg:postcode":"92612",
    "sg:province":"CA",
    "wof:name":"Cross Community Church",
    "wof:placetype":"venue"
},
  "geometry": {"coordinates":[-117.85910800000001,33.678619],"type":"Point"}
}