{
  "type": "Feature",
  "properties": {
    "iso:country":"US",
    "sg:address":"12032 Brookhurst St",
    "sg:city":"Garden Grove",
    "sg:classifiers":[
        {
            "category":"Shopping",
            "subcategory":"Jewelry",
            "type":"Retail Goods"
        }
    ],
    "sg:phone":"+1 714 539 6531",
    "sg:postcode":"92840",
    "sg:province":"CA",
    "wof:name":"Continental Custom Jewelry Coin & Pawn",
    "wof:placetype":"venue"
},
  "geometry": {"coordinates":[-117.959,33.788101],"type":"Point"}
}