{
  "type": "Feature",
  "properties": {
    "addr:full":"22550 Foothill Blvd Hayward CA 94541",
    "addr:housenumber":"22550",
    "addr:postcode":"94541",
    "addr:street":"Foothill Blvd",
    "iso:country":"US",
    "sg:address":"22550 Foothill Blvd",
    "sg:city":"Hayward",
    "sg:classifiers":[
        {
            "category":"Shopping",
            "subcategory":"Party Supplies",
            "type":"Retail Goods"
        }
    ],
    "sg:phone":"+1 510 881 1838",
    "sg:postcode":"94541",
    "sg:province":"CA",
    "wof:name":"Creaciones LIZ",
    "wof:placetype":"venue"
},
  "geometry": {"coordinates":[-122.123456,37.674753],"type":"Point"}
}