{
  "type": "Feature",
  "properties": {
    "addr:full":"145 2nd Ave San Francisco CA 94118",
    "addr:housenumber":"145",
    "addr:postcode":"94118",
    "addr:street":"2Nd Ave",
    "iso:country":"US",
    "sg:address":"145 2nd Ave",
    "sg:city":"San Francisco",
    "sg:classifiers":[
        {
            "category":"Professional",
            "type":"Services"
        }
    ],
    "sg:phone":"+1 415 379 9692",
    "sg:postcode":"94118",
    "sg:province":"CA",
    "wof:name":"Twenty Bricks LLC",
    "wof:placetype":"venue"
},
  "geometry": {"coordinates":[-122.46042799999999,37.786324],"type":"Point"}
}