{
  "type": "Feature",
  "properties": {
    "iso:country":"US",
    "sg:address":"250 Aqua Ln",
    "sg:city":"Ramona",
    "sg:classifiers":[
        {
            "category":"Wholesale",
            "subcategory":"Machinery & Supplies",
            "type":"Manufacturing & Wholesale Goods"
        }
    ],
    "sg:phone":"+1 760 789 0174",
    "sg:postcode":"92065",
    "sg:province":"CA",
    "sg:tags":[
        "bottle"
    ],
    "wof:name":"Famous Ramona Water",
    "wof:placetype":"venue"
},
  "geometry": {"coordinates":[-116.86194399999999,33.048993],"type":"Point"}
}