{
  "type": "Feature",
  "properties": {
    "addr:full":"5753 E La Palma Ave Anaheim CA 92807",
    "addr:housenumber":"5753",
    "addr:postcode":"92807",
    "addr:street":"E La Palma Ave",
    "iso:country":"US",
    "sg:address":"5753 E La Palma Ave",
    "sg:city":"Anaheim",
    "sg:classifiers":[
        {
            "category":"Health Services",
            "subcategory":"Optometrist",
            "type":"Services"
        }
    ],
    "sg:phone":"+1 714 779 2596",
    "sg:postcode":"92807",
    "sg:province":"CA",
    "wof:name":"La Croix Ronald A OD",
    "wof:placetype":"venue"
},
  "geometry": {"coordinates":[-117.789001,33.8596],"type":"Point"}
}