{
  "type": "Feature",
  "properties": {
    "addr:full":"9005 Pinfield Ct Elk Grove CA 95758",
    "addr:housenumber":"9005",
    "addr:postcode":"95758",
    "addr:street":"Pinfield Ct",
    "iso:country":"US",
    "sg:address":"9005 Pinfield Ct",
    "sg:city":"Elk Grove",
    "sg:classifiers":[
        {
            "category":"Retail",
            "subcategory":"Animal Services",
            "type":"Services"
        }
    ],
    "sg:phone":"+1 916 424 0756",
    "sg:postcode":"95758",
    "sg:province":"CA",
    "sg:tags":[
        "pet"
    ],
    "wof:name":"Pat's Pet Sitting Svc",
    "wof:placetype":"venue"
},
  "geometry": {"coordinates":[-121.450425,38.430242],"type":"Point"}
}