{
  "type": "Feature",
  "properties": {
    "iso:country":"US",
    "sg:address":"717 K St",
    "sg:city":"Sacramento",
    "sg:classifiers":[
        {
            "category":"Insurance",
            "subcategory":"Hazard Insurance",
            "type":"Services"
        }
    ],
    "sg:phone":"+1 916 443 3089",
    "sg:postcode":"95814",
    "sg:province":"CA",
    "sg:tags":[
        "bond"
    ],
    "wof:name":"Tillman's Investigation & Bail",
    "wof:placetype":"venue"
},
  "geometry": {"coordinates":[-121.496642,38.579846],"type":"Point"}
}