{
  "type": "Feature",
  "properties": {
    "iso:country":"US",
    "sg:address":"27475 Ynez Rd",
    "sg:city":"Temecula",
    "sg:classifiers":[
        {
            "category":"Building & Trades",
            "subcategory":"Equipment Rental",
            "type":"Services"
        }
    ],
    "sg:phone":"+1 951 699 3143",
    "sg:postcode":"92591",
    "sg:province":"CA",
    "sg:tags":[
        "wireless",
        "communications"
    ],
    "wof:name":"Airtech Industries Inc",
    "wof:placetype":"venue"
},
  "geometry": {"coordinates":[-117.150159,33.506844],"type":"Point"}
}