{
  "type": "Feature",
  "properties": {
    "iso:country":"US",
    "sg:address":"2421 Dunstan St",
    "sg:city":"Oceanside",
    "sg:classifiers":[
        {
            "category":"Banks & Credit Unions",
            "subcategory":"Financial Services",
            "type":"Services"
        }
    ],
    "sg:phone":"+1 760 433 8846",
    "sg:postcode":"92054",
    "sg:province":"CA",
    "sg:tags":[
        "trust",
        "management"
    ],
    "wof:name":"Gaffey Family Trust",
    "wof:placetype":"venue"
},
  "geometry": {"coordinates":[-117.341886,33.194752],"type":"Point"}
}