{
  "type": "Feature",
  "properties": {
    "iso:country":"US",
    "sg:address":"1981 Pruneridge Avenue",
    "sg:city":"Santa Clara",
    "sg:classifiers":[
        {
            "category":"Professional",
            "subcategory":"Accounting & Tax Preparation",
            "type":"Services"
        }
    ],
    "sg:phone":"+1 408 249 0360",
    "sg:postcode":"95050",
    "sg:province":"CA",
    "sg:tags":[
        "accountant"
    ],
    "wof:name":"Babcock James M CPA",
    "wof:placetype":"venue"
},
  "geometry": {"coordinates":[-121.954165,37.329837],"type":"Point"}
}