{
  "type": "Feature",
  "properties": {
    "addr:full":"10008 National Blvd Los Angeles CA 90034",
    "addr:housenumber":"10008",
    "addr:postcode":"90034",
    "addr:street":"National Blvd",
    "iso:country":"US",
    "sg:address":"10008 National Blvd",
    "sg:city":"Los Angeles",
    "sg:classifiers":[
        {
            "category":"Professional",
            "type":"Services"
        }
    ],
    "sg:phone":"+1 310 287 0800",
    "sg:postcode":"90034",
    "sg:province":"CA",
    "wof:name":"Intergrated Project Managment",
    "wof:placetype":"venue"
},
  "geometry": {"coordinates":[-118.403452,34.028973],"type":"Point"}
}