{
  "type": "Feature",
  "properties": {
    "iso:country":"US",
    "sg:address":"16508 Dartolo Rd",
    "sg:city":"Ramona",
    "sg:classifiers":[
        {
            "category":"Sports & Exercise",
            "subcategory":"Gym",
            "type":"Entertainment"
        }
    ],
    "sg:phone":"+1 760 787 0877",
    "sg:postcode":"92065",
    "sg:province":"CA",
    "sg:tags":[
        "equipment",
        "fitness"
    ],
    "wof:name":"San Diego Fitness Eqp Repr",
    "wof:placetype":"venue"
},
  "geometry": {"coordinates":[-116.791845,33.014338],"type":"Point"}
}