{
  "type": "Feature",
  "properties": {
    "addr:full":"24727 Railroad Ave Newhall CA 91321",
    "addr:housenumber":"24727",
    "addr:postcode":"91321",
    "addr:street":"Railroad Ave",
    "iso:country":"US",
    "sg:address":"24727 Railroad Ave",
    "sg:city":"Newhall",
    "sg:phone":"+1 661 255 7871",
    "sg:postcode":"91321",
    "sg:province":"CA",
    "wof:name":"Valley Bicycles",
    "wof:placetype":"venue"
},
  "geometry": {"coordinates":[-118.531319,34.384713],"type":"Point"}
}