{
  "type": "Feature",
  "properties": {
    "addr:full":"5411 3rd St San Francisco CA 94124",
    "addr:housenumber":"5411",
    "addr:postcode":"94124",
    "addr:street":"3Rd St",
    "iso:country":"US",
    "sg:address":"5411 3rd St",
    "sg:city":"San Francisco",
    "sg:classifiers":[
        {
            "category":"Restaurant",
            "type":"Food & Drink"
        }
    ],
    "sg:menulink":"http://www.allmenus.com/ca/san-francisco/216539-mcdonalds/menu/",
    "sg:postcode":"94124",
    "sg:province":"CA",
    "sg:tags":[
        "burger",
        "american"
    ],
    "wof:name":"McDonald's",
    "wof:placetype":"venue"
},
  "geometry": {"coordinates":[-122.39256,37.727942],"type":"Point"}
}