{
  "type": "Feature",
  "properties": {
    "addr:full":"16715 Anaconda Rd Madera CA 93636",
    "addr:housenumber":"16715",
    "addr:postcode":"93636",
    "addr:street":"Anaconda Rd",
    "iso:country":"US",
    "sg:address":"16715 Anaconda Rd",
    "sg:city":"Madera",
    "sg:classifiers":[
        {
            "category":"Wholesale",
            "subcategory":"Non-durable Goods",
            "type":"Manufacturing & Wholesale Goods"
        }
    ],
    "sg:phone":"+1 559 645 5225",
    "sg:postcode":"93636",
    "sg:province":"CA",
    "wof:name":"McClellan Enterprises",
    "wof:placetype":"venue"
},
  "geometry": {"coordinates":[-119.868376,36.991607],"type":"Point"}
}