{
  "type": "Feature",
  "properties": {
    "iso:country":"US",
    "sg:address":"1430 Esplanade",
    "sg:city":"Chico",
    "sg:classifiers":[
        {
            "category":"Health Services",
            "subcategory":"Health Practitioner",
            "type":"Services"
        }
    ],
    "sg:phone":"+1 530 894 0221",
    "sg:postcode":"95926",
    "sg:province":"CA",
    "sg:tags":[
        "therapist",
        "physical"
    ],
    "wof:name":"Valponi Physical Therapy",
    "wof:placetype":"venue"
},
  "geometry": {"coordinates":[-121.84844699999999,39.741773],"type":"Point"}
}