{
  "type": "Feature",
  "properties": {
    "addr:full":"1324 Wilshire Blvd Los Angeles CA 90017",
    "addr:housenumber":"1324",
    "addr:postcode":"90017",
    "addr:street":"Wilshire Blvd",
    "iso:country":"US",
    "sg:address":"1324 Wilshire Blvd",
    "sg:city":"Los Angeles",
    "sg:classifiers":[
        {
            "category":"Manufacturing",
            "subcategory":"Printing",
            "type":"Manufacturing & Wholesale Goods"
        }
    ],
    "sg:phone":"+1 213 413 9784",
    "sg:postcode":"90017",
    "sg:province":"CA",
    "sg:tags":[
        "lithographic",
        "commercial"
    ],
    "wof:name":"David Rodarte",
    "wof:placetype":"venue"
},
  "geometry": {"coordinates":[-118.268233,34.054421],"type":"Point"}
}