{
  "type": "Feature",
  "properties": {
    "iso:country":"US",
    "sg:address":"3925 Blizzard Mine Rd",
    "sg:city":"Wilseyville",
    "sg:classifiers":[
        {
            "category":"Shopping",
            "subcategory":"Bicycles & Sporting Goods",
            "type":"Retail Goods"
        }
    ],
    "sg:phone":"+1 209 293 4449",
    "sg:postcode":"95248",
    "sg:province":"CA",
    "sg:tags":[
        "equipment",
        "archery",
        "supply"
    ],
    "wof:name":"Blue Mountain Archery",
    "wof:placetype":"venue"
},
  "geometry": {"coordinates":[-120.515659,38.37851],"type":"Point"}
}