{
  "type": "Feature",
  "properties": {
    "addr:full":"3232 Mission Blvd. San Diego CA 92109",
    "addr:housenumber":"3232",
    "addr:postcode":"92109",
    "addr:street":"Mission Blvd.",
    "iso:country":"US",
    "sg:address":"3232 Mission Blvd.",
    "sg:city":"San Diego",
    "sg:classifiers":[
        {
            "category":"Shopping",
            "subcategory":"Bicycles & Sporting Goods",
            "type":"Retail Goods"
        }
    ],
    "sg:phone":"+1 858 412 4041",
    "sg:postcode":"92109",
    "sg:province":"CA",
    "sg:tags":[
        "outdoor",
        "gear"
    ],
    "wof:name":"Rail 2 Rail",
    "wof:placetype":"venue"
},
  "geometry": {"coordinates":[-117.25151200000001,32.772719],"type":"Point"}
}