{
  "type": "Feature",
  "properties": {
    "addr:full":"1180 Western St Fairfield CA 94533",
    "addr:housenumber":"1180",
    "addr:postcode":"94533",
    "addr:street":"Western St",
    "iso:country":"US",
    "sg:address":"1180 Western St",
    "sg:city":"Fairfield",
    "sg:classifiers":[
        {
            "category":"Place Of Worship",
            "subcategory":"Church",
            "type":"Public Place"
        },
        {
            "category":"Place Of Worship",
            "type":"Public Place"
        }
    ],
    "sg:phone":"+1 707 438 0700",
    "sg:postcode":"94533",
    "sg:province":"CA",
    "sg:tags":[
        "churches-calvary",
        "chapel"
    ],
    "sg:website":"http://www.calvarysolano.org",
    "wof:name":"Calvary Chapel Of Solano County",
    "wof:placetype":"venue"
},
  "geometry": {"coordinates":[-122.008484,38.27424],"type":"Point"}
}