{
  "type": "Feature",
  "properties": {
    "addr:full":"1152 Daniel Dr Petaluma CA 94954",
    "addr:housenumber":"1152",
    "addr:postcode":"94954",
    "addr:street":"Daniel Dr",
    "iso:country":"US",
    "sg:address":"1152 Daniel Dr",
    "sg:city":"Petaluma",
    "sg:classifiers":[
        {
            "category":"Manufacturing",
            "subcategory":"Soap",
            "type":"Manufacturing & Wholesale Goods"
        }
    ],
    "sg:phone":"+1 707 775 3429",
    "sg:postcode":"94954",
    "sg:province":"CA",
    "sg:tags":[
        "detergent",
        "mfg"
    ],
    "wof:name":"Ecolab 010305 K McDonald",
    "wof:placetype":"venue"
},
  "geometry": {"coordinates":[-122.603292,38.237998],"type":"Point"}
}