{
  "type": "Feature",
  "properties": {
    "addr:full":"1630 S Delaware Street. San Mateo CA 94402",
    "addr:housenumber":"1630",
    "addr:postcode":"94402",
    "addr:street":"S Delaware Street.",
    "iso:country":"US",
    "sg:address":"1630 S Delaware Street.",
    "sg:city":"San Mateo",
    "sg:classifiers":[
        {
            "category":"Government",
            "subcategory":"Post Office",
            "type":"Public Place"
        }
    ],
    "sg:phone":"+1 650 358 8490",
    "sg:postcode":"94402",
    "sg:province":"CA",
    "sg:website":"www.usps.com",
    "wof:name":"US Post Office",
    "wof:placetype":"venue"
},
  "geometry": {"coordinates":[-122.308882,37.555798],"type":"Point"}
}