{
  "type": "Feature",
  "properties": {
    "iso:country":"US",
    "sg:address":"1605 E Elizabeth St",
    "sg:city":"Pasadena",
    "sg:classifiers":[
        {
            "category":"Organizations",
            "subcategory":"Non-profit Organization",
            "type":"Services"
        }
    ],
    "sg:phone":"+1 626 398 2244",
    "sg:postcode":"91104",
    "sg:province":"CA",
    "sg:tags":[
        "human"
    ],
    "wof:name":"Comhina",
    "wof:placetype":"venue"
},
  "geometry": {"coordinates":[-118.117484,34.173827],"type":"Point"}
}