{
  "type": "Feature",
  "properties": {
    "iso:country":"US",
    "sg:address":"696 Calaveras Dr",
    "sg:city":"Salinas",
    "sg:classifiers":[
        {
            "category":"Building & Trades",
            "subcategory":"Plumbing",
            "type":"Services"
        }
    ],
    "sg:phone":"+1 831 262 4513",
    "sg:postcode":"93906",
    "sg:province":"CA",
    "sg:tags":[
        "plumber",
        "industrial",
        "contractors-commercial"
    ],
    "wof:name":"H2o Plumbing",
    "wof:placetype":"venue"
},
  "geometry": {"coordinates":[-121.628714,36.706583],"type":"Point"}
}