{
  "type": "Feature",
  "properties": {
    "iso:country":"US",
    "sg:address":"10265 Beardon Dr",
    "sg:city":"Cupertino",
    "sg:classifiers":[
        {
            "category":"Banks & Credit Unions",
            "subcategory":"Investment Brokerage",
            "type":"Services"
        }
    ],
    "sg:phone":"+1 408 996 1122",
    "sg:postcode":"95014",
    "sg:province":"CA",
    "sg:tags":[
        "management"
    ],
    "wof:name":"America Enterprise Invstmnt",
    "wof:placetype":"venue"
},
  "geometry": {"coordinates":[-122.036922,37.327761],"type":"Point"}
}