{
  "type": "Feature",
  "properties": {
    "addr:full":"1339 W 18th St Merced CA 95340",
    "addr:housenumber":"1339",
    "addr:postcode":"95340",
    "addr:street":"W 18Th St",
    "iso:country":"US",
    "sg:address":"1339 W 18th St",
    "sg:city":"Merced",
    "sg:classifiers":[
        {
            "category":"Food & Beverages",
            "subcategory":"Bakery",
            "type":"Retail Goods"
        }
    ],
    "sg:phone":"+1 209 383 2080",
    "sg:postcode":"95340",
    "sg:province":"CA",
    "sg:tags":[
        "doughnut"
    ],
    "wof:name":"LA Michoacana Bakery",
    "wof:placetype":"venue"
},
  "geometry": {"coordinates":[-120.49581000000001,37.307245],"type":"Point"}
}