{
  "type": "Feature",
  "properties": {
    "addr:full":"839 Miller Ave Cupertino CA 95014",
    "addr:housenumber":"839",
    "addr:postcode":"95014",
    "addr:street":"Miller Ave",
    "iso:country":"US",
    "sg:address":"839 Miller Ave",
    "sg:city":"Cupertino",
    "sg:classifiers":[
        {
            "category":"Wholesale",
            "subcategory":"Durable Goods & Equipment",
            "type":"Manufacturing & Wholesale Goods"
        }
    ],
    "sg:phone":"+1 408 343 0640",
    "sg:postcode":"95014",
    "sg:province":"CA",
    "sg:tags":[
        "importer"
    ],
    "wof:name":"Cosmos Enterprises",
    "wof:placetype":"venue"
},
  "geometry": {"coordinates":[-122.013462,37.312521],"type":"Point"}
}