{
  "type": "Feature",
  "properties": {
    "addr:full":"3509 Highland Ave Manhattan Beach CA 90266",
    "addr:housenumber":"3509",
    "addr:postcode":"90266",
    "addr:street":"Highland Ave",
    "iso:country":"US",
    "sg:address":"3509 Highland Ave",
    "sg:city":"Manhattan Beach",
    "sg:classifiers":[
        {
            "category":"Retail",
            "subcategory":"Laundry & Dry Cleaning",
            "type":"Services"
        }
    ],
    "sg:phone":"+1 310 546 5929",
    "sg:postcode":"90266",
    "sg:province":"CA",
    "wof:name":"Thrifty Cleaners",
    "wof:placetype":"venue"
},
  "geometry": {"coordinates":[-118.417,33.899899],"type":"Point"}
}