{
  "type": "Feature",
  "properties": {
    "addr:full":"27502 Ave Scott Valencia CA 91355",
    "addr:housenumber":"27502",
    "addr:postcode":"91355",
    "addr:street":"Ave Scott",
    "iso:country":"US",
    "sg:address":"27502 Ave Scott",
    "sg:city":"Valencia",
    "sg:classifiers":[
        {
            "category":"Building & Trades",
            "subcategory":"Landscaping Services",
            "type":"Services"
        }
    ],
    "sg:phone":"+1 661 257 1266",
    "sg:postcode":"91355",
    "sg:province":"CA",
    "sg:tags":[
        "landscape",
        "contractor"
    ],
    "wof:name":"Gothic Landscape Inc",
    "wof:placetype":"venue"
},
  "geometry": {"coordinates":[-118.566495,34.430955],"type":"Point"}
}