{
  "type": "Feature",
  "properties": {
    "iso:country":"US",
    "sg:address":"1900 S Sepulveda Blvd",
    "sg:city":"Los Angeles",
    "sg:classifiers":[
        {
            "category":"Professional",
            "subcategory":"Engineering",
            "type":"Services"
        },
        {
            "category":"Professional",
            "subcategory":"Research",
            "type":"Services"
        }
    ],
    "sg:phone":"+1 310 954 2200",
    "sg:postcode":"90025",
    "sg:province":"CA",
    "sg:tags":[
        "development",
        "equipment",
        "mfg",
        "laboratory"
    ],
    "wof:name":"Technology Service Corporation",
    "wof:placetype":"venue"
},
  "geometry": {"coordinates":[-118.440312,34.042999],"type":"Point"}
}