{
  "type": "Feature",
  "properties": {
    "addr:full":"538 E Hemlock St Oxnard CA 93033",
    "addr:housenumber":"538",
    "addr:postcode":"93033",
    "addr:street":"E Hemlock St",
    "iso:country":"US",
    "sg:address":"538 E Hemlock St",
    "sg:city":"Oxnard",
    "sg:classifiers":[
        {
            "category":"Restaurant",
            "type":"Food & Drink"
        }
    ],
    "sg:phone":"+1 805 247 1450",
    "sg:postcode":"93033",
    "sg:province":"CA",
    "wof:name":"El Rebozo Mexican Restaurant",
    "wof:placetype":"venue"
},
  "geometry": {"coordinates":[-119.16970499999999,34.180194],"type":"Point"}
}