{
  "type": "Feature",
  "properties": {
    "addr:full":"2881 W Valley Blvd Alhambra CA 91803",
    "addr:housenumber":"2881",
    "addr:postcode":"91803",
    "addr:street":"W Valley Blvd",
    "iso:country":"US",
    "sg:address":"2881 W Valley Blvd",
    "sg:city":"Alhambra",
    "sg:classifiers":[
        {
            "category":"Home & Garden",
            "subcategory":"Home Furnishings",
            "type":"Retail Goods"
        }
    ],
    "sg:phone":"+1 626 281 7437",
    "sg:postcode":"91803",
    "sg:province":"CA",
    "sg:tags":[
        "curtain",
        "made",
        "drapery"
    ],
    "wof:name":"Sen's Draperies",
    "wof:placetype":"venue"
},
  "geometry": {"coordinates":[-118.157487,34.076554],"type":"Point"}
}