{
  "type": "Feature",
  "properties": {
    "iso:country":"US",
    "sg:address":"1140 Cedar Ave",
    "sg:city":"Long Beach",
    "sg:classifiers":[
        {
            "category":"Professional",
            "type":"Services"
        }
    ],
    "sg:phone":"+1 562 590 2227",
    "sg:postcode":"90813",
    "sg:province":"CA",
    "wof:name":"New Ways Living",
    "wof:placetype":"venue"
},
  "geometry": {"coordinates":[-118.194979,33.779683],"type":"Point"}
}