{
  "type": "Feature",
  "properties": {
    "addr:full":"8190 Florin Rd Sacramento CA 95828",
    "addr:housenumber":"8190",
    "addr:postcode":"95828",
    "addr:street":"Florin Rd",
    "iso:country":"US",
    "sg:address":"8190 Florin Rd",
    "sg:city":"Sacramento",
    "sg:classifiers":[
        {
            "category":"Building & Trades",
            "subcategory":"Construction",
            "type":"Services"
        }
    ],
    "sg:phone":"+1 916 752 5825",
    "sg:postcode":"95828",
    "sg:province":"CA",
    "wof:name":"CMJ Construction",
    "wof:placetype":"venue"
},
  "geometry": {"coordinates":[-121.407543,38.495968],"type":"Point"}
}