{
  "type": "Feature",
  "properties": {
    "iso:country":"US",
    "sg:address":"999 N Tustin Ave",
    "sg:city":"Santa Ana",
    "sg:classifiers":[
        {
            "category":"Health Services",
            "subcategory":"Doctor",
            "type":"Services"
        }
    ],
    "sg:phone":"+1 714 288 3015",
    "sg:postcode":"92705",
    "sg:province":"CA",
    "wof:name":"Quimbo Araceli C MD",
    "wof:placetype":"venue"
},
  "geometry": {"coordinates":[-117.834,33.7537],"type":"Point"}
}