{
  "type": "Feature",
  "properties": {
    "iso:country":"US",
    "sg:address":"4471 Salisbury Dr",
    "sg:city":"Carlsbad",
    "sg:classifiers":[
        {
            "category":"Manufacturing",
            "subcategory":"Jewelry",
            "type":"Manufacturing & Wholesale Goods"
        }
    ],
    "sg:phone":"+1 760 434 2428",
    "sg:postcode":"92010",
    "sg:province":"CA",
    "sg:tags":[
        "stamping",
        "gold"
    ],
    "wof:name":"Imprints Unlimited",
    "wof:placetype":"venue"
},
  "geometry": {"coordinates":[-117.310236,33.158954],"type":"Point"}
}