{
  "type": "Feature",
  "properties": {
    "iso:country":"US",
    "sg:address":"458 W Arrow Hwy",
    "sg:city":"San Dimas",
    "sg:classifiers":[
        {
            "category":"Autos & Motor Vehicles",
            "subcategory":"Automobile Sales",
            "type":"Retail Goods"
        },
        {
            "category":"Wholesale",
            "subcategory":"Motor Vehicles",
            "type":"Manufacturing & Wholesale Goods"
        }
    ],
    "sg:phone":"+1 909 394 5622",
    "sg:postcode":"91773",
    "sg:province":"CA",
    "sg:tags":[
        "used",
        "truck",
        "broker"
    ],
    "wof:name":"Inland Auto D'Italia",
    "wof:placetype":"venue"
},
  "geometry": {"coordinates":[-117.814269,34.102848],"type":"Point"}
}