{
  "type": "Feature",
  "properties": {
    "iso:country":"US",
    "sg:address":"9905 Timothy Path",
    "sg:city":"Salinas",
    "sg:classifiers":[
        {
            "category":"Building & Trades",
            "subcategory":"Cleaning & Sanitation",
            "type":"Services"
        }
    ],
    "sg:phone":"+1 831 375 2629",
    "sg:postcode":"93907",
    "sg:province":"CA",
    "sg:tags":[
        "carpet"
    ],
    "wof:name":"Flawless Janitor Service",
    "wof:placetype":"venue"
},
  "geometry": {"coordinates":[-121.728267,36.774756],"type":"Point"}
}