{
  "type": "Feature",
  "properties": {
    "addr:full":"157 Sloan Ct Tracy CA 95304",
    "addr:housenumber":"157",
    "addr:postcode":"95304",
    "addr:street":"Sloan Ct",
    "iso:country":"US",
    "sg:address":"157 Sloan Ct",
    "sg:city":"Tracy",
    "sg:classifiers":[
        {
            "category":"Home & Garden",
            "subcategory":"Mobile Homes",
            "type":"Retail Goods"
        }
    ],
    "sg:phone":"+1 209 836 8877",
    "sg:postcode":"95304",
    "sg:province":"CA",
    "sg:tags":[
        "commercial",
        "unit"
    ],
    "wof:name":"Anderson & Sons Transport",
    "wof:placetype":"venue"
},
  "geometry": {"coordinates":[-121.426852,37.767838],"type":"Point"}
}