{
  "type": "Feature",
  "properties": {
    "iso:country":"US",
    "sg:address":"1909 Colorado Boulevard",
    "sg:city":"Los Angeles",
    "sg:classifiers":[
        {
            "category":"Health Services",
            "subcategory":"Dentist",
            "type":"Services"
        }
    ],
    "sg:phone":"+1 323 254 3415",
    "sg:postcode":"90041",
    "sg:province":"CA",
    "wof:name":"Vardan Dental Frames",
    "wof:placetype":"venue"
},
  "geometry": {"coordinates":[-118.20919600000001,34.13921],"type":"Point"}
}