{
  "type": "Feature",
  "properties": {
    "addr:full":"31300 Digger Creek Dr Fort Bragg CA 95437",
    "addr:postcode":"31300;95437",
    "addr:street":"Digger Creek Dr",
    "iso:country":"US",
    "sg:address":"31300 Digger Creek Dr",
    "sg:city":"Fort Bragg",
    "sg:classifiers":[
        {
            "category":"Professional",
            "type":"Services"
        }
    ],
    "sg:phone":"+1 707 961 0771",
    "sg:postcode":"95437",
    "sg:province":"CA",
    "sg:tags":[
        "arts",
        "artist"
    ],
    "wof:name":"Ickes Sev",
    "wof:placetype":"venue"
},
  "geometry": {"coordinates":[-123.779636,39.391872],"type":"Point"}
}