{
  "type": "Feature",
  "properties": {
    "iso:country":"US",
    "sg:address":"219 S Main St",
    "sg:city":"Blythe",
    "sg:classifiers":[
        {
            "category":"Restaurant",
            "type":"Food & Drink"
        }
    ],
    "sg:phone":"+1 760 921 4508",
    "sg:postcode":"92225",
    "sg:province":"CA",
    "wof:name":"Harmony Kitchen",
    "wof:placetype":"venue"
},
  "geometry": {"coordinates":[-114.59955100000001,33.607741],"type":"Point"}
}