{
  "type": "Feature",
  "properties": {
    "iso:country":"US",
    "sg:address":"27 Saint Paul",
    "sg:city":"Laguna Niguel",
    "sg:classifiers":[
        {
            "category":"Professional",
            "type":"Services"
        }
    ],
    "sg:phone":"+1 949 489 5638",
    "sg:postcode":"92677",
    "sg:province":"CA",
    "wof:name":"Vazac Cstm Wl Dsgn",
    "wof:placetype":"venue"
},
  "geometry": {"coordinates":[-117.696237,33.494559],"type":"Point"}
}