{
  "type": "Feature",
  "properties": {
    "iso:country":"US",
    "sg:address":"2197 E Bayshore Rd",
    "sg:city":"Palo Alto",
    "sg:classifiers":[
        {
            "category":"Real Estate",
            "subcategory":"Developer",
            "type":"Services"
        }
    ],
    "sg:phone":"+1 650 325 1047",
    "sg:postcode":"94303",
    "sg:province":"CA",
    "wof:name":"Bay Area Ind Corp",
    "wof:placetype":"venue"
},
  "geometry": {"coordinates":[-122.120926,37.449725],"type":"Point"}
}