{
  "type": "Feature",
  "properties": {
    "iso:country":"US",
    "sg:address":"11040 Rancho Carmel Dr",
    "sg:city":"San Diego",
    "sg:classifiers":[
        {
            "category":"Retail",
            "subcategory":"Laundry & Dry Cleaning",
            "type":"Services"
        }
    ],
    "sg:phone":"+1 858 451 3518",
    "sg:postcode":"92128",
    "sg:province":"CA",
    "sg:tags":[
        "cleaners"
    ],
    "wof:name":"Marston Cleaners",
    "wof:placetype":"venue"
},
  "geometry": {"coordinates":[-117.08249000000001,32.977378],"type":"Point"}
}