{
  "type": "Feature",
  "properties": {
    "addr:full":"5345 Santa Monica Boulevard Los Angeles CA 90029",
    "addr:housenumber":"5345",
    "addr:postcode":"90029",
    "addr:street":"Santa Monica Boulevard",
    "iso:country":"US",
    "sg:address":"5345 Santa Monica Boulevard",
    "sg:city":"Los Angeles",
    "sg:classifiers":[
        {
            "category":"Food & Beverages",
            "subcategory":"Groceries & Convenience Stores",
            "type":"Retail Goods"
        }
    ],
    "sg:phone":"+1 323 462 0700",
    "sg:postcode":"90029",
    "sg:province":"CA",
    "wof:name":"Ani Produce Market",
    "wof:placetype":"venue"
},
  "geometry": {"coordinates":[-118.306152,34.090669],"type":"Point"}
}