{
  "type": "Feature",
  "properties": {
    "iso:country":"US",
    "sg:address":"405 Vernon Way",
    "sg:city":"El Cajon",
    "sg:classifiers":[
        {
            "category":"Professional",
            "subcategory":"Business Services",
            "type":"Services"
        }
    ],
    "sg:phone":"+1 619 593 8200",
    "sg:postcode":"92020",
    "sg:province":"CA",
    "sg:tags":[
        "fire",
        "protection"
    ],
    "wof:name":"Innovative Fire Protection",
    "wof:placetype":"venue"
},
  "geometry": {"coordinates":[-116.96645599999999,32.812286],"type":"Point"}
}