{
  "type": "Feature",
  "properties": {
    "addr:full":"1001 Brannan St San Francisco CA 94103",
    "addr:housenumber":"1001",
    "addr:postcode":"94103",
    "addr:street":"Brannan St",
    "iso:country":"US",
    "sg:address":"1001 Brannan St",
    "sg:city":"San Francisco",
    "sg:classifiers":[
        {
            "category":"Sports & Exercise",
            "subcategory":"Gym",
            "type":"Entertainment"
        }
    ],
    "sg:phone":"+1 415 552 4653",
    "sg:postcode":"94103",
    "sg:province":"CA",
    "sg:tags":[
        "club",
        "studio",
        "health",
        "gymnasium"
    ],
    "sg:website":"www.goldsgym.com",
    "wof:name":"Gold's Gym",
    "wof:placetype":"venue"
},
  "geometry": {"coordinates":[-122.406919,37.769648],"type":"Point"}
}