{
  "type": "Feature",
  "properties": {
    "iso:country":"US",
    "sg:address":"12114 Park St",
    "sg:city":"Cerritos",
    "sg:classifiers":[
        {
            "category":"Recreation",
            "subcategory":"Arcade",
            "type":"Entertainment"
        }
    ],
    "sg:phone":"+1 562 802 8085",
    "sg:postcode":"90703",
    "sg:province":"CA",
    "sg:tags":[
        "amusement",
        "devices"
    ],
    "wof:name":"Lakey Amusement",
    "wof:placetype":"venue"
},
  "geometry": {"coordinates":[-118.072844,33.878147],"type":"Point"}
}