{
  "type": "Feature",
  "properties": {
    "addr:full":"14738 Amigos Rd Chino Hills CA 91709",
    "addr:postcode":"14738;91709",
    "addr:street":"Amigos Rd",
    "iso:country":"US",
    "sg:address":"14738 Amigos Rd",
    "sg:city":"Chino Hills",
    "sg:classifiers":[
        {
            "category":"Building & Trades",
            "subcategory":"Construction",
            "type":"Services"
        }
    ],
    "sg:phone":"+1 909 393 7400",
    "sg:postcode":"91709",
    "sg:province":"CA",
    "sg:tags":[
        "plastering",
        "contractor"
    ],
    "wof:name":"John Witherspoon Plastering",
    "wof:placetype":"venue"
},
  "geometry": {"coordinates":[-117.755796,33.986249],"type":"Point"}
}