{
  "type": "Feature",
  "properties": {
    "addr:full":"4073 Linda Vista Dr Fallbrook CA 92028",
    "addr:housenumber":"4073",
    "addr:postcode":"92028",
    "addr:street":"Linda Vista Dr",
    "iso:country":"US",
    "sg:address":"4073 Linda Vista Dr",
    "sg:city":"Fallbrook",
    "sg:classifiers":[
        {
            "category":"Professional",
            "subcategory":"Detective & Security Services",
            "type":"Services"
        }
    ],
    "sg:phone":"+1 760 731 1011",
    "sg:postcode":"92028",
    "sg:province":"CA",
    "sg:tags":[
        "equipment",
        "system",
        "consultant"
    ],
    "wof:name":"Armed Response Security S",
    "wof:placetype":"venue"
},
  "geometry": {"coordinates":[-117.20802,33.317792],"type":"Point"}
}