{
  "type": "Feature",
  "properties": {
    "iso:country":"US",
    "sg:address":"3000 Benton St",
    "sg:city":"Santa Clara",
    "sg:classifiers":[
        {
            "category":"Education",
            "subcategory":"School",
            "type":"Public Place"
        }
    ],
    "sg:phone":"+1 408 423 2600",
    "sg:postcode":"95051",
    "sg:province":"CA",
    "sg:tags":[
        "high",
        "middle"
    ],
    "sg:website":"www.santaclarahigh.org/home",
    "wof:name":"Santa Clara High School",
    "wof:placetype":"venue"
},
  "geometry": {"coordinates":[-121.98304400000001,37.346556],"type":"Point"}
}