{
  "type": "Feature",
  "properties": {
    "addr:full":"7320 Lucerne Vis Yucca Valley CA 92284",
    "addr:housenumber":"7320",
    "addr:postcode":"92284",
    "iso:country":"US",
    "sg:address":"7320 Lucerne Vis",
    "sg:city":"Yucca Valley",
    "sg:classifiers":[
        {
            "category":"Organizations",
            "subcategory":"Religious Organization",
            "type":"Services"
        }
    ],
    "sg:phone":"+1 760 365 4844",
    "sg:postcode":"92284",
    "sg:province":"CA",
    "sg:tags":[
        "church"
    ],
    "wof:name":"Jehovah's Witnesses",
    "wof:placetype":"venue"
},
  "geometry": {"coordinates":[-116.40831900000001,34.120071],"type":"Point"}
}