{
  "type": "Feature",
  "properties": {
    "addr:full":"2335 W Foothill Blvd Upland CA 91786",
    "addr:housenumber":"2335",
    "addr:postcode":"91786",
    "addr:street":"W Foothill Blvd",
    "iso:country":"US",
    "sg:address":"2335 W Foothill Blvd",
    "sg:city":"Upland",
    "sg:classifiers":[
        {
            "category":"Banks & Credit Unions",
            "subcategory":"Investment Brokerage",
            "type":"Services"
        }
    ],
    "sg:phone":"+1 909 981 3553",
    "sg:postcode":"91786",
    "sg:province":"CA",
    "sg:tags":[
        "advisory",
        "financial"
    ],
    "wof:name":"Us Auto Management",
    "wof:placetype":"venue"
},
  "geometry": {"coordinates":[-117.696614,34.106888],"type":"Point"}
}