{
  "type": "Feature",
  "properties": {
    "addr:full":"2812 N San Fernando Blvd Burbank CA 91504",
    "addr:housenumber":"2812",
    "addr:postcode":"91504",
    "addr:street":"N San Fernando Blvd",
    "iso:country":"US",
    "sg:address":"2812 N San Fernando Blvd",
    "sg:city":"Burbank",
    "sg:classifiers":[
        {
            "category":"Retail",
            "subcategory":"Auto Repair",
            "type":"Services"
        }
    ],
    "sg:phone":"+1 818 848 3697",
    "sg:postcode":"91504",
    "sg:province":"CA",
    "sg:website":"www.automattersburbankautorepair...",
    "wof:name":"Auto Matters",
    "wof:placetype":"venue"
},
  "geometry": {"coordinates":[-118.339348,34.199826],"type":"Point"}
}