{
  "type": "Feature",
  "properties": {
    "iso:country":"US",
    "sg:address":"29112 Summersweet Pl",
    "sg:city":"Murrieta",
    "sg:classifiers":[
        {
            "category":"Restaurant",
            "type":"Food & Drink"
        }
    ],
    "sg:phone":"+1 951 723 8336",
    "sg:postcode":"92563",
    "sg:province":"CA",
    "sg:tags":[
        "house",
        "steak",
        "barbecue"
    ],
    "wof:name":"Inland Bar-B-Que Pits",
    "wof:placetype":"venue"
},
  "geometry": {"coordinates":[-117.152192,33.630902],"type":"Point"}
}