{
  "type": "Feature",
  "properties": {
    "iso:country":"US",
    "sg:address":"210 Post St",
    "sg:city":"San Francisco",
    "sg:classifiers":[
        {
            "category":"Retail",
            "subcategory":"Repair Shop",
            "type":"Services"
        },
        {
            "category":"Shopping",
            "subcategory":"Jewelry",
            "type":"Retail Goods"
        }
    ],
    "sg:phone":"+1 415 986 1469",
    "sg:postcode":"94108",
    "sg:province":"CA",
    "sg:tags":[
        "watch",
        "store"
    ],
    "wof:name":"Downtown Watch Repair",
    "wof:placetype":"venue"
},
  "geometry": {"coordinates":[-122.406657,37.788593],"type":"Point"}
}