{
  "type": "Feature",
  "properties": {
    "iso:country":"US",
    "sg:address":"525 29th St",
    "sg:city":"Oakland",
    "sg:classifiers":[
        {
            "category":"Place Of Worship",
            "subcategory":"Church",
            "type":"Public Place"
        },
        {
            "category":"Place Of Worship",
            "type":"Public Place"
        }
    ],
    "sg:phone":"+1 510 832 6462",
    "sg:postcode":"94609",
    "sg:province":"CA",
    "sg:tags":[
        "churches-episcopal-anglican",
        "churches-episcopal"
    ],
    "sg:website":"www.staugepiscopal.org",
    "wof:name":"St Augustine's Episcopal Church",
    "wof:placetype":"venue"
},
  "geometry": {"coordinates":[-122.26799800000001,37.818199],"type":"Point"}
}