{
  "type": "Feature",
  "properties": {
    "iso:country":"US",
    "sg:address":"5402 Cameo Rd",
    "sg:city":"Carpinteria",
    "sg:classifiers":[
        {
            "category":"Professional",
            "type":"Services"
        }
    ],
    "sg:phone":"+1 805 684 0654",
    "sg:postcode":"93013",
    "sg:province":"CA",
    "wof:name":"Independt Retirement Adv",
    "wof:placetype":"venue"
},
  "geometry": {"coordinates":[-119.509745,34.397749],"type":"Point"}
}