{
  "type": "Feature",
  "properties": {
    "addr:full":"6231 Yarrow Dr Carlsbad CA 92009",
    "addr:housenumber":"6231",
    "addr:postcode":"92009",
    "addr:street":"Yarrow Dr",
    "iso:country":"US",
    "sg:address":"6231 Yarrow Dr",
    "sg:city":"Carlsbad",
    "sg:classifiers":[
        {
            "category":"Wholesale",
            "subcategory":"Sporting Goods",
            "type":"Manufacturing & Wholesale Goods"
        }
    ],
    "sg:phone":"+1 760 431 1795",
    "sg:postcode":"92009",
    "sg:province":"CA",
    "wof:name":"Sea Quest Shipping Department",
    "wof:placetype":"venue"
},
  "geometry": {"coordinates":[-117.27356399999999,33.119144],"type":"Point"}
}