{
  "type": "Feature",
  "properties": {
    "iso:country":"US",
    "sg:address":"28924 S Western Ave Ste 201",
    "sg:city":"Rancho Palos Verdes",
    "sg:classifiers":[
        {
            "category":"Health Services",
            "subcategory":"Doctor",
            "type":"Services"
        }
    ],
    "sg:phone":"+1 310 514 8034",
    "sg:postcode":"90275",
    "sg:province":"CA",
    "wof:name":"Molaie Majid MD",
    "wof:placetype":"venue"
},
  "geometry": {"coordinates":[-118.31004,33.75629],"type":"Point"}
}