{
  "type": "Feature",
  "properties": {
    "addr:full":"2503 S H St Bakersfield CA 93304",
    "addr:housenumber":"2503",
    "addr:postcode":"93304",
    "addr:street":"S H St",
    "iso:country":"US",
    "sg:address":"2503 S H St",
    "sg:city":"Bakersfield",
    "sg:classifiers":[
        {
            "category":"Food & Beverages",
            "subcategory":"Groceries & Convenience Stores",
            "type":"Retail Goods"
        }
    ],
    "sg:phone":"+1 661 834 4469",
    "sg:postcode":"93304",
    "sg:province":"CA",
    "sg:tags":[
        "grocer"
    ],
    "wof:name":"Basic Foods",
    "wof:placetype":"venue"
},
  "geometry": {"coordinates":[-119.02127900000001,35.32881],"type":"Point"}
}