{
  "type": "Feature",
  "properties": {
    "addr:full":"4125 Blackford Ave San Jose CA 95117",
    "addr:housenumber":"4125",
    "addr:postcode":"95117",
    "addr:street":"Blackford Ave",
    "iso:country":"US",
    "sg:address":"4125 Blackford Ave",
    "sg:city":"San Jose",
    "sg:classifiers":[
        {
            "category":"Health Services",
            "subcategory":"Health Practitioner",
            "type":"Services"
        }
    ],
    "sg:phone":"+1 408 985 8220",
    "sg:postcode":"95117",
    "sg:province":"CA",
    "sg:tags":[
        "acupuncture"
    ],
    "wof:name":"California Traditional Articulated Healing Center",
    "wof:placetype":"venue"
},
  "geometry": {"coordinates":[-121.973606,37.314483],"type":"Point"}
}