{
  "type": "Feature",
  "properties": {
    "addr:full":"6747 Ridgeway Dr Pollock Pines CA 95726",
    "addr:housenumber":"6747",
    "addr:postcode":"95726",
    "addr:street":"Ridgeway Dr",
    "iso:country":"US",
    "sg:address":"6747 Ridgeway Dr",
    "sg:city":"Pollock Pines",
    "sg:classifiers":[
        {
            "category":"Freight",
            "type":"Transportation"
        }
    ],
    "sg:phone":"+1 530 644 5767",
    "sg:postcode":"95726",
    "sg:province":"CA",
    "sg:tags":[
        "operator",
        "local",
        "trucking"
    ],
    "wof:name":"JP Musholt Trucking",
    "wof:placetype":"venue"
},
  "geometry": {"coordinates":[-120.568076,38.760086],"type":"Point"}
}