{
  "type": "Feature",
  "properties": {
    "addr:full":"1816 Oak St Los Angeles CA 90015",
    "addr:housenumber":"1816",
    "addr:postcode":"90015",
    "addr:street":"Oak St",
    "iso:country":"US",
    "sg:address":"1816 Oak St",
    "sg:city":"Los Angeles",
    "sg:classifiers":[
        {
            "category":"Shopping",
            "subcategory":"Clothing, Apparel, & Fashions",
            "type":"Retail Goods"
        }
    ],
    "sg:phone":"+1 213 749 2586",
    "sg:postcode":"90015",
    "sg:province":"CA",
    "sg:tags":[
        "designer"
    ],
    "sg:website":"www.puzzlesent.com",
    "wof:name":"Puzzles",
    "wof:placetype":"venue"
},
  "geometry": {"coordinates":[-118.277435,34.03694],"type":"Point"}
}