{
  "type": "Feature",
  "properties": {
    "addr:full":"5251 E Beverly Blvd Los Angeles CA 90022",
    "addr:housenumber":"5251",
    "addr:postcode":"90022",
    "addr:street":"E Beverly Blvd",
    "iso:country":"US",
    "sg:address":"5251 E Beverly Blvd",
    "sg:city":"Los Angeles",
    "sg:classifiers":[
        {
            "category":"Social Services",
            "type":"Services"
        }
    ],
    "sg:phone":"+1 323 726 0299",
    "sg:postcode":"90022",
    "sg:province":"CA",
    "sg:tags":[
        "organization",
        "welfare"
    ],
    "wof:name":"Casa De Hermandad",
    "wof:placetype":"venue"
},
  "geometry": {"coordinates":[-118.15153100000001,34.030967],"type":"Point"}
}