{
  "type": "Feature",
  "properties": {
    "addr:full":"1355 E 4th St Ontario CA 91764",
    "addr:housenumber":"1355",
    "addr:postcode":"91764",
    "addr:street":"E 4Th St",
    "iso:country":"US",
    "sg:address":"1355 E 4th St",
    "sg:city":"Ontario",
    "sg:classifiers":[
        {
            "category":"Bars & Pubs",
            "type":"Food & Drink"
        }
    ],
    "sg:phone":"+1 909 984 5405",
    "sg:postcode":"91764",
    "sg:province":"CA",
    "sg:tags":[
        "lounge",
        "cocktail"
    ],
    "wof:name":"Capri Lounge",
    "wof:placetype":"venue"
},
  "geometry": {"coordinates":[-117.627092,34.077727],"type":"Point"}
}