{
  "type": "Feature",
  "properties": {
    "iso:country":"US",
    "sg:address":"1801 E March Ln",
    "sg:city":"Stockton",
    "sg:classifiers":[
        {
            "category":"Health Services",
            "subcategory":"Doctor",
            "type":"Services"
        }
    ],
    "sg:phone":"+1 209 473 6890",
    "sg:postcode":"95210",
    "sg:province":"CA",
    "sg:website":"www.capitaldialysis.com",
    "wof:name":"Dialysis Of Stockton",
    "wof:placetype":"venue"
},
  "geometry": {"coordinates":[-121.285586,38.562302],"type":"Point"}
}