{
  "type": "Feature",
  "properties": {
    "iso:country":"US",
    "sg:address":"701 W 5th St",
    "sg:city":"San Bernardino",
    "sg:classifiers":[
        {
            "category":"Banks & Credit Unions",
            "subcategory":"Bank",
            "type":"Services"
        }
    ],
    "sg:phone":"+1 909 888 1664",
    "sg:postcode":"92410",
    "sg:province":"CA",
    "sg:tags":[
        "cashing",
        "check"
    ],
    "wof:name":"Cash 4 Checks",
    "wof:placetype":"venue"
},
  "geometry": {"coordinates":[-117.300898,34.108333],"type":"Point"}
}