{
  "type": "Feature",
  "properties": {
    "iso:country":"US",
    "sg:address":"3119 S Willow Ave",
    "sg:city":"Fresno",
    "sg:classifiers":[
        {
            "category":"Professional",
            "subcategory":"Advertising",
            "type":"Services"
        }
    ],
    "sg:phone":"+1 559 264 2291",
    "sg:postcode":"93725",
    "sg:province":"CA",
    "sg:tags":[
        "distribution"
    ],
    "sg:website":"www.wynit.com",
    "wof:name":"Wynit Inc",
    "wof:placetype":"venue"
},
  "geometry": {"coordinates":[-119.726979,36.688032],"type":"Point"}
}