{
  "type": "Feature",
  "properties": {
    "addr:full":"233 E Carrillo St Santa Barbara CA 93101",
    "addr:housenumber":"233",
    "addr:postcode":"93101",
    "addr:street":"E Carrillo St",
    "iso:country":"US",
    "sg:address":"233 E Carrillo St",
    "sg:city":"Santa Barbara",
    "sg:classifiers":[
        {
            "category":"Real Estate",
            "subcategory":"Developer",
            "type":"Services"
        }
    ],
    "sg:phone":"+1 805 965 6671",
    "sg:postcode":"93101",
    "sg:province":"CA",
    "sg:website":"www.woodsidepartners.com",
    "wof:name":"Woodside Partners",
    "wof:placetype":"venue"
},
  "geometry": {"coordinates":[-119.69883,34.424369],"type":"Point"}
}