{
  "type": "Feature",
  "properties": {
    "iso:country":"US",
    "sg:address":"6262 Patterson Pass Rd",
    "sg:city":"Livermore",
    "sg:classifiers":[
        {
            "category":"Manufacturing",
            "subcategory":"Printing",
            "type":"Manufacturing & Wholesale Goods"
        }
    ],
    "sg:phone":"+1 925 455 2500",
    "sg:postcode":"94550",
    "sg:province":"CA",
    "sg:tags":[
        "color",
        "photo",
        "engrave"
    ],
    "wof:name":"Color Media",
    "wof:placetype":"venue"
},
  "geometry": {"coordinates":[-121.716391,37.695389],"type":"Point"}
}