{
  "type": "Feature",
  "properties": {
    "iso:country":"US",
    "sg:address":"2222 Foothill Blvd",
    "sg:city":"La Canada Fltrdg",
    "sg:classifiers":[
        {
            "category":"Professional",
            "subcategory":"Management & Consulting",
            "type":"Services"
        }
    ],
    "sg:phone":"+1 818 542 3730",
    "sg:postcode":"91011",
    "sg:province":"CA",
    "sg:tags":[
        "consultant",
        "broker"
    ],
    "wof:name":"Ncl & Assoc LLC",
    "wof:placetype":"venue"
},
  "geometry": {"coordinates":[-118.22640699999999,34.216594],"type":"Point"}
}