{
  "type": "Feature",
  "properties": {
    "addr:full":"13668 Oxnard St Van Nuys CA 91401",
    "addr:housenumber":"13668",
    "addr:postcode":"91401",
    "addr:street":"Oxnard St",
    "iso:country":"US",
    "sg:address":"13668 Oxnard St",
    "sg:city":"Van Nuys",
    "sg:classifiers":[
        {
            "category":"Food & Beverages",
            "subcategory":"Bakery",
            "type":"Retail Goods"
        }
    ],
    "sg:phone":"+1 818 988 5148",
    "sg:postcode":"91401",
    "sg:province":"CA",
    "sg:tags":[
        "baker"
    ],
    "wof:name":"Sweet's Bakery",
    "wof:placetype":"venue"
},
  "geometry": {"coordinates":[-118.431,34.179501],"type":"Point"}
}