{
  "type": "Feature",
  "properties": {
    "addr:full":"13465 Cam Canada El Cajon CA 92021",
    "addr:housenumber":"13465",
    "addr:postcode":"92021",
    "addr:street":"Cam Canada",
    "iso:country":"US",
    "sg:address":"13465 Cam Canada",
    "sg:city":"El Cajon",
    "sg:classifiers":[
        {
            "category":"Restaurant",
            "type":"Food & Drink"
        }
    ],
    "sg:phone":"+1 619 390 4000",
    "sg:postcode":"92021",
    "sg:province":"CA",
    "sg:tags":[
        "pizza"
    ],
    "wof:name":"Giant New York Pizza & Ice Crm",
    "wof:placetype":"venue"
},
  "geometry": {"coordinates":[-116.90136099999999,32.825656],"type":"Point"}
}