{
  "type": "Feature",
  "properties": {
    "addr:full":"15732 Screaming Eagle Ave Bakersfield CA 93312",
    "addr:postcode":"15732;93312",
    "addr:street":"Screaming Eagle Ave",
    "iso:country":"US",
    "sg:address":"15732 Screaming Eagle Ave",
    "sg:city":"Bakersfield",
    "sg:classifiers":[
        {
            "category":"Freight",
            "type":"Transportation"
        }
    ],
    "sg:phone":"+1 661 829 1873",
    "sg:postcode":"93312",
    "sg:province":"CA",
    "sg:tags":[
        "trucking"
    ],
    "wof:name":"T & T Trucking Crane Inc",
    "wof:placetype":"venue"
},
  "geometry": {"coordinates":[-119.176992,35.375561],"type":"Point"}
}