{
  "type": "Feature",
  "properties": {
    "iso:country":"US",
    "sg:address":"2455 Otay Center Dr",
    "sg:city":"San Diego",
    "sg:classifiers":[
        {
            "category":"Real Estate",
            "subcategory":"Real Estate Operator",
            "type":"Services"
        }
    ],
    "sg:phone":"+1 619 661 9850",
    "sg:postcode":"92154",
    "sg:province":"CA",
    "sg:tags":[
        "mall",
        "shopping",
        "center"
    ],
    "wof:name":"Otay Shopping Ctr",
    "wof:placetype":"venue"
},
  "geometry": {"coordinates":[-116.944124,32.556651],"type":"Point"}
}