{
  "type": "Feature",
  "properties": {
    "addr:full":"932 E 12th St Los Angeles CA 90021",
    "addr:housenumber":"932",
    "addr:postcode":"90021",
    "addr:street":"E 12Th St",
    "iso:country":"US",
    "sg:address":"932 E 12th St",
    "sg:city":"Los Angeles",
    "sg:classifiers":[
        {
            "category":"Professional",
            "type":"Services"
        }
    ],
    "sg:phone":"+1 213 748 9943",
    "sg:postcode":"90021",
    "sg:province":"CA",
    "sg:tags":[
        "establishment"
    ],
    "wof:name":"Watch Time",
    "wof:placetype":"venue"
},
  "geometry": {"coordinates":[-118.248075,34.031286],"type":"Point"}
}