{
  "type": "Feature",
  "properties": {
    "iso:country":"US",
    "sg:address":"686 Broadway St",
    "sg:city":"Redwood City",
    "sg:classifiers":[
        {
            "category":"Food & Beverages",
            "subcategory":"Bakery",
            "type":"Retail Goods"
        }
    ],
    "sg:phone":"+1 650 369 9644",
    "sg:postcode":"94063",
    "sg:province":"CA",
    "sg:tags":[
        "baker"
    ],
    "wof:name":"Douce France",
    "wof:placetype":"venue"
},
  "geometry": {"coordinates":[-122.207347,37.486025],"type":"Point"}
}