{
  "type": "Feature",
  "properties": {
    "addr:full":"2840 Greenwood Rd Greenwood CA 95635",
    "addr:housenumber":"2840",
    "addr:postcode":"95635",
    "addr:street":"Greenwood Rd",
    "iso:country":"US",
    "sg:address":"2840 Greenwood Rd",
    "sg:city":"Greenwood",
    "sg:classifiers":[
        {
            "category":"Home & Garden",
            "subcategory":"Household Appliances",
            "type":"Retail Goods"
        }
    ],
    "sg:phone":"+1 530 889 8704",
    "sg:postcode":"95635",
    "sg:province":"CA",
    "wof:name":"Owen Mc Coy Appliance Repair",
    "wof:placetype":"venue"
},
  "geometry": {"coordinates":[-120.908097,38.889051],"type":"Point"}
}