{
  "type": "Feature",
  "properties": {
    "addr:full":"1100 W Olive Ave Fullerton CA 92833",
    "addr:housenumber":"1100",
    "addr:postcode":"92833",
    "addr:street":"W Olive Ave",
    "iso:country":"US",
    "sg:address":"1100 W Olive Ave",
    "sg:city":"Fullerton",
    "sg:classifiers":[
        {
            "category":"Education",
            "subcategory":"School",
            "type":"Public Place"
        }
    ],
    "sg:phone":"+1 714 447 7775",
    "sg:postcode":"92833",
    "sg:province":"CA",
    "sg:tags":[
        "high",
        "middle",
        "elementary"
    ],
    "sg:website":"www.fsd.k12.ca.us",
    "wof:name":"Fullerton Elementary School District",
    "wof:placetype":"venue"
},
  "geometry": {"coordinates":[-117.943878,33.862812],"type":"Point"}
}