{
  "type": "Feature",
  "properties": {
    "addr:full":"15508 Lakewood Blvd Bellflower CA 90706",
    "addr:housenumber":"15508",
    "addr:postcode":"90706",
    "addr:street":"Lakewood Blvd",
    "iso:country":"US",
    "sg:address":"15508 Lakewood Blvd",
    "sg:city":"Bellflower",
    "sg:classifiers":[
        {
            "category":"Building & Trades",
            "subcategory":"Construction",
            "type":"Services"
        }
    ],
    "sg:phone":"+1 562 866 3396",
    "sg:postcode":"90706",
    "sg:province":"CA",
    "sg:tags":[
        "paving",
        "contractor"
    ],
    "sg:website":"www.shamrockpaving.com",
    "wof:name":"Shamrock Asphalt Inc",
    "wof:placetype":"venue"
},
  "geometry": {"coordinates":[-118.142544,33.894268],"type":"Point"}
}