{
  "type": "Feature",
  "properties": {
    "iso:country":"US",
    "sg:address":"2441 Summerhill Ln",
    "sg:city":"Fallbrook",
    "sg:classifiers":[
        {
            "category":"Real Estate",
            "subcategory":"Real Estate Operator",
            "type":"Services"
        }
    ],
    "sg:phone":"+1 760 728 5616",
    "sg:postcode":"92028",
    "sg:province":"CA",
    "sg:tags":[
        "property",
        "lessor"
    ],
    "wof:name":"Suzanne Zimmerle",
    "wof:placetype":"venue"
},
  "geometry": {"coordinates":[-117.241212,33.350254],"type":"Point"}
}