{
  "type": "Feature",
  "properties": {
    "addr:full":"2112 Fruitvale Ave Oakland CA 94601",
    "addr:housenumber":"2112",
    "addr:postcode":"94601",
    "addr:street":"Fruitvale Ave",
    "iso:country":"US",
    "sg:address":"2112 Fruitvale Ave",
    "sg:city":"Oakland",
    "sg:classifiers":[
        {
            "category":"Education",
            "subcategory":"Special Training",
            "type":"Public Place"
        }
    ],
    "sg:phone":"+1 510 792 2750",
    "sg:postcode":"94601",
    "sg:province":"CA",
    "sg:tags":[
        "tutoring"
    ],
    "wof:name":"Amy's Tutoring",
    "wof:placetype":"venue"
},
  "geometry": {"coordinates":[-122.222476,37.784411],"type":"Point"}
}