{
  "type": "Feature",
  "properties": {
    "iso:country":"US",
    "sg:address":"2268 Galleria At Tyler",
    "sg:city":"Riverside",
    "sg:classifiers":[
        {
            "category":"Restaurant",
            "type":"Food & Drink"
        }
    ],
    "sg:menulink":"http://www.allmenus.com/ca/riverside/239994-panda-express/menu/",
    "sg:phone":"+1 951 352 3652",
    "sg:postcode":"92503",
    "sg:province":"CA",
    "sg:tags":[
        "asian",
        "chinese"
    ],
    "wof:name":"Panda Express",
    "wof:placetype":"venue"
},
  "geometry": {"coordinates":[-117.45862700000001,33.908902],"type":"Point"}
}