{
  "type": "Feature",
  "properties": {
    "addr:full":"1263 E Arques Ave Sunnyvale CA 94086",
    "addr:housenumber":"1263",
    "addr:postcode":"94086",
    "addr:street":"E Arques Ave",
    "iso:country":"US",
    "sg:address":"1263 E Arques Ave",
    "sg:city":"Sunnyvale",
    "sg:classifiers":[
        {
            "category":"Professional",
            "subcategory":"Testing Lab",
            "type":"Services"
        }
    ],
    "sg:phone":"+1 408 764 2000",
    "sg:postcode":"94086",
    "sg:province":"CA",
    "sg:tags":[
        "laboratory"
    ],
    "sg:website":"www.symyx.com",
    "wof:name":"Symyx Technologies Inc",
    "wof:placetype":"venue"
},
  "geometry": {"coordinates":[-122.00094,37.38053],"type":"Point"}
}