{
  "type": "Feature",
  "properties": {
    "addr:full":"180 Market Pl San Ramon CA 94583",
    "addr:housenumber":"180",
    "addr:postcode":"94583",
    "addr:street":"Market Pl",
    "iso:country":"US",
    "sg:address":"180 Market Pl",
    "sg:city":"San Ramon",
    "sg:classifiers":[
        {
            "category":"Recreation",
            "type":"Entertainment"
        }
    ],
    "sg:phone":"+1 925 244 1171",
    "sg:postcode":"94583",
    "sg:province":"CA",
    "sg:tags":[
        "instruction",
        "gymnastic"
    ],
    "wof:name":"My Gym Children's Fitness Ctr",
    "wof:placetype":"venue"
},
  "geometry": {"coordinates":[-121.949607,37.763679],"type":"Point"}
}