{
  "type": "Feature",
  "properties": {
    "iso:country":"US",
    "sg:address":"1320 Leafwood Dr",
    "sg:city":"Novato",
    "sg:classifiers":[
        {
            "category":"Building & Trades",
            "subcategory":"Landscaping Services",
            "type":"Services"
        }
    ],
    "sg:phone":"+1 415 898 8833",
    "sg:postcode":"94947",
    "sg:province":"CA",
    "sg:tags":[
        "lawn",
        "maintenance",
        "grounds"
    ],
    "wof:name":"Figueroa Brothers",
    "wof:placetype":"venue"
},
  "geometry": {"coordinates":[-122.562304,38.08909],"type":"Point"}
}