{
  "type": "Feature",
  "properties": {
    "addr:full":"509 Park Boulevard San Diego CA 92101",
    "addr:housenumber":"509",
    "addr:postcode":"92101",
    "addr:street":"Park Boulevard",
    "iso:country":"US",
    "sg:address":"509 Park Boulevard",
    "sg:city":"San Diego",
    "sg:classifiers":[
        {
            "category":"Personal",
            "subcategory":"Tattoo Parlor",
            "type":"Services"
        }
    ],
    "sg:phone":"+1 619 236 0020",
    "sg:postcode":"92101",
    "sg:province":"CA",
    "wof:name":"Swallowtail Tattoo",
    "wof:placetype":"venue"
},
  "geometry": {"coordinates":[-117.15387,32.710797],"type":"Point"}
}