{
  "type": "Feature",
  "properties": {
    "addr:full":"7373 Co Rd 19 Orland CA 95963",
    "addr:housenumber":"7373;19",
    "addr:postcode":"95963",
    "addr:street":"Co Rd",
    "iso:country":"US",
    "sg:address":"7373 Co Rd 19",
    "sg:city":"Orland",
    "sg:classifiers":[
        {
            "category":"Professional",
            "type":"Services"
        }
    ],
    "sg:phone":"+1 530 891 1095",
    "sg:postcode":"95963",
    "sg:province":"CA",
    "wof:name":"Brad Hall",
    "wof:placetype":"venue"
},
  "geometry": {"coordinates":[-122.09904,39.728455],"type":"Point"}
}