{
  "type": "Feature",
  "properties": {
    "addr:full":"125 Jewell Street Santa Cruz CA 95060",
    "addr:housenumber":"125",
    "addr:postcode":"95060",
    "addr:street":"Jewell Street",
    "iso:country":"US",
    "sg:address":"125 Jewell Street",
    "sg:city":"Santa Cruz",
    "sg:classifiers":[
        {
            "category":"Professional",
            "subcategory":"Accounting & Tax Preparation",
            "type":"Services"
        }
    ],
    "sg:phone":"+1 831 466 0778",
    "sg:postcode":"95060",
    "sg:province":"CA",
    "sg:tags":[
        "accountant"
    ],
    "wof:name":"Adams Kirk S CPA",
    "wof:placetype":"venue"
},
  "geometry": {"coordinates":[-122.02580399999999,36.988341],"type":"Point"}
}