{
  "type": "Feature",
  "properties": {
    "iso:country":"US",
    "sg:address":"9146 E Stockton Blvd",
    "sg:city":"Elk Grove",
    "sg:classifiers":[
        {
            "category":"Shopping",
            "subcategory":"Stationery & Office Supplies",
            "type":"Retail Goods"
        }
    ],
    "sg:phone":"+1 916 686 2450",
    "sg:postcode":"95624",
    "sg:province":"CA",
    "wof:name":"Staples The Office Superstore",
    "wof:placetype":"venue"
},
  "geometry": {"coordinates":[-121.395231,38.425503],"type":"Point"}
}