{
  "type": "Feature",
  "properties": {
    "iso:country":"US",
    "sg:address":"3731 Wilshire Blvd",
    "sg:city":"Los Angeles",
    "sg:classifiers":[
        {
            "category":"Health Services",
            "subcategory":"Doctor",
            "type":"Services"
        }
    ],
    "sg:phone":"+1 213 382 6746",
    "sg:postcode":"90010",
    "sg:province":"CA",
    "sg:tags":[
        "surgeon",
        "oral"
    ],
    "wof:name":"Wong Edmund DDS",
    "wof:placetype":"venue"
},
  "geometry": {"coordinates":[-118.306999,34.061699],"type":"Point"}
}