{
  "type": "Feature",
  "properties": {
    "addr:full":"5776 Stoneridge Mall Rd Pleasanton CA 94588",
    "addr:housenumber":"5776",
    "addr:postcode":"94588",
    "addr:street":"Stoneridge Mall Rd",
    "iso:country":"US",
    "sg:address":"5776 Stoneridge Mall Rd",
    "sg:city":"Pleasanton",
    "sg:classifiers":[
        {
            "category":"Organizations",
            "subcategory":"Religious Organization",
            "type":"Services"
        }
    ],
    "sg:phone":"+1 925 734 8772",
    "sg:postcode":"94588",
    "sg:province":"CA",
    "sg:tags":[
        "counseling",
        "pastoral",
        "clergy"
    ],
    "wof:name":"Dick Matthews",
    "wof:placetype":"venue"
},
  "geometry": {"coordinates":[-121.931341,37.693536],"type":"Point"}
}