{
  "type": "Feature",
  "properties": {
    "addr:full":"950 Orange Ave Coronado CA 92118",
    "addr:housenumber":"950",
    "addr:postcode":"92118",
    "addr:street":"Orange Ave",
    "iso:country":"US",
    "sg:address":"950 Orange Ave",
    "sg:city":"Coronado",
    "sg:classifiers":[
        {
            "category":"Organizations",
            "subcategory":"Non-profit Organization",
            "type":"Services"
        }
    ],
    "sg:phone":"+1 619 435 9972",
    "sg:postcode":"92118",
    "sg:province":"CA",
    "sg:tags":[
        "information",
        "alcoholism",
        "treatment"
    ],
    "wof:name":"Alano Club Of Coronado",
    "wof:placetype":"venue"
},
  "geometry": {"coordinates":[-117.17953900000001,32.686657],"type":"Point"}
}