{
  "type": "Feature",
  "properties": {
    "addr:full":"602 Oakborough Ave # 602 Roseville CA 95747",
    "addr:housenumber":"602",
    "addr:postcode":"95747",
    "addr:street":"Oakborough Ave # 602",
    "iso:country":"US",
    "sg:address":"602 Oakborough Ave # 602",
    "sg:city":"Roseville",
    "sg:classifiers":[
        {
            "category":"Government",
            "subcategory":"Post Office",
            "type":"Public Place"
        }
    ],
    "sg:phone":"+1 916 847 3846",
    "sg:postcode":"95747",
    "sg:province":"CA",
    "sg:tags":[
        "delivery",
        "courier"
    ],
    "wof:name":"(Ete)Edward Tompkins Express",
    "wof:placetype":"venue"
},
  "geometry": {"coordinates":[-121.315302,38.754869],"type":"Point"}
}