{
  "type": "Feature",
  "properties": {
    "addr:full":"1475 S Harbor Blvd Fullerton CA 92832",
    "addr:housenumber":"1475",
    "addr:postcode":"92832",
    "addr:street":"S Harbor Blvd",
    "iso:country":"US",
    "sg:address":"1475 S Harbor Blvd",
    "sg:city":"Fullerton",
    "sg:classifiers":[
        {
            "category":"Shopping",
            "subcategory":"Jewelry",
            "type":"Retail Goods"
        }
    ],
    "sg:phone":"+1 714 526 0814",
    "sg:postcode":"92832",
    "sg:province":"CA",
    "sg:website":"www.northandsouthjewelry.com",
    "wof:name":"North & South Jewelry Co",
    "wof:placetype":"venue"
},
  "geometry": {"coordinates":[-117.924004,33.855099],"type":"Point"}
}