{
  "type": "Feature",
  "properties": {
    "addr:full":"360 W Linden Ave Burbank CA 91506",
    "addr:housenumber":"360",
    "addr:postcode":"91506",
    "addr:street":"W Linden Ave",
    "iso:country":"US",
    "sg:address":"360 W Linden Ave",
    "sg:city":"Burbank",
    "sg:classifiers":[
        {
            "category":"Professional",
            "subcategory":"Advertising",
            "type":"Services"
        }
    ],
    "sg:phone":"+1 818 842 2110",
    "sg:postcode":"91506",
    "sg:province":"CA",
    "wof:name":"Vision International",
    "wof:placetype":"venue"
},
  "geometry": {"coordinates":[-118.30631700000001,34.163224],"type":"Point"}
}