{
  "type": "Feature",
  "properties": {
    "iso:country":"US",
    "sg:address":"1893 Knoll Dr",
    "sg:city":"Ventura",
    "sg:classifiers":[
        {
            "category":"Professional",
            "subcategory":"Lawyer & Legal Services",
            "type":"Services"
        }
    ],
    "sg:phone":"+1 805 642 2001",
    "sg:postcode":"93003",
    "sg:province":"CA",
    "sg:tags":[
        "attorney"
    ],
    "wof:name":"Joseph R Henderson",
    "wof:placetype":"venue"
},
  "geometry": {"coordinates":[-119.22012599999999,34.256163],"type":"Point"}
}