{
  "type": "Feature",
  "properties": {
    "iso:country":"US",
    "sg:address":"3641 E Thousand Oaks Blvd",
    "sg:city":"Westlake Village",
    "sg:classifiers":[
        {
            "category":"Shopping",
            "subcategory":"Shoes",
            "type":"Retail Goods"
        }
    ],
    "sg:phone":"+1 805 373 5399",
    "sg:postcode":"91362",
    "sg:province":"CA",
    "wof:name":"Pagano Shoe Repair",
    "wof:placetype":"venue"
},
  "geometry": {"coordinates":[-118.82965,34.164602],"type":"Point"}
}