{
  "type": "Feature",
  "properties": {
    "addr:full":"3940 Valley Blvd Walnut CA 91789",
    "addr:housenumber":"3940",
    "addr:postcode":"91789",
    "addr:street":"Valley Blvd",
    "iso:country":"US",
    "sg:address":"3940 Valley Blvd",
    "sg:city":"Walnut",
    "sg:classifiers":[
        {
            "category":"Wholesale",
            "subcategory":"Apparel",
            "type":"Manufacturing & Wholesale Goods"
        }
    ],
    "sg:phone":"+1 909 598 3455",
    "sg:postcode":"91789",
    "sg:province":"CA",
    "sg:tags":[
        "clothing"
    ],
    "wof:name":"Kazah Fashion Inc",
    "wof:placetype":"venue"
},
  "geometry": {"coordinates":[-117.82054599999999,34.040364],"type":"Point"}
}