{
  "type": "Feature",
  "properties": {
    "addr:full":"7677 Center Ave Huntington Beach CA 92647",
    "addr:housenumber":"7677",
    "addr:postcode":"92647",
    "addr:street":"Center Ave",
    "iso:country":"US",
    "sg:address":"7677 Center Ave",
    "sg:city":"Huntington Beach",
    "sg:classifiers":[
        {
            "category":"Health Services",
            "subcategory":"Clinic",
            "type":"Services"
        }
    ],
    "sg:phone":"+1 714 896 0705",
    "sg:postcode":"92647",
    "sg:province":"CA",
    "sg:tags":[
        "home",
        "care"
    ],
    "wof:name":"HealthSouth",
    "wof:placetype":"venue"
},
  "geometry": {"coordinates":[-117.996669,33.73403],"type":"Point"}
}