{
  "type": "Feature",
  "properties": {
    "addr:full":"2001 Peralta St Oakland CA 94607",
    "addr:housenumber":"2001",
    "addr:postcode":"94607",
    "addr:street":"Peralta St",
    "iso:country":"US",
    "sg:address":"2001 Peralta St",
    "sg:city":"Oakland",
    "sg:classifiers":[
        {
            "category":"Wholesale",
            "subcategory":"Chemicals & Plastics",
            "type":"Manufacturing & Wholesale Goods"
        }
    ],
    "sg:phone":"+1 510 834 0432",
    "sg:postcode":"94607",
    "sg:province":"CA",
    "sg:tags":[
        "helium"
    ],
    "wof:name":"Liquid Carbonic",
    "wof:placetype":"venue"
},
  "geometry": {"coordinates":[-122.28967,37.817001],"type":"Point"}
}