{
  "type": "Feature",
  "properties": {
    "iso:country":"US",
    "sg:address":"11942 Hawthorne Blvd",
    "sg:city":"Hawthorne",
    "sg:classifiers":[
        {
            "category":"Shopping",
            "subcategory":"Clothing, Apparel, & Fashions",
            "type":"Retail Goods"
        }
    ],
    "sg:phone":"+1 310 973 0804",
    "sg:postcode":"90250",
    "sg:province":"CA",
    "sg:tags":[
        "apparel",
        "clothing",
        "store",
        "women's"
    ],
    "wof:name":"D Giovannis Fashion",
    "wof:placetype":"venue"
},
  "geometry": {"coordinates":[-118.35247099999999,33.924681],"type":"Point"}
}