{
  "type": "Feature",
  "properties": {
    "iso:country":"US",
    "sg:address":"2042 Market St",
    "sg:city":"Redding",
    "sg:classifiers":[
        {
            "category":"Building & Trades",
            "subcategory":"Construction",
            "type":"Services"
        }
    ],
    "sg:phone":"+1 530 245 1703",
    "sg:postcode":"96001",
    "sg:province":"CA",
    "sg:tags":[
        "contractor"
    ],
    "wof:name":"Finish Crew",
    "wof:placetype":"venue"
},
  "geometry": {"coordinates":[-122.388727,40.579179],"type":"Point"}
}