{
  "type": "Feature",
  "properties": {
    "addr:full":"4890 E Holland Ave Fresno CA 93726",
    "addr:housenumber":"4890",
    "addr:postcode":"93726",
    "addr:street":"E Holland Ave",
    "iso:country":"US",
    "sg:address":"4890 E Holland Ave",
    "sg:city":"Fresno",
    "sg:classifiers":[
        {
            "category":"Organizations",
            "subcategory":"Religious Organization",
            "type":"Services"
        }
    ],
    "sg:phone":"+1 559 291 5521",
    "sg:postcode":"93726",
    "sg:province":"CA",
    "sg:tags":[
        "churches-baptist",
        "church"
    ],
    "sg:website":"http://www.trinityfresno.org",
    "wof:name":"Trinity Southern Baptist Church",
    "wof:placetype":"venue"
},
  "geometry": {"coordinates":[-119.732073,36.79765],"type":"Point"}
}