{
  "type": "Feature",
  "properties": {
    "addr:full":"18853 Lenny St Salinas CA 93906",
    "addr:postcode":"18853;93906",
    "addr:street":"Lenny St",
    "iso:country":"US",
    "sg:address":"18853 Lenny St",
    "sg:city":"Salinas",
    "sg:classifiers":[
        {
            "category":"Professional",
            "subcategory":"Art Services",
            "type":"Services"
        }
    ],
    "sg:phone":"+1 831 442 1651",
    "sg:postcode":"93906",
    "sg:province":"CA",
    "sg:tags":[
        "commercial",
        "mfg",
        "design",
        "trimming"
    ],
    "wof:name":"Motiv8 Sportswear",
    "wof:placetype":"venue"
},
  "geometry": {"coordinates":[-121.646247,36.726662],"type":"Point"}
}