{
  "type": "Feature",
  "properties": {
    "addr:full":"14160 Culver Dr Irvine CA 92714",
    "addr:housenumber":"14160",
    "addr:postcode":"92714",
    "addr:street":"Culver Dr",
    "iso:country":"US",
    "sg:address":"14160 Culver Dr",
    "sg:city":"Irvine",
    "sg:classifiers":[
        {
            "category":"Restaurant",
            "type":"Food & Drink"
        }
    ],
    "sg:phone":"+1 949 857 5500",
    "sg:postcode":"92714",
    "sg:province":"CA",
    "wof:name":"Denny's Restaurant",
    "wof:placetype":"venue"
},
  "geometry": {"coordinates":[-117.783951,33.70813],"type":"Point"}
}