{
  "type": "Feature",
  "properties": {
    "addr:full":"11428 214th St Lakewood CA 90715",
    "addr:housenumber":"11428",
    "addr:postcode":"90715",
    "addr:street":"214Th St",
    "iso:country":"US",
    "sg:address":"11428 214th St",
    "sg:city":"Lakewood",
    "sg:classifiers":[
        {
            "category":"Professional",
            "type":"Services"
        }
    ],
    "sg:phone":"+1 562 860 8221",
    "sg:postcode":"90715",
    "sg:province":"CA",
    "sg:tags":[
        "establishment"
    ],
    "wof:name":"Images By Daniel",
    "wof:placetype":"venue"
},
  "geometry": {"coordinates":[-118.09011099999999,33.834751],"type":"Point"}
}