{
  "type": "Feature",
  "properties": {
    "addr:full":"559 W Palm Dr Arcadia CA 91007",
    "addr:housenumber":"559",
    "addr:postcode":"91007",
    "addr:street":"W Palm Dr",
    "iso:country":"US",
    "sg:address":"559 W Palm Dr",
    "sg:city":"Arcadia",
    "sg:classifiers":[
        {
            "category":"Professional",
            "type":"Services"
        }
    ],
    "sg:phone":"+1 626 574 1468",
    "sg:postcode":"91007",
    "sg:province":"CA",
    "wof:name":"Lee Hsun-Liang",
    "wof:placetype":"venue"
},
  "geometry": {"coordinates":[-118.047386,34.111479],"type":"Point"}
}