{
  "type": "Feature",
  "properties": {
    "iso:country":"US",
    "sg:address":"1602 S Palos Verdes St",
    "sg:city":"San Pedro",
    "sg:classifiers":[
        {
            "category":"Shopping",
            "subcategory":"Computers & Home Electronics",
            "type":"Retail Goods"
        }
    ],
    "sg:phone":"+1 310 831 4996",
    "sg:postcode":"90731",
    "sg:province":"CA",
    "sg:tags":[
        "television",
        "radio"
    ],
    "wof:name":"Sal's Mobile TV Repair",
    "wof:placetype":"venue"
},
  "geometry": {"coordinates":[-118.281328,33.728774],"type":"Point"}
}