{
  "type": "Feature",
  "properties": {
    "addr:full":"2883 Church St Georgetown CA 95634",
    "addr:housenumber":"2883",
    "addr:postcode":"95634",
    "addr:street":"Church St",
    "iso:country":"US",
    "sg:address":"2883 Church St",
    "sg:city":"Georgetown",
    "sg:classifiers":[
        {
            "category":"Insurance",
            "subcategory":"Hazard Insurance",
            "type":"Services"
        }
    ],
    "sg:phone":"+1 530 333 4362",
    "sg:postcode":"95634",
    "sg:province":"CA",
    "sg:tags":[
        "commercial",
        "business"
    ],
    "wof:name":"Ericson Financial",
    "wof:placetype":"venue"
},
  "geometry": {"coordinates":[-120.838303,38.908256],"type":"Point"}
}