{
  "type": "Feature",
  "properties": {
    "iso:country":"US",
    "sg:address":"1838 Tyler Ave",
    "sg:city":"South El Monte",
    "sg:classifiers":[
        {
            "category":"Home & Garden",
            "subcategory":"Furniture",
            "type":"Retail Goods"
        }
    ],
    "sg:phone":"+1 626 350 9095",
    "sg:postcode":"91733",
    "sg:province":"CA",
    "sg:tags":[
        "equipment",
        "kitchen",
        "cabinet"
    ],
    "wof:name":"Amcal Wood Corp",
    "wof:placetype":"venue"
},
  "geometry": {"coordinates":[-118.039692,34.049224],"type":"Point"}
}