{
  "type": "Feature",
  "properties": {
    "iso:country":"US",
    "sg:address":"904 Oak Grove Ave",
    "sg:city":"Burlingame",
    "sg:classifiers":[
        {
            "category":"Freight",
            "type":"Transportation"
        }
    ],
    "sg:phone":"+1 650 558 0848",
    "sg:postcode":"94010",
    "sg:province":"CA",
    "sg:tags":[
        "delivery"
    ],
    "wof:name":"B B Express",
    "wof:placetype":"venue"
},
  "geometry": {"coordinates":[-122.34984300000001,37.583248],"type":"Point"}
}