{
  "type": "Feature",
  "properties": {
    "iso:country":"US",
    "sg:address":"315 W Pondera St Ste B",
    "sg:city":"Lancaster",
    "sg:classifiers":[
        {
            "category":"Retail",
            "subcategory":"Auto Rental",
            "type":"Services"
        },
        {
            "category":"Local Transit",
            "type":"Transportation"
        }
    ],
    "sg:phone":"+1 661 729 9231",
    "sg:postcode":"93534",
    "sg:province":"CA",
    "sg:tags":[
        "shuttle",
        "limousine"
    ],
    "wof:name":"5 Starr Limousine",
    "wof:placetype":"venue"
},
  "geometry": {"coordinates":[-118.13270799999999,34.69018],"type":"Point"}
}