{
  "type": "Feature",
  "properties": {
    "addr:full":"5711 Lynnbrook Plz Yorba Linda CA 92886",
    "addr:housenumber":"5711",
    "addr:postcode":"92886",
    "addr:street":"Lynnbrook Plz",
    "iso:country":"US",
    "sg:address":"5711 Lynnbrook Plz",
    "sg:city":"Yorba Linda",
    "sg:classifiers":[
        {
            "category":"Building & Trades",
            "subcategory":"Electrical",
            "type":"Services"
        }
    ],
    "sg:phone":"+1 714 777 1020",
    "sg:postcode":"92886",
    "sg:province":"CA",
    "sg:tags":[
        "electrical",
        "contractor"
    ],
    "wof:name":"BTS Lighting Electric",
    "wof:placetype":"venue"
},
  "geometry": {"coordinates":[-117.79118200000001,33.877266],"type":"Point"}
}