{
  "type": "Feature",
  "properties": {
    "addr:full":"15333 Culver Drive Suite 690 Irvine CA 92604",
    "addr:housenumber":"15333",
    "addr:postcode":"92604",
    "addr:street":"Culver Drive Suite 690",
    "iso:country":"US",
    "sg:address":"15333 Culver Drive Suite 690",
    "sg:city":"Irvine",
    "sg:classifiers":[
        {
            "category":"Health Services",
            "subcategory":"Optometrist",
            "type":"Services"
        },
        {
            "category":"Shopping",
            "subcategory":"Optician",
            "type":"Retail Goods"
        }
    ],
    "sg:phone":"+1 949 552 4271",
    "sg:postcode":"92604",
    "sg:province":"CA",
    "sg:tags":[
        "eyewear"
    ],
    "wof:name":"Golden Vision Optometry",
    "wof:placetype":"venue"
},
  "geometry": {"coordinates":[-117.78927299999999,33.689026],"type":"Point"}
}