{
  "type": "Feature",
  "properties": {
    "iso:country":"US",
    "sg:address":"44424 10th St W",
    "sg:city":"Lancaster",
    "sg:classifiers":[
        {
            "category":"Real Estate",
            "subcategory":"Real Estate Services",
            "type":"Services"
        },
        {
            "category":"Banks & Credit Unions",
            "subcategory":"Financial Services",
            "type":"Services"
        }
    ],
    "sg:phone":"+1 949 723 5222",
    "sg:postcode":"93534",
    "sg:province":"CA",
    "sg:tags":[
        "loan",
        "mortgage"
    ],
    "sg:website":"http://www.powermortgagelender.com",
    "wof:name":"Seny Ike",
    "wof:placetype":"venue"
},
  "geometry": {"coordinates":[-118.148033,34.690138],"type":"Point"}
}