{
  "type": "Feature",
  "properties": {
    "addr:full":"30851 Agoura Rd Agoura Hills CA 91301",
    "addr:housenumber":"30851",
    "addr:postcode":"91301",
    "addr:street":"Agoura Rd",
    "iso:country":"US",
    "sg:address":"30851 Agoura Rd",
    "sg:city":"Agoura Hills",
    "sg:classifiers":[
        {
            "category":"Wholesale",
            "subcategory":"Electrical",
            "type":"Manufacturing & Wholesale Goods"
        }
    ],
    "sg:phone":"+1 818 735 3899",
    "sg:postcode":"91301",
    "sg:province":"CA",
    "sg:tags":[
        "software",
        "developer"
    ],
    "wof:name":"I D T",
    "wof:placetype":"venue"
},
  "geometry": {"coordinates":[-118.79259,34.144752],"type":"Point"}
}