{
  "type": "Feature",
  "properties": {
    "iso:country":"US",
    "sg:address":"1011 W Olive Ave Ste B",
    "sg:city":"Burbank",
    "sg:classifiers":[
        {
            "category":"Real Estate",
            "subcategory":"Real Estate Services",
            "type":"Services"
        }
    ],
    "sg:phone":"+1 818 303 8633",
    "sg:postcode":"91506",
    "sg:province":"CA",
    "sg:tags":[
        "management",
        "property"
    ],
    "wof:name":"Lar Incorporated",
    "wof:placetype":"venue"
},
  "geometry": {"coordinates":[-118.317621,34.172636],"type":"Point"}
}