{
  "type": "Feature",
  "properties": {
    "iso:country":"US",
    "sg:address":"200 Brannan St",
    "sg:city":"San Francisco",
    "sg:classifiers":[
        {
            "category":"Real Estate",
            "subcategory":"Real Estate Operator",
            "type":"Services"
        }
    ],
    "sg:postcode":"94107",
    "sg:province":"CA",
    "sg:tags":[
        "apartment"
    ],
    "sg:website":"www.200brannan.org",
    "wof:name":"200 Brannan",
    "wof:placetype":"venue"
},
  "geometry": {"coordinates":[-122.390592,37.784062],"type":"Point"}
}