{
  "type": "Feature",
  "properties": {
    "addr:full":"220 Ventura Ave Palo Alto CA 94306",
    "addr:housenumber":"220",
    "addr:postcode":"94306",
    "addr:street":"Ventura Ave",
    "iso:country":"US",
    "sg:address":"220 Ventura Ave",
    "sg:city":"Palo Alto",
    "sg:classifiers":[
        {
            "category":"Real Estate",
            "subcategory":"Real Estate Operator",
            "type":"Services"
        }
    ],
    "sg:phone":"+1 650 493 9576",
    "sg:postcode":"94306",
    "sg:province":"CA",
    "sg:tags":[
        "apartment"
    ],
    "wof:name":"Park Terrace Apartments",
    "wof:placetype":"venue"
},
  "geometry": {"coordinates":[-122.128708,37.418583],"type":"Point"}
}