{
  "type": "Feature",
  "properties": {
    "addr:full":"872 5th St Manhattan Beach CA 90266",
    "addr:housenumber":"872",
    "addr:postcode":"90266",
    "addr:street":"5Th St",
    "iso:country":"US",
    "sg:address":"872 5th St",
    "sg:city":"Manhattan Beach",
    "sg:classifiers":[
        {
            "category":"Professional",
            "subcategory":"Art Services",
            "type":"Services"
        }
    ],
    "sg:phone":"+1 310 937 3669",
    "sg:postcode":"90266",
    "sg:province":"CA",
    "sg:tags":[
        "graphic",
        "designer"
    ],
    "wof:name":"Graphic Directions Inc",
    "wof:placetype":"venue"
},
  "geometry": {"coordinates":[-118.400854,33.881896],"type":"Point"}
}