{
  "type": "Feature",
  "properties": {
    "addr:full":"2440 Larkin St San Francisco CA 94109",
    "addr:housenumber":"2440",
    "addr:postcode":"94109",
    "addr:street":"Larkin St",
    "iso:country":"US",
    "sg:address":"2440 Larkin St",
    "sg:city":"San Francisco",
    "sg:classifiers":[
        {
            "category":"Professional",
            "subcategory":"Art Services",
            "type":"Services"
        }
    ],
    "sg:phone":"+1 415 673 4394",
    "sg:postcode":"94109",
    "sg:province":"CA",
    "sg:tags":[
        "photographer"
    ],
    "wof:name":"Grace Sevy Photography",
    "wof:placetype":"venue"
},
  "geometry": {"coordinates":[-122.420931,37.800464],"type":"Point"}
}