{
  "type": "Feature",
  "properties": {
    "addr:full":"1401 N Broadway Los Angeles CA 90012",
    "addr:housenumber":"1401",
    "addr:postcode":"90012",
    "addr:street":"N Broadway",
    "iso:country":"US",
    "sg:address":"1401 N Broadway",
    "sg:city":"Los Angeles",
    "sg:classifiers":[
        {
            "category":"Professional",
            "type":"Services"
        },
        {
            "category":"Building & Trades",
            "subcategory":"Construction",
            "type":"Services"
        }
    ],
    "sg:phone":"+1 213 895 0224",
    "sg:postcode":"90012",
    "sg:province":"CA",
    "sg:tags":[
        "contractor"
    ],
    "sg:website":"www.cordobacorp.com/",
    "wof:name":"Cordoba Corporation",
    "wof:placetype":"venue"
},
  "geometry": {"coordinates":[-118.230144,34.07141],"type":"Point"}
}