{
  "type": "Feature",
  "properties": {
    "addr:full":"100 Bush Street Suite 300 San Francisco CA 94104",
    "addr:housenumber":"100",
    "addr:postcode":"94104",
    "addr:street":"Bush Street Suite 300",
    "iso:country":"US",
    "sg:address":"100 Bush Street Suite 300",
    "sg:city":"San Francisco",
    "sg:classifiers":[
        {
            "category":"Professional",
            "subcategory":"Computer Services",
            "type":"Services"
        }
    ],
    "sg:phone":"+60 14 642 8915",
    "sg:postcode":"94104",
    "sg:province":"CA",
    "sg:tags":[
        "money-transfer",
        "paypal",
        "international-money-transfer",
        "send-money"
    ],
    "sg:website":"http://xoom.com",
    "wof:name":"Xoom",
    "wof:placetype":"venue"
},
  "geometry": {"coordinates":[-122.400744,37.791177],"type":"Point"}
}