{
  "type": "Feature",
  "properties": {
    "addr:full":"2515 W 74th St Los Angeles CA 90043",
    "addr:housenumber":"2515",
    "addr:postcode":"90043",
    "addr:street":"W 74Th St",
    "iso:country":"US",
    "sg:address":"2515 W 74th St",
    "sg:city":"Los Angeles",
    "sg:classifiers":[
        {
            "category":"Shopping",
            "subcategory":"Computers & Home Electronics",
            "type":"Retail Goods"
        }
    ],
    "sg:phone":"+1 323 752 2799",
    "sg:postcode":"90043",
    "sg:province":"CA",
    "sg:tags":[
        "sound",
        "equipment",
        "system"
    ],
    "wof:name":"Sounds R Us",
    "wof:placetype":"venue"
},
  "geometry": {"coordinates":[-118.32105300000001,33.972843],"type":"Point"}
}