{
  "type": "Feature",
  "properties": {
    "addr:full":"5720 Ave Juan Bautista Riverside CA 92509",
    "addr:housenumber":"5720",
    "addr:postcode":"92509",
    "addr:street":"Ave Juan Bautista",
    "iso:country":"US",
    "sg:address":"5720 Ave Juan Bautista",
    "sg:city":"Riverside",
    "sg:classifiers":[
        {
            "category":"Wholesale",
            "subcategory":"Non-durable Goods",
            "type":"Manufacturing & Wholesale Goods"
        }
    ],
    "sg:phone":"+1 951 781 9800",
    "sg:postcode":"92509",
    "sg:province":"CA",
    "wof:name":"Aarcee Promotional Products",
    "wof:placetype":"venue"
},
  "geometry": {"coordinates":[-117.433528,33.983467],"type":"Point"}
}