{
  "type": "Feature",
  "properties": {
    "iso:country":"US",
    "sg:address":"1272 S Magnolia Ave",
    "sg:city":"Anaheim",
    "sg:classifiers":[
        {
            "category":"Personal",
            "type":"Services"
        }
    ],
    "sg:phone":"+1 714 826 4580",
    "sg:postcode":"92804",
    "sg:province":"CA",
    "sg:tags":[
        "sewing",
        "alteration"
    ],
    "wof:name":"West Anaheim Cleaners",
    "wof:placetype":"venue"
},
  "geometry": {"coordinates":[-117.975998,33.816898],"type":"Point"}
}