{
  "type": "Feature",
  "properties": {
    "addr:full":"2727 Walsh Ave Ste 101 Santa Clara CA 95051",
    "addr:housenumber":"2727",
    "addr:postcode":"95051",
    "addr:street":"Walsh Ave Ste 101",
    "iso:country":"US",
    "sg:address":"2727 Walsh Ave Ste 101",
    "sg:city":"Santa Clara",
    "sg:classifiers":[
        {
            "category":"Professional",
            "subcategory":"Employment Agencies",
            "type":"Services"
        }
    ],
    "sg:phone":"+1 408 562 2080",
    "sg:postcode":"95051",
    "sg:province":"CA",
    "wof:name":"Netsoft",
    "wof:placetype":"venue"
},
  "geometry": {"coordinates":[-121.975127,37.374033],"type":"Point"}
}