{
  "type": "Feature",
  "properties": {
    "iso:country":"US",
    "sg:address":"601 University Ave Ste 110",
    "sg:city":"Sacramento",
    "sg:classifiers":[
        {
            "category":"Professional",
            "subcategory":"Lawyer & Legal Services",
            "type":"Services"
        }
    ],
    "sg:phone":"+1 916 929 9060",
    "sg:postcode":"95825",
    "sg:province":"CA",
    "wof:name":"Freidberg Law Corp",
    "wof:placetype":"venue"
},
  "geometry": {"coordinates":[-121.420075,38.568352],"type":"Point"}
}