{
  "type": "Feature",
  "properties": {
    "addr:full":"1701 Pacific Ave Oxnard CA 93033",
    "addr:housenumber":"1701",
    "addr:postcode":"93033",
    "addr:street":"Pacific Ave",
    "iso:country":"US",
    "sg:address":"1701 Pacific Ave",
    "sg:city":"Oxnard",
    "sg:classifiers":[
        {
            "category":"Manufacturing",
            "subcategory":"Apparel",
            "type":"Manufacturing & Wholesale Goods"
        }
    ],
    "sg:phone":"+1 805 483 6339",
    "sg:postcode":"93033",
    "sg:province":"CA",
    "sg:tags":[
        "leather",
        "clothing",
        "durable",
        "fur",
        "mfg"
    ],
    "wof:name":"Scully Leather Wear",
    "wof:placetype":"venue"
},
  "geometry": {"coordinates":[-119.1643,34.180633],"type":"Point"}
}