{
  "type": "Feature",
  "properties": {
    "iso:country":"US",
    "sg:address":"4960 el Cajon Blvd",
    "sg:city":"San Diego",
    "sg:classifiers":[
        {
            "category":"Personal",
            "subcategory":"Beauty Salon",
            "type":"Services"
        }
    ],
    "sg:phone":"+1 619 583 0836",
    "sg:postcode":"92115",
    "sg:province":"CA",
    "wof:name":"Body Hair & Nials",
    "wof:placetype":"venue"
},
  "geometry": {"coordinates":[-117.087567,32.756755],"type":"Point"}
}