{
  "type": "Feature",
  "properties": {
    "iso:country":"US",
    "sg:address":"7419 S Normandie Ave",
    "sg:city":"Los Angeles",
    "sg:classifiers":[
        {
            "category":"Social Services",
            "subcategory":"Child Care",
            "type":"Services"
        }
    ],
    "sg:phone":"+1 323 750 1079",
    "sg:postcode":"90044",
    "sg:province":"CA",
    "sg:tags":[
        "day"
    ],
    "wof:name":"Little Rainbow Children's Center",
    "wof:placetype":"venue"
},
  "geometry": {"coordinates":[-118.300003,33.9725],"type":"Point"}
}