{
  "type": "Feature",
  "properties": {
    "addr:full":"615 S Rengstorff Ave Mountain View CA 94040",
    "addr:housenumber":"615",
    "addr:postcode":"94040",
    "addr:street":"S Rengstorff Ave",
    "iso:country":"US",
    "sg:address":"615 S Rengstorff Ave",
    "sg:city":"Mountain View",
    "sg:classifiers":[
        {
            "category":"Restaurant",
            "type":"Food & Drink"
        }
    ],
    "sg:menulink":"http://www.allmenus.com/ca/san-jose/19678-maldonados-pizzeria/menu/",
    "sg:phone":"+1 650 962 8499",
    "sg:postcode":"94040",
    "sg:province":"CA",
    "sg:tags":[
        "american",
        "pizza"
    ],
    "wof:name":"Maldonado's Pizzeria",
    "wof:placetype":"venue"
},
  "geometry": {"coordinates":[-122.10139100000001,37.396686],"type":"Point"}
}