{
  "type": "Feature",
  "properties": {
    "iso:country":"US",
    "sg:address":"122 Race St",
    "sg:city":"San Jose",
    "sg:classifiers":[
        {
            "category":"Organizations",
            "subcategory":"Religious Organization",
            "type":"Services"
        }
    ],
    "sg:phone":"+1 408 345 2319",
    "sg:postcode":"95126",
    "sg:province":"CA",
    "sg:tags":[
        "church"
    ],
    "wof:name":"Celebration Of Faith",
    "wof:placetype":"venue"
},
  "geometry": {"coordinates":[-121.911717,37.327918],"type":"Point"}
}