{
  "type": "Feature",
  "properties": {
    "addr:full":"5445 Martin Luther King Jr Blvd Lynwood CA 90262",
    "addr:housenumber":"5445",
    "addr:postcode":"90262",
    "addr:street":"Martin Luther King Jr Blvd",
    "iso:country":"US",
    "sg:address":"5445 Martin Luther King Jr Blvd",
    "sg:city":"Lynwood",
    "sg:classifiers":[
        {
            "category":"Manufacturing",
            "subcategory":"Motor Vehicles & Parts",
            "type":"Manufacturing & Wholesale Goods"
        }
    ],
    "sg:phone":"+1 310 635 0524",
    "sg:postcode":"90262",
    "sg:province":"CA",
    "sg:tags":[
        "trailer"
    ],
    "wof:name":"J & L Tank Co",
    "wof:placetype":"venue"
},
  "geometry": {"coordinates":[-118.18088899999999,33.919406],"type":"Point"}
}