{
  "type": "Feature",
  "properties": {
    "addr:full":"50 Los Ranchitos Rd San Rafael CA 94903",
    "addr:housenumber":"50",
    "addr:postcode":"94903",
    "addr:street":"Los Ranchitos Rd",
    "iso:country":"US",
    "sg:address":"50 Los Ranchitos Rd",
    "sg:city":"San Rafael",
    "sg:classifiers":[
        {
            "category":"Organizations",
            "subcategory":"Religious Organization",
            "type":"Services"
        }
    ],
    "sg:phone":"+1 415 479 4700",
    "sg:postcode":"94903",
    "sg:province":"CA",
    "sg:tags":[
        "church"
    ],
    "sg:website":"www.ccsr.com",
    "wof:name":"Christian Church Of San Rafael",
    "wof:placetype":"venue"
},
  "geometry": {"coordinates":[-122.534103,37.99204],"type":"Point"}
}