{
  "type": "Feature",
  "properties": {
    "addr:full":"442 Victoria Pl Claremont CA 91711",
    "addr:housenumber":"442",
    "addr:postcode":"91711",
    "addr:street":"Victoria Pl",
    "iso:country":"US",
    "sg:address":"442 Victoria Pl",
    "sg:city":"Claremont",
    "sg:classifiers":[
        {
            "category":"Building & Trades",
            "subcategory":"Plumbing",
            "type":"Services"
        }
    ],
    "sg:phone":"+1 909 447 6500",
    "sg:postcode":"91711",
    "sg:province":"CA",
    "sg:tags":[
        "plumber",
        "industrial",
        "contractors-commercial"
    ],
    "wof:name":"John Plumber",
    "wof:placetype":"venue"
},
  "geometry": {"coordinates":[-117.707778,34.088613],"type":"Point"}
}