{
  "type": "Feature",
  "properties": {
    "iso:country":"US",
    "sg:address":"10745 Gold Center Drive",
    "sg:city":"Gold River",
    "sg:classifiers":[
        {
            "category":"Travel",
            "subcategory":"Hotels & Motels",
            "type":"Entertainment"
        }
    ],
    "sg:phone":"+1 916 858 8680",
    "sg:postcode":"95670",
    "sg:province":"CA",
    "wof:name":"Wingate Inn",
    "wof:placetype":"venue"
},
  "geometry": {"coordinates":[-121.28621,38.589786],"type":"Point"}
}