{
  "type": "Feature",
  "properties": {
    "iso:country":"US",
    "sg:address":"925 Linden Ave",
    "sg:city":"South San Francisco",
    "sg:classifiers":[
        {
            "category":"Communications",
            "subcategory":"Newspaper",
            "type":"Services"
        }
    ],
    "sg:phone":"+1 650 952 4961",
    "sg:postcode":"94080",
    "sg:province":"CA",
    "sg:tags":[
        "print",
        "medium"
    ],
    "wof:name":"Mainland Newspaper Inc",
    "wof:placetype":"venue"
},
  "geometry": {"coordinates":[-122.40701900000001,37.662267],"type":"Point"}
}