{
  "type": "Feature",
  "properties": {
    "addr:full":"23740 Hawthorne Blvd Ste 104 Torrance CA 90505",
    "addr:housenumber":"23740",
    "addr:postcode":"90505",
    "addr:street":"Hawthorne Blvd Ste 104",
    "iso:country":"US",
    "sg:address":"23740 Hawthorne Blvd Ste 104",
    "sg:city":"Torrance",
    "sg:classifiers":[
        {
            "category":"Real Estate",
            "subcategory":"Real Estate Services",
            "type":"Services"
        }
    ],
    "sg:phone":"+1 310 378 6347",
    "sg:postcode":"90505",
    "sg:province":"CA",
    "sg:tags":[
        "home",
        "inspector"
    ],
    "wof:name":"Advanced Environmental Consultants",
    "wof:placetype":"venue"
},
  "geometry": {"coordinates":[-118.35057399999999,33.809769],"type":"Point"}
}