{
  "type": "Feature",
  "properties": {
    "iso:country":"US",
    "sg:address":"2944 E Anaheim St",
    "sg:city":"Long Beach",
    "sg:classifiers":[
        {
            "category":"Health Services",
            "subcategory":"Doctor",
            "type":"Services"
        }
    ],
    "sg:phone":"+1 562 599 5777",
    "sg:postcode":"90804",
    "sg:province":"CA",
    "wof:name":"Le Bao Q MD",
    "wof:placetype":"venue"
},
  "geometry": {"coordinates":[-118.156998,33.782501],"type":"Point"}
}