{
  "type": "Feature",
  "properties": {
    "iso:country":"US",
    "sg:address":"628 S Broadway",
    "sg:city":"Los Angeles",
    "sg:classifiers":[
        {
            "category":"Shopping",
            "subcategory":"Clothing, Apparel, & Fashions",
            "type":"Retail Goods"
        }
    ],
    "sg:phone":"+1 213 624 5489",
    "sg:postcode":"90014",
    "sg:province":"CA",
    "sg:tags":[
        "furnishing"
    ],
    "wof:name":"Saab Hafez",
    "wof:placetype":"venue"
},
  "geometry": {"coordinates":[-118.252992,34.045577],"type":"Point"}
}