{
  "type": "Feature",
  "properties": {
    "addr:full":"1645 Madrid St Salinas CA 93906",
    "addr:housenumber":"1645",
    "addr:postcode":"93906",
    "addr:street":"Madrid St",
    "iso:country":"US",
    "sg:address":"1645 Madrid St",
    "sg:city":"Salinas",
    "sg:classifiers":[
        {
            "category":"Building & Trades",
            "subcategory":"Plumbing",
            "type":"Services"
        }
    ],
    "sg:phone":"+1 831 442 9383",
    "sg:postcode":"93906",
    "sg:province":"CA",
    "sg:tags":[
        "contractor"
    ],
    "wof:name":"Arreola Air Conditioning Servi",
    "wof:placetype":"venue"
},
  "geometry": {"coordinates":[-121.658751,36.712868],"type":"Point"}
}