{
  "type": "Feature",
  "properties": {
    "iso:country":"US",
    "sg:address":"671 Via Alondra Ste 801",
    "sg:city":"Camarillo",
    "sg:classifiers":[
        {
            "category":"Home & Garden",
            "subcategory":"Kitchen Supply",
            "type":"Retail Goods"
        }
    ],
    "sg:phone":"+1 805 484 6666",
    "sg:postcode":"93012",
    "sg:province":"CA",
    "sg:tags":[
        "utensil",
        "cookware"
    ],
    "wof:name":"Century Unia Corp",
    "wof:placetype":"venue"
},
  "geometry": {"coordinates":[-119.025229,34.223792],"type":"Point"}
}