{
  "type": "Feature",
  "properties": {
    "addr:full":"5217 Venice Boulevard Los Angeles CA 90019",
    "addr:housenumber":"5217",
    "addr:postcode":"90019",
    "addr:street":"Venice Boulevard",
    "iso:country":"US",
    "sg:address":"5217 Venice Boulevard",
    "sg:city":"Los Angeles",
    "sg:classifiers":[
        {
            "category":"Building & Trades",
            "subcategory":"Construction",
            "type":"Services"
        }
    ],
    "sg:phone":"+1 323 938 3878",
    "sg:postcode":"90019",
    "sg:province":"CA",
    "sg:tags":[
        "interior",
        "design"
    ],
    "wof:name":"Santa Cruz Designs",
    "wof:placetype":"venue"
},
  "geometry": {"coordinates":[-118.354517,34.04464],"type":"Point"}
}