{
  "type": "Feature",
  "properties": {
    "iso:country":"US",
    "sg:address":"375 Huntington Dr Ste G",
    "sg:city":"San Marino",
    "sg:classifiers":[
        {
            "category":"Health Services",
            "subcategory":"Doctor",
            "type":"Services"
        }
    ],
    "sg:phone":"+1 626 441 4231",
    "sg:postcode":"91108",
    "sg:province":"CA",
    "wof:name":"Huntington Medical Foundation",
    "wof:placetype":"venue"
},
  "geometry": {"coordinates":[-118.134225,34.107475],"type":"Point"}
}