{
  "type": "Feature",
  "properties": {
    "addr:full":"191 Granite St Corona CA 92879",
    "addr:housenumber":"191",
    "addr:postcode":"92879",
    "addr:street":"Granite St",
    "iso:country":"US",
    "sg:address":"191 Granite St",
    "sg:city":"Corona",
    "sg:classifiers":[
        {
            "category":"Real Estate",
            "subcategory":"Real Estate Agent",
            "type":"Services"
        }
    ],
    "sg:phone":"+1 951 272 3550",
    "sg:postcode":"92879",
    "sg:province":"CA",
    "wof:name":"Eadington Co LLC",
    "wof:placetype":"venue"
},
  "geometry": {"coordinates":[-117.50205099999999,33.890501],"type":"Point"}
}