{
  "type": "Feature",
  "properties": {
    "addr:full":"8215 Corte Las Lenas San Diego CA 92129",
    "addr:housenumber":"8215",
    "addr:postcode":"92129",
    "addr:street":"Corte Las Lenas",
    "iso:country":"US",
    "sg:address":"8215 Corte Las Lenas",
    "sg:city":"San Diego",
    "sg:classifiers":[
        {
            "category":"Professional",
            "type":"Services"
        }
    ],
    "sg:phone":"+1 858 538 0745",
    "sg:postcode":"92129",
    "sg:province":"CA",
    "wof:name":"Outdoor Luxuries",
    "wof:placetype":"venue"
},
  "geometry": {"coordinates":[-117.146883,32.951303],"type":"Point"}
}