{
  "type": "Feature",
  "properties": {
    "iso:country":"US",
    "sg:address":"540 Martin Ave",
    "sg:city":"Santa Clara",
    "sg:classifiers":[
        {
            "category":"Manufacturing",
            "subcategory":"Rubber & Plastics",
            "type":"Manufacturing & Wholesale Goods"
        }
    ],
    "sg:phone":"+1 408 727 2593",
    "sg:postcode":"95050",
    "sg:province":"CA",
    "sg:tags":[
        "box",
        "transparent"
    ],
    "wof:name":"Palex Metal Inc",
    "wof:placetype":"venue"
},
  "geometry": {"coordinates":[-121.943264,37.366385],"type":"Point"}
}