{
  "type": "Feature",
  "properties": {
    "addr:full":"Graceful Transitions 3022 Filmore St San Francisco CA 94123",
    "addr:housenumber":"3022",
    "addr:postcode":"94123",
    "addr:street":"Filmore St",
    "iso:country":"US",
    "sg:address":"Graceful Transitions 3022 Filmore St",
    "sg:city":"San Francisco",
    "sg:classifiers":[
        {
            "category":"Health Services",
            "subcategory":"Clinic",
            "type":"Services"
        }
    ],
    "sg:phone":"+1 415 239 1087",
    "sg:postcode":"94123",
    "sg:province":"CA",
    "sg:tags":[
        "counseling",
        "mental"
    ],
    "sg:website":"www.roslynwhitney.com",
    "wof:name":"Roslyn Whitney, MS",
    "wof:placetype":"venue"
},
  "geometry": {"coordinates":[-122.435545,37.797335],"type":"Point"}
}