{
  "type": "Feature",
  "properties": {
    "addr:full":"1578 Hudson St Redwood City CA 94061",
    "addr:housenumber":"1578",
    "addr:postcode":"94061",
    "addr:street":"Hudson St",
    "iso:country":"US",
    "sg:address":"1578 Hudson St",
    "sg:city":"Redwood City",
    "sg:classifiers":[
        {
            "category":"Manufacturing",
            "subcategory":"Printing",
            "type":"Manufacturing & Wholesale Goods"
        }
    ],
    "sg:phone":"+1 650 368 7799",
    "sg:postcode":"94061",
    "sg:province":"CA",
    "sg:tags":[
        "bureau",
        "typesetting"
    ],
    "wof:name":"The Typemasters",
    "wof:placetype":"venue"
},
  "geometry": {"coordinates":[-122.224294,37.469493],"type":"Point"}
}