{
  "type": "Feature",
  "properties": {
    "iso:country":"US",
    "sg:address":"4676 Lakeview Ave",
    "sg:city":"Yorba Linda",
    "sg:classifiers":[
        {
            "category":"Health Services",
            "subcategory":"Health Practitioner",
            "type":"Services"
        }
    ],
    "sg:phone":"+1 714 779 6721",
    "sg:postcode":"92886",
    "sg:province":"CA",
    "sg:tags":[
        "psychotherapist"
    ],
    "wof:name":"Joyce E Alessi",
    "wof:placetype":"venue"
},
  "geometry": {"coordinates":[-117.81138,33.89178],"type":"Point"}
}