{
  "type": "Feature",
  "properties": {
    "addr:full":"328 Ingalls St Santa Cruz CA 95060",
    "addr:housenumber":"328",
    "addr:postcode":"95060",
    "addr:street":"Ingalls St",
    "iso:country":"US",
    "sg:address":"328 Ingalls St",
    "sg:city":"Santa Cruz",
    "sg:classifiers":[
        {
            "category":"Manufacturing",
            "subcategory":"Metals",
            "type":"Manufacturing & Wholesale Goods"
        }
    ],
    "sg:phone":"+1 831 427 3422",
    "sg:postcode":"95060",
    "sg:province":"CA",
    "sg:tags":[
        "ornamental",
        "work"
    ],
    "wof:name":"Freedom Forge",
    "wof:placetype":"venue"
},
  "geometry": {"coordinates":[-122.048633,36.958547],"type":"Point"}
}