{
  "type": "Feature",
  "properties": {
    "iso:country":"US",
    "sg:address":"88 4th St",
    "sg:city":"San Francisco",
    "sg:classifiers":[
        {
            "category":"Education",
            "subcategory":"University",
            "type":"Public Place"
        }
    ],
    "sg:phone":"+1 415 267 6500",
    "sg:postcode":"94101",
    "sg:province":"CA",
    "sg:tags":[
        "college"
    ],
    "sg:website":"www.ccsf.edu",
    "wof:name":"City College of San Francisco - Downtown Campus",
    "wof:placetype":"venue"
},
  "geometry": {"coordinates":[-122.40463,37.784613],"type":"Point"}
}