{
  "type": "Feature",
  "properties": {
    "addr:full":"7650 Newcastle Rd Stockton CA 95215",
    "addr:housenumber":"7650",
    "addr:postcode":"95215",
    "addr:street":"Newcastle Rd",
    "iso:country":"US",
    "sg:address":"7650 Newcastle Rd",
    "sg:city":"Stockton",
    "sg:classifiers":[
        {
            "category":"Wholesale",
            "subcategory":"Electrical",
            "type":"Manufacturing & Wholesale Goods"
        }
    ],
    "sg:phone":"+1 209 946 0721",
    "sg:postcode":"95215",
    "sg:province":"CA",
    "sg:tags":[
        "assembler",
        "electronic",
        "parts"
    ],
    "wof:name":"Merit Corp",
    "wof:placetype":"venue"
},
  "geometry": {"coordinates":[-121.20199,37.892361],"type":"Point"}
}