{
  "type": "Feature",
  "properties": {
    "addr:full":"523 Cypress Ave Millbrae CA 94030",
    "addr:housenumber":"523",
    "addr:postcode":"94030",
    "addr:street":"Cypress Ave",
    "iso:country":"US",
    "sg:address":"523 Cypress Ave",
    "sg:city":"Millbrae",
    "sg:classifiers":[
        {
            "category":"Real Estate",
            "subcategory":"Real Estate Agent",
            "type":"Services"
        }
    ],
    "sg:phone":"+1 650 873 9490",
    "sg:postcode":"94030",
    "sg:province":"CA",
    "wof:name":"Jack Ditty / Prudential Realty",
    "wof:placetype":"venue"
},
  "geometry": {"coordinates":[-122.409541,37.612501],"type":"Point"}
}