{
  "type": "Feature",
  "properties": {
    "addr:full":"2129 Myrtle St Oakland CA 94607",
    "addr:housenumber":"2129",
    "addr:postcode":"94607",
    "addr:street":"Myrtle St",
    "iso:country":"US",
    "sg:address":"2129 Myrtle St",
    "sg:city":"Oakland",
    "sg:classifiers":[
        {
            "category":"Freight",
            "type":"Transportation"
        }
    ],
    "sg:phone":"+1 510 465 4727",
    "sg:postcode":"94607",
    "sg:province":"CA",
    "sg:tags":[
        "hauling",
        "trucking"
    ],
    "wof:name":"Quick Hauling & Yard Work",
    "wof:placetype":"venue"
},
  "geometry": {"coordinates":[-122.27994,37.814324],"type":"Point"}
}