{
  "type": "Feature",
  "properties": {
    "addr:full":"1412 4th St Santa Monica CA 90401",
    "addr:housenumber":"1412",
    "addr:postcode":"90401",
    "addr:street":"4Th St",
    "iso:country":"US",
    "sg:address":"1412 4th St",
    "sg:city":"Santa Monica",
    "sg:classifiers":[
        {
            "category":"Wholesale",
            "subcategory":"Jewelry",
            "type":"Manufacturing & Wholesale Goods"
        }
    ],
    "sg:phone":"+1 310 393 6864",
    "sg:postcode":"90401",
    "sg:province":"CA",
    "sg:tags":[
        "jeweler"
    ],
    "wof:name":"Nobel Gems Inc",
    "wof:placetype":"venue"
},
  "geometry": {"coordinates":[-118.49380499999999,34.015192],"type":"Point"}
}