{
  "type": "Feature",
  "properties": {
    "iso:country":"US",
    "sg:address":"79305 US Hwy 111",
    "sg:city":"La Quinta",
    "sg:classifiers":[
        {
            "category":"Personal",
            "subcategory":"Beauty Salon",
            "type":"Services"
        }
    ],
    "sg:phone":"+1 760 771 2683",
    "sg:postcode":"92253",
    "sg:province":"CA",
    "wof:name":"Hair Masters",
    "wof:placetype":"venue"
},
  "geometry": {"coordinates":[-116.278918,33.707315],"type":"Point"}
}