{
  "type": "Feature",
  "properties": {
    "iso:country":"US",
    "sg:address":"24711 Kim Cir",
    "sg:city":"Laguna Hills",
    "sg:classifiers":[
        {
            "category":"Banks & Credit Unions",
            "subcategory":"Bank",
            "type":"Services"
        }
    ],
    "sg:phone":"+1 949 297 3840",
    "sg:postcode":"92653",
    "sg:province":"CA",
    "wof:name":"Sterling Bank",
    "wof:placetype":"venue"
},
  "geometry": {"coordinates":[-117.69765099999999,33.604046],"type":"Point"}
}