{
  "type": "Feature",
  "properties": {
    "addr:full":"142 S San Vicente Blvd Los Angeles CA 90048",
    "addr:housenumber":"142",
    "addr:postcode":"90048",
    "addr:street":"S San Vicente Blvd",
    "iso:country":"US",
    "sg:address":"142 S San Vicente Blvd",
    "sg:city":"Los Angeles",
    "sg:classifiers":[
        {
            "category":"Home & Garden",
            "subcategory":"Home Furnishings",
            "type":"Retail Goods"
        }
    ],
    "sg:phone":"+1 310 652 1380",
    "sg:postcode":"90048",
    "sg:province":"CA",
    "sg:tags":[
        "linen",
        "decor"
    ],
    "wof:name":"Bed Bath & Beyond",
    "wof:placetype":"venue"
},
  "geometry": {"coordinates":[-118.378998,34.075901],"type":"Point"}
}