{
  "type": "Feature",
  "properties": {
    "addr:full":"2301 E 28th St Long Beach CA 90755",
    "addr:housenumber":"2301",
    "addr:postcode":"90755",
    "addr:street":"E 28Th St",
    "iso:country":"US",
    "sg:address":"2301 E 28th St",
    "sg:city":"Long Beach",
    "sg:classifiers":[
        {
            "category":"Professional",
            "subcategory":"Engineering",
            "type":"Services"
        }
    ],
    "sg:phone":"+1 562 424 2929",
    "sg:postcode":"90755",
    "sg:province":"CA",
    "wof:name":"Cem Group Inc",
    "wof:placetype":"venue"
},
  "geometry": {"coordinates":[-118.163246,33.808022],"type":"Point"}
}