{
  "type": "Feature",
  "properties": {
    "iso:country":"US",
    "sg:address":"922 E Calwa Ave",
    "sg:city":"Fresno",
    "sg:classifiers":[
        {
            "category":"Retail",
            "subcategory":"Repair Shop",
            "type":"Services"
        }
    ],
    "sg:phone":"+1 559 486 5397",
    "sg:postcode":"93706",
    "sg:province":"CA",
    "sg:tags":[
        "lock",
        "locksmith"
    ],
    "wof:name":"J & B Mobile Locksmithing",
    "wof:placetype":"venue"
},
  "geometry": {"coordinates":[-119.797741,36.704936],"type":"Point"}
}