{
  "type": "Feature",
  "properties": {
    "iso:country":"US",
    "sg:address":"1930 W 120th Street",
    "sg:city":"Los Angeles",
    "sg:classifiers":[
        {
            "category":"Sports & Exercise",
            "subcategory":"Golf",
            "type":"Entertainment"
        }
    ],
    "sg:phone":"+1 323 756 6975",
    "sg:postcode":"90047",
    "sg:province":"CA",
    "wof:name":"Los Angeles County of",
    "wof:placetype":"venue"
},
  "geometry": {"coordinates":[-118.30849499999999,33.924183],"type":"Point"}
}