{
  "type": "Feature",
  "properties": {
    "addr:full":"12 E Gabilan St Ste 6 Salinas CA 93901",
    "addr:housenumber":"12",
    "addr:postcode":"93901",
    "addr:street":"E Gabilan St Ste 6",
    "iso:country":"US",
    "sg:address":"12 E Gabilan St Ste 6",
    "sg:city":"Salinas",
    "sg:classifiers":[
        {
            "category":"Shopping",
            "subcategory":"Department Store",
            "type":"Retail Goods"
        }
    ],
    "sg:phone":"+1 831 422 3003",
    "sg:postcode":"93901",
    "sg:province":"CA",
    "sg:website":"http://nordstrom.com/",
    "wof:name":"Nordstrom",
    "wof:placetype":"venue"
},
  "geometry": {"coordinates":[-121.654678,36.67572],"type":"Point"}
}