{
  "type": "Feature",
  "properties": {
    "addr:full":"20768 Lake Forest Dr Lake Forest CA 92630",
    "addr:housenumber":"20768",
    "addr:postcode":"92630",
    "addr:street":"Lake Forest Dr",
    "iso:country":"US",
    "sg:address":"20768 Lake Forest Dr",
    "sg:city":"Lake Forest",
    "sg:classifiers":[
        {
            "category":"Travel",
            "subcategory":"Hotels & Motels",
            "type":"Entertainment"
        }
    ],
    "sg:phone":"+1 949 900 1288",
    "sg:postcode":"92630",
    "sg:province":"CA",
    "sg:website":"www.prominencehotel.com",
    "wof:name":"The Prominence Hotel and Suites",
    "wof:placetype":"venue"
},
  "geometry": {"coordinates":[-117.66787600000001,33.660631],"type":"Point"}
}