{
  "type": "Feature",
  "properties": {
    "iso:country":"US",
    "sg:address":"2196 Rustic Park Ct",
    "sg:city":"Thousand Oaks",
    "sg:classifiers":[
        {
            "category":"Home & Garden",
            "subcategory":"Building Materials",
            "type":"Retail Goods"
        }
    ],
    "sg:phone":"+1 805 485 8586",
    "sg:postcode":"91362",
    "sg:province":"CA",
    "sg:tags":[
        "door"
    ],
    "wof:name":"American Sliding Door Repair",
    "wof:placetype":"venue"
},
  "geometry": {"coordinates":[-118.835261,34.210334],"type":"Point"}
}