{
  "type": "Feature",
  "properties": {
    "addr:full":"400 Stafford St Folsom CA 95630",
    "addr:housenumber":"400",
    "addr:postcode":"95630",
    "addr:street":"Stafford St",
    "iso:country":"US",
    "sg:address":"400 Stafford St",
    "sg:city":"Folsom",
    "sg:classifiers":[
        {
            "category":"Social Services",
            "subcategory":"Child Care",
            "type":"Services"
        },
        {
            "category":"Education",
            "subcategory":"Preschool",
            "type":"Public Place"
        },
        {
            "category":"Education",
            "subcategory":"School",
            "type":"Public Place"
        }
    ],
    "sg:phone":"+1 916 988 9633",
    "sg:postcode":"95630",
    "sg:province":"CA",
    "sg:tags":[
        "kindergarten",
        "nursery",
        "day"
    ],
    "sg:website":"http://www.actiondaylearningcenter.com",
    "wof:name":"Action Day Learning Center",
    "wof:placetype":"venue"
},
  "geometry": {"coordinates":[-121.16693100000001,38.680771],"type":"Point"}
}