{
  "type": "Feature",
  "properties": {
    "addr:full":"155 Valencia Street San Francisco CA 94103",
    "addr:housenumber":"155",
    "addr:postcode":"94103",
    "addr:street":"Valencia Street",
    "iso:country":"US",
    "sg:address":"155 Valencia Street",
    "sg:city":"San Francisco",
    "sg:classifiers":[
        {
            "category":"Health Services",
            "subcategory":"Chiropractor",
            "type":"Services"
        }
    ],
    "sg:phone":"+1 415 575 7200",
    "sg:postcode":"94103",
    "sg:province":"CA",
    "sg:website":"www.drbiegel.com",
    "wof:name":"Advanced Chiropractic Center",
    "wof:placetype":"venue"
},
  "geometry": {"coordinates":[-122.422352,37.770935],"type":"Point"}
}