{
  "type": "Feature",
  "properties": {
    "addr:full":"177 Post St San Francisco CA 94108",
    "addr:housenumber":"177",
    "addr:postcode":"94108",
    "addr:street":"Post St",
    "iso:country":"US",
    "sg:address":"177 Post St",
    "sg:city":"San Francisco",
    "sg:classifiers":[
        {
            "category":"Professional",
            "subcategory":"Lawyer & Legal Services",
            "type":"Services"
        }
    ],
    "sg:phone":"+1 415 398 3900",
    "sg:postcode":"94108",
    "sg:province":"CA",
    "sg:tags":[
        "attorney"
    ],
    "wof:name":"Cohen David J Law Office",
    "wof:placetype":"venue"
},
  "geometry": {"coordinates":[-122.404753,37.788489],"type":"Point"}
}