{
  "type": "Feature",
  "properties": {
    "iso:country":"US",
    "sg:address":"6819 Clark Rd",
    "sg:city":"Paradise",
    "sg:classifiers":[
        {
            "category":"Home & Garden",
            "subcategory":"Home Furnishings",
            "type":"Retail Goods"
        }
    ],
    "sg:phone":"+1 530 872 9694",
    "sg:postcode":"95969",
    "sg:province":"CA",
    "sg:tags":[
        "residential",
        "lighting",
        "mfg"
    ],
    "wof:name":"Lightguy",
    "wof:placetype":"venue"
},
  "geometry": {"coordinates":[-121.58784300000001,39.783142],"type":"Point"}
}