{
  "type": "Feature",
  "properties": {
    "iso:country":"US",
    "sg:address":"232 Bernard St",
    "sg:city":"Bakersfield",
    "sg:classifiers":[
        {
            "category":"Real Estate",
            "subcategory":"Real Estate Agent",
            "type":"Services"
        }
    ],
    "sg:phone":"+1 661 321 0890",
    "sg:postcode":"93305",
    "sg:province":"CA",
    "wof:name":"Choice Property Management",
    "wof:placetype":"venue"
},
  "geometry": {"coordinates":[-118.998442,35.390317],"type":"Point"}
}