{
  "type": "Feature",
  "properties": {
    "iso:country":"US",
    "sg:address":"1800 Argyle Ave",
    "sg:city":"Los Angeles",
    "sg:classifiers":[
        {
            "category":"Professional",
            "type":"Services"
        }
    ],
    "sg:phone":"+1 323 785 4140",
    "sg:postcode":"90028",
    "sg:province":"CA",
    "sg:tags":[
        "establishment"
    ],
    "wof:name":"Sky Marketing",
    "wof:placetype":"venue"
},
  "geometry": {"coordinates":[-118.325254,34.104321],"type":"Point"}
}