{
  "type": "Feature",
  "properties": {
    "iso:country":"US",
    "sg:address":"3910 Broad St",
    "sg:city":"San Luis Obispo",
    "sg:classifiers":[
        {
            "category":"Real Estate",
            "subcategory":"Real Estate Agent",
            "type":"Services"
        }
    ],
    "sg:phone":"+1 805 544 1060",
    "sg:postcode":"93401",
    "sg:province":"CA",
    "wof:name":"Remax Seven Cities Realty",
    "wof:placetype":"venue"
},
  "geometry": {"coordinates":[-120.643697,35.249599],"type":"Point"}
}