{
  "type": "Feature",
  "properties": {
    "addr:full":"487 Dundee Ave Milpitas CA 95035",
    "addr:housenumber":"487",
    "addr:postcode":"95035",
    "addr:street":"Dundee Ave",
    "iso:country":"US",
    "sg:address":"487 Dundee Ave",
    "sg:city":"Milpitas",
    "sg:classifiers":[
        {
            "category":"Professional",
            "type":"Services"
        }
    ],
    "sg:phone":"+1 408 935 8227",
    "sg:postcode":"95035",
    "sg:province":"CA",
    "wof:name":"Islandworks Inc",
    "wof:placetype":"venue"
},
  "geometry": {"coordinates":[-121.900622,37.43921],"type":"Point"}
}