{
  "type": "Feature",
  "properties": {
    "addr:full":"1290 San Pablo Ave Rodeo CA 94572",
    "addr:housenumber":"1290",
    "addr:postcode":"94572",
    "addr:street":"San Pablo Ave",
    "iso:country":"US",
    "sg:address":"1290 San Pablo Ave",
    "sg:city":"Rodeo",
    "sg:classifiers":[
        {
            "category":"Professional",
            "type":"Services"
        }
    ],
    "sg:phone":"+1 510 799 9192",
    "sg:postcode":"94572",
    "sg:province":"CA",
    "wof:name":"Newtron Inc",
    "wof:placetype":"venue"
},
  "geometry": {"coordinates":[-122.25021599999999,38.048109],"type":"Point"}
}