{
  "type": "Feature",
  "properties": {
    "iso:country":"US",
    "sg:address":"1415 E Colorado St",
    "sg:city":"Glendale",
    "sg:classifiers":[
        {
            "category":"Health Services",
            "subcategory":"Clinic",
            "type":"Services"
        }
    ],
    "sg:phone":"+1 818 244 5112",
    "sg:postcode":"91205",
    "sg:province":"CA",
    "sg:tags":[
        "home"
    ],
    "wof:name":"USA Home Health Inc",
    "wof:placetype":"venue"
},
  "geometry": {"coordinates":[-118.23329200000001,34.14285],"type":"Point"}
}