{
  "type": "Feature",
  "properties": {
    "iso:country":"US",
    "sg:address":"11030 Arrow Rte",
    "sg:city":"Rancho Cucamonga",
    "sg:classifiers":[
        {
            "category":"Banks & Credit Unions",
            "subcategory":"Investment Brokerage",
            "type":"Services"
        }
    ],
    "sg:phone":"+1 909 483 1125",
    "sg:postcode":"91730",
    "sg:province":"CA",
    "sg:tags":[
        "consultant",
        "planning",
        "financial"
    ],
    "wof:name":"Rick Bell",
    "wof:placetype":"venue"
},
  "geometry": {"coordinates":[-117.56093199999999,34.099166],"type":"Point"}
}