{
  "type": "Feature",
  "properties": {
    "addr:full":"2684 Armstrong Ave Clovis CA 93611",
    "addr:housenumber":"2684",
    "addr:postcode":"93611",
    "addr:street":"Armstrong Ave",
    "iso:country":"US",
    "sg:address":"2684 Armstrong Ave",
    "sg:city":"Clovis",
    "sg:classifiers":[
        {
            "category":"Banks & Credit Unions",
            "subcategory":"Bank",
            "type":"Services"
        }
    ],
    "sg:phone":"+1 559 346 1001",
    "sg:postcode":"93611",
    "sg:province":"CA",
    "sg:tags":[
        "loan",
        "real estate"
    ],
    "wof:name":"Century Mortgage Lenders",
    "wof:placetype":"venue"
},
  "geometry": {"coordinates":[-119.673104,36.801514],"type":"Point"}
}