{
  "type": "Feature",
  "properties": {
    "iso:country":"US",
    "sg:address":"20271 SW Acacia St",
    "sg:city":"Newport Beach",
    "sg:classifiers":[
        {
            "category":"Professional",
            "subcategory":"Lawyer & Legal Services",
            "type":"Services"
        }
    ],
    "sg:phone":"+1 949 757 0949",
    "sg:postcode":"92660",
    "sg:province":"CA",
    "sg:tags":[
        "attorney"
    ],
    "wof:name":"David M Zeligs Law Office",
    "wof:placetype":"venue"
},
  "geometry": {"coordinates":[-117.880118,33.657302],"type":"Point"}
}