{
  "type": "Feature",
  "properties": {
    "addr:full":"1474 Berger Dr San Jose CA 95112",
    "addr:housenumber":"1474",
    "addr:postcode":"95112",
    "addr:street":"Berger Dr",
    "iso:country":"US",
    "sg:address":"1474 Berger Dr",
    "sg:city":"San Jose",
    "sg:classifiers":[
        {
            "category":"Building & Trades",
            "subcategory":"Landscaping Services",
            "type":"Services"
        }
    ],
    "sg:phone":"+1 408 288 2942",
    "sg:postcode":"95112",
    "sg:province":"CA",
    "sg:tags":[
        "tree"
    ],
    "wof:name":"Arbortek Tree Service",
    "wof:placetype":"venue"
},
  "geometry": {"coordinates":[-121.896843,37.370318],"type":"Point"}
}