{
  "type": "Feature",
  "properties": {
    "iso:country":"US",
    "sg:address":"919 S Grand Ave",
    "sg:city":"Los Angeles",
    "sg:classifiers":[
        {
            "category":"Professional",
            "subcategory":"Lawyer & Legal Services",
            "type":"Services"
        }
    ],
    "sg:phone":"+1 213 688 8872",
    "sg:postcode":"90015",
    "sg:province":"CA",
    "sg:tags":[
        "attorney"
    ],
    "wof:name":"Bonaparte & Miyamoto",
    "wof:placetype":"venue"
},
  "geometry": {"coordinates":[-118.260477,34.043298],"type":"Point"}
}