{
  "type": "Feature",
  "properties": {
    "addr:full":"9608 N Columbus Ave North Hills CA 91343",
    "addr:housenumber":"9608",
    "addr:postcode":"91343",
    "addr:street":"N Columbus Ave",
    "iso:country":"US",
    "sg:address":"9608 N Columbus Ave",
    "sg:city":"North Hills",
    "sg:classifiers":[
        {
            "category":"Organizations",
            "subcategory":"Membership Organization",
            "type":"Services"
        }
    ],
    "sg:phone":"+1 818 893 3642",
    "sg:postcode":"91343",
    "sg:province":"CA",
    "sg:tags":[
        "durable",
        "good"
    ],
    "wof:name":"California Gold Gathering",
    "wof:placetype":"venue"
},
  "geometry": {"coordinates":[-118.465243,34.244416],"type":"Point"}
}