{
  "type": "Feature",
  "properties": {
    "iso:country":"US",
    "sg:address":"7360 Auburn Blvd",
    "sg:city":"Citrus Heights",
    "sg:classifiers":[
        {
            "category":"Shopping",
            "type":"Retail Goods"
        }
    ],
    "sg:phone":"+1 916 723 1367",
    "sg:postcode":"95610",
    "sg:province":"CA",
    "sg:tags":[
        "pet",
        "shop",
        "merchandise"
    ],
    "wof:name":"Kasch's Kritters",
    "wof:placetype":"venue"
},
  "geometry": {"coordinates":[-121.290255,38.698254],"type":"Point"}
}