{
  "type": "Feature",
  "properties": {
    "addr:full":"38727 Tierra Subida Ave Palmdale CA 93551",
    "addr:housenumber":"38727",
    "addr:postcode":"ca 93551",
    "addr:street":"Tierra Subida Ave",
    "iso:country":"US",
    "sg:address":"38727 Tierra Subida Ave",
    "sg:city":"Palmdale",
    "sg:classifiers":[
        {
            "category":"Building & Trades",
            "subcategory":"Construction",
            "type":"Services"
        }
    ],
    "sg:phone":"+1 661 274 8708",
    "sg:postcode":"93551",
    "sg:province":"CA",
    "sg:tags":[
        "contractor"
    ],
    "wof:name":"H E I Construction",
    "wof:placetype":"venue"
},
  "geometry": {"coordinates":[-118.147498,34.584025],"type":"Point"}
}