{
  "type": "Feature",
  "properties": {
    "addr:full":"9955 Muirlands Blvd Irvine CA 92618",
    "addr:housenumber":"9955",
    "addr:postcode":"92618",
    "addr:street":"Muirlands Blvd",
    "iso:country":"US",
    "sg:address":"9955 Muirlands Blvd",
    "sg:city":"Irvine",
    "sg:classifiers":[
        {
            "category":"Building & Trades",
            "subcategory":"Construction",
            "type":"Services"
        }
    ],
    "sg:phone":"+1 949 770 5094",
    "sg:postcode":"92618",
    "sg:province":"CA",
    "sg:tags":[
        "contractor"
    ],
    "sg:website":"www.verticalconstruction.com",
    "wof:name":"Vertical Construction",
    "wof:placetype":"venue"
},
  "geometry": {"coordinates":[-117.716916,33.64058],"type":"Point"}
}