{
  "type": "Feature",
  "properties": {
    "addr:full":"16165 Monterey St Morgan Hill CA 95037",
    "addr:housenumber":"16165",
    "addr:postcode":"95037",
    "addr:street":"Monterey St",
    "iso:country":"US",
    "sg:address":"16165 Monterey St",
    "sg:city":"Morgan Hill",
    "sg:classifiers":[
        {
            "category":"Shopping",
            "subcategory":"Computers & Home Electronics",
            "type":"Retail Goods"
        }
    ],
    "sg:phone":"+1 408 776 1616",
    "sg:postcode":"95037",
    "sg:province":"CA",
    "sg:tags":[
        "publishing"
    ],
    "sg:website":"www.electropub.com",
    "wof:name":"Electro Publishing",
    "wof:placetype":"venue"
},
  "geometry": {"coordinates":[-121.64373500000001,37.113927],"type":"Point"}
}