{
  "type": "Feature",
  "properties": {
    "iso:country":"US",
    "sg:address":"221 Ave I",
    "sg:city":"Redondo Beach",
    "sg:classifiers":[
        {
            "category":"Professional",
            "subcategory":"Lawyer & Legal Services",
            "type":"Services"
        }
    ],
    "sg:phone":"+1 310 540 1212",
    "sg:postcode":"90277",
    "sg:province":"CA",
    "sg:tags":[
        "attorney"
    ],
    "wof:name":"Randall C Kimose Law Offices",
    "wof:placetype":"venue"
},
  "geometry": {"coordinates":[-118.38685,33.819181],"type":"Point"}
}