{
  "type": "Feature",
  "properties": {
    "addr:full":"1085 Tasman Dr Spc 109 Sunnyvale CA 94089",
    "addr:housenumber":"1085;109",
    "addr:postcode":"94089",
    "addr:street":"Tasman Dr",
    "iso:country":"US",
    "sg:address":"1085 Tasman Dr Spc 109",
    "sg:city":"Sunnyvale",
    "sg:phone":"+1 408 541 1889",
    "sg:postcode":"94089",
    "sg:province":"CA",
    "wof:name":"Hair Beautiful",
    "wof:placetype":"venue"
},
  "geometry": {"coordinates":[-121.996466,37.403502],"type":"Point"}
}