{
  "type": "Feature",
  "properties": {
    "iso:country":"US",
    "sg:address":"1135 Santee St",
    "sg:city":"Los Angeles",
    "sg:classifiers":[
        {
            "category":"Wholesale",
            "subcategory":"Apparel",
            "type":"Manufacturing & Wholesale Goods"
        }
    ],
    "sg:phone":"+1 213 748 9228",
    "sg:postcode":"90015",
    "sg:province":"CA",
    "wof:name":"Artesia",
    "wof:placetype":"venue"
},
  "geometry": {"coordinates":[-118.257046,34.036848],"type":"Point"}
}