{
  "type": "Feature",
  "properties": {
    "addr:full":"312 W Brokaw Rd Santa Clara CA 95050",
    "addr:housenumber":"312",
    "addr:postcode":"95050",
    "addr:street":"W Brokaw Rd",
    "iso:country":"US",
    "sg:address":"312 W Brokaw Rd",
    "sg:city":"Santa Clara",
    "sg:classifiers":[
        {
            "category":"Organizations",
            "subcategory":"Political Organization",
            "type":"Services"
        }
    ],
    "sg:phone":"+1 408 748 1964",
    "sg:postcode":"95050",
    "sg:province":"CA",
    "wof:name":"Sally Lieber For Assembly",
    "wof:placetype":"venue"
},
  "geometry": {"coordinates":[-121.93340999999999,37.358162],"type":"Point"}
}