{
  "type": "Feature",
  "properties": {
    "iso:country":"US",
    "sg:address":"924 W Alameda Ave",
    "sg:city":"Burbank",
    "sg:classifiers":[
        {
            "category":"Health Services",
            "subcategory":"Chiropractor",
            "type":"Services"
        }
    ],
    "sg:phone":"+1 818 842 7700",
    "sg:postcode":"91506",
    "sg:province":"CA",
    "wof:name":"Essential Health Care",
    "wof:placetype":"venue"
},
  "geometry": {"coordinates":[-118.31468099999999,34.162652],"type":"Point"}
}