{
  "type": "Feature",
  "properties": {
    "addr:full":"6072 Cam Real Riverside CA 92509",
    "addr:housenumber":"6072",
    "addr:postcode":"92509",
    "addr:street":"Cam Real",
    "iso:country":"US",
    "sg:address":"6072 Cam Real",
    "sg:city":"Riverside",
    "sg:classifiers":[
        {
            "category":"Autos & Motor Vehicles",
            "subcategory":"Auto Supplies",
            "type":"Retail Goods"
        }
    ],
    "sg:phone":"+1 951 685 1000",
    "sg:postcode":"92509",
    "sg:province":"CA",
    "sg:tags":[
        "tire"
    ],
    "wof:name":"Scher Certified Auto Ctr",
    "wof:placetype":"venue"
},
  "geometry": {"coordinates":[-117.45120199999999,33.977862],"type":"Point"}
}