{
  "type": "Feature",
  "properties": {
    "addr:full":"136 Sutherland Dr Auburn CA 95603",
    "addr:housenumber":"136",
    "addr:postcode":"ca 95603",
    "addr:street":"Sutherland Dr",
    "iso:country":"US",
    "sg:address":"136 Sutherland Dr",
    "sg:city":"Auburn",
    "sg:classifiers":[
        {
            "category":"Retail",
            "subcategory":"Auto Repair",
            "type":"Services"
        }
    ],
    "sg:phone":"+1 530 889 1223",
    "sg:postcode":"95603",
    "sg:province":"CA",
    "sg:website":"http://ezlocal.com/CA/Auburn/Auto-Repair-Shop/41247",
    "wof:name":"Automotive Repair Center",
    "wof:placetype":"venue"
},
  "geometry": {"coordinates":[-121.06223900000001,38.918616],"type":"Point"}
}