{
  "type": "Feature",
  "properties": {
    "addr:full":"8383 Wilshire Boulevard Beverly Hills CA 90211",
    "addr:housenumber":"8383",
    "addr:postcode":"90211",
    "addr:street":"Wilshire Boulevard",
    "iso:country":"US",
    "sg:address":"8383 Wilshire Boulevard",
    "sg:city":"Beverly Hills",
    "sg:classifiers":[
        {
            "category":"Banks & Credit Unions",
            "subcategory":"Investment Brokerage",
            "type":"Services"
        }
    ],
    "sg:phone":"+1 323 852 9300",
    "sg:postcode":"90211",
    "sg:province":"CA",
    "sg:tags":[
        "investing"
    ],
    "wof:name":"Crane Asset Management",
    "wof:placetype":"venue"
},
  "geometry": {"coordinates":[-118.373908,34.064667],"type":"Point"}
}