{
  "type": "Feature",
  "properties": {
    "iso:country":"US",
    "sg:address":"20621 Gelman Dr",
    "sg:city":"Riverside",
    "sg:classifiers":[
        {
            "category":"Freight",
            "type":"Transportation"
        }
    ],
    "sg:phone":"+1 951 653 3334",
    "sg:postcode":"92508",
    "sg:province":"CA",
    "sg:tags":[
        "trucking"
    ],
    "wof:name":"R+D Payton Trucking",
    "wof:placetype":"venue"
},
  "geometry": {"coordinates":[-117.301243,33.898275],"type":"Point"}
}