{
  "type": "Feature",
  "properties": {
    "addr:full":"21153 Newport Coast Dr Newport Coast CA 92657",
    "addr:housenumber":"21153",
    "addr:postcode":"92657",
    "addr:street":"Newport Coast Dr",
    "iso:country":"US",
    "sg:address":"21153 Newport Coast Dr",
    "sg:city":"Newport Coast",
    "sg:classifiers":[
        {
            "category":"Personal",
            "subcategory":"Day Spa",
            "type":"Services"
        },
        {
            "category":"Personal",
            "subcategory":"Nail Salon",
            "type":"Services"
        }
    ],
    "sg:phone":"+1 949 644 4250",
    "sg:postcode":"92657",
    "sg:province":"CA",
    "sg:website":"www.happynails.com",
    "wof:name":"Happy Nails & Spa",
    "wof:placetype":"venue"
},
  "geometry": {"coordinates":[-117.826222,33.607811],"type":"Point"}
}