{
  "type": "Feature",
  "properties": {
    "addr:full":"7860 Church St Gilroy CA 95020",
    "addr:housenumber":"7860",
    "addr:postcode":"95020",
    "addr:street":"Church St",
    "iso:country":"US",
    "sg:address":"7860 Church St",
    "sg:city":"Gilroy",
    "sg:classifiers":[
        {
            "category":"Real Estate",
            "subcategory":"Real Estate Agent",
            "type":"Services"
        }
    ],
    "sg:phone":"+1 408 842 0052",
    "sg:postcode":"95020",
    "sg:province":"CA",
    "wof:name":"Pacific Equity Mortgage & Real",
    "wof:placetype":"venue"
},
  "geometry": {"coordinates":[-121.57422800000001,37.013045],"type":"Point"}
}