{
  "type": "Feature",
  "properties": {
    "addr:full":"2295 Davis Ct Hayward CA 94545",
    "addr:housenumber":"2295",
    "addr:postcode":"94545",
    "addr:street":"Davis Ct",
    "iso:country":"US",
    "sg:address":"2295 Davis Ct",
    "sg:city":"Hayward",
    "sg:classifiers":[
        {
            "category":"Professional",
            "type":"Services"
        }
    ],
    "sg:phone":"+1 510 785 4700",
    "sg:postcode":"94545",
    "sg:province":"CA",
    "wof:name":"Narinder Kaur",
    "wof:placetype":"venue"
},
  "geometry": {"coordinates":[-122.13184,37.646844],"type":"Point"}
}