{
  "type": "Feature",
  "properties": {
    "addr:full":"26990 Co Rd 95A Davis CA 95616",
    "addr:housenumber":"26990;95a",
    "addr:postcode":"95616",
    "addr:street":"Co Rd",
    "iso:country":"US",
    "sg:address":"26990 Co Rd 95A",
    "sg:city":"Davis",
    "sg:classifiers":[
        {
            "category":"Home & Garden",
            "subcategory":"Garden Supply",
            "type":"Retail Goods"
        }
    ],
    "sg:phone":"+1 530 756 8355",
    "sg:postcode":"95616",
    "sg:province":"CA",
    "sg:tags":[
        "nurseryman"
    ],
    "wof:name":"Three Palms Nursery",
    "wof:placetype":"venue"
},
  "geometry": {"coordinates":[-121.852144,38.539334],"type":"Point"}
}