{
  "type": "Feature",
  "properties": {
    "addr:full":"14481 Edwards Street Westminster CA 92683",
    "addr:housenumber":"14481",
    "addr:postcode":"92683",
    "addr:street":"Edwards Street",
    "iso:country":"US",
    "sg:address":"14481 Edwards Street",
    "sg:city":"Westminster",
    "sg:classifiers":[
        {
            "category":"Shopping",
            "subcategory":"Antiques",
            "type":"Retail Goods"
        }
    ],
    "sg:phone":"+1 714 895 5222",
    "sg:postcode":"92683",
    "sg:province":"CA",
    "wof:name":"Country Cottage Antiques",
    "wof:placetype":"venue"
},
  "geometry": {"coordinates":[-118.015962,33.752444],"type":"Point"}
}