{
  "type": "Feature",
  "properties": {
    "addr:full":"141 North St Healdsburg CA 95448",
    "addr:housenumber":"141",
    "addr:postcode":"95448",
    "addr:street":"North St",
    "iso:country":"US",
    "sg:address":"141 North St",
    "sg:city":"Healdsburg",
    "sg:classifiers":[
        {
            "category":"Professional",
            "subcategory":"Lawyer & Legal Services",
            "type":"Services"
        }
    ],
    "sg:phone":"+1 707 431 0576",
    "sg:postcode":"95448",
    "sg:province":"CA",
    "sg:tags":[
        "attorney"
    ],
    "wof:name":"Piller & Garofalo",
    "wof:placetype":"venue"
},
  "geometry": {"coordinates":[-122.86886199999999,38.612381],"type":"Point"}
}