{
  "type": "Feature",
  "properties": {
    "iso:country":"US",
    "sg:address":"1875 S. Bascom Ave., #650",
    "sg:city":"Campbell",
    "sg:classifiers":[
        {
            "category":"Personal",
            "subcategory":"Massage",
            "type":"Services"
        },
        {
            "category":"Health Services",
            "subcategory":"Clinic",
            "type":"Services"
        }
    ],
    "sg:phone":"+1 408 679 3689",
    "sg:postcode":"95008",
    "sg:province":"CA",
    "sg:tags":[
        "medical"
    ],
    "sg:website":"www.massageenvy.com/clinics/CA/C...",
    "wof:name":"Massage Envy Campbell",
    "wof:placetype":"venue"
},
  "geometry": {"coordinates":[-121.931769,37.289905],"type":"Point"}
}