{
  "type": "Feature",
  "properties": {
    "addr:full":"818 N Hill St Los Angeles CA 90012",
    "addr:housenumber":"818",
    "addr:postcode":"90012",
    "addr:street":"N Hill St",
    "iso:country":"US",
    "sg:address":"818 N Hill St",
    "sg:city":"Los Angeles",
    "sg:classifiers":[
        {
            "category":"Travel",
            "subcategory":"Hotels & Motels",
            "type":"Entertainment"
        }
    ],
    "sg:phone":"+1 213 617 3077",
    "sg:postcode":"90012",
    "sg:province":"CA",
    "wof:name":"Best Western Dragon Gate Inn",
    "wof:placetype":"venue"
},
  "geometry": {"coordinates":[-118.238998,34.063099],"type":"Point"}
}