{
  "type": "Feature",
  "properties": {
    "addr:full":"4002 Macarthur Blvd Oakland CA 94619",
    "addr:housenumber":"4002",
    "addr:postcode":"94619",
    "addr:street":"Macarthur Blvd",
    "iso:country":"US",
    "sg:address":"4002 Macarthur Blvd",
    "sg:city":"Oakland",
    "sg:classifiers":[
        {
            "category":"Shopping",
            "subcategory":"Clothing, Apparel, & Fashions",
            "type":"Retail Goods"
        }
    ],
    "sg:phone":"+1 510 531 9750",
    "sg:postcode":"94619",
    "sg:province":"CA",
    "sg:tags":[
        "uniform"
    ],
    "wof:name":"School Yard Uniforms",
    "wof:placetype":"venue"
},
  "geometry": {"coordinates":[-122.196878,37.789658],"type":"Point"}
}