{
  "type": "Feature",
  "properties": {
    "iso:country":"US",
    "sg:address":"225 E Ridgecrest Blvd",
    "sg:city":"Ridgecrest",
    "sg:classifiers":[
        {
            "category":"Shopping",
            "subcategory":"Computers & Home Electronics",
            "type":"Retail Goods"
        }
    ],
    "sg:phone":"+1 760 371 1361",
    "sg:postcode":"93555",
    "sg:province":"CA",
    "sg:tags":[
        "equipment",
        "electronic",
        "supply"
    ],
    "sg:website":"www.e-z-rent.com",
    "wof:name":"Loewen's",
    "wof:placetype":"venue"
},
  "geometry": {"coordinates":[-117.665564,35.62239],"type":"Point"}
}