{
  "type": "Feature",
  "properties": {
    "addr:full":"407 Main St Watsonville CA 95076",
    "addr:housenumber":"407",
    "addr:postcode":"95076",
    "addr:street":"Main St",
    "iso:country":"US",
    "sg:address":"407 Main St",
    "sg:city":"Watsonville",
    "sg:classifiers":[
        {
            "category":"Shopping",
            "subcategory":"Department Store",
            "type":"Retail Goods"
        }
    ],
    "sg:phone":"+1 831 728 0888",
    "sg:postcode":"95076",
    "sg:province":"CA",
    "wof:name":"Gottschalks 36",
    "wof:placetype":"venue"
},
  "geometry": {"coordinates":[-121.758381,36.911452],"type":"Point"}
}