{
  "type": "Feature",
  "properties": {
    "iso:country":"US",
    "sg:address":"23876 Aliso Creek Rd",
    "sg:city":"Laguna Niguel",
    "sg:classifiers":[
        {
            "category":"Health Services",
            "subcategory":"Dentist",
            "type":"Services"
        }
    ],
    "sg:phone":"+1 949 831 4346",
    "sg:postcode":"92675",
    "sg:province":"CA",
    "sg:tags":[
        "orthodontist",
        "endodontist",
        "cosmetic"
    ],
    "sg:website":"www.advancedentalart.com",
    "wof:name":"Advance Dental Art",
    "wof:placetype":"venue"
},
  "geometry": {"coordinates":[-117.71972599999999,33.582066],"type":"Point"}
}