{
  "type": "Feature",
  "properties": {
    "iso:country":"US",
    "sg:address":"17517 Colima Rd",
    "sg:city":"City Of Industry",
    "sg:classifiers":[
        {
            "category":"Personal",
            "subcategory":"Beauty Salon",
            "type":"Services"
        }
    ],
    "sg:phone":"+1 626 965 9655",
    "sg:postcode":"91748",
    "sg:province":"CA",
    "wof:name":"Lugiani Salon",
    "wof:placetype":"venue"
},
  "geometry": {"coordinates":[-117.92326,33.990449],"type":"Point"}
}