{
  "type": "Feature",
  "properties": {
    "iso:country":"US",
    "sg:address":"2512 Chambers Rd",
    "sg:city":"Tustin",
    "sg:classifiers":[
        {
            "category":"Professional",
            "subcategory":"Advertising",
            "type":"Services"
        }
    ],
    "sg:phone":"+1 714 730 7634",
    "sg:postcode":"92780",
    "sg:province":"CA",
    "sg:tags":[
        "counselor"
    ],
    "wof:name":"Atomic Curve",
    "wof:placetype":"venue"
},
  "geometry": {"coordinates":[-117.80701000000001,33.71722],"type":"Point"}
}