{
  "type": "Feature",
  "properties": {
    "iso:country":"US",
    "sg:address":"19000 Portola Dr",
    "sg:city":"Salinas",
    "sg:classifiers":[
        {
            "category":"Real Estate",
            "subcategory":"Real Estate Agent",
            "type":"Services"
        }
    ],
    "sg:phone":"+1 831 455 2052",
    "sg:postcode":"93908",
    "sg:province":"CA",
    "wof:name":"Backus Properties",
    "wof:placetype":"venue"
},
  "geometry": {"coordinates":[-121.686424,36.619945],"type":"Point"}
}