{
  "type": "Feature",
  "properties": {
    "iso:country":"US",
    "sg:address":"645 N Kenter Ave",
    "sg:city":"Los Angeles",
    "sg:classifiers":[
        {
            "category":"Education",
            "subcategory":"School",
            "type":"Public Place"
        }
    ],
    "sg:phone":"+1 310 472 5918",
    "sg:postcode":"90049",
    "sg:province":"CA",
    "wof:name":"Kenter Canyon Elementary Schl",
    "wof:placetype":"venue"
},
  "geometry": {"coordinates":[-118.489078,34.071675],"type":"Point"}
}