{
  "type": "Feature",
  "properties": {
    "iso:country":"US",
    "sg:address":"1538 Market St",
    "sg:city":"Redding",
    "sg:classifiers":[
        {
            "category":"Real Estate",
            "subcategory":"Real Estate Agent",
            "type":"Services"
        }
    ],
    "sg:phone":"+1 530 243 6968",
    "sg:postcode":"96001",
    "sg:province":"CA",
    "sg:tags":[
        "management"
    ],
    "wof:name":"Midtown Mall Benefit Corp",
    "wof:placetype":"venue"
},
  "geometry": {"coordinates":[-122.390553,40.583637],"type":"Point"}
}