{
  "type": "Feature",
  "properties": {
    "addr:full":"6830 Coyote Canyon Rd Somis CA 93066",
    "addr:housenumber":"6830",
    "addr:postcode":"93066",
    "addr:street":"Coyote Canyon Rd",
    "iso:country":"US",
    "sg:address":"6830 Coyote Canyon Rd",
    "sg:city":"Somis",
    "sg:classifiers":[
        {
            "category":"Retail",
            "subcategory":"Veterinary Services",
            "type":"Services"
        }
    ],
    "sg:phone":"+1 805 386 4855",
    "sg:postcode":"93066",
    "sg:province":"CA",
    "sg:tags":[
        "veterinarian"
    ],
    "wof:name":"Hugh F Hewitt DVM",
    "wof:placetype":"venue"
},
  "geometry": {"coordinates":[-119.00152,34.303244],"type":"Point"}
}