{
  "type": "Feature",
  "properties": {
    "iso:country":"US",
    "sg:address":"770 S Brea Blvd",
    "sg:city":"Brea",
    "sg:classifiers":[
        {
            "category":"Education",
            "subcategory":"Dance Studio",
            "type":"Public Place"
        }
    ],
    "sg:phone":"+1 714 990 6222",
    "sg:postcode":"92821",
    "sg:province":"CA",
    "sg:tags":[
        "instruction",
        "dancing"
    ],
    "wof:name":"Webby Dance Co",
    "wof:placetype":"venue"
},
  "geometry": {"coordinates":[-117.904529,33.908638],"type":"Point"}
}