{
  "type": "Feature",
  "properties": {
    "addr:full":"720 Market St San Francisco CA 94102",
    "addr:housenumber":"720",
    "addr:postcode":"94102",
    "addr:street":"Market St",
    "iso:country":"US",
    "sg:address":"720 Market St",
    "sg:city":"San Francisco",
    "sg:classifiers":[
        {
            "category":"Travel",
            "subcategory":"Travel Agent",
            "type":"Entertainment"
        }
    ],
    "sg:phone":"+1 415 421 1822",
    "sg:postcode":"94102",
    "sg:province":"CA",
    "sg:tags":[
        "agency",
        "bureau"
    ],
    "sg:website":"www.nippon.com",
    "wof:name":"Nippon Express Travel U S A",
    "wof:placetype":"venue"
},
  "geometry": {"coordinates":[-122.403144,37.78809],"type":"Point"}
}