{
  "type": "Feature",
  "properties": {
    "iso:country":"US",
    "sg:address":"932 French St",
    "sg:city":"Santa Ana",
    "sg:classifiers":[
        {
            "category":"Professional",
            "subcategory":"Lawyer & Legal Services",
            "type":"Services"
        }
    ],
    "sg:phone":"+1 714 558 7922",
    "sg:postcode":"92701",
    "sg:province":"CA",
    "wof:name":"Merrit McKeon ESQ",
    "wof:placetype":"venue"
},
  "geometry": {"coordinates":[-117.864684,33.75285],"type":"Point"}
}