{
  "type": "Feature",
  "properties": {
    "iso:country":"US",
    "sg:address":"3156 Market St",
    "sg:city":"San Diego",
    "sg:classifiers":[
        {
            "category":"Autos & Motor Vehicles",
            "subcategory":"Automobile Sales",
            "type":"Retail Goods"
        }
    ],
    "sg:phone":"+1 619 234 4940",
    "sg:postcode":"92102",
    "sg:province":"CA",
    "sg:tags":[
        "car",
        "dealer"
    ],
    "wof:name":"Del Mar Auto Sales",
    "wof:placetype":"venue"
},
  "geometry": {"coordinates":[-117.12639900000001,32.711743],"type":"Point"}
}