{
  "type": "Feature",
  "properties": {
    "addr:full":"460 Boulevard Way Piedmont CA 94610",
    "addr:housenumber":"460",
    "addr:postcode":"94610",
    "addr:street":"Boulevard Way",
    "iso:country":"US",
    "sg:address":"460 Boulevard Way",
    "sg:city":"Piedmont",
    "sg:classifiers":[
        {
            "category":"Professional",
            "type":"Services"
        }
    ],
    "sg:phone":"+1 510 654 1311",
    "sg:postcode":"94610",
    "sg:province":"CA",
    "sg:tags":[
        "print",
        "medium"
    ],
    "wof:name":"Piedmont Post",
    "wof:placetype":"venue"
},
  "geometry": {"coordinates":[-122.244153,37.818386],"type":"Point"}
}