{
  "type": "Feature",
  "properties": {
    "addr:full":"12711 Ventura Blvd Ste 460 Studio City CA 91604",
    "addr:housenumber":"12711",
    "addr:postcode":"91604",
    "addr:street":"Ventura Blvd Ste 460",
    "iso:country":"US",
    "sg:address":"12711 Ventura Blvd Ste 460",
    "sg:city":"Studio City",
    "sg:classifiers":[
        {
            "category":"Food & Beverages",
            "subcategory":"Liquor & Beverages",
            "type":"Retail Goods"
        }
    ],
    "sg:phone":"+1 818 508 3388",
    "sg:postcode":"91604",
    "sg:province":"CA",
    "sg:tags":[
        "beer",
        "spirit",
        "wine"
    ],
    "wof:name":"L & L Wine & Spirits Co",
    "wof:placetype":"venue"
},
  "geometry": {"coordinates":[-118.410004,34.144699],"type":"Point"}
}