{
  "type": "Feature",
  "properties": {
    "iso:country":"US",
    "sg:address":"1202 Lincoln Ave",
    "sg:city":"San Jose",
    "sg:classifiers":[
        {
            "category":"Education",
            "subcategory":"Music School",
            "type":"Public Place"
        }
    ],
    "sg:phone":"+1 408 306 2739",
    "sg:postcode":"95125",
    "sg:province":"CA",
    "sg:tags":[
        "instrument",
        "teacher",
        "musical"
    ],
    "sg:website":"www.youtube.com/bassbaby82",
    "wof:name":"David's Bass Lessons",
    "wof:placetype":"venue"
},
  "geometry": {"coordinates":[-121.899424,37.306917],"type":"Point"}
}