{
  "type": "Feature",
  "properties": {
    "iso:country":"US",
    "sg:address":"9465 Earhart Rd",
    "sg:city":"Oakland",
    "sg:classifiers":[
        {
            "category":"Education",
            "subcategory":"Special Training",
            "type":"Public Place"
        }
    ],
    "sg:phone":"+1 510 568 6100",
    "sg:postcode":"94621",
    "sg:province":"CA",
    "sg:tags":[
        "aircraft",
        "school"
    ],
    "wof:name":"Sierra Academy Of Aeronautics",
    "wof:placetype":"venue"
},
  "geometry": {"coordinates":[-122.20644799999999,37.728102],"type":"Point"}
}