{
  "type": "Feature",
  "properties": {
    "iso:country":"US",
    "sg:address":"13570 Autumn Ln",
    "sg:city":"Chico",
    "sg:classifiers":[
        {
            "category":"Professional",
            "subcategory":"Research",
            "type":"Services"
        }
    ],
    "sg:phone":"+1 530 899 7480",
    "sg:postcode":"95928",
    "sg:province":"CA",
    "wof:name":"Equity Research Investments",
    "wof:placetype":"venue"
},
  "geometry": {"coordinates":[-121.71643,39.79983],"type":"Point"}
}