{
  "type": "Feature",
  "properties": {
    "addr:full":"820 N Kalsman Ave Compton CA 90220",
    "addr:housenumber":"820",
    "addr:postcode":"90220",
    "addr:street":"N Kalsman Ave",
    "iso:country":"US",
    "sg:address":"820 N Kalsman Ave",
    "sg:city":"Compton",
    "sg:classifiers":[
        {
            "category":"Retail",
            "subcategory":"Auto Repair",
            "type":"Services"
        }
    ],
    "sg:phone":"+1 310 603 2778",
    "sg:postcode":"90220",
    "sg:province":"CA",
    "sg:tags":[
        "repairing",
        "automobile"
    ],
    "wof:name":"M & W Auto Care",
    "wof:placetype":"venue"
},
  "geometry": {"coordinates":[-118.2483,33.901082],"type":"Point"}
}