{
  "type": "Feature",
  "properties": {
    "iso:country":"US",
    "sg:address":"321 W Katella Ave Garden Walk, #120",
    "sg:city":"Anaheim",
    "sg:classifiers":[
        {
            "category":"Restaurant",
            "type":"Food & Drink"
        }
    ],
    "sg:phone":"+1 714 507 2021",
    "sg:postcode":"92802",
    "sg:province":"CA",
    "sg:tags":[
        "chinese"
    ],
    "sg:website":"www.pfchangs.com",
    "wof:name":"P.F. Chang's China Bistro",
    "wof:placetype":"venue"
},
  "geometry": {"coordinates":[-117.910484,33.803426],"type":"Point"}
}