{
  "type": "Feature",
  "properties": {
    "iso:country":"US",
    "sg:address":"5004 Newport Ave",
    "sg:city":"San Diego",
    "sg:classifiers":[
        {
            "category":"Food & Beverages",
            "subcategory":"Groceries & Convenience Stores",
            "type":"Retail Goods"
        }
    ],
    "sg:phone":"+1 619 223 5549",
    "sg:postcode":"92107",
    "sg:province":"CA",
    "sg:tags":[
        "grocer"
    ],
    "wof:name":"Newport's Farms Market",
    "wof:placetype":"venue"
},
  "geometry": {"coordinates":[-117.252226,32.747658],"type":"Point"}
}