{
  "type": "Feature",
  "properties": {
    "iso:country":"US",
    "sg:address":"337 W 35th St",
    "sg:city":"National City",
    "sg:classifiers":[
        {
            "category":"Building & Trades",
            "subcategory":"Construction",
            "type":"Services"
        }
    ],
    "sg:phone":"+1 619 409 6966",
    "sg:postcode":"91950",
    "sg:province":"CA",
    "sg:tags":[
        "contractor"
    ],
    "wof:name":"Reyes Construction",
    "wof:placetype":"venue"
},
  "geometry": {"coordinates":[-117.09833500000001,32.650014],"type":"Point"}
}