{
  "type": "Feature",
  "properties": {
    "iso:country":"US",
    "sg:address":"1350 E 17th Street",
    "sg:city":"Los Angeles",
    "sg:classifiers":[
        {
            "category":"Professional",
            "subcategory":"Computer Services",
            "type":"Services"
        }
    ],
    "sg:phone":"+1 213 744 1144",
    "sg:postcode":"90021",
    "sg:province":"CA",
    "sg:tags":[
        "stereo",
        "installation"
    ],
    "wof:name":"Absolute USA",
    "wof:placetype":"venue"
},
  "geometry": {"coordinates":[-118.24937799999999,34.025405],"type":"Point"}
}