{
  "type": "Feature",
  "properties": {
    "addr:full":"3661 Elkhorn Blvd North Highlands CA 95660",
    "addr:housenumber":"3661",
    "addr:postcode":"95660",
    "addr:street":"Elkhorn Blvd",
    "iso:country":"US",
    "sg:address":"3661 Elkhorn Blvd",
    "sg:city":"North Highlands",
    "sg:classifiers":[
        {
            "category":"Shopping",
            "subcategory":"Department Store",
            "type":"Retail Goods"
        }
    ],
    "sg:phone":"+1 916 348 8355",
    "sg:postcode":"95660",
    "sg:province":"CA",
    "sg:tags":[
        "shop"
    ],
    "wof:name":"Dollar Tree",
    "wof:placetype":"venue"
},
  "geometry": {"coordinates":[-121.38079,38.69038],"type":"Point"}
}