{
  "type": "Feature",
  "properties": {
    "iso:country":"US",
    "sg:address":"3875 Wilshire Boulevard",
    "sg:city":"Los Angeles",
    "sg:classifiers":[
        {
            "category":"Parking",
            "type":"Transportation"
        }
    ],
    "sg:phone":"+1 213 382 2703",
    "sg:postcode":"90010",
    "sg:province":"CA",
    "wof:name":"King Valet Parking",
    "wof:placetype":"venue"
},
  "geometry": {"coordinates":[-118.311278,34.06169],"type":"Point"}
}