{
  "type": "Feature",
  "properties": {
    "iso:country":"US",
    "sg:address":"29555 Elvira Dr",
    "sg:city":"Nuevo",
    "sg:classifiers":[
        {
            "category":"Building & Trades",
            "subcategory":"Pest Control",
            "type":"Services"
        }
    ],
    "sg:phone":"+1 951 928 3993",
    "sg:postcode":"92567",
    "sg:province":"CA",
    "wof:name":"Western Star Termite & Pest",
    "wof:placetype":"venue"
},
  "geometry": {"coordinates":[-117.146005,33.796185],"type":"Point"}
}