{
  "type": "Feature",
  "properties": {
    "addr:full":"665 E El Camino Real Sunnyvale CA 94087",
    "addr:housenumber":"665",
    "addr:postcode":"94087",
    "addr:street":"E El Camino Real",
    "iso:country":"US",
    "sg:address":"665 E El Camino Real",
    "sg:city":"Sunnyvale",
    "sg:classifiers":[
        {
            "category":"Retail",
            "subcategory":"Auto Repair",
            "type":"Services"
        }
    ],
    "sg:phone":"+1 408 733 1360",
    "sg:postcode":"94087",
    "sg:province":"CA",
    "wof:name":"Alfa Romeo by Continental Motors Inc",
    "wof:placetype":"venue"
},
  "geometry": {"coordinates":[-122.019997,37.357601],"type":"Point"}
}