{
  "type": "Feature",
  "properties": {
    "iso:country":"US",
    "sg:address":"1537 Franklin St Ste 103",
    "sg:city":"San Francisco",
    "sg:classifiers":[
        {
            "category":"Building & Trades",
            "subcategory":"Construction",
            "type":"Services"
        }
    ],
    "sg:phone":"+1 415 672 3220",
    "sg:postcode":"94109",
    "sg:province":"CA",
    "sg:tags":[
        "interior",
        "design"
    ],
    "sg:website":"www.goodfrienddesigngroup.com",
    "wof:name":"Goodfriend Design Group",
    "wof:placetype":"venue"
},
  "geometry": {"coordinates":[-122.42399500000001,37.788797],"type":"Point"}
}