{
  "type": "Feature",
  "properties": {
    "addr:full":"27250 Alicia Parkway Mission Viejo CA 92691",
    "addr:housenumber":"27250",
    "addr:postcode":"92691",
    "addr:street":"Alicia Parkway",
    "iso:country":"US",
    "sg:address":"27250 Alicia Parkway",
    "sg:city":"Mission Viejo",
    "sg:classifiers":[
        {
            "category":"Banks & Credit Unions",
            "subcategory":"Bank",
            "type":"Services"
        }
    ],
    "sg:phone":"+1 949 831 0128",
    "sg:postcode":"92691",
    "sg:province":"CA",
    "wof:name":"Wells Fargo Bank Na",
    "wof:placetype":"venue"
},
  "geometry": {"coordinates":[-117.66731299999999,33.611646],"type":"Point"}
}