{
  "type": "Feature",
  "properties": {
    "iso:country":"US",
    "sg:address":"211 Ivy St",
    "sg:city":"Salinas",
    "sg:classifiers":[
        {
            "category":"Retail",
            "subcategory":"Auto Repair",
            "type":"Services"
        }
    ],
    "sg:phone":"+1 831 757 7004",
    "sg:postcode":"93901",
    "sg:province":"CA",
    "sg:tags":[
        "repairing",
        "automobile"
    ],
    "wof:name":"Chacon's Automotive",
    "wof:placetype":"venue"
},
  "geometry": {"coordinates":[-121.643905,36.678051],"type":"Point"}
}