{
  "type": "Feature",
  "properties": {
    "iso:country":"US",
    "sg:address":"2243 San Diego Ave",
    "sg:city":"San Diego",
    "sg:classifiers":[
        {
            "category":"Professional",
            "subcategory":"Engineering",
            "type":"Services"
        },
        {
            "category":"Professional",
            "subcategory":"Computer Services",
            "type":"Services"
        }
    ],
    "sg:phone":"+1 619 295 0033",
    "sg:postcode":"92110",
    "sg:province":"CA",
    "sg:tags":[
        "technology",
        "system",
        "analysis"
    ],
    "wof:name":"Titan Corporation",
    "wof:placetype":"venue"
},
  "geometry": {"coordinates":[-117.18920300000001,32.746349],"type":"Point"}
}