{
  "type": "Feature",
  "properties": {
    "iso:country":"US",
    "sg:address":"1720 H St",
    "sg:city":"Fresno",
    "sg:classifiers":[
        {
            "category":"Wholesale",
            "subcategory":"Home Furnishings",
            "type":"Manufacturing & Wholesale Goods"
        }
    ],
    "sg:phone":"+1 559 252 1891",
    "sg:postcode":"93721",
    "sg:province":"CA",
    "sg:tags":[
        "floor",
        "covering"
    ],
    "wof:name":"DH Robertson",
    "wof:placetype":"venue"
},
  "geometry": {"coordinates":[-119.80062700000001,36.740221],"type":"Point"}
}