{
  "type": "Feature",
  "properties": {
    "addr:full":"2065 Martin Ave Santa Clara CA 95050",
    "addr:housenumber":"2065",
    "addr:postcode":"95050",
    "addr:street":"Martin Ave",
    "iso:country":"US",
    "sg:address":"2065 Martin Ave",
    "sg:city":"Santa Clara",
    "sg:classifiers":[
        {
            "category":"Professional",
            "subcategory":"Engineering",
            "type":"Services"
        }
    ],
    "sg:phone":"+1 408 970 8811",
    "sg:postcode":"95050",
    "sg:province":"CA",
    "sg:tags":[
        "engineer"
    ],
    "wof:name":"QSED Inc",
    "wof:placetype":"venue"
},
  "geometry": {"coordinates":[-121.96110400000001,37.366315],"type":"Point"}
}