{
  "type": "Feature",
  "properties": {
    "addr:full":"1776 W March Ln Suite 300 Stockton CA 95207",
    "addr:housenumber":"1776",
    "addr:postcode":"95207",
    "addr:street":"W March Ln Suite 300",
    "iso:country":"US",
    "sg:address":"1776 W March Ln Suite 300",
    "sg:city":"Stockton",
    "sg:classifiers":[
        {
            "category":"Professional",
            "subcategory":"Management & Consulting",
            "type":"Services"
        },
        {
            "category":"Personal",
            "type":"Services"
        },
        {
            "category":"Professional",
            "subcategory":"Detective & Security Services",
            "type":"Services"
        },
        {
            "category":"Professional",
            "subcategory":"Employment Agencies",
            "type":"Services"
        }
    ],
    "sg:phone":"+1 209 473 7892",
    "sg:postcode":"95207",
    "sg:province":"CA",
    "sg:tags":[
        "patrol",
        "consultant",
        "guard",
        "safety",
        "maintenance",
        "property",
        "opportunity"
    ],
    "sg:website":"http://www.securitasusa.com",
    "wof:name":"Securitas Security Services USA",
    "wof:placetype":"venue"
},
  "geometry": {"coordinates":[-121.327817,37.987473],"type":"Point"}
}