{
  "type": "Feature",
  "properties": {
    "iso:country":"US",
    "sg:address":"24933 Kit Carson Rd",
    "sg:city":"Calabasas",
    "sg:classifiers":[
        {
            "category":"Building & Trades",
            "subcategory":"Construction",
            "type":"Services"
        }
    ],
    "sg:phone":"+1 805 494 6631",
    "sg:postcode":"91302",
    "sg:province":"CA",
    "sg:tags":[
        "house",
        "family",
        "contractor"
    ],
    "wof:name":"R H Construction Inc",
    "wof:placetype":"venue"
},
  "geometry": {"coordinates":[-118.670813,34.167192],"type":"Point"}
}