{
  "type": "Feature",
  "properties": {
    "addr:full":"8200 W Sunset Blvd Los Angeles CA 90046",
    "addr:housenumber":"8200",
    "addr:postcode":"90046",
    "addr:street":"W Sunset Blvd",
    "iso:country":"US",
    "sg:address":"8200 W Sunset Blvd",
    "sg:city":"Los Angeles",
    "sg:classifiers":[
        {
            "category":"Restaurant",
            "type":"Food & Drink"
        }
    ],
    "sg:phone":"+1 323 822 1100",
    "sg:postcode":"90046",
    "sg:province":"CA",
    "sg:tags":[
        "mexican"
    ],
    "wof:name":"Julio's Taqueria",
    "wof:placetype":"venue"
},
  "geometry": {"coordinates":[-118.367656,34.097963],"type":"Point"}
}