{
  "type": "Feature",
  "properties": {
    "addr:full":"1400 N Benson Ave Upland CA 91786",
    "addr:housenumber":"1400",
    "addr:postcode":"91786",
    "addr:street":"N Benson Ave",
    "iso:country":"US",
    "sg:address":"1400 N Benson Ave",
    "sg:city":"Upland",
    "sg:classifiers":[
        {
            "category":"Shopping",
            "subcategory":"Clothing, Apparel, & Fashions",
            "type":"Retail Goods"
        }
    ],
    "sg:phone":"+1 909 982 5736",
    "sg:postcode":"91786",
    "sg:province":"CA",
    "sg:tags":[
        "theatrical",
        "costume"
    ],
    "wof:name":"Theatre Co",
    "wof:placetype":"venue"
},
  "geometry": {"coordinates":[-117.680837,34.111425],"type":"Point"}
}