{
  "type": "Feature",
  "properties": {
    "addr:full":"16337 Main St Hesperia CA 92345",
    "addr:housenumber":"16337",
    "addr:postcode":"92345",
    "addr:street":"Main St",
    "iso:country":"US",
    "sg:address":"16337 Main St",
    "sg:city":"Hesperia",
    "sg:classifiers":[
        {
            "category":"Autos & Motor Vehicles",
            "subcategory":"Fuel & Gas Station",
            "type":"Retail Goods"
        },
        {
            "category":"Food & Beverages",
            "subcategory":"Groceries & Convenience Stores",
            "type":"Retail Goods"
        }
    ],
    "sg:phone":"+1 760 949 0521",
    "sg:postcode":"92345",
    "sg:province":"CA",
    "wof:name":"Arco Thrifty Gas",
    "wof:placetype":"venue"
},
  "geometry": {"coordinates":[-117.30611399999999,34.422215],"type":"Point"}
}