{
  "type": "Feature",
  "properties": {
    "addr:full":"738 N Resh St Anaheim CA 92805",
    "addr:housenumber":"738",
    "addr:postcode":"92805",
    "addr:street":"N Resh St",
    "iso:country":"US",
    "sg:address":"738 N Resh St",
    "sg:city":"Anaheim",
    "sg:classifiers":[
        {
            "category":"Utilities",
            "subcategory":"Telephone",
            "type":"Services"
        }
    ],
    "sg:phone":"+1 714 535 1586",
    "sg:postcode":"92805",
    "sg:province":"CA",
    "sg:tags":[
        "communication"
    ],
    "wof:name":"Phyllis Barge",
    "wof:placetype":"venue"
},
  "geometry": {"coordinates":[-117.924817,33.840929],"type":"Point"}
}