{
  "type": "Feature",
  "properties": {
    "iso:country":"US",
    "sg:address":"6855 Santa Rosa Rd",
    "sg:city":"Buellton",
    "sg:classifiers":[
        {
            "category":"Manufacturing",
            "subcategory":"Food",
            "type":"Manufacturing & Wholesale Goods"
        }
    ],
    "sg:phone":"+1 805 688 7921",
    "sg:postcode":"93427",
    "sg:province":"CA",
    "sg:tags":[
        "winery"
    ],
    "wof:name":"Lafond Winery & Vineyard",
    "wof:placetype":"venue"
},
  "geometry": {"coordinates":[-120.269155,34.594743],"type":"Point"}
}