{
  "type": "Feature",
  "properties": {
    "addr:full":"1 National City Blvd National City CA 91950",
    "addr:housenumber":"1",
    "addr:postcode":"91950",
    "addr:street":"National City Blvd",
    "iso:country":"US",
    "sg:address":"1 National City Blvd",
    "sg:city":"National City",
    "sg:classifiers":[
        {
            "category":"Retail",
            "subcategory":"Auto Repair",
            "type":"Services"
        }
    ],
    "sg:phone":"+1 619 477 0884",
    "sg:postcode":"91950",
    "sg:province":"CA",
    "sg:tags":[
        "repairing",
        "automobile"
    ],
    "wof:name":"Econo Auto Repair",
    "wof:placetype":"venue"
},
  "geometry": {"coordinates":[-117.10988,32.68192],"type":"Point"}
}