{
  "type": "Feature",
  "properties": {
    "iso:country":"US",
    "sg:address":"43979 15th St W",
    "sg:city":"Lancaster",
    "sg:classifiers":[
        {
            "category":"Banks & Credit Unions",
            "subcategory":"Bank",
            "type":"Services"
        }
    ],
    "sg:phone":"+1 661 949 0316",
    "sg:postcode":"93534",
    "sg:province":"CA",
    "sg:tags":[
        "loan",
        "real estate"
    ],
    "wof:name":"Countrywide Funding Corp",
    "wof:placetype":"venue"
},
  "geometry": {"coordinates":[-118.156812,34.680481],"type":"Point"}
}