{
  "type": "Feature",
  "properties": {
    "addr:full":"27949 Leidig Ct Hayward CA 94544",
    "addr:postcode":"27949;94544",
    "addr:street":"Leidig Ct",
    "iso:country":"US",
    "sg:address":"27949 Leidig Ct",
    "sg:city":"Hayward",
    "sg:classifiers":[
        {
            "category":"Utilities",
            "subcategory":"Mobile Phone",
            "type":"Services"
        }
    ],
    "sg:phone":"+1 510 732 0192",
    "sg:postcode":"94544",
    "sg:province":"CA",
    "sg:tags":[
        "telephone",
        "cellular"
    ],
    "wof:name":"Wireless Wave 2",
    "wof:placetype":"venue"
},
  "geometry": {"coordinates":[-122.06630800000001,37.636579],"type":"Point"}
}