{
  "type": "Feature",
  "properties": {
    "addr:full":"4816 Mount Abbott St Riverside CA 92509",
    "addr:housenumber":"4816",
    "addr:postcode":"92509",
    "addr:street":"Mount Abbott St",
    "iso:country":"US",
    "sg:address":"4816 Mount Abbott St",
    "sg:city":"Riverside",
    "sg:classifiers":[
        {
            "category":"Manufacturing",
            "subcategory":"Paper Products",
            "type":"Manufacturing & Wholesale Goods"
        }
    ],
    "sg:phone":"+1 951 681 9311",
    "sg:postcode":"92509",
    "sg:province":"CA",
    "sg:tags":[
        "mfg"
    ],
    "wof:name":"Contact Pricing Systems",
    "wof:placetype":"venue"
},
  "geometry": {"coordinates":[-117.44908700000001,34.000777],"type":"Point"}
}