{
  "type": "Feature",
  "properties": {
    "iso:country":"US",
    "sg:address":"5100 California Ave",
    "sg:city":"Bakersfield",
    "sg:classifiers":[
        {
            "category":"Professional",
            "subcategory":"Lawyer & Legal Services",
            "type":"Services"
        }
    ],
    "sg:phone":"+1 661 861 6188",
    "sg:postcode":"93309",
    "sg:province":"CA",
    "sg:tags":[
        "attorney"
    ],
    "wof:name":"Downey Brand Seymour & Rohwer",
    "wof:placetype":"venue"
},
  "geometry": {"coordinates":[-119.05721800000001,35.363892],"type":"Point"}
}