{
  "type": "Feature",
  "properties": {
    "addr:full":"1400 W 4th St Antioch CA 94509",
    "addr:housenumber":"1400",
    "addr:postcode":"ca 94509",
    "addr:street":"W 4Th St",
    "iso:country":"US",
    "sg:address":"1400 W 4th St",
    "sg:city":"Antioch",
    "sg:classifiers":[
        {
            "category":"Home & Garden",
            "subcategory":"Home Furnishings",
            "type":"Retail Goods"
        }
    ],
    "sg:phone":"+1 925 757 0500",
    "sg:postcode":"94509",
    "sg:province":"CA",
    "sg:tags":[
        "glassware",
        "chinaware"
    ],
    "wof:name":"Owen Illinois Glass Containers",
    "wof:placetype":"venue"
},
  "geometry": {"coordinates":[-121.826414,38.015322],"type":"Point"}
}