{
  "type": "Feature",
  "properties": {
    "iso:country":"US",
    "sg:address":"538 S Anaheim Blvd",
    "sg:city":"Anaheim",
    "sg:classifiers":[
        {
            "category":"Retail",
            "subcategory":"Auto Repair",
            "type":"Services"
        }
    ],
    "sg:phone":"+1 714 956 2240",
    "sg:postcode":"92805",
    "sg:province":"CA",
    "sg:tags":[
        "repairing",
        "automobile"
    ],
    "wof:name":"Beach Cities Automotive",
    "wof:placetype":"venue"
},
  "geometry": {"coordinates":[-117.912003,33.8307],"type":"Point"}
}