{
  "type": "Feature",
  "properties": {
    "iso:country":"US",
    "sg:address":"3053 W Olympic Blvd",
    "sg:city":"Los Angeles",
    "sg:classifiers":[
        {
            "category":"Health Services",
            "subcategory":"Health Practitioner",
            "type":"Services"
        }
    ],
    "sg:phone":"+1 213 385 7333",
    "sg:postcode":"90006",
    "sg:province":"CA",
    "sg:tags":[
        "acupuncture"
    ],
    "wof:name":"Owhs Acupuncture",
    "wof:placetype":"venue"
},
  "geometry": {"coordinates":[-118.30176,34.053007],"type":"Point"}
}