{
  "type": "Feature",
  "properties": {
    "iso:country":"US",
    "sg:address":"4972 W Pico Boulevard",
    "sg:city":"Los Angeles",
    "sg:classifiers":[
        {
            "category":"Health Services",
            "subcategory":"Health Practitioner",
            "type":"Services"
        },
        {
            "category":"Insurance",
            "subcategory":"Health Insurance",
            "type":"Services"
        }
    ],
    "sg:phone":"+1 323 937 1120",
    "sg:postcode":"90019",
    "sg:province":"CA",
    "sg:tags":[
        "nutritionist",
        "market"
    ],
    "wof:name":"Green Farms Nutrition",
    "wof:placetype":"venue"
},
  "geometry": {"coordinates":[-118.345206,34.047819],"type":"Point"}
}