{
  "type": "Feature",
  "properties": {
    "addr:full":"1225 Armstrong Rd Lodi CA 95242",
    "addr:housenumber":"1225",
    "addr:postcode":"95242",
    "addr:street":"Armstrong Rd",
    "iso:country":"US",
    "sg:address":"1225 Armstrong Rd",
    "sg:city":"Lodi",
    "sg:classifiers":[
        {
            "category":"Professional",
            "type":"Services"
        }
    ],
    "sg:phone":"+1 209 465 4424",
    "sg:postcode":"95242",
    "sg:province":"CA",
    "sg:tags":[
        "establishment"
    ],
    "wof:name":"H Max Lee Inc",
    "wof:placetype":"venue"
},
  "geometry": {"coordinates":[-121.310481,38.086518],"type":"Point"}
}