{
  "type": "Feature",
  "properties": {
    "iso:country":"US",
    "sg:address":"1005 E Washington Blvd",
    "sg:city":"Los Angeles",
    "sg:classifiers":[
        {
            "category":"Community Center",
            "type":"Public Place"
        }
    ],
    "sg:phone":"+1 213 745 3636",
    "sg:postcode":"90021",
    "sg:province":"CA",
    "sg:tags":[
        "medical"
    ],
    "wof:name":"Alfa Allied Medical Center",
    "wof:placetype":"venue"
},
  "geometry": {"coordinates":[-118.252543,34.026031],"type":"Point"}
}