{
  "type": "Feature",
  "properties": {
    "addr:full":"1268 el Rancho Dr Santa Cruz CA 95060",
    "addr:housenumber":"1268",
    "addr:postcode":"95060",
    "addr:street":"El Rancho Dr",
    "iso:country":"US",
    "sg:address":"1268 el Rancho Dr",
    "sg:city":"Santa Cruz",
    "sg:classifiers":[
        {
            "category":"Professional",
            "subcategory":"Management & Consulting",
            "type":"Services"
        }
    ],
    "sg:phone":"+1 831 429 8960",
    "sg:postcode":"95060",
    "sg:province":"CA",
    "sg:tags":[
        "consultant",
        "business"
    ],
    "wof:name":"Rubedo Group",
    "wof:placetype":"venue"
},
  "geometry": {"coordinates":[-122.02724600000001,37.018343],"type":"Point"}
}