{
  "type": "Feature",
  "properties": {
    "iso:country":"US",
    "sg:address":"1100 Melody Ln",
    "sg:city":"Roseville",
    "sg:classifiers":[
        {
            "category":"Banks & Credit Unions",
            "subcategory":"Bank",
            "type":"Services"
        }
    ],
    "sg:phone":"+1 916 967 2975",
    "sg:postcode":"95678",
    "sg:province":"CA",
    "sg:tags":[
        "broker",
        "mortgage"
    ],
    "wof:name":"Pacific West Financial",
    "wof:placetype":"venue"
},
  "geometry": {"coordinates":[-121.29085600000001,38.727637],"type":"Point"}
}