{
  "type": "Feature",
  "properties": {
    "addr:full":"1177 65th St Emeryville CA 94608",
    "addr:housenumber":"1177",
    "addr:postcode":"94608",
    "addr:street":"65Th St",
    "iso:country":"US",
    "sg:address":"1177 65th St",
    "sg:city":"Emeryville",
    "sg:classifiers":[
        {
            "category":"Wholesale",
            "subcategory":"Machinery & Supplies",
            "type":"Manufacturing & Wholesale Goods"
        }
    ],
    "sg:phone":"+1 510 652 1412",
    "sg:postcode":"94608",
    "sg:province":"CA",
    "sg:tags":[
        "equipment",
        "injection",
        "molding"
    ],
    "wof:name":"Acex",
    "wof:placetype":"venue"
},
  "geometry": {"coordinates":[-122.287572,37.84754],"type":"Point"}
}