{
  "type": "Feature",
  "properties": {
    "addr:full":"30001 Town Center Dr Laguna Niguel CA 92677",
    "addr:housenumber":"30001",
    "addr:postcode":"92677",
    "addr:street":"Town Center Dr",
    "iso:country":"US",
    "sg:address":"30001 Town Center Dr",
    "sg:city":"Laguna Niguel",
    "sg:classifiers":[
        {
            "category":"Restaurant",
            "type":"Food & Drink"
        }
    ],
    "sg:menulink":"http://www.allmenus.com/ca/south-coast/284346-china-moon/menu/",
    "sg:phone":"+1 949 249 6868",
    "sg:postcode":"92677",
    "sg:province":"CA",
    "sg:tags":[
        "asian",
        "chinese"
    ],
    "wof:name":"China Moon",
    "wof:placetype":"venue"
},
  "geometry": {"coordinates":[-117.713013,33.527371],"type":"Point"}
}