{
  "type": "Feature",
  "properties": {
    "addr:full":"2025 Gateway Pl Ste 240 San Jose CA 95110",
    "addr:housenumber":"2025",
    "addr:postcode":"95110",
    "addr:street":"Gateway Pl Ste 240",
    "iso:country":"US",
    "sg:address":"2025 Gateway Pl Ste 240",
    "sg:city":"San Jose",
    "sg:classifiers":[
        {
            "category":"Professional",
            "subcategory":"Employment Agencies",
            "type":"Services"
        }
    ],
    "sg:phone":"+1 408 441 1141",
    "sg:postcode":"95110",
    "sg:province":"CA",
    "wof:name":"Westaff",
    "wof:placetype":"venue"
},
  "geometry": {"coordinates":[-121.922997,37.370602],"type":"Point"}
}