{
  "type": "Feature",
  "properties": {
    "iso:country":"US",
    "sg:address":"18220 Colima Rd",
    "sg:city":"Rowland Heights",
    "sg:classifiers":[
        {
            "category":"Banks & Credit Unions",
            "subcategory":"Bank",
            "type":"Services"
        }
    ],
    "sg:phone":"+1 626 000 1111",
    "sg:postcode":"91748",
    "sg:province":"CA",
    "wof:name":"PFF Bank & Trust",
    "wof:placetype":"venue"
},
  "geometry": {"coordinates":[-117.907964,33.988419],"type":"Point"}
}