{
  "type": "Feature",
  "properties": {
    "addr:full":"18220 Colima Rd Rowland Heights CA 91748",
    "addr:housenumber":"18220",
    "addr:postcode":"91748",
    "addr:street":"Colima Rd",
    "iso:country":"US",
    "sg:address":"18220 Colima Rd",
    "sg:city":"Rowland Heights",
    "sg:classifiers":[
        {
            "category":"Banks & Credit Unions",
            "subcategory":"Bank",
            "type":"Services"
        }
    ],
    "sg:phone":"+1 626 000 1111",
    "sg:postcode":"91748",
    "sg:province":"CA",
    "wof:name":"PFF Bank & Trust",
    "wof:placetype":"venue"
},
  "geometry": {"coordinates":[-117.90796400000001,33.988419],"type":"Point"}
}