{
  "type": "Feature",
  "properties": {
    "addr:full":"2482 Technology Dr Hayward CA 94545",
    "addr:housenumber":"2482",
    "addr:postcode":"94545",
    "addr:street":"Technology Dr",
    "iso:country":"US",
    "sg:address":"2482 Technology Dr",
    "sg:city":"Hayward",
    "sg:classifiers":[
        {
            "category":"Home & Garden",
            "subcategory":"Furniture",
            "type":"Retail Goods"
        }
    ],
    "sg:phone":"+1 510 732 6200",
    "sg:postcode":"94545",
    "sg:province":"CA",
    "sg:tags":[
        "equipment",
        "contractor",
        "kitchen",
        "cabinet"
    ],
    "sg:website":"www.americandesignbuild.com",
    "wof:name":"American Design & Build Inc",
    "wof:placetype":"venue"
},
  "geometry": {"coordinates":[-122.08699799999999,37.619099],"type":"Point"}
}