{
  "type": "Feature",
  "properties": {
    "addr:full":"501 N Idaho St La Habra CA 90631",
    "addr:housenumber":"501",
    "addr:postcode":"90631",
    "addr:street":"N Idaho St",
    "iso:country":"US",
    "sg:address":"501 N Idaho St",
    "sg:city":"La Habra",
    "sg:classifiers":[
        {
            "category":"Education",
            "subcategory":"Special Training",
            "type":"Public Place"
        }
    ],
    "sg:phone":"+1 562 697 9247",
    "sg:postcode":"90631",
    "sg:province":"CA",
    "sg:tags":[
        "educational"
    ],
    "wof:name":"Elite Education Of Fullerton",
    "wof:placetype":"venue"
},
  "geometry": {"coordinates":[-117.959187,33.935596],"type":"Point"}
}