{
  "type": "Feature",
  "properties": {
    "iso:country":"US",
    "sg:address":"370 9th St",
    "sg:city":"Crescent City",
    "sg:classifiers":[
        {
            "category":"Health Services",
            "subcategory":"Doctor",
            "type":"Services"
        }
    ],
    "sg:phone":"+1 707 465 5167",
    "sg:postcode":"95531",
    "sg:province":"CA",
    "sg:tags":[
        "physician",
        "surgeon"
    ],
    "wof:name":"Joseph R Meyers MD",
    "wof:placetype":"venue"
},
  "geometry": {"coordinates":[-124.205794,41.754017],"type":"Point"}
}