{
  "type": "Feature",
  "properties": {
    "iso:country":"US",
    "sg:address":"5300 Stevens Creek Boulevard,  Suite 450",
    "sg:city":"San Jose",
    "sg:classifiers":[
        {
            "category":"Professional",
            "subcategory":"Computer Services",
            "type":"Services"
        }
    ],
    "sg:phone":"+1 408 252 7111",
    "sg:postcode":"95129",
    "sg:province":"CA",
    "sg:tags":[
        "outsourced-product-development",
        "offshore-product-development",
        "opensocial",
        "soa-based-platforms",
        "s3",
        "ec2",
        "lucene",
        "amazon-web-services",
        "shindig",
        "ria",
        "web-2-0",
        "web-3-0",
        "lamp",
        "ruby-on-rails",
        "ajax",
        "google-apps",
        "flex",
        "platforms-for-multicore-computing",
        "software-"
    ],
    "sg:website":"http://www.impetus.com/",
    "wof:name":"Impetus Technologies, Inc.",
    "wof:placetype":"venue"
},
  "geometry": {"coordinates":[-121.971638,37.323095],"type":"Point"}
}