{
  "type": "Feature",
  "properties": {
    "iso:country":"US",
    "sg:address":"1210 N Azusa Canyon Rd",
    "sg:city":"West Covina",
    "sg:classifiers":[
        {
            "category":"Manufacturing",
            "subcategory":"Printing",
            "type":"Manufacturing & Wholesale Goods"
        }
    ],
    "sg:phone":"+1 626 962 8811",
    "sg:postcode":"91790",
    "sg:province":"CA",
    "sg:tags":[
        "newspaper"
    ],
    "wof:name":"San Gabriel Valley Tribune",
    "wof:placetype":"venue"
},
  "geometry": {"coordinates":[-117.942938,34.091209],"type":"Point"}
}