{
  "type": "Feature",
  "properties": {
    "addr:full":"2800 Naglee Rd Tracy CA 95304",
    "addr:housenumber":"2800",
    "addr:postcode":"95304",
    "addr:street":"Naglee Rd",
    "iso:country":"US",
    "sg:address":"2800 Naglee Rd",
    "sg:city":"Tracy",
    "sg:classifiers":[
        {
            "category":"Coffee & Tea",
            "type":"Food & Drink"
        }
    ],
    "sg:menulink":"http://www.allmenus.com/ca/tracy/118535-starbucks-coffee/menu/",
    "sg:phone":"+1 209 833 3494",
    "sg:postcode":"95304",
    "sg:province":"CA",
    "sg:tags":[
        "american"
    ],
    "wof:name":"Starbucks Coffee",
    "wof:placetype":"venue"
},
  "geometry": {"coordinates":[-121.45831800000001,37.757501],"type":"Point"}
}