{
  "type": "Feature",
  "properties": {
    "addr:full":"3500 Jalama Rd Lompoc CA 93436",
    "addr:postcode":"3500;93436",
    "addr:street":"Jalama Rd",
    "iso:country":"US",
    "sg:address":"3500 Jalama Rd",
    "sg:city":"Lompoc",
    "sg:phone":"+1 805 736 1889",
    "sg:postcode":"93436",
    "sg:province":"CA",
    "sg:tags":[
        "beef",
        "farm",
        "cash",
        "grain",
        "cattle",
        "feedlot"
    ],
    "wof:name":"Pata and Pata",
    "wof:placetype":"venue"
},
  "geometry": {"coordinates":[-120.41419,34.577134],"type":"Point"}
}