{
  "type": "Feature",
  "properties": {
    "addr:full":"1720 S Soto St Los Angeles CA 90023",
    "addr:housenumber":"1720",
    "addr:postcode":"90023",
    "addr:street":"S Soto St",
    "iso:country":"US",
    "sg:address":"1720 S Soto St",
    "sg:city":"Los Angeles",
    "sg:classifiers":[
        {
            "category":"Restaurant",
            "type":"Food & Drink"
        }
    ],
    "sg:phone":"+1 323 268 5225",
    "sg:postcode":"90023",
    "sg:province":"CA",
    "sg:tags":[
        "korean"
    ],
    "wof:name":"Momo Korean BBQ",
    "wof:placetype":"venue"
},
  "geometry": {"coordinates":[-118.219702,34.01752],"type":"Point"}
}