{
  "type": "Feature",
  "properties": {
    "iso:country":"US",
    "sg:address":"188 E 17th St Studio 102",
    "sg:city":"Costa Mesa",
    "sg:classifiers":[
        {
            "category":"Personal",
            "subcategory":"Beauty Salon",
            "type":"Services"
        }
    ],
    "sg:phone":"+1 949 646 6615",
    "sg:postcode":"92628",
    "sg:province":"CA",
    "sg:tags":[
        "hair"
    ],
    "wof:name":"Mirabella Salon",
    "wof:placetype":"venue"
},
  "geometry": {"coordinates":[-117.918965,33.635569],"type":"Point"}
}