{
  "type": "Feature",
  "properties": {
    "iso:country":"US",
    "sg:address":"147 Bay St",
    "sg:city":"Santa Monica",
    "sg:classifiers":[
        {
            "category":"Professional",
            "subcategory":"Research",
            "type":"Services"
        }
    ],
    "sg:phone":"+1 310 314 3660",
    "sg:postcode":"90405",
    "sg:province":"CA",
    "sg:tags":[
        "development",
        "marketing",
        "product"
    ],
    "wof:name":"2 Cool",
    "wof:placetype":"venue"
},
  "geometry": {"coordinates":[-118.489052,34.007135],"type":"Point"}
}