{
  "type": "Feature",
  "properties": {
    "addr:full":"6182 San Ramon Pl Rohnert Park CA 94928",
    "addr:housenumber":"6182",
    "addr:postcode":"94928",
    "addr:street":"San Ramon Pl",
    "iso:country":"US",
    "sg:address":"6182 San Ramon Pl",
    "sg:city":"Rohnert Park",
    "sg:classifiers":[
        {
            "category":"Restaurant",
            "type":"Food & Drink"
        }
    ],
    "sg:phone":"+1 707 484 4462",
    "sg:postcode":"94928",
    "sg:province":"CA",
    "sg:tags":[
        "caterer"
    ],
    "wof:name":"Runcible Spoon Catering",
    "wof:placetype":"venue"
},
  "geometry": {"coordinates":[-122.688596,38.349587],"type":"Point"}
}