{
  "type": "Feature",
  "properties": {
    "addr:full":"4330 Ridgecrest St Santa Maria CA 93455",
    "addr:housenumber":"4330",
    "addr:postcode":"93455",
    "addr:street":"Ridgecrest St",
    "iso:country":"US",
    "sg:address":"4330 Ridgecrest St",
    "sg:city":"Santa Maria",
    "sg:classifiers":[
        {
            "category":"Building & Trades",
            "subcategory":"Construction",
            "type":"Services"
        }
    ],
    "sg:phone":"+1 805 937 3216",
    "sg:postcode":"93455",
    "sg:province":"CA",
    "sg:tags":[
        "coping",
        "plastering",
        "tiling",
        "pool",
        "swimming"
    ],
    "wof:name":"Professional Pool & Spa Svc",
    "wof:placetype":"venue"
},
  "geometry": {"coordinates":[-120.423434,34.877108],"type":"Point"}
}