{
  "type": "Feature",
  "properties": {
    "iso:country":"US",
    "sg:address":"32124 Pso Adelanto",
    "sg:city":"San Juan Cpstrno",
    "sg:classifiers":[
        {
            "category":"Government",
            "subcategory":"Post Office",
            "type":"Public Place"
        }
    ],
    "sg:phone":"+1 949 364 9606",
    "sg:postcode":"92675",
    "sg:province":"CA",
    "sg:tags":[
        "postal",
        "us"
    ],
    "wof:name":"US Post Office",
    "wof:placetype":"venue"
},
  "geometry": {"coordinates":[-117.66535,33.494241],"type":"Point"}
}