{
  "type": "Feature",
  "properties": {
    "iso:country":"US",
    "sg:address":"8241 Beech Ave",
    "sg:city":"Fontana",
    "sg:classifiers":[
        {
            "category":"Wholesale",
            "subcategory":"Construction Materials",
            "type":"Manufacturing & Wholesale Goods"
        }
    ],
    "sg:phone":"+1 909 854 6454",
    "sg:postcode":"92335",
    "sg:province":"CA",
    "sg:tags":[
        "granite"
    ],
    "wof:name":"Granite Works",
    "wof:placetype":"venue"
},
  "geometry": {"coordinates":[-117.471154,34.100882],"type":"Point"}
}