{
  "type": "Feature",
  "properties": {
    "iso:country":"US",
    "sg:address":"1670 S Etiwanda Ave",
    "sg:city":"Ontario",
    "sg:classifiers":[
        {
            "category":"Freight",
            "type":"Transportation"
        }
    ],
    "sg:phone":"+1 909 390 7793",
    "sg:postcode":"91761",
    "sg:province":"CA",
    "sg:tags":[
        "packaging",
        "distribution",
        "specialty",
        "center"
    ],
    "wof:name":"Pactiv National Dist Ctr",
    "wof:placetype":"venue"
},
  "geometry": {"coordinates":[-117.52436899999999,34.046149],"type":"Point"}
}