{
  "type": "Feature",
  "properties": {
    "addr:full":"9750 Airport Blvd Los Angeles CA 90045",
    "addr:housenumber":"9750",
    "addr:postcode":"90045",
    "addr:street":"Airport Blvd",
    "iso:country":"US",
    "sg:address":"9750 Airport Blvd",
    "sg:city":"Los Angeles",
    "sg:classifiers":[
        {
            "category":"Retail",
            "subcategory":"Auto Rental",
            "type":"Services"
        }
    ],
    "sg:phone":"+1 310 216 0000",
    "sg:postcode":"90045",
    "sg:province":"CA",
    "sg:tags":[
        "car"
    ],
    "sg:website":"www.acerentacar.com",
    "wof:name":"Ace Rent a Car",
    "wof:placetype":"venue"
},
  "geometry": {"coordinates":[-118.385064,33.947621],"type":"Point"}
}