{
  "type": "Feature",
  "properties": {
    "iso:country":"US",
    "sg:address":"234 E 17th Street Suite 210",
    "sg:city":"Costa Mesa",
    "sg:classifiers":[
        {
            "category":"Health Services",
            "subcategory":"Health Practitioner",
            "type":"Services"
        }
    ],
    "sg:phone":"+1 949 646 0440",
    "sg:postcode":"92627",
    "sg:province":"CA",
    "sg:tags":[
        "acupuncture"
    ],
    "wof:name":"Acupuncture & Herbal Clinic of Traditional Chinese Medicine",
    "wof:placetype":"venue"
},
  "geometry": {"coordinates":[-117.91723399999999,33.634394],"type":"Point"}
}