{
  "type": "Feature",
  "properties": {
    "iso:country":"US",
    "sg:address":"1734 Chestnut St",
    "sg:city":"Redding",
    "sg:classifiers":[
        {
            "category":"Shopping",
            "subcategory":"Catalog Store",
            "type":"Retail Goods"
        }
    ],
    "sg:phone":"+1 530 244 2872",
    "sg:postcode":"96001",
    "sg:province":"CA",
    "sg:tags":[
        "mail",
        "novelty",
        "house"
    ],
    "wof:name":"Kahoonies",
    "wof:placetype":"venue"
},
  "geometry": {"coordinates":[-122.397132,40.580199],"type":"Point"}
}