{
  "type": "Feature",
  "properties": {
    "addr:full":"8509 S Figueroa St Los Angeles CA 90003",
    "addr:housenumber":"8509",
    "addr:postcode":"90003",
    "addr:street":"S Figueroa St",
    "iso:country":"US",
    "sg:address":"8509 S Figueroa St",
    "sg:city":"Los Angeles",
    "sg:classifiers":[
        {
            "category":"Wholesale",
            "subcategory":"Medical Equipment & Supplies",
            "type":"Manufacturing & Wholesale Goods"
        }
    ],
    "sg:phone":"+1 323 752 0264",
    "sg:postcode":"90003",
    "sg:province":"CA",
    "wof:name":"Simply Care Medical Supply",
    "wof:placetype":"venue"
},
  "geometry": {"coordinates":[-118.282776,33.960165],"type":"Point"}
}