{
  "type": "Feature",
  "properties": {
    "addr:full":"1686 Jessica Pl Santa Rosa CA 95403",
    "addr:housenumber":"1686",
    "addr:postcode":"95403",
    "addr:street":"Jessica Pl",
    "iso:country":"US",
    "sg:address":"1686 Jessica Pl",
    "sg:city":"Santa Rosa",
    "sg:classifiers":[
        {
            "category":"Professional",
            "subcategory":"Research",
            "type":"Services"
        }
    ],
    "sg:phone":"+1 707 575 4820",
    "sg:postcode":"95403",
    "sg:province":"CA",
    "sg:tags":[
        "market",
        "analysis"
    ],
    "wof:name":"Micro-Tech Consultants",
    "wof:placetype":"venue"
},
  "geometry": {"coordinates":[-122.75287400000001,38.478874],"type":"Point"}
}