{
  "type": "Feature",
  "properties": {
    "iso:country":"US",
    "sg:address":"52 E Campbell Ave",
    "sg:city":"Campbell",
    "sg:classifiers":[
        {
            "category":"Personal",
            "subcategory":"Beauty Salon",
            "type":"Services"
        }
    ],
    "sg:phone":"+1 408 374 4919",
    "sg:postcode":"95008",
    "sg:province":"CA",
    "sg:tags":[
        "hair"
    ],
    "wof:name":"La Bamba and Hair",
    "wof:placetype":"venue"
},
  "geometry": {"coordinates":[-121.949034,37.287041],"type":"Point"}
}