{
  "type": "Feature",
  "properties": {
    "addr:full":"35312 7th Standard Rd Bakersfield CA 93308",
    "addr:housenumber":"35312",
    "addr:postcode":"93308",
    "addr:street":"7Th Standard Rd",
    "iso:country":"US",
    "sg:address":"35312 7th Standard Rd",
    "sg:city":"Bakersfield",
    "sg:classifiers":[
        {
            "category":"Wholesale",
            "subcategory":"Machinery & Supplies",
            "type":"Manufacturing & Wholesale Goods"
        }
    ],
    "sg:phone":"+1 661 391 0117",
    "sg:postcode":"93308",
    "sg:province":"CA",
    "sg:tags":[
        "equipment",
        "welding"
    ],
    "wof:name":"Airgas West",
    "wof:placetype":"venue"
},
  "geometry": {"coordinates":[-119.07293799999999,35.441436],"type":"Point"}
}