{
  "type": "Feature",
  "properties": {
    "iso:country":"US",
    "sg:address":"11900 South St Ste 120",
    "sg:city":"Cerritos",
    "sg:classifiers":[
        {
            "category":"Building & Trades",
            "subcategory":"Locksmith",
            "type":"Services"
        }
    ],
    "sg:phone":"+1 562 865 4019",
    "sg:postcode":"90703",
    "sg:province":"CA",
    "sg:tags":[
        "key"
    ],
    "wof:name":"Southern California Security Centers Inc",
    "wof:placetype":"venue"
},
  "geometry": {"coordinates":[-118.079532,33.85791],"type":"Point"}
}