{
  "type": "Feature",
  "properties": {
    "addr:full":"667 Portola Dr San Francisco CA 94127",
    "addr:housenumber":"667",
    "addr:postcode":"94127",
    "addr:street":"Portola Dr",
    "iso:country":"US",
    "sg:address":"667 Portola Dr",
    "sg:city":"San Francisco",
    "sg:classifiers":[
        {
            "category":"Retail",
            "subcategory":"Laundry & Dry Cleaning",
            "type":"Services"
        }
    ],
    "sg:phone":"+1 415 564 7398",
    "sg:postcode":"94127",
    "sg:province":"CA",
    "sg:tags":[
        "cleaner"
    ],
    "wof:name":"Miraloma Cleaners",
    "wof:placetype":"venue"
},
  "geometry": {"coordinates":[-122.452742,37.744452],"type":"Point"}
}