{
  "type": "Feature",
  "properties": {
    "iso:country":"US",
    "sg:address":"1427 Chapin Ave",
    "sg:city":"Burlingame",
    "sg:classifiers":[
        {
            "category":"Real Estate",
            "subcategory":"Real Estate Services",
            "type":"Services"
        },
        {
            "category":"Real Estate",
            "subcategory":"Real Estate Agent",
            "type":"Services"
        }
    ],
    "sg:phone":"+1 650 720 5483",
    "sg:postcode":"94010",
    "sg:province":"CA",
    "sg:website":"www.raziel.com",
    "wof:name":"Raziel Ungar - Coldwell Banker",
    "wof:placetype":"venue"
},
  "geometry": {"coordinates":[-122.34983699999999,37.577768],"type":"Point"}
}