{
  "type": "Feature",
  "properties": {
    "iso:country":"US",
    "sg:address":"250 S Mills Rd",
    "sg:city":"Ventura",
    "sg:classifiers":[
        {
            "category":"Banks & Credit Unions",
            "subcategory":"Bank",
            "type":"Services"
        }
    ],
    "sg:phone":"+1 805 289 3560",
    "sg:postcode":"93003",
    "sg:province":"CA",
    "sg:tags":[
        "commercial",
        "saving"
    ],
    "sg:website":"http://www.sbbt.com",
    "wof:name":"Santa Barbara Bank & Trust",
    "wof:placetype":"venue"
},
  "geometry": {"coordinates":[-119.247067,34.270142],"type":"Point"}
}