{
  "type": "Feature",
  "properties": {
    "iso:country":"US",
    "sg:address":"919 12th St",
    "sg:city":"Santa Monica",
    "sg:classifiers":[
        {
            "category":"Professional",
            "type":"Services"
        }
    ],
    "sg:phone":"+1 310 393 7706",
    "sg:postcode":"90403",
    "sg:province":"CA",
    "wof:name":"Lindsay Caruso Designs",
    "wof:placetype":"venue"
},
  "geometry": {"coordinates":[-118.49409300000001,34.028281],"type":"Point"}
}