{
  "type": "Feature",
  "properties": {
    "addr:full":"1901 Harrison St Oakland CA 94612",
    "addr:housenumber":"1901",
    "addr:postcode":"94612",
    "addr:street":"Harrison St",
    "iso:country":"US",
    "sg:address":"1901 Harrison St",
    "sg:city":"Oakland",
    "sg:classifiers":[
        {
            "category":"Professional",
            "subcategory":"Lawyer & Legal Services",
            "type":"Services"
        }
    ],
    "sg:phone":"+1 510 452 2133",
    "sg:postcode":"94612",
    "sg:province":"CA",
    "sg:tags":[
        "attorney"
    ],
    "sg:website":"www.dyanicpackaging.com",
    "wof:name":"Horton Roberts & Hand",
    "wof:placetype":"venue"
},
  "geometry": {"coordinates":[-122.264544,37.808125],"type":"Point"}
}