{
  "type": "Feature",
  "properties": {
    "iso:country":"US",
    "sg:address":"19209 Colima Rd",
    "sg:city":"Rowland Heights",
    "sg:classifiers":[
        {
            "category":"Restaurant",
            "type":"Food & Drink"
        }
    ],
    "sg:phone":"+1 626 810 1626",
    "sg:postcode":"91748",
    "sg:province":"CA",
    "wof:name":"Maki Yaki",
    "wof:placetype":"venue"
},
  "geometry": {"coordinates":[-117.88185900000001,33.987162],"type":"Point"}
}