{
  "type": "Feature",
  "properties": {
    "addr:full":"8990 Grove St Elk Grove CA 95624",
    "addr:housenumber":"8990",
    "addr:postcode":"95624",
    "addr:street":"Grove St",
    "iso:country":"US",
    "sg:address":"8990 Grove St",
    "sg:city":"Elk Grove",
    "sg:classifiers":[
        {
            "category":"Organizations",
            "subcategory":"Religious Organization",
            "type":"Services"
        }
    ],
    "sg:phone":"+1 916 686 2728",
    "sg:postcode":"95624",
    "sg:province":"CA",
    "sg:tags":[
        "church"
    ],
    "sg:website":"www.lightforlife.net",
    "wof:name":"Light Of Our Saviour",
    "wof:placetype":"venue"
},
  "geometry": {"coordinates":[-121.367345,38.407825],"type":"Point"}
}