{
  "type": "Feature",
  "properties": {
    "iso:country":"US",
    "sg:address":"4051 US Hwy 101",
    "sg:city":"Arcata",
    "sg:classifiers":[
        {
            "category":"Home & Garden",
            "subcategory":"Building Materials",
            "type":"Retail Goods"
        }
    ],
    "sg:phone":"+1 707 825 9088",
    "sg:postcode":"95503",
    "sg:province":"CA",
    "wof:name":"Structure Group Inc",
    "wof:placetype":"venue"
},
  "geometry": {"coordinates":[-124.191254,40.770021],"type":"Point"}
}