{
  "type": "Feature",
  "properties": {
    "addr:full":"945 Kingston Ave Piedmont CA 94611",
    "addr:housenumber":"945",
    "addr:postcode":"94611",
    "addr:street":"Kingston Ave",
    "iso:country":"US",
    "sg:address":"945 Kingston Ave",
    "sg:city":"Piedmont",
    "sg:classifiers":[
        {
            "category":"Arts & Performance",
            "subcategory":"Art Gallery",
            "type":"Entertainment"
        }
    ],
    "sg:phone":"+1 510 655 5976",
    "sg:postcode":"94611",
    "sg:province":"CA",
    "wof:name":"Michelle Bello Fine Art Consulting",
    "wof:placetype":"venue"
},
  "geometry": {"coordinates":[-122.246447,37.82602],"type":"Point"}
}