{
  "type": "Feature",
  "properties": {
    "iso:country":"US",
    "sg:address":"5226 Palo Comado Cyn Rd",
    "sg:city":"Agoura Hills",
    "sg:classifiers":[
        {
            "category":"Autos & Motor Vehicles",
            "subcategory":"Fuel & Gas Station",
            "type":"Retail Goods"
        }
    ],
    "sg:phone":"+1 818 991 6698",
    "sg:postcode":"91301",
    "sg:province":"CA",
    "wof:name":"Agoura Hills Texaco",
    "wof:placetype":"venue"
},
  "geometry": {"coordinates":[-118.738998,34.141701],"type":"Point"}
}