{
  "type": "Feature",
  "properties": {
    "iso:country":"US",
    "sg:address":"107 S Fair Oaks Ave",
    "sg:city":"Pasadena",
    "sg:classifiers":[
        {
            "category":"Wholesale",
            "subcategory":"Electrical",
            "type":"Manufacturing & Wholesale Goods"
        }
    ],
    "sg:phone":"+1 626 744 9200",
    "sg:postcode":"91105",
    "sg:province":"CA",
    "sg:tags":[
        "electronic"
    ],
    "wof:name":"Workshops Southwest LLC",
    "wof:placetype":"venue"
},
  "geometry": {"coordinates":[-118.150531,34.144341],"type":"Point"}
}