{
  "type": "Feature",
  "properties": {
    "addr:full":"2280 Dockery Ave Selma CA 93662",
    "addr:housenumber":"2280",
    "addr:postcode":"93662",
    "addr:street":"Dockery Ave",
    "iso:country":"US",
    "sg:address":"2280 Dockery Ave",
    "sg:city":"Selma",
    "sg:classifiers":[
        {
            "category":"Health Services",
            "subcategory":"Nursing And Care Facility",
            "type":"Services"
        }
    ],
    "sg:phone":"+1 559 896 4900",
    "sg:postcode":"93662",
    "sg:province":"CA",
    "sg:tags":[
        "living",
        "extended",
        "assisted",
        "elder",
        "convalescent",
        "home"
    ],
    "wof:name":"Bethel Lutheran Home Inc",
    "wof:placetype":"venue"
},
  "geometry": {"coordinates":[-119.601837,36.566642],"type":"Point"}
}