{
  "type": "Feature",
  "properties": {
    "addr:full":"27468 Ynez Rd Suite B-1 Temecula CA 92591",
    "addr:housenumber":"27468",
    "addr:postcode":"92591",
    "addr:street":"Ynez Rd Suite B-1",
    "iso:country":"US",
    "sg:address":"27468 Ynez Rd Suite B-1",
    "sg:city":"Temecula",
    "sg:classifiers":[
        {
            "category":"Autos & Motor Vehicles",
            "subcategory":"Automobile Sales",
            "type":"Retail Goods"
        },
        {
            "category":"Retail",
            "subcategory":"Auto Rental",
            "type":"Services"
        }
    ],
    "sg:phone":"+1 951 694 1520",
    "sg:postcode":"92591",
    "sg:province":"CA",
    "sg:tags":[
        "car",
        "leasing",
        "truck"
    ],
    "sg:website":"http://www.enterprise.com/car_rental/deeplinkmap.do?gpbr=32H7&bid=004&cnty=US&arc=YPTRL01&cm_mmc=Yellowpages.com-_-IYP-_-Tradelisting-_-branch",
    "wof:name":"Enterprise Rent-A-Car",
    "wof:placetype":"venue"
},
  "geometry": {"coordinates":[-117.149759,33.504985],"type":"Point"}
}