{
  "type": "Feature",
  "properties": {
    "addr:full":"2071 Mountain Blvd Oakland CA 94611",
    "addr:housenumber":"2071",
    "addr:postcode":"94611",
    "addr:street":"Mountain Blvd",
    "iso:country":"US",
    "sg:address":"2071 Mountain Blvd",
    "sg:city":"Oakland",
    "sg:classifiers":[
        {
            "category":"Real Estate",
            "subcategory":"Architect",
            "type":"Services"
        }
    ],
    "sg:phone":"+1 510 339 8585",
    "sg:postcode":"94611",
    "sg:province":"CA",
    "wof:name":"Sheehan Architects",
    "wof:placetype":"venue"
},
  "geometry": {"coordinates":[-122.209,37.825699],"type":"Point"}
}