{
  "type": "Feature",
  "properties": {
    "iso:country":"US",
    "sg:address":"378 Hillsdale Mall",
    "sg:city":"San Mateo",
    "sg:classifiers":[
        {
            "category":"Shopping",
            "type":"Retail Goods"
        }
    ],
    "sg:phone":"+1 650 312 9088",
    "sg:postcode":"94403",
    "sg:province":"CA",
    "wof:name":"Sanrio Surprises",
    "wof:placetype":"venue"
},
  "geometry": {"coordinates":[-122.300003,37.5373],"type":"Point"}
}