{
  "type": "Feature",
  "properties": {
    "iso:country":"US",
    "sg:address":"70 Dorman Ave",
    "sg:city":"San Francisco",
    "sg:classifiers":[
        {
            "category":"Manufacturing",
            "subcategory":"Tools & Machinery",
            "type":"Manufacturing & Wholesale Goods"
        }
    ],
    "sg:phone":"+1 415 643 4460",
    "sg:postcode":"94124",
    "sg:province":"CA",
    "sg:tags":[
        "lab",
        "mfg"
    ],
    "wof:name":"Randox Laboratories Ltd",
    "wof:placetype":"venue"
},
  "geometry": {"coordinates":[-122.40269600000001,37.73993],"type":"Point"}
}