{
  "type": "Feature",
  "properties": {
    "iso:country":"US",
    "sg:address":"13805 Cuyamaca Dr",
    "sg:city":"Desert Hot Springs",
    "sg:classifiers":[
        {
            "category":"Building & Trades",
            "subcategory":"Landscaping Services",
            "type":"Services"
        }
    ],
    "sg:phone":"+1 760 251 0025",
    "sg:postcode":"92240",
    "sg:province":"CA",
    "wof:name":"Total Yard Care",
    "wof:placetype":"venue"
},
  "geometry": {"coordinates":[-116.508385,33.94825],"type":"Point"}
}