{
  "type": "Feature",
  "properties": {
    "addr:full":"1941 Ringwood Ave San Jose CA 95131",
    "addr:housenumber":"1941",
    "addr:postcode":"95131",
    "addr:street":"Ringwood Ave",
    "iso:country":"US",
    "sg:address":"1941 Ringwood Ave",
    "sg:city":"San Jose",
    "sg:classifiers":[
        {
            "category":"Wholesale",
            "subcategory":"Electrical",
            "type":"Manufacturing & Wholesale Goods"
        }
    ],
    "sg:phone":"+1 408 451 9400",
    "sg:postcode":"95131",
    "sg:province":"CA",
    "sg:tags":[
        "distributor",
        "semiconductor",
        "product",
        "computer",
        "devices"
    ],
    "sg:website":"www.bellmicro.com",
    "wof:name":"Bell Microproducts Inc",
    "wof:placetype":"venue"
},
  "geometry": {"coordinates":[-121.89566600000001,37.390318],"type":"Point"}
}