{
  "type": "Feature",
  "properties": {
    "addr:full":"4905 S Santa Fe Ave Los Angeles CA 90058",
    "addr:housenumber":"4905",
    "addr:postcode":"90058",
    "addr:street":"S Santa Fe Ave",
    "iso:country":"US",
    "sg:address":"4905 S Santa Fe Ave",
    "sg:city":"Los Angeles",
    "sg:classifiers":[
        {
            "category":"Professional",
            "subcategory":"Business Services",
            "type":"Services"
        },
        {
            "category":"Manufacturing",
            "subcategory":"Printing",
            "type":"Manufacturing & Wholesale Goods"
        }
    ],
    "sg:phone":"+1 323 583 4200",
    "sg:postcode":"90058",
    "sg:province":"CA",
    "sg:tags":[
        "industrial",
        "equipment",
        "printer"
    ],
    "wof:name":"Silva's Printing",
    "wof:placetype":"venue"
},
  "geometry": {"coordinates":[-118.230293,33.998547],"type":"Point"}
}