{
  "type": "Feature",
  "properties": {
    "addr:full":"1467 Hooker Oak Ave Chico CA 95926",
    "addr:housenumber":"1467",
    "addr:postcode":"95926",
    "addr:street":"Hooker Oak Ave",
    "iso:country":"US",
    "sg:address":"1467 Hooker Oak Ave",
    "sg:city":"Chico",
    "sg:classifiers":[
        {
            "category":"Farming",
            "subcategory":"Livestock Farm",
            "type":"Manufacturing & Wholesale Goods"
        }
    ],
    "sg:phone":"+1 530 343 1893",
    "sg:postcode":"95926",
    "sg:province":"CA",
    "sg:tags":[
        "specialty",
        "animal"
    ],
    "wof:name":"Mark Hoover Beekeeper",
    "wof:placetype":"venue"
},
  "geometry": {"coordinates":[-121.814697,39.747548],"type":"Point"}
}