{
  "type": "Feature",
  "properties": {
    "addr:full":"401 Terry Francois St Ste 126 San Francisco CA 94101",
    "addr:housenumber":"401",
    "addr:postcode":"94101",
    "addr:street":"Terry Francois St Ste 126",
    "iso:country":"US",
    "sg:address":"401 Terry Francois St Ste 126",
    "sg:city":"San Francisco",
    "sg:classifiers":[
        {
            "category":"Personal",
            "type":"Services"
        }
    ],
    "sg:phone":"+1 415 777 3250",
    "sg:postcode":"94101",
    "sg:province":"CA",
    "sg:tags":[
        "mover"
    ],
    "sg:website":"www.onebigman.com",
    "wof:name":"One Big Man, One Big Truck",
    "wof:placetype":"venue"
},
  "geometry": {"coordinates":[-122.387766,37.776196],"type":"Point"}
}