{
  "type": "Feature",
  "properties": {
    "wof:name":"Wall of Rant",
    "wof:placetype":"venue"
},
  "geometry": {"coordinates":[-122.42088,37.752939],"type":"Point"}
}