{
  "type": "Feature",
  "properties": {
    "addr:full":"3386 Meadow Way Rocklin CA 95677",
    "addr:housenumber":"3386",
    "addr:postcode":"95677",
    "addr:street":"Meadow Way",
    "iso:country":"US",
    "sg:address":"3386 Meadow Way",
    "sg:city":"Rocklin",
    "sg:classifiers":[
        {
            "category":"Building & Trades",
            "subcategory":"Construction",
            "type":"Services"
        }
    ],
    "sg:phone":"+1 916 230 7319",
    "sg:postcode":"95677",
    "sg:province":"CA",
    "sg:tags":[
        "floor",
        "laying",
        "contractor"
    ],
    "wof:name":"CA Tile & Stone",
    "wof:placetype":"venue"
},
  "geometry": {"coordinates":[-121.23579599999999,38.797705],"type":"Point"}
}