{
  "type": "Feature",
  "properties": {
    "iso:country":"US",
    "sg:address":"9930 Sierra Ave",
    "sg:city":"Fontana",
    "sg:classifiers":[
        {
            "category":"Retail",
            "subcategory":"Laundry & Dry Cleaning",
            "type":"Services"
        }
    ],
    "sg:phone":"+1 909 355 9247",
    "sg:postcode":"92335",
    "sg:province":"CA",
    "sg:tags":[
        "cleaner"
    ],
    "wof:name":"Mena Cleaners",
    "wof:placetype":"venue"
},
  "geometry": {"coordinates":[-117.43567299999999,34.073317],"type":"Point"}
}