{
  "type": "Feature",
  "properties": {
    "addr:full":"94 Hangar Way Watsonville CA 95076",
    "addr:housenumber":"94",
    "addr:postcode":"95076",
    "addr:street":"Hangar Way",
    "iso:country":"US",
    "sg:address":"94 Hangar Way",
    "sg:city":"Watsonville",
    "sg:classifiers":[
        {
            "category":"Wholesale",
            "subcategory":"Office Equipment",
            "type":"Manufacturing & Wholesale Goods"
        }
    ],
    "sg:phone":"+1 831 728 8828",
    "sg:postcode":"95076",
    "sg:province":"CA",
    "sg:tags":[
        "machine",
        "duplicating",
        "copying"
    ],
    "sg:website":"www.xpresscopy.com",
    "wof:name":"Office Dynamics",
    "wof:placetype":"venue"
},
  "geometry": {"coordinates":[-121.791009,36.92813],"type":"Point"}
}