{
  "type": "Feature",
  "properties": {
    "addr:full":"1052 South St Orland CA 95963",
    "addr:housenumber":"1052",
    "addr:postcode":"95963",
    "addr:street":"South St",
    "iso:country":"US",
    "sg:address":"1052 South St",
    "sg:city":"Orland",
    "sg:classifiers":[
        {
            "category":"Travel",
            "subcategory":"Hotels & Motels",
            "type":"Entertainment"
        }
    ],
    "sg:phone":"+1 530 865 7632",
    "sg:postcode":"95963",
    "sg:province":"CA",
    "wof:name":"Orland Inn",
    "wof:placetype":"venue"
},
  "geometry": {"coordinates":[-122.20095600000001,39.740432],"type":"Point"}
}