{
  "type": "Feature",
  "properties": {
    "addr:full":"1691 Roanoke Ave Tustin CA 92780",
    "addr:housenumber":"1691",
    "addr:postcode":"92780",
    "addr:street":"Roanoke Ave",
    "iso:country":"US",
    "sg:address":"1691 Roanoke Ave",
    "sg:city":"Tustin",
    "sg:classifiers":[
        {
            "category":"Shopping",
            "subcategory":"Gifts & Souvenirs",
            "type":"Retail Goods"
        }
    ],
    "sg:phone":"+1 714 832 9879",
    "sg:postcode":"92780",
    "sg:province":"CA",
    "sg:tags":[
        "shop"
    ],
    "wof:name":"Annette's Gifts",
    "wof:placetype":"venue"
},
  "geometry": {"coordinates":[-117.818603,33.724911],"type":"Point"}
}