{
  "type": "Feature",
  "properties": {
    "iso:country":"US",
    "sg:address":"3554 E Country Club Ln",
    "sg:city":"Sacramento",
    "sg:classifiers":[
        {
            "category":"Autos & Motor Vehicles",
            "subcategory":"Automobile Sales",
            "type":"Retail Goods"
        }
    ],
    "sg:phone":"+1 916 484 3404",
    "sg:postcode":"95821",
    "sg:province":"CA",
    "wof:name":"A&T Aircraft",
    "wof:placetype":"venue"
},
  "geometry": {"coordinates":[-121.385434,38.630915],"type":"Point"}
}