{
  "type": "Feature",
  "properties": {
    "addr:full":"118 W Hazel St Inglewood CA 90302",
    "addr:housenumber":"118",
    "addr:postcode":"90302",
    "addr:street":"W Hazel St",
    "iso:country":"US",
    "sg:address":"118 W Hazel St",
    "sg:city":"Inglewood",
    "sg:classifiers":[
        {
            "category":"Freight",
            "type":"Transportation"
        }
    ],
    "sg:phone":"+1 310 677 2283",
    "sg:postcode":"90302",
    "sg:province":"CA",
    "sg:tags":[
        "broker",
        "customs"
    ],
    "wof:name":"A C Customs Svc",
    "wof:placetype":"venue"
},
  "geometry": {"coordinates":[-118.35676599999999,33.967765],"type":"Point"}
}