{
  "type": "Feature",
  "properties": {
    "addr:full":"1923 Cll Barcelona Carlsbad CA 92009",
    "addr:housenumber":"1923",
    "addr:postcode":"92009",
    "addr:street":"Cll Barcelona",
    "iso:country":"US",
    "sg:address":"1923 Cll Barcelona",
    "sg:city":"Carlsbad",
    "sg:classifiers":[
        {
            "category":"Shopping",
            "subcategory":"Clothing, Apparel, & Fashions",
            "type":"Retail Goods"
        }
    ],
    "sg:phone":"+1 760 633 2201",
    "sg:postcode":"92009",
    "sg:province":"CA",
    "wof:name":"Ann Taylor",
    "wof:placetype":"venue"
},
  "geometry": {"coordinates":[-117.26468800000001,33.072978],"type":"Point"}
}