{
  "type": "Feature",
  "properties": {
    "iso:country":"US",
    "sg:address":"3303 Harbor Blvd",
    "sg:city":"Costa Mesa",
    "sg:classifiers":[
        {
            "category":"Autos & Motor Vehicles",
            "subcategory":"Automobile Sales",
            "type":"Retail Goods"
        },
        {
            "category":"Retail",
            "subcategory":"Auto Repair",
            "type":"Services"
        }
    ],
    "sg:phone":"+1 949 650 2690",
    "sg:postcode":"92626",
    "sg:province":"CA",
    "sg:tags":[
        "repairing"
    ],
    "wof:name":"Garry Roberts & Company",
    "wof:placetype":"venue"
},
  "geometry": {"coordinates":[-117.919645,33.693657],"type":"Point"}
}