{
  "type": "Feature",
  "properties": {
    "iso:country":"US",
    "sg:address":"429 Capri Dr",
    "sg:city":"South Lake Tahoe",
    "sg:classifiers":[
        {
            "category":"Freight",
            "type":"Transportation"
        }
    ],
    "sg:phone":"+1 530 541 2953",
    "sg:postcode":"96150",
    "sg:province":"CA",
    "sg:tags":[
        "operator",
        "tour"
    ],
    "wof:name":"Borges Sligh Hay Crriage Rides",
    "wof:placetype":"venue"
},
  "geometry": {"coordinates":[-120.006469,38.93535],"type":"Point"}
}