{
  "type": "Feature",
  "properties": {
    "addr:full":"2055 Oxford Ave Cardiff By The Sea CA 92007",
    "addr:housenumber":"2055",
    "addr:postcode":"92007",
    "addr:street":"Oxford Ave",
    "iso:country":"US",
    "sg:address":"2055 Oxford Ave",
    "sg:city":"Cardiff By The Sea",
    "sg:classifiers":[
        {
            "category":"Professional",
            "subcategory":"Management & Consulting",
            "type":"Services"
        }
    ],
    "sg:phone":"+1 760 632 1979",
    "sg:postcode":"92007",
    "sg:province":"CA",
    "wof:name":"Christman John H SEC Conslt CP",
    "wof:placetype":"venue"
},
  "geometry": {"coordinates":[-117.27973,33.0236],"type":"Point"}
}