{
  "type": "Feature",
  "properties": {
    "addr:full":"5128 Farago Ave Temple City CA 91780",
    "addr:housenumber":"5128",
    "addr:postcode":"91780",
    "addr:street":"Farago Ave",
    "iso:country":"US",
    "sg:address":"5128 Farago Ave",
    "sg:city":"Temple City",
    "sg:classifiers":[
        {
            "category":"Shopping",
            "subcategory":"Catalog Store",
            "type":"Retail Goods"
        }
    ],
    "sg:phone":"+1 626 575 5920",
    "sg:postcode":"91780",
    "sg:province":"CA",
    "sg:tags":[
        "mail",
        "order"
    ],
    "wof:name":"Joey Jetson Music",
    "wof:placetype":"venue"
},
  "geometry": {"coordinates":[-118.03017,34.098228],"type":"Point"}
}