{
  "type": "Feature",
  "properties": {
    "addr:full":"6219 Radford Ave North Hollywood CA 91606",
    "addr:housenumber":"6219",
    "addr:postcode":"91606",
    "addr:street":"Radford Ave",
    "iso:country":"US",
    "sg:address":"6219 Radford Ave",
    "sg:city":"North Hollywood",
    "sg:classifiers":[
        {
            "category":"Building & Trades",
            "subcategory":"Construction",
            "type":"Services"
        }
    ],
    "sg:phone":"+1 818 762 5584",
    "sg:postcode":"91606",
    "sg:province":"CA",
    "sg:tags":[
        "contractor"
    ],
    "wof:name":"Cervantes Drywall",
    "wof:placetype":"venue"
},
  "geometry": {"coordinates":[-118.392219,34.184527],"type":"Point"}
}