{
  "type": "Feature",
  "properties": {
    "addr:full":"1000 High St Santa Cruz CA 95060",
    "addr:housenumber":"1000",
    "addr:postcode":"95060",
    "addr:street":"High St",
    "iso:country":"US",
    "sg:address":"1000 High St",
    "sg:city":"Santa Cruz",
    "sg:classifiers":[
        {
            "category":"Social Services",
            "subcategory":"Child Care",
            "type":"Services"
        }
    ],
    "sg:phone":"+1 831 458 2259",
    "sg:postcode":"95060",
    "sg:province":"CA",
    "sg:tags":[
        "day"
    ],
    "wof:name":"Campus Kids Connection Inc",
    "wof:placetype":"venue"
},
  "geometry": {"coordinates":[-122.047997,36.977901],"type":"Point"}
}