{
  "type": "Feature",
  "properties": {
    "iso:country":"US",
    "sg:address":"19245 Malaguerra Ave",
    "sg:city":"Morgan Hill",
    "sg:classifiers":[
        {
            "category":"Recreation",
            "type":"Entertainment"
        }
    ],
    "sg:phone":"+1 408 779 3634",
    "sg:postcode":"95037",
    "sg:province":"CA",
    "sg:tags":[
        "executive"
    ],
    "wof:name":"Anderson Park",
    "wof:placetype":"venue"
},
  "geometry": {"coordinates":[-121.645274,37.164442],"type":"Point"}
}