{
  "type": "Feature",
  "properties": {
    "iso:country":"US",
    "sg:address":"23372 Madero",
    "sg:city":"Mission Viejo",
    "sg:classifiers":[
        {
            "category":"Professional",
            "subcategory":"Computer Services",
            "type":"Services"
        }
    ],
    "sg:phone":"+1 949 770 1916",
    "sg:postcode":"92691",
    "sg:province":"CA",
    "sg:tags":[
        "wiring"
    ],
    "sg:website":"www.execuphone.com",
    "wof:name":"Execu-Phone",
    "wof:placetype":"venue"
},
  "geometry": {"coordinates":[-117.67836699999999,33.623712],"type":"Point"}
}