{
  "type": "Feature",
  "properties": {
    "iso:country":"US",
    "sg:address":"24150 Sunset Crossing Rd",
    "sg:city":"Diamond Bar",
    "sg:classifiers":[
        {
            "category":"Education",
            "subcategory":"School",
            "type":"Public Place"
        }
    ],
    "sg:phone":"+1 909 397 4587",
    "sg:postcode":"91765",
    "sg:province":"CA",
    "wof:name":"Diamond Point Elementary",
    "wof:placetype":"venue"
},
  "geometry": {"coordinates":[-117.796987,34.033062],"type":"Point"}
}