{
  "type": "Feature",
  "properties": {
    "iso:country":"US",
    "sg:address":"4938 Mcbryde Ave",
    "sg:city":"Richmond",
    "sg:classifiers":[
        {
            "category":"Real Estate",
            "subcategory":"Architect",
            "type":"Services"
        }
    ],
    "sg:phone":"+1 510 234 3649",
    "sg:postcode":"94805",
    "sg:province":"CA",
    "sg:tags":[
        "specification",
        "construction",
        "architectural",
        "engineer"
    ],
    "wof:name":"Lupinsky & Associates-Architects AIA",
    "wof:placetype":"venue"
},
  "geometry": {"coordinates":[-122.330562,37.947332],"type":"Point"}
}