{
  "type": "Feature",
  "properties": {
    "addr:full":"2535 Forest Ave Chico CA 95928",
    "addr:housenumber":"2535",
    "addr:postcode":"95928",
    "addr:street":"Forest Ave",
    "iso:country":"US",
    "sg:address":"2535 Forest Ave",
    "sg:city":"Chico",
    "sg:classifiers":[
        {
            "category":"Real Estate",
            "subcategory":"Real Estate Agent",
            "type":"Services"
        }
    ],
    "sg:phone":"+1 530 342 8200",
    "sg:postcode":"95928",
    "sg:province":"CA",
    "wof:name":"Gecco Development",
    "wof:placetype":"venue"
},
  "geometry": {"coordinates":[-121.793278,39.718108],"type":"Point"}
}