{
  "type": "Feature",
  "properties": {
    "iso:country":"US",
    "sg:address":"4101 Pleiades Pl",
    "sg:city":"Union City",
    "sg:classifiers":[
        {
            "category":"Social Services",
            "subcategory":"Child Care",
            "type":"Services"
        }
    ],
    "sg:phone":"+1 510 489 4191",
    "sg:postcode":"94587",
    "sg:province":"CA",
    "wof:name":"Adventure Montessori Academy",
    "wof:placetype":"venue"
},
  "geometry": {"coordinates":[-122.06643699999999,37.587511],"type":"Point"}
}