{
  "type": "Feature",
  "properties": {
    "iso:country":"US",
    "sg:address":"16701 Bajio Ct",
    "sg:city":"Encino",
    "sg:classifiers":[
        {
            "category":"Shopping",
            "subcategory":"Clothing, Apparel, & Fashions",
            "type":"Retail Goods"
        }
    ],
    "sg:phone":"+1 818 990 6264",
    "sg:postcode":"91436",
    "sg:province":"CA",
    "sg:tags":[
        "designer"
    ],
    "sg:website":"www.infectiousawareables.com",
    "wof:name":"Infectious Awarables",
    "wof:placetype":"venue"
},
  "geometry": {"coordinates":[-118.497739,34.14828],"type":"Point"}
}