{
  "type": "Feature",
  "properties": {
    "iso:country":"US",
    "sg:address":"4537 Cyclamen Way",
    "sg:city":"Sacramento",
    "sg:classifiers":[
        {
            "category":"Wholesale",
            "subcategory":"Plants",
            "type":"Manufacturing & Wholesale Goods"
        }
    ],
    "sg:phone":"+1 916 331 0765",
    "sg:postcode":"95841",
    "sg:province":"CA",
    "sg:tags":[
        "supply"
    ],
    "wof:name":"Tami Levario",
    "wof:placetype":"venue"
},
  "geometry": {"coordinates":[-121.35788,38.657022],"type":"Point"}
}