{
  "type": "Feature",
  "properties": {
    "iso:country":"US",
    "sg:address":"2386 Warmlands Ave",
    "sg:city":"Vista",
    "sg:classifiers":[
        {
            "category":"Building & Trades",
            "subcategory":"Plumbing",
            "type":"Services"
        }
    ],
    "sg:phone":"+1 760 945 9340",
    "sg:postcode":"92084",
    "sg:province":"CA",
    "wof:name":"Code 3 Plumbing Heating & Cooling",
    "wof:placetype":"venue"
},
  "geometry": {"coordinates":[-117.22372799999999,33.233074],"type":"Point"}
}