{
  "type": "Feature",
  "properties": {
    "iso:country":"US",
    "sg:address":"2554 Orange Ave",
    "sg:city":"Costa Mesa",
    "sg:classifiers":[
        {
            "category":"Manufacturing",
            "subcategory":"Printing",
            "type":"Manufacturing & Wholesale Goods"
        }
    ],
    "sg:phone":"+1 949 548 8930",
    "sg:postcode":"92627",
    "sg:province":"CA",
    "sg:tags":[
        "publishing"
    ],
    "wof:name":"Orpheus Publications",
    "wof:placetype":"venue"
},
  "geometry": {"coordinates":[-117.894423,33.659699],"type":"Point"}
}