{
  "type": "Feature",
  "properties": {
    "addr:full":"8212 Cook Riolo Rd Antelope CA 95843",
    "addr:housenumber":"8212",
    "addr:postcode":"95843",
    "addr:street":"Cook Riolo Rd",
    "iso:country":"US",
    "sg:address":"8212 Cook Riolo Rd",
    "sg:city":"Antelope",
    "sg:classifiers":[
        {
            "category":"Food & Beverages",
            "subcategory":"Dairy",
            "type":"Retail Goods"
        }
    ],
    "sg:phone":"+1 916 722 9600",
    "sg:postcode":"95843",
    "sg:province":"CA",
    "sg:tags":[
        "product"
    ],
    "wof:name":"All American Ice Cream",
    "wof:placetype":"venue"
},
  "geometry": {"coordinates":[-121.33680699999999,38.719539],"type":"Point"}
}