{
  "type": "Feature",
  "properties": {
    "iso:country":"US",
    "sg:address":"2550 La Loma Drive",
    "sg:city":"Rancho Cordova",
    "sg:classifiers":[
        {
            "category":"Education",
            "subcategory":"School",
            "type":"Public Place"
        }
    ],
    "sg:phone":"+1 916 363 9406",
    "sg:postcode":"95670",
    "sg:province":"CA",
    "sg:tags":[
        "high",
        "middle",
        "elementary"
    ],
    "wof:name":"Folsom Cordova Unified School District",
    "wof:placetype":"venue"
},
  "geometry": {"coordinates":[-121.315521,38.589785],"type":"Point"}
}