{
  "type": "Feature",
  "properties": {
    "addr:full":"1144 2nd St Hermosa Beach CA 90254",
    "addr:housenumber":"1144",
    "addr:postcode":"90254",
    "addr:street":"2Nd St",
    "iso:country":"US",
    "sg:address":"1144 2nd St",
    "sg:city":"Hermosa Beach",
    "sg:classifiers":[
        {
            "category":"Manufacturing",
            "subcategory":"Jewelry",
            "type":"Manufacturing & Wholesale Goods"
        }
    ],
    "sg:phone":"+1 310 374 8610",
    "sg:postcode":"90254",
    "sg:province":"CA",
    "sg:tags":[
        "precious",
        "metal",
        "mfg"
    ],
    "wof:name":"Trudgen David",
    "wof:placetype":"venue"
},
  "geometry": {"coordinates":[-118.387619,33.857131],"type":"Point"}
}