{
  "type": "Feature",
  "properties": {
    "addr:full":"10737 Beverly Blvd Whittier CA 90601",
    "addr:housenumber":"10737",
    "addr:postcode":"90601",
    "addr:street":"Beverly Blvd",
    "iso:country":"US",
    "sg:address":"10737 Beverly Blvd",
    "sg:city":"Whittier",
    "sg:classifiers":[
        {
            "category":"Autos & Motor Vehicles",
            "subcategory":"Fuel & Gas Station",
            "type":"Retail Goods"
        }
    ],
    "sg:phone":"+1 562 699 4888",
    "sg:postcode":"90601",
    "sg:province":"CA",
    "sg:tags":[
        "oil"
    ],
    "wof:name":"S & I Svc Ctr Mobil",
    "wof:placetype":"venue"
},
  "geometry": {"coordinates":[-118.055682,33.998874],"type":"Point"}
}