{
  "type": "Feature",
  "properties": {
    "iso:country":"US",
    "sg:address":"2505 Harmon Rd",
    "sg:city":"West Sacramento",
    "sg:classifiers":[
        {
            "category":"Sports & Exercise",
            "subcategory":"Stables",
            "type":"Entertainment"
        }
    ],
    "sg:phone":"+1 916 753 4836",
    "sg:postcode":"95691",
    "sg:province":"CA",
    "sg:tags":[
        "riding",
        "horseback"
    ],
    "wof:name":"Buffington Performance Horses",
    "wof:placetype":"venue"
},
  "geometry": {"coordinates":[-121.546825,38.535363],"type":"Point"}
}