{
  "type": "Feature",
  "properties": {
    "addr:full":"Eagle Rd Bldg 18 Alameda CA 94501",
    "addr:housenumber":"18",
    "addr:postcode":"94501",
    "addr:street":"Eagle Rd Bldg;Alameda",
    "iso:country":"US",
    "sg:address":"Eagle Rd Bldg 18",
    "sg:city":"Alameda",
    "sg:classifiers":[
        {
            "category":"Military Area",
            "type":"Public Place"
        }
    ],
    "sg:phone":"+1 510 437 3291",
    "sg:postcode":"94501",
    "sg:province":"CA",
    "sg:tags":[
        "force",
        "armed",
        "recruiting"
    ],
    "sg:website":"http://www.uscg.mil",
    "wof:name":"Cg Pacific Area Training Team",
    "wof:placetype":"venue"
},
  "geometry": {"coordinates":[-122.24749,37.781914],"type":"Point"}
}