{
  "type": "Feature",
  "properties": {
    "addr:full":"1449 Spinnaker Dr Ventura CA 93001",
    "addr:housenumber":"1449",
    "addr:postcode":"93001",
    "addr:street":"Spinnaker Dr",
    "iso:country":"US",
    "sg:address":"1449 Spinnaker Dr",
    "sg:city":"Ventura",
    "sg:classifiers":[
        {
            "category":"Manufacturing",
            "subcategory":"Food",
            "type":"Manufacturing & Wholesale Goods"
        },
        {
            "category":"Wholesale",
            "subcategory":"Seafood",
            "type":"Manufacturing & Wholesale Goods"
        }
    ],
    "sg:phone":"+1 805 658 2069",
    "sg:postcode":"93001",
    "sg:province":"CA",
    "sg:tags":[
        "product",
        "fish",
        "prepared"
    ],
    "wof:name":"Pierpont Seafoods",
    "wof:placetype":"venue"
},
  "geometry": {"coordinates":[-119.262154,34.239595],"type":"Point"}
}