{
  "type": "Feature",
  "properties": {
    "addr:full":"7700 Hollywood Blvd West Hollywood CA 90046",
    "addr:housenumber":"7700",
    "addr:postcode":"90046",
    "addr:street":"Hollywood Blvd",
    "iso:country":"US",
    "sg:address":"7700 Hollywood Blvd",
    "sg:city":"West Hollywood",
    "sg:classifiers":[
        {
            "category":"Health Services",
            "subcategory":"Clinic",
            "type":"Services"
        }
    ],
    "sg:phone":"+1 323 654 6666",
    "sg:postcode":"90046",
    "sg:province":"CA",
    "wof:name":"West Hollywood Health & Fitns",
    "wof:placetype":"venue"
},
  "geometry": {"coordinates":[-118.357372,34.101678],"type":"Point"}
}