{
  "type": "Feature",
  "properties": {
    "addr:full":"24445 Wayman St Newhall CA 91321",
    "addr:postcode":"24445;91321",
    "addr:street":"Wayman St",
    "iso:country":"US",
    "sg:address":"24445 Wayman St",
    "sg:city":"Newhall",
    "sg:classifiers":[
        {
            "category":"Professional",
            "type":"Services"
        }
    ],
    "sg:phone":"+1 661 259 9060",
    "sg:postcode":"91321",
    "sg:province":"CA",
    "wof:name":"Cofilm Bitomsky & Schwing",
    "wof:placetype":"venue"
},
  "geometry": {"coordinates":[-118.533661,34.376546],"type":"Point"}
}