{
  "type": "Feature",
  "properties": {
    "addr:full":"9040 Lindblade St Culver City CA 90232",
    "addr:postcode":"9040;90232",
    "addr:street":"Lindblade St",
    "iso:country":"US",
    "sg:address":"9040 Lindblade St",
    "sg:city":"Culver City",
    "sg:classifiers":[
        {
            "category":"Personal",
            "type":"Services"
        }
    ],
    "sg:phone":"+1 310 253 9079",
    "sg:postcode":"90232",
    "sg:province":"CA",
    "sg:tags":[
        "control",
        "weight"
    ],
    "sg:website":"www.dietdesigns.com",
    "wof:name":"Diet Designs",
    "wof:placetype":"venue"
},
  "geometry": {"coordinates":[-118.39083599999999,34.024491],"type":"Point"}
}