{
  "type": "Feature",
  "properties": {
    "iso:country":"US",
    "sg:address":"20270 Charlanne Dr",
    "sg:city":"Redding",
    "sg:classifiers":[
        {
            "category":"Manufacturing",
            "subcategory":"Tools & Machinery",
            "type":"Manufacturing & Wholesale Goods"
        }
    ],
    "sg:phone":"+1 530 222 2373",
    "sg:postcode":"96002",
    "sg:province":"CA",
    "sg:tags":[
        "physician",
        "surgeon"
    ],
    "sg:website":"www.sagersplints.com",
    "wof:name":"Minto Research & Development",
    "wof:placetype":"venue"
},
  "geometry": {"coordinates":[-122.303351,40.54608],"type":"Point"}
}