{
  "type": "Feature",
  "properties": {
    "addr:full":"6267 Jackie Ave Woodland Hills CA 91367",
    "addr:housenumber":"6267",
    "addr:postcode":"91367",
    "addr:street":"Jackie Ave",
    "iso:country":"US",
    "sg:address":"6267 Jackie Ave",
    "sg:city":"Woodland Hills",
    "sg:classifiers":[
        {
            "category":"Real Estate",
            "subcategory":"Architect",
            "type":"Services"
        }
    ],
    "sg:phone":"+1 818 704 7065",
    "sg:postcode":"91367",
    "sg:province":"CA",
    "sg:tags":[
        "building",
        "designer"
    ],
    "wof:name":"B B Building & Design",
    "wof:placetype":"venue"
},
  "geometry": {"coordinates":[-118.635943,34.185238],"type":"Point"}
}