{
  "type": "Feature",
  "properties": {
    "addr:full":"44 Buckingham Moraga CA 94556",
    "addr:housenumber":"44",
    "addr:postcode":"94556",
    "addr:street":"Buckingham",
    "iso:country":"US",
    "sg:address":"44 Buckingham",
    "sg:city":"Moraga",
    "sg:classifiers":[
        {
            "category":"Shopping",
            "subcategory":"Used Merchandise",
            "type":"Retail Goods"
        }
    ],
    "sg:phone":"+1 925 376 1573",
    "sg:postcode":"94556",
    "sg:province":"CA",
    "sg:tags":[
        "book",
        "rare",
        "dealer"
    ],
    "wof:name":"Anmar's Children's Series Bks",
    "wof:placetype":"venue"
},
  "geometry": {"coordinates":[-122.122648,37.864313],"type":"Point"}
}