{
  "type": "Feature",
  "properties": {
    "addr:full":"5890 Grinnell Dr Riverside CA 92509",
    "addr:housenumber":"5890",
    "addr:postcode":"92509",
    "addr:street":"Grinnell Dr",
    "iso:country":"US",
    "sg:address":"5890 Grinnell Dr",
    "sg:city":"Riverside",
    "sg:classifiers":[
        {
            "category":"Professional",
            "type":"Services"
        }
    ],
    "sg:phone":"+1 951 360 8802",
    "sg:postcode":"92509",
    "sg:province":"CA",
    "wof:name":"Prickly Palace",
    "wof:placetype":"venue"
},
  "geometry": {"coordinates":[-117.460117,33.981001],"type":"Point"}
}