{
  "type": "Feature",
  "properties": {
    "iso:country":"US",
    "sg:address":"510 E Balboa Blvd",
    "sg:city":"Newport Beach",
    "sg:classifiers":[
        {
            "category":"Deli",
            "type":"Food & Drink"
        }
    ],
    "sg:phone":"+1 949 675 6864",
    "sg:postcode":"92661",
    "sg:province":"CA",
    "sg:website":"www.balharborliquor.com",
    "wof:name":"Bal Harbor Liquor & Deli",
    "wof:placetype":"venue"
},
  "geometry": {"coordinates":[-117.902,33.602798],"type":"Point"}
}