{
  "type": "Feature",
  "properties": {
    "iso:country":"US",
    "sg:address":"2166 Zeus Ct",
    "sg:city":"Bakersfield",
    "sg:classifiers":[
        {
            "category":"Manufacturing",
            "subcategory":"Tools & Machinery",
            "type":"Manufacturing & Wholesale Goods"
        }
    ],
    "sg:phone":"+1 661 392 7600",
    "sg:postcode":"93308",
    "sg:province":"CA",
    "sg:tags":[
        "pumps-wholesale",
        "manufacturer"
    ],
    "sg:website":"http://www.modypump.com",
    "wof:name":"Mody",
    "wof:placetype":"venue"
},
  "geometry": {"coordinates":[-119.06791200000001,35.432416],"type":"Point"}
}