{
  "type": "Feature",
  "properties": {
    "iso:country":"US",
    "sg:address":"41739 Enterprise Cir N",
    "sg:city":"Temecula",
    "sg:classifiers":[
        {
            "category":"Banks & Credit Unions",
            "subcategory":"Investment Brokerage",
            "type":"Services"
        }
    ],
    "sg:phone":"+1 951 296 5220",
    "sg:postcode":"92590",
    "sg:province":"CA",
    "sg:tags":[
        "advisory",
        "financial"
    ],
    "wof:name":"Inland Financial",
    "wof:placetype":"venue"
},
  "geometry": {"coordinates":[-117.168781,33.520203],"type":"Point"}
}