{
  "type": "Feature",
  "properties": {
    "addr:full":"801 Portola Dr Suite 204 San Francisco CA 94127",
    "addr:housenumber":"801",
    "addr:postcode":"94127",
    "addr:street":"Portola Dr Suite 204",
    "iso:country":"US",
    "sg:address":"801 Portola Dr Suite 204",
    "sg:city":"San Francisco",
    "sg:classifiers":[
        {
            "category":"Health Services",
            "subcategory":"Dentist",
            "type":"Services"
        }
    ],
    "sg:phone":"+1 415 566 9700",
    "sg:postcode":"94127",
    "sg:province":"CA",
    "sg:website":"drnicolas.com",
    "wof:name":"Joseph A. Nicolas, DDS",
    "wof:placetype":"venue"
},
  "geometry": {"coordinates":[-122.454095,37.743615],"type":"Point"}
}