{
  "type": "Feature",
  "properties": {
    "iso:country":"US",
    "sg:address":"767 Birch St",
    "sg:city":"Paradise",
    "sg:classifiers":[
        {
            "category":"Government",
            "subcategory":"Fire Station",
            "type":"Public Place"
        }
    ],
    "sg:phone":"+1 530 872 6264",
    "sg:postcode":"95969",
    "sg:province":"CA",
    "sg:tags":[
        "protection"
    ],
    "wof:name":"Town of Paradise",
    "wof:placetype":"venue"
},
  "geometry": {"coordinates":[-121.625178,39.753748],"type":"Point"}
}