{
  "type": "Feature",
  "properties": {
    "addr:full":"430 E Central Ave Santa Ana CA 92707",
    "addr:housenumber":"430",
    "addr:postcode":"92707",
    "addr:street":"E Central Ave",
    "iso:country":"US",
    "sg:address":"430 E Central Ave",
    "sg:city":"Santa Ana",
    "sg:classifiers":[
        {
            "category":"Professional",
            "type":"Services"
        }
    ],
    "sg:phone":"+1 714 641 0231",
    "sg:postcode":"92707",
    "sg:province":"CA",
    "wof:name":"Eliazar Toledo",
    "wof:placetype":"venue"
},
  "geometry": {"coordinates":[-117.863359,33.713831],"type":"Point"}
}