{
  "type": "Feature",
  "properties": {
    "iso:country":"US",
    "sg:address":"8226 Fountainarbor Way",
    "sg:city":"Antelope",
    "sg:classifiers":[
        {
            "category":"Home & Garden",
            "subcategory":"Building Materials",
            "type":"Retail Goods"
        },
        {
            "category":"Building & Trades",
            "subcategory":"Construction",
            "type":"Services"
        }
    ],
    "sg:phone":"+1 916 910 9662",
    "sg:postcode":"95843",
    "sg:province":"CA",
    "sg:tags":[
        "repair",
        "handyman",
        "contractor",
        "maintenance",
        "improvement",
        "painting"
    ],
    "sg:website":"http://www.jblcontracting.com",
    "wof:name":"Jbl Contracting",
    "wof:placetype":"venue"
},
  "geometry": {"coordinates":[-121.35032699999999,38.719158],"type":"Point"}
}