{
  "type": "Feature",
  "properties": {
    "iso:country":"US",
    "sg:address":"16168 Beach Blvd",
    "sg:city":"Huntington Beach",
    "sg:classifiers":[
        {
            "category":"Professional",
            "type":"Services"
        }
    ],
    "sg:phone":"+1 714 841 5285",
    "sg:postcode":"92647",
    "sg:province":"CA",
    "wof:name":"Coastal Accident & Injury",
    "wof:placetype":"venue"
},
  "geometry": {"coordinates":[-117.989092,33.728777],"type":"Point"}
}