{
  "type": "Feature",
  "properties": {
    "addr:full":"1227 Montana Ave Santa Monica CA 90403",
    "addr:housenumber":"1227",
    "addr:postcode":"90403",
    "addr:street":"Montana Ave",
    "iso:country":"US",
    "sg:address":"1227 Montana Ave",
    "sg:city":"Santa Monica",
    "sg:classifiers":[
        {
            "category":"Social Services",
            "subcategory":"Child Care",
            "type":"Services"
        }
    ],
    "sg:phone":"+1 310 393 7731",
    "sg:postcode":"90403",
    "sg:province":"CA",
    "sg:tags":[
        "kindergarten",
        "academic",
        "school"
    ],
    "wof:name":"Circle Of Children Pre-School",
    "wof:placetype":"venue"
},
  "geometry": {"coordinates":[-118.49686699999999,34.030899],"type":"Point"}
}