{
  "type": "Feature",
  "properties": {
    "addr:full":"34318 Quartz Ter Fremont CA 94555",
    "addr:housenumber":"34318",
    "addr:postcode":"94555",
    "addr:street":"Quartz Ter",
    "iso:country":"US",
    "sg:address":"34318 Quartz Ter",
    "sg:city":"Fremont",
    "sg:classifiers":[
        {
            "category":"Manufacturing",
            "subcategory":"Tools & Machinery",
            "type":"Manufacturing & Wholesale Goods"
        }
    ],
    "sg:phone":"+1 510 742 1828",
    "sg:postcode":"94555",
    "sg:province":"CA",
    "sg:tags":[
        "computer",
        "electronic",
        "mfg"
    ],
    "wof:name":"Outlet 88",
    "wof:placetype":"venue"
},
  "geometry": {"coordinates":[-122.05381199999999,37.56324],"type":"Point"}
}