{
  "type": "Feature",
  "properties": {
    "addr:full":"5525 W Slauson Avenue Los Angeles CA 90056",
    "addr:housenumber":"5525",
    "addr:postcode":"90056",
    "addr:street":"W Slauson Avenue",
    "iso:country":"US",
    "sg:address":"5525 W Slauson Avenue",
    "sg:city":"Los Angeles",
    "sg:classifiers":[
        {
            "category":"Health Services",
            "subcategory":"Hospital",
            "type":"Services"
        }
    ],
    "sg:phone":"+1 310 642 0325",
    "sg:postcode":"90056",
    "sg:province":"CA",
    "wof:name":"Kindred Hospital Los Angeles",
    "wof:placetype":"venue"
},
  "geometry": {"coordinates":[-118.37802499999999,33.988882],"type":"Point"}
}