{
  "type": "Feature",
  "properties": {
    "addr:full":"200 E Rowland St Covina CA 91723",
    "addr:housenumber":"200",
    "addr:postcode":"91723",
    "addr:street":"E Rowland St",
    "iso:country":"US",
    "sg:address":"200 E Rowland St",
    "sg:city":"Covina",
    "sg:classifiers":[
        {
            "category":"Travel",
            "subcategory":"Travel Agent",
            "type":"Entertainment"
        }
    ],
    "sg:phone":"+1 626 331 4864",
    "sg:postcode":"91723",
    "sg:province":"CA",
    "sg:tags":[
        "agency",
        "bureau"
    ],
    "wof:name":"Nelson's Travel",
    "wof:placetype":"venue"
},
  "geometry": {"coordinates":[-117.887332,34.078973],"type":"Point"}
}