{
  "type": "Feature",
  "properties": {
    "addr:full":"3840 Finley Ave Santa Rosa CA 95407",
    "addr:housenumber":"3840",
    "addr:postcode":"95407",
    "addr:street":"Finley Ave",
    "iso:country":"US",
    "sg:address":"3840 Finley Ave",
    "sg:city":"Santa Rosa",
    "sg:classifiers":[
        {
            "category":"Organizations",
            "subcategory":"Religious Organization",
            "type":"Services"
        }
    ],
    "sg:phone":"+1 707 579 0737",
    "sg:postcode":"95407",
    "sg:province":"CA",
    "sg:tags":[
        "church"
    ],
    "wof:name":"Center For The Transformationl",
    "wof:placetype":"venue"
},
  "geometry": {"coordinates":[-122.76411,38.420065],"type":"Point"}
}