{
  "type": "Feature",
  "properties": {
    "iso:country":"US",
    "sg:address":"150 Davis Ln",
    "sg:city":"Monterey",
    "sg:classifiers":[
        {
            "category":"Social Services",
            "type":"Services"
        }
    ],
    "sg:phone":"+1 831 649 5036",
    "sg:postcode":"93940",
    "sg:province":"CA",
    "sg:tags":[
        "counselor",
        "marriage",
        "family"
    ],
    "wof:name":"Sally Post",
    "wof:placetype":"venue"
},
  "geometry": {"coordinates":[-121.894695,36.593473],"type":"Point"}
}