{
  "type": "Feature",
  "properties": {
    "addr:full":"6368 Hollywood Blvd Los Angeles CA 90028",
    "addr:housenumber":"6368",
    "addr:postcode":"90028",
    "addr:street":"Hollywood Blvd",
    "iso:country":"US",
    "sg:address":"6368 Hollywood Blvd",
    "sg:city":"Los Angeles",
    "sg:classifiers":[
        {
            "category":"Shopping",
            "subcategory":"Pharmacy",
            "type":"Retail Goods"
        }
    ],
    "sg:phone":"+1 323 466 9931",
    "sg:postcode":"90028",
    "sg:province":"CA",
    "sg:tags":[
        "drugstore"
    ],
    "wof:name":"Astral Pharmacy",
    "wof:placetype":"venue"
},
  "geometry": {"coordinates":[-118.329002,34.1017],"type":"Point"}
}