{
  "type": "Feature",
  "properties": {
    "iso:country":"US",
    "sg:address":"435 Skyline Dr",
    "sg:city":"Placerville",
    "sg:classifiers":[
        {
            "category":"Retail",
            "subcategory":"Repair Shop",
            "type":"Services"
        }
    ],
    "sg:phone":"+1 530 626 7937",
    "sg:postcode":"95667",
    "sg:province":"CA",
    "sg:tags":[
        "welding"
    ],
    "wof:name":"Skyline Welding",
    "wof:placetype":"venue"
},
  "geometry": {"coordinates":[-120.811414,38.72473],"type":"Point"}
}