{
  "type": "Feature",
  "properties": {
    "addr:full":"9380 7th St Rancho Cucamonga CA 91730",
    "addr:housenumber":"9380",
    "addr:postcode":"91730",
    "addr:street":"7Th St",
    "iso:country":"US",
    "sg:address":"9380 7th St",
    "sg:city":"Rancho Cucamonga",
    "sg:classifiers":[
        {
            "category":"Professional",
            "subcategory":"Management & Consulting",
            "type":"Services"
        }
    ],
    "sg:phone":"+1 909 466 7525",
    "sg:postcode":"91730",
    "sg:province":"CA",
    "sg:tags":[
        "construction"
    ],
    "wof:name":"Tigerwall Inc",
    "wof:placetype":"venue"
},
  "geometry": {"coordinates":[-117.59940899999999,34.08851],"type":"Point"}
}