{
  "type": "Feature",
  "properties": {
    "addr:full":"19055 Bushard St Huntington Beach CA 92646",
    "addr:postcode":"19055;92646",
    "addr:street":"Bushard St",
    "iso:country":"US",
    "sg:address":"19055 Bushard St",
    "sg:city":"Huntington Beach",
    "sg:classifiers":[
        {
            "category":"Personal",
            "subcategory":"Beauty Salon",
            "type":"Services"
        }
    ],
    "sg:phone":"+1 714 813 2435",
    "sg:postcode":"92646",
    "sg:province":"CA",
    "sg:tags":[
        "shop"
    ],
    "wof:name":"Vous Hair Studio",
    "wof:placetype":"venue"
},
  "geometry": {"coordinates":[-117.962791,33.686629],"type":"Point"}
}