{
  "type": "Feature",
  "properties": {
    "iso:country":"US",
    "sg:address":"888 Wilshire Blvd",
    "sg:city":"Los Angeles",
    "sg:classifiers":[
        {
            "category":"Professional",
            "type":"Services"
        }
    ],
    "sg:phone":"+1 213 624 7495",
    "sg:postcode":"90017",
    "sg:province":"CA",
    "sg:tags":[
        "establishment"
    ],
    "wof:name":"Vinnell Corp",
    "wof:placetype":"venue"
},
  "geometry": {"coordinates":[-118.258875,34.049685],"type":"Point"}
}