{
  "type": "Feature",
  "properties": {
    "addr:full":"770 Neal Ave San Carlos CA 94070",
    "addr:housenumber":"770",
    "addr:postcode":"94070",
    "addr:street":"Neal Ave",
    "iso:country":"US",
    "sg:address":"770 Neal Ave",
    "sg:city":"San Carlos",
    "sg:classifiers":[
        {
            "category":"Retail",
            "subcategory":"Laundry & Dry Cleaning",
            "type":"Services"
        }
    ],
    "sg:phone":"+1 650 363 0874",
    "sg:postcode":"94070",
    "sg:province":"CA",
    "sg:tags":[
        "cleaners",
        "rug",
        "carpet"
    ],
    "wof:name":"Mattea Carpet & Upholstery",
    "wof:placetype":"venue"
},
  "geometry": {"coordinates":[-122.263288,37.488148],"type":"Point"}
}