{
  "type": "Feature",
  "properties": {
    "addr:full":"23110 Atlantic Cir Moreno Valley CA 92553",
    "addr:housenumber":"23110",
    "addr:postcode":"92553",
    "addr:street":"Atlantic Cir",
    "iso:country":"US",
    "sg:address":"23110 Atlantic Cir",
    "sg:city":"Moreno Valley",
    "sg:classifiers":[
        {
            "category":"Health Services",
            "subcategory":"Doctor",
            "type":"Services"
        }
    ],
    "sg:phone":"+1 951 656 6757",
    "sg:postcode":"92553",
    "sg:province":"CA",
    "sg:tags":[
        "physician",
        "surgeon"
    ],
    "wof:name":"Rogelio Drenning MD",
    "wof:placetype":"venue"
},
  "geometry": {"coordinates":[-117.260199,33.933188],"type":"Point"}
}