{
  "type": "Feature",
  "properties": {
    "iso:country":"US",
    "sg:address":"58 N Ash St",
    "sg:city":"Ventura",
    "sg:classifiers":[
        {
            "category":"Professional",
            "subcategory":"Lawyer & Legal Services",
            "type":"Services"
        }
    ],
    "sg:phone":"+1 805 648 1772",
    "sg:postcode":"93001",
    "sg:province":"CA",
    "sg:tags":[
        "attorney"
    ],
    "wof:name":"Peter J Celeste",
    "wof:placetype":"venue"
},
  "geometry": {"coordinates":[-119.288428,34.281369],"type":"Point"}
}