{
  "type": "Feature",
  "properties": {
    "addr:full":"331 Santa Monica Blvd Santa Monica CA 90401",
    "addr:housenumber":"331",
    "addr:postcode":"90401",
    "addr:street":"Santa Monica Blvd",
    "iso:country":"US",
    "sg:address":"331 Santa Monica Blvd",
    "sg:city":"Santa Monica",
    "sg:classifiers":[
        {
            "category":"Travel",
            "subcategory":"Hotels & Motels",
            "type":"Entertainment"
        }
    ],
    "sg:phone":"+1 310 395 0804",
    "sg:postcode":"90401",
    "sg:province":"CA",
    "sg:tags":[
        "operation"
    ],
    "wof:name":"Tides Building",
    "wof:placetype":"venue"
},
  "geometry": {"coordinates":[-118.495439,34.016224],"type":"Point"}
}