{
  "type": "Feature",
  "properties": {
    "addr:full":"411 Borel Ave San Mateo CA 94402",
    "addr:housenumber":"411",
    "addr:postcode":"94402",
    "addr:street":"Borel Ave",
    "iso:country":"US",
    "sg:address":"411 Borel Ave",
    "sg:city":"San Mateo",
    "sg:classifiers":[
        {
            "category":"Wholesale",
            "subcategory":"Drugs",
            "type":"Manufacturing & Wholesale Goods"
        }
    ],
    "sg:phone":"+1 650 578 1558",
    "sg:postcode":"94402",
    "sg:province":"CA",
    "sg:tags":[
        "medical"
    ],
    "wof:name":"Pfizer",
    "wof:placetype":"venue"
},
  "geometry": {"coordinates":[-122.32010200000001,37.549056],"type":"Point"}
}