{
  "type": "Feature",
  "properties": {
    "addr:full":"4707 Greenleaf Ct Modesto CA 95356",
    "addr:housenumber":"4707",
    "addr:postcode":"ca 95356",
    "addr:street":"Greenleaf Ct",
    "iso:country":"US",
    "sg:address":"4707 Greenleaf Ct",
    "sg:city":"Modesto",
    "sg:classifiers":[
        {
            "category":"Social Services",
            "type":"Services"
        }
    ],
    "sg:phone":"+1 209 543 1340",
    "sg:postcode":"95356",
    "sg:province":"CA",
    "sg:tags":[
        "organization",
        "welfare"
    ],
    "sg:website":"www.communitycatalyst.org",
    "wof:name":"Community Catalyst Of Ca",
    "wof:placetype":"venue"
},
  "geometry": {"coordinates":[-121.07088899999999,37.701656],"type":"Point"}
}