{
  "type": "Feature",
  "properties": {
    "addr:full":"5999 Curtis Pl California City CA 93505",
    "addr:housenumber":"5999",
    "addr:postcode":"93505",
    "addr:street":"Curtis Pl",
    "iso:country":"US",
    "sg:address":"5999 Curtis Pl",
    "sg:city":"California City",
    "sg:classifiers":[
        {
            "category":"Recreation",
            "type":"Entertainment"
        }
    ],
    "sg:phone":"+1 661 765 5550",
    "sg:postcode":"93505",
    "sg:province":"CA",
    "sg:tags":[
        "parachute",
        "skydiving",
        "jumping"
    ],
    "wof:name":"Air Adventures West",
    "wof:placetype":"venue"
},
  "geometry": {"coordinates":[-118.018721,35.148439],"type":"Point"}
}