{
  "type": "Feature",
  "properties": {
    "addr:full":"1315 Woodcreek Way Stockton CA 95209",
    "addr:housenumber":"1315",
    "addr:postcode":"95209",
    "addr:street":"Woodcreek Way",
    "iso:country":"US",
    "sg:address":"1315 Woodcreek Way",
    "sg:city":"Stockton",
    "sg:classifiers":[
        {
            "category":"Education",
            "subcategory":"School",
            "type":"Public Place"
        }
    ],
    "sg:phone":"+1 209 953 8392",
    "sg:postcode":"95209",
    "sg:province":"CA",
    "wof:name":"Oakwood Elementary School",
    "wof:placetype":"venue"
},
  "geometry": {"coordinates":[-121.32930899999999,38.033967],"type":"Point"}
}