{
  "type": "Feature",
  "properties": {
    "addr:full":"1969 Mountain Blvd Oakland CA 94611",
    "addr:housenumber":"1969",
    "addr:postcode":"94611",
    "addr:street":"Mountain Blvd",
    "iso:country":"US",
    "sg:address":"1969 Mountain Blvd",
    "sg:city":"Oakland",
    "sg:classifiers":[
        {
            "category":"Real Estate",
            "subcategory":"Real Estate Services",
            "type":"Services"
        }
    ],
    "sg:phone":"+1 510 338 0257",
    "sg:postcode":"94611",
    "sg:province":"CA",
    "sg:tags":[
        "company",
        "title"
    ],
    "wof:name":"Fidelity National Title",
    "wof:placetype":"venue"
},
  "geometry": {"coordinates":[-122.21082,37.828941],"type":"Point"}
}