{
  "type": "Feature",
  "properties": {
    "addr:full":"201 Technology Dr Irvine CA 92618",
    "addr:housenumber":"201",
    "addr:postcode":"92618",
    "addr:street":"Technology Dr",
    "iso:country":"US",
    "sg:address":"201 Technology Dr",
    "sg:city":"Irvine",
    "sg:classifiers":[
        {
            "category":"Manufacturing",
            "subcategory":"Tools & Machinery",
            "type":"Manufacturing & Wholesale Goods"
        }
    ],
    "sg:phone":"+1 949 450 5400",
    "sg:postcode":"92618",
    "sg:province":"CA",
    "sg:tags":[
        "manufacture"
    ],
    "sg:website":"www.endocare.com",
    "wof:name":"Endocare Inc",
    "wof:placetype":"venue"
},
  "geometry": {"coordinates":[-117.74611,33.664803],"type":"Point"}
}