{
  "type": "Feature",
  "properties": {
    "addr:full":"11031 Camarillo St North Hollywood CA 91602",
    "addr:housenumber":"11031",
    "addr:postcode":"91602",
    "addr:street":"Camarillo St",
    "iso:country":"US",
    "sg:address":"11031 Camarillo St",
    "sg:city":"North Hollywood",
    "sg:classifiers":[
        {
            "category":"Arts & Performance",
            "subcategory":"Arts Center",
            "type":"Entertainment"
        }
    ],
    "sg:phone":"+1 818 745 8527",
    "sg:postcode":"91602",
    "sg:province":"CA",
    "sg:tags":[
        "performing"
    ],
    "sg:website":"www.crowncitytheatre.com/",
    "wof:name":"Crown City Theater",
    "wof:placetype":"venue"
},
  "geometry": {"coordinates":[-118.371779,34.157981],"type":"Point"}
}