{
  "type": "Feature",
  "properties": {
    "addr:full":"5502 White Pine Way Bakersfield CA 93313",
    "addr:housenumber":"5502",
    "addr:postcode":"93313",
    "addr:street":"White Pine Way",
    "iso:country":"US",
    "sg:address":"5502 White Pine Way",
    "sg:city":"Bakersfield",
    "sg:classifiers":[
        {
            "category":"Wholesale",
            "subcategory":"Non-durable Goods",
            "type":"Manufacturing & Wholesale Goods"
        }
    ],
    "sg:phone":"+1 661 831 4256",
    "sg:postcode":"93313",
    "sg:province":"CA",
    "wof:name":"TLC Distributing",
    "wof:placetype":"venue"
},
  "geometry": {"coordinates":[-119.065699,35.305334],"type":"Point"}
}