{
  "type": "Feature",
  "properties": {
    "addr:full":"1243 Lincoln Blvd Santa Monica CA 90401",
    "addr:housenumber":"1243",
    "addr:postcode":"90401",
    "addr:street":"Lincoln Blvd",
    "iso:country":"US",
    "sg:address":"1243 Lincoln Blvd",
    "sg:city":"Santa Monica",
    "sg:classifiers":[
        {
            "category":"Travel",
            "subcategory":"Hotels & Motels",
            "type":"Entertainment"
        }
    ],
    "sg:phone":"+1 310 458 1411",
    "sg:postcode":"90401",
    "sg:province":"CA",
    "wof:name":"American Motel",
    "wof:placetype":"venue"
},
  "geometry": {"coordinates":[-118.493487,34.021483],"type":"Point"}
}