{
  "type": "Feature",
  "properties": {
    "addr:full":"8624 Alden Ln Windsor CA 95492",
    "addr:housenumber":"8624",
    "addr:postcode":"95492",
    "addr:street":"Alden Ln",
    "iso:country":"US",
    "sg:address":"8624 Alden Ln",
    "sg:city":"Windsor",
    "sg:classifiers":[
        {
            "category":"Manufacturing",
            "subcategory":"Retail Goods",
            "type":"Manufacturing & Wholesale Goods"
        }
    ],
    "sg:phone":"+1 707 837 8308",
    "sg:postcode":"95492",
    "sg:province":"CA",
    "sg:tags":[
        "product",
        "mfg"
    ],
    "wof:name":"Caldwell Mfg",
    "wof:placetype":"venue"
},
  "geometry": {"coordinates":[-122.799515,38.546516],"type":"Point"}
}