{
  "type": "Feature",
  "properties": {
    "iso:country":"US",
    "sg:address":"3333 Bowers Ave",
    "sg:city":"Santa Clara",
    "sg:classifiers":[
        {
            "category":"Building & Trades",
            "subcategory":"Equipment Rental",
            "type":"Services"
        }
    ],
    "sg:phone":"+1 408 264 4643",
    "sg:postcode":"95054",
    "sg:province":"CA",
    "sg:tags":[
        "leasing"
    ],
    "wof:name":"Sanco Equipment Leasing",
    "wof:placetype":"venue"
},
  "geometry": {"coordinates":[-121.97772999999999,37.381769],"type":"Point"}
}