{
  "type": "Feature",
  "properties": {
    "iso:country":"US",
    "sg:address":"356 El Camino Real",
    "sg:city":"San Bruno",
    "sg:classifiers":[
        {
            "category":"Sports & Exercise",
            "subcategory":"Gym",
            "type":"Entertainment"
        },
        {
            "category":"Arena",
            "subcategory":"Sports Club",
            "type":"Entertainment"
        }
    ],
    "sg:phone":"+1 650 589 8018",
    "sg:postcode":"94066",
    "sg:province":"CA",
    "sg:tags":[
        "trainer",
        "martial art",
        "yoga"
    ],
    "wof:name":"Omine Karate Dojo",
    "wof:placetype":"venue"
},
  "geometry": {"coordinates":[-122.41100299999999,37.620899],"type":"Point"}
}