{
  "type": "Feature",
  "properties": {
    "iso:country":"US",
    "sg:address":"10041 Central Ave",
    "sg:city":"Montclair",
    "sg:classifiers":[
        {
            "category":"Professional",
            "subcategory":"Art Services",
            "type":"Services"
        },
        {
            "category":"Shopping",
            "subcategory":"Pets & Pet Supplies",
            "type":"Retail Goods"
        }
    ],
    "sg:phone":"+1 909 626 5564",
    "sg:postcode":"91763",
    "sg:province":"CA",
    "sg:tags":[
        "taxidermists-equipment",
        "taxidermist"
    ],
    "wof:name":"Dave's Taxidermy",
    "wof:placetype":"venue"
},
  "geometry": {"coordinates":[-117.689498,34.071541],"type":"Point"}
}