{
  "type": "Feature",
  "properties": {
    "addr:full":"512 Valley Way Milpitas CA 95035",
    "addr:housenumber":"512",
    "addr:postcode":"95035",
    "addr:street":"Valley Way",
    "iso:country":"US",
    "sg:address":"512 Valley Way",
    "sg:city":"Milpitas",
    "sg:classifiers":[
        {
            "category":"Social Services",
            "type":"Services"
        }
    ],
    "sg:phone":"+1 408 416 0271",
    "sg:postcode":"95035",
    "sg:province":"CA",
    "sg:tags":[
        "organization",
        "welfare"
    ],
    "wof:name":"Project MATCH",
    "wof:placetype":"venue"
},
  "geometry": {"coordinates":[-121.91402100000001,37.427226],"type":"Point"}
}