{
  "type": "Feature",
  "properties": {
    "addr:full":"8250 Mira Mesa Blvd San Diego CA 92126",
    "addr:housenumber":"8250",
    "addr:postcode":"92126",
    "addr:street":"Mira Mesa Blvd",
    "iso:country":"US",
    "sg:address":"8250 Mira Mesa Blvd",
    "sg:city":"San Diego",
    "sg:classifiers":[
        {
            "category":"Personal",
            "subcategory":"Barber",
            "type":"Services"
        }
    ],
    "sg:phone":"+1 858 566 6100",
    "sg:postcode":"92126",
    "sg:province":"CA",
    "wof:name":"Rocco's Hair Designs",
    "wof:placetype":"venue"
},
  "geometry": {"coordinates":[-117.14554099999999,32.912739],"type":"Point"}
}