{
  "type": "Feature",
  "properties": {
    "addr:full":"5911 Riverside Blvd Sacramento CA 95831",
    "addr:housenumber":"5911",
    "addr:postcode":"95831",
    "addr:street":"Riverside Blvd",
    "iso:country":"US",
    "sg:address":"5911 Riverside Blvd",
    "sg:city":"Sacramento",
    "sg:classifiers":[
        {
            "category":"Shopping",
            "subcategory":"Bicycles & Sporting Goods",
            "type":"Retail Goods"
        }
    ],
    "sg:phone":"+1 916 428 4689",
    "sg:postcode":"95831",
    "sg:province":"CA",
    "sg:tags":[
        "equipment",
        "golf",
        "supply"
    ],
    "wof:name":"World Golfing Emporium",
    "wof:placetype":"venue"
},
  "geometry": {"coordinates":[-121.52216900000001,38.522814],"type":"Point"}
}