{
  "type": "Feature",
  "properties": {
    "iso:country":"US",
    "sg:address":"128 S Glenoaks Blvd",
    "sg:city":"Burbank",
    "sg:classifiers":[
        {
            "category":"Shopping",
            "subcategory":"Clothing, Apparel, & Fashions",
            "type":"Retail Goods"
        }
    ],
    "sg:phone":"+1 818 843 7549",
    "sg:postcode":"91502",
    "sg:province":"CA",
    "sg:tags":[
        "tailor"
    ],
    "wof:name":"Fashions International",
    "wof:placetype":"venue"
},
  "geometry": {"coordinates":[-118.305398,34.182712],"type":"Point"}
}