{
  "type": "Feature",
  "properties": {
    "iso:country":"US",
    "sg:address":"684 N Puente Ave",
    "sg:city":"La Puente",
    "sg:classifiers":[
        {
            "category":"Organizations",
            "subcategory":"Religious Organization",
            "type":"Services"
        }
    ],
    "sg:phone":"+1 626 962 0616",
    "sg:postcode":"91746",
    "sg:province":"CA",
    "sg:tags":[
        "church"
    ],
    "wof:name":"Iglesia Evangelica Bautista",
    "wof:placetype":"venue"
},
  "geometry": {"coordinates":[-117.980572,34.051745],"type":"Point"}
}