{
  "type": "Feature",
  "properties": {
    "iso:country":"US",
    "sg:address":"4888 N Glenn Ave",
    "sg:city":"Fresno",
    "sg:classifiers":[
        {
            "category":"Real Estate",
            "subcategory":"Real Estate Operator",
            "type":"Services"
        }
    ],
    "sg:phone":"+1 559 227 1554",
    "sg:postcode":"93704",
    "sg:province":"CA",
    "wof:name":"Reef Apts",
    "wof:placetype":"venue"
},
  "geometry": {"coordinates":[-119.79261,36.805075],"type":"Point"}
}