{
  "type": "Feature",
  "properties": {
    "iso:country":"US",
    "sg:address":"9104 International Blvd",
    "sg:city":"Oakland",
    "sg:classifiers":[
        {
            "category":"Food & Beverages",
            "subcategory":"Groceries & Convenience Stores",
            "type":"Retail Goods"
        }
    ],
    "sg:phone":"+1 510 635 2587",
    "sg:postcode":"94603",
    "sg:province":"CA",
    "wof:name":"El Mercado Numero Uno",
    "wof:placetype":"venue"
},
  "geometry": {"coordinates":[-122.17376299999999,37.749164],"type":"Point"}
}