{
  "type": "Feature",
  "properties": {
    "addr:full":"302 N Fair Oaks Ave Sunnyvale CA 94085",
    "addr:housenumber":"302",
    "addr:postcode":"94085",
    "addr:street":"N Fair Oaks Ave",
    "iso:country":"US",
    "sg:address":"302 N Fair Oaks Ave",
    "sg:city":"Sunnyvale",
    "sg:classifiers":[
        {
            "category":"Restaurant",
            "type":"Food & Drink"
        }
    ],
    "sg:phone":"+1 408 774 9090",
    "sg:postcode":"94085",
    "sg:province":"CA",
    "sg:tags":[
        "thai"
    ],
    "sg:website":"www.elephantexpress.net/",
    "wof:name":"Elephant Express",
    "wof:placetype":"venue"
},
  "geometry": {"coordinates":[-122.01792500000001,37.381884],"type":"Point"}
}