{
  "type": "Feature",
  "properties": {
    "iso:country":"US",
    "sg:address":"4021 Paula St",
    "sg:city":"La Mesa",
    "sg:classifiers":[
        {
            "category":"Manufacturing",
            "subcategory":"Tools & Machinery",
            "type":"Manufacturing & Wholesale Goods"
        }
    ],
    "sg:phone":"+1 619 462 3337",
    "sg:postcode":"91941",
    "sg:province":"CA",
    "sg:tags":[
        "radiology"
    ],
    "wof:name":"Lee Hall",
    "wof:placetype":"venue"
},
  "geometry": {"coordinates":[-117.04374900000001,32.751566],"type":"Point"}
}