{
  "type": "Feature",
  "properties": {
    "addr:full":"140 University Ave Palo Alto CA 94301",
    "addr:housenumber":"140",
    "addr:postcode":"94301",
    "addr:street":"University Ave",
    "iso:country":"US",
    "sg:address":"140 University Ave",
    "sg:city":"Palo Alto",
    "sg:classifiers":[
        {
            "category":"Sports & Exercise",
            "subcategory":"Gym",
            "type":"Entertainment"
        }
    ],
    "sg:phone":"+1 650 851 8923",
    "sg:postcode":"94301",
    "sg:province":"CA",
    "sg:tags":[
        "personal",
        "trainer"
    ],
    "wof:name":"Workouts On Wheels",
    "wof:placetype":"venue"
},
  "geometry": {"coordinates":[-122.16359199999999,37.443681],"type":"Point"}
}