{
  "type": "Feature",
  "properties": {
    "iso:country":"US",
    "sg:address":"587 Canyon Rd",
    "sg:city":"Redwood City",
    "sg:classifiers":[
        {
            "category":"Restaurant",
            "type":"Food & Drink"
        }
    ],
    "sg:phone":"+1 650 369 1646",
    "sg:postcode":"94062",
    "sg:province":"CA",
    "wof:name":"Canyon Inn",
    "wof:placetype":"venue"
},
  "geometry": {"coordinates":[-122.25966,37.472315],"type":"Point"}
}