{
  "type": "Feature",
  "properties": {
    "iso:country":"US",
    "sg:address":"4808 Melrose Ave",
    "sg:city":"Los Angeles",
    "sg:classifiers":[
        {
            "category":"Restaurant",
            "type":"Food & Drink"
        }
    ],
    "sg:phone":"+1 323 669 1180",
    "sg:postcode":"90029",
    "sg:province":"CA",
    "sg:website":"www.bbqunlimited.com/",
    "wof:name":"BBQ Unlimited",
    "wof:placetype":"venue"
},
  "geometry": {"coordinates":[-118.304754,34.083491],"type":"Point"}
}