{
  "type": "Feature",
  "properties": {
    "iso:country":"US",
    "sg:address":"1001 2nd St",
    "sg:city":"Napa",
    "sg:classifiers":[
        {
            "category":"Restaurant",
            "type":"Food & Drink"
        }
    ],
    "sg:menulink":"http://www.allmenus.com/ca/napa/48221-peking-palace/menu/",
    "sg:phone":"+1 707 257 7197",
    "sg:postcode":"94559",
    "sg:province":"CA",
    "sg:tags":[
        "asian",
        "chinese"
    ],
    "wof:name":"Peking Palace",
    "wof:placetype":"venue"
},
  "geometry": {"coordinates":[-122.285464,38.298218],"type":"Point"}
}