{
  "type": "Feature",
  "properties": {
    "iso:country":"US",
    "sg:address":"537 Seabright Ave",
    "sg:city":"Santa Cruz",
    "sg:classifiers":[
        {
            "category":"Restaurant",
            "type":"Food & Drink"
        }
    ],
    "sg:phone":"+1 831 429 1856",
    "sg:postcode":"95062",
    "sg:province":"CA",
    "sg:tags":[
        "pizza"
    ],
    "sg:website":"www.engferpizzaworks.com",
    "wof:name":"Engfer Pizza Works",
    "wof:placetype":"venue"
},
  "geometry": {"coordinates":[-122.008003,36.968201],"type":"Point"}
}