{
  "type": "Feature",
  "properties": {
    "addr:full":"6273 Skittone Rd Modesto CA 95356",
    "addr:housenumber":"6273",
    "addr:postcode":"ca 95356",
    "addr:street":"Skittone Rd",
    "iso:country":"US",
    "sg:address":"6273 Skittone Rd",
    "sg:city":"Modesto",
    "sg:classifiers":[
        {
            "category":"Farming",
            "subcategory":"Crops",
            "type":"Manufacturing & Wholesale Goods"
        }
    ],
    "sg:phone":"+1 209 523 0264",
    "sg:postcode":"95356",
    "sg:province":"CA",
    "sg:tags":[
        "grove",
        "nut",
        "tree"
    ],
    "wof:name":"Richard Mason",
    "wof:placetype":"venue"
},
  "geometry": {"coordinates":[-120.984861,37.719542],"type":"Point"}
}