{
  "type": "Feature",
  "properties": {
    "addr:full":"2310 W Whitendale Ave Visalia CA 93277",
    "addr:housenumber":"2310",
    "addr:postcode":"93277",
    "addr:street":"W Whitendale Ave",
    "iso:country":"US",
    "sg:address":"2310 W Whitendale Ave",
    "sg:city":"Visalia",
    "sg:classifiers":[
        {
            "category":"Health Services",
            "subcategory":"Dentist",
            "type":"Services"
        }
    ],
    "sg:phone":"+1 559 732 4543",
    "sg:postcode":"93277",
    "sg:province":"CA",
    "sg:tags":[
        "product",
        "dentists-cosmetic",
        "dentistry",
        "whitening",
        "teeth",
        "implant",
        "dentists-orthodontists",
        "dentists-implantology"
    ],
    "sg:website":"http://www.erikswansondmd.com",
    "wof:name":"Swanson Erik DMD",
    "wof:placetype":"venue"
},
  "geometry": {"coordinates":[-119.31589700000001,36.305758],"type":"Point"}
}