{
  "type": "Feature",
  "properties": {
    "addr:full":"2350 W Shaw Ave Fresno CA 93711",
    "addr:housenumber":"2350",
    "addr:postcode":"93711",
    "addr:street":"W Shaw Ave",
    "iso:country":"US",
    "sg:address":"2350 W Shaw Ave",
    "sg:city":"Fresno",
    "sg:classifiers":[
        {
            "category":"Building & Trades",
            "subcategory":"Equipment Rental",
            "type":"Services"
        }
    ],
    "sg:phone":"+1 559 438 7100",
    "sg:postcode":"93711",
    "sg:province":"CA",
    "sg:tags":[
        "leasing"
    ],
    "sg:website":"www.comlease.com",
    "wof:name":"Comlease USA",
    "wof:placetype":"venue"
},
  "geometry": {"coordinates":[-119.834142,36.808362],"type":"Point"}
}