{
  "type": "Feature",
  "properties": {
    "iso:country":"US",
    "sg:address":"2550 Wardlow Rd",
    "sg:city":"Corona",
    "sg:classifiers":[
        {
            "category":"Retail",
            "subcategory":"Auto Rental",
            "type":"Services"
        }
    ],
    "sg:phone":"+1 951 270 0170",
    "sg:postcode":"92882",
    "sg:province":"CA",
    "sg:tags":[
        "passenger",
        "car"
    ],
    "wof:name":"Enterprise Rent-A-Car",
    "wof:placetype":"venue"
},
  "geometry": {"coordinates":[-117.612793,33.882155],"type":"Point"}
}