{
  "type": "Feature",
  "properties": {
    "iso:country":"US",
    "sg:address":"3451 E Coast Hwy",
    "sg:city":"Corona Del Mar",
    "sg:classifiers":[
        {
            "category":"Personal",
            "subcategory":"Nail Salon",
            "type":"Services"
        }
    ],
    "sg:phone":"+1 949 673 9530",
    "sg:postcode":"92625",
    "sg:province":"CA",
    "wof:name":"Make Up & Skin Care",
    "wof:placetype":"venue"
},
  "geometry": {"coordinates":[-117.869463,33.595279],"type":"Point"}
}