{
  "type": "Feature",
  "properties": {
    "addr:full":"1922 N Arthur Ave Fresno CA 93705",
    "addr:housenumber":"1922",
    "addr:postcode":"93705",
    "addr:street":"N Arthur Ave",
    "iso:country":"US",
    "sg:address":"1922 N Arthur Ave",
    "sg:city":"Fresno",
    "sg:classifiers":[
        {
            "category":"Professional",
            "type":"Services"
        }
    ],
    "sg:phone":"+1 559 779 1633",
    "sg:postcode":"93705",
    "sg:province":"CA",
    "sg:tags":[
        "caterer"
    ],
    "wof:name":"Ochineros Catering",
    "wof:placetype":"venue"
},
  "geometry": {"coordinates":[-119.815383,36.767777],"type":"Point"}
}