{
  "type": "Feature",
  "properties": {
    "addr:full":"1703 Bruce Dr Anderson CA 96007",
    "addr:housenumber":"1703",
    "addr:postcode":"96007",
    "addr:street":"Bruce Dr",
    "iso:country":"US",
    "sg:address":"1703 Bruce Dr",
    "sg:city":"Anderson",
    "sg:classifiers":[
        {
            "category":"Restaurant",
            "type":"Food & Drink"
        }
    ],
    "sg:phone":"+1 530 365 5988",
    "sg:postcode":"96007",
    "sg:province":"CA",
    "sg:tags":[
        "eating"
    ],
    "wof:name":"Oriental Express",
    "wof:placetype":"venue"
},
  "geometry": {"coordinates":[-122.29637700000001,40.444073],"type":"Point"}
}