{
  "type": "Feature",
  "properties": {
    "iso:country":"US",
    "sg:address":"1077 S Green Valley Rd",
    "sg:city":"Watsonville",
    "sg:classifiers":[
        {
            "category":"Retail",
            "subcategory":"Laundry & Dry Cleaning",
            "type":"Services"
        }
    ],
    "sg:phone":"+1 831 722 7361",
    "sg:postcode":"95076",
    "sg:province":"CA",
    "wof:name":"Launderland Coin-Op",
    "wof:placetype":"venue"
},
  "geometry": {"coordinates":[-121.78441100000001,36.917232],"type":"Point"}
}