{
  "type": "Feature",
  "properties": {
    "addr:full":"25108 Marguerite Pkwy Mission Viejo CA 92692",
    "addr:housenumber":"25108",
    "addr:postcode":"92692",
    "addr:street":"Marguerite Pkwy",
    "iso:country":"US",
    "sg:address":"25108 Marguerite Pkwy",
    "sg:city":"Mission Viejo",
    "sg:classifiers":[
        {
            "category":"Professional",
            "subcategory":"Business Services",
            "type":"Services"
        }
    ],
    "sg:phone":"+1 949 454 1942",
    "sg:postcode":"92692",
    "sg:province":"CA",
    "wof:name":"Creative Benefit Solutions",
    "wof:placetype":"venue"
},
  "geometry": {"coordinates":[-117.657624,33.597868],"type":"Point"}
}