{
  "type": "Feature",
  "properties": {
    "iso:country":"US",
    "sg:address":"Portland Ave and Carmel Ave",
    "sg:city":"Albany",
    "sg:classifiers":[
        {
            "category":"Park",
            "type":"Public Place"
        }
    ],
    "sg:postcode":"94706",
    "sg:province":"CA",
    "wof:name":"Veterans Memorial Park",
    "wof:placetype":"venue"
},
  "geometry": {"coordinates":[-122.29002,37.894831],"type":"Point"}
}