{
  "type": "Feature",
  "properties": {
    "addr:full":"50 E 4th St Long Beach CA 90802",
    "addr:housenumber":"50",
    "addr:postcode":"90802",
    "addr:street":"E 4Th St",
    "iso:country":"US",
    "sg:address":"50 E 4th St",
    "sg:city":"Long Beach",
    "sg:classifiers":[
        {
            "category":"Shopping",
            "subcategory":"Clothing, Apparel, & Fashions",
            "type":"Retail Goods"
        }
    ],
    "sg:phone":"+1 562 435 2307",
    "sg:postcode":"90802",
    "sg:province":"CA",
    "sg:tags":[
        "men's",
        "clothing"
    ],
    "wof:name":"Abbani Men's Wear",
    "wof:placetype":"venue"
},
  "geometry": {"coordinates":[-118.191936,33.771718],"type":"Point"}
}