{
  "type": "Feature",
  "properties": {
    "iso:country":"US",
    "sg:address":"1203 Carpenter Canyon Rd",
    "sg:city":"Arroyo Grande",
    "sg:classifiers":[
        {
            "category":"Real Estate",
            "subcategory":"Surveying",
            "type":"Services"
        }
    ],
    "sg:phone":"+1 805 489 6647",
    "sg:postcode":"93420",
    "sg:province":"CA",
    "sg:tags":[
        "surveyor"
    ],
    "wof:name":"Jensen-Lenger Surveys",
    "wof:placetype":"venue"
},
  "geometry": {"coordinates":[-120.577111,35.155551],"type":"Point"}
}