{
  "type": "Feature",
  "properties": {
    "addr:full":"1075 Sutter St San Francisco CA 94109",
    "addr:housenumber":"1075",
    "addr:postcode":"94109",
    "addr:street":"Sutter St",
    "iso:country":"US",
    "sg:address":"1075 Sutter St",
    "sg:city":"San Francisco",
    "sg:classifiers":[
        {
            "category":"Travel",
            "subcategory":"Hotels & Motels",
            "type":"Entertainment"
        }
    ],
    "sg:phone":"+1 415 673 0242",
    "sg:postcode":"94109",
    "sg:province":"CA",
    "sg:website":"www.hotelcarltonsf.com",
    "wof:name":"Hotel Carlton",
    "wof:placetype":"venue"
},
  "geometry": {"coordinates":[-122.417967,37.787926],"type":"Point"}
}