{
  "type": "Feature",
  "properties": {
    "iso:country":"US",
    "sg:address":"6452 Farallon Way",
    "sg:city":"Oakland",
    "sg:classifiers":[
        {
            "category":"Communications",
            "type":"Services"
        }
    ],
    "sg:phone":"+1 510 654 5702",
    "sg:postcode":"94611",
    "sg:province":"CA",
    "sg:tags":[
        "communication"
    ],
    "wof:name":"Pierce Communications",
    "wof:placetype":"venue"
},
  "geometry": {"coordinates":[-122.213428,37.846732],"type":"Point"}
}