{
  "type": "Feature",
  "properties": {
    "addr:full":"2107 N 1st Street San Jose CA 95131",
    "addr:housenumber":"2107",
    "addr:postcode":"95131",
    "addr:street":"N 1St Street",
    "iso:country":"US",
    "sg:address":"2107 N 1st Street",
    "sg:city":"San Jose",
    "sg:classifiers":[
        {
            "category":"Real Estate",
            "subcategory":"Real Estate Services",
            "type":"Services"
        }
    ],
    "sg:phone":"+1 408 441 9336",
    "sg:postcode":"95131",
    "sg:province":"CA",
    "sg:tags":[
        "management",
        "property"
    ],
    "wof:name":"Bayshore Plaza",
    "wof:placetype":"venue"
},
  "geometry": {"coordinates":[-121.919608,37.374854],"type":"Point"}
}