{
  "type": "Feature",
  "properties": {
    "addr:full":"9820 Bonnie Vista Dr La Mesa CA 91941",
    "addr:housenumber":"9820",
    "addr:postcode":"91941",
    "addr:street":"Bonnie Vista Dr",
    "iso:country":"US",
    "sg:address":"9820 Bonnie Vista Dr",
    "sg:city":"La Mesa",
    "sg:classifiers":[
        {
            "category":"Insurance",
            "subcategory":"Insurance Agent",
            "type":"Services"
        }
    ],
    "sg:phone":"+1 619 670 5228",
    "sg:postcode":"91941",
    "sg:province":"CA",
    "wof:name":"Bond Professional Surety Ins",
    "wof:placetype":"venue"
},
  "geometry": {"coordinates":[-116.983484,32.756177],"type":"Point"}
}