{
  "type": "Feature",
  "properties": {
    "addr:full":"2536 Wah Ave Sacramento CA 95822",
    "addr:housenumber":"2536",
    "addr:postcode":"95822",
    "addr:street":"Wah Ave",
    "iso:country":"US",
    "sg:address":"2536 Wah Ave",
    "sg:city":"Sacramento",
    "sg:classifiers":[
        {
            "category":"Real Estate",
            "subcategory":"Real Estate Operator",
            "type":"Services"
        }
    ],
    "sg:phone":"+1 916 428 4530",
    "sg:postcode":"95822",
    "sg:province":"CA",
    "sg:tags":[
        "apartment"
    ],
    "wof:name":"Florin Gardens Co-Op East No 2",
    "wof:placetype":"venue"
},
  "geometry": {"coordinates":[-121.480003,38.501202],"type":"Point"}
}