{
  "type": "Feature",
  "properties": {
    "iso:country":"US",
    "sg:address":"265 Cypress Avenue",
    "sg:city":"Santa Clara",
    "sg:classifiers":[
        {
            "category":"Building & Trades",
            "subcategory":"Landscaping Services",
            "type":"Services"
        }
    ],
    "sg:phone":"+1 408 247 4870",
    "sg:postcode":"95050",
    "sg:province":"CA",
    "wof:name":"Best Green Landscape Maintenance",
    "wof:placetype":"venue"
},
  "geometry": {"coordinates":[-121.960016,37.32753],"type":"Point"}
}