{
  "type": "Feature",
  "properties": {
    "addr:full":"25920 Belle Porte Ave Harbor City CA 90710",
    "addr:housenumber":"25920",
    "addr:postcode":"90710",
    "addr:street":"Belle Porte Ave",
    "iso:country":"US",
    "sg:address":"25920 Belle Porte Ave",
    "sg:city":"Harbor City",
    "sg:classifiers":[
        {
            "category":"Manufacturing",
            "subcategory":"Wood Products",
            "type":"Manufacturing & Wholesale Goods"
        }
    ],
    "sg:phone":"+1 310 891 2040",
    "sg:postcode":"90710",
    "sg:province":"CA",
    "sg:tags":[
        "basket"
    ],
    "sg:website":"www.marintl.com",
    "wof:name":"Mar International Trading Corp",
    "wof:placetype":"venue"
},
  "geometry": {"coordinates":[-118.30109899999999,33.787115],"type":"Point"}
}