{
  "type": "Feature",
  "properties": {
    "iso:country":"US",
    "sg:address":"14771 Washington Dr",
    "sg:city":"Fontana",
    "sg:classifiers":[
        {
            "category":"Professional",
            "subcategory":"Engineering",
            "type":"Services"
        }
    ],
    "sg:phone":"+1 909 427 1177",
    "sg:postcode":"92335",
    "sg:province":"CA",
    "sg:tags":[
        "general",
        "contractor"
    ],
    "wof:name":"4-Con Engineering Inc",
    "wof:placetype":"venue"
},
  "geometry": {"coordinates":[-117.481391,34.067041],"type":"Point"}
}