{
  "type": "Feature",
  "properties": {
    "addr:full":"6800 Balfour Rd Brentwood CA 94513",
    "addr:housenumber":"6800",
    "addr:postcode":"ca 94513",
    "addr:street":"Balfour Rd",
    "iso:country":"US",
    "sg:address":"6800 Balfour Rd",
    "sg:city":"Brentwood",
    "sg:classifiers":[
        {
            "category":"Building & Trades",
            "subcategory":"Construction",
            "type":"Services"
        }
    ],
    "sg:phone":"+1 925 513 0440",
    "sg:postcode":"94513",
    "sg:province":"CA",
    "sg:tags":[
        "water",
        "well",
        "drilling"
    ],
    "wof:name":"Pacific Coast Drilling",
    "wof:placetype":"venue"
},
  "geometry": {"coordinates":[-121.654931,37.925556],"type":"Point"}
}