{
  "type": "Feature",
  "properties": {
    "addr:full":"1700 Standiford Ave Ste 240 Modesto CA 95350",
    "addr:housenumber":"1700",
    "addr:postcode":"ca 95350",
    "addr:street":"Standiford Ave Ste 240",
    "iso:country":"US",
    "sg:address":"1700 Standiford Ave Ste 240",
    "sg:city":"Modesto",
    "sg:classifiers":[
        {
            "category":"Professional",
            "subcategory":"Lawyer & Legal Services",
            "type":"Services"
        }
    ],
    "sg:phone":"+1 209 476 0522",
    "sg:postcode":"95350",
    "sg:province":"CA",
    "wof:name":"Mastache Jorge Attorney At Law",
    "wof:placetype":"venue"
},
  "geometry": {"coordinates":[-121.008003,37.673801],"type":"Point"}
}