{
  "type": "Feature",
  "properties": {
    "iso:country":"US",
    "sg:address":"21001 Mission Blvd",
    "sg:city":"Hayward",
    "sg:classifiers":[
        {
            "category":"Personal",
            "subcategory":"Beauty Salon",
            "type":"Services"
        }
    ],
    "sg:phone":"+1 510 317 8011",
    "sg:postcode":"94541",
    "sg:province":"CA",
    "sg:tags":[
        "hair"
    ],
    "wof:name":"Luz Hair Salon",
    "wof:placetype":"venue"
},
  "geometry": {"coordinates":[-122.097992,37.683484],"type":"Point"}
}