{
  "type": "Feature",
  "properties": {
    "addr:full":"2025 Long Beach Ave W Los Angeles CA 90058",
    "addr:housenumber":"2025",
    "addr:postcode":"90058",
    "addr:street":"Long Beach Ave W",
    "iso:country":"US",
    "sg:address":"2025 Long Beach Ave W",
    "sg:city":"Los Angeles",
    "sg:classifiers":[
        {
            "category":"Wholesale",
            "subcategory":"Apparel",
            "type":"Manufacturing & Wholesale Goods"
        }
    ],
    "sg:phone":"+1 213 765 5090",
    "sg:postcode":"90058",
    "sg:province":"CA",
    "sg:tags":[
        "clothing"
    ],
    "wof:name":"Steps of Apparel",
    "wof:placetype":"venue"
},
  "geometry": {"coordinates":[-118.24328300000001,34.016895],"type":"Point"}
}