{
  "type": "Feature",
  "properties": {
    "addr:full":"4858 W Century Blvd Inglewood CA 90304",
    "addr:housenumber":"4858",
    "addr:postcode":"90304",
    "addr:street":"W Century Blvd",
    "iso:country":"US",
    "sg:address":"4858 W Century Blvd",
    "sg:city":"Inglewood",
    "sg:classifiers":[
        {
            "category":"Retail",
            "subcategory":"Auto Rental",
            "type":"Services"
        }
    ],
    "sg:phone":"+1 310 641 7002",
    "sg:postcode":"90304",
    "sg:province":"CA",
    "sg:tags":[
        "car"
    ],
    "wof:name":"Lax Rent-A-Car",
    "wof:placetype":"venue"
},
  "geometry": {"coordinates":[-118.363438,33.945247],"type":"Point"}
}