{
  "type": "Feature",
  "properties": {
    "addr:full":"840 Towne Center Dr Pomona CA 91767",
    "addr:housenumber":"840",
    "addr:postcode":"91767",
    "addr:street":"Towne Center Dr",
    "iso:country":"US",
    "sg:address":"840 Towne Center Dr",
    "sg:city":"Pomona",
    "sg:classifiers":[
        {
            "category":"Wholesale",
            "subcategory":"Auto Parts",
            "type":"Manufacturing & Wholesale Goods"
        }
    ],
    "sg:phone":"+1 909 398 1550",
    "sg:postcode":"91767",
    "sg:province":"CA",
    "sg:tags":[
        "accessories-wholesale",
        "equipment",
        "truck",
        "manufacturer"
    ],
    "wof:name":"Resources",
    "wof:placetype":"venue"
},
  "geometry": {"coordinates":[-117.733124,34.092412],"type":"Point"}
}