{
  "type": "Feature",
  "properties": {
    "addr:full":"5264 Austin Rd Santa Barbara CA 93111",
    "addr:housenumber":"5264",
    "addr:postcode":"93111",
    "addr:street":"Austin Rd",
    "iso:country":"US",
    "sg:address":"5264 Austin Rd",
    "sg:city":"Santa Barbara",
    "sg:classifiers":[
        {
            "category":"Travel",
            "subcategory":"Travel Agent",
            "type":"Entertainment"
        }
    ],
    "sg:phone":"+1 805 692 2146",
    "sg:postcode":"93111",
    "sg:province":"CA",
    "sg:tags":[
        "agency",
        "bureau"
    ],
    "wof:name":"Just Travel",
    "wof:placetype":"venue"
},
  "geometry": {"coordinates":[-119.805424,34.418174],"type":"Point"}
}