{
  "type": "Feature",
  "properties": {
    "addr:full":"4275 Rosewood Dr Pleasanton CA 94588",
    "addr:housenumber":"4275",
    "addr:postcode":"94588",
    "addr:street":"Rosewood Dr",
    "iso:country":"US",
    "sg:address":"4275 Rosewood Dr",
    "sg:city":"Pleasanton",
    "sg:classifiers":[
        {
            "category":"Restaurant",
            "type":"Food & Drink"
        }
    ],
    "sg:menulink":"http://www.allmenus.com/ca/livermore-pleasanton/46599-korea-garden/menu/",
    "sg:phone":"+1 925 463 0551",
    "sg:postcode":"94588",
    "sg:province":"CA",
    "sg:tags":[
        "korean",
        "asian"
    ],
    "wof:name":"Korea Garden",
    "wof:placetype":"venue"
},
  "geometry": {"coordinates":[-121.876192,37.700548],"type":"Point"}
}