{
  "type": "Feature",
  "properties": {
    "addr:full":"2800 N Main St Santa Ana CA 92705",
    "addr:housenumber":"2800",
    "addr:postcode":"92705",
    "addr:street":"N Main St",
    "iso:country":"US",
    "sg:address":"2800 N Main St",
    "sg:city":"Santa Ana",
    "sg:classifiers":[
        {
            "category":"Restaurant",
            "type":"Food & Drink"
        }
    ],
    "sg:menulink":"http://www.allmenus.com/ca/anaheim-santa-ana-garden-grove/216285-mcdonalds/menu/",
    "sg:postcode":"92705",
    "sg:province":"CA",
    "sg:tags":[
        "burger",
        "american"
    ],
    "wof:name":"McDonald's",
    "wof:placetype":"venue"
},
  "geometry": {"coordinates":[-117.869174,33.776339],"type":"Point"}
}