{
  "type": "Feature",
  "properties": {
    "iso:country":"US",
    "sg:address":"419 Adams St",
    "sg:city":"Bakersfield",
    "sg:classifiers":[
        {
            "category":"Building & Trades",
            "subcategory":"Construction",
            "type":"Services"
        }
    ],
    "sg:phone":"+1 661 832 2056",
    "sg:postcode":"93307",
    "sg:province":"CA",
    "sg:tags":[
        "painter"
    ],
    "wof:name":"D & B Painting & Cleaning",
    "wof:placetype":"venue"
},
  "geometry": {"coordinates":[-118.99424999999999,35.343549],"type":"Point"}
}