{
  "type": "Feature",
  "properties": {
    "addr:full":"555 California St San Francisco CA 94104",
    "addr:housenumber":"555",
    "addr:postcode":"94104",
    "addr:street":"California St",
    "iso:country":"US",
    "sg:address":"555 California St",
    "sg:city":"San Francisco",
    "sg:classifiers":[
        {
            "category":"Professional",
            "subcategory":"Research",
            "type":"Services"
        }
    ],
    "sg:phone":"+1 415 953 0223",
    "sg:postcode":"94104",
    "sg:province":"CA",
    "sg:tags":[
        "risk",
        "general"
    ],
    "wof:name":"Risk & Capital Analysis",
    "wof:placetype":"venue"
},
  "geometry": {"coordinates":[-122.40436699999999,37.792571],"type":"Point"}
}