{
  "type": "Feature",
  "properties": {
    "iso:country":"US",
    "sg:address":"13220 E Imperial Hwy",
    "sg:city":"Santa Fe Springs",
    "sg:classifiers":[
        {
            "category":"Restaurant",
            "type":"Food & Drink"
        }
    ],
    "sg:phone":"+1 562 404 5599",
    "sg:postcode":"90670",
    "sg:province":"CA",
    "sg:tags":[
        "traditional",
        "american"
    ],
    "sg:website":"www.farmerboys.com",
    "wof:name":"FarmerBoys",
    "wof:placetype":"venue"
},
  "geometry": {"coordinates":[-118.051143,33.916761],"type":"Point"}
}