{
  "type": "Feature",
  "properties": {
    "iso:country":"US",
    "sg:address":"5000 Willows Rd",
    "sg:city":"Alpine",
    "sg:classifiers":[
        {
            "category":"Recreation",
            "type":"Entertainment"
        }
    ],
    "sg:phone":"+1 619 445 5400",
    "sg:postcode":"91901",
    "sg:province":"CA",
    "sg:tags":[
        "eating"
    ],
    "wof:name":"Viejas Casino and Turf Club",
    "wof:placetype":"venue"
},
  "geometry": {"coordinates":[-116.701596,32.842177],"type":"Point"}
}