{
  "type": "Feature",
  "properties": {
    "addr:full":"8295 Fruitridge Rd Sacramento CA 95826",
    "addr:housenumber":"8295",
    "addr:postcode":"95826",
    "addr:street":"Fruitridge Rd",
    "iso:country":"US",
    "sg:address":"8295 Fruitridge Rd",
    "sg:city":"Sacramento",
    "sg:classifiers":[
        {
            "category":"Sports & Exercise",
            "subcategory":"Golf",
            "type":"Entertainment"
        }
    ],
    "sg:phone":"+1 916 386 8477",
    "sg:postcode":"95826",
    "sg:province":"CA",
    "sg:tags":[
        "course"
    ],
    "wof:name":"Golf Smith",
    "wof:placetype":"venue"
},
  "geometry": {"coordinates":[-121.400886,38.525186],"type":"Point"}
}