{
  "type": "Feature",
  "properties": {
    "iso:country":"US",
    "sg:address":"2550 S Santa Fe Ave",
    "sg:city":"Vista",
    "sg:classifiers":[
        {
            "category":"Wholesale",
            "subcategory":"Machinery & Supplies",
            "type":"Manufacturing & Wholesale Goods"
        }
    ],
    "sg:phone":"+1 760 727 2300",
    "sg:postcode":"92084",
    "sg:province":"CA",
    "sg:tags":[
        "cargo",
        "container",
        "freight"
    ],
    "wof:name":"Aztec Technology Corp",
    "wof:placetype":"venue"
},
  "geometry": {"coordinates":[-117.20522099999999,33.16499],"type":"Point"}
}