{
  "type": "Feature",
  "properties": {
    "addr:full":"4713 1st St Pleasanton CA 94566",
    "addr:housenumber":"4713",
    "addr:postcode":"94566",
    "addr:street":"1St St",
    "iso:country":"US",
    "sg:address":"4713 1st St",
    "sg:city":"Pleasanton",
    "sg:classifiers":[
        {
            "category":"Professional",
            "subcategory":"Computer Services",
            "type":"Services"
        }
    ],
    "sg:phone":"+1 925 426 2322",
    "sg:postcode":"94566",
    "sg:province":"CA",
    "sg:tags":[
        "information",
        "technology"
    ],
    "wof:name":"Tanis Information Systems",
    "wof:placetype":"venue"
},
  "geometry": {"coordinates":[-121.87741,37.656556],"type":"Point"}
}