{
  "type": "Feature",
  "properties": {
    "addr:full":"450 Rosewood Ave Camarillo CA 93010",
    "addr:housenumber":"450",
    "addr:postcode":"93010",
    "addr:street":"Rosewood Ave",
    "iso:country":"US",
    "sg:address":"450 Rosewood Ave",
    "sg:city":"Camarillo",
    "sg:classifiers":[
        {
            "category":"Banks & Credit Unions",
            "subcategory":"Investment Brokerage",
            "type":"Services"
        }
    ],
    "sg:phone":"+1 805 389 9100",
    "sg:postcode":"93010",
    "sg:province":"CA",
    "sg:tags":[
        "investing"
    ],
    "wof:name":"John N Manocchio Cfp",
    "wof:placetype":"venue"
},
  "geometry": {"coordinates":[-119.06199599999999,34.221298],"type":"Point"}
}