{
  "type": "Feature",
  "properties": {
    "iso:country":"US",
    "sg:address":"6520 Chiquita Way",
    "sg:city":"Carmichael",
    "sg:classifiers":[
        {
            "category":"Building & Trades",
            "subcategory":"Electrical",
            "type":"Services"
        }
    ],
    "sg:phone":"+1 916 971 4111",
    "sg:postcode":"95608",
    "sg:province":"CA",
    "sg:tags":[
        "electrical",
        "contractor"
    ],
    "wof:name":"Conover Electric",
    "wof:placetype":"venue"
},
  "geometry": {"coordinates":[-121.31357199999999,38.621094],"type":"Point"}
}