{
  "type": "Feature",
  "properties": {
    "iso:country":"US",
    "sg:address":"240 S Beverly Dr",
    "sg:city":"Beverly Hills",
    "sg:classifiers":[
        {
            "category":"Food & Beverages",
            "subcategory":"Dairy",
            "type":"Retail Goods"
        }
    ],
    "sg:phone":"+1 310 275 0760",
    "sg:postcode":"90212",
    "sg:province":"CA",
    "sg:tags":[
        "yogurt"
    ],
    "wof:name":"Mrs Fields-Tcby",
    "wof:placetype":"venue"
},
  "geometry": {"coordinates":[-118.39899699999999,34.063344],"type":"Point"}
}