{
  "type": "Feature",
  "properties": {
    "iso:country":"US",
    "sg:address":"250 Napoleon St",
    "sg:city":"San Francisco",
    "sg:classifiers":[
        {
            "category":"Retail",
            "subcategory":"Auto Repair",
            "type":"Services"
        }
    ],
    "sg:phone":"+1 415 821 4745",
    "sg:postcode":"94124",
    "sg:province":"CA",
    "sg:tags":[
        "body",
        "automobile",
        "painting"
    ],
    "wof:name":"AJC Auto Body",
    "wof:placetype":"venue"
},
  "geometry": {"coordinates":[-122.397802,37.747188],"type":"Point"}
}