{
  "type": "Feature",
  "properties": {
    "addr:full":"2856 Vail Ave Los Angeles CA 90040",
    "addr:housenumber":"2856",
    "addr:postcode":"90040",
    "addr:street":"Vail Ave",
    "iso:country":"US",
    "sg:address":"2856 Vail Ave",
    "sg:city":"Los Angeles",
    "sg:classifiers":[
        {
            "category":"Wholesale",
            "subcategory":"Stationery",
            "type":"Manufacturing & Wholesale Goods"
        }
    ],
    "sg:phone":"+1 323 728 2680",
    "sg:postcode":"90040",
    "sg:province":"CA",
    "sg:tags":[
        "directory",
        "bulletin",
        "boards"
    ],
    "sg:website":"www.a-1visuals.com",
    "wof:name":"A-1 Visual Systems",
    "wof:placetype":"venue"
},
  "geometry": {"coordinates":[-118.13130200000001,33.990601],"type":"Point"}
}