{
  "type": "Feature",
  "properties": {
    "iso:country":"US",
    "sg:address":"2509 W Empire Ave",
    "sg:city":"Burbank",
    "sg:classifiers":[
        {
            "category":"Manufacturing",
            "subcategory":"Printing",
            "type":"Manufacturing & Wholesale Goods"
        }
    ],
    "sg:phone":"+1 818 953 8730",
    "sg:postcode":"91504",
    "sg:province":"CA",
    "sg:tags":[
        "publisher"
    ],
    "wof:name":"Bicycling Magazine",
    "wof:placetype":"venue"
},
  "geometry": {"coordinates":[-118.339005,34.191954],"type":"Point"}
}