{
  "type": "Feature",
  "properties": {
    "addr:full":"1810 Gillespie Way El Cajon CA 92020",
    "addr:housenumber":"1810",
    "addr:postcode":"92020",
    "addr:street":"Gillespie Way",
    "iso:country":"US",
    "sg:address":"1810 Gillespie Way",
    "sg:city":"El Cajon",
    "sg:classifiers":[
        {
            "category":"Professional",
            "subcategory":"Computer Services",
            "type":"Services"
        }
    ],
    "sg:phone":"+1 619 449 1200",
    "sg:postcode":"92020",
    "sg:province":"CA",
    "sg:tags":[
        "repair"
    ],
    "wof:name":"Cbl Data Recovery Technology Inc",
    "wof:placetype":"venue"
},
  "geometry": {"coordinates":[-116.981003,32.819302],"type":"Point"}
}