{
  "type": "Feature",
  "properties": {
    "iso:country":"US",
    "sg:address":"95 Fremont Street",
    "sg:city":"San Francisco",
    "sg:classifiers":[
        {
            "category":"Professional",
            "type":"Services"
        },
        {
            "category":"Deli",
            "type":"Food & Drink"
        }
    ],
    "sg:phone":"+1 415 371 9595",
    "sg:postcode":"94105",
    "sg:province":"CA",
    "sg:tags":[
        "caterer"
    ],
    "wof:name":"Lee's Deli",
    "wof:placetype":"venue"
},
  "geometry": {"coordinates":[-122.396004,37.790401],"type":"Point"}
}