{
  "type": "Feature",
  "properties": {
    "addr:full":"2122 S Central Ave Los Angeles CA 90011",
    "addr:housenumber":"2122",
    "addr:postcode":"90011",
    "addr:street":"S Central Ave",
    "iso:country":"US",
    "sg:address":"2122 S Central Ave",
    "sg:city":"Los Angeles",
    "sg:classifiers":[
        {
            "category":"Shopping",
            "subcategory":"Discount & Variety Stores",
            "type":"Retail Goods"
        }
    ],
    "sg:phone":"+1 213 748 3599",
    "sg:postcode":"90011",
    "sg:province":"CA",
    "wof:name":"Veronica Novedades Store",
    "wof:placetype":"venue"
},
  "geometry": {"coordinates":[-118.25305,34.021605],"type":"Point"}
}