{
  "type": "Feature",
  "properties": {
    "iso:country":"US",
    "sg:address":"623 Davis St",
    "sg:city":"Exeter",
    "sg:classifiers":[
        {
            "category":"Freight",
            "type":"Transportation"
        }
    ],
    "sg:phone":"+1 559 592 1272",
    "sg:postcode":"93221",
    "sg:province":"CA",
    "sg:tags":[
        "operator",
        "trucking"
    ],
    "wof:name":"A Rivas Trucking",
    "wof:placetype":"venue"
},
  "geometry": {"coordinates":[-119.149314,36.286043],"type":"Point"}
}