{
  "type": "Feature",
  "properties": {
    "iso:country":"US",
    "sg:address":"2540 E Alondra Boulevard",
    "sg:city":"Compton",
    "sg:classifiers":[
        {
            "category":"Personal",
            "subcategory":"Nail Salon",
            "type":"Services"
        }
    ],
    "sg:phone":"+1 310 763 2712",
    "sg:postcode":"90221",
    "sg:province":"CA",
    "wof:name":"Pro Nails",
    "wof:placetype":"venue"
},
  "geometry": {"coordinates":[-118.195824,33.888627],"type":"Point"}
}