{
  "type": "Feature",
  "properties": {
    "iso:country":"US",
    "sg:address":"25692 Atlantic Ocean Dr",
    "sg:city":"Lake Forest",
    "sg:classifiers":[
        {
            "category":"Professional",
            "type":"Services"
        }
    ],
    "sg:phone":"+1 949 583 9204",
    "sg:postcode":"92630",
    "sg:province":"CA",
    "wof:name":"Qualis International",
    "wof:placetype":"venue"
},
  "geometry": {"coordinates":[-117.675902,33.666531],"type":"Point"}
}