{
  "type": "Feature",
  "properties": {
    "iso:country":"US",
    "sg:address":"1300 Stroud Ave",
    "sg:city":"Kingsburg",
    "sg:classifiers":[
        {
            "category":"Education",
            "subcategory":"School",
            "type":"Public Place"
        }
    ],
    "sg:phone":"+1 559 897 1091",
    "sg:postcode":"93631",
    "sg:province":"CA",
    "sg:website":"www.kingsburg-elem.k12.ca.us",
    "wof:name":"Rafer Johnson Jr High School",
    "wof:placetype":"venue"
},
  "geometry": {"coordinates":[-119.553363,36.525079],"type":"Point"}
}