{
  "type": "Feature",
  "properties": {
    "addr:full":"712 Bancroft Rd Walnut Creek CA 94598",
    "addr:housenumber":"712",
    "addr:postcode":"94598",
    "addr:street":"Bancroft Rd",
    "iso:country":"US",
    "sg:address":"712 Bancroft Rd",
    "sg:city":"Walnut Creek",
    "sg:classifiers":[
        {
            "category":"Wholesale",
            "subcategory":"Non-durable Goods",
            "type":"Manufacturing & Wholesale Goods"
        }
    ],
    "sg:phone":"+1 925 363 5314",
    "sg:postcode":"94598",
    "sg:province":"CA",
    "sg:tags":[
        "advertising",
        "specialty"
    ],
    "wof:name":"Logo Motion Concepts",
    "wof:placetype":"venue"
},
  "geometry": {"coordinates":[-122.041144,37.927814],"type":"Point"}
}