{
  "type": "Feature",
  "properties": {
    "iso:country":"US",
    "sg:address":"1920 San Pablo Ave",
    "sg:city":"Oakland",
    "sg:classifiers":[
        {
            "category":"Travel",
            "subcategory":"Hotels & Motels",
            "type":"Entertainment"
        }
    ],
    "sg:phone":"+1 510 832 9964",
    "sg:postcode":"94612",
    "sg:province":"CA",
    "sg:tags":[
        "operation"
    ],
    "wof:name":"Westerner Hotel Annex",
    "wof:placetype":"venue"
},
  "geometry": {"coordinates":[-122.27284299999999,37.809196],"type":"Point"}
}