{
  "type": "Feature",
  "properties": {
    "iso:country":"US",
    "sg:address":"123 N Stanislaus St",
    "sg:city":"Stockton",
    "sg:classifiers":[
        {
            "category":"Real Estate",
            "subcategory":"Real Estate Operator",
            "type":"Services"
        }
    ],
    "sg:phone":"+1 209 463 4960",
    "sg:postcode":"95202",
    "sg:province":"CA",
    "sg:tags":[
        "apartment"
    ],
    "wof:name":"Silvercrest Residence",
    "wof:placetype":"venue"
},
  "geometry": {"coordinates":[-121.282527,37.955761],"type":"Point"}
}