{
  "type": "Feature",
  "properties": {
    "addr:full":"935 S La Brea Avenue Inglewood CA 90301",
    "addr:housenumber":"935",
    "addr:postcode":"90301",
    "addr:street":"S La Brea Avenue",
    "iso:country":"US",
    "sg:address":"935 S La Brea Avenue",
    "sg:city":"Inglewood",
    "sg:classifiers":[
        {
            "category":"Bakery",
            "type":"Food & Drink"
        }
    ],
    "sg:phone":"+1 310 673 6517",
    "sg:postcode":"90301",
    "sg:province":"CA",
    "wof:name":"Zulema Bakery",
    "wof:placetype":"venue"
},
  "geometry": {"coordinates":[-118.35260700000001,33.951856],"type":"Point"}
}