{
  "type": "Feature",
  "properties": {
    "iso:country":"US",
    "sg:address":"3378 Via Loma",
    "sg:city":"Fallbrook",
    "sg:classifiers":[
        {
            "category":"Wholesale",
            "subcategory":"Fruits & Vegetables",
            "type":"Manufacturing & Wholesale Goods"
        }
    ],
    "sg:phone":"+1 760 728 7069",
    "sg:postcode":"92028",
    "sg:province":"CA",
    "sg:tags":[
        "vegetables-wholesale"
    ],
    "wof:name":"Bay Produce Co",
    "wof:placetype":"venue"
},
  "geometry": {"coordinates":[-117.190991,33.331582],"type":"Point"}
}