{
  "type": "Feature",
  "properties": {
    "iso:country":"US",
    "sg:address":"1996 Don Lee Pl",
    "sg:city":"Escondido",
    "sg:classifiers":[
        {
            "category":"Wholesale",
            "subcategory":"Machinery & Supplies",
            "type":"Manufacturing & Wholesale Goods"
        }
    ],
    "sg:phone":"+1 760 746 0531",
    "sg:postcode":"92029",
    "sg:province":"CA",
    "sg:tags":[
        "dry wall",
        "contractor"
    ],
    "sg:website":"www.jbmaterials.com",
    "wof:name":"J & B Materials Inc",
    "wof:placetype":"venue"
},
  "geometry": {"coordinates":[-117.119366,33.127467],"type":"Point"}
}