{
  "type": "Feature",
  "properties": {
    "iso:country":"US",
    "sg:address":"30941 Agoura Rd",
    "sg:city":"Westlake Village",
    "sg:classifiers":[
        {
            "category":"Education",
            "subcategory":"Special Training",
            "type":"Public Place"
        }
    ],
    "sg:phone":"+1 818 865 9455",
    "sg:postcode":"91361",
    "sg:province":"CA",
    "sg:tags":[
        "school",
        "driving"
    ],
    "wof:name":"Jimbos Ace Driving School",
    "wof:placetype":"venue"
},
  "geometry": {"coordinates":[-118.796267,34.144885],"type":"Point"}
}