{
  "type": "Feature",
  "properties": {
    "iso:country":"US",
    "sg:address":"3377 Kathy Way",
    "sg:city":"Loomis",
    "sg:classifiers":[
        {
            "category":"Professional",
            "subcategory":"Business Services",
            "type":"Services"
        }
    ],
    "sg:phone":"+1 916 652 6682",
    "sg:postcode":"95650",
    "sg:province":"CA",
    "wof:name":"Prior Pool Service",
    "wof:placetype":"venue"
},
  "geometry": {"coordinates":[-121.194036,38.830514],"type":"Point"}
}