{
  "type": "Feature",
  "properties": {
    "addr:full":"1475 S State College Blvd Ste 112 Anaheim CA 92806",
    "addr:housenumber":"1475",
    "addr:postcode":"92806",
    "addr:street":"S;Blvd Ste 112",
    "iso:country":"US",
    "sg:address":"1475 S State College Blvd Ste 112",
    "sg:city":"Anaheim",
    "sg:classifiers":[
        {
            "category":"Professional",
            "subcategory":"Lawyer & Legal Services",
            "type":"Services"
        }
    ],
    "sg:phone":"+1 714 635 5240",
    "sg:postcode":"92806",
    "sg:province":"CA",
    "wof:name":"Cero Debts LLC",
    "wof:placetype":"venue"
},
  "geometry": {"coordinates":[-117.88937799999999,33.811298],"type":"Point"}
}