{
  "type": "Feature",
  "properties": {
    "addr:full":"10020 Prospect Ave Santee CA 92071",
    "addr:housenumber":"10020",
    "addr:postcode":"92071",
    "addr:street":"Prospect Ave",
    "iso:country":"US",
    "sg:address":"10020 Prospect Ave",
    "sg:city":"Santee",
    "sg:classifiers":[
        {
            "category":"Building & Trades",
            "subcategory":"Construction",
            "type":"Services"
        }
    ],
    "sg:phone":"+1 619 449 2984",
    "sg:postcode":"92071",
    "sg:province":"CA",
    "sg:tags":[
        "woodworker"
    ],
    "wof:name":"Custom Woodworking",
    "wof:placetype":"venue"
},
  "geometry": {"coordinates":[-116.98159099999999,32.831465],"type":"Point"}
}