{
  "type": "Feature",
  "properties": {
    "iso:country":"US",
    "sg:address":"2627 Saturn Ave",
    "sg:city":"Huntington Park",
    "sg:classifiers":[
        {
            "category":"Food & Beverages",
            "subcategory":"Groceries & Convenience Stores",
            "type":"Retail Goods"
        }
    ],
    "sg:phone":"+1 323 583 5160",
    "sg:postcode":"90255",
    "sg:province":"CA",
    "wof:name":"Rita's Mini Market",
    "wof:placetype":"venue"
},
  "geometry": {"coordinates":[-118.224998,33.9771],"type":"Point"}
}