{
  "type": "Feature",
  "properties": {
    "iso:country":"US",
    "sg:address":"1258 W Temple St",
    "sg:city":"Los Angeles",
    "sg:classifiers":[
        {
            "category":"Food & Beverages",
            "subcategory":"Bakery",
            "type":"Retail Goods"
        }
    ],
    "sg:phone":"+1 213 481 7511",
    "sg:postcode":"90026",
    "sg:province":"CA",
    "sg:tags":[
        "baker"
    ],
    "wof:name":"K Bakery",
    "wof:placetype":"venue"
},
  "geometry": {"coordinates":[-118.253998,34.066601],"type":"Point"}
}