{
  "type": "Feature",
  "properties": {
    "addr:full":"3945 Marysville Boulevard Sacramento CA 95838",
    "addr:housenumber":"3945",
    "addr:postcode":"95838",
    "addr:street":"Marysville Boulevard",
    "iso:country":"US",
    "sg:address":"3945 Marysville Boulevard",
    "sg:city":"Sacramento",
    "sg:classifiers":[
        {
            "category":"Health Services",
            "subcategory":"Dentist",
            "type":"Services"
        }
    ],
    "sg:phone":"+1 916 564 5200",
    "sg:postcode":"95838",
    "sg:province":"CA",
    "wof:name":"Access Dental Centers",
    "wof:placetype":"venue"
},
  "geometry": {"coordinates":[-121.429164,38.639694],"type":"Point"}
}