{
  "type": "Feature",
  "properties": {
    "iso:country":"US",
    "sg:address":"10862 Atlantic Avenue",
    "sg:city":"Lynwood",
    "sg:classifiers":[
        {
            "category":"Retail",
            "subcategory":"Car Wash",
            "type":"Services"
        }
    ],
    "sg:phone":"+1 310 637 7203",
    "sg:postcode":"90262",
    "sg:province":"CA",
    "wof:name":"Ace Atlantic Corporation",
    "wof:placetype":"venue"
},
  "geometry": {"coordinates":[-118.182996,33.932276],"type":"Point"}
}