{
  "type": "Feature",
  "properties": {
    "addr:full":"994 Flower Glen St Simi Valley CA 93065",
    "addr:housenumber":"994",
    "addr:postcode":"93065",
    "addr:street":"Flower Glen St",
    "iso:country":"US",
    "sg:address":"994 Flower Glen St",
    "sg:city":"Simi Valley",
    "sg:classifiers":[
        {
            "category":"Professional",
            "type":"Services"
        }
    ],
    "sg:phone":"+1 805 584 8200",
    "sg:postcode":"93065",
    "sg:province":"CA",
    "sg:tags":[
        "establishment"
    ],
    "wof:name":"Whittaker Corp",
    "wof:placetype":"venue"
},
  "geometry": {"coordinates":[-118.782111,34.285327],"type":"Point"}
}