{
  "type": "Feature",
  "properties": {
    "addr:full":"5145 Stevens Creek Blvd Santa Clara CA 95051",
    "addr:housenumber":"5145",
    "addr:postcode":"95051",
    "addr:street":"Stevens Creek Blvd",
    "iso:country":"US",
    "sg:address":"5145 Stevens Creek Blvd",
    "sg:city":"Santa Clara",
    "sg:classifiers":[
        {
            "category":"Banks & Credit Unions",
            "subcategory":"Bank",
            "type":"Services"
        }
    ],
    "sg:phone":"+1 408 248 9800",
    "sg:postcode":"95051",
    "sg:province":"CA",
    "sg:tags":[
        "loan",
        "real estate"
    ],
    "wof:name":"Vaam & Assoc",
    "wof:placetype":"venue"
},
  "geometry": {"coordinates":[-121.99426200000001,37.322965],"type":"Point"}
}