{
  "type": "Feature",
  "properties": {
    "iso:country":"US",
    "sg:address":"61 Via Castanada",
    "sg:city":"Monterey",
    "sg:classifiers":[
        {
            "category":"Autos & Motor Vehicles",
            "subcategory":"Automobile Sales",
            "type":"Retail Goods"
        }
    ],
    "sg:phone":"+1 831 372 6662",
    "sg:postcode":"93940",
    "sg:province":"CA",
    "sg:tags":[
        "aircraft"
    ],
    "wof:name":"Jon Mayer Aircraft Sales",
    "wof:placetype":"venue"
},
  "geometry": {"coordinates":[-121.904225,36.582081],"type":"Point"}
}