{
  "type": "Feature",
  "properties": {
    "iso:country":"US",
    "sg:address":"14318 California Ave",
    "sg:city":"Victorville",
    "sg:classifiers":[
        {
            "category":"Real Estate",
            "subcategory":"Real Estate Agent",
            "type":"Services"
        }
    ],
    "sg:phone":"+1 760 243 2105",
    "sg:postcode":"92392",
    "sg:province":"CA",
    "wof:name":"Grubb & Ellis Co",
    "wof:placetype":"venue"
},
  "geometry": {"coordinates":[-117.328686,34.510502],"type":"Point"}
}