{
  "type": "Feature",
  "properties": {
    "iso:country":"US",
    "sg:address":"23184 el Toro Rd",
    "sg:city":"Lake Forest",
    "sg:classifiers":[
        {
            "category":"Building & Trades",
            "subcategory":"Landscaping Services",
            "type":"Services"
        }
    ],
    "sg:phone":"+1 949 699 0868",
    "sg:postcode":"92630",
    "sg:province":"CA",
    "sg:tags":[
        "landscape",
        "contractor"
    ],
    "wof:name":"Pro-Turf Professional Landscp",
    "wof:placetype":"venue"
},
  "geometry": {"coordinates":[-117.693916,33.626015],"type":"Point"}
}