{
  "type": "Feature",
  "properties": {
    "iso:country":"US",
    "sg:address":"3105 Cedar Ravine Rd",
    "sg:city":"Placerville",
    "sg:classifiers":[
        {
            "category":"Health Services",
            "subcategory":"Doctor",
            "type":"Services"
        }
    ],
    "sg:phone":"+1 530 344 2070",
    "sg:postcode":"95667",
    "sg:province":"CA",
    "sg:tags":[
        "physician",
        "surgeon"
    ],
    "wof:name":"Benjamin Ling MD",
    "wof:placetype":"venue"
},
  "geometry": {"coordinates":[-120.794201,38.72589],"type":"Point"}
}