{
  "type": "Feature",
  "properties": {
    "iso:country":"US",
    "sg:address":"19040 Portola Dr",
    "sg:city":"Salinas",
    "sg:classifiers":[
        {
            "category":"Wholesale",
            "subcategory":"Fruits & Vegetables",
            "type":"Manufacturing & Wholesale Goods"
        }
    ],
    "sg:phone":"+1 831 663 2746",
    "sg:postcode":"93908",
    "sg:province":"CA",
    "wof:name":"P & M Marketing",
    "wof:placetype":"venue"
},
  "geometry": {"coordinates":[-121.686391,36.620182],"type":"Point"}
}