{
  "type": "Feature",
  "properties": {
    "addr:full":"403 N Chester Ave Bakersfield CA 93308",
    "addr:housenumber":"403",
    "addr:postcode":"93308",
    "addr:street":"N Chester Ave",
    "iso:country":"US",
    "sg:address":"403 N Chester Ave",
    "sg:city":"Bakersfield",
    "sg:classifiers":[
        {
            "category":"Shopping",
            "subcategory":"Florist",
            "type":"Retail Goods"
        }
    ],
    "sg:phone":"+1 661 392 9571",
    "sg:postcode":"93308",
    "sg:province":"CA",
    "wof:name":"Kim's Flowers & Gifts",
    "wof:placetype":"venue"
},
  "geometry": {"coordinates":[-119.02116599999999,35.410462],"type":"Point"}
}