{
  "type": "Feature",
  "properties": {
    "addr:full":"4170 S Vermont Avenue Los Angeles CA 90037",
    "addr:housenumber":"4170",
    "addr:postcode":"90037",
    "addr:street":"S Vermont Avenue",
    "iso:country":"US",
    "sg:address":"4170 S Vermont Avenue",
    "sg:city":"Los Angeles",
    "sg:classifiers":[
        {
            "category":"Shopping",
            "subcategory":"Books",
            "type":"Retail Goods"
        }
    ],
    "sg:phone":"+1 323 233 5765",
    "sg:postcode":"90037",
    "sg:province":"CA",
    "sg:tags":[
        "bookstore"
    ],
    "wof:name":"Rosa De Saron Libreria Christiana",
    "wof:placetype":"venue"
},
  "geometry": {"coordinates":[-118.291693,34.007791],"type":"Point"}
}