{
  "type": "Feature",
  "properties": {
    "iso:country":"US",
    "sg:address":"1110 S Holt Ave",
    "sg:city":"Los Angeles",
    "sg:classifiers":[
        {
            "category":"Shopping",
            "subcategory":"Catalog Store",
            "type":"Retail Goods"
        }
    ],
    "sg:phone":"+1 310 652 8734",
    "sg:postcode":"90035",
    "sg:province":"CA",
    "sg:tags":[
        "retailer"
    ],
    "wof:name":"Worldwide Distribution",
    "wof:placetype":"venue"
},
  "geometry": {"coordinates":[-118.37842,34.053941],"type":"Point"}
}