{
  "type": "Feature",
  "properties": {
    "addr:full":"1788 S La Cienega Blvd. Los Angeles CA 90035",
    "addr:housenumber":"1788",
    "addr:postcode":"90035",
    "addr:street":"S La Cienega Blvd.",
    "iso:country":"US",
    "sg:address":"1788 S La Cienega Blvd.",
    "sg:city":"Los Angeles",
    "sg:classifiers":[
        {
            "category":"Autos & Motor Vehicles",
            "subcategory":"Automobile Sales",
            "type":"Retail Goods"
        }
    ],
    "sg:phone":"+1 310 841 4000",
    "sg:postcode":"90035",
    "sg:province":"CA",
    "sg:tags":[
        "car"
    ],
    "sg:website":"milanomotors.com/",
    "wof:name":"Milano Motors",
    "wof:placetype":"venue"
},
  "geometry": {"coordinates":[-118.376424,34.044863],"type":"Point"}
}