{
  "type": "Feature",
  "properties": {
    "addr:full":"12802 Morning Star Rd Apple Valley CA 92308",
    "addr:housenumber":"12802",
    "addr:postcode":"92308",
    "addr:street":"Morning Star Rd",
    "iso:country":"US",
    "sg:address":"12802 Morning Star Rd",
    "sg:city":"Apple Valley",
    "sg:classifiers":[
        {
            "category":"Professional",
            "type":"Services"
        }
    ],
    "sg:phone":"+1 760 240 4746",
    "sg:postcode":"92308",
    "sg:province":"CA",
    "wof:name":"Gene Wolfe Installaton & Repai",
    "wof:placetype":"venue"
},
  "geometry": {"coordinates":[-117.19280999999999,34.484075],"type":"Point"}
}