{
  "type": "Feature",
  "properties": {
    "addr:full":"27600 Bouquet Canyon Rd Santa Clarita CA 91350",
    "addr:housenumber":"27600",
    "addr:postcode":"91350",
    "addr:street":"Bouquet Canyon Rd",
    "iso:country":"US",
    "sg:address":"27600 Bouquet Canyon Rd",
    "sg:city":"Santa Clarita",
    "sg:classifiers":[
        {
            "category":"Banks & Credit Unions",
            "subcategory":"Financial Services",
            "type":"Services"
        }
    ],
    "sg:phone":"+1 661 297 8981",
    "sg:postcode":"91350",
    "sg:province":"CA",
    "sg:tags":[
        "broker",
        "mortgage"
    ],
    "wof:name":"Platinum Real Estate VIP & Lending",
    "wof:placetype":"venue"
},
  "geometry": {"coordinates":[-118.512129,34.442405],"type":"Point"}
}