{
  "type": "Feature",
  "properties": {
    "iso:country":"US",
    "sg:address":"1164 Clark St",
    "sg:city":"San Jose",
    "sg:classifiers":[
        {
            "category":"Building & Trades",
            "subcategory":"Plumbing",
            "type":"Services"
        }
    ],
    "sg:phone":"+1 408 292 8906",
    "sg:postcode":"95125",
    "sg:province":"CA",
    "sg:tags":[
        "contractor"
    ],
    "wof:name":"Rowe Jn Hvac Design",
    "wof:placetype":"venue"
},
  "geometry": {"coordinates":[-121.89107300000001,37.311493],"type":"Point"}
}