{
  "type": "Feature",
  "properties": {
    "addr:full":"956 Leroy Ln Walnut Creek CA 94597",
    "addr:housenumber":"956",
    "addr:postcode":"94597",
    "addr:street":"Leroy Ln",
    "iso:country":"US",
    "sg:address":"956 Leroy Ln",
    "sg:city":"Walnut Creek",
    "sg:classifiers":[
        {
            "category":"Professional",
            "type":"Services"
        }
    ],
    "sg:phone":"+1 925 947 3183",
    "sg:postcode":"94597",
    "sg:province":"CA",
    "wof:name":"Sandys Place Inc",
    "wof:placetype":"venue"
},
  "geometry": {"coordinates":[-122.077851,37.913065],"type":"Point"}
}