{
  "type": "Feature",
  "properties": {
    "iso:country":"US",
    "sg:address":"1433 Kern St",
    "sg:city":"Fresno",
    "sg:classifiers":[
        {
            "category":"Social Services",
            "type":"Services"
        }
    ],
    "sg:phone":"+1 559 441 7915",
    "sg:postcode":"93706",
    "sg:province":"CA",
    "sg:tags":[
        "organization",
        "welfare"
    ],
    "wof:name":"Chinatown Revitalization Inc",
    "wof:placetype":"venue"
},
  "geometry": {"coordinates":[-119.793912,36.729514],"type":"Point"}
}