{
  "type": "Feature",
  "properties": {
    "iso:country":"US",
    "sg:address":"824 E Carson St Ste 201",
    "sg:city":"Carson",
    "sg:classifiers":[
        {
            "category":"Health Services",
            "subcategory":"Doctor",
            "type":"Services"
        }
    ],
    "sg:phone":"+1 310 233 3228",
    "sg:postcode":"90745",
    "sg:province":"CA",
    "sg:tags":[
        "physician",
        "family",
        "practice",
        "surgeons",
        "medicine"
    ],
    "wof:name":"Family Practice Assoc Of Carso",
    "wof:placetype":"venue"
},
  "geometry": {"coordinates":[-118.260595,33.831623],"type":"Point"}
}