{
  "type": "Feature",
  "properties": {
    "addr:full":"1601 New Stine Rd Bakersfield CA 93309",
    "addr:housenumber":"1601",
    "addr:postcode":"93309",
    "addr:street":"New Stine Rd",
    "iso:country":"US",
    "sg:address":"1601 New Stine Rd",
    "sg:city":"Bakersfield",
    "sg:classifiers":[
        {
            "category":"Organizations",
            "subcategory":"Membership Organization",
            "type":"Services"
        }
    ],
    "sg:phone":"+1 661 835 8493",
    "sg:postcode":"93309",
    "sg:province":"CA",
    "wof:name":"Latino Coalition",
    "wof:placetype":"venue"
},
  "geometry": {"coordinates":[-119.06120799999999,35.341044],"type":"Point"}
}