{
  "type": "Feature",
  "properties": {
    "iso:country":"US",
    "sg:address":"23622 Rockfield Blvd",
    "sg:city":"Lake Forest",
    "sg:classifiers":[
        {
            "category":"Freight",
            "type":"Transportation"
        }
    ],
    "sg:phone":"+1 949 461 7721",
    "sg:postcode":"92630",
    "sg:province":"CA",
    "sg:tags":[
        "operator",
        "trucking"
    ],
    "wof:name":"Western Carrier Corporation",
    "wof:placetype":"venue"
},
  "geometry": {"coordinates":[-117.712444,33.624371],"type":"Point"}
}