{
  "type": "Feature",
  "properties": {
    "addr:full":"263 N Pearson Dr Porterville CA 93257",
    "addr:housenumber":"263",
    "addr:postcode":"93257",
    "addr:street":"N Pearson Dr",
    "iso:country":"US",
    "sg:address":"263 N Pearson Dr",
    "sg:city":"Porterville",
    "sg:classifiers":[
        {
            "category":"Health Services",
            "subcategory":"Doctor",
            "type":"Services"
        }
    ],
    "sg:phone":"+1 559 781 3931",
    "sg:postcode":"93257",
    "sg:province":"CA",
    "sg:tags":[
        "physician",
        "surgeon"
    ],
    "wof:name":"Sierra Foothills Medical Group",
    "wof:placetype":"venue"
},
  "geometry": {"coordinates":[-119.02768,36.071752],"type":"Point"}
}