{
  "type": "Feature",
  "properties": {
    "addr:full":"5052 Warner Ave Huntington Beach CA 92649",
    "addr:housenumber":"5052",
    "addr:postcode":"92649",
    "addr:street":"Warner Ave",
    "iso:country":"US",
    "sg:address":"5052 Warner Ave",
    "sg:city":"Huntington Beach",
    "sg:classifiers":[
        {
            "category":"Organizations",
            "subcategory":"Religious Organization",
            "type":"Services"
        }
    ],
    "sg:phone":"+1 714 846 2285",
    "sg:postcode":"92649",
    "sg:province":"CA",
    "sg:tags":[
        "synagogue"
    ],
    "wof:name":"Chabad Of West Orange County",
    "wof:placetype":"venue"
},
  "geometry": {"coordinates":[-118.03983700000001,33.715195],"type":"Point"}
}