{
  "type": "Feature",
  "properties": {
    "iso:country":"US",
    "sg:address":"21400 Burbank Blvd",
    "sg:city":"Woodland Hills",
    "sg:classifiers":[
        {
            "category":"Insurance",
            "subcategory":"Insurance Agent",
            "type":"Services"
        }
    ],
    "sg:phone":"+1 818 342 3300",
    "sg:postcode":"91367",
    "sg:province":"CA",
    "wof:name":"Friedman Insurance Group",
    "wof:placetype":"venue"
},
  "geometry": {"coordinates":[-118.600191,34.173283],"type":"Point"}
}