{
  "type": "Feature",
  "properties": {
    "iso:country":"US",
    "sg:address":"3404 30th St",
    "sg:city":"San Diego",
    "sg:classifiers":[
        {
            "category":"Manufacturing",
            "subcategory":"Leather Goods",
            "type":"Manufacturing & Wholesale Goods"
        }
    ],
    "sg:phone":"+1 619 574 1579",
    "sg:postcode":"92104",
    "sg:province":"CA",
    "wof:name":"Crypt At Wolf's the",
    "wof:placetype":"venue"
},
  "geometry": {"coordinates":[-117.129997,32.741199],"type":"Point"}
}