{
  "type": "Feature",
  "properties": {
    "iso:country":"US",
    "sg:address":"2388 Glendale Blvd",
    "sg:city":"Los Angeles",
    "sg:classifiers":[
        {
            "category":"Shopping",
            "subcategory":"Books",
            "type":"Retail Goods"
        }
    ],
    "sg:phone":"+1 323 913 9677",
    "sg:postcode":"90039",
    "sg:province":"CA",
    "sg:tags":[
        "bookstore"
    ],
    "wof:name":"C M Bookshop In Silverlake",
    "wof:placetype":"venue"
},
  "geometry": {"coordinates":[-118.259003,34.099701],"type":"Point"}
}