{
  "type": "Feature",
  "properties": {
    "iso:country":"US",
    "sg:address":"684 Barham Dr",
    "sg:city":"San Marcos",
    "sg:classifiers":[
        {
            "category":"Building & Trades",
            "subcategory":"Construction",
            "type":"Services"
        }
    ],
    "sg:phone":"+1 760 744 1250",
    "sg:postcode":"92078",
    "sg:province":"CA",
    "sg:tags":[
        "fence",
        "contractor"
    ],
    "wof:name":"Cal-West Fence Co",
    "wof:placetype":"venue"
},
  "geometry": {"coordinates":[-117.15148499999999,33.13548],"type":"Point"}
}