{
  "type": "Feature",
  "properties": {
    "iso:country":"US",
    "sg:address":"4244 Alhambra Way",
    "sg:city":"Martinez",
    "sg:classifiers":[
        {
            "category":"Home & Garden",
            "subcategory":"Furniture",
            "type":"Retail Goods"
        }
    ],
    "sg:phone":"+1 925 228 6515",
    "sg:postcode":"94553",
    "sg:province":"CA",
    "sg:tags":[
        "builder",
        "custom"
    ],
    "wof:name":"Quercus",
    "wof:placetype":"venue"
},
  "geometry": {"coordinates":[-122.127173,37.992327],"type":"Point"}
}