{
  "type": "Feature",
  "properties": {
    "iso:country":"US",
    "sg:address":"2324 N Batavia St",
    "sg:city":"Orange",
    "sg:classifiers":[
        {
            "category":"Professional",
            "type":"Services"
        }
    ],
    "sg:phone":"+1 714 279 0282",
    "sg:postcode":"92865",
    "sg:province":"CA",
    "wof:name":"Totally Wired Networks Inc",
    "wof:placetype":"venue"
},
  "geometry": {"coordinates":[-117.861921,33.828954],"type":"Point"}
}