{
  "type": "Feature",
  "properties": {
    "iso:country":"US",
    "sg:address":"48860 Milmont Dr",
    "sg:city":"Fremont",
    "sg:classifiers":[
        {
            "category":"Professional",
            "type":"Services"
        }
    ],
    "sg:phone":"+1 510 687 9501",
    "sg:postcode":"94538",
    "sg:province":"CA",
    "sg:tags":[
        "establishment"
    ],
    "wof:name":"Globespan",
    "wof:placetype":"venue"
},
  "geometry": {"coordinates":[-121.92213,37.46173],"type":"Point"}
}