{
  "type": "Feature",
  "properties": {
    "addr:full":"204 Market St Colusa CA 95932",
    "addr:housenumber":"204",
    "addr:postcode":"95932",
    "addr:street":"Market St",
    "iso:country":"US",
    "sg:address":"204 Market St",
    "sg:city":"Colusa",
    "sg:classifiers":[
        {
            "category":"Building & Trades",
            "subcategory":"Construction",
            "type":"Services"
        }
    ],
    "sg:phone":"+1 530 458 3795",
    "sg:postcode":"95932",
    "sg:province":"CA",
    "sg:tags":[
        "painter"
    ],
    "wof:name":"H & E Quality Painting",
    "wof:placetype":"venue"
},
  "geometry": {"coordinates":[-122.005259,39.2135],"type":"Point"}
}