{
  "type": "Feature",
  "properties": {
    "iso:country":"US",
    "sg:address":"115 W Walnut St Ste 2",
    "sg:city":"Lodi",
    "sg:classifiers":[
        {
            "category":"Professional",
            "subcategory":"Lawyer & Legal Services",
            "type":"Services"
        }
    ],
    "sg:phone":"+1 209 368 5229",
    "sg:postcode":"95240",
    "sg:province":"CA",
    "sg:tags":[
        "attorney",
        "practice"
    ],
    "wof:name":"Randy D Roxson Attorney At Law",
    "wof:placetype":"venue"
},
  "geometry": {"coordinates":[-121.27405400000001,38.131789],"type":"Point"}
}