{
  "type": "Feature",
  "properties": {
    "addr:full":"13506 Pomerado Rd Poway CA 92064",
    "addr:housenumber":"13506",
    "addr:postcode":"ca 92064",
    "addr:street":"Pomerado Rd",
    "iso:country":"US",
    "sg:address":"13506 Pomerado Rd",
    "sg:city":"Poway",
    "sg:classifiers":[
        {
            "category":"Autos & Motor Vehicles",
            "subcategory":"Automobile Sales",
            "type":"Retail Goods"
        },
        {
            "category":"Autos & Motor Vehicles",
            "subcategory":"Fuel & Gas Station",
            "type":"Retail Goods"
        },
        {
            "category":"Autos & Motor Vehicles",
            "subcategory":"Auto Supplies",
            "type":"Retail Goods"
        },
        {
            "category":"Retail",
            "subcategory":"Auto Repair",
            "type":"Services"
        }
    ],
    "sg:phone":"+1 858 848 5991",
    "sg:postcode":"92064",
    "sg:province":"CA",
    "sg:tags":[
        "wheel",
        "exhaust",
        "oil",
        "muffler",
        "balancing",
        "wheels-aligning",
        "servicing-automotive",
        "system",
        "accessory",
        "equipment",
        "lube",
        "electrical",
        "axle",
        "equipment-service",
        "alignment-frame",
        "brake",
        "inspection",
        "air conditioning"
    ],
    "sg:website":"http://www.tomtracker.com/redirect.cfm?bID=4837&hID=111353",
    "wof:name":"Meineke Car Care Center",
    "wof:placetype":"venue"
},
  "geometry": {"coordinates":[-117.06249200000001,32.959719],"type":"Point"}
}