{
  "type": "Feature",
  "properties": {
    "addr:full":"15054 Eureka St Lake Elsinore CA 92530",
    "addr:housenumber":"15054",
    "addr:postcode":"92530",
    "addr:street":"Eureka St",
    "iso:country":"US",
    "sg:address":"15054 Eureka St",
    "sg:city":"Lake Elsinore",
    "sg:classifiers":[
        {
            "category":"Building & Trades",
            "subcategory":"Electrical",
            "type":"Services"
        }
    ],
    "sg:phone":"+1 951 678 6433",
    "sg:postcode":"92530",
    "sg:province":"CA",
    "sg:tags":[
        "electrical",
        "contractor"
    ],
    "wof:name":"D&S Electric",
    "wof:placetype":"venue"
},
  "geometry": {"coordinates":[-117.389686,33.674101],"type":"Point"}
}