{
  "type": "Feature",
  "properties": {
    "addr:full":"968 Cooper Ave Yuba City CA 95991",
    "addr:housenumber":"968",
    "addr:postcode":"95991",
    "addr:street":"Cooper Ave",
    "iso:country":"US",
    "sg:address":"968 Cooper Ave",
    "sg:city":"Yuba City",
    "sg:classifiers":[
        {
            "category":"Restaurant",
            "type":"Food & Drink"
        }
    ],
    "sg:phone":"+1 530 673 4172",
    "sg:postcode":"95991",
    "sg:province":"CA",
    "sg:tags":[
        "out"
    ],
    "wof:name":"Pancho's Big Burger",
    "wof:placetype":"venue"
},
  "geometry": {"coordinates":[-121.623767,39.141477],"type":"Point"}
}