{
  "type": "Feature",
  "properties": {
    "addr:full":"28052 Camino Capistrano Laguna Niguel CA 92677",
    "addr:housenumber":"28052",
    "addr:postcode":"92677",
    "addr:street":"Camino Capistrano",
    "iso:country":"US",
    "sg:address":"28052 Camino Capistrano",
    "sg:city":"Laguna Niguel",
    "sg:classifiers":[
        {
            "category":"Education",
            "subcategory":"Music School",
            "type":"Public Place"
        }
    ],
    "sg:phone":"+1 949 493 2537",
    "sg:postcode":"92677",
    "sg:province":"CA",
    "sg:tags":[
        "instrument",
        "teacher",
        "musical"
    ],
    "wof:name":"Discount Pianos",
    "wof:placetype":"venue"
},
  "geometry": {"coordinates":[-117.67392100000001,33.555344],"type":"Point"}
}