{
  "type": "Feature",
  "properties": {
    "iso:country":"US",
    "sg:address":"7213 Walnut Rd",
    "sg:city":"Fair Oaks",
    "sg:classifiers":[
        {
            "category":"Utilities",
            "subcategory":"Refuse",
            "type":"Services"
        }
    ],
    "sg:phone":"+1 916 966 1159",
    "sg:postcode":"95628",
    "sg:province":"CA",
    "sg:tags":[
        "system"
    ],
    "wof:name":"Golden State Disposal",
    "wof:placetype":"venue"
},
  "geometry": {"coordinates":[-121.295275,38.642326],"type":"Point"}
}