{
  "type": "Feature",
  "properties": {
    "iso:country":"US",
    "sg:address":"3450 3rd St",
    "sg:city":"San Francisco",
    "sg:classifiers":[
        {
            "category":"Professional",
            "type":"Services"
        }
    ],
    "sg:phone":"+1 415 821 3889",
    "sg:postcode":"94124",
    "sg:province":"CA",
    "sg:tags":[
        "establishment"
    ],
    "wof:name":"Bags For Less",
    "wof:placetype":"venue"
},
  "geometry": {"coordinates":[-122.387266,37.74562],"type":"Point"}
}