{
  "type": "Feature",
  "properties": {
    "iso:country":"US",
    "sg:address":"43385 Bus Park Dr",
    "sg:city":"Temecula",
    "sg:classifiers":[
        {
            "category":"Banks & Credit Unions",
            "subcategory":"Bank",
            "type":"Services"
        }
    ],
    "sg:phone":"+1 951 676 8168",
    "sg:postcode":"92590",
    "sg:province":"CA",
    "sg:website":"www.integritybancorp.com",
    "wof:name":"Integrity Bancorp",
    "wof:placetype":"venue"
},
  "geometry": {"coordinates":[-117.166593,33.503483],"type":"Point"}
}