{
  "type": "Feature",
  "properties": {
    "iso:country":"US",
    "sg:address":"1023 S De Anza Boulevard",
    "sg:city":"San Jose",
    "sg:classifiers":[
        {
            "category":"Travel",
            "subcategory":"Travel Agent",
            "type":"Entertainment"
        }
    ],
    "sg:phone":"+1 650 968 0161",
    "sg:postcode":"95129",
    "sg:province":"CA",
    "sg:website":"www.coriontravel.com/sitebuilder/",
    "wof:name":"Corion Travel",
    "wof:placetype":"venue"
},
  "geometry": {"coordinates":[-122.032205,37.309629],"type":"Point"}
}