{
  "type": "Feature",
  "properties": {
    "addr:full":"199 Willow St San Jose CA 95110",
    "addr:housenumber":"199",
    "addr:postcode":"95110",
    "addr:street":"Willow St",
    "iso:country":"US",
    "sg:address":"199 Willow St",
    "sg:city":"San Jose",
    "sg:classifiers":[
        {
            "category":"Food & Beverages",
            "subcategory":"Bakery",
            "type":"Retail Goods"
        }
    ],
    "sg:phone":"+1 408 293 2116",
    "sg:postcode":"95110",
    "sg:province":"CA",
    "sg:tags":[
        "donut",
        "doughnut"
    ],
    "wof:name":"Willow Donuts",
    "wof:placetype":"venue"
},
  "geometry": {"coordinates":[-121.88200399999999,37.318901],"type":"Point"}
}