{
  "type": "Feature",
  "properties": {
    "addr:full":"1689 Arden Way Sacramento CA 95815",
    "addr:housenumber":"1689",
    "addr:postcode":"95815",
    "addr:street":"Arden Way",
    "iso:country":"US",
    "sg:address":"1689 Arden Way",
    "sg:city":"Sacramento",
    "sg:classifiers":[
        {
            "category":"Shopping",
            "subcategory":"Mobile Phones",
            "type":"Retail Goods"
        }
    ],
    "sg:phone":"+1 916 929 2123",
    "sg:postcode":"95815",
    "sg:province":"CA",
    "wof:name":"Wireless Only",
    "wof:placetype":"venue"
},
  "geometry": {"coordinates":[-121.425003,38.5989],"type":"Point"}
}