{
  "type": "Feature",
  "properties": {
    "addr:full":"3051 Cutting Blvd Richmond CA 94804",
    "addr:housenumber":"3051",
    "addr:postcode":"94804",
    "addr:street":"Cutting Blvd",
    "iso:country":"US",
    "sg:address":"3051 Cutting Blvd",
    "sg:city":"Richmond",
    "sg:classifiers":[
        {
            "category":"Restaurant",
            "type":"Food & Drink"
        }
    ],
    "sg:phone":"+1 510 234 3500",
    "sg:postcode":"94804",
    "sg:province":"CA",
    "sg:tags":[
        "barbeque"
    ],
    "wof:name":"Boulevard Fish & Barbeque",
    "wof:placetype":"venue"
},
  "geometry": {"coordinates":[-122.33899700000001,37.925301],"type":"Point"}
}