{
  "type": "Feature",
  "properties": {
    "iso:country":"US",
    "sg:address":"946 W 8th St",
    "sg:city":"Los Angeles",
    "sg:classifiers":[
        {
            "category":"Parking",
            "type":"Transportation"
        }
    ],
    "sg:phone":"+1 213 892 8477",
    "sg:postcode":"90017",
    "sg:province":"CA",
    "sg:tags":[
        "garage"
    ],
    "wof:name":"Standard Parking",
    "wof:placetype":"venue"
},
  "geometry": {"coordinates":[-118.262147,34.048302],"type":"Point"}
}