{
  "type": "Feature",
  "properties": {
    "addr:full":"230 Walnut Ave Santa Cruz CA 95060",
    "addr:housenumber":"230",
    "addr:postcode":"95060",
    "addr:street":"Walnut Ave",
    "iso:country":"US",
    "sg:address":"230 Walnut Ave",
    "sg:city":"Santa Cruz",
    "sg:classifiers":[
        {
            "category":"Government",
            "subcategory":"Fire Station",
            "type":"Public Place"
        }
    ],
    "sg:phone":"+1 831 420 5280",
    "sg:postcode":"95060",
    "sg:province":"CA",
    "sg:tags":[
        "protection"
    ],
    "wof:name":"Fire Department",
    "wof:placetype":"venue"
},
  "geometry": {"coordinates":[-122.030013,36.972823],"type":"Point"}
}