{
  "type": "Feature",
  "properties": {
    "iso:country":"US",
    "sg:address":"20130 Lake Chabot Rd Ste 307",
    "sg:city":"Castro Valley",
    "sg:classifiers":[
        {
            "category":"Health Services",
            "subcategory":"Doctor",
            "type":"Services"
        }
    ],
    "sg:phone":"+1 510 889 1673",
    "sg:postcode":"94546",
    "sg:province":"CA",
    "sg:tags":[
        "medicine",
        "internal"
    ],
    "wof:name":"Steven R. Una, MD",
    "wof:placetype":"venue"
},
  "geometry": {"coordinates":[-122.08706100000001,37.697561],"type":"Point"}
}