{
  "type": "Feature",
  "properties": {
    "addr:full":"18700 Beach Boulevard Huntington Beach CA 92648",
    "addr:housenumber":"18700",
    "addr:postcode":"92648",
    "addr:street":"Beach Boulevard",
    "iso:country":"US",
    "sg:address":"18700 Beach Boulevard",
    "sg:city":"Huntington Beach",
    "sg:classifiers":[
        {
            "category":"Banks & Credit Unions",
            "subcategory":"Financial Services",
            "type":"Services"
        }
    ],
    "sg:phone":"+1 714 378 5201",
    "sg:postcode":"92648",
    "sg:province":"CA",
    "sg:tags":[
        "broker",
        "mortgage"
    ],
    "wof:name":"City Bancorp.",
    "wof:placetype":"venue"
},
  "geometry": {"coordinates":[-117.98871800000001,33.690984],"type":"Point"}
}