{
  "type": "Feature",
  "properties": {
    "iso:country":"US",
    "sg:address":"1 Annabel Ln",
    "sg:city":"San Ramon",
    "sg:classifiers":[
        {
            "category":"Professional",
            "subcategory":"Management & Consulting",
            "type":"Services"
        }
    ],
    "sg:phone":"+1 925 830 8896",
    "sg:postcode":"94583",
    "sg:province":"CA",
    "sg:tags":[
        "consultant",
        "educational"
    ],
    "wof:name":"Decision Development Corp",
    "wof:placetype":"venue"
},
  "geometry": {"coordinates":[-121.97061100000001,37.772166],"type":"Point"}
}