{
  "type": "Feature",
  "properties": {
    "iso:country":"US",
    "sg:address":"3280 Township Rd",
    "sg:city":"Paso Robles",
    "sg:classifiers":[
        {
            "category":"Farming",
            "subcategory":"Vineyard",
            "type":"Manufacturing & Wholesale Goods"
        }
    ],
    "sg:phone":"+1 805 239 9432",
    "sg:postcode":"93446",
    "sg:province":"CA",
    "sg:tags":[
        "grape"
    ],
    "wof:name":"AJB Vineyards",
    "wof:placetype":"venue"
},
  "geometry": {"coordinates":[-120.756377,35.569254],"type":"Point"}
}