{
  "type": "Feature",
  "properties": {
    "iso:country":"US",
    "sg:address":"2250 N Broadway",
    "sg:city":"Escondido",
    "sg:classifiers":[
        {
            "category":"Real Estate",
            "subcategory":"Real Estate Agent",
            "type":"Services"
        }
    ],
    "sg:phone":"+1 760 741 1911",
    "sg:postcode":"92026",
    "sg:province":"CA",
    "wof:name":"Amicorp Properties",
    "wof:placetype":"venue"
},
  "geometry": {"coordinates":[-117.09213200000001,33.156623],"type":"Point"}
}