{
  "type": "Feature",
  "properties": {
    "addr:full":"1214 Daniel Ct Milpitas CA 95035",
    "addr:housenumber":"1214",
    "addr:postcode":"95035",
    "addr:street":"Daniel Ct",
    "iso:country":"US",
    "sg:address":"1214 Daniel Ct",
    "sg:city":"Milpitas",
    "sg:classifiers":[
        {
            "category":"Professional",
            "subcategory":"Business Services",
            "type":"Services"
        }
    ],
    "sg:phone":"+1 408 586 8659",
    "sg:postcode":"95035",
    "sg:province":"CA",
    "sg:tags":[
        "drafting"
    ],
    "wof:name":"JJD Drafting Svc",
    "wof:placetype":"venue"
},
  "geometry": {"coordinates":[-121.88758799999999,37.447086],"type":"Point"}
}