{
  "type": "Feature",
  "properties": {
    "addr:full":"3271 Ridgeview Dr El Dorado Hills CA 95762",
    "addr:housenumber":"3271",
    "addr:postcode":"95762",
    "addr:street":"Ridgeview Dr",
    "iso:country":"US",
    "sg:address":"3271 Ridgeview Dr",
    "sg:city":"El Dorado Hills",
    "sg:classifiers":[
        {
            "category":"Professional",
            "type":"Services"
        }
    ],
    "sg:phone":"+1 916 933 8510",
    "sg:postcode":"95762",
    "sg:province":"CA",
    "wof:name":"Welmed Inc",
    "wof:placetype":"venue"
},
  "geometry": {"coordinates":[-121.085672,38.674092],"type":"Point"}
}