{
  "type": "Feature",
  "properties": {
    "addr:full":"2633 Prospect Ave La Crescenta CA 91214",
    "addr:housenumber":"2633",
    "addr:postcode":"91214",
    "addr:street":"Prospect Ave",
    "iso:country":"US",
    "sg:address":"2633 Prospect Ave",
    "sg:city":"La Crescenta",
    "sg:classifiers":[
        {
            "category":"Professional",
            "subcategory":"Detective & Security Services",
            "type":"Services"
        }
    ],
    "sg:phone":"+1 818 249 1732",
    "sg:postcode":"91214",
    "sg:province":"CA",
    "sg:tags":[
        "investigator"
    ],
    "wof:name":"Triedstone Investigations",
    "wof:placetype":"venue"
},
  "geometry": {"coordinates":[-118.235124,34.218472],"type":"Point"}
}