{
  "type": "Feature",
  "properties": {
    "iso:country":"US",
    "sg:address":"35 Mitchell Blvd",
    "sg:city":"San Rafael",
    "sg:classifiers":[
        {
            "category":"Education",
            "subcategory":"Special Training",
            "type":"Public Place"
        }
    ],
    "sg:phone":"+1 415 444 0571",
    "sg:postcode":"94903",
    "sg:province":"CA",
    "sg:tags":[
        "instruction",
        "driving"
    ],
    "wof:name":"ABC Driving School",
    "wof:placetype":"venue"
},
  "geometry": {"coordinates":[-122.538659,38.017081],"type":"Point"}
}