{
  "type": "Feature",
  "properties": {
    "addr:full":"1091 7th St Calimesa CA 92320",
    "addr:housenumber":"1091",
    "addr:postcode":"92320",
    "addr:street":"7Th St",
    "iso:country":"US",
    "sg:address":"1091 7th St",
    "sg:city":"Calimesa",
    "sg:classifiers":[
        {
            "category":"Wholesale",
            "subcategory":"Machinery & Supplies",
            "type":"Manufacturing & Wholesale Goods"
        }
    ],
    "sg:phone":"+1 909 795 0003",
    "sg:postcode":"92320",
    "sg:province":"CA",
    "sg:tags":[
        "pressure",
        "washing",
        "equipment"
    ],
    "wof:name":"Washer Industry Parts",
    "wof:placetype":"venue"
},
  "geometry": {"coordinates":[-117.061593,33.995727],"type":"Point"}
}