{
  "type": "Feature",
  "properties": {
    "addr:full":"331 J St Sacramento CA 95814",
    "addr:housenumber":"331",
    "addr:postcode":"95814",
    "addr:street":"J St",
    "iso:country":"US",
    "sg:address":"331 J St",
    "sg:city":"Sacramento",
    "sg:classifiers":[
        {
            "category":"Professional",
            "subcategory":"Lawyer & Legal Services",
            "type":"Services"
        }
    ],
    "sg:phone":"+1 916 441 1077",
    "sg:postcode":"95814",
    "sg:province":"CA",
    "sg:tags":[
        "attorney"
    ],
    "wof:name":"Michael Borkowski",
    "wof:placetype":"venue"
},
  "geometry": {"coordinates":[-121.501874,38.582667],"type":"Point"}
}