{
  "type": "Feature",
  "properties": {
    "iso:country":"US",
    "sg:address":"1441 Eastlake Avenue",
    "sg:city":"Los Angeles",
    "sg:classifiers":[
        {
            "category":"Health Services",
            "subcategory":"Hospital",
            "type":"Services"
        }
    ],
    "sg:phone":"+1 323 865 3000",
    "sg:postcode":"90089",
    "sg:province":"CA",
    "wof:name":"Usc-Norris Cancer Hospital",
    "wof:placetype":"venue"
},
  "geometry": {"coordinates":[-118.287733,34.020396],"type":"Point"}
}