{
  "type": "Feature",
  "properties": {
    "iso:country":"US",
    "sg:address":"20695 S Western Ave",
    "sg:city":"Torrance",
    "sg:classifiers":[
        {
            "category":"Education",
            "subcategory":"Special Training",
            "type":"Public Place"
        }
    ],
    "sg:phone":"+1 310 328 5500",
    "sg:postcode":"90501",
    "sg:province":"CA",
    "sg:tags":[
        "tutoring"
    ],
    "wof:name":"Joyfull Education Svc",
    "wof:placetype":"venue"
},
  "geometry": {"coordinates":[-118.309332,33.843366],"type":"Point"}
}