{
  "type": "Feature",
  "properties": {
    "addr:full":"686 W Napa St Sonoma CA 95476",
    "addr:housenumber":"686",
    "addr:postcode":"95476",
    "addr:street":"W Napa St",
    "iso:country":"US",
    "sg:address":"686 W Napa St",
    "sg:city":"Sonoma",
    "sg:classifiers":[
        {
            "category":"Personal",
            "subcategory":"Beauty Salon",
            "type":"Services"
        }
    ],
    "sg:phone":"+1 707 939 1761",
    "sg:postcode":"95476",
    "sg:province":"CA",
    "wof:name":"S Cutright Salon",
    "wof:placetype":"venue"
},
  "geometry": {"coordinates":[-122.470449,38.293225],"type":"Point"}
}