{
  "type": "Feature",
  "properties": {
    "addr:full":"19028 Norwalk Blvd Artesia CA 90701",
    "addr:housenumber":"19028",
    "addr:postcode":"90701",
    "addr:street":"Norwalk Blvd",
    "iso:country":"US",
    "sg:address":"19028 Norwalk Blvd",
    "sg:city":"Artesia",
    "sg:classifiers":[
        {
            "category":"Personal",
            "subcategory":"Beauty Salon",
            "type":"Services"
        }
    ],
    "sg:phone":"+1 562 865 8648",
    "sg:postcode":"90701",
    "sg:province":"CA",
    "wof:name":"Happy Beauty Salon",
    "wof:placetype":"venue"
},
  "geometry": {"coordinates":[-118.072215,33.857091],"type":"Point"}
}