{
  "type": "Feature",
  "properties": {
    "addr:full":"27349 Agoura Rd Agoura Hills CA 91301",
    "addr:housenumber":"27349",
    "addr:postcode":"91301",
    "addr:street":"Agoura Rd",
    "iso:country":"US",
    "sg:address":"27349 Agoura Rd",
    "sg:city":"Agoura Hills",
    "sg:classifiers":[
        {
            "category":"Banks & Credit Unions",
            "subcategory":"Bank",
            "type":"Services"
        }
    ],
    "sg:phone":"+1 818 595 0200",
    "sg:postcode":"91301",
    "sg:province":"CA",
    "sg:tags":[
        "loan",
        "broker",
        "mortgage"
    ],
    "wof:name":"Ownit Mortgage Solutions Inc",
    "wof:placetype":"venue"
},
  "geometry": {"coordinates":[-118.721586,34.137815],"type":"Point"}
}