{
  "type": "Feature",
  "properties": {
    "iso:country":"US",
    "sg:address":"1313 N Milpitas Blvd Ste 235",
    "sg:city":"Milpitas",
    "sg:classifiers":[
        {
            "category":"Real Estate",
            "subcategory":"Real Estate Services",
            "type":"Services"
        },
        {
            "category":"Real Estate",
            "subcategory":"Real Estate Agent",
            "type":"Services"
        }
    ],
    "sg:phone":"+1 408 775 5668",
    "sg:postcode":"95035",
    "sg:province":"CA",
    "sg:website":"www.jonahmarc.com",
    "wof:name":"Jonah Marc Properties",
    "wof:placetype":"venue"
},
  "geometry": {"coordinates":[-121.804423,37.287432],"type":"Point"}
}