{
  "type": "Feature",
  "properties": {
    "iso:country":"US",
    "sg:address":"825 E Evelyn Ave.",
    "sg:city":"Sunnyvale",
    "sg:classifiers":[
        {
            "category":"Real Estate",
            "subcategory":"Real Estate Operator",
            "type":"Services"
        }
    ],
    "sg:phone":"+1 408 733 2306",
    "sg:postcode":"94085",
    "sg:province":"CA",
    "sg:tags":[
        "apartment"
    ],
    "wof:name":"Windsor Ridge Apartments",
    "wof:placetype":"venue"
},
  "geometry": {"coordinates":[-122.01464799999999,37.370663],"type":"Point"}
}