{
  "type": "Feature",
  "properties": {
    "addr:full":"2079 Lincoln St Oroville CA 95966",
    "addr:housenumber":"2079",
    "addr:postcode":"95966",
    "addr:street":"Lincoln St",
    "iso:country":"US",
    "sg:address":"2079 Lincoln St",
    "sg:city":"Oroville",
    "sg:classifiers":[
        {
            "category":"Wholesale",
            "subcategory":"Groceries",
            "type":"Manufacturing & Wholesale Goods"
        }
    ],
    "sg:phone":"+1 530 533 8724",
    "sg:postcode":"95966",
    "sg:province":"CA",
    "sg:tags":[
        "baker"
    ],
    "wof:name":"Sara Lee Bakery Group",
    "wof:placetype":"venue"
},
  "geometry": {"coordinates":[-121.55381199999999,39.506656],"type":"Point"}
}