{
  "type": "Feature",
  "properties": {
    "addr:full":"1434 W 25th St San Pedro CA 90732",
    "addr:housenumber":"1434",
    "addr:postcode":"90732",
    "addr:street":"W 25Th St",
    "iso:country":"US",
    "sg:address":"1434 W 25th St",
    "sg:city":"San Pedro",
    "sg:classifiers":[
        {
            "category":"Personal",
            "subcategory":"Beauty Salon",
            "type":"Services"
        }
    ],
    "sg:phone":"+1 310 519 1900",
    "sg:postcode":"90732",
    "sg:province":"CA",
    "sg:tags":[
        "manicuring"
    ],
    "wof:name":"Nail Pro",
    "wof:placetype":"venue"
},
  "geometry": {"coordinates":[-118.31107299999999,33.72177],"type":"Point"}
}