{
  "type": "Feature",
  "properties": {
    "iso:country":"US",
    "sg:address":"6344 Ferris Sq",
    "sg:city":"San Diego",
    "sg:classifiers":[
        {
            "category":"Manufacturing",
            "subcategory":"Electronics",
            "type":"Manufacturing & Wholesale Goods"
        }
    ],
    "sg:phone":"+1 858 550 7300",
    "sg:postcode":"92121",
    "sg:province":"CA",
    "sg:tags":[
        "equipment",
        "electronic",
        "supply"
    ],
    "sg:website":"www.weco.com",
    "wof:name":"Wintriss Engineering Corp",
    "wof:placetype":"venue"
},
  "geometry": {"coordinates":[-117.18165500000001,32.890302],"type":"Point"}
}