{
  "type": "Feature",
  "properties": {
    "iso:country":"US",
    "sg:address":"9200 Lakewood Blvd",
    "sg:city":"Downey",
    "sg:classifiers":[
        {
            "category":"Food & Beverages",
            "subcategory":"Groceries & Convenience Stores",
            "type":"Retail Goods"
        }
    ],
    "sg:phone":"+1 562 869 2042",
    "sg:postcode":"90240",
    "sg:province":"CA",
    "sg:tags":[
        "supermarket"
    ],
    "wof:name":"Ralphs",
    "wof:placetype":"venue"
},
  "geometry": {"coordinates":[-118.113538,33.954299],"type":"Point"}
}