{
  "type": "Feature",
  "properties": {
    "addr:full":"615 York Street San Francisco CA 94110",
    "addr:housenumber":"615",
    "addr:postcode":"94110",
    "addr:street":"York Street",
    "iso:country":"US",
    "sg:address":"615 York Street",
    "sg:city":"San Francisco",
    "sg:classifiers":[
        {
            "category":"Building & Trades",
            "subcategory":"Cleaning & Sanitation",
            "type":"Services"
        }
    ],
    "sg:phone":"+1 415 684 4422",
    "sg:postcode":"94110",
    "sg:province":"CA",
    "sg:tags":[
        "home"
    ],
    "wof:name":"Holy Hand Cleaning",
    "wof:placetype":"venue"
},
  "geometry": {"coordinates":[-122.408801,37.761374],"type":"Point"}
}