{
  "type": "Feature",
  "properties": {
    "iso:country":"US",
    "sg:address":"102 Raley Blvd",
    "sg:city":"Chico",
    "sg:classifiers":[
        {
            "category":"Insurance",
            "subcategory":"Hazard Insurance",
            "type":"Services"
        },
        {
            "category":"Insurance",
            "subcategory":"Health Insurance",
            "type":"Services"
        }
    ],
    "sg:phone":"+1 530 895 5260",
    "sg:postcode":"95928",
    "sg:province":"CA",
    "sg:tags":[
        "plans-information",
        "referral"
    ],
    "sg:website":"http://www.SweeneyIns.com",
    "wof:name":"Sweeney & Sweeney Insurance Services",
    "wof:placetype":"venue"
},
  "geometry": {"coordinates":[-121.789693,39.716034],"type":"Point"}
}