{
  "type": "Feature",
  "properties": {
    "iso:country":"US",
    "sg:address":"12900 Garden Grove Blvd",
    "sg:city":"Garden Grove",
    "sg:classifiers":[
        {
            "category":"Utilities",
            "subcategory":"Telephone",
            "type":"Services"
        }
    ],
    "sg:phone":"+1 714 537 6615",
    "sg:postcode":"92843",
    "sg:province":"CA",
    "sg:tags":[
        "security",
        "engineering",
        "internet"
    ],
    "wof:name":"Net2link",
    "wof:placetype":"venue"
},
  "geometry": {"coordinates":[-117.907349,33.774351],"type":"Point"}
}