{
  "type": "Feature",
  "properties": {
    "addr:full":"405 E 5th St Santa Ana CA 92701",
    "addr:housenumber":"405",
    "addr:postcode":"92701",
    "addr:street":"E 5Th St",
    "iso:country":"US",
    "sg:address":"405 E 5th St",
    "sg:city":"Santa Ana",
    "sg:classifiers":[
        {
            "category":"Government",
            "subcategory":"Office",
            "type":"Public Place"
        }
    ],
    "sg:phone":"+1 714 796 0188",
    "sg:postcode":"92701",
    "sg:province":"CA",
    "wof:name":"Orange County Cultural Cmptncy",
    "wof:placetype":"venue"
},
  "geometry": {"coordinates":[-117.863556,33.748964],"type":"Point"}
}