{
  "type": "Feature",
  "properties": {
    "iso:country":"US",
    "sg:address":"7611 Apperson St",
    "sg:city":"Tujunga",
    "sg:classifiers":[
        {
            "category":"Professional",
            "subcategory":"Printing & Photocopies",
            "type":"Services"
        }
    ],
    "sg:phone":"+1 818 472 7616",
    "sg:postcode":"91042",
    "sg:province":"CA",
    "sg:tags":[
        "form",
        "printers-business"
    ],
    "wof:name":"Jd Powers Solutions, Inc.",
    "wof:placetype":"venue"
},
  "geometry": {"coordinates":[-118.298304,34.255984],"type":"Point"}
}