{
  "type": "Feature",
  "properties": {
    "addr:full":"2625 Aztec Dr Chico CA 95928",
    "addr:housenumber":"2625",
    "addr:postcode":"95928",
    "addr:street":"Aztec Dr",
    "iso:country":"US",
    "sg:address":"2625 Aztec Dr",
    "sg:city":"Chico",
    "sg:classifiers":[
        {
            "category":"Manufacturing",
            "subcategory":"Metals",
            "type":"Manufacturing & Wholesale Goods"
        }
    ],
    "sg:phone":"+1 530 343 2333",
    "sg:postcode":"95928",
    "sg:province":"CA",
    "sg:tags":[
        "coating",
        "powder"
    ],
    "wof:name":"Chico Color Craft",
    "wof:placetype":"venue"
},
  "geometry": {"coordinates":[-121.819412,39.70709],"type":"Point"}
}