{
  "type": "Feature",
  "properties": {
    "addr:full":"8400 Maple Pl Rancho Cucamonga CA 91730",
    "addr:housenumber":"8400",
    "addr:postcode":"91730",
    "addr:street":"Maple Pl",
    "iso:country":"US",
    "sg:address":"8400 Maple Pl",
    "sg:city":"Rancho Cucamonga",
    "sg:classifiers":[
        {
            "category":"Building & Trades",
            "subcategory":"Pest Control",
            "type":"Services"
        }
    ],
    "sg:phone":"+1 909 476 1443",
    "sg:postcode":"91730",
    "sg:province":"CA",
    "wof:name":"Pro-Active Pest Management",
    "wof:placetype":"venue"
},
  "geometry": {"coordinates":[-117.562881,34.100688],"type":"Point"}
}