{
  "type": "Feature",
  "properties": {
    "addr:full":"605 Susana Ave Redondo Beach CA 90277",
    "addr:housenumber":"605",
    "addr:postcode":"90277",
    "addr:street":"Susana Ave",
    "iso:country":"US",
    "sg:address":"605 Susana Ave",
    "sg:city":"Redondo Beach",
    "sg:classifiers":[
        {
            "category":"Building & Trades",
            "subcategory":"Plumbing",
            "type":"Services"
        }
    ],
    "sg:phone":"+1 310 316 5043",
    "sg:postcode":"90277",
    "sg:province":"CA",
    "sg:tags":[
        "plumbing",
        "contractor"
    ],
    "wof:name":"Bruno Spitz Plumbing",
    "wof:placetype":"venue"
},
  "geometry": {"coordinates":[-118.37469299999999,33.83408],"type":"Point"}
}