{
  "type": "Feature",
  "properties": {
    "iso:country":"US",
    "sg:address":"219 Tank Farm Rd",
    "sg:city":"San Luis Obispo",
    "sg:classifiers":[
        {
            "category":"Wholesale",
            "subcategory":"Auto Parts",
            "type":"Manufacturing & Wholesale Goods"
        }
    ],
    "sg:phone":"+1 805 543 4134",
    "sg:postcode":"93401",
    "sg:province":"CA",
    "sg:tags":[
        "equipment",
        "truck"
    ],
    "wof:name":"San Luis Truck Svc Garage",
    "wof:placetype":"venue"
},
  "geometry": {"coordinates":[-120.668088,35.246726],"type":"Point"}
}