{
  "type": "Feature",
  "properties": {
    "addr:full":"39525 Los Alamos Rd Murrieta CA 92563",
    "addr:housenumber":"39525",
    "addr:postcode":"92563",
    "addr:street":"Los Alamos Rd",
    "iso:country":"US",
    "sg:address":"39525 Los Alamos Rd",
    "sg:city":"Murrieta",
    "sg:classifiers":[
        {
            "category":"Restaurant",
            "type":"Food & Drink"
        }
    ],
    "sg:phone":"+1 951 698 5767",
    "sg:postcode":"92563",
    "sg:province":"CA",
    "wof:name":"Peony Chinese Cuisine",
    "wof:placetype":"venue"
},
  "geometry": {"coordinates":[-117.177648,33.574905],"type":"Point"}
}