{
  "type": "Feature",
  "properties": {
    "iso:country":"US",
    "sg:address":"1190 S Victoria Ave",
    "sg:city":"Ventura",
    "sg:classifiers":[
        {
            "category":"Banks & Credit Unions",
            "subcategory":"Bank",
            "type":"Services"
        }
    ],
    "sg:phone":"+1 805 650 9640",
    "sg:postcode":"93003",
    "sg:province":"CA",
    "sg:tags":[
        "escrow"
    ],
    "wof:name":"Westland Escrow",
    "wof:placetype":"venue"
},
  "geometry": {"coordinates":[-119.212271,34.265234],"type":"Point"}
}