{
  "type": "Feature",
  "properties": {
    "iso:country":"US",
    "sg:address":"870 Innes Ave",
    "sg:city":"San Francisco",
    "sg:classifiers":[
        {
            "category":"Social Services",
            "type":"Services"
        }
    ],
    "sg:phone":"+1 415 647 2912",
    "sg:postcode":"94124",
    "sg:province":"CA",
    "sg:tags":[
        "organization",
        "welfare"
    ],
    "wof:name":"Family Restoration House",
    "wof:placetype":"venue"
},
  "geometry": {"coordinates":[-122.372006,37.729873],"type":"Point"}
}