{
  "type": "Feature",
  "properties": {
    "addr:full":"1862 Dunn Rd Merced CA 95340",
    "addr:housenumber":"1862",
    "addr:postcode":"95340",
    "addr:street":"Dunn Rd",
    "iso:country":"US",
    "sg:address":"1862 Dunn Rd",
    "sg:city":"Merced",
    "sg:classifiers":[
        {
            "category":"Restaurant",
            "type":"Food & Drink"
        }
    ],
    "sg:phone":"+1 209 724 9363",
    "sg:postcode":"95340",
    "sg:province":"CA",
    "wof:name":"T's Asian Bistro",
    "wof:placetype":"venue"
},
  "geometry": {"coordinates":[-120.450062,37.339393],"type":"Point"}
}