{
  "type": "Feature",
  "properties": {
    "iso:country":"US",
    "sg:address":"3094 Cedar Ravine Rd",
    "sg:city":"Placerville",
    "sg:classifiers":[
        {
            "category":"Retail",
            "subcategory":"Funeral Services",
            "type":"Services"
        }
    ],
    "sg:phone":"+1 530 626 9508",
    "sg:postcode":"95667",
    "sg:province":"CA",
    "sg:tags":[
        "crematory"
    ],
    "wof:name":"Foothill Cremation & Burial",
    "wof:placetype":"venue"
},
  "geometry": {"coordinates":[-120.794518,38.726143],"type":"Point"}
}