{
  "type": "Feature",
  "properties": {
    "addr:full":"36 Terrace Cir Laguna Niguel CA 92677",
    "addr:housenumber":"36",
    "addr:postcode":"92677",
    "addr:street":"Terrace Cir",
    "iso:country":"US",
    "sg:address":"36 Terrace Cir",
    "sg:city":"Laguna Niguel",
    "sg:classifiers":[
        {
            "category":"Manufacturing",
            "subcategory":"Furniture",
            "type":"Manufacturing & Wholesale Goods"
        }
    ],
    "sg:phone":"+1 949 293 1888",
    "sg:postcode":"92677",
    "sg:province":"CA",
    "sg:tags":[
        "household",
        "metal",
        "mfg"
    ],
    "wof:name":"Pierres Et Terres De France",
    "wof:placetype":"venue"
},
  "geometry": {"coordinates":[-117.70492,33.503517],"type":"Point"}
}