{
  "type": "Feature",
  "properties": {
    "iso:country":"US",
    "sg:address":"145 E Ojai Ave",
    "sg:city":"Ojai",
    "sg:classifiers":[
        {
            "category":"Arts & Performance",
            "subcategory":"Theater",
            "type":"Entertainment"
        }
    ],
    "sg:phone":"+1 805 646 1011",
    "sg:postcode":"93023",
    "sg:province":"CA",
    "wof:name":"Ojai Playhouse",
    "wof:placetype":"venue"
},
  "geometry": {"coordinates":[-119.24637,34.44772],"type":"Point"}
}