{
  "type": "Feature",
  "properties": {
    "iso:country":"US",
    "sg:address":"4606 Meridian Ave",
    "sg:city":"San Jose",
    "sg:classifiers":[
        {
            "category":"Professional",
            "subcategory":"Accounting & Tax Preparation",
            "type":"Services"
        }
    ],
    "sg:phone":"+1 408 267 8202",
    "sg:postcode":"95124",
    "sg:province":"CA",
    "sg:tags":[
        "return",
        "filing"
    ],
    "wof:name":"Hancock Financial",
    "wof:placetype":"venue"
},
  "geometry": {"coordinates":[-121.898644,37.255988],"type":"Point"}
}