{
  "type": "Feature",
  "properties": {
    "addr:full":"9711 Dublin Canyon Rd Castro Valley CA 94552",
    "addr:housenumber":"9711",
    "addr:postcode":"94552",
    "addr:street":"Dublin Canyon Rd",
    "iso:country":"US",
    "sg:address":"9711 Dublin Canyon Rd",
    "sg:city":"Castro Valley",
    "sg:classifiers":[
        {
            "category":"Home & Garden",
            "subcategory":"Garden Supply",
            "type":"Retail Goods"
        },
        {
            "category":"Food & Beverages",
            "subcategory":"Farmers Market",
            "type":"Retail Goods"
        },
        {
            "category":"Arts & Performance",
            "subcategory":"Arts Center",
            "type":"Entertainment"
        }
    ],
    "sg:phone":"+1 510 886 6015",
    "sg:postcode":"94552",
    "sg:province":"CA",
    "sg:tags":[
        "nursery",
        "gardening"
    ],
    "sg:website":"www.moorespumpkinpatch.com",
    "wof:name":"Moore's Pumpkin Patch & Christmas Trees",
    "wof:placetype":"venue"
},
  "geometry": {"coordinates":[-122.008003,37.702999],"type":"Point"}
}