{
  "type": "Feature",
  "properties": {
    "addr:full":"839 Richland Rd Yuba City CA 95991",
    "addr:housenumber":"839",
    "addr:postcode":"95991",
    "addr:street":"Richland Rd",
    "iso:country":"US",
    "sg:address":"839 Richland Rd",
    "sg:city":"Yuba City",
    "sg:classifiers":[
        {
            "category":"Building & Trades",
            "subcategory":"Cleaning & Sanitation",
            "type":"Services"
        }
    ],
    "sg:phone":"+1 530 673 4789",
    "sg:postcode":"95991",
    "sg:province":"CA",
    "sg:tags":[
        "ceiling"
    ],
    "wof:name":"Overhead Impressions",
    "wof:placetype":"venue"
},
  "geometry": {"coordinates":[-121.624056,39.118188],"type":"Point"}
}