{
  "type": "Feature",
  "properties": {
    "addr:full":"9852 Vicksburg Dr Huntington Beach CA 92646",
    "addr:housenumber":"9852",
    "addr:postcode":"92646",
    "addr:street":"Vicksburg Dr",
    "iso:country":"US",
    "sg:address":"9852 Vicksburg Dr",
    "sg:city":"Huntington Beach",
    "sg:classifiers":[
        {
            "category":"Manufacturing",
            "subcategory":"Electronics",
            "type":"Manufacturing & Wholesale Goods"
        }
    ],
    "sg:phone":"+1 714 963 4861",
    "sg:postcode":"92646",
    "sg:province":"CA",
    "sg:tags":[
        "mfg",
        "boards",
        "circuit",
        "printed"
    ],
    "wof:name":"Hasan Rashida",
    "wof:placetype":"venue"
},
  "geometry": {"coordinates":[-117.956244,33.666165],"type":"Point"}
}