{
  "type": "Feature",
  "properties": {
    "addr:full":"75 Castro Ave San Rafael CA 94901",
    "addr:housenumber":"75",
    "addr:postcode":"94901",
    "addr:street":"Castro Ave",
    "iso:country":"US",
    "sg:address":"75 Castro Ave",
    "sg:city":"San Rafael",
    "sg:classifiers":[
        {
            "category":"Shopping",
            "subcategory":"Computers & Home Electronics",
            "type":"Retail Goods"
        }
    ],
    "sg:phone":"+1 415 457 5430",
    "sg:postcode":"94901",
    "sg:province":"CA",
    "wof:name":"Communications Center",
    "wof:placetype":"venue"
},
  "geometry": {"coordinates":[-122.50330200000001,37.960538],"type":"Point"}
}