{
  "type": "Feature",
  "properties": {
    "addr:full":"8391 Beverly Blvd Los Angeles CA 90048",
    "addr:housenumber":"8391",
    "addr:postcode":"90048",
    "addr:street":"Beverly Blvd",
    "iso:country":"US",
    "sg:address":"8391 Beverly Blvd",
    "sg:city":"Los Angeles",
    "sg:classifiers":[
        {
            "category":"Manufacturing",
            "subcategory":"Furniture",
            "type":"Manufacturing & Wholesale Goods"
        }
    ],
    "sg:phone":"+1 310 281 1900",
    "sg:postcode":"90048",
    "sg:province":"CA",
    "sg:tags":[
        "animal",
        "mfg"
    ],
    "wof:name":"Puchibag",
    "wof:placetype":"venue"
},
  "geometry": {"coordinates":[-118.37247600000001,34.076131],"type":"Point"}
}