{
  "type": "Feature",
  "properties": {
    "addr:full":"5334 E Washington Blvd City Of Commerce CA 90040",
    "addr:housenumber":"5334",
    "addr:postcode":"90040",
    "addr:street":"E Washington Blvd",
    "iso:country":"US",
    "sg:address":"5334 E Washington Blvd",
    "sg:city":"City Of Commerce",
    "sg:classifiers":[
        {
            "category":"Manufacturing",
            "subcategory":"Glass & Minerals",
            "type":"Manufacturing & Wholesale Goods"
        },
        {
            "category":"Manufacturing",
            "subcategory":"Apparel",
            "type":"Manufacturing & Wholesale Goods"
        }
    ],
    "sg:phone":"+1 323 261 5350",
    "sg:postcode":"90040",
    "sg:province":"CA",
    "sg:tags":[
        "ready",
        "concrete",
        "clothing",
        "mfg"
    ],
    "wof:name":"Ready Apparel Group",
    "wof:placetype":"venue"
},
  "geometry": {"coordinates":[-118.16374500000001,34.0016],"type":"Point"}
}