{
  "type": "Feature",
  "properties": {
    "addr:full":"5242 Katella Ave Ste 103 Los Alamitos CA 90720",
    "addr:housenumber":"5242",
    "addr:postcode":"90720",
    "addr:street":"Katella Ave Ste 103",
    "iso:country":"US",
    "sg:address":"5242 Katella Ave Ste 103",
    "sg:city":"Los Alamitos",
    "sg:classifiers":[
        {
            "category":"Retail",
            "subcategory":"Animal Services",
            "type":"Services"
        }
    ],
    "sg:phone":"+1 562 799 9196",
    "sg:postcode":"90720",
    "sg:province":"CA",
    "sg:tags":[
        "pet"
    ],
    "sg:website":"www.lukasracing.com",
    "wof:name":"Lukas Racing Stables",
    "wof:placetype":"venue"
},
  "geometry": {"coordinates":[-118.041,33.802898],"type":"Point"}
}