{
  "type": "Feature",
  "properties": {
    "iso:country":"US",
    "sg:address":"9528 Richmond Pl",
    "sg:city":"Rancho Cucamonga",
    "sg:classifiers":[
        {
            "category":"Shopping",
            "subcategory":"Bicycles & Sporting Goods",
            "type":"Retail Goods"
        }
    ],
    "sg:phone":"+1 909 980 0841",
    "sg:postcode":"91730",
    "sg:province":"CA",
    "sg:tags":[
        "equipment",
        "arts",
        "supply",
        "martial"
    ],
    "sg:website":"www.goldentiger.com",
    "wof:name":"Golden Tiger Martial Arts",
    "wof:placetype":"venue"
},
  "geometry": {"coordinates":[-117.55260699999999,34.084589],"type":"Point"}
}