{
  "type": "Feature",
  "properties": {
    "addr:full":"13 Quail Ct San Rafael CA 94903",
    "addr:housenumber":"13",
    "addr:postcode":"94903",
    "addr:street":"Quail Ct",
    "iso:country":"US",
    "sg:address":"13 Quail Ct",
    "sg:city":"San Rafael",
    "sg:classifiers":[
        {
            "category":"Professional",
            "subcategory":"Management & Consulting",
            "type":"Services"
        }
    ],
    "sg:phone":"+1 415 499 0639",
    "sg:postcode":"94903",
    "sg:province":"CA",
    "sg:tags":[
        "communications",
        "consultant"
    ],
    "sg:website":"www.nlpmarin.com",
    "wof:name":"NLP Marin",
    "wof:placetype":"venue"
},
  "geometry": {"coordinates":[-122.543324,38.034489],"type":"Point"}
}