{
  "type": "Feature",
  "properties": {
    "iso:country":"US",
    "sg:address":"6370 Split Rock Ave",
    "sg:city":"Twentynine Palms",
    "sg:classifiers":[
        {
            "category":"Health Services",
            "subcategory":"Doctor",
            "type":"Services"
        }
    ],
    "sg:phone":"+1 760 367 7100",
    "sg:postcode":"92277",
    "sg:province":"CA",
    "sg:tags":[
        "physician",
        "surgeon"
    ],
    "wof:name":"Morongo Basin Ob/Gyn Medical",
    "wof:placetype":"venue"
},
  "geometry": {"coordinates":[-116.060858,34.139196],"type":"Point"}
}