{
  "type": "Feature",
  "properties": {
    "iso:country":"US",
    "sg:address":"19441 Neuralia Rd",
    "sg:city":"California City",
    "sg:classifiers":[
        {
            "category":"Retail",
            "subcategory":"Auto Repair",
            "type":"Services"
        }
    ],
    "sg:phone":"+1 760 373 8575",
    "sg:postcode":"93505",
    "sg:province":"CA",
    "sg:tags":[
        "repairing",
        "automobile"
    ],
    "wof:name":"Kustoms By Jean Paul",
    "wof:placetype":"venue"
},
  "geometry": {"coordinates":[-117.985758,35.103651],"type":"Point"}
}