{
  "type": "Feature",
  "properties": {
    "iso:country":"US",
    "sg:address":"4909 Date Ave",
    "sg:city":"Sacramento",
    "sg:classifiers":[
        {
            "category":"Building & Trades",
            "subcategory":"Cleaning & Sanitation",
            "type":"Services"
        }
    ],
    "sg:phone":"+1 916 338 3114",
    "sg:postcode":"95841",
    "sg:province":"CA",
    "sg:tags":[
        "house"
    ],
    "wof:name":"All American House Cleaning",
    "wof:placetype":"venue"
},
  "geometry": {"coordinates":[-121.355243,38.654687],"type":"Point"}
}