{
  "type": "Feature",
  "properties": {
    "iso:country":"US",
    "sg:address":"1148 E 78th St",
    "sg:city":"Los Angeles",
    "sg:classifiers":[
        {
            "category":"Retail",
            "subcategory":"Repair Shop",
            "type":"Services"
        }
    ],
    "sg:phone":"+1 323 589 7191",
    "sg:postcode":"90001",
    "sg:province":"CA",
    "sg:tags":[
        "equipment",
        "video"
    ],
    "wof:name":"Rodriguez TV Svc",
    "wof:placetype":"venue"
},
  "geometry": {"coordinates":[-118.256297,33.96796],"type":"Point"}
}