{
  "type": "Feature",
  "properties": {
    "addr:full":"99 Scripps Dr Ste 200 Sacramento CA 95825",
    "addr:housenumber":"99",
    "addr:postcode":"95825",
    "addr:street":"Scripps Dr Ste 200",
    "iso:country":"US",
    "sg:address":"99 Scripps Dr Ste 200",
    "sg:city":"Sacramento",
    "sg:classifiers":[
        {
            "category":"Health Services",
            "subcategory":"Dentist",
            "type":"Services"
        }
    ],
    "sg:phone":"+1 916 929 5050",
    "sg:postcode":"95825",
    "sg:province":"CA",
    "sg:website":"www.sacperio.com",
    "wof:name":"Campus Commons Periodontics",
    "wof:placetype":"venue"
},
  "geometry": {"coordinates":[-121.409254,38.571689],"type":"Point"}
}