{
  "type": "Feature",
  "properties": {
    "iso:country":"US",
    "sg:address":"2876 Westmoreland Ave",
    "sg:city":"Redwood City",
    "sg:classifiers":[
        {
            "category":"Building & Trades",
            "subcategory":"Construction",
            "type":"Services"
        }
    ],
    "sg:phone":"+1 650 281 8344",
    "sg:postcode":"94063",
    "sg:province":"CA",
    "sg:tags":[
        "general",
        "contractor"
    ],
    "wof:name":"Lomas Construction",
    "wof:placetype":"venue"
},
  "geometry": {"coordinates":[-122.21119,37.472555],"type":"Point"}
}