{
  "type": "Feature",
  "properties": {
    "iso:country":"US",
    "sg:address":"Peninsula School of Performing Arts 700 Silver Spur",
    "sg:city":"Rolling Hills Estates",
    "sg:classifiers":[
        {
            "category":"Education",
            "subcategory":"Dance Studio",
            "type":"Public Place"
        }
    ],
    "sg:phone":"+1 310 872 7763",
    "sg:postcode":"90274",
    "sg:province":"CA",
    "sg:website":"www.niasun.com",
    "wof:name":"Nia",
    "wof:placetype":"venue"
},
  "geometry": {"coordinates":[-118.369975,33.771252],"type":"Point"}
}