{
  "type": "Feature",
  "properties": {
    "iso:country":"US",
    "sg:address":"17605 Fabrica Way",
    "sg:city":"Cerritos",
    "sg:classifiers":[
        {
            "category":"Wholesale",
            "subcategory":"Office Equipment",
            "type":"Manufacturing & Wholesale Goods"
        }
    ],
    "sg:phone":"+1 562 921 4360",
    "sg:postcode":"90703",
    "sg:province":"CA",
    "sg:tags":[
        "machine",
        "duplicating",
        "supply"
    ],
    "wof:name":"Standard Manifold",
    "wof:placetype":"venue"
},
  "geometry": {"coordinates":[-118.031184,33.871451],"type":"Point"}
}