{
  "type": "Feature",
  "properties": {
    "addr:full":"12046 Jacaranda Ave Ste D Hesperia CA 92345",
    "addr:housenumber":"12046",
    "addr:postcode":"92345",
    "addr:street":"Jacaranda Ave Ste D",
    "iso:country":"US",
    "sg:address":"12046 Jacaranda Ave Ste D",
    "sg:city":"Hesperia",
    "sg:classifiers":[
        {
            "category":"Building & Trades",
            "subcategory":"Construction",
            "type":"Services"
        }
    ],
    "sg:phone":"+1 760 949 9972",
    "sg:postcode":"92345",
    "sg:province":"CA",
    "sg:tags":[
        "repair",
        "system",
        "specialty",
        "heating",
        "contractor",
        "air conditioning"
    ],
    "wof:name":"Independent Air Group Incorporated",
    "wof:placetype":"venue"
},
  "geometry": {"coordinates":[-117.263318,34.468315],"type":"Point"}
}