{
  "type": "Feature",
  "properties": {
    "iso:country":"US",
    "sg:address":"2936 Cliff Dr",
    "sg:city":"Newport Beach",
    "sg:classifiers":[
        {
            "category":"Wholesale",
            "subcategory":"Durable Goods & Equipment",
            "type":"Manufacturing & Wholesale Goods"
        }
    ],
    "sg:phone":"+1 949 548 5011",
    "sg:postcode":"92663",
    "sg:province":"CA",
    "wof:name":"Diskovery Publication Graphics",
    "wof:placetype":"venue"
},
  "geometry": {"coordinates":[-117.92547999999999,33.62268],"type":"Point"}
}