{
  "type": "Feature",
  "properties": {
    "addr:full":"2254 Floyd Ave Modesto CA 95355",
    "addr:housenumber":"2254",
    "addr:postcode":"ca 95355",
    "addr:street":"Floyd Ave",
    "iso:country":"US",
    "sg:address":"2254 Floyd Ave",
    "sg:city":"Modesto",
    "sg:classifiers":[
        {
            "category":"Health Services",
            "subcategory":"Chiropractor",
            "type":"Services"
        }
    ],
    "sg:phone":"+1 209 551 4073",
    "sg:postcode":"95355",
    "sg:province":"CA",
    "wof:name":"Amy Parker DC",
    "wof:placetype":"venue"
},
  "geometry": {"coordinates":[-120.955473,37.677991],"type":"Point"}
}