{
  "type": "Feature",
  "properties": {
    "addr:full":"9755 Sycamore Canyon Rd Moreno Valley CA 92557",
    "addr:housenumber":"9755",
    "addr:postcode":"92557",
    "addr:street":"Sycamore Canyon Rd",
    "iso:country":"US",
    "sg:address":"9755 Sycamore Canyon Rd",
    "sg:city":"Moreno Valley",
    "sg:classifiers":[
        {
            "category":"Shopping",
            "subcategory":"Computers & Home Electronics",
            "type":"Retail Goods"
        }
    ],
    "sg:phone":"+1 951 653 2988",
    "sg:postcode":"92557",
    "sg:province":"CA",
    "sg:tags":[
        "repair"
    ],
    "wof:name":"C & W T V",
    "wof:placetype":"venue"
},
  "geometry": {"coordinates":[-117.26644,33.980486],"type":"Point"}
}