{
  "type": "Feature",
  "properties": {
    "iso:country":"US",
    "sg:address":"4801 Pacific Coast Hwy",
    "sg:city":"Torrance",
    "sg:classifiers":[
        {
            "category":"Education",
            "subcategory":"School",
            "type":"Public Place"
        }
    ],
    "sg:phone":"+1 310 373 1177",
    "sg:postcode":"90505",
    "sg:province":"CA",
    "sg:tags":[
        "academic",
        "special"
    ],
    "wof:name":"Asahi Gakugn",
    "wof:placetype":"venue"
},
  "geometry": {"coordinates":[-118.364431,33.810233],"type":"Point"}
}