{
  "type": "Feature",
  "properties": {
    "iso:country":"US",
    "sg:address":"2059 Camden Ave",
    "sg:city":"San Jose",
    "sg:classifiers":[
        {
            "category":"Freight",
            "type":"Transportation"
        }
    ],
    "sg:phone":"+1 408 365 9666",
    "sg:postcode":"95124",
    "sg:province":"CA",
    "sg:tags":[
        "operator",
        "local",
        "trucking"
    ],
    "wof:name":"Overflow Delivery",
    "wof:placetype":"venue"
},
  "geometry": {"coordinates":[-121.93469899999999,37.26209],"type":"Point"}
}