{
  "type": "Feature",
  "properties": {
    "addr:full":"633 S Broadway Los Angeles CA 90014",
    "addr:housenumber":"633",
    "addr:postcode":"90014",
    "addr:street":"S Broadway",
    "iso:country":"US",
    "sg:address":"633 S Broadway",
    "sg:city":"Los Angeles",
    "sg:classifiers":[
        {
            "category":"Shopping",
            "subcategory":"Music",
            "type":"Retail Goods"
        }
    ],
    "sg:phone":"+1 213 629 8045",
    "sg:postcode":"90014",
    "sg:province":"CA",
    "sg:tags":[
        "dvd's"
    ],
    "wof:name":"Barba Azul",
    "wof:placetype":"venue"
},
  "geometry": {"coordinates":[-118.252921,34.045932],"type":"Point"}
}