{
  "type": "Feature",
  "properties": {
    "iso:country":"US",
    "sg:address":"7148 Johnson Dr",
    "sg:city":"Pleasanton",
    "sg:classifiers":[
        {
            "category":"Recreation",
            "type":"Entertainment"
        }
    ],
    "sg:phone":"+1 925 847 8702",
    "sg:postcode":"94588",
    "sg:province":"CA",
    "sg:tags":[
        "charter",
        "boat"
    ],
    "wof:name":"World Class Charters",
    "wof:placetype":"venue"
},
  "geometry": {"coordinates":[-121.91462300000001,37.691012],"type":"Point"}
}