{
  "type": "Feature",
  "properties": {
    "addr:full":"12645 Picrus St San Diego CA 92129",
    "addr:housenumber":"12645",
    "addr:postcode":"92129",
    "addr:street":"Picrus St",
    "iso:country":"US",
    "sg:address":"12645 Picrus St",
    "sg:city":"San Diego",
    "sg:classifiers":[
        {
            "category":"Manufacturing",
            "subcategory":"Tools & Machinery",
            "type":"Manufacturing & Wholesale Goods"
        }
    ],
    "sg:phone":"+1 858 538 8761",
    "sg:postcode":"92129",
    "sg:province":"CA",
    "sg:tags":[
        "sterilization",
        "medical",
        "devices",
        "cancer",
        "treatment"
    ],
    "wof:name":"Lummed Inc",
    "wof:placetype":"venue"
},
  "geometry": {"coordinates":[-117.141925,32.945943],"type":"Point"}
}