{
  "type": "Feature",
  "properties": {
    "iso:country":"US",
    "sg:address":"6420 Wilshire Blvd",
    "sg:city":"Los Angeles",
    "sg:classifiers":[
        {
            "category":"Building & Trades",
            "subcategory":"Construction",
            "type":"Services"
        }
    ],
    "sg:phone":"+1 323 655 1750",
    "sg:postcode":"90048",
    "sg:province":"CA",
    "sg:tags":[
        "general",
        "contractor"
    ],
    "wof:name":"Mirage Construction",
    "wof:placetype":"venue"
},
  "geometry": {"coordinates":[-118.371139,34.063998],"type":"Point"}
}