{
  "type": "Feature",
  "properties": {
    "iso:country":"US",
    "sg:address":"73925 Hwy 111",
    "sg:city":"Palm Desert",
    "sg:classifiers":[
        {
            "category":"Health Services",
            "subcategory":"Doctor",
            "type":"Services"
        }
    ],
    "sg:phone":"+1 760 341 0077",
    "sg:postcode":"92260",
    "sg:province":"CA",
    "sg:tags":[
        "dentist"
    ],
    "wof:name":"Steven T Rivera DDS",
    "wof:placetype":"venue"
},
  "geometry": {"coordinates":[-116.375536,33.721228],"type":"Point"}
}