{
  "type": "Feature",
  "properties": {
    "addr:full":"980 Ontario Mills Dr Ontario CA 91764",
    "addr:housenumber":"980",
    "addr:postcode":"91764",
    "addr:street":"Ontario Mills Dr",
    "iso:country":"US",
    "sg:address":"980 Ontario Mills Dr",
    "sg:city":"Ontario",
    "sg:classifiers":[
        {
            "category":"Real Estate",
            "subcategory":"Real Estate Agent",
            "type":"Services"
        }
    ],
    "sg:phone":"+1 909 476 9824",
    "sg:postcode":"91764",
    "sg:province":"CA",
    "wof:name":"Day Break Properties",
    "wof:placetype":"venue"
},
  "geometry": {"coordinates":[-117.547889,34.070476],"type":"Point"}
}