{
  "type": "Feature",
  "properties": {
    "addr:full":"3834 4th Ave San Diego CA 92103",
    "addr:housenumber":"3834",
    "addr:postcode":"92103",
    "addr:street":"4Th Ave",
    "iso:country":"US",
    "sg:address":"3834 4th Ave",
    "sg:city":"San Diego",
    "sg:classifiers":[
        {
            "category":"Shopping",
            "subcategory":"Hobbies, Toys, & Games",
            "type":"Retail Goods"
        }
    ],
    "sg:phone":"+1 619 295 7340",
    "sg:postcode":"92103",
    "sg:province":"CA",
    "sg:tags":[
        "bookstore",
        "eating"
    ],
    "wof:name":"Whistle Stop",
    "wof:placetype":"venue"
},
  "geometry": {"coordinates":[-117.161593,32.747408],"type":"Point"}
}