{
  "type": "Feature",
  "properties": {
    "addr:full":"40831 Fremont Blvd Fremont CA 94538",
    "addr:housenumber":"40831",
    "addr:postcode":"94538",
    "addr:street":"Fremont Blvd",
    "iso:country":"US",
    "sg:address":"40831 Fremont Blvd",
    "sg:city":"Fremont",
    "sg:classifiers":[
        {
            "category":"Restaurant",
            "type":"Food & Drink"
        }
    ],
    "sg:menulink":"http://www.allmenus.com/ca/fremont/75115-round-table-pizza/menu/",
    "sg:phone":"+1 510 651 2111",
    "sg:postcode":"94538",
    "sg:province":"CA",
    "sg:tags":[
        "american",
        "pizza"
    ],
    "wof:name":"Round Table Pizza",
    "wof:placetype":"venue"
},
  "geometry": {"coordinates":[-121.961951,37.5344],"type":"Point"}
}