{
  "type": "Feature",
  "properties": {
    "addr:full":"3666 Lightfare Ct San Jose CA 95121",
    "addr:housenumber":"3666",
    "addr:postcode":"95121",
    "addr:street":"Lightfare Ct",
    "iso:country":"US",
    "sg:address":"3666 Lightfare Ct",
    "sg:city":"San Jose",
    "sg:classifiers":[
        {
            "category":"Building & Trades",
            "subcategory":"Landscaping Services",
            "type":"Services"
        }
    ],
    "sg:phone":"+1 408 966 9509",
    "sg:postcode":"95121",
    "sg:province":"CA",
    "sg:tags":[
        "landscape"
    ],
    "wof:name":"Arroyos Landscape Mainte",
    "wof:placetype":"venue"
},
  "geometry": {"coordinates":[-121.814538,37.298196],"type":"Point"}
}