{
  "type": "Feature",
  "properties": {
    "addr:full":"17080 Foothill Blvd Fontana CA 92335",
    "addr:housenumber":"17080",
    "addr:postcode":"92335",
    "addr:street":"Foothill Blvd",
    "iso:country":"US",
    "sg:address":"17080 Foothill Blvd",
    "sg:city":"Fontana",
    "sg:classifiers":[
        {
            "category":"Food & Beverages",
            "subcategory":"Groceries & Convenience Stores",
            "type":"Retail Goods"
        }
    ],
    "sg:phone":"+1 909 829 4172",
    "sg:postcode":"92335",
    "sg:province":"CA",
    "wof:name":"Sami's Three Market & Liquor",
    "wof:placetype":"venue"
},
  "geometry": {"coordinates":[-117.433712,34.106703],"type":"Point"}
}