{
  "type": "Feature",
  "properties": {
    "iso:country":"US",
    "sg:address":"3115 Myers St",
    "sg:city":"Oroville",
    "sg:classifiers":[
        {
            "category":"Organizations",
            "subcategory":"Religious Organization",
            "type":"Services"
        }
    ],
    "sg:phone":"+1 530 533 6489",
    "sg:postcode":"95966",
    "sg:province":"CA",
    "sg:tags":[
        "denomination",
        "churches-various",
        "church"
    ],
    "wof:name":"Trinity Bible Church",
    "wof:placetype":"venue"
},
  "geometry": {"coordinates":[-121.54839699999999,39.500271],"type":"Point"}
}