{
  "type": "Feature",
  "properties": {
    "addr:full":"2729 Wawona Pl Los Angeles CA 90065",
    "addr:housenumber":"2729",
    "addr:postcode":"90065",
    "addr:street":"Wawona Pl",
    "iso:country":"US",
    "sg:address":"2729 Wawona Pl",
    "sg:city":"Los Angeles",
    "sg:classifiers":[
        {
            "category":"Insurance",
            "subcategory":"Insurance Agent",
            "type":"Services"
        }
    ],
    "sg:phone":"+1 213 550 8009",
    "sg:postcode":"90065",
    "sg:province":"CA",
    "wof:name":"AFLAC",
    "wof:placetype":"venue"
},
  "geometry": {"coordinates":[-118.22388100000001,34.134343],"type":"Point"}
}