{
  "type": "Feature",
  "properties": {
    "iso:country":"US",
    "sg:address":"1300 San Juan Rd",
    "sg:city":"Hollister",
    "sg:classifiers":[
        {
            "category":"Food & Beverages",
            "subcategory":"Groceries & Convenience Stores",
            "type":"Retail Goods"
        }
    ],
    "sg:phone":"+1 831 637 0796",
    "sg:postcode":"95023",
    "sg:province":"CA",
    "wof:name":"Quik Stop",
    "wof:placetype":"venue"
},
  "geometry": {"coordinates":[-121.42136000000001,36.853153],"type":"Point"}
}