{
  "type": "Feature",
  "properties": {
    "addr:full":"336 Hillsdale Mall San Mateo CA 94403",
    "addr:housenumber":"336",
    "addr:postcode":"94403",
    "addr:street":"Hillsdale Mall",
    "iso:country":"US",
    "sg:address":"336 Hillsdale Mall",
    "sg:city":"San Mateo",
    "sg:classifiers":[
        {
            "category":"Shopping",
            "subcategory":"Clothing, Apparel, & Fashions",
            "type":"Retail Goods"
        }
    ],
    "sg:phone":"+1 650 212 5455",
    "sg:postcode":"94403",
    "sg:province":"CA",
    "sg:tags":[
        "accessory",
        "clothing",
        "women's"
    ],
    "wof:name":"j.jill",
    "wof:placetype":"venue"
},
  "geometry": {"coordinates":[-122.30033,37.53734],"type":"Point"}
}