{
  "type": "Feature",
  "properties": {
    "addr:full":"6142 W Laguna Ave Riverdale CA 93656",
    "addr:housenumber":"6142",
    "addr:postcode":"93656",
    "addr:street":"W Laguna Ave",
    "iso:country":"US",
    "sg:address":"6142 W Laguna Ave",
    "sg:city":"Riverdale",
    "sg:classifiers":[
        {
            "category":"Autos & Motor Vehicles",
            "subcategory":"Auto Supplies",
            "type":"Retail Goods"
        }
    ],
    "sg:phone":"+1 559 867 3274",
    "sg:postcode":"93656",
    "sg:province":"CA",
    "sg:tags":[
        "tire"
    ],
    "wof:name":"M W Tire",
    "wof:placetype":"venue"
},
  "geometry": {"coordinates":[-119.9117,36.416232],"type":"Point"}
}