{
  "type": "Feature",
  "properties": {
    "addr:full":"20611 Hawthorne Blvd Torrance CA 90503",
    "addr:housenumber":"20611",
    "addr:postcode":"90503",
    "addr:street":"Hawthorne Blvd",
    "iso:country":"US",
    "sg:address":"20611 Hawthorne Blvd",
    "sg:city":"Torrance",
    "sg:classifiers":[
        {
            "category":"Shopping",
            "subcategory":"Department Store",
            "type":"Retail Goods"
        }
    ],
    "sg:phone":"+1 310 542 8133",
    "sg:postcode":"90503",
    "sg:province":"CA",
    "sg:tags":[
        "shop"
    ],
    "sg:website":"www.pier1.com",
    "wof:name":"Pier 1 Imports",
    "wof:placetype":"venue"
},
  "geometry": {"coordinates":[-118.353686,33.841458],"type":"Point"}
}