{
  "type": "Feature",
  "properties": {
    "addr:full":"8121 Sunrise East Way Fair Oaks CA 95628",
    "addr:housenumber":"8121",
    "addr:postcode":"95628",
    "addr:street":"Sunrise East Way",
    "iso:country":"US",
    "sg:address":"8121 Sunrise East Way",
    "sg:city":"Fair Oaks",
    "sg:classifiers":[
        {
            "category":"Home & Garden",
            "subcategory":"Building Materials",
            "type":"Retail Goods"
        }
    ],
    "sg:phone":"+1 916 338 2627",
    "sg:postcode":"95628",
    "sg:province":"CA",
    "sg:tags":[
        "glass",
        "window",
        "plate"
    ],
    "wof:name":"K 1 Auto Windshield Repair",
    "wof:placetype":"venue"
},
  "geometry": {"coordinates":[-121.259708,38.672594],"type":"Point"}
}