{
  "type": "Feature",
  "properties": {
    "addr:full":"430 W Arbor Vitae St Inglewood CA 90301",
    "addr:housenumber":"430",
    "addr:postcode":"90301",
    "addr:street":"W Arbor Vitae St",
    "iso:country":"US",
    "sg:address":"430 W Arbor Vitae St",
    "sg:city":"Inglewood",
    "sg:classifiers":[
        {
            "category":"Food & Beverages",
            "subcategory":"Groceries & Convenience Stores",
            "type":"Retail Goods"
        }
    ],
    "sg:phone":"+1 310 330 1312",
    "sg:postcode":"90301",
    "sg:province":"CA",
    "wof:name":"Lety's Store",
    "wof:placetype":"venue"
},
  "geometry": {"coordinates":[-118.36215,33.952562],"type":"Point"}
}