{
  "type": "Feature",
  "properties": {
    "addr:full":"115 Sansome St Ste 807 San Francisco CA 94104",
    "addr:housenumber":"115",
    "addr:postcode":"94104",
    "addr:street":"Sansome St Ste 807",
    "iso:country":"US",
    "sg:address":"115 Sansome St Ste 807",
    "sg:city":"San Francisco",
    "sg:classifiers":[
        {
            "category":"Health Services",
            "subcategory":"Health Practitioner",
            "type":"Services"
        }
    ],
    "sg:phone":"+1 415 225 4880",
    "sg:postcode":"94104",
    "sg:province":"CA",
    "sg:tags":[
        "acupuncture"
    ],
    "sg:website":"www.middlepathacupuncture.com",
    "wof:name":"Adam Wiscomb, CMT, LAc",
    "wof:placetype":"venue"
},
  "geometry": {"coordinates":[-122.401038,37.791427],"type":"Point"}
}