{
  "type": "Feature",
  "properties": {
    "addr:full":"11324 Sunrise Ct Rancho Cucamonga CA 91701",
    "addr:housenumber":"11324",
    "addr:postcode":"91701",
    "addr:street":"Sunrise Ct",
    "iso:country":"US",
    "sg:address":"11324 Sunrise Ct",
    "sg:city":"Rancho Cucamonga",
    "sg:classifiers":[
        {
            "category":"Wholesale",
            "subcategory":"Machinery & Supplies",
            "type":"Manufacturing & Wholesale Goods"
        }
    ],
    "sg:phone":"+1 909 260 2516",
    "sg:postcode":"91701",
    "sg:province":"CA",
    "sg:tags":[
        "product",
        "industrial"
    ],
    "wof:name":"Clh Supply",
    "wof:placetype":"venue"
},
  "geometry": {"coordinates":[-117.55765100000001,34.133948],"type":"Point"}
}