{
  "type": "Feature",
  "properties": {
    "iso:country":"US",
    "sg:address":"6025 N 1st St",
    "sg:city":"Fresno",
    "sg:classifiers":[
        {
            "category":"Banks & Credit Unions",
            "subcategory":"Bank",
            "type":"Services"
        }
    ],
    "sg:phone":"+1 559 000 1111",
    "sg:postcode":"93710",
    "sg:province":"CA",
    "wof:name":"Citibank",
    "wof:placetype":"venue"
},
  "geometry": {"coordinates":[-119.772316,36.825343],"type":"Point"}
}