{
  "type": "Feature",
  "properties": {
    "addr:full":"16051 Brookhurst St Ste B Fountain Valley CA 92708",
    "addr:housenumber":"16051",
    "addr:postcode":"92708",
    "addr:street":"Brookhurst St Ste B",
    "iso:country":"US",
    "sg:address":"16051 Brookhurst St Ste B",
    "sg:city":"Fountain Valley",
    "sg:classifiers":[
        {
            "category":"Professional",
            "subcategory":"Accounting & Tax Preparation",
            "type":"Services"
        }
    ],
    "sg:phone":"+1 714 775 9077",
    "sg:postcode":"92708",
    "sg:province":"CA",
    "sg:tags":[
        "accountant"
    ],
    "sg:website":"www.ton-associates.com",
    "wof:name":"DT Ton & Associates",
    "wof:placetype":"venue"
},
  "geometry": {"coordinates":[-117.95505799999999,33.729669],"type":"Point"}
}