{
  "type": "Feature",
  "properties": {
    "iso:country":"US",
    "sg:address":"7136 Haskell Ave",
    "sg:city":"Van Nuys",
    "sg:classifiers":[
        {
            "category":"Manufacturing",
            "subcategory":"Printing",
            "type":"Manufacturing & Wholesale Goods"
        }
    ],
    "sg:phone":"+1 818 778 6777",
    "sg:postcode":"91406",
    "sg:province":"CA",
    "sg:tags":[
        "commercial"
    ],
    "wof:name":"Inkcentric",
    "wof:placetype":"venue"
},
  "geometry": {"coordinates":[-118.474851,34.200432],"type":"Point"}
}