{
  "type": "Feature",
  "properties": {
    "iso:country":"US",
    "sg:address":"3691 Apple Blossom Ln",
    "sg:city":"Turlock",
    "sg:classifiers":[
        {
            "category":"Real Estate",
            "subcategory":"Architect",
            "type":"Services"
        }
    ],
    "sg:phone":"+1 209 634 7344",
    "sg:postcode":"95382",
    "sg:province":"CA",
    "wof:name":"Arthur Yohannan",
    "wof:placetype":"venue"
},
  "geometry": {"coordinates":[-120.83896300000001,37.525998],"type":"Point"}
}