{
  "type": "Feature",
  "properties": {
    "iso:country":"US",
    "sg:address":"4133 Viking Way",
    "sg:city":"Long Beach",
    "sg:classifiers":[
        {
            "category":"Shopping",
            "subcategory":"Clothing, Apparel, & Fashions",
            "type":"Retail Goods"
        }
    ],
    "sg:phone":"+1 562 421 6300",
    "sg:postcode":"90808",
    "sg:province":"CA",
    "sg:tags":[
        "clothing",
        "women's"
    ],
    "sg:website":"www.laurieslittlesecret.com",
    "wof:name":"Laurie's Little Secret",
    "wof:placetype":"venue"
},
  "geometry": {"coordinates":[-118.12624599999999,33.833043],"type":"Point"}
}