{
  "type": "Feature",
  "properties": {
    "iso:country":"US",
    "sg:address":"1898 Alcatraz Ave",
    "sg:city":"Berkeley",
    "sg:classifiers":[
        {
            "category":"Shopping",
            "subcategory":"Jewelry",
            "type":"Retail Goods"
        },
        {
            "category":"Manufacturing",
            "subcategory":"Jewelry",
            "type":"Manufacturing & Wholesale Goods"
        }
    ],
    "sg:phone":"+1 510 757 5935",
    "sg:postcode":"94703",
    "sg:province":"CA",
    "sg:tags":[
        "designer",
        "jeweler"
    ],
    "wof:name":"Leah Mazor",
    "wof:placetype":"venue"
},
  "geometry": {"coordinates":[-122.27018099999999,37.848903],"type":"Point"}
}