{
  "type": "Feature",
  "properties": {
    "iso:country":"US",
    "sg:address":"242 E Airport Dr",
    "sg:city":"San Bernardino",
    "sg:classifiers":[
        {
            "category":"Real Estate",
            "subcategory":"Real Estate Agent",
            "type":"Services"
        }
    ],
    "sg:phone":"+1 909 890 2583",
    "sg:postcode":"92408",
    "sg:province":"CA",
    "wof:name":"Timber Wolf Real Estate",
    "wof:placetype":"venue"
},
  "geometry": {"coordinates":[-117.284085,34.067312],"type":"Point"}
}