{
  "type": "Feature",
  "properties": {
    "addr:full":"5641 Rosemead Blvd Pico Rivera CA 90660",
    "addr:housenumber":"5641",
    "addr:postcode":"90660",
    "addr:street":"Rosemead Blvd",
    "iso:country":"US",
    "sg:address":"5641 Rosemead Blvd",
    "sg:city":"Pico Rivera",
    "sg:classifiers":[
        {
            "category":"Wholesale",
            "subcategory":"Machinery & Supplies",
            "type":"Manufacturing & Wholesale Goods"
        }
    ],
    "sg:phone":"+1 562 948 3661",
    "sg:postcode":"90660",
    "sg:province":"CA",
    "sg:tags":[
        "salon",
        "beauty"
    ],
    "wof:name":"Silvia's Beauty Supply",
    "wof:placetype":"venue"
},
  "geometry": {"coordinates":[-118.08810699999999,33.993469],"type":"Point"}
}