{
  "type": "Feature",
  "properties": {
    "iso:country":"US",
    "sg:address":"3241 Weedpatch Hwy",
    "sg:city":"Bakersfield",
    "sg:classifiers":[
        {
            "category":"Building & Trades",
            "subcategory":"Construction",
            "type":"Services"
        }
    ],
    "sg:phone":"+1 661 201 2138",
    "sg:postcode":"93307",
    "sg:province":"CA",
    "sg:tags":[
        "site",
        "clean"
    ],
    "wof:name":"Gary Newton Backhoe Svc",
    "wof:placetype":"venue"
},
  "geometry": {"coordinates":[-118.914222,35.327678],"type":"Point"}
}