{
  "type": "Feature",
  "properties": {
    "addr:full":"13239 Willard St North Hollywood CA 91605",
    "addr:housenumber":"13239",
    "addr:postcode":"91605",
    "addr:street":"Willard St",
    "iso:country":"US",
    "sg:address":"13239 Willard St",
    "sg:city":"North Hollywood",
    "sg:classifiers":[
        {
            "category":"Building & Trades",
            "subcategory":"Cleaning & Sanitation",
            "type":"Services"
        }
    ],
    "sg:phone":"+1 818 781 1430",
    "sg:postcode":"91605",
    "sg:province":"CA",
    "sg:tags":[
        "house"
    ],
    "wof:name":"Ruiz Maintenance Svc",
    "wof:placetype":"venue"
},
  "geometry": {"coordinates":[-118.42261000000001,34.218012],"type":"Point"}
}