{
  "type": "Feature",
  "properties": {
    "iso:country":"US",
    "sg:address":"201 N La Brea Ave",
    "sg:city":"Inglewood",
    "sg:classifiers":[
        {
            "category":"Shopping",
            "subcategory":"Antiques",
            "type":"Retail Goods"
        }
    ],
    "sg:phone":"+1 310 412 7720",
    "sg:postcode":"90301",
    "sg:province":"CA",
    "wof:name":"Sebastian's Adam",
    "wof:placetype":"venue"
},
  "geometry": {"coordinates":[-118.353996,33.964699],"type":"Point"}
}