{
  "type": "Feature",
  "properties": {
    "addr:full":"1542 Glendale Boulevard Los Angeles CA 90026",
    "addr:housenumber":"1542",
    "addr:postcode":"90026",
    "addr:street":"Glendale Boulevard",
    "iso:country":"US",
    "sg:address":"1542 Glendale Boulevard",
    "sg:city":"Los Angeles",
    "sg:classifiers":[
        {
            "category":"Shopping",
            "subcategory":"Florist",
            "type":"Retail Goods"
        }
    ],
    "sg:phone":"+1 213 484 4171",
    "sg:postcode":"90026",
    "sg:province":"CA",
    "wof:name":"Exquisite Flower Shop",
    "wof:placetype":"venue"
},
  "geometry": {"coordinates":[-118.259777,34.082753],"type":"Point"}
}