{
  "type": "Feature",
  "properties": {
    "iso:country":"US",
    "sg:address":"2535 E 54th St",
    "sg:city":"Huntington Park",
    "sg:classifiers":[
        {
            "category":"Manufacturing",
            "subcategory":"Jewelry",
            "type":"Manufacturing & Wholesale Goods"
        }
    ],
    "sg:phone":"+1 323 583 1422",
    "sg:postcode":"90255",
    "sg:province":"CA",
    "sg:tags":[
        "manufacture",
        "stainless",
        "ware",
        "plated"
    ],
    "wof:name":"West Coast Stainless",
    "wof:placetype":"venue"
},
  "geometry": {"coordinates":[-118.226654,33.993928],"type":"Point"}
}