{
  "type": "Feature",
  "properties": {
    "addr:full":"16136 Sherman Way Van Nuys CA 91406",
    "addr:housenumber":"16136",
    "addr:postcode":"91406",
    "addr:street":"Sherman Way",
    "iso:country":"US",
    "sg:address":"16136 Sherman Way",
    "sg:city":"Van Nuys",
    "sg:classifiers":[
        {
            "category":"Professional",
            "subcategory":"Detective & Security Services",
            "type":"Services"
        }
    ],
    "sg:phone":"+1 818 782 6184",
    "sg:postcode":"91406",
    "sg:province":"CA",
    "sg:tags":[
        "guard",
        "patrol"
    ],
    "sg:website":"www.securitasinc.com",
    "wof:name":"Securitas Security Svc USA Inc",
    "wof:placetype":"venue"
},
  "geometry": {"coordinates":[-118.48518,34.200975],"type":"Point"}
}