{
  "type": "Feature",
  "properties": {
    "addr:full":"1323 San Anselmo Ave San Anselmo CA 94960",
    "addr:housenumber":"1323",
    "addr:postcode":"94960",
    "addr:street":"San Anselmo Ave",
    "iso:country":"US",
    "sg:address":"1323 San Anselmo Ave",
    "sg:city":"San Anselmo",
    "sg:classifiers":[
        {
            "category":"Manufacturing",
            "subcategory":"Printing",
            "type":"Manufacturing & Wholesale Goods"
        }
    ],
    "sg:phone":"+1 415 453 8886",
    "sg:postcode":"94960",
    "sg:province":"CA",
    "sg:tags":[
        "publisher"
    ],
    "sg:website":"www.mybook.org",
    "wof:name":"Mybook Org Self-Publishing Svc",
    "wof:placetype":"venue"
},
  "geometry": {"coordinates":[-122.57588699999999,37.980724],"type":"Point"}
}