{
  "type": "Feature",
  "properties": {
    "iso:country":"US",
    "sg:address":"18256 Calvert St",
    "sg:city":"Tarzana",
    "sg:classifiers":[
        {
            "category":"Building & Trades",
            "subcategory":"Electrical",
            "type":"Services"
        }
    ],
    "sg:phone":"+1 818 343 8402",
    "sg:postcode":"91335",
    "sg:province":"CA",
    "sg:tags":[
        "contractors-commercial",
        "industrial",
        "electrician",
        "electric",
        "contractor"
    ],
    "sg:website":"http://www.eagleelectriclic.com",
    "wof:name":"Eagle Electric Inc.",
    "wof:placetype":"venue"
},
  "geometry": {"coordinates":[-118.53126,34.181831],"type":"Point"}
}