{
  "type": "Feature",
  "properties": {
    "iso:country":"US",
    "sg:address":"44100 Monterey Ave",
    "sg:city":"Palm Desert",
    "sg:classifiers":[
        {
            "category":"Social Services",
            "subcategory":"Job Training",
            "type":"Services"
        }
    ],
    "sg:phone":"+1 760 836 0406",
    "sg:postcode":"92260",
    "sg:province":"CA",
    "sg:tags":[
        "rehabilitation"
    ],
    "wof:name":"Innovative Rehab",
    "wof:placetype":"venue"
},
  "geometry": {"coordinates":[-116.39120200000001,33.72789],"type":"Point"}
}