{
  "type": "Feature",
  "properties": {
    "addr:full":"24231 El Toro Rd Laguna Woods CA 92637",
    "addr:housenumber":"24231",
    "addr:postcode":"92637",
    "addr:street":"El Toro Rd",
    "iso:country":"US",
    "sg:address":"24231 El Toro Rd",
    "sg:city":"Laguna Woods",
    "sg:classifiers":[
        {
            "category":"Education",
            "subcategory":"Preschool",
            "type":"Public Place"
        },
        {
            "category":"Education",
            "subcategory":"School",
            "type":"Public Place"
        }
    ],
    "sg:phone":"+1 949 581 8115",
    "sg:postcode":"92637",
    "sg:province":"CA",
    "sg:tags":[
        "high",
        "middle",
        "elementary"
    ],
    "wof:name":"Aliso Viejo Christian School",
    "wof:placetype":"venue"
},
  "geometry": {"coordinates":[-117.710999,33.608398],"type":"Point"}
}