{
  "type": "Feature",
  "properties": {
    "addr:full":"1827 Pontius Ave Los Angeles CA 90025",
    "addr:housenumber":"1827",
    "addr:postcode":"90025",
    "addr:street":"Pontius Ave",
    "iso:country":"US",
    "sg:address":"1827 Pontius Ave",
    "sg:city":"Los Angeles",
    "sg:classifiers":[
        {
            "category":"Retail",
            "subcategory":"Veterinary Services",
            "type":"Services"
        }
    ],
    "sg:phone":"+1 310 943 9650",
    "sg:postcode":"90025",
    "sg:province":"CA",
    "sg:tags":[
        "veterinarian"
    ],
    "sg:website":"www.animalimagingla.com",
    "wof:name":"Animal Imaging Center",
    "wof:placetype":"venue"
},
  "geometry": {"coordinates":[-118.44311,34.044879],"type":"Point"}
}