{
  "type": "Feature",
  "properties": {
    "iso:country":"US",
    "sg:address":"8482 E. Garvey",
    "sg:city":"Rosemead",
    "sg:classifiers":[
        {
            "category":"Shopping",
            "subcategory":"Florist",
            "type":"Retail Goods"
        }
    ],
    "sg:phone":"+1 626 572 4330",
    "sg:postcode":"91770",
    "sg:province":"CA",
    "wof:name":"Chelas's Flowers & Plants",
    "wof:placetype":"venue"
},
  "geometry": {"coordinates":[-118.083557,34.062329],"type":"Point"}
}