{
  "type": "Feature",
  "properties": {
    "iso:country":"US",
    "sg:address":"620 N Larchmont Blvd",
    "sg:city":"Los Angeles",
    "sg:classifiers":[
        {
            "category":"Shopping",
            "type":"Retail Goods"
        }
    ],
    "sg:phone":"+1 323 462 3516",
    "sg:postcode":"90004",
    "sg:province":"CA",
    "sg:tags":[
        "stone",
        "merchandise"
    ],
    "wof:name":"Hartt Trophy & Engraving Co",
    "wof:placetype":"venue"
},
  "geometry": {"coordinates":[-118.323589,34.083125],"type":"Point"}
}