{
  "type": "Feature",
  "properties": {
    "iso:country":"US",
    "sg:address":"2799 E Bidwell St",
    "sg:city":"Folsom",
    "sg:classifiers":[
        {
            "category":"Shopping",
            "subcategory":"Clothing, Apparel, & Fashions",
            "type":"Retail Goods"
        },
        {
            "category":"Shopping",
            "subcategory":"Hobbies, Toys, & Games",
            "type":"Retail Goods"
        },
        {
            "category":"Sports & Exercise",
            "subcategory":"Bicycle Rental",
            "type":"Entertainment"
        },
        {
            "category":"Parking",
            "subcategory":"Bicycle",
            "type":"Transportation"
        },
        {
            "category":"Shopping",
            "subcategory":"Bicycles & Sporting Goods",
            "type":"Retail Goods"
        },
        {
            "category":"Sports & Exercise",
            "subcategory":"Gym",
            "type":"Entertainment"
        },
        {
            "category":"Recreation",
            "subcategory":"Fishing",
            "type":"Entertainment"
        },
        {
            "category":"Recreation",
            "subcategory":"Water Park",
            "type":"Entertainment"
        },
        {
            "category":"Recreation",
            "type":"Entertainment"
        },
        {
            "category":"Sports & Exercise",
            "subcategory":"Tennis Court",
            "type":"Entertainment"
        },
        {
            "category":"Sports & Exercise",
            "subcategory":"Golf",
            "type":"Entertainment"
        },
        {
            "category":"Marine",
            "type":"Transportation"
        }
    ],
    "sg:phone":"+1 916 983 5821",
    "sg:postcode":"95630",
    "sg:province":"CA",
    "sg:tags":[
        "shop",
        "archery",
        "camping",
        "supply",
        "racquetball",
        "system",
        "equipment-repairing",
        "fitness",
        "equipment",
        "snowboard",
        "billiard",
        "bicycles-renting",
        "skiing",
        "tackle",
        "security",
        "ski",
        "rack",
        "sportswear"
    ],
    "sg:website":"http://www.sportsauthority.com",
    "wof:name":"The Sports Authority",
    "wof:placetype":"venue"
},
  "geometry": {"coordinates":[-121.12217699999999,38.65369],"type":"Point"}
}