{
  "type": "Feature",
  "properties": {
    "iso:country":"US",
    "sg:address":"1222 Trancas St",
    "sg:city":"Napa",
    "sg:classifiers":[
        {
            "category":"Fast Food",
            "type":"Food & Drink"
        },
        {
            "category":"Restaurant",
            "type":"Food & Drink"
        }
    ],
    "sg:phone":"+1 707 254 9271",
    "sg:postcode":"94558",
    "sg:province":"CA",
    "sg:tags":[
        "thai",
        "take",
        "pan",
        "asian"
    ],
    "wof:name":"Thai Kitchen Restaurant",
    "wof:placetype":"venue"
},
  "geometry": {"coordinates":[-122.29884300000001,38.322998],"type":"Point"}
}