{
  "type": "Feature",
  "properties": {
    "iso:country":"US",
    "sg:address":"571 W Channel Islands Blvd",
    "sg:city":"Port Hueneme",
    "sg:classifiers":[
        {
            "category":"Shopping",
            "subcategory":"Florist",
            "type":"Retail Goods"
        }
    ],
    "sg:phone":"+1 805 483 0494",
    "sg:postcode":"93041",
    "sg:province":"CA",
    "wof:name":"Daisy Whoopsie Florist",
    "wof:placetype":"venue"
},
  "geometry": {"coordinates":[-119.213932,34.175847],"type":"Point"}
}