{
  "type": "Feature",
  "properties": {
    "iso:country":"US",
    "sg:address":"18601 Stare St",
    "sg:city":"Northridge",
    "sg:classifiers":[
        {
            "category":"Professional",
            "type":"Services"
        }
    ],
    "sg:phone":"+1 818 773 1725",
    "sg:postcode":"91324",
    "sg:province":"CA",
    "wof:name":"Susan Rhee",
    "wof:placetype":"venue"
},
  "geometry": {"coordinates":[-118.539528,34.252592],"type":"Point"}
}