{
  "type": "Feature",
  "properties": {
    "addr:full":"857 S Idyllwild Ave Rialto CA 92376",
    "addr:housenumber":"857",
    "addr:postcode":"92376",
    "addr:street":"S Idyllwild Ave",
    "iso:country":"US",
    "sg:address":"857 S Idyllwild Ave",
    "sg:city":"Rialto",
    "sg:classifiers":[
        {
            "category":"Travel",
            "subcategory":"Travel Agent",
            "type":"Entertainment"
        }
    ],
    "sg:phone":"+1 909 419 0282",
    "sg:postcode":"92376",
    "sg:province":"CA",
    "sg:tags":[
        "agency"
    ],
    "wof:name":"Jump With US",
    "wof:placetype":"venue"
},
  "geometry": {"coordinates":[-117.38595599999999,34.085889],"type":"Point"}
}