{
  "type": "Feature",
  "properties": {
    "addr:full":"1247 Highland Ave National City CA 91950",
    "addr:housenumber":"1247",
    "addr:postcode":"91950",
    "addr:street":"Highland Ave",
    "iso:country":"US",
    "sg:address":"1247 Highland Ave",
    "sg:city":"National City",
    "sg:classifiers":[
        {
            "category":"Wholesale",
            "subcategory":"Fruits & Vegetables",
            "type":"Manufacturing & Wholesale Goods"
        }
    ],
    "sg:phone":"+1 619 336 9934",
    "sg:postcode":"91950",
    "sg:province":"CA",
    "wof:name":"Loya Produce",
    "wof:placetype":"venue"
},
  "geometry": {"coordinates":[-117.09703,32.674035],"type":"Point"}
}