{
  "type": "Feature",
  "properties": {
    "iso:country":"US",
    "sg:address":"6200 Palm Ave.",
    "sg:city":"Huntington Beach",
    "sg:classifiers":[
        {
            "category":"Park",
            "type":"Public Place"
        }
    ],
    "sg:postcode":"92648",
    "sg:province":"CA",
    "wof:name":"Pattinson Park",
    "wof:placetype":"venue"
},
  "geometry": {"coordinates":[-118.02246100000001,33.675679],"type":"Point"}
}