{
  "type": "Feature",
  "properties": {
    "iso:country":"US",
    "sg:address":"830 E Evelyn Ave",
    "sg:city":"Sunnyvale",
    "sg:classifiers":[
        {
            "category":"Shopping",
            "subcategory":"Bicycles & Sporting Goods",
            "type":"Retail Goods"
        },
        {
            "category":"Sports & Exercise",
            "subcategory":"Golf",
            "type":"Entertainment"
        }
    ],
    "sg:phone":"+1 408 530 8588",
    "sg:postcode":"94086",
    "sg:province":"CA",
    "sg:tags":[
        "equipment",
        "instruction",
        "course",
        "supply"
    ],
    "sg:website":"http://www.golfachiever.com",
    "wof:name":"Golf Achiever Learning Center",
    "wof:placetype":"venue"
},
  "geometry": {"coordinates":[-122.015137,37.370781],"type":"Point"}
}