{
  "type": "Feature",
  "properties": {
    "iso:country":"US",
    "sg:address":"4061 E Castro Valley Blvd Ste 454",
    "sg:city":"Castro Valley",
    "sg:classifiers":[
        {
            "category":"Building & Trades",
            "subcategory":"Construction",
            "type":"Services"
        }
    ],
    "sg:phone":"+1 510 972 4776",
    "sg:postcode":"94552",
    "sg:province":"CA",
    "sg:tags":[
        "contractor"
    ],
    "sg:website":"www.ProsRemodel.com",
    "wof:name":"Property Pros Construction Inc",
    "wof:placetype":"venue"
},
  "geometry": {"coordinates":[-122.050072,37.696164],"type":"Point"}
}