{
  "type": "Feature",
  "properties": {
    "iso:country":"US",
    "sg:address":"2621 Lincoln Blvd",
    "sg:city":"Santa Monica",
    "sg:classifiers":[
        {
            "category":"Wholesale",
            "subcategory":"Machinery & Supplies",
            "type":"Manufacturing & Wholesale Goods"
        }
    ],
    "sg:phone":"+1 310 314 0444",
    "sg:postcode":"90405",
    "sg:province":"CA",
    "sg:tags":[
        "salon",
        "beauty"
    ],
    "wof:name":"Sunny Wigs & Beauty Supply",
    "wof:placetype":"venue"
},
  "geometry": {"coordinates":[-118.475791,34.006663],"type":"Point"}
}