{
  "type": "Feature",
  "properties": {
    "addr:full":"100 Century Center Court # 670 San jose CA 95112",
    "addr:housenumber":"100",
    "addr:postcode":"95112",
    "addr:street":"Century Center Court # 670",
    "iso:country":"US",
    "sg:address":"100 Century Center Court # 670",
    "sg:city":"San jose",
    "sg:classifiers":[
        {
            "category":"Travel",
            "subcategory":"Travel Agent",
            "type":"Entertainment"
        }
    ],
    "sg:phone":"+1 408 727 7515",
    "sg:postcode":"95112",
    "sg:province":"CA",
    "sg:website":"www.peninsulavisa.com",
    "wof:name":"Peninsula Visa Service",
    "wof:placetype":"venue"
},
  "geometry": {"coordinates":[-121.915949,37.367293],"type":"Point"}
}