{
  "type": "Feature",
  "properties": {
    "iso:country":"US",
    "sg:address":"3300 el Camino Ave",
    "sg:city":"Sacramento",
    "sg:classifiers":[
        {
            "category":"Social Services",
            "subcategory":"Adult Care",
            "type":"Services"
        }
    ],
    "sg:phone":"+1 916 979 4975",
    "sg:postcode":"95821",
    "sg:province":"CA",
    "sg:tags":[
        "organization",
        "senior",
        "citizen"
    ],
    "wof:name":"Personalized Homecare Agency",
    "wof:placetype":"venue"
},
  "geometry": {"coordinates":[-121.385486,38.610478],"type":"Point"}
}