{
  "type": "Feature",
  "properties": {
    "addr:full":"11000 Olson Dr Gold River CA 95670",
    "addr:housenumber":"11000",
    "addr:postcode":"95670",
    "addr:street":"Olson Dr",
    "iso:country":"US",
    "sg:address":"11000 Olson Dr",
    "sg:city":"Gold River",
    "sg:classifiers":[
        {
            "category":"Health Services",
            "subcategory":"Doctor",
            "type":"Services"
        }
    ],
    "sg:phone":"+1 916 635 7134",
    "sg:postcode":"95670",
    "sg:province":"CA",
    "sg:tags":[
        "physician",
        "surgeon"
    ],
    "wof:name":"I-Mei Hsiu-Menchaca MD",
    "wof:placetype":"venue"
},
  "geometry": {"coordinates":[-121.284094,38.59376],"type":"Point"}
}