{
  "type": "Feature",
  "properties": {
    "iso:country":"US",
    "sg:address":"713 9th St Ste A",
    "sg:city":"Sacramento",
    "sg:classifiers":[
        {
            "category":"Professional",
            "subcategory":"Lawyer & Legal Services",
            "type":"Services"
        }
    ],
    "sg:phone":"+1 916 446 1426",
    "sg:postcode":"95814",
    "sg:province":"CA",
    "wof:name":"Cayocca Kenneth B Atty",
    "wof:placetype":"venue"
},
  "geometry": {"coordinates":[-121.49299600000001,38.583801],"type":"Point"}
}