{
  "type": "Feature",
  "properties": {
    "addr:full":"7611 S Alameda St Los Angeles CA 90001",
    "addr:housenumber":"7611",
    "addr:postcode":"90001",
    "addr:street":"S Alameda St",
    "iso:country":"US",
    "sg:address":"7611 S Alameda St",
    "sg:city":"Los Angeles",
    "sg:classifiers":[
        {
            "category":"Professional",
            "type":"Services"
        }
    ],
    "sg:phone":"+1 323 582 4101",
    "sg:postcode":"90001",
    "sg:province":"CA",
    "sg:tags":[
        "establishment"
    ],
    "wof:name":"Ruiz Solder Shop",
    "wof:placetype":"venue"
},
  "geometry": {"coordinates":[-118.234016,33.97081],"type":"Point"}
}