{
  "type": "Feature",
  "properties": {
    "addr:full":"14549 Archwood St Van Nuys CA 91405",
    "addr:housenumber":"14549",
    "addr:postcode":"91405",
    "addr:street":"Archwood St",
    "iso:country":"US",
    "sg:address":"14549 Archwood St",
    "sg:city":"Van Nuys",
    "sg:classifiers":[
        {
            "category":"Professional",
            "subcategory":"Lawyer & Legal Services",
            "type":"Services"
        }
    ],
    "sg:phone":"+1 818 780 4800",
    "sg:postcode":"91405",
    "sg:province":"CA",
    "sg:tags":[
        "attorney"
    ],
    "wof:name":"Bufete Quintana Foreign Legal",
    "wof:placetype":"venue"
},
  "geometry": {"coordinates":[-118.45038599999999,34.193011],"type":"Point"}
}