{
  "type": "Feature",
  "properties": {
    "addr:full":"2590 S River Rd West Sacramento CA 95691",
    "addr:housenumber":"2590",
    "addr:postcode":"95691",
    "addr:street":"S River Rd",
    "iso:country":"US",
    "sg:address":"2590 S River Rd",
    "sg:city":"West Sacramento",
    "sg:classifiers":[
        {
            "category":"Building & Trades",
            "subcategory":"Construction",
            "type":"Services"
        }
    ],
    "sg:phone":"+1 916 371 1938",
    "sg:postcode":"95691",
    "sg:province":"CA",
    "sg:tags":[
        "plastering",
        "contractor"
    ],
    "wof:name":"J F Mc Cray Plastering Inc",
    "wof:placetype":"venue"
},
  "geometry": {"coordinates":[-121.514396,38.549483],"type":"Point"}
}