{
  "type": "Feature",
  "properties": {
    "iso:country":"US",
    "sg:address":"27 Ross Aly",
    "sg:city":"San Francisco",
    "sg:classifiers":[
        {
            "category":"Shopping",
            "subcategory":"Clothing, Apparel, & Fashions",
            "type":"Retail Goods"
        }
    ],
    "sg:phone":"+1 415 772 9190",
    "sg:postcode":"94108",
    "sg:province":"CA",
    "sg:tags":[
        "designer"
    ],
    "wof:name":"Li Ying Sewing Factory",
    "wof:placetype":"venue"
},
  "geometry": {"coordinates":[-122.407432,37.795927],"type":"Point"}
}