{
  "type": "Feature",
  "properties": {
    "addr:full":"1993 E Florence Ave Los Angeles CA 90001",
    "addr:housenumber":"1993",
    "addr:postcode":"90001",
    "addr:street":"E Florence Ave",
    "iso:country":"US",
    "sg:address":"1993 E Florence Ave",
    "sg:city":"Los Angeles",
    "sg:classifiers":[
        {
            "category":"Banks & Credit Unions",
            "subcategory":"Bank",
            "type":"Services"
        }
    ],
    "sg:phone":"+1 323 581 3026",
    "sg:postcode":"90001",
    "sg:province":"CA",
    "sg:tags":[
        "cashing",
        "check"
    ],
    "wof:name":"AMERICAS Cash Express",
    "wof:placetype":"venue"
},
  "geometry": {"coordinates":[-118.23693799999999,33.974812],"type":"Point"}
}