{
  "type": "Feature",
  "properties": {
    "addr:full":"1421 Lexington Dr San Jose CA 95117",
    "addr:housenumber":"1421",
    "addr:postcode":"95117",
    "addr:street":"Lexington Dr",
    "iso:country":"US",
    "sg:address":"1421 Lexington Dr",
    "sg:city":"San Jose",
    "sg:classifiers":[
        {
            "category":"Building & Trades",
            "subcategory":"Plumbing",
            "type":"Services"
        }
    ],
    "sg:phone":"+1 408 871 8008",
    "sg:postcode":"95117",
    "sg:province":"CA",
    "sg:website":"www.waterheatersrus.net",
    "wof:name":"Water Heaters R Us",
    "wof:placetype":"venue"
},
  "geometry": {"coordinates":[-121.955733,37.298403],"type":"Point"}
}