{
  "type": "Feature",
  "properties": {
    "iso:country":"US",
    "sg:address":"288 Browning Rd",
    "sg:city":"Mc Farland",
    "sg:classifiers":[
        {
            "category":"Food & Beverages",
            "subcategory":"Groceries & Convenience Stores",
            "type":"Retail Goods"
        }
    ],
    "sg:phone":"+1 661 792 3872",
    "sg:postcode":"93250",
    "sg:province":"CA",
    "sg:tags":[
        "grocer"
    ],
    "wof:name":"Community Market",
    "wof:placetype":"venue"
},
  "geometry": {"coordinates":[-119.223088,35.676433],"type":"Point"}
}