{
  "type": "Feature",
  "properties": {
    "addr:full":"3851 Alton Pkwy Irvine CA 92606",
    "addr:housenumber":"3851",
    "addr:postcode":"92606",
    "addr:street":"Alton Pkwy",
    "iso:country":"US",
    "sg:address":"3851 Alton Pkwy",
    "sg:city":"Irvine",
    "sg:classifiers":[
        {
            "category":"Restaurant",
            "type":"Food & Drink"
        }
    ],
    "sg:menulink":"http://www.allmenus.com/ca/el-toro/62362-round-table/menu/",
    "sg:phone":"+1 949 476 3030",
    "sg:postcode":"92606",
    "sg:province":"CA",
    "sg:tags":[
        "american",
        "pizza"
    ],
    "wof:name":"Round Table",
    "wof:placetype":"venue"
},
  "geometry": {"coordinates":[-117.813165,33.681973],"type":"Point"}
}