{
  "type": "Feature",
  "properties": {
    "iso:country":"US",
    "sg:address":"1954 la Ramada Dr",
    "sg:city":"Camarillo",
    "sg:classifiers":[
        {
            "category":"Professional",
            "subcategory":"Accounting & Tax Preparation",
            "type":"Services"
        },
        {
            "category":"Professional",
            "subcategory":"Business Services",
            "type":"Services"
        }
    ],
    "sg:phone":"+1 805 484 4114",
    "sg:postcode":"93012",
    "sg:province":"CA",
    "sg:tags":[
        "consultant",
        "coach",
        "billing",
        "bookkeeping"
    ],
    "wof:name":"Sansei-Business Services",
    "wof:placetype":"venue"
},
  "geometry": {"coordinates":[-118.981953,34.237423],"type":"Point"}
}