{
  "type": "Feature",
  "properties": {
    "addr:full":"617 N Ventura Ave Ventura CA 93001",
    "addr:housenumber":"617",
    "addr:postcode":"93001",
    "addr:street":"N Ventura Ave",
    "iso:country":"US",
    "sg:address":"617 N Ventura Ave",
    "sg:city":"Ventura",
    "sg:classifiers":[
        {
            "category":"Autos & Motor Vehicles",
            "subcategory":"Auto Supplies",
            "type":"Retail Goods"
        }
    ],
    "sg:phone":"+1 805 648 4334",
    "sg:postcode":"93001",
    "sg:province":"CA",
    "sg:tags":[
        "tire"
    ],
    "wof:name":"Avenue Tire & Svc",
    "wof:placetype":"venue"
},
  "geometry": {"coordinates":[-119.298424,34.289424],"type":"Point"}
}