{
  "type": "Feature",
  "properties": {
    "iso:country":"US",
    "sg:address":"1597 Normanton Pl",
    "sg:city":"El Dorado Hills",
    "sg:classifiers":[
        {
            "category":"Insurance",
            "subcategory":"Hazard Insurance",
            "type":"Services"
        }
    ],
    "sg:phone":"+1 916 933 3578",
    "sg:postcode":"95762",
    "sg:province":"CA",
    "sg:tags":[
        "carrier"
    ],
    "wof:name":"Kemper Insurance Companies",
    "wof:placetype":"venue"
},
  "geometry": {"coordinates":[-121.072678,38.684891],"type":"Point"}
}