{
  "type": "Feature",
  "properties": {
    "addr:full":"671 N Waterbury Ave Covina CA 91722",
    "addr:housenumber":"671",
    "addr:postcode":"91722",
    "addr:street":"N Waterbury Ave",
    "iso:country":"US",
    "sg:address":"671 N Waterbury Ave",
    "sg:city":"Covina",
    "sg:classifiers":[
        {
            "category":"Freight",
            "type":"Transportation"
        }
    ],
    "sg:phone":"+1 626 966 6603",
    "sg:postcode":"91722",
    "sg:province":"CA",
    "sg:tags":[
        "operator",
        "local",
        "trucking"
    ],
    "wof:name":"Hagens Trucking",
    "wof:placetype":"venue"
},
  "geometry": {"coordinates":[-117.91372699999999,34.091461],"type":"Point"}
}