{
  "type": "Feature",
  "properties": {
    "iso:country":"US",
    "sg:address":"7400 Reseda Blvd",
    "sg:city":"Reseda",
    "sg:classifiers":[
        {
            "category":"Shopping",
            "subcategory":"Pharmacy",
            "type":"Retail Goods"
        }
    ],
    "sg:phone":"+1 818 776 2600",
    "sg:postcode":"91335",
    "sg:province":"CA",
    "wof:name":"CVS Pharmacy",
    "wof:placetype":"venue"
},
  "geometry": {"coordinates":[-118.536056,34.206571],"type":"Point"}
}