{
  "type": "Feature",
  "properties": {
    "iso:country":"US",
    "sg:address":"240 W Mission Rd",
    "sg:city":"San Marcos",
    "sg:classifiers":[
        {
            "category":"Food & Beverages",
            "subcategory":"Liquor & Beverages",
            "type":"Retail Goods"
        }
    ],
    "sg:phone":"+1 760 744 7160",
    "sg:postcode":"92069",
    "sg:province":"CA",
    "wof:name":"4 Way Liquor",
    "wof:placetype":"venue"
},
  "geometry": {"coordinates":[-117.166894,33.143761],"type":"Point"}
}