{
  "type": "Feature",
  "properties": {
    "iso:country":"US",
    "sg:address":"200 Bernard St",
    "sg:city":"Bakersfield",
    "sg:classifiers":[
        {
            "category":"Personal",
            "subcategory":"Beauty Salon",
            "type":"Services"
        }
    ],
    "sg:phone":"+1 661 861 0866",
    "sg:postcode":"93305",
    "sg:province":"CA",
    "wof:name":"Nails By Pamela",
    "wof:placetype":"venue"
},
  "geometry": {"coordinates":[-118.997207,35.390254],"type":"Point"}
}