{
  "type": "Feature",
  "properties": {
    "addr:full":"4005 Eagle Rock Blvd Los Angeles CA 90065",
    "addr:housenumber":"4005",
    "addr:postcode":"90065",
    "addr:street":"Eagle Rock Blvd",
    "iso:country":"US",
    "sg:address":"4005 Eagle Rock Blvd",
    "sg:city":"Los Angeles",
    "sg:classifiers":[
        {
            "category":"Autos & Motor Vehicles",
            "subcategory":"Fuel & Gas Station",
            "type":"Retail Goods"
        }
    ],
    "sg:phone":"+1 323 254 4250",
    "sg:postcode":"90065",
    "sg:province":"CA",
    "wof:name":"Jim's Chevron",
    "wof:placetype":"venue"
},
  "geometry": {"coordinates":[-118.228996,34.120399],"type":"Point"}
}