{
  "type": "Feature",
  "properties": {
    "iso:country":"US",
    "sg:address":"15215 S Atlantic Ave Ste W21",
    "sg:city":"Compton",
    "sg:classifiers":[
        {
            "category":"Shopping",
            "subcategory":"Music",
            "type":"Retail Goods"
        }
    ],
    "sg:phone":"+1 310 884 9007",
    "sg:postcode":"90221",
    "sg:province":"CA",
    "sg:tags":[
        "used",
        "tapes",
        "vintage",
        "records",
        "cd's",
        "store"
    ],
    "wof:name":"Global Touch Communications",
    "wof:placetype":"venue"
},
  "geometry": {"coordinates":[-118.193421,33.895025],"type":"Point"}
}