{
  "type": "Feature",
  "properties": {
    "iso:country":"US",
    "sg:address":"310 Mcarthur Way",
    "sg:city":"Upland",
    "sg:classifiers":[
        {
            "category":"Building & Trades",
            "subcategory":"Pest Control",
            "type":"Services"
        }
    ],
    "sg:phone":"+1 909 946 4443",
    "sg:postcode":"91786",
    "sg:province":"CA",
    "sg:tags":[
        "mothproofing"
    ],
    "sg:website":"http://www.orkin.com",
    "wof:name":"Orkin Pest Control",
    "wof:placetype":"venue"
},
  "geometry": {"coordinates":[-117.679337,34.096636],"type":"Point"}
}