{
  "type": "Feature",
  "properties": {
    "addr:full":"748 Oakland Ave Oakland CA 94611",
    "addr:housenumber":"748",
    "addr:postcode":"94611",
    "addr:street":"Oakland Ave",
    "iso:country":"US",
    "sg:address":"748 Oakland Ave",
    "sg:city":"Oakland",
    "sg:classifiers":[
        {
            "category":"Professional",
            "subcategory":"Art Services",
            "type":"Services"
        }
    ],
    "sg:phone":"+1 510 547 7705",
    "sg:postcode":"94611",
    "sg:province":"CA",
    "sg:tags":[
        "graphic",
        "designer"
    ],
    "wof:name":"Elaine Chu Graphic Design",
    "wof:placetype":"venue"
},
  "geometry": {"coordinates":[-122.249915,37.820886],"type":"Point"}
}