{
  "type": "Feature",
  "properties": {
    "addr:full":"13232 Kagel Canyon St Pacoima CA 91331",
    "addr:housenumber":"13232",
    "addr:postcode":"91331",
    "addr:street":"Kagel Canyon St",
    "iso:country":"US",
    "sg:address":"13232 Kagel Canyon St",
    "sg:city":"Pacoima",
    "sg:classifiers":[
        {
            "category":"Social Services",
            "subcategory":"Child Care",
            "type":"Services"
        }
    ],
    "sg:phone":"+1 818 897 5427",
    "sg:postcode":"91331",
    "sg:province":"CA",
    "sg:tags":[
        "nursery",
        "day"
    ],
    "sg:website":"http://www.ebenezerchildrenshome.org",
    "wof:name":"Kids First Learning Center",
    "wof:placetype":"venue"
},
  "geometry": {"coordinates":[-118.421102,34.250992],"type":"Point"}
}