{
  "type": "Feature",
  "properties": {
    "addr:full":"244 Smoketree Ave Agoura Hills CA 91377",
    "addr:housenumber":"244",
    "addr:postcode":"91377",
    "addr:street":"Smoketree Ave",
    "iso:country":"US",
    "sg:address":"244 Smoketree Ave",
    "sg:city":"Agoura Hills",
    "sg:classifiers":[
        {
            "category":"Building & Trades",
            "subcategory":"Construction",
            "type":"Services"
        }
    ],
    "sg:phone":"+1 818 735 7859",
    "sg:postcode":"91377",
    "sg:province":"CA",
    "sg:tags":[
        "heavy"
    ],
    "wof:name":"K and K Ponds and Puddles",
    "wof:placetype":"venue"
},
  "geometry": {"coordinates":[-118.761685,34.172981],"type":"Point"}
}