{
  "type": "Feature",
  "properties": {
    "addr:full":"946 Wible Rd Bakersfield CA 93304",
    "addr:housenumber":"946",
    "addr:postcode":"93304",
    "addr:street":"Wible Rd",
    "iso:country":"US",
    "sg:address":"946 Wible Rd",
    "sg:city":"Bakersfield",
    "sg:classifiers":[
        {
            "category":"Education",
            "subcategory":"Vocational School",
            "type":"Public Place"
        }
    ],
    "sg:phone":"+1 661 398 3133",
    "sg:postcode":"93304",
    "sg:province":"CA",
    "sg:tags":[
        "training",
        "computer"
    ],
    "wof:name":"Kids Of Tomorrow",
    "wof:placetype":"venue"
},
  "geometry": {"coordinates":[-119.038883,35.345799],"type":"Point"}
}