{
  "type": "Feature",
  "properties": {
    "addr:full":"3686 Riverside Dr Ste J Chino CA 91710",
    "addr:housenumber":"3686",
    "addr:postcode":"91710",
    "addr:street":"Riverside Dr Ste J",
    "iso:country":"US",
    "sg:address":"3686 Riverside Dr Ste J",
    "sg:city":"Chino",
    "sg:classifiers":[
        {
            "category":"Food & Beverages",
            "subcategory":"Groceries & Convenience Stores",
            "type":"Retail Goods"
        }
    ],
    "sg:phone":"+1 909 628 9656",
    "sg:postcode":"91710",
    "sg:province":"CA",
    "wof:name":"V S Mini Mart",
    "wof:placetype":"venue"
},
  "geometry": {"coordinates":[-117.724447,34.018858],"type":"Point"}
}