{
  "type": "Feature",
  "properties": {
    "iso:country":"US",
    "sg:address":"711 W Kimberly Ave",
    "sg:city":"Placentia",
    "sg:classifiers":[
        {
            "category":"Education",
            "subcategory":"College",
            "type":"Public Place"
        }
    ],
    "sg:phone":"+1 714 646 0390",
    "sg:postcode":"92870",
    "sg:province":"CA",
    "sg:tags":[
        "academic",
        "school"
    ],
    "wof:name":"Cybertek College",
    "wof:placetype":"venue"
},
  "geometry": {"coordinates":[-117.880567,33.863068],"type":"Point"}
}