{
  "type": "Feature",
  "properties": {
    "iso:country":"US",
    "sg:address":"31129 Via Colinas",
    "sg:city":"Westlake Village",
    "sg:classifiers":[
        {
            "category":"Freight",
            "type":"Transportation"
        }
    ],
    "sg:phone":"+1 818 991 9463",
    "sg:postcode":"91362",
    "sg:province":"CA",
    "sg:tags":[
        "storage",
        "wine"
    ],
    "sg:website":"www.cellarmastersinc.com",
    "wof:name":"Cellar Masters",
    "wof:placetype":"venue"
},
  "geometry": {"coordinates":[-118.802327,34.15333],"type":"Point"}
}