{
  "type": "Feature",
  "properties": {
    "iso:country":"US",
    "sg:address":"1299 Lawrence Expy",
    "sg:city":"Santa Clara",
    "sg:classifiers":[
        {
            "category":"Restaurant",
            "type":"Food & Drink"
        }
    ],
    "sg:menulink":"http://www.allmenus.com/ca/san-jose/6550-acapulco/menu/",
    "sg:phone":"+1 408 249 2001",
    "sg:postcode":"95051",
    "sg:province":"CA",
    "sg:tags":[
        "american",
        "mexican",
        "tex-mex"
    ],
    "wof:name":"Acapulco",
    "wof:placetype":"venue"
},
  "geometry": {"coordinates":[-121.995732,37.34782],"type":"Point"}
}