{
  "type": "Feature",
  "properties": {
    "addr:full":"2400 Las Gallinas Ave San Rafael CA 94903",
    "addr:housenumber":"2400",
    "addr:postcode":"94903",
    "addr:street":"Las Gallinas Ave",
    "iso:country":"US",
    "sg:address":"2400 Las Gallinas Ave",
    "sg:city":"San Rafael",
    "sg:classifiers":[
        {
            "category":"Real Estate",
            "subcategory":"Real Estate Agent",
            "type":"Services"
        }
    ],
    "sg:phone":"+1 415 491 4555",
    "sg:postcode":"94903",
    "sg:province":"CA",
    "sg:tags":[
        "appraiser"
    ],
    "wof:name":"Scott Harritt",
    "wof:placetype":"venue"
},
  "geometry": {"coordinates":[-122.54447399999999,38.033525],"type":"Point"}
}