{
  "type": "Feature",
  "properties": {
    "iso:country":"US",
    "sg:address":"1224 Higuera St",
    "sg:city":"San Luis Obispo",
    "sg:classifiers":[
        {
            "category":"Professional",
            "subcategory":"Accounting & Tax Preparation",
            "type":"Services"
        }
    ],
    "sg:phone":"+1 805 781 6222",
    "sg:postcode":"93401",
    "sg:province":"CA",
    "sg:tags":[
        "accountant"
    ],
    "wof:name":"Preheim & Co",
    "wof:placetype":"venue"
},
  "geometry": {"coordinates":[-120.656853,35.283468],"type":"Point"}
}