{
  "type": "Feature",
  "properties": {
    "iso:country":"US",
    "sg:address":"2072 W Middlefield Rd",
    "sg:city":"Mountain View",
    "sg:classifiers":[
        {
            "category":"Personal",
            "subcategory":"Beauty Salon",
            "type":"Services"
        }
    ],
    "sg:phone":"+1 650 965 8067",
    "sg:postcode":"94043",
    "sg:province":"CA",
    "wof:name":"Rosa Maria Beauty Salon",
    "wof:placetype":"venue"
},
  "geometry": {"coordinates":[-122.090839,37.410999],"type":"Point"}
}