{
  "type": "Feature",
  "properties": {
    "iso:country":"US",
    "sg:address":"The Westmor Dance Studio 607 S Western Ave",
    "sg:city":"Los Angeles",
    "sg:classifiers":[
        {
            "category":"Education",
            "subcategory":"Special Training",
            "type":"Public Place"
        },
        {
            "category":"Recreation",
            "type":"Entertainment"
        }
    ],
    "sg:phone":"+1 626 354 1755",
    "sg:postcode":"90005",
    "sg:province":"CA",
    "sg:tags":[
        "active",
        "school",
        "life",
        "specialty"
    ],
    "sg:website":"www.bravodancing.com",
    "wof:name":"Bravo Dancing Ballroom Dance Instruction",
    "wof:placetype":"venue"
},
  "geometry": {"coordinates":[-118.309237,34.06316],"type":"Point"}
}