{
  "type": "Feature",
  "properties": {
    "iso:country":"US",
    "sg:address":"167 S Fortuna Blvd",
    "sg:city":"Fortuna",
    "sg:classifiers":[
        {
            "category":"Building & Trades",
            "subcategory":"Plumbing",
            "type":"Services"
        }
    ],
    "sg:phone":"+1 707 444 8227",
    "sg:postcode":"95540",
    "sg:province":"CA",
    "sg:tags":[
        "sheet",
        "work",
        "metal",
        "contractor"
    ],
    "wof:name":"Air Tight Heating & Sheet Mtl",
    "wof:placetype":"venue"
},
  "geometry": {"coordinates":[-124.146573,40.591393],"type":"Point"}
}