{
  "type": "Feature",
  "properties": {
    "iso:country":"US",
    "sg:address":"1227 Myszka Pl",
    "sg:city":"Ukiah",
    "sg:classifiers":[
        {
            "category":"Shopping",
            "type":"Retail Goods"
        }
    ],
    "sg:phone":"+1 707 462 8008",
    "sg:postcode":"95482",
    "sg:province":"CA",
    "sg:tags":[
        "merchandise",
        "monument"
    ],
    "wof:name":"Mendocino Monuments",
    "wof:placetype":"venue"
},
  "geometry": {"coordinates":[-123.22033500000001,39.147321],"type":"Point"}
}