{
  "type": "Feature",
  "properties": {
    "iso:country":"US",
    "sg:address":"1633 Cypress Ln",
    "sg:city":"Paradise",
    "sg:classifiers":[
        {
            "category":"Health Services",
            "subcategory":"Nursing And Care Facility",
            "type":"Services"
        }
    ],
    "sg:phone":"+1 530 877 9316",
    "sg:postcode":"95969",
    "sg:province":"CA",
    "sg:tags":[
        "skilled"
    ],
    "wof:name":"Cypress Acres Cnvalescent Hosp",
    "wof:placetype":"venue"
},
  "geometry": {"coordinates":[-121.585504,39.783871],"type":"Point"}
}