{
  "type": "Feature",
  "properties": {
    "addr:full":"544 E Magnolia Blvd Burbank CA 91501",
    "addr:housenumber":"544",
    "addr:postcode":"91501",
    "addr:street":"E Magnolia Blvd",
    "iso:country":"US",
    "sg:address":"544 E Magnolia Blvd",
    "sg:city":"Burbank",
    "sg:classifiers":[
        {
            "category":"Professional",
            "type":"Services"
        }
    ],
    "sg:phone":"+1 818 556 3950",
    "sg:postcode":"91501",
    "sg:province":"CA",
    "wof:name":"Clydon Corp",
    "wof:placetype":"venue"
},
  "geometry": {"coordinates":[-118.307238,34.187121],"type":"Point"}
}