{
  "type": "Feature",
  "properties": {
    "iso:country":"US",
    "sg:address":"3520 Maricopa St",
    "sg:city":"Torrance",
    "sg:classifiers":[
        {
            "category":"Wholesale",
            "subcategory":"Apparel",
            "type":"Manufacturing & Wholesale Goods"
        }
    ],
    "sg:phone":"+1 310 371 9151",
    "sg:postcode":"90503",
    "sg:province":"CA",
    "sg:tags":[
        "clothing"
    ],
    "wof:name":"Max Pose",
    "wof:placetype":"venue"
},
  "geometry": {"coordinates":[-118.348902,33.839373],"type":"Point"}
}