{
  "type": "Feature",
  "properties": {
    "iso:country":"US",
    "sg:address":"655 N Linden Dr",
    "sg:city":"Oxnard",
    "sg:classifiers":[
        {
            "category":"Retail",
            "subcategory":"Portrait Studio",
            "type":"Services"
        }
    ],
    "sg:phone":"+1 805 486 0018",
    "sg:postcode":"93033",
    "sg:province":"CA",
    "sg:tags":[
        "photographer"
    ],
    "wof:name":"Kennedy's Special Occasion",
    "wof:placetype":"venue"
},
  "geometry": {"coordinates":[-119.185507,34.176568],"type":"Point"}
}