{
  "type": "Feature",
  "properties": {
    "iso:country":"US",
    "sg:address":"4695 MacArthur Ct Ste 1440",
    "sg:city":"Newport Beach",
    "sg:classifiers":[
        {
            "category":"Professional",
            "subcategory":"Employment Agencies",
            "type":"Services"
        }
    ],
    "sg:phone":"+1 949 553 4200",
    "sg:postcode":"92660",
    "sg:province":"CA",
    "sg:website":"www.JobspringPartners.com",
    "wof:name":"Jobspring Partners",
    "wof:placetype":"venue"
},
  "geometry": {"coordinates":[-117.862551,33.669801],"type":"Point"}
}