{
  "type": "Feature",
  "properties": {
    "addr:full":"2413 S Fairview St Ste H Santa Ana CA 92704",
    "addr:housenumber":"2413",
    "addr:postcode":"92704",
    "addr:street":"S Fairview St Ste H",
    "iso:country":"US",
    "sg:address":"2413 S Fairview St Ste H",
    "sg:city":"Santa Ana",
    "sg:classifiers":[
        {
            "category":"Fast Food",
            "type":"Food & Drink"
        },
        {
            "category":"Restaurant",
            "type":"Food & Drink"
        }
    ],
    "sg:phone":"+1 714 434 0821",
    "sg:postcode":"92704",
    "sg:province":"CA",
    "sg:tags":[
        "mexican"
    ],
    "sg:website":"www.elpollomexicangrill.com",
    "wof:name":"Don Jacinto Pollo Grill",
    "wof:placetype":"venue"
},
  "geometry": {"coordinates":[-117.907044,33.713598],"type":"Point"}
}