{
  "type": "Feature",
  "properties": {
    "iso:country":"US",
    "sg:address":"13700 Marina Pointe Dr",
    "sg:city":"Marina del Rey",
    "sg:classifiers":[
        {
            "category":"Real Estate",
            "subcategory":"Real Estate Services",
            "type":"Services"
        }
    ],
    "sg:postcode":"90292",
    "sg:province":"CA",
    "sg:website":"www.azzurra-delrey.com",
    "wof:name":"Azzurra Del Rey Luxury High Rise Condos",
    "wof:placetype":"venue"
},
  "geometry": {"coordinates":[-118.445028,33.985068],"type":"Point"}
}