{
  "type": "Feature",
  "properties": {
    "addr:full":"1920 W Balboa Boulevard Newport Beach CA 92663",
    "addr:housenumber":"1920",
    "addr:postcode":"92663",
    "addr:street":"W Balboa Boulevard",
    "iso:country":"US",
    "sg:address":"1920 W Balboa Boulevard",
    "sg:city":"Newport Beach",
    "sg:classifiers":[
        {
            "category":"Food & Beverages",
            "subcategory":"Groceries & Convenience Stores",
            "type":"Retail Goods"
        }
    ],
    "sg:phone":"+1 949 673 6910",
    "sg:postcode":"92663",
    "sg:province":"CA",
    "wof:name":"7-Eleven Food Stores",
    "wof:placetype":"venue"
},
  "geometry": {"coordinates":[-117.926496,33.60819],"type":"Point"}
}