{
  "type": "Feature",
  "properties": {
    "addr:full":"551 Lighthouse Ave Pacific Grove CA 93950",
    "addr:housenumber":"551",
    "addr:postcode":"93950",
    "addr:street":"Lighthouse Ave",
    "iso:country":"US",
    "sg:address":"551 Lighthouse Ave",
    "sg:city":"Pacific Grove",
    "sg:classifiers":[
        {
            "category":"Shopping",
            "subcategory":"Used Merchandise",
            "type":"Retail Goods"
        }
    ],
    "sg:phone":"+1 831 655 1880",
    "sg:postcode":"93950",
    "sg:province":"CA",
    "sg:tags":[
        "clothing"
    ],
    "wof:name":"Deja Vu",
    "wof:placetype":"venue"
},
  "geometry": {"coordinates":[-121.916909,36.620621],"type":"Point"}
}