{
  "type": "Feature",
  "properties": {
    "addr:full":"70385 Highway 111 Rancho Mirage CA 92270",
    "addr:housenumber":"70385",
    "addr:postcode":"92270",
    "addr:street":"Highway 111",
    "iso:country":"US",
    "sg:address":"70385 Highway 111",
    "sg:city":"Rancho Mirage",
    "sg:classifiers":[
        {
            "category":"Restaurant",
            "type":"Food & Drink"
        }
    ],
    "sg:phone":"+1 760 328 1161",
    "sg:postcode":"92270",
    "sg:province":"CA",
    "wof:name":"Lord Fletcher's Restaurant",
    "wof:placetype":"venue"
},
  "geometry": {"coordinates":[-116.433998,33.756599],"type":"Point"}
}