{
  "type": "Feature",
  "properties": {
    "addr:full":"1215 N Sepulveda Boulevard Manhattan Beach CA 90266",
    "addr:housenumber":"1215",
    "addr:postcode":"90266",
    "addr:street":"N Sepulveda Boulevard",
    "iso:country":"US",
    "sg:address":"1215 N Sepulveda Boulevard",
    "sg:city":"Manhattan Beach",
    "sg:classifiers":[
        {
            "category":"Retail",
            "subcategory":"Animal Services",
            "type":"Services"
        }
    ],
    "sg:phone":"+1 310 545 8209",
    "sg:postcode":"90266",
    "sg:province":"CA",
    "sg:tags":[
        "pet"
    ],
    "wof:name":"Fuji Pet Salon",
    "wof:placetype":"venue"
},
  "geometry": {"coordinates":[-118.396198,33.888217],"type":"Point"}
}