{
  "type": "Feature",
  "properties": {
    "addr:full":"1650 E 4th St Santa Ana CA 92701",
    "addr:housenumber":"1650",
    "addr:postcode":"92701",
    "addr:street":"E 4Th St",
    "iso:country":"US",
    "sg:address":"1650 E 4th St",
    "sg:city":"Santa Ana",
    "sg:classifiers":[
        {
            "category":"Banks & Credit Unions",
            "subcategory":"Bank",
            "type":"Services"
        }
    ],
    "sg:phone":"+1 714 285 2911",
    "sg:postcode":"92701",
    "sg:province":"CA",
    "sg:tags":[
        "loan",
        "real estate"
    ],
    "wof:name":"First Mortgage Corp",
    "wof:placetype":"venue"
},
  "geometry": {"coordinates":[-117.84674699999999,33.748015],"type":"Point"}
}