{
  "type": "Feature",
  "properties": {
    "addr:full":"20237 Chapter Dr Woodland Hills CA 91364",
    "addr:postcode":"20237;91364",
    "addr:street":"Chapter Dr",
    "iso:country":"US",
    "sg:address":"20237 Chapter Dr",
    "sg:city":"Woodland Hills",
    "sg:classifiers":[
        {
            "category":"Retail",
            "subcategory":"Portrait Studio",
            "type":"Services"
        }
    ],
    "sg:phone":"+1 818 883 7866",
    "sg:postcode":"91364",
    "sg:province":"CA",
    "sg:tags":[
        "photographer"
    ],
    "wof:name":"California Family Photography",
    "wof:placetype":"venue"
},
  "geometry": {"coordinates":[-118.57690700000001,34.148429],"type":"Point"}
}