{
  "type": "Feature",
  "properties": {
    "iso:country":"US",
    "sg:address":"555 Beech Ave",
    "sg:city":"Carlsbad",
    "sg:classifiers":[
        {
            "category":"Manufacturing",
            "subcategory":"Printing",
            "type":"Manufacturing & Wholesale Goods"
        }
    ],
    "sg:phone":"+1 760 730 3023",
    "sg:postcode":"92008",
    "sg:province":"CA",
    "sg:tags":[
        "commercial"
    ],
    "wof:name":"Graphic Design",
    "wof:placetype":"venue"
},
  "geometry": {"coordinates":[-117.350634,33.162457],"type":"Point"}
}