{
  "type": "Feature",
  "properties": {
    "addr:full":"23825 Anza Ave Torrance CA 90505",
    "addr:housenumber":"23825",
    "addr:postcode":"90505",
    "addr:street":"Anza Ave",
    "iso:country":"US",
    "sg:address":"23825 Anza Ave",
    "sg:city":"Torrance",
    "sg:classifiers":[
        {
            "category":"Professional",
            "type":"Services"
        }
    ],
    "sg:phone":"+1 310 324 8824",
    "sg:postcode":"90505",
    "sg:province":"CA",
    "sg:tags":[
        "establishment"
    ],
    "wof:name":"Futureteco",
    "wof:placetype":"venue"
},
  "geometry": {"coordinates":[-118.35778500000001,33.80773],"type":"Point"}
}