{
  "type": "Feature",
  "properties": {
    "iso:country":"US",
    "sg:address":"880 Wagon Wheel Rd",
    "sg:city":"Oxnard",
    "sg:classifiers":[
        {
            "category":"Education",
            "subcategory":"Dance Studio",
            "type":"Public Place"
        }
    ],
    "sg:phone":"+1 805 485 0115",
    "sg:postcode":"93036",
    "sg:province":"CA",
    "sg:tags":[
        "instruction",
        "dancing"
    ],
    "sg:website":"www.mackinnondance.com",
    "wof:name":"Mac Kinnon Dance Academy",
    "wof:placetype":"venue"
},
  "geometry": {"coordinates":[-119.178883,34.233448],"type":"Point"}
}