{
  "type": "Feature",
  "properties": {
    "iso:country":"US",
    "sg:address":"800 Lindberg Ln",
    "sg:city":"Petaluma",
    "sg:classifiers":[
        {
            "category":"Insurance",
            "subcategory":"Hazard Insurance",
            "type":"Services"
        },
        {
            "category":"Insurance",
            "subcategory":"Insurance Agent",
            "type":"Services"
        },
        {
            "category":"Insurance",
            "subcategory":"Life Insurance",
            "type":"Services"
        }
    ],
    "sg:phone":"+1 707 766 0298",
    "sg:postcode":"94952",
    "sg:province":"CA",
    "sg:tags":[
        "auto"
    ],
    "sg:website":"http://statefarm.mqgroup.com/url.asp?usr=052094",
    "wof:name":"Cooley, Nancy - State Farm Insurance Agent",
    "wof:placetype":"venue"
},
  "geometry": {"coordinates":[-122.62404600000001,38.237309],"type":"Point"}
}