{
  "type": "Feature",
  "properties": {
    "addr:full":"67 Oakcrest Dr San Rafael CA 94903",
    "addr:housenumber":"67",
    "addr:postcode":"94903",
    "addr:street":"Oakcrest Dr",
    "iso:country":"US",
    "sg:address":"67 Oakcrest Dr",
    "sg:city":"San Rafael",
    "sg:classifiers":[
        {
            "category":"Professional",
            "subcategory":"Accounting & Tax Preparation",
            "type":"Services"
        }
    ],
    "sg:phone":"+1 415 472 3868",
    "sg:postcode":"94903",
    "sg:province":"CA",
    "sg:tags":[
        "billing"
    ],
    "wof:name":"O'Neal Medical Reimbursement",
    "wof:placetype":"venue"
},
  "geometry": {"coordinates":[-122.51870700000001,38.005239],"type":"Point"}
}