{
  "type": "Feature",
  "properties": {
    "iso:country":"US",
    "sg:address":"4741 Laurel Canyon Blvd",
    "sg:city":"Valley Village",
    "sg:classifiers":[
        {
            "category":"Communications",
            "subcategory":"Film & Video Production",
            "type":"Services"
        }
    ],
    "sg:phone":"+1 818 760 3110",
    "sg:postcode":"91607",
    "sg:province":"CA",
    "sg:tags":[
        "motion",
        "picture",
        "casting"
    ],
    "wof:name":"Richard Delancy & Assoc",
    "wof:placetype":"venue"
},
  "geometry": {"coordinates":[-118.396557,34.156443],"type":"Point"}
}