{
  "type": "Feature",
  "properties": {
    "iso:country":"US",
    "sg:address":"5601 Santa Ana St",
    "sg:city":"Ontario",
    "sg:classifiers":[
        {
            "category":"Manufacturing",
            "subcategory":"Rubber & Plastics",
            "type":"Manufacturing & Wholesale Goods"
        }
    ],
    "sg:phone":"+1 909 390 8866",
    "sg:postcode":"91761",
    "sg:province":"CA",
    "sg:tags":[
        "producer"
    ],
    "wof:name":"Exopack",
    "wof:placetype":"venue"
},
  "geometry": {"coordinates":[-117.526584,34.055449],"type":"Point"}
}