{
  "type": "Feature",
  "properties": {
    "addr:full":"38126 Sierra Hwy Palmdale CA 93550",
    "addr:housenumber":"38126",
    "addr:postcode":"ca 93550",
    "addr:street":"Sierra Hwy",
    "iso:country":"US",
    "sg:address":"38126 Sierra Hwy",
    "sg:city":"Palmdale",
    "sg:classifiers":[
        {
            "category":"Building & Trades",
            "subcategory":"Construction",
            "type":"Services"
        }
    ],
    "sg:phone":"+1 661 947 4151",
    "sg:postcode":"93550",
    "sg:province":"CA",
    "sg:tags":[
        "grading",
        "contractor"
    ],
    "wof:name":"Public Works Constr Permit",
    "wof:placetype":"venue"
},
  "geometry": {"coordinates":[-118.115652,34.573679],"type":"Point"}
}