{
  "type": "Feature",
  "properties": {
    "iso:country":"US",
    "sg:address":"608 Main St",
    "sg:city":"Pleasanton",
    "sg:classifiers":[
        {
            "category":"Professional",
            "subcategory":"Accounting & Tax Preparation",
            "type":"Services"
        }
    ],
    "sg:phone":"+1 925 484 5801",
    "sg:postcode":"94566",
    "sg:province":"CA",
    "sg:tags":[
        "accountant"
    ],
    "sg:website":"www.tvscpa.com",
    "wof:name":"Troy Van Sloten & Assoc",
    "wof:placetype":"venue"
},
  "geometry": {"coordinates":[-121.874913,37.662388],"type":"Point"}
}