{
  "type": "Feature",
  "properties": {
    "addr:full":"9115 Dice Rd Santa Fe Springs CA 90670",
    "addr:housenumber":"9115",
    "addr:postcode":"90670",
    "addr:street":"Dice Rd",
    "iso:country":"US",
    "sg:address":"9115 Dice Rd",
    "sg:city":"Santa Fe Springs",
    "sg:classifiers":[
        {
            "category":"Wholesale",
            "subcategory":"Office Equipment",
            "type":"Manufacturing & Wholesale Goods"
        }
    ],
    "sg:phone":"+1 562 941 1111",
    "sg:postcode":"90670",
    "sg:province":"CA",
    "wof:name":"Neamco",
    "wof:placetype":"venue"
},
  "geometry": {"coordinates":[-118.06688200000001,33.955563],"type":"Point"}
}