{
  "type": "Feature",
  "properties": {
    "addr:full":"1551 McCarthy Blvd Milpitas CA 95035",
    "addr:housenumber":"1551",
    "addr:postcode":"95035",
    "addr:street":"Mccarthy Blvd",
    "iso:country":"US",
    "sg:address":"1551 McCarthy Blvd",
    "sg:city":"Milpitas",
    "sg:classifiers":[
        {
            "category":"Banks & Credit Unions",
            "subcategory":"Financial Services",
            "type":"Services"
        }
    ],
    "sg:phone":"+1 408 433 0100",
    "sg:postcode":"95035",
    "sg:province":"CA",
    "sg:tags":[
        "broker",
        "mortgage"
    ],
    "wof:name":"Dreamworks Diversified Investment",
    "wof:placetype":"venue"
},
  "geometry": {"coordinates":[-121.919594,37.406633],"type":"Point"}
}