{
  "type": "Feature",
  "properties": {
    "iso:country":"US",
    "sg:address":"1656 W Ave L",
    "sg:city":"Lancaster",
    "sg:classifiers":[
        {
            "category":"Farming",
            "subcategory":"Livestock Farm",
            "type":"Manufacturing & Wholesale Goods"
        }
    ],
    "sg:phone":"+1 661 948 2476",
    "sg:postcode":"93534",
    "sg:province":"CA",
    "sg:tags":[
        "ornamental",
        "nursery",
        "specialty",
        "animal"
    ],
    "wof:name":"Shade Tree Farms",
    "wof:placetype":"venue"
},
  "geometry": {"coordinates":[-118.159297,34.660242],"type":"Point"}
}