{
  "type": "Feature",
  "properties": {
    "addr:full":"6441 Caldor Rd Somerset CA 95684",
    "addr:housenumber":"6441",
    "addr:postcode":"95684",
    "addr:street":"Caldor Rd",
    "iso:country":"US",
    "sg:address":"6441 Caldor Rd",
    "sg:city":"Somerset",
    "sg:classifiers":[
        {
            "category":"Farming",
            "subcategory":"Farm",
            "type":"Manufacturing & Wholesale Goods"
        }
    ],
    "sg:phone":"+1 530 622 3660",
    "sg:postcode":"95684",
    "sg:province":"CA",
    "wof:name":"Flying W Ranch",
    "wof:placetype":"venue"
},
  "geometry": {"coordinates":[-120.58992000000001,38.614639],"type":"Point"}
}