{
  "type": "Feature",
  "properties": {
    "iso:country":"US",
    "sg:address":"725 Deep Valley Dr",
    "sg:city":"Rolling Hls Ests",
    "sg:classifiers":[
        {
            "category":"Local Transit",
            "type":"Transportation"
        }
    ],
    "sg:phone":"+1 310 798 5466",
    "sg:postcode":"90274",
    "sg:province":"CA",
    "sg:tags":[
        "limousine"
    ],
    "wof:name":"Beach Cities Limousine Svc",
    "wof:placetype":"venue"
},
  "geometry": {"coordinates":[-118.371312,33.77042],"type":"Point"}
}