{
  "type": "Feature",
  "properties": {
    "addr:full":"7205 S Figueroa St Los Angeles CA 90003",
    "addr:housenumber":"7205",
    "addr:postcode":"90003",
    "addr:street":"S Figueroa St",
    "iso:country":"US",
    "sg:address":"7205 S Figueroa St",
    "sg:city":"Los Angeles",
    "sg:classifiers":[
        {
            "category":"Insurance",
            "subcategory":"Insurance Agent",
            "type":"Services"
        }
    ],
    "sg:phone":"+1 323 565 3520",
    "sg:postcode":"90003",
    "sg:province":"CA",
    "wof:name":"Van Ross Insurance Svc",
    "wof:placetype":"venue"
},
  "geometry": {"coordinates":[-118.28274999999999,33.973702],"type":"Point"}
}