{
  "type": "Feature",
  "properties": {
    "iso:country":"US",
    "sg:address":"44396 Galicia Dr",
    "sg:city":"Hemet",
    "sg:phone":"+1 951 927 6199",
    "sg:postcode":"92544",
    "sg:province":"CA",
    "sg:website":"http://www.bcroofingco.com",
    "wof:name":"B C's Roofing Co",
    "wof:placetype":"venue"
},
  "geometry": {"coordinates":[-116.886949,33.76159],"type":"Point"}
}