{
  "type": "Feature",
  "properties": {
    "iso:country":"US",
    "sg:address":"1801 Barber Ln",
    "sg:city":"Milpitas",
    "sg:classifiers":[
        {
            "category":"Shopping",
            "subcategory":"Gifts & Souvenirs",
            "type":"Retail Goods"
        }
    ],
    "sg:phone":"+1 408 473 8125",
    "sg:postcode":"95035",
    "sg:province":"CA",
    "sg:tags":[
        "shop"
    ],
    "wof:name":"Humas Gifts",
    "wof:placetype":"venue"
},
  "geometry": {"coordinates":[-121.911426,37.40826],"type":"Point"}
}