{
  "type": "Feature",
  "properties": {
    "addr:full":"18000 Studebaker Rd Ste 900A Cerritos CA 90703",
    "addr:housenumber":"18000;900a",
    "addr:postcode":"ca 90703",
    "addr:street":"Studebaker Rd Ste",
    "iso:country":"US",
    "sg:address":"18000 Studebaker Rd Ste 900A",
    "sg:city":"Cerritos",
    "sg:classifiers":[
        {
            "category":"Education",
            "subcategory":"Special Training",
            "type":"Public Place"
        },
        {
            "category":"Education",
            "subcategory":"School",
            "type":"Public Place"
        },
        {
            "category":"Education",
            "subcategory":"University",
            "type":"Public Place"
        }
    ],
    "sg:phone":"+1 562 809 5100",
    "sg:postcode":"90703",
    "sg:province":"CA",
    "sg:tags":[
        "college",
        "adult",
        "massage"
    ],
    "sg:website":"www.fremont.edu",
    "wof:name":"Fremont College",
    "wof:placetype":"venue"
},
  "geometry": {"coordinates":[-118.096367,33.868256],"type":"Point"}
}