{
  "type": "Feature",
  "properties": {
    "iso:country":"US",
    "sg:address":"135 E Las Flores Ave",
    "sg:city":"Arcadia",
    "sg:classifiers":[
        {
            "category":"Wholesale",
            "subcategory":"Chemicals & Plastics",
            "type":"Manufacturing & Wholesale Goods"
        }
    ],
    "sg:phone":"+1 626 447 5464",
    "sg:postcode":"91006",
    "sg:province":"CA",
    "wof:name":"Sue P Narevsky",
    "wof:placetype":"venue"
},
  "geometry": {"coordinates":[-118.026042,34.116202],"type":"Point"}
}