{
  "type": "Feature",
  "properties": {
    "addr:full":"3997 Hibiscus Cir Carlsbad CA 92008",
    "addr:housenumber":"3997",
    "addr:postcode":"92008",
    "addr:street":"Hibiscus Cir",
    "iso:country":"US",
    "sg:address":"3997 Hibiscus Cir",
    "sg:city":"Carlsbad",
    "sg:classifiers":[
        {
            "category":"Building & Trades",
            "subcategory":"Construction",
            "type":"Services"
        }
    ],
    "sg:phone":"+1 760 729 3432",
    "sg:postcode":"92008",
    "sg:province":"CA",
    "sg:tags":[
        "contractor"
    ],
    "wof:name":"Horizontal KURB",
    "wof:placetype":"venue"
},
  "geometry": {"coordinates":[-117.34004,33.149645],"type":"Point"}
}