{
  "type": "Feature",
  "properties": {
    "iso:country":"US",
    "sg:address":"4699 24th St",
    "sg:city":"Sacramento",
    "sg:classifiers":[
        {
            "category":"Wholesale",
            "subcategory":"Hardware",
            "type":"Manufacturing & Wholesale Goods"
        }
    ],
    "sg:phone":"+1 916 451 2821",
    "sg:postcode":"95822",
    "sg:province":"CA",
    "sg:tags":[
        "store"
    ],
    "sg:website":"http://www.cbhsec.com",
    "wof:name":"Capitol Builders Hardware Inc",
    "wof:placetype":"venue"
},
  "geometry": {"coordinates":[-121.483253,38.532249],"type":"Point"}
}