{
  "type": "Feature",
  "properties": {
    "iso:country":"US",
    "sg:address":"1060 S Broadway",
    "sg:city":"Los Angeles",
    "sg:classifiers":[
        {
            "category":"Shopping",
            "subcategory":"Crafts & Fabrics",
            "type":"Retail Goods"
        }
    ],
    "sg:phone":"+1 213 765 0145",
    "sg:postcode":"90015",
    "sg:province":"CA",
    "sg:tags":[
        "material",
        "needlework"
    ],
    "wof:name":"Appariel Angel",
    "wof:placetype":"venue"
},
  "geometry": {"coordinates":[-118.258032,34.040352],"type":"Point"}
}