{
  "type": "Feature",
  "properties": {
    "addr:full":"704 Garner Ave Salinas CA 93905",
    "addr:housenumber":"704",
    "addr:postcode":"93905",
    "addr:street":"Garner Ave",
    "iso:country":"US",
    "sg:address":"704 Garner Ave",
    "sg:city":"Salinas",
    "sg:classifiers":[
        {
            "category":"Freight",
            "type":"Transportation"
        }
    ],
    "sg:phone":"+1 831 753 1379",
    "sg:postcode":"93905",
    "sg:province":"CA",
    "sg:tags":[
        "operator",
        "local",
        "trucking"
    ],
    "wof:name":"L&G Trucking",
    "wof:placetype":"venue"
},
  "geometry": {"coordinates":[-121.618549,36.690097],"type":"Point"}
}