{
  "type": "Feature",
  "properties": {
    "iso:country":"US",
    "sg:address":"448 S Pershing Ave",
    "sg:city":"San Bernardino",
    "sg:classifiers":[
        {
            "category":"Autos & Motor Vehicles",
            "subcategory":"Auto Supplies",
            "type":"Retail Goods"
        }
    ],
    "sg:phone":"+1 909 383 3880",
    "sg:postcode":"92408",
    "sg:province":"CA",
    "sg:tags":[
        "equipment",
        "racing",
        "car",
        "automobile"
    ],
    "wof:name":"Spirit Products Inc",
    "wof:placetype":"venue"
},
  "geometry": {"coordinates":[-117.288597,34.095983],"type":"Point"}
}