{
  "type": "Feature",
  "properties": {
    "iso:country":"US",
    "sg:address":"8281 Monroe Ave",
    "sg:city":"Stanton",
    "sg:classifiers":[
        {
            "category":"Retail",
            "subcategory":"Repair Shop",
            "type":"Services"
        }
    ],
    "sg:phone":"+1 714 827 5077",
    "sg:postcode":"90680",
    "sg:province":"CA",
    "sg:tags":[
        "related"
    ],
    "wof:name":"Superior Manufacturing Eqpt",
    "wof:placetype":"venue"
},
  "geometry": {"coordinates":[-117.984571,33.805874],"type":"Point"}
}