{
  "type": "Feature",
  "properties": {
    "iso:country":"US",
    "sg:address":"15840 Ventura Blvd",
    "sg:city":"Encino",
    "sg:classifiers":[
        {
            "category":"Banks & Credit Unions",
            "subcategory":"Bank",
            "type":"Services"
        }
    ],
    "sg:phone":"+1 818 907 5246",
    "sg:postcode":"91436",
    "sg:province":"CA",
    "sg:tags":[
        "loan"
    ],
    "sg:website":"www.arnoldsutton.com",
    "wof:name":"Real Estate Investments",
    "wof:placetype":"venue"
},
  "geometry": {"coordinates":[-118.478676,34.1556],"type":"Point"}
}