{
  "type": "Feature",
  "properties": {
    "addr:full":"7080 Donlon Way Suite 215 Dublin CA 94568",
    "addr:postcode":"7080;94568",
    "addr:street":"Donlon Way Suite 215",
    "iso:country":"US",
    "sg:address":"7080 Donlon Way Suite 215",
    "sg:city":"Dublin",
    "sg:classifiers":[
        {
            "category":"Social Services",
            "type":"Services"
        },
        {
            "category":"Health Services",
            "subcategory":"Nursing And Care Facility",
            "type":"Services"
        },
        {
            "category":"Health Services",
            "subcategory":"Health Practitioner",
            "type":"Services"
        },
        {
            "category":"Social Services",
            "subcategory":"Adult Care",
            "type":"Services"
        }
    ],
    "sg:phone":"+1 925 833 9770",
    "sg:postcode":"94568",
    "sg:province":"CA",
    "sg:tags":[
        "counseling",
        "nurses-home",
        "consulting",
        "geriatric",
        "alzheimer's",
        "assisted",
        "disability",
        "elder",
        "citizen",
        "home",
        "living",
        "nurse",
        "eldercare-home",
        "senior"
    ],
    "sg:website":"http://www.brightstarcare.com/find-a-location/ca/castro-valley-san-leandro/",
    "wof:name":"BrightStar - Castro Valley & Dublin",
    "wof:placetype":"venue"
},
  "geometry": {"coordinates":[-121.93921899999999,37.702695],"type":"Point"}
}