{
  "type": "Feature",
  "properties": {
    "addr:full":"602 Farroll Rd Grover Beach CA 93433",
    "addr:housenumber":"602",
    "addr:postcode":"93433",
    "addr:street":"Farroll Rd",
    "iso:country":"US",
    "sg:address":"602 Farroll Rd",
    "sg:city":"Grover Beach",
    "sg:classifiers":[
        {
            "category":"Manufacturing",
            "subcategory":"Pottery",
            "type":"Manufacturing & Wholesale Goods"
        },
        {
            "category":"Wholesale",
            "subcategory":"Non-durable Goods",
            "type":"Manufacturing & Wholesale Goods"
        }
    ],
    "sg:phone":"+1 805 473 1749",
    "sg:postcode":"93433",
    "sg:province":"CA",
    "wof:name":"Moonlight & Roses",
    "wof:placetype":"venue"
},
  "geometry": {"coordinates":[-120.624458,35.114438],"type":"Point"}
}