{
  "type": "Feature",
  "properties": {
    "iso:country":"US",
    "sg:address":"34864 Mission Blvd",
    "sg:city":"Union City",
    "sg:classifiers":[
        {
            "category":"Professional",
            "subcategory":"Accounting & Tax Preparation",
            "type":"Services"
        }
    ],
    "sg:phone":"+1 510 754 9855",
    "sg:postcode":"94587",
    "sg:province":"CA",
    "sg:tags":[
        "return",
        "filing"
    ],
    "wof:name":"Gonzales Professional Svc",
    "wof:placetype":"venue"
},
  "geometry": {"coordinates":[-122.002474,37.590699],"type":"Point"}
}