{
  "type": "Feature",
  "properties": {
    "iso:country":"US",
    "sg:address":"9501 Kruse Rd",
    "sg:city":"Pico Rivera",
    "sg:classifiers":[
        {
            "category":"Building & Trades",
            "subcategory":"Construction",
            "type":"Services"
        }
    ],
    "sg:phone":"+1 562 692 1203",
    "sg:postcode":"90660",
    "sg:province":"CA",
    "sg:tags":[
        "excavating",
        "contractor"
    ],
    "wof:name":"A L Mac Intosh Co",
    "wof:placetype":"venue"
},
  "geometry": {"coordinates":[-118.063159,34.019686],"type":"Point"}
}