{
  "type": "Feature",
  "properties": {
    "addr:full":"5223 S Normandie Ave Los Angeles CA 90037",
    "addr:housenumber":"5223",
    "addr:postcode":"90037",
    "addr:street":"S Normandie Ave",
    "iso:country":"US",
    "sg:address":"5223 S Normandie Ave",
    "sg:city":"Los Angeles",
    "sg:classifiers":[
        {
            "category":"Retail",
            "subcategory":"Auto Repair",
            "type":"Services"
        }
    ],
    "sg:phone":"+1 323 299 8374",
    "sg:postcode":"90037",
    "sg:province":"CA",
    "sg:tags":[
        "automotive",
        "information"
    ],
    "wof:name":"Umana Auto Registration",
    "wof:placetype":"venue"
},
  "geometry": {"coordinates":[-118.300254,33.994346],"type":"Point"}
}