{
  "type": "Feature",
  "properties": {
    "iso:country":"US",
    "sg:address":"13101 W Washington Blvd Ste 204",
    "sg:city":"Los Angeles",
    "sg:classifiers":[
        {
            "category":"Shopping",
            "subcategory":"Music",
            "type":"Retail Goods"
        }
    ],
    "sg:phone":"+1 310 566 7515",
    "sg:postcode":"90066",
    "sg:province":"CA",
    "sg:tags":[
        "dvd's"
    ],
    "sg:website":"www.jbhomecare.com",
    "wof:name":"JB Home Care Referral Agency",
    "wof:placetype":"venue"
},
  "geometry": {"coordinates":[-118.440833,33.994092],"type":"Point"}
}