{
  "type": "Feature",
  "properties": {
    "iso:country":"US",
    "sg:address":"10900 Alondra Blvd",
    "sg:city":"Cerritos",
    "sg:classifiers":[
        {
            "category":"Restaurant",
            "type":"Food & Drink"
        }
    ],
    "sg:phone":"+1 562 865 2717",
    "sg:postcode":"90703",
    "sg:province":"CA",
    "sg:tags":[
        "new",
        "american"
    ],
    "wof:name":"Spires Restaurants Inc",
    "wof:placetype":"venue"
},
  "geometry": {"coordinates":[-118.100998,33.887402],"type":"Point"}
}