{
  "type": "Feature",
  "properties": {
    "addr:full":"8737 Holloway Dr Los Angeles CA 90069",
    "addr:housenumber":"8737",
    "addr:postcode":"90069",
    "addr:street":"Holloway Dr",
    "iso:country":"US",
    "sg:address":"8737 Holloway Dr",
    "sg:city":"Los Angeles",
    "sg:classifiers":[
        {
            "category":"Professional",
            "subcategory":"Business Services",
            "type":"Services"
        }
    ],
    "sg:phone":"+1 310 855 1128",
    "sg:postcode":"90069",
    "sg:province":"CA",
    "sg:tags":[
        "plant",
        "design",
        "maintenance"
    ],
    "wof:name":"Bill Vicik",
    "wof:placetype":"venue"
},
  "geometry": {"coordinates":[-118.382721,34.090668],"type":"Point"}
}