{
  "type": "Feature",
  "properties": {
    "addr:full":"1901 Church Ln San Pablo CA 94806",
    "addr:housenumber":"1901",
    "addr:postcode":"94806",
    "addr:street":"Church Ln",
    "iso:country":"US",
    "sg:address":"1901 Church Ln",
    "sg:city":"San Pablo",
    "sg:classifiers":[
        {
            "category":"Organizations",
            "subcategory":"Non-profit Organization",
            "type":"Services"
        }
    ],
    "sg:phone":"+1 510 236 3134",
    "sg:postcode":"94806",
    "sg:province":"CA",
    "sg:tags":[
        "info",
        "addiction",
        "abuse",
        "treatment",
        "drug"
    ],
    "wof:name":"Rectory Women's Residential",
    "wof:placetype":"venue"
},
  "geometry": {"coordinates":[-122.340834,37.958076],"type":"Point"}
}