{
  "type": "Feature",
  "properties": {
    "iso:country":"US",
    "sg:address":"1355 Adams Ct",
    "sg:city":"Menlo Park",
    "sg:classifiers":[
        {
            "category":"Freight",
            "type":"Transportation"
        }
    ],
    "sg:phone":"+1 650 462 4800",
    "sg:postcode":"94025",
    "sg:province":"CA",
    "sg:tags":[
        "mover"
    ],
    "wof:name":"Rossiter Relocation Svc",
    "wof:placetype":"venue"
},
  "geometry": {"coordinates":[-122.144732,37.478764],"type":"Point"}
}