{
  "type": "Feature",
  "properties": {
    "addr:full":"2411 2nd Ave San Diego CA 92101",
    "addr:housenumber":"2411",
    "addr:postcode":"92101",
    "addr:street":"2Nd Ave",
    "iso:country":"US",
    "sg:address":"2411 2nd Ave",
    "sg:city":"San Diego",
    "sg:classifiers":[
        {
            "category":"Professional",
            "type":"Services"
        }
    ],
    "sg:phone":"+1 619 235 9484",
    "sg:postcode":"92101",
    "sg:province":"CA",
    "sg:tags":[
        "establishment"
    ],
    "wof:name":"Metroplan LLC",
    "wof:placetype":"venue"
},
  "geometry": {"coordinates":[-117.162952,32.731267],"type":"Point"}
}