{
  "type": "Feature",
  "properties": {
    "addr:full":"2334 S Atlantic Blvd Suite #B Monterey Park CA 91754",
    "addr:housenumber":"2334",
    "addr:postcode":"91754",
    "addr:street":"S Atlantic Blvd Suite # B",
    "iso:country":"US",
    "sg:address":"2334 S Atlantic Blvd Suite #B",
    "sg:city":"Monterey Park",
    "sg:classifiers":[
        {
            "category":"Shopping",
            "subcategory":"Computers & Home Electronics",
            "type":"Retail Goods"
        },
        {
            "category":"Professional",
            "subcategory":"Computer Services",
            "type":"Services"
        }
    ],
    "sg:phone":"+1 323 722 9800",
    "sg:postcode":"91754",
    "sg:province":"CA",
    "sg:tags":[
        "stereo",
        "installation"
    ],
    "sg:website":"www.ArmexCarAudio.com",
    "wof:name":"Armex Car Audio",
    "wof:placetype":"venue"
},
  "geometry": {"coordinates":[-118.147616,34.036622],"type":"Point"}
}