{
  "type": "Feature",
  "properties": {
    "iso:country":"US",
    "sg:address":"1416 9th St",
    "sg:city":"Sacramento",
    "sg:classifiers":[
        {
            "category":"Government",
            "subcategory":"Office",
            "type":"Public Place"
        }
    ],
    "sg:phone":"+1 916 653 4280",
    "sg:postcode":"95814",
    "sg:province":"CA",
    "sg:tags":[
        "conservation"
    ],
    "wof:name":"Fisheries Programs",
    "wof:placetype":"venue"
},
  "geometry": {"coordinates":[-121.496968,38.575899],"type":"Point"}
}