{
  "type": "Feature",
  "properties": {
    "addr:full":"8641 Wilshire Boulevard Beverly Hills CA 90211",
    "addr:housenumber":"8641",
    "addr:postcode":"90211",
    "addr:street":"Wilshire Boulevard",
    "iso:country":"US",
    "sg:address":"8641 Wilshire Boulevard",
    "sg:city":"Beverly Hills",
    "sg:classifiers":[
        {
            "category":"Health Services",
            "subcategory":"Doctor",
            "type":"Services"
        }
    ],
    "sg:phone":"+1 310 659 3251",
    "sg:postcode":"90211",
    "sg:province":"CA",
    "wof:name":"Smith Samuel J MD.",
    "wof:placetype":"venue"
},
  "geometry": {"coordinates":[-118.379481,34.066083],"type":"Point"}
}