{
  "type": "Feature",
  "properties": {
    "addr:full":"421 Gharkey St Santa Cruz CA 95060",
    "addr:housenumber":"421",
    "addr:postcode":"95060",
    "addr:street":"Gharkey St",
    "iso:country":"US",
    "sg:address":"421 Gharkey St",
    "sg:city":"Santa Cruz",
    "sg:classifiers":[
        {
            "category":"Professional",
            "type":"Services"
        }
    ],
    "sg:phone":"+1 831 425 1602",
    "sg:postcode":"95060",
    "sg:province":"CA",
    "wof:name":"Nancy Howells",
    "wof:placetype":"venue"
},
  "geometry": {"coordinates":[-122.03122399999999,36.959819],"type":"Point"}
}