{
  "type": "Feature",
  "properties": {
    "iso:country":"US",
    "sg:address":"606 S Broadway",
    "sg:city":"Los Angeles",
    "sg:classifiers":[
        {
            "category":"Shopping",
            "subcategory":"Jewelry",
            "type":"Retail Goods"
        }
    ],
    "sg:phone":"+1 213 688 7920",
    "sg:postcode":"90014",
    "sg:province":"CA",
    "wof:name":"Casey's Jewelry",
    "wof:placetype":"venue"
},
  "geometry": {"coordinates":[-118.251999,34.046501],"type":"Point"}
}