{
  "type": "Feature",
  "properties": {
    "iso:country":"US",
    "sg:address":"13246 Fiji Way",
    "sg:city":"Marina Del Rey",
    "sg:classifiers":[
        {
            "category":"Professional",
            "subcategory":"Lawyer & Legal Services",
            "type":"Services"
        }
    ],
    "sg:phone":"+1 310 821 8886",
    "sg:postcode":"90292",
    "sg:province":"CA",
    "wof:name":"Goldman Ronald L M",
    "wof:placetype":"venue"
},
  "geometry": {"coordinates":[-118.434072,33.979938],"type":"Point"}
}