{
  "type": "Feature",
  "properties": {
    "iso:country":"US",
    "sg:address":"3720 Florence St",
    "sg:city":"Redwood City",
    "sg:classifiers":[
        {
            "category":"Personal",
            "subcategory":"Beauty Salon",
            "type":"Services"
        }
    ],
    "sg:phone":"+1 650 599 9227",
    "sg:postcode":"94063",
    "sg:province":"CA",
    "sg:tags":[
        "manicuring"
    ],
    "wof:name":"Helena's Nail Salon",
    "wof:placetype":"venue"
},
  "geometry": {"coordinates":[-122.186566,37.478661],"type":"Point"}
}