{
  "type": "Feature",
  "properties": {
    "addr:full":"2259 N Roswell Ave Long Beach CA 90815",
    "addr:housenumber":"2259",
    "addr:postcode":"90815",
    "addr:street":"N Roswell Ave",
    "iso:country":"US",
    "sg:address":"2259 N Roswell Ave",
    "sg:city":"Long Beach",
    "sg:classifiers":[
        {
            "category":"Professional",
            "type":"Services"
        }
    ],
    "sg:phone":"+1 562 597 7879",
    "sg:postcode":"90815",
    "sg:province":"CA",
    "wof:name":"Chapter 7 Fullerton Exper",
    "wof:placetype":"venue"
},
  "geometry": {"coordinates":[-118.14344800000001,33.797764],"type":"Point"}
}