{
  "type": "Feature",
  "properties": {
    "addr:full":"303 2nd St Ste 300 N San Francisco CA 94107",
    "addr:housenumber":"303",
    "addr:postcode":"94107",
    "addr:street":"2Nd St Ste 300 N",
    "iso:country":"US",
    "sg:address":"303 2nd St Ste 300 N",
    "sg:city":"San Francisco",
    "sg:classifiers":[
        {
            "category":"Communications",
            "subcategory":"Newspaper",
            "type":"Services"
        }
    ],
    "sg:phone":"+1 415 403 8000",
    "sg:postcode":"94107",
    "sg:province":"CA",
    "sg:tags":[
        "print",
        "medium"
    ],
    "sg:website":"www.greysf.com",
    "wof:name":"Grey San Francisco",
    "wof:placetype":"venue"
},
  "geometry": {"coordinates":[-122.39668899999999,37.78554],"type":"Point"}
}