{
  "type": "Feature",
  "properties": {
    "iso:country":"US",
    "sg:address":"2015 Shattuck Ave",
    "sg:city":"Berkeley",
    "sg:classifiers":[
        {
            "category":"Professional",
            "subcategory":"Printing & Photocopies",
            "type":"Services"
        }
    ],
    "sg:phone":"+1 510 704 9700",
    "sg:postcode":"94704",
    "sg:province":"CA",
    "sg:tags":[
        "duplicating",
        "copying"
    ],
    "wof:name":"Instant Copying & Laser Ptg",
    "wof:placetype":"venue"
},
  "geometry": {"coordinates":[-122.26780100000001,37.872178],"type":"Point"}
}