{
  "type": "Feature",
  "properties": {
    "iso:country":"US",
    "sg:address":"5380 Dehesa Rd",
    "sg:city":"El Cajon",
    "sg:classifiers":[
        {
            "category":"Retail",
            "subcategory":"Animal Services",
            "type":"Services"
        }
    ],
    "sg:phone":"+1 619 659 2888",
    "sg:postcode":"92019",
    "sg:province":"CA",
    "wof:name":"Peppertree Pet Resort",
    "wof:placetype":"venue"
},
  "geometry": {"coordinates":[-116.836692,32.790536],"type":"Point"}
}