{
  "type": "Feature",
  "properties": {
    "addr:full":"3530 Wilshire Blvd Los Angeles CA 90010",
    "addr:housenumber":"3530",
    "addr:postcode":"90010",
    "addr:street":"Wilshire Blvd",
    "iso:country":"US",
    "sg:address":"3530 Wilshire Blvd",
    "sg:city":"Los Angeles",
    "sg:classifiers":[
        {
            "category":"Insurance",
            "subcategory":"Insurance Agent",
            "type":"Services"
        }
    ],
    "sg:phone":"+1 213 380 0709",
    "sg:postcode":"90010",
    "sg:province":"CA",
    "wof:name":"Met Life",
    "wof:placetype":"venue"
},
  "geometry": {"coordinates":[-118.301256,34.061662],"type":"Point"}
}