{
  "type": "Feature",
  "properties": {
    "addr:full":"2200 34th Ave San Francisco CA 94116",
    "addr:housenumber":"2200",
    "addr:postcode":"94116",
    "addr:street":"34Th Ave",
    "iso:country":"US",
    "sg:address":"2200 34th Ave",
    "sg:city":"San Francisco",
    "sg:classifiers":[
        {
            "category":"Wholesale",
            "subcategory":"Electrical",
            "type":"Manufacturing & Wholesale Goods"
        }
    ],
    "sg:phone":"+1 415 665 3688",
    "sg:postcode":"94116",
    "sg:province":"CA",
    "sg:tags":[
        "equipment"
    ],
    "wof:name":"Satellite Intl Trade Co",
    "wof:placetype":"venue"
},
  "geometry": {"coordinates":[-122.491901,37.744209],"type":"Point"}
}