{
  "type": "Feature",
  "properties": {
    "iso:country":"US",
    "sg:address":"98 Main St",
    "sg:city":"Belvedere Tibrn",
    "sg:classifiers":[
        {
            "category":"Manufacturing",
            "subcategory":"Tools & Machinery",
            "type":"Manufacturing & Wholesale Goods"
        }
    ],
    "sg:phone":"+1 415 435 1891",
    "sg:postcode":"94920",
    "sg:province":"CA",
    "sg:tags":[
        "physician",
        "surgeon"
    ],
    "wof:name":"Laurel Designs",
    "wof:placetype":"venue"
},
  "geometry": {"coordinates":[-122.458369,37.873713],"type":"Point"}
}