{
  "type": "Feature",
  "properties": {
    "iso:country":"US",
    "sg:address":"77 Pacific Ave",
    "sg:city":"Auburn",
    "sg:classifiers":[
        {
            "category":"Real Estate",
            "subcategory":"Real Estate Operator",
            "type":"Services"
        }
    ],
    "sg:phone":"+1 530 888 7343",
    "sg:postcode":"95603",
    "sg:province":"CA",
    "sg:tags":[
        "apartment"
    ],
    "wof:name":"Crest View Apartments",
    "wof:placetype":"venue"
},
  "geometry": {"coordinates":[-121.07644999999999,38.88561],"type":"Point"}
}