{
  "type": "Feature",
  "properties": {
    "iso:country":"US",
    "sg:address":"924-2 Santee St 2nd Fl",
    "sg:city":"Los Angeles",
    "sg:classifiers":[
        {
            "category":"Personal",
            "type":"Services"
        }
    ],
    "sg:phone":"+1 213 627 3994",
    "sg:postcode":"90015",
    "sg:province":"CA",
    "sg:tags":[
        "sewing",
        "alteration"
    ],
    "wof:name":"Santee Alterations",
    "wof:placetype":"venue"
},
  "geometry": {"coordinates":[-118.254012,34.039533],"type":"Point"}
}