{
  "type": "Feature",
  "properties": {
    "iso:country":"US",
    "sg:address":"633 S Main St",
    "sg:city":"Ukiah",
    "sg:classifiers":[
        {
            "category":"Professional",
            "subcategory":"Computer Services",
            "type":"Services"
        }
    ],
    "sg:phone":"+1 707 462 1578",
    "sg:postcode":"95482",
    "sg:province":"CA",
    "sg:tags":[
        "repair"
    ],
    "wof:name":"Computer Scene",
    "wof:placetype":"venue"
},
  "geometry": {"coordinates":[-123.205054,39.144442],"type":"Point"}
}