{
  "type": "Feature",
  "properties": {
    "iso:country":"US",
    "sg:address":"1584 W Base Line St",
    "sg:city":"San Bernardino",
    "sg:classifiers":[
        {
            "category":"Retail",
            "subcategory":"Self-service Laundry",
            "type":"Services"
        }
    ],
    "sg:phone":"+1 909 383 1054",
    "sg:postcode":"92411",
    "sg:province":"CA",
    "wof:name":"Laundryland",
    "wof:placetype":"venue"
},
  "geometry": {"coordinates":[-117.32199900000001,34.121427],"type":"Point"}
}