{
  "type": "Feature",
  "properties": {
    "addr:full":"16300 Arrow Hwy Baldwin Park CA 91706",
    "addr:housenumber":"16300",
    "addr:postcode":"91706",
    "addr:street":"Arrow Hwy",
    "iso:country":"US",
    "sg:address":"16300 Arrow Hwy",
    "sg:city":"Baldwin Park",
    "sg:classifiers":[
        {
            "category":"Retail",
            "subcategory":"Repair Shop",
            "type":"Services"
        }
    ],
    "sg:phone":"+1 626 338 5597",
    "sg:postcode":"91706",
    "sg:province":"CA",
    "sg:tags":[
        "tool",
        "parts"
    ],
    "wof:name":"Stuart Construction Tool Ctr",
    "wof:placetype":"venue"
},
  "geometry": {"coordinates":[-117.928827,34.106973],"type":"Point"}
}