{
  "type": "Feature",
  "properties": {
    "iso:country":"US",
    "sg:address":"6747 Odessa Ave",
    "sg:city":"Van Nuys",
    "sg:classifiers":[
        {
            "category":"Wholesale",
            "subcategory":"Non-durable Goods",
            "type":"Manufacturing & Wholesale Goods"
        }
    ],
    "sg:phone":"+1 818 780 1611",
    "sg:postcode":"91406",
    "sg:province":"CA",
    "wof:name":"Millenium Global Import & Expo",
    "wof:placetype":"venue"
},
  "geometry": {"coordinates":[-118.490274,34.191223],"type":"Point"}
}