{
  "type": "Feature",
  "properties": {
    "addr:full":"9665 Wilshire Blvd Beverly Hills CA 90212",
    "addr:housenumber":"9665",
    "addr:postcode":"90212",
    "addr:street":"Wilshire Blvd",
    "iso:country":"US",
    "sg:address":"9665 Wilshire Blvd",
    "sg:city":"Beverly Hills",
    "sg:classifiers":[
        {
            "category":"Banks & Credit Unions",
            "subcategory":"Investment Brokerage",
            "type":"Services"
        }
    ],
    "sg:phone":"+1 310 288 7000",
    "sg:postcode":"90212",
    "sg:province":"CA",
    "sg:tags":[
        "firm",
        "brokerage",
        "stock"
    ],
    "wof:name":"Ryan Beck & Co Inc",
    "wof:placetype":"venue"
},
  "geometry": {"coordinates":[-118.40536899999999,34.067141],"type":"Point"}
}