{
  "type": "Feature",
  "properties": {
    "addr:full":"212 E Grand Blvd Corona CA 92879",
    "addr:housenumber":"212",
    "addr:postcode":"92879",
    "addr:street":"E Grand Blvd",
    "iso:country":"US",
    "sg:address":"212 E Grand Blvd",
    "sg:city":"Corona",
    "sg:classifiers":[
        {
            "category":"Organizations",
            "subcategory":"Religious Organization",
            "type":"Services"
        }
    ],
    "sg:phone":"+1 951 736 1031",
    "sg:postcode":"92879",
    "sg:province":"CA",
    "sg:tags":[
        "church"
    ],
    "wof:name":"Salvation Army",
    "wof:placetype":"venue"
},
  "geometry": {"coordinates":[-117.559387,33.877921],"type":"Point"}
}