{
  "type": "Feature",
  "properties": {
    "addr:full":"17085 Malaga St Fontana CA 92336",
    "addr:postcode":"17085;92336",
    "addr:street":"Malaga St",
    "iso:country":"US",
    "sg:address":"17085 Malaga St",
    "sg:city":"Fontana",
    "sg:classifiers":[
        {
            "category":"Building & Trades",
            "subcategory":"Construction",
            "type":"Services"
        }
    ],
    "sg:phone":"+1 909 428 1898",
    "sg:postcode":"92336",
    "sg:province":"CA",
    "sg:tags":[
        "contractor"
    ],
    "wof:name":"Cal Star Roofing",
    "wof:placetype":"venue"
},
  "geometry": {"coordinates":[-117.435446,34.111132],"type":"Point"}
}