{
  "type": "Feature",
  "properties": {
    "iso:country":"US",
    "sg:address":"3774 Mission Boulevard",
    "sg:city":"San Diego",
    "sg:classifiers":[
        {
            "category":"Restaurant",
            "type":"Food & Drink"
        }
    ],
    "sg:phone":"+1 619 645 7124",
    "sg:postcode":"92109",
    "sg:province":"CA",
    "wof:name":"Ono Sushi",
    "wof:placetype":"venue"
},
  "geometry": {"coordinates":[-117.252666,32.784269],"type":"Point"}
}