{
  "type": "Feature",
  "properties": {
    "iso:country":"US",
    "sg:address":"1455 Crenshaw Blvd",
    "sg:city":"Torrance",
    "sg:classifiers":[
        {
            "category":"Professional",
            "subcategory":"Lawyer & Legal Services",
            "type":"Services"
        }
    ],
    "sg:phone":"+1 310 320 7700",
    "sg:postcode":"90501",
    "sg:province":"CA",
    "wof:name":"Eto Gary Atty",
    "wof:placetype":"venue"
},
  "geometry": {"coordinates":[-118.327003,33.836399],"type":"Point"}
}