{
  "type": "Feature",
  "properties": {
    "iso:country":"US",
    "sg:address":"2521 Stockton Blvd",
    "sg:city":"Sacramento",
    "sg:classifiers":[
        {
            "category":"Shopping",
            "type":"Retail Goods"
        }
    ],
    "sg:phone":"+1 916 734 5400",
    "sg:postcode":"95817",
    "sg:province":"CA",
    "sg:tags":[
        "merchandise"
    ],
    "wof:name":"Doyle Karen J Md Phd Otolog Y",
    "wof:placetype":"venue"
},
  "geometry": {"coordinates":[-121.455659,38.551594],"type":"Point"}
}