{
  "type": "Feature",
  "properties": {
    "addr:full":"10430 S de Anza Blvd Cupertino CA 95014",
    "addr:housenumber":"10430",
    "addr:postcode":"95014",
    "addr:street":"S De Anza Blvd",
    "iso:country":"US",
    "sg:address":"10430 S de Anza Blvd",
    "sg:city":"Cupertino",
    "sg:classifiers":[
        {
            "category":"Health Services",
            "subcategory":"Doctor",
            "type":"Services"
        }
    ],
    "sg:phone":"+1 408 996 1007",
    "sg:postcode":"95014",
    "sg:province":"CA",
    "sg:tags":[
        "dentist"
    ],
    "wof:name":"Leon Davis Jr DDS",
    "wof:placetype":"venue"
},
  "geometry": {"coordinates":[-122.03236,37.318042],"type":"Point"}
}