{
  "type": "Feature",
  "properties": {
    "iso:country":"US",
    "sg:address":"1600 Riviera Ave",
    "sg:city":"Walnut Creek",
    "sg:classifiers":[
        {
            "category":"Professional",
            "subcategory":"Accounting & Tax Preparation",
            "type":"Services"
        }
    ],
    "sg:phone":"+1 925 951 1366",
    "sg:postcode":"94596",
    "sg:province":"CA",
    "sg:tags":[
        "management"
    ],
    "wof:name":"Anesthesia Consultants of Cont",
    "wof:placetype":"venue"
},
  "geometry": {"coordinates":[-122.06683099999999,37.911259],"type":"Point"}
}