{
  "type": "Feature",
  "properties": {
    "iso:country":"US",
    "sg:address":"2404 San Ramon Valley Blvd",
    "sg:city":"San Ramon",
    "sg:classifiers":[
        {
            "category":"Insurance",
            "subcategory":"Insurance Agent",
            "type":"Services"
        }
    ],
    "sg:phone":"+1 925 743 3399",
    "sg:postcode":"94583",
    "sg:province":"CA",
    "wof:name":"Lincoln National Life Ins Co",
    "wof:placetype":"venue"
},
  "geometry": {"coordinates":[-121.973476,37.771273],"type":"Point"}
}