{
  "type": "Feature",
  "properties": {
    "iso:country":"US",
    "sg:address":"2038 Corte Del Nogal Ste 100",
    "sg:city":"Carlsbad",
    "sg:classifiers":[
        {
            "category":"Banks & Credit Unions",
            "subcategory":"Investment Brokerage",
            "type":"Services"
        }
    ],
    "sg:phone":"+1 760 804 6020",
    "sg:postcode":"92011",
    "sg:province":"CA",
    "sg:tags":[
        "investing"
    ],
    "sg:website":"www.hunterchase.com",
    "wof:name":"Hunter Chase & Co",
    "wof:placetype":"venue"
},
  "geometry": {"coordinates":[-117.278239,33.11992],"type":"Point"}
}