{
  "type": "Feature",
  "properties": {
    "iso:country":"US",
    "sg:address":"2350 Mission College Blvd",
    "sg:city":"Santa Clara",
    "sg:classifiers":[
        {
            "category":"Restaurant",
            "type":"Food & Drink"
        }
    ],
    "sg:phone":"+1 408 567 0678",
    "sg:postcode":"95054",
    "sg:province":"CA",
    "sg:tags":[
        "cafeteria"
    ],
    "wof:name":"Regency Cafe",
    "wof:placetype":"venue"
},
  "geometry": {"coordinates":[-121.96659,37.38879],"type":"Point"}
}