{
  "type": "Feature",
  "properties": {
    "iso:country":"US",
    "sg:address":"413 Mariposa Dr",
    "sg:city":"Ventura",
    "sg:classifiers":[
        {
            "category":"Building & Trades",
            "subcategory":"Construction",
            "type":"Services"
        }
    ],
    "sg:phone":"+1 805 652 1556",
    "sg:postcode":"93001",
    "sg:province":"CA",
    "sg:tags":[
        "repairing",
        "remodeling",
        "contractor"
    ],
    "wof:name":"S G Enterprise",
    "wof:placetype":"venue"
},
  "geometry": {"coordinates":[-119.2769,34.28709],"type":"Point"}
}