{
  "type": "Feature",
  "properties": {
    "addr:full":"2629 Waterloo Rd Stockton CA 95205",
    "addr:housenumber":"2629",
    "addr:postcode":"95205",
    "addr:street":"Waterloo Rd",
    "iso:country":"US",
    "sg:address":"2629 Waterloo Rd",
    "sg:city":"Stockton",
    "sg:classifiers":[
        {
            "category":"Real Estate",
            "subcategory":"Real Estate Operator",
            "type":"Services"
        }
    ],
    "sg:phone":"+1 209 463 4413",
    "sg:postcode":"95205",
    "sg:province":"CA",
    "sg:tags":[
        "mobile",
        "home",
        "community"
    ],
    "wof:name":"El Rey Mobile Home Park",
    "wof:placetype":"venue"
},
  "geometry": {"coordinates":[-121.25878,37.978986],"type":"Point"}
}