{
  "type": "Feature",
  "properties": {
    "addr:full":"9330 Sky Park Ct San Diego CA 92123",
    "addr:housenumber":"9330",
    "addr:postcode":"92123",
    "addr:street":"Sky Park Ct",
    "iso:country":"US",
    "sg:address":"9330 Sky Park Ct",
    "sg:city":"San Diego",
    "sg:classifiers":[
        {
            "category":"Manufacturing",
            "subcategory":"Tools & Machinery",
            "type":"Manufacturing & Wholesale Goods"
        }
    ],
    "sg:phone":"+1 858 694 1616",
    "sg:postcode":"92123",
    "sg:province":"CA",
    "sg:tags":[
        "turbine",
        "mfg"
    ],
    "wof:name":"Solar Turbines Incorporated",
    "wof:placetype":"venue"
},
  "geometry": {"coordinates":[-117.126869,32.815341],"type":"Point"}
}