{
  "type": "Feature",
  "properties": {
    "addr:full":"452 Manor Plz Pacifica CA 94044",
    "addr:housenumber":"452",
    "addr:postcode":"94044",
    "addr:street":"Manor Plz",
    "iso:country":"US",
    "sg:address":"452 Manor Plz",
    "sg:city":"Pacifica",
    "sg:classifiers":[
        {
            "category":"Retail",
            "subcategory":"Laundry & Dry Cleaning",
            "type":"Services"
        }
    ],
    "sg:phone":"+1 650 359 2234",
    "sg:postcode":"94044",
    "sg:province":"CA",
    "sg:tags":[
        "cleaners"
    ],
    "wof:name":"Cleaning By Albert",
    "wof:placetype":"venue"
},
  "geometry": {"coordinates":[-122.491287,37.650147],"type":"Point"}
}