{
  "type": "Feature",
  "properties": {
    "addr:full":"6443 Canoga Ave Woodland Hills CA 91367",
    "addr:housenumber":"6443",
    "addr:postcode":"91367",
    "addr:street":"Canoga Ave",
    "iso:country":"US",
    "sg:address":"6443 Canoga Ave",
    "sg:city":"Woodland Hills",
    "sg:classifiers":[
        {
            "category":"Shopping",
            "subcategory":"Clothing, Apparel, & Fashions",
            "type":"Retail Goods"
        }
    ],
    "sg:phone":"+1 818 713 9208",
    "sg:postcode":"91367",
    "sg:province":"CA",
    "sg:tags":[
        "furnishing"
    ],
    "wof:name":"Casual Male Big & Tall",
    "wof:placetype":"venue"
},
  "geometry": {"coordinates":[-118.597452,34.185605],"type":"Point"}
}