{
  "type": "Feature",
  "properties": {
    "addr:full":"5719 Pioneer Blvd Whittier CA 90606",
    "addr:housenumber":"5719",
    "addr:postcode":"90606",
    "addr:street":"Pioneer Blvd",
    "iso:country":"US",
    "sg:address":"5719 Pioneer Blvd",
    "sg:city":"Whittier",
    "sg:classifiers":[
        {
            "category":"Retail",
            "subcategory":"Repair Shop",
            "type":"Services"
        }
    ],
    "sg:phone":"+1 562 695 9225",
    "sg:postcode":"90606",
    "sg:province":"CA",
    "sg:tags":[
        "welding"
    ],
    "wof:name":"Javier B Gonzalez",
    "wof:placetype":"venue"
},
  "geometry": {"coordinates":[-118.06674599999999,33.998478],"type":"Point"}
}