{
  "type": "Feature",
  "properties": {
    "iso:country":"US",
    "sg:address":"600 Aldean Pl",
    "sg:city":"Newport Beach",
    "sg:classifiers":[
        {
            "category":"Wholesale",
            "subcategory":"Construction Materials",
            "type":"Manufacturing & Wholesale Goods"
        }
    ],
    "sg:phone":"+1 714 549 5840",
    "sg:postcode":"92663",
    "sg:province":"CA",
    "sg:tags":[
        "lumber"
    ],
    "wof:name":"Treated Forest Products Inc",
    "wof:placetype":"venue"
},
  "geometry": {"coordinates":[-117.914914,33.624196],"type":"Point"}
}