{
  "type": "Feature",
  "properties": {
    "addr:full":"1325 Howe Ave Ste 111 Sacramento CA 95825",
    "addr:housenumber":"1325",
    "addr:postcode":"95825",
    "addr:street":"Howe Ave Ste 111",
    "iso:country":"US",
    "sg:address":"1325 Howe Ave Ste 111",
    "sg:city":"Sacramento",
    "sg:classifiers":[
        {
            "category":"Professional",
            "subcategory":"Lawyer & Legal Services",
            "type":"Services"
        }
    ],
    "sg:phone":"+1 916 925 1894",
    "sg:postcode":"95825",
    "sg:province":"CA",
    "sg:tags":[
        "attorney",
        "law",
        "personal",
        "medical",
        "immigration",
        "malpractice",
        "injury",
        "bankruptcy"
    ],
    "sg:website":"www.lawofficesofnonyeugorji.com/",
    "wof:name":"Law Offices Of Nonye Ugorji",
    "wof:placetype":"venue"
},
  "geometry": {"coordinates":[-121.415609,38.589552],"type":"Point"}
}