{
  "type": "Feature",
  "properties": {
    "iso:country":"US",
    "sg:address":"5460 Lorraine Ave",
    "sg:city":"Santa Maria",
    "sg:classifiers":[
        {
            "category":"Building & Trades",
            "subcategory":"Plumbing",
            "type":"Services"
        }
    ],
    "sg:phone":"+1 805 928 1414",
    "sg:postcode":"93455",
    "sg:province":"CA",
    "sg:tags":[
        "plumbing",
        "contractor"
    ],
    "wof:name":"Valley Septic",
    "wof:placetype":"venue"
},
  "geometry": {"coordinates":[-120.42628,34.859107],"type":"Point"}
}