{
  "type": "Feature",
  "properties": {
    "iso:country":"US",
    "sg:address":"1614 Kearney St",
    "sg:city":"El Cerrito",
    "sg:classifiers":[
        {
            "category":"Shopping",
            "subcategory":"Used Merchandise",
            "type":"Retail Goods"
        }
    ],
    "sg:phone":"+1 510 234 3214",
    "sg:postcode":"94530",
    "sg:province":"CA",
    "sg:tags":[
        "book",
        "rare",
        "dealer"
    ],
    "sg:website":"www.hackenbooks.com",
    "wof:name":"Hackenberg Booksellers",
    "wof:placetype":"venue"
},
  "geometry": {"coordinates":[-122.31468,37.921841],"type":"Point"}
}