{
  "type": "Feature",
  "properties": {
    "addr:full":"20627 Berendo Ave Torrance CA 90502",
    "addr:postcode":"20627;90502",
    "addr:street":"Berendo Ave",
    "iso:country":"US",
    "sg:address":"20627 Berendo Ave",
    "sg:city":"Torrance",
    "sg:classifiers":[
        {
            "category":"Professional",
            "type":"Services"
        }
    ],
    "sg:phone":"+1 310 324 3023",
    "sg:postcode":"90502",
    "sg:province":"CA",
    "wof:name":"Jesses Tents & Stuff",
    "wof:placetype":"venue"
},
  "geometry": {"coordinates":[-118.29280900000001,33.842718],"type":"Point"}
}