{
  "type": "Feature",
  "properties": {
    "iso:country":"US",
    "sg:address":"Los Feliz Village 1700 Hillhurst Ave",
    "sg:city":"Los Angeles",
    "sg:classifiers":[
        {
            "category":"Restaurant",
            "type":"Food & Drink"
        }
    ],
    "sg:phone":"+1 323 666 1166",
    "sg:postcode":"90027",
    "sg:province":"CA",
    "sg:website":"www.desertroserestaurant.com",
    "wof:name":"Desert Rose Restaurant",
    "wof:placetype":"venue"
},
  "geometry": {"coordinates":[-118.28704,34.10195],"type":"Point"}
}