{
  "type": "Feature",
  "properties": {
    "iso:country":"US",
    "sg:address":"2301 Armstrong St",
    "sg:city":"Livermore",
    "sg:classifiers":[
        {
            "category":"Manufacturing",
            "subcategory":"Electronics",
            "type":"Manufacturing & Wholesale Goods"
        }
    ],
    "sg:phone":"+1 925 245 7600",
    "sg:postcode":"94551",
    "sg:province":"CA",
    "sg:tags":[
        "equipment",
        "fiber",
        "network",
        "optic"
    ],
    "wof:name":"Alloptic Inc",
    "wof:placetype":"venue"
},
  "geometry": {"coordinates":[-121.812033,37.699025],"type":"Point"}
}