{
  "type": "Feature",
  "properties": {
    "iso:country":"US",
    "sg:address":"3888 Bluebird Canyon Rd",
    "sg:city":"Vista",
    "sg:classifiers":[
        {
            "category":"Professional",
            "type":"Services"
        }
    ],
    "sg:phone":"+1 760 727 7500",
    "sg:postcode":"92084",
    "sg:province":"CA",
    "wof:name":"Timothy James Kataras",
    "wof:placetype":"venue"
},
  "geometry": {"coordinates":[-117.17900400000001,33.178174],"type":"Point"}
}