{
  "type": "Feature",
  "properties": {
    "addr:full":"1808 Art St Bakersfield CA 93312",
    "addr:housenumber":"1808",
    "addr:postcode":"93312",
    "addr:street":"Art St",
    "iso:country":"US",
    "sg:address":"1808 Art St",
    "sg:city":"Bakersfield",
    "sg:classifiers":[
        {
            "category":"Autos & Motor Vehicles",
            "subcategory":"Auto Supplies",
            "type":"Retail Goods"
        },
        {
            "category":"Retail",
            "subcategory":"Auto Repair",
            "type":"Services"
        }
    ],
    "sg:phone":"+1 661 342 1926",
    "sg:postcode":"93312",
    "sg:province":"CA",
    "sg:tags":[
        "transmission"
    ],
    "wof:name":"Rony Recinos Transmission",
    "wof:placetype":"venue"
},
  "geometry": {"coordinates":[-119.10772900000001,35.374977],"type":"Point"}
}