{
  "type": "Feature",
  "properties": {
    "iso:country":"US",
    "sg:address":"5226 Arlington Ave",
    "sg:city":"Riverside",
    "sg:classifiers":[
        {
            "category":"Food & Beverages",
            "subcategory":"Specialty",
            "type":"Retail Goods"
        }
    ],
    "sg:phone":"+1 951 637 1112",
    "sg:postcode":"92504",
    "sg:province":"CA",
    "sg:tags":[
        "vitamin"
    ],
    "wof:name":"General Nutrition Ctr",
    "wof:placetype":"venue"
},
  "geometry": {"coordinates":[-117.416419,33.946001],"type":"Point"}
}