{
  "type": "Feature",
  "properties": {
    "iso:country":"US",
    "sg:address":"3021 E 17th St",
    "sg:city":"Oakland",
    "sg:classifiers":[
        {
            "category":"Real Estate",
            "subcategory":"Real Estate Services",
            "type":"Services"
        },
        {
            "category":"Building & Trades",
            "subcategory":"Cleaning & Sanitation",
            "type":"Services"
        }
    ],
    "sg:phone":"+1 510 261 0473",
    "sg:postcode":"94601",
    "sg:province":"CA",
    "sg:tags":[
        "maintenance",
        "cleaners-interior"
    ],
    "wof:name":"Romi General Maintenance",
    "wof:placetype":"venue"
},
  "geometry": {"coordinates":[-122.224902,37.781387],"type":"Point"}
}