{
  "type": "Feature",
  "properties": {
    "iso:country":"US",
    "sg:address":"3815 Atlantic Ave",
    "sg:city":"Long Beach",
    "sg:classifiers":[
        {
            "category":"Health Services",
            "subcategory":"Health Practitioner",
            "type":"Services"
        }
    ],
    "sg:phone":"+1 562 595 4770",
    "sg:postcode":"90807",
    "sg:province":"CA",
    "sg:tags":[
        "psychologist"
    ],
    "wof:name":"Rochelle Fried",
    "wof:placetype":"venue"
},
  "geometry": {"coordinates":[-118.185083,33.827041],"type":"Point"}
}