{
  "type": "Feature",
  "properties": {
    "iso:country":"US",
    "sg:address":"68828 Ramon Rd",
    "sg:city":"Cathedral City",
    "sg:classifiers":[
        {
            "category":"Organizations",
            "subcategory":"Religious Organization",
            "type":"Services"
        }
    ],
    "sg:phone":"+1 760 318 4388",
    "sg:postcode":"92234",
    "sg:province":"CA",
    "wof:name":"Church Resource Ministries",
    "wof:placetype":"venue"
},
  "geometry": {"coordinates":[-116.461037,33.816028],"type":"Point"}
}