{
  "type": "Feature",
  "properties": {
    "iso:country":"US",
    "sg:address":"809 N Cahuenga Blvd",
    "sg:city":"Los Angeles",
    "sg:classifiers":[
        {
            "category":"Communications",
            "subcategory":"Film & Video Production",
            "type":"Services"
        }
    ],
    "sg:phone":"+1 323 462 6266",
    "sg:postcode":"90038",
    "sg:province":"CA",
    "sg:tags":[
        "post",
        "tape"
    ],
    "wof:name":"Pacific Video Inc",
    "wof:placetype":"venue"
},
  "geometry": {"coordinates":[-118.328867,34.086961],"type":"Point"}
}