{
  "type": "Feature",
  "properties": {
    "iso:country":"US",
    "sg:address":"1617 Firvale Ave",
    "sg:city":"Montebello",
    "sg:classifiers":[
        {
            "category":"Professional",
            "type":"Services"
        }
    ],
    "sg:phone":"+1 323 724 5053",
    "sg:postcode":"90640",
    "sg:province":"CA",
    "wof:name":"Future of Tomorrow Founda",
    "wof:placetype":"venue"
},
  "geometry": {"coordinates":[-118.092044,34.039568],"type":"Point"}
}