{
  "type": "Feature",
  "properties": {
    "addr:full":"7501 Hospital Dr Ste 206 Sacramento CA 95823",
    "addr:housenumber":"7501",
    "addr:postcode":"95823",
    "addr:street":"Hospital Dr Ste 206",
    "iso:country":"US",
    "sg:address":"7501 Hospital Dr Ste 206",
    "sg:city":"Sacramento",
    "sg:classifiers":[
        {
            "category":"Health Services",
            "subcategory":"Doctor",
            "type":"Services"
        }
    ],
    "sg:phone":"+1 916 681 8091",
    "sg:postcode":"95823",
    "sg:province":"CA",
    "sg:tags":[
        "physician",
        "pediatrics-emergency",
        "pediatrics",
        "surgeons",
        "medicine",
        "surgeon"
    ],
    "wof:name":"An-Shyang Tsai Md",
    "wof:placetype":"venue"
},
  "geometry": {"coordinates":[-121.417511,38.46423],"type":"Point"}
}