{
  "type": "Feature",
  "properties": {
    "addr:full":"5001 Carriage Ln Santa Rosa CA 95403",
    "addr:housenumber":"5001",
    "addr:postcode":"95403",
    "addr:street":"Carriage Ln",
    "iso:country":"US",
    "sg:address":"5001 Carriage Ln",
    "sg:city":"Santa Rosa",
    "sg:classifiers":[
        {
            "category":"Sports & Exercise",
            "subcategory":"Golf",
            "type":"Entertainment"
        }
    ],
    "sg:phone":"+1 707 546 8787",
    "sg:postcode":"95403",
    "sg:province":"CA",
    "sg:tags":[
        "course"
    ],
    "wof:name":"Wikiup Golf Course",
    "wof:placetype":"venue"
},
  "geometry": {"coordinates":[-122.745434,38.504969],"type":"Point"}
}