{
  "type": "Feature",
  "properties": {
    "addr:full":"180 Nadina Way Greenbrae CA 94904",
    "addr:housenumber":"180",
    "addr:postcode":"94904",
    "addr:street":"Nadina Way",
    "iso:country":"US",
    "sg:address":"180 Nadina Way",
    "sg:city":"Greenbrae",
    "sg:classifiers":[
        {
            "category":"Manufacturing",
            "subcategory":"Apparel",
            "type":"Manufacturing & Wholesale Goods"
        },
        {
            "category":"Home & Garden",
            "subcategory":"Home Furnishings",
            "type":"Retail Goods"
        }
    ],
    "sg:phone":"+1 415 461 7454",
    "sg:postcode":"94904",
    "sg:province":"CA",
    "sg:tags":[
        "textile",
        "mfg",
        "accessory",
        "sales",
        "kitchen"
    ],
    "sg:website":"www.kentfields.com",
    "wof:name":"Kentfield's",
    "wof:placetype":"venue"
},
  "geometry": {"coordinates":[-122.53033499999999,37.950384],"type":"Point"}
}