{
  "type": "Feature",
  "properties": {
    "addr:full":"400 Upper Ter San Francisco CA 94117",
    "addr:housenumber":"400",
    "addr:postcode":"94117",
    "addr:street":"Upper Ter",
    "iso:country":"US",
    "sg:address":"400 Upper Ter",
    "sg:city":"San Francisco",
    "sg:classifiers":[
        {
            "category":"Food & Beverages",
            "subcategory":"Bakery",
            "type":"Retail Goods"
        }
    ],
    "sg:phone":"+1 650 871 2515",
    "sg:postcode":"94117",
    "sg:province":"CA",
    "sg:tags":[
        "baker"
    ],
    "wof:name":"Boudin Sourdough Bakery & Cafe",
    "wof:placetype":"venue"
},
  "geometry": {"coordinates":[-122.445025,37.763269],"type":"Point"}
}