{
  "type": "Feature",
  "properties": {
    "iso:country":"US",
    "sg:address":"11612 Knott St",
    "sg:city":"Garden Grove",
    "sg:classifiers":[
        {
            "category":"Professional",
            "subcategory":"Detective & Security Services",
            "type":"Services"
        }
    ],
    "sg:phone":"+1 714 952 2777",
    "sg:postcode":"92841",
    "sg:province":"CA",
    "sg:tags":[
        "guard",
        "patrol"
    ],
    "sg:website":"www.americanshield.com",
    "wof:name":"American Shield Private Sec",
    "wof:placetype":"venue"
},
  "geometry": {"coordinates":[-118.011002,33.793198],"type":"Point"}
}