{
  "type": "Feature",
  "properties": {
    "addr:full":"2836 W Rialto Ave Rialto CA 92376",
    "addr:housenumber":"2836",
    "addr:postcode":"92376",
    "addr:street":"W Rialto Ave",
    "iso:country":"US",
    "sg:address":"2836 W Rialto Ave",
    "sg:city":"Rialto",
    "sg:classifiers":[
        {
            "category":"Health Services",
            "subcategory":"Doctor",
            "type":"Services"
        }
    ],
    "sg:phone":"+1 909 820 9454",
    "sg:postcode":"92376",
    "sg:province":"CA",
    "sg:tags":[
        "dentist"
    ],
    "wof:name":"Dr KWON Dental",
    "wof:placetype":"venue"
},
  "geometry": {"coordinates":[-117.35006300000001,34.099633],"type":"Point"}
}