{
  "type": "Feature",
  "properties": {
    "iso:country":"US",
    "sg:address":"1125 Riley St",
    "sg:city":"Folsom",
    "sg:classifiers":[
        {
            "category":"Food & Beverages",
            "subcategory":"Bakery",
            "type":"Retail Goods"
        }
    ],
    "sg:phone":"+1 916 983 6444",
    "sg:postcode":"95630",
    "sg:province":"CA",
    "sg:tags":[
        "bagel"
    ],
    "wof:name":"Main Street Bagel Cafe",
    "wof:placetype":"venue"
},
  "geometry": {"coordinates":[-121.172241,38.673585],"type":"Point"}
}