{
  "type": "Feature",
  "properties": {
    "iso:country":"US",
    "sg:address":"20 High School Ct",
    "sg:city":"Los Gatos",
    "sg:classifiers":[
        {
            "category":"Arena",
            "subcategory":"Sports Club",
            "type":"Entertainment"
        }
    ],
    "sg:postcode":"95030",
    "sg:province":"CA",
    "sg:tags":[
        "martial art"
    ],
    "sg:website":"www.americancupbjj.com/Home_Page...",
    "wof:name":"3rd American Cup Brazilian Jiu-Jitsu Tournament",
    "wof:placetype":"venue"
},
  "geometry": {"coordinates":[-121.97590099999999,37.221478],"type":"Point"}
}