{
  "type": "Feature",
  "properties": {
    "addr:full":"5272 E 2nd St Long Beach CA 90803",
    "addr:housenumber":"5272",
    "addr:postcode":"90803",
    "addr:street":"E 2Nd St",
    "iso:country":"US",
    "sg:address":"5272 E 2nd St",
    "sg:city":"Long Beach",
    "sg:classifiers":[
        {
            "category":"Food & Beverages",
            "subcategory":"Bakery",
            "type":"Retail Goods"
        }
    ],
    "sg:phone":"+1 562 439 7262",
    "sg:postcode":"90803",
    "sg:province":"CA",
    "sg:tags":[
        "product",
        "mfg"
    ],
    "wof:name":"Le Donuts & Croissants",
    "wof:placetype":"venue"
},
  "geometry": {"coordinates":[-118.13389599999999,33.759855],"type":"Point"}
}