{
  "type": "Feature",
  "properties": {
    "addr:full":"1824 Noriega St Ste 6 San Francisco CA 94122",
    "addr:housenumber":"1824",
    "addr:postcode":"94122",
    "addr:street":"Noriega St Ste 6",
    "iso:country":"US",
    "sg:address":"1824 Noriega St Ste 6",
    "sg:city":"San Francisco",
    "sg:classifiers":[
        {
            "category":"Personal",
            "subcategory":"Skin Care",
            "type":"Services"
        },
        {
            "category":"Personal",
            "subcategory":"Day Spa",
            "type":"Services"
        }
    ],
    "sg:phone":"+1 415 682 3838",
    "sg:postcode":"94122",
    "sg:province":"CA",
    "wof:name":"MG Beauty Care",
    "wof:placetype":"venue"
},
  "geometry": {"coordinates":[-122.48343800000001,37.753952],"type":"Point"}
}