{
  "type": "Feature",
  "properties": {
    "iso:country":"US",
    "sg:address":"4116 Crenshaw Blvd",
    "sg:city":"Los Angeles",
    "sg:classifiers":[
        {
            "category":"Home & Garden",
            "subcategory":"Home Furnishings",
            "type":"Retail Goods"
        }
    ],
    "sg:phone":"+1 323 291 5665",
    "sg:postcode":"90008",
    "sg:province":"CA",
    "sg:tags":[
        "venetian",
        "blind"
    ],
    "wof:name":"Moss Drapery Center",
    "wof:placetype":"venue"
},
  "geometry": {"coordinates":[-118.33502,34.009562],"type":"Point"}
}