{
  "type": "Feature",
  "properties": {
    "iso:country":"US",
    "sg:address":"1240 Manor Blvd",
    "sg:city":"San Leandro",
    "sg:classifiers":[
        {
            "category":"Food & Beverages",
            "subcategory":"Groceries & Convenience Stores",
            "type":"Retail Goods"
        }
    ],
    "sg:phone":"+1 510 352 2324",
    "sg:postcode":"94579",
    "sg:province":"CA",
    "sg:website":"www.7-eleven.com",
    "wof:name":"7-Eleven",
    "wof:placetype":"venue"
},
  "geometry": {"coordinates":[-122.15300000000001,37.691399],"type":"Point"}
}