{
  "type": "Feature",
  "properties": {
    "addr:full":"2601 Hoover Ave National City CA 91950",
    "addr:housenumber":"2601",
    "addr:postcode":"91950",
    "addr:street":"Hoover Ave",
    "iso:country":"US",
    "sg:address":"2601 Hoover Ave",
    "sg:city":"National City",
    "sg:classifiers":[
        {
            "category":"Recreation",
            "subcategory":"Marina",
            "type":"Entertainment"
        }
    ],
    "sg:phone":"+1 619 336 1646",
    "sg:postcode":"91950",
    "sg:province":"CA",
    "sg:tags":[
        "repairing",
        "boat"
    ],
    "wof:name":"Evolution Engineering",
    "wof:placetype":"venue"
},
  "geometry": {"coordinates":[-117.103767,32.658904],"type":"Point"}
}