{
  "type": "Feature",
  "properties": {
    "addr:full":"18500 Mountain Meadows Dr Victorville CA 92392",
    "addr:housenumber":"18500",
    "addr:postcode":"92392",
    "addr:street":"Mountain Meadows Dr",
    "iso:country":"US",
    "sg:address":"18500 Mountain Meadows Dr",
    "sg:city":"Victorville",
    "sg:classifiers":[
        {
            "category":"Wholesale",
            "subcategory":"Machinery & Supplies",
            "type":"Manufacturing & Wholesale Goods"
        }
    ],
    "sg:phone":"+1 760 243 4144",
    "sg:postcode":"92392",
    "sg:province":"CA",
    "sg:tags":[
        "equipment",
        "printing"
    ],
    "wof:name":"M & R Sales & Svc Inc",
    "wof:placetype":"venue"
},
  "geometry": {"coordinates":[-117.25907100000001,34.481843],"type":"Point"}
}