{
  "type": "Feature",
  "properties": {
    "addr:full":"21534 Devonshire St Ste A Chatsworth CA 91311",
    "addr:housenumber":"21534",
    "addr:postcode":"91311",
    "addr:street":"Devonshire St Ste A",
    "iso:country":"US",
    "sg:address":"21534 Devonshire St Ste A",
    "sg:city":"Chatsworth",
    "sg:classifiers":[
        {
            "category":"Fast Food",
            "type":"Food & Drink"
        },
        {
            "category":"Deli",
            "type":"Food & Drink"
        },
        {
            "category":"Restaurant",
            "type":"Food & Drink"
        },
        {
            "category":"Food & Beverages",
            "subcategory":"Groceries & Convenience Stores",
            "type":"Retail Goods"
        }
    ],
    "sg:phone":"+1 818 734 7827",
    "sg:postcode":"91311",
    "sg:province":"CA",
    "sg:tags":[
        "shop",
        "delicatessen",
        "sandwich",
        "take"
    ],
    "sg:website":"http://www.quiznos.com",
    "wof:name":"Quiznos Sub Chatsworth",
    "wof:placetype":"venue"
},
  "geometry": {"coordinates":[-118.59898699999999,34.25724],"type":"Point"}
}