{
  "type": "Feature",
  "properties": {
    "addr:full":"14319 River Rd Walnut Grove CA 95690",
    "addr:housenumber":"14319",
    "addr:postcode":"95690",
    "addr:street":"River Rd",
    "iso:country":"US",
    "sg:address":"14319 River Rd",
    "sg:city":"Walnut Grove",
    "sg:classifiers":[
        {
            "category":"Banks & Credit Unions",
            "subcategory":"Investment Brokerage",
            "type":"Services"
        }
    ],
    "sg:phone":"+1 916 776 2022",
    "sg:postcode":"95690",
    "sg:province":"CA",
    "wof:name":"O'Connor Investments",
    "wof:placetype":"venue"
},
  "geometry": {"coordinates":[-121.51670900000001,38.237387],"type":"Point"}
}