{
  "type": "Feature",
  "properties": {
    "iso:country":"US",
    "sg:address":"3100 Hansen Way",
    "sg:city":"Palo Alto",
    "sg:classifiers":[
        {
            "category":"Manufacturing",
            "subcategory":"Tools & Machinery",
            "type":"Manufacturing & Wholesale Goods"
        }
    ],
    "sg:phone":"+1 650 493 4000",
    "sg:postcode":"94304",
    "sg:province":"CA",
    "sg:tags":[
        "linear",
        "accelerator",
        "mfg",
        "medical",
        "x",
        "tube",
        "apparatus"
    ],
    "sg:website":"www.varian.com",
    "wof:name":"Varian Medical Systems Inc",
    "wof:placetype":"venue"
},
  "geometry": {"coordinates":[-122.141916,37.417294],"type":"Point"}
}