{
  "type": "Feature",
  "properties": {
    "iso:country":"US",
    "sg:address":"1500 E Lincoln Ave",
    "sg:city":"Orange",
    "sg:classifiers":[
        {
            "category":"Restaurant",
            "type":"Food & Drink"
        }
    ],
    "sg:phone":"+1 714 998 5100",
    "sg:postcode":"92865",
    "sg:province":"CA",
    "sg:tags":[
        "pizza"
    ],
    "sg:website":"www.whatalottapizza.com",
    "wof:name":"Whata Lotta Pizza",
    "wof:placetype":"venue"
},
  "geometry": {"coordinates":[-117.83809100000001,33.834953],"type":"Point"}
}