{
  "type": "Feature",
  "properties": {
    "addr:full":"4111 18th St San Francisco CA 94114",
    "addr:housenumber":"4111",
    "addr:postcode":"94114",
    "addr:street":"18Th St",
    "iso:country":"US",
    "sg:address":"4111 18th St",
    "sg:city":"San Francisco",
    "sg:classifiers":[
        {
            "category":"Professional",
            "subcategory":"Management & Consulting",
            "type":"Services"
        }
    ],
    "sg:phone":"+1 415 255 9200",
    "sg:postcode":"94114",
    "sg:province":"CA",
    "sg:tags":[
        "consultant",
        "business"
    ],
    "sg:website":"www.glinsky.com",
    "wof:name":"Glinsky Group",
    "wof:placetype":"venue"
},
  "geometry": {"coordinates":[-122.436019,37.760756],"type":"Point"}
}