{
  "type": "Feature",
  "properties": {
    "iso:country":"US",
    "sg:address":"1055 W San Ysidro Boulevard",
    "sg:city":"San Ysidro",
    "sg:classifiers":[
        {
            "category":"Real Estate",
            "subcategory":"Real Estate Operator",
            "type":"Services"
        }
    ],
    "sg:phone":"+1 619 428 1376",
    "sg:postcode":"92173",
    "sg:province":"CA",
    "sg:tags":[
        "apartment"
    ],
    "wof:name":"P V A Ltd",
    "wof:placetype":"venue"
},
  "geometry": {"coordinates":[-117.064322,32.561026],"type":"Point"}
}