{
  "type": "Feature",
  "properties": {
    "addr:full":"1175 Willow Ave Sunnyvale CA 94086",
    "addr:housenumber":"1175",
    "addr:postcode":"94086",
    "addr:street":"Willow Ave",
    "iso:country":"US",
    "sg:address":"1175 Willow Ave",
    "sg:city":"Sunnyvale",
    "sg:classifiers":[
        {
            "category":"Real Estate",
            "subcategory":"Architect",
            "type":"Services"
        }
    ],
    "sg:phone":"+1 408 241 0551",
    "sg:postcode":"94086",
    "sg:province":"CA",
    "wof:name":"Trispec Architectural Hardware",
    "wof:placetype":"venue"
},
  "geometry": {"coordinates":[-121.99811,37.36796],"type":"Point"}
}