{
  "type": "Feature",
  "properties": {
    "addr:full":"9801 Airport Boulevard Inglewood CA 90301",
    "addr:housenumber":"9801",
    "addr:postcode":"90301",
    "addr:street":"Airport Boulevard",
    "iso:country":"US",
    "sg:address":"9801 Airport Boulevard",
    "sg:city":"Inglewood",
    "sg:classifiers":[
        {
            "category":"Travel",
            "subcategory":"Hotels & Motels",
            "type":"Entertainment"
        }
    ],
    "sg:phone":"+1 310 215 1000",
    "sg:postcode":"90301",
    "sg:province":"CA",
    "wof:name":"Embassy Suites Hotel",
    "wof:placetype":"venue"
},
  "geometry": {"coordinates":[-118.354029,33.957167],"type":"Point"}
}