{
  "type": "Feature",
  "properties": {
    "iso:country":"US",
    "sg:address":"2810 N Van Ness Blvd",
    "sg:city":"Fresno",
    "sg:classifiers":[
        {
            "category":"Shopping Center",
            "type":"Public Place"
        }
    ],
    "sg:phone":"+1 559 226 7788",
    "sg:postcode":"93704",
    "sg:province":"CA",
    "sg:tags":[
        "mall"
    ],
    "wof:name":"Vineyard Erganian",
    "wof:placetype":"venue"
},
  "geometry": {"coordinates":[-119.80403099999999,36.775885],"type":"Point"}
}