{
  "type": "Feature",
  "properties": {
    "addr:full":"9985 Old Redwood Hwy Penngrove CA 94951",
    "addr:housenumber":"9985",
    "addr:postcode":"94951",
    "addr:street":"Old Redwood Hwy",
    "iso:country":"US",
    "sg:address":"9985 Old Redwood Hwy",
    "sg:city":"Penngrove",
    "sg:classifiers":[
        {
            "category":"Building & Trades",
            "subcategory":"Construction",
            "type":"Services"
        }
    ],
    "sg:phone":"+1 707 795 4448",
    "sg:postcode":"94951",
    "sg:province":"CA",
    "sg:tags":[
        "house"
    ],
    "wof:name":"Swain Builders",
    "wof:placetype":"venue"
},
  "geometry": {"coordinates":[-122.684067,38.305047],"type":"Point"}
}