{
  "type": "Feature",
  "properties": {
    "iso:country":"US",
    "sg:address":"2355 Whitman Rd",
    "sg:city":"Concord",
    "sg:classifiers":[
        {
            "category":"Manufacturing",
            "subcategory":"Glass & Minerals",
            "type":"Manufacturing & Wholesale Goods"
        }
    ],
    "sg:phone":"+1 925 676 8222",
    "sg:postcode":"94518",
    "sg:province":"CA",
    "sg:tags":[
        "tile"
    ],
    "wof:name":"Dal-Tile",
    "wof:placetype":"venue"
},
  "geometry": {"coordinates":[-122.030039,37.952168],"type":"Point"}
}