{
  "type": "Feature",
  "properties": {
    "iso:country":"US",
    "sg:address":"24201 Valencia Blvd",
    "sg:city":"Valencia",
    "sg:classifiers":[
        {
            "category":"Shopping",
            "subcategory":"Clothing, Apparel, & Fashions",
            "type":"Retail Goods"
        }
    ],
    "sg:phone":"+1 661 288 1067",
    "sg:postcode":"91355",
    "sg:province":"CA",
    "sg:tags":[
        "infant",
        "wear"
    ],
    "sg:website":"www.gymboree.com",
    "wof:name":"Gymboree",
    "wof:placetype":"venue"
},
  "geometry": {"coordinates":[-118.556816,34.413124],"type":"Point"}
}