{
  "type": "Feature",
  "properties": {
    "addr:full":"Junipero Ave & 5th Ave Carmel CA 93921",
    "addr:postcode":"93921",
    "addr:street":"Junipero Ave & 5Th Ave",
    "iso:country":"US",
    "sg:address":"Junipero Ave & 5th Ave",
    "sg:city":"Carmel",
    "sg:classifiers":[
        {
            "category":"Restaurant",
            "type":"Food & Drink"
        }
    ],
    "sg:phone":"+1 831 624 8643",
    "sg:postcode":"93921",
    "sg:province":"CA",
    "sg:tags":[
        "french"
    ],
    "wof:name":"French Poodle Restaurant Francais",
    "wof:placetype":"venue"
},
  "geometry": {"coordinates":[-121.920095,36.556882],"type":"Point"}
}