{
  "type": "Feature",
  "properties": {
    "iso:country":"US",
    "sg:address":"10427 Burbank Blvd",
    "sg:city":"North Hollywood",
    "sg:classifiers":[
        {
            "category":"Health Services",
            "subcategory":"Health Practitioner",
            "type":"Services"
        }
    ],
    "sg:phone":"+1 818 509 9028",
    "sg:postcode":"91601",
    "sg:province":"CA",
    "sg:tags":[
        "acupuncture"
    ],
    "wof:name":"Harmony Acupuncture",
    "wof:placetype":"venue"
},
  "geometry": {"coordinates":[-118.35847800000001,34.172297],"type":"Point"}
}