{
  "type": "Feature",
  "properties": {
    "iso:country":"US",
    "sg:address":"14475 Ventura Blvd",
    "sg:city":"Sherman Oaks",
    "sg:classifiers":[
        {
            "category":"Banks & Credit Unions",
            "subcategory":"Bank",
            "type":"Services"
        }
    ],
    "sg:phone":"+1 818 000 1111",
    "sg:postcode":"91423",
    "sg:province":"CA",
    "wof:name":"California National Bank",
    "wof:placetype":"venue"
},
  "geometry": {"coordinates":[-118.448438,34.150941],"type":"Point"}
}