{
  "type": "Feature",
  "properties": {
    "iso:country":"US",
    "sg:address":"1111 Talbot Ave",
    "sg:city":"Albany",
    "sg:classifiers":[
        {
            "category":"Professional",
            "subcategory":"Art Services",
            "type":"Services"
        }
    ],
    "sg:phone":"+1 510 526 0737",
    "sg:postcode":"94706",
    "sg:province":"CA",
    "sg:tags":[
        "graphic",
        "designer"
    ],
    "wof:name":"Ellen Toomey Graphic Design",
    "wof:placetype":"venue"
},
  "geometry": {"coordinates":[-122.293454,37.884502],"type":"Point"}
}