{
  "type": "Feature",
  "properties": {
    "addr:full":"2701 Corabel Ln Sacramento CA 95821",
    "addr:housenumber":"2701",
    "addr:postcode":"95821",
    "addr:street":"Corabel Ln",
    "iso:country":"US",
    "sg:address":"2701 Corabel Ln",
    "sg:city":"Sacramento",
    "sg:classifiers":[
        {
            "category":"Building & Trades",
            "subcategory":"Construction",
            "type":"Services"
        }
    ],
    "sg:phone":"+1 916 488 6836",
    "sg:postcode":"95821",
    "sg:province":"CA",
    "sg:tags":[
        "concrete",
        "contractor"
    ],
    "wof:name":"A B Concrete",
    "wof:placetype":"venue"
},
  "geometry": {"coordinates":[-121.396784,38.617968],"type":"Point"}
}