{
  "type": "Feature",
  "properties": {
    "iso:country":"US",
    "sg:address":"1539 Beverly Blvd",
    "sg:city":"Los Angeles",
    "sg:classifiers":[
        {
            "category":"Professional",
            "subcategory":"Lawyer & Legal Services",
            "type":"Services"
        }
    ],
    "sg:phone":"+1 213 977 0453",
    "sg:postcode":"90026",
    "sg:province":"CA",
    "wof:name":"Matinog Alfonso C Attorney At Law",
    "wof:placetype":"venue"
},
  "geometry": {"coordinates":[-118.263,34.063099],"type":"Point"}
}