{
  "type": "Feature",
  "properties": {
    "addr:full":"4310 Genesee Avenue Suite 106 San Diego CA 92117",
    "addr:housenumber":"4310",
    "addr:postcode":"92117",
    "addr:street":"Genesee Avenue Suite 106",
    "iso:country":"US",
    "sg:address":"4310 Genesee Avenue Suite 106",
    "sg:city":"San Diego",
    "sg:classifiers":[
        {
            "category":"Restaurant",
            "type":"Food & Drink"
        }
    ],
    "sg:phone":"+1 858 467 0775",
    "sg:postcode":"92117",
    "sg:province":"CA",
    "sg:tags":[
        "mexican"
    ],
    "wof:name":"Don Mario's Mexican Food",
    "wof:placetype":"venue"
},
  "geometry": {"coordinates":[-117.183037,32.821416],"type":"Point"}
}