{
  "type": "Feature",
  "properties": {
    "addr:full":"1748 Broadway Dr Salinas CA 93906",
    "addr:housenumber":"1748",
    "addr:postcode":"93906",
    "addr:street":"Broadway Dr",
    "iso:country":"US",
    "sg:address":"1748 Broadway Dr",
    "sg:city":"Salinas",
    "sg:classifiers":[
        {
            "category":"Manufacturing",
            "subcategory":"Tools & Machinery",
            "type":"Manufacturing & Wholesale Goods"
        }
    ],
    "sg:phone":"+1 831 443 2147",
    "sg:postcode":"93906",
    "sg:province":"CA",
    "sg:tags":[
        "mfg"
    ],
    "wof:name":"Mold Consultant Mold Abatement",
    "wof:placetype":"venue"
},
  "geometry": {"coordinates":[-121.64725799999999,36.713795],"type":"Point"}
}