{
  "type": "Feature",
  "properties": {
    "iso:country":"US",
    "sg:address":"614 N Bush St",
    "sg:city":"Santa Ana",
    "sg:classifiers":[
        {
            "category":"Education",
            "subcategory":"Special Training",
            "type":"Public Place"
        }
    ],
    "sg:phone":"+1 714 543 1715",
    "sg:postcode":"92701",
    "sg:province":"CA",
    "sg:tags":[
        "tutoring"
    ],
    "wof:name":"Noah Project",
    "wof:placetype":"venue"
},
  "geometry": {"coordinates":[-117.866666,33.750495],"type":"Point"}
}