{
  "type": "Feature",
  "properties": {
    "iso:country":"US",
    "sg:address":"909 W 16th St",
    "sg:city":"Newport Beach",
    "sg:classifiers":[
        {
            "category":"Retail",
            "subcategory":"Auto Repair",
            "type":"Services"
        }
    ],
    "sg:phone":"+1 949 642 1075",
    "sg:postcode":"92663",
    "sg:province":"CA",
    "sg:tags":[
        "exchanging",
        "engine"
    ],
    "wof:name":"Brown's Engineering Inc",
    "wof:placetype":"venue"
},
  "geometry": {"coordinates":[-117.938975,33.63235],"type":"Point"}
}