{
  "type": "Feature",
  "properties": {
    "addr:full":"110 North St Taft CA 93268",
    "addr:housenumber":"110",
    "addr:postcode":"93268",
    "addr:street":"North St",
    "iso:country":"US",
    "sg:address":"110 North St",
    "sg:city":"Taft",
    "sg:classifiers":[
        {
            "category":"Professional",
            "type":"Services"
        }
    ],
    "sg:phone":"+1 661 638 0214",
    "sg:postcode":"93268",
    "sg:province":"CA",
    "sg:tags":[
        "establishment"
    ],
    "wof:name":"Chw Bakersfield Memorial",
    "wof:placetype":"venue"
},
  "geometry": {"coordinates":[-119.45403399999999,35.14039],"type":"Point"}
}