{
  "type": "Feature",
  "properties": {
    "iso:country":"US",
    "sg:address":"5865 Rolling Rd",
    "sg:city":"Woodland Hills",
    "sg:classifiers":[
        {
            "category":"Building & Trades",
            "subcategory":"Construction",
            "type":"Services"
        }
    ],
    "sg:phone":"+1 818 340 9379",
    "sg:postcode":"91367",
    "sg:province":"CA",
    "sg:tags":[
        "wallpaper"
    ],
    "wof:name":"Wallpapering-European Experts",
    "wof:placetype":"venue"
},
  "geometry": {"coordinates":[-118.60597,34.178205],"type":"Point"}
}