{
  "type": "Feature",
  "properties": {
    "iso:country":"US",
    "sg:address":"250 E Webb St",
    "sg:city":"Montague",
    "sg:classifiers":[
        {
            "category":"Food & Beverages",
            "subcategory":"Groceries & Convenience Stores",
            "type":"Retail Goods"
        }
    ],
    "sg:phone":"+1 530 459 3414",
    "sg:postcode":"96064",
    "sg:province":"CA",
    "sg:tags":[
        "grocer"
    ],
    "wof:name":"Cortright Market & Deli",
    "wof:placetype":"venue"
},
  "geometry": {"coordinates":[-122.525029,41.727225],"type":"Point"}
}