{
  "type": "Feature",
  "properties": {
    "addr:full":"9700 Woodman Ave Suite A19 Arleta CA 91331",
    "addr:housenumber":"9700",
    "addr:postcode":"91331",
    "addr:street":"Woodman Ave Suite A19",
    "iso:country":"US",
    "sg:address":"9700 Woodman Ave Suite A19",
    "sg:city":"Arleta",
    "sg:classifiers":[
        {
            "category":"Banks & Credit Unions",
            "subcategory":"Financial Services",
            "type":"Services"
        }
    ],
    "sg:phone":"+1 818 834 4434",
    "sg:postcode":"91331",
    "sg:province":"CA",
    "sg:tags":[
        "financing",
        "cashing",
        "money",
        "loan",
        "check",
        "payday",
        "order"
    ],
    "sg:website":"http://ad.doubleclick.net/clk;225053199;48888911;w?http://www.checkngo.com?source=yellowpages&cat=TLs&AfsCampaignId=642",
    "wof:name":"Check 'n Go",
    "wof:placetype":"venue"
},
  "geometry": {"coordinates":[-118.44758899999999,34.246178],"type":"Point"}
}