{
  "type": "Feature",
  "properties": {
    "iso:country":"US",
    "sg:address":"3333 Standish Ave",
    "sg:city":"Santa Rosa",
    "sg:classifiers":[
        {
            "category":"Building & Trades",
            "subcategory":"Construction",
            "type":"Services"
        }
    ],
    "sg:phone":"+1 707 585 9013",
    "sg:postcode":"95407",
    "sg:province":"CA",
    "sg:tags":[
        "maker",
        "cabinet"
    ],
    "wof:name":"Creative Cabinets Inc",
    "wof:placetype":"venue"
},
  "geometry": {"coordinates":[-122.723194,38.394043],"type":"Point"}
}