{
  "type": "Feature",
  "properties": {
    "addr:full":"56 Acacia Dr Orinda CA 94563",
    "addr:housenumber":"56",
    "addr:postcode":"94563",
    "addr:street":"Acacia Dr",
    "iso:country":"US",
    "sg:address":"56 Acacia Dr",
    "sg:city":"Orinda",
    "sg:classifiers":[
        {
            "category":"Real Estate",
            "subcategory":"Architect",
            "type":"Services"
        }
    ],
    "sg:phone":"+1 925 330 7423",
    "sg:postcode":"94563",
    "sg:province":"CA",
    "wof:name":"T GOODWIN ASSOCIATES",
    "wof:placetype":"venue"
},
  "geometry": {"coordinates":[-122.198446,37.894984],"type":"Point"}
}