{
  "type": "Feature",
  "properties": {
    "iso:country":"US",
    "sg:address":"951 2nd St",
    "sg:city":"Calimesa",
    "sg:classifiers":[
        {
            "category":"Wholesale",
            "subcategory":"Hardware",
            "type":"Manufacturing & Wholesale Goods"
        }
    ],
    "sg:phone":"+1 909 795 4330",
    "sg:postcode":"92320",
    "sg:province":"CA",
    "sg:tags":[
        "plumbing",
        "re",
        "health",
        "market"
    ],
    "wof:name":"Fisher Associates",
    "wof:placetype":"venue"
},
  "geometry": {"coordinates":[-117.04299899999999,34.002499],"type":"Point"}
}