{
  "type": "Feature",
  "properties": {
    "iso:country":"US",
    "sg:address":"11803 Slauson Ave",
    "sg:city":"Santa Fe Springs",
    "sg:classifiers":[
        {
            "category":"Autos & Motor Vehicles",
            "subcategory":"Motorcycle Sales",
            "type":"Retail Goods"
        }
    ],
    "sg:phone":"+1 562 945 2453",
    "sg:postcode":"90670",
    "sg:province":"CA",
    "wof:name":"C T World Class Products",
    "wof:placetype":"venue"
},
  "geometry": {"coordinates":[-118.064003,33.964699],"type":"Point"}
}