{
  "type": "Feature",
  "properties": {
    "addr:full":"5598 Atlantic Ave Long Beach CA 90805",
    "addr:housenumber":"5598",
    "addr:postcode":"90805",
    "addr:street":"Atlantic Ave",
    "iso:country":"US",
    "sg:address":"5598 Atlantic Ave",
    "sg:city":"Long Beach",
    "sg:classifiers":[
        {
            "category":"Communications",
            "subcategory":"Film & Video Production",
            "type":"Services"
        }
    ],
    "sg:phone":"+1 562 984 6260",
    "sg:postcode":"90805",
    "sg:province":"CA",
    "sg:tags":[
        "audio"
    ],
    "wof:name":"Mendenhall Productions",
    "wof:placetype":"venue"
},
  "geometry": {"coordinates":[-118.184944,33.856251],"type":"Point"}
}