{
  "type": "Feature",
  "properties": {
    "iso:country":"US",
    "sg:address":"1327 Broadway",
    "sg:city":"Burlingame",
    "sg:classifiers":[
        {
            "category":"Bars & Pubs",
            "type":"Food & Drink"
        }
    ],
    "sg:phone":"+1 650 344 0265",
    "sg:postcode":"94010",
    "sg:province":"CA",
    "wof:name":"Behan's Irish Pub",
    "wof:placetype":"venue"
},
  "geometry": {"coordinates":[-122.364998,37.585201],"type":"Point"}
}