{
  "type": "Feature",
  "properties": {
    "addr:full":"908 Admiral Callaghan Ln Vallejo CA 94591",
    "addr:housenumber":"908",
    "addr:postcode":"94591",
    "addr:street":"Admiral Callaghan Ln",
    "iso:country":"US",
    "sg:address":"908 Admiral Callaghan Ln",
    "sg:city":"Vallejo",
    "sg:classifiers":[
        {
            "category":"Shopping",
            "subcategory":"Clothing, Apparel, & Fashions",
            "type":"Retail Goods"
        },
        {
            "category":"Shopping",
            "subcategory":"Shoes",
            "type":"Retail Goods"
        }
    ],
    "sg:phone":"+1 707 552 3731",
    "sg:postcode":"94591",
    "sg:province":"CA",
    "sg:tags":[
        "accessory",
        "store",
        "women's"
    ],
    "sg:website":"http://www.paylessshoesource.com",
    "wof:name":"Payless ShoeSource",
    "wof:placetype":"venue"
},
  "geometry": {"coordinates":[-122.223995,38.132127],"type":"Point"}
}