{
  "type": "Feature",
  "properties": {
    "iso:country":"US",
    "sg:address":"2713 W 6th St",
    "sg:city":"Los Angeles",
    "sg:classifiers":[
        {
            "category":"Professional",
            "type":"Services"
        }
    ],
    "sg:phone":"+1 213 389 5341",
    "sg:postcode":"90057",
    "sg:province":"CA",
    "wof:name":"Arguetas Concepcion",
    "wof:placetype":"venue"
},
  "geometry": {"coordinates":[-118.281803,34.062699],"type":"Point"}
}