{
  "type": "Feature",
  "properties": {
    "iso:country":"US",
    "sg:address":"1910 Olympic Blvd",
    "sg:city":"Walnut Creek",
    "sg:classifiers":[
        {
            "category":"Professional",
            "subcategory":"Accounting & Tax Preparation",
            "type":"Services"
        }
    ],
    "sg:phone":"+1 925 932 1655",
    "sg:postcode":"94595",
    "sg:province":"CA",
    "sg:tags":[
        "accountant"
    ],
    "wof:name":"Phillip S Winslow CPA",
    "wof:placetype":"venue"
},
  "geometry": {"coordinates":[-122.066227,37.893517],"type":"Point"}
}