{
  "type": "Feature",
  "properties": {
    "addr:full":"22440 Clarendon St Woodland Hills CA 91367",
    "addr:housenumber":"22440",
    "addr:postcode":"91367",
    "addr:street":"Clarendon St",
    "iso:country":"US",
    "sg:address":"22440 Clarendon St",
    "sg:city":"Woodland Hills",
    "sg:classifiers":[
        {
            "category":"Health Services",
            "subcategory":"Clinic",
            "type":"Services"
        }
    ],
    "sg:phone":"+1 818 222 4181",
    "sg:postcode":"91367",
    "sg:province":"CA",
    "sg:website":"www.superiorhealthexam.com",
    "wof:name":"Superior Health Examiners",
    "wof:placetype":"venue"
},
  "geometry": {"coordinates":[-118.616022,34.169141],"type":"Point"}
}