{
  "type": "Feature",
  "properties": {
    "addr:full":"1565 Farmers Ln Santa Rosa CA 95405",
    "addr:housenumber":"1565",
    "addr:postcode":"95405",
    "addr:street":"Farmers Ln",
    "iso:country":"US",
    "sg:address":"1565 Farmers Ln",
    "sg:city":"Santa Rosa",
    "sg:classifiers":[
        {
            "category":"Home & Garden",
            "subcategory":"Home Furnishings",
            "type":"Retail Goods"
        }
    ],
    "sg:phone":"+1 707 545 0534",
    "sg:postcode":"95405",
    "sg:province":"CA",
    "sg:tags":[
        "housewares"
    ],
    "sg:website":"www.hardistys.com",
    "wof:name":"Hardisty's Homewares",
    "wof:placetype":"venue"
},
  "geometry": {"coordinates":[-122.688507,38.433666],"type":"Point"}
}