{
  "type": "Feature",
  "properties": {
    "addr:full":"1275 N 1st St Fresno CA 93703",
    "addr:housenumber":"1275",
    "addr:postcode":"93703",
    "addr:street":"N 1St St",
    "iso:country":"US",
    "sg:address":"1275 N 1st St",
    "sg:city":"Fresno",
    "sg:classifiers":[
        {
            "category":"Wholesale",
            "subcategory":"Fruits & Vegetables",
            "type":"Manufacturing & Wholesale Goods"
        }
    ],
    "sg:phone":"+1 559 497 6939",
    "sg:postcode":"93703",
    "sg:province":"CA",
    "wof:name":"Produmex Fresno",
    "wof:placetype":"venue"
},
  "geometry": {"coordinates":[-119.772572,36.759059],"type":"Point"}
}