{
  "type": "Feature",
  "properties": {
    "addr:full":"1021 Highland Ave National City CA 91950",
    "addr:housenumber":"1021",
    "addr:postcode":"91950",
    "addr:street":"Highland Ave",
    "iso:country":"US",
    "sg:address":"1021 Highland Ave",
    "sg:city":"National City",
    "sg:classifiers":[
        {
            "category":"Home & Garden",
            "subcategory":"Carpets & Floor Coverings",
            "type":"Retail Goods"
        }
    ],
    "sg:phone":"+1 619 477 7722",
    "sg:postcode":"91950",
    "sg:province":"CA",
    "sg:tags":[
        "dealer",
        "rug"
    ],
    "wof:name":"Rug Gallery",
    "wof:placetype":"venue"
},
  "geometry": {"coordinates":[-117.097308,32.674717],"type":"Point"}
}