{
  "type": "Feature",
  "properties": {
    "addr:full":"2516 Blanding Ave Alameda CA 94501",
    "addr:housenumber":"2516",
    "addr:postcode":"94501",
    "addr:street":"Blanding Ave",
    "iso:country":"US",
    "sg:address":"2516 Blanding Ave",
    "sg:city":"Alameda",
    "sg:classifiers":[
        {
            "category":"Communications",
            "subcategory":"Film & Video Production",
            "type":"Services"
        }
    ],
    "sg:phone":"+1 510 521 4533",
    "sg:postcode":"94501",
    "sg:province":"CA",
    "wof:name":"Neptune Beach Media",
    "wof:placetype":"venue"
},
  "geometry": {"coordinates":[-122.235471,37.769546],"type":"Point"}
}