{
  "type": "Feature",
  "properties": {
    "addr:full":"9915 Santa Monica Blvd Beverly Hills CA 90212",
    "addr:housenumber":"9915",
    "addr:postcode":"90212",
    "addr:street":"Santa Monica Blvd",
    "iso:country":"US",
    "sg:address":"9915 Santa Monica Blvd",
    "sg:city":"Beverly Hills",
    "sg:classifiers":[
        {
            "category":"Social Services",
            "type":"Services"
        }
    ],
    "sg:phone":"+1 310 556 8961",
    "sg:postcode":"90212",
    "sg:province":"CA",
    "sg:tags":[
        "counselor",
        "marriage",
        "family"
    ],
    "sg:website":"www.magicofhealing.com",
    "wof:name":"Darcy Lubbers",
    "wof:placetype":"venue"
},
  "geometry": {"coordinates":[-118.41269,34.065548],"type":"Point"}
}