{
  "type": "Feature",
  "properties": {
    "addr:full":"3730 Barrington Dr Concord CA 94518",
    "addr:housenumber":"3730",
    "addr:postcode":"94518",
    "addr:street":"Barrington Dr",
    "iso:country":"US",
    "sg:address":"3730 Barrington Dr",
    "sg:city":"Concord",
    "sg:classifiers":[
        {
            "category":"Food & Beverages",
            "subcategory":"Chocolate",
            "type":"Retail Goods"
        }
    ],
    "sg:phone":"+1 925 680 5541",
    "sg:postcode":"94518",
    "sg:province":"CA",
    "sg:tags":[
        "cocoa"
    ],
    "wof:name":"Chocolate Creations",
    "wof:placetype":"venue"
},
  "geometry": {"coordinates":[-122.009023,37.964675],"type":"Point"}
}