{
  "type": "Feature",
  "properties": {
    "addr:full":"500 Newport Center Dr Ste 960 Newport Beach CA 92660",
    "addr:housenumber":"500",
    "addr:postcode":"92660",
    "addr:street":"Newport Center Dr Ste 960",
    "iso:country":"US",
    "sg:address":"500 Newport Center Dr Ste 960",
    "sg:city":"Newport Beach",
    "sg:classifiers":[
        {
            "category":"Banks & Credit Unions",
            "subcategory":"Bank",
            "type":"Services"
        }
    ],
    "sg:phone":"+1 949 718 6050",
    "sg:postcode":"92660",
    "sg:province":"CA",
    "wof:name":"California Independent Bankers",
    "wof:placetype":"venue"
},
  "geometry": {"coordinates":[-117.87200199999999,33.615398],"type":"Point"}
}