{
  "type": "Feature",
  "properties": {
    "iso:country":"US",
    "sg:address":"6170 Landino Dr",
    "sg:city":"Thousand Oaks",
    "sg:classifiers":[
        {
            "category":"Shopping",
            "subcategory":"Florist",
            "type":"Retail Goods"
        }
    ],
    "sg:phone":"+1 818 991 5377",
    "sg:postcode":"91362",
    "sg:province":"CA",
    "wof:name":"Designs Unique By Sherree",
    "wof:placetype":"venue"
},
  "geometry": {"coordinates":[-118.792831,34.163069],"type":"Point"}
}