{
  "type": "Feature",
  "properties": {
    "addr:full":"931 Chester Ave Bakersfield CA 93301",
    "addr:housenumber":"931",
    "addr:postcode":"93301",
    "addr:street":"Chester Ave",
    "iso:country":"US",
    "sg:address":"931 Chester Ave",
    "sg:city":"Bakersfield",
    "sg:classifiers":[
        {
            "category":"Shopping",
            "subcategory":"Clothing, Apparel, & Fashions",
            "type":"Retail Goods"
        }
    ],
    "sg:phone":"+1 661 327 2679",
    "sg:postcode":"93301",
    "sg:province":"CA",
    "sg:tags":[
        "shirts-custom",
        "tailor",
        "alterations-clothing",
        "made"
    ],
    "wof:name":"Alterations And Tailors Manu",
    "wof:placetype":"venue"
},
  "geometry": {"coordinates":[-119.018867,35.365842],"type":"Point"}
}