{
  "type": "Feature",
  "properties": {
    "addr:full":"5559 Quail St Inyokern CA 93527",
    "addr:housenumber":"5559",
    "addr:postcode":"93527",
    "addr:street":"Quail St",
    "iso:country":"US",
    "sg:address":"5559 Quail St",
    "sg:city":"Inyokern",
    "sg:classifiers":[
        {
            "category":"Utilities",
            "subcategory":"Fuel Oil & Lpg",
            "type":"Services"
        }
    ],
    "sg:phone":"+1 760 377 4465",
    "sg:postcode":"93527",
    "sg:province":"CA",
    "sg:tags":[
        "firewood"
    ],
    "wof:name":"Wilhorn & Sons Firewood",
    "wof:placetype":"venue"
},
  "geometry": {"coordinates":[-117.843825,35.719979],"type":"Point"}
}