{
  "type": "Feature",
  "properties": {
    "addr:full":"1399 64th St Emeryville CA 94608",
    "addr:housenumber":"1399",
    "addr:postcode":"94608",
    "addr:street":"64Th St",
    "iso:country":"US",
    "sg:address":"1399 64th St",
    "sg:city":"Emeryville",
    "sg:classifiers":[
        {
            "category":"Shopping",
            "subcategory":"Computers & Home Electronics",
            "type":"Retail Goods"
        }
    ],
    "sg:phone":"+1 510 597 1701",
    "sg:postcode":"94608",
    "sg:province":"CA",
    "sg:tags":[
        "recorder",
        "time",
        "clock"
    ],
    "wof:name":"Tiffany Stewart Solutions",
    "wof:placetype":"venue"
},
  "geometry": {"coordinates":[-122.29084,37.844799],"type":"Point"}
}