{
  "type": "Feature",
  "properties": {
    "iso:country":"US",
    "sg:address":"1126 W Valley Blvd",
    "sg:city":"Alhambra",
    "sg:classifiers":[
        {
            "category":"Manufacturing",
            "subcategory":"Electronics",
            "type":"Manufacturing & Wholesale Goods"
        }
    ],
    "sg:phone":"+1 626 300 0066",
    "sg:postcode":"91803",
    "sg:province":"CA",
    "sg:tags":[
        "mfg",
        "boards",
        "circuit",
        "printed"
    ],
    "wof:name":"Envision",
    "wof:placetype":"venue"
},
  "geometry": {"coordinates":[-118.135642,34.07777],"type":"Point"}
}