{
  "type": "Feature",
  "properties": {
    "addr:full":"1824 E Palmdale Blvd Palmdale CA 93550",
    "addr:housenumber":"1824",
    "addr:postcode":"ca 93550",
    "addr:street":"E Palmdale Blvd",
    "iso:country":"US",
    "sg:address":"1824 E Palmdale Blvd",
    "sg:city":"Palmdale",
    "sg:classifiers":[
        {
            "category":"Fast Food",
            "type":"Food & Drink"
        },
        {
            "category":"Restaurant",
            "type":"Food & Drink"
        }
    ],
    "sg:phone":"+1 661 224 1448",
    "sg:postcode":"93550",
    "sg:province":"CA",
    "sg:tags":[
        "take"
    ],
    "wof:name":"Sky Burgers No 3",
    "wof:placetype":"venue"
},
  "geometry": {"coordinates":[-118.096073,34.57969],"type":"Point"}
}