{
  "type": "Feature",
  "properties": {
    "iso:country":"US",
    "sg:address":"24180 Ernest Johnson Cir",
    "sg:city":"Yorba Linda",
    "sg:classifiers":[
        {
            "category":"Government",
            "subcategory":"Office",
            "type":"Public Place"
        }
    ],
    "sg:phone":"+1 714 694 0403",
    "sg:postcode":"92887",
    "sg:province":"CA",
    "sg:tags":[
        "management"
    ],
    "wof:name":"Coast Air Quality",
    "wof:placetype":"venue"
},
  "geometry": {"coordinates":[-117.708645,33.874345],"type":"Point"}
}