{
  "type": "Feature",
  "properties": {
    "iso:country":"US",
    "sg:address":"1850 Ramada Dr",
    "sg:city":"Paso Robles",
    "sg:classifiers":[
        {
            "category":"Freight",
            "type":"Transportation"
        }
    ],
    "sg:phone":"+1 805 237 0353",
    "sg:postcode":"93446",
    "sg:province":"CA",
    "sg:tags":[
        "trucking"
    ],
    "wof:name":"A Schultz Transportation",
    "wof:placetype":"venue"
},
  "geometry": {"coordinates":[-120.695546,35.586237],"type":"Point"}
}