{
  "type": "Feature",
  "properties": {
    "addr:full":"1850 Ramada Dr Paso Robles CA 93446",
    "addr:housenumber":"1850",
    "addr:postcode":"93446",
    "addr:street":"Ramada Dr",
    "iso:country":"US",
    "sg:address":"1850 Ramada Dr",
    "sg:city":"Paso Robles",
    "sg:classifiers":[
        {
            "category":"Freight",
            "type":"Transportation"
        }
    ],
    "sg:phone":"+1 805 237 0353",
    "sg:postcode":"93446",
    "sg:province":"CA",
    "sg:tags":[
        "trucking"
    ],
    "wof:name":"A Schultz Transportation",
    "wof:placetype":"venue"
},
  "geometry": {"coordinates":[-120.69554599999999,35.586237],"type":"Point"}
}