{
  "type": "Feature",
  "properties": {
    "iso:country":"US",
    "sg:address":"436 High St",
    "sg:city":"Palo Alto",
    "sg:classifiers":[
        {
            "category":"Professional",
            "type":"Services"
        }
    ],
    "sg:phone":"+1 650 838 9228",
    "sg:postcode":"94301",
    "sg:province":"CA",
    "sg:tags":[
        "establishment"
    ],
    "wof:name":"Philip Brady Co",
    "wof:placetype":"venue"
},
  "geometry": {"coordinates":[-122.16384499999999,37.444304],"type":"Point"}
}