{
  "type": "Feature",
  "properties": {
    "addr:full":"3026 Cielo Pl Carlsbad CA 92009",
    "addr:housenumber":"3026",
    "addr:postcode":"92009",
    "addr:street":"Cielo Pl",
    "iso:country":"US",
    "sg:address":"3026 Cielo Pl",
    "sg:city":"Carlsbad",
    "sg:classifiers":[
        {
            "category":"Building & Trades",
            "subcategory":"Construction",
            "type":"Services"
        }
    ],
    "sg:phone":"+1 760 942 2266",
    "sg:postcode":"92009",
    "sg:province":"CA",
    "sg:tags":[
        "concrete",
        "contractor"
    ],
    "wof:name":"J L Concrete Inc",
    "wof:placetype":"venue"
},
  "geometry": {"coordinates":[-117.242615,33.087991],"type":"Point"}
}