{
  "type": "Feature",
  "properties": {
    "iso:country":"US",
    "sg:address":"2001 Addison St",
    "sg:city":"Berkeley",
    "sg:classifiers":[
        {
            "category":"Professional",
            "subcategory":"Management & Consulting",
            "type":"Services"
        }
    ],
    "sg:phone":"+1 510 548 3922",
    "sg:postcode":"94704",
    "sg:province":"CA",
    "sg:tags":[
        "consultant",
        "business"
    ],
    "sg:website":"www.roncocorp.com",
    "wof:name":"Ronco Consulting Corp",
    "wof:placetype":"venue"
},
  "geometry": {"coordinates":[-122.268289,37.871178],"type":"Point"}
}