{
  "type": "Feature",
  "properties": {
    "addr:full":"1501 Powell St Emeryville CA 94608",
    "addr:housenumber":"1501",
    "addr:postcode":"94608",
    "addr:street":"Powell St",
    "iso:country":"US",
    "sg:address":"1501 Powell St",
    "sg:city":"Emeryville",
    "sg:classifiers":[
        {
            "category":"Professional",
            "subcategory":"Printing & Photocopies",
            "type":"Services"
        }
    ],
    "sg:phone":"+1 510 655 6756",
    "sg:postcode":"94608",
    "sg:province":"CA",
    "sg:tags":[
        "screen"
    ],
    "wof:name":"Astropress",
    "wof:placetype":"venue"
},
  "geometry": {"coordinates":[-122.290909,37.839169],"type":"Point"}
}