{
  "type": "Feature",
  "properties": {
    "iso:country":"US",
    "sg:address":"1440 N Harbor Blvd",
    "sg:city":"Fullerton",
    "sg:classifiers":[
        {
            "category":"Health Services",
            "subcategory":"Doctor",
            "type":"Services"
        }
    ],
    "sg:phone":"+1 714 447 4555",
    "sg:postcode":"92835",
    "sg:province":"CA",
    "sg:tags":[
        "physician",
        "surgeon"
    ],
    "wof:name":"Centers For Excellence In Pain",
    "wof:placetype":"venue"
},
  "geometry": {"coordinates":[-117.926338,33.886423],"type":"Point"}
}