{
  "type": "Feature",
  "properties": {
    "iso:country":"US",
    "sg:address":"650 10th St",
    "sg:city":"Arcata",
    "sg:classifiers":[
        {
            "category":"Shopping",
            "subcategory":"Bicycles & Sporting Goods",
            "type":"Retail Goods"
        }
    ],
    "sg:phone":"+1 707 822 4673",
    "sg:postcode":"95521",
    "sg:province":"CA",
    "sg:website":"www.adventuresedge.com",
    "wof:name":"Adventure's Edge",
    "wof:placetype":"venue"
},
  "geometry": {"coordinates":[-124.08504600000001,40.869547],"type":"Point"}
}