{
  "type": "Feature",
  "properties": {
    "addr:full":"7909 Quest St Bakersfield CA 93307",
    "addr:housenumber":"7909",
    "addr:postcode":"93307",
    "addr:street":"Quest St",
    "iso:country":"US",
    "sg:address":"7909 Quest St",
    "sg:city":"Bakersfield",
    "sg:classifiers":[
        {
            "category":"Health Services",
            "subcategory":"Doctor",
            "type":"Services"
        }
    ],
    "sg:phone":"+1 661 397 3759",
    "sg:postcode":"93307",
    "sg:province":"CA",
    "sg:tags":[
        "physician",
        "surgeon"
    ],
    "wof:name":"Bholjit S Cheema",
    "wof:placetype":"venue"
},
  "geometry": {"coordinates":[-119.015839,35.283311],"type":"Point"}
}