{
  "type": "Feature",
  "properties": {
    "iso:country":"US",
    "sg:address":"200 Burnett Ave",
    "sg:city":"Morgan Hill",
    "sg:classifiers":[
        {
            "category":"Building & Trades",
            "subcategory":"Landscaping Services",
            "type":"Services"
        }
    ],
    "sg:phone":"+1 408 778 2306",
    "sg:postcode":"95037",
    "sg:province":"CA",
    "wof:name":"AP Landscape Maint",
    "wof:placetype":"venue"
},
  "geometry": {"coordinates":[-121.67142,37.156159],"type":"Point"}
}