{
  "type": "Feature",
  "properties": {
    "iso:country":"US",
    "sg:address":"2727 Stingle Ave",
    "sg:city":"Rosemead",
    "sg:classifiers":[
        {
            "category":"Manufacturing",
            "subcategory":"Building Materials",
            "type":"Manufacturing & Wholesale Goods"
        }
    ],
    "sg:phone":"+1 626 589 7628",
    "sg:postcode":"91770",
    "sg:province":"CA",
    "sg:tags":[
        "mfg",
        "wood",
        "kitchen",
        "cabinet"
    ],
    "wof:name":"FB Products USA Company",
    "wof:placetype":"venue"
},
  "geometry": {"coordinates":[-118.074935,34.059508],"type":"Point"}
}