{
  "type": "Feature",
  "properties": {
    "addr:full":"453 E Verdugo Ave Ste 207 Burbank CA 91501",
    "addr:housenumber":"453",
    "addr:postcode":"91501",
    "addr:street":"E Verdugo Ave Ste 207",
    "iso:country":"US",
    "sg:address":"453 E Verdugo Ave Ste 207",
    "sg:city":"Burbank",
    "sg:classifiers":[
        {
            "category":"Building & Trades",
            "subcategory":"Construction",
            "type":"Services"
        }
    ],
    "sg:phone":"+1 818 424 2722",
    "sg:postcode":"91501",
    "sg:province":"CA",
    "sg:tags":[
        "air",
        "heating",
        "conditioning/hvac"
    ],
    "sg:website":"www.ascc.com",
    "wof:name":"Air Systems Control Co.",
    "wof:placetype":"venue"
},
  "geometry": {"coordinates":[-118.30271500000001,34.182014],"type":"Point"}
}