{
  "type": "Feature",
  "properties": {
    "addr:full":"592 Jean St #202 Oakland CA 94610",
    "addr:housenumber":"592;202",
    "addr:postcode":"94610",
    "addr:street":"Jean St #",
    "iso:country":"US",
    "sg:address":"592 Jean St #202",
    "sg:city":"Oakland",
    "sg:classifiers":[
        {
            "category":"Health Services",
            "subcategory":"Clinic",
            "type":"Services"
        }
    ],
    "sg:phone":"+1 925 914 1212",
    "sg:postcode":"94610",
    "sg:province":"CA",
    "sg:tags":[
        "counseling",
        "mental"
    ],
    "sg:website":"www.leslienipps.com",
    "wof:name":"Leslie Nipps Counseling",
    "wof:placetype":"venue"
},
  "geometry": {"coordinates":[-122.24781900000001,37.817485],"type":"Point"}
}