{
  "type": "Feature",
  "properties": {
    "iso:country":"US",
    "sg:address":"1450 23rd St",
    "sg:city":"Santa Monica",
    "sg:classifiers":[
        {
            "category":"Professional",
            "subcategory":"Computer Services",
            "type":"Services"
        }
    ],
    "sg:phone":"+1 310 453 3259",
    "sg:postcode":"90404",
    "sg:province":"CA",
    "sg:tags":[
        "consultant",
        "designer",
        "datum",
        "system"
    ],
    "wof:name":"Meruit Inc",
    "wof:placetype":"venue"
},
  "geometry": {"coordinates":[-118.476022,34.029495],"type":"Point"}
}