{
  "type": "Feature",
  "properties": {
    "iso:country":"US",
    "sg:address":"735 N Main St",
    "sg:city":"Manteca",
    "sg:classifiers":[
        {
            "category":"Banks & Credit Unions",
            "subcategory":"Bank",
            "type":"Services"
        }
    ],
    "sg:phone":"+1 209 239 5550",
    "sg:postcode":"95336",
    "sg:province":"CA",
    "sg:tags":[
        "loan"
    ],
    "wof:name":"Capital Pacific Mortgage",
    "wof:placetype":"venue"
},
  "geometry": {"coordinates":[-121.21708099999999,37.809719],"type":"Point"}
}