{
  "type": "Feature",
  "properties": {
    "addr:full":"30131 Town Center Dr Laguna Niguel CA 92677",
    "addr:housenumber":"30131",
    "addr:postcode":"92677",
    "addr:street":"Town Center Dr",
    "iso:country":"US",
    "sg:address":"30131 Town Center Dr",
    "sg:city":"Laguna Niguel",
    "sg:classifiers":[
        {
            "category":"Professional",
            "subcategory":"Business Services",
            "type":"Services"
        }
    ],
    "sg:phone":"+1 949 464 1270",
    "sg:postcode":"92677",
    "sg:province":"CA",
    "sg:tags":[
        "mail",
        "voice",
        "messaging"
    ],
    "wof:name":"Direct Effect",
    "wof:placetype":"venue"
},
  "geometry": {"coordinates":[-117.713758,33.52629],"type":"Point"}
}