{
  "type": "Feature",
  "properties": {
    "addr:full":"4140 Bangs Ave Modesto CA 95356",
    "addr:housenumber":"4140",
    "addr:postcode":"ca 95356",
    "addr:street":"Bangs Ave",
    "iso:country":"US",
    "sg:address":"4140 Bangs Ave",
    "sg:city":"Modesto",
    "sg:classifiers":[
        {
            "category":"Wholesale",
            "subcategory":"Medical Equipment & Supplies",
            "type":"Manufacturing & Wholesale Goods"
        }
    ],
    "sg:phone":"+1 209 527 3641",
    "sg:postcode":"95356",
    "sg:province":"CA",
    "sg:tags":[
        "physician",
        "surgeon"
    ],
    "wof:name":"Med-Mart",
    "wof:placetype":"venue"
},
  "geometry": {"coordinates":[-121.07032100000001,37.704437],"type":"Point"}
}