{
  "type": "Feature",
  "properties": {
    "iso:country":"US",
    "sg:address":"26901 Columbia Way",
    "sg:city":"Tehachapi",
    "sg:classifiers":[
        {
            "category":"Manufacturing",
            "subcategory":"Motor Vehicles & Parts",
            "type":"Manufacturing & Wholesale Goods"
        }
    ],
    "sg:phone":"+1 661 821 3405",
    "sg:postcode":"93561",
    "sg:province":"CA",
    "sg:tags":[
        "body",
        "mfg"
    ],
    "wof:name":"Valenciamotorsportscom",
    "wof:placetype":"venue"
},
  "geometry": {"coordinates":[-118.602335,35.164434],"type":"Point"}
}