{
  "type": "Feature",
  "properties": {
    "addr:full":"7648 Painter Ave Whittier CA 90602",
    "addr:housenumber":"7648",
    "addr:postcode":"90602",
    "addr:street":"Painter Ave",
    "iso:country":"US",
    "sg:address":"7648 Painter Ave",
    "sg:city":"Whittier",
    "sg:classifiers":[
        {
            "category":"Manufacturing",
            "subcategory":"Metals",
            "type":"Manufacturing & Wholesale Goods"
        },
        {
            "category":"Autos & Motor Vehicles",
            "subcategory":"Motorcycle Sales",
            "type":"Retail Goods"
        }
    ],
    "sg:phone":"+1 562 945 7600",
    "sg:postcode":"90602",
    "sg:province":"CA",
    "sg:tags":[
        "hardware",
        "scooter",
        "mfg"
    ],
    "wof:name":"Brraaap",
    "wof:placetype":"venue"
},
  "geometry": {"coordinates":[-118.03259799999999,33.972013],"type":"Point"}
}