{
  "type": "Feature",
  "properties": {
    "addr:full":"1030 Murray St Berkeley CA 94710",
    "addr:housenumber":"1030",
    "addr:postcode":"94710",
    "addr:street":"Murray St",
    "iso:country":"US",
    "sg:address":"1030 Murray St",
    "sg:city":"Berkeley",
    "sg:classifiers":[
        {
            "category":"Restaurant",
            "type":"Food & Drink"
        }
    ],
    "sg:phone":"+1 510 549 3760",
    "sg:postcode":"94710",
    "sg:province":"CA",
    "sg:tags":[
        "caterer"
    ],
    "sg:website":"www.labonnecuisine.com",
    "wof:name":"La Bonne Cuisine",
    "wof:placetype":"venue"
},
  "geometry": {"coordinates":[-122.288234,37.851372],"type":"Point"}
}