{
  "type": "Feature",
  "properties": {
    "iso:country":"US",
    "sg:address":"21220 Commerce Point Dr",
    "sg:city":"Walnut",
    "sg:classifiers":[
        {
            "category":"Building & Trades",
            "subcategory":"Construction",
            "type":"Services"
        }
    ],
    "sg:phone":"+1 909 468 2600",
    "sg:postcode":"91789",
    "sg:province":"CA",
    "sg:tags":[
        "system",
        "contractor",
        "mechanical",
        "air conditioning"
    ],
    "wof:name":"Air Flow Mechanical, Inc.",
    "wof:placetype":"venue"
},
  "geometry": {"coordinates":[-117.841728,34.017567],"type":"Point"}
}