{
  "type": "Feature",
  "properties": {
    "iso:country":"US",
    "sg:address":"4594 Saint Andrews Dr",
    "sg:city":"Chino Hills",
    "sg:classifiers":[
        {
            "category":"Banks & Credit Unions",
            "subcategory":"Bank",
            "type":"Services"
        }
    ],
    "sg:phone":"+1 909 606 6492",
    "sg:postcode":"91709",
    "sg:province":"CA",
    "sg:tags":[
        "loan",
        "real estate"
    ],
    "sg:website":"www.pacifictechfinancial.com",
    "wof:name":"Pacific Tech Financial",
    "wof:placetype":"venue"
},
  "geometry": {"coordinates":[-117.704784,33.958654],"type":"Point"}
}