{
  "type": "Feature",
  "properties": {
    "addr:full":"1835 S Centre City Pkwy Escondido CA 92025",
    "addr:housenumber":"1835",
    "addr:postcode":"92025",
    "addr:street":"S Centre City Pkwy",
    "iso:country":"US",
    "sg:address":"1835 S Centre City Pkwy",
    "sg:city":"Escondido",
    "sg:classifiers":[
        {
            "category":"Professional",
            "subcategory":"Computer Services",
            "type":"Services"
        }
    ],
    "sg:phone":"+1 760 747 9011",
    "sg:postcode":"92025",
    "sg:province":"CA",
    "sg:tags":[
        "consultant",
        "designer"
    ],
    "wof:name":"Burbidge & Assoc",
    "wof:placetype":"venue"
},
  "geometry": {"coordinates":[-117.07349600000001,33.100267],"type":"Point"}
}