{
  "type": "Feature",
  "properties": {
    "iso:country":"US",
    "sg:address":"3170 De La Cruz Blvd",
    "sg:city":"Santa Clara",
    "sg:classifiers":[
        {
            "category":"Restaurant",
            "type":"Food & Drink"
        },
        {
            "category":"Coffee & Tea",
            "type":"Food & Drink"
        },
        {
            "category":"Food & Beverages",
            "subcategory":"Bakery",
            "type":"Retail Goods"
        }
    ],
    "sg:phone":"+1 408 748 9880",
    "sg:postcode":"95054",
    "sg:province":"CA",
    "sg:tags":[
        "sandwich",
        "vietnamese"
    ],
    "wof:name":"Lily Coffee & Sandwich",
    "wof:placetype":"venue"
},
  "geometry": {"coordinates":[-121.941183,37.379899],"type":"Point"}
}