{
  "type": "Feature",
  "properties": {
    "iso:country":"US",
    "sg:address":"403 W A St",
    "sg:city":"San Diego",
    "sg:classifiers":[
        {
            "category":"Real Estate",
            "subcategory":"Real Estate Services",
            "type":"Services"
        }
    ],
    "sg:phone":"+1 619 330 9464",
    "sg:postcode":"92101",
    "sg:province":"CA",
    "wof:name":"Office Space in San Diego",
    "wof:placetype":"venue"
},
  "geometry": {"coordinates":[-117.166951,32.718809],"type":"Point"}
}