{
  "type": "Feature",
  "properties": {
    "iso:country":"US",
    "sg:address":"820 Sartori Dr",
    "sg:city":"Petaluma",
    "sg:classifiers":[
        {
            "category":"Building & Trades",
            "subcategory":"Construction",
            "type":"Services"
        }
    ],
    "sg:phone":"+1 707 763 4081",
    "sg:postcode":"94954",
    "sg:province":"CA",
    "sg:tags":[
        "designer"
    ],
    "wof:name":"Design Soft",
    "wof:placetype":"venue"
},
  "geometry": {"coordinates":[-122.595229,38.235483],"type":"Point"}
}