{
  "type": "Feature",
  "properties": {
    "addr:full":"847 Emerson St Palo Alto CA 94301",
    "addr:housenumber":"847",
    "addr:postcode":"94301",
    "addr:street":"Emerson St",
    "iso:country":"US",
    "sg:address":"847 Emerson St",
    "sg:city":"Palo Alto",
    "sg:classifiers":[
        {
            "category":"Professional",
            "subcategory":"Art Services",
            "type":"Services"
        }
    ],
    "sg:phone":"+1 650 321 2443",
    "sg:postcode":"94301",
    "sg:province":"CA",
    "sg:tags":[
        "artist"
    ],
    "wof:name":"Russell Leong Design",
    "wof:placetype":"venue"
},
  "geometry": {"coordinates":[-122.157904,37.441713],"type":"Point"}
}