{
  "type": "Feature",
  "properties": {
    "addr:full":"26121 Ave Hall Santa Clarita CA 91355",
    "addr:housenumber":"26121",
    "addr:postcode":"91355",
    "addr:street":"Ave Hall",
    "iso:country":"US",
    "sg:address":"26121 Ave Hall",
    "sg:city":"Santa Clarita",
    "sg:classifiers":[
        {
            "category":"Wholesale",
            "subcategory":"Durable Goods & Equipment",
            "type":"Manufacturing & Wholesale Goods"
        }
    ],
    "sg:phone":"+1 661 257 0753",
    "sg:postcode":"91355",
    "sg:province":"CA",
    "sg:tags":[
        "importer"
    ],
    "wof:name":"Contractors Wardrobe",
    "wof:placetype":"venue"
},
  "geometry": {"coordinates":[-118.59047200000001,34.439763],"type":"Point"}
}