{
  "type": "Feature",
  "properties": {
    "iso:country":"US",
    "sg:address":"461 7th St W",
    "sg:city":"Sonoma",
    "sg:classifiers":[
        {
            "category":"Professional",
            "subcategory":"Management & Consulting",
            "type":"Services"
        }
    ],
    "sg:phone":"+1 707 938 9463",
    "sg:postcode":"95476",
    "sg:province":"CA",
    "sg:tags":[
        "consultant",
        "wine"
    ],
    "sg:website":"www.enologix.com",
    "wof:name":"Enologix",
    "wof:placetype":"venue"
},
  "geometry": {"coordinates":[-122.47163,38.29388],"type":"Point"}
}