{
  "type": "Feature",
  "properties": {
    "addr:full":"7530 Santa Paula Dr Gilroy CA 95020",
    "addr:housenumber":"7530",
    "addr:postcode":"95020",
    "addr:street":"Santa Paula Dr",
    "iso:country":"US",
    "sg:address":"7530 Santa Paula Dr",
    "sg:city":"Gilroy",
    "sg:classifiers":[
        {
            "category":"Building & Trades",
            "subcategory":"Electrical",
            "type":"Services"
        }
    ],
    "sg:phone":"+1 408 847 8949",
    "sg:postcode":"95020",
    "sg:province":"CA",
    "sg:tags":[
        "electrical",
        "contractor"
    ],
    "wof:name":"Chad Hulbert Electric",
    "wof:placetype":"venue"
},
  "geometry": {"coordinates":[-121.5896,37.005379],"type":"Point"}
}