{
  "type": "Feature",
  "properties": {
    "addr:full":"2400 Wible Rd Bakersfield CA 93304",
    "addr:postcode":"2400;93304",
    "addr:street":"Wible Rd",
    "iso:country":"US",
    "sg:address":"2400 Wible Rd",
    "sg:city":"Bakersfield",
    "sg:classifiers":[
        {
            "category":"Shopping",
            "subcategory":"Pharmacy",
            "type":"Retail Goods"
        }
    ],
    "sg:phone":"+1 661 835 7979",
    "sg:postcode":"93304",
    "sg:province":"CA",
    "wof:name":"Wible Pharmacy Inc",
    "wof:placetype":"venue"
},
  "geometry": {"coordinates":[-119.038979,35.333057],"type":"Point"}
}