{
  "type": "Feature",
  "properties": {
    "iso:country":"US",
    "sg:address":"904 G St",
    "sg:city":"Eureka",
    "sg:classifiers":[
        {
            "category":"Social Services",
            "type":"Services"
        }
    ],
    "sg:phone":"+1 707 443 8322",
    "sg:postcode":"95501",
    "sg:province":"CA",
    "sg:tags":[
        "youth",
        "organization",
        "center"
    ],
    "wof:name":"Youth Service Bureau Redwood",
    "wof:placetype":"venue"
},
  "geometry": {"coordinates":[-124.164162,40.79874],"type":"Point"}
}