{
  "type": "Feature",
  "properties": {
    "addr:full":"80 Gilman Ave Campbell CA 95008",
    "addr:housenumber":"80",
    "addr:postcode":"95008",
    "addr:street":"Gilman Ave",
    "iso:country":"US",
    "sg:address":"80 Gilman Ave",
    "sg:city":"Campbell",
    "sg:classifiers":[
        {
            "category":"Real Estate",
            "subcategory":"Architect",
            "type":"Services"
        }
    ],
    "sg:phone":"+1 408 370 3366",
    "sg:postcode":"95008",
    "sg:province":"CA",
    "sg:tags":[
        "home",
        "planning",
        "design"
    ],
    "sg:website":"http://www.cornerstonelimited.com",
    "wof:name":"Cornerstone Limited",
    "wof:placetype":"venue"
},
  "geometry": {"coordinates":[-121.940234,37.28611],"type":"Point"}
}