{
  "type": "Feature",
  "properties": {
    "iso:country":"US",
    "sg:address":"1128 Main St",
    "sg:city":"Newman",
    "sg:classifiers":[
        {
            "category":"Bars & Pubs",
            "type":"Food & Drink"
        }
    ],
    "sg:phone":"+1 209 823 1625",
    "sg:postcode":"95360",
    "sg:province":"CA",
    "sg:tags":[
        "drinking"
    ],
    "wof:name":"Circle Room",
    "wof:placetype":"venue"
},
  "geometry": {"coordinates":[-121.023441,37.317613],"type":"Point"}
}