{
  "type": "Feature",
  "properties": {
    "addr:full":"22601 Davis Rd Crows Landing CA 95360",
    "addr:housenumber":"22601",
    "addr:postcode":"95360",
    "addr:street":"Davis Rd",
    "iso:country":"US",
    "sg:address":"22601 Davis Rd",
    "sg:city":"Crows Landing",
    "sg:classifiers":[
        {
            "category":"Wholesale",
            "subcategory":"Groceries",
            "type":"Manufacturing & Wholesale Goods"
        }
    ],
    "sg:phone":"+1 209 837 4331",
    "sg:postcode":"95360",
    "sg:province":"CA",
    "sg:tags":[
        "grocer"
    ],
    "wof:name":"Beltran Farms",
    "wof:placetype":"venue"
},
  "geometry": {"coordinates":[-121.129396,37.381294],"type":"Point"}
}