{
  "type": "Feature",
  "properties": {
    "iso:country":"US",
    "sg:address":"2591 Giannini Rd",
    "sg:city":"Atwater",
    "sg:classifiers":[
        {
            "category":"Autos & Motor Vehicles",
            "subcategory":"Auto Supplies",
            "type":"Retail Goods"
        },
        {
            "category":"Farming",
            "subcategory":"Farm",
            "type":"Manufacturing & Wholesale Goods"
        }
    ],
    "sg:phone":"+1 209 358 4896",
    "sg:postcode":"95301",
    "sg:province":"CA",
    "sg:tags":[
        "alfalfa",
        "product"
    ],
    "wof:name":"Frank Fagundes",
    "wof:placetype":"venue"
},
  "geometry": {"coordinates":[-120.60087300000001,37.325351],"type":"Point"}
}