{
  "type": "Feature",
  "properties": {
    "addr:full":"11050 Olson Dr Rancho Cordova CA 95670",
    "addr:housenumber":"11050",
    "addr:postcode":"95670",
    "addr:street":"Olson Dr",
    "iso:country":"US",
    "sg:address":"11050 Olson Dr",
    "sg:city":"Rancho Cordova",
    "sg:classifiers":[
        {
            "category":"Professional",
            "subcategory":"Computer Services",
            "type":"Services"
        }
    ],
    "sg:phone":"+1 916 636 4200",
    "sg:postcode":"95670",
    "sg:province":"CA",
    "sg:tags":[
        "processing",
        "datum"
    ],
    "wof:name":"EDS Corp",
    "wof:placetype":"venue"
},
  "geometry": {"coordinates":[-121.286551,38.593581],"type":"Point"}
}