{
  "type": "Feature",
  "properties": {
    "iso:country":"US",
    "sg:address":"9361 Ronda Ave",
    "sg:city":"San Diego",
    "sg:classifiers":[
        {
            "category":"Shopping",
            "subcategory":"Catalog Store",
            "type":"Retail Goods"
        }
    ],
    "sg:phone":"+1 858 571 6567",
    "sg:postcode":"92123",
    "sg:province":"CA",
    "sg:tags":[
        "mail",
        "house"
    ],
    "wof:name":"Merchants Freedom",
    "wof:placetype":"venue"
},
  "geometry": {"coordinates":[-117.12285199999999,32.792458],"type":"Point"}
}