{
  "type": "Feature",
  "properties": {
    "addr:full":"1620 E Cartagena St Long Beach CA 90807",
    "addr:housenumber":"1620",
    "addr:postcode":"90807",
    "addr:street":"E Cartagena St",
    "iso:country":"US",
    "sg:address":"1620 E Cartagena St",
    "sg:city":"Long Beach",
    "sg:classifiers":[
        {
            "category":"Local Transit",
            "type":"Transportation"
        }
    ],
    "sg:phone":"+1 562 989 9601",
    "sg:postcode":"90807",
    "sg:province":"CA",
    "sg:tags":[
        "medical"
    ],
    "wof:name":"Beverly Services",
    "wof:placetype":"venue"
},
  "geometry": {"coordinates":[-118.17119599999999,33.832963],"type":"Point"}
}