{
  "type": "Feature",
  "properties": {
    "addr:full":"7436 Mission Valley Rd San Diego CA 92108",
    "addr:housenumber":"7436",
    "addr:postcode":"92108",
    "addr:street":"Mission Valley Rd",
    "iso:country":"US",
    "sg:address":"7436 Mission Valley Rd",
    "sg:city":"San Diego",
    "sg:classifiers":[
        {
            "category":"Manufacturing",
            "subcategory":"Electronics",
            "type":"Manufacturing & Wholesale Goods"
        }
    ],
    "sg:phone":"+1 619 278 2000",
    "sg:postcode":"92108",
    "sg:province":"CA",
    "sg:tags":[
        "information",
        "solution",
        "to",
        "defense",
        "provides",
        "technology"
    ],
    "wof:name":"Titan Corporation",
    "wof:placetype":"venue"
},
  "geometry": {"coordinates":[-117.15782299999999,32.77917],"type":"Point"}
}