{
  "type": "Feature",
  "properties": {
    "addr:full":"12352 Viarna St Cerritos CA 90703",
    "addr:housenumber":"12352",
    "addr:postcode":"ca 90703",
    "addr:street":"Viarna St",
    "iso:country":"US",
    "sg:address":"12352 Viarna St",
    "sg:city":"Cerritos",
    "sg:classifiers":[
        {
            "category":"Retail",
            "subcategory":"Laundry & Dry Cleaning",
            "type":"Services"
        },
        {
            "category":"Building & Trades",
            "subcategory":"Cleaning & Sanitation",
            "type":"Services"
        },
        {
            "category":"Home & Garden",
            "subcategory":"Carpets & Floor Coverings",
            "type":"Retail Goods"
        }
    ],
    "sg:phone":"+1 562 860 4808",
    "sg:postcode":"90703",
    "sg:province":"CA",
    "sg:tags":[
        "cleaner",
        "rug",
        "carpeting"
    ],
    "wof:name":"Day-N-Nite Carpet Cleaning",
    "wof:placetype":"venue"
},
  "geometry": {"coordinates":[-118.068001,33.850498],"type":"Point"}
}