{
  "type": "Feature",
  "properties": {
    "iso:country":"US",
    "sg:address":"1551 Bishop St",
    "sg:city":"San Luis Obispo",
    "sg:classifiers":[
        {
            "category":"Health Services",
            "subcategory":"Doctor",
            "type":"Services"
        }
    ],
    "sg:phone":"+1 805 543 8492",
    "sg:postcode":"93401",
    "sg:province":"CA",
    "sg:tags":[
        "physician",
        "surgeon"
    ],
    "wof:name":"Darius Soleimany MD",
    "wof:placetype":"venue"
},
  "geometry": {"coordinates":[-120.647763,35.273291],"type":"Point"}
}