{
  "type": "Feature",
  "properties": {
    "addr:full":"PO Box 5064 San Mateo CA 94402",
    "addr:housenumber":"po",
    "addr:postcode":"94402",
    "addr:street":"Box 5064",
    "iso:country":"US",
    "sg:address":"PO Box 5064",
    "sg:city":"San Mateo",
    "sg:classifiers":[
        {
            "category":"Building & Trades",
            "subcategory":"Construction",
            "type":"Services"
        }
    ],
    "sg:phone":"+1 650 349 1717",
    "sg:postcode":"94402",
    "sg:province":"CA",
    "sg:tags":[
        "contractor"
    ],
    "wof:name":"A C Seigart Construction & Roofing",
    "wof:placetype":"venue"
},
  "geometry": {"coordinates":[-122.328003,37.551498],"type":"Point"}
}