{
  "type": "Feature",
  "properties": {
    "iso:country":"US",
    "sg:address":"28202 Cabot Rd",
    "sg:city":"Laguna Niguel",
    "sg:classifiers":[
        {
            "category":"Personal",
            "type":"Services"
        }
    ],
    "sg:phone":"+1 949 831 5777",
    "sg:postcode":"92677",
    "sg:province":"CA",
    "sg:tags":[
        "bankruptcy"
    ],
    "wof:name":"Winterbotham Parham Teeple",
    "wof:placetype":"venue"
},
  "geometry": {"coordinates":[-117.679034,33.551748],"type":"Point"}
}