{
  "type": "Feature",
  "properties": {
    "iso:country":"US",
    "sg:address":"3941 Ironwood Dr",
    "sg:city":"El Dorado Hills",
    "sg:classifiers":[
        {
            "category":"Building & Trades",
            "subcategory":"Landscaping Services",
            "type":"Services"
        }
    ],
    "sg:phone":"+1 916 941 9868",
    "sg:postcode":"95762",
    "sg:province":"CA",
    "sg:tags":[
        "designer",
        "landscape"
    ],
    "wof:name":"Outdoor Living Designs",
    "wof:placetype":"venue"
},
  "geometry": {"coordinates":[-121.06724800000001,38.673717],"type":"Point"}
}