{
  "type": "Feature",
  "properties": {
    "iso:country":"US",
    "sg:address":"1110 Melody Ln",
    "sg:city":"Roseville",
    "sg:classifiers":[
        {
            "category":"Organizations",
            "subcategory":"Community Association",
            "type":"Services"
        }
    ],
    "sg:phone":"+1 916 797 0169",
    "sg:postcode":"95678",
    "sg:province":"CA",
    "sg:tags":[
        "military"
    ],
    "wof:name":"American Legion",
    "wof:placetype":"venue"
},
  "geometry": {"coordinates":[-121.29085600000001,38.727854],"type":"Point"}
}