{
  "type": "Feature",
  "properties": {
    "iso:country":"US",
    "sg:address":"400 Chatsworth Dr",
    "sg:city":"San Fernando",
    "sg:classifiers":[
        {
            "category":"Building & Trades",
            "subcategory":"Electrical",
            "type":"Services"
        }
    ],
    "sg:phone":"+1 818 361 7774",
    "sg:postcode":"91340",
    "sg:province":"CA",
    "sg:tags":[
        "electrical",
        "contractor"
    ],
    "wof:name":"IBEW Local 11 Dist 4",
    "wof:placetype":"venue"
},
  "geometry": {"coordinates":[-118.441246,34.279246],"type":"Point"}
}