{
  "type": "Feature",
  "properties": {
    "addr:full":"246 Lorton Ave Burlingame CA 94010",
    "addr:housenumber":"246",
    "addr:postcode":"94010",
    "addr:street":"Lorton Ave",
    "iso:country":"US",
    "sg:address":"246 Lorton Ave",
    "sg:city":"Burlingame",
    "sg:classifiers":[
        {
            "category":"Bars & Pubs",
            "type":"Food & Drink"
        }
    ],
    "sg:phone":"+1 650 344 0284",
    "sg:postcode":"94010",
    "sg:province":"CA",
    "sg:tags":[
        "lounge",
        "cocktail"
    ],
    "sg:website":"www.paddyflynns.com",
    "wof:name":"Paddy Flynn's",
    "wof:placetype":"venue"
},
  "geometry": {"coordinates":[-122.34535099999999,37.578829],"type":"Point"}
}