{
  "type": "Feature",
  "properties": {
    "iso:country":"US",
    "sg:address":"9135 Alabama Ave",
    "sg:city":"Chatsworth",
    "sg:classifiers":[
        {
            "category":"Professional",
            "subcategory":"Art Services",
            "type":"Services"
        }
    ],
    "sg:phone":"+1 818 280 0833",
    "sg:postcode":"91311",
    "sg:province":"CA",
    "sg:tags":[
        "graphic",
        "designer"
    ],
    "wof:name":"K D 70 LLC",
    "wof:placetype":"venue"
},
  "geometry": {"coordinates":[-118.599855,34.238455],"type":"Point"}
}