{
  "type": "Feature",
  "properties": {
    "iso:country":"US",
    "sg:address":"952 Nosotros St",
    "sg:city":"Calexico",
    "sg:classifiers":[
        {
            "category":"Professional",
            "type":"Services"
        }
    ],
    "sg:phone":"+1 760 357 0141",
    "sg:postcode":"92231",
    "sg:province":"CA",
    "wof:name":"Virgen Boutique",
    "wof:placetype":"venue"
},
  "geometry": {"coordinates":[-115.518828,32.676561],"type":"Point"}
}