{
  "type": "Feature",
  "properties": {
    "addr:full":"5862 C St Chino CA 91710",
    "addr:housenumber":"5862",
    "addr:postcode":"91710",
    "addr:street":"C St",
    "iso:country":"US",
    "sg:address":"5862 C St",
    "sg:city":"Chino",
    "sg:classifiers":[
        {
            "category":"Education",
            "subcategory":"School",
            "type":"Public Place"
        }
    ],
    "sg:phone":"+1 909 627 9496",
    "sg:postcode":"91710",
    "sg:province":"CA",
    "sg:website":"www.chino.k12.ca.us",
    "wof:name":"El Rancho Elementary School",
    "wof:placetype":"venue"
},
  "geometry": {"coordinates":[-117.67625099999999,34.015677],"type":"Point"}
}