{
  "type": "Feature",
  "properties": {
    "iso:country":"US",
    "sg:address":"11206 Weddington St",
    "sg:city":"North Hollywood",
    "sg:classifiers":[
        {
            "category":"Communications",
            "type":"Services"
        }
    ],
    "sg:phone":"+1 818 506 5554",
    "sg:postcode":"91601",
    "sg:province":"CA",
    "sg:tags":[
        "web",
        "design"
    ],
    "wof:name":"La Digital Works Inc",
    "wof:placetype":"venue"
},
  "geometry": {"coordinates":[-118.375991,34.166862],"type":"Point"}
}