{
  "type": "Feature",
  "properties": {
    "iso:country":"US",
    "sg:address":"101 Monterey Blvd",
    "sg:city":"Culver City",
    "sg:classifiers":[
        {
            "category":"Professional",
            "subcategory":"Computer Services",
            "type":"Services"
        }
    ],
    "sg:phone":"+1 310 936 2833",
    "sg:postcode":"90254",
    "sg:province":"CA",
    "wof:name":"Prottus",
    "wof:placetype":"venue"
},
  "geometry": {"coordinates":[-118.396208,33.855253],"type":"Point"}
}