{
  "type": "Feature",
  "properties": {
    "addr:full":"1355 Sepulveda Blvd Torrance CA 90501",
    "addr:housenumber":"1355",
    "addr:postcode":"90501",
    "addr:street":"Sepulveda Blvd",
    "iso:country":"US",
    "sg:address":"1355 Sepulveda Blvd",
    "sg:city":"Torrance",
    "sg:classifiers":[
        {
            "category":"Shopping",
            "subcategory":"Bicycles & Sporting Goods",
            "type":"Retail Goods"
        }
    ],
    "sg:phone":"+1 310 326 4797",
    "sg:postcode":"90501",
    "sg:province":"CA",
    "sg:tags":[
        "equipment",
        "golf",
        "supply"
    ],
    "wof:name":"Plaza Golf At Mullcan",
    "wof:placetype":"venue"
},
  "geometry": {"coordinates":[-118.29935500000001,33.81351],"type":"Point"}
}