{
  "type": "Feature",
  "properties": {
    "addr:full":"27865 Berwick Dr Carmel CA 93923",
    "addr:housenumber":"27865",
    "addr:postcode":"93923",
    "addr:street":"Berwick Dr",
    "iso:country":"US",
    "sg:address":"27865 Berwick Dr",
    "sg:city":"Carmel",
    "sg:classifiers":[
        {
            "category":"Professional",
            "subcategory":"Research",
            "type":"Services"
        }
    ],
    "sg:phone":"+1 831 624 0303",
    "sg:postcode":"93923",
    "sg:province":"CA",
    "sg:website":"www.adamsmediaresearch.com",
    "wof:name":"Adams Media Research",
    "wof:placetype":"venue"
},
  "geometry": {"coordinates":[-121.808589,36.521957],"type":"Point"}
}