{
  "type": "Feature",
  "properties": {
    "iso:country":"US",
    "sg:address":"14700 Manzanita Rd",
    "sg:city":"Beaumont",
    "sg:classifiers":[
        {
            "category":"Social Services",
            "subcategory":"Child Care",
            "type":"Services"
        }
    ],
    "sg:phone":"+1 951 845 6737",
    "sg:postcode":"92223",
    "sg:province":"CA",
    "sg:tags":[
        "day"
    ],
    "wof:name":"Childhelp USA",
    "wof:placetype":"venue"
},
  "geometry": {"coordinates":[-116.968002,33.918598],"type":"Point"}
}