{
  "type": "Feature",
  "properties": {
    "addr:full":"6756 Central Ave Newark CA 94560",
    "addr:housenumber":"6756",
    "addr:postcode":"94560",
    "addr:street":"Central Ave",
    "iso:country":"US",
    "sg:address":"6756 Central Ave",
    "sg:city":"Newark",
    "sg:classifiers":[
        {
            "category":"Home & Garden",
            "subcategory":"Building Materials",
            "type":"Retail Goods"
        },
        {
            "category":"Building & Trades",
            "subcategory":"Construction",
            "type":"Services"
        },
        {
            "category":"Manufacturing",
            "subcategory":"Building Materials",
            "type":"Manufacturing & Wholesale Goods"
        }
    ],
    "sg:phone":"+1 510 745 9692",
    "sg:postcode":"94560",
    "sg:province":"CA",
    "sg:tags":[
        "bathroom",
        "altering",
        "top",
        "counter",
        "marble-cultured",
        "cabinet",
        "accessory",
        "fixtures",
        "contractor",
        "remodeling"
    ],
    "sg:website":"http://www.tcmarble.com",
    "wof:name":"Remodeling By TCM Inc.",
    "wof:placetype":"venue"
},
  "geometry": {"coordinates":[-122.027354,37.526794],"type":"Point"}
}