{
  "type": "Feature",
  "properties": {
    "iso:country":"US",
    "sg:address":"27266 Camp Plenty Rd",
    "sg:city":"Canyon Country",
    "sg:classifiers":[
        {
            "category":"Retail",
            "subcategory":"Auto Repair",
            "type":"Services"
        }
    ],
    "sg:phone":"+1 661 298 1290",
    "sg:postcode":"91351",
    "sg:province":"CA",
    "sg:tags":[
        "repairing",
        "automobile"
    ],
    "wof:name":"Jeep Shop",
    "wof:placetype":"venue"
},
  "geometry": {"coordinates":[-118.475645,34.416236],"type":"Point"}
}