{
  "type": "Feature",
  "properties": {
    "iso:country":"US",
    "sg:address":"498 14th St",
    "sg:city":"San Francisco",
    "sg:classifiers":[
        {
            "category":"Retail",
            "subcategory":"Laundry & Dry Cleaning",
            "type":"Services"
        }
    ],
    "sg:postcode":"94103",
    "sg:province":"CA",
    "wof:name":"Wash-Dry",
    "wof:placetype":"venue"
},
  "geometry": {"coordinates":[-122.424351,37.768051],"type":"Point"}
}