{
  "type": "Feature",
  "properties": {
    "addr:full":"2837 Rawson Street Oakland CA 94619",
    "addr:postcode":"2837;94619",
    "addr:street":"Rawson Street",
    "iso:country":"US",
    "sg:address":"2837 Rawson Street",
    "sg:city":"Oakland",
    "sg:classifiers":[
        {
            "category":"Arts & Performance",
            "subcategory":"Arts Center",
            "type":"Entertainment"
        },
        {
            "category":"Education",
            "subcategory":"Special Training",
            "type":"Public Place"
        },
        {
            "category":"Communications",
            "type":"Services"
        }
    ],
    "sg:phone":"+1 510 532 1531",
    "sg:postcode":"94619",
    "sg:province":"CA",
    "sg:tags":[
        "recording",
        "rehearsal",
        "performing",
        "studio",
        "adult"
    ],
    "sg:website":"www.kailaflexer.com",
    "wof:name":"Kaila Flexer - Violin Lessons",
    "wof:placetype":"venue"
},
  "geometry": {"coordinates":[-122.19580000000001,37.778199],"type":"Point"}
}