{
  "type": "Feature",
  "properties": {
    "iso:country":"US",
    "sg:address":"2125 S El Camino Real",
    "sg:city":"Oceanside",
    "sg:classifiers":[
        {
            "category":"Health Services",
            "subcategory":"Doctor",
            "type":"Services"
        }
    ],
    "sg:phone":"+1 760 730 5900",
    "sg:postcode":"92054",
    "sg:province":"CA",
    "wof:name":"Psych Barent Mynderes",
    "wof:placetype":"venue"
},
  "geometry": {"coordinates":[-117.328369,33.189858],"type":"Point"}
}