{
  "type": "Feature",
  "properties": {
    "addr:full":"14330 Memory Ln Clearlake CA 95422",
    "addr:housenumber":"14330",
    "addr:postcode":"95422",
    "addr:street":"Memory Ln",
    "iso:country":"US",
    "sg:address":"14330 Memory Ln",
    "sg:city":"Clearlake",
    "sg:classifiers":[
        {
            "category":"Organizations",
            "subcategory":"Religious Organization",
            "type":"Services"
        }
    ],
    "sg:phone":"+1 707 994 5683",
    "sg:postcode":"95422",
    "sg:province":"CA",
    "sg:tags":[
        "church"
    ],
    "wof:name":"Calvary Chapel Of Clearlake",
    "wof:placetype":"venue"
},
  "geometry": {"coordinates":[-122.644902,38.962507],"type":"Point"}
}