{
  "type": "Feature",
  "properties": {
    "addr:full":"4713 1st St Pleasanton CA 94566",
    "addr:housenumber":"4713",
    "addr:postcode":"94566",
    "addr:street":"1St St",
    "iso:country":"US",
    "sg:address":"4713 1st St",
    "sg:city":"Pleasanton",
    "sg:classifiers":[
        {
            "category":"Restaurant",
            "type":"Food & Drink"
        }
    ],
    "sg:menulink":"http://www.allmenus.com/ca/livermore-pleasanton/47470-me--mai/menu/",
    "sg:phone":"+1 925 417 2001",
    "sg:postcode":"94566",
    "sg:province":"CA",
    "sg:tags":[
        "american"
    ],
    "wof:name":"Me & Mai",
    "wof:placetype":"venue"
},
  "geometry": {"coordinates":[-121.876104,37.657717],"type":"Point"}
}