{
  "type": "Feature",
  "properties": {
    "addr:full":"2125 Centerpointe Pkwy Santa Maria CA 93455",
    "addr:housenumber":"2125",
    "addr:postcode":"93455",
    "addr:street":"Centerpointe Pkwy",
    "iso:country":"US",
    "sg:address":"2125 Centerpointe Pkwy",
    "sg:city":"Santa Maria",
    "sg:classifiers":[
        {
            "category":"Health Services",
            "subcategory":"Doctor",
            "type":"Services"
        }
    ],
    "sg:phone":"+1 805 739 8701",
    "sg:postcode":"93455",
    "sg:province":"CA",
    "wof:name":"Reffigee Lester MD",
    "wof:placetype":"venue"
},
  "geometry": {"coordinates":[-120.42854,34.922223],"type":"Point"}
}