{
  "type": "Feature",
  "properties": {
    "iso:country":"US",
    "sg:address":"1005 Monterey St",
    "sg:city":"San Luis Obispo",
    "sg:classifiers":[
        {
            "category":"Restaurant",
            "type":"Food & Drink"
        }
    ],
    "sg:phone":"+1 805 541 5999",
    "sg:postcode":"93401",
    "sg:province":"CA",
    "wof:name":"Hudson's Grill",
    "wof:placetype":"venue"
},
  "geometry": {"coordinates":[-120.659946,35.282485],"type":"Point"}
}