{
  "type": "Feature",
  "properties": {
    "iso:country":"US",
    "sg:address":"1860 Silverwood Dr",
    "sg:city":"Concord",
    "sg:classifiers":[
        {
            "category":"Government",
            "subcategory":"Office",
            "type":"Public Place"
        }
    ],
    "sg:phone":"+1 925 646 5733",
    "sg:postcode":"94519",
    "sg:province":"CA",
    "sg:tags":[
        "county",
        "program",
        "health"
    ],
    "wof:name":"Public Health Svc",
    "wof:placetype":"venue"
},
  "geometry": {"coordinates":[-122.00318900000001,37.985868],"type":"Point"}
}