{
  "type": "Feature",
  "properties": {
    "iso:country":"US",
    "sg:address":"1223 University Ave",
    "sg:city":"Riverside",
    "sg:classifiers":[
        {
            "category":"Government",
            "subcategory":"Court House",
            "type":"Public Place"
        }
    ],
    "sg:phone":"+1 951 369 6644",
    "sg:postcode":"92507",
    "sg:province":"CA",
    "sg:tags":[
        "legislator"
    ],
    "wof:name":"Assembly, California",
    "wof:placetype":"venue"
},
  "geometry": {"coordinates":[-117.338381,33.975739],"type":"Point"}
}