{
  "type": "Feature",
  "properties": {
    "iso:country":"US",
    "sg:address":"354 Umbarger Rd Ste 7",
    "sg:city":"San Jose",
    "sg:classifiers":[
        {
            "category":"Bakery",
            "type":"Food & Drink"
        }
    ],
    "sg:phone":"+1 408 629 0363",
    "sg:postcode":"95111",
    "sg:province":"CA",
    "wof:name":"Le Croissant",
    "wof:placetype":"venue"
},
  "geometry": {"coordinates":[-121.846001,37.299099],"type":"Point"}
}