{
  "type": "Feature",
  "properties": {
    "addr:full":"2891 W 120th St Hawthorne CA 90250",
    "addr:housenumber":"2891",
    "addr:postcode":"90250",
    "addr:street":"W 120Th St",
    "iso:country":"US",
    "sg:address":"2891 W 120th St",
    "sg:city":"Hawthorne",
    "sg:classifiers":[
        {
            "category":"Fast Food",
            "type":"Food & Drink"
        }
    ],
    "sg:phone":"+1 323 777 2098",
    "sg:postcode":"90250",
    "sg:province":"CA",
    "sg:tags":[
        "burger"
    ],
    "sg:website":"wendys.com",
    "wof:name":"Wendy's",
    "wof:placetype":"venue"
},
  "geometry": {"coordinates":[-118.32518399999999,33.923747],"type":"Point"}
}