{
  "type": "Feature",
  "properties": {
    "iso:country":"US",
    "sg:address":"4409 Hackberry Ln",
    "sg:city":"Carmichael",
    "sg:classifiers":[
        {
            "category":"Home & Garden",
            "subcategory":"Furniture",
            "type":"Retail Goods"
        }
    ],
    "sg:phone":"+1 916 973 1064",
    "sg:postcode":"95608",
    "sg:province":"CA",
    "wof:name":"Klismos Furniture Trading Inc",
    "wof:placetype":"venue"
},
  "geometry": {"coordinates":[-121.332159,38.642673],"type":"Point"}
}