{
  "type": "Feature",
  "properties": {
    "addr:full":"1211 N Brighton St Burbank CA 91506",
    "addr:housenumber":"1211",
    "addr:postcode":"91506",
    "addr:street":"N Brighton St",
    "iso:country":"US",
    "sg:address":"1211 N Brighton St",
    "sg:city":"Burbank",
    "sg:classifiers":[
        {
            "category":"Place Of Worship",
            "type":"Public Place"
        }
    ],
    "sg:phone":"+1 818 845 5302",
    "sg:postcode":"91506",
    "sg:province":"CA",
    "sg:tags":[
        "church"
    ],
    "wof:name":"Home Missions Church Inc",
    "wof:placetype":"venue"
},
  "geometry": {"coordinates":[-118.337222,34.179065],"type":"Point"}
}