{
  "type": "Feature",
  "properties": {
    "iso:country":"US",
    "sg:address":"15031 Rockfold Dr",
    "sg:city":"Hacienda Heights",
    "sg:classifiers":[
        {
            "category":"Professional",
            "type":"Services"
        }
    ],
    "sg:phone":"+1 626 333 4783",
    "sg:postcode":"91745",
    "sg:province":"CA",
    "wof:name":"Ann Petros",
    "wof:placetype":"venue"
},
  "geometry": {"coordinates":[-117.983868,34.004856],"type":"Point"}
}