{
  "type": "Feature",
  "properties": {
    "iso:country":"US",
    "sg:address":"5016 York Blvd",
    "sg:city":"Los Angeles",
    "sg:classifiers":[
        {
            "category":"Health Services",
            "subcategory":"Doctor",
            "type":"Services"
        }
    ],
    "sg:phone":"+1 323 254 1831",
    "sg:postcode":"90042",
    "sg:province":"CA",
    "sg:tags":[
        "dentist"
    ],
    "wof:name":"Highland Park Dental Clinic",
    "wof:placetype":"venue"
},
  "geometry": {"coordinates":[-118.205063,34.121062],"type":"Point"}
}