{
  "type": "Feature",
  "properties": {
    "addr:full":"8323 13th Ave Hanford CA 93230",
    "addr:housenumber":"8323",
    "addr:postcode":"ca 93230",
    "addr:street":"13Th Ave",
    "iso:country":"US",
    "sg:address":"8323 13th Ave",
    "sg:city":"Hanford",
    "sg:classifiers":[
        {
            "category":"Farming",
            "subcategory":"Dairy Farm",
            "type":"Manufacturing & Wholesale Goods"
        }
    ],
    "sg:phone":"+1 559 582 6577",
    "sg:postcode":"93230",
    "sg:province":"CA",
    "wof:name":"Jmcs Dairy",
    "wof:placetype":"venue"
},
  "geometry": {"coordinates":[-119.690939,36.355655],"type":"Point"}
}