{
  "type": "Feature",
  "properties": {
    "iso:country":"US",
    "sg:address":"22910 Crenshaw Blvd",
    "sg:city":"Torrance",
    "sg:classifiers":[
        {
            "category":"Health Services",
            "subcategory":"Doctor",
            "type":"Services"
        }
    ],
    "sg:phone":"+1 310 831 8127",
    "sg:postcode":"90505",
    "sg:province":"CA",
    "sg:tags":[
        "physician",
        "surgeon"
    ],
    "wof:name":"Peninsula Pain Management Clnc",
    "wof:placetype":"venue"
},
  "geometry": {"coordinates":[-118.32794800000001,33.818125],"type":"Point"}
}