{
  "type": "Feature",
  "properties": {
    "addr:full":"37640 Cedar Blvd Newark CA 94560",
    "addr:housenumber":"37640",
    "addr:postcode":"94560",
    "addr:street":"Cedar Blvd",
    "iso:country":"US",
    "sg:address":"37640 Cedar Blvd",
    "sg:city":"Newark",
    "sg:classifiers":[
        {
            "category":"Retail",
            "subcategory":"Auto Repair",
            "type":"Services"
        }
    ],
    "sg:phone":"+1 510 797 8592",
    "sg:postcode":"94560",
    "sg:province":"CA",
    "sg:tags":[
        "repairing",
        "automobile"
    ],
    "wof:name":"Kenco Automotive",
    "wof:placetype":"venue"
},
  "geometry": {"coordinates":[-122.017449,37.536359],"type":"Point"}
}