{
  "type": "Feature",
  "properties": {
    "addr:full":"54730 N Circle Dr Idyllwild CA 92549",
    "addr:housenumber":"54730",
    "addr:postcode":"92549",
    "addr:street":"N Circle Dr",
    "iso:country":"US",
    "sg:address":"54730 N Circle Dr",
    "sg:city":"Idyllwild",
    "sg:classifiers":[
        {
            "category":"Building & Trades",
            "subcategory":"Plumbing",
            "type":"Services"
        }
    ],
    "sg:phone":"+1 951 659 4328",
    "sg:postcode":"92549",
    "sg:province":"CA",
    "sg:tags":[
        "ventilating",
        "contractor"
    ],
    "wof:name":"Idyllwild Heating & Cooling",
    "wof:placetype":"venue"
},
  "geometry": {"coordinates":[-116.706569,33.751666],"type":"Point"}
}