{
  "type": "Feature",
  "properties": {
    "iso:country":"US",
    "sg:address":"2190 White Ln",
    "sg:city":"Bakersfield",
    "sg:classifiers":[
        {
            "category":"Restaurant",
            "type":"Food & Drink"
        }
    ],
    "sg:phone":"+1 661 833 3892",
    "sg:postcode":"93304",
    "sg:province":"CA",
    "sg:tags":[
        "shop",
        "coffee"
    ],
    "wof:name":"Winchell's Donut House",
    "wof:placetype":"venue"
},
  "geometry": {"coordinates":[-119.028644,35.317744],"type":"Point"}
}