{
  "type": "Feature",
  "properties": {
    "addr:full":"1948 Colfax St Concord CA 94520",
    "addr:housenumber":"1948",
    "addr:postcode":"94520",
    "addr:street":"Colfax St",
    "iso:country":"US",
    "sg:address":"1948 Colfax St",
    "sg:city":"Concord",
    "sg:classifiers":[
        {
            "category":"Government",
            "subcategory":"Office",
            "type":"Public Place"
        }
    ],
    "sg:phone":"+1 925 671 3123",
    "sg:postcode":"94520",
    "sg:province":"CA",
    "sg:tags":[
        "village"
    ],
    "wof:name":"Ticket Center",
    "wof:placetype":"venue"
},
  "geometry": {"coordinates":[-122.032113,37.978081],"type":"Point"}
}