{
  "type": "Feature",
  "properties": {
    "iso:country":"US",
    "sg:address":"14892 Freeman Ave",
    "sg:city":"San Jose",
    "sg:classifiers":[
        {
            "category":"Building & Trades",
            "subcategory":"Plumbing",
            "type":"Services"
        }
    ],
    "sg:phone":"+1 650 566 8323",
    "sg:postcode":"95127",
    "sg:province":"CA",
    "sg:tags":[
        "plumbing",
        "contractor"
    ],
    "wof:name":"Alert Plumbing",
    "wof:placetype":"venue"
},
  "geometry": {"coordinates":[-121.832633,37.391924],"type":"Point"}
}