{
  "type": "Feature",
  "properties": {
    "iso:country":"US",
    "sg:address":"2326 Mark West Springs Rd",
    "sg:city":"Santa Rosa",
    "sg:classifiers":[
        {
            "category":"Professional",
            "type":"Services"
        }
    ],
    "sg:phone":"+1 707 257 1338",
    "sg:postcode":"95404",
    "sg:province":"CA",
    "wof:name":"California Directors Thea",
    "wof:placetype":"venue"
},
  "geometry": {"coordinates":[-122.720404,38.546824],"type":"Point"}
}