{
  "type": "Feature",
  "properties": {
    "iso:country":"US",
    "sg:address":"124 S E St",
    "sg:city":"Madera",
    "sg:classifiers":[
        {
            "category":"Farming",
            "subcategory":"Farm & Veterinary Services",
            "type":"Manufacturing & Wholesale Goods"
        }
    ],
    "sg:phone":"+1 559 674 0041",
    "sg:postcode":"93638",
    "sg:province":"CA",
    "sg:tags":[
        "industrial",
        "management",
        "motorcycle"
    ],
    "wof:name":"Honda Suzuki Of Madera",
    "wof:placetype":"venue"
},
  "geometry": {"coordinates":[-120.05935599999999,36.961635],"type":"Point"}
}