{
  "type": "Feature",
  "properties": {
    "iso:country":"US",
    "sg:address":"1717 S State College Blvd",
    "sg:city":"Anaheim",
    "sg:phone":"+1 714 704 1490",
    "sg:postcode":"92806",
    "sg:province":"CA",
    "sg:tags":[
        "product",
        "petroleum"
    ],
    "wof:name":"Pennzoil - Quaker State Co",
    "wof:placetype":"venue"
},
  "geometry": {"coordinates":[-117.889196,33.804126],"type":"Point"}
}