{
  "type": "Feature",
  "properties": {
    "addr:full":"2124 Parker St Apt 20 Berkeley CA 94704",
    "addr:housenumber":"2124;20",
    "addr:postcode":"94704",
    "addr:street":"Parker St Apt",
    "iso:country":"US",
    "sg:address":"2124 Parker St Apt 20",
    "sg:city":"Berkeley",
    "sg:classifiers":[
        {
            "category":"Retail",
            "subcategory":"Laundry & Dry Cleaning",
            "type":"Services"
        },
        {
            "category":"Building & Trades",
            "subcategory":"Cleaning & Sanitation",
            "type":"Services"
        }
    ],
    "sg:phone":"+1 510 502 9126",
    "sg:postcode":"94704",
    "sg:province":"CA",
    "sg:tags":[
        "cleaner",
        "house"
    ],
    "wof:name":"Sauber Cleaning Company",
    "wof:placetype":"venue"
},
  "geometry": {"coordinates":[-122.26658999999999,37.862222],"type":"Point"}
}