{
  "type": "Feature",
  "properties": {
    "iso:country":"US",
    "sg:address":"2090 Fortune Dr",
    "sg:city":"San Jose",
    "sg:classifiers":[
        {
            "category":"Professional",
            "subcategory":"Business Services",
            "type":"Services"
        }
    ],
    "sg:phone":"+1 510 468 9822",
    "sg:postcode":"95131",
    "sg:province":"CA",
    "sg:tags":[
        "notary"
    ],
    "wof:name":"By The Book Notary Svc",
    "wof:placetype":"venue"
},
  "geometry": {"coordinates":[-121.890823,37.40079],"type":"Point"}
}