{
  "type": "Feature",
  "properties": {
    "addr:full":"24300 San Fernando Rd Newhall CA 91321",
    "addr:housenumber":"24300",
    "addr:postcode":"91321",
    "addr:street":"San Fernando Rd",
    "iso:country":"US",
    "sg:address":"24300 San Fernando Rd",
    "sg:city":"Newhall",
    "sg:classifiers":[
        {
            "category":"Professional",
            "subcategory":"Accounting & Tax Preparation",
            "type":"Services"
        }
    ],
    "sg:phone":"+1 661 254 2809",
    "sg:postcode":"91321",
    "sg:province":"CA",
    "sg:tags":[
        "return",
        "filing"
    ],
    "wof:name":"Evelyn Escoto Income Tax Svc",
    "wof:placetype":"venue"
},
  "geometry": {"coordinates":[-118.52779200000001,34.378615],"type":"Point"}
}