{
  "type": "Feature",
  "properties": {
    "iso:country":"US",
    "sg:address":"2108 Lewis Rd",
    "sg:city":"Wheatland",
    "sg:classifiers":[
        {
            "category":"Retail",
            "subcategory":"Repair Shop",
            "type":"Services"
        }
    ],
    "sg:phone":"+1 530 633 4639",
    "sg:postcode":"95692",
    "sg:province":"CA",
    "sg:tags":[
        "welding"
    ],
    "wof:name":"Bess Welding",
    "wof:placetype":"venue"
},
  "geometry": {"coordinates":[-121.448738,39.018978],"type":"Point"}
}