{
  "type": "Feature",
  "properties": {
    "addr:full":"12782 Homeridge Ln Chino Hills CA 91709",
    "addr:housenumber":"12782",
    "addr:postcode":"91709",
    "addr:street":"Homeridge Ln",
    "iso:country":"US",
    "sg:address":"12782 Homeridge Ln",
    "sg:city":"Chino Hills",
    "sg:classifiers":[
        {
            "category":"Professional",
            "type":"Services"
        }
    ],
    "sg:phone":"+1 909 591 4656",
    "sg:postcode":"91709",
    "sg:province":"CA",
    "sg:tags":[
        "writer"
    ],
    "wof:name":"Papyrus Books & Training",
    "wof:placetype":"venue"
},
  "geometry": {"coordinates":[-117.756524,34.021013],"type":"Point"}
}