{
  "type": "Feature",
  "properties": {
    "iso:country":"US",
    "sg:address":"2547 8th St",
    "sg:city":"Berkeley",
    "sg:classifiers":[
        {
            "category":"Manufacturing",
            "subcategory":"Glass & Minerals",
            "type":"Manufacturing & Wholesale Goods"
        }
    ],
    "sg:phone":"+1 510 649 1977",
    "sg:postcode":"94710",
    "sg:province":"CA",
    "sg:tags":[
        "mfg"
    ],
    "wof:name":"Lee Miltier",
    "wof:placetype":"venue"
},
  "geometry": {"coordinates":[-122.29275699999999,37.860042],"type":"Point"}
}