{
  "type": "Feature",
  "properties": {
    "addr:full":"23622 Calabasas Rd, Ste 320, Calabasas CA 91302",
    "addr:housenumber":"23622",
    "addr:postcode":"91302",
    "addr:street":"Calabasas Rd Ste 320",
    "iso:country":"US",
    "sg:address":"23622 Calabasas Rd, Ste 320,",
    "sg:city":"Calabasas",
    "sg:classifiers":[
        {
            "category":"Banks & Credit Unions",
            "subcategory":"Investment Brokerage",
            "type":"Services"
        },
        {
            "category":"Banks & Credit Unions",
            "subcategory":"Financial Services",
            "type":"Services"
        }
    ],
    "sg:phone":"+1 818 227 9780",
    "sg:postcode":"91302",
    "sg:province":"CA",
    "sg:tags":[
        "investing",
        "advising"
    ],
    "sg:website":"www.ameripriseadvisors.com/jason...",
    "wof:name":"Jason Semeleng - Ameriprise Financial Advisor",
    "wof:placetype":"venue"
},
  "geometry": {"coordinates":[-118.64154499999999,34.155974],"type":"Point"}
}