{
  "type": "Feature",
  "properties": {
    "addr:full":"5100 El Paraiso Ave Sacramento CA 95824",
    "addr:housenumber":"5100",
    "addr:postcode":"95824",
    "addr:street":"El Paraiso Ave",
    "iso:country":"US",
    "sg:address":"5100 El Paraiso Ave",
    "sg:city":"Sacramento",
    "sg:classifiers":[
        {
            "category":"Education",
            "subcategory":"School",
            "type":"Public Place"
        }
    ],
    "sg:phone":"+1 916 433 5440",
    "sg:postcode":"95824",
    "sg:province":"CA",
    "sg:tags":[
        "high",
        "middle",
        "elementary"
    ],
    "wof:name":"Wire Clayton B Elementary School",
    "wof:placetype":"venue"
},
  "geometry": {"coordinates":[-121.44699900000001,38.513699],"type":"Point"}
}