{
  "type": "Feature",
  "properties": {
    "addr:full":"14701 E 14th St San Leandro CA 94578",
    "addr:housenumber":"14701",
    "addr:postcode":"94578",
    "addr:street":"E 14Th St",
    "iso:country":"US",
    "sg:address":"14701 E 14th St",
    "sg:city":"San Leandro",
    "sg:classifiers":[
        {
            "category":"Restaurant",
            "type":"Food & Drink"
        }
    ],
    "sg:menulink":"http://www.allmenus.com/ca/hayward/54345-ozeki-sushi--teriyaki/menu/",
    "sg:phone":"+1 510 614 8300",
    "sg:postcode":"94578",
    "sg:province":"CA",
    "sg:tags":[
        "japanese",
        "asian"
    ],
    "wof:name":"Ozeki Sushi & Teriyaki",
    "wof:placetype":"venue"
},
  "geometry": {"coordinates":[-122.134249,37.709193],"type":"Point"}
}