{
  "type": "Feature",
  "properties": {
    "iso:country":"US",
    "sg:address":"7707 N Carnegie Ave",
    "sg:city":"Fresno",
    "sg:classifiers":[
        {
            "category":"Building & Trades",
            "subcategory":"Landscaping Services",
            "type":"Services"
        }
    ],
    "sg:phone":"+1 559 274 9179",
    "sg:postcode":"93722",
    "sg:province":"CA",
    "wof:name":"Thomas Lawn Service",
    "wof:placetype":"venue"
},
  "geometry": {"coordinates":[-119.89304199999999,36.846268],"type":"Point"}
}