{
  "type": "Feature",
  "properties": {
    "iso:country":"US",
    "sg:address":"853 N Mountain Ave",
    "sg:city":"Ontario",
    "sg:classifiers":[
        {
            "category":"Arena",
            "subcategory":"Sports Club",
            "type":"Entertainment"
        }
    ],
    "sg:phone":"+1 909 467 5648",
    "sg:postcode":"91762",
    "sg:province":"CA",
    "sg:tags":[
        "soccer"
    ],
    "wof:name":"Ontario Wings",
    "wof:placetype":"venue"
},
  "geometry": {"coordinates":[-117.67016,34.072457],"type":"Point"}
}