{
  "type": "Feature",
  "properties": {
    "addr:full":"6919 Lankershim Blvd North Hollywood CA 91605",
    "addr:housenumber":"6919",
    "addr:postcode":"91605",
    "addr:street":"Lankershim Blvd",
    "iso:country":"US",
    "sg:address":"6919 Lankershim Blvd",
    "sg:city":"North Hollywood",
    "sg:classifiers":[
        {
            "category":"Manufacturing",
            "subcategory":"Apparel",
            "type":"Manufacturing & Wholesale Goods"
        }
    ],
    "sg:phone":"+1 818 764 5566",
    "sg:postcode":"91605",
    "sg:province":"CA",
    "sg:tags":[
        "sewing",
        "contractor"
    ],
    "wof:name":"Mimi Sportswear Inc",
    "wof:placetype":"venue"
},
  "geometry": {"coordinates":[-118.38777899999999,34.197567],"type":"Point"}
}