{
  "type": "Feature",
  "properties": {
    "addr:full":"1101 Pacific Ave Ste E Santa Cruz CA 95060",
    "addr:housenumber":"1101",
    "addr:postcode":"95060",
    "addr:street":"Pacific Ave Ste E",
    "iso:country":"US",
    "sg:address":"1101 Pacific Ave Ste E",
    "sg:city":"Santa Cruz",
    "sg:classifiers":[
        {
            "category":"Shopping",
            "subcategory":"Optician",
            "type":"Retail Goods"
        }
    ],
    "sg:phone":"+1 831 466 3937",
    "sg:postcode":"95060",
    "sg:province":"CA",
    "sg:tags":[
        "eyewear"
    ],
    "sg:website":"www.eyeqsantacruz.com",
    "wof:name":"Eye Q",
    "wof:placetype":"venue"
},
  "geometry": {"coordinates":[-122.02589399999999,36.971908],"type":"Point"}
}