{
  "type": "Feature",
  "properties": {
    "addr:full":"7626 Hollywood Blvd West Hollywood CA 90046",
    "addr:housenumber":"7626",
    "addr:postcode":"90046",
    "addr:street":"Hollywood Blvd",
    "iso:country":"US",
    "sg:address":"7626 Hollywood Blvd",
    "sg:city":"West Hollywood",
    "sg:classifiers":[
        {
            "category":"Shopping",
            "subcategory":"Music",
            "type":"Retail Goods"
        }
    ],
    "sg:phone":"+1 323 848 8838",
    "sg:postcode":"90046",
    "sg:province":"CA",
    "sg:tags":[
        "video",
        "disc",
        "tape",
        "cassette"
    ],
    "wof:name":"Russian Video Books & Gifts",
    "wof:placetype":"venue"
},
  "geometry": {"coordinates":[-118.35562899999999,34.10159],"type":"Point"}
}