{
  "type": "Feature",
  "properties": {
    "addr:full":"960 Ferguson Rd Sebastopol CA 95472",
    "addr:housenumber":"960",
    "addr:postcode":"95472",
    "addr:street":"Ferguson Rd",
    "iso:country":"US",
    "sg:address":"960 Ferguson Rd",
    "sg:city":"Sebastopol",
    "sg:classifiers":[
        {
            "category":"Building & Trades",
            "subcategory":"Construction",
            "type":"Services"
        }
    ],
    "sg:phone":"+1 707 829 9577",
    "sg:postcode":"95472",
    "sg:province":"CA",
    "sg:tags":[
        "interior",
        "design"
    ],
    "wof:name":"Shoestring Design",
    "wof:placetype":"venue"
},
  "geometry": {"coordinates":[-122.870003,38.407001],"type":"Point"}
}