{
  "type": "Feature",
  "properties": {
    "addr:full":"11508 Tarron Ave Hawthorne CA 90250",
    "addr:housenumber":"11508",
    "addr:postcode":"90250",
    "addr:street":"Tarron Ave",
    "iso:country":"US",
    "sg:address":"11508 Tarron Ave",
    "sg:city":"Hawthorne",
    "sg:classifiers":[
        {
            "category":"Health Services",
            "subcategory":"Chiropractor",
            "type":"Services"
        }
    ],
    "sg:phone":"+1 323 779 8271",
    "sg:postcode":"90250",
    "sg:province":"CA",
    "sg:tags":[
        "chiropractic"
    ],
    "wof:name":"Harris Richardson Family Chi",
    "wof:placetype":"venue"
},
  "geometry": {"coordinates":[-118.314308,33.929925],"type":"Point"}
}