{
  "type": "Feature",
  "properties": {
    "iso:country":"US",
    "sg:address":"3153 W Pico Blvd",
    "sg:city":"Los Angeles",
    "sg:classifiers":[
        {
            "category":"Retail",
            "subcategory":"Auto Repair",
            "type":"Services"
        }
    ],
    "sg:phone":"+1 323 737 7633",
    "sg:postcode":"90019",
    "sg:province":"CA",
    "sg:tags":[
        "body",
        "automobile",
        "painting"
    ],
    "wof:name":"One Day Paint & Body Ctr",
    "wof:placetype":"venue"
},
  "geometry": {"coordinates":[-118.311187,34.047261],"type":"Point"}
}