{
  "type": "Feature",
  "properties": {
    "iso:country":"US",
    "sg:address":"2565 Cam del Rio S",
    "sg:city":"San Diego",
    "sg:classifiers":[
        {
            "category":"Professional",
            "subcategory":"Lawyer & Legal Services",
            "type":"Services"
        }
    ],
    "sg:phone":"+1 619 321 0402",
    "sg:postcode":"92108",
    "sg:province":"CA",
    "sg:tags":[
        "attorney"
    ],
    "wof:name":"Vin Casiano Law Offices",
    "wof:placetype":"venue"
},
  "geometry": {"coordinates":[-117.137528,32.769471],"type":"Point"}
}