{
  "type": "Feature",
  "properties": {
    "iso:country":"US",
    "sg:address":"6719 Somerset Blvd",
    "sg:city":"Paramount",
    "sg:classifiers":[
        {
            "category":"Education",
            "subcategory":"Preschool",
            "type":"Public Place"
        },
        {
            "category":"Education",
            "subcategory":"School",
            "type":"Public Place"
        }
    ],
    "sg:phone":"+1 310 933 0732",
    "sg:postcode":"90723",
    "sg:province":"CA",
    "sg:tags":[
        "elementary"
    ],
    "wof:name":"CDI Head Start",
    "wof:placetype":"venue"
},
  "geometry": {"coordinates":[-118.180556,33.89647],"type":"Point"}
}