{
  "type": "Feature",
  "properties": {
    "addr:full":"2740 Hillcrest Dr Cameron Park CA 95682",
    "addr:housenumber":"2740",
    "addr:postcode":"95682",
    "addr:street":"Hillcrest Dr",
    "iso:country":"US",
    "sg:address":"2740 Hillcrest Dr",
    "sg:city":"Cameron Park",
    "sg:classifiers":[
        {
            "category":"Shopping",
            "subcategory":"Stationery & Office Supplies",
            "type":"Retail Goods"
        }
    ],
    "sg:phone":"+1 530 672 0147",
    "sg:postcode":"95682",
    "sg:province":"CA",
    "sg:tags":[
        "rubber",
        "stamp",
        "plastic"
    ],
    "wof:name":"Stampin'Up-Demonstrator",
    "wof:placetype":"venue"
},
  "geometry": {"coordinates":[-121.00114600000001,38.688847],"type":"Point"}
}