{
  "type": "Feature",
  "properties": {
    "addr:full":"513 Pine Ter S San Francisco CA 94080",
    "addr:housenumber":"513",
    "addr:postcode":"94080",
    "addr:street":"Pine Ter S",
    "iso:country":"US",
    "sg:address":"513 Pine Ter",
    "sg:city":"S San Francisco",
    "sg:classifiers":[
        {
            "category":"Building & Trades",
            "subcategory":"Plumbing",
            "type":"Services"
        }
    ],
    "sg:phone":"+1 650 952 1925",
    "sg:postcode":"94080",
    "sg:province":"CA",
    "sg:tags":[
        "conditioning",
        "air",
        "system",
        "contractor"
    ],
    "wof:name":"Madrid Heating & Air Cond",
    "wof:placetype":"venue"
},
  "geometry": {"coordinates":[-122.413808,37.658891],"type":"Point"}
}