{
  "type": "Feature",
  "properties": {
    "addr:full":"506 31st St Newport Beach CA 92663",
    "addr:housenumber":"506",
    "addr:postcode":"92663",
    "addr:street":"31St St",
    "iso:country":"US",
    "sg:address":"506 31st St",
    "sg:city":"Newport Beach",
    "sg:classifiers":[
        {
            "category":"Coffee & Tea",
            "type":"Food & Drink"
        }
    ],
    "sg:phone":"+1 949 675 0233",
    "sg:postcode":"92663",
    "sg:province":"CA",
    "sg:website":"www.altacoffeeshop.com/",
    "wof:name":"Alta Coffee",
    "wof:placetype":"venue"
},
  "geometry": {"coordinates":[-117.928258,33.615157],"type":"Point"}
}