{
  "type": "Feature",
  "properties": {
    "addr:full":"18618 Pioneer Blvd Artesia CA 90701",
    "addr:housenumber":"18618",
    "addr:postcode":"90701",
    "addr:street":"Pioneer Blvd",
    "iso:country":"US",
    "sg:address":"18618 Pioneer Blvd",
    "sg:city":"Artesia",
    "sg:classifiers":[
        {
            "category":"Shopping",
            "subcategory":"Gifts & Souvenirs",
            "type":"Retail Goods"
        },
        {
            "category":"Manufacturing",
            "subcategory":"Jewelry",
            "type":"Manufacturing & Wholesale Goods"
        }
    ],
    "sg:phone":"+1 562 809 8093",
    "sg:postcode":"90701",
    "sg:province":"CA",
    "sg:tags":[
        "shop",
        "novelty"
    ],
    "wof:name":"Aakar Handicrafts",
    "wof:placetype":"venue"
},
  "geometry": {"coordinates":[-118.082155,33.862532],"type":"Point"}
}