{
  "type": "Feature",
  "properties": {
    "addr:full":"651 Wharton Dr Claremont CA 91711",
    "addr:housenumber":"651",
    "addr:postcode":"91711",
    "addr:street":"Wharton Dr",
    "iso:country":"US",
    "sg:address":"651 Wharton Dr",
    "sg:city":"Claremont",
    "sg:classifiers":[
        {
            "category":"Professional",
            "subcategory":"Management & Consulting",
            "type":"Services"
        },
        {
            "category":"Professional",
            "subcategory":"Advertising",
            "type":"Services"
        }
    ],
    "sg:phone":"+1 909 399 4000",
    "sg:postcode":"91711",
    "sg:province":"CA",
    "sg:tags":[
        "marketing",
        "program",
        "specialty",
        "consultant"
    ],
    "sg:website":"http://www.phoenixmarketing.net",
    "wof:name":"Phoenix Marketing Svc",
    "wof:placetype":"venue"
},
  "geometry": {"coordinates":[-117.724278,34.092752],"type":"Point"}
}