{
  "type": "Feature",
  "properties": {
    "iso:country":"US",
    "sg:address":"12345 Hawthorne Blvd",
    "sg:city":"Hawthorne",
    "sg:classifiers":[
        {
            "category":"Shopping",
            "subcategory":"Shoes",
            "type":"Retail Goods"
        }
    ],
    "sg:phone":"+1 310 644 3200",
    "sg:postcode":"90250",
    "sg:province":"CA",
    "wof:name":"999 Shoe Outlet",
    "wof:placetype":"venue"
},
  "geometry": {"coordinates":[-118.352529,33.923193],"type":"Point"}
}