{
  "type": "Feature",
  "properties": {
    "iso:country":"US",
    "sg:address":"17541 Chatsworth St",
    "sg:city":"Granada Hills",
    "sg:classifiers":[
        {
            "category":"Banks & Credit Unions",
            "subcategory":"Investment Brokerage",
            "type":"Services"
        }
    ],
    "sg:phone":"+1 818 366 4310",
    "sg:postcode":"91344",
    "sg:province":"CA",
    "wof:name":"National Republic Investments",
    "wof:placetype":"venue"
},
  "geometry": {"coordinates":[-118.516819,34.264939],"type":"Point"}
}