{
  "type": "Feature",
  "properties": {
    "addr:full":"12615 Artesia Blvd Cerritos CA 90703",
    "addr:housenumber":"12615",
    "addr:postcode":"ca 90703",
    "addr:street":"Artesia Blvd",
    "iso:country":"US",
    "sg:address":"12615 Artesia Blvd",
    "sg:city":"Cerritos",
    "sg:classifiers":[
        {
            "category":"Shopping",
            "subcategory":"Books",
            "type":"Retail Goods"
        }
    ],
    "sg:phone":"+1 562 809 5775",
    "sg:postcode":"90703",
    "sg:province":"CA",
    "sg:tags":[
        "dealer"
    ],
    "sg:website":"www.borderstores.com",
    "wof:name":"Borders Books & Music",
    "wof:placetype":"venue"
},
  "geometry": {"coordinates":[-118.061058,33.873239],"type":"Point"}
}