{
  "type": "Feature",
  "properties": {
    "addr:full":"15959 Lawrence Dr Mojave CA 93501",
    "addr:housenumber":"15959",
    "addr:postcode":"93501",
    "addr:street":"Lawrence Dr",
    "iso:country":"US",
    "sg:address":"15959 Lawrence Dr",
    "sg:city":"Mojave",
    "sg:classifiers":[
        {
            "category":"Professional",
            "subcategory":"Detective & Security Services",
            "type":"Services"
        }
    ],
    "sg:phone":"+1 661 824 4330",
    "sg:postcode":"93501",
    "sg:province":"CA",
    "sg:tags":[
        "information",
        "bureau"
    ],
    "wof:name":"Harget Computer Services",
    "wof:placetype":"venue"
},
  "geometry": {"coordinates":[-118.190116,35.052345],"type":"Point"}
}