{
  "type": "Feature",
  "properties": {
    "addr:full":"6228 Marysville Rd Browns Valley CA 95918",
    "addr:housenumber":"6228",
    "addr:postcode":"95918",
    "addr:street":"Marysville Rd",
    "iso:country":"US",
    "sg:address":"6228 Marysville Rd",
    "sg:city":"Browns Valley",
    "sg:classifiers":[
        {
            "category":"Wholesale",
            "subcategory":"Farm Supplies",
            "type":"Manufacturing & Wholesale Goods"
        }
    ],
    "sg:phone":"+1 530 743 6066",
    "sg:postcode":"95918",
    "sg:province":"CA",
    "sg:tags":[
        "feed"
    ],
    "wof:name":"Ray Bradley's Feed Store",
    "wof:placetype":"venue"
},
  "geometry": {"coordinates":[-121.39267,39.280449],"type":"Point"}
}