{
  "type": "Feature",
  "properties": {
    "addr:full":"20996 Bake Pkwy Lake Forest CA 92630",
    "addr:housenumber":"20996",
    "addr:postcode":"92630",
    "addr:street":"Bake Pkwy",
    "iso:country":"US",
    "sg:address":"20996 Bake Pkwy",
    "sg:city":"Lake Forest",
    "sg:classifiers":[
        {
            "category":"Shopping",
            "type":"Retail Goods"
        },
        {
            "category":"Manufacturing",
            "subcategory":"Signs",
            "type":"Manufacturing & Wholesale Goods"
        }
    ],
    "sg:phone":"+1 949 597 1866",
    "sg:postcode":"92630",
    "sg:province":"CA",
    "sg:tags":[
        "banner",
        "specialty",
        "mfg"
    ],
    "sg:website":"www.saddlebacksigns.com",
    "wof:name":"Saddleback Signs Inc",
    "wof:placetype":"venue"
},
  "geometry": {"coordinates":[-117.702826,33.65507],"type":"Point"}
}