{
  "type": "Feature",
  "properties": {
    "addr:full":"6068 Lean Avenue San Jose CA 95123",
    "addr:postcode":"6068;95123",
    "addr:street":"Lean Avenue",
    "iso:country":"US",
    "sg:address":"6068 Lean Avenue",
    "sg:city":"San Jose",
    "sg:classifiers":[
        {
            "category":"Shopping",
            "subcategory":"Party Supplies",
            "type":"Retail Goods"
        }
    ],
    "sg:phone":"+1 408 224 1626",
    "sg:postcode":"95123",
    "sg:province":"CA",
    "wof:name":"Jumps R US",
    "wof:placetype":"venue"
},
  "geometry": {"coordinates":[-121.81698400000001,37.237612],"type":"Point"}
}