{
  "type": "Feature",
  "properties": {
    "iso:country":"US",
    "sg:address":"1456 Bridge St",
    "sg:city":"Yuba City",
    "sg:classifiers":[
        {
            "category":"Restaurant",
            "type":"Food & Drink"
        }
    ],
    "sg:phone":"+1 530 751 5156",
    "sg:postcode":"95993",
    "sg:province":"CA",
    "wof:name":"Taste Of India",
    "wof:placetype":"venue"
},
  "geometry": {"coordinates":[-121.637632,39.132304],"type":"Point"}
}