{
  "type": "Feature",
  "properties": {
    "addr:full":"205 E Middlefield Road Mountain View CA 94043",
    "addr:housenumber":"205",
    "addr:postcode":"94043",
    "addr:street":"E Middlefield Road",
    "iso:country":"US",
    "sg:address":"205 E Middlefield Road",
    "sg:city":"Mountain View",
    "sg:classifiers":[
        {
            "category":"Banks & Credit Unions",
            "subcategory":"Bank",
            "type":"Services"
        }
    ],
    "sg:phone":"+1 650 988 8990",
    "sg:postcode":"94043",
    "sg:province":"CA",
    "wof:name":"State Farm Bank",
    "wof:placetype":"venue"
},
  "geometry": {"coordinates":[-122.07971000000001,37.404629],"type":"Point"}
}