{
  "type": "Feature",
  "properties": {
    "addr:full":"22371 el Toro Rd Lake Forest CA 92630",
    "addr:housenumber":"22371",
    "addr:postcode":"92630",
    "addr:street":"El Toro Rd",
    "iso:country":"US",
    "sg:address":"22371 el Toro Rd",
    "sg:city":"Lake Forest",
    "sg:classifiers":[
        {
            "category":"Education",
            "subcategory":"Special Training",
            "type":"Public Place"
        }
    ],
    "sg:phone":"+1 949 768 9500",
    "sg:postcode":"92630",
    "sg:province":"CA",
    "sg:tags":[
        "tutoring"
    ],
    "wof:name":"Tutoring Club",
    "wof:placetype":"venue"
},
  "geometry": {"coordinates":[-117.627207,33.671765],"type":"Point"}
}