{
  "type": "Feature",
  "properties": {
    "addr:full":"23762 Mercury Rd Ste A Lake Forest CA 92630",
    "addr:housenumber":"23762",
    "addr:postcode":"92630",
    "addr:street":"Mercury Rd Ste A",
    "iso:country":"US",
    "sg:address":"23762 Mercury Rd Ste A",
    "sg:city":"Lake Forest",
    "sg:classifiers":[
        {
            "category":"Sports & Exercise",
            "subcategory":"Gym",
            "type":"Entertainment"
        }
    ],
    "sg:phone":"+1 949 586 3343",
    "sg:postcode":"92630",
    "sg:province":"CA",
    "wof:name":"Cutting Edge Athletic Performance Enhancement",
    "wof:placetype":"venue"
},
  "geometry": {"coordinates":[-117.71399700000001,33.625599],"type":"Point"}
}