{
  "type": "Feature",
  "properties": {
    "iso:country":"US",
    "sg:address":"2089 W Los Altos Ave",
    "sg:city":"Fresno",
    "sg:classifiers":[
        {
            "category":"Arts & Performance",
            "subcategory":"Theater",
            "type":"Entertainment"
        }
    ],
    "sg:phone":"+1 559 287 3918",
    "sg:postcode":"93711",
    "sg:province":"CA",
    "sg:tags":[
        "live",
        "music"
    ],
    "wof:name":"Dimentional Transfer",
    "wof:placetype":"venue"
},
  "geometry": {"coordinates":[-119.82651,36.831592],"type":"Point"}
}