{
  "type": "Feature",
  "properties": {
    "iso:country":"US",
    "sg:address":"13825 Garfield Ave",
    "sg:city":"Paramount",
    "sg:classifiers":[
        {
            "category":"Building & Trades",
            "subcategory":"Construction",
            "type":"Services"
        }
    ],
    "sg:phone":"+1 562 531 0285",
    "sg:postcode":"90723",
    "sg:province":"CA",
    "sg:tags":[
        "contractor"
    ],
    "wof:name":"Kenco Builders Division of Kenneth Tnkvch Cnstrctn",
    "wof:placetype":"venue"
},
  "geometry": {"coordinates":[-118.168999,33.91],"type":"Point"}
}