{
  "type": "Feature",
  "properties": {
    "iso:country":"US",
    "sg:address":"4342 Elenda St",
    "sg:city":"Culver City",
    "sg:classifiers":[
        {
            "category":"Manufacturing",
            "subcategory":"Printing",
            "type":"Manufacturing & Wholesale Goods"
        }
    ],
    "sg:phone":"+1 310 204 4807",
    "sg:postcode":"90230",
    "sg:province":"CA",
    "sg:tags":[
        "publishing"
    ],
    "wof:name":"Latino Press",
    "wof:placetype":"venue"
},
  "geometry": {"coordinates":[-118.403002,34.008421],"type":"Point"}
}