{
  "type": "Feature",
  "properties": {
    "addr:full":"8620 Orchard Ave Los Angeles CA 90044",
    "addr:housenumber":"8620",
    "addr:postcode":"90044",
    "addr:street":"Orchard Ave",
    "iso:country":"US",
    "sg:address":"8620 Orchard Ave",
    "sg:city":"Los Angeles",
    "sg:classifiers":[
        {
            "category":"Food & Beverages",
            "subcategory":"Groceries & Convenience Stores",
            "type":"Retail Goods"
        }
    ],
    "sg:phone":"+1 323 751 0160",
    "sg:postcode":"90044",
    "sg:province":"CA",
    "sg:tags":[
        "grocer"
    ],
    "wof:name":"Ralph's",
    "wof:placetype":"venue"
},
  "geometry": {"coordinates":[-118.28807399999999,33.958161],"type":"Point"}
}