{
  "type": "Feature",
  "properties": {
    "addr:full":"1800 Hamilton Ave San Jose CA 95125",
    "addr:housenumber":"1800",
    "addr:postcode":"95125",
    "addr:street":"Hamilton Ave",
    "iso:country":"US",
    "sg:address":"1800 Hamilton Ave",
    "sg:city":"San Jose",
    "sg:classifiers":[
        {
            "category":"Professional",
            "subcategory":"Accounting & Tax Preparation",
            "type":"Services"
        }
    ],
    "sg:phone":"+1 408 448 4945",
    "sg:postcode":"95125",
    "sg:province":"CA",
    "sg:tags":[
        "return",
        "filing"
    ],
    "wof:name":"Elaine Phillips",
    "wof:placetype":"venue"
},
  "geometry": {"coordinates":[-121.91876499999999,37.294398],"type":"Point"}
}