{
  "type": "Feature",
  "properties": {
    "addr:full":"23305 Grant Ave Torrance CA 90505",
    "addr:housenumber":"23305",
    "addr:postcode":"90505",
    "addr:street":"Grant Ave",
    "iso:country":"US",
    "sg:address":"23305 Grant Ave",
    "sg:city":"Torrance",
    "sg:classifiers":[
        {
            "category":"Shopping",
            "subcategory":"Gifts & Souvenirs",
            "type":"Retail Goods"
        }
    ],
    "sg:phone":"+1 310 375 1733",
    "sg:postcode":"90505",
    "sg:province":"CA",
    "wof:name":"Peters Cecelia",
    "wof:placetype":"venue"
},
  "geometry": {"coordinates":[-118.356261,33.814449],"type":"Point"}
}