{
  "type": "Feature",
  "properties": {
    "iso:country":"US",
    "sg:address":"1319 Lakeshore Cir",
    "sg:city":"San Jose",
    "sg:classifiers":[
        {
            "category":"Professional",
            "subcategory":"Secretarial Services",
            "type":"Services"
        }
    ],
    "sg:phone":"+1 408 392 9169",
    "sg:postcode":"95131",
    "sg:province":"CA",
    "sg:tags":[
        "information",
        "document",
        "financial"
    ],
    "wof:name":"HNS",
    "wof:placetype":"venue"
},
  "geometry": {"coordinates":[-121.892705,37.385524],"type":"Point"}
}