{
  "type": "Feature",
  "properties": {
    "addr:full":"929 Redwood Dr Garberville CA 95542",
    "addr:housenumber":"929",
    "addr:postcode":"95542",
    "addr:street":"Redwood Dr",
    "iso:country":"US",
    "sg:address":"929 Redwood Dr",
    "sg:city":"Garberville",
    "sg:classifiers":[
        {
            "category":"Cinema",
            "subcategory":"Movie Rental",
            "type":"Entertainment"
        }
    ],
    "sg:phone":"+1 707 923 2942",
    "sg:postcode":"95542",
    "sg:province":"CA",
    "sg:tags":[
        "leasing",
        "video",
        "disc",
        "tape"
    ],
    "wof:name":"Town & Country Video",
    "wof:placetype":"venue"
},
  "geometry": {"coordinates":[-123.79500299999999,40.096773],"type":"Point"}
}