{
  "type": "Feature",
  "properties": {
    "addr:full":"7915 Silverton Ave San Diego CA 92126",
    "addr:housenumber":"7915",
    "addr:postcode":"92126",
    "addr:street":"Silverton Ave",
    "iso:country":"US",
    "sg:address":"7915 Silverton Ave",
    "sg:city":"San Diego",
    "sg:classifiers":[
        {
            "category":"Wholesale",
            "subcategory":"Non-durable Goods",
            "type":"Manufacturing & Wholesale Goods"
        }
    ],
    "sg:phone":"+1 858 549 6968",
    "sg:postcode":"92126",
    "sg:province":"CA",
    "wof:name":"Pacha Imports",
    "wof:placetype":"venue"
},
  "geometry": {"coordinates":[-117.152963,32.890826],"type":"Point"}
}