{
  "type": "Feature",
  "properties": {
    "iso:country":"US",
    "sg:address":"1119 S Mission Rd",
    "sg:city":"Fallbrook",
    "sg:classifiers":[
        {
            "category":"Banks & Credit Unions",
            "subcategory":"Bank",
            "type":"Services"
        }
    ],
    "sg:phone":"+1 760 728 9267",
    "sg:postcode":"92028",
    "sg:province":"CA",
    "sg:tags":[
        "loan"
    ],
    "wof:name":"Investment Capital Resources",
    "wof:placetype":"venue"
},
  "geometry": {"coordinates":[-117.252598,33.371419],"type":"Point"}
}