{
  "type": "Feature",
  "properties": {
    "addr:full":"1640 Camino Del Rio N Ste 155 San Diego CA 92108",
    "addr:housenumber":"1640",
    "addr:postcode":"92108",
    "addr:street":"Camino Del Rio N Ste 155",
    "iso:country":"US",
    "sg:address":"1640 Camino Del Rio N Ste 155",
    "sg:city":"San Diego",
    "sg:classifiers":[
        {
            "category":"Shopping",
            "subcategory":"Clothing, Apparel, & Fashions",
            "type":"Retail Goods"
        }
    ],
    "sg:phone":"+1 619 294 2151",
    "sg:postcode":"92108",
    "sg:province":"CA",
    "sg:tags":[
        "lingerie",
        "accessory"
    ],
    "sg:website":"www.fredericks.com/",
    "wof:name":"Frederick's of Hollywood",
    "wof:placetype":"venue"
},
  "geometry": {"coordinates":[-117.14796,32.767194],"type":"Point"}
}