{
  "type": "Feature",
  "properties": {
    "iso:country":"US",
    "sg:address":"343 E Main St",
    "sg:city":"Stockton",
    "sg:classifiers":[
        {
            "category":"Health Services",
            "subcategory":"Clinic",
            "type":"Services"
        }
    ],
    "sg:phone":"+1 209 466 2860",
    "sg:postcode":"95202",
    "sg:province":"CA",
    "sg:tags":[
        "welfare"
    ],
    "wof:name":"Health Alliance America",
    "wof:placetype":"venue"
},
  "geometry": {"coordinates":[-121.28664999999999,37.953234],"type":"Point"}
}