{
  "type": "Feature",
  "properties": {
    "addr:full":"4478 River Ash Ct Concord CA 94521",
    "addr:housenumber":"4478",
    "addr:postcode":"94521",
    "addr:street":"River Ash Ct",
    "iso:country":"US",
    "sg:address":"4478 River Ash Ct",
    "sg:city":"Concord",
    "sg:classifiers":[
        {
            "category":"Professional",
            "subcategory":"Lawyer & Legal Services",
            "type":"Services"
        }
    ],
    "sg:phone":"+1 925 975 0330",
    "sg:postcode":"94521",
    "sg:province":"CA",
    "sg:tags":[
        "attorney"
    ],
    "wof:name":"Timothy Power Law Office",
    "wof:placetype":"venue"
},
  "geometry": {"coordinates":[-121.984442,37.950078],"type":"Point"}
}