{
  "type": "Feature",
  "properties": {
    "addr:full":"1297 Peralta Dr San Jose CA 95120",
    "addr:housenumber":"1297",
    "addr:postcode":"95120",
    "addr:street":"Peralta Dr",
    "iso:country":"US",
    "sg:address":"1297 Peralta Dr",
    "sg:city":"San Jose",
    "sg:classifiers":[
        {
            "category":"Recreation",
            "type":"Entertainment"
        }
    ],
    "sg:phone":"+1 408 997 0182",
    "sg:postcode":"95120",
    "sg:province":"CA",
    "sg:tags":[
        "club",
        "membership"
    ],
    "wof:name":"Crossgate Swim Club",
    "wof:placetype":"venue"
},
  "geometry": {"coordinates":[-121.872409,37.224962],"type":"Point"}
}