{
  "type": "Feature",
  "properties": {
    "iso:country":"US",
    "sg:address":"481 W Bullard Ave Apt 5",
    "sg:city":"Clovis",
    "sg:classifiers":[
        {
            "category":"Professional",
            "subcategory":"Management & Consulting",
            "type":"Services"
        }
    ],
    "sg:phone":"+1 559 708 0694",
    "sg:postcode":"93612",
    "sg:province":"CA",
    "sg:tags":[
        "consultant"
    ],
    "wof:name":"Debbie Bevington",
    "wof:placetype":"venue"
},
  "geometry": {"coordinates":[-119.72054300000001,36.823025],"type":"Point"}
}