{
  "type": "Feature",
  "properties": {
    "iso:country":"US",
    "sg:address":"2250 E 69th St",
    "sg:city":"Long Beach",
    "sg:classifiers":[
        {
            "category":"Freight",
            "type":"Transportation"
        }
    ],
    "sg:phone":"+1 562 634 4902",
    "sg:postcode":"90805",
    "sg:province":"CA",
    "sg:tags":[
        "operator",
        "trucking"
    ],
    "wof:name":"Best Overnite Express Inc",
    "wof:placetype":"venue"
},
  "geometry": {"coordinates":[-118.16775,33.88051],"type":"Point"}
}