{
  "type": "Feature",
  "properties": {
    "iso:country":"US",
    "sg:address":"3255 Swetzer Rd",
    "sg:city":"Loomis",
    "sg:classifiers":[
        {
            "category":"Building & Trades",
            "subcategory":"Construction",
            "type":"Services"
        }
    ],
    "sg:phone":"+1 916 660 9681",
    "sg:postcode":"95650",
    "sg:province":"CA",
    "sg:tags":[
        "maker",
        "cabinet"
    ],
    "sg:website":"www.garagesource.com",
    "wof:name":"Storage Source",
    "wof:placetype":"venue"
},
  "geometry": {"coordinates":[-121.191676,38.835119],"type":"Point"}
}