{
  "type": "Feature",
  "properties": {
    "addr:full":"290 Panama St Stanford CA 94305",
    "addr:housenumber":"290",
    "addr:postcode":"94305",
    "addr:street":"Panama St",
    "iso:country":"US",
    "sg:address":"290 Panama St",
    "sg:city":"Stanford",
    "sg:classifiers":[
        {
            "category":"Professional",
            "type":"Services"
        }
    ],
    "sg:phone":"+1 650 325 1521",
    "sg:postcode":"94305",
    "sg:province":"CA",
    "sg:tags":[
        "establishment"
    ],
    "wof:name":"Carnegie Institution-Wshngtn",
    "wof:placetype":"venue"
},
  "geometry": {"coordinates":[-122.178192,37.429069],"type":"Point"}
}