{
  "type": "Feature",
  "properties": {
    "addr:full":"12806 Paramount Blvd Downey CA 90242",
    "addr:housenumber":"12806",
    "addr:postcode":"90242",
    "addr:street":"Paramount Blvd",
    "iso:country":"US",
    "sg:address":"12806 Paramount Blvd",
    "sg:city":"Downey",
    "sg:classifiers":[
        {
            "category":"Shopping",
            "subcategory":"Bicycles & Sporting Goods",
            "type":"Retail Goods"
        }
    ],
    "sg:phone":"+1 562 861 5308",
    "sg:postcode":"90242",
    "sg:province":"CA",
    "wof:name":"Llamas Bike Shop",
    "wof:placetype":"venue"
},
  "geometry": {"coordinates":[-118.154515,33.920705],"type":"Point"}
}