{
  "type": "Feature",
  "properties": {
    "addr:full":"7615 S Western Ave Los Angeles CA 90047",
    "addr:housenumber":"7615",
    "addr:postcode":"90047",
    "addr:street":"S Western Ave",
    "iso:country":"US",
    "sg:address":"7615 S Western Ave",
    "sg:city":"Los Angeles",
    "sg:classifiers":[
        {
            "category":"Organizations",
            "subcategory":"Religious Organization",
            "type":"Services"
        }
    ],
    "sg:phone":"+1 323 759 2065",
    "sg:postcode":"90047",
    "sg:province":"CA",
    "sg:tags":[
        "church"
    ],
    "wof:name":"Alpha & Omega Christian Ctr",
    "wof:placetype":"venue"
},
  "geometry": {"coordinates":[-118.30906299999999,33.970102],"type":"Point"}
}