{
  "type": "Feature",
  "properties": {
    "iso:country":"US",
    "sg:address":"7615 S Western Ave",
    "sg:city":"Los Angeles",
    "sg:classifiers":[
        {
            "category":"Organizations",
            "subcategory":"Religious Organization",
            "type":"Services"
        }
    ],
    "sg:phone":"+1 323 759 2065",
    "sg:postcode":"90047",
    "sg:province":"CA",
    "sg:tags":[
        "church"
    ],
    "wof:name":"Alpha & Omega Christian Ctr",
    "wof:placetype":"venue"
},
  "geometry": {"coordinates":[-118.309063,33.970102],"type":"Point"}
}