{
  "type": "Feature",
  "properties": {
    "addr:full":"4704 Mission St San Francisco CA 94112",
    "addr:housenumber":"4704",
    "addr:postcode":"94112",
    "addr:street":"Mission St",
    "iso:country":"US",
    "sg:address":"4704 Mission St",
    "sg:city":"San Francisco",
    "sg:classifiers":[
        {
            "category":"Bars & Pubs",
            "type":"Food & Drink"
        }
    ],
    "sg:phone":"+1 415 337 1678",
    "sg:postcode":"94112",
    "sg:province":"CA",
    "wof:name":"Bottom's Up",
    "wof:placetype":"venue"
},
  "geometry": {"coordinates":[-122.436227,37.722916],"type":"Point"}
}