{
  "type": "Feature",
  "properties": {
    "addr:full":"948 Center St San Carlos CA 94070",
    "addr:housenumber":"948",
    "addr:postcode":"94070",
    "addr:street":"Center St",
    "iso:country":"US",
    "sg:address":"948 Center St",
    "sg:city":"San Carlos",
    "sg:classifiers":[
        {
            "category":"Building & Trades",
            "subcategory":"Construction",
            "type":"Services"
        }
    ],
    "sg:phone":"+1 650 593 4600",
    "sg:postcode":"94070",
    "sg:province":"CA",
    "sg:tags":[
        "fence",
        "contractor"
    ],
    "wof:name":"Outstanding Fence Co",
    "wof:placetype":"venue"
},
  "geometry": {"coordinates":[-122.24538200000001,37.499326],"type":"Point"}
}