{
  "type": "Feature",
  "properties": {
    "iso:country":"US",
    "sg:address":"11307 Warmington St",
    "sg:city":"Riverside",
    "sg:classifiers":[
        {
            "category":"Wholesale",
            "subcategory":"Durable Goods & Equipment",
            "type":"Manufacturing & Wholesale Goods"
        }
    ],
    "sg:phone":"+1 714 225 9637",
    "sg:postcode":"92503",
    "sg:province":"CA",
    "sg:tags":[
        "professional"
    ],
    "wof:name":"Bomber USA",
    "wof:placetype":"venue"
},
  "geometry": {"coordinates":[-117.465479,33.883027],"type":"Point"}
}