{
  "type": "Feature",
  "properties": {
    "addr:full":"2400 Sand Creek Rd Brentwood CA 94513",
    "addr:housenumber":"2400",
    "addr:postcode":"ca 94513",
    "addr:street":"Sand Creek Rd",
    "iso:country":"US",
    "sg:address":"2400 Sand Creek Rd",
    "sg:city":"Brentwood",
    "sg:classifiers":[
        {
            "category":"Food & Beverages",
            "subcategory":"Groceries & Convenience Stores",
            "type":"Retail Goods"
        }
    ],
    "sg:phone":"+1 925 513 9400",
    "sg:postcode":"94513",
    "sg:province":"CA",
    "sg:tags":[
        "grocer"
    ],
    "wof:name":"Raley's Bakery",
    "wof:placetype":"venue"
},
  "geometry": {"coordinates":[-121.742509,37.947141],"type":"Point"}
}