{
  "type": "Feature",
  "properties": {
    "iso:country":"US",
    "sg:address":"427 E 17th St",
    "sg:city":"Costa Mesa",
    "sg:classifiers":[
        {
            "category":"Personal",
            "subcategory":"Beauty Salon",
            "type":"Services"
        }
    ],
    "sg:phone":"+1 949 722 6571",
    "sg:postcode":"92627",
    "sg:province":"CA",
    "wof:name":"Haircutters",
    "wof:placetype":"venue"
},
  "geometry": {"coordinates":[-117.909588,33.628991],"type":"Point"}
}