{
  "type": "Feature",
  "properties": {
    "iso:country":"US",
    "sg:address":"975 D St",
    "sg:city":"Hayward",
    "sg:classifiers":[
        {
            "category":"Shopping",
            "subcategory":"Clothing, Apparel, & Fashions",
            "type":"Retail Goods"
        }
    ],
    "sg:phone":"+1 510 582 9807",
    "sg:postcode":"94541",
    "sg:province":"CA",
    "sg:tags":[
        "sheepskin",
        "specialty"
    ],
    "wof:name":"Era East West",
    "wof:placetype":"venue"
},
  "geometry": {"coordinates":[-122.081494,37.670163],"type":"Point"}
}