{
  "type": "Feature",
  "properties": {
    "addr:full":"13549 Hwy 8 Bus El Cajon CA 92021",
    "addr:housenumber":"13549",
    "addr:postcode":"92021",
    "addr:street":"Hwy 8 Bus",
    "iso:country":"US",
    "sg:address":"13549 Hwy 8 Bus",
    "sg:city":"El Cajon",
    "sg:classifiers":[
        {
            "category":"Shopping",
            "type":"Retail Goods"
        },
        {
            "category":"Manufacturing",
            "subcategory":"Signs",
            "type":"Manufacturing & Wholesale Goods"
        }
    ],
    "sg:phone":"+1 619 443 2908",
    "sg:postcode":"92021",
    "sg:province":"CA",
    "sg:tags":[
        "merchandise"
    ],
    "wof:name":"Montijo Wood Art Sign Village",
    "wof:placetype":"venue"
},
  "geometry": {"coordinates":[-116.896568,32.838319],"type":"Point"}
}