{
  "type": "Feature",
  "properties": {
    "addr:full":"2650 W Hatch Rd Modesto CA 95358",
    "addr:housenumber":"2650",
    "addr:postcode":"ca 95358",
    "addr:street":"W Hatch Rd",
    "iso:country":"US",
    "sg:address":"2650 W Hatch Rd",
    "sg:city":"Modesto",
    "sg:classifiers":[
        {
            "category":"Utilities",
            "subcategory":"Refuse",
            "type":"Services"
        }
    ],
    "sg:phone":"+1 209 538 2267",
    "sg:postcode":"95358",
    "sg:province":"CA",
    "sg:tags":[
        "system"
    ],
    "wof:name":"Recycle Center",
    "wof:placetype":"venue"
},
  "geometry": {"coordinates":[-121.048157,37.608527],"type":"Point"}
}