{
  "type": "Feature",
  "properties": {
    "iso:country":"US",
    "sg:address":"519 E Arrow Hwy",
    "sg:city":"Upland",
    "sg:classifiers":[
        {
            "category":"Professional",
            "type":"Services"
        }
    ],
    "sg:phone":"+1 909 982 2036",
    "sg:postcode":"91786",
    "sg:province":"CA",
    "wof:name":"Extraordinary People",
    "wof:placetype":"venue"
},
  "geometry": {"coordinates":[-117.642978,34.099848],"type":"Point"}
}