{
  "type": "Feature",
  "properties": {
    "iso:country":"US",
    "sg:address":"1241 Anna St",
    "sg:city":"Broderick",
    "sg:classifiers":[
        {
            "category":"Building & Trades",
            "subcategory":"Landscaping Services",
            "type":"Services"
        }
    ],
    "sg:phone":"+1 916 371 4031",
    "sg:postcode":"95605",
    "sg:province":"CA",
    "sg:tags":[
        "lawn",
        "maintenance",
        "grounds"
    ],
    "wof:name":"Mendez Gardening Svc",
    "wof:placetype":"venue"
},
  "geometry": {"coordinates":[-121.532751,38.59545],"type":"Point"}
}