{
  "type": "Feature",
  "properties": {
    "iso:country":"US",
    "sg:address":"862 Laguna St",
    "sg:city":"Livermore",
    "sg:classifiers":[
        {
            "category":"Professional",
            "type":"Services"
        }
    ],
    "sg:phone":"+1 925 443 6526",
    "sg:postcode":"94550",
    "sg:province":"CA",
    "wof:name":"Michael & Carol Haynes",
    "wof:placetype":"venue"
},
  "geometry": {"coordinates":[-121.795491,37.670765],"type":"Point"}
}