{
  "type": "Feature",
  "properties": {
    "addr:full":"5932 Busch Dr Malibu CA 90265",
    "addr:housenumber":"5932",
    "addr:postcode":"90265",
    "addr:street":"Busch Dr",
    "iso:country":"US",
    "sg:address":"5932 Busch Dr",
    "sg:city":"Malibu",
    "sg:classifiers":[
        {
            "category":"Professional",
            "type":"Services"
        }
    ],
    "sg:phone":"+1 310 457 3740",
    "sg:postcode":"90265",
    "sg:province":"CA",
    "wof:name":"Whisper",
    "wof:placetype":"venue"
},
  "geometry": {"coordinates":[-118.820705,34.026474],"type":"Point"}
}