{
  "type": "Feature",
  "properties": {
    "addr:full":"40321 Salem Way Temecula CA 92591",
    "addr:postcode":"40321;92591",
    "addr:street":"Salem Way",
    "iso:country":"US",
    "sg:address":"40321 Salem Way",
    "sg:city":"Temecula",
    "sg:classifiers":[
        {
            "category":"Social Services",
            "subcategory":"Child Care",
            "type":"Services"
        }
    ],
    "sg:phone":"+1 951 587 4267",
    "sg:postcode":"92591",
    "sg:province":"CA",
    "sg:tags":[
        "nursery",
        "day"
    ],
    "wof:name":"Olivias Child Care",
    "wof:placetype":"venue"
},
  "geometry": {"coordinates":[-117.158592,33.53508],"type":"Point"}
}