{
  "type": "Feature",
  "properties": {
    "addr:full":"3644 Bolivar Ave North Highlands CA 95660",
    "addr:housenumber":"3644",
    "addr:postcode":"95660",
    "addr:street":"Bolivar Ave",
    "iso:country":"US",
    "sg:address":"3644 Bolivar Ave",
    "sg:city":"North Highlands",
    "sg:classifiers":[
        {
            "category":"Organizations",
            "subcategory":"Religious Organization",
            "type":"Services"
        }
    ],
    "sg:phone":"+1 916 332 4001",
    "sg:postcode":"95660",
    "sg:province":"CA",
    "sg:tags":[
        "church"
    ],
    "wof:name":"Zion Lutheran Church Missouri",
    "wof:placetype":"venue"
},
  "geometry": {"coordinates":[-121.381266,38.682952],"type":"Point"}
}