{
  "type": "Feature",
  "properties": {
    "iso:country":"US",
    "sg:address":"27 E Victoria St",
    "sg:city":"Santa Barbara",
    "sg:classifiers":[
        {
            "category":"Education",
            "subcategory":"Special Training",
            "type":"Public Place"
        }
    ],
    "sg:phone":"+1 805 898 8987",
    "sg:postcode":"93101",
    "sg:province":"CA",
    "sg:tags":[
        "school",
        "language"
    ],
    "sg:website":"www.spanishschoolsbca.com",
    "wof:name":"Siglo Xxi Language Institute",
    "wof:placetype":"venue"
},
  "geometry": {"coordinates":[-119.704892,34.425131],"type":"Point"}
}