{
  "type": "Feature",
  "properties": {
    "addr:full":"1419 J St Modesto CA 95354",
    "addr:housenumber":"1419",
    "addr:postcode":"ca 95354",
    "addr:street":"J St",
    "iso:country":"US",
    "sg:address":"1419 J St",
    "sg:city":"Modesto",
    "sg:classifiers":[
        {
            "category":"Banks & Credit Unions",
            "subcategory":"Bank",
            "type":"Services"
        }
    ],
    "sg:phone":"+1 209 549 8500",
    "sg:postcode":"95354",
    "sg:province":"CA",
    "wof:name":"Valley First",
    "wof:placetype":"venue"
},
  "geometry": {"coordinates":[-120.996002,37.643902],"type":"Point"}
}