{
  "type": "Feature",
  "properties": {
    "iso:country":"US",
    "sg:address":"1140 Commerce Center Dr",
    "sg:city":"Lancaster",
    "sg:classifiers":[
        {
            "category":"Autos & Motor Vehicles",
            "subcategory":"Auto Supplies",
            "type":"Retail Goods"
        }
    ],
    "sg:phone":"+1 661 400 2846",
    "sg:postcode":"93534",
    "sg:province":"CA",
    "sg:tags":[
        "tire"
    ],
    "sg:website":"http://BRITISHINDIATIRES.COM",
    "wof:name":"BRITISH INDIA TIRES",
    "wof:placetype":"venue"
},
  "geometry": {"coordinates":[-118.15173,34.672387],"type":"Point"}
}