{
  "type": "Feature",
  "properties": {
    "iso:country":"US",
    "sg:address":"16638 Crenshaw Blvd",
    "sg:city":"Torrance",
    "sg:classifiers":[
        {
            "category":"Personal",
            "subcategory":"Barber",
            "type":"Services"
        }
    ],
    "sg:phone":"+1 310 771 0620",
    "sg:postcode":"90504",
    "sg:province":"CA",
    "wof:name":"Sachi's Hair House",
    "wof:placetype":"venue"
},
  "geometry": {"coordinates":[-118.326386,33.878815],"type":"Point"}
}