{
  "type": "Feature",
  "properties": {
    "addr:full":"21239 S Wilmington Ave Carson CA 90810",
    "addr:housenumber":"21239",
    "addr:postcode":"90810",
    "addr:street":"S Wilmington Ave",
    "iso:country":"US",
    "sg:address":"21239 S Wilmington Ave",
    "sg:city":"Carson",
    "sg:classifiers":[
        {
            "category":"Fast Food",
            "type":"Food & Drink"
        }
    ],
    "sg:phone":"+1 310 830 4009",
    "sg:postcode":"90810",
    "sg:province":"CA",
    "sg:tags":[
        "burger"
    ],
    "wof:name":"Apollo Burgers",
    "wof:placetype":"venue"
},
  "geometry": {"coordinates":[-118.237999,33.835701],"type":"Point"}
}