{
  "type": "Feature",
  "properties": {
    "addr:full":"10806 Penara St San Diego CA 92126",
    "addr:housenumber":"10806",
    "addr:postcode":"92126",
    "addr:street":"Penara St",
    "iso:country":"US",
    "sg:address":"10806 Penara St",
    "sg:city":"San Diego",
    "sg:classifiers":[
        {
            "category":"Professional",
            "subcategory":"Management & Consulting",
            "type":"Services"
        }
    ],
    "sg:phone":"+1 858 578 5582",
    "sg:postcode":"92126",
    "sg:province":"CA",
    "sg:tags":[
        "consultant"
    ],
    "wof:name":"J F Design Consulting",
    "wof:placetype":"venue"
},
  "geometry": {"coordinates":[-117.16852900000001,32.914825],"type":"Point"}
}