{
  "type": "Feature",
  "properties": {
    "addr:full":"5693 Camass Ct Newark CA 94560",
    "addr:housenumber":"5693",
    "addr:postcode":"94560",
    "addr:street":"Camass Ct",
    "iso:country":"US",
    "sg:address":"5693 Camass Ct",
    "sg:city":"Newark",
    "sg:classifiers":[
        {
            "category":"Building & Trades",
            "subcategory":"Construction",
            "type":"Services"
        }
    ],
    "sg:phone":"+1 510 796 8277",
    "sg:postcode":"94560",
    "sg:province":"CA",
    "sg:tags":[
        "general",
        "contractor"
    ],
    "wof:name":"Cunningham Constr Co",
    "wof:placetype":"venue"
},
  "geometry": {"coordinates":[-122.017804,37.535298],"type":"Point"}
}