{
  "type": "Feature",
  "properties": {
    "iso:country":"US",
    "sg:address":"905 S Victory Blvd",
    "sg:city":"Burbank",
    "sg:classifiers":[
        {
            "category":"Arts & Performance",
            "subcategory":"Dance",
            "type":"Entertainment"
        }
    ],
    "sg:phone":"+1 818 841 3547",
    "sg:postcode":"91502",
    "sg:province":"CA",
    "sg:tags":[
        "instruction",
        "dancing"
    ],
    "wof:name":"Mook Kunewa",
    "wof:placetype":"venue"
},
  "geometry": {"coordinates":[-118.30879400000001,34.167386],"type":"Point"}
}