{
  "type": "Feature",
  "properties": {
    "iso:country":"US",
    "sg:address":"401 W Dyer Rd",
    "sg:city":"Santa Ana",
    "sg:classifiers":[
        {
            "category":"Sports & Exercise",
            "subcategory":"Bicycle Rental",
            "type":"Entertainment"
        }
    ],
    "sg:phone":"+1 714 549 8080",
    "sg:postcode":"92707",
    "sg:province":"CA",
    "sg:tags":[
        "wear"
    ],
    "wof:name":"P S Sportswear",
    "wof:placetype":"venue"
},
  "geometry": {"coordinates":[-117.873001,33.708801],"type":"Point"}
}