{
  "type": "Feature",
  "properties": {
    "addr:full":"7817 Reseda Blvd Reseda CA 91335",
    "addr:housenumber":"7817",
    "addr:postcode":"91335",
    "addr:street":"Reseda Blvd",
    "iso:country":"US",
    "sg:address":"7817 Reseda Blvd",
    "sg:city":"Reseda",
    "sg:classifiers":[
        {
            "category":"Building & Trades",
            "subcategory":"Electrical",
            "type":"Services"
        }
    ],
    "sg:phone":"+1 818 269 9966",
    "sg:postcode":"91335",
    "sg:province":"CA",
    "sg:tags":[
        "electric",
        "contractor"
    ],
    "wof:name":"A Sharp Electric",
    "wof:placetype":"venue"
},
  "geometry": {"coordinates":[-118.536068,34.213831],"type":"Point"}
}