{
  "type": "Feature",
  "properties": {
    "iso:country":"US",
    "sg:address":"611 N Howard St",
    "sg:city":"Glendale",
    "sg:classifiers":[
        {
            "category":"Real Estate",
            "subcategory":"Real Estate Operator",
            "type":"Services"
        }
    ],
    "sg:phone":"+1 818 502 2627",
    "sg:postcode":"91206",
    "sg:province":"CA",
    "sg:tags":[
        "apartment"
    ],
    "wof:name":"James Terrace Apartments",
    "wof:placetype":"venue"
},
  "geometry": {"coordinates":[-118.248001,34.1549],"type":"Point"}
}