{
  "type": "Feature",
  "properties": {
    "addr:full":"2070 Mountain Blvd Oakland CA 94611",
    "addr:housenumber":"2070",
    "addr:postcode":"94611",
    "addr:street":"Mountain Blvd",
    "iso:country":"US",
    "sg:address":"2070 Mountain Blvd",
    "sg:city":"Oakland",
    "sg:classifiers":[
        {
            "category":"Real Estate",
            "subcategory":"Real Estate Services",
            "type":"Services"
        },
        {
            "category":"Real Estate",
            "subcategory":"Real Estate Agent",
            "type":"Services"
        }
    ],
    "sg:phone":"+1 510 847 3924",
    "sg:postcode":"94611",
    "sg:province":"CA",
    "wof:name":"Richard Buijs - RE/MAX Accord",
    "wof:placetype":"venue"
},
  "geometry": {"coordinates":[-122.209245,37.826078],"type":"Point"}
}