{
  "type": "Feature",
  "properties": {
    "addr:full":"1416 2nd St Napa CA 94559",
    "addr:housenumber":"1416",
    "addr:postcode":"94559",
    "addr:street":"2Nd St",
    "iso:country":"US",
    "sg:address":"1416 2nd St",
    "sg:city":"Napa",
    "sg:classifiers":[
        {
            "category":"Shopping",
            "subcategory":"Music",
            "type":"Retail Goods"
        }
    ],
    "sg:phone":"+1 707 226 2666",
    "sg:postcode":"94559",
    "sg:province":"CA",
    "sg:tags":[
        "video",
        "disc",
        "tape",
        "cassette"
    ],
    "wof:name":"Pleasures Unlimited",
    "wof:placetype":"venue"
},
  "geometry": {"coordinates":[-122.28876099999999,38.296638],"type":"Point"}
}