{
  "type": "Feature",
  "properties": {
    "iso:country":"US",
    "sg:address":"4001 Lester Ave",
    "sg:city":"Corona",
    "sg:classifiers":[
        {
            "category":"Farming",
            "subcategory":"Livestock Farm",
            "type":"Manufacturing & Wholesale Goods"
        }
    ],
    "sg:phone":"+1 951 737 5996",
    "sg:postcode":"92881",
    "sg:province":"CA",
    "sg:tags":[
        "ranch"
    ],
    "wof:name":"Crown Ranch Pumping Co",
    "wof:placetype":"venue"
},
  "geometry": {"coordinates":[-117.553314,33.823451],"type":"Point"}
}