{
  "type": "Feature",
  "properties": {
    "iso:country":"US",
    "sg:address":"14358 Golden Sunset Ln",
    "sg:city":"Poway",
    "sg:classifiers":[
        {
            "category":"Farming",
            "subcategory":"Orchard",
            "type":"Manufacturing & Wholesale Goods"
        },
        {
            "category":"Arena",
            "subcategory":"Horse Racetrack",
            "type":"Entertainment"
        }
    ],
    "sg:phone":"+1 858 486 4955",
    "sg:postcode":"92064",
    "sg:province":"CA",
    "sg:tags":[
        "transporting",
        "livestock",
        "hauling"
    ],
    "wof:name":"Jack's Horse Hauling",
    "wof:placetype":"venue"
},
  "geometry": {"coordinates":[-117.020596,32.984755],"type":"Point"}
}