{
  "type": "Feature",
  "properties": {
    "iso:country":"US",
    "sg:address":"4214 California St",
    "sg:city":"San Francisco",
    "sg:classifiers":[
        {
            "category":"Health Services",
            "subcategory":"Dentist",
            "type":"Services"
        }
    ],
    "sg:phone":"+1 415 752 0844",
    "sg:postcode":"94118",
    "sg:province":"CA",
    "sg:website":"dr.nikolaeff.com",
    "wof:name":"Natalia Nikolaeff Svensson, DDS",
    "wof:placetype":"venue"
},
  "geometry": {"coordinates":[-122.462616,37.785275],"type":"Point"}
}