{
  "type": "Feature",
  "properties": {
    "iso:country":"US",
    "sg:address":"1432 W 25th St",
    "sg:city":"San Pedro",
    "sg:classifiers":[
        {
            "category":"Personal",
            "subcategory":"Beauty Salon",
            "type":"Services"
        }
    ],
    "sg:phone":"+1 310 832 7726",
    "sg:postcode":"90732",
    "sg:province":"CA",
    "wof:name":"Wild Orchid Hair Studio",
    "wof:placetype":"venue"
},
  "geometry": {"coordinates":[-118.311134,33.721798],"type":"Point"}
}