{
  "type": "Feature",
  "properties": {
    "iso:country":"US",
    "sg:address":"78 E Blithedale Ave",
    "sg:city":"Mill Valley",
    "sg:classifiers":[
        {
            "category":"Shopping",
            "type":"Retail Goods"
        }
    ],
    "sg:phone":"+1 415 388 2044",
    "sg:postcode":"94941",
    "sg:province":"CA",
    "sg:tags":[
        "art",
        "gallery",
        "dealer"
    ],
    "wof:name":"Artisans Gallery",
    "wof:placetype":"venue"
},
  "geometry": {"coordinates":[-122.545403,37.906002],"type":"Point"}
}