{
  "type": "Feature",
  "properties": {
    "iso:country":"US",
    "sg:address":"854 N Plumas St",
    "sg:city":"Willows",
    "sg:classifiers":[
        {
            "category":"Building & Trades",
            "subcategory":"Landscaping Services",
            "type":"Services"
        }
    ],
    "sg:phone":"+1 530 934 9580",
    "sg:postcode":"95988",
    "sg:province":"CA",
    "wof:name":"Coffman Landscaping",
    "wof:placetype":"venue"
},
  "geometry": {"coordinates":[-122.198154,39.53229],"type":"Point"}
}