{
  "type": "Feature",
  "properties": {
    "iso:country":"US",
    "sg:address":"545 Aldo Ave. Suite 19",
    "sg:city":"Santa Clara",
    "sg:classifiers":[
        {
            "category":"Professional",
            "subcategory":"Printing & Photocopies",
            "type":"Services"
        }
    ],
    "sg:phone":"+1 408 748 8562",
    "sg:postcode":"95054",
    "sg:province":"CA",
    "sg:website":"www.jeronimoslithocraft.com",
    "wof:name":"Jeronimo's Lithocraft",
    "wof:placetype":"venue"
},
  "geometry": {"coordinates":[-121.945999,37.385751],"type":"Point"}
}