{
  "type": "Feature",
  "properties": {
    "addr:full":"11124 Los Alamitos Blvd Los Alamitos CA 90720",
    "addr:housenumber":"11124",
    "addr:postcode":"90720",
    "addr:street":"Los Alamitos Blvd",
    "iso:country":"US",
    "sg:address":"11124 Los Alamitos Blvd",
    "sg:city":"Los Alamitos",
    "sg:classifiers":[
        {
            "category":"Food & Beverages",
            "subcategory":"Meat & Fish",
            "type":"Retail Goods"
        }
    ],
    "sg:phone":"+1 714 828 4492",
    "sg:postcode":"90720",
    "sg:province":"CA",
    "sg:tags":[
        "shop"
    ],
    "wof:name":"Fairfax Kosher Meat Market",
    "wof:placetype":"venue"
},
  "geometry": {"coordinates":[-118.07199900000001,33.801102],"type":"Point"}
}