{
  "type": "Feature",
  "properties": {
    "addr:full":"11201 San Pablo Ave El Cerrito CA 94530",
    "addr:housenumber":"11201",
    "addr:postcode":"94530",
    "addr:street":"San Pablo Ave",
    "iso:country":"US",
    "sg:address":"11201 San Pablo Ave",
    "sg:city":"El Cerrito",
    "sg:classifiers":[
        {
            "category":"Shopping",
            "subcategory":"Florist",
            "type":"Retail Goods"
        }
    ],
    "sg:phone":"+1 510 237 5466",
    "sg:postcode":"94530",
    "sg:province":"CA",
    "wof:name":"El Cerrito Florist",
    "wof:placetype":"venue"
},
  "geometry": {"coordinates":[-122.314396,37.919469],"type":"Point"}
}