{
  "type": "Feature",
  "properties": {
    "addr:full":"1600 Pisco Ln Oxnard CA 93035",
    "addr:housenumber":"1600",
    "addr:postcode":"93035",
    "addr:street":"Pisco Ln",
    "iso:country":"US",
    "sg:address":"1600 Pisco Ln",
    "sg:city":"Oxnard",
    "sg:classifiers":[
        {
            "category":"Building & Trades",
            "subcategory":"Electrical",
            "type":"Services"
        }
    ],
    "sg:phone":"+1 805 382 2568",
    "sg:postcode":"93035",
    "sg:province":"CA",
    "sg:tags":[
        "work",
        "electrical"
    ],
    "wof:name":"James F Smith Elec Contrs",
    "wof:placetype":"venue"
},
  "geometry": {"coordinates":[-119.19700400000001,34.18917],"type":"Point"}
}