{
  "type": "Feature",
  "properties": {
    "iso:country":"US",
    "sg:address":"10417 Lakewood Blvd",
    "sg:city":"Downey",
    "sg:classifiers":[
        {
            "category":"Manufacturing",
            "subcategory":"Printing",
            "type":"Manufacturing & Wholesale Goods"
        }
    ],
    "sg:phone":"+1 562 861 0863",
    "sg:postcode":"90241",
    "sg:province":"CA",
    "sg:tags":[
        "commercial",
        "lithographic",
        "photocopying"
    ],
    "wof:name":"Pip Printing",
    "wof:placetype":"venue"
},
  "geometry": {"coordinates":[-118.11900300000001,33.943802],"type":"Point"}
}