{
  "type": "Feature",
  "properties": {
    "iso:country":"US",
    "sg:address":"4610 Pine St",
    "sg:city":"Riverside",
    "sg:classifiers":[
        {
            "category":"Personal",
            "subcategory":"Tanning Parlor",
            "type":"Services"
        }
    ],
    "sg:phone":"+1 951 682 2585",
    "sg:postcode":"92501",
    "sg:province":"CA",
    "sg:tags":[
        "salon"
    ],
    "wof:name":"Tropical Tanning II",
    "wof:placetype":"venue"
},
  "geometry": {"coordinates":[-117.389442,33.976991],"type":"Point"}
}