{
  "type": "Feature",
  "properties": {
    "iso:country":"US",
    "sg:address":"6427 Hollywood Blvd",
    "sg:city":"Los Angeles",
    "sg:classifiers":[
        {
            "category":"Shopping",
            "subcategory":"Hobbies, Toys, & Games",
            "type":"Retail Goods"
        }
    ],
    "sg:phone":"+1 323 962 8698",
    "sg:postcode":"90028",
    "sg:province":"CA",
    "sg:tags":[
        "toy",
        "store"
    ],
    "wof:name":"Dynasty Collections",
    "wof:placetype":"venue"
},
  "geometry": {"coordinates":[-118.330002,34.101501],"type":"Point"}
}