{
  "type": "Feature",
  "properties": {
    "iso:country":"US",
    "sg:address":"7066 Commerce Cir",
    "sg:city":"Pleasanton",
    "sg:classifiers":[
        {
            "category":"Communications",
            "type":"Services"
        }
    ],
    "sg:phone":"+1 925 426 9494",
    "sg:postcode":"94588",
    "sg:province":"CA",
    "sg:tags":[
        "communication"
    ],
    "wof:name":"Infinity Communications Inc",
    "wof:placetype":"venue"
},
  "geometry": {"coordinates":[-121.91598,37.698155],"type":"Point"}
}