{
  "type": "Feature",
  "properties": {
    "iso:country":"US",
    "sg:address":"8560 N Linda Ln",
    "sg:city":"Clovis",
    "sg:classifiers":[
        {
            "category":"Communications",
            "subcategory":"Film & Video Production",
            "type":"Services"
        }
    ],
    "sg:phone":"+1 559 299 7300",
    "sg:postcode":"93619",
    "sg:province":"CA",
    "sg:tags":[
        "taping"
    ],
    "wof:name":"Bryant Productions",
    "wof:placetype":"venue"
},
  "geometry": {"coordinates":[-119.676013,36.861209],"type":"Point"}
}