{
  "type": "Feature",
  "properties": {
    "addr:full":"3801 Wilson Rd Bakersfield CA 93309",
    "addr:housenumber":"3801",
    "addr:postcode":"93309",
    "addr:street":"Wilson Rd",
    "iso:country":"US",
    "sg:address":"3801 Wilson Rd",
    "sg:city":"Bakersfield",
    "sg:classifiers":[
        {
            "category":"Retail",
            "subcategory":"Repair Shop",
            "type":"Services"
        }
    ],
    "sg:phone":"+1 661 832 9702",
    "sg:postcode":"93309",
    "sg:province":"CA",
    "sg:tags":[
        "equipment",
        "dental",
        "refinishing"
    ],
    "wof:name":"Hayes The Local Handpiece",
    "wof:placetype":"venue"
},
  "geometry": {"coordinates":[-119.046414,35.332189],"type":"Point"}
}