{
  "type": "Feature",
  "properties": {
    "iso:country":"US",
    "sg:address":"21271 Burbank Blvd",
    "sg:city":"Woodland Hills",
    "sg:classifiers":[
        {
            "category":"Professional",
            "subcategory":"Lawyer & Legal Services",
            "type":"Services"
        }
    ],
    "sg:phone":"+1 818 992 6300",
    "sg:postcode":"91367",
    "sg:province":"CA",
    "sg:tags":[
        "attorney"
    ],
    "wof:name":"O'Meara & Smith",
    "wof:placetype":"venue"
},
  "geometry": {"coordinates":[-118.597435,34.173289],"type":"Point"}
}