{
  "type": "Feature",
  "properties": {
    "addr:full":"396 Atlantic Ave Pittsburg CA 94565",
    "addr:housenumber":"396",
    "addr:postcode":"94565",
    "addr:street":"Atlantic Ave",
    "iso:country":"US",
    "sg:address":"396 Atlantic Ave",
    "sg:city":"Pittsburg",
    "sg:classifiers":[
        {
            "category":"Shopping",
            "subcategory":"Department Store",
            "type":"Retail Goods"
        }
    ],
    "sg:phone":"+1 925 473 1343",
    "sg:postcode":"94565",
    "sg:province":"CA",
    "sg:website":"www.factory2-u.com",
    "wof:name":"Factory 2-U",
    "wof:placetype":"venue"
},
  "geometry": {"coordinates":[-121.888532,38.00802],"type":"Point"}
}