{
  "type": "Feature",
  "properties": {
    "addr:full":"2644 Centennial Cir Corona CA 92882",
    "addr:housenumber":"2644",
    "addr:postcode":"92882",
    "addr:street":"Centennial Cir",
    "iso:country":"US",
    "sg:address":"2644 Centennial Cir",
    "sg:city":"Corona",
    "sg:classifiers":[
        {
            "category":"Education",
            "subcategory":"Special Training",
            "type":"Public Place"
        }
    ],
    "sg:phone":"+1 951 733 6933",
    "sg:postcode":"92882",
    "sg:province":"CA",
    "sg:tags":[
        "aircraft",
        "school"
    ],
    "wof:name":"Coyote Vintage Aviation",
    "wof:placetype":"venue"
},
  "geometry": {"coordinates":[-117.60148100000001,33.85309],"type":"Point"}
}