{
  "type": "Feature",
  "properties": {
    "iso:country":"US",
    "sg:address":"921 S Coast Hwy",
    "sg:city":"Oceanside",
    "sg:classifiers":[
        {
            "category":"Health Services",
            "subcategory":"Clinic",
            "type":"Services"
        }
    ],
    "sg:phone":"+1 760 439 7498",
    "sg:postcode":"92054",
    "sg:province":"CA",
    "sg:tags":[
        "cannabis"
    ],
    "sg:website":"cannaconsultantsmedicalmarijuana...",
    "wof:name":"Canna Consultants Medical Marijuana Doctors",
    "wof:placetype":"venue"
},
  "geometry": {"coordinates":[-117.372483,33.187461],"type":"Point"}
}