{
  "type": "Feature",
  "properties": {
    "addr:full":"4759 Tomlinson Ave Riverside CA 92503",
    "addr:housenumber":"4759",
    "addr:postcode":"92503",
    "addr:street":"Tomlinson Ave",
    "iso:country":"US",
    "sg:address":"4759 Tomlinson Ave",
    "sg:city":"Riverside",
    "sg:classifiers":[
        {
            "category":"Professional",
            "subcategory":"Accounting & Tax Preparation",
            "type":"Services"
        }
    ],
    "sg:phone":"+1 951 687 4101",
    "sg:postcode":"92503",
    "sg:province":"CA",
    "sg:tags":[
        "bookkeeping",
        "general"
    ],
    "wof:name":"Sheldon's Bookkeeping & Tax",
    "wof:placetype":"venue"
},
  "geometry": {"coordinates":[-117.47158899999999,33.929438],"type":"Point"}
}