{
  "type": "Feature",
  "properties": {
    "iso:country":"US",
    "sg:address":"181 E 9th Ave",
    "sg:city":"Chico",
    "sg:classifiers":[
        {
            "category":"Home & Garden",
            "subcategory":"Garden Supply",
            "type":"Retail Goods"
        }
    ],
    "sg:phone":"+1 530 893 3030",
    "sg:postcode":"95926",
    "sg:province":"CA",
    "sg:tags":[
        "lawn",
        "mower"
    ],
    "wof:name":"Chico Power Equipment",
    "wof:placetype":"venue"
},
  "geometry": {"coordinates":[-121.850144,39.746848],"type":"Point"}
}