{
  "type": "Feature",
  "properties": {
    "iso:country":"US",
    "sg:address":"1111 E Ocean Ave",
    "sg:city":"Lompoc",
    "sg:classifiers":[
        {
            "category":"Health Services",
            "subcategory":"Medical Lab",
            "type":"Services"
        }
    ],
    "sg:phone":"+1 805 735 3608",
    "sg:postcode":"93436",
    "sg:province":"CA",
    "sg:tags":[
        "x"
    ],
    "wof:name":"Lompoc Hospital Outpatient Ima",
    "wof:placetype":"venue"
},
  "geometry": {"coordinates":[-120.442857,34.638957],"type":"Point"}
}