{
  "type": "Feature",
  "properties": {
    "iso:country":"US",
    "sg:address":"2731 Bodfish Canyon Rd",
    "sg:city":"Bodfish",
    "sg:classifiers":[
        {
            "category":"Building & Trades",
            "subcategory":"Construction",
            "type":"Services"
        }
    ],
    "sg:phone":"+1 760 379 1625",
    "sg:postcode":"93205",
    "sg:province":"CA",
    "sg:tags":[
        "maintenance",
        "contractor"
    ],
    "wof:name":"Rover Maintenance",
    "wof:placetype":"venue"
},
  "geometry": {"coordinates":[-118.451856,35.579281],"type":"Point"}
}