{
  "type": "Feature",
  "properties": {
    "iso:country":"US",
    "sg:address":"1524 E Main St",
    "sg:city":"Woodland",
    "sg:classifiers":[
        {
            "category":"Travel",
            "subcategory":"Hotels & Motels",
            "type":"Entertainment"
        }
    ],
    "sg:phone":"+1 530 666 3800",
    "sg:postcode":"95776",
    "sg:province":"CA",
    "sg:tags":[
        "corporate",
        "lodging"
    ],
    "sg:website":"http://www.daysinn.com",
    "wof:name":"Woodland Days Inn",
    "wof:placetype":"venue"
},
  "geometry": {"coordinates":[-121.749954,38.677264],"type":"Point"}
}