{
  "type": "Feature",
  "properties": {
    "addr:full":"5350 Ontario Mills Pkwy Ontario CA 91764",
    "addr:housenumber":"5350",
    "addr:postcode":"91764",
    "addr:street":"Ontario Mills Pkwy",
    "iso:country":"US",
    "sg:address":"5350 Ontario Mills Pkwy",
    "sg:city":"Ontario",
    "sg:classifiers":[
        {
            "category":"Recreation",
            "subcategory":"Picnic Area",
            "type":"Entertainment"
        },
        {
            "category":"Landmark",
            "subcategory":"Tourist Information",
            "type":"Public Place"
        }
    ],
    "sg:phone":"+1 909 980 0286",
    "sg:postcode":"91764",
    "sg:province":"CA",
    "sg:tags":[
        "attraction",
        "amusement",
        "arcade"
    ],
    "wof:name":"K 1 Speed",
    "wof:placetype":"venue"
},
  "geometry": {"coordinates":[-117.53817600000001,34.069958],"type":"Point"}
}