{
  "type": "Feature",
  "properties": {
    "iso:country":"US",
    "sg:address":"20407 Brian Way",
    "sg:city":"Tehachapi",
    "sg:classifiers":[
        {
            "category":"Shopping",
            "subcategory":"Musical Instruments",
            "type":"Retail Goods"
        }
    ],
    "sg:phone":"+1 661 822 0459",
    "sg:postcode":"93561",
    "sg:province":"CA",
    "wof:name":"Lee's House Of Music",
    "wof:placetype":"venue"
},
  "geometry": {"coordinates":[-118.49195899999999,35.125234],"type":"Point"}
}