{
  "type": "Feature",
  "properties": {
    "iso:country":"US",
    "sg:address":"171 Brush St",
    "sg:city":"Ukiah",
    "sg:classifiers":[
        {
            "category":"Education",
            "subcategory":"Special Training",
            "type":"Public Place"
        }
    ],
    "sg:phone":"+1 707 621 1388",
    "sg:postcode":"95482",
    "sg:province":"CA",
    "sg:tags":[
        "ceramics"
    ],
    "wof:name":"Stacey Mc Dorman",
    "wof:placetype":"venue"
},
  "geometry": {"coordinates":[-123.20687,39.159194],"type":"Point"}
}