{
  "type": "Feature",
  "properties": {
    "addr:full":"212 Warren Way San Luis Obispo CA 93405",
    "addr:housenumber":"212",
    "addr:postcode":"93405",
    "addr:street":"Warren Way",
    "iso:country":"US",
    "sg:address":"212 Warren Way",
    "sg:city":"San Luis Obispo",
    "sg:classifiers":[
        {
            "category":"Building & Trades",
            "subcategory":"Plumbing",
            "type":"Services"
        }
    ],
    "sg:phone":"+1 805 544 1833",
    "sg:postcode":"93405",
    "sg:province":"CA",
    "sg:tags":[
        "contractor"
    ],
    "wof:name":"Gold Coast Plumbing",
    "wof:placetype":"venue"
},
  "geometry": {"coordinates":[-120.683173,35.297622],"type":"Point"}
}