{
  "type": "Feature",
  "properties": {
    "iso:country":"US",
    "sg:address":"1401 E 51st Street",
    "sg:city":"Los Angeles",
    "sg:classifiers":[
        {
            "category":"Ice Cream",
            "type":"Food & Drink"
        }
    ],
    "sg:phone":"+1 323 232 2542",
    "sg:postcode":"90011",
    "sg:province":"CA",
    "sg:tags":[
        "frozen",
        "yogurt"
    ],
    "wof:name":"Ice Cream Saritas",
    "wof:placetype":"venue"
},
  "geometry": {"coordinates":[-118.249942,33.996652],"type":"Point"}
}