{
  "type": "Feature",
  "properties": {
    "iso:country":"US",
    "sg:address":"1800 S Main St",
    "sg:city":"Lakeport",
    "sg:classifiers":[
        {
            "category":"Professional",
            "subcategory":"Lawyer & Legal Services",
            "type":"Services"
        }
    ],
    "sg:phone":"+1 707 263 6633",
    "sg:postcode":"95453",
    "sg:province":"CA",
    "sg:tags":[
        "attorney"
    ],
    "wof:name":"Betty J Browner",
    "wof:placetype":"venue"
},
  "geometry": {"coordinates":[-122.915949,39.032374],"type":"Point"}
}