{
  "type": "Feature",
  "properties": {
    "iso:country":"US",
    "sg:address":"560 S Murphy Ave",
    "sg:city":"Sunnyvale",
    "sg:classifiers":[
        {
            "category":"Cinema",
            "subcategory":"Movie Rental",
            "type":"Entertainment"
        }
    ],
    "sg:phone":"+1 408 737 8802",
    "sg:postcode":"94086",
    "sg:province":"CA",
    "sg:tags":[
        "game",
        "video"
    ],
    "wof:name":"Coconut Hill Indian Video",
    "wof:placetype":"venue"
},
  "geometry": {"coordinates":[-122.03299699999999,37.369701],"type":"Point"}
}