{
  "type": "Feature",
  "properties": {
    "iso:country":"US",
    "sg:address":"5155 Convoy St",
    "sg:city":"San Diego",
    "sg:classifiers":[
        {
            "category":"Autos & Motor Vehicles",
            "subcategory":"Automobile Sales",
            "type":"Retail Goods"
        }
    ],
    "sg:phone":"+1 858 292 1963",
    "sg:postcode":"92111",
    "sg:province":"CA",
    "sg:tags":[
        "classic"
    ],
    "wof:name":"Shelby Cobras-Only Yesterday",
    "wof:placetype":"venue"
},
  "geometry": {"coordinates":[-117.152683,32.834564],"type":"Point"}
}