{
  "type": "Feature",
  "properties": {
    "addr:full":"576 Vermont St San Francisco CA 94199",
    "addr:housenumber":"576",
    "addr:postcode":"94199",
    "addr:street":"Vermont St",
    "iso:country":"US",
    "sg:address":"576 Vermont St",
    "sg:city":"San Francisco",
    "sg:classifiers":[
        {
            "category":"Building & Trades",
            "subcategory":"Construction",
            "type":"Services"
        }
    ],
    "sg:phone":"+1 415 487 0992",
    "sg:postcode":"94199",
    "sg:province":"CA",
    "sg:tags":[
        "contractor"
    ],
    "wof:name":"Eco Wood Floors",
    "wof:placetype":"venue"
},
  "geometry": {"coordinates":[-122.40427200000001,37.762399],"type":"Point"}
}