{
  "type": "Feature",
  "properties": {
    "iso:country":"US",
    "sg:address":"23407 Berwick Pl",
    "sg:city":"Valencia",
    "sg:classifiers":[
        {
            "category":"Professional",
            "type":"Services"
        }
    ],
    "sg:phone":"+1 661 513 9800",
    "sg:postcode":"91354",
    "sg:province":"CA",
    "wof:name":"Blame It On Mariah Inc",
    "wof:placetype":"venue"
},
  "geometry": {"coordinates":[-118.54555499999999,34.432794],"type":"Point"}
}