{
  "type": "Feature",
  "properties": {
    "iso:country":"US",
    "sg:address":"3015 J St",
    "sg:city":"Sacramento",
    "sg:classifiers":[
        {
            "category":"Health Services",
            "subcategory":"Health Practitioner",
            "type":"Services"
        }
    ],
    "sg:phone":"+1 916 443 4005",
    "sg:postcode":"95816",
    "sg:province":"CA",
    "sg:tags":[
        "acupuncture"
    ],
    "wof:name":"Tian Chao Herbs",
    "wof:placetype":"venue"
},
  "geometry": {"coordinates":[-121.46532999999999,38.572895],"type":"Point"}
}