{
  "type": "Feature",
  "properties": {
    "addr:full":"2383 N Oxnard Blvd Oxnard CA 93036",
    "addr:housenumber":"2383",
    "addr:postcode":"93036",
    "addr:street":"N Oxnard Blvd",
    "iso:country":"US",
    "sg:address":"2383 N Oxnard Blvd",
    "sg:city":"Oxnard",
    "sg:classifiers":[
        {
            "category":"Professional",
            "subcategory":"Accounting & Tax Preparation",
            "type":"Services"
        }
    ],
    "sg:phone":"+1 805 983 6639",
    "sg:postcode":"93036",
    "sg:province":"CA",
    "sg:tags":[
        "return",
        "filing"
    ],
    "wof:name":"H & R Block Tax Svc",
    "wof:placetype":"venue"
},
  "geometry": {"coordinates":[-119.177739,34.227136],"type":"Point"}
}