{
  "type": "Feature",
  "properties": {
    "addr:full":"1136 Broadway El Cajon CA 92021",
    "addr:housenumber":"1136",
    "addr:postcode":"92021",
    "addr:street":"Broadway",
    "iso:country":"US",
    "sg:address":"1136 Broadway",
    "sg:city":"El Cajon",
    "sg:classifiers":[
        {
            "category":"Social Services",
            "type":"Services"
        }
    ],
    "sg:phone":"+1 619 562 5850",
    "sg:postcode":"92021",
    "sg:province":"CA",
    "sg:tags":[
        "organization",
        "welfare"
    ],
    "wof:name":"Accord East County DUIP",
    "wof:placetype":"venue"
},
  "geometry": {"coordinates":[-116.941666,32.807783],"type":"Point"}
}