{
  "type": "Feature",
  "properties": {
    "addr:full":"308 Santa Isabel Ave Costa Mesa CA 92627",
    "addr:housenumber":"308",
    "addr:postcode":"92627",
    "addr:street":"Santa Isabel Ave",
    "iso:country":"US",
    "sg:address":"308 Santa Isabel Ave",
    "sg:city":"Costa Mesa",
    "sg:classifiers":[
        {
            "category":"Building & Trades",
            "subcategory":"Construction",
            "type":"Services"
        }
    ],
    "sg:phone":"+1 949 642 2647",
    "sg:postcode":"92627",
    "sg:province":"CA",
    "sg:tags":[
        "handyman"
    ],
    "wof:name":"Fixations",
    "wof:placetype":"venue"
},
  "geometry": {"coordinates":[-117.895769,33.652593],"type":"Point"}
}