{
  "type": "Feature",
  "properties": {
    "addr:full":"408 Chapala St Santa Barbara CA 93101",
    "addr:housenumber":"408",
    "addr:postcode":"93101",
    "addr:street":"Chapala St",
    "iso:country":"US",
    "sg:address":"408 Chapala St",
    "sg:city":"Santa Barbara",
    "sg:classifiers":[
        {
            "category":"Autos & Motor Vehicles",
            "subcategory":"Motorcycle Sales",
            "type":"Retail Goods"
        }
    ],
    "sg:phone":"+1 805 965 4814",
    "sg:postcode":"93101",
    "sg:province":"CA",
    "sg:tags":[
        "scooter"
    ],
    "wof:name":"Honda",
    "wof:placetype":"venue"
},
  "geometry": {"coordinates":[-119.696505,34.415708],"type":"Point"}
}