{
  "type": "Feature",
  "properties": {
    "iso:country":"US",
    "sg:address":"1211 E Pine Ave",
    "sg:city":"Lompoc",
    "sg:classifiers":[
        {
            "category":"Education",
            "subcategory":"School",
            "type":"Public Place"
        }
    ],
    "sg:phone":"+1 805 742 2100",
    "sg:postcode":"93436",
    "sg:province":"CA",
    "sg:tags":[
        "elementary"
    ],
    "sg:website":"http://www.d-scene.com",
    "wof:name":"Leonora Fillmore Elementary School",
    "wof:placetype":"venue"
},
  "geometry": {"coordinates":[-120.443742,34.650059],"type":"Point"}
}