{
  "type": "Feature",
  "properties": {
    "addr:full":"410 S Lemon St Fullerton CA 92832",
    "addr:housenumber":"410",
    "addr:postcode":"92832",
    "addr:street":"S Lemon St",
    "iso:country":"US",
    "sg:address":"410 S Lemon St",
    "sg:city":"Fullerton",
    "sg:classifiers":[
        {
            "category":"Food & Beverages",
            "subcategory":"Groceries & Convenience Stores",
            "type":"Retail Goods"
        }
    ],
    "sg:phone":"+1 714 525 1881",
    "sg:postcode":"92832",
    "sg:province":"CA",
    "wof:name":"San Marcos Market",
    "wof:placetype":"venue"
},
  "geometry": {"coordinates":[-117.91958200000001,33.867235],"type":"Point"}
}