{
  "type": "Feature",
  "properties": {
    "addr:full":"3610 Bassett St Santa Clara CA 95054",
    "addr:housenumber":"3610",
    "addr:postcode":"95054",
    "addr:street":"Bassett St",
    "iso:country":"US",
    "sg:address":"3610 Bassett St",
    "sg:city":"Santa Clara",
    "sg:classifiers":[
        {
            "category":"Manufacturing",
            "subcategory":"Tools & Machinery",
            "type":"Manufacturing & Wholesale Goods"
        }
    ],
    "sg:phone":"+1 408 970 8360",
    "sg:postcode":"95054",
    "sg:province":"CA",
    "sg:tags":[
        "industrial",
        "mfg"
    ],
    "wof:name":"Letech Manufacturing",
    "wof:placetype":"venue"
},
  "geometry": {"coordinates":[-121.953328,37.386141],"type":"Point"}
}