{
  "type": "Feature",
  "properties": {
    "addr:full":"724 Colleen Dr San Jose CA 95123",
    "addr:housenumber":"724",
    "addr:postcode":"95123",
    "addr:street":"Colleen Dr",
    "iso:country":"US",
    "sg:address":"724 Colleen Dr",
    "sg:city":"San Jose",
    "sg:classifiers":[
        {
            "category":"Building & Trades",
            "subcategory":"Electrical",
            "type":"Services"
        }
    ],
    "sg:phone":"+1 408 224 0176",
    "sg:postcode":"95123",
    "sg:province":"CA",
    "sg:tags":[
        "general",
        "electrical",
        "contractor"
    ],
    "wof:name":"Delta Electric",
    "wof:placetype":"venue"
},
  "geometry": {"coordinates":[-121.83743800000001,37.229756],"type":"Point"}
}