{
  "type": "Feature",
  "properties": {
    "addr:full":"1447 Eaton Rd San Dimas CA 91773",
    "addr:housenumber":"1447",
    "addr:postcode":"91773",
    "addr:street":"Eaton Rd",
    "iso:country":"US",
    "sg:address":"1447 Eaton Rd",
    "sg:city":"San Dimas",
    "sg:classifiers":[
        {
            "category":"Building & Trades",
            "subcategory":"Cleaning & Sanitation",
            "type":"Services"
        }
    ],
    "sg:phone":"+1 909 599 2243",
    "sg:postcode":"91773",
    "sg:province":"CA",
    "sg:tags":[
        "janitor"
    ],
    "wof:name":"Advanced Building Maintenance",
    "wof:placetype":"venue"
},
  "geometry": {"coordinates":[-117.836085,34.105323],"type":"Point"}
}