{
  "type": "Feature",
  "properties": {
    "iso:country":"US",
    "sg:address":"2251 West Ball Road",
    "sg:city":"Anaheim",
    "sg:classifiers":[
        {
            "category":"Shopping",
            "subcategory":"Discount & Variety Stores",
            "type":"Retail Goods"
        }
    ],
    "sg:phone":"+1 714 780 1155",
    "sg:postcode":"92804",
    "sg:province":"CA",
    "wof:name":"Dollar Discount Center",
    "wof:placetype":"venue"
},
  "geometry": {"coordinates":[-117.95946499999999,33.817794],"type":"Point"}
}