{
  "type": "Feature",
  "properties": {
    "addr:full":"3044 Kaanapali Way San Diego CA 92154",
    "addr:housenumber":"3044",
    "addr:postcode":"92154",
    "addr:street":"Kaanapali Way",
    "iso:country":"US",
    "sg:address":"3044 Kaanapali Way",
    "sg:city":"San Diego",
    "sg:classifiers":[
        {
            "category":"Food & Beverages",
            "subcategory":"Groceries & Convenience Stores",
            "type":"Retail Goods"
        }
    ],
    "sg:phone":"+1 619 429 1399",
    "sg:postcode":"92154",
    "sg:province":"CA",
    "sg:tags":[
        "market"
    ],
    "wof:name":"Pinoy Marketplace",
    "wof:placetype":"venue"
},
  "geometry": {"coordinates":[-117.06792900000001,32.58718],"type":"Point"}
}