{
  "type": "Feature",
  "properties": {
    "addr:full":"1900 N Palm Canyon Dr Palm Springs CA 92262",
    "addr:housenumber":"1900",
    "addr:postcode":"92262",
    "addr:street":"N Palm Canyon Dr",
    "iso:country":"US",
    "sg:address":"1900 N Palm Canyon Dr",
    "sg:city":"Palm Springs",
    "sg:classifiers":[
        {
            "category":"Travel",
            "subcategory":"Hotels & Motels",
            "type":"Entertainment"
        }
    ],
    "sg:phone":"+1 760 322 3757",
    "sg:postcode":"92262",
    "sg:province":"CA",
    "sg:website":"www.americasbestvalueinn.com",
    "wof:name":"America's Best Value Inn",
    "wof:placetype":"venue"
},
  "geometry": {"coordinates":[-116.547113,33.847237],"type":"Point"}
}