{
  "type": "Feature",
  "properties": {
    "iso:country":"US",
    "sg:address":"27137 5th St",
    "sg:city":"Highland",
    "sg:classifiers":[
        {
            "category":"Building & Trades",
            "subcategory":"Equipment Rental",
            "type":"Services"
        }
    ],
    "sg:phone":"+1 909 864 1810",
    "sg:postcode":"92346",
    "sg:province":"CA",
    "sg:tags":[
        "yard"
    ],
    "wof:name":"Highland Equipment Rental",
    "wof:placetype":"venue"
},
  "geometry": {"coordinates":[-117.212199,34.108045],"type":"Point"}
}