{
  "type": "Feature",
  "properties": {
    "iso:country":"US",
    "sg:address":"7574 Gibraltar St",
    "sg:city":"Carlsbad",
    "sg:classifiers":[
        {
            "category":"Building & Trades",
            "subcategory":"Construction",
            "type":"Services"
        }
    ],
    "sg:phone":"+1 760 943 0605",
    "sg:postcode":"92009",
    "sg:province":"CA",
    "sg:tags":[
        "carpentry",
        "contractor"
    ],
    "wof:name":"Km Construction",
    "wof:placetype":"venue"
},
  "geometry": {"coordinates":[-117.248143,33.08501],"type":"Point"}
}