{
  "type": "Feature",
  "properties": {
    "iso:country":"US",
    "sg:address":"245 S Railroad Ave",
    "sg:city":"San Mateo",
    "sg:classifiers":[
        {
            "category":"Education",
            "subcategory":"Music School",
            "type":"Public Place"
        }
    ],
    "sg:phone":"+1 650 342 2208",
    "sg:postcode":"94401",
    "sg:province":"CA",
    "sg:tags":[
        "instrument",
        "teacher",
        "musical"
    ],
    "sg:website":"www.bstreetmusic.com/",
    "wof:name":"B Street Music",
    "wof:placetype":"venue"
},
  "geometry": {"coordinates":[-122.32199900000001,37.566601],"type":"Point"}
}