{
  "type": "Feature",
  "properties": {
    "addr:full":"6254 Satsuma Ave North Hollywood CA 91606",
    "addr:housenumber":"6254",
    "addr:postcode":"91606",
    "addr:street":"Satsuma Ave",
    "iso:country":"US",
    "sg:address":"6254 Satsuma Ave",
    "sg:city":"North Hollywood",
    "sg:classifiers":[
        {
            "category":"Building & Trades",
            "subcategory":"Plumbing",
            "type":"Services"
        }
    ],
    "sg:phone":"+1 818 985 2934",
    "sg:postcode":"91606",
    "sg:province":"CA",
    "sg:website":"www.rootermaster.com",
    "wof:name":"Rooter Master Plumbing",
    "wof:placetype":"venue"
},
  "geometry": {"coordinates":[-118.366997,34.1847],"type":"Point"}
}