{
  "type": "Feature",
  "properties": {
    "addr:full":"221 McHenry Ave Modesto CA 95354",
    "addr:housenumber":"221",
    "addr:postcode":"ca 95354",
    "addr:street":"Mchenry Ave",
    "iso:country":"US",
    "sg:address":"221 McHenry Ave",
    "sg:city":"Modesto",
    "sg:classifiers":[
        {
            "category":"Building & Trades",
            "subcategory":"Equipment Rental",
            "type":"Services"
        }
    ],
    "sg:phone":"+1 209 521 7260",
    "sg:postcode":"95354",
    "sg:province":"CA",
    "sg:tags":[
        "disabled",
        "person",
        "supply"
    ],
    "wof:name":"Modesto Independent Living Ctr",
    "wof:placetype":"venue"
},
  "geometry": {"coordinates":[-120.99379500000001,37.648139],"type":"Point"}
}