{
  "type": "Feature",
  "properties": {
    "addr:full":"45 Windsor Ave Kensington CA 94708",
    "addr:housenumber":"45",
    "addr:postcode":"94708",
    "addr:street":"Windsor Ave",
    "iso:country":"US",
    "sg:address":"45 Windsor Ave",
    "sg:city":"Kensington",
    "sg:classifiers":[
        {
            "category":"Personal",
            "type":"Services"
        }
    ],
    "sg:phone":"+1 510 526 4657",
    "sg:postcode":"94708",
    "sg:province":"CA",
    "sg:tags":[
        "program",
        "physical",
        "exercise",
        "fitness"
    ],
    "wof:name":"Fit First",
    "wof:placetype":"venue"
},
  "geometry": {"coordinates":[-122.278837,37.911256],"type":"Point"}
}