{
  "type": "Feature",
  "properties": {
    "addr:full":"9000 Ming Ave Bakersfield CA 93309",
    "addr:housenumber":"9000",
    "addr:postcode":"93309",
    "addr:street":"Ming Ave",
    "iso:country":"US",
    "sg:address":"9000 Ming Ave",
    "sg:city":"Bakersfield",
    "sg:classifiers":[
        {
            "category":"Retail",
            "subcategory":"Laundry & Dry Cleaning",
            "type":"Services"
        }
    ],
    "sg:phone":"+1 661 634 1211",
    "sg:postcode":"93309",
    "sg:province":"CA",
    "sg:tags":[
        "cleaners"
    ],
    "wof:name":"Today Cleaners",
    "wof:placetype":"venue"
},
  "geometry": {"coordinates":[-119.10193599999999,35.339841],"type":"Point"}
}