{
  "type": "Feature",
  "properties": {
    "addr:full":"2521 Stockton Blvd Sacramento CA 95817",
    "addr:housenumber":"2521",
    "addr:postcode":"95817",
    "addr:street":"Stockton Blvd",
    "iso:country":"US",
    "sg:address":"2521 Stockton Blvd",
    "sg:city":"Sacramento",
    "sg:classifiers":[
        {
            "category":"Health Services",
            "subcategory":"Doctor",
            "type":"Services"
        }
    ],
    "sg:phone":"+1 916 734 3112",
    "sg:postcode":"95817",
    "sg:province":"CA",
    "sg:tags":[
        "cardiologist"
    ],
    "wof:name":"Jocson Jennifer MD Pediatrics",
    "wof:placetype":"venue"
},
  "geometry": {"coordinates":[-121.455752,38.552318],"type":"Point"}
}