{
  "type": "Feature",
  "properties": {
    "iso:country":"US",
    "sg:address":"40079 Mission Blvd",
    "sg:city":"Fremont",
    "sg:classifiers":[
        {
            "category":"Recreation",
            "type":"Entertainment"
        }
    ],
    "sg:phone":"+1 510 226 1481",
    "sg:postcode":"94539",
    "sg:province":"CA",
    "sg:tags":[
        "martial",
        "arts",
        "instruction"
    ],
    "wof:name":"West Coast Karate",
    "wof:placetype":"venue"
},
  "geometry": {"coordinates":[-121.950504,37.556662],"type":"Point"}
}