{
  "type": "Feature",
  "properties": {
    "addr:full":"1213 Meadowlark Dr Fairfield CA 94533",
    "addr:housenumber":"1213",
    "addr:postcode":"94533",
    "addr:street":"Meadowlark Dr",
    "iso:country":"US",
    "sg:address":"1213 Meadowlark Dr",
    "sg:city":"Fairfield",
    "sg:classifiers":[
        {
            "category":"Building & Trades",
            "subcategory":"Landscaping Services",
            "type":"Services"
        }
    ],
    "sg:phone":"+1 707 429 3218",
    "sg:postcode":"94533",
    "sg:province":"CA",
    "wof:name":"Veterans Lawn Service",
    "wof:placetype":"venue"
},
  "geometry": {"coordinates":[-122.00743900000001,38.267024],"type":"Point"}
}