{
  "type": "Feature",
  "properties": {
    "addr:full":"1000 Roth Rd French Camp CA 95231",
    "addr:housenumber":"1000",
    "addr:postcode":"95231",
    "addr:street":"Roth Rd",
    "iso:country":"US",
    "sg:address":"1000 Roth Rd",
    "sg:city":"French Camp",
    "sg:classifiers":[
        {
            "category":"Freight",
            "type":"Transportation"
        }
    ],
    "sg:phone":"+1 209 942 5391",
    "sg:postcode":"95231",
    "sg:province":"CA",
    "sg:tags":[
        "cargo",
        "handler",
        "marine"
    ],
    "wof:name":"Ssa Marine",
    "wof:placetype":"venue"
},
  "geometry": {"coordinates":[-121.256365,37.855519],"type":"Point"}
}