{
  "type": "Feature",
  "properties": {
    "addr:full":"564 Market St San Francisco CA 94104",
    "addr:housenumber":"564",
    "addr:postcode":"94104",
    "addr:street":"Market St",
    "iso:country":"US",
    "sg:address":"564 Market St",
    "sg:city":"San Francisco",
    "sg:classifiers":[
        {
            "category":"Banks & Credit Unions",
            "subcategory":"Financial Services",
            "type":"Services"
        }
    ],
    "sg:phone":"+1 415 397 2526",
    "sg:postcode":"94104",
    "sg:province":"CA",
    "sg:tags":[
        "program",
        "scholarship"
    ],
    "sg:website":"www.nmfonline.org",
    "wof:name":"National Medical Fellowships",
    "wof:placetype":"venue"
},
  "geometry": {"coordinates":[-122.400527,37.790271],"type":"Point"}
}