{
  "type": "Feature",
  "properties": {
    "iso:country":"US",
    "sg:address":"12444 W McKinley Dr",
    "sg:city":"Blythe",
    "sg:classifiers":[
        {
            "category":"Retail",
            "subcategory":"Repair Shop",
            "type":"Services"
        }
    ],
    "sg:phone":"+1 760 922 3120",
    "sg:postcode":"92225",
    "sg:province":"CA",
    "sg:tags":[
        "lock",
        "locksmith"
    ],
    "wof:name":"C B Enterprises Locksmith Svc",
    "wof:placetype":"venue"
},
  "geometry": {"coordinates":[-114.632874,33.611098],"type":"Point"}
}