{
  "type": "Feature",
  "properties": {
    "iso:country":"US",
    "sg:address":"13041 Rosecrans Ave Ste 201",
    "sg:city":"Norwalk",
    "sg:classifiers":[
        {
            "category":"Food & Beverages",
            "subcategory":"Groceries & Convenience Stores",
            "type":"Retail Goods"
        }
    ],
    "sg:phone":"+1 562 404 2870",
    "sg:postcode":"90650",
    "sg:province":"CA",
    "wof:name":"T & S Mart",
    "wof:placetype":"venue"
},
  "geometry": {"coordinates":[-118.393625,33.902572],"type":"Point"}
}