{
  "type": "Feature",
  "properties": {
    "addr:full":"7851 Mission Center Ct Ste 250 San Diego CA 92108",
    "addr:housenumber":"7851",
    "addr:postcode":"92108",
    "addr:street":"Mission Center Ct Ste 250",
    "iso:country":"US",
    "sg:address":"7851 Mission Center Ct Ste 250",
    "sg:city":"San Diego",
    "sg:classifiers":[
        {
            "category":"Professional",
            "subcategory":"Lawyer & Legal Services",
            "type":"Services"
        }
    ],
    "sg:phone":"+1 619 239 8181",
    "sg:postcode":"92108",
    "sg:province":"CA",
    "wof:name":"Alpert Phillip S Law Corp",
    "wof:placetype":"venue"
},
  "geometry": {"coordinates":[-117.155356,32.773064],"type":"Point"}
}