{
  "type": "Feature",
  "properties": {
    "addr:full":"1011 5th St Modesto CA 95351",
    "addr:housenumber":"1011",
    "addr:postcode":"ca 95351",
    "addr:street":"5Th St",
    "iso:country":"US",
    "sg:address":"1011 5th St",
    "sg:city":"Modesto",
    "sg:classifiers":[
        {
            "category":"Retail",
            "subcategory":"Auto Repair",
            "type":"Services"
        }
    ],
    "sg:phone":"+1 209 578 1782",
    "sg:postcode":"95351",
    "sg:province":"CA",
    "sg:tags":[
        "muffler",
        "exhaust",
        "system"
    ],
    "wof:name":"Royal Muffler",
    "wof:placetype":"venue"
},
  "geometry": {"coordinates":[-121.00614899999999,37.637757],"type":"Point"}
}