{
  "type": "Feature",
  "properties": {
    "addr:full":"182 Country Club Gate Center Pacific Grove CA 93950",
    "addr:housenumber":"182",
    "addr:postcode":"93950",
    "addr:street":"Country Club Gate",
    "iso:country":"US",
    "sg:address":"182 Country Club Gate Center",
    "sg:city":"Pacific Grove",
    "sg:classifiers":[
        {
            "category":"Shopping",
            "type":"Retail Goods"
        }
    ],
    "sg:phone":"+1 831 643 0260",
    "sg:postcode":"93950",
    "sg:province":"CA",
    "sg:tags":[
        "art",
        "gallery",
        "dealer"
    ],
    "wof:name":"Stokes Collection",
    "wof:placetype":"venue"
},
  "geometry": {"coordinates":[-121.922904,36.609131],"type":"Point"}
}