{
  "type": "Feature",
  "properties": {
    "addr:full":"443 Park Royal Ave Santa Rosa CA 95401",
    "addr:housenumber":"443",
    "addr:postcode":"95401",
    "addr:street":"Park Royal Ave",
    "iso:country":"US",
    "sg:address":"443 Park Royal Ave",
    "sg:city":"Santa Rosa",
    "sg:classifiers":[
        {
            "category":"Building & Trades",
            "subcategory":"Construction",
            "type":"Services"
        }
    ],
    "sg:phone":"+1 707 571 8326",
    "sg:postcode":"95401",
    "sg:province":"CA",
    "sg:tags":[
        "acoustical",
        "contractor"
    ],
    "wof:name":"Dana Kitchens & Assoc",
    "wof:placetype":"venue"
},
  "geometry": {"coordinates":[-122.78126899999999,38.438845],"type":"Point"}
}