{
  "type": "Feature",
  "properties": {
    "addr:full":"951 Cll Negocio San Clemente CA 92673",
    "addr:housenumber":"951",
    "addr:postcode":"92673",
    "addr:street":"Cll Negocio",
    "iso:country":"US",
    "sg:address":"951 Cll Negocio",
    "sg:city":"San Clemente",
    "sg:classifiers":[
        {
            "category":"Real Estate",
            "subcategory":"Developer",
            "type":"Services"
        }
    ],
    "sg:phone":"+1 949 498 1366",
    "sg:postcode":"92673",
    "sg:province":"CA",
    "sg:tags":[
        "company",
        "land",
        "dev"
    ],
    "sg:website":"www.talega.com",
    "wof:name":"Talega Associates LLC",
    "wof:placetype":"venue"
},
  "geometry": {"coordinates":[-117.604938,33.452112],"type":"Point"}
}