{
  "type": "Feature",
  "properties": {
    "iso:country":"US",
    "sg:address":"1495 W 9th St",
    "sg:city":"Upland",
    "sg:classifiers":[
        {
            "category":"Manufacturing",
            "subcategory":"Tools & Machinery",
            "type":"Manufacturing & Wholesale Goods"
        }
    ],
    "sg:phone":"+1 909 946 0683",
    "sg:postcode":"91786",
    "sg:province":"CA",
    "sg:tags":[
        "shop",
        "machine",
        "engineering",
        "industrial",
        "mfg"
    ],
    "wof:name":"AST Engineering",
    "wof:placetype":"venue"
},
  "geometry": {"coordinates":[-117.67118000000001,34.0961],"type":"Point"}
}