{
  "type": "Feature",
  "properties": {
    "iso:country":"US",
    "sg:address":"238 Palm Ave",
    "sg:city":"Imperial Beach",
    "sg:classifiers":[
        {
            "category":"Professional",
            "type":"Services"
        }
    ],
    "sg:phone":"+1 619 424 8760",
    "sg:postcode":"91932",
    "sg:province":"CA",
    "wof:name":"American Cutter Inc",
    "wof:placetype":"venue"
},
  "geometry": {"coordinates":[-117.127768,32.584011],"type":"Point"}
}