{
  "type": "Feature",
  "properties": {
    "iso:country":"US",
    "sg:address":"1840 S Santa Fe St",
    "sg:city":"Santa Ana",
    "sg:classifiers":[
        {
            "category":"Manufacturing",
            "subcategory":"Toys & Sporting Goods",
            "type":"Manufacturing & Wholesale Goods"
        }
    ],
    "sg:phone":"+1 714 546 3045",
    "sg:postcode":"92705",
    "sg:province":"CA",
    "sg:tags":[
        "radio",
        "mfg",
        "controlled",
        "car"
    ],
    "wof:name":"Raco Modelcraft Inc",
    "wof:placetype":"venue"
},
  "geometry": {"coordinates":[-117.853465,33.724123],"type":"Point"}
}