{
  "type": "Feature",
  "properties": {
    "addr:full":"20850 Pepper Tree Ln Cupertino CA 95014",
    "addr:housenumber":"20850",
    "addr:postcode":"95014",
    "addr:street":"Pepper Tree Ln",
    "iso:country":"US",
    "sg:address":"20850 Pepper Tree Ln",
    "sg:city":"Cupertino",
    "sg:classifiers":[
        {
            "category":"Shopping",
            "subcategory":"Discount & Variety Stores",
            "type":"Retail Goods"
        }
    ],
    "sg:phone":"+1 408 255 5175",
    "sg:postcode":"95014",
    "sg:province":"CA",
    "sg:tags":[
        "merchandise",
        "general"
    ],
    "wof:name":"Ruell Ann",
    "wof:placetype":"venue"
},
  "geometry": {"coordinates":[-122.041282,37.319556],"type":"Point"}
}