{
  "type": "Feature",
  "properties": {
    "addr:full":"5877 Rodeo Rd Los Angeles CA 90016",
    "addr:housenumber":"5877",
    "addr:postcode":"90016",
    "addr:street":"Rodeo Rd",
    "iso:country":"US",
    "sg:address":"5877 Rodeo Rd",
    "sg:city":"Los Angeles",
    "sg:classifiers":[
        {
            "category":"Recreation",
            "type":"Entertainment"
        }
    ],
    "sg:phone":"+1 310 836 2000",
    "sg:postcode":"90016",
    "sg:province":"CA",
    "sg:tags":[
        "amusement"
    ],
    "wof:name":"Next Motor Sports",
    "wof:placetype":"venue"
},
  "geometry": {"coordinates":[-118.375519,34.021928],"type":"Point"}
}