{
  "type": "Feature",
  "properties": {
    "iso:country":"US",
    "sg:address":"6409 Independence Ave",
    "sg:city":"Woodland Hills",
    "sg:classifiers":[
        {
            "category":"Freight",
            "type":"Transportation"
        }
    ],
    "sg:phone":"+1 818 710 6300",
    "sg:postcode":"91367",
    "sg:province":"CA",
    "sg:tags":[
        "delivery"
    ],
    "wof:name":"Warner Express Svc Inc",
    "wof:placetype":"venue"
},
  "geometry": {"coordinates":[-118.590687,34.188239],"type":"Point"}
}