{
  "type": "Feature",
  "properties": {
    "addr:full":"1955 Carroll Ave San Francisco CA 94124",
    "addr:housenumber":"1955",
    "addr:postcode":"94124",
    "addr:street":"Carroll Ave",
    "iso:country":"US",
    "sg:address":"1955 Carroll Ave",
    "sg:city":"San Francisco",
    "sg:classifiers":[
        {
            "category":"Food & Beverages",
            "subcategory":"Specialty",
            "type":"Retail Goods"
        }
    ],
    "sg:phone":"+1 415 656 4372",
    "sg:postcode":"94124",
    "sg:province":"CA",
    "sg:tags":[
        "herb"
    ],
    "wof:name":"Touch Of Sun Herbs",
    "wof:placetype":"venue"
},
  "geometry": {"coordinates":[-122.39983100000001,37.728724],"type":"Point"}
}