{
  "type": "Feature",
  "properties": {
    "iso:country":"US",
    "sg:address":"555 Riverdale Dr",
    "sg:city":"Glendale",
    "sg:classifiers":[
        {
            "category":"Real Estate",
            "subcategory":"Real Estate Agent",
            "type":"Services"
        }
    ],
    "sg:phone":"+1 818 502 2420",
    "sg:postcode":"91204",
    "sg:province":"CA",
    "sg:tags":[
        "finding",
        "apartment",
        "rental"
    ],
    "sg:website":"www.aptsforrent.com",
    "wof:name":"For Rent Magazine",
    "wof:placetype":"venue"
},
  "geometry": {"coordinates":[-118.26758100000001,34.138633],"type":"Point"}
}