{
  "type": "Feature",
  "properties": {
    "iso:country":"US",
    "sg:address":"1301 W Walnut Street",
    "sg:city":"Compton",
    "sg:classifiers":[
        {
            "category":"Shopping",
            "subcategory":"Bicycles & Sporting Goods",
            "type":"Retail Goods"
        }
    ],
    "sg:phone":"+1 310 631 3452",
    "sg:postcode":"90220",
    "sg:province":"CA",
    "wof:name":"Ziffco",
    "wof:placetype":"venue"
},
  "geometry": {"coordinates":[-118.244368,33.875596],"type":"Point"}
}