{
  "type": "Feature",
  "properties": {
    "addr:full":"1187 E Anaheim St Long Beach CA 90813",
    "addr:housenumber":"1187",
    "addr:postcode":"90813",
    "addr:street":"E Anaheim St",
    "iso:country":"US",
    "sg:address":"1187 E Anaheim St",
    "sg:city":"Long Beach",
    "sg:classifiers":[
        {
            "category":"Home & Garden",
            "subcategory":"Furniture",
            "type":"Retail Goods"
        }
    ],
    "sg:phone":"+1 562 599 2227",
    "sg:postcode":"90813",
    "sg:province":"CA",
    "sg:tags":[
        "bedding"
    ],
    "wof:name":"Mary's Wholesale Comforters",
    "wof:placetype":"venue"
},
  "geometry": {"coordinates":[-118.17723599999999,33.782679],"type":"Point"}
}