{
  "type": "Feature",
  "properties": {
    "iso:country":"US",
    "sg:address":"7508 E Endemont Ct",
    "sg:city":"Anaheim",
    "sg:classifiers":[
        {
            "category":"Professional",
            "type":"Services"
        }
    ],
    "sg:phone":"+1 714 280 8598",
    "sg:postcode":"92808",
    "sg:province":"CA",
    "wof:name":"Morey Inc",
    "wof:placetype":"venue"
},
  "geometry": {"coordinates":[-117.75094900000001,33.856162],"type":"Point"}
}