{
  "type": "Feature",
  "properties": {
    "iso:country":"US",
    "sg:address":"2493 Telegraph Ave",
    "sg:city":"Berkeley",
    "sg:classifiers":[
        {
            "category":"Shopping",
            "subcategory":"Clothing, Apparel, & Fashions",
            "type":"Retail Goods"
        }
    ],
    "sg:phone":"+1 510 549 0876",
    "sg:postcode":"94704",
    "sg:province":"CA",
    "sg:tags":[
        "clothing",
        "women's"
    ],
    "sg:website":"www.tiendahoberkeley.com",
    "wof:name":"Tienda Ho",
    "wof:placetype":"venue"
},
  "geometry": {"coordinates":[-122.25846,37.865247],"type":"Point"}
}