{
  "type": "Feature",
  "properties": {
    "iso:country":"US",
    "sg:address":"2561 Strozier Ave",
    "sg:city":"South El Monte",
    "sg:classifiers":[
        {
            "category":"Shopping",
            "subcategory":"Discount & Variety Stores",
            "type":"Retail Goods"
        }
    ],
    "sg:phone":"+1 626 582 8139",
    "sg:postcode":"91733",
    "sg:province":"CA",
    "sg:tags":[
        "merchandise",
        "general"
    ],
    "wof:name":"Prince Products Corp",
    "wof:placetype":"venue"
},
  "geometry": {"coordinates":[-118.050022,34.056164],"type":"Point"}
}