{
  "type": "Feature",
  "properties": {
    "iso:country":"US",
    "sg:address":"6930 Hollywood Blvd",
    "sg:city":"Los Angeles",
    "sg:classifiers":[
        {
            "category":"Banks & Credit Unions",
            "subcategory":"Bank",
            "type":"Services"
        }
    ],
    "sg:phone":"+1 323 000 1111",
    "sg:postcode":"90028",
    "sg:province":"CA",
    "wof:name":"California National Bank",
    "wof:placetype":"venue"
},
  "geometry": {"coordinates":[-118.341094,34.101464],"type":"Point"}
}