{
  "type": "Feature",
  "properties": {
    "addr:full":"3723 Old Santa Rita Rd Pleasanton CA 94588",
    "addr:housenumber":"3723",
    "addr:postcode":"94588",
    "addr:street":"Old Santa Rita Rd",
    "iso:country":"US",
    "sg:address":"3723 Old Santa Rita Rd",
    "sg:city":"Pleasanton",
    "sg:classifiers":[
        {
            "category":"Retail",
            "subcategory":"Auto Repair",
            "type":"Services"
        }
    ],
    "sg:phone":"+1 925 225 9500",
    "sg:postcode":"94588",
    "sg:province":"CA",
    "sg:tags":[
        "automobile",
        "diagnostic"
    ],
    "wof:name":"Vehicle Inspection Svc",
    "wof:placetype":"venue"
},
  "geometry": {"coordinates":[-121.87888700000001,37.700129],"type":"Point"}
}