{
  "type": "Feature",
  "properties": {
    "addr:full":"8928 W Olympic Blvd Beverly Hills CA 90211",
    "addr:housenumber":"8928",
    "addr:postcode":"90211",
    "addr:street":"W Olympic Blvd",
    "iso:country":"US",
    "sg:address":"8928 W Olympic Blvd",
    "sg:city":"Beverly Hills",
    "sg:classifiers":[
        {
            "category":"Professional",
            "subcategory":"Art Services",
            "type":"Services"
        }
    ],
    "sg:phone":"+1 310 858 7770",
    "sg:postcode":"90211",
    "sg:province":"CA",
    "sg:tags":[
        "photographer"
    ],
    "wof:name":"Loa Photography",
    "wof:placetype":"venue"
},
  "geometry": {"coordinates":[-118.387722,34.059363],"type":"Point"}
}