{
  "type": "Feature",
  "properties": {
    "iso:country":"US",
    "sg:address":"10815 Hesby St",
    "sg:city":"North Hollywood",
    "sg:classifiers":[
        {
            "category":"Retail",
            "subcategory":"Animal Services",
            "type":"Services"
        }
    ],
    "sg:phone":"+1 818 623 0512",
    "sg:postcode":"91601",
    "sg:province":"CA",
    "sg:tags":[
        "training",
        "dog"
    ],
    "wof:name":"Sand Castle Enterprises",
    "wof:placetype":"venue"
},
  "geometry": {"coordinates":[-118.367816,34.161805],"type":"Point"}
}