{
  "type": "Feature",
  "properties": {
    "iso:country":"US",
    "sg:address":"747 S Central Ave",
    "sg:city":"Los Angeles",
    "sg:classifiers":[
        {
            "category":"Food & Beverages",
            "subcategory":"Fruits & Vegetables",
            "type":"Retail Goods"
        }
    ],
    "sg:phone":"+1 213 236 9419",
    "sg:postcode":"90021",
    "sg:province":"CA",
    "sg:tags":[
        "produce"
    ],
    "wof:name":"Vegetales Tecoman",
    "wof:placetype":"venue"
},
  "geometry": {"coordinates":[-118.242442,34.035169],"type":"Point"}
}