{
  "type": "Feature",
  "properties": {
    "iso:country":"US",
    "sg:address":"6750 Foster Bridge Blvd",
    "sg:city":"Bell Gardens",
    "sg:classifiers":[
        {
            "category":"Building & Trades",
            "subcategory":"Electrical",
            "type":"Services"
        }
    ],
    "sg:phone":"+1 323 562 1858",
    "sg:postcode":"90201",
    "sg:province":"CA",
    "sg:tags":[
        "electric",
        "contractor"
    ],
    "wof:name":"Z Electric",
    "wof:placetype":"venue"
},
  "geometry": {"coordinates":[-118.138857,33.968495],"type":"Point"}
}