{
  "type": "Feature",
  "properties": {
    "addr:full":"11600 Alondra Blvd Norwalk CA 90650",
    "addr:housenumber":"11600",
    "addr:postcode":"90650",
    "addr:street":"Alondra Blvd",
    "iso:country":"US",
    "sg:address":"11600 Alondra Blvd",
    "sg:city":"Norwalk",
    "sg:classifiers":[
        {
            "category":"Manufacturing",
            "subcategory":"Apparel",
            "type":"Manufacturing & Wholesale Goods"
        }
    ],
    "sg:phone":"+1 562 924 5079",
    "sg:postcode":"90650",
    "sg:province":"CA",
    "sg:tags":[
        "embroidery"
    ],
    "wof:name":"S K Embroidery",
    "wof:placetype":"venue"
},
  "geometry": {"coordinates":[-118.086868,33.88755],"type":"Point"}
}