{
  "type": "Feature",
  "properties": {
    "addr:full":"1420 F St Modesto CA 95354",
    "addr:housenumber":"1420",
    "addr:postcode":"ca 95354",
    "addr:street":"F St",
    "iso:country":"US",
    "sg:address":"1420 F St",
    "sg:city":"Modesto",
    "sg:classifiers":[
        {
            "category":"Professional",
            "subcategory":"Lawyer & Legal Services",
            "type":"Services"
        }
    ],
    "sg:phone":"+1 209 529 3001",
    "sg:postcode":"95354",
    "sg:province":"CA",
    "sg:tags":[
        "attorney"
    ],
    "wof:name":"Mary Lynn Belsher",
    "wof:placetype":"venue"
},
  "geometry": {"coordinates":[-120.991041,37.640036],"type":"Point"}
}