{
  "type": "Feature",
  "properties": {
    "addr:full":"7249 Deering Ave Canoga Park CA 91303",
    "addr:housenumber":"7249",
    "addr:postcode":"91303",
    "addr:street":"Deering Ave",
    "iso:country":"US",
    "sg:address":"7249 Deering Ave",
    "sg:city":"Canoga Park",
    "sg:classifiers":[
        {
            "category":"Retail",
            "subcategory":"Auto Repair",
            "type":"Services"
        }
    ],
    "sg:phone":"+1 818 992 4000",
    "sg:postcode":"91303",
    "sg:province":"CA",
    "sg:tags":[
        "towing"
    ],
    "wof:name":"Atlas Towing",
    "wof:placetype":"venue"
},
  "geometry": {"coordinates":[-118.596715,34.201959],"type":"Point"}
}