{
  "type": "Feature",
  "properties": {
    "iso:country":"US",
    "sg:address":"9820 San Fernando Rd",
    "sg:city":"Pacoima",
    "sg:classifiers":[
        {
            "category":"Wholesale",
            "subcategory":"Scrap",
            "type":"Manufacturing & Wholesale Goods"
        }
    ],
    "sg:phone":"+1 818 899 8899",
    "sg:postcode":"91331",
    "sg:province":"CA",
    "sg:tags":[
        "material",
        "u",
        "supply"
    ],
    "wof:name":"Center Auto Dismantling",
    "wof:placetype":"venue"
},
  "geometry": {"coordinates":[-118.405502,34.251099],"type":"Point"}
}