{
  "type": "Feature",
  "properties": {
    "iso:country":"US",
    "sg:address":"2429 24th Street Apartment B",
    "sg:city":"San Francisco",
    "sg:classifiers":[
        {
            "category":"Health Services",
            "subcategory":"Health Practitioner",
            "type":"Services"
        }
    ],
    "sg:phone":"+1 415 285 0720",
    "sg:postcode":"94110",
    "sg:province":"CA",
    "sg:tags":[
        "therapy",
        "physical"
    ],
    "wof:name":"Cheryl Tyler, Massage Therapist",
    "wof:placetype":"venue"
},
  "geometry": {"coordinates":[-122.403902,37.75292],"type":"Point"}
}