{
  "type": "Feature",
  "properties": {
    "addr:full":"605 16th Ave San Francisco CA 94118",
    "addr:housenumber":"605",
    "addr:postcode":"94118",
    "addr:street":"16Th Ave",
    "iso:country":"US",
    "sg:address":"605 16th Ave",
    "sg:city":"San Francisco",
    "sg:classifiers":[
        {
            "category":"Government",
            "subcategory":"Office",
            "type":"Public Place"
        }
    ],
    "sg:phone":"+1 415 221 7701",
    "sg:postcode":"94118",
    "sg:province":"CA",
    "sg:tags":[
        "management"
    ],
    "wof:name":"Geoffrey M Chan",
    "wof:placetype":"venue"
},
  "geometry": {"coordinates":[-122.47476399999999,37.774949],"type":"Point"}
}