{
  "type": "Feature",
  "properties": {
    "addr:full":"1951 Redemeyer Rd Ukiah CA 95482",
    "addr:housenumber":"1951",
    "addr:postcode":"ca 95482",
    "addr:street":"Redemeyer Rd",
    "iso:country":"US",
    "sg:address":"1951 Redemeyer Rd",
    "sg:city":"Ukiah",
    "sg:classifiers":[
        {
            "category":"Organizations",
            "subcategory":"Community Association",
            "type":"Services"
        }
    ],
    "sg:phone":"+1 707 462 7727",
    "sg:postcode":"95482",
    "sg:province":"CA",
    "wof:name":"Delta Kppa Gmma Soc Intrntonal",
    "wof:placetype":"venue"
},
  "geometry": {"coordinates":[-123.187932,39.175629],"type":"Point"}
}