{
  "type": "Feature",
  "properties": {
    "addr:full":"3318 Harrison Ave Eureka CA 95503",
    "addr:housenumber":"3318",
    "addr:postcode":"95503",
    "addr:street":"Harrison Ave",
    "iso:country":"US",
    "sg:address":"3318 Harrison Ave",
    "sg:city":"Eureka",
    "sg:classifiers":[
        {
            "category":"Shopping",
            "subcategory":"Used Merchandise",
            "type":"Retail Goods"
        }
    ],
    "sg:phone":"+1 707 442 8191",
    "sg:postcode":"95503",
    "sg:province":"CA",
    "wof:name":"Next To You Inc",
    "wof:placetype":"venue"
},
  "geometry": {"coordinates":[-124.13972699999999,40.778061],"type":"Point"}
}