{
  "type": "Feature",
  "properties": {
    "addr:full":"590 S Vincent Ave Azusa CA 91702",
    "addr:housenumber":"590",
    "addr:postcode":"91702",
    "addr:street":"S Vincent Ave",
    "iso:country":"US",
    "sg:address":"590 S Vincent Ave",
    "sg:city":"Azusa",
    "sg:classifiers":[
        {
            "category":"Wholesale",
            "subcategory":"Medical Equipment & Supplies",
            "type":"Manufacturing & Wholesale Goods"
        }
    ],
    "sg:phone":"+1 626 812 0044",
    "sg:postcode":"91702",
    "sg:province":"CA",
    "sg:tags":[
        "physician",
        "surgeon"
    ],
    "wof:name":"Dis Inc",
    "wof:placetype":"venue"
},
  "geometry": {"coordinates":[-117.92527,34.111715],"type":"Point"}
}