{
  "type": "Feature",
  "properties": {
    "addr:full":"3535 Landfair Rd Pasadena CA 91107",
    "addr:housenumber":"3535",
    "addr:postcode":"91107",
    "addr:street":"Landfair Rd",
    "iso:country":"US",
    "sg:address":"3535 Landfair Rd",
    "sg:city":"Pasadena",
    "sg:classifiers":[
        {
            "category":"Building & Trades",
            "subcategory":"Construction",
            "type":"Services"
        }
    ],
    "sg:phone":"+1 626 390 3480",
    "sg:postcode":"91107",
    "sg:province":"CA",
    "sg:tags":[
        "roofing"
    ],
    "sg:website":"www.lansfordroofing.com",
    "wof:name":"Lansford Roofing Co, Inc",
    "wof:placetype":"venue"
},
  "geometry": {"coordinates":[-118.07708,34.159175],"type":"Point"}
}