{
  "type": "Feature",
  "properties": {
    "iso:country":"US",
    "sg:address":"1986 Geary Ave",
    "sg:city":"Sanger",
    "sg:classifiers":[
        {
            "category":"Building & Trades",
            "subcategory":"Landscaping Services",
            "type":"Services"
        }
    ],
    "sg:phone":"+1 559 305 2850",
    "sg:postcode":"93657",
    "sg:province":"CA",
    "sg:tags":[
        "landscape",
        "contractor"
    ],
    "wof:name":"A Rod Landscaping",
    "wof:placetype":"venue"
},
  "geometry": {"coordinates":[-119.56508100000001,36.718785],"type":"Point"}
}