{
  "type": "Feature",
  "properties": {
    "addr:full":"649 Pso de la Playa Redondo Beach CA 90277",
    "addr:housenumber":"649",
    "addr:postcode":"90277",
    "addr:street":"Pso De La Playa",
    "iso:country":"US",
    "sg:address":"649 Pso de la Playa",
    "sg:city":"Redondo Beach",
    "sg:classifiers":[
        {
            "category":"Insurance",
            "subcategory":"Insurance Agent",
            "type":"Services"
        }
    ],
    "sg:phone":"+1 310 791 0921",
    "sg:postcode":"90277",
    "sg:province":"CA",
    "sg:tags":[
        "taxicab"
    ],
    "wof:name":"Taw Insurance & Taxes",
    "wof:placetype":"venue"
},
  "geometry": {"coordinates":[-118.390512,33.804827],"type":"Point"}
}