{
  "type": "Feature",
  "properties": {
    "iso:country":"US",
    "sg:address":"667 N Lovekin Blvd",
    "sg:city":"Blythe",
    "sg:classifiers":[
        {
            "category":"Government",
            "subcategory":"Office",
            "type":"Public Place"
        }
    ],
    "sg:phone":"+1 760 921 3219",
    "sg:postcode":"92225",
    "sg:province":"CA",
    "sg:tags":[
        "federal",
        "security"
    ],
    "wof:name":"Us Army JROTC",
    "wof:placetype":"venue"
},
  "geometry": {"coordinates":[-114.60587200000001,33.622944],"type":"Point"}
}