{
  "type": "Feature",
  "properties": {
    "addr:full":"451 Stonewood St Downey CA 90241",
    "addr:housenumber":"451",
    "addr:postcode":"90241",
    "addr:street":"Stonewood St",
    "iso:country":"US",
    "sg:address":"451 Stonewood St",
    "sg:city":"Downey",
    "sg:classifiers":[
        {
            "category":"Home & Garden",
            "subcategory":"Home Furnishings",
            "type":"Retail Goods"
        }
    ],
    "sg:phone":"+1 562 861 6939",
    "sg:postcode":"90241",
    "sg:province":"CA",
    "sg:tags":[
        "housewares"
    ],
    "wof:name":"As Seen On TV/Solutions Now",
    "wof:placetype":"venue"
},
  "geometry": {"coordinates":[-118.122563,33.937158],"type":"Point"}
}