{
  "type": "Feature",
  "properties": {
    "addr:full":"13405 Washington Blvd Marina del Rey CA 90292",
    "addr:housenumber":"13405",
    "addr:postcode":"90292",
    "addr:street":"Washington Blvd",
    "iso:country":"US",
    "sg:address":"13405 Washington Blvd",
    "sg:city":"Marina del Rey",
    "sg:classifiers":[
        {
            "category":"Banks & Credit Unions",
            "subcategory":"Bank",
            "type":"Services"
        }
    ],
    "sg:phone":"+1 310 577 7551",
    "sg:postcode":"90292",
    "sg:province":"CA",
    "wof:name":"First Federal Bank of California",
    "wof:placetype":"venue"
},
  "geometry": {"coordinates":[-118.444705,33.992443],"type":"Point"}
}