{
  "type": "Feature",
  "properties": {
    "addr:full":"1764 The Alameda San Jose CA 95126",
    "addr:housenumber":"1764",
    "addr:postcode":"95126",
    "addr:street":"The Alameda",
    "iso:country":"US",
    "sg:address":"1764 The Alameda",
    "sg:city":"San Jose",
    "sg:classifiers":[
        {
            "category":"Professional",
            "type":"Services"
        }
    ],
    "sg:phone":"+1 408 264 2364",
    "sg:postcode":"95126",
    "sg:province":"CA",
    "wof:name":"Rubino Brntti Ptrcia G Trustee",
    "wof:placetype":"venue"
},
  "geometry": {"coordinates":[-121.92058299999999,37.338779],"type":"Point"}
}