{
  "type": "Feature",
  "properties": {
    "iso:country":"US",
    "sg:address":"9697 Bolsa Ave",
    "sg:city":"Westminster",
    "sg:classifiers":[
        {
            "category":"Food & Beverages",
            "subcategory":"Groceries & Convenience Stores",
            "type":"Retail Goods"
        }
    ],
    "sg:phone":"+1 714 839 3661",
    "sg:postcode":"92683",
    "sg:province":"CA",
    "wof:name":"Thuan Hoa",
    "wof:placetype":"venue"
},
  "geometry": {"coordinates":[-117.959779,33.745127],"type":"Point"}
}