{
  "type": "Feature",
  "properties": {
    "addr:full":"3857 Foothill Blvd La Crescenta CA 91214",
    "addr:housenumber":"3857",
    "addr:postcode":"91214",
    "addr:street":"Foothill Blvd",
    "iso:country":"US",
    "sg:address":"3857 Foothill Blvd",
    "sg:city":"La Crescenta",
    "sg:classifiers":[
        {
            "category":"Education",
            "subcategory":"Special Training",
            "type":"Public Place"
        }
    ],
    "sg:phone":"+1 818 249 0063",
    "sg:postcode":"91214",
    "sg:province":"CA",
    "sg:tags":[
        "tutoring"
    ],
    "wof:name":"Aguilar Tutoring",
    "wof:placetype":"venue"
},
  "geometry": {"coordinates":[-118.26285900000001,34.238364],"type":"Point"}
}