{
  "type": "Feature",
  "properties": {
    "iso:country":"US",
    "sg:address":"7240 Remmet Ave",
    "sg:city":"Canoga Park",
    "sg:classifiers":[
        {
            "category":"Manufacturing",
            "subcategory":"Printing",
            "type":"Manufacturing & Wholesale Goods"
        }
    ],
    "sg:phone":"+1 818 703 6614",
    "sg:postcode":"91303",
    "sg:province":"CA",
    "sg:tags":[
        "printer"
    ],
    "sg:website":"www.westongraphics.net",
    "wof:name":"Adam Weston Graphics",
    "wof:placetype":"venue"
},
  "geometry": {"coordinates":[-118.60020400000001,34.202102],"type":"Point"}
}