{
  "type": "Feature",
  "properties": {
    "iso:country":"US",
    "sg:address":"3656 W Shaw Ave",
    "sg:city":"Fresno",
    "sg:classifiers":[
        {
            "category":"Shopping",
            "subcategory":"Shoes",
            "type":"Retail Goods"
        }
    ],
    "sg:phone":"+1 559 277 9682",
    "sg:postcode":"93711",
    "sg:province":"CA",
    "sg:website":"www.payless.com",
    "wof:name":"Payless Shoe Source",
    "wof:placetype":"venue"
},
  "geometry": {"coordinates":[-119.862105,36.808352],"type":"Point"}
}