{
  "type": "Feature",
  "properties": {
    "iso:country":"US",
    "sg:address":"2688 W Araz Rd",
    "sg:city":"Winterhaven",
    "sg:classifiers":[
        {
            "category":"Real Estate",
            "subcategory":"Real Estate Operator",
            "type":"Services"
        }
    ],
    "sg:phone":"+1 760 572 5612",
    "sg:postcode":"92283",
    "sg:province":"CA",
    "sg:tags":[
        "mobile",
        "home",
        "community"
    ],
    "wof:name":"Vee's Trailer Park Manford",
    "wof:placetype":"venue"
},
  "geometry": {"coordinates":[-114.680711,32.752612],"type":"Point"}
}