{
  "type": "Feature",
  "properties": {
    "iso:country":"US",
    "sg:address":"1551 Botelho Dr",
    "sg:city":"Walnut Creek",
    "sg:classifiers":[
        {
            "category":"Shopping",
            "subcategory":"Clothing, Apparel, & Fashions",
            "type":"Retail Goods"
        }
    ],
    "sg:phone":"+1 925 934 8694",
    "sg:postcode":"94596",
    "sg:province":"CA",
    "sg:tags":[
        "maternity"
    ],
    "wof:name":"Motherhood Maternity",
    "wof:placetype":"venue"
},
  "geometry": {"coordinates":[-122.060812,37.894832],"type":"Point"}
}