{
  "type": "Feature",
  "properties": {
    "addr:full":"65 Hangar Way Watsonville CA 95076",
    "addr:housenumber":"65",
    "addr:postcode":"95076",
    "addr:street":"Hangar Way",
    "iso:country":"US",
    "sg:address":"65 Hangar Way",
    "sg:city":"Watsonville",
    "sg:classifiers":[
        {
            "category":"Retail",
            "subcategory":"Repair Shop",
            "type":"Services"
        }
    ],
    "sg:phone":"+1 831 786 8503",
    "sg:postcode":"95076",
    "sg:province":"CA",
    "sg:tags":[
        "welding"
    ],
    "wof:name":"Fred Salata's Welding",
    "wof:placetype":"venue"
},
  "geometry": {"coordinates":[-121.790774,36.92689],"type":"Point"}
}