{
  "type": "Feature",
  "properties": {
    "addr:full":"1740 Junction Ave San Jose CA 95112",
    "addr:housenumber":"1740",
    "addr:postcode":"95112",
    "addr:street":"Junction Ave",
    "iso:country":"US",
    "sg:address":"1740 Junction Ave",
    "sg:city":"San Jose",
    "sg:classifiers":[
        {
            "category":"Manufacturing",
            "subcategory":"Retail Goods",
            "type":"Manufacturing & Wholesale Goods"
        }
    ],
    "sg:phone":"+1 408 436 1040",
    "sg:postcode":"95112",
    "sg:province":"CA",
    "sg:tags":[
        "manufacturer"
    ],
    "wof:name":"Group Manufacturing Svc Inc",
    "wof:placetype":"venue"
},
  "geometry": {"coordinates":[-121.90742899999999,37.373284],"type":"Point"}
}