{
  "type": "Feature",
  "properties": {
    "addr:full":"460 Coletas Way Byron CA 94514",
    "addr:housenumber":"460",
    "addr:postcode":"94514",
    "addr:street":"Coletas Way",
    "iso:country":"US",
    "sg:address":"460 Coletas Way",
    "sg:city":"Byron",
    "sg:classifiers":[
        {
            "category":"Professional",
            "type":"Services"
        }
    ],
    "sg:phone":"+1 925 513 0665",
    "sg:postcode":"94514",
    "sg:province":"CA",
    "wof:name":"Surface Connection Inc",
    "wof:placetype":"venue"
},
  "geometry": {"coordinates":[-121.626487,37.868937],"type":"Point"}
}