{
  "type": "Feature",
  "properties": {
    "iso:country":"US",
    "sg:address":"194 N Marina Dr",
    "sg:city":"Long Beach",
    "sg:classifiers":[
        {
            "category":"Manufacturing",
            "subcategory":"Retail Goods",
            "type":"Manufacturing & Wholesale Goods"
        }
    ],
    "sg:phone":"+1 562 795 0243",
    "sg:postcode":"90803",
    "sg:province":"CA",
    "sg:tags":[
        "manufacturer"
    ],
    "wof:name":"North Manufacturing",
    "wof:placetype":"venue"
},
  "geometry": {"coordinates":[-118.10929400000001,33.75081],"type":"Point"}
}