{
  "type": "Feature",
  "properties": {
    "addr:full":"1908 Meer Way Sacramento CA 95822",
    "addr:housenumber":"1908",
    "addr:postcode":"95822",
    "addr:street":"Meer Way",
    "iso:country":"US",
    "sg:address":"1908 Meer Way",
    "sg:city":"Sacramento",
    "sg:classifiers":[
        {
            "category":"Building & Trades",
            "subcategory":"Landscaping Services",
            "type":"Services"
        }
    ],
    "sg:phone":"+1 916 452 7242",
    "sg:postcode":"95822",
    "sg:province":"CA",
    "sg:tags":[
        "tree"
    ],
    "wof:name":"Park Land Tree Service",
    "wof:placetype":"venue"
},
  "geometry": {"coordinates":[-121.49611299999999,38.534115],"type":"Point"}
}