{
  "type": "Feature",
  "properties": {
    "iso:country":"US",
    "sg:address":"8340 Vickers St",
    "sg:city":"San Diego",
    "sg:classifiers":[
        {
            "category":"Wholesale",
            "subcategory":"Medical Equipment & Supplies",
            "type":"Manufacturing & Wholesale Goods"
        }
    ],
    "sg:phone":"+1 858 278 2077",
    "sg:postcode":"92111",
    "sg:province":"CA",
    "wof:name":"T L G Medical Products",
    "wof:placetype":"venue"
},
  "geometry": {"coordinates":[-117.14793400000001,32.827348],"type":"Point"}
}