{
  "type": "Feature",
  "properties": {
    "addr:full":"5373 Wilshire Blvd Los Angeles CA 90036",
    "addr:housenumber":"5373",
    "addr:postcode":"90036",
    "addr:street":"Wilshire Blvd",
    "iso:country":"US",
    "sg:address":"5373 Wilshire Blvd",
    "sg:city":"Los Angeles",
    "sg:classifiers":[
        {
            "category":"Personal",
            "subcategory":"Beauty Salon",
            "type":"Services"
        }
    ],
    "sg:phone":"+1 310 276 8626",
    "sg:postcode":"90036",
    "sg:province":"CA",
    "sg:tags":[
        "hair"
    ],
    "sg:website":"www.sahairah.com",
    "wof:name":"Sa-Hair-aH",
    "wof:placetype":"venue"
},
  "geometry": {"coordinates":[-118.34590799999999,34.062463],"type":"Point"}
}