{
  "type": "Feature",
  "properties": {
    "addr:full":"408 7th St Ste A Eureka CA 95501",
    "addr:housenumber":"408",
    "addr:postcode":"95501",
    "addr:street":"7Th St Ste A",
    "iso:country":"US",
    "sg:address":"408 7th St Ste A",
    "sg:city":"Eureka",
    "sg:classifiers":[
        {
            "category":"Professional",
            "subcategory":"Management & Consulting",
            "type":"Services"
        }
    ],
    "sg:phone":"+1 707 268 3812",
    "sg:postcode":"95501",
    "sg:province":"CA",
    "sg:tags":[
        "planning",
        "consultant",
        "space",
        "facility"
    ],
    "wof:name":"Cambria Environmental Technology, Inc.",
    "wof:placetype":"venue"
},
  "geometry": {"coordinates":[-124.166586,40.800133],"type":"Point"}
}