{
  "type": "Feature",
  "properties": {
    "addr:full":"501 Harbor Blvd West Sacramento CA 95691",
    "addr:housenumber":"501",
    "addr:postcode":"95691",
    "addr:street":"Harbor Blvd",
    "iso:country":"US",
    "sg:address":"501 Harbor Blvd",
    "sg:city":"West Sacramento",
    "sg:classifiers":[
        {
            "category":"Wholesale",
            "subcategory":"Hardware",
            "type":"Manufacturing & Wholesale Goods"
        }
    ],
    "sg:phone":"+1 916 371 8015",
    "sg:postcode":"95691",
    "sg:province":"CA",
    "sg:tags":[
        "fastener"
    ],
    "wof:name":"Fastenal Co",
    "wof:placetype":"venue"
},
  "geometry": {"coordinates":[-121.547234,38.584517],"type":"Point"}
}