{
  "type": "Feature",
  "properties": {
    "addr:full":"420 S San Antonio Rd Los Altos CA 94022",
    "addr:housenumber":"420",
    "addr:postcode":"94022",
    "addr:street":"S;Antonio Rd",
    "iso:country":"US",
    "sg:address":"420 S San Antonio Rd",
    "sg:city":"Los Altos",
    "sg:classifiers":[
        {
            "category":"Restaurant",
            "type":"Food & Drink"
        }
    ],
    "sg:menulink":"http://www.allmenus.com/ca/san-jose/239220-the-original-pancake-house/menu/",
    "sg:phone":"+1 650 559 9197",
    "sg:postcode":"94022",
    "sg:province":"CA",
    "sg:tags":[
        "american",
        "diner"
    ],
    "wof:name":"The Original Pancake House",
    "wof:placetype":"venue"
},
  "geometry": {"coordinates":[-122.114276,37.375173],"type":"Point"}
}