{
  "type": "Feature",
  "properties": {
    "iso:country":"US",
    "sg:address":"3000 Ocean Park Blvd",
    "sg:city":"Santa Monica",
    "sg:classifiers":[
        {
            "category":"Building & Trades",
            "subcategory":"Cleaning & Sanitation",
            "type":"Services"
        }
    ],
    "sg:phone":"+1 310 664 2850",
    "sg:postcode":"90405",
    "sg:province":"CA",
    "sg:tags":[
        "house"
    ],
    "sg:website":"www.tenaska.com",
    "wof:name":"Good Housekeeping",
    "wof:placetype":"venue"
},
  "geometry": {"coordinates":[-118.453803,34.019956],"type":"Point"}
}