{
  "type": "Feature",
  "properties": {
    "iso:country":"US",
    "sg:address":"5420 Kohler Ave",
    "sg:city":"Sacramento",
    "sg:classifiers":[
        {
            "category":"Government",
            "subcategory":"Post Office",
            "type":"Public Place"
        }
    ],
    "sg:postcode":"95841",
    "sg:province":"CA",
    "sg:website":"www.usps.com",
    "wof:name":"US Post Office - Foothill Farms",
    "wof:placetype":"venue"
},
  "geometry": {"coordinates":[-121.344407,38.66472],"type":"Point"}
}