{
  "type": "Feature",
  "properties": {
    "addr:full":"23 W Easy St Simi Valley CA 93065",
    "addr:housenumber":"23",
    "addr:postcode":"93065",
    "addr:street":"W Easy St",
    "iso:country":"US",
    "sg:address":"23 W Easy St",
    "sg:city":"Simi Valley",
    "sg:classifiers":[
        {
            "category":"Building & Trades",
            "subcategory":"Plumbing",
            "type":"Services"
        }
    ],
    "sg:phone":"+1 805 527 9117",
    "sg:postcode":"93065",
    "sg:province":"CA",
    "sg:tags":[
        "plumbing",
        "contractor"
    ],
    "wof:name":"Sierra Commercial Plumbing",
    "wof:placetype":"venue"
},
  "geometry": {"coordinates":[-118.79735100000001,34.278331],"type":"Point"}
}