{
  "type": "Feature",
  "properties": {
    "addr:full":"5126 Stevens Creek Blvd San Jose CA 95129",
    "addr:housenumber":"5126",
    "addr:postcode":"95129",
    "addr:street":"Stevens Creek Blvd",
    "iso:country":"US",
    "sg:address":"5126 Stevens Creek Blvd",
    "sg:city":"San Jose",
    "sg:classifiers":[
        {
            "category":"Ice Cream",
            "type":"Food & Drink"
        }
    ],
    "sg:phone":"+1 408 982 5586",
    "sg:postcode":"95129",
    "sg:province":"CA",
    "sg:tags":[
        "frozen",
        "yogurt"
    ],
    "sg:website":"www.goldenspoon.com",
    "wof:name":"Golden Spoon Frozen Yogurt",
    "wof:placetype":"venue"
},
  "geometry": {"coordinates":[-121.992729,37.322946],"type":"Point"}
}