{
  "type": "Feature",
  "properties": {
    "iso:country":"US",
    "sg:address":"5548 Green Oak Dr",
    "sg:city":"Los Angeles",
    "sg:classifiers":[
        {
            "category":"Building & Trades",
            "subcategory":"Electrical",
            "type":"Services"
        }
    ],
    "sg:phone":"+1 323 461 0695",
    "sg:postcode":"90068",
    "sg:province":"CA",
    "sg:tags":[
        "electrical",
        "contractor"
    ],
    "wof:name":"Hart Communications Inc",
    "wof:placetype":"venue"
},
  "geometry": {"coordinates":[-118.311716,34.119279],"type":"Point"}
}