{
  "type": "Feature",
  "properties": {
    "addr:full":"6540 Lusk Blvd San Diego CA 92121",
    "addr:housenumber":"6540",
    "addr:postcode":"92121",
    "addr:street":"Lusk Blvd",
    "iso:country":"US",
    "sg:address":"6540 Lusk Blvd",
    "sg:city":"San Diego",
    "sg:classifiers":[
        {
            "category":"Arts & Performance",
            "subcategory":"Theater",
            "type":"Entertainment"
        }
    ],
    "sg:phone":"+1 858 455 5758",
    "sg:postcode":"92121",
    "sg:province":"CA",
    "sg:tags":[
        "dance",
        "company"
    ],
    "wof:name":"Magic Motion LTD",
    "wof:placetype":"venue"
},
  "geometry": {"coordinates":[-117.20263199999999,32.901527],"type":"Point"}
}