{
  "type": "Feature",
  "properties": {
    "iso:country":"US",
    "sg:address":"17565 Crenshaw Blvd",
    "sg:city":"Torrance",
    "sg:classifiers":[
        {
            "category":"Wholesale",
            "subcategory":"Plants",
            "type":"Manufacturing & Wholesale Goods"
        }
    ],
    "sg:phone":"+1 310 380 6800",
    "sg:postcode":"90504",
    "sg:province":"CA",
    "sg:tags":[
        "nursery",
        "gardening",
        "supply"
    ],
    "wof:name":"Plant City",
    "wof:placetype":"venue"
},
  "geometry": {"coordinates":[-118.325996,33.8713],"type":"Point"}
}