{
  "type": "Feature",
  "properties": {
    "iso:country":"US",
    "sg:address":"120 Village Pl",
    "sg:city":"Orinda",
    "sg:classifiers":[
        {
            "category":"Personal",
            "type":"Services"
        }
    ],
    "sg:phone":"+1 925 254 7920",
    "sg:postcode":"94553",
    "sg:province":"CA",
    "sg:tags":[
        "mail",
        "receiving"
    ],
    "wof:name":"Orinda Mail Call",
    "wof:placetype":"venue"
},
  "geometry": {"coordinates":[-122.113584,37.999205],"type":"Point"}
}