{
  "type": "Feature",
  "properties": {
    "addr:full":"1340 E Wilson Ave Glendale CA 91206",
    "addr:housenumber":"1340",
    "addr:postcode":"91206",
    "addr:street":"E Wilson Ave",
    "iso:country":"US",
    "sg:address":"1340 E Wilson Ave",
    "sg:city":"Glendale",
    "sg:classifiers":[
        {
            "category":"Personal",
            "subcategory":"Beauty Salon",
            "type":"Services"
        }
    ],
    "sg:phone":"+1 818 409 1970",
    "sg:postcode":"91206",
    "sg:province":"CA",
    "wof:name":"Pixie Dust",
    "wof:placetype":"venue"
},
  "geometry": {"coordinates":[-118.236344,34.147991],"type":"Point"}
}