{
  "type": "Feature",
  "properties": {
    "iso:country":"US",
    "sg:address":"2957 Teagarden St",
    "sg:city":"San Leandro",
    "sg:classifiers":[
        {
            "category":"Manufacturing",
            "subcategory":"Tools & Machinery",
            "type":"Manufacturing & Wholesale Goods"
        }
    ],
    "sg:phone":"+1 510 614 0694",
    "sg:postcode":"94577",
    "sg:province":"CA",
    "sg:tags":[
        "mfg"
    ],
    "wof:name":"Crane Services",
    "wof:placetype":"venue"
},
  "geometry": {"coordinates":[-122.157101,37.705196],"type":"Point"}
}