{
  "type": "Feature",
  "properties": {
    "addr:full":"1560 E Florence Avenue Los Angeles CA 90001",
    "addr:housenumber":"1560",
    "addr:postcode":"90001",
    "addr:street":"E Florence Avenue",
    "iso:country":"US",
    "sg:address":"1560 E Florence Avenue",
    "sg:city":"Los Angeles",
    "sg:classifiers":[
        {
            "category":"Shopping",
            "subcategory":"Pawn Shop",
            "type":"Retail Goods"
        }
    ],
    "sg:phone":"+1 323 582 3010",
    "sg:postcode":"90001",
    "sg:province":"CA",
    "wof:name":"Jack's Jewelry & Loan Corporation",
    "wof:placetype":"venue"
},
  "geometry": {"coordinates":[-118.24569099999999,33.974663],"type":"Point"}
}