{
  "type": "Feature",
  "properties": {
    "addr:full":"645 E Champlain Dr Fresno CA 93730",
    "addr:housenumber":"645",
    "addr:postcode":"93730",
    "addr:street":"E Champlain Dr",
    "iso:country":"US",
    "sg:address":"645 E Champlain Dr",
    "sg:city":"Fresno",
    "sg:classifiers":[
        {
            "category":"Professional",
            "subcategory":"Business Services",
            "type":"Services"
        },
        {
            "category":"Personal",
            "subcategory":"Adult",
            "type":"Services"
        }
    ],
    "sg:phone":"+1 559 273 8986",
    "sg:postcode":"93730",
    "sg:province":"CA",
    "sg:tags":[
        "consultant",
        "coach",
        "coaching-business"
    ],
    "sg:website":"http://www.garysgrossmanphd.com",
    "wof:name":"Grossman Gary S PhD",
    "wof:placetype":"venue"
},
  "geometry": {"coordinates":[-119.77176799999999,36.877387],"type":"Point"}
}