{
  "type": "Feature",
  "properties": {
    "addr:full":"4709 W 132nd St Hawthorne CA 90250",
    "addr:housenumber":"4709",
    "addr:postcode":"90250",
    "addr:street":"W 132Nd St",
    "iso:country":"US",
    "sg:address":"4709 W 132nd St",
    "sg:city":"Hawthorne",
    "sg:classifiers":[
        {
            "category":"Personal",
            "subcategory":"Beauty Salon",
            "type":"Services"
        }
    ],
    "sg:phone":"+1 310 973 7306",
    "sg:postcode":"90250",
    "sg:province":"CA",
    "sg:tags":[
        "hair"
    ],
    "wof:name":"Mane Event Unisex Hairstyling",
    "wof:placetype":"venue"
},
  "geometry": {"coordinates":[-118.35927700000001,33.912924],"type":"Point"}
}