{
  "type": "Feature",
  "properties": {
    "addr:full":"405 N Lake Blvd Tahoe City CA 96145",
    "addr:housenumber":"405",
    "addr:postcode":"96145",
    "addr:street":"N Lake Blvd",
    "iso:country":"US",
    "sg:address":"405 N Lake Blvd",
    "sg:city":"Tahoe City",
    "sg:classifiers":[
        {
            "category":"Professional",
            "subcategory":"Engineering",
            "type":"Services"
        }
    ],
    "sg:phone":"+1 530 583 2211",
    "sg:postcode":"96145",
    "sg:province":"CA",
    "sg:tags":[
        "engineer"
    ],
    "wof:name":"Three Sticks Design & Eng",
    "wof:placetype":"venue"
},
  "geometry": {"coordinates":[-120.1413,39.170771],"type":"Point"}
}