{
  "type": "Feature",
  "properties": {
    "addr:full":"408 Roseville Sq Roseville CA 95678",
    "addr:housenumber":"408",
    "addr:postcode":"95678",
    "addr:street":"Roseville Sq",
    "iso:country":"US",
    "sg:address":"408 Roseville Sq",
    "sg:city":"Roseville",
    "sg:classifiers":[
        {
            "category":"Shopping",
            "type":"Retail Goods"
        }
    ],
    "sg:phone":"+1 916 782 5330",
    "sg:postcode":"95678",
    "sg:province":"CA",
    "sg:tags":[
        "art",
        "gallery",
        "dealer"
    ],
    "sg:website":"www.allovio.com",
    "wof:name":"Allovio Gifts & Collectables",
    "wof:placetype":"venue"
},
  "geometry": {"coordinates":[-121.27406000000001,38.745974],"type":"Point"}
}