{
  "type": "Feature",
  "properties": {
    "iso:country":"US",
    "sg:address":"5905 Wilhoff Ln",
    "sg:city":"Granite Bay",
    "sg:classifiers":[
        {
            "category":"Farming",
            "subcategory":"Nursery",
            "type":"Manufacturing & Wholesale Goods"
        }
    ],
    "sg:phone":"+1 916 791 0242",
    "sg:postcode":"95746",
    "sg:province":"CA",
    "sg:tags":[
        "ornamental",
        "merchandise"
    ],
    "wof:name":"Granite Bay Daylily Garden",
    "wof:placetype":"venue"
},
  "geometry": {"coordinates":[-121.186707,38.760795],"type":"Point"}
}