{
  "type": "Feature",
  "properties": {
    "addr:full":"1073 Mono Way Sonora CA 95370",
    "addr:housenumber":"1073",
    "addr:postcode":"95370",
    "addr:street":"Mono Way",
    "iso:country":"US",
    "sg:address":"1073 Mono Way",
    "sg:city":"Sonora",
    "sg:classifiers":[
        {
            "category":"Restaurant",
            "type":"Food & Drink"
        }
    ],
    "sg:phone":"+1 209 536 9887",
    "sg:postcode":"95370",
    "sg:province":"CA",
    "sg:tags":[
        "asian",
        "chinese",
        "pan"
    ],
    "wof:name":"Mandarin Palace",
    "wof:placetype":"venue"
},
  "geometry": {"coordinates":[-120.364631,37.975901],"type":"Point"}
}