{
  "type": "Feature",
  "properties": {
    "addr:full":"2141 Petaluma Blvd S Petaluma CA 94952",
    "addr:housenumber":"2141",
    "addr:postcode":"94952",
    "addr:street":"Petaluma Blvd S Petaluma",
    "iso:country":"US",
    "sg:address":"2141 Petaluma Blvd S",
    "sg:city":"Petaluma",
    "sg:classifiers":[
        {
            "category":"Building & Trades",
            "subcategory":"Construction",
            "type":"Services"
        },
        {
            "category":"Manufacturing",
            "subcategory":"Building Materials",
            "type":"Manufacturing & Wholesale Goods"
        }
    ],
    "sg:phone":"+1 707 762 2341",
    "sg:postcode":"94952",
    "sg:province":"CA",
    "sg:tags":[
        "roofing",
        "industrial",
        "sheet",
        "work",
        "metal",
        "contractor",
        "siding",
        "contractors-commercial"
    ],
    "wof:name":"J&K Roofing Services",
    "wof:placetype":"venue"
},
  "geometry": {"coordinates":[-122.615071,38.227983],"type":"Point"}
}