{
  "type": "Feature",
  "properties": {
    "iso:country":"US",
    "sg:address":"135 S Jackson St",
    "sg:city":"Glendale",
    "sg:classifiers":[
        {
            "category":"Communications",
            "subcategory":"Newspaper",
            "type":"Services"
        }
    ],
    "sg:phone":"+1 818 507 7057",
    "sg:postcode":"91205",
    "sg:province":"CA",
    "sg:tags":[
        "print",
        "medium"
    ],
    "wof:name":"Ethnopress USA",
    "wof:placetype":"venue"
},
  "geometry": {"coordinates":[-118.25024999999999,34.145713],"type":"Point"}
}