{
  "type": "Feature",
  "properties": {
    "iso:country":"US",
    "sg:address":"8038 Archibald Ave",
    "sg:city":"Rancho Cucamonga",
    "sg:classifiers":[
        {
            "category":"Insurance",
            "subcategory":"Insurance Agent",
            "type":"Services"
        }
    ],
    "sg:phone":"+1 909 987 4413",
    "sg:postcode":"91730",
    "sg:province":"CA",
    "wof:name":"Sorrells Insurance",
    "wof:placetype":"venue"
},
  "geometry": {"coordinates":[-117.593557,34.108306],"type":"Point"}
}