{
  "type": "Feature",
  "properties": {
    "iso:country":"US",
    "sg:address":"3115 Jefferson Ave",
    "sg:city":"Redwood City",
    "sg:classifiers":[
        {
            "category":"Food & Beverages",
            "subcategory":"Groceries & Convenience Stores",
            "type":"Retail Goods"
        }
    ],
    "sg:phone":"+1 650 369 0206",
    "sg:postcode":"94062",
    "sg:province":"CA",
    "sg:tags":[
        "grocer"
    ],
    "wof:name":"B & W Market",
    "wof:placetype":"venue"
},
  "geometry": {"coordinates":[-122.247001,37.469769],"type":"Point"}
}