{
  "type": "Feature",
  "properties": {
    "iso:country":"US",
    "sg:address":"11050 Rio Hondo Dr",
    "sg:city":"Downey",
    "sg:classifiers":[
        {
            "category":"Building & Trades",
            "subcategory":"Construction",
            "type":"Services"
        }
    ],
    "sg:phone":"+1 562 927 8988",
    "sg:postcode":"90241",
    "sg:province":"CA",
    "sg:tags":[
        "contractor"
    ],
    "wof:name":"L & L Construction",
    "wof:placetype":"venue"
},
  "geometry": {"coordinates":[-118.156059,33.952977],"type":"Point"}
}