{
  "type": "Feature",
  "properties": {
    "addr:full":"837 N Glendale Ave Glendale CA 91206",
    "addr:housenumber":"837",
    "addr:postcode":"91206",
    "addr:street":"N Glendale Ave",
    "iso:country":"US",
    "sg:address":"837 N Glendale Ave",
    "sg:city":"Glendale",
    "sg:classifiers":[
        {
            "category":"Health Services",
            "subcategory":"Health Practitioner",
            "type":"Services"
        }
    ],
    "sg:phone":"+1 818 241 1102",
    "sg:postcode":"91206",
    "sg:province":"CA",
    "sg:tags":[
        "home",
        "care"
    ],
    "sg:website":"www.ComForcare.com",
    "wof:name":"ComForcare Senior Service",
    "wof:placetype":"venue"
},
  "geometry": {"coordinates":[-118.240731,34.158139],"type":"Point"}
}