{
  "type": "Feature",
  "properties": {
    "addr:full":"1719 N Edison Blvd Burbank CA 91505",
    "addr:housenumber":"1719",
    "addr:postcode":"91505",
    "addr:street":"N Edison Blvd",
    "iso:country":"US",
    "sg:address":"1719 N Edison Blvd",
    "sg:city":"Burbank",
    "sg:classifiers":[
        {
            "category":"Restaurant",
            "type":"Food & Drink"
        }
    ],
    "sg:phone":"+1 818 846 7239",
    "sg:postcode":"91505",
    "sg:province":"CA",
    "sg:tags":[
        "out"
    ],
    "wof:name":"Gary Matevosian",
    "wof:placetype":"venue"
},
  "geometry": {"coordinates":[-118.355448,34.178293],"type":"Point"}
}