{
  "type": "Feature",
  "properties": {
    "iso:country":"US",
    "sg:address":"1002 del Monte Ave",
    "sg:city":"Salinas",
    "sg:classifiers":[
        {
            "category":"Shopping",
            "subcategory":"Jewelry",
            "type":"Retail Goods"
        }
    ],
    "sg:phone":"+1 831 771 9342",
    "sg:postcode":"93905",
    "sg:province":"CA",
    "sg:tags":[
        "jeweler"
    ],
    "wof:name":"V Joyeria Aroba",
    "wof:placetype":"venue"
},
  "geometry": {"coordinates":[-121.610643,36.688378],"type":"Point"}
}