{
  "type": "Feature",
  "properties": {
    "addr:full":"123 Bonita Ln Moss Beach CA 94038",
    "addr:housenumber":"123",
    "addr:postcode":"94038",
    "addr:street":"Bonita Ln",
    "iso:country":"US",
    "sg:address":"123 Bonita Ln",
    "sg:city":"Moss Beach",
    "sg:classifiers":[
        {
            "category":"Shopping",
            "subcategory":"Used Merchandise",
            "type":"Retail Goods"
        }
    ],
    "sg:phone":"+1 650 563 9280",
    "sg:postcode":"94038",
    "sg:province":"CA",
    "sg:tags":[
        "record",
        "rare"
    ],
    "sg:website":"www.hrmusic.com",
    "wof:name":"Harmony Ridge Music",
    "wof:placetype":"venue"
},
  "geometry": {"coordinates":[-122.500193,37.508833],"type":"Point"}
}