{
  "type": "Feature",
  "properties": {
    "iso:country":"US",
    "sg:address":"2170 Main St Ste 1",
    "sg:city":"Oakley",
    "sg:classifiers":[
        {
            "category":"Communications",
            "subcategory":"News Services",
            "type":"Services"
        },
        {
            "category":"Transit Center",
            "subcategory":"Freight",
            "type":"Transportation"
        },
        {
            "category":"Professional",
            "subcategory":"Business Services",
            "type":"Services"
        },
        {
            "category":"Professional",
            "subcategory":"Printing & Photocopies",
            "type":"Services"
        }
    ],
    "sg:phone":"+1 925 679 0615",
    "sg:postcode":"94561",
    "sg:province":"CA",
    "sg:tags":[
        "cargo",
        "fax",
        "transparency",
        "package",
        "color",
        "express",
        "duplicating",
        "shipping",
        "air",
        "copying",
        "print",
        "mail",
        "photographic"
    ],
    "sg:website":"http://www.kinkos.com",
    "wof:name":"Fedex Kinko's",
    "wof:placetype":"venue"
},
  "geometry": {"coordinates":[-121.732231,38.002669],"type":"Point"}
}