{
  "type": "Feature",
  "properties": {
    "addr:full":"3613 Alameda Menlo Park CA 94025",
    "addr:housenumber":"3613",
    "addr:postcode":"94025",
    "addr:street":"Alameda",
    "iso:country":"US",
    "sg:address":"3613 Alameda",
    "sg:city":"Menlo Park",
    "sg:classifiers":[
        {
            "category":"Retail",
            "subcategory":"Laundry & Dry Cleaning",
            "type":"Services"
        }
    ],
    "sg:phone":"+1 650 854 6910",
    "sg:postcode":"94025",
    "sg:province":"CA",
    "sg:tags":[
        "cleaners"
    ],
    "wof:name":"Village Cleaners",
    "wof:placetype":"venue"
},
  "geometry": {"coordinates":[-122.20093,37.431531],"type":"Point"}
}