{
  "type": "Feature",
  "properties": {
    "addr:full":"1065 Carlsbad Village Dr Ste A Carlsbad CA 92008",
    "addr:housenumber":"1065",
    "addr:postcode":"92008",
    "addr:street":"Carlsbad Village Dr Ste A",
    "iso:country":"US",
    "sg:address":"1065 Carlsbad Village Dr Ste A",
    "sg:city":"Carlsbad",
    "sg:classifiers":[
        {
            "category":"Health Services",
            "subcategory":"Doctor",
            "type":"Services"
        },
        {
            "category":"Personal",
            "subcategory":"Skin Care",
            "type":"Services"
        },
        {
            "category":"Personal",
            "subcategory":"Nail Salon",
            "type":"Services"
        }
    ],
    "sg:phone":"+1 760 729 3355",
    "sg:postcode":"92008",
    "sg:province":"CA",
    "wof:name":"Village Hairlines PHD",
    "wof:placetype":"venue"
},
  "geometry": {"coordinates":[-117.328003,33.159698],"type":"Point"}
}