{
  "type": "Feature",
  "properties": {
    "iso:country":"US",
    "sg:address":"1185 Grand Ave",
    "sg:city":"Arroyo Grande",
    "sg:classifiers":[
        {
            "category":"Home & Garden",
            "subcategory":"Furniture",
            "type":"Retail Goods"
        }
    ],
    "sg:phone":"+1 805 474 5887",
    "sg:postcode":"93420",
    "sg:province":"CA",
    "sg:tags":[
        "top",
        "counter"
    ],
    "wof:name":"Duracite Manufacturing Co",
    "wof:placetype":"venue"
},
  "geometry": {"coordinates":[-120.599844,35.120407],"type":"Point"}
}