{
  "type": "Feature",
  "properties": {
    "iso:country":"US",
    "sg:address":"241 Bus Park Way",
    "sg:city":"Atwater",
    "sg:classifiers":[
        {
            "category":"Professional",
            "subcategory":"Testing Lab",
            "type":"Services"
        }
    ],
    "sg:phone":"+1 209 356 0355",
    "sg:postcode":"95301",
    "sg:province":"CA",
    "sg:tags":[
        "laboratory"
    ],
    "wof:name":"Central Counties DHI",
    "wof:placetype":"venue"
},
  "geometry": {"coordinates":[-120.601755,37.334301],"type":"Point"}
}