{
  "type": "Feature",
  "properties": {
    "addr:full":"515 N Main St Santa Ana CA 92701",
    "addr:housenumber":"515",
    "addr:postcode":"92701",
    "addr:street":"N Main St",
    "iso:country":"US",
    "sg:address":"515 N Main St",
    "sg:city":"Santa Ana",
    "sg:classifiers":[
        {
            "category":"Organizations",
            "subcategory":"Community Association",
            "type":"Services"
        }
    ],
    "sg:phone":"+1 714 835 7287",
    "sg:postcode":"92701",
    "sg:province":"CA",
    "sg:tags":[
        "environmental",
        "org"
    ],
    "wof:name":"Heritage Orange County Inc",
    "wof:placetype":"venue"
},
  "geometry": {"coordinates":[-117.867547,33.749616],"type":"Point"}
}