{
  "type": "Feature",
  "properties": {
    "iso:country":"US",
    "sg:address":"3531 S Academy Ave",
    "sg:city":"Sanger",
    "sg:classifiers":[
        {
            "category":"Food & Beverages",
            "subcategory":"Groceries & Convenience Stores",
            "type":"Retail Goods"
        }
    ],
    "sg:phone":"+1 559 875 4001",
    "sg:postcode":"93657",
    "sg:province":"CA",
    "wof:name":"J's Market & Gas",
    "wof:placetype":"venue"
},
  "geometry": {"coordinates":[-119.556586,36.67844],"type":"Point"}
}