{
  "type": "Feature",
  "properties": {
    "addr:full":"8501 Auburn Blvd Citrus Heights CA 95610",
    "addr:housenumber":"8501",
    "addr:postcode":"95610",
    "addr:street":"Auburn Blvd",
    "iso:country":"US",
    "sg:address":"8501 Auburn Blvd",
    "sg:city":"Citrus Heights",
    "sg:classifiers":[
        {
            "category":"Retail",
            "subcategory":"Portrait Studio",
            "type":"Services"
        }
    ],
    "sg:phone":"+1 916 723 9730",
    "sg:postcode":"95610",
    "sg:province":"CA",
    "wof:name":"Olan Mills Studios",
    "wof:placetype":"venue"
},
  "geometry": {"coordinates":[-121.29048,38.719494],"type":"Point"}
}