{
  "type": "Feature",
  "properties": {
    "iso:country":"US",
    "sg:address":"60 Montgomery St",
    "sg:city":"San Francisco",
    "sg:classifiers":[
        {
            "category":"Professional",
            "subcategory":"Accounting & Tax Preparation",
            "type":"Services"
        }
    ],
    "sg:phone":"+1 415 217 6902",
    "sg:postcode":"94104",
    "sg:province":"CA",
    "sg:tags":[
        "accountant"
    ],
    "wof:name":"Crista M Lucey",
    "wof:placetype":"venue"
},
  "geometry": {"coordinates":[-122.402023,37.789486],"type":"Point"}
}