{
  "type": "Feature",
  "properties": {
    "addr:full":"1150 Mesa View Dr Arroyo Grande CA 93420",
    "addr:housenumber":"1150",
    "addr:postcode":"93420",
    "addr:street":"Mesa View Dr",
    "iso:country":"US",
    "sg:address":"1150 Mesa View Dr",
    "sg:city":"Arroyo Grande",
    "sg:classifiers":[
        {
            "category":"Professional",
            "type":"Services"
        }
    ],
    "sg:phone":"+1 805 489 2187",
    "sg:postcode":"93420",
    "sg:province":"CA",
    "sg:tags":[
        "establishment"
    ],
    "wof:name":"Dune Lakes LTD",
    "wof:placetype":"venue"
},
  "geometry": {"coordinates":[-120.597302,35.0633],"type":"Point"}
}