{
  "type": "Feature",
  "properties": {
    "addr:full":"8930 W Pico Blvd Los Angeles CA 90035",
    "addr:housenumber":"8930",
    "addr:postcode":"90035",
    "addr:street":"W Pico Blvd",
    "iso:country":"US",
    "sg:address":"8930 W Pico Blvd",
    "sg:city":"Los Angeles",
    "sg:classifiers":[
        {
            "category":"Restaurant",
            "type":"Food & Drink"
        }
    ],
    "sg:phone":"+1 310 858 8590",
    "sg:postcode":"90035",
    "sg:province":"CA",
    "sg:tags":[
        "deli",
        "grocery",
        "eating"
    ],
    "sg:website":"www.jeffsgourmet.com",
    "wof:name":"Jeff's Gourmet Kosher Sausage Factory",
    "wof:placetype":"venue"
},
  "geometry": {"coordinates":[-118.386743,34.055275],"type":"Point"}
}