{
  "type": "Feature",
  "properties": {
    "addr:full":"9290 Old Redwood Hwy Windsor CA 95492",
    "addr:housenumber":"9290",
    "addr:postcode":"95492",
    "addr:street":"Old Redwood Hwy",
    "iso:country":"US",
    "sg:address":"9290 Old Redwood Hwy",
    "sg:city":"Windsor",
    "sg:classifiers":[
        {
            "category":"Real Estate",
            "subcategory":"Real Estate Operator",
            "type":"Services"
        }
    ],
    "sg:phone":"+1 707 838 4882",
    "sg:postcode":"95492",
    "sg:province":"CA",
    "sg:tags":[
        "mobile",
        "home",
        "community"
    ],
    "sg:website":"www.windsorland.com",
    "wof:name":"Windsor Land",
    "wof:placetype":"venue"
},
  "geometry": {"coordinates":[-122.81340899999999,38.54951],"type":"Point"}
}