{
  "type": "Feature",
  "properties": {
    "addr:full":"2363 Decatur Ave Clovis CA 93611",
    "addr:housenumber":"2363",
    "addr:postcode":"93611",
    "addr:street":"Decatur Ave",
    "iso:country":"US",
    "sg:address":"2363 Decatur Ave",
    "sg:city":"Clovis",
    "sg:classifiers":[
        {
            "category":"Communications",
            "subcategory":"Film & Video Production",
            "type":"Services"
        }
    ],
    "sg:phone":"+1 559 323 5956",
    "sg:postcode":"93611",
    "sg:province":"CA",
    "sg:tags":[
        "duplication",
        "tape"
    ],
    "sg:website":"http://www.clovisvideotransfer.com",
    "wof:name":"Clovis Video Transfer",
    "wof:placetype":"venue"
},
  "geometry": {"coordinates":[-119.67173099999999,36.848036],"type":"Point"}
}