{
  "type": "Feature",
  "properties": {
    "addr:full":"770 Menlo Ave Menlo Park CA 94025",
    "addr:housenumber":"770",
    "addr:postcode":"94025",
    "addr:street":"Menlo Ave",
    "iso:country":"US",
    "sg:address":"770 Menlo Ave",
    "sg:city":"Menlo Park",
    "sg:classifiers":[
        {
            "category":"Health Services",
            "subcategory":"Doctor",
            "type":"Services"
        }
    ],
    "sg:phone":"+1 408 996 3500",
    "sg:postcode":"94025",
    "sg:province":"CA",
    "sg:tags":[
        "physician",
        "surgeon"
    ],
    "wof:name":"Carl Levinson MD",
    "wof:placetype":"venue"
},
  "geometry": {"coordinates":[-122.183817,37.450649],"type":"Point"}
}