{
  "type": "Feature",
  "properties": {
    "addr:full":"809 Riesling Rd Petaluma CA 94954",
    "addr:housenumber":"809",
    "addr:postcode":"94954",
    "addr:street":"Riesling Rd",
    "iso:country":"US",
    "sg:address":"809 Riesling Rd",
    "sg:city":"Petaluma",
    "sg:classifiers":[
        {
            "category":"Food & Beverages",
            "subcategory":"Candy",
            "type":"Retail Goods"
        }
    ],
    "sg:phone":"+1 707 773 0823",
    "sg:postcode":"94954",
    "sg:province":"CA",
    "wof:name":"Darn Good Nuts",
    "wof:placetype":"venue"
},
  "geometry": {"coordinates":[-122.641897,38.272956],"type":"Point"}
}