{
  "type": "Feature",
  "properties": {
    "iso:country":"US",
    "sg:address":"633 Irwin St",
    "sg:city":"San Rafael",
    "sg:classifiers":[
        {
            "category":"Retail",
            "subcategory":"Auto Repair",
            "type":"Services"
        }
    ],
    "sg:phone":"+1 415 457 2403",
    "sg:postcode":"94901",
    "sg:province":"CA",
    "sg:tags":[
        "repairing",
        "automobile"
    ],
    "wof:name":"Bertolli's Auto & Truck Svc",
    "wof:placetype":"venue"
},
  "geometry": {"coordinates":[-122.521568,37.968455],"type":"Point"}
}