{
  "type": "Feature",
  "properties": {
    "addr:full":"1249 Waterloo Rd Stockton CA 95205",
    "addr:housenumber":"1249",
    "addr:postcode":"95205",
    "addr:street":"Waterloo Rd",
    "iso:country":"US",
    "sg:address":"1249 Waterloo Rd",
    "sg:city":"Stockton",
    "sg:classifiers":[
        {
            "category":"Building & Trades",
            "subcategory":"Plumbing",
            "type":"Services"
        }
    ],
    "sg:phone":"+1 209 467 3188",
    "sg:postcode":"95205",
    "sg:province":"CA",
    "sg:tags":[
        "plumbing",
        "contractor"
    ],
    "wof:name":"Roto Rod Plumbing",
    "wof:placetype":"venue"
},
  "geometry": {"coordinates":[-121.270607,37.969533],"type":"Point"}
}