{
  "type": "Feature",
  "properties": {
    "addr:full":"20813 Pine Ridge Ave Apple Valley CA 92307",
    "addr:housenumber":"20813",
    "addr:postcode":"92307",
    "addr:street":"Pine Ridge Ave",
    "iso:country":"US",
    "sg:address":"20813 Pine Ridge Ave",
    "sg:city":"Apple Valley",
    "sg:classifiers":[
        {
            "category":"Freight",
            "type":"Transportation"
        }
    ],
    "sg:phone":"+1 760 240 4277",
    "sg:postcode":"92307",
    "sg:province":"CA",
    "sg:tags":[
        "operator",
        "trucking"
    ],
    "wof:name":"TDS Freight System",
    "wof:placetype":"venue"
},
  "geometry": {"coordinates":[-117.209693,34.520576],"type":"Point"}
}