{
  "type": "Feature",
  "properties": {
    "iso:country":"US",
    "sg:address":"2 Ashbrook Pl",
    "sg:city":"Moraga",
    "sg:classifiers":[
        {
            "category":"Building & Trades",
            "subcategory":"Construction",
            "type":"Services"
        }
    ],
    "sg:phone":"+1 925 631 1055",
    "sg:postcode":"94556",
    "sg:province":"CA",
    "sg:tags":[
        "repairing",
        "residential",
        "remodeling",
        "contractor"
    ],
    "wof:name":"Michael Verbrugge Construction",
    "wof:placetype":"venue"
},
  "geometry": {"coordinates":[-122.138381,37.852325],"type":"Point"}
}