{
  "type": "Feature",
  "properties": {
    "addr:full":"1333 E Washington Blvd Los Angeles CA 90021",
    "addr:housenumber":"1333",
    "addr:postcode":"90021",
    "addr:street":"E Washington Blvd",
    "iso:country":"US",
    "sg:address":"1333 E Washington Blvd",
    "sg:city":"Los Angeles",
    "sg:classifiers":[
        {
            "category":"Professional",
            "type":"Services"
        }
    ],
    "sg:phone":"+1 213 742 0530",
    "sg:postcode":"90021",
    "sg:province":"CA",
    "sg:tags":[
        "establishment"
    ],
    "wof:name":"Paspal USA",
    "wof:placetype":"venue"
},
  "geometry": {"coordinates":[-118.248677,34.023548],"type":"Point"}
}