{
  "type": "Feature",
  "properties": {
    "iso:country":"US",
    "sg:address":"1800 Dwight Way Suite A",
    "sg:city":"Berkeley",
    "sg:classifiers":[
        {
            "category":"Arts & Performance",
            "subcategory":"Arts Center",
            "type":"Entertainment"
        },
        {
            "category":"Arts & Performance",
            "subcategory":"Dance",
            "type":"Entertainment"
        }
    ],
    "sg:phone":"+1 510 841 8913",
    "sg:postcode":"94703",
    "sg:province":"CA",
    "sg:tags":[
        "performing",
        "instruction",
        "dancing"
    ],
    "sg:website":"www.berkeleycityballet.org/",
    "wof:name":"Berkeley City Ballet",
    "wof:placetype":"venue"
},
  "geometry": {"coordinates":[-122.27407100000001,37.862829],"type":"Point"}
}