{
  "type": "Feature",
  "properties": {
    "addr:full":"2501 Mountain View Rd El Monte CA 91733",
    "addr:housenumber":"2501",
    "addr:postcode":"91733",
    "addr:street":"Mountain View Rd",
    "iso:country":"US",
    "sg:address":"2501 Mountain View Rd",
    "sg:city":"El Monte",
    "sg:classifiers":[
        {
            "category":"Food & Beverages",
            "subcategory":"Meat & Fish",
            "type":"Retail Goods"
        }
    ],
    "sg:phone":"+1 626 442 3713",
    "sg:postcode":"91733",
    "sg:province":"CA",
    "wof:name":"Tamazula Meat Market",
    "wof:placetype":"venue"
},
  "geometry": {"coordinates":[-118.02786,34.057567],"type":"Point"}
}