{
  "type": "Feature",
  "properties": {
    "addr:full":"722 W Wilson Ave Glendale CA 91203",
    "addr:housenumber":"722",
    "addr:postcode":"91203",
    "addr:street":"W Wilson Ave",
    "iso:country":"US",
    "sg:address":"722 W Wilson Ave",
    "sg:city":"Glendale",
    "sg:classifiers":[
        {
            "category":"Government",
            "subcategory":"Fire Station",
            "type":"Public Place"
        },
        {
            "category":"Personal",
            "type":"Services"
        },
        {
            "category":"Professional",
            "subcategory":"Detective & Security Services",
            "type":"Services"
        },
        {
            "category":"Building & Trades",
            "subcategory":"Construction",
            "type":"Services"
        },
        {
            "category":"Manufacturing",
            "subcategory":"Building Materials",
            "type":"Manufacturing & Wholesale Goods"
        }
    ],
    "sg:phone":"+1 818 502 2051",
    "sg:postcode":"91203",
    "sg:province":"CA",
    "sg:tags":[
        "control",
        "monitoring",
        "alarm",
        "system",
        "contractor",
        "systems-wholesale",
        "protection",
        "medical",
        "manufacturer"
    ],
    "wof:name":"National Fire Systems & Services",
    "wof:placetype":"venue"
},
  "geometry": {"coordinates":[-118.27105400000001,34.14772],"type":"Point"}
}