{
  "type": "Feature",
  "properties": {
    "iso:country":"US",
    "sg:address":"19824 San Miguel Ave",
    "sg:city":"Castro Valley",
    "sg:classifiers":[
        {
            "category":"Building & Trades",
            "subcategory":"Construction",
            "type":"Services"
        }
    ],
    "sg:phone":"+1 510 247 0504",
    "sg:postcode":"94546",
    "sg:province":"CA",
    "sg:tags":[
        "contractor"
    ],
    "wof:name":"Robert Deen Construction",
    "wof:placetype":"venue"
},
  "geometry": {"coordinates":[-122.08479800000001,37.700801],"type":"Point"}
}