{
  "type": "Feature",
  "properties": {
    "iso:country":"US",
    "sg:address":"25081 Front St",
    "sg:city":"Lake Forest",
    "sg:classifiers":[
        {
            "category":"Retail",
            "subcategory":"Auto Repair",
            "type":"Services"
        }
    ],
    "sg:phone":"+1 949 859 7990",
    "sg:postcode":"92630",
    "sg:province":"CA",
    "sg:tags":[
        "automobile",
        "customizing"
    ],
    "sg:website":"www.southcountyautobody.com",
    "wof:name":"South County Auto Body",
    "wof:placetype":"venue"
},
  "geometry": {"coordinates":[-117.692384,33.626227],"type":"Point"}
}