{
  "type": "Feature",
  "properties": {
    "addr:full":"400 E Alondra Blvd Gardena CA 90248",
    "addr:housenumber":"400",
    "addr:postcode":"90248",
    "addr:street":"E Alondra Blvd",
    "iso:country":"US",
    "sg:address":"400 E Alondra Blvd",
    "sg:city":"Gardena",
    "sg:classifiers":[
        {
            "category":"Wholesale",
            "subcategory":"Groceries",
            "type":"Manufacturing & Wholesale Goods"
        }
    ],
    "sg:phone":"+1 310 515 7411",
    "sg:postcode":"90248",
    "sg:province":"CA",
    "sg:tags":[
        "food",
        "broker"
    ],
    "wof:name":"Dae Won Food Inc",
    "wof:placetype":"venue"
},
  "geometry": {"coordinates":[-118.269577,33.885739],"type":"Point"}
}