{
  "type": "Feature",
  "properties": {
    "iso:country":"US",
    "sg:address":"207 Todd Rd",
    "sg:city":"Santa Rosa",
    "sg:classifiers":[
        {
            "category":"Government",
            "subcategory":"Fire Station",
            "type":"Public Place"
        }
    ],
    "sg:phone":"+1 707 584 7288",
    "sg:postcode":"95407",
    "sg:province":"CA",
    "sg:tags":[
        "protection"
    ],
    "wof:name":"Rincon Vly Fire Protection Dst",
    "wof:placetype":"venue"
},
  "geometry": {"coordinates":[-122.720156,38.387236],"type":"Point"}
}