{
  "type": "Feature",
  "properties": {
    "addr:full":"11489 Calvert St North Hollywood CA 91606",
    "addr:housenumber":"11489",
    "addr:postcode":"91606",
    "addr:street":"Calvert St",
    "iso:country":"US",
    "sg:address":"11489 Calvert St",
    "sg:city":"North Hollywood",
    "sg:classifiers":[
        {
            "category":"Shopping",
            "subcategory":"Music",
            "type":"Retail Goods"
        }
    ],
    "sg:phone":"+1 818 761 7669",
    "sg:postcode":"91606",
    "sg:province":"CA",
    "wof:name":"Kalfayan Marie Will Travel",
    "wof:placetype":"venue"
},
  "geometry": {"coordinates":[-118.38280899999999,34.181314],"type":"Point"}
}