{
  "type": "Feature",
  "properties": {
    "iso:country":"US",
    "sg:address":"807 Davis St",
    "sg:city":"Vacaville",
    "sg:classifiers":[
        {
            "category":"Food & Beverages",
            "subcategory":"Groceries & Convenience Stores",
            "type":"Retail Goods"
        }
    ],
    "sg:phone":"+1 707 448 7213",
    "sg:postcode":"95687",
    "sg:province":"CA",
    "wof:name":"Quik Stop",
    "wof:placetype":"venue"
},
  "geometry": {"coordinates":[-121.986467,38.349221],"type":"Point"}
}