{
  "type": "Feature",
  "properties": {
    "iso:country":"US",
    "sg:address":"14017 Paramount Blvd",
    "sg:city":"Paramount",
    "sg:classifiers":[
        {
            "category":"Personal",
            "subcategory":"Barber",
            "type":"Services"
        }
    ],
    "sg:phone":"+1 562 602 1224",
    "sg:postcode":"90723",
    "sg:province":"CA",
    "wof:name":"Sports Barber Shop",
    "wof:placetype":"venue"
},
  "geometry": {"coordinates":[-118.160737,33.906719],"type":"Point"}
}