{
  "type": "Feature",
  "properties": {
    "addr:full":"3733 Taylor Rd Loomis CA 95650",
    "addr:housenumber":"3733",
    "addr:postcode":"95650",
    "addr:street":"Taylor Rd",
    "iso:country":"US",
    "sg:address":"3733 Taylor Rd",
    "sg:city":"Loomis",
    "sg:classifiers":[
        {
            "category":"Social Services",
            "subcategory":"Child Care",
            "type":"Services"
        }
    ],
    "sg:phone":"+1 916 652 5814",
    "sg:postcode":"95650",
    "sg:province":"CA",
    "sg:tags":[
        "foster",
        "agency"
    ],
    "sg:website":"http://www.tropicanachristianfellowship.com",
    "wof:name":"Koinonia Loomis FFA",
    "wof:placetype":"venue"
},
  "geometry": {"coordinates":[-121.19519200000001,38.819477],"type":"Point"}
}