{
  "type": "Feature",
  "properties": {
    "iso:country":"US",
    "sg:address":"3 Greenwood Pl",
    "sg:city":"Menlo Park",
    "sg:classifiers":[
        {
            "category":"Building & Trades",
            "subcategory":"Construction",
            "type":"Services"
        }
    ],
    "sg:phone":"+1 650 328 4418",
    "sg:postcode":"94025",
    "sg:province":"CA",
    "sg:tags":[
        "residential",
        "remodeling",
        "contractor"
    ],
    "wof:name":"Sako Thompson Construction",
    "wof:placetype":"venue"
},
  "geometry": {"coordinates":[-122.174797,37.477278],"type":"Point"}
}