{
  "type": "Feature",
  "properties": {
    "iso:country":"US",
    "sg:address":"2047 W College Ave",
    "sg:city":"Santa Rosa",
    "sg:classifiers":[
        {
            "category":"Building & Trades",
            "subcategory":"Electrical",
            "type":"Services"
        }
    ],
    "sg:phone":"+1 707 542 1466",
    "sg:postcode":"95401",
    "sg:province":"CA",
    "sg:tags":[
        "body",
        "auto",
        "use",
        "electrical",
        "contractor"
    ],
    "wof:name":"Exotic Auto Sales",
    "wof:placetype":"venue"
},
  "geometry": {"coordinates":[-122.749018,38.445212],"type":"Point"}
}