{
  "type": "Feature",
  "properties": {
    "addr:full":"1801 Countryside Drive Turlock CA 95380",
    "addr:housenumber":"1801",
    "addr:postcode":"95380",
    "addr:street":"Countryside Drive",
    "iso:country":"US",
    "sg:address":"1801 Countryside Drive",
    "sg:city":"Turlock",
    "sg:classifiers":[
        {
            "category":"Restaurant",
            "type":"Food & Drink"
        }
    ],
    "sg:phone":"+1 209 656 9189",
    "sg:postcode":"95380",
    "sg:province":"CA",
    "sg:tags":[
        "chinese"
    ],
    "wof:name":"Chong's Cuisine",
    "wof:placetype":"venue"
},
  "geometry": {"coordinates":[-120.87635400000001,37.50881],"type":"Point"}
}