{
  "type": "Feature",
  "properties": {
    "addr:full":"354 Santa Fe Dr Ste Enc81 Encinitas CA 92024",
    "addr:housenumber":"354",
    "addr:postcode":"92024",
    "addr:street":"Santa Fe Dr Ste Enc81",
    "iso:country":"US",
    "sg:address":"354 Santa Fe Dr Ste Enc81",
    "sg:city":"Encinitas",
    "sg:classifiers":[
        {
            "category":"Health Services",
            "subcategory":"Nursing And Care Facility",
            "type":"Services"
        }
    ],
    "sg:phone":"+1 760 633 7685",
    "sg:postcode":"92024",
    "sg:province":"CA",
    "sg:tags":[
        "emergency"
    ],
    "wof:name":"Scripps Well Being",
    "wof:placetype":"venue"
},
  "geometry": {"coordinates":[-117.28439899999999,33.03621],"type":"Point"}
}