{
  "type": "Feature",
  "properties": {
    "addr:full":"37891 2nd St Fremont CA 94536",
    "addr:housenumber":"37891",
    "addr:postcode":"94536",
    "addr:street":"2Nd St",
    "iso:country":"US",
    "sg:address":"37891 2nd St",
    "sg:city":"Fremont",
    "sg:classifiers":[
        {
            "category":"Organizations",
            "subcategory":"Religious Organization",
            "type":"Services"
        }
    ],
    "sg:phone":"+1 510 790 3207",
    "sg:postcode":"94536",
    "sg:province":"CA",
    "sg:tags":[
        "church"
    ],
    "wof:name":"Corpus Christi Church",
    "wof:placetype":"venue"
},
  "geometry": {"coordinates":[-121.975553,37.57497],"type":"Point"}
}