{
  "type": "Feature",
  "properties": {
    "addr:full":"1213 El Mirador Dr Fullerton CA 92835",
    "addr:housenumber":"1213",
    "addr:postcode":"92835",
    "addr:street":"El Mirador Dr",
    "iso:country":"US",
    "sg:address":"1213 El Mirador Dr",
    "sg:city":"Fullerton",
    "sg:classifiers":[
        {
            "category":"Professional",
            "subcategory":"Research",
            "type":"Services"
        }
    ],
    "sg:phone":"+1 714 256 1428",
    "sg:postcode":"92835",
    "sg:province":"CA",
    "wof:name":"Ken Cowans Enterprises",
    "wof:placetype":"venue"
},
  "geometry": {"coordinates":[-117.905725,33.905494],"type":"Point"}
}