{
  "type": "Feature",
  "properties": {
    "iso:country":"US",
    "sg:address":"4045 Lake Tahoe Blvd",
    "sg:city":"South Lake Tahoe",
    "sg:classifiers":[
        {
            "category":"Recreation",
            "type":"Entertainment"
        },
        {
            "category":"Shopping",
            "subcategory":"Bicycles & Sporting Goods",
            "type":"Retail Goods"
        }
    ],
    "sg:phone":"+1 530 542 6222",
    "sg:postcode":"96150",
    "sg:province":"CA",
    "sg:tags":[
        "equipment",
        "rental",
        "skiing"
    ],
    "wof:name":"Powder House The",
    "wof:placetype":"venue"
},
  "geometry": {"coordinates":[-119.944485,38.955656],"type":"Point"}
}