{
  "type": "Feature",
  "properties": {
    "addr:full":"1321 61st St Emeryville CA 94608",
    "addr:housenumber":"1321",
    "addr:postcode":"94608",
    "addr:street":"61St St",
    "iso:country":"US",
    "sg:address":"1321 61st St",
    "sg:city":"Emeryville",
    "sg:classifiers":[
        {
            "category":"Communications",
            "type":"Services"
        }
    ],
    "sg:phone":"+1 510 333 5334",
    "sg:postcode":"94608",
    "sg:province":"CA",
    "sg:tags":[
        "recording",
        "rehearsal",
        "studio"
    ],
    "sg:website":"www.spliggityfidge.com",
    "wof:name":"Spliggityfidge",
    "wof:placetype":"venue"
},
  "geometry": {"coordinates":[-122.288826,37.842957],"type":"Point"}
}