{
  "type": "Feature",
  "properties": {
    "addr:full":"5963 La Place Ct Carlsbad CA 92008",
    "addr:housenumber":"5963",
    "addr:postcode":"92008",
    "addr:street":"La Place Ct",
    "iso:country":"US",
    "sg:address":"5963 La Place Ct",
    "sg:city":"Carlsbad",
    "sg:classifiers":[
        {
            "category":"Professional",
            "subcategory":"Lawyer & Legal Services",
            "type":"Services"
        },
        {
            "category":"Banks & Credit Unions",
            "subcategory":"Atm",
            "type":"Services"
        }
    ],
    "sg:phone":"+1 760 438 5291",
    "sg:postcode":"92008",
    "sg:province":"CA",
    "sg:tags":[
        "divorce",
        "law",
        "family",
        "bankruptcy"
    ],
    "sg:website":"www.countylawcenter.com/",
    "wof:name":"County Law Center",
    "wof:placetype":"venue"
},
  "geometry": {"coordinates":[-117.27244399999999,33.131644],"type":"Point"}
}