{
  "type": "Feature",
  "properties": {
    "addr:full":"4th Ave & Mission St Carmel By The Sea CA 93923",
    "addr:postcode":"93923",
    "addr:street":"4Th;St",
    "iso:country":"US",
    "sg:address":"4th Ave & Mission St",
    "sg:city":"Carmel By The Sea",
    "sg:classifiers":[
        {
            "category":"Travel",
            "subcategory":"Hotels & Motels",
            "type":"Entertainment"
        },
        {
            "category":"Travel",
            "subcategory":"Bed & Breakfast",
            "type":"Entertainment"
        }
    ],
    "sg:phone":"+1 831 624 2711",
    "sg:postcode":"93923",
    "sg:province":"CA",
    "sg:website":"www.CarmelWayfarerInn.com",
    "wof:name":"Carmel Wayfarer Inn",
    "wof:placetype":"venue"
},
  "geometry": {"coordinates":[-121.920959,36.558131],"type":"Point"}
}