{
  "type": "Feature",
  "properties": {
    "iso:country":"US",
    "sg:address":"1431 Mott Rd",
    "sg:city":"Mt Shasta",
    "sg:classifiers":[
        {
            "category":"Building & Trades",
            "subcategory":"Construction",
            "type":"Services"
        }
    ],
    "sg:phone":"+1 530 926 2828",
    "sg:postcode":"96067",
    "sg:province":"CA",
    "sg:tags":[
        "tile",
        "dealer"
    ],
    "wof:name":"Starr Tile",
    "wof:placetype":"venue"
},
  "geometry": {"coordinates":[-122.281296,41.260658],"type":"Point"}
}