{
  "type": "Feature",
  "properties": {
    "addr:full":"1516 Del Paso Boulevard Sacramento CA 95815",
    "addr:housenumber":"1516",
    "addr:postcode":"95815",
    "addr:street":"Del Paso Boulevard",
    "iso:country":"US",
    "sg:address":"1516 Del Paso Boulevard",
    "sg:city":"Sacramento",
    "sg:classifiers":[
        {
            "category":"Professional",
            "type":"Services"
        }
    ],
    "sg:phone":"+1 916 925 2310",
    "sg:postcode":"95815",
    "sg:province":"CA",
    "sg:website":"austinsuptown.com",
    "wof:name":"Austin's Uptown Studio",
    "wof:placetype":"venue"
},
  "geometry": {"coordinates":[-121.457533,38.606739],"type":"Point"}
}