{
  "type": "Feature",
  "properties": {
    "addr:full":"2245 S Hacienda Blvd Hacienda Heights CA 91745",
    "addr:housenumber":"2245",
    "addr:postcode":"91745",
    "addr:street":"S Hacienda Blvd",
    "iso:country":"US",
    "sg:address":"2245 S Hacienda Blvd",
    "sg:city":"Hacienda Heights",
    "sg:classifiers":[
        {
            "category":"Organizations",
            "subcategory":"Religious Organization",
            "type":"Services"
        }
    ],
    "sg:phone":"+1 626 333 2634",
    "sg:postcode":"91745",
    "sg:province":"CA",
    "sg:tags":[
        "church"
    ],
    "sg:website":"www.efchh.org",
    "wof:name":"Evangelical Formosan",
    "wof:placetype":"venue"
},
  "geometry": {"coordinates":[-117.968667,33.994271],"type":"Point"}
}