{
  "type": "Feature",
  "properties": {
    "addr:full":"1800 E Walnut Ave Fullerton CA 92831",
    "addr:housenumber":"1800",
    "addr:postcode":"92831",
    "addr:street":"E Walnut Ave",
    "iso:country":"US",
    "sg:address":"1800 E Walnut Ave",
    "sg:city":"Fullerton",
    "sg:classifiers":[
        {
            "category":"Wholesale",
            "subcategory":"Electrical",
            "type":"Manufacturing & Wholesale Goods"
        }
    ],
    "sg:phone":"+1 714 680 6800",
    "sg:postcode":"92831",
    "sg:province":"CA",
    "sg:tags":[
        "cleaners",
        "vacuum"
    ],
    "wof:name":"Blakeman's",
    "wof:placetype":"venue"
},
  "geometry": {"coordinates":[-117.89579999999999,33.868571],"type":"Point"}
}