{
  "type": "Feature",
  "properties": {
    "addr:full":"300 Carlsbad Village Dr Carlsbad CA 92008",
    "addr:housenumber":"300",
    "addr:postcode":"92008",
    "addr:street":"Carlsbad Village Dr",
    "iso:country":"US",
    "sg:address":"300 Carlsbad Village Dr",
    "sg:city":"Carlsbad",
    "sg:classifiers":[
        {
            "category":"Building & Trades",
            "subcategory":"Construction",
            "type":"Services"
        }
    ],
    "sg:phone":"+1 760 519 1291",
    "sg:postcode":"92008",
    "sg:province":"CA",
    "sg:tags":[
        "wallcoverings-installation",
        "wallpaper",
        "painting",
        "contractor"
    ],
    "wof:name":"Boswell Painting",
    "wof:placetype":"venue"
},
  "geometry": {"coordinates":[-117.35095200000001,33.158291],"type":"Point"}
}