{
  "type": "Feature",
  "properties": {
    "iso:country":"US",
    "sg:address":"13668 Frame Rd",
    "sg:city":"Poway",
    "sg:classifiers":[
        {
            "category":"Social Services",
            "subcategory":"Child Care",
            "type":"Services"
        }
    ],
    "sg:phone":"+1 858 748 3694",
    "sg:postcode":"92064",
    "sg:province":"CA",
    "wof:name":"Little Peoples Child Care",
    "wof:placetype":"venue"
},
  "geometry": {"coordinates":[-117.060984,32.960276],"type":"Point"}
}