{
  "type": "Feature",
  "properties": {
    "addr:full":"Loehmann's Plaza 2511 Fair Oaks Blvd Sacramento CA 95825",
    "addr:housenumber":"2511",
    "addr:postcode":"95825",
    "addr:street":"Fair Oaks Blvd",
    "iso:country":"US",
    "sg:address":"Loehmann's Plaza 2511 Fair Oaks Blvd",
    "sg:city":"Sacramento",
    "sg:classifiers":[
        {
            "category":"Personal",
            "subcategory":"Massage",
            "type":"Services"
        },
        {
            "category":"Personal",
            "subcategory":"Day Spa",
            "type":"Services"
        },
        {
            "category":"Personal",
            "subcategory":"Skin Care",
            "type":"Services"
        }
    ],
    "sg:phone":"+1 916 481 3689",
    "sg:postcode":"95825",
    "sg:province":"CA",
    "sg:tags":[
        "therapist"
    ],
    "sg:website":"massageenvy.com/clinics/CA/Loehm...",
    "wof:name":"Massage Envy",
    "wof:placetype":"venue"
},
  "geometry": {"coordinates":[-121.403733,38.574325],"type":"Point"}
}