{
  "type": "Feature",
  "properties": {
    "addr:full":"3303 Harbor Blvd Ste B11 Costa Mesa CA 92626",
    "addr:housenumber":"3303",
    "addr:postcode":"92626",
    "addr:street":"Harbor Blvd Ste B11",
    "iso:country":"US",
    "sg:address":"3303 Harbor Blvd Ste B11",
    "sg:city":"Costa Mesa",
    "sg:classifiers":[
        {
            "category":"Wholesale",
            "subcategory":"Computers",
            "type":"Manufacturing & Wholesale Goods"
        }
    ],
    "sg:phone":"+1 714 241 0211",
    "sg:postcode":"92626",
    "sg:province":"CA",
    "sg:website":"www.alphadent.com",
    "wof:name":"Alphadent",
    "wof:placetype":"venue"
},
  "geometry": {"coordinates":[-117.920023,33.693154],"type":"Point"}
}