{
  "type": "Feature",
  "properties": {
    "iso:country":"US",
    "sg:address":"2224 Vineyard Ct",
    "sg:city":"Los Altos",
    "sg:classifiers":[
        {
            "category":"Real Estate",
            "subcategory":"Real Estate Agent",
            "type":"Services"
        }
    ],
    "sg:phone":"+1 650 968 3891",
    "sg:postcode":"94024",
    "sg:province":"CA",
    "wof:name":"Westland Investments",
    "wof:placetype":"venue"
},
  "geometry": {"coordinates":[-122.071843,37.336898],"type":"Point"}
}