{
  "type": "Feature",
  "properties": {
    "iso:country":"US",
    "sg:address":"285 W Huntington Dr",
    "sg:city":"Arcadia",
    "sg:classifiers":[
        {
            "category":"Retail",
            "subcategory":"Animal Services",
            "type":"Services"
        }
    ],
    "sg:phone":"+1 626 574 7761",
    "sg:postcode":"91007",
    "sg:province":"CA",
    "sg:tags":[
        "pet"
    ],
    "wof:name":"Hofman David",
    "wof:placetype":"venue"
},
  "geometry": {"coordinates":[-118.124563,34.136361],"type":"Point"}
}