{
  "type": "Feature",
  "properties": {
    "iso:country":"US",
    "sg:address":"785 Walnut St",
    "sg:city":"San Carlos",
    "sg:classifiers":[
        {
            "category":"Social Services",
            "subcategory":"Child Care",
            "type":"Services"
        }
    ],
    "sg:phone":"+1 650 593 8081",
    "sg:postcode":"94070",
    "sg:province":"CA",
    "wof:name":"Little Learners Preschool",
    "wof:placetype":"venue"
},
  "geometry": {"coordinates":[-122.260266,37.504375],"type":"Point"}
}