{
  "type": "Feature",
  "properties": {
    "addr:full":"761 S Los Angeles St Los Angeles CA 90014",
    "addr:housenumber":"761",
    "addr:postcode":"90014",
    "addr:street":"S Los Angeles St",
    "iso:country":"US",
    "sg:address":"761 S Los Angeles St",
    "sg:city":"Los Angeles",
    "sg:classifiers":[
        {
            "category":"Shopping",
            "subcategory":"Crafts & Fabrics",
            "type":"Retail Goods"
        }
    ],
    "sg:phone":"+1 213 607 1558",
    "sg:postcode":"90014",
    "sg:province":"CA",
    "sg:tags":[
        "art",
        "supply"
    ],
    "sg:website":"www.unitynick.com",
    "wof:name":"Unity Nick Inc",
    "wof:placetype":"venue"
},
  "geometry": {"coordinates":[-118.251999,34.042],"type":"Point"}
}