{
  "type": "Feature",
  "properties": {
    "iso:country":"US",
    "sg:address":"455 N Rexford Dr",
    "sg:city":"Beverly Hills",
    "sg:classifiers":[
        {
            "category":"Government",
            "subcategory":"Office",
            "type":"Public Place"
        }
    ],
    "sg:phone":"+1 310 285 2438",
    "sg:postcode":"90210",
    "sg:province":"CA",
    "sg:tags":[
        "village"
    ],
    "wof:name":"Communications & Marketing",
    "wof:placetype":"venue"
},
  "geometry": {"coordinates":[-118.399844,34.072843],"type":"Point"}
}