{
  "type": "Feature",
  "properties": {
    "iso:country":"US",
    "sg:address":"220 E 10th St",
    "sg:city":"Gilroy",
    "sg:classifiers":[
        {
            "category":"Personal",
            "type":"Services"
        }
    ],
    "sg:phone":"+1 408 842 6877",
    "sg:postcode":"95020",
    "sg:province":"CA",
    "sg:tags":[
        "control",
        "weight"
    ],
    "wof:name":"Gilroy Medical Weight Control",
    "wof:placetype":"venue"
},
  "geometry": {"coordinates":[-121.561533,37.001343],"type":"Point"}
}