{
  "type": "Feature",
  "properties": {
    "iso:country":"US",
    "sg:address":"10010 Canoga Ave",
    "sg:city":"Chatsworth",
    "sg:classifiers":[
        {
            "category":"Wholesale",
            "subcategory":"Computers",
            "type":"Manufacturing & Wholesale Goods"
        },
        {
            "category":"Shopping",
            "subcategory":"Catalog Store",
            "type":"Retail Goods"
        }
    ],
    "sg:phone":"+1 818 998 4045",
    "sg:postcode":"91311",
    "sg:province":"CA",
    "sg:tags":[
        "prepackaged",
        "e",
        "software"
    ],
    "sg:website":"www.ruhungry.com",
    "wof:name":"All You Can Eat Inc",
    "wof:placetype":"venue"
},
  "geometry": {"coordinates":[-118.59723099999999,34.251586],"type":"Point"}
}