{
  "type": "Feature",
  "properties": {
    "iso:country":"US",
    "sg:address":"2938 Crocker Ave",
    "sg:city":"Redwood City",
    "sg:classifiers":[
        {
            "category":"Retail",
            "subcategory":"Auto Repair",
            "type":"Services"
        }
    ],
    "sg:phone":"+1 650 361 8697",
    "sg:postcode":"94063",
    "sg:province":"CA",
    "sg:tags":[
        "road"
    ],
    "wof:name":"All Weather Towing",
    "wof:placetype":"venue"
},
  "geometry": {"coordinates":[-122.207777,37.475135],"type":"Point"}
}