{
  "type": "Feature",
  "properties": {
    "iso:country":"US",
    "sg:address":"801 Riverside Ave",
    "sg:city":"Roseville",
    "sg:classifiers":[
        {
            "category":"Wholesale",
            "subcategory":"Scrap",
            "type":"Manufacturing & Wholesale Goods"
        }
    ],
    "sg:phone":"+1 916 780 9300",
    "sg:postcode":"95678",
    "sg:province":"CA",
    "sg:tags":[
        "salvage",
        "surplus",
        "merchandise"
    ],
    "wof:name":"Export International Nic",
    "wof:placetype":"venue"
},
  "geometry": {"coordinates":[-121.290404,38.729943],"type":"Point"}
}