{
  "type": "Feature",
  "properties": {
    "iso:country":"US",
    "sg:address":"3030 W Olympic Blvd",
    "sg:city":"Los Angeles",
    "sg:classifiers":[
        {
            "category":"Shopping",
            "subcategory":"Clothing, Apparel, & Fashions",
            "type":"Retail Goods"
        }
    ],
    "sg:phone":"+1 213 380 1446",
    "sg:postcode":"90006",
    "sg:province":"CA",
    "wof:name":"S S Collection",
    "wof:placetype":"venue"
},
  "geometry": {"coordinates":[-118.301908,34.05254],"type":"Point"}
}