{
  "type": "Feature",
  "properties": {
    "iso:country":"US",
    "sg:address":"10825 7th St",
    "sg:city":"Rancho Cucamonga",
    "sg:classifiers":[
        {
            "category":"Shopping",
            "subcategory":"Hobbies, Toys, & Games",
            "type":"Retail Goods"
        }
    ],
    "sg:phone":"+1 909 466 1615",
    "sg:postcode":"91730",
    "sg:province":"CA",
    "sg:tags":[
        "product",
        "ceramic"
    ],
    "wof:name":"Radford Tableware",
    "wof:placetype":"venue"
},
  "geometry": {"coordinates":[-117.567098,34.08858],"type":"Point"}
}