{
  "type": "Feature",
  "properties": {
    "addr:full":"2938 4th St Ceres CA 95307",
    "addr:housenumber":"2938",
    "addr:postcode":"95307",
    "addr:street":"4Th St",
    "iso:country":"US",
    "sg:address":"2938 4th St",
    "sg:city":"Ceres",
    "sg:classifiers":[
        {
            "category":"Home & Garden",
            "subcategory":"Furniture",
            "type":"Retail Goods"
        }
    ],
    "sg:phone":"+1 209 538 7125",
    "sg:postcode":"95307",
    "sg:province":"CA",
    "wof:name":"Mayra's Furniture",
    "wof:placetype":"venue"
},
  "geometry": {"coordinates":[-120.95326300000001,37.590731],"type":"Point"}
}