{
  "type": "Feature",
  "properties": {
    "iso:country":"US",
    "sg:address":"5241 Passons Blvd",
    "sg:city":"Pico Rivera",
    "sg:classifiers":[
        {
            "category":"Education",
            "subcategory":"School",
            "type":"Public Place"
        }
    ],
    "sg:phone":"+1 562 801 5177",
    "sg:postcode":"90660",
    "sg:province":"CA",
    "wof:name":"South Ranchito Elementary",
    "wof:placetype":"venue"
},
  "geometry": {"coordinates":[-118.08000199999999,33.995201],"type":"Point"}
}