{
  "type": "Feature",
  "properties": {
    "addr:full":"1164 Triton Dr San Mateo CA 94404",
    "addr:housenumber":"1164",
    "addr:postcode":"94404",
    "addr:street":"Triton Dr",
    "iso:country":"US",
    "sg:address":"1164 Triton Dr",
    "sg:city":"San Mateo",
    "sg:classifiers":[
        {
            "category":"Professional",
            "subcategory":"Art Services",
            "type":"Services"
        }
    ],
    "sg:phone":"+1 650 578 8333",
    "sg:postcode":"94404",
    "sg:province":"CA",
    "sg:tags":[
        "commercial",
        "design",
        "typesetting"
    ],
    "wof:name":"Seven Worldwide  Inc",
    "wof:placetype":"venue"
},
  "geometry": {"coordinates":[-122.270809,37.563487],"type":"Point"}
}