{
  "type": "Feature",
  "properties": {
    "addr:full":"4475 Leisa Ln Penryn CA 95663",
    "addr:housenumber":"4475",
    "addr:postcode":"95663",
    "addr:street":"Leisa Ln",
    "iso:country":"US",
    "sg:address":"4475 Leisa Ln",
    "sg:city":"Penryn",
    "sg:classifiers":[
        {
            "category":"Building & Trades",
            "subcategory":"Construction",
            "type":"Services"
        }
    ],
    "sg:phone":"+1 916 652 9146",
    "sg:postcode":"95663",
    "sg:province":"CA",
    "sg:tags":[
        "painter"
    ],
    "wof:name":"Ted Neal Painting & Decorating",
    "wof:placetype":"venue"
},
  "geometry": {"coordinates":[-121.217865,38.844636],"type":"Point"}
}