{
  "type": "Feature",
  "properties": {
    "iso:country":"US",
    "sg:address":"6121 Hollis St",
    "sg:city":"Emeryville",
    "sg:classifiers":[
        {
            "category":"Professional",
            "type":"Services"
        }
    ],
    "sg:phone":"+1 510 903 7200",
    "sg:postcode":"94608",
    "sg:province":"CA",
    "wof:name":"Evault",
    "wof:placetype":"venue"
},
  "geometry": {"coordinates":[-122.290354,37.842843],"type":"Point"}
}