{
  "type": "Feature",
  "properties": {
    "addr:full":"6333 W 3rd St Los Angeles CA 90036",
    "addr:housenumber":"6333",
    "addr:postcode":"90036",
    "addr:street":"W 3Rd St",
    "iso:country":"US",
    "sg:address":"6333 W 3rd St",
    "sg:city":"Los Angeles",
    "sg:classifiers":[
        {
            "category":"Shopping",
            "subcategory":"Mobile Phones",
            "type":"Retail Goods"
        }
    ],
    "sg:phone":"+1 323 937 4665",
    "sg:postcode":"90036",
    "sg:province":"CA",
    "sg:website":"www.powercell.com",
    "wof:name":"Powercell",
    "wof:placetype":"venue"
},
  "geometry": {"coordinates":[-118.360067,34.146998],"type":"Point"}
}