{
  "type": "Feature",
  "properties": {
    "addr:full":"3162 Fillmore St Riverside CA 92503",
    "addr:housenumber":"3162",
    "addr:postcode":"92503",
    "addr:street":"Fillmore St",
    "iso:country":"US",
    "sg:address":"3162 Fillmore St",
    "sg:city":"Riverside",
    "sg:classifiers":[
        {
            "category":"Wholesale",
            "subcategory":"Medical Equipment & Supplies",
            "type":"Manufacturing & Wholesale Goods"
        }
    ],
    "sg:phone":"+1 909 590 0092",
    "sg:postcode":"92503",
    "sg:province":"CA",
    "sg:tags":[
        "hospital"
    ],
    "wof:name":"Millennium Medical Supply",
    "wof:placetype":"venue"
},
  "geometry": {"coordinates":[-117.47539999999999,33.889012],"type":"Point"}
}