{
  "type": "Feature",
  "properties": {
    "addr:full":"1001 2nd St Napa CA 94559",
    "addr:housenumber":"1001",
    "addr:postcode":"94559",
    "addr:street":"2Nd St",
    "iso:country":"US",
    "sg:address":"1001 2nd St",
    "sg:city":"Napa",
    "sg:classifiers":[
        {
            "category":"Restaurant",
            "type":"Food & Drink"
        }
    ],
    "sg:phone":"+1 707 224 0607",
    "sg:postcode":"94559",
    "sg:province":"CA",
    "wof:name":"LA Gondola",
    "wof:placetype":"venue"
},
  "geometry": {"coordinates":[-122.285391,38.298232],"type":"Point"}
}