{
  "type": "Feature",
  "properties": {
    "addr:full":"8730 Wilshire Blvd Suite 310 Beverly Hills CA 90211",
    "addr:housenumber":"8730",
    "addr:postcode":"90211",
    "addr:street":"Wilshire Blvd Suite 310;Hills Ca",
    "iso:country":"US",
    "sg:address":"8730 Wilshire Blvd Suite 310",
    "sg:city":"Beverly Hills",
    "sg:classifiers":[
        {
            "category":"Professional",
            "subcategory":"Computer Services",
            "type":"Services"
        }
    ],
    "sg:phone":"+1 310 770 9398",
    "sg:postcode":"90211",
    "sg:province":"CA",
    "sg:tags":[
        "repair"
    ],
    "sg:website":"provalint.com",
    "wof:name":"ProValint Solutions",
    "wof:placetype":"venue"
},
  "geometry": {"coordinates":[-118.382358,34.066375],"type":"Point"}
}