{
  "type": "Feature",
  "properties": {
    "iso:country":"US",
    "sg:address":"1977 Wyrick Avenue",
    "sg:city":"San Jose",
    "sg:classifiers":[
        {
            "category":"Shopping",
            "subcategory":"Books",
            "type":"Retail Goods"
        }
    ],
    "sg:phone":"+1 408 377 9452",
    "sg:postcode":"95124",
    "sg:province":"CA",
    "sg:tags":[
        "bookstore"
    ],
    "wof:name":"The Church of Jesus Christ of Latter-Day Saints",
    "wof:placetype":"venue"
},
  "geometry": {"coordinates":[-121.91790899999999,37.254005],"type":"Point"}
}