{
  "type": "Feature",
  "properties": {
    "iso:country":"US",
    "sg:address":"1983 Potrero Grande Dr",
    "sg:city":"Monterey Park",
    "sg:classifiers":[
        {
            "category":"Wholesale",
            "subcategory":"Chemicals & Plastics",
            "type":"Manufacturing & Wholesale Goods"
        }
    ],
    "sg:phone":"+1 626 573 0242",
    "sg:postcode":"91755",
    "sg:province":"CA",
    "sg:tags":[
        "bulk",
        "carbon",
        "system",
        "fire",
        "dioxide"
    ],
    "wof:name":"Rigoli Pacific Company Inc",
    "wof:placetype":"venue"
},
  "geometry": {"coordinates":[-118.10081,34.043983],"type":"Point"}
}