{
  "type": "Feature",
  "properties": {
    "iso:country":"US",
    "sg:address":"220 Sierra Manor Rd",
    "sg:city":"Mammoth Lakes",
    "sg:classifiers":[
        {
            "category":"Building & Trades",
            "subcategory":"Plumbing",
            "type":"Services"
        }
    ],
    "sg:phone":"+1 760 934 7567",
    "sg:postcode":"93546",
    "sg:province":"CA",
    "sg:tags":[
        "plumbing",
        "contractor"
    ],
    "wof:name":"Higerd Plumbing",
    "wof:placetype":"venue"
},
  "geometry": {"coordinates":[-118.96485,37.640105],"type":"Point"}
}