{
  "type": "Feature",
  "properties": {
    "iso:country":"US",
    "sg:address":"1011 Encinas Ave",
    "sg:city":"Calexico",
    "sg:classifiers":[
        {
            "category":"Autos & Motor Vehicles",
            "subcategory":"Auto Supplies",
            "type":"Retail Goods"
        }
    ],
    "sg:phone":"+1 760 357 6005",
    "sg:postcode":"92231",
    "sg:province":"CA",
    "sg:tags":[
        "tire"
    ],
    "wof:name":"German's Tires",
    "wof:placetype":"venue"
},
  "geometry": {"coordinates":[-115.48831800000001,32.677711],"type":"Point"}
}