{
  "type": "Feature",
  "properties": {
    "addr:full":"1304 Southpoint Blvd Petaluma CA 94954",
    "addr:housenumber":"1304",
    "addr:postcode":"94954",
    "addr:street":"Southpoint Blvd",
    "iso:country":"US",
    "sg:address":"1304 Southpoint Blvd",
    "sg:city":"Petaluma",
    "sg:classifiers":[
        {
            "category":"Professional",
            "subcategory":"Computer Services",
            "type":"Services"
        }
    ],
    "sg:phone":"+1 707 762 1225",
    "sg:postcode":"94954",
    "sg:province":"CA",
    "sg:tags":[
        "consultant",
        "designer"
    ],
    "wof:name":"ETA Accounting Software Spec",
    "wof:placetype":"venue"
},
  "geometry": {"coordinates":[-122.648132,38.260579],"type":"Point"}
}