{
  "type": "Feature",
  "properties": {
    "iso:country":"US",
    "sg:address":"6 Pamaron Way",
    "sg:city":"Novato",
    "sg:classifiers":[
        {
            "category":"Building & Trades",
            "subcategory":"Construction",
            "type":"Services"
        }
    ],
    "sg:phone":"+1 415 883 8882",
    "sg:postcode":"94949",
    "sg:province":"CA",
    "sg:tags":[
        "interior",
        "finishing",
        "furnishing"
    ],
    "wof:name":"Artistic Drapery",
    "wof:placetype":"venue"
},
  "geometry": {"coordinates":[-122.530896,38.06572],"type":"Point"}
}