{
  "type": "Feature",
  "properties": {
    "addr:full":"24625 Harrison St Foresthill CA 95631",
    "addr:housenumber":"24625",
    "addr:postcode":"95631",
    "addr:street":"Harrison St",
    "iso:country":"US",
    "sg:address":"24625 Harrison St",
    "sg:city":"Foresthill",
    "sg:classifiers":[
        {
            "category":"Utilities",
            "subcategory":"Water",
            "type":"Services"
        }
    ],
    "sg:phone":"+1 530 367 2291",
    "sg:postcode":"95631",
    "sg:province":"CA",
    "sg:tags":[
        "company",
        "sewage"
    ],
    "wof:name":"Placer County Water Agency",
    "wof:placetype":"venue"
},
  "geometry": {"coordinates":[-120.814173,39.021999],"type":"Point"}
}