{
  "type": "Feature",
  "properties": {
    "iso:country":"US",
    "sg:address":"16626 S Main St",
    "sg:city":"Gardena",
    "sg:classifiers":[
        {
            "category":"Retail",
            "subcategory":"Auto Repair",
            "type":"Services"
        }
    ],
    "sg:phone":"+1 310 515 5663",
    "sg:postcode":"90248",
    "sg:province":"CA",
    "sg:website":"www.paulsautomotive.com",
    "wof:name":"Pauls Automotive 2",
    "wof:placetype":"venue"
},
  "geometry": {"coordinates":[-118.275539,33.880452],"type":"Point"}
}