{
  "type": "Feature",
  "properties": {
    "addr:full":"232 N Azusa Ave Azusa CA 91702",
    "addr:housenumber":"232",
    "addr:postcode":"91702",
    "addr:street":"N Azusa Ave",
    "iso:country":"US",
    "sg:address":"232 N Azusa Ave",
    "sg:city":"Azusa",
    "sg:classifiers":[
        {
            "category":"Building & Trades",
            "subcategory":"Electrical",
            "type":"Services"
        }
    ],
    "sg:phone":"+1 626 969 3677",
    "sg:postcode":"91702",
    "sg:province":"CA",
    "sg:tags":[
        "electrical",
        "contractor"
    ],
    "wof:name":"Dans Electric",
    "wof:placetype":"venue"
},
  "geometry": {"coordinates":[-117.907498,34.125632],"type":"Point"}
}