{
  "type": "Feature",
  "properties": {
    "addr:full":"620 W Charter Way Stockton CA 95206",
    "addr:housenumber":"620",
    "addr:postcode":"95206",
    "addr:street":"W Charter Way",
    "iso:country":"US",
    "sg:address":"620 W Charter Way",
    "sg:city":"Stockton",
    "sg:classifiers":[
        {
            "category":"Autos & Motor Vehicles",
            "subcategory":"Fuel & Gas Station",
            "type":"Retail Goods"
        }
    ],
    "sg:phone":"+1 209 466 1901",
    "sg:postcode":"95206",
    "sg:province":"CA",
    "sg:tags":[
        "oil"
    ],
    "wof:name":"Charter Way Shell",
    "wof:placetype":"venue"
},
  "geometry": {"coordinates":[-121.296331,37.936997],"type":"Point"}
}