{
  "type": "Feature",
  "properties": {
    "addr:full":"2423 Cam del Rio S San Diego CA 92108",
    "addr:housenumber":"2423",
    "addr:postcode":"92108",
    "addr:street":"Cam Del Rio S",
    "iso:country":"US",
    "sg:address":"2423 Cam del Rio S",
    "sg:city":"San Diego",
    "sg:classifiers":[
        {
            "category":"Real Estate",
            "subcategory":"Real Estate Agent",
            "type":"Services"
        }
    ],
    "sg:phone":"+1 619 291 5262",
    "sg:postcode":"92108",
    "sg:province":"CA",
    "sg:tags":[
        "consultant"
    ],
    "wof:name":"Nefran Financial & Cnsltnt Svc",
    "wof:placetype":"venue"
},
  "geometry": {"coordinates":[-117.13916,32.76727],"type":"Point"}
}