{
  "type": "Feature",
  "properties": {
    "addr:full":"81581 US Hwy 111 Indio CA 92201",
    "addr:housenumber":"81581",
    "addr:postcode":"92201",
    "addr:street":"Us Hwy 111",
    "iso:country":"US",
    "sg:address":"81581 US Hwy 111",
    "sg:city":"Indio",
    "sg:classifiers":[
        {
            "category":"Retail",
            "subcategory":"Repair Shop",
            "type":"Services"
        }
    ],
    "sg:phone":"+1 760 342 1044",
    "sg:postcode":"92201",
    "sg:province":"CA",
    "sg:tags":[
        "lock",
        "locksmith"
    ],
    "wof:name":"Lock Shop-Security Ctr",
    "wof:placetype":"venue"
},
  "geometry": {"coordinates":[-116.239969,33.709146],"type":"Point"}
}