{
  "type": "Feature",
  "properties": {
    "addr:full":"2984 Teagarden St San Leandro CA 94577",
    "addr:housenumber":"2984",
    "addr:postcode":"94577",
    "addr:street":"Teagarden St",
    "iso:country":"US",
    "sg:address":"2984 Teagarden St",
    "sg:city":"San Leandro",
    "sg:classifiers":[
        {
            "category":"Professional",
            "subcategory":"Research",
            "type":"Services"
        }
    ],
    "sg:phone":"+1 510 667 6440",
    "sg:postcode":"94577",
    "sg:province":"CA",
    "sg:tags":[
        "environmental",
        "ecological"
    ],
    "wof:name":"Winzler & Kelly Consulting",
    "wof:placetype":"venue"
},
  "geometry": {"coordinates":[-122.15736699999999,37.705635],"type":"Point"}
}