{
  "type": "Feature",
  "properties": {
    "addr:full":"457 Mariposa St San Francisco CA 94107",
    "addr:housenumber":"457",
    "addr:postcode":"94107",
    "addr:street":"Mariposa St",
    "iso:country":"US",
    "sg:address":"457 Mariposa St",
    "sg:city":"San Francisco",
    "sg:classifiers":[
        {
            "category":"Wholesale",
            "subcategory":"Medical Equipment & Supplies",
            "type":"Manufacturing & Wholesale Goods"
        }
    ],
    "sg:phone":"+1 415 241 2400",
    "sg:postcode":"94107",
    "sg:province":"CA",
    "sg:tags":[
        "physician",
        "surgeon"
    ],
    "wof:name":"A-SPINE USA Inc",
    "wof:placetype":"venue"
},
  "geometry": {"coordinates":[-122.388423,37.76428],"type":"Point"}
}