{
  "type": "Feature",
  "properties": {
    "iso:country":"US",
    "sg:address":"1575 Omaha Ct",
    "sg:city":"Riverside",
    "sg:classifiers":[
        {
            "category":"Manufacturing",
            "subcategory":"Rubber & Plastics",
            "type":"Manufacturing & Wholesale Goods"
        },
        {
            "category":"Wholesale",
            "subcategory":"Chemicals & Plastics",
            "type":"Manufacturing & Wholesale Goods"
        }
    ],
    "sg:phone":"+1 951 782 9020",
    "sg:postcode":"92507",
    "sg:province":"CA",
    "sg:tags":[
        "plastics-extruders",
        "pressure",
        "plastics-vacuum",
        "forming-manufacturers"
    ],
    "wof:name":"Bm Extrusion Inc",
    "wof:placetype":"venue"
},
  "geometry": {"coordinates":[-117.345128,33.995121],"type":"Point"}
}