{
  "type": "Feature",
  "properties": {
    "addr:full":"760 Market St San Francisco CA 94102",
    "addr:housenumber":"760",
    "addr:postcode":"94102",
    "addr:street":"Market St",
    "iso:country":"US",
    "sg:address":"760 Market St",
    "sg:city":"San Francisco",
    "sg:classifiers":[
        {
            "category":"Building & Trades",
            "subcategory":"Construction",
            "type":"Services"
        }
    ],
    "sg:phone":"+1 415 839 4040",
    "sg:postcode":"94102",
    "sg:province":"CA",
    "sg:tags":[
        "maintenance",
        "contractor"
    ],
    "wof:name":"C & C Maintenance",
    "wof:placetype":"venue"
},
  "geometry": {"coordinates":[-122.405405,37.786324],"type":"Point"}
}