{
  "type": "Feature",
  "properties": {
    "iso:country":"US",
    "sg:address":"6559 Duke St",
    "sg:city":"Riverside",
    "sg:classifiers":[
        {
            "category":"Freight",
            "type":"Transportation"
        }
    ],
    "sg:phone":"+1 951 276 2857",
    "sg:postcode":"92506",
    "sg:province":"CA",
    "sg:tags":[
        "operator",
        "local",
        "trucking"
    ],
    "wof:name":"Jrs Trucking",
    "wof:placetype":"venue"
},
  "geometry": {"coordinates":[-117.385552,33.944532],"type":"Point"}
}