{
  "type": "Feature",
  "properties": {
    "addr:full":"1937 20th Ave San Francisco CA 94116",
    "addr:housenumber":"1937",
    "addr:postcode":"94116",
    "addr:street":"20Th Ave",
    "iso:country":"US",
    "sg:address":"1937 20th Ave",
    "sg:city":"San Francisco",
    "sg:classifiers":[
        {
            "category":"Wholesale",
            "subcategory":"Machinery & Supplies",
            "type":"Manufacturing & Wholesale Goods"
        }
    ],
    "sg:phone":"+1 415 681 9968",
    "sg:postcode":"94116",
    "sg:province":"CA",
    "sg:tags":[
        "sewing"
    ],
    "wof:name":"Bridgeway Trading Company",
    "wof:placetype":"venue"
},
  "geometry": {"coordinates":[-122.477396,37.751144],"type":"Point"}
}