{
  "type": "Feature",
  "properties": {
    "addr:full":"16372 Construction Cir E Irvine CA 92606",
    "addr:housenumber":"16372",
    "addr:postcode":"92606",
    "addr:street":"Construction Cir E",
    "iso:country":"US",
    "sg:address":"16372 Construction Cir E",
    "sg:city":"Irvine",
    "sg:classifiers":[
        {
            "category":"Retail",
            "subcategory":"Auto Repair",
            "type":"Services"
        }
    ],
    "sg:phone":"+1 949 559 1691",
    "sg:postcode":"92606",
    "sg:province":"CA",
    "wof:name":"Tanaka Auto",
    "wof:placetype":"venue"
},
  "geometry": {"coordinates":[-117.82199900000001,33.693901],"type":"Point"}
}