{
  "type": "Feature",
  "properties": {
    "iso:country":"US",
    "sg:address":"2555 Lafayette St",
    "sg:city":"Santa Clara",
    "sg:classifiers":[
        {
            "category":"Retail",
            "subcategory":"Auto Repair",
            "type":"Services"
        }
    ],
    "sg:phone":"+1 408 562 1000",
    "sg:postcode":"95050",
    "sg:province":"CA",
    "sg:tags":[
        "repairing",
        "automobile"
    ],
    "wof:name":"Apex Motorsports",
    "wof:placetype":"venue"
},
  "geometry": {"coordinates":[-121.95024100000001,37.367234],"type":"Point"}
}