{
  "type": "Feature",
  "properties": {
    "iso:country":"US",
    "sg:address":"660 Beaumont Ave",
    "sg:city":"Beaumont",
    "sg:classifiers":[
        {
            "category":"Home & Garden",
            "subcategory":"Building Materials",
            "type":"Retail Goods"
        }
    ],
    "sg:phone":"+1 951 845 5402",
    "sg:postcode":"92223",
    "sg:province":"CA",
    "sg:tags":[
        "plate",
        "glass-auto",
        "window",
        "glass"
    ],
    "wof:name":"Beaumont Glass Co",
    "wof:placetype":"venue"
},
  "geometry": {"coordinates":[-116.977159,33.930315],"type":"Point"}
}