{
  "type": "Feature",
  "properties": {
    "iso:country":"US",
    "sg:address":"12871 Abbott Ct",
    "sg:city":"Garden Grove",
    "sg:classifiers":[
        {
            "category":"Building & Trades",
            "subcategory":"Landscaping Services",
            "type":"Services"
        }
    ],
    "sg:phone":"+1 714 539 0413",
    "sg:postcode":"92841",
    "sg:province":"CA",
    "sg:tags":[
        "landscape"
    ],
    "wof:name":"Cliffs Landscaping Co",
    "wof:placetype":"venue"
},
  "geometry": {"coordinates":[-117.965735,33.774418],"type":"Point"}
}