{
  "type": "Feature",
  "properties": {
    "iso:country":"US",
    "sg:address":"1110 W Taft Ave",
    "sg:city":"Orange",
    "sg:classifiers":[
        {
            "category":"Organizations",
            "subcategory":"Religious Organization",
            "type":"Services"
        }
    ],
    "sg:phone":"+1 714 974 7031",
    "sg:postcode":"92865",
    "sg:province":"CA",
    "sg:tags":[
        "church"
    ],
    "wof:name":"Brand New Life Christian Ctr",
    "wof:placetype":"venue"
},
  "geometry": {"coordinates":[-117.86635099999999,33.815581],"type":"Point"}
}