{
  "type": "Feature",
  "properties": {
    "iso:country":"US",
    "sg:address":"1501 Polk St",
    "sg:city":"San Francisco",
    "sg:classifiers":[
        {
            "category":"Shopping",
            "subcategory":"Tobacco",
            "type":"Retail Goods"
        }
    ],
    "sg:phone":"+1 415 885 5479",
    "sg:postcode":"94109",
    "sg:province":"CA",
    "sg:tags":[
        "cigarette",
        "cigar",
        "dealer"
    ],
    "wof:name":"California Tobacco Ctr",
    "wof:placetype":"venue"
},
  "geometry": {"coordinates":[-122.420873,37.791495],"type":"Point"}
}