{
  "type": "Feature",
  "properties": {
    "addr:full":"9561 Oasis Ave Garden Grove CA 92844",
    "addr:housenumber":"9561",
    "addr:postcode":"92844",
    "addr:street":"Oasis Ave",
    "iso:country":"US",
    "sg:address":"9561 Oasis Ave",
    "sg:city":"Garden Grove",
    "sg:classifiers":[
        {
            "category":"Shopping",
            "subcategory":"Florist",
            "type":"Retail Goods"
        }
    ],
    "sg:phone":"+1 714 638 9534",
    "sg:postcode":"92844",
    "sg:province":"CA",
    "wof:name":"All Seasons Floral",
    "wof:placetype":"venue"
},
  "geometry": {"coordinates":[-117.962226,33.756384],"type":"Point"}
}