{
  "type": "Feature",
  "properties": {
    "iso:country":"US",
    "sg:address":"2892 Blazing Star Dr",
    "sg:city":"Thousand Oaks",
    "sg:classifiers":[
        {
            "category":"Professional",
            "type":"Services"
        }
    ],
    "sg:phone":"+1 805 241 5886",
    "sg:postcode":"91362",
    "sg:province":"CA",
    "wof:name":"Gtec Corp",
    "wof:placetype":"venue"
},
  "geometry": {"coordinates":[-118.820229,34.218634],"type":"Point"}
}