{
  "type": "Feature",
  "properties": {
    "iso:country":"US",
    "sg:address":"3114 W Beverly Blvd",
    "sg:city":"Montebello",
    "sg:classifiers":[
        {
            "category":"Banks & Credit Unions",
            "subcategory":"Bank",
            "type":"Services"
        }
    ],
    "sg:phone":"+1 323 887 8808",
    "sg:postcode":"90640",
    "sg:province":"CA",
    "sg:tags":[
        "escrow"
    ],
    "wof:name":"A & D Escrow Inc",
    "wof:placetype":"venue"
},
  "geometry": {"coordinates":[-118.135639,34.023359],"type":"Point"}
}