{
  "type": "Feature",
  "properties": {
    "iso:country":"US",
    "sg:address":"3307 Swetzer Rd",
    "sg:city":"Loomis",
    "sg:classifiers":[
        {
            "category":"Manufacturing",
            "subcategory":"Glass & Minerals",
            "type":"Manufacturing & Wholesale Goods"
        }
    ],
    "sg:phone":"+1 916 660 9388",
    "sg:postcode":"95650",
    "sg:province":"CA",
    "sg:tags":[
        "concrete",
        "brick",
        "prod",
        "block"
    ],
    "wof:name":"High Performance Coatings",
    "wof:placetype":"venue"
},
  "geometry": {"coordinates":[-121.19174599999999,38.834886],"type":"Point"}
}