{
  "type": "Feature",
  "properties": {
    "addr:full":"1161 Chess Drive Foster City CA 94404",
    "addr:housenumber":"1161",
    "addr:postcode":"94404",
    "addr:street":"Chess Drive",
    "iso:country":"US",
    "sg:address":"1161 Chess Drive",
    "sg:city":"Foster City",
    "sg:classifiers":[
        {
            "category":"Arts & Performance",
            "subcategory":"Arts Center",
            "type":"Entertainment"
        }
    ],
    "sg:phone":"+1 650 627 9164",
    "sg:postcode":"94404",
    "sg:province":"CA",
    "sg:tags":[
        "performing"
    ],
    "wof:name":"Bay Area Educational Theater Company",
    "wof:placetype":"venue"
},
  "geometry": {"coordinates":[-122.272305,37.566426],"type":"Point"}
}