{
  "type": "Feature",
  "properties": {
    "iso:country":"US",
    "sg:address":"6658 Alhambra Ave",
    "sg:city":"Martinez",
    "sg:classifiers":[
        {
            "category":"Personal",
            "subcategory":"Beauty Salon",
            "type":"Services"
        }
    ],
    "sg:phone":"+1 925 934 4179",
    "sg:postcode":"94553",
    "sg:province":"CA",
    "wof:name":"Perfect Haircuts",
    "wof:placetype":"venue"
},
  "geometry": {"coordinates":[-122.093841,37.959443],"type":"Point"}
}