{
  "type": "Feature",
  "properties": {
    "addr:full":"17440 Burbank Blvd Encino CA 91316",
    "addr:housenumber":"17440",
    "addr:postcode":"91316",
    "addr:street":"Burbank Blvd",
    "iso:country":"US",
    "sg:address":"17440 Burbank Blvd",
    "sg:city":"Encino",
    "sg:classifiers":[
        {
            "category":"Banks & Credit Unions",
            "subcategory":"Investment Brokerage",
            "type":"Services"
        }
    ],
    "sg:phone":"+1 818 728 0657",
    "sg:postcode":"91316",
    "sg:province":"CA",
    "wof:name":"A M Investments",
    "wof:placetype":"venue"
},
  "geometry": {"coordinates":[-118.512563,34.172185],"type":"Point"}
}