{
  "type": "Feature",
  "properties": {
    "iso:country":"US",
    "sg:address":"510 S Velie Dr",
    "sg:city":"Visalia",
    "sg:classifiers":[
        {
            "category":"Professional",
            "subcategory":"Credit Reporting & Collection",
            "type":"Services"
        }
    ],
    "sg:phone":"+1 559 635 7270",
    "sg:postcode":"93292",
    "sg:province":"CA",
    "wof:name":"Star Credit Service & Collectn",
    "wof:placetype":"venue"
},
  "geometry": {"coordinates":[-119.25750600000001,36.325678],"type":"Point"}
}