{
  "type": "Feature",
  "properties": {
    "addr:full":"809 Westwood Ave Modesto CA 95350",
    "addr:housenumber":"809",
    "addr:postcode":"ca 95350",
    "addr:street":"Westwood Ave",
    "iso:country":"US",
    "sg:address":"809 Westwood Ave",
    "sg:city":"Modesto",
    "sg:classifiers":[
        {
            "category":"Real Estate",
            "subcategory":"Real Estate Agent",
            "type":"Services"
        }
    ],
    "sg:phone":"+1 209 522 2224",
    "sg:postcode":"95350",
    "sg:province":"CA",
    "sg:tags":[
        "appraiser"
    ],
    "wof:name":"Selover Real Estate Appraiser",
    "wof:placetype":"venue"
},
  "geometry": {"coordinates":[-120.983808,37.670036],"type":"Point"}
}