{
  "type": "Feature",
  "properties": {
    "addr:full":"1450 S Palm Canyon Dr Palm Springs CA 92264",
    "addr:housenumber":"1450",
    "addr:postcode":"92264",
    "addr:street":"S Palm Canyon Dr",
    "iso:country":"US",
    "sg:address":"1450 S Palm Canyon Dr",
    "sg:city":"Palm Springs",
    "sg:classifiers":[
        {
            "category":"Travel",
            "subcategory":"Hotels & Motels",
            "type":"Entertainment"
        }
    ],
    "sg:phone":"+1 760 320 7767",
    "sg:postcode":"92264",
    "sg:province":"CA",
    "wof:name":"Palm Canyon Inn",
    "wof:placetype":"venue"
},
  "geometry": {"coordinates":[-116.545998,33.804501],"type":"Point"}
}