{
  "type": "Feature",
  "properties": {
    "addr:full":"435 Assembly Way Santa Cruz CA 95062",
    "addr:housenumber":"435",
    "addr:postcode":"95062",
    "addr:street":"Assembly Way",
    "iso:country":"US",
    "sg:address":"435 Assembly Way",
    "sg:city":"Santa Cruz",
    "sg:classifiers":[
        {
            "category":"Freight",
            "type":"Transportation"
        }
    ],
    "sg:phone":"+1 831 464 1907",
    "sg:postcode":"95062",
    "sg:province":"CA",
    "sg:tags":[
        "mover"
    ],
    "wof:name":"Easy Transitions Of Santa Cruz",
    "wof:placetype":"venue"
},
  "geometry": {"coordinates":[-121.998701,36.967283],"type":"Point"}
}