{
  "type": "Feature",
  "properties": {
    "iso:country":"US",
    "sg:address":"3643 Village Rd",
    "sg:city":"Concord",
    "sg:classifiers":[
        {
            "category":"Professional",
            "subcategory":"Printing & Photocopies",
            "type":"Services"
        },
        {
            "category":"Manufacturing",
            "subcategory":"Apparel",
            "type":"Manufacturing & Wholesale Goods"
        }
    ],
    "sg:phone":"+1 925 676 8566",
    "sg:postcode":"94519",
    "sg:province":"CA",
    "sg:tags":[
        "accessories-wholesale",
        "flag",
        "flags",
        "pennant",
        "flagpole",
        "banners",
        "manufacturer"
    ],
    "wof:name":"A N C Flag & Pole",
    "wof:placetype":"venue"
},
  "geometry": {"coordinates":[-122.00495100000001,37.984169],"type":"Point"}
}