{
  "type": "Feature",
  "properties": {
    "iso:country":"US",
    "sg:address":"1575 Heather Dr",
    "sg:city":"Yuba City",
    "sg:classifiers":[
        {
            "category":"Real Estate",
            "subcategory":"Real Estate Operator",
            "type":"Services"
        }
    ],
    "sg:phone":"+1 530 673 9264",
    "sg:postcode":"95993",
    "sg:province":"CA",
    "sg:tags":[
        "apartment"
    ],
    "wof:name":"Garden West One Apartments",
    "wof:placetype":"venue"
},
  "geometry": {"coordinates":[-121.64288,39.149758],"type":"Point"}
}