{
  "type": "Feature",
  "properties": {
    "iso:country":"US",
    "sg:address":"5700 Wilshire Boulevard Suite 555",
    "sg:city":"Los Angeles",
    "sg:classifiers":[
        {
            "category":"Communications",
            "subcategory":"Newspaper",
            "type":"Services"
        }
    ],
    "sg:phone":"+1 323 930 3300",
    "sg:postcode":"90036",
    "sg:province":"CA",
    "sg:tags":[
        "magazine"
    ],
    "wof:name":"US Magazine",
    "wof:placetype":"venue"
},
  "geometry": {"coordinates":[-118.352485,34.062385],"type":"Point"}
}