{
  "type": "Feature",
  "properties": {
    "addr:full":"4319 E Slauson Ave Maywood CA 90270",
    "addr:housenumber":"4319",
    "addr:postcode":"90270",
    "addr:street":"E Slauson Ave",
    "iso:country":"US",
    "sg:address":"4319 E Slauson Ave",
    "sg:city":"Maywood",
    "sg:classifiers":[
        {
            "category":"Government",
            "subcategory":"Office",
            "type":"Public Place"
        }
    ],
    "sg:phone":"+1 323 562 5000",
    "sg:postcode":"90270",
    "sg:province":"CA",
    "sg:tags":[
        "city"
    ],
    "wof:name":"Maywood Inc City of",
    "wof:placetype":"venue"
},
  "geometry": {"coordinates":[-118.189555,33.98763],"type":"Point"}
}