{
  "type": "Feature",
  "properties": {
    "addr:full":"2062 Ave Feliciano Rancho Pls Vrds CA 90275",
    "addr:housenumber":"2062",
    "addr:postcode":"90275",
    "addr:street":"Ave Feliciano",
    "iso:country":"US",
    "sg:address":"2062 Ave Feliciano",
    "sg:city":"Rancho Pls Vrds",
    "sg:classifiers":[
        {
            "category":"Building & Trades",
            "subcategory":"Construction",
            "type":"Services"
        }
    ],
    "sg:phone":"+1 310 548 1138",
    "sg:postcode":"90275",
    "sg:province":"CA",
    "sg:tags":[
        "concrete",
        "pumping"
    ],
    "wof:name":"Carl's Concrete Pump Svc",
    "wof:placetype":"venue"
},
  "geometry": {"coordinates":[-118.31706200000001,33.770105],"type":"Point"}
}