{
  "type": "Feature",
  "properties": {
    "iso:country":"US",
    "sg:address":"6654 Koll Center Pkwy",
    "sg:city":"Pleasanton",
    "sg:classifiers":[
        {
            "category":"Professional",
            "subcategory":"Advertising",
            "type":"Services"
        }
    ],
    "sg:phone":"+1 925 600 1140",
    "sg:postcode":"94566",
    "sg:province":"CA",
    "sg:tags":[
        "mailing",
        "shipping"
    ],
    "wof:name":"Amin Mail CTR",
    "wof:placetype":"venue"
},
  "geometry": {"coordinates":[-121.898709,37.659287],"type":"Point"}
}