{
  "type": "Feature",
  "properties": {
    "addr:full":"737 Palomar Ave El Cajon CA 92020",
    "addr:housenumber":"737",
    "addr:postcode":"92020",
    "addr:street":"Palomar Ave",
    "iso:country":"US",
    "sg:address":"737 Palomar Ave",
    "sg:city":"El Cajon",
    "sg:classifiers":[
        {
            "category":"Building & Trades",
            "subcategory":"Cleaning & Sanitation",
            "type":"Services"
        }
    ],
    "sg:phone":"+1 619 588 1631",
    "sg:postcode":"92020",
    "sg:province":"CA",
    "sg:tags":[
        "house"
    ],
    "wof:name":"Home-Aide Cleaning Svc",
    "wof:placetype":"venue"
},
  "geometry": {"coordinates":[-116.971531,32.778382],"type":"Point"}
}