{
  "type": "Feature",
  "properties": {
    "iso:country":"US",
    "sg:address":"654 S Detroit St",
    "sg:city":"Los Angeles",
    "sg:classifiers":[
        {
            "category":"Professional",
            "type":"Services"
        }
    ],
    "sg:phone":"+1 323 933 4399",
    "sg:postcode":"90036",
    "sg:province":"CA",
    "wof:name":"Angry Cat",
    "wof:placetype":"venue"
},
  "geometry": {"coordinates":[-118.345027,34.063829],"type":"Point"}
}