{
  "type": "Feature",
  "properties": {
    "addr:full":"3780 Wilshire Blvd Los Angeles CA 90010",
    "addr:housenumber":"3780",
    "addr:postcode":"90010",
    "addr:street":"Wilshire Blvd",
    "iso:country":"US",
    "sg:address":"3780 Wilshire Blvd",
    "sg:city":"Los Angeles",
    "sg:classifiers":[
        {
            "category":"Wholesale",
            "subcategory":"Electrical",
            "type":"Manufacturing & Wholesale Goods"
        }
    ],
    "sg:phone":"+1 213 251 9769",
    "sg:postcode":"90010",
    "sg:province":"CA",
    "sg:tags":[
        "recording",
        "studio"
    ],
    "sg:website":"www.tecton-engineering.com",
    "wof:name":"Tec Ton",
    "wof:placetype":"venue"
},
  "geometry": {"coordinates":[-118.308438,34.061622],"type":"Point"}
}