{
  "type": "Feature",
  "properties": {
    "addr:full":"1145 Estates Dr Lafayette CA 94549",
    "addr:housenumber":"1145",
    "addr:postcode":"94549",
    "addr:street":"Estates Dr",
    "iso:country":"US",
    "sg:address":"1145 Estates Dr",
    "sg:city":"Lafayette",
    "sg:classifiers":[
        {
            "category":"Travel",
            "subcategory":"Travel Agent",
            "type":"Entertainment"
        }
    ],
    "sg:phone":"+1 925 284 7007",
    "sg:postcode":"94549",
    "sg:province":"CA",
    "sg:tags":[
        "agency"
    ],
    "wof:name":"Trueurope Travel Inc",
    "wof:placetype":"venue"
},
  "geometry": {"coordinates":[-122.157842,37.897114],"type":"Point"}
}