{
  "type": "Feature",
  "properties": {
    "iso:country":"US",
    "sg:address":"1541 Bulldog Ln",
    "sg:city":"Fresno",
    "sg:classifiers":[
        {
            "category":"Real Estate",
            "subcategory":"Real Estate Operator",
            "type":"Services"
        }
    ],
    "sg:phone":"+1 559 226 7383",
    "sg:postcode":"93710",
    "sg:province":"CA",
    "sg:tags":[
        "apartment"
    ],
    "wof:name":"Campus Court Yard",
    "wof:placetype":"venue"
},
  "geometry": {"coordinates":[-119.75951000000001,36.812154],"type":"Point"}
}