{
  "type": "Feature",
  "properties": {
    "addr:full":"2131 Walnut St Sutter CA 95982",
    "addr:housenumber":"2131",
    "addr:postcode":"ca 95982",
    "addr:street":"Walnut St",
    "iso:country":"US",
    "sg:address":"2131 Walnut St",
    "sg:city":"Sutter",
    "sg:classifiers":[
        {
            "category":"Farming",
            "subcategory":"Crops",
            "type":"Manufacturing & Wholesale Goods"
        }
    ],
    "sg:phone":"+1 530 755 0323",
    "sg:postcode":"95982",
    "sg:province":"CA",
    "sg:tags":[
        "grove",
        "farm",
        "nut",
        "rice",
        "tree"
    ],
    "wof:name":"Dewitt Farms",
    "wof:placetype":"venue"
},
  "geometry": {"coordinates":[-121.75492800000001,39.159455],"type":"Point"}
}