{
  "type": "Feature",
  "properties": {
    "addr:full":"1603 Garnet Ave San Diego CA 92109",
    "addr:housenumber":"1603",
    "addr:postcode":"92109",
    "addr:street":"Garnet Ave",
    "iso:country":"US",
    "sg:address":"1603 Garnet Ave",
    "sg:city":"San Diego",
    "sg:classifiers":[
        {
            "category":"Shopping",
            "type":"Retail Goods"
        }
    ],
    "sg:phone":"+1 858 274 3631",
    "sg:postcode":"92109",
    "sg:province":"CA",
    "sg:tags":[
        "telephone",
        "cellular"
    ],
    "wof:name":"Radio Shack",
    "wof:placetype":"venue"
},
  "geometry": {"coordinates":[-117.239002,32.80012],"type":"Point"}
}