{
  "type": "Feature",
  "properties": {
    "iso:country":"US",
    "sg:address":"766 Moorpark St",
    "sg:city":"Oakland",
    "sg:classifiers":[
        {
            "category":"Wholesale",
            "subcategory":"Machinery & Supplies",
            "type":"Manufacturing & Wholesale Goods"
        }
    ],
    "sg:phone":"+1 510 639 7788",
    "sg:postcode":"94603",
    "sg:province":"CA",
    "sg:tags":[
        "industrial"
    ],
    "wof:name":"Venegas Custom Cabinets",
    "wof:placetype":"venue"
},
  "geometry": {"coordinates":[-122.17409600000001,37.73177],"type":"Point"}
}