{
  "type": "Feature",
  "properties": {
    "iso:country":"US",
    "sg:address":"1524 2nd St",
    "sg:city":"Santa Monica",
    "sg:classifiers":[
        {
            "category":"Professional",
            "type":"Services"
        }
    ],
    "sg:phone":"+1 310 395 9298",
    "sg:postcode":"90401",
    "sg:province":"CA",
    "wof:name":"Wimbo",
    "wof:placetype":"venue"
},
  "geometry": {"coordinates":[-118.494281,34.01252],"type":"Point"}
}