{
  "type": "Feature",
  "properties": {
    "addr:full":"17 Olvera St Los Angeles CA 90012",
    "addr:housenumber":"17",
    "addr:postcode":"90012",
    "addr:street":"Olvera St",
    "iso:country":"US",
    "sg:address":"17 Olvera St",
    "sg:city":"Los Angeles",
    "sg:classifiers":[
        {
            "category":"Restaurant",
            "type":"Food & Drink"
        }
    ],
    "sg:phone":"+1 213 628 4349",
    "sg:postcode":"90012",
    "sg:province":"CA",
    "sg:tags":[
        "mexican"
    ],
    "wof:name":"Casa La Golondrina Mexican Cafe",
    "wof:placetype":"venue"
},
  "geometry": {"coordinates":[-118.237999,34.0578],"type":"Point"}
}