{
  "type": "Feature",
  "properties": {
    "addr:full":"153 Bayhurst Dr Vallejo CA 94591",
    "addr:housenumber":"153",
    "addr:postcode":"94591",
    "addr:street":"Bayhurst Dr",
    "iso:country":"US",
    "sg:address":"153 Bayhurst Dr",
    "sg:city":"Vallejo",
    "sg:classifiers":[
        {
            "category":"Real Estate",
            "subcategory":"Real Estate Agent",
            "type":"Services"
        }
    ],
    "sg:phone":"+1 707 645 1048",
    "sg:postcode":"94591",
    "sg:province":"CA",
    "sg:tags":[
        "inspection"
    ],
    "wof:name":"Star Quality Home Inspection",
    "wof:placetype":"venue"
},
  "geometry": {"coordinates":[-122.223545,38.07221],"type":"Point"}
}