{
  "type": "Feature",
  "properties": {
    "addr:full":"464 S Cataract Ave San Dimas CA 91773",
    "addr:housenumber":"464",
    "addr:postcode":"91773",
    "addr:street":"S Cataract Ave",
    "iso:country":"US",
    "sg:address":"464 S Cataract Ave",
    "sg:city":"San Dimas",
    "sg:classifiers":[
        {
            "category":"Retail",
            "subcategory":"Auto Repair",
            "type":"Services"
        }
    ],
    "sg:phone":"+1 909 592 1006",
    "sg:postcode":"91773",
    "sg:province":"CA",
    "sg:tags":[
        "transmission"
    ],
    "wof:name":"Remac Transmission Inc",
    "wof:placetype":"venue"
},
  "geometry": {"coordinates":[-117.811391,34.102016],"type":"Point"}
}