{
  "type": "Feature",
  "properties": {
    "iso:country":"US",
    "sg:address":"555 Canyon del Rey Blvd",
    "sg:city":"Monterey",
    "sg:classifiers":[
        {
            "category":"Organizations",
            "subcategory":"Community Association",
            "type":"Services"
        }
    ],
    "sg:phone":"+1 408 394 6896",
    "sg:postcode":"93940",
    "sg:province":"CA",
    "wof:name":"Moose Fmly Ctr 876 - Monterey",
    "wof:placetype":"venue"
},
  "geometry": {"coordinates":[-121.831186,36.587416],"type":"Point"}
}