{
  "type": "Feature",
  "properties": {
    "iso:country":"US",
    "sg:address":"3700 W Florida Ave",
    "sg:city":"Hemet",
    "sg:classifiers":[
        {
            "category":"Travel",
            "subcategory":"Hotels & Motels",
            "type":"Entertainment"
        }
    ],
    "sg:phone":"+1 951 929 7373",
    "sg:postcode":"92545",
    "sg:province":"CA",
    "sg:tags":[
        "lodging"
    ],
    "sg:website":"http://www.hemetsuites.hamptoninn.com",
    "wof:name":"Hampton Inn and Suites",
    "wof:placetype":"venue"
},
  "geometry": {"coordinates":[-117.011376,33.746655],"type":"Point"}
}