{
  "type": "Feature",
  "properties": {
    "addr:full":"2390 Crenshaw Blvd Torrance CA 90501",
    "addr:housenumber":"2390",
    "addr:postcode":"90501",
    "addr:street":"Crenshaw Blvd",
    "iso:country":"US",
    "sg:address":"2390 Crenshaw Blvd",
    "sg:city":"Torrance",
    "sg:classifiers":[
        {
            "category":"Personal",
            "type":"Services"
        }
    ],
    "sg:phone":"+1 310 257 1378",
    "sg:postcode":"90501",
    "sg:province":"CA",
    "sg:tags":[
        "bankruptcy"
    ],
    "wof:name":"Precision Support Group",
    "wof:placetype":"venue"
},
  "geometry": {"coordinates":[-118.32831899999999,33.823258],"type":"Point"}
}