{
  "type": "Feature",
  "properties": {
    "addr:full":"9831 Shamrock Ave Fountain Valley CA 92708",
    "addr:housenumber":"9831",
    "addr:postcode":"92708",
    "addr:street":"Shamrock Ave",
    "iso:country":"US",
    "sg:address":"9831 Shamrock Ave",
    "sg:city":"Fountain Valley",
    "sg:classifiers":[
        {
            "category":"Building & Trades",
            "subcategory":"Plumbing",
            "type":"Services"
        }
    ],
    "sg:phone":"+1 714 839 3528",
    "sg:postcode":"92708",
    "sg:province":"CA",
    "sg:tags":[
        "contractor"
    ],
    "wof:name":"Lee Mechanical",
    "wof:placetype":"venue"
},
  "geometry": {"coordinates":[-117.95790100000001,33.730004],"type":"Point"}
}