{
  "type": "Feature",
  "properties": {
    "addr:full":"2730 Santiago St San Francisco CA 94116",
    "addr:housenumber":"2730",
    "addr:postcode":"94116",
    "addr:street":"Santiago St",
    "iso:country":"US",
    "sg:address":"2730 Santiago St",
    "sg:city":"San Francisco",
    "sg:classifiers":[
        {
            "category":"Travel",
            "subcategory":"Travel Agent",
            "type":"Entertainment"
        }
    ],
    "sg:phone":"+1 415 664 8908",
    "sg:postcode":"94116",
    "sg:province":"CA",
    "sg:tags":[
        "agency",
        "bureau"
    ],
    "wof:name":"Sts Tours",
    "wof:placetype":"venue"
},
  "geometry": {"coordinates":[-122.496994,37.744063],"type":"Point"}
}