{
  "type": "Feature",
  "properties": {
    "addr:full":"586 S Warm Sands Dr Palm Springs CA 92264",
    "addr:housenumber":"586",
    "addr:postcode":"92264",
    "addr:street":"S Warm Sands Dr",
    "iso:country":"US",
    "sg:address":"586 S Warm Sands Dr",
    "sg:city":"Palm Springs",
    "sg:classifiers":[
        {
            "category":"Travel",
            "subcategory":"Hotels & Motels",
            "type":"Entertainment"
        }
    ],
    "sg:phone":"+1 760 327 8111",
    "sg:postcode":"92264",
    "sg:province":"CA",
    "wof:name":"Hacienda En Sueno",
    "wof:placetype":"venue"
},
  "geometry": {"coordinates":[-116.53612200000001,33.814543],"type":"Point"}
}