{
  "type": "Feature",
  "properties": {
    "addr:full":"639 S Hill Street Los Angeles CA 90014",
    "addr:housenumber":"639",
    "addr:postcode":"90014",
    "addr:street":"S Hill Street",
    "iso:country":"US",
    "sg:address":"639 S Hill Street",
    "sg:city":"Los Angeles",
    "sg:classifiers":[
        {
            "category":"Shopping",
            "subcategory":"Jewelry",
            "type":"Retail Goods"
        }
    ],
    "sg:phone":"+1 213 614 8000",
    "sg:postcode":"90014",
    "sg:province":"CA",
    "wof:name":"Jewels by Mike",
    "wof:placetype":"venue"
},
  "geometry": {"coordinates":[-118.253612,34.046839],"type":"Point"}
}