{
  "type": "Feature",
  "properties": {
    "addr:full":"11156 Balboa Blvd Granada Hills CA 91344",
    "addr:housenumber":"11156",
    "addr:postcode":"91344",
    "addr:street":"Balboa Blvd",
    "iso:country":"US",
    "sg:address":"11156 Balboa Blvd",
    "sg:city":"Granada Hills",
    "sg:classifiers":[
        {
            "category":"Retail",
            "subcategory":"Animal Services",
            "type":"Services"
        }
    ],
    "sg:phone":"+1 818 366 9069",
    "sg:postcode":"91344",
    "sg:province":"CA",
    "wof:name":"Puppy Palace",
    "wof:placetype":"venue"
},
  "geometry": {"coordinates":[-118.502116,34.272846],"type":"Point"}
}