{
  "type": "Feature",
  "properties": {
    "iso:country":"US",
    "sg:address":"371 Grand Ave.",
    "sg:city":"South San Francisco",
    "sg:classifiers":[
        {
            "category":"Shopping",
            "subcategory":"Party Supplies",
            "type":"Retail Goods"
        },
        {
            "category":"Shopping",
            "subcategory":"Bridal",
            "type":"Retail Goods"
        }
    ],
    "sg:phone":"+1 650 875 9345",
    "sg:postcode":"94080",
    "sg:province":"CA",
    "wof:name":"Tina's Bridal & Creations",
    "wof:placetype":"venue"
},
  "geometry": {"coordinates":[-122.41185299999999,37.655533],"type":"Point"}
}