{
  "type": "Feature",
  "properties": {
    "iso:country":"US",
    "sg:address":"11111 Santa Monica Boulevard",
    "sg:city":"Los Angeles",
    "sg:classifiers":[
        {
            "category":"Banks & Credit Unions",
            "subcategory":"Investment Brokerage",
            "type":"Services"
        }
    ],
    "sg:phone":"+1 310 689 0800",
    "sg:postcode":"90025",
    "sg:province":"CA",
    "sg:tags":[
        "investing"
    ],
    "wof:name":"Evercore Partners",
    "wof:placetype":"venue"
},
  "geometry": {"coordinates":[-118.44448199999999,34.047698],"type":"Point"}
}