{
  "type": "Feature",
  "properties": {
    "addr:full":"5670 Wilshire Blvd Ste 1590 Los Angeles CA 90036",
    "addr:housenumber":"5670",
    "addr:postcode":"90036",
    "addr:street":"Wilshire Blvd Ste 1590",
    "iso:country":"US",
    "sg:address":"5670 Wilshire Blvd Ste 1590",
    "sg:city":"Los Angeles",
    "sg:classifiers":[
        {
            "category":"Personal",
            "type":"Services"
        }
    ],
    "sg:phone":"+1 323 904 4400",
    "sg:postcode":"90036",
    "sg:province":"CA",
    "sg:tags":[
        "party",
        "planning",
        "event"
    ],
    "wof:name":"Grant Associates",
    "wof:placetype":"venue"
},
  "geometry": {"coordinates":[-118.35217,34.062197],"type":"Point"}
}