{
  "type": "Feature",
  "properties": {
    "addr:full":"4784 Whittier Boulevard Los Angeles CA 90022",
    "addr:housenumber":"4784",
    "addr:postcode":"90022",
    "addr:street":"Whittier Boulevard",
    "iso:country":"US",
    "sg:address":"4784 Whittier Boulevard",
    "sg:city":"Los Angeles",
    "sg:classifiers":[
        {
            "category":"Shopping",
            "subcategory":"Mobile Phones",
            "type":"Retail Goods"
        }
    ],
    "sg:phone":"+1 323 268 5555",
    "sg:postcode":"90022",
    "sg:province":"CA",
    "wof:name":"M & M Cellular",
    "wof:placetype":"venue"
},
  "geometry": {"coordinates":[-118.16466200000001,34.021865],"type":"Point"}
}