{
  "type": "Feature",
  "properties": {
    "iso:country":"US",
    "sg:address":"14236 Monte Verde Ave",
    "sg:city":"Apple Valley",
    "sg:classifiers":[
        {
            "category":"Building & Trades",
            "subcategory":"Landscaping Services",
            "type":"Services"
        }
    ],
    "sg:phone":"+1 760 242 8180",
    "sg:postcode":"92307",
    "sg:province":"CA",
    "wof:name":"Garys Gardening",
    "wof:placetype":"venue"
},
  "geometry": {"coordinates":[-117.240673,34.509941],"type":"Point"}
}