{
  "type": "Feature",
  "properties": {
    "iso:country":"US",
    "sg:address":"2141 Rosecrans Avenue",
    "sg:city":"El Segundo",
    "sg:classifiers":[
        {
            "category":"Shopping",
            "subcategory":"Music",
            "type":"Retail Goods"
        }
    ],
    "sg:phone":"+1 310 416 9898",
    "sg:postcode":"90245",
    "sg:province":"CA",
    "sg:tags":[
        "dvd's"
    ],
    "wof:name":"Integrated Data Services",
    "wof:placetype":"venue"
},
  "geometry": {"coordinates":[-118.387226,33.901974],"type":"Point"}
}