{
  "type": "Feature",
  "properties": {
    "addr:full":"PO Box 602 Berkeley CA 94701",
    "addr:housenumber":"po",
    "addr:postcode":"94701",
    "addr:street":"Box 602",
    "iso:country":"US",
    "sg:address":"PO Box 602",
    "sg:city":"Berkeley",
    "sg:classifiers":[
        {
            "category":"Sports & Exercise",
            "subcategory":"Gym",
            "type":"Entertainment"
        }
    ],
    "sg:phone":"+1 510 735 1372",
    "sg:postcode":"94701",
    "sg:province":"CA",
    "sg:tags":[
        "yoga"
    ],
    "sg:website":"www.lasaguashealingarts.com",
    "wof:name":"Las Aguas Healing Arts: Shoshanna Marks",
    "wof:placetype":"venue"
},
  "geometry": {"coordinates":[-122.2718,37.8718],"type":"Point"}
}