{
  "type": "Feature",
  "properties": {
    "iso:country":"US",
    "sg:address":"1215 Linda Vista Dr",
    "sg:city":"San Marcos",
    "sg:classifiers":[
        {
            "category":"Wholesale",
            "subcategory":"Machinery & Supplies",
            "type":"Manufacturing & Wholesale Goods"
        }
    ],
    "sg:phone":"+1 760 744 7422",
    "sg:postcode":"92078",
    "sg:province":"CA",
    "sg:tags":[
        "bearing"
    ],
    "wof:name":"Applied Industrial Tech Inc",
    "wof:placetype":"venue"
},
  "geometry": {"coordinates":[-117.18932599999999,33.138424],"type":"Point"}
}