{
  "type": "Feature",
  "properties": {
    "iso:country":"US",
    "sg:address":"3751 Prestwick Dr",
    "sg:city":"Los Angeles",
    "sg:classifiers":[
        {
            "category":"Professional",
            "type":"Services"
        }
    ],
    "sg:phone":"+1 323 913 2950",
    "sg:postcode":"90027",
    "sg:province":"CA",
    "wof:name":"Under Own Name",
    "wof:placetype":"venue"
},
  "geometry": {"coordinates":[-118.280202,34.118127],"type":"Point"}
}