{
  "type": "Feature",
  "properties": {
    "iso:country":"US",
    "sg:address":"7311 Greenhaven Dr",
    "sg:city":"Sacramento",
    "sg:classifiers":[
        {
            "category":"Manufacturing",
            "subcategory":"Printing",
            "type":"Manufacturing & Wholesale Goods"
        }
    ],
    "sg:phone":"+1 916 424 5870",
    "sg:postcode":"95831",
    "sg:province":"CA",
    "sg:tags":[
        "publisher",
        "software"
    ],
    "wof:name":"Neunet Solutions Inc",
    "wof:placetype":"venue"
},
  "geometry": {"coordinates":[-121.519295,38.491319],"type":"Point"}
}