{
  "type": "Feature",
  "properties": {
    "addr:full":"636 4th Street Second floor San Francisco CA 94107",
    "addr:housenumber":"636",
    "addr:postcode":"94107",
    "addr:street":"4Th Street Second Floor",
    "iso:country":"US",
    "sg:address":"636 4th Street Second floor",
    "sg:city":"San Francisco",
    "sg:classifiers":[
        {
            "category":"Banks & Credit Unions",
            "subcategory":"Financial Services",
            "type":"Services"
        }
    ],
    "sg:phone":"+1 415 694 5556",
    "sg:postcode":"94107",
    "sg:province":"CA",
    "sg:tags":[
        "broker",
        "mortgage"
    ],
    "sg:website":"www.serenagreening.com",
    "wof:name":"Guarantee Mortgage Corporation - Serena Greening",
    "wof:placetype":"venue"
},
  "geometry": {"coordinates":[-122.395872,37.777821],"type":"Point"}
}