{
  "type": "Feature",
  "properties": {
    "addr:full":"12520 Magnolia Blvd Ste 302 Valley Village CA 91607",
    "addr:housenumber":"12520",
    "addr:postcode":"91607",
    "addr:street":"Magnolia Blvd Ste 302",
    "iso:country":"US",
    "sg:address":"12520 Magnolia Blvd Ste 302",
    "sg:city":"Valley Village",
    "sg:classifiers":[
        {
            "category":"Health Services",
            "subcategory":"Doctor",
            "type":"Services"
        },
        {
            "category":"Health Services",
            "subcategory":"Clinic",
            "type":"Services"
        }
    ],
    "sg:phone":"+1 818 752 3330",
    "sg:postcode":"91607",
    "sg:province":"CA",
    "sg:tags":[
        "counseling",
        "mental"
    ],
    "wof:name":"Halote Barry A PHD",
    "wof:placetype":"venue"
},
  "geometry": {"coordinates":[-118.405998,34.164902],"type":"Point"}
}