{
  "type": "Feature",
  "properties": {
    "addr:full":"5301 Madison Ave Ste 204 Sacramento CA 95841",
    "addr:housenumber":"5301",
    "addr:postcode":"95841",
    "addr:street":"Madison Ave Ste 204",
    "iso:country":"US",
    "sg:address":"5301 Madison Ave Ste 204",
    "sg:city":"Sacramento",
    "sg:classifiers":[
        {
            "category":"Banks & Credit Unions",
            "subcategory":"Financial Services",
            "type":"Services"
        },
        {
            "category":"Professional",
            "subcategory":"Credit Reporting & Collection",
            "type":"Services"
        }
    ],
    "sg:phone":"+1 916 349 1508",
    "sg:postcode":"95841",
    "sg:province":"CA",
    "sg:tags":[
        "debt",
        "adjuster",
        "agency"
    ],
    "wof:name":"Alternative Resource Management",
    "wof:placetype":"venue"
},
  "geometry": {"coordinates":[-121.341301,38.660889],"type":"Point"}
}