{
  "type": "Feature",
  "properties": {
    "iso:country":"US",
    "sg:address":"1419 W Warner Ave",
    "sg:city":"Santa Ana",
    "sg:classifiers":[
        {
            "category":"Wholesale",
            "subcategory":"Fruits & Vegetables",
            "type":"Manufacturing & Wholesale Goods"
        }
    ],
    "sg:phone":"+1 714 751 4808",
    "sg:postcode":"92704",
    "sg:province":"CA",
    "sg:tags":[
        "veggie"
    ],
    "wof:name":"Jugos Mazatlan Produce Market",
    "wof:placetype":"venue"
},
  "geometry": {"coordinates":[-117.887001,33.716202],"type":"Point"}
}