{
  "type": "Feature",
  "properties": {
    "iso:country":"US",
    "sg:address":"61 E Arrow Hwy",
    "sg:city":"Upland",
    "sg:classifiers":[
        {
            "category":"Food & Beverages",
            "subcategory":"Liquor & Beverages",
            "type":"Retail Goods"
        }
    ],
    "sg:phone":"+1 909 985 1546",
    "sg:postcode":"91786",
    "sg:province":"CA",
    "wof:name":"Arrow Liquor Inc",
    "wof:placetype":"venue"
},
  "geometry": {"coordinates":[-117.650469,34.099816],"type":"Point"}
}