{
  "type": "Feature",
  "properties": {
    "addr:full":"20130 State Rd Cerritos CA 90703",
    "addr:housenumber":"20130",
    "addr:postcode":"ca 90703",
    "addr:street":"State Rd",
    "iso:country":"US",
    "sg:address":"20130 State Rd",
    "sg:city":"Cerritos",
    "sg:classifiers":[
        {
            "category":"Professional",
            "type":"Services"
        }
    ],
    "sg:phone":"+1 562 865 5251",
    "sg:postcode":"90703",
    "sg:province":"CA",
    "sg:tags":[
        "establishment"
    ],
    "wof:name":"Hess Microgen LLC",
    "wof:placetype":"venue"
},
  "geometry": {"coordinates":[-118.094917,33.847043],"type":"Point"}
}