{
  "type": "Feature",
  "properties": {
    "iso:country":"US",
    "sg:address":"3100 E Imperial Hwy",
    "sg:city":"Lynwood",
    "sg:classifiers":[
        {
            "category":"Shopping",
            "subcategory":"Beauty & Cosmetics",
            "type":"Retail Goods"
        }
    ],
    "sg:phone":"+1 310 638 6890",
    "sg:postcode":"90262",
    "sg:province":"CA",
    "sg:tags":[
        "perfume"
    ],
    "wof:name":"Perfumeria- Accesorios Y Cosmeticos Elisa",
    "wof:placetype":"venue"
},
  "geometry": {"coordinates":[-118.216293,33.93045],"type":"Point"}
}