{
  "type": "Feature",
  "properties": {
    "addr:full":"2835 Jim Valley Rd Placerville CA 95667",
    "addr:housenumber":"2835",
    "addr:postcode":"95667",
    "addr:street":"Jim Valley Rd",
    "iso:country":"US",
    "sg:address":"2835 Jim Valley Rd",
    "sg:city":"Placerville",
    "sg:classifiers":[
        {
            "category":"Building & Trades",
            "subcategory":"Construction",
            "type":"Services"
        }
    ],
    "sg:phone":"+1 530 622 4509",
    "sg:postcode":"95667",
    "sg:province":"CA",
    "sg:tags":[
        "dry wall",
        "contractor"
    ],
    "wof:name":"El Dorado Drywall",
    "wof:placetype":"venue"
},
  "geometry": {"coordinates":[-120.718024,38.708708],"type":"Point"}
}