{
  "type": "Feature",
  "properties": {
    "addr:full":"472 N Arrowhead Ave San Bernardino CA 92401",
    "addr:housenumber":"472",
    "addr:postcode":"92401",
    "addr:street":"N Arrowhead Ave",
    "iso:country":"US",
    "sg:address":"472 N Arrowhead Ave",
    "sg:city":"San Bernardino",
    "sg:classifiers":[
        {
            "category":"Real Estate",
            "subcategory":"Real Estate Agent",
            "type":"Services"
        }
    ],
    "sg:phone":"+1 909 888 7177",
    "sg:postcode":"92401",
    "sg:province":"CA",
    "wof:name":"Teel & Teel & Assoc",
    "wof:placetype":"venue"
},
  "geometry": {"coordinates":[-117.289749,34.106939],"type":"Point"}
}