{
  "type": "Feature",
  "properties": {
    "iso:country":"US",
    "sg:address":"900 N Alameda St Ste 200",
    "sg:city":"Los Angeles",
    "sg:classifiers":[
        {
            "category":"Professional",
            "type":"Services"
        }
    ],
    "sg:phone":"+1 866 777 2673",
    "sg:postcode":"90012",
    "sg:province":"CA",
    "sg:website":"coresite.com/Los-Angeles-data-ce...",
    "wof:name":"CoreSite",
    "wof:placetype":"venue"
},
  "geometry": {"coordinates":[-118.235299,34.058723],"type":"Point"}
}