{
  "type": "Feature",
  "properties": {
    "iso:country":"US",
    "sg:address":"681 Broadway",
    "sg:city":"Sonoma",
    "sg:classifiers":[
        {
            "category":"Travel",
            "subcategory":"Hotels & Motels",
            "type":"Entertainment"
        }
    ],
    "sg:phone":"+1 707 996 1031",
    "sg:postcode":"95476",
    "sg:province":"CA",
    "sg:tags":[
        "breakfast",
        "accommodation",
        "bed"
    ],
    "wof:name":"Magliulo's Rose Garden Inn",
    "wof:placetype":"venue"
},
  "geometry": {"coordinates":[-122.45843499999999,38.288598],"type":"Point"}
}