{
  "type": "Feature",
  "properties": {
    "addr:full":"637 Merchant St Vacaville CA 95688",
    "addr:housenumber":"637",
    "addr:postcode":"95688",
    "addr:street":"Merchant St",
    "iso:country":"US",
    "sg:address":"637 Merchant St",
    "sg:city":"Vacaville",
    "sg:classifiers":[
        {
            "category":"Professional",
            "type":"Services"
        }
    ],
    "sg:phone":"+1 707 455 0224",
    "sg:postcode":"95688",
    "sg:province":"CA",
    "wof:name":"Attic Gallery",
    "wof:placetype":"venue"
},
  "geometry": {"coordinates":[-121.99320899999999,38.351805],"type":"Point"}
}