{
  "type": "Feature",
  "properties": {
    "addr:full":"13435 Telegraph Rd Whittier CA 90605",
    "addr:housenumber":"13435",
    "addr:postcode":"90605",
    "addr:street":"Telegraph Rd",
    "iso:country":"US",
    "sg:address":"13435 Telegraph Rd",
    "sg:city":"Whittier",
    "sg:classifiers":[
        {
            "category":"Retail",
            "subcategory":"Photofinishing",
            "type":"Services"
        }
    ],
    "sg:phone":"+1 562 903 1951",
    "sg:postcode":"90605",
    "sg:province":"CA",
    "sg:tags":[
        "photo",
        "photography",
        "finishing",
        "store"
    ],
    "wof:name":"Express One Hr Photo",
    "wof:placetype":"venue"
},
  "geometry": {"coordinates":[-118.04499800000001,33.9398],"type":"Point"}
}