{
  "type": "Feature",
  "properties": {
    "iso:country":"US",
    "sg:address":"1019 Mission St",
    "sg:city":"South Pasadena",
    "sg:classifiers":[
        {
            "category":"Restaurant",
            "type":"Food & Drink"
        },
        {
            "category":"Bakery",
            "type":"Food & Drink"
        }
    ],
    "sg:phone":"+1 626 441 4786",
    "sg:postcode":"91030",
    "sg:province":"CA",
    "sg:website":"www.greatharvestsouthpasadena.com",
    "wof:name":"Great Harvest Bread Co",
    "wof:placetype":"venue"
},
  "geometry": {"coordinates":[-118.156402,34.115731],"type":"Point"}
}