{
  "type": "Feature",
  "properties": {
    "addr:full":"2900 Broadway Oakland CA 94611",
    "addr:housenumber":"2900",
    "addr:postcode":"94611",
    "addr:street":"Broadway",
    "iso:country":"US",
    "sg:address":"2900 Broadway",
    "sg:city":"Oakland",
    "sg:classifiers":[
        {
            "category":"Food & Beverages",
            "subcategory":"Liquor & Beverages",
            "type":"Retail Goods"
        },
        {
            "category":"Food & Beverages",
            "subcategory":"Supermarket",
            "type":"Retail Goods"
        },
        {
            "category":"Food & Beverages",
            "subcategory":"Groceries & Convenience Stores",
            "type":"Retail Goods"
        }
    ],
    "sg:phone":"+1 510 465 5649",
    "sg:postcode":"94611",
    "sg:province":"CA",
    "sg:tags":[
        "beer",
        "super",
        "spirit",
        "wine"
    ],
    "sg:website":"www.groceryoutlets.com",
    "wof:name":"Grocery Outlet",
    "wof:placetype":"venue"
},
  "geometry": {"coordinates":[-122.26300000000001,37.817799],"type":"Point"}
}