{
  "type": "Feature",
  "properties": {
    "iso:country":"US",
    "sg:address":"14351 Hindry Ave",
    "sg:city":"Hawthorne",
    "sg:classifiers":[
        {
            "category":"Shopping",
            "subcategory":"Discount & Variety Stores",
            "type":"Retail Goods"
        }
    ],
    "sg:phone":"+1 310 643 9806",
    "sg:postcode":"90250",
    "sg:province":"CA",
    "sg:tags":[
        "outlet"
    ],
    "wof:name":"Bed Bath & Beyond",
    "wof:placetype":"venue"
},
  "geometry": {"coordinates":[-118.37200199999999,33.901798],"type":"Point"}
}