{
  "type": "Feature",
  "properties": {
    "iso:country":"US",
    "sg:address":"4791 Titan St",
    "sg:city":"Santa Maria",
    "sg:classifiers":[
        {
            "category":"Professional",
            "subcategory":"Accounting & Tax Preparation",
            "type":"Services"
        }
    ],
    "sg:phone":"+1 805 937 2266",
    "sg:postcode":"93455",
    "sg:province":"CA",
    "sg:tags":[
        "consultant"
    ],
    "wof:name":"Arc Financial & Tax Svc",
    "wof:placetype":"venue"
},
  "geometry": {"coordinates":[-120.408338,34.867422],"type":"Point"}
}