{
  "type": "Feature",
  "properties": {
    "addr:full":"5610 Broadway Oakland CA 94618",
    "addr:housenumber":"5610",
    "addr:postcode":"94618",
    "addr:street":"Broadway",
    "iso:country":"US",
    "sg:address":"5610 Broadway",
    "sg:city":"Oakland",
    "sg:classifiers":[
        {
            "category":"Education",
            "subcategory":"Preschool",
            "type":"Public Place"
        }
    ],
    "sg:phone":"+1 510 652 7021",
    "sg:postcode":"94618",
    "sg:province":"CA",
    "sg:website":"www.rockridgemontessori.org",
    "wof:name":"Rockridge Montessori School",
    "wof:placetype":"venue"
},
  "geometry": {"coordinates":[-122.24700199999999,37.8433],"type":"Point"}
}