{
  "type": "Feature",
  "properties": {
    "iso:country":"US",
    "sg:address":"2630 Sonoma Blvd",
    "sg:city":"Vallejo",
    "sg:classifiers":[
        {
            "category":"Personal",
            "subcategory":"Beauty Salon",
            "type":"Services"
        }
    ],
    "sg:phone":"+1 707 557 1905",
    "sg:postcode":"94590",
    "sg:province":"CA",
    "sg:tags":[
        "nail",
        "manicuring"
    ],
    "wof:name":"Tammy's Nails & Hair",
    "wof:placetype":"venue"
},
  "geometry": {"coordinates":[-122.254729,38.110545],"type":"Point"}
}