{
  "type": "Feature",
  "properties": {
    "iso:country":"US",
    "sg:address":"10025 Huennekens St",
    "sg:city":"San Diego",
    "sg:classifiers":[
        {
            "category":"Manufacturing",
            "subcategory":"Printing",
            "type":"Manufacturing & Wholesale Goods"
        }
    ],
    "sg:phone":"+1 858 866 3920",
    "sg:postcode":"92121",
    "sg:province":"CA",
    "sg:tags":[
        "printer"
    ],
    "sg:website":"www.conceptimaging.net",
    "wof:name":"Concept Imaging",
    "wof:placetype":"venue"
},
  "geometry": {"coordinates":[-117.183424,32.902672],"type":"Point"}
}