{
  "type": "Feature",
  "properties": {
    "iso:country":"US",
    "sg:address":"1740 W Artesia Blvd Ste C",
    "sg:city":"Gardena",
    "sg:classifiers":[
        {
            "category":"Restaurant",
            "type":"Food & Drink"
        }
    ],
    "sg:phone":"+1 310 515 5110",
    "sg:postcode":"90248",
    "sg:province":"CA",
    "wof:name":"Kau Kau Korner",
    "wof:placetype":"venue"
},
  "geometry": {"coordinates":[-118.293999,33.869598],"type":"Point"}
}