{
  "type": "Feature",
  "properties": {
    "addr:full":"4523 Van Nuys Blvd Sherman Oaks CA 91403",
    "addr:housenumber":"4523",
    "addr:postcode":"91403",
    "addr:street":"Van Nuys Blvd",
    "iso:country":"US",
    "sg:address":"4523 Van Nuys Blvd",
    "sg:city":"Sherman Oaks",
    "sg:classifiers":[
        {
            "category":"Organizations",
            "subcategory":"Non-profit Organization",
            "type":"Services"
        }
    ],
    "sg:phone":"+1 818 894 1175",
    "sg:postcode":"91403",
    "sg:province":"CA",
    "sg:tags":[
        "group",
        "social"
    ],
    "wof:name":"Protecting Adlt Wlfre Fndtn",
    "wof:placetype":"venue"
},
  "geometry": {"coordinates":[-118.448769,34.154376],"type":"Point"}
}