{
  "type": "Feature",
  "properties": {
    "addr:full":"4365 Mammoth Ave Sherman Oaks CA 91423",
    "addr:housenumber":"4365",
    "addr:postcode":"91423",
    "addr:street":"Mammoth Ave",
    "iso:country":"US",
    "sg:address":"4365 Mammoth Ave",
    "sg:city":"Sherman Oaks",
    "sg:classifiers":[
        {
            "category":"Professional",
            "type":"Services"
        }
    ],
    "sg:phone":"+1 818 206 8610",
    "sg:postcode":"91423",
    "sg:province":"CA",
    "sg:tags":[
        "caterer"
    ],
    "sg:website":"www.yamseatery.com",
    "wof:name":"Yams Catering",
    "wof:placetype":"venue"
},
  "geometry": {"coordinates":[-118.432982,34.150117],"type":"Point"}
}