{
  "type": "Feature",
  "properties": {
    "addr:full":"8204 Sunland Blvd Sun Valley CA 91352",
    "addr:housenumber":"8204",
    "addr:postcode":"91352",
    "addr:street":"Sunland Blvd",
    "iso:country":"US",
    "sg:address":"8204 Sunland Blvd",
    "sg:city":"Sun Valley",
    "sg:classifiers":[
        {
            "category":"Restaurant",
            "type":"Food & Drink"
        }
    ],
    "sg:phone":"+1 818 767 1501",
    "sg:postcode":"91352",
    "sg:province":"CA",
    "wof:name":"LA Zeca Taco Inn",
    "wof:placetype":"venue"
},
  "geometry": {"coordinates":[-118.370075,34.217721],"type":"Point"}
}