{
  "type": "Feature",
  "properties": {
    "addr:full":"650 Grand Ave Oakland CA 94610",
    "addr:housenumber":"650",
    "addr:postcode":"94610",
    "addr:street":"Grand Ave",
    "iso:country":"US",
    "sg:address":"650 Grand Ave",
    "sg:city":"Oakland",
    "sg:classifiers":[
        {
            "category":"Home & Garden",
            "subcategory":"Furniture",
            "type":"Retail Goods"
        }
    ],
    "sg:phone":"+1 800 924 6067",
    "sg:postcode":"94610",
    "sg:province":"CA",
    "sg:tags":[
        "store"
    ],
    "wof:name":"Bermans Home Furnishings",
    "wof:placetype":"venue"
},
  "geometry": {"coordinates":[-122.249298,37.809644],"type":"Point"}
}