{
  "type": "Feature",
  "properties": {
    "iso:country":"US",
    "sg:address":"704 S Spring St",
    "sg:city":"Los Angeles",
    "sg:classifiers":[
        {
            "category":"Shopping",
            "subcategory":"Clothing, Apparel, & Fashions",
            "type":"Retail Goods"
        }
    ],
    "sg:phone":"+1 213 891 1542",
    "sg:postcode":"90014",
    "sg:province":"CA",
    "sg:tags":[
        "accessory",
        "clothing",
        "women's"
    ],
    "wof:name":"Magda's Fashion",
    "wof:placetype":"venue"
},
  "geometry": {"coordinates":[-118.251999,34.0448],"type":"Point"}
}