{
  "type": "Feature",
  "properties": {
    "iso:country":"US",
    "sg:address":"1509 Agnew Rd",
    "sg:city":"Santa Clara",
    "sg:classifiers":[
        {
            "category":"Social Services",
            "type":"Services"
        }
    ],
    "sg:phone":"+1 408 855 8506",
    "sg:postcode":"95054",
    "sg:province":"CA",
    "sg:tags":[
        "housing",
        "assistance"
    ],
    "sg:website":"www.homelessness.org",
    "wof:name":"Sobrato Family Living Ctr",
    "wof:placetype":"venue"
},
  "geometry": {"coordinates":[-121.95647599999999,37.395755],"type":"Point"}
}