{
  "type": "Feature",
  "properties": {
    "iso:country":"US",
    "sg:address":"1415 25th St",
    "sg:city":"Bakersfield",
    "sg:classifiers":[
        {
            "category":"Retail",
            "subcategory":"Auto Repair",
            "type":"Services"
        }
    ],
    "sg:phone":"+1 661 322 1869",
    "sg:postcode":"93301",
    "sg:province":"CA",
    "sg:tags":[
        "repairing",
        "automobile"
    ],
    "wof:name":"Automotive Specialist",
    "wof:placetype":"venue"
},
  "geometry": {"coordinates":[-119.018637,35.381864],"type":"Point"}
}