{
  "type": "Feature",
  "properties": {
    "iso:country":"US",
    "sg:address":"13509 Poway Rd",
    "sg:city":"Poway",
    "sg:classifiers":[
        {
            "category":"Ice Cream",
            "type":"Food & Drink"
        }
    ],
    "sg:menulink":"http://www.allmenus.com/ca/san-diego/242299-baskin-robbins/menu/",
    "sg:phone":"+1 858 486 3131",
    "sg:postcode":"92064",
    "sg:province":"CA",
    "sg:tags":[
        "american"
    ],
    "wof:name":"Baskin-Robbins",
    "wof:placetype":"venue"
},
  "geometry": {"coordinates":[-117.03815,32.955056],"type":"Point"}
}