{
  "type": "Feature",
  "properties": {
    "addr:full":"30950 Huntwood Ave Hayward CA 94544",
    "addr:housenumber":"30950",
    "addr:postcode":"94544",
    "addr:street":"Huntwood Ave",
    "iso:country":"US",
    "sg:address":"30950 Huntwood Ave",
    "sg:city":"Hayward",
    "sg:classifiers":[
        {
            "category":"Manufacturing",
            "subcategory":"Tools & Machinery",
            "type":"Manufacturing & Wholesale Goods"
        }
    ],
    "sg:phone":"+1 510 471 0188",
    "sg:postcode":"94544",
    "sg:province":"CA",
    "sg:tags":[
        "machine",
        "shop"
    ],
    "wof:name":"Edge's Special Parts",
    "wof:placetype":"venue"
},
  "geometry": {"coordinates":[-122.054773,37.616033],"type":"Point"}
}