{
  "type": "Feature",
  "properties": {
    "addr:full":"402 Alpine Heights Rd Alpine CA 91901",
    "addr:housenumber":"402",
    "addr:postcode":"91901",
    "addr:street":"Alpine Heights Rd",
    "iso:country":"US",
    "sg:address":"402 Alpine Heights Rd",
    "sg:city":"Alpine",
    "sg:classifiers":[
        {
            "category":"Building & Trades",
            "subcategory":"Electrical",
            "type":"Services"
        }
    ],
    "sg:phone":"+1 619 445 8955",
    "sg:postcode":"91901",
    "sg:province":"CA",
    "sg:tags":[
        "electrician"
    ],
    "wof:name":"Andrew Electric",
    "wof:placetype":"venue"
},
  "geometry": {"coordinates":[-116.805604,32.818956],"type":"Point"}
}