{
  "type": "Feature",
  "properties": {
    "addr:full":"300 E Bellevue Dr Pasadena CA 91101",
    "addr:housenumber":"300",
    "addr:postcode":"91101",
    "addr:street":"E Bellevue Dr",
    "iso:country":"US",
    "sg:address":"300 E Bellevue Dr",
    "sg:city":"Pasadena",
    "sg:classifiers":[
        {
            "category":"Retail",
            "subcategory":"Car Wash",
            "type":"Services"
        }
    ],
    "sg:phone":"+1 323 759 4551",
    "sg:postcode":"91101",
    "sg:province":"CA",
    "sg:tags":[
        "automobile",
        "detail",
        "clean"
    ],
    "wof:name":"Goodrow Auto Detailers",
    "wof:placetype":"venue"
},
  "geometry": {"coordinates":[-118.142966,34.13791],"type":"Point"}
}