{
  "type": "Feature",
  "properties": {
    "addr:full":"219 Mount Hermon Rd Scotts Valley CA 95066",
    "addr:housenumber":"219",
    "addr:postcode":"95066",
    "addr:street":"Mount Hermon Rd",
    "iso:country":"US",
    "sg:address":"219 Mount Hermon Rd",
    "sg:city":"Scotts Valley",
    "sg:classifiers":[
        {
            "category":"Organizations",
            "subcategory":"Professional Association",
            "type":"Services"
        }
    ],
    "sg:phone":"+1 831 338 3982",
    "sg:postcode":"95066",
    "sg:province":"CA",
    "wof:name":"Valley Speech & Language Assoc",
    "wof:placetype":"venue"
},
  "geometry": {"coordinates":[-122.03274,37.047508],"type":"Point"}
}