{
  "type": "Feature",
  "properties": {
    "addr:full":"3214 Broadway Sacramento CA 95817",
    "addr:housenumber":"3214",
    "addr:postcode":"95817",
    "addr:street":"Broadway",
    "iso:country":"US",
    "sg:address":"3214 Broadway",
    "sg:city":"Sacramento",
    "sg:classifiers":[
        {
            "category":"Personal",
            "subcategory":"Barber",
            "type":"Services"
        }
    ],
    "sg:phone":"+1 916 454 2006",
    "sg:postcode":"95817",
    "sg:province":"CA",
    "wof:name":"The One Barber Shop",
    "wof:placetype":"venue"
},
  "geometry": {"coordinates":[-121.47105999999999,38.554285],"type":"Point"}
}