{
  "type": "Feature",
  "properties": {
    "addr:full":"16566 Hacienda Ct Hidden Valley Lk CA 95467",
    "addr:housenumber":"16566",
    "addr:postcode":"95467",
    "addr:street":"Hacienda Ct",
    "iso:country":"US",
    "sg:address":"16566 Hacienda Ct",
    "sg:city":"Hidden Valley Lk",
    "sg:classifiers":[
        {
            "category":"Building & Trades",
            "subcategory":"Construction",
            "type":"Services"
        }
    ],
    "sg:phone":"+1 707 987 2222",
    "sg:postcode":"95467",
    "sg:province":"CA",
    "sg:tags":[
        "painter"
    ],
    "wof:name":"Sawyer's Painting",
    "wof:placetype":"venue"
},
  "geometry": {"coordinates":[-122.56887999999999,38.820629],"type":"Point"}
}