{
  "type": "Feature",
  "properties": {
    "iso:country":"US",
    "sg:address":"230 California St",
    "sg:city":"San Francisco",
    "sg:classifiers":[
        {
            "category":"Restaurant",
            "type":"Food & Drink"
        }
    ],
    "sg:menulink":"http://www.allmenus.com/ca/san-francisco/22396-perbacco/menu/",
    "sg:phone":"+1 415 955 0663",
    "sg:postcode":"94111",
    "sg:province":"CA",
    "sg:tags":[
        "italian"
    ],
    "wof:name":"Perbacco",
    "wof:placetype":"venue"
},
  "geometry": {"coordinates":[-122.399224,37.793346],"type":"Point"}
}