{
  "type": "Feature",
  "properties": {
    "addr:full":"74 Yellow Hammer Dr Oroville CA 95966",
    "addr:housenumber":"74",
    "addr:postcode":"95966",
    "addr:street":"Yellow Hammer Dr",
    "iso:country":"US",
    "sg:address":"74 Yellow Hammer Dr",
    "sg:city":"Oroville",
    "sg:classifiers":[
        {
            "category":"Restaurant",
            "type":"Food & Drink"
        }
    ],
    "sg:phone":"+1 530 533 9087",
    "sg:postcode":"95966",
    "sg:province":"CA",
    "wof:name":"Memories Made By Marla",
    "wof:placetype":"venue"
},
  "geometry": {"coordinates":[-121.50318799999999,39.501162],"type":"Point"}
}