{
  "type": "Feature",
  "properties": {
    "iso:country":"US",
    "sg:address":"619 Olive St",
    "sg:city":"Santa Barbara",
    "sg:classifiers":[
        {
            "category":"Professional",
            "type":"Services"
        }
    ],
    "sg:phone":"+1 805 899 2126",
    "sg:postcode":"93101",
    "sg:province":"CA",
    "sg:tags":[
        "writer"
    ],
    "wof:name":"Olive Productions",
    "wof:placetype":"venue"
},
  "geometry": {"coordinates":[-119.69225,34.423741],"type":"Point"}
}