{
  "type": "Feature",
  "properties": {
    "iso:country":"US",
    "sg:address":"3443 Orange St",
    "sg:city":"Riverside",
    "sg:classifiers":[
        {
            "category":"Professional",
            "type":"Services"
        }
    ],
    "sg:phone":"+1 951 684 2312",
    "sg:postcode":"92501",
    "sg:province":"CA",
    "wof:name":"Itty Bitty Treasures",
    "wof:placetype":"venue"
},
  "geometry": {"coordinates":[-117.371118,33.984801],"type":"Point"}
}