{
  "type": "Feature",
  "properties": {
    "iso:country":"US",
    "sg:address":"900 Market St",
    "sg:city":"Oakland",
    "sg:classifiers":[
        {
            "category":"Personal",
            "subcategory":"Beauty Salon",
            "type":"Services"
        }
    ],
    "sg:phone":"+1 510 625 1100",
    "sg:postcode":"94607",
    "sg:province":"CA",
    "sg:tags":[
        "hair",
        "stylist"
    ],
    "wof:name":"Hair's The Point",
    "wof:placetype":"venue"
},
  "geometry": {"coordinates":[-122.282265,37.804553],"type":"Point"}
}