{
  "type": "Feature",
  "properties": {
    "addr:full":"2900 S Harbor Blvd Santa Ana CA 92704",
    "addr:housenumber":"2900",
    "addr:postcode":"92704",
    "addr:street":"S Harbor Blvd",
    "iso:country":"US",
    "sg:address":"2900 S Harbor Blvd",
    "sg:city":"Santa Ana",
    "sg:classifiers":[
        {
            "category":"Shopping",
            "subcategory":"Stationery & Office Supplies",
            "type":"Retail Goods"
        },
        {
            "category":"Manufacturing",
            "subcategory":"Retail Goods",
            "type":"Manufacturing & Wholesale Goods"
        }
    ],
    "sg:phone":"+1 714 429 2223",
    "sg:postcode":"92704",
    "sg:province":"CA",
    "sg:tags":[
        "aids",
        "educational",
        "material",
        "mfg"
    ],
    "sg:website":"www.gatewaylearning.com",
    "wof:name":"Gateway Learning Corporation",
    "wof:placetype":"venue"
},
  "geometry": {"coordinates":[-117.91973,33.707049],"type":"Point"}
}