{
  "type": "Feature",
  "properties": {
    "addr:full":"1028 W Big Bear Blvd Big Bear City CA 92314",
    "addr:housenumber":"1028",
    "addr:postcode":"92314",
    "addr:street":"W Big Bear Blvd",
    "iso:country":"US",
    "sg:address":"1028 W Big Bear Blvd",
    "sg:city":"Big Bear City",
    "sg:classifiers":[
        {
            "category":"Shopping",
            "type":"Retail Goods"
        }
    ],
    "sg:phone":"+1 909 585 9977",
    "sg:postcode":"92314",
    "sg:province":"CA",
    "sg:tags":[
        "art",
        "gallery",
        "dealer"
    ],
    "wof:name":"Serenity Place",
    "wof:placetype":"venue"
},
  "geometry": {"coordinates":[-116.863657,34.260406],"type":"Point"}
}