{
  "type": "Feature",
  "properties": {
    "addr:full":"850 W 34th St Los Angeles CA 90089",
    "addr:housenumber":"850",
    "addr:postcode":"90089",
    "addr:street":"W 34Th St",
    "iso:country":"US",
    "sg:address":"850 W 34th St",
    "sg:city":"Los Angeles",
    "sg:classifiers":[
        {
            "category":"Education",
            "subcategory":"College",
            "type":"Public Place"
        }
    ],
    "sg:phone":"+1 213 740 2921",
    "sg:postcode":"90089",
    "sg:province":"CA",
    "sg:tags":[
        "university"
    ],
    "wof:name":"Usc Cinema--Tv",
    "wof:placetype":"venue"
},
  "geometry": {"coordinates":[-118.283807,34.022611],"type":"Point"}
}