{
  "type": "Feature",
  "properties": {
    "iso:country":"US",
    "sg:address":"14929 Via la Senda",
    "sg:city":"Del Mar",
    "sg:classifiers":[
        {
            "category":"Professional",
            "subcategory":"Employment Agencies",
            "type":"Services"
        }
    ],
    "sg:phone":"+1 858 755 9376",
    "sg:postcode":"92014",
    "sg:province":"CA",
    "sg:tags":[
        "consultant",
        "search",
        "executive"
    ],
    "wof:name":"Power Works Intl",
    "wof:placetype":"venue"
},
  "geometry": {"coordinates":[-117.242188,32.990536],"type":"Point"}
}