{
  "type": "Feature",
  "properties": {
    "addr:full":"1125 W Olive St San Diego CA 92103",
    "addr:housenumber":"1125",
    "addr:postcode":"92103",
    "addr:street":"W Olive St",
    "iso:country":"US",
    "sg:address":"1125 W Olive St",
    "sg:city":"San Diego",
    "sg:classifiers":[
        {
            "category":"Shopping",
            "subcategory":"Optician",
            "type":"Retail Goods"
        }
    ],
    "sg:phone":"+1 619 295 7334",
    "sg:postcode":"92103",
    "sg:province":"CA",
    "sg:tags":[
        "eyewear"
    ],
    "wof:name":"Red Eye Wear",
    "wof:placetype":"venue"
},
  "geometry": {"coordinates":[-117.172055,32.733203],"type":"Point"}
}