{
  "type": "Feature",
  "properties": {
    "sfgov:dept":"7",
    "sfgov:deptname":"SF Unified School District (SFUSD)",
    "sfgov:facility_i":"0000060168",
    "sfgov:school_typ":"Charter School",
    "wof:categories":[
        "education_and_religion:education=school"
    ],
    "wof:name":"Life Learning Academy Charter School",
    "wof:placetype":"venue"
},
  "geometry": {"coordinates":[-122.36792911279943,37.82529785839608],"type":"Point"}
}