{
  "type": "Feature",
  "properties": {
    "iso:country":"US",
    "sg:address":"1555 Fulton Ave",
    "sg:city":"Sacramento",
    "sg:classifiers":[
        {
            "category":"Home & Garden",
            "subcategory":"Home Furnishings",
            "type":"Retail Goods"
        },
        {
            "category":"Manufacturing",
            "subcategory":"Pottery",
            "type":"Manufacturing & Wholesale Goods"
        },
        {
            "category":"Community Center",
            "type":"Public Place"
        },
        {
            "category":"Home & Garden",
            "subcategory":"Furniture",
            "type":"Retail Goods"
        },
        {
            "category":"Home & Garden",
            "subcategory":"Carpets & Floor Coverings",
            "type":"Retail Goods"
        },
        {
            "category":"Manufacturing",
            "subcategory":"Chemicals & Compounds",
            "type":"Manufacturing & Wholesale Goods"
        },
        {
            "category":"Manufacturing",
            "subcategory":"Glass & Minerals",
            "type":"Manufacturing & Wholesale Goods"
        }
    ],
    "sg:phone":"+1 916 481 5395",
    "sg:postcode":"95825",
    "sg:province":"CA",
    "sg:tags":[
        "decor",
        "products-decorative",
        "house",
        "ceramic",
        "product",
        "housewares",
        "rug",
        "crystal",
        "china",
        "wicker",
        "basket",
        "candle",
        "glassware",
        "store"
    ],
    "sg:website":"http://www.pier1.com",
    "wof:name":"Pier 1 Imports",
    "wof:placetype":"venue"
},
  "geometry": {"coordinates":[-121.401492,38.593752],"type":"Point"}
}