{
  "type": "Feature",
  "properties": {
    "addr:full":"1055 Pine St Menlo Park CA 94025",
    "addr:housenumber":"1055",
    "addr:postcode":"94025",
    "addr:street":"Pine St",
    "iso:country":"US",
    "sg:address":"1055 Pine St",
    "sg:city":"Menlo Park",
    "sg:classifiers":[
        {
            "category":"Banks & Credit Unions",
            "subcategory":"Investment Brokerage",
            "type":"Services"
        },
        {
            "category":"Manufacturing",
            "subcategory":"Printing",
            "type":"Manufacturing & Wholesale Goods"
        }
    ],
    "sg:phone":"+1 650 321 9064",
    "sg:postcode":"94025",
    "sg:province":"CA",
    "sg:tags":[
        "publisher",
        "stock",
        "bond"
    ],
    "wof:name":"Flow of Capital Inc",
    "wof:placetype":"venue"
},
  "geometry": {"coordinates":[-122.179271,37.456686],"type":"Point"}
}