{
  "type": "Feature",
  "properties": {
    "addr:full":"5401 Coliseum Way Oakland CA 94601",
    "addr:housenumber":"5401",
    "addr:postcode":"94601",
    "addr:street":"Coliseum Way",
    "iso:country":"US",
    "sg:address":"5401 Coliseum Way",
    "sg:city":"Oakland",
    "sg:classifiers":[
        {
            "category":"Shopping",
            "subcategory":"Clothing, Apparel, & Fashions",
            "type":"Retail Goods"
        }
    ],
    "sg:phone":"+1 510 467 3870",
    "sg:postcode":"94601",
    "sg:province":"CA",
    "sg:tags":[
        "accessory",
        "women's"
    ],
    "wof:name":"Janet Bolds Kisha",
    "wof:placetype":"venue"
},
  "geometry": {"coordinates":[-122.212328,37.762464],"type":"Point"}
}