{
  "type": "Feature",
  "properties": {
    "addr:full":"289 Commercial St Portola CA 96122",
    "addr:housenumber":"289",
    "addr:postcode":"96122",
    "addr:street":"Commercial St",
    "iso:country":"US",
    "sg:address":"289 Commercial St",
    "sg:city":"Portola",
    "sg:classifiers":[
        {
            "category":"Shopping",
            "subcategory":"Discount & Variety Stores",
            "type":"Retail Goods"
        }
    ],
    "sg:phone":"+1 530 832 4870",
    "sg:postcode":"96122",
    "sg:province":"CA",
    "wof:name":"Mitchell's Dollar Store",
    "wof:placetype":"venue"
},
  "geometry": {"coordinates":[-120.470189,39.805904],"type":"Point"}
}