{
  "type": "Feature",
  "properties": {
    "iso:country":"US",
    "sg:address":"2702 11th St",
    "sg:city":"Santa Monica",
    "sg:classifiers":[
        {
            "category":"Professional",
            "type":"Services"
        }
    ],
    "sg:phone":"+1 310 396 5621",
    "sg:postcode":"90405",
    "sg:province":"CA",
    "sg:tags":[
        "establishment"
    ],
    "wof:name":"Ocean Breeze Place",
    "wof:placetype":"venue"
},
  "geometry": {"coordinates":[-118.472949,34.007513],"type":"Point"}
}