{
  "type": "Feature",
  "properties": {
    "iso:country":"US",
    "sg:address":"1930 W Summerfield Ct",
    "sg:city":"Oakley",
    "sg:classifiers":[
        {
            "category":"Building & Trades",
            "subcategory":"Plumbing",
            "type":"Services"
        }
    ],
    "sg:phone":"+1 925 625 8212",
    "sg:postcode":"94561",
    "sg:province":"CA",
    "sg:tags":[
        "contractor"
    ],
    "wof:name":"Bullards Htg Air",
    "wof:placetype":"venue"
},
  "geometry": {"coordinates":[-121.729421,38.003125],"type":"Point"}
}