{
  "type": "Feature",
  "properties": {
    "addr:full":"120 Oakcrest Ct Danville CA 94526",
    "addr:housenumber":"120",
    "addr:postcode":"94526",
    "addr:street":"Oakcrest Ct",
    "iso:country":"US",
    "sg:address":"120 Oakcrest Ct",
    "sg:city":"Danville",
    "sg:classifiers":[
        {
            "category":"Building & Trades",
            "subcategory":"Cleaning & Sanitation",
            "type":"Services"
        }
    ],
    "sg:phone":"+1 925 735 1606",
    "sg:postcode":"94526",
    "sg:province":"CA",
    "sg:tags":[
        "house"
    ],
    "wof:name":"Hilda's House Keeping",
    "wof:placetype":"venue"
},
  "geometry": {"coordinates":[-121.96978,37.790031],"type":"Point"}
}