{
  "type": "Feature",
  "properties": {
    "iso:country":"US",
    "sg:address":"1940 Kellogg Ave",
    "sg:city":"Carlsbad",
    "sg:classifiers":[
        {
            "category":"Personal",
            "type":"Services"
        }
    ],
    "sg:phone":"+1 760 603 8000",
    "sg:postcode":"92008",
    "sg:province":"CA",
    "sg:tags":[
        "planning",
        "wedding"
    ],
    "wof:name":"Foster Wayne Music & Entertainment",
    "wof:placetype":"venue"
},
  "geometry": {"coordinates":[-117.28600299999999,33.124699],"type":"Point"}
}