{
  "type": "Feature",
  "properties": {
    "addr:full":"7183 Opportunity Rd San Diego CA 92111",
    "addr:housenumber":"7183",
    "addr:postcode":"92111",
    "addr:street":"Opportunity Rd",
    "iso:country":"US",
    "sg:address":"7183 Opportunity Rd",
    "sg:city":"San Diego",
    "sg:classifiers":[
        {
            "category":"Government",
            "subcategory":"Police Station",
            "type":"Public Place"
        }
    ],
    "sg:phone":"+1 858 637 3800",
    "sg:postcode":"92111",
    "sg:province":"CA",
    "sg:tags":[
        "patrol",
        "highway"
    ],
    "wof:name":"Border Communications Center",
    "wof:placetype":"venue"
},
  "geometry": {"coordinates":[-117.158721,32.825297],"type":"Point"}
}