{
  "type": "Feature",
  "properties": {
    "addr:full":"980 Mission Ct Fremont CA 94539",
    "addr:housenumber":"980",
    "addr:postcode":"94539",
    "addr:street":"Mission Ct",
    "iso:country":"US",
    "sg:address":"980 Mission Ct",
    "sg:city":"Fremont",
    "sg:classifiers":[
        {
            "category":"Professional",
            "type":"Services"
        }
    ],
    "sg:phone":"+1 510 249 5110",
    "sg:postcode":"94539",
    "sg:province":"CA",
    "sg:tags":[
        "establishment"
    ],
    "wof:name":"Innerstep",
    "wof:placetype":"venue"
},
  "geometry": {"coordinates":[-121.930297,37.490585],"type":"Point"}
}