{
  "type": "Feature",
  "properties": {
    "addr:full":"1157 Oasis Ave Chula Vista CA 91911",
    "addr:housenumber":"1157",
    "addr:postcode":"91911",
    "addr:street":"Oasis Ave",
    "iso:country":"US",
    "sg:address":"1157 Oasis Ave",
    "sg:city":"Chula Vista",
    "sg:classifiers":[
        {
            "category":"Social Services",
            "subcategory":"Child Care",
            "type":"Services"
        }
    ],
    "sg:phone":"+1 619 421 3576",
    "sg:postcode":"91911",
    "sg:province":"CA",
    "wof:name":"Gracie's Day Care",
    "wof:placetype":"venue"
},
  "geometry": {"coordinates":[-117.03745600000001,32.620444],"type":"Point"}
}