{
  "type": "Feature",
  "properties": {
    "addr:full":"110 Liberty St Petaluma CA 94952",
    "addr:housenumber":"110",
    "addr:postcode":"94952",
    "addr:street":"Liberty St",
    "iso:country":"US",
    "sg:address":"110 Liberty St",
    "sg:city":"Petaluma",
    "sg:classifiers":[
        {
            "category":"Professional",
            "subcategory":"Testing Lab",
            "type":"Services"
        }
    ],
    "sg:phone":"+1 707 769 3128",
    "sg:postcode":"94952",
    "sg:province":"CA",
    "sg:tags":[
        "laboratory"
    ],
    "wof:name":"Analytical Sciences",
    "wof:placetype":"venue"
},
  "geometry": {"coordinates":[-122.642976,38.233373],"type":"Point"}
}