{
  "type": "Feature",
  "properties": {
    "addr:full":"4121 Napier St San Diego CA 92110",
    "addr:housenumber":"4121",
    "addr:postcode":"92110",
    "addr:street":"Napier St",
    "iso:country":"US",
    "sg:address":"4121 Napier St",
    "sg:city":"San Diego",
    "sg:classifiers":[
        {
            "category":"Professional",
            "subcategory":"Engineering",
            "type":"Services"
        }
    ],
    "sg:phone":"+1 619 275 1530",
    "sg:postcode":"92110",
    "sg:province":"CA",
    "sg:tags":[
        "engineer"
    ],
    "wof:name":"Atkinson Johnson & Spurrier",
    "wof:placetype":"venue"
},
  "geometry": {"coordinates":[-117.206228,32.782159],"type":"Point"}
}