{
  "type": "Feature",
  "properties": {
    "addr:full":"6934 Palm Avenue Fair Oaks CA 95628",
    "addr:housenumber":"6934",
    "addr:postcode":"95628",
    "addr:street":"Palm Avenue",
    "iso:country":"US",
    "sg:address":"6934 Palm Avenue",
    "sg:city":"Fair Oaks",
    "sg:classifiers":[
        {
            "category":"Building & Trades",
            "subcategory":"Cleaning & Sanitation",
            "type":"Services"
        }
    ],
    "sg:phone":"+1 916 967 6645",
    "sg:postcode":"95628",
    "sg:province":"CA",
    "sg:tags":[
        "carpet"
    ],
    "wof:name":"Sharper's Carpet Cleaning",
    "wof:placetype":"venue"
},
  "geometry": {"coordinates":[-121.30185899999999,38.661048],"type":"Point"}
}