{
  "type": "Feature",
  "properties": {
    "iso:country":"US",
    "sg:address":"Sunset Blvd. & Whittier Drive",
    "sg:city":"Beverly Hills",
    "sg:classifiers":[
        {
            "category":"Park",
            "type":"Public Place"
        }
    ],
    "sg:postcode":"90210",
    "sg:province":"CA",
    "wof:name":"The Maltz Park",
    "wof:placetype":"venue"
},
  "geometry": {"coordinates":[-118.419958,34.077164],"type":"Point"}
}