{
  "type": "Feature",
  "properties": {
    "addr:full":"1041 7th Ave San Diego CA 92101",
    "addr:housenumber":"1041",
    "addr:postcode":"92101",
    "addr:street":"7Th Ave",
    "iso:country":"US",
    "sg:address":"1041 7th Ave",
    "sg:city":"San Diego",
    "sg:classifiers":[
        {
            "category":"Bars & Pubs",
            "type":"Food & Drink"
        }
    ],
    "sg:phone":"+1 619 230 1107",
    "sg:postcode":"92101",
    "sg:province":"CA",
    "sg:tags":[
        "club",
        "night"
    ],
    "wof:name":"Antonio Restaurant & Showcase",
    "wof:placetype":"venue"
},
  "geometry": {"coordinates":[-117.158269,32.716266],"type":"Point"}
}