{
  "type": "Feature",
  "properties": {
    "iso:country":"US",
    "sg:address":"511 Sutter St",
    "sg:city":"Jackson",
    "sg:classifiers":[
        {
            "category":"Health Services",
            "subcategory":"Doctor",
            "type":"Services"
        }
    ],
    "sg:phone":"+1 209 223 0204",
    "sg:postcode":"95642",
    "sg:province":"CA",
    "sg:tags":[
        "dentist"
    ],
    "wof:name":"Roland Womack DDS",
    "wof:placetype":"venue"
},
  "geometry": {"coordinates":[-120.780852,38.352981],"type":"Point"}
}