{
  "type": "Feature",
  "properties": {
    "addr:full":"5115 Ave Encinas Carlsbad CA 92008",
    "addr:housenumber":"5115",
    "addr:postcode":"92008",
    "addr:street":"Ave Encinas",
    "iso:country":"US",
    "sg:address":"5115 Ave Encinas",
    "sg:city":"Carlsbad",
    "sg:classifiers":[
        {
            "category":"Manufacturing",
            "subcategory":"Electronics",
            "type":"Manufacturing & Wholesale Goods"
        }
    ],
    "sg:phone":"+1 760 931 6417",
    "sg:postcode":"92008",
    "sg:province":"CA",
    "sg:tags":[
        "equipment",
        "video"
    ],
    "wof:name":"Applied Magic",
    "wof:placetype":"venue"
},
  "geometry": {"coordinates":[-117.329235,33.131684],"type":"Point"}
}