{
  "type": "Feature",
  "properties": {
    "addr:full":"41154 Via Cielito Temecula CA 92591",
    "addr:housenumber":"41154",
    "addr:postcode":"92591",
    "addr:street":"Via Cielito",
    "iso:country":"US",
    "sg:address":"41154 Via Cielito",
    "sg:city":"Temecula",
    "sg:classifiers":[
        {
            "category":"Manufacturing",
            "subcategory":"Metals",
            "type":"Manufacturing & Wholesale Goods"
        }
    ],
    "sg:phone":"+1 951 699 9351",
    "sg:postcode":"92591",
    "sg:province":"CA",
    "sg:tags":[
        "water",
        "storage",
        "tank",
        "mfg"
    ],
    "wof:name":"Waterboy Mobile Tanker",
    "wof:placetype":"venue"
},
  "geometry": {"coordinates":[-117.141395,33.52258],"type":"Point"}
}