{
  "type": "Feature",
  "properties": {
    "addr:full":"25761 Le Parc Unit 84 Lake Forest CA 92630",
    "addr:housenumber":"25761;84",
    "addr:postcode":"92630",
    "addr:street":"Le Parc Unit",
    "iso:country":"US",
    "sg:address":"25761 Le Parc Unit 84",
    "sg:city":"Lake Forest",
    "sg:classifiers":[
        {
            "category":"Banks & Credit Unions",
            "subcategory":"Investment Brokerage",
            "type":"Services"
        }
    ],
    "sg:phone":"+1 888 310 7689",
    "sg:postcode":"92630",
    "sg:province":"CA",
    "sg:tags":[
        "investing"
    ],
    "wof:name":"Aha Investors",
    "wof:placetype":"venue"
},
  "geometry": {"coordinates":[-117.68029799999999,33.641074],"type":"Point"}
}