{
  "type": "Feature",
  "properties": {
    "addr:full":"7700 College Town Dr Ste 250 Sacramento CA 95826",
    "addr:housenumber":"7700",
    "addr:postcode":"95826",
    "addr:street":"College Town Dr Ste 250",
    "iso:country":"US",
    "sg:address":"7700 College Town Dr Ste 250",
    "sg:city":"Sacramento",
    "sg:classifiers":[
        {
            "category":"Professional",
            "type":"Services"
        }
    ],
    "sg:phone":"+1 888 595 2747",
    "sg:postcode":"95826",
    "sg:province":"CA",
    "sg:website":"www.sundocumentfilings.com",
    "wof:name":"Sun Document Filings",
    "wof:placetype":"venue"
},
  "geometry": {"coordinates":[-121.414918,38.553558],"type":"Point"}
}