{
  "type": "Feature",
  "properties": {
    "iso:country":"US",
    "sg:address":"3524 Jarena Dr",
    "sg:city":"Modesto",
    "sg:classifiers":[
        {
            "category":"Professional",
            "subcategory":"Business Services",
            "type":"Services"
        }
    ],
    "sg:phone":"+1 209 526 3972",
    "sg:postcode":"95357",
    "sg:province":"CA",
    "sg:tags":[
        "auctioneer"
    ],
    "wof:name":"J L Enterprises",
    "wof:placetype":"venue"
},
  "geometry": {"coordinates":[-120.92693,37.64155],"type":"Point"}
}