{
  "type": "Feature",
  "properties": {
    "addr:full":"5895 Pacific St Rocklin CA 95677",
    "addr:housenumber":"5895",
    "addr:postcode":"95677",
    "addr:street":"Pacific St",
    "iso:country":"US",
    "sg:address":"5895 Pacific St",
    "sg:city":"Rocklin",
    "sg:phone":"+1 916 624 3747",
    "sg:postcode":"95677",
    "sg:province":"CA",
    "wof:name":"Blue Moose Deli and Coffee House",
    "wof:placetype":"venue"
},
  "geometry": {"coordinates":[-121.242102,38.781382],"type":"Point"}
}