{
  "type": "Feature",
  "properties": {
    "iso:country":"US",
    "sg:address":"22801 Vanowen St",
    "sg:city":"West Hills",
    "sg:classifiers":[
        {
            "category":"Autos & Motor Vehicles",
            "subcategory":"Fuel & Gas Station",
            "type":"Retail Goods"
        }
    ],
    "sg:phone":"+1 818 883 7600",
    "sg:postcode":"91307",
    "sg:province":"CA",
    "wof:name":"West Hills 76",
    "wof:placetype":"venue"
},
  "geometry": {"coordinates":[-118.62400100000001,34.1936],"type":"Point"}
}