{
  "type": "Feature",
  "properties": {
    "iso:country":"US",
    "sg:address":"9121 Bolsa Ave",
    "sg:city":"Westminster",
    "sg:classifiers":[
        {
            "category":"Banks & Credit Unions",
            "subcategory":"Bank",
            "type":"Services"
        }
    ],
    "sg:phone":"+1 714 901 9369",
    "sg:postcode":"92683",
    "sg:province":"CA",
    "wof:name":"Cathay Bank",
    "wof:placetype":"venue"
},
  "geometry": {"coordinates":[-117.970001,33.7449],"type":"Point"}
}