{
  "type": "Feature",
  "properties": {
    "iso:country":"US",
    "sg:address":"555 McMurray Rd",
    "sg:city":"Buellton",
    "sg:classifiers":[
        {
            "category":"Travel",
            "subcategory":"Hotels & Motels",
            "type":"Entertainment"
        }
    ],
    "sg:phone":"+1 805 688 1000",
    "sg:postcode":"93427",
    "sg:province":"CA",
    "wof:name":"Rancho Santa Barbara Marriott",
    "wof:placetype":"venue"
},
  "geometry": {"coordinates":[-120.188881,34.611683],"type":"Point"}
}