{
  "type": "Feature",
  "properties": {
    "addr:full":"555 McMurray Rd Buellton CA 93427",
    "addr:housenumber":"555",
    "addr:postcode":"93427",
    "addr:street":"Mcmurray Rd",
    "iso:country":"US",
    "sg:address":"555 McMurray Rd",
    "sg:city":"Buellton",
    "sg:classifiers":[
        {
            "category":"Travel",
            "subcategory":"Hotels & Motels",
            "type":"Entertainment"
        }
    ],
    "sg:phone":"+1 805 688 1000",
    "sg:postcode":"93427",
    "sg:province":"CA",
    "wof:name":"Rancho Santa Barbara Marriott",
    "wof:placetype":"venue"
},
  "geometry": {"coordinates":[-120.18888099999999,34.611683],"type":"Point"}
}