{
  "type": "Feature",
  "properties": {
    "addr:full":"1276 N Palm Canyon Dr Palm Springs CA 92262",
    "addr:housenumber":"1276",
    "addr:postcode":"92262",
    "addr:street":"N Palm Canyon Dr",
    "iso:country":"US",
    "sg:address":"1276 N Palm Canyon Dr",
    "sg:city":"Palm Springs",
    "sg:classifiers":[
        {
            "category":"Real Estate",
            "subcategory":"Real Estate Agent",
            "type":"Services"
        }
    ],
    "sg:phone":"+1 760 325 7784",
    "sg:postcode":"92262",
    "sg:province":"CA",
    "wof:name":"Real Estate Firm",
    "wof:placetype":"venue"
},
  "geometry": {"coordinates":[-116.54670299999999,33.84009],"type":"Point"}
}