{
  "type": "Feature",
  "properties": {
    "iso:country":"US",
    "sg:address":"4317 S Downey Rd",
    "sg:city":"Vernon",
    "sg:classifiers":[
        {
            "category":"Freight",
            "type":"Transportation"
        }
    ],
    "sg:phone":"+1 323 583 1577",
    "sg:postcode":"90058",
    "sg:province":"CA",
    "sg:tags":[
        "trucking"
    ],
    "wof:name":"J & H Trucking",
    "wof:placetype":"venue"
},
  "geometry": {"coordinates":[-118.204937,34.005319],"type":"Point"}
}