{
  "type": "Feature",
  "properties": {
    "addr:full":"540 Main St Diamond Springs CA 95694",
    "addr:housenumber":"540",
    "addr:postcode":"ca 95694",
    "addr:street":"Main St Diamond",
    "iso:country":"US",
    "sg:address":"540 Main St",
    "sg:city":"Diamond Springs",
    "sg:classifiers":[
        {
            "category":"Banks & Credit Unions",
            "subcategory":"Bank",
            "type":"Services"
        }
    ],
    "sg:phone":"+1 530 626 0152",
    "sg:postcode":"95694",
    "sg:province":"CA",
    "sg:tags":[
        "loan",
        "real estate"
    ],
    "wof:name":"Sellsmart Renshaw & Assoc",
    "wof:placetype":"venue"
},
  "geometry": {"coordinates":[-121.981078,38.519472],"type":"Point"}
}