{
  "type": "Feature",
  "properties": {
    "iso:country":"US",
    "sg:address":"923 S Harvard Blvd",
    "sg:city":"Los Angeles",
    "sg:classifiers":[
        {
            "category":"Building & Trades",
            "subcategory":"Cleaning & Sanitation",
            "type":"Services"
        }
    ],
    "sg:phone":"+1 213 380 4780",
    "sg:postcode":"90006",
    "sg:province":"CA",
    "sg:tags":[
        "janitor"
    ],
    "wof:name":"Giant Painting Co",
    "wof:placetype":"venue"
},
  "geometry": {"coordinates":[-118.304227,34.055112],"type":"Point"}
}