{
  "type": "Feature",
  "properties": {
    "iso:country":"US",
    "sg:address":"198 Loma Alta Ave",
    "sg:city":"Los Gatos",
    "sg:classifiers":[
        {
            "category":"Professional",
            "type":"Services"
        }
    ],
    "sg:phone":"+1 408 354 4351",
    "sg:postcode":"95030",
    "sg:province":"CA",
    "wof:name":"John W/Margarita L Panigh",
    "wof:placetype":"venue"
},
  "geometry": {"coordinates":[-121.970017,37.219843],"type":"Point"}
}