{
  "type": "Feature",
  "properties": {
    "iso:country":"US",
    "sg:address":"2300 Broadway Apt 1",
    "sg:city":"Oakland",
    "sg:classifiers":[
        {
            "category":"Professional",
            "subcategory":"Business Services",
            "type":"Services"
        }
    ],
    "sg:phone":"+1 510 893 1313",
    "sg:postcode":"94612",
    "sg:province":"CA",
    "sg:tags":[
        "management"
    ],
    "wof:name":"Trinity Soul",
    "wof:placetype":"venue"
},
  "geometry": {"coordinates":[-122.266289,37.81213],"type":"Point"}
}