{
  "type": "Feature",
  "properties": {
    "addr:full":"238 1/2 S Beverly Dr Beverly Hills CA 90212",
    "addr:housenumber":"238 1 / 2",
    "addr:postcode":"90212",
    "addr:street":"S Beverly Dr",
    "iso:country":"US",
    "sg:address":"238 1/2 S Beverly Dr",
    "sg:city":"Beverly Hills",
    "sg:classifiers":[
        {
            "category":"Shopping",
            "subcategory":"Clothing, Apparel, & Fashions",
            "type":"Retail Goods"
        }
    ],
    "sg:phone":"+1 310 276 5652",
    "sg:postcode":"90212",
    "sg:province":"CA",
    "sg:tags":[
        "children's",
        "clothing"
    ],
    "wof:name":"Lola Et Moi",
    "wof:placetype":"venue"
},
  "geometry": {"coordinates":[-118.398917,34.391817],"type":"Point"}
}