{
  "type": "Feature",
  "properties": {
    "iso:country":"US",
    "sg:address":"619 Grove St",
    "sg:city":"Bishop",
    "sg:classifiers":[
        {
            "category":"Building & Trades",
            "subcategory":"Cleaning & Sanitation",
            "type":"Services"
        }
    ],
    "sg:phone":"+1 760 872 2254",
    "sg:postcode":"93514",
    "sg:province":"CA",
    "sg:tags":[
        "janitor"
    ],
    "wof:name":"Dan's Janitorial",
    "wof:placetype":"venue"
},
  "geometry": {"coordinates":[-118.400598,37.364696],"type":"Point"}
}