{
  "type": "Feature",
  "properties": {
    "addr:full":"3950 T St Sacramento CA 95819",
    "addr:housenumber":"3950",
    "addr:postcode":"95819",
    "addr:street":"T St",
    "iso:country":"US",
    "sg:address":"3950 T St",
    "sg:city":"Sacramento",
    "sg:classifiers":[
        {
            "category":"Building & Trades",
            "subcategory":"Cleaning & Sanitation",
            "type":"Services"
        }
    ],
    "sg:phone":"+1 916 454 3268",
    "sg:postcode":"95819",
    "sg:province":"CA",
    "sg:tags":[
        "cleaning-industrial",
        "contractor"
    ],
    "wof:name":"Iris Cleaning Services",
    "wof:placetype":"venue"
},
  "geometry": {"coordinates":[-121.458247,38.558416],"type":"Point"}
}