{
  "type": "Feature",
  "properties": {
    "iso:country":"US",
    "sg:address":"12416 Morning Ave",
    "sg:city":"Downey",
    "sg:classifiers":[
        {
            "category":"Restaurant",
            "type":"Food & Drink"
        }
    ],
    "sg:phone":"+1 562 861 2358",
    "sg:postcode":"90242",
    "sg:province":"CA",
    "sg:tags":[
        "style",
        "family"
    ],
    "wof:name":"Earth Friendly Green Solutions, Inc.",
    "wof:placetype":"venue"
},
  "geometry": {"coordinates":[-118.152228,33.927013],"type":"Point"}
}