{
  "type": "Feature",
  "properties": {
    "iso:country":"US",
    "sg:address":"33288 Little Reb Pl",
    "sg:city":"Menifee",
    "sg:classifiers":[
        {
            "category":"Wholesale",
            "subcategory":"Non-durable Goods",
            "type":"Manufacturing & Wholesale Goods"
        }
    ],
    "sg:phone":"+1 951 679 0884",
    "sg:postcode":"92584",
    "sg:province":"CA",
    "wof:name":"Red Barn Basket Company",
    "wof:placetype":"venue"
},
  "geometry": {"coordinates":[-117.164323,33.635804],"type":"Point"}
}