{
  "type": "Feature",
  "properties": {
    "iso:country":"US",
    "sg:address":"2209 Chico Ave",
    "sg:city":"South El Monte",
    "sg:classifiers":[
        {
            "category":"Wholesale",
            "subcategory":"Groceries",
            "type":"Manufacturing & Wholesale Goods"
        }
    ],
    "sg:phone":"+1 626 579 1296",
    "sg:postcode":"91733",
    "sg:province":"CA",
    "sg:tags":[
        "food",
        "product"
    ],
    "wof:name":"Ho Shun Lee Company",
    "wof:placetype":"venue"
},
  "geometry": {"coordinates":[-118.06006499999999,34.052881],"type":"Point"}
}