{
  "type": "Feature",
  "properties": {
    "addr:full":"1017 MacDonald Ave Richmond CA 94801",
    "addr:housenumber":"1017",
    "addr:postcode":"94801",
    "addr:street":"Macdonald Ave",
    "iso:country":"US",
    "sg:address":"1017 MacDonald Ave",
    "sg:city":"Richmond",
    "sg:classifiers":[
        {
            "category":"Professional",
            "subcategory":"Lawyer & Legal Services",
            "type":"Services"
        }
    ],
    "sg:phone":"+1 925 372 8209",
    "sg:postcode":"94801",
    "sg:province":"CA",
    "wof:name":"Legal Services Foundation Contra Costa",
    "wof:placetype":"venue"
},
  "geometry": {"coordinates":[-122.360001,37.935902],"type":"Point"}
}