{
  "type": "Feature",
  "properties": {
    "iso:country":"US",
    "sg:address":"2632 Myrtle Ave",
    "sg:city":"San Diego",
    "sg:classifiers":[
        {
            "category":"Shopping",
            "subcategory":"Gifts & Souvenirs",
            "type":"Retail Goods"
        }
    ],
    "sg:phone":"+1 619 546 4513",
    "sg:postcode":"92104",
    "sg:province":"CA",
    "sg:tags":[
        "arts",
        "craft",
        "handmade"
    ],
    "wof:name":"Thread & Spirit",
    "wof:placetype":"venue"
},
  "geometry": {"coordinates":[-117.134981,32.742215],"type":"Point"}
}