{
  "type": "Feature",
  "properties": {
    "addr:full":"7940 Limonite Ave Riverside CA 92509",
    "addr:housenumber":"7940",
    "addr:postcode":"92509",
    "addr:street":"Limonite Ave",
    "iso:country":"US",
    "sg:address":"7940 Limonite Ave",
    "sg:city":"Riverside",
    "sg:classifiers":[
        {
            "category":"Restaurant",
            "type":"Food & Drink"
        }
    ],
    "sg:phone":"+1 951 681 2600",
    "sg:postcode":"92509",
    "sg:province":"CA",
    "wof:name":"Taco Bell",
    "wof:placetype":"venue"
},
  "geometry": {"coordinates":[-117.466661,33.975708],"type":"Point"}
}