{
  "type": "Feature",
  "properties": {
    "addr:full":"710 Epperson Dr City Of Industry CA 91748",
    "addr:housenumber":"710",
    "addr:postcode":"91748",
    "addr:street":"Epperson Dr",
    "iso:country":"US",
    "sg:address":"710 Epperson Dr",
    "sg:city":"City Of Industry",
    "sg:classifiers":[
        {
            "category":"Manufacturing",
            "subcategory":"Food",
            "type":"Manufacturing & Wholesale Goods"
        }
    ],
    "sg:phone":"+1 626 964 5797",
    "sg:postcode":"91748",
    "sg:province":"CA",
    "sg:tags":[
        "frozen",
        "dessert",
        "ice",
        "cream"
    ],
    "wof:name":"Haagen-Dazs Ice Cream",
    "wof:placetype":"venue"
},
  "geometry": {"coordinates":[-117.895247,34.001492],"type":"Point"}
}