{
  "type": "Feature",
  "properties": {
    "iso:country":"US",
    "sg:address":"1139 Virginia St",
    "sg:city":"Berkeley",
    "sg:classifiers":[
        {
            "category":"Manufacturing",
            "subcategory":"Metals",
            "type":"Manufacturing & Wholesale Goods"
        }
    ],
    "sg:phone":"+1 510 528 2562",
    "sg:postcode":"94702",
    "sg:province":"CA",
    "sg:tags":[
        "steel",
        "distributor",
        "mill",
        "warehouse"
    ],
    "wof:name":"Johnny Steele Com",
    "wof:placetype":"venue"
},
  "geometry": {"coordinates":[-122.292089,37.873641],"type":"Point"}
}