{
  "type": "Feature",
  "properties": {
    "iso:country":"US",
    "sg:address":"625 Broadway Ste 1210",
    "sg:city":"San Diego",
    "sg:classifiers":[
        {
            "category":"Professional",
            "subcategory":"Lawyer & Legal Services",
            "type":"Services"
        }
    ],
    "sg:phone":"+1 858 587 2510",
    "sg:postcode":"92101",
    "sg:province":"CA",
    "wof:name":"Biotech Beach Law",
    "wof:placetype":"venue"
},
  "geometry": {"coordinates":[-117.15900000000001,32.715525],"type":"Point"}
}