{
  "type": "Feature",
  "properties": {
    "addr:full":"1164 Solano Ave 106 Albany CA 94706",
    "addr:housenumber":"1164;106",
    "addr:postcode":"94706",
    "addr:street":"Solano Ave",
    "iso:country":"US",
    "sg:address":"1164 Solano Ave 106",
    "sg:city":"Albany",
    "sg:classifiers":[
        {
            "category":"Autos & Motor Vehicles",
            "subcategory":"Automobile Sales",
            "type":"Retail Goods"
        }
    ],
    "sg:phone":"+1 415 725 8910",
    "sg:postcode":"94706",
    "sg:province":"CA",
    "sg:tags":[
        "limo"
    ],
    "sg:website":"citysightslimo.com",
    "wof:name":"City Sights Limo",
    "wof:placetype":"venue"
},
  "geometry": {"coordinates":[-122.296691,37.890394],"type":"Point"}
}