{
  "type": "Feature",
  "properties": {
    "iso:country":"US",
    "sg:address":"2458 Whipple Rd",
    "sg:city":"Hayward",
    "sg:classifiers":[
        {
            "category":"Retail",
            "subcategory":"Auto Repair",
            "type":"Services"
        }
    ],
    "sg:phone":"+1 800 996 8782",
    "sg:postcode":"94544",
    "sg:province":"CA",
    "sg:tags":[
        "truck"
    ],
    "wof:name":"California Fleet Maintenance",
    "wof:placetype":"venue"
},
  "geometry": {"coordinates":[-122.06282,37.60682],"type":"Point"}
}