{
  "type": "Feature",
  "properties": {
    "addr:full":"60 E 3rd Avenue Suite 300 San Mateo CA 94401",
    "addr:housenumber":"60",
    "addr:postcode":"94401",
    "addr:street":"E 3Rd Avenue Suite 300",
    "iso:country":"US",
    "sg:address":"60 E 3rd Avenue Suite 300",
    "sg:city":"San Mateo",
    "sg:classifiers":[
        {
            "category":"Real Estate",
            "subcategory":"Architect",
            "type":"Services"
        }
    ],
    "sg:phone":"+1 650 579 0995",
    "sg:postcode":"94401",
    "sg:province":"CA",
    "wof:name":"Gumbinger Avram Architects",
    "wof:placetype":"venue"
},
  "geometry": {"coordinates":[-122.324816,37.563816],"type":"Point"}
}