{
  "type": "Feature",
  "properties": {
    "addr:full":"333 S Auburn St Colfax CA 95713",
    "addr:housenumber":"333",
    "addr:postcode":"95713",
    "addr:street":"S Auburn St",
    "iso:country":"US",
    "sg:address":"333 S Auburn St",
    "sg:city":"Colfax",
    "sg:classifiers":[
        {
            "category":"Health Services",
            "subcategory":"Optometrist",
            "type":"Services"
        }
    ],
    "sg:phone":"+1 530 346 2269",
    "sg:postcode":"95713",
    "sg:province":"CA",
    "wof:name":"Colfax Vision Ctr Optometric",
    "wof:placetype":"venue"
},
  "geometry": {"coordinates":[-120.951086,39.097531],"type":"Point"}
}