{
  "type": "Feature",
  "properties": {
    "addr:full":"11110 Los Alamitos Blvd Los Alamitos CA 90720",
    "addr:housenumber":"11110",
    "addr:postcode":"90720",
    "addr:street":"Los Alamitos Blvd",
    "iso:country":"US",
    "sg:address":"11110 Los Alamitos Blvd",
    "sg:city":"Los Alamitos",
    "sg:classifiers":[
        {
            "category":"Professional",
            "type":"Services"
        }
    ],
    "sg:phone":"+1 562 430 3377",
    "sg:postcode":"90720",
    "sg:province":"CA",
    "wof:name":"Luz Delsol Inc",
    "wof:placetype":"venue"
},
  "geometry": {"coordinates":[-118.07188499999999,33.800858],"type":"Point"}
}