{
  "type": "Feature",
  "properties": {
    "iso:country":"US",
    "sg:address":"520 Alisha Ln",
    "sg:city":"Tracy",
    "sg:classifiers":[
        {
            "category":"Social Services",
            "subcategory":"Child Care",
            "type":"Services"
        }
    ],
    "sg:phone":"+1 209 833 7504",
    "sg:postcode":"95376",
    "sg:province":"CA",
    "wof:name":"Jingle Bells Day Care",
    "wof:placetype":"venue"
},
  "geometry": {"coordinates":[-121.417222,37.722675],"type":"Point"}
}