{
  "type": "Feature",
  "properties": {
    "iso:country":"US",
    "sg:address":"6626 Hayvenhurst Ave",
    "sg:city":"Van Nuys",
    "sg:classifiers":[
        {
            "category":"Real Estate",
            "subcategory":"Real Estate Operator",
            "type":"Services"
        }
    ],
    "sg:phone":"+1 818 989 4343",
    "sg:postcode":"91406",
    "sg:province":"CA",
    "sg:tags":[
        "apartment"
    ],
    "wof:name":"Balboa Point Apartments",
    "wof:placetype":"venue"
},
  "geometry": {"coordinates":[-118.492308,34.192406],"type":"Point"}
}