{
  "type": "Feature",
  "properties": {
    "addr:full":"37 N San Pedro St San Jose CA 95113",
    "addr:housenumber":"37",
    "addr:postcode":"95113",
    "addr:street":"N San Pedro St",
    "iso:country":"US",
    "sg:address":"37 N San Pedro St",
    "sg:city":"San Jose",
    "sg:classifiers":[
        {
            "category":"Coffee & Tea",
            "type":"Food & Drink"
        }
    ],
    "sg:phone":"+1 408 772 4500",
    "sg:postcode":"95113",
    "sg:province":"CA",
    "sg:website":"teagre.com",
    "wof:name":"Teagre",
    "wof:placetype":"venue"
},
  "geometry": {"coordinates":[-121.893388,37.335764],"type":"Point"}
}