{
  "type": "Feature",
  "properties": {
    "iso:country":"US",
    "sg:address":"5670 Wilshire Blvd",
    "sg:city":"Los Angeles",
    "sg:classifiers":[
        {
            "category":"Insurance",
            "subcategory":"Insurance Agent",
            "type":"Services"
        }
    ],
    "sg:phone":"+1 323 932 7013",
    "sg:postcode":"90036",
    "sg:province":"CA",
    "wof:name":"Bernstein Insurance Svc",
    "wof:placetype":"venue"
},
  "geometry": {"coordinates":[-118.352197,34.062255],"type":"Point"}
}