{
  "type": "Feature",
  "properties": {
    "iso:country":"US",
    "sg:address":"1830 Brundage Ln",
    "sg:city":"Bakersfield",
    "sg:classifiers":[
        {
            "category":"Real Estate",
            "subcategory":"Real Estate Agent",
            "type":"Services"
        }
    ],
    "sg:phone":"+1 661 324 4561",
    "sg:postcode":"93304",
    "sg:province":"CA",
    "sg:tags":[
        "management"
    ],
    "wof:name":"SJR Properties",
    "wof:placetype":"venue"
},
  "geometry": {"coordinates":[-119.022036,35.35404],"type":"Point"}
}