{
  "type": "Feature",
  "properties": {
    "addr:full":"1098 Foster City Blvd Foster City CA 94404",
    "addr:housenumber":"1098",
    "addr:postcode":"94404",
    "addr:street":"Foster City Blvd",
    "iso:country":"US",
    "sg:address":"1098 Foster City Blvd",
    "sg:city":"Foster City",
    "sg:classifiers":[
        {
            "category":"Real Estate",
            "subcategory":"Real Estate Services",
            "type":"Services"
        }
    ],
    "sg:phone":"+1 650 357 9030",
    "sg:postcode":"94404",
    "sg:province":"CA",
    "sg:tags":[
        "company",
        "title"
    ],
    "wof:name":"Fidelity National Title",
    "wof:placetype":"venue"
},
  "geometry": {"coordinates":[-122.25877800000001,37.553934],"type":"Point"}
}