{
  "type": "Feature",
  "properties": {
    "addr:full":"842 N Fairfax Ave Los Angeles CA 90046",
    "addr:housenumber":"842",
    "addr:postcode":"90046",
    "addr:street":"N Fairfax Ave",
    "iso:country":"US",
    "sg:address":"842 N Fairfax Ave",
    "sg:city":"Los Angeles",
    "sg:classifiers":[
        {
            "category":"Arts & Performance",
            "subcategory":"Art Gallery",
            "type":"Entertainment"
        }
    ],
    "sg:phone":"+1 323 658 6348",
    "sg:postcode":"90046",
    "sg:province":"CA",
    "wof:name":"Madam One",
    "wof:placetype":"venue"
},
  "geometry": {"coordinates":[-118.361,34.0868],"type":"Point"}
}