{
  "type": "Feature",
  "properties": {
    "addr:full":"601 E Arrellaga St Santa Barbara CA 93103",
    "addr:housenumber":"601",
    "addr:postcode":"93103",
    "addr:street":"E Arrellaga St",
    "iso:country":"US",
    "sg:address":"601 E Arrellaga St",
    "sg:city":"Santa Barbara",
    "sg:classifiers":[
        {
            "category":"Health Services",
            "subcategory":"Doctor",
            "type":"Services"
        }
    ],
    "sg:phone":"+1 805 963 2029",
    "sg:postcode":"93103",
    "sg:province":"CA",
    "sg:tags":[
        "physician",
        "surgeon"
    ],
    "wof:name":"Santa Barbara Pulmonary",
    "wof:placetype":"venue"
},
  "geometry": {"coordinates":[-119.703913,34.432396],"type":"Point"}
}