{
  "type": "Feature",
  "properties": {
    "iso:country":"US",
    "sg:address":"2363 Needham Rd",
    "sg:city":"El Cajon",
    "sg:classifiers":[
        {
            "category":"Insurance",
            "subcategory":"Insurance Agent",
            "type":"Services"
        }
    ],
    "sg:phone":"+1 619 464 3825",
    "sg:postcode":"92020",
    "sg:province":"CA",
    "wof:name":"Lumber Insurance Co",
    "wof:placetype":"venue"
},
  "geometry": {"coordinates":[-116.997099,32.803351],"type":"Point"}
}