{
  "type": "Feature",
  "properties": {
    "addr:full":"949 Kings Rd Ste 306 West Hollywood CA 90069",
    "addr:housenumber":"949",
    "addr:postcode":"90069",
    "addr:street":"Kings Rd Ste 306",
    "iso:country":"US",
    "sg:address":"949 Kings Rd Ste 306",
    "sg:city":"West Hollywood",
    "sg:classifiers":[
        {
            "category":"Personal",
            "type":"Services"
        }
    ],
    "sg:phone":"+1 323 712 1250",
    "sg:postcode":"90069",
    "sg:province":"CA",
    "sg:tags":[
        "party",
        "planning",
        "event"
    ],
    "sg:website":"www.facebook.com",
    "wof:name":"Miguel's Martinis and More Bartending Service",
    "wof:placetype":"venue"
},
  "geometry": {"coordinates":[-118.372162,34.088503],"type":"Point"}
}