{
  "type": "Feature",
  "properties": {
    "iso:country":"US",
    "sg:address":"1535 Tidelands Ave",
    "sg:city":"National City",
    "sg:classifiers":[
        {
            "category":"Manufacturing",
            "subcategory":"Furniture",
            "type":"Manufacturing & Wholesale Goods"
        },
        {
            "category":"Building & Trades",
            "subcategory":"Construction",
            "type":"Services"
        }
    ],
    "sg:phone":"+1 619 474 5102",
    "sg:postcode":"91950",
    "sg:province":"CA",
    "sg:tags":[
        "cabinet",
        "maker",
        "custom"
    ],
    "wof:name":"Courington Woodworks Inc",
    "wof:placetype":"venue"
},
  "geometry": {"coordinates":[-117.11529400000001,32.664081],"type":"Point"}
}