{
  "type": "Feature",
  "properties": {
    "iso:country":"US",
    "sg:address":"16902 Cod Cir",
    "sg:city":"Huntington Beach",
    "sg:classifiers":[
        {
            "category":"Shopping",
            "subcategory":"Crafts & Fabrics",
            "type":"Retail Goods"
        }
    ],
    "sg:phone":"+1 714 847 0517",
    "sg:postcode":"92647",
    "sg:province":"CA",
    "sg:tags":[
        "sewing"
    ],
    "wof:name":"Technical Fabric Solutions",
    "wof:placetype":"venue"
},
  "geometry": {"coordinates":[-118.012568,33.716314],"type":"Point"}
}