{
  "type": "Feature",
  "properties": {
    "iso:country":"US",
    "sg:address":"9242 Airdrome Street",
    "sg:city":"Los Angeles",
    "sg:classifiers":[
        {
            "category":"Communications",
            "type":"Services"
        }
    ],
    "sg:phone":"+1 310 275 5260",
    "sg:postcode":"90035",
    "sg:province":"CA",
    "sg:tags":[
        "recording",
        "rehearsal",
        "studio"
    ],
    "wof:name":"Besterman Douglas",
    "wof:placetype":"venue"
},
  "geometry": {"coordinates":[-118.390616,34.049909],"type":"Point"}
}