{
  "type": "Feature",
  "properties": {
    "iso:country":"US",
    "sg:address":"2939 Alta View Dr",
    "sg:city":"San Diego",
    "sg:classifiers":[
        {
            "category":"Wholesale",
            "subcategory":"Hardware",
            "type":"Manufacturing & Wholesale Goods"
        }
    ],
    "sg:phone":"+1 619 479 7739",
    "sg:postcode":"92139",
    "sg:province":"CA",
    "sg:tags":[
        "water",
        "cooler",
        "fountain",
        "filter"
    ],
    "wof:name":"Pure Water Plus 4",
    "wof:placetype":"venue"
},
  "geometry": {"coordinates":[-117.037982,32.676326],"type":"Point"}
}