{
  "type": "Feature",
  "properties": {
    "addr:full":"443 S Gramercy Pl Los Angeles CA 90020",
    "addr:housenumber":"443",
    "addr:postcode":"90020",
    "addr:street":"S Gramercy Pl",
    "iso:country":"US",
    "sg:address":"443 S Gramercy Pl",
    "sg:city":"Los Angeles",
    "sg:classifiers":[
        {
            "category":"Retail",
            "subcategory":"Repair Shop",
            "type":"Services"
        }
    ],
    "sg:phone":"+1 323 766 0009",
    "sg:postcode":"90020",
    "sg:province":"CA",
    "sg:tags":[
        "repairing",
        "vault",
        "safe"
    ],
    "wof:name":"Hana Locksmiths",
    "wof:placetype":"venue"
},
  "geometry": {"coordinates":[-118.312893,34.066103],"type":"Point"}
}