{
  "type": "Feature",
  "properties": {
    "iso:country":"US",
    "sg:address":"7601 Sandholdt Rd",
    "sg:city":"Moss Landing",
    "sg:classifiers":[
        {
            "category":"Professional",
            "type":"Services"
        }
    ],
    "sg:phone":"+1 831 633 8530",
    "sg:postcode":"95039",
    "sg:province":"CA",
    "sg:tags":[
        "establishment"
    ],
    "wof:name":"Del Mar Seafoods Inc",
    "wof:placetype":"venue"
},
  "geometry": {"coordinates":[-121.78776999999999,36.800152],"type":"Point"}
}