{
  "type": "Feature",
  "properties": {
    "iso:country":"US",
    "sg:address":"6077 Big Bend Rd",
    "sg:city":"Oroville",
    "sg:classifiers":[
        {
            "category":"Manufacturing",
            "subcategory":"Soap",
            "type":"Manufacturing & Wholesale Goods"
        }
    ],
    "sg:phone":"+1 530 519 5311",
    "sg:postcode":"95965",
    "sg:province":"CA",
    "sg:tags":[
        "detergent"
    ],
    "wof:name":"Smith's House Of Soap",
    "wof:placetype":"venue"
},
  "geometry": {"coordinates":[-121.44336300000001,39.69565],"type":"Point"}
}