{
  "type": "Feature",
  "properties": {
    "iso:country":"US",
    "sg:address":"1483 67th St",
    "sg:city":"Emeryville",
    "sg:classifiers":[
        {
            "category":"Home & Garden",
            "subcategory":"Building Materials",
            "type":"Retail Goods"
        },
        {
            "category":"Train Station",
            "subcategory":"Rail",
            "type":"Transportation"
        }
    ],
    "sg:phone":"+1 510 601 9916",
    "sg:postcode":"94608",
    "sg:province":"CA",
    "sg:tags":[
        "stairway",
        "railing",
        "rails",
        "accessory"
    ],
    "wof:name":"Jayco Hawaii-California",
    "wof:placetype":"venue"
},
  "geometry": {"coordinates":[-122.29476699999999,37.848314],"type":"Point"}
}