{
  "type": "Feature",
  "properties": {
    "iso:country":"US",
    "sg:address":"18571 Valley Blvd",
    "sg:city":"Bloomington",
    "sg:classifiers":[
        {
            "category":"Retail",
            "subcategory":"Laundry & Dry Cleaning",
            "type":"Services"
        }
    ],
    "sg:phone":"+1 909 877 9024",
    "sg:postcode":"92316",
    "sg:province":"CA",
    "sg:tags":[
        "curtain",
        "drapery",
        "cleaners"
    ],
    "wof:name":"Valley Cleaners",
    "wof:placetype":"venue"
},
  "geometry": {"coordinates":[-117.39788900000001,34.070403],"type":"Point"}
}