{
  "type": "Feature",
  "properties": {
    "addr:full":"423 Garnet Way Santa Maria CA 93454",
    "addr:housenumber":"423",
    "addr:postcode":"93454",
    "addr:street":"Garnet Way",
    "iso:country":"US",
    "sg:address":"423 Garnet Way",
    "sg:city":"Santa Maria",
    "sg:classifiers":[
        {
            "category":"Real Estate",
            "subcategory":"Real Estate Agent",
            "type":"Services"
        }
    ],
    "sg:phone":"+1 805 346 2122",
    "sg:postcode":"93454",
    "sg:province":"CA",
    "sg:tags":[
        "inspection"
    ],
    "wof:name":"Professional Home Inspections",
    "wof:placetype":"venue"
},
  "geometry": {"coordinates":[-120.413016,34.957029],"type":"Point"}
}