{
  "type": "Feature",
  "properties": {
    "iso:country":"US",
    "sg:address":"1250 Howe Avenue #3A",
    "sg:city":"Sacramento",
    "sg:classifiers":[
        {
            "category":"Shopping",
            "subcategory":"Hobbies, Toys, & Games",
            "type":"Retail Goods"
        },
        {
            "category":"Shopping",
            "subcategory":"Comic Books",
            "type":"Retail Goods"
        }
    ],
    "sg:phone":"+1 916 927 0810",
    "sg:postcode":"95825",
    "sg:province":"CA",
    "sg:tags":[
        "shop",
        "hobby",
        "toy",
        "store"
    ],
    "sg:website":"www.greatescapegames.com/",
    "wof:name":"Great Escape Games",
    "wof:placetype":"venue"
},
  "geometry": {"coordinates":[-121.41379999999999,38.587917],"type":"Point"}
}