{
  "type": "Feature",
  "properties": {
    "addr:full":"2821 Menlo Ave Los Angeles CA 90007",
    "addr:housenumber":"2821",
    "addr:postcode":"90007",
    "addr:street":"Menlo Ave",
    "iso:country":"US",
    "sg:address":"2821 Menlo Ave",
    "sg:city":"Los Angeles",
    "sg:classifiers":[
        {
            "category":"Organizations",
            "subcategory":"Religious Organization",
            "type":"Services"
        }
    ],
    "sg:phone":"+1 323 734 1397",
    "sg:postcode":"90007",
    "sg:province":"CA",
    "sg:tags":[
        "church"
    ],
    "wof:name":"Western Spanish Jehovah's",
    "wof:placetype":"venue"
},
  "geometry": {"coordinates":[-118.29039299999999,34.029068],"type":"Point"}
}