{
  "type": "Feature",
  "properties": {
    "iso:country":"US",
    "sg:address":"909 Soule Street",
    "sg:city":"West Sacramento",
    "sg:classifiers":[
        {
            "category":"Retail",
            "subcategory":"Auto Repair",
            "type":"Services"
        }
    ],
    "sg:phone":"+1 916 371 1821",
    "sg:postcode":"95691",
    "sg:province":"CA",
    "wof:name":"Jack's",
    "wof:placetype":"venue"
},
  "geometry": {"coordinates":[-121.52309099999999,38.576219],"type":"Point"}
}