{
  "type": "Feature",
  "properties": {
    "iso:country":"US",
    "sg:address":"3386 S Bristol St",
    "sg:city":"Santa Ana",
    "sg:classifiers":[
        {
            "category":"Professional",
            "type":"Services"
        }
    ],
    "sg:phone":"+1 714 434 1272",
    "sg:postcode":"92704",
    "sg:province":"CA",
    "wof:name":"Lemon",
    "wof:placetype":"venue"
},
  "geometry": {"coordinates":[-117.885699,33.702319],"type":"Point"}
}