{
  "type": "Feature",
  "properties": {
    "addr:full":"1000 N Broadway Santa Maria CA 93454",
    "addr:housenumber":"1000",
    "addr:postcode":"93454",
    "addr:street":"N Broadway",
    "iso:country":"US",
    "sg:address":"1000 N Broadway",
    "sg:city":"Santa Maria",
    "sg:classifiers":[
        {
            "category":"Food & Beverages",
            "subcategory":"Groceries & Convenience Stores",
            "type":"Retail Goods"
        }
    ],
    "sg:phone":"+1 805 214 9505",
    "sg:postcode":"93454",
    "sg:province":"CA",
    "wof:name":"MI Terra LLC",
    "wof:placetype":"venue"
},
  "geometry": {"coordinates":[-120.435655,34.963248],"type":"Point"}
}