{
  "type": "Feature",
  "properties": {
    "iso:country":"US",
    "sg:address":"10814 Jefferson Blvd",
    "sg:city":"Culver City",
    "sg:classifiers":[
        {
            "category":"Restaurant",
            "type":"Food & Drink"
        }
    ],
    "sg:phone":"+1 310 204 2659",
    "sg:postcode":"90230",
    "sg:province":"CA",
    "wof:name":"Campos Tacos",
    "wof:placetype":"venue"
},
  "geometry": {"coordinates":[-118.394997,34.001701],"type":"Point"}
}