{
  "type": "Feature",
  "properties": {
    "iso:country":"US",
    "sg:address":"500 Sutter St Ste 509",
    "sg:city":"San Francisco",
    "sg:classifiers":[
        {
            "category":"Personal",
            "subcategory":"Hair Removal",
            "type":"Services"
        },
        {
            "category":"Personal",
            "subcategory":"Nail Salon",
            "type":"Services"
        }
    ],
    "sg:phone":"+1 415 568 5085",
    "sg:postcode":"94102",
    "sg:province":"CA",
    "wof:name":"Pampered Nail by Tammy",
    "wof:placetype":"venue"
},
  "geometry": {"coordinates":[-122.40889300000001,37.789439],"type":"Point"}
}