{
  "type": "Feature",
  "properties": {
    "iso:country":"US",
    "sg:address":"1403 Foothill Blvd",
    "sg:city":"La Verne",
    "sg:classifiers":[
        {
            "category":"Professional",
            "subcategory":"Accounting & Tax Preparation",
            "type":"Services"
        }
    ],
    "sg:phone":"+1 909 593 0355",
    "sg:postcode":"91750",
    "sg:province":"CA",
    "sg:tags":[
        "return",
        "filing"
    ],
    "wof:name":"Anderson Tax Svc",
    "wof:placetype":"venue"
},
  "geometry": {"coordinates":[-117.775734,34.116892],"type":"Point"}
}