{
  "type": "Feature",
  "properties": {
    "addr:full":"4924 Helen Way Sacramento CA 95822",
    "addr:housenumber":"4924",
    "addr:postcode":"95822",
    "addr:street":"Helen Way",
    "iso:country":"US",
    "sg:address":"4924 Helen Way",
    "sg:city":"Sacramento",
    "sg:classifiers":[
        {
            "category":"Building & Trades",
            "subcategory":"Construction",
            "type":"Services"
        }
    ],
    "sg:phone":"+1 916 451 6856",
    "sg:postcode":"95822",
    "sg:province":"CA",
    "sg:tags":[
        "general",
        "contractor"
    ],
    "wof:name":"Dawson Construction & Design",
    "wof:placetype":"venue"
},
  "geometry": {"coordinates":[-121.493359,38.529005],"type":"Point"}
}