{
  "type": "Feature",
  "properties": {
    "addr:full":"19 S San Joaquin St Stockton CA 95202",
    "addr:housenumber":"19",
    "addr:postcode":"95202",
    "addr:street":"S San Joaquin St",
    "iso:country":"US",
    "sg:address":"19 S San Joaquin St",
    "sg:city":"Stockton",
    "sg:classifiers":[
        {
            "category":"Deli",
            "type":"Food & Drink"
        }
    ],
    "sg:phone":"+1 209 463 6304",
    "sg:postcode":"95202",
    "sg:province":"CA",
    "sg:tags":[
        "delicatessen"
    ],
    "wof:name":"Yvettes Bakery Cafe",
    "wof:placetype":"venue"
},
  "geometry": {"coordinates":[-121.287156,37.952953],"type":"Point"}
}