{
  "type": "Feature",
  "properties": {
    "addr:full":"2431 Peralta St Oakland CA 94607",
    "addr:housenumber":"2431",
    "addr:postcode":"94607",
    "addr:street":"Peralta St",
    "iso:country":"US",
    "sg:address":"2431 Peralta St",
    "sg:city":"Oakland",
    "sg:classifiers":[
        {
            "category":"Wholesale",
            "subcategory":"Sporting Goods",
            "type":"Manufacturing & Wholesale Goods"
        }
    ],
    "sg:phone":"+1 510 774 4384",
    "sg:postcode":"94607",
    "sg:province":"CA",
    "wof:name":"Trips 2 Win Racing",
    "wof:placetype":"venue"
},
  "geometry": {"coordinates":[-122.287578,37.819585],"type":"Point"}
}