{
  "type": "Feature",
  "properties": {
    "iso:country":"US",
    "sg:address":"5178 Brooks St",
    "sg:city":"Montclair",
    "sg:classifiers":[
        {
            "category":"Farming",
            "subcategory":"Livestock Farm",
            "type":"Manufacturing & Wholesale Goods"
        }
    ],
    "sg:phone":"+1 909 398 4663",
    "sg:postcode":"91763",
    "sg:province":"CA",
    "sg:tags":[
        "reptile"
    ],
    "wof:name":"Southland Reptiles",
    "wof:placetype":"venue"
},
  "geometry": {"coordinates":[-117.695971,34.061759],"type":"Point"}
}