{
  "type": "Feature",
  "properties": {
    "addr:full":"1065 University Ave San Diego CA 92103",
    "addr:housenumber":"1065",
    "addr:postcode":"92103",
    "addr:street":"University Ave",
    "iso:country":"US",
    "sg:address":"1065 University Ave",
    "sg:city":"San Diego",
    "sg:classifiers":[
        {
            "category":"Professional",
            "subcategory":"Printing & Photocopies",
            "type":"Services"
        }
    ],
    "sg:phone":"+1 619 295 4112",
    "sg:postcode":"92103",
    "sg:province":"CA",
    "sg:tags":[
        "blueprinting"
    ],
    "wof:name":"Mayer Reprographics",
    "wof:placetype":"venue"
},
  "geometry": {"coordinates":[-117.154005,32.748399],"type":"Point"}
}