{
  "type": "Feature",
  "properties": {
    "addr:full":"1839 W 6th St Los Angeles CA 90057",
    "addr:housenumber":"1839",
    "addr:postcode":"90057",
    "addr:street":"W 6Th St",
    "iso:country":"US",
    "sg:address":"1839 W 6th St",
    "sg:city":"Los Angeles",
    "sg:classifiers":[
        {
            "category":"Food & Beverages",
            "subcategory":"Groceries & Convenience Stores",
            "type":"Retail Goods"
        }
    ],
    "sg:phone":"+1 213 484 1124",
    "sg:postcode":"90057",
    "sg:province":"CA",
    "wof:name":"Angeles Market",
    "wof:placetype":"venue"
},
  "geometry": {"coordinates":[-118.272003,34.0583],"type":"Point"}
}