{
  "type": "Feature",
  "properties": {
    "addr:full":"9538 Gunn Ave Whittier CA 90605",
    "addr:housenumber":"9538",
    "addr:postcode":"90605",
    "addr:street":"Gunn Ave",
    "iso:country":"US",
    "sg:address":"9538 Gunn Ave",
    "sg:city":"Whittier",
    "sg:classifiers":[
        {
            "category":"Wholesale",
            "subcategory":"Hardware",
            "type":"Manufacturing & Wholesale Goods"
        }
    ],
    "sg:phone":"+1 562 755 3717",
    "sg:postcode":"90605",
    "sg:province":"CA",
    "sg:tags":[
        "plumbing",
        "distribution",
        "fixture",
        "rep"
    ],
    "wof:name":"Imperial Sales Distribution",
    "wof:placetype":"venue"
},
  "geometry": {"coordinates":[-118.026201,33.948189],"type":"Point"}
}