{
  "type": "Feature",
  "properties": {
    "iso:country":"US",
    "sg:address":"1047 Mettler Frontage Rd W",
    "sg:city":"Bakersfield",
    "sg:classifiers":[
        {
            "category":"Restaurant",
            "type":"Food & Drink"
        }
    ],
    "sg:phone":"+1 661 858 2979",
    "sg:postcode":"93313",
    "sg:province":"CA",
    "sg:tags":[
        "delicatessen"
    ],
    "wof:name":"Day & Night Market",
    "wof:placetype":"venue"
},
  "geometry": {"coordinates":[-118.97484,35.077856],"type":"Point"}
}