{
  "type": "Feature",
  "properties": {
    "addr:full":"8580 Sunset Blvd West Hollywood CA 90069",
    "addr:housenumber":"8580",
    "addr:postcode":"90069",
    "addr:street":"Sunset Blvd",
    "iso:country":"US",
    "sg:address":"8580 Sunset Blvd",
    "sg:city":"West Hollywood",
    "sg:classifiers":[
        {
            "category":"Shopping",
            "subcategory":"Clothing, Apparel, & Fashions",
            "type":"Retail Goods"
        }
    ],
    "sg:phone":"+1 310 855 9683",
    "sg:postcode":"90069",
    "sg:province":"CA",
    "sg:tags":[
        "clothing",
        "women's"
    ],
    "sg:website":"www.hm.com/us/#/startpagedefault/",
    "wof:name":"H & M",
    "wof:placetype":"venue"
},
  "geometry": {"coordinates":[-118.378828,34.092774],"type":"Point"}
}