{
  "type": "Feature",
  "properties": {
    "iso:country":"US",
    "sg:address":"5301 Beethoven St",
    "sg:city":"Los Angeles",
    "sg:classifiers":[
        {
            "category":"Professional",
            "subcategory":"Accounting & Tax Preparation",
            "type":"Services"
        }
    ],
    "sg:phone":"+1 310 821 3513",
    "sg:postcode":"90066",
    "sg:province":"CA",
    "sg:tags":[
        "accountant"
    ],
    "wof:name":"Howard Ernest F CPA",
    "wof:placetype":"venue"
},
  "geometry": {"coordinates":[-118.42364,33.978818],"type":"Point"}
}