{
  "type": "Feature",
  "properties": {
    "addr:full":"1 City Blvd W Orange CA 92868",
    "addr:housenumber":"1",
    "addr:postcode":"92868",
    "addr:street":"City Blvd W",
    "iso:country":"US",
    "sg:address":"1 City Blvd W",
    "sg:city":"Orange",
    "sg:classifiers":[
        {
            "category":"Banks & Credit Unions",
            "subcategory":"Bank",
            "type":"Services"
        }
    ],
    "sg:phone":"+1 714 456 9010",
    "sg:postcode":"92868",
    "sg:province":"CA",
    "sg:tags":[
        "financing"
    ],
    "wof:name":"Americredit Financial Svc",
    "wof:placetype":"venue"
},
  "geometry": {"coordinates":[-117.894263,33.780122],"type":"Point"}
}