{
  "type": "Feature",
  "properties": {
    "addr:full":"Pier 40 San Francisco CA 94107",
    "addr:postcode":"94107",
    "iso:country":"US",
    "sg:address":"Pier 40",
    "sg:city":"San Francisco",
    "sg:classifiers":[
        {
            "category":"Bars & Pubs",
            "subcategory":"Nightclub",
            "type":"Food & Drink"
        }
    ],
    "sg:phone":"+1 415 320 6693",
    "sg:postcode":"94107",
    "sg:province":"CA",
    "sg:tags":[
        "nightlife"
    ],
    "sg:website":"www.amidnightaffair.com",
    "wof:name":"Blended Events - A Midnight Affair NYE Party",
    "wof:placetype":"venue"
},
  "geometry": {"coordinates":[-122.386636,37.78169],"type":"Point"}
}