{
  "type": "Feature",
  "properties": {
    "addr:full":"1009 E Capitol Expy San Jose CA 95121",
    "addr:housenumber":"1009",
    "addr:postcode":"95121",
    "addr:street":"E Capitol Expy",
    "iso:country":"US",
    "sg:address":"1009 E Capitol Expy",
    "sg:city":"San Jose",
    "sg:classifiers":[
        {
            "category":"Professional",
            "subcategory":"Management & Consulting",
            "type":"Services"
        }
    ],
    "sg:phone":"+1 408 363 9031",
    "sg:postcode":"95121",
    "sg:province":"CA",
    "sg:tags":[
        "marketing",
        "program"
    ],
    "wof:name":"M & N Marketing Enterprises",
    "wof:placetype":"venue"
},
  "geometry": {"coordinates":[-121.82114799999999,37.300336],"type":"Point"}
}