{
  "type": "Feature",
  "properties": {
    "iso:country":"US",
    "sg:address":"11202 Spruce Ave",
    "sg:city":"Bloomington",
    "sg:classifiers":[
        {
            "category":"Farming",
            "subcategory":"Nursery",
            "type":"Manufacturing & Wholesale Goods"
        }
    ],
    "sg:phone":"+1 909 873 9057",
    "sg:postcode":"92316",
    "sg:province":"CA",
    "sg:tags":[
        "greenhouse"
    ],
    "wof:name":"J & G Growers",
    "wof:placetype":"venue"
},
  "geometry": {"coordinates":[-117.387709,34.04842],"type":"Point"}
}