{
  "type": "Feature",
  "properties": {
    "iso:country":"US",
    "sg:address":"9555 Santa Monica Blvd",
    "sg:city":"Beverly Hills",
    "sg:classifiers":[
        {
            "category":"Health Services",
            "subcategory":"Health Practitioner",
            "type":"Services"
        }
    ],
    "sg:phone":"+1 310 275 3363",
    "sg:postcode":"90210",
    "sg:province":"CA",
    "sg:tags":[
        "therapy",
        "physical"
    ],
    "wof:name":"Octavia Derma Therapy Facialist Armoma Therapist",
    "wof:placetype":"venue"
},
  "geometry": {"coordinates":[-118.404999,34.070301],"type":"Point"}
}