{
  "type": "Feature",
  "properties": {
    "addr:full":"15564 Producer Ln Huntington Beach CA 92649",
    "addr:postcode":"15564;92649",
    "addr:street":"Producer Ln",
    "iso:country":"US",
    "sg:address":"15564 Producer Ln",
    "sg:city":"Huntington Beach",
    "sg:classifiers":[
        {
            "category":"Autos & Motor Vehicles",
            "subcategory":"Auto Supplies",
            "type":"Retail Goods"
        }
    ],
    "sg:phone":"+1 714 892 5050",
    "sg:postcode":"92649",
    "sg:province":"CA",
    "sg:tags":[
        "used",
        "parts"
    ],
    "wof:name":"West Coast Haus",
    "wof:placetype":"venue"
},
  "geometry": {"coordinates":[-118.026032,33.734726],"type":"Point"}
}