{
  "type": "Feature",
  "properties": {
    "iso:country":"US",
    "sg:address":"333 E Nutwood St Ste A",
    "sg:city":"Inglewood",
    "sg:classifiers":[
        {
            "category":"Health Services",
            "subcategory":"Chiropractor",
            "type":"Services"
        }
    ],
    "sg:phone":"+1 310 671 4224",
    "sg:postcode":"90301",
    "sg:province":"CA",
    "sg:tags":[
        "chiropractic"
    ],
    "wof:name":"Nwude Chiropractic Inc.",
    "wof:placetype":"venue"
},
  "geometry": {"coordinates":[-118.351022,33.960637],"type":"Point"}
}