{
  "type": "Feature",
  "properties": {
    "addr:full":"1705 N Main St Orange CA 92868",
    "addr:housenumber":"1705",
    "addr:postcode":"92868",
    "addr:street":"N Main St",
    "iso:country":"US",
    "sg:address":"1705 N Main St",
    "sg:city":"Orange",
    "sg:classifiers":[
        {
            "category":"Manufacturing",
            "subcategory":"Glass & Minerals",
            "type":"Manufacturing & Wholesale Goods"
        }
    ],
    "sg:phone":"+1 714 637 8594",
    "sg:postcode":"92868",
    "sg:province":"CA",
    "sg:tags":[
        "concrete",
        "brick",
        "mfg"
    ],
    "sg:website":"www.angelusblock.com",
    "wof:name":"Angelus Block Co Inc",
    "wof:placetype":"venue"
},
  "geometry": {"coordinates":[-117.867222,33.818978],"type":"Point"}
}