{
  "type": "Feature",
  "properties": {
    "iso:country":"US",
    "sg:address":"2908 E Whitmore Ave",
    "sg:city":"Ceres",
    "sg:classifiers":[
        {
            "category":"Restaurant",
            "type":"Food & Drink"
        }
    ],
    "sg:phone":"+1 209 538 7704",
    "sg:postcode":"95307",
    "sg:province":"CA",
    "sg:tags":[
        "mexican"
    ],
    "wof:name":"La Cascada Mexican Restaurant",
    "wof:placetype":"venue"
},
  "geometry": {"coordinates":[-120.94000200000001,37.5947],"type":"Point"}
}