{
  "type": "Feature",
  "properties": {
    "iso:country":"US",
    "sg:address":"175 Alvarado Ave",
    "sg:city":"Pittsburg",
    "sg:classifiers":[
        {
            "category":"Organizations",
            "subcategory":"Non-profit Organization",
            "type":"Services"
        }
    ],
    "sg:phone":"+1 925 432 3013",
    "sg:postcode":"94565",
    "sg:province":"CA",
    "wof:name":"Lion's Center Visualy Impaired",
    "wof:placetype":"venue"
},
  "geometry": {"coordinates":[-121.900762,38.011572],"type":"Point"}
}