{
  "type": "Feature",
  "properties": {
    "iso:country":"US",
    "sg:address":"4122 Byway E",
    "sg:city":"Napa",
    "sg:classifiers":[
        {
            "category":"Retail",
            "subcategory":"Auto Repair",
            "type":"Services"
        }
    ],
    "sg:phone":"+1 707 252 8188",
    "sg:postcode":"94558",
    "sg:province":"CA",
    "sg:tags":[
        "recreational",
        "vehicle"
    ],
    "wof:name":"Advantage Rv Ctr Inc",
    "wof:placetype":"venue"
},
  "geometry": {"coordinates":[-122.321147,38.336197],"type":"Point"}
}