{
  "type": "Feature",
  "properties": {
    "addr:full":"21338 Dumetz Rd Woodland Hills CA 91364",
    "addr:housenumber":"21338",
    "addr:postcode":"91364",
    "addr:street":"Dumetz Rd",
    "iso:country":"US",
    "sg:address":"21338 Dumetz Rd",
    "sg:city":"Woodland Hills",
    "sg:classifiers":[
        {
            "category":"Organizations",
            "subcategory":"Religious Organization",
            "type":"Services"
        }
    ],
    "sg:phone":"+1 818 347 7700",
    "sg:postcode":"91364",
    "sg:province":"CA",
    "sg:tags":[
        "church"
    ],
    "sg:website":"www.spiritfoodchristiancenter.com",
    "wof:name":"Spirit Food Christian Center",
    "wof:placetype":"venue"
},
  "geometry": {"coordinates":[-118.596001,34.157799],"type":"Point"}
}