{
  "type": "Feature",
  "properties": {
    "iso:country":"US",
    "sg:address":"345 Balboa Cir",
    "sg:city":"Camarillo",
    "sg:classifiers":[
        {
            "category":"Manufacturing",
            "subcategory":"Tools & Machinery",
            "type":"Manufacturing & Wholesale Goods"
        }
    ],
    "sg:phone":"+1 805 384 1376",
    "sg:postcode":"93012",
    "sg:province":"CA",
    "sg:tags":[
        "mold"
    ],
    "wof:name":"Spears Manufacturing Co",
    "wof:placetype":"venue"
},
  "geometry": {"coordinates":[-118.992651,34.213155],"type":"Point"}
}