{
  "type": "Feature",
  "properties": {
    "iso:country":"US",
    "sg:address":"6550 Moonstone Beach Dr",
    "sg:city":"Cambria",
    "sg:classifiers":[
        {
            "category":"Restaurant",
            "type":"Food & Drink"
        }
    ],
    "sg:phone":"+1 805 927 1592",
    "sg:postcode":"93428",
    "sg:province":"CA",
    "sg:tags":[
        "seafood",
        "steakhouse"
    ],
    "sg:website":"www.moonstonebeach.com/",
    "wof:name":"Moonstone Beach Bar & Grill",
    "wof:placetype":"venue"
},
  "geometry": {"coordinates":[-121.113998,35.577099],"type":"Point"}
}