{
  "type": "Feature",
  "properties": {
    "iso:country":"US",
    "sg:address":"12772 Monarch St",
    "sg:city":"Garden Grove",
    "sg:classifiers":[
        {
            "category":"Shopping",
            "subcategory":"Gifts & Souvenirs",
            "type":"Retail Goods"
        }
    ],
    "sg:phone":"+1 714 892 9802",
    "sg:postcode":"92841",
    "sg:province":"CA",
    "sg:tags":[
        "shop"
    ],
    "sg:website":"www.tourtechinternational.com",
    "wof:name":"ACG Gree Group Inc",
    "wof:placetype":"venue"
},
  "geometry": {"coordinates":[-118.00569,33.779971],"type":"Point"}
}