{
  "type": "Feature",
  "properties": {
    "addr:full":"49 Kearny St San Francisco CA 94108",
    "addr:housenumber":"49",
    "addr:postcode":"94108",
    "addr:street":"Kearny St",
    "iso:country":"US",
    "sg:address":"49 Kearny St",
    "sg:city":"San Francisco",
    "sg:classifiers":[
        {
            "category":"Personal",
            "subcategory":"Nail Salon",
            "type":"Services"
        }
    ],
    "sg:phone":"+1 415 544 0375",
    "sg:postcode":"94108",
    "sg:province":"CA",
    "wof:name":"Union Square Nails",
    "wof:placetype":"venue"
},
  "geometry": {"coordinates":[-122.403841,37.788575],"type":"Point"}
}