{
  "type": "Feature",
  "properties": {
    "addr:full":"17401 Irvine Blvd Tustin CA 92780",
    "addr:housenumber":"17401",
    "addr:postcode":"92780",
    "addr:street":"Irvine Blvd",
    "iso:country":"US",
    "sg:address":"17401 Irvine Blvd",
    "sg:city":"Tustin",
    "sg:classifiers":[
        {
            "category":"Wholesale",
            "subcategory":"Apparel",
            "type":"Manufacturing & Wholesale Goods"
        }
    ],
    "sg:phone":"+1 714 360 0055",
    "sg:postcode":"92780",
    "sg:province":"CA",
    "sg:tags":[
        "shoes"
    ],
    "wof:name":"Antonini",
    "wof:placetype":"venue"
},
  "geometry": {"coordinates":[-117.828515,33.748221],"type":"Point"}
}