{
  "type": "Feature",
  "properties": {
    "addr:full":"633 W Katella Ave Orange CA 92867",
    "addr:housenumber":"633",
    "addr:postcode":"92867",
    "addr:street":"W Katella Ave",
    "iso:country":"US",
    "sg:address":"633 W Katella Ave",
    "sg:city":"Orange",
    "sg:classifiers":[
        {
            "category":"Professional",
            "type":"Services"
        }
    ],
    "sg:phone":"+1 714 289 1242",
    "sg:postcode":"92867",
    "sg:province":"CA",
    "sg:tags":[
        "establishment"
    ],
    "wof:name":"Mix Place",
    "wof:placetype":"venue"
},
  "geometry": {"coordinates":[-117.85756600000001,33.809108],"type":"Point"}
}