{
  "type": "Feature",
  "properties": {
    "addr:full":"2939 Freedom Blvd Watsonville CA 95076",
    "addr:housenumber":"2939",
    "addr:postcode":"95076",
    "addr:street":"Freedom Blvd",
    "iso:country":"US",
    "sg:address":"2939 Freedom Blvd",
    "sg:city":"Watsonville",
    "sg:classifiers":[
        {
            "category":"Home & Garden",
            "subcategory":"Garden Supply",
            "type":"Retail Goods"
        }
    ],
    "sg:phone":"+1 831 254 5058",
    "sg:postcode":"95076",
    "sg:province":"CA",
    "sg:tags":[
        "lawn"
    ],
    "wof:name":"Southeast China Garden Product",
    "wof:placetype":"venue"
},
  "geometry": {"coordinates":[-121.81738900000001,36.969308],"type":"Point"}
}