{
  "type": "Feature",
  "properties": {
    "addr:full":"101 California Street Suite 3100 San Francisco CA 94111",
    "addr:housenumber":"101",
    "addr:postcode":"94111",
    "addr:street":"California Street Suite 3100",
    "iso:country":"US",
    "sg:address":"101 California Street Suite 3100",
    "sg:city":"San Francisco",
    "sg:classifiers":[
        {
            "category":"Banks & Credit Unions",
            "subcategory":"Investment Brokerage",
            "type":"Services"
        }
    ],
    "sg:phone":"+1 415 402 6000",
    "sg:postcode":"94111",
    "sg:province":"CA",
    "sg:tags":[
        "investing"
    ],
    "sg:website":"www.nollenbergercapital.com",
    "wof:name":"Nollenberger Capital Partners",
    "wof:placetype":"venue"
},
  "geometry": {"coordinates":[-122.398099,37.792949],"type":"Point"}
}