{
  "type": "Feature",
  "properties": {
    "addr:full":"1515 S Melrose Dr Ofc Vista CA 92081",
    "addr:housenumber":"1515",
    "addr:postcode":"92081",
    "addr:street":"S Melrose Dr",
    "iso:country":"US",
    "sg:address":"1515 S Melrose Dr Ofc",
    "sg:city":"Vista",
    "sg:classifiers":[
        {
            "category":"Real Estate",
            "subcategory":"Real Estate Operator",
            "type":"Services"
        }
    ],
    "sg:phone":"+1 760 598 1222",
    "sg:postcode":"92081",
    "sg:province":"CA",
    "sg:tags":[
        "apartment"
    ],
    "wof:name":"Shadowridge Meadows Apartments",
    "wof:placetype":"venue"
},
  "geometry": {"coordinates":[-117.248001,33.167599],"type":"Point"}
}