{
  "type": "Feature",
  "properties": {
    "iso:country":"US",
    "sg:address":"2732 Bayshore Ave",
    "sg:city":"Ventura",
    "sg:classifiers":[
        {
            "category":"Professional",
            "type":"Services"
        }
    ],
    "sg:phone":"+1 805 644 4941",
    "sg:postcode":"93001",
    "sg:province":"CA",
    "wof:name":"Robert A Ledner M D",
    "wof:placetype":"venue"
},
  "geometry": {"coordinates":[-119.26691099999999,34.256798],"type":"Point"}
}