{
  "type": "Feature",
  "properties": {
    "iso:country":"US",
    "sg:address":"7729 University Ave",
    "sg:city":"La Mesa",
    "sg:classifiers":[
        {
            "category":"Manufacturing",
            "subcategory":"Textiles",
            "type":"Manufacturing & Wholesale Goods"
        }
    ],
    "sg:phone":"+1 619 589 8127",
    "sg:postcode":"91941",
    "sg:province":"CA",
    "sg:tags":[
        "plant",
        "fiber",
        "sewing",
        "alteration",
        "p",
        "finishing",
        "silk",
        "cotton"
    ],
    "wof:name":"San Diego Shirt Works",
    "wof:placetype":"venue"
},
  "geometry": {"coordinates":[-117.030998,32.7616],"type":"Point"}
}