{
  "type": "Feature",
  "properties": {
    "iso:country":"US",
    "sg:address":"1001 Bridgeway",
    "sg:city":"Sausalito",
    "sg:classifiers":[
        {
            "category":"Real Estate",
            "subcategory":"Real Estate Services",
            "type":"Services"
        },
        {
            "category":"Real Estate",
            "subcategory":"Real Estate Agent",
            "type":"Services"
        }
    ],
    "sg:phone":"+1 415 332 7900",
    "sg:postcode":"94965",
    "sg:province":"CA",
    "sg:tags":[
        "management"
    ],
    "sg:website":"http://www.paradisep.com",
    "wof:name":"Paradise Properties Inc.",
    "wof:placetype":"venue"
},
  "geometry": {"coordinates":[-122.483047,37.858452],"type":"Point"}
}