{
  "type": "Feature",
  "properties": {
    "addr:full":"2420 N Oxnard Blvd Oxnard CA 93036",
    "addr:housenumber":"2420",
    "addr:postcode":"93036",
    "addr:street":"N Oxnard Blvd",
    "iso:country":"US",
    "sg:address":"2420 N Oxnard Blvd",
    "sg:city":"Oxnard",
    "sg:classifiers":[
        {
            "category":"Freight",
            "type":"Transportation"
        }
    ],
    "sg:phone":"+1 805 981 7076",
    "sg:postcode":"93036",
    "sg:province":"CA",
    "sg:tags":[
        "operator",
        "trucking"
    ],
    "wof:name":"F Javier Valencia Trucking",
    "wof:placetype":"venue"
},
  "geometry": {"coordinates":[-119.179514,34.233032],"type":"Point"}
}