{
  "type": "Feature",
  "properties": {
    "addr:full":"1550 E Shaw Ave Fresno CA 93710",
    "addr:housenumber":"1550",
    "addr:postcode":"93710",
    "addr:street":"E Shaw Ave",
    "iso:country":"US",
    "sg:address":"1550 E Shaw Ave",
    "sg:city":"Fresno",
    "sg:classifiers":[
        {
            "category":"Professional",
            "subcategory":"Lawyer & Legal Services",
            "type":"Services"
        }
    ],
    "sg:phone":"+1 559 241 7050",
    "sg:postcode":"93710",
    "sg:province":"CA",
    "sg:tags":[
        "attorney"
    ],
    "wof:name":"Richard E Hemb",
    "wof:placetype":"venue"
},
  "geometry": {"coordinates":[-119.760835,36.808666],"type":"Point"}
}