{
  "type": "Feature",
  "properties": {
    "iso:country":"US",
    "sg:address":"1470 W San Carlos St",
    "sg:city":"San Jose",
    "sg:classifiers":[
        {
            "category":"Retail",
            "subcategory":"Car Wash",
            "type":"Services"
        }
    ],
    "sg:phone":"+1 408 998 0530",
    "sg:postcode":"95126",
    "sg:province":"CA",
    "sg:tags":[
        "auto",
        "detailing",
        "detail",
        "clean",
        "automobile"
    ],
    "wof:name":"Auto Detail by Robles",
    "wof:placetype":"venue"
},
  "geometry": {"coordinates":[-121.916,37.323502],"type":"Point"}
}