{
  "type": "Feature",
  "properties": {
    "addr:full":"1889 Walters Ct Fairfield CA 94533",
    "addr:housenumber":"1889",
    "addr:postcode":"94533",
    "addr:street":"Walters Ct",
    "iso:country":"US",
    "sg:address":"1889 Walters Ct",
    "sg:city":"Fairfield",
    "sg:classifiers":[
        {
            "category":"Home & Garden",
            "subcategory":"Building Materials",
            "type":"Retail Goods"
        }
    ],
    "sg:phone":"+1 707 427 2852",
    "sg:postcode":"94533",
    "sg:province":"CA",
    "sg:tags":[
        "door"
    ],
    "wof:name":"D & Y Door & Millwork",
    "wof:placetype":"venue"
},
  "geometry": {"coordinates":[-121.994451,38.269929],"type":"Point"}
}