{
  "type": "Feature",
  "properties": {
    "iso:country":"US",
    "sg:address":"6818 Doriana St",
    "sg:city":"San Diego",
    "sg:classifiers":[
        {
            "category":"Building & Trades",
            "subcategory":"Cleaning & Sanitation",
            "type":"Services"
        }
    ],
    "sg:phone":"+1 619 267 6541",
    "sg:postcode":"92139",
    "sg:province":"CA",
    "sg:tags":[
        "janitor"
    ],
    "wof:name":"Esthela's Janitorial Svc",
    "wof:placetype":"venue"
},
  "geometry": {"coordinates":[-117.047912,32.685355],"type":"Point"}
}