{
  "type": "Feature",
  "properties": {
    "addr:full":"4160 Market St Ventura CA 93003",
    "addr:housenumber":"4160",
    "addr:postcode":"93003",
    "addr:street":"Market St",
    "iso:country":"US",
    "sg:address":"4160 Market St",
    "sg:city":"Ventura",
    "sg:classifiers":[
        {
            "category":"Retail",
            "subcategory":"Auto Repair",
            "type":"Services"
        }
    ],
    "sg:phone":"+1 805 642 8468",
    "sg:postcode":"93003",
    "sg:province":"CA",
    "sg:tags":[
        "glass",
        "coating",
        "tinting"
    ],
    "wof:name":"A-1 Performance Window Tinting",
    "wof:placetype":"venue"
},
  "geometry": {"coordinates":[-119.23870100000001,34.258987],"type":"Point"}
}