{
  "type": "Feature",
  "properties": {
    "iso:country":"US",
    "sg:address":"104 N Bascom Ave",
    "sg:city":"San Jose",
    "sg:classifiers":[
        {
            "category":"Building & Trades",
            "subcategory":"Cleaning & Sanitation",
            "type":"Services"
        }
    ],
    "sg:phone":"+1 408 269 8646",
    "sg:postcode":"95128",
    "sg:province":"CA",
    "sg:tags":[
        "window"
    ],
    "wof:name":"Complete Services Inc",
    "wof:placetype":"venue"
},
  "geometry": {"coordinates":[-121.931965,37.325396],"type":"Point"}
}