{
  "type": "Feature",
  "properties": {
    "iso:country":"US",
    "sg:address":"3845 S Cochran Ave",
    "sg:city":"Los Angeles",
    "sg:classifiers":[
        {
            "category":"Professional",
            "subcategory":"Accounting & Tax Preparation",
            "type":"Services"
        }
    ],
    "sg:phone":"+1 323 292 2232",
    "sg:postcode":"90008",
    "sg:province":"CA",
    "sg:tags":[
        "bookkeeping",
        "general"
    ],
    "wof:name":"Fouche's Tax & Bookkeeping Svc",
    "wof:placetype":"venue"
},
  "geometry": {"coordinates":[-118.361557,34.01692],"type":"Point"}
}