{
  "type": "Feature",
  "properties": {
    "addr:full":"117 N 2nd St King City CA 93930",
    "addr:housenumber":"117",
    "addr:postcode":"93930",
    "addr:street":"N 2Nd St",
    "iso:country":"US",
    "sg:address":"117 N 2nd St",
    "sg:city":"King City",
    "sg:classifiers":[
        {
            "category":"Education",
            "subcategory":"College",
            "type":"Public Place"
        }
    ],
    "sg:phone":"+1 831 386 7100",
    "sg:postcode":"93930",
    "sg:province":"CA",
    "sg:tags":[
        "academic",
        "school"
    ],
    "wof:name":"Hartnell College South County",
    "wof:placetype":"venue"
},
  "geometry": {"coordinates":[-121.12567,36.2143],"type":"Point"}
}