{
  "type": "Feature",
  "properties": {
    "addr:full":"7145 Watt Ave North Highlands CA 95660",
    "addr:housenumber":"7145",
    "addr:postcode":"95660",
    "addr:street":"Watt Ave",
    "iso:country":"US",
    "sg:address":"7145 Watt Ave",
    "sg:city":"North Highlands",
    "sg:classifiers":[
        {
            "category":"Personal",
            "subcategory":"Beauty Salon",
            "type":"Services"
        }
    ],
    "sg:phone":"+1 916 348 9941",
    "sg:postcode":"95660",
    "sg:province":"CA",
    "wof:name":"Crystal Beauty By Ladda",
    "wof:placetype":"venue"
},
  "geometry": {"coordinates":[-121.382882,38.696871],"type":"Point"}
}