{
  "type": "Feature",
  "properties": {
    "iso:country":"US",
    "sg:address":"10108 Donner Pass Rd",
    "sg:city":"Truckee",
    "sg:classifiers":[
        {
            "category":"Wholesale",
            "subcategory":"Sporting Goods",
            "type":"Manufacturing & Wholesale Goods"
        }
    ],
    "sg:phone":"+1 530 550 0645",
    "sg:postcode":"96161",
    "sg:province":"CA",
    "sg:tags":[
        "paint",
        "game",
        "ball"
    ],
    "wof:name":"TNT",
    "wof:placetype":"venue"
},
  "geometry": {"coordinates":[-120.186318,39.32763],"type":"Point"}
}