{
  "type": "Feature",
  "properties": {
    "addr:full":"3920 Cypress Dr Petaluma CA 94954",
    "addr:housenumber":"3920",
    "addr:postcode":"94954",
    "addr:street":"Cypress Dr",
    "iso:country":"US",
    "sg:address":"3920 Cypress Dr",
    "sg:city":"Petaluma",
    "sg:classifiers":[
        {
            "category":"Shopping",
            "subcategory":"Computers & Home Electronics",
            "type":"Retail Goods"
        }
    ],
    "sg:phone":"+1 707 781 0890",
    "sg:postcode":"94954",
    "sg:province":"CA",
    "sg:tags":[
        "equipment",
        "dealer"
    ],
    "sg:website":"www.planits.com",
    "wof:name":"Planit Solutions",
    "wof:placetype":"venue"
},
  "geometry": {"coordinates":[-122.58541200000001,38.22806],"type":"Point"}
}