{
  "type": "Feature",
  "properties": {
    "iso:country":"US",
    "sg:address":"5222 Hillsdale Blvd",
    "sg:city":"Sacramento",
    "sg:classifiers":[
        {
            "category":"Building & Trades",
            "subcategory":"Locksmith",
            "type":"Services"
        }
    ],
    "sg:phone":"+1 916 576 5131",
    "sg:postcode":"95842",
    "sg:province":"CA",
    "sg:tags":[
        "key"
    ],
    "wof:name":"Always Affective Available Emergency Locks",
    "wof:placetype":"venue"
},
  "geometry": {"coordinates":[-121.364164,38.6618],"type":"Point"}
}