{
  "type": "Feature",
  "properties": {
    "iso:country":"US",
    "sg:address":"647 W 9th St",
    "sg:city":"San Pedro",
    "sg:classifiers":[
        {
            "category":"Professional",
            "subcategory":"Lawyer & Legal Services",
            "type":"Services"
        }
    ],
    "sg:phone":"+1 760 323 3605",
    "sg:postcode":"90731",
    "sg:province":"CA",
    "sg:tags":[
        "attorney"
    ],
    "wof:name":"Thomas R Horn",
    "wof:placetype":"venue"
},
  "geometry": {"coordinates":[-118.29013399999999,33.736042],"type":"Point"}
}