{
  "type": "Feature",
  "properties": {
    "iso:country":"US",
    "sg:address":"2644 Tiller Ave",
    "sg:city":"Port Hueneme",
    "sg:classifiers":[
        {
            "category":"Professional",
            "type":"Services"
        }
    ],
    "sg:phone":"+1 805 984 1268",
    "sg:postcode":"93041",
    "sg:province":"CA",
    "wof:name":"Brilliant Building",
    "wof:placetype":"venue"
},
  "geometry": {"coordinates":[-119.217248,34.178672],"type":"Point"}
}