{
  "type": "Feature",
  "properties": {
    "iso:country":"US",
    "sg:address":"55 Geil St",
    "sg:city":"Salinas",
    "sg:phone":"+1 831 759 8824",
    "sg:postcode":"93901",
    "sg:province":"CA",
    "sg:website":"http://www.coastvalleyelectric.com",
    "wof:name":"Coast Valley Electric",
    "wof:placetype":"venue"
},
  "geometry": {"coordinates":[-121.65839699999999,36.666022],"type":"Point"}
}