{
  "type": "Feature",
  "properties": {
    "iso:country":"US",
    "sg:address":"8031 Okean Ter",
    "sg:city":"Los Angeles",
    "sg:classifiers":[
        {
            "category":"Manufacturing",
            "subcategory":"Jewelry",
            "type":"Manufacturing & Wholesale Goods"
        }
    ],
    "sg:phone":"+1 213 623 3768",
    "sg:postcode":"90046",
    "sg:province":"CA",
    "sg:tags":[
        "precious",
        "metal",
        "mfg"
    ],
    "wof:name":"Tempo Electronics",
    "wof:placetype":"venue"
},
  "geometry": {"coordinates":[-118.371889,34.123766],"type":"Point"}
}