{
  "type": "Feature",
  "properties": {
    "addr:full":"1214 E L St Wilmington CA 90744",
    "addr:housenumber":"1214",
    "addr:postcode":"90744",
    "addr:street":"E L St",
    "iso:country":"US",
    "sg:address":"1214 E L St",
    "sg:city":"Wilmington",
    "sg:classifiers":[
        {
            "category":"Food & Beverages",
            "subcategory":"Bakery",
            "type":"Retail Goods"
        }
    ],
    "sg:phone":"+1 310 513 9270",
    "sg:postcode":"90744",
    "sg:province":"CA",
    "sg:tags":[
        "baker"
    ],
    "wof:name":"Viana's Bakery",
    "wof:placetype":"venue"
},
  "geometry": {"coordinates":[-118.24955,33.787331],"type":"Point"}
}