{
  "type": "Feature",
  "properties": {
    "iso:country":"US",
    "sg:address":"313 W 1st Ave",
    "sg:city":"La Habra",
    "sg:classifiers":[
        {
            "category":"Real Estate",
            "subcategory":"Real Estate Operator",
            "type":"Services"
        }
    ],
    "sg:phone":"+1 562 697 2472",
    "sg:postcode":"90631",
    "sg:province":"CA",
    "sg:tags":[
        "mobile",
        "home",
        "site"
    ],
    "wof:name":"City Trailer Park",
    "wof:placetype":"venue"
},
  "geometry": {"coordinates":[-117.949197,33.930919],"type":"Point"}
}