{
  "type": "Feature",
  "properties": {
    "iso:country":"US",
    "sg:address":"3535 Ross Ave",
    "sg:city":"San Jose",
    "sg:classifiers":[
        {
            "category":"Health Services",
            "subcategory":"Doctor",
            "type":"Services"
        }
    ],
    "sg:phone":"+1 408 266 0424",
    "sg:postcode":"95124",
    "sg:province":"CA",
    "sg:tags":[
        "dentist"
    ],
    "wof:name":"Rick Jow DDS",
    "wof:placetype":"venue"
},
  "geometry": {"coordinates":[-121.916768,37.263605],"type":"Point"}
}