{
  "type": "Feature",
  "properties": {
    "iso:country":"US",
    "sg:address":"118 E 2nd St",
    "sg:city":"Calexico",
    "sg:classifiers":[
        {
            "category":"Shopping",
            "subcategory":"Clothing, Apparel, & Fashions",
            "type":"Retail Goods"
        }
    ],
    "sg:phone":"+1 760 357 4949",
    "sg:postcode":"92231",
    "sg:province":"CA",
    "wof:name":"Casa Sonia Fashions",
    "wof:placetype":"venue"
},
  "geometry": {"coordinates":[-115.497309,32.666616],"type":"Point"}
}