{
  "type": "Feature",
  "properties": {
    "iso:country":"US",
    "sg:address":"281 S Atlantic Blvd",
    "sg:city":"Los Angeles",
    "sg:classifiers":[
        {
            "category":"Personal",
            "subcategory":"Beauty Salon",
            "type":"Services"
        }
    ],
    "sg:phone":"+1 323 266 3932",
    "sg:postcode":"90022",
    "sg:province":"CA",
    "wof:name":"International Beauty Salon",
    "wof:placetype":"venue"
},
  "geometry": {"coordinates":[-118.152997,34.033018],"type":"Point"}
}