{
  "type": "Feature",
  "properties": {
    "iso:country":"US",
    "sg:address":"1430 Randall St",
    "sg:city":"Glendale",
    "sg:classifiers":[
        {
            "category":"Organizations",
            "subcategory":"Professional Association",
            "type":"Services"
        }
    ],
    "sg:phone":"+1 818 242 5783",
    "sg:postcode":"91201",
    "sg:province":"CA",
    "sg:tags":[
        "agency",
        "bureau",
        "entertainment"
    ],
    "sg:website":"http://www.thelifeoftheparty.com",
    "wof:name":"Life Of The Party",
    "wof:placetype":"venue"
},
  "geometry": {"coordinates":[-118.29388,34.158611],"type":"Point"}
}