{
  "type": "Feature",
  "properties": {
    "iso:country":"US",
    "sg:address":"12100 W Olympic Blvd",
    "sg:city":"Los Angeles",
    "sg:classifiers":[
        {
            "category":"Recreation",
            "type":"Entertainment"
        }
    ],
    "sg:phone":"+1 310 836 8000",
    "sg:postcode":"90064",
    "sg:province":"CA",
    "sg:tags":[
        "martial",
        "arts",
        "instruction"
    ],
    "wof:name":"Bodies In Motion",
    "wof:placetype":"venue"
},
  "geometry": {"coordinates":[-118.457615,34.031656],"type":"Point"}
}