{
  "type": "Feature",
  "properties": {
    "addr:full":"2310 Fair Oaks Boulevard Sacramento CA 95825",
    "addr:housenumber":"2310",
    "addr:postcode":"95825",
    "addr:street":"Fair Oaks Boulevard",
    "iso:country":"US",
    "sg:address":"2310 Fair Oaks Boulevard",
    "sg:city":"Sacramento",
    "sg:classifiers":[
        {
            "category":"Restaurant",
            "type":"Food & Drink"
        }
    ],
    "sg:phone":"+1 916 923 1212",
    "sg:postcode":"95825",
    "sg:province":"CA",
    "wof:name":"Subway Sandwiches",
    "wof:placetype":"venue"
},
  "geometry": {"coordinates":[-121.410265,38.574131],"type":"Point"}
}