{
  "type": "Feature",
  "properties": {
    "addr:full":"22134 S Vermont Ave Torrance CA 90502",
    "addr:housenumber":"22134",
    "addr:postcode":"90502",
    "addr:street":"S Vermont Ave",
    "iso:country":"US",
    "sg:address":"22134 S Vermont Ave",
    "sg:city":"Torrance",
    "sg:classifiers":[
        {
            "category":"Autos & Motor Vehicles",
            "subcategory":"Auto Supplies",
            "type":"Retail Goods"
        }
    ],
    "sg:phone":"+1 310 782 8229",
    "sg:postcode":"90502",
    "sg:province":"CA",
    "sg:tags":[
        "equipment",
        "racing",
        "car",
        "automobile"
    ],
    "wof:name":"Run-It-Again Motor Sports Inc",
    "wof:placetype":"venue"
},
  "geometry": {"coordinates":[-118.29019099999999,33.82787],"type":"Point"}
}