{
  "type": "Feature",
  "properties": {
    "iso:country":"US",
    "sg:address":"743 Sanborn Pl",
    "sg:city":"Salinas",
    "sg:classifiers":[
        {
            "category":"Farming",
            "subcategory":"Farm & Veterinary Services",
            "type":"Manufacturing & Wholesale Goods"
        }
    ],
    "sg:phone":"+1 831 757 1287",
    "sg:postcode":"93901",
    "sg:province":"CA",
    "sg:tags":[
        "crop",
        "harvesting"
    ],
    "wof:name":"Prime Source Harvesting",
    "wof:placetype":"venue"
},
  "geometry": {"coordinates":[-121.631032,36.662799],"type":"Point"}
}