{
  "type": "Feature",
  "properties": {
    "iso:country":"US",
    "sg:address":"621 Tully Rd",
    "sg:city":"San Jose",
    "sg:classifiers":[
        {
            "category":"Home & Garden",
            "subcategory":"Mobile Homes",
            "type":"Retail Goods"
        }
    ],
    "sg:phone":"+1 408 297 8754",
    "sg:postcode":"95111",
    "sg:province":"CA",
    "wof:name":"Golden State Homes",
    "wof:placetype":"venue"
},
  "geometry": {"coordinates":[-121.845411,37.309428],"type":"Point"}
}