{
  "type": "Feature",
  "properties": {
    "iso:country":"US",
    "sg:address":"1608 E 5th St",
    "sg:city":"Oxnard",
    "sg:classifiers":[
        {
            "category":"Retail",
            "subcategory":"Auto Repair",
            "type":"Services"
        }
    ],
    "sg:phone":"+1 805 487 0117",
    "sg:postcode":"93030",
    "sg:province":"CA",
    "sg:tags":[
        "wrecker"
    ],
    "wof:name":"Mc Carty & Sons Towing",
    "wof:placetype":"venue"
},
  "geometry": {"coordinates":[-119.144671,34.196813],"type":"Point"}
}