{
  "type": "Feature",
  "properties": {
    "iso:country":"US",
    "sg:address":"17050 Passage Ave Apt 31",
    "sg:city":"Bellflower",
    "sg:classifiers":[
        {
            "category":"Building & Trades",
            "subcategory":"Pest Control",
            "type":"Services"
        }
    ],
    "sg:phone":"+1 562 602 0343",
    "sg:postcode":"90706",
    "sg:province":"CA",
    "wof:name":"Le Treazure Chest",
    "wof:placetype":"venue"
},
  "geometry": {"coordinates":[-118.148581,33.878751],"type":"Point"}
}