{
  "type": "Feature",
  "properties": {
    "addr:full":"3999 E Santa Ana Canyon Rd Anaheim CA 92807",
    "addr:housenumber":"3999",
    "addr:postcode":"92807",
    "addr:street":"E Santa Ana Canyon Rd",
    "iso:country":"US",
    "sg:address":"3999 E Santa Ana Canyon Rd",
    "sg:city":"Anaheim",
    "sg:classifiers":[
        {
            "category":"Personal",
            "type":"Services"
        }
    ],
    "sg:phone":"+1 714 998 8317",
    "sg:postcode":"92807",
    "sg:province":"CA",
    "sg:tags":[
        "party",
        "planning",
        "event"
    ],
    "wof:name":"Dat Productions",
    "wof:placetype":"venue"
},
  "geometry": {"coordinates":[-117.82800899999999,33.843287],"type":"Point"}
}