{
  "type": "Feature",
  "properties": {
    "iso:country":"US",
    "sg:address":"239 S Beverly Dr",
    "sg:city":"Beverly Hills",
    "sg:classifiers":[
        {
            "category":"Personal",
            "subcategory":"Beauty Salon",
            "type":"Services"
        }
    ],
    "sg:phone":"+1 310 273 2030",
    "sg:postcode":"90212",
    "sg:province":"CA",
    "wof:name":"Skin Care By Vida",
    "wof:placetype":"venue"
},
  "geometry": {"coordinates":[-118.399147,34.063288],"type":"Point"}
}