{
  "type": "Feature",
  "properties": {
    "iso:country":"US",
    "sg:address":"1075 E Rose Cir",
    "sg:city":"Los Altos",
    "sg:classifiers":[
        {
            "category":"Professional",
            "subcategory":"Engineering",
            "type":"Services"
        }
    ],
    "sg:phone":"+1 650 966 8585",
    "sg:postcode":"94024",
    "sg:province":"CA",
    "wof:name":"Delta Vision",
    "wof:placetype":"venue"
},
  "geometry": {"coordinates":[-122.078825,37.363468],"type":"Point"}
}