{
  "type": "Feature",
  "properties": {
    "iso:country":"US",
    "sg:address":"1737 N 1st St",
    "sg:city":"San Jose",
    "sg:classifiers":[
        {
            "category":"Wholesale",
            "subcategory":"Electrical",
            "type":"Manufacturing & Wholesale Goods"
        }
    ],
    "sg:phone":"+1 408 467 0660",
    "sg:postcode":"95112",
    "sg:province":"CA",
    "sg:tags":[
        "semiconductor"
    ],
    "sg:website":"www.signetics.com",
    "wof:name":"Signetics High Technology",
    "wof:placetype":"venue"
},
  "geometry": {"coordinates":[-121.915163,37.36896],"type":"Point"}
}