{
  "type": "Feature",
  "properties": {
    "iso:country":"US",
    "sg:address":"436 Blossom Hill Rd",
    "sg:city":"San Jose",
    "sg:classifiers":[
        {
            "category":"Restaurant",
            "type":"Food & Drink"
        }
    ],
    "sg:phone":"+1 408 227 5502",
    "sg:postcode":"95123",
    "sg:province":"CA",
    "sg:tags":[
        "pizza",
        "italian"
    ],
    "wof:name":"Angelo's Italian Restaurant & Pizza",
    "wof:placetype":"venue"
},
  "geometry": {"coordinates":[-121.829429,37.25144],"type":"Point"}
}