{
  "type": "Feature",
  "properties": {
    "iso:country":"US",
    "sg:address":"520 W Lacey Blvd",
    "sg:city":"Hanford",
    "sg:classifiers":[
        {
            "category":"Professional",
            "subcategory":"Accounting & Tax Preparation",
            "type":"Services"
        }
    ],
    "sg:phone":"+1 559 589 1900",
    "sg:postcode":"93230",
    "sg:province":"CA",
    "sg:tags":[
        "consultant"
    ],
    "wof:name":"Sonora Tax Viajes Y Envios",
    "wof:placetype":"venue"
},
  "geometry": {"coordinates":[-119.65295,36.328027],"type":"Point"}
}