{
  "type": "Feature",
  "properties": {
    "addr:full":"11478 Pikes Peak Ct Rancho Cucamonga CA 91737",
    "addr:housenumber":"11478",
    "addr:postcode":"91737",
    "addr:street":"Pikes Peak Ct",
    "iso:country":"US",
    "sg:address":"11478 Pikes Peak Ct",
    "sg:city":"Rancho Cucamonga",
    "sg:classifiers":[
        {
            "category":"Wholesale",
            "subcategory":"Drugs",
            "type":"Manufacturing & Wholesale Goods"
        }
    ],
    "sg:phone":"+1 909 944 1792",
    "sg:postcode":"91737",
    "sg:province":"CA",
    "wof:name":"Be Formula Corp",
    "wof:placetype":"venue"
},
  "geometry": {"coordinates":[-117.55406600000001,34.139448],"type":"Point"}
}