{
  "type": "Feature",
  "properties": {
    "addr:full":"1800 Orchard Ln Brentwood CA 94513",
    "addr:housenumber":"1800",
    "addr:postcode":"94513",
    "addr:street":"Orchard Ln",
    "iso:country":"US",
    "sg:address":"1800 Orchard Ln",
    "sg:city":"Brentwood",
    "sg:classifiers":[
        {
            "category":"Farming",
            "subcategory":"Orchard",
            "type":"Manufacturing & Wholesale Goods"
        }
    ],
    "sg:phone":"+1 925 634 5115",
    "sg:postcode":"94513",
    "sg:province":"CA",
    "sg:tags":[
        "fruit",
        "tree"
    ],
    "wof:name":"Galen Tidrick",
    "wof:placetype":"venue"
},
  "geometry": {"coordinates":[-121.71241999999999,37.902062],"type":"Point"}
}