{
  "type": "Feature",
  "properties": {
    "addr:full":"2026 Kelton Ave Los Angeles CA 90025",
    "addr:housenumber":"2026",
    "addr:postcode":"90025",
    "addr:street":"Kelton Ave",
    "iso:country":"US",
    "sg:address":"2026 Kelton Ave",
    "sg:city":"Los Angeles",
    "sg:classifiers":[
        {
            "category":"Wholesale",
            "subcategory":"Machinery & Supplies",
            "type":"Manufacturing & Wholesale Goods"
        }
    ],
    "sg:phone":"+1 626 960 4464",
    "sg:postcode":"90025",
    "sg:province":"CA",
    "sg:tags":[
        "janitorial"
    ],
    "wof:name":"Americas Supply Co",
    "wof:placetype":"venue"
},
  "geometry": {"coordinates":[-118.434926,34.044602],"type":"Point"}
}