{
  "type": "Feature",
  "properties": {
    "addr:full":"70 E Washington St Petaluma CA 94952",
    "addr:housenumber":"70",
    "addr:postcode":"94952",
    "addr:street":"E Washington St",
    "iso:country":"US",
    "sg:address":"70 E Washington St",
    "sg:city":"Petaluma",
    "sg:classifiers":[
        {
            "category":"Professional",
            "subcategory":"Computer Services",
            "type":"Services"
        }
    ],
    "sg:phone":"+1 707 762 1000",
    "sg:postcode":"94952",
    "sg:province":"CA",
    "sg:tags":[
        "scanning"
    ],
    "wof:name":"Pixelworks Digital Color Lab",
    "wof:placetype":"venue"
},
  "geometry": {"coordinates":[-122.639405,38.236214],"type":"Point"}
}