{
  "type": "Feature",
  "properties": {
    "addr:full":"3225 N Harbor Dr Terminal One, Southwest Rotunda, Gates 3 - 10 San Diego CA 92101",
    "addr:housenumber":"3225;3 10",
    "addr:postcode":"92101",
    "addr:street":"N Harbor Dr;Rotunda Gates",
    "iso:country":"US",
    "sg:address":"3225 N Harbor Dr Terminal One, Southwest Rotunda, Gates 3 - 10",
    "sg:city":"San Diego",
    "sg:classifiers":[
        {
            "category":"Restaurant",
            "type":"Food & Drink"
        }
    ],
    "sg:postcode":"92101",
    "sg:province":"CA",
    "sg:tags":[
        "pizza"
    ],
    "sg:website":"www.unos.com",
    "wof:name":"Pizzeria Uno",
    "wof:placetype":"venue"
},
  "geometry": {"coordinates":[-117.189643,32.729208],"type":"Point"}
}