{
  "type": "Feature",
  "properties": {
    "iso:country":"US",
    "sg:address":"2740 Arden Wy",
    "sg:city":"Sacramento",
    "sg:classifiers":[
        {
            "category":"Bars & Pubs",
            "type":"Food & Drink"
        },
        {
            "category":"Bars & Pubs",
            "subcategory":"Lounge",
            "type":"Food & Drink"
        }
    ],
    "sg:phone":"+1 916 489 4207",
    "sg:postcode":"95825",
    "sg:province":"CA",
    "sg:tags":[
        "karaoke"
    ],
    "wof:name":"Maple Room",
    "wof:placetype":"venue"
},
  "geometry": {"coordinates":[-121.39859,38.595623],"type":"Point"}
}