{
  "type": "Feature",
  "properties": {
    "iso:country":"US",
    "sg:address":"2203 del Paso Blvd",
    "sg:city":"Sacramento",
    "sg:classifiers":[
        {
            "category":"Manufacturing",
            "subcategory":"Printing",
            "type":"Manufacturing & Wholesale Goods"
        }
    ],
    "sg:phone":"+1 916 568 6466",
    "sg:postcode":"95815",
    "sg:province":"CA",
    "sg:tags":[
        "newspaper"
    ],
    "wof:name":"North Sacramento Union",
    "wof:placetype":"venue"
},
  "geometry": {"coordinates":[-121.449754,38.610705],"type":"Point"}
}