{
  "type": "Feature",
  "properties": {
    "iso:country":"US",
    "sg:address":"727 18th Ave",
    "sg:city":"San Francisco",
    "sg:classifiers":[
        {
            "category":"Building & Trades",
            "subcategory":"Construction",
            "type":"Services"
        }
    ],
    "sg:phone":"+1 415 387 2336",
    "sg:postcode":"94121",
    "sg:province":"CA",
    "sg:tags":[
        "nonresidential"
    ],
    "wof:name":"Hoffs Construction",
    "wof:placetype":"venue"
},
  "geometry": {"coordinates":[-122.476797,37.773403],"type":"Point"}
}