{
  "type": "Feature",
  "properties": {
    "addr:full":"240 W E St Dixon CA 95620",
    "addr:housenumber":"240",
    "addr:postcode":"95620",
    "addr:street":"W E St",
    "iso:country":"US",
    "sg:address":"240 W E St",
    "sg:city":"Dixon",
    "sg:classifiers":[
        {
            "category":"Professional",
            "subcategory":"Research",
            "type":"Services"
        }
    ],
    "sg:phone":"+1 707 678 2330",
    "sg:postcode":"95620",
    "sg:province":"CA",
    "sg:tags":[
        "archaeologist"
    ],
    "sg:website":"www.tremainecnrs.com",
    "wof:name":"Tremaine & Assoc",
    "wof:placetype":"venue"
},
  "geometry": {"coordinates":[-121.82453599999999,38.449574],"type":"Point"}
}