{
  "type": "Feature",
  "properties": {
    "iso:country":"US",
    "sg:address":"1451 Center St",
    "sg:city":"Manteca",
    "sg:classifiers":[
        {
            "category":"Banks & Credit Unions",
            "subcategory":"Investment Brokerage",
            "type":"Services"
        }
    ],
    "sg:phone":"+1 209 825 2040",
    "sg:postcode":"95337",
    "sg:province":"CA",
    "sg:tags":[
        "management"
    ],
    "wof:name":"Stonegate Apartments",
    "wof:placetype":"venue"
},
  "geometry": {"coordinates":[-121.23993900000001,37.799807],"type":"Point"}
}