{
  "type": "Feature",
  "properties": {
    "addr:full":"1910 W El Camino Real Ste C1 Mountain View CA 94040",
    "addr:housenumber":"1910",
    "addr:postcode":"94040",
    "addr:street":"W El Camino Real Ste C1",
    "iso:country":"US",
    "sg:address":"1910 W El Camino Real Ste C1",
    "sg:city":"Mountain View",
    "sg:classifiers":[
        {
            "category":"Shopping",
            "subcategory":"Beauty & Cosmetics",
            "type":"Retail Goods"
        }
    ],
    "sg:phone":"+1 650 968 8282",
    "sg:postcode":"94040",
    "sg:province":"CA",
    "sg:tags":[
        "supply"
    ],
    "wof:name":"Beauty Unlimited Beauty Supply",
    "wof:placetype":"venue"
},
  "geometry": {"coordinates":[-122.09682100000001,37.393996],"type":"Point"}
}