{
  "type": "Feature",
  "properties": {
    "iso:country":"US",
    "sg:address":"5150 W Pico Blvd",
    "sg:city":"Los Angeles",
    "sg:classifiers":[
        {
            "category":"Autos & Motor Vehicles",
            "subcategory":"Automobile Sales",
            "type":"Retail Goods"
        }
    ],
    "sg:phone":"+1 323 935 4016",
    "sg:postcode":"90019",
    "sg:province":"CA",
    "sg:tags":[
        "automotive"
    ],
    "wof:name":"Best Tires",
    "wof:placetype":"venue"
},
  "geometry": {"coordinates":[-118.350776,34.04778],"type":"Point"}
}