{
  "type": "Feature",
  "properties": {
    "addr:full":"231 W Vernon Ave Ste 100 Los Angeles CA 90037",
    "addr:housenumber":"231",
    "addr:postcode":"90037",
    "addr:street":"W Vernon Ave Ste 100",
    "iso:country":"US",
    "sg:address":"231 W Vernon Ave Ste 100",
    "sg:city":"Los Angeles",
    "sg:classifiers":[
        {
            "category":"Shopping",
            "subcategory":"Pharmacy",
            "type":"Retail Goods"
        }
    ],
    "sg:phone":"+1 323 232 1111",
    "sg:postcode":"90037",
    "sg:province":"CA",
    "sg:tags":[
        "drugstore"
    ],
    "wof:name":"Vernbro Medical Pharmacy",
    "wof:placetype":"venue"
},
  "geometry": {"coordinates":[-118.277,34.003799],"type":"Point"}
}