{
  "type": "Feature",
  "properties": {
    "addr:full":"23382 Madero Mission Viejo CA 92691",
    "addr:housenumber":"23382",
    "addr:postcode":"92691",
    "addr:street":"Madero",
    "iso:country":"US",
    "sg:address":"23382 Madero",
    "sg:city":"Mission Viejo",
    "sg:classifiers":[
        {
            "category":"Professional",
            "subcategory":"Management & Consulting",
            "type":"Services"
        }
    ],
    "sg:phone":"+1 949 581 6360",
    "sg:postcode":"92691",
    "sg:province":"CA",
    "sg:tags":[
        "consultant"
    ],
    "wof:name":"Bel Esprit Consulting",
    "wof:placetype":"venue"
},
  "geometry": {"coordinates":[-117.678575,33.623849],"type":"Point"}
}