{
  "type": "Feature",
  "properties": {
    "iso:country":"US",
    "sg:address":"2237 N Plaza Dr",
    "sg:city":"Visalia",
    "sg:classifiers":[
        {
            "category":"Wholesale",
            "subcategory":"Medical Equipment & Supplies",
            "type":"Manufacturing & Wholesale Goods"
        },
        {
            "category":"Shopping",
            "subcategory":"Pharmacy",
            "type":"Retail Goods"
        }
    ],
    "sg:phone":"+1 559 651 9088",
    "sg:postcode":"93291",
    "sg:province":"CA",
    "sg:tags":[
        "home",
        "health",
        "care"
    ],
    "wof:name":"Bound Tree Medical",
    "wof:placetype":"venue"
},
  "geometry": {"coordinates":[-119.394547,36.339973],"type":"Point"}
}