{
  "type": "Feature",
  "properties": {
    "iso:country":"US",
    "sg:address":"624 South Grand Suite 904",
    "sg:city":"Los Angeles",
    "sg:classifiers":[
        {
            "category":"Professional",
            "subcategory":"Management & Consulting",
            "type":"Services"
        }
    ],
    "sg:phone":"+1 702 987 1595",
    "sg:postcode":"90017",
    "sg:province":"CA",
    "sg:tags":[
        "web-software",
        "consulting",
        "payment-processing",
        "payments",
        "software-architecture",
        "enterprise-systems"
    ],
    "sg:website":"http://www.maasglobalsolutions.com",
    "wof:name":"Maas Global Solutions Corporation",
    "wof:placetype":"venue"
},
  "geometry": {"coordinates":[-118.255476,34.048504],"type":"Point"}
}