{
  "type": "Feature",
  "properties": {
    "addr:full":"13650 Vaughn St San Fernando CA 91340",
    "addr:housenumber":"13650",
    "addr:postcode":"91340",
    "addr:street":"Vaughn St",
    "iso:country":"US",
    "sg:address":"13650 Vaughn St",
    "sg:city":"San Fernando",
    "sg:classifiers":[
        {
            "category":"Shopping",
            "type":"Retail Goods"
        }
    ],
    "sg:phone":"+1 818 896 6633",
    "sg:postcode":"91340",
    "sg:province":"CA",
    "sg:tags":[
        "equipment",
        "irrigation",
        "system"
    ],
    "wof:name":"Yosef Amzalag Supply",
    "wof:placetype":"venue"
},
  "geometry": {"coordinates":[-118.429196,34.276938],"type":"Point"}
}