{
  "type": "Feature",
  "properties": {
    "addr:full":"5650 Hollis St Emeryville CA 94608",
    "addr:housenumber":"5650",
    "addr:postcode":"94608",
    "addr:street":"Hollis St",
    "iso:country":"US",
    "sg:address":"5650 Hollis St",
    "sg:city":"Emeryville",
    "sg:classifiers":[
        {
            "category":"Manufacturing",
            "subcategory":"Chemicals & Compounds",
            "type":"Manufacturing & Wholesale Goods"
        },
        {
            "category":"Wholesale",
            "subcategory":"Medical Equipment & Supplies",
            "type":"Manufacturing & Wholesale Goods"
        }
    ],
    "sg:phone":"+1 510 597 8957",
    "sg:postcode":"94608",
    "sg:province":"CA",
    "sg:tags":[
        "pharmaceutical",
        "product",
        "products-wholesale",
        "manufacturer"
    ],
    "sg:website":"http://www.multiplesclerosis.com",
    "wof:name":"Bayer Healthcare Pharmaceuticals Inc.",
    "wof:placetype":"venue"
},
  "geometry": {"coordinates":[-122.28827800000001,37.837501],"type":"Point"}
}