{
  "type": "Feature",
  "properties": {
    "iso:country":"US",
    "sg:address":"923 College Ave",
    "sg:city":"Santa Rosa",
    "sg:classifiers":[
        {
            "category":"Professional",
            "subcategory":"Secretarial Services",
            "type":"Services"
        }
    ],
    "sg:phone":"+1 707 546 8436",
    "sg:postcode":"95404",
    "sg:province":"CA",
    "sg:tags":[
        "convention",
        "court",
        "reporter"
    ],
    "wof:name":"Maes & Assoc Inc",
    "wof:placetype":"venue"
},
  "geometry": {"coordinates":[-122.711192,38.445543],"type":"Point"}
}