{
  "type": "Feature",
  "properties": {
    "iso:country":"US",
    "sg:address":"340 N Ellsworth Ave",
    "sg:city":"San Mateo",
    "sg:classifiers":[
        {
            "category":"Shopping",
            "subcategory":"Discount & Variety Stores",
            "type":"Retail Goods"
        }
    ],
    "sg:phone":"+1 650 348 3711",
    "sg:postcode":"94401",
    "sg:province":"CA",
    "wof:name":"99 Cent Store",
    "wof:placetype":"venue"
},
  "geometry": {"coordinates":[-122.33070600000001,37.572486],"type":"Point"}
}