{
  "type": "Feature",
  "properties": {
    "addr:full":"2400 State Rte 154 Santa Barbara CA 93105",
    "addr:housenumber":"2400",
    "addr:postcode":"93105",
    "addr:street":"State Rte 154",
    "iso:country":"US",
    "sg:address":"2400 State Rte 154",
    "sg:city":"Santa Barbara",
    "sg:classifiers":[
        {
            "category":"Travel",
            "subcategory":"Campground",
            "type":"Entertainment"
        }
    ],
    "sg:phone":"+1 805 962 6776",
    "sg:postcode":"93105",
    "sg:province":"CA",
    "sg:tags":[
        "camp"
    ],
    "sg:website":"www.campwhittier.org",
    "wof:name":"Camp Whittier",
    "wof:placetype":"venue"
},
  "geometry": {"coordinates":[-119.885063,34.546843],"type":"Point"}
}