{
  "type": "Feature",
  "properties": {
    "addr:full":"1950 Sawtelle Blvd Los Angeles CA 90025",
    "addr:housenumber":"1950",
    "addr:postcode":"90025",
    "addr:street":"Sawtelle Blvd",
    "iso:country":"US",
    "sg:address":"1950 Sawtelle Blvd",
    "sg:city":"Los Angeles",
    "sg:classifiers":[
        {
            "category":"Health Services",
            "subcategory":"Health Practitioner",
            "type":"Services"
        }
    ],
    "sg:phone":"+1 310 208 2446",
    "sg:postcode":"90025",
    "sg:province":"CA",
    "sg:tags":[
        "psychologist"
    ],
    "wof:name":"Cheri Adrian PHD",
    "wof:placetype":"venue"
},
  "geometry": {"coordinates":[-118.444159,34.041795],"type":"Point"}
}