{
  "type": "Feature",
  "properties": {
    "iso:country":"US",
    "sg:address":"362 E Grand Ave",
    "sg:city":"South San Francisco",
    "sg:phone":"+1 510 782 0417",
    "sg:postcode":"94080",
    "sg:province":"CA",
    "sg:tags":[
        "equipment",
        "commercial"
    ],
    "wof:name":"Em Pierpoint Inc",
    "wof:placetype":"venue"
},
  "geometry": {"coordinates":[-122.387366,37.651259],"type":"Point"}
}