{
  "type": "Feature",
  "properties": {
    "iso:country":"US",
    "sg:address":"7435 Kamwood St",
    "sg:city":"San Diego",
    "sg:classifiers":[
        {
            "category":"Wholesale",
            "subcategory":"Apparel",
            "type":"Manufacturing & Wholesale Goods"
        }
    ],
    "sg:phone":"+1 858 549 3607",
    "sg:postcode":"92126",
    "sg:province":"CA",
    "sg:tags":[
        "clothing"
    ],
    "wof:name":"Comfort Clothiers Associates",
    "wof:placetype":"venue"
},
  "geometry": {"coordinates":[-117.166238,32.904509],"type":"Point"}
}