{
  "type": "Feature",
  "properties": {
    "addr:full":"944 Santa Estella Solana Beach CA 92075",
    "addr:housenumber":"944",
    "addr:postcode":"92075",
    "addr:street":"Santa Estella",
    "iso:country":"US",
    "sg:address":"944 Santa Estella",
    "sg:city":"Solana Beach",
    "sg:classifiers":[
        {
            "category":"Building & Trades",
            "subcategory":"Landscaping Services",
            "type":"Services"
        }
    ],
    "sg:phone":"+1 858 481 6652",
    "sg:postcode":"92075",
    "sg:province":"CA",
    "wof:name":"Harold Vita",
    "wof:placetype":"venue"
},
  "geometry": {"coordinates":[-117.253929,33.004824],"type":"Point"}
}