{
  "type": "Feature",
  "properties": {
    "addr:full":"311 N McClelland St Santa Maria CA 93454",
    "addr:housenumber":"311",
    "addr:postcode":"93454",
    "addr:street":"N Mcclelland St",
    "iso:country":"US",
    "sg:address":"311 N McClelland St",
    "sg:city":"Santa Maria",
    "sg:classifiers":[
        {
            "category":"Wholesale",
            "subcategory":"Machinery & Supplies",
            "type":"Manufacturing & Wholesale Goods"
        }
    ],
    "sg:phone":"+1 805 922 6699",
    "sg:postcode":"93454",
    "sg:province":"CA",
    "wof:name":"Coast Lawnmower Service",
    "wof:placetype":"venue"
},
  "geometry": {"coordinates":[-120.434292,34.955805],"type":"Point"}
}