{
  "type": "Feature",
  "properties": {
    "addr:full":"12600 River Rd Guerneville CA 95446",
    "addr:housenumber":"12600",
    "addr:postcode":"95446",
    "addr:street":"River Rd",
    "iso:country":"US",
    "sg:address":"12600 River Rd",
    "sg:city":"Guerneville",
    "sg:classifiers":[
        {
            "category":"Travel",
            "subcategory":"Campground",
            "type":"Entertainment"
        }
    ],
    "sg:phone":"+1 707 869 2311",
    "sg:postcode":"95446",
    "sg:province":"CA",
    "wof:name":"Schoolhouse Canyon Campground",
    "wof:placetype":"venue"
},
  "geometry": {"coordinates":[-122.94047500000001,38.504143],"type":"Point"}
}