{
  "type": "Feature",
  "properties": {
    "iso:country":"US",
    "sg:address":"1136 Fremont Ave Ste 107",
    "sg:city":"South Pasadena",
    "sg:classifiers":[
        {
            "category":"Health Services",
            "subcategory":"Dentist",
            "type":"Services"
        }
    ],
    "sg:phone":"+1 323 682 3377",
    "sg:postcode":"91030",
    "sg:province":"CA",
    "wof:name":"Has-Camino Travel",
    "wof:placetype":"venue"
},
  "geometry": {"coordinates":[-118.15300000000001,34.113098],"type":"Point"}
}