{
  "type": "Feature",
  "properties": {
    "addr:full":"2328 Golden Hill Rd Paso Robles CA 93446",
    "addr:housenumber":"2328",
    "addr:postcode":"93446",
    "addr:street":"Golden Hill Rd",
    "iso:country":"US",
    "sg:address":"2328 Golden Hill Rd",
    "sg:city":"Paso Robles",
    "sg:classifiers":[
        {
            "category":"Building & Trades",
            "subcategory":"Construction",
            "type":"Services"
        }
    ],
    "sg:phone":"+1 805 239 8618",
    "sg:postcode":"93446",
    "sg:province":"CA",
    "sg:tags":[
        "contractor"
    ],
    "wof:name":"Brian Wilson Construction Inc",
    "wof:placetype":"venue"
},
  "geometry": {"coordinates":[-120.657743,35.634015],"type":"Point"}
}