{
  "type": "Feature",
  "properties": {
    "addr:full":"2161 E Avion Dr Ontario CA 91761",
    "addr:housenumber":"2161",
    "addr:postcode":"91761",
    "addr:street":"E Avion Dr",
    "iso:country":"US",
    "sg:address":"2161 E Avion Dr",
    "sg:city":"Ontario",
    "sg:classifiers":[
        {
            "category":"Retail",
            "subcategory":"Auto Rental",
            "type":"Services"
        }
    ],
    "sg:phone":"+1 909 605 6290",
    "sg:postcode":"91761",
    "sg:province":"CA",
    "sg:tags":[
        "automobile",
        "leasing"
    ],
    "wof:name":"Hertz Corp",
    "wof:placetype":"venue"
},
  "geometry": {"coordinates":[-117.602251,34.049216],"type":"Point"}
}