{
  "type": "Feature",
  "properties": {
    "addr:full":"2441 S Grove Ave Ontario CA 91761",
    "addr:housenumber":"2441",
    "addr:postcode":"91761",
    "addr:street":"S Grove Ave",
    "iso:country":"US",
    "sg:address":"2441 S Grove Ave",
    "sg:city":"Ontario",
    "sg:classifiers":[
        {
            "category":"Retail",
            "subcategory":"Laundry & Dry Cleaning",
            "type":"Services"
        }
    ],
    "sg:phone":"+1 909 947 4333",
    "sg:postcode":"91761",
    "sg:province":"CA",
    "sg:tags":[
        "cleaners"
    ],
    "wof:name":"1 Grove Cleaners",
    "wof:placetype":"venue"
},
  "geometry": {"coordinates":[-117.628348,34.028506],"type":"Point"}
}