{
  "type": "Feature",
  "properties": {
    "iso:country":"US",
    "sg:address":"422 Bolivia",
    "sg:city":"San Clemente",
    "sg:classifiers":[
        {
            "category":"Airline",
            "type":"Transportation"
        }
    ],
    "sg:phone":"+1 949 498 2550",
    "sg:postcode":"92672",
    "sg:province":"CA",
    "sg:tags":[
        "nonscheduled",
        "air"
    ],
    "wof:name":"Rmp",
    "wof:placetype":"venue"
},
  "geometry": {"coordinates":[-117.59023000000001,33.441789],"type":"Point"}
}