{
  "type": "Feature",
  "properties": {
    "addr:full":"4547 Riverside Dr Chino CA 91710",
    "addr:housenumber":"4547",
    "addr:postcode":"91710",
    "addr:street":"Riverside Dr",
    "iso:country":"US",
    "sg:address":"4547 Riverside Dr",
    "sg:city":"Chino",
    "sg:classifiers":[
        {
            "category":"Restaurant",
            "type":"Food & Drink"
        }
    ],
    "sg:phone":"+1 909 590 0129",
    "sg:postcode":"91710",
    "sg:province":"CA",
    "wof:name":"Restaurant El Rey Inc",
    "wof:placetype":"venue"
},
  "geometry": {"coordinates":[-117.70658,34.018888],"type":"Point"}
}