{
  "type": "Feature",
  "properties": {
    "addr:full":"3128 E Harcourt St Compton CA 90221",
    "addr:housenumber":"3128",
    "addr:postcode":"90221",
    "addr:street":"E Harcourt St",
    "iso:country":"US",
    "sg:address":"3128 E Harcourt St",
    "sg:city":"Compton",
    "sg:classifiers":[
        {
            "category":"Professional",
            "type":"Services"
        }
    ],
    "sg:phone":"+1 310 635 7880",
    "sg:postcode":"90221",
    "sg:province":"CA",
    "sg:tags":[
        "establishment"
    ],
    "wof:name":"Li & Fung Inc",
    "wof:placetype":"venue"
},
  "geometry": {"coordinates":[-118.206907,33.867314],"type":"Point"}
}