{
  "type": "Feature",
  "properties": {
    "iso:country":"US",
    "sg:address":"308 N Broadway St",
    "sg:city":"Yreka",
    "sg:classifiers":[
        {
            "category":"Shopping",
            "type":"Retail Goods"
        },
        {
            "category":"Shopping",
            "subcategory":"Gifts & Souvenirs",
            "type":"Retail Goods"
        }
    ],
    "sg:phone":"+1 530 842 1792",
    "sg:postcode":"96097",
    "sg:province":"CA",
    "sg:tags":[
        "cards",
        "sport",
        "baseball",
        "memorabilia"
    ],
    "wof:name":"Mick's Clubhouse",
    "wof:placetype":"venue"
},
  "geometry": {"coordinates":[-122.63551,41.733588],"type":"Point"}
}