{
  "type": "Feature",
  "properties": {
    "iso:country":"US",
    "sg:address":"11516 Oxnard St",
    "sg:city":"North Hollywood",
    "sg:classifiers":[
        {
            "category":"Health Services",
            "subcategory":"Dentist",
            "type":"Services"
        }
    ],
    "sg:phone":"+1 818 769 9551",
    "sg:postcode":"91606",
    "sg:province":"CA",
    "wof:name":"Oganesyan Arsen Dntst",
    "wof:placetype":"venue"
},
  "geometry": {"coordinates":[-118.383003,34.179501],"type":"Point"}
}