{
  "type": "Feature",
  "properties": {
    "addr:full":"2793 Bert Crane Rd Atwater CA 95301",
    "addr:housenumber":"2793",
    "addr:postcode":"95301",
    "addr:street":"Bert Crane Rd",
    "iso:country":"US",
    "sg:address":"2793 Bert Crane Rd",
    "sg:city":"Atwater",
    "sg:classifiers":[
        {
            "category":"Farming",
            "subcategory":"Crops",
            "type":"Manufacturing & Wholesale Goods"
        }
    ],
    "sg:phone":"+1 209 358 7380",
    "sg:postcode":"95301",
    "sg:province":"CA",
    "sg:tags":[
        "grove",
        "nut",
        "tree"
    ],
    "wof:name":"Darwin Simmons",
    "wof:placetype":"venue"
},
  "geometry": {"coordinates":[-120.632811,37.327687],"type":"Point"}
}