{
  "type": "Feature",
  "properties": {
    "iso:country":"US",
    "sg:address":"15520 Rockfield Blvd",
    "sg:city":"Irvine",
    "sg:classifiers":[
        {
            "category":"Building & Trades",
            "subcategory":"Plumbing",
            "type":"Services"
        }
    ],
    "sg:phone":"+1 949 454 2288",
    "sg:postcode":"92618",
    "sg:province":"CA",
    "sg:tags":[
        "plumbing",
        "air",
        "conditioning",
        "heating"
    ],
    "wof:name":"Spectrum Mechanical Inc",
    "wof:placetype":"venue"
},
  "geometry": {"coordinates":[-117.721377,33.638885],"type":"Point"}
}