{
  "type": "Feature",
  "properties": {
    "iso:country":"US",
    "sg:address":"233 Valle de Paz Ave",
    "sg:city":"Firebaugh",
    "sg:phone":"+1 559 659 2408",
    "sg:postcode":"93622",
    "sg:province":"CA",
    "sg:tags":[
        "farm",
        "wheat"
    ],
    "wof:name":"Fuentes Farms",
    "wof:placetype":"venue"
},
  "geometry": {"coordinates":[-120.46552800000001,36.867571],"type":"Point"}
}