{
  "type": "Feature",
  "properties": {
    "addr:full":"1800 Rosecrans St San Diego CA 92106",
    "addr:housenumber":"1800",
    "addr:postcode":"92106",
    "addr:street":"Rosecrans St",
    "iso:country":"US",
    "sg:address":"1800 Rosecrans St",
    "sg:city":"San Diego",
    "sg:classifiers":[
        {
            "category":"Professional",
            "subcategory":"Lawyer & Legal Services",
            "type":"Services"
        }
    ],
    "sg:phone":"+1 619 222 2777",
    "sg:postcode":"92106",
    "sg:province":"CA",
    "wof:name":"Higuera Law Offices",
    "wof:placetype":"venue"
},
  "geometry": {"coordinates":[-117.224914,32.729868],"type":"Point"}
}