{
  "type": "Feature",
  "properties": {
    "iso:country":"US",
    "sg:address":"1801 H St",
    "sg:city":"Eureka",
    "sg:classifiers":[
        {
            "category":"Health Services",
            "subcategory":"Clinic",
            "type":"Services"
        }
    ],
    "sg:phone":"+1 707 445 4876",
    "sg:postcode":"95501",
    "sg:province":"CA",
    "sg:tags":[
        "home"
    ],
    "wof:name":"Double RR Care Home Corp",
    "wof:placetype":"venue"
},
  "geometry": {"coordinates":[-124.16118899999999,40.79135],"type":"Point"}
}