{
  "type": "Feature",
  "properties": {
    "addr:full":"44 Montgomery Street, Ste 4210 San Francisco CA 94104",
    "addr:housenumber":"44",
    "addr:postcode":"94104",
    "addr:street":"Montgomery Street Ste 4210",
    "iso:country":"US",
    "sg:address":"44 Montgomery Street, Ste 4210",
    "sg:city":"San Francisco",
    "sg:classifiers":[
        {
            "category":"Banks & Credit Unions",
            "subcategory":"Financial Services",
            "type":"Services"
        }
    ],
    "sg:phone":"+1 415 623 2450",
    "sg:postcode":"94104",
    "sg:province":"CA",
    "sg:website":"www.ameripriseadvisors.com/kate....",
    "wof:name":"Kate Wilusz - Ameriprise Financial",
    "wof:placetype":"venue"
},
  "geometry": {"coordinates":[-122.402018,37.789663],"type":"Point"}
}