{
  "type": "Feature",
  "properties": {
    "addr:full":"44050 Barbara Trl Aguanga CA 92536",
    "addr:housenumber":"44050",
    "addr:postcode":"92536",
    "addr:street":"Barbara Trl",
    "iso:country":"US",
    "sg:address":"44050 Barbara Trl",
    "sg:city":"Aguanga",
    "sg:classifiers":[
        {
            "category":"Farming",
            "subcategory":"Livestock Farm",
            "type":"Manufacturing & Wholesale Goods"
        }
    ],
    "sg:phone":"+1 951 763 9696",
    "sg:postcode":"92536",
    "sg:province":"CA",
    "sg:tags":[
        "specialty",
        "animal"
    ],
    "wof:name":"Full Circle Organic Farms",
    "wof:placetype":"venue"
},
  "geometry": {"coordinates":[-116.805429,33.482706],"type":"Point"}
}