{
  "type": "Feature",
  "properties": {
    "addr:full":"1223 Santee Street Los Angeles CA 90015",
    "addr:housenumber":"1223",
    "addr:postcode":"90015",
    "addr:street":"Santee Street",
    "iso:country":"US",
    "sg:address":"1223 Santee Street",
    "sg:city":"Los Angeles",
    "sg:classifiers":[
        {
            "category":"Parking",
            "type":"Transportation"
        }
    ],
    "sg:phone":"+1 213 742 0174",
    "sg:postcode":"90015",
    "sg:province":"CA",
    "sg:website":"www.centralparkingsystem.com",
    "wof:name":"Central Parking System",
    "wof:placetype":"venue"
},
  "geometry": {"coordinates":[-118.257695,34.035652],"type":"Point"}
}