{
  "type": "Feature",
  "properties": {
    "iso:country":"US",
    "sg:address":"1025 N Chestnut Ave",
    "sg:city":"Rialto",
    "sg:classifiers":[
        {
            "category":"Real Estate",
            "subcategory":"Real Estate Operator",
            "type":"Services"
        }
    ],
    "sg:phone":"+1 909 875 1852",
    "sg:postcode":"92376",
    "sg:province":"CA",
    "sg:tags":[
        "apartment"
    ],
    "wof:name":"Hammond's Community Care",
    "wof:placetype":"venue"
},
  "geometry": {"coordinates":[-117.355282,34.117386],"type":"Point"}
}