{
  "type": "Feature",
  "properties": {
    "iso:country":"US",
    "sg:address":"12145 Carson St",
    "sg:city":"Hawaiian Gardens",
    "sg:classifiers":[
        {
            "category":"Shopping",
            "subcategory":"Mobile Phones",
            "type":"Retail Goods"
        }
    ],
    "sg:phone":"+1 562 402 1734",
    "sg:postcode":"90716",
    "sg:province":"CA",
    "wof:name":"Cingular Wireless",
    "wof:placetype":"venue"
},
  "geometry": {"coordinates":[-118.338636,33.831657],"type":"Point"}
}