{
  "type": "Feature",
  "properties": {
    "addr:full":"1255 Montgomery St San Francisco CA 94133",
    "addr:housenumber":"1255",
    "addr:postcode":"94133",
    "addr:street":"Montgomery St",
    "iso:country":"US",
    "sg:address":"1255 Montgomery St",
    "sg:city":"San Francisco",
    "sg:classifiers":[
        {
            "category":"Professional",
            "subcategory":"Advertising",
            "type":"Services"
        }
    ],
    "sg:phone":"+1 415 398 5420",
    "sg:postcode":"94133",
    "sg:province":"CA",
    "sg:tags":[
        "counselor"
    ],
    "wof:name":"Lombardo & Assoc",
    "wof:placetype":"venue"
},
  "geometry": {"coordinates":[-122.40448000000001,37.80088],"type":"Point"}
}