{
  "type": "Feature",
  "properties": {
    "iso:country":"US",
    "sg:address":"366 N Harbor Blvd",
    "sg:city":"La Habra",
    "sg:classifiers":[
        {
            "category":"Restaurant",
            "type":"Food & Drink"
        }
    ],
    "sg:menulink":"http://www.allmenus.com/ca/anaheim-santa-ana-garden-grove/78769-pizza-hut/menu/",
    "sg:phone":"+1 562 691 1394",
    "sg:postcode":"90631",
    "sg:province":"CA",
    "sg:tags":[
        "american",
        "pizza"
    ],
    "wof:name":"Pizza Hut",
    "wof:placetype":"venue"
},
  "geometry": {"coordinates":[-117.93305599999999,33.934176],"type":"Point"}
}