{
  "type": "Feature",
  "properties": {
    "iso:country":"US",
    "sg:address":"1120 W Olive Ave",
    "sg:city":"Sunnyvale",
    "sg:classifiers":[
        {
            "category":"Real Estate",
            "subcategory":"Real Estate Operator",
            "type":"Services"
        }
    ],
    "sg:phone":"+1 408 736 2128",
    "sg:postcode":"94086",
    "sg:province":"CA",
    "sg:tags":[
        "apartment"
    ],
    "wof:name":"Castlemont Arms Apartments",
    "wof:placetype":"venue"
},
  "geometry": {"coordinates":[-122.052002,37.374401],"type":"Point"}
}