{
  "type": "Feature",
  "properties": {
    "iso:country":"US",
    "sg:address":"1680 S E St",
    "sg:city":"San Bernardino",
    "sg:classifiers":[
        {
            "category":"Home & Garden",
            "subcategory":"Furniture",
            "type":"Retail Goods"
        }
    ],
    "sg:phone":"+1 909 888 7632",
    "sg:postcode":"92408",
    "sg:province":"CA",
    "wof:name":"Rooms 4 U",
    "wof:placetype":"venue"
},
  "geometry": {"coordinates":[-117.29424,34.075145],"type":"Point"}
}