{
  "type": "Feature",
  "properties": {
    "iso:country":"US",
    "sg:address":"4302 W Victory Blvd",
    "sg:city":"Burbank",
    "sg:classifiers":[
        {
            "category":"Wholesale",
            "subcategory":"Medical Equipment & Supplies",
            "type":"Manufacturing & Wholesale Goods"
        }
    ],
    "sg:phone":"+1 818 845 2884",
    "sg:postcode":"91505",
    "sg:province":"CA",
    "sg:tags":[
        "merchandise"
    ],
    "wof:name":"Burbank Medical Supplies",
    "wof:placetype":"venue"
},
  "geometry": {"coordinates":[-118.358293,34.184774],"type":"Point"}
}