{
  "type": "Feature",
  "properties": {
    "iso:country":"US",
    "sg:address":"1020 Fedora Street",
    "sg:city":"Los Angeles",
    "sg:classifiers":[
        {
            "category":"Health Services",
            "subcategory":"Health Practitioner",
            "type":"Services"
        }
    ],
    "sg:phone":"+1 213 388 1396",
    "sg:postcode":"90006",
    "sg:province":"CA",
    "sg:tags":[
        "acupuncture"
    ],
    "wof:name":"Asian Herb & Acupuncture Center",
    "wof:placetype":"venue"
},
  "geometry": {"coordinates":[-118.298024,34.052381],"type":"Point"}
}