{
  "type": "Feature",
  "properties": {
    "iso:country":"US",
    "sg:address":"8724 G St",
    "sg:city":"Oakland",
    "sg:classifiers":[
        {
            "category":"Freight",
            "type":"Transportation"
        }
    ],
    "sg:phone":"+1 510 635 8292",
    "sg:postcode":"94621",
    "sg:province":"CA",
    "sg:tags":[
        "trucking"
    ],
    "wof:name":"Allstar Transport Inc",
    "wof:placetype":"venue"
},
  "geometry": {"coordinates":[-122.18403499999999,37.747432],"type":"Point"}
}