{
  "type": "Feature",
  "properties": {
    "addr:full":"4654 Via Palma La Mesa CA 91941",
    "addr:housenumber":"4654",
    "addr:postcode":"91941",
    "addr:street":"Via Palma",
    "iso:country":"US",
    "sg:address":"4654 Via Palma",
    "sg:city":"La Mesa",
    "sg:classifiers":[
        {
            "category":"Personal",
            "subcategory":"Beauty Salon",
            "type":"Services"
        }
    ],
    "sg:phone":"+1 619 589 2920",
    "sg:postcode":"91941",
    "sg:province":"CA",
    "wof:name":"Sheri Powers",
    "wof:placetype":"venue"
},
  "geometry": {"coordinates":[-116.953273,32.745867],"type":"Point"}
}