{
  "type": "Feature",
  "properties": {
    "iso:country":"US",
    "sg:address":"509 N Coast Hwy",
    "sg:city":"Oceanside",
    "sg:classifiers":[
        {
            "category":"Real Estate",
            "subcategory":"Real Estate Services",
            "type":"Services"
        }
    ],
    "sg:phone":"+1 760 966 7040",
    "sg:postcode":"92054",
    "sg:province":"CA",
    "sg:tags":[
        "management",
        "property"
    ],
    "sg:website":"www.bluepacificrealtors.com",
    "wof:name":"Blue Pacific Realtors",
    "wof:placetype":"venue"
},
  "geometry": {"coordinates":[-117.382234,33.198698],"type":"Point"}
}