{
  "type": "Feature",
  "properties": {
    "addr:full":"1421 McCarthy Blvd. Milpitas  CA 95035",
    "addr:housenumber":"1421",
    "addr:postcode":"95035",
    "addr:street":"Mccarthy Blvd.",
    "iso:country":"US",
    "sg:address":"1421 McCarthy Blvd.",
    "sg:city":"Milpitas ",
    "sg:classifiers":[
        {
            "category":"Professional",
            "subcategory":"Business Services",
            "type":"Services"
        }
    ],
    "sg:phone":"+1 408 965 3300",
    "sg:postcode":"95035",
    "sg:province":"CA",
    "sg:website":"http://www.xbow.com/",
    "wof:name":"Crossbow Technologies",
    "wof:placetype":"venue"
},
  "geometry": {"coordinates":[-121.92148400000001,37.409354],"type":"Point"}
}