{
  "type": "Feature",
  "properties": {
    "addr:full":"10161 Bolsa Ave Westminster CA 92683",
    "addr:housenumber":"10161",
    "addr:postcode":"92683",
    "addr:street":"Bolsa Ave",
    "iso:country":"US",
    "sg:address":"10161 Bolsa Ave",
    "sg:city":"Westminster",
    "sg:classifiers":[
        {
            "category":"Real Estate",
            "subcategory":"Real Estate Services",
            "type":"Services"
        },
        {
            "category":"Real Estate",
            "subcategory":"Real Estate Agent",
            "type":"Services"
        }
    ],
    "sg:phone":"+1 714 775 7100",
    "sg:postcode":"92683",
    "sg:province":"CA",
    "sg:tags":[
        "buyer",
        "management",
        "broker"
    ],
    "wof:name":"Hpt Realty & Finance",
    "wof:placetype":"venue"
},
  "geometry": {"coordinates":[-117.95120199999999,33.745049],"type":"Point"}
}