{
  "type": "Feature",
  "properties": {
    "iso:country":"US",
    "sg:address":"6747 Fallbrook Ave",
    "sg:city":"West Hills",
    "sg:classifiers":[
        {
            "category":"Shopping",
            "subcategory":"Clothing, Apparel, & Fashions",
            "type":"Retail Goods"
        }
    ],
    "sg:phone":"+1 818 884 0837",
    "sg:postcode":"91307",
    "sg:province":"CA",
    "sg:website":"www.oldnavy.com",
    "wof:name":"Old Navy",
    "wof:placetype":"venue"
},
  "geometry": {"coordinates":[-118.62344899999999,34.191462],"type":"Point"}
}