{
  "type": "Feature",
  "properties": {
    "iso:country":"US",
    "sg:address":"633 N Spring St Ste 6",
    "sg:city":"Los Angeles",
    "sg:classifiers":[
        {
            "category":"Bakery",
            "type":"Food & Drink"
        }
    ],
    "sg:phone":"+1 213 680 7855",
    "sg:postcode":"90012",
    "sg:province":"CA",
    "wof:name":"Amy Bakery",
    "wof:placetype":"venue"
},
  "geometry": {"coordinates":[-118.237999,34.0588],"type":"Point"}
}