{
  "type": "Feature",
  "properties": {
    "iso:country":"US",
    "sg:address":"20315 Ventura Blvd Ste A",
    "sg:city":"Woodland Hills",
    "sg:classifiers":[
        {
            "category":"Health Services",
            "subcategory":"Chiropractor",
            "type":"Services"
        }
    ],
    "sg:phone":"+1 818 710 0800",
    "sg:postcode":"91364",
    "sg:province":"CA",
    "wof:name":"Esudri Chiropractic",
    "wof:placetype":"venue"
},
  "geometry": {"coordinates":[-118.575249,34.169375],"type":"Point"}
}