{
  "type": "Feature",
  "properties": {
    "iso:country":"US",
    "sg:address":"7638 N Meridian Rd",
    "sg:city":"Vacaville",
    "sg:classifiers":[
        {
            "category":"Shopping",
            "subcategory":"Bicycles & Sporting Goods",
            "type":"Retail Goods"
        }
    ],
    "sg:phone":"+1 707 678 3512",
    "sg:postcode":"95688",
    "sg:province":"CA",
    "sg:tags":[
        "boarding",
        "shop",
        "lesson",
        "saddle"
    ],
    "wof:name":"Buckeye Ranch & Saddle Shop",
    "wof:placetype":"venue"
},
  "geometry": {"coordinates":[-121.91550100000001,38.435708],"type":"Point"}
}