{
  "type": "Feature",
  "properties": {
    "addr:full":"6709 Reseda Blvd Reseda CA 91335",
    "addr:housenumber":"6709",
    "addr:postcode":"91335",
    "addr:street":"Reseda Blvd",
    "iso:country":"US",
    "sg:address":"6709 Reseda Blvd",
    "sg:city":"Reseda",
    "sg:classifiers":[
        {
            "category":"Autos & Motor Vehicles",
            "subcategory":"Automobile Sales",
            "type":"Retail Goods"
        }
    ],
    "sg:phone":"+1 818 881 5555",
    "sg:postcode":"91335",
    "sg:province":"CA",
    "sg:tags":[
        "dealers-used",
        "car",
        "used",
        "cars-wholesale"
    ],
    "wof:name":"Green Light Enterprises Inc",
    "wof:placetype":"venue"
},
  "geometry": {"coordinates":[-118.536034,34.192531],"type":"Point"}
}