{
  "type": "Feature",
  "properties": {
    "addr:full":"350 N Kilroy Rd Turlock CA 95380",
    "addr:housenumber":"350",
    "addr:postcode":"95380",
    "addr:street":"N Kilroy Rd",
    "iso:country":"US",
    "sg:address":"350 N Kilroy Rd",
    "sg:city":"Turlock",
    "sg:classifiers":[
        {
            "category":"Social Services",
            "subcategory":"Child Care",
            "type":"Services"
        }
    ],
    "sg:phone":"+1 209 669 6374",
    "sg:postcode":"95380",
    "sg:province":"CA",
    "sg:tags":[
        "nursery",
        "day"
    ],
    "wof:name":"Central California Child Development Services",
    "wof:placetype":"venue"
},
  "geometry": {"coordinates":[-120.876341,37.493424],"type":"Point"}
}