{
  "type": "Feature",
  "properties": {
    "addr:full":"716 57th St Sacramento CA 95819",
    "addr:housenumber":"716",
    "addr:postcode":"95819",
    "addr:street":"57Th St",
    "iso:country":"US",
    "sg:address":"716 57th St",
    "sg:city":"Sacramento",
    "sg:classifiers":[
        {
            "category":"Sports & Exercise",
            "subcategory":"Gym",
            "type":"Entertainment"
        }
    ],
    "sg:phone":"+1 916 451 8100",
    "sg:postcode":"95819",
    "sg:province":"CA",
    "sg:tags":[
        "instruction",
        "yoga"
    ],
    "sg:website":"www.sacramentoyoga.net",
    "wof:name":"East Sac Yoga Studio",
    "wof:placetype":"venue"
},
  "geometry": {"coordinates":[-121.432787,38.567738],"type":"Point"}
}