{
  "type": "Feature",
  "properties": {
    "iso:country":"US",
    "sg:address":"31431 Santa Margarita Pkwy",
    "sg:city":"Rcho Sta Marg",
    "sg:classifiers":[
        {
            "category":"Restaurant",
            "type":"Food & Drink"
        }
    ],
    "sg:phone":"+1 949 459 7750",
    "sg:postcode":"92688",
    "sg:province":"CA",
    "wof:name":"East Coast Bagel",
    "wof:placetype":"venue"
},
  "geometry": {"coordinates":[-117.58259200000001,33.648646],"type":"Point"}
}