{
  "type": "Feature",
  "properties": {
    "addr:full":"360 San Miguel Dr Newport Beach CA 92660",
    "addr:housenumber":"360",
    "addr:postcode":"92660",
    "addr:street":"San Miguel Dr",
    "iso:country":"US",
    "sg:address":"360 San Miguel Dr",
    "sg:city":"Newport Beach",
    "sg:classifiers":[
        {
            "category":"Health Services",
            "subcategory":"Doctor",
            "type":"Services"
        }
    ],
    "sg:phone":"+1 949 759 4733",
    "sg:postcode":"92660",
    "sg:province":"CA",
    "sg:tags":[
        "physician",
        "surgeon"
    ],
    "wof:name":"Val Lambros MD",
    "wof:placetype":"venue"
},
  "geometry": {"coordinates":[-117.87157999999999,33.612423],"type":"Point"}
}