{
  "type": "Feature",
  "properties": {
    "addr:full":"1957 W Winton Ave Hayward CA 94545",
    "addr:housenumber":"1957",
    "addr:postcode":"94545",
    "addr:street":"W Winton Ave",
    "iso:country":"US",
    "sg:address":"1957 W Winton Ave",
    "sg:city":"Hayward",
    "sg:classifiers":[
        {
            "category":"Autos & Motor Vehicles",
            "subcategory":"Motorcycle Sales",
            "type":"Retail Goods"
        },
        {
            "category":"Retail",
            "subcategory":"Auto Repair",
            "type":"Services"
        }
    ],
    "sg:phone":"+1 510 785 4396",
    "sg:postcode":"94545",
    "sg:province":"CA",
    "wof:name":"Wheel Works",
    "wof:placetype":"venue"
},
  "geometry": {"coordinates":[-122.129862,37.652947],"type":"Point"}
}