{
  "type": "Feature",
  "properties": {
    "addr:full":"6300 27th St Ste B Sacramento CA 95822",
    "addr:housenumber":"6300",
    "addr:postcode":"95822",
    "addr:street":"27Th St Ste B",
    "iso:country":"US",
    "sg:address":"6300 27th St Ste B",
    "sg:city":"Sacramento",
    "sg:classifiers":[
        {
            "category":"Retail",
            "subcategory":"Auto Repair",
            "type":"Services"
        }
    ],
    "sg:phone":"+1 916 399 1672",
    "sg:postcode":"95822",
    "sg:province":"CA",
    "sg:tags":[
        "body",
        "shop"
    ],
    "wof:name":"Long Auto Body",
    "wof:placetype":"venue"
},
  "geometry": {"coordinates":[-121.47765099999999,38.511705],"type":"Point"}
}