{
  "type": "Feature",
  "properties": {
    "addr:full":"5566 Alhambra Ave Los Angeles CA 90032",
    "addr:housenumber":"5566",
    "addr:postcode":"90032",
    "addr:street":"Alhambra Ave",
    "iso:country":"US",
    "sg:address":"5566 Alhambra Ave",
    "sg:city":"Los Angeles",
    "sg:classifiers":[
        {
            "category":"Manufacturing",
            "subcategory":"Printing",
            "type":"Manufacturing & Wholesale Goods"
        }
    ],
    "sg:phone":"+1 323 223 2998",
    "sg:postcode":"90032",
    "sg:province":"CA",
    "sg:tags":[
        "commercial"
    ],
    "wof:name":"Cruelle Designs",
    "wof:placetype":"venue"
},
  "geometry": {"coordinates":[-118.16333899999999,34.078996],"type":"Point"}
}