{
  "type": "Feature",
  "properties": {
    "addr:full":"15 McCoy Pl Simi Valley CA 93065",
    "addr:housenumber":"15",
    "addr:postcode":"93065",
    "addr:street":"Mccoy Pl",
    "iso:country":"US",
    "sg:address":"15 McCoy Pl",
    "sg:city":"Simi Valley",
    "sg:classifiers":[
        {
            "category":"Professional",
            "subcategory":"Engineering",
            "type":"Services"
        }
    ],
    "sg:phone":"+1 805 584 8862",
    "sg:postcode":"93065",
    "sg:province":"CA",
    "sg:tags":[
        "engineer"
    ],
    "wof:name":"Nac Image Techonology",
    "wof:placetype":"venue"
},
  "geometry": {"coordinates":[-118.797865,34.270327],"type":"Point"}
}