{
  "type": "Feature",
  "properties": {
    "addr:full":"13821 Newport Ave Ste 160 Tustin CA 92780",
    "addr:housenumber":"13821",
    "addr:postcode":"92780",
    "addr:street":"Newport Ave Ste 160",
    "iso:country":"US",
    "sg:address":"13821 Newport Ave Ste 160",
    "sg:city":"Tustin",
    "sg:classifiers":[
        {
            "category":"Professional",
            "subcategory":"Accounting & Tax Preparation",
            "type":"Services"
        }
    ],
    "sg:phone":"+1 714 665 2250",
    "sg:postcode":"92780",
    "sg:province":"CA",
    "sg:tags":[
        "accountant"
    ],
    "wof:name":"Degrange Arthur J CPA",
    "wof:placetype":"venue"
},
  "geometry": {"coordinates":[-117.81999999999999,33.740101],"type":"Point"}
}