{
  "type": "Feature",
  "properties": {
    "addr:full":"1140 Abbott St Salinas CA 93901",
    "addr:housenumber":"1140",
    "addr:postcode":"93901",
    "addr:street":"Abbott St",
    "iso:country":"US",
    "sg:address":"1140 Abbott St",
    "sg:city":"Salinas",
    "sg:classifiers":[
        {
            "category":"Professional",
            "subcategory":"Management & Consulting",
            "type":"Services"
        }
    ],
    "sg:phone":"+1 831 759 2553",
    "sg:postcode":"93901",
    "sg:province":"CA",
    "sg:tags":[
        "agricultural",
        "consultant"
    ],
    "wof:name":"Fallen Oak Packing",
    "wof:placetype":"venue"
},
  "geometry": {"coordinates":[-121.632716,36.655112],"type":"Point"}
}