{
  "type": "Feature",
  "properties": {
    "iso:country":"US",
    "sg:address":"6175 Stockton Blvd",
    "sg:city":"Sacramento",
    "sg:classifiers":[
        {
            "category":"Restaurant",
            "type":"Food & Drink"
        }
    ],
    "sg:phone":"+1 916 428 9411",
    "sg:postcode":"95824",
    "sg:province":"CA",
    "wof:name":"Papaya House",
    "wof:placetype":"venue"
},
  "geometry": {"coordinates":[-121.436763,38.512733],"type":"Point"}
}