{
  "type": "Feature",
  "properties": {
    "addr:full":"1849 98th Ave Oakland CA 94603",
    "addr:housenumber":"1849",
    "addr:postcode":"94603",
    "addr:street":"98Th Ave",
    "iso:country":"US",
    "sg:address":"1849 98th Ave",
    "sg:city":"Oakland",
    "sg:classifiers":[
        {
            "category":"Retail",
            "subcategory":"Self-service Laundry",
            "type":"Services"
        }
    ],
    "sg:phone":"+1 510 562 8347",
    "sg:postcode":"94603",
    "sg:province":"CA",
    "wof:name":"Neighborhood Wash & Dry",
    "wof:placetype":"venue"
},
  "geometry": {"coordinates":[-122.16560699999999,37.746755],"type":"Point"}
}