{
  "type": "Feature",
  "properties": {
    "addr:full":"13713 Doublegrove St Baldwin Park CA 91706",
    "addr:housenumber":"13713",
    "addr:postcode":"91706",
    "addr:street":"Doublegrove St",
    "iso:country":"US",
    "sg:address":"13713 Doublegrove St",
    "sg:city":"Baldwin Park",
    "sg:classifiers":[
        {
            "category":"Manufacturing",
            "subcategory":"Furniture",
            "type":"Manufacturing & Wholesale Goods"
        }
    ],
    "sg:phone":"+1 626 960 5776",
    "sg:postcode":"91706",
    "sg:province":"CA",
    "sg:tags":[
        "drapery",
        "mfg"
    ],
    "wof:name":"M G Verticals",
    "wof:placetype":"venue"
},
  "geometry": {"coordinates":[-117.97519800000001,34.070522],"type":"Point"}
}