{
  "type": "Feature",
  "properties": {
    "addr:full":"137 Cronin Dr Santa Clara CA 95051",
    "addr:housenumber":"137",
    "addr:postcode":"95051",
    "addr:street":"Cronin Dr",
    "iso:country":"US",
    "sg:address":"137 Cronin Dr",
    "sg:city":"Santa Clara",
    "sg:classifiers":[
        {
            "category":"Organizations",
            "subcategory":"Religious Organization",
            "type":"Services"
        }
    ],
    "sg:phone":"+1 408 554 6529",
    "sg:postcode":"95051",
    "sg:province":"CA",
    "sg:tags":[
        "church"
    ],
    "wof:name":"Church Of The New Life",
    "wof:placetype":"venue"
},
  "geometry": {"coordinates":[-121.986575,37.32562],"type":"Point"}
}