{
  "type": "Feature",
  "properties": {
    "addr:full":"671 S Beach Blvd La Habra CA 90631",
    "addr:housenumber":"671",
    "addr:postcode":"90631",
    "addr:street":"S Beach Blvd",
    "iso:country":"US",
    "sg:address":"671 S Beach Blvd",
    "sg:city":"La Habra",
    "sg:classifiers":[
        {
            "category":"Food & Beverages",
            "subcategory":"Groceries & Convenience Stores",
            "type":"Retail Goods"
        }
    ],
    "sg:phone":"+1 562 691 4417",
    "sg:postcode":"90631",
    "sg:province":"CA",
    "wof:name":"Shop & Go Markets",
    "wof:placetype":"venue"
},
  "geometry": {"coordinates":[-117.968002,33.925201],"type":"Point"}
}