{
  "type": "Feature",
  "properties": {
    "addr:full":"13929 S Hughes Ave Caruthers CA 93609",
    "addr:housenumber":"13929",
    "addr:postcode":"93609",
    "addr:street":"S Hughes Ave",
    "iso:country":"US",
    "sg:address":"13929 S Hughes Ave",
    "sg:city":"Caruthers",
    "sg:classifiers":[
        {
            "category":"Shopping",
            "subcategory":"Gifts & Souvenirs",
            "type":"Retail Goods"
        }
    ],
    "sg:phone":"+1 559 864 3890",
    "sg:postcode":"93609",
    "sg:province":"CA",
    "sg:tags":[
        "shop"
    ],
    "wof:name":"Trendy Treasures",
    "wof:placetype":"venue"
},
  "geometry": {"coordinates":[-119.835947,36.534382],"type":"Point"}
}