{
  "type": "Feature",
  "properties": {
    "addr:full":"10020 San Pablo Avenue El Cerrito CA 94530",
    "addr:housenumber":"10020",
    "addr:postcode":"94530",
    "addr:street":"San Pablo Avenue",
    "iso:country":"US",
    "sg:address":"10020 San Pablo Avenue",
    "sg:city":"El Cerrito",
    "sg:classifiers":[
        {
            "category":"Shopping",
            "subcategory":"Comic Books",
            "type":"Retail Goods"
        }
    ],
    "sg:phone":"+1 510 525 3223",
    "sg:postcode":"94530",
    "sg:province":"CA",
    "wof:name":"Stand-Up Comics",
    "wof:placetype":"venue"
},
  "geometry": {"coordinates":[-122.30300099999999,37.901001],"type":"Point"}
}