{
  "type": "Feature",
  "properties": {
    "iso:country":"US",
    "sg:address":"3242 Greyling Dr",
    "sg:city":"San Diego",
    "sg:classifiers":[
        {
            "category":"Personal",
            "subcategory":"Beauty Salon",
            "type":"Services"
        }
    ],
    "sg:phone":"+1 858 268 7710",
    "sg:postcode":"92123",
    "sg:province":"CA",
    "sg:tags":[
        "nail",
        "manicuring"
    ],
    "wof:name":"Mai's Nails",
    "wof:placetype":"venue"
},
  "geometry": {"coordinates":[-117.139,32.8022],"type":"Point"}
}