{
  "type": "Feature",
  "properties": {
    "iso:country":"US",
    "sg:address":"8343 Laurel Canyon Blvd",
    "sg:city":"Sun Valley",
    "sg:classifiers":[
        {
            "category":"Shopping",
            "subcategory":"Clothing, Apparel, & Fashions",
            "type":"Retail Goods"
        }
    ],
    "sg:phone":"+1 818 252 5982",
    "sg:postcode":"91352",
    "sg:province":"CA",
    "sg:tags":[
        "accessory",
        "clothing",
        "women's"
    ],
    "sg:website":"www.avenue.com",
    "wof:name":"Avenue",
    "wof:placetype":"venue"
},
  "geometry": {"coordinates":[-118.397003,34.2225],"type":"Point"}
}