{
  "type": "Feature",
  "properties": {
    "addr:full":"1307 Limekiln Rd Hollister CA 95043",
    "addr:housenumber":"1307",
    "addr:postcode":"hollister ca 95043",
    "addr:street":"Limekiln Rd",
    "iso:country":"US",
    "sg:address":"1307 Limekiln Rd",
    "sg:city":"Hollister",
    "sg:classifiers":[
        {
            "category":"Farming",
            "subcategory":"Livestock Farm",
            "type":"Manufacturing & Wholesale Goods"
        }
    ],
    "sg:phone":"+1 831 637 9495",
    "sg:postcode":"95043",
    "sg:province":"CA",
    "sg:tags":[
        "animal",
        "general"
    ],
    "wof:name":"Libby Ranch",
    "wof:placetype":"venue"
},
  "geometry": {"coordinates":[-121.33945799999999,36.692538],"type":"Point"}
}