{
  "type": "Feature",
  "properties": {
    "iso:country":"US",
    "sg:address":"925 Blossom Hill Rd Ste 1637",
    "sg:city":"San Jose",
    "sg:classifiers":[
        {
            "category":"Restaurant",
            "type":"Food & Drink"
        }
    ],
    "sg:phone":"+1 408 229 0777",
    "sg:postcode":"95123",
    "sg:province":"CA",
    "sg:tags":[
        "sushi",
        "bar",
        "japanese"
    ],
    "wof:name":"Sushi Boat",
    "wof:placetype":"venue"
},
  "geometry": {"coordinates":[-121.86166799999999,37.252492],"type":"Point"}
}