{
  "type": "Feature",
  "properties": {
    "addr:full":"2546 Nye St San Diego CA 92111",
    "addr:housenumber":"2546",
    "addr:postcode":"92111",
    "addr:street":"Nye St",
    "iso:country":"US",
    "sg:address":"2546 Nye St",
    "sg:city":"San Diego",
    "sg:classifiers":[
        {
            "category":"Banks & Credit Unions",
            "subcategory":"Financial Services",
            "type":"Services"
        }
    ],
    "sg:phone":"+1 858 560 8600",
    "sg:postcode":"92111",
    "sg:province":"CA",
    "sg:tags":[
        "trust",
        "management"
    ],
    "wof:name":"Turner Clipper Jr Trust",
    "wof:placetype":"venue"
},
  "geometry": {"coordinates":[-117.17624000000001,32.79052],"type":"Point"}
}