{
  "type": "Feature",
  "properties": {
    "iso:country":"US",
    "sg:address":"1321 Wilson St",
    "sg:city":"Los Angeles",
    "sg:classifiers":[
        {
            "category":"Manufacturing",
            "subcategory":"Metals",
            "type":"Manufacturing & Wholesale Goods"
        }
    ],
    "sg:phone":"+1 213 627 7755",
    "sg:postcode":"90021",
    "sg:province":"CA",
    "sg:tags":[
        "recovering",
        "refining",
        "nonferrous"
    ],
    "wof:name":"Martin Metals",
    "wof:placetype":"venue"
},
  "geometry": {"coordinates":[-118.23492400000001,34.026079],"type":"Point"}
}