{
  "type": "Feature",
  "properties": {
    "iso:country":"US",
    "sg:address":"1527 Olympic Cir",
    "sg:city":"Rocklin",
    "sg:classifiers":[
        {
            "category":"Banks & Credit Unions",
            "subcategory":"Investment Brokerage",
            "type":"Services"
        },
        {
            "category":"Banks & Credit Unions",
            "subcategory":"Financial Services",
            "type":"Services"
        }
    ],
    "sg:phone":"+1 916 792 3221",
    "sg:postcode":"95765",
    "sg:province":"CA",
    "sg:tags":[
        "advisory",
        "planner"
    ],
    "wof:name":"Cam Investment Firm",
    "wof:placetype":"venue"
},
  "geometry": {"coordinates":[-121.289563,38.801481],"type":"Point"}
}