{
  "type": "Feature",
  "properties": {
    "addr:full":"7170 Bandini Blvd Commerce CA 90040",
    "addr:housenumber":"7170",
    "addr:postcode":"90040",
    "addr:street":"Bandini Blvd",
    "iso:country":"US",
    "sg:address":"7170 Bandini Blvd",
    "sg:city":"Commerce",
    "sg:classifiers":[
        {
            "category":"Retail",
            "subcategory":"Auto Rental",
            "type":"Services"
        }
    ],
    "sg:phone":"+1 800 333 3020",
    "sg:postcode":"90040",
    "sg:province":"CA",
    "sg:tags":[
        "renting",
        "leasing",
        "trailer"
    ],
    "wof:name":"Tip-Transport Intl. Pool",
    "wof:placetype":"venue"
},
  "geometry": {"coordinates":[-118.13467300000001,33.984978],"type":"Point"}
}