{
  "type": "Feature",
  "properties": {
    "iso:country":"US",
    "sg:address":"1295 Shaw Ave",
    "sg:city":"Clovis",
    "sg:classifiers":[
        {
            "category":"Professional",
            "type":"Services"
        }
    ],
    "sg:phone":"+1 559 325 2993",
    "sg:postcode":"93612",
    "sg:province":"CA",
    "wof:name":"Sea Breeze Cruises",
    "wof:placetype":"venue"
},
  "geometry": {"coordinates":[-119.695211,36.808577],"type":"Point"}
}