{
  "type": "Feature",
  "properties": {
    "iso:country":"US",
    "sg:address":"813 State Rte 66",
    "sg:city":"Glendora",
    "sg:classifiers":[
        {
            "category":"Education",
            "subcategory":"Dance Studio",
            "type":"Public Place"
        }
    ],
    "sg:phone":"+1 626 335 6940",
    "sg:postcode":"91740",
    "sg:province":"CA",
    "sg:tags":[
        "instruction",
        "dancing"
    ],
    "wof:name":"Larson Academy Of Traditional",
    "wof:placetype":"venue"
},
  "geometry": {"coordinates":[-117.851933,34.128771],"type":"Point"}
}