{
  "type": "Feature",
  "properties": {
    "addr:full":"711 Highland Ave Piedmont CA 94611",
    "addr:housenumber":"711",
    "addr:postcode":"94611",
    "addr:street":"Highland Ave",
    "iso:country":"US",
    "sg:address":"711 Highland Ave",
    "sg:city":"Piedmont",
    "sg:classifiers":[
        {
            "category":"Park",
            "type":"Public Place"
        }
    ],
    "sg:postcode":"94611",
    "sg:province":"CA",
    "wof:name":"Piedmont Park",
    "wof:placetype":"venue"
},
  "geometry": {"coordinates":[-122.22983000000001,37.823942],"type":"Point"}
}