{
  "type": "Feature",
  "properties": {
    "addr:full":"3967 Missouri Flat Rd Placerville CA 95667",
    "addr:housenumber":"3967",
    "addr:postcode":"95667",
    "addr:street":"Missouri Flat Rd",
    "iso:country":"US",
    "sg:address":"3967 Missouri Flat Rd",
    "sg:city":"Placerville",
    "sg:classifiers":[
        {
            "category":"Restaurant",
            "type":"Food & Drink"
        }
    ],
    "sg:menulink":"http://www.allmenus.com/ca/north-el-dorado/123696-quiznos-sub/menu/",
    "sg:phone":"+1 530 622 7878",
    "sg:postcode":"95667",
    "sg:province":"CA",
    "sg:tags":[
        "wrap",
        "american",
        "sandwich"
    ],
    "wof:name":"Quiznos Sub",
    "wof:placetype":"venue"
},
  "geometry": {"coordinates":[-120.83898000000001,38.713247],"type":"Point"}
}