{
  "type": "Feature",
  "properties": {
    "iso:country":"US",
    "sg:address":"4649 Saloma Ave",
    "sg:city":"Sherman Oaks",
    "sg:classifiers":[
        {
            "category":"Professional",
            "subcategory":"Computer Services",
            "type":"Services"
        }
    ],
    "sg:phone":"+1 818 995 7630",
    "sg:postcode":"91403",
    "sg:province":"CA",
    "sg:tags":[
        "information",
        "search",
        "retrieval"
    ],
    "wof:name":"Gold Rush Asset Recovery",
    "wof:placetype":"venue"
},
  "geometry": {"coordinates":[-118.458589,34.155537],"type":"Point"}
}