{
  "type": "Feature",
  "properties": {
    "addr:full":"9464 Circle R Dr Escondido CA 92026",
    "addr:housenumber":"9464",
    "addr:postcode":"92026",
    "addr:street":"Circle R Dr",
    "iso:country":"US",
    "sg:address":"9464 Circle R Dr",
    "sg:city":"Escondido",
    "sg:classifiers":[
        {
            "category":"Manufacturing",
            "subcategory":"Musical Instruments",
            "type":"Manufacturing & Wholesale Goods"
        }
    ],
    "sg:phone":"+1 760 749 1933",
    "sg:postcode":"92026",
    "sg:province":"CA",
    "sg:tags":[
        "instruments-industrial-repairing"
    ],
    "sg:website":"http://www.johnsfarmletservices.com",
    "wof:name":"Johns Farm Service",
    "wof:placetype":"venue"
},
  "geometry": {"coordinates":[-117.14390899999999,33.25577],"type":"Point"}
}