{
  "type": "Feature",
  "properties": {
    "addr:full":"39 S San Joaquin St Stockton CA 95202",
    "addr:housenumber":"39",
    "addr:postcode":"95202",
    "addr:street":"S San Joaquin St",
    "iso:country":"US",
    "sg:address":"39 S San Joaquin St",
    "sg:city":"Stockton",
    "sg:classifiers":[
        {
            "category":"Retail",
            "subcategory":"Repair Shop",
            "type":"Services"
        }
    ],
    "sg:phone":"+1 209 547 1668",
    "sg:postcode":"95202",
    "sg:province":"CA",
    "sg:tags":[
        "jewelry"
    ],
    "wof:name":"Guillermo's Jewelers",
    "wof:placetype":"venue"
},
  "geometry": {"coordinates":[-121.287064,37.952525],"type":"Point"}
}