{
  "type": "Feature",
  "properties": {
    "addr:full":"3800 Barham Boulevard Suite 503 Los Angeles CA 90068",
    "addr:housenumber":"3800",
    "addr:postcode":"90068",
    "addr:street":"Barham Boulevard Suite 503",
    "iso:country":"US",
    "sg:address":"3800 Barham Boulevard Suite 503",
    "sg:city":"Los Angeles",
    "sg:classifiers":[
        {
            "category":"Arts & Performance",
            "subcategory":"Arts Center",
            "type":"Entertainment"
        }
    ],
    "sg:phone":"+1 323 874 2009",
    "sg:postcode":"90068",
    "sg:province":"CA",
    "sg:tags":[
        "performing"
    ],
    "wof:name":"Quincy Jones Productions",
    "wof:placetype":"venue"
},
  "geometry": {"coordinates":[-118.34118599999999,34.14366],"type":"Point"}
}