{
  "type": "Feature",
  "properties": {
    "addr:full":"1000 Continentals Way Belmont CA 94002",
    "addr:housenumber":"1000",
    "addr:postcode":"94002",
    "addr:street":"Continentals Way",
    "iso:country":"US",
    "sg:address":"1000 Continentals Way",
    "sg:city":"Belmont",
    "sg:classifiers":[
        {
            "category":"Real Estate",
            "subcategory":"Real Estate Operator",
            "type":"Services"
        }
    ],
    "sg:phone":"+1 650 592 8428",
    "sg:postcode":"94002",
    "sg:province":"CA",
    "sg:tags":[
        "apartment"
    ],
    "sg:website":"http://www.belmontrentals.com",
    "wof:name":"Timberlane Apartments",
    "wof:placetype":"venue"
},
  "geometry": {"coordinates":[-122.304001,37.5117],"type":"Point"}
}