{
  "type": "Feature",
  "properties": {
    "addr:full":"435 S Molino St Los Angeles CA 90013",
    "addr:housenumber":"435",
    "addr:postcode":"90013",
    "addr:street":"S Molino St",
    "iso:country":"US",
    "sg:address":"435 S Molino St",
    "sg:city":"Los Angeles",
    "sg:classifiers":[
        {
            "category":"Arts & Performance",
            "subcategory":"Arts Center",
            "type":"Entertainment"
        },
        {
            "category":"Retail",
            "subcategory":"Event Space",
            "type":"Services"
        }
    ],
    "sg:phone":"+1 213 253 2623",
    "sg:postcode":"90013",
    "sg:province":"CA",
    "sg:tags":[
        "venue"
    ],
    "sg:website":"kessprostudios.com/",
    "wof:name":"KESSPRO Studios",
    "wof:placetype":"venue"
},
  "geometry": {"coordinates":[-118.234089,34.042014],"type":"Point"}
}