{
  "type": "Feature",
  "properties": {
    "addr:full":"7911 Seville Ave Huntington Park CA 90255",
    "addr:housenumber":"7911",
    "addr:postcode":"90255",
    "addr:street":"Seville Ave;Park",
    "iso:country":"US",
    "sg:address":"7911 Seville Ave",
    "sg:city":"Huntington Park",
    "sg:classifiers":[
        {
            "category":"Personal",
            "subcategory":"Beauty Salon",
            "type":"Services"
        }
    ],
    "sg:phone":"+1 323 581 9833",
    "sg:postcode":"90255",
    "sg:province":"CA",
    "wof:name":"Reyna's Beauty Salon",
    "wof:placetype":"venue"
},
  "geometry": {"coordinates":[-118.222454,33.965631],"type":"Point"}
}