{
  "type": "Feature",
  "properties": {
    "iso:country":"US",
    "sg:address":"675 US Hwy 101",
    "sg:city":"Crescent City",
    "sg:classifiers":[
        {
            "category":"Restaurant",
            "type":"Food & Drink"
        }
    ],
    "sg:phone":"+1 707 465 5656",
    "sg:postcode":"95531",
    "sg:province":"CA",
    "wof:name":"Northwoods Restaurant",
    "wof:placetype":"venue"
},
  "geometry": {"coordinates":[-124.195503,41.75679],"type":"Point"}
}