{
  "type": "Feature",
  "properties": {
    "iso:country":"US",
    "sg:address":"311 Twin Ridge Dr",
    "sg:city":"San Luis Obispo",
    "sg:classifiers":[
        {
            "category":"Professional",
            "type":"Services"
        }
    ],
    "sg:phone":"+1 805 541 5141",
    "sg:postcode":"93405",
    "sg:province":"CA",
    "wof:name":"Maulhardt Foundation Inc",
    "wof:placetype":"venue"
},
  "geometry": {"coordinates":[-120.68283,35.305319],"type":"Point"}
}