{
  "type": "Feature",
  "properties": {
    "iso:country":"US",
    "sg:address":"1511 S Elk Rd",
    "sg:city":"Anaheim",
    "sg:classifiers":[
        {
            "category":"Freight",
            "type":"Transportation"
        }
    ],
    "sg:phone":"+1 800 510 0111",
    "sg:postcode":"92804",
    "sg:province":"CA",
    "sg:tags":[
        "material",
        "trucking",
        "moving",
        "services-labor",
        "operator",
        "local"
    ],
    "sg:website":"http://www.amazingpianomovers.com",
    "wof:name":"Amazing Movers",
    "wof:placetype":"venue"
},
  "geometry": {"coordinates":[-117.95685,33.810491],"type":"Point"}
}