{
  "type": "Feature",
  "properties": {
    "addr:full":"839 Larkin St San Francisco CA 94109",
    "addr:housenumber":"839",
    "addr:postcode":"94109",
    "addr:street":"Larkin St",
    "iso:country":"US",
    "sg:address":"839 Larkin St",
    "sg:city":"San Francisco",
    "sg:classifiers":[
        {
            "category":"Shopping",
            "type":"Retail Goods"
        }
    ],
    "sg:phone":"+1 415 931 8035",
    "sg:postcode":"94109",
    "sg:province":"CA",
    "sg:tags":[
        "art",
        "gallery"
    ],
    "sg:website":"www.shootinggallerysf.com/",
    "wof:name":"Shooting Gallery",
    "wof:placetype":"venue"
},
  "geometry": {"coordinates":[-122.418058,37.785803],"type":"Point"}
}