{
  "type": "Feature",
  "properties": {
    "iso:country":"US",
    "sg:address":"1690 Carol Dr",
    "sg:city":"Napa",
    "sg:classifiers":[
        {
            "category":"Building & Trades",
            "subcategory":"Construction",
            "type":"Services"
        }
    ],
    "sg:phone":"+1 707 226 7292",
    "sg:postcode":"94558",
    "sg:province":"CA",
    "sg:tags":[
        "hanging",
        "contractor"
    ],
    "wof:name":"Valley Color Craft Inc",
    "wof:placetype":"venue"
},
  "geometry": {"coordinates":[-122.313523,38.319309],"type":"Point"}
}