{
  "type": "Feature",
  "properties": {
    "iso:country":"US",
    "sg:address":"840 S Hilda St",
    "sg:city":"Anaheim",
    "sg:classifiers":[
        {
            "category":"Building & Trades",
            "subcategory":"Construction",
            "type":"Services"
        }
    ],
    "sg:phone":"+1 714 526 0307",
    "sg:postcode":"92806",
    "sg:province":"CA",
    "sg:tags":[
        "contractor"
    ],
    "sg:website":"www.coxtilecontractor.com",
    "wof:name":"Cox Tile Contractor",
    "wof:placetype":"venue"
},
  "geometry": {"coordinates":[-117.87799800000001,33.828602],"type":"Point"}
}