{
  "type": "Feature",
  "properties": {
    "iso:country":"US",
    "sg:address":"408 9th Avenue",
    "sg:city":"San Mateo",
    "sg:classifiers":[
        {
            "category":"Home & Garden",
            "subcategory":"Garden Supply",
            "type":"Retail Goods"
        }
    ],
    "sg:phone":"+1 650 340 8850",
    "sg:postcode":"94402",
    "sg:province":"CA",
    "sg:tags":[
        "nursery",
        "gardening"
    ],
    "sg:website":"www.centralgardencenter.biz",
    "wof:name":"Central Garden Center",
    "wof:placetype":"venue"
},
  "geometry": {"coordinates":[-122.316689,37.562265],"type":"Point"}
}