{
  "type": "Feature",
  "properties": {
    "addr:full":"103 Waverly Pl San Francisco CA 94108",
    "addr:housenumber":"103",
    "addr:postcode":"94108",
    "addr:street":"Waverly Pl",
    "iso:country":"US",
    "sg:address":"103 Waverly Pl",
    "sg:city":"San Francisco",
    "sg:classifiers":[
        {
            "category":"Manufacturing",
            "subcategory":"Printing",
            "type":"Manufacturing & Wholesale Goods"
        }
    ],
    "sg:phone":"+1 415 772 1907",
    "sg:postcode":"94108",
    "sg:province":"CA",
    "sg:tags":[
        "printer",
        "commercial"
    ],
    "wof:name":"Superprinting Corporation",
    "wof:placetype":"venue"
},
  "geometry": {"coordinates":[-122.407072,37.795047],"type":"Point"}
}