{
  "type": "Feature",
  "properties": {
    "iso:country":"US",
    "sg:address":"1040 N Magnolia Ave",
    "sg:city":"Anaheim",
    "sg:classifiers":[
        {
            "category":"Fast Food",
            "type":"Food & Drink"
        },
        {
            "category":"Restaurant",
            "type":"Food & Drink"
        }
    ],
    "sg:phone":"+1 714 761 4351",
    "sg:postcode":"92801",
    "sg:province":"CA",
    "sg:tags":[
        "burger",
        "diner"
    ],
    "wof:name":"Paul's Place",
    "wof:placetype":"venue"
},
  "geometry": {"coordinates":[-117.975998,33.845001],"type":"Point"}
}