{
  "type": "Feature",
  "properties": {
    "addr:full":"6150 Snell Ave San Jose CA 95123",
    "addr:housenumber":"6150",
    "addr:postcode":"95123",
    "addr:street":"Snell Ave",
    "iso:country":"US",
    "sg:address":"6150 Snell Ave",
    "sg:city":"San Jose",
    "sg:classifiers":[
        {
            "category":"Education",
            "subcategory":"School",
            "type":"Public Place"
        }
    ],
    "sg:postcode":"95123",
    "sg:province":"CA",
    "sg:tags":[
        "high",
        "middle"
    ],
    "sg:website":"sths.ca.campusgrid.net/home",
    "wof:name":"Santa Teresa High School",
    "wof:placetype":"venue"
},
  "geometry": {"coordinates":[-121.83058,37.235098],"type":"Point"}
}