{
  "type": "Feature",
  "properties": {
    "iso:country":"US",
    "sg:address":"1007 S Hill St",
    "sg:city":"Los Angeles",
    "sg:classifiers":[
        {
            "category":"Shopping",
            "subcategory":"Clothing, Apparel, & Fashions",
            "type":"Retail Goods"
        }
    ],
    "sg:phone":"+1 213 745 7351",
    "sg:postcode":"90015",
    "sg:province":"CA",
    "sg:tags":[
        "accessory",
        "clothing",
        "women's"
    ],
    "wof:name":"Victoria's Styles",
    "wof:placetype":"venue"
},
  "geometry": {"coordinates":[-118.259003,34.041199],"type":"Point"}
}