{
  "type": "Feature",
  "properties": {
    "iso:country":"US",
    "sg:address":"2934 Riverside Dr",
    "sg:city":"Los Angeles",
    "sg:classifiers":[
        {
            "category":"Home & Garden",
            "subcategory":"Building Materials",
            "type":"Retail Goods"
        }
    ],
    "sg:phone":"+1 323 805 0200",
    "sg:postcode":"90039",
    "sg:province":"CA",
    "sg:tags":[
        "door"
    ],
    "wof:name":"Taylor Brothers",
    "wof:placetype":"venue"
},
  "geometry": {"coordinates":[-118.266572,34.111747],"type":"Point"}
}