{
  "type": "Feature",
  "properties": {
    "addr:full":"419 Broadway Jackson CA 95642",
    "addr:housenumber":"419",
    "addr:postcode":"95642",
    "addr:street":"Broadway",
    "iso:country":"US",
    "sg:address":"419 Broadway",
    "sg:city":"Jackson",
    "sg:classifiers":[
        {
            "category":"Building & Trades",
            "subcategory":"Plumbing",
            "type":"Services"
        }
    ],
    "sg:phone":"+1 209 223 3656",
    "sg:postcode":"95642",
    "sg:province":"CA",
    "sg:tags":[
        "plumber"
    ],
    "wof:name":"Tim Voss Plumbing",
    "wof:placetype":"venue"
},
  "geometry": {"coordinates":[-120.768134,38.346539],"type":"Point"}
}