{
  "type": "Feature",
  "properties": {
    "iso:country":"US",
    "sg:address":"6230 Greenback Ln",
    "sg:city":"Citrus Heights",
    "sg:classifiers":[
        {
            "category":"Professional",
            "subcategory":"Computer Services",
            "type":"Services"
        }
    ],
    "sg:phone":"+1 916 468 0820",
    "sg:postcode":"95621",
    "sg:province":"CA",
    "sg:tags":[
        "stereo",
        "installation"
    ],
    "sg:website":"westcoastaudiocar.com",
    "wof:name":"West Coast Car Audio",
    "wof:placetype":"venue"
},
  "geometry": {"coordinates":[-121.319357,38.67804],"type":"Point"}
}