{
  "type": "Feature",
  "properties": {
    "iso:country":"US",
    "sg:address":"275 Central Ave",
    "sg:city":"Fillmore",
    "sg:classifiers":[
        {
            "category":"Organizations",
            "subcategory":"Professional Association",
            "type":"Services"
        }
    ],
    "sg:phone":"+1 805 524 0351",
    "sg:postcode":"93015",
    "sg:province":"CA",
    "sg:tags":[
        "chambers",
        "commerce"
    ],
    "sg:website":"www.fillmorechamber.com",
    "wof:name":"Fillmore Chamber Of Commerce",
    "wof:placetype":"venue"
},
  "geometry": {"coordinates":[-118.913276,34.398573],"type":"Point"}
}