{
  "type": "Feature",
  "properties": {
    "addr:full":"9829 Lemona Ave North Hills CA 91343",
    "addr:housenumber":"9829",
    "addr:postcode":"91343",
    "addr:street":"Lemona Ave",
    "iso:country":"US",
    "sg:address":"9829 Lemona Ave",
    "sg:city":"North Hills",
    "sg:classifiers":[
        {
            "category":"Building & Trades",
            "subcategory":"Construction",
            "type":"Services"
        }
    ],
    "sg:phone":"+1 818 894 4905",
    "sg:postcode":"91343",
    "sg:province":"CA",
    "sg:tags":[
        "carpenter"
    ],
    "wof:name":"F Sharp & Co",
    "wof:placetype":"venue"
},
  "geometry": {"coordinates":[-118.458808,34.247663],"type":"Point"}
}