{
  "type": "Feature",
  "properties": {
    "addr:full":"221 N Pico Ave Fallbrook CA 92028",
    "addr:housenumber":"221",
    "addr:postcode":"92028",
    "addr:street":"N Pico Ave",
    "iso:country":"US",
    "sg:address":"221 N Pico Ave",
    "sg:city":"Fallbrook",
    "sg:classifiers":[
        {
            "category":"Organizations",
            "subcategory":"Religious Organization",
            "type":"Services"
        }
    ],
    "sg:phone":"+1 760 728 7771",
    "sg:postcode":"92028",
    "sg:province":"CA",
    "wof:name":"Fallbrook First Baptist Church",
    "wof:placetype":"venue"
},
  "geometry": {"coordinates":[-117.252402,33.383024],"type":"Point"}
}