{
  "type": "Feature",
  "properties": {
    "addr:full":"150 Ave del Mar San Clemente CA 92672",
    "addr:housenumber":"150",
    "addr:postcode":"92672",
    "addr:street":"Ave Del",
    "iso:country":"US",
    "sg:address":"150 Ave del Mar",
    "sg:city":"San Clemente",
    "sg:classifiers":[
        {
            "category":"Wholesale",
            "subcategory":"Machinery & Supplies",
            "type":"Manufacturing & Wholesale Goods"
        }
    ],
    "sg:phone":"+1 949 492 8180",
    "sg:postcode":"92672",
    "sg:province":"CA",
    "sg:tags":[
        "salon",
        "beauty"
    ],
    "wof:name":"Del Mar Spa",
    "wof:placetype":"venue"
},
  "geometry": {"coordinates":[-117.613516,33.427271],"type":"Point"}
}