{
  "type": "Feature",
  "properties": {
    "addr:full":"1101 E Huntington Dr Monrovia CA 91016",
    "addr:housenumber":"1101",
    "addr:postcode":"91016",
    "addr:street":"E Huntington Dr",
    "iso:country":"US",
    "sg:address":"1101 E Huntington Dr",
    "sg:city":"Monrovia",
    "sg:classifiers":[
        {
            "category":"Restaurant",
            "type":"Food & Drink"
        }
    ],
    "sg:phone":"+1 626 357 3359",
    "sg:postcode":"91016",
    "sg:province":"CA",
    "sg:website":"www.laparisiennerestaurant.com",
    "wof:name":"LA Parisienne French Rstrnt",
    "wof:placetype":"venue"
},
  "geometry": {"coordinates":[-117.981105,34.139521],"type":"Point"}
}