{
  "type": "Feature",
  "properties": {
    "iso:country":"US",
    "sg:address":"1761 Container Cir",
    "sg:city":"Riverside",
    "sg:classifiers":[
        {
            "category":"Building & Trades",
            "subcategory":"Construction",
            "type":"Services"
        }
    ],
    "sg:phone":"+1 951 682 7576",
    "sg:postcode":"92509",
    "sg:province":"CA",
    "sg:tags":[
        "handyman"
    ],
    "wof:name":"Superior Property Maintenance",
    "wof:placetype":"venue"
},
  "geometry": {"coordinates":[-117.39104,34.022978],"type":"Point"}
}