{
  "type": "Feature",
  "properties": {
    "iso:country":"US",
    "sg:address":"452 Morro Hills Rd",
    "sg:city":"Fallbrook",
    "sg:classifiers":[
        {
            "category":"Building & Trades",
            "subcategory":"Construction",
            "type":"Services"
        }
    ],
    "sg:phone":"+1 760 451 9589",
    "sg:postcode":"92028",
    "sg:province":"CA",
    "sg:tags":[
        "general",
        "contractor"
    ],
    "wof:name":"Eagle Eye Construction",
    "wof:placetype":"venue"
},
  "geometry": {"coordinates":[-117.257115,33.301904],"type":"Point"}
}