{
  "type": "Feature",
  "properties": {
    "addr:full":"31441 Santa Margarita Pkwy Rancho Santa Margarita CA 92688",
    "addr:housenumber":"31441",
    "addr:postcode":"92688",
    "addr:street":"Santa Margarita Pkwy",
    "iso:country":"US",
    "sg:address":"31441 Santa Margarita Pkwy",
    "sg:city":"Rancho Santa Margarita",
    "sg:classifiers":[
        {
            "category":"Wholesale",
            "subcategory":"Electrical",
            "type":"Manufacturing & Wholesale Goods"
        }
    ],
    "sg:phone":"+1 949 888 8438",
    "sg:postcode":"92688",
    "sg:province":"CA",
    "sg:tags":[
        "equipment"
    ],
    "wof:name":"Wright Light Sales",
    "wof:placetype":"venue"
},
  "geometry": {"coordinates":[-117.582458,33.648631],"type":"Point"}
}