{
  "type": "Feature",
  "properties": {
    "addr:full":"5241 Elkhorn Blvd Sacramento CA 95842",
    "addr:housenumber":"5241",
    "addr:postcode":"95842",
    "addr:street":"Elkhorn Blvd",
    "iso:country":"US",
    "sg:address":"5241 Elkhorn Blvd",
    "sg:city":"Sacramento",
    "sg:classifiers":[
        {
            "category":"Real Estate",
            "subcategory":"Real Estate Agent",
            "type":"Services"
        }
    ],
    "sg:phone":"+1 916 338 8200",
    "sg:postcode":"95842",
    "sg:province":"CA",
    "wof:name":"Re/Max",
    "wof:placetype":"venue"
},
  "geometry": {"coordinates":[-121.343262,38.687486],"type":"Point"}
}