{
  "type": "Feature",
  "properties": {
    "iso:country":"US",
    "sg:address":"7950 el Capitan Dr",
    "sg:city":"La Mesa",
    "sg:classifiers":[
        {
            "category":"Building & Trades",
            "subcategory":"Landscaping Services",
            "type":"Services"
        }
    ],
    "sg:phone":"+1 619 698 4373",
    "sg:postcode":"91941",
    "sg:province":"CA",
    "sg:tags":[
        "landscape",
        "contractor"
    ],
    "wof:name":"El Burro Landscaping & Mainten",
    "wof:placetype":"venue"
},
  "geometry": {"coordinates":[-117.026278,32.768009],"type":"Point"}
}