{
  "type": "Feature",
  "properties": {
    "addr:full":"152 Kings Hwy Boulder Creek CA 95006",
    "addr:housenumber":"152",
    "addr:postcode":"95006",
    "addr:street":"Kings Hwy",
    "iso:country":"US",
    "sg:address":"152 Kings Hwy",
    "sg:city":"Boulder Creek",
    "sg:classifiers":[
        {
            "category":"Shopping",
            "subcategory":"Gifts & Souvenirs",
            "type":"Retail Goods"
        }
    ],
    "sg:phone":"+1 831 338 7368",
    "sg:postcode":"95006",
    "sg:province":"CA",
    "sg:tags":[
        "shop"
    ],
    "wof:name":"Country Home",
    "wof:placetype":"venue"
},
  "geometry": {"coordinates":[-122.161564,37.156289],"type":"Point"}
}