{
  "type": "Feature",
  "properties": {
    "addr:full":"11300 Ridge Rd Martell CA 95685",
    "addr:housenumber":"11300",
    "addr:postcode":"95685",
    "addr:street":"Ridge Rd",
    "iso:country":"US",
    "sg:address":"11300 Ridge Rd",
    "sg:city":"Martell",
    "sg:classifiers":[
        {
            "category":"Manufacturing",
            "subcategory":"Lumber",
            "type":"Manufacturing & Wholesale Goods"
        }
    ],
    "sg:phone":"+1 209 223 1690",
    "sg:postcode":"95685",
    "sg:province":"CA",
    "sg:website":"www.sierrapine.com",
    "wof:name":"Sierra Pine",
    "wof:placetype":"venue"
},
  "geometry": {"coordinates":[-120.790626,38.382259],"type":"Point"}
}