{
  "type": "Feature",
  "properties": {
    "addr:full":"245 Addison St San Francisco CA 94131",
    "addr:housenumber":"245",
    "addr:postcode":"94131",
    "addr:street":"Addison St",
    "iso:country":"US",
    "sg:address":"245 Addison St",
    "sg:city":"San Francisco",
    "sg:classifiers":[
        {
            "category":"Professional",
            "subcategory":"Art Services",
            "type":"Services"
        }
    ],
    "sg:phone":"+1 415 564 8181",
    "sg:postcode":"94131",
    "sg:province":"CA",
    "sg:tags":[
        "photographer"
    ],
    "wof:name":"Don Lane Photographs",
    "wof:placetype":"venue"
},
  "geometry": {"coordinates":[-122.430324,37.737764],"type":"Point"}
}