{
  "type": "Feature",
  "properties": {
    "iso:country":"US",
    "sg:address":"17808 Pioneer Blvd Ste 110",
    "sg:city":"Artesia",
    "sg:classifiers":[
        {
            "category":"Health Services",
            "subcategory":"Dentist",
            "type":"Services"
        }
    ],
    "sg:phone":"+1 562 468 1168",
    "sg:postcode":"90701",
    "sg:province":"CA",
    "wof:name":"Oriel Marissa Bautista Dental",
    "wof:placetype":"venue"
},
  "geometry": {"coordinates":[-118.082001,33.869301],"type":"Point"}
}