{
  "type": "Feature",
  "properties": {
    "addr:full":"1327 E 14th St Oakland CA 94606",
    "addr:housenumber":"1327",
    "addr:postcode":"94606",
    "addr:street":"E 14Th St",
    "iso:country":"US",
    "sg:address":"1327 E 14th St",
    "sg:city":"Oakland",
    "sg:classifiers":[
        {
            "category":"Freight",
            "type":"Transportation"
        }
    ],
    "sg:phone":"+1 510 536 3108",
    "sg:postcode":"94606",
    "sg:province":"CA",
    "sg:tags":[
        "general"
    ],
    "wof:name":"Public Storage Inc",
    "wof:placetype":"venue"
},
  "geometry": {"coordinates":[-122.2465,37.789503],"type":"Point"}
}