{
  "type": "Feature",
  "properties": {
    "iso:country":"US",
    "sg:address":"5339 N Fresno St",
    "sg:city":"Fresno",
    "sg:classifiers":[
        {
            "category":"Health Services",
            "subcategory":"Doctor",
            "type":"Services"
        }
    ],
    "sg:phone":"+1 559 225 1111",
    "sg:postcode":"93710",
    "sg:province":"CA",
    "sg:tags":[
        "physician",
        "clinic",
        "surgeon"
    ],
    "wof:name":"Lifepoint Wellness & Medical Ctr",
    "wof:placetype":"venue"
},
  "geometry": {"coordinates":[-119.78135399999999,36.814641],"type":"Point"}
}