{
  "type": "Feature",
  "properties": {
    "addr:full":"8035 Soquel Dr Aptos CA 95003",
    "addr:housenumber":"8035",
    "addr:postcode":"ca 95003",
    "addr:street":"Soquel Dr",
    "iso:country":"US",
    "sg:address":"8035 Soquel Dr",
    "sg:city":"Aptos",
    "sg:classifiers":[
        {
            "category":"Sports & Exercise",
            "subcategory":"Gym",
            "type":"Entertainment"
        }
    ],
    "sg:phone":"+1 831 423 2488",
    "sg:postcode":"95003",
    "sg:province":"CA",
    "sg:tags":[
        "club",
        "health",
        "studio",
        "gymnasium"
    ],
    "wof:name":"Bodyrock",
    "wof:placetype":"venue"
},
  "geometry": {"coordinates":[-121.902344,36.977064],"type":"Point"}
}