{
  "type": "Feature",
  "properties": {
    "iso:country":"US",
    "sg:address":"333 W Santa Clara Street",
    "sg:city":"San Jose",
    "sg:classifiers":[
        {
            "category":"Professional",
            "subcategory":"Lawyer & Legal Services",
            "type":"Services"
        }
    ],
    "sg:phone":"+1 408 280 0535",
    "sg:postcode":"95113",
    "sg:province":"CA",
    "wof:name":"Caputo Lisa I",
    "wof:placetype":"venue"
},
  "geometry": {"coordinates":[-121.896562,37.333398],"type":"Point"}
}