{
  "type": "Feature",
  "properties": {
    "addr:full":"84805 Ave 48 Coachella CA 92236",
    "addr:housenumber":"84805",
    "addr:postcode":"92236",
    "addr:street":"Ave 48",
    "iso:country":"US",
    "sg:address":"84805 Ave 48",
    "sg:city":"Coachella",
    "sg:classifiers":[
        {
            "category":"Retail",
            "subcategory":"Repair Shop",
            "type":"Services"
        }
    ],
    "sg:phone":"+1 760 345 5227",
    "sg:postcode":"92236",
    "sg:province":"CA",
    "sg:tags":[
        "lock",
        "locksmith"
    ],
    "wof:name":"Budge Towing",
    "wof:placetype":"venue"
},
  "geometry": {"coordinates":[-116.182652,33.700322],"type":"Point"}
}