{
  "type": "Feature",
  "properties": {
    "iso:country":"US",
    "sg:address":"2938 Washington St",
    "sg:city":"San Francisco",
    "sg:classifiers":[
        {
            "category":"Education",
            "subcategory":"School",
            "type":"Public Place"
        }
    ],
    "sg:phone":"+1 415 931 2750",
    "sg:postcode":"94115",
    "sg:province":"CA",
    "sg:tags":[
        "elementary"
    ],
    "sg:website":"www.sfwaldorf.org",
    "wof:name":"San Francisco Waldorf Elementary School",
    "wof:placetype":"venue"
},
  "geometry": {"coordinates":[-122.44149,37.790713],"type":"Point"}
}