{
  "type": "Feature",
  "properties": {
    "iso:country":"US",
    "sg:address":"3840 Dell Rd",
    "sg:city":"Carmichael",
    "sg:classifiers":[
        {
            "category":"Health Services",
            "subcategory":"Nursing And Care Facility",
            "type":"Services"
        }
    ],
    "sg:phone":"+1 916 944 4069",
    "sg:postcode":"95608",
    "sg:province":"CA",
    "sg:tags":[
        "residential"
    ],
    "wof:name":"Ashley Manor",
    "wof:placetype":"venue"
},
  "geometry": {"coordinates":[-121.295699,38.634033],"type":"Point"}
}