{
  "type": "Feature",
  "properties": {
    "iso:country":"US",
    "sg:address":"2881 E Coronado St",
    "sg:city":"Anaheim",
    "sg:classifiers":[
        {
            "category":"Manufacturing",
            "subcategory":"Wood Products",
            "type":"Manufacturing & Wholesale Goods"
        }
    ],
    "sg:phone":"+1 714 630 2173",
    "sg:postcode":"92806",
    "sg:province":"CA",
    "sg:tags":[
        "mfg"
    ],
    "wof:name":"A & E Pallets",
    "wof:placetype":"venue"
},
  "geometry": {"coordinates":[-117.865666,33.85284],"type":"Point"}
}