{
  "type": "Feature",
  "properties": {
    "iso:country":"US",
    "sg:address":"7901 Canoga Ave Ste H",
    "sg:city":"Canoga Park",
    "sg:classifiers":[
        {
            "category":"Retail",
            "subcategory":"Auto Repair",
            "type":"Services"
        },
        {
            "category":"Government",
            "subcategory":"Office",
            "type":"Public Place"
        }
    ],
    "sg:phone":"+1 818 888 2448",
    "sg:postcode":"91304",
    "sg:province":"CA",
    "sg:tags":[
        "smog",
        "check"
    ],
    "wof:name":"Mike Willard Automotive",
    "wof:placetype":"venue"
},
  "geometry": {"coordinates":[-118.610001,34.219601],"type":"Point"}
}