{
  "type": "Feature",
  "properties": {
    "iso:country":"US",
    "sg:address":"990 W 190th St Ste 200",
    "sg:city":"Torrance",
    "sg:classifiers":[
        {
            "category":"Education",
            "subcategory":"Special Training",
            "type":"Public Place"
        }
    ],
    "sg:phone":"+1 310 225 2960",
    "sg:postcode":"90502",
    "sg:province":"CA",
    "sg:tags":[
        "tutoring"
    ],
    "wof:name":"Kumon Math & Reading Centers",
    "wof:placetype":"venue"
},
  "geometry": {"coordinates":[-118.29299899999999,33.858299],"type":"Point"}
}