{
  "type": "Feature",
  "properties": {
    "addr:full":"10770 Chalon Rd Los Angeles CA 90077",
    "addr:housenumber":"10770",
    "addr:postcode":"90077",
    "addr:street":"Chalon Rd",
    "iso:country":"US",
    "sg:address":"10770 Chalon Rd",
    "sg:city":"Los Angeles",
    "sg:classifiers":[
        {
            "category":"Professional",
            "type":"Services"
        }
    ],
    "sg:phone":"+1 310 476 2262",
    "sg:postcode":"90077",
    "sg:province":"CA",
    "wof:name":"Bel Air House Concerts",
    "wof:placetype":"venue"
},
  "geometry": {"coordinates":[-118.450813,34.082359],"type":"Point"}
}