{
  "type": "Feature",
  "properties": {
    "addr:full":"1825 de la Cruz Blvd Santa Clara CA 95050",
    "addr:housenumber":"1825",
    "addr:postcode":"95050",
    "addr:street":"De La Cruz Blvd",
    "iso:country":"US",
    "sg:address":"1825 de la Cruz Blvd",
    "sg:city":"Santa Clara",
    "sg:classifiers":[
        {
            "category":"Wholesale",
            "subcategory":"Computers",
            "type":"Manufacturing & Wholesale Goods"
        },
        {
            "category":"Professional",
            "subcategory":"Engineering",
            "type":"Services"
        }
    ],
    "sg:phone":"+1 408 654 9703",
    "sg:postcode":"95050",
    "sg:province":"CA",
    "sg:tags":[
        "engineer"
    ],
    "wof:name":"Mezztech Systems Inc",
    "wof:placetype":"venue"
},
  "geometry": {"coordinates":[-121.940394,37.358674],"type":"Point"}
}