{
  "type": "Feature",
  "properties": {
    "iso:country":"US",
    "sg:address":"31511 Cam Capistrano",
    "sg:city":"San Juan Cpstrno",
    "sg:classifiers":[
        {
            "category":"Shopping",
            "subcategory":"Used Merchandise",
            "type":"Retail Goods"
        }
    ],
    "sg:phone":"+1 949 489 7820",
    "sg:postcode":"92675",
    "sg:province":"CA",
    "sg:tags":[
        "antique"
    ],
    "wof:name":"Antiqua",
    "wof:placetype":"venue"
},
  "geometry": {"coordinates":[-117.665935,33.507867],"type":"Point"}
}