{
  "type": "Feature",
  "properties": {
    "addr:full":"316 Escuela Ave Mountain View CA 94040",
    "addr:housenumber":"316",
    "addr:postcode":"94040",
    "addr:street":"Escuela Ave",
    "iso:country":"US",
    "sg:address":"316 Escuela Ave",
    "sg:city":"Mountain View",
    "sg:classifiers":[
        {
            "category":"Shopping",
            "type":"Retail Goods"
        }
    ],
    "sg:phone":"+1 650 969 7331",
    "sg:postcode":"94040",
    "sg:province":"CA",
    "sg:tags":[
        "equipment",
        "telephone",
        "supply"
    ],
    "wof:name":"California Telecommunications",
    "wof:placetype":"venue"
},
  "geometry": {"coordinates":[-122.09310600000001,37.398519],"type":"Point"}
}