{
  "type": "Feature",
  "properties": {
    "addr:full":"1718 Toulouse Ct Tracy CA 95304",
    "addr:housenumber":"1718",
    "addr:postcode":"95304",
    "addr:street":"Toulouse Ct",
    "iso:country":"US",
    "sg:address":"1718 Toulouse Ct",
    "sg:city":"Tracy",
    "sg:classifiers":[
        {
            "category":"Building & Trades",
            "subcategory":"Electrical",
            "type":"Services"
        }
    ],
    "sg:phone":"+1 209 833 1369",
    "sg:postcode":"95304",
    "sg:province":"CA",
    "sg:tags":[
        "electrician"
    ],
    "wof:name":"American Power & Communication",
    "wof:placetype":"venue"
},
  "geometry": {"coordinates":[-121.399286,37.714955],"type":"Point"}
}