{
  "type": "Feature",
  "properties": {
    "iso:country":"US",
    "sg:address":"27127 Cll Arroyo",
    "sg:city":"San Juan Capistrano",
    "sg:classifiers":[
        {
            "category":"Professional",
            "subcategory":"Management & Consulting",
            "type":"Services"
        }
    ],
    "sg:phone":"+1 949 388 9269",
    "sg:postcode":"92675",
    "sg:province":"CA",
    "wof:name":"Broadmoore Group",
    "wof:placetype":"venue"
},
  "geometry": {"coordinates":[-117.65659599999999,33.49912],"type":"Point"}
}