{
  "type": "Feature",
  "properties": {
    "iso:country":"US",
    "sg:address":"19845 Bloss Ave",
    "sg:city":"Hilmar",
    "sg:classifiers":[
        {
            "category":"Building & Trades",
            "subcategory":"Construction",
            "type":"Services"
        }
    ],
    "sg:phone":"+1 209 669 6600",
    "sg:postcode":"95324",
    "sg:province":"CA",
    "sg:tags":[
        "fabricator",
        "metal"
    ],
    "wof:name":"Liberty Mechanical",
    "wof:placetype":"venue"
},
  "geometry": {"coordinates":[-120.847423,37.404172],"type":"Point"}
}