{
  "type": "Feature",
  "properties": {
    "iso:country":"US",
    "sg:address":"1979 Estrella Ave",
    "sg:city":"Los Angeles",
    "sg:classifiers":[
        {
            "category":"Professional",
            "subcategory":"Business Services",
            "type":"Services"
        }
    ],
    "sg:phone":"+1 213 741 2365",
    "sg:postcode":"90007",
    "sg:province":"CA",
    "sg:tags":[
        "detection",
        "paint",
        "lead"
    ],
    "wof:name":"Healthy Homes",
    "wof:placetype":"venue"
},
  "geometry": {"coordinates":[-118.275658,34.033745],"type":"Point"}
}