{
  "type": "Feature",
  "properties": {
    "addr:full":"1979 Estrella Ave Los Angeles CA 90007",
    "addr:housenumber":"1979",
    "addr:postcode":"90007",
    "addr:street":"Estrella Ave",
    "iso:country":"US",
    "sg:address":"1979 Estrella Ave",
    "sg:city":"Los Angeles",
    "sg:classifiers":[
        {
            "category":"Professional",
            "subcategory":"Business Services",
            "type":"Services"
        }
    ],
    "sg:phone":"+1 213 741 2365",
    "sg:postcode":"90007",
    "sg:province":"CA",
    "sg:tags":[
        "detection",
        "paint",
        "lead"
    ],
    "wof:name":"Healthy Homes",
    "wof:placetype":"venue"
},
  "geometry": {"coordinates":[-118.27565800000001,34.033745],"type":"Point"}
}