{
  "type": "Feature",
  "properties": {
    "addr:full":"155 G St Upland CA 91786",
    "addr:housenumber":"155",
    "addr:postcode":"91786",
    "addr:street":"G St",
    "iso:country":"US",
    "sg:address":"155 G St",
    "sg:city":"Upland",
    "sg:classifiers":[
        {
            "category":"Professional",
            "subcategory":"Accounting & Tax Preparation",
            "type":"Services"
        }
    ],
    "sg:phone":"+1 909 946 3232",
    "sg:postcode":"91786",
    "sg:province":"CA",
    "sg:tags":[
        "bookkeeping",
        "general"
    ],
    "wof:name":"Laubach & Assoc",
    "wof:placetype":"venue"
},
  "geometry": {"coordinates":[-117.652953,34.101638],"type":"Point"}
}