{
  "type": "Feature",
  "properties": {
    "iso:country":"US",
    "sg:address":"18959 Labin Ct",
    "sg:city":"Rowland Heights",
    "sg:classifiers":[
        {
            "category":"Retail",
            "subcategory":"Auto Repair",
            "type":"Services"
        }
    ],
    "sg:phone":"+1 626 581 1770",
    "sg:postcode":"91748",
    "sg:province":"CA",
    "sg:tags":[
        "repairing",
        "automobile"
    ],
    "wof:name":"Silver Skyy Auto Svc",
    "wof:placetype":"venue"
},
  "geometry": {"coordinates":[-117.889152,33.991982],"type":"Point"}
}