{
  "type": "Feature",
  "properties": {
    "addr:full":"1800 Cedar St Berkeley CA 94703",
    "addr:housenumber":"1800",
    "addr:postcode":"94703",
    "addr:street":"Cedar St",
    "iso:country":"US",
    "sg:address":"1800 Cedar St",
    "sg:city":"Berkeley",
    "sg:classifiers":[
        {
            "category":"Shopping",
            "subcategory":"Musical Instruments",
            "type":"Retail Goods"
        },
        {
            "category":"Arts & Performance",
            "subcategory":"Music",
            "type":"Entertainment"
        },
        {
            "category":"Retail",
            "subcategory":"Repair Shop",
            "type":"Services"
        },
        {
            "category":"Manufacturing",
            "subcategory":"Musical Instruments",
            "type":"Manufacturing & Wholesale Goods"
        },
        {
            "category":"Education",
            "subcategory":"Music School",
            "type":"Public Place"
        }
    ],
    "sg:phone":"+1 510 841 4106",
    "sg:postcode":"94703",
    "sg:province":"CA",
    "sg:tags":[
        "instruments-repair",
        "amplifier",
        "accessory",
        "guitar",
        "instruments-supplies",
        "teacher"
    ],
    "sg:website":"www.fatdawg.com",
    "wof:name":"Subway Guitars",
    "wof:placetype":"venue"
},
  "geometry": {"coordinates":[-122.275921,37.877528],"type":"Point"}
}