{
  "type": "Feature",
  "properties": {
    "iso:country":"US",
    "sg:address":"818 1st St",
    "sg:city":"Brentwood",
    "sg:classifiers":[
        {
            "category":"Personal",
            "subcategory":"Nail Salon",
            "type":"Services"
        }
    ],
    "sg:phone":"+1 925 513 3211",
    "sg:postcode":"94513",
    "sg:province":"CA",
    "sg:website":"rhondasnaturalnails.com/",
    "wof:name":"The Classy Cottage",
    "wof:placetype":"venue"
},
  "geometry": {"coordinates":[-121.695795,37.934243],"type":"Point"}
}