{
  "type": "Feature",
  "properties": {
    "iso:country":"US",
    "sg:address":"247 Folsom Ave",
    "sg:city":"Hayward",
    "sg:classifiers":[
        {
            "category":"Building & Trades",
            "subcategory":"Construction",
            "type":"Services"
        }
    ],
    "sg:phone":"+1 510 782 8222",
    "sg:postcode":"94544",
    "sg:province":"CA",
    "sg:tags":[
        "contractor"
    ],
    "wof:name":"Mike Emerson Masonry",
    "wof:placetype":"venue"
},
  "geometry": {"coordinates":[-122.058925,37.627781],"type":"Point"}
}