{
  "type": "Feature",
  "properties": {
    "addr:full":"1826 N Broadway Los Angeles CA 90031",
    "addr:housenumber":"1826",
    "addr:postcode":"90031",
    "addr:street":"N Broadway",
    "iso:country":"US",
    "sg:address":"1826 N Broadway",
    "sg:city":"Los Angeles",
    "sg:classifiers":[
        {
            "category":"Banks & Credit Unions",
            "subcategory":"Investment Brokerage",
            "type":"Services"
        }
    ],
    "sg:phone":"+1 323 223 2042",
    "sg:postcode":"90031",
    "sg:province":"CA",
    "sg:tags":[
        "advisory",
        "financial"
    ],
    "wof:name":"Molina's Financial Svc",
    "wof:placetype":"venue"
},
  "geometry": {"coordinates":[-118.221496,34.071941],"type":"Point"}
}