{
  "type": "Feature",
  "properties": {
    "iso:country":"US",
    "sg:address":"1958 Missouri St",
    "sg:city":"San Diego",
    "sg:classifiers":[
        {
            "category":"Communications",
            "subcategory":"Newspaper",
            "type":"Services"
        }
    ],
    "sg:phone":"+1 619 806 8424",
    "sg:postcode":"92109",
    "sg:province":"CA",
    "sg:tags":[
        "advertising"
    ],
    "wof:name":"BeyondClicks",
    "wof:placetype":"venue"
},
  "geometry": {"coordinates":[-117.235411,32.805245],"type":"Point"}
}