{
  "type": "Feature",
  "properties": {
    "iso:country":"US",
    "sg:address":"16001 Liberty St",
    "sg:city":"San Leandro",
    "sg:classifiers":[
        {
            "category":"Real Estate",
            "subcategory":"Real Estate Operator",
            "type":"Services"
        }
    ],
    "sg:phone":"+1 510 278 7939",
    "sg:postcode":"94578",
    "sg:province":"CA",
    "sg:tags":[
        "apartment"
    ],
    "wof:name":"Liberty Hill Townhouses",
    "wof:placetype":"venue"
},
  "geometry": {"coordinates":[-122.113449,37.702757],"type":"Point"}
}