{
  "type": "Feature",
  "properties": {
    "addr:full":"3016 Rohrer Dr Lafayette CA 94549",
    "addr:housenumber":"3016",
    "addr:postcode":"94549",
    "addr:street":"Rohrer Dr",
    "iso:country":"US",
    "sg:address":"3016 Rohrer Dr",
    "sg:city":"Lafayette",
    "sg:classifiers":[
        {
            "category":"Recreation",
            "type":"Entertainment"
        }
    ],
    "sg:phone":"+1 925 299 6993",
    "sg:postcode":"94549",
    "sg:province":"CA",
    "sg:tags":[
        "pool",
        "swimming"
    ],
    "wof:name":"Rancho Colorados Swim Club Off",
    "wof:placetype":"venue"
},
  "geometry": {"coordinates":[-122.089567,37.862148],"type":"Point"}
}