{
  "type": "Feature",
  "properties": {
    "iso:country":"US",
    "sg:address":"7407 Elsie Ave",
    "sg:city":"Sacramento",
    "sg:classifiers":[
        {
            "category":"Travel",
            "subcategory":"Hotels & Motels",
            "type":"Entertainment"
        }
    ],
    "sg:phone":"+1 916 689 6555",
    "sg:postcode":"95828",
    "sg:province":"CA",
    "wof:name":"Motel 6",
    "wof:placetype":"venue"
},
  "geometry": {"coordinates":[-121.416279,38.474415],"type":"Point"}
}