{
  "type": "Feature",
  "properties": {
    "iso:country":"US",
    "sg:address":"31583 Castaic Rd",
    "sg:city":"Castaic",
    "sg:classifiers":[
        {
            "category":"Personal",
            "type":"Services"
        }
    ],
    "sg:phone":"+1 661 299 4869",
    "sg:postcode":"91384",
    "sg:province":"CA",
    "sg:tags":[
        "towing"
    ],
    "wof:name":"Preferred Towing",
    "wof:placetype":"venue"
},
  "geometry": {"coordinates":[-118.61900300000001,34.492199],"type":"Point"}
}