{
  "type": "Feature",
  "properties": {
    "addr:full":"13841 Roswell Ave Chino CA 91710",
    "addr:housenumber":"13841",
    "addr:postcode":"91710",
    "addr:street":"Roswell Ave",
    "iso:country":"US",
    "sg:address":"13841 Roswell Ave",
    "sg:city":"Chino",
    "sg:classifiers":[
        {
            "category":"Home & Garden",
            "subcategory":"Carpets & Floor Coverings",
            "type":"Retail Goods"
        }
    ],
    "sg:phone":"+1 909 628 7733",
    "sg:postcode":"91710",
    "sg:province":"CA",
    "wof:name":"Model Interiors",
    "wof:placetype":"venue"
},
  "geometry": {"coordinates":[-117.721706,34.003429],"type":"Point"}
}