{
  "type": "Feature",
  "properties": {
    "iso:country":"US",
    "sg:address":"5220 Via Valarta",
    "sg:city":"San Diego",
    "sg:classifiers":[
        {
            "category":"Utilities",
            "subcategory":"Telephone",
            "type":"Services"
        }
    ],
    "sg:phone":"+1 858 335 4013",
    "sg:postcode":"92124",
    "sg:province":"CA",
    "sg:tags":[
        "internet"
    ],
    "wof:name":"Neurodesign",
    "wof:placetype":"venue"
},
  "geometry": {"coordinates":[-117.084868,32.838953],"type":"Point"}
}