{
  "type": "Feature",
  "properties": {
    "iso:country":"US",
    "sg:address":"33848 Ave G",
    "sg:city":"Yucaipa",
    "sg:classifiers":[
        {
            "category":"Real Estate",
            "subcategory":"Real Estate Operator",
            "type":"Services"
        }
    ],
    "sg:phone":"+1 909 795 8766",
    "sg:postcode":"92399",
    "sg:province":"CA",
    "sg:tags":[
        "mobile",
        "home",
        "site",
        "community"
    ],
    "wof:name":"Las Casitas Mobile Estates",
    "wof:placetype":"venue"
},
  "geometry": {"coordinates":[-117.064128,34.012018],"type":"Point"}
}