{
  "type": "Feature",
  "properties": {
    "addr:full":"963 Heritage Rd San Diego CA 92154",
    "addr:housenumber":"963",
    "addr:postcode":"92154",
    "addr:street":"Heritage Rd",
    "iso:country":"US",
    "sg:address":"963 Heritage Rd",
    "sg:city":"San Diego",
    "sg:classifiers":[
        {
            "category":"Wholesale",
            "subcategory":"Auto Parts",
            "type":"Manufacturing & Wholesale Goods"
        }
    ],
    "sg:phone":"+1 619 661 6424",
    "sg:postcode":"92154",
    "sg:province":"CA",
    "sg:tags":[
        "automobile"
    ],
    "wof:name":"Dave's Auto Wrecking III",
    "wof:placetype":"venue"
},
  "geometry": {"coordinates":[-116.996838,32.576378],"type":"Point"}
}