{
  "type": "Feature",
  "properties": {
    "addr:full":"580 California St San Francisco CA 94104",
    "addr:housenumber":"580",
    "addr:postcode":"94104",
    "addr:street":"California St",
    "iso:country":"US",
    "sg:address":"580 California St",
    "sg:city":"San Francisco",
    "sg:classifiers":[
        {
            "category":"Professional",
            "subcategory":"Management & Consulting",
            "type":"Services"
        }
    ],
    "sg:phone":"+1 415 439 4867",
    "sg:postcode":"94104",
    "sg:province":"CA",
    "sg:tags":[
        "consultant",
        "business"
    ],
    "wof:name":"First Manhattan Consulting",
    "wof:placetype":"venue"
},
  "geometry": {"coordinates":[-122.404287,37.792737],"type":"Point"}
}