{
  "type": "Feature",
  "properties": {
    "addr:full":"22025 Ventura Blvd Woodland Hills CA 91364",
    "addr:housenumber":"22025",
    "addr:postcode":"91364",
    "addr:street":"Ventura Blvd",
    "iso:country":"US",
    "sg:address":"22025 Ventura Blvd",
    "sg:city":"Woodland Hills",
    "sg:classifiers":[
        {
            "category":"Professional",
            "type":"Services"
        },
        {
            "category":"Banks & Credit Unions",
            "subcategory":"Bank",
            "type":"Services"
        }
    ],
    "sg:phone":"+1 818 610 7200",
    "sg:postcode":"91364",
    "sg:province":"CA",
    "sg:tags":[
        "escrow"
    ],
    "wof:name":"Impact Escrow Inc",
    "wof:placetype":"venue"
},
  "geometry": {"coordinates":[-118.607714,34.168615],"type":"Point"}
}