{
  "type": "Feature",
  "properties": {
    "addr:full":"7376 Hollywood Blvd West Hollywood CA 90046",
    "addr:housenumber":"7376",
    "addr:postcode":"90046",
    "addr:street":"Hollywood Blvd",
    "iso:country":"US",
    "sg:address":"7376 Hollywood Blvd",
    "sg:city":"West Hollywood",
    "sg:classifiers":[
        {
            "category":"Retail",
            "subcategory":"Repair Shop",
            "type":"Services"
        }
    ],
    "sg:phone":"+1 323 939 2858",
    "sg:postcode":"90046",
    "sg:province":"CA",
    "sg:tags":[
        "lock",
        "locksmith"
    ],
    "wof:name":"Acme Lock & Key",
    "wof:placetype":"venue"
},
  "geometry": {"coordinates":[-118.35140199999999,34.101561],"type":"Point"}
}