{
  "type": "Feature",
  "properties": {
    "iso:country":"US",
    "sg:address":"13527 Ventura Blvd Ste B",
    "sg:city":"Sherman Oaks",
    "sg:classifiers":[
        {
            "category":"Professional",
            "subcategory":"Lawyer & Legal Services",
            "type":"Services"
        }
    ],
    "sg:phone":"+1 818 990 4507",
    "sg:postcode":"91423",
    "sg:province":"CA",
    "wof:name":"Medical Legal Resources",
    "wof:placetype":"venue"
},
  "geometry": {"coordinates":[-118.42800099999999,34.147499],"type":"Point"}
}