{
  "type": "Feature",
  "properties": {
    "iso:country":"US",
    "sg:address":"4545 Sequoyah Rd",
    "sg:city":"Oakland",
    "sg:classifiers":[
        {
            "category":"Professional",
            "type":"Services"
        }
    ],
    "sg:phone":"+1 510 568 1163",
    "sg:postcode":"94605",
    "sg:province":"CA",
    "wof:name":"Zimart of California",
    "wof:placetype":"venue"
},
  "geometry": {"coordinates":[-122.13707599999999,37.766441],"type":"Point"}
}