{
  "type": "Feature",
  "properties": {
    "addr:full":"541 Pamlar Ave San Jose CA 95128",
    "addr:housenumber":"541",
    "addr:postcode":"95128",
    "addr:street":"Pamlar Ave",
    "iso:country":"US",
    "sg:address":"541 Pamlar Ave",
    "sg:city":"San Jose",
    "sg:classifiers":[
        {
            "category":"Shopping",
            "type":"Retail Goods"
        }
    ],
    "sg:phone":"+1 408 283 0648",
    "sg:postcode":"95128",
    "sg:province":"CA",
    "sg:tags":[
        "merchandise"
    ],
    "wof:name":"Patiocoveringscom",
    "wof:placetype":"venue"
},
  "geometry": {"coordinates":[-121.935226,37.299376],"type":"Point"}
}