{
  "type": "Feature",
  "properties": {
    "iso:country":"US",
    "sg:address":"5306 E Washington Blvd",
    "sg:city":"Los Angeles",
    "sg:classifiers":[
        {
            "category":"Personal",
            "subcategory":"Barber",
            "type":"Services"
        }
    ],
    "sg:phone":"+1 323 265 3374",
    "sg:postcode":"90040",
    "sg:province":"CA",
    "wof:name":"Frank & Fernie",
    "wof:placetype":"venue"
},
  "geometry": {"coordinates":[-118.16322,34.001407],"type":"Point"}
}