{
  "type": "Feature",
  "properties": {
    "iso:country":"US",
    "sg:address":"4224 California St Ste 203",
    "sg:city":"San Francisco",
    "sg:classifiers":[
        {
            "category":"Health Services",
            "subcategory":"Clinic",
            "type":"Services"
        },
        {
            "category":"Shopping",
            "subcategory":"Bicycles & Sporting Goods",
            "type":"Retail Goods"
        }
    ],
    "sg:phone":"+1 415 922 2225",
    "sg:postcode":"94118",
    "sg:province":"CA",
    "sg:tags":[
        "medical"
    ],
    "wof:name":"Orthotic Shop of San Francisco",
    "wof:placetype":"venue"
},
  "geometry": {"coordinates":[-122.463159,37.785414],"type":"Point"}
}