{
  "type": "Feature",
  "properties": {
    "addr:full":"7555 Merced Falls Rd Snelling CA 95369",
    "addr:housenumber":"7555",
    "addr:postcode":"95369",
    "addr:street":"Merced Falls Rd",
    "iso:country":"US",
    "sg:address":"7555 Merced Falls Rd",
    "sg:city":"Snelling",
    "sg:classifiers":[
        {
            "category":"Farming",
            "subcategory":"Farm",
            "type":"Manufacturing & Wholesale Goods"
        }
    ],
    "sg:phone":"+1 209 563 6389",
    "sg:postcode":"95369",
    "sg:province":"CA",
    "sg:tags":[
        "crop",
        "general"
    ],
    "wof:name":"Sullivan Farms LLC",
    "wof:placetype":"venue"
},
  "geometry": {"coordinates":[-120.33706599999999,37.52184],"type":"Point"}
}