{
  "type": "Feature",
  "properties": {
    "addr:full":"170 Windsor River Rd Windsor CA 95492",
    "addr:housenumber":"170",
    "addr:postcode":"95492",
    "addr:street":"Windsor River Rd",
    "iso:country":"US",
    "sg:address":"170 Windsor River Rd",
    "sg:city":"Windsor",
    "sg:classifiers":[
        {
            "category":"Personal",
            "subcategory":"Barber",
            "type":"Services"
        }
    ],
    "sg:phone":"+1 707 838 0249",
    "sg:postcode":"95492",
    "sg:province":"CA",
    "wof:name":"Dan's Barber Shop",
    "wof:placetype":"venue"
},
  "geometry": {"coordinates":[-122.811879,38.547262],"type":"Point"}
}