{
  "type": "Feature",
  "properties": {
    "iso:country":"US",
    "sg:address":"435 Empire Ave",
    "sg:city":"Modesto",
    "sg:classifiers":[
        {
            "category":"Retail",
            "subcategory":"Auto Rental",
            "type":"Services"
        },
        {
            "category":"Building & Trades",
            "subcategory":"Equipment Rental",
            "type":"Services"
        },
        {
            "category":"Retail",
            "subcategory":"Storage",
            "type":"Services"
        }
    ],
    "sg:phone":"+1 209 241 5297",
    "sg:postcode":"95354",
    "sg:province":"CA",
    "sg:tags":[
        "renting",
        "moving-self",
        "leasing",
        "truck",
        "store",
        "yard",
        "trailer"
    ],
    "wof:name":"U -Haul Co",
    "wof:placetype":"venue"
},
  "geometry": {"coordinates":[-120.968582,37.633153],"type":"Point"}
}