{
  "type": "Feature",
  "properties": {
    "iso:country":"US",
    "sg:address":"7523 Fay Ave Ste G",
    "sg:city":"La Jolla",
    "sg:classifiers":[
        {
            "category":"Personal",
            "subcategory":"Shoe Repair & Shine",
            "type":"Services"
        }
    ],
    "sg:phone":"+1 858 551 0259",
    "sg:postcode":"92037",
    "sg:province":"CA",
    "wof:name":"La Jolla Shoe Repair",
    "wof:placetype":"venue"
},
  "geometry": {"coordinates":[-117.274002,32.840599],"type":"Point"}
}