{
  "type": "Feature",
  "properties": {
    "iso:country":"US",
    "sg:address":"1831 Pacific Ave",
    "sg:city":"Stockton",
    "sg:classifiers":[
        {
            "category":"Restaurant",
            "type":"Food & Drink"
        }
    ],
    "sg:menulink":"http://www.allmenus.com/ca/stockton/60107-casa-flores/menu/",
    "sg:phone":"+1 209 941 8817",
    "sg:postcode":"95204",
    "sg:province":"CA",
    "sg:tags":[
        "mexican"
    ],
    "wof:name":"Casa Flores",
    "wof:placetype":"venue"
},
  "geometry": {"coordinates":[-121.299076,37.969475],"type":"Point"}
}