{
  "type": "Feature",
  "properties": {
    "iso:country":"US",
    "sg:address":"1313 Hartnell Ave",
    "sg:city":"Redding",
    "sg:classifiers":[
        {
            "category":"Restaurant",
            "type":"Food & Drink"
        }
    ],
    "sg:phone":"+1 530 222 4466",
    "sg:postcode":"96002",
    "sg:province":"CA",
    "sg:tags":[
        "pizza"
    ],
    "wof:name":"Best Choice Take N Bake Pizza",
    "wof:placetype":"venue"
},
  "geometry": {"coordinates":[-122.342699,40.563674],"type":"Point"}
}