{
  "type": "Feature",
  "properties": {
    "addr:full":"11 Maiden Ln San Francisco CA 94108",
    "addr:housenumber":"11",
    "addr:postcode":"94108",
    "addr:street":"Maiden Ln",
    "iso:country":"US",
    "sg:address":"11 Maiden Ln",
    "sg:city":"San Francisco",
    "sg:classifiers":[
        {
            "category":"Food & Beverages",
            "subcategory":"Chocolate",
            "type":"Retail Goods"
        }
    ],
    "sg:phone":"+1 415 399 9922",
    "sg:postcode":"94108",
    "sg:province":"CA",
    "sg:tags":[
        "shop",
        "chocolatiers"
    ],
    "sg:website":"www.alegio.com",
    "wof:name":"Alegio Chocolat?",
    "wof:placetype":"venue"
},
  "geometry": {"coordinates":[-122.403865,37.788266],"type":"Point"}
}