{
  "type": "Feature",
  "properties": {
    "addr:full":"3438 E Collins Ave Orange CA 92867",
    "addr:housenumber":"3438",
    "addr:postcode":"92867",
    "addr:street":"E Collins Ave",
    "iso:country":"US",
    "sg:address":"3438 E Collins Ave",
    "sg:city":"Orange",
    "sg:classifiers":[
        {
            "category":"Professional",
            "subcategory":"Business Services",
            "type":"Services"
        }
    ],
    "sg:phone":"+1 714 744 3858",
    "sg:postcode":"92867",
    "sg:province":"CA",
    "wof:name":"LAC Svc",
    "wof:placetype":"venue"
},
  "geometry": {"coordinates":[-117.822875,33.802243],"type":"Point"}
}