{
  "type": "Feature",
  "properties": {
    "addr:full":"155 Valhalla Ct Vacaville CA 95687",
    "addr:housenumber":"155",
    "addr:postcode":"95687",
    "addr:street":"Valhalla Ct",
    "iso:country":"US",
    "sg:address":"155 Valhalla Ct",
    "sg:city":"Vacaville",
    "sg:classifiers":[
        {
            "category":"Professional",
            "type":"Services"
        }
    ],
    "sg:phone":"+1 707 446 0639",
    "sg:postcode":"95687",
    "sg:province":"CA",
    "wof:name":"Judy Bs Studio",
    "wof:placetype":"venue"
},
  "geometry": {"coordinates":[-121.965748,38.340469],"type":"Point"}
}