{
  "type": "Feature",
  "properties": {
    "iso:country":"US",
    "sg:address":"6078 Rio Valle Dr",
    "sg:city":"Bonsall",
    "sg:classifiers":[
        {
            "category":"Manufacturing",
            "subcategory":"Glass & Minerals",
            "type":"Manufacturing & Wholesale Goods"
        }
    ],
    "sg:phone":"+1 760 758 9107",
    "sg:postcode":"92003",
    "sg:province":"CA",
    "sg:tags":[
        "product",
        "mfg"
    ],
    "wof:name":"Custom Glass & Mirror",
    "wof:placetype":"venue"
},
  "geometry": {"coordinates":[-117.226669,33.29566],"type":"Point"}
}