{
  "type": "Feature",
  "properties": {
    "iso:country":"US",
    "sg:address":"3501 Civic Center Dr",
    "sg:city":"San Rafael",
    "sg:classifiers":[
        {
            "category":"Building & Trades",
            "subcategory":"Construction",
            "type":"Services"
        },
        {
            "category":"Government",
            "subcategory":"Office",
            "type":"Public Place"
        }
    ],
    "sg:phone":"+1 415 499 7877",
    "sg:postcode":"94903",
    "sg:province":"CA",
    "sg:tags":[
        "grading",
        "contractor"
    ],
    "wof:name":"Marin County Public Works",
    "wof:placetype":"venue"
},
  "geometry": {"coordinates":[-122.528432,37.996741],"type":"Point"}
}