{
  "type": "Feature",
  "properties": {
    "addr:full":"1100 Moraga Way Moraga CA 94563",
    "addr:housenumber":"1100",
    "addr:postcode":"94563",
    "addr:street":"Moraga Way",
    "iso:country":"US",
    "sg:address":"1100 Moraga Way",
    "sg:city":"Moraga",
    "sg:classifiers":[
        {
            "category":"Banks & Credit Unions",
            "subcategory":"Bank",
            "type":"Services"
        }
    ],
    "sg:phone":"+1 925 247 0374",
    "sg:postcode":"94563",
    "sg:province":"CA",
    "sg:tags":[
        "financing"
    ],
    "wof:name":"Bayview Portfolio Svc",
    "wof:placetype":"venue"
},
  "geometry": {"coordinates":[-122.134423,37.836984],"type":"Point"}
}