{
  "type": "Feature",
  "properties": {
    "addr:full":"18572 Prospect Rd Ste B Saratoga CA 95070",
    "addr:housenumber":"18572",
    "addr:postcode":"95070",
    "addr:street":"Prospect Rd Ste B",
    "iso:country":"US",
    "sg:address":"18572 Prospect Rd Ste B",
    "sg:city":"Saratoga",
    "sg:classifiers":[
        {
            "category":"Education",
            "subcategory":"Special Training",
            "type":"Public Place"
        }
    ],
    "sg:phone":"+1 408 203 3510",
    "sg:postcode":"95070",
    "sg:province":"CA",
    "sg:tags":[
        "school",
        "specialty"
    ],
    "sg:website":"www.avlonimusic.com/index.htm",
    "wof:name":"Avloni Academy of Music",
    "wof:placetype":"venue"
},
  "geometry": {"coordinates":[-121.99606,37.292164],"type":"Point"}
}