{
  "type": "Feature",
  "properties": {
    "addr:full":"2231 Agate Ct Simi Valley CA 93065",
    "addr:housenumber":"2231",
    "addr:postcode":"93065",
    "addr:street":"Agate Ct",
    "iso:country":"US",
    "sg:address":"2231 Agate Ct",
    "sg:city":"Simi Valley",
    "sg:classifiers":[
        {
            "category":"Wholesale",
            "subcategory":"Non-durable Goods",
            "type":"Manufacturing & Wholesale Goods"
        }
    ],
    "sg:phone":"+1 805 583 3373",
    "sg:postcode":"93065",
    "sg:province":"CA",
    "sg:tags":[
        "pet",
        "supply"
    ],
    "wof:name":"Gold'n Pets",
    "wof:placetype":"venue"
},
  "geometry": {"coordinates":[-118.783325,34.275025],"type":"Point"}
}