{
  "type": "Feature",
  "properties": {
    "iso:country":"US",
    "sg:address":"16520 Aston",
    "sg:city":"Irvine",
    "sg:classifiers":[
        {
            "category":"Wholesale",
            "subcategory":"Medical Equipment & Supplies",
            "type":"Manufacturing & Wholesale Goods"
        }
    ],
    "sg:phone":"+1 949 553 8885",
    "sg:postcode":"92606",
    "sg:province":"CA",
    "sg:tags":[
        "physician",
        "surgeon"
    ],
    "sg:website":"www.americanimex.com",
    "wof:name":"American Imex",
    "wof:placetype":"venue"
},
  "geometry": {"coordinates":[-117.84162600000001,33.702282],"type":"Point"}
}