{
  "type": "Feature",
  "properties": {
    "iso:country":"US",
    "sg:address":"701 Palomar Airport Rd",
    "sg:city":"Carlsbad",
    "sg:classifiers":[
        {
            "category":"Insurance",
            "subcategory":"Insurance Agent",
            "type":"Services"
        },
        {
            "category":"Banks & Credit Unions",
            "subcategory":"Financial Services",
            "type":"Services"
        }
    ],
    "sg:phone":"+1 800 540 5745",
    "sg:postcode":"92011",
    "sg:province":"CA",
    "sg:tags":[
        "counseling",
        "debt",
        "adjuster"
    ],
    "wof:name":"Lincoln Capital Solutions Inc",
    "wof:placetype":"venue"
},
  "geometry": {"coordinates":[-117.324079,33.122112],"type":"Point"}
}