{
  "type": "Feature",
  "properties": {
    "addr:full":"5 Serramonte Blvd Daly City CA 94015",
    "addr:housenumber":"5",
    "addr:postcode":"94015",
    "addr:street":"Serramonte Blvd",
    "iso:country":"US",
    "sg:address":"5 Serramonte Blvd",
    "sg:city":"Daly City",
    "sg:classifiers":[
        {
            "category":"Health Services",
            "subcategory":"Optometrist",
            "type":"Services"
        }
    ],
    "sg:phone":"+1 650 992 8595",
    "sg:postcode":"94015",
    "sg:province":"CA",
    "wof:name":"Eyexam 2000",
    "wof:placetype":"venue"
},
  "geometry": {"coordinates":[-122.466538,37.669538],"type":"Point"}
}