{
  "type": "Feature",
  "properties": {
    "iso:country":"US",
    "sg:address":"124 S Beth Cir",
    "sg:city":"Anaheim",
    "sg:classifiers":[
        {
            "category":"Building & Trades",
            "subcategory":"Cleaning & Sanitation",
            "type":"Services"
        }
    ],
    "sg:phone":"+1 714 632 9608",
    "sg:postcode":"92806",
    "sg:province":"CA",
    "sg:tags":[
        "maintenance"
    ],
    "wof:name":"F&E Cleaning Services",
    "wof:placetype":"venue"
},
  "geometry": {"coordinates":[-117.87017899999999,33.841204],"type":"Point"}
}