{
  "type": "Feature",
  "properties": {
    "iso:country":"US",
    "sg:address":"160 Kipling Ave",
    "sg:city":"Ben Lomond",
    "sg:classifiers":[
        {
            "category":"Shopping",
            "subcategory":"Musical Instruments",
            "type":"Retail Goods"
        }
    ],
    "sg:phone":"+1 831 336 1853",
    "sg:postcode":"95005",
    "sg:province":"CA",
    "wof:name":"Slow Rick Drums",
    "wof:placetype":"venue"
},
  "geometry": {"coordinates":[-122.084537,37.092003],"type":"Point"}
}