{
  "type": "Feature",
  "properties": {
    "addr:full":"4121 Franklin Blvd Sacramento CA 95820",
    "addr:housenumber":"4121",
    "addr:postcode":"95820",
    "addr:street":"Franklin Blvd",
    "iso:country":"US",
    "sg:address":"4121 Franklin Blvd",
    "sg:city":"Sacramento",
    "sg:classifiers":[
        {
            "category":"Organizations",
            "subcategory":"Religious Organization",
            "type":"Services"
        }
    ],
    "sg:phone":"+1 916 736 3737",
    "sg:postcode":"95820",
    "sg:province":"CA",
    "sg:tags":[
        "church"
    ],
    "wof:name":"Eglesia LA Roca",
    "wof:placetype":"venue"
},
  "geometry": {"coordinates":[-121.474531,38.536402],"type":"Point"}
}