{
  "type": "Feature",
  "properties": {
    "addr:full":"703 Lassen St Vallejo CA 94591",
    "addr:housenumber":"703",
    "addr:postcode":"94591",
    "addr:street":"Lassen St",
    "iso:country":"US",
    "sg:address":"703 Lassen St",
    "sg:city":"Vallejo",
    "sg:classifiers":[
        {
            "category":"Health Services",
            "subcategory":"Doctor",
            "type":"Services"
        }
    ],
    "sg:phone":"+1 707 553 9248",
    "sg:postcode":"94591",
    "sg:province":"CA",
    "sg:tags":[
        "physician",
        "surgeon"
    ],
    "wof:name":"Primary Care Nurses Family Prc",
    "wof:placetype":"venue"
},
  "geometry": {"coordinates":[-122.22657100000001,38.107067],"type":"Point"}
}