{
  "type": "Feature",
  "properties": {
    "iso:country":"US",
    "sg:address":"4935 Sunshine Ln",
    "sg:city":"Sacramento",
    "sg:classifiers":[
        {
            "category":"Building & Trades",
            "subcategory":"Construction",
            "type":"Services"
        }
    ],
    "sg:phone":"+1 916 519 1630",
    "sg:postcode":"95841",
    "sg:province":"CA",
    "sg:tags":[
        "painter"
    ],
    "wof:name":"Modern Images",
    "wof:placetype":"venue"
},
  "geometry": {"coordinates":[-121.34634699999999,38.658574],"type":"Point"}
}