{
  "type": "Feature",
  "properties": {
    "iso:country":"US",
    "sg:address":"1092 Border Ave",
    "sg:city":"Corona",
    "sg:classifiers":[
        {
            "category":"Banks & Credit Unions",
            "subcategory":"Investment Brokerage",
            "type":"Services"
        }
    ],
    "sg:phone":"+1 951 340 0828",
    "sg:postcode":"92882",
    "sg:province":"CA",
    "sg:tags":[
        "consultant",
        "financing"
    ],
    "wof:name":"JWD Trini Enterprises Inc",
    "wof:placetype":"venue"
},
  "geometry": {"coordinates":[-117.59066199999999,33.8721],"type":"Point"}
}