{
  "type": "Feature",
  "properties": {
    "iso:country":"US",
    "sg:address":"11641 Corbin Ave",
    "sg:city":"Northridge",
    "sg:classifiers":[
        {
            "category":"Government",
            "subcategory":"Fire Station",
            "type":"Public Place"
        }
    ],
    "sg:phone":"+1 818 756 9728",
    "sg:postcode":"91326",
    "sg:province":"CA",
    "sg:tags":[
        "protection"
    ],
    "wof:name":"Fire Dept-Station 28",
    "wof:placetype":"venue"
},
  "geometry": {"coordinates":[-118.566894,34.280497],"type":"Point"}
}