{
  "type": "Feature",
  "properties": {
    "addr:full":"1700 Winchester Blvd Campbell CA 95008",
    "addr:housenumber":"1700",
    "addr:postcode":"95008",
    "addr:street":"Winchester Blvd",
    "iso:country":"US",
    "sg:address":"1700 Winchester Blvd",
    "sg:city":"Campbell",
    "sg:classifiers":[
        {
            "category":"Banks & Credit Unions",
            "subcategory":"Bank",
            "type":"Services"
        }
    ],
    "sg:phone":"+1 408 364 1388",
    "sg:postcode":"95008",
    "sg:province":"CA",
    "sg:tags":[
        "loan"
    ],
    "wof:name":"Microtek International",
    "wof:placetype":"venue"
},
  "geometry": {"coordinates":[-121.949721,37.2934],"type":"Point"}
}