{
  "type": "Feature",
  "properties": {
    "iso:country":"US",
    "sg:address":"2320 Ramada Dr",
    "sg:city":"Paso Robles",
    "sg:classifiers":[
        {
            "category":"Shopping",
            "subcategory":"Used Merchandise",
            "type":"Retail Goods"
        },
        {
            "category":"Shopping",
            "subcategory":"Gifts & Souvenirs",
            "type":"Retail Goods"
        }
    ],
    "sg:phone":"+1 805 237 4012",
    "sg:postcode":"93446",
    "sg:province":"CA",
    "sg:tags":[
        "antique"
    ],
    "wof:name":"Vineyard Antique Mall",
    "wof:placetype":"venue"
},
  "geometry": {"coordinates":[-120.695964,35.583103],"type":"Point"}
}