{
  "type": "Feature",
  "properties": {
    "iso:country":"US",
    "sg:address":"805 W La Veta Ave Ste 108",
    "sg:city":"Orange",
    "sg:classifiers":[
        {
            "category":"Health Services",
            "subcategory":"Doctor",
            "type":"Services"
        }
    ],
    "sg:phone":"+1 714 744 0776",
    "sg:postcode":"92868",
    "sg:province":"CA",
    "wof:name":"Agran Phyllis MD",
    "wof:placetype":"venue"
},
  "geometry": {"coordinates":[-117.860321,33.781501],"type":"Point"}
}