{
  "type": "Feature",
  "properties": {
    "iso:country":"US",
    "sg:address":"658 S San Marcos Rd",
    "sg:city":"Santa Barbara",
    "sg:classifiers":[
        {
            "category":"Building & Trades",
            "subcategory":"Landscaping Services",
            "type":"Services"
        }
    ],
    "sg:phone":"+1 805 637 7905",
    "sg:postcode":"93111",
    "sg:province":"CA",
    "sg:tags":[
        "designer",
        "landscape"
    ],
    "sg:website":"www.lanegoodkind.com",
    "wof:name":"Lane Goodkin",
    "wof:placetype":"venue"
},
  "geometry": {"coordinates":[-119.795909,34.4301],"type":"Point"}
}