{
  "type": "Feature",
  "properties": {
    "addr:full":"2270 Palmer Cir Fairfield CA 94534",
    "addr:housenumber":"2270",
    "addr:postcode":"94534",
    "addr:street":"Palmer Cir",
    "iso:country":"US",
    "sg:address":"2270 Palmer Cir",
    "sg:city":"Fairfield",
    "sg:classifiers":[
        {
            "category":"Airline",
            "type":"Transportation"
        }
    ],
    "sg:phone":"+1 707 432 0123",
    "sg:postcode":"94534",
    "sg:province":"CA",
    "sg:tags":[
        "aircraft-charter",
        "leasing",
        "rental",
        "pilot"
    ],
    "wof:name":"Pacific Rim Aviation",
    "wof:placetype":"venue"
},
  "geometry": {"coordinates":[-122.063322,38.276476],"type":"Point"}
}