{
  "type": "Feature",
  "properties": {
    "addr:full":"1392 E Main St Woodland CA 95776",
    "addr:housenumber":"1392",
    "addr:postcode":"95776",
    "addr:street":"E Main St",
    "iso:country":"US",
    "sg:address":"1392 E Main St",
    "sg:city":"Woodland",
    "sg:classifiers":[
        {
            "category":"Shopping",
            "subcategory":"Used Merchandise",
            "type":"Retail Goods"
        }
    ],
    "sg:phone":"+1 530 661 7077",
    "sg:postcode":"95776",
    "sg:province":"CA",
    "sg:tags":[
        "shop",
        "thrift"
    ],
    "wof:name":"LA Mariposa Thrift Store",
    "wof:placetype":"venue"
},
  "geometry": {"coordinates":[-121.75995500000001,38.677306],"type":"Point"}
}