{
  "type": "Feature",
  "properties": {
    "addr:full":"1043 Regency Knoll Dr San Jose CA 95129",
    "addr:housenumber":"1043",
    "addr:postcode":"95129",
    "addr:street":"Regency Knoll Dr",
    "iso:country":"US",
    "sg:address":"1043 Regency Knoll Dr",
    "sg:city":"San Jose",
    "sg:classifiers":[
        {
            "category":"Manufacturing",
            "subcategory":"Retail Goods",
            "type":"Manufacturing & Wholesale Goods"
        },
        {
            "category":"Shopping",
            "subcategory":"Florist",
            "type":"Retail Goods"
        }
    ],
    "sg:phone":"+1 408 255 6899",
    "sg:postcode":"95129",
    "sg:province":"CA",
    "sg:tags":[
        "mfg",
        "product",
        "flower",
        "wedding"
    ],
    "wof:name":"Wedding Bokay",
    "wof:placetype":"venue"
},
  "geometry": {"coordinates":[-122.011331,37.307126],"type":"Point"}
}