{
  "type": "Feature",
  "properties": {
    "iso:country":"US",
    "sg:address":"7040 Shepard Mesa Dr",
    "sg:city":"Carpinteria",
    "sg:classifiers":[
        {
            "category":"Social Services",
            "type":"Services"
        }
    ],
    "sg:phone":"+1 805 684 8434",
    "sg:postcode":"93013",
    "sg:province":"CA",
    "sg:tags":[
        "counselor",
        "marriage",
        "family"
    ],
    "wof:name":"Toni Wellen",
    "wof:placetype":"venue"
},
  "geometry": {"coordinates":[-119.46907299999999,34.394719],"type":"Point"}
}