{
  "type": "Feature",
  "properties": {
    "iso:country":"US",
    "sg:address":"3030 Exposition Blvd",
    "sg:city":"Los Angeles",
    "sg:classifiers":[
        {
            "category":"Manufacturing",
            "subcategory":"Rubber & Plastics",
            "type":"Manufacturing & Wholesale Goods"
        }
    ],
    "sg:phone":"+1 323 298 1966",
    "sg:postcode":"90018",
    "sg:province":"CA",
    "sg:tags":[
        "forming"
    ],
    "wof:name":"Sandel Products",
    "wof:placetype":"venue"
},
  "geometry": {"coordinates":[-118.32920799999999,34.021449],"type":"Point"}
}