{
  "type": "Feature",
  "properties": {
    "iso:country":"US",
    "sg:address":"70 W Garzas Rd",
    "sg:city":"Carmel Valley",
    "sg:classifiers":[
        {
            "category":"Shopping",
            "type":"Retail Goods"
        },
        {
            "category":"Manufacturing",
            "subcategory":"Pottery",
            "type":"Manufacturing & Wholesale Goods"
        }
    ],
    "sg:phone":"+1 831 659 3610",
    "sg:postcode":"93924",
    "sg:province":"CA",
    "sg:tags":[
        "tableware",
        "wedding",
        "china",
        "supply"
    ],
    "wof:name":"Set In Your Way Table Setting",
    "wof:placetype":"venue"
},
  "geometry": {"coordinates":[-121.753579,36.493282],"type":"Point"}
}