{
  "type": "Feature",
  "properties": {
    "addr:full":"9083 Dallas St La Mesa CA 91942",
    "addr:housenumber":"9083",
    "addr:postcode":"91942",
    "addr:street":"Dallas St",
    "iso:country":"US",
    "sg:address":"9083 Dallas St",
    "sg:city":"La Mesa",
    "sg:classifiers":[
        {
            "category":"Restaurant",
            "type":"Food & Drink"
        }
    ],
    "sg:phone":"+1 619 469 1050",
    "sg:postcode":"91942",
    "sg:province":"CA",
    "sg:tags":[
        "pizza"
    ],
    "wof:name":"Pizza Express Take & Bake",
    "wof:placetype":"venue"
},
  "geometry": {"coordinates":[-117.00299800000001,32.7925],"type":"Point"}
}