{
  "type": "Feature",
  "properties": {
    "iso:country":"US",
    "sg:address":"1367 Rocking W Dr",
    "sg:city":"Bishop",
    "sg:classifiers":[
        {
            "category":"Place Of Worship",
            "subcategory":"Church",
            "type":"Public Place"
        },
        {
            "category":"Place Of Worship",
            "type":"Public Place"
        }
    ],
    "sg:phone":"+1 760 872 4618",
    "sg:postcode":"93514",
    "sg:province":"CA",
    "sg:tags":[
        "churches-interdenominational",
        "denomination",
        "churches-various",
        "churches-non-denominational"
    ],
    "wof:name":"Bishop Christian Center",
    "wof:placetype":"venue"
},
  "geometry": {"coordinates":[-118.42017800000001,37.377985],"type":"Point"}
}