{
  "type": "Feature",
  "properties": {
    "iso:country":"US",
    "sg:address":"15802 Chemical Lane",
    "sg:city":"Huntington Beach",
    "sg:classifiers":[
        {
            "category":"Banks & Credit Unions",
            "subcategory":"Financial Services",
            "type":"Services"
        }
    ],
    "sg:phone":"+1 714 901 6764",
    "sg:postcode":"92649",
    "sg:province":"CA",
    "sg:tags":[
        "broker",
        "mortgage"
    ],
    "wof:name":"Arl-American Refinance & Lending",
    "wof:placetype":"venue"
},
  "geometry": {"coordinates":[-118.036734,33.73269],"type":"Point"}
}