{
  "type": "Feature",
  "properties": {
    "iso:country":"US",
    "sg:address":"224 S Leandro St",
    "sg:city":"Anaheim",
    "sg:classifiers":[
        {
            "category":"Building & Trades",
            "subcategory":"Electrical",
            "type":"Services"
        }
    ],
    "sg:phone":"+1 714 685 7713",
    "sg:postcode":"92807",
    "sg:province":"CA",
    "sg:tags":[
        "electrical",
        "contractor"
    ],
    "wof:name":"Pro Tek Electrical Contractors",
    "wof:placetype":"venue"
},
  "geometry": {"coordinates":[-117.78210900000001,33.849164],"type":"Point"}
}