{
  "type": "Feature",
  "properties": {
    "addr:full":"2207 Judah St San Francisco CA 94199",
    "addr:housenumber":"2207",
    "addr:postcode":"94199",
    "addr:street":"Judah St",
    "iso:country":"US",
    "sg:address":"2207 Judah St",
    "sg:city":"San Francisco",
    "sg:classifiers":[
        {
            "category":"Professional",
            "subcategory":"Computer Services",
            "type":"Services"
        }
    ],
    "sg:phone":"+1 415 661 9020",
    "sg:postcode":"94199",
    "sg:province":"CA",
    "sg:tags":[
        "repair"
    ],
    "sg:website":"www.actnetonline.com",
    "wof:name":"Actnet",
    "wof:placetype":"venue"
},
  "geometry": {"coordinates":[-122.485775,37.76137],"type":"Point"}
}