{
  "type": "Feature",
  "properties": {
    "addr:full":"8229 Woodman Ave Panorama City CA 91402",
    "addr:housenumber":"8229",
    "addr:postcode":"91402",
    "addr:street":"Woodman Ave",
    "iso:country":"US",
    "sg:address":"8229 Woodman Ave",
    "sg:city":"Panorama City",
    "sg:classifiers":[
        {
            "category":"Shopping",
            "subcategory":"Clothing, Apparel, & Fashions",
            "type":"Retail Goods"
        }
    ],
    "sg:phone":"+1 818 780 2248",
    "sg:postcode":"91402",
    "sg:province":"CA",
    "sg:tags":[
        "uniform"
    ],
    "wof:name":"Comfort Wear Outlet",
    "wof:placetype":"venue"
},
  "geometry": {"coordinates":[-118.432773,34.221026],"type":"Point"}
}