{
  "type": "Feature",
  "properties": {
    "iso:country":"US",
    "sg:address":"6644 Mission St",
    "sg:city":"Daly City",
    "sg:classifiers":[
        {
            "category":"Wholesale",
            "subcategory":"Apparel",
            "type":"Manufacturing & Wholesale Goods"
        }
    ],
    "sg:phone":"+1 650 757 7100",
    "sg:postcode":"94014",
    "sg:province":"CA",
    "sg:tags":[
        "upholstery",
        "fabric"
    ],
    "wof:name":"Melo's Upholstery Supply",
    "wof:placetype":"venue"
},
  "geometry": {"coordinates":[-122.46303,37.702214],"type":"Point"}
}