{
  "type": "Feature",
  "properties": {
    "iso:country":"US",
    "sg:address":"600 El Camino Real",
    "sg:city":"San Bruno",
    "sg:classifiers":[
        {
            "category":"Professional",
            "subcategory":"Lawyer & Legal Services",
            "type":"Services"
        }
    ],
    "sg:phone":"+1 650 871 1323",
    "sg:postcode":"94066",
    "sg:province":"CA",
    "sg:tags":[
        "divorce",
        "law",
        "family"
    ],
    "sg:website":"www.joelstrauslaw.com",
    "wof:name":"Joel K Straus",
    "wof:placetype":"venue"
},
  "geometry": {"coordinates":[-122.414181,37.625335],"type":"Point"}
}