{
  "type": "Feature",
  "properties": {
    "addr:full":"1377 S Lilac Ave Bloomington CA 92316",
    "addr:housenumber":"1377",
    "addr:postcode":"92316",
    "addr:street":"S Lilac Ave",
    "iso:country":"US",
    "sg:address":"1377 S Lilac Ave",
    "sg:city":"Bloomington",
    "sg:classifiers":[
        {
            "category":"Shopping",
            "subcategory":"Gifts & Souvenirs",
            "type":"Retail Goods"
        }
    ],
    "sg:phone":"+1 909 873 9880",
    "sg:postcode":"92316",
    "sg:province":"CA",
    "sg:tags":[
        "party",
        "supply"
    ],
    "wof:name":"Jump For Less",
    "wof:placetype":"venue"
},
  "geometry": {"coordinates":[-117.378946,34.07741],"type":"Point"}
}