{
  "type": "Feature",
  "properties": {
    "iso:country":"US",
    "sg:address":"834 E California Blvd",
    "sg:city":"Pasadena",
    "sg:classifiers":[
        {
            "category":"Shopping",
            "subcategory":"Used Merchandise",
            "type":"Retail Goods"
        }
    ],
    "sg:phone":"+1 626 584 9431",
    "sg:postcode":"91106",
    "sg:province":"CA",
    "sg:tags":[
        "antique"
    ],
    "wof:name":"Jane Warren Antiques",
    "wof:placetype":"venue"
},
  "geometry": {"coordinates":[-118.132858,34.135803],"type":"Point"}
}