{
  "type": "Feature",
  "properties": {
    "addr:full":"120 Montgomery Street Suite 2410 San Francisco CA 94104",
    "addr:housenumber":"120",
    "addr:postcode":"94104",
    "addr:street":"Montgomery Street Suite 2410",
    "iso:country":"US",
    "sg:address":"120 Montgomery Street Suite 2410",
    "sg:city":"San Francisco",
    "sg:classifiers":[
        {
            "category":"Professional",
            "subcategory":"Lawyer & Legal Services",
            "type":"Services"
        }
    ],
    "sg:phone":"+1 415 981 1801",
    "sg:postcode":"94104",
    "sg:province":"CA",
    "sg:tags":[
        "personal",
        "injury"
    ],
    "wof:name":"Harlem Robert A & Associates",
    "wof:placetype":"venue"
},
  "geometry": {"coordinates":[-122.402,37.791599],"type":"Point"}
}