{
  "type": "Feature",
  "properties": {
    "addr:full":"3840 Medford St Los Angeles CA 90063",
    "addr:housenumber":"3840",
    "addr:postcode":"90063",
    "addr:street":"Medford St",
    "iso:country":"US",
    "sg:address":"3840 Medford St",
    "sg:city":"Los Angeles",
    "sg:classifiers":[
        {
            "category":"Retail",
            "subcategory":"Auto Repair",
            "type":"Services"
        }
    ],
    "sg:phone":"+1 323 265 2416",
    "sg:postcode":"90063",
    "sg:province":"CA",
    "sg:tags":[
        "transmission"
    ],
    "wof:name":"City Terrace Transmission",
    "wof:placetype":"venue"
},
  "geometry": {"coordinates":[-118.184652,34.059475],"type":"Point"}
}