{
  "type": "Feature",
  "properties": {
    "iso:country":"US",
    "sg:address":"517 Center St",
    "sg:city":"Santa Cruz",
    "sg:classifiers":[
        {
            "category":"Organizations",
            "subcategory":"Religious Organization",
            "type":"Services"
        }
    ],
    "sg:phone":"+1 831 423 6388",
    "sg:postcode":"95060",
    "sg:province":"CA",
    "sg:tags":[
        "church"
    ],
    "wof:name":"Progressive Missionary Baptist",
    "wof:placetype":"venue"
},
  "geometry": {"coordinates":[-122.02789300000001,36.971107],"type":"Point"}
}