{
  "type": "Feature",
  "properties": {
    "addr:full":"930 Oddstad Boulevard Pacifica, Ca 94044",
    "wof:categories":[
        "education_and_religion:education=school"
    ],
    "wof:name":"Oddstad Elementary School",
    "wof:placetype":"venue"
},
  "geometry": {"coordinates":[-122.46858964722983,37.58729350469935],"type":"Point"}
}