{
  "type": "Feature",
  "properties": {
    "iso:country":"US",
    "sg:address":"2251 W Whittier Blvd",
    "sg:city":"La Habra",
    "sg:classifiers":[
        {
            "category":"Home & Garden",
            "subcategory":"Building Materials",
            "type":"Retail Goods"
        }
    ],
    "sg:phone":"+1 562 691 0901",
    "sg:postcode":"90631",
    "sg:province":"CA",
    "sg:tags":[
        "plate",
        "window",
        "auto",
        "glass"
    ],
    "wof:name":"East Whittier Glass Co",
    "wof:placetype":"venue"
},
  "geometry": {"coordinates":[-117.971001,33.9398],"type":"Point"}
}