{
  "type": "Feature",
  "properties": {
    "iso:country":"US",
    "sg:address":"20995 Skywest Dr",
    "sg:city":"Hayward",
    "sg:classifiers":[
        {
            "category":"Real Estate",
            "subcategory":"Developer",
            "type":"Services"
        }
    ],
    "sg:phone":"+1 510 264 0348",
    "sg:postcode":"94541",
    "sg:province":"CA",
    "sg:tags":[
        "helicopter",
        "charter",
        "rental"
    ],
    "wof:name":"Makin Air Helicopters",
    "wof:placetype":"venue"
},
  "geometry": {"coordinates":[-122.118824,37.662173],"type":"Point"}
}