{
  "type": "Feature",
  "properties": {
    "iso:country":"US",
    "sg:address":"1807 S Chester Ave",
    "sg:city":"Bakersfield",
    "sg:classifiers":[
        {
            "category":"Retail",
            "subcategory":"Auto Repair",
            "type":"Services"
        }
    ],
    "sg:phone":"+1 661 836 8926",
    "sg:postcode":"93304",
    "sg:province":"CA",
    "sg:tags":[
        "muffler",
        "exhaust",
        "system"
    ],
    "wof:name":"Good Ol' Boys Muffler Masters",
    "wof:placetype":"venue"
},
  "geometry": {"coordinates":[-119.017623,35.337473],"type":"Point"}
}