{
  "type": "Feature",
  "properties": {
    "addr:full":"17701 Comstock Rd Linden CA 95236",
    "addr:housenumber":"17701",
    "addr:postcode":"95236",
    "addr:street":"Comstock Rd",
    "iso:country":"US",
    "sg:address":"17701 Comstock Rd",
    "sg:city":"Linden",
    "sg:classifiers":[
        {
            "category":"Retail",
            "subcategory":"Repair Shop",
            "type":"Services"
        }
    ],
    "sg:phone":"+1 209 887 3716",
    "sg:postcode":"95236",
    "sg:province":"CA",
    "sg:tags":[
        "welding"
    ],
    "wof:name":"Johnnie's Welding",
    "wof:placetype":"venue"
},
  "geometry": {"coordinates":[-121.09796,38.044889],"type":"Point"}
}