{
  "type": "Feature",
  "properties": {
    "addr:full":"9425 Telegraph Rd Pico Rivera CA 90240",
    "addr:housenumber":"9425",
    "addr:postcode":"90240",
    "addr:street":"Telegraph Rd",
    "iso:country":"US",
    "sg:address":"9425 Telegraph Rd",
    "sg:city":"Pico Rivera",
    "sg:classifiers":[
        {
            "category":"Personal",
            "subcategory":"Barber",
            "type":"Services"
        }
    ],
    "sg:phone":"+1 562 948 4901",
    "sg:postcode":"90240",
    "sg:province":"CA",
    "wof:name":"Cris Barber Shop",
    "wof:placetype":"venue"
},
  "geometry": {"coordinates":[-118.10183499999999,33.955323],"type":"Point"}
}