{
  "type": "Feature",
  "properties": {
    "addr:full":"20 S Grant St San Mateo CA 94401",
    "addr:housenumber":"20",
    "addr:postcode":"94401",
    "addr:street":"S Grant St",
    "iso:country":"US",
    "sg:address":"20 S Grant St",
    "sg:city":"San Mateo",
    "sg:classifiers":[
        {
            "category":"Building & Trades",
            "subcategory":"Cleaning & Sanitation",
            "type":"Services"
        }
    ],
    "sg:phone":"+1 650 224 3512",
    "sg:postcode":"94401",
    "sg:province":"CA",
    "sg:tags":[
        "home"
    ],
    "wof:name":"Expert Martin Martha Maids",
    "wof:placetype":"venue"
},
  "geometry": {"coordinates":[-122.320072,37.571135],"type":"Point"}
}