{
  "type": "Feature",
  "properties": {
    "iso:country":"US",
    "sg:address":"5592 Kern Dr",
    "sg:city":"Huntington Beach",
    "sg:classifiers":[
        {
            "category":"Shopping",
            "subcategory":"Catalog Store",
            "type":"Retail Goods"
        }
    ],
    "sg:phone":"+1 714 846 7784",
    "sg:postcode":"92649",
    "sg:province":"CA",
    "sg:tags":[
        "mail",
        "house"
    ],
    "wof:name":"Mimis Gems",
    "wof:placetype":"venue"
},
  "geometry": {"coordinates":[-118.03160200000001,33.711504],"type":"Point"}
}