{
  "type": "Feature",
  "properties": {
    "iso:country":"US",
    "sg:address":"5155 W Rosecrans Ave Ste 251",
    "sg:city":"Hawthorne",
    "sg:classifiers":[
        {
            "category":"Shopping",
            "subcategory":"Music",
            "type":"Retail Goods"
        },
        {
            "category":"Wholesale",
            "subcategory":"Computers",
            "type":"Manufacturing & Wholesale Goods"
        }
    ],
    "sg:phone":"+1 310 676 9038",
    "sg:postcode":"90250",
    "sg:province":"CA",
    "sg:tags":[
        "dvd's"
    ],
    "wof:name":"Topaz",
    "wof:placetype":"venue"
},
  "geometry": {"coordinates":[-118.368296,33.902035],"type":"Point"}
}