{
  "type": "Feature",
  "properties": {
    "addr:full":"1916 Donahue Dr El Cajon CA 92019",
    "addr:housenumber":"1916",
    "addr:postcode":"92019",
    "addr:street":"Donahue Dr",
    "iso:country":"US",
    "sg:address":"1916 Donahue Dr",
    "sg:city":"El Cajon",
    "sg:classifiers":[
        {
            "category":"Professional",
            "type":"Services"
        }
    ],
    "sg:phone":"+1 619 588 1901",
    "sg:postcode":"92019",
    "sg:province":"CA",
    "wof:name":"Platts Tebbetts & Fitch",
    "wof:placetype":"venue"
},
  "geometry": {"coordinates":[-116.91204500000001,32.758675],"type":"Point"}
}