{
  "type": "Feature",
  "properties": {
    "iso:country":"US",
    "sg:address":"4301 Atlantic Ave Suite 2",
    "sg:city":"Long Beach",
    "sg:classifiers":[
        {
            "category":"Health Services",
            "subcategory":"Dentist",
            "type":"Services"
        }
    ],
    "sg:phone":"+1 562 427 1426",
    "sg:postcode":"90807",
    "sg:province":"CA",
    "sg:tags":[
        "orthodontist"
    ],
    "sg:website":"www.mksmiles.com",
    "wof:name":"Miller and Kan Orthodontics",
    "wof:placetype":"venue"
},
  "geometry": {"coordinates":[-118.18532,33.834644],"type":"Point"}
}