{
  "type": "Feature",
  "properties": {
    "iso:country":"US",
    "sg:address":"500 Hunter Dr",
    "sg:city":"Fillmore",
    "sg:classifiers":[
        {
            "category":"Farming",
            "subcategory":"Orchard",
            "type":"Manufacturing & Wholesale Goods"
        }
    ],
    "sg:phone":"+1 805 524 0493",
    "sg:postcode":"93015",
    "sg:province":"CA",
    "wof:name":"Larry Stewart",
    "wof:placetype":"venue"
},
  "geometry": {"coordinates":[-118.91574900000001,34.410839],"type":"Point"}
}