{
  "type": "Feature",
  "properties": {
    "iso:country":"US",
    "sg:address":"41050 13th St W",
    "sg:city":"Palmdale",
    "sg:classifiers":[
        {
            "category":"Building & Trades",
            "subcategory":"Construction",
            "type":"Services"
        }
    ],
    "sg:phone":"+1 661 947 5252",
    "sg:postcode":"93551",
    "sg:province":"CA",
    "sg:tags":[
        "nonresidential"
    ],
    "wof:name":"RC Akers",
    "wof:placetype":"venue"
},
  "geometry": {"coordinates":[-118.154214,34.62829],"type":"Point"}
}