{
  "type": "Feature",
  "properties": {
    "addr:full":"1639 Chalcedony Ct Folsom CA 95630",
    "addr:housenumber":"1639",
    "addr:postcode":"95630",
    "addr:street":"Chalcedony Ct",
    "iso:country":"US",
    "sg:address":"1639 Chalcedony Ct",
    "sg:city":"Folsom",
    "sg:classifiers":[
        {
            "category":"Retail",
            "subcategory":"Repair Shop",
            "type":"Services"
        }
    ],
    "sg:phone":"+1 916 983 6298",
    "sg:postcode":"95630",
    "sg:province":"CA",
    "sg:tags":[
        "upholsterer"
    ],
    "wof:name":"Hide-All Storage Cover",
    "wof:placetype":"venue"
},
  "geometry": {"coordinates":[-121.11675700000001,38.680579],"type":"Point"}
}