{
  "type": "Feature",
  "properties": {
    "iso:country":"US",
    "sg:address":"8950 Carley Cir",
    "sg:city":"San Diego",
    "sg:classifiers":[
        {
            "category":"Manufacturing",
            "subcategory":"Electronics",
            "type":"Manufacturing & Wholesale Goods"
        }
    ],
    "sg:phone":"+1 858 536 8023",
    "sg:postcode":"92126",
    "sg:province":"CA",
    "sg:tags":[
        "devices",
        "mfg"
    ],
    "wof:name":"Versalynx Corp",
    "wof:placetype":"venue"
},
  "geometry": {"coordinates":[-117.130759,32.929554],"type":"Point"}
}