{
  "type": "Feature",
  "properties": {
    "addr:full":"13173 Black Mountain Rd San Diego CA 92129",
    "addr:housenumber":"13173",
    "addr:postcode":"92129",
    "addr:street":"Black Mountain Rd",
    "iso:country":"US",
    "sg:address":"13173 Black Mountain Rd",
    "sg:city":"San Diego",
    "sg:classifiers":[
        {
            "category":"Sports & Exercise",
            "subcategory":"Gym",
            "type":"Entertainment"
        }
    ],
    "sg:phone":"+1 858 484 5420",
    "sg:postcode":"92129",
    "sg:province":"CA",
    "sg:tags":[
        "club",
        "health",
        "studio",
        "gymnasium"
    ],
    "wof:name":"Curves For Women",
    "wof:placetype":"venue"
},
  "geometry": {"coordinates":[-117.12891,32.956933],"type":"Point"}
}