{
  "type": "Feature",
  "properties": {
    "addr:full":"780 S Rochester Ave Ontario CA 91761",
    "addr:housenumber":"780",
    "addr:postcode":"91761",
    "addr:street":"S Rochester Ave",
    "iso:country":"US",
    "sg:address":"780 S Rochester Ave",
    "sg:city":"Ontario",
    "sg:classifiers":[
        {
            "category":"Wholesale",
            "subcategory":"Auto Parts",
            "type":"Manufacturing & Wholesale Goods"
        }
    ],
    "sg:phone":"+1 909 390 9722",
    "sg:postcode":"91761",
    "sg:province":"CA",
    "sg:tags":[
        "truck",
        "accessory"
    ],
    "wof:name":"Rancho Motorsports & Rhino",
    "wof:placetype":"venue"
},
  "geometry": {"coordinates":[-117.547684,34.055059],"type":"Point"}
}