{
  "type": "Feature",
  "properties": {
    "iso:country":"US",
    "sg:address":"321 W Katella Ave Ste 136",
    "sg:city":"Anaheim",
    "sg:classifiers":[
        {
            "category":"Shopping",
            "subcategory":"Clothing, Apparel, & Fashions",
            "type":"Retail Goods"
        }
    ],
    "sg:phone":"+1 714 991 7730",
    "sg:postcode":"92802",
    "sg:province":"CA",
    "sg:tags":[
        "accessory",
        "clothing",
        "women's"
    ],
    "wof:name":"White House Black Market",
    "wof:placetype":"venue"
},
  "geometry": {"coordinates":[-117.91049,33.803565],"type":"Point"}
}