{
  "type": "Feature",
  "properties": {
    "addr:full":"5804 E Muir Dr Orange CA 92869",
    "addr:housenumber":"5804",
    "addr:postcode":"92869",
    "addr:street":"E Muir Dr",
    "iso:country":"US",
    "sg:address":"5804 E Muir Dr",
    "sg:city":"Orange",
    "sg:classifiers":[
        {
            "category":"Professional",
            "type":"Services"
        }
    ],
    "sg:phone":"+1 714 628 1860",
    "sg:postcode":"92869",
    "sg:province":"CA",
    "wof:name":"Hartless Inc",
    "wof:placetype":"venue"
},
  "geometry": {"coordinates":[-117.791229,33.808842],"type":"Point"}
}