{
  "type": "Feature",
  "properties": {
    "addr:full":"2500 Marconi Ave Ste 209A Sacramento CA 95821",
    "addr:housenumber":"2500",
    "addr:postcode":"95821",
    "addr:street":"Marconi Ave Ste 209A",
    "iso:country":"US",
    "sg:address":"2500 Marconi Ave Ste 209A",
    "sg:city":"Sacramento",
    "sg:classifiers":[
        {
            "category":"Organizations",
            "subcategory":"Community Association",
            "type":"Services"
        }
    ],
    "sg:phone":"+1 916 974 1125",
    "sg:postcode":"95821",
    "sg:province":"CA",
    "sg:tags":[
        "lie",
        "detection"
    ],
    "sg:website":"http://www.ultimatetruthinvestigations.com",
    "wof:name":"Ultimate Truth Investigations",
    "wof:placetype":"venue"
},
  "geometry": {"coordinates":[-121.403519,38.618038],"type":"Point"}
}