{
  "type": "Feature",
  "properties": {
    "addr:full":"909 E Valley Pkwy Escondido CA 92025",
    "addr:housenumber":"909",
    "addr:postcode":"92025",
    "addr:street":"E Valley Pkwy",
    "iso:country":"US",
    "sg:address":"909 E Valley Pkwy",
    "sg:city":"Escondido",
    "sg:classifiers":[
        {
            "category":"Shopping",
            "subcategory":"Pharmacy",
            "type":"Retail Goods"
        }
    ],
    "sg:phone":"+1 760 480 1081",
    "sg:postcode":"92025",
    "sg:province":"CA",
    "sg:website":"www.medrxdrug.com",
    "wof:name":"Med-Rx Drug",
    "wof:placetype":"venue"
},
  "geometry": {"coordinates":[-117.06988,33.129067],"type":"Point"}
}