{
  "type": "Feature",
  "properties": {
    "addr:full":"15555 Main St Ste D4 Hesperia CA 92345",
    "addr:housenumber":"15555",
    "addr:postcode":"92345",
    "addr:street":"Main St Ste D4",
    "iso:country":"US",
    "sg:address":"15555 Main St Ste D4",
    "sg:city":"Hesperia",
    "sg:classifiers":[
        {
            "category":"Real Estate",
            "subcategory":"Real Estate Services",
            "type":"Services"
        },
        {
            "category":"Real Estate",
            "subcategory":"Real Estate Agent",
            "type":"Services"
        }
    ],
    "sg:phone":"+1 760 949 3695",
    "sg:postcode":"92345",
    "sg:province":"CA",
    "sg:tags":[
        "buyer",
        "broker"
    ],
    "wof:name":"J R Realty",
    "wof:placetype":"venue"
},
  "geometry": {"coordinates":[-117.32432900000001,34.424914],"type":"Point"}
}