{
  "type": "Feature",
  "properties": {
    "iso:country":"US",
    "sg:address":"6585 Clark Rd",
    "sg:city":"Paradise",
    "sg:classifiers":[
        {
            "category":"Shopping",
            "subcategory":"Pharmacy",
            "type":"Retail Goods"
        }
    ],
    "sg:phone":"+1 530 877 3712",
    "sg:postcode":"95969",
    "sg:province":"CA",
    "wof:name":"Cobblestone Pharmacy",
    "wof:placetype":"venue"
},
  "geometry": {"coordinates":[-121.59466,39.773573],"type":"Point"}
}