{
  "type": "Feature",
  "properties": {
    "iso:country":"US",
    "sg:address":"5240 Rocklin Rd",
    "sg:city":"Rocklin",
    "sg:classifiers":[
        {
            "category":"Real Estate",
            "subcategory":"Real Estate Operator",
            "type":"Services"
        }
    ],
    "sg:phone":"+1 916 624 4213",
    "sg:postcode":"95677",
    "sg:province":"CA",
    "sg:tags":[
        "apartment"
    ],
    "wof:name":"Rocklin Manor Apartments",
    "wof:placetype":"venue"
},
  "geometry": {"coordinates":[-121.202054,38.788551],"type":"Point"}
}