{
  "type": "Feature",
  "properties": {
    "iso:country":"US",
    "sg:address":"680 Seneca Dr",
    "sg:city":"South Lake Tahoe",
    "sg:classifiers":[
        {
            "category":"Shopping",
            "subcategory":"Books",
            "type":"Retail Goods"
        }
    ],
    "sg:phone":"+1 530 577 2089",
    "sg:postcode":"96150",
    "sg:province":"CA",
    "sg:tags":[
        "dealer"
    ],
    "wof:name":"Up Country Letters",
    "wof:placetype":"venue"
},
  "geometry": {"coordinates":[-120.034031,38.867458],"type":"Point"}
}