{
  "type": "Feature",
  "properties": {
    "addr:full":"9059 San Bernardino Rd Rancho Cucamonga CA 91730",
    "addr:housenumber":"9059",
    "addr:postcode":"91730",
    "addr:street":"San Bernardino Rd",
    "iso:country":"US",
    "sg:address":"9059 San Bernardino Rd",
    "sg:city":"Rancho Cucamonga",
    "sg:classifiers":[
        {
            "category":"Government",
            "subcategory":"Office",
            "type":"Public Place"
        }
    ],
    "sg:phone":"+1 909 477 2785",
    "sg:postcode":"91730",
    "sg:province":"CA",
    "sg:tags":[
        "village"
    ],
    "sg:website":"www.rcpark.com",
    "wof:name":"Rancho Cucamonga Family Sports",
    "wof:placetype":"venue"
},
  "geometry": {"coordinates":[-117.606291,34.108799],"type":"Point"}
}