{
  "type": "Feature",
  "properties": {
    "iso:country":"US",
    "sg:address":"808 E Kelso St",
    "sg:city":"Inglewood",
    "sg:classifiers":[
        {
            "category":"Real Estate",
            "subcategory":"Real Estate Agent",
            "type":"Services"
        }
    ],
    "sg:phone":"+1 310 672 5405",
    "sg:postcode":"90301",
    "sg:province":"CA",
    "wof:name":"Evero Realty",
    "wof:placetype":"venue"
},
  "geometry": {"coordinates":[-118.34473800000001,33.956686],"type":"Point"}
}