{
  "type": "Feature",
  "properties": {
    "addr:full":"209 18th Street Manhattan Beach CA 90266",
    "addr:housenumber":"209",
    "addr:postcode":"90266",
    "addr:street":"18Th Street",
    "iso:country":"US",
    "sg:address":"209 18th Street",
    "sg:city":"Manhattan Beach",
    "sg:classifiers":[
        {
            "category":"Building & Trades",
            "subcategory":"Construction",
            "type":"Services"
        }
    ],
    "sg:phone":"+1 310 545 0164",
    "sg:postcode":"90266",
    "sg:province":"CA",
    "sg:tags":[
        "contractor"
    ],
    "wof:name":"Art Delight Construction",
    "wof:placetype":"venue"
},
  "geometry": {"coordinates":[-118.41279,33.889258],"type":"Point"}
}