{
  "type": "Feature",
  "properties": {
    "iso:country":"US",
    "sg:address":"38605 Calistoga Dr # 140",
    "sg:city":"Murrieta",
    "sg:classifiers":[
        {
            "category":"Professional",
            "subcategory":"Lawyer & Legal Services",
            "type":"Services"
        }
    ],
    "sg:phone":"+1 951 698 8890",
    "sg:postcode":"92563",
    "sg:province":"CA",
    "sg:tags":[
        "information",
        "attorney",
        "referral"
    ],
    "wof:name":"Rodriguez & Associates",
    "wof:placetype":"venue"
},
  "geometry": {"coordinates":[-117.12718700000001,33.55614],"type":"Point"}
}