{
  "type": "Feature",
  "properties": {
    "addr:full":"13762 Santa Ana Ave Fontana CA 92337",
    "addr:housenumber":"13762",
    "addr:postcode":"92337",
    "addr:street":"Santa Ana Ave",
    "iso:country":"US",
    "sg:address":"13762 Santa Ana Ave",
    "sg:city":"Fontana",
    "sg:classifiers":[
        {
            "category":"Real Estate",
            "subcategory":"Real Estate Agent",
            "type":"Services"
        }
    ],
    "sg:phone":"+1 909 877 0552",
    "sg:postcode":"92337",
    "sg:province":"CA",
    "wof:name":"Patrick Properties",
    "wof:placetype":"venue"
},
  "geometry": {"coordinates":[-117.50340199999999,34.055656],"type":"Point"}
}