{
  "type": "Feature",
  "properties": {
    "addr:full":"2285 Martin Ave Santa Clara CA 95050",
    "addr:housenumber":"2285",
    "addr:postcode":"95050",
    "addr:street":"Martin Ave",
    "iso:country":"US",
    "sg:address":"2285 Martin Ave",
    "sg:city":"Santa Clara",
    "sg:classifiers":[
        {
            "category":"Manufacturing",
            "subcategory":"Electronics",
            "type":"Manufacturing & Wholesale Goods"
        }
    ],
    "sg:phone":"+1 408 986 1088",
    "sg:postcode":"95050",
    "sg:province":"CA",
    "sg:tags":[
        "semiconductor",
        "devices"
    ],
    "sg:website":"www.imtflash.com",
    "wof:name":"Integrated Memory Technologies",
    "wof:placetype":"venue"
},
  "geometry": {"coordinates":[-121.96333199999999,37.369158],"type":"Point"}
}