{
  "type": "Feature",
  "properties": {
    "iso:country":"US",
    "sg:address":"15709 Crenshaw Blvd",
    "sg:city":"Gardena",
    "sg:classifiers":[
        {
            "category":"Restaurant",
            "type":"Food & Drink"
        },
        {
            "category":"Food & Beverages",
            "subcategory":"Ethnic Foods",
            "type":"Retail Goods"
        }
    ],
    "sg:phone":"+1 310 644 0700",
    "sg:postcode":"90249",
    "sg:province":"CA",
    "sg:tags":[
        "asian",
        "pan",
        "vietnamese"
    ],
    "wof:name":"Nhu Restaurant",
    "wof:placetype":"venue"
},
  "geometry": {"coordinates":[-118.326538,33.888031],"type":"Point"}
}