{
  "type": "Feature",
  "properties": {
    "iso:country":"US",
    "sg:address":"6115 Lake Murray Blvd",
    "sg:city":"La Mesa",
    "sg:classifiers":[
        {
            "category":"Personal",
            "subcategory":"Beauty Salon",
            "type":"Services"
        }
    ],
    "sg:phone":"+1 619 462 3411",
    "sg:postcode":"91942",
    "sg:province":"CA",
    "sg:tags":[
        "shop"
    ],
    "wof:name":"Sally Hartman Hair",
    "wof:placetype":"venue"
},
  "geometry": {"coordinates":[-117.020657,32.790674],"type":"Point"}
}