{
  "type": "Feature",
  "properties": {
    "iso:country":"US",
    "sg:address":"68379 Kieley Rd",
    "sg:city":"Cathedral City",
    "sg:classifiers":[
        {
            "category":"Building & Trades",
            "subcategory":"Construction",
            "type":"Services"
        }
    ],
    "sg:phone":"+1 760 328 1747",
    "sg:postcode":"92234",
    "sg:province":"CA",
    "sg:tags":[
        "sewer",
        "contractor"
    ],
    "wof:name":"TLE Construction Inc",
    "wof:placetype":"venue"
},
  "geometry": {"coordinates":[-116.470315,33.78621],"type":"Point"}
}