{
  "type": "Feature",
  "properties": {
    "addr:full":"1006 Overland Dr Napa CA 94558",
    "addr:housenumber":"1006",
    "addr:postcode":"94558",
    "addr:street":"Overland Dr",
    "iso:country":"US",
    "sg:address":"1006 Overland Dr",
    "sg:city":"Napa",
    "sg:classifiers":[
        {
            "category":"Building & Trades",
            "subcategory":"Construction",
            "type":"Services"
        }
    ],
    "sg:phone":"+1 707 966 1519",
    "sg:postcode":"94558",
    "sg:province":"CA",
    "sg:tags":[
        "sandblasting"
    ],
    "wof:name":"Precision Coatings",
    "wof:placetype":"venue"
},
  "geometry": {"coordinates":[-122.195476,38.505473],"type":"Point"}
}