{
  "type": "Feature",
  "properties": {
    "addr:full":"1946 Trower Ave Napa CA 94558",
    "addr:housenumber":"1946",
    "addr:postcode":"94558",
    "addr:street":"Trower Ave",
    "iso:country":"US",
    "sg:address":"1946 Trower Ave",
    "sg:city":"Napa",
    "sg:classifiers":[
        {
            "category":"Arena",
            "subcategory":"Sports Club",
            "type":"Entertainment"
        }
    ],
    "sg:phone":"+1 707 251 3837",
    "sg:postcode":"94558",
    "sg:province":"CA",
    "sg:tags":[
        "soccer"
    ],
    "wof:name":"Pure Potential",
    "wof:placetype":"venue"
},
  "geometry": {"coordinates":[-122.316435,38.331314],"type":"Point"}
}