{
  "type": "Feature",
  "properties": {
    "addr:full":"946 N 6th St San Jose CA 95112",
    "addr:housenumber":"946",
    "addr:postcode":"95112",
    "addr:street":"N 6Th St",
    "iso:country":"US",
    "sg:address":"946 N 6th St",
    "sg:city":"San Jose",
    "sg:classifiers":[
        {
            "category":"Real Estate",
            "subcategory":"Real Estate Operator",
            "type":"Services"
        }
    ],
    "sg:phone":"+1 408 279 6088",
    "sg:postcode":"95112",
    "sg:province":"CA",
    "sg:tags":[
        "property",
        "lessor"
    ],
    "wof:name":"Robert Charles Ross",
    "wof:placetype":"venue"
},
  "geometry": {"coordinates":[-121.898777,37.356885],"type":"Point"}
}