{
  "type": "Feature",
  "properties": {
    "addr:full":"2108 Wellington Rd Los Angeles CA 90016",
    "addr:housenumber":"2108",
    "addr:postcode":"90016",
    "addr:street":"Wellington Rd",
    "iso:country":"US",
    "sg:address":"2108 Wellington Rd",
    "sg:city":"Los Angeles",
    "sg:classifiers":[
        {
            "category":"Professional",
            "type":"Services"
        }
    ],
    "sg:phone":"+1 323 766 0668",
    "sg:postcode":"90016",
    "sg:province":"CA",
    "wof:name":"Grow Network Ltd",
    "wof:placetype":"venue"
},
  "geometry": {"coordinates":[-118.335111,34.037728],"type":"Point"}
}