{
  "type": "Feature",
  "properties": {
    "iso:country":"US",
    "sg:address":"3335 N Arthur Ave",
    "sg:city":"Fresno",
    "sg:classifiers":[
        {
            "category":"Education",
            "subcategory":"School",
            "type":"Public Place"
        }
    ],
    "sg:phone":"+1 559 248 7480",
    "sg:postcode":"93705",
    "sg:province":"CA",
    "sg:tags":[
        "elementary"
    ],
    "sg:website":"http://www.fresno.k12.ca.us",
    "wof:name":"Phoenix Elementary School",
    "wof:placetype":"venue"
},
  "geometry": {"coordinates":[-119.81532799999999,36.780578],"type":"Point"}
}