{
  "type": "Feature",
  "properties": {
    "iso:country":"US",
    "sg:address":"1733 Abbot Kinney Blvd",
    "sg:city":"Venice",
    "sg:classifiers":[
        {
            "category":"Professional",
            "subcategory":"Employment Agencies",
            "type":"Services"
        }
    ],
    "sg:phone":"+1 310 823 2017",
    "sg:postcode":"90291",
    "sg:province":"CA",
    "sg:tags":[
        "consultant",
        "search",
        "executive"
    ],
    "wof:name":"Engineering Management",
    "wof:placetype":"venue"
},
  "geometry": {"coordinates":[-118.459873,33.988027],"type":"Point"}
}