{
  "type": "Feature",
  "properties": {
    "iso:country":"US",
    "sg:address":"2481 Heritage Park Ln",
    "sg:city":"Sacramento",
    "sg:classifiers":[
        {
            "category":"Sports & Exercise",
            "subcategory":"Sports Center",
            "type":"Entertainment"
        }
    ],
    "sg:phone":"+1 916 515 2121",
    "sg:postcode":"95835",
    "sg:province":"CA",
    "wof:name":"Clubhouse Heritage Park",
    "wof:placetype":"venue"
},
  "geometry": {"coordinates":[-121.517444,38.682067],"type":"Point"}
}