{
  "type": "Feature",
  "properties": {
    "iso:country":"US",
    "sg:address":"6269 Van Nuys Blvd",
    "sg:city":"Van Nuys",
    "sg:classifiers":[
        {
            "category":"Restaurant",
            "type":"Food & Drink"
        }
    ],
    "sg:phone":"+1 818 989 4902",
    "sg:postcode":"91401",
    "sg:province":"CA",
    "wof:name":"A 1 Cafe",
    "wof:placetype":"venue"
},
  "geometry": {"coordinates":[-118.44878799999999,34.184129],"type":"Point"}
}