{
  "type": "Feature",
  "properties": {
    "addr:full":"23861 Mcbean Pkwy Valencia CA 91355",
    "addr:housenumber":"23861",
    "addr:postcode":"91355",
    "addr:street":"Mcbean Pkwy",
    "iso:country":"US",
    "sg:address":"23861 Mcbean Pkwy",
    "sg:city":"Valencia",
    "sg:classifiers":[
        {
            "category":"Health Services",
            "subcategory":"Doctor",
            "type":"Services"
        }
    ],
    "sg:phone":"+1 661 259 6180",
    "sg:postcode":"91355",
    "sg:province":"CA",
    "sg:tags":[
        "physician",
        "immunology",
        "allergy",
        "surgeons",
        "surgeon"
    ],
    "wof:name":"Strick Lawrence MD",
    "wof:placetype":"venue"
},
  "geometry": {"coordinates":[-118.554208,34.395664],"type":"Point"}
}