{
  "type": "Feature",
  "properties": {
    "addr:full":"11133 Kerrigan Dr Oakland CA 94605",
    "addr:housenumber":"11133",
    "addr:postcode":"94605",
    "addr:street":"Kerrigan Dr",
    "iso:country":"US",
    "sg:address":"11133 Kerrigan Dr",
    "sg:city":"Oakland",
    "sg:classifiers":[
        {
            "category":"Freight",
            "type":"Transportation"
        }
    ],
    "sg:phone":"+1 510 506 1408",
    "sg:postcode":"94605",
    "sg:province":"CA",
    "sg:tags":[
        "operator",
        "local",
        "trucking"
    ],
    "wof:name":"Moving You",
    "wof:placetype":"venue"
},
  "geometry": {"coordinates":[-122.13548900000001,37.74385],"type":"Point"}
}