{
  "type": "Feature",
  "properties": {
    "iso:country":"US",
    "sg:address":"24860 Main St",
    "sg:city":"Fall River Mills",
    "sg:classifiers":[
        {
            "category":"Travel",
            "subcategory":"Hotels & Motels",
            "type":"Entertainment"
        }
    ],
    "sg:phone":"+1 530 336 5550",
    "sg:postcode":"96028",
    "sg:province":"CA",
    "sg:website":"www.fallriverhotel.com",
    "wof:name":"Fall River Hotel & Restaurant",
    "wof:placetype":"venue"
},
  "geometry": {"coordinates":[-121.438543,41.002682],"type":"Point"}
}