{
  "type": "Feature",
  "properties": {
    "addr:full":"795 Alamo Dr Vacaville CA 95688",
    "addr:housenumber":"795",
    "addr:postcode":"95688",
    "addr:street":"Alamo Dr",
    "iso:country":"US",
    "sg:address":"795 Alamo Dr",
    "sg:city":"Vacaville",
    "sg:classifiers":[
        {
            "category":"Professional",
            "subcategory":"Research",
            "type":"Services"
        }
    ],
    "sg:phone":"+1 707 448 5999",
    "sg:postcode":"95688",
    "sg:province":"CA",
    "sg:tags":[
        "laboratory"
    ],
    "wof:name":"Recommended Test Labs Inc",
    "wof:placetype":"venue"
},
  "geometry": {"coordinates":[-121.99975999999999,38.349341],"type":"Point"}
}