{
  "type": "Feature",
  "properties": {
    "iso:country":"US",
    "sg:address":"145 Heinlen St",
    "sg:city":"Lemoore",
    "sg:classifiers":[
        {
            "category":"Professional",
            "subcategory":"Computer Services",
            "type":"Services"
        }
    ],
    "sg:phone":"+1 559 925 0204",
    "sg:postcode":"93245",
    "sg:province":"CA",
    "sg:tags":[
        "consultant",
        "designer"
    ],
    "wof:name":"Hindrichs Computing & More",
    "wof:placetype":"venue"
},
  "geometry": {"coordinates":[-119.784499,36.299707],"type":"Point"}
}