{
  "type": "Feature",
  "properties": {
    "iso:country":"US",
    "sg:address":"2669 Myrtle Ave",
    "sg:city":"Signal Hill",
    "sg:classifiers":[
        {
            "category":"Manufacturing",
            "subcategory":"Printing",
            "type":"Manufacturing & Wholesale Goods"
        }
    ],
    "sg:phone":"+1 562 427 8678",
    "sg:postcode":"90755",
    "sg:province":"CA",
    "sg:tags":[
        "newspaper"
    ],
    "wof:name":"Signal",
    "wof:placetype":"venue"
},
  "geometry": {"coordinates":[-118.18181800000001,33.805856],"type":"Point"}
}