{
  "type": "Feature",
  "properties": {
    "addr:full":"1025 Arden Rd Pasadena CA 91106",
    "addr:housenumber":"1025",
    "addr:postcode":"91106",
    "addr:street":"Arden Rd",
    "iso:country":"US",
    "sg:address":"1025 Arden Rd",
    "sg:city":"Pasadena",
    "sg:classifiers":[
        {
            "category":"Education",
            "subcategory":"School",
            "type":"Public Place"
        }
    ],
    "sg:phone":"+1 626 792 2147",
    "sg:postcode":"91106",
    "sg:province":"CA",
    "sg:tags":[
        "high",
        "middle",
        "elementary"
    ],
    "wof:name":"Polytechnic Schools",
    "wof:placetype":"venue"
},
  "geometry": {"coordinates":[-118.128905,34.132053],"type":"Point"}
}