{
  "type": "Feature",
  "properties": {
    "iso:country":"US",
    "sg:address":"2579 Ezie Ave",
    "sg:city":"Clovis",
    "sg:classifiers":[
        {
            "category":"Building & Trades",
            "subcategory":"Electrical",
            "type":"Services"
        }
    ],
    "sg:phone":"+1 559 291 6901",
    "sg:postcode":"93611",
    "sg:province":"CA",
    "sg:tags":[
        "electrical",
        "contractor"
    ],
    "wof:name":"Execu-Tech",
    "wof:placetype":"venue"
},
  "geometry": {"coordinates":[-119.685461,36.803121],"type":"Point"}
}