{
  "type": "Feature",
  "properties": {
    "iso:country":"US",
    "sg:address":"6790 Long Beach Blvd",
    "sg:city":"Long Beach",
    "sg:classifiers":[
        {
            "category":"Food & Beverages",
            "subcategory":"Groceries & Convenience Stores",
            "type":"Retail Goods"
        }
    ],
    "sg:phone":"+1 310 537 1539",
    "sg:postcode":"90805",
    "sg:province":"CA",
    "wof:name":"El Nuevo Guadalajara Market",
    "wof:placetype":"venue"
},
  "geometry": {"coordinates":[-118.203523,33.87751],"type":"Point"}
}