{
  "type": "Feature",
  "properties": {
    "addr:full":"2318 Clement Ave Alameda CA 94501",
    "addr:housenumber":"2318",
    "addr:postcode":"94501",
    "addr:street":"Clement Ave",
    "iso:country":"US",
    "sg:address":"2318 Clement Ave",
    "sg:city":"Alameda",
    "sg:classifiers":[
        {
            "category":"Home & Garden",
            "subcategory":"Furniture",
            "type":"Retail Goods"
        }
    ],
    "sg:phone":"+1 510 865 2787",
    "sg:postcode":"94501",
    "sg:province":"CA",
    "sg:tags":[
        "builder",
        "designer",
        "custom"
    ],
    "sg:website":"www.yother.com",
    "wof:name":"C J's",
    "wof:placetype":"venue"
},
  "geometry": {"coordinates":[-122.239727,37.770474],"type":"Point"}
}