{
  "type": "Feature",
  "properties": {
    "iso:country":"US",
    "sg:address":"100 1st St",
    "sg:city":"San Francisco",
    "sg:classifiers":[
        {
            "category":"Professional",
            "subcategory":"Lawyer & Legal Services",
            "type":"Services"
        }
    ],
    "sg:phone":"+1 415 882 4200",
    "sg:postcode":"94105",
    "sg:province":"CA",
    "sg:tags":[
        "attorney"
    ],
    "wof:name":"Lossing & Elston",
    "wof:placetype":"venue"
},
  "geometry": {"coordinates":[-122.397035,37.789333],"type":"Point"}
}