{
  "type": "Feature",
  "properties": {
    "addr:full":"115 S Church St Visalia CA 93291",
    "addr:housenumber":"115",
    "addr:postcode":"93291",
    "addr:street":"S Church St",
    "iso:country":"US",
    "sg:address":"115 S Church St",
    "sg:city":"Visalia",
    "sg:classifiers":[
        {
            "category":"Professional",
            "subcategory":"Lawyer & Legal Services",
            "type":"Services"
        }
    ],
    "sg:phone":"+1 559 622 9900",
    "sg:postcode":"93291",
    "sg:province":"CA",
    "sg:tags":[
        "attorney"
    ],
    "wof:name":"Kenn A Bovetti",
    "wof:placetype":"venue"
},
  "geometry": {"coordinates":[-119.291251,36.329839],"type":"Point"}
}