{
  "type": "Feature",
  "properties": {
    "addr:full":"510 N 3rd St San Jose CA 95112",
    "addr:housenumber":"510",
    "addr:postcode":"95112",
    "addr:street":"N 3Rd St",
    "iso:country":"US",
    "sg:address":"510 N 3rd St",
    "sg:city":"San Jose",
    "sg:classifiers":[
        {
            "category":"Professional",
            "subcategory":"Lawyer & Legal Services",
            "type":"Services"
        }
    ],
    "sg:phone":"+1 408 288 5505",
    "sg:postcode":"95112",
    "sg:province":"CA",
    "wof:name":"Derania Paul J Atty",
    "wof:placetype":"venue"
},
  "geometry": {"coordinates":[-121.895088,37.346092],"type":"Point"}
}