{
  "type": "Feature",
  "properties": {
    "iso:country":"US",
    "sg:address":"4931 Cloutier Dr",
    "sg:city":"Salida",
    "sg:classifiers":[
        {
            "category":"Wholesale",
            "subcategory":"Machinery & Supplies",
            "type":"Manufacturing & Wholesale Goods"
        }
    ],
    "sg:phone":"+1 209 543 9070",
    "sg:postcode":"95368",
    "sg:province":"CA",
    "sg:tags":[
        "compressor",
        "gas"
    ],
    "wof:name":"Cisco Air Systems Inc",
    "wof:placetype":"venue"
},
  "geometry": {"coordinates":[-121.08564,37.710003],"type":"Point"}
}