{
  "type": "Feature",
  "properties": {
    "iso:country":"US",
    "sg:address":"1926 S Main St",
    "sg:city":"Santa Ana",
    "sg:classifiers":[
        {
            "category":"Banks & Credit Unions",
            "subcategory":"Financial Services",
            "type":"Services"
        }
    ],
    "sg:phone":"+1 714 444 3022",
    "sg:postcode":"92707",
    "sg:province":"CA",
    "sg:tags":[
        "broker",
        "mortgage"
    ],
    "wof:name":"Santa Ana Mortgage",
    "wof:placetype":"venue"
},
  "geometry": {"coordinates":[-117.86799600000001,33.721001],"type":"Point"}
}