{
  "type": "Feature",
  "properties": {
    "iso:country":"US",
    "sg:address":"1217 Waterview Dr",
    "sg:city":"Mill Valley",
    "sg:classifiers":[
        {
            "category":"Manufacturing",
            "subcategory":"Furniture",
            "type":"Manufacturing & Wholesale Goods"
        }
    ],
    "sg:phone":"+1 415 383 3008",
    "sg:postcode":"94941",
    "sg:province":"CA",
    "sg:tags":[
        "residential",
        "mfg",
        "commercial",
        "general"
    ],
    "wof:name":"Keresztury Peter Design",
    "wof:placetype":"venue"
},
  "geometry": {"coordinates":[-122.54346099999999,37.888454],"type":"Point"}
}