{
  "type": "Feature",
  "properties": {
    "iso:country":"US",
    "sg:address":"509 Magnolia Ave",
    "sg:city":"Larkspur",
    "sg:classifiers":[
        {
            "category":"Personal",
            "subcategory":"Beauty Salon",
            "type":"Services"
        }
    ],
    "sg:phone":"+1 415 924 2338",
    "sg:postcode":"94939",
    "sg:province":"CA",
    "wof:name":"Hillary Bennett Skin Care",
    "wof:placetype":"venue"
},
  "geometry": {"coordinates":[-122.53519300000001,37.936301],"type":"Point"}
}