{
  "type": "Feature",
  "properties": {
    "iso:country":"US",
    "sg:address":"11404 Atlantic Ave",
    "sg:city":"Lynwood",
    "sg:classifiers":[
        {
            "category":"Professional",
            "subcategory":"Computer Services",
            "type":"Services"
        }
    ],
    "sg:phone":"+1 310 763 0724",
    "sg:postcode":"90262",
    "sg:province":"CA",
    "sg:tags":[
        "repair"
    ],
    "wof:name":"Pc Web Center",
    "wof:placetype":"venue"
},
  "geometry": {"coordinates":[-118.18724400000001,33.921067],"type":"Point"}
}