{
  "type": "Feature",
  "properties": {
    "iso:country":"US",
    "sg:address":"10062 Miller Ave",
    "sg:city":"Cupertino",
    "sg:classifiers":[
        {
            "category":"Real Estate",
            "subcategory":"Real Estate Agent",
            "type":"Services"
        }
    ],
    "sg:phone":"+1 408 366 2800",
    "sg:postcode":"95014",
    "sg:province":"CA",
    "wof:name":"ERA",
    "wof:placetype":"venue"
},
  "geometry": {"coordinates":[-122.014025,37.322454],"type":"Point"}
}