{
  "type": "Feature",
  "properties": {
    "addr:full":"10105 Shoemaker Ave Santa Fe Springs CA 90670",
    "addr:housenumber":"10105",
    "addr:postcode":"90670",
    "addr:street":"Shoemaker Ave",
    "iso:country":"US",
    "sg:address":"10105 Shoemaker Ave",
    "sg:city":"Santa Fe Springs",
    "sg:classifiers":[
        {
            "category":"Manufacturing",
            "subcategory":"Printing",
            "type":"Manufacturing & Wholesale Goods"
        }
    ],
    "sg:phone":"+1 562 944 2995",
    "sg:postcode":"90670",
    "sg:province":"CA",
    "sg:tags":[
        "printer"
    ],
    "wof:name":"Speed KOTE",
    "wof:placetype":"venue"
},
  "geometry": {"coordinates":[-118.055268,33.944992],"type":"Point"}
}