{
  "type": "Feature",
  "properties": {
    "iso:country":"US",
    "sg:address":"7840 Mission Center Ct",
    "sg:city":"San Diego",
    "sg:classifiers":[
        {
            "category":"Professional",
            "subcategory":"Lawyer & Legal Services",
            "type":"Services"
        }
    ],
    "sg:phone":"+1 619 293 3232",
    "sg:postcode":"92108",
    "sg:province":"CA",
    "sg:tags":[
        "attorney"
    ],
    "wof:name":"John Kiwan Law Offices",
    "wof:placetype":"venue"
},
  "geometry": {"coordinates":[-117.154929,32.77376],"type":"Point"}
}