{
  "type": "Feature",
  "properties": {
    "iso:country":"US",
    "sg:address":"1229 Rosemarie Ln Ste A",
    "sg:city":"Stockton",
    "sg:classifiers":[
        {
            "category":"Real Estate",
            "subcategory":"Real Estate Services",
            "type":"Services"
        },
        {
            "category":"Real Estate",
            "subcategory":"Real Estate Agent",
            "type":"Services"
        }
    ],
    "sg:phone":"+1 209 957 3831",
    "sg:postcode":"95207",
    "sg:province":"CA",
    "sg:tags":[
        "buyer",
        "management",
        "broker"
    ],
    "sg:website":"http://www.bruceghiorealtors.com",
    "wof:name":"Ghio Bruce Realtors",
    "wof:placetype":"venue"
},
  "geometry": {"coordinates":[-121.31982000000001,37.986863],"type":"Point"}
}