{
  "type": "Feature",
  "properties": {
    "addr:full":"23099 Connecticut St Hayward CA 94545",
    "addr:housenumber":"23099",
    "addr:postcode":"94545",
    "addr:street":"Connecticut St",
    "iso:country":"US",
    "sg:address":"23099 Connecticut St",
    "sg:city":"Hayward",
    "sg:classifiers":[
        {
            "category":"Professional",
            "type":"Services"
        }
    ],
    "sg:phone":"+1 510 785 9148",
    "sg:postcode":"94545",
    "sg:province":"CA",
    "sg:website":"www.sftubebending.com",
    "wof:name":"S.F. Tube, Inc",
    "wof:placetype":"venue"
},
  "geometry": {"coordinates":[-122.129688,37.643631],"type":"Point"}
}