{
  "type": "Feature",
  "properties": {
    "addr:full":"25621 Hercules St Valencia CA 91355",
    "addr:postcode":"25621;91355",
    "addr:street":"Hercules St",
    "iso:country":"US",
    "sg:address":"25621 Hercules St",
    "sg:city":"Valencia",
    "sg:classifiers":[
        {
            "category":"Personal",
            "type":"Services"
        },
        {
            "category":"Retail",
            "subcategory":"Storage",
            "type":"Services"
        }
    ],
    "sg:phone":"+1 888 928 4424",
    "sg:postcode":"91355",
    "sg:province":"CA",
    "sg:tags":[
        "mover",
        "self"
    ],
    "sg:website":"www.watfordmoving.com",
    "wof:name":"Watford Moving and Storage",
    "wof:placetype":"venue"
},
  "geometry": {"coordinates":[-118.57965900000001,34.453153],"type":"Point"}
}