{
  "type": "Feature",
  "properties": {
    "addr:full":"612 N Irena Ave Redondo Beach CA 90277",
    "addr:housenumber":"612",
    "addr:postcode":"90277",
    "addr:street":"N Irena Ave",
    "iso:country":"US",
    "sg:address":"612 N Irena Ave",
    "sg:city":"Redondo Beach",
    "sg:classifiers":[
        {
            "category":"Wholesale",
            "subcategory":"Machinery & Supplies",
            "type":"Manufacturing & Wholesale Goods"
        }
    ],
    "sg:phone":"+1 310 849 0001",
    "sg:postcode":"90277",
    "sg:province":"CA",
    "wof:name":"Seiche River Photonics",
    "wof:placetype":"venue"
},
  "geometry": {"coordinates":[-118.386326,33.850563],"type":"Point"}
}