{
  "type": "Feature",
  "properties": {
    "iso:country":"US",
    "sg:address":"181 Stare St",
    "sg:city":"Pomona",
    "sg:classifiers":[
        {
            "category":"Wholesale",
            "subcategory":"Hardware",
            "type":"Manufacturing & Wholesale Goods"
        }
    ],
    "sg:phone":"+1 909 392 2198",
    "sg:postcode":"91767",
    "sg:province":"CA",
    "sg:tags":[
        "industrial",
        "supply"
    ],
    "sg:website":"www.calico-tools.com",
    "wof:name":"Calico Products Inc",
    "wof:placetype":"venue"
},
  "geometry": {"coordinates":[-117.751599,34.090783],"type":"Point"}
}