{
  "type": "Feature",
  "properties": {
    "addr:full":"3701 Northgate Wood Ct Walnut Creek CA 94598",
    "addr:housenumber":"3701",
    "addr:postcode":"94598",
    "addr:street":"Northgate Wood Ct",
    "iso:country":"US",
    "sg:address":"3701 Northgate Wood Ct",
    "sg:city":"Walnut Creek",
    "sg:classifiers":[
        {
            "category":"Professional",
            "subcategory":"Computer Services",
            "type":"Services"
        }
    ],
    "sg:phone":"+1 415 357 1500",
    "sg:postcode":"94598",
    "sg:province":"CA",
    "sg:tags":[
        "hardware",
        "provider",
        "internet",
        "software"
    ],
    "wof:name":"I G Development",
    "wof:placetype":"venue"
},
  "geometry": {"coordinates":[-121.992746,37.911623],"type":"Point"}
}