{
  "type": "Feature",
  "properties": {
    "addr:full":"361 N San Antonio Rd Los Altos CA 94022",
    "addr:housenumber":"361",
    "addr:postcode":"94022",
    "addr:street":"N San Antonio Rd",
    "iso:country":"US",
    "sg:address":"361 N San Antonio Rd",
    "sg:city":"Los Altos",
    "sg:classifiers":[
        {
            "category":"Manufacturing",
            "subcategory":"Printing",
            "type":"Manufacturing & Wholesale Goods"
        }
    ],
    "sg:phone":"+1 650 949 9680",
    "sg:postcode":"94022",
    "sg:province":"CA",
    "sg:tags":[
        "periodical"
    ],
    "wof:name":"Enthusieist Publication Ltd",
    "wof:placetype":"venue"
},
  "geometry": {"coordinates":[-122.114088,37.387828],"type":"Point"}
}