{
  "type": "Feature",
  "properties": {
    "iso:country":"US",
    "sg:address":"2 S Park Ave",
    "sg:city":"San Francisco",
    "sg:classifiers":[
        {
            "category":"Banks & Credit Unions",
            "subcategory":"Financial Services",
            "type":"Services"
        }
    ],
    "sg:phone":"+1 415 979 9600",
    "sg:postcode":"94107",
    "sg:province":"CA",
    "sg:tags":[
        "company",
        "venture",
        "capital"
    ],
    "sg:website":"www.hwvp.com",
    "wof:name":"Hummer Winblad Venture Partner",
    "wof:placetype":"venue"
},
  "geometry": {"coordinates":[-122.393246,37.782137],"type":"Point"}
}