{
  "type": "Feature",
  "properties": {
    "iso:country":"US",
    "sg:address":"1450 N Tustin Ave",
    "sg:city":"Santa Ana",
    "sg:classifiers":[
        {
            "category":"Utilities",
            "subcategory":"Telephone",
            "type":"Services"
        }
    ],
    "sg:phone":"+1 714 547 8084",
    "sg:postcode":"92705",
    "sg:province":"CA",
    "sg:tags":[
        "communications",
        "consulting",
        "business"
    ],
    "wof:name":"Uplink Systems",
    "wof:placetype":"venue"
},
  "geometry": {"coordinates":[-117.834171,33.758625],"type":"Point"}
}