{
  "type": "Feature",
  "properties": {
    "iso:country":"US",
    "sg:address":"1600 Potrero Grande Dr Ste 7",
    "sg:city":"Rosemead",
    "sg:classifiers":[
        {
            "category":"Restaurant",
            "type":"Food & Drink"
        }
    ],
    "sg:phone":"+1 626 572 4600",
    "sg:postcode":"91770",
    "sg:province":"CA",
    "sg:tags":[
        "seafood"
    ],
    "sg:website":"www.fortunasea.com",
    "wof:name":"Fortuna Sea Products Inc",
    "wof:placetype":"venue"
},
  "geometry": {"coordinates":[-118.098,34.0481],"type":"Point"}
}