{
  "type": "Feature",
  "properties": {
    "addr:full":"1492 Egbert Ave San Francisco CA 94124",
    "addr:housenumber":"1492",
    "addr:postcode":"94124",
    "addr:street":"Egbert Ave",
    "iso:country":"US",
    "sg:address":"1492 Egbert Ave",
    "sg:city":"San Francisco",
    "sg:classifiers":[
        {
            "category":"Wholesale",
            "subcategory":"Hardware",
            "type":"Manufacturing & Wholesale Goods"
        }
    ],
    "sg:phone":"+1 415 822 6150",
    "sg:postcode":"94124",
    "sg:province":"CA",
    "sg:tags":[
        "furnace"
    ],
    "wof:name":"Gow Supply Co",
    "wof:placetype":"venue"
},
  "geometry": {"coordinates":[-122.394031,37.723422],"type":"Point"}
}