{
  "type": "Feature",
  "properties": {
    "addr:full":"1200 Rodeo Dr Imperial CA 92251",
    "addr:housenumber":"1200",
    "addr:postcode":"92251",
    "addr:street":"Rodeo Dr",
    "iso:country":"US",
    "sg:address":"1200 Rodeo Dr",
    "sg:city":"Imperial",
    "sg:classifiers":[
        {
            "category":"Professional",
            "type":"Services"
        }
    ],
    "sg:phone":"+1 760 355 8398",
    "sg:postcode":"92251",
    "sg:province":"CA",
    "wof:name":"Tom Turner",
    "wof:placetype":"venue"
},
  "geometry": {"coordinates":[-115.569067,32.859866],"type":"Point"}
}