{
  "type": "Feature",
  "properties": {
    "addr:full":"43418 Sanger Ln Fall River Mills CA 96028",
    "addr:housenumber":"43418",
    "addr:postcode":"96028",
    "addr:street":"Sanger Ln",
    "iso:country":"US",
    "sg:address":"43418 Sanger Ln",
    "sg:city":"Fall River Mills",
    "sg:classifiers":[
        {
            "category":"Building & Trades",
            "subcategory":"Plumbing",
            "type":"Services"
        }
    ],
    "sg:phone":"+1 530 336 5098",
    "sg:postcode":"96028",
    "sg:province":"CA",
    "sg:tags":[
        "tank",
        "septic"
    ],
    "wof:name":"Danny's Backhoe Svc",
    "wof:placetype":"venue"
},
  "geometry": {"coordinates":[-121.43288099999999,40.971447],"type":"Point"}
}