{
  "type": "Feature",
  "properties": {
    "addr:full":"6113 Buffalo Ave Van Nuys CA 91401",
    "addr:housenumber":"6113",
    "addr:postcode":"91401",
    "addr:street":"Buffalo Ave",
    "iso:country":"US",
    "sg:address":"6113 Buffalo Ave",
    "sg:city":"Van Nuys",
    "sg:classifiers":[
        {
            "category":"Wholesale",
            "subcategory":"Machinery & Supplies",
            "type":"Manufacturing & Wholesale Goods"
        }
    ],
    "sg:phone":"+1 818 988 0192",
    "sg:postcode":"91401",
    "sg:province":"CA",
    "sg:tags":[
        "equipment",
        "transportation"
    ],
    "wof:name":"Terrick Corp",
    "wof:placetype":"venue"
},
  "geometry": {"coordinates":[-118.430228,34.18197],"type":"Point"}
}