{
  "type": "Feature",
  "properties": {
    "addr:full":"6 Baruna Ct Newport Beach CA 92663",
    "addr:housenumber":"6",
    "addr:postcode":"92663",
    "addr:street":"Baruna Ct",
    "iso:country":"US",
    "sg:address":"6 Baruna Ct",
    "sg:city":"Newport Beach",
    "sg:classifiers":[
        {
            "category":"Utilities",
            "subcategory":"Telephone",
            "type":"Services"
        }
    ],
    "sg:phone":"+1 949 642 6620",
    "sg:postcode":"92663",
    "sg:province":"CA",
    "sg:tags":[
        "communications"
    ],
    "wof:name":"Instantorganizercom",
    "wof:placetype":"venue"
},
  "geometry": {"coordinates":[-117.937938,33.626771],"type":"Point"}
}