{
  "type": "Feature",
  "properties": {
    "iso:country":"US",
    "sg:address":"2890 Lopes Ln",
    "sg:city":"Loomis",
    "sg:classifiers":[
        {
            "category":"Professional",
            "type":"Services"
        }
    ],
    "sg:phone":"+1 916 652 5155",
    "sg:postcode":"95650",
    "sg:province":"CA",
    "wof:name":"Fundraising Power Co",
    "wof:placetype":"venue"
},
  "geometry": {"coordinates":[-121.184444,38.843982],"type":"Point"}
}