{
  "type": "Feature",
  "properties": {
    "iso:country":"US",
    "sg:address":"15576 Brookhurst St",
    "sg:city":"Westminster",
    "sg:classifiers":[
        {
            "category":"Real Estate",
            "subcategory":"Real Estate Agent",
            "type":"Services"
        }
    ],
    "sg:phone":"+1 714 775 6332",
    "sg:postcode":"92683",
    "sg:province":"CA",
    "wof:name":"Century 21",
    "wof:placetype":"venue"
},
  "geometry": {"coordinates":[-117.954579,33.735574],"type":"Point"}
}