{
  "type": "Feature",
  "properties": {
    "iso:country":"US",
    "sg:address":"2521 Paseo Del Compo",
    "sg:city":"Sacramento",
    "sg:classifiers":[
        {
            "category":"Building & Trades",
            "subcategory":"Landscaping Services",
            "type":"Services"
        }
    ],
    "sg:phone":"+1 916 476 8400",
    "sg:postcode":"95821",
    "sg:province":"CA",
    "wof:name":"American Landscape Design & Installation",
    "wof:placetype":"venue"
},
  "geometry": {"coordinates":[-121.403589,38.622724],"type":"Point"}
}