{
  "type": "Feature",
  "properties": {
    "iso:country":"US",
    "sg:address":"12036 Wilshire Blvd",
    "sg:city":"Los Angeles",
    "sg:classifiers":[
        {
            "category":"Shopping",
            "type":"Retail Goods"
        }
    ],
    "sg:phone":"+1 310 571 7100",
    "sg:postcode":"90025",
    "sg:province":"CA",
    "sg:tags":[
        "telephone",
        "cellular"
    ],
    "wof:name":"Wireless Innovations",
    "wof:placetype":"venue"
},
  "geometry": {"coordinates":[-118.466993,34.044464],"type":"Point"}
}