{
  "type": "Feature",
  "properties": {
    "addr:full":"10940 Fair Oaks Blvd Fair Oaks CA 95628",
    "addr:housenumber":"10940",
    "addr:postcode":"95628",
    "addr:street":"Fair Oaks Blvd",
    "iso:country":"US",
    "sg:address":"10940 Fair Oaks Blvd",
    "sg:city":"Fair Oaks",
    "sg:classifiers":[
        {
            "category":"Personal",
            "subcategory":"Nail Salon",
            "type":"Services"
        }
    ],
    "sg:phone":"+1 916 965 7347",
    "sg:postcode":"95628",
    "sg:province":"CA",
    "wof:name":"Rosy Nails",
    "wof:placetype":"venue"
},
  "geometry": {"coordinates":[-121.264044,38.649862],"type":"Point"}
}