{
  "type": "Feature",
  "properties": {
    "iso:country":"US",
    "sg:address":"2760 Corabel Ln",
    "sg:city":"Sacramento",
    "sg:classifiers":[
        {
            "category":"Building & Trades",
            "subcategory":"Construction",
            "type":"Services"
        }
    ],
    "sg:phone":"+1 916 483 4935",
    "sg:postcode":"95821",
    "sg:province":"CA",
    "sg:tags":[
        "resurfacing",
        "laying",
        "refinishing",
        "floor"
    ],
    "wof:name":"Eric Floors",
    "wof:placetype":"venue"
},
  "geometry": {"coordinates":[-121.396712,38.617053],"type":"Point"}
}