{
  "type": "Feature",
  "properties": {
    "addr:full":"625 Avington Ct Brentwood CA 94513",
    "addr:housenumber":"625",
    "addr:postcode":"94513",
    "addr:street":"Avington Ct",
    "iso:country":"US",
    "sg:address":"625 Avington Ct",
    "sg:city":"Brentwood",
    "sg:classifiers":[
        {
            "category":"Shopping",
            "subcategory":"Computers & Home Electronics",
            "type":"Retail Goods"
        }
    ],
    "sg:phone":"+1 925 516 8141",
    "sg:postcode":"94513",
    "sg:province":"CA",
    "sg:tags":[
        "software"
    ],
    "wof:name":"Jagdstaffel Software",
    "wof:placetype":"venue"
},
  "geometry": {"coordinates":[-121.70828,37.924538],"type":"Point"}
}