{
  "type": "Feature",
  "properties": {
    "addr:full":"2513 E Gage Ave Huntington Park CA 90255",
    "addr:housenumber":"2513",
    "addr:postcode":"90255",
    "addr:street":"E Gage Ave;Park",
    "iso:country":"US",
    "sg:address":"2513 E Gage Ave",
    "sg:city":"Huntington Park",
    "sg:classifiers":[
        {
            "category":"Autos & Motor Vehicles",
            "subcategory":"Auto Supplies",
            "type":"Retail Goods"
        }
    ],
    "sg:phone":"+1 323 585 7144",
    "sg:postcode":"90255",
    "sg:province":"CA",
    "sg:tags":[
        "accessory"
    ],
    "wof:name":"Super Auto Accessories",
    "wof:placetype":"venue"
},
  "geometry": {"coordinates":[-118.227412,33.981695],"type":"Point"}
}