{
  "type": "Feature",
  "properties": {
    "addr:full":"1501 E Laurel Ave Lompoc CA 93436",
    "addr:housenumber":"1501",
    "addr:postcode":"93436",
    "addr:street":"E Laurel Ave",
    "iso:country":"US",
    "sg:address":"1501 E Laurel Ave",
    "sg:city":"Lompoc",
    "sg:classifiers":[
        {
            "category":"Recreation",
            "type":"Entertainment"
        }
    ],
    "sg:phone":"+1 805 735 6163",
    "sg:postcode":"93436",
    "sg:province":"CA",
    "sg:tags":[
        "instruction",
        "gymnastic"
    ],
    "wof:name":"Gymnastics North",
    "wof:placetype":"venue"
},
  "geometry": {"coordinates":[-120.43601099999999,34.643611],"type":"Point"}
}