{
  "type": "Feature",
  "properties": {
    "addr:full":"5935 Labath Ave Rohnert Park CA 94928",
    "addr:housenumber":"5935",
    "addr:postcode":"94928",
    "addr:street":"Labath Ave",
    "iso:country":"US",
    "sg:address":"5935 Labath Ave",
    "sg:city":"Rohnert Park",
    "sg:classifiers":[
        {
            "category":"Professional",
            "type":"Services"
        }
    ],
    "sg:phone":"+1 707 584 5600",
    "sg:postcode":"94928",
    "sg:province":"CA",
    "sg:tags":[
        "establishment"
    ],
    "wof:name":"Cyclone West",
    "wof:placetype":"venue"
},
  "geometry": {"coordinates":[-122.72157199999999,38.352495],"type":"Point"}
}