{
  "type": "Feature",
  "properties": {
    "addr:full":"12824 Ave 416 Orosi CA 93647",
    "addr:housenumber":"12824",
    "addr:postcode":"93647",
    "addr:street":"Ave 416",
    "iso:country":"US",
    "sg:address":"12824 Ave 416",
    "sg:city":"Orosi",
    "sg:classifiers":[
        {
            "category":"Recreation",
            "type":"Entertainment"
        }
    ],
    "sg:phone":"+1 559 528 2201",
    "sg:postcode":"93647",
    "sg:province":"CA",
    "sg:tags":[
        "martial",
        "arts",
        "instruction"
    ],
    "wof:name":"T's Kenpo Karate",
    "wof:placetype":"venue"
},
  "geometry": {"coordinates":[-119.28588999999999,36.544869],"type":"Point"}
}