{
  "type": "Feature",
  "properties": {
    "addr:full":"2126 Haste St Berkeley CA 94704",
    "addr:housenumber":"2126",
    "addr:postcode":"94704",
    "addr:street":"Haste St",
    "iso:country":"US",
    "sg:address":"2126 Haste St",
    "sg:city":"Berkeley",
    "sg:classifiers":[
        {
            "category":"Retail",
            "subcategory":"Veterinary Services",
            "type":"Services"
        },
        {
            "category":"Retail",
            "subcategory":"Animal Services",
            "type":"Services"
        }
    ],
    "sg:phone":"+1 510 848 5041",
    "sg:postcode":"94704",
    "sg:province":"CA",
    "sg:tags":[
        "emergency",
        "pet",
        "hospital",
        "specialty",
        "laboratories-veterinary",
        "clinic",
        "veterinarian"
    ],
    "sg:website":"http://www.berkeleydogandcat.com",
    "wof:name":"Berkeley Dog & Cat Hospital",
    "wof:placetype":"venue"
},
  "geometry": {"coordinates":[-122.266943,37.864991],"type":"Point"}
}