{
  "type": "Feature",
  "properties": {
    "iso:country":"US",
    "sg:address":"5017 Stockton Blvd",
    "sg:city":"Sacramento",
    "sg:classifiers":[
        {
            "category":"Ice Cream",
            "type":"Food & Drink"
        }
    ],
    "sg:phone":"+1 916 737 8888",
    "sg:postcode":"95820",
    "sg:province":"CA",
    "sg:tags":[
        "frozen",
        "yogurt"
    ],
    "wof:name":"Long Island Ice Cream",
    "wof:placetype":"venue"
},
  "geometry": {"coordinates":[-121.445048,38.530504],"type":"Point"}
}