{
  "type": "Feature",
  "properties": {
    "iso:country":"US",
    "sg:address":"3601 Vista Way Ste 202",
    "sg:city":"Oceanside",
    "sg:classifiers":[
        {
            "category":"Health Services",
            "subcategory":"Dentist",
            "type":"Services"
        }
    ],
    "sg:phone":"+1 760 439 1871",
    "sg:postcode":"92056",
    "sg:province":"CA",
    "wof:name":"Burgess Chad DDS",
    "wof:placetype":"venue"
},
  "geometry": {"coordinates":[-117.307,33.180899],"type":"Point"}
}