{
  "type": "Feature",
  "properties": {
    "addr:full":"1593 W Redlands Blvd Redlands CA 92373",
    "addr:housenumber":"1593",
    "addr:postcode":"92373",
    "addr:street":"W Redlands Blvd",
    "iso:country":"US",
    "sg:address":"1593 W Redlands Blvd",
    "sg:city":"Redlands",
    "sg:classifiers":[
        {
            "category":"Utilities",
            "subcategory":"Mobile Phone",
            "type":"Services"
        }
    ],
    "sg:phone":"+1 909 307 2030",
    "sg:postcode":"92373",
    "sg:province":"CA",
    "sg:tags":[
        "telephone",
        "cellular"
    ],
    "wof:name":"All Stop Wireless",
    "wof:placetype":"venue"
},
  "geometry": {"coordinates":[-117.208778,34.062803],"type":"Point"}
}