{
  "type": "Feature",
  "properties": {
    "iso:country":"US",
    "sg:address":"10201 Lindley Ave",
    "sg:city":"Northridge",
    "sg:classifiers":[
        {
            "category":"Real Estate",
            "subcategory":"Real Estate Operator",
            "type":"Services"
        }
    ],
    "sg:phone":"+1 818 363 4029",
    "sg:postcode":"91325",
    "sg:province":"CA",
    "sg:tags":[
        "apartment"
    ],
    "wof:name":"Canyon Creek Apartments",
    "wof:placetype":"venue"
},
  "geometry": {"coordinates":[-118.52742499999999,34.257266],"type":"Point"}
}