{
  "type": "Feature",
  "properties": {
    "addr:full":"2195 E Prosperity Ave Tulare CA 93274",
    "addr:housenumber":"2195",
    "addr:postcode":"93274",
    "addr:street":"E Prosperity Ave",
    "iso:country":"US",
    "sg:address":"2195 E Prosperity Ave",
    "sg:city":"Tulare",
    "sg:classifiers":[
        {
            "category":"Shopping",
            "subcategory":"Department Store",
            "type":"Retail Goods"
        },
        {
            "category":"Shopping",
            "subcategory":"Clothing, Apparel, & Fashions",
            "type":"Retail Goods"
        },
        {
            "category":"Shopping",
            "type":"Retail Goods"
        },
        {
            "category":"Shopping",
            "subcategory":"Discount & Variety Stores",
            "type":"Retail Goods"
        }
    ],
    "sg:phone":"+1 559 631 1128",
    "sg:postcode":"93274",
    "sg:province":"CA",
    "sg:tags":[
        "clothing",
        "merchandise"
    ],
    "sg:website":"http://www.target.com",
    "wof:name":"Target",
    "wof:placetype":"venue"
},
  "geometry": {"coordinates":[-119.311424,36.225914],"type":"Point"}
}