{
  "type": "Feature",
  "properties": {
    "iso:country":"US",
    "sg:address":"456 W Marshall Blvd",
    "sg:city":"San Bernardino",
    "sg:classifiers":[
        {
            "category":"Retail",
            "subcategory":"Auto Repair",
            "type":"Services"
        }
    ],
    "sg:phone":"+1 909 882 6016",
    "sg:postcode":"92405",
    "sg:province":"CA",
    "sg:tags":[
        "repairing",
        "automobile"
    ],
    "wof:name":"Chuck Jacobson Auto Svc",
    "wof:placetype":"venue"
},
  "geometry": {"coordinates":[-117.29405199999999,34.149577],"type":"Point"}
}