{
  "type": "Feature",
  "properties": {
    "iso:country":"US",
    "sg:address":"3738 Ruffin Rd",
    "sg:city":"San Diego",
    "sg:classifiers":[
        {
            "category":"Professional",
            "subcategory":"Engineering",
            "type":"Services"
        }
    ],
    "sg:phone":"+1 858 292 8922",
    "sg:postcode":"92123",
    "sg:province":"CA",
    "sg:tags":[
        "engineer"
    ],
    "wof:name":"Racal Pelagos Inc",
    "wof:placetype":"venue"
},
  "geometry": {"coordinates":[-117.119402,32.809766],"type":"Point"}
}