{
  "type": "Feature",
  "properties": {
    "addr:full":"887 41st Avenue Santa Cruz CA 95062",
    "addr:housenumber":"887",
    "addr:postcode":"95062",
    "addr:street":"41St Avenue",
    "iso:country":"US",
    "sg:address":"887 41st Avenue",
    "sg:city":"Santa Cruz",
    "sg:classifiers":[
        {
            "category":"Health Services",
            "subcategory":"Chiropractor",
            "type":"Services"
        }
    ],
    "sg:phone":"+1 831 475 2225",
    "sg:postcode":"95062",
    "sg:province":"CA",
    "wof:name":"Moffet Chiropractic Office",
    "wof:placetype":"venue"
},
  "geometry": {"coordinates":[-121.96500399999999,36.964492],"type":"Point"}
}