{
  "type": "Feature",
  "properties": {
    "addr:full":"1211 Coast Village Rd Santa Barbara CA 93108",
    "addr:housenumber":"1211",
    "addr:postcode":"93108",
    "addr:street":"Coast Village Rd",
    "iso:country":"US",
    "sg:address":"1211 Coast Village Rd",
    "sg:city":"Santa Barbara",
    "sg:classifiers":[
        {
            "category":"Social Services",
            "type":"Services"
        }
    ],
    "sg:phone":"+1 805 969 2050",
    "sg:postcode":"93108",
    "sg:province":"CA",
    "sg:tags":[
        "counselor",
        "marriage",
        "family"
    ],
    "wof:name":"Jaffe & Jaffe",
    "wof:placetype":"venue"
},
  "geometry": {"coordinates":[-119.64198399999999,34.421191],"type":"Point"}
}