{
  "type": "Feature",
  "properties": {
    "addr:full":"205 Brighton Ct. Alameda CA 94502",
    "addr:housenumber":"205",
    "addr:postcode":"94502",
    "addr:street":"Brighton Ct.",
    "iso:country":"US",
    "sg:address":"205 Brighton Ct.",
    "sg:city":"Alameda",
    "sg:classifiers":[
        {
            "category":"Professional",
            "type":"Services"
        }
    ],
    "sg:phone":"+1 510 769 7469",
    "sg:postcode":"94502",
    "sg:province":"CA",
    "sg:website":"www.wordprocess.com",
    "wof:name":"BZ Business Services",
    "wof:placetype":"venue"
},
  "geometry": {"coordinates":[-122.24473500000001,37.744044],"type":"Point"}
}