{
  "type": "Feature",
  "properties": {
    "iso:country":"US",
    "sg:address":"124 Baypointe Dr",
    "sg:city":"Newport Beach",
    "sg:classifiers":[
        {
            "category":"Professional",
            "type":"Services"
        }
    ],
    "sg:phone":"+1 949 706 1197",
    "sg:postcode":"92660",
    "sg:province":"CA",
    "wof:name":"Reflections of Youth",
    "wof:placetype":"venue"
},
  "geometry": {"coordinates":[-117.864456,33.650015],"type":"Point"}
}