{
  "type": "Feature",
  "properties": {
    "iso:country":"US",
    "sg:address":"19925 Stevens Creek Blvd",
    "sg:city":"Cupertino",
    "sg:classifiers":[
        {
            "category":"Manufacturing",
            "subcategory":"Electronics",
            "type":"Manufacturing & Wholesale Goods"
        }
    ],
    "sg:phone":"+1 408 973 7845",
    "sg:postcode":"95014",
    "sg:province":"CA",
    "sg:tags":[
        "semiconductor",
        "devices"
    ],
    "wof:name":"Chipcon",
    "wof:placetype":"venue"
},
  "geometry": {"coordinates":[-122.022649,37.32292],"type":"Point"}
}