{
  "type": "Feature",
  "properties": {
    "addr:full":"2214 Arden Way Sacramento CA 95825",
    "addr:housenumber":"2214",
    "addr:postcode":"95825",
    "addr:street":"Arden Way",
    "iso:country":"US",
    "sg:address":"2214 Arden Way",
    "sg:city":"Sacramento",
    "sg:classifiers":[
        {
            "category":"Professional",
            "subcategory":"Computer Services",
            "type":"Services"
        }
    ],
    "sg:phone":"+1 916 290 8614",
    "sg:postcode":"95825",
    "sg:province":"CA",
    "sg:tags":[
        "internet"
    ],
    "wof:name":"Ipolis Corp",
    "wof:placetype":"venue"
},
  "geometry": {"coordinates":[-121.41529800000001,38.596119],"type":"Point"}
}