{
  "type": "Feature",
  "properties": {
    "addr:full":"10 Locust Ave Mill Valley CA 94941",
    "addr:housenumber":"10",
    "addr:postcode":"94941",
    "addr:street":"Locust Ave",
    "iso:country":"US",
    "sg:address":"10 Locust Ave",
    "sg:city":"Mill Valley",
    "sg:classifiers":[
        {
            "category":"Real Estate",
            "subcategory":"Real Estate Operator",
            "type":"Services"
        }
    ],
    "sg:phone":"+1 415 388 0140",
    "sg:postcode":"94941",
    "sg:province":"CA",
    "sg:tags":[
        "apartment"
    ],
    "wof:name":"Apartment A",
    "wof:placetype":"venue"
},
  "geometry": {"coordinates":[-122.537362,37.898371],"type":"Point"}
}