{
  "type": "Feature",
  "properties": {
    "addr:full":"555 McLaughlin Ave San Jose CA 95116",
    "addr:housenumber":"555",
    "addr:postcode":"95116",
    "addr:street":"Mclaughlin Ave",
    "iso:country":"US",
    "sg:address":"555 McLaughlin Ave",
    "sg:city":"San Jose",
    "sg:classifiers":[
        {
            "category":"Real Estate",
            "subcategory":"Real Estate Operator",
            "type":"Services"
        }
    ],
    "sg:phone":"+1 408 297 0360",
    "sg:postcode":"95116",
    "sg:province":"CA",
    "sg:tags":[
        "mobile",
        "home",
        "community"
    ],
    "wof:name":"Sunset Mobile Manor Office",
    "wof:placetype":"venue"
},
  "geometry": {"coordinates":[-121.861678,37.340784],"type":"Point"}
}