{
  "type": "Feature",
  "properties": {
    "addr:full":"2027 Preisker Ln Santa Maria CA 93454",
    "addr:housenumber":"2027",
    "addr:postcode":"93454",
    "addr:street":"Preisker Ln",
    "iso:country":"US",
    "sg:address":"2027 Preisker Ln",
    "sg:city":"Santa Maria",
    "sg:classifiers":[
        {
            "category":"Manufacturing",
            "subcategory":"Printing",
            "type":"Manufacturing & Wholesale Goods"
        }
    ],
    "sg:phone":"+1 805 925 7170",
    "sg:postcode":"93454",
    "sg:province":"CA",
    "sg:tags":[
        "screen",
        "commercial"
    ],
    "wof:name":"Images Screen Printing",
    "wof:placetype":"venue"
},
  "geometry": {"coordinates":[-120.432134,34.979018],"type":"Point"}
}