{
  "type": "Feature",
  "properties": {
    "iso:country":"US",
    "sg:address":"6055 Windemere Way",
    "sg:city":"Riverside",
    "sg:classifiers":[
        {
            "category":"Wholesale",
            "subcategory":"Medical Equipment & Supplies",
            "type":"Manufacturing & Wholesale Goods"
        }
    ],
    "sg:phone":"+1 951 784 7880",
    "sg:postcode":"92506",
    "sg:province":"CA",
    "wof:name":"Vista Innovations Inc",
    "wof:placetype":"venue"
},
  "geometry": {"coordinates":[-117.348119,33.940502],"type":"Point"}
}