{
  "type": "Feature",
  "properties": {
    "iso:country":"US",
    "sg:address":"300 N Dearborn St",
    "sg:city":"Redlands",
    "sg:classifiers":[
        {
            "category":"Shopping",
            "subcategory":"Clothing, Apparel, & Fashions",
            "type":"Retail Goods"
        },
        {
            "category":"Shopping",
            "subcategory":"Bicycles & Sporting Goods",
            "type":"Retail Goods"
        }
    ],
    "sg:phone":"+1 909 794 6995",
    "sg:postcode":"92374",
    "sg:province":"CA",
    "sg:tags":[
        "sportswear"
    ],
    "wof:name":"Redlands Racquet & Golf Shop",
    "wof:placetype":"venue"
},
  "geometry": {"coordinates":[-117.147667,34.058265],"type":"Point"}
}