{
  "type": "Feature",
  "properties": {
    "addr:full":"3918 Hicock St San Diego CA 92110",
    "addr:housenumber":"3918",
    "addr:postcode":"92110",
    "addr:street":"Hicock St",
    "iso:country":"US",
    "sg:address":"3918 Hicock St",
    "sg:city":"San Diego",
    "sg:classifiers":[
        {
            "category":"Arts & Performance",
            "subcategory":"Theater",
            "type":"Entertainment"
        }
    ],
    "sg:phone":"+1 619 692 0590",
    "sg:postcode":"92110",
    "sg:province":"CA",
    "wof:name":"Full Spectrum Arts Inc",
    "wof:placetype":"venue"
},
  "geometry": {"coordinates":[-117.207871,32.758455],"type":"Point"}
}