{
  "type": "Feature",
  "properties": {
    "iso:country":"US",
    "sg:address":"32332 Cam Capistrano",
    "sg:city":"San Juan Capistrano",
    "sg:classifiers":[
        {
            "category":"Wholesale",
            "subcategory":"Computers",
            "type":"Manufacturing & Wholesale Goods"
        }
    ],
    "sg:phone":"+1 949 234 1173",
    "sg:postcode":"92675",
    "sg:province":"CA",
    "sg:tags":[
        "internet",
        "based",
        "system",
        "learning",
        "software"
    ],
    "wof:name":"RSI",
    "wof:placetype":"venue"
},
  "geometry": {"coordinates":[-117.662581,33.494644],"type":"Point"}
}