{
  "type": "Feature",
  "properties": {
    "addr:full":"16176 Beaver Rd Adelanto CA 92301",
    "addr:housenumber":"16176",
    "addr:postcode":"92301",
    "addr:street":"Beaver Rd",
    "iso:country":"US",
    "sg:address":"16176 Beaver Rd",
    "sg:city":"Adelanto",
    "sg:classifiers":[
        {
            "category":"Professional",
            "subcategory":"Business Services",
            "type":"Services"
        }
    ],
    "sg:phone":"+1 760 246 8191",
    "sg:postcode":"92301",
    "sg:province":"CA",
    "sg:tags":[
        "water",
        "treatment"
    ],
    "wof:name":"O & G Water",
    "wof:placetype":"venue"
},
  "geometry": {"coordinates":[-117.460058,34.539342],"type":"Point"}
}