{
  "type": "Feature",
  "properties": {
    "iso:country":"US",
    "sg:address":"2111 Palm Ave",
    "sg:city":"San Mateo",
    "sg:classifiers":[
        {
            "category":"Personal",
            "type":"Services"
        }
    ],
    "sg:phone":"+1 650 595 4869",
    "sg:postcode":"94403",
    "sg:province":"CA",
    "sg:tags":[
        "towing"
    ],
    "sg:website":"www.qualitytowing4u.com",
    "wof:name":"Quality Towing",
    "wof:placetype":"venue"
},
  "geometry": {"coordinates":[-122.307276,37.548164],"type":"Point"}
}