{
  "type": "Feature",
  "properties": {
    "iso:country":"US",
    "sg:address":"1326 Broadway",
    "sg:city":"Burlingame",
    "sg:classifiers":[
        {
            "category":"Home & Garden",
            "subcategory":"Hardware",
            "type":"Retail Goods"
        }
    ],
    "sg:phone":"+1 650 347 2822",
    "sg:postcode":"94010",
    "sg:province":"CA",
    "sg:tags":[
        "store"
    ],
    "wof:name":"Broadway Hardware",
    "wof:placetype":"venue"
},
  "geometry": {"coordinates":[-122.36599699999999,37.585201],"type":"Point"}
}