{
  "type": "Feature",
  "properties": {
    "addr:full":"2902 Oak St Paso Robles CA 93446",
    "addr:housenumber":"2902",
    "addr:postcode":"93446",
    "addr:street":"Oak St",
    "iso:country":"US",
    "sg:address":"2902 Oak St",
    "sg:city":"Paso Robles",
    "sg:classifiers":[
        {
            "category":"Building & Trades",
            "subcategory":"Construction",
            "type":"Services"
        }
    ],
    "sg:phone":"+1 805 227 6428",
    "sg:postcode":"93446",
    "sg:province":"CA",
    "sg:tags":[
        "contractor"
    ],
    "wof:name":"Drewisch Plastering",
    "wof:placetype":"venue"
},
  "geometry": {"coordinates":[-120.694711,35.644797],"type":"Point"}
}