{
  "type": "Feature",
  "properties": {
    "addr:full":"4001 N Meadowbrook St Orange CA 92865",
    "addr:housenumber":"4001",
    "addr:postcode":"92865",
    "addr:street":"N Meadowbrook St",
    "iso:country":"US",
    "sg:address":"4001 N Meadowbrook St",
    "sg:city":"Orange",
    "sg:classifiers":[
        {
            "category":"Manufacturing",
            "subcategory":"Motor Vehicles & Parts",
            "type":"Manufacturing & Wholesale Goods"
        }
    ],
    "sg:phone":"+1 805 300 2868",
    "sg:postcode":"92865",
    "sg:province":"CA",
    "sg:tags":[
        "mfg"
    ],
    "wof:name":"Eightball Rods & Choppers",
    "wof:placetype":"venue"
},
  "geometry": {"coordinates":[-117.843208,33.843897],"type":"Point"}
}