{
  "type": "Feature",
  "properties": {
    "addr:full":"4300 San Pablo Dam Rd El Sobrante CA 94803",
    "addr:housenumber":"4300",
    "addr:postcode":"94803",
    "addr:street":"San Pablo Dam Rd",
    "iso:country":"US",
    "sg:address":"4300 San Pablo Dam Rd",
    "sg:city":"El Sobrante",
    "sg:classifiers":[
        {
            "category":"Health Services",
            "subcategory":"Doctor",
            "type":"Services"
        }
    ],
    "sg:phone":"+1 510 222 2442",
    "sg:postcode":"94803",
    "sg:province":"CA",
    "sg:tags":[
        "dentist"
    ],
    "wof:name":"Brisbin & Brisbin",
    "wof:placetype":"venue"
},
  "geometry": {"coordinates":[-122.301152,37.966248],"type":"Point"}
}