{
  "type": "Feature",
  "properties": {
    "addr:full":"23639 Arlington Ave Torrance CA 90501",
    "addr:housenumber":"23639",
    "addr:postcode":"90501",
    "addr:street":"Arlington Ave",
    "iso:country":"US",
    "sg:address":"23639 Arlington Ave",
    "sg:city":"Torrance",
    "sg:classifiers":[
        {
            "category":"Manufacturing",
            "subcategory":"Buildings",
            "type":"Manufacturing & Wholesale Goods"
        }
    ],
    "sg:phone":"+1 310 534 5755",
    "sg:postcode":"90501",
    "sg:province":"CA",
    "sg:tags":[
        "prefab"
    ],
    "wof:name":"National Mobile Home Listings",
    "wof:placetype":"venue"
},
  "geometry": {"coordinates":[-118.31997200000001,33.810008],"type":"Point"}
}