{
  "type": "Feature",
  "properties": {
    "iso:country":"US",
    "sg:address":"16901 Main St",
    "sg:city":"Hesperia",
    "sg:classifiers":[
        {
            "category":"Home & Garden",
            "subcategory":"Carpets & Floor Coverings",
            "type":"Retail Goods"
        }
    ],
    "sg:phone":"+1 760 244 3197",
    "sg:postcode":"92345",
    "sg:province":"CA",
    "sg:tags":[
        "dealer",
        "rug"
    ],
    "wof:name":"Carpet Corral",
    "wof:placetype":"venue"
},
  "geometry": {"coordinates":[-117.295609,34.420594],"type":"Point"}
}