{
  "type": "Feature",
  "properties": {
    "addr:full":"10837 Commerce Way Fontana CA 92337",
    "addr:housenumber":"10837",
    "addr:postcode":"92337",
    "addr:street":"Commerce Way",
    "iso:country":"US",
    "sg:address":"10837 Commerce Way",
    "sg:city":"Fontana",
    "sg:classifiers":[
        {
            "category":"Professional",
            "subcategory":"Advertising",
            "type":"Services"
        }
    ],
    "sg:phone":"+1 909 357 0761",
    "sg:postcode":"92337",
    "sg:province":"CA",
    "sg:tags":[
        "distribution"
    ],
    "wof:name":"LSI Regional Sales Office",
    "wof:placetype":"venue"
},
  "geometry": {"coordinates":[-117.513109,34.061747],"type":"Point"}
}