{
  "type": "Feature",
  "properties": {
    "addr:full":"10776 Lower Azusa Rd El Monte CA 91731",
    "addr:housenumber":"10776",
    "addr:postcode":"91731",
    "addr:street":"Lower Azusa Rd",
    "iso:country":"US",
    "sg:address":"10776 Lower Azusa Rd",
    "sg:city":"El Monte",
    "sg:classifiers":[
        {
            "category":"Manufacturing",
            "subcategory":"Signs",
            "type":"Manufacturing & Wholesale Goods"
        }
    ],
    "sg:phone":"+1 626 579 2100",
    "sg:postcode":"91731",
    "sg:province":"CA",
    "sg:tags":[
        "specialty",
        "mfg"
    ],
    "wof:name":"Hollywood Sign Works",
    "wof:placetype":"venue"
},
  "geometry": {"coordinates":[-118.032735,34.09266],"type":"Point"}
}