{
  "type": "Feature",
  "properties": {
    "iso:country":"US",
    "sg:address":"19548 4 Oaks St",
    "sg:city":"Santa Clarita",
    "sg:classifiers":[
        {
            "category":"Wholesale",
            "subcategory":"Hardware",
            "type":"Manufacturing & Wholesale Goods"
        }
    ],
    "sg:phone":"+1 661 299 1555",
    "sg:postcode":"91351",
    "sg:province":"CA",
    "sg:tags":[
        "prevention",
        "flow",
        "back",
        "devices"
    ],
    "wof:name":"A V Sierra Plumbing & Backflow",
    "wof:placetype":"venue"
},
  "geometry": {"coordinates":[-118.597112,34.392091],"type":"Point"}
}