{
  "type": "Feature",
  "properties": {
    "addr:full":"7007 Friars Rd Ste 550 San Diego CA 92108",
    "addr:housenumber":"7007",
    "addr:postcode":"92108",
    "addr:street":"Friars Rd Ste 550",
    "iso:country":"US",
    "sg:address":"7007 Friars Rd Ste 550",
    "sg:city":"San Diego",
    "sg:classifiers":[
        {
            "category":"Shopping",
            "subcategory":"Clothing, Apparel, & Fashions",
            "type":"Retail Goods"
        }
    ],
    "sg:phone":"+1 619 542 1414",
    "sg:postcode":"92108",
    "sg:province":"CA",
    "sg:tags":[
        "accessory",
        "clothing",
        "women's"
    ],
    "wof:name":"Jewel",
    "wof:placetype":"venue"
},
  "geometry": {"coordinates":[-117.168999,32.769501],"type":"Point"}
}