{
  "type": "Feature",
  "properties": {
    "iso:country":"US",
    "sg:address":"6911 Deerwood Ct",
    "sg:city":"Livermore",
    "sg:classifiers":[
        {
            "category":"Shopping",
            "subcategory":"Bicycles & Sporting Goods",
            "type":"Retail Goods"
        }
    ],
    "sg:phone":"+1 925 454 8697",
    "sg:postcode":"94550",
    "sg:province":"CA",
    "sg:tags":[
        "equipment",
        "skateboard"
    ],
    "sg:website":"www.gopedguy.com",
    "wof:name":"KAOS Board Shop",
    "wof:placetype":"venue"
},
  "geometry": {"coordinates":[-121.711043,37.718623],"type":"Point"}
}