{
  "type": "Feature",
  "properties": {
    "iso:country":"US",
    "sg:address":"1043 W 23rd St",
    "sg:city":"Los Angeles",
    "sg:classifiers":[
        {
            "category":"Building & Trades",
            "subcategory":"Construction",
            "type":"Services"
        }
    ],
    "sg:phone":"+1 213 745 5891",
    "sg:postcode":"90007",
    "sg:province":"CA",
    "sg:tags":[
        "contractor"
    ],
    "wof:name":"Jjs General Contractor",
    "wof:placetype":"venue"
},
  "geometry": {"coordinates":[-118.282755,34.034672],"type":"Point"}
}