{
  "type": "Feature",
  "properties": {
    "addr:full":"1117 W Union Ave Modesto CA 95356",
    "addr:housenumber":"1117",
    "addr:postcode":"ca 95356",
    "addr:street":"W Union Ave",
    "iso:country":"US",
    "sg:address":"1117 W Union Ave",
    "sg:city":"Modesto",
    "sg:classifiers":[
        {
            "category":"Education",
            "subcategory":"Special Training",
            "type":"Public Place"
        }
    ],
    "sg:phone":"+1 209 492 0418",
    "sg:postcode":"95356",
    "sg:province":"CA",
    "sg:tags":[
        "educational"
    ],
    "wof:name":"Motherbirth",
    "wof:placetype":"venue"
},
  "geometry": {"coordinates":[-121.008444,37.693054],"type":"Point"}
}