{
  "type": "Feature",
  "properties": {
    "iso:country":"US",
    "sg:address":"14125 Oxnard St",
    "sg:city":"Van Nuys",
    "sg:classifiers":[
        {
            "category":"Government",
            "subcategory":"Office",
            "type":"Public Place"
        }
    ],
    "sg:phone":"+1 818 782 5393",
    "sg:postcode":"91401",
    "sg:province":"CA",
    "sg:tags":[
        "smog",
        "check"
    ],
    "sg:website":"www.smogcheckvannuys.com/",
    "wof:name":"Smog Zone",
    "wof:placetype":"venue"
},
  "geometry": {"coordinates":[-118.440929,34.179414],"type":"Point"}
}