{
  "type": "Feature",
  "properties": {
    "addr:full":"3140 de la Cruz Blvd Santa Clara CA 95054",
    "addr:housenumber":"3140",
    "addr:postcode":"95054",
    "addr:street":"De La Cruz Blvd",
    "iso:country":"US",
    "sg:address":"3140 de la Cruz Blvd",
    "sg:city":"Santa Clara",
    "sg:classifiers":[
        {
            "category":"Real Estate",
            "subcategory":"Real Estate Agent",
            "type":"Services"
        }
    ],
    "sg:phone":"+1 408 988 7060",
    "sg:postcode":"95054",
    "sg:province":"CA",
    "wof:name":"Realty World Premier Homes",
    "wof:placetype":"venue"
},
  "geometry": {"coordinates":[-121.940313,37.380475],"type":"Point"}
}