{
  "type": "Feature",
  "properties": {
    "iso:country":"US",
    "sg:address":"210 Bel Ayre Dr",
    "sg:city":"San Jose",
    "sg:classifiers":[
        {
            "category":"Banks & Credit Unions",
            "subcategory":"Financial Services",
            "type":"Services"
        }
    ],
    "sg:phone":"+1 408 260 7450",
    "sg:postcode":"95117",
    "sg:province":"CA",
    "sg:tags":[
        "investor"
    ],
    "wof:name":"Neighborhood Notary & Tax Svc",
    "wof:placetype":"venue"
},
  "geometry": {"coordinates":[-121.960919,37.325804],"type":"Point"}
}