{
  "type": "Feature",
  "properties": {
    "iso:country":"US",
    "sg:address":"17443 Grevillea St",
    "sg:city":"Fontana",
    "sg:classifiers":[
        {
            "category":"Building & Trades",
            "subcategory":"Landscaping Services",
            "type":"Services"
        }
    ],
    "sg:phone":"+1 909 829 2874",
    "sg:postcode":"92335",
    "sg:province":"CA",
    "wof:name":"Gettings Gardening",
    "wof:placetype":"venue"
},
  "geometry": {"coordinates":[-117.425358,34.079443],"type":"Point"}
}