{
  "type": "Feature",
  "properties": {
    "iso:country":"US",
    "sg:address":"1311 25th St",
    "sg:city":"Richmond",
    "sg:classifiers":[
        {
            "category":"Building & Trades",
            "subcategory":"Cleaning & Sanitation",
            "type":"Services"
        }
    ],
    "sg:phone":"+1 510 620 0536",
    "sg:postcode":"94806",
    "sg:province":"CA",
    "sg:tags":[
        "janitor"
    ],
    "wof:name":"JDN Janitorial",
    "wof:placetype":"venue"
},
  "geometry": {"coordinates":[-122.34463100000001,37.953485],"type":"Point"}
}