{
  "type": "Feature",
  "properties": {
    "addr:full":"430 Cam Bandera San Clemente CA 92673",
    "addr:housenumber":"430",
    "addr:postcode":"92673",
    "addr:street":"Cam Bandera",
    "iso:country":"US",
    "sg:address":"430 Cam Bandera",
    "sg:city":"San Clemente",
    "sg:classifiers":[
        {
            "category":"Wholesale",
            "subcategory":"Groceries",
            "type":"Manufacturing & Wholesale Goods"
        }
    ],
    "sg:phone":"+1 949 366 9898",
    "sg:postcode":"92673",
    "sg:province":"CA",
    "wof:name":"San Francisco Pretzel",
    "wof:placetype":"venue"
},
  "geometry": {"coordinates":[-117.593722,33.468753],"type":"Point"}
}