{
  "type": "Feature",
  "properties": {
    "addr:full":"498 N Mathilda Avenue Sunnyvale CA 94085",
    "addr:housenumber":"498",
    "addr:postcode":"94085",
    "addr:street":"N Mathilda Avenue",
    "iso:country":"US",
    "sg:address":"498 N Mathilda Avenue",
    "sg:city":"Sunnyvale",
    "sg:classifiers":[
        {
            "category":"Autos & Motor Vehicles",
            "subcategory":"Fuel & Gas Station",
            "type":"Retail Goods"
        },
        {
            "category":"Retail",
            "subcategory":"Auto Repair",
            "type":"Services"
        }
    ],
    "sg:phone":"+1 408 245 2122",
    "sg:postcode":"94085",
    "sg:province":"CA",
    "wof:name":"Mathilda Valero Station Auto Services",
    "wof:placetype":"venue"
},
  "geometry": {"coordinates":[-122.030248,37.389515],"type":"Point"}
}