{
  "type": "Feature",
  "properties": {
    "addr:full":"4183 Chino Hills Pkwy Chino Hills CA 91709",
    "addr:housenumber":"4183",
    "addr:postcode":"91709",
    "addr:street":"Chino Hills Pkwy",
    "iso:country":"US",
    "sg:address":"4183 Chino Hills Pkwy",
    "sg:city":"Chino Hills",
    "sg:classifiers":[
        {
            "category":"Health Services",
            "subcategory":"Doctor",
            "type":"Services"
        }
    ],
    "sg:phone":"+1 909 393 7966",
    "sg:postcode":"91709",
    "sg:province":"CA",
    "sg:tags":[
        "physician",
        "surgeon"
    ],
    "wof:name":"Allergy & Asthma Group",
    "wof:placetype":"venue"
},
  "geometry": {"coordinates":[-117.71257,33.982605],"type":"Point"}
}