{
  "type": "Feature",
  "properties": {
    "addr:full":"25422 Trabuco Rd Ste 105-426 Lake Forest CA 92630",
    "addr:housenumber":"25422",
    "addr:postcode":"92630",
    "addr:street":"Trabuco Rd Ste 105-426",
    "iso:country":"US",
    "sg:address":"25422 Trabuco Rd Ste 105-426",
    "sg:city":"Lake Forest",
    "sg:classifiers":[
        {
            "category":"Professional",
            "subcategory":"Computer Services",
            "type":"Services"
        }
    ],
    "sg:phone":"+1 949 235 8742",
    "sg:postcode":"92630",
    "sg:province":"CA",
    "sg:tags":[
        "repair"
    ],
    "sg:website":"www.th2tech.com",
    "wof:name":"TH2 TECHNOLOGIES INC",
    "wof:placetype":"venue"
},
  "geometry": {"coordinates":[-117.687028,33.648107],"type":"Point"}
}