{
  "type": "Feature",
  "properties": {
    "iso:country":"US",
    "sg:address":"25491 Redlands Blvd",
    "sg:city":"Loma Linda",
    "sg:classifiers":[
        {
            "category":"Banks & Credit Unions",
            "subcategory":"Bank",
            "type":"Services"
        }
    ],
    "sg:phone":"+1 951 674 1961",
    "sg:postcode":"92354",
    "sg:province":"CA",
    "sg:tags":[
        "broker",
        "mortgage"
    ],
    "wof:name":"Matrix RE & Investments",
    "wof:placetype":"venue"
},
  "geometry": {"coordinates":[-117.249583,34.062992],"type":"Point"}
}