{
  "type": "Feature",
  "properties": {
    "addr:full":"900 Island Dr Redwood City CA 94065",
    "addr:housenumber":"900",
    "addr:postcode":"94065",
    "addr:street":"Island Dr",
    "iso:country":"US",
    "sg:address":"900 Island Dr",
    "sg:city":"Redwood City",
    "sg:classifiers":[
        {
            "category":"Manufacturing",
            "subcategory":"Printing",
            "type":"Manufacturing & Wholesale Goods"
        }
    ],
    "sg:phone":"+1 650 620 4100",
    "sg:postcode":"94065",
    "sg:province":"CA",
    "sg:tags":[
        "book",
        "publishing"
    ],
    "wof:name":"Softbook Press Inc",
    "wof:placetype":"venue"
},
  "geometry": {"coordinates":[-122.256377,37.535734],"type":"Point"}
}