{
  "type": "Feature",
  "properties": {
    "iso:country":"US",
    "sg:address":"8610 Cadillac Ave",
    "sg:city":"Los Angeles",
    "sg:classifiers":[
        {
            "category":"Home & Garden",
            "subcategory":"Building Materials",
            "type":"Retail Goods"
        },
        {
            "category":"Building & Trades",
            "subcategory":"Electrical",
            "type":"Services"
        }
    ],
    "sg:phone":"+1 310 559 8324",
    "sg:postcode":"90034",
    "sg:province":"CA",
    "sg:tags":[
        "equipment",
        "lighting",
        "fixture",
        "electrician"
    ],
    "sg:website":"www.powermanelectric.com/",
    "wof:name":"Power-Man Electric",
    "wof:placetype":"venue"
},
  "geometry": {"coordinates":[-118.378452,34.038273],"type":"Point"}
}