{
  "type": "Feature",
  "properties": {
    "iso:country":"US",
    "sg:address":"696 Lincoln Ave",
    "sg:city":"Napa",
    "sg:classifiers":[
        {
            "category":"Home & Garden",
            "subcategory":"Carpets & Floor Coverings",
            "type":"Retail Goods"
        }
    ],
    "sg:phone":"+1 707 253 7888",
    "sg:postcode":"94558",
    "sg:province":"CA",
    "sg:tags":[
        "contractor"
    ],
    "wof:name":"H & H Design",
    "wof:placetype":"venue"
},
  "geometry": {"coordinates":[-122.28212000000001,38.310294],"type":"Point"}
}