{
  "type": "Feature",
  "properties": {
    "iso:country":"US",
    "sg:address":"158 Reina del Mar Ave",
    "sg:city":"Pacifica",
    "sg:classifiers":[
        {
            "category":"Real Estate",
            "subcategory":"Real Estate Services",
            "type":"Services"
        },
        {
            "category":"Real Estate",
            "subcategory":"Surveying",
            "type":"Services"
        },
        {
            "category":"Real Estate",
            "subcategory":"Real Estate Agent",
            "type":"Services"
        }
    ],
    "sg:phone":"+1 650 355 4111",
    "sg:postcode":"94044",
    "sg:province":"CA",
    "sg:tags":[
        "buyer",
        "industrial",
        "appraisers-commercial",
        "broker",
        "appraiser"
    ],
    "wof:name":"George Edsell & Co",
    "wof:placetype":"venue"
},
  "geometry": {"coordinates":[-122.486903,37.613784],"type":"Point"}
}