{
  "type": "Feature",
  "properties": {
    "addr:full":"20 H St San Rafael CA 94901",
    "addr:housenumber":"20",
    "addr:postcode":"94901",
    "addr:street":"H St",
    "iso:country":"US",
    "sg:address":"20 H St",
    "sg:city":"San Rafael",
    "sg:classifiers":[
        {
            "category":"Social Services",
            "type":"Services"
        }
    ],
    "sg:phone":"+1 415 721 7772",
    "sg:postcode":"94901",
    "sg:province":"CA",
    "sg:tags":[
        "organization",
        "welfare"
    ],
    "sg:website":"www.ofiinc.org",
    "wof:name":"Opportunity For Independence",
    "wof:placetype":"venue"
},
  "geometry": {"coordinates":[-122.53840099999999,37.974987],"type":"Point"}
}