{
  "type": "Feature",
  "properties": {
    "iso:country":"US",
    "sg:address":"11008 Downey Ave",
    "sg:city":"Downey",
    "sg:classifiers":[
        {
            "category":"Retail",
            "subcategory":"Repair Shop",
            "type":"Services"
        }
    ],
    "sg:phone":"+1 562 921 0654",
    "sg:postcode":"90241",
    "sg:province":"CA",
    "sg:tags":[
        "machine",
        "washing"
    ],
    "wof:name":"Airflow Appliance Repair",
    "wof:placetype":"venue"
},
  "geometry": {"coordinates":[-118.132322,33.941026],"type":"Point"}
}