{
  "type": "Feature",
  "properties": {
    "iso:country":"US",
    "sg:address":"1053 Cresta Way",
    "sg:city":"San Rafael",
    "sg:classifiers":[
        {
            "category":"Farming",
            "subcategory":"Livestock Farm",
            "type":"Manufacturing & Wholesale Goods"
        }
    ],
    "sg:phone":"+1 415 491 9689",
    "sg:postcode":"94903",
    "sg:province":"CA",
    "sg:tags":[
        "hog",
        "or",
        "feedlot"
    ],
    "wof:name":"Hogs Workspop",
    "wof:placetype":"venue"
},
  "geometry": {"coordinates":[-122.53413,38.02214],"type":"Point"}
}