{
  "type": "Feature",
  "properties": {
    "addr:full":"661 Glendora Ave La Puente CA 91744",
    "addr:housenumber":"661",
    "addr:postcode":"91744",
    "addr:street":"Glendora Ave",
    "iso:country":"US",
    "sg:address":"661 Glendora Ave",
    "sg:city":"La Puente",
    "sg:classifiers":[
        {
            "category":"Shopping",
            "subcategory":"Clothing, Apparel, & Fashions",
            "type":"Retail Goods"
        }
    ],
    "sg:phone":"+1 626 333 0494",
    "sg:postcode":"91744",
    "sg:province":"CA",
    "sg:tags":[
        "alteration"
    ],
    "wof:name":"Nelly's Closet",
    "wof:placetype":"venue"
},
  "geometry": {"coordinates":[-117.950796,34.02858],"type":"Point"}
}