{
  "type": "Feature",
  "properties": {
    "addr:full":"10791 El Gorra Cir Fountain Valley CA 92708",
    "addr:housenumber":"10791",
    "addr:postcode":"92708",
    "addr:street":"El Gorra Cir",
    "iso:country":"US",
    "sg:address":"10791 El Gorra Cir",
    "sg:city":"Fountain Valley",
    "sg:classifiers":[
        {
            "category":"Building & Trades",
            "subcategory":"Construction",
            "type":"Services"
        }
    ],
    "sg:phone":"+1 714 965 0623",
    "sg:postcode":"92708",
    "sg:province":"CA",
    "sg:tags":[
        "painter"
    ],
    "wof:name":"Excel Painting",
    "wof:placetype":"venue"
},
  "geometry": {"coordinates":[-117.941002,33.713799],"type":"Point"}
}