{
  "type": "Feature",
  "properties": {
    "addr:full":"2930 Bristol St. Ste A112 Costa Mesa CA 92626",
    "addr:housenumber":"2930",
    "addr:postcode":"92626",
    "addr:street":"Bristol St. Ste A112 Costa",
    "iso:country":"US",
    "sg:address":"2930 Bristol St. Ste A112",
    "sg:city":"Costa Mesa",
    "sg:classifiers":[
        {
            "category":"Shopping",
            "subcategory":"Optician",
            "type":"Retail Goods"
        }
    ],
    "sg:phone":"+1 714 557 2044",
    "sg:postcode":"92626",
    "sg:province":"CA",
    "sg:tags":[
        "eyewear"
    ],
    "sg:website":"www.eyesocietyonline.com",
    "wof:name":"Eye Society",
    "wof:placetype":"venue"
},
  "geometry": {"coordinates":[-117.88567399999999,33.677513],"type":"Point"}
}