{
  "type": "Feature",
  "properties": {
    "addr:full":"1144 Vineyard Rd Bakersfield CA 93307",
    "addr:housenumber":"1144",
    "addr:postcode":"93307",
    "addr:street":"Vineyard Rd",
    "iso:country":"US",
    "sg:address":"1144 Vineyard Rd",
    "sg:city":"Bakersfield",
    "sg:classifiers":[
        {
            "category":"Retail",
            "subcategory":"Car Wash",
            "type":"Services"
        }
    ],
    "sg:phone":"+1 661 366 0316",
    "sg:postcode":"93307",
    "sg:province":"CA",
    "sg:tags":[
        "truck",
        "cleaning"
    ],
    "wof:name":"Mobile Industrial Truck Wash",
    "wof:placetype":"venue"
},
  "geometry": {"coordinates":[-118.905388,35.344797],"type":"Point"}
}