{
  "type": "Feature",
  "properties": {
    "iso:country":"US",
    "sg:address":"303 Bradford St",
    "sg:city":"Redwood City",
    "sg:classifiers":[
        {
            "category":"Professional",
            "subcategory":"Detective & Security Services",
            "type":"Services"
        }
    ],
    "sg:phone":"+1 650 363 0103",
    "sg:postcode":"94063",
    "sg:province":"CA",
    "sg:tags":[
        "investigator"
    ],
    "wof:name":"Private Eyes",
    "wof:placetype":"venue"
},
  "geometry": {"coordinates":[-122.23141,37.488493],"type":"Point"}
}