{
  "type": "Feature",
  "properties": {
    "iso:country":"US",
    "sg:address":"318 S B St",
    "sg:city":"San Mateo",
    "sg:classifiers":[
        {
            "category":"Utilities",
            "subcategory":"Mobile Phone",
            "type":"Services"
        }
    ],
    "sg:phone":"+1 650 375 0108",
    "sg:postcode":"94401",
    "sg:province":"CA",
    "sg:tags":[
        "telephone",
        "cellular"
    ],
    "wof:name":"Atlas Mobile",
    "wof:placetype":"venue"
},
  "geometry": {"coordinates":[-122.321748,37.564832],"type":"Point"}
}