{
  "type": "Feature",
  "properties": {
    "iso:country":"US",
    "sg:address":"2550 S Garnsey St",
    "sg:city":"Santa Ana",
    "sg:classifiers":[
        {
            "category":"Retail",
            "subcategory":"Auto Repair",
            "type":"Services"
        }
    ],
    "sg:phone":"+1 714 547 6924",
    "sg:postcode":"92707",
    "sg:province":"CA",
    "sg:tags":[
        "wrecker"
    ],
    "wof:name":"A & P Towing",
    "wof:placetype":"venue"
},
  "geometry": {"coordinates":[-117.874812,33.710663],"type":"Point"}
}