{
  "type": "Feature",
  "properties": {
    "addr:full":"8350 Cook Riolo Rd Roseville CA 95747",
    "addr:housenumber":"8350",
    "addr:postcode":"95747",
    "addr:street":"Cook Riolo Rd",
    "iso:country":"US",
    "sg:address":"8350 Cook Riolo Rd",
    "sg:city":"Roseville",
    "sg:classifiers":[
        {
            "category":"Government",
            "subcategory":"Fire Station",
            "type":"Public Place"
        }
    ],
    "sg:phone":"+1 916 771 0107",
    "sg:postcode":"95747",
    "sg:province":"CA",
    "sg:tags":[
        "department"
    ],
    "wof:name":"Dry Creek Fire Department",
    "wof:placetype":"venue"
},
  "geometry": {"coordinates":[-121.337042,38.745023],"type":"Point"}
}