{
  "type": "Feature",
  "properties": {
    "addr:full":"611 Vaqueros Ave Sunnyvale CA 94085",
    "addr:housenumber":"611",
    "addr:postcode":"94085",
    "addr:street":"Vaqueros Ave",
    "iso:country":"US",
    "sg:address":"611 Vaqueros Ave",
    "sg:city":"Sunnyvale",
    "sg:classifiers":[
        {
            "category":"Shopping",
            "subcategory":"Computers & Home Electronics",
            "type":"Retail Goods"
        }
    ],
    "sg:phone":"+1 408 331 8822",
    "sg:postcode":"94085",
    "sg:province":"CA",
    "sg:tags":[
        "theater",
        "consumer",
        "system"
    ],
    "wof:name":"Cirago International Ltd",
    "wof:placetype":"venue"
},
  "geometry": {"coordinates":[-122.03229,37.392736],"type":"Point"}
}