{
  "type": "Feature",
  "properties": {
    "iso:country":"US",
    "sg:address":"2787 Moorpark Ave",
    "sg:city":"San Jose",
    "sg:classifiers":[
        {
            "category":"Wholesale",
            "subcategory":"Non-durable Goods",
            "type":"Manufacturing & Wholesale Goods"
        }
    ],
    "sg:phone":"+1 408 296 8092",
    "sg:postcode":"95128",
    "sg:province":"CA",
    "wof:name":"Nienschanz",
    "wof:placetype":"venue"
},
  "geometry": {"coordinates":[-121.944669,37.316058],"type":"Point"}
}