{
  "type": "Feature",
  "properties": {
    "addr:full":"4001 California Ave Bakersfield CA 93309",
    "addr:housenumber":"4001",
    "addr:postcode":"93309",
    "addr:street":"California Ave",
    "iso:country":"US",
    "sg:address":"4001 California Ave",
    "sg:city":"Bakersfield",
    "sg:classifiers":[
        {
            "category":"Shopping",
            "subcategory":"Books",
            "type":"Retail Goods"
        }
    ],
    "sg:phone":"+1 661 631 2575",
    "sg:postcode":"93309",
    "sg:province":"CA",
    "sg:tags":[
        "dealer"
    ],
    "wof:name":"Barnes & Noble Booksellers",
    "wof:placetype":"venue"
},
  "geometry": {"coordinates":[-119.04524600000001,35.3674],"type":"Point"}
}