{
  "type": "Feature",
  "properties": {
    "addr:full":"12655 Garzoli Ave Mc Farland CA 93250",
    "addr:housenumber":"12655",
    "addr:postcode":"93250",
    "addr:street":"Garzoli Ave Mc Farland",
    "iso:country":"US",
    "sg:address":"12655 Garzoli Ave",
    "sg:city":"Mc Farland",
    "sg:classifiers":[
        {
            "category":"Organizations",
            "subcategory":"Professional Association",
            "type":"Services"
        }
    ],
    "sg:phone":"+1 661 792 2171",
    "sg:postcode":"93250",
    "sg:province":"CA",
    "sg:tags":[
        "farm"
    ],
    "wof:name":"Central Valley Almond Assoc",
    "wof:placetype":"venue"
},
  "geometry": {"coordinates":[-119.24091,35.693958],"type":"Point"}
}