{
  "type": "Feature",
  "properties": {
    "iso:country":"US",
    "sg:address":"4099 Cerrito Ln",
    "sg:city":"Santa Barbara",
    "sg:classifiers":[
        {
            "category":"Organizations",
            "subcategory":"Religious Organization",
            "type":"Services"
        }
    ],
    "sg:phone":"+1 805 687 4319",
    "sg:postcode":"93110",
    "sg:province":"CA",
    "wof:name":"Santa Barbara Jewish Community",
    "wof:placetype":"venue"
},
  "geometry": {"coordinates":[-119.757775,34.4534],"type":"Point"}
}