{
  "type": "Feature",
  "properties": {
    "iso:country":"US",
    "sg:address":"10890 San Pablo Ave",
    "sg:city":"El Cerrito",
    "sg:classifiers":[
        {
            "category":"Government",
            "subcategory":"Office",
            "type":"Public Place"
        }
    ],
    "sg:phone":"+1 510 215 4320",
    "sg:postcode":"94530",
    "sg:province":"CA",
    "sg:tags":[
        "city",
        "planning",
        "dev",
        "village"
    ],
    "sg:website":"www.el-cerrito.org",
    "wof:name":"El Cerrito Community Deveopmen",
    "wof:placetype":"venue"
},
  "geometry": {"coordinates":[-122.311504,37.915634],"type":"Point"}
}