{
  "type": "Feature",
  "properties": {
    "iso:country":"US",
    "sg:address":"9471 Ridgehaven Ct",
    "sg:city":"San Diego",
    "sg:classifiers":[
        {
            "category":"Real Estate",
            "subcategory":"Real Estate Operator",
            "type":"Services"
        }
    ],
    "sg:phone":"+1 858 277 6450",
    "sg:postcode":"92123",
    "sg:province":"CA",
    "sg:tags":[
        "building",
        "management",
        "property",
        "park"
    ],
    "wof:name":"Balboa Business Center",
    "wof:placetype":"venue"
},
  "geometry": {"coordinates":[-117.12599899999999,32.820099],"type":"Point"}
}