{
  "type": "Feature",
  "properties": {
    "addr:full":"1927 Chicago St San Diego CA 92110",
    "addr:housenumber":"1927",
    "addr:postcode":"92110",
    "addr:street":"Chicago St",
    "iso:country":"US",
    "sg:address":"1927 Chicago St",
    "sg:city":"San Diego",
    "sg:classifiers":[
        {
            "category":"Professional",
            "type":"Services"
        }
    ],
    "sg:phone":"+1 619 275 5552",
    "sg:postcode":"92110",
    "sg:province":"CA",
    "wof:name":"Symmetrical Systems",
    "wof:placetype":"venue"
},
  "geometry": {"coordinates":[-117.20607200000001,32.781332],"type":"Point"}
}