{
  "type": "Feature",
  "properties": {
    "addr:full":"2035 Adams Ave San Diego CA 92116",
    "addr:housenumber":"2035",
    "addr:postcode":"92116",
    "addr:street":"Adams Ave",
    "iso:country":"US",
    "sg:address":"2035 Adams Ave",
    "sg:city":"San Diego",
    "sg:classifiers":[
        {
            "category":"Organizations",
            "subcategory":"Religious Organization",
            "type":"Services"
        }
    ],
    "sg:phone":"+1 619 295 2300",
    "sg:postcode":"92116",
    "sg:province":"CA",
    "sg:tags":[
        "church"
    ],
    "wof:name":"Jehovah's Witnesses",
    "wof:placetype":"venue"
},
  "geometry": {"coordinates":[-117.142945,32.762466],"type":"Point"}
}