{
  "type": "Feature",
  "properties": {
    "addr:full":"224 Airport Pkwy Ste 620 San Jose CA 95110",
    "addr:housenumber":"224",
    "addr:postcode":"95110",
    "addr:street":"Airport Pkwy Ste 620",
    "iso:country":"US",
    "sg:address":"224 Airport Pkwy Ste 620",
    "sg:city":"San Jose",
    "sg:classifiers":[
        {
            "category":"Restaurant",
            "type":"Food & Drink"
        }
    ],
    "sg:phone":"+1 408 501 7864",
    "sg:postcode":"95110",
    "sg:province":"CA",
    "sg:tags":[
        "flavor",
        "local"
    ],
    "sg:website":"svturkeytrot.com",
    "wof:name":"Applied Materials Silicon Valley Turkey Trot 2008",
    "wof:placetype":"venue"
},
  "geometry": {"coordinates":[-121.922045,37.369694],"type":"Point"}
}