{
  "type": "Feature",
  "properties": {
    "iso:country":"US",
    "sg:address":"106 W Manchester Ave",
    "sg:city":"Los Angeles",
    "sg:classifiers":[
        {
            "category":"Banks & Credit Unions",
            "subcategory":"Financial Services",
            "type":"Services"
        }
    ],
    "sg:phone":"+1 323 759 7734",
    "sg:postcode":"90003",
    "sg:province":"CA",
    "sg:tags":[
        "broker",
        "mortgage"
    ],
    "wof:name":"Security Investments Inc",
    "wof:placetype":"venue"
},
  "geometry": {"coordinates":[-118.274002,33.960098],"type":"Point"}
}