{
  "type": "Feature",
  "properties": {
    "addr:full":"7996 Old Winding Way Ste 300 Fair Oaks CA 95628",
    "addr:housenumber":"7996",
    "addr:postcode":"95628",
    "addr:street":"Old Winding Way Ste 300",
    "iso:country":"US",
    "sg:address":"7996 Old Winding Way Ste 300",
    "sg:city":"Fair Oaks",
    "sg:classifiers":[
        {
            "category":"Health Services",
            "subcategory":"Clinic",
            "type":"Services"
        }
    ],
    "sg:phone":"+1 916 276 0626",
    "sg:postcode":"95628",
    "sg:province":"CA",
    "sg:tags":[
        "counseling",
        "mental"
    ],
    "sg:website":"www.recoveryhappens.com",
    "wof:name":"Recovery Happens Drug & Alcohol Counseling",
    "wof:placetype":"venue"
},
  "geometry": {"coordinates":[-121.268573,38.644614],"type":"Point"}
}