{
  "type": "Feature",
  "properties": {
    "iso:country":"US",
    "sg:address":"1289 E Valley Blvd",
    "sg:city":"Alhambra",
    "sg:classifiers":[
        {
            "category":"Restaurant",
            "type":"Food & Drink"
        }
    ],
    "sg:phone":"+1 626 282 5589",
    "sg:postcode":"91801",
    "sg:province":"CA",
    "sg:tags":[
        "vietnamese"
    ],
    "sg:website":"www.leesandwiches.com",
    "wof:name":"Lee's Sandwiches",
    "wof:placetype":"venue"
},
  "geometry": {"coordinates":[-118.110001,34.0793],"type":"Point"}
}