{
  "type": "Feature",
  "properties": {
    "addr:full":"6487 Cavalleri Rd Malibu CA 90265",
    "addr:postcode":"6487;90265",
    "addr:street":"Cavalleri Rd",
    "iso:country":"US",
    "sg:address":"6487 Cavalleri Rd",
    "sg:city":"Malibu",
    "sg:classifiers":[
        {
            "category":"Real Estate",
            "subcategory":"Real Estate Operator",
            "type":"Services"
        }
    ],
    "sg:phone":"+1 310 589 2645",
    "sg:postcode":"90265",
    "sg:province":"CA",
    "sg:tags":[
        "apartment"
    ],
    "wof:name":"Malibu Bella Mar Apts",
    "wof:placetype":"venue"
},
  "geometry": {"coordinates":[-118.804607,34.022123],"type":"Point"}
}