{
  "type": "Feature",
  "properties": {
    "addr:full":"444 E Atlee St Stockton CA 95204",
    "addr:housenumber":"444",
    "addr:postcode":"95204",
    "addr:street":"E Atlee St",
    "iso:country":"US",
    "sg:address":"444 E Atlee St",
    "sg:city":"Stockton",
    "sg:classifiers":[
        {
            "category":"Retail",
            "subcategory":"Laundry & Dry Cleaning",
            "type":"Services"
        }
    ],
    "sg:phone":"+1 209 941 9714",
    "sg:postcode":"95204",
    "sg:province":"CA",
    "sg:tags":[
        "cleaner",
        "rug",
        "carpet"
    ],
    "wof:name":"Stockton Carpet Cleaning Co",
    "wof:placetype":"venue"
},
  "geometry": {"coordinates":[-121.296634,37.985634],"type":"Point"}
}