{
  "type": "Feature",
  "properties": {
    "iso:country":"US",
    "sg:address":"4045 Cirrus St",
    "sg:city":"Redding",
    "sg:classifiers":[
        {
            "category":"Building & Trades",
            "subcategory":"Landscaping Services",
            "type":"Services"
        }
    ],
    "sg:phone":"+1 530 221 9485",
    "sg:postcode":"96002",
    "sg:province":"CA",
    "sg:tags":[
        "landscape"
    ],
    "wof:name":"Heaven On Earth Landscape",
    "wof:placetype":"venue"
},
  "geometry": {"coordinates":[-122.335763,40.551148],"type":"Point"}
}