{
  "type": "Feature",
  "properties": {
    "iso:country":"US",
    "sg:address":"1501 W Rosecrans Avenue",
    "sg:city":"Gardena",
    "sg:classifiers":[
        {
            "category":"Retail",
            "subcategory":"Auto Repair",
            "type":"Services"
        }
    ],
    "sg:phone":"+1 310 532 8803",
    "sg:postcode":"90249",
    "sg:province":"CA",
    "wof:name":"Blue Sky Auto Repair",
    "wof:placetype":"venue"
},
  "geometry": {"coordinates":[-118.302685,33.901792],"type":"Point"}
}