{
  "type": "Feature",
  "properties": {
    "addr:full":"144 24th Ave San Mateo CA 94403",
    "addr:housenumber":"144",
    "addr:postcode":"94403",
    "addr:street":"24Th Ave",
    "iso:country":"US",
    "sg:address":"144 24th Ave",
    "sg:city":"San Mateo",
    "sg:classifiers":[
        {
            "category":"Manufacturing",
            "subcategory":"Tools & Machinery",
            "type":"Manufacturing & Wholesale Goods"
        }
    ],
    "sg:phone":"+1 650 345 1140",
    "sg:postcode":"94403",
    "sg:province":"CA",
    "sg:tags":[
        "recording",
        "medium",
        "mfg"
    ],
    "wof:name":"Zamples Inc",
    "wof:placetype":"venue"
},
  "geometry": {"coordinates":[-122.308716,37.544346],"type":"Point"}
}