{
  "type": "Feature",
  "properties": {
    "addr:full":"10902 I Ave Hesperia CA 92345",
    "addr:housenumber":"10902",
    "addr:postcode":"92345",
    "addr:street":"I Ave",
    "iso:country":"US",
    "sg:address":"10902 I Ave",
    "sg:city":"Hesperia",
    "sg:classifiers":[
        {
            "category":"Retail",
            "subcategory":"Repair Shop",
            "type":"Services"
        }
    ],
    "sg:phone":"+1 760 244 7750",
    "sg:postcode":"92345",
    "sg:province":"CA",
    "sg:tags":[
        "scooter",
        "motorcycle",
        "motor"
    ],
    "wof:name":"Stallone's Motorcycles",
    "wof:placetype":"venue"
},
  "geometry": {"coordinates":[-117.277202,34.450755],"type":"Point"}
}