{
  "type": "Feature",
  "properties": {
    "addr:full":"2119 Schmidt Rd Gustine CA 95322",
    "addr:housenumber":"2119",
    "addr:postcode":"95322",
    "addr:street":"Schmidt Rd",
    "iso:country":"US",
    "sg:address":"2119 Schmidt Rd",
    "sg:city":"Gustine",
    "sg:classifiers":[
        {
            "category":"Farming",
            "subcategory":"Poultry Farm",
            "type":"Manufacturing & Wholesale Goods"
        }
    ],
    "sg:phone":"+1 209 854 2746",
    "sg:postcode":"95322",
    "sg:province":"CA",
    "sg:tags":[
        "chicken",
        "egg"
    ],
    "wof:name":"Richard Dabney",
    "wof:placetype":"venue"
},
  "geometry": {"coordinates":[-121.04922000000001,37.258459],"type":"Point"}
}