{
  "type": "Feature",
  "properties": {
    "iso:country":"US",
    "sg:address":"613 W Valley Pkwy",
    "sg:city":"Escondido",
    "sg:classifiers":[
        {
            "category":"Professional",
            "subcategory":"Lawyer & Legal Services",
            "type":"Services"
        }
    ],
    "sg:phone":"+1 760 741 7544",
    "sg:postcode":"92025",
    "sg:province":"CA",
    "sg:tags":[
        "attorney"
    ],
    "wof:name":"Laturno & Graves",
    "wof:placetype":"venue"
},
  "geometry": {"coordinates":[-117.09039799999999,33.118374],"type":"Point"}
}