{
  "type": "Feature",
  "properties": {
    "addr:full":"1142 S Main St Manteca CA 95337",
    "addr:housenumber":"1142",
    "addr:postcode":"95337",
    "addr:street":"S Main St",
    "iso:country":"US",
    "sg:address":"1142 S Main St",
    "sg:city":"Manteca",
    "sg:classifiers":[
        {
            "category":"Banks & Credit Unions",
            "subcategory":"Bank",
            "type":"Services"
        }
    ],
    "sg:phone":"+1 209 239 7800",
    "sg:postcode":"95337",
    "sg:province":"CA",
    "sg:tags":[
        "cashing",
        "check"
    ],
    "wof:name":"Check 'n Go",
    "wof:placetype":"venue"
},
  "geometry": {"coordinates":[-121.215749,37.786827],"type":"Point"}
}