{
  "type": "Feature",
  "properties": {
    "addr:full":"2345 Calumet St Carmichael CA 95608",
    "addr:housenumber":"2345",
    "addr:postcode":"95608",
    "addr:street":"Calumet St",
    "iso:country":"US",
    "sg:address":"2345 Calumet St",
    "sg:city":"Carmichael",
    "sg:classifiers":[
        {
            "category":"Professional",
            "subcategory":"Business Services",
            "type":"Services"
        }
    ],
    "sg:phone":"+1 916 359 2988",
    "sg:postcode":"95608",
    "sg:province":"CA",
    "sg:tags":[
        "consultant",
        "coach"
    ],
    "wof:name":"Bill Dunning Consultant",
    "wof:placetype":"venue"
},
  "geometry": {"coordinates":[-121.33967699999999,38.607864],"type":"Point"}
}