{
  "type": "Feature",
  "properties": {
    "iso:country":"US",
    "sg:address":"10953 Meridian Dr",
    "sg:city":"Cypress",
    "sg:classifiers":[
        {
            "category":"Personal",
            "subcategory":"Beauty Salon",
            "type":"Services"
        }
    ],
    "sg:phone":"+1 714 995 8203",
    "sg:postcode":"90630",
    "sg:province":"CA",
    "wof:name":"Club Nails & Hair",
    "wof:placetype":"venue"
},
  "geometry": {"coordinates":[-118.014406,33.803684],"type":"Point"}
}