{
  "type": "Feature",
  "properties": {
    "iso:country":"US",
    "sg:address":"36046 Jefferson Blvd",
    "sg:city":"Clarksburg",
    "sg:classifiers":[
        {
            "category":"Coffee & Tea",
            "type":"Food & Drink"
        },
        {
            "category":"Restaurant",
            "type":"Food & Drink"
        }
    ],
    "sg:phone":"+1 916 744 1346",
    "sg:postcode":"95612",
    "sg:province":"CA",
    "sg:tags":[
        "mexican",
        "espresso"
    ],
    "wof:name":"La Amistad",
    "wof:placetype":"venue"
},
  "geometry": {"coordinates":[-121.582846,38.413353],"type":"Point"}
}