{
  "type": "Feature",
  "properties": {
    "iso:country":"US",
    "sg:address":"3619 Midway Dr",
    "sg:city":"San Diego",
    "sg:classifiers":[
        {
            "category":"Cinema",
            "subcategory":"Movie Rental",
            "type":"Entertainment"
        }
    ],
    "sg:phone":"+1 619 224 2548",
    "sg:postcode":"92110",
    "sg:province":"CA",
    "sg:tags":[
        "game",
        "video"
    ],
    "sg:website":"www.ebgames.com",
    "wof:name":"EB Games",
    "wof:placetype":"venue"
},
  "geometry": {"coordinates":[-117.215386,32.752284],"type":"Point"}
}