{
  "type": "Feature",
  "properties": {
    "iso:country":"US",
    "sg:address":"477 Arlington St",
    "sg:city":"San Francisco",
    "sg:classifiers":[
        {
            "category":"Professional",
            "type":"Services"
        }
    ],
    "sg:phone":"+1 415 587 9264",
    "sg:postcode":"94131",
    "sg:province":"CA",
    "wof:name":"Kay Daya Comms",
    "wof:placetype":"venue"
},
  "geometry": {"coordinates":[-122.429305,37.735253],"type":"Point"}
}