{
  "type": "Feature",
  "properties": {
    "addr:full":"482 E Las Flores Dr Altadena CA 91001",
    "addr:housenumber":"482",
    "addr:postcode":"91001",
    "addr:street":"E Las Flores Dr",
    "iso:country":"US",
    "sg:address":"482 E Las Flores Dr",
    "sg:city":"Altadena",
    "sg:classifiers":[
        {
            "category":"Professional",
            "subcategory":"Business Services",
            "type":"Services"
        }
    ],
    "sg:phone":"+1 626 791 9735",
    "sg:postcode":"91001",
    "sg:province":"CA",
    "sg:tags":[
        "interior",
        "designer"
    ],
    "wof:name":"Alosta Design Center",
    "wof:placetype":"venue"
},
  "geometry": {"coordinates":[-118.137565,34.197017],"type":"Point"}
}