{
  "type": "Feature",
  "properties": {
    "iso:country":"US",
    "sg:address":"609 Deep Valley Dr",
    "sg:city":"Rolling Hls Ests",
    "sg:classifiers":[
        {
            "category":"Professional",
            "type":"Services"
        }
    ],
    "sg:phone":"+1 310 265 4437",
    "sg:postcode":"90274",
    "sg:province":"CA",
    "sg:tags":[
        "establishment"
    ],
    "wof:name":"Single Parents Alliance",
    "wof:placetype":"venue"
},
  "geometry": {"coordinates":[-118.36882300000001,33.769497],"type":"Point"}
}