{
  "type": "Feature",
  "properties": {
    "addr:full":"11448 Antigua Dr Mira Loma CA 91752",
    "addr:housenumber":"11448",
    "addr:postcode":"91752",
    "addr:street":"Antigua Dr",
    "iso:country":"US",
    "sg:address":"11448 Antigua Dr",
    "sg:city":"Mira Loma",
    "sg:classifiers":[
        {
            "category":"Manufacturing",
            "subcategory":"Printing",
            "type":"Manufacturing & Wholesale Goods"
        }
    ],
    "sg:phone":"+1 951 685 1705",
    "sg:postcode":"91752",
    "sg:province":"CA",
    "sg:tags":[
        "commercial"
    ],
    "wof:name":"Gotta Look Sharp",
    "wof:placetype":"venue"
},
  "geometry": {"coordinates":[-117.53348800000001,33.99544],"type":"Point"}
}