{
  "type": "Feature",
  "properties": {
    "iso:country":"US",
    "sg:address":"167 W Orangethorpe Ave",
    "sg:city":"Placentia",
    "sg:classifiers":[
        {
            "category":"Manufacturing",
            "subcategory":"Tools & Machinery",
            "type":"Manufacturing & Wholesale Goods"
        }
    ],
    "sg:phone":"+1 714 528 4695",
    "sg:postcode":"92870",
    "sg:province":"CA",
    "sg:tags":[
        "instrument",
        "surgical"
    ],
    "sg:website":"www.biosealnet.net",
    "wof:name":"Bioseal Medical Packaging",
    "wof:placetype":"venue"
},
  "geometry": {"coordinates":[-117.874703,33.861945],"type":"Point"}
}