{
  "type": "Feature",
  "properties": {
    "addr:full":"40548 Brisa Dr Palmdale CA 93551",
    "addr:postcode":"40548;ca 93551",
    "addr:street":"Brisa Dr",
    "iso:country":"US",
    "sg:address":"40548 Brisa Dr",
    "sg:city":"Palmdale",
    "sg:classifiers":[
        {
            "category":"Shopping",
            "subcategory":"Party Supplies",
            "type":"Retail Goods"
        }
    ],
    "sg:phone":"+1 661 949 8883",
    "sg:postcode":"93551",
    "sg:province":"CA",
    "sg:tags":[
        "decoration",
        "rental"
    ],
    "wof:name":"Special Flair Party",
    "wof:placetype":"venue"
},
  "geometry": {"coordinates":[-118.217758,34.618408],"type":"Point"}
}