{
  "type": "Feature",
  "properties": {
    "addr:full":"1134 Villa Calimesa, Calimesa CA 92320",
    "addr:housenumber":"1134",
    "addr:postcode":"92320",
    "addr:street":"Villa Calimesa",
    "iso:country":"US",
    "sg:address":"1134 Villa Calimesa,",
    "sg:city":"Calimesa",
    "sg:classifiers":[
        {
            "category":"Professional",
            "type":"Services"
        },
        {
            "category":"Personal",
            "subcategory":"Psychics & Astrologers",
            "type":"Services"
        },
        {
            "category":"Social Services",
            "subcategory":"Job Training",
            "type":"Services"
        }
    ],
    "sg:phone":"+1 707 888 8098",
    "sg:postcode":"92320",
    "sg:province":"CA",
    "sg:tags":[
        "career",
        "counseling"
    ],
    "sg:website":"www.modernmystical.com",
    "wof:name":"Modern Mystical",
    "wof:placetype":"venue"
},
  "geometry": {"coordinates":[-117.065899,33.995638],"type":"Point"}
}