{
  "type": "Feature",
  "properties": {
    "addr:full":"207 W Los Angeles Ave Moorpark CA 93021",
    "addr:housenumber":"207",
    "addr:postcode":"ca 93021",
    "addr:street":"W Los Angeles Ave",
    "iso:country":"US",
    "sg:address":"207 W Los Angeles Ave",
    "sg:city":"Moorpark",
    "sg:classifiers":[
        {
            "category":"Professional",
            "subcategory":"Accounting & Tax Preparation",
            "type":"Services"
        }
    ],
    "sg:phone":"+1 805 578 8590",
    "sg:postcode":"93021",
    "sg:province":"CA",
    "sg:tags":[
        "payroll"
    ],
    "wof:name":"Open Computing Platforms",
    "wof:placetype":"venue"
},
  "geometry": {"coordinates":[-118.80735900000001,34.2859],"type":"Point"}
}