{
  "type": "Feature",
  "properties": {
    "iso:country":"US",
    "sg:address":"3317 Julliard Dr",
    "sg:city":"Sacramento",
    "sg:classifiers":[
        {
            "category":"Retail",
            "subcategory":"Auto Rental",
            "type":"Services"
        }
    ],
    "sg:phone":"+1 916 381 6242",
    "sg:postcode":"95826",
    "sg:province":"CA",
    "sg:tags":[
        "renting",
        "truck",
        "leasing"
    ],
    "wof:name":"U-Haul Co",
    "wof:placetype":"venue"
},
  "geometry": {"coordinates":[-121.392296,38.547634],"type":"Point"}
}