{
  "type": "Feature",
  "properties": {
    "addr:full":"2307 Harnage St Lake Isabella CA 93240",
    "addr:housenumber":"2307",
    "addr:postcode":"93240",
    "addr:street":"Harnage St",
    "iso:country":"US",
    "sg:address":"2307 Harnage St",
    "sg:city":"Lake Isabella",
    "sg:classifiers":[
        {
            "category":"Shopping",
            "type":"Retail Goods"
        }
    ],
    "sg:phone":"+1 760 379 4307",
    "sg:postcode":"93240",
    "sg:province":"CA",
    "sg:tags":[
        "equipment",
        "supply"
    ],
    "wof:name":"R & R Carnation",
    "wof:placetype":"venue"
},
  "geometry": {"coordinates":[-118.48940399999999,35.605305],"type":"Point"}
}