{
  "type": "Feature",
  "properties": {
    "addr:full":"2175 S El Camino Real San Mateo CA 94403",
    "addr:housenumber":"2175",
    "addr:postcode":"94403",
    "addr:street":"S El Camino Real",
    "iso:country":"US",
    "sg:address":"2175 S El Camino Real",
    "sg:city":"San Mateo",
    "sg:classifiers":[
        {
            "category":"Travel",
            "subcategory":"Hotels & Motels",
            "type":"Entertainment"
        }
    ],
    "sg:phone":"+1 650 458 6556",
    "sg:postcode":"94403",
    "sg:province":"CA",
    "wof:name":"Firestone Lodge",
    "wof:placetype":"venue"
},
  "geometry": {"coordinates":[-122.308998,37.547501],"type":"Point"}
}