{
  "type": "Feature",
  "properties": {
    "addr:full":"10130 Redwood Ave Fontana CA 92335",
    "addr:housenumber":"10130",
    "addr:postcode":"92335",
    "addr:street":"Redwood Ave",
    "iso:country":"US",
    "sg:address":"10130 Redwood Ave",
    "sg:city":"Fontana",
    "sg:classifiers":[
        {
            "category":"Building & Trades",
            "subcategory":"Construction",
            "type":"Services"
        }
    ],
    "sg:phone":"+1 909 355 0125",
    "sg:postcode":"92335",
    "sg:province":"CA",
    "sg:tags":[
        "resurfacing",
        "laying",
        "refinishing",
        "floor"
    ],
    "wof:name":"Donald M Hoover Co",
    "wof:placetype":"venue"
},
  "geometry": {"coordinates":[-117.48438400000001,34.067571],"type":"Point"}
}