{
  "type": "Feature",
  "properties": {
    "addr:full":"57 Johnson Rd Watsonville CA 95076",
    "addr:housenumber":"57",
    "addr:postcode":"95076",
    "addr:street":"Johnson Rd",
    "iso:country":"US",
    "sg:address":"57 Johnson Rd",
    "sg:city":"Watsonville",
    "sg:classifiers":[
        {
            "category":"Farming",
            "subcategory":"Farm",
            "type":"Manufacturing & Wholesale Goods"
        }
    ],
    "sg:phone":"+1 831 728 4964",
    "sg:postcode":"95076",
    "sg:province":"CA",
    "sg:tags":[
        "crop",
        "general"
    ],
    "wof:name":"Medina Farms",
    "wof:placetype":"venue"
},
  "geometry": {"coordinates":[-121.707566,36.858261],"type":"Point"}
}