{
  "type": "Feature",
  "properties": {
    "addr:full":"1825 Ebers St San Diego CA 92107",
    "addr:housenumber":"1825",
    "addr:postcode":"92107",
    "addr:street":"Ebers St",
    "iso:country":"US",
    "sg:address":"1825 Ebers St",
    "sg:city":"San Diego",
    "sg:classifiers":[
        {
            "category":"Personal",
            "type":"Services"
        }
    ],
    "sg:phone":"+1 619 224 4556",
    "sg:postcode":"92107",
    "sg:province":"CA",
    "sg:tags":[
        "therapist",
        "massage"
    ],
    "wof:name":"San Diego Sports Massage Team",
    "wof:placetype":"venue"
},
  "geometry": {"coordinates":[-117.247305,32.741971],"type":"Point"}
}