{
  "type": "Feature",
  "properties": {
    "iso:country":"US",
    "sg:address":"4255 Campus Drive",
    "sg:city":"Irvine",
    "sg:classifiers":[
        {
            "category":"Health Services",
            "subcategory":"Dentist",
            "type":"Services"
        }
    ],
    "sg:phone":"+1 949 856 0594",
    "sg:postcode":"92612",
    "sg:province":"CA",
    "wof:name":"Phillips Gary B DDS",
    "wof:placetype":"venue"
},
  "geometry": {"coordinates":[-117.838875,33.648726],"type":"Point"}
}