{
  "type": "Feature",
  "properties": {
    "addr:full":"357 Grand Ave Oakland CA 94610",
    "addr:housenumber":"357",
    "addr:postcode":"94610",
    "addr:street":"Grand Ave",
    "iso:country":"US",
    "sg:address":"357 Grand Ave",
    "sg:city":"Oakland",
    "sg:classifiers":[
        {
            "category":"Shopping",
            "subcategory":"Used Merchandise",
            "type":"Retail Goods"
        }
    ],
    "sg:phone":"+1 510 835 4341",
    "sg:postcode":"94610",
    "sg:province":"CA",
    "sg:tags":[
        "shop",
        "consignment"
    ],
    "wof:name":"Many Hands Many Lands",
    "wof:placetype":"venue"
},
  "geometry": {"coordinates":[-122.25541200000001,37.808876],"type":"Point"}
}