{
  "type": "Feature",
  "properties": {
    "addr:full":"11815 165th St Norwalk CA 90650",
    "addr:housenumber":"11815",
    "addr:postcode":"90650",
    "addr:street":"165Th St",
    "iso:country":"US",
    "sg:address":"11815 165th St",
    "sg:city":"Norwalk",
    "sg:classifiers":[
        {
            "category":"Home & Garden",
            "subcategory":"Carpets & Floor Coverings",
            "type":"Retail Goods"
        }
    ],
    "sg:phone":"+1 562 926 5599",
    "sg:postcode":"90650",
    "sg:province":"CA",
    "sg:tags":[
        "carpeting"
    ],
    "wof:name":"Taimay Carpets",
    "wof:placetype":"venue"
},
  "geometry": {"coordinates":[-118.08200100000001,33.8811],"type":"Point"}
}