{
  "type": "Feature",
  "properties": {
    "iso:country":"US",
    "sg:address":"1910 Lincoln Blvd",
    "sg:city":"Santa Monica",
    "sg:classifiers":[
        {
            "category":"Shopping",
            "subcategory":"Computers & Home Electronics",
            "type":"Retail Goods"
        }
    ],
    "sg:phone":"+1 310 399 5444",
    "sg:postcode":"90405",
    "sg:province":"CA",
    "sg:tags":[
        "software"
    ],
    "wof:name":"Electronics Boutique",
    "wof:placetype":"venue"
},
  "geometry": {"coordinates":[-118.482275,34.011655],"type":"Point"}
}