{
  "type": "Feature",
  "properties": {
    "addr:full":"7660 14th Ave Sacramento CA 95820",
    "addr:housenumber":"7660",
    "addr:postcode":"95820",
    "addr:street":"14Th Ave",
    "iso:country":"US",
    "sg:address":"7660 14th Ave",
    "sg:city":"Sacramento",
    "sg:classifiers":[
        {
            "category":"Retail",
            "subcategory":"Auto Repair",
            "type":"Services"
        }
    ],
    "sg:phone":"+1 916 452 6700",
    "sg:postcode":"95820",
    "sg:province":"CA",
    "sg:tags":[
        "wrecker"
    ],
    "wof:name":"Extreme Auto Recovery Inc",
    "wof:placetype":"venue"
},
  "geometry": {"coordinates":[-121.417385,38.539529],"type":"Point"}
}