{
  "type": "Feature",
  "properties": {
    "iso:country":"US",
    "sg:address":"1135 W Chateau Ave",
    "sg:city":"Anaheim",
    "sg:classifiers":[
        {
            "category":"Banks & Credit Unions",
            "subcategory":"Investment Brokerage",
            "type":"Services"
        }
    ],
    "sg:phone":"+1 714 563 1438",
    "sg:postcode":"92802",
    "sg:province":"CA",
    "sg:tags":[
        "advisory"
    ],
    "wof:name":"Prize America Financial Svc",
    "wof:placetype":"venue"
},
  "geometry": {"coordinates":[-117.92526700000001,33.82193],"type":"Point"}
}