{
  "type": "Feature",
  "properties": {
    "addr:full":"2401 N Ashley Way Fresno CA 93727",
    "addr:housenumber":"2401",
    "addr:postcode":"93727",
    "addr:street":"N Ashley Way",
    "iso:country":"US",
    "sg:address":"2401 N Ashley Way",
    "sg:city":"Fresno",
    "sg:classifiers":[
        {
            "category":"Airline",
            "type":"Transportation"
        }
    ],
    "sg:phone":"+1 559 621 4500",
    "sg:postcode":"93727",
    "sg:province":"CA",
    "sg:tags":[
        "airport"
    ],
    "sg:website":"http://www.fresno.com/flyfresno/fyihome.htm",
    "wof:name":"FAT - Fresno Yosemite International Airport",
    "wof:placetype":"venue"
},
  "geometry": {"coordinates":[-119.722672,36.771412],"type":"Point"}
}