{
  "type": "Feature",
  "properties": {
    "addr:full":"17451 N Tretheway Rd Lockeford CA 95237",
    "addr:housenumber":"17451",
    "addr:postcode":"95237",
    "addr:street":"N Tretheway Rd",
    "iso:country":"US",
    "sg:address":"17451 N Tretheway Rd",
    "sg:city":"Lockeford",
    "sg:classifiers":[
        {
            "category":"Retail",
            "subcategory":"Auto Repair",
            "type":"Services"
        }
    ],
    "sg:phone":"+1 209 369 9315",
    "sg:postcode":"95237",
    "sg:province":"CA",
    "sg:tags":[
        "repairing",
        "automobile"
    ],
    "wof:name":"Joe's House Of Tone Automotive",
    "wof:placetype":"venue"
},
  "geometry": {"coordinates":[-121.178369,38.145421],"type":"Point"}
}