{
  "type": "Feature",
  "properties": {
    "iso:country":"US",
    "sg:address":"4935 McConnell Ave",
    "sg:city":"Los Angeles",
    "sg:classifiers":[
        {
            "category":"Professional",
            "subcategory":"Art Services",
            "type":"Services"
        }
    ],
    "sg:phone":"+1 310 306 7574",
    "sg:postcode":"90066",
    "sg:province":"CA",
    "sg:tags":[
        "photographer"
    ],
    "wof:name":"Kodama & Moriarty Photography",
    "wof:placetype":"venue"
},
  "geometry": {"coordinates":[-118.424489,33.984469],"type":"Point"}
}