{
  "type": "Feature",
  "properties": {
    "iso:country":"US",
    "sg:address":"300 12th St",
    "sg:city":"Oakland",
    "sg:classifiers":[
        {
            "category":"Health Services",
            "subcategory":"Doctor",
            "type":"Services"
        }
    ],
    "sg:phone":"+1 510 444 4808",
    "sg:postcode":"94607",
    "sg:province":"CA",
    "sg:tags":[
        "surgeon",
        "oral"
    ],
    "wof:name":"Pham Dung DDS",
    "wof:placetype":"venue"
},
  "geometry": {"coordinates":[-122.268997,37.801701],"type":"Point"}
}