{
  "type": "Feature",
  "properties": {
    "addr:full":"3530 Portola Dr Santa Cruz CA 95062",
    "addr:housenumber":"3530",
    "addr:postcode":"95062",
    "addr:street":"Portola Dr",
    "iso:country":"US",
    "sg:address":"3530 Portola Dr",
    "sg:city":"Santa Cruz",
    "sg:classifiers":[
        {
            "category":"Bars & Pubs",
            "type":"Food & Drink"
        }
    ],
    "sg:phone":"+1 831 476 3679",
    "sg:postcode":"95062",
    "sg:province":"CA",
    "sg:tags":[
        "nightlife"
    ],
    "wof:name":"Over the Hill Gang Saloon",
    "wof:placetype":"venue"
},
  "geometry": {"coordinates":[-121.970001,36.963299],"type":"Point"}
}