{
  "type": "Feature",
  "properties": {
    "addr:full":"9355 Hearst Dr San Simeon CA 93452",
    "addr:housenumber":"9355",
    "addr:postcode":"93452",
    "addr:street":"Hearst Dr",
    "iso:country":"US",
    "sg:address":"9355 Hearst Dr",
    "sg:city":"San Simeon",
    "sg:classifiers":[
        {
            "category":"Travel",
            "subcategory":"Hotels & Motels",
            "type":"Entertainment"
        }
    ],
    "sg:phone":"+1 805 927 3243",
    "sg:postcode":"93452",
    "sg:province":"CA",
    "wof:name":"Sands Motel San Simeon",
    "wof:placetype":"venue"
},
  "geometry": {"coordinates":[-121.143997,35.617802],"type":"Point"}
}