{
  "type": "Feature",
  "properties": {
    "addr:full":"210 Main St Weed CA 96094",
    "addr:housenumber":"210",
    "addr:postcode":"96094",
    "addr:street":"Main St",
    "iso:country":"US",
    "sg:address":"210 Main St",
    "sg:city":"Weed",
    "sg:classifiers":[
        {
            "category":"Home & Garden",
            "subcategory":"Hardware",
            "type":"Retail Goods"
        }
    ],
    "sg:phone":"+1 530 938 3056",
    "sg:postcode":"96094",
    "sg:province":"CA",
    "wof:name":"D & R True Value Hardware",
    "wof:placetype":"venue"
},
  "geometry": {"coordinates":[-122.384361,41.424066],"type":"Point"}
}