{
  "type": "Feature",
  "properties": {
    "iso:country":"US",
    "sg:address":"650 S Grand Ave",
    "sg:city":"Los Angeles",
    "sg:classifiers":[
        {
            "category":"Professional",
            "subcategory":"Printing & Photocopies",
            "type":"Services"
        }
    ],
    "sg:phone":"+1 213 271 1514",
    "sg:postcode":"90017",
    "sg:province":"CA",
    "sg:tags":[
        "duplicating",
        "copying"
    ],
    "wof:name":"E Copy Svc",
    "wof:placetype":"venue"
},
  "geometry": {"coordinates":[-118.256405,34.047415],"type":"Point"}
}