{
  "type": "Feature",
  "properties": {
    "addr:full":"913 Oakland Hills Dr Banning CA 92220",
    "addr:housenumber":"913",
    "addr:postcode":"92220",
    "addr:street":"Oakland Hills Dr",
    "iso:country":"US",
    "sg:address":"913 Oakland Hills Dr",
    "sg:city":"Banning",
    "sg:classifiers":[
        {
            "category":"Building & Trades",
            "subcategory":"Construction",
            "type":"Services"
        },
        {
            "category":"Wholesale",
            "subcategory":"Home Furnishings",
            "type":"Manufacturing & Wholesale Goods"
        }
    ],
    "sg:phone":"+1 951 845 3191",
    "sg:postcode":"92220",
    "sg:province":"CA",
    "sg:tags":[
        "radiators-heating",
        "supply",
        "fixture",
        "sales",
        "part",
        "plumbing",
        "supplies-wholesale",
        "manufacturer"
    ],
    "wof:name":"Barnes, Jim Plumbing Supplies",
    "wof:placetype":"venue"
},
  "geometry": {"coordinates":[-116.93548199999999,33.916421],"type":"Point"}
}