{
  "type": "Feature",
  "properties": {
    "iso:country":"US",
    "sg:address":"9110 Dice Rd",
    "sg:city":"Santa Fe Springs",
    "sg:classifiers":[
        {
            "category":"Retail",
            "subcategory":"Auto Repair",
            "type":"Services"
        }
    ],
    "sg:phone":"+1 562 941 6131",
    "sg:postcode":"90670",
    "sg:province":"CA",
    "wof:name":"Tin Shed Machine Shop and Antique Auto Repair",
    "wof:placetype":"venue"
},
  "geometry": {"coordinates":[-118.066329,33.955869],"type":"Point"}
}