{
  "type": "Feature",
  "properties": {
    "addr:full":"1430 Fruitdale Ave San Jose CA 95128",
    "addr:housenumber":"1430",
    "addr:postcode":"95128",
    "addr:street":"Fruitdale Ave",
    "iso:country":"US",
    "sg:address":"1430 Fruitdale Ave",
    "sg:city":"San Jose",
    "sg:classifiers":[
        {
            "category":"Food & Beverages",
            "subcategory":"Groceries & Convenience Stores",
            "type":"Retail Goods"
        }
    ],
    "sg:phone":"+1 408 294 4916",
    "sg:postcode":"95128",
    "sg:province":"CA",
    "wof:name":"7-Eleven",
    "wof:placetype":"venue"
},
  "geometry": {"coordinates":[-121.915689,37.310562],"type":"Point"}
}