{
  "type": "Feature",
  "properties": {
    "iso:country":"US",
    "sg:address":"21880 Hawthorne Blvd",
    "sg:city":"Torrance",
    "sg:classifiers":[
        {
            "category":"Restaurant",
            "type":"Food & Drink"
        }
    ],
    "sg:menulink":"http://www.allmenus.com/ca/torrance/233393-pretzel-maker/menu/",
    "sg:phone":"+1 310 214 1032",
    "sg:postcode":"90503",
    "sg:province":"CA",
    "sg:tags":[
        "new",
        "american"
    ],
    "wof:name":"Pretzel Maker",
    "wof:placetype":"venue"
},
  "geometry": {"coordinates":[-118.3518,33.827428],"type":"Point"}
}