{
  "type": "Feature",
  "properties": {
    "iso:country":"US",
    "sg:address":"140 E Hillcrest Dr",
    "sg:city":"Thousand Oaks",
    "sg:classifiers":[
        {
            "category":"Restaurant",
            "type":"Food & Drink"
        }
    ],
    "sg:phone":"+1 805 496 9102",
    "sg:postcode":"91360",
    "sg:province":"CA",
    "wof:name":"Yomama",
    "wof:placetype":"venue"
},
  "geometry": {"coordinates":[-118.875209,34.181126],"type":"Point"}
}