{
  "type": "Feature",
  "properties": {
    "addr:full":"309 Washington St Coalinga CA 93210",
    "addr:housenumber":"309",
    "addr:postcode":"93210",
    "addr:street":"Washington St",
    "iso:country":"US",
    "sg:address":"309 Washington St",
    "sg:city":"Coalinga",
    "sg:classifiers":[
        {
            "category":"Recreation",
            "type":"Entertainment"
        }
    ],
    "sg:phone":"+1 559 707 2123",
    "sg:postcode":"93210",
    "sg:province":"CA",
    "sg:tags":[
        "entertainers-family",
        "business"
    ],
    "wof:name":"Dagoof Group Entertainment",
    "wof:placetype":"venue"
},
  "geometry": {"coordinates":[-120.36723600000001,36.143768],"type":"Point"}
}