{
  "type": "Feature",
  "properties": {
    "addr:full":"1739 S Euclid Ave Ontario CA 91762",
    "addr:housenumber":"1739",
    "addr:postcode":"91762",
    "addr:street":"S Euclid Ave",
    "iso:country":"US",
    "sg:address":"1739 S Euclid Ave",
    "sg:city":"Ontario",
    "sg:classifiers":[
        {
            "category":"Personal",
            "type":"Services"
        }
    ],
    "sg:phone":"+1 909 391 0203",
    "sg:postcode":"91762",
    "sg:province":"CA",
    "sg:tags":[
        "control",
        "weight"
    ],
    "wof:name":"Herbalife Independent Dist",
    "wof:placetype":"venue"
},
  "geometry": {"coordinates":[-117.650826,34.041217],"type":"Point"}
}