{
  "type": "Feature",
  "properties": {
    "iso:country":"US",
    "sg:address":"8802 Dunbar St",
    "sg:city":"Bellflower",
    "sg:classifiers":[
        {
            "category":"Building & Trades",
            "subcategory":"Landscaping Services",
            "type":"Services"
        }
    ],
    "sg:phone":"+1 562 531 6079",
    "sg:postcode":"90706",
    "sg:province":"CA",
    "sg:tags":[
        "landscape"
    ],
    "wof:name":"Torres Landscaping",
    "wof:placetype":"venue"
},
  "geometry": {"coordinates":[-118.143114,33.887372],"type":"Point"}
}