{
  "type": "Feature",
  "properties": {
    "addr:full":"22720 Ventura Blvd Woodland Hills CA 91364",
    "addr:housenumber":"22720",
    "addr:postcode":"91364",
    "addr:street":"Ventura Blvd",
    "iso:country":"US",
    "sg:address":"22720 Ventura Blvd",
    "sg:city":"Woodland Hills",
    "sg:classifiers":[
        {
            "category":"Retail",
            "subcategory":"Veterinary Services",
            "type":"Services"
        }
    ],
    "sg:phone":"+1 818 225 7071",
    "sg:postcode":"91364",
    "sg:province":"CA",
    "wof:name":"Fallbrook Pet Clinic",
    "wof:placetype":"venue"
},
  "geometry": {"coordinates":[-118.622851,34.166124],"type":"Point"}
}