{
  "type": "Feature",
  "properties": {
    "addr:full":"8135 Elder Creek Rd Sacramento CA 95824",
    "addr:housenumber":"8135",
    "addr:postcode":"95824",
    "addr:street":"Elder Creek Rd",
    "iso:country":"US",
    "sg:address":"8135 Elder Creek Rd",
    "sg:city":"Sacramento",
    "sg:classifiers":[
        {
            "category":"Professional",
            "type":"Services"
        }
    ],
    "sg:phone":"+1 817 615 3052",
    "sg:postcode":"95824",
    "sg:province":"CA",
    "wof:name":"Bimbo Bakeries USA",
    "wof:placetype":"venue"
},
  "geometry": {"coordinates":[-121.403589,38.510634],"type":"Point"}
}