{
  "type": "Feature",
  "properties": {
    "addr:full":"1104 E 17th St Santa Ana CA 92701",
    "addr:housenumber":"1104",
    "addr:postcode":"92701",
    "addr:street":"E 17Th St",
    "iso:country":"US",
    "sg:address":"1104 E 17th St",
    "sg:city":"Santa Ana",
    "sg:classifiers":[
        {
            "category":"Personal",
            "type":"Services"
        }
    ],
    "sg:phone":"+1 714 285 1201",
    "sg:postcode":"92701",
    "sg:province":"CA",
    "sg:tags":[
        "sewing",
        "alteration"
    ],
    "wof:name":"Expert Alterations",
    "wof:placetype":"venue"
},
  "geometry": {"coordinates":[-117.856003,33.759899],"type":"Point"}
}