{
  "type": "Feature",
  "properties": {
    "iso:country":"US",
    "sg:address":"3572 Arlington Ave",
    "sg:city":"Riverside",
    "sg:classifiers":[
        {
            "category":"Banks & Credit Unions",
            "subcategory":"Bank",
            "type":"Services"
        }
    ],
    "sg:phone":"+1 951 367 1611",
    "sg:postcode":"92506",
    "sg:province":"CA",
    "sg:tags":[
        "loan",
        "real estate"
    ],
    "wof:name":"Amerifund Mortgage",
    "wof:placetype":"venue"
},
  "geometry": {"coordinates":[-117.391571,33.946211],"type":"Point"}
}