{
  "type": "Feature",
  "properties": {
    "iso:country":"US",
    "sg:address":"347 Rodriguez St",
    "sg:city":"Watsonville",
    "sg:classifiers":[
        {
            "category":"Shopping",
            "subcategory":"Department Store",
            "type":"Retail Goods"
        }
    ],
    "sg:phone":"+1 831 722 6600",
    "sg:postcode":"95076",
    "sg:province":"CA",
    "wof:name":"Watsonville Discount Mall",
    "wof:placetype":"venue"
},
  "geometry": {"coordinates":[-121.757583,36.908856],"type":"Point"}
}