{
  "type": "Feature",
  "properties": {
    "iso:country":"US",
    "sg:address":"501 Santa Monica Blvd",
    "sg:city":"Santa Monica",
    "sg:classifiers":[
        {
            "category":"Wholesale",
            "subcategory":"Machinery & Supplies",
            "type":"Manufacturing & Wholesale Goods"
        },
        {
            "category":"Manufacturing",
            "subcategory":"Metals",
            "type":"Manufacturing & Wholesale Goods"
        }
    ],
    "sg:phone":"+1 310 319 5388",
    "sg:postcode":"90401",
    "sg:province":"CA",
    "sg:tags":[
        "industrial",
        "cable",
        "mfg",
        "equipment",
        "wire",
        "electronic"
    ],
    "sg:website":"www.stormproducts.com",
    "wof:name":"Storm Products Co",
    "wof:placetype":"venue"
},
  "geometry": {"coordinates":[-118.49370999999999,34.017567],"type":"Point"}
}