{
  "type": "Feature",
  "properties": {
    "iso:country":"US",
    "sg:address":"1157 Riley St",
    "sg:city":"Folsom",
    "sg:classifiers":[
        {
            "category":"Shopping",
            "type":"Retail Goods"
        }
    ],
    "sg:phone":"+1 916 983 5691",
    "sg:postcode":"95630",
    "sg:province":"CA",
    "sg:tags":[
        "telephone",
        "cellular"
    ],
    "wof:name":"Parrott Cellular",
    "wof:placetype":"venue"
},
  "geometry": {"coordinates":[-121.172,38.673257],"type":"Point"}
}