{
  "type": "Feature",
  "properties": {
    "addr:full":"4316 W Jefferson Blvd Los Angeles CA 90016",
    "addr:housenumber":"4316",
    "addr:postcode":"90016",
    "addr:street":"W Jefferson Blvd",
    "iso:country":"US",
    "sg:address":"4316 W Jefferson Blvd",
    "sg:city":"Los Angeles",
    "sg:classifiers":[
        {
            "category":"Retail",
            "subcategory":"Repair Shop",
            "type":"Services"
        }
    ],
    "sg:phone":"+1 323 732 4964",
    "sg:postcode":"90016",
    "sg:province":"CA",
    "sg:tags":[
        "reupholstery",
        "furniture"
    ],
    "wof:name":"Jesse's Custom Wood Finishing",
    "wof:placetype":"venue"
},
  "geometry": {"coordinates":[-118.343002,34.0257],"type":"Point"}
}