{
  "type": "Feature",
  "properties": {
    "addr:full":"225 Santa Monica Blvd. 6th Floor Santa Monica CA 90401",
    "addr:housenumber":"225",
    "addr:postcode":"90401",
    "addr:street":"Santa Monica Blvd. 6Th Floor",
    "iso:country":"US",
    "sg:address":"225 Santa Monica Blvd. 6th Floor",
    "sg:city":"Santa Monica",
    "sg:classifiers":[
        {
            "category":"Professional",
            "subcategory":"Computer Services",
            "type":"Services"
        }
    ],
    "sg:phone":"+1 310 571 0300",
    "sg:postcode":"90401",
    "sg:province":"CA",
    "sg:website":"http://www.nesting.com",
    "wof:name":"Nesting",
    "wof:placetype":"venue"
},
  "geometry": {"coordinates":[-118.496836,34.015147],"type":"Point"}
}