{
  "type": "Feature",
  "properties": {
    "addr:full":"2060 E Pleasant Valley Rd Oxnard CA 93033",
    "addr:housenumber":"2060",
    "addr:postcode":"93033",
    "addr:street":"E Pleasant Valley Rd",
    "iso:country":"US",
    "sg:address":"2060 E Pleasant Valley Rd",
    "sg:city":"Oxnard",
    "sg:classifiers":[
        {
            "category":"Food & Beverages",
            "subcategory":"Groceries & Convenience Stores",
            "type":"Retail Goods"
        }
    ],
    "sg:phone":"+1 805 488 8500",
    "sg:postcode":"93033",
    "sg:province":"CA",
    "sg:tags":[
        "money",
        "order"
    ],
    "sg:website":"http://www.7-eleven.com",
    "wof:name":"7-Eleven",
    "wof:placetype":"venue"
},
  "geometry": {"coordinates":[-119.152226,34.161454],"type":"Point"}
}