{
  "type": "Feature",
  "properties": {
    "iso:country":"US",
    "sg:address":"30330 Holdridge Cir",
    "sg:city":"Porterville",
    "sg:classifiers":[
        {
            "category":"Professional",
            "subcategory":"Detective & Security Services",
            "type":"Services"
        }
    ],
    "sg:phone":"+1 559 784 9594",
    "sg:postcode":"93257",
    "sg:province":"CA",
    "sg:tags":[
        "information",
        "bureau"
    ],
    "wof:name":"Accurate Construction Service, Inc.",
    "wof:placetype":"venue"
},
  "geometry": {"coordinates":[-118.896263,36.104946],"type":"Point"}
}