{
  "type": "Feature",
  "properties": {
    "addr:full":"699 Chenery Street San Francisco CA 94131",
    "addr:housenumber":"699",
    "addr:postcode":"94131",
    "addr:street":"Chenery Street",
    "iso:country":"US",
    "sg:address":"699 Chenery Street",
    "sg:city":"San Francisco",
    "sg:classifiers":[
        {
            "category":"Building & Trades",
            "subcategory":"Plumbing",
            "type":"Services"
        },
        {
            "category":"Building & Trades",
            "subcategory":"Construction",
            "type":"Services"
        }
    ],
    "sg:phone":"+1 415 586 2293",
    "sg:postcode":"94131",
    "sg:province":"CA",
    "sg:tags":[
        "air",
        "heating",
        "conditioning/hvac"
    ],
    "wof:name":"Tracy Wm A Heating & Plumbing",
    "wof:placetype":"venue"
},
  "geometry": {"coordinates":[-122.433998,37.734402],"type":"Point"}
}