{
  "type": "Feature",
  "properties": {
    "iso:country":"US",
    "sg:address":"6815 Fair Oaks Blvd Ste 1",
    "sg:city":"Carmichael",
    "sg:classifiers":[
        {
            "category":"Professional",
            "subcategory":"Management & Consulting",
            "type":"Services"
        },
        {
            "category":"Banks & Credit Unions",
            "subcategory":"Financial Services",
            "type":"Services"
        }
    ],
    "sg:phone":"+1 916 733 0400",
    "sg:postcode":"95608",
    "sg:province":"CA",
    "sg:tags":[
        "consultant",
        "financing",
        "planning"
    ],
    "wof:name":"California Financial",
    "wof:placetype":"venue"
},
  "geometry": {"coordinates":[-121.328414,38.624828],"type":"Point"}
}