{
  "type": "Feature",
  "properties": {
    "iso:country":"US",
    "sg:address":"2927 19th St",
    "sg:city":"Bakersfield",
    "sg:classifiers":[
        {
            "category":"Government",
            "subcategory":"Office",
            "type":"Public Place"
        }
    ],
    "sg:phone":"+1 661 321 0210",
    "sg:postcode":"93301",
    "sg:province":"CA",
    "sg:tags":[
        "medium",
        "relations"
    ],
    "wof:name":"Gene Tackett",
    "wof:placetype":"venue"
},
  "geometry": {"coordinates":[-119.03606600000001,35.376224],"type":"Point"}
}