{
  "type": "Feature",
  "properties": {
    "addr:full":"236 West Portal Ave San Francisco CA 94127",
    "addr:housenumber":"236",
    "addr:postcode":"94127",
    "addr:street":"West Portal Ave",
    "iso:country":"US",
    "sg:address":"236 West Portal Ave",
    "sg:city":"San Francisco",
    "sg:classifiers":[
        {
            "category":"Professional",
            "subcategory":"Management & Consulting",
            "type":"Services"
        },
        {
            "category":"Education",
            "subcategory":"School",
            "type":"Public Place"
        },
        {
            "category":"Social Services",
            "subcategory":"Job Training",
            "type":"Services"
        }
    ],
    "sg:phone":"+1 415 200 0513",
    "sg:postcode":"94127",
    "sg:province":"CA",
    "sg:tags":[
        "career",
        "counseling",
        "life",
        "coach"
    ],
    "sg:website":"www.meredithhaberfeld.com",
    "wof:name":"Meredith Haberfeld Coaching- San Francisco",
    "wof:placetype":"venue"
},
  "geometry": {"coordinates":[-122.46852800000001,37.7385],"type":"Point"}
}