{
  "type": "Feature",
  "properties": {
    "iso:country":"US",
    "sg:address":"9777 Wilshire Blvd Ste 815",
    "sg:city":"Beverly Hills",
    "sg:classifiers":[
        {
            "category":"Real Estate",
            "subcategory":"Real Estate Services",
            "type":"Services"
        }
    ],
    "sg:phone":"+1 310 274 9786",
    "sg:postcode":"90212",
    "sg:province":"CA",
    "sg:tags":[
        "management",
        "property"
    ],
    "wof:name":"Beverly Hills Gateway Lp",
    "wof:placetype":"venue"
},
  "geometry": {"coordinates":[-118.409134,34.067096],"type":"Point"}
}