{
  "type": "Feature",
  "properties": {
    "iso:country":"US",
    "sg:address":"15981 Yarnell St",
    "sg:city":"Sylmar",
    "sg:classifiers":[
        {
            "category":"Professional",
            "subcategory":"Management & Consulting",
            "type":"Services"
        }
    ],
    "sg:phone":"+1 818 364 1111",
    "sg:postcode":"91342",
    "sg:province":"CA",
    "sg:tags":[
        "party",
        "planning"
    ],
    "sg:website":"www.bouncerus.com",
    "wof:name":"Bounce R Us",
    "wof:placetype":"venue"
},
  "geometry": {"coordinates":[-118.479145,34.322326],"type":"Point"}
}