{
  "type": "Feature",
  "properties": {
    "addr:full":"607 Desert Gardens Dr El Centro CA 92243",
    "addr:housenumber":"607",
    "addr:postcode":"92243",
    "addr:street":"Desert Gardens Dr",
    "iso:country":"US",
    "sg:address":"607 Desert Gardens Dr",
    "sg:city":"El Centro",
    "sg:classifiers":[
        {
            "category":"Organizations",
            "subcategory":"Religious Organization",
            "type":"Services"
        }
    ],
    "sg:phone":"+1 760 353 2134",
    "sg:postcode":"92243",
    "sg:province":"CA",
    "sg:tags":[
        "church"
    ],
    "wof:name":"Imperial Valley Ctr-Creative",
    "wof:placetype":"venue"
},
  "geometry": {"coordinates":[-115.56112899999999,32.780879],"type":"Point"}
}