{
  "type": "Feature",
  "properties": {
    "iso:country":"US",
    "sg:address":"301 E Colorado Blvd Ste 514",
    "sg:city":"Pasadena",
    "sg:classifiers":[
        {
            "category":"Professional",
            "subcategory":"Lawyer & Legal Services",
            "type":"Services"
        }
    ],
    "sg:phone":"+1 626 432 1975",
    "sg:postcode":"91101",
    "sg:province":"CA",
    "sg:tags":[
        "divorce",
        "law",
        "family"
    ],
    "sg:website":"www.rwmedina.com",
    "wof:name":"Law Offices of Randy W. Medina, APLC",
    "wof:placetype":"venue"
},
  "geometry": {"coordinates":[-118.1434,34.146805],"type":"Point"}
}