{
  "type": "Feature",
  "properties": {
    "iso:country":"US",
    "sg:address":"1203 E Vermont Ave",
    "sg:city":"Anaheim",
    "sg:classifiers":[
        {
            "category":"Health Services",
            "subcategory":"Chiropractor",
            "type":"Services"
        }
    ],
    "sg:phone":"+1 562 595 7226",
    "sg:postcode":"92805",
    "sg:province":"CA",
    "wof:name":"Bixby Knolls Family Chiropractic",
    "wof:placetype":"venue"
},
  "geometry": {"coordinates":[-117.898003,33.825901],"type":"Point"}
}