{
  "type": "Feature",
  "properties": {
    "addr:full":"4540 Campus Dr Newport Beach CA 92660",
    "addr:housenumber":"4540",
    "addr:postcode":"92660",
    "addr:street":"Campus Dr",
    "iso:country":"US",
    "sg:address":"4540 Campus Dr",
    "sg:city":"Newport Beach",
    "sg:classifiers":[
        {
            "category":"Utilities",
            "subcategory":"Telephone",
            "type":"Services"
        }
    ],
    "sg:phone":"+1 949 252 8717",
    "sg:postcode":"92660",
    "sg:province":"CA",
    "sg:tags":[
        "communications"
    ],
    "wof:name":"Netping America Inc",
    "wof:placetype":"venue"
},
  "geometry": {"coordinates":[-117.86561,33.671285],"type":"Point"}
}