{
  "type": "Feature",
  "properties": {
    "iso:country":"US",
    "sg:address":"2225 W Shaw Ave",
    "sg:city":"Fresno",
    "sg:classifiers":[
        {
            "category":"Restaurant",
            "type":"Food & Drink"
        }
    ],
    "sg:phone":"+1 559 222 9346",
    "sg:postcode":"93711",
    "sg:province":"CA",
    "wof:name":"California Pizza LLC",
    "wof:placetype":"venue"
},
  "geometry": {"coordinates":[-119.831985,36.808197],"type":"Point"}
}