{
  "type": "Feature",
  "properties": {
    "iso:country":"US",
    "sg:address":"931 W 7th St",
    "sg:city":"Oxnard",
    "sg:classifiers":[
        {
            "category":"Health Services",
            "subcategory":"Doctor",
            "type":"Services"
        }
    ],
    "sg:phone":"+1 805 483 1879",
    "sg:postcode":"93030",
    "sg:province":"CA",
    "sg:tags":[
        "physician",
        "surgeon"
    ],
    "wof:name":"Chun-Lang Cheng MD",
    "wof:placetype":"venue"
},
  "geometry": {"coordinates":[-119.18965799999999,34.195242],"type":"Point"}
}