{
  "type": "Feature",
  "properties": {
    "addr:full":"938 W College Ave Santa Rosa CA 95401",
    "addr:housenumber":"938",
    "addr:postcode":"95401",
    "addr:street":"W College Ave",
    "iso:country":"US",
    "sg:address":"938 W College Ave",
    "sg:city":"Santa Rosa",
    "sg:classifiers":[
        {
            "category":"Professional",
            "subcategory":"Management & Consulting",
            "type":"Services"
        }
    ],
    "sg:phone":"+1 707 576 8412",
    "sg:postcode":"95401",
    "sg:province":"CA",
    "sg:tags":[
        "consultant",
        "educational"
    ],
    "wof:name":"Eritrean Community Cultural",
    "wof:placetype":"venue"
},
  "geometry": {"coordinates":[-122.739195,38.445347],"type":"Point"}
}