{
  "type": "Feature",
  "properties": {
    "addr:full":"5777 Tower Rd Riverside CA 92506",
    "addr:housenumber":"5777",
    "addr:postcode":"92506",
    "addr:street":"Tower Rd",
    "iso:country":"US",
    "sg:address":"5777 Tower Rd",
    "sg:city":"Riverside",
    "sg:classifiers":[
        {
            "category":"Building & Trades",
            "subcategory":"Construction",
            "type":"Services"
        }
    ],
    "sg:phone":"+1 909 855 0386",
    "sg:postcode":"92506",
    "sg:province":"CA",
    "sg:tags":[
        "tile",
        "dealer"
    ],
    "wof:name":"Allstar Tile & Stone",
    "wof:placetype":"venue"
},
  "geometry": {"coordinates":[-117.40353399999999,33.965879],"type":"Point"}
}