{
  "type": "Feature",
  "properties": {
    "addr:full":"4211 Barrett Ave Richmond CA 94805",
    "addr:housenumber":"4211",
    "addr:postcode":"94805",
    "addr:street":"Barrett Ave",
    "iso:country":"US",
    "sg:address":"4211 Barrett Ave",
    "sg:city":"Richmond",
    "sg:classifiers":[
        {
            "category":"Taxi",
            "type":"Transportation"
        }
    ],
    "sg:phone":"+1 510 685 0476",
    "sg:postcode":"94805",
    "sg:province":"CA",
    "sg:tags":[
        "taxicab"
    ],
    "wof:name":"Town Cab",
    "wof:placetype":"venue"
},
  "geometry": {"coordinates":[-122.32850999999999,37.935858],"type":"Point"}
}