{
  "type": "Feature",
  "properties": {
    "iso:country":"US",
    "sg:address":"120 W 2nd St",
    "sg:city":"Chico",
    "sg:classifiers":[
        {
            "category":"Professional",
            "subcategory":"Business Services",
            "type":"Services"
        }
    ],
    "sg:phone":"+1 530 898 0815",
    "sg:postcode":"95928",
    "sg:province":"CA",
    "sg:tags":[
        "recording",
        "studio"
    ],
    "wof:name":"Single-Malt Studio",
    "wof:placetype":"venue"
},
  "geometry": {"coordinates":[-121.841201,39.729923],"type":"Point"}
}