{
  "type": "Feature",
  "properties": {
    "addr:full":"972 Azalea Dr Costa Mesa CA 92626",
    "addr:housenumber":"972",
    "addr:postcode":"92626",
    "addr:street":"Azalea Dr",
    "iso:country":"US",
    "sg:address":"972 Azalea Dr",
    "sg:city":"Costa Mesa",
    "sg:classifiers":[
        {
            "category":"Professional",
            "type":"Services"
        }
    ],
    "sg:phone":"+1 714 432 7461",
    "sg:postcode":"92626",
    "sg:province":"CA",
    "wof:name":"Globesoftres",
    "wof:placetype":"venue"
},
  "geometry": {"coordinates":[-117.895264,33.69488],"type":"Point"}
}