{
  "type": "Feature",
  "properties": {
    "iso:country":"US",
    "sg:address":"336 Desert View Dr",
    "sg:city":"Thermal",
    "sg:classifiers":[
        {
            "category":"Building & Trades",
            "subcategory":"Construction",
            "type":"Services"
        },
        {
            "category":"Recreation",
            "subcategory":"Campground",
            "type":"Entertainment"
        }
    ],
    "sg:phone":"+1 760 394 4333",
    "sg:postcode":"92274",
    "sg:province":"CA",
    "sg:tags":[
        "manufactured",
        "housing-communities",
        "recreational",
        "park",
        "vehicle"
    ],
    "wof:name":"Salton Sea Partners Inc",
    "wof:placetype":"venue"
},
  "geometry": {"coordinates":[-116.043656,33.403209],"type":"Point"}
}