{
  "type": "Feature",
  "properties": {
    "addr:full":"480 Keyes Street San Jose CA 95112",
    "addr:housenumber":"480",
    "addr:postcode":"95112",
    "addr:street":"Keyes Street",
    "iso:country":"US",
    "sg:address":"480 Keyes Street",
    "sg:city":"San Jose",
    "sg:classifiers":[
        {
            "category":"Autos & Motor Vehicles",
            "subcategory":"Auto Supplies",
            "type":"Retail Goods"
        }
    ],
    "sg:phone":"+1 408 298 4940",
    "sg:postcode":"95112",
    "sg:province":"CA",
    "sg:tags":[
        "part"
    ],
    "wof:name":"Pleck's Auto Supply",
    "wof:placetype":"venue"
},
  "geometry": {"coordinates":[-121.86811400000001,37.324411],"type":"Point"}
}