{
  "type": "Feature",
  "properties": {
    "addr:full":"1745 Adrian Rd. Suite 1 Burlingame CA 94010",
    "addr:housenumber":"1745",
    "addr:postcode":"94010",
    "addr:street":"Adrian Rd. Suite 1",
    "iso:country":"US",
    "sg:address":"1745 Adrian Rd. Suite 1",
    "sg:city":"Burlingame",
    "sg:classifiers":[
        {
            "category":"Professional",
            "subcategory":"Advertising",
            "type":"Services"
        }
    ],
    "sg:phone":"+1 650 690 7566",
    "sg:postcode":"94010",
    "sg:province":"CA",
    "sg:tags":[
        "online-advertising-sales-consulting-digital-media-ad-operations-cpm-cpc"
    ],
    "sg:website":"http://genymediainc.com",
    "wof:name":"Gen-Y Media ",
    "wof:placetype":"venue"
},
  "geometry": {"coordinates":[-122.382914,37.599458],"type":"Point"}
}