{
  "type": "Feature",
  "properties": {
    "iso:country":"US",
    "sg:address":"2620 Broadway",
    "sg:city":"Santa Monica",
    "sg:classifiers":[
        {
            "category":"Health Services",
            "subcategory":"Nursing And Care Facility",
            "type":"Services"
        }
    ],
    "sg:phone":"+1 310 453 8816",
    "sg:postcode":"90404",
    "sg:province":"CA",
    "sg:tags":[
        "home",
        "retirement",
        "community"
    ],
    "wof:name":"Berkley Gardens",
    "wof:placetype":"venue"
},
  "geometry": {"coordinates":[-118.472353,34.032131],"type":"Point"}
}