{
  "type": "Feature",
  "properties": {
    "addr:full":"1212 N Bellflower Blvd Cal State Long Beach Long Beach CA 90815",
    "addr:housenumber":"1212",
    "addr:postcode":"90815",
    "addr:street":"N Bellflower Blvd Cal State",
    "iso:country":"US",
    "sg:address":"1212 N Bellflower Blvd Cal State Long Beach",
    "sg:city":"Long Beach",
    "sg:classifiers":[
        {
            "category":"Coffee & Tea",
            "type":"Food & Drink"
        }
    ],
    "sg:phone":"+1 562 985 3477",
    "sg:postcode":"90815",
    "sg:province":"CA",
    "sg:website":"www.coffeebean.com",
    "wof:name":"The Coffee Bean & Tea Leaf",
    "wof:placetype":"venue"
},
  "geometry": {"coordinates":[-118.12236,33.781737],"type":"Point"}
}