{
  "type": "Feature",
  "properties": {
    "addr:full":"1390 Rollins Rd Burlingame CA 94010",
    "addr:housenumber":"1390",
    "addr:postcode":"94010",
    "addr:street":"Rollins Rd",
    "iso:country":"US",
    "sg:address":"1390 Rollins Rd",
    "sg:city":"Burlingame",
    "sg:classifiers":[
        {
            "category":"Autos & Motor Vehicles",
            "subcategory":"Auto Supplies",
            "type":"Retail Goods"
        }
    ],
    "sg:phone":"+1 650 558 8253",
    "sg:postcode":"94010",
    "sg:province":"CA",
    "sg:tags":[
        "automobile",
        "parts"
    ],
    "wof:name":"Sportcars Italiano",
    "wof:placetype":"venue"
},
  "geometry": {"coordinates":[-122.365968,37.590775],"type":"Point"}
}