{
  "type": "Feature",
  "properties": {
    "iso:country":"US",
    "sg:address":"4714 Whittier Blvd",
    "sg:city":"Los Angeles",
    "sg:classifiers":[
        {
            "category":"Shopping",
            "subcategory":"Used Merchandise",
            "type":"Retail Goods"
        }
    ],
    "sg:phone":"+1 323 265 4424",
    "sg:postcode":"90022",
    "sg:province":"CA",
    "sg:tags":[
        "secondhand",
        "store"
    ],
    "wof:name":"L A Barato",
    "wof:placetype":"venue"
},
  "geometry": {"coordinates":[-118.16605,34.02218],"type":"Point"}
}