{
  "type": "Feature",
  "properties": {
    "iso:country":"US",
    "sg:address":"850 W Foothill Blvd # 15",
    "sg:city":"Azusa",
    "sg:classifiers":[
        {
            "category":"Professional",
            "subcategory":"Engineering",
            "type":"Services"
        }
    ],
    "sg:phone":"+1 626 334 4500",
    "sg:postcode":"91702",
    "sg:province":"CA",
    "sg:tags":[
        "refrigeration",
        "engineer"
    ],
    "wof:name":"Thomas Refrigeration",
    "wof:placetype":"venue"
},
  "geometry": {"coordinates":[-117.91727400000001,34.133549],"type":"Point"}
}