{
  "type": "Feature",
  "properties": {
    "iso:country":"US",
    "sg:address":"7026 Castle Peak Dr",
    "sg:city":"Canoga Park",
    "sg:classifiers":[
        {
            "category":"Autos & Motor Vehicles",
            "subcategory":"Automobile Sales",
            "type":"Retail Goods"
        }
    ],
    "sg:phone":"+1 818 266 1769",
    "sg:postcode":"91307",
    "sg:province":"CA",
    "sg:tags":[
        "used"
    ],
    "wof:name":"Gdg Auto Sales",
    "wof:placetype":"venue"
},
  "geometry": {"coordinates":[-118.660848,34.200329],"type":"Point"}
}