{
  "type": "Feature",
  "properties": {
    "iso:country":"US",
    "sg:address":"632 E Canon Perdido St",
    "sg:city":"Santa Barbara",
    "sg:classifiers":[
        {
            "category":"Social Services",
            "type":"Services"
        }
    ],
    "sg:phone":"+1 805 962 2382",
    "sg:postcode":"93103",
    "sg:province":"CA",
    "sg:tags":[
        "youth",
        "organization",
        "center"
    ],
    "sg:website":"www.boysgirls.org",
    "wof:name":"Boys & Girls Clubs",
    "wof:placetype":"venue"
},
  "geometry": {"coordinates":[-119.69293500000001,34.427534],"type":"Point"}
}