{
  "type": "Feature",
  "properties": {
    "addr:full":"1440 State College Blvd Anaheim CA 92801",
    "addr:housenumber":"1440",
    "addr:postcode":"92801",
    "addr:street":"State College Blvd",
    "iso:country":"US",
    "sg:address":"1440 State College Blvd",
    "sg:city":"Anaheim",
    "sg:classifiers":[
        {
            "category":"Home & Garden",
            "subcategory":"Carpets & Floor Coverings",
            "type":"Retail Goods"
        }
    ],
    "sg:phone":"+1 714 774 8404",
    "sg:postcode":"92801",
    "sg:province":"CA",
    "sg:tags":[
        "flooring"
    ],
    "wof:name":"Castle Wood Flooring",
    "wof:placetype":"venue"
},
  "geometry": {"coordinates":[-117.889039,33.855648],"type":"Point"}
}