{
  "type": "Feature",
  "properties": {
    "addr:full":"2412 N Ponderosa Dr Ste B107 Camarillo CA 93012",
    "addr:housenumber":"2412",
    "addr:postcode":"93012",
    "addr:street":"N Ponderosa Dr Ste B107",
    "iso:country":"US",
    "sg:address":"2412 N Ponderosa Dr Ste B107",
    "sg:city":"Camarillo",
    "sg:classifiers":[
        {
            "category":"Health Services",
            "subcategory":"Clinic",
            "type":"Services"
        }
    ],
    "sg:postcode":"93012",
    "sg:province":"CA",
    "sg:tags":[
        "medical"
    ],
    "wof:name":"Foundation Laboratories",
    "wof:placetype":"venue"
},
  "geometry": {"coordinates":[-119.040289,34.171192],"type":"Point"}
}