{
  "type": "Feature",
  "properties": {
    "iso:country":"US",
    "sg:address":"123 6th Ave",
    "sg:city":"La Puente",
    "sg:classifiers":[
        {
            "category":"Shopping",
            "subcategory":"Pharmacy",
            "type":"Retail Goods"
        }
    ],
    "sg:phone":"+1 626 961 4657",
    "sg:postcode":"91746",
    "sg:province":"CA",
    "sg:tags":[
        "product",
        "health",
        "care"
    ],
    "wof:name":"King House Corp",
    "wof:placetype":"venue"
},
  "geometry": {"coordinates":[-117.978399,34.037265],"type":"Point"}
}