{
  "type": "Feature",
  "properties": {
    "iso:country":"US",
    "sg:address":"911 Industrial Way",
    "sg:city":"Lodi",
    "sg:classifiers":[
        {
            "category":"Banks & Credit Unions",
            "subcategory":"Bank",
            "type":"Services"
        }
    ],
    "sg:phone":"+1 209 333 1493",
    "sg:postcode":"95240",
    "sg:province":"CA",
    "sg:tags":[
        "loan",
        "real estate"
    ],
    "sg:website":"www.centralfinancial.net",
    "wof:name":"Central Financial",
    "wof:placetype":"venue"
},
  "geometry": {"coordinates":[-121.253792,38.12553],"type":"Point"}
}