{
  "type": "Feature",
  "properties": {
    "iso:country":"US",
    "sg:address":"500 San Pablo Ave # 300",
    "sg:city":"Albany",
    "sg:classifiers":[
        {
            "category":"Health Services",
            "subcategory":"Doctor",
            "type":"Services"
        }
    ],
    "sg:phone":"+1 510 524 1580",
    "sg:postcode":"94706",
    "sg:province":"CA",
    "sg:tags":[
        "physician",
        "surgeon"
    ],
    "wof:name":"Gjeltema, Kenneth J, Md - Sutter East Bay Foundation",
    "wof:placetype":"venue"
},
  "geometry": {"coordinates":[-122.301041,37.896847],"type":"Point"}
}