{
  "type": "Feature",
  "properties": {
    "addr:full":"29000 S Western Avenue Rancho Palos Verdes CA 90275",
    "addr:housenumber":"29000",
    "addr:postcode":"90275",
    "addr:street":"S Western Avenue",
    "iso:country":"US",
    "sg:address":"29000 S Western Avenue",
    "sg:city":"Rancho Palos Verdes",
    "sg:classifiers":[
        {
            "category":"Health Services",
            "subcategory":"Doctor",
            "type":"Services"
        }
    ],
    "sg:phone":"+1 310 833 1334",
    "sg:postcode":"90275",
    "sg:province":"CA",
    "sg:website":"www.familyallergist.com",
    "wof:name":"Family Allergy & Asthma Medical Center",
    "wof:placetype":"venue"
},
  "geometry": {"coordinates":[-118.309574,33.755508],"type":"Point"}
}