{
  "type": "Feature",
  "properties": {
    "iso:country":"US",
    "sg:address":"2883 Highland Ave",
    "sg:city":"Selma",
    "sg:classifiers":[
        {
            "category":"Restaurant",
            "type":"Food & Drink"
        }
    ],
    "sg:menulink":"http://www.allmenus.com/ca/selma/214191-taco-bell/menu/",
    "sg:phone":"+1 559 896 7011",
    "sg:postcode":"93662",
    "sg:province":"CA",
    "sg:tags":[
        "mexican"
    ],
    "wof:name":"Taco Bell",
    "wof:placetype":"venue"
},
  "geometry": {"coordinates":[-119.628719,36.574808],"type":"Point"}
}