{
  "type": "Feature",
  "properties": {
    "addr:full":"12843 Foothill Blvd Sylmar CA 91342",
    "addr:housenumber":"12843",
    "addr:postcode":"91342",
    "addr:street":"Foothill Blvd",
    "iso:country":"US",
    "sg:address":"12843 Foothill Blvd",
    "sg:city":"Sylmar",
    "sg:classifiers":[
        {
            "category":"Organizations",
            "subcategory":"Professional Association",
            "type":"Services"
        }
    ],
    "sg:phone":"+1 818 361 4206",
    "sg:postcode":"91342",
    "sg:province":"CA",
    "wof:name":"Fulfillment Options Inc Assn",
    "wof:placetype":"venue"
},
  "geometry": {"coordinates":[-118.415667,34.293932],"type":"Point"}
}