{
  "type": "Feature",
  "properties": {
    "addr:full":"3755 Murphy Canyon Rd San Diego CA 92123",
    "addr:housenumber":"3755",
    "addr:postcode":"92123",
    "addr:street":"Murphy Canyon Rd",
    "iso:country":"US",
    "sg:address":"3755 Murphy Canyon Rd",
    "sg:city":"San Diego",
    "sg:classifiers":[
        {
            "category":"Personal",
            "subcategory":"Beauty Salon",
            "type":"Services"
        },
        {
            "category":"Personal",
            "subcategory":"Barber",
            "type":"Services"
        }
    ],
    "sg:phone":"+1 619 265 2632",
    "sg:postcode":"92123",
    "sg:province":"CA",
    "sg:tags":[
        "hair"
    ],
    "sg:website":"www.freewebs.com/itsmenateg",
    "wof:name":"Nate G Master Barber & Stylist",
    "wof:placetype":"venue"
},
  "geometry": {"coordinates":[-117.11597399999999,32.810737],"type":"Point"}
}