{
  "type": "Feature",
  "properties": {
    "iso:country":"US",
    "sg:address":"2000 Broadway St",
    "sg:city":"Redwood City",
    "sg:classifiers":[
        {
            "category":"Health Services",
            "subcategory":"Health Practitioner",
            "type":"Services"
        }
    ],
    "sg:phone":"+1 650 369 5354",
    "sg:postcode":"94063",
    "sg:province":"CA",
    "sg:tags":[
        "pathologist",
        "speech"
    ],
    "wof:name":"Carl H Scott",
    "wof:placetype":"venue"
},
  "geometry": {"coordinates":[-122.22686299999999,37.486578],"type":"Point"}
}