{
  "type": "Feature",
  "properties": {
    "iso:country":"US",
    "sg:address":"1515 E Acequia Ave",
    "sg:city":"Visalia",
    "sg:classifiers":[
        {
            "category":"Retail",
            "subcategory":"Repair Shop",
            "type":"Services"
        }
    ],
    "sg:phone":"+1 559 732 2109",
    "sg:postcode":"93292",
    "sg:province":"CA",
    "sg:tags":[
        "welding"
    ],
    "wof:name":"Weldcraft Welding & Fab",
    "wof:placetype":"venue"
},
  "geometry": {"coordinates":[-119.27642899999999,36.329118],"type":"Point"}
}