{
  "type": "Feature",
  "properties": {
    "iso:country":"US",
    "sg:address":"611 S Atlantic Boulevard",
    "sg:city":"Los Angeles",
    "sg:classifiers":[
        {
            "category":"Shopping",
            "subcategory":"Mobile Phones",
            "type":"Retail Goods"
        }
    ],
    "sg:phone":"+1 323 980 0850",
    "sg:postcode":"90022",
    "sg:province":"CA",
    "sg:website":"www.radioshack.com",
    "wof:name":"Radioshack",
    "wof:placetype":"venue"
},
  "geometry": {"coordinates":[-118.15610599999999,34.023834],"type":"Point"}
}