{
  "type": "Feature",
  "properties": {
    "iso:country":"US",
    "sg:address":"6160 Florin Rd",
    "sg:city":"Sacramento",
    "sg:classifiers":[
        {
            "category":"Autos & Motor Vehicles",
            "subcategory":"Auto Supplies",
            "type":"Retail Goods"
        },
        {
            "category":"Retail",
            "subcategory":"Auto Repair",
            "type":"Services"
        }
    ],
    "sg:phone":"+1 916 421 0399",
    "sg:postcode":"95823",
    "sg:province":"CA",
    "sg:tags":[
        "exhaust",
        "muffler",
        "system"
    ],
    "sg:website":"http://www.gotduals.com",
    "wof:name":"Muffler Tech",
    "wof:placetype":"venue"
},
  "geometry": {"coordinates":[-121.434275,38.496101],"type":"Point"}
}