{
  "type": "Feature",
  "properties": {
    "addr:full":"515 W Rialto Ave Rialto CA 92376",
    "addr:housenumber":"515",
    "addr:postcode":"92376",
    "addr:street":"W Rialto Ave",
    "iso:country":"US",
    "sg:address":"515 W Rialto Ave",
    "sg:city":"Rialto",
    "sg:classifiers":[
        {
            "category":"Education",
            "subcategory":"School",
            "type":"Public Place"
        }
    ],
    "sg:phone":"+1 909 874 1330",
    "sg:postcode":"92376",
    "sg:province":"CA",
    "wof:name":"Rialto Community School",
    "wof:placetype":"venue"
},
  "geometry": {"coordinates":[-117.382774,34.099448],"type":"Point"}
}