{
  "type": "Feature",
  "properties": {
    "iso:country":"US",
    "sg:address":"6860 Mount Aukum Rd",
    "sg:city":"Somerset",
    "sg:classifiers":[
        {
            "category":"Education",
            "subcategory":"School",
            "type":"Public Place"
        }
    ],
    "sg:phone":"+1 530 620 7210",
    "sg:postcode":"95684",
    "sg:province":"CA",
    "wof:name":"Pioneer Union School District",
    "wof:placetype":"venue"
},
  "geometry": {"coordinates":[-120.710061,38.60702],"type":"Point"}
}