{
  "type": "Feature",
  "properties": {
    "addr:full":"3963 Pacific Coast Hwy Torrance CA 90505",
    "addr:housenumber":"3963",
    "addr:postcode":"90505",
    "addr:street":"Pacific Coast Hwy",
    "iso:country":"US",
    "sg:address":"3963 Pacific Coast Hwy",
    "sg:city":"Torrance",
    "sg:classifiers":[
        {
            "category":"Restaurant",
            "type":"Food & Drink"
        }
    ],
    "sg:phone":"+1 310 378 2990",
    "sg:postcode":"90505",
    "sg:province":"CA",
    "sg:tags":[
        "sushi",
        "bar",
        "japanese"
    ],
    "sg:website":"www.fusionsushi.com",
    "wof:name":"Fusion Sushi",
    "wof:placetype":"venue"
},
  "geometry": {"coordinates":[-118.355003,33.806301],"type":"Point"}
}