{
  "type": "Feature",
  "properties": {
    "iso:country":"US",
    "sg:address":"722 S Broadway",
    "sg:city":"Los Angeles",
    "sg:classifiers":[
        {
            "category":"Shopping",
            "subcategory":"Jewelry",
            "type":"Retail Goods"
        }
    ],
    "sg:phone":"+1 213 627 5531",
    "sg:postcode":"90014",
    "sg:province":"CA",
    "wof:name":"Fine Silver Max",
    "wof:placetype":"venue"
},
  "geometry": {"coordinates":[-118.253998,34.044701],"type":"Point"}
}