{
  "type": "Feature",
  "properties": {
    "iso:country":"US",
    "sg:address":"3701 Sacramento St",
    "sg:city":"San Francisco",
    "sg:classifiers":[
        {
            "category":"Professional",
            "subcategory":"Lawyer & Legal Services",
            "type":"Services"
        }
    ],
    "sg:phone":"+1 415 750 4210",
    "sg:postcode":"94118",
    "sg:province":"CA",
    "sg:tags":[
        "attorney"
    ],
    "wof:name":"Daniel F Reidy Law Offices",
    "wof:placetype":"venue"
},
  "geometry": {"coordinates":[-122.455236,37.787137],"type":"Point"}
}