{
  "type": "Feature",
  "properties": {
    "iso:country":"US",
    "sg:address":"424 N 1st Ave",
    "sg:city":"Arcadia",
    "sg:classifiers":[
        {
            "category":"Health Services",
            "subcategory":"Hospital",
            "type":"Services"
        },
        {
            "category":"Insurance",
            "subcategory":"Hazard Insurance",
            "type":"Services"
        }
    ],
    "sg:phone":"+1 626 294 2800",
    "sg:postcode":"91006",
    "sg:province":"CA",
    "sg:tags":[
        "plan",
        "medical",
        "hospitalization",
        "surgical"
    ],
    "sg:website":"http://www.ebadmin.com",
    "wof:name":"E B A",
    "wof:placetype":"venue"
},
  "geometry": {"coordinates":[-118.028431,34.14474],"type":"Point"}
}