{
  "type": "Feature",
  "properties": {
    "addr:full":"839 Main St Redwood City CA 94063",
    "addr:housenumber":"839",
    "addr:postcode":"94063",
    "addr:street":"Main St",
    "iso:country":"US",
    "sg:address":"839 Main St",
    "sg:city":"Redwood City",
    "sg:classifiers":[
        {
            "category":"Organizations",
            "subcategory":"Community Association",
            "type":"Services"
        }
    ],
    "sg:phone":"+1 650 369 1633",
    "sg:postcode":"94063",
    "sg:province":"CA",
    "sg:tags":[
        "fraternal"
    ],
    "wof:name":"IOOF",
    "wof:placetype":"venue"
},
  "geometry": {"coordinates":[-122.226164,37.485726],"type":"Point"}
}