{
  "type": "Feature",
  "properties": {
    "iso:country":"US",
    "sg:address":"1001 Edinger Ave",
    "sg:city":"Tustin",
    "sg:classifiers":[
        {
            "category":"Utilities",
            "subcategory":"Natural Gas",
            "type":"Services"
        }
    ],
    "sg:phone":"+1 714 259 8100",
    "sg:postcode":"92780",
    "sg:province":"CA",
    "sg:tags":[
        "propane"
    ],
    "wof:name":"Mutual Liquid Gas & Equipment Co.",
    "wof:placetype":"venue"
},
  "geometry": {"coordinates":[-117.834976,33.726742],"type":"Point"}
}