{
  "type": "Feature",
  "properties": {
    "iso:country":"US",
    "sg:address":"1264 Stevens Ct",
    "sg:city":"Merced",
    "sg:classifiers":[
        {
            "category":"Home & Garden",
            "subcategory":"Household Appliances",
            "type":"Retail Goods"
        }
    ],
    "sg:phone":"+1 209 726 0543",
    "sg:postcode":"95340",
    "sg:province":"CA",
    "wof:name":"Cencal Appliance Svc & Repair",
    "wof:placetype":"venue"
},
  "geometry": {"coordinates":[-120.456855,37.319982],"type":"Point"}
}