{
  "type": "Feature",
  "properties": {
    "addr:full":"25550 Ironwood Ave Moreno Valley CA 92557",
    "addr:housenumber":"25550",
    "addr:postcode":"92557",
    "addr:street":"Ironwood Ave",
    "iso:country":"US",
    "sg:address":"25550 Ironwood Ave",
    "sg:city":"Moreno Valley",
    "sg:classifiers":[
        {
            "category":"Organizations",
            "subcategory":"Religious Organization",
            "type":"Services"
        }
    ],
    "sg:phone":"+1 951 247 2273",
    "sg:postcode":"92557",
    "sg:province":"CA",
    "sg:tags":[
        "church"
    ],
    "sg:website":"www.palmcanyon.org",
    "wof:name":"Palm Canyon Community Church",
    "wof:placetype":"venue"
},
  "geometry": {"coordinates":[-117.216353,33.946768],"type":"Point"}
}