{
  "type": "Feature",
  "properties": {
    "iso:country":"US",
    "sg:address":"12521 Oxnard St",
    "sg:city":"North Hollywood",
    "sg:classifiers":[
        {
            "category":"Deli",
            "type":"Food & Drink"
        },
        {
            "category":"Food & Beverages",
            "subcategory":"Groceries & Convenience Stores",
            "type":"Retail Goods"
        }
    ],
    "sg:phone":"+1 818 985 2662",
    "sg:postcode":"91606",
    "sg:province":"CA",
    "wof:name":"Olive Fresh Garden Marketplace",
    "wof:placetype":"venue"
},
  "geometry": {"coordinates":[-118.406071,34.179695],"type":"Point"}
}