{
  "type": "Feature",
  "properties": {
    "addr:full":"330 Chestnut St Redwood City CA 94063",
    "addr:housenumber":"330",
    "addr:postcode":"94063",
    "addr:street":"Chestnut St",
    "iso:country":"US",
    "sg:address":"330 Chestnut St",
    "sg:city":"Redwood City",
    "sg:classifiers":[
        {
            "category":"Retail",
            "subcategory":"Car Wash",
            "type":"Services"
        }
    ],
    "sg:phone":"+1 650 366 7503",
    "sg:postcode":"94063",
    "sg:province":"CA",
    "sg:tags":[
        "automobile",
        "detail",
        "clean"
    ],
    "wof:name":"Delta Auto Detailing",
    "wof:placetype":"venue"
},
  "geometry": {"coordinates":[-122.222342,37.481038],"type":"Point"}
}