{
  "type": "Feature",
  "properties": {
    "iso:country":"US",
    "sg:address":"6422 del Amo Blvd",
    "sg:city":"Lakewood",
    "sg:classifiers":[
        {
            "category":"Health Services",
            "subcategory":"Doctor",
            "type":"Services"
        }
    ],
    "sg:phone":"+1 562 421 8438",
    "sg:postcode":"90713",
    "sg:province":"CA",
    "sg:tags":[
        "dentist"
    ],
    "wof:name":"Marjorie Handshuh DDS Inc",
    "wof:placetype":"venue"
},
  "geometry": {"coordinates":[-118.107685,33.847001],"type":"Point"}
}