{
  "type": "Feature",
  "properties": {
    "addr:full":"831 S Douglas St El Segundo CA 90245",
    "addr:housenumber":"831",
    "addr:postcode":"90245",
    "addr:street":"S Douglas St",
    "iso:country":"US",
    "sg:address":"831 S Douglas St",
    "sg:city":"El Segundo",
    "sg:classifiers":[
        {
            "category":"Banks & Credit Unions",
            "subcategory":"Bank",
            "type":"Services"
        }
    ],
    "sg:phone":"+1 310 302 7300",
    "sg:postcode":"90245",
    "sg:province":"CA",
    "sg:tags":[
        "national"
    ],
    "wof:name":"Residential Mortgage Ctr 39",
    "wof:placetype":"venue"
},
  "geometry": {"coordinates":[-118.383199,33.903718],"type":"Point"}
}