{
  "type": "Feature",
  "properties": {
    "iso:country":"US",
    "sg:address":"28010 Elena Rd",
    "sg:city":"Los Altos Hills",
    "sg:classifiers":[
        {
            "category":"Building & Trades",
            "subcategory":"Landscaping Services",
            "type":"Services"
        }
    ],
    "sg:phone":"+1 650 948 6326",
    "sg:postcode":"94022",
    "sg:province":"CA",
    "sg:tags":[
        "architect",
        "landscape",
        "contractor"
    ],
    "wof:name":"Grimes Natural Landscape Inc",
    "wof:placetype":"venue"
},
  "geometry": {"coordinates":[-122.15283599999999,37.377139],"type":"Point"}
}