{
  "type": "Feature",
  "properties": {
    "addr:full":"7827 Sunrise Blvd Citrus Heights CA 95610",
    "addr:housenumber":"7827",
    "addr:postcode":"95610",
    "addr:street":"Sunrise Blvd",
    "iso:country":"US",
    "sg:address":"7827 Sunrise Blvd",
    "sg:city":"Citrus Heights",
    "sg:classifiers":[
        {
            "category":"Wholesale",
            "subcategory":"Jewelry",
            "type":"Manufacturing & Wholesale Goods"
        }
    ],
    "sg:phone":"+1 916 728 2619",
    "sg:postcode":"95610",
    "sg:province":"CA",
    "sg:tags":[
        "jeweler"
    ],
    "wof:name":"Alma's Jewelry",
    "wof:placetype":"venue"
},
  "geometry": {"coordinates":[-121.271839,38.708844],"type":"Point"}
}