{
  "type": "Feature",
  "properties": {
    "iso:country":"US",
    "sg:address":"80 Maiden Lane",
    "sg:city":"San Francisco",
    "sg:classifiers":[
        {
            "category":"Banks & Credit Unions",
            "subcategory":"Investment Brokerage",
            "type":"Services"
        }
    ],
    "sg:phone":"+1 415 732 1212",
    "sg:postcode":"94108",
    "sg:province":"CA",
    "sg:tags":[
        "investing"
    ],
    "wof:name":"K S P Capital Management",
    "wof:placetype":"venue"
},
  "geometry": {"coordinates":[-122.404999,37.788399],"type":"Point"}
}