{
  "type": "Feature",
  "properties": {
    "addr:full":"3220 Leona Cir Sacramento CA 95834",
    "addr:housenumber":"3220",
    "addr:postcode":"95834",
    "addr:street":"Leona Cir",
    "iso:country":"US",
    "sg:address":"3220 Leona Cir",
    "sg:city":"Sacramento",
    "sg:classifiers":[
        {
            "category":"Farming",
            "subcategory":"Farm",
            "type":"Manufacturing & Wholesale Goods"
        }
    ],
    "sg:phone":"+1 916 925 6342",
    "sg:postcode":"95834",
    "sg:province":"CA",
    "sg:tags":[
        "crop"
    ],
    "wof:name":"R Norton",
    "wof:placetype":"venue"
},
  "geometry": {"coordinates":[-121.53899699999999,38.636028],"type":"Point"}
}