{
  "type": "Feature",
  "properties": {
    "iso:country":"US",
    "sg:address":"1050 Shaw Ave",
    "sg:city":"Clovis",
    "sg:classifiers":[
        {
            "category":"Food & Beverages",
            "subcategory":"Bakery",
            "type":"Retail Goods"
        }
    ],
    "sg:phone":"+1 559 323 5623",
    "sg:postcode":"93612",
    "sg:province":"CA",
    "sg:tags":[
        "cookie",
        "cracker"
    ],
    "wof:name":"Hungry Bear Cookies",
    "wof:placetype":"venue"
},
  "geometry": {"coordinates":[-119.697277,36.808424],"type":"Point"}
}