{
  "type": "Feature",
  "properties": {
    "addr:full":"3476 Davidson Dr Antelope CA 95843",
    "addr:housenumber":"3476",
    "addr:postcode":"95843",
    "addr:street":"Davidson Dr",
    "iso:country":"US",
    "sg:address":"3476 Davidson Dr",
    "sg:city":"Antelope",
    "sg:classifiers":[
        {
            "category":"Professional",
            "subcategory":"Management & Consulting",
            "type":"Services"
        }
    ],
    "sg:phone":"+1 916 331 5794",
    "sg:postcode":"95843",
    "sg:province":"CA",
    "sg:tags":[
        "consultant",
        "educational"
    ],
    "wof:name":"Iota Enterprises",
    "wof:placetype":"venue"
},
  "geometry": {"coordinates":[-121.384202,38.706946],"type":"Point"}
}