{
  "type": "Feature",
  "properties": {
    "addr:full":"3800 Main St Chula Vista CA 91911",
    "addr:housenumber":"3800",
    "addr:postcode":"91911",
    "addr:street":"Main St",
    "iso:country":"US",
    "sg:address":"3800 Main St",
    "sg:city":"Chula Vista",
    "sg:classifiers":[
        {
            "category":"Manufacturing",
            "subcategory":"Tools & Machinery",
            "type":"Manufacturing & Wholesale Goods"
        }
    ],
    "sg:phone":"+1 619 498 8227",
    "sg:postcode":"91911",
    "sg:province":"CA",
    "sg:tags":[
        "packaging",
        "mfg",
        "vacuum"
    ],
    "wof:name":"Amerivacs",
    "wof:placetype":"venue"
},
  "geometry": {"coordinates":[-117.049384,32.594696],"type":"Point"}
}