{
  "type": "Feature",
  "properties": {
    "iso:country":"US",
    "sg:address":"35644 Glacier Cir",
    "sg:city":"Winchester",
    "sg:classifiers":[
        {
            "category":"Real Estate",
            "subcategory":"Real Estate Services",
            "type":"Services"
        },
        {
            "category":"Real Estate",
            "subcategory":"Real Estate Agent",
            "type":"Services"
        }
    ],
    "sg:phone":"+1 951 926 7500",
    "sg:postcode":"92596",
    "sg:province":"CA",
    "sg:tags":[
        "management"
    ],
    "wof:name":"Egreen Realty",
    "wof:placetype":"venue"
},
  "geometry": {"coordinates":[-117.098912,33.60352],"type":"Point"}
}