{
  "type": "Feature",
  "properties": {
    "iso:country":"US",
    "sg:address":"10122 S Figueroa St",
    "sg:city":"Los Angeles",
    "sg:classifiers":[
        {
            "category":"Cinema",
            "subcategory":"Movie Rental",
            "type":"Entertainment"
        }
    ],
    "sg:phone":"+1 323 242 9624",
    "sg:postcode":"90003",
    "sg:province":"CA",
    "sg:tags":[
        "leasing",
        "video",
        "disc",
        "tape"
    ],
    "wof:name":"K Video",
    "wof:placetype":"venue"
},
  "geometry": {"coordinates":[-118.282535,33.943976],"type":"Point"}
}