{
  "type": "Feature",
  "properties": {
    "addr:full":"1765 Heywood St Simi Valley CA 93065",
    "addr:housenumber":"1765",
    "addr:postcode":"93065",
    "addr:street":"Heywood St",
    "iso:country":"US",
    "sg:address":"1765 Heywood St",
    "sg:city":"Simi Valley",
    "sg:classifiers":[
        {
            "category":"Building & Trades",
            "subcategory":"Cleaning & Sanitation",
            "type":"Services"
        }
    ],
    "sg:phone":"+1 805 520 9486",
    "sg:postcode":"93065",
    "sg:province":"CA",
    "sg:tags":[
        "property",
        "maintenance"
    ],
    "wof:name":"Heywood Apartments",
    "wof:placetype":"venue"
},
  "geometry": {"coordinates":[-118.76244699999999,34.268538],"type":"Point"}
}