{
  "type": "Feature",
  "properties": {
    "iso:country":"US",
    "sg:address":"600 Maple St",
    "sg:city":"Livermore",
    "sg:classifiers":[
        {
            "category":"Building & Trades",
            "subcategory":"Construction",
            "type":"Services"
        }
    ],
    "sg:phone":"+1 925 449 9592",
    "sg:postcode":"94550",
    "sg:province":"CA",
    "sg:tags":[
        "general",
        "contractor"
    ],
    "wof:name":"Thompson Pacific Constr Inc",
    "wof:placetype":"venue"
},
  "geometry": {"coordinates":[-121.760957,37.680002],"type":"Point"}
}