{
  "type": "Feature",
  "properties": {
    "addr:full":"6332 Elvas Avenue Sacramento CA 95819",
    "addr:housenumber":"6332",
    "addr:postcode":"95819",
    "addr:street":"Elvas Avenue",
    "iso:country":"US",
    "sg:address":"6332 Elvas Avenue",
    "sg:city":"Sacramento",
    "sg:classifiers":[
        {
            "category":"Personal",
            "type":"Services"
        }
    ],
    "sg:phone":"+1 916 454 2432",
    "sg:postcode":"95819",
    "sg:province":"CA",
    "sg:tags":[
        "local"
    ],
    "sg:website":"sacpromotionalproduct.com",
    "wof:name":"Creative Impressions",
    "wof:placetype":"venue"
},
  "geometry": {"coordinates":[-121.42794600000001,38.556929],"type":"Point"}
}