{
  "type": "Feature",
  "properties": {
    "addr:full":"930 W San Ysidro Boulevard San Ysidro CA 92173",
    "addr:housenumber":"930",
    "addr:postcode":"92173",
    "addr:street":"W San Ysidro Boulevard",
    "iso:country":"US",
    "sg:address":"930 W San Ysidro Boulevard",
    "sg:city":"San Ysidro",
    "sg:classifiers":[
        {
            "category":"Travel",
            "subcategory":"Hotels & Motels",
            "type":"Entertainment"
        }
    ],
    "sg:phone":"+1 619 690 2633",
    "sg:postcode":"92173",
    "sg:province":"CA",
    "wof:name":"Best Value Inn",
    "wof:placetype":"venue"
},
  "geometry": {"coordinates":[-117.062943,32.56],"type":"Point"}
}