{
  "type": "Feature",
  "properties": {
    "iso:country":"US",
    "sg:address":"16701 Valley Blvd",
    "sg:city":"Fontana",
    "sg:classifiers":[
        {
            "category":"Health Services",
            "subcategory":"Doctor",
            "type":"Services"
        }
    ],
    "sg:phone":"+1 909 434 4755",
    "sg:postcode":"92335",
    "sg:province":"CA",
    "sg:tags":[
        "clinic"
    ],
    "wof:name":"California Medical Clinic",
    "wof:placetype":"venue"
},
  "geometry": {"coordinates":[-117.435688,34.070353],"type":"Point"}
}