{
  "type": "Feature",
  "properties": {
    "iso:country":"US",
    "sg:address":"451 Oceana Blvd",
    "sg:city":"Pacifica",
    "sg:classifiers":[
        {
            "category":"Home & Garden",
            "subcategory":"Hardware",
            "type":"Retail Goods"
        }
    ],
    "sg:phone":"+1 650 355 2922",
    "sg:postcode":"94044",
    "sg:province":"CA",
    "wof:name":"Pacific Manor Hardware Inc",
    "wof:placetype":"venue"
},
  "geometry": {"coordinates":[-122.4898,37.651776],"type":"Point"}
}