{
  "type": "Feature",
  "properties": {
    "iso:country":"US",
    "sg:address":"2360 Park Ave",
    "sg:city":"Chico",
    "sg:classifiers":[
        {
            "category":"Retail",
            "subcategory":"Auto Repair",
            "type":"Services"
        }
    ],
    "sg:phone":"+1 530 899 2300",
    "sg:postcode":"95928",
    "sg:province":"CA",
    "sg:tags":[
        "repairing",
        "automobile"
    ],
    "wof:name":"Chico Independent Auto Care",
    "wof:placetype":"venue"
},
  "geometry": {"coordinates":[-121.817732,39.716298],"type":"Point"}
}