{
  "type": "Feature",
  "properties": {
    "iso:country":"US",
    "sg:address":"109 E 5th St",
    "sg:city":"Hanford",
    "sg:classifiers":[
        {
            "category":"Home & Garden",
            "subcategory":"Building Materials",
            "type":"Retail Goods"
        },
        {
            "category":"Professional",
            "subcategory":"Printing & Photocopies",
            "type":"Services"
        },
        {
            "category":"Manufacturing",
            "subcategory":"Signs",
            "type":"Manufacturing & Wholesale Goods"
        }
    ],
    "sg:phone":"+1 559 583 1175",
    "sg:postcode":"93230",
    "sg:province":"CA",
    "sg:tags":[
        "awning",
        "canopy",
        "flag",
        "banners",
        "pennant"
    ],
    "wof:name":"Signworks",
    "wof:placetype":"venue"
},
  "geometry": {"coordinates":[-119.645088,36.324712],"type":"Point"}
}