{
  "type": "Feature",
  "properties": {
    "iso:country":"US",
    "sg:address":"2464 Tripaldi Way",
    "sg:city":"Hayward",
    "sg:classifiers":[
        {
            "category":"Manufacturing",
            "subcategory":"Tools & Machinery",
            "type":"Manufacturing & Wholesale Goods"
        }
    ],
    "sg:phone":"+1 510 887 1927",
    "sg:postcode":"94545",
    "sg:province":"CA",
    "sg:tags":[
        "equipment",
        "safety",
        "clothing"
    ],
    "wof:name":"Bauer Compressors Inc",
    "wof:placetype":"venue"
},
  "geometry": {"coordinates":[-122.08491,37.614457],"type":"Point"}
}