{
  "type": "Feature",
  "properties": {
    "addr:full":"3150 18th st #275 San Francisco CA 94110",
    "addr:housenumber":"3150",
    "addr:postcode":"94110",
    "addr:street":"18Th St # 275",
    "iso:country":"US",
    "sg:address":"3150 18th st #275",
    "sg:city":"San Francisco",
    "sg:classifiers":[
        {
            "category":"Personal",
            "subcategory":"Beauty Salon",
            "type":"Services"
        }
    ],
    "sg:phone":"+1 415 573 4264",
    "sg:postcode":"94110",
    "sg:province":"CA",
    "sg:tags":[
        "hair"
    ],
    "sg:website":"www.crimelabsalon.com",
    "wof:name":"crime lab",
    "wof:placetype":"venue"
},
  "geometry": {"coordinates":[-122.41396,37.762132],"type":"Point"}
}