{
  "type": "Feature",
  "properties": {
    "addr:full":"541 N Palm Ave Hemet CA 92543",
    "addr:housenumber":"541",
    "addr:postcode":"92543",
    "addr:street":"N Palm Ave",
    "iso:country":"US",
    "sg:address":"541 N Palm Ave",
    "sg:city":"Hemet",
    "sg:classifiers":[
        {
            "category":"Autos & Motor Vehicles",
            "subcategory":"Auto Supplies",
            "type":"Retail Goods"
        },
        {
            "category":"Retail",
            "subcategory":"Auto Repair",
            "type":"Services"
        }
    ],
    "sg:phone":"+1 951 658 7077",
    "sg:postcode":"92543",
    "sg:province":"CA",
    "sg:tags":[
        "automobile",
        "accessory"
    ],
    "wof:name":"All Pro Off Road",
    "wof:placetype":"venue"
},
  "geometry": {"coordinates":[-116.98045500000001,33.754959],"type":"Point"}
}