{
  "type": "Feature",
  "properties": {
    "addr:full":"8543 Mulberry Ave Fontana CA 92335",
    "addr:housenumber":"8543",
    "addr:postcode":"92335",
    "addr:street":"Mulberry Ave",
    "iso:country":"US",
    "sg:address":"8543 Mulberry Ave",
    "sg:city":"Fontana",
    "sg:classifiers":[
        {
            "category":"Professional",
            "type":"Services"
        }
    ],
    "sg:phone":"+1 909 350 2054",
    "sg:postcode":"92335",
    "sg:province":"CA",
    "wof:name":"Catalina Structures",
    "wof:placetype":"venue"
},
  "geometry": {"coordinates":[-117.50614400000001,34.095275],"type":"Point"}
}