{
  "type": "Feature",
  "properties": {
    "addr:full":"2085 Winchester Blvd Campbell CA 95008",
    "addr:housenumber":"2085",
    "addr:postcode":"95008",
    "addr:street":"Winchester Blvd",
    "iso:country":"US",
    "sg:address":"2085 Winchester Blvd",
    "sg:city":"Campbell",
    "sg:classifiers":[
        {
            "category":"Personal",
            "subcategory":"Shoe Repair & Shine",
            "type":"Services"
        }
    ],
    "sg:phone":"+1 408 378 2352",
    "sg:postcode":"95008",
    "sg:province":"CA",
    "sg:website":"www.facebook.com/group.php?gid=2...",
    "wof:name":"Willie's Shoe Repair",
    "wof:placetype":"venue"
},
  "geometry": {"coordinates":[-121.949862,37.286146],"type":"Point"}
}