{
  "type": "Feature",
  "properties": {
    "iso:country":"US",
    "sg:address":"3645 Inglewood Ave",
    "sg:city":"Redondo Beach",
    "sg:classifiers":[
        {
            "category":"Shopping",
            "subcategory":"Florist",
            "type":"Retail Goods"
        }
    ],
    "sg:phone":"+1 310 536 0008",
    "sg:postcode":"90278",
    "sg:province":"CA",
    "sg:tags":[
        "flower",
        "wedding"
    ],
    "wof:name":"Ava's Garden",
    "wof:placetype":"venue"
},
  "geometry": {"coordinates":[-118.3614,33.888018],"type":"Point"}
}