{
  "type": "Feature",
  "properties": {
    "iso:country":"US",
    "sg:address":"6707 Sampson Rd",
    "sg:city":"Stockton",
    "sg:classifiers":[
        {
            "category":"Shopping",
            "type":"Retail Goods"
        }
    ],
    "sg:phone":"+1 209 957 9195",
    "sg:postcode":"95212",
    "sg:province":"CA",
    "sg:tags":[
        "telephone",
        "cellular"
    ],
    "wof:name":"Radio Shack",
    "wof:placetype":"venue"
},
  "geometry": {"coordinates":[-121.267821,38.019545],"type":"Point"}
}