{
  "type": "Feature",
  "properties": {
    "iso:country":"US",
    "sg:address":"765 N Dodsworth Ave",
    "sg:city":"Covina",
    "sg:classifiers":[
        {
            "category":"Manufacturing",
            "subcategory":"Toys & Sporting Goods",
            "type":"Manufacturing & Wholesale Goods"
        }
    ],
    "sg:phone":"+1 626 967 1351",
    "sg:postcode":"91724",
    "sg:province":"CA",
    "sg:tags":[
        "water",
        "product",
        "mfg",
        "skiing"
    ],
    "wof:name":"Ski-Seat Water Sport Inds",
    "wof:placetype":"venue"
},
  "geometry": {"coordinates":[-117.86934,34.09492],"type":"Point"}
}