{
  "type": "Feature",
  "properties": {
    "addr:full":"957 Channing Ave Palo Alto CA 94301",
    "addr:housenumber":"957",
    "addr:postcode":"94301",
    "addr:street":"Channing Ave",
    "iso:country":"US",
    "sg:address":"957 Channing Ave",
    "sg:city":"Palo Alto",
    "sg:classifiers":[
        {
            "category":"Building & Trades",
            "subcategory":"Construction",
            "type":"Services"
        }
    ],
    "sg:phone":"+1 650 326 6885",
    "sg:postcode":"94301",
    "sg:province":"CA",
    "sg:tags":[
        "fiber",
        "optics"
    ],
    "wof:name":"Logilight",
    "wof:placetype":"venue"
},
  "geometry": {"coordinates":[-122.14788,37.448844],"type":"Point"}
}