{
  "type": "Feature",
  "properties": {
    "addr:full":"202 N Plumas St Willows CA 95988",
    "addr:housenumber":"202",
    "addr:postcode":"95988",
    "addr:street":"N Plumas St",
    "iso:country":"US",
    "sg:address":"202 N Plumas St",
    "sg:city":"Willows",
    "sg:classifiers":[
        {
            "category":"Place Of Worship",
            "subcategory":"Church",
            "type":"Public Place"
        },
        {
            "category":"Place Of Worship",
            "type":"Public Place"
        }
    ],
    "sg:phone":"+1 530 934 9109",
    "sg:postcode":"95988",
    "sg:province":"CA",
    "sg:tags":[
        "churches-pentecostal-independent",
        "churches-pentecostal"
    ],
    "wof:name":"Life Harvest Church",
    "wof:placetype":"venue"
},
  "geometry": {"coordinates":[-122.19822000000001,39.521866],"type":"Point"}
}