{
  "type": "Feature",
  "properties": {
    "iso:country":"US",
    "sg:address":"1836 Elkwood Dr",
    "sg:city":"Concord",
    "sg:classifiers":[
        {
            "category":"Communications",
            "type":"Services"
        }
    ],
    "sg:phone":"+1 925 429 1850",
    "sg:postcode":"94519",
    "sg:province":"CA",
    "wof:name":"Forward Health Communications",
    "wof:placetype":"venue"
},
  "geometry": {"coordinates":[-121.997995,37.988361],"type":"Point"}
}