{
  "type": "Feature",
  "properties": {
    "iso:country":"US",
    "sg:address":"610 E Virginia Ave",
    "sg:city":"Glendora",
    "sg:classifiers":[
        {
            "category":"Recreation",
            "type":"Entertainment"
        }
    ],
    "sg:phone":"+1 626 914 6156",
    "sg:postcode":"91741",
    "sg:province":"CA",
    "sg:tags":[
        "club",
        "membership"
    ],
    "wof:name":"Glendora America Little League",
    "wof:placetype":"venue"
},
  "geometry": {"coordinates":[-117.856004,34.145073],"type":"Point"}
}