{
  "type": "Feature",
  "properties": {
    "addr:full":"916 Santee Street Los Angeles CA 90015",
    "addr:housenumber":"916",
    "addr:postcode":"90015",
    "addr:street":"Santee Street",
    "iso:country":"US",
    "sg:address":"916 Santee Street",
    "sg:city":"Los Angeles",
    "sg:classifiers":[
        {
            "category":"Shopping",
            "subcategory":"Clothing, Apparel, & Fashions",
            "type":"Retail Goods"
        }
    ],
    "sg:phone":"+1 213 624 0240",
    "sg:postcode":"90015",
    "sg:province":"CA",
    "sg:tags":[
        "accessory",
        "clothing",
        "women's"
    ],
    "wof:name":"Ethos",
    "wof:placetype":"venue"
},
  "geometry": {"coordinates":[-118.25386899999999,34.039823],"type":"Point"}
}