{
  "type": "Feature",
  "properties": {
    "iso:country":"US",
    "sg:address":"167 Cam Dorado",
    "sg:city":"Napa",
    "sg:classifiers":[
        {
            "category":"Real Estate",
            "subcategory":"Real Estate Agent",
            "type":"Services"
        }
    ],
    "sg:phone":"+1 707 253 2277",
    "sg:postcode":"94558",
    "sg:province":"CA",
    "sg:tags":[
        "appraiser"
    ],
    "wof:name":"Commercial Development Cnsltng",
    "wof:placetype":"venue"
},
  "geometry": {"coordinates":[-122.256907,38.229283],"type":"Point"}
}