{
  "type": "Feature",
  "properties": {
    "iso:country":"US",
    "sg:address":"13717 Victory Blvd",
    "sg:city":"Van Nuys",
    "sg:classifiers":[
        {
            "category":"Shopping",
            "subcategory":"Clothing, Apparel, & Fashions",
            "type":"Retail Goods"
        }
    ],
    "sg:phone":"+1 818 782 2141",
    "sg:postcode":"91401",
    "sg:province":"CA",
    "sg:tags":[
        "jean"
    ],
    "wof:name":"Jean 4 Us Discount Store",
    "wof:placetype":"venue"
},
  "geometry": {"coordinates":[-118.43204799999999,34.186742],"type":"Point"}
}