{
  "type": "Feature",
  "properties": {
    "addr:full":"2344 Tulare St Fresno CA 93706",
    "addr:housenumber":"2344",
    "addr:postcode":"93706",
    "addr:street":"Tulare St",
    "iso:country":"US",
    "sg:address":"2344 Tulare St",
    "sg:city":"Fresno",
    "sg:classifiers":[
        {
            "category":"Government",
            "subcategory":"Office",
            "type":"Public Place"
        }
    ],
    "sg:phone":"+1 559 498 1885",
    "sg:postcode":"93706",
    "sg:province":"CA",
    "sg:tags":[
        "city",
        "planning",
        "dev"
    ],
    "wof:name":"Fresno City Redevelopment Agy",
    "wof:placetype":"venue"
},
  "geometry": {"coordinates":[-119.78641,36.73643],"type":"Point"}
}