{
  "type": "Feature",
  "properties": {
    "iso:country":"US",
    "sg:address":"3150 E Imperial Hwy",
    "sg:city":"Lynwood",
    "sg:classifiers":[
        {
            "category":"Health Services",
            "subcategory":"Dentist",
            "type":"Services"
        }
    ],
    "sg:phone":"+1 310 608 7777",
    "sg:postcode":"90262",
    "sg:province":"CA",
    "sg:tags":[
        "clinic",
        "dental"
    ],
    "sg:website":"www.pacificsmilesdental.com",
    "wof:name":"Pacific Smiles Dental Center",
    "wof:placetype":"venue"
},
  "geometry": {"coordinates":[-118.214651,33.930263],"type":"Point"}
}