{
  "type": "Feature",
  "properties": {
    "iso:country":"US",
    "sg:address":"8450 Valley Blvd Ste 110",
    "sg:city":"Rosemead",
    "sg:classifiers":[
        {
            "category":"Health Services",
            "subcategory":"Optometrist",
            "type":"Services"
        }
    ],
    "sg:phone":"+1 626 280 6212",
    "sg:postcode":"91770",
    "sg:province":"CA",
    "wof:name":"Envue Optometry",
    "wof:placetype":"venue"
},
  "geometry": {"coordinates":[-118.083,34.080399],"type":"Point"}
}