{
  "type": "Feature",
  "properties": {
    "addr:full":"16990 Main St Hesperia CA 92345",
    "addr:housenumber":"16990",
    "addr:postcode":"92345",
    "addr:street":"Main St",
    "iso:country":"US",
    "sg:address":"16990 Main St",
    "sg:city":"Hesperia",
    "sg:classifiers":[
        {
            "category":"Personal",
            "subcategory":"Barber",
            "type":"Services"
        }
    ],
    "sg:phone":"+1 760 244 5744",
    "sg:postcode":"92345",
    "sg:province":"CA",
    "wof:name":"Fox Barbers",
    "wof:placetype":"venue"
},
  "geometry": {"coordinates":[-117.292227,34.420247],"type":"Point"}
}