{
  "type": "Feature",
  "properties": {
    "iso:country":"US",
    "sg:address":"22470 Foothill Blvd",
    "sg:city":"Hayward",
    "sg:classifiers":[
        {
            "category":"Real Estate",
            "subcategory":"Real Estate Agent",
            "type":"Services"
        }
    ],
    "sg:phone":"+1 510 581 4466",
    "sg:postcode":"94541",
    "sg:province":"CA",
    "sg:tags":[
        "consultant"
    ],
    "wof:name":"Tmw Commerce Com",
    "wof:placetype":"venue"
},
  "geometry": {"coordinates":[-122.082295,37.675852],"type":"Point"}
}