{
  "type": "Feature",
  "properties": {
    "addr:full":"1914 S Pacific Coast Hwy Suite 100 Redondo Beach CA 90277",
    "addr:housenumber":"1914",
    "addr:postcode":"90277",
    "addr:street":"S Pacific Coast Hwy Suite 100",
    "iso:country":"US",
    "sg:address":"1914 S Pacific Coast Hwy Suite 100",
    "sg:city":"Redondo Beach",
    "sg:classifiers":[
        {
            "category":"Building & Trades",
            "subcategory":"Construction",
            "type":"Services"
        }
    ],
    "sg:phone":"+1 310 316 4621",
    "sg:postcode":"90277",
    "sg:province":"CA",
    "sg:tags":[
        "contractor"
    ],
    "wof:name":"Hoffman Construction",
    "wof:placetype":"venue"
},
  "geometry": {"coordinates":[-118.37918999999999,33.816191],"type":"Point"}
}