{
  "type": "Feature",
  "properties": {
    "addr:full":"1021 N Cypress St La Habra CA 90631",
    "addr:housenumber":"1021",
    "addr:postcode":"90631",
    "addr:street":"N Cypress St",
    "iso:country":"US",
    "sg:address":"1021 N Cypress St",
    "sg:city":"La Habra",
    "sg:classifiers":[
        {
            "category":"Retail",
            "subcategory":"Auto Repair",
            "type":"Services"
        }
    ],
    "sg:phone":"+1 714 525 0871",
    "sg:postcode":"90631",
    "sg:province":"CA",
    "sg:tags":[
        "repairing",
        "automobile"
    ],
    "wof:name":"R & V Complete Auto Repair",
    "wof:placetype":"venue"
},
  "geometry": {"coordinates":[-117.941901,33.94145],"type":"Point"}
}