{
  "type": "Feature",
  "properties": {
    "iso:country":"US",
    "sg:address":"1517 Taraval St",
    "sg:city":"San Francisco",
    "sg:classifiers":[
        {
            "category":"Personal",
            "subcategory":"Beauty Salon",
            "type":"Services"
        }
    ],
    "sg:phone":"+1 415 731 4764",
    "sg:postcode":"94116",
    "sg:province":"CA",
    "sg:tags":[
        "hair"
    ],
    "wof:name":"Fatima's Taraval Hairstylist",
    "wof:placetype":"venue"
},
  "geometry": {"coordinates":[-122.48257700000001,37.742647],"type":"Point"}
}