{
  "type": "Feature",
  "properties": {
    "iso:country":"US",
    "sg:address":"2100 S Santa Fe Ave",
    "sg:city":"Compton",
    "sg:classifiers":[
        {
            "category":"Wholesale",
            "subcategory":"Electrical",
            "type":"Manufacturing & Wholesale Goods"
        }
    ],
    "sg:phone":"+1 310 632 7664",
    "sg:postcode":"90221",
    "sg:province":"CA",
    "sg:tags":[
        "fire",
        "alarm",
        "system"
    ],
    "wof:name":"Right On Smog",
    "wof:placetype":"venue"
},
  "geometry": {"coordinates":[-118.214596,33.874545],"type":"Point"}
}