{
  "type": "Feature",
  "properties": {
    "iso:country":"US",
    "sg:address":"240 E Grand Ave",
    "sg:city":"Escondido",
    "sg:classifiers":[
        {
            "category":"Shopping",
            "subcategory":"Bicycles & Sporting Goods",
            "type":"Retail Goods"
        }
    ],
    "sg:phone":"+1 760 747 5592",
    "sg:postcode":"92025",
    "sg:province":"CA",
    "wof:name":"Escondido BMX Bicycles",
    "wof:placetype":"venue"
},
  "geometry": {"coordinates":[-117.079295,33.122818],"type":"Point"}
}