{
  "type": "Feature",
  "properties": {
    "iso:country":"US",
    "sg:address":"2957 Honolulu Ave",
    "sg:city":"La Crescenta",
    "sg:classifiers":[
        {
            "category":"Professional",
            "subcategory":"Engineering",
            "type":"Services"
        }
    ],
    "sg:phone":"+1 818 248 3281",
    "sg:postcode":"91214",
    "sg:province":"CA",
    "sg:tags":[
        "engineer"
    ],
    "wof:name":"Ronald James Parking Engineers",
    "wof:placetype":"venue"
},
  "geometry": {"coordinates":[-118.24353,34.213688],"type":"Point"}
}