{
  "type": "Feature",
  "properties": {
    "iso:country":"US",
    "sg:address":"4141 N Blythe Ave",
    "sg:city":"Fresno",
    "sg:classifiers":[
        {
            "category":"Real Estate",
            "subcategory":"Real Estate Operator",
            "type":"Services"
        }
    ],
    "sg:phone":"+1 559 276 2206",
    "sg:postcode":"93722",
    "sg:province":"CA",
    "sg:tags":[
        "apartment"
    ],
    "wof:name":"Stonegate Apartments",
    "wof:placetype":"venue"
},
  "geometry": {"coordinates":[-119.87141699999999,36.79431],"type":"Point"}
}