{
  "type": "Feature",
  "properties": {
    "iso:country":"US",
    "sg:address":"2500 N Hollywood Way",
    "sg:city":"Burbank",
    "sg:classifiers":[
        {
            "category":"Arts & Performance",
            "subcategory":"Arts Center",
            "type":"Entertainment"
        }
    ],
    "sg:phone":"+1 951 258 4968",
    "sg:postcode":"91504",
    "sg:province":"CA",
    "sg:tags":[
        "performing"
    ],
    "sg:website":"www.hollywoodshow.com",
    "wof:name":"Hollywood Show",
    "wof:placetype":"venue"
},
  "geometry": {"coordinates":[-118.34698,34.194414],"type":"Point"}
}