{
  "type": "Feature",
  "properties": {
    "iso:country":"US",
    "sg:address":"1030 Curtis St",
    "sg:city":"Menlo Park",
    "sg:classifiers":[
        {
            "category":"Local Transit",
            "type":"Transportation"
        }
    ],
    "sg:phone":"+1 650 327 4400",
    "sg:postcode":"94025",
    "sg:province":"CA",
    "sg:tags":[
        "limousine"
    ],
    "wof:name":"Chariot Limousine",
    "wof:placetype":"venue"
},
  "geometry": {"coordinates":[-122.183677,37.452071],"type":"Point"}
}