{
  "type": "Feature",
  "properties": {
    "iso:country":"US",
    "sg:address":"11111 Wilmington Avenue",
    "sg:city":"Los Angeles",
    "sg:classifiers":[
        {
            "category":"Restaurant",
            "type":"Food & Drink"
        }
    ],
    "sg:phone":"+1 323 563 3310",
    "sg:postcode":"90059",
    "sg:province":"CA",
    "wof:name":"El Pollo Macho",
    "wof:placetype":"venue"
},
  "geometry": {"coordinates":[-118.238877,33.933746],"type":"Point"}
}