{
  "type": "Feature",
  "properties": {
    "iso:country":"US",
    "sg:address":"18017 Sky Park Cir Ste M",
    "sg:city":"Irvine",
    "sg:classifiers":[
        {
            "category":"Shopping",
            "subcategory":"Jewelry",
            "type":"Retail Goods"
        }
    ],
    "sg:phone":"+1 949 387 6222",
    "sg:postcode":"92614",
    "sg:province":"CA",
    "sg:website":"www.cynthiahdesigns.com",
    "wof:name":"Cynthia H Designs",
    "wof:placetype":"venue"
},
  "geometry": {"coordinates":[-117.85677699999999,33.68771],"type":"Point"}
}