{
  "type": "Feature",
  "properties": {
    "addr:full":"25 Zoe St San Francisco CA 94107",
    "addr:housenumber":"25",
    "addr:postcode":"94107",
    "addr:street":"Zoe St",
    "iso:country":"US",
    "sg:address":"25 Zoe St",
    "sg:city":"San Francisco",
    "sg:classifiers":[
        {
            "category":"Professional",
            "subcategory":"Art Services",
            "type":"Services"
        }
    ],
    "sg:phone":"+1 415 777 2492",
    "sg:postcode":"94107",
    "sg:province":"CA",
    "sg:tags":[
        "graphic",
        "designer"
    ],
    "sg:website":"www.corsondesign.com",
    "wof:name":"Madeleine Corson Design Office",
    "wof:placetype":"venue"
},
  "geometry": {"coordinates":[-122.39659399999999,37.780494],"type":"Point"}
}