{
  "type": "Feature",
  "properties": {
    "iso:country":"US",
    "sg:address":"43164 Corte Montilla",
    "sg:city":"Temecula",
    "sg:classifiers":[
        {
            "category":"Social Services",
            "subcategory":"Child Care",
            "type":"Services"
        }
    ],
    "sg:phone":"+1 951 303 2379",
    "sg:postcode":"92592",
    "sg:province":"CA",
    "sg:tags":[
        "diaper"
    ],
    "wof:name":"Dream Diaper",
    "wof:placetype":"venue"
},
  "geometry": {"coordinates":[-117.11195499999999,33.495443],"type":"Point"}
}