{
  "type": "Feature",
  "properties": {
    "iso:country":"US",
    "sg:address":"3877 Finley Ave",
    "sg:city":"Santa Rosa",
    "sg:classifiers":[
        {
            "category":"Retail",
            "subcategory":"Repair Shop",
            "type":"Services"
        }
    ],
    "sg:phone":"+1 707 541 0492",
    "sg:postcode":"95407",
    "sg:province":"CA",
    "sg:tags":[
        "crane",
        "testing"
    ],
    "wof:name":"Resolute Certification Co",
    "wof:placetype":"venue"
},
  "geometry": {"coordinates":[-122.763428,38.420283],"type":"Point"}
}