{
  "type": "Feature",
  "properties": {
    "addr:full":"11725 Santa Monica Blvd Los Angeles CA 90025",
    "addr:housenumber":"11725",
    "addr:postcode":"90025",
    "addr:street":"Santa Monica Blvd",
    "iso:country":"US",
    "sg:address":"11725 Santa Monica Blvd",
    "sg:city":"Los Angeles",
    "sg:classifiers":[
        {
            "category":"Retail",
            "subcategory":"Auto Rental",
            "type":"Services"
        }
    ],
    "sg:phone":"+1 310 477 8080",
    "sg:postcode":"90025",
    "sg:province":"CA",
    "sg:tags":[
        "renting",
        "automobile"
    ],
    "wof:name":"California Rent A Car",
    "wof:placetype":"venue"
},
  "geometry": {"coordinates":[-118.45647599999999,34.043706],"type":"Point"}
}