{
  "type": "Feature",
  "properties": {
    "iso:country":"US",
    "sg:address":"4164 Brockton Ave",
    "sg:city":"Riverside",
    "sg:classifiers":[
        {
            "category":"Organizations",
            "subcategory":"Non-profit Organization",
            "type":"Services"
        }
    ],
    "sg:phone":"+1 951 683 5193",
    "sg:postcode":"92501",
    "sg:province":"CA",
    "sg:tags":[
        "info",
        "addiction",
        "abuse",
        "treatment",
        "drug"
    ],
    "wof:name":"Youth Service Ctr",
    "wof:placetype":"venue"
},
  "geometry": {"coordinates":[-117.381326,33.980858],"type":"Point"}
}