{
  "type": "Feature",
  "properties": {
    "iso:country":"US",
    "sg:address":"1333 W 145th Pl",
    "sg:city":"Gardena",
    "sg:classifiers":[
        {
            "category":"Insurance",
            "subcategory":"Hazard Insurance",
            "type":"Services"
        }
    ],
    "sg:phone":"+1 310 225 5673",
    "sg:postcode":"90247",
    "sg:province":"CA",
    "sg:tags":[
        "commercial",
        "business"
    ],
    "wof:name":"Nishisaka Insurance",
    "wof:placetype":"venue"
},
  "geometry": {"coordinates":[-118.298974,33.899665],"type":"Point"}
}