{
  "type": "Feature",
  "properties": {
    "addr:full":"3655 Fillmore St San Francisco CA 94123",
    "addr:housenumber":"3655",
    "addr:postcode":"94123",
    "addr:street":"Fillmore St",
    "iso:country":"US",
    "sg:address":"3655 Fillmore St",
    "sg:city":"San Francisco",
    "sg:classifiers":[
        {
            "category":"Health Services",
            "subcategory":"Clinic",
            "type":"Services"
        },
        {
            "category":"Personal",
            "type":"Services"
        }
    ],
    "sg:phone":"+1 888 444 6984",
    "sg:postcode":"94123",
    "sg:province":"CA",
    "sg:tags":[
        "home",
        "medical"
    ],
    "wof:name":"Canopy Home Care",
    "wof:placetype":"venue"
},
  "geometry": {"coordinates":[-122.43717700000001,37.803799],"type":"Point"}
}