{
  "type": "Feature",
  "properties": {
    "iso:country":"US",
    "sg:address":"10910 Elm Ave",
    "sg:city":"Fontana",
    "sg:classifiers":[
        {
            "category":"Wholesale",
            "subcategory":"Construction Materials",
            "type":"Manufacturing & Wholesale Goods"
        }
    ],
    "sg:phone":"+1 909 355 6500",
    "sg:postcode":"92337",
    "sg:province":"CA",
    "sg:tags":[
        "hydraulic",
        "cement",
        "mfg"
    ],
    "wof:name":"Hardie James Building Products",
    "wof:placetype":"venue"
},
  "geometry": {"coordinates":[-117.466994,34.048381],"type":"Point"}
}