{
  "type": "Feature",
  "properties": {
    "addr:full":"660 San Felipe Rd Hollister CA 95023",
    "addr:housenumber":"660",
    "addr:postcode":"hollister ca 95023",
    "addr:street":"San Felipe Rd",
    "iso:country":"US",
    "sg:address":"660 San Felipe Rd",
    "sg:city":"Hollister",
    "sg:classifiers":[
        {
            "category":"Travel",
            "subcategory":"Hotels & Motels",
            "type":"Entertainment"
        }
    ],
    "sg:phone":"+1 831 637 9248",
    "sg:postcode":"95023",
    "sg:province":"CA",
    "wof:name":"Best Western Inn",
    "wof:placetype":"venue"
},
  "geometry": {"coordinates":[-121.40145200000001,36.866307],"type":"Point"}
}