{
  "type": "Feature",
  "properties": {
    "iso:country":"US",
    "sg:address":"1117 Lone Palm Ave",
    "sg:city":"Modesto",
    "sg:classifiers":[
        {
            "category":"Professional",
            "subcategory":"Engineering",
            "type":"Services"
        },
        {
            "category":"Building & Trades",
            "subcategory":"Electrical",
            "type":"Services"
        },
        {
            "category":"Professional",
            "subcategory":"Management & Consulting",
            "type":"Services"
        }
    ],
    "sg:phone":"+1 209 579 2221",
    "sg:postcode":"95351",
    "sg:province":"CA",
    "sg:tags":[
        "control",
        "consultant",
        "system",
        "controls",
        "regulator",
        "environmental",
        "ecological",
        "engineer"
    ],
    "sg:website":"http://www.atcassociates.com",
    "wof:name":"A T C Associates",
    "wof:placetype":"venue"
},
  "geometry": {"coordinates":[-121.02340700000001,37.650476],"type":"Point"}
}