{
  "type": "Feature",
  "properties": {
    "iso:country":"US",
    "sg:address":"18 Victor Sq",
    "sg:city":"Scotts Valley",
    "sg:classifiers":[
        {
            "category":"Banks & Credit Unions",
            "subcategory":"Bank",
            "type":"Services"
        }
    ],
    "sg:phone":"+1 831 438 7130",
    "sg:postcode":"95066",
    "sg:province":"CA",
    "sg:tags":[
        "loan"
    ],
    "wof:name":"Mountain Coast Properties",
    "wof:placetype":"venue"
},
  "geometry": {"coordinates":[-122.006484,37.060236],"type":"Point"}
}