{
  "type": "Feature",
  "properties": {
    "iso:country":"US",
    "sg:address":"1660 Mission St",
    "sg:city":"San Francisco",
    "sg:classifiers":[
        {
            "category":"Government",
            "subcategory":"Office",
            "type":"Public Place"
        }
    ],
    "sg:phone":"+1 415 558 6096",
    "sg:postcode":"94103",
    "sg:province":"CA",
    "sg:tags":[
        "development",
        "urban",
        "housing",
        "program",
        "community"
    ],
    "wof:name":"Bldg Inspection Dept",
    "wof:placetype":"venue"
},
  "geometry": {"coordinates":[-122.419399,37.771625],"type":"Point"}
}