{
  "type": "Feature",
  "properties": {
    "addr:full":"683 Harrow Ave San Mateo CA 94402",
    "addr:housenumber":"683",
    "addr:postcode":"94402",
    "addr:street":"Harrow Ave",
    "iso:country":"US",
    "sg:address":"683 Harrow Ave",
    "sg:city":"San Mateo",
    "sg:classifiers":[
        {
            "category":"Professional",
            "subcategory":"Computer Services",
            "type":"Services"
        }
    ],
    "sg:phone":"+1 650 458 8403",
    "sg:postcode":"94402",
    "sg:province":"CA",
    "sg:tags":[
        "home",
        "consulting",
        "page",
        "dev",
        "internet"
    ],
    "wof:name":"WEBB Technologies",
    "wof:placetype":"venue"
},
  "geometry": {"coordinates":[-122.310779,37.560199],"type":"Point"}
}