{
  "type": "Feature",
  "properties": {
    "iso:country":"US",
    "sg:address":"621 Montara Rd",
    "sg:city":"Barstow",
    "sg:classifiers":[
        {
            "category":"Utilities",
            "subcategory":"Mobile Phone",
            "type":"Services"
        }
    ],
    "sg:phone":"+1 760 252 5460",
    "sg:postcode":"92311",
    "sg:province":"CA",
    "sg:tags":[
        "communication",
        "radiotelephone"
    ],
    "wof:name":"AT&T Wireless",
    "wof:placetype":"venue"
},
  "geometry": {"coordinates":[-116.9937,34.88164],"type":"Point"}
}