{
  "type": "Feature",
  "properties": {
    "iso:country":"US",
    "sg:address":"487 Saratoga Ave",
    "sg:city":"San Jose",
    "sg:classifiers":[
        {
            "category":"Restaurant",
            "type":"Food & Drink"
        }
    ],
    "sg:phone":"+1 408 557 8799",
    "sg:postcode":"95129",
    "sg:province":"CA",
    "sg:tags":[
        "japanese"
    ],
    "sg:website":"ramentenma.com/RamenTenma/Welcom...",
    "wof:name":"Ramen Tenma",
    "wof:placetype":"venue"
},
  "geometry": {"coordinates":[-121.973809,37.318709],"type":"Point"}
}