{
  "type": "Feature",
  "properties": {
    "iso:country":"US",
    "sg:address":"2532 N Marks Ave",
    "sg:city":"Fresno",
    "sg:classifiers":[
        {
            "category":"Recreation",
            "type":"Entertainment"
        }
    ],
    "sg:phone":"+1 559 275 9597",
    "sg:postcode":"93722",
    "sg:province":"CA",
    "sg:tags":[
        "hall",
        "auditorium"
    ],
    "wof:name":"Verdi Club",
    "wof:placetype":"venue"
},
  "geometry": {"coordinates":[-119.84426,36.773158],"type":"Point"}
}