{
  "type": "Feature",
  "properties": {
    "iso:country":"US",
    "sg:address":"1643 84th Ave",
    "sg:city":"Oakland",
    "sg:classifiers":[
        {
            "category":"Personal",
            "subcategory":"Beauty Salon",
            "type":"Services"
        }
    ],
    "sg:phone":"+1 510 639 4489",
    "sg:postcode":"94621",
    "sg:province":"CA",
    "wof:name":"Salon De Von",
    "wof:placetype":"venue"
},
  "geometry": {"coordinates":[-122.175286,37.755689],"type":"Point"}
}