{
  "type": "Feature",
  "properties": {
    "iso:country":"US",
    "sg:address":"5900 S Eastern Ave",
    "sg:city":"Los Angeles",
    "sg:classifiers":[
        {
            "category":"Social Services",
            "subcategory":"Adult Care",
            "type":"Services"
        }
    ],
    "sg:phone":"+1 323 278 6501",
    "sg:postcode":"90040",
    "sg:province":"CA",
    "sg:tags":[
        "residential",
        "foster"
    ],
    "wof:name":"Hanna's Childrens Home",
    "wof:placetype":"venue"
},
  "geometry": {"coordinates":[-118.162071,33.985157],"type":"Point"}
}