{
  "type": "Feature",
  "properties": {
    "iso:country":"US",
    "sg:address":"790 S Atlantic Blvd Ste 105",
    "sg:city":"Monterey Park",
    "sg:classifiers":[
        {
            "category":"Health Services",
            "subcategory":"Optometrist",
            "type":"Services"
        }
    ],
    "sg:phone":"+1 626 458 6017",
    "sg:postcode":"91754",
    "sg:province":"CA",
    "wof:name":"Clear Sight Optometry Corp",
    "wof:placetype":"venue"
},
  "geometry": {"coordinates":[-118.13707599999999,34.220794],"type":"Point"}
}