{
  "type": "Feature",
  "properties": {
    "addr:full":"350 Fox Hills Mall Culver City CA 90230",
    "addr:housenumber":"350",
    "addr:postcode":"90230",
    "addr:street":"Fox Hills Mall",
    "iso:country":"US",
    "sg:address":"350 Fox Hills Mall",
    "sg:city":"Culver City",
    "sg:classifiers":[
        {
            "category":"Restaurant",
            "type":"Food & Drink"
        }
    ],
    "sg:phone":"+1 310 397 9056",
    "sg:postcode":"90230",
    "sg:province":"CA",
    "sg:tags":[
        "italian"
    ],
    "wof:name":"Sbarro the Italian Eatery",
    "wof:placetype":"venue"
},
  "geometry": {"coordinates":[-118.395168,33.985656],"type":"Point"}
}