{
  "type": "Feature",
  "properties": {
    "iso:country":"US",
    "sg:address":"18410 Ventura Blvd",
    "sg:city":"Tarzana",
    "sg:classifiers":[
        {
            "category":"Shopping",
            "subcategory":"Gifts & Souvenirs",
            "type":"Retail Goods"
        },
        {
            "category":"Shopping",
            "subcategory":"Jewelry",
            "type":"Retail Goods"
        },
        {
            "category":"Manufacturing",
            "subcategory":"Jewelry",
            "type":"Manufacturing & Wholesale Goods"
        },
        {
            "category":"Retail",
            "subcategory":"Repair Shop",
            "type":"Services"
        }
    ],
    "sg:phone":"+1 818 881 4653",
    "sg:postcode":"91356",
    "sg:province":"CA",
    "sg:tags":[
        "repairing",
        "platinum",
        "stamping",
        "gold",
        "watch",
        "jeweler",
        "buyer",
        "silver"
    ],
    "sg:website":"http://www.darvajewelers.com",
    "wof:name":"Darva Jewelers",
    "wof:placetype":"venue"
},
  "geometry": {"coordinates":[-118.533939,34.16793],"type":"Point"}
}