{
  "type": "Feature",
  "properties": {
    "iso:country":"US",
    "sg:address":"7221 Heather Tree Dr",
    "sg:city":"Sacramento",
    "sg:classifiers":[
        {
            "category":"Wholesale",
            "subcategory":"Stationery",
            "type":"Manufacturing & Wholesale Goods"
        }
    ],
    "sg:phone":"+1 916 992 6433",
    "sg:postcode":"95842",
    "sg:province":"CA",
    "sg:tags":[
        "business",
        "form",
        "system"
    ],
    "wof:name":"Corporate Forms Management",
    "wof:placetype":"venue"
},
  "geometry": {"coordinates":[-121.359083,38.69702],"type":"Point"}
}