{
  "type": "Feature",
  "properties": {
    "iso:country":"US",
    "sg:address":"1800 Charm Way",
    "sg:city":"Sacramento",
    "sg:classifiers":[
        {
            "category":"Professional",
            "type":"Services"
        }
    ],
    "sg:phone":"+1 916 928 8013",
    "sg:postcode":"95835",
    "sg:province":"CA",
    "sg:tags":[
        "establishment"
    ],
    "wof:name":"Califorina Boilers",
    "wof:placetype":"venue"
},
  "geometry": {"coordinates":[-121.500388,38.678985],"type":"Point"}
}