{
  "type": "Feature",
  "properties": {
    "addr:full":"10865 Merritt St Castroville CA 95012",
    "addr:housenumber":"10865",
    "addr:postcode":"95012",
    "addr:street":"Merritt St",
    "iso:country":"US",
    "sg:address":"10865 Merritt St",
    "sg:city":"Castroville",
    "sg:classifiers":[
        {
            "category":"Wholesale",
            "subcategory":"Auto Parts",
            "type":"Manufacturing & Wholesale Goods"
        }
    ],
    "sg:phone":"+1 831 633 2431",
    "sg:postcode":"95012",
    "sg:province":"CA",
    "sg:tags":[
        "automobile",
        "supply"
    ],
    "wof:name":"Pettigrew & Foletta Auto Parts",
    "wof:placetype":"venue"
},
  "geometry": {"coordinates":[-121.756781,36.764872],"type":"Point"}
}