{
  "type": "Feature",
  "properties": {
    "iso:country":"US",
    "sg:address":"2000 Rockwood Dr",
    "sg:city":"Sacramento",
    "sg:classifiers":[
        {
            "category":"Restaurant",
            "type":"Food & Drink"
        }
    ],
    "sg:phone":"+1 916 971 1411",
    "sg:postcode":"95864",
    "sg:province":"CA",
    "sg:tags":[
        "caterer"
    ],
    "wof:name":"Nancy's Quisine",
    "wof:placetype":"venue"
},
  "geometry": {"coordinates":[-121.374,38.60165],"type":"Point"}
}