{
  "type": "Feature",
  "properties": {
    "addr:full":"3307 Los Olivos Ln La Crescenta CA 91214",
    "addr:housenumber":"3307",
    "addr:postcode":"91214",
    "addr:street":"Los Olivos Ln",
    "iso:country":"US",
    "sg:address":"3307 Los Olivos Ln",
    "sg:city":"La Crescenta",
    "sg:classifiers":[
        {
            "category":"Building & Trades",
            "subcategory":"Plumbing",
            "type":"Services"
        }
    ],
    "sg:phone":"+1 818 248 1284",
    "sg:postcode":"91214",
    "sg:province":"CA",
    "sg:tags":[
        "contractor"
    ],
    "wof:name":"Raz Cool Air Conditioning",
    "wof:placetype":"venue"
},
  "geometry": {"coordinates":[-118.25284499999999,34.235875],"type":"Point"}
}