{
  "type": "Feature",
  "properties": {
    "addr:full":"29926 Rolling Ridge Dr Agoura Hills CA 91301",
    "addr:housenumber":"29926",
    "addr:postcode":"91301",
    "addr:street":"Rolling Ridge Dr",
    "iso:country":"US",
    "sg:address":"29926 Rolling Ridge Dr",
    "sg:city":"Agoura Hills",
    "sg:classifiers":[
        {
            "category":"Professional",
            "type":"Services"
        }
    ],
    "sg:phone":"+1 818 889 4347",
    "sg:postcode":"91301",
    "sg:province":"CA",
    "wof:name":"James McGinnes",
    "wof:placetype":"venue"
},
  "geometry": {"coordinates":[-118.775104,34.159055],"type":"Point"}
}