{
  "type": "Feature",
  "properties": {
    "addr:full":"3022 Stockton Blvd Ste 5 Sacramento CA 95820",
    "addr:housenumber":"3022",
    "addr:postcode":"95820",
    "addr:street":"Stockton Blvd Ste 5",
    "iso:country":"US",
    "sg:address":"3022 Stockton Blvd Ste 5",
    "sg:city":"Sacramento",
    "sg:classifiers":[
        {
            "category":"Insurance",
            "subcategory":"Hazard Insurance",
            "type":"Services"
        }
    ],
    "sg:phone":"+1 916 454 4495",
    "sg:postcode":"95820",
    "sg:province":"CA",
    "sg:tags":[
        "commercial",
        "business"
    ],
    "wof:name":"Apna Insurance Agency",
    "wof:placetype":"venue"
},
  "geometry": {"coordinates":[-121.454002,38.5466],"type":"Point"}
}