{
  "type": "Feature",
  "properties": {
    "addr:full":"2601 E Chapman Ave Orange CA 92869",
    "addr:housenumber":"2601",
    "addr:postcode":"92869",
    "addr:street":"E Chapman Ave",
    "iso:country":"US",
    "sg:address":"2601 E Chapman Ave",
    "sg:city":"Orange",
    "sg:classifiers":[
        {
            "category":"Health Services",
            "subcategory":"Doctor",
            "type":"Services"
        }
    ],
    "sg:phone":"+1 714 639 5117",
    "sg:postcode":"92869",
    "sg:province":"CA",
    "sg:tags":[
        "physician",
        "surgeon"
    ],
    "wof:name":"Gregory B Barnes MD",
    "wof:placetype":"venue"
},
  "geometry": {"coordinates":[-117.823379,33.7878],"type":"Point"}
}