{
  "type": "Feature",
  "properties": {
    "iso:country":"US",
    "sg:address":"248 W Gainsborough Rd",
    "sg:city":"Thousand Oaks",
    "sg:classifiers":[
        {
            "category":"Real Estate",
            "subcategory":"Developer",
            "type":"Services"
        }
    ],
    "sg:phone":"+1 805 373 9976",
    "sg:postcode":"91360",
    "sg:province":"CA",
    "wof:name":"Main St Development",
    "wof:placetype":"venue"
},
  "geometry": {"coordinates":[-118.882835,34.196642],"type":"Point"}
}