{
  "type": "Feature",
  "properties": {
    "addr:full":"7576 Creighton Ct Fontana CA 92336",
    "addr:housenumber":"7576",
    "addr:postcode":"92336",
    "addr:street":"Creighton Ct",
    "iso:country":"US",
    "sg:address":"7576 Creighton Ct",
    "sg:city":"Fontana",
    "sg:classifiers":[
        {
            "category":"Freight",
            "type":"Transportation"
        }
    ],
    "sg:phone":"+1 909 822 8875",
    "sg:postcode":"92336",
    "sg:province":"CA",
    "wof:name":"Style Transportation",
    "wof:placetype":"venue"
},
  "geometry": {"coordinates":[-117.41091,34.116008],"type":"Point"}
}