{
  "type": "Feature",
  "properties": {
    "iso:country":"US",
    "sg:address":"1639 Monrovia Ave",
    "sg:city":"Costa Mesa",
    "sg:classifiers":[
        {
            "category":"Building & Trades",
            "subcategory":"Construction",
            "type":"Services"
        }
    ],
    "sg:phone":"+1 949 554 0880",
    "sg:postcode":"92627",
    "sg:province":"CA",
    "sg:tags":[
        "handyman"
    ],
    "wof:name":"Andy's Handyman",
    "wof:placetype":"venue"
},
  "geometry": {"coordinates":[-117.935997,33.6339],"type":"Point"}
}