{
  "type": "Feature",
  "properties": {
    "iso:country":"US",
    "sg:address":"6256 Greenwich Dr",
    "sg:city":"San Diego",
    "sg:classifiers":[
        {
            "category":"Professional",
            "subcategory":"Management & Consulting",
            "type":"Services"
        }
    ],
    "sg:phone":"+1 858 450 7661",
    "sg:postcode":"92122",
    "sg:province":"CA",
    "sg:tags":[
        "association"
    ],
    "wof:name":"Merit Property Management",
    "wof:placetype":"venue"
},
  "geometry": {"coordinates":[-117.18448100000001,32.85401],"type":"Point"}
}