{
  "type": "Feature",
  "properties": {
    "addr:full":"115 Washington Blvd Roseville CA 95678",
    "addr:housenumber":"115",
    "addr:postcode":"95678",
    "addr:street":"Washington Blvd",
    "iso:country":"US",
    "sg:address":"115 Washington Blvd",
    "sg:city":"Roseville",
    "sg:classifiers":[
        {
            "category":"Professional",
            "type":"Services"
        }
    ],
    "sg:phone":"+1 916 786 5424",
    "sg:postcode":"95678",
    "sg:province":"CA",
    "sg:tags":[
        "establishment"
    ],
    "wof:name":"James Hansen & Assoc",
    "wof:placetype":"venue"
},
  "geometry": {"coordinates":[-121.287266,38.751515],"type":"Point"}
}