{
  "type": "Feature",
  "properties": {
    "addr:full":"630 W 6th St Los Angeles CA 90017",
    "addr:housenumber":"630",
    "addr:postcode":"90017",
    "addr:street":"W 6Th St",
    "iso:country":"US",
    "sg:address":"630 W 6th St",
    "sg:city":"Los Angeles",
    "sg:classifiers":[
        {
            "category":"Juice Bar",
            "subcategory":"None",
            "type":"Food & Drink"
        }
    ],
    "sg:phone":"+1 213 489 4136",
    "sg:postcode":"90017",
    "sg:province":"CA",
    "sg:tags":[
        "smoothy"
    ],
    "sg:website":"www.juiceitup.com",
    "wof:name":"Juice It Up",
    "wof:placetype":"venue"
},
  "geometry": {"coordinates":[-118.25609300000001,34.049328],"type":"Point"}
}