{
  "type": "Feature",
  "properties": {
    "addr:full":"839 Howard St San Francisco CA 94103",
    "addr:housenumber":"839",
    "addr:postcode":"94103",
    "addr:street":"Howard St",
    "iso:country":"US",
    "sg:address":"839 Howard St",
    "sg:city":"San Francisco",
    "sg:classifiers":[
        {
            "category":"Retail",
            "subcategory":"Event Space",
            "type":"Services"
        }
    ],
    "sg:phone":"+1 415 543 1275",
    "sg:postcode":"94103",
    "sg:province":"CA",
    "sg:tags":[
        "venue"
    ],
    "sg:website":"www.elan-sf.com",
    "wof:name":"Elan Event Venue",
    "wof:placetype":"venue"
},
  "geometry": {"coordinates":[-122.40360200000001,37.782531],"type":"Point"}
}