{
  "type": "Feature",
  "properties": {
    "iso:country":"US",
    "sg:address":"226 E Elmwood Ave 5",
    "sg:city":"Burbank",
    "sg:classifiers":[
        {
            "category":"Wholesale",
            "subcategory":"Non-durable Goods",
            "type":"Manufacturing & Wholesale Goods"
        }
    ],
    "sg:phone":"+1 818 567 2018",
    "sg:postcode":"91502",
    "sg:province":"CA",
    "sg:tags":[
        "dry",
        "goods-wholesale"
    ],
    "wof:name":"A&D Wholesales",
    "wof:placetype":"venue"
},
  "geometry": {"coordinates":[-118.301478,34.176146],"type":"Point"}
}