{
  "type": "Feature",
  "properties": {
    "addr:full":"14918 Gwenchris Ct Paramount CA 90723",
    "addr:housenumber":"14918",
    "addr:postcode":"90723",
    "addr:street":"Gwenchris Ct",
    "iso:country":"US",
    "sg:address":"14918 Gwenchris Ct",
    "sg:city":"Paramount",
    "sg:classifiers":[
        {
            "category":"Wholesale",
            "subcategory":"Apparel",
            "type":"Manufacturing & Wholesale Goods"
        }
    ],
    "sg:phone":"+1 562 408 4830",
    "sg:postcode":"90723",
    "sg:province":"CA",
    "sg:tags":[
        "clothing"
    ],
    "wof:name":"K & B Fashion",
    "wof:placetype":"venue"
},
  "geometry": {"coordinates":[-118.16695799999999,33.897177],"type":"Point"}
}