{
  "type": "Feature",
  "properties": {
    "iso:country":"US",
    "sg:address":"2026 Waring St",
    "sg:city":"Seaside",
    "sg:classifiers":[
        {
            "category":"Wholesale",
            "subcategory":"Durable Goods & Equipment",
            "type":"Manufacturing & Wholesale Goods"
        }
    ],
    "sg:phone":"+1 831 394 3740",
    "sg:postcode":"93955",
    "sg:province":"CA",
    "sg:tags":[
        "representative",
        "manufacturer"
    ],
    "wof:name":"Bite Rite Technologies",
    "wof:placetype":"venue"
},
  "geometry": {"coordinates":[-121.83484900000001,36.620653],"type":"Point"}
}