{
  "type": "Feature",
  "properties": {
    "addr:full":"5740 Roseville Road Sacramento CA 95842",
    "addr:housenumber":"5740",
    "addr:postcode":"95842",
    "addr:street":"Roseville Road",
    "iso:country":"US",
    "sg:address":"5740 Roseville Road",
    "sg:city":"Sacramento",
    "sg:classifiers":[
        {
            "category":"Building & Trades",
            "subcategory":"Plumbing",
            "type":"Services"
        },
        {
            "category":"Home & Garden",
            "subcategory":"Building Materials",
            "type":"Retail Goods"
        },
        {
            "category":"Utilities",
            "subcategory":"Sewage",
            "type":"Services"
        },
        {
            "category":"Building & Trades",
            "subcategory":"Cleaning & Sanitation",
            "type":"Services"
        }
    ],
    "sg:phone":"+1 916 481 3836",
    "sg:postcode":"95842",
    "sg:province":"CA",
    "sg:tags":[
        "heater",
        "plumber",
        "industrial",
        "repair",
        "repairer",
        "contractor",
        "water",
        "sewer",
        "contractors-commercial",
        "plumbing-drain",
        "cleaner"
    ],
    "sg:website":"http://www.straightlineplumbing.net",
    "wof:name":"Straight Line Plumbing",
    "wof:placetype":"venue"
},
  "geometry": {"coordinates":[-121.36955500000001,38.671232],"type":"Point"}
}