{
  "type": "Feature",
  "properties": {
    "addr:full":"310 E Huntington Dr Arcadia CA 91006",
    "addr:housenumber":"310",
    "addr:postcode":"91006",
    "addr:street":"E Huntington Dr",
    "iso:country":"US",
    "sg:address":"310 E Huntington Dr",
    "sg:city":"Arcadia",
    "sg:classifiers":[
        {
            "category":"Manufacturing",
            "subcategory":"Furniture",
            "type":"Manufacturing & Wholesale Goods"
        }
    ],
    "sg:phone":"+1 626 445 3422",
    "sg:postcode":"91006",
    "sg:province":"CA",
    "sg:tags":[
        "drapery",
        "mfg"
    ],
    "wof:name":"3 Day Blinds 37",
    "wof:placetype":"venue"
},
  "geometry": {"coordinates":[-118.02059,34.140188],"type":"Point"}
}