{
  "type": "Feature",
  "properties": {
    "addr:full":"2257 N Pacific St Orange CA 92865",
    "addr:housenumber":"2257",
    "addr:postcode":"92865",
    "addr:street":"N Pacific St",
    "iso:country":"US",
    "sg:address":"2257 N Pacific St",
    "sg:city":"Orange",
    "sg:classifiers":[
        {
            "category":"Manufacturing",
            "subcategory":"Printing",
            "type":"Manufacturing & Wholesale Goods"
        }
    ],
    "sg:phone":"+1 714 998 9200",
    "sg:postcode":"92865",
    "sg:province":"CA",
    "sg:tags":[
        "lithographic",
        "commercial",
        "publishing"
    ],
    "wof:name":"Fisher Printing Co Inc",
    "wof:placetype":"venue"
},
  "geometry": {"coordinates":[-117.85655199999999,33.823021],"type":"Point"}
}