{
  "type": "Feature",
  "properties": {
    "addr:full":"4690 E Jensen Ave Fresno CA 93725",
    "addr:housenumber":"4690",
    "addr:postcode":"93725",
    "addr:street":"E Jensen Ave",
    "iso:country":"US",
    "sg:address":"4690 E Jensen Ave",
    "sg:city":"Fresno",
    "sg:classifiers":[
        {
            "category":"Manufacturing",
            "subcategory":"Tools & Machinery",
            "type":"Manufacturing & Wholesale Goods"
        },
        {
            "category":"Autos & Motor Vehicles",
            "subcategory":"Auto Supplies",
            "type":"Retail Goods"
        },
        {
            "category":"Wholesale",
            "subcategory":"Electrical",
            "type":"Manufacturing & Wholesale Goods"
        },
        {
            "category":"Manufacturing",
            "subcategory":"Motor Vehicles & Parts",
            "type":"Manufacturing & Wholesale Goods"
        }
    ],
    "sg:phone":"+1 559 486 4222",
    "sg:postcode":"93725",
    "sg:province":"CA",
    "sg:tags":[
        "equipment",
        "manufacturer",
        "supplies-wholesale",
        "electric",
        "motors-used"
    ],
    "sg:website":"http://www.alliedelectric.net",
    "wof:name":"Allied Electric Motor Service, Inc.",
    "wof:placetype":"venue"
},
  "geometry": {"coordinates":[-119.74145900000001,36.706777],"type":"Point"}
}