{
  "type": "Feature",
  "properties": {
    "addr:full":"2150 Allston Way Ste 400 Berkeley CA 94704",
    "addr:housenumber":"2150",
    "addr:postcode":"94704",
    "addr:street":"Allston Way Ste 400",
    "iso:country":"US",
    "sg:address":"2150 Allston Way Ste 400",
    "sg:city":"Berkeley",
    "sg:classifiers":[
        {
            "category":"Organizations",
            "subcategory":"Non-profit Organization",
            "type":"Services"
        }
    ],
    "sg:phone":"+1 415 742 8048",
    "sg:postcode":"94704",
    "sg:province":"CA",
    "sg:tags":[
        "service/non-profit",
        "community"
    ],
    "sg:website":"www.reach-global.org",
    "wof:name":"Reach Global",
    "wof:placetype":"venue"
},
  "geometry": {"coordinates":[-122.265962,37.869637],"type":"Point"}
}