{
  "type": "Feature",
  "properties": {
    "iso:country":"US",
    "sg:address":"8300 Tamarind Way",
    "sg:city":"Riverside",
    "sg:classifiers":[
        {
            "category":"Retail",
            "subcategory":"Repair Shop",
            "type":"Services"
        }
    ],
    "sg:phone":"+1 951 685 9405",
    "sg:postcode":"92509",
    "sg:province":"CA",
    "sg:tags":[
        "equipment",
        "hydraulic"
    ],
    "wof:name":"Performance Hydraulics Inc",
    "wof:placetype":"venue"
},
  "geometry": {"coordinates":[-117.465448,33.977876],"type":"Point"}
}