{
  "type": "Feature",
  "properties": {
    "iso:country":"US",
    "sg:address":"354 S Halcyon Rd",
    "sg:city":"Arroyo Grande",
    "sg:classifiers":[
        {
            "category":"Health Services",
            "subcategory":"Clinic",
            "type":"Services"
        }
    ],
    "sg:phone":"+1 805 489 4026",
    "sg:postcode":"93420",
    "sg:province":"CA",
    "sg:tags":[
        "specialty",
        "outpatient"
    ],
    "wof:name":"Eoc Health Services",
    "wof:placetype":"venue"
},
  "geometry": {"coordinates":[-120.591652,35.113537],"type":"Point"}
}