{
  "type": "Feature",
  "properties": {
    "addr:full":"4393 Imperial Ave Ste 100 San Diego CA 92113",
    "addr:housenumber":"4393",
    "addr:postcode":"92113",
    "addr:street":"Imperial Ave Ste 100",
    "iso:country":"US",
    "sg:address":"4393 Imperial Ave Ste 100",
    "sg:city":"San Diego",
    "sg:classifiers":[
        {
            "category":"Education",
            "subcategory":"Special Training",
            "type":"Public Place"
        },
        {
            "category":"Education",
            "subcategory":"University",
            "type":"Public Place"
        }
    ],
    "sg:phone":"+1 877 978 3257",
    "sg:postcode":"92113",
    "sg:province":"CA",
    "sg:tags":[
        "school",
        "college",
        "specialty"
    ],
    "sg:website":"www.concordecareers.com",
    "wof:name":"Concorde Career College",
    "wof:placetype":"venue"
},
  "geometry": {"coordinates":[-117.10170100000001,32.703933],"type":"Point"}
}