{
  "type": "Feature",
  "properties": {
    "addr:full":"1746 Cll Poniente Santa Barbara CA 93101",
    "addr:housenumber":"1746",
    "addr:postcode":"93101",
    "addr:street":"Cll Poniente",
    "iso:country":"US",
    "sg:address":"1746 Cll Poniente",
    "sg:city":"Santa Barbara",
    "sg:classifiers":[
        {
            "category":"Real Estate",
            "subcategory":"Architect",
            "type":"Services"
        }
    ],
    "sg:phone":"+1 805 883 1600",
    "sg:postcode":"93101",
    "sg:province":"CA",
    "wof:name":"Jose Luis Esparza",
    "wof:placetype":"venue"
},
  "geometry": {"coordinates":[-119.73189499999999,34.415275],"type":"Point"}
}