{
  "type": "Feature",
  "properties": {
    "iso:country":"US",
    "sg:address":"6175 N Figarden Dr # 117",
    "sg:city":"Fresno",
    "sg:classifiers":[
        {
            "category":"Communications",
            "subcategory":"Film & Video Production",
            "type":"Services"
        },
        {
            "category":"Professional",
            "subcategory":"Printing & Photocopies",
            "type":"Services"
        }
    ],
    "sg:phone":"+1 559 307 4661",
    "sg:postcode":"93722",
    "sg:province":"CA",
    "sg:tags":[
        "photographers-commercial",
        "services-commercial"
    ],
    "sg:website":"http://www.svpproductions.com",
    "wof:name":"Svp Productions",
    "wof:placetype":"venue"
},
  "geometry": {"coordinates":[-119.86988100000001,36.82613],"type":"Point"}
}