{
  "type": "Feature",
  "properties": {
    "addr:full":"7393 Rd 208 Terra Bella CA 93270",
    "addr:housenumber":"7393",
    "addr:postcode":"93270",
    "addr:street":"Rd 208",
    "iso:country":"US",
    "sg:address":"7393 Rd 208",
    "sg:city":"Terra Bella",
    "sg:classifiers":[
        {
            "category":"Farming",
            "subcategory":"Farm & Veterinary Services",
            "type":"Manufacturing & Wholesale Goods"
        }
    ],
    "sg:phone":"+1 559 791 1206",
    "sg:postcode":"93270",
    "sg:province":"CA",
    "sg:tags":[
        "management"
    ],
    "wof:name":"B T V Crown Equities Inc",
    "wof:placetype":"venue"
},
  "geometry": {"coordinates":[-119.10788100000001,35.899023],"type":"Point"}
}