{
  "type": "Feature",
  "properties": {
    "addr:full":"38343 5th Pl W Palmdale CA 93551",
    "addr:housenumber":"38343",
    "addr:postcode":"ca 93551",
    "addr:street":"5Th Pl W",
    "iso:country":"US",
    "sg:address":"38343 5th Pl W",
    "sg:city":"Palmdale",
    "sg:classifiers":[
        {
            "category":"Professional",
            "subcategory":"Engineering",
            "type":"Services"
        }
    ],
    "sg:phone":"+1 661 273 2125",
    "sg:postcode":"93551",
    "sg:province":"CA",
    "sg:tags":[
        "civil",
        "engineer"
    ],
    "wof:name":"Felt Engineering",
    "wof:placetype":"venue"
},
  "geometry": {"coordinates":[-118.13905699999999,34.579152],"type":"Point"}
}