{
  "type": "Feature",
  "properties": {
    "iso:country":"US",
    "sg:address":"4900 Santa Anita Ave",
    "sg:city":"El Monte",
    "sg:classifiers":[
        {
            "category":"Insurance",
            "subcategory":"Insurance Agent",
            "type":"Services"
        }
    ],
    "sg:phone":"+1 626 454 1320",
    "sg:postcode":"91731",
    "sg:province":"CA",
    "wof:name":"Sam Mirkamali Insurance",
    "wof:placetype":"venue"
},
  "geometry": {"coordinates":[-118.028398,34.09639],"type":"Point"}
}