{
  "type": "Feature",
  "properties": {
    "iso:country":"US",
    "sg:address":"35040 Beech Ave",
    "sg:city":"Yucaipa",
    "sg:classifiers":[
        {
            "category":"Real Estate",
            "subcategory":"Real Estate Agent",
            "type":"Services"
        }
    ],
    "sg:phone":"+1 909 797 1130",
    "sg:postcode":"92399",
    "sg:province":"CA",
    "wof:name":"J R Real Estate",
    "wof:placetype":"venue"
},
  "geometry": {"coordinates":[-117.040001,34.0359],"type":"Point"}
}