{
  "type": "Feature",
  "properties": {
    "iso:country":"US",
    "sg:address":"340 Five Cities Dr",
    "sg:city":"Pismo Beach",
    "sg:classifiers":[
        {
            "category":"Autos & Motor Vehicles",
            "subcategory":"Fuel & Gas Station",
            "type":"Retail Goods"
        }
    ],
    "sg:phone":"+1 805 773 1668",
    "sg:postcode":"93449",
    "sg:province":"CA",
    "sg:tags":[
        "oil"
    ],
    "wof:name":"Five Cities Chevron",
    "wof:placetype":"venue"
},
  "geometry": {"coordinates":[-120.62871,35.136682],"type":"Point"}
}