{
  "type": "Feature",
  "properties": {
    "iso:country":"US",
    "sg:address":"1739 Ashby Rd",
    "sg:city":"Merced",
    "sg:classifiers":[
        {
            "category":"Building & Trades",
            "subcategory":"Construction",
            "type":"Services"
        }
    ],
    "sg:phone":"+1 209 722 7307",
    "sg:postcode":"95348",
    "sg:province":"CA",
    "sg:tags":[
        "contractor"
    ],
    "wof:name":"Rod Brawley Construction",
    "wof:placetype":"venue"
},
  "geometry": {"coordinates":[-120.51379900000001,37.312449],"type":"Point"}
}