{
  "type": "Feature",
  "properties": {
    "iso:country":"US",
    "sg:address":"703 S Main St",
    "sg:city":"Burbank",
    "sg:classifiers":[
        {
            "category":"Manufacturing",
            "subcategory":"Food",
            "type":"Manufacturing & Wholesale Goods"
        }
    ],
    "sg:phone":"+1 818 841 9347",
    "sg:postcode":"91506",
    "sg:province":"CA",
    "sg:tags":[
        "bakery",
        "prod",
        "cookie"
    ],
    "wof:name":"Viktor Benes Continental Bkry",
    "wof:placetype":"venue"
},
  "geometry": {"coordinates":[-118.31335199999999,34.16689],"type":"Point"}
}