{
  "type": "Feature",
  "properties": {
    "addr:full":"3869 Piedmont Ave Oakland CA 94611",
    "addr:housenumber":"3869",
    "addr:postcode":"94611",
    "addr:street":"Piedmont Ave",
    "iso:country":"US",
    "sg:address":"3869 Piedmont Ave",
    "sg:city":"Oakland",
    "sg:classifiers":[
        {
            "category":"Personal",
            "subcategory":"Beauty Salon",
            "type":"Services"
        },
        {
            "category":"Shopping",
            "subcategory":"Beauty & Cosmetics",
            "type":"Retail Goods"
        }
    ],
    "sg:phone":"+1 510 652 5454",
    "sg:postcode":"94611",
    "sg:province":"CA",
    "sg:tags":[
        "hair",
        "makeup",
        "artist",
        "supply"
    ],
    "sg:website":"www.givaesalon.com",
    "wof:name":"Givae Salon",
    "wof:placetype":"venue"
},
  "geometry": {"coordinates":[-122.25599699999999,37.823898],"type":"Point"}
}