{
  "type": "Feature",
  "properties": {
    "addr:full":"73290 el Paseo Palm Desert CA 92260",
    "addr:housenumber":"73290",
    "addr:postcode":"ca 92260",
    "addr:street":"El Paseo",
    "iso:country":"US",
    "sg:address":"73290 el Paseo",
    "sg:city":"Palm Desert",
    "sg:classifiers":[
        {
            "category":"Personal",
            "subcategory":"Beauty Salon",
            "type":"Services"
        }
    ],
    "sg:phone":"+1 760 341 3471",
    "sg:postcode":"92260",
    "sg:province":"CA",
    "wof:name":"Vaughan & Vaughan",
    "wof:placetype":"venue"
},
  "geometry": {"coordinates":[-116.38557400000001,33.719845],"type":"Point"}
}