{
  "type": "Feature",
  "properties": {
    "addr:full":"12891 Western Ave Garden Grove CA 92841",
    "addr:housenumber":"12891",
    "addr:postcode":"92841",
    "addr:street":"Western Ave",
    "iso:country":"US",
    "sg:address":"12891 Western Ave",
    "sg:city":"Garden Grove",
    "sg:classifiers":[
        {
            "category":"Building & Trades",
            "subcategory":"Plumbing",
            "type":"Services"
        }
    ],
    "sg:phone":"+1 949 650 5226",
    "sg:postcode":"92841",
    "sg:province":"CA",
    "wof:name":"Sos Snake Out Sewer and Drain Cleaning Service",
    "wof:placetype":"venue"
},
  "geometry": {"coordinates":[-118.00099899999999,33.773899],"type":"Point"}
}