{
  "type": "Feature",
  "properties": {
    "addr:full":"526 Hofgaarden St La Puente CA 91744",
    "addr:housenumber":"526",
    "addr:postcode":"91744",
    "addr:street":"Hofgaarden St",
    "iso:country":"US",
    "sg:address":"526 Hofgaarden St",
    "sg:city":"La Puente",
    "sg:classifiers":[
        {
            "category":"Wholesale",
            "subcategory":"Machinery & Supplies",
            "type":"Manufacturing & Wholesale Goods"
        }
    ],
    "sg:phone":"+1 626 961 0474",
    "sg:postcode":"91744",
    "sg:province":"CA",
    "sg:tags":[
        "fitting",
        "hose",
        "coupling"
    ],
    "sg:website":"www.lahose.com",
    "wof:name":"L A Hose & Fittings",
    "wof:placetype":"venue"
},
  "geometry": {"coordinates":[-117.944478,34.013719],"type":"Point"}
}