{
  "type": "Feature",
  "properties": {
    "iso:country":"US",
    "sg:address":"421 Lazy Brook Ct",
    "sg:city":"Simi Valley",
    "sg:classifiers":[
        {
            "category":"Professional",
            "type":"Services"
        }
    ],
    "sg:phone":"+1 805 526 4723",
    "sg:postcode":"93065",
    "sg:province":"CA",
    "wof:name":"Avalanche Electronics",
    "wof:placetype":"venue"
},
  "geometry": {"coordinates":[-118.803753,34.24803],"type":"Point"}
}