{
  "type": "Feature",
  "properties": {
    "addr:full":"2708 Torrey Pines Way Modesto CA 95355",
    "addr:housenumber":"2708",
    "addr:postcode":"ca 95355",
    "addr:street":"Torrey Pines Way",
    "iso:country":"US",
    "sg:address":"2708 Torrey Pines Way",
    "sg:city":"Modesto",
    "sg:classifiers":[
        {
            "category":"Shopping",
            "subcategory":"Computers & Home Electronics",
            "type":"Retail Goods"
        }
    ],
    "sg:phone":"+1 209 551 2317",
    "sg:postcode":"95355",
    "sg:province":"CA",
    "sg:tags":[
        "software"
    ],
    "wof:name":"Sentient Inc",
    "wof:placetype":"venue"
},
  "geometry": {"coordinates":[-120.94481,37.686226],"type":"Point"}
}