{
  "type": "Feature",
  "properties": {
    "iso:country":"US",
    "sg:address":"9923 Pioneer Blvd",
    "sg:city":"Santa Fe Springs",
    "sg:classifiers":[
        {
            "category":"Wholesale",
            "subcategory":"Furniture",
            "type":"Manufacturing & Wholesale Goods"
        }
    ],
    "sg:phone":"+1 562 222 2800",
    "sg:postcode":"90670",
    "sg:province":"CA",
    "wof:name":"Meva International LLC",
    "wof:placetype":"venue"
},
  "geometry": {"coordinates":[-118.079679,33.947485],"type":"Point"}
}