{
  "type": "Feature",
  "properties": {
    "iso:country":"US",
    "sg:address":"14619 S Western Ave",
    "sg:city":"Gardena",
    "sg:classifiers":[
        {
            "category":"Retail",
            "subcategory":"Repair Shop",
            "type":"Services"
        }
    ],
    "sg:phone":"+1 310 527 2004",
    "sg:postcode":"90249",
    "sg:province":"CA",
    "sg:tags":[
        "plumbing",
        "drain",
        "cleaning",
        "sewer"
    ],
    "wof:name":"Yolanda Gonzalez",
    "wof:placetype":"venue"
},
  "geometry": {"coordinates":[-118.30919900000001,33.898103],"type":"Point"}
}