{
  "type": "Feature",
  "properties": {
    "iso:country":"US",
    "sg:address":"8550 Conn Creek Rd",
    "sg:city":"St Helena",
    "sg:classifiers":[
        {
            "category":"Farming",
            "subcategory":"Farm & Veterinary Services",
            "type":"Manufacturing & Wholesale Goods"
        }
    ],
    "sg:phone":"+1 707 963 8890",
    "sg:postcode":"94558",
    "sg:province":"CA",
    "sg:tags":[
        "vineyard",
        "consultant"
    ],
    "wof:name":"Winegrowers Farming Co",
    "wof:placetype":"venue"
},
  "geometry": {"coordinates":[-122.39890699999999,38.47015],"type":"Point"}
}