{
  "type": "Feature",
  "properties": {
    "iso:country":"US",
    "sg:address":"1723 J St",
    "sg:city":"Sacramento",
    "sg:classifiers":[
        {
            "category":"Personal",
            "subcategory":"Beauty Salon",
            "type":"Services"
        }
    ],
    "sg:phone":"+1 916 444 1359",
    "sg:postcode":"95811",
    "sg:province":"CA",
    "sg:tags":[
        "hair",
        "makeup",
        "artist"
    ],
    "sg:website":"www.flygarage.com",
    "wof:name":"Spanish Fly Hair Garage",
    "wof:placetype":"venue"
},
  "geometry": {"coordinates":[-121.48295,38.577859],"type":"Point"}
}