{
  "type": "Feature",
  "properties": {
    "iso:country":"US",
    "sg:address":"1860 S Bascom Avenue Suite #102",
    "sg:city":"Campbell",
    "sg:classifiers":[
        {
            "category":"Building & Trades",
            "subcategory":"Cleaning & Sanitation",
            "type":"Services"
        }
    ],
    "sg:phone":"+1 408 377 3800",
    "sg:postcode":"95008",
    "sg:province":"CA",
    "sg:tags":[
        "home"
    ],
    "sg:website":"www.maidpro.com/campbell",
    "wof:name":"MaidPro",
    "wof:placetype":"venue"
},
  "geometry": {"coordinates":[-121.931577,37.289797],"type":"Point"}
}