{
  "type": "Feature",
  "properties": {
    "addr:full":"1810 W Campbell Ave Campbell CA 95008",
    "addr:housenumber":"1810",
    "addr:postcode":"95008",
    "addr:street":"W Campbell Ave",
    "iso:country":"US",
    "sg:address":"1810 W Campbell Ave",
    "sg:city":"Campbell",
    "sg:classifiers":[
        {
            "category":"Personal",
            "subcategory":"Tanning Parlor",
            "type":"Services"
        }
    ],
    "sg:phone":"+1 408 866 5151",
    "sg:postcode":"95008",
    "sg:province":"CA",
    "sg:website":"www.australiantanningcompany.com/",
    "wof:name":"Australian Tanning",
    "wof:placetype":"venue"
},
  "geometry": {"coordinates":[-121.98258300000001,37.285931],"type":"Point"}
}