{
  "type": "Feature",
  "properties": {
    "iso:country":"US",
    "sg:address":"24837 E Milton Rd",
    "sg:city":"Linden",
    "sg:classifiers":[
        {
            "category":"Health Services",
            "subcategory":"Chiropractor",
            "type":"Services"
        }
    ],
    "sg:phone":"+1 209 887 2158",
    "sg:postcode":"95236",
    "sg:province":"CA",
    "sg:tags":[
        "chiropractic"
    ],
    "wof:name":"Cross Don Masonry",
    "wof:placetype":"venue"
},
  "geometry": {"coordinates":[-120.999295,37.988044],"type":"Point"}
}