{
  "type": "Feature",
  "properties": {
    "addr:full":"13250 Skyline Blvd Redwood City CA 94062",
    "addr:housenumber":"13250",
    "addr:postcode":"94062",
    "addr:street":"Skyline Blvd",
    "iso:country":"US",
    "sg:address":"13250 Skyline Blvd",
    "sg:city":"Redwood City",
    "sg:classifiers":[
        {
            "category":"Health Services",
            "subcategory":"Chiropractor",
            "type":"Services"
        }
    ],
    "sg:phone":"+1 408 774 1800",
    "sg:postcode":"94062",
    "sg:province":"CA",
    "sg:website":"www.carpaltunnel-solutions.com",
    "wof:name":"Vitality Health Group",
    "wof:placetype":"venue"
},
  "geometry": {"coordinates":[-122.33994800000001,37.452882],"type":"Point"}
}