{
  "type": "Feature",
  "properties": {
    "iso:country":"US",
    "sg:address":"13250 Skyline Blvd",
    "sg:city":"Redwood City",
    "sg:classifiers":[
        {
            "category":"Health Services",
            "subcategory":"Chiropractor",
            "type":"Services"
        }
    ],
    "sg:phone":"+1 408 774 1800",
    "sg:postcode":"94062",
    "sg:province":"CA",
    "sg:website":"www.carpaltunnel-solutions.com",
    "wof:name":"Vitality Health Group",
    "wof:placetype":"venue"
},
  "geometry": {"coordinates":[-122.339948,37.452882],"type":"Point"}
}