{
  "type": "Feature",
  "properties": {
    "iso:country":"US",
    "sg:address":"1584 Oak Canyon Dr",
    "sg:city":"San Jose",
    "sg:classifiers":[
        {
            "category":"Wholesale",
            "subcategory":"Electrical",
            "type":"Manufacturing & Wholesale Goods"
        }
    ],
    "sg:phone":"+1 408 268 1024",
    "sg:postcode":"95120",
    "sg:province":"CA",
    "sg:tags":[
        "electronic"
    ],
    "wof:name":"Actum Co",
    "wof:placetype":"venue"
},
  "geometry": {"coordinates":[-121.902149,37.229032],"type":"Point"}
}