{
  "type": "Feature",
  "properties": {
    "addr:full":"2168 Union Street San Francisco CA 94123",
    "addr:housenumber":"2168",
    "addr:postcode":"94123",
    "addr:street":"Union Street",
    "iso:country":"US",
    "sg:address":"2168 Union Street",
    "sg:city":"San Francisco",
    "sg:classifiers":[
        {
            "category":"Building & Trades",
            "subcategory":"Plumbing",
            "type":"Services"
        }
    ],
    "sg:phone":"+1 415 441 6585",
    "sg:postcode":"94123",
    "sg:province":"CA",
    "wof:name":"Buckley Plumbing",
    "wof:placetype":"venue"
},
  "geometry": {"coordinates":[-122.43506499999999,37.797288],"type":"Point"}
}