{
  "type": "Feature",
  "properties": {
    "addr:full":"2183 Fairview Rd Costa Mesa CA 92627",
    "addr:housenumber":"2183",
    "addr:postcode":"92627",
    "addr:street":"Fairview Rd",
    "iso:country":"US",
    "sg:address":"2183 Fairview Rd",
    "sg:city":"Costa Mesa",
    "sg:classifiers":[
        {
            "category":"Professional",
            "subcategory":"Lawyer & Legal Services",
            "type":"Services"
        }
    ],
    "sg:phone":"+1 949 642 4694",
    "sg:postcode":"92627",
    "sg:province":"CA",
    "sg:tags":[
        "attorney"
    ],
    "wof:name":"Ali Farahmand Attorney",
    "wof:placetype":"venue"
},
  "geometry": {"coordinates":[-117.90767,33.65447],"type":"Point"}
}