{
  "type": "Feature",
  "properties": {
    "addr:full":"11960 Heritage Oak Pl Auburn CA 95603",
    "addr:housenumber":"11960",
    "addr:postcode":"ca 95603",
    "addr:street":"Heritage Oak Pl",
    "iso:country":"US",
    "sg:address":"11960 Heritage Oak Pl",
    "sg:city":"Auburn",
    "sg:classifiers":[
        {
            "category":"Manufacturing",
            "subcategory":"Printing",
            "type":"Manufacturing & Wholesale Goods"
        }
    ],
    "sg:phone":"+1 530 823 8212",
    "sg:postcode":"95603",
    "sg:province":"CA",
    "sg:tags":[
        "newspaper"
    ],
    "wof:name":"Sacramento Bee Newspaper",
    "wof:placetype":"venue"
},
  "geometry": {"coordinates":[-121.099379,38.940545],"type":"Point"}
}