{
  "type": "Feature",
  "properties": {
    "iso:country":"US",
    "sg:address":"32839 State Hwy 79 S",
    "sg:city":"Temecula",
    "sg:classifiers":[
        {
            "category":"Building & Trades",
            "subcategory":"Construction",
            "type":"Services"
        }
    ],
    "sg:phone":"+1 951 694 5032",
    "sg:postcode":"92592",
    "sg:province":"CA",
    "sg:tags":[
        "concrete",
        "contractor"
    ],
    "wof:name":"Barfknecht Construction",
    "wof:placetype":"venue"
},
  "geometry": {"coordinates":[-117.079556,33.48582],"type":"Point"}
}