{
  "type": "Feature",
  "properties": {
    "addr:full":"543 31st St Oakland CA 94609",
    "addr:housenumber":"543",
    "addr:postcode":"94609",
    "addr:street":"31St St",
    "iso:country":"US",
    "sg:address":"543 31st St",
    "sg:city":"Oakland",
    "sg:classifiers":[
        {
            "category":"Communications",
            "subcategory":"Film & Video Production",
            "type":"Services"
        }
    ],
    "sg:phone":"+1 510 601 0193",
    "sg:postcode":"94609",
    "sg:province":"CA",
    "sg:tags":[
        "consultant",
        "audio"
    ],
    "wof:name":"Design Engineering",
    "wof:placetype":"venue"
},
  "geometry": {"coordinates":[-122.268649,37.820574],"type":"Point"}
}