{
  "type": "Feature",
  "properties": {
    "iso:country":"US",
    "sg:address":"120 N Ash St",
    "sg:city":"Escondido",
    "sg:classifiers":[
        {
            "category":"Social Services",
            "subcategory":"Child Care",
            "type":"Services"
        }
    ],
    "sg:phone":"+1 760 741 6490",
    "sg:postcode":"92027",
    "sg:province":"CA",
    "sg:tags":[
        "kindergarten",
        "academic",
        "school"
    ],
    "wof:name":"Light & Life Christian Prescho",
    "wof:placetype":"venue"
},
  "geometry": {"coordinates":[-117.065595,33.127512],"type":"Point"}
}