{
  "type": "Feature",
  "properties": {
    "iso:country":"US",
    "sg:address":"906 Grant Ave",
    "sg:city":"Novato",
    "sg:classifiers":[
        {
            "category":"Shopping",
            "subcategory":"Bicycles & Sporting Goods",
            "type":"Retail Goods"
        }
    ],
    "sg:phone":"+1 415 209 9887",
    "sg:postcode":"94945",
    "sg:province":"CA",
    "sg:tags":[
        "equipment",
        "skateboard"
    ],
    "wof:name":"Luckies Skate & Snow",
    "wof:placetype":"venue"
},
  "geometry": {"coordinates":[-122.570155,38.10761],"type":"Point"}
}