{
  "type": "Feature",
  "properties": {
    "iso:country":"US",
    "sg:address":"3483 Grove St",
    "sg:city":"Lemon Grove",
    "sg:classifiers":[
        {
            "category":"Retail",
            "subcategory":"Auto Repair",
            "type":"Services"
        }
    ],
    "sg:phone":"+1 619 463 3352",
    "sg:postcode":"91945",
    "sg:province":"CA",
    "sg:tags":[
        "transmission"
    ],
    "wof:name":"Lemon Grove Transmission",
    "wof:placetype":"venue"
},
  "geometry": {"coordinates":[-117.02728,32.742913],"type":"Point"}
}