{
  "type": "Feature",
  "properties": {
    "iso:country":"US",
    "sg:address":"3003 3rd St",
    "sg:city":"San Francisco",
    "sg:classifiers":[
        {
            "category":"Wholesale",
            "subcategory":"Electrical",
            "type":"Manufacturing & Wholesale Goods"
        }
    ],
    "sg:phone":"+1 415 821 3011",
    "sg:postcode":"94107",
    "sg:province":"CA",
    "sg:tags":[
        "equipment",
        "electric",
        "supply"
    ],
    "wof:name":"City Electric Supply",
    "wof:placetype":"venue"
},
  "geometry": {"coordinates":[-122.387506,37.750255],"type":"Point"}
}