{
  "type": "Feature",
  "properties": {
    "addr:full":"5885 Pacific St Rocklin CA 95677",
    "addr:housenumber":"5885",
    "addr:postcode":"95677",
    "addr:street":"Pacific St",
    "iso:country":"US",
    "sg:address":"5885 Pacific St",
    "sg:city":"Rocklin",
    "sg:classifiers":[
        {
            "category":"Shopping",
            "subcategory":"Florist",
            "type":"Retail Goods"
        }
    ],
    "sg:phone":"+1 916 624 1651",
    "sg:postcode":"95677",
    "sg:province":"CA",
    "sg:website":"www.rocklinflorist.com",
    "wof:name":"Rocklin Florist",
    "wof:placetype":"venue"
},
  "geometry": {"coordinates":[-121.23970300000001,38.785649],"type":"Point"}
}