{
  "type": "Feature",
  "properties": {
    "addr:full":"4109 Isle Dr Carlsbad CA 92008",
    "addr:housenumber":"4109",
    "addr:postcode":"92008",
    "addr:street":"Isle Dr",
    "iso:country":"US",
    "sg:address":"4109 Isle Dr",
    "sg:city":"Carlsbad",
    "sg:classifiers":[
        {
            "category":"Restaurant",
            "type":"Food & Drink"
        }
    ],
    "sg:phone":"+1 760 940 0647",
    "sg:postcode":"92008",
    "sg:province":"CA",
    "sg:tags":[
        "delicatessen"
    ],
    "wof:name":"Blue Moon Cafe & Deli",
    "wof:placetype":"venue"
},
  "geometry": {"coordinates":[-117.32521199999999,33.151082],"type":"Point"}
}