{
  "type": "Feature",
  "properties": {
    "iso:country":"US",
    "sg:address":"14311 Cerise Ave",
    "sg:city":"Hawthorne",
    "sg:classifiers":[
        {
            "category":"Real Estate",
            "subcategory":"Real Estate Agent",
            "type":"Services"
        }
    ],
    "sg:phone":"+1 310 355 0374",
    "sg:postcode":"90250",
    "sg:province":"CA",
    "sg:tags":[
        "business"
    ],
    "wof:name":"Aas Appraisal Service",
    "wof:placetype":"venue"
},
  "geometry": {"coordinates":[-118.333072,33.90093],"type":"Point"}
}