{
  "type": "Feature",
  "properties": {
    "addr:full":"1600 Main St Venice CA 90291",
    "addr:housenumber":"1600",
    "addr:postcode":"90291",
    "addr:street":"Main St",
    "iso:country":"US",
    "sg:address":"1600 Main St",
    "sg:city":"Venice",
    "sg:classifiers":[
        {
            "category":"Professional",
            "subcategory":"Printing & Photocopies",
            "type":"Services"
        }
    ],
    "sg:phone":"+1 310 821 4440",
    "sg:postcode":"90291",
    "sg:province":"CA",
    "sg:tags":[
        "duplicating",
        "copying"
    ],
    "wof:name":"Venice Supply Depot",
    "wof:placetype":"venue"
},
  "geometry": {"coordinates":[-118.470782,33.987581],"type":"Point"}
}