{
  "type": "Feature",
  "properties": {
    "iso:country":"US",
    "sg:address":"13436 Maxella Ave",
    "sg:city":"Marina Del Rey",
    "sg:classifiers":[
        {
            "category":"Personal",
            "subcategory":"Beauty Salon",
            "type":"Services"
        }
    ],
    "sg:phone":"+1 310 574 4726",
    "sg:postcode":"90292",
    "sg:province":"CA",
    "sg:tags":[
        "hair"
    ],
    "wof:name":"Fantastic Sams",
    "wof:placetype":"venue"
},
  "geometry": {"coordinates":[-118.441002,33.987099],"type":"Point"}
}