{
  "type": "Feature",
  "properties": {
    "addr:full":"2837 Lenwood Rd Barstow CA 92311",
    "addr:housenumber":"2837",
    "addr:postcode":"92311",
    "addr:street":"Lenwood Rd",
    "iso:country":"US",
    "sg:address":"2837 Lenwood Rd",
    "sg:city":"Barstow",
    "sg:classifiers":[
        {
            "category":"Professional",
            "type":"Services"
        }
    ],
    "sg:phone":"+1 760 253 7901",
    "sg:postcode":"92311",
    "sg:province":"CA",
    "wof:name":"Ashworth Inc",
    "wof:placetype":"venue"
},
  "geometry": {"coordinates":[-117.089096,34.854962],"type":"Point"}
}