{
  "type": "Feature",
  "properties": {
    "iso:country":"US",
    "sg:address":"100 Main St",
    "sg:city":"Belvedere Tibrn",
    "sg:classifiers":[
        {
            "category":"Professional",
            "subcategory":"Research",
            "type":"Services"
        }
    ],
    "sg:phone":"+1 415 789 1007",
    "sg:postcode":"94920",
    "sg:province":"CA",
    "wof:name":"California Health Research",
    "wof:placetype":"venue"
},
  "geometry": {"coordinates":[-122.457941,37.873718],"type":"Point"}
}