{
  "type": "Feature",
  "properties": {
    "addr:full":"445 W California Ave Vista CA 92083",
    "addr:housenumber":"445",
    "addr:postcode":"92083",
    "addr:street":"W California Ave",
    "iso:country":"US",
    "sg:address":"445 W California Ave",
    "sg:city":"Vista",
    "sg:classifiers":[
        {
            "category":"Autos & Motor Vehicles",
            "subcategory":"Fuel & Gas Station",
            "type":"Retail Goods"
        }
    ],
    "sg:phone":"+1 619 200 1768",
    "sg:postcode":"92083",
    "sg:province":"CA",
    "sg:tags":[
        "station",
        "gasoline"
    ],
    "wof:name":"Artro Mobil Service",
    "wof:placetype":"venue"
},
  "geometry": {"coordinates":[-117.25022300000001,33.207992],"type":"Point"}
}