{
  "type": "Feature",
  "properties": {
    "addr:full":"17140 Aspen Way Morgan Hill CA 95037",
    "addr:housenumber":"17140",
    "addr:postcode":"95037",
    "addr:street":"Aspen Way",
    "iso:country":"US",
    "sg:address":"17140 Aspen Way",
    "sg:city":"Morgan Hill",
    "sg:classifiers":[
        {
            "category":"Shopping",
            "subcategory":"Computers & Home Electronics",
            "type":"Retail Goods"
        }
    ],
    "sg:phone":"+1 530 343 5754",
    "sg:postcode":"95037",
    "sg:province":"CA",
    "sg:tags":[
        "software"
    ],
    "wof:name":"Boring Software",
    "wof:placetype":"venue"
},
  "geometry": {"coordinates":[-121.62472099999999,37.137976],"type":"Point"}
}