{
  "type": "Feature",
  "properties": {
    "iso:country":"US",
    "sg:address":"355 Gellert Blvd",
    "sg:city":"Daly City",
    "sg:classifiers":[
        {
            "category":"Professional",
            "type":"Services"
        }
    ],
    "sg:phone":"+1 650 991 5124",
    "sg:postcode":"94015",
    "sg:province":"CA",
    "wof:name":"Center For Indepnc Disabled",
    "wof:placetype":"venue"
},
  "geometry": {"coordinates":[-122.46913600000001,37.664078],"type":"Point"}
}