{
  "type": "Feature",
  "properties": {
    "iso:country":"US",
    "sg:address":"8905 Rhine River Ave",
    "sg:city":"Fountain Valley",
    "sg:classifiers":[
        {
            "category":"Professional",
            "subcategory":"Art Services",
            "type":"Services"
        }
    ],
    "sg:phone":"+1 714 964 4056",
    "sg:postcode":"92708",
    "sg:province":"CA",
    "sg:tags":[
        "photographer"
    ],
    "sg:website":"www.arnierosner.com",
    "wof:name":"Arnie Rosner Enterprises",
    "wof:placetype":"venue"
},
  "geometry": {"coordinates":[-117.97341400000001,33.699189],"type":"Point"}
}