{
  "type": "Feature",
  "properties": {
    "iso:country":"US",
    "sg:address":"1530 The Alameda",
    "sg:city":"San Jose",
    "sg:classifiers":[
        {
            "category":"Professional",
            "subcategory":"Accounting & Tax Preparation",
            "type":"Services"
        }
    ],
    "sg:phone":"+1 408 293 3004",
    "sg:postcode":"95126",
    "sg:province":"CA",
    "sg:tags":[
        "accountant"
    ],
    "wof:name":"Cook Michele A CPA",
    "wof:placetype":"venue"
},
  "geometry": {"coordinates":[-121.91555700000001,37.33462],"type":"Point"}
}