{
  "type": "Feature",
  "properties": {
    "iso:country":"US",
    "sg:address":"2107 W Washington Blvd",
    "sg:city":"Los Angeles",
    "sg:classifiers":[
        {
            "category":"Professional",
            "subcategory":"Business Services",
            "type":"Services"
        }
    ],
    "sg:phone":"+1 323 737 0184",
    "sg:postcode":"90018",
    "sg:province":"CA",
    "sg:tags":[
        "recording",
        "studio"
    ],
    "wof:name":"Cross Over Records",
    "wof:placetype":"venue"
},
  "geometry": {"coordinates":[-118.30572100000001,34.03995],"type":"Point"}
}