{
  "type": "Feature",
  "properties": {
    "iso:country":"US",
    "sg:address":"892 6th St",
    "sg:city":"Norco",
    "sg:classifiers":[
        {
            "category":"Retail",
            "subcategory":"Veterinary Services",
            "type":"Services"
        }
    ],
    "sg:phone":"+1 951 736 1917",
    "sg:postcode":"92860",
    "sg:province":"CA",
    "wof:name":"Norco Animal Hospital",
    "wof:placetype":"venue"
},
  "geometry": {"coordinates":[-117.539151,33.938353],"type":"Point"}
}