{
  "type": "Feature",
  "properties": {
    "addr:full":"920 Quails Trail Rd Vista CA 92081",
    "addr:housenumber":"920",
    "addr:postcode":"92081",
    "addr:street":"Quails Trail Rd",
    "iso:country":"US",
    "sg:address":"920 Quails Trail Rd",
    "sg:city":"Vista",
    "sg:classifiers":[
        {
            "category":"Banks & Credit Unions",
            "subcategory":"Financial Services",
            "type":"Services"
        }
    ],
    "sg:phone":"+1 760 727 3346",
    "sg:postcode":"92081",
    "sg:province":"CA",
    "sg:tags":[
        "trust",
        "management"
    ],
    "wof:name":"Felter Family Trust",
    "wof:placetype":"venue"
},
  "geometry": {"coordinates":[-117.22874400000001,33.172784],"type":"Point"}
}