{
  "type": "Feature",
  "properties": {
    "addr:full":"5102 Tujunga Ave North Hollywood CA 91601",
    "addr:housenumber":"5102",
    "addr:postcode":"91601",
    "addr:street":"Tujunga Ave",
    "iso:country":"US",
    "sg:address":"5102 Tujunga Ave",
    "sg:city":"North Hollywood",
    "sg:classifiers":[
        {
            "category":"Arts & Performance",
            "subcategory":"Theater",
            "type":"Entertainment"
        }
    ],
    "sg:phone":"+1 818 314 8309",
    "sg:postcode":"91601",
    "sg:province":"CA",
    "sg:tags":[
        "live",
        "music"
    ],
    "wof:name":"Hollywood Dj's",
    "wof:placetype":"venue"
},
  "geometry": {"coordinates":[-118.378901,34.164857],"type":"Point"}
}