{
  "type": "Feature",
  "properties": {
    "iso:country":"US",
    "sg:address":"747 San Pablo Ave",
    "sg:city":"Albany",
    "sg:classifiers":[
        {
            "category":"Food & Beverages",
            "subcategory":"Groceries & Convenience Stores",
            "type":"Retail Goods"
        }
    ],
    "sg:phone":"+1 510 525 5575",
    "sg:postcode":"94706",
    "sg:province":"CA",
    "wof:name":"Super Stop Market",
    "wof:placetype":"venue"
},
  "geometry": {"coordinates":[-122.299969,37.893396],"type":"Point"}
}