{
  "type": "Feature",
  "properties": {
    "iso:country":"US",
    "sg:address":"542 San Benito St",
    "sg:city":"Hollister",
    "sg:classifiers":[
        {
            "category":"Building & Trades",
            "subcategory":"Electrical",
            "type":"Services"
        }
    ],
    "sg:phone":"+1 831 637 3795",
    "sg:postcode":"95023",
    "sg:province":"CA",
    "sg:tags":[
        "electric",
        "contractor"
    ],
    "wof:name":"Enterprise Electric Co",
    "wof:placetype":"venue"
},
  "geometry": {"coordinates":[-121.40216599999999,36.850935],"type":"Point"}
}