{
  "type": "Feature",
  "properties": {
    "addr:full":"201 Manor Dr Stateline CA 89449",
    "addr:housenumber":"201",
    "addr:postcode":"89449",
    "addr:street":"Manor Dr",
    "iso:country":"US",
    "sg:address":"201 Manor Dr",
    "sg:city":"Stateline",
    "sg:classifiers":[
        {
            "category":"Banks & Credit Unions",
            "subcategory":"Investment Brokerage",
            "type":"Services"
        }
    ],
    "sg:phone":"+1 775 588 9642",
    "sg:postcode":"89449",
    "sg:province":"CA",
    "sg:tags":[
        "advisory",
        "financial"
    ],
    "wof:name":"L & L Financial Resources",
    "wof:placetype":"venue"
},
  "geometry": {"coordinates":[-119.929942,38.971482],"type":"Point"}
}