{
  "type": "Feature",
  "properties": {
    "iso:country":"US",
    "sg:address":"9507 Kristine Way",
    "sg:city":"Windsor",
    "sg:classifiers":[
        {
            "category":"Retail",
            "subcategory":"Laundry & Dry Cleaning",
            "type":"Services"
        }
    ],
    "sg:phone":"+1 707 836 7700",
    "sg:postcode":"95492",
    "sg:province":"CA",
    "sg:tags":[
        "cleaners",
        "rug",
        "carpet"
    ],
    "wof:name":"Dry Pex Carpet Care",
    "wof:placetype":"venue"
},
  "geometry": {"coordinates":[-122.810499,38.558895],"type":"Point"}
}