{
  "type": "Feature",
  "properties": {
    "addr:full":"2311 Altisma Way Carlsbad CA 92009",
    "addr:housenumber":"2311",
    "addr:postcode":"92009",
    "addr:street":"Altisma Way",
    "iso:country":"US",
    "sg:address":"2311 Altisma Way",
    "sg:city":"Carlsbad",
    "sg:classifiers":[
        {
            "category":"Professional",
            "subcategory":"Detective & Security Services",
            "type":"Services"
        }
    ],
    "sg:phone":"+1 760 929 9376",
    "sg:postcode":"92009",
    "sg:province":"CA",
    "sg:tags":[
        "information",
        "bureau"
    ],
    "wof:name":"Sinofile Information Services",
    "wof:placetype":"venue"
},
  "geometry": {"coordinates":[-117.257321,33.095945],"type":"Point"}
}