{
  "type": "Feature",
  "properties": {
    "addr:full":"4432 Ranchero Dr Soquel CA 95073",
    "addr:housenumber":"4432",
    "addr:postcode":"95073",
    "addr:street":"Ranchero Dr",
    "iso:country":"US",
    "sg:address":"4432 Ranchero Dr",
    "sg:city":"Soquel",
    "sg:classifiers":[
        {
            "category":"Professional",
            "type":"Services"
        }
    ],
    "sg:phone":"+1 831 334 5109",
    "sg:postcode":"95073",
    "sg:province":"CA",
    "wof:name":"All About You",
    "wof:placetype":"venue"
},
  "geometry": {"coordinates":[-121.960291,36.995879],"type":"Point"}
}