{
  "type": "Feature",
  "properties": {
    "iso:country":"US",
    "sg:address":"511 Bernard St",
    "sg:city":"Bakersfield",
    "sg:classifiers":[
        {
            "category":"Food & Beverages",
            "subcategory":"Groceries & Convenience Stores",
            "type":"Retail Goods"
        }
    ],
    "sg:phone":"+1 661 327 1228",
    "sg:postcode":"93305",
    "sg:province":"CA",
    "sg:tags":[
        "market"
    ],
    "wof:name":"R & S Market",
    "wof:placetype":"venue"
},
  "geometry": {"coordinates":[-118.9909,35.390161],"type":"Point"}
}