{
  "type": "Feature",
  "properties": {
    "iso:country":"US",
    "sg:address":"5214 E 12th St",
    "sg:city":"Oakland",
    "sg:classifiers":[
        {
            "category":"Building & Trades",
            "subcategory":"Construction",
            "type":"Services"
        }
    ],
    "sg:phone":"+1 510 536 7663",
    "sg:postcode":"94601",
    "sg:province":"CA",
    "sg:tags":[
        "roofing",
        "contractor"
    ],
    "sg:website":"www.rkroofing.com",
    "wof:name":"Rk Roofing & Construction",
    "wof:placetype":"venue"
},
  "geometry": {"coordinates":[-122.209,37.7663],"type":"Point"}
}