{
  "type": "Feature",
  "properties": {
    "addr:full":"791 8th St Arcata CA 95521",
    "addr:housenumber":"791",
    "addr:postcode":"95521",
    "addr:street":"8Th St",
    "iso:country":"US",
    "sg:address":"791 8th St",
    "sg:city":"Arcata",
    "sg:classifiers":[
        {
            "category":"Retail",
            "subcategory":"Portrait Studio",
            "type":"Services"
        },
        {
            "category":"Professional",
            "subcategory":"Art Services",
            "type":"Services"
        }
    ],
    "sg:phone":"+1 707 825 1061",
    "sg:postcode":"95521",
    "sg:province":"CA",
    "sg:tags":[
        "rental",
        "photographers-portrait",
        "photographic",
        "darkroom"
    ],
    "wof:name":"Arcata Photo Studios",
    "wof:placetype":"venue"
},
  "geometry": {"coordinates":[-124.087006,40.868243],"type":"Point"}
}