{
  "type": "Feature",
  "properties": {
    "addr:full":"25061 W Ave Standford Ste 120 Valencia CA 91355",
    "addr:housenumber":"25061",
    "addr:postcode":"91355",
    "addr:street":"W Ave;Ste 120",
    "iso:country":"US",
    "sg:address":"25061 W Ave Standford Ste 120",
    "sg:city":"Valencia",
    "sg:classifiers":[
        {
            "category":"Insurance",
            "subcategory":"Hazard Insurance",
            "type":"Services"
        }
    ],
    "sg:phone":"+1 661 799 1437",
    "sg:postcode":"91355",
    "sg:province":"CA",
    "sg:website":"www.icoverassets4u.com",
    "wof:name":"Farmers Insurance - Pablo Santibanez",
    "wof:placetype":"venue"
},
  "geometry": {"coordinates":[-118.574595,34.437411],"type":"Point"}
}