{
  "type": "Feature",
  "properties": {
    "addr:full":"7300 Capistrano Ave West Hills CA 91307",
    "addr:housenumber":"7300",
    "addr:postcode":"91307",
    "addr:street":"Capistrano Ave",
    "iso:country":"US",
    "sg:address":"7300 Capistrano Ave",
    "sg:city":"West Hills",
    "sg:classifiers":[
        {
            "category":"Building & Trades",
            "subcategory":"Construction",
            "type":"Services"
        }
    ],
    "sg:phone":"+1 818 713 0804",
    "sg:postcode":"91307",
    "sg:province":"CA",
    "sg:tags":[
        "carpenter"
    ],
    "wof:name":"S P Meichtry Construction",
    "wof:placetype":"venue"
},
  "geometry": {"coordinates":[-118.617594,34.203396],"type":"Point"}
}