{
  "type": "Feature",
  "properties": {
    "addr:full":"5010 Ave 308 Visalia CA 93291",
    "addr:housenumber":"5010",
    "addr:postcode":"93291",
    "addr:street":"Ave 308",
    "iso:country":"US",
    "sg:address":"5010 Ave 308",
    "sg:city":"Visalia",
    "sg:classifiers":[
        {
            "category":"Shopping",
            "subcategory":"Gifts & Souvenirs",
            "type":"Retail Goods"
        }
    ],
    "sg:phone":"+1 559 651 2438",
    "sg:postcode":"93291",
    "sg:province":"CA",
    "sg:tags":[
        "party",
        "supply"
    ],
    "wof:name":"Elissa's Pony Express",
    "wof:placetype":"venue"
},
  "geometry": {"coordinates":[-119.46174000000001,36.349108],"type":"Point"}
}