{
  "type": "Feature",
  "properties": {
    "iso:country":"US",
    "sg:address":"2725 E Pacific Coast Hwy Ste 101",
    "sg:city":"Signal Hill",
    "sg:classifiers":[
        {
            "category":"Personal",
            "type":"Services"
        }
    ],
    "sg:phone":"+1 310 408 3304",
    "sg:postcode":"90755",
    "sg:province":"CA",
    "sg:tags":[
        "local"
    ],
    "sg:website":"www.escalonaservices.com",
    "wof:name":"Escalona Services",
    "wof:placetype":"venue"
},
  "geometry": {"coordinates":[-118.159678,33.790131],"type":"Point"}
}