{
  "type": "Feature",
  "properties": {
    "iso:country":"US",
    "sg:address":"78677 Saguaro Rd",
    "sg:city":"La Quinta",
    "sg:classifiers":[
        {
            "category":"Food & Beverages",
            "subcategory":"Specialty",
            "type":"Retail Goods"
        }
    ],
    "sg:phone":"+1 760 360 0805",
    "sg:postcode":"92253",
    "sg:province":"CA",
    "sg:tags":[
        "health",
        "diet"
    ],
    "wof:name":"Low Carbz",
    "wof:placetype":"venue"
},
  "geometry": {"coordinates":[-116.292536,33.687489],"type":"Point"}
}