{
  "type": "Feature",
  "properties": {
    "addr:full":"3560 Oro Dam Blvd E Oroville CA 95965",
    "addr:housenumber":"3560",
    "addr:postcode":"95965",
    "addr:street":"Oro Dam Blvd E",
    "iso:country":"US",
    "sg:address":"3560 Oro Dam Blvd E",
    "sg:city":"Oroville",
    "sg:classifiers":[
        {
            "category":"Food & Beverages",
            "subcategory":"Groceries & Convenience Stores",
            "type":"Retail Goods"
        }
    ],
    "sg:phone":"+1 530 533 3211",
    "sg:postcode":"95965",
    "sg:province":"CA",
    "wof:name":"7-Eleven",
    "wof:placetype":"venue"
},
  "geometry": {"coordinates":[-121.534955,39.517314],"type":"Point"}
}