{
  "type": "Feature",
  "properties": {
    "addr:full":"2027 N Main St Salinas CA 93906",
    "addr:housenumber":"2027",
    "addr:postcode":"93906",
    "addr:street":"N Main St",
    "iso:country":"US",
    "sg:address":"2027 N Main St",
    "sg:city":"Salinas",
    "sg:classifiers":[
        {
            "category":"Personal",
            "subcategory":"Beauty Salon",
            "type":"Services"
        }
    ],
    "sg:phone":"+1 831 442 9602",
    "sg:postcode":"93906",
    "sg:province":"CA",
    "wof:name":"Marta's MAJIC Hand",
    "wof:placetype":"venue"
},
  "geometry": {"coordinates":[-121.656352,36.722087],"type":"Point"}
}