{
  "type": "Feature",
  "properties": {
    "iso:country":"US",
    "sg:address":"8629 Mellowoods Way",
    "sg:city":"Sacramento",
    "sg:classifiers":[
        {
            "category":"Banks & Credit Unions",
            "subcategory":"Financial Services",
            "type":"Services"
        }
    ],
    "sg:phone":"+1 916 688 5549",
    "sg:postcode":"95828",
    "sg:province":"CA",
    "sg:tags":[
        "investor"
    ],
    "wof:name":"K&D Real Estate Investments",
    "wof:placetype":"venue"
},
  "geometry": {"coordinates":[-121.384936,38.475551],"type":"Point"}
}