{
  "type": "Feature",
  "properties": {
    "addr:full":"21819 Avalon Blvd Carson CA 90745",
    "addr:housenumber":"21819",
    "addr:postcode":"90745",
    "addr:street":"Avalon Blvd",
    "iso:country":"US",
    "sg:address":"21819 Avalon Blvd",
    "sg:city":"Carson",
    "sg:classifiers":[
        {
            "category":"Autos & Motor Vehicles",
            "subcategory":"Auto Supplies",
            "type":"Retail Goods"
        },
        {
            "category":"Wholesale",
            "subcategory":"Auto Parts",
            "type":"Manufacturing & Wholesale Goods"
        },
        {
            "category":"Retail",
            "subcategory":"Auto Repair",
            "type":"Services"
        }
    ],
    "sg:phone":"+1 310 549 2936",
    "sg:postcode":"90745",
    "sg:province":"CA",
    "sg:tags":[
        "body",
        "equipment",
        "truck",
        "automobile",
        "accessory"
    ],
    "sg:website":"http://www.oreillyauto.com?utm_source=yellowpages&utm_medium=iyp&utm_campaign=3023",
    "wof:name":"Kragen Auto Parts",
    "wof:placetype":"venue"
},
  "geometry": {"coordinates":[-118.264,33.829601],"type":"Point"}
}