{
  "type": "Feature",
  "properties": {
    "iso:country":"US",
    "sg:address":"211 E Orangethorpe Ave",
    "sg:city":"Fullerton",
    "sg:classifiers":[
        {
            "category":"Restaurant",
            "type":"Food & Drink"
        }
    ],
    "sg:phone":"+1 714 870 1333",
    "sg:postcode":"92832",
    "sg:province":"CA",
    "sg:tags":[
        "thai"
    ],
    "wof:name":"Thai Original BBQ",
    "wof:placetype":"venue"
},
  "geometry": {"coordinates":[-117.921997,33.8596],"type":"Point"}
}