{
  "type": "Feature",
  "properties": {
    "addr:full":"15401 Carmenita Rd Santa Fe Springs CA 90670",
    "addr:postcode":"15401;90670",
    "addr:street":"Carmenita Rd",
    "iso:country":"US",
    "sg:address":"15401 Carmenita Rd",
    "sg:city":"Santa Fe Springs",
    "sg:classifiers":[
        {
            "category":"Wholesale",
            "subcategory":"Apparel",
            "type":"Manufacturing & Wholesale Goods"
        }
    ],
    "sg:phone":"+1 562 802 0419",
    "sg:postcode":"90670",
    "sg:province":"CA",
    "sg:tags":[
        "clothing"
    ],
    "wof:name":"Juni Fashions Inc",
    "wof:placetype":"venue"
},
  "geometry": {"coordinates":[-118.04661,33.889839],"type":"Point"}
}