{
  "type": "Feature",
  "properties": {
    "addr:full":"306 S Glendora Ave West Covina CA 91790",
    "addr:housenumber":"306",
    "addr:postcode":"91790",
    "addr:street":"S Glendora Ave",
    "iso:country":"US",
    "sg:address":"306 S Glendora Ave",
    "sg:city":"West Covina",
    "sg:classifiers":[
        {
            "category":"Personal",
            "subcategory":"Beauty Salon",
            "type":"Services"
        }
    ],
    "sg:phone":"+1 626 917 4500",
    "sg:postcode":"91790",
    "sg:province":"CA",
    "wof:name":"Euphoria",
    "wof:placetype":"venue"
},
  "geometry": {"coordinates":[-117.924542,34.067991],"type":"Point"}
}