{
  "type": "Feature",
  "properties": {
    "addr:full":"8440 Cerritos Ave Ste H Stanton CA 90680",
    "addr:housenumber":"8440",
    "addr:postcode":"ca 90680",
    "addr:street":"Cerritos Ave Ste H",
    "iso:country":"US",
    "sg:address":"8440 Cerritos Ave Ste H",
    "sg:city":"Stanton",
    "sg:classifiers":[
        {
            "category":"Home & Garden",
            "subcategory":"Furniture",
            "type":"Retail Goods"
        }
    ],
    "sg:phone":"+1 714 828 8560",
    "sg:postcode":"90680",
    "sg:province":"CA",
    "sg:tags":[
        "store"
    ],
    "wof:name":"Wild Instinct Futons",
    "wof:placetype":"venue"
},
  "geometry": {"coordinates":[-117.985345,33.810095],"type":"Point"}
}