{
  "type": "Feature",
  "properties": {
    "iso:country":"US",
    "sg:address":"1644 Sandal Wood Pl",
    "sg:city":"Thousand Oaks",
    "sg:classifiers":[
        {
            "category":"Local Transit",
            "type":"Transportation"
        }
    ],
    "sg:phone":"+1 805 492 5050",
    "sg:postcode":"91362",
    "sg:province":"CA",
    "sg:tags":[
        "passenger"
    ],
    "wof:name":"Tc Transportation",
    "wof:placetype":"venue"
},
  "geometry": {"coordinates":[-118.846139,34.213777],"type":"Point"}
}