{
  "type": "Feature",
  "properties": {
    "iso:country":"US",
    "sg:address":"9811 Kika Court",
    "sg:city":"San Diego",
    "sg:classifiers":[
        {
            "category":"Professional",
            "subcategory":"Computer Services",
            "type":"Services"
        }
    ],
    "sg:phone":"+1 858 430 3899",
    "sg:postcode":"92129 ",
    "sg:province":"CA",
    "sg:tags":[
        "virtual-teams",
        "collaboration",
        "agile-software"
    ],
    "sg:website":"http://www.extremeplanner.com/",
    "wof:name":"Extreme Planner",
    "wof:placetype":"venue"
},
  "geometry": {"coordinates":[-117.111943,32.940544],"type":"Point"}
}