{
  "type": "Feature",
  "properties": {
    "iso:country":"US",
    "sg:address":"39660 Kirkwood Ct",
    "sg:city":"Rancho Mirage",
    "sg:classifiers":[
        {
            "category":"Professional",
            "subcategory":"Lawyer & Legal Services",
            "type":"Services"
        }
    ],
    "sg:phone":"+1 760 770 0760",
    "sg:postcode":"92270",
    "sg:province":"CA",
    "wof:name":"Price Law Group",
    "wof:placetype":"venue"
},
  "geometry": {"coordinates":[-116.419979,33.760314],"type":"Point"}
}