{
  "type": "Feature",
  "properties": {
    "addr:full":"655 N Central Ave Glendale CA 91203",
    "addr:housenumber":"655",
    "addr:postcode":"91203",
    "addr:street":"N Central Ave",
    "iso:country":"US",
    "sg:address":"655 N Central Ave",
    "sg:city":"Glendale",
    "sg:classifiers":[
        {
            "category":"Personal",
            "subcategory":"Shoe Repair & Shine",
            "type":"Services"
        }
    ],
    "sg:phone":"+1 818 240 5585",
    "sg:postcode":"91203",
    "sg:province":"CA",
    "wof:name":"Aved Shoe Repair",
    "wof:placetype":"venue"
},
  "geometry": {"coordinates":[-118.258003,34.1553],"type":"Point"}
}