{
  "type": "Feature",
  "properties": {
    "addr:full":"1204 Magnolia Ave Corona CA 92833",
    "addr:housenumber":"1204",
    "addr:postcode":"92833",
    "addr:street":"Magnolia Ave",
    "iso:country":"US",
    "sg:address":"1204 Magnolia Ave",
    "sg:city":"Corona",
    "sg:classifiers":[
        {
            "category":"Autos & Motor Vehicles",
            "subcategory":"Fuel & Gas Station",
            "type":"Retail Goods"
        }
    ],
    "sg:phone":"+1 951 278 2220",
    "sg:postcode":"92833",
    "sg:province":"CA",
    "sg:tags":[
        "oil"
    ],
    "wof:name":"Mobil Oil Corp SOI",
    "wof:placetype":"venue"
},
  "geometry": {"coordinates":[-117.976145,33.860056],"type":"Point"}
}