{
  "type": "Feature",
  "properties": {
    "addr:full":"6856 Van Nuys Blvd Van Nuys CA 91405",
    "addr:housenumber":"6856",
    "addr:postcode":"91405",
    "addr:street":"Van Nuys Blvd",
    "iso:country":"US",
    "sg:address":"6856 Van Nuys Blvd",
    "sg:city":"Van Nuys",
    "sg:classifiers":[
        {
            "category":"Wholesale",
            "subcategory":"Machinery & Supplies",
            "type":"Manufacturing & Wholesale Goods"
        }
    ],
    "sg:phone":"+1 818 786 2125",
    "sg:postcode":"91405",
    "sg:province":"CA",
    "sg:tags":[
        "janitor"
    ],
    "wof:name":"Mc Calla Co Janitorial Supply",
    "wof:placetype":"venue"
},
  "geometry": {"coordinates":[-118.44864699999999,34.197339],"type":"Point"}
}