{
  "type": "Feature",
  "properties": {
    "addr:full":"454 11th Ave San Francisco CA 94118",
    "addr:housenumber":"454",
    "addr:postcode":"94118",
    "addr:street":"11Th Ave",
    "iso:country":"US",
    "sg:address":"454 11th Ave",
    "sg:city":"San Francisco",
    "sg:classifiers":[
        {
            "category":"Professional",
            "subcategory":"Computer Services",
            "type":"Services"
        }
    ],
    "sg:phone":"+1 415 652 3248",
    "sg:postcode":"94118",
    "sg:province":"CA",
    "sg:tags":[
        "repair"
    ],
    "sg:website":"www.golddengatecomputer.com",
    "wof:name":"Golden Gate Computer Company",
    "wof:placetype":"venue"
},
  "geometry": {"coordinates":[-122.469227,37.779696],"type":"Point"}
}