{
  "type": "Feature",
  "properties": {
    "addr:full":"725 E 10th St Oakland CA 94606",
    "addr:housenumber":"725",
    "addr:postcode":"94606",
    "addr:street":"E 10Th St",
    "iso:country":"US",
    "sg:address":"725 E 10th St",
    "sg:city":"Oakland",
    "sg:classifiers":[
        {
            "category":"Manufacturing",
            "subcategory":"Retail Goods",
            "type":"Manufacturing & Wholesale Goods"
        }
    ],
    "sg:phone":"+1 510 839 1736",
    "sg:postcode":"94606",
    "sg:province":"CA",
    "sg:tags":[
        "product",
        "mfg"
    ],
    "wof:name":"John Dove",
    "wof:placetype":"venue"
},
  "geometry": {"coordinates":[-122.25500700000001,37.792209],"type":"Point"}
}