{
  "type": "Feature",
  "properties": {
    "addr:full":"1800 E 16th St Santa Ana CA 92701",
    "addr:housenumber":"1800",
    "addr:postcode":"92701",
    "addr:street":"E 16Th St",
    "iso:country":"US",
    "sg:address":"1800 E 16th St",
    "sg:city":"Santa Ana",
    "sg:classifiers":[
        {
            "category":"Professional",
            "subcategory":"Engineering",
            "type":"Services"
        }
    ],
    "sg:phone":"+1 714 835 2800",
    "sg:postcode":"92701",
    "sg:province":"CA",
    "sg:tags":[
        "engineer"
    ],
    "wof:name":"Esi Fme Inc",
    "wof:placetype":"venue"
},
  "geometry": {"coordinates":[-117.83904099999999,33.758966],"type":"Point"}
}