{
  "type": "Feature",
  "properties": {
    "iso:country":"US",
    "sg:address":"90 E Latimer Ave",
    "sg:city":"Campbell",
    "sg:classifiers":[
        {
            "category":"Education",
            "subcategory":"School",
            "type":"Public Place"
        }
    ],
    "sg:phone":"+1 408 370 3073",
    "sg:postcode":"95008",
    "sg:province":"CA",
    "sg:tags":[
        "elementary"
    ],
    "sg:website":"www.casadimir.org",
    "wof:name":"Casa Di Mir Montessori School",
    "wof:placetype":"venue"
},
  "geometry": {"coordinates":[-121.948292,37.290209],"type":"Point"}
}