{
  "type": "Feature",
  "properties": {
    "addr:full":"2270 Douglas Blvd Roseville CA 95678",
    "addr:housenumber":"2270",
    "addr:postcode":"95678",
    "addr:street":"Douglas Blvd",
    "iso:country":"US",
    "sg:address":"2270 Douglas Blvd",
    "sg:city":"Roseville",
    "sg:classifiers":[
        {
            "category":"Real Estate",
            "subcategory":"Real Estate Agent",
            "type":"Services"
        }
    ],
    "sg:phone":"+1 916 600 0880",
    "sg:postcode":"95678",
    "sg:province":"CA",
    "wof:name":"Holdwell Banker",
    "wof:placetype":"venue"
},
  "geometry": {"coordinates":[-121.248593,38.744206],"type":"Point"}
}