{
  "type": "Feature",
  "properties": {
    "addr:full":"4129 Georgia St San Diego CA 92103",
    "addr:housenumber":"4129",
    "addr:postcode":"92103",
    "addr:street":"Georgia St",
    "iso:country":"US",
    "sg:address":"4129 Georgia St",
    "sg:city":"San Diego",
    "sg:classifiers":[
        {
            "category":"Sports & Exercise",
            "subcategory":"Gym",
            "type":"Entertainment"
        }
    ],
    "sg:phone":"+1 619 296 6991",
    "sg:postcode":"92103",
    "sg:province":"CA",
    "sg:tags":[
        "club",
        "health",
        "studio",
        "gymnasium"
    ],
    "wof:name":"Myogenics Fitness",
    "wof:placetype":"venue"
},
  "geometry": {"coordinates":[-117.14491700000001,32.753487],"type":"Point"}
}