{
  "type": "Feature",
  "properties": {
    "iso:country":"US",
    "sg:address":"5821 Dennis Mccarthy Dr",
    "sg:city":"Lebec",
    "sg:classifiers":[
        {
            "category":"Fast Food",
            "type":"Food & Drink"
        },
        {
            "category":"Restaurant",
            "type":"Food & Drink"
        },
        {
            "category":"Food & Beverages",
            "subcategory":"Groceries & Convenience Stores",
            "type":"Retail Goods"
        }
    ],
    "sg:phone":"+1 661 663 4330",
    "sg:postcode":"93243",
    "sg:province":"CA",
    "sg:tags":[
        "shop",
        "american",
        "sandwich",
        "take"
    ],
    "sg:website":"http://www.subway.com",
    "wof:name":"Subway",
    "wof:placetype":"venue"
},
  "geometry": {"coordinates":[-118.948353,34.984699],"type":"Point"}
}