{
  "type": "Feature",
  "properties": {
    "addr:full":"840 W 9th St Upland CA 91786",
    "addr:housenumber":"840",
    "addr:postcode":"91786",
    "addr:street":"W 9Th St",
    "iso:country":"US",
    "sg:address":"840 W 9th St",
    "sg:city":"Upland",
    "sg:classifiers":[
        {
            "category":"Wholesale",
            "subcategory":"Photographic Equipment",
            "type":"Manufacturing & Wholesale Goods"
        }
    ],
    "sg:phone":"+1 909 981 2806",
    "sg:postcode":"91786",
    "sg:province":"CA",
    "sg:tags":[
        "audio"
    ],
    "wof:name":"Case Logic Inc",
    "wof:placetype":"venue"
},
  "geometry": {"coordinates":[-117.662909,34.095987],"type":"Point"}
}