{
  "type": "Feature",
  "properties": {
    "addr:full":"14851 Yorba St Tustin CA 92780",
    "addr:housenumber":"14851",
    "addr:postcode":"92780",
    "addr:street":"Yorba St",
    "iso:country":"US",
    "sg:address":"14851 Yorba St",
    "sg:city":"Tustin",
    "sg:classifiers":[
        {
            "category":"Health Services",
            "subcategory":"Hospital",
            "type":"Services"
        }
    ],
    "sg:phone":"+1 714 832 9200",
    "sg:postcode":"92780",
    "sg:province":"CA",
    "wof:name":"Healthsouth Tustin Rehabilitation Hospi Tal",
    "wof:placetype":"venue"
},
  "geometry": {"coordinates":[-117.83000199999999,33.746201],"type":"Point"}
}