{
  "type": "Feature",
  "properties": {
    "addr:full":"76450 Covelo Rd Covelo CA 95428",
    "addr:postcode":"76450;95428",
    "addr:street":"Covelo Rd",
    "iso:country":"US",
    "sg:address":"76450 Covelo Rd",
    "sg:city":"Covelo",
    "sg:classifiers":[
        {
            "category":"Home & Garden",
            "subcategory":"Building Materials",
            "type":"Retail Goods"
        }
    ],
    "sg:phone":"+1 707 983 6413",
    "sg:postcode":"95428",
    "sg:province":"CA",
    "sg:tags":[
        "lumber"
    ],
    "wof:name":"Northern Builders Supply",
    "wof:placetype":"venue"
},
  "geometry": {"coordinates":[-123.24800399999999,39.800587],"type":"Point"}
}