{
  "type": "Feature",
  "properties": {
    "iso:country":"US",
    "sg:address":"5930 Rickenbacker Ave",
    "sg:city":"Riverside",
    "sg:classifiers":[
        {
            "category":"Building & Trades",
            "subcategory":"Construction",
            "type":"Services"
        }
    ],
    "sg:phone":"+1 951 352 9832",
    "sg:postcode":"92504",
    "sg:province":"CA",
    "sg:tags":[
        "system",
        "specialty",
        "heating",
        "contractor",
        "air conditioning"
    ],
    "wof:name":"Mechanical Air Control",
    "wof:placetype":"venue"
},
  "geometry": {"coordinates":[-117.45836199999999,33.959586],"type":"Point"}
}