{
  "type": "Feature",
  "properties": {
    "addr:full":"654 N Santa Cruz Ave Ste C # 137 Los Gatos CA 95030",
    "addr:housenumber":"654",
    "addr:postcode":"95030",
    "addr:street":"N Santa Cruz Ave Ste C # 137",
    "iso:country":"US",
    "sg:address":"654 N Santa Cruz Ave Ste C # 137",
    "sg:city":"Los Gatos",
    "sg:classifiers":[
        {
            "category":"Building & Trades",
            "subcategory":"Plumbing",
            "type":"Services"
        },
        {
            "category":"Building & Trades",
            "subcategory":"Construction",
            "type":"Services"
        }
    ],
    "sg:phone":"+1 408 613 6566",
    "sg:postcode":"95030",
    "sg:province":"CA",
    "sg:tags":[
        "contractor"
    ],
    "sg:website":"www.mrrescueplumbing.com/losgatos",
    "wof:name":"Mr. Rescue Plumbing & Drain Cleaning of Los Gatos",
    "wof:placetype":"venue"
},
  "geometry": {"coordinates":[-121.977976,37.235058],"type":"Point"}
}