{
  "type": "Feature",
  "properties": {
    "addr:full":"720 Adams St Davis CA 95616",
    "addr:housenumber":"720",
    "addr:postcode":"95616",
    "addr:street":"Adams St",
    "iso:country":"US",
    "sg:address":"720 Adams St",
    "sg:city":"Davis",
    "sg:classifiers":[
        {
            "category":"Real Estate",
            "subcategory":"Real Estate Operator",
            "type":"Services"
        }
    ],
    "sg:phone":"+1 530 759 0665",
    "sg:postcode":"95616",
    "sg:province":"CA",
    "sg:tags":[
        "apartment"
    ],
    "wof:name":"Walnut Manor",
    "wof:placetype":"venue"
},
  "geometry": {"coordinates":[-121.769249,38.548711],"type":"Point"}
}