{
  "type": "Feature",
  "properties": {
    "iso:country":"US",
    "sg:address":"803 W el Camino Real",
    "sg:city":"Mountain View",
    "sg:classifiers":[
        {
            "category":"Retail",
            "subcategory":"Laundry & Dry Cleaning",
            "type":"Services"
        }
    ],
    "sg:phone":"+1 650 967 8737",
    "sg:postcode":"94040",
    "sg:province":"CA",
    "sg:tags":[
        "cleaners"
    ],
    "wof:name":"Super Fluff Cleaners & Laundry",
    "wof:placetype":"venue"
},
  "geometry": {"coordinates":[-122.082599,37.38489],"type":"Point"}
}