{
  "type": "Feature",
  "properties": {
    "iso:country":"US",
    "sg:address":"795 Shard Ct",
    "sg:city":"Fremont",
    "sg:classifiers":[
        {
            "category":"Professional",
            "subcategory":"Business Services",
            "type":"Services"
        }
    ],
    "sg:phone":"+1 510 438 0219",
    "sg:postcode":"94539",
    "sg:province":"CA",
    "sg:tags":[
        "interior",
        "consultant",
        "design",
        "decorator"
    ],
    "wof:name":"All About Interiors",
    "wof:placetype":"venue"
},
  "geometry": {"coordinates":[-121.91799899999999,37.484402],"type":"Point"}
}