{
  "type": "Feature",
  "properties": {
    "iso:country":"US",
    "sg:address":"2008 Cotner Ave",
    "sg:city":"Los Angeles",
    "sg:classifiers":[
        {
            "category":"Autos & Motor Vehicles",
            "subcategory":"Auto Supplies",
            "type":"Retail Goods"
        }
    ],
    "sg:phone":"+1 310 445 3246",
    "sg:postcode":"90025",
    "sg:province":"CA",
    "sg:tags":[
        "battery"
    ],
    "wof:name":"Interstate Battery System",
    "wof:placetype":"venue"
},
  "geometry": {"coordinates":[-118.440562,34.040859],"type":"Point"}
}