{
  "type": "Feature",
  "properties": {
    "iso:country":"US",
    "sg:address":"2143 N Point St",
    "sg:city":"San Francisco",
    "sg:classifiers":[
        {
            "category":"Professional",
            "subcategory":"Advertising",
            "type":"Services"
        }
    ],
    "sg:phone":"+1 415 346 9091",
    "sg:postcode":"94123",
    "sg:province":"CA",
    "sg:tags":[
        "marketing"
    ],
    "sg:website":"www.solarmarketinggroup.com",
    "wof:name":"Solar Marketing Group",
    "wof:placetype":"venue"
},
  "geometry": {"coordinates":[-122.44248399999999,37.802878],"type":"Point"}
}