{
  "type": "Feature",
  "properties": {
    "addr:full":"2020 E Orangethorpe Ave Fullerton CA 92831",
    "addr:housenumber":"2020",
    "addr:postcode":"92831",
    "addr:street":"E Orangethorpe Ave",
    "iso:country":"US",
    "sg:address":"2020 E Orangethorpe Ave",
    "sg:city":"Fullerton",
    "sg:classifiers":[
        {
            "category":"Real Estate",
            "subcategory":"Real Estate Services",
            "type":"Services"
        }
    ],
    "sg:phone":"+1 714 680 3812",
    "sg:postcode":"92831",
    "sg:province":"CA",
    "sg:tags":[
        "management",
        "property"
    ],
    "wof:name":"Le Baron Investments",
    "wof:placetype":"venue"
},
  "geometry": {"coordinates":[-117.89496200000001,33.859512],"type":"Point"}
}