{
  "type": "Feature",
  "properties": {
    "addr:full":"1310 South Ave Turlock CA 95380",
    "addr:housenumber":"1310",
    "addr:postcode":"95380",
    "addr:street":"South Ave",
    "iso:country":"US",
    "sg:address":"1310 South Ave",
    "sg:city":"Turlock",
    "sg:classifiers":[
        {
            "category":"Shopping",
            "subcategory":"Stationery & Office Supplies",
            "type":"Retail Goods"
        }
    ],
    "sg:phone":"+1 800 606 4522",
    "sg:postcode":"95380",
    "sg:province":"CA",
    "sg:tags":[
        "machine",
        "copy"
    ],
    "wof:name":"Dedicated Copy-Rapid Copy",
    "wof:placetype":"venue"
},
  "geometry": {"coordinates":[-120.86515199999999,37.48547],"type":"Point"}
}