{
  "type": "Feature",
  "properties": {
    "iso:country":"US",
    "sg:address":"2421 Country Club Blvd",
    "sg:city":"Stockton",
    "sg:classifiers":[
        {
            "category":"Building & Trades",
            "subcategory":"Landscaping Services",
            "type":"Services"
        }
    ],
    "sg:phone":"+1 209 942 1341",
    "sg:postcode":"95204",
    "sg:province":"CA",
    "sg:tags":[
        "landscape",
        "contractor"
    ],
    "wof:name":"Sloniker & Daughter Landscape",
    "wof:placetype":"venue"
},
  "geometry": {"coordinates":[-121.333608,37.964833],"type":"Point"}
}