{
  "type": "Feature",
  "properties": {
    "iso:country":"US",
    "sg:address":"1145 Martin Luther King Jr Way",
    "sg:city":"Merced",
    "sg:classifiers":[
        {
            "category":"Autos & Motor Vehicles",
            "subcategory":"Fuel & Gas Station",
            "type":"Retail Goods"
        },
        {
            "category":"Autos & Motor Vehicles",
            "subcategory":"Automobile Sales",
            "type":"Retail Goods"
        },
        {
            "category":"Autos & Motor Vehicles",
            "subcategory":"Auto Supplies",
            "type":"Retail Goods"
        },
        {
            "category":"Retail",
            "subcategory":"Auto Repair",
            "type":"Services"
        }
    ],
    "sg:phone":"+1 209 723 0726",
    "sg:postcode":"95341",
    "sg:province":"CA",
    "sg:tags":[
        "exhaust",
        "oil",
        "painting",
        "clutch",
        "body",
        "system",
        "equipment",
        "lube",
        "brake",
        "air conditioning",
        "muffler",
        "inspection",
        "repairing"
    ],
    "wof:name":"Performance Auto Repair",
    "wof:placetype":"venue"
},
  "geometry": {"coordinates":[-120.483706,37.294478],"type":"Point"}
}