{
  "type": "Feature",
  "properties": {
    "addr:full":"13957 Spring Water Ct Garden Grove CA 92843",
    "addr:housenumber":"13957",
    "addr:postcode":"92843",
    "addr:street":"Spring Water Ct",
    "iso:country":"US",
    "sg:address":"13957 Spring Water Ct",
    "sg:city":"Garden Grove",
    "sg:classifiers":[
        {
            "category":"Manufacturing",
            "subcategory":"Printing",
            "type":"Manufacturing & Wholesale Goods"
        }
    ],
    "sg:phone":"+1 714 554 8912",
    "sg:postcode":"92843",
    "sg:province":"CA",
    "sg:tags":[
        "newspaper"
    ],
    "wof:name":"Khemarak Newspaper",
    "wof:placetype":"venue"
},
  "geometry": {"coordinates":[-117.913174,33.760382],"type":"Point"}
}