{
  "type": "Feature",
  "properties": {
    "iso:country":"US",
    "sg:address":"150 9th St",
    "sg:city":"San Francisco",
    "sg:classifiers":[
        {
            "category":"Social Services",
            "type":"Services"
        }
    ],
    "sg:phone":"+1 415 863 4582",
    "sg:postcode":"94103",
    "sg:province":"CA",
    "sg:tags":[
        "organization",
        "welfare"
    ],
    "wof:name":"El Dorado Hotel",
    "wof:placetype":"venue"
},
  "geometry": {"coordinates":[-122.413361,37.775088],"type":"Point"}
}