{
  "type": "Feature",
  "properties": {
    "addr:full":"10203 E St Oakland CA 94603",
    "addr:housenumber":"10203",
    "addr:postcode":"94603",
    "addr:street":"E St",
    "iso:country":"US",
    "sg:address":"10203 E St",
    "sg:city":"Oakland",
    "sg:classifiers":[
        {
            "category":"Building & Trades",
            "subcategory":"Construction",
            "type":"Services"
        }
    ],
    "sg:phone":"+1 510 638 2800",
    "sg:postcode":"94603",
    "sg:province":"CA",
    "sg:tags":[
        "asbestos",
        "cleaners-interior",
        "removal"
    ],
    "sg:website":"www.sterlingenv.com",
    "wof:name":"Sterling Environmental",
    "wof:placetype":"venue"
},
  "geometry": {"coordinates":[-122.174189,37.738384],"type":"Point"}
}