{
  "type": "Feature",
  "properties": {
    "iso:country":"US",
    "sg:address":"3852 Inverness Way",
    "sg:city":"Livermore",
    "sg:classifiers":[
        {
            "category":"Banks & Credit Unions",
            "subcategory":"Bank",
            "type":"Services"
        }
    ],
    "sg:phone":"+1 925 580 2231",
    "sg:postcode":"94551",
    "sg:province":"CA",
    "sg:tags":[
        "broker",
        "mortgage"
    ],
    "wof:name":"Best Rate Home Loans",
    "wof:placetype":"venue"
},
  "geometry": {"coordinates":[-121.75245700000001,37.692355],"type":"Point"}
}