{
  "type": "Feature",
  "properties": {
    "iso:country":"US",
    "sg:address":"423 Central Ave",
    "sg:city":"Fillmore",
    "sg:classifiers":[
        {
            "category":"Communications",
            "type":"Services"
        }
    ],
    "sg:phone":"+1 805 524 2191",
    "sg:postcode":"93015",
    "sg:province":"CA",
    "wof:name":"Mickey's Communications",
    "wof:placetype":"venue"
},
  "geometry": {"coordinates":[-118.913979,34.401683],"type":"Point"}
}