{
  "type": "Feature",
  "properties": {
    "iso:country":"US",
    "sg:address":"17956 S Mountain Rd",
    "sg:city":"Santa Paula",
    "sg:classifiers":[
        {
            "category":"Mining & Drilling",
            "type":"Manufacturing & Wholesale Goods"
        }
    ],
    "sg:phone":"+1 805 525 7839",
    "sg:postcode":"93060",
    "sg:province":"CA",
    "sg:tags":[
        "production",
        "gas"
    ],
    "wof:name":"Vintage Petroleum Inc",
    "wof:placetype":"venue"
},
  "geometry": {"coordinates":[-119.04816599999999,34.345072],"type":"Point"}
}