{
  "type": "Feature",
  "properties": {
    "iso:country":"US",
    "sg:address":"5817 Crenshaw Boulevard",
    "sg:city":"Los Angeles",
    "sg:classifiers":[
        {
            "category":"Restaurant",
            "type":"Food & Drink"
        }
    ],
    "sg:phone":"+1 323 296 4200",
    "sg:postcode":"90043",
    "sg:province":"CA",
    "wof:name":"Kentucky Fried Chicken",
    "wof:placetype":"venue"
},
  "geometry": {"coordinates":[-118.330819,33.988784],"type":"Point"}
}