{
  "type": "Feature",
  "properties": {
    "iso:country":"US",
    "sg:address":"794 Lighthouse Ave",
    "sg:city":"Monterey",
    "sg:classifiers":[
        {
            "category":"Restaurant",
            "type":"Food & Drink"
        }
    ],
    "sg:phone":"+1 831 642 0231",
    "sg:postcode":"93940",
    "sg:province":"CA",
    "sg:tags":[
        "house",
        "steak",
        "mediterranean"
    ],
    "wof:name":"Amir's Kabob House",
    "wof:placetype":"venue"
},
  "geometry": {"coordinates":[-121.90358000000001,36.615784],"type":"Point"}
}