{
  "type": "Feature",
  "properties": {
    "addr:full":"176 Lawrence St Quincy CA 95971",
    "addr:housenumber":"176",
    "addr:postcode":"95971",
    "addr:street":"Lawrence St",
    "iso:country":"US",
    "sg:address":"176 Lawrence St",
    "sg:city":"Quincy",
    "sg:classifiers":[
        {
            "category":"Organizations",
            "subcategory":"Religious Organization",
            "type":"Services"
        }
    ],
    "sg:phone":"+1 530 283 0890",
    "sg:postcode":"95971",
    "sg:province":"CA",
    "sg:tags":[
        "place",
        "worship",
        "church"
    ],
    "wof:name":"Catholic Church",
    "wof:placetype":"venue"
},
  "geometry": {"coordinates":[-120.94197800000001,39.937729],"type":"Point"}
}