{
  "type": "Feature",
  "properties": {
    "iso:country":"US",
    "sg:address":"3304 14th St",
    "sg:city":"Riverside",
    "sg:classifiers":[
        {
            "category":"Retail",
            "subcategory":"Car Wash",
            "type":"Services"
        }
    ],
    "sg:phone":"+1 951 684 5560",
    "sg:postcode":"92501",
    "sg:province":"CA",
    "sg:tags":[
        "polishing",
        "washing"
    ],
    "wof:name":"Bubble Machine Car Wash",
    "wof:placetype":"venue"
},
  "geometry": {"coordinates":[-117.374692,33.974407],"type":"Point"}
}