{
  "type": "Feature",
  "properties": {
    "addr:full":"3930 W El Segundo Blvd Hawthorne CA 90250",
    "addr:housenumber":"3930",
    "addr:postcode":"90250",
    "addr:street":"W El Segundo Blvd",
    "iso:country":"US",
    "sg:address":"3930 W El Segundo Blvd",
    "sg:city":"Hawthorne",
    "sg:classifiers":[
        {
            "category":"Fast Food",
            "type":"Food & Drink"
        }
    ],
    "sg:phone":"+1 310 644 7773",
    "sg:postcode":"90250",
    "sg:province":"CA",
    "sg:tags":[
        "burger"
    ],
    "wof:name":"Burger King",
    "wof:placetype":"venue"
},
  "geometry": {"coordinates":[-118.342871,33.916411],"type":"Point"}
}