{
  "type": "Feature",
  "properties": {
    "addr:full":"410 13th St Oakland CA 94612",
    "addr:housenumber":"410",
    "addr:postcode":"94612",
    "addr:street":"13Th St",
    "iso:country":"US",
    "sg:address":"410 13th St",
    "sg:city":"Oakland",
    "sg:classifiers":[
        {
            "category":"Shopping",
            "subcategory":"Jewelry",
            "type":"Retail Goods"
        }
    ],
    "sg:phone":"+1 510 645 1029",
    "sg:postcode":"94612",
    "sg:province":"CA",
    "sg:tags":[
        "jeweler"
    ],
    "wof:name":"Crown Jewelers",
    "wof:placetype":"venue"
},
  "geometry": {"coordinates":[-122.27142600000001,37.803631],"type":"Point"}
}