{
  "type": "Feature",
  "properties": {
    "addr:full":"39 Rue Fontainbleau Newport Beach CA 92660",
    "addr:housenumber":"39",
    "addr:postcode":"92660",
    "addr:street":"Rue Fontainbleau",
    "iso:country":"US",
    "sg:address":"39 Rue Fontainbleau",
    "sg:city":"Newport Beach",
    "sg:classifiers":[
        {
            "category":"Sports & Exercise",
            "subcategory":"Gym",
            "type":"Entertainment"
        }
    ],
    "sg:phone":"+1 949 760 6079",
    "sg:postcode":"92660",
    "sg:province":"CA",
    "sg:website":"www.wcsfitness.com",
    "wof:name":"WCS Fitness",
    "wof:placetype":"venue"
},
  "geometry": {"coordinates":[-117.877213,33.626312],"type":"Point"}
}