{
  "type": "Feature",
  "properties": {
    "addr:full":"16 Antelope Blvd. Red Bluff CA 96080",
    "addr:housenumber":"16",
    "addr:postcode":"96080",
    "addr:street":"Antelope Blvd.",
    "iso:country":"US",
    "sg:address":"16 Antelope Blvd.",
    "sg:city":"Red Bluff",
    "sg:classifiers":[
        {
            "category":"Professional",
            "subcategory":"Computer Services",
            "type":"Services"
        }
    ],
    "sg:phone":"+1 888 873 0712",
    "sg:postcode":"96080",
    "sg:province":"CA",
    "sg:tags":[
        "photo-scanning-services",
        "scan-old-photos",
        "convert-photos-to-digital",
        "scan-slides",
        "scan-negatives",
        "photo-scan-to-dvd",
        "convert-vhs-to-digital",
        "scanning-negatives-to-dvd",
        "scanning-slides-dvd"
    ],
    "sg:website":"http://www.gophoto.com",
    "wof:name":"GoPhoto",
    "wof:placetype":"venue"
},
  "geometry": {"coordinates":[-122.225354,40.180585],"type":"Point"}
}