{
  "type": "Feature",
  "properties": {
    "addr:full":"12810 Sherman Way North Hollywood CA 91605",
    "addr:housenumber":"12810",
    "addr:postcode":"91605",
    "addr:street":"Sherman Way",
    "iso:country":"US",
    "sg:address":"12810 Sherman Way",
    "sg:city":"North Hollywood",
    "sg:classifiers":[
        {
            "category":"Autos & Motor Vehicles",
            "subcategory":"Automobile Sales",
            "type":"Retail Goods"
        }
    ],
    "sg:phone":"+1 818 765 4755",
    "sg:postcode":"91605",
    "sg:province":"CA",
    "sg:tags":[
        "car",
        "dealer"
    ],
    "wof:name":"In & Out Auto Sales",
    "wof:placetype":"venue"
},
  "geometry": {"coordinates":[-118.411783,34.20112],"type":"Point"}
}