{
  "type": "Feature",
  "properties": {
    "addr:full":"3333 Midway Dr San Diego CA 92110",
    "addr:housenumber":"3333",
    "addr:postcode":"92110",
    "addr:street":"Midway Dr",
    "iso:country":"US",
    "sg:address":"3333 Midway Dr",
    "sg:city":"San Diego",
    "sg:classifiers":[
        {
            "category":"Cinema",
            "subcategory":"Movie Rental",
            "type":"Entertainment"
        }
    ],
    "sg:phone":"+1 619 523 0879",
    "sg:postcode":"92110",
    "sg:province":"CA",
    "sg:tags":[
        "leasing",
        "video",
        "disc",
        "tape"
    ],
    "wof:name":"Erectus Video",
    "wof:placetype":"venue"
},
  "geometry": {"coordinates":[-117.212048,32.750348],"type":"Point"}
}