{
  "type": "Feature",
  "properties": {
    "addr:full":"1740 Spring St Paso Robles CA 93446",
    "addr:housenumber":"1740",
    "addr:postcode":"93446",
    "addr:street":"Spring St",
    "iso:country":"US",
    "sg:address":"1740 Spring St",
    "sg:city":"Paso Robles",
    "sg:classifiers":[
        {
            "category":"Farming",
            "subcategory":"Farm & Veterinary Services",
            "type":"Manufacturing & Wholesale Goods"
        }
    ],
    "sg:phone":"+1 805 239 2276",
    "sg:postcode":"93446",
    "sg:province":"CA",
    "sg:tags":[
        "management"
    ],
    "wof:name":"Perez Contracting",
    "wof:placetype":"venue"
},
  "geometry": {"coordinates":[-120.691749,35.632497],"type":"Point"}
}