{
  "type": "Feature",
  "properties": {
    "iso:country":"US",
    "sg:address":"606 Indian Hill Blvd",
    "sg:city":"Pomona",
    "sg:classifiers":[
        {
            "category":"Shopping",
            "type":"Retail Goods"
        }
    ],
    "sg:phone":"+1 909 624 9788",
    "sg:postcode":"91767",
    "sg:province":"CA",
    "sg:tags":[
        "cosmetic",
        "perfume"
    ],
    "wof:name":"Angel's Beauty Supply",
    "wof:placetype":"venue"
},
  "geometry": {"coordinates":[-117.719133,34.064384],"type":"Point"}
}