{
  "type": "Feature",
  "properties": {
    "iso:country":"US",
    "sg:address":"5850 W 3rd Street",
    "sg:city":"Los Angeles",
    "sg:classifiers":[
        {
            "category":"Retail",
            "subcategory":"Laundry & Dry Cleaning",
            "type":"Services"
        }
    ],
    "sg:phone":"+1 323 954 1295",
    "sg:postcode":"90036",
    "sg:province":"CA",
    "wof:name":"Mitage Cleaners",
    "wof:placetype":"venue"
},
  "geometry": {"coordinates":[-118.347404,34.069204],"type":"Point"}
}