{
  "type": "Feature",
  "properties": {
    "addr:full":"3472 Keaton Loop San Jose CA 95121",
    "addr:housenumber":"3472",
    "addr:postcode":"95121",
    "addr:street":"Keaton Loop",
    "iso:country":"US",
    "sg:address":"3472 Keaton Loop",
    "sg:city":"San Jose",
    "sg:classifiers":[
        {
            "category":"Banks & Credit Unions",
            "subcategory":"Investment Brokerage",
            "type":"Services"
        }
    ],
    "sg:phone":"+1 408 532 0366",
    "sg:postcode":"95121",
    "sg:province":"CA",
    "wof:name":"American Delta Investment",
    "wof:placetype":"venue"
},
  "geometry": {"coordinates":[-121.78852000000001,37.311716],"type":"Point"}
}