{
  "type": "Feature",
  "properties": {
    "iso:country":"US",
    "sg:address":"46183 Butternut Ln",
    "sg:city":"Squaw Valley",
    "sg:classifiers":[
        {
            "category":"Home & Garden",
            "subcategory":"Hardware",
            "type":"Retail Goods"
        },
        {
            "category":"Wholesale",
            "subcategory":"Hardware",
            "type":"Manufacturing & Wholesale Goods"
        }
    ],
    "sg:phone":"+1 559 338 2423",
    "sg:postcode":"93675",
    "sg:province":"CA",
    "sg:tags":[
        "tool"
    ],
    "wof:name":"Terry's Tools",
    "wof:placetype":"venue"
},
  "geometry": {"coordinates":[-119.120811,36.696463],"type":"Point"}
}