{
  "type": "Feature",
  "properties": {
    "iso:country":"US",
    "sg:address":"143 Cranford Rd",
    "sg:city":"Trinidad",
    "sg:classifiers":[
        {
            "category":"Building & Trades",
            "subcategory":"Construction",
            "type":"Services"
        }
    ],
    "sg:phone":"+1 707 677 1680",
    "sg:postcode":"95570",
    "sg:province":"CA",
    "sg:tags":[
        "house",
        "contractor",
        "nonresidential"
    ],
    "wof:name":"Hubbert Construction Co",
    "wof:placetype":"venue"
},
  "geometry": {"coordinates":[-124.106832,41.048421],"type":"Point"}
}