{
  "type": "Feature",
  "properties": {
    "addr:full":"2261 Palma Dr Ventura CA 93003",
    "addr:housenumber":"2261",
    "addr:postcode":"93003",
    "addr:street":"Palma Dr",
    "iso:country":"US",
    "sg:address":"2261 Palma Dr",
    "sg:city":"Ventura",
    "sg:classifiers":[
        {
            "category":"Health Services",
            "subcategory":"Medical Lab",
            "type":"Services"
        }
    ],
    "sg:phone":"+1 805 339 9532",
    "sg:postcode":"93003",
    "sg:province":"CA",
    "sg:tags":[
        "laboratory"
    ],
    "wof:name":"DNS",
    "wof:placetype":"venue"
},
  "geometry": {"coordinates":[-119.227107,34.251437],"type":"Point"}
}