{
  "type": "Feature",
  "properties": {
    "addr:full":"25959 Summer Hill Ct Murrieta CA 92563",
    "addr:housenumber":"25959",
    "addr:postcode":"92563",
    "addr:street":"Summer Hill Ct",
    "iso:country":"US",
    "sg:address":"25959 Summer Hill Ct",
    "sg:city":"Murrieta",
    "sg:classifiers":[
        {
            "category":"Professional",
            "type":"Services"
        }
    ],
    "sg:phone":"+1 951 696 0922",
    "sg:postcode":"92563",
    "sg:province":"CA",
    "wof:name":"Automatic Custom Gate",
    "wof:placetype":"venue"
},
  "geometry": {"coordinates":[-117.166442,33.557021],"type":"Point"}
}