{
  "type": "Feature",
  "properties": {
    "iso:country":"US",
    "sg:address":"717 N Western Ave",
    "sg:city":"Los Angeles",
    "sg:classifiers":[
        {
            "category":"Retail",
            "subcategory":"Auto Repair",
            "type":"Services"
        }
    ],
    "sg:phone":"+1 323 465 2397",
    "sg:postcode":"90029",
    "sg:province":"CA",
    "sg:tags":[
        "body",
        "automobile",
        "painting"
    ],
    "wof:name":"Siam Auto Repair",
    "wof:placetype":"venue"
},
  "geometry": {"coordinates":[-118.30922099999999,34.083884],"type":"Point"}
}