{
  "type": "Feature",
  "properties": {
    "iso:country":"US",
    "sg:address":"227 S Riverside Ave",
    "sg:city":"Rialto",
    "sg:classifiers":[
        {
            "category":"Personal",
            "subcategory":"Piercing",
            "type":"Services"
        }
    ],
    "sg:phone":"+1 909 421 8282",
    "sg:postcode":"92376",
    "sg:province":"CA",
    "sg:tags":[
        "body"
    ],
    "wof:name":"Heroes & Madman Tattoo",
    "wof:placetype":"venue"
},
  "geometry": {"coordinates":[-117.37020099999999,34.09745],"type":"Point"}
}