{
  "type": "Feature",
  "properties": {
    "addr:full":"48477 Harrison St Coachella CA 92236",
    "addr:housenumber":"48477",
    "addr:postcode":"92236",
    "addr:street":"Harrison St",
    "iso:country":"US",
    "sg:address":"48477 Harrison St",
    "sg:city":"Coachella",
    "sg:classifiers":[
        {
            "category":"Autos & Motor Vehicles",
            "subcategory":"Automobile Sales",
            "type":"Retail Goods"
        }
    ],
    "sg:phone":"+1 760 398 6088",
    "sg:postcode":"92236",
    "sg:province":"CA",
    "sg:tags":[
        "car",
        "dealer"
    ],
    "wof:name":"Jiquilpan Auto Sale",
    "wof:placetype":"venue"
},
  "geometry": {"coordinates":[-116.18163,33.698599],"type":"Point"}
}