{
  "type": "Feature",
  "properties": {
    "iso:country":"US",
    "sg:address":"1040 N Las Palmas Avenue",
    "sg:city":"Los Angeles",
    "sg:classifiers":[
        {
            "category":"Professional",
            "type":"Services"
        }
    ],
    "sg:phone":"+1 323 860 3553",
    "sg:postcode":"90038",
    "sg:province":"CA",
    "sg:tags":[
        "caterer"
    ],
    "wof:name":"Food",
    "wof:placetype":"venue"
},
  "geometry": {"coordinates":[-118.336152,34.089514],"type":"Point"}
}