{
  "type": "Feature",
  "properties": {
    "iso:country":"US",
    "sg:address":"2850 Webster St",
    "sg:city":"San Francisco",
    "sg:classifiers":[
        {
            "category":"Professional",
            "subcategory":"Management & Consulting",
            "type":"Services"
        }
    ],
    "sg:phone":"+1 415 441 2366",
    "sg:postcode":"94123",
    "sg:province":"CA",
    "sg:tags":[
        "consultant",
        "educational"
    ],
    "wof:name":"Patricia Henery",
    "wof:placetype":"venue"
},
  "geometry": {"coordinates":[-122.433697,37.796835],"type":"Point"}
}