{
  "type": "Feature",
  "properties": {
    "addr:full":"7645 San Fernando Rd Sun Valley CA 91352",
    "addr:housenumber":"7645",
    "addr:postcode":"91352",
    "addr:street":"San Fernando Rd",
    "iso:country":"US",
    "sg:address":"7645 San Fernando Rd",
    "sg:city":"Sun Valley",
    "sg:classifiers":[
        {
            "category":"Wholesale",
            "subcategory":"Durable Goods & Equipment",
            "type":"Manufacturing & Wholesale Goods"
        }
    ],
    "sg:phone":"+1 818 504 7765",
    "sg:postcode":"91352",
    "sg:province":"CA",
    "sg:tags":[
        "novelty"
    ],
    "wof:name":"Kat Inc",
    "wof:placetype":"venue"
},
  "geometry": {"coordinates":[-118.354463,34.209514],"type":"Point"}
}