{
  "type": "Feature",
  "properties": {
    "addr:full":"4426 Atlantic Ave Long Beach CA 90807",
    "addr:housenumber":"4426",
    "addr:postcode":"90807",
    "addr:street":"Atlantic Ave",
    "iso:country":"US",
    "sg:address":"4426 Atlantic Ave",
    "sg:city":"Long Beach",
    "sg:classifiers":[
        {
            "category":"Professional",
            "subcategory":"Accounting & Tax Preparation",
            "type":"Services"
        }
    ],
    "sg:phone":"+1 562 428 9800",
    "sg:postcode":"90807",
    "sg:province":"CA",
    "sg:tags":[
        "accountant"
    ],
    "sg:website":"www.libertytax.com",
    "wof:name":"Liberty Tax Service",
    "wof:placetype":"venue"
},
  "geometry": {"coordinates":[-118.18437299999999,33.837887],"type":"Point"}
}