{
  "type": "Feature",
  "properties": {
    "iso:country":"US",
    "sg:address":"31765 E Kings Canyon Rd",
    "sg:city":"Squaw Valley",
    "sg:classifiers":[
        {
            "category":"Food & Beverages",
            "subcategory":"Specialty",
            "type":"Retail Goods"
        }
    ],
    "sg:phone":"+1 559 332 2909",
    "sg:postcode":"93675",
    "sg:province":"CA",
    "sg:tags":[
        "herb"
    ],
    "wof:name":"Squaw Valley Herb Gardens",
    "wof:placetype":"venue"
},
  "geometry": {"coordinates":[-119.232595,36.744349],"type":"Point"}
}