{
  "type": "Feature",
  "properties": {
    "addr:full":"60 Liberty Ship Way Sausalito CA 94965",
    "addr:housenumber":"60",
    "addr:postcode":"94965",
    "addr:street":"Liberty Ship Way",
    "iso:country":"US",
    "sg:address":"60 Liberty Ship Way",
    "sg:city":"Sausalito",
    "sg:classifiers":[
        {
            "category":"Manufacturing",
            "subcategory":"Apparel",
            "type":"Manufacturing & Wholesale Goods"
        }
    ],
    "sg:phone":"+1 415 289 0885",
    "sg:postcode":"94965",
    "sg:province":"CA",
    "sg:tags":[
        "product",
        "mfg"
    ],
    "wof:name":"Ship Shape Canvas",
    "wof:placetype":"venue"
},
  "geometry": {"coordinates":[-122.491956,37.863329],"type":"Point"}
}