{
  "type": "Feature",
  "properties": {
    "addr:full":"11922 Garfield Ave South Gate CA 90280",
    "addr:housenumber":"11922",
    "addr:postcode":"90280",
    "addr:street":"Garfield Ave;Gate",
    "iso:country":"US",
    "sg:address":"11922 Garfield Ave",
    "sg:city":"South Gate",
    "sg:classifiers":[
        {
            "category":"Health Services",
            "subcategory":"Dentist",
            "type":"Services"
        }
    ],
    "sg:phone":"+1 562 531 1194",
    "sg:postcode":"90280",
    "sg:province":"CA",
    "wof:name":"Sullivan Michael Dr",
    "wof:placetype":"venue"
},
  "geometry": {"coordinates":[-118.168999,33.917999],"type":"Point"}
}