{
  "type": "Feature",
  "properties": {
    "addr:full":"12832 Muscatine St Pacoima CA 91331",
    "addr:housenumber":"12832",
    "addr:postcode":"91331",
    "addr:street":"Muscatine St",
    "iso:country":"US",
    "sg:address":"12832 Muscatine St",
    "sg:city":"Pacoima",
    "sg:classifiers":[
        {
            "category":"Manufacturing",
            "subcategory":"Apparel",
            "type":"Manufacturing & Wholesale Goods"
        }
    ],
    "sg:phone":"+1 818 767 5721",
    "sg:postcode":"91331",
    "sg:province":"CA",
    "sg:tags":[
        "sewing",
        "contractor"
    ],
    "wof:name":"Angela Torti Fashion Inc",
    "wof:placetype":"venue"
},
  "geometry": {"coordinates":[-118.412249,34.239461],"type":"Point"}
}