{
  "type": "Feature",
  "properties": {
    "iso:country":"US",
    "sg:address":"730 Skylake Way",
    "sg:city":"Sacramento",
    "sg:classifiers":[
        {
            "category":"Wholesale",
            "subcategory":"Apparel",
            "type":"Manufacturing & Wholesale Goods"
        }
    ],
    "sg:phone":"+1 818 430 1821",
    "sg:postcode":"95831",
    "sg:province":"CA",
    "sg:tags":[
        "wear",
        "formal"
    ],
    "wof:name":"Formal Headquarters Intnl",
    "wof:placetype":"venue"
},
  "geometry": {"coordinates":[-121.533547,38.499393],"type":"Point"}
}