{
  "type": "Feature",
  "properties": {
    "addr:full":"13344 S Main St Los Angeles CA 90061",
    "addr:housenumber":"13344",
    "addr:postcode":"90061",
    "addr:street":"S Main St",
    "iso:country":"US",
    "sg:address":"13344 S Main St",
    "sg:city":"Los Angeles",
    "sg:classifiers":[
        {
            "category":"Wholesale",
            "subcategory":"Apparel",
            "type":"Manufacturing & Wholesale Goods"
        },
        {
            "category":"Professional",
            "subcategory":"Business Services",
            "type":"Services"
        }
    ],
    "sg:phone":"+1 310 965 1900",
    "sg:postcode":"90061",
    "sg:province":"CA",
    "sg:tags":[
        "textile"
    ],
    "wof:name":"Paradigm Industries Inc",
    "wof:placetype":"venue"
},
  "geometry": {"coordinates":[-118.273898,33.91146],"type":"Point"}
}