{
  "type": "Feature",
  "properties": {
    "iso:country":"US",
    "sg:address":"30 Cleveland St",
    "sg:city":"San Francisco",
    "sg:classifiers":[
        {
            "category":"Sports & Exercise",
            "subcategory":"Gym",
            "type":"Entertainment"
        }
    ],
    "sg:phone":"+1 415 830 7220",
    "sg:postcode":"94103",
    "sg:province":"CA",
    "sg:tags":[
        "trainer",
        "pilate"
    ],
    "sg:website":"www.altercenter.com",
    "wof:name":"AlterCenter",
    "wof:placetype":"venue"
},
  "geometry": {"coordinates":[-122.406926,37.776813],"type":"Point"}
}