{
  "type": "Feature",
  "properties": {
    "addr:full":"23830 Cassel Fall River Rd Fall River Mills CA 96028",
    "addr:postcode":"23830;96028",
    "addr:street":"Fall River Rd",
    "iso:country":"US",
    "sg:address":"23830 Cassel Fall River Rd",
    "sg:city":"Fall River Mills",
    "sg:classifiers":[
        {
            "category":"Freight",
            "type":"Transportation"
        }
    ],
    "sg:phone":"+1 530 336 5075",
    "sg:postcode":"96028",
    "sg:province":"CA",
    "sg:tags":[
        "operator",
        "local",
        "trucking"
    ],
    "wof:name":"Wellemeyer Trucking",
    "wof:placetype":"venue"
},
  "geometry": {"coordinates":[-121.433162,40.975683],"type":"Point"}
}