{
  "type": "Feature",
  "properties": {
    "addr:full":"1136 Howard St San Francisco CA 94103",
    "addr:housenumber":"1136",
    "addr:postcode":"94103",
    "addr:street":"Howard St",
    "iso:country":"US",
    "sg:address":"1136 Howard St",
    "sg:city":"San Francisco",
    "sg:classifiers":[
        {
            "category":"Professional",
            "subcategory":"Management & Consulting",
            "type":"Services"
        }
    ],
    "sg:phone":"+1 415 255 6710",
    "sg:postcode":"94103",
    "sg:province":"CA",
    "sg:tags":[
        "consultant",
        "energy",
        "conservation"
    ],
    "wof:name":"Breidinger & Assoc",
    "wof:placetype":"venue"
},
  "geometry": {"coordinates":[-122.41031099999999,37.777393],"type":"Point"}
}