{
  "type": "Feature",
  "properties": {
    "addr:full":"10633 Roselle St San Diego CA 92121",
    "addr:housenumber":"10633",
    "addr:postcode":"92121",
    "addr:street":"Roselle St",
    "iso:country":"US",
    "sg:address":"10633 Roselle St",
    "sg:city":"San Diego",
    "sg:classifiers":[
        {
            "category":"Wholesale",
            "subcategory":"Durable Goods & Equipment",
            "type":"Manufacturing & Wholesale Goods"
        }
    ],
    "sg:phone":"+1 760 728 0127",
    "sg:postcode":"92121",
    "sg:province":"CA",
    "sg:tags":[
        "fire",
        "extinguisher"
    ],
    "wof:name":"Fallbrook Fire Extinguisher",
    "wof:placetype":"venue"
},
  "geometry": {"coordinates":[-117.22199500000001,32.897384],"type":"Point"}
}