{
  "type": "Feature",
  "properties": {
    "iso:country":"US",
    "sg:address":"810 Emerald St",
    "sg:city":"San Diego",
    "sg:classifiers":[
        {
            "category":"Professional",
            "subcategory":"Lawyer & Legal Services",
            "type":"Services"
        }
    ],
    "sg:phone":"+1 858 490 1327",
    "sg:postcode":"92109",
    "sg:province":"CA",
    "sg:tags":[
        "attorney"
    ],
    "wof:name":"Robert Gary Medof Attorney-Law",
    "wof:placetype":"venue"
},
  "geometry": {"coordinates":[-117.254409,32.798866],"type":"Point"}
}