{
  "type": "Feature",
  "properties": {
    "addr:full":"306 Livorna Heights Rd Alamo CA 94507",
    "addr:housenumber":"306",
    "addr:postcode":"94507",
    "addr:street":"Livorna Heights Rd",
    "iso:country":"US",
    "sg:address":"306 Livorna Heights Rd",
    "sg:city":"Alamo",
    "sg:classifiers":[
        {
            "category":"Banks & Credit Unions",
            "subcategory":"Investment Brokerage",
            "type":"Services"
        }
    ],
    "sg:phone":"+1 925 935 1014",
    "sg:postcode":"94507",
    "sg:province":"CA",
    "sg:tags":[
        "consultant",
        "planning",
        "financial"
    ],
    "wof:name":"Alamo Financial Svc Group",
    "wof:placetype":"venue"
},
  "geometry": {"coordinates":[-122.02440300000001,37.869641],"type":"Point"}
}