{
  "type": "Feature",
  "properties": {
    "iso:country":"US",
    "sg:address":"1960 Sequoia Ave",
    "sg:city":"Simi Valley",
    "sg:classifiers":[
        {
            "category":"Health Services",
            "subcategory":"Doctor",
            "type":"Services"
        }
    ],
    "sg:phone":"+1 805 584 3999",
    "sg:postcode":"93063",
    "sg:province":"CA",
    "sg:tags":[
        "dentist"
    ],
    "wof:name":"Sequoia Dentistry",
    "wof:placetype":"venue"
},
  "geometry": {"coordinates":[-118.730414,34.27088],"type":"Point"}
}