{
  "type": "Feature",
  "properties": {
    "iso:country":"US",
    "sg:address":"6151 Foxfield Ln",
    "sg:city":"Yorba Linda",
    "sg:classifiers":[
        {
            "category":"Professional",
            "type":"Services"
        }
    ],
    "sg:phone":"+1 714 779 6379",
    "sg:postcode":"92886",
    "sg:province":"CA",
    "wof:name":"John H Mac Queen",
    "wof:placetype":"venue"
},
  "geometry": {"coordinates":[-117.795735,33.874463],"type":"Point"}
}