{
  "type": "Feature",
  "properties": {
    "addr:full":"3550 Saviers Rd Oxnard CA 93033",
    "addr:housenumber":"3550",
    "addr:postcode":"93033",
    "addr:street":"Saviers Rd",
    "iso:country":"US",
    "sg:address":"3550 Saviers Rd",
    "sg:city":"Oxnard",
    "sg:classifiers":[
        {
            "category":"Restaurant",
            "type":"Food & Drink"
        }
    ],
    "sg:phone":"+1 805 247 9221",
    "sg:postcode":"93033",
    "sg:province":"CA",
    "wof:name":"Mariscos Lel Pulpo",
    "wof:placetype":"venue"
},
  "geometry": {"coordinates":[-119.17753999999999,34.168334],"type":"Point"}
}