{
  "type": "Feature",
  "properties": {
    "iso:country":"US",
    "sg:address":"983 Rose Arbor Dr",
    "sg:city":"San Marcos",
    "sg:classifiers":[
        {
            "category":"Wholesale",
            "subcategory":"Chemicals & Plastics",
            "type":"Manufacturing & Wholesale Goods"
        }
    ],
    "sg:phone":"+1 760 741 1036",
    "sg:postcode":"92078",
    "sg:province":"CA",
    "wof:name":"Natrochem Intl",
    "wof:placetype":"venue"
},
  "geometry": {"coordinates":[-117.13742000000001,33.12945],"type":"Point"}
}