{
  "type": "Feature",
  "properties": {
    "iso:country":"US",
    "sg:address":"4754 Mchenry Ave",
    "sg:city":"Modesto",
    "sg:classifiers":[
        {
            "category":"Autos & Motor Vehicles",
            "subcategory":"Automobile Sales",
            "type":"Retail Goods"
        },
        {
            "category":"Autos & Motor Vehicles",
            "subcategory":"Auto Supplies",
            "type":"Retail Goods"
        },
        {
            "category":"Retail",
            "subcategory":"Auto Repair",
            "type":"Services"
        }
    ],
    "sg:phone":"+1 209 549 5000",
    "sg:postcode":"95356",
    "sg:province":"CA",
    "sg:tags":[
        "car",
        "part",
        "used",
        "leasing",
        "new"
    ],
    "sg:website":"http://www.mistlinhonda.com",
    "wof:name":"Mistlin Honda Automobiles Sales & Service",
    "wof:placetype":"venue"
},
  "geometry": {"coordinates":[-120.99481,37.707631],"type":"Point"}
}