{
  "type": "Feature",
  "properties": {
    "addr:full":"2121 Imperial Ave San Diego CA 92101",
    "addr:housenumber":"2121",
    "addr:postcode":"92101",
    "addr:street":"Imperial Ave",
    "iso:country":"US",
    "sg:address":"2121 Imperial Ave",
    "sg:city":"San Diego",
    "sg:classifiers":[
        {
            "category":"Retail",
            "subcategory":"Repair Shop",
            "type":"Services"
        }
    ],
    "sg:phone":"+1 619 234 6397",
    "sg:postcode":"92101",
    "sg:province":"CA",
    "sg:tags":[
        "jewelry"
    ],
    "wof:name":"JTA Jewelry & Watch Repair",
    "wof:placetype":"venue"
},
  "geometry": {"coordinates":[-117.144141,32.706199],"type":"Point"}
}