{
  "type": "Feature",
  "properties": {
    "iso:country":"US",
    "sg:address":"13689 Calimesa Blvd",
    "sg:city":"Yucaipa",
    "sg:classifiers":[
        {
            "category":"Personal",
            "subcategory":"Barber",
            "type":"Services"
        }
    ],
    "sg:phone":"+1 909 795 4097",
    "sg:postcode":"92399",
    "sg:province":"CA",
    "wof:name":"Ron & Judy's Barber Shop",
    "wof:placetype":"venue"
},
  "geometry": {"coordinates":[-117.062635,34.00516],"type":"Point"}
}