{
  "type": "Feature",
  "properties": {
    "addr:full":"4703 71st St La Mesa CA 91941",
    "addr:housenumber":"4703",
    "addr:postcode":"91941",
    "addr:street":"71St St",
    "iso:country":"US",
    "sg:address":"4703 71st St",
    "sg:city":"La Mesa",
    "sg:classifiers":[
        {
            "category":"Building & Trades",
            "subcategory":"Construction",
            "type":"Services"
        }
    ],
    "sg:phone":"+1 619 463 3202",
    "sg:postcode":"91941",
    "sg:province":"CA",
    "sg:tags":[
        "house",
        "architect",
        "architectural"
    ],
    "wof:name":"Swulius Jack Architect",
    "wof:placetype":"venue"
},
  "geometry": {"coordinates":[-117.045998,32.764599],"type":"Point"}
}