{
  "type": "Feature",
  "properties": {
    "iso:country":"US",
    "sg:address":"204 Locust St",
    "sg:city":"Santa Cruz",
    "sg:classifiers":[
        {
            "category":"Shopping",
            "subcategory":"Books",
            "type":"Retail Goods"
        }
    ],
    "sg:phone":"+1 831 457 1195",
    "sg:postcode":"95060",
    "sg:province":"CA",
    "sg:tags":[
        "bookstore"
    ],
    "sg:website":"www.literaryguillotine.com",
    "wof:name":"The Literary Guillotine",
    "wof:placetype":"venue"
},
  "geometry": {"coordinates":[-122.02800000000001,36.975101],"type":"Point"}
}