{
  "type": "Feature",
  "properties": {
    "iso:country":"US",
    "sg:address":"1904 Bailey St",
    "sg:city":"Los Angeles",
    "sg:classifiers":[
        {
            "category":"Health Services",
            "subcategory":"Doctor",
            "type":"Services"
        }
    ],
    "sg:phone":"+1 323 222 9675",
    "sg:postcode":"90033",
    "sg:province":"CA",
    "sg:tags":[
        "physician",
        "surgeon"
    ],
    "sg:website":"www.whitememorial.com",
    "wof:name":"Occupational Medicine Ctr",
    "wof:placetype":"venue"
},
  "geometry": {"coordinates":[-118.213385,34.052612],"type":"Point"}
}