{
  "type": "Feature",
  "properties": {
    "iso:country":"US",
    "sg:address":"8885 Venice Boulevard",
    "sg:city":"Los Angeles",
    "sg:classifiers":[
        {
            "category":"Building & Trades",
            "subcategory":"Construction",
            "type":"Services"
        }
    ],
    "sg:phone":"+1 310 280 9025",
    "sg:postcode":"90034",
    "sg:province":"CA",
    "sg:tags":[
        "contractor"
    ],
    "wof:name":"Basix Design and Remodeling",
    "wof:placetype":"venue"
},
  "geometry": {"coordinates":[-118.387742,34.029755],"type":"Point"}
}