{
  "type": "Feature",
  "properties": {
    "addr:full":"3500 Wilbur Ave Antioch CA 94509",
    "addr:housenumber":"3500",
    "addr:postcode":"ca 94509",
    "addr:street":"Wilbur Ave",
    "iso:country":"US",
    "sg:address":"3500 Wilbur Ave",
    "sg:city":"Antioch",
    "sg:classifiers":[
        {
            "category":"Wholesale",
            "subcategory":"Machinery & Supplies",
            "type":"Manufacturing & Wholesale Goods"
        },
        {
            "category":"Bars & Pubs",
            "subcategory":"Oxygen Bar",
            "type":"Food & Drink"
        },
        {
            "category":"Shopping",
            "type":"Retail Goods"
        }
    ],
    "sg:phone":"+1 925 779 1401",
    "sg:postcode":"94509",
    "sg:province":"CA",
    "sg:tags":[
        "gas-industrial",
        "medical-cylinder",
        "bulk",
        "equipment",
        "safety",
        "clothing",
        "equipment-renting",
        "welding"
    ],
    "wof:name":"East Bay Welding Supply",
    "wof:placetype":"venue"
},
  "geometry": {"coordinates":[-121.75519,38.012274],"type":"Point"}
}