{
  "type": "Feature",
  "properties": {
    "addr:full":"21 Blair Ave Oakland CA 94611",
    "addr:housenumber":"21",
    "addr:postcode":"94611",
    "addr:street":"Blair Ave",
    "iso:country":"US",
    "sg:address":"21 Blair Ave",
    "sg:city":"Oakland",
    "sg:classifiers":[
        {
            "category":"Professional",
            "type":"Services"
        }
    ],
    "sg:phone":"+1 510 584 9222",
    "sg:postcode":"94611",
    "sg:province":"CA",
    "wof:name":"Michael Kennedy",
    "wof:placetype":"venue"
},
  "geometry": {"coordinates":[-122.239912,37.82522],"type":"Point"}
}