{
  "type": "Feature",
  "properties": {
    "iso:country":"US",
    "sg:address":"320 W Cerritos Ave",
    "sg:city":"Glendale",
    "sg:classifiers":[
        {
            "category":"Wholesale",
            "subcategory":"Medical Equipment & Supplies",
            "type":"Manufacturing & Wholesale Goods"
        }
    ],
    "sg:phone":"+1 714 285 1891",
    "sg:postcode":"91204",
    "sg:province":"CA",
    "wof:name":"Fresenius Usa Inc",
    "wof:placetype":"venue"
},
  "geometry": {"coordinates":[-118.258252,34.124148],"type":"Point"}
}