{
  "type": "Feature",
  "properties": {
    "addr:full":"4000 Klose Way Richmond CA 94806",
    "addr:postcode":"4000;94806",
    "addr:street":"Klose Way",
    "iso:country":"US",
    "sg:address":"4000 Klose Way",
    "sg:city":"Richmond",
    "sg:classifiers":[
        {
            "category":"Shopping",
            "subcategory":"Books",
            "type":"Retail Goods"
        }
    ],
    "sg:phone":"+1 510 222 3266",
    "sg:postcode":"94806",
    "sg:province":"CA",
    "sg:tags":[
        "dealer"
    ],
    "wof:name":"Barnes & Noble Booksellers",
    "wof:placetype":"venue"
},
  "geometry": {"coordinates":[-122.321567,37.981854],"type":"Point"}
}