{
  "type": "Feature",
  "properties": {
    "addr:full":"6024 E Larkellen Ct Agoura Hills CA 91377",
    "addr:housenumber":"6024",
    "addr:postcode":"91377",
    "addr:street":"E Larkellen Ct",
    "iso:country":"US",
    "sg:address":"6024 E Larkellen Ct",
    "sg:city":"Agoura Hills",
    "sg:classifiers":[
        {
            "category":"Building & Trades",
            "subcategory":"Landscaping Services",
            "type":"Services"
        }
    ],
    "sg:phone":"+1 818 865 8979",
    "sg:postcode":"91377",
    "sg:province":"CA",
    "wof:name":"Cannon Design",
    "wof:placetype":"venue"
},
  "geometry": {"coordinates":[-118.76022399999999,34.175992],"type":"Point"}
}