{
  "type": "Feature",
  "properties": {
    "addr:full":"24250 Town Center Dr Valencia CA 91355",
    "addr:housenumber":"24250",
    "addr:postcode":"91355",
    "addr:street":"Town Center Dr",
    "iso:country":"US",
    "sg:address":"24250 Town Center Dr",
    "sg:city":"Valencia",
    "sg:classifiers":[
        {
            "category":"Personal",
            "subcategory":"Beauty Salon",
            "type":"Services"
        }
    ],
    "sg:phone":"+1 661 799 9556",
    "sg:postcode":"91355",
    "sg:province":"CA",
    "sg:tags":[
        "hair"
    ],
    "sg:website":"www.carltonhairinternational.com",
    "wof:name":"Carlton Hair",
    "wof:placetype":"venue"
},
  "geometry": {"coordinates":[-118.55999799999999,34.417099],"type":"Point"}
}