{
  "type": "Feature",
  "properties": {
    "addr:full":"195 S San Antonio Rd Los Altos CA 94022",
    "addr:housenumber":"195",
    "addr:postcode":"94022",
    "addr:street":"S San Antonio Rd",
    "iso:country":"US",
    "sg:address":"195 S San Antonio Rd",
    "sg:city":"Los Altos",
    "sg:classifiers":[
        {
            "category":"Real Estate",
            "subcategory":"Real Estate Agent",
            "type":"Services"
        }
    ],
    "sg:phone":"+1 650 941 4300",
    "sg:postcode":"94022",
    "sg:province":"CA",
    "sg:website":"www.campi.com",
    "wof:name":"Campi Properties Inc",
    "wof:placetype":"venue"
},
  "geometry": {"coordinates":[-122.11398199999999,37.378807],"type":"Point"}
}