{
  "type": "Feature",
  "properties": {
    "iso:country":"US",
    "sg:address":"42315 10th St W",
    "sg:city":"Lancaster",
    "sg:classifiers":[
        {
            "category":"Insurance",
            "subcategory":"Insurance Agent",
            "type":"Services"
        }
    ],
    "sg:phone":"+1 661 948 4111",
    "sg:postcode":"93534",
    "sg:province":"CA",
    "wof:name":"Strategic Capital Management",
    "wof:placetype":"venue"
},
  "geometry": {"coordinates":[-118.147733,34.649713],"type":"Point"}
}