{
  "type": "Feature",
  "properties": {
    "addr:full":"350 Bird Ave San Jose CA 95126",
    "addr:housenumber":"350",
    "addr:postcode":"95126",
    "addr:street":"Bird Ave",
    "iso:country":"US",
    "sg:address":"350 Bird Ave",
    "sg:city":"San Jose",
    "sg:classifiers":[
        {
            "category":"Real Estate",
            "subcategory":"Real Estate Operator",
            "type":"Services"
        }
    ],
    "sg:phone":"+1 408 993 9252",
    "sg:postcode":"95126",
    "sg:province":"CA",
    "sg:tags":[
        "apartment"
    ],
    "wof:name":"Delmas Park Apartments",
    "wof:placetype":"venue"
},
  "geometry": {"coordinates":[-121.899652,37.324112],"type":"Point"}
}