{
  "type": "Feature",
  "properties": {
    "iso:country":"US",
    "sg:address":"1032 Mohr Ln",
    "sg:city":"Concord",
    "sg:classifiers":[
        {
            "category":"Building & Trades",
            "subcategory":"Construction",
            "type":"Services"
        }
    ],
    "sg:phone":"+1 925 687 1198",
    "sg:postcode":"94518",
    "sg:province":"CA",
    "wof:name":"Falcon Paving",
    "wof:placetype":"venue"
},
  "geometry": {"coordinates":[-122.044704,37.945437],"type":"Point"}
}