{
  "type": "Feature",
  "properties": {
    "iso:country":"US",
    "sg:address":"1006 Herbert Ave",
    "sg:city":"South Lake Tahoe",
    "sg:classifiers":[
        {
            "category":"Food & Beverages",
            "subcategory":"Groceries & Convenience Stores",
            "type":"Retail Goods"
        }
    ],
    "sg:phone":"+1 530 544 9497",
    "sg:postcode":"96150",
    "sg:province":"CA",
    "sg:tags":[
        "grocer"
    ],
    "wof:name":"Plaza Tapatia 99 Cents",
    "wof:placetype":"venue"
},
  "geometry": {"coordinates":[-119.960774,38.947058],"type":"Point"}
}