{
  "type": "Feature",
  "properties": {
    "addr:full":"15 W Mill Ave Porterville CA 93257",
    "addr:housenumber":"15",
    "addr:postcode":"93257",
    "addr:street":"W Mill Ave",
    "iso:country":"US",
    "sg:address":"15 W Mill Ave",
    "sg:city":"Porterville",
    "sg:classifiers":[
        {
            "category":"Shopping",
            "subcategory":"Clothing, Apparel, & Fashions",
            "type":"Retail Goods"
        }
    ],
    "sg:phone":"+1 559 789 0103",
    "sg:postcode":"93257",
    "sg:province":"CA",
    "wof:name":"Sugar Plum's Boutique",
    "wof:placetype":"venue"
},
  "geometry": {"coordinates":[-119.016564,36.068732],"type":"Point"}
}