{
  "type": "Feature",
  "properties": {
    "addr:full":"141 Lynch Creek Way Petaluma CA 94954",
    "addr:housenumber":"141",
    "addr:postcode":"94954",
    "addr:street":"Lynch Creek Way",
    "iso:country":"US",
    "sg:address":"141 Lynch Creek Way",
    "sg:city":"Petaluma",
    "sg:classifiers":[
        {
            "category":"Health Services",
            "subcategory":"Doctor",
            "type":"Services"
        }
    ],
    "sg:phone":"+1 707 778 2313",
    "sg:postcode":"94954",
    "sg:province":"CA",
    "sg:tags":[
        "physician",
        "surgeon"
    ],
    "wof:name":"Aesthetic Institute",
    "wof:placetype":"venue"
},
  "geometry": {"coordinates":[-122.63441,38.25194],"type":"Point"}
}