{
  "type": "Feature",
  "properties": {
    "addr:full":"3231 Ocean Park Blvd Santa Monica CA 90405",
    "addr:housenumber":"3231",
    "addr:postcode":"90405",
    "addr:street":"Ocean Park Blvd",
    "iso:country":"US",
    "sg:address":"3231 Ocean Park Blvd",
    "sg:city":"Santa Monica",
    "sg:classifiers":[
        {
            "category":"Manufacturing",
            "subcategory":"Metals",
            "type":"Manufacturing & Wholesale Goods"
        }
    ],
    "sg:phone":"+1 310 396 8004",
    "sg:postcode":"90405",
    "sg:province":"CA",
    "sg:tags":[
        "casting"
    ],
    "wof:name":"Yeskel Ronnie Casting",
    "wof:placetype":"venue"
},
  "geometry": {"coordinates":[-118.451205,34.021515],"type":"Point"}
}